{
  "id": 1052861,
  "type": "Feature",
  "properties": {
    "tgn:hierarchy":[
        "tgn:1052861",
        "tgn:1000003",
        "tgn:7011661",
        "tgn:7006660",
        "tgn:7029392"
    ],
    "tgn:id":1052861,
    "tgn:name":"Boguslav",
    "tgn:placetype":[
        "aat:300008347"
    ]
},
  "bbox": [],
  "geometry": {"coordinates":[30.8667,49.5333],"type":"Point"}
}