{
  "id": 7484090,
  "type": "Feature",
  "properties": {
    "tgn:hierarchy":[
        "tgn:7484090",
        "tgn:1000004",
        "tgn:7492971",
        "tgn:1000141",
        "tgn:7029392"
    ],
    "tgn:id":7484090,
    "tgn:name":"Sanliuliuhao Qiao",
    "tgn:placetype":[
        "aat:300007836"
    ]
},
  "bbox": [],
  "geometry": {"coordinates":[120.631389,22.32],"type":"Point"}
}