<<<<<<< HEAD
{
  "id": 7484090,
  "type": "Feature",
  "properties": {
    "tgn:hierarchy":[
        "tgn:7484090",
        "tgn:1000004",
        "tgn:7492971",
        "tgn:1000141",
        "tgn:7029392"
    ],
    "tgn:id":7484090,
    "tgn:name":"Sanliuliuhao Qiao",
    "tgn:placetype":[
        "aat:300007836"
    ]
},
  "bbox": [],
  "geometry": {"coordinates":[120.631389,22.32],"type":"Point"}
}
=======
{"geometry":{"type":"Point","coordinates":[120.631389,22.320000]},"type":"Feature","properties":{"hierarchy":["tgn:7484090","tgn:1000004","tgn:7492971","tgn:1000141","tgn:7029392"],"placetype":["aat:300007836"],"id":7484090,"name:xx":"Sanliuliuhao Qiao"}}
>>>>>>> 03f74aca74312dbeaf24d7e61306dd6a786dc3d0
