{
  "id": 7361399,
  "type": "Feature",
  "properties": {
    "tgn:hierarchy":[
        "tgn:7361399",
        "tgn:7005586",
        "tgn:1000001",
        "tgn:7005560",
        "tgn:7029392"
    ],
    "tgn:id":7361399,
    "tgn:name":"El Ixcapil, Cerro",
    "tgn:placetype":[
        "aat:300008777"
    ]
},
  "bbox": [],
  "geometry": {"coordinates":[-103.583333,19.816667],"type":"Point"}
}