<<<<<<< HEAD
{
  "id": 2406702,
  "type": "Feature",
  "properties": {
    "tgn:hierarchy":[
        "tgn:2406702",
        "tgn:1000001",
        "tgn:7012149",
        "tgn:7022246",
        "tgn:7007825",
        "tgn:7029392"
    ],
    "tgn:id":2406702,
    "tgn:name":"Hunt Hollow",
    "tgn:placetype":[
        "aat:300008761"
    ]
},
  "bbox": [],
  "geometry": {"coordinates":[-85.8667,35.9833],"type":"Point"}
}
=======
{"geometry":{"type":"Point","coordinates":[-85.866700,35.983300]},"type":"Feature","properties":{"hierarchy":["tgn:2406702","tgn:1000001","tgn:7012149","tgn:7022246","tgn:7007825","tgn:7029392"],"placetype":["aat:300008761"],"id":2406702,"name:xx":"Hunt Hollow"}}
>>>>>>> 03f74aca74312dbeaf24d7e61306dd6a786dc3d0
