{
  "id": 2008070,
  "type": "Feature",
  "properties": {
    "tgn:hierarchy":[
        "tgn:2008070",
        "tgn:1000001",
        "tgn:7016172",
        "tgn:7012149",
        "tgn:2000161",
        "tgn:7029392"
    ],
    "tgn:id":2008070,
    "tgn:name":"Dallas",
    "tgn:placetype":[
        "aat:300008347",
        "aat:300387210"
    ]
},
  "bbox": [],
  "geometry": {"coordinates":[-94.2167,34.5333],"type":"Point"}
}