{
  "id": 7095287,
  "type": "Feature",
  "properties": {
    "tgn:hierarchy":[
        "tgn:7095287",
        "tgn:7003669",
        "tgn:1000003",
        "tgn:7000084",
        "tgn:7029392"
    ],
    "tgn:id":7095287,
    "tgn:name":"Schwarzenbach",
    "tgn:placetype":[
        "aat:300008347"
    ]
},
  "bbox": [],
  "geometry": {"coordinates":[12.383333,49.85],"type":"Point"}
}