{
  "id": 7292325,
  "type": "Feature",
  "properties": {
    "tgn:hierarchy":[
        "tgn:7292325",
        "tgn:1001708",
        "tgn:1000049",
        "tgn:1000002",
        "tgn:7029392"
    ],
    "tgn:id":7292325,
    "tgn:name":"El Trigalillo, Loma",
    "tgn:placetype":[
        "aat:300266640"
    ]
},
  "bbox": [],
  "geometry": {"coordinates":[-70.65,-33.75],"type":"Point"}
}