{
  "id": 2751289,
  "type": "Feature",
  "properties": {
    "tgn:hierarchy":[
        "tgn:2751289",
        "tgn:2002138",
        "tgn:1000001",
        "tgn:7012149",
        "tgn:7007919",
        "tgn:7029392"
    ],
    "tgn:id":2751289,
    "tgn:name":"Warm River Cave",
    "tgn:placetype":[
        "aat:300008746"
    ]
},
  "bbox": [],
  "geometry": {"coordinates":[-79.9167,37.8667],"type":"Point"}
}