{
  "id": 2374463,
  "type": "Feature",
  "properties": {
    "tgn:hierarchy":[
        "tgn:2374463",
        "tgn:7023902",
        "tgn:1000001",
        "tgn:7012149",
        "tgn:7007249",
        "tgn:7029392"
    ],
    "tgn:id":2374463,
    "tgn:name":"Hanaipoe",
    "tgn:placetype":[
        "aat:300008347"
    ]
},
  "bbox": [],
  "geometry": {"coordinates":[-155.45,19.9333],"type":"Point"}
}