{
  "id": 7491653,
  "type": "Feature",
  "properties": {
    "tgn:hierarchy":[
        "tgn:7491653",
        "tgn:1000004",
        "tgn:7489179",
        "tgn:1000141",
        "tgn:7029392"
    ],
    "tgn:id":7491653,
    "tgn:name":"Dali",
    "tgn:placetype":[
        "aat:300008347"
    ]
},
  "bbox": [],
  "geometry": {"coordinates":[121.921389,24.964722],"type":"Point"}
}