{
  "id": 7286724,
  "type": "Feature",
  "properties": {
    "tgn:hierarchy":[
        "tgn:7286724",
        "tgn:1001637",
        "tgn:1000049",
        "tgn:1000002",
        "tgn:7029392"
    ],
    "tgn:id":7286724,
    "tgn:name":"Guaqui",
    "tgn:placetype":[
        "aat:300000206"
    ]
},
  "bbox": [],
  "geometry": {"coordinates":[-72.666667,-37.35],"type":"Point"}
}