{
  "id": 2407101,
  "type": "Feature",
  "properties": {
    "tgn:hierarchy":[
        "tgn:2407101",
        "tgn:1000001",
        "tgn:7012149",
        "tgn:7007520",
        "tgn:7029392"
    ],
    "tgn:id":2407101,
    "tgn:name":"Hunters Brook",
    "tgn:placetype":[
        "aat:300008699"
    ]
},
  "bbox": [],
  "geometry": {"coordinates":[-87.45,46.0667],"type":"Point"}
}