{
  "id": 7161124,
  "type": "Feature",
  "properties": {
    "tgn:hierarchy":[
        "tgn:7161124",
        "tgn:1000003",
        "tgn:7003677",
        "tgn:7000084",
        "tgn:7029392"
    ],
    "tgn:id":7161124,
    "tgn:name":"Holsterhausen",
    "tgn:placetype":[
        "aat:300000745"
    ]
},
  "bbox": [],
  "geometry": {"coordinates":[6.983333,51.366667],"type":"Point"}
}