{
  "id": 7011295,
  "type": "Feature",
  "properties": {
    "tgn:hierarchy":[
        "tgn:7011295",
        "tgn:7002445",
        "tgn:1000003",
        "tgn:7011961",
        "tgn:7008591",
        "tgn:7029392"
    ],
    "tgn:id":7011295,
    "tgn:name:ang":"Porland",
    "tgn:placetype":[
        "aat:300000467",
        "aat:300387306",
        "aat:300008804"
    ]
},
  "bbox": [],
  "geometry": {"coordinates":[-2.433333,50.55],"type":"Point"}
}