{
  "id": 7168356,
  "type": "Feature",
  "properties": {
    "tgn:hierarchy":[
        "tgn:7168356",
        "tgn:7003669",
        "tgn:1000003",
        "tgn:7000084",
        "tgn:7029392"
    ],
    "tgn:id":7168356,
    "tgn:name":"Hart",
    "tgn:placetype":[
        "aat:300008863"
    ]
},
  "bbox": [],
  "geometry": {"coordinates":[10.283333,48.283333],"type":"Point"}
}