{
  "id": 7589507,
  "type": "Feature",
  "properties": {
    "tgn:hierarchy":[
        "tgn:7589507",
        "tgn:1000004",
        "tgn:7000198",
        "tgn:7000799",
        "tgn:7029392"
    ],
    "tgn:id":7589507,
    "tgn:name:en":"Balin N\u0101la",
    "tgn:placetype":[
        "aat:300008699"
    ]
},
  "bbox": [],
  "geometry": {"coordinates":[74.928874,32.78723],"type":"Point"}
}