{
  "id": 2694411,
  "type": "Feature",
  "properties": {
    "tgn:hierarchy":[
        "tgn:2694411",
        "tgn:1000001",
        "tgn:2001416",
        "tgn:7012149",
        "tgn:7007526",
        "tgn:7029392"
    ],
    "tgn:id":2694411,
    "tgn:name":"Steward Reservoir",
    "tgn:placetype":[
        "aat:300006191"
    ]
},
  "bbox": [],
  "geometry": {"coordinates":[-114.65,38.3167],"type":"Point"}
}