<<<<<<< HEAD
{
  "id": 7052625,
  "type": "Feature",
  "properties": {
    "tgn:hierarchy":[
        "tgn:7052625",
        "tgn:7005852",
        "tgn:1000003",
        "tgn:7003237",
        "tgn:1000080",
        "tgn:7029392"
    ],
    "tgn:id":7052625,
    "tgn:name":"Intelvi, Val d'",
    "tgn:placetype":[
        "aat:300008761"
    ]
},
  "bbox": [],
  "geometry": {"coordinates":[9.083333,45.95],"type":"Point"}
}
=======
{"geometry":{"type":"Point","coordinates":[9.083333,45.950000]},"type":"Feature","properties":{"hierarchy":["tgn:7052625","tgn:7005852","tgn:1000003","tgn:7003237","tgn:1000080","tgn:7029392"],"placetype":["aat:300008761"],"id":7052625,"name:xx":"Intelvi, Val d'"}}
>>>>>>> 03f74aca74312dbeaf24d7e61306dd6a786dc3d0
