{
  "id": 2637358,
  "type": "Feature",
  "properties": {
    "tgn:hierarchy":[
        "tgn:2637358",
        "tgn:1000001",
        "tgn:7012149",
        "tgn:2001222",
        "tgn:7007523",
        "tgn:7029392"
    ],
    "tgn:id":2637358,
    "tgn:name":"Saint Johns Bayou",
    "tgn:placetype":[
        "aat:300008699"
    ]
},
  "bbox": [],
  "geometry": {"coordinates":[-89.45,36.6333],"type":"Point"}
}