<<<<<<< HEAD
{
  "id": 7176201,
  "type": "Feature",
  "properties": {
    "tgn:hierarchy":[
        "tgn:7176201",
        "tgn:7003669",
        "tgn:1000003",
        "tgn:7000084",
        "tgn:7029392"
    ],
    "tgn:id":7176201,
    "tgn:name":"Greu\u00dfenheim",
    "tgn:placetype":[
        "aat:300008347"
    ]
},
  "bbox": [],
  "geometry": {"coordinates":[9.766667,49.816667],"type":"Point"}
}
=======
{"geometry":{"type":"Point","coordinates":[9.766667,49.816667]},"type":"Feature","properties":{"hierarchy":["tgn:7176201","tgn:7003669","tgn:1000003","tgn:7000084","tgn:7029392"],"placetype":["aat:300008347"],"id":7176201,"name:xx":"Greu\u00dfenheim"}}
>>>>>>> 03f74aca74312dbeaf24d7e61306dd6a786dc3d0
