{
  "id": 7384634,
  "type": "Feature",
  "properties": {
    "tgn:hierarchy":[
        "tgn:7384634",
        "tgn:1000001",
        "tgn:1001906",
        "tgn:7005560",
        "tgn:7029392"
    ],
    "tgn:id":7384634,
    "tgn:name":"Navarrete",
    "tgn:placetype":[
        "aat:300008347"
    ]
},
  "bbox": [],
  "geometry": {"coordinates":[-105.116667,21.65],"type":"Point"}
}