{
  "id": 2120789,
  "type": "Feature",
  "properties": {
    "tgn:hierarchy":[
        "tgn:2120789",
        "tgn:1000001",
        "tgn:2002313",
        "tgn:7012149",
        "tgn:7007922",
        "tgn:7029392"
    ],
    "tgn:id":2120789,
    "tgn:name":"Boyd",
    "tgn:placetype":[
        "aat:300008347"
    ]
},
  "bbox": [],
  "geometry": {"coordinates":[-91.0333,44.95],"type":"Point"}
}