{
  "id": 2614041,
  "type": "Feature",
  "properties": {
    "tgn:hierarchy":[
        "tgn:2614041",
        "tgn:1000001",
        "tgn:7012149",
        "tgn:1002785",
        "tgn:7007920",
        "tgn:7029392"
    ],
    "tgn:id":2614041,
    "tgn:name":"Reese Lake",
    "tgn:placetype":[
        "aat:300008680"
    ]
},
  "bbox": [],
  "geometry": {"coordinates":[-121.4333,46.9667],"type":"Point"}
}