{
  "id": 7491894,
  "type": "Feature",
  "properties": {
    "tgn:hierarchy":[
        "tgn:7491894",
        "tgn:7001004",
        "tgn:1000004",
        "tgn:1000141",
        "tgn:7029392"
    ],
    "tgn:id":7491894,
    "tgn:name":"Baolai Xi",
    "tgn:placetype":[
        "aat:300008699"
    ]
},
  "bbox": [],
  "geometry": {"coordinates":[120.696944,23.106389],"type":"Point"}
}