{
  "id": 7419675,
  "type": "Feature",
  "properties": {
    "tgn:hierarchy":[
        "tgn:7419675",
        "tgn:1001836",
        "tgn:1000001",
        "tgn:7005560",
        "tgn:7029392"
    ],
    "tgn:id":7419675,
    "tgn:name":"El Barranco",
    "tgn:placetype":[
        "aat:300008347"
    ]
},
  "bbox": [],
  "geometry": {"coordinates":[-110.000278,23.343611],"type":"Point"}
}