{
  "id": 1128003,
  "type": "Feature",
  "properties": {
    "tgn:hierarchy":[
        "tgn:1128003",
        "tgn:1000001",
        "tgn:7012149",
        "tgn:7007248",
        "tgn:7029392"
    ],
    "tgn:id":1128003,
    "tgn:name":"Oconee",
    "tgn:placetype":[
        "aat:300008707"
    ]
},
  "bbox": [],
  "geometry": {"coordinates":[-83.35,33.8667],"type":"Point"}
}