{
  "id": 1131079,
  "type": "Feature",
  "properties": {
    "tgn:hierarchy":[
        "tgn:1131079",
        "tgn:7001242",
        "tgn:7016749",
        "tgn:1000193",
        "tgn:7029392"
    ],
    "tgn:id":1131079,
    "tgn:name":"Tugela",
    "tgn:placetype":[
        "aat:300008707"
    ]
},
  "bbox": [],
  "geometry": {"coordinates":[31.497,-29.225],"type":"Point"}
}