{
  "id": 7073980,
  "type": "Feature",
  "properties": {
    "tgn:hierarchy":[
        "tgn:7073980",
        "tgn:1000003",
        "tgn:7000094",
        "tgn:7000084",
        "tgn:7029392"
    ],
    "tgn:id":7073980,
    "tgn:name":"Tessin",
    "tgn:placetype":[
        "aat:300008347"
    ]
},
  "bbox": [],
  "geometry": {"coordinates":[11.583333,53.716667],"type":"Point"}
}