<<<<<<< HEAD
{
  "id": 7243732,
  "type": "Feature",
  "properties": {
    "tgn:hierarchy":[
        "tgn:7243732",
        "tgn:7007877",
        "tgn:1000003",
        "tgn:1000063",
        "tgn:4012014",
        "tgn:7029392"
    ],
    "tgn:id":7243732,
    "tgn:name":"Houraing",
    "tgn:placetype":[
        "aat:300008347"
    ]
},
  "bbox": [],
  "geometry": {"coordinates":[3.828341,50.702919],"type":"Point"}
}
=======
{"geometry":{"type":"Point","coordinates":[3.828341,50.702919]},"type":"Feature","properties":{"hierarchy":["tgn:7243732","tgn:7007877","tgn:1000003","tgn:1000063","tgn:4012014","tgn:7029392"],"placetype":["aat:300008347"],"id":7243732,"name:xx":"Houraing"}}
>>>>>>> 03f74aca74312dbeaf24d7e61306dd6a786dc3d0
