{
  "id": 7481249,
  "type": "Feature",
  "properties": {
    "tgn:hierarchy":[
        "tgn:7481249",
        "tgn:1000004",
        "tgn:7004300",
        "tgn:1000141",
        "tgn:7029392"
    ],
    "tgn:id":7481249,
    "tgn:name":"Senfa Dian",
    "tgn:placetype":[
        "aat:300007595"
    ]
},
  "bbox": [],
  "geometry": {"coordinates":[119.434167,23.215],"type":"Point"}
}