{
  "id": 2476036,
  "type": "Feature",
  "properties": {
    "tgn:hierarchy":[
        "tgn:2476036",
        "tgn:1000001",
        "tgn:7012149",
        "tgn:2001901",
        "tgn:7007825",
        "tgn:7029392"
    ],
    "tgn:id":2476036,
    "tgn:name":"Luke Hall Mill Branch",
    "tgn:placetype":[
        "aat:300008699"
    ]
},
  "bbox": [],
  "geometry": {"coordinates":[-84.8667,36.15],"type":"Point"}
}