<<<<<<< HEAD
{
  "id": 7482469,
  "type": "Feature",
  "properties": {
    "tgn:hierarchy":[
        "tgn:7482469",
        "tgn:7468018",
        "tgn:1000004",
        "tgn:1000141",
        "tgn:7029392"
    ],
    "tgn:id":7482469,
    "tgn:name":"Dapi Shan",
    "tgn:placetype":[
        "aat:300008777"
    ]
},
  "bbox": [],
  "geometry": {"coordinates":[120.443889,23.42],"type":"Point"}
}
=======
{"geometry":{"type":"Point","coordinates":[120.443889,23.420000]},"type":"Feature","properties":{"hierarchy":["tgn:7482469","tgn:7468018","tgn:1000004","tgn:1000141","tgn:7029392"],"placetype":["aat:300008777"],"id":7482469,"name:xx":"Dapi Shan"}}
>>>>>>> 03f74aca74312dbeaf24d7e61306dd6a786dc3d0
