{
  "id": 7399018,
  "type": "Feature",
  "properties": {
    "tgn:hierarchy":[
        "tgn:7399018",
        "tgn:1000001",
        "tgn:1001893",
        "tgn:7005560",
        "tgn:7029392"
    ],
    "tgn:id":7399018,
    "tgn:name":"San Juan de los Jarros",
    "tgn:placetype":[
        "aat:300008347"
    ]
},
  "bbox": [],
  "geometry": {"coordinates":[-99.918889,19.861389],"type":"Point"}
}