{
  "id": 7070738,
  "type": "Feature",
  "properties": {
    "tgn:hierarchy":[
        "tgn:7070738",
        "tgn:7003669",
        "tgn:1000003",
        "tgn:7000084",
        "tgn:7029392"
    ],
    "tgn:id":7070738,
    "tgn:name":"Steinb\u00fchl",
    "tgn:placetype":[
        "aat:300008347"
    ]
},
  "bbox": [],
  "geometry": {"coordinates":[12.916667,48.883333],"type":"Point"}
}