{
  "id": 2504671,
  "type": "Feature",
  "properties": {
    "tgn:hierarchy":[
        "tgn:2504671",
        "tgn:1000001",
        "tgn:7006451",
        "tgn:2000093",
        "tgn:7012149",
        "tgn:7029392"
    ],
    "tgn:id":2504671,
    "tgn:name":"Meddler Point",
    "tgn:placetype":[
        "aat:300008850"
    ]
},
  "bbox": [],
  "geometry": {"coordinates":[-110.95,33.6167],"type":"Point"}
}