{
  "id": 7324954,
  "type": "Feature",
  "properties": {
    "tgn:hierarchy":[
        "tgn:7324954",
        "tgn:7002759",
        "tgn:7002845",
        "tgn:1000003",
        "tgn:1000095",
        "tgn:7029392"
    ],
    "tgn:id":7324954,
    "tgn:name":"Santa Isabel",
    "tgn:placetype":[
        "aat:300008347"
    ]
},
  "bbox": [],
  "geometry": {"coordinates":[-0.833333,41.666667],"type":"Point"}
}