{
  "id": 1050494,
  "type": "Feature",
  "properties": {
    "tgn:hierarchy":[
        "tgn:1050494",
        "tgn:7019094",
        "tgn:7002444",
        "tgn:1000003",
        "tgn:7008591",
        "tgn:7029392"
    ],
    "tgn:id":1050494,
    "tgn:name:en":"Cairndow",
    "tgn:placetype":[
        "aat:300008347"
    ]
},
  "bbox": [],
  "geometry": {"coordinates":[-4.933333,56.25],"type":"Point"}
}