{
  "id": 2307328,
  "type": "Feature",
  "properties": {
    "tgn:hierarchy":[
        "tgn:2307328",
        "tgn:1000001",
        "tgn:2001411",
        "tgn:7012149",
        "tgn:7007526",
        "tgn:7029392"
    ],
    "tgn:id":2307328,
    "tgn:name":"East Fork Rattlesnake Canyon",
    "tgn:placetype":[
        "aat:300008761"
    ]
},
  "bbox": [],
  "geometry": {"coordinates":[-115.3667,41.9333],"type":"Point"}
}