{
  "id": 2365743,
  "type": "Feature",
  "properties": {
    "tgn:hierarchy":[
        "tgn:2365743",
        "tgn:2000105",
        "tgn:1000001",
        "tgn:7016172",
        "tgn:7012149",
        "tgn:7029392"
    ],
    "tgn:id":2365743,
    "tgn:name":"Gregory Lake",
    "tgn:placetype":[
        "aat:300006191"
    ]
},
  "bbox": [],
  "geometry": {"coordinates":[-91.3167,34.1667],"type":"Point"}
}