{
  "id": 7349623,
  "type": "Feature",
  "properties": {
    "tgn:hierarchy":[
        "tgn:7349623",
        "tgn:7005583",
        "tgn:1000001",
        "tgn:7005560",
        "tgn:7029392"
    ],
    "tgn:id":7349623,
    "tgn:name":"Aguanaval, Ri\u00f3",
    "tgn:placetype":[
        "aat:300008699"
    ]
},
  "bbox": [],
  "geometry": {"coordinates":[-103.65,25.433333],"type":"Point"}
}