{
  "id": 7555671,
  "type": "Feature",
  "properties": {
    "tgn:hierarchy":[
        "tgn:7555671",
        "tgn:1000004",
        "tgn:7000198",
        "tgn:1001882",
        "tgn:7029392"
    ],
    "tgn:id":7555671,
    "tgn:name:en":"Nandipalli",
    "tgn:placetype":[
        "aat:300008347"
    ]
},
  "bbox": [],
  "geometry": {"coordinates":[77.383333,16.683333],"type":"Point"}
}