{
  "id": 7410524,
  "type": "Feature",
  "properties": {
    "tgn:hierarchy":[
        "tgn:7410524",
        "tgn:1000001",
        "tgn:7005592",
        "tgn:7005560",
        "tgn:7029392"
    ],
    "tgn:id":7410524,
    "tgn:name":"Xolotla",
    "tgn:placetype":[
        "aat:300008347"
    ]
},
  "bbox": [],
  "geometry": {"coordinates":[-98.133333,20.258333],"type":"Point"}
}