<<<<<<< HEAD
{
  "id": 7021621,
  "type": "Feature",
  "properties": {
    "tgn:hierarchy":[
        "tgn:7021621",
        "tgn:1000001",
        "tgn:7012149",
        "tgn:1002456",
        "tgn:7007826",
        "tgn:7029392"
    ],
    "tgn:id":7021621,
    "tgn:name":"South Side Place",
    "tgn:placetype":[
        "aat:300008347"
    ]
},
  "bbox": [],
  "geometry": {"coordinates":[-95.4167,29.7],"type":"Point"}
}
=======
{"geometry":{"type":"Point","coordinates":[-95.416700,29.700000]},"type":"Feature","properties":{"hierarchy":["tgn:7021621","tgn:1000001","tgn:7012149","tgn:1002456","tgn:7007826","tgn:7029392"],"placetype":["aat:300008347"],"id":7021621,"name:xx":"South Side Place"}}
>>>>>>> 03f74aca74312dbeaf24d7e61306dd6a786dc3d0
