{
  "id": 2054963,
  "type": "Feature",
  "properties": {
    "tgn:hierarchy":[
        "tgn:2054963",
        "tgn:1000001",
        "tgn:7012149",
        "tgn:2001067",
        "tgn:7007521",
        "tgn:7029392"
    ],
    "tgn:id":2054963,
    "tgn:name":"Markham",
    "tgn:placetype":[
        "aat:300008347"
    ]
},
  "bbox": [],
  "geometry": {"coordinates":[-92.2167,47.2833],"type":"Point"}
}