{
  "id": 7456202,
  "type": "Feature",
  "properties": {
    "tgn:hierarchy":[
        "tgn:7456202",
        "tgn:7019164",
        "tgn:7002448",
        "tgn:1000003",
        "tgn:7008591",
        "tgn:7029392"
    ],
    "tgn:id":7456202,
    "tgn:name:en":"Clogh River",
    "tgn:placetype":[
        "aat:300008699"
    ]
},
  "bbox": [],
  "geometry": {"coordinates":[-6.383333,54.933333],"type":"Point"}
}