{
  "id": 1077399,
  "type": "Feature",
  "properties": {
    "tgn:hierarchy":[
        "tgn:1077399",
        "tgn:1000004",
        "tgn:1001338",
        "tgn:1000116",
        "tgn:7029392"
    ],
    "tgn:id":1077399,
    "tgn:name":"Bakumpai",
    "tgn:placetype":[
        "aat:300008347"
    ]
},
  "bbox": [],
  "geometry": {"coordinates":[113.0833,-1.4333],"type":"Point"}
}