{
  "id": 7070836,
  "type": "Feature",
  "properties": {
    "tgn:hierarchy":[
        "tgn:7070836",
        "tgn:1000003",
        "tgn:7003676",
        "tgn:7000084",
        "tgn:7029392"
    ],
    "tgn:id":7070836,
    "tgn:name":"Steinbergsh\u00f6rn",
    "tgn:placetype":[
        "aat:300008347"
    ]
},
  "bbox": [],
  "geometry": {"coordinates":[8.95,53.616667],"type":"Point"}
}