{
  "id": 1018174,
  "type": "Feature",
  "properties": {
    "tgn:hierarchy":[
        "tgn:1018174",
        "tgn:1000001",
        "tgn:7005591",
        "tgn:7005560",
        "tgn:7029392"
    ],
    "tgn:id":1018174,
    "tgn:name":"San Francisco Ixhuat\u00e1n",
    "tgn:placetype":[
        "aat:300008347"
    ]
},
  "bbox": [],
  "geometry": {"coordinates":[-94.4833,16.3667],"type":"Point"}
}