{
  "id": 2137321,
  "type": "Feature",
  "properties": {
    "tgn:hierarchy":[
        "tgn:2137321",
        "tgn:1000001",
        "tgn:7012149",
        "tgn:2001067",
        "tgn:7007521",
        "tgn:7029392"
    ],
    "tgn:id":2137321,
    "tgn:name":"Armstrong Bay",
    "tgn:placetype":[
        "aat:300132316"
    ]
},
  "bbox": [],
  "geometry": {"coordinates":[-92.1667,47.8333],"type":"Point"}
}