{
  "id": 2356917,
  "type": "Feature",
  "properties": {
    "tgn:hierarchy":[
        "tgn:2356917",
        "tgn:1000001",
        "tgn:7012149",
        "tgn:2000181",
        "tgn:7007157",
        "tgn:7029392"
    ],
    "tgn:id":2356917,
    "tgn:name":"Gosinta Creek",
    "tgn:placetype":[
        "aat:300008706"
    ]
},
  "bbox": [],
  "geometry": {"coordinates":[-123.95,40.9167],"type":"Point"}
}