{
  "id": 1106897,
  "type": "Feature",
  "properties": {
    "tgn:hierarchy":[
        "tgn:1106897",
        "tgn:7009084",
        "tgn:7004154",
        "tgn:1000003",
        "tgn:1000080",
        "tgn:7029392"
    ],
    "tgn:id":1106897,
    "tgn:name":"Velino, Monte",
    "tgn:placetype":[
        "aat:300008795"
    ]
},
  "bbox": [],
  "geometry": {"coordinates":[13.383333,42.15],"type":"Point"}
}