{
  "id": 2407972,
  "type": "Feature",
  "properties": {
    "tgn:hierarchy":[
        "tgn:2407972",
        "tgn:1000001",
        "tgn:2001483",
        "tgn:7012149",
        "tgn:7007709",
        "tgn:7029392"
    ],
    "tgn:id":2407972,
    "tgn:name":"Hurricane Creek",
    "tgn:placetype":[
        "aat:300008706"
    ]
},
  "bbox": [],
  "geometry": {"coordinates":[-83.6667,35.0667],"type":"Point"}
}