<<<<<<< HEAD
{
  "id": 2767300,
  "type": "Feature",
  "properties": {
    "tgn:hierarchy":[
        "tgn:2767300",
        "tgn:1000001",
        "tgn:2001429",
        "tgn:7012149",
        "tgn:7007566",
        "tgn:7029392"
    ],
    "tgn:id":2767300,
    "tgn:name":"White Rocks Tank",
    "tgn:placetype":[
        "aat:300006191"
    ]
},
  "bbox": [],
  "geometry": {"coordinates":[-109.0167,33.4833],"type":"Point"}
}
=======
{"geometry":{"type":"Point","coordinates":[-109.016700,33.483300]},"type":"Feature","properties":{"hierarchy":["tgn:2767300","tgn:1000001","tgn:2001429","tgn:7012149","tgn:7007566","tgn:7029392"],"placetype":["aat:300006191"],"id":2767300,"name:xx":"White Rocks Tank"}}
>>>>>>> 03f74aca74312dbeaf24d7e61306dd6a786dc3d0
