{
  "id": 2767300,
  "type": "Feature",
  "properties": {
    "tgn:hierarchy":[
        "tgn:2767300",
        "tgn:1000001",
        "tgn:2001429",
        "tgn:7012149",
        "tgn:7007566",
        "tgn:7029392"
    ],
    "tgn:id":2767300,
    "tgn:name":"White Rocks Tank",
    "tgn:placetype":[
        "aat:300006191"
    ]
},
  "bbox": [],
  "geometry": {"coordinates":[-109.0167,33.4833],"type":"Point"}
}