{
  "id": 2475303,
  "type": "Feature",
  "properties": {
    "tgn:hierarchy":[
        "tgn:2475303",
        "tgn:1000001",
        "tgn:7012149",
        "tgn:7007157",
        "tgn:7029392"
    ],
    "tgn:id":2475303,
    "tgn:name":"Lucas Canyon",
    "tgn:placetype":[
        "aat:300008761"
    ]
},
  "bbox": [],
  "geometry": {"coordinates":[-117.45,33.5667],"type":"Point"}
}