{
  "id": 2168457,
  "type": "Feature",
  "properties": {
    "tgn:hierarchy":[
        "tgn:2168457",
        "tgn:1000001",
        "tgn:7012149",
        "tgn:1002314",
        "tgn:7007240",
        "tgn:7029392"
    ],
    "tgn:id":2168457,
    "tgn:name":"Big Hammock",
    "tgn:placetype":[
        "aat:300008791"
    ]
},
  "bbox": [],
  "geometry": {"coordinates":[-80.7833,25.8167],"type":"Point"}
}