{
  "id": 7459709,
  "type": "Feature",
  "properties": {
    "tgn:hierarchy":[
        "tgn:7459709",
        "tgn:7002443",
        "tgn:1000003",
        "tgn:7018966",
        "tgn:7008591",
        "tgn:7029392"
    ],
    "tgn:id":7459709,
    "tgn:name:en":"Nash Sands",
    "tgn:placetype":[
        "aat:300386970"
    ]
},
  "bbox": [],
  "geometry": {"coordinates":[-3.65,51.416667],"type":"Point"}
}