{
  "id": 7574328,
  "type": "Feature",
  "properties": {
    "tgn:hierarchy":[
        "tgn:7574328",
        "tgn:1000004",
        "tgn:7000198",
        "tgn:1001894",
        "tgn:7029392"
    ],
    "tgn:id":7574328,
    "tgn:name:en":"Jaitpur",
    "tgn:placetype":[
        "aat:300008347"
    ]
},
  "bbox": [],
  "geometry": {"coordinates":[79.047089,23.494847],"type":"Point"}
}