{
  "id": 1065711,
  "type": "Feature",
  "properties": {
    "tgn:hierarchy":[
        "tgn:1065711",
        "tgn:1000004",
        "tgn:7000191",
        "tgn:1000105",
        "tgn:7029392"
    ],
    "tgn:id":1065711,
    "tgn:name":"God\u0101g\u0101ri",
    "tgn:placetype":[
        "aat:300008347"
    ]
},
  "bbox": [],
  "geometry": {"coordinates":[88.3333,24.4667],"type":"Point"}
}