{
  "id": 2623602,
  "type": "Feature",
  "properties": {
    "tgn:hierarchy":[
        "tgn:2623602",
        "tgn:1000001",
        "tgn:7012149",
        "tgn:7007523",
        "tgn:7029392"
    ],
    "tgn:id":2623602,
    "tgn:name":"Rock Creek",
    "tgn:placetype":[
        "aat:300008706"
    ]
},
  "bbox": [],
  "geometry": {"coordinates":[-90.55,37.5167],"type":"Point"}
}