{
  "id": 2709777,
  "type": "Feature",
  "properties": {
    "tgn:hierarchy":[
        "tgn:2709777",
        "tgn:1000001",
        "tgn:2001633",
        "tgn:7012149",
        "tgn:7007707",
        "tgn:7029392"
    ],
    "tgn:id":2709777,
    "tgn:name":"Tahlequah Creek",
    "tgn:placetype":[
        "aat:300008706"
    ]
},
  "bbox": [],
  "geometry": {"coordinates":[-94.95,35.95],"type":"Point"}
}