<<<<<<< HEAD
{
  "id": 2709777,
  "type": "Feature",
  "properties": {
    "tgn:hierarchy":[
        "tgn:2709777",
        "tgn:1000001",
        "tgn:2001633",
        "tgn:7012149",
        "tgn:7007707",
        "tgn:7029392"
    ],
    "tgn:id":2709777,
    "tgn:name":"Tahlequah Creek",
    "tgn:placetype":[
        "aat:300008706"
    ]
},
  "bbox": [],
  "geometry": {"coordinates":[-94.95,35.95],"type":"Point"}
}
=======
{"geometry":{"type":"Point","coordinates":[-94.950000,35.950000]},"type":"Feature","properties":{"hierarchy":["tgn:2709777","tgn:1000001","tgn:2001633","tgn:7012149","tgn:7007707","tgn:7029392"],"placetype":["aat:300008706"],"id":2709777,"name:xx":"Tahlequah Creek"}}
>>>>>>> 03f74aca74312dbeaf24d7e61306dd6a786dc3d0
