{
  "id": 1078004,
  "type": "Feature",
  "properties": {
    "tgn:hierarchy":[
        "tgn:1078004",
        "tgn:7016479",
        "tgn:1000004",
        "tgn:1000116",
        "tgn:7029392"
    ],
    "tgn:id":1078004,
    "tgn:name":"Lhokkruet",
    "tgn:placetype":[
        "aat:300008347"
    ]
},
  "bbox": [],
  "geometry": {"coordinates":[95.4333,4.85],"type":"Point"}
}