<<<<<<< HEAD
{
  "id": 7373918,
  "type": "Feature",
  "properties": {
    "tgn:hierarchy":[
        "tgn:7373918",
        "tgn:1000001",
        "tgn:7005589",
        "tgn:7005560",
        "tgn:7029392"
    ],
    "tgn:id":7373918,
    "tgn:name":"La Guardiana",
    "tgn:placetype":[
        "aat:300008347"
    ]
},
  "bbox": [],
  "geometry": {"coordinates":[-99.1,25.066667],"type":"Point"}
}
=======
{"geometry":{"type":"Point","coordinates":[-99.100000,25.066667]},"type":"Feature","properties":{"hierarchy":["tgn:7373918","tgn:1000001","tgn:7005589","tgn:7005560","tgn:7029392"],"placetype":["aat:300008347"],"id":7373918,"name:xx":"La Guardiana"}}
>>>>>>> 03f74aca74312dbeaf24d7e61306dd6a786dc3d0
