{
  "id": 7498810,
  "type": "Feature",
  "properties": {
    "tgn:hierarchy":[
        "tgn:7498810",
        "tgn:1000004",
        "tgn:7001009",
        "tgn:1000141",
        "tgn:7029392"
    ],
    "tgn:id":7498810,
    "tgn:name":"Dapinglong Shan",
    "tgn:placetype":[
        "aat:300008795"
    ]
},
  "bbox": [],
  "geometry": {"coordinates":[120.8804,24.201732],"type":"Point"}
}