{
  "id": 7095137,
  "type": "Feature",
  "properties": {
    "tgn:hierarchy":[
        "tgn:7095137",
        "tgn:1000003",
        "tgn:7003677",
        "tgn:7000084",
        "tgn:7029392"
    ],
    "tgn:id":7095137,
    "tgn:name":"Schulte van Almsick",
    "tgn:placetype":[
        "aat:300000206"
    ]
},
  "bbox": [],
  "geometry": {"coordinates":[6.95,52.016667],"type":"Point"}
}