<<<<<<< HEAD
{
  "id": 7115642,
  "type": "Feature",
  "properties": {
    "tgn:hierarchy":[
        "tgn:7115642",
        "tgn:7003669",
        "tgn:1000003",
        "tgn:7000084",
        "tgn:7029392"
    ],
    "tgn:id":7115642,
    "tgn:name":"Pachmayer",
    "tgn:placetype":[
        "aat:300000206"
    ]
},
  "bbox": [],
  "geometry": {"coordinates":[12.866667,48.266667],"type":"Point"}
}
=======
{"geometry":{"type":"Point","coordinates":[12.866667,48.266667]},"type":"Feature","properties":{"hierarchy":["tgn:7115642","tgn:7003669","tgn:1000003","tgn:7000084","tgn:7029392"],"placetype":["aat:300000206"],"id":7115642,"name:xx":"Pachmayer"}}
>>>>>>> 03f74aca74312dbeaf24d7e61306dd6a786dc3d0
