{
  "id": 2023032,
  "type": "Feature",
  "properties": {
    "tgn:hierarchy":[
        "tgn:2023032",
        "tgn:1000001",
        "tgn:7012149",
        "tgn:2000449",
        "tgn:7007248",
        "tgn:7029392"
    ],
    "tgn:id":2023032,
    "tgn:name":"Gordon",
    "tgn:placetype":[
        "aat:300008347"
    ]
},
  "bbox": [],
  "geometry": {"coordinates":[-83.3167,32.8667],"type":"Point"}
}