{
  "id": 2656317,
  "type": "Feature",
  "properties": {
    "tgn:hierarchy":[
        "tgn:2656317",
        "tgn:1000001",
        "tgn:7012149",
        "tgn:2001543",
        "tgn:7007709",
        "tgn:7029392"
    ],
    "tgn:id":2656317,
    "tgn:name":"Shear Knob",
    "tgn:placetype":[
        "aat:300008798"
    ]
},
  "bbox": [],
  "geometry": {"coordinates":[-83.5167,35.3833],"type":"Point"}
}