{
  "id": 7176229,
  "type": "Feature",
  "properties": {
    "tgn:hierarchy":[
        "tgn:7176229",
        "tgn:7003669",
        "tgn:1000003",
        "tgn:7000084",
        "tgn:7029392"
    ],
    "tgn:id":7176229,
    "tgn:name":"Gre\u00dfthal",
    "tgn:placetype":[
        "aat:300008347"
    ]
},
  "bbox": [],
  "geometry": {"coordinates":[10.033333,50.083333],"type":"Point"}
}