{
  "id": 1045138,
  "type": "Feature",
  "properties": {
    "tgn:hierarchy":[
        "tgn:1045138",
        "tgn:1001724",
        "tgn:1000003",
        "tgn:7003121",
        "tgn:1000080",
        "tgn:7029392"
    ],
    "tgn:id":1045138,
    "tgn:name":"Lotzorai",
    "tgn:placetype":[
        "aat:300008347"
    ]
},
  "bbox": [],
  "geometry": {"coordinates":[9.660833,39.97],"type":"Point"}
}