{
  "id": 7307543,
  "type": "Feature",
  "properties": {
    "tgn:hierarchy":[
        "tgn:7307543",
        "tgn:7002758",
        "tgn:7002821",
        "tgn:1000003",
        "tgn:1000095",
        "tgn:7029392"
    ],
    "tgn:id":7307543,
    "tgn:name":"Marmolance, Sierra de",
    "tgn:placetype":[
        "aat:300266640"
    ]
},
  "bbox": [],
  "geometry": {"coordinates":[-2.616667,37.816667],"type":"Point"}
}