{
  "id": 7536331,
  "type": "Feature",
  "properties": {
    "tgn:hierarchy":[
        "tgn:7536331",
        "tgn:7001242",
        "tgn:7016833",
        "tgn:1001418",
        "tgn:7029392"
    ],
    "tgn:id":7536331,
    "tgn:name:en":"Ghur\u0101b\u012b, Ghurd",
    "tgn:placetype":[
        "aat:300008750"
    ]
},
  "bbox": [],
  "geometry": {"coordinates":[28.816329,28.871815],"type":"Point"}
}