{
  "id": 2703787,
  "type": "Feature",
  "properties": {
    "tgn:hierarchy":[
        "tgn:2703787",
        "tgn:1000001",
        "tgn:7012149",
        "tgn:7007157",
        "tgn:1002608",
        "tgn:1008951",
        "tgn:7029392"
    ],
    "tgn:id":2703787,
    "tgn:name":"Sun Point",
    "tgn:placetype":[
        "aat:300008850"
    ]
},
  "bbox": [],
  "geometry": {"coordinates":[-118.3667,32.8167],"type":"Point"}
}