{
  "id": 2436839,
  "type": "Feature",
  "properties": {
    "tgn:hierarchy":[
        "tgn:2436839",
        "tgn:1000001",
        "tgn:7012149",
        "tgn:7016021",
        "tgn:7007568",
        "tgn:7029392"
    ],
    "tgn:id":2436839,
    "tgn:name":"Kildare Pond",
    "tgn:placetype":[
        "aat:300008680"
    ]
},
  "bbox": [],
  "geometry": {"coordinates":[-74.6833,44.4333],"type":"Point"}
}