{
  "id": 2784268,
  "type": "Feature",
  "properties": {
    "tgn:hierarchy":[
        "tgn:2784268",
        "tgn:1000001",
        "tgn:7012149",
        "tgn:2002371",
        "tgn:7007923",
        "tgn:7029392"
    ],
    "tgn:id":2784268,
    "tgn:name":"Yankee Gulch",
    "tgn:placetype":[
        "aat:300008761"
    ]
},
  "bbox": [],
  "geometry": {"coordinates":[-108.6667,42.5333],"type":"Point"}
}