{
  "id": 7279595,
  "type": "Feature",
  "properties": {
    "tgn:hierarchy":[
        "tgn:7279595",
        "tgn:1001768",
        "tgn:1000049",
        "tgn:1000002",
        "tgn:7029392"
    ],
    "tgn:id":7279595,
    "tgn:name":"Rinc\u00f3n de las Majadas",
    "tgn:placetype":[
        "aat:300387200"
    ]
},
  "bbox": [],
  "geometry": {"coordinates":[-71.116667,-32.533333],"type":"Point"}
}