{
  "id": 2734153,
  "type": "Feature",
  "properties": {
    "tgn:hierarchy":[
        "tgn:2734153",
        "tgn:1000001",
        "tgn:7012149",
        "tgn:2001719",
        "tgn:7007708",
        "tgn:7029392"
    ],
    "tgn:id":2734153,
    "tgn:name":"Turpentine Creek",
    "tgn:placetype":[
        "aat:300008706"
    ]
},
  "bbox": [],
  "geometry": {"coordinates":[-119.1833,45.1667],"type":"Point"}
}