<<<<<<< HEAD
{
  "id": 2408408,
  "type": "Feature",
  "properties": {
    "tgn:hierarchy":[
        "tgn:2408408",
        "tgn:1000001",
        "tgn:7012149",
        "tgn:2001500",
        "tgn:7007709",
        "tgn:7029392"
    ],
    "tgn:id":2408408,
    "tgn:name":"Hutchens Lake",
    "tgn:placetype":[
        "aat:300006191"
    ]
},
  "bbox": [],
  "geometry": {"coordinates":[-80.0,36.0333],"type":"Point"}
}
=======
{"geometry":{"type":"Point","coordinates":[-80.000000,36.033300]},"type":"Feature","properties":{"hierarchy":["tgn:2408408","tgn:1000001","tgn:7012149","tgn:2001500","tgn:7007709","tgn:7029392"],"placetype":["aat:300006191"],"id":2408408,"name:xx":"Hutchens Lake"}}
>>>>>>> 03f74aca74312dbeaf24d7e61306dd6a786dc3d0
