<<<<<<< HEAD
{
  "id": 2334836,
  "type": "Feature",
  "properties": {
    "tgn:hierarchy":[
        "tgn:2334836",
        "tgn:1000001",
        "tgn:7012149",
        "tgn:2001540",
        "tgn:7007709",
        "tgn:7029392"
    ],
    "tgn:id":2334836,
    "tgn:name":"Fork Section",
    "tgn:placetype":[
        "aat:300266640"
    ]
},
  "bbox": [],
  "geometry": {"coordinates":[-80.0667,35.1667],"type":"Point"}
}
=======
{"geometry":{"type":"Point","coordinates":[-80.066700,35.166700]},"type":"Feature","properties":{"hierarchy":["tgn:2334836","tgn:1000001","tgn:7012149","tgn:2001540","tgn:7007709","tgn:7029392"],"placetype":["aat:300266640"],"id":2334836,"name:xx":"Fork Section"}}
>>>>>>> 03f74aca74312dbeaf24d7e61306dd6a786dc3d0
