{
  "id": 1117875,
  "type": "Feature",
  "properties": {
    "tgn:hierarchy":[
        "tgn:1117875",
        "tgn:1000001",
        "tgn:2001777",
        "tgn:7012149",
        "tgn:7007713",
        "tgn:7029392"
    ],
    "tgn:id":1117875,
    "tgn:name":"Red Lake",
    "tgn:placetype":[
        "aat:300008680"
    ]
},
  "bbox": [],
  "geometry": {"coordinates":[-99.2167,43.7167],"type":"Point"}
}