{
  "id": 2276682,
  "type": "Feature",
  "properties": {
    "tgn:hierarchy":[
        "tgn:2276682",
        "tgn:1000001",
        "tgn:7012149",
        "tgn:7007709",
        "tgn:7029392"
    ],
    "tgn:id":2276682,
    "tgn:name":"Davidson Creek",
    "tgn:placetype":[
        "aat:300008706"
    ]
},
  "bbox": [],
  "geometry": {"coordinates":[-80.85,35.5167],"type":"Point"}
}