{
  "id": 7111247,
  "type": "Feature",
  "properties": {
    "tgn:hierarchy":[
        "tgn:7111247",
        "tgn:7000096",
        "tgn:1000003",
        "tgn:7000084",
        "tgn:7029392"
    ],
    "tgn:id":7111247,
    "tgn:name":"Rieckshof",
    "tgn:placetype":[
        "aat:300000206"
    ]
},
  "bbox": [],
  "geometry": {"coordinates":[13.583333,53.166667],"type":"Point"}
}