{
  "id": 2548423,
  "type": "Feature",
  "properties": {
    "tgn:hierarchy":[
        "tgn:2548423",
        "tgn:1000001",
        "tgn:7012149",
        "tgn:2000927",
        "tgn:7007515",
        "tgn:7029392"
    ],
    "tgn:id":2548423,
    "tgn:name":"North Lincoln",
    "tgn:placetype":[
        "aat:300008347"
    ]
},
  "bbox": [],
  "geometry": {"coordinates":[-68.45,45.4167],"type":"Point"}
}