{
  "id": 7423885,
  "type": "Feature",
  "properties": {
    "tgn:hierarchy":[
        "tgn:7423885",
        "tgn:1000001",
        "tgn:7005597",
        "tgn:7005560",
        "tgn:7029392"
    ],
    "tgn:id":7423885,
    "tgn:name":"Uat",
    "tgn:placetype":[
        "aat:300007783"
    ]
},
  "bbox": [],
  "geometry": {"coordinates":[-98.966667,22.716667],"type":"Point"}
}