{
  "id": 7181475,
  "type": "Feature",
  "properties": {
    "tgn:hierarchy":[
        "tgn:7181475",
        "tgn:1000003",
        "tgn:7003682",
        "tgn:7000084",
        "tgn:7029392"
    ],
    "tgn:id":7181475,
    "tgn:name":"G\u00e4h-Berg",
    "tgn:placetype":[
        "aat:300008777"
    ]
},
  "bbox": [],
  "geometry": {"coordinates":[8.016667,49.05],"type":"Point"}
}