<<<<<<< HEAD
{
  "id": 7372033,
  "type": "Feature",
  "properties": {
    "tgn:hierarchy":[
        "tgn:7372033",
        "tgn:7016644",
        "tgn:1000001",
        "tgn:7005560",
        "tgn:7029392"
    ],
    "tgn:id":7372033,
    "tgn:name":"La Nancera, Cerro",
    "tgn:placetype":[
        "aat:300008795"
    ]
},
  "bbox": [],
  "geometry": {"coordinates":[-103.983333,19.2],"type":"Point"}
}
=======
{"geometry":{"type":"Point","coordinates":[-103.983333,19.200000]},"type":"Feature","properties":{"hierarchy":["tgn:7372033","tgn:7016644","tgn:1000001","tgn:7005560","tgn:7029392"],"placetype":["aat:300008795"],"id":7372033,"name:xx":"La Nancera, Cerro"}}
>>>>>>> 03f74aca74312dbeaf24d7e61306dd6a786dc3d0
