{
  "id": 7321075,
  "type": "Feature",
  "properties": {
    "tgn:hierarchy":[
        "tgn:7321075",
        "tgn:1001702",
        "tgn:1000049",
        "tgn:1000002",
        "tgn:7029392"
    ],
    "tgn:id":7321075,
    "tgn:name":"Blanca, Punta",
    "tgn:placetype":[
        "aat:300386846"
    ]
},
  "bbox": [],
  "geometry": {"coordinates":[-74.383333,-50.85],"type":"Point"}
}