{
  "id": 2745912,
  "type": "Feature",
  "properties": {
    "tgn:hierarchy":[
        "tgn:2745912",
        "tgn:1000001",
        "tgn:2001018",
        "tgn:7012149",
        "tgn:7007521",
        "tgn:7029392"
    ],
    "tgn:id":2745912,
    "tgn:name":"Vlasaty",
    "tgn:placetype":[
        "aat:300008347"
    ]
},
  "bbox": [],
  "geometry": {"coordinates":[-92.8333,43.95],"type":"Point"}
}