{
  "id": 7550110,
  "type": "Feature",
  "properties": {
    "tgn:hierarchy":[
        "tgn:7550110",
        "tgn:1000004",
        "tgn:1001832",
        "tgn:7000198",
        "tgn:7029392"
    ],
    "tgn:id":7550110,
    "tgn:name:en":"Dhekiajuli Road",
    "tgn:placetype":[
        "aat:300007783"
    ]
},
  "bbox": [],
  "geometry": {"coordinates":[92.404841,26.81291],"type":"Point"}
}