{
  "id": 2145707,
  "type": "Feature",
  "properties": {
    "tgn:hierarchy":[
        "tgn:2145707",
        "tgn:1000001",
        "tgn:7012149",
        "tgn:1002599",
        "tgn:7007708",
        "tgn:7029392"
    ],
    "tgn:id":2145707,
    "tgn:name":"Baldy Creek",
    "tgn:placetype":[
        "aat:300008706"
    ]
},
  "bbox": [],
  "geometry": {"coordinates":[-123.9833,44.9333],"type":"Point"}
}