{
  "id": 7574105,
  "type": "Feature",
  "properties": {
    "tgn:hierarchy":[
        "tgn:7574105",
        "tgn:1000004",
        "tgn:7000198",
        "tgn:1001977",
        "tgn:7029392"
    ],
    "tgn:id":7574105,
    "tgn:name:en":"Haldia Channel",
    "tgn:placetype":[
        "aat:300386965"
    ]
},
  "bbox": [],
  "geometry": {"coordinates":[88.027697,21.918208],"type":"Point"}
}