{
  "id": 7019245,
  "type": "Feature",
  "properties": {
    "tgn:hierarchy":[
        "tgn:7019245",
        "tgn:1000001",
        "tgn:2001429",
        "tgn:7012149",
        "tgn:7007566",
        "tgn:7029392"
    ],
    "tgn:id":7019245,
    "tgn:name":"Minnehaha Mine",
    "tgn:placetype":[
        "aat:300000390"
    ]
},
  "bbox": [],
  "geometry": {"coordinates":[-107.7333,33.4667],"type":"Point"}
}