{
  "id": 2424125,
  "type": "Feature",
  "properties": {
    "tgn:hierarchy":[
        "tgn:2424125",
        "tgn:1000001",
        "tgn:7012149",
        "tgn:2000227",
        "tgn:7007158",
        "tgn:7029392"
    ],
    "tgn:id":2424125,
    "tgn:name":"Johns Lake",
    "tgn:placetype":[
        "aat:300008680"
    ]
},
  "bbox": [],
  "geometry": {"coordinates":[-104.4167,37.2667],"type":"Point"}
}