{
  "id": 7337860,
  "type": "Feature",
  "properties": {
    "tgn:hierarchy":[
        "tgn:7337860",
        "tgn:7002825",
        "tgn:7016622",
        "tgn:1000003",
        "tgn:1000095",
        "tgn:7029392"
    ],
    "tgn:id":7337860,
    "tgn:name":"Ceniciento, Roque",
    "tgn:placetype":[
        "aat:300011692"
    ]
},
  "bbox": [],
  "geometry": {"coordinates":[-15.416667,28.183333],"type":"Point"}
}