{
  "id": 7592463,
  "type": "Feature",
  "properties": {
    "tgn:hierarchy":[
        "tgn:7592463",
        "tgn:1000004",
        "tgn:7000198",
        "tgn:7000799",
        "tgn:7029392"
    ],
    "tgn:id":7592463,
    "tgn:name:en":"Uparla Bhajnoa",
    "tgn:placetype":[
        "aat:300008347"
    ]
},
  "bbox": [],
  "geometry": {"coordinates":[74.191667,33.136111],"type":"Point"}
}