<<<<<<< HEAD
{
  "id": 7486642,
  "type": "Feature",
  "properties": {
    "tgn:hierarchy":[
        "tgn:7486642",
        "tgn:1000004",
        "tgn:7489179",
        "tgn:1000141",
        "tgn:7029392"
    ],
    "tgn:id":7486642,
    "tgn:name":"Paigu Xi",
    "tgn:placetype":[
        "aat:300008699"
    ]
},
  "bbox": [],
  "geometry": {"coordinates":[121.514444,24.596944],"type":"Point"}
}
=======
{"geometry":{"type":"Point","coordinates":[121.514444,24.596944]},"type":"Feature","properties":{"hierarchy":["tgn:7486642","tgn:1000004","tgn:7489179","tgn:1000141","tgn:7029392"],"placetype":["aat:300008699"],"id":7486642,"name:xx":"Paigu Xi"}}
>>>>>>> 03f74aca74312dbeaf24d7e61306dd6a786dc3d0
