{
  "id": 2469286,
  "type": "Feature",
  "properties": {
    "tgn:hierarchy":[
        "tgn:2469286",
        "tgn:1000001",
        "tgn:7012149",
        "tgn:2002274",
        "tgn:7013961",
        "tgn:7029392"
    ],
    "tgn:id":2469286,
    "tgn:name":"Longpole Creek",
    "tgn:placetype":[
        "aat:300008706"
    ]
},
  "bbox": [],
  "geometry": {"coordinates":[-81.8333,37.5333],"type":"Point"}
}