{
  "id": 7262493,
  "type": "Feature",
  "properties": {
    "tgn:hierarchy":[
        "tgn:7262493",
        "tgn:7003619",
        "tgn:1000003",
        "tgn:7016845",
        "tgn:7029392"
    ],
    "tgn:id":7262493,
    "tgn:name:nl":"Bruinhorst",
    "tgn:placetype":[
        "aat:300387502"
    ]
},
  "bbox": [],
  "geometry": {"coordinates":[5.583333,52.066667],"type":"Point"}
}