{
  "id": 2266129,
  "type": "Feature",
  "properties": {
    "tgn:hierarchy":[
        "tgn:2266129",
        "tgn:2002142",
        "tgn:1000001",
        "tgn:7012149",
        "tgn:7007919",
        "tgn:7029392"
    ],
    "tgn:id":2266129,
    "tgn:name":"Crawford Knob",
    "tgn:placetype":[
        "aat:300008798"
    ]
},
  "bbox": [],
  "geometry": {"coordinates":[-79.25,38.2333],"type":"Point"}
}