{
  "id": 7184957,
  "type": "Feature",
  "properties": {
    "tgn:hierarchy":[
        "tgn:7184957",
        "tgn:7000096",
        "tgn:1000003",
        "tgn:7000084",
        "tgn:7029392"
    ],
    "tgn:id":7184957,
    "tgn:name":"Gl\u00f6vzin",
    "tgn:placetype":[
        "aat:300008347"
    ]
},
  "bbox": [],
  "geometry": {"coordinates":[11.783333,53.133333],"type":"Point"}
}