{
  "id": 1139632,
  "type": "Feature",
  "properties": {
    "tgn:hierarchy":[
        "tgn:1139632",
        "tgn:1000004",
        "tgn:1000960",
        "tgn:1000111",
        "tgn:7029392"
    ],
    "tgn:id":1139632,
    "tgn:name":"Shuangtang",
    "tgn:placetype":[
        "aat:300008347"
    ]
},
  "bbox": [],
  "geometry": {"coordinates":[116.9333,38.8667],"type":"Point"}
}