{
  "id": 2571073,
  "type": "Feature",
  "properties": {
    "tgn:hierarchy":[
        "tgn:2571073",
        "tgn:1000001",
        "tgn:7012149",
        "tgn:2001709",
        "tgn:7007708",
        "tgn:7029392"
    ],
    "tgn:id":2571073,
    "tgn:name":"Patterson Spring",
    "tgn:placetype":[
        "aat:300008697"
    ]
},
  "bbox": [],
  "geometry": {"coordinates":[-118.8333,43.8333],"type":"Point"}
}