{
  "id": 7548468,
  "type": "Feature",
  "properties": {
    "tgn:hierarchy":[
        "tgn:7548468",
        "tgn:1000004",
        "tgn:7000198",
        "tgn:7016722",
        "tgn:7029392"
    ],
    "tgn:id":7548468,
    "tgn:name:en":"Deoria Kal\u0101n",
    "tgn:placetype":[
        "aat:300008347"
    ]
},
  "bbox": [],
  "geometry": {"coordinates":[79.933487,28.376154],"type":"Point"}
}