{
  "id": 2548158,
  "type": "Feature",
  "properties": {
    "tgn:hierarchy":[
        "tgn:2548158",
        "tgn:2000453",
        "tgn:1000001",
        "tgn:7012149",
        "tgn:7007250",
        "tgn:7029392"
    ],
    "tgn:id":2548158,
    "tgn:name":"North Hornet Mine",
    "tgn:placetype":[
        "aat:300000390"
    ]
},
  "bbox": [],
  "geometry": {"coordinates":[-116.6333,44.8833],"type":"Point"}
}