{
  "id": 2223583,
  "type": "Feature",
  "properties": {
    "tgn:hierarchy":[
        "tgn:2223583",
        "tgn:1000001",
        "tgn:7012149",
        "tgn:2000472",
        "tgn:7007250",
        "tgn:7029392"
    ],
    "tgn:id":2223583,
    "tgn:name":"Carter Creek",
    "tgn:placetype":[
        "aat:300008706"
    ]
},
  "bbox": [],
  "geometry": {"coordinates":[-111.6167,42.1667],"type":"Point"}
}