{
  "id": 2243301,
  "type": "Feature",
  "properties": {
    "tgn:hierarchy":[
        "tgn:2243301",
        "tgn:1000001",
        "tgn:7012149",
        "tgn:2001122",
        "tgn:7007522",
        "tgn:7029392"
    ],
    "tgn:id":2243301,
    "tgn:name":"Clear Spring Branch",
    "tgn:placetype":[
        "aat:300008699"
    ]
},
  "bbox": [],
  "geometry": {"coordinates":[-89.5833,31.2167],"type":"Point"}
}