{
  "id": 1117286,
  "type": "Feature",
  "properties": {
    "tgn:hierarchy":[
        "tgn:1117286",
        "tgn:1000001",
        "tgn:7012149",
        "tgn:7007157",
        "tgn:1002859",
        "tgn:7029392"
    ],
    "tgn:id":1117286,
    "tgn:name":"Merced, Lake",
    "tgn:placetype":[
        "aat:300008680"
    ]
},
  "bbox": [],
  "geometry": {"coordinates":[-122.4833,37.7167],"type":"Point"}
}