{
  "id": 2361073,
  "type": "Feature",
  "properties": {
    "tgn:hierarchy":[
        "tgn:2361073",
        "tgn:1000001",
        "tgn:7012149",
        "tgn:2001883",
        "tgn:7007825",
        "tgn:7029392"
    ],
    "tgn:id":2361073,
    "tgn:name":"Grassy Valley",
    "tgn:placetype":[
        "aat:300008761"
    ]
},
  "bbox": [],
  "geometry": {"coordinates":[-83.8667,36.05],"type":"Point"}
}