{
  "id": 2571328,
  "type": "Feature",
  "properties": {
    "tgn:hierarchy":[
        "tgn:2571328",
        "tgn:1002338",
        "tgn:1000001",
        "tgn:7012149",
        "tgn:7007516",
        "tgn:7029392"
    ],
    "tgn:id":2571328,
    "tgn:name":"Paul Cove",
    "tgn:placetype":[
        "aat:300132316"
    ]
},
  "bbox": [],
  "geometry": {"coordinates":[-76.1333,38.2667],"type":"Point"}
}