{
  "id": 7566784,
  "type": "Feature",
  "properties": {
    "tgn:hierarchy":[
        "tgn:7566784",
        "tgn:1000004",
        "tgn:7000198",
        "tgn:1001894",
        "tgn:7029392"
    ],
    "tgn:id":7566784,
    "tgn:name:en":"Kan\u0101ri Reserved Forest",
    "tgn:placetype":[
        "aat:300008865"
    ]
},
  "bbox": [],
  "geometry": {"coordinates":[79.015458,24.172248],"type":"Point"}
}