{
  "id": 7386611,
  "type": "Feature",
  "properties": {
    "tgn:hierarchy":[
        "tgn:7386611",
        "tgn:1001835",
        "tgn:1000001",
        "tgn:7005560",
        "tgn:7029392"
    ],
    "tgn:id":7386611,
    "tgn:name":"Providencia",
    "tgn:placetype":[
        "aat:300387007"
    ]
},
  "bbox": [],
  "geometry": {"coordinates":[-115.133333,31.016667],"type":"Point"}
}