{
  "id": 2685333,
  "type": "Feature",
  "properties": {
    "tgn:hierarchy":[
        "tgn:2685333",
        "tgn:1000001",
        "tgn:7012149",
        "tgn:1002779",
        "tgn:7007710",
        "tgn:7029392"
    ],
    "tgn:id":2685333,
    "tgn:name":"Spotts Knob",
    "tgn:placetype":[
        "aat:300008798"
    ]
},
  "bbox": [],
  "geometry": {"coordinates":[-77.2667,40.3333],"type":"Point"}
}