<<<<<<< HEAD
{
  "id": 7022820,
  "type": "Feature",
  "properties": {
    "tgn:hierarchy":[
        "tgn:7022820",
        "tgn:1000001",
        "tgn:7012149",
        "tgn:2002114",
        "tgn:7007827",
        "tgn:7029392"
    ],
    "tgn:id":7022820,
    "tgn:name":"DMAD Reservoir",
    "tgn:placetype":[
        "aat:300006191"
    ]
},
  "bbox": [],
  "geometry": {"coordinates":[-112.4833,39.3833],"type":"Point"}
}
=======
{"geometry":{"type":"Point","coordinates":[-112.483300,39.383300]},"type":"Feature","properties":{"hierarchy":["tgn:7022820","tgn:1000001","tgn:7012149","tgn:2002114","tgn:7007827","tgn:7029392"],"placetype":["aat:300006191"],"id":7022820,"name:xx":"DMAD Reservoir"}}
>>>>>>> 03f74aca74312dbeaf24d7e61306dd6a786dc3d0
