{
  "id": 2602666,
  "type": "Feature",
  "properties": {
    "tgn:hierarchy":[
        "tgn:2602666",
        "tgn:1000001",
        "tgn:2000862",
        "tgn:7012149",
        "tgn:7007256",
        "tgn:7029392"
    ],
    "tgn:id":2602666,
    "tgn:name":"Quail Ridge",
    "tgn:placetype":[
        "aat:300008347"
    ]
},
  "bbox": [],
  "geometry": {"coordinates":[-93.85,32.4167],"type":"Point"}
}