{
  "id": 2426528,
  "type": "Feature",
  "properties": {
    "tgn:hierarchy":[
        "tgn:2426528",
        "tgn:1000001",
        "tgn:7012149",
        "tgn:7013941",
        "tgn:7007568",
        "tgn:7029392"
    ],
    "tgn:id":2426528,
    "tgn:name":"Jones Hill",
    "tgn:placetype":[
        "aat:300008798"
    ]
},
  "bbox": [],
  "geometry": {"coordinates":[-74.15,44.4333],"type":"Point"}
}