{
  "id": 2594193,
  "type": "Feature",
  "properties": {
    "tgn:hierarchy":[
        "tgn:2594193",
        "tgn:1000001",
        "tgn:7012149",
        "tgn:2000966",
        "tgn:7007520",
        "tgn:7029392"
    ],
    "tgn:id":2594193,
    "tgn:name":"Porter Creek",
    "tgn:placetype":[
        "aat:300008706"
    ]
},
  "bbox": [],
  "geometry": {"coordinates":[-88.5667,46.3167],"type":"Point"}
}