{
  "id": 7081368,
  "type": "Feature",
  "properties": {
    "tgn:hierarchy":[
        "tgn:7081368",
        "tgn:1000003",
        "tgn:7003678",
        "tgn:7000084",
        "tgn:7029392"
    ],
    "tgn:id":7081368,
    "tgn:name":"Ysenburger Hecken",
    "tgn:placetype":[
        "aat:300008863"
    ]
},
  "bbox": [],
  "geometry": {"coordinates":[9.066667,50.15],"type":"Point"}
}