{
  "id": 2071623,
  "type": "Feature",
  "properties": {
    "tgn:hierarchy":[
        "tgn:2071623",
        "tgn:1000001",
        "tgn:7012149",
        "tgn:1002950",
        "tgn:7007568",
        "tgn:7029392"
    ],
    "tgn:id":2071623,
    "tgn:name":"Peruville",
    "tgn:placetype":[
        "aat:300008347"
    ]
},
  "bbox": [],
  "geometry": {"coordinates":[-76.3667,42.55],"type":"Point"}
}