{
  "id": 7477181,
  "type": "Feature",
  "properties": {
    "tgn:hierarchy":[
        "tgn:7477181",
        "tgn:7488858",
        "tgn:1000004",
        "tgn:1000141",
        "tgn:7029392"
    ],
    "tgn:id":7477181,
    "tgn:name":"Guwei",
    "tgn:placetype":[
        "aat:300008347"
    ]
},
  "bbox": [],
  "geometry": {"coordinates":[120.935837,23.910205],"type":"Point"}
}