{
  "id": 2299594,
  "type": "Feature",
  "properties": {
    "tgn:hierarchy":[
        "tgn:2299594",
        "tgn:1002149",
        "tgn:1000001",
        "tgn:7012149",
        "tgn:7007826",
        "tgn:7029392"
    ],
    "tgn:id":2299594,
    "tgn:name":"Duck Roost",
    "tgn:placetype":[
        "aat:300008798"
    ]
},
  "bbox": [],
  "geometry": {"coordinates":[-94.8333,31.15],"type":"Point"}
}