<<<<<<< HEAD
{
  "id": 7020330,
  "type": "Feature",
  "properties": {
    "tgn:hierarchy":[
        "tgn:7020330",
        "tgn:1000001",
        "tgn:7012149",
        "tgn:2001515",
        "tgn:7007709",
        "tgn:7029392"
    ],
    "tgn:id":7020330,
    "tgn:name":"Rich Mountain",
    "tgn:placetype":[
        "aat:300008798"
    ]
},
  "bbox": [],
  "geometry": {"coordinates":[-83.1667,35.0333],"type":"Point"}
}
=======
{"geometry":{"type":"Point","coordinates":[-83.166700,35.033300]},"type":"Feature","properties":{"hierarchy":["tgn:7020330","tgn:1000001","tgn:7012149","tgn:2001515","tgn:7007709","tgn:7029392"],"placetype":["aat:300008798"],"id":7020330,"name:xx":"Rich Mountain"}}
>>>>>>> 03f74aca74312dbeaf24d7e61306dd6a786dc3d0
