{
  "id": 7516326,
  "type": "Feature",
  "properties": {
    "tgn:hierarchy":[
        "tgn:7516326",
        "tgn:1009227",
        "tgn:7001866",
        "tgn:1000226",
        "tgn:1000006",
        "tgn:7029392"
    ],
    "tgn:id":7516326,
    "tgn:name:en":"Lawrence River",
    "tgn:placetype":[
        "aat:300008699"
    ]
},
  "bbox": [],
  "geometry": {"coordinates":[170.85,-43.45],"type":"Point"}
}