{
  "id": 2640587,
  "type": "Feature",
  "properties": {
    "tgn:hierarchy":[
        "tgn:2640587",
        "tgn:1000001",
        "tgn:7012149",
        "tgn:2001456",
        "tgn:7007566",
        "tgn:7029392"
    ],
    "tgn:id":2640587,
    "tgn:name":"San Lorenzo Arroyo",
    "tgn:placetype":[
        "aat:300008699"
    ]
},
  "bbox": [],
  "geometry": {"coordinates":[-107.0167,34.15],"type":"Point"}
}