{
  "id": 2371015,
  "type": "Feature",
  "properties": {
    "tgn:hierarchy":[
        "tgn:2371015",
        "tgn:1000001",
        "tgn:7012149",
        "tgn:2001708",
        "tgn:7007708",
        "tgn:7029392"
    ],
    "tgn:id":2371015,
    "tgn:name":"Hadson Creek",
    "tgn:placetype":[
        "aat:300008706"
    ]
},
  "bbox": [],
  "geometry": {"coordinates":[-119.0667,44.3667],"type":"Point"}
}