<<<<<<< HEAD
{
  "id": 7477590,
  "type": "Feature",
  "properties": {
    "tgn:hierarchy":[
        "tgn:7477590",
        "tgn:1000004",
        "tgn:7001013",
        "tgn:1000141",
        "tgn:7029392"
    ],
    "tgn:id":7477590,
    "tgn:name":"Liugu Pi",
    "tgn:placetype":[
        "aat:300008688"
    ]
},
  "bbox": [],
  "geometry": {"coordinates":[121.085785,24.998733],"type":"Point"}
}
=======
{"geometry":{"type":"Point","coordinates":[121.085785,24.998733]},"type":"Feature","properties":{"hierarchy":["tgn:7477590","tgn:1000004","tgn:7001013","tgn:1000141","tgn:7029392"],"placetype":["aat:300008688"],"id":7477590,"name:xx":"Liugu Pi"}}
>>>>>>> 03f74aca74312dbeaf24d7e61306dd6a786dc3d0
