{
  "id": 2760136,
  "type": "Feature",
  "properties": {
    "tgn:hierarchy":[
        "tgn:2760136",
        "tgn:1000001",
        "tgn:7016172",
        "tgn:2000119",
        "tgn:7012149",
        "tgn:7029392"
    ],
    "tgn:id":2760136,
    "tgn:name":"West Fork Point Remove Creek Site 14 Reservoir",
    "tgn:placetype":[
        "aat:300006191"
    ]
},
  "bbox": [],
  "geometry": {"coordinates":[-92.75,35.3333],"type":"Point"}
}