<<<<<<< HEAD
{
  "id": 2760136,
  "type": "Feature",
  "properties": {
    "tgn:hierarchy":[
        "tgn:2760136",
        "tgn:1000001",
        "tgn:7016172",
        "tgn:2000119",
        "tgn:7012149",
        "tgn:7029392"
    ],
    "tgn:id":2760136,
    "tgn:name":"West Fork Point Remove Creek Site 14 Reservoir",
    "tgn:placetype":[
        "aat:300006191"
    ]
},
  "bbox": [],
  "geometry": {"coordinates":[-92.75,35.3333],"type":"Point"}
}
=======
{"geometry":{"type":"Point","coordinates":[-92.750000,35.333300]},"type":"Feature","properties":{"hierarchy":["tgn:2760136","tgn:1000001","tgn:7016172","tgn:2000119","tgn:7012149","tgn:7029392"],"placetype":["aat:300006191"],"id":2760136,"name:xx":"West Fork Point Remove Creek Site 14 Reservoir"}}
>>>>>>> 03f74aca74312dbeaf24d7e61306dd6a786dc3d0
