{
  "id": 2128047,
  "type": "Feature",
  "properties": {
    "tgn:hierarchy":[
        "tgn:2128047",
        "tgn:1000001",
        "tgn:7012149",
        "tgn:2000285",
        "tgn:7007240",
        "tgn:7029392"
    ],
    "tgn:id":2128047,
    "tgn:name":"Albert Gordon Pond",
    "tgn:placetype":[
        "aat:300008680"
    ]
},
  "bbox": [],
  "geometry": {"coordinates":[-87.0333,30.55],"type":"Point"}
}