{
  "id": 2000676,
  "type": "Feature",
  "properties": {
    "tgn:hierarchy":[
        "tgn:2000676",
        "tgn:1000001",
        "tgn:7012149",
        "tgn:7007254",
        "tgn:7029392"
    ],
    "tgn:id":2000676,
    "tgn:name":"Comanche",
    "tgn:placetype":[
        "aat:300387145",
        "aat:300000771"
    ]
},
  "bbox": [],
  "geometry": {"coordinates":[-99.2667,37.1833],"type":"Point"}
}