{
  "id": 7008226,
  "type": "Feature",
  "properties": {
    "tgn:hierarchy":[
        "tgn:7008226",
        "tgn:1000003",
        "tgn:7002875",
        "tgn:1000070",
        "tgn:7029392"
    ],
    "tgn:id":7008226,
    "tgn:name":"Is-sur-Tille",
    "tgn:placetype":[
        "aat:300008347"
    ]
},
  "bbox": [],
  "geometry": {"coordinates":[5.1167,47.5333],"type":"Point"}
}