{
  "id": 7291697,
  "type": "Feature",
  "properties": {
    "tgn:hierarchy":[
        "tgn:7291697",
        "tgn:1001768",
        "tgn:1000049",
        "tgn:1000002",
        "tgn:7029392"
    ],
    "tgn:id":7291697,
    "tgn:name":"El Potrerillo, Quebrada",
    "tgn:placetype":[
        "aat:300008699"
    ]
},
  "bbox": [],
  "geometry": {"coordinates":[-70.75,-32.583333],"type":"Point"}
}