{
  "id": 7534450,
  "type": "Feature",
  "properties": {
    "tgn:hierarchy":[
        "tgn:7534450",
        "tgn:7001242",
        "tgn:7016833",
        "tgn:7000123",
        "tgn:7029392"
    ],
    "tgn:id":7534450,
    "tgn:name:en":"Dayr al Mal\u0101k",
    "tgn:placetype":[
        "aat:300000641"
    ]
},
  "bbox": [],
  "geometry": {"coordinates":[32.316667,26.066667],"type":"Point"}
}