{
  "id": 2224430,
  "type": "Feature",
  "properties": {
    "tgn:hierarchy":[
        "tgn:2224430",
        "tgn:1000001",
        "tgn:2001793",
        "tgn:7012149",
        "tgn:7007713",
        "tgn:7029392"
    ],
    "tgn:id":2224430,
    "tgn:name":"Cascade Springs",
    "tgn:placetype":[
        "aat:300008697"
    ]
},
  "bbox": [],
  "geometry": {"coordinates":[-103.55,43.3333],"type":"Point"}
}