{
  "id": 7584730,
  "type": "Feature",
  "properties": {
    "tgn:hierarchy":[
        "tgn:7584730",
        "tgn:1000004",
        "tgn:7000198",
        "tgn:1001998",
        "tgn:7029392"
    ],
    "tgn:id":7584730,
    "tgn:name:en":"Zawngin",
    "tgn:placetype":[
        "aat:300008347"
    ]
},
  "bbox": [],
  "geometry": {"coordinates":[93.01808,23.902815],"type":"Point"}
}