{
  "id": 2367916,
  "type": "Feature",
  "properties": {
    "tgn:hierarchy":[
        "tgn:2367916",
        "tgn:1000001",
        "tgn:7012149",
        "tgn:2000992",
        "tgn:7007520",
        "tgn:7029392"
    ],
    "tgn:id":2367916,
    "tgn:name":"Groveton",
    "tgn:placetype":[
        "aat:300008347"
    ]
},
  "bbox": [],
  "geometry": {"coordinates":[-84.1167,43.2333],"type":"Point"}
}