{
  "id": 2775991,
  "type": "Feature",
  "properties": {
    "tgn:hierarchy":[
        "tgn:2775991",
        "tgn:1000001",
        "tgn:7012149",
        "tgn:2001457",
        "tgn:7007566",
        "tgn:7029392"
    ],
    "tgn:id":2775991,
    "tgn:name":"Wilson Prospect",
    "tgn:placetype":[
        "aat:300000390"
    ]
},
  "bbox": [],
  "geometry": {"coordinates":[-105.7833,36.2167],"type":"Point"}
}