{
  "id": 2188125,
  "type": "Feature",
  "properties": {
    "tgn:hierarchy":[
        "tgn:2188125",
        "tgn:1000001",
        "tgn:7012149",
        "tgn:7007157",
        "tgn:7029392"
    ],
    "tgn:id":2188125,
    "tgn:name":"Borrow Pit Drain",
    "tgn:placetype":[
        "aat:300006075"
    ]
},
  "bbox": [],
  "geometry": {"coordinates":[-114.6167,33.4833],"type":"Point"}
}