<<<<<<< HEAD
{
  "id": 2767664,
  "type": "Feature",
  "properties": {
    "tgn:hierarchy":[
        "tgn:2767664",
        "tgn:1000001",
        "tgn:7012149",
        "tgn:2001067",
        "tgn:7007521",
        "tgn:7029392"
    ],
    "tgn:id":2767664,
    "tgn:name":"Whiteface Reservoir",
    "tgn:placetype":[
        "aat:300006191"
    ]
},
  "bbox": [],
  "geometry": {"coordinates":[-92.2,47.2667],"type":"Point"}
}
=======
{"geometry":{"type":"Point","coordinates":[-92.200000,47.266700]},"type":"Feature","properties":{"hierarchy":["tgn:2767664","tgn:1000001","tgn:7012149","tgn:2001067","tgn:7007521","tgn:7029392"],"placetype":["aat:300006191"],"id":2767664,"name:xx":"Whiteface Reservoir"}}
>>>>>>> 03f74aca74312dbeaf24d7e61306dd6a786dc3d0
