{
  "id": 2684042,
  "type": "Feature",
  "properties": {
    "tgn:hierarchy":[
        "tgn:2684042",
        "tgn:1000001",
        "tgn:7012149",
        "tgn:1002358",
        "tgn:7007710",
        "tgn:7029392"
    ],
    "tgn:id":2684042,
    "tgn:name":"Spencer Creek",
    "tgn:placetype":[
        "aat:300008706"
    ]
},
  "bbox": [],
  "geometry": {"coordinates":[-79.6833,41.9667],"type":"Point"}
}