{
  "id": 7580640,
  "type": "Feature",
  "properties": {
    "tgn:hierarchy":[
        "tgn:7580640",
        "tgn:1000004",
        "tgn:1001832",
        "tgn:7000198",
        "tgn:7029392"
    ],
    "tgn:id":7580640,
    "tgn:name:en":"Tihu",
    "tgn:placetype":[
        "aat:300007783"
    ]
},
  "bbox": [],
  "geometry": {"coordinates":[91.25,26.466667],"type":"Point"}
}