{
  "id": 2365781,
  "type": "Feature",
  "properties": {
    "tgn:hierarchy":[
        "tgn:2365781",
        "tgn:1000001",
        "tgn:7012149",
        "tgn:7029392"
    ],
    "tgn:id":2365781,
    "tgn:name":"Gregorys Little Bald",
    "tgn:placetype":[
        "aat:300008798"
    ]
},
  "bbox": [],
  "geometry": {"coordinates":[-83.85,35.5167],"type":"Point"}
}