{
  "id": 7415116,
  "type": "Feature",
  "properties": {
    "tgn:hierarchy":[
        "tgn:7415116",
        "tgn:7005584",
        "tgn:1000001",
        "tgn:7005560",
        "tgn:7029392"
    ],
    "tgn:id":7415116,
    "tgn:name":"Los Amoles, Arroyo",
    "tgn:placetype":[
        "aat:300266554",
        "aat:300008699"
    ]
},
  "bbox": [],
  "geometry": {"coordinates":[-100.843611,20.046667],"type":"Point"}
}