{
  "id": 7524659,
  "type": "Feature",
  "properties": {
    "tgn:hierarchy":[
        "tgn:7524659",
        "tgn:7001242",
        "tgn:7016833",
        "tgn:1001088",
        "tgn:7029392"
    ],
    "tgn:id":7524659,
    "tgn:name:en":"Al Ma\u0163\u0101hirah ash Sharq\u012byah",
    "tgn:placetype":[
        "aat:300008347"
    ]
},
  "bbox": [],
  "geometry": {"coordinates":[30.852626,28.007003],"type":"Point"}
}