{
  "id": 7547011,
  "type": "Feature",
  "properties": {
    "tgn:hierarchy":[
        "tgn:7547011",
        "tgn:1000004",
        "tgn:7000198",
        "tgn:7016722",
        "tgn:7029392"
    ],
    "tgn:id":7547011,
    "tgn:name:en":"Adhaura",
    "tgn:placetype":[
        "aat:300008347"
    ]
},
  "bbox": [],
  "geometry": {"coordinates":[83.60976,24.695319],"type":"Point"}
}