{
  "id": 2307598,
  "type": "Feature",
  "properties": {
    "tgn:hierarchy":[
        "tgn:2307598",
        "tgn:1000001",
        "tgn:7012149",
        "tgn:2001282",
        "tgn:7007524",
        "tgn:7029392"
    ],
    "tgn:id":2307598,
    "tgn:name":"East Fork Stiner Creek",
    "tgn:placetype":[
        "aat:300008706"
    ]
},
  "bbox": [],
  "geometry": {"coordinates":[-110.4833,46.8833],"type":"Point"}
}