{
  "id": 2635049,
  "type": "Feature",
  "properties": {
    "tgn:hierarchy":[
        "tgn:2635049",
        "tgn:1000001",
        "tgn:7012149",
        "tgn:2000232",
        "tgn:7007158",
        "tgn:7029392"
    ],
    "tgn:id":2635049,
    "tgn:name":"Rye Grass Draw",
    "tgn:placetype":[
        "aat:300008761"
    ]
},
  "bbox": [],
  "geometry": {"coordinates":[-108.6833,40.5667],"type":"Point"}
}