{
  "id": 2226347,
  "type": "Feature",
  "properties": {
    "tgn:hierarchy":[
        "tgn:2226347",
        "tgn:1000001",
        "tgn:7012149",
        "tgn:2001252",
        "tgn:7007523",
        "tgn:7029392"
    ],
    "tgn:id":2226347,
    "tgn:name":"Cathcart Hollow",
    "tgn:placetype":[
        "aat:300008761"
    ]
},
  "bbox": [],
  "geometry": {"coordinates":[-91.9167,37.35],"type":"Point"}
}