{
  "id": 2608154,
  "type": "Feature",
  "properties": {
    "tgn:hierarchy":[
        "tgn:2608154",
        "tgn:1000001",
        "tgn:7012149",
        "tgn:7007157",
        "tgn:2000189",
        "tgn:7029392"
    ],
    "tgn:id":2608154,
    "tgn:name":"Rattlesnake Butte",
    "tgn:placetype":[
        "aat:300008798"
    ]
},
  "bbox": [],
  "geometry": {"coordinates":[-121.9667,41.75],"type":"Point"}
}