<<<<<<< HEAD
{
  "id": 7350336,
  "type": "Feature",
  "properties": {
    "tgn:hierarchy":[
        "tgn:7350336",
        "tgn:7005583",
        "tgn:1000001",
        "tgn:7005560",
        "tgn:7029392"
    ],
    "tgn:id":7350336,
    "tgn:name":"Bernalejo",
    "tgn:placetype":[
        "aat:300008347"
    ]
},
  "bbox": [],
  "geometry": {"coordinates":[-104.225,22.7],"type":"Point"}
}
=======
{"geometry":{"type":"Point","coordinates":[-104.225000,22.700000]},"type":"Feature","properties":{"hierarchy":["tgn:7350336","tgn:7005583","tgn:1000001","tgn:7005560","tgn:7029392"],"placetype":["aat:300008347"],"id":7350336,"name:xx":"Bernalejo"}}
>>>>>>> 03f74aca74312dbeaf24d7e61306dd6a786dc3d0
