{
  "id": 2303102,
  "type": "Feature",
  "properties": {
    "tgn:hierarchy":[
        "tgn:2303102",
        "tgn:1000001",
        "tgn:2001409",
        "tgn:7012149",
        "tgn:7007526",
        "tgn:7029392"
    ],
    "tgn:id":2303102,
    "tgn:name":"E Line Canal",
    "tgn:placetype":[
        "aat:300006075"
    ]
},
  "bbox": [],
  "geometry": {"coordinates":[-118.8667,39.4167],"type":"Point"}
}