{
  "id": 2628482,
  "type": "Feature",
  "properties": {
    "tgn:hierarchy":[
        "tgn:2628482",
        "tgn:1000001",
        "tgn:7012149",
        "tgn:2001287",
        "tgn:7007524",
        "tgn:7029392"
    ],
    "tgn:id":2628482,
    "tgn:name":"Rooney Spring",
    "tgn:placetype":[
        "aat:300008697"
    ]
},
  "bbox": [],
  "geometry": {"coordinates":[-106.0167,47.8333],"type":"Point"}
}