{
  "id": 2202137,
  "type": "Feature",
  "properties": {
    "tgn:hierarchy":[
        "tgn:2202137",
        "tgn:1000001",
        "tgn:7012149",
        "tgn:1002919",
        "tgn:7007252",
        "tgn:7029392"
    ],
    "tgn:id":2202137,
    "tgn:name":"Buck Lake",
    "tgn:placetype":[
        "aat:300008680"
    ]
},
  "bbox": [],
  "geometry": {"coordinates":[-85.0333,41.6333],"type":"Point"}
}