{
  "id": 7048317,
  "type": "Feature",
  "properties": {
    "tgn:hierarchy":[
        "tgn:7048317",
        "tgn:7003164",
        "tgn:1000003",
        "tgn:7009760",
        "tgn:1000080",
        "tgn:7029392"
    ],
    "tgn:id":7048317,
    "tgn:name":"Enfola, Capo d'",
    "tgn:placetype":[
        "aat:300008850"
    ]
},
  "bbox": [],
  "geometry": {"coordinates":[10.266667,42.833333],"type":"Point"}
}