{
  "id": 1100341,
  "type": "Feature",
  "properties": {
    "tgn:hierarchy":[
        "tgn:1100341",
        "tgn:1000003",
        "tgn:7003687",
        "tgn:7000084",
        "tgn:7029392"
    ],
    "tgn:id":1100341,
    "tgn:name":"Rudelsburg",
    "tgn:placetype":[
        "aat:300006891"
    ]
},
  "bbox": [],
  "geometry": {"coordinates":[11.7167,51.1167],"type":"Point"}
}