<<<<<<< HEAD
{
  "id": 2407137,
  "type": "Feature",
  "properties": {
    "tgn:hierarchy":[
        "tgn:2407137",
        "tgn:1000001",
        "tgn:2001263",
        "tgn:7012149",
        "tgn:7007524",
        "tgn:7029392"
    ],
    "tgn:id":2407137,
    "tgn:name":"Hunters Gulch",
    "tgn:placetype":[
        "aat:300008761"
    ]
},
  "bbox": [],
  "geometry": {"coordinates":[-111.5667,46.7],"type":"Point"}
}
=======
{"geometry":{"type":"Point","coordinates":[-111.566700,46.700000]},"type":"Feature","properties":{"hierarchy":["tgn:2407137","tgn:1000001","tgn:2001263","tgn:7012149","tgn:7007524","tgn:7029392"],"placetype":["aat:300008761"],"id":2407137,"name:xx":"Hunters Gulch"}}
>>>>>>> 03f74aca74312dbeaf24d7e61306dd6a786dc3d0
