{
  "id": 7172998,
  "type": "Feature",
  "properties": {
    "tgn:hierarchy":[
        "tgn:7172998",
        "tgn:7003692",
        "tgn:1000003",
        "tgn:7000084",
        "tgn:7029392"
    ],
    "tgn:id":7172998,
    "tgn:name":"Gro\u00dfer Wald",
    "tgn:placetype":[
        "aat:300008863"
    ]
},
  "bbox": [],
  "geometry": {"coordinates":[8.216667,48.666667],"type":"Point"}
}