{
  "id": 1030603,
  "type": "Feature",
  "properties": {
    "tgn:hierarchy":[
        "tgn:1030603",
        "tgn:7002445",
        "tgn:1003664",
        "tgn:1000003",
        "tgn:7026570",
        "tgn:7008591",
        "tgn:7029392"
    ],
    "tgn:id":1030603,
    "tgn:name":"Shevington Moor",
    "tgn:placetype":[
        "aat:300008347"
    ]
},
  "bbox": [],
  "geometry": {"coordinates":[-2.6833,53.5833],"type":"Point"}
}