{
  "id": 1006101,
  "type": "Feature",
  "properties": {
    "tgn:hierarchy":[
        "tgn:1006101",
        "tgn:1010215",
        "tgn:1000217",
        "tgn:1000006",
        "tgn:7029392"
    ],
    "tgn:id":1006101,
    "tgn:name":"Rawaki",
    "tgn:placetype":[
        "aat:300008793"
    ]
},
  "bbox": [],
  "geometry": {"coordinates":[-170.7167,-3.7167],"type":"Point"}
}