{
  "id": 7158693,
  "type": "Feature",
  "properties": {
    "tgn:hierarchy":[
        "tgn:7158693",
        "tgn:7003672",
        "tgn:1000003",
        "tgn:7000084",
        "tgn:7029392"
    ],
    "tgn:id":7158693,
    "tgn:name":"Hohentorshafen",
    "tgn:placetype":[
        "aat:300008678"
    ]
},
  "bbox": [],
  "geometry": {"coordinates":[8.766667,53.083333],"type":"Point"}
}