{
  "id": 2011159,
  "type": "Feature",
  "properties": {
    "tgn:hierarchy":[
        "tgn:2011159",
        "tgn:1000001",
        "tgn:7012149",
        "tgn:1002350",
        "tgn:7007157",
        "tgn:7029392"
    ],
    "tgn:id":2011159,
    "tgn:name":"Echo Lake",
    "tgn:placetype":[
        "aat:300008347"
    ]
},
  "bbox": [],
  "geometry": {"coordinates":[-120.0333,38.8333],"type":"Point"}
}