{
  "id": 2092461,
  "type": "Feature",
  "properties": {
    "tgn:hierarchy":[
        "tgn:2092461",
        "tgn:1000001",
        "tgn:7012149",
        "tgn:1002692",
        "tgn:7007710",
        "tgn:7029392"
    ],
    "tgn:id":2092461,
    "tgn:name":"Ridgeville",
    "tgn:placetype":[
        "aat:300008347"
    ]
},
  "bbox": [],
  "geometry": {"coordinates":[-76.55,40.9667],"type":"Point"}
}