{
  "id": 7298065,
  "type": "Feature",
  "properties": {
    "tgn:hierarchy":[
        "tgn:7298065",
        "tgn:7002822",
        "tgn:1001647",
        "tgn:1000003",
        "tgn:1000095",
        "tgn:7029392"
    ],
    "tgn:id":7298065,
    "tgn:name":"Solana, Arroyo de la",
    "tgn:placetype":[
        "aat:300008699"
    ]
},
  "bbox": [],
  "geometry": {"coordinates":[-2.65,40.55],"type":"Point"}
}