{
  "id": 7226624,
  "type": "Feature",
  "properties": {
    "tgn:hierarchy":[
        "tgn:7226624",
        "tgn:7011330",
        "tgn:7002674",
        "tgn:1000003",
        "tgn:1000074",
        "tgn:7029392"
    ],
    "tgn:id":7226624,
    "tgn:name":"P\u00e1tos, \u00c1kra",
    "tgn:placetype":[
        "aat:300008850"
    ]
},
  "bbox": [],
  "geometry": {"coordinates":[27.866667,36.533333],"type":"Point"}
}