<<<<<<< HEAD
{
  "id": 2333574,
  "type": "Feature",
  "properties": {
    "tgn:hierarchy":[
        "tgn:2333574",
        "tgn:1000001",
        "tgn:7012149",
        "tgn:2000232",
        "tgn:7007158",
        "tgn:7029392"
    ],
    "tgn:id":2333574,
    "tgn:name":"Fonce Wash",
    "tgn:placetype":[
        "aat:300008761"
    ]
},
  "bbox": [],
  "geometry": {"coordinates":[-108.85,40.9333],"type":"Point"}
}
=======
{"geometry":{"type":"Point","coordinates":[-108.850000,40.933300]},"type":"Feature","properties":{"hierarchy":["tgn:2333574","tgn:1000001","tgn:7012149","tgn:2000232","tgn:7007158","tgn:7029392"],"placetype":["aat:300008761"],"id":2333574,"name:xx":"Fonce Wash"}}
>>>>>>> 03f74aca74312dbeaf24d7e61306dd6a786dc3d0
