{
  "id": 7004326,
  "type": "Feature",
  "properties": {
    "tgn:hierarchy":[
        "tgn:7004326",
        "tgn:7003669",
        "tgn:1000003",
        "tgn:7000084",
        "tgn:7029392"
    ],
    "tgn:id":7004326,
    "tgn:name:de":"Bayreuth",
    "tgn:placetype":[
        "aat:300008347",
        "aat:300387218",
        "aat:300008389",
        "aat:300387222",
        "aat:300005135"
    ]
},
  "bbox": [],
  "geometry": {"coordinates":[11.5833,49.45],"type":"Point"}
}