{
  "id": 2389396,
  "type": "Feature",
  "properties": {
    "tgn:hierarchy":[
        "tgn:2389396",
        "tgn:2000918",
        "tgn:1000001",
        "tgn:7012149",
        "tgn:7007515",
        "tgn:7029392"
    ],
    "tgn:id":2389396,
    "tgn:name":"Higgins Corner",
    "tgn:placetype":[
        "aat:300008347"
    ]
},
  "bbox": [],
  "geometry": {"coordinates":[-70.0333,44.0333],"type":"Point"}
}