<<<<<<< HEAD
{
  "id": 2401743,
  "type": "Feature",
  "properties": {
    "tgn:hierarchy":[
        "tgn:2401743",
        "tgn:1000001",
        "tgn:7012149",
        "tgn:2000990",
        "tgn:7007520",
        "tgn:7029392"
    ],
    "tgn:id":2401743,
    "tgn:name":"Horseshoe Lake",
    "tgn:placetype":[
        "aat:300008680"
    ]
},
  "bbox": [],
  "geometry": {"coordinates":[-83.95,45.25],"type":"Point"}
}
=======
{"geometry":{"type":"Point","coordinates":[-83.950000,45.250000]},"type":"Feature","properties":{"hierarchy":["tgn:2401743","tgn:1000001","tgn:7012149","tgn:2000990","tgn:7007520","tgn:7029392"],"placetype":["aat:300008680"],"id":2401743,"name:xx":"Horseshoe Lake"}}
>>>>>>> 03f74aca74312dbeaf24d7e61306dd6a786dc3d0
