{
  "id": 7029359,
  "type": "Feature",
  "properties": {
    "tgn:hierarchy":[
        "tgn:7029359",
        "tgn:7002445",
        "tgn:1000003",
        "tgn:7008166",
        "tgn:7008591",
        "tgn:7029392"
    ],
    "tgn:id":7029359,
    "tgn:name":"South Duffield",
    "tgn:placetype":[
        "aat:300008347",
        "aat:300008372"
    ]
},
  "bbox": [],
  "geometry": {"coordinates":[-0.965,53.785],"type":"Point"}
}