{
  "id": 1113677,
  "type": "Feature",
  "properties": {
    "tgn:hierarchy":[
        "tgn:1113677",
        "tgn:1002933",
        "tgn:1000001",
        "tgn:7012149",
        "tgn:7007239",
        "tgn:7029392"
    ],
    "tgn:id":1113677,
    "tgn:name":"Rehoboth Bay",
    "tgn:placetype":[
        "aat:300132316"
    ]
},
  "bbox": [],
  "geometry": {"coordinates":[-75.0833,38.65],"type":"Point"}
}