<<<<<<< HEAD
{
  "id": 2159504,
  "type": "Feature",
  "properties": {
    "tgn:hierarchy":[
        "tgn:2159504",
        "tgn:1000001",
        "tgn:7012149",
        "tgn:7007157",
        "tgn:7014516",
        "tgn:7029392"
    ],
    "tgn:id":2159504,
    "tgn:name":"Bee Knoll",
    "tgn:placetype":[
        "aat:300008798"
    ]
},
  "bbox": [],
  "geometry": {"coordinates":[-123.2167,38.6833],"type":"Point"}
}
=======
{"geometry":{"type":"Point","coordinates":[-123.216700,38.683300]},"type":"Feature","properties":{"hierarchy":["tgn:2159504","tgn:1000001","tgn:7012149","tgn:7007157","tgn:7014516","tgn:7029392"],"placetype":["aat:300008798"],"id":2159504,"name:xx":"Bee Knoll"}}
>>>>>>> 03f74aca74312dbeaf24d7e61306dd6a786dc3d0
