{
  "id": 2159504,
  "type": "Feature",
  "properties": {
    "tgn:hierarchy":[
        "tgn:2159504",
        "tgn:1000001",
        "tgn:7012149",
        "tgn:7007157",
        "tgn:7014516",
        "tgn:7029392"
    ],
    "tgn:id":2159504,
    "tgn:name":"Bee Knoll",
    "tgn:placetype":[
        "aat:300008798"
    ]
},
  "bbox": [],
  "geometry": {"coordinates":[-123.2167,38.6833],"type":"Point"}
}