{
  "id": 7336044,
  "type": "Feature",
  "properties": {
    "tgn:hierarchy":[
        "tgn:7336044",
        "tgn:7002834",
        "tgn:1000003",
        "tgn:7002786",
        "tgn:1000095",
        "tgn:7029392"
    ],
    "tgn:id":7336044,
    "tgn:name":"Furnia, R\u00edo de la",
    "tgn:placetype":[
        "aat:300008699"
    ]
},
  "bbox": [],
  "geometry": {"coordinates":[-8.683333,41.983333],"type":"Point"}
}