{
  "id": 1062036,
  "type": "Feature",
  "properties": {
    "tgn:hierarchy":[
        "tgn:1062036",
        "tgn:7002805",
        "tgn:7002758",
        "tgn:1000003",
        "tgn:1000095",
        "tgn:7029392"
    ],
    "tgn:id":1062036,
    "tgn:name":"G\u00e1dor",
    "tgn:placetype":[
        "aat:300008347"
    ]
},
  "bbox": [],
  "geometry": {"coordinates":[-2.483333,36.95],"type":"Point"}
}