{
  "id": 2671527,
  "type": "Feature",
  "properties": {
    "tgn:hierarchy":[
        "tgn:2671527",
        "tgn:1000001",
        "tgn:2000327",
        "tgn:7012149",
        "tgn:7007248",
        "tgn:7029392"
    ],
    "tgn:id":2671527,
    "tgn:name":"Smith Lake",
    "tgn:placetype":[
        "aat:300006191"
    ]
},
  "bbox": [],
  "geometry": {"coordinates":[-82.2333,33.5833],"type":"Point"}
}