{
  "id": 1099275,
  "type": "Feature",
  "properties": {
    "tgn:hierarchy":[
        "tgn:1099275",
        "tgn:1008380",
        "tgn:1000226",
        "tgn:7000512",
        "tgn:1000006",
        "tgn:7029392"
    ],
    "tgn:id":1099275,
    "tgn:name:en":"Tinui",
    "tgn:placetype":[
        "aat:300008347"
    ]
},
  "bbox": [],
  "geometry": {"coordinates":[176.066667,-40.883333],"type":"Point"}
}