{
  "id": 1092901,
  "type": "Feature",
  "properties": {
    "tgn:hierarchy":[
        "tgn:1092901",
        "tgn:7001242",
        "tgn:7017584",
        "tgn:1000193",
        "tgn:7029392"
    ],
    "tgn:id":1092901,
    "tgn:name":"Bonnievale",
    "tgn:placetype":[
        "aat:300008347"
    ]
},
  "bbox": [],
  "geometry": {"coordinates":[20.0833,-33.9167],"type":"Point"}
}