{
  "id": 7344557,
  "type": "Feature",
  "properties": {
    "tgn:hierarchy":[
        "tgn:7344557",
        "tgn:7002824",
        "tgn:1000003",
        "tgn:7002786",
        "tgn:1000095",
        "tgn:7029392"
    ],
    "tgn:id":7344557,
    "tgn:name":"Anse\u00e1n",
    "tgn:placetype":[
        "aat:300008347"
    ]
},
  "bbox": [],
  "geometry": {"coordinates":[-9.083333,42.966667],"type":"Point"}
}