{
  "id": 7294450,
  "type": "Feature",
  "properties": {
    "tgn:hierarchy":[
        "tgn:7294450",
        "tgn:7002844",
        "tgn:7030216",
        "tgn:1000003",
        "tgn:1000095",
        "tgn:7029392"
    ],
    "tgn:id":7294450,
    "tgn:name":"Vallvert, R\u00edo",
    "tgn:placetype":[
        "aat:300008699"
    ]
},
  "bbox": [],
  "geometry": {"coordinates":[1.220275,41.431423],"type":"Point"}
}