{
  "id": 2629749,
  "type": "Feature",
  "properties": {
    "tgn:hierarchy":[
        "tgn:2629749",
        "tgn:1000001",
        "tgn:7012149",
        "tgn:2001927",
        "tgn:7007825",
        "tgn:7029392"
    ],
    "tgn:id":2629749,
    "tgn:name":"Ross Creek",
    "tgn:placetype":[
        "aat:300008706"
    ]
},
  "bbox": [],
  "geometry": {"coordinates":[-87.9167,35.3667],"type":"Point"}
}