{
  "id": 1128016,
  "type": "Feature",
  "properties": {
    "tgn:hierarchy":[
        "tgn:1128016",
        "tgn:1000003",
        "tgn:7002877",
        "tgn:1000070",
        "tgn:7029392"
    ],
    "tgn:id":1128016,
    "tgn:name":"Oeuf",
    "tgn:placetype":[
        "aat:300008707"
    ]
},
  "bbox": [],
  "geometry": {"coordinates":[2.35,48.1833],"type":"Point"}
}