{
  "id": 2370917,
  "type": "Feature",
  "properties": {
    "tgn:hierarchy":[
        "tgn:2370917",
        "tgn:1000001",
        "tgn:7012149",
        "tgn:7007708",
        "tgn:7029392"
    ],
    "tgn:id":2370917,
    "tgn:name":"Haden Creek",
    "tgn:placetype":[
        "aat:300008706"
    ]
},
  "bbox": [],
  "geometry": {"coordinates":[-118.9833,44.9667],"type":"Point"}
}