{
  "id": 2244812,
  "type": "Feature",
  "properties": {
    "tgn:hierarchy":[
        "tgn:2244812",
        "tgn:1000001",
        "tgn:7012149",
        "tgn:2001297",
        "tgn:7007524",
        "tgn:7029392"
    ],
    "tgn:id":2244812,
    "tgn:name":"Cloudburst Reservoir",
    "tgn:placetype":[
        "aat:300006191"
    ]
},
  "bbox": [],
  "geometry": {"coordinates":[-106.0833,45.4167],"type":"Point"}
}