<<<<<<< HEAD
{
  "id": 2337769,
  "type": "Feature",
  "properties": {
    "tgn:hierarchy":[
        "tgn:2337769",
        "tgn:1000001",
        "tgn:7012149",
        "tgn:2001556",
        "tgn:7007709",
        "tgn:7029392"
    ],
    "tgn:id":2337769,
    "tgn:name":"Fox Creek",
    "tgn:placetype":[
        "aat:300008706"
    ]
},
  "bbox": [],
  "geometry": {"coordinates":[-82.4833,35.9333],"type":"Point"}
}
=======
{"geometry":{"type":"Point","coordinates":[-82.483300,35.933300]},"type":"Feature","properties":{"hierarchy":["tgn:2337769","tgn:1000001","tgn:7012149","tgn:2001556","tgn:7007709","tgn:7029392"],"placetype":["aat:300008706"],"id":2337769,"name:xx":"Fox Creek"}}
>>>>>>> 03f74aca74312dbeaf24d7e61306dd6a786dc3d0
