{
  "id": 7234877,
  "type": "Feature",
  "properties": {
    "tgn:hierarchy":[
        "tgn:7234877",
        "tgn:7002752",
        "tgn:7001399",
        "tgn:1000003",
        "tgn:1000074",
        "tgn:7029392"
    ],
    "tgn:id":7234877,
    "tgn:name":"A\u00ebt\u00f3s",
    "tgn:placetype":[
        "aat:300008347"
    ]
},
  "bbox": [],
  "geometry": {"coordinates":[21.283333,39.462222],"type":"Point"}
}