<<<<<<< HEAD
{
  "id": 7485333,
  "type": "Feature",
  "properties": {
    "tgn:hierarchy":[
        "tgn:7485333",
        "tgn:7468018",
        "tgn:1000004",
        "tgn:1000141",
        "tgn:7029392"
    ],
    "tgn:id":7485333,
    "tgn:name":"Shanmei",
    "tgn:placetype":[
        "aat:300008347"
    ]
},
  "bbox": [],
  "geometry": {"coordinates":[120.549444,23.572222],"type":"Point"}
}
=======
{"geometry":{"type":"Point","coordinates":[120.549444,23.572222]},"type":"Feature","properties":{"hierarchy":["tgn:7485333","tgn:7468018","tgn:1000004","tgn:1000141","tgn:7029392"],"placetype":["aat:300008347"],"id":7485333,"name:xx":"Shanmei"}}
>>>>>>> 03f74aca74312dbeaf24d7e61306dd6a786dc3d0
