{
  "id": 7103871,
  "type": "Feature",
  "properties": {
    "tgn:hierarchy":[
        "tgn:7103871",
        "tgn:7003669",
        "tgn:1000003",
        "tgn:7000084",
        "tgn:7029392"
    ],
    "tgn:id":7103871,
    "tgn:name":"Schlag",
    "tgn:placetype":[
        "aat:300000206"
    ]
},
  "bbox": [],
  "geometry": {"coordinates":[12.916667,48.633333],"type":"Point"}
}