{
  "id": 7552925,
  "type": "Feature",
  "properties": {
    "tgn:hierarchy":[
        "tgn:7552925",
        "tgn:1000004",
        "tgn:7000198",
        "tgn:7000799",
        "tgn:7029392"
    ],
    "tgn:id":7552925,
    "tgn:name:en":"Mujhpathar",
    "tgn:placetype":[
        "aat:300008347"
    ]
},
  "bbox": [],
  "geometry": {"coordinates":[74.628905,33.883933],"type":"Point"}
}