{
  "id": 7477167,
  "type": "Feature",
  "properties": {
    "tgn:hierarchy":[
        "tgn:7477167",
        "tgn:7488858",
        "tgn:1000004",
        "tgn:1000141",
        "tgn:7029392"
    ],
    "tgn:id":7477167,
    "tgn:name":"Tiaomikengkou",
    "tgn:placetype":[
        "aat:300008347"
    ]
},
  "bbox": [],
  "geometry": {"coordinates":[120.771325,23.864377],"type":"Point"}
}