{
  "id": 7320061,
  "type": "Feature",
  "properties": {
    "tgn:hierarchy":[
        "tgn:7320061",
        "tgn:1001657",
        "tgn:1000049",
        "tgn:1000002",
        "tgn:7029392"
    ],
    "tgn:id":7320061,
    "tgn:name":"Alcones, Quebrada",
    "tgn:placetype":[
        "aat:300266554",
        "aat:300008699"
    ]
},
  "bbox": [],
  "geometry": {"coordinates":[-71.516667,-30.75],"type":"Point"}
}