{
  "id": 2584423,
  "type": "Feature",
  "properties": {
    "tgn:hierarchy":[
        "tgn:2584423",
        "tgn:1000001",
        "tgn:7012149",
        "tgn:2002378",
        "tgn:7007923",
        "tgn:7029392"
    ],
    "tgn:id":2584423,
    "tgn:name":"Piney Draw",
    "tgn:placetype":[
        "aat:300008761"
    ]
},
  "bbox": [],
  "geometry": {"coordinates":[-104.8167,43.4167],"type":"Point"}
}