{
  "id": 7279866,
  "type": "Feature",
  "properties": {
    "tgn:hierarchy":[
        "tgn:7279866",
        "tgn:1001657",
        "tgn:1000049",
        "tgn:1000002",
        "tgn:7029392"
    ],
    "tgn:id":7279866,
    "tgn:name":"Ramadillas, Quebrada",
    "tgn:placetype":[
        "aat:300008699"
    ]
},
  "bbox": [],
  "geometry": {"coordinates":[-70.666667,-30.916667],"type":"Point"}
}