{
  "id": 2339664,
  "type": "Feature",
  "properties": {
    "tgn:hierarchy":[
        "tgn:2339664",
        "tgn:1000001",
        "tgn:2002260",
        "tgn:7012149",
        "tgn:7013961",
        "tgn:7029392"
    ],
    "tgn:id":2339664,
    "tgn:name":"Freds Run",
    "tgn:placetype":[
        "aat:300008699"
    ]
},
  "bbox": [],
  "geometry": {"coordinates":[-80.8333,39.2167],"type":"Point"}
}