{
  "id": 2317482,
  "type": "Feature",
  "properties": {
    "tgn:hierarchy":[
        "tgn:2317482",
        "tgn:1000001",
        "tgn:2001431",
        "tgn:7012149",
        "tgn:7007566",
        "tgn:7029392"
    ],
    "tgn:id":2317482,
    "tgn:name":"Encantada, Mesa",
    "tgn:placetype":[
        "aat:300008798"
    ]
},
  "bbox": [],
  "geometry": {"coordinates":[-107.55,34.9167],"type":"Point"}
}