<<<<<<< HEAD
{
  "id": 2404043,
  "type": "Feature",
  "properties": {
    "tgn:hierarchy":[
        "tgn:2404043",
        "tgn:1000001",
        "tgn:7012149",
        "tgn:1003008",
        "tgn:7007710",
        "tgn:7029392"
    ],
    "tgn:id":2404043,
    "tgn:name":"Howell Pond",
    "tgn:placetype":[
        "aat:300008680"
    ]
},
  "bbox": [],
  "geometry": {"coordinates":[-75.35,41.75],"type":"Point"}
}
=======
{"geometry":{"type":"Point","coordinates":[-75.350000,41.750000]},"type":"Feature","properties":{"hierarchy":["tgn:2404043","tgn:1000001","tgn:7012149","tgn:1003008","tgn:7007710","tgn:7029392"],"placetype":["aat:300008680"],"id":2404043,"name:xx":"Howell Pond"}}
>>>>>>> 03f74aca74312dbeaf24d7e61306dd6a786dc3d0
