{
  "id": 2774193,
  "type": "Feature",
  "properties": {
    "tgn:hierarchy":[
        "tgn:2774193",
        "tgn:1000001",
        "tgn:7012149",
        "tgn:2001715",
        "tgn:7007708",
        "tgn:7029392"
    ],
    "tgn:id":2774193,
    "tgn:name":"Willow Creek Hills",
    "tgn:placetype":[
        "aat:300008798"
    ]
},
  "bbox": [],
  "geometry": {"coordinates":[-120.5833,42.15],"type":"Point"}
}