{
  "id": 2692724,
  "type": "Feature",
  "properties": {
    "tgn:hierarchy":[
        "tgn:2692724",
        "tgn:1000001",
        "tgn:7012149",
        "tgn:7007253",
        "tgn:7029392"
    ],
    "tgn:id":2692724,
    "tgn:name":"Steel Creek",
    "tgn:placetype":[
        "aat:300008706"
    ]
},
  "bbox": [],
  "geometry": {"coordinates":[-93.5667,40.8333],"type":"Point"}
}