{
  "id": 2184277,
  "type": "Feature",
  "properties": {
    "tgn:hierarchy":[
        "tgn:2184277",
        "tgn:1000001",
        "tgn:7012149",
        "tgn:1002486",
        "tgn:7007826",
        "tgn:7029392"
    ],
    "tgn:id":2184277,
    "tgn:name":"Bobbitt Lake",
    "tgn:placetype":[
        "aat:300008680"
    ]
},
  "bbox": [],
  "geometry": {"coordinates":[-95.2667,31.5333],"type":"Point"}
}