{
  "id": 2296788,
  "type": "Feature",
  "properties": {
    "tgn:hierarchy":[
        "tgn:2296788",
        "tgn:1000001",
        "tgn:2000667",
        "tgn:7012149",
        "tgn:7007254",
        "tgn:7029392"
    ],
    "tgn:id":2296788,
    "tgn:name":"Dry Creek",
    "tgn:placetype":[
        "aat:300008706"
    ]
},
  "bbox": [],
  "geometry": {"coordinates":[-97.1333,38.0333],"type":"Point"}
}