{
  "id": 2494993,
  "type": "Feature",
  "properties": {
    "tgn:hierarchy":[
        "tgn:2494993",
        "tgn:1000001",
        "tgn:7012149",
        "tgn:2000907",
        "tgn:7007256",
        "tgn:7029392"
    ],
    "tgn:id":2494993,
    "tgn:name":"Martins Landing",
    "tgn:placetype":[
        "aat:300008347"
    ]
},
  "bbox": [],
  "geometry": {"coordinates":[-91.5667,31.8333],"type":"Point"}
}