{
  "id": 7499326,
  "type": "Feature",
  "properties": {
    "tgn:hierarchy":[
        "tgn:7499326",
        "tgn:7001010",
        "tgn:1000004",
        "tgn:1000141",
        "tgn:7029392"
    ],
    "tgn:id":7499326,
    "tgn:name":"Nengya Qiao",
    "tgn:placetype":[
        "aat:300007836"
    ]
},
  "bbox": [],
  "geometry": {"coordinates":[121.40337,23.466701],"type":"Point"}
}