{
  "id": 2268602,
  "type": "Feature",
  "properties": {
    "tgn:hierarchy":[
        "tgn:2268602",
        "tgn:1000001",
        "tgn:7012149",
        "tgn:1002986",
        "tgn:7007568",
        "tgn:7029392"
    ],
    "tgn:id":2268602,
    "tgn:name":"Crosbyside",
    "tgn:placetype":[
        "aat:300008347"
    ]
},
  "bbox": [],
  "geometry": {"coordinates":[-73.6833,43.4167],"type":"Point"}
}