{
  "id": 7574539,
  "type": "Feature",
  "properties": {
    "tgn:hierarchy":[
        "tgn:7574539",
        "tgn:1000004",
        "tgn:1001869",
        "tgn:7000198",
        "tgn:7029392"
    ],
    "tgn:id":7574539,
    "tgn:name:en":"Kunria",
    "tgn:placetype":[
        "aat:300008347"
    ]
},
  "bbox": [],
  "geometry": {"coordinates":[69.727217,23.402634],"type":"Point"}
}