<<<<<<< HEAD
{
  "id": 2330282,
  "type": "Feature",
  "properties": {
    "tgn:hierarchy":[
        "tgn:2330282",
        "tgn:1000001",
        "tgn:2001014",
        "tgn:7012149",
        "tgn:7007521",
        "tgn:7029392"
    ],
    "tgn:id":2330282,
    "tgn:name":"Flap Lake",
    "tgn:placetype":[
        "aat:300008680"
    ]
},
  "bbox": [],
  "geometry": {"coordinates":[-90.9833,48.1],"type":"Point"}
}
=======
{"geometry":{"type":"Point","coordinates":[-90.983300,48.100000]},"type":"Feature","properties":{"hierarchy":["tgn:2330282","tgn:1000001","tgn:2001014","tgn:7012149","tgn:7007521","tgn:7029392"],"placetype":["aat:300008680"],"id":2330282,"name:xx":"Flap Lake"}}
>>>>>>> 03f74aca74312dbeaf24d7e61306dd6a786dc3d0
