{
  "id": 7376113,
  "type": "Feature",
  "properties": {
    "tgn:hierarchy":[
        "tgn:7376113",
        "tgn:1001853",
        "tgn:1000001",
        "tgn:7005560",
        "tgn:7029392"
    ],
    "tgn:id":7376113,
    "tgn:name":"Las Hormigas",
    "tgn:placetype":[
        "aat:300008347"
    ]
},
  "bbox": [],
  "geometry": {"coordinates":[-100.833333,24.966667],"type":"Point"}
}