{
  "id": 2577847,
  "type": "Feature",
  "properties": {
    "tgn:hierarchy":[
        "tgn:2577847",
        "tgn:2000858",
        "tgn:1000001",
        "tgn:7012149",
        "tgn:7007256",
        "tgn:7029392"
    ],
    "tgn:id":2577847,
    "tgn:name":"Petite Bayou du Lac",
    "tgn:placetype":[
        "aat:300008680"
    ]
},
  "bbox": [],
  "geometry": {"coordinates":[-91.9667,31.0667],"type":"Point"}
}