{
  "id": 7433793,
  "type": "Feature",
  "properties": {
    "tgn:hierarchy":[
        "tgn:7433793",
        "tgn:1000001",
        "tgn:7005592",
        "tgn:7005560",
        "tgn:7029392"
    ],
    "tgn:id":7433793,
    "tgn:name":"Yaon\u00e1huac",
    "tgn:placetype":[
        "aat:300008347"
    ]
},
  "bbox": [],
  "geometry": {"coordinates":[-97.45,19.866667],"type":"Point"}
}