{
  "id": 2730648,
  "type": "Feature",
  "properties": {
    "tgn:hierarchy":[
        "tgn:2730648",
        "tgn:1000001",
        "tgn:7012149",
        "tgn:7007157",
        "tgn:1002608",
        "tgn:7029392"
    ],
    "tgn:id":2730648,
    "tgn:name":"Trust Me Canyon",
    "tgn:placetype":[
        "aat:300008761"
    ]
},
  "bbox": [],
  "geometry": {"coordinates":[-118.8167,34.75],"type":"Point"}
}