<<<<<<< HEAD
{
  "id": 7244329,
  "type": "Feature",
  "properties": {
    "tgn:hierarchy":[
        "tgn:7244329",
        "tgn:7003461",
        "tgn:1000003",
        "tgn:1000063",
        "tgn:7018236",
        "tgn:7029392"
    ],
    "tgn:id":7244329,
    "tgn:name":"Kauwberg",
    "tgn:placetype":[
        "aat:300008777"
    ]
},
  "bbox": [],
  "geometry": {"coordinates":[5.033333,51.0],"type":"Point"}
}
=======
{"geometry":{"type":"Point","coordinates":[5.033333,51.000000]},"type":"Feature","properties":{"hierarchy":["tgn:7244329","tgn:7003461","tgn:1000003","tgn:1000063","tgn:7018236","tgn:7029392"],"placetype":["aat:300008777"],"id":7244329,"name:xx":"Kauwberg"}}
>>>>>>> 03f74aca74312dbeaf24d7e61306dd6a786dc3d0
