{
  "id": 7540405,
  "type": "Feature",
  "properties": {
    "tgn:hierarchy":[
        "tgn:7540405",
        "tgn:7001242",
        "tgn:1001075",
        "tgn:7016833",
        "tgn:7029392"
    ],
    "tgn:id":7540405,
    "tgn:name:en":"Minshat Aryamun",
    "tgn:placetype":[
        "aat:300008347"
    ]
},
  "bbox": [],
  "geometry": {"coordinates":[30.499913,31.138669],"type":"Point"}
}