{
  "id": 7237020,
  "type": "Feature",
  "properties": {
    "tgn:hierarchy":[
        "tgn:7237020",
        "tgn:7011330",
        "tgn:7002674",
        "tgn:1000003",
        "tgn:1000074",
        "tgn:7029392"
    ],
    "tgn:id":7237020,
    "tgn:name":"\u00c1gios Fok\u00e1s, \u00c1kra",
    "tgn:placetype":[
        "aat:300008850"
    ]
},
  "bbox": [],
  "geometry": {"coordinates":[27.355556,36.858333],"type":"Point"}
}