{
  "id": 1052454,
  "type": "Feature",
  "properties": {
    "tgn:hierarchy":[
        "tgn:1052454",
        "tgn:1000004",
        "tgn:7011604",
        "tgn:7018214",
        "tgn:7002435",
        "tgn:7029392"
    ],
    "tgn:id":1052454,
    "tgn:name":"Bakchar",
    "tgn:placetype":[
        "aat:300008347"
    ]
},
  "bbox": [],
  "geometry": {"coordinates":[82.1333,57.0667],"type":"Point"}
}