{
  "id": 7495775,
  "type": "Feature",
  "properties": {
    "tgn:hierarchy":[
        "tgn:7495775",
        "tgn:7488858",
        "tgn:1000004",
        "tgn:1000141",
        "tgn:7029392"
    ],
    "tgn:id":7495775,
    "tgn:name":"Lankoudian Yihao Qiao",
    "tgn:placetype":[
        "aat:300007836"
    ]
},
  "bbox": [],
  "geometry": {"coordinates":[120.646913,23.865956],"type":"Point"}
}