{
  "id": 2280128,
  "type": "Feature",
  "properties": {
    "tgn:hierarchy":[
        "tgn:2280128",
        "tgn:1000001",
        "tgn:2001424",
        "tgn:7012149",
        "tgn:7007564",
        "tgn:7029392"
    ],
    "tgn:id":2280128,
    "tgn:name":"Dearth Brook",
    "tgn:placetype":[
        "aat:300008699"
    ]
},
  "bbox": [],
  "geometry": {"coordinates":[-71.8667,44.1167],"type":"Point"}
}