{
  "id": 1108936,
  "type": "Feature",
  "properties": {
    "tgn:hierarchy":[
        "tgn:1108936",
        "tgn:1000001",
        "tgn:7005493",
        "tgn:7029392"
    ],
    "tgn:id":1108936,
    "tgn:name":"Cuchumatanes, Sierra de los",
    "tgn:placetype":[
        "aat:300008795"
    ]
},
  "bbox": [],
  "geometry": {"coordinates":[-91.346,15.416],"type":"Point"}
}