{
  "id": 1120903,
  "type": "Feature",
  "properties": {
    "tgn:hierarchy":[
        "tgn:1120903",
        "tgn:1000004",
        "tgn:7029392"
    ],
    "tgn:id":1120903,
    "tgn:name":"H\u0332adera",
    "tgn:placetype":[
        "aat:300008707"
    ]
},
  "bbox": [],
  "geometry": {"coordinates":[34.9167,32.4167],"type":"Point"}
}