<<<<<<< HEAD
{
  "id": 7368307,
  "type": "Feature",
  "properties": {
    "tgn:hierarchy":[
        "tgn:7368307",
        "tgn:1000001",
        "tgn:7005601",
        "tgn:7005560",
        "tgn:7029392"
    ],
    "tgn:id":7368307,
    "tgn:name":"Grullo, Tanque de",
    "tgn:placetype":[
        "aat:300008688"
    ]
},
  "bbox": [],
  "geometry": {"coordinates":[-102.4,24.033333],"type":"Point"}
}
=======
{"geometry":{"type":"Point","coordinates":[-102.400000,24.033333]},"type":"Feature","properties":{"hierarchy":["tgn:7368307","tgn:1000001","tgn:7005601","tgn:7005560","tgn:7029392"],"placetype":["aat:300008688"],"id":7368307,"name:xx":"Grullo, Tanque de"}}
>>>>>>> 03f74aca74312dbeaf24d7e61306dd6a786dc3d0
