{
  "id": 2466092,
  "type": "Feature",
  "properties": {
    "tgn:hierarchy":[
        "tgn:2466092",
        "tgn:1000001",
        "tgn:7012149",
        "tgn:2001718",
        "tgn:7007708",
        "tgn:7029392"
    ],
    "tgn:id":2466092,
    "tgn:name":"Lone Willow Creek",
    "tgn:placetype":[
        "aat:300008706"
    ]
},
  "bbox": [],
  "geometry": {"coordinates":[-117.2833,43.75],"type":"Point"}
}