{
  "id": 7233065,
  "type": "Feature",
  "properties": {
    "tgn:hierarchy":[
        "tgn:7233065",
        "tgn:4003773",
        "tgn:7001395",
        "tgn:1000003",
        "tgn:1000074",
        "tgn:7029392"
    ],
    "tgn:id":7233065,
    "tgn:name":"Korfi\u00e1des",
    "tgn:placetype":[
        "aat:300008347"
    ]
},
  "bbox": [],
  "geometry": {"coordinates":[21.642778,39.144167],"type":"Point"}
}