{
  "id": 2095004,
  "type": "Feature",
  "properties": {
    "tgn:hierarchy":[
        "tgn:2095004",
        "tgn:1002996",
        "tgn:1000001",
        "tgn:7012149",
        "tgn:7007711",
        "tgn:7029392"
    ],
    "tgn:id":2095004,
    "tgn:name":"Misquamicut",
    "tgn:placetype":[
        "aat:300008347"
    ]
},
  "bbox": [],
  "geometry": {"coordinates":[-71.8167,41.3167],"type":"Point"}
}