<<<<<<< HEAD
{
  "id": 7363860,
  "type": "Feature",
  "properties": {
    "tgn:hierarchy":[
        "tgn:7363860",
        "tgn:1000001",
        "tgn:7005601",
        "tgn:7005560",
        "tgn:7029392"
    ],
    "tgn:id":7363860,
    "tgn:name":"El Baj\u00edo de Claras",
    "tgn:placetype":[
        "aat:300008347"
    ]
},
  "bbox": [],
  "geometry": {"coordinates":[-102.983333,22.8],"type":"Point"}
}
=======
{"geometry":{"type":"Point","coordinates":[-102.983333,22.800000]},"type":"Feature","properties":{"hierarchy":["tgn:7363860","tgn:1000001","tgn:7005601","tgn:7005560","tgn:7029392"],"placetype":["aat:300008347"],"id":7363860,"name:xx":"El Baj\u00edo de Claras"}}
>>>>>>> 03f74aca74312dbeaf24d7e61306dd6a786dc3d0
