<<<<<<< HEAD
{
  "id": 7364752,
  "type": "Feature",
  "properties": {
    "tgn:hierarchy":[
        "tgn:7364752",
        "tgn:7005578",
        "tgn:1000001",
        "tgn:7005560",
        "tgn:7029392"
    ],
    "tgn:id":7364752,
    "tgn:name":"Flor de Mayo",
    "tgn:placetype":[
        "aat:300008347"
    ]
},
  "bbox": [],
  "geometry": {"coordinates":[-91.1,18.383333],"type":"Point"}
}
=======
{"geometry":{"type":"Point","coordinates":[-91.100000,18.383333]},"type":"Feature","properties":{"hierarchy":["tgn:7364752","tgn:7005578","tgn:1000001","tgn:7005560","tgn:7029392"],"placetype":["aat:300008347"],"id":7364752,"name:xx":"Flor de Mayo"}}
>>>>>>> 03f74aca74312dbeaf24d7e61306dd6a786dc3d0
