{
  "id": 7144811,
  "type": "Feature",
  "properties": {
    "tgn:hierarchy":[
        "tgn:7144811",
        "tgn:1000003",
        "tgn:7003677",
        "tgn:7000084",
        "tgn:7029392"
    ],
    "tgn:id":7144811,
    "tgn:name":"Wasserstra\u00dfe",
    "tgn:placetype":[
        "aat:300008347"
    ]
},
  "bbox": [],
  "geometry": {"coordinates":[9.116667,52.483333],"type":"Point"}
}