{
  "id": 2271204,
  "type": "Feature",
  "properties": {
    "tgn:hierarchy":[
        "tgn:2271204",
        "tgn:1000001",
        "tgn:2001014",
        "tgn:7012149",
        "tgn:7007521",
        "tgn:7029392"
    ],
    "tgn:id":2271204,
    "tgn:name":"Cuffs Lake",
    "tgn:placetype":[
        "aat:300008680"
    ]
},
  "bbox": [],
  "geometry": {"coordinates":[-89.7333,47.9333],"type":"Point"}
}