{
  "id": 2097619,
  "type": "Feature",
  "properties": {
    "tgn:hierarchy":[
        "tgn:2097619",
        "tgn:1000001",
        "tgn:2001812",
        "tgn:7012149",
        "tgn:7007713",
        "tgn:7029392"
    ],
    "tgn:id":2097619,
    "tgn:name":"Vivian",
    "tgn:placetype":[
        "aat:300008347"
    ]
},
  "bbox": [],
  "geometry": {"coordinates":[-100.2833,43.9167],"type":"Point"}
}