{
  "id": 7503844,
  "type": "Feature",
  "properties": {
    "tgn:hierarchy":[
        "tgn:7503844",
        "tgn:7001004",
        "tgn:1000004",
        "tgn:1000141",
        "tgn:7029392"
    ],
    "tgn:id":7503844,
    "tgn:name":"Baishulin Qiao",
    "tgn:placetype":[
        "aat:300007836"
    ]
},
  "bbox": [],
  "geometry": {"coordinates":[120.496667,22.964444],"type":"Point"}
}