{
  "id": 2390368,
  "type": "Feature",
  "properties": {
    "tgn:hierarchy":[
        "tgn:2390368",
        "tgn:1000001",
        "tgn:7012149",
        "tgn:2001138",
        "tgn:7007522",
        "tgn:7029392"
    ],
    "tgn:id":2390368,
    "tgn:name":"Highland Estates",
    "tgn:placetype":[
        "aat:300008347"
    ]
},
  "bbox": [],
  "geometry": {"coordinates":[-88.85,33.45],"type":"Point"}
}