{
  "id": 7365470,
  "type": "Feature",
  "properties": {
    "tgn:hierarchy":[
        "tgn:7365470",
        "tgn:1000001",
        "tgn:1001893",
        "tgn:7005560",
        "tgn:7029392"
    ],
    "tgn:id":7365470,
    "tgn:name":"Estaci\u00f3n Fresno",
    "tgn:placetype":[
        "aat:300007783"
    ]
},
  "bbox": [],
  "geometry": {"coordinates":[-99.425833,19.291389],"type":"Point"}
}