{
  "id": 1019747,
  "type": "Feature",
  "properties": {
    "tgn:hierarchy":[
        "tgn:1019747",
        "tgn:1001160",
        "tgn:7006477",
        "tgn:1000002",
        "tgn:7029392"
    ],
    "tgn:id":1019747,
    "tgn:name":"Mariano Acosta",
    "tgn:placetype":[
        "aat:300008347"
    ]
},
  "bbox": [],
  "geometry": {"coordinates":[-58.7833,-34.7167],"type":"Point"}
}