{
  "id": 2556411,
  "type": "Feature",
  "properties": {
    "tgn:hierarchy":[
        "tgn:2556411",
        "tgn:1000001",
        "tgn:7012149",
        "tgn:1002599",
        "tgn:7007708",
        "tgn:7029392"
    ],
    "tgn:id":2556411,
    "tgn:name":"Olalla Creek",
    "tgn:placetype":[
        "aat:300008706"
    ]
},
  "bbox": [],
  "geometry": {"coordinates":[-123.8833,44.6667],"type":"Point"}
}