{
  "id": 1072199,
  "type": "Feature",
  "properties": {
    "tgn:hierarchy":[
        "tgn:1072199",
        "tgn:1000004",
        "tgn:7002087",
        "tgn:1000111",
        "tgn:7029392"
    ],
    "tgn:id":1072199,
    "tgn:name":"Taxusi",
    "tgn:placetype":[
        "aat:300008347"
    ]
},
  "bbox": [],
  "geometry": {"coordinates":[98.1667,32.9667],"type":"Point"}
}