{
  "id": 1073673,
  "type": "Feature",
  "properties": {
    "tgn:hierarchy":[
        "tgn:1073673",
        "tgn:1000004",
        "tgn:7024355",
        "tgn:1000111",
        "tgn:7029392"
    ],
    "tgn:id":1073673,
    "tgn:name":"Zhongduo",
    "tgn:placetype":[
        "aat:300008347"
    ]
},
  "bbox": [],
  "geometry": {"coordinates":[108.75,28.8667],"type":"Point"}
}