<<<<<<< HEAD
{
  "id": 2152028,
  "type": "Feature",
  "properties": {
    "tgn:hierarchy":[
        "tgn:2152028",
        "tgn:1000001",
        "tgn:7012149",
        "tgn:7007157",
        "tgn:7014516",
        "tgn:7029392"
    ],
    "tgn:id":2152028,
    "tgn:name":"Baumert Springs",
    "tgn:placetype":[
        "aat:300008697"
    ]
},
  "bbox": [],
  "geometry": {"coordinates":[-122.95,38.4167],"type":"Point"}
}
=======
{"geometry":{"type":"Point","coordinates":[-122.950000,38.416700]},"type":"Feature","properties":{"hierarchy":["tgn:2152028","tgn:1000001","tgn:7012149","tgn:7007157","tgn:7014516","tgn:7029392"],"placetype":["aat:300008697"],"id":2152028,"name:xx":"Baumert Springs"}}
>>>>>>> 03f74aca74312dbeaf24d7e61306dd6a786dc3d0
