{
  "id": 7077397,
  "type": "Feature",
  "properties": {
    "tgn:hierarchy":[
        "tgn:7077397",
        "tgn:1000003",
        "tgn:7003685",
        "tgn:7000084",
        "tgn:7029392"
    ],
    "tgn:id":7077397,
    "tgn:name":"Ziegen-Berg",
    "tgn:placetype":[
        "aat:300008777"
    ]
},
  "bbox": [],
  "geometry": {"coordinates":[13.483333,50.733333],"type":"Point"}
}