{
  "id": 2214258,
  "type": "Feature",
  "properties": {
    "tgn:hierarchy":[
        "tgn:2214258",
        "tgn:1000001",
        "tgn:7006451",
        "tgn:7012149",
        "tgn:2000101",
        "tgn:7029392"
    ],
    "tgn:id":2214258,
    "tgn:name":"Cairo Hill",
    "tgn:placetype":[
        "aat:300008798"
    ]
},
  "bbox": [],
  "geometry": {"coordinates":[-110.9667,33.1667],"type":"Point"}
}