{
  "id": 2421064,
  "type": "Feature",
  "properties": {
    "tgn:hierarchy":[
        "tgn:2421064",
        "tgn:1000001",
        "tgn:7012149",
        "tgn:2000558",
        "tgn:7007252",
        "tgn:7029392"
    ],
    "tgn:id":2421064,
    "tgn:name":"Jericho Creek",
    "tgn:placetype":[
        "aat:300008706"
    ]
},
  "bbox": [],
  "geometry": {"coordinates":[-87.45,40.0667],"type":"Point"}
}