{
  "id": 7457492,
  "type": "Feature",
  "properties": {
    "tgn:hierarchy":[
        "tgn:7457492",
        "tgn:7002444",
        "tgn:1000003",
        "tgn:7008082",
        "tgn:7008591",
        "tgn:7029392"
    ],
    "tgn:id":7457492,
    "tgn:name:en":"Maoile Lunndaidh",
    "tgn:placetype":[
        "aat:300008795"
    ]
},
  "bbox": [],
  "geometry": {"coordinates":[-5.116667,57.466667],"type":"Point"}
}