{
  "id": 7540049,
  "type": "Feature",
  "properties": {
    "tgn:hierarchy":[
        "tgn:7540049",
        "tgn:7001242",
        "tgn:7016833",
        "tgn:7000124",
        "tgn:7029392"
    ],
    "tgn:id":7540049,
    "tgn:name:en":"Nag' Ghaz\u00e2li",
    "tgn:placetype":[
        "aat:300008347"
    ]
},
  "bbox": [],
  "geometry": {"coordinates":[31.516667,26.65],"type":"Point"}
}