{
  "id": 2438047,
  "type": "Feature",
  "properties": {
    "tgn:hierarchy":[
        "tgn:2438047",
        "tgn:1000001",
        "tgn:7012149",
        "tgn:1002613",
        "tgn:7007710",
        "tgn:7029392"
    ],
    "tgn:id":2438047,
    "tgn:name":"King Run",
    "tgn:placetype":[
        "aat:300008699"
    ]
},
  "bbox": [],
  "geometry": {"coordinates":[-76.8333,41.4333],"type":"Point"}
}