{
  "id": 2400241,
  "type": "Feature",
  "properties": {
    "tgn:hierarchy":[
        "tgn:2400241",
        "tgn:1000001",
        "tgn:7012149",
        "tgn:2001288",
        "tgn:7007524",
        "tgn:7029392"
    ],
    "tgn:id":2400241,
    "tgn:name":"Horse Creek Bull Quartz Mine",
    "tgn:placetype":[
        "aat:300000390"
    ]
},
  "bbox": [],
  "geometry": {"coordinates":[-112.1167,45.4167],"type":"Point"}
}