<<<<<<< HEAD
{
  "id": 2400241,
  "type": "Feature",
  "properties": {
    "tgn:hierarchy":[
        "tgn:2400241",
        "tgn:1000001",
        "tgn:7012149",
        "tgn:2001288",
        "tgn:7007524",
        "tgn:7029392"
    ],
    "tgn:id":2400241,
    "tgn:name":"Horse Creek Bull Quartz Mine",
    "tgn:placetype":[
        "aat:300000390"
    ]
},
  "bbox": [],
  "geometry": {"coordinates":[-112.1167,45.4167],"type":"Point"}
}
=======
{"geometry":{"type":"Point","coordinates":[-112.116700,45.416700]},"type":"Feature","properties":{"hierarchy":["tgn:2400241","tgn:1000001","tgn:7012149","tgn:2001288","tgn:7007524","tgn:7029392"],"placetype":["aat:300000390"],"id":2400241,"name:xx":"Horse Creek Bull Quartz Mine"}}
>>>>>>> 03f74aca74312dbeaf24d7e61306dd6a786dc3d0
