<<<<<<< HEAD
{
  "id": 2253103,
  "type": "Feature",
  "properties": {
    "tgn:hierarchy":[
        "tgn:2253103",
        "tgn:7006450",
        "tgn:1000001",
        "tgn:7030547",
        "tgn:7012149",
        "tgn:7029392"
    ],
    "tgn:id":2253103,
    "tgn:name":"Contact Creek",
    "tgn:placetype":[
        "aat:300008706"
    ]
},
  "bbox": [],
  "geometry": {"coordinates":[-150.2833,63.3667],"type":"Point"}
}
=======
{"geometry":{"type":"Point","coordinates":[-150.283300,63.366700]},"type":"Feature","properties":{"hierarchy":["tgn:2253103","tgn:7006450","tgn:1000001","tgn:7030547","tgn:7012149","tgn:7029392"],"placetype":["aat:300008706"],"id":2253103,"name:xx":"Contact Creek"}}
>>>>>>> 03f74aca74312dbeaf24d7e61306dd6a786dc3d0
