{
  "id": 7484023,
  "type": "Feature",
  "properties": {
    "tgn:hierarchy":[
        "tgn:7484023",
        "tgn:1000004",
        "tgn:7001009",
        "tgn:1000141",
        "tgn:7029392"
    ],
    "tgn:id":7484023,
    "tgn:name":"Haigang Dalou",
    "tgn:placetype":[
        "aat:300004792"
    ]
},
  "bbox": [],
  "geometry": {"coordinates":[120.523611,24.256389],"type":"Point"}
}