{
  "id": 7500352,
  "type": "Feature",
  "properties": {
    "tgn:hierarchy":[
        "tgn:7500352",
        "tgn:7001004",
        "tgn:1000004",
        "tgn:1000141",
        "tgn:7029392"
    ],
    "tgn:id":7500352,
    "tgn:name":"Daoming Qiao",
    "tgn:placetype":[
        "aat:300007836"
    ]
},
  "bbox": [],
  "geometry": {"coordinates":[120.492778,22.953333],"type":"Point"}
}