{
  "id": 2181330,
  "type": "Feature",
  "properties": {
    "tgn:hierarchy":[
        "tgn:2181330",
        "tgn:1000001",
        "tgn:7012149",
        "tgn:2001706",
        "tgn:7007708",
        "tgn:7029392"
    ],
    "tgn:id":2181330,
    "tgn:name":"Blue Creek",
    "tgn:placetype":[
        "aat:300008706"
    ]
},
  "bbox": [],
  "geometry": {"coordinates":[-123.25,42.7667],"type":"Point"}
}