{
  "id": 7401759,
  "type": "Feature",
  "properties": {
    "tgn:hierarchy":[
        "tgn:7401759",
        "tgn:1000001",
        "tgn:7005599",
        "tgn:7005560",
        "tgn:7029392"
    ],
    "tgn:id":7401759,
    "tgn:name":"Loma de Enmedio",
    "tgn:placetype":[
        "aat:300008347"
    ]
},
  "bbox": [],
  "geometry": {"coordinates":[-96.698611,18.908333],"type":"Point"}
}