{
  "id": 7592286,
  "type": "Feature",
  "properties": {
    "tgn:hierarchy":[
        "tgn:7592286",
        "tgn:1000004",
        "tgn:7000198",
        "tgn:7031786",
        "tgn:7029392"
    ],
    "tgn:id":7592286,
    "tgn:name:en":"Dh\u0101nga Rao",
    "tgn:placetype":[
        "aat:300008699"
    ]
},
  "bbox": [],
  "geometry": {"coordinates":[77.757505,30.405786],"type":"Point"}
}