<<<<<<< HEAD
{
  "id": 7170896,
  "type": "Feature",
  "properties": {
    "tgn:hierarchy":[
        "tgn:7170896",
        "tgn:1000003",
        "tgn:7003685",
        "tgn:7000084",
        "tgn:7029392"
    ],
    "tgn:id":7170896,
    "tgn:name":"Vorwerk Himmelreich",
    "tgn:placetype":[
        "aat:300000206"
    ]
},
  "bbox": [],
  "geometry": {"coordinates":[13.95,50.933333],"type":"Point"}
}
=======
{"geometry":{"type":"Point","coordinates":[13.950000,50.933333]},"type":"Feature","properties":{"hierarchy":["tgn:7170896","tgn:1000003","tgn:7003685","tgn:7000084","tgn:7029392"],"placetype":["aat:300000206"],"id":7170896,"name:xx":"Vorwerk Himmelreich"}}
>>>>>>> 03f74aca74312dbeaf24d7e61306dd6a786dc3d0
