{
  "id": 2119762,
  "type": "Feature",
  "properties": {
    "tgn:hierarchy":[
        "tgn:2119762",
        "tgn:1000001",
        "tgn:7012149",
        "tgn:2002279",
        "tgn:7013961",
        "tgn:7029392"
    ],
    "tgn:id":2119762,
    "tgn:name":"Ridgeley",
    "tgn:placetype":[
        "aat:300008347"
    ]
},
  "bbox": [],
  "geometry": {"coordinates":[-78.7667,39.6333],"type":"Point"}
}