{
  "id": 7506959,
  "type": "Feature",
  "properties": {
    "tgn:hierarchy":[
        "tgn:7506959",
        "tgn:7016670",
        "tgn:1008380",
        "tgn:1000226",
        "tgn:1000006",
        "tgn:7029392"
    ],
    "tgn:id":7506959,
    "tgn:name:en":"Rangi-iti",
    "tgn:placetype":[
        "aat:300008777"
    ]
},
  "bbox": [],
  "geometry": {"coordinates":[176.383333,-39.883333],"type":"Point"}
}