{
  "id": 7148089,
  "type": "Feature",
  "properties": {
    "tgn:hierarchy":[
        "tgn:7148089",
        "tgn:7000096",
        "tgn:1000003",
        "tgn:7000084",
        "tgn:7029392"
    ],
    "tgn:id":7148089,
    "tgn:name":"Lange-Berge",
    "tgn:placetype":[
        "aat:300266640"
    ]
},
  "bbox": [],
  "geometry": {"coordinates":[12.733333,52.266667],"type":"Point"}
}