{
  "id": 2191350,
  "type": "Feature",
  "properties": {
    "tgn:hierarchy":[
        "tgn:2191350",
        "tgn:1000001",
        "tgn:2001418",
        "tgn:7012149",
        "tgn:7007526",
        "tgn:7029392"
    ],
    "tgn:id":2191350,
    "tgn:name":"Bracket Peak",
    "tgn:placetype":[
        "aat:300008798"
    ]
},
  "bbox": [],
  "geometry": {"coordinates":[-116.6833,38.2833],"type":"Point"}
}