{
  "id": 7319202,
  "type": "Feature",
  "properties": {
    "tgn:hierarchy":[
        "tgn:7319202",
        "tgn:1001623",
        "tgn:1000049",
        "tgn:1000002",
        "tgn:7029392"
    ],
    "tgn:id":7319202,
    "tgn:name":"Angosta, Punta",
    "tgn:placetype":[
        "aat:300386846"
    ]
},
  "bbox": [],
  "geometry": {"coordinates":[-73.216667,-45.283333],"type":"Point"}
}