{
  "id": 7081437,
  "type": "Feature",
  "properties": {
    "tgn:hierarchy":[
        "tgn:7081437",
        "tgn:1000003",
        "tgn:7003676",
        "tgn:7000084",
        "tgn:7029392"
    ],
    "tgn:id":7081437,
    "tgn:name":"W\u00f6lpinghausen",
    "tgn:placetype":[
        "aat:300008347"
    ]
},
  "bbox": [],
  "geometry": {"coordinates":[9.233333,52.416667],"type":"Point"}
}