{
  "id": 2301886,
  "type": "Feature",
  "properties": {
    "tgn:hierarchy":[
        "tgn:2301886",
        "tgn:1000001",
        "tgn:7012149",
        "tgn:2001552",
        "tgn:7007709",
        "tgn:7029392"
    ],
    "tgn:id":2301886,
    "tgn:name":"Durhams Lake",
    "tgn:placetype":[
        "aat:300006191"
    ]
},
  "bbox": [],
  "geometry": {"coordinates":[-78.05,35.2667],"type":"Point"}
}