{
  "id": 7327242,
  "type": "Feature",
  "properties": {
    "tgn:hierarchy":[
        "tgn:7327242",
        "tgn:7002759",
        "tgn:7008909",
        "tgn:1000003",
        "tgn:1000095",
        "tgn:7029392"
    ],
    "tgn:id":7327242,
    "tgn:name":"Panzano",
    "tgn:placetype":[
        "aat:300008347"
    ]
},
  "bbox": [],
  "geometry": {"coordinates":[-0.166973,42.209471],"type":"Point"}
}