{
  "id": 2546951,
  "type": "Feature",
  "properties": {
    "tgn:hierarchy":[
        "tgn:2546951",
        "tgn:1000001",
        "tgn:2002367",
        "tgn:7012149",
        "tgn:7007923",
        "tgn:7029392"
    ],
    "tgn:id":2546951,
    "tgn:name":"North Fork Olmstead Creek",
    "tgn:placetype":[
        "aat:300008706"
    ]
},
  "bbox": [],
  "geometry": {"coordinates":[-105.5667,44.9833],"type":"Point"}
}