{
  "id": 2394039,
  "type": "Feature",
  "properties": {
    "tgn:hierarchy":[
        "tgn:2394039",
        "tgn:1000001",
        "tgn:2001485",
        "tgn:7012149",
        "tgn:7007709",
        "tgn:7029392"
    ],
    "tgn:id":2394039,
    "tgn:name":"Hog Swamp",
    "tgn:placetype":[
        "aat:300008905"
    ]
},
  "bbox": [],
  "geometry": {"coordinates":[-78.5667,34.1167],"type":"Point"}
}