{
  "id": 2198498,
  "type": "Feature",
  "properties": {
    "tgn:hierarchy":[
        "tgn:2198498",
        "tgn:1000001",
        "tgn:2000299",
        "tgn:7012149",
        "tgn:7007248",
        "tgn:7029392"
    ],
    "tgn:id":2198498,
    "tgn:name":"Browns Lake",
    "tgn:placetype":[
        "aat:300006191"
    ]
},
  "bbox": [],
  "geometry": {"coordinates":[-84.85,34.0833],"type":"Point"}
}