{
  "id": 2304122,
  "type": "Feature",
  "properties": {
    "tgn:hierarchy":[
        "tgn:2304122",
        "tgn:1000001",
        "tgn:7012149",
        "tgn:2001503",
        "tgn:7007709",
        "tgn:7029392"
    ],
    "tgn:id":2304122,
    "tgn:name":"Eaglenest Mountain",
    "tgn:placetype":[
        "aat:300008798"
    ]
},
  "bbox": [],
  "geometry": {"coordinates":[-83.0333,35.4833],"type":"Point"}
}