{
  "id": 7062811,
  "type": "Feature",
  "properties": {
    "tgn:hierarchy":[
        "tgn:7062811",
        "tgn:7003669",
        "tgn:1000003",
        "tgn:7000084",
        "tgn:7029392"
    ],
    "tgn:id":7062811,
    "tgn:name":"Axtheid-Berg",
    "tgn:placetype":[
        "aat:300008347"
    ]
},
  "bbox": [],
  "geometry": {"coordinates":[11.816667,49.616667],"type":"Point"}
}