{
  "id": 1114133,
  "type": "Feature",
  "properties": {
    "tgn:hierarchy":[
        "tgn:1114133",
        "tgn:1000003",
        "tgn:7000094",
        "tgn:7000084",
        "tgn:7029392"
    ],
    "tgn:id":1114133,
    "tgn:name":"Gellenstrom",
    "tgn:placetype":[
        "aat:300387028",
        "aat:300008713"
    ]
},
  "bbox": [],
  "geometry": {"coordinates":[13.05,54.466667],"type":"Point"}
}