{
  "id": 7114545,
  "type": "Feature",
  "properties": {
    "tgn:hierarchy":[
        "tgn:7114545",
        "tgn:1000003",
        "tgn:7003676",
        "tgn:7000084",
        "tgn:7029392"
    ],
    "tgn:id":7114545,
    "tgn:name":"Robben Plate",
    "tgn:placetype":[
        "aat:300386885"
    ]
},
  "bbox": [],
  "geometry": {"coordinates":[7.666667,53.783333],"type":"Point"}
}