{
  "id": 2532848,
  "type": "Feature",
  "properties": {
    "tgn:hierarchy":[
        "tgn:2532848",
        "tgn:1000001",
        "tgn:7012149",
        "tgn:2001828",
        "tgn:7007713",
        "tgn:7029392"
    ],
    "tgn:id":2532848,
    "tgn:name":"Murray Butte",
    "tgn:placetype":[
        "aat:300008798"
    ]
},
  "bbox": [],
  "geometry": {"coordinates":[-100.7333,44.2667],"type":"Point"}
}