{
  "id": 7078208,
  "type": "Feature",
  "properties": {
    "tgn:hierarchy":[
        "tgn:7078208",
        "tgn:1000003",
        "tgn:7003676",
        "tgn:7000084",
        "tgn:7029392"
    ],
    "tgn:id":7078208,
    "tgn:name":"Memmert Wattfahrwasser",
    "tgn:placetype":[
        "aat:300008713"
    ]
},
  "bbox": [],
  "geometry": {"coordinates":[7.016667,53.641667],"type":"Point"}
}