{
  "id": 7075673,
  "type": "Feature",
  "properties": {
    "tgn:hierarchy":[
        "tgn:7075673",
        "tgn:7003692",
        "tgn:1000003",
        "tgn:7000084",
        "tgn:7029392"
    ],
    "tgn:id":7075673,
    "tgn:name":"Zizingen",
    "tgn:placetype":[
        "aat:300008347"
    ]
},
  "bbox": [],
  "geometry": {"coordinates":[7.616667,47.783333],"type":"Point"}
}