{
  "id": 2719624,
  "type": "Feature",
  "properties": {
    "tgn:hierarchy":[
        "tgn:2719624",
        "tgn:1000001",
        "tgn:7012149",
        "tgn:1002502",
        "tgn:7007520",
        "tgn:7029392"
    ],
    "tgn:id":2719624,
    "tgn:name":"Three Lakes",
    "tgn:placetype":[
        "aat:300008680"
    ]
},
  "bbox": [],
  "geometry": {"coordinates":[-84.2833,42.7667],"type":"Point"}
}