{
  "id": 2228297,
  "type": "Feature",
  "properties": {
    "tgn:hierarchy":[
        "tgn:2228297",
        "tgn:1000001",
        "tgn:7012149",
        "tgn:2000364",
        "tgn:7007248",
        "tgn:7029392"
    ],
    "tgn:id":2228297,
    "tgn:name":"Cedar Creek",
    "tgn:placetype":[
        "aat:300008706"
    ]
},
  "bbox": [],
  "geometry": {"coordinates":[-82.9333,34.3333],"type":"Point"}
}