{
  "id": 7321594,
  "type": "Feature",
  "properties": {
    "tgn:hierarchy":[
        "tgn:7321594",
        "tgn:7002464",
        "tgn:1000049",
        "tgn:1000002",
        "tgn:7029392"
    ],
    "tgn:id":7321594,
    "tgn:name":"Pumire Azufreras",
    "tgn:placetype":[
        "aat:300008347"
    ]
},
  "bbox": [],
  "geometry": {"coordinates":[-69.05,-19.05],"type":"Point"}
}