{
  "id": 7171951,
  "type": "Feature",
  "properties": {
    "tgn:hierarchy":[
        "tgn:7171951",
        "tgn:7003692",
        "tgn:1000003",
        "tgn:7000084",
        "tgn:7029392"
    ],
    "tgn:id":7171951,
    "tgn:name":"Hirnberg",
    "tgn:placetype":[
        "aat:300008795"
    ]
},
  "bbox": [],
  "geometry": {"coordinates":[9.333333,48.45],"type":"Point"}
}