<<<<<<< HEAD
{
  "id": 2153614,
  "type": "Feature",
  "properties": {
    "tgn:hierarchy":[
        "tgn:2153614",
        "tgn:1000001",
        "tgn:2000575",
        "tgn:7012149",
        "tgn:7007253",
        "tgn:7029392"
    ],
    "tgn:id":2153614,
    "tgn:name":"Bear Branch",
    "tgn:placetype":[
        "aat:300008699"
    ]
},
  "bbox": [],
  "geometry": {"coordinates":[-94.95,41.3167],"type":"Point"}
}
=======
{"geometry":{"type":"Point","coordinates":[-94.950000,41.316700]},"type":"Feature","properties":{"hierarchy":["tgn:2153614","tgn:1000001","tgn:2000575","tgn:7012149","tgn:7007253","tgn:7029392"],"placetype":["aat:300008699"],"id":2153614,"name:xx":"Bear Branch"}}
>>>>>>> 03f74aca74312dbeaf24d7e61306dd6a786dc3d0
