{
  "id": 2515478,
  "type": "Feature",
  "properties": {
    "tgn:hierarchy":[
        "tgn:2515478",
        "tgn:1000001",
        "tgn:7012149",
        "tgn:7007523",
        "tgn:7029392"
    ],
    "tgn:id":2515478,
    "tgn:name":"Mills Creek",
    "tgn:placetype":[
        "aat:300008706"
    ]
},
  "bbox": [],
  "geometry": {"coordinates":[-91.35,39.65],"type":"Point"}
}