{
  "id": 7303801,
  "type": "Feature",
  "properties": {
    "tgn:hierarchy":[
        "tgn:7303801",
        "tgn:7002822",
        "tgn:1001647",
        "tgn:1000003",
        "tgn:1000095",
        "tgn:7029392"
    ],
    "tgn:id":7303801,
    "tgn:name":"Osa, Fuente de la",
    "tgn:placetype":[
        "aat:300008697"
    ]
},
  "bbox": [],
  "geometry": {"coordinates":[-2.35,40.766667],"type":"Point"}
}