{
  "id": 7552444,
  "type": "Feature",
  "properties": {
    "tgn:hierarchy":[
        "tgn:7552444",
        "tgn:1000004",
        "tgn:7000198",
        "tgn:7016722",
        "tgn:7029392"
    ],
    "tgn:id":7552444,
    "tgn:name:en":"M\u0101nir\u0101m",
    "tgn:placetype":[
        "aat:300007783"
    ]
},
  "bbox": [],
  "geometry": {"coordinates":[83.340579,26.840817],"type":"Point"}
}