{
  "id": 7550294,
  "type": "Feature",
  "properties": {
    "tgn:hierarchy":[
        "tgn:7550294",
        "tgn:1000004",
        "tgn:7000198",
        "tgn:7016722",
        "tgn:7029392"
    ],
    "tgn:id":7550294,
    "tgn:name:en":"Bishn\u0101thganj",
    "tgn:placetype":[
        "aat:300007783"
    ]
},
  "bbox": [],
  "geometry": {"coordinates":[81.9349,25.801426],"type":"Point"}
}