{
  "id": 7266893,
  "type": "Feature",
  "properties": {
    "tgn:hierarchy":[
        "tgn:7266893",
        "tgn:1000003",
        "tgn:7006951",
        "tgn:7016845",
        "tgn:7029392"
    ],
    "tgn:id":7266893,
    "tgn:name:nl":"Jan van Riebeeckhaven",
    "tgn:placetype":[
        "aat:300120801"
    ]
},
  "bbox": [],
  "geometry": {"coordinates":[4.85,52.416667],"type":"Point"}
}