{
  "id": 2463976,
  "type": "Feature",
  "properties": {
    "tgn:hierarchy":[
        "tgn:2463976",
        "tgn:1000001",
        "tgn:7012149",
        "tgn:2000909",
        "tgn:7007256",
        "tgn:7029392"
    ],
    "tgn:id":2463976,
    "tgn:name":"Loco",
    "tgn:placetype":[
        "aat:300008347"
    ]
},
  "bbox": [],
  "geometry": {"coordinates":[-92.15,32.9333],"type":"Point"}
}