{
  "id": 2289380,
  "type": "Feature",
  "properties": {
    "tgn:hierarchy":[
        "tgn:2289380",
        "tgn:1000001",
        "tgn:7012149",
        "tgn:2001509",
        "tgn:7007709",
        "tgn:7029392"
    ],
    "tgn:id":2289380,
    "tgn:name":"Dixie Crossroads",
    "tgn:placetype":[
        "aat:300008347"
    ]
},
  "bbox": [],
  "geometry": {"coordinates":[-78.2167,35.6833],"type":"Point"}
}