{
  "id": 2000753,
  "type": "Feature",
  "properties": {
    "tgn:hierarchy":[
        "tgn:2000753",
        "tgn:1000001",
        "tgn:7012149",
        "tgn:7007254",
        "tgn:7029392"
    ],
    "tgn:id":2000753,
    "tgn:name":"Stanton",
    "tgn:placetype":[
        "aat:300387145",
        "aat:300000771"
    ]
},
  "bbox": [],
  "geometry": {"coordinates":[-101.7833,37.5667],"type":"Point"}
}