{
  "id": 7546527,
  "type": "Feature",
  "properties": {
    "tgn:hierarchy":[
        "tgn:7546527",
        "tgn:1000004",
        "tgn:7000198",
        "tgn:7016788",
        "tgn:7029392"
    ],
    "tgn:id":7546527,
    "tgn:name:en":"Bichh\u012bw\u0101ra",
    "tgn:placetype":[
        "aat:300008347"
    ]
},
  "bbox": [],
  "geometry": {"coordinates":[73.522544,23.786272],"type":"Point"}
}