{
  "id": 2182571,
  "type": "Feature",
  "properties": {
    "tgn:hierarchy":[
        "tgn:2182571",
        "tgn:1000001",
        "tgn:2001014",
        "tgn:7012149",
        "tgn:7007521",
        "tgn:7029392"
    ],
    "tgn:id":2182571,
    "tgn:name":"Blue Snow Lake",
    "tgn:placetype":[
        "aat:300008680"
    ]
},
  "bbox": [],
  "geometry": {"coordinates":[-90.8667,48.05],"type":"Point"}
}