<<<<<<< HEAD
{
  "id": 2333494,
  "type": "Feature",
  "properties": {
    "tgn:hierarchy":[
        "tgn:2333494",
        "tgn:2002142",
        "tgn:1000001",
        "tgn:7012149",
        "tgn:7007919",
        "tgn:7029392"
    ],
    "tgn:id":2333494,
    "tgn:name":"Folly Mills",
    "tgn:placetype":[
        "aat:300008347"
    ]
},
  "bbox": [],
  "geometry": {"coordinates":[-79.0833,38.0833],"type":"Point"}
}
=======
{"geometry":{"type":"Point","coordinates":[-79.083300,38.083300]},"type":"Feature","properties":{"hierarchy":["tgn:2333494","tgn:2002142","tgn:1000001","tgn:7012149","tgn:7007919","tgn:7029392"],"placetype":["aat:300008347"],"id":2333494,"name:xx":"Folly Mills"}}
>>>>>>> 03f74aca74312dbeaf24d7e61306dd6a786dc3d0
