<<<<<<< HEAD
{
  "id": 2400670,
  "type": "Feature",
  "properties": {
    "tgn:hierarchy":[
        "tgn:2400670",
        "tgn:1000001",
        "tgn:7012149",
        "tgn:2002249",
        "tgn:7007920",
        "tgn:7029392"
    ],
    "tgn:id":2400670,
    "tgn:name":"Horse Mountain",
    "tgn:placetype":[
        "aat:300008798"
    ]
},
  "bbox": [],
  "geometry": {"coordinates":[-117.0667,47.8833],"type":"Point"}
}
=======
{"geometry":{"type":"Point","coordinates":[-117.066700,47.883300]},"type":"Feature","properties":{"hierarchy":["tgn:2400670","tgn:1000001","tgn:7012149","tgn:2002249","tgn:7007920","tgn:7029392"],"placetype":["aat:300008798"],"id":2400670,"name:xx":"Horse Mountain"}}
>>>>>>> 03f74aca74312dbeaf24d7e61306dd6a786dc3d0
