{
  "id": 2400670,
  "type": "Feature",
  "properties": {
    "tgn:hierarchy":[
        "tgn:2400670",
        "tgn:1000001",
        "tgn:7012149",
        "tgn:2002249",
        "tgn:7007920",
        "tgn:7029392"
    ],
    "tgn:id":2400670,
    "tgn:name":"Horse Mountain",
    "tgn:placetype":[
        "aat:300008798"
    ]
},
  "bbox": [],
  "geometry": {"coordinates":[-117.0667,47.8833],"type":"Point"}
}