<<<<<<< HEAD
{
  "id": 2250463,
  "type": "Feature",
  "properties": {
    "tgn:hierarchy":[
        "tgn:2250463",
        "tgn:7002659",
        "tgn:1000001",
        "tgn:7012149",
        "tgn:2000062",
        "tgn:7029392"
    ],
    "tgn:id":2250463,
    "tgn:name":"Colonial Hills",
    "tgn:placetype":[
        "aat:300008347"
    ]
},
  "bbox": [],
  "geometry": {"coordinates":[-87.5,33.2167],"type":"Point"}
}
=======
{"geometry":{"type":"Point","coordinates":[-87.500000,33.216700]},"type":"Feature","properties":{"hierarchy":["tgn:2250463","tgn:7002659","tgn:1000001","tgn:7012149","tgn:2000062","tgn:7029392"],"placetype":["aat:300008347"],"id":2250463,"name:xx":"Colonial Hills"}}
>>>>>>> 03f74aca74312dbeaf24d7e61306dd6a786dc3d0
