{
  "id": 2367755,
  "type": "Feature",
  "properties": {
    "tgn:hierarchy":[
        "tgn:2367755",
        "tgn:1000001",
        "tgn:7012149",
        "tgn:7007712",
        "tgn:7029392"
    ],
    "tgn:id":2367755,
    "tgn:name":"Grove Creek",
    "tgn:placetype":[
        "aat:300008706"
    ]
},
  "bbox": [],
  "geometry": {"coordinates":[-82.4167,34.7333],"type":"Point"}
}