{
  "id": 2385315,
  "type": "Feature",
  "properties": {
    "tgn:hierarchy":[
        "tgn:2385315",
        "tgn:1000001",
        "tgn:7012149",
        "tgn:2000346",
        "tgn:7007248",
        "tgn:7029392"
    ],
    "tgn:id":2385315,
    "tgn:name":"Hemp Top",
    "tgn:placetype":[
        "aat:300008798"
    ]
},
  "bbox": [],
  "geometry": {"coordinates":[-84.5167,34.9667],"type":"Point"}
}