{
  "id": 7300026,
  "type": "Feature",
  "properties": {
    "tgn:hierarchy":[
        "tgn:7300026",
        "tgn:7002836",
        "tgn:7016622",
        "tgn:1000003",
        "tgn:1000095",
        "tgn:7029392"
    ],
    "tgn:id":7300026,
    "tgn:name":"Terremoto, Monta\u00f1a",
    "tgn:placetype":[
        "aat:300008795"
    ]
},
  "bbox": [],
  "geometry": {"coordinates":[-16.333333,28.433333],"type":"Point"}
}