{
  "id": 7570905,
  "type": "Feature",
  "properties": {
    "tgn:hierarchy":[
        "tgn:7570905",
        "tgn:1000004",
        "tgn:1001869",
        "tgn:7000198",
        "tgn:7029392"
    ],
    "tgn:id":7570905,
    "tgn:name:en":"Kaliana",
    "tgn:placetype":[
        "aat:300008347"
    ]
},
  "bbox": [],
  "geometry": {"coordinates":[70.15,22.266667],"type":"Point"}
}