{
  "id": 2415478,
  "type": "Feature",
  "properties": {
    "tgn:hierarchy":[
        "tgn:2415478",
        "tgn:7014201",
        "tgn:1000001",
        "tgn:7012149",
        "tgn:7007239",
        "tgn:7029392"
    ],
    "tgn:id":2415478,
    "tgn:name":"Island, The",
    "tgn:placetype":[
        "aat:300008791"
    ]
},
  "bbox": [],
  "geometry": {"coordinates":[-75.5833,39.45],"type":"Point"}
}