{
  "id": 1098073,
  "type": "Feature",
  "properties": {
    "tgn:hierarchy":[
        "tgn:1098073",
        "tgn:7000490",
        "tgn:1000006",
        "tgn:7001834",
        "tgn:7029392"
    ],
    "tgn:id":1098073,
    "tgn:name":"Rockingham",
    "tgn:placetype":[
        "aat:300008347"
    ]
},
  "bbox": [],
  "geometry": {"coordinates":[115.35,-32.2667],"type":"Point"}
}