{
  "id": 1123596,
  "type": "Feature",
  "properties": {
    "tgn:hierarchy":[
        "tgn:1123596",
        "tgn:7001242",
        "tgn:7017584",
        "tgn:1000193",
        "tgn:7029392"
    ],
    "tgn:id":1123596,
    "tgn:name":"Dwyka",
    "tgn:placetype":[
        "aat:300008707"
    ]
},
  "bbox": [],
  "geometry": {"coordinates":[28.522,-33.267],"type":"Point"}
}