{
  "id": 7574357,
  "type": "Feature",
  "properties": {
    "tgn:hierarchy":[
        "tgn:7574357",
        "tgn:1000004",
        "tgn:1001832",
        "tgn:7000198",
        "tgn:7029392"
    ],
    "tgn:id":7574357,
    "tgn:name:en":"Jaipur",
    "tgn:placetype":[
        "aat:300008347"
    ]
},
  "bbox": [],
  "geometry": {"coordinates":[93.058137,24.903213],"type":"Point"}
}