{
  "id": 2625168,
  "type": "Feature",
  "properties": {
    "tgn:hierarchy":[
        "tgn:2625168",
        "tgn:1000001",
        "tgn:2001410",
        "tgn:7012149",
        "tgn:7007526",
        "tgn:7029392"
    ],
    "tgn:id":2625168,
    "tgn:name":"Rockefeller Mine",
    "tgn:placetype":[
        "aat:300000390"
    ]
},
  "bbox": [],
  "geometry": {"coordinates":[-114.7667,35.5667],"type":"Point"}
}