{
  "id": 7230035,
  "type": "Feature",
  "properties": {
    "tgn:hierarchy":[
        "tgn:7230035",
        "tgn:7002711",
        "tgn:7001338",
        "tgn:1000003",
        "tgn:1000074",
        "tgn:7029392"
    ],
    "tgn:id":7230035,
    "tgn:name":"L\u00e1kka, \u00c1kra",
    "tgn:placetype":[
        "aat:300008850"
    ]
},
  "bbox": [],
  "geometry": {"coordinates":[20.1325,39.240833],"type":"Point"}
}