{
  "id": 2627551,
  "type": "Feature",
  "properties": {
    "tgn:hierarchy":[
        "tgn:2627551",
        "tgn:1000001",
        "tgn:7012149",
        "tgn:2000930",
        "tgn:7007515",
        "tgn:7029392"
    ],
    "tgn:id":2627551,
    "tgn:name":"Rogers Brook",
    "tgn:placetype":[
        "aat:300008699"
    ]
},
  "bbox": [],
  "geometry": {"coordinates":[-69.7833,44.7333],"type":"Point"}
}