{
  "id": 7485931,
  "type": "Feature",
  "properties": {
    "tgn:hierarchy":[
        "tgn:7485931",
        "tgn:7468018",
        "tgn:1000004",
        "tgn:1000141",
        "tgn:7029392"
    ],
    "tgn:id":7485931,
    "tgn:name":"Taixing Guoxiao",
    "tgn:placetype":[
        "aat:300006495"
    ]
},
  "bbox": [],
  "geometry": {"coordinates":[120.634444,23.5425],"type":"Point"}
}