<<<<<<< HEAD
{
  "id": 7485931,
  "type": "Feature",
  "properties": {
    "tgn:hierarchy":[
        "tgn:7485931",
        "tgn:7468018",
        "tgn:1000004",
        "tgn:1000141",
        "tgn:7029392"
    ],
    "tgn:id":7485931,
    "tgn:name":"Taixing Guoxiao",
    "tgn:placetype":[
        "aat:300006495"
    ]
},
  "bbox": [],
  "geometry": {"coordinates":[120.634444,23.5425],"type":"Point"}
}
=======
{"geometry":{"type":"Point","coordinates":[120.634444,23.542500]},"type":"Feature","properties":{"hierarchy":["tgn:7485931","tgn:7468018","tgn:1000004","tgn:1000141","tgn:7029392"],"placetype":["aat:300006495"],"id":7485931,"name:xx":"Taixing Guoxiao"}}
>>>>>>> 03f74aca74312dbeaf24d7e61306dd6a786dc3d0
