{
  "id": 2367148,
  "type": "Feature",
  "properties": {
    "tgn:hierarchy":[
        "tgn:2367148",
        "tgn:7002659",
        "tgn:1000001",
        "tgn:7012149",
        "tgn:2000060",
        "tgn:7029392"
    ],
    "tgn:id":2367148,
    "tgn:name":"Grogans Spring",
    "tgn:placetype":[
        "aat:300008697"
    ]
},
  "bbox": [],
  "geometry": {"coordinates":[-86.15,33.3833],"type":"Point"}
}