<<<<<<< HEAD
{
  "id": 2761434,
  "type": "Feature",
  "properties": {
    "tgn:hierarchy":[
        "tgn:2761434",
        "tgn:1000001",
        "tgn:1002461",
        "tgn:7012149",
        "tgn:7007159",
        "tgn:7029392"
    ],
    "tgn:id":2761434,
    "tgn:name":"West Mountains",
    "tgn:placetype":[
        "aat:300386831"
    ]
},
  "bbox": [],
  "geometry": {"coordinates":[-72.85,41.8833],"type":"Point"}
}
=======
{"geometry":{"type":"Point","coordinates":[-72.850000,41.883300]},"type":"Feature","properties":{"hierarchy":["tgn:2761434","tgn:1000001","tgn:1002461","tgn:7012149","tgn:7007159","tgn:7029392"],"placetype":["aat:300386831"],"id":2761434,"name:xx":"West Mountains"}}
>>>>>>> 03f74aca74312dbeaf24d7e61306dd6a786dc3d0
