{
  "id": 2761434,
  "type": "Feature",
  "properties": {
    "tgn:hierarchy":[
        "tgn:2761434",
        "tgn:1000001",
        "tgn:1002461",
        "tgn:7012149",
        "tgn:7007159",
        "tgn:7029392"
    ],
    "tgn:id":2761434,
    "tgn:name":"West Mountains",
    "tgn:placetype":[
        "aat:300386831"
    ]
},
  "bbox": [],
  "geometry": {"coordinates":[-72.85,41.8833],"type":"Point"}
}