{
  "id": 7023885,
  "type": "Feature",
  "properties": {
    "tgn:hierarchy":[
        "tgn:7023885",
        "tgn:1000004",
        "tgn:7011528",
        "tgn:7002435",
        "tgn:7029392"
    ],
    "tgn:id":7023885,
    "tgn:name":"Olekminsk",
    "tgn:placetype":[
        "aat:300008347"
    ]
},
  "bbox": [],
  "geometry": {"coordinates":[120.4167,60.4167],"type":"Point"}
}