{
  "id": 2387376,
  "type": "Feature",
  "properties": {
    "tgn:hierarchy":[
        "tgn:2387376",
        "tgn:1000001",
        "tgn:2000273",
        "tgn:7012149",
        "tgn:7007240",
        "tgn:7029392"
    ],
    "tgn:id":2387376,
    "tgn:name":"Hettie Pond",
    "tgn:placetype":[
        "aat:300008680"
    ]
},
  "bbox": [],
  "geometry": {"coordinates":[-84.95,30.85],"type":"Point"}
}