{
  "id": 7379845,
  "type": "Feature",
  "properties": {
    "tgn:hierarchy":[
        "tgn:7379845",
        "tgn:1000001",
        "tgn:7005601",
        "tgn:7005560",
        "tgn:7029392"
    ],
    "tgn:id":7379845,
    "tgn:name":"Los Encinos",
    "tgn:placetype":[
        "aat:300008347"
    ]
},
  "bbox": [],
  "geometry": {"coordinates":[-102.983333,21.95],"type":"Point"}
}