{
  "id": 2711996,
  "type": "Feature",
  "properties": {
    "tgn:hierarchy":[
        "tgn:2711996",
        "tgn:7002659",
        "tgn:1000001",
        "tgn:7012149",
        "tgn:2000023",
        "tgn:7029392"
    ],
    "tgn:id":2711996,
    "tgn:name":"Tarver Bar",
    "tgn:placetype":[
        "aat:300132348"
    ]
},
  "bbox": [],
  "geometry": {"coordinates":[-86.95,32.3667],"type":"Point"}
}