{
  "id": 1017748,
  "type": "Feature",
  "properties": {
    "tgn:hierarchy":[
        "tgn:1017748",
        "tgn:1001835",
        "tgn:1000001",
        "tgn:7005560",
        "tgn:7029392"
    ],
    "tgn:id":1017748,
    "tgn:name":"Las Escobas",
    "tgn:placetype":[
        "aat:300008347"
    ]
},
  "bbox": [],
  "geometry": {"coordinates":[-115.933333,30.55],"type":"Point"}
}