{
  "id": 2312033,
  "type": "Feature",
  "properties": {
    "tgn:hierarchy":[
        "tgn:2312033",
        "tgn:1000001",
        "tgn:7012149",
        "tgn:2001278",
        "tgn:7007524",
        "tgn:7029392"
    ],
    "tgn:id":2312033,
    "tgn:name":"Egge Ditch",
    "tgn:placetype":[
        "aat:300006075"
    ]
},
  "bbox": [],
  "geometry": {"coordinates":[-108.8167,46.2667],"type":"Point"}
}