{
  "id": 7020132,
  "type": "Feature",
  "properties": {
    "tgn:hierarchy":[
        "tgn:7020132",
        "tgn:2001463",
        "tgn:1000001",
        "tgn:7012149",
        "tgn:7007709",
        "tgn:7029392"
    ],
    "tgn:id":7020132,
    "tgn:name":"Forest Lake",
    "tgn:placetype":[
        "aat:300006191"
    ]
},
  "bbox": [],
  "geometry": {"coordinates":[-79.2667,36.1167],"type":"Point"}
}