{
  "id": 2421874,
  "type": "Feature",
  "properties": {
    "tgn:hierarchy":[
        "tgn:2421874",
        "tgn:1000001",
        "tgn:7012149",
        "tgn:2002098",
        "tgn:7007826",
        "tgn:7029392"
    ],
    "tgn:id":2421874,
    "tgn:name":"Jim Anderson Creek",
    "tgn:placetype":[
        "aat:300008706"
    ]
},
  "bbox": [],
  "geometry": {"coordinates":[-98.6667,33.1333],"type":"Point"}
}