<<<<<<< HEAD
{
  "id": 2764054,
  "type": "Feature",
  "properties": {
    "tgn:hierarchy":[
        "tgn:2764054",
        "tgn:1000001",
        "tgn:7012149",
        "tgn:2001843",
        "tgn:7007825",
        "tgn:7029392"
    ],
    "tgn:id":2764054,
    "tgn:name":"Wheeler Creek",
    "tgn:placetype":[
        "aat:300008706"
    ]
},
  "bbox": [],
  "geometry": {"coordinates":[-84.2667,36.3333],"type":"Point"}
}
=======
{"geometry":{"type":"Point","coordinates":[-84.266700,36.333300]},"type":"Feature","properties":{"hierarchy":["tgn:2764054","tgn:1000001","tgn:7012149","tgn:2001843","tgn:7007825","tgn:7029392"],"placetype":["aat:300008706"],"id":2764054,"name:xx":"Wheeler Creek"}}
>>>>>>> 03f74aca74312dbeaf24d7e61306dd6a786dc3d0
