{
  "id": 2460225,
  "type": "Feature",
  "properties": {
    "tgn:hierarchy":[
        "tgn:2460225",
        "tgn:1000001",
        "tgn:7012149",
        "tgn:2002119",
        "tgn:7007827",
        "tgn:7029392"
    ],
    "tgn:id":2460225,
    "tgn:name":"Little Ruin Canyon",
    "tgn:placetype":[
        "aat:300008761"
    ]
},
  "bbox": [],
  "geometry": {"coordinates":[-109.05,37.3667],"type":"Point"}
}