<<<<<<< HEAD
{
  "id": 2404035,
  "type": "Feature",
  "properties": {
    "tgn:hierarchy":[
        "tgn:2404035",
        "tgn:1000001",
        "tgn:7012149",
        "tgn:2000287",
        "tgn:7007240",
        "tgn:7029392"
    ],
    "tgn:id":2404035,
    "tgn:name":"Howell Place",
    "tgn:placetype":[
        "aat:300008347"
    ]
},
  "bbox": [],
  "geometry": {"coordinates":[-83.5,29.7667],"type":"Point"}
}
=======
{"geometry":{"type":"Point","coordinates":[-83.500000,29.766700]},"type":"Feature","properties":{"hierarchy":["tgn:2404035","tgn:1000001","tgn:7012149","tgn:2000287","tgn:7007240","tgn:7029392"],"placetype":["aat:300008347"],"id":2404035,"name:xx":"Howell Place"}}
>>>>>>> 03f74aca74312dbeaf24d7e61306dd6a786dc3d0
