{
  "id": 1126231,
  "type": "Feature",
  "properties": {
    "tgn:hierarchy":[
        "tgn:1126231",
        "tgn:1000001",
        "tgn:7012149",
        "tgn:7007516",
        "tgn:7029392"
    ],
    "tgn:id":1126231,
    "tgn:name":"Little Patuxent",
    "tgn:placetype":[
        "aat:300008707"
    ]
},
  "bbox": [],
  "geometry": {"coordinates":[-76.9333,39.3167],"type":"Point"}
}