{
  "id": 7500368,
  "type": "Feature",
  "properties": {
    "tgn:hierarchy":[
        "tgn:7500368",
        "tgn:1000004",
        "tgn:7001009",
        "tgn:1000141",
        "tgn:7029392"
    ],
    "tgn:id":7500368,
    "tgn:name":"Shizhangzi",
    "tgn:placetype":[
        "aat:300008347"
    ]
},
  "bbox": [],
  "geometry": {"coordinates":[120.53846,24.188486],"type":"Point"}
}