{
  "id": 7199897,
  "type": "Feature",
  "properties": {
    "tgn:hierarchy":[
        "tgn:7199897",
        "tgn:7000096",
        "tgn:1000003",
        "tgn:7000084",
        "tgn:7029392"
    ],
    "tgn:id":7199897,
    "tgn:name":"Drehnow",
    "tgn:placetype":[
        "aat:300008347"
    ]
},
  "bbox": [],
  "geometry": {"coordinates":[14.366667,51.866667],"type":"Point"}
}