{
  "id": 2128714,
  "type": "Feature",
  "properties": {
    "tgn:hierarchy":[
        "tgn:2128714",
        "tgn:1000001",
        "tgn:7014090",
        "tgn:7012149",
        "tgn:7007565",
        "tgn:7029392"
    ],
    "tgn:id":2128714,
    "tgn:name":"Aldrich Lake",
    "tgn:placetype":[
        "aat:300006191"
    ]
},
  "bbox": [],
  "geometry": {"coordinates":[-74.25,40.1333],"type":"Point"}
}