{
  "id": 7337541,
  "type": "Feature",
  "properties": {
    "tgn:hierarchy":[
        "tgn:7337541",
        "tgn:7002834",
        "tgn:1000003",
        "tgn:7002786",
        "tgn:1000095",
        "tgn:7029392"
    ],
    "tgn:id":7337541,
    "tgn:name":"Chilreu, Islote de",
    "tgn:placetype":[
        "aat:300008791"
    ]
},
  "bbox": [],
  "geometry": {"coordinates":[-8.733333,42.366667],"type":"Point"}
}