{
  "id": 1038937,
  "type": "Feature",
  "properties": {
    "tgn:hierarchy":[
        "tgn:1038937",
        "tgn:1000003",
        "tgn:7003682",
        "tgn:7000084",
        "tgn:7029392"
    ],
    "tgn:id":1038937,
    "tgn:name":"Eisenschmitt",
    "tgn:placetype":[
        "aat:300008347"
    ]
},
  "bbox": [],
  "geometry": {"coordinates":[6.716667,50.05],"type":"Point"}
}