{
  "id": 2214909,
  "type": "Feature",
  "properties": {
    "tgn:hierarchy":[
        "tgn:2214909",
        "tgn:1000001",
        "tgn:7012149",
        "tgn:2001447",
        "tgn:7007566",
        "tgn:7029392"
    ],
    "tgn:id":2214909,
    "tgn:name":"Caliche Spring",
    "tgn:placetype":[
        "aat:300008697"
    ]
},
  "bbox": [],
  "geometry": {"coordinates":[-105.8333,33.0333],"type":"Point"}
}