{
  "id": 2498100,
  "type": "Feature",
  "properties": {
    "tgn:hierarchy":[
        "tgn:2498100",
        "tgn:1000001",
        "tgn:7012149",
        "tgn:2001131",
        "tgn:7007522",
        "tgn:7029392"
    ],
    "tgn:id":2498100,
    "tgn:name":"Mays Creek",
    "tgn:placetype":[
        "aat:300008706"
    ]
},
  "bbox": [],
  "geometry": {"coordinates":[-89.95,31.1667],"type":"Point"}
}