{
  "id": 2752624,
  "type": "Feature",
  "properties": {
    "tgn:hierarchy":[
        "tgn:2752624",
        "tgn:1000001",
        "tgn:1002985",
        "tgn:7012149",
        "tgn:7007565",
        "tgn:7029392"
    ],
    "tgn:id":2752624,
    "tgn:name":"Wasigan, Lake",
    "tgn:placetype":[
        "aat:300006191"
    ]
},
  "bbox": [],
  "geometry": {"coordinates":[-74.9333,40.95],"type":"Point"}
}