{
  "id": 2152560,
  "type": "Feature",
  "properties": {
    "tgn:hierarchy":[
        "tgn:2152560",
        "tgn:1000001",
        "tgn:7012149",
        "tgn:2001488",
        "tgn:7007709",
        "tgn:7029392"
    ],
    "tgn:id":2152560,
    "tgn:name":"Bayberry Bluffs",
    "tgn:placetype":[
        "aat:300008347"
    ]
},
  "bbox": [],
  "geometry": {"coordinates":[-75.75,36.1667],"type":"Point"}
}