{
  "id": 7427903,
  "type": "Feature",
  "properties": {
    "tgn:hierarchy":[
        "tgn:7427903",
        "tgn:1000001",
        "tgn:7005594",
        "tgn:7005560",
        "tgn:7029392"
    ],
    "tgn:id":7427903,
    "tgn:name":"Estaci\u00f3n Coronados",
    "tgn:placetype":[
        "aat:300007783"
    ]
},
  "bbox": [],
  "geometry": {"coordinates":[-100.966667,23.533333],"type":"Point"}
}