{
  "id": 2080853,
  "type": "Feature",
  "properties": {
    "tgn:hierarchy":[
        "tgn:2080853",
        "tgn:1000001",
        "tgn:7012149",
        "tgn:2001612",
        "tgn:7007706",
        "tgn:7029392"
    ],
    "tgn:id":2080853,
    "tgn:name":"Morgan Center",
    "tgn:placetype":[
        "aat:300008347",
        "aat:300387210"
    ]
},
  "bbox": [],
  "geometry": {"coordinates":[-82.2667,38.9667],"type":"Point"}
}