<<<<<<< HEAD
{
  "id": 7377019,
  "type": "Feature",
  "properties": {
    "tgn:hierarchy":[
        "tgn:7377019",
        "tgn:1000001",
        "tgn:7005595",
        "tgn:7005560",
        "tgn:7029392"
    ],
    "tgn:id":7377019,
    "tgn:name":"La Tuna",
    "tgn:placetype":[
        "aat:300008347"
    ]
},
  "bbox": [],
  "geometry": {"coordinates":[-105.216667,22.966667],"type":"Point"}
}
=======
{"geometry":{"type":"Point","coordinates":[-105.216667,22.966667]},"type":"Feature","properties":{"hierarchy":["tgn:7377019","tgn:1000001","tgn:7005595","tgn:7005560","tgn:7029392"],"placetype":["aat:300008347"],"id":7377019,"name:xx":"La Tuna"}}
>>>>>>> 03f74aca74312dbeaf24d7e61306dd6a786dc3d0
