{
  "id": 7007380,
  "type": "Feature",
  "properties": {
    "tgn:hierarchy":[
        "tgn:7007380",
        "tgn:7003742",
        "tgn:1000003",
        "tgn:7011731",
        "tgn:7029392"
    ],
    "tgn:id":7007380,
    "tgn:name":"Kallnach",
    "tgn:placetype":[
        "aat:300008347"
    ]
},
  "bbox": [],
  "geometry": {"coordinates":[7.25,47.0333],"type":"Point"}
}