<<<<<<< HEAD
{
  "id": 7474196,
  "type": "Feature",
  "properties": {
    "tgn:hierarchy":[
        "tgn:7474196",
        "tgn:1000004",
        "tgn:1000454",
        "tgn:1000141",
        "tgn:7029392"
    ],
    "tgn:id":7474196,
    "tgn:name":"Wukuzi Shan",
    "tgn:placetype":[
        "aat:300387002"
    ]
},
  "bbox": [],
  "geometry": {"coordinates":[121.703111,24.943587],"type":"Point"}
}
=======
{"geometry":{"type":"Point","coordinates":[121.703111,24.943587]},"type":"Feature","properties":{"hierarchy":["tgn:7474196","tgn:1000004","tgn:1000454","tgn:1000141","tgn:7029392"],"placetype":["aat:300387002"],"id":7474196,"name:xx":"Wukuzi Shan"}}
>>>>>>> 03f74aca74312dbeaf24d7e61306dd6a786dc3d0
