{
  "id": 2139430,
  "type": "Feature",
  "properties": {
    "tgn:hierarchy":[
        "tgn:2139430",
        "tgn:1000001",
        "tgn:7012149",
        "tgn:2001708",
        "tgn:7007708",
        "tgn:7029392"
    ],
    "tgn:id":2139430,
    "tgn:name":"Aspen Spring",
    "tgn:placetype":[
        "aat:300008697"
    ]
},
  "bbox": [],
  "geometry": {"coordinates":[-118.2833,44.15],"type":"Point"}
}