{
  "id": 2219314,
  "type": "Feature",
  "properties": {
    "tgn:hierarchy":[
        "tgn:2219314",
        "tgn:7006450",
        "tgn:1000001",
        "tgn:7012149",
        "tgn:2000088",
        "tgn:7029392"
    ],
    "tgn:id":2219314,
    "tgn:name":"Cannery Creek",
    "tgn:placetype":[
        "aat:300008706"
    ]
},
  "bbox": [],
  "geometry": {"coordinates":[-132.1167,55.75],"type":"Point"}
}