{
  "id": 7442130,
  "type": "Feature",
  "properties": {
    "tgn:hierarchy":[
        "tgn:7442130",
        "tgn:7002445",
        "tgn:1000003",
        "tgn:7012032",
        "tgn:7008591",
        "tgn:7029392"
    ],
    "tgn:id":7442130,
    "tgn:name:en":"Washford",
    "tgn:placetype":[
        "aat:300008347"
    ]
},
  "bbox": [],
  "geometry": {"coordinates":[-3.361944,51.160833],"type":"Point"}
}