{
  "id": 7293854,
  "type": "Feature",
  "properties": {
    "tgn:hierarchy":[
        "tgn:7293854",
        "tgn:7008912",
        "tgn:7030216",
        "tgn:1000003",
        "tgn:1000095",
        "tgn:7029392"
    ],
    "tgn:id":7293854,
    "tgn:name":"Vilamitjana",
    "tgn:placetype":[
        "aat:300008347"
    ]
},
  "bbox": [],
  "geometry": {"coordinates":[1.378836,42.348358],"type":"Point"}
}