<<<<<<< HEAD
{
  "id": 2407461,
  "type": "Feature",
  "properties": {
    "tgn:hierarchy":[
        "tgn:2407461",
        "tgn:1000001",
        "tgn:7012149",
        "tgn:2000408",
        "tgn:7007248",
        "tgn:7029392"
    ],
    "tgn:id":2407461,
    "tgn:name":"Hunts",
    "tgn:placetype":[
        "aat:300008347"
    ]
},
  "bbox": [],
  "geometry": {"coordinates":[-83.4,33.3333],"type":"Point"}
}
=======
{"geometry":{"type":"Point","coordinates":[-83.400000,33.333300]},"type":"Feature","properties":{"hierarchy":["tgn:2407461","tgn:1000001","tgn:7012149","tgn:2000408","tgn:7007248","tgn:7029392"],"placetype":["aat:300008347"],"id":2407461,"name:xx":"Hunts"}}
>>>>>>> 03f74aca74312dbeaf24d7e61306dd6a786dc3d0
