{
  "id": 2630985,
  "type": "Feature",
  "properties": {
    "tgn:hierarchy":[
        "tgn:2630985",
        "tgn:1000001",
        "tgn:7020676",
        "tgn:7012149",
        "tgn:7007256",
        "tgn:7029392"
    ],
    "tgn:id":2630985,
    "tgn:name":"Round Lake Canal",
    "tgn:placetype":[
        "aat:300006075"
    ]
},
  "bbox": [],
  "geometry": {"coordinates":[-92.65,29.8667],"type":"Point"}
}