{
  "id": 1068243,
  "type": "Feature",
  "properties": {
    "tgn:hierarchy":[
        "tgn:1068243",
        "tgn:1000004",
        "tgn:7002085",
        "tgn:1000111",
        "tgn:7029392"
    ],
    "tgn:id":1068243,
    "tgn:name":"Gaomi",
    "tgn:placetype":[
        "aat:300008347"
    ]
},
  "bbox": [],
  "geometry": {"coordinates":[119.5833,36.3833],"type":"Point"}
}