{
  "id": 2235413,
  "type": "Feature",
  "properties": {
    "tgn:hierarchy":[
        "tgn:2235413",
        "tgn:1000001",
        "tgn:7012149",
        "tgn:2002119",
        "tgn:7007827",
        "tgn:7029392"
    ],
    "tgn:id":2235413,
    "tgn:name":"Chess Ridge Mine",
    "tgn:placetype":[
        "aat:300000390"
    ]
},
  "bbox": [],
  "geometry": {"coordinates":[-109.3167,38.4667],"type":"Point"}
}