{
  "id": 7548264,
  "type": "Feature",
  "properties": {
    "tgn:hierarchy":[
        "tgn:7548264",
        "tgn:1000004",
        "tgn:7000198",
        "tgn:1001977",
        "tgn:7029392"
    ],
    "tgn:id":7548264,
    "tgn:name:en":"Bar\u0101dighi",
    "tgn:placetype":[
        "aat:300007783"
    ]
},
  "bbox": [],
  "geometry": {"coordinates":[88.740074,26.794272],"type":"Point"}
}