{
  "id": 7560765,
  "type": "Feature",
  "properties": {
    "tgn:hierarchy":[
        "tgn:7560765",
        "tgn:1000004",
        "tgn:7000198",
        "tgn:7016722",
        "tgn:7029392"
    ],
    "tgn:id":7560765,
    "tgn:name:en":"T\u0101r ka Nagla",
    "tgn:placetype":[
        "aat:300008347"
    ]
},
  "bbox": [],
  "geometry": {"coordinates":[79.088473,26.758888],"type":"Point"}
}