{
  "id": 2109407,
  "type": "Feature",
  "properties": {
    "tgn:hierarchy":[
        "tgn:2109407",
        "tgn:1000001",
        "tgn:1002753",
        "tgn:7012149",
        "tgn:7007828",
        "tgn:7029392"
    ],
    "tgn:id":2109407,
    "tgn:name":"Albany Center",
    "tgn:placetype":[
        "aat:300008347",
        "aat:300387210"
    ]
},
  "bbox": [],
  "geometry": {"coordinates":[-72.35,44.7333],"type":"Point"}
}