{
  "id": 2551136,
  "type": "Feature",
  "properties": {
    "tgn:hierarchy":[
        "tgn:2551136",
        "tgn:1000001",
        "tgn:7012149",
        "tgn:7007157",
        "tgn:2000189",
        "tgn:7029392"
    ],
    "tgn:id":2551136,
    "tgn:name":"Noyes Valley Creek",
    "tgn:placetype":[
        "aat:300008706"
    ]
},
  "bbox": [],
  "geometry": {"coordinates":[-122.65,41.45],"type":"Point"}
}