{
  "id": 2312375,
  "type": "Feature",
  "properties": {
    "tgn:hierarchy":[
        "tgn:2312375",
        "tgn:1000001",
        "tgn:7012149",
        "tgn:2001609",
        "tgn:7007705",
        "tgn:7029392"
    ],
    "tgn:id":2312375,
    "tgn:name":"Eightmile Creek",
    "tgn:placetype":[
        "aat:300008706"
    ]
},
  "bbox": [],
  "geometry": {"coordinates":[-103.9333,48.1667],"type":"Point"}
}