{
  "id": 2554554,
  "type": "Feature",
  "properties": {
    "tgn:hierarchy":[
        "tgn:2554554",
        "tgn:1000001",
        "tgn:7014352",
        "tgn:7012149",
        "tgn:7007564",
        "tgn:7029392"
    ],
    "tgn:id":2554554,
    "tgn:name":"Oaklands, The",
    "tgn:placetype":[
        "aat:300132451"
    ]
},
  "bbox": [],
  "geometry": {"coordinates":[-70.95,42.9833],"type":"Point"}
}