{
  "id": 1092920,
  "type": "Feature",
  "properties": {
    "tgn:hierarchy":[
        "tgn:1092920",
        "tgn:7001242",
        "tgn:7017584",
        "tgn:1000193",
        "tgn:7029392"
    ],
    "tgn:id":1092920,
    "tgn:name":"Bredasdorp",
    "tgn:placetype":[
        "aat:300008347"
    ]
},
  "bbox": [],
  "geometry": {"coordinates":[20.0333,-34.5333],"type":"Point"}
}