{
  "id": 7587461,
  "type": "Feature",
  "properties": {
    "tgn:hierarchy":[
        "tgn:7587461",
        "tgn:1000004",
        "tgn:7000198",
        "tgn:7000799",
        "tgn:7029392"
    ],
    "tgn:id":7587461,
    "tgn:name:en":"Rainaw\u0101di",
    "tgn:placetype":[
        "aat:300008347"
    ]
},
  "bbox": [],
  "geometry": {"coordinates":[74.826389,34.094444],"type":"Point"}
}