{
  "id": 2297585,
  "type": "Feature",
  "properties": {
    "tgn:hierarchy":[
        "tgn:2297585",
        "tgn:1000001",
        "tgn:2002366",
        "tgn:7012149",
        "tgn:7007923",
        "tgn:7029392"
    ],
    "tgn:id":2297585,
    "tgn:name":"Dry Fork Granite Creek",
    "tgn:placetype":[
        "aat:300008706"
    ]
},
  "bbox": [],
  "geometry": {"coordinates":[-107.55,44.6167],"type":"Point"}
}