{
  "id": 7554626,
  "type": "Feature",
  "properties": {
    "tgn:hierarchy":[
        "tgn:7554626",
        "tgn:1000004",
        "tgn:7000198",
        "tgn:7001797",
        "tgn:7029392"
    ],
    "tgn:id":7554626,
    "tgn:name:en":"Melpatti",
    "tgn:placetype":[
        "aat:300008347"
    ]
},
  "bbox": [],
  "geometry": {"coordinates":[78.766667,12.866667],"type":"Point"}
}