{
  "id": 7422000,
  "type": "Feature",
  "properties": {
    "tgn:hierarchy":[
        "tgn:7422000",
        "tgn:1000001",
        "tgn:1001960",
        "tgn:7005560",
        "tgn:7029392"
    ],
    "tgn:id":7422000,
    "tgn:name":"Las Panelas",
    "tgn:placetype":[
        "aat:300008347"
    ]
},
  "bbox": [],
  "geometry": {"coordinates":[-108.883333,27.433333],"type":"Point"}
}