<<<<<<< HEAD
{
  "id": 7488913,
  "type": "Feature",
  "properties": {
    "tgn:hierarchy":[
        "tgn:7488913",
        "tgn:1000004",
        "tgn:7491221",
        "tgn:1000141",
        "tgn:7029392"
    ],
    "tgn:id":7488913,
    "tgn:name":"Hutou Shan",
    "tgn:placetype":[
        "aat:300008777"
    ]
},
  "bbox": [],
  "geometry": {"coordinates":[121.147953,22.793518],"type":"Point"}
}
=======
{"geometry":{"type":"Point","coordinates":[121.147953,22.793518]},"type":"Feature","properties":{"hierarchy":["tgn:7488913","tgn:1000004","tgn:7491221","tgn:1000141","tgn:7029392"],"placetype":["aat:300008777"],"id":7488913,"name:xx":"Hutou Shan"}}
>>>>>>> 03f74aca74312dbeaf24d7e61306dd6a786dc3d0
