{
  "id": 2017019,
  "type": "Feature",
  "properties": {
    "tgn:hierarchy":[
        "tgn:2017019",
        "tgn:1000001",
        "tgn:1002461",
        "tgn:7012149",
        "tgn:7007159",
        "tgn:7029392"
    ],
    "tgn:id":2017019,
    "tgn:name":"Kensington",
    "tgn:placetype":[
        "aat:300008347"
    ]
},
  "bbox": [],
  "geometry": {"coordinates":[-72.7667,41.6333],"type":"Point"}
}