{
  "id": 2167377,
  "type": "Feature",
  "properties": {
    "tgn:hierarchy":[
        "tgn:2167377",
        "tgn:7002659",
        "tgn:1000001",
        "tgn:7012149",
        "tgn:2000044",
        "tgn:7029392"
    ],
    "tgn:id":2167377,
    "tgn:name":"Big Cove Creek",
    "tgn:placetype":[
        "aat:300008706"
    ]
},
  "bbox": [],
  "geometry": {"coordinates":[-86.5167,34.7167],"type":"Point"}
}