{
  "id": 2758182,
  "type": "Feature",
  "properties": {
    "tgn:hierarchy":[
        "tgn:2758182",
        "tgn:1000001",
        "tgn:1002840",
        "tgn:7012149",
        "tgn:7007828",
        "tgn:7029392"
    ],
    "tgn:id":2758182,
    "tgn:name":"West Branch Tweed River",
    "tgn:placetype":[
        "aat:300008707"
    ]
},
  "bbox": [],
  "geometry": {"coordinates":[-72.8833,43.7833],"type":"Point"}
}