{
  "id": 2199593,
  "type": "Feature",
  "properties": {
    "tgn:hierarchy":[
        "tgn:2199593",
        "tgn:1000001",
        "tgn:7012149",
        "tgn:2002375",
        "tgn:7007923",
        "tgn:7029392"
    ],
    "tgn:id":2199593,
    "tgn:name":"Brush Creek",
    "tgn:placetype":[
        "aat:300008706"
    ]
},
  "bbox": [],
  "geometry": {"coordinates":[-105.0167,41.0167],"type":"Point"}
}