{
  "id": 2037915,
  "type": "Feature",
  "properties": {
    "tgn:hierarchy":[
        "tgn:2037915",
        "tgn:1000001",
        "tgn:7012149",
        "tgn:1002382",
        "tgn:7007255",
        "tgn:7029392"
    ],
    "tgn:id":2037915,
    "tgn:name":"Bridgeport",
    "tgn:placetype":[
        "aat:300008347"
    ]
},
  "bbox": [],
  "geometry": {"coordinates":[-84.95,38.15],"type":"Point"}
}