{
  "id": 2550546,
  "type": "Feature",
  "properties": {
    "tgn:hierarchy":[
        "tgn:2550546",
        "tgn:1000001",
        "tgn:7012149",
        "tgn:2001243",
        "tgn:7007523",
        "tgn:7029392"
    ],
    "tgn:id":2550546,
    "tgn:name":"Norton",
    "tgn:placetype":[
        "aat:300008347"
    ]
},
  "bbox": [],
  "geometry": {"coordinates":[-93.1333,39.1833],"type":"Point"}
}