{
  "id": 7206832,
  "type": "Feature",
  "properties": {
    "tgn:hierarchy":[
        "tgn:7206832",
        "tgn:7003669",
        "tgn:1000003",
        "tgn:7000084",
        "tgn:7029392"
    ],
    "tgn:id":7206832,
    "tgn:name":"Buxberg",
    "tgn:placetype":[
        "aat:300008347"
    ]
},
  "bbox": [],
  "geometry": {"coordinates":[11.266667,48.433333],"type":"Point"}
}