<<<<<<< HEAD
{
  "id": 7055928,
  "type": "Feature",
  "properties": {
    "tgn:hierarchy":[
        "tgn:7055928",
        "tgn:1003478",
        "tgn:1000003",
        "tgn:7003120",
        "tgn:1000080",
        "tgn:7029392"
    ],
    "tgn:id":7055928,
    "tgn:name":"Orasso",
    "tgn:placetype":[
        "aat:300008347"
    ]
},
  "bbox": [],
  "geometry": {"coordinates":[8.583333,46.1],"type":"Point"}
}
=======
{"geometry":{"type":"Point","coordinates":[8.583333,46.100000]},"type":"Feature","properties":{"hierarchy":["tgn:7055928","tgn:1003478","tgn:1000003","tgn:7003120","tgn:1000080","tgn:7029392"],"placetype":["aat:300008347"],"id":7055928,"name:xx":"Orasso"}}
>>>>>>> 03f74aca74312dbeaf24d7e61306dd6a786dc3d0
