{
  "id": 1006976,
  "type": "Feature",
  "properties": {
    "tgn:hierarchy":[
        "tgn:1006976",
        "tgn:1000003",
        "tgn:7003632",
        "tgn:7016845",
        "tgn:7029392"
    ],
    "tgn:id":1006976,
    "tgn:name":"Dordrecht, Gemeente",
    "tgn:placetype":[
        "aat:300008791"
    ]
},
  "bbox": [],
  "geometry": {"coordinates":[4.6667,51.7833],"type":"Point"}
}