{
  "id": 2503339,
  "type": "Feature",
  "properties": {
    "tgn:hierarchy":[
        "tgn:2503339",
        "tgn:1000001",
        "tgn:7012149",
        "tgn:1002691",
        "tgn:7007826",
        "tgn:7029392"
    ],
    "tgn:id":2503339,
    "tgn:name":"McRae Creek",
    "tgn:placetype":[
        "aat:300008706"
    ]
},
  "bbox": [],
  "geometry": {"coordinates":[-95.3833,30.4833],"type":"Point"}
}