{
  "id": 2211580,
  "type": "Feature",
  "properties": {
    "tgn:hierarchy":[
        "tgn:2211580",
        "tgn:1000001",
        "tgn:7012149",
        "tgn:7007157",
        "tgn:2000190",
        "tgn:7029392"
    ],
    "tgn:id":2211580,
    "tgn:name":"Buttermilk Creek",
    "tgn:placetype":[
        "aat:300008706"
    ]
},
  "bbox": [],
  "geometry": {"coordinates":[-122.85,39.8333],"type":"Point"}
}