{
  "id": 7538613,
  "type": "Feature",
  "properties": {
    "tgn:hierarchy":[
        "tgn:7538613",
        "tgn:7001242",
        "tgn:7016833",
        "tgn:7001335",
        "tgn:7029392"
    ],
    "tgn:id":7538613,
    "tgn:name":"Munaydirat al Uthayl\u012b, Jabal",
    "tgn:placetype":[
        "aat:300008795"
    ]
},
  "bbox": [],
  "geometry": {"coordinates":[33.605957,30.524726],"type":"Point"}
}