{
  "id": 7491861,
  "type": "Feature",
  "properties": {
    "tgn:hierarchy":[
        "tgn:7491861",
        "tgn:1000004",
        "tgn:7471332",
        "tgn:1000141",
        "tgn:7029392"
    ],
    "tgn:id":7491861,
    "tgn:name":"Shuibiantou",
    "tgn:placetype":[
        "aat:300008347"
    ]
},
  "bbox": [],
  "geometry": {"coordinates":[121.110833,24.816944],"type":"Point"}
}