{
  "id": 7099110,
  "type": "Feature",
  "properties": {
    "tgn:hierarchy":[
        "tgn:7099110",
        "tgn:7003669",
        "tgn:1000003",
        "tgn:7000084",
        "tgn:7029392"
    ],
    "tgn:id":7099110,
    "tgn:name":"Sommersberg",
    "tgn:placetype":[
        "aat:300008347"
    ]
},
  "bbox": [],
  "geometry": {"coordinates":[13.233333,48.916667],"type":"Point"}
}