{
  "id": 7027304,
  "type": "Feature",
  "properties": {
    "tgn:hierarchy":[
        "tgn:7027304",
        "tgn:7002445",
        "tgn:7011980",
        "tgn:1000003",
        "tgn:7008591",
        "tgn:7029392"
    ],
    "tgn:id":7027304,
    "tgn:name:ang":"Riptune",
    "tgn:placetype":[
        "aat:300008347",
        "aat:300008372"
    ]
},
  "bbox": [],
  "geometry": {"coordinates":[-0.183333,52.383333],"type":"Point"}
}