{
  "id": 1089360,
  "type": "Feature",
  "properties": {
    "tgn:hierarchy":[
        "tgn:1089360",
        "tgn:7001242",
        "tgn:7016654",
        "tgn:1000159",
        "tgn:7029392"
    ],
    "tgn:id":1089360,
    "tgn:name":"Moma",
    "tgn:placetype":[
        "aat:300008347"
    ]
},
  "bbox": [],
  "geometry": {"coordinates":[23.95,-1.5833],"type":"Point"}
}