{
  "id": 2616594,
  "type": "Feature",
  "properties": {
    "tgn:hierarchy":[
        "tgn:2616594",
        "tgn:1000001",
        "tgn:7012149",
        "tgn:2000291",
        "tgn:7007240",
        "tgn:7029392"
    ],
    "tgn:id":2616594,
    "tgn:name":"Rice Machine Pond",
    "tgn:placetype":[
        "aat:300008680"
    ]
},
  "bbox": [],
  "geometry": {"coordinates":[-85.5333,30.5833],"type":"Point"}
}