<<<<<<< HEAD
{
  "id": 2764163,
  "type": "Feature",
  "properties": {
    "tgn:hierarchy":[
        "tgn:2764163",
        "tgn:1000001",
        "tgn:7012149",
        "tgn:1002899",
        "tgn:7007920",
        "tgn:7029392"
    ],
    "tgn:id":2764163,
    "tgn:name":"Wheeler Mountain",
    "tgn:placetype":[
        "aat:300008798"
    ]
},
  "bbox": [],
  "geometry": {"coordinates":[-121.9,48.2333],"type":"Point"}
}
=======
{"geometry":{"type":"Point","coordinates":[-121.900000,48.233300]},"type":"Feature","properties":{"hierarchy":["tgn:2764163","tgn:1000001","tgn:7012149","tgn:1002899","tgn:7007920","tgn:7029392"],"placetype":["aat:300008798"],"id":2764163,"name:xx":"Wheeler Mountain"}}
>>>>>>> 03f74aca74312dbeaf24d7e61306dd6a786dc3d0
