{
  "id": 2270767,
  "type": "Feature",
  "properties": {
    "tgn:hierarchy":[
        "tgn:2270767",
        "tgn:1000001",
        "tgn:7012149",
        "tgn:2002273",
        "tgn:7013961",
        "tgn:7029392"
    ],
    "tgn:id":2270767,
    "tgn:name":"Cub Branch",
    "tgn:placetype":[
        "aat:300008699"
    ]
},
  "bbox": [],
  "geometry": {"coordinates":[-81.8167,37.8167],"type":"Point"}
}