{
  "id": 7573897,
  "type": "Feature",
  "properties": {
    "tgn:hierarchy":[
        "tgn:7573897",
        "tgn:1000004",
        "tgn:7000198",
        "tgn:7016694",
        "tgn:7029392"
    ],
    "tgn:id":7573897,
    "tgn:name:en":"Jagann\u0101thapur",
    "tgn:placetype":[
        "aat:300007783"
    ]
},
  "bbox": [],
  "geometry": {"coordinates":[84.866667,19.333333],"type":"Point"}
}