{
  "id": 2181018,
  "type": "Feature",
  "properties": {
    "tgn:hierarchy":[
        "tgn:2181018",
        "tgn:1000001",
        "tgn:7012149",
        "tgn:1009002",
        "tgn:7007157",
        "tgn:1002867",
        "tgn:7029392"
    ],
    "tgn:id":2181018,
    "tgn:name":"Blue Banks Anchorage",
    "tgn:placetype":[
        "aat:300008678"
    ]
},
  "bbox": [],
  "geometry": {"coordinates":[-119.6667,33.9667],"type":"Point"}
}