{
  "id": 2411680,
  "type": "Feature",
  "properties": {
    "tgn:hierarchy":[
        "tgn:2411680",
        "tgn:1000001",
        "tgn:7012149",
        "tgn:2001190",
        "tgn:7007523",
        "tgn:7029392"
    ],
    "tgn:id":2411680,
    "tgn:name":"Indian Lake",
    "tgn:placetype":[
        "aat:300006191"
    ]
},
  "bbox": [],
  "geometry": {"coordinates":[-91.45,38.0833],"type":"Point"}
}