{
  "id": 1023998,
  "type": "Feature",
  "properties": {
    "tgn:hierarchy":[
        "tgn:1023998",
        "tgn:1000050",
        "tgn:1000682",
        "tgn:1000002",
        "tgn:7029392"
    ],
    "tgn:id":1023998,
    "tgn:name":"Santa Ana",
    "tgn:placetype":[
        "aat:300008347"
    ]
},
  "bbox": [],
  "geometry": {"coordinates":[-74.5833,9.3167],"type":"Point"}
}