{
  "id": 7086606,
  "type": "Feature",
  "properties": {
    "tgn:hierarchy":[
        "tgn:7086606",
        "tgn:7003669",
        "tgn:1000003",
        "tgn:7000084",
        "tgn:7029392"
    ],
    "tgn:id":7086606,
    "tgn:name":"Weindorf",
    "tgn:placetype":[
        "aat:300008347"
    ]
},
  "bbox": [],
  "geometry": {"coordinates":[11.216667,47.683333],"type":"Point"}
}