<<<<<<< HEAD
{
  "id": 7244337,
  "type": "Feature",
  "properties": {
    "tgn:hierarchy":[
        "tgn:7244337",
        "tgn:7003457",
        "tgn:1000003",
        "tgn:1000063",
        "tgn:7018236",
        "tgn:7029392"
    ],
    "tgn:id":7244337,
    "tgn:name":"Kaudenberg",
    "tgn:placetype":[
        "aat:300008347"
    ]
},
  "bbox": [],
  "geometry": {"coordinates":[3.821103,50.816461],"type":"Point"}
}
=======
{"geometry":{"type":"Point","coordinates":[3.821103,50.816461]},"type":"Feature","properties":{"hierarchy":["tgn:7244337","tgn:7003457","tgn:1000003","tgn:1000063","tgn:7018236","tgn:7029392"],"placetype":["aat:300008347"],"id":7244337,"name:xx":"Kaudenberg"}}
>>>>>>> 03f74aca74312dbeaf24d7e61306dd6a786dc3d0
