{
  "id": 7392889,
  "type": "Feature",
  "properties": {
    "tgn:hierarchy":[
        "tgn:7392889",
        "tgn:7005585",
        "tgn:1000001",
        "tgn:7005560",
        "tgn:7029392"
    ],
    "tgn:id":7392889,
    "tgn:name":"San Francisco",
    "tgn:placetype":[
        "aat:300008347"
    ]
},
  "bbox": [],
  "geometry": {"coordinates":[-101.45,18.133333],"type":"Point"}
}