{
  "id": 2694364,
  "type": "Feature",
  "properties": {
    "tgn:hierarchy":[
        "tgn:2694364",
        "tgn:1000001",
        "tgn:7012149",
        "tgn:1002950",
        "tgn:7007568",
        "tgn:7029392"
    ],
    "tgn:id":2694364,
    "tgn:name":"Steventown Hill",
    "tgn:placetype":[
        "aat:300008798"
    ]
},
  "bbox": [],
  "geometry": {"coordinates":[-76.4167,42.3667],"type":"Point"}
}