<<<<<<< HEAD
{
  "id": 2255427,
  "type": "Feature",
  "properties": {
    "tgn:hierarchy":[
        "tgn:2255427",
        "tgn:1002172",
        "tgn:1000001",
        "tgn:7012149",
        "tgn:7007710",
        "tgn:7029392"
    ],
    "tgn:id":2255427,
    "tgn:name":"Coot Hill",
    "tgn:placetype":[
        "aat:300008798"
    ]
},
  "bbox": [],
  "geometry": {"coordinates":[-78.3167,40.1667],"type":"Point"}
}
=======
{"geometry":{"type":"Point","coordinates":[-78.316700,40.166700]},"type":"Feature","properties":{"hierarchy":["tgn:2255427","tgn:1002172","tgn:1000001","tgn:7012149","tgn:7007710","tgn:7029392"],"placetype":["aat:300008798"],"id":2255427,"name:xx":"Coot Hill"}}
>>>>>>> 03f74aca74312dbeaf24d7e61306dd6a786dc3d0
