{
  "id": 2627854,
  "type": "Feature",
  "properties": {
    "tgn:hierarchy":[
        "tgn:2627854",
        "tgn:7006450",
        "tgn:1000001",
        "tgn:7012149",
        "tgn:2000086",
        "tgn:7029392"
    ],
    "tgn:id":2627854,
    "tgn:name":"Rohn Glacier",
    "tgn:placetype":[
        "aat:300008835"
    ]
},
  "bbox": [],
  "geometry": {"coordinates":[-142.4833,61.75],"type":"Point"}
}