<<<<<<< HEAD
{
  "id": 2708730,
  "type": "Feature",
  "properties": {
    "tgn:hierarchy":[
        "tgn:2708730",
        "tgn:1000001",
        "tgn:7012149",
        "tgn:7016057",
        "tgn:7007520",
        "tgn:7029392"
    ],
    "tgn:id":2708730,
    "tgn:name":"Sylvan Lake",
    "tgn:placetype":[
        "aat:300008680"
    ]
},
  "bbox": [],
  "geometry": {"coordinates":[-85.45,41.9],"type":"Point"}
}
=======
{"geometry":{"type":"Point","coordinates":[-85.450000,41.900000]},"type":"Feature","properties":{"hierarchy":["tgn:2708730","tgn:1000001","tgn:7012149","tgn:7016057","tgn:7007520","tgn:7029392"],"placetype":["aat:300008680"],"id":2708730,"name:xx":"Sylvan Lake"}}
>>>>>>> 03f74aca74312dbeaf24d7e61306dd6a786dc3d0
