<<<<<<< HEAD
{
  "id": 2406177,
  "type": "Feature",
  "properties": {
    "tgn:hierarchy":[
        "tgn:2406177",
        "tgn:7006450",
        "tgn:1000001",
        "tgn:7012149",
        "tgn:2000088",
        "tgn:7029392"
    ],
    "tgn:id":2406177,
    "tgn:name":"Hump Knoll",
    "tgn:placetype":[
        "aat:300008798"
    ]
},
  "bbox": [],
  "geometry": {"coordinates":[-132.8,57.1333],"type":"Point"}
}
=======
{"geometry":{"type":"Point","coordinates":[-132.800000,57.133300]},"type":"Feature","properties":{"hierarchy":["tgn:2406177","tgn:7006450","tgn:1000001","tgn:7012149","tgn:2000088","tgn:7029392"],"placetype":["aat:300008798"],"id":2406177,"name:xx":"Hump Knoll"}}
>>>>>>> 03f74aca74312dbeaf24d7e61306dd6a786dc3d0
