{
  "id": 2471143,
  "type": "Feature",
  "properties": {
    "tgn:hierarchy":[
        "tgn:2471143",
        "tgn:1000001",
        "tgn:7012149",
        "tgn:1002598",
        "tgn:7007523",
        "tgn:7029392"
    ],
    "tgn:id":2471143,
    "tgn:name":"Lost Creek Watershed E-2 Reservoir",
    "tgn:placetype":[
        "aat:300006191"
    ]
},
  "bbox": [],
  "geometry": {"coordinates":[-90.8167,39.1167],"type":"Point"}
}