{
  "id": 1078191,
  "type": "Feature",
  "properties": {
    "tgn:hierarchy":[
        "tgn:1078191",
        "tgn:7003974",
        "tgn:1000004",
        "tgn:1001467",
        "tgn:1000116",
        "tgn:7029392"
    ],
    "tgn:id":1078191,
    "tgn:name":"Mukusaki",
    "tgn:placetype":[
        "aat:300008347"
    ]
},
  "bbox": [],
  "geometry": {"coordinates":[121.6167,-8.55],"type":"Point"}
}