{
  "id": 7425133,
  "type": "Feature",
  "properties": {
    "tgn:hierarchy":[
        "tgn:7425133",
        "tgn:7005581",
        "tgn:1000001",
        "tgn:7005560",
        "tgn:7029392"
    ],
    "tgn:id":7425133,
    "tgn:name":"Grande, Laguna",
    "tgn:placetype":[
        "aat:300008680"
    ]
},
  "bbox": [],
  "geometry": {"coordinates":[-105.633333,30.05],"type":"Point"}
}