{
  "id": 7560777,
  "type": "Feature",
  "properties": {
    "tgn:hierarchy":[
        "tgn:7560777",
        "tgn:1000004",
        "tgn:7000198",
        "tgn:7016722",
        "tgn:7029392"
    ],
    "tgn:id":7560777,
    "tgn:name:en":"Kunwarpur",
    "tgn:placetype":[
        "aat:300008347"
    ]
},
  "bbox": [],
  "geometry": {"coordinates":[79.135722,26.753459],"type":"Point"}
}