{
  "id": 7380085,
  "type": "Feature",
  "properties": {
    "tgn:hierarchy":[
        "tgn:7380085",
        "tgn:7005586",
        "tgn:1000001",
        "tgn:7005560",
        "tgn:7029392"
    ],
    "tgn:id":7380085,
    "tgn:name":"Los Guajes",
    "tgn:placetype":[
        "aat:300008347"
    ]
},
  "bbox": [],
  "geometry": {"coordinates":[-104.016667,20.083333],"type":"Point"}
}