<<<<<<< HEAD
{
  "id": 2335597,
  "type": "Feature",
  "properties": {
    "tgn:hierarchy":[
        "tgn:2335597",
        "tgn:1000001",
        "tgn:7012149",
        "tgn:2001506",
        "tgn:7007709",
        "tgn:7029392"
    ],
    "tgn:id":2335597,
    "tgn:name":"Fortescue Creek",
    "tgn:placetype":[
        "aat:300008706"
    ]
},
  "bbox": [],
  "geometry": {"coordinates":[-76.4833,35.4],"type":"Point"}
}
=======
{"geometry":{"type":"Point","coordinates":[-76.483300,35.400000]},"type":"Feature","properties":{"hierarchy":["tgn:2335597","tgn:1000001","tgn:7012149","tgn:2001506","tgn:7007709","tgn:7029392"],"placetype":["aat:300008706"],"id":2335597,"name:xx":"Fortescue Creek"}}
>>>>>>> 03f74aca74312dbeaf24d7e61306dd6a786dc3d0
