{
  "id": 7037475,
  "type": "Feature",
  "properties": {
    "tgn:hierarchy":[
        "tgn:7037475",
        "tgn:1000003",
        "tgn:1003508",
        "tgn:7003237",
        "tgn:1000080",
        "tgn:7029392"
    ],
    "tgn:id":7037475,
    "tgn:name":"Tronzano Lago Maggiore",
    "tgn:placetype":[
        "aat:300008347"
    ]
},
  "bbox": [],
  "geometry": {"coordinates":[8.733333,46.083333],"type":"Point"}
}