{
  "id": 7417853,
  "type": "Feature",
  "properties": {
    "tgn:hierarchy":[
        "tgn:7417853",
        "tgn:7005584",
        "tgn:1000001",
        "tgn:7005560",
        "tgn:7029392"
    ],
    "tgn:id":7417853,
    "tgn:name":"San Antonio Corrales",
    "tgn:placetype":[
        "aat:300008347"
    ]
},
  "bbox": [],
  "geometry": {"coordinates":[-100.449167,20.382778],"type":"Point"}
}