{
  "id": 2244771,
  "type": "Feature",
  "properties": {
    "tgn:hierarchy":[
        "tgn:2244771",
        "tgn:7006450",
        "tgn:1000001",
        "tgn:2124053",
        "tgn:7012149",
        "tgn:7029392"
    ],
    "tgn:id":2244771,
    "tgn:name":"Cloud Creek",
    "tgn:placetype":[
        "aat:300008706"
    ]
},
  "bbox": [],
  "geometry": {"coordinates":[-150.2167,62.8667],"type":"Point"}
}