{
  "id": 7501557,
  "type": "Feature",
  "properties": {
    "tgn:hierarchy":[
        "tgn:7501557",
        "tgn:1000004",
        "tgn:7492971",
        "tgn:1000141",
        "tgn:7029392"
    ],
    "tgn:id":7501557,
    "tgn:name":"Yitun Qiao",
    "tgn:placetype":[
        "aat:300007836"
    ]
},
  "bbox": [],
  "geometry": {"coordinates":[120.788889,22.214167],"type":"Point"}
}