{
  "id": 2690706,
  "type": "Feature",
  "properties": {
    "tgn:hierarchy":[
        "tgn:2690706",
        "tgn:7006450",
        "tgn:1000001",
        "tgn:7012149",
        "tgn:2000089",
        "tgn:7029392"
    ],
    "tgn:id":2690706,
    "tgn:name":"Strand Peak",
    "tgn:placetype":[
        "aat:300008798"
    ]
},
  "bbox": [],
  "geometry": {"coordinates":[-154.7167,63.2667],"type":"Point"}
}