{
  "id": 7413377,
  "type": "Feature",
  "properties": {
    "tgn:hierarchy":[
        "tgn:7413377",
        "tgn:7005587",
        "tgn:1000001",
        "tgn:7005560",
        "tgn:7029392"
    ],
    "tgn:id":7413377,
    "tgn:name:es":"Verde, Cerro",
    "tgn:placetype":[
        "aat:300008795"
    ]
},
  "bbox": [],
  "geometry": {"coordinates":[-98.783333,20.45],"type":"Point"}
}