{
  "id": 7424273,
  "type": "Feature",
  "properties": {
    "tgn:hierarchy":[
        "tgn:7424273",
        "tgn:1000001",
        "tgn:1001960",
        "tgn:7005560",
        "tgn:7029392"
    ],
    "tgn:id":7424273,
    "tgn:name":"Campo N\u00fa\u00f1ez",
    "tgn:placetype":[
        "aat:300008347"
    ]
},
  "bbox": [],
  "geometry": {"coordinates":[-110.983333,29.366667],"type":"Point"}
}