{
  "id": 1087333,
  "type": "Feature",
  "properties": {
    "tgn:hierarchy":[
        "tgn:1087333",
        "tgn:7001242",
        "tgn:7014973",
        "tgn:7001644",
        "tgn:7029392"
    ],
    "tgn:id":1087333,
    "tgn:name":"Tadjoura",
    "tgn:placetype":[
        "aat:300008347",
        "aat:300387222",
        "aat:300008375"
    ]
},
  "bbox": [],
  "geometry": {"coordinates":[42.9333,11.8167],"type":"Point"}
}