{
  "id": 7067241,
  "type": "Feature",
  "properties": {
    "tgn:hierarchy":[
        "tgn:7067241",
        "tgn:7000096",
        "tgn:1000003",
        "tgn:7000084",
        "tgn:7029392"
    ],
    "tgn:id":7067241,
    "tgn:name":"Stolpe-S\u00fcd",
    "tgn:placetype":[
        "aat:300008347"
    ]
},
  "bbox": [],
  "geometry": {"coordinates":[13.233333,52.633333],"type":"Point"}
}