<<<<<<< HEAD
{
  "id": 7240943,
  "type": "Feature",
  "properties": {
    "tgn:hierarchy":[
        "tgn:7240943",
        "tgn:7003466",
        "tgn:1000003",
        "tgn:1000063",
        "tgn:4012014",
        "tgn:7029392"
    ],
    "tgn:id":7240943,
    "tgn:name":"Ch\u00e2teau de la Fontain Libion",
    "tgn:placetype":[
        "aat:300005567"
    ]
},
  "bbox": [],
  "geometry": {"coordinates":[5.183333,50.266667],"type":"Point"}
}
=======
{"geometry":{"type":"Point","coordinates":[5.183333,50.266667]},"type":"Feature","properties":{"hierarchy":["tgn:7240943","tgn:7003466","tgn:1000003","tgn:1000063","tgn:4012014","tgn:7029392"],"placetype":["aat:300005567"],"id":7240943,"name:xx":"Ch\u00e2teau de la Fontain Libion"}}
>>>>>>> 03f74aca74312dbeaf24d7e61306dd6a786dc3d0
