{
  "id": 7537062,
  "type": "Feature",
  "properties": {
    "tgn:hierarchy":[
        "tgn:7537062",
        "tgn:7001242",
        "tgn:1001075",
        "tgn:7016833",
        "tgn:7029392"
    ],
    "tgn:id":7537062,
    "tgn:name:en":"Bay\u1e11ah, Bu\u1e29ayrat al",
    "tgn:placetype":[
        "aat:300008680"
    ]
},
  "bbox": [],
  "geometry": {"coordinates":[30.24238,30.43148],"type":"Point"}
}