{
  "id": 2128253,
  "type": "Feature",
  "properties": {
    "tgn:hierarchy":[
        "tgn:2128253",
        "tgn:1000001",
        "tgn:2001099",
        "tgn:7012149",
        "tgn:7007522",
        "tgn:7029392"
    ],
    "tgn:id":2128253,
    "tgn:name":"Alcorn Brake",
    "tgn:placetype":[
        "aat:300008905"
    ]
},
  "bbox": [],
  "geometry": {"coordinates":[-90.45,34.2833],"type":"Point"}
}