{
  "id": 2365818,
  "type": "Feature",
  "properties": {
    "tgn:hierarchy":[
        "tgn:2365818",
        "tgn:1000001",
        "tgn:7012149",
        "tgn:7007522",
        "tgn:7029392"
    ],
    "tgn:id":2365818,
    "tgn:name":"Grenada Lake",
    "tgn:placetype":[
        "aat:300006191"
    ]
},
  "bbox": [],
  "geometry": {"coordinates":[-89.7667,33.8167],"type":"Point"}
}