{
  "id": 2723043,
  "type": "Feature",
  "properties": {
    "tgn:hierarchy":[
        "tgn:2723043",
        "tgn:1000001",
        "tgn:7012149",
        "tgn:2001148",
        "tgn:7007522",
        "tgn:7029392"
    ],
    "tgn:id":2723043,
    "tgn:name":"Tisdell Landing",
    "tgn:placetype":[
        "aat:300008347"
    ]
},
  "bbox": [],
  "geometry": {"coordinates":[-90.75,32.9167],"type":"Point"}
}