{
  "id": 2195161,
  "type": "Feature",
  "properties": {
    "tgn:hierarchy":[
        "tgn:2195161",
        "tgn:1000001",
        "tgn:1002738",
        "tgn:7012149",
        "tgn:7007565",
        "tgn:7029392"
    ],
    "tgn:id":2195161,
    "tgn:name":"Brindle Lake",
    "tgn:placetype":[
        "aat:300006191"
    ]
},
  "bbox": [],
  "geometry": {"coordinates":[-74.5167,40.0167],"type":"Point"}
}