{
  "id": 7212586,
  "type": "Feature",
  "properties": {
    "tgn:hierarchy":[
        "tgn:7212586",
        "tgn:1000003",
        "tgn:7003677",
        "tgn:7000084",
        "tgn:7029392"
    ],
    "tgn:id":7212586,
    "tgn:name":"Bocks-Berg",
    "tgn:placetype":[
        "aat:300008777"
    ]
},
  "bbox": [],
  "geometry": {"coordinates":[8.65,51.183333],"type":"Point"}
}