{
  "id": 2752740,
  "type": "Feature",
  "properties": {
    "tgn:hierarchy":[
        "tgn:2752740",
        "tgn:1000001",
        "tgn:7012149",
        "tgn:2001218",
        "tgn:7007523",
        "tgn:7029392"
    ],
    "tgn:id":2752740,
    "tgn:name":"Wataga",
    "tgn:placetype":[
        "aat:300008347"
    ]
},
  "bbox": [],
  "geometry": {"coordinates":[-93.6167,40.55],"type":"Point"}
}