{
  "id": 7513060,
  "type": "Feature",
  "properties": {
    "tgn:hierarchy":[
        "tgn:7513060",
        "tgn:7000508",
        "tgn:1008380",
        "tgn:1000226",
        "tgn:1000006",
        "tgn:7029392"
    ],
    "tgn:id":7513060,
    "tgn:name:en":"Hamiltons Gap",
    "tgn:placetype":[
        "aat:300008773"
    ]
},
  "bbox": [],
  "geometry": {"coordinates":[174.566667,-37.133333],"type":"Point"}
}