{
  "id": 7280963,
  "type": "Feature",
  "properties": {
    "tgn:hierarchy":[
        "tgn:7280963",
        "tgn:1001692",
        "tgn:1000049",
        "tgn:1000002",
        "tgn:7029392"
    ],
    "tgn:id":7280963,
    "tgn:name":"Tahuao Mall\u00edn, Estero",
    "tgn:placetype":[
        "aat:300008699"
    ]
},
  "bbox": [],
  "geometry": {"coordinates":[-71.083333,-38.333333],"type":"Point"}
}