{
  "id": 1003927,
  "type": "Feature",
  "properties": {
    "tgn:hierarchy":[
        "tgn:1003927",
        "tgn:1000004",
        "tgn:7000894",
        "tgn:1001032",
        "tgn:7004472",
        "tgn:1000120",
        "tgn:7029392"
    ],
    "tgn:id":1003927,
    "tgn:name":"Akatsutsumi",
    "tgn:placetype":[
        "aat:300000745"
    ]
},
  "bbox": [],
  "geometry": {"coordinates":[139.65,35.65],"type":"Point"}
}