{
  "id": 2613237,
  "type": "Feature",
  "properties": {
    "tgn:hierarchy":[
        "tgn:2613237",
        "tgn:1000001",
        "tgn:7012149",
        "tgn:2001119",
        "tgn:7007522",
        "tgn:7029392"
    ],
    "tgn:id":2613237,
    "tgn:name":"Reed Brake Branch",
    "tgn:placetype":[
        "aat:300008699"
    ]
},
  "bbox": [],
  "geometry": {"coordinates":[-89.3333,31.75],"type":"Point"}
}