{
  "id": 7289045,
  "type": "Feature",
  "properties": {
    "tgn:hierarchy":[
        "tgn:7289045",
        "tgn:1001630",
        "tgn:1000049",
        "tgn:1000002",
        "tgn:7029392"
    ],
    "tgn:id":7289045,
    "tgn:name":"Isla, Cerro de la",
    "tgn:placetype":[
        "aat:300008795"
    ]
},
  "bbox": [],
  "geometry": {"coordinates":[-68.683333,-25.766667],"type":"Point"}
}