{
  "id": 2111331,
  "type": "Feature",
  "properties": {
    "tgn:hierarchy":[
        "tgn:2111331",
        "tgn:1000001",
        "tgn:7012149",
        "tgn:2002194",
        "tgn:7007919",
        "tgn:7029392"
    ],
    "tgn:id":2111331,
    "tgn:name":"Fleenor Spring",
    "tgn:placetype":[
        "aat:300008347",
        "aat:300387210"
    ]
},
  "bbox": [],
  "geometry": {"coordinates":[-82.1333,36.6667],"type":"Point"}
}