<<<<<<< HEAD
{
  "id": 2332329,
  "type": "Feature",
  "properties": {
    "tgn:hierarchy":[
        "tgn:2332329",
        "tgn:1000001",
        "tgn:7012149",
        "tgn:2000226",
        "tgn:7007158",
        "tgn:7029392"
    ],
    "tgn:id":2332329,
    "tgn:name":"Floodwater Retention B-3 Reservoir",
    "tgn:placetype":[
        "aat:300006191"
    ]
},
  "bbox": [],
  "geometry": {"coordinates":[-104.9833,40.8],"type":"Point"}
}
=======
{"geometry":{"type":"Point","coordinates":[-104.983300,40.800000]},"type":"Feature","properties":{"hierarchy":["tgn:2332329","tgn:1000001","tgn:7012149","tgn:2000226","tgn:7007158","tgn:7029392"],"placetype":["aat:300006191"],"id":2332329,"name:xx":"Floodwater Retention B-3 Reservoir"}}
>>>>>>> 03f74aca74312dbeaf24d7e61306dd6a786dc3d0
