<<<<<<< HEAD
{
  "id": 2151558,
  "type": "Feature",
  "properties": {
    "tgn:hierarchy":[
        "tgn:2151558",
        "tgn:7006450",
        "tgn:1000001",
        "tgn:7012149",
        "tgn:2124005",
        "tgn:7029392"
    ],
    "tgn:id":2151558,
    "tgn:name":"Battery Creek",
    "tgn:placetype":[
        "aat:300008706"
    ]
},
  "bbox": [],
  "geometry": {"coordinates":[-165.4333,68.15],"type":"Point"}
}
=======
{"geometry":{"type":"Point","coordinates":[-165.433300,68.150000]},"type":"Feature","properties":{"hierarchy":["tgn:2151558","tgn:7006450","tgn:1000001","tgn:7012149","tgn:2124005","tgn:7029392"],"placetype":["aat:300008706"],"id":2151558,"name:xx":"Battery Creek"}}
>>>>>>> 03f74aca74312dbeaf24d7e61306dd6a786dc3d0
