{
  "id": 2397776,
  "type": "Feature",
  "properties": {
    "tgn:hierarchy":[
        "tgn:2397776",
        "tgn:1002648",
        "tgn:1000001",
        "tgn:7019158",
        "tgn:7012149",
        "tgn:7007249",
        "tgn:7029392"
    ],
    "tgn:id":2397776,
    "tgn:name":"Honomaele Gulch",
    "tgn:placetype":[
        "aat:300008761"
    ]
},
  "bbox": [],
  "geometry": {"coordinates":[-156.0667,20.75],"type":"Point"}
}