{
  "id": 2139161,
  "type": "Feature",
  "properties": {
    "tgn:hierarchy":[
        "tgn:2139161",
        "tgn:1000001",
        "tgn:7012149",
        "tgn:7007920",
        "tgn:7029392"
    ],
    "tgn:id":2139161,
    "tgn:name":"Ashnola River",
    "tgn:placetype":[
        "aat:300008707"
    ]
},
  "bbox": [],
  "geometry": {"coordinates":[-120.2333,48.8833],"type":"Point"}
}