{
  "id": 2097195,
  "type": "Feature",
  "properties": {
    "tgn:hierarchy":[
        "tgn:2097195",
        "tgn:1000001",
        "tgn:7012149",
        "tgn:2001828",
        "tgn:7007713",
        "tgn:7029392"
    ],
    "tgn:id":2097195,
    "tgn:name":"Fort Pierre",
    "tgn:placetype":[
        "aat:300008347"
    ]
},
  "bbox": [],
  "geometry": {"coordinates":[-100.3667,44.35],"type":"Point"}
}