{
  "id": 2185135,
  "type": "Feature",
  "properties": {
    "tgn:hierarchy":[
        "tgn:2185135",
        "tgn:1000001",
        "tgn:7012149",
        "tgn:7021746",
        "tgn:7007826",
        "tgn:7029392"
    ],
    "tgn:id":2185135,
    "tgn:name":"Boggy Branch",
    "tgn:placetype":[
        "aat:300008699"
    ]
},
  "bbox": [],
  "geometry": {"coordinates":[-97.3333,28.9833],"type":"Point"}
}