{
  "id": 1128069,
  "type": "Feature",
  "properties": {
    "tgn:hierarchy":[
        "tgn:1128069",
        "tgn:1000004",
        "tgn:7011457",
        "tgn:7014786",
        "tgn:7029392"
    ],
    "tgn:id":1128069,
    "tgn:name":"Olenty",
    "tgn:placetype":[
        "aat:300008707"
    ]
},
  "bbox": [],
  "geometry": {"coordinates":[52.0833,49.8333],"type":"Point"}
}