{
  "id": 7430901,
  "type": "Feature",
  "properties": {
    "tgn:hierarchy":[
        "tgn:7430901",
        "tgn:1000001",
        "tgn:7005595",
        "tgn:7005560",
        "tgn:7029392"
    ],
    "tgn:id":7430901,
    "tgn:name":"El Pl\u00e1tano",
    "tgn:placetype":[
        "aat:300008347"
    ]
},
  "bbox": [],
  "geometry": {"coordinates":[-107.516667,26.116667],"type":"Point"}
}