{
  "id": 7470504,
  "type": "Feature",
  "properties": {
    "tgn:hierarchy":[
        "tgn:7470504",
        "tgn:7488858",
        "tgn:1000004",
        "tgn:1000141",
        "tgn:7029392"
    ],
    "tgn:id":7470504,
    "tgn:name":"Beitoujiujie",
    "tgn:placetype":[
        "aat:300008347"
    ]
},
  "bbox": [],
  "geometry": {"coordinates":[120.657585,23.984],"type":"Point"}
}