{
  "id": 2694845,
  "type": "Feature",
  "properties": {
    "tgn:hierarchy":[
        "tgn:2694845",
        "tgn:1000001",
        "tgn:2001424",
        "tgn:7012149",
        "tgn:7007564",
        "tgn:7029392"
    ],
    "tgn:id":2694845,
    "tgn:name":"Stickney, Mount",
    "tgn:placetype":[
        "aat:300008798"
    ]
},
  "bbox": [],
  "geometry": {"coordinates":[-71.45,44.2333],"type":"Point"}
}