{
  "id": 2688455,
  "type": "Feature",
  "properties": {
    "tgn:hierarchy":[
        "tgn:2688455",
        "tgn:1000001",
        "tgn:7012149",
        "tgn:1002567",
        "tgn:7007240",
        "tgn:7029392"
    ],
    "tgn:id":2688455,
    "tgn:name":"Spruce Lake",
    "tgn:placetype":[
        "aat:300008680"
    ]
},
  "bbox": [],
  "geometry": {"coordinates":[-81.4333,28.9333],"type":"Point"}
}