<<<<<<< HEAD
{
  "id": 2155425,
  "type": "Feature",
  "properties": {
    "tgn:hierarchy":[
        "tgn:2155425",
        "tgn:1000001",
        "tgn:7012149",
        "tgn:2000927",
        "tgn:7007515",
        "tgn:7029392"
    ],
    "tgn:id":2155425,
    "tgn:name":"Bear Pond",
    "tgn:placetype":[
        "aat:300008680"
    ]
},
  "bbox": [],
  "geometry": {"coordinates":[-68.7167,45.4333],"type":"Point"}
}
=======
{"geometry":{"type":"Point","coordinates":[-68.716700,45.433300]},"type":"Feature","properties":{"hierarchy":["tgn:2155425","tgn:1000001","tgn:7012149","tgn:2000927","tgn:7007515","tgn:7029392"],"placetype":["aat:300008680"],"id":2155425,"name:xx":"Bear Pond"}}
>>>>>>> 03f74aca74312dbeaf24d7e61306dd6a786dc3d0
