{
  "id": 7208071,
  "type": "Feature",
  "properties": {
    "tgn:hierarchy":[
        "tgn:7208071",
        "tgn:7003669",
        "tgn:1000003",
        "tgn:7000084",
        "tgn:7029392"
    ],
    "tgn:id":7208071,
    "tgn:name":"B\u00fcchenbach",
    "tgn:placetype":[
        "aat:300000745"
    ]
},
  "bbox": [],
  "geometry": {"coordinates":[10.966667,49.583333],"type":"Point"}
}