{
  "id": 7569216,
  "type": "Feature",
  "properties": {
    "tgn:hierarchy":[
        "tgn:7569216",
        "tgn:1000004",
        "tgn:7000198",
        "tgn:7016788",
        "tgn:7029392"
    ],
    "tgn:id":7569216,
    "tgn:name:en":"K\u0101chhota",
    "tgn:placetype":[
        "aat:300008347"
    ]
},
  "bbox": [],
  "geometry": {"coordinates":[75.545039,25.658199],"type":"Point"}
}