{
  "id": 2455269,
  "type": "Feature",
  "properties": {
    "tgn:hierarchy":[
        "tgn:2455269",
        "tgn:1000001",
        "tgn:7012149",
        "tgn:1002472",
        "tgn:7007568",
        "tgn:7029392"
    ],
    "tgn:id":2455269,
    "tgn:name":"Little Five",
    "tgn:placetype":[
        "aat:300008680"
    ]
},
  "bbox": [],
  "geometry": {"coordinates":[-74.9333,44.05],"type":"Point"}
}