{
  "id": 2414081,
  "type": "Feature",
  "properties": {
    "tgn:hierarchy":[
        "tgn:2414081",
        "tgn:1000001",
        "tgn:7012149",
        "tgn:2001457",
        "tgn:7007566",
        "tgn:7029392"
    ],
    "tgn:id":2414081,
    "tgn:name":"Iron King Prospect",
    "tgn:placetype":[
        "aat:300000390"
    ]
},
  "bbox": [],
  "geometry": {"coordinates":[-105.4667,36.7333],"type":"Point"}
}