{
  "id": 7498629,
  "type": "Feature",
  "properties": {
    "tgn:hierarchy":[
        "tgn:7498629",
        "tgn:1000957",
        "tgn:1000004",
        "tgn:1000141",
        "tgn:7029392"
    ],
    "tgn:id":7498629,
    "tgn:name":"Fumin Qiao",
    "tgn:placetype":[
        "aat:300007836"
    ]
},
  "bbox": [],
  "geometry": {"coordinates":[121.674071,25.132713],"type":"Point"}
}