{
  "id": 7413872,
  "type": "Feature",
  "properties": {
    "tgn:hierarchy":[
        "tgn:7413872",
        "tgn:1000001",
        "tgn:7005596",
        "tgn:7005560",
        "tgn:7029392"
    ],
    "tgn:id":7413872,
    "tgn:name:es":"Andr\u00e9s Quintana Roo",
    "tgn:placetype":[
        "aat:300008347"
    ]
},
  "bbox": [],
  "geometry": {"coordinates":[-93.008333,17.716667],"type":"Point"}
}