{
  "id": 2435661,
  "type": "Feature",
  "properties": {
    "tgn:hierarchy":[
        "tgn:2435661",
        "tgn:1000001",
        "tgn:7012149",
        "tgn:2000238",
        "tgn:7007158",
        "tgn:7029392"
    ],
    "tgn:id":2435661,
    "tgn:name":"Kester Sweet Ditch",
    "tgn:placetype":[
        "aat:300006075"
    ]
},
  "bbox": [],
  "geometry": {"coordinates":[-105.9833,39.0667],"type":"Point"}
}