{
  "id": 7509945,
  "type": "Feature",
  "properties": {
    "tgn:hierarchy":[
        "tgn:7509945",
        "tgn:1008380",
        "tgn:1000226",
        "tgn:7018426",
        "tgn:1000006",
        "tgn:7029392"
    ],
    "tgn:id":7509945,
    "tgn:name:en":"Te Puhi",
    "tgn:placetype":[
        "aat:300008777"
    ]
},
  "bbox": [],
  "geometry": {"coordinates":[175.15,-38.183333],"type":"Point"}
}