{
  "id": 7150384,
  "type": "Feature",
  "properties": {
    "tgn:hierarchy":[
        "tgn:7150384",
        "tgn:1000003",
        "tgn:7003676",
        "tgn:7000084",
        "tgn:7029392"
    ],
    "tgn:id":7150384,
    "tgn:name":"L\u00e4germarsch",
    "tgn:placetype":[
        "aat:300000206"
    ]
},
  "bbox": [],
  "geometry": {"coordinates":[7.283333,52.566667],"type":"Point"}
}