{
  "id": 7097336,
  "type": "Feature",
  "properties": {
    "tgn:hierarchy":[
        "tgn:7097336",
        "tgn:1000003",
        "tgn:7003687",
        "tgn:7000084",
        "tgn:7029392"
    ],
    "tgn:id":7097336,
    "tgn:name":"Siptenfelde",
    "tgn:placetype":[
        "aat:300008347"
    ]
},
  "bbox": [],
  "geometry": {"coordinates":[11.066667,51.65],"type":"Point"}
}