<<<<<<< HEAD
{
  "id": 2330459,
  "type": "Feature",
  "properties": {
    "tgn:hierarchy":[
        "tgn:2330459",
        "tgn:1002541",
        "tgn:1000001",
        "tgn:7012149",
        "tgn:7007711",
        "tgn:7029392"
    ],
    "tgn:id":2330459,
    "tgn:name":"Flat Cove",
    "tgn:placetype":[
        "aat:300132316"
    ]
},
  "bbox": [],
  "geometry": {"coordinates":[-71.4,41.6167],"type":"Point"}
}
=======
{"geometry":{"type":"Point","coordinates":[-71.400000,41.616700]},"type":"Feature","properties":{"hierarchy":["tgn:2330459","tgn:1002541","tgn:1000001","tgn:7012149","tgn:7007711","tgn:7029392"],"placetype":["aat:300132316"],"id":2330459,"name:xx":"Flat Cove"}}
>>>>>>> 03f74aca74312dbeaf24d7e61306dd6a786dc3d0
