{
  "id": 2389941,
  "type": "Feature",
  "properties": {
    "tgn:hierarchy":[
        "tgn:2389941",
        "tgn:1000001",
        "tgn:7016102",
        "tgn:7012149",
        "tgn:7007516",
        "tgn:7029392"
    ],
    "tgn:id":2389941,
    "tgn:name":"High Point",
    "tgn:placetype":[
        "aat:300008850"
    ]
},
  "bbox": [],
  "geometry": {"coordinates":[-76.1167,39.4833],"type":"Point"}
}