{
  "id": 7464554,
  "type": "Feature",
  "properties": {
    "tgn:hierarchy":[
        "tgn:7464554",
        "tgn:7019094",
        "tgn:7002444",
        "tgn:1000003",
        "tgn:7008591",
        "tgn:7029392"
    ],
    "tgn:id":7464554,
    "tgn:name:en":"Airds Bay",
    "tgn:placetype":[
        "aat:300132316"
    ]
},
  "bbox": [],
  "geometry": {"coordinates":[-5.233333,56.433333],"type":"Point"}
}