{
  "id": 7405080,
  "type": "Feature",
  "properties": {
    "tgn:hierarchy":[
        "tgn:7405080",
        "tgn:7005585",
        "tgn:1000001",
        "tgn:7005560",
        "tgn:7029392"
    ],
    "tgn:id":7405080,
    "tgn:name":"Nuevo Galeana",
    "tgn:placetype":[
        "aat:300008347"
    ]
},
  "bbox": [],
  "geometry": {"coordinates":[-100.625,18.558333],"type":"Point"}
}