{
  "id": 2184975,
  "type": "Feature",
  "properties": {
    "tgn:hierarchy":[
        "tgn:2184975",
        "tgn:1000001",
        "tgn:7021603",
        "tgn:7012149",
        "tgn:7007240",
        "tgn:7029392"
    ],
    "tgn:id":2184975,
    "tgn:name":"Boggess Lake",
    "tgn:placetype":[
        "aat:300008680"
    ]
},
  "bbox": [],
  "geometry": {"coordinates":[-81.9833,27.0333],"type":"Point"}
}