{
  "id": 7388419,
  "type": "Feature",
  "properties": {
    "tgn:hierarchy":[
        "tgn:7388419",
        "tgn:7016644",
        "tgn:1000001",
        "tgn:7005560",
        "tgn:7029392"
    ],
    "tgn:id":7388419,
    "tgn:name":"Potrero Grande",
    "tgn:placetype":[
        "aat:300008347"
    ]
},
  "bbox": [],
  "geometry": {"coordinates":[-104.083333,19.333333],"type":"Point"}
}