{
  "id": 2543663,
  "type": "Feature",
  "properties": {
    "tgn:hierarchy":[
        "tgn:2543663",
        "tgn:1002300",
        "tgn:1000001",
        "tgn:7012149",
        "tgn:7007564",
        "tgn:7029392"
    ],
    "tgn:id":2543663,
    "tgn:name":"North Baldface",
    "tgn:placetype":[
        "aat:300008798"
    ]
},
  "bbox": [],
  "geometry": {"coordinates":[-71.0833,44.2333],"type":"Point"}
}