{
  "id": 2551152,
  "type": "Feature",
  "properties": {
    "tgn:hierarchy":[
        "tgn:2551152",
        "tgn:1000001",
        "tgn:7012149",
        "tgn:1002612",
        "tgn:7007710",
        "tgn:7029392"
    ],
    "tgn:id":2551152,
    "tgn:name":"Nuangola Outlet",
    "tgn:placetype":[
        "aat:300008699"
    ]
},
  "bbox": [],
  "geometry": {"coordinates":[-75.9667,41.15],"type":"Point"}
}