<<<<<<< HEAD
{
  "id": 7024979,
  "type": "Feature",
  "properties": {
    "tgn:hierarchy":[
        "tgn:7024979",
        "tgn:7002445",
        "tgn:7008103",
        "tgn:1000003",
        "tgn:7008591",
        "tgn:7029392"
    ],
    "tgn:id":7024979,
    "tgn:name":"Upper Shelton",
    "tgn:placetype":[
        "aat:300008347",
        "aat:300008372"
    ]
},
  "bbox": [],
  "geometry": {"coordinates":[-0.5333,52.0667],"type":"Point"}
}
=======
{"geometry":{"type":"Point","coordinates":[-0.533300,52.066700]},"type":"Feature","properties":{"hierarchy":["tgn:7024979","tgn:7002445","tgn:7008103","tgn:1000003","tgn:7008591","tgn:7029392"],"placetype":["aat:300008347","aat:300008372"],"id":7024979,"name:xx":"Upper Shelton"}}
>>>>>>> 03f74aca74312dbeaf24d7e61306dd6a786dc3d0
