{
  "id": 7008388,
  "type": "Feature",
  "properties": {
    "tgn:hierarchy":[
        "tgn:7008388",
        "tgn:1000003",
        "tgn:7001095",
        "tgn:1000070",
        "tgn:7029392"
    ],
    "tgn:id":7008388,
    "tgn:name":"Aubazines",
    "tgn:placetype":[
        "aat:300008347"
    ]
},
  "bbox": [],
  "geometry": {"coordinates":[1.6667,45.1833],"type":"Point"}
}