{
  "id": 2674600,
  "type": "Feature",
  "properties": {
    "tgn:hierarchy":[
        "tgn:2674600",
        "tgn:1000001",
        "tgn:7012149",
        "tgn:1002357",
        "tgn:7007706",
        "tgn:7029392"
    ],
    "tgn:id":2674600,
    "tgn:name":"Snyders Ditch",
    "tgn:placetype":[
        "aat:300006075"
    ]
},
  "bbox": [],
  "geometry": {"coordinates":[-82.8167,41.3167],"type":"Point"}
}