{
  "id": 1095907,
  "type": "Feature",
  "properties": {
    "tgn:hierarchy":[
        "tgn:1095907",
        "tgn:7001242",
        "tgn:1001461",
        "tgn:1000209",
        "tgn:7029392"
    ],
    "tgn:id":1095907,
    "tgn:name":"Chinsali",
    "tgn:placetype":[
        "aat:300008347"
    ]
},
  "bbox": [],
  "geometry": {"coordinates":[32.0833,-10.55],"type":"Point"}
}