{
  "id": 2598143,
  "type": "Feature",
  "properties": {
    "tgn:hierarchy":[
        "tgn:2598143",
        "tgn:1000001",
        "tgn:7012149",
        "tgn:2001289",
        "tgn:7007524",
        "tgn:7029392"
    ],
    "tgn:id":2598143,
    "tgn:name":"Preston",
    "tgn:placetype":[
        "aat:300008347"
    ]
},
  "bbox": [],
  "geometry": {"coordinates":[-111.35,46.7333],"type":"Point"}
}