{
  "id": 7385281,
  "type": "Feature",
  "properties": {
    "tgn:hierarchy":[
        "tgn:7385281",
        "tgn:1000001",
        "tgn:7005597",
        "tgn:7005560",
        "tgn:7029392"
    ],
    "tgn:id":7385281,
    "tgn:name":"Palmito",
    "tgn:placetype":[
        "aat:300008347"
    ]
},
  "bbox": [],
  "geometry": {"coordinates":[-97.716667,25.85],"type":"Point"}
}