<<<<<<< HEAD
{
  "id": 2766847,
  "type": "Feature",
  "properties": {
    "tgn:hierarchy":[
        "tgn:2766847",
        "tgn:1000001",
        "tgn:7012149",
        "tgn:7007524",
        "tgn:7029392"
    ],
    "tgn:id":2766847,
    "tgn:name":"White Pine Canyon",
    "tgn:placetype":[
        "aat:300008761"
    ]
},
  "bbox": [],
  "geometry": {"coordinates":[-109.55,48.2],"type":"Point"}
}
=======
{"geometry":{"type":"Point","coordinates":[-109.550000,48.200000]},"type":"Feature","properties":{"hierarchy":["tgn:2766847","tgn:1000001","tgn:7012149","tgn:7007524","tgn:7029392"],"placetype":["aat:300008761"],"id":2766847,"name:xx":"White Pine Canyon"}}
>>>>>>> 03f74aca74312dbeaf24d7e61306dd6a786dc3d0
