{
  "id": 7130435,
  "type": "Feature",
  "properties": {
    "tgn:hierarchy":[
        "tgn:7130435",
        "tgn:7003692",
        "tgn:1000003",
        "tgn:7000084",
        "tgn:7029392"
    ],
    "tgn:id":7130435,
    "tgn:name":"Mittelstenweiler",
    "tgn:placetype":[
        "aat:300008347"
    ]
},
  "bbox": [],
  "geometry": {"coordinates":[9.333333,47.75],"type":"Point"}
}