{
  "id": 7184175,
  "type": "Feature",
  "properties": {
    "tgn:hierarchy":[
        "tgn:7184175",
        "tgn:7003669",
        "tgn:1000003",
        "tgn:7000084",
        "tgn:7029392"
    ],
    "tgn:id":7184175,
    "tgn:name":"Greggenhofen",
    "tgn:placetype":[
        "aat:300008347"
    ]
},
  "bbox": [],
  "geometry": {"coordinates":[10.266667,47.566667],"type":"Point"}
}