{
  "id": 7544159,
  "type": "Feature",
  "properties": {
    "tgn:hierarchy":[
        "tgn:7544159",
        "tgn:7001242",
        "tgn:7016833",
        "tgn:1001079",
        "tgn:7029392"
    ],
    "tgn:id":7544159,
    "tgn:name:en":"Qaryat Bah\u012bj",
    "tgn:placetype":[
        "aat:300008347"
    ]
},
  "bbox": [],
  "geometry": {"coordinates":[29.605349,30.93459],"type":"Point"}
}