<<<<<<< HEAD
{
  "id": 2156495,
  "type": "Feature",
  "properties": {
    "tgn:hierarchy":[
        "tgn:2156495",
        "tgn:1000001",
        "tgn:7012149",
        "tgn:1002545",
        "tgn:7007157",
        "tgn:7029392"
    ],
    "tgn:id":2156495,
    "tgn:name":"Beartrap Creek",
    "tgn:placetype":[
        "aat:300008706"
    ]
},
  "bbox": [],
  "geometry": {"coordinates":[-118.4167,35.4667],"type":"Point"}
}
=======
{"geometry":{"type":"Point","coordinates":[-118.416700,35.466700]},"type":"Feature","properties":{"hierarchy":["tgn:2156495","tgn:1000001","tgn:7012149","tgn:1002545","tgn:7007157","tgn:7029392"],"placetype":["aat:300008706"],"id":2156495,"name:xx":"Beartrap Creek"}}
>>>>>>> 03f74aca74312dbeaf24d7e61306dd6a786dc3d0
