{
  "id": 2159764,
  "type": "Feature",
  "properties": {
    "tgn:hierarchy":[
        "tgn:2159764",
        "tgn:1000001",
        "tgn:7012149",
        "tgn:2000789",
        "tgn:7007255",
        "tgn:7029392"
    ],
    "tgn:id":2159764,
    "tgn:name":"Beech Branch",
    "tgn:placetype":[
        "aat:300008699"
    ]
},
  "bbox": [],
  "geometry": {"coordinates":[-82.8167,37.6167],"type":"Point"}
}