<<<<<<< HEAD
{
  "id": 2159764,
  "type": "Feature",
  "properties": {
    "tgn:hierarchy":[
        "tgn:2159764",
        "tgn:1000001",
        "tgn:7012149",
        "tgn:2000789",
        "tgn:7007255",
        "tgn:7029392"
    ],
    "tgn:id":2159764,
    "tgn:name":"Beech Branch",
    "tgn:placetype":[
        "aat:300008699"
    ]
},
  "bbox": [],
  "geometry": {"coordinates":[-82.8167,37.6167],"type":"Point"}
}
=======
{"geometry":{"type":"Point","coordinates":[-82.816700,37.616700]},"type":"Feature","properties":{"hierarchy":["tgn:2159764","tgn:1000001","tgn:7012149","tgn:2000789","tgn:7007255","tgn:7029392"],"placetype":["aat:300008699"],"id":2159764,"name:xx":"Beech Branch"}}
>>>>>>> 03f74aca74312dbeaf24d7e61306dd6a786dc3d0
