{
  "id": 2676048,
  "type": "Feature",
  "properties": {
    "tgn:hierarchy":[
        "tgn:2676048",
        "tgn:1000001",
        "tgn:7012149",
        "tgn:7014510",
        "tgn:7007920",
        "tgn:7029392"
    ],
    "tgn:id":2676048,
    "tgn:name":"Sorenson Creek",
    "tgn:placetype":[
        "aat:300008706"
    ]
},
  "bbox": [],
  "geometry": {"coordinates":[-122.0833,48.4333],"type":"Point"}
}