{
  "id": 7055220,
  "type": "Feature",
  "properties": {
    "tgn:hierarchy":[
        "tgn:7055220",
        "tgn:7015163",
        "tgn:1000003",
        "tgn:7003121",
        "tgn:1000080",
        "tgn:7029392"
    ],
    "tgn:id":7055220,
    "tgn:name":"Orul\u00f2, Monte",
    "tgn:placetype":[
        "aat:300008795"
    ]
},
  "bbox": [],
  "geometry": {"coordinates":[9.133333,40.633333],"type":"Point"}
}