{
  "id": 1055413,
  "type": "Feature",
  "properties": {
    "tgn:hierarchy":[
        "tgn:1055413",
        "tgn:1000004",
        "tgn:1003417",
        "tgn:7018214",
        "tgn:7002435",
        "tgn:7029392"
    ],
    "tgn:id":1055413,
    "tgn:name":"Kochetovka",
    "tgn:placetype":[
        "aat:300008347"
    ]
},
  "bbox": [],
  "geometry": {"coordinates":[40.4833,52.9667],"type":"Point"}
}