{
  "id": 1094491,
  "type": "Feature",
  "properties": {
    "tgn:hierarchy":[
        "tgn:1094491",
        "tgn:7001242",
        "tgn:1000201",
        "tgn:1001368",
        "tgn:7029392"
    ],
    "tgn:id":1094491,
    "tgn:name":"Umm Ruwaba",
    "tgn:placetype":[
        "aat:300008347"
    ]
},
  "bbox": [],
  "geometry": {"coordinates":[31.3333,12.8333],"type":"Point"}
}