<<<<<<< HEAD
{
  "id": 2764114,
  "type": "Feature",
  "properties": {
    "tgn:hierarchy":[
        "tgn:2764114",
        "tgn:1000001",
        "tgn:7012149",
        "tgn:2000926",
        "tgn:7007515",
        "tgn:7029392"
    ],
    "tgn:id":2764114,
    "tgn:name":"Wheeler Island",
    "tgn:placetype":[
        "aat:300008791"
    ]
},
  "bbox": [],
  "geometry": {"coordinates":[-70.5333,44.5167],"type":"Point"}
}
=======
{"geometry":{"type":"Point","coordinates":[-70.533300,44.516700]},"type":"Feature","properties":{"hierarchy":["tgn:2764114","tgn:1000001","tgn:7012149","tgn:2000926","tgn:7007515","tgn:7029392"],"placetype":["aat:300008791"],"id":2764114,"name:xx":"Wheeler Island"}}
>>>>>>> 03f74aca74312dbeaf24d7e61306dd6a786dc3d0
