<<<<<<< HEAD
{
  "id": 2156871,
  "type": "Feature",
  "properties": {
    "tgn:hierarchy":[
        "tgn:2156871",
        "tgn:1000001",
        "tgn:7016172",
        "tgn:7012149",
        "tgn:2000164",
        "tgn:7029392"
    ],
    "tgn:id":2156871,
    "tgn:name":"Beauchamp Branch",
    "tgn:placetype":[
        "aat:300008699"
    ]
},
  "bbox": [],
  "geometry": {"coordinates":[-92.4833,34.7167],"type":"Point"}
}
=======
{"geometry":{"type":"Point","coordinates":[-92.483300,34.716700]},"type":"Feature","properties":{"hierarchy":["tgn:2156871","tgn:1000001","tgn:7016172","tgn:7012149","tgn:2000164","tgn:7029392"],"placetype":["aat:300008699"],"id":2156871,"name:xx":"Beauchamp Branch"}}
>>>>>>> 03f74aca74312dbeaf24d7e61306dd6a786dc3d0
