{
  "id": 7235776,
  "type": "Feature",
  "properties": {
    "tgn:hierarchy":[
        "tgn:7235776",
        "tgn:7002715",
        "tgn:7002731",
        "tgn:1000003",
        "tgn:1000074",
        "tgn:7029392"
    ],
    "tgn:id":7235776,
    "tgn:name":"Apollon\u00eda",
    "tgn:placetype":[
        "aat:300008347"
    ]
},
  "bbox": [],
  "geometry": {"coordinates":[23.483333,40.65],"type":"Point"}
}