<<<<<<< HEAD
{
  "id": 2250234,
  "type": "Feature",
  "properties": {
    "tgn:hierarchy":[
        "tgn:2250234",
        "tgn:1000001",
        "tgn:7012149",
        "tgn:2002371",
        "tgn:7007923",
        "tgn:7029392"
    ],
    "tgn:id":2250234,
    "tgn:name":"Collins Place",
    "tgn:placetype":[
        "aat:300008347"
    ]
},
  "bbox": [],
  "geometry": {"coordinates":[-109.0833,43.5167],"type":"Point"}
}
=======
{"geometry":{"type":"Point","coordinates":[-109.083300,43.516700]},"type":"Feature","properties":{"hierarchy":["tgn:2250234","tgn:1000001","tgn:7012149","tgn:2002371","tgn:7007923","tgn:7029392"],"placetype":["aat:300008347"],"id":2250234,"name:xx":"Collins Place"}}
>>>>>>> 03f74aca74312dbeaf24d7e61306dd6a786dc3d0
