{
  "id": 1005468,
  "type": "Feature",
  "properties": {
    "tgn:hierarchy":[
        "tgn:1005468",
        "tgn:7003321",
        "tgn:7003030",
        "tgn:1000003",
        "tgn:1000062",
        "tgn:7029392"
    ],
    "tgn:id":1005468,
    "tgn:name":"Rothneusiedl",
    "tgn:placetype":[
        "aat:300000874"
    ]
},
  "bbox": [],
  "geometry": {"coordinates":[16.3833,48.1333],"type":"Point"}
}