{
  "id": 7417338,
  "type": "Feature",
  "properties": {
    "tgn:hierarchy":[
        "tgn:7417338",
        "tgn:1000001",
        "tgn:7005591",
        "tgn:7005560",
        "tgn:7029392"
    ],
    "tgn:id":7417338,
    "tgn:name:es":"Yutacuite, R\u00edo",
    "tgn:placetype":[
        "aat:300008699"
    ]
},
  "bbox": [],
  "geometry": {"coordinates":[-98.156111,16.343611],"type":"Point"}
}