{
  "id": 7045939,
  "type": "Feature",
  "properties": {
    "tgn:hierarchy":[
        "tgn:7045939",
        "tgn:7015163",
        "tgn:1000003",
        "tgn:7003121",
        "tgn:1000080",
        "tgn:7029392"
    ],
    "tgn:id":7045939,
    "tgn:name":"Conca, Riu sa",
    "tgn:placetype":[
        "aat:300008699"
    ]
},
  "bbox": [],
  "geometry": {"coordinates":[9.216667,40.75],"type":"Point"}
}