{
  "id": 7140338,
  "type": "Feature",
  "properties": {
    "tgn:hierarchy":[
        "tgn:7140338",
        "tgn:7003669",
        "tgn:1000003",
        "tgn:7000084",
        "tgn:7029392"
    ],
    "tgn:id":7140338,
    "tgn:name":"Lindach",
    "tgn:placetype":[
        "aat:300000206"
    ]
},
  "bbox": [],
  "geometry": {"coordinates":[12.716667,48.066667],"type":"Point"}
}