{
  "id": 2689487,
  "type": "Feature",
  "properties": {
    "tgn:hierarchy":[
        "tgn:2689487",
        "tgn:1000001",
        "tgn:1002221",
        "tgn:7012149",
        "tgn:7007251",
        "tgn:7029392"
    ],
    "tgn:id":2689487,
    "tgn:name":"Squaw Island",
    "tgn:placetype":[
        "aat:300008791"
    ]
},
  "bbox": [],
  "geometry": {"coordinates":[-90.4833,38.9333],"type":"Point"}
}