{
  "id": 2418618,
  "type": "Feature",
  "properties": {
    "tgn:hierarchy":[
        "tgn:2418618",
        "tgn:1000001",
        "tgn:7012149",
        "tgn:2000846",
        "tgn:7007255",
        "tgn:7029392"
    ],
    "tgn:id":2418618,
    "tgn:name":"Jake Fork",
    "tgn:placetype":[
        "aat:300008699"
    ]
},
  "bbox": [],
  "geometry": {"coordinates":[-88.0667,36.85],"type":"Point"}
}