{
  "id": 1043044,
  "type": "Feature",
  "properties": {
    "tgn:hierarchy":[
        "tgn:1043044",
        "tgn:7001198",
        "tgn:7003482",
        "tgn:1000003",
        "tgn:1000078",
        "tgn:7029392"
    ],
    "tgn:id":1043044,
    "tgn:name":"Tulsk",
    "tgn:placetype":[
        "aat:300008347"
    ]
},
  "bbox": [],
  "geometry": {"coordinates":[-8.25,53.7833],"type":"Point"}
}