{
  "id": 2302562,
  "type": "Feature",
  "properties": {
    "tgn:hierarchy":[
        "tgn:2302562",
        "tgn:1000001",
        "tgn:7012149",
        "tgn:2001719",
        "tgn:7007708",
        "tgn:7029392"
    ],
    "tgn:id":2302562,
    "tgn:name":"Dutton Canyon",
    "tgn:placetype":[
        "aat:300008761"
    ]
},
  "bbox": [],
  "geometry": {"coordinates":[-119.5667,45.3333],"type":"Point"}
}