{
  "id": 7415103,
  "type": "Feature",
  "properties": {
    "tgn:hierarchy":[
        "tgn:7415103",
        "tgn:1000001",
        "tgn:7005591",
        "tgn:7005560",
        "tgn:7029392"
    ],
    "tgn:id":7415103,
    "tgn:name:es":"San Antonio Nouaxico",
    "tgn:placetype":[
        "aat:300008347"
    ]
},
  "bbox": [],
  "geometry": {"coordinates":[-97.729167,17.3975],"type":"Point"}
}