{
  "id": 2598407,
  "type": "Feature",
  "properties": {
    "tgn:hierarchy":[
        "tgn:2598407",
        "tgn:1000001",
        "tgn:7012149",
        "tgn:7007826",
        "tgn:7029392"
    ],
    "tgn:id":2598407,
    "tgn:name":"Price Branch",
    "tgn:placetype":[
        "aat:300008699"
    ]
},
  "bbox": [],
  "geometry": {"coordinates":[-95.65,32.35],"type":"Point"}
}