{
  "id": 7408852,
  "type": "Feature",
  "properties": {
    "tgn:hierarchy":[
        "tgn:7408852",
        "tgn:1000001",
        "tgn:7005590",
        "tgn:7005560",
        "tgn:7029392"
    ],
    "tgn:id":7408852,
    "tgn:name":"Cuanajillo",
    "tgn:placetype":[
        "aat:300008347"
    ]
},
  "bbox": [],
  "geometry": {"coordinates":[-101.340278,19.65],"type":"Point"}
}