{
  "id": 2565343,
  "type": "Feature",
  "properties": {
    "tgn:hierarchy":[
        "tgn:2565343",
        "tgn:1000001",
        "tgn:7012149",
        "tgn:2000966",
        "tgn:7007520",
        "tgn:7029392"
    ],
    "tgn:id":2565343,
    "tgn:name":"Paint Lake",
    "tgn:placetype":[
        "aat:300008680"
    ]
},
  "bbox": [],
  "geometry": {"coordinates":[-88.8833,46.35],"type":"Point"}
}