{
  "id": 7511960,
  "type": "Feature",
  "properties": {
    "tgn:hierarchy":[
        "tgn:7511960",
        "tgn:1008380",
        "tgn:7000507",
        "tgn:1000226",
        "tgn:1000006",
        "tgn:7029392"
    ],
    "tgn:id":7511960,
    "tgn:name:en":"Kaingaroa",
    "tgn:placetype":[
        "aat:300008347"
    ]
},
  "bbox": [],
  "geometry": {"coordinates":[173.333333,-35.033333],"type":"Point"}
}