{
  "id": 7551927,
  "type": "Feature",
  "properties": {
    "tgn:hierarchy":[
        "tgn:7551927",
        "tgn:1000004",
        "tgn:7000198",
        "tgn:1001894",
        "tgn:7029392"
    ],
    "tgn:id":7551927,
    "tgn:name:en":"Br\u0101hmangaon",
    "tgn:placetype":[
        "aat:300008347"
    ]
},
  "bbox": [],
  "geometry": {"coordinates":[75.284891,22.119922],"type":"Point"}
}