{
  "id": 7492015,
  "type": "Feature",
  "properties": {
    "tgn:hierarchy":[
        "tgn:7492015",
        "tgn:1000004",
        "tgn:7471332",
        "tgn:1000141",
        "tgn:7029392"
    ],
    "tgn:id":7492015,
    "tgn:name":"Shuiweigou Qiao",
    "tgn:placetype":[
        "aat:300007836"
    ]
},
  "bbox": [],
  "geometry": {"coordinates":[120.9825,24.760278],"type":"Point"}
}