{
  "id": 1077956,
  "type": "Feature",
  "properties": {
    "tgn:hierarchy":[
        "tgn:1077956",
        "tgn:1000004",
        "tgn:1001549",
        "tgn:1000116",
        "tgn:7029392"
    ],
    "tgn:id":1077956,
    "tgn:name":"Laloa",
    "tgn:placetype":[
        "aat:300008347"
    ]
},
  "bbox": [],
  "geometry": {"coordinates":[121.8667,-4.85],"type":"Point"}
}