<<<<<<< HEAD
{
  "id": 7113662,
  "type": "Feature",
  "properties": {
    "tgn:hierarchy":[
        "tgn:7113662",
        "tgn:1000003",
        "tgn:7003687",
        "tgn:7000084",
        "tgn:7029392"
    ],
    "tgn:id":7113662,
    "tgn:name":"Vorwerk R\u00f6del",
    "tgn:placetype":[
        "aat:300000206"
    ]
},
  "bbox": [],
  "geometry": {"coordinates":[11.75,51.2],"type":"Point"}
}
=======
{"geometry":{"type":"Point","coordinates":[11.750000,51.200000]},"type":"Feature","properties":{"hierarchy":["tgn:7113662","tgn:1000003","tgn:7003687","tgn:7000084","tgn:7029392"],"placetype":["aat:300000206"],"id":7113662,"name:xx":"Vorwerk R\u00f6del"}}
>>>>>>> 03f74aca74312dbeaf24d7e61306dd6a786dc3d0
