{
  "id": 2532387,
  "type": "Feature",
  "properties": {
    "tgn:hierarchy":[
        "tgn:2532387",
        "tgn:1000001",
        "tgn:7012149",
        "tgn:1002993",
        "tgn:7007568",
        "tgn:7029392"
    ],
    "tgn:id":2532387,
    "tgn:name":"Murdock Mountain",
    "tgn:placetype":[
        "aat:300008798"
    ]
},
  "bbox": [],
  "geometry": {"coordinates":[-73.45,43.2167],"type":"Point"}
}