{
  "id": 2447375,
  "type": "Feature",
  "properties": {
    "tgn:hierarchy":[
        "tgn:2447375",
        "tgn:1000001",
        "tgn:7012149",
        "tgn:1002370",
        "tgn:7007252",
        "tgn:7029392"
    ],
    "tgn:id":2447375,
    "tgn:name":"Lick Creek",
    "tgn:placetype":[
        "aat:300008706"
    ]
},
  "bbox": [],
  "geometry": {"coordinates":[-85.8333,39.7333],"type":"Point"}
}