{
  "id": 2634992,
  "type": "Feature",
  "properties": {
    "tgn:hierarchy":[
        "tgn:2634992",
        "tgn:1000001",
        "tgn:7012149",
        "tgn:1002561",
        "tgn:7007252",
        "tgn:7029392"
    ],
    "tgn:id":2634992,
    "tgn:name":"Ryden Lakes",
    "tgn:placetype":[
        "aat:300008680"
    ]
},
  "bbox": [],
  "geometry": {"coordinates":[-86.8167,41.6167],"type":"Point"}
}