<<<<<<< HEAD
{
  "id": 7350195,
  "type": "Feature",
  "properties": {
    "tgn:hierarchy":[
        "tgn:7350195",
        "tgn:1000001",
        "tgn:7005592",
        "tgn:7005560",
        "tgn:7029392"
    ],
    "tgn:id":7350195,
    "tgn:name":"Ahuatelco",
    "tgn:placetype":[
        "aat:300008347"
    ]
},
  "bbox": [],
  "geometry": {"coordinates":[-98.716667,18.8],"type":"Point"}
}
=======
{"geometry":{"type":"Point","coordinates":[-98.716667,18.800000]},"type":"Feature","properties":{"hierarchy":["tgn:7350195","tgn:1000001","tgn:7005592","tgn:7005560","tgn:7029392"],"placetype":["aat:300008347"],"id":7350195,"name:xx":"Ahuatelco"}}
>>>>>>> 03f74aca74312dbeaf24d7e61306dd6a786dc3d0
