{
  "id": 7333704,
  "type": "Feature",
  "properties": {
    "tgn:hierarchy":[
        "tgn:7333704",
        "tgn:7002758",
        "tgn:7002817",
        "tgn:1000003",
        "tgn:1000095",
        "tgn:7029392"
    ],
    "tgn:id":7333704,
    "tgn:name":"Escoboso, Cerro",
    "tgn:placetype":[
        "aat:300008777"
    ]
},
  "bbox": [],
  "geometry": {"coordinates":[-5.05,37.95],"type":"Point"}
}