<<<<<<< HEAD
{
  "id": 2765047,
  "type": "Feature",
  "properties": {
    "tgn:hierarchy":[
        "tgn:2765047",
        "tgn:1000001",
        "tgn:7012149",
        "tgn:2001067",
        "tgn:7007521",
        "tgn:7029392"
    ],
    "tgn:id":2765047,
    "tgn:name":"Whisky Jack Lake",
    "tgn:placetype":[
        "aat:300008680"
    ]
},
  "bbox": [],
  "geometry": {"coordinates":[-91.8667,48.1],"type":"Point"}
}
=======
{"geometry":{"type":"Point","coordinates":[-91.866700,48.100000]},"type":"Feature","properties":{"hierarchy":["tgn:2765047","tgn:1000001","tgn:7012149","tgn:2001067","tgn:7007521","tgn:7029392"],"placetype":["aat:300008680"],"id":2765047,"name:xx":"Whisky Jack Lake"}}
>>>>>>> 03f74aca74312dbeaf24d7e61306dd6a786dc3d0
