{
  "id": 2768024,
  "type": "Feature",
  "properties": {
    "tgn:hierarchy":[
        "tgn:2768024",
        "tgn:1000001",
        "tgn:7012149",
        "tgn:2001892",
        "tgn:7007825",
        "tgn:7029392"
    ],
    "tgn:id":2768024,
    "tgn:name":"Whiteoak Saltpeter Cave",
    "tgn:placetype":[
        "aat:300008746"
    ]
},
  "bbox": [],
  "geometry": {"coordinates":[-85.9833,36.55],"type":"Point"}
}