{
  "id": 2713129,
  "type": "Feature",
  "properties": {
    "tgn:hierarchy":[
        "tgn:2713129",
        "tgn:1000001",
        "tgn:7012149",
        "tgn:1002990",
        "tgn:7007708",
        "tgn:7029392"
    ],
    "tgn:id":2713129,
    "tgn:name":"Taylor Point",
    "tgn:placetype":[
        "aat:300008850"
    ]
},
  "bbox": [],
  "geometry": {"coordinates":[-120.65,45.0167],"type":"Point"}
}