{
  "id": 2656383,
  "type": "Feature",
  "properties": {
    "tgn:hierarchy":[
        "tgn:2656383",
        "tgn:1000001",
        "tgn:7006451",
        "tgn:2000092",
        "tgn:7012149",
        "tgn:7029392"
    ],
    "tgn:id":2656383,
    "tgn:name":"Sheba Temple",
    "tgn:placetype":[
        "aat:300008798"
    ]
},
  "bbox": [],
  "geometry": {"coordinates":[-111.9167,36.05],"type":"Point"}
}