{
  "id": 2508646,
  "type": "Feature",
  "properties": {
    "tgn:hierarchy":[
        "tgn:2508646",
        "tgn:1000001",
        "tgn:7012149",
        "tgn:2001981",
        "tgn:7007826",
        "tgn:7029392"
    ],
    "tgn:id":2508646,
    "tgn:name":"Middle Drain",
    "tgn:placetype":[
        "aat:300006075"
    ]
},
  "bbox": [],
  "geometry": {"coordinates":[-106.25,31.6167],"type":"Point"}
}