{
  "id": 2034935,
  "type": "Feature",
  "properties": {
    "tgn:hierarchy":[
        "tgn:2034935",
        "tgn:1000001",
        "tgn:7012149",
        "tgn:2000617",
        "tgn:7007253",
        "tgn:7029392"
    ],
    "tgn:id":2034935,
    "tgn:name":"Hiawatha",
    "tgn:placetype":[
        "aat:300008347"
    ]
},
  "bbox": [],
  "geometry": {"coordinates":[-91.6667,42.0333],"type":"Point"}
}