{
  "id": 7539281,
  "type": "Feature",
  "properties": {
    "tgn:hierarchy":[
        "tgn:7539281",
        "tgn:7001242",
        "tgn:7016833",
        "tgn:1001114",
        "tgn:7029392"
    ],
    "tgn:id":7539281,
    "tgn:name:en":"Maz\u012bnah",
    "tgn:placetype":[
        "aat:300008347"
    ]
},
  "bbox": [],
  "geometry": {"coordinates":[30.833333,27.516667],"type":"Point"}
}