{
  "id": 2548111,
  "type": "Feature",
  "properties": {
    "tgn:hierarchy":[
        "tgn:2548111",
        "tgn:1000001",
        "tgn:7006451",
        "tgn:7012149",
        "tgn:2000103",
        "tgn:7029392"
    ],
    "tgn:id":2548111,
    "tgn:name":"North Hole",
    "tgn:placetype":[
        "aat:300386845"
    ]
},
  "bbox": [],
  "geometry": {"coordinates":[-111.8667,34.4833],"type":"Point"}
}