{
  "id": 2730415,
  "type": "Feature",
  "properties": {
    "tgn:hierarchy":[
        "tgn:2730415",
        "tgn:1000001",
        "tgn:2000307",
        "tgn:7012149",
        "tgn:7007248",
        "tgn:7029392"
    ],
    "tgn:id":2730415,
    "tgn:name":"Truckers",
    "tgn:placetype":[
        "aat:300008347"
    ]
},
  "bbox": [],
  "geometry": {"coordinates":[-81.6333,32.35],"type":"Point"}
}