<<<<<<< HEAD
{
  "id": 7485646,
  "type": "Feature",
  "properties": {
    "tgn:hierarchy":[
        "tgn:7485646",
        "tgn:1000004",
        "tgn:7490934",
        "tgn:1000141",
        "tgn:7029392"
    ],
    "tgn:id":7485646,
    "tgn:name":"Dijiu Gongmu",
    "tgn:placetype":[
        "aat:300266755"
    ]
},
  "bbox": [],
  "geometry": {"coordinates":[120.255833,22.937778],"type":"Point"}
}
=======
{"geometry":{"type":"Point","coordinates":[120.255833,22.937778]},"type":"Feature","properties":{"hierarchy":["tgn:7485646","tgn:1000004","tgn:7490934","tgn:1000141","tgn:7029392"],"placetype":["aat:300266755"],"id":7485646,"name:xx":"Dijiu Gongmu"}}
>>>>>>> 03f74aca74312dbeaf24d7e61306dd6a786dc3d0
