<<<<<<< HEAD
{
  "id": 7479109,
  "type": "Feature",
  "properties": {
    "tgn:hierarchy":[
        "tgn:7479109",
        "tgn:1000004",
        "tgn:7490934",
        "tgn:1000141",
        "tgn:7029392"
    ],
    "tgn:id":7479109,
    "tgn:name":"Fenglizhai",
    "tgn:placetype":[
        "aat:300008347"
    ]
},
  "bbox": [],
  "geometry": {"coordinates":[120.36404,23.056685],"type":"Point"}
}
=======
{"geometry":{"type":"Point","coordinates":[120.364040,23.056685]},"type":"Feature","properties":{"hierarchy":["tgn:7479109","tgn:1000004","tgn:7490934","tgn:1000141","tgn:7029392"],"placetype":["aat:300008347"],"id":7479109,"name:xx":"Fenglizhai"}}
>>>>>>> 03f74aca74312dbeaf24d7e61306dd6a786dc3d0
