<<<<<<< HEAD
{
  "id": 7023747,
  "type": "Feature",
  "properties": {
    "tgn:hierarchy":[
        "tgn:7023747",
        "tgn:1000001",
        "tgn:7012149",
        "tgn:7029392"
    ],
    "tgn:id":7023747,
    "tgn:name":"Thorofare Island",
    "tgn:placetype":[
        "aat:300008791"
    ]
},
  "bbox": [],
  "geometry": {"coordinates":[-75.9833,37.8667],"type":"Point"}
}
=======
{"geometry":{"type":"Point","coordinates":[-75.983300,37.866700]},"type":"Feature","properties":{"hierarchy":["tgn:7023747","tgn:1000001","tgn:7012149","tgn:7029392"],"placetype":["aat:300008791"],"id":7023747,"name:xx":"Thorofare Island"}}
>>>>>>> 03f74aca74312dbeaf24d7e61306dd6a786dc3d0
