{
  "id": 2512390,
  "type": "Feature",
  "properties": {
    "tgn:hierarchy":[
        "tgn:2512390",
        "tgn:7002659",
        "tgn:1000001",
        "tgn:7012149",
        "tgn:2000047",
        "tgn:7029392"
    ],
    "tgn:id":2512390,
    "tgn:name":"Mill Creek",
    "tgn:placetype":[
        "aat:300132316"
    ]
},
  "bbox": [],
  "geometry": {"coordinates":[-86.2167,34.4667],"type":"Point"}
}