{
  "id": 2458578,
  "type": "Feature",
  "properties": {
    "tgn:hierarchy":[
        "tgn:2458578",
        "tgn:1000001",
        "tgn:7012149",
        "tgn:1002943",
        "tgn:7007708",
        "tgn:7029392"
    ],
    "tgn:id":2458578,
    "tgn:name":"Little North Fork Wilson River",
    "tgn:placetype":[
        "aat:300008707"
    ]
},
  "bbox": [],
  "geometry": {"coordinates":[-123.6333,45.5667],"type":"Point"}
}