{
  "id": 7586076,
  "type": "Feature",
  "properties": {
    "tgn:hierarchy":[
        "tgn:7586076",
        "tgn:1000004",
        "tgn:7000198",
        "tgn:1001977",
        "tgn:7029392"
    ],
    "tgn:id":7586076,
    "tgn:name:en":"Begampur",
    "tgn:placetype":[
        "aat:300008347"
    ]
},
  "bbox": [],
  "geometry": {"coordinates":[88.25764,22.730698],"type":"Point"}
}