<<<<<<< HEAD
{
  "id": 2158173,
  "type": "Feature",
  "properties": {
    "tgn:hierarchy":[
        "tgn:2158173",
        "tgn:1000001",
        "tgn:7012149",
        "tgn:2000928",
        "tgn:7007515",
        "tgn:7029392"
    ],
    "tgn:id":2158173,
    "tgn:name":"Beaver Pond Ridge",
    "tgn:placetype":[
        "aat:300266640"
    ]
},
  "bbox": [],
  "geometry": {"coordinates":[-68.85,46.2667],"type":"Point"}
}
=======
{"geometry":{"type":"Point","coordinates":[-68.850000,46.266700]},"type":"Feature","properties":{"hierarchy":["tgn:2158173","tgn:1000001","tgn:7012149","tgn:2000928","tgn:7007515","tgn:7029392"],"placetype":["aat:300266640"],"id":2158173,"name:xx":"Beaver Pond Ridge"}}
>>>>>>> 03f74aca74312dbeaf24d7e61306dd6a786dc3d0
