{
  "id": 7466989,
  "type": "Feature",
  "properties": {
    "tgn:hierarchy":[
        "tgn:7466989",
        "tgn:7002445",
        "tgn:1000003",
        "tgn:7008129",
        "tgn:7008591",
        "tgn:7029392"
    ],
    "tgn:id":7466989,
    "tgn:name:en":"Birling Gap",
    "tgn:placetype":[
        "aat:300008805"
    ]
},
  "bbox": [],
  "geometry": {"coordinates":[0.183333,50.733333],"type":"Point"}
}