{
  "id": 2761488,
  "type": "Feature",
  "properties": {
    "tgn:hierarchy":[
        "tgn:2761488",
        "tgn:1000001",
        "tgn:7012149",
        "tgn:7007157",
        "tgn:2000190",
        "tgn:7029392"
    ],
    "tgn:id":2761488,
    "tgn:name":"West North Main Canal",
    "tgn:placetype":[
        "aat:300006075"
    ]
},
  "bbox": [],
  "geometry": {"coordinates":[-122.0333,39.95],"type":"Point"}
}