{
  "id": 2459521,
  "type": "Feature",
  "properties": {
    "tgn:hierarchy":[
        "tgn:2459521",
        "tgn:2124017",
        "tgn:7006450",
        "tgn:1000001",
        "tgn:7012149",
        "tgn:7029392"
    ],
    "tgn:id":2459521,
    "tgn:name":"Little Rabbit Creek",
    "tgn:placetype":[
        "aat:300008706"
    ]
},
  "bbox": [],
  "geometry": {"coordinates":[-149.6667,61.0333],"type":"Point"}
}