{
  "id": 2781230,
  "type": "Feature",
  "properties": {
    "tgn:hierarchy":[
        "tgn:2781230",
        "tgn:1000001",
        "tgn:7012149",
        "tgn:2001273",
        "tgn:7007524",
        "tgn:7029392"
    ],
    "tgn:id":2781230,
    "tgn:name":"Woodhawk Creek",
    "tgn:placetype":[
        "aat:300008706"
    ]
},
  "bbox": [],
  "geometry": {"coordinates":[-109.2333,47.7167],"type":"Point"}
}