{
  "id": 7101656,
  "type": "Feature",
  "properties": {
    "tgn:hierarchy":[
        "tgn:7101656",
        "tgn:1000003",
        "tgn:7003682",
        "tgn:7000084",
        "tgn:7029392"
    ],
    "tgn:id":7101656,
    "tgn:name":"Salz-Bach",
    "tgn:placetype":[
        "aat:300008699"
    ]
},
  "bbox": [],
  "geometry": {"coordinates":[8.05,50.466667],"type":"Point"}
}