{
  "id": 2770785,
  "type": "Feature",
  "properties": {
    "tgn:hierarchy":[
        "tgn:2770785",
        "tgn:1000001",
        "tgn:7012149",
        "tgn:1002446",
        "tgn:7007251",
        "tgn:7029392"
    ],
    "tgn:id":2770785,
    "tgn:name":"Wildcat Creek",
    "tgn:placetype":[
        "aat:300008706"
    ]
},
  "bbox": [],
  "geometry": {"coordinates":[-91.0833,40.5833],"type":"Point"}
}