{
  "id": 7496709,
  "type": "Feature",
  "properties": {
    "tgn:hierarchy":[
        "tgn:7496709",
        "tgn:1000004",
        "tgn:7001013",
        "tgn:1000141",
        "tgn:7029392"
    ],
    "tgn:id":7496709,
    "tgn:name":"Shangyunei",
    "tgn:placetype":[
        "aat:300008347"
    ]
},
  "bbox": [],
  "geometry": {"coordinates":[121.395061,24.78658],"type":"Point"}
}