<<<<<<< HEAD
{
  "id": 2152576,
  "type": "Feature",
  "properties": {
    "tgn:hierarchy":[
        "tgn:2152576",
        "tgn:1000001",
        "tgn:7012149",
        "tgn:2002377",
        "tgn:7007923",
        "tgn:7029392"
    ],
    "tgn:id":2152576,
    "tgn:name":"Bayer Draw",
    "tgn:placetype":[
        "aat:300008761"
    ]
},
  "bbox": [],
  "geometry": {"coordinates":[-106.5333,43.2],"type":"Point"}
}
=======
{"geometry":{"type":"Point","coordinates":[-106.533300,43.200000]},"type":"Feature","properties":{"hierarchy":["tgn:2152576","tgn:1000001","tgn:7012149","tgn:2002377","tgn:7007923","tgn:7029392"],"placetype":["aat:300008761"],"id":2152576,"name:xx":"Bayer Draw"}}
>>>>>>> 03f74aca74312dbeaf24d7e61306dd6a786dc3d0
