<<<<<<< HEAD
{
  "id": 2333740,
  "type": "Feature",
  "properties": {
    "tgn:hierarchy":[
        "tgn:2333740",
        "tgn:1000001",
        "tgn:7012149",
        "tgn:2000965",
        "tgn:7007520",
        "tgn:7029392"
    ],
    "tgn:id":2333740,
    "tgn:name":"Foote Dam Pond",
    "tgn:placetype":[
        "aat:300006191"
    ]
},
  "bbox": [],
  "geometry": {"coordinates":[-83.4333,44.4333],"type":"Point"}
}
=======
{"geometry":{"type":"Point","coordinates":[-83.433300,44.433300]},"type":"Feature","properties":{"hierarchy":["tgn:2333740","tgn:1000001","tgn:7012149","tgn:2000965","tgn:7007520","tgn:7029392"],"placetype":["aat:300006191"],"id":2333740,"name:xx":"Foote Dam Pond"}}
>>>>>>> 03f74aca74312dbeaf24d7e61306dd6a786dc3d0
