{
  "id": 4001508,
  "type": "Feature",
  "properties": {
    "tgn:hierarchy":[
        "tgn:4001508",
        "tgn:1000003",
        "tgn:1000443",
        "tgn:1000091",
        "tgn:7029392"
    ],
    "tgn:id":4001508,
    "tgn:name":"Biertan",
    "tgn:placetype":[
        "aat:300008347"
    ]
},
  "bbox": [],
  "geometry": {"coordinates":[24.5167,46.1333],"type":"Point"}
}