<<<<<<< HEAD
{
  "id": 2761539,
  "type": "Feature",
  "properties": {
    "tgn:hierarchy":[
        "tgn:2761539",
        "tgn:1000001",
        "tgn:7012149",
        "tgn:1003038",
        "tgn:7007517",
        "tgn:7029392"
    ],
    "tgn:id":2761539,
    "tgn:name":"West Oxford",
    "tgn:placetype":[
        "aat:300008347"
    ]
},
  "bbox": [],
  "geometry": {"coordinates":[-71.8833,42.1],"type":"Point"}
}
=======
{"geometry":{"type":"Point","coordinates":[-71.883300,42.100000]},"type":"Feature","properties":{"hierarchy":["tgn:2761539","tgn:1000001","tgn:7012149","tgn:1003038","tgn:7007517","tgn:7029392"],"placetype":["aat:300008347"],"id":2761539,"name:xx":"West Oxford"}}
>>>>>>> 03f74aca74312dbeaf24d7e61306dd6a786dc3d0
