{
  "id": 7436894,
  "type": "Feature",
  "properties": {
    "tgn:hierarchy":[
        "tgn:7436894",
        "tgn:7005581",
        "tgn:1000001",
        "tgn:7005560",
        "tgn:7029392"
    ],
    "tgn:id":7436894,
    "tgn:name":"Tarabillas, Cerro",
    "tgn:placetype":[
        "aat:300008795"
    ]
},
  "bbox": [],
  "geometry": {"coordinates":[-106.25,29.866667],"type":"Point"}
}