{
  "id": 7270852,
  "type": "Feature",
  "properties": {
    "tgn:hierarchy":[
        "tgn:7270852",
        "tgn:1000003",
        "tgn:7003622",
        "tgn:7016845",
        "tgn:7029392"
    ],
    "tgn:id":7270852,
    "tgn:name:nl":"Sint Pietershoeve",
    "tgn:placetype":[
        "aat:300000206"
    ]
},
  "bbox": [],
  "geometry": {"coordinates":[5.883333,51.483333],"type":"Point"}
}