{
  "id": 2170380,
  "type": "Feature",
  "properties": {
    "tgn:hierarchy":[
        "tgn:2170380",
        "tgn:1000001",
        "tgn:1002344",
        "tgn:7012149",
        "tgn:7007517",
        "tgn:7029392"
    ],
    "tgn:id":2170380,
    "tgn:name":"Big Rock",
    "tgn:placetype":[
        "aat:300387099",
        "aat:300011692"
    ]
},
  "bbox": [],
  "geometry": {"coordinates":[-70.6167,41.4667],"type":"Point"}
}