<<<<<<< HEAD
{
  "id": 7110001,
  "type": "Feature",
  "properties": {
    "tgn:hierarchy":[
        "tgn:7110001",
        "tgn:1000003",
        "tgn:7003678",
        "tgn:7000084",
        "tgn:7029392"
    ],
    "tgn:id":7110001,
    "tgn:name":"Reimenrod",
    "tgn:placetype":[
        "aat:300008347"
    ]
},
  "bbox": [],
  "geometry": {"coordinates":[9.433333,50.75],"type":"Point"}
}
=======
{"geometry":{"type":"Point","coordinates":[9.433333,50.750000]},"type":"Feature","properties":{"hierarchy":["tgn:7110001","tgn:1000003","tgn:7003678","tgn:7000084","tgn:7029392"],"placetype":["aat:300008347"],"id":7110001,"name:xx":"Reimenrod"}}
>>>>>>> 03f74aca74312dbeaf24d7e61306dd6a786dc3d0
