<<<<<<< HEAD
{
  "id": 2763714,
  "type": "Feature",
  "properties": {
    "tgn:hierarchy":[
        "tgn:2763714",
        "tgn:7013349",
        "tgn:1000001",
        "tgn:7012149",
        "tgn:7007708",
        "tgn:7029392"
    ],
    "tgn:id":2763714,
    "tgn:name":"Wham Whited Ditch",
    "tgn:placetype":[
        "aat:300006075"
    ]
},
  "bbox": [],
  "geometry": {"coordinates":[-118.2,44.4833],"type":"Point"}
}
=======
{"geometry":{"type":"Point","coordinates":[-118.200000,44.483300]},"type":"Feature","properties":{"hierarchy":["tgn:2763714","tgn:7013349","tgn:1000001","tgn:7012149","tgn:7007708","tgn:7029392"],"placetype":["aat:300006075"],"id":2763714,"name:xx":"Wham Whited Ditch"}}
>>>>>>> 03f74aca74312dbeaf24d7e61306dd6a786dc3d0
