{
  "id": 7577798,
  "type": "Feature",
  "properties": {
    "tgn:hierarchy":[
        "tgn:7577798",
        "tgn:1000004",
        "tgn:7000198",
        "tgn:7016694",
        "tgn:7029392"
    ],
    "tgn:id":7577798,
    "tgn:name:en":"Kull\u0101da",
    "tgn:placetype":[
        "aat:300008347"
    ]
},
  "bbox": [],
  "geometry": {"coordinates":[84.633333,19.966667],"type":"Point"}
}