{
  "id": 2641965,
  "type": "Feature",
  "properties": {
    "tgn:hierarchy":[
        "tgn:2641965",
        "tgn:1000001",
        "tgn:7012149",
        "tgn:2000837",
        "tgn:7007255",
        "tgn:7029392"
    ],
    "tgn:id":2641965,
    "tgn:name":"Sand Lick",
    "tgn:placetype":[
        "aat:300008699"
    ]
},
  "bbox": [],
  "geometry": {"coordinates":[-82.3667,37.6333],"type":"Point"}
}