{
  "id": 7512519,
  "type": "Feature",
  "properties": {
    "tgn:hierarchy":[
        "tgn:7512519",
        "tgn:7000509",
        "tgn:1008380",
        "tgn:1000226",
        "tgn:1000006",
        "tgn:7029392"
    ],
    "tgn:id":7512519,
    "tgn:name:en":"Horohoro",
    "tgn:placetype":[
        "aat:300008795"
    ]
},
  "bbox": [],
  "geometry": {"coordinates":[176.133333,-38.283333],"type":"Point"}
}