{
  "id": 2220302,
  "type": "Feature",
  "properties": {
    "tgn:hierarchy":[
        "tgn:2220302",
        "tgn:7006450",
        "tgn:2000069",
        "tgn:1000001",
        "tgn:7012149",
        "tgn:7029392"
    ],
    "tgn:id":2220302,
    "tgn:name":"Cape Algonquin",
    "tgn:placetype":[
        "aat:300008850"
    ]
},
  "bbox": [],
  "geometry": {"coordinates":[-166.9333,60.2167],"type":"Point"}
}