{
  "id": 7581280,
  "type": "Feature",
  "properties": {
    "tgn:hierarchy":[
        "tgn:7581280",
        "tgn:1000004",
        "tgn:7000198",
        "tgn:1001894",
        "tgn:7029392"
    ],
    "tgn:id":7581280,
    "tgn:name:en":"Sil\u0101ri",
    "tgn:placetype":[
        "aat:300008347"
    ]
},
  "bbox": [],
  "geometry": {"coordinates":[79.287875,21.57904],"type":"Point"}
}