{
  "id": 2030220,
  "type": "Feature",
  "properties": {
    "tgn:hierarchy":[
        "tgn:2030220",
        "tgn:1000001",
        "tgn:7012149",
        "tgn:1003024",
        "tgn:7007251",
        "tgn:7029392"
    ],
    "tgn:id":2030220,
    "tgn:name":"Spencer",
    "tgn:placetype":[
        "aat:300008347"
    ]
},
  "bbox": [],
  "geometry": {"coordinates":[-87.9333,41.4833],"type":"Point"}
}