<<<<<<< HEAD
{
  "id": 2339220,
  "type": "Feature",
  "properties": {
    "tgn:hierarchy":[
        "tgn:2339220",
        "tgn:1000001",
        "tgn:7012149",
        "tgn:2000211",
        "tgn:7007158",
        "tgn:7029392"
    ],
    "tgn:id":2339220,
    "tgn:name":"Franktown Parker FPE-9 Reservoir",
    "tgn:placetype":[
        "aat:300006191"
    ]
},
  "bbox": [],
  "geometry": {"coordinates":[-104.65,39.2],"type":"Point"}
}
=======
{"geometry":{"type":"Point","coordinates":[-104.650000,39.200000]},"type":"Feature","properties":{"hierarchy":["tgn:2339220","tgn:1000001","tgn:7012149","tgn:2000211","tgn:7007158","tgn:7029392"],"placetype":["aat:300006191"],"id":2339220,"name:xx":"Franktown Parker FPE-9 Reservoir"}}
>>>>>>> 03f74aca74312dbeaf24d7e61306dd6a786dc3d0
