{
  "id": 1129563,
  "type": "Feature",
  "properties": {
    "tgn:hierarchy":[
        "tgn:1129563",
        "tgn:1000050",
        "tgn:1000002",
        "tgn:7029392"
    ],
    "tgn:id":1129563,
    "tgn:name":"San Juan, R\u00edo",
    "tgn:placetype":[
        "aat:300008707"
    ]
},
  "bbox": [],
  "geometry": {"coordinates":[-77.443,4.047],"type":"Point"}
}