{
  "id": 7321295,
  "type": "Feature",
  "properties": {
    "tgn:hierarchy":[
        "tgn:7321295",
        "tgn:7002464",
        "tgn:1000049",
        "tgn:1000002",
        "tgn:7029392"
    ],
    "tgn:id":7321295,
    "tgn:name":"Buenaventura",
    "tgn:placetype":[
        "aat:300008347"
    ]
},
  "bbox": [],
  "geometry": {"coordinates":[-69.733333,-20.833333],"type":"Point"}
}