{
  "id": 7502633,
  "type": "Feature",
  "properties": {
    "tgn:hierarchy":[
        "tgn:7502633",
        "tgn:7487020",
        "tgn:1000004",
        "tgn:1000141",
        "tgn:7029392"
    ],
    "tgn:id":7502633,
    "tgn:name":"Tuoping",
    "tgn:placetype":[
        "aat:300008347"
    ]
},
  "bbox": [],
  "geometry": {"coordinates":[120.775591,24.473882],"type":"Point"}
}