{
  "id": 1055463,
  "type": "Feature",
  "properties": {
    "tgn:hierarchy":[
        "tgn:1055463",
        "tgn:7006640",
        "tgn:1000003",
        "tgn:7006540",
        "tgn:7029392"
    ],
    "tgn:id":1055463,
    "tgn:name:en":"Kohila",
    "tgn:placetype":[
        "aat:300008347"
    ]
},
  "bbox": [],
  "geometry": {"coordinates":[24.762,59.168],"type":"Point"}
}