{
  "id": 7362925,
  "type": "Feature",
  "properties": {
    "tgn:hierarchy":[
        "tgn:7362925",
        "tgn:1000001",
        "tgn:7005597",
        "tgn:7005560",
        "tgn:7029392"
    ],
    "tgn:id":7362925,
    "tgn:name":"El Escondido",
    "tgn:placetype":[
        "aat:300008699"
    ]
},
  "bbox": [],
  "geometry": {"coordinates":[-97.783333,23.383333],"type":"Point"}
}