{
  "id": 7519576,
  "type": "Feature",
  "properties": {
    "tgn:hierarchy":[
        "tgn:7519576",
        "tgn:1009227",
        "tgn:1000226",
        "tgn:7016729",
        "tgn:1000006",
        "tgn:7029392"
    ],
    "tgn:id":7519576,
    "tgn:name:en":"Admiralty Bay",
    "tgn:placetype":[
        "aat:300008347"
    ]
},
  "bbox": [],
  "geometry": {"coordinates":[173.916667,-40.95],"type":"Point"}
}