{
  "id": 2124451,
  "type": "Feature",
  "properties": {
    "tgn:hierarchy":[
        "tgn:2124451",
        "tgn:1000001",
        "tgn:7012149",
        "tgn:2001519",
        "tgn:7007709",
        "tgn:7029392"
    ],
    "tgn:id":2124451,
    "tgn:name":"Aaron Branch",
    "tgn:placetype":[
        "aat:300008699"
    ]
},
  "bbox": [],
  "geometry": {"coordinates":[-82.2333,36.0833],"type":"Point"}
}