{
  "id": 7566585,
  "type": "Feature",
  "properties": {
    "tgn:hierarchy":[
        "tgn:7566585",
        "tgn:1000004",
        "tgn:1001832",
        "tgn:7000198",
        "tgn:7029392"
    ],
    "tgn:id":7566585,
    "tgn:name:en":"Petla Uj\u0101n",
    "tgn:placetype":[
        "aat:300008347"
    ]
},
  "bbox": [],
  "geometry": {"coordinates":[89.8728,26.292687],"type":"Point"}
}