{
  "id": 2247711,
  "type": "Feature",
  "properties": {
    "tgn:hierarchy":[
        "tgn:2247711",
        "tgn:1002716",
        "tgn:1000001",
        "tgn:7012149",
        "tgn:7007711",
        "tgn:7029392"
    ],
    "tgn:id":2247711,
    "tgn:name":"Coggeshall Cove",
    "tgn:placetype":[
        "aat:300132316"
    ]
},
  "bbox": [],
  "geometry": {"coordinates":[-71.3333,41.65],"type":"Point"}
}