{
  "id": 2343389,
  "type": "Feature",
  "properties": {
    "tgn:hierarchy":[
        "tgn:2343389",
        "tgn:1000001",
        "tgn:7012149",
        "tgn:2001894",
        "tgn:7007825",
        "tgn:7029392"
    ],
    "tgn:id":2343389,
    "tgn:name":"Gaines Cove Branch",
    "tgn:placetype":[
        "aat:300008699"
    ]
},
  "bbox": [],
  "geometry": {"coordinates":[-85.8167,35.1333],"type":"Point"}
}