{
  "id": 2306985,
  "type": "Feature",
  "properties": {
    "tgn:hierarchy":[
        "tgn:2306985",
        "tgn:1000001",
        "tgn:7012149",
        "tgn:2001516",
        "tgn:7007709",
        "tgn:7029392"
    ],
    "tgn:id":2306985,
    "tgn:name":"East Fork Little Creek",
    "tgn:placetype":[
        "aat:300008706"
    ]
},
  "bbox": [],
  "geometry": {"coordinates":[-82.95,35.7833],"type":"Point"}
}