{
  "id": 2008572,
  "type": "Feature",
  "properties": {
    "tgn:hierarchy":[
        "tgn:2008572",
        "tgn:1000001",
        "tgn:7016172",
        "tgn:7012149",
        "tgn:2000161",
        "tgn:7029392"
    ],
    "tgn:id":2008572,
    "tgn:name":"Ink",
    "tgn:placetype":[
        "aat:300008347",
        "aat:300387210"
    ]
},
  "bbox": [],
  "geometry": {"coordinates":[-94.1167,34.5833],"type":"Point"}
}