{
  "id": 1108066,
  "type": "Feature",
  "properties": {
    "tgn:hierarchy":[
        "tgn:1108066",
        "tgn:7016675",
        "tgn:1000004",
        "tgn:7000896",
        "tgn:1000120",
        "tgn:7029392"
    ],
    "tgn:id":1108066,
    "tgn:name":"Kirizume-t\u014dge",
    "tgn:placetype":[
        "aat:300008777"
    ]
},
  "bbox": [],
  "geometry": {"coordinates":[135.2667,34.9333],"type":"Point"}
}