{
  "id": 2031871,
  "type": "Feature",
  "properties": {
    "tgn:hierarchy":[
        "tgn:2031871",
        "tgn:1000001",
        "tgn:7012149",
        "tgn:1002512",
        "tgn:7007252",
        "tgn:7029392"
    ],
    "tgn:id":2031871,
    "tgn:name":"Fountain Park",
    "tgn:placetype":[
        "aat:300008347",
        "aat:300387247"
    ]
},
  "bbox": [],
  "geometry": {"coordinates":[-87.15,40.7667],"type":"Point"}
}