{
  "id": 2180792,
  "type": "Feature",
  "properties": {
    "tgn:hierarchy":[
        "tgn:2180792",
        "tgn:1000001",
        "tgn:7012149",
        "tgn:2000390",
        "tgn:7007248",
        "tgn:7029392"
    ],
    "tgn:id":2180792,
    "tgn:name":"Blount Creek",
    "tgn:placetype":[
        "aat:300008706"
    ]
},
  "bbox": [],
  "geometry": {"coordinates":[-84.75,33.0167],"type":"Point"}
}