{
  "id": 1024585,
  "type": "Feature",
  "properties": {
    "tgn:hierarchy":[
        "tgn:1024585",
        "tgn:1000500",
        "tgn:1000002",
        "tgn:1000056",
        "tgn:7029392"
    ],
    "tgn:id":1024585,
    "tgn:name":"Lamud",
    "tgn:placetype":[
        "aat:300008347"
    ]
},
  "bbox": [],
  "geometry": {"coordinates":[-77.9167,-6.15],"type":"Point"}
}