{
  "id": 7224736,
  "type": "Feature",
  "properties": {
    "tgn:hierarchy":[
        "tgn:7224736",
        "tgn:7002681",
        "tgn:7001395",
        "tgn:1000003",
        "tgn:1000074",
        "tgn:7029392"
    ],
    "tgn:id":7224736,
    "tgn:name":"Riz\u00f3polis",
    "tgn:placetype":[
        "aat:300000745"
    ]
},
  "bbox": [],
  "geometry": {"coordinates":[23.75,38.033333],"type":"Point"}
}