{
  "id": 7532768,
  "type": "Feature",
  "properties": {
    "tgn:hierarchy":[
        "tgn:7532768",
        "tgn:7001242",
        "tgn:7016833",
        "tgn:7001336",
        "tgn:7029392"
    ],
    "tgn:id":7532768,
    "tgn:name":"Madeiriq, W\u00e2di",
    "tgn:placetype":[
        "aat:300379998"
    ]
},
  "bbox": [],
  "geometry": {"coordinates":[34.521944,28.638333],"type":"Point"}
}