{
  "id": 7219772,
  "type": "Feature",
  "properties": {
    "tgn:hierarchy":[
        "tgn:7219772",
        "tgn:7011170",
        "tgn:7002715",
        "tgn:1000003",
        "tgn:1000074",
        "tgn:7029392"
    ],
    "tgn:id":7219772,
    "tgn:name":"Virs\u00ednis, \u00d3ros",
    "tgn:placetype":[
        "aat:300008795"
    ]
},
  "bbox": [],
  "geometry": {"coordinates":[25.783333,41.333333],"type":"Point"}
}