{
  "id": 2516046,
  "type": "Feature",
  "properties": {
    "tgn:hierarchy":[
        "tgn:2516046",
        "tgn:1000001",
        "tgn:7012149",
        "tgn:1002331",
        "tgn:7007826",
        "tgn:7029392"
    ],
    "tgn:id":2516046,
    "tgn:name":"Minchin",
    "tgn:placetype":[
        "aat:300008347"
    ]
},
  "bbox": [],
  "geometry": {"coordinates":[-97.15,33.1667],"type":"Point"}
}