{
  "id": 7022282,
  "type": "Feature",
  "properties": {
    "tgn:hierarchy":[
        "tgn:7022282",
        "tgn:1000001",
        "tgn:7012149",
        "tgn:7029392"
    ],
    "tgn:id":7022282,
    "tgn:name":"Advent Creek",
    "tgn:placetype":[
        "aat:300008706"
    ]
},
  "bbox": [],
  "geometry": {"coordinates":[-98.3833,39.9833],"type":"Point"}
}