{
  "id": 7390900,
  "type": "Feature",
  "properties": {
    "tgn:hierarchy":[
        "tgn:7390900",
        "tgn:1001853",
        "tgn:1000001",
        "tgn:7005560",
        "tgn:7029392"
    ],
    "tgn:id":7390900,
    "tgn:name":"Rancho San Alberto",
    "tgn:placetype":[
        "aat:300000241"
    ]
},
  "bbox": [],
  "geometry": {"coordinates":[-101.283333,25.116667],"type":"Point"}
}