{
  "id": 1090507,
  "type": "Feature",
  "properties": {
    "tgn:hierarchy":[
        "tgn:1090507",
        "tgn:7001242",
        "tgn:7593781",
        "tgn:1000169",
        "tgn:7029392"
    ],
    "tgn:id":1090507,
    "tgn:name":"Marsabit",
    "tgn:placetype":[
        "aat:300008347"
    ]
},
  "bbox": [],
  "geometry": {"coordinates":[37.9833,2.3333],"type":"Point"}
}