{
  "id": 7260944,
  "type": "Feature",
  "properties": {
    "tgn:concordances":{
        "gn:id":"2755229"
    },
    "tgn:hierarchy":[
        "tgn:7260944",
        "tgn:7003619",
        "tgn:1000003",
        "tgn:7016845",
        "tgn:7029392"
    ],
    "tgn:id":7260944,
    "tgn:name:nl":"Groot Dochteren",
    "tgn:placetype":[
        "aat:300008347"
    ]
},
  "bbox": [],
  "geometry": {"coordinates":[6.366667,52.15],"type":"Point"}
}