<<<<<<< HEAD
{
  "id": 7355281,
  "type": "Feature",
  "properties": {
    "tgn:hierarchy":[
        "tgn:7355281",
        "tgn:1000001",
        "tgn:7005591",
        "tgn:7005560",
        "tgn:7029392"
    ],
    "tgn:id":7355281,
    "tgn:name":"Cedro",
    "tgn:placetype":[
        "aat:300008347"
    ]
},
  "bbox": [],
  "geometry": {"coordinates":[-95.35,17.516667],"type":"Point"}
}
=======
{"geometry":{"type":"Point","coordinates":[-95.350000,17.516667]},"type":"Feature","properties":{"hierarchy":["tgn:7355281","tgn:1000001","tgn:7005591","tgn:7005560","tgn:7029392"],"placetype":["aat:300008347"],"id":7355281,"name:xx":"Cedro"}}
>>>>>>> 03f74aca74312dbeaf24d7e61306dd6a786dc3d0
