{
  "id": 7530679,
  "type": "Feature",
  "properties": {
    "tgn:hierarchy":[
        "tgn:7530679",
        "tgn:7001242",
        "tgn:7016833",
        "tgn:1001083",
        "tgn:7029392"
    ],
    "tgn:id":7530679,
    "tgn:name":"S\u012bnam\u0101 R\u0101d\u016bb\u012bs",
    "tgn:placetype":[
        "aat:300004792"
    ]
},
  "bbox": [],
  "geometry": {"coordinates":[31.194559,30.006337],"type":"Point"}
}