{
  "id": 2160122,
  "type": "Feature",
  "properties": {
    "tgn:hierarchy":[
        "tgn:2160122",
        "tgn:1000001",
        "tgn:7012149",
        "tgn:1002440",
        "tgn:7007568",
        "tgn:7029392"
    ],
    "tgn:id":2160122,
    "tgn:name":"Beecher Island",
    "tgn:placetype":[
        "aat:300008791"
    ]
},
  "bbox": [],
  "geometry": {"coordinates":[-74.6167,43.8667],"type":"Point"}
}