{
  "id": 7325895,
  "type": "Feature",
  "properties": {
    "tgn:hierarchy":[
        "tgn:7325895",
        "tgn:7002808",
        "tgn:7030216",
        "tgn:1000003",
        "tgn:1000095",
        "tgn:7029392"
    ],
    "tgn:id":7325895,
    "tgn:name":"Ermita de San Sim\u00f3n",
    "tgn:placetype":[
        "aat:300000640"
    ]
},
  "bbox": [],
  "geometry": {"coordinates":[2.45,41.533333],"type":"Point"}
}