{
  "id": 2236015,
  "type": "Feature",
  "properties": {
    "tgn:hierarchy":[
        "tgn:2236015",
        "tgn:1000001",
        "tgn:7012149",
        "tgn:1002999",
        "tgn:7007526",
        "tgn:7029392"
    ],
    "tgn:id":2236015,
    "tgn:name":"Chewing Gum Spring",
    "tgn:placetype":[
        "aat:300008697"
    ]
},
  "bbox": [],
  "geometry": {"coordinates":[-119.85,39.9333],"type":"Point"}
}