{
  "id": 2440041,
  "type": "Feature",
  "properties": {
    "tgn:hierarchy":[
        "tgn:2440041",
        "tgn:1000001",
        "tgn:7012149",
        "tgn:2000228",
        "tgn:7007158",
        "tgn:7029392"
    ],
    "tgn:id":2440041,
    "tgn:name":"Kkrval",
    "tgn:placetype":[
        "aat:300008347"
    ]
},
  "bbox": [],
  "geometry": {"coordinates":[-103.5333,38.7333],"type":"Point"}
}