{
  "id": 7039569,
  "type": "Feature",
  "properties": {
    "tgn:hierarchy":[
        "tgn:7039569",
        "tgn:7003171",
        "tgn:1000003",
        "tgn:7003125",
        "tgn:1000080",
        "tgn:7029392"
    ],
    "tgn:id":7039569,
    "tgn:name":"Sant'Urbano",
    "tgn:placetype":[
        "aat:300008347"
    ]
},
  "bbox": [],
  "geometry": {"coordinates":[12.583333,42.466667],"type":"Point"}
}