{
  "id": 2589439,
  "type": "Feature",
  "properties": {
    "tgn:hierarchy":[
        "tgn:2589439",
        "tgn:7006450",
        "tgn:1000001",
        "tgn:7012149",
        "tgn:2000086",
        "tgn:7029392"
    ],
    "tgn:id":2589439,
    "tgn:name":"Point Eleanor",
    "tgn:placetype":[
        "aat:300008850"
    ]
},
  "bbox": [],
  "geometry": {"coordinates":[-147.55,60.5667],"type":"Point"}
}