{
  "id": 2139784,
  "type": "Feature",
  "properties": {
    "tgn:hierarchy":[
        "tgn:2139784",
        "tgn:1000001",
        "tgn:7012149",
        "tgn:2000234",
        "tgn:7007158",
        "tgn:7029392"
    ],
    "tgn:id":2139784,
    "tgn:name":"Atkinson Breaks",
    "tgn:placetype":[
        "aat:300008798"
    ]
},
  "bbox": [],
  "geometry": {"coordinates":[-108.6667,38.45],"type":"Point"}
}