<<<<<<< HEAD
{
  "id": 2153504,
  "type": "Feature",
  "properties": {
    "tgn:hierarchy":[
        "tgn:2153504",
        "tgn:1000001",
        "tgn:7016172",
        "tgn:7012149",
        "tgn:2000130",
        "tgn:7029392"
    ],
    "tgn:id":2153504,
    "tgn:name":"Bear",
    "tgn:placetype":[
        "aat:300008347"
    ]
},
  "bbox": [],
  "geometry": {"coordinates":[-93.2667,34.5333],"type":"Point"}
}
=======
{"geometry":{"type":"Point","coordinates":[-93.266700,34.533300]},"type":"Feature","properties":{"hierarchy":["tgn:2153504","tgn:1000001","tgn:7016172","tgn:7012149","tgn:2000130","tgn:7029392"],"placetype":["aat:300008347"],"id":2153504,"name:xx":"Bear"}}
>>>>>>> 03f74aca74312dbeaf24d7e61306dd6a786dc3d0
