<<<<<<< HEAD
{
  "id": 7367836,
  "type": "Feature",
  "properties": {
    "tgn:hierarchy":[
        "tgn:7367836",
        "tgn:7005586",
        "tgn:1000001",
        "tgn:7005560",
        "tgn:7029392"
    ],
    "tgn:id":7367836,
    "tgn:name":"El Potrero de Rivera",
    "tgn:placetype":[
        "aat:300008347"
    ]
},
  "bbox": [],
  "geometry": {"coordinates":[-102.433333,21.066667],"type":"Point"}
}
=======
{"geometry":{"type":"Point","coordinates":[-102.433333,21.066667]},"type":"Feature","properties":{"hierarchy":["tgn:7367836","tgn:7005586","tgn:1000001","tgn:7005560","tgn:7029392"],"placetype":["aat:300008347"],"id":7367836,"name:xx":"El Potrero de Rivera"}}
>>>>>>> 03f74aca74312dbeaf24d7e61306dd6a786dc3d0
