{
  "id": 1013347,
  "type": "Feature",
  "properties": {
    "tgn:hierarchy":[
        "tgn:1013347",
        "tgn:7005694",
        "tgn:7005685",
        "tgn:1000001",
        "tgn:7029392"
    ],
    "tgn:id":1013347,
    "tgn:name":"Wembley",
    "tgn:placetype":[
        "aat:300008347"
    ]
},
  "bbox": [],
  "geometry": {"coordinates":[-119.15,55.15],"type":"Point"}
}