{
  "id": 7278730,
  "type": "Feature",
  "properties": {
    "tgn:hierarchy":[
        "tgn:7278730",
        "tgn:1001699",
        "tgn:1000049",
        "tgn:1000002",
        "tgn:7029392"
    ],
    "tgn:id":7278730,
    "tgn:name":"Solitaria, Roca",
    "tgn:placetype":[
        "aat:300011692"
    ]
},
  "bbox": [],
  "geometry": {"coordinates":[-73.769444,-41.586111],"type":"Point"}
}