<<<<<<< HEAD
{
  "id": 2250374,
  "type": "Feature",
  "properties": {
    "tgn:hierarchy":[
        "tgn:2250374",
        "tgn:7002659",
        "tgn:1000001",
        "tgn:2000009",
        "tgn:7012149",
        "tgn:7029392"
    ],
    "tgn:id":2250374,
    "tgn:name":"Coloma Mountain",
    "tgn:placetype":[
        "aat:300266640"
    ]
},
  "bbox": [],
  "geometry": {"coordinates":[-85.6,34.0333],"type":"Point"}
}
=======
{"geometry":{"type":"Point","coordinates":[-85.600000,34.033300]},"type":"Feature","properties":{"hierarchy":["tgn:2250374","tgn:7002659","tgn:1000001","tgn:2000009","tgn:7012149","tgn:7029392"],"placetype":["aat:300266640"],"id":2250374,"name:xx":"Coloma Mountain"}}
>>>>>>> 03f74aca74312dbeaf24d7e61306dd6a786dc3d0
