{
  "id": 7420939,
  "type": "Feature",
  "properties": {
    "tgn:hierarchy":[
        "tgn:7420939",
        "tgn:7005584",
        "tgn:1000001",
        "tgn:7005560",
        "tgn:7029392"
    ],
    "tgn:id":7420939,
    "tgn:name":"Jeric\u00f3",
    "tgn:placetype":[
        "aat:300008347"
    ]
},
  "bbox": [],
  "geometry": {"coordinates":[-101.027222,21.295833],"type":"Point"}
}