{
  "id": 2118985,
  "type": "Feature",
  "properties": {
    "tgn:hierarchy":[
        "tgn:2118985",
        "tgn:1000001",
        "tgn:7012149",
        "tgn:2002284",
        "tgn:7013961",
        "tgn:7029392"
    ],
    "tgn:id":2118985,
    "tgn:name":"Lockwood",
    "tgn:placetype":[
        "aat:300008347"
    ]
},
  "bbox": [],
  "geometry": {"coordinates":[-81.0333,38.25],"type":"Point"}
}