<<<<<<< HEAD
{
  "id": 7175335,
  "type": "Feature",
  "properties": {
    "tgn:hierarchy":[
        "tgn:7175335",
        "tgn:7000096",
        "tgn:1000003",
        "tgn:7000084",
        "tgn:7029392"
    ],
    "tgn:id":7175335,
    "tgn:name":"Grie\u00dfen",
    "tgn:placetype":[
        "aat:300008347"
    ]
},
  "bbox": [],
  "geometry": {"coordinates":[14.6,51.85],"type":"Point"}
}
=======
{"geometry":{"type":"Point","coordinates":[14.600000,51.850000]},"type":"Feature","properties":{"hierarchy":["tgn:7175335","tgn:7000096","tgn:1000003","tgn:7000084","tgn:7029392"],"placetype":["aat:300008347"],"id":7175335,"name:xx":"Grie\u00dfen"}}
>>>>>>> 03f74aca74312dbeaf24d7e61306dd6a786dc3d0
