{
  "id": 2424558,
  "type": "Feature",
  "properties": {
    "tgn:hierarchy":[
        "tgn:2424558",
        "tgn:1000001",
        "tgn:7012149",
        "tgn:2000479",
        "tgn:7007250",
        "tgn:7029392"
    ],
    "tgn:id":2424558,
    "tgn:name":"Johnson Creek",
    "tgn:placetype":[
        "aat:300008706"
    ]
},
  "bbox": [],
  "geometry": {"coordinates":[-116.9833,47.85],"type":"Point"}
}