{
  "id": 7022968,
  "type": "Feature",
  "properties": {
    "tgn:hierarchy":[
        "tgn:7022968",
        "tgn:1000001",
        "tgn:7012149",
        "tgn:7007256",
        "tgn:7029392"
    ],
    "tgn:id":7022968,
    "tgn:name":"Forty Arpent Canal",
    "tgn:placetype":[
        "aat:300006075"
    ]
},
  "bbox": [],
  "geometry": {"coordinates":[-89.9167,29.9333],"type":"Point"}
}