<<<<<<< HEAD
{
  "id": 7022968,
  "type": "Feature",
  "properties": {
    "tgn:hierarchy":[
        "tgn:7022968",
        "tgn:1000001",
        "tgn:7012149",
        "tgn:7007256",
        "tgn:7029392"
    ],
    "tgn:id":7022968,
    "tgn:name":"Forty Arpent Canal",
    "tgn:placetype":[
        "aat:300006075"
    ]
},
  "bbox": [],
  "geometry": {"coordinates":[-89.9167,29.9333],"type":"Point"}
}
=======
{"geometry":{"type":"Point","coordinates":[-89.916700,29.933300]},"type":"Feature","properties":{"hierarchy":["tgn:7022968","tgn:1000001","tgn:7012149","tgn:7007256","tgn:7029392"],"placetype":["aat:300006075"],"id":7022968,"name:xx":"Forty Arpent Canal"}}
>>>>>>> 03f74aca74312dbeaf24d7e61306dd6a786dc3d0
