{
  "id": 2710745,
  "type": "Feature",
  "properties": {
    "tgn:hierarchy":[
        "tgn:2710745",
        "tgn:7030516",
        "tgn:7006450",
        "tgn:1000001",
        "tgn:7012149",
        "tgn:7029392"
    ],
    "tgn:id":2710745,
    "tgn:name":"Tanaskan Bay",
    "tgn:placetype":[
        "aat:300132316"
    ]
},
  "bbox": [],
  "geometry": {"coordinates":[-166.4667,53.7167],"type":"Point"}
}