{
  "id": 2122572,
  "type": "Feature",
  "properties": {
    "tgn:hierarchy":[
        "tgn:2122572",
        "tgn:1000001",
        "tgn:7012149",
        "tgn:2002362",
        "tgn:7007922",
        "tgn:7029392"
    ],
    "tgn:id":2122572,
    "tgn:name":"Tustin",
    "tgn:placetype":[
        "aat:300008347"
    ]
},
  "bbox": [],
  "geometry": {"coordinates":[-88.8833,44.15],"type":"Point"}
}