{
  "id": 2662457,
  "type": "Feature",
  "properties": {
    "tgn:hierarchy":[
        "tgn:2662457",
        "tgn:1000001",
        "tgn:2001745",
        "tgn:7012149",
        "tgn:7007712",
        "tgn:7029392"
    ],
    "tgn:id":2662457,
    "tgn:name":"Siesta Village",
    "tgn:placetype":[
        "aat:300008347"
    ]
},
  "bbox": [],
  "geometry": {"coordinates":[-79.75,34.1667],"type":"Point"}
}