{
  "id": 2607088,
  "type": "Feature",
  "properties": {
    "tgn:hierarchy":[
        "tgn:2607088",
        "tgn:1000001",
        "tgn:7012149",
        "tgn:2001449",
        "tgn:7007566",
        "tgn:7029392"
    ],
    "tgn:id":2607088,
    "tgn:name":"Ranchos, Ca\u00f1oncito de los",
    "tgn:placetype":[
        "aat:300008761"
    ]
},
  "bbox": [],
  "geometry": {"coordinates":[-106.3333,36.0167],"type":"Point"}
}