<<<<<<< HEAD
{
  "id": 7023586,
  "type": "Feature",
  "properties": {
    "tgn:hierarchy":[
        "tgn:7023586",
        "tgn:1000001",
        "tgn:7012149",
        "tgn:7029392"
    ],
    "tgn:id":7023586,
    "tgn:name":"North Fritz Island",
    "tgn:placetype":[
        "aat:300008791"
    ]
},
  "bbox": [],
  "geometry": {"coordinates":[-91.0833,39.5167],"type":"Point"}
}
=======
{"geometry":{"type":"Point","coordinates":[-91.083300,39.516700]},"type":"Feature","properties":{"hierarchy":["tgn:7023586","tgn:1000001","tgn:7012149","tgn:7029392"],"placetype":["aat:300008791"],"id":7023586,"name:xx":"North Fritz Island"}}
>>>>>>> 03f74aca74312dbeaf24d7e61306dd6a786dc3d0
