<<<<<<< HEAD
{
  "id": 2257696,
  "type": "Feature",
  "properties": {
    "tgn:hierarchy":[
        "tgn:2257696",
        "tgn:1000001",
        "tgn:2000470",
        "tgn:7012149",
        "tgn:7007250",
        "tgn:7029392"
    ],
    "tgn:id":2257696,
    "tgn:name":"Corral Creek Summit",
    "tgn:placetype":[
        "aat:300008798"
    ]
},
  "bbox": [],
  "geometry": {"coordinates":[-113.7833,43.9],"type":"Point"}
}
=======
{"geometry":{"type":"Point","coordinates":[-113.783300,43.900000]},"type":"Feature","properties":{"hierarchy":["tgn:2257696","tgn:1000001","tgn:2000470","tgn:7012149","tgn:7007250","tgn:7029392"],"placetype":["aat:300008798"],"id":2257696,"name:xx":"Corral Creek Summit"}}
>>>>>>> 03f74aca74312dbeaf24d7e61306dd6a786dc3d0
