{
  "id": 2199111,
  "type": "Feature",
  "properties": {
    "tgn:hierarchy":[
        "tgn:2199111",
        "tgn:1000001",
        "tgn:7012149",
        "tgn:2001190",
        "tgn:7007523",
        "tgn:7029392"
    ],
    "tgn:id":2199111,
    "tgn:name":"Brummet Lake",
    "tgn:placetype":[
        "aat:300006191"
    ]
},
  "bbox": [],
  "geometry": {"coordinates":[-91.3667,38.05],"type":"Point"}
}