<<<<<<< HEAD
{
  "id": 2403027,
  "type": "Feature",
  "properties": {
    "tgn:hierarchy":[
        "tgn:2403027",
        "tgn:1000001",
        "tgn:7012149",
        "tgn:2001657",
        "tgn:7007707",
        "tgn:7029392"
    ],
    "tgn:id":2403027,
    "tgn:name":"Houghtubby Spring",
    "tgn:placetype":[
        "aat:300008697"
    ]
},
  "bbox": [],
  "geometry": {"coordinates":[-96.5167,34.4167],"type":"Point"}
}
=======
{"geometry":{"type":"Point","coordinates":[-96.516700,34.416700]},"type":"Feature","properties":{"hierarchy":["tgn:2403027","tgn:1000001","tgn:7012149","tgn:2001657","tgn:7007707","tgn:7029392"],"placetype":["aat:300008697"],"id":2403027,"name:xx":"Houghtubby Spring"}}
>>>>>>> 03f74aca74312dbeaf24d7e61306dd6a786dc3d0
