{
  "id": 7517898,
  "type": "Feature",
  "properties": {
    "tgn:hierarchy":[
        "tgn:7517898",
        "tgn:1009227",
        "tgn:7001866",
        "tgn:1000226",
        "tgn:1000006",
        "tgn:7029392"
    ],
    "tgn:id":7517898,
    "tgn:name:en":"McCoys Creek",
    "tgn:placetype":[
        "aat:300008699"
    ]
},
  "bbox": [],
  "geometry": {"coordinates":[170.783333,-43.383333],"type":"Point"}
}