{
  "id": 2680627,
  "type": "Feature",
  "properties": {
    "tgn:hierarchy":[
        "tgn:2680627",
        "tgn:1000001",
        "tgn:7012149",
        "tgn:2002356",
        "tgn:7007922",
        "tgn:7029392"
    ],
    "tgn:id":2680627,
    "tgn:name":"South Harper Lake",
    "tgn:placetype":[
        "aat:300008680"
    ]
},
  "bbox": [],
  "geometry": {"coordinates":[-90.1833,45.35],"type":"Point"}
}