{
  "id": 7482835,
  "type": "Feature",
  "properties": {
    "tgn:hierarchy":[
        "tgn:7482835",
        "tgn:1000004",
        "tgn:7001014",
        "tgn:1000141",
        "tgn:7029392"
    ],
    "tgn:id":7482835,
    "tgn:name":"Wanxing Qiao",
    "tgn:placetype":[
        "aat:300007836"
    ]
},
  "bbox": [],
  "geometry": {"coordinates":[120.237222,23.580278],"type":"Point"}
}