{
  "id": 2393075,
  "type": "Feature",
  "properties": {
    "tgn:hierarchy":[
        "tgn:2393075",
        "tgn:1000001",
        "tgn:2000683",
        "tgn:7012149",
        "tgn:7007254",
        "tgn:7029392"
    ],
    "tgn:id":2393075,
    "tgn:name":"Hodges",
    "tgn:placetype":[
        "aat:300008347"
    ]
},
  "bbox": [],
  "geometry": {"coordinates":[-99.3833,37.8167],"type":"Point"}
}