{
  "id": 2199178,
  "type": "Feature",
  "properties": {
    "tgn:hierarchy":[
        "tgn:2199178",
        "tgn:1000001",
        "tgn:7012149",
        "tgn:2001764",
        "tgn:7007712",
        "tgn:7029392"
    ],
    "tgn:id":2199178,
    "tgn:name":"Bruners Pond",
    "tgn:placetype":[
        "aat:300006191"
    ]
},
  "bbox": [],
  "geometry": {"coordinates":[-80.9333,34.0833],"type":"Point"}
}