{
  "id": 7002364,
  "type": "Feature",
  "properties": {
    "tgn:hierarchy":[
        "tgn:7002364",
        "tgn:1000004",
        "tgn:1000113",
        "tgn:7029392"
    ],
    "tgn:id":7002364,
    "tgn:name":"Lefko\u015fa",
    "tgn:placetype":[
        "aat:300387064",
        "aat:300387081"
    ]
},
  "bbox": [],
  "geometry": {"coordinates":[33.3333,35.3333],"type":"Point"}
}