{
  "id": 2205312,
  "type": "Feature",
  "properties": {
    "tgn:hierarchy":[
        "tgn:2205312",
        "tgn:1000001",
        "tgn:7012149",
        "tgn:7007157",
        "tgn:1002857",
        "tgn:7029392"
    ],
    "tgn:id":2205312,
    "tgn:name":"Bull Canyon",
    "tgn:placetype":[
        "aat:300008761"
    ]
},
  "bbox": [],
  "geometry": {"coordinates":[-117.55,34.1833],"type":"Point"}
}