{
  "id": 2140083,
  "type": "Feature",
  "properties": {
    "tgn:hierarchy":[
        "tgn:2140083",
        "tgn:1000001",
        "tgn:7012149",
        "tgn:2000907",
        "tgn:7007256",
        "tgn:7029392"
    ],
    "tgn:id":2140083,
    "tgn:name":"Aubrey",
    "tgn:placetype":[
        "aat:300008347"
    ]
},
  "bbox": [],
  "geometry": {"coordinates":[-91.3167,31.9167],"type":"Point"}
}