{
  "id": 2306025,
  "type": "Feature",
  "properties": {
    "tgn:hierarchy":[
        "tgn:2306025",
        "tgn:1000001",
        "tgn:7012149",
        "tgn:2000217",
        "tgn:7007158",
        "tgn:7029392"
    ],
    "tgn:id":2306025,
    "tgn:name":"East Fork Alder Creek",
    "tgn:placetype":[
        "aat:300008706"
    ]
},
  "bbox": [],
  "geometry": {"coordinates":[-106.6333,38.6333],"type":"Point"}
}