{
  "id": 2201341,
  "type": "Feature",
  "properties": {
    "tgn:hierarchy":[
        "tgn:2201341",
        "tgn:1000001",
        "tgn:7012149",
        "tgn:2000290",
        "tgn:7007240",
        "tgn:7029392"
    ],
    "tgn:id":2201341,
    "tgn:name":"Buck Branch",
    "tgn:placetype":[
        "aat:300008699"
    ]
},
  "bbox": [],
  "geometry": {"coordinates":[-86.25,30.7333],"type":"Point"}
}