{
  "id": 2735629,
  "type": "Feature",
  "properties": {
    "tgn:hierarchy":[
        "tgn:2735629",
        "tgn:1000001",
        "tgn:1002260",
        "tgn:7012149",
        "tgn:7007920",
        "tgn:7029392"
    ],
    "tgn:id":2735629,
    "tgn:name":"Twin Harbor Creek",
    "tgn:placetype":[
        "aat:300008706"
    ]
},
  "bbox": [],
  "geometry": {"coordinates":[-120.5333,48.1167],"type":"Point"}
}