{
  "id": 2200468,
  "type": "Feature",
  "properties": {
    "tgn:hierarchy":[
        "tgn:2200468",
        "tgn:2001172",
        "tgn:1000001",
        "tgn:7012149",
        "tgn:7007523",
        "tgn:7029392"
    ],
    "tgn:id":2200468,
    "tgn:name":"Brushy Mound Lake",
    "tgn:placetype":[
        "aat:300006191"
    ]
},
  "bbox": [],
  "geometry": {"coordinates":[-94.3833,38.1333],"type":"Point"}
}