{
  "id": 2659202,
  "type": "Feature",
  "properties": {
    "tgn:hierarchy":[
        "tgn:2659202",
        "tgn:1000001",
        "tgn:7012149",
        "tgn:7014334",
        "tgn:7007919",
        "tgn:7029392"
    ],
    "tgn:id":2659202,
    "tgn:name":"Shields Lake",
    "tgn:placetype":[
        "aat:300006191"
    ]
},
  "bbox": [],
  "geometry": {"coordinates":[-77.4667,37.5333],"type":"Point"}
}