<<<<<<< HEAD
{
  "id": 7171734,
  "type": "Feature",
  "properties": {
    "tgn:hierarchy":[
        "tgn:7171734",
        "tgn:1000003",
        "tgn:7003687",
        "tgn:7000084",
        "tgn:7029392"
    ],
    "tgn:id":7171734,
    "tgn:name":"Hirschbach-Berg",
    "tgn:placetype":[
        "aat:300008777"
    ]
},
  "bbox": [],
  "geometry": {"coordinates":[11.133333,51.433333],"type":"Point"}
}
=======
{"geometry":{"type":"Point","coordinates":[11.133333,51.433333]},"type":"Feature","properties":{"hierarchy":["tgn:7171734","tgn:1000003","tgn:7003687","tgn:7000084","tgn:7029392"],"placetype":["aat:300008777"],"id":7171734,"name:xx":"Hirschbach-Berg"}}
>>>>>>> 03f74aca74312dbeaf24d7e61306dd6a786dc3d0
