{
  "id": 2202113,
  "type": "Feature",
  "properties": {
    "tgn:hierarchy":[
        "tgn:2202113",
        "tgn:1000001",
        "tgn:7012149",
        "tgn:7007157",
        "tgn:1002791",
        "tgn:7029392"
    ],
    "tgn:id":2202113,
    "tgn:name":"Buck Lake",
    "tgn:placetype":[
        "aat:300008680"
    ]
},
  "bbox": [],
  "geometry": {"coordinates":[-120.1833,39.05],"type":"Point"}
}