{
  "id": 2358864,
  "type": "Feature",
  "properties": {
    "tgn:hierarchy":[
        "tgn:2358864",
        "tgn:1000001",
        "tgn:7012149",
        "tgn:2002123",
        "tgn:7007827",
        "tgn:7029392"
    ],
    "tgn:id":2358864,
    "tgn:name":"Granite Canyon Spring",
    "tgn:placetype":[
        "aat:300008697"
    ]
},
  "bbox": [],
  "geometry": {"coordinates":[-112.6167,40.55],"type":"Point"}
}