{
  "id": 2743883,
  "type": "Feature",
  "properties": {
    "tgn:hierarchy":[
        "tgn:2743883",
        "tgn:7006450",
        "tgn:2000069",
        "tgn:1000001",
        "tgn:7012149",
        "tgn:7029392"
    ],
    "tgn:id":2743883,
    "tgn:name":"Velvet Creek",
    "tgn:placetype":[
        "aat:300008706"
    ]
},
  "bbox": [],
  "geometry": {"coordinates":[-161.3833,59.3333],"type":"Point"}
}