<<<<<<< HEAD
{
  "id": 2157099,
  "type": "Feature",
  "properties": {
    "tgn:hierarchy":[
        "tgn:2157099",
        "tgn:1002227",
        "tgn:1000001",
        "tgn:7012149",
        "tgn:7007565",
        "tgn:7029392"
    ],
    "tgn:id":2157099,
    "tgn:name":"Beaver Brook",
    "tgn:placetype":[
        "aat:300008699"
    ]
},
  "bbox": [],
  "geometry": {"coordinates":[-75.0333,39.85],"type":"Point"}
}
=======
{"geometry":{"type":"Point","coordinates":[-75.033300,39.850000]},"type":"Feature","properties":{"hierarchy":["tgn:2157099","tgn:1002227","tgn:1000001","tgn:7012149","tgn:7007565","tgn:7029392"],"placetype":["aat:300008699"],"id":2157099,"name:xx":"Beaver Brook"}}
>>>>>>> 03f74aca74312dbeaf24d7e61306dd6a786dc3d0
