<<<<<<< HEAD
{
  "id": 7353575,
  "type": "Feature",
  "properties": {
    "tgn:hierarchy":[
        "tgn:7353575",
        "tgn:1000001",
        "tgn:7005589",
        "tgn:7005560",
        "tgn:7029392"
    ],
    "tgn:id":7353575,
    "tgn:name":"Azeliado, Puerto del",
    "tgn:placetype":[
        "aat:300259572"
    ]
},
  "bbox": [],
  "geometry": {"coordinates":[-100.583333,25.216667],"type":"Point"}
}
=======
{"geometry":{"type":"Point","coordinates":[-100.583333,25.216667]},"type":"Feature","properties":{"hierarchy":["tgn:7353575","tgn:1000001","tgn:7005589","tgn:7005560","tgn:7029392"],"placetype":["aat:300259572"],"id":7353575,"name:xx":"Azeliado, Puerto del"}}
>>>>>>> 03f74aca74312dbeaf24d7e61306dd6a786dc3d0
