{
  "id": 7331560,
  "type": "Feature",
  "properties": {
    "tgn:hierarchy":[
        "tgn:7331560",
        "tgn:7002825",
        "tgn:7016622",
        "tgn:1000003",
        "tgn:1000095",
        "tgn:7029392"
    ],
    "tgn:id":7331560,
    "tgn:name":"Lajita",
    "tgn:placetype":[
        "aat:300008347"
    ]
},
  "bbox": [],
  "geometry": {"coordinates":[-14.15,28.166667],"type":"Point"}
}