{
  "id": 2532895,
  "type": "Feature",
  "properties": {
    "tgn:hierarchy":[
        "tgn:2532895",
        "tgn:1000001",
        "tgn:7012149",
        "tgn:2002385",
        "tgn:7007923",
        "tgn:7029392"
    ],
    "tgn:id":2532895,
    "tgn:name":"Murray Ditch",
    "tgn:placetype":[
        "aat:300006075"
    ]
},
  "bbox": [],
  "geometry": {"coordinates":[-110.3833,41.0667],"type":"Point"}
}