{
  "id": 7312934,
  "type": "Feature",
  "properties": {
    "tgn:hierarchy":[
        "tgn:7312934",
        "tgn:1001699",
        "tgn:1000049",
        "tgn:1000002",
        "tgn:7029392"
    ],
    "tgn:id":7312934,
    "tgn:name":"La Poza, Estero",
    "tgn:placetype":[
        "aat:300132317"
    ]
},
  "bbox": [],
  "geometry": {"coordinates":[-72.783333,-41.866667],"type":"Point"}
}