{
  "id": 7213238,
  "type": "Feature",
  "properties": {
    "tgn:hierarchy":[
        "tgn:7213238",
        "tgn:7003669",
        "tgn:1000003",
        "tgn:7000084",
        "tgn:7029392"
    ],
    "tgn:id":7213238,
    "tgn:name":"Bockarten",
    "tgn:placetype":[
        "aat:300008347"
    ]
},
  "bbox": [],
  "geometry": {"coordinates":[10.366667,47.75],"type":"Point"}
}