{
  "id": 7565224,
  "type": "Feature",
  "properties": {
    "tgn:hierarchy":[
        "tgn:7565224",
        "tgn:1000004",
        "tgn:7000198",
        "tgn:7016722",
        "tgn:7029392"
    ],
    "tgn:id":7565224,
    "tgn:name:en":"Mihauli",
    "tgn:placetype":[
        "aat:300008347"
    ]
},
  "bbox": [],
  "geometry": {"coordinates":[79.437674,26.48891],"type":"Point"}
}