<<<<<<< HEAD
{
  "id": 7057622,
  "type": "Feature",
  "properties": {
    "tgn:hierarchy":[
        "tgn:7057622",
        "tgn:7003006",
        "tgn:1000003",
        "tgn:7002997",
        "tgn:1000080",
        "tgn:7029392"
    ],
    "tgn:id":7057622,
    "tgn:name":"Arzeri di Sopra",
    "tgn:placetype":[
        "aat:300008347"
    ]
},
  "bbox": [],
  "geometry": {"coordinates":[12.55,45.7],"type":"Point"}
}
=======
{"geometry":{"type":"Point","coordinates":[12.550000,45.700000]},"type":"Feature","properties":{"hierarchy":["tgn:7057622","tgn:7003006","tgn:1000003","tgn:7002997","tgn:1000080","tgn:7029392"],"placetype":["aat:300008347"],"id":7057622,"name:xx":"Arzeri di Sopra"}}
>>>>>>> 03f74aca74312dbeaf24d7e61306dd6a786dc3d0
