{
  "id": 2630516,
  "type": "Feature",
  "properties": {
    "tgn:hierarchy":[
        "tgn:2630516",
        "tgn:1000001",
        "tgn:2002323",
        "tgn:7012149",
        "tgn:7007922",
        "tgn:7029392"
    ],
    "tgn:id":2630516,
    "tgn:name":"Round Creek",
    "tgn:placetype":[
        "aat:300008706"
    ]
},
  "bbox": [],
  "geometry": {"coordinates":[-88.6667,45.4833],"type":"Point"}
}