{
  "id": 2255536,
  "type": "Feature",
  "properties": {
    "tgn:hierarchy":[
        "tgn:2255536",
        "tgn:7006450",
        "tgn:1000001",
        "tgn:2124053",
        "tgn:7012149",
        "tgn:7029392"
    ],
    "tgn:id":2255536,
    "tgn:name":"Copeland Creek",
    "tgn:placetype":[
        "aat:300008706"
    ]
},
  "bbox": [],
  "geometry": {"coordinates":[-149.7833,63.1833],"type":"Point"}
}