<<<<<<< HEAD
{
  "id": 7172725,
  "type": "Feature",
  "properties": {
    "tgn:hierarchy":[
        "tgn:7172725",
        "tgn:7003669",
        "tgn:1000003",
        "tgn:7000084",
        "tgn:7029392"
    ],
    "tgn:id":7172725,
    "tgn:name":"Heuwies",
    "tgn:placetype":[
        "aat:300000206"
    ]
},
  "bbox": [],
  "geometry": {"coordinates":[12.65,48.45],"type":"Point"}
}
=======
{"geometry":{"type":"Point","coordinates":[12.650000,48.450000]},"type":"Feature","properties":{"hierarchy":["tgn:7172725","tgn:7003669","tgn:1000003","tgn:7000084","tgn:7029392"],"placetype":["aat:300000206"],"id":7172725,"name:xx":"Heuwies"}}
>>>>>>> 03f74aca74312dbeaf24d7e61306dd6a786dc3d0
