{
  "id": 7172725,
  "type": "Feature",
  "properties": {
    "tgn:hierarchy":[
        "tgn:7172725",
        "tgn:7003669",
        "tgn:1000003",
        "tgn:7000084",
        "tgn:7029392"
    ],
    "tgn:id":7172725,
    "tgn:name":"Heuwies",
    "tgn:placetype":[
        "aat:300000206"
    ]
},
  "bbox": [],
  "geometry": {"coordinates":[12.65,48.45],"type":"Point"}
}