{
  "id": 2677095,
  "type": "Feature",
  "properties": {
    "tgn:hierarchy":[
        "tgn:2677095",
        "tgn:1000001",
        "tgn:7012149",
        "tgn:7007922",
        "tgn:7029392"
    ],
    "tgn:id":2677095,
    "tgn:name":"South Branch Popple River",
    "tgn:placetype":[
        "aat:300008707"
    ]
},
  "bbox": [],
  "geometry": {"coordinates":[-88.6667,45.75],"type":"Point"}
}