{
  "id": 7060607,
  "type": "Feature",
  "properties": {
    "tgn:hierarchy":[
        "tgn:7060607",
        "tgn:1000003",
        "tgn:7000094",
        "tgn:7000084",
        "tgn:7029392"
    ],
    "tgn:id":7060607,
    "tgn:name":"Alt Poppentin",
    "tgn:placetype":[
        "aat:300008347"
    ]
},
  "bbox": [],
  "geometry": {"coordinates":[12.533333,53.45],"type":"Point"}
}