<<<<<<< HEAD
{
  "id": 2407729,
  "type": "Feature",
  "properties": {
    "tgn:hierarchy":[
        "tgn:2407729",
        "tgn:1000001",
        "tgn:1002479",
        "tgn:7012149",
        "tgn:7007240",
        "tgn:7029392"
    ],
    "tgn:id":2407729,
    "tgn:name":"Hurrah Lake",
    "tgn:placetype":[
        "aat:300008680"
    ]
},
  "bbox": [],
  "geometry": {"coordinates":[-82.1333,27.75],"type":"Point"}
}
=======
{"geometry":{"type":"Point","coordinates":[-82.133300,27.750000]},"type":"Feature","properties":{"hierarchy":["tgn:2407729","tgn:1000001","tgn:1002479","tgn:7012149","tgn:7007240","tgn:7029392"],"placetype":["aat:300008680"],"id":2407729,"name:xx":"Hurrah Lake"}}
>>>>>>> 03f74aca74312dbeaf24d7e61306dd6a786dc3d0
