{
  "id": 2623381,
  "type": "Feature",
  "properties": {
    "tgn:hierarchy":[
        "tgn:2623381",
        "tgn:1000001",
        "tgn:7012149",
        "tgn:2001458",
        "tgn:7007566",
        "tgn:7029392"
    ],
    "tgn:id":2623381,
    "tgn:name":"Rock Canyon Tank",
    "tgn:placetype":[
        "aat:300006191"
    ]
},
  "bbox": [],
  "geometry": {"coordinates":[-106.0167,34.3833],"type":"Point"}
}