{
  "id": 2153699,
  "type": "Feature",
  "properties": {
    "tgn:hierarchy":[
        "tgn:2153699",
        "tgn:1000001",
        "tgn:7012149",
        "tgn:1002691",
        "tgn:7007826",
        "tgn:7029392"
    ],
    "tgn:id":2153699,
    "tgn:name":"Bear Branch",
    "tgn:placetype":[
        "aat:300008699"
    ]
},
  "bbox": [],
  "geometry": {"coordinates":[-95.5833,30.2333],"type":"Point"}
}