{
  "id": 7422318,
  "type": "Feature",
  "properties": {
    "tgn:hierarchy":[
        "tgn:7422318",
        "tgn:1000001",
        "tgn:1001960",
        "tgn:7005560",
        "tgn:7029392"
    ],
    "tgn:id":7422318,
    "tgn:name":"La Puerta del Bellotal",
    "tgn:placetype":[
        "aat:300008347"
    ]
},
  "bbox": [],
  "geometry": {"coordinates":[-110.783333,30.783333],"type":"Point"}
}