{
  "id": 2354567,
  "type": "Feature",
  "properties": {
    "tgn:hierarchy":[
        "tgn:2354567",
        "tgn:1000001",
        "tgn:7012149",
        "tgn:2002376",
        "tgn:7007923",
        "tgn:7029392"
    ],
    "tgn:id":2354567,
    "tgn:name":"Gomm Hollow",
    "tgn:placetype":[
        "aat:300008761"
    ]
},
  "bbox": [],
  "geometry": {"coordinates":[-110.8333,42.7167],"type":"Point"}
}