{
  "id": 7590588,
  "type": "Feature",
  "properties": {
    "tgn:hierarchy":[
        "tgn:7590588",
        "tgn:1000004",
        "tgn:7000198",
        "tgn:7000799",
        "tgn:7029392"
    ],
    "tgn:id":7590588,
    "tgn:name:en":"Chhapar",
    "tgn:placetype":[
        "aat:300008699"
    ]
},
  "bbox": [],
  "geometry": {"coordinates":[74.388889,33.811111],"type":"Point"}
}