{
  "id": 7411736,
  "type": "Feature",
  "properties": {
    "tgn:hierarchy":[
        "tgn:7411736",
        "tgn:7005580",
        "tgn:1000001",
        "tgn:7005560",
        "tgn:7029392"
    ],
    "tgn:id":7411736,
    "tgn:name":"Chinal",
    "tgn:placetype":[
        "aat:300008347"
    ]
},
  "bbox": [],
  "geometry": {"coordinates":[-91.691667,17.475],"type":"Point"}
}