{
  "id": 2554529,
  "type": "Feature",
  "properties": {
    "tgn:hierarchy":[
        "tgn:2554529",
        "tgn:1000001",
        "tgn:7006451",
        "tgn:7012149",
        "tgn:2000104",
        "tgn:7029392"
    ],
    "tgn:id":2554529,
    "tgn:name":"Oakland Mine",
    "tgn:placetype":[
        "aat:300000390"
    ]
},
  "bbox": [],
  "geometry": {"coordinates":[-113.6833,33.35],"type":"Point"}
}