{
  "id": 7478490,
  "type": "Feature",
  "properties": {
    "tgn:hierarchy":[
        "tgn:7478490",
        "tgn:1000004",
        "tgn:7489179",
        "tgn:1000141",
        "tgn:7029392"
    ],
    "tgn:id":7478490,
    "tgn:name":"Xin'an Gong",
    "tgn:placetype":[
        "aat:300007595"
    ]
},
  "bbox": [],
  "geometry": {"coordinates":[121.814933,24.685367],"type":"Point"}
}