<<<<<<< HEAD
{
  "id": 7478490,
  "type": "Feature",
  "properties": {
    "tgn:hierarchy":[
        "tgn:7478490",
        "tgn:1000004",
        "tgn:7489179",
        "tgn:1000141",
        "tgn:7029392"
    ],
    "tgn:id":7478490,
    "tgn:name":"Xin'an Gong",
    "tgn:placetype":[
        "aat:300007595"
    ]
},
  "bbox": [],
  "geometry": {"coordinates":[121.814933,24.685367],"type":"Point"}
}
=======
{"geometry":{"type":"Point","coordinates":[121.814933,24.685367]},"type":"Feature","properties":{"hierarchy":["tgn:7478490","tgn:1000004","tgn:7489179","tgn:1000141","tgn:7029392"],"placetype":["aat:300007595"],"id":7478490,"name:xx":"Xin'an Gong"}}
>>>>>>> 03f74aca74312dbeaf24d7e61306dd6a786dc3d0
