<<<<<<< HEAD
{
  "id": 7026193,
  "type": "Feature",
  "properties": {
    "tgn:hierarchy":[
        "tgn:7026193",
        "tgn:7002445",
        "tgn:1000003",
        "tgn:7008167",
        "tgn:7008591",
        "tgn:7029392"
    ],
    "tgn:id":7026193,
    "tgn:name:en":"Newstead",
    "tgn:placetype":[
        "aat:300008347"
    ]
},
  "bbox": [],
  "geometry": {"coordinates":[-1.216667,53.066667],"type":"Point"}
}
=======
{"geometry":{"type":"Point","coordinates":[-1.216667,53.066667]},"type":"Feature","properties":{"hierarchy":["tgn:7026193","tgn:7002445","tgn:1000003","tgn:7008167","tgn:7008591","tgn:7029392"],"placetype":["aat:300008347"],"name:en":"Newstead","id":7026193}}
>>>>>>> 03f74aca74312dbeaf24d7e61306dd6a786dc3d0
