{
  "id": 7188232,
  "type": "Feature",
  "properties": {
    "tgn:hierarchy":[
        "tgn:7188232",
        "tgn:1000003",
        "tgn:7003688",
        "tgn:7000084",
        "tgn:7029392"
    ],
    "tgn:id":7188232,
    "tgn:name":"Estrup",
    "tgn:placetype":[
        "aat:300008347"
    ]
},
  "bbox": [],
  "geometry": {"coordinates":[9.533333,54.716667],"type":"Point"}
}