{
  "id": 1085537,
  "type": "Feature",
  "properties": {
    "tgn:hierarchy":[
        "tgn:1085537",
        "tgn:7000915",
        "tgn:7005194",
        "tgn:1000004",
        "tgn:1000142",
        "tgn:7029392"
    ],
    "tgn:id":1085537,
    "tgn:name":"Hot",
    "tgn:placetype":[
        "aat:300008347"
    ]
},
  "bbox": [],
  "geometry": {"coordinates":[98.5667,18.1167],"type":"Point"}
}