{
  "id": 2667084,
  "type": "Feature",
  "properties": {
    "tgn:hierarchy":[
        "tgn:2667084",
        "tgn:1000001",
        "tgn:2000459",
        "tgn:7012149",
        "tgn:7007250",
        "tgn:7029392"
    ],
    "tgn:id":2667084,
    "tgn:name":"Skid Road Creek",
    "tgn:placetype":[
        "aat:300008706"
    ]
},
  "bbox": [],
  "geometry": {"coordinates":[-115.9333,44.2167],"type":"Point"}
}