{
  "id": 2787026,
  "type": "Feature",
  "properties": {
    "tgn:hierarchy":[
        "tgn:2787026",
        "tgn:1000001",
        "tgn:7012149",
        "tgn:2001286",
        "tgn:7007524",
        "tgn:7029392"
    ],
    "tgn:id":2787026,
    "tgn:name":"Zimmerman Hill",
    "tgn:placetype":[
        "aat:300008798"
    ]
},
  "bbox": [],
  "geometry": {"coordinates":[-115.6167,48.9167],"type":"Point"}
}