{
  "id": 2692777,
  "type": "Feature",
  "properties": {
    "tgn:hierarchy":[
        "tgn:2692777",
        "tgn:1000001",
        "tgn:7012149",
        "tgn:2001622",
        "tgn:7007706",
        "tgn:7029392"
    ],
    "tgn:id":2692777,
    "tgn:name":"Steel Run",
    "tgn:placetype":[
        "aat:300008699"
    ]
},
  "bbox": [],
  "geometry": {"coordinates":[-81.2667,39.4833],"type":"Point"}
}