{
  "id": 7045180,
  "type": "Feature",
  "properties": {
    "tgn:hierarchy":[
        "tgn:7045180",
        "tgn:7003005",
        "tgn:7003014",
        "tgn:1000003",
        "tgn:1000080",
        "tgn:7029392"
    ],
    "tgn:id":7045180,
    "tgn:name":"Castelluccio Cosentino",
    "tgn:placetype":[
        "aat:300008347"
    ]
},
  "bbox": [],
  "geometry": {"coordinates":[15.35,40.583333],"type":"Point"}
}