{
  "id": 2074532,
  "type": "Feature",
  "properties": {
    "tgn:hierarchy":[
        "tgn:2074532",
        "tgn:1000001",
        "tgn:7012149",
        "tgn:2001540",
        "tgn:7007709",
        "tgn:7029392"
    ],
    "tgn:id":2074532,
    "tgn:name":"Endy",
    "tgn:placetype":[
        "aat:300008347"
    ]
},
  "bbox": [],
  "geometry": {"coordinates":[-80.2167,35.3167],"type":"Point"}
}