<<<<<<< HEAD
{
  "id": 2403107,
  "type": "Feature",
  "properties": {
    "tgn:hierarchy":[
        "tgn:2403107",
        "tgn:1000001",
        "tgn:7012149",
        "tgn:7007826",
        "tgn:7029392"
    ],
    "tgn:id":2403107,
    "tgn:name":"House Canyon",
    "tgn:placetype":[
        "aat:300008761"
    ]
},
  "bbox": [],
  "geometry": {"coordinates":[-101.6,30.3],"type":"Point"}
}
=======
{"geometry":{"type":"Point","coordinates":[-101.600000,30.300000]},"type":"Feature","properties":{"hierarchy":["tgn:2403107","tgn:1000001","tgn:7012149","tgn:7007826","tgn:7029392"],"placetype":["aat:300008761"],"id":2403107,"name:xx":"House Canyon"}}
>>>>>>> 03f74aca74312dbeaf24d7e61306dd6a786dc3d0
