{
  "id": 1058669,
  "type": "Feature",
  "properties": {
    "tgn:hierarchy":[
        "tgn:1058669",
        "tgn:7012076",
        "tgn:1000003",
        "tgn:7006660",
        "tgn:7029392"
    ],
    "tgn:id":1058669,
    "tgn:name":"Primoreskoye",
    "tgn:placetype":[
        "aat:300008347"
    ]
},
  "bbox": [],
  "geometry": {"coordinates":[37.6333,47.1667],"type":"Point"}
}