{
  "id": 2548798,
  "type": "Feature",
  "properties": {
    "tgn:hierarchy":[
        "tgn:2548798",
        "tgn:2002308",
        "tgn:1000001",
        "tgn:7012149",
        "tgn:7007922",
        "tgn:7029392"
    ],
    "tgn:id":2548798,
    "tgn:name":"North Pikes Creek",
    "tgn:placetype":[
        "aat:300008706"
    ]
},
  "bbox": [],
  "geometry": {"coordinates":[-90.85,46.8667],"type":"Point"}
}