{
  "id": 2142082,
  "type": "Feature",
  "properties": {
    "tgn:hierarchy":[
        "tgn:2142082",
        "tgn:1002338",
        "tgn:1000001",
        "tgn:7012149",
        "tgn:7007516",
        "tgn:7029392"
    ],
    "tgn:id":2142082,
    "tgn:name":"Back Creek",
    "tgn:placetype":[
        "aat:300132316"
    ]
},
  "bbox": [],
  "geometry": {"coordinates":[-76.2167,38.3167],"type":"Point"}
}