{
  "id": 2699663,
  "type": "Feature",
  "properties": {
    "tgn:hierarchy":[
        "tgn:2699663",
        "tgn:1000001",
        "tgn:7012149",
        "tgn:2002265",
        "tgn:7013961",
        "tgn:7029392"
    ],
    "tgn:id":2699663,
    "tgn:name":"Stuart Hollow",
    "tgn:placetype":[
        "aat:300008761"
    ]
},
  "bbox": [],
  "geometry": {"coordinates":[-78.5333,39.2333],"type":"Point"}
}