<<<<<<< HEAD
{
  "id": 2258368,
  "type": "Feature",
  "properties": {
    "tgn:hierarchy":[
        "tgn:2258368",
        "tgn:1000001",
        "tgn:2001702",
        "tgn:7012149",
        "tgn:7007708",
        "tgn:7029392"
    ],
    "tgn:id":2258368,
    "tgn:name":"Cotton Butte",
    "tgn:placetype":[
        "aat:300008798"
    ]
},
  "bbox": [],
  "geometry": {"coordinates":[-124.2833,42.95],"type":"Point"}
}
=======
{"geometry":{"type":"Point","coordinates":[-124.283300,42.950000]},"type":"Feature","properties":{"hierarchy":["tgn:2258368","tgn:1000001","tgn:2001702","tgn:7012149","tgn:7007708","tgn:7029392"],"placetype":["aat:300008798"],"id":2258368,"name:xx":"Cotton Butte"}}
>>>>>>> 03f74aca74312dbeaf24d7e61306dd6a786dc3d0
