{
  "id": 2258368,
  "type": "Feature",
  "properties": {
    "tgn:hierarchy":[
        "tgn:2258368",
        "tgn:1000001",
        "tgn:2001702",
        "tgn:7012149",
        "tgn:7007708",
        "tgn:7029392"
    ],
    "tgn:id":2258368,
    "tgn:name":"Cotton Butte",
    "tgn:placetype":[
        "aat:300008798"
    ]
},
  "bbox": [],
  "geometry": {"coordinates":[-124.2833,42.95],"type":"Point"}
}