{
  "id": 7565772,
  "type": "Feature",
  "properties": {
    "tgn:hierarchy":[
        "tgn:7565772",
        "tgn:1000004",
        "tgn:7000198",
        "tgn:7016722",
        "tgn:7029392"
    ],
    "tgn:id":7565772,
    "tgn:name:en":"Kunwarpura J\u0101laun",
    "tgn:placetype":[
        "aat:300008347"
    ]
},
  "bbox": [],
  "geometry": {"coordinates":[79.32587,26.070529],"type":"Point"}
}