<<<<<<< HEAD
{
  "id": 2255851,
  "type": "Feature",
  "properties": {
    "tgn:hierarchy":[
        "tgn:2255851",
        "tgn:1000001",
        "tgn:7012149",
        "tgn:7007255",
        "tgn:7029392"
    ],
    "tgn:id":2255851,
    "tgn:name":"Copper Creek",
    "tgn:placetype":[
        "aat:300008706"
    ]
},
  "bbox": [],
  "geometry": {"coordinates":[-84.35,37.5333],"type":"Point"}
}
=======
{"geometry":{"type":"Point","coordinates":[-84.350000,37.533300]},"type":"Feature","properties":{"hierarchy":["tgn:2255851","tgn:1000001","tgn:7012149","tgn:7007255","tgn:7029392"],"placetype":["aat:300008706"],"id":2255851,"name:xx":"Copper Creek"}}
>>>>>>> 03f74aca74312dbeaf24d7e61306dd6a786dc3d0
