{
  "id": 7041785,
  "type": "Feature",
  "properties": {
    "tgn:hierarchy":[
        "tgn:7041785",
        "tgn:7007850",
        "tgn:1003491",
        "tgn:1000003",
        "tgn:1000080",
        "tgn:7029392"
    ],
    "tgn:id":7041785,
    "tgn:name":"San Francesco",
    "tgn:placetype":[
        "aat:300008347"
    ]
},
  "bbox": [],
  "geometry": {"coordinates":[15.65,38.15],"type":"Point"}
}