{
  "id": 1031101,
  "type": "Feature",
  "properties": {
    "tgn:hierarchy":[
        "tgn:1031101",
        "tgn:7002445",
        "tgn:7008114",
        "tgn:1000003",
        "tgn:7008591",
        "tgn:7029392"
    ],
    "tgn:id":1031101,
    "tgn:name":"Whitby",
    "tgn:placetype":[
        "aat:300008347"
    ]
},
  "bbox": [],
  "geometry": {"coordinates":[-2.9167,53.2667],"type":"Point"}
}