{
  "id": 7514931,
  "type": "Feature",
  "properties": {
    "tgn:hierarchy":[
        "tgn:7514931",
        "tgn:1009227",
        "tgn:1000226",
        "tgn:1000006",
        "tgn:7016850",
        "tgn:7029392"
    ],
    "tgn:id":7514931,
    "tgn:name:en":"Commodore Ridge",
    "tgn:placetype":[
        "aat:300266640"
    ]
},
  "bbox": [],
  "geometry": {"coordinates":[171.216667,-42.983333],"type":"Point"}
}