<<<<<<< HEAD
{
  "id": 2406227,
  "type": "Feature",
  "properties": {
    "tgn:hierarchy":[
        "tgn:2406227",
        "tgn:1000001",
        "tgn:7012149",
        "tgn:7007524",
        "tgn:7029392"
    ],
    "tgn:id":2406227,
    "tgn:name":"Humphrey Coulee",
    "tgn:placetype":[
        "aat:300008761"
    ]
},
  "bbox": [],
  "geometry": {"coordinates":[-106.2833,47.8833],"type":"Point"}
}
=======
{"geometry":{"type":"Point","coordinates":[-106.283300,47.883300]},"type":"Feature","properties":{"hierarchy":["tgn:2406227","tgn:1000001","tgn:7012149","tgn:7007524","tgn:7029392"],"placetype":["aat:300008761"],"id":2406227,"name:xx":"Humphrey Coulee"}}
>>>>>>> 03f74aca74312dbeaf24d7e61306dd6a786dc3d0
