{
  "id": 7516010,
  "type": "Feature",
  "properties": {
    "tgn:hierarchy":[
        "tgn:7516010",
        "tgn:7000509",
        "tgn:1008380",
        "tgn:1000226",
        "tgn:1000006",
        "tgn:7029392"
    ],
    "tgn:id":7516010,
    "tgn:name:en":"Okiore",
    "tgn:placetype":[
        "aat:300008347"
    ]
},
  "bbox": [],
  "geometry": {"coordinates":[177.283333,-38.183333],"type":"Point"}
}