{
  "id": 2214838,
  "type": "Feature",
  "properties": {
    "tgn:hierarchy":[
        "tgn:2214838",
        "tgn:1002132",
        "tgn:1000001",
        "tgn:7012149",
        "tgn:7007919",
        "tgn:7029392"
    ],
    "tgn:id":2214838,
    "tgn:name":"Calfpen Bay",
    "tgn:placetype":[
        "aat:300132316"
    ]
},
  "bbox": [],
  "geometry": {"coordinates":[-75.2833,37.9833],"type":"Point"}
}