{
  "id": 2139808,
  "type": "Feature",
  "properties": {
    "tgn:hierarchy":[
        "tgn:2139808",
        "tgn:2001423",
        "tgn:1000001",
        "tgn:7012149",
        "tgn:7007564",
        "tgn:7029392"
    ],
    "tgn:id":2139808,
    "tgn:name":"Atkinson Mountain",
    "tgn:placetype":[
        "aat:300008798"
    ]
},
  "bbox": [],
  "geometry": {"coordinates":[-71.0667,43.9167],"type":"Point"}
}