{
  "id": 2784450,
  "type": "Feature",
  "properties": {
    "tgn:hierarchy":[
        "tgn:2784450",
        "tgn:1000001",
        "tgn:7012149",
        "tgn:1002679",
        "tgn:7007520",
        "tgn:7029392"
    ],
    "tgn:id":2784450,
    "tgn:name":"Yarger Drain",
    "tgn:placetype":[
        "aat:300006075"
    ]
},
  "bbox": [],
  "geometry": {"coordinates":[-83.5167,41.8333],"type":"Point"}
}