{
  "id": 2644171,
  "type": "Feature",
  "properties": {
    "tgn:hierarchy":[
        "tgn:2644171",
        "tgn:1000001",
        "tgn:7012149",
        "tgn:7007157",
        "tgn:7029392"
    ],
    "tgn:id":2644171,
    "tgn:name":"Santa Ynez Mountains",
    "tgn:placetype":[
        "aat:300386831"
    ]
},
  "bbox": [],
  "geometry": {"coordinates":[-120.0333,34.5333],"type":"Point"}
}