{
  "id": 2561358,
  "type": "Feature",
  "properties": {
    "tgn:hierarchy":[
        "tgn:2561358",
        "tgn:1000001",
        "tgn:7012149",
        "tgn:2002188",
        "tgn:7007919",
        "tgn:7029392"
    ],
    "tgn:id":2561358,
    "tgn:name":"Osborne Hollow",
    "tgn:placetype":[
        "aat:300008761"
    ]
},
  "bbox": [],
  "geometry": {"coordinates":[-82.3333,36.8333],"type":"Point"}
}