{
  "id": 2107732,
  "type": "Feature",
  "properties": {
    "tgn:hierarchy":[
        "tgn:2107732",
        "tgn:1000001",
        "tgn:7012149",
        "tgn:2002071",
        "tgn:7007826",
        "tgn:7029392"
    ],
    "tgn:id":2107732,
    "tgn:name":"Snyder",
    "tgn:placetype":[
        "aat:300008347"
    ]
},
  "bbox": [],
  "geometry": {"coordinates":[-100.9167,32.7167],"type":"Point"}
}