{
  "id": 7203134,
  "type": "Feature",
  "properties": {
    "tgn:hierarchy":[
        "tgn:7203134",
        "tgn:1000003",
        "tgn:7003677",
        "tgn:7000084",
        "tgn:7029392"
    ],
    "tgn:id":7203134,
    "tgn:name":"Broch",
    "tgn:placetype":[
        "aat:300008347"
    ]
},
  "bbox": [],
  "geometry": {"coordinates":[7.283333,51.05],"type":"Point"}
}