{
  "id": 2258481,
  "type": "Feature",
  "properties": {
    "tgn:hierarchy":[
        "tgn:2258481",
        "tgn:1000001",
        "tgn:7012149",
        "tgn:2001196",
        "tgn:7007523",
        "tgn:7029392"
    ],
    "tgn:id":2258481,
    "tgn:name":"Cotton Patch Hollow",
    "tgn:placetype":[
        "aat:300008761"
    ]
},
  "bbox": [],
  "geometry": {"coordinates":[-92.4333,36.8833],"type":"Point"}
}