<<<<<<< HEAD
{
  "id": 2258481,
  "type": "Feature",
  "properties": {
    "tgn:hierarchy":[
        "tgn:2258481",
        "tgn:1000001",
        "tgn:7012149",
        "tgn:2001196",
        "tgn:7007523",
        "tgn:7029392"
    ],
    "tgn:id":2258481,
    "tgn:name":"Cotton Patch Hollow",
    "tgn:placetype":[
        "aat:300008761"
    ]
},
  "bbox": [],
  "geometry": {"coordinates":[-92.4333,36.8833],"type":"Point"}
}
=======
{"geometry":{"type":"Point","coordinates":[-92.433300,36.883300]},"type":"Feature","properties":{"hierarchy":["tgn:2258481","tgn:1000001","tgn:7012149","tgn:2001196","tgn:7007523","tgn:7029392"],"placetype":["aat:300008761"],"id":2258481,"name:xx":"Cotton Patch Hollow"}}
>>>>>>> 03f74aca74312dbeaf24d7e61306dd6a786dc3d0
