{
  "id": 2199492,
  "type": "Feature",
  "properties": {
    "tgn:hierarchy":[
        "tgn:2199492",
        "tgn:1000001",
        "tgn:2001269",
        "tgn:7012149",
        "tgn:7007524",
        "tgn:7029392"
    ],
    "tgn:id":2199492,
    "tgn:name":"Brush Creek",
    "tgn:placetype":[
        "aat:300008706"
    ]
},
  "bbox": [],
  "geometry": {"coordinates":[-105.7667,48.8167],"type":"Point"}
}