{
  "id": 7316582,
  "type": "Feature",
  "properties": {
    "tgn:hierarchy":[
        "tgn:7316582",
        "tgn:1001692",
        "tgn:1000049",
        "tgn:1000002",
        "tgn:7029392"
    ],
    "tgn:id":7316582,
    "tgn:name":"Carriringue",
    "tgn:placetype":[
        "aat:300004792"
    ]
},
  "bbox": [],
  "geometry": {"coordinates":[-72.45,-39.033333],"type":"Point"}
}