{
  "id": 2314035,
  "type": "Feature",
  "properties": {
    "tgn:hierarchy":[
        "tgn:2314035",
        "tgn:1000001",
        "tgn:7012149",
        "tgn:2002122",
        "tgn:7007827",
        "tgn:7029392"
    ],
    "tgn:id":2314035,
    "tgn:name":"Elizabeth Mountain",
    "tgn:placetype":[
        "aat:300008798"
    ]
},
  "bbox": [],
  "geometry": {"coordinates":[-110.7167,40.9667],"type":"Point"}
}