{
  "id": 2688673,
  "type": "Feature",
  "properties": {
    "tgn:hierarchy":[
        "tgn:2688673",
        "tgn:1000001",
        "tgn:7012149",
        "tgn:2001719",
        "tgn:7007708",
        "tgn:7029392"
    ],
    "tgn:id":2688673,
    "tgn:name":"Spruce Spring",
    "tgn:placetype":[
        "aat:300008697"
    ]
},
  "bbox": [],
  "geometry": {"coordinates":[-119.2167,45.1667],"type":"Point"}
}