{
  "id": 2771654,
  "type": "Feature",
  "properties": {
    "tgn:hierarchy":[
        "tgn:2771654",
        "tgn:1000001",
        "tgn:2001584",
        "tgn:7012149",
        "tgn:7007705",
        "tgn:7029392"
    ],
    "tgn:id":2771654,
    "tgn:name":"Wildwood Lake",
    "tgn:placetype":[
        "aat:300008680"
    ]
},
  "bbox": [],
  "geometry": {"coordinates":[-100.95,47.1667],"type":"Point"}
}