{
  "id": 7469871,
  "type": "Feature",
  "properties": {
    "tgn:hierarchy":[
        "tgn:7469871",
        "tgn:1000004",
        "tgn:7490934",
        "tgn:1000141",
        "tgn:7029392"
    ],
    "tgn:id":7469871,
    "tgn:name":"Xiatan",
    "tgn:placetype":[
        "aat:300008347"
    ]
},
  "bbox": [],
  "geometry": {"coordinates":[120.288056,23.375278],"type":"Point"}
}