{
  "id": 7548790,
  "type": "Feature",
  "properties": {
    "tgn:hierarchy":[
        "tgn:7548790",
        "tgn:1000004",
        "tgn:7000198",
        "tgn:7000799",
        "tgn:7029392"
    ],
    "tgn:id":7548790,
    "tgn:name:en":"Burdun G\u00f6mpa",
    "tgn:placetype":[
        "aat:300008347"
    ]
},
  "bbox": [],
  "geometry": {"coordinates":[76.913454,33.397816],"type":"Point"}
}