{
  "id": 2527223,
  "type": "Feature",
  "properties": {
    "tgn:hierarchy":[
        "tgn:2527223",
        "tgn:1000001",
        "tgn:7012149",
        "tgn:2000657",
        "tgn:7007253",
        "tgn:7029392"
    ],
    "tgn:id":2527223,
    "tgn:name":"Mount Lucia",
    "tgn:placetype":[
        "aat:300008347"
    ]
},
  "bbox": [],
  "geometry": {"coordinates":[-96.45,42.5333],"type":"Point"}
}