{
  "id": 1060344,
  "type": "Feature",
  "properties": {
    "tgn:hierarchy":[
        "tgn:1060344",
        "tgn:1000004",
        "tgn:7011479",
        "tgn:7006655",
        "tgn:7029392"
    ],
    "tgn:id":1060344,
    "tgn:name":"Toguzbulak",
    "tgn:placetype":[
        "aat:300008347"
    ]
},
  "bbox": [],
  "geometry": {"coordinates":[76.7333,42.0833],"type":"Point"}
}