{
  "id": 7329425,
  "type": "Feature",
  "properties": {
    "tgn:hierarchy":[
        "tgn:7329425",
        "tgn:7002760",
        "tgn:1000003",
        "tgn:1000095",
        "tgn:7029392"
    ],
    "tgn:id":7329425,
    "tgn:name":"Marnay, Islote",
    "tgn:placetype":[
        "aat:300011692"
    ]
},
  "bbox": [],
  "geometry": {"coordinates":[-3.796667,43.433611],"type":"Point"}
}