{
  "id": 1064917,
  "type": "Feature",
  "properties": {
    "tgn:hierarchy":[
        "tgn:1064917",
        "tgn:1000003",
        "tgn:7006669",
        "tgn:7029392"
    ],
    "tgn:id":1064917,
    "tgn:name":"Bela Palanka",
    "tgn:placetype":[
        "aat:300008347"
    ]
},
  "bbox": [],
  "geometry": {"coordinates":[22.2833,43.2167],"type":"Point"}
}