{
  "id": 2073003,
  "type": "Feature",
  "properties": {
    "tgn:hierarchy":[
        "tgn:2073003",
        "tgn:1000001",
        "tgn:1002259",
        "tgn:7012149",
        "tgn:7007568",
        "tgn:7029392"
    ],
    "tgn:id":2073003,
    "tgn:name":"Wattlesburg",
    "tgn:placetype":[
        "aat:300008347",
        "aat:300387210"
    ]
},
  "bbox": [],
  "geometry": {"coordinates":[-79.6833,42.2167],"type":"Point"}
}