{
  "id": 7448177,
  "type": "Feature",
  "properties": {
    "tgn:hierarchy":[
        "tgn:7448177",
        "tgn:7002445",
        "tgn:1000003",
        "tgn:7008166",
        "tgn:7008591",
        "tgn:7029392"
    ],
    "tgn:id":7448177,
    "tgn:name:en":"Stainsacre",
    "tgn:placetype":[
        "aat:300008347"
    ]
},
  "bbox": [],
  "geometry": {"coordinates":[-0.583333,54.45],"type":"Point"}
}