{
  "id": 2528823,
  "type": "Feature",
  "properties": {
    "tgn:hierarchy":[
        "tgn:2528823",
        "tgn:1000001",
        "tgn:7012149",
        "tgn:2000519",
        "tgn:7007251",
        "tgn:7029392"
    ],
    "tgn:id":2528823,
    "tgn:name":"Mud Creek",
    "tgn:placetype":[
        "aat:300008706"
    ]
},
  "bbox": [],
  "geometry": {"coordinates":[-88.4833,37.1167],"type":"Point"}
}