{
  "id": 2204059,
  "type": "Feature",
  "properties": {
    "tgn:hierarchy":[
        "tgn:2204059",
        "tgn:1000001",
        "tgn:1002714",
        "tgn:7012149",
        "tgn:7007159",
        "tgn:7029392"
    ],
    "tgn:id":2204059,
    "tgn:name":"Buddington Pond",
    "tgn:placetype":[
        "aat:300008680"
    ]
},
  "bbox": [],
  "geometry": {"coordinates":[-72.0333,41.3667],"type":"Point"}
}