{
  "id": 7050386,
  "type": "Feature",
  "properties": {
    "tgn:hierarchy":[
        "tgn:7050386",
        "tgn:1000003",
        "tgn:7003122",
        "tgn:1000080",
        "tgn:7029392"
    ],
    "tgn:id":7050386,
    "tgn:name":"Mazzar\u00e0, Torrente",
    "tgn:placetype":[
        "aat:300008699"
    ]
},
  "bbox": [],
  "geometry": {"coordinates":[15.15,38.15],"type":"Point"}
}