{
  "id": 2279168,
  "type": "Feature",
  "properties": {
    "tgn:hierarchy":[
        "tgn:2279168",
        "tgn:1000001",
        "tgn:7012149",
        "tgn:2002376",
        "tgn:7007923",
        "tgn:7029392"
    ],
    "tgn:id":2279168,
    "tgn:name":"Deadhorse Canyon",
    "tgn:placetype":[
        "aat:300008761"
    ]
},
  "bbox": [],
  "geometry": {"coordinates":[-110.9333,43.2333],"type":"Point"}
}