{
  "id": 2629849,
  "type": "Feature",
  "properties": {
    "tgn:hierarchy":[
        "tgn:2629849",
        "tgn:1000001",
        "tgn:7012149",
        "tgn:2001167",
        "tgn:7007522",
        "tgn:7029392"
    ],
    "tgn:id":2629849,
    "tgn:name":"Ross Lake",
    "tgn:placetype":[
        "aat:300008680"
    ]
},
  "bbox": [],
  "geometry": {"coordinates":[-90.1333,32.6833],"type":"Point"}
}