{
  "id": 2642356,
  "type": "Feature",
  "properties": {
    "tgn:hierarchy":[
        "tgn:2642356",
        "tgn:1000001",
        "tgn:7012149",
        "tgn:2000232",
        "tgn:7007158",
        "tgn:7029392"
    ],
    "tgn:id":2642356,
    "tgn:name":"Sand Spring Gulch",
    "tgn:placetype":[
        "aat:300008761"
    ]
},
  "bbox": [],
  "geometry": {"coordinates":[-107.65,40.5333],"type":"Point"}
}