{
  "id": 7308710,
  "type": "Feature",
  "properties": {
    "tgn:hierarchy":[
        "tgn:7308710",
        "tgn:1001708",
        "tgn:1000049",
        "tgn:1000002",
        "tgn:7029392"
    ],
    "tgn:id":7308710,
    "tgn:name":"Manantiales, Quebrada de",
    "tgn:placetype":[
        "aat:300008699"
    ]
},
  "bbox": [],
  "geometry": {"coordinates":[-71.133333,-33.316667],"type":"Point"}
}