{
  "id": 7262193,
  "type": "Feature",
  "properties": {
    "tgn:concordances":{
        "gn:id":"2756946"
    },
    "tgn:hierarchy":[
        "tgn:7262193",
        "tgn:1000003",
        "tgn:7003624",
        "tgn:7016845",
        "tgn:7029392"
    ],
    "tgn:id":7262193,
    "tgn:name:nl":"De Weijer",
    "tgn:placetype":[
        "aat:300008347"
    ]
},
  "bbox": [],
  "geometry": {"coordinates":[5.716667,51.45],"type":"Point"}
}