{
  "id": 7298726,
  "type": "Feature",
  "properties": {
    "tgn:hierarchy":[
        "tgn:7298726",
        "tgn:7002824",
        "tgn:1000003",
        "tgn:7002786",
        "tgn:1000095",
        "tgn:7029392"
    ],
    "tgn:id":7298726,
    "tgn:name":"Vado, Punta del",
    "tgn:placetype":[
        "aat:300386846"
    ]
},
  "bbox": [],
  "geometry": {"coordinates":[-8.85,42.55],"type":"Point"}
}