{
  "id": 2164992,
  "type": "Feature",
  "properties": {
    "tgn:hierarchy":[
        "tgn:2164992",
        "tgn:1000001",
        "tgn:2000870",
        "tgn:7012149",
        "tgn:7007256",
        "tgn:7029392"
    ],
    "tgn:id":2164992,
    "tgn:name":"Bethany Cooperative Community",
    "tgn:placetype":[
        "aat:300008347"
    ]
},
  "bbox": [],
  "geometry": {"coordinates":[-91.1333,30.5667],"type":"Point"}
}