<<<<<<< HEAD
{
  "id": 2250715,
  "type": "Feature",
  "properties": {
    "tgn:hierarchy":[
        "tgn:2250715",
        "tgn:1000001",
        "tgn:2001741",
        "tgn:7012149",
        "tgn:7007712",
        "tgn:7029392"
    ],
    "tgn:id":2250715,
    "tgn:name":"Colson Bay",
    "tgn:placetype":[
        "aat:300386845"
    ]
},
  "bbox": [],
  "geometry": {"coordinates":[-79.2333,34.3667],"type":"Point"}
}
=======
{"geometry":{"type":"Point","coordinates":[-79.233300,34.366700]},"type":"Feature","properties":{"hierarchy":["tgn:2250715","tgn:1000001","tgn:2001741","tgn:7012149","tgn:7007712","tgn:7029392"],"placetype":["aat:300386845"],"id":2250715,"name:xx":"Colson Bay"}}
>>>>>>> 03f74aca74312dbeaf24d7e61306dd6a786dc3d0
