{
  "id": 2250715,
  "type": "Feature",
  "properties": {
    "tgn:hierarchy":[
        "tgn:2250715",
        "tgn:1000001",
        "tgn:2001741",
        "tgn:7012149",
        "tgn:7007712",
        "tgn:7029392"
    ],
    "tgn:id":2250715,
    "tgn:name":"Colson Bay",
    "tgn:placetype":[
        "aat:300386845"
    ]
},
  "bbox": [],
  "geometry": {"coordinates":[-79.2333,34.3667],"type":"Point"}
}