{
  "id": 2078744,
  "type": "Feature",
  "properties": {
    "tgn:hierarchy":[
        "tgn:2078744",
        "tgn:1000001",
        "tgn:7012149",
        "tgn:2001616",
        "tgn:7007706",
        "tgn:7029392"
    ],
    "tgn:id":2078744,
    "tgn:name":"Carpenter",
    "tgn:placetype":[
        "aat:300008347"
    ]
},
  "bbox": [],
  "geometry": {"coordinates":[-82.2167,39.15],"type":"Point"}
}