{
  "id": 7558004,
  "type": "Feature",
  "properties": {
    "tgn:hierarchy":[
        "tgn:7558004",
        "tgn:1000004",
        "tgn:7000198",
        "tgn:1001894",
        "tgn:7029392"
    ],
    "tgn:id":7558004,
    "tgn:name:en":"Panna Hills",
    "tgn:placetype":[
        "aat:300008795"
    ]
},
  "bbox": [],
  "geometry": {"coordinates":[81.183333,24.866667],"type":"Point"}
}