<<<<<<< HEAD
{
  "id": 7242484,
  "type": "Feature",
  "properties": {
    "tgn:hierarchy":[
        "tgn:7242484",
        "tgn:7003460",
        "tgn:1000003",
        "tgn:1000063",
        "tgn:4012014",
        "tgn:7029392"
    ],
    "tgn:id":7242484,
    "tgn:name":"Longfaye",
    "tgn:placetype":[
        "aat:300008347"
    ]
},
  "bbox": [],
  "geometry": {"coordinates":[6.083333,50.466667],"type":"Point"}
}
=======
{"geometry":{"type":"Point","coordinates":[6.083333,50.466667]},"type":"Feature","properties":{"hierarchy":["tgn:7242484","tgn:7003460","tgn:1000003","tgn:1000063","tgn:4012014","tgn:7029392"],"placetype":["aat:300008347"],"id":7242484,"name:xx":"Longfaye"}}
>>>>>>> 03f74aca74312dbeaf24d7e61306dd6a786dc3d0
