{
  "id": 2267368,
  "type": "Feature",
  "properties": {
    "tgn:hierarchy":[
        "tgn:2267368",
        "tgn:1000001",
        "tgn:7006451",
        "tgn:7012149",
        "tgn:2000097",
        "tgn:7029392"
    ],
    "tgn:id":2267368,
    "tgn:name":"Crismon, Canal",
    "tgn:placetype":[
        "aat:300006075",
        "aat:300000833"
    ]
},
  "bbox": [],
  "geometry": {"coordinates":[-111.7833,33.4667],"type":"Point"}
}