<<<<<<< HEAD
{
  "id": 2154953,
  "type": "Feature",
  "properties": {
    "tgn:hierarchy":[
        "tgn:2154953",
        "tgn:1000001",
        "tgn:7012149",
        "tgn:2000905",
        "tgn:7007256",
        "tgn:7029392"
    ],
    "tgn:id":2154953,
    "tgn:name":"Bear Island",
    "tgn:placetype":[
        "aat:300008791"
    ]
},
  "bbox": [],
  "geometry": {"coordinates":[-89.8,30.4833],"type":"Point"}
}
=======
{"geometry":{"type":"Point","coordinates":[-89.800000,30.483300]},"type":"Feature","properties":{"hierarchy":["tgn:2154953","tgn:1000001","tgn:7012149","tgn:2000905","tgn:7007256","tgn:7029392"],"placetype":["aat:300008791"],"id":2154953,"name:xx":"Bear Island"}}
>>>>>>> 03f74aca74312dbeaf24d7e61306dd6a786dc3d0
