<<<<<<< HEAD
{
  "id": 7024778,
  "type": "Feature",
  "properties": {
    "tgn:hierarchy":[
        "tgn:7024778",
        "tgn:7002445",
        "tgn:1000003",
        "tgn:7026489",
        "tgn:7008591",
        "tgn:7029392"
    ],
    "tgn:id":7024778,
    "tgn:name:en":"Caversham",
    "tgn:placetype":[
        "aat:300008347"
    ]
},
  "bbox": [],
  "geometry": {"coordinates":[-0.966667,51.466667],"type":"Point"}
}
=======
{"geometry":{"type":"Point","coordinates":[-0.966667,51.466667]},"type":"Feature","properties":{"hierarchy":["tgn:7024778","tgn:7002445","tgn:1000003","tgn:7026489","tgn:7008591","tgn:7029392"],"placetype":["aat:300008347"],"name:en":"Caversham","id":7024778}}
>>>>>>> 03f74aca74312dbeaf24d7e61306dd6a786dc3d0
