{
  "id": 2498910,
  "type": "Feature",
  "properties": {
    "tgn:hierarchy":[
        "tgn:2498910",
        "tgn:1000001",
        "tgn:7012149",
        "tgn:1002939",
        "tgn:7007826",
        "tgn:7029392"
    ],
    "tgn:id":2498910,
    "tgn:name":"McCann Branch",
    "tgn:placetype":[
        "aat:300008699"
    ]
},
  "bbox": [],
  "geometry": {"coordinates":[-97.45,32.95],"type":"Point"}
}