{
  "id": 2680618,
  "type": "Feature",
  "properties": {
    "tgn:hierarchy":[
        "tgn:2680618",
        "tgn:1000001",
        "tgn:7012149",
        "tgn:1002594",
        "tgn:7007920",
        "tgn:7029392"
    ],
    "tgn:id":2680618,
    "tgn:name":"South Hanaford Creek",
    "tgn:placetype":[
        "aat:300008706"
    ]
},
  "bbox": [],
  "geometry": {"coordinates":[-122.7667,46.6833],"type":"Point"}
}