{
  "id": 7135936,
  "type": "Feature",
  "properties": {
    "tgn:hierarchy":[
        "tgn:7135936",
        "tgn:7000096",
        "tgn:1000003",
        "tgn:7000084",
        "tgn:7029392"
    ],
    "tgn:id":7135936,
    "tgn:name":"M\u00fchlenfenn",
    "tgn:placetype":[
        "aat:300008903"
    ]
},
  "bbox": [],
  "geometry": {"coordinates":[12.466667,52.35],"type":"Point"}
}