{
  "id": 7565703,
  "type": "Feature",
  "properties": {
    "tgn:hierarchy":[
        "tgn:7565703",
        "tgn:1000004",
        "tgn:7000198",
        "tgn:7016788",
        "tgn:7029392"
    ],
    "tgn:id":7565703,
    "tgn:name:en":"Si Thal",
    "tgn:placetype":[
        "aat:300008347"
    ]
},
  "bbox": [],
  "geometry": {"coordinates":[71.880796,27.734883],"type":"Point"}
}