{
  "id": 2532243,
  "type": "Feature",
  "properties": {
    "tgn:hierarchy":[
        "tgn:2532243",
        "tgn:7002659",
        "tgn:1000001",
        "tgn:7012149",
        "tgn:2000022",
        "tgn:7029392"
    ],
    "tgn:id":2532243,
    "tgn:name":"Munson Heights",
    "tgn:placetype":[
        "aat:300008347"
    ]
},
  "bbox": [],
  "geometry": {"coordinates":[-85.7167,31.3333],"type":"Point"}
}