{
  "id": 1014860,
  "type": "Feature",
  "properties": {
    "tgn:hierarchy":[
        "tgn:1014860",
        "tgn:7005685",
        "tgn:1000001",
        "tgn:7013154",
        "tgn:7029392"
    ],
    "tgn:id":1014860,
    "tgn:name":"Kinmount",
    "tgn:placetype":[
        "aat:300008347"
    ]
},
  "bbox": [],
  "geometry": {"coordinates":[-78.65,44.7833],"type":"Point"}
}