{
  "id": 7506520,
  "type": "Feature",
  "properties": {
    "tgn:hierarchy":[
        "tgn:7506520",
        "tgn:1009227",
        "tgn:1000226",
        "tgn:7016822",
        "tgn:1000006",
        "tgn:7029392"
    ],
    "tgn:id":7506520,
    "tgn:name:en":"Rogers Point",
    "tgn:placetype":[
        "aat:300386846"
    ]
},
  "bbox": [],
  "geometry": {"coordinates":[166.933333,-45.333333],"type":"Point"}
}