{
  "id": 7594031,
  "type": "Feature",
  "properties": {
    "tgn:hierarchy":[
        "tgn:7594031",
        "tgn:1000003",
        "tgn:7006542",
        "tgn:7029392"
    ],
    "tgn:id":7594031,
    "tgn:name":"Druskininkai",
    "tgn:placetype":[
        "aat:300387064",
        "aat:300265612"
    ]
},
  "bbox": [],
  "geometry": {"coordinates":[23.966,54.016],"type":"Point"}
}