{
  "id": 7411848,
  "type": "Feature",
  "properties": {
    "tgn:hierarchy":[
        "tgn:7411848",
        "tgn:7005587",
        "tgn:1000001",
        "tgn:7005560",
        "tgn:7029392"
    ],
    "tgn:id":7411848,
    "tgn:name:es":"Pesmayo",
    "tgn:placetype":[
        "aat:300008347"
    ]
},
  "bbox": [],
  "geometry": {"coordinates":[-98.283333,20.825],"type":"Point"}
}