{
  "id": 1117412,
  "type": "Feature",
  "properties": {
    "tgn:hierarchy":[
        "tgn:1117412",
        "tgn:7005694",
        "tgn:7005685",
        "tgn:1000001",
        "tgn:7029392"
    ],
    "tgn:id":1117412,
    "tgn:name":"Muskwa Lake",
    "tgn:placetype":[
        "aat:300008680"
    ]
},
  "bbox": [],
  "geometry": {"coordinates":[-114.6333,56.15],"type":"Point"}
}