{
  "id": 2396768,
  "type": "Feature",
  "properties": {
    "tgn:hierarchy":[
        "tgn:2396768",
        "tgn:1000001",
        "tgn:7012149",
        "tgn:2001053",
        "tgn:7007521",
        "tgn:7029392"
    ],
    "tgn:id":2396768,
    "tgn:name":"Home Creek",
    "tgn:placetype":[
        "aat:300008706"
    ]
},
  "bbox": [],
  "geometry": {"coordinates":[-92.3833,43.9167],"type":"Point"}
}