{
  "id": 2481446,
  "type": "Feature",
  "properties": {
    "tgn:hierarchy":[
        "tgn:2481446",
        "tgn:1000001",
        "tgn:7012149",
        "tgn:2001712",
        "tgn:7007708",
        "tgn:7029392"
    ],
    "tgn:id":2481446,
    "tgn:name":"Lamonta",
    "tgn:placetype":[
        "aat:300008347"
    ]
},
  "bbox": [],
  "geometry": {"coordinates":[-121.0333,44.4667],"type":"Point"}
}