{
  "id": 7280188,
  "type": "Feature",
  "properties": {
    "tgn:hierarchy":[
        "tgn:7280188",
        "tgn:7002464",
        "tgn:1000049",
        "tgn:1000002",
        "tgn:7029392"
    ],
    "tgn:id":7280188,
    "tgn:name":"Ra\u00fal, Cerro",
    "tgn:placetype":[
        "aat:300008795"
    ]
},
  "bbox": [],
  "geometry": {"coordinates":[-69.266667,-21.083333],"type":"Point"}
}