{
  "id": 7429886,
  "type": "Feature",
  "properties": {
    "tgn:hierarchy":[
        "tgn:7429886",
        "tgn:7005583",
        "tgn:1000001",
        "tgn:7005560",
        "tgn:7029392"
    ],
    "tgn:id":7429886,
    "tgn:name":"Victor Manuel Sanchez",
    "tgn:placetype":[
        "aat:300008347"
    ]
},
  "bbox": [],
  "geometry": {"coordinates":[-104.15,24.95],"type":"Point"}
}