{
  "id": 2183380,
  "type": "Feature",
  "properties": {
    "tgn:hierarchy":[
        "tgn:2183380",
        "tgn:1000001",
        "tgn:7012149",
        "tgn:1002486",
        "tgn:7007826",
        "tgn:7029392"
    ],
    "tgn:id":2183380,
    "tgn:name":"Bluff Creek",
    "tgn:placetype":[
        "aat:300008706"
    ]
},
  "bbox": [],
  "geometry": {"coordinates":[-95.1667,31.55],"type":"Point"}
}