{
  "id": 7533853,
  "type": "Feature",
  "properties": {
    "tgn:hierarchy":[
        "tgn:7533853",
        "tgn:7001242",
        "tgn:7001311",
        "tgn:7016833",
        "tgn:7029392"
    ],
    "tgn:id":7533853,
    "tgn:name:en":"\u1e28amr\u0101wayn, Jabal",
    "tgn:placetype":[
        "aat:300008795"
    ]
},
  "bbox": [],
  "geometry": {"coordinates":[34.037366,26.208608],"type":"Point"}
}