{
  "id": 2418547,
  "type": "Feature",
  "properties": {
    "tgn:hierarchy":[
        "tgn:2418547",
        "tgn:1000001",
        "tgn:7012149",
        "tgn:7007157",
        "tgn:1002566",
        "tgn:7029392"
    ],
    "tgn:id":2418547,
    "tgn:name":"Jago Bay",
    "tgn:placetype":[
        "aat:300132316"
    ]
},
  "bbox": [],
  "geometry": {"coordinates":[-122.6667,38.9333],"type":"Point"}
}