{
  "id": 2212009,
  "type": "Feature",
  "properties": {
    "tgn:hierarchy":[
        "tgn:2212009",
        "tgn:1000001",
        "tgn:7012149",
        "tgn:2001921",
        "tgn:7007825",
        "tgn:7029392"
    ],
    "tgn:id":2212009,
    "tgn:name":"Buzzard Cave",
    "tgn:placetype":[
        "aat:300008746"
    ]
},
  "bbox": [],
  "geometry": {"coordinates":[-86.2333,36.3167],"type":"Point"}
}