{
  "id": 2205666,
  "type": "Feature",
  "properties": {
    "tgn:hierarchy":[
        "tgn:2205666",
        "tgn:1000001",
        "tgn:7012149",
        "tgn:1002604",
        "tgn:7007568",
        "tgn:7029392"
    ],
    "tgn:id":2205666,
    "tgn:name":"Bull Head Pond",
    "tgn:placetype":[
        "aat:300008680"
    ]
},
  "bbox": [],
  "geometry": {"coordinates":[-77.75,42.85],"type":"Point"}
}