{
  "id": 1019418,
  "type": "Feature",
  "properties": {
    "tgn:hierarchy":[
        "tgn:1019418",
        "tgn:1001182",
        "tgn:7006477",
        "tgn:1000002",
        "tgn:7029392"
    ],
    "tgn:id":1019418,
    "tgn:name":"El Puesto",
    "tgn:placetype":[
        "aat:300008347"
    ]
},
  "bbox": [],
  "geometry": {"coordinates":[-67.6333,-27.95],"type":"Point"}
}