{
  "id": 7516073,
  "type": "Feature",
  "properties": {
    "tgn:hierarchy":[
        "tgn:7516073",
        "tgn:1008380",
        "tgn:7000507",
        "tgn:1000226",
        "tgn:1000006",
        "tgn:7029392"
    ],
    "tgn:id":7516073,
    "tgn:name:en":"Marotere Islands",
    "tgn:placetype":[
        "aat:300008791"
    ]
},
  "bbox": [],
  "geometry": {"coordinates":[174.75,-35.883333],"type":"Point"}
}