<<<<<<< HEAD
{
  "id": 7020224,
  "type": "Feature",
  "properties": {
    "tgn:hierarchy":[
        "tgn:7020224",
        "tgn:1000001",
        "tgn:7012149",
        "tgn:2001488",
        "tgn:7007709",
        "tgn:7029392"
    ],
    "tgn:id":7020224,
    "tgn:name":"Jeanette Sedge",
    "tgn:placetype":[
        "aat:300008905"
    ]
},
  "bbox": [],
  "geometry": {"coordinates":[-75.5333,35.25],"type":"Point"}
}
=======
{"geometry":{"type":"Point","coordinates":[-75.533300,35.250000]},"type":"Feature","properties":{"hierarchy":["tgn:7020224","tgn:1000001","tgn:7012149","tgn:2001488","tgn:7007709","tgn:7029392"],"placetype":["aat:300008905"],"id":7020224,"name:xx":"Jeanette Sedge"}}
>>>>>>> 03f74aca74312dbeaf24d7e61306dd6a786dc3d0
