{
  "id": 7576361,
  "type": "Feature",
  "properties": {
    "tgn:hierarchy":[
        "tgn:7576361",
        "tgn:1000004",
        "tgn:7000198",
        "tgn:7000799",
        "tgn:7029392"
    ],
    "tgn:id":7576361,
    "tgn:name:en":"Lamzo La",
    "tgn:placetype":[
        "aat:300259572"
    ]
},
  "bbox": [],
  "geometry": {"coordinates":[78.481009,34.049253],"type":"Point"}
}