{
  "id": 2588697,
  "type": "Feature",
  "properties": {
    "tgn:hierarchy":[
        "tgn:2588697",
        "tgn:1000001",
        "tgn:7012149",
        "tgn:2000398",
        "tgn:7007248",
        "tgn:7029392"
    ],
    "tgn:id":2588697,
    "tgn:name":"Plunkett Neck",
    "tgn:placetype":[
        "aat:300132316"
    ]
},
  "bbox": [],
  "geometry": {"coordinates":[-83.85,33.3667],"type":"Point"}
}