{
  "id": 1034602,
  "type": "Feature",
  "properties": {
    "tgn:hierarchy":[
        "tgn:1034602",
        "tgn:1000003",
        "tgn:7012216",
        "tgn:1000070",
        "tgn:7029392"
    ],
    "tgn:id":1034602,
    "tgn:name":"Muzillac",
    "tgn:placetype":[
        "aat:300008347"
    ]
},
  "bbox": [],
  "geometry": {"coordinates":[-2.4667,47.5667],"type":"Point"}
}