{
  "id": 7424446,
  "type": "Feature",
  "properties": {
    "tgn:hierarchy":[
        "tgn:7424446",
        "tgn:1000001",
        "tgn:1001906",
        "tgn:7005560",
        "tgn:7029392"
    ],
    "tgn:id":7424446,
    "tgn:name":"El Diablo, Cerro",
    "tgn:placetype":[
        "aat:300008795"
    ]
},
  "bbox": [],
  "geometry": {"coordinates":[-105.293889,22.246111],"type":"Point"}
}