{
  "id": 2345794,
  "type": "Feature",
  "properties": {
    "tgn:hierarchy":[
        "tgn:2345794",
        "tgn:1000001",
        "tgn:7012149",
        "tgn:2000350",
        "tgn:7007248",
        "tgn:7029392"
    ],
    "tgn:id":2345794,
    "tgn:name":"Garrison Pond",
    "tgn:placetype":[
        "aat:300006191"
    ]
},
  "bbox": [],
  "geometry": {"coordinates":[-83.3667,34.3667],"type":"Point"}
}