{
  "id": 7075837,
  "type": "Feature",
  "properties": {
    "tgn:hierarchy":[
        "tgn:7075837",
        "tgn:1000003",
        "tgn:7003678",
        "tgn:7000084",
        "tgn:7029392"
    ],
    "tgn:id":7075837,
    "tgn:name":"Linsengericht",
    "tgn:placetype":[
        "aat:300387173"
    ]
},
  "bbox": [],
  "geometry": {"coordinates":[9.216667,50.166667],"type":"Point"}
}