{
  "id": 7538930,
  "type": "Feature",
  "properties": {
    "tgn:hierarchy":[
        "tgn:7538930",
        "tgn:7001242",
        "tgn:7016833",
        "tgn:7001335",
        "tgn:7029392"
    ],
    "tgn:id":7538930,
    "tgn:name":"Mustabiq, Sabkhat al",
    "tgn:placetype":[
        "aat:300386999"
    ]
},
  "bbox": [],
  "geometry": {"coordinates":[33.320845,31.028382],"type":"Point"}
}