{
  "id": 2287308,
  "type": "Feature",
  "properties": {
    "tgn:hierarchy":[
        "tgn:2287308",
        "tgn:1000001",
        "tgn:7012149",
        "tgn:2001614",
        "tgn:7007706",
        "tgn:7029392"
    ],
    "tgn:id":2287308,
    "tgn:name":"Dicks Creek",
    "tgn:placetype":[
        "aat:300008706"
    ]
},
  "bbox": [],
  "geometry": {"coordinates":[-82.55,38.8833],"type":"Point"}
}