{
  "id": 2165212,
  "type": "Feature",
  "properties": {
    "tgn:hierarchy":[
        "tgn:2165212",
        "tgn:1000001",
        "tgn:7012149",
        "tgn:2000969",
        "tgn:7007520",
        "tgn:7029392"
    ],
    "tgn:id":2165212,
    "tgn:name":"Betsy Bay",
    "tgn:placetype":[
        "aat:300132316"
    ]
},
  "bbox": [],
  "geometry": {"coordinates":[-88.05,47.2833],"type":"Point"}
}