{
  "id": 1041939,
  "type": "Feature",
  "properties": {
    "tgn:hierarchy":[
        "tgn:1041939",
        "tgn:7002681",
        "tgn:7001395",
        "tgn:1000003",
        "tgn:1000074",
        "tgn:7029392"
    ],
    "tgn:id":1041939,
    "tgn:name":"\u00c1gioi An\u00e1rgyroi",
    "tgn:placetype":[
        "aat:300008347"
    ]
},
  "bbox": [],
  "geometry": {"coordinates":[23.723,38.03],"type":"Point"}
}