{
  "id": 7452578,
  "type": "Feature",
  "properties": {
    "tgn:hierarchy":[
        "tgn:7452578",
        "tgn:7002443",
        "tgn:1000003",
        "tgn:7029493",
        "tgn:7008591",
        "tgn:7029392"
    ],
    "tgn:id":7452578,
    "tgn:name:en":"Gorad Goch, Ynys",
    "tgn:placetype":[
        "aat:300008791"
    ]
},
  "bbox": [],
  "geometry": {"coordinates":[-4.183333,53.216667],"type":"Point"}
}