<<<<<<< HEAD
{
  "id": 7479187,
  "type": "Feature",
  "properties": {
    "tgn:hierarchy":[
        "tgn:7479187",
        "tgn:1000004",
        "tgn:7490934",
        "tgn:1000141",
        "tgn:7029392"
    ],
    "tgn:id":7479187,
    "tgn:name":"Hailiao Ti",
    "tgn:placetype":[
        "aat:300006156"
    ]
},
  "bbox": [],
  "geometry": {"coordinates":[120.183333,23.092778],"type":"Point"}
}
=======
{"geometry":{"type":"Point","coordinates":[120.183333,23.092778]},"type":"Feature","properties":{"hierarchy":["tgn:7479187","tgn:1000004","tgn:7490934","tgn:1000141","tgn:7029392"],"placetype":["aat:300006156"],"id":7479187,"name:xx":"Hailiao Ti"}}
>>>>>>> 03f74aca74312dbeaf24d7e61306dd6a786dc3d0
