{
  "id": 7479187,
  "type": "Feature",
  "properties": {
    "tgn:hierarchy":[
        "tgn:7479187",
        "tgn:1000004",
        "tgn:7490934",
        "tgn:1000141",
        "tgn:7029392"
    ],
    "tgn:id":7479187,
    "tgn:name":"Hailiao Ti",
    "tgn:placetype":[
        "aat:300006156"
    ]
},
  "bbox": [],
  "geometry": {"coordinates":[120.183333,23.092778],"type":"Point"}
}