{
  "id": 7118628,
  "type": "Feature",
  "properties": {
    "tgn:hierarchy":[
        "tgn:7118628",
        "tgn:7003669",
        "tgn:1000003",
        "tgn:7000084",
        "tgn:7029392"
    ],
    "tgn:id":7118628,
    "tgn:name":"Pollersbach",
    "tgn:placetype":[
        "aat:300000206"
    ]
},
  "bbox": [],
  "geometry": {"coordinates":[12.733333,48.416667],"type":"Point"}
}