{
  "id": 2466941,
  "type": "Feature",
  "properties": {
    "tgn:hierarchy":[
        "tgn:2466941",
        "tgn:1000001",
        "tgn:7019560",
        "tgn:7012149",
        "tgn:7007566",
        "tgn:7029392"
    ],
    "tgn:id":2466941,
    "tgn:name":"Long Canyon",
    "tgn:placetype":[
        "aat:300008761"
    ]
},
  "bbox": [],
  "geometry": {"coordinates":[-104.0333,34.4833],"type":"Point"}
}