{
  "id": 1020818,
  "type": "Feature",
  "properties": {
    "tgn:hierarchy":[
        "tgn:1020818",
        "tgn:7006247",
        "tgn:1000047",
        "tgn:7002456",
        "tgn:1000002",
        "tgn:7029392"
    ],
    "tgn:id":1020818,
    "tgn:name":"Beja",
    "tgn:placetype":[
        "aat:300008347"
    ]
},
  "bbox": [],
  "geometry": {"coordinates":[-48.8167,-1.5667],"type":"Point"}
}