<<<<<<< HEAD
{
  "id": 7174774,
  "type": "Feature",
  "properties": {
    "tgn:hierarchy":[
        "tgn:7174774",
        "tgn:1000003",
        "tgn:7003685",
        "tgn:7000084",
        "tgn:7029392"
    ],
    "tgn:id":7174774,
    "tgn:name":"Gro\u00dfhermsdorf",
    "tgn:placetype":[
        "aat:300008347"
    ]
},
  "bbox": [],
  "geometry": {"coordinates":[12.4,51.116667],"type":"Point"}
}
=======
{"geometry":{"type":"Point","coordinates":[12.400000,51.116667]},"type":"Feature","properties":{"hierarchy":["tgn:7174774","tgn:1000003","tgn:7003685","tgn:7000084","tgn:7029392"],"placetype":["aat:300008347"],"id":7174774,"name:xx":"Gro\u00dfhermsdorf"}}
>>>>>>> 03f74aca74312dbeaf24d7e61306dd6a786dc3d0
