{
  "id": 7568421,
  "type": "Feature",
  "properties": {
    "tgn:hierarchy":[
        "tgn:7568421",
        "tgn:1000004",
        "tgn:7000198",
        "tgn:7016788",
        "tgn:7029392"
    ],
    "tgn:id":7568421,
    "tgn:name:en":"J\u0101s\u0101sar",
    "tgn:placetype":[
        "aat:300008347"
    ]
},
  "bbox": [],
  "geometry": {"coordinates":[74.72039,28.259897],"type":"Point"}
}