{
  "id": 7540324,
  "type": "Feature",
  "properties": {
    "tgn:hierarchy":[
        "tgn:7540324",
        "tgn:7001242",
        "tgn:7016833",
        "tgn:7000123",
        "tgn:7029392"
    ],
    "tgn:id":7540324,
    "tgn:name:en":"Naj' ad Dawmah",
    "tgn:placetype":[
        "aat:300008347"
    ]
},
  "bbox": [],
  "geometry": {"coordinates":[32.791389,26.108056],"type":"Point"}
}