{
  "id": 1013593,
  "type": "Feature",
  "properties": {
    "tgn:hierarchy":[
        "tgn:1013593",
        "tgn:7005735",
        "tgn:7005685",
        "tgn:1000001",
        "tgn:7013409",
        "tgn:7029392"
    ],
    "tgn:id":1013593,
    "tgn:name":"Lake Cowichan",
    "tgn:placetype":[
        "aat:300008347"
    ]
},
  "bbox": [],
  "geometry": {"coordinates":[-124.0333,48.8167],"type":"Point"}
}