{
  "id": 7321253,
  "type": "Feature",
  "properties": {
    "tgn:hierarchy":[
        "tgn:7321253",
        "tgn:1001708",
        "tgn:1000049",
        "tgn:1000002",
        "tgn:7029392"
    ],
    "tgn:id":7321253,
    "tgn:name":"Estaci\u00f3n Buin",
    "tgn:placetype":[
        "aat:300007783"
    ]
},
  "bbox": [],
  "geometry": {"coordinates":[-70.733333,-33.733333],"type":"Point"}
}