<<<<<<< HEAD
{
  "id": 7248857,
  "type": "Feature",
  "properties": {
    "tgn:hierarchy":[
        "tgn:7248857",
        "tgn:7007877",
        "tgn:1000003",
        "tgn:1000063",
        "tgn:4012014",
        "tgn:7029392"
    ],
    "tgn:id":7248857,
    "tgn:name":"Bois Fichaux",
    "tgn:placetype":[
        "aat:300008347"
    ]
},
  "bbox": [],
  "geometry": {"coordinates":[3.214063,50.76342],"type":"Point"}
}
=======
{"geometry":{"type":"Point","coordinates":[3.214063,50.763420]},"type":"Feature","properties":{"hierarchy":["tgn:7248857","tgn:7007877","tgn:1000003","tgn:1000063","tgn:4012014","tgn:7029392"],"placetype":["aat:300008347"],"id":7248857,"name:xx":"Bois Fichaux"}}
>>>>>>> 03f74aca74312dbeaf24d7e61306dd6a786dc3d0
