{
  "id": 2278910,
  "type": "Feature",
  "properties": {
    "tgn:hierarchy":[
        "tgn:2278910",
        "tgn:1000001",
        "tgn:2000460",
        "tgn:7012149",
        "tgn:7007250",
        "tgn:7029392"
    ],
    "tgn:id":2278910,
    "tgn:name":"Dead Man Creek",
    "tgn:placetype":[
        "aat:300008706"
    ]
},
  "bbox": [],
  "geometry": {"coordinates":[-116.15,48.45],"type":"Point"}
}