{
  "id": 2432897,
  "type": "Feature",
  "properties": {
    "tgn:hierarchy":[
        "tgn:2432897",
        "tgn:7006450",
        "tgn:1000001",
        "tgn:7030547",
        "tgn:7012149",
        "tgn:7029392"
    ],
    "tgn:id":2432897,
    "tgn:name":"Keevy Peak",
    "tgn:placetype":[
        "aat:300008798"
    ]
},
  "bbox": [],
  "geometry": {"coordinates":[-148.0333,63.9167],"type":"Point"}
}