{
  "id": 7525317,
  "type": "Feature",
  "properties": {
    "tgn:hierarchy":[
        "tgn:7525317",
        "tgn:7001242",
        "tgn:7016833",
        "tgn:1001123",
        "tgn:7029392"
    ],
    "tgn:id":7525317,
    "tgn:name":"D\u00e2khlet el-Gh\u00e2la",
    "tgn:placetype":[
        "aat:300008791"
    ]
},
  "bbox": [],
  "geometry": {"coordinates":[32.0925,31.027778],"type":"Point"}
}