{
  "id": 2630531,
  "type": "Feature",
  "properties": {
    "tgn:hierarchy":[
        "tgn:2630531",
        "tgn:1000001",
        "tgn:7012149",
        "tgn:2001488",
        "tgn:7007709",
        "tgn:7029392"
    ],
    "tgn:id":2630531,
    "tgn:name":"Round Hammock Bay",
    "tgn:placetype":[
        "aat:300132316"
    ]
},
  "bbox": [],
  "geometry": {"coordinates":[-75.4667,35.6167],"type":"Point"}
}