{
  "id": 7405578,
  "type": "Feature",
  "properties": {
    "tgn:hierarchy":[
        "tgn:7405578",
        "tgn:7005585",
        "tgn:1000001",
        "tgn:7005560",
        "tgn:7029392"
    ],
    "tgn:id":7405578,
    "tgn:name":"Pantla",
    "tgn:placetype":[
        "aat:300008347"
    ]
},
  "bbox": [],
  "geometry": {"coordinates":[-101.616667,17.75],"type":"Point"}
}