{
  "id": 7063018,
  "type": "Feature",
  "properties": {
    "tgn:hierarchy":[
        "tgn:7063018",
        "tgn:1000003",
        "tgn:7003677",
        "tgn:7000084",
        "tgn:7029392"
    ],
    "tgn:id":7063018,
    "tgn:name":"Am B\u00f6rsting",
    "tgn:placetype":[
        "aat:300000206"
    ]
},
  "bbox": [],
  "geometry": {"coordinates":[7.633333,51.433333],"type":"Point"}
}