{
  "id": 2511678,
  "type": "Feature",
  "properties": {
    "tgn:hierarchy":[
        "tgn:2511678",
        "tgn:1000001",
        "tgn:7012149",
        "tgn:2002353",
        "tgn:7007922",
        "tgn:7029392"
    ],
    "tgn:id":2511678,
    "tgn:name":"Miles Point",
    "tgn:placetype":[
        "aat:300008850"
    ]
},
  "bbox": [],
  "geometry": {"coordinates":[-91.2333,45.9167],"type":"Point"}
}