{
  "id": 2467158,
  "type": "Feature",
  "properties": {
    "tgn:hierarchy":[
        "tgn:2467158",
        "tgn:1000001",
        "tgn:7012149",
        "tgn:1002431",
        "tgn:7007826",
        "tgn:7029392"
    ],
    "tgn:id":2467158,
    "tgn:name":"Long Creek",
    "tgn:placetype":[
        "aat:300008706"
    ]
},
  "bbox": [],
  "geometry": {"coordinates":[-98.1333,29.65],"type":"Point"}
}