{
  "id": 7478444,
  "type": "Feature",
  "properties": {
    "tgn:hierarchy":[
        "tgn:7478444",
        "tgn:1000004",
        "tgn:7492971",
        "tgn:1000141",
        "tgn:7029392"
    ],
    "tgn:id":7478444,
    "tgn:name":"Xiapou Paishuigou",
    "tgn:placetype":[
        "aat:300006075"
    ]
},
  "bbox": [],
  "geometry": {"coordinates":[120.49864,22.473811],"type":"Point"}
}