{
  "id": 2058854,
  "type": "Feature",
  "properties": {
    "tgn:hierarchy":[
        "tgn:2058854",
        "tgn:1000001",
        "tgn:7012149",
        "tgn:2001203",
        "tgn:7007523",
        "tgn:7029392"
    ],
    "tgn:id":2058854,
    "tgn:name":"Galmey",
    "tgn:placetype":[
        "aat:300008347"
    ]
},
  "bbox": [],
  "geometry": {"coordinates":[-93.35,37.8833],"type":"Point"}
}