{
  "id": 2306022,
  "type": "Feature",
  "properties": {
    "tgn:hierarchy":[
        "tgn:2306022",
        "tgn:1000001",
        "tgn:7012149",
        "tgn:2001284",
        "tgn:7007524",
        "tgn:7029392"
    ],
    "tgn:id":2306022,
    "tgn:name":"East Fork Ahorn Creek",
    "tgn:placetype":[
        "aat:300008706"
    ]
},
  "bbox": [],
  "geometry": {"coordinates":[-113.0167,47.4833],"type":"Point"}
}