<<<<<<< HEAD
{
  "id": 2763707,
  "type": "Feature",
  "properties": {
    "tgn:hierarchy":[
        "tgn:2763707",
        "tgn:1000001",
        "tgn:7012149",
        "tgn:2001461",
        "tgn:7007568",
        "tgn:7029392"
    ],
    "tgn:id":2763707,
    "tgn:name":"Whallon Bay",
    "tgn:placetype":[
        "aat:300132316"
    ]
},
  "bbox": [],
  "geometry": {"coordinates":[-73.3333,44.2667],"type":"Point"}
}
=======
{"geometry":{"type":"Point","coordinates":[-73.333300,44.266700]},"type":"Feature","properties":{"hierarchy":["tgn:2763707","tgn:1000001","tgn:7012149","tgn:2001461","tgn:7007568","tgn:7029392"],"placetype":["aat:300132316"],"id":2763707,"name:xx":"Whallon Bay"}}
>>>>>>> 03f74aca74312dbeaf24d7e61306dd6a786dc3d0
