{
  "id": 7519912,
  "type": "Feature",
  "properties": {
    "tgn:hierarchy":[
        "tgn:7519912",
        "tgn:1009227",
        "tgn:1000226",
        "tgn:7016729",
        "tgn:1000006",
        "tgn:7029392"
    ],
    "tgn:id":7519912,
    "tgn:name:en":"Benhopai",
    "tgn:placetype":[
        "aat:300000206"
    ]
},
  "bbox": [],
  "geometry": {"coordinates":[173.583333,-41.666667],"type":"Point"}
}