{
  "id": 7070659,
  "type": "Feature",
  "properties": {
    "tgn:hierarchy":[
        "tgn:7070659",
        "tgn:7003692",
        "tgn:1000003",
        "tgn:7000084",
        "tgn:7029392"
    ],
    "tgn:id":7070659,
    "tgn:name":"Steinenb\u00e4chle",
    "tgn:placetype":[
        "aat:300008699"
    ]
},
  "bbox": [],
  "geometry": {"coordinates":[8.133333,47.766667],"type":"Point"}
}