{
  "id": 7236756,
  "type": "Feature",
  "properties": {
    "tgn:hierarchy":[
        "tgn:7236756",
        "tgn:7002706",
        "tgn:7002705",
        "tgn:1000003",
        "tgn:1000074",
        "tgn:7029392"
    ],
    "tgn:id":7236756,
    "tgn:name":"\u00c1gios Char\u00e1lampos",
    "tgn:placetype":[
        "aat:300008347"
    ]
},
  "bbox": [],
  "geometry": {"coordinates":[21.128611,39.289722],"type":"Point"}
}