{
  "id": 7113180,
  "type": "Feature",
  "properties": {
    "tgn:hierarchy":[
        "tgn:7113180",
        "tgn:7000096",
        "tgn:1000003",
        "tgn:7000084",
        "tgn:7029392"
    ],
    "tgn:id":7113180,
    "tgn:name":"R\u00f6derwildbett",
    "tgn:placetype":[
        "aat:300008699"
    ]
},
  "bbox": [],
  "geometry": {"coordinates":[13.466667,51.466667],"type":"Point"}
}