{
  "id": 7080243,
  "type": "Feature",
  "properties": {
    "tgn:hierarchy":[
        "tgn:7080243",
        "tgn:7000096",
        "tgn:1000003",
        "tgn:7000084",
        "tgn:7029392"
    ],
    "tgn:id":7080243,
    "tgn:name":"Zechiner Loose",
    "tgn:placetype":[
        "aat:300055621"
    ]
},
  "bbox": [],
  "geometry": {"coordinates":[14.45,52.633333],"type":"Point"}
}