{
  "id": 2519635,
  "type": "Feature",
  "properties": {
    "tgn:hierarchy":[
        "tgn:2519635",
        "tgn:1000001",
        "tgn:7006451",
        "tgn:7012149",
        "tgn:2000098",
        "tgn:7029392"
    ],
    "tgn:id":2519635,
    "tgn:name":"Mohave Tank",
    "tgn:placetype":[
        "aat:300006191"
    ]
},
  "bbox": [],
  "geometry": {"coordinates":[-114.0167,34.4167],"type":"Point"}
}