{
  "id": 1141035,
  "type": "Feature",
  "properties": {
    "tgn:hierarchy":[
        "tgn:1141035",
        "tgn:7000895",
        "tgn:1000004",
        "tgn:1000974",
        "tgn:1000120",
        "tgn:7029392"
    ],
    "tgn:id":1141035,
    "tgn:name":"O-shima",
    "tgn:placetype":[
        "aat:300008791"
    ]
},
  "bbox": [],
  "geometry": {"coordinates":[136.1167,36.25],"type":"Point"}
}