{
  "id": 1089805,
  "type": "Feature",
  "properties": {
    "tgn:hierarchy":[
        "tgn:1089805",
        "tgn:7001242",
        "tgn:1001286",
        "tgn:7000489",
        "tgn:7029392"
    ],
    "tgn:id":1089805,
    "tgn:name":"Fik'",
    "tgn:placetype":[
        "aat:300008347"
    ]
},
  "bbox": [],
  "geometry": {"coordinates":[42.3167,8.1667],"type":"Point"}
}