{
  "id": 7556793,
  "type": "Feature",
  "properties": {
    "tgn:hierarchy":[
        "tgn:7556793",
        "tgn:1000004",
        "tgn:7000198",
        "tgn:1001894",
        "tgn:7029392"
    ],
    "tgn:id":7556793,
    "tgn:name:en":"Semai",
    "tgn:placetype":[
        "aat:300007783"
    ]
},
  "bbox": [],
  "geometry": {"coordinates":[77.522369,26.285596],"type":"Point"}
}