{
  "id": 7216240,
  "type": "Feature",
  "properties": {
    "tgn:hierarchy":[
        "tgn:7216240",
        "tgn:7003669",
        "tgn:1000003",
        "tgn:7000084",
        "tgn:7029392"
    ],
    "tgn:id":7216240,
    "tgn:name":"Althegnenberg",
    "tgn:placetype":[
        "aat:300008347"
    ]
},
  "bbox": [],
  "geometry": {"coordinates":[11.066667,48.233333],"type":"Point"}
}