{
  "id": 1093413,
  "type": "Feature",
  "properties": {
    "tgn:hierarchy":[
        "tgn:1093413",
        "tgn:7001242",
        "tgn:7017584",
        "tgn:1000193",
        "tgn:7029392"
    ],
    "tgn:id":1093413,
    "tgn:name":"Murraysburg",
    "tgn:placetype":[
        "aat:300008347"
    ]
},
  "bbox": [],
  "geometry": {"coordinates":[23.75,-31.9667],"type":"Point"}
}