{
  "id": 2687997,
  "type": "Feature",
  "properties": {
    "tgn:hierarchy":[
        "tgn:2687997",
        "tgn:1000001",
        "tgn:7012149",
        "tgn:2000422",
        "tgn:7007248",
        "tgn:7029392"
    ],
    "tgn:id":2687997,
    "tgn:name":"Springfield",
    "tgn:placetype":[
        "aat:300008347"
    ]
},
  "bbox": [],
  "geometry": {"coordinates":[-82.9333,33.6167],"type":"Point"}
}