{
  "id": 2020291,
  "type": "Feature",
  "properties": {
    "tgn:hierarchy":[
        "tgn:2020291",
        "tgn:1000001",
        "tgn:7012149",
        "tgn:1002582",
        "tgn:7007240",
        "tgn:7029392"
    ],
    "tgn:id":2020291,
    "tgn:name":"Matlacha",
    "tgn:placetype":[
        "aat:300008347"
    ]
},
  "bbox": [],
  "geometry": {"coordinates":[-82.0667,26.6167],"type":"Point"}
}