<<<<<<< HEAD
{
  "id": 7179258,
  "type": "Feature",
  "properties": {
    "tgn:hierarchy":[
        "tgn:7179258",
        "tgn:7003669",
        "tgn:1000003",
        "tgn:7000084",
        "tgn:7029392"
    ],
    "tgn:id":7179258,
    "tgn:name":"Haberg",
    "tgn:placetype":[
        "aat:300000206"
    ]
},
  "bbox": [],
  "geometry": {"coordinates":[13.25,48.633333],"type":"Point"}
}
=======
{"geometry":{"type":"Point","coordinates":[13.250000,48.633333]},"type":"Feature","properties":{"hierarchy":["tgn:7179258","tgn:7003669","tgn:1000003","tgn:7000084","tgn:7029392"],"placetype":["aat:300000206"],"id":7179258,"name:xx":"Haberg"}}
>>>>>>> 03f74aca74312dbeaf24d7e61306dd6a786dc3d0
