{
  "id": 7498138,
  "type": "Feature",
  "properties": {
    "tgn:hierarchy":[
        "tgn:7498138",
        "tgn:1000004",
        "tgn:7491221",
        "tgn:1000141",
        "tgn:7029392"
    ],
    "tgn:id":7498138,
    "tgn:name":"Zhiben Kenqu",
    "tgn:placetype":[
        "aat:300006163"
    ]
},
  "bbox": [],
  "geometry": {"coordinates":[121.057398,22.752986],"type":"Point"}
}