{
  "id": 7467861,
  "type": "Feature",
  "properties": {
    "tgn:hierarchy":[
        "tgn:7467861",
        "tgn:1000004",
        "tgn:7491221",
        "tgn:1000141",
        "tgn:7029392"
    ],
    "tgn:id":7467861,
    "tgn:name":"Zhangyuan Qiao",
    "tgn:placetype":[
        "aat:300007836"
    ]
},
  "bbox": [],
  "geometry": {"coordinates":[121.479563,23.400608],"type":"Point"}
}