{
  "id": 2603815,
  "type": "Feature",
  "properties": {
    "tgn:hierarchy":[
        "tgn:2603815",
        "tgn:1000001",
        "tgn:2001261",
        "tgn:7012149",
        "tgn:7007524",
        "tgn:7029392"
    ],
    "tgn:id":2603815,
    "tgn:name":"Quietus",
    "tgn:placetype":[
        "aat:300008347"
    ]
},
  "bbox": [],
  "geometry": {"coordinates":[-106.2667,45.0833],"type":"Point"}
}