{
  "id": 2181207,
  "type": "Feature",
  "properties": {
    "tgn:hierarchy":[
        "tgn:2181207",
        "tgn:1000001",
        "tgn:7012149",
        "tgn:2002377",
        "tgn:7007923",
        "tgn:7029392"
    ],
    "tgn:id":2181207,
    "tgn:name":"Blue Canyon",
    "tgn:placetype":[
        "aat:300008761"
    ]
},
  "bbox": [],
  "geometry": {"coordinates":[-106.8333,42.9167],"type":"Point"}
}