{
  "id": 2251832,
  "type": "Feature",
  "properties": {
    "tgn:hierarchy":[
        "tgn:2251832",
        "tgn:1000001",
        "tgn:7012149",
        "tgn:1002751",
        "tgn:7007568",
        "tgn:7029392"
    ],
    "tgn:id":2251832,
    "tgn:name":"Con Hook",
    "tgn:placetype":[
        "aat:300008850"
    ]
},
  "bbox": [],
  "geometry": {"coordinates":[-73.95,41.35],"type":"Point"}
}