<<<<<<< HEAD
{
  "id": 2251832,
  "type": "Feature",
  "properties": {
    "tgn:hierarchy":[
        "tgn:2251832",
        "tgn:1000001",
        "tgn:7012149",
        "tgn:1002751",
        "tgn:7007568",
        "tgn:7029392"
    ],
    "tgn:id":2251832,
    "tgn:name":"Con Hook",
    "tgn:placetype":[
        "aat:300008850"
    ]
},
  "bbox": [],
  "geometry": {"coordinates":[-73.95,41.35],"type":"Point"}
}
=======
{"geometry":{"type":"Point","coordinates":[-73.950000,41.350000]},"type":"Feature","properties":{"hierarchy":["tgn:2251832","tgn:1000001","tgn:7012149","tgn:1002751","tgn:7007568","tgn:7029392"],"placetype":["aat:300008850"],"id":2251832,"name:xx":"Con Hook"}}
>>>>>>> 03f74aca74312dbeaf24d7e61306dd6a786dc3d0
