{
  "id": 2093972,
  "type": "Feature",
  "properties": {
    "tgn:hierarchy":[
        "tgn:2093972",
        "tgn:1000001",
        "tgn:7012149",
        "tgn:2093962",
        "tgn:1002690",
        "tgn:7007710",
        "tgn:7029392"
    ],
    "tgn:id":2093972,
    "tgn:name":"Henderson Park",
    "tgn:placetype":[
        "aat:300387331"
    ]
},
  "bbox": [],
  "geometry": {"coordinates":[-75.35,40.0833],"type":"Point"}
}