{
  "id": 2455180,
  "type": "Feature",
  "properties": {
    "tgn:hierarchy":[
        "tgn:2455180",
        "tgn:1000001",
        "tgn:7012149",
        "tgn:1002990",
        "tgn:7007708",
        "tgn:7029392"
    ],
    "tgn:id":2455180,
    "tgn:name":"Little Fawn Spring",
    "tgn:placetype":[
        "aat:300008697"
    ]
},
  "bbox": [],
  "geometry": {"coordinates":[-121.1667,44.95],"type":"Point"}
}