{
  "id": 7506422,
  "type": "Feature",
  "properties": {
    "tgn:hierarchy":[
        "tgn:7506422",
        "tgn:1009227",
        "tgn:7001866",
        "tgn:1000226",
        "tgn:1000006",
        "tgn:7029392"
    ],
    "tgn:id":7506422,
    "tgn:name:en":"Rough Creek",
    "tgn:placetype":[
        "aat:300008699"
    ]
},
  "bbox": [],
  "geometry": {"coordinates":[173.183333,-42.333333],"type":"Point"}
}