<<<<<<< HEAD
{
  "id": 2402933,
  "type": "Feature",
  "properties": {
    "tgn:hierarchy":[
        "tgn:2402933",
        "tgn:1000001",
        "tgn:7012149",
        "tgn:2000809",
        "tgn:7007255",
        "tgn:7029392"
    ],
    "tgn:id":2402933,
    "tgn:name":"Houckville",
    "tgn:placetype":[
        "aat:300008347"
    ]
},
  "bbox": [],
  "geometry": {"coordinates":[-82.85,38.1],"type":"Point"}
}
=======
{"geometry":{"type":"Point","coordinates":[-82.850000,38.100000]},"type":"Feature","properties":{"hierarchy":["tgn:2402933","tgn:1000001","tgn:7012149","tgn:2000809","tgn:7007255","tgn:7029392"],"placetype":["aat:300008347"],"id":2402933,"name:xx":"Houckville"}}
>>>>>>> 03f74aca74312dbeaf24d7e61306dd6a786dc3d0
