{
  "id": 7100675,
  "type": "Feature",
  "properties": {
    "tgn:hierarchy":[
        "tgn:7100675",
        "tgn:1000003",
        "tgn:7003688",
        "tgn:7000084",
        "tgn:7029392"
    ],
    "tgn:id":7100675,
    "tgn:name":"Schaalby",
    "tgn:placetype":[
        "aat:300008347"
    ]
},
  "bbox": [],
  "geometry": {"coordinates":[9.633333,54.55],"type":"Point"}
}