{
  "id": 7277113,
  "type": "Feature",
  "properties": {
    "tgn:hierarchy":[
        "tgn:7277113",
        "tgn:1001692",
        "tgn:1000049",
        "tgn:1000002",
        "tgn:7029392"
    ],
    "tgn:id":7277113,
    "tgn:name":"Yenellenchico, R\u00edo",
    "tgn:placetype":[
        "aat:300008699"
    ]
},
  "bbox": [],
  "geometry": {"coordinates":[-73.266667,-39.133333],"type":"Point"}
}