<<<<<<< HEAD
{
  "id": 2407629,
  "type": "Feature",
  "properties": {
    "tgn:hierarchy":[
        "tgn:2407629",
        "tgn:1000001",
        "tgn:7012149",
        "tgn:7007157",
        "tgn:2000189",
        "tgn:7029392"
    ],
    "tgn:id":2407629,
    "tgn:name":"Hurds Gulch",
    "tgn:placetype":[
        "aat:300008761"
    ]
},
  "bbox": [],
  "geometry": {"coordinates":[-122.7833,41.5167],"type":"Point"}
}
=======
{"geometry":{"type":"Point","coordinates":[-122.783300,41.516700]},"type":"Feature","properties":{"hierarchy":["tgn:2407629","tgn:1000001","tgn:7012149","tgn:7007157","tgn:2000189","tgn:7029392"],"placetype":["aat:300008761"],"id":2407629,"name:xx":"Hurds Gulch"}}
>>>>>>> 03f74aca74312dbeaf24d7e61306dd6a786dc3d0
