<<<<<<< HEAD
{
  "id": 7483729,
  "type": "Feature",
  "properties": {
    "tgn:hierarchy":[
        "tgn:7483729",
        "tgn:1000004",
        "tgn:7490934",
        "tgn:1000141",
        "tgn:7029392"
    ],
    "tgn:id":7483729,
    "tgn:name":"Kengnei Qiao",
    "tgn:placetype":[
        "aat:300007836"
    ]
},
  "bbox": [],
  "geometry": {"coordinates":[120.465833,23.332222],"type":"Point"}
}
=======
{"geometry":{"type":"Point","coordinates":[120.465833,23.332222]},"type":"Feature","properties":{"hierarchy":["tgn:7483729","tgn:1000004","tgn:7490934","tgn:1000141","tgn:7029392"],"placetype":["aat:300007836"],"id":7483729,"name:xx":"Kengnei Qiao"}}
>>>>>>> 03f74aca74312dbeaf24d7e61306dd6a786dc3d0
