{
  "id": 7588902,
  "type": "Feature",
  "properties": {
    "tgn:hierarchy":[
        "tgn:7588902",
        "tgn:1000004",
        "tgn:7000198",
        "tgn:7016788",
        "tgn:7029392"
    ],
    "tgn:id":7588902,
    "tgn:name:en":"Hariy\u0101li N\u0101di",
    "tgn:placetype":[
        "aat:300008347"
    ]
},
  "bbox": [],
  "geometry": {"coordinates":[71.96731,26.593365],"type":"Point"}
}