{
  "id": 7525069,
  "type": "Feature",
  "properties": {
    "tgn:hierarchy":[
        "tgn:7525069",
        "tgn:7001242",
        "tgn:7016833",
        "tgn:7001336",
        "tgn:7029392"
    ],
    "tgn:id":7525069,
    "tgn:name:en":"Cairn Point",
    "tgn:placetype":[
        "aat:300386846"
    ]
},
  "bbox": [],
  "geometry": {"coordinates":[33.134806,29.030087],"type":"Point"}
}