{
  "id": 7008520,
  "type": "Feature",
  "properties": {
    "tgn:hierarchy":[
        "tgn:7008520",
        "tgn:7002443",
        "tgn:1000003",
        "tgn:7008050",
        "tgn:7008591",
        "tgn:7029392"
    ],
    "tgn:id":7008520,
    "tgn:name:en":"Llandrindod Wells",
    "tgn:placetype":[
        "aat:300008347",
        "aat:300008416",
        "aat:300008389",
        "aat:300387220",
        "aat:300000547",
        "aat:300387294"
    ]
},
  "bbox": [],
  "geometry": {"coordinates":[-3.383333,52.233333],"type":"Point"}
}