{
  "id": 2470528,
  "type": "Feature",
  "properties": {
    "tgn:hierarchy":[
        "tgn:2470528",
        "tgn:1000001",
        "tgn:7012149",
        "tgn:2001459",
        "tgn:7007566",
        "tgn:7029392"
    ],
    "tgn:id":2470528,
    "tgn:name":"Los Gatos Canyon",
    "tgn:placetype":[
        "aat:300008761"
    ]
},
  "bbox": [],
  "geometry": {"coordinates":[-103.4667,36.1333],"type":"Point"}
}