{
  "id": 2579285,
  "type": "Feature",
  "properties": {
    "tgn:hierarchy":[
        "tgn:2579285",
        "tgn:1000001",
        "tgn:7012149",
        "tgn:7007826",
        "tgn:7029392"
    ],
    "tgn:id":2579285,
    "tgn:name":"Pickard Creek",
    "tgn:placetype":[
        "aat:300008706"
    ]
},
  "bbox": [],
  "geometry": {"coordinates":[-98.5333,32.9333],"type":"Point"}
}