{
  "id": 2189699,
  "type": "Feature",
  "properties": {
    "tgn:hierarchy":[
        "tgn:2189699",
        "tgn:1000001",
        "tgn:7012149",
        "tgn:2000378",
        "tgn:7007248",
        "tgn:7029392"
    ],
    "tgn:id":2189699,
    "tgn:name":"Bowens Lake",
    "tgn:placetype":[
        "aat:300008680"
    ]
},
  "bbox": [],
  "geometry": {"coordinates":[-82.9333,32.6333],"type":"Point"}
}