{
  "id": 2145834,
  "type": "Feature",
  "properties": {
    "tgn:hierarchy":[
        "tgn:2145834",
        "tgn:1000001",
        "tgn:7012149",
        "tgn:2001286",
        "tgn:7007524",
        "tgn:7029392"
    ],
    "tgn:id":2145834,
    "tgn:name":"Baldy, Mount",
    "tgn:placetype":[
        "aat:300008798"
    ]
},
  "bbox": [],
  "geometry": {"coordinates":[-115.9167,48.8333],"type":"Point"}
}