{
  "id": 1052144,
  "type": "Feature",
  "properties": {
    "tgn:hierarchy":[
        "tgn:1052144",
        "tgn:7011438",
        "tgn:1000004",
        "tgn:7006646",
        "tgn:7029392"
    ],
    "tgn:id":1052144,
    "tgn:name":"Alunitdag",
    "tgn:placetype":[
        "aat:300008347"
    ]
},
  "bbox": [],
  "geometry": {"coordinates":[46.0667,40.5333],"type":"Point"}
}