{
  "id": 2483327,
  "type": "Feature",
  "properties": {
    "tgn:hierarchy":[
        "tgn:2483327",
        "tgn:1000001",
        "tgn:7012149",
        "tgn:2000833",
        "tgn:7007255",
        "tgn:7029392"
    ],
    "tgn:id":2483327,
    "tgn:name":"Lasley Run",
    "tgn:placetype":[
        "aat:300008699"
    ]
},
  "bbox": [],
  "geometry": {"coordinates":[-85.45,37.9333],"type":"Point"}
}