{
  "id": 7133332,
  "type": "Feature",
  "properties": {
    "tgn:hierarchy":[
        "tgn:7133332",
        "tgn:7003692",
        "tgn:1000003",
        "tgn:7000084",
        "tgn:7029392"
    ],
    "tgn:id":7133332,
    "tgn:name":"Neibsheim",
    "tgn:placetype":[
        "aat:300008347"
    ]
},
  "bbox": [],
  "geometry": {"coordinates":[8.683889,49.070278],"type":"Point"}
}