{
  "id": 1118580,
  "type": "Feature",
  "properties": {
    "tgn:hierarchy":[
        "tgn:1118580",
        "tgn:7006477",
        "tgn:1001522",
        "tgn:1000002",
        "tgn:7029392"
    ],
    "tgn:id":1118580,
    "tgn:name":"Viedma, Lago",
    "tgn:placetype":[
        "aat:300008680"
    ]
},
  "bbox": [],
  "geometry": {"coordinates":[-72.5833,-49.5833],"type":"Point"}
}