{
  "id": 7228535,
  "type": "Feature",
  "properties": {
    "tgn:hierarchy":[
        "tgn:7228535",
        "tgn:7002711",
        "tgn:7001338",
        "tgn:1000003",
        "tgn:1000074",
        "tgn:7029392"
    ],
    "tgn:id":7228535,
    "tgn:name":"Gaz\u00e1tika",
    "tgn:placetype":[
        "aat:300008347"
    ]
},
  "bbox": [],
  "geometry": {"coordinates":[19.815278,39.675],"type":"Point"}
}