{
  "id": 7486396,
  "type": "Feature",
  "properties": {
    "tgn:hierarchy":[
        "tgn:7486396",
        "tgn:1000004",
        "tgn:7490934",
        "tgn:1000141",
        "tgn:7029392"
    ],
    "tgn:id":7486396,
    "tgn:name":"Niubu Shan",
    "tgn:placetype":[
        "aat:300008777"
    ]
},
  "bbox": [],
  "geometry": {"coordinates":[120.495269,23.084237],"type":"Point"}
}