{
  "id": 2226493,
  "type": "Feature",
  "properties": {
    "tgn:hierarchy":[
        "tgn:2226493",
        "tgn:1000001",
        "tgn:7012149",
        "tgn:1002553",
        "tgn:7007920",
        "tgn:7029392"
    ],
    "tgn:id":2226493,
    "tgn:name":"Catherine, Mount",
    "tgn:placetype":[
        "aat:300008798"
    ]
},
  "bbox": [],
  "geometry": {"coordinates":[-121.4167,47.3667],"type":"Point"}
}