{
  "id": 2408794,
  "type": "Feature",
  "properties": {
    "tgn:hierarchy":[
        "tgn:2408794",
        "tgn:1000001",
        "tgn:7006451",
        "tgn:7012149",
        "tgn:2000103",
        "tgn:7029392"
    ],
    "tgn:id":2408794,
    "tgn:name":"Hyde Spring",
    "tgn:placetype":[
        "aat:300008697"
    ]
},
  "bbox": [],
  "geometry": {"coordinates":[-112.8167,34.85],"type":"Point"}
}