{
  "id": 2733355,
  "type": "Feature",
  "properties": {
    "tgn:hierarchy":[
        "tgn:2733355",
        "tgn:1000001",
        "tgn:7012149",
        "tgn:1002756",
        "tgn:7007240",
        "tgn:7029392"
    ],
    "tgn:id":2733355,
    "tgn:name":"Turkey Slough",
    "tgn:placetype":[
        "aat:300008699"
    ]
},
  "bbox": [],
  "geometry": {"coordinates":[-81.0167,28.0333],"type":"Point"}
}