{
  "id": 7494849,
  "type": "Feature",
  "properties": {
    "tgn:hierarchy":[
        "tgn:7494849",
        "tgn:7487020",
        "tgn:1000004",
        "tgn:1000141",
        "tgn:7029392"
    ],
    "tgn:id":7494849,
    "tgn:name":"Dalukeng Qiao",
    "tgn:placetype":[
        "aat:300007836"
    ]
},
  "bbox": [],
  "geometry": {"coordinates":[120.848757,24.466114],"type":"Point"}
}