{
  "id": 2752338,
  "type": "Feature",
  "properties": {
    "tgn:hierarchy":[
        "tgn:2752338",
        "tgn:1000001",
        "tgn:7012149",
        "tgn:2002127",
        "tgn:7007827",
        "tgn:7029392"
    ],
    "tgn:id":2752338,
    "tgn:name":"Washington Black Ridge",
    "tgn:placetype":[
        "aat:300266640"
    ]
},
  "bbox": [],
  "geometry": {"coordinates":[-113.45,37.1333],"type":"Point"}
}