{
  "id": 2463243,
  "type": "Feature",
  "properties": {
    "tgn:hierarchy":[
        "tgn:2463243",
        "tgn:1000001",
        "tgn:7012149",
        "tgn:2001717",
        "tgn:7007708",
        "tgn:7029392"
    ],
    "tgn:id":2463243,
    "tgn:name":"Lizard Lake",
    "tgn:placetype":[
        "aat:300008680"
    ]
},
  "bbox": [],
  "geometry": {"coordinates":[-121.8667,44.6167],"type":"Point"}
}