{
  "id": 2060181,
  "type": "Feature",
  "properties": {
    "tgn:hierarchy":[
        "tgn:2060181",
        "tgn:1000001",
        "tgn:7012149",
        "tgn:2001237",
        "tgn:7007523",
        "tgn:7029392"
    ],
    "tgn:id":2060181,
    "tgn:name":"Purman",
    "tgn:placetype":[
        "aat:300008347",
        "aat:300387210"
    ]
},
  "bbox": [],
  "geometry": {"coordinates":[-90.7333,36.5167],"type":"Point"}
}