<<<<<<< HEAD
{
  "id": 7240763,
  "type": "Feature",
  "properties": {
    "tgn:hierarchy":[
        "tgn:7240763",
        "tgn:7007877",
        "tgn:1000003",
        "tgn:1000063",
        "tgn:4012014",
        "tgn:7029392"
    ],
    "tgn:id":7240763,
    "tgn:name":"Ferme de la Femme",
    "tgn:placetype":[
        "aat:300000206"
    ]
},
  "bbox": [],
  "geometry": {"coordinates":[4.15,50.6],"type":"Point"}
}
=======
{"geometry":{"type":"Point","coordinates":[4.150000,50.600000]},"type":"Feature","properties":{"hierarchy":["tgn:7240763","tgn:7007877","tgn:1000003","tgn:1000063","tgn:4012014","tgn:7029392"],"placetype":["aat:300000206"],"id":7240763,"name:xx":"Ferme de la Femme"}}
>>>>>>> 03f74aca74312dbeaf24d7e61306dd6a786dc3d0
