{
  "id": 2539681,
  "type": "Feature",
  "properties": {
    "tgn:hierarchy":[
        "tgn:2539681",
        "tgn:1000001",
        "tgn:7012149",
        "tgn:2001915",
        "tgn:7007825",
        "tgn:7029392"
    ],
    "tgn:id":2539681,
    "tgn:name":"New South Memphis",
    "tgn:placetype":[
        "aat:300008347"
    ]
},
  "bbox": [],
  "geometry": {"coordinates":[-90.05,35.0833],"type":"Point"}
}