{
  "id": 7338615,
  "type": "Feature",
  "properties": {
    "tgn:hierarchy":[
        "tgn:7338615",
        "tgn:7002760",
        "tgn:1000003",
        "tgn:1000095",
        "tgn:7029392"
    ],
    "tgn:id":7338615,
    "tgn:name":"Cud\u00f3n",
    "tgn:placetype":[
        "aat:300008347"
    ]
},
  "bbox": [],
  "geometry": {"coordinates":[-4.016667,43.416667],"type":"Point"}
}