{
  "id": 2759253,
  "type": "Feature",
  "properties": {
    "tgn:hierarchy":[
        "tgn:2759253",
        "tgn:1000001",
        "tgn:7012149",
        "tgn:2001543",
        "tgn:7007709",
        "tgn:7029392"
    ],
    "tgn:id":2759253,
    "tgn:name":"West Fork Chambers Creek",
    "tgn:placetype":[
        "aat:300008706"
    ]
},
  "bbox": [],
  "geometry": {"coordinates":[-83.6167,35.4833],"type":"Point"}
}