{
  "id": 2630706,
  "type": "Feature",
  "properties": {
    "tgn:hierarchy":[
        "tgn:2630706",
        "tgn:1000001",
        "tgn:7012149",
        "tgn:2000833",
        "tgn:7007255",
        "tgn:7029392"
    ],
    "tgn:id":2630706,
    "tgn:name":"Round Knob",
    "tgn:placetype":[
        "aat:300008798"
    ]
},
  "bbox": [],
  "geometry": {"coordinates":[-85.5667,37.55],"type":"Point"}
}