<<<<<<< HEAD
{
  "id": 7175246,
  "type": "Feature",
  "properties": {
    "tgn:hierarchy":[
        "tgn:7175246",
        "tgn:1000003",
        "tgn:7003687",
        "tgn:7000084",
        "tgn:7029392"
    ],
    "tgn:id":7175246,
    "tgn:name":"Gro\u00dfer Dautzsch",
    "tgn:placetype":[
        "aat:300008777"
    ]
},
  "bbox": [],
  "geometry": {"coordinates":[12.033333,51.5],"type":"Point"}
}
=======
{"geometry":{"type":"Point","coordinates":[12.033333,51.500000]},"type":"Feature","properties":{"hierarchy":["tgn:7175246","tgn:1000003","tgn:7003687","tgn:7000084","tgn:7029392"],"placetype":["aat:300008777"],"id":7175246,"name:xx":"Gro\u00dfer Dautzsch"}}
>>>>>>> 03f74aca74312dbeaf24d7e61306dd6a786dc3d0
