{
  "id": 2456318,
  "type": "Feature",
  "properties": {
    "tgn:hierarchy":[
        "tgn:2456318",
        "tgn:1000001",
        "tgn:7006451",
        "tgn:2000092",
        "tgn:7012149",
        "tgn:7029392"
    ],
    "tgn:id":2456318,
    "tgn:name":"Little Horse Tank",
    "tgn:placetype":[
        "aat:300006191"
    ]
},
  "bbox": [],
  "geometry": {"coordinates":[-111.5833,34.95],"type":"Point"}
}