{
  "id": 7065648,
  "type": "Feature",
  "properties": {
    "tgn:hierarchy":[
        "tgn:7065648",
        "tgn:1000003",
        "tgn:7003682",
        "tgn:7000084",
        "tgn:7029392"
    ],
    "tgn:id":7065648,
    "tgn:name":"Stelzen-Berg",
    "tgn:placetype":[
        "aat:300008777"
    ]
},
  "bbox": [],
  "geometry": {"coordinates":[7.716667,49.383333],"type":"Point"}
}