{
  "id": 7481497,
  "type": "Feature",
  "properties": {
    "tgn:hierarchy":[
        "tgn:7481497",
        "tgn:7487020",
        "tgn:1000004",
        "tgn:1000141",
        "tgn:7029392"
    ],
    "tgn:id":7481497,
    "tgn:name":"Touying Shan Beifeng",
    "tgn:placetype":[
        "aat:300008798"
    ]
},
  "bbox": [],
  "geometry": {"coordinates":[121.134444,24.374167],"type":"Point"}
}