{
  "id": 2775541,
  "type": "Feature",
  "properties": {
    "tgn:hierarchy":[
        "tgn:2775541",
        "tgn:1000001",
        "tgn:7012149",
        "tgn:7007568",
        "tgn:7029392"
    ],
    "tgn:id":2775541,
    "tgn:name":"Wilson Creek",
    "tgn:placetype":[
        "aat:300008706"
    ]
},
  "bbox": [],
  "geometry": {"coordinates":[-77.05,42.8167],"type":"Point"}
}