<<<<<<< HEAD
{
  "id": 7355208,
  "type": "Feature",
  "properties": {
    "tgn:hierarchy":[
        "tgn:7355208",
        "tgn:1000001",
        "tgn:7005591",
        "tgn:7005560",
        "tgn:7029392"
    ],
    "tgn:id":7355208,
    "tgn:name":"Cantor",
    "tgn:placetype":[
        "aat:300008347"
    ]
},
  "bbox": [],
  "geometry": {"coordinates":[-96.6,15.916667],"type":"Point"}
}
=======
{"geometry":{"type":"Point","coordinates":[-96.600000,15.916667]},"type":"Feature","properties":{"hierarchy":["tgn:7355208","tgn:1000001","tgn:7005591","tgn:7005560","tgn:7029392"],"placetype":["aat:300008347"],"id":7355208,"name:xx":"Cantor"}}
>>>>>>> 03f74aca74312dbeaf24d7e61306dd6a786dc3d0
