{
  "id": 2416156,
  "type": "Feature",
  "properties": {
    "tgn:hierarchy":[
        "tgn:2416156",
        "tgn:1000001",
        "tgn:2001745",
        "tgn:7012149",
        "tgn:7007712",
        "tgn:7029392"
    ],
    "tgn:id":2416156,
    "tgn:name":"J H Holliday Pond",
    "tgn:placetype":[
        "aat:300006191"
    ]
},
  "bbox": [],
  "geometry": {"coordinates":[-79.5167,33.8833],"type":"Point"}
}