{
  "id": 1096638,
  "type": "Feature",
  "properties": {
    "tgn:hierarchy":[
        "tgn:1096638",
        "tgn:7000490",
        "tgn:1000006",
        "tgn:7001830",
        "tgn:7029392"
    ],
    "tgn:id":1096638,
    "tgn:name":"Cooroy",
    "tgn:placetype":[
        "aat:300008347"
    ]
},
  "bbox": [],
  "geometry": {"coordinates":[152.8333,-26.4833],"type":"Point"}
}