{
  "id": 7588457,
  "type": "Feature",
  "properties": {
    "tgn:hierarchy":[
        "tgn:7588457",
        "tgn:1000004",
        "tgn:7000198",
        "tgn:7000799",
        "tgn:7029392"
    ],
    "tgn:id":7588457,
    "tgn:name:en":"Chatabug",
    "tgn:placetype":[
        "aat:300008347"
    ]
},
  "bbox": [],
  "geometry": {"coordinates":[74.673622,34.069328],"type":"Point"}
}