<<<<<<< HEAD
{
  "id": 2402104,
  "type": "Feature",
  "properties": {
    "tgn:hierarchy":[
        "tgn:2402104",
        "tgn:1000001",
        "tgn:7006451",
        "tgn:2000092",
        "tgn:7012149",
        "tgn:7029392"
    ],
    "tgn:id":2402104,
    "tgn:name":"Horseshoe Tank",
    "tgn:placetype":[
        "aat:300006191"
    ]
},
  "bbox": [],
  "geometry": {"coordinates":[-111.8667,35.3333],"type":"Point"}
}
=======
{"geometry":{"type":"Point","coordinates":[-111.866700,35.333300]},"type":"Feature","properties":{"hierarchy":["tgn:2402104","tgn:1000001","tgn:7006451","tgn:2000092","tgn:7012149","tgn:7029392"],"placetype":["aat:300006191"],"id":2402104,"name:xx":"Horseshoe Tank"}}
>>>>>>> 03f74aca74312dbeaf24d7e61306dd6a786dc3d0
