{
  "id": 7060389,
  "type": "Feature",
  "properties": {
    "tgn:hierarchy":[
        "tgn:7060389",
        "tgn:7003669",
        "tgn:1000003",
        "tgn:7000084",
        "tgn:7029392"
    ],
    "tgn:id":7060389,
    "tgn:name":"Albis",
    "tgn:placetype":[
        "aat:300008347"
    ]
},
  "bbox": [],
  "geometry": {"coordinates":[10.35,47.633333],"type":"Point"}
}