{
  "id": 2415332,
  "type": "Feature",
  "properties": {
    "tgn:hierarchy":[
        "tgn:2415332",
        "tgn:1000001",
        "tgn:7012149",
        "tgn:2001376",
        "tgn:7007525",
        "tgn:7029392"
    ],
    "tgn:id":2415332,
    "tgn:name":"Island Number 7",
    "tgn:placetype":[
        "aat:300008791"
    ]
},
  "bbox": [],
  "geometry": {"coordinates":[-97.95,41.0833],"type":"Point"}
}