{
  "id": 2373017,
  "type": "Feature",
  "properties": {
    "tgn:hierarchy":[
        "tgn:2373017",
        "tgn:1000001",
        "tgn:7012149",
        "tgn:1002732",
        "tgn:7007710",
        "tgn:7029392"
    ],
    "tgn:id":2373017,
    "tgn:name":"Hallowing Run",
    "tgn:placetype":[
        "aat:300008699"
    ]
},
  "bbox": [],
  "geometry": {"coordinates":[-76.75,40.7833],"type":"Point"}
}