<<<<<<< HEAD
{
  "id": 7353230,
  "type": "Feature",
  "properties": {
    "tgn:hierarchy":[
        "tgn:7353230",
        "tgn:1000001",
        "tgn:7005600",
        "tgn:7005560",
        "tgn:7029392"
    ],
    "tgn:id":7353230,
    "tgn:name":"Baz, Punta",
    "tgn:placetype":[
        "aat:300386846"
    ]
},
  "bbox": [],
  "geometry": {"coordinates":[-90.125,21.15],"type":"Point"}
}
=======
{"geometry":{"type":"Point","coordinates":[-90.125000,21.150000]},"type":"Feature","properties":{"hierarchy":["tgn:7353230","tgn:1000001","tgn:7005600","tgn:7005560","tgn:7029392"],"placetype":["aat:300386846"],"id":7353230,"name:xx":"Baz, Punta"}}
>>>>>>> 03f74aca74312dbeaf24d7e61306dd6a786dc3d0
