{
  "id": 7353230,
  "type": "Feature",
  "properties": {
    "tgn:hierarchy":[
        "tgn:7353230",
        "tgn:1000001",
        "tgn:7005600",
        "tgn:7005560",
        "tgn:7029392"
    ],
    "tgn:id":7353230,
    "tgn:name":"Baz, Punta",
    "tgn:placetype":[
        "aat:300386846"
    ]
},
  "bbox": [],
  "geometry": {"coordinates":[-90.125,21.15],"type":"Point"}
}