{
  "id": 2629462,
  "type": "Feature",
  "properties": {
    "tgn:hierarchy":[
        "tgn:2629462",
        "tgn:1000001",
        "tgn:2001746",
        "tgn:7012149",
        "tgn:7007712",
        "tgn:7029392"
    ],
    "tgn:id":2629462,
    "tgn:name":"Rosemont",
    "tgn:placetype":[
        "aat:300008347"
    ]
},
  "bbox": [],
  "geometry": {"coordinates":[-79.2833,33.3833],"type":"Point"}
}