{
  "id": 7381249,
  "type": "Feature",
  "properties": {
    "tgn:hierarchy":[
        "tgn:7381249",
        "tgn:1000001",
        "tgn:7005589",
        "tgn:7005560",
        "tgn:7029392"
    ],
    "tgn:id":7381249,
    "tgn:name":"Rancho Los Mesquites",
    "tgn:placetype":[
        "aat:300000241"
    ]
},
  "bbox": [],
  "geometry": {"coordinates":[-99.966667,25.95],"type":"Point"}
}