{
  "id": 7483093,
  "type": "Feature",
  "properties": {
    "tgn:hierarchy":[
        "tgn:7483093",
        "tgn:7468018",
        "tgn:1000004",
        "tgn:1000141",
        "tgn:7029392"
    ],
    "tgn:id":7483093,
    "tgn:name":"Shuangxi",
    "tgn:placetype":[
        "aat:300008347"
    ]
},
  "bbox": [],
  "geometry": {"coordinates":[120.536389,23.557222],"type":"Point"}
}