<<<<<<< HEAD
{
  "id": 7483093,
  "type": "Feature",
  "properties": {
    "tgn:hierarchy":[
        "tgn:7483093",
        "tgn:7468018",
        "tgn:1000004",
        "tgn:1000141",
        "tgn:7029392"
    ],
    "tgn:id":7483093,
    "tgn:name":"Shuangxi",
    "tgn:placetype":[
        "aat:300008347"
    ]
},
  "bbox": [],
  "geometry": {"coordinates":[120.536389,23.557222],"type":"Point"}
}
=======
{"geometry":{"type":"Point","coordinates":[120.536389,23.557222]},"type":"Feature","properties":{"hierarchy":["tgn:7483093","tgn:7468018","tgn:1000004","tgn:1000141","tgn:7029392"],"placetype":["aat:300008347"],"id":7483093,"name:xx":"Shuangxi"}}
>>>>>>> 03f74aca74312dbeaf24d7e61306dd6a786dc3d0
