{
  "id": 7309899,
  "type": "Feature",
  "properties": {
    "tgn:hierarchy":[
        "tgn:7309899",
        "tgn:1001699",
        "tgn:1000049",
        "tgn:1000002",
        "tgn:7029392"
    ],
    "tgn:id":7309899,
    "tgn:name":"Osorio, Roca",
    "tgn:placetype":[
        "aat:300011692"
    ]
},
  "bbox": [],
  "geometry": {"coordinates":[-73.916667,-41.766667],"type":"Point"}
}