<<<<<<< HEAD
{
  "id": 7027170,
  "type": "Feature",
  "properties": {
    "tgn:hierarchy":[
        "tgn:7027170",
        "tgn:7002445",
        "tgn:1000003",
        "tgn:7008143",
        "tgn:7008591",
        "tgn:7029392"
    ],
    "tgn:id":7027170,
    "tgn:name:en":"Willersley",
    "tgn:placetype":[
        "aat:300008347",
        "aat:300008372"
    ]
},
  "bbox": [],
  "geometry": {"coordinates":[-3.0,52.116667],"type":"Point"}
}
=======
{"geometry":{"type":"Point","coordinates":[-3.000000,52.116667]},"type":"Feature","properties":{"hierarchy":["tgn:7027170","tgn:7002445","tgn:1000003","tgn:7008143","tgn:7008591","tgn:7029392"],"placetype":["aat:300008347","aat:300008372"],"name:en":"Willersley","id":7027170}}
>>>>>>> 03f74aca74312dbeaf24d7e61306dd6a786dc3d0
