{
  "id": 1049016,
  "type": "Feature",
  "properties": {
    "tgn:hierarchy":[
        "tgn:1049016",
        "tgn:1000003",
        "tgn:7024114",
        "tgn:7006366",
        "tgn:7029392"
    ],
    "tgn:id":1049016,
    "tgn:name":"Drawno",
    "tgn:placetype":[
        "aat:300008347"
    ]
},
  "bbox": [],
  "geometry": {"coordinates":[15.75,53.2167],"type":"Point"}
}