{
  "id": 7126205,
  "type": "Feature",
  "properties": {
    "tgn:hierarchy":[
        "tgn:7126205",
        "tgn:7003669",
        "tgn:1000003",
        "tgn:7000084",
        "tgn:7029392"
    ],
    "tgn:id":7126205,
    "tgn:name":"Nordenberger Forst",
    "tgn:placetype":[
        "aat:300008863"
    ]
},
  "bbox": [],
  "geometry": {"coordinates":[10.266667,49.416667],"type":"Point"}
}