{
  "id": 2155188,
  "type": "Feature",
  "properties": {
    "tgn:hierarchy":[
        "tgn:2155188",
        "tgn:2002143",
        "tgn:1000001",
        "tgn:7012149",
        "tgn:7007919",
        "tgn:7029392"
    ],
    "tgn:id":2155188,
    "tgn:name":"Bear Loop Branch",
    "tgn:placetype":[
        "aat:300008699"
    ]
},
  "bbox": [],
  "geometry": {"coordinates":[-79.8167,37.95],"type":"Point"}
}