{
  "id": 2399721,
  "type": "Feature",
  "properties": {
    "tgn:hierarchy":[
        "tgn:2399721",
        "tgn:1000001",
        "tgn:7012149",
        "tgn:2002264",
        "tgn:7013961",
        "tgn:7029392"
    ],
    "tgn:id":2399721,
    "tgn:name":"Horrock",
    "tgn:placetype":[
        "aat:300008347"
    ]
},
  "bbox": [],
  "geometry": {"coordinates":[-80.2833,38.0167],"type":"Point"}
}