{
  "id": 1114109,
  "type": "Feature",
  "properties": {
    "tgn:hierarchy":[
        "tgn:1114109",
        "tgn:7000508",
        "tgn:1008380",
        "tgn:1000226",
        "tgn:1000006",
        "tgn:7029392"
    ],
    "tgn:id":1114109,
    "tgn:name":"Craddock Channel",
    "tgn:placetype":[
        "aat:300008713"
    ]
},
  "bbox": [],
  "geometry": {"coordinates":[175.216,-36.166],"type":"Point"}
}