{
  "id": 2527905,
  "type": "Feature",
  "properties": {
    "tgn:hierarchy":[
        "tgn:2527905",
        "tgn:1000001",
        "tgn:7012149",
        "tgn:2002162",
        "tgn:7007919",
        "tgn:7029392"
    ],
    "tgn:id":2527905,
    "tgn:name":"Mountain Lake",
    "tgn:placetype":[
        "aat:300008680"
    ]
},
  "bbox": [],
  "geometry": {"coordinates":[-80.5333,37.35],"type":"Point"}
}