{
  "id": 7348861,
  "type": "Feature",
  "properties": {
    "tgn:hierarchy":[
        "tgn:7348861",
        "tgn:1000001",
        "tgn:1001960",
        "tgn:7005560",
        "tgn:7029392"
    ],
    "tgn:id":7348861,
    "tgn:name":"\u00c1lamo, Cerro",
    "tgn:placetype":[
        "aat:300008795"
    ]
},
  "bbox": [],
  "geometry": {"coordinates":[-110.433333,27.933333],"type":"Point"}
}