<<<<<<< HEAD
{
  "id": 2257394,
  "type": "Feature",
  "properties": {
    "tgn:hierarchy":[
        "tgn:2257394",
        "tgn:1000001",
        "tgn:7006451",
        "tgn:7012149",
        "tgn:2000098",
        "tgn:7029392"
    ],
    "tgn:id":2257394,
    "tgn:name":"Cornwall Canyon",
    "tgn:placetype":[
        "aat:300008761"
    ]
},
  "bbox": [],
  "geometry": {"coordinates":[-113.3667,34.65],"type":"Point"}
}
=======
{"geometry":{"type":"Point","coordinates":[-113.366700,34.650000]},"type":"Feature","properties":{"hierarchy":["tgn:2257394","tgn:1000001","tgn:7006451","tgn:7012149","tgn:2000098","tgn:7029392"],"placetype":["aat:300008761"],"id":2257394,"name:xx":"Cornwall Canyon"}}
>>>>>>> 03f74aca74312dbeaf24d7e61306dd6a786dc3d0
