{
  "id": 2626207,
  "type": "Feature",
  "properties": {
    "tgn:hierarchy":[
        "tgn:2626207",
        "tgn:1000001",
        "tgn:7012149",
        "tgn:2002030",
        "tgn:7007826",
        "tgn:7029392"
    ],
    "tgn:id":2626207,
    "tgn:name":"Rocky Creek",
    "tgn:placetype":[
        "aat:300008706"
    ]
},
  "bbox": [],
  "geometry": {"coordinates":[-98.55,30.6667],"type":"Point"}
}