<<<<<<< HEAD
{
  "id": 7116939,
  "type": "Feature",
  "properties": {
    "tgn:hierarchy":[
        "tgn:7116939",
        "tgn:1000003",
        "tgn:7003676",
        "tgn:7000084",
        "tgn:7029392"
    ],
    "tgn:id":7116939,
    "tgn:name":"Oesedium",
    "tgn:placetype":[
        "aat:300008347"
    ]
},
  "bbox": [],
  "geometry": {"coordinates":[8.9,52.833333],"type":"Point"}
}
=======
{"geometry":{"type":"Point","coordinates":[8.900000,52.833333]},"type":"Feature","properties":{"hierarchy":["tgn:7116939","tgn:1000003","tgn:7003676","tgn:7000084","tgn:7029392"],"placetype":["aat:300008347"],"id":7116939,"name:xx":"Oesedium"}}
>>>>>>> 03f74aca74312dbeaf24d7e61306dd6a786dc3d0
