{
  "id": 2487931,
  "type": "Feature",
  "properties": {
    "tgn:hierarchy":[
        "tgn:2487931",
        "tgn:1000001",
        "tgn:2002256",
        "tgn:7012149",
        "tgn:7013961",
        "tgn:7029392"
    ],
    "tgn:id":2487931,
    "tgn:name":"Left Fork Wolf Creek",
    "tgn:placetype":[
        "aat:300008706"
    ]
},
  "bbox": [],
  "geometry": {"coordinates":[-80.6333,38.5667],"type":"Point"}
}