{
  "id": 2464501,
  "type": "Feature",
  "properties": {
    "tgn:hierarchy":[
        "tgn:2464501",
        "tgn:1000001",
        "tgn:7012149",
        "tgn:2001714",
        "tgn:7007708",
        "tgn:7029392"
    ],
    "tgn:id":2464501,
    "tgn:name":"Log Cabin Spring",
    "tgn:placetype":[
        "aat:300008697"
    ]
},
  "bbox": [],
  "geometry": {"coordinates":[-120.9167,42.05],"type":"Point"}
}