{
  "id": 2453904,
  "type": "Feature",
  "properties": {
    "tgn:hierarchy":[
        "tgn:2453904",
        "tgn:7002659",
        "tgn:1000001",
        "tgn:7012149",
        "tgn:2000036",
        "tgn:7029392"
    ],
    "tgn:id":2453904,
    "tgn:name":"Little Creek",
    "tgn:placetype":[
        "aat:300008706"
    ]
},
  "bbox": [],
  "geometry": {"coordinates":[-86.95,33.4667],"type":"Point"}
}