{
  "id": 2607190,
  "type": "Feature",
  "properties": {
    "tgn:hierarchy":[
        "tgn:2607190",
        "tgn:1000001",
        "tgn:7012149",
        "tgn:2001708",
        "tgn:7007708",
        "tgn:7029392"
    ],
    "tgn:id":2607190,
    "tgn:name":"Randall Spring",
    "tgn:placetype":[
        "aat:300008697"
    ]
},
  "bbox": [],
  "geometry": {"coordinates":[-119.0333,44.1333],"type":"Point"}
}