{
  "id": 7124684,
  "type": "Feature",
  "properties": {
    "tgn:hierarchy":[
        "tgn:7124684",
        "tgn:1000003",
        "tgn:7003689",
        "tgn:7000084",
        "tgn:7029392"
    ],
    "tgn:id":7124684,
    "tgn:name":"Neufrankenroda",
    "tgn:placetype":[
        "aat:300008347"
    ]
},
  "bbox": [],
  "geometry": {"coordinates":[10.566667,50.966667],"type":"Point"}
}