{
  "id": 7080226,
  "type": "Feature",
  "properties": {
    "tgn:hierarchy":[
        "tgn:7080226",
        "tgn:1000003",
        "tgn:7003687",
        "tgn:7000084",
        "tgn:7029392"
    ],
    "tgn:id":7080226,
    "tgn:name":"Zeddenbach",
    "tgn:placetype":[
        "aat:300008347"
    ]
},
  "bbox": [],
  "geometry": {"coordinates":[11.75,51.216667],"type":"Point"}
}