{
  "id": 2454865,
  "type": "Feature",
  "properties": {
    "tgn:hierarchy":[
        "tgn:2454865",
        "tgn:1000001",
        "tgn:7012149",
        "tgn:1002472",
        "tgn:7007568",
        "tgn:7029392"
    ],
    "tgn:id":2454865,
    "tgn:name":"Little Duck Pond",
    "tgn:placetype":[
        "aat:300008680"
    ]
},
  "bbox": [],
  "geometry": {"coordinates":[-74.8667,44.0167],"type":"Point"}
}