{
  "id": 7562463,
  "type": "Feature",
  "properties": {
    "tgn:hierarchy":[
        "tgn:7562463",
        "tgn:1000004",
        "tgn:7000198",
        "tgn:7016722",
        "tgn:7029392"
    ],
    "tgn:id":7562463,
    "tgn:name:en":"T\u0101r\u0101pur",
    "tgn:placetype":[
        "aat:300008347"
    ]
},
  "bbox": [],
  "geometry": {"coordinates":[79.807,27.1424],"type":"Point"}
}