{
  "id": 1133869,
  "type": "Feature",
  "properties": {
    "tgn:hierarchy":[
        "tgn:1133869",
        "tgn:1000001",
        "tgn:7012149",
        "tgn:7007710",
        "tgn:7029392"
    ],
    "tgn:id":1133869,
    "tgn:name":"Millers Run",
    "tgn:placetype":[
        "aat:300008706"
    ]
},
  "bbox": [],
  "geometry": {"coordinates":[-80.2833,40.3333],"type":"Point"}
}