{
  "id": 7005042,
  "type": "Feature",
  "properties": {
    "tgn:hierarchy":[
        "tgn:7005042",
        "tgn:7003170",
        "tgn:1000003",
        "tgn:7003125",
        "tgn:1000080",
        "tgn:7029392"
    ],
    "tgn:id":7005042,
    "tgn:name":"Spoleto",
    "tgn:placetype":[
        "aat:300387277",
        "aat:300008347",
        "aat:300000810",
        "aat:300387308",
        "aat:300005135",
        "aat:300386570",
        "aat:300387235",
        "aat:300020471",
        "aat:300008375",
        "aat:300387267",
        "aat:300387291"
    ]
},
  "bbox": [],
  "geometry": {"coordinates":[12.733333,42.733333],"type":"Point"}
}