{
  "id": 2080535,
  "type": "Feature",
  "properties": {
    "tgn:hierarchy":[
        "tgn:2080535",
        "tgn:1000001",
        "tgn:7012149",
        "tgn:1002917",
        "tgn:7007706",
        "tgn:7029392"
    ],
    "tgn:id":2080535,
    "tgn:name":"Magnolia",
    "tgn:placetype":[
        "aat:300008347"
    ]
},
  "bbox": [],
  "geometry": {"coordinates":[-81.2833,40.65],"type":"Point"}
}