{
  "id": 1008416,
  "type": "Feature",
  "properties": {
    "tgn:hierarchy":[
        "tgn:1008416",
        "tgn:1000223",
        "tgn:1000006",
        "tgn:7029392"
    ],
    "tgn:id":1008416,
    "tgn:name":"Observatoire, Caye de l'",
    "tgn:placetype":[
        "aat:300008791"
    ]
},
  "bbox": [],
  "geometry": {"coordinates":[158.9333,-21.4667],"type":"Point"}
}