{
  "id": 7246701,
  "type": "Feature",
  "properties": {
    "tgn:hierarchy":[
        "tgn:7246701",
        "tgn:7003457",
        "tgn:1000003",
        "tgn:1000063",
        "tgn:7018236",
        "tgn:7029392"
    ],
    "tgn:id":7246701,
    "tgn:name":"Bosstraat",
    "tgn:placetype":[
        "aat:300008347"
    ]
},
  "bbox": [],
  "geometry": {"coordinates":[3.95,50.916667],"type":"Point"}
}