<<<<<<< HEAD
{
  "id": 7115795,
  "type": "Feature",
  "properties": {
    "tgn:hierarchy":[
        "tgn:7115795",
        "tgn:1000003",
        "tgn:7003676",
        "tgn:7000084",
        "tgn:7029392"
    ],
    "tgn:id":7115795,
    "tgn:name":"Ohr",
    "tgn:placetype":[
        "aat:300008347"
    ]
},
  "bbox": [],
  "geometry": {"coordinates":[9.35,52.066667],"type":"Point"}
}
=======
{"geometry":{"type":"Point","coordinates":[9.350000,52.066667]},"type":"Feature","properties":{"hierarchy":["tgn:7115795","tgn:1000003","tgn:7003676","tgn:7000084","tgn:7029392"],"placetype":["aat:300008347"],"id":7115795,"name:xx":"Ohr"}}
>>>>>>> 03f74aca74312dbeaf24d7e61306dd6a786dc3d0
