{
  "id": 2612508,
  "type": "Feature",
  "properties": {
    "tgn:hierarchy":[
        "tgn:2612508",
        "tgn:1000001",
        "tgn:7012149",
        "tgn:7007158",
        "tgn:7029392"
    ],
    "tgn:id":2612508,
    "tgn:name":"Red Willow Creek",
    "tgn:placetype":[
        "aat:300008706"
    ]
},
  "bbox": [],
  "geometry": {"coordinates":[-102.7833,40.3833],"type":"Point"}
}