{
  "id": 1088782,
  "type": "Feature",
  "properties": {
    "tgn:hierarchy":[
        "tgn:1088782",
        "tgn:7001242",
        "tgn:7016755",
        "tgn:1000159",
        "tgn:7029392"
    ],
    "tgn:id":1088782,
    "tgn:name":"Bambili",
    "tgn:placetype":[
        "aat:300008347"
    ]
},
  "bbox": [],
  "geometry": {"coordinates":[26.1167,3.5667],"type":"Point"}
}