{
  "id": 2236224,
  "type": "Feature",
  "properties": {
    "tgn:hierarchy":[
        "tgn:2236224",
        "tgn:7006450",
        "tgn:1000001",
        "tgn:7012149",
        "tgn:2000082",
        "tgn:7029392"
    ],
    "tgn:id":2236224,
    "tgn:name":"Chickamin Glacier",
    "tgn:placetype":[
        "aat:300008835"
    ]
},
  "bbox": [],
  "geometry": {"coordinates":[-130.2833,56.05],"type":"Point"}
}