{
  "id": 1062981,
  "type": "Feature",
  "properties": {
    "tgn:hierarchy":[
        "tgn:1062981",
        "tgn:1000003",
        "tgn:1000462",
        "tgn:1000097",
        "tgn:7029392"
    ],
    "tgn:id":1062981,
    "tgn:name":"Forsmark",
    "tgn:placetype":[
        "aat:300008347"
    ]
},
  "bbox": [],
  "geometry": {"coordinates":[18.1667,60.3667],"type":"Point"}
}