{
  "id": 2365720,
  "type": "Feature",
  "properties": {
    "tgn:hierarchy":[
        "tgn:2365720",
        "tgn:1000001",
        "tgn:7012149",
        "tgn:2000476",
        "tgn:7007250",
        "tgn:7029392"
    ],
    "tgn:id":2365720,
    "tgn:name":"Gregory Creek",
    "tgn:placetype":[
        "aat:300008706"
    ]
},
  "bbox": [],
  "geometry": {"coordinates":[-116.3833,45.7333],"type":"Point"}
}