{
  "id": 7486957,
  "type": "Feature",
  "properties": {
    "tgn:hierarchy":[
        "tgn:7486957",
        "tgn:7001004",
        "tgn:1000004",
        "tgn:1000141",
        "tgn:7029392"
    ],
    "tgn:id":7486957,
    "tgn:name":"Lingyaliao",
    "tgn:placetype":[
        "aat:300000745"
    ]
},
  "bbox": [],
  "geometry": {"coordinates":[120.298456,22.619667],"type":"Point"}
}