{
  "id": 2305893,
  "type": "Feature",
  "properties": {
    "tgn:hierarchy":[
        "tgn:2305893",
        "tgn:1000001",
        "tgn:7012149",
        "tgn:2002383",
        "tgn:7007923",
        "tgn:7029392"
    ],
    "tgn:id":2305893,
    "tgn:name":"East Draw",
    "tgn:placetype":[
        "aat:300008761"
    ]
},
  "bbox": [],
  "geometry": {"coordinates":[-108.7167,41.1667],"type":"Point"}
}