<<<<<<< HEAD
{
  "id": 2409584,
  "type": "Feature",
  "properties": {
    "tgn:hierarchy":[
        "tgn:2409584",
        "tgn:7006450",
        "tgn:1000001",
        "tgn:7030547",
        "tgn:7012149",
        "tgn:7029392"
    ],
    "tgn:id":2409584,
    "tgn:name":"Igloo Mountain",
    "tgn:placetype":[
        "aat:300008798"
    ]
},
  "bbox": [],
  "geometry": {"coordinates":[-149.6167,63.6],"type":"Point"}
}
=======
{"geometry":{"type":"Point","coordinates":[-149.616700,63.600000]},"type":"Feature","properties":{"hierarchy":["tgn:2409584","tgn:7006450","tgn:1000001","tgn:7030547","tgn:7012149","tgn:7029392"],"placetype":["aat:300008798"],"id":2409584,"name:xx":"Igloo Mountain"}}
>>>>>>> 03f74aca74312dbeaf24d7e61306dd6a786dc3d0
