{
  "id": 2116059,
  "type": "Feature",
  "properties": {
    "tgn:hierarchy":[
        "tgn:2116059",
        "tgn:1000001",
        "tgn:7012149",
        "tgn:1002554",
        "tgn:7007920",
        "tgn:7029392"
    ],
    "tgn:id":2116059,
    "tgn:name":"Klickitat",
    "tgn:placetype":[
        "aat:300008347"
    ]
},
  "bbox": [],
  "geometry": {"coordinates":[-121.15,45.8167],"type":"Point"}
}