{
  "id": 1132720,
  "type": "Feature",
  "properties": {
    "tgn:hierarchy":[
        "tgn:1132720",
        "tgn:1000001",
        "tgn:7012149",
        "tgn:2000917",
        "tgn:7007256",
        "tgn:7029392"
    ],
    "tgn:id":1132720,
    "tgn:name":"Castor Creek",
    "tgn:placetype":[
        "aat:300008706"
    ]
},
  "bbox": [],
  "geometry": {"coordinates":[-92.35,31.7833],"type":"Point"}
}