{
  "id": 2724922,
  "type": "Feature",
  "properties": {
    "tgn:hierarchy":[
        "tgn:2724922",
        "tgn:1000001",
        "tgn:7012149",
        "tgn:7007157",
        "tgn:1002710",
        "tgn:7029392"
    ],
    "tgn:id":2724922,
    "tgn:name":"Toms Creek",
    "tgn:placetype":[
        "aat:300008706"
    ]
},
  "bbox": [],
  "geometry": {"coordinates":[-120.6333,39.4667],"type":"Point"}
}