{
  "id": 2540414,
  "type": "Feature",
  "properties": {
    "tgn:hierarchy":[
        "tgn:2540414",
        "tgn:1000001",
        "tgn:7012149",
        "tgn:1002627",
        "tgn:7007706",
        "tgn:7029392"
    ],
    "tgn:id":2540414,
    "tgn:name":"Newport Lake",
    "tgn:placetype":[
        "aat:300006191"
    ]
},
  "bbox": [],
  "geometry": {"coordinates":[-80.6667,41.05],"type":"Point"}
}