{
  "id": 2364309,
  "type": "Feature",
  "properties": {
    "tgn:hierarchy":[
        "tgn:2364309",
        "tgn:1000001",
        "tgn:7012149",
        "tgn:7007157",
        "tgn:1002857",
        "tgn:7029392"
    ],
    "tgn:id":2364309,
    "tgn:name":"Green Rock Mine",
    "tgn:placetype":[
        "aat:300000390"
    ]
},
  "bbox": [],
  "geometry": {"coordinates":[-116.7167,34.4833],"type":"Point"}
}