<<<<<<< HEAD
{
  "id": 7486202,
  "type": "Feature",
  "properties": {
    "tgn:hierarchy":[
        "tgn:7486202",
        "tgn:7487020",
        "tgn:1000004",
        "tgn:1000141",
        "tgn:7029392"
    ],
    "tgn:id":7486202,
    "tgn:name":"Niubu",
    "tgn:placetype":[
        "aat:300008347"
    ]
},
  "bbox": [],
  "geometry": {"coordinates":[120.754529,24.502559],"type":"Point"}
}
=======
{"geometry":{"type":"Point","coordinates":[120.754529,24.502559]},"type":"Feature","properties":{"hierarchy":["tgn:7486202","tgn:7487020","tgn:1000004","tgn:1000141","tgn:7029392"],"placetype":["aat:300008347"],"id":7486202,"name:xx":"Niubu"}}
>>>>>>> 03f74aca74312dbeaf24d7e61306dd6a786dc3d0
