{
  "id": 7142484,
  "type": "Feature",
  "properties": {
    "tgn:hierarchy":[
        "tgn:7142484",
        "tgn:7003669",
        "tgn:1000003",
        "tgn:7000084",
        "tgn:7029392"
    ],
    "tgn:id":7142484,
    "tgn:name":"Ludwigs-Kanal",
    "tgn:placetype":[
        "aat:300006075"
    ]
},
  "bbox": [],
  "geometry": {"coordinates":[11.766667,48.366667],"type":"Point"}
}