{
  "id": 7340273,
  "type": "Feature",
  "properties": {
    "tgn:hierarchy":[
        "tgn:7340273",
        "tgn:7002824",
        "tgn:1000003",
        "tgn:7002786",
        "tgn:1000095",
        "tgn:7029392"
    ],
    "tgn:id":7340273,
    "tgn:name":"Collantres",
    "tgn:placetype":[
        "aat:300008347"
    ]
},
  "bbox": [],
  "geometry": {"coordinates":[-8.166667,43.266667],"type":"Point"}
}