{
  "id": 2747616,
  "type": "Feature",
  "properties": {
    "tgn:hierarchy":[
        "tgn:2747616",
        "tgn:1002648",
        "tgn:1000001",
        "tgn:1008191",
        "tgn:7012149",
        "tgn:7007249",
        "tgn:7029392"
    ],
    "tgn:id":2747616,
    "tgn:name":"Wailoku Gulch",
    "tgn:placetype":[
        "aat:300008761"
    ]
},
  "bbox": [],
  "geometry": {"coordinates":[-156.7333,21.1333],"type":"Point"}
}