{
  "id": 7592348,
  "type": "Feature",
  "properties": {
    "tgn:hierarchy":[
        "tgn:7592348",
        "tgn:1000004",
        "tgn:7000198",
        "tgn:7000799",
        "tgn:7029392"
    ],
    "tgn:id":7592348,
    "tgn:name:en":"Gura",
    "tgn:placetype":[
        "aat:300008347"
    ]
},
  "bbox": [],
  "geometry": {"coordinates":[74.180555,33.169989],"type":"Point"}
}