<<<<<<< HEAD
{
  "id": 2767212,
  "type": "Feature",
  "properties": {
    "tgn:hierarchy":[
        "tgn:2767212",
        "tgn:1000001",
        "tgn:7012149",
        "tgn:7007157",
        "tgn:1002684",
        "tgn:7029392"
    ],
    "tgn:id":2767212,
    "tgn:name":"White Rock Number Two",
    "tgn:placetype":[
        "aat:300132348"
    ]
},
  "bbox": [],
  "geometry": {"coordinates":[-121.3667,35.8167],"type":"Point"}
}
=======
{"geometry":{"type":"Point","coordinates":[-121.366700,35.816700]},"type":"Feature","properties":{"hierarchy":["tgn:2767212","tgn:1000001","tgn:7012149","tgn:7007157","tgn:1002684","tgn:7029392"],"placetype":["aat:300132348"],"id":2767212,"name:xx":"White Rock Number Two"}}
>>>>>>> 03f74aca74312dbeaf24d7e61306dd6a786dc3d0
