{
  "id": 2198125,
  "type": "Feature",
  "properties": {
    "tgn:hierarchy":[
        "tgn:2198125",
        "tgn:1000001",
        "tgn:2002319",
        "tgn:7012149",
        "tgn:7007922",
        "tgn:7029392"
    ],
    "tgn:id":2198125,
    "tgn:name":"Browning Lake",
    "tgn:placetype":[
        "aat:300132316"
    ]
},
  "bbox": [],
  "geometry": {"coordinates":[-91.8833,44.6833],"type":"Point"}
}