{
  "id": 7283938,
  "type": "Feature",
  "properties": {
    "tgn:hierarchy":[
        "tgn:7283938",
        "tgn:1001623",
        "tgn:1000049",
        "tgn:1000002",
        "tgn:7029392"
    ],
    "tgn:id":7283938,
    "tgn:name":"Pups, Islotes",
    "tgn:placetype":[
        "aat:300008791"
    ]
},
  "bbox": [],
  "geometry": {"coordinates":[-74.85,-45.833333],"type":"Point"}
}