<<<<<<< HEAD
{
  "id": 7481810,
  "type": "Feature",
  "properties": {
    "tgn:hierarchy":[
        "tgn:7481810",
        "tgn:1000004",
        "tgn:7490934",
        "tgn:1000141",
        "tgn:7029392"
    ],
    "tgn:id":7481810,
    "tgn:name":"Guandong",
    "tgn:placetype":[
        "aat:300008347"
    ]
},
  "bbox": [],
  "geometry": {"coordinates":[120.115248,23.257924],"type":"Point"}
}
=======
{"geometry":{"type":"Point","coordinates":[120.115248,23.257924]},"type":"Feature","properties":{"hierarchy":["tgn:7481810","tgn:1000004","tgn:7490934","tgn:1000141","tgn:7029392"],"placetype":["aat:300008347"],"id":7481810,"name:xx":"Guandong"}}
>>>>>>> 03f74aca74312dbeaf24d7e61306dd6a786dc3d0
