{
  "id": 7404877,
  "type": "Feature",
  "properties": {
    "tgn:hierarchy":[
        "tgn:7404877",
        "tgn:7005585",
        "tgn:1000001",
        "tgn:7005560",
        "tgn:7029392"
    ],
    "tgn:id":7404877,
    "tgn:name":"Tlapexpa",
    "tgn:placetype":[
        "aat:300008347"
    ]
},
  "bbox": [],
  "geometry": {"coordinates":[-100.45,18.325],"type":"Point"}
}