{
  "id": 2368034,
  "type": "Feature",
  "properties": {
    "tgn:hierarchy":[
        "tgn:2368034",
        "tgn:1000001",
        "tgn:7012149",
        "tgn:2001449",
        "tgn:7007566",
        "tgn:7029392"
    ],
    "tgn:id":2368034,
    "tgn:name":"Grulla, Valle de la",
    "tgn:placetype":[
        "aat:300008761"
    ]
},
  "bbox": [],
  "geometry": {"coordinates":[-106.5667,36.0667],"type":"Point"}
}