{
  "id": 2370023,
  "type": "Feature",
  "properties": {
    "tgn:hierarchy":[
        "tgn:2370023",
        "tgn:1000001",
        "tgn:7012149",
        "tgn:2000237",
        "tgn:7007158",
        "tgn:7029392"
    ],
    "tgn:id":2370023,
    "tgn:name":"Gutshall Spring",
    "tgn:placetype":[
        "aat:300008697"
    ]
},
  "bbox": [],
  "geometry": {"coordinates":[-107.85,38.1833],"type":"Point"}
}