{
  "id": 2489430,
  "type": "Feature",
  "properties": {
    "tgn:hierarchy":[
        "tgn:2489430",
        "tgn:1000001",
        "tgn:1002271",
        "tgn:7012149",
        "tgn:7007920",
        "tgn:7029392"
    ],
    "tgn:id":2489430,
    "tgn:name":"Maletti Hill",
    "tgn:placetype":[
        "aat:300008798"
    ]
},
  "bbox": [],
  "geometry": {"coordinates":[-123.3167,48.0167],"type":"Point"}
}