{
  "id": 7528235,
  "type": "Feature",
  "properties": {
    "tgn:hierarchy":[
        "tgn:7528235",
        "tgn:7001242",
        "tgn:7016833",
        "tgn:7029392"
    ],
    "tgn:id":7528235,
    "tgn:name":"Qisayb, W\u0101d\u012b",
    "tgn:placetype":[
        "aat:300379998"
    ]
},
  "bbox": [],
  "geometry": {"coordinates":[31.838421,29.34676],"type":"Point"}
}