{
  "id": 2288852,
  "type": "Feature",
  "properties": {
    "tgn:hierarchy":[
        "tgn:2288852",
        "tgn:1000001",
        "tgn:7012149",
        "tgn:2001222",
        "tgn:7007523",
        "tgn:7029392"
    ],
    "tgn:id":2288852,
    "tgn:name":"Ditch Number 57",
    "tgn:placetype":[
        "aat:300006075"
    ]
},
  "bbox": [],
  "geometry": {"coordinates":[-89.8167,36.4333],"type":"Point"}
}