{
  "id": 2474765,
  "type": "Feature",
  "properties": {
    "tgn:hierarchy":[
        "tgn:2474765",
        "tgn:1000001",
        "tgn:7012149",
        "tgn:2000488",
        "tgn:7007250",
        "tgn:7029392"
    ],
    "tgn:id":2474765,
    "tgn:name":"Lower Swale",
    "tgn:placetype":[
        "aat:300008761"
    ]
},
  "bbox": [],
  "geometry": {"coordinates":[-115.85,42.05],"type":"Point"}
}