{
  "id": 1064072,
  "type": "Feature",
  "properties": {
    "tgn:hierarchy":[
        "tgn:1064072",
        "tgn:7003740",
        "tgn:1000003",
        "tgn:7011731",
        "tgn:7029392"
    ],
    "tgn:id":1064072,
    "tgn:name":"Gelterkinden",
    "tgn:placetype":[
        "aat:300008347"
    ]
},
  "bbox": [],
  "geometry": {"coordinates":[7.8667,47.45],"type":"Point"}
}