<<<<<<< HEAD
{
  "id": 2252854,
  "type": "Feature",
  "properties": {
    "tgn:hierarchy":[
        "tgn:2252854",
        "tgn:1000001",
        "tgn:7012149",
        "tgn:2001517",
        "tgn:7007709",
        "tgn:7029392"
    ],
    "tgn:id":2252854,
    "tgn:name":"Conoho",
    "tgn:placetype":[
        "aat:300008347"
    ]
},
  "bbox": [],
  "geometry": {"coordinates":[-77.3,35.9833],"type":"Point"}
}
=======
{"geometry":{"type":"Point","coordinates":[-77.300000,35.983300]},"type":"Feature","properties":{"hierarchy":["tgn:2252854","tgn:1000001","tgn:7012149","tgn:2001517","tgn:7007709","tgn:7029392"],"placetype":["aat:300008347"],"id":2252854,"name:xx":"Conoho"}}
>>>>>>> 03f74aca74312dbeaf24d7e61306dd6a786dc3d0
