{
  "id": 2208544,
  "type": "Feature",
  "properties": {
    "tgn:hierarchy":[
        "tgn:2208544",
        "tgn:1000001",
        "tgn:7012149",
        "tgn:7019676",
        "tgn:7007566",
        "tgn:7029392"
    ],
    "tgn:id":2208544,
    "tgn:name":"Burning Bridge Wash",
    "tgn:placetype":[
        "aat:300008699"
    ]
},
  "bbox": [],
  "geometry": {"coordinates":[-107.6667,35.8667],"type":"Point"}
}