{
  "id": 2221704,
  "type": "Feature",
  "properties": {
    "tgn:hierarchy":[
        "tgn:2221704",
        "tgn:1000001",
        "tgn:7012149",
        "tgn:2001917",
        "tgn:7007825",
        "tgn:7029392"
    ],
    "tgn:id":2221704,
    "tgn:name":"Carlisle Spring",
    "tgn:placetype":[
        "aat:300008697"
    ]
},
  "bbox": [],
  "geometry": {"coordinates":[-87.75,36.4167],"type":"Point"}
}