<<<<<<< HEAD
{
  "id": 7371790,
  "type": "Feature",
  "properties": {
    "tgn:hierarchy":[
        "tgn:7371790",
        "tgn:1000001",
        "tgn:7005595",
        "tgn:7005560",
        "tgn:7029392"
    ],
    "tgn:id":7371790,
    "tgn:name":"Rancho La Huerta",
    "tgn:placetype":[
        "aat:300000241"
    ]
},
  "bbox": [],
  "geometry": {"coordinates":[-107.55,25.45],"type":"Point"}
}
=======
{"geometry":{"type":"Point","coordinates":[-107.550000,25.450000]},"type":"Feature","properties":{"hierarchy":["tgn:7371790","tgn:1000001","tgn:7005595","tgn:7005560","tgn:7029392"],"placetype":["aat:300000241"],"id":7371790,"name:xx":"Rancho La Huerta"}}
>>>>>>> 03f74aca74312dbeaf24d7e61306dd6a786dc3d0
