{
  "id": 7139740,
  "type": "Feature",
  "properties": {
    "tgn:hierarchy":[
        "tgn:7139740",
        "tgn:1000003",
        "tgn:7003678",
        "tgn:7000084",
        "tgn:7029392"
    ],
    "tgn:id":7139740,
    "tgn:name":"Langengrund",
    "tgn:placetype":[
        "aat:300008761"
    ]
},
  "bbox": [],
  "geometry": {"coordinates":[8.683333,50.95],"type":"Point"}
}