{
  "id": 4001047,
  "type": "Feature",
  "properties": {
    "tgn:hierarchy":[
        "tgn:4001047",
        "tgn:1000003",
        "tgn:7594009",
        "tgn:1000066",
        "tgn:7029392"
    ],
    "tgn:id":4001047,
    "tgn:name":"B\u00f8rsmose",
    "tgn:placetype":[
        "aat:300008347"
    ]
},
  "bbox": [],
  "geometry": {"coordinates":[81.1667,55.6667],"type":"Point"}
}