<<<<<<< HEAD
{
  "id": 7373233,
  "type": "Feature",
  "properties": {
    "tgn:hierarchy":[
        "tgn:7373233",
        "tgn:1000001",
        "tgn:7005599",
        "tgn:7005560",
        "tgn:7029392"
    ],
    "tgn:id":7373233,
    "tgn:name":"La Chorrera",
    "tgn:placetype":[
        "aat:300008347"
    ]
},
  "bbox": [],
  "geometry": {"coordinates":[-95.783333,18.55],"type":"Point"}
}
=======
{"geometry":{"type":"Point","coordinates":[-95.783333,18.550000]},"type":"Feature","properties":{"hierarchy":["tgn:7373233","tgn:1000001","tgn:7005599","tgn:7005560","tgn:7029392"],"placetype":["aat:300008347"],"id":7373233,"name:xx":"La Chorrera"}}
>>>>>>> 03f74aca74312dbeaf24d7e61306dd6a786dc3d0
