{
  "id": 7549957,
  "type": "Feature",
  "properties": {
    "tgn:hierarchy":[
        "tgn:7549957",
        "tgn:1000004",
        "tgn:7000198",
        "tgn:7016788",
        "tgn:7029392"
    ],
    "tgn:id":7549957,
    "tgn:name:en":"Dharmi Khu",
    "tgn:placetype":[
        "aat:300006207"
    ]
},
  "bbox": [],
  "geometry": {"coordinates":[70.627482,27.778954],"type":"Point"}
}