{
  "id": 2553465,
  "type": "Feature",
  "properties": {
    "tgn:hierarchy":[
        "tgn:2553465",
        "tgn:1000001",
        "tgn:7012149",
        "tgn:7007157",
        "tgn:1002867",
        "tgn:7029392"
    ],
    "tgn:id":2553465,
    "tgn:name":"Oak Creek",
    "tgn:placetype":[
        "aat:300008706"
    ]
},
  "bbox": [],
  "geometry": {"coordinates":[-119.6167,34.45],"type":"Point"}
}