{
  "id": 1023296,
  "type": "Feature",
  "properties": {
    "tgn:hierarchy":[
        "tgn:1023296",
        "tgn:7012827",
        "tgn:7002454",
        "tgn:1000047",
        "tgn:1000002",
        "tgn:7029392"
    ],
    "tgn:id":1023296,
    "tgn:name":"Valdel\u00e2ndia",
    "tgn:placetype":[
        "aat:300008347"
    ]
},
  "bbox": [],
  "geometry": {"coordinates":[-50.0333,-15.1833],"type":"Point"}
}