{
  "id": 7440146,
  "type": "Feature",
  "properties": {
    "tgn:hierarchy":[
        "tgn:7440146",
        "tgn:1000001",
        "tgn:7005596",
        "tgn:7005560",
        "tgn:7029392"
    ],
    "tgn:id":7440146,
    "tgn:name":"San Marcos, Laguna",
    "tgn:placetype":[
        "aat:300008680"
    ]
},
  "bbox": [],
  "geometry": {"coordinates":[-91.333333,17.333333],"type":"Point"}
}