{
  "id": 1136729,
  "type": "Feature",
  "properties": {
    "tgn:hierarchy":[
        "tgn:1136729",
        "tgn:7002445",
        "tgn:1000003",
        "tgn:7008153",
        "tgn:7008591",
        "tgn:7029392"
    ],
    "tgn:id":1136729,
    "tgn:name:en":"Newington",
    "tgn:placetype":[
        "aat:300008347",
        "aat:300008372"
    ]
},
  "bbox": [],
  "geometry": {"coordinates":[0.666667,51.35],"type":"Point"}
}