{
  "id": 4010627,
  "type": "Feature",
  "properties": {
    "tgn:hierarchy":[
        "tgn:4010627",
        "tgn:7002810",
        "tgn:7001158",
        "tgn:1000003",
        "tgn:1000095",
        "tgn:7029392"
    ],
    "tgn:id":4010627,
    "tgn:name":"Sotillo de la Ribera",
    "tgn:placetype":[
        "aat:300008347"
    ]
},
  "bbox": [],
  "geometry": {"coordinates":[-3.816667,41.783333],"type":"Point"}
}