{
  "id": 2753004,
  "type": "Feature",
  "properties": {
    "tgn:hierarchy":[
        "tgn:2753004",
        "tgn:1000001",
        "tgn:7012149",
        "tgn:2001288",
        "tgn:7007524",
        "tgn:7029392"
    ],
    "tgn:id":2753004,
    "tgn:name":"Water Gulch",
    "tgn:placetype":[
        "aat:300008761"
    ]
},
  "bbox": [],
  "geometry": {"coordinates":[-111.9667,45.35],"type":"Point"}
}