{
  "id": 2221764,
  "type": "Feature",
  "properties": {
    "tgn:hierarchy":[
        "tgn:2221764",
        "tgn:1000001",
        "tgn:2001436",
        "tgn:7012149",
        "tgn:7007566",
        "tgn:7029392"
    ],
    "tgn:id":2221764,
    "tgn:name":"Carlsbad Pit",
    "tgn:placetype":[
        "aat:300000390"
    ]
},
  "bbox": [],
  "geometry": {"coordinates":[-104.25,32.3333],"type":"Point"}
}