{
  "id": 7025200,
  "type": "Feature",
  "properties": {
    "tgn:hierarchy":[
        "tgn:7025200",
        "tgn:7002445",
        "tgn:1000003",
        "tgn:7008118",
        "tgn:7008591",
        "tgn:7029392"
    ],
    "tgn:id":7025200,
    "tgn:name:ang":"Henlege",
    "tgn:placetype":[
        "aat:300008347"
    ]
},
  "bbox": [],
  "geometry": {"coordinates":[-1.3833,53.2833],"type":"Point"}
}