{
  "id": 2755229,
  "type": "Feature",
  "properties": {
    "tgn:hierarchy":[
        "tgn:2755229",
        "tgn:1000001",
        "tgn:7012149",
        "tgn:2001713",
        "tgn:7007708",
        "tgn:7029392"
    ],
    "tgn:id":2755229,
    "tgn:name":"Webb Reservoir",
    "tgn:placetype":[
        "aat:300006191"
    ]
},
  "bbox": [],
  "geometry": {"coordinates":[-123.25,42.25],"type":"Point"}
}