{
  "id": 7429536,
  "type": "Feature",
  "properties": {
    "tgn:hierarchy":[
        "tgn:7429536",
        "tgn:1000001",
        "tgn:7005595",
        "tgn:7005560",
        "tgn:7029392"
    ],
    "tgn:id":7429536,
    "tgn:name":"Presa La Vinata",
    "tgn:placetype":[
        "aat:300006191"
    ]
},
  "bbox": [],
  "geometry": {"coordinates":[-107.233333,24.55],"type":"Point"}
}