{
  "id": 7499790,
  "type": "Feature",
  "properties": {
    "tgn:hierarchy":[
        "tgn:7499790",
        "tgn:7001010",
        "tgn:1000004",
        "tgn:1000141",
        "tgn:7029392"
    ],
    "tgn:id":7499790,
    "tgn:name":"Bu Shan",
    "tgn:placetype":[
        "aat:300387002"
    ]
},
  "bbox": [],
  "geometry": {"coordinates":[121.330492,23.455162],"type":"Point"}
}