{
  "id": 2591746,
  "type": "Feature",
  "properties": {
    "tgn:hierarchy":[
        "tgn:2591746",
        "tgn:1002153",
        "tgn:1000001",
        "tgn:7012149",
        "tgn:7007710",
        "tgn:7029392"
    ],
    "tgn:id":2591746,
    "tgn:name":"Pond Five",
    "tgn:placetype":[
        "aat:300006191"
    ]
},
  "bbox": [],
  "geometry": {"coordinates":[-79.4167,40.9167],"type":"Point"}
}