{
  "id": 2202075,
  "type": "Feature",
  "properties": {
    "tgn:hierarchy":[
        "tgn:2202075",
        "tgn:1000001",
        "tgn:7012149",
        "tgn:2001551",
        "tgn:7007709",
        "tgn:7029392"
    ],
    "tgn:id":2202075,
    "tgn:name":"Buck Knob",
    "tgn:placetype":[
        "aat:300008798"
    ]
},
  "bbox": [],
  "geometry": {"coordinates":[-81.75,36.1333],"type":"Point"}
}