{
  "id": 2644818,
  "type": "Feature",
  "properties": {
    "tgn:hierarchy":[
        "tgn:2644818",
        "tgn:1000001",
        "tgn:7012149",
        "tgn:2000550",
        "tgn:7007252",
        "tgn:7029392"
    ],
    "tgn:id":2644818,
    "tgn:name":"Sassafras",
    "tgn:placetype":[
        "aat:300008347"
    ]
},
  "bbox": [],
  "geometry": {"coordinates":[-86.6833,38.1833],"type":"Point"}
}