{
  "id": 7585436,
  "type": "Feature",
  "properties": {
    "tgn:hierarchy":[
        "tgn:7585436",
        "tgn:1000004",
        "tgn:7000198",
        "tgn:7016722",
        "tgn:7029392"
    ],
    "tgn:id":7585436,
    "tgn:name:en":"Kharkhari Minor",
    "tgn:placetype":[
        "aat:300006075"
    ]
},
  "bbox": [],
  "geometry": {"coordinates":[78.441793,24.842155],"type":"Point"}
}