{
  "id": 7444718,
  "type": "Feature",
  "properties": {
    "tgn:hierarchy":[
        "tgn:7444718",
        "tgn:7002445",
        "tgn:1000003",
        "tgn:7012032",
        "tgn:7008591",
        "tgn:7029392"
    ],
    "tgn:id":7444718,
    "tgn:name:en":"Blue Anchor Bay",
    "tgn:placetype":[
        "aat:300132317"
    ]
},
  "bbox": [],
  "geometry": {"coordinates":[-3.400833,51.191111],"type":"Point"}
}