<<<<<<< HEAD
{
  "id": 2254202,
  "type": "Feature",
  "properties": {
    "tgn:hierarchy":[
        "tgn:2254202",
        "tgn:1000001",
        "tgn:2000925",
        "tgn:7012149",
        "tgn:7007515",
        "tgn:7029392"
    ],
    "tgn:id":2254202,
    "tgn:name":"Coombs Ledge",
    "tgn:placetype":[
        "aat:300132348"
    ]
},
  "bbox": [],
  "geometry": {"coordinates":[-69.4167,43.95],"type":"Point"}
}
=======
{"geometry":{"type":"Point","coordinates":[-69.416700,43.950000]},"type":"Feature","properties":{"hierarchy":["tgn:2254202","tgn:1000001","tgn:2000925","tgn:7012149","tgn:7007515","tgn:7029392"],"placetype":["aat:300132348"],"id":2254202,"name:xx":"Coombs Ledge"}}
>>>>>>> 03f74aca74312dbeaf24d7e61306dd6a786dc3d0
