{
  "id": 7163817,
  "type": "Feature",
  "properties": {
    "tgn:hierarchy":[
        "tgn:7163817",
        "tgn:1000003",
        "tgn:7003677",
        "tgn:7000084",
        "tgn:7029392"
    ],
    "tgn:id":7163817,
    "tgn:name":"Kalth\u00f6ferholz",
    "tgn:placetype":[
        "aat:300008347"
    ]
},
  "bbox": [],
  "geometry": {"coordinates":[7.35,51.333333],"type":"Point"}
}