{
  "id": 7537083,
  "type": "Feature",
  "properties": {
    "tgn:hierarchy":[
        "tgn:7537083",
        "tgn:7001242",
        "tgn:7016833",
        "tgn:1001087",
        "tgn:7029392"
    ],
    "tgn:id":7537083,
    "tgn:name":"Q\u016bra\u015f",
    "tgn:placetype":[
        "aat:300008347"
    ]
},
  "bbox": [],
  "geometry": {"coordinates":[31.064846,30.277122],"type":"Point"}
}