{
  "id": 1139795,
  "type": "Feature",
  "properties": {
    "tgn:hierarchy":[
        "tgn:1139795",
        "tgn:1000004",
        "tgn:7002086",
        "tgn:1000111",
        "tgn:7029392"
    ],
    "tgn:id":1139795,
    "tgn:name":"Xiaguan",
    "tgn:placetype":[
        "aat:300008347"
    ]
},
  "bbox": [],
  "geometry": {"coordinates":[114.15,39.1167],"type":"Point"}
}