{
  "id": 7404276,
  "type": "Feature",
  "properties": {
    "tgn:hierarchy":[
        "tgn:7404276",
        "tgn:7005578",
        "tgn:1000001",
        "tgn:7005560",
        "tgn:7029392"
    ],
    "tgn:id":7404276,
    "tgn:name":"La Ortiga",
    "tgn:placetype":[
        "aat:300008347"
    ]
},
  "bbox": [],
  "geometry": {"coordinates":[-91.033333,18.758333],"type":"Point"}
}