{
  "id": 7061762,
  "type": "Feature",
  "properties": {
    "tgn:hierarchy":[
        "tgn:7061762",
        "tgn:1000003",
        "tgn:7003682",
        "tgn:7000084",
        "tgn:7029392"
    ],
    "tgn:id":7061762,
    "tgn:name":"Auf dem Horn",
    "tgn:placetype":[
        "aat:300008777"
    ]
},
  "bbox": [],
  "geometry": {"coordinates":[7.233333,50.616667],"type":"Point"}
}