{
  "id": 2738244,
  "type": "Feature",
  "properties": {
    "tgn:hierarchy":[
        "tgn:2738244",
        "tgn:1000001",
        "tgn:7012149",
        "tgn:1002251",
        "tgn:7007826",
        "tgn:7029392"
    ],
    "tgn:id":2738244,
    "tgn:name":"Umbrella Point",
    "tgn:placetype":[
        "aat:300008850"
    ]
},
  "bbox": [],
  "geometry": {"coordinates":[-94.8667,29.6667],"type":"Point"}
}