{
  "id": 7484511,
  "type": "Feature",
  "properties": {
    "tgn:hierarchy":[
        "tgn:7484511",
        "tgn:7001004",
        "tgn:1000004",
        "tgn:1000141",
        "tgn:7029392"
    ],
    "tgn:id":7484511,
    "tgn:name":"Youkuangxiang",
    "tgn:placetype":[
        "aat:300008347"
    ]
},
  "bbox": [],
  "geometry": {"coordinates":[120.611389,23.089444],"type":"Point"}
}