{
  "id": 7304487,
  "type": "Feature",
  "properties": {
    "tgn:hierarchy":[
        "tgn:7304487",
        "tgn:7002826",
        "tgn:7001158",
        "tgn:1000003",
        "tgn:1000095",
        "tgn:7029392"
    ],
    "tgn:id":7304487,
    "tgn:name":"Liegos",
    "tgn:placetype":[
        "aat:300008347"
    ]
},
  "bbox": [],
  "geometry": {"coordinates":[-5.066667,43.016667],"type":"Point"}
}