{
  "id": 7375422,
  "type": "Feature",
  "properties": {
    "tgn:hierarchy":[
        "tgn:7375422",
        "tgn:7005586",
        "tgn:1000001",
        "tgn:7005560",
        "tgn:7029392"
    ],
    "tgn:id":7375422,
    "tgn:name":"La Pur\u00edsima",
    "tgn:placetype":[
        "aat:300008347"
    ]
},
  "bbox": [],
  "geometry": {"coordinates":[-103.35,19.466667],"type":"Point"}
}