{
  "id": 2197896,
  "type": "Feature",
  "properties": {
    "tgn:hierarchy":[
        "tgn:2197896",
        "tgn:1000001",
        "tgn:7012149",
        "tgn:2001907",
        "tgn:7007825",
        "tgn:7029392"
    ],
    "tgn:id":2197896,
    "tgn:name":"Brown Ridge",
    "tgn:placetype":[
        "aat:300266640"
    ]
},
  "bbox": [],
  "geometry": {"coordinates":[-85.6333,36.1833],"type":"Point"}
}