{
  "id": 2088457,
  "type": "Feature",
  "properties": {
    "tgn:hierarchy":[
        "tgn:2088457",
        "tgn:1000001",
        "tgn:1002217",
        "tgn:7012149",
        "tgn:7007710",
        "tgn:7029392"
    ],
    "tgn:id":2088457,
    "tgn:name":"Fisher Heights",
    "tgn:placetype":[
        "aat:300008347"
    ]
},
  "bbox": [],
  "geometry": {"coordinates":[-79.95,40.9167],"type":"Point"}
}