{
  "id": 7196570,
  "type": "Feature",
  "properties": {
    "tgn:hierarchy":[
        "tgn:7196570",
        "tgn:1000003",
        "tgn:7003682",
        "tgn:7000084",
        "tgn:7029392"
    ],
    "tgn:id":7196570,
    "tgn:name":"Detzem",
    "tgn:placetype":[
        "aat:300008347"
    ]
},
  "bbox": [],
  "geometry": {"coordinates":[6.85,49.816667],"type":"Point"}
}