{
  "id": 1115869,
  "type": "Feature",
  "properties": {
    "tgn:hierarchy":[
        "tgn:1115869",
        "tgn:1000001",
        "tgn:7012149",
        "tgn:7013855",
        "tgn:7007251",
        "tgn:7029392"
    ],
    "tgn:id":1115869,
    "tgn:name":"Charles, Lake",
    "tgn:placetype":[
        "aat:300008680"
    ]
},
  "bbox": [],
  "geometry": {"coordinates":[-87.95,42.25],"type":"Point"}
}