{
  "id": 7427935,
  "type": "Feature",
  "properties": {
    "tgn:hierarchy":[
        "tgn:7427935",
        "tgn:1000001",
        "tgn:7005594",
        "tgn:7005560",
        "tgn:7029392"
    ],
    "tgn:id":7427935,
    "tgn:name":"Mar\u00eda de San Jos\u00e9",
    "tgn:placetype":[
        "aat:300008347"
    ]
},
  "bbox": [],
  "geometry": {"coordinates":[-100.716667,23.75],"type":"Point"}
}