{
  "id": 7226523,
  "type": "Feature",
  "properties": {
    "tgn:hierarchy":[
        "tgn:7226523",
        "tgn:7011167",
        "tgn:7001338",
        "tgn:1000003",
        "tgn:1000074",
        "tgn:7029392"
    ],
    "tgn:id":7226523,
    "tgn:name":"Skr\u00f3fa, \u00d3rmos",
    "tgn:placetype":[
        "aat:300132316"
    ]
},
  "bbox": [],
  "geometry": {"coordinates":[21.133333,38.316667],"type":"Point"}
}