{
  "id": 7519551,
  "type": "Feature",
  "properties": {
    "tgn:hierarchy":[
        "tgn:7519551",
        "tgn:7000508",
        "tgn:1008380",
        "tgn:1000226",
        "tgn:1000006",
        "tgn:7029392"
    ],
    "tgn:id":7519551,
    "tgn:name:en":"Ahuapunga",
    "tgn:placetype":[
        "aat:300008777"
    ]
},
  "bbox": [],
  "geometry": {"coordinates":[174.766667,-37.55],"type":"Point"}
}