<<<<<<< HEAD
{
  "id": 2769948,
  "type": "Feature",
  "properties": {
    "tgn:hierarchy":[
        "tgn:2769948",
        "tgn:1000001",
        "tgn:7012149",
        "tgn:2001916",
        "tgn:7007825",
        "tgn:7029392"
    ],
    "tgn:id":2769948,
    "tgn:name":"Wilburn Creek",
    "tgn:placetype":[
        "aat:300008706"
    ]
},
  "bbox": [],
  "geometry": {"coordinates":[-86.0,36.35],"type":"Point"}
}
=======
{"geometry":{"type":"Point","coordinates":[-86.000000,36.350000]},"type":"Feature","properties":{"hierarchy":["tgn:2769948","tgn:1000001","tgn:7012149","tgn:2001916","tgn:7007825","tgn:7029392"],"placetype":["aat:300008706"],"id":2769948,"name:xx":"Wilburn Creek"}}
>>>>>>> 03f74aca74312dbeaf24d7e61306dd6a786dc3d0
