{
  "id": 7509750,
  "type": "Feature",
  "properties": {
    "tgn:hierarchy":[
        "tgn:7509750",
        "tgn:1009227",
        "tgn:1000226",
        "tgn:7016729",
        "tgn:1000006",
        "tgn:7029392"
    ],
    "tgn:id":7509750,
    "tgn:name:en":"Stronvar",
    "tgn:placetype":[
        "aat:300000206"
    ]
},
  "bbox": [],
  "geometry": {"coordinates":[173.416667,-41.733333],"type":"Point"}
}