{
  "id": 2078445,
  "type": "Feature",
  "properties": {
    "tgn:hierarchy":[
        "tgn:2078445",
        "tgn:1000001",
        "tgn:7012149",
        "tgn:1002482",
        "tgn:7007706",
        "tgn:7029392"
    ],
    "tgn:id":2078445,
    "tgn:name":"Berlin",
    "tgn:placetype":[
        "aat:300008347"
    ]
},
  "bbox": [],
  "geometry": {"coordinates":[-81.7833,40.55],"type":"Point"}
}