{
  "id": 2221066,
  "type": "Feature",
  "properties": {
    "tgn:hierarchy":[
        "tgn:2221066",
        "tgn:1000001",
        "tgn:7012149",
        "tgn:2001253",
        "tgn:7007523",
        "tgn:7029392"
    ],
    "tgn:id":2221066,
    "tgn:name":"Carbon Center",
    "tgn:placetype":[
        "aat:300008347"
    ]
},
  "bbox": [],
  "geometry": {"coordinates":[-94.3167,38.0333],"type":"Point"}
}