{
  "id": 7338691,
  "type": "Feature",
  "properties": {
    "tgn:hierarchy":[
        "tgn:7338691",
        "tgn:7008911",
        "tgn:1000003",
        "tgn:7002763",
        "tgn:1000095",
        "tgn:7029392"
    ],
    "tgn:id":7338691,
    "tgn:name":"Corollos",
    "tgn:placetype":[
        "aat:300008347"
    ]
},
  "bbox": [],
  "geometry": {"coordinates":[-6.183333,43.533333],"type":"Point"}
}