{
  "id": 2098989,
  "type": "Feature",
  "properties": {
    "tgn:hierarchy":[
        "tgn:2098989",
        "tgn:1000001",
        "tgn:7012149",
        "tgn:2001916",
        "tgn:7007825",
        "tgn:7029392"
    ],
    "tgn:id":2098989,
    "tgn:name":"Enigma",
    "tgn:placetype":[
        "aat:300008347",
        "aat:300387210"
    ]
},
  "bbox": [],
  "geometry": {"coordinates":[-85.7833,36.2167],"type":"Point"}
}