{
  "id": 2627232,
  "type": "Feature",
  "properties": {
    "tgn:hierarchy":[
        "tgn:2627232",
        "tgn:1000001",
        "tgn:7012149",
        "tgn:7007157",
        "tgn:2000185",
        "tgn:7029392"
    ],
    "tgn:id":2627232,
    "tgn:name":"Rodeo Valley",
    "tgn:placetype":[
        "aat:300386845"
    ]
},
  "bbox": [],
  "geometry": {"coordinates":[-123.3167,39.6333],"type":"Point"}
}