{
  "id": 2270879,
  "type": "Feature",
  "properties": {
    "tgn:hierarchy":[
        "tgn:2270879",
        "tgn:1000001",
        "tgn:7012149",
        "tgn:2001980",
        "tgn:7007826",
        "tgn:7029392"
    ],
    "tgn:id":2270879,
    "tgn:name":"Cub Lake",
    "tgn:placetype":[
        "aat:300008680"
    ]
},
  "bbox": [],
  "geometry": {"coordinates":[-100.1833,29.9667],"type":"Point"}
}