{
  "id": 2467023,
  "type": "Feature",
  "properties": {
    "tgn:hierarchy":[
        "tgn:2467023",
        "tgn:7014651",
        "tgn:1000001",
        "tgn:7012149",
        "tgn:7007516",
        "tgn:7029392"
    ],
    "tgn:id":2467023,
    "tgn:name":"Long Cove",
    "tgn:placetype":[
        "aat:300132316"
    ]
},
  "bbox": [],
  "geometry": {"coordinates":[-76.4667,39.0833],"type":"Point"}
}