{
  "id": 7567742,
  "type": "Feature",
  "properties": {
    "tgn:hierarchy":[
        "tgn:7567742",
        "tgn:1001828",
        "tgn:1000004",
        "tgn:7000198",
        "tgn:7029392"
    ],
    "tgn:id":7567742,
    "tgn:name:en":"R\u0101mayapalli",
    "tgn:placetype":[
        "aat:300008347"
    ]
},
  "bbox": [],
  "geometry": {"coordinates":[78.474444,17.7825],"type":"Point"}
}