{
  "id": 7293196,
  "type": "Feature",
  "properties": {
    "tgn:hierarchy":[
        "tgn:7293196",
        "tgn:1001768",
        "tgn:1000049",
        "tgn:1000002",
        "tgn:7029392"
    ],
    "tgn:id":7293196,
    "tgn:name":"Espol\u00f3n, Punta",
    "tgn:placetype":[
        "aat:300386846"
    ]
},
  "bbox": [],
  "geometry": {"coordinates":[-109.433333,-27.116667],"type":"Point"}
}