{
  "id": 2728678,
  "type": "Feature",
  "properties": {
    "tgn:hierarchy":[
        "tgn:2728678",
        "tgn:1000001",
        "tgn:7006451",
        "tgn:7012149",
        "tgn:2000102",
        "tgn:7029392"
    ],
    "tgn:id":2728678,
    "tgn:name":"Trenton Mine",
    "tgn:placetype":[
        "aat:300000390"
    ]
},
  "bbox": [],
  "geometry": {"coordinates":[-110.85,31.5833],"type":"Point"}
}