{
  "id": 2314791,
  "type": "Feature",
  "properties": {
    "tgn:hierarchy":[
        "tgn:2314791",
        "tgn:1000001",
        "tgn:7012149",
        "tgn:2001206",
        "tgn:7007523",
        "tgn:7029392"
    ],
    "tgn:id":2314791,
    "tgn:name":"Elkhorn Branch",
    "tgn:placetype":[
        "aat:300008699"
    ]
},
  "bbox": [],
  "geometry": {"coordinates":[-91.9333,36.5333],"type":"Point"}
}