{
  "id": 7578678,
  "type": "Feature",
  "properties": {
    "tgn:hierarchy":[
        "tgn:7578678",
        "tgn:1000004",
        "tgn:7000198",
        "tgn:1001895",
        "tgn:7029392"
    ],
    "tgn:id":7578678,
    "tgn:name:en":"Sir\u016br",
    "tgn:placetype":[
        "aat:300008347"
    ]
},
  "bbox": [],
  "geometry": {"coordinates":[75.433333,19.066667],"type":"Point"}
}