{
  "id": 7332745,
  "type": "Feature",
  "properties": {
    "tgn:hierarchy":[
        "tgn:7332745",
        "tgn:7002758",
        "tgn:7002841",
        "tgn:1000003",
        "tgn:1000095",
        "tgn:7029392"
    ],
    "tgn:id":7332745,
    "tgn:name":"La Alcornocosa",
    "tgn:placetype":[
        "aat:300008347"
    ]
},
  "bbox": [],
  "geometry": {"coordinates":[-6.283333,37.733333],"type":"Point"}
}