{
  "id": 2140082,
  "type": "Feature",
  "properties": {
    "tgn:hierarchy":[
        "tgn:2140082",
        "tgn:1000001",
        "tgn:2000299",
        "tgn:7012149",
        "tgn:7007248",
        "tgn:7029392"
    ],
    "tgn:id":2140082,
    "tgn:name":"Aubrey",
    "tgn:placetype":[
        "aat:300008347"
    ]
},
  "bbox": [],
  "geometry": {"coordinates":[-84.75,34.25],"type":"Point"}
}