{
  "id": 2607990,
  "type": "Feature",
  "properties": {
    "tgn:hierarchy":[
        "tgn:2607990",
        "tgn:1000001",
        "tgn:7012149",
        "tgn:2002042",
        "tgn:7007826",
        "tgn:7029392"
    ],
    "tgn:id":2607990,
    "tgn:name":"Ratler",
    "tgn:placetype":[
        "aat:300008347"
    ]
},
  "bbox": [],
  "geometry": {"coordinates":[-98.7667,31.3667],"type":"Point"}
}