{
  "id": 2758751,
  "type": "Feature",
  "properties": {
    "tgn:hierarchy":[
        "tgn:2758751",
        "tgn:1000001",
        "tgn:2002109",
        "tgn:7012149",
        "tgn:7007827",
        "tgn:7029392"
    ],
    "tgn:id":2758751,
    "tgn:name":"West Ditch",
    "tgn:placetype":[
        "aat:300006075"
    ]
},
  "bbox": [],
  "geometry": {"coordinates":[-112.4333,37.85],"type":"Point"}
}