{
  "id": 2099308,
  "type": "Feature",
  "properties": {
    "tgn:hierarchy":[
        "tgn:2099308",
        "tgn:1000001",
        "tgn:7012149",
        "tgn:2001859",
        "tgn:7007825",
        "tgn:7029392"
    ],
    "tgn:id":2099308,
    "tgn:name":"Good Hope",
    "tgn:placetype":[
        "aat:300008347",
        "aat:300387210"
    ]
},
  "bbox": [],
  "geometry": {"coordinates":[-89.2833,36.05],"type":"Point"}
}