{
  "id": 7466479,
  "type": "Feature",
  "properties": {
    "tgn:hierarchy":[
        "tgn:7466479",
        "tgn:7002443",
        "tgn:5000552",
        "tgn:1000003",
        "tgn:7008591",
        "tgn:7029392"
    ],
    "tgn:id":7466479,
    "tgn:name:en":"Brondini",
    "tgn:placetype":[
        "aat:300008347"
    ]
},
  "bbox": [],
  "geometry": {"coordinates":[-4.183333,51.733333],"type":"Point"}
}