{
  "id": 7528848,
  "type": "Feature",
  "properties": {
    "tgn:hierarchy":[
        "tgn:7528848",
        "tgn:7001242",
        "tgn:7016833",
        "tgn:1001080",
        "tgn:7029392"
    ],
    "tgn:id":7528848,
    "tgn:name:en":"Umm Mitm\u0101m",
    "tgn:placetype":[
        "aat:300008750"
    ]
},
  "bbox": [],
  "geometry": {"coordinates":[32.590979,30.695626],"type":"Point"}
}