<<<<<<< HEAD
{
  "id": 7051014,
  "type": "Feature",
  "properties": {
    "tgn:hierarchy":[
        "tgn:7051014",
        "tgn:7003139",
        "tgn:1000003",
        "tgn:7003080",
        "tgn:1000080",
        "tgn:7029392"
    ],
    "tgn:id":7051014,
    "tgn:name":"Piansano",
    "tgn:placetype":[
        "aat:300008347"
    ]
},
  "bbox": [],
  "geometry": {"coordinates":[11.833333,42.516667],"type":"Point"}
}
=======
{"geometry":{"type":"Point","coordinates":[11.833333,42.516667]},"type":"Feature","properties":{"hierarchy":["tgn:7051014","tgn:7003139","tgn:1000003","tgn:7003080","tgn:1000080","tgn:7029392"],"placetype":["aat:300008347"],"id":7051014,"name:xx":"Piansano"}}
>>>>>>> 03f74aca74312dbeaf24d7e61306dd6a786dc3d0
