{
  "id": 7560007,
  "type": "Feature",
  "properties": {
    "tgn:hierarchy":[
        "tgn:7560007",
        "tgn:1000004",
        "tgn:7000198",
        "tgn:7016722",
        "tgn:7029392"
    ],
    "tgn:id":7560007,
    "tgn:name:en":"Kaua T\u0101nda",
    "tgn:placetype":[
        "aat:300008347"
    ]
},
  "bbox": [],
  "geometry": {"coordinates":[79.248783,27.207116],"type":"Point"}
}