<<<<<<< HEAD
{
  "id": 7473326,
  "type": "Feature",
  "properties": {
    "tgn:hierarchy":[
        "tgn:7473326",
        "tgn:1000004",
        "tgn:7489179",
        "tgn:1000141",
        "tgn:7029392"
    ],
    "tgn:id":7473326,
    "tgn:name":"Tongpanku",
    "tgn:placetype":[
        "aat:300008347"
    ]
},
  "bbox": [],
  "geometry": {"coordinates":[121.935556,24.975],"type":"Point"}
}
=======
{"geometry":{"type":"Point","coordinates":[121.935556,24.975000]},"type":"Feature","properties":{"hierarchy":["tgn:7473326","tgn:1000004","tgn:7489179","tgn:1000141","tgn:7029392"],"placetype":["aat:300008347"],"id":7473326,"name:xx":"Tongpanku"}}
>>>>>>> 03f74aca74312dbeaf24d7e61306dd6a786dc3d0
