{
  "id": 7312525,
  "type": "Feature",
  "properties": {
    "tgn:hierarchy":[
        "tgn:7312525",
        "tgn:1001702",
        "tgn:1000049",
        "tgn:1000002",
        "tgn:7029392"
    ],
    "tgn:id":7312525,
    "tgn:name":"Langlois, Puerto",
    "tgn:placetype":[
        "aat:300132317"
    ]
},
  "bbox": [],
  "geometry": {"coordinates":[-71.416667,-54.65],"type":"Point"}
}