<<<<<<< HEAD
{
  "id": 7177100,
  "type": "Feature",
  "properties": {
    "tgn:hierarchy":[
        "tgn:7177100",
        "tgn:7003669",
        "tgn:1000003",
        "tgn:7000084",
        "tgn:7029392"
    ],
    "tgn:id":7177100,
    "tgn:name":"Hard",
    "tgn:placetype":[
        "aat:300008863"
    ]
},
  "bbox": [],
  "geometry": {"coordinates":[11.133333,49.166667],"type":"Point"}
}
=======
{"geometry":{"type":"Point","coordinates":[11.133333,49.166667]},"type":"Feature","properties":{"hierarchy":["tgn:7177100","tgn:7003669","tgn:1000003","tgn:7000084","tgn:7029392"],"placetype":["aat:300008863"],"id":7177100,"name:xx":"Hard"}}
>>>>>>> 03f74aca74312dbeaf24d7e61306dd6a786dc3d0
