{
  "id": 7504272,
  "type": "Feature",
  "properties": {
    "tgn:hierarchy":[
        "tgn:7504272",
        "tgn:1009227",
        "tgn:1000226",
        "tgn:7018437",
        "tgn:1000006",
        "tgn:7029392"
    ],
    "tgn:id":7504272,
    "tgn:name:en":"Waiwera Creek",
    "tgn:placetype":[
        "aat:300008699"
    ]
},
  "bbox": [],
  "geometry": {"coordinates":[169.45,-44.866667],"type":"Point"}
}