{
  "id": 2433460,
  "type": "Feature",
  "properties": {
    "tgn:hierarchy":[
        "tgn:2433460",
        "tgn:1000001",
        "tgn:7016102",
        "tgn:7012149",
        "tgn:7007516",
        "tgn:7029392"
    ],
    "tgn:id":2433460,
    "tgn:name":"Kellogg Branch",
    "tgn:placetype":[
        "aat:300008699"
    ]
},
  "bbox": [],
  "geometry": {"coordinates":[-76.4333,39.6167],"type":"Point"}
}