{
  "id": 2747761,
  "type": "Feature",
  "properties": {
    "tgn:hierarchy":[
        "tgn:2747761",
        "tgn:7002659",
        "tgn:1000001",
        "tgn:7012149",
        "tgn:2000035",
        "tgn:7029392"
    ],
    "tgn:id":2747761,
    "tgn:name":"Waites Lake",
    "tgn:placetype":[
        "aat:300006191"
    ]
},
  "bbox": [],
  "geometry": {"coordinates":[-85.9333,34.6333],"type":"Point"}
}