{
  "id": 2471064,
  "type": "Feature",
  "properties": {
    "tgn:hierarchy":[
        "tgn:2471064",
        "tgn:1000001",
        "tgn:7012149",
        "tgn:1002897",
        "tgn:7007920",
        "tgn:7029392"
    ],
    "tgn:id":2471064,
    "tgn:name":"Lost Creek",
    "tgn:placetype":[
        "aat:300008706"
    ]
},
  "bbox": [],
  "geometry": {"coordinates":[-121.7167,45.7833],"type":"Point"}
}