{
  "id": 7162377,
  "type": "Feature",
  "properties": {
    "tgn:hierarchy":[
        "tgn:7162377",
        "tgn:7003669",
        "tgn:1000003",
        "tgn:7000084",
        "tgn:7029392"
    ],
    "tgn:id":7162377,
    "tgn:name":"Innwerk Kanal",
    "tgn:placetype":[
        "aat:300006075"
    ]
},
  "bbox": [],
  "geometry": {"coordinates":[12.583333,48.25],"type":"Point"}
}