{
  "id": 1006059,
  "type": "Feature",
  "properties": {
    "tgn:hierarchy":[
        "tgn:1006059",
        "tgn:1010365",
        "tgn:1000216",
        "tgn:1000006",
        "tgn:7029392"
    ],
    "tgn:id":1006059,
    "tgn:name":"Manuhangi",
    "tgn:placetype":[
        "aat:300008793"
    ]
},
  "bbox": [],
  "geometry": {"coordinates":[-141.2833,-19.15],"type":"Point"}
}