{
  "id": 7223196,
  "type": "Feature",
  "properties": {
    "tgn:hierarchy":[
        "tgn:7223196",
        "tgn:7002707",
        "tgn:7002705",
        "tgn:1000003",
        "tgn:1000074",
        "tgn:7029392"
    ],
    "tgn:id":7223196,
    "tgn:name":"Merope, Oros",
    "tgn:placetype":[
        "aat:300008795"
    ]
},
  "bbox": [],
  "geometry": {"coordinates":[20.483333,40.066667],"type":"Point"}
}