{
  "id": 1109088,
  "type": "Feature",
  "properties": {
    "tgn:hierarchy":[
        "tgn:1109088",
        "tgn:1001488",
        "tgn:1000001",
        "tgn:7004624",
        "tgn:7029392"
    ],
    "tgn:id":1109088,
    "tgn:name":"Guaniguanico, Cordillera de",
    "tgn:placetype":[
        "aat:300386831"
    ]
},
  "bbox": [],
  "geometry": {"coordinates":[-83.8333,22.5833],"type":"Point"}
}