{
  "id": 7222782,
  "type": "Feature",
  "properties": {
    "tgn:hierarchy":[
        "tgn:7222782",
        "tgn:4003773",
        "tgn:7001395",
        "tgn:1000003",
        "tgn:1000074",
        "tgn:7029392"
    ],
    "tgn:id":7222782,
    "tgn:name":"Palai\u00f3khanon",
    "tgn:placetype":[
        "aat:300008347"
    ]
},
  "bbox": [],
  "geometry": {"coordinates":[21.95,38.416667],"type":"Point"}
}