{
  "id": 2514261,
  "type": "Feature",
  "properties": {
    "tgn:hierarchy":[
        "tgn:2514261",
        "tgn:7006450",
        "tgn:1000001",
        "tgn:7012149",
        "tgn:2000086",
        "tgn:7029392"
    ],
    "tgn:id":2514261,
    "tgn:name":"Miller Creek",
    "tgn:placetype":[
        "aat:300008706"
    ]
},
  "bbox": [],
  "geometry": {"coordinates":[-142.35,60.15],"type":"Point"}
}