{
  "id": 7564330,
  "type": "Feature",
  "properties": {
    "tgn:hierarchy":[
        "tgn:7564330",
        "tgn:1000004",
        "tgn:7000198",
        "tgn:7016788",
        "tgn:7029392"
    ],
    "tgn:id":7564330,
    "tgn:name:en":"Bandua",
    "tgn:placetype":[
        "aat:300008347"
    ]
},
  "bbox": [],
  "geometry": {"coordinates":[74.440165,28.068965],"type":"Point"}
}