{
  "id": 2518076,
  "type": "Feature",
  "properties": {
    "tgn:hierarchy":[
        "tgn:2518076",
        "tgn:1000001",
        "tgn:7012149",
        "tgn:2000967",
        "tgn:7007520",
        "tgn:7029392"
    ],
    "tgn:id":2518076,
    "tgn:name":"Mission Creek",
    "tgn:placetype":[
        "aat:300008706"
    ]
},
  "bbox": [],
  "geometry": {"coordinates":[-84.8167,43.6167],"type":"Point"}
}