{
  "id": 2454257,
  "type": "Feature",
  "properties": {
    "tgn:hierarchy":[
        "tgn:2454257",
        "tgn:7002659",
        "tgn:1000001",
        "tgn:7012149",
        "tgn:7021514",
        "tgn:7029392"
    ],
    "tgn:id":2454257,
    "tgn:name":"Little Creek Cave",
    "tgn:placetype":[
        "aat:300008746"
    ]
},
  "bbox": [],
  "geometry": {"coordinates":[-85.9167,34.2667],"type":"Point"}
}