{
  "id": 1094133,
  "type": "Feature",
  "properties": {
    "tgn:hierarchy":[
        "tgn:1094133",
        "tgn:7001242",
        "tgn:1000201",
        "tgn:1001097",
        "tgn:7029392"
    ],
    "tgn:id":1094133,
    "tgn:name":"Karaba, El",
    "tgn:placetype":[
        "aat:300008347"
    ]
},
  "bbox": [],
  "geometry": {"coordinates":[33.6833,18.55],"type":"Point"}
}