{
  "id": 2549330,
  "type": "Feature",
  "properties": {
    "tgn:hierarchy":[
        "tgn:2549330",
        "tgn:1000001",
        "tgn:7012149",
        "tgn:2000220",
        "tgn:7007158",
        "tgn:7029392"
    ],
    "tgn:id":2549330,
    "tgn:name":"North Sand Hills",
    "tgn:placetype":[
        "aat:300386831"
    ]
},
  "bbox": [],
  "geometry": {"coordinates":[-106.1833,40.8667],"type":"Point"}
}