{
  "id": 2127877,
  "type": "Feature",
  "properties": {
    "tgn:hierarchy":[
        "tgn:2127877",
        "tgn:7006450",
        "tgn:1000001",
        "tgn:7012149",
        "tgn:2124005",
        "tgn:7029392"
    ],
    "tgn:id":2127877,
    "tgn:name":"Alapah Mountain",
    "tgn:placetype":[
        "aat:300008798"
    ]
},
  "bbox": [],
  "geometry": {"coordinates":[-150.8167,68.15],"type":"Point"}
}