{
  "id": 7295212,
  "type": "Feature",
  "properties": {
    "tgn:hierarchy":[
        "tgn:7295212",
        "tgn:7002760",
        "tgn:1000003",
        "tgn:1000095",
        "tgn:7029392"
    ],
    "tgn:id":7295212,
    "tgn:name":"Villegar",
    "tgn:placetype":[
        "aat:300008347"
    ]
},
  "bbox": [],
  "geometry": {"coordinates":[-3.95,43.216667],"type":"Point"}
}