{
  "id": 7105927,
  "type": "Feature",
  "properties": {
    "tgn:hierarchy":[
        "tgn:7105927",
        "tgn:1000003",
        "tgn:7003682",
        "tgn:7000084",
        "tgn:7029392"
    ],
    "tgn:id":7105927,
    "tgn:name":"Schletter-Berg",
    "tgn:placetype":[
        "aat:300266640"
    ]
},
  "bbox": [],
  "geometry": {"coordinates":[7.983333,49.183333],"type":"Point"}
}