<<<<<<< HEAD
{
  "id": 7359003,
  "type": "Feature",
  "properties": {
    "tgn:hierarchy":[
        "tgn:7359003",
        "tgn:1000001",
        "tgn:7005594",
        "tgn:7005560",
        "tgn:7029392"
    ],
    "tgn:id":7359003,
    "tgn:name":"Cruz",
    "tgn:placetype":[
        "aat:300008347"
    ]
},
  "bbox": [],
  "geometry": {"coordinates":[-100.9,22.35],"type":"Point"}
}
=======
{"geometry":{"type":"Point","coordinates":[-100.900000,22.350000]},"type":"Feature","properties":{"hierarchy":["tgn:7359003","tgn:1000001","tgn:7005594","tgn:7005560","tgn:7029392"],"placetype":["aat:300008347"],"id":7359003,"name:xx":"Cruz"}}
>>>>>>> 03f74aca74312dbeaf24d7e61306dd6a786dc3d0
