{
  "id": 7509660,
  "type": "Feature",
  "properties": {
    "tgn:hierarchy":[
        "tgn:7509660",
        "tgn:1008380",
        "tgn:7000507",
        "tgn:1000226",
        "tgn:1000006",
        "tgn:7029392"
    ],
    "tgn:id":7509660,
    "tgn:name:en":"Te Rotomanao",
    "tgn:placetype":[
        "aat:300008795"
    ]
},
  "bbox": [],
  "geometry": {"coordinates":[173.666667,-35.183333],"type":"Point"}
}