<<<<<<< HEAD
{
  "id": 7178929,
  "type": "Feature",
  "properties": {
    "tgn:hierarchy":[
        "tgn:7178929",
        "tgn:7003669",
        "tgn:1000003",
        "tgn:7000084",
        "tgn:7029392"
    ],
    "tgn:id":7178929,
    "tgn:name":"Haidforst",
    "tgn:placetype":[
        "aat:300008863"
    ]
},
  "bbox": [],
  "geometry": {"coordinates":[11.35,48.616667],"type":"Point"}
}
=======
{"geometry":{"type":"Point","coordinates":[11.350000,48.616667]},"type":"Feature","properties":{"hierarchy":["tgn:7178929","tgn:7003669","tgn:1000003","tgn:7000084","tgn:7029392"],"placetype":["aat:300008863"],"id":7178929,"name:xx":"Haidforst"}}
>>>>>>> 03f74aca74312dbeaf24d7e61306dd6a786dc3d0
