{
  "id": 7003634,
  "type": "Feature",
  "properties": {
    "tgn:hierarchy":[
        "tgn:7003634",
        "tgn:7015163",
        "tgn:1000003",
        "tgn:7003121",
        "tgn:1000080",
        "tgn:7029392"
    ],
    "tgn:id":7003634,
    "tgn:name":"Perfugas",
    "tgn:placetype":[
        "aat:300008347"
    ]
},
  "bbox": [],
  "geometry": {"coordinates":[8.883333,40.833333],"type":"Point"}
}