<<<<<<< HEAD
{
  "id": 7020643,
  "type": "Feature",
  "properties": {
    "tgn:hierarchy":[
        "tgn:7020643",
        "tgn:1000001",
        "tgn:7012149",
        "tgn:7029392"
    ],
    "tgn:id":7020643,
    "tgn:name":"Deep Canyon",
    "tgn:placetype":[
        "aat:300008761"
    ]
},
  "bbox": [],
  "geometry": {"coordinates":[-120.0,39.45],"type":"Point"}
}
=======
{"geometry":{"type":"Point","coordinates":[-120.000000,39.450000]},"type":"Feature","properties":{"hierarchy":["tgn:7020643","tgn:1000001","tgn:7012149","tgn:7029392"],"placetype":["aat:300008761"],"id":7020643,"name:xx":"Deep Canyon"}}
>>>>>>> 03f74aca74312dbeaf24d7e61306dd6a786dc3d0
