{
  "id": 2542367,
  "type": "Feature",
  "properties": {
    "tgn:hierarchy":[
        "tgn:2542367",
        "tgn:1000001",
        "tgn:7012149",
        "tgn:2002113",
        "tgn:7007827",
        "tgn:7029392"
    ],
    "tgn:id":2542367,
    "tgn:name":"No Mans Mesa",
    "tgn:placetype":[
        "aat:300008798"
    ]
},
  "bbox": [],
  "geometry": {"coordinates":[-111.9833,37.25],"type":"Point"}
}