{
  "id": 2417204,
  "type": "Feature",
  "properties": {
    "tgn:hierarchy":[
        "tgn:2417204",
        "tgn:1000001",
        "tgn:7012149",
        "tgn:1002837",
        "tgn:7007255",
        "tgn:7029392"
    ],
    "tgn:id":2417204,
    "tgn:name":"Jacks Branch",
    "tgn:placetype":[
        "aat:300008699"
    ]
},
  "bbox": [],
  "geometry": {"coordinates":[-83.4333,38.2167],"type":"Point"}
}