{
  "id": 4000934,
  "type": "Feature",
  "properties": {
    "tgn:hierarchy":[
        "tgn:4000934",
        "tgn:7003669",
        "tgn:1000003",
        "tgn:7000084",
        "tgn:7029392"
    ],
    "tgn:id":4000934,
    "tgn:name":"Au am Inn",
    "tgn:placetype":[
        "aat:300008347"
    ]
},
  "bbox": [],
  "geometry": {"coordinates":[12.333333,48.166667],"type":"Point"}
}