<<<<<<< HEAD
{
  "id": 7244102,
  "type": "Feature",
  "properties": {
    "tgn:hierarchy":[
        "tgn:7244102",
        "tgn:7003457",
        "tgn:1000003",
        "tgn:1000063",
        "tgn:7018236",
        "tgn:7029392"
    ],
    "tgn:id":7244102,
    "tgn:name":"Dijk van Kallo",
    "tgn:placetype":[
        "aat:300170882"
    ]
},
  "bbox": [],
  "geometry": {"coordinates":[4.233333,51.266667],"type":"Point"}
}
=======
{"geometry":{"type":"Point","coordinates":[4.233333,51.266667]},"type":"Feature","properties":{"hierarchy":["tgn:7244102","tgn:7003457","tgn:1000003","tgn:1000063","tgn:7018236","tgn:7029392"],"placetype":["aat:300170882"],"id":7244102,"name:xx":"Dijk van Kallo"}}
>>>>>>> 03f74aca74312dbeaf24d7e61306dd6a786dc3d0
