{
  "id": 7244102,
  "type": "Feature",
  "properties": {
    "tgn:hierarchy":[
        "tgn:7244102",
        "tgn:7003457",
        "tgn:1000003",
        "tgn:1000063",
        "tgn:7018236",
        "tgn:7029392"
    ],
    "tgn:id":7244102,
    "tgn:name":"Dijk van Kallo",
    "tgn:placetype":[
        "aat:300170882"
    ]
},
  "bbox": [],
  "geometry": {"coordinates":[4.233333,51.266667],"type":"Point"}
}