{
  "id": 7399370,
  "type": "Feature",
  "properties": {
    "tgn:hierarchy":[
        "tgn:7399370",
        "tgn:1000001",
        "tgn:7005593",
        "tgn:7005560",
        "tgn:7029392"
    ],
    "tgn:id":7399370,
    "tgn:name":"La Valla",
    "tgn:placetype":[
        "aat:300008347"
    ]
},
  "bbox": [],
  "geometry": {"coordinates":[-100.030556,20.498611],"type":"Point"}
}