<<<<<<< HEAD
{
  "id": 2151375,
  "type": "Feature",
  "properties": {
    "tgn:hierarchy":[
        "tgn:2151375",
        "tgn:7002659",
        "tgn:1000001",
        "tgn:2000016",
        "tgn:7012149",
        "tgn:7029392"
    ],
    "tgn:id":2151375,
    "tgn:name":"Bates Pond",
    "tgn:placetype":[
        "aat:300008680"
    ]
},
  "bbox": [],
  "geometry": {"coordinates":[-87.5667,34.7333],"type":"Point"}
}
=======
{"geometry":{"type":"Point","coordinates":[-87.566700,34.733300]},"type":"Feature","properties":{"hierarchy":["tgn:2151375","tgn:7002659","tgn:1000001","tgn:2000016","tgn:7012149","tgn:7029392"],"placetype":["aat:300008680"],"id":2151375,"name:xx":"Bates Pond"}}
>>>>>>> 03f74aca74312dbeaf24d7e61306dd6a786dc3d0
