{
  "id": 1043099,
  "type": "Feature",
  "properties": {
    "tgn:hierarchy":[
        "tgn:1043099",
        "tgn:1003450",
        "tgn:7007850",
        "tgn:1000003",
        "tgn:1000080",
        "tgn:7029392"
    ],
    "tgn:id":1043099,
    "tgn:name":"Acquappesa",
    "tgn:placetype":[
        "aat:300008347"
    ]
},
  "bbox": [],
  "geometry": {"coordinates":[15.95,39.483333],"type":"Point"}
}