<<<<<<< HEAD
{
  "id": 2403905,
  "type": "Feature",
  "properties": {
    "tgn:hierarchy":[
        "tgn:2403905",
        "tgn:1000001",
        "tgn:7012149",
        "tgn:2001274",
        "tgn:7007524",
        "tgn:7029392"
    ],
    "tgn:id":2403905,
    "tgn:name":"Howe Lake",
    "tgn:placetype":[
        "aat:300008680"
    ]
},
  "bbox": [],
  "geometry": {"coordinates":[-113.9833,48.6],"type":"Point"}
}
=======
{"geometry":{"type":"Point","coordinates":[-113.983300,48.600000]},"type":"Feature","properties":{"hierarchy":["tgn:2403905","tgn:1000001","tgn:7012149","tgn:2001274","tgn:7007524","tgn:7029392"],"placetype":["aat:300008680"],"id":2403905,"name:xx":"Howe Lake"}}
>>>>>>> 03f74aca74312dbeaf24d7e61306dd6a786dc3d0
