{
  "id": 2443917,
  "type": "Feature",
  "properties": {
    "tgn:hierarchy":[
        "tgn:2443917",
        "tgn:1000001",
        "tgn:7012149",
        "tgn:2001454",
        "tgn:7007566",
        "tgn:7029392"
    ],
    "tgn:id":2443917,
    "tgn:name":"La Puebla Ditch",
    "tgn:placetype":[
        "aat:300006075"
    ]
},
  "bbox": [],
  "geometry": {"coordinates":[-105.9833,35.9833],"type":"Point"}
}