{
  "id": 7326098,
  "type": "Feature",
  "properties": {
    "tgn:hierarchy":[
        "tgn:7326098",
        "tgn:7002824",
        "tgn:1000003",
        "tgn:7002786",
        "tgn:1000095",
        "tgn:7029392"
    ],
    "tgn:id":7326098,
    "tgn:name":"Portigo de Villasen\u00edn, R\u00edo de",
    "tgn:placetype":[
        "aat:300008699"
    ]
},
  "bbox": [],
  "geometry": {"coordinates":[-8.466667,43.133333],"type":"Point"}
}