{
  "id": 7568123,
  "type": "Feature",
  "properties": {
    "tgn:hierarchy":[
        "tgn:7568123",
        "tgn:1000004",
        "tgn:7000198",
        "tgn:1001996",
        "tgn:7029392"
    ],
    "tgn:id":7568123,
    "tgn:name:en":"Lalt\u0101na",
    "tgn:placetype":[
        "aat:300008347"
    ]
},
  "bbox": [],
  "geometry": {"coordinates":[77.000833,31.179722],"type":"Point"}
}