{
  "id": 7555975,
  "type": "Feature",
  "properties": {
    "tgn:hierarchy":[
        "tgn:7555975",
        "tgn:1000004",
        "tgn:7000198",
        "tgn:1001895",
        "tgn:7029392"
    ],
    "tgn:id":7555975,
    "tgn:name:en":"Peth",
    "tgn:placetype":[
        "aat:300008347"
    ]
},
  "bbox": [],
  "geometry": {"coordinates":[73.916667,18.916667],"type":"Point"}
}