{
  "id": 2735670,
  "type": "Feature",
  "properties": {
    "tgn:hierarchy":[
        "tgn:2735670",
        "tgn:1000001",
        "tgn:1002249",
        "tgn:7012149",
        "tgn:7007710",
        "tgn:7029392"
    ],
    "tgn:id":2735670,
    "tgn:name":"Twin Hollows",
    "tgn:placetype":[
        "aat:300008347"
    ]
},
  "bbox": [],
  "geometry": {"coordinates":[-77.9667,41.1667],"type":"Point"}
}