{
  "id": 7289527,
  "type": "Feature",
  "properties": {
    "tgn:hierarchy":[
        "tgn:7289527",
        "tgn:7016598",
        "tgn:1000049",
        "tgn:1000002",
        "tgn:7029392"
    ],
    "tgn:id":7289527,
    "tgn:name":"Infieles, Quebrada",
    "tgn:placetype":[
        "aat:300266554",
        "aat:300008699"
    ]
},
  "bbox": [],
  "geometry": {"coordinates":[-70.533333,-25.466667],"type":"Point"}
}