{
  "id": 2712789,
  "type": "Feature",
  "properties": {
    "tgn:hierarchy":[
        "tgn:2712789",
        "tgn:1000001",
        "tgn:7012149",
        "tgn:1002948",
        "tgn:7007826",
        "tgn:7029392"
    ],
    "tgn:id":2712789,
    "tgn:name":"Taylor Creek",
    "tgn:placetype":[
        "aat:300008706"
    ]
},
  "bbox": [],
  "geometry": {"coordinates":[-94.8333,33.25],"type":"Point"}
}