{
  "id": 7445503,
  "type": "Feature",
  "properties": {
    "tgn:hierarchy":[
        "tgn:7445503",
        "tgn:7002445",
        "tgn:1000003",
        "tgn:7008160",
        "tgn:7008591",
        "tgn:7029392"
    ],
    "tgn:id":7445503,
    "tgn:name:en":"Wisbech Eye",
    "tgn:placetype":[
        "aat:300386846"
    ]
},
  "bbox": [],
  "geometry": {"coordinates":[0.233333,52.85],"type":"Point"}
}