{
  "id": 2181490,
  "type": "Feature",
  "properties": {
    "tgn:hierarchy":[
        "tgn:2181490",
        "tgn:1000001",
        "tgn:7012149",
        "tgn:1002611",
        "tgn:7007706",
        "tgn:7029392"
    ],
    "tgn:id":2181490,
    "tgn:name":"Blue Grass Island",
    "tgn:placetype":[
        "aat:300008791"
    ]
},
  "bbox": [],
  "geometry": {"coordinates":[-83.6667,41.55],"type":"Point"}
}