<<<<<<< HEAD
{
  "id": 2154994,
  "type": "Feature",
  "properties": {
    "tgn:hierarchy":[
        "tgn:2154994",
        "tgn:1000001",
        "tgn:7012149",
        "tgn:1002873",
        "tgn:7007568",
        "tgn:7029392"
    ],
    "tgn:id":2154994,
    "tgn:name":"Bear Kill",
    "tgn:placetype":[
        "aat:300008699"
    ]
},
  "bbox": [],
  "geometry": {"coordinates":[-74.3167,42.4333],"type":"Point"}
}
=======
{"geometry":{"type":"Point","coordinates":[-74.316700,42.433300]},"type":"Feature","properties":{"hierarchy":["tgn:2154994","tgn:1000001","tgn:7012149","tgn:1002873","tgn:7007568","tgn:7029392"],"placetype":["aat:300008699"],"id":2154994,"name:xx":"Bear Kill"}}
>>>>>>> 03f74aca74312dbeaf24d7e61306dd6a786dc3d0
