{
  "id": 2330550,
  "type": "Feature",
  "properties": {
    "tgn:hierarchy":[
        "tgn:2330550",
        "tgn:1000001",
        "tgn:7012149",
        "tgn:2001315",
        "tgn:7007524",
        "tgn:7029392"
    ],
    "tgn:id":2330550,
    "tgn:name":"Flat Creek",
    "tgn:placetype":[
        "aat:300008706"
    ]
},
  "bbox": [],
  "geometry": {"coordinates":[-108.2333,45.5667],"type":"Point"}
}