<<<<<<< HEAD
{
  "id": 7486889,
  "type": "Feature",
  "properties": {
    "tgn:hierarchy":[
        "tgn:7486889",
        "tgn:7001004",
        "tgn:1000004",
        "tgn:1000141",
        "tgn:7029392"
    ],
    "tgn:id":7486889,
    "tgn:name":"Weizhuang",
    "tgn:placetype":[
        "aat:300008347"
    ]
},
  "bbox": [],
  "geometry": {"coordinates":[120.653438,22.984206],"type":"Point"}
}
=======
{"geometry":{"type":"Point","coordinates":[120.653438,22.984206]},"type":"Feature","properties":{"hierarchy":["tgn:7486889","tgn:7001004","tgn:1000004","tgn:1000141","tgn:7029392"],"placetype":["aat:300008347"],"id":7486889,"name:xx":"Weizhuang"}}
>>>>>>> 03f74aca74312dbeaf24d7e61306dd6a786dc3d0
