{
  "id": 2194577,
  "type": "Feature",
  "properties": {
    "tgn:hierarchy":[
        "tgn:2194577",
        "tgn:1000001",
        "tgn:7016172",
        "tgn:7012149",
        "tgn:2000177",
        "tgn:7029392"
    ],
    "tgn:id":2194577,
    "tgn:name":"Bridges Lake",
    "tgn:placetype":[
        "aat:300006191"
    ]
},
  "bbox": [],
  "geometry": {"coordinates":[-91.65,35.4167],"type":"Point"}
}