{
  "id": 2459880,
  "type": "Feature",
  "properties": {
    "tgn:hierarchy":[
        "tgn:2459880",
        "tgn:1000001",
        "tgn:7012149",
        "tgn:2002174",
        "tgn:7007919",
        "tgn:7029392"
    ],
    "tgn:id":2459880,
    "tgn:name":"Little River Reservoir",
    "tgn:placetype":[
        "aat:300006191"
    ]
},
  "bbox": [],
  "geometry": {"coordinates":[-80.5667,37.0667],"type":"Point"}
}