{
  "id": 2563793,
  "type": "Feature",
  "properties": {
    "tgn:hierarchy":[
        "tgn:2563793",
        "tgn:1000001",
        "tgn:7012149",
        "tgn:2000968",
        "tgn:7007520",
        "tgn:7029392"
    ],
    "tgn:id":2563793,
    "tgn:name":"Oxbow Lake",
    "tgn:placetype":[
        "aat:300008680"
    ]
},
  "bbox": [],
  "geometry": {"coordinates":[-84.9667,44.8167],"type":"Point"}
}