{
  "id": 7587941,
  "type": "Feature",
  "properties": {
    "tgn:hierarchy":[
        "tgn:7587941",
        "tgn:1000004",
        "tgn:7000198",
        "tgn:7000799",
        "tgn:7029392"
    ],
    "tgn:id":7587941,
    "tgn:name:en":"Kh\u0101rapur",
    "tgn:placetype":[
        "aat:300008347"
    ]
},
  "bbox": [],
  "geometry": {"coordinates":[74.514424,34.055283],"type":"Point"}
}