<<<<<<< HEAD
{
  "id": 2767604,
  "type": "Feature",
  "properties": {
    "tgn:hierarchy":[
        "tgn:2767604",
        "tgn:1000001",
        "tgn:7012149",
        "tgn:1002636",
        "tgn:7007708",
        "tgn:7029392"
    ],
    "tgn:id":2767604,
    "tgn:name":"Whiteaker",
    "tgn:placetype":[
        "aat:300008347"
    ]
},
  "bbox": [],
  "geometry": {"coordinates":[-122.75,44.8667],"type":"Point"}
}
=======
{"geometry":{"type":"Point","coordinates":[-122.750000,44.866700]},"type":"Feature","properties":{"hierarchy":["tgn:2767604","tgn:1000001","tgn:7012149","tgn:1002636","tgn:7007708","tgn:7029392"],"placetype":["aat:300008347"],"id":2767604,"name:xx":"Whiteaker"}}
>>>>>>> 03f74aca74312dbeaf24d7e61306dd6a786dc3d0
