{
  "id": 7222336,
  "type": "Feature",
  "properties": {
    "tgn:hierarchy":[
        "tgn:7222336",
        "tgn:7011170",
        "tgn:7002715",
        "tgn:1000003",
        "tgn:1000074",
        "tgn:7029392"
    ],
    "tgn:id":7222336,
    "tgn:name":"Pol\u00edneron",
    "tgn:placetype":[
        "aat:300008347"
    ]
},
  "bbox": [],
  "geometry": {"coordinates":[24.483333,41.083333],"type":"Point"}
}