{
  "id": 2276937,
  "type": "Feature",
  "properties": {
    "tgn:hierarchy":[
        "tgn:2276937",
        "tgn:1000001",
        "tgn:7006451",
        "tgn:2000091",
        "tgn:7012149",
        "tgn:7029392"
    ],
    "tgn:id":2276937,
    "tgn:name":"Davis Canyon",
    "tgn:placetype":[
        "aat:300008761"
    ]
},
  "bbox": [],
  "geometry": {"coordinates":[-110.0833,32.35],"type":"Point"}
}