{
  "id": 1016458,
  "type": "Feature",
  "properties": {
    "tgn:hierarchy":[
        "tgn:1016458",
        "tgn:7014983",
        "tgn:1000001",
        "tgn:7004641",
        "tgn:7029392"
    ],
    "tgn:id":1016458,
    "tgn:name":"La Plaine",
    "tgn:placetype":[
        "aat:300008347",
        "aat:300008372"
    ]
},
  "bbox": [],
  "geometry": {"coordinates":[-61.25,15.3333],"type":"Point"}
}