<<<<<<< HEAD
{
  "id": 2258516,
  "type": "Feature",
  "properties": {
    "tgn:hierarchy":[
        "tgn:2258516",
        "tgn:1000001",
        "tgn:7012149",
        "tgn:2001696",
        "tgn:7007707",
        "tgn:7029392"
    ],
    "tgn:id":2258516,
    "tgn:name":"Cotton Valley",
    "tgn:placetype":[
        "aat:300008347"
    ]
},
  "bbox": [],
  "geometry": {"coordinates":[-95.85,36.9667],"type":"Point"}
}
=======
{"geometry":{"type":"Point","coordinates":[-95.850000,36.966700]},"type":"Feature","properties":{"hierarchy":["tgn:2258516","tgn:1000001","tgn:7012149","tgn:2001696","tgn:7007707","tgn:7029392"],"placetype":["aat:300008347"],"id":2258516,"name:xx":"Cotton Valley"}}
>>>>>>> 03f74aca74312dbeaf24d7e61306dd6a786dc3d0
