{
  "id": 7553255,
  "type": "Feature",
  "properties": {
    "tgn:hierarchy":[
        "tgn:7553255",
        "tgn:1001828",
        "tgn:1000004",
        "tgn:7000198",
        "tgn:7029392"
    ],
    "tgn:id":7553255,
    "tgn:name:en":"Nerijamupalle",
    "tgn:placetype":[
        "aat:300008347"
    ]
},
  "bbox": [],
  "geometry": {"coordinates":[78.016667,14.533333],"type":"Point"}
}