{
  "id": 7151866,
  "type": "Feature",
  "properties": {
    "tgn:hierarchy":[
        "tgn:7151866",
        "tgn:7003692",
        "tgn:1000003",
        "tgn:7000084",
        "tgn:7029392"
    ],
    "tgn:id":7151866,
    "tgn:name":"Kammerhof",
    "tgn:placetype":[
        "aat:300000206"
    ]
},
  "bbox": [],
  "geometry": {"coordinates":[9.55,48.016667],"type":"Point"}
}