{
  "id": 7125300,
  "type": "Feature",
  "properties": {
    "tgn:hierarchy":[
        "tgn:7125300",
        "tgn:7000096",
        "tgn:1000003",
        "tgn:7000084",
        "tgn:7029392"
    ],
    "tgn:id":7125300,
    "tgn:name":"Neulewin",
    "tgn:placetype":[
        "aat:300008347"
    ]
},
  "bbox": [],
  "geometry": {"coordinates":[14.283333,52.716667],"type":"Point"}
}