{
  "id": 2267211,
  "type": "Feature",
  "properties": {
    "tgn:hierarchy":[
        "tgn:2267211",
        "tgn:1000001",
        "tgn:7012149",
        "tgn:2001553",
        "tgn:7007709",
        "tgn:7029392"
    ],
    "tgn:id":2267211,
    "tgn:name":"Cricket Park",
    "tgn:placetype":[
        "aat:300008347"
    ]
},
  "bbox": [],
  "geometry": {"coordinates":[-81.1833,36.1667],"type":"Point"}
}