{
  "id": 2181198,
  "type": "Feature",
  "properties": {
    "tgn:hierarchy":[
        "tgn:2181198",
        "tgn:7013349",
        "tgn:1000001",
        "tgn:7012149",
        "tgn:7007708",
        "tgn:7029392"
    ],
    "tgn:id":2181198,
    "tgn:name":"Blue Canyon",
    "tgn:placetype":[
        "aat:300008761"
    ]
},
  "bbox": [],
  "geometry": {"coordinates":[-117.3333,44.9667],"type":"Point"}
}