{
  "id": 7360443,
  "type": "Feature",
  "properties": {
    "tgn:hierarchy":[
        "tgn:7360443",
        "tgn:7005581",
        "tgn:1000001",
        "tgn:7005560",
        "tgn:7029392"
    ],
    "tgn:id":7360443,
    "tgn:name":"Cochero, Arroyo del",
    "tgn:placetype":[
        "aat:300266554",
        "aat:300008699"
    ]
},
  "bbox": [],
  "geometry": {"coordinates":[-107.766667,29.65],"type":"Point"}
}