{
  "id": 7514997,
  "type": "Feature",
  "properties": {
    "tgn:hierarchy":[
        "tgn:7514997",
        "tgn:1008380",
        "tgn:1000226",
        "tgn:7000512",
        "tgn:1000006",
        "tgn:7029392"
    ],
    "tgn:id":7514997,
    "tgn:name:en":"Carrington Creek",
    "tgn:placetype":[
        "aat:300008699"
    ]
},
  "bbox": [],
  "geometry": {"coordinates":[175.483333,-41.05],"type":"Point"}
}