{
  "id": 2719023,
  "type": "Feature",
  "properties": {
    "tgn:hierarchy":[
        "tgn:2719023",
        "tgn:1000001",
        "tgn:7012149",
        "tgn:7020792",
        "tgn:7007524",
        "tgn:7029392"
    ],
    "tgn:id":2719023,
    "tgn:name":"Thornton Lake",
    "tgn:placetype":[
        "aat:300006191"
    ]
},
  "bbox": [],
  "geometry": {"coordinates":[-113.0333,46.25],"type":"Point"}
}