{
  "id": 7314204,
  "type": "Feature",
  "properties": {
    "tgn:hierarchy":[
        "tgn:7314204",
        "tgn:1001702",
        "tgn:1000049",
        "tgn:1000002",
        "tgn:7029392"
    ],
    "tgn:id":7314204,
    "tgn:name":"Lorca, Ensenada",
    "tgn:placetype":[
        "aat:300132317"
    ]
},
  "bbox": [],
  "geometry": {"coordinates":[-71.566667,-52.566667],"type":"Point"}
}