{
  "id": 1049338,
  "type": "Feature",
  "properties": {
    "tgn:hierarchy":[
        "tgn:1049338",
        "tgn:1000003",
        "tgn:7024124",
        "tgn:7006366",
        "tgn:7029392"
    ],
    "tgn:id":1049338,
    "tgn:name":"Otmuch\u00f3w",
    "tgn:placetype":[
        "aat:300008347"
    ]
},
  "bbox": [],
  "geometry": {"coordinates":[17.15,50.4667],"type":"Point"}
}