{
  "id": 1133389,
  "type": "Feature",
  "properties": {
    "tgn:hierarchy":[
        "tgn:1133389",
        "tgn:1002215",
        "tgn:1000001",
        "tgn:7012149",
        "tgn:7007565",
        "tgn:7029392"
    ],
    "tgn:id":1133389,
    "tgn:name":"Haynes Creek",
    "tgn:placetype":[
        "aat:300008706"
    ]
},
  "bbox": [],
  "geometry": {"coordinates":[-74.8333,39.8667],"type":"Point"}
}