{
  "id": 7456809,
  "type": "Feature",
  "properties": {
    "tgn:hierarchy":[
        "tgn:7456809",
        "tgn:7002445",
        "tgn:1000003",
        "tgn:7012077",
        "tgn:7008591",
        "tgn:7029392"
    ],
    "tgn:id":7456809,
    "tgn:name:en":"Marystow",
    "tgn:placetype":[
        "aat:300008347"
    ]
},
  "bbox": [],
  "geometry": {"coordinates":[-4.216667,50.616667],"type":"Point"}
}