{
  "id": 7259425,
  "type": "Feature",
  "properties": {
    "tgn:hierarchy":[
        "tgn:7259425",
        "tgn:7003456",
        "tgn:1000003",
        "tgn:1000063",
        "tgn:7018236",
        "tgn:7029392"
    ],
    "tgn:id":7259425,
    "tgn:name":"Fort van Walem",
    "tgn:placetype":[
        "aat:300006909"
    ]
},
  "bbox": [],
  "geometry": {"coordinates":[4.462064,51.061488],"type":"Point"}
}