{
  "id": 2106334,
  "type": "Feature",
  "properties": {
    "tgn:hierarchy":[
        "tgn:2106334",
        "tgn:1000001",
        "tgn:7012149",
        "tgn:2001983",
        "tgn:7007826",
        "tgn:7029392"
    ],
    "tgn:id":2106334,
    "tgn:name":"Nobility",
    "tgn:placetype":[
        "aat:300008347",
        "aat:300387210"
    ]
},
  "bbox": [],
  "geometry": {"coordinates":[-96.35,33.3667],"type":"Point"}
}