{
  "id": 2535097,
  "type": "Feature",
  "properties": {
    "tgn:hierarchy":[
        "tgn:2535097",
        "tgn:1000001",
        "tgn:7012149",
        "tgn:7007825",
        "tgn:7029392"
    ],
    "tgn:id":2535097,
    "tgn:name":"Nances Shoals",
    "tgn:placetype":[
        "aat:300132348"
    ]
},
  "bbox": [],
  "geometry": {"coordinates":[-83.6333,36.1333],"type":"Point"}
}