{
  "id": 2387314,
  "type": "Feature",
  "properties": {
    "tgn:hierarchy":[
        "tgn:2387314",
        "tgn:2001732",
        "tgn:1000001",
        "tgn:7012149",
        "tgn:7007712",
        "tgn:7029392"
    ],
    "tgn:id":2387314,
    "tgn:name":"Hester Canal",
    "tgn:placetype":[
        "aat:300006075"
    ]
},
  "bbox": [],
  "geometry": {"coordinates":[-79.7833,33.0833],"type":"Point"}
}