{
  "id": 7061627,
  "type": "Feature",
  "properties": {
    "tgn:hierarchy":[
        "tgn:7061627",
        "tgn:7003669",
        "tgn:1000003",
        "tgn:7000084",
        "tgn:7029392"
    ],
    "tgn:id":7061627,
    "tgn:name":"Anatswald",
    "tgn:placetype":[
        "aat:300008347"
    ]
},
  "bbox": [],
  "geometry": {"coordinates":[10.266667,47.35],"type":"Point"}
}