<<<<<<< HEAD
{
  "id": 7027887,
  "type": "Feature",
  "properties": {
    "tgn:hierarchy":[
        "tgn:7027887",
        "tgn:7002445",
        "tgn:1000003",
        "tgn:7008157",
        "tgn:7008591",
        "tgn:7029392"
    ],
    "tgn:id":7027887,
    "tgn:name:en":"Grainthorpe",
    "tgn:placetype":[
        "aat:300008347",
        "aat:300008372",
        "aat:300120599"
    ]
},
  "bbox": [],
  "geometry": {"coordinates":[0.083333,53.466667],"type":"Point"}
}
=======
{"geometry":{"type":"Point","coordinates":[0.083333,53.466667]},"type":"Feature","properties":{"hierarchy":["tgn:7027887","tgn:7002445","tgn:1000003","tgn:7008157","tgn:7008591","tgn:7029392"],"placetype":["aat:300008347","aat:300008372","aat:300120599"],"name:en":"Grainthorpe","id":7027887}}
>>>>>>> 03f74aca74312dbeaf24d7e61306dd6a786dc3d0
