{
  "id": 7496453,
  "type": "Feature",
  "properties": {
    "tgn:hierarchy":[
        "tgn:7496453",
        "tgn:1000004",
        "tgn:7001013",
        "tgn:1000141",
        "tgn:7029392"
    ],
    "tgn:id":7496453,
    "tgn:name":"Cihu",
    "tgn:placetype":[
        "aat:300008347"
    ]
},
  "bbox": [],
  "geometry": {"coordinates":[121.299241,24.84225],"type":"Point"}
}