{
  "id": 7566711,
  "type": "Feature",
  "properties": {
    "tgn:hierarchy":[
        "tgn:7566711",
        "tgn:1000004",
        "tgn:7000198",
        "tgn:7016722",
        "tgn:7029392"
    ],
    "tgn:id":7566711,
    "tgn:name:en":"Kanjh\u0101i",
    "tgn:placetype":[
        "aat:300008347"
    ]
},
  "bbox": [],
  "geometry": {"coordinates":[79.993067,26.673928],"type":"Point"}
}