{
  "id": 7249589,
  "type": "Feature",
  "properties": {
    "tgn:hierarchy":[
        "tgn:7249589",
        "tgn:7007877",
        "tgn:1000003",
        "tgn:1000063",
        "tgn:4012014",
        "tgn:7029392"
    ],
    "tgn:id":7249589,
    "tgn:name":"Pont d'Ancre",
    "tgn:placetype":[
        "aat:300008347"
    ]
},
  "bbox": [],
  "geometry": {"coordinates":[3.827598,50.722402],"type":"Point"}
}