{
  "id": 7187580,
  "type": "Feature",
  "properties": {
    "tgn:hierarchy":[
        "tgn:7187580",
        "tgn:7003669",
        "tgn:1000003",
        "tgn:7000084",
        "tgn:7029392"
    ],
    "tgn:id":7187580,
    "tgn:name":"Etzenrichter Wald",
    "tgn:placetype":[
        "aat:300008863"
    ]
},
  "bbox": [],
  "geometry": {"coordinates":[12.083333,49.616667],"type":"Point"}
}