<<<<<<< HEAD
{
  "id": 2702336,
  "type": "Feature",
  "properties": {
    "tgn:hierarchy":[
        "tgn:2702336",
        "tgn:1000001",
        "tgn:7012149",
        "tgn:2000329",
        "tgn:7007248",
        "tgn:7029392"
    ],
    "tgn:id":2702336,
    "tgn:name":"Sullivan Lake",
    "tgn:placetype":[
        "aat:300006191"
    ]
},
  "bbox": [],
  "geometry": {"coordinates":[-84.7,33.3833],"type":"Point"}
}
=======
{"geometry":{"type":"Point","coordinates":[-84.700000,33.383300]},"type":"Feature","properties":{"hierarchy":["tgn:2702336","tgn:1000001","tgn:7012149","tgn:2000329","tgn:7007248","tgn:7029392"],"placetype":["aat:300006191"],"id":2702336,"name:xx":"Sullivan Lake"}}
>>>>>>> 03f74aca74312dbeaf24d7e61306dd6a786dc3d0
