{
  "id": 7302795,
  "type": "Feature",
  "properties": {
    "tgn:hierarchy":[
        "tgn:7302795",
        "tgn:7002806",
        "tgn:7001158",
        "tgn:1000003",
        "tgn:1000095",
        "tgn:7029392"
    ],
    "tgn:id":7302795,
    "tgn:name":"M\u00fanez",
    "tgn:placetype":[
        "aat:300008347"
    ]
},
  "bbox": [],
  "geometry": {"coordinates":[-4.983333,40.616667],"type":"Point"}
}