{
  "id": 2549671,
  "type": "Feature",
  "properties": {
    "tgn:hierarchy":[
        "tgn:2549671",
        "tgn:1000001",
        "tgn:7012149",
        "tgn:7007825",
        "tgn:7029392"
    ],
    "tgn:id":2549671,
    "tgn:name":"North Suck Creek",
    "tgn:placetype":[
        "aat:300008706"
    ]
},
  "bbox": [],
  "geometry": {"coordinates":[-85.4167,35.2167],"type":"Point"}
}