{
  "id": 7295101,
  "type": "Feature",
  "properties": {
    "tgn:hierarchy":[
        "tgn:7295101",
        "tgn:7002834",
        "tgn:1000003",
        "tgn:7002786",
        "tgn:1000095",
        "tgn:7029392"
    ],
    "tgn:id":7295101,
    "tgn:name":"Greix\u00f1a, Punta",
    "tgn:placetype":[
        "aat:300386846"
    ]
},
  "bbox": [],
  "geometry": {"coordinates":[-8.834722,42.256944],"type":"Point"}
}