{
  "id": 2592949,
  "type": "Feature",
  "properties": {
    "tgn:hierarchy":[
        "tgn:2592949",
        "tgn:1000001",
        "tgn:7012149",
        "tgn:2001503",
        "tgn:7007709",
        "tgn:7029392"
    ],
    "tgn:id":2592949,
    "tgn:name":"Poplar Cove Branch",
    "tgn:placetype":[
        "aat:300008699"
    ]
},
  "bbox": [],
  "geometry": {"coordinates":[-82.9833,35.7333],"type":"Point"}
}