<<<<<<< HEAD
{
  "id": 2153526,
  "type": "Feature",
  "properties": {
    "tgn:hierarchy":[
        "tgn:2153526",
        "tgn:7030515",
        "tgn:7006450",
        "tgn:1000001",
        "tgn:7012149",
        "tgn:7029392"
    ],
    "tgn:id":2153526,
    "tgn:name":"Bear Bay",
    "tgn:placetype":[
        "aat:300132316"
    ]
},
  "bbox": [],
  "geometry": {"coordinates":[-162.0,55.1667],"type":"Point"}
}
=======
{"geometry":{"type":"Point","coordinates":[-162.000000,55.166700]},"type":"Feature","properties":{"hierarchy":["tgn:2153526","tgn:7030515","tgn:7006450","tgn:1000001","tgn:7012149","tgn:7029392"],"placetype":["aat:300132316"],"id":2153526,"name:xx":"Bear Bay"}}
>>>>>>> 03f74aca74312dbeaf24d7e61306dd6a786dc3d0
