{
  "id": 2519772,
  "type": "Feature",
  "properties": {
    "tgn:hierarchy":[
        "tgn:2519772",
        "tgn:1000001",
        "tgn:7006451",
        "tgn:7012149",
        "tgn:2000098",
        "tgn:7029392"
    ],
    "tgn:id":2519772,
    "tgn:name":"Mohon Tank",
    "tgn:placetype":[
        "aat:300006191"
    ]
},
  "bbox": [],
  "geometry": {"coordinates":[-113.3667,35.0333],"type":"Point"}
}