{
  "id": 2395111,
  "type": "Feature",
  "properties": {
    "tgn:hierarchy":[
        "tgn:2395111",
        "tgn:1000001",
        "tgn:7006451",
        "tgn:2000092",
        "tgn:7012149",
        "tgn:7029392"
    ],
    "tgn:id":2395111,
    "tgn:name":"Hole in the Rock",
    "tgn:placetype":[
        "aat:300386837"
    ]
},
  "bbox": [],
  "geometry": {"coordinates":[-111.8333,36.9333],"type":"Point"}
}