{
  "id": 7080787,
  "type": "Feature",
  "properties": {
    "tgn:hierarchy":[
        "tgn:7080787",
        "tgn:1000003",
        "tgn:7003677",
        "tgn:7000084",
        "tgn:7029392"
    ],
    "tgn:id":7080787,
    "tgn:name":"W\u00f6hren",
    "tgn:placetype":[
        "aat:300008347"
    ]
},
  "bbox": [],
  "geometry": {"coordinates":[9.016667,51.966667],"type":"Point"}
}