{
  "id": 1123814,
  "type": "Feature",
  "properties": {
    "tgn:hierarchy":[
        "tgn:1123814",
        "tgn:1003429",
        "tgn:1000003",
        "tgn:7003240",
        "tgn:1000080",
        "tgn:7029392"
    ],
    "tgn:id":1123814,
    "tgn:name":"Esino",
    "tgn:placetype":[
        "aat:300008707",
        "aat:300008699"
    ]
},
  "bbox": [],
  "geometry": {"coordinates":[13.366667,43.65],"type":"Point"}
}