<<<<<<< HEAD
{
  "id": 7178315,
  "type": "Feature",
  "properties": {
    "tgn:hierarchy":[
        "tgn:7178315",
        "tgn:1000003",
        "tgn:7003685",
        "tgn:7000084",
        "tgn:7029392"
    ],
    "tgn:id":7178315,
    "tgn:name":"Hadria Teich",
    "tgn:placetype":[
        "aat:300008688"
    ]
},
  "bbox": [],
  "geometry": {"coordinates":[14.666667,51.35],"type":"Point"}
}
=======
{"geometry":{"type":"Point","coordinates":[14.666667,51.350000]},"type":"Feature","properties":{"hierarchy":["tgn:7178315","tgn:1000003","tgn:7003685","tgn:7000084","tgn:7029392"],"placetype":["aat:300008688"],"id":7178315,"name:xx":"Hadria Teich"}}
>>>>>>> 03f74aca74312dbeaf24d7e61306dd6a786dc3d0
