{
  "id": 7261391,
  "type": "Feature",
  "properties": {
    "tgn:hierarchy":[
        "tgn:7261391",
        "tgn:1000003",
        "tgn:7003626",
        "tgn:7016845",
        "tgn:7029392"
    ],
    "tgn:id":7261391,
    "tgn:name:nl":"Groot Lankhorst",
    "tgn:placetype":[
        "aat:300008863"
    ]
},
  "bbox": [],
  "geometry": {"coordinates":[6.183333,52.333333],"type":"Point"}
}