{
  "id": 7515169,
  "type": "Feature",
  "properties": {
    "tgn:hierarchy":[
        "tgn:7515169",
        "tgn:1009227",
        "tgn:7001866",
        "tgn:1000226",
        "tgn:1000006",
        "tgn:7029392"
    ],
    "tgn:id":7515169,
    "tgn:name:en":"Cow Stream",
    "tgn:placetype":[
        "aat:300008699"
    ]
},
  "bbox": [],
  "geometry": {"coordinates":[172.666667,-42.416667],"type":"Point"}
}