{
  "id": 2387872,
  "type": "Feature",
  "properties": {
    "tgn:hierarchy":[
        "tgn:2387872",
        "tgn:1000001",
        "tgn:7016172",
        "tgn:7012149",
        "tgn:2000151",
        "tgn:7029392"
    ],
    "tgn:id":2387872,
    "tgn:name":"Hickman Landing",
    "tgn:placetype":[
        "aat:300008347"
    ]
},
  "bbox": [],
  "geometry": {"coordinates":[-89.6833,35.9333],"type":"Point"}
}