{
  "id": 2377151,
  "type": "Feature",
  "properties": {
    "tgn:hierarchy":[
        "tgn:2377151",
        "tgn:1000001",
        "tgn:7012149",
        "tgn:2002351",
        "tgn:7007922",
        "tgn:7029392"
    ],
    "tgn:id":2377151,
    "tgn:name":"Harmin Lake",
    "tgn:placetype":[
        "aat:300008680"
    ]
},
  "bbox": [],
  "geometry": {"coordinates":[-92.2667,45.1833],"type":"Point"}
}