{
  "id": 7442954,
  "type": "Feature",
  "properties": {
    "tgn:hierarchy":[
        "tgn:7442954",
        "tgn:7002445",
        "tgn:1000003",
        "tgn:7008134",
        "tgn:7008591",
        "tgn:7029392"
    ],
    "tgn:id":7442954,
    "tgn:name:en":"Walberton",
    "tgn:placetype":[
        "aat:300008347"
    ]
},
  "bbox": [],
  "geometry": {"coordinates":[-0.616667,50.85],"type":"Point"}
}