{
  "id": 2197552,
  "type": "Feature",
  "properties": {
    "tgn:hierarchy":[
        "tgn:2197552",
        "tgn:1000001",
        "tgn:1002714",
        "tgn:7012149",
        "tgn:7007159",
        "tgn:7029392"
    ],
    "tgn:id":2197552,
    "tgn:name":"Brown Hill",
    "tgn:placetype":[
        "aat:300008798"
    ]
},
  "bbox": [],
  "geometry": {"coordinates":[-72.3167,41.3833],"type":"Point"}
}