{
  "id": 7061537,
  "type": "Feature",
  "properties": {
    "tgn:hierarchy":[
        "tgn:7061537",
        "tgn:1000003",
        "tgn:7003676",
        "tgn:7000084",
        "tgn:7029392"
    ],
    "tgn:id":7061537,
    "tgn:name":"Auf dem Wiebusch",
    "tgn:placetype":[
        "aat:300008347"
    ]
},
  "bbox": [],
  "geometry": {"coordinates":[8.416667,52.216667],"type":"Point"}
}