{
  "id": 7121818,
  "type": "Feature",
  "properties": {
    "tgn:hierarchy":[
        "tgn:7121818",
        "tgn:7003669",
        "tgn:1000003",
        "tgn:7000084",
        "tgn:7029392"
    ],
    "tgn:id":7121818,
    "tgn:name":"Pinzgau",
    "tgn:placetype":[
        "aat:300008347"
    ]
},
  "bbox": [],
  "geometry": {"coordinates":[12.533333,48.083333],"type":"Point"}
}