{
  "id": 7196606,
  "type": "Feature",
  "properties": {
    "tgn:hierarchy":[
        "tgn:7196606",
        "tgn:1000003",
        "tgn:7000094",
        "tgn:7000084",
        "tgn:7029392"
    ],
    "tgn:id":7196606,
    "tgn:name":"Datzow",
    "tgn:placetype":[
        "aat:300008347"
    ]
},
  "bbox": [],
  "geometry": {"coordinates":[13.25,54.316667],"type":"Point"}
}