{
  "id": 7168746,
  "type": "Feature",
  "properties": {
    "tgn:hierarchy":[
        "tgn:7168746",
        "tgn:1000003",
        "tgn:7003687",
        "tgn:7000084",
        "tgn:7029392"
    ],
    "tgn:id":7168746,
    "tgn:name":"Hassel",
    "tgn:placetype":[
        "aat:300008699"
    ]
},
  "bbox": [],
  "geometry": {"coordinates":[10.816667,51.716667],"type":"Point"}
}