{
  "id": 2422790,
  "type": "Feature",
  "properties": {
    "tgn:hierarchy":[
        "tgn:2422790",
        "tgn:1000001",
        "tgn:7012149",
        "tgn:2001924",
        "tgn:7007825",
        "tgn:7029392"
    ],
    "tgn:id":2422790,
    "tgn:name":"Joe Branch",
    "tgn:placetype":[
        "aat:300008699"
    ]
},
  "bbox": [],
  "geometry": {"coordinates":[-85.3333,35.6833],"type":"Point"}
}