{
  "id": 1132826,
  "type": "Feature",
  "properties": {
    "tgn:hierarchy":[
        "tgn:1132826",
        "tgn:1001945",
        "tgn:1000047",
        "tgn:7002457",
        "tgn:1000002",
        "tgn:7029392"
    ],
    "tgn:id":1132826,
    "tgn:name":"Claro, Ribeir\u00e3o",
    "tgn:placetype":[
        "aat:300008706"
    ]
},
  "bbox": [],
  "geometry": {"coordinates":[-46.2833,-23.6667],"type":"Point"}
}