{
  "id": 2641256,
  "type": "Feature",
  "properties": {
    "tgn:hierarchy":[
        "tgn:2641256",
        "tgn:1000001",
        "tgn:7012149",
        "tgn:2000289",
        "tgn:7007240",
        "tgn:7029392"
    ],
    "tgn:id":2641256,
    "tgn:name":"Sand Creek",
    "tgn:placetype":[
        "aat:300008706"
    ]
},
  "bbox": [],
  "geometry": {"coordinates":[-84.3333,29.9667],"type":"Point"}
}