{
  "id": 7232147,
  "type": "Feature",
  "properties": {
    "tgn:hierarchy":[
        "tgn:7232147",
        "tgn:7011167",
        "tgn:7001338",
        "tgn:1000003",
        "tgn:1000074",
        "tgn:7029392"
    ],
    "tgn:id":7232147,
    "tgn:name":"Kalam\u00e1kion",
    "tgn:placetype":[
        "aat:300008347"
    ]
},
  "bbox": [],
  "geometry": {"coordinates":[20.916667,37.733333],"type":"Point"}
}