{
  "id": 2505966,
  "type": "Feature",
  "properties": {
    "tgn:hierarchy":[
        "tgn:2505966",
        "tgn:1002538",
        "tgn:1000001",
        "tgn:7012149",
        "tgn:7007239",
        "tgn:7029392"
    ],
    "tgn:id":2505966,
    "tgn:name":"Meredith Branch",
    "tgn:placetype":[
        "aat:300008699"
    ]
},
  "bbox": [],
  "geometry": {"coordinates":[-75.65,38.9833],"type":"Point"}
}