{
  "id": 7400108,
  "type": "Feature",
  "properties": {
    "tgn:hierarchy":[
        "tgn:7400108",
        "tgn:1000001",
        "tgn:7005593",
        "tgn:7005560",
        "tgn:7029392"
    ],
    "tgn:id":7400108,
    "tgn:name":"El Charco",
    "tgn:placetype":[
        "aat:300008347"
    ]
},
  "bbox": [],
  "geometry": {"coordinates":[-99.195833,21.384722],"type":"Point"}
}