<<<<<<< HEAD
{
  "id": 2258654,
  "type": "Feature",
  "properties": {
    "tgn:hierarchy":[
        "tgn:2258654",
        "tgn:1000001",
        "tgn:2001417",
        "tgn:7012149",
        "tgn:7007526",
        "tgn:7029392"
    ],
    "tgn:id":2258654,
    "tgn:name":"Cottonwood Ca\u00f1on",
    "tgn:placetype":[
        "aat:300008761"
    ]
},
  "bbox": [],
  "geometry": {"coordinates":[-118.6667,38.3667],"type":"Point"}
}
=======
{"geometry":{"type":"Point","coordinates":[-118.666700,38.366700]},"type":"Feature","properties":{"hierarchy":["tgn:2258654","tgn:1000001","tgn:2001417","tgn:7012149","tgn:7007526","tgn:7029392"],"placetype":["aat:300008761"],"id":2258654,"name:xx":"Cottonwood Ca\u00f1on"}}
>>>>>>> 03f74aca74312dbeaf24d7e61306dd6a786dc3d0
