{
  "id": 2258654,
  "type": "Feature",
  "properties": {
    "tgn:hierarchy":[
        "tgn:2258654",
        "tgn:1000001",
        "tgn:2001417",
        "tgn:7012149",
        "tgn:7007526",
        "tgn:7029392"
    ],
    "tgn:id":2258654,
    "tgn:name":"Cottonwood Ca\u00f1on",
    "tgn:placetype":[
        "aat:300008761"
    ]
},
  "bbox": [],
  "geometry": {"coordinates":[-118.6667,38.3667],"type":"Point"}
}