{
  "id": 7495343,
  "type": "Feature",
  "properties": {
    "tgn:hierarchy":[
        "tgn:7495343",
        "tgn:1000004",
        "tgn:7001014",
        "tgn:1000141",
        "tgn:7029392"
    ],
    "tgn:id":7495343,
    "tgn:name":"Xinyi Guoxiao",
    "tgn:placetype":[
        "aat:300006495"
    ]
},
  "bbox": [],
  "geometry": {"coordinates":[120.280422,23.656885],"type":"Point"}
}