{
  "id": 7258135,
  "type": "Feature",
  "properties": {
    "tgn:hierarchy":[
        "tgn:7258135",
        "tgn:1000003",
        "tgn:7003635",
        "tgn:7016845",
        "tgn:7029392"
    ],
    "tgn:id":7258135,
    "tgn:name:nl":"Boomkreek",
    "tgn:placetype":[
        "aat:300008699"
    ]
},
  "bbox": [],
  "geometry": {"coordinates":[3.483333,51.316667],"type":"Point"}
}