{
  "id": 2714932,
  "type": "Feature",
  "properties": {
    "tgn:hierarchy":[
        "tgn:2714932",
        "tgn:1000001",
        "tgn:2002109",
        "tgn:7012149",
        "tgn:7007827",
        "tgn:7029392"
    ],
    "tgn:id":2714932,
    "tgn:name":"Tenmile Spring",
    "tgn:placetype":[
        "aat:300008697"
    ]
},
  "bbox": [],
  "geometry": {"coordinates":[-111.4667,37.6667],"type":"Point"}
}