{
  "id": 2710955,
  "type": "Feature",
  "properties": {
    "tgn:hierarchy":[
        "tgn:2710955",
        "tgn:1000001",
        "tgn:7012149",
        "tgn:2002125",
        "tgn:7007827",
        "tgn:7029392"
    ],
    "tgn:id":2710955,
    "tgn:name":"Tank Hollow",
    "tgn:placetype":[
        "aat:300008761"
    ]
},
  "bbox": [],
  "geometry": {"coordinates":[-111.3167,39.9833],"type":"Point"}
}