{
  "id": 7531132,
  "type": "Feature",
  "properties": {
    "tgn:hierarchy":[
        "tgn:7531132",
        "tgn:7001242",
        "tgn:7016833",
        "tgn:1001091",
        "tgn:7029392"
    ],
    "tgn:id":7531132,
    "tgn:name":"Kan\u012bsat al 'Adhr\u0101' wa al Mal\u0101k M\u012bkh\u0101'\u012bl",
    "tgn:placetype":[
        "aat:300007466"
    ]
},
  "bbox": [],
  "geometry": {"coordinates":[31.248121,30.09698],"type":"Point"}
}