{
  "id": 7021341,
  "type": "Feature",
  "properties": {
    "tgn:hierarchy":[
        "tgn:7021341",
        "tgn:1000001",
        "tgn:7012149",
        "tgn:2002290",
        "tgn:7013961",
        "tgn:7029392"
    ],
    "tgn:id":7021341,
    "tgn:name":"Plumley Mountain",
    "tgn:placetype":[
        "aat:300008798"
    ]
},
  "bbox": [],
  "geometry": {"coordinates":[-80.9833,37.7667],"type":"Point"}
}