<<<<<<< HEAD
{
  "id": 2151648,
  "type": "Feature",
  "properties": {
    "tgn:hierarchy":[
        "tgn:2151648",
        "tgn:1000001",
        "tgn:7012149",
        "tgn:2000712",
        "tgn:7007254",
        "tgn:7029392"
    ],
    "tgn:id":2151648,
    "tgn:name":"Battle Creek",
    "tgn:placetype":[
        "aat:300008706"
    ]
},
  "bbox": [],
  "geometry": {"coordinates":[-98.2,39.1167],"type":"Point"}
}
=======
{"geometry":{"type":"Point","coordinates":[-98.200000,39.116700]},"type":"Feature","properties":{"hierarchy":["tgn:2151648","tgn:1000001","tgn:7012149","tgn:2000712","tgn:7007254","tgn:7029392"],"placetype":["aat:300008706"],"id":2151648,"name:xx":"Battle Creek"}}
>>>>>>> 03f74aca74312dbeaf24d7e61306dd6a786dc3d0
