{
  "id": 7591184,
  "type": "Feature",
  "properties": {
    "tgn:hierarchy":[
        "tgn:7591184",
        "tgn:1000004",
        "tgn:7000198",
        "tgn:7000799",
        "tgn:7029392"
    ],
    "tgn:id":7591184,
    "tgn:name:en":"Dablehar",
    "tgn:placetype":[
        "aat:300008347"
    ]
},
  "bbox": [],
  "geometry": {"coordinates":[74.772222,32.577778],"type":"Point"}
}