{
  "id": 7497859,
  "type": "Feature",
  "properties": {
    "tgn:hierarchy":[
        "tgn:7497859",
        "tgn:1000004",
        "tgn:7491221",
        "tgn:1000141",
        "tgn:7029392"
    ],
    "tgn:id":7497859,
    "tgn:name":"Taiping Cun",
    "tgn:placetype":[
        "aat:300387173"
    ]
},
  "bbox": [],
  "geometry": {"coordinates":[121.081148,22.785325],"type":"Point"}
}