{
  "id": 1083552,
  "type": "Feature",
  "properties": {
    "tgn:hierarchy":[
        "tgn:1083552",
        "tgn:1000004",
        "tgn:1001490",
        "tgn:1000133",
        "tgn:7029392"
    ],
    "tgn:id":1083552,
    "tgn:name":"Kanganpur",
    "tgn:placetype":[
        "aat:300008347"
    ]
},
  "bbox": [],
  "geometry": {"coordinates":[74.1333,30.7667],"type":"Point"}
}