{
  "id": 7517810,
  "type": "Feature",
  "properties": {
    "tgn:hierarchy":[
        "tgn:7517810",
        "tgn:1008380",
        "tgn:7520093",
        "tgn:1000226",
        "tgn:1000006",
        "tgn:7029392"
    ],
    "tgn:id":7517810,
    "tgn:name:en":"Ngaturi Creek",
    "tgn:placetype":[
        "aat:300008699"
    ]
},
  "bbox": [],
  "geometry": {"coordinates":[175.916667,-40.466667],"type":"Point"}
}