{
  "id": 2126245,
  "type": "Feature",
  "properties": {
    "tgn:hierarchy":[
        "tgn:2126245",
        "tgn:1000001",
        "tgn:7012149",
        "tgn:2001843",
        "tgn:7007825",
        "tgn:7029392"
    ],
    "tgn:id":2126245,
    "tgn:name":"Adkins Branch",
    "tgn:placetype":[
        "aat:300008699"
    ]
},
  "bbox": [],
  "geometry": {"coordinates":[-84.3667,36.2333],"type":"Point"}
}