{
  "id": 7177209,
  "type": "Feature",
  "properties": {
    "tgn:hierarchy":[
        "tgn:7177209",
        "tgn:7003669",
        "tgn:1000003",
        "tgn:7000084",
        "tgn:7029392"
    ],
    "tgn:id":7177209,
    "tgn:name":"Hagendorf",
    "tgn:placetype":[
        "aat:300008347"
    ]
},
  "bbox": [],
  "geometry": {"coordinates":[12.466667,49.65],"type":"Point"}
}