{
  "id": 2566973,
  "type": "Feature",
  "properties": {
    "tgn:hierarchy":[
        "tgn:2566973",
        "tgn:1000001",
        "tgn:7012149",
        "tgn:2000793",
        "tgn:7007255",
        "tgn:7029392"
    ],
    "tgn:id":2566973,
    "tgn:name":"Panther Creek",
    "tgn:placetype":[
        "aat:300008706"
    ]
},
  "bbox": [],
  "geometry": {"coordinates":[-86.45,37.55],"type":"Point"}
}