{
  "id": 7092962,
  "type": "Feature",
  "properties": {
    "tgn:hierarchy":[
        "tgn:7092962",
        "tgn:7003669",
        "tgn:1000003",
        "tgn:7000084",
        "tgn:7029392"
    ],
    "tgn:id":7092962,
    "tgn:name":"Schweinthal",
    "tgn:placetype":[
        "aat:300000206"
    ]
},
  "bbox": [],
  "geometry": {"coordinates":[11.85,47.75],"type":"Point"}
}