{
  "id": 2536365,
  "type": "Feature",
  "properties": {
    "tgn:hierarchy":[
        "tgn:2536365",
        "tgn:1000001",
        "tgn:7012149",
        "tgn:1002511",
        "tgn:7007919",
        "tgn:7029392"
    ],
    "tgn:id":2536365,
    "tgn:name":"Nayses Bay",
    "tgn:placetype":[
        "aat:300132316"
    ]
},
  "bbox": [],
  "geometry": {"coordinates":[-76.8333,37.2667],"type":"Point"}
}