{
  "id": 2406725,
  "type": "Feature",
  "properties": {
    "tgn:hierarchy":[
        "tgn:2406725",
        "tgn:1000001",
        "tgn:2001842",
        "tgn:7012149",
        "tgn:7007825",
        "tgn:7029392"
    ],
    "tgn:id":2406725,
    "tgn:name":"Hunt Lake",
    "tgn:placetype":[
        "aat:300006191"
    ]
},
  "bbox": [],
  "geometry": {"coordinates":[-84.85,35.0833],"type":"Point"}
}