<<<<<<< HEAD
{
  "id": 2406725,
  "type": "Feature",
  "properties": {
    "tgn:hierarchy":[
        "tgn:2406725",
        "tgn:1000001",
        "tgn:2001842",
        "tgn:7012149",
        "tgn:7007825",
        "tgn:7029392"
    ],
    "tgn:id":2406725,
    "tgn:name":"Hunt Lake",
    "tgn:placetype":[
        "aat:300006191"
    ]
},
  "bbox": [],
  "geometry": {"coordinates":[-84.85,35.0833],"type":"Point"}
}
=======
{"geometry":{"type":"Point","coordinates":[-84.850000,35.083300]},"type":"Feature","properties":{"hierarchy":["tgn:2406725","tgn:1000001","tgn:2001842","tgn:7012149","tgn:7007825","tgn:7029392"],"placetype":["aat:300006191"],"id":2406725,"name:xx":"Hunt Lake"}}
>>>>>>> 03f74aca74312dbeaf24d7e61306dd6a786dc3d0
