{
  "id": 7348165,
  "type": "Feature",
  "properties": {
    "tgn:hierarchy":[
        "tgn:7348165",
        "tgn:7002759",
        "tgn:7002845",
        "tgn:1000003",
        "tgn:1000095",
        "tgn:7029392"
    ],
    "tgn:id":7348165,
    "tgn:name":"Ainz\u00f3n",
    "tgn:placetype":[
        "aat:300008347"
    ]
},
  "bbox": [],
  "geometry": {"coordinates":[-1.516667,41.816667],"type":"Point"}
}