{
  "id": 2346901,
  "type": "Feature",
  "properties": {
    "tgn:hierarchy":[
        "tgn:2346901",
        "tgn:1000001",
        "tgn:7012149",
        "tgn:2001619",
        "tgn:7007706",
        "tgn:7029392"
    ],
    "tgn:id":2346901,
    "tgn:name":"Gem",
    "tgn:placetype":[
        "aat:300008347"
    ]
},
  "bbox": [],
  "geometry": {"coordinates":[-81.4167,39.65],"type":"Point"}
}