<<<<<<< HEAD
{
  "id": 2158001,
  "type": "Feature",
  "properties": {
    "tgn:hierarchy":[
        "tgn:2158001",
        "tgn:1000001",
        "tgn:7012149",
        "tgn:2001295",
        "tgn:7007524",
        "tgn:7029392"
    ],
    "tgn:id":2158001,
    "tgn:name":"Beaver Mine",
    "tgn:placetype":[
        "aat:300000390"
    ]
},
  "bbox": [],
  "geometry": {"coordinates":[-108.5167,47.95],"type":"Point"}
}
=======
{"geometry":{"type":"Point","coordinates":[-108.516700,47.950000]},"type":"Feature","properties":{"hierarchy":["tgn:2158001","tgn:1000001","tgn:7012149","tgn:2001295","tgn:7007524","tgn:7029392"],"placetype":["aat:300000390"],"id":2158001,"name:xx":"Beaver Mine"}}
>>>>>>> 03f74aca74312dbeaf24d7e61306dd6a786dc3d0
