{
  "id": 2194944,
  "type": "Feature",
  "properties": {
    "tgn:hierarchy":[
        "tgn:2194944",
        "tgn:1000001",
        "tgn:7012149",
        "tgn:7029392"
    ],
    "tgn:id":2194944,
    "tgn:name":"Bright Hollow",
    "tgn:placetype":[
        "aat:300008761"
    ]
},
  "bbox": [],
  "geometry": {"coordinates":[-82.4167,36.5833],"type":"Point"}
}