{
  "id": 2125491,
  "type": "Feature",
  "properties": {
    "tgn:hierarchy":[
        "tgn:2125491",
        "tgn:1000001",
        "tgn:7012149",
        "tgn:7007157",
        "tgn:1002608",
        "tgn:7029392"
    ],
    "tgn:id":2125491,
    "tgn:name":"Acton Canyon",
    "tgn:placetype":[
        "aat:300008761"
    ]
},
  "bbox": [],
  "geometry": {"coordinates":[-118.15,34.5167],"type":"Point"}
}