{
  "id": 7364736,
  "type": "Feature",
  "properties": {
    "tgn:hierarchy":[
        "tgn:7364736",
        "tgn:7005581",
        "tgn:1000001",
        "tgn:7005560",
        "tgn:7029392"
    ],
    "tgn:id":7364736,
    "tgn:name":"Flores",
    "tgn:placetype":[
        "aat:300008347"
    ]
},
  "bbox": [],
  "geometry": {"coordinates":[-106.566667,31.716667],"type":"Point"}
}