<<<<<<< HEAD
{
  "id": 2707467,
  "type": "Feature",
  "properties": {
    "tgn:hierarchy":[
        "tgn:2707467",
        "tgn:1000001",
        "tgn:7012149",
        "tgn:1002636",
        "tgn:7007708",
        "tgn:7029392"
    ],
    "tgn:id":2707467,
    "tgn:name":"Sweet Spring Creek",
    "tgn:placetype":[
        "aat:300008706"
    ]
},
  "bbox": [],
  "geometry": {"coordinates":[-122.4333,44.85],"type":"Point"}
}
=======
{"geometry":{"type":"Point","coordinates":[-122.433300,44.850000]},"type":"Feature","properties":{"hierarchy":["tgn:2707467","tgn:1000001","tgn:7012149","tgn:1002636","tgn:7007708","tgn:7029392"],"placetype":["aat:300008706"],"id":2707467,"name:xx":"Sweet Spring Creek"}}
>>>>>>> 03f74aca74312dbeaf24d7e61306dd6a786dc3d0
