{
  "id": 2482112,
  "type": "Feature",
  "properties": {
    "tgn:hierarchy":[
        "tgn:2482112",
        "tgn:1000001",
        "tgn:7012149",
        "tgn:2001437",
        "tgn:7007566",
        "tgn:7029392"
    ],
    "tgn:id":2482112,
    "tgn:name":"Laney Spring",
    "tgn:placetype":[
        "aat:300008697"
    ]
},
  "bbox": [],
  "geometry": {"coordinates":[-108.0167,32.95],"type":"Point"}
}