{
  "id": 2264789,
  "type": "Feature",
  "properties": {
    "tgn:hierarchy":[
        "tgn:2264789",
        "tgn:1000001",
        "tgn:2000317",
        "tgn:7012149",
        "tgn:7007248",
        "tgn:7029392"
    ],
    "tgn:id":2264789,
    "tgn:name":"Craig Hill",
    "tgn:placetype":[
        "aat:300008798"
    ]
},
  "bbox": [],
  "geometry": {"coordinates":[-84.9167,32.3333],"type":"Point"}
}