{
  "id": 2443878,
  "type": "Feature",
  "properties": {
    "tgn:hierarchy":[
        "tgn:2443878",
        "tgn:1000001",
        "tgn:7012149",
        "tgn:2000225",
        "tgn:7007158",
        "tgn:7029392"
    ],
    "tgn:id":2443878,
    "tgn:name":"La Plata",
    "tgn:placetype":[
        "aat:300008347"
    ]
},
  "bbox": [],
  "geometry": {"coordinates":[-108.05,37.3833],"type":"Point"}
}