{
  "id": 2004098,
  "type": "Feature",
  "properties": {
    "tgn:hierarchy":[
        "tgn:2004098",
        "tgn:7002659",
        "tgn:1000001",
        "tgn:7012149",
        "tgn:2000049",
        "tgn:7029392"
    ],
    "tgn:id":2004098,
    "tgn:name":"Keith",
    "tgn:placetype":[
        "aat:300387016"
    ]
},
  "bbox": [],
  "geometry": {"coordinates":[-87.35,31.6667],"type":"Point"}
}