{
  "id": 7294264,
  "type": "Feature",
  "properties": {
    "tgn:hierarchy":[
        "tgn:7294264",
        "tgn:7001158",
        "tgn:7002850",
        "tgn:1000003",
        "tgn:1000095",
        "tgn:7029392"
    ],
    "tgn:id":7294264,
    "tgn:name":"Valtorno, Arroyo de",
    "tgn:placetype":[
        "aat:300008699"
    ]
},
  "bbox": [],
  "geometry": {"coordinates":[-6.133333,42.083333],"type":"Point"}
}