{
  "id": 2356781,
  "type": "Feature",
  "properties": {
    "tgn:hierarchy":[
        "tgn:2356781",
        "tgn:7006450",
        "tgn:1000001",
        "tgn:7012149",
        "tgn:2124002",
        "tgn:7029392"
    ],
    "tgn:id":2356781,
    "tgn:name":"Gornoi Island",
    "tgn:placetype":[
        "aat:300008791"
    ]
},
  "bbox": [],
  "geometry": {"coordinates":[-135.35,56.7833],"type":"Point"}
}