{
  "id": 2538927,
  "type": "Feature",
  "properties": {
    "tgn:hierarchy":[
        "tgn:2538927",
        "tgn:7002659",
        "tgn:1000001",
        "tgn:7012149",
        "tgn:2000059",
        "tgn:7029392"
    ],
    "tgn:id":2538927,
    "tgn:name":"New Big Lake",
    "tgn:placetype":[
        "aat:300006191"
    ]
},
  "bbox": [],
  "geometry": {"coordinates":[-88.25,32.85],"type":"Point"}
}