{
  "id": 7322012,
  "type": "Feature",
  "properties": {
    "tgn:hierarchy":[
        "tgn:7322012",
        "tgn:1001630",
        "tgn:1000049",
        "tgn:1000002",
        "tgn:7029392"
    ],
    "tgn:id":7322012,
    "tgn:name":"Bayo, Cerro",
    "tgn:placetype":[
        "aat:300008777"
    ]
},
  "bbox": [],
  "geometry": {"coordinates":[-69.533333,-26.216667],"type":"Point"}
}