{
  "id": 2673091,
  "type": "Feature",
  "properties": {
    "tgn:hierarchy":[
        "tgn:2673091",
        "tgn:1000001",
        "tgn:7012149",
        "tgn:2000226",
        "tgn:7007158",
        "tgn:7029392"
    ],
    "tgn:id":2673091,
    "tgn:name":"Snake Lake",
    "tgn:placetype":[
        "aat:300006191"
    ]
},
  "bbox": [],
  "geometry": {"coordinates":[-105.5667,40.7833],"type":"Point"}
}