{
  "id": 7527545,
  "type": "Feature",
  "properties": {
    "tgn:hierarchy":[
        "tgn:7527545",
        "tgn:7001242",
        "tgn:7016833",
        "tgn:1001114",
        "tgn:7029392"
    ],
    "tgn:id":7527545,
    "tgn:name:en":"S\u012bd\u012b Sul\u0163\u0101n",
    "tgn:placetype":[
        "aat:300005926"
    ]
},
  "bbox": [],
  "geometry": {"coordinates":[30.983333,27.25],"type":"Point"}
}