<<<<<<< HEAD
{
  "id": 2334842,
  "type": "Feature",
  "properties": {
    "tgn:hierarchy":[
        "tgn:2334842",
        "tgn:1000001",
        "tgn:7012149",
        "tgn:2000801",
        "tgn:7007255",
        "tgn:7029392"
    ],
    "tgn:id":2334842,
    "tgn:name":"Fork Spring",
    "tgn:placetype":[
        "aat:300008697"
    ]
},
  "bbox": [],
  "geometry": {"coordinates":[-87.6833,37.2167],"type":"Point"}
}
=======
{"geometry":{"type":"Point","coordinates":[-87.683300,37.216700]},"type":"Feature","properties":{"hierarchy":["tgn:2334842","tgn:1000001","tgn:7012149","tgn:2000801","tgn:7007255","tgn:7029392"],"placetype":["aat:300008697"],"id":2334842,"name:xx":"Fork Spring"}}
>>>>>>> 03f74aca74312dbeaf24d7e61306dd6a786dc3d0
