{
  "id": 7197299,
  "type": "Feature",
  "properties": {
    "tgn:hierarchy":[
        "tgn:7197299",
        "tgn:7003669",
        "tgn:1000003",
        "tgn:7000084",
        "tgn:7029392"
    ],
    "tgn:id":7197299,
    "tgn:name":"Dantl am Hart",
    "tgn:placetype":[
        "aat:300000206"
    ]
},
  "bbox": [],
  "geometry": {"coordinates":[13.216667,48.333333],"type":"Point"}
}