{
  "id": 2686643,
  "type": "Feature",
  "properties": {
    "tgn:hierarchy":[
        "tgn:2686643",
        "tgn:1000001",
        "tgn:7012149",
        "tgn:2001895",
        "tgn:7007825",
        "tgn:7029392"
    ],
    "tgn:id":2686643,
    "tgn:name":"Spring Creek",
    "tgn:placetype":[
        "aat:300008706"
    ]
},
  "bbox": [],
  "geometry": {"coordinates":[-86.6833,35.6833],"type":"Point"}
}