{
  "id": 1075176,
  "type": "Feature",
  "properties": {
    "tgn:hierarchy":[
        "tgn:1075176",
        "tgn:1000004",
        "tgn:1001869",
        "tgn:7000198",
        "tgn:7029392"
    ],
    "tgn:id":1075176,
    "tgn:name:en":"Dholka",
    "tgn:placetype":[
        "aat:300008347"
    ]
},
  "bbox": [],
  "geometry": {"coordinates":[72.466667,22.716667],"type":"Point"}
}