{
  "id": 2055764,
  "type": "Feature",
  "properties": {
    "tgn:hierarchy":[
        "tgn:2055764",
        "tgn:1000001",
        "tgn:7012149",
        "tgn:2001058",
        "tgn:7007521",
        "tgn:7029392"
    ],
    "tgn:id":2055764,
    "tgn:name":"Wilds",
    "tgn:placetype":[
        "aat:300387016"
    ]
},
  "bbox": [],
  "geometry": {"coordinates":[-96.6333,47.7333],"type":"Point"}
}