<<<<<<< HEAD
{
  "id": 2764633,
  "type": "Feature",
  "properties": {
    "tgn:hierarchy":[
        "tgn:2764633",
        "tgn:7002659",
        "tgn:1000001",
        "tgn:7012149",
        "tgn:2000045",
        "tgn:7029392"
    ],
    "tgn:id":2764633,
    "tgn:name":"Whirl Creek",
    "tgn:placetype":[
        "aat:300008706"
    ]
},
  "bbox": [],
  "geometry": {"coordinates":[-87.7667,32.4],"type":"Point"}
}
=======
{"geometry":{"type":"Point","coordinates":[-87.766700,32.400000]},"type":"Feature","properties":{"hierarchy":["tgn:2764633","tgn:7002659","tgn:1000001","tgn:7012149","tgn:2000045","tgn:7029392"],"placetype":["aat:300008706"],"id":2764633,"name:xx":"Whirl Creek"}}
>>>>>>> 03f74aca74312dbeaf24d7e61306dd6a786dc3d0
