{
  "id": 7499725,
  "type": "Feature",
  "properties": {
    "tgn:hierarchy":[
        "tgn:7499725",
        "tgn:1000004",
        "tgn:1000959",
        "tgn:1000141",
        "tgn:7029392"
    ],
    "tgn:id":7499725,
    "tgn:name":"Songshan Gaozhong",
    "tgn:placetype":[
        "aat:300006495"
    ]
},
  "bbox": [],
  "geometry": {"coordinates":[121.565108,25.043772],"type":"Point"}
}