{
  "id": 2405611,
  "type": "Feature",
  "properties": {
    "tgn:hierarchy":[
        "tgn:2405611",
        "tgn:1000001",
        "tgn:7012149",
        "tgn:1002929",
        "tgn:7007240",
        "tgn:7029392"
    ],
    "tgn:id":2405611,
    "tgn:name":"Hughes Pond",
    "tgn:placetype":[
        "aat:300008680"
    ]
},
  "bbox": [],
  "geometry": {"coordinates":[-82.0167,28.6167],"type":"Point"}
}