<<<<<<< HEAD
{
  "id": 2405611,
  "type": "Feature",
  "properties": {
    "tgn:hierarchy":[
        "tgn:2405611",
        "tgn:1000001",
        "tgn:7012149",
        "tgn:1002929",
        "tgn:7007240",
        "tgn:7029392"
    ],
    "tgn:id":2405611,
    "tgn:name":"Hughes Pond",
    "tgn:placetype":[
        "aat:300008680"
    ]
},
  "bbox": [],
  "geometry": {"coordinates":[-82.0167,28.6167],"type":"Point"}
}
=======
{"geometry":{"type":"Point","coordinates":[-82.016700,28.616700]},"type":"Feature","properties":{"hierarchy":["tgn:2405611","tgn:1000001","tgn:7012149","tgn:1002929","tgn:7007240","tgn:7029392"],"placetype":["aat:300008680"],"id":2405611,"name:xx":"Hughes Pond"}}
>>>>>>> 03f74aca74312dbeaf24d7e61306dd6a786dc3d0
