{
  "id": 7559097,
  "type": "Feature",
  "properties": {
    "tgn:hierarchy":[
        "tgn:7559097",
        "tgn:1000004",
        "tgn:7000198",
        "tgn:1001894",
        "tgn:7029392"
    ],
    "tgn:id":7559097,
    "tgn:name:en":"R\u012bthi",
    "tgn:placetype":[
        "aat:300008347"
    ]
},
  "bbox": [],
  "geometry": {"coordinates":[80.141961,23.910768],"type":"Point"}
}