{
  "id": 1137619,
  "type": "Feature",
  "properties": {
    "tgn:hierarchy":[
        "tgn:1137619",
        "tgn:1000004",
        "tgn:7012943",
        "tgn:7014786",
        "tgn:7029392"
    ],
    "tgn:id":1137619,
    "tgn:name":"Karabulak",
    "tgn:placetype":[
        "aat:300008347"
    ]
},
  "bbox": [],
  "geometry": {"coordinates":[84.6667,47.5667],"type":"Point"}
}