{
  "id": 2710207,
  "type": "Feature",
  "properties": {
    "tgn:hierarchy":[
        "tgn:2710207",
        "tgn:7002659",
        "tgn:1000001",
        "tgn:2000010",
        "tgn:7012149",
        "tgn:7029392"
    ],
    "tgn:id":2710207,
    "tgn:name":"Talley Branch",
    "tgn:placetype":[
        "aat:300008699"
    ]
},
  "bbox": [],
  "geometry": {"coordinates":[-86.7167,32.7667],"type":"Point"}
}