{
  "id": 2618642,
  "type": "Feature",
  "properties": {
    "tgn:hierarchy":[
        "tgn:2618642",
        "tgn:1000001",
        "tgn:7012149",
        "tgn:2000837",
        "tgn:7007255",
        "tgn:7029392"
    ],
    "tgn:id":2618642,
    "tgn:name":"Right Fork Malachi Branch",
    "tgn:placetype":[
        "aat:300008699"
    ]
},
  "bbox": [],
  "geometry": {"coordinates":[-82.0667,37.5167],"type":"Point"}
}