{
  "id": 2168055,
  "type": "Feature",
  "properties": {
    "tgn:hierarchy":[
        "tgn:2168055",
        "tgn:1000001",
        "tgn:7012149",
        "tgn:2000824",
        "tgn:7007255",
        "tgn:7029392"
    ],
    "tgn:id":2168055,
    "tgn:name":"Big Elk Creek",
    "tgn:placetype":[
        "aat:300008706"
    ]
},
  "bbox": [],
  "geometry": {"coordinates":[-82.4667,37.85],"type":"Point"}
}