{
  "id": 7592881,
  "type": "Feature",
  "properties": {
    "tgn:hierarchy":[
        "tgn:7592881",
        "tgn:1000004",
        "tgn:7000198",
        "tgn:7000799",
        "tgn:7029392"
    ],
    "tgn:id":7592881,
    "tgn:name:en":"Dhok Baniy\u0101r",
    "tgn:placetype":[
        "aat:300008347"
    ]
},
  "bbox": [],
  "geometry": {"coordinates":[74.410365,33.021771],"type":"Point"}
}