{
  "id": 7454524,
  "type": "Feature",
  "properties": {
    "tgn:hierarchy":[
        "tgn:7454524",
        "tgn:7002445",
        "tgn:1000003",
        "tgn:7008165",
        "tgn:7008591",
        "tgn:7029392"
    ],
    "tgn:id":7454524,
    "tgn:name:en":"Deadwater",
    "tgn:placetype":[
        "aat:300007783"
    ]
},
  "bbox": [],
  "geometry": {"coordinates":[-2.616667,55.25],"type":"Point"}
}