{
  "id": 1042423,
  "type": "Feature",
  "properties": {
    "tgn:hierarchy":[
        "tgn:1042423",
        "tgn:1000385",
        "tgn:1000003",
        "tgn:7006278",
        "tgn:7029392"
    ],
    "tgn:id":1042423,
    "tgn:name":"Ny\u00edradony",
    "tgn:placetype":[
        "aat:300008347"
    ]
},
  "bbox": [],
  "geometry": {"coordinates":[21.95,47.6833],"type":"Point"}
}