{
  "id": 7498376,
  "type": "Feature",
  "properties": {
    "tgn:hierarchy":[
        "tgn:7498376",
        "tgn:7001004",
        "tgn:1000004",
        "tgn:1000141",
        "tgn:7029392"
    ],
    "tgn:id":7498376,
    "tgn:name":"Sixi Shan",
    "tgn:placetype":[
        "aat:300008798"
    ]
},
  "bbox": [],
  "geometry": {"coordinates":[120.779731,23.322075],"type":"Point"}
}