{
  "id": 2211477,
  "type": "Feature",
  "properties": {
    "tgn:hierarchy":[
        "tgn:2211477",
        "tgn:1000001",
        "tgn:7012149",
        "tgn:7021313",
        "tgn:7007521",
        "tgn:7029392"
    ],
    "tgn:id":2211477,
    "tgn:name":"Butterfield Harbor",
    "tgn:placetype":[
        "aat:300008678"
    ]
},
  "bbox": [],
  "geometry": {"coordinates":[-94.85,49.3167],"type":"Point"}
}