{
  "id": 2505888,
  "type": "Feature",
  "properties": {
    "tgn:hierarchy":[
        "tgn:2505888",
        "tgn:1000001",
        "tgn:7012149",
        "tgn:2000450",
        "tgn:7007248",
        "tgn:7029392"
    ],
    "tgn:id":2505888,
    "tgn:name":"Mercer Millpond",
    "tgn:placetype":[
        "aat:300008680"
    ]
},
  "bbox": [],
  "geometry": {"coordinates":[-83.9833,31.6667],"type":"Point"}
}