{
  "id": 7369506,
  "type": "Feature",
  "properties": {
    "tgn:hierarchy":[
        "tgn:7369506",
        "tgn:7005583",
        "tgn:1000001",
        "tgn:7005560",
        "tgn:7029392"
    ],
    "tgn:id":7369506,
    "tgn:name":"Jabali, Cerro del",
    "tgn:placetype":[
        "aat:300008795"
    ]
},
  "bbox": [],
  "geometry": {"coordinates":[-104.416667,25.933333],"type":"Point"}
}