{
  "id": 2135679,
  "type": "Feature",
  "properties": {
    "tgn:hierarchy":[
        "tgn:2135679",
        "tgn:1000001",
        "tgn:7012149",
        "tgn:2001449",
        "tgn:7007566",
        "tgn:7029392"
    ],
    "tgn:id":2135679,
    "tgn:name":"Apache del Ojito, Ca\u00f1ada del",
    "tgn:placetype":[
        "aat:300008699"
    ]
},
  "bbox": [],
  "geometry": {"coordinates":[-105.85,36.0833],"type":"Point"}
}