{
  "id": 2632604,
  "type": "Feature",
  "properties": {
    "tgn:hierarchy":[
        "tgn:2632604",
        "tgn:1000001",
        "tgn:7012149",
        "tgn:2002154",
        "tgn:7007919",
        "tgn:7029392"
    ],
    "tgn:id":2632604,
    "tgn:name":"Ruben Springs Hollow",
    "tgn:placetype":[
        "aat:300008761"
    ]
},
  "bbox": [],
  "geometry": {"coordinates":[-80.3167,37.3667],"type":"Point"}
}