<<<<<<< HEAD
{
  "id": 7487401,
  "type": "Feature",
  "properties": {
    "tgn:hierarchy":[
        "tgn:7487401",
        "tgn:1000004",
        "tgn:7490934",
        "tgn:1000141",
        "tgn:7029392"
    ],
    "tgn:id":7487401,
    "tgn:name":"Xidiliao",
    "tgn:placetype":[
        "aat:300008347"
    ]
},
  "bbox": [],
  "geometry": {"coordinates":[120.2686,23.1686],"type":"Point"}
}
=======
{"geometry":{"type":"Point","coordinates":[120.268600,23.168600]},"type":"Feature","properties":{"hierarchy":["tgn:7487401","tgn:1000004","tgn:7490934","tgn:1000141","tgn:7029392"],"placetype":["aat:300008347"],"id":7487401,"name:xx":"Xidiliao"}}
>>>>>>> 03f74aca74312dbeaf24d7e61306dd6a786dc3d0
