{
  "id": 7487401,
  "type": "Feature",
  "properties": {
    "tgn:hierarchy":[
        "tgn:7487401",
        "tgn:1000004",
        "tgn:7490934",
        "tgn:1000141",
        "tgn:7029392"
    ],
    "tgn:id":7487401,
    "tgn:name":"Xidiliao",
    "tgn:placetype":[
        "aat:300008347"
    ]
},
  "bbox": [],
  "geometry": {"coordinates":[120.2686,23.1686],"type":"Point"}
}