{
  "id": 7399332,
  "type": "Feature",
  "properties": {
    "tgn:hierarchy":[
        "tgn:7399332",
        "tgn:1000001",
        "tgn:7005593",
        "tgn:7005560",
        "tgn:7029392"
    ],
    "tgn:id":7399332,
    "tgn:name":"El Ranchito",
    "tgn:placetype":[
        "aat:300008347"
    ]
},
  "bbox": [],
  "geometry": {"coordinates":[-100.408333,20.491667],"type":"Point"}
}