{
  "id": 7124068,
  "type": "Feature",
  "properties": {
    "tgn:hierarchy":[
        "tgn:7124068",
        "tgn:1000003",
        "tgn:7003677",
        "tgn:7000084",
        "tgn:7029392"
    ],
    "tgn:id":7124068,
    "tgn:name":"Niederhalen",
    "tgn:placetype":[
        "aat:300000206"
    ]
},
  "bbox": [],
  "geometry": {"coordinates":[6.683333,51.483333],"type":"Point"}
}