{
  "id": 7486264,
  "type": "Feature",
  "properties": {
    "tgn:hierarchy":[
        "tgn:7486264",
        "tgn:1000957",
        "tgn:1000004",
        "tgn:1000141",
        "tgn:7029392"
    ],
    "tgn:id":7486264,
    "tgn:name":"Lantougou",
    "tgn:placetype":[
        "aat:300008347"
    ]
},
  "bbox": [],
  "geometry": {"coordinates":[121.779668,25.149057],"type":"Point"}
}