{
  "id": 7522315,
  "type": "Feature",
  "properties": {
    "tgn:hierarchy":[
        "tgn:7522315",
        "tgn:7001242",
        "tgn:7016833",
        "tgn:1001225",
        "tgn:7029392"
    ],
    "tgn:id":7522315,
    "tgn:name:en":"Dayr, Tall ad",
    "tgn:placetype":[
        "aat:300008777"
    ]
},
  "bbox": [],
  "geometry": {"coordinates":[31.696111,31.431667],"type":"Point"}
}