{
  "id": 7016699,
  "type": "Feature",
  "properties": {
    "tgn:hierarchy":[
        "tgn:7016699",
        "tgn:7000419",
        "tgn:7018452",
        "tgn:1000004",
        "tgn:1000144",
        "tgn:7029392"
    ],
    "tgn:id":7016699,
    "tgn:name":"Karamanl\u0131",
    "tgn:placetype":[
        "aat:300008347"
    ]
},
  "bbox": [],
  "geometry": {"coordinates":[29.7833,37.3667],"type":"Point"}
}