{
  "id": 7351797,
  "type": "Feature",
  "properties": {
    "tgn:hierarchy":[
        "tgn:7351797",
        "tgn:7005584",
        "tgn:1000001",
        "tgn:7005560",
        "tgn:7029392"
    ],
    "tgn:id":7351797,
    "tgn:name":"Boquillas",
    "tgn:placetype":[
        "aat:300008347"
    ]
},
  "bbox": [],
  "geometry": {"coordinates":[-101.433333,20.416667],"type":"Point"}
}