{
  "id": 2276680,
  "type": "Feature",
  "properties": {
    "tgn:hierarchy":[
        "tgn:2276680",
        "tgn:1000001",
        "tgn:7012149",
        "tgn:2001307",
        "tgn:7007524",
        "tgn:7029392"
    ],
    "tgn:id":2276680,
    "tgn:name":"Davidson Creek",
    "tgn:placetype":[
        "aat:300008706"
    ]
},
  "bbox": [],
  "geometry": {"coordinates":[-109.6167,45.4833],"type":"Point"}
}