{
  "id": 7567743,
  "type": "Feature",
  "properties": {
    "tgn:hierarchy":[
        "tgn:7567743",
        "tgn:1001828",
        "tgn:1000004",
        "tgn:7000198",
        "tgn:7029392"
    ],
    "tgn:id":7567743,
    "tgn:name:en":"R\u0101m\u0101yanpalli",
    "tgn:placetype":[
        "aat:300008347"
    ]
},
  "bbox": [],
  "geometry": {"coordinates":[78.326111,17.943611],"type":"Point"}
}