<<<<<<< HEAD
{
  "id": 2150421,
  "type": "Feature",
  "properties": {
    "tgn:hierarchy":[
        "tgn:2150421",
        "tgn:1000001",
        "tgn:7012149",
        "tgn:2002384",
        "tgn:7007923",
        "tgn:7029392"
    ],
    "tgn:id":2150421,
    "tgn:name":"Basin Creek Lake",
    "tgn:placetype":[
        "aat:300008680"
    ]
},
  "bbox": [],
  "geometry": {"coordinates":[-110.5167,44.2],"type":"Point"}
}
=======
{"geometry":{"type":"Point","coordinates":[-110.516700,44.200000]},"type":"Feature","properties":{"hierarchy":["tgn:2150421","tgn:1000001","tgn:7012149","tgn:2002384","tgn:7007923","tgn:7029392"],"placetype":["aat:300008680"],"id":2150421,"name:xx":"Basin Creek Lake"}}
>>>>>>> 03f74aca74312dbeaf24d7e61306dd6a786dc3d0
