{
  "id": 2296868,
  "type": "Feature",
  "properties": {
    "tgn:hierarchy":[
        "tgn:2296868",
        "tgn:1000001",
        "tgn:7012149",
        "tgn:1002629",
        "tgn:7007523",
        "tgn:7029392"
    ],
    "tgn:id":2296868,
    "tgn:name":"Dry Creek",
    "tgn:placetype":[
        "aat:300008706"
    ]
},
  "bbox": [],
  "geometry": {"coordinates":[-92.0167,38.05],"type":"Point"}
}