{
  "id": 7139930,
  "type": "Feature",
  "properties": {
    "tgn:hierarchy":[
        "tgn:7139930",
        "tgn:1000003",
        "tgn:7003689",
        "tgn:7000084",
        "tgn:7029392"
    ],
    "tgn:id":7139930,
    "tgn:name":"Langenfeld, Forst",
    "tgn:placetype":[
        "aat:300008863"
    ]
},
  "bbox": [],
  "geometry": {"coordinates":[10.216667,50.766667],"type":"Point"}
}