{
  "id": 7289347,
  "type": "Feature",
  "properties": {
    "tgn:hierarchy":[
        "tgn:7289347",
        "tgn:7002464",
        "tgn:1000049",
        "tgn:1000002",
        "tgn:7029392"
    ],
    "tgn:id":7289347,
    "tgn:name":"Huaylican",
    "tgn:placetype":[
        "aat:300004792"
    ]
},
  "bbox": [],
  "geometry": {"coordinates":[-70.233333,-18.416667],"type":"Point"}
}