{
  "id": 2540061,
  "type": "Feature",
  "properties": {
    "tgn:hierarchy":[
        "tgn:2540061",
        "tgn:1000001",
        "tgn:7016172",
        "tgn:7012149",
        "tgn:2000129",
        "tgn:7029392"
    ],
    "tgn:id":2540061,
    "tgn:name":"Newcomb Branch",
    "tgn:placetype":[
        "aat:300008699"
    ]
},
  "bbox": [],
  "geometry": {"coordinates":[-91.8167,36.4833],"type":"Point"}
}