{
  "id": 7422669,
  "type": "Feature",
  "properties": {
    "tgn:hierarchy":[
        "tgn:7422669",
        "tgn:1000001",
        "tgn:1001960",
        "tgn:7005560",
        "tgn:7029392"
    ],
    "tgn:id":7422669,
    "tgn:name":"El Pilar",
    "tgn:placetype":[
        "aat:300008347"
    ]
},
  "bbox": [],
  "geometry": {"coordinates":[-110.983333,27.966667],"type":"Point"}
}