{
  "id": 2705795,
  "type": "Feature",
  "properties": {
    "tgn:hierarchy":[
        "tgn:2705795",
        "tgn:7006450",
        "tgn:1000001",
        "tgn:7012149",
        "tgn:2000082",
        "tgn:7029392"
    ],
    "tgn:id":2705795,
    "tgn:name":"Sutter Lake",
    "tgn:placetype":[
        "aat:300008680"
    ]
},
  "bbox": [],
  "geometry": {"coordinates":[-133.4333,56.1333],"type":"Point"}
}