{
  "id": 1112652,
  "type": "Feature",
  "properties": {
    "tgn:hierarchy":[
        "tgn:1112652",
        "tgn:1000004",
        "tgn:7016720",
        "tgn:1000135",
        "tgn:7029392"
    ],
    "tgn:id":1112652,
    "tgn:name":"Basiad Bay",
    "tgn:placetype":[
        "aat:300132316"
    ]
},
  "bbox": [],
  "geometry": {"coordinates":[122.3167,14.2667],"type":"Point"}
}