{
  "id": 2459178,
  "type": "Feature",
  "properties": {
    "tgn:hierarchy":[
        "tgn:2459178",
        "tgn:2002143",
        "tgn:1000001",
        "tgn:7012149",
        "tgn:7007919",
        "tgn:7029392"
    ],
    "tgn:id":2459178,
    "tgn:name":"Little Piney Hollow",
    "tgn:placetype":[
        "aat:300008761"
    ]
},
  "bbox": [],
  "geometry": {"coordinates":[-79.95,38.0167],"type":"Point"}
}