{
  "id": 7076182,
  "type": "Feature",
  "properties": {
    "tgn:hierarchy":[
        "tgn:7076182",
        "tgn:7003669",
        "tgn:1000003",
        "tgn:7000084",
        "tgn:7029392"
    ],
    "tgn:id":7076182,
    "tgn:name":"Zinn",
    "tgn:placetype":[
        "aat:300006891"
    ]
},
  "bbox": [],
  "geometry": {"coordinates":[12.116667,48.633333],"type":"Point"}
}