{
  "id": 7591019,
  "type": "Feature",
  "properties": {
    "tgn:hierarchy":[
        "tgn:7591019",
        "tgn:1000004",
        "tgn:7000198",
        "tgn:7000799",
        "tgn:7029392"
    ],
    "tgn:id":7591019,
    "tgn:name:en":"Man\u0101war Tawi",
    "tgn:placetype":[
        "aat:300008699"
    ]
},
  "bbox": [],
  "geometry": {"coordinates":[74.412018,32.937725],"type":"Point"}
}