<<<<<<< HEAD
{
  "id": 7373169,
  "type": "Feature",
  "properties": {
    "tgn:hierarchy":[
        "tgn:7373169",
        "tgn:1001853",
        "tgn:1000001",
        "tgn:7005560",
        "tgn:7029392"
    ],
    "tgn:id":7373169,
    "tgn:name":"La Palma, Valle de",
    "tgn:placetype":[
        "aat:300008761"
    ]
},
  "bbox": [],
  "geometry": {"coordinates":[-102.216667,28.1],"type":"Point"}
}
=======
{"geometry":{"type":"Point","coordinates":[-102.216667,28.100000]},"type":"Feature","properties":{"hierarchy":["tgn:7373169","tgn:1001853","tgn:1000001","tgn:7005560","tgn:7029392"],"placetype":["aat:300008761"],"id":7373169,"name:xx":"La Palma, Valle de"}}
>>>>>>> 03f74aca74312dbeaf24d7e61306dd6a786dc3d0
