{
  "id": 2181010,
  "type": "Feature",
  "properties": {
    "tgn:hierarchy":[
        "tgn:2181010",
        "tgn:1000001",
        "tgn:7012149",
        "tgn:1002676",
        "tgn:7007240",
        "tgn:7029392"
    ],
    "tgn:id":2181010,
    "tgn:name":"Blue Bank",
    "tgn:placetype":[
        "aat:300132348"
    ]
},
  "bbox": [],
  "geometry": {"coordinates":[-80.95,24.9833],"type":"Point"}
}