{
  "id": 2034226,
  "type": "Feature",
  "properties": {
    "tgn:hierarchy":[
        "tgn:2034226",
        "tgn:1000001",
        "tgn:7012149",
        "tgn:2000547",
        "tgn:7007252",
        "tgn:7029392"
    ],
    "tgn:id":2034226,
    "tgn:name":"Yountsville",
    "tgn:placetype":[
        "aat:300008347"
    ]
},
  "bbox": [],
  "geometry": {"coordinates":[-86.9667,40.0167],"type":"Point"}
}