{
  "id": 2363556,
  "type": "Feature",
  "properties": {
    "tgn:hierarchy":[
        "tgn:2363556",
        "tgn:1000001",
        "tgn:2000922",
        "tgn:7012149",
        "tgn:7007515",
        "tgn:7029392"
    ],
    "tgn:id":2363556,
    "tgn:name":"Green Head",
    "tgn:placetype":[
        "aat:300008850"
    ]
},
  "bbox": [],
  "geometry": {"coordinates":[-68.6667,44.15],"type":"Point"}
}