{
  "id": 1115765,
  "type": "Feature",
  "properties": {
    "tgn:hierarchy":[
        "tgn:1115765",
        "tgn:7005685",
        "tgn:1000001",
        "tgn:7013154",
        "tgn:7029392"
    ],
    "tgn:id":1115765,
    "tgn:name":"Calabogie Lake",
    "tgn:placetype":[
        "aat:300008680"
    ]
},
  "bbox": [],
  "geometry": {"coordinates":[-76.75,45.2667],"type":"Point"}
}