{
  "id": 7017944,
  "type": "Feature",
  "properties": {
    "tgn:hierarchy":[
        "tgn:7017944",
        "tgn:7001242",
        "tgn:7029392"
    ],
    "tgn:id":7017944,
    "tgn:name":"Gambia",
    "tgn:placetype":[
        "aat:300008707"
    ]
},
  "bbox": [],
  "geometry": {"coordinates":[-16.5667,13.4667],"type":"Point"}
}