<<<<<<< HEAD
{
  "id": 2403996,
  "type": "Feature",
  "properties": {
    "tgn:hierarchy":[
        "tgn:2403996",
        "tgn:1000001",
        "tgn:2001264",
        "tgn:7012149",
        "tgn:7007524",
        "tgn:7029392"
    ],
    "tgn:id":2403996,
    "tgn:name":"Howell Gulch",
    "tgn:placetype":[
        "aat:300008761"
    ]
},
  "bbox": [],
  "geometry": {"coordinates":[-109.25,45.1],"type":"Point"}
}
=======
{"geometry":{"type":"Point","coordinates":[-109.250000,45.100000]},"type":"Feature","properties":{"hierarchy":["tgn:2403996","tgn:1000001","tgn:2001264","tgn:7012149","tgn:7007524","tgn:7029392"],"placetype":["aat:300008761"],"id":2403996,"name:xx":"Howell Gulch"}}
>>>>>>> 03f74aca74312dbeaf24d7e61306dd6a786dc3d0
