{
  "id": 7291903,
  "type": "Feature",
  "properties": {
    "tgn:hierarchy":[
        "tgn:7291903",
        "tgn:1001699",
        "tgn:1000049",
        "tgn:1000002",
        "tgn:7029392"
    ],
    "tgn:id":7291903,
    "tgn:name":"Emma, Isla",
    "tgn:placetype":[
        "aat:300008791"
    ]
},
  "bbox": [],
  "geometry": {"coordinates":[-73.713056,-43.940556],"type":"Point"}
}