{
  "id": 2431430,
  "type": "Feature",
  "properties": {
    "tgn:hierarchy":[
        "tgn:2431430",
        "tgn:1000001",
        "tgn:2000459",
        "tgn:7012149",
        "tgn:7007250",
        "tgn:7029392"
    ],
    "tgn:id":2431430,
    "tgn:name":"Karney Creek",
    "tgn:placetype":[
        "aat:300008706"
    ]
},
  "bbox": [],
  "geometry": {"coordinates":[-116.0667,43.6833],"type":"Point"}
}