{
  "id": 7559912,
  "type": "Feature",
  "properties": {
    "tgn:hierarchy":[
        "tgn:7559912",
        "tgn:1000004",
        "tgn:7000198",
        "tgn:7016722",
        "tgn:7029392"
    ],
    "tgn:id":7559912,
    "tgn:name:en":"Nagla T\u0101r",
    "tgn:placetype":[
        "aat:300008347"
    ]
},
  "bbox": [],
  "geometry": {"coordinates":[79.275585,27.244115],"type":"Point"}
}