{
  "id": 2419227,
  "type": "Feature",
  "properties": {
    "tgn:hierarchy":[
        "tgn:2419227",
        "tgn:1000001",
        "tgn:1002200",
        "tgn:7012149",
        "tgn:7007240",
        "tgn:7029392"
    ],
    "tgn:id":2419227,
    "tgn:name":"Jane Green Swamp",
    "tgn:placetype":[
        "aat:300008905"
    ]
},
  "bbox": [],
  "geometry": {"coordinates":[-80.8333,28.0333],"type":"Point"}
}