{
  "id": 7372010,
  "type": "Feature",
  "properties": {
    "tgn:hierarchy":[
        "tgn:7372010",
        "tgn:1001836",
        "tgn:1000001",
        "tgn:7005560",
        "tgn:7029392"
    ],
    "tgn:id":7372010,
    "tgn:name":"Landing",
    "tgn:placetype":[
        "aat:300008347"
    ]
},
  "bbox": [],
  "geometry": {"coordinates":[-111.916667,24.716667],"type":"Point"}
}