{
  "id": 2764725,
  "type": "Feature",
  "properties": {
    "tgn:hierarchy":[
        "tgn:2764725",
        "tgn:1000001",
        "tgn:7012149",
        "tgn:7007157",
        "tgn:2000189",
        "tgn:7029392"
    ],
    "tgn:id":2764725,
    "tgn:name":"Whiskey Creek",
    "tgn:placetype":[
        "aat:300008706"
    ]
},
  "bbox": [],
  "geometry": {"coordinates":[-121.9333,41.2167],"type":"Point"}
}