{
  "id": 2394683,
  "type": "Feature",
  "properties": {
    "tgn:hierarchy":[
        "tgn:2394683",
        "tgn:1000001",
        "tgn:7012149",
        "tgn:7007920",
        "tgn:7029392"
    ],
    "tgn:id":2394683,
    "tgn:name":"Hoh Creek",
    "tgn:placetype":[
        "aat:300008706"
    ]
},
  "bbox": [],
  "geometry": {"coordinates":[-123.7833,47.8833],"type":"Point"}
}