{
  "id": 7415332,
  "type": "Feature",
  "properties": {
    "tgn:hierarchy":[
        "tgn:7415332",
        "tgn:1000001",
        "tgn:7005591",
        "tgn:7005560",
        "tgn:7029392"
    ],
    "tgn:id":7415332,
    "tgn:name:es":"Pueblo Viejo",
    "tgn:placetype":[
        "aat:300008347"
    ]
},
  "bbox": [],
  "geometry": {"coordinates":[-97.264167,17.150556],"type":"Point"}
}