{
  "id": 1097062,
  "type": "Feature",
  "properties": {
    "tgn:hierarchy":[
        "tgn:1097062",
        "tgn:7000490",
        "tgn:1000006",
        "tgn:7006238",
        "tgn:7029392"
    ],
    "tgn:id":1097062,
    "tgn:name":"Hallam",
    "tgn:placetype":[
        "aat:300008347"
    ]
},
  "bbox": [],
  "geometry": {"coordinates":[145.2667,-38.0167],"type":"Point"}
}