{
  "id": 2249927,
  "type": "Feature",
  "properties": {
    "tgn:hierarchy":[
        "tgn:2249927",
        "tgn:1000001",
        "tgn:7012149",
        "tgn:2001716",
        "tgn:7007708",
        "tgn:7029392"
    ],
    "tgn:id":2249927,
    "tgn:name":"Collier Cone",
    "tgn:placetype":[
        "aat:300008798"
    ]
},
  "bbox": [],
  "geometry": {"coordinates":[-121.7833,44.1833],"type":"Point"}
}