{
  "id": 2530603,
  "type": "Feature",
  "properties": {
    "tgn:hierarchy":[
        "tgn:2530603",
        "tgn:1000001",
        "tgn:7012149",
        "tgn:2002385",
        "tgn:7007923",
        "tgn:7029392"
    ],
    "tgn:id":2530603,
    "tgn:name":"Muddy Creek",
    "tgn:placetype":[
        "aat:300008706"
    ]
},
  "bbox": [],
  "geometry": {"coordinates":[-110.65,41.1667],"type":"Point"}
}