<<<<<<< HEAD
{
  "id": 2258526,
  "type": "Feature",
  "properties": {
    "tgn:hierarchy":[
        "tgn:2258526",
        "tgn:1000001",
        "tgn:7012149",
        "tgn:2001152",
        "tgn:7007522",
        "tgn:7029392"
    ],
    "tgn:id":2258526,
    "tgn:name":"Cottondale",
    "tgn:placetype":[
        "aat:300008347"
    ]
},
  "bbox": [],
  "geometry": {"coordinates":[-90.5333,33.6833],"type":"Point"}
}
=======
{"geometry":{"type":"Point","coordinates":[-90.533300,33.683300]},"type":"Feature","properties":{"hierarchy":["tgn:2258526","tgn:1000001","tgn:7012149","tgn:2001152","tgn:7007522","tgn:7029392"],"placetype":["aat:300008347"],"id":2258526,"name:xx":"Cottondale"}}
>>>>>>> 03f74aca74312dbeaf24d7e61306dd6a786dc3d0
