{
  "id": 2258526,
  "type": "Feature",
  "properties": {
    "tgn:hierarchy":[
        "tgn:2258526",
        "tgn:1000001",
        "tgn:7012149",
        "tgn:2001152",
        "tgn:7007522",
        "tgn:7029392"
    ],
    "tgn:id":2258526,
    "tgn:name":"Cottondale",
    "tgn:placetype":[
        "aat:300008347"
    ]
},
  "bbox": [],
  "geometry": {"coordinates":[-90.5333,33.6833],"type":"Point"}
}