{
  "id": 2341016,
  "type": "Feature",
  "properties": {
    "tgn:hierarchy":[
        "tgn:2341016",
        "tgn:1000001",
        "tgn:7012149",
        "tgn:7014398",
        "tgn:7013961",
        "tgn:7029392"
    ],
    "tgn:id":2341016,
    "tgn:name":"Friends Run",
    "tgn:placetype":[
        "aat:300008699"
    ]
},
  "bbox": [],
  "geometry": {"coordinates":[-79.4333,38.65],"type":"Point"}
}