<<<<<<< HEAD
{
  "id": 2336998,
  "type": "Feature",
  "properties": {
    "tgn:hierarchy":[
        "tgn:2336998",
        "tgn:1000001",
        "tgn:7012149",
        "tgn:7007157",
        "tgn:2000189",
        "tgn:7029392"
    ],
    "tgn:id":2336998,
    "tgn:name":"Fourmile Hill",
    "tgn:placetype":[
        "aat:300008798"
    ]
},
  "bbox": [],
  "geometry": {"coordinates":[-121.6,41.6333],"type":"Point"}
}
=======
{"geometry":{"type":"Point","coordinates":[-121.600000,41.633300]},"type":"Feature","properties":{"hierarchy":["tgn:2336998","tgn:1000001","tgn:7012149","tgn:7007157","tgn:2000189","tgn:7029392"],"placetype":["aat:300008798"],"id":2336998,"name:xx":"Fourmile Hill"}}
>>>>>>> 03f74aca74312dbeaf24d7e61306dd6a786dc3d0
