{
  "id": 2172810,
  "type": "Feature",
  "properties": {
    "tgn:hierarchy":[
        "tgn:2172810",
        "tgn:1000001",
        "tgn:7006451",
        "tgn:2000092",
        "tgn:7012149",
        "tgn:7029392"
    ],
    "tgn:id":2172810,
    "tgn:name":"Billy Back Spring",
    "tgn:placetype":[
        "aat:300008697"
    ]
},
  "bbox": [],
  "geometry": {"coordinates":[-111.3333,35.0167],"type":"Point"}
}