<<<<<<< HEAD
{
  "id": 2405254,
  "type": "Feature",
  "properties": {
    "tgn:hierarchy":[
        "tgn:2405254",
        "tgn:1000001",
        "tgn:7012149",
        "tgn:2001851",
        "tgn:7007825",
        "tgn:7029392"
    ],
    "tgn:id":2405254,
    "tgn:name":"Huff Prospect",
    "tgn:placetype":[
        "aat:300000390"
    ]
},
  "bbox": [],
  "geometry": {"coordinates":[-83.0333,35.9333],"type":"Point"}
}
=======
{"geometry":{"type":"Point","coordinates":[-83.033300,35.933300]},"type":"Feature","properties":{"hierarchy":["tgn:2405254","tgn:1000001","tgn:7012149","tgn:2001851","tgn:7007825","tgn:7029392"],"placetype":["aat:300000390"],"id":2405254,"name:xx":"Huff Prospect"}}
>>>>>>> 03f74aca74312dbeaf24d7e61306dd6a786dc3d0
