{
  "id": 2632980,
  "type": "Feature",
  "properties": {
    "tgn:hierarchy":[
        "tgn:2632980",
        "tgn:1000001",
        "tgn:7006451",
        "tgn:2000092",
        "tgn:7012149",
        "tgn:7029392"
    ],
    "tgn:id":2632980,
    "tgn:name":"Rudds Tank",
    "tgn:placetype":[
        "aat:300006191"
    ]
},
  "bbox": [],
  "geometry": {"coordinates":[-111.7333,35.2333],"type":"Point"}
}