<<<<<<< HEAD
{
  "id": 2402440,
  "type": "Feature",
  "properties": {
    "tgn:hierarchy":[
        "tgn:2402440",
        "tgn:1000001",
        "tgn:7012149",
        "tgn:1002879",
        "tgn:7007252",
        "tgn:7029392"
    ],
    "tgn:id":2402440,
    "tgn:name":"Hosea Lake",
    "tgn:placetype":[
        "aat:300006191"
    ]
},
  "bbox": [],
  "geometry": {"coordinates":[-85.8167,38.6833],"type":"Point"}
}
=======
{"geometry":{"type":"Point","coordinates":[-85.816700,38.683300]},"type":"Feature","properties":{"hierarchy":["tgn:2402440","tgn:1000001","tgn:7012149","tgn:1002879","tgn:7007252","tgn:7029392"],"placetype":["aat:300006191"],"id":2402440,"name:xx":"Hosea Lake"}}
>>>>>>> 03f74aca74312dbeaf24d7e61306dd6a786dc3d0
