<<<<<<< HEAD
{
  "id": 2402240,
  "type": "Feature",
  "properties": {
    "tgn:hierarchy":[
        "tgn:2402240",
        "tgn:1000001",
        "tgn:7012149",
        "tgn:2000226",
        "tgn:7007158",
        "tgn:7029392"
    ],
    "tgn:id":2402240,
    "tgn:name":"Horsetooth Reservoir",
    "tgn:placetype":[
        "aat:300006191"
    ]
},
  "bbox": [],
  "geometry": {"coordinates":[-105.1667,40.5833],"type":"Point"}
}
=======
{"geometry":{"type":"Point","coordinates":[-105.166700,40.583300]},"type":"Feature","properties":{"hierarchy":["tgn:2402240","tgn:1000001","tgn:7012149","tgn:2000226","tgn:7007158","tgn:7029392"],"placetype":["aat:300006191"],"id":2402240,"name:xx":"Horsetooth Reservoir"}}
>>>>>>> 03f74aca74312dbeaf24d7e61306dd6a786dc3d0
