{
  "id": 2402240,
  "type": "Feature",
  "properties": {
    "tgn:hierarchy":[
        "tgn:2402240",
        "tgn:1000001",
        "tgn:7012149",
        "tgn:2000226",
        "tgn:7007158",
        "tgn:7029392"
    ],
    "tgn:id":2402240,
    "tgn:name":"Horsetooth Reservoir",
    "tgn:placetype":[
        "aat:300006191"
    ]
},
  "bbox": [],
  "geometry": {"coordinates":[-105.1667,40.5833],"type":"Point"}
}