{
  "id": 7088555,
  "type": "Feature",
  "properties": {
    "tgn:hierarchy":[
        "tgn:7088555",
        "tgn:1000003",
        "tgn:7003678",
        "tgn:7000084",
        "tgn:7029392"
    ],
    "tgn:id":7088555,
    "tgn:name":"W\u00e4lse-Bach",
    "tgn:placetype":[
        "aat:300008699"
    ]
},
  "bbox": [],
  "geometry": {"coordinates":[9.566667,50.833333],"type":"Point"}
}