{
  "id": 2481743,
  "type": "Feature",
  "properties": {
    "tgn:hierarchy":[
        "tgn:2481743",
        "tgn:1000001",
        "tgn:7012149",
        "tgn:2001201",
        "tgn:7007523",
        "tgn:7029392"
    ],
    "tgn:id":2481743,
    "tgn:name":"Landes Lake",
    "tgn:placetype":[
        "aat:300006191"
    ]
},
  "bbox": [],
  "geometry": {"coordinates":[-93.8667,40.2833],"type":"Point"}
}