{
  "id": 7145340,
  "type": "Feature",
  "properties": {
    "tgn:hierarchy":[
        "tgn:7145340",
        "tgn:7003669",
        "tgn:1000003",
        "tgn:7000084",
        "tgn:7029392"
    ],
    "tgn:id":7145340,
    "tgn:name":"Knogl",
    "tgn:placetype":[
        "aat:300000206"
    ]
},
  "bbox": [],
  "geometry": {"coordinates":[12.05,47.95],"type":"Point"}
}