{
  "id": 1018679,
  "type": "Feature",
  "properties": {
    "tgn:hierarchy":[
        "tgn:1018679",
        "tgn:7005586",
        "tgn:1000001",
        "tgn:7005560",
        "tgn:7029392"
    ],
    "tgn:id":1018679,
    "tgn:name":"Zapotlanejo",
    "tgn:placetype":[
        "aat:300008347"
    ]
},
  "bbox": [],
  "geometry": {"coordinates":[-103.066667,20.633333],"type":"Point"}
}