{
  "id": 2138145,
  "type": "Feature",
  "properties": {
    "tgn:hierarchy":[
        "tgn:2138145",
        "tgn:1000001",
        "tgn:7006451",
        "tgn:2000091",
        "tgn:7012149",
        "tgn:7029392"
    ],
    "tgn:id":2138145,
    "tgn:name":"Art Hill",
    "tgn:placetype":[
        "aat:300266640"
    ]
},
  "bbox": [],
  "geometry": {"coordinates":[-109.9167,31.4333],"type":"Point"}
}