<<<<<<< HEAD
{
  "id": 2254598,
  "type": "Feature",
  "properties": {
    "tgn:hierarchy":[
        "tgn:2254598",
        "tgn:1000001",
        "tgn:7012149",
        "tgn:2001887",
        "tgn:7007825",
        "tgn:7029392"
    ],
    "tgn:id":2254598,
    "tgn:name":"Coon Hollow",
    "tgn:placetype":[
        "aat:300008761"
    ]
},
  "bbox": [],
  "geometry": {"coordinates":[-87.5333,35.5833],"type":"Point"}
}
=======
{"geometry":{"type":"Point","coordinates":[-87.533300,35.583300]},"type":"Feature","properties":{"hierarchy":["tgn:2254598","tgn:1000001","tgn:7012149","tgn:2001887","tgn:7007825","tgn:7029392"],"placetype":["aat:300008761"],"id":2254598,"name:xx":"Coon Hollow"}}
>>>>>>> 03f74aca74312dbeaf24d7e61306dd6a786dc3d0
