{
  "id": 7587493,
  "type": "Feature",
  "properties": {
    "tgn:hierarchy":[
        "tgn:7587493",
        "tgn:1000004",
        "tgn:7000198",
        "tgn:7016788",
        "tgn:7029392"
    ],
    "tgn:id":7587493,
    "tgn:name:en":"Gaje Singh Ka Tar",
    "tgn:placetype":[
        "aat:300006207"
    ]
},
  "bbox": [],
  "geometry": {"coordinates":[70.222794,27.697394],"type":"Point"}
}