{
  "id": 7504188,
  "type": "Feature",
  "properties": {
    "tgn:hierarchy":[
        "tgn:7504188",
        "tgn:1009227",
        "tgn:1000226",
        "tgn:7520095",
        "tgn:1000006",
        "tgn:7029392"
    ],
    "tgn:id":7504188,
    "tgn:name:en":"Wangapeka Valley",
    "tgn:placetype":[
        "aat:300008347"
    ]
},
  "bbox": [],
  "geometry": {"coordinates":[172.116667,-41.35],"type":"Point"}
}