{
  "id": 7255187,
  "type": "Feature",
  "properties": {
    "tgn:hierarchy":[
        "tgn:7255187",
        "tgn:7007877",
        "tgn:1000003",
        "tgn:1000063",
        "tgn:4012014",
        "tgn:7029392"
    ],
    "tgn:id":7255187,
    "tgn:name":"Robechies, Bois de",
    "tgn:placetype":[
        "aat:300008863"
    ]
},
  "bbox": [],
  "geometry": {"coordinates":[4.283333,50.083333],"type":"Point"}
}