<<<<<<< HEAD
{
  "id": 2761909,
  "type": "Feature",
  "properties": {
    "tgn:hierarchy":[
        "tgn:2761909",
        "tgn:1000001",
        "tgn:7012149",
        "tgn:2001918",
        "tgn:7007825",
        "tgn:7029392"
    ],
    "tgn:id":2761909,
    "tgn:name":"West Ridge",
    "tgn:placetype":[
        "aat:300008347"
    ]
},
  "bbox": [],
  "geometry": {"coordinates":[-82.2167,36.5833],"type":"Point"}
}
=======
{"geometry":{"type":"Point","coordinates":[-82.216700,36.583300]},"type":"Feature","properties":{"hierarchy":["tgn:2761909","tgn:1000001","tgn:7012149","tgn:2001918","tgn:7007825","tgn:7029392"],"placetype":["aat:300008347"],"id":2761909,"name:xx":"West Ridge"}}
>>>>>>> 03f74aca74312dbeaf24d7e61306dd6a786dc3d0
