{
  "id": 2469926,
  "type": "Feature",
  "properties": {
    "tgn:hierarchy":[
        "tgn:2469926",
        "tgn:7006450",
        "tgn:1000001",
        "tgn:7012149",
        "tgn:2000086",
        "tgn:7029392"
    ],
    "tgn:id":2469926,
    "tgn:name":"Loon Lake",
    "tgn:placetype":[
        "aat:300008680"
    ]
},
  "bbox": [],
  "geometry": {"coordinates":[-146.5833,62.1833],"type":"Point"}
}