{
  "id": 2349586,
  "type": "Feature",
  "properties": {
    "tgn:hierarchy":[
        "tgn:2349586",
        "tgn:1000001",
        "tgn:7019560",
        "tgn:7012149",
        "tgn:7007566",
        "tgn:7029392"
    ],
    "tgn:id":2349586,
    "tgn:name":"Gillespie Draw",
    "tgn:placetype":[
        "aat:300008761"
    ]
},
  "bbox": [],
  "geometry": {"coordinates":[-104.5333,34.25],"type":"Point"}
}