{
  "id": 7230500,
  "type": "Feature",
  "properties": {
    "tgn:hierarchy":[
        "tgn:7230500",
        "tgn:7011163",
        "tgn:7002674",
        "tgn:1000003",
        "tgn:1000074",
        "tgn:7029392"
    ],
    "tgn:id":7230500,
    "tgn:name":"Khl\u00f3\u00ef, \u00c1kra",
    "tgn:placetype":[
        "aat:300008850"
    ]
},
  "bbox": [],
  "geometry": {"coordinates":[25.333333,39.966667],"type":"Point"}
}