<<<<<<< HEAD
{
  "id": 7480776,
  "type": "Feature",
  "properties": {
    "tgn:hierarchy":[
        "tgn:7480776",
        "tgn:7001010",
        "tgn:1000004",
        "tgn:1000141",
        "tgn:7029392"
    ],
    "tgn:id":7480776,
    "tgn:name":"Dongjing Chansi",
    "tgn:placetype":[
        "aat:300007595"
    ]
},
  "bbox": [],
  "geometry": {"coordinates":[121.612778,23.975278],"type":"Point"}
}
=======
{"geometry":{"type":"Point","coordinates":[121.612778,23.975278]},"type":"Feature","properties":{"hierarchy":["tgn:7480776","tgn:7001010","tgn:1000004","tgn:1000141","tgn:7029392"],"placetype":["aat:300007595"],"id":7480776,"name:xx":"Dongjing Chansi"}}
>>>>>>> 03f74aca74312dbeaf24d7e61306dd6a786dc3d0
