{
  "id": 2676287,
  "type": "Feature",
  "properties": {
    "tgn:hierarchy":[
        "tgn:2676287",
        "tgn:1000001",
        "tgn:7012149",
        "tgn:2000475",
        "tgn:7007250",
        "tgn:7029392"
    ],
    "tgn:id":2676287,
    "tgn:name":"Sourdough Creek",
    "tgn:placetype":[
        "aat:300008706"
    ]
},
  "bbox": [],
  "geometry": {"coordinates":[-114.9333,43.1833],"type":"Point"}
}