{
  "id": 7032946,
  "type": "Feature",
  "properties": {
    "tgn:hierarchy":[
        "tgn:7032946",
        "tgn:7002108",
        "tgn:1000004",
        "tgn:7000231",
        "tgn:7029392"
    ],
    "tgn:id":7032946,
    "tgn:name:en":"Heriz",
    "tgn:placetype":[
        "aat:300008347"
    ]
},
  "bbox": [],
  "geometry": {"coordinates":[45.542,38.258],"type":"Point"}
}