{
  "id": 7475150,
  "type": "Feature",
  "properties": {
    "tgn:hierarchy":[
        "tgn:7475150",
        "tgn:1000004",
        "tgn:1000454",
        "tgn:1000141",
        "tgn:7029392"
    ],
    "tgn:id":7475150,
    "tgn:name":"Caigongkeng",
    "tgn:placetype":[
        "aat:300008347"
    ]
},
  "bbox": [],
  "geometry": {"coordinates":[121.512542,25.202496],"type":"Point"}
}