{
  "id": 2523176,
  "type": "Feature",
  "properties": {
    "tgn:hierarchy":[
        "tgn:2523176",
        "tgn:1000001",
        "tgn:7012149",
        "tgn:2001765",
        "tgn:7007712",
        "tgn:7029392"
    ],
    "tgn:id":2523176,
    "tgn:name":"Moores Creek",
    "tgn:placetype":[
        "aat:300008706"
    ]
},
  "bbox": [],
  "geometry": {"coordinates":[-81.6167,33.8833],"type":"Point"}
}