{
  "id": 1133447,
  "type": "Feature",
  "properties": {
    "tgn:hierarchy":[
        "tgn:1133447",
        "tgn:1000001",
        "tgn:7012149",
        "tgn:1002690",
        "tgn:7007710",
        "tgn:7029392"
    ],
    "tgn:id":1133447,
    "tgn:name":"Huntingdon Valley Creek",
    "tgn:placetype":[
        "aat:300008706"
    ]
},
  "bbox": [],
  "geometry": {"coordinates":[-75.0333,40.1333],"type":"Point"}
}