{
  "id": 2424569,
  "type": "Feature",
  "properties": {
    "tgn:hierarchy":[
        "tgn:2424569",
        "tgn:1000001",
        "tgn:7012149",
        "tgn:2000631",
        "tgn:7007253",
        "tgn:7029392"
    ],
    "tgn:id":2424569,
    "tgn:name":"Johnson Creek",
    "tgn:placetype":[
        "aat:300008706"
    ]
},
  "bbox": [],
  "geometry": {"coordinates":[-95.75,43.0167],"type":"Point"}
}