{
  "id": 2533773,
  "type": "Feature",
  "properties": {
    "tgn:hierarchy":[
        "tgn:2533773",
        "tgn:1000001",
        "tgn:1002245",
        "tgn:7012149",
        "tgn:7007568",
        "tgn:7029392"
    ],
    "tgn:id":2533773,
    "tgn:name":"Mutton Hollow",
    "tgn:placetype":[
        "aat:300008761"
    ]
},
  "bbox": [],
  "geometry": {"coordinates":[-78.6833,42.25],"type":"Point"}
}