<<<<<<< HEAD
{
  "id": 2151520,
  "type": "Feature",
  "properties": {
    "tgn:hierarchy":[
        "tgn:2151520",
        "tgn:1000001",
        "tgn:7012149",
        "tgn:2001141",
        "tgn:7007522",
        "tgn:7029392"
    ],
    "tgn:id":2151520,
    "tgn:name":"Batt Place",
    "tgn:placetype":[
        "aat:300008347"
    ]
},
  "bbox": [],
  "geometry": {"coordinates":[-88.9667,30.9667],"type":"Point"}
}
=======
{"geometry":{"type":"Point","coordinates":[-88.966700,30.966700]},"type":"Feature","properties":{"hierarchy":["tgn:2151520","tgn:1000001","tgn:7012149","tgn:2001141","tgn:7007522","tgn:7029392"],"placetype":["aat:300008347"],"id":2151520,"name:xx":"Batt Place"}}
>>>>>>> 03f74aca74312dbeaf24d7e61306dd6a786dc3d0
