{
  "id": 2151520,
  "type": "Feature",
  "properties": {
    "tgn:hierarchy":[
        "tgn:2151520",
        "tgn:1000001",
        "tgn:7012149",
        "tgn:2001141",
        "tgn:7007522",
        "tgn:7029392"
    ],
    "tgn:id":2151520,
    "tgn:name":"Batt Place",
    "tgn:placetype":[
        "aat:300008347"
    ]
},
  "bbox": [],
  "geometry": {"coordinates":[-88.9667,30.9667],"type":"Point"}
}