{
  "id": 7033587,
  "type": "Feature",
  "properties": {
    "tgn:hierarchy":[
        "tgn:7033587",
        "tgn:7003133",
        "tgn:1000003",
        "tgn:7008516",
        "tgn:1000080",
        "tgn:7029392"
    ],
    "tgn:id":7033587,
    "tgn:name":"Villa Brocchi",
    "tgn:placetype":[
        "aat:300008347"
    ]
},
  "bbox": [],
  "geometry": {"coordinates":[12.085278,44.371111],"type":"Point"}
}