<<<<<<< HEAD
{
  "id": 2156539,
  "type": "Feature",
  "properties": {
    "tgn:hierarchy":[
        "tgn:2156539",
        "tgn:1000001",
        "tgn:7012149",
        "tgn:2001706",
        "tgn:7007708",
        "tgn:7029392"
    ],
    "tgn:id":2156539,
    "tgn:name":"Beartree Creek",
    "tgn:placetype":[
        "aat:300008706"
    ]
},
  "bbox": [],
  "geometry": {"coordinates":[-122.2833,43.0167],"type":"Point"}
}
=======
{"geometry":{"type":"Point","coordinates":[-122.283300,43.016700]},"type":"Feature","properties":{"hierarchy":["tgn:2156539","tgn:1000001","tgn:7012149","tgn:2001706","tgn:7007708","tgn:7029392"],"placetype":["aat:300008706"],"id":2156539,"name:xx":"Beartree Creek"}}
>>>>>>> 03f74aca74312dbeaf24d7e61306dd6a786dc3d0
