{
  "id": 1081740,
  "type": "Feature",
  "properties": {
    "tgn:hierarchy":[
        "tgn:1081740",
        "tgn:7000895",
        "tgn:1000004",
        "tgn:1001010",
        "tgn:1000120",
        "tgn:7029392"
    ],
    "tgn:id":1081740,
    "tgn:name":"Yamagata",
    "tgn:placetype":[
        "aat:300008347",
        "aat:300387220"
    ]
},
  "bbox": [],
  "geometry": {"coordinates":[137.8667,36.1667],"type":"Point"}
}