{
  "id": 7524603,
  "type": "Feature",
  "properties": {
    "tgn:hierarchy":[
        "tgn:7524603",
        "tgn:7001242",
        "tgn:7016833",
        "tgn:7001312",
        "tgn:7029392"
    ],
    "tgn:id":7524603,
    "tgn:name:en":"B\u016brayj",
    "tgn:placetype":[
        "aat:300008347"
    ]
},
  "bbox": [],
  "geometry": {"coordinates":[30.966008,30.903566],"type":"Point"}
}