{
  "id": 7312349,
  "type": "Feature",
  "properties": {
    "tgn:hierarchy":[
        "tgn:7312349",
        "tgn:1001705",
        "tgn:1000049",
        "tgn:1000002",
        "tgn:7029392"
    ],
    "tgn:id":7312349,
    "tgn:name":"La Palma",
    "tgn:placetype":[
        "aat:300000206"
    ]
},
  "bbox": [],
  "geometry": {"coordinates":[-71.55,-34.883333],"type":"Point"}
}