{
  "id": 7097640,
  "type": "Feature",
  "properties": {
    "tgn:hierarchy":[
        "tgn:7097640",
        "tgn:7000096",
        "tgn:1000003",
        "tgn:7000084",
        "tgn:7029392"
    ],
    "tgn:id":7097640,
    "tgn:name":"Springbleiche",
    "tgn:placetype":[
        "aat:300000206"
    ]
},
  "bbox": [],
  "geometry": {"coordinates":[13.55,52.166667],"type":"Point"}
}