{
  "id": 2372850,
  "type": "Feature",
  "properties": {
    "tgn:hierarchy":[
        "tgn:2372850",
        "tgn:1002138",
        "tgn:1000001",
        "tgn:7012149",
        "tgn:7007157",
        "tgn:7029392"
    ],
    "tgn:id":2372850,
    "tgn:name":"Hall Station",
    "tgn:placetype":[
        "aat:300008347"
    ]
},
  "bbox": [],
  "geometry": {"coordinates":[-122.05,37.5833],"type":"Point"}
}