{
  "id": 7493337,
  "type": "Feature",
  "properties": {
    "tgn:hierarchy":[
        "tgn:7493337",
        "tgn:7001004",
        "tgn:1000004",
        "tgn:1000141",
        "tgn:7029392"
    ],
    "tgn:id":7493337,
    "tgn:name":"Dabengfeng Shan",
    "tgn:placetype":[
        "aat:300008798"
    ]
},
  "bbox": [],
  "geometry": {"coordinates":[120.611593,22.916205],"type":"Point"}
}