{
  "id": 2448847,
  "type": "Feature",
  "properties": {
    "tgn:hierarchy":[
        "tgn:2448847",
        "tgn:1000001",
        "tgn:7012149",
        "tgn:2002126",
        "tgn:7007827",
        "tgn:7029392"
    ],
    "tgn:id":2448847,
    "tgn:name":"Lime Canyon",
    "tgn:placetype":[
        "aat:300008761"
    ]
},
  "bbox": [],
  "geometry": {"coordinates":[-111.5333,40.5167],"type":"Point"}
}