{
  "id": 2289004,
  "type": "Feature",
  "properties": {
    "tgn:hierarchy":[
        "tgn:2289004",
        "tgn:1000001",
        "tgn:7012149",
        "tgn:2000559",
        "tgn:7007252",
        "tgn:7029392"
    ],
    "tgn:id":2289004,
    "tgn:name":"Dive Branch",
    "tgn:placetype":[
        "aat:300008699"
    ]
},
  "bbox": [],
  "geometry": {"coordinates":[-87.2167,39.55],"type":"Point"}
}