{
  "id": 2134455,
  "type": "Feature",
  "properties": {
    "tgn:hierarchy":[
        "tgn:2134455",
        "tgn:1002165",
        "tgn:1000001",
        "tgn:7012149",
        "tgn:7007517",
        "tgn:7029392"
    ],
    "tgn:id":2134455,
    "tgn:name":"Anns Cove",
    "tgn:placetype":[
        "aat:300132316"
    ]
},
  "bbox": [],
  "geometry": {"coordinates":[-70.4667,41.5833],"type":"Point"}
}