<<<<<<< HEAD
{
  "id": 7362507,
  "type": "Feature",
  "properties": {
    "tgn:hierarchy":[
        "tgn:7362507",
        "tgn:7005581",
        "tgn:1000001",
        "tgn:7005560",
        "tgn:7029392"
    ],
    "tgn:id":7362507,
    "tgn:name":"El Paso Hondo",
    "tgn:placetype":[
        "aat:300008347"
    ]
},
  "bbox": [],
  "geometry": {"coordinates":[-106.8,27.533333],"type":"Point"}
}
=======
{"geometry":{"type":"Point","coordinates":[-106.800000,27.533333]},"type":"Feature","properties":{"hierarchy":["tgn:7362507","tgn:7005581","tgn:1000001","tgn:7005560","tgn:7029392"],"placetype":["aat:300008347"],"id":7362507,"name:xx":"El Paso Hondo"}}
>>>>>>> 03f74aca74312dbeaf24d7e61306dd6a786dc3d0
