{
  "id": 7255087,
  "type": "Feature",
  "properties": {
    "tgn:hierarchy":[
        "tgn:7255087",
        "tgn:7018238",
        "tgn:1000003",
        "tgn:1000063",
        "tgn:4012014",
        "tgn:7029392"
    ],
    "tgn:id":7255087,
    "tgn:name":"Vieux Manant",
    "tgn:placetype":[
        "aat:300008347"
    ]
},
  "bbox": [],
  "geometry": {"coordinates":[4.416667,50.65],"type":"Point"}
}