{
  "id": 7575673,
  "type": "Feature",
  "properties": {
    "tgn:hierarchy":[
        "tgn:7575673",
        "tgn:1000004",
        "tgn:7000198",
        "tgn:1001996",
        "tgn:7029392"
    ],
    "tgn:id":7575673,
    "tgn:name:en":"L\u0101hri",
    "tgn:placetype":[
        "aat:300008347"
    ]
},
  "bbox": [],
  "geometry": {"coordinates":[76.058445,32.547961],"type":"Point"}
}