{
  "id": 2023615,
  "type": "Feature",
  "properties": {
    "tgn:hierarchy":[
        "tgn:2023615",
        "tgn:1000001",
        "tgn:7012149",
        "tgn:2000446",
        "tgn:7007248",
        "tgn:7029392"
    ],
    "tgn:id":2023615,
    "tgn:name":"Mill Creek",
    "tgn:placetype":[
        "aat:300008347"
    ]
},
  "bbox": [],
  "geometry": {"coordinates":[-85.0333,34.7167],"type":"Point"}
}