{
  "id": 7210116,
  "type": "Feature",
  "properties": {
    "tgn:hierarchy":[
        "tgn:7210116",
        "tgn:7003692",
        "tgn:1000003",
        "tgn:7000084",
        "tgn:7029392"
    ],
    "tgn:id":7210116,
    "tgn:name":"Banzenweiler",
    "tgn:placetype":[
        "aat:300008347"
    ]
},
  "bbox": [],
  "geometry": {"coordinates":[9.974167,49.095],"type":"Point"}
}