{
  "id": 2635815,
  "type": "Feature",
  "properties": {
    "tgn:hierarchy":[
        "tgn:2635815",
        "tgn:1000001",
        "tgn:7012149",
        "tgn:7007157",
        "tgn:1002956",
        "tgn:7029392"
    ],
    "tgn:id":2635815,
    "tgn:name":"Sacatar Canyon",
    "tgn:placetype":[
        "aat:300008761"
    ]
},
  "bbox": [],
  "geometry": {"coordinates":[-118.0333,35.95],"type":"Point"}
}