{
  "id": 1099427,
  "type": "Feature",
  "properties": {
    "tgn:hierarchy":[
        "tgn:1099427",
        "tgn:7006160",
        "tgn:1000951",
        "tgn:1000006",
        "tgn:7029392"
    ],
    "tgn:id":1099427,
    "tgn:name":"Baiyer River",
    "tgn:placetype":[
        "aat:300008347"
    ]
},
  "bbox": [],
  "geometry": {"coordinates":[144.1167,-5.55],"type":"Point"}
}