{
  "id": 2344915,
  "type": "Feature",
  "properties": {
    "tgn:hierarchy":[
        "tgn:2344915",
        "tgn:1000001",
        "tgn:7012149",
        "tgn:2001711",
        "tgn:7007708",
        "tgn:7029392"
    ],
    "tgn:id":2344915,
    "tgn:name":"Gardener Reservoir",
    "tgn:placetype":[
        "aat:300006191"
    ]
},
  "bbox": [],
  "geometry": {"coordinates":[-122.5667,42.4333],"type":"Point"}
}