{
  "id": 7234796,
  "type": "Feature",
  "properties": {
    "tgn:hierarchy":[
        "tgn:7234796",
        "tgn:7002728",
        "tgn:7002715",
        "tgn:1000003",
        "tgn:1000074",
        "tgn:7029392"
    ],
    "tgn:id":7234796,
    "tgn:name":"\u00c1spri P\u00e9tra",
    "tgn:placetype":[
        "aat:300387002"
    ]
},
  "bbox": [],
  "geometry": {"coordinates":[21.866667,40.983333],"type":"Point"}
}