<<<<<<< HEAD
{
  "id": 2335549,
  "type": "Feature",
  "properties": {
    "tgn:hierarchy":[
        "tgn:2335549",
        "tgn:1000001",
        "tgn:7019560",
        "tgn:7012149",
        "tgn:7007566",
        "tgn:7029392"
    ],
    "tgn:id":2335549,
    "tgn:name":"Fort Sumner Main Canal",
    "tgn:placetype":[
        "aat:300006075"
    ]
},
  "bbox": [],
  "geometry": {"coordinates":[-104.2,34.4333],"type":"Point"}
}
=======
{"geometry":{"type":"Point","coordinates":[-104.200000,34.433300]},"type":"Feature","properties":{"hierarchy":["tgn:2335549","tgn:1000001","tgn:7019560","tgn:7012149","tgn:7007566","tgn:7029392"],"placetype":["aat:300006075"],"id":2335549,"name:xx":"Fort Sumner Main Canal"}}
>>>>>>> 03f74aca74312dbeaf24d7e61306dd6a786dc3d0
