{
  "id": 7273232,
  "type": "Feature",
  "properties": {
    "tgn:hierarchy":[
        "tgn:7273232",
        "tgn:1000003",
        "tgn:7003613",
        "tgn:7016845",
        "tgn:7029392"
    ],
    "tgn:id":7273232,
    "tgn:name:nl":"Westerleesche Lagemeeden, Polder de",
    "tgn:placetype":[
        "aat:300006163"
    ]
},
  "bbox": [],
  "geometry": {"coordinates":[6.966667,53.133333],"type":"Point"}
}