{
  "id": 2267900,
  "type": "Feature",
  "properties": {
    "tgn:hierarchy":[
        "tgn:2267900",
        "tgn:1000001",
        "tgn:7012149",
        "tgn:1002387",
        "tgn:7007710",
        "tgn:7029392"
    ],
    "tgn:id":2267900,
    "tgn:name":"Crooked Cave",
    "tgn:placetype":[
        "aat:300008746"
    ]
},
  "bbox": [],
  "geometry": {"coordinates":[-77.6333,39.95],"type":"Point"}
}