{
  "id": 2151862,
  "type": "Feature",
  "properties": {
    "tgn:hierarchy":[
        "tgn:2151862",
        "tgn:7006450",
        "tgn:1000001",
        "tgn:2124089",
        "tgn:7012149",
        "tgn:7029392"
    ],
    "tgn:id":2151862,
    "tgn:name":"Battleship Island",
    "tgn:placetype":[
        "aat:300008791"
    ]
},
  "bbox": [],
  "geometry": {"coordinates":[-134.65,58.35],"type":"Point"}
}