{
  "id": 2497586,
  "type": "Feature",
  "properties": {
    "tgn:hierarchy":[
        "tgn:2497586",
        "tgn:1002144",
        "tgn:1000001",
        "tgn:7012149",
        "tgn:7007706",
        "tgn:7029392"
    ],
    "tgn:id":2497586,
    "tgn:name":"May Ditch",
    "tgn:placetype":[
        "aat:300006075"
    ]
},
  "bbox": [],
  "geometry": {"coordinates":[-83.95,40.8333],"type":"Point"}
}