{
  "id": 2600762,
  "type": "Feature",
  "properties": {
    "tgn:hierarchy":[
        "tgn:2600762",
        "tgn:1000001",
        "tgn:7012149",
        "tgn:7029392"
    ],
    "tgn:id":2600762,
    "tgn:name":"Pump Canyon",
    "tgn:placetype":[
        "aat:300008761"
    ]
},
  "bbox": [],
  "geometry": {"coordinates":[-107.6833,37.05],"type":"Point"}
}