<<<<<<< HEAD
{
  "id": 7059828,
  "type": "Feature",
  "properties": {
    "tgn:hierarchy":[
        "tgn:7059828",
        "tgn:1000003",
        "tgn:7003682",
        "tgn:7000084",
        "tgn:7029392"
    ],
    "tgn:id":7059828,
    "tgn:name":"Altenklosterhof",
    "tgn:placetype":[
        "aat:300000206"
    ]
},
  "bbox": [],
  "geometry": {"coordinates":[7.9,50.7],"type":"Point"}
}
=======
{"geometry":{"type":"Point","coordinates":[7.900000,50.700000]},"type":"Feature","properties":{"hierarchy":["tgn:7059828","tgn:1000003","tgn:7003682","tgn:7000084","tgn:7029392"],"placetype":["aat:300000206"],"id":7059828,"name:xx":"Altenklosterhof"}}
>>>>>>> 03f74aca74312dbeaf24d7e61306dd6a786dc3d0
