{
  "id": 7458905,
  "type": "Feature",
  "properties": {
    "tgn:hierarchy":[
        "tgn:7458905",
        "tgn:7002444",
        "tgn:1000003",
        "tgn:7009907",
        "tgn:7008591",
        "tgn:7029392"
    ],
    "tgn:id":7458905,
    "tgn:name:en":"Mae Sand",
    "tgn:placetype":[
        "aat:300386848"
    ]
},
  "bbox": [],
  "geometry": {"coordinates":[-2.966667,59.266667],"type":"Point"}
}