{
  "id": 7015438,
  "type": "Feature",
  "properties": {
    "tgn:hierarchy":[
        "tgn:7015438",
        "tgn:7018774",
        "tgn:1000003",
        "tgn:7006664",
        "tgn:7029392"
    ],
    "tgn:id":7015438,
    "tgn:name:bs":"Sarajevo",
    "tgn:placetype":[
        "aat:300387236",
        "aat:300008347",
        "aat:300008389",
        "aat:300387308",
        "aat:300387319",
        "aat:300387219",
        "aat:300005135",
        "aat:300387270",
        "aat:300387302",
        "aat:300387296"
    ]
},
  "bbox": [],
  "geometry": {"coordinates":[18.3833,43.85],"type":"Point"}
}