{
  "id": 7403887,
  "type": "Feature",
  "properties": {
    "tgn:hierarchy":[
        "tgn:7403887",
        "tgn:7005585",
        "tgn:1000001",
        "tgn:7005560",
        "tgn:7029392"
    ],
    "tgn:id":7403887,
    "tgn:name":"Grande, R\u00edo",
    "tgn:placetype":[
        "aat:300008699"
    ]
},
  "bbox": [],
  "geometry": {"coordinates":[-98.983333,17.066667],"type":"Point"}
}