{
  "id": 7585322,
  "type": "Feature",
  "properties": {
    "tgn:hierarchy":[
        "tgn:7585322",
        "tgn:1000004",
        "tgn:1001871",
        "tgn:7000198",
        "tgn:7029392"
    ],
    "tgn:id":7585322,
    "tgn:name:en":"Ch\u0101ndnod",
    "tgn:placetype":[
        "aat:300008347"
    ]
},
  "bbox": [],
  "geometry": {"coordinates":[75.718214,28.968239],"type":"Point"}
}