{
  "id": 7058271,
  "type": "Feature",
  "properties": {
    "tgn:hierarchy":[
        "tgn:7058271",
        "tgn:7015163",
        "tgn:1000003",
        "tgn:7003121",
        "tgn:1000080",
        "tgn:7029392"
    ],
    "tgn:id":7058271,
    "tgn:name":"Annaru, Monte",
    "tgn:placetype":[
        "aat:300008795"
    ]
},
  "bbox": [],
  "geometry": {"coordinates":[8.75,40.483333],"type":"Point"}
}