{
  "id": 2113824,
  "type": "Feature",
  "properties": {
    "tgn:hierarchy":[
        "tgn:2113824",
        "tgn:1000001",
        "tgn:7012149",
        "tgn:2002166",
        "tgn:7007919",
        "tgn:7029392"
    ],
    "tgn:id":2113824,
    "tgn:name":"Rabat",
    "tgn:placetype":[
        "aat:300008347",
        "aat:300387210"
    ]
},
  "bbox": [],
  "geometry": {"coordinates":[-78.9333,36.9667],"type":"Point"}
}