<<<<<<< HEAD
{
  "id": 7484723,
  "type": "Feature",
  "properties": {
    "tgn:hierarchy":[
        "tgn:7484723",
        "tgn:7488858",
        "tgn:1000004",
        "tgn:1000141",
        "tgn:7029392"
    ],
    "tgn:id":7484723,
    "tgn:name":"Baigu Dashan Xinanfeng",
    "tgn:placetype":[
        "aat:300008798"
    ]
},
  "bbox": [],
  "geometry": {"coordinates":[121.091389,24.184722],"type":"Point"}
}
=======
{"geometry":{"type":"Point","coordinates":[121.091389,24.184722]},"type":"Feature","properties":{"hierarchy":["tgn:7484723","tgn:7488858","tgn:1000004","tgn:1000141","tgn:7029392"],"placetype":["aat:300008798"],"id":7484723,"name:xx":"Baigu Dashan Xinanfeng"}}
>>>>>>> 03f74aca74312dbeaf24d7e61306dd6a786dc3d0
