{
  "id": 2279476,
  "type": "Feature",
  "properties": {
    "tgn:hierarchy":[
        "tgn:2279476",
        "tgn:1000001",
        "tgn:7012149",
        "tgn:1002694",
        "tgn:7007252",
        "tgn:7029392"
    ],
    "tgn:id":2279476,
    "tgn:name":"Deadman Hollow",
    "tgn:placetype":[
        "aat:300008761"
    ]
},
  "bbox": [],
  "geometry": {"coordinates":[-86.4167,39.3333],"type":"Point"}
}