{
  "id": 2709467,
  "type": "Feature",
  "properties": {
    "tgn:hierarchy":[
        "tgn:2709467",
        "tgn:1000001",
        "tgn:7012149",
        "tgn:2001212",
        "tgn:7007523",
        "tgn:7029392"
    ],
    "tgn:id":2709467,
    "tgn:name":"Tabo Creek",
    "tgn:placetype":[
        "aat:300008706"
    ]
},
  "bbox": [],
  "geometry": {"coordinates":[-93.85,39.0167],"type":"Point"}
}