{
  "id": 2756140,
  "type": "Feature",
  "properties": {
    "tgn:hierarchy":[
        "tgn:2756140",
        "tgn:2002239",
        "tgn:1000001",
        "tgn:7012149",
        "tgn:7007920",
        "tgn:7029392"
    ],
    "tgn:id":2756140,
    "tgn:name":"Weissenfels Ridge",
    "tgn:placetype":[
        "aat:300266640"
    ]
},
  "bbox": [],
  "geometry": {"coordinates":[-117.0167,46.1667],"type":"Point"}
}