{
  "id": 2572923,
  "type": "Feature",
  "properties": {
    "tgn:hierarchy":[
        "tgn:2572923",
        "tgn:7006450",
        "tgn:2000069",
        "tgn:1000001",
        "tgn:7012149",
        "tgn:7029392"
    ],
    "tgn:id":2572923,
    "tgn:name":"Pearl Creek",
    "tgn:placetype":[
        "aat:300008706"
    ]
},
  "bbox": [],
  "geometry": {"coordinates":[-159.45,61.05],"type":"Point"}
}