<<<<<<< HEAD
{
  "id": 2767964,
  "type": "Feature",
  "properties": {
    "tgn:hierarchy":[
        "tgn:2767964",
        "tgn:7002659",
        "tgn:1000001",
        "tgn:7012149",
        "tgn:2000064",
        "tgn:7029392"
    ],
    "tgn:id":2767964,
    "tgn:name":"Whiteoak Branch",
    "tgn:placetype":[
        "aat:300008699"
    ]
},
  "bbox": [],
  "geometry": {"coordinates":[-88.2333,31.3667],"type":"Point"}
}
=======
{"geometry":{"type":"Point","coordinates":[-88.233300,31.366700]},"type":"Feature","properties":{"hierarchy":["tgn:2767964","tgn:7002659","tgn:1000001","tgn:7012149","tgn:2000064","tgn:7029392"],"placetype":["aat:300008699"],"id":2767964,"name:xx":"Whiteoak Branch"}}
>>>>>>> 03f74aca74312dbeaf24d7e61306dd6a786dc3d0
