{
  "id": 7092704,
  "type": "Feature",
  "properties": {
    "tgn:hierarchy":[
        "tgn:7092704",
        "tgn:7000096",
        "tgn:1000003",
        "tgn:7000084",
        "tgn:7029392"
    ],
    "tgn:id":7092704,
    "tgn:name":"Vor dem Baruther Tor",
    "tgn:placetype":[
        "aat:300008347"
    ]
},
  "bbox": [],
  "geometry": {"coordinates":[13.183333,52.083333],"type":"Point"}
}