{
  "id": 7296929,
  "type": "Feature",
  "properties": {
    "tgn:hierarchy":[
        "tgn:7296929",
        "tgn:7002832",
        "tgn:7001158",
        "tgn:1000003",
        "tgn:1000095",
        "tgn:7029392"
    ],
    "tgn:id":7296929,
    "tgn:name":"Triollo",
    "tgn:placetype":[
        "aat:300008347"
    ]
},
  "bbox": [],
  "geometry": {"coordinates":[-4.683333,42.933333],"type":"Point"}
}