{
  "id": 7008882,
  "type": "Feature",
  "properties": {
    "tgn:hierarchy":[
        "tgn:7008882",
        "tgn:1000003",
        "tgn:1000063",
        "tgn:7029392"
    ],
    "tgn:id":7008882,
    "tgn:name":"Kempen",
    "tgn:placetype":[
        "aat:300387346",
        "aat:300132339"
    ]
},
  "bbox": [],
  "geometry": {"coordinates":[5.3333,51.1667],"type":"Point"}
}