{
  "id": 2584382,
  "type": "Feature",
  "properties": {
    "tgn:hierarchy":[
        "tgn:2584382",
        "tgn:1000001",
        "tgn:7012149",
        "tgn:7007522",
        "tgn:7029392"
    ],
    "tgn:id":2584382,
    "tgn:name":"Piney Creek",
    "tgn:placetype":[
        "aat:300008706"
    ]
},
  "bbox": [],
  "geometry": {"coordinates":[-88.9167,31.7667],"type":"Point"}
}