{
  "id": 7217493,
  "type": "Feature",
  "properties": {
    "tgn:hierarchy":[
        "tgn:7217493",
        "tgn:7011170",
        "tgn:7002715",
        "tgn:1000003",
        "tgn:1000074",
        "tgn:7029392"
    ],
    "tgn:id":7217493,
    "tgn:name":"Tsalapetin\u00f3s",
    "tgn:placetype":[
        "aat:300008347"
    ]
},
  "bbox": [],
  "geometry": {"coordinates":[25.116667,41.283333],"type":"Point"}
}