{
  "id": 7112040,
  "type": "Feature",
  "properties": {
    "tgn:hierarchy":[
        "tgn:7112040",
        "tgn:7003692",
        "tgn:1000003",
        "tgn:7000084",
        "tgn:7029392"
    ],
    "tgn:id":7112040,
    "tgn:name":"Rohrbach",
    "tgn:placetype":[
        "aat:300008699"
    ]
},
  "bbox": [],
  "geometry": {"coordinates":[9.266667,48.683333],"type":"Point"}
}