<<<<<<< HEAD
{
  "id": 7055815,
  "type": "Feature",
  "properties": {
    "tgn:hierarchy":[
        "tgn:7055815",
        "tgn:7003005",
        "tgn:7003014",
        "tgn:1000003",
        "tgn:1000080",
        "tgn:7029392"
    ],
    "tgn:id":7055815,
    "tgn:name":"Platano, Torrente",
    "tgn:placetype":[
        "aat:300008699"
    ]
},
  "bbox": [],
  "geometry": {"coordinates":[15.45,40.616667],"type":"Point"}
}
=======
{"geometry":{"type":"Point","coordinates":[15.450000,40.616667]},"type":"Feature","properties":{"hierarchy":["tgn:7055815","tgn:7003005","tgn:7003014","tgn:1000003","tgn:1000080","tgn:7029392"],"placetype":["aat:300008699"],"id":7055815,"name:xx":"Platano, Torrente"}}
>>>>>>> 03f74aca74312dbeaf24d7e61306dd6a786dc3d0
