{
  "id": 7055815,
  "type": "Feature",
  "properties": {
    "tgn:hierarchy":[
        "tgn:7055815",
        "tgn:7003005",
        "tgn:7003014",
        "tgn:1000003",
        "tgn:1000080",
        "tgn:7029392"
    ],
    "tgn:id":7055815,
    "tgn:name":"Platano, Torrente",
    "tgn:placetype":[
        "aat:300008699"
    ]
},
  "bbox": [],
  "geometry": {"coordinates":[15.45,40.616667],"type":"Point"}
}