{
  "id": 2369637,
  "type": "Feature",
  "properties": {
    "tgn:hierarchy":[
        "tgn:2369637",
        "tgn:1000001",
        "tgn:7012149",
        "tgn:2002113",
        "tgn:7007827",
        "tgn:7029392"
    ],
    "tgn:id":2369637,
    "tgn:name":"Gunsight Bay",
    "tgn:placetype":[
        "aat:300132316"
    ]
},
  "bbox": [],
  "geometry": {"coordinates":[-111.3333,37.05],"type":"Point"}
}