{
  "id": 7080608,
  "type": "Feature",
  "properties": {
    "tgn:hierarchy":[
        "tgn:7080608",
        "tgn:7003692",
        "tgn:1000003",
        "tgn:7000084",
        "tgn:7029392"
    ],
    "tgn:id":7080608,
    "tgn:name":"W\u00f6hrlehof",
    "tgn:placetype":[
        "aat:300000206"
    ]
},
  "bbox": [],
  "geometry": {"coordinates":[7.933333,48.383333],"type":"Point"}
}