{
  "id": 2363764,
  "type": "Feature",
  "properties": {
    "tgn:hierarchy":[
        "tgn:2363764",
        "tgn:1000001",
        "tgn:7016172",
        "tgn:2000110",
        "tgn:7012149",
        "tgn:7029392"
    ],
    "tgn:id":2363764,
    "tgn:name":"Green Lake",
    "tgn:placetype":[
        "aat:300008680"
    ]
},
  "bbox": [],
  "geometry": {"coordinates":[-92.2667,33.2833],"type":"Point"}
}