{
  "id": 2065885,
  "type": "Feature",
  "properties": {
    "tgn:hierarchy":[
        "tgn:2065885",
        "tgn:1002157",
        "tgn:1000001",
        "tgn:7012149",
        "tgn:7007565",
        "tgn:7029392"
    ],
    "tgn:id":2065885,
    "tgn:name":"Pinehurst",
    "tgn:placetype":[
        "aat:300008347"
    ]
},
  "bbox": [],
  "geometry": {"coordinates":[-74.55,39.4667],"type":"Point"}
}