<<<<<<< HEAD
{
  "id": 7377690,
  "type": "Feature",
  "properties": {
    "tgn:hierarchy":[
        "tgn:7377690",
        "tgn:7005581",
        "tgn:1000001",
        "tgn:7005560",
        "tgn:7029392"
    ],
    "tgn:id":7377690,
    "tgn:name":"Rancho La Soledad",
    "tgn:placetype":[
        "aat:300000241"
    ]
},
  "bbox": [],
  "geometry": {"coordinates":[-104.7,28.216667],"type":"Point"}
}
=======
{"geometry":{"type":"Point","coordinates":[-104.700000,28.216667]},"type":"Feature","properties":{"hierarchy":["tgn:7377690","tgn:7005581","tgn:1000001","tgn:7005560","tgn:7029392"],"placetype":["aat:300000241"],"id":7377690,"name:xx":"Rancho La Soledad"}}
>>>>>>> 03f74aca74312dbeaf24d7e61306dd6a786dc3d0
