{
  "id": 7573770,
  "type": "Feature",
  "properties": {
    "tgn:hierarchy":[
        "tgn:7573770",
        "tgn:1000004",
        "tgn:7000198",
        "tgn:1001977",
        "tgn:7029392"
    ],
    "tgn:id":7573770,
    "tgn:name:en":"Garh P\u0101nchkot",
    "tgn:placetype":[
        "aat:300008347"
    ]
},
  "bbox": [],
  "geometry": {"coordinates":[86.772914,23.597698],"type":"Point"}
}