{
  "id": 7013559,
  "type": "Feature",
  "properties": {
    "tgn:hierarchy":[
        "tgn:7013559",
        "tgn:1000001",
        "tgn:7012149",
        "tgn:1002423",
        "tgn:7007568",
        "tgn:7029392"
    ],
    "tgn:id":7013559,
    "tgn:name":"Catskill",
    "tgn:placetype":[
        "aat:300008347"
    ]
},
  "bbox": [],
  "geometry": {"coordinates":[-73.85,42.2167],"type":"Point"}
}