{
  "id": 2423208,
  "type": "Feature",
  "properties": {
    "tgn:hierarchy":[
        "tgn:2423208",
        "tgn:1000001",
        "tgn:2002256",
        "tgn:7012149",
        "tgn:7013961",
        "tgn:7029392"
    ],
    "tgn:id":2423208,
    "tgn:name":"Joes Fork",
    "tgn:placetype":[
        "aat:300008699"
    ]
},
  "bbox": [],
  "geometry": {"coordinates":[-80.8833,38.6333],"type":"Point"}
}