{
  "id": 1112582,
  "type": "Feature",
  "properties": {
    "tgn:hierarchy":[
        "tgn:1112582",
        "tgn:1001160",
        "tgn:7006477",
        "tgn:1000002",
        "tgn:7029392"
    ],
    "tgn:id":1112582,
    "tgn:name":"Anegada, Bah\u00eda",
    "tgn:placetype":[
        "aat:300132316"
    ]
},
  "bbox": [],
  "geometry": {"coordinates":[-62.25,-40.25],"type":"Point"}
}