{
  "id": 7490234,
  "type": "Feature",
  "properties": {
    "tgn:hierarchy":[
        "tgn:7490234",
        "tgn:1000004",
        "tgn:1000454",
        "tgn:1000141",
        "tgn:7029392"
    ],
    "tgn:id":7490234,
    "tgn:name":"Shiliufen",
    "tgn:placetype":[
        "aat:300008347"
    ]
},
  "bbox": [],
  "geometry": {"coordinates":[121.601886,24.95597],"type":"Point"}
}