{
  "id": 7001170,
  "type": "Feature",
  "properties": {
    "tgn:hierarchy":[
        "tgn:7001170",
        "tgn:7001242",
        "tgn:7031756",
        "tgn:7016752",
        "tgn:1000769",
        "tgn:7029392"
    ],
    "tgn:id":7001170,
    "tgn:name":"Djemila",
    "tgn:placetype":[
        "aat:300008347",
        "aat:300000810",
        "aat:300167671",
        "aat:300263063"
    ]
},
  "bbox": [],
  "geometry": {"coordinates":[5.7333,36.4167],"type":"Point"}
}