<<<<<<< HEAD
{
  "id": 7373374,
  "type": "Feature",
  "properties": {
    "tgn:hierarchy":[
        "tgn:7373374",
        "tgn:1000001",
        "tgn:7005589",
        "tgn:7005560",
        "tgn:7029392"
    ],
    "tgn:id":7373374,
    "tgn:name":"Rancho La Leona",
    "tgn:placetype":[
        "aat:300000241"
    ]
},
  "bbox": [],
  "geometry": {"coordinates":[-99.983333,26.866667],"type":"Point"}
}
=======
{"geometry":{"type":"Point","coordinates":[-99.983333,26.866667]},"type":"Feature","properties":{"hierarchy":["tgn:7373374","tgn:1000001","tgn:7005589","tgn:7005560","tgn:7029392"],"placetype":["aat:300000241"],"id":7373374,"name:xx":"Rancho La Leona"}}
>>>>>>> 03f74aca74312dbeaf24d7e61306dd6a786dc3d0
