<<<<<<< HEAD
{
  "id": 2765696,
  "type": "Feature",
  "properties": {
    "tgn:hierarchy":[
        "tgn:2765696",
        "tgn:1000001",
        "tgn:7012149",
        "tgn:1002407",
        "tgn:7007568",
        "tgn:7029392"
    ],
    "tgn:id":2765696,
    "tgn:name":"White Creek",
    "tgn:placetype":[
        "aat:300008706"
    ]
},
  "bbox": [],
  "geometry": {"coordinates":[-78.0833,42.8833],"type":"Point"}
}
=======
{"geometry":{"type":"Point","coordinates":[-78.083300,42.883300]},"type":"Feature","properties":{"hierarchy":["tgn:2765696","tgn:1000001","tgn:7012149","tgn:1002407","tgn:7007568","tgn:7029392"],"placetype":["aat:300008706"],"id":2765696,"name:xx":"White Creek"}}
>>>>>>> 03f74aca74312dbeaf24d7e61306dd6a786dc3d0
