<<<<<<< HEAD
{
  "id": 2251765,
  "type": "Feature",
  "properties": {
    "tgn:hierarchy":[
        "tgn:2251765",
        "tgn:1000001",
        "tgn:7012149",
        "tgn:7007157",
        "tgn:2000184",
        "tgn:7029392"
    ],
    "tgn:id":2251765,
    "tgn:name":"Compton Spring",
    "tgn:placetype":[
        "aat:300008697"
    ]
},
  "bbox": [],
  "geometry": {"coordinates":[-121.3,40.95],"type":"Point"}
}
=======
{"geometry":{"type":"Point","coordinates":[-121.300000,40.950000]},"type":"Feature","properties":{"hierarchy":["tgn:2251765","tgn:1000001","tgn:7012149","tgn:7007157","tgn:2000184","tgn:7029392"],"placetype":["aat:300008697"],"id":2251765,"name:xx":"Compton Spring"}}
>>>>>>> 03f74aca74312dbeaf24d7e61306dd6a786dc3d0
