{
  "id": 7473214,
  "type": "Feature",
  "properties": {
    "tgn:hierarchy":[
        "tgn:7473214",
        "tgn:1000004",
        "tgn:7471332",
        "tgn:1000141",
        "tgn:7029392"
    ],
    "tgn:id":7473214,
    "tgn:name":"Yangxiwo",
    "tgn:placetype":[
        "aat:300008347"
    ]
},
  "bbox": [],
  "geometry": {"coordinates":[121.076944,24.879444],"type":"Point"}
}