{
  "id": 7472810,
  "type": "Feature",
  "properties": {
    "tgn:hierarchy":[
        "tgn:7472810",
        "tgn:1000004",
        "tgn:7001014",
        "tgn:1000141",
        "tgn:7029392"
    ],
    "tgn:id":7472810,
    "tgn:name":"Dongzhuangliao",
    "tgn:placetype":[
        "aat:300008347"
    ]
},
  "bbox": [],
  "geometry": {"coordinates":[120.215278,23.652778],"type":"Point"}
}