<<<<<<< HEAD
{
  "id": 7369876,
  "type": "Feature",
  "properties": {
    "tgn:hierarchy":[
        "tgn:7369876",
        "tgn:1000001",
        "tgn:1001893",
        "tgn:7005560",
        "tgn:7029392"
    ],
    "tgn:id":7369876,
    "tgn:name":"La Huasteca, Subregi\u00f3n",
    "tgn:placetype":[
        "aat:300387346"
    ]
},
  "bbox": [],
  "geometry": {"coordinates":[-98.25,22.0],"type":"Point"}
}
=======
{"geometry":{"type":"Point","coordinates":[-98.250000,22.000000]},"type":"Feature","properties":{"hierarchy":["tgn:7369876","tgn:1000001","tgn:1001893","tgn:7005560","tgn:7029392"],"placetype":["aat:300387346"],"id":7369876,"name:xx":"La Huasteca, Subregi\u00f3n"}}
>>>>>>> 03f74aca74312dbeaf24d7e61306dd6a786dc3d0
