{
  "id": 2456646,
  "type": "Feature",
  "properties": {
    "tgn:hierarchy":[
        "tgn:2456646",
        "tgn:1000001",
        "tgn:7012149",
        "tgn:2002302",
        "tgn:7013961",
        "tgn:7029392"
    ],
    "tgn:id":2456646,
    "tgn:name":"Little Island Run",
    "tgn:placetype":[
        "aat:300008699"
    ]
},
  "bbox": [],
  "geometry": {"coordinates":[-81.3333,39.0833],"type":"Point"}
}