{
  "id": 7034110,
  "type": "Feature",
  "properties": {
    "tgn:hierarchy":[
        "tgn:7034110",
        "tgn:1003468",
        "tgn:1000003",
        "tgn:7010380",
        "tgn:1000080",
        "tgn:7029392"
    ],
    "tgn:id":7034110,
    "tgn:name":"Masseria Perrandina",
    "tgn:placetype":[
        "aat:300000206"
    ]
},
  "bbox": [],
  "geometry": {"coordinates":[18.115278,40.431111],"type":"Point"}
}