{
  "id": 1134210,
  "type": "Feature",
  "properties": {
    "tgn:hierarchy":[
        "tgn:1134210",
        "tgn:1000610",
        "tgn:1000002",
        "tgn:1000058",
        "tgn:7029392"
    ],
    "tgn:id":1134210,
    "tgn:name":"Pintos, Arroyo de",
    "tgn:placetype":[
        "aat:300008706"
    ]
},
  "bbox": [],
  "geometry": {"coordinates":[-56.85,-33.9167],"type":"Point"}
}