{
  "id": 1087412,
  "type": "Feature",
  "properties": {
    "tgn:hierarchy":[
        "tgn:1087412",
        "tgn:1000486",
        "tgn:7001242",
        "tgn:7016752",
        "tgn:7029392"
    ],
    "tgn:id":1087412,
    "tgn:name":"Charou\u00efne",
    "tgn:placetype":[
        "aat:300008347"
    ]
},
  "bbox": [],
  "geometry": {"coordinates":[-0.2667,29.0167],"type":"Point"}
}