{
  "id": 7309024,
  "type": "Feature",
  "properties": {
    "tgn:hierarchy":[
        "tgn:7309024",
        "tgn:1001630",
        "tgn:1000049",
        "tgn:1000002",
        "tgn:7029392"
    ],
    "tgn:id":7309024,
    "tgn:name":"Los Sapos",
    "tgn:placetype":[
        "aat:300008347"
    ]
},
  "bbox": [],
  "geometry": {"coordinates":[-69.516667,-26.466667],"type":"Point"}
}