{
  "id": 2682779,
  "type": "Feature",
  "properties": {
    "tgn:hierarchy":[
        "tgn:2682779",
        "tgn:1000001",
        "tgn:2000922",
        "tgn:7012149",
        "tgn:7007515",
        "tgn:7029392"
    ],
    "tgn:id":2682779,
    "tgn:name":"Southwest Cove",
    "tgn:placetype":[
        "aat:300132316"
    ]
},
  "bbox": [],
  "geometry": {"coordinates":[-68.4833,44.7167],"type":"Point"}
}