{
  "id": 7292074,
  "type": "Feature",
  "properties": {
    "tgn:hierarchy":[
        "tgn:7292074",
        "tgn:7002464",
        "tgn:1000049",
        "tgn:1000002",
        "tgn:7029392"
    ],
    "tgn:id":7292074,
    "tgn:name":"Filo",
    "tgn:placetype":[
        "aat:300387033"
    ]
},
  "bbox": [],
  "geometry": {"coordinates":[-70.033333,-19.883333],"type":"Point"}
}