{
  "id": 7372060,
  "type": "Feature",
  "properties": {
    "tgn:hierarchy":[
        "tgn:7372060",
        "tgn:7005581",
        "tgn:1000001",
        "tgn:7005560",
        "tgn:7029392"
    ],
    "tgn:id":7372060,
    "tgn:name":"Lajas",
    "tgn:placetype":[
        "aat:300008347"
    ]
},
  "bbox": [],
  "geometry": {"coordinates":[-106.816667,29.05],"type":"Point"}
}