{
  "id": 1035561,
  "type": "Feature",
  "properties": {
    "tgn:hierarchy":[
        "tgn:1035561",
        "tgn:7002871",
        "tgn:1000003",
        "tgn:1000070",
        "tgn:7029392"
    ],
    "tgn:id":1035561,
    "tgn:name":"Sainte-Agathe",
    "tgn:placetype":[
        "aat:300008347"
    ]
},
  "bbox": [],
  "geometry": {"coordinates":[3.6167,45.8167],"type":"Point"}
}