{
  "id": 2722048,
  "type": "Feature",
  "properties": {
    "tgn:hierarchy":[
        "tgn:2722048",
        "tgn:1000001",
        "tgn:7012149",
        "tgn:1002506",
        "tgn:7007919",
        "tgn:7029392"
    ],
    "tgn:id":2722048,
    "tgn:name":"Timber Swamp",
    "tgn:placetype":[
        "aat:300008699"
    ]
},
  "bbox": [],
  "geometry": {"coordinates":[-76.8167,36.9667],"type":"Point"}
}