{
  "id": 7514354,
  "type": "Feature",
  "properties": {
    "tgn:hierarchy":[
        "tgn:7514354",
        "tgn:1008380",
        "tgn:1000226",
        "tgn:7000512",
        "tgn:1000006",
        "tgn:7029392"
    ],
    "tgn:id":7514354,
    "tgn:name:en":"Dry River",
    "tgn:placetype":[
        "aat:300008699"
    ]
},
  "bbox": [],
  "geometry": {"coordinates":[175.383333,-41.25],"type":"Point"}
}