{
  "id": 7222834,
  "type": "Feature",
  "properties": {
    "tgn:hierarchy":[
        "tgn:7222834",
        "tgn:7002711",
        "tgn:7001338",
        "tgn:1000003",
        "tgn:1000074",
        "tgn:7029392"
    ],
    "tgn:id":7222834,
    "tgn:name":"Mesong\u00ed",
    "tgn:placetype":[
        "aat:300008347"
    ]
},
  "bbox": [],
  "geometry": {"coordinates":[19.933889,39.478056],"type":"Point"}
}