{
  "id": 2519401,
  "type": "Feature",
  "properties": {
    "tgn:hierarchy":[
        "tgn:2519401",
        "tgn:1000001",
        "tgn:7012149",
        "tgn:1002961",
        "tgn:7007568",
        "tgn:7029392"
    ],
    "tgn:id":2519401,
    "tgn:name":"Modena Gardens",
    "tgn:placetype":[
        "aat:300008347"
    ]
},
  "bbox": [],
  "geometry": {"coordinates":[-74.1167,41.6333],"type":"Point"}
}