{
  "id": 2161991,
  "type": "Feature",
  "properties": {
    "tgn:hierarchy":[
        "tgn:2161991",
        "tgn:1000001",
        "tgn:7012149",
        "tgn:2000280",
        "tgn:7007240",
        "tgn:7029392"
    ],
    "tgn:id":2161991,
    "tgn:name":"Bells River",
    "tgn:placetype":[
        "aat:300008707"
    ]
},
  "bbox": [],
  "geometry": {"coordinates":[-81.5667,30.7167],"type":"Point"}
}