{
  "id": 1032447,
  "type": "Feature",
  "properties": {
    "tgn:hierarchy":[
        "tgn:1032447",
        "tgn:1000003",
        "tgn:7002885",
        "tgn:1000070",
        "tgn:7029392"
    ],
    "tgn:id":1032447,
    "tgn:name":"Castries",
    "tgn:placetype":[
        "aat:300008347"
    ]
},
  "bbox": [],
  "geometry": {"coordinates":[3.9833,43.6833],"type":"Point"}
}