{
  "id": 2244323,
  "type": "Feature",
  "properties": {
    "tgn:hierarchy":[
        "tgn:2244323",
        "tgn:1000001",
        "tgn:1002347",
        "tgn:7012149",
        "tgn:7007568",
        "tgn:7029392"
    ],
    "tgn:id":2244323,
    "tgn:name":"Clifton Point",
    "tgn:placetype":[
        "aat:300008850"
    ]
},
  "bbox": [],
  "geometry": {"coordinates":[-73.9333,41.95],"type":"Point"}
}