{
  "id": 7394341,
  "type": "Feature",
  "properties": {
    "tgn:hierarchy":[
        "tgn:7394341",
        "tgn:1000001",
        "tgn:7005589",
        "tgn:7005560",
        "tgn:7029392"
    ],
    "tgn:id":7394341,
    "tgn:name":"Sangre Linda, Cerro",
    "tgn:placetype":[
        "aat:300008795"
    ]
},
  "bbox": [],
  "geometry": {"coordinates":[-100.166667,24.483333],"type":"Point"}
}