{
  "id": 2119561,
  "type": "Feature",
  "properties": {
    "tgn:hierarchy":[
        "tgn:2119561",
        "tgn:1000001",
        "tgn:7012149",
        "tgn:2002290",
        "tgn:7013961",
        "tgn:7029392"
    ],
    "tgn:id":2119561,
    "tgn:name":"Pettus",
    "tgn:placetype":[
        "aat:300008347"
    ]
},
  "bbox": [],
  "geometry": {"coordinates":[-81.5333,37.95],"type":"Point"}
}