{
  "id": 2299218,
  "type": "Feature",
  "properties": {
    "tgn:hierarchy":[
        "tgn:2299218",
        "tgn:1000001",
        "tgn:7012149",
        "tgn:2001461",
        "tgn:7007568",
        "tgn:7029392"
    ],
    "tgn:id":2299218,
    "tgn:name":"Duck Hole",
    "tgn:placetype":[
        "aat:300132316"
    ]
},
  "bbox": [],
  "geometry": {"coordinates":[-73.8167,44.0167],"type":"Point"}
}