{
  "id": 2631279,
  "type": "Feature",
  "properties": {
    "tgn:hierarchy":[
        "tgn:2631279",
        "tgn:7002659",
        "tgn:1000001",
        "tgn:2000012",
        "tgn:7012149",
        "tgn:7029392"
    ],
    "tgn:id":2631279,
    "tgn:name":"Round Pond",
    "tgn:placetype":[
        "aat:300008680"
    ]
},
  "bbox": [],
  "geometry": {"coordinates":[-88.05,31.65],"type":"Point"}
}