{
  "id": 2715565,
  "type": "Feature",
  "properties": {
    "tgn:hierarchy":[
        "tgn:2715565",
        "tgn:7030516",
        "tgn:7006450",
        "tgn:1000001",
        "tgn:7012149",
        "tgn:7029392"
    ],
    "tgn:id":2715565,
    "tgn:name":"Terrible Mountain",
    "tgn:placetype":[
        "aat:300008798"
    ]
},
  "bbox": [],
  "geometry": {"coordinates":[173.15,52.85],"type":"Point"}
}