{
  "id": 2727859,
  "type": "Feature",
  "properties": {
    "tgn:hierarchy":[
        "tgn:2727859",
        "tgn:2001732",
        "tgn:1000001",
        "tgn:7012149",
        "tgn:7007712",
        "tgn:7029392"
    ],
    "tgn:id":2727859,
    "tgn:name":"Tramway",
    "tgn:placetype":[
        "aat:300008347"
    ]
},
  "bbox": [],
  "geometry": {"coordinates":[-80.1333,33.05],"type":"Point"}
}