{
  "id": 7545568,
  "type": "Feature",
  "properties": {
    "tgn:hierarchy":[
        "tgn:7545568",
        "tgn:1000004",
        "tgn:7000198",
        "tgn:7016883",
        "tgn:7029392"
    ],
    "tgn:id":7545568,
    "tgn:name:en":"B\u0101gha Pur\u0101na",
    "tgn:placetype":[
        "aat:300008347"
    ]
},
  "bbox": [],
  "geometry": {"coordinates":[75.095718,30.687468],"type":"Point"}
}