{
  "id": 2130443,
  "type": "Feature",
  "properties": {
    "tgn:hierarchy":[
        "tgn:2130443",
        "tgn:1000001",
        "tgn:7012149",
        "tgn:2000525",
        "tgn:7007251",
        "tgn:7029392"
    ],
    "tgn:id":2130443,
    "tgn:name":"Allforks Creek",
    "tgn:placetype":[
        "aat:300008706"
    ]
},
  "bbox": [],
  "geometry": {"coordinates":[-89.15,41.2667],"type":"Point"}
}