{
  "id": 2368416,
  "type": "Feature",
  "properties": {
    "tgn:hierarchy":[
        "tgn:2368416",
        "tgn:1000001",
        "tgn:7012149",
        "tgn:1002465",
        "tgn:7007252",
        "tgn:7029392"
    ],
    "tgn:id":2368416,
    "tgn:name":"Guilford Branch",
    "tgn:placetype":[
        "aat:300008699"
    ]
},
  "bbox": [],
  "geometry": {"coordinates":[-86.3333,39.6667],"type":"Point"}
}