{
  "id": 1001303,
  "type": "Feature",
  "properties": {
    "tgn:hierarchy":[
        "tgn:1001303",
        "tgn:7001242",
        "tgn:1000179",
        "tgn:7593679",
        "tgn:7029392"
    ],
    "tgn:id":1001303,
    "tgn:name":"Ifrane, Province d'",
    "tgn:placetype":[
        "aat:300387064",
        "aat:300387145",
        "aat:300000774"
    ]
},
  "bbox": [],
  "geometry": {"coordinates":[-5.25,33.4167],"type":"Point"}
}