{
  "id": 7184439,
  "type": "Feature",
  "properties": {
    "tgn:hierarchy":[
        "tgn:7184439",
        "tgn:1000003",
        "tgn:7003676",
        "tgn:7000084",
        "tgn:7029392"
    ],
    "tgn:id":7184439,
    "tgn:name":"Bahnhof Grauhof",
    "tgn:placetype":[
        "aat:300007783"
    ]
},
  "bbox": [],
  "geometry": {"coordinates":[10.433333,51.95],"type":"Point"}
}