{
  "id": 7491553,
  "type": "Feature",
  "properties": {
    "tgn:hierarchy":[
        "tgn:7491553",
        "tgn:1000004",
        "tgn:7491221",
        "tgn:1000141",
        "tgn:7029392"
    ],
    "tgn:id":7491553,
    "tgn:name":"Bei Xi",
    "tgn:placetype":[
        "aat:300008699"
    ]
},
  "bbox": [],
  "geometry": {"coordinates":[121.283563,23.000592],"type":"Point"}
}