{
  "id": 2201184,
  "type": "Feature",
  "properties": {
    "tgn:hierarchy":[
        "tgn:2201184",
        "tgn:1000001",
        "tgn:7012149",
        "tgn:2000438",
        "tgn:7007248",
        "tgn:7029392"
    ],
    "tgn:id":2201184,
    "tgn:name":"Bucaneer Lake",
    "tgn:placetype":[
        "aat:300006191"
    ]
},
  "bbox": [],
  "geometry": {"coordinates":[-83.7167,33.8167],"type":"Point"}
}