<<<<<<< HEAD
{
  "id": 2767706,
  "type": "Feature",
  "properties": {
    "tgn:hierarchy":[
        "tgn:2767706",
        "tgn:1000001",
        "tgn:7012149",
        "tgn:7007707",
        "tgn:7029392"
    ],
    "tgn:id":2767706,
    "tgn:name":"Whitegrass Creek",
    "tgn:placetype":[
        "aat:300008706"
    ]
},
  "bbox": [],
  "geometry": {"coordinates":[-96.0167,34.0667],"type":"Point"}
}
=======
{"geometry":{"type":"Point","coordinates":[-96.016700,34.066700]},"type":"Feature","properties":{"hierarchy":["tgn:2767706","tgn:1000001","tgn:7012149","tgn:7007707","tgn:7029392"],"placetype":["aat:300008706"],"id":2767706,"name:xx":"Whitegrass Creek"}}
>>>>>>> 03f74aca74312dbeaf24d7e61306dd6a786dc3d0
