{
  "id": 7541902,
  "type": "Feature",
  "properties": {
    "tgn:hierarchy":[
        "tgn:7541902",
        "tgn:7001242",
        "tgn:7016833",
        "tgn:7001335",
        "tgn:7029392"
    ],
    "tgn:id":7541902,
    "tgn:name":"Maz\u012bra'a, W\u0101d\u012b al",
    "tgn:placetype":[
        "aat:300379998"
    ]
},
  "bbox": [],
  "geometry": {"coordinates":[34.153056,30.6575],"type":"Point"}
}