{
  "id": 2629560,
  "type": "Feature",
  "properties": {
    "tgn:hierarchy":[
        "tgn:2629560",
        "tgn:1000001",
        "tgn:1002270",
        "tgn:7012149",
        "tgn:7007708",
        "tgn:7029392"
    ],
    "tgn:id":2629560,
    "tgn:name":"Rosewood",
    "tgn:placetype":[
        "aat:300008347"
    ]
},
  "bbox": [],
  "geometry": {"coordinates":[-122.7167,45.3833],"type":"Point"}
}