{
  "id": 7083618,
  "type": "Feature",
  "properties": {
    "tgn:hierarchy":[
        "tgn:7083618",
        "tgn:1000003",
        "tgn:7003677",
        "tgn:7000084",
        "tgn:7029392"
    ],
    "tgn:id":7083618,
    "tgn:name":"Wiedey-Bach",
    "tgn:placetype":[
        "aat:300008699"
    ]
},
  "bbox": [],
  "geometry": {"coordinates":[8.35,51.433333],"type":"Point"}
}