{
  "id": 2645588,
  "type": "Feature",
  "properties": {
    "tgn:hierarchy":[
        "tgn:2645588",
        "tgn:1000001",
        "tgn:1002665",
        "tgn:7012149",
        "tgn:7007517",
        "tgn:7029392"
    ],
    "tgn:id":2645588,
    "tgn:name":"Sawins Pond",
    "tgn:placetype":[
        "aat:300008680"
    ]
},
  "bbox": [],
  "geometry": {"coordinates":[-71.15,42.35],"type":"Point"}
}