{
  "id": 2331832,
  "type": "Feature",
  "properties": {
    "tgn:hierarchy":[
        "tgn:2331832",
        "tgn:1000001",
        "tgn:7012149",
        "tgn:2000494",
        "tgn:7007250",
        "tgn:7029392"
    ],
    "tgn:id":2331832,
    "tgn:name":"Fletcher Butte",
    "tgn:placetype":[
        "aat:300008798"
    ]
},
  "bbox": [],
  "geometry": {"coordinates":[-116.1833,44.1833],"type":"Point"}
}