{
  "id": 2731566,
  "type": "Feature",
  "properties": {
    "tgn:hierarchy":[
        "tgn:2731566",
        "tgn:1000001",
        "tgn:2001409",
        "tgn:7012149",
        "tgn:7007526",
        "tgn:7029392"
    ],
    "tgn:id":2731566,
    "tgn:name":"Tule Lake",
    "tgn:placetype":[
        "aat:300006191"
    ]
},
  "bbox": [],
  "geometry": {"coordinates":[-118.4333,39.6333],"type":"Point"}
}