{
  "id": 7562023,
  "type": "Feature",
  "properties": {
    "tgn:hierarchy":[
        "tgn:7562023",
        "tgn:1000004",
        "tgn:7000198",
        "tgn:7016722",
        "tgn:7029392"
    ],
    "tgn:id":7562023,
    "tgn:name:en":"Karehka",
    "tgn:placetype":[
        "aat:300008347"
    ]
},
  "bbox": [],
  "geometry": {"coordinates":[79.9819,27.1413],"type":"Point"}
}