{
  "id": 2591789,
  "type": "Feature",
  "properties": {
    "tgn:hierarchy":[
        "tgn:2591789",
        "tgn:1000001",
        "tgn:7012149",
        "tgn:2001615",
        "tgn:7007706",
        "tgn:7029392"
    ],
    "tgn:id":2591789,
    "tgn:name":"Pond Hollow",
    "tgn:placetype":[
        "aat:300008761"
    ]
},
  "bbox": [],
  "geometry": {"coordinates":[-82.65,38.7167],"type":"Point"}
}