{
  "id": 7246417,
  "type": "Feature",
  "properties": {
    "tgn:hierarchy":[
        "tgn:7246417",
        "tgn:7003456",
        "tgn:1000003",
        "tgn:1000063",
        "tgn:7018236",
        "tgn:7029392"
    ],
    "tgn:id":7246417,
    "tgn:name":"Bosbeek",
    "tgn:placetype":[
        "aat:300008699"
    ]
},
  "bbox": [],
  "geometry": {"coordinates":[4.796359,51.200928],"type":"Point"}
}