{
  "id": 2714811,
  "type": "Feature",
  "properties": {
    "tgn:hierarchy":[
        "tgn:2714811",
        "tgn:1000001",
        "tgn:7012149",
        "tgn:7021314",
        "tgn:7007521",
        "tgn:7029392"
    ],
    "tgn:id":2714811,
    "tgn:name":"Tenmile Creek",
    "tgn:placetype":[
        "aat:300008706"
    ]
},
  "bbox": [],
  "geometry": {"coordinates":[-96.05,44.85],"type":"Point"}
}