<<<<<<< HEAD
{
  "id": 2259520,
  "type": "Feature",
  "properties": {
    "tgn:hierarchy":[
        "tgn:2259520",
        "tgn:1000001",
        "tgn:2002109",
        "tgn:7012149",
        "tgn:7007827",
        "tgn:7029392"
    ],
    "tgn:id":2259520,
    "tgn:name":"Cottonwood Tanks",
    "tgn:placetype":[
        "aat:300006191"
    ]
},
  "bbox": [],
  "geometry": {"coordinates":[-110.9667,37.8],"type":"Point"}
}
=======
{"geometry":{"type":"Point","coordinates":[-110.966700,37.800000]},"type":"Feature","properties":{"hierarchy":["tgn:2259520","tgn:1000001","tgn:2002109","tgn:7012149","tgn:7007827","tgn:7029392"],"placetype":["aat:300006191"],"id":2259520,"name:xx":"Cottonwood Tanks"}}
>>>>>>> 03f74aca74312dbeaf24d7e61306dd6a786dc3d0
