{
  "id": 7443800,
  "type": "Feature",
  "properties": {
    "tgn:hierarchy":[
        "tgn:7443800",
        "tgn:7002448",
        "tgn:7008700",
        "tgn:1000003",
        "tgn:7008591",
        "tgn:7029392"
    ],
    "tgn:id":7443800,
    "tgn:name:en":"Tempo River",
    "tgn:placetype":[
        "aat:300008699"
    ]
},
  "bbox": [],
  "geometry": {"coordinates":[-7.483333,54.283333],"type":"Point"}
}