<<<<<<< HEAD
{
  "id": 2337368,
  "type": "Feature",
  "properties": {
    "tgn:hierarchy":[
        "tgn:2337368",
        "tgn:1000001",
        "tgn:7012149",
        "tgn:1002588",
        "tgn:7007520",
        "tgn:7029392"
    ],
    "tgn:id":2337368,
    "tgn:name":"Fouty Creek",
    "tgn:placetype":[
        "aat:300008706"
    ]
},
  "bbox": [],
  "geometry": {"coordinates":[-84.15,41.95],"type":"Point"}
}
=======
{"geometry":{"type":"Point","coordinates":[-84.150000,41.950000]},"type":"Feature","properties":{"hierarchy":["tgn:2337368","tgn:1000001","tgn:7012149","tgn:1002588","tgn:7007520","tgn:7029392"],"placetype":["aat:300008706"],"id":2337368,"name:xx":"Fouty Creek"}}
>>>>>>> 03f74aca74312dbeaf24d7e61306dd6a786dc3d0
