{
  "id": 2182556,
  "type": "Feature",
  "properties": {
    "tgn:hierarchy":[
        "tgn:2182556",
        "tgn:1000001",
        "tgn:7012149",
        "tgn:2001904",
        "tgn:7007825",
        "tgn:7029392"
    ],
    "tgn:id":2182556,
    "tgn:name":"Blue Sky",
    "tgn:placetype":[
        "aat:300008347"
    ]
},
  "bbox": [],
  "geometry": {"coordinates":[-87.8667,35.75],"type":"Point"}
}