{
  "id": 2537791,
  "type": "Feature",
  "properties": {
    "tgn:hierarchy":[
        "tgn:2537791",
        "tgn:1000001",
        "tgn:7012149",
        "tgn:2001989",
        "tgn:7007826",
        "tgn:7029392"
    ],
    "tgn:id":2537791,
    "tgn:name":"Nell Tank",
    "tgn:placetype":[
        "aat:300006191"
    ]
},
  "bbox": [],
  "geometry": {"coordinates":[-101.2333,33.1667],"type":"Point"}
}