{
  "id": 7527262,
  "type": "Feature",
  "properties": {
    "tgn:hierarchy":[
        "tgn:7527262",
        "tgn:7001242",
        "tgn:7016833",
        "tgn:1001418",
        "tgn:7029392"
    ],
    "tgn:id":7527262,
    "tgn:name:en":"Z\u0327ahr al \u1e28im\u0101r, Minq\u0101r",
    "tgn:placetype":[
        "aat:300008749"
    ]
},
  "bbox": [],
  "geometry": {"coordinates":[27.920195,30.382873],"type":"Point"}
}