{
  "id": 2091788,
  "type": "Feature",
  "properties": {
    "tgn:hierarchy":[
        "tgn:2091788",
        "tgn:1000001",
        "tgn:1002213",
        "tgn:7012149",
        "tgn:7007710",
        "tgn:7029392"
    ],
    "tgn:id":2091788,
    "tgn:name":"Penn Valley",
    "tgn:placetype":[
        "aat:300008347"
    ]
},
  "bbox": [],
  "geometry": {"coordinates":[-74.7833,40.1667],"type":"Point"}
}