{
  "id": 7462274,
  "type": "Feature",
  "properties": {
    "tgn:hierarchy":[
        "tgn:7462274",
        "tgn:7002444",
        "tgn:1000003",
        "tgn:7029508",
        "tgn:7008591",
        "tgn:7029392"
    ],
    "tgn:id":7462274,
    "tgn:name:en":"Hellabrick's Wick",
    "tgn:placetype":[
        "aat:300132316"
    ]
},
  "bbox": [],
  "geometry": {"coordinates":[-2.066667,60.116667],"type":"Point"}
}