{
  "id": 1112821,
  "type": "Feature",
  "properties": {
    "tgn:hierarchy":[
        "tgn:1112821",
        "tgn:7005685",
        "tgn:1000001",
        "tgn:7005802",
        "tgn:7029392"
    ],
    "tgn:id":1112821,
    "tgn:name":"Cobequid Bay",
    "tgn:placetype":[
        "aat:300132316"
    ]
},
  "bbox": [],
  "geometry": {"coordinates":[-63.8333,45.3333],"type":"Point"}
}