{
  "id": 7072797,
  "type": "Feature",
  "properties": {
    "tgn:hierarchy":[
        "tgn:7072797",
        "tgn:1000003",
        "tgn:7003688",
        "tgn:7000084",
        "tgn:7029392"
    ],
    "tgn:id":7072797,
    "tgn:name":"Striepel",
    "tgn:placetype":[
        "aat:300000206"
    ]
},
  "bbox": [],
  "geometry": {"coordinates":[9.433333,53.95],"type":"Point"}
}