{
  "id": 2732465,
  "type": "Feature",
  "properties": {
    "tgn:hierarchy":[
        "tgn:2732465",
        "tgn:1000001",
        "tgn:7012149",
        "tgn:1003038",
        "tgn:7007517",
        "tgn:7029392"
    ],
    "tgn:id":2732465,
    "tgn:name":"Turkey Brook",
    "tgn:placetype":[
        "aat:300008699"
    ]
},
  "bbox": [],
  "geometry": {"coordinates":[-71.9333,42.3333],"type":"Point"}
}