{
  "id": 2547445,
  "type": "Feature",
  "properties": {
    "tgn:hierarchy":[
        "tgn:2547445",
        "tgn:1000001",
        "tgn:7012149",
        "tgn:2002375",
        "tgn:7007923",
        "tgn:7029392"
    ],
    "tgn:id":2547445,
    "tgn:name":"North Fork South Fork Bear Creek",
    "tgn:placetype":[
        "aat:300008706"
    ]
},
  "bbox": [],
  "geometry": {"coordinates":[-105.0833,41.5167],"type":"Point"}
}