{
  "id": 7356846,
  "type": "Feature",
  "properties": {
    "tgn:hierarchy":[
        "tgn:7356846",
        "tgn:7005581",
        "tgn:1000001",
        "tgn:7005560",
        "tgn:7029392"
    ],
    "tgn:id":7356846,
    "tgn:name":"Chacone\u00f1a, Sierra",
    "tgn:placetype":[
        "aat:300266640"
    ]
},
  "bbox": [],
  "geometry": {"coordinates":[-106.316667,27.983333],"type":"Point"}
}