<<<<<<< HEAD
{
  "id": 7356846,
  "type": "Feature",
  "properties": {
    "tgn:hierarchy":[
        "tgn:7356846",
        "tgn:7005581",
        "tgn:1000001",
        "tgn:7005560",
        "tgn:7029392"
    ],
    "tgn:id":7356846,
    "tgn:name":"Chacone\u00f1a, Sierra",
    "tgn:placetype":[
        "aat:300266640"
    ]
},
  "bbox": [],
  "geometry": {"coordinates":[-106.316667,27.983333],"type":"Point"}
}
=======
{"geometry":{"type":"Point","coordinates":[-106.316667,27.983333]},"type":"Feature","properties":{"hierarchy":["tgn:7356846","tgn:7005581","tgn:1000001","tgn:7005560","tgn:7029392"],"placetype":["aat:300266640"],"id":7356846,"name:xx":"Chacone\u00f1a, Sierra"}}
>>>>>>> 03f74aca74312dbeaf24d7e61306dd6a786dc3d0
