{
  "id": 7434403,
  "type": "Feature",
  "properties": {
    "tgn:hierarchy":[
        "tgn:7434403",
        "tgn:1000001",
        "tgn:1001893",
        "tgn:7005560",
        "tgn:7029392"
    ],
    "tgn:id":7434403,
    "tgn:name":"Chepavilzaj",
    "tgn:placetype":[
        "aat:300008795"
    ]
},
  "bbox": [],
  "geometry": {"coordinates":[-92.166667,15.216667],"type":"Point"}
}