{
  "id": 2411734,
  "type": "Feature",
  "properties": {
    "tgn:hierarchy":[
        "tgn:2411734",
        "tgn:1000001",
        "tgn:7012149",
        "tgn:1002432",
        "tgn:7007706",
        "tgn:7029392"
    ],
    "tgn:id":2411734,
    "tgn:name":"Indian Lakes Recreation Area Upper Lake",
    "tgn:placetype":[
        "aat:300006191"
    ]
},
  "bbox": [],
  "geometry": {"coordinates":[-81.5667,39.9333],"type":"Point"}
}