{
  "id": 2702560,
  "type": "Feature",
  "properties": {
    "tgn:hierarchy":[
        "tgn:2702560",
        "tgn:1000001",
        "tgn:7012149",
        "tgn:7007248",
        "tgn:7029392"
    ],
    "tgn:id":2702560,
    "tgn:name":"Sulphur Creek",
    "tgn:placetype":[
        "aat:300008706"
    ]
},
  "bbox": [],
  "geometry": {"coordinates":[-84.7333,32.9167],"type":"Point"}
}