{
  "id": 2223630,
  "type": "Feature",
  "properties": {
    "tgn:hierarchy":[
        "tgn:2223630",
        "tgn:1000001",
        "tgn:7012149",
        "tgn:2001844",
        "tgn:7007825",
        "tgn:7029392"
    ],
    "tgn:id":2223630,
    "tgn:name":"Carter Creek",
    "tgn:placetype":[
        "aat:300008706"
    ]
},
  "bbox": [],
  "geometry": {"coordinates":[-86.1333,35.9167],"type":"Point"}
}