{
  "id": 7572715,
  "type": "Feature",
  "properties": {
    "tgn:hierarchy":[
        "tgn:7572715",
        "tgn:1000004",
        "tgn:7000198",
        "tgn:7016788",
        "tgn:7029392"
    ],
    "tgn:id":7572715,
    "tgn:name:en":"Gadra Road",
    "tgn:placetype":[
        "aat:300007783"
    ]
},
  "bbox": [],
  "geometry": {"coordinates":[70.642287,25.744224],"type":"Point"}
}