{
  "id": 1122477,
  "type": "Feature",
  "properties": {
    "tgn:hierarchy":[
        "tgn:1122477",
        "tgn:1000001",
        "tgn:7012149",
        "tgn:7007568",
        "tgn:7029392"
    ],
    "tgn:id":1122477,
    "tgn:name":"Canisteo",
    "tgn:placetype":[
        "aat:300008707"
    ]
},
  "bbox": [],
  "geometry": {"coordinates":[-77.8833,42.3833],"type":"Point"}
}