{
  "id": 2540588,
  "type": "Feature",
  "properties": {
    "tgn:hierarchy":[
        "tgn:2540588",
        "tgn:1000001",
        "tgn:7012149",
        "tgn:7007158",
        "tgn:2000245",
        "tgn:7029392"
    ],
    "tgn:id":2540588,
    "tgn:name":"Newton Gulch Reservoir",
    "tgn:placetype":[
        "aat:300006191"
    ]
},
  "bbox": [],
  "geometry": {"coordinates":[-106.8667,40.0667],"type":"Point"}
}