{
  "id": 7322464,
  "type": "Feature",
  "properties": {
    "tgn:hierarchy":[
        "tgn:7322464",
        "tgn:7002824",
        "tgn:1000003",
        "tgn:7002786",
        "tgn:1000095",
        "tgn:7029392"
    ],
    "tgn:id":7322464,
    "tgn:name":"San Saturnino",
    "tgn:placetype":[
        "aat:300008347"
    ]
},
  "bbox": [],
  "geometry": {"coordinates":[-8.066667,43.533333],"type":"Point"}
}