{
  "id": 2214826,
  "type": "Feature",
  "properties": {
    "tgn:hierarchy":[
        "tgn:2214826",
        "tgn:1000001",
        "tgn:7012149",
        "tgn:2002174",
        "tgn:7007919",
        "tgn:7029392"
    ],
    "tgn:id":2214826,
    "tgn:name":"Calfee Knob",
    "tgn:placetype":[
        "aat:300008798"
    ]
},
  "bbox": [],
  "geometry": {"coordinates":[-80.4833,37.0167],"type":"Point"}
}