{
  "id": 7238758,
  "type": "Feature",
  "properties": {
    "tgn:hierarchy":[
        "tgn:7238758",
        "tgn:7003460",
        "tgn:1000003",
        "tgn:1000063",
        "tgn:4012014",
        "tgn:7029392"
    ],
    "tgn:id":7238758,
    "tgn:name":"Hochtumsknopf",
    "tgn:placetype":[
        "aat:300008777"
    ]
},
  "bbox": [],
  "geometry": {"coordinates":[6.057778,50.231944],"type":"Point"}
}