{
  "id": 7509497,
  "type": "Feature",
  "properties": {
    "tgn:hierarchy":[
        "tgn:7509497",
        "tgn:7016670",
        "tgn:1008380",
        "tgn:1000226",
        "tgn:1000006",
        "tgn:7029392"
    ],
    "tgn:id":7509497,
    "tgn:name:en":"Waikoau River",
    "tgn:placetype":[
        "aat:300008699"
    ]
},
  "bbox": [],
  "geometry": {"coordinates":[176.883333,-39.266667],"type":"Point"}
}