{
  "id": 2201223,
  "type": "Feature",
  "properties": {
    "tgn:hierarchy":[
        "tgn:2201223",
        "tgn:1000001",
        "tgn:7012149",
        "tgn:2002005",
        "tgn:7007826",
        "tgn:7029392"
    ],
    "tgn:id":2201223,
    "tgn:name":"Buchanan Dam",
    "tgn:placetype":[
        "aat:300008347"
    ]
},
  "bbox": [],
  "geometry": {"coordinates":[-98.4167,30.7333],"type":"Point"}
}