{
  "id": 7015325,
  "type": "Feature",
  "properties": {
    "tgn:hierarchy":[
        "tgn:7015325",
        "tgn:7017310",
        "tgn:1000003",
        "tgn:7006663",
        "tgn:7029392"
    ],
    "tgn:id":7015325,
    "tgn:name":"Vid",
    "tgn:placetype":[
        "aat:300008347",
        "aat:300000810",
        "aat:300008389",
        "aat:300008372"
    ]
},
  "bbox": [],
  "geometry": {"coordinates":[17.598,43.046],"type":"Point"}
}