{
  "id": 7592223,
  "type": "Feature",
  "properties": {
    "tgn:hierarchy":[
        "tgn:7592223",
        "tgn:1000004",
        "tgn:7000198",
        "tgn:7000799",
        "tgn:7029392"
    ],
    "tgn:id":7592223,
    "tgn:name:en":"Sure Chak",
    "tgn:placetype":[
        "aat:300008347"
    ]
},
  "bbox": [],
  "geometry": {"coordinates":[74.805,32.694104],"type":"Point"}
}