{
  "id": 7463668,
  "type": "Feature",
  "properties": {
    "tgn:hierarchy":[
        "tgn:7463668",
        "tgn:7019094",
        "tgn:7002444",
        "tgn:1000003",
        "tgn:7008591",
        "tgn:7029392"
    ],
    "tgn:id":7463668,
    "tgn:name:en":"Loin, Glen",
    "tgn:placetype":[
        "aat:300008761"
    ]
},
  "bbox": [],
  "geometry": {"coordinates":[-4.733333,56.216667],"type":"Point"}
}