{
  "id": 2657085,
  "type": "Feature",
  "properties": {
    "tgn:hierarchy":[
        "tgn:2657085",
        "tgn:1000001",
        "tgn:2001410",
        "tgn:7012149",
        "tgn:7007526",
        "tgn:7029392"
    ],
    "tgn:id":2657085,
    "tgn:name":"Sheep Pass Guzzler",
    "tgn:placetype":[
        "aat:300006191"
    ]
},
  "bbox": [],
  "geometry": {"coordinates":[-115.2833,36.8333],"type":"Point"}
}