{
  "id": 1095124,
  "type": "Feature",
  "properties": {
    "tgn:hierarchy":[
        "tgn:1095124",
        "tgn:7001242",
        "tgn:1001075",
        "tgn:7016833",
        "tgn:7029392"
    ],
    "tgn:id":1095124,
    "tgn:name:en":"\u015eaf\u0163 al Mul\u016bk",
    "tgn:placetype":[
        "aat:300008347"
    ]
},
  "bbox": [],
  "geometry": {"coordinates":[30.562,30.937],"type":"Point"}
}