{
  "id": 7272986,
  "type": "Feature",
  "properties": {
    "tgn:hierarchy":[
        "tgn:7272986",
        "tgn:7003616",
        "tgn:1000003",
        "tgn:7016845",
        "tgn:7029392"
    ],
    "tgn:id":7272986,
    "tgn:name:nl":"Van Ameland, Vlakte",
    "tgn:placetype":[
        "aat:300387036"
    ]
},
  "bbox": [],
  "geometry": {"coordinates":[5.55,53.516667],"type":"Point"}
}