<<<<<<< HEAD
{
  "id": 7028290,
  "type": "Feature",
  "properties": {
    "tgn:hierarchy":[
        "tgn:7028290",
        "tgn:7002445",
        "tgn:1000003",
        "tgn:7008160",
        "tgn:7008591",
        "tgn:7029392"
    ],
    "tgn:id":7028290,
    "tgn:name":"Bittering",
    "tgn:placetype":[
        "aat:300008347",
        "aat:300008372"
    ]
},
  "bbox": [],
  "geometry": {"coordinates":[0.864,52.717],"type":"Point"}
}
=======
{"geometry":{"type":"Point","coordinates":[0.864000,52.717000]},"type":"Feature","properties":{"hierarchy":["tgn:7028290","tgn:7002445","tgn:1000003","tgn:7008160","tgn:7008591","tgn:7029392"],"placetype":["aat:300008347","aat:300008372"],"id":7028290,"name:xx":"Bittering"}}
>>>>>>> 03f74aca74312dbeaf24d7e61306dd6a786dc3d0
