{
  "id": 7028290,
  "type": "Feature",
  "properties": {
    "tgn:hierarchy":[
        "tgn:7028290",
        "tgn:7002445",
        "tgn:1000003",
        "tgn:7008160",
        "tgn:7008591",
        "tgn:7029392"
    ],
    "tgn:id":7028290,
    "tgn:name":"Bittering",
    "tgn:placetype":[
        "aat:300008347",
        "aat:300008372"
    ]
},
  "bbox": [],
  "geometry": {"coordinates":[0.864,52.717],"type":"Point"}
}