{
  "id": 7110871,
  "type": "Feature",
  "properties": {
    "tgn:hierarchy":[
        "tgn:7110871",
        "tgn:1000003",
        "tgn:7000094",
        "tgn:7000084",
        "tgn:7029392"
    ],
    "tgn:id":7110871,
    "tgn:name":"Puchow",
    "tgn:placetype":[
        "aat:300008347"
    ]
},
  "bbox": [],
  "geometry": {"coordinates":[13.066667,53.533333],"type":"Point"}
}