{
  "id": 2770106,
  "type": "Feature",
  "properties": {
    "tgn:hierarchy":[
        "tgn:2770106",
        "tgn:1000001",
        "tgn:7012149",
        "tgn:2001488",
        "tgn:7007709",
        "tgn:7029392"
    ],
    "tgn:id":2770106,
    "tgn:name":"Wild Boar Point",
    "tgn:placetype":[
        "aat:300008850"
    ]
},
  "bbox": [],
  "geometry": {"coordinates":[-75.7333,35.65],"type":"Point"}
}