{
  "id": 2644836,
  "type": "Feature",
  "properties": {
    "tgn:hierarchy":[
        "tgn:2644836",
        "tgn:1000001",
        "tgn:2000863",
        "tgn:7012149",
        "tgn:7007256",
        "tgn:7029392"
    ],
    "tgn:id":2644836,
    "tgn:name":"Sassafras Island",
    "tgn:placetype":[
        "aat:300008791"
    ]
},
  "bbox": [],
  "geometry": {"coordinates":[-93.65,30.0833],"type":"Point"}
}