{
  "id": 7033594,
  "type": "Feature",
  "properties": {
    "tgn:hierarchy":[
        "tgn:7033594",
        "tgn:7003133",
        "tgn:1000003",
        "tgn:7008516",
        "tgn:1000080",
        "tgn:7029392"
    ],
    "tgn:id":7033594,
    "tgn:name":"Borgo Montanari",
    "tgn:placetype":[
        "aat:300008347"
    ]
},
  "bbox": [],
  "geometry": {"coordinates":[12.089722,44.3225],"type":"Point"}
}