{
  "id": 7556344,
  "type": "Feature",
  "properties": {
    "tgn:hierarchy":[
        "tgn:7556344",
        "tgn:1000004",
        "tgn:7000198",
        "tgn:1001882",
        "tgn:7029392"
    ],
    "tgn:id":7556344,
    "tgn:name:en":"Saundalga",
    "tgn:placetype":[
        "aat:300008347"
    ]
},
  "bbox": [],
  "geometry": {"coordinates":[74.35,16.483333],"type":"Point"}
}