{
  "id": 2690354,
  "type": "Feature",
  "properties": {
    "tgn:hierarchy":[
        "tgn:2690354",
        "tgn:1000001",
        "tgn:7012149",
        "tgn:2002119",
        "tgn:7007827",
        "tgn:7029392"
    ],
    "tgn:id":2690354,
    "tgn:name":"Stagecoach Wash",
    "tgn:placetype":[
        "aat:300008761"
    ]
},
  "bbox": [],
  "geometry": {"coordinates":[-110.05,37.0333],"type":"Point"}
}