{
  "id": 7173390,
  "type": "Feature",
  "properties": {
    "tgn:hierarchy":[
        "tgn:7173390",
        "tgn:7003669",
        "tgn:1000003",
        "tgn:7000084",
        "tgn:7029392"
    ],
    "tgn:id":7173390,
    "tgn:name":"Gro\u00dfreut",
    "tgn:placetype":[
        "aat:300000206"
    ]
},
  "bbox": [],
  "geometry": {"coordinates":[12.666667,47.966667],"type":"Point"}
}