{
  "id": 1030415,
  "type": "Feature",
  "properties": {
    "tgn:hierarchy":[
        "tgn:1030415",
        "tgn:7002445",
        "tgn:1000003",
        "tgn:7008145",
        "tgn:7008591",
        "tgn:7029392"
    ],
    "tgn:id":1030415,
    "tgn:name:en":"Redbourn",
    "tgn:placetype":[
        "aat:300008347",
        "aat:300008372"
    ]
},
  "bbox": [],
  "geometry": {"coordinates":[-0.383333,51.783333],"type":"Point"}
}