{
  "id": 2171311,
  "type": "Feature",
  "properties": {
    "tgn:hierarchy":[
        "tgn:2171311",
        "tgn:1000001",
        "tgn:7012149",
        "tgn:2002125",
        "tgn:7007827",
        "tgn:7029392"
    ],
    "tgn:id":2171311,
    "tgn:name":"Big Spring Hollow",
    "tgn:placetype":[
        "aat:300008761"
    ]
},
  "bbox": [],
  "geometry": {"coordinates":[-111.5667,40.2833],"type":"Point"}
}