{
  "id": 7511175,
  "type": "Feature",
  "properties": {
    "tgn:hierarchy":[
        "tgn:7511175",
        "tgn:1009227",
        "tgn:7001866",
        "tgn:1000226",
        "tgn:1000006",
        "tgn:7029392"
    ],
    "tgn:id":7511175,
    "tgn:name:en":"Sinclair, Mount",
    "tgn:placetype":[
        "aat:300008795"
    ]
},
  "bbox": [],
  "geometry": {"coordinates":[170.816667,-43.65],"type":"Point"}
}