{
  "id": 1013913,
  "type": "Feature",
  "properties": {
    "tgn:hierarchy":[
        "tgn:1013913",
        "tgn:7005685",
        "tgn:1000001",
        "tgn:7005734",
        "tgn:7029392"
    ],
    "tgn:id":1013913,
    "tgn:name":"Great Falls",
    "tgn:placetype":[
        "aat:300008347"
    ]
},
  "bbox": [],
  "geometry": {"coordinates":[-96.0167,50.45],"type":"Point"}
}