{
  "id": 7030229,
  "type": "Feature",
  "properties": {
    "tgn:hierarchy":[
        "tgn:7030229",
        "tgn:1000003",
        "tgn:7024620",
        "tgn:1000097",
        "tgn:7029392"
    ],
    "tgn:id":7030229,
    "tgn:name":"Tanum",
    "tgn:placetype":[
        "aat:300008347"
    ]
},
  "bbox": [],
  "geometry": {"coordinates":[11.254,58.777],"type":"Point"}
}