{
  "id": 2312152,
  "type": "Feature",
  "properties": {
    "tgn:hierarchy":[
        "tgn:2312152",
        "tgn:1000001",
        "tgn:7012149",
        "tgn:7022246",
        "tgn:7007825",
        "tgn:7029392"
    ],
    "tgn:id":2312152,
    "tgn:name":"Egypt Hollow Branch",
    "tgn:placetype":[
        "aat:300008699"
    ]
},
  "bbox": [],
  "geometry": {"coordinates":[-85.8667,35.95],"type":"Point"}
}