<<<<<<< HEAD
{
  "id": 7479996,
  "type": "Feature",
  "properties": {
    "tgn:hierarchy":[
        "tgn:7479996",
        "tgn:7001004",
        "tgn:1000004",
        "tgn:1000141",
        "tgn:7029392"
    ],
    "tgn:id":7479996,
    "tgn:name":"Lan Qiao",
    "tgn:placetype":[
        "aat:300007836"
    ]
},
  "bbox": [],
  "geometry": {"coordinates":[120.503515,23.004135],"type":"Point"}
}
=======
{"geometry":{"type":"Point","coordinates":[120.503515,23.004135]},"type":"Feature","properties":{"hierarchy":["tgn:7479996","tgn:7001004","tgn:1000004","tgn:1000141","tgn:7029392"],"placetype":["aat:300007836"],"id":7479996,"name:xx":"Lan Qiao"}}
>>>>>>> 03f74aca74312dbeaf24d7e61306dd6a786dc3d0
