{
  "id": 7479996,
  "type": "Feature",
  "properties": {
    "tgn:hierarchy":[
        "tgn:7479996",
        "tgn:7001004",
        "tgn:1000004",
        "tgn:1000141",
        "tgn:7029392"
    ],
    "tgn:id":7479996,
    "tgn:name":"Lan Qiao",
    "tgn:placetype":[
        "aat:300007836"
    ]
},
  "bbox": [],
  "geometry": {"coordinates":[120.503515,23.004135],"type":"Point"}
}