{
  "id": 2351462,
  "type": "Feature",
  "properties": {
    "tgn:hierarchy":[
        "tgn:2351462",
        "tgn:2000090",
        "tgn:1000001",
        "tgn:7006451",
        "tgn:7012149",
        "tgn:7029392"
    ],
    "tgn:id":2351462,
    "tgn:name":"Glen Livet Reservoir",
    "tgn:placetype":[
        "aat:300006191"
    ]
},
  "bbox": [],
  "geometry": {"coordinates":[-109.2167,34.0167],"type":"Point"}
}