{
  "id": 2165771,
  "type": "Feature",
  "properties": {
    "tgn:hierarchy":[
        "tgn:2165771",
        "tgn:1000001",
        "tgn:7012149",
        "tgn:1003038",
        "tgn:7007517",
        "tgn:7029392"
    ],
    "tgn:id":2165771,
    "tgn:name":"Bickford Hill",
    "tgn:placetype":[
        "aat:300008798"
    ]
},
  "bbox": [],
  "geometry": {"coordinates":[-71.9667,42.5667],"type":"Point"}
}