{
  "id": 2217361,
  "type": "Feature",
  "properties": {
    "tgn:hierarchy":[
        "tgn:2217361",
        "tgn:1000001",
        "tgn:7012149",
        "tgn:7007157",
        "tgn:2000186",
        "tgn:7029392"
    ],
    "tgn:id":2217361,
    "tgn:name":"Campbell",
    "tgn:placetype":[
        "aat:300008347"
    ]
},
  "bbox": [],
  "geometry": {"coordinates":[-120.2667,41.2333],"type":"Point"}
}