<<<<<<< HEAD
{
  "id": 7379425,
  "type": "Feature",
  "properties": {
    "tgn:hierarchy":[
        "tgn:7379425",
        "tgn:7005585",
        "tgn:1000001",
        "tgn:7005560",
        "tgn:7029392"
    ],
    "tgn:id":7379425,
    "tgn:name":"Miahuich\u00e1n",
    "tgn:placetype":[
        "aat:300008347"
    ]
},
  "bbox": [],
  "geometry": {"coordinates":[-98.95,17.8],"type":"Point"}
}
=======
{"geometry":{"type":"Point","coordinates":[-98.950000,17.800000]},"type":"Feature","properties":{"hierarchy":["tgn:7379425","tgn:7005585","tgn:1000001","tgn:7005560","tgn:7029392"],"placetype":["aat:300008347"],"id":7379425,"name:xx":"Miahuich\u00e1n"}}
>>>>>>> 03f74aca74312dbeaf24d7e61306dd6a786dc3d0
