{
  "id": 7531437,
  "type": "Feature",
  "properties": {
    "tgn:hierarchy":[
        "tgn:7531437",
        "tgn:7001242",
        "tgn:7016833",
        "tgn:1001079",
        "tgn:7029392"
    ],
    "tgn:id":7531437,
    "tgn:name:en":"Cleopatra Beach",
    "tgn:placetype":[
        "aat:300008816"
    ]
},
  "bbox": [],
  "geometry": {"coordinates":[29.935959,31.225706],"type":"Point"}
}