{
  "id": 7462871,
  "type": "Feature",
  "properties": {
    "tgn:hierarchy":[
        "tgn:7462871",
        "tgn:7002445",
        "tgn:1000003",
        "tgn:7008180",
        "tgn:7008591",
        "tgn:7029392"
    ],
    "tgn:id":7462871,
    "tgn:name:en":"Imber",
    "tgn:placetype":[
        "aat:300008347"
    ]
},
  "bbox": [],
  "geometry": {"coordinates":[-2.05,51.233333],"type":"Point"}
}