{
  "id": 7191430,
  "type": "Feature",
  "properties": {
    "tgn:hierarchy":[
        "tgn:7191430",
        "tgn:7003669",
        "tgn:1000003",
        "tgn:7000084",
        "tgn:7029392"
    ],
    "tgn:id":7191430,
    "tgn:name":"Fassoldshof",
    "tgn:placetype":[
        "aat:300008347"
    ]
},
  "bbox": [],
  "geometry": {"coordinates":[11.35,50.116667],"type":"Point"}
}