{
  "id": 2368516,
  "type": "Feature",
  "properties": {
    "tgn:hierarchy":[
        "tgn:2368516",
        "tgn:1000001",
        "tgn:7012149",
        "tgn:2001027",
        "tgn:7007521",
        "tgn:7029392"
    ],
    "tgn:id":2368516,
    "tgn:name":"Gulch Creek",
    "tgn:placetype":[
        "aat:300008706"
    ]
},
  "bbox": [],
  "geometry": {"coordinates":[-94.8667,47.1667],"type":"Point"}
}