<<<<<<< HEAD
{
  "id": 7113398,
  "type": "Feature",
  "properties": {
    "tgn:hierarchy":[
        "tgn:7113398",
        "tgn:1000003",
        "tgn:7003685",
        "tgn:7000084",
        "tgn:7029392"
    ],
    "tgn:id":7113398,
    "tgn:name":"R\u00f6der-Berg",
    "tgn:placetype":[
        "aat:300008777"
    ]
},
  "bbox": [],
  "geometry": {"coordinates":[13.933333,51.2],"type":"Point"}
}
=======
{"geometry":{"type":"Point","coordinates":[13.933333,51.200000]},"type":"Feature","properties":{"hierarchy":["tgn:7113398","tgn:1000003","tgn:7003685","tgn:7000084","tgn:7029392"],"placetype":["aat:300008777"],"id":7113398,"name:xx":"R\u00f6der-Berg"}}
>>>>>>> 03f74aca74312dbeaf24d7e61306dd6a786dc3d0
