{
  "id": 2427195,
  "type": "Feature",
  "properties": {
    "tgn:hierarchy":[
        "tgn:2427195",
        "tgn:1000001",
        "tgn:7012149",
        "tgn:7007825",
        "tgn:7029392"
    ],
    "tgn:id":2427195,
    "tgn:name":"Jordan Branch",
    "tgn:placetype":[
        "aat:300008699"
    ]
},
  "bbox": [],
  "geometry": {"coordinates":[-87.5167,36.25],"type":"Point"}
}