<<<<<<< HEAD
{
  "id": 7360933,
  "type": "Feature",
  "properties": {
    "tgn:hierarchy":[
        "tgn:7360933",
        "tgn:1000001",
        "tgn:7005596",
        "tgn:7005560",
        "tgn:7029392"
    ],
    "tgn:id":7360933,
    "tgn:name":"Coronel",
    "tgn:placetype":[
        "aat:300008347"
    ]
},
  "bbox": [],
  "geometry": {"coordinates":[-93.5,17.516667],"type":"Point"}
}
=======
{"geometry":{"type":"Point","coordinates":[-93.500000,17.516667]},"type":"Feature","properties":{"hierarchy":["tgn:7360933","tgn:1000001","tgn:7005596","tgn:7005560","tgn:7029392"],"placetype":["aat:300008347"],"id":7360933,"name:xx":"Coronel"}}
>>>>>>> 03f74aca74312dbeaf24d7e61306dd6a786dc3d0
