{
  "id": 2714812,
  "type": "Feature",
  "properties": {
    "tgn:hierarchy":[
        "tgn:2714812",
        "tgn:1000001",
        "tgn:7012149",
        "tgn:2001151",
        "tgn:7007522",
        "tgn:7029392"
    ],
    "tgn:id":2714812,
    "tgn:name":"Tenmile Creek",
    "tgn:placetype":[
        "aat:300008706"
    ]
},
  "bbox": [],
  "geometry": {"coordinates":[-89.25,30.7833],"type":"Point"}
}