{
  "id": 7027958,
  "type": "Feature",
  "properties": {
    "tgn:hierarchy":[
        "tgn:7027958",
        "tgn:7002445",
        "tgn:1000003",
        "tgn:7008157",
        "tgn:7008591",
        "tgn:7029392"
    ],
    "tgn:id":7027958,
    "tgn:name:en":"Laughton",
    "tgn:placetype":[
        "aat:300008347",
        "aat:300008372"
    ]
},
  "bbox": [],
  "geometry": {"coordinates":[-0.716667,53.466667],"type":"Point"}
}