{
  "id": 7530102,
  "type": "Feature",
  "properties": {
    "tgn:hierarchy":[
        "tgn:7530102",
        "tgn:7001242",
        "tgn:7016833",
        "tgn:7001335",
        "tgn:7029392"
    ],
    "tgn:id":7530102,
    "tgn:name":"Khad\u0101khid, W\u0101d\u012b",
    "tgn:placetype":[
        "aat:300379998"
    ]
},
  "bbox": [],
  "geometry": {"coordinates":[34.499722,30.041389],"type":"Point"}
}