{
  "id": 7152774,
  "type": "Feature",
  "properties": {
    "tgn:hierarchy":[
        "tgn:7152774",
        "tgn:7003692",
        "tgn:1000003",
        "tgn:7000084",
        "tgn:7029392"
    ],
    "tgn:id":7152774,
    "tgn:name":"Ruine Kaltenburg",
    "tgn:placetype":[
        "aat:300008057"
    ]
},
  "bbox": [],
  "geometry": {"coordinates":[10.216667,48.583333],"type":"Point"}
}