{
  "id": 2061629,
  "type": "Feature",
  "properties": {
    "tgn:hierarchy":[
        "tgn:2061629",
        "tgn:1000001",
        "tgn:7012149",
        "tgn:2001315",
        "tgn:7007524",
        "tgn:7029392"
    ],
    "tgn:id":2061629,
    "tgn:name":"Pompeys Pillar",
    "tgn:placetype":[
        "aat:300008347"
    ]
},
  "bbox": [],
  "geometry": {"coordinates":[-107.95,45.9833],"type":"Point"}
}