{
  "id": 2432441,
  "type": "Feature",
  "properties": {
    "tgn:hierarchy":[
        "tgn:2432441",
        "tgn:1000001",
        "tgn:7012149",
        "tgn:2001844",
        "tgn:7007825",
        "tgn:7029392"
    ],
    "tgn:id":2432441,
    "tgn:name":"Keaton Hollow",
    "tgn:placetype":[
        "aat:300008761"
    ]
},
  "bbox": [],
  "geometry": {"coordinates":[-86.0167,35.95],"type":"Point"}
}