{
  "id": 1106038,
  "type": "Feature",
  "properties": {
    "tgn:hierarchy":[
        "tgn:1106038",
        "tgn:7018001",
        "tgn:1000003",
        "tgn:1000062",
        "tgn:7029392"
    ],
    "tgn:id":1106038,
    "tgn:name":"Pf\u00e4nder",
    "tgn:placetype":[
        "aat:300008795"
    ]
},
  "bbox": [],
  "geometry": {"coordinates":[9.8333,47.5167],"type":"Point"}
}