{
  "id": 1108708,
  "type": "Feature",
  "properties": {
    "tgn:hierarchy":[
        "tgn:1108708",
        "tgn:7001155",
        "tgn:1000003",
        "tgn:7002790",
        "tgn:1000095",
        "tgn:7029392"
    ],
    "tgn:id":1108708,
    "tgn:name":"Andia, Sierra de",
    "tgn:placetype":[
        "aat:300386831",
        "aat:300008795"
    ]
},
  "bbox": [],
  "geometry": {"coordinates":[-10.966667,42.85],"type":"Point"}
}