{
  "id": 7585716,
  "type": "Feature",
  "properties": {
    "tgn:hierarchy":[
        "tgn:7585716",
        "tgn:1000004",
        "tgn:7000198",
        "tgn:7000799",
        "tgn:7029392"
    ],
    "tgn:id":7585716,
    "tgn:name:en":"K\u016btn\u0101r Forest",
    "tgn:placetype":[
        "aat:300008863"
    ]
},
  "bbox": [],
  "geometry": {"coordinates":[74.883333,34.305556],"type":"Point"}
}