{
  "id": 2277914,
  "type": "Feature",
  "properties": {
    "tgn:hierarchy":[
        "tgn:2277914",
        "tgn:1000001",
        "tgn:2000920",
        "tgn:7012149",
        "tgn:7007515",
        "tgn:7029392"
    ],
    "tgn:id":2277914,
    "tgn:name":"Day Brook",
    "tgn:placetype":[
        "aat:300008699"
    ]
},
  "bbox": [],
  "geometry": {"coordinates":[-70.75,44.0333],"type":"Point"}
}