<<<<<<< HEAD
{
  "id": 7249751,
  "type": "Feature",
  "properties": {
    "tgn:hierarchy":[
        "tgn:7249751",
        "tgn:7003456",
        "tgn:1000003",
        "tgn:1000063",
        "tgn:7018236",
        "tgn:7029392"
    ],
    "tgn:id":7249751,
    "tgn:name":"Potaardehoeve",
    "tgn:placetype":[
        "aat:300000206"
    ]
},
  "bbox": [],
  "geometry": {"coordinates":[4.35,50.916667],"type":"Point"}
}
=======
{"geometry":{"type":"Point","coordinates":[4.350000,50.916667]},"type":"Feature","properties":{"hierarchy":["tgn:7249751","tgn:7003456","tgn:1000003","tgn:1000063","tgn:7018236","tgn:7029392"],"placetype":["aat:300000206"],"id":7249751,"name:xx":"Potaardehoeve"}}
>>>>>>> 03f74aca74312dbeaf24d7e61306dd6a786dc3d0
