{
  "id": 7354016,
  "type": "Feature",
  "properties": {
    "tgn:hierarchy":[
        "tgn:7354016",
        "tgn:1000001",
        "tgn:7005600",
        "tgn:7005560",
        "tgn:7029392"
    ],
    "tgn:id":7354016,
    "tgn:name":"Chan Azul, Cenote",
    "tgn:placetype":[
        "aat:300343547"
    ]
},
  "bbox": [],
  "geometry": {"coordinates":[-88.766667,21.116667],"type":"Point"}
}