{
  "id": 1114170,
  "type": "Feature",
  "properties": {
    "tgn:hierarchy":[
        "tgn:1114170",
        "tgn:1002534",
        "tgn:1000001",
        "tgn:7012149",
        "tgn:7007249",
        "tgn:7029392"
    ],
    "tgn:id":1114170,
    "tgn:name":"Kaulakahi Channel",
    "tgn:placetype":[
        "aat:300008713"
    ]
},
  "bbox": [],
  "geometry": {"coordinates":[-159.9333,22.0167],"type":"Point"}
}