{
  "id": 7335821,
  "type": "Feature",
  "properties": {
    "tgn:hierarchy":[
        "tgn:7335821",
        "tgn:7007780",
        "tgn:1000003",
        "tgn:7009604",
        "tgn:1000095",
        "tgn:7029392"
    ],
    "tgn:id":7335821,
    "tgn:name":"Gainchurizqueta, Collado",
    "tgn:placetype":[
        "aat:300259572"
    ]
},
  "bbox": [],
  "geometry": {"coordinates":[-1.833333,43.333333],"type":"Point"}
}