{
  "id": 7394858,
  "type": "Feature",
  "properties": {
    "tgn:hierarchy":[
        "tgn:7394858",
        "tgn:1000001",
        "tgn:7005594",
        "tgn:7005560",
        "tgn:7029392"
    ],
    "tgn:id":7394858,
    "tgn:name":"San Jos\u00e9 de la Enramada",
    "tgn:placetype":[
        "aat:300008347"
    ]
},
  "bbox": [],
  "geometry": {"coordinates":[-101.033333,22.666667],"type":"Point"}
}