{
  "id": 7587520,
  "type": "Feature",
  "properties": {
    "tgn:hierarchy":[
        "tgn:7587520",
        "tgn:1000004",
        "tgn:7000198",
        "tgn:7000799",
        "tgn:7029392"
    ],
    "tgn:id":7587520,
    "tgn:name:en":"Chak Dew\u0101n Badri N\u0101th",
    "tgn:placetype":[
        "aat:300008347"
    ]
},
  "bbox": [],
  "geometry": {"coordinates":[74.618056,34.097222],"type":"Point"}
}