{
  "id": 2579967,
  "type": "Feature",
  "properties": {
    "tgn:hierarchy":[
        "tgn:2579967",
        "tgn:1000001",
        "tgn:2001431",
        "tgn:7012149",
        "tgn:7007566",
        "tgn:7029392"
    ],
    "tgn:id":2579967,
    "tgn:name":"Piedra Lumbre, Arroyo de",
    "tgn:placetype":[
        "aat:300008699"
    ]
},
  "bbox": [],
  "geometry": {"coordinates":[-107.2333,35.15],"type":"Point"}
}