{
  "id": 2392867,
  "type": "Feature",
  "properties": {
    "tgn:hierarchy":[
        "tgn:2392867",
        "tgn:1000001",
        "tgn:7006451",
        "tgn:2000095",
        "tgn:7012149",
        "tgn:7029392"
    ],
    "tgn:id":2392867,
    "tgn:name":"Hobo Spring",
    "tgn:placetype":[
        "aat:300008697"
    ]
},
  "bbox": [],
  "geometry": {"coordinates":[-109.15,33.3667],"type":"Point"}
}