{
  "id": 2441757,
  "type": "Feature",
  "properties": {
    "tgn:hierarchy":[
        "tgn:2441757",
        "tgn:7013349",
        "tgn:1000001",
        "tgn:7012149",
        "tgn:7007708",
        "tgn:7029392"
    ],
    "tgn:id":2441757,
    "tgn:name":"Kolb Reservoir",
    "tgn:placetype":[
        "aat:300006191"
    ]
},
  "bbox": [],
  "geometry": {"coordinates":[-117.85,44.7667],"type":"Point"}
}