{
  "id": 7373317,
  "type": "Feature",
  "properties": {
    "tgn:hierarchy":[
        "tgn:7373317",
        "tgn:7005583",
        "tgn:1000001",
        "tgn:7005560",
        "tgn:7029392"
    ],
    "tgn:id":7373317,
    "tgn:name":"La Gallega",
    "tgn:placetype":[
        "aat:300008347"
    ]
},
  "bbox": [],
  "geometry": {"coordinates":[-105.133333,25.816667],"type":"Point"}
}