<<<<<<< HEAD
{
  "id": 7482395,
  "type": "Feature",
  "properties": {
    "tgn:hierarchy":[
        "tgn:7482395",
        "tgn:1000004",
        "tgn:7001009",
        "tgn:1000141",
        "tgn:7029392"
    ],
    "tgn:id":7482395,
    "tgn:name":"Zhongyangjian Xi",
    "tgn:placetype":[
        "aat:300008699"
    ]
},
  "bbox": [],
  "geometry": {"coordinates":[121.383056,24.3475],"type":"Point"}
}
=======
{"geometry":{"type":"Point","coordinates":[121.383056,24.347500]},"type":"Feature","properties":{"hierarchy":["tgn:7482395","tgn:1000004","tgn:7001009","tgn:1000141","tgn:7029392"],"placetype":["aat:300008699"],"id":7482395,"name:xx":"Zhongyangjian Xi"}}
>>>>>>> 03f74aca74312dbeaf24d7e61306dd6a786dc3d0
