{
  "id": 7510480,
  "type": "Feature",
  "properties": {
    "tgn:hierarchy":[
        "tgn:7510480",
        "tgn:1009227",
        "tgn:1000226",
        "tgn:7016822",
        "tgn:1000006",
        "tgn:7029392"
    ],
    "tgn:id":7510480,
    "tgn:name:en":"South West Point",
    "tgn:placetype":[
        "aat:300386846"
    ]
},
  "bbox": [],
  "geometry": {"coordinates":[166.85,-45.233333],"type":"Point"}
}