{
  "id": 7425466,
  "type": "Feature",
  "properties": {
    "tgn:hierarchy":[
        "tgn:7425466",
        "tgn:1000001",
        "tgn:7005594",
        "tgn:7005560",
        "tgn:7029392"
    ],
    "tgn:id":7425466,
    "tgn:name":"Agua Zarca",
    "tgn:placetype":[
        "aat:300008347"
    ]
},
  "bbox": [],
  "geometry": {"coordinates":[-100.533333,22.116667],"type":"Point"}
}