{
  "id": 2296067,
  "type": "Feature",
  "properties": {
    "tgn:hierarchy":[
        "tgn:2296067",
        "tgn:7002659",
        "tgn:1000001",
        "tgn:7012149",
        "tgn:2000063",
        "tgn:7029392"
    ],
    "tgn:id":2296067,
    "tgn:name":"Dry Branch",
    "tgn:placetype":[
        "aat:300008699"
    ]
},
  "bbox": [],
  "geometry": {"coordinates":[-87.3667,33.8833],"type":"Point"}
}