{
  "id": 1051436,
  "type": "Feature",
  "properties": {
    "tgn:hierarchy":[
        "tgn:1051436",
        "tgn:4000818",
        "tgn:1000004",
        "tgn:7018214",
        "tgn:7002435",
        "tgn:7029392"
    ],
    "tgn:id":1051436,
    "tgn:name":"Chublasa",
    "tgn:placetype":[
        "aat:300008347"
    ]
},
  "bbox": [],
  "geometry": {"coordinates":[45.1167,64.7333],"type":"Point"}
}