{
  "id": 7323668,
  "type": "Feature",
  "properties": {
    "tgn:hierarchy":[
        "tgn:7323668",
        "tgn:7002829",
        "tgn:1000003",
        "tgn:7002786",
        "tgn:1000095",
        "tgn:7029392"
    ],
    "tgn:id":7323668,
    "tgn:name":"Roimil",
    "tgn:placetype":[
        "aat:300008347"
    ]
},
  "bbox": [],
  "geometry": {"coordinates":[-7.833333,43.066667],"type":"Point"}
}