{
  "id": 7235410,
  "type": "Feature",
  "properties": {
    "tgn:hierarchy":[
        "tgn:7235410",
        "tgn:7002681",
        "tgn:7001395",
        "tgn:1000003",
        "tgn:1000074",
        "tgn:7029392"
    ],
    "tgn:id":7235410,
    "tgn:name":"Baladh\u00f3ni, R\u00e9ma",
    "tgn:placetype":[
        "aat:300008699"
    ]
},
  "bbox": [],
  "geometry": {"coordinates":[23.483333,38.166667],"type":"Point"}
}