{
  "id": 2112664,
  "type": "Feature",
  "properties": {
    "tgn:hierarchy":[
        "tgn:2112664",
        "tgn:1000001",
        "tgn:7012149",
        "tgn:1002548",
        "tgn:7007919",
        "tgn:7029392"
    ],
    "tgn:id":2112664,
    "tgn:name":"Lester Manor",
    "tgn:placetype":[
        "aat:300008347",
        "aat:300387210"
    ]
},
  "bbox": [],
  "geometry": {"coordinates":[-76.9833,37.5833],"type":"Point"}
}