<<<<<<< HEAD
{
  "id": 7378348,
  "type": "Feature",
  "properties": {
    "tgn:hierarchy":[
        "tgn:7378348",
        "tgn:7005581",
        "tgn:1000001",
        "tgn:7005560",
        "tgn:7029392"
    ],
    "tgn:id":7378348,
    "tgn:name":"Las Cruces",
    "tgn:placetype":[
        "aat:300008347"
    ]
},
  "bbox": [],
  "geometry": {"coordinates":[-104.316667,28.733333],"type":"Point"}
}
=======
{"geometry":{"type":"Point","coordinates":[-104.316667,28.733333]},"type":"Feature","properties":{"hierarchy":["tgn:7378348","tgn:7005581","tgn:1000001","tgn:7005560","tgn:7029392"],"placetype":["aat:300008347"],"id":7378348,"name:xx":"Las Cruces"}}
>>>>>>> 03f74aca74312dbeaf24d7e61306dd6a786dc3d0
