{
  "id": 7016030,
  "type": "Feature",
  "properties": {
    "tgn:hierarchy":[
        "tgn:7016030",
        "tgn:7006450",
        "tgn:1000001",
        "tgn:2124076",
        "tgn:7019707",
        "tgn:7012149",
        "tgn:7029392"
    ],
    "tgn:id":7016030,
    "tgn:name":"Ketchikan",
    "tgn:placetype":[
        "aat:300008347",
        "aat:300008375"
    ]
},
  "bbox": [],
  "geometry": {"coordinates":[-131.6333,55.3333],"type":"Point"}
}