{
  "id": 7349795,
  "type": "Feature",
  "properties": {
    "tgn:hierarchy":[
        "tgn:7349795",
        "tgn:1000001",
        "tgn:7005592",
        "tgn:7005560",
        "tgn:7029392"
    ],
    "tgn:id":7349795,
    "tgn:name":"Acatl\u00e1n, R\u00edo",
    "tgn:placetype":[
        "aat:300008699"
    ]
},
  "bbox": [],
  "geometry": {"coordinates":[-98.316667,18.066667],"type":"Point"}
}