{
  "id": 1071665,
  "type": "Feature",
  "properties": {
    "tgn:hierarchy":[
        "tgn:1071665",
        "tgn:1000004",
        "tgn:1001390",
        "tgn:1000111",
        "tgn:7029392"
    ],
    "tgn:id":1071665,
    "tgn:name":"Shihe",
    "tgn:placetype":[
        "aat:300008347"
    ]
},
  "bbox": [],
  "geometry": {"coordinates":[121.8667,39.3333],"type":"Point"}
}