{
  "id": 7356442,
  "type": "Feature",
  "properties": {
    "tgn:hierarchy":[
        "tgn:7356442",
        "tgn:7005583",
        "tgn:1000001",
        "tgn:7005560",
        "tgn:7029392"
    ],
    "tgn:id":7356442,
    "tgn:name":"Cerro Prieto",
    "tgn:placetype":[
        "aat:300008347"
    ]
},
  "bbox": [],
  "geometry": {"coordinates":[-102.616667,24.566667],"type":"Point"}
}