{
  "id": 2273149,
  "type": "Feature",
  "properties": {
    "tgn:hierarchy":[
        "tgn:2273149",
        "tgn:7006450",
        "tgn:1000001",
        "tgn:7012149",
        "tgn:7029392"
    ],
    "tgn:id":2273149,
    "tgn:name":"Cygnus Cone",
    "tgn:placetype":[
        "aat:300008798"
    ]
},
  "bbox": [],
  "geometry": {"coordinates":[-163.1833,65.45],"type":"Point"}
}