{
  "id": 7518838,
  "type": "Feature",
  "properties": {
    "tgn:hierarchy":[
        "tgn:7518838",
        "tgn:7000508",
        "tgn:1008380",
        "tgn:1000226",
        "tgn:1000006",
        "tgn:7029392"
    ],
    "tgn:id":7518838,
    "tgn:name:en":"Auckland Harbour",
    "tgn:placetype":[
        "aat:300008678"
    ]
},
  "bbox": [],
  "geometry": {"coordinates":[174.833333,-36.833333],"type":"Point"}
}