{
  "id": 2479867,
  "type": "Feature",
  "properties": {
    "tgn:hierarchy":[
        "tgn:2479867",
        "tgn:1000001",
        "tgn:7012149",
        "tgn:2002061",
        "tgn:7007826",
        "tgn:7029392"
    ],
    "tgn:id":2479867,
    "tgn:name":"Lake Drain Creek",
    "tgn:placetype":[
        "aat:300008706"
    ]
},
  "bbox": [],
  "geometry": {"coordinates":[-95.2833,33.5667],"type":"Point"}
}