{
  "id": 1105370,
  "type": "Feature",
  "properties": {
    "tgn:hierarchy":[
        "tgn:1105370",
        "tgn:7003502",
        "tgn:7003478",
        "tgn:1000003",
        "tgn:1000078",
        "tgn:7029392"
    ],
    "tgn:id":1105370,
    "tgn:name":"League, Slieve",
    "tgn:placetype":[
        "aat:300008795"
    ]
},
  "bbox": [],
  "geometry": {"coordinates":[-8.7333,54.65],"type":"Point"}
}