{
  "id": 7112460,
  "type": "Feature",
  "properties": {
    "tgn:hierarchy":[
        "tgn:7112460",
        "tgn:1000003",
        "tgn:7003685",
        "tgn:7000084",
        "tgn:7029392"
    ],
    "tgn:id":7112460,
    "tgn:name":"Rosinh\u00e4uschen",
    "tgn:placetype":[
        "aat:300000206"
    ]
},
  "bbox": [],
  "geometry": {"coordinates":[13.383333,50.883333],"type":"Point"}
}