<<<<<<< HEAD
{
  "id": 7054676,
  "type": "Feature",
  "properties": {
    "tgn:hierarchy":[
        "tgn:7054676",
        "tgn:7003170",
        "tgn:1000003",
        "tgn:7003125",
        "tgn:1000080",
        "tgn:7029392"
    ],
    "tgn:id":7054676,
    "tgn:name":"Ponte",
    "tgn:placetype":[
        "aat:300008347"
    ]
},
  "bbox": [],
  "geometry": {"coordinates":[12.9,42.8],"type":"Point"}
}
=======
{"geometry":{"type":"Point","coordinates":[12.900000,42.800000]},"type":"Feature","properties":{"hierarchy":["tgn:7054676","tgn:7003170","tgn:1000003","tgn:7003125","tgn:1000080","tgn:7029392"],"placetype":["aat:300008347"],"id":7054676,"name:xx":"Ponte"}}
>>>>>>> 03f74aca74312dbeaf24d7e61306dd6a786dc3d0
