{
  "id": 2392596,
  "type": "Feature",
  "properties": {
    "tgn:hierarchy":[
        "tgn:2392596",
        "tgn:1000001",
        "tgn:7012149",
        "tgn:7015778",
        "tgn:7007919",
        "tgn:7029392"
    ],
    "tgn:id":2392596,
    "tgn:name":"Hoadly Run",
    "tgn:placetype":[
        "aat:300008699"
    ]
},
  "bbox": [],
  "geometry": {"coordinates":[-77.35,38.6667],"type":"Point"}
}