{
  "id": 2445603,
  "type": "Feature",
  "properties": {
    "tgn:hierarchy":[
        "tgn:2445603",
        "tgn:1000001",
        "tgn:7012149",
        "tgn:7007157",
        "tgn:1002608",
        "tgn:7029392"
    ],
    "tgn:id":2445603,
    "tgn:name":"Leona Valley",
    "tgn:placetype":[
        "aat:300008761"
    ]
},
  "bbox": [],
  "geometry": {"coordinates":[-118.3667,34.6333],"type":"Point"}
}