{
  "id": 2448823,
  "type": "Feature",
  "properties": {
    "tgn:hierarchy":[
        "tgn:2448823",
        "tgn:1000001",
        "tgn:7012149",
        "tgn:2001298",
        "tgn:7007524",
        "tgn:7029392"
    ],
    "tgn:id":2448823,
    "tgn:name":"Limburger Spring",
    "tgn:placetype":[
        "aat:300008697"
    ]
},
  "bbox": [],
  "geometry": {"coordinates":[-112.4833,46.45],"type":"Point"}
}