{
  "id": 2167856,
  "type": "Feature",
  "properties": {
    "tgn:hierarchy":[
        "tgn:2167856",
        "tgn:1000001",
        "tgn:7012149",
        "tgn:2000786",
        "tgn:7007255",
        "tgn:7029392"
    ],
    "tgn:id":2167856,
    "tgn:name":"Big Ditch",
    "tgn:placetype":[
        "aat:300006075"
    ]
},
  "bbox": [],
  "geometry": {"coordinates":[-87.15,37.7167],"type":"Point"}
}