<<<<<<< HEAD
{
  "id": 7173532,
  "type": "Feature",
  "properties": {
    "tgn:hierarchy":[
        "tgn:7173532",
        "tgn:1000003",
        "tgn:7003677",
        "tgn:7000084",
        "tgn:7029392"
    ],
    "tgn:id":7173532,
    "tgn:name":"Gro\u00df Bracht",
    "tgn:placetype":[
        "aat:300000206"
    ]
},
  "bbox": [],
  "geometry": {"coordinates":[7.7,51.966667],"type":"Point"}
}
=======
{"geometry":{"type":"Point","coordinates":[7.700000,51.966667]},"type":"Feature","properties":{"hierarchy":["tgn:7173532","tgn:1000003","tgn:7003677","tgn:7000084","tgn:7029392"],"placetype":["aat:300000206"],"id":7173532,"name:xx":"Gro\u00df Bracht"}}
>>>>>>> 03f74aca74312dbeaf24d7e61306dd6a786dc3d0
