{
  "id": 2245149,
  "type": "Feature",
  "properties": {
    "tgn:hierarchy":[
        "tgn:2245149",
        "tgn:1000001",
        "tgn:7012149",
        "tgn:7007157",
        "tgn:7014516",
        "tgn:7029392"
    ],
    "tgn:id":2245149,
    "tgn:name":"Cloverdale Mine Headquarters",
    "tgn:placetype":[
        "aat:300000390"
    ]
},
  "bbox": [],
  "geometry": {"coordinates":[-122.8667,38.8167],"type":"Point"}
}