{
  "id": 2371065,
  "type": "Feature",
  "properties": {
    "tgn:hierarchy":[
        "tgn:2371065",
        "tgn:1000001",
        "tgn:7012149",
        "tgn:2001256",
        "tgn:7007523",
        "tgn:7029392"
    ],
    "tgn:id":2371065,
    "tgn:name":"Hagan Branch",
    "tgn:placetype":[
        "aat:300008699"
    ]
},
  "bbox": [],
  "geometry": {"coordinates":[-92.8667,37.45],"type":"Point"}
}