{
  "id": 2359904,
  "type": "Feature",
  "properties": {
    "tgn:hierarchy":[
        "tgn:2359904",
        "tgn:1000001",
        "tgn:7012149",
        "tgn:2001456",
        "tgn:7007566",
        "tgn:7029392"
    ],
    "tgn:id":2359904,
    "tgn:name":"Grapevine Spring",
    "tgn:placetype":[
        "aat:300008697"
    ]
},
  "bbox": [],
  "geometry": {"coordinates":[-107.3167,34.3333],"type":"Point"}
}