{
  "id": 7173409,
  "type": "Feature",
  "properties": {
    "tgn:hierarchy":[
        "tgn:7173409",
        "tgn:7003669",
        "tgn:1000003",
        "tgn:7000084",
        "tgn:7029392"
    ],
    "tgn:id":7173409,
    "tgn:name":"Gro\u00dfpr\u00fcfening",
    "tgn:placetype":[
        "aat:300008347"
    ]
},
  "bbox": [],
  "geometry": {"coordinates":[12.033333,49.016667],"type":"Point"}
}