{
  "id": 7077324,
  "type": "Feature",
  "properties": {
    "tgn:hierarchy":[
        "tgn:7077324",
        "tgn:7003692",
        "tgn:1000003",
        "tgn:7000084",
        "tgn:7029392"
    ],
    "tgn:id":7077324,
    "tgn:name":"Zollernalbkreis",
    "tgn:placetype":[
        "aat:300387198"
    ]
},
  "bbox": [],
  "geometry": {"coordinates":[8.941111,48.278056],"type":"Point"}
}