{
  "id": 2742173,
  "type": "Feature",
  "properties": {
    "tgn:hierarchy":[
        "tgn:2742173",
        "tgn:1000001",
        "tgn:7012149",
        "tgn:1002746",
        "tgn:7007568",
        "tgn:7029392"
    ],
    "tgn:id":2742173,
    "tgn:name":"Valentines Beach",
    "tgn:placetype":[
        "aat:300008347"
    ]
},
  "bbox": [],
  "geometry": {"coordinates":[-76.0333,43.1833],"type":"Point"}
}