{
  "id": 7020206,
  "type": "Feature",
  "properties": {
    "tgn:hierarchy":[
        "tgn:7020206",
        "tgn:1000001",
        "tgn:7012149",
        "tgn:2000789",
        "tgn:7007255",
        "tgn:7029392"
    ],
    "tgn:id":7020206,
    "tgn:name":"Aker Branch",
    "tgn:placetype":[
        "aat:300008699"
    ]
},
  "bbox": [],
  "geometry": {"coordinates":[-82.5833,37.4333],"type":"Point"}
}