{
  "id": 2687338,
  "type": "Feature",
  "properties": {
    "tgn:hierarchy":[
        "tgn:2687338",
        "tgn:1000001",
        "tgn:2001007",
        "tgn:7012149",
        "tgn:7007521",
        "tgn:7029392"
    ],
    "tgn:id":2687338,
    "tgn:name":"Spring Lake",
    "tgn:placetype":[
        "aat:300008680"
    ]
},
  "bbox": [],
  "geometry": {"coordinates":[-92.7333,46.45],"type":"Point"}
}