{
  "id": 7328500,
  "type": "Feature",
  "properties": {
    "tgn:hierarchy":[
        "tgn:7328500",
        "tgn:7002810",
        "tgn:7001158",
        "tgn:1000003",
        "tgn:1000095",
        "tgn:7029392"
    ],
    "tgn:id":7328500,
    "tgn:name":"Regumiel de la Sierra",
    "tgn:placetype":[
        "aat:300008347"
    ]
},
  "bbox": [],
  "geometry": {"coordinates":[-2.983333,41.966667],"type":"Point"}
}