{
  "id": 2443879,
  "type": "Feature",
  "properties": {
    "tgn:hierarchy":[
        "tgn:2443879",
        "tgn:1000001",
        "tgn:2000199",
        "tgn:7012149",
        "tgn:7007158",
        "tgn:7029392"
    ],
    "tgn:id":2443879,
    "tgn:name":"La Plata Basin",
    "tgn:placetype":[
        "aat:300386845"
    ]
},
  "bbox": [],
  "geometry": {"coordinates":[-106.4667,39.0333],"type":"Point"}
}