{
  "id": 7418740,
  "type": "Feature",
  "properties": {
    "tgn:hierarchy":[
        "tgn:7418740",
        "tgn:1000001",
        "tgn:7005589",
        "tgn:7005560",
        "tgn:7029392"
    ],
    "tgn:id":7418740,
    "tgn:name:es":"La Leona",
    "tgn:placetype":[
        "aat:300008347"
    ]
},
  "bbox": [],
  "geometry": {"coordinates":[-100.286667,24.614722],"type":"Point"}
}