{
  "id": 7588938,
  "type": "Feature",
  "properties": {
    "tgn:hierarchy":[
        "tgn:7588938",
        "tgn:1000004",
        "tgn:7000198",
        "tgn:7000799",
        "tgn:7029392"
    ],
    "tgn:id":7588938,
    "tgn:name:en":"S\u0101ngal Katha",
    "tgn:placetype":[
        "aat:300008699"
    ]
},
  "bbox": [],
  "geometry": {"coordinates":[74.147222,33.663889],"type":"Point"}
}