{
  "id": 7141389,
  "type": "Feature",
  "properties": {
    "tgn:hierarchy":[
        "tgn:7141389",
        "tgn:1000003",
        "tgn:7003676",
        "tgn:7000084",
        "tgn:7029392"
    ],
    "tgn:id":7141389,
    "tgn:name":"Longewehr",
    "tgn:placetype":[
        "aat:300000206"
    ]
},
  "bbox": [],
  "geometry": {"coordinates":[7.233333,53.45],"type":"Point"}
}