{
  "id": 7109773,
  "type": "Feature",
  "properties": {
    "tgn:hierarchy":[
        "tgn:7109773",
        "tgn:7003669",
        "tgn:1000003",
        "tgn:7000084",
        "tgn:7029392"
    ],
    "tgn:id":7109773,
    "tgn:name":"Reingrub",
    "tgn:placetype":[
        "aat:300000206"
    ]
},
  "bbox": [],
  "geometry": {"coordinates":[12.066667,49.133333],"type":"Point"}
}