{
  "id": 2377125,
  "type": "Feature",
  "properties": {
    "tgn:hierarchy":[
        "tgn:2377125",
        "tgn:1000001",
        "tgn:2001477",
        "tgn:7012149",
        "tgn:7007709",
        "tgn:7029392"
    ],
    "tgn:id":2377125,
    "tgn:name":"Harlowe Creek",
    "tgn:placetype":[
        "aat:300008706"
    ]
},
  "bbox": [],
  "geometry": {"coordinates":[-76.7333,34.8167],"type":"Point"}
}