{
  "id": 7582928,
  "type": "Feature",
  "properties": {
    "tgn:hierarchy":[
        "tgn:7582928",
        "tgn:1000004",
        "tgn:7000198",
        "tgn:7016788",
        "tgn:7029392"
    ],
    "tgn:id":7582928,
    "tgn:name:en":"Goth",
    "tgn:placetype":[
        "aat:300008347"
    ]
},
  "bbox": [],
  "geometry": {"coordinates":[75.74016,28.134229],"type":"Point"}
}