{
  "id": 1014094,
  "type": "Feature",
  "properties": {
    "tgn:hierarchy":[
        "tgn:1014094",
        "tgn:7005685",
        "tgn:1000001",
        "tgn:7005799",
        "tgn:7029392"
    ],
    "tgn:id":1014094,
    "tgn:name":"Nashwaaksis",
    "tgn:placetype":[
        "aat:300008347"
    ]
},
  "bbox": [],
  "geometry": {"coordinates":[-66.6667,45.9667],"type":"Point"}
}