{
  "id": 7528343,
  "type": "Feature",
  "properties": {
    "tgn:hierarchy":[
        "tgn:7528343",
        "tgn:7001242",
        "tgn:7001311",
        "tgn:7016833",
        "tgn:7029392"
    ],
    "tgn:id":7528343,
    "tgn:name:en":"Spit Reef",
    "tgn:placetype":[
        "aat:300008808"
    ]
},
  "bbox": [],
  "geometry": {"coordinates":[33.966667,26.683333],"type":"Point"}
}