<<<<<<< HEAD
{
  "id": 7029273,
  "type": "Feature",
  "properties": {
    "tgn:hierarchy":[
        "tgn:7029273",
        "tgn:7002445",
        "tgn:1000003",
        "tgn:7008167",
        "tgn:7008591",
        "tgn:7029392"
    ],
    "tgn:id":7029273,
    "tgn:name:en":"Darlton",
    "tgn:placetype":[
        "aat:300008347",
        "aat:300008372"
    ]
},
  "bbox": [],
  "geometry": {"coordinates":[-0.85,53.233333],"type":"Point"}
}
=======
{"geometry":{"type":"Point","coordinates":[-0.850000,53.233333]},"type":"Feature","properties":{"hierarchy":["tgn:7029273","tgn:7002445","tgn:1000003","tgn:7008167","tgn:7008591","tgn:7029392"],"placetype":["aat:300008347","aat:300008372"],"name:en":"Darlton","id":7029273}}
>>>>>>> 03f74aca74312dbeaf24d7e61306dd6a786dc3d0
