{
  "id": 7582666,
  "type": "Feature",
  "properties": {
    "tgn:hierarchy":[
        "tgn:7582666",
        "tgn:1000004",
        "tgn:7000198",
        "tgn:7016788",
        "tgn:7029392"
    ],
    "tgn:id":7582666,
    "tgn:name:en":"Bhobiyan",
    "tgn:placetype":[
        "aat:300008347"
    ]
},
  "bbox": [],
  "geometry": {"coordinates":[75.66,28.3099],"type":"Point"}
}