{
  "id": 7566063,
  "type": "Feature",
  "properties": {
    "tgn:hierarchy":[
        "tgn:7566063",
        "tgn:1000004",
        "tgn:7000198",
        "tgn:1001894",
        "tgn:7029392"
    ],
    "tgn:id":7566063,
    "tgn:name:en":"Dargawa",
    "tgn:placetype":[
        "aat:300008795"
    ]
},
  "bbox": [],
  "geometry": {"coordinates":[79.021888,24.620784],"type":"Point"}
}