{
  "id": 7399545,
  "type": "Feature",
  "properties": {
    "tgn:hierarchy":[
        "tgn:7399545",
        "tgn:1000001",
        "tgn:7005599",
        "tgn:7005560",
        "tgn:7029392"
    ],
    "tgn:id":7399545,
    "tgn:name":"Arroyo San Pedro",
    "tgn:placetype":[
        "aat:300008347"
    ]
},
  "bbox": [],
  "geometry": {"coordinates":[-95.608333,17.691667],"type":"Point"}
}