{
  "id": 7430116,
  "type": "Feature",
  "properties": {
    "tgn:hierarchy":[
        "tgn:7430116",
        "tgn:7005583",
        "tgn:1000001",
        "tgn:7005560",
        "tgn:7029392"
    ],
    "tgn:id":7430116,
    "tgn:name":"Del Alaz\u00e1n",
    "tgn:placetype":[
        "aat:300008347"
    ]
},
  "bbox": [],
  "geometry": {"coordinates":[-105.916667,24.883333],"type":"Point"}
}