{
  "id": 1068728,
  "type": "Feature",
  "properties": {
    "tgn:hierarchy":[
        "tgn:1068728",
        "tgn:1000004",
        "tgn:7002082",
        "tgn:1000111",
        "tgn:7029392"
    ],
    "tgn:id":1068728,
    "tgn:name":"Hetanbu",
    "tgn:placetype":[
        "aat:300008347"
    ]
},
  "bbox": [],
  "geometry": {"coordinates":[117.2667,28.3667],"type":"Point"}
}