{
  "id": 2214416,
  "type": "Feature",
  "properties": {
    "tgn:hierarchy":[
        "tgn:2214416",
        "tgn:1000001",
        "tgn:7012149",
        "tgn:7007157",
        "tgn:1002957",
        "tgn:7029392"
    ],
    "tgn:id":2214416,
    "tgn:name":"Calaveras Bigtree National Forest",
    "tgn:placetype":[
        "aat:300008863"
    ]
},
  "bbox": [],
  "geometry": {"coordinates":[-120.2333,38.25],"type":"Point"}
}