{
  "id": 2568576,
  "type": "Feature",
  "properties": {
    "tgn:hierarchy":[
        "tgn:2568576",
        "tgn:1000001",
        "tgn:7012149",
        "tgn:2001440",
        "tgn:7007566",
        "tgn:7029392"
    ],
    "tgn:id":2568576,
    "tgn:name":"Park Tank",
    "tgn:placetype":[
        "aat:300006191"
    ]
},
  "bbox": [],
  "geometry": {"coordinates":[-108.6833,31.5833],"type":"Point"}
}