{
  "id": 7149434,
  "type": "Feature",
  "properties": {
    "tgn:hierarchy":[
        "tgn:7149434",
        "tgn:1000003",
        "tgn:7003688",
        "tgn:7000084",
        "tgn:7029392"
    ],
    "tgn:id":7149434,
    "tgn:name":"Krebs-See",
    "tgn:placetype":[
        "aat:300008680"
    ]
},
  "bbox": [],
  "geometry": {"coordinates":[10.716667,53.566667],"type":"Point"}
}