{
  "id": 2498276,
  "type": "Feature",
  "properties": {
    "tgn:hierarchy":[
        "tgn:2498276",
        "tgn:1000001",
        "tgn:2156155",
        "tgn:7012149",
        "tgn:7007248",
        "tgn:7029392"
    ],
    "tgn:id":2498276,
    "tgn:name":"Mc Clure Lake",
    "tgn:placetype":[
        "aat:300006191"
    ]
},
  "bbox": [],
  "geometry": {"coordinates":[-84.6833,32.55],"type":"Point"}
}