{
  "id": 7309396,
  "type": "Feature",
  "properties": {
    "tgn:hierarchy":[
        "tgn:7309396",
        "tgn:1001702",
        "tgn:1000049",
        "tgn:1000002",
        "tgn:7029392"
    ],
    "tgn:id":7309396,
    "tgn:name":"Paget, Islotes",
    "tgn:placetype":[
        "aat:300008791"
    ]
},
  "bbox": [],
  "geometry": {"coordinates":[-74.166667,-51.083333],"type":"Point"}
}