{
  "id": 2328083,
  "type": "Feature",
  "properties": {
    "tgn:hierarchy":[
        "tgn:2328083",
        "tgn:1000001",
        "tgn:2000922",
        "tgn:7012149",
        "tgn:7007515",
        "tgn:7029392"
    ],
    "tgn:id":2328083,
    "tgn:name":"Fish Point",
    "tgn:placetype":[
        "aat:300008850"
    ]
},
  "bbox": [],
  "geometry": {"coordinates":[-68.1333,44.3833],"type":"Point"}
}