{
  "id": 7125783,
  "type": "Feature",
  "properties": {
    "tgn:hierarchy":[
        "tgn:7125783",
        "tgn:1000003",
        "tgn:7003685",
        "tgn:7000084",
        "tgn:7029392"
    ],
    "tgn:id":7125783,
    "tgn:name":"Niederschlag",
    "tgn:placetype":[
        "aat:300008347"
    ]
},
  "bbox": [],
  "geometry": {"coordinates":[13.033333,50.466667],"type":"Point"}
}