{
  "id": 2663988,
  "type": "Feature",
  "properties": {
    "tgn:hierarchy":[
        "tgn:2663988",
        "tgn:1000001",
        "tgn:2001412",
        "tgn:7012149",
        "tgn:7007526",
        "tgn:7029392"
    ],
    "tgn:id":2663988,
    "tgn:name":"Silver Moon Mine",
    "tgn:placetype":[
        "aat:300000390"
    ]
},
  "bbox": [],
  "geometry": {"coordinates":[-117.2333,37.3333],"type":"Point"}
}