<<<<<<< HEAD
{
  "id": 7023558,
  "type": "Feature",
  "properties": {
    "tgn:hierarchy":[
        "tgn:7023558",
        "tgn:1000001",
        "tgn:7012149",
        "tgn:7007827",
        "tgn:7029392"
    ],
    "tgn:id":7023558,
    "tgn:name":"Nebeker Spring",
    "tgn:placetype":[
        "aat:300008697"
    ]
},
  "bbox": [],
  "geometry": {"coordinates":[-111.4833,41.7667],"type":"Point"}
}
=======
{"geometry":{"type":"Point","coordinates":[-111.483300,41.766700]},"type":"Feature","properties":{"hierarchy":["tgn:7023558","tgn:1000001","tgn:7012149","tgn:7007827","tgn:7029392"],"placetype":["aat:300008697"],"id":7023558,"name:xx":"Nebeker Spring"}}
>>>>>>> 03f74aca74312dbeaf24d7e61306dd6a786dc3d0
