{
  "id": 7569952,
  "type": "Feature",
  "properties": {
    "tgn:hierarchy":[
        "tgn:7569952",
        "tgn:1001828",
        "tgn:1000004",
        "tgn:7000198",
        "tgn:7029392"
    ],
    "tgn:id":7569952,
    "tgn:name:en":"\u0100regudam",
    "tgn:placetype":[
        "aat:300008347"
    ]
},
  "bbox": [],
  "geometry": {"coordinates":[78.960556,17.216389],"type":"Point"}
}