<<<<<<< HEAD
{
  "id": 7486555,
  "type": "Feature",
  "properties": {
    "tgn:hierarchy":[
        "tgn:7486555",
        "tgn:1000004",
        "tgn:1000454",
        "tgn:1000141",
        "tgn:7029392"
    ],
    "tgn:id":7486555,
    "tgn:name":"Kengzi",
    "tgn:placetype":[
        "aat:300008347"
    ]
},
  "bbox": [],
  "geometry": {"coordinates":[121.874728,25.057379],"type":"Point"}
}
=======
{"geometry":{"type":"Point","coordinates":[121.874728,25.057379]},"type":"Feature","properties":{"hierarchy":["tgn:7486555","tgn:1000004","tgn:1000454","tgn:1000141","tgn:7029392"],"placetype":["aat:300008347"],"id":7486555,"name:xx":"Kengzi"}}
>>>>>>> 03f74aca74312dbeaf24d7e61306dd6a786dc3d0
