{
  "id": 7551179,
  "type": "Feature",
  "properties": {
    "tgn:hierarchy":[
        "tgn:7551179",
        "tgn:1000004",
        "tgn:1001832",
        "tgn:7000198",
        "tgn:7029392"
    ],
    "tgn:id":7551179,
    "tgn:name:en":"Diphu",
    "tgn:placetype":[
        "aat:300008347"
    ]
},
  "bbox": [],
  "geometry": {"coordinates":[93.43116,25.84341],"type":"Point"}
}