{
  "id": 2326878,
  "type": "Feature",
  "properties": {
    "tgn:hierarchy":[
        "tgn:2326878",
        "tgn:7006450",
        "tgn:1000001",
        "tgn:7012149",
        "tgn:2124005",
        "tgn:7029392"
    ],
    "tgn:id":2326878,
    "tgn:name":"Fire Creek",
    "tgn:placetype":[
        "aat:300008706"
    ]
},
  "bbox": [],
  "geometry": {"coordinates":[-153.2833,68.3167],"type":"Point"}
}