{
  "id": 2210325,
  "type": "Feature",
  "properties": {
    "tgn:hierarchy":[
        "tgn:2210325",
        "tgn:1000001",
        "tgn:1002245",
        "tgn:7012149",
        "tgn:7007568",
        "tgn:7029392"
    ],
    "tgn:id":2210325,
    "tgn:name":"Bush Hill",
    "tgn:placetype":[
        "aat:300008798"
    ]
},
  "bbox": [],
  "geometry": {"coordinates":[-78.3333,42.3833],"type":"Point"}
}