{
  "id": 7593319,
  "type": "Feature",
  "properties": {
    "tgn:hierarchy":[
        "tgn:7593319",
        "tgn:1001487",
        "tgn:7002561",
        "tgn:1000051",
        "tgn:1000002",
        "tgn:7029392"
    ],
    "tgn:id":7593319,
    "tgn:name":"Quebrada de Sangolqu\u00ed",
    "tgn:placetype":[
        "aat:300008699"
    ]
},
  "bbox": [],
  "geometry": {"coordinates":[-78.583,-0.416],"type":"Point"}
}