{
  "id": 7048198,
  "type": "Feature",
  "properties": {
    "tgn:hierarchy":[
        "tgn:7048198",
        "tgn:7003007",
        "tgn:1000003",
        "tgn:7002997",
        "tgn:1000080",
        "tgn:7029392"
    ],
    "tgn:id":7048198,
    "tgn:name":"Casale di Scodosia",
    "tgn:placetype":[
        "aat:300008347"
    ]
},
  "bbox": [],
  "geometry": {"coordinates":[11.466667,45.183333],"type":"Point"}
}