{
  "id": 2337890,
  "type": "Feature",
  "properties": {
    "tgn:hierarchy":[
        "tgn:2337890",
        "tgn:1002201",
        "tgn:1000001",
        "tgn:7012149",
        "tgn:7007517",
        "tgn:7029392"
    ],
    "tgn:id":2337890,
    "tgn:name":"Fox Hill",
    "tgn:placetype":[
        "aat:300008798"
    ]
},
  "bbox": [],
  "geometry": {"coordinates":[-71.1833,41.7167],"type":"Point"}
}