{
  "id": 2184479,
  "type": "Feature",
  "properties": {
    "tgn:hierarchy":[
        "tgn:2184479",
        "tgn:1000001",
        "tgn:2001260",
        "tgn:7012149",
        "tgn:7007524",
        "tgn:7029392"
    ],
    "tgn:id":2184479,
    "tgn:name":"Bobs Lake",
    "tgn:placetype":[
        "aat:300008680"
    ]
},
  "bbox": [],
  "geometry": {"coordinates":[-112.9833,45.65],"type":"Point"}
}