{
  "id": 2030057,
  "type": "Feature",
  "properties": {
    "tgn:hierarchy":[
        "tgn:2030057",
        "tgn:1000001",
        "tgn:2000498",
        "tgn:7012149",
        "tgn:7007251",
        "tgn:7029392"
    ],
    "tgn:id":2030057,
    "tgn:name":"Savanna",
    "tgn:placetype":[
        "aat:300008347"
    ]
},
  "bbox": [],
  "geometry": {"coordinates":[-90.15,42.0833],"type":"Point"}
}