{
  "id": 2710052,
  "type": "Feature",
  "properties": {
    "tgn:hierarchy":[
        "tgn:2710052",
        "tgn:1000001",
        "tgn:7012149",
        "tgn:2002179",
        "tgn:7007919",
        "tgn:7029392"
    ],
    "tgn:id":2710052,
    "tgn:name":"Talbott Reservoir",
    "tgn:placetype":[
        "aat:300006191"
    ]
},
  "bbox": [],
  "geometry": {"coordinates":[-80.3833,36.6667],"type":"Point"}
}