{
  "id": 2413414,
  "type": "Feature",
  "properties": {
    "tgn:hierarchy":[
        "tgn:2413414",
        "tgn:1000001",
        "tgn:2001418",
        "tgn:7012149",
        "tgn:7007526",
        "tgn:7029392"
    ],
    "tgn:id":2413414,
    "tgn:name":"Ione Summit",
    "tgn:placetype":[
        "aat:300008798"
    ]
},
  "bbox": [],
  "geometry": {"coordinates":[-117.5333,38.9667],"type":"Point"}
}