{
  "id": 6004427,
  "type": "Feature",
  "properties": {
    "tgn:hierarchy":[
        "tgn:6004427",
        "tgn:1000004",
        "tgn:1000111",
        "tgn:7029392"
    ],
    "tgn:id":6004427,
    "tgn:name":"Ordos Desert",
    "tgn:placetype":[
        "aat:300008916"
    ]
},
  "bbox": [],
  "geometry": {"coordinates":[109.152,38.75],"type":"Point"}
}