{
  "id": 2175403,
  "type": "Feature",
  "properties": {
    "tgn:hierarchy":[
        "tgn:2175403",
        "tgn:1000001",
        "tgn:7012149",
        "tgn:7029392"
    ],
    "tgn:id":2175403,
    "tgn:name":"Black Canyon",
    "tgn:placetype":[
        "aat:300008761"
    ]
},
  "bbox": [],
  "geometry": {"coordinates":[-114.7167,36.0167],"type":"Point"}
}