{
  "id": 7515994,
  "type": "Feature",
  "properties": {
    "tgn:hierarchy":[
        "tgn:7515994",
        "tgn:1008380",
        "tgn:1000226",
        "tgn:7000512",
        "tgn:1000006",
        "tgn:7029392"
    ],
    "tgn:id":7515994,
    "tgn:name:en":"Okoropunga Stream",
    "tgn:placetype":[
        "aat:300008699"
    ]
},
  "bbox": [],
  "geometry": {"coordinates":[175.65,-41.45],"type":"Point"}
}