{
  "id": 2442501,
  "type": "Feature",
  "properties": {
    "tgn:hierarchy":[
        "tgn:2442501",
        "tgn:1000001",
        "tgn:2001414",
        "tgn:7012149",
        "tgn:7007526",
        "tgn:7029392"
    ],
    "tgn:id":2442501,
    "tgn:name":"Krug Mine",
    "tgn:placetype":[
        "aat:300000390"
    ]
},
  "bbox": [],
  "geometry": {"coordinates":[-118.3333,41.0833],"type":"Point"}
}