<<<<<<< HEAD
{
  "id": 2766284,
  "type": "Feature",
  "properties": {
    "tgn:hierarchy":[
        "tgn:2766284",
        "tgn:1000001",
        "tgn:2001810",
        "tgn:7012149",
        "tgn:7007713",
        "tgn:7029392"
    ],
    "tgn:id":2766284,
    "tgn:name":"White Mansion",
    "tgn:placetype":[
        "aat:300008798"
    ]
},
  "bbox": [],
  "geometry": {"coordinates":[-103.5167,44.2167],"type":"Point"}
}
=======
{"geometry":{"type":"Point","coordinates":[-103.516700,44.216700]},"type":"Feature","properties":{"hierarchy":["tgn:2766284","tgn:1000001","tgn:2001810","tgn:7012149","tgn:7007713","tgn:7029392"],"placetype":["aat:300008798"],"id":2766284,"name:xx":"White Mansion"}}
>>>>>>> 03f74aca74312dbeaf24d7e61306dd6a786dc3d0
