{
  "id": 2766284,
  "type": "Feature",
  "properties": {
    "tgn:hierarchy":[
        "tgn:2766284",
        "tgn:1000001",
        "tgn:2001810",
        "tgn:7012149",
        "tgn:7007713",
        "tgn:7029392"
    ],
    "tgn:id":2766284,
    "tgn:name":"White Mansion",
    "tgn:placetype":[
        "aat:300008798"
    ]
},
  "bbox": [],
  "geometry": {"coordinates":[-103.5167,44.2167],"type":"Point"}
}