{
  "id": 2233334,
  "type": "Feature",
  "properties": {
    "tgn:hierarchy":[
        "tgn:2233334",
        "tgn:1000001",
        "tgn:7012149",
        "tgn:2001447",
        "tgn:7007566",
        "tgn:7029392"
    ],
    "tgn:id":2233334,
    "tgn:name":"Charley Tank",
    "tgn:placetype":[
        "aat:300006191"
    ]
},
  "bbox": [],
  "geometry": {"coordinates":[-105.8333,32.0833],"type":"Point"}
}