{
  "id": 2718809,
  "type": "Feature",
  "properties": {
    "tgn:hierarchy":[
        "tgn:2718809",
        "tgn:1000001",
        "tgn:7012149",
        "tgn:1002943",
        "tgn:7007708",
        "tgn:7029392"
    ],
    "tgn:id":2718809,
    "tgn:name":"Thorn Creek",
    "tgn:placetype":[
        "aat:300008706"
    ]
},
  "bbox": [],
  "geometry": {"coordinates":[-123.5167,45.25],"type":"Point"}
}