{
  "id": 7486454,
  "type": "Feature",
  "properties": {
    "tgn:hierarchy":[
        "tgn:7486454",
        "tgn:1000004",
        "tgn:7492971",
        "tgn:1000141",
        "tgn:7029392"
    ],
    "tgn:id":7486454,
    "tgn:name":"Ganggang",
    "tgn:placetype":[
        "aat:300008347"
    ]
},
  "bbox": [],
  "geometry": {"coordinates":[120.452066,22.520352],"type":"Point"}
}