{
  "id": 2229640,
  "type": "Feature",
  "properties": {
    "tgn:hierarchy":[
        "tgn:2229640",
        "tgn:1000001",
        "tgn:7012149",
        "tgn:2000406",
        "tgn:7007248",
        "tgn:7029392"
    ],
    "tgn:id":2229640,
    "tgn:name":"Cedar Rock Lake",
    "tgn:placetype":[
        "aat:300006191"
    ]
},
  "bbox": [],
  "geometry": {"coordinates":[-85.1833,33.9333],"type":"Point"}
}