{
  "id": 7590619,
  "type": "Feature",
  "properties": {
    "tgn:hierarchy":[
        "tgn:7590619",
        "tgn:1000004",
        "tgn:7000198",
        "tgn:7000799",
        "tgn:7029392"
    ],
    "tgn:id":7590619,
    "tgn:name:en":"Joi\u0101n",
    "tgn:placetype":[
        "aat:300008347"
    ]
},
  "bbox": [],
  "geometry": {"coordinates":[74.869878,32.520318],"type":"Point"}
}