{
  "id": 2031618,
  "type": "Feature",
  "properties": {
    "tgn:hierarchy":[
        "tgn:2031618",
        "tgn:1000001",
        "tgn:7012149",
        "tgn:1002678",
        "tgn:7007252",
        "tgn:7029392"
    ],
    "tgn:id":2031618,
    "tgn:name":"Dolan",
    "tgn:placetype":[
        "aat:300008347"
    ]
},
  "bbox": [],
  "geometry": {"coordinates":[-86.4833,39.2333],"type":"Point"}
}