{
  "id": 2461246,
  "type": "Feature",
  "properties": {
    "tgn:hierarchy":[
        "tgn:2461246",
        "tgn:1000001",
        "tgn:7012149",
        "tgn:2001826",
        "tgn:7007713",
        "tgn:7029392"
    ],
    "tgn:id":2461246,
    "tgn:name":"Little Squaw-Humper Table",
    "tgn:placetype":[
        "aat:300008798"
    ]
},
  "bbox": [],
  "geometry": {"coordinates":[-102.9167,43.5833],"type":"Point"}
}