{
  "id": 1076104,
  "type": "Feature",
  "properties": {
    "tgn:hierarchy":[
        "tgn:1076104",
        "tgn:1000004",
        "tgn:7000198",
        "tgn:1001977",
        "tgn:7029392"
    ],
    "tgn:id":1076104,
    "tgn:name":"Magara",
    "tgn:placetype":[
        "aat:300008347"
    ]
},
  "bbox": [],
  "geometry": {"coordinates":[87.5667,22.5667],"type":"Point"}
}