{
  "id": 7418789,
  "type": "Feature",
  "properties": {
    "tgn:hierarchy":[
        "tgn:7418789",
        "tgn:7005579",
        "tgn:1000001",
        "tgn:7005560",
        "tgn:7029392"
    ],
    "tgn:id":7418789,
    "tgn:name":"Grande, Arroyo",
    "tgn:placetype":[
        "aat:300266554",
        "aat:300008699"
    ]
},
  "bbox": [],
  "geometry": {"coordinates":[-102.216667,22.141667],"type":"Point"}
}