{
  "id": 7279955,
  "type": "Feature",
  "properties": {
    "tgn:hierarchy":[
        "tgn:7279955",
        "tgn:1001699",
        "tgn:1000049",
        "tgn:1000002",
        "tgn:7029392"
    ],
    "tgn:id":7279955,
    "tgn:name":"Rhone, Puerto",
    "tgn:placetype":[
        "aat:300008678"
    ]
},
  "bbox": [],
  "geometry": {"coordinates":[-74.115556,-44.034722],"type":"Point"}
}