{
  "id": 2264053,
  "type": "Feature",
  "properties": {
    "tgn:hierarchy":[
        "tgn:2264053",
        "tgn:1000001",
        "tgn:1002260",
        "tgn:7012149",
        "tgn:7007920",
        "tgn:7029392"
    ],
    "tgn:id":2264053,
    "tgn:name":"Coyote Ridge",
    "tgn:placetype":[
        "aat:300266640"
    ]
},
  "bbox": [],
  "geometry": {"coordinates":[-120.2833,48.0833],"type":"Point"}
}