{
  "id": 2612909,
  "type": "Feature",
  "properties": {
    "tgn:hierarchy":[
        "tgn:2612909",
        "tgn:1000001",
        "tgn:7012149",
        "tgn:2001507",
        "tgn:7007709",
        "tgn:7029392"
    ],
    "tgn:id":2612909,
    "tgn:name":"Redmond Mountain",
    "tgn:placetype":[
        "aat:300008798"
    ]
},
  "bbox": [],
  "geometry": {"coordinates":[-80.9833,36.0333],"type":"Point"}
}