{
  "id": 7318950,
  "type": "Feature",
  "properties": {
    "tgn:hierarchy":[
        "tgn:7318950",
        "tgn:1001695",
        "tgn:1000049",
        "tgn:1000002",
        "tgn:7029392"
    ],
    "tgn:id":7318950,
    "tgn:name":"Arica",
    "tgn:placetype":[
        "aat:300000206"
    ]
},
  "bbox": [],
  "geometry": {"coordinates":[-71.116667,-34.616667],"type":"Point"}
}