{
  "id": 2704488,
  "type": "Feature",
  "properties": {
    "tgn:hierarchy":[
        "tgn:2704488",
        "tgn:1000001",
        "tgn:7012149",
        "tgn:1002520",
        "tgn:7007710",
        "tgn:7029392"
    ],
    "tgn:id":2704488,
    "tgn:name":"Sunrise",
    "tgn:placetype":[
        "aat:300008347"
    ]
},
  "bbox": [],
  "geometry": {"coordinates":[-79.1667,40.9667],"type":"Point"}
}