{
  "id": 7319773,
  "type": "Feature",
  "properties": {
    "tgn:hierarchy":[
        "tgn:7319773",
        "tgn:1001699",
        "tgn:1000049",
        "tgn:1000002",
        "tgn:7029392"
    ],
    "tgn:id":7319773,
    "tgn:name":"Ahui, Punta",
    "tgn:placetype":[
        "aat:300386846"
    ]
},
  "bbox": [],
  "geometry": {"coordinates":[-73.866667,-41.833333],"type":"Point"}
}