<<<<<<< HEAD
{
  "id": 7020804,
  "type": "Feature",
  "properties": {
    "tgn:hierarchy":[
        "tgn:7020804",
        "tgn:1000001",
        "tgn:2000465",
        "tgn:7012149",
        "tgn:7007250",
        "tgn:7029392"
    ],
    "tgn:id":7020804,
    "tgn:name":"Goose Egg Island",
    "tgn:placetype":[
        "aat:300008791"
    ]
},
  "bbox": [],
  "geometry": {"coordinates":[-117.0167,43.75],"type":"Point"}
}
=======
{"geometry":{"type":"Point","coordinates":[-117.016700,43.750000]},"type":"Feature","properties":{"hierarchy":["tgn:7020804","tgn:1000001","tgn:2000465","tgn:7012149","tgn:7007250","tgn:7029392"],"placetype":["aat:300008791"],"id":7020804,"name:xx":"Goose Egg Island"}}
>>>>>>> 03f74aca74312dbeaf24d7e61306dd6a786dc3d0
