{
  "id": 7294468,
  "type": "Feature",
  "properties": {
    "tgn:hierarchy":[
        "tgn:7294468",
        "tgn:1001439",
        "tgn:1000003",
        "tgn:7002797",
        "tgn:1000095",
        "tgn:7029392"
    ],
    "tgn:id":7294468,
    "tgn:name":"Ventorrillo, Islote del",
    "tgn:placetype":[
        "aat:300008791"
    ]
},
  "bbox": [],
  "geometry": {"coordinates":[-0.75,37.783333],"type":"Point"}
}