{
  "id": 2649431,
  "type": "Feature",
  "properties": {
    "tgn:hierarchy":[
        "tgn:2649431",
        "tgn:1000001",
        "tgn:7006451",
        "tgn:7012149",
        "tgn:2000098",
        "tgn:7029392"
    ],
    "tgn:id":2649431,
    "tgn:name":"Scotts Hole",
    "tgn:placetype":[
        "aat:300386845"
    ]
},
  "bbox": [],
  "geometry": {"coordinates":[-112.7167,36.7667],"type":"Point"}
}