{
  "id": 2279421,
  "type": "Feature",
  "properties": {
    "tgn:hierarchy":[
        "tgn:2279421",
        "tgn:1000001",
        "tgn:7012149",
        "tgn:7007157",
        "tgn:2000191",
        "tgn:7029392"
    ],
    "tgn:id":2279421,
    "tgn:name":"Deadman Gulch",
    "tgn:placetype":[
        "aat:300008761"
    ]
},
  "bbox": [],
  "geometry": {"coordinates":[-122.9167,41.1667],"type":"Point"}
}