{
  "id": 7500400,
  "type": "Feature",
  "properties": {
    "tgn:hierarchy":[
        "tgn:7500400",
        "tgn:1000004",
        "tgn:7004300",
        "tgn:1000141",
        "tgn:7029392"
    ],
    "tgn:id":7500400,
    "tgn:name":"Diqi Gongmu",
    "tgn:placetype":[
        "aat:300266755"
    ]
},
  "bbox": [],
  "geometry": {"coordinates":[119.492222,23.568333],"type":"Point"}
}