{
  "id": 2084602,
  "type": "Feature",
  "properties": {
    "tgn:hierarchy":[
        "tgn:2084602",
        "tgn:1000001",
        "tgn:7012149",
        "tgn:2001716",
        "tgn:7007708",
        "tgn:7029392"
    ],
    "tgn:id":2084602,
    "tgn:name":"Creswell",
    "tgn:placetype":[
        "aat:300008347"
    ]
},
  "bbox": [],
  "geometry": {"coordinates":[-123.0167,43.9167],"type":"Point"}
}