<<<<<<< HEAD
{
  "id": 2338409,
  "type": "Feature",
  "properties": {
    "tgn:hierarchy":[
        "tgn:2338409",
        "tgn:1000001",
        "tgn:7012149",
        "tgn:2001617",
        "tgn:7007706",
        "tgn:7029392"
    ],
    "tgn:id":2338409,
    "tgn:name":"Foxtown",
    "tgn:placetype":[
        "aat:300008347"
    ]
},
  "bbox": [],
  "geometry": {"coordinates":[-81.0,39.6667],"type":"Point"}
}
=======
{"geometry":{"type":"Point","coordinates":[-81.000000,39.666700]},"type":"Feature","properties":{"hierarchy":["tgn:2338409","tgn:1000001","tgn:7012149","tgn:2001617","tgn:7007706","tgn:7029392"],"placetype":["aat:300008347"],"id":2338409,"name:xx":"Foxtown"}}
>>>>>>> 03f74aca74312dbeaf24d7e61306dd6a786dc3d0
