{
  "id": 7460134,
  "type": "Feature",
  "properties": {
    "tgn:hierarchy":[
        "tgn:7460134",
        "tgn:7002444",
        "tgn:1000003",
        "tgn:7009907",
        "tgn:7008591",
        "tgn:7029392"
    ],
    "tgn:id":7460134,
    "tgn:name:en":"Odness, Holm of",
    "tgn:placetype":[
        "aat:300008791"
    ]
},
  "bbox": [],
  "geometry": {"coordinates":[-2.533333,59.133333],"type":"Point"}
}