<<<<<<< HEAD
{
  "id": 7372343,
  "type": "Feature",
  "properties": {
    "tgn:hierarchy":[
        "tgn:7372343",
        "tgn:1000001",
        "tgn:7005599",
        "tgn:7005560",
        "tgn:7029392"
    ],
    "tgn:id":7372343,
    "tgn:name":"La Cantera",
    "tgn:placetype":[
        "aat:300008347"
    ]
},
  "bbox": [],
  "geometry": {"coordinates":[-96.316667,19.05],"type":"Point"}
}
=======
{"geometry":{"type":"Point","coordinates":[-96.316667,19.050000]},"type":"Feature","properties":{"hierarchy":["tgn:7372343","tgn:1000001","tgn:7005599","tgn:7005560","tgn:7029392"],"placetype":["aat:300008347"],"id":7372343,"name:xx":"La Cantera"}}
>>>>>>> 03f74aca74312dbeaf24d7e61306dd6a786dc3d0
