{
  "id": 2620442,
  "type": "Feature",
  "properties": {
    "tgn:hierarchy":[
        "tgn:2620442",
        "tgn:1000001",
        "tgn:7016172",
        "tgn:7012149",
        "tgn:2000164",
        "tgn:7029392"
    ],
    "tgn:id":2620442,
    "tgn:name":"River Ridge Manor",
    "tgn:placetype":[
        "aat:300008347"
    ]
},
  "bbox": [],
  "geometry": {"coordinates":[-92.3667,34.7833],"type":"Point"}
}