{
  "id": 7491814,
  "type": "Feature",
  "properties": {
    "tgn:hierarchy":[
        "tgn:7491814",
        "tgn:1000004",
        "tgn:7001013",
        "tgn:1000141",
        "tgn:7029392"
    ],
    "tgn:id":7491814,
    "tgn:name":"Shalun",
    "tgn:placetype":[
        "aat:300008347"
    ]
},
  "bbox": [],
  "geometry": {"coordinates":[121.222581,25.094129],"type":"Point"}
}