{
  "id": 7030626,
  "type": "Feature",
  "properties": {
    "tgn:hierarchy":[
        "tgn:7030626",
        "tgn:7002445",
        "tgn:1000003",
        "tgn:7019064",
        "tgn:7008591",
        "tgn:7029392"
    ],
    "tgn:id":7030626,
    "tgn:name:en":"Upper Poppleton",
    "tgn:placetype":[
        "aat:300008347",
        "aat:300008372"
    ]
},
  "bbox": [],
  "geometry": {"coordinates":[-1.15,53.966667],"type":"Point"}
}