{
  "id": 2219147,
  "type": "Feature",
  "properties": {
    "tgn:hierarchy":[
        "tgn:2219147",
        "tgn:1000001",
        "tgn:7012149",
        "tgn:2000841",
        "tgn:7007255",
        "tgn:7029392"
    ],
    "tgn:id":2219147,
    "tgn:name":"Caney Fork",
    "tgn:placetype":[
        "aat:300008699"
    ]
},
  "bbox": [],
  "geometry": {"coordinates":[-85.0667,37.05],"type":"Point"}
}