{
  "id": 1048728,
  "type": "Feature",
  "properties": {
    "tgn:hierarchy":[
        "tgn:1048728",
        "tgn:7003645",
        "tgn:1000003",
        "tgn:1000088",
        "tgn:7029392"
    ],
    "tgn:id":1048728,
    "tgn:name":"S\u00f8rli",
    "tgn:placetype":[
        "aat:300008347"
    ]
},
  "bbox": [],
  "geometry": {"coordinates":[13.8333,64.25],"type":"Point"}
}