{
  "id": 7466153,
  "type": "Feature",
  "properties": {
    "tgn:hierarchy":[
        "tgn:7466153",
        "tgn:7019094",
        "tgn:7002444",
        "tgn:1000003",
        "tgn:7008591",
        "tgn:7029392"
    ],
    "tgn:id":7466153,
    "tgn:name:en":"Ardnave",
    "tgn:placetype":[
        "aat:300008347"
    ]
},
  "bbox": [],
  "geometry": {"coordinates":[-6.35,55.866667],"type":"Point"}
}