{
  "id": 7272857,
  "type": "Feature",
  "properties": {
    "tgn:hierarchy":[
        "tgn:7272857",
        "tgn:1000003",
        "tgn:7003613",
        "tgn:7016845",
        "tgn:7029392"
    ],
    "tgn:id":7272857,
    "tgn:name:nl":"Uithuizerwad",
    "tgn:placetype":[
        "aat:300132350"
    ]
},
  "bbox": [],
  "geometry": {"coordinates":[6.683333,53.466667],"type":"Point"}
}