<<<<<<< HEAD
{
  "id": 2256434,
  "type": "Feature",
  "properties": {
    "tgn:hierarchy":[
        "tgn:2256434",
        "tgn:1000001",
        "tgn:7012149",
        "tgn:2001049",
        "tgn:7007521",
        "tgn:7029392"
    ],
    "tgn:id":2256434,
    "tgn:name":"Corabelle Lake",
    "tgn:placetype":[
        "aat:300008680"
    ]
},
  "bbox": [],
  "geometry": {"coordinates":[-95.8,43.8667],"type":"Point"}
}
=======
{"geometry":{"type":"Point","coordinates":[-95.800000,43.866700]},"type":"Feature","properties":{"hierarchy":["tgn:2256434","tgn:1000001","tgn:7012149","tgn:2001049","tgn:7007521","tgn:7029392"],"placetype":["aat:300008680"],"id":2256434,"name:xx":"Corabelle Lake"}}
>>>>>>> 03f74aca74312dbeaf24d7e61306dd6a786dc3d0
