{
  "id": 2551306,
  "type": "Feature",
  "properties": {
    "tgn:hierarchy":[
        "tgn:2551306",
        "tgn:1000001",
        "tgn:7012149",
        "tgn:7007157",
        "tgn:1002608",
        "tgn:7029392"
    ],
    "tgn:id":2551306,
    "tgn:name":"Nugget Point",
    "tgn:placetype":[
        "aat:300008850"
    ]
},
  "bbox": [],
  "geometry": {"coordinates":[-118.7667,34.65],"type":"Point"}
}