{
  "id": 2062862,
  "type": "Feature",
  "properties": {
    "tgn:hierarchy":[
        "tgn:2062862",
        "tgn:1000001",
        "tgn:2001414",
        "tgn:7012149",
        "tgn:7007526",
        "tgn:7029392"
    ],
    "tgn:id":2062862,
    "tgn:name":"Denio",
    "tgn:placetype":[
        "aat:300008347"
    ]
},
  "bbox": [],
  "geometry": {"coordinates":[-118.6333,41.9833],"type":"Point"}
}