<<<<<<< HEAD
{
  "id": 2766541,
  "type": "Feature",
  "properties": {
    "tgn:hierarchy":[
        "tgn:2766541",
        "tgn:1000001",
        "tgn:7012149",
        "tgn:7007251",
        "tgn:7029392"
    ],
    "tgn:id":2766541,
    "tgn:name":"White Oak Creek",
    "tgn:placetype":[
        "aat:300008706"
    ]
},
  "bbox": [],
  "geometry": {"coordinates":[-88.4167,37.8167],"type":"Point"}
}
=======
{"geometry":{"type":"Point","coordinates":[-88.416700,37.816700]},"type":"Feature","properties":{"hierarchy":["tgn:2766541","tgn:1000001","tgn:7012149","tgn:7007251","tgn:7029392"],"placetype":["aat:300008706"],"id":2766541,"name:xx":"White Oak Creek"}}
>>>>>>> 03f74aca74312dbeaf24d7e61306dd6a786dc3d0
