{
  "id": 7536728,
  "type": "Feature",
  "properties": {
    "tgn:hierarchy":[
        "tgn:7536728",
        "tgn:7001242",
        "tgn:7016833",
        "tgn:1001113",
        "tgn:7029392"
    ],
    "tgn:id":7536728,
    "tgn:name":"Kafr Awl\u0101d 'Abduh",
    "tgn:placetype":[
        "aat:300008347"
    ]
},
  "bbox": [],
  "geometry": {"coordinates":[31.703889,30.670556],"type":"Point"}
}