{
  "id": 1135809,
  "type": "Feature",
  "properties": {
    "tgn:hierarchy":[
        "tgn:1135809",
        "tgn:1000004",
        "tgn:7000190",
        "tgn:1000105",
        "tgn:7029392"
    ],
    "tgn:id":1135809,
    "tgn:name":"Tetulia",
    "tgn:placetype":[
        "aat:300387055"
    ]
},
  "bbox": [],
  "geometry": {"coordinates":[90.6167,22.25],"type":"Point"}
}