{
  "id": 2524646,
  "type": "Feature",
  "properties": {
    "tgn:hierarchy":[
        "tgn:2524646",
        "tgn:1000001",
        "tgn:2001414",
        "tgn:7012149",
        "tgn:7007526",
        "tgn:7029392"
    ],
    "tgn:id":2524646,
    "tgn:name":"Mormon Dan Peak",
    "tgn:placetype":[
        "aat:300008798"
    ]
},
  "bbox": [],
  "geometry": {"coordinates":[-119.1667,40.9667],"type":"Point"}
}