{
  "id": 2618196,
  "type": "Feature",
  "properties": {
    "tgn:hierarchy":[
        "tgn:2618196",
        "tgn:1000001",
        "tgn:7012149",
        "tgn:2002381",
        "tgn:7007923",
        "tgn:7029392"
    ],
    "tgn:id":2618196,
    "tgn:name":"Rifle Creek",
    "tgn:placetype":[
        "aat:300008706"
    ]
},
  "bbox": [],
  "geometry": {"coordinates":[-106.8833,44.6167],"type":"Point"}
}