{
  "id": 2610429,
  "type": "Feature",
  "properties": {
    "tgn:hierarchy":[
        "tgn:2610429",
        "tgn:1000001",
        "tgn:2000468",
        "tgn:7012149",
        "tgn:7007250",
        "tgn:7029392"
    ],
    "tgn:id":2610429,
    "tgn:name":"Red Canyon",
    "tgn:placetype":[
        "aat:300008761"
    ]
},
  "bbox": [],
  "geometry": {"coordinates":[-112.6167,44.4667],"type":"Point"}
}