{
  "id": 7074223,
  "type": "Feature",
  "properties": {
    "tgn:hierarchy":[
        "tgn:7074223",
        "tgn:7003669",
        "tgn:1000003",
        "tgn:7000084",
        "tgn:7029392"
    ],
    "tgn:id":7074223,
    "tgn:name":"Tennig",
    "tgn:placetype":[
        "aat:300008347"
    ]
},
  "bbox": [],
  "geometry": {"coordinates":[11.45,49.916667],"type":"Point"}
}