{
  "id": 7292782,
  "type": "Feature",
  "properties": {
    "tgn:hierarchy":[
        "tgn:7292782",
        "tgn:1001708",
        "tgn:1000049",
        "tgn:1000002",
        "tgn:7029392"
    ],
    "tgn:id":7292782,
    "tgn:name":"El Talhuenal",
    "tgn:placetype":[
        "aat:300008795"
    ]
},
  "bbox": [],
  "geometry": {"coordinates":[-70.65,-33.116667],"type":"Point"}
}