{
  "id": 7133072,
  "type": "Feature",
  "properties": {
    "tgn:hierarchy":[
        "tgn:7133072",
        "tgn:7003692",
        "tgn:1000003",
        "tgn:7000084",
        "tgn:7029392"
    ],
    "tgn:id":7133072,
    "tgn:name":"Mocken",
    "tgn:placetype":[
        "aat:300000206"
    ]
},
  "bbox": [],
  "geometry": {"coordinates":[9.55,47.783333],"type":"Point"}
}