{
  "id": 2237660,
  "type": "Feature",
  "properties": {
    "tgn:hierarchy":[
        "tgn:2237660",
        "tgn:1000001",
        "tgn:7012149",
        "tgn:7007524",
        "tgn:7029392"
    ],
    "tgn:id":2237660,
    "tgn:name":"Chinese Wall",
    "tgn:placetype":[
        "aat:300266640"
    ]
},
  "bbox": [],
  "geometry": {"coordinates":[-113.15,47.6833],"type":"Point"}
}