{
  "id": 7587743,
  "type": "Feature",
  "properties": {
    "tgn:hierarchy":[
        "tgn:7587743",
        "tgn:1000004",
        "tgn:1001832",
        "tgn:7000198",
        "tgn:7029392"
    ],
    "tgn:id":7587743,
    "tgn:name:en":"Killarbogh",
    "tgn:placetype":[
        "aat:300008347"
    ]
},
  "bbox": [],
  "geometry": {"coordinates":[92.531422,24.296521],"type":"Point"}
}