{
  "id": 7169210,
  "type": "Feature",
  "properties": {
    "tgn:hierarchy":[
        "tgn:7169210",
        "tgn:1000003",
        "tgn:7003677",
        "tgn:7000084",
        "tgn:7029392"
    ],
    "tgn:id":7169210,
    "tgn:name":"Helle",
    "tgn:placetype":[
        "aat:300266640"
    ]
},
  "bbox": [],
  "geometry": {"coordinates":[8.283333,51.066667],"type":"Point"}
}