{
  "id": 2243731,
  "type": "Feature",
  "properties": {
    "tgn:hierarchy":[
        "tgn:2243731",
        "tgn:1000001",
        "tgn:7012149",
        "tgn:7014510",
        "tgn:7007920",
        "tgn:7029392"
    ],
    "tgn:id":2243731,
    "tgn:name":"Clendenen Creek",
    "tgn:placetype":[
        "aat:300008706"
    ]
},
  "bbox": [],
  "geometry": {"coordinates":[-121.7333,48.3833],"type":"Point"}
}