{
  "id": 7182151,
  "type": "Feature",
  "properties": {
    "tgn:hierarchy":[
        "tgn:7182151",
        "tgn:7003669",
        "tgn:1000003",
        "tgn:7000084",
        "tgn:7029392"
    ],
    "tgn:id":7182151,
    "tgn:name":"Furthof",
    "tgn:placetype":[
        "aat:300000206"
    ]
},
  "bbox": [],
  "geometry": {"coordinates":[11.65,48.683333],"type":"Point"}
}