{
  "id": 7141095,
  "type": "Feature",
  "properties": {
    "tgn:hierarchy":[
        "tgn:7141095",
        "tgn:7003669",
        "tgn:1000003",
        "tgn:7000084",
        "tgn:7029392"
    ],
    "tgn:id":7141095,
    "tgn:name":"Luss Berg",
    "tgn:placetype":[
        "aat:300008795"
    ]
},
  "bbox": [],
  "geometry": {"coordinates":[12.583333,49.483333],"type":"Point"}
}