{
  "id": 2492614,
  "type": "Feature",
  "properties": {
    "tgn:hierarchy":[
        "tgn:2492614",
        "tgn:1000001",
        "tgn:2001477",
        "tgn:7012149",
        "tgn:7007709",
        "tgn:7029392"
    ],
    "tgn:id":2492614,
    "tgn:name":"Marina Creek",
    "tgn:placetype":[
        "aat:300008706"
    ]
},
  "bbox": [],
  "geometry": {"coordinates":[-76.4167,34.8333],"type":"Point"}
}