{
  "id": 1081276,
  "type": "Feature",
  "properties": {
    "tgn:hierarchy":[
        "tgn:1081276",
        "tgn:1000971",
        "tgn:1000004",
        "tgn:7000894",
        "tgn:1000120",
        "tgn:7029392"
    ],
    "tgn:id":1081276,
    "tgn:name":"Shibayama",
    "tgn:placetype":[
        "aat:300008347"
    ]
},
  "bbox": [],
  "geometry": {"coordinates":[140.4333,35.6833],"type":"Point"}
}