{
  "id": 2243448,
  "type": "Feature",
  "properties": {
    "tgn:hierarchy":[
        "tgn:2243448",
        "tgn:1000001",
        "tgn:7012149",
        "tgn:1002793",
        "tgn:7007240",
        "tgn:7029392"
    ],
    "tgn:id":2243448,
    "tgn:name":"Clearwater Lake",
    "tgn:placetype":[
        "aat:300008680"
    ]
},
  "bbox": [],
  "geometry": {"coordinates":[-81.8167,28.1667],"type":"Point"}
}