{
  "id": 2049514,
  "type": "Feature",
  "properties": {
    "tgn:hierarchy":[
        "tgn:2049514",
        "tgn:1000001",
        "tgn:7014423",
        "tgn:7012149",
        "tgn:7007517",
        "tgn:7029392"
    ],
    "tgn:id":2049514,
    "tgn:name":"Brant Rock",
    "tgn:placetype":[
        "aat:300008347"
    ]
},
  "bbox": [],
  "geometry": {"coordinates":[-70.6333,42.0833],"type":"Point"}
}