{
  "id": 7429489,
  "type": "Feature",
  "properties": {
    "tgn:hierarchy":[
        "tgn:7429489",
        "tgn:1001835",
        "tgn:1000001",
        "tgn:7005560",
        "tgn:7029392"
    ],
    "tgn:id":7429489,
    "tgn:name":"El D\u00e1til",
    "tgn:placetype":[
        "aat:300008347"
    ]
},
  "bbox": [],
  "geometry": {"coordinates":[-116.133333,31.233333],"type":"Point"}
}