{
  "id": 2613802,
  "type": "Feature",
  "properties": {
    "tgn:hierarchy":[
        "tgn:2613802",
        "tgn:1000001",
        "tgn:2000325",
        "tgn:7012149",
        "tgn:7007248",
        "tgn:7029392"
    ],
    "tgn:id":2613802,
    "tgn:name":"Reedy Creek",
    "tgn:placetype":[
        "aat:300008706"
    ]
},
  "bbox": [],
  "geometry": {"coordinates":[-83.0167,31.5667],"type":"Point"}
}