{
  "id": 2188802,
  "type": "Feature",
  "properties": {
    "tgn:hierarchy":[
        "tgn:2188802",
        "tgn:1000001",
        "tgn:7012149",
        "tgn:2000182",
        "tgn:7007157",
        "tgn:7029392"
    ],
    "tgn:id":2188802,
    "tgn:name":"Boulder Creek",
    "tgn:placetype":[
        "aat:300008706"
    ]
},
  "bbox": [],
  "geometry": {"coordinates":[-116.0833,32.6167],"type":"Point"}
}