{
  "id": 2034967,
  "type": "Feature",
  "properties": {
    "tgn:hierarchy":[
        "tgn:2034967",
        "tgn:1000001",
        "tgn:7012149",
        "tgn:2000644",
        "tgn:7007253",
        "tgn:7029392"
    ],
    "tgn:id":2034967,
    "tgn:name":"Hull",
    "tgn:placetype":[
        "aat:300008347"
    ]
},
  "bbox": [],
  "geometry": {"coordinates":[-96.1333,43.1833],"type":"Point"}
}