{
  "id": 2576616,
  "type": "Feature",
  "properties": {
    "tgn:hierarchy":[
        "tgn:2576616",
        "tgn:1000001",
        "tgn:7012149",
        "tgn:2001762",
        "tgn:7007712",
        "tgn:7029392"
    ],
    "tgn:id":2576616,
    "tgn:name":"Persimmon Branch",
    "tgn:placetype":[
        "aat:300008699"
    ]
},
  "bbox": [],
  "geometry": {"coordinates":[-81.0167,33.6667],"type":"Point"}
}