{
  "id": 7589887,
  "type": "Feature",
  "properties": {
    "tgn:hierarchy":[
        "tgn:7589887",
        "tgn:1000004",
        "tgn:7000198",
        "tgn:7000799",
        "tgn:7029392"
    ],
    "tgn:id":7589887,
    "tgn:name:en":"Charw\u0101l",
    "tgn:placetype":[
        "aat:300008347"
    ]
},
  "bbox": [],
  "geometry": {"coordinates":[74.432172,33.070126],"type":"Point"}
}