{
  "id": 2457378,
  "type": "Feature",
  "properties": {
    "tgn:hierarchy":[
        "tgn:2457378",
        "tgn:1000001",
        "tgn:7012149",
        "tgn:7014589",
        "tgn:7007515",
        "tgn:7029392"
    ],
    "tgn:id":2457378,
    "tgn:name":"Little Lily Lake",
    "tgn:placetype":[
        "aat:300008680"
    ]
},
  "bbox": [],
  "geometry": {"coordinates":[-67.45,44.75],"type":"Point"}
}