{
  "id": 1091171,
  "type": "Feature",
  "properties": {
    "tgn:hierarchy":[
        "tgn:1091171",
        "tgn:7001242",
        "tgn:1001688",
        "tgn:1000175",
        "tgn:7029392"
    ],
    "tgn:id":1091171,
    "tgn:name":"Kali",
    "tgn:placetype":[
        "aat:300008347"
    ]
},
  "bbox": [],
  "geometry": {"coordinates":[-11.4833,12.1667],"type":"Point"}
}