<<<<<<< HEAD
{
  "id": 2150460,
  "type": "Feature",
  "properties": {
    "tgn:hierarchy":[
        "tgn:2150460",
        "tgn:1000001",
        "tgn:2000304",
        "tgn:7012149",
        "tgn:7007248",
        "tgn:7029392"
    ],
    "tgn:id":2150460,
    "tgn:name":"Basin Lake",
    "tgn:placetype":[
        "aat:300008680"
    ]
},
  "bbox": [],
  "geometry": {"coordinates":[-81.8667,31.2667],"type":"Point"}
}
=======
{"geometry":{"type":"Point","coordinates":[-81.866700,31.266700]},"type":"Feature","properties":{"hierarchy":["tgn:2150460","tgn:1000001","tgn:2000304","tgn:7012149","tgn:7007248","tgn:7029392"],"placetype":["aat:300008680"],"id":2150460,"name:xx":"Basin Lake"}}
>>>>>>> 03f74aca74312dbeaf24d7e61306dd6a786dc3d0
