{
  "id": 2660960,
  "type": "Feature",
  "properties": {
    "tgn:hierarchy":[
        "tgn:2660960",
        "tgn:1000001",
        "tgn:2001260",
        "tgn:7012149",
        "tgn:7007524",
        "tgn:7029392"
    ],
    "tgn:id":2660960,
    "tgn:name":"Short Creek",
    "tgn:placetype":[
        "aat:300008706"
    ]
},
  "bbox": [],
  "geometry": {"coordinates":[-113.35,45.1333],"type":"Point"}
}