{
  "id": 7304914,
  "type": "Feature",
  "properties": {
    "tgn:hierarchy":[
        "tgn:7304914",
        "tgn:7002759",
        "tgn:7008909",
        "tgn:1000003",
        "tgn:1000095",
        "tgn:7029392"
    ],
    "tgn:id":7304914,
    "tgn:name":"Latorrecilla",
    "tgn:placetype":[
        "aat:300008347"
    ]
},
  "bbox": [],
  "geometry": {"coordinates":[0.085944,42.403164],"type":"Point"}
}