{
  "id": 2653896,
  "type": "Feature",
  "properties": {
    "tgn:hierarchy":[
        "tgn:2653896",
        "tgn:1000001",
        "tgn:7012149",
        "tgn:7007828",
        "tgn:7029392"
    ],
    "tgn:id":2653896,
    "tgn:name":"Seymour River",
    "tgn:placetype":[
        "aat:300008707"
    ]
},
  "bbox": [],
  "geometry": {"coordinates":[-72.8667,44.5333],"type":"Point"}
}