{
  "id": 2647610,
  "type": "Feature",
  "properties": {
    "tgn:hierarchy":[
        "tgn:2647610",
        "tgn:1000001",
        "tgn:2000675",
        "tgn:7012149",
        "tgn:7007254",
        "tgn:7029392"
    ],
    "tgn:id":2647610,
    "tgn:name":"School Creek",
    "tgn:placetype":[
        "aat:300008706"
    ]
},
  "bbox": [],
  "geometry": {"coordinates":[-95.65,38.35],"type":"Point"}
}