<<<<<<< HEAD
{
  "id": 7175478,
  "type": "Feature",
  "properties": {
    "tgn:hierarchy":[
        "tgn:7175478",
        "tgn:1000003",
        "tgn:7003682",
        "tgn:7000084",
        "tgn:7029392"
    ],
    "tgn:id":7175478,
    "tgn:name":"Gro\u00dfer Berg",
    "tgn:placetype":[
        "aat:300008777"
    ]
},
  "bbox": [],
  "geometry": {"coordinates":[7.933333,49.4],"type":"Point"}
}
=======
{"geometry":{"type":"Point","coordinates":[7.933333,49.400000]},"type":"Feature","properties":{"hierarchy":["tgn:7175478","tgn:1000003","tgn:7003682","tgn:7000084","tgn:7029392"],"placetype":["aat:300008777"],"id":7175478,"name:xx":"Gro\u00dfer Berg"}}
>>>>>>> 03f74aca74312dbeaf24d7e61306dd6a786dc3d0
