{
  "id": 2488845,
  "type": "Feature",
  "properties": {
    "tgn:hierarchy":[
        "tgn:2488845",
        "tgn:1000001",
        "tgn:7012149",
        "tgn:2002062",
        "tgn:7007826",
        "tgn:7029392"
    ],
    "tgn:id":2488845,
    "tgn:name":"Main Canal",
    "tgn:placetype":[
        "aat:300006075"
    ]
},
  "bbox": [],
  "geometry": {"coordinates":[-103.7667,30.9667],"type":"Point"}
}