{
  "id": 7475680,
  "type": "Feature",
  "properties": {
    "tgn:hierarchy":[
        "tgn:7475680",
        "tgn:7488858",
        "tgn:1000004",
        "tgn:1000141",
        "tgn:7029392"
    ],
    "tgn:id":7475680,
    "tgn:name":"Baiyelin",
    "tgn:placetype":[
        "aat:300008347"
    ]
},
  "bbox": [],
  "geometry": {"coordinates":[120.8047,23.7889],"type":"Point"}
}