{
  "id": 7421152,
  "type": "Feature",
  "properties": {
    "tgn:hierarchy":[
        "tgn:7421152",
        "tgn:7005584",
        "tgn:1000001",
        "tgn:7005560",
        "tgn:7029392"
    ],
    "tgn:id":7421152,
    "tgn:name":"San Juan de la Chica",
    "tgn:placetype":[
        "aat:300008347"
    ]
},
  "bbox": [],
  "geometry": {"coordinates":[-101.292778,21.351111],"type":"Point"}
}