{
  "id": 7534199,
  "type": "Feature",
  "properties": {
    "tgn:hierarchy":[
        "tgn:7534199",
        "tgn:7001242",
        "tgn:7016833",
        "tgn:7001336",
        "tgn:7029392"
    ],
    "tgn:id":7534199,
    "tgn:name:en":"Mars\u00e1 Ma\u1e29ash al Aa'l\u00e1",
    "tgn:placetype":[
        "aat:300386968"
    ]
},
  "bbox": [],
  "geometry": {"coordinates":[34.755197,29.324214],"type":"Point"}
}