{
  "id": 2552274,
  "type": "Feature",
  "properties": {
    "tgn:hierarchy":[
        "tgn:2552274",
        "tgn:1000001",
        "tgn:7012149",
        "tgn:1002978",
        "tgn:7007252",
        "tgn:7029392"
    ],
    "tgn:id":2552274,
    "tgn:name":"Number Thirteen, Reserve",
    "tgn:placetype":[
        "aat:300008178"
    ]
},
  "bbox": [],
  "geometry": {"coordinates":[-85.8833,40.7667],"type":"Point"}
}