{
  "id": 7030783,
  "type": "Feature",
  "properties": {
    "tgn:hierarchy":[
        "tgn:7030783",
        "tgn:7002445",
        "tgn:1000003",
        "tgn:7012031",
        "tgn:7008591",
        "tgn:7029392"
    ],
    "tgn:id":7030783,
    "tgn:name:en":"Braybrooke",
    "tgn:placetype":[
        "aat:300008347",
        "aat:300008372"
    ]
},
  "bbox": [],
  "geometry": {"coordinates":[-0.866667,52.45],"type":"Point"}
}