{
  "id": 7470989,
  "type": "Feature",
  "properties": {
    "tgn:hierarchy":[
        "tgn:7470989",
        "tgn:1000004",
        "tgn:7490934",
        "tgn:1000141",
        "tgn:7029392"
    ],
    "tgn:id":7470989,
    "tgn:name":"Houliao",
    "tgn:placetype":[
        "aat:300008347"
    ]
},
  "bbox": [],
  "geometry": {"coordinates":[120.34843,23.00883],"type":"Point"}
}