{
  "id": 1137005,
  "type": "Feature",
  "properties": {
    "tgn:hierarchy":[
        "tgn:1137005",
        "tgn:7003158",
        "tgn:1000003",
        "tgn:7003124",
        "tgn:1000080",
        "tgn:7029392"
    ],
    "tgn:id":1137005,
    "tgn:name":"Calliano",
    "tgn:placetype":[
        "aat:300008347"
    ]
},
  "bbox": [],
  "geometry": {"coordinates":[11.083333,45.933333],"type":"Point"}
}