<<<<<<< HEAD
{
  "id": 2253704,
  "type": "Feature",
  "properties": {
    "tgn:hierarchy":[
        "tgn:2253704",
        "tgn:1000001",
        "tgn:7012149",
        "tgn:2002340",
        "tgn:7007922",
        "tgn:7029392"
    ],
    "tgn:id":2253704,
    "tgn:name":"Cook Valley",
    "tgn:placetype":[
        "aat:300008761"
    ]
},
  "bbox": [],
  "geometry": {"coordinates":[-90.6667,43.7667],"type":"Point"}
}
=======
{"geometry":{"type":"Point","coordinates":[-90.666700,43.766700]},"type":"Feature","properties":{"hierarchy":["tgn:2253704","tgn:1000001","tgn:7012149","tgn:2002340","tgn:7007922","tgn:7029392"],"placetype":["aat:300008761"],"id":2253704,"name:xx":"Cook Valley"}}
>>>>>>> 03f74aca74312dbeaf24d7e61306dd6a786dc3d0
