{
  "id": 1079717,
  "type": "Feature",
  "properties": {
    "tgn:hierarchy":[
        "tgn:1079717",
        "tgn:1001015",
        "tgn:7000897",
        "tgn:1000004",
        "tgn:1000120",
        "tgn:7029392"
    ],
    "tgn:id":1079717,
    "tgn:name":"\u014csa",
    "tgn:placetype":[
        "aat:300008347"
    ]
},
  "bbox": [],
  "geometry": {"coordinates":[133.5667,35.0833],"type":"Point"}
}