{
  "id": 7109673,
  "type": "Feature",
  "properties": {
    "tgn:hierarchy":[
        "tgn:7109673",
        "tgn:7003692",
        "tgn:1000003",
        "tgn:7000084",
        "tgn:7029392"
    ],
    "tgn:id":7109673,
    "tgn:name":"Ramsee",
    "tgn:placetype":[
        "aat:300008347"
    ]
},
  "bbox": [],
  "geometry": {"coordinates":[9.55,47.833333],"type":"Point"}
}