{
  "id": 2745917,
  "type": "Feature",
  "properties": {
    "tgn:hierarchy":[
        "tgn:2745917",
        "tgn:1000001",
        "tgn:7012149",
        "tgn:1002961",
        "tgn:7007568",
        "tgn:7029392"
    ],
    "tgn:id":2745917,
    "tgn:name":"Vly Brook",
    "tgn:placetype":[
        "aat:300008699"
    ]
},
  "bbox": [],
  "geometry": {"coordinates":[-74.2333,41.85],"type":"Point"}
}