{
  "id": 7163767,
  "type": "Feature",
  "properties": {
    "tgn:hierarchy":[
        "tgn:7163767",
        "tgn:1000003",
        "tgn:7003678",
        "tgn:7000084",
        "tgn:7029392"
    ],
    "tgn:id":7163767,
    "tgn:name":"Immen-Graben",
    "tgn:placetype":[
        "aat:300008773"
    ]
},
  "bbox": [],
  "geometry": {"coordinates":[9.133333,51.15],"type":"Point"}
}