{
  "id": 7039585,
  "type": "Feature",
  "properties": {
    "tgn:hierarchy":[
        "tgn:7039585",
        "tgn:1003450",
        "tgn:7007850",
        "tgn:1000003",
        "tgn:1000080",
        "tgn:7029392"
    ],
    "tgn:id":7039585,
    "tgn:name":"Santo Stefano di Rogliano",
    "tgn:placetype":[
        "aat:300008347"
    ]
},
  "bbox": [],
  "geometry": {"coordinates":[16.316667,39.183333],"type":"Point"}
}