{
  "id": 2325870,
  "type": "Feature",
  "properties": {
    "tgn:hierarchy":[
        "tgn:2325870",
        "tgn:1000001",
        "tgn:7012149",
        "tgn:2001724",
        "tgn:7007710",
        "tgn:7029392"
    ],
    "tgn:id":2325870,
    "tgn:name":"Fieldsons Crossroads",
    "tgn:placetype":[
        "aat:300008347"
    ]
},
  "bbox": [],
  "geometry": {"coordinates":[-79.9333,39.7833],"type":"Point"}
}