{
  "id": 2732944,
  "type": "Feature",
  "properties": {
    "tgn:hierarchy":[
        "tgn:2732944",
        "tgn:1000001",
        "tgn:7012149",
        "tgn:1002580",
        "tgn:7007710",
        "tgn:7029392"
    ],
    "tgn:id":2732944,
    "tgn:name":"Turkey Hill",
    "tgn:placetype":[
        "aat:300008798"
    ]
},
  "bbox": [],
  "geometry": {"coordinates":[-80.3167,40.9167],"type":"Point"}
}