{
  "id": 7334934,
  "type": "Feature",
  "properties": {
    "tgn:hierarchy":[
        "tgn:7334934",
        "tgn:7002816",
        "tgn:1001647",
        "tgn:1000003",
        "tgn:1000095",
        "tgn:7029392"
    ],
    "tgn:id":7334934,
    "tgn:name":"Fuenllana",
    "tgn:placetype":[
        "aat:300008347"
    ]
},
  "bbox": [],
  "geometry": {"coordinates":[-2.95,38.75],"type":"Point"}
}