<<<<<<< HEAD
{
  "id": 7175615,
  "type": "Feature",
  "properties": {
    "tgn:hierarchy":[
        "tgn:7175615",
        "tgn:1000003",
        "tgn:7003682",
        "tgn:7000084",
        "tgn:7029392"
    ],
    "tgn:id":7175615,
    "tgn:name":"Gro\u00df-Winternheim",
    "tgn:placetype":[
        "aat:300008347"
    ]
},
  "bbox": [],
  "geometry": {"coordinates":[8.08,49.943889],"type":"Point"}
}
=======
{"geometry":{"type":"Point","coordinates":[8.080000,49.943889]},"type":"Feature","properties":{"hierarchy":["tgn:7175615","tgn:1000003","tgn:7003682","tgn:7000084","tgn:7029392"],"placetype":["aat:300008347"],"id":7175615,"name:xx":"Gro\u00df-Winternheim"}}
>>>>>>> 03f74aca74312dbeaf24d7e61306dd6a786dc3d0
