{
  "id": 2110379,
  "type": "Feature",
  "properties": {
    "tgn:hierarchy":[
        "tgn:2110379",
        "tgn:1000001",
        "tgn:7012149",
        "tgn:1002411",
        "tgn:7007919",
        "tgn:7029392"
    ],
    "tgn:id":2110379,
    "tgn:name":"Ark",
    "tgn:placetype":[
        "aat:300008347"
    ]
},
  "bbox": [],
  "geometry": {"coordinates":[-76.5667,37.4333],"type":"Point"}
}