{
  "id": 2383274,
  "type": "Feature",
  "properties": {
    "tgn:hierarchy":[
        "tgn:2383274",
        "tgn:1000001",
        "tgn:2000464",
        "tgn:7012149",
        "tgn:7007250",
        "tgn:7029392"
    ],
    "tgn:id":2383274,
    "tgn:name":"Hearn Creek",
    "tgn:placetype":[
        "aat:300008706"
    ]
},
  "bbox": [],
  "geometry": {"coordinates":[-115.05,43.4167],"type":"Point"}
}