{
  "id": 2427564,
  "type": "Feature",
  "properties": {
    "tgn:hierarchy":[
        "tgn:2427564",
        "tgn:1000001",
        "tgn:7012149",
        "tgn:2001712",
        "tgn:7007708",
        "tgn:7029392"
    ],
    "tgn:id":2427564,
    "tgn:name":"Jory Basin",
    "tgn:placetype":[
        "aat:300386845"
    ]
},
  "bbox": [],
  "geometry": {"coordinates":[-120.7833,44.7333],"type":"Point"}
}