{
  "id": 7060523,
  "type": "Feature",
  "properties": {
    "tgn:hierarchy":[
        "tgn:7060523",
        "tgn:1000003",
        "tgn:7003687",
        "tgn:7000084",
        "tgn:7029392"
    ],
    "tgn:id":7060523,
    "tgn:name":"Bahnhof Annaburg",
    "tgn:placetype":[
        "aat:300007783"
    ]
},
  "bbox": [],
  "geometry": {"coordinates":[13.333611,51.728333],"type":"Point"}
}