{
  "id": 2669114,
  "type": "Feature",
  "properties": {
    "tgn:hierarchy":[
        "tgn:2669114",
        "tgn:1000001",
        "tgn:7012149",
        "tgn:1002993",
        "tgn:7007568",
        "tgn:7029392"
    ],
    "tgn:id":2669114,
    "tgn:name":"Sleeping Beauty",
    "tgn:placetype":[
        "aat:300008798"
    ]
},
  "bbox": [],
  "geometry": {"coordinates":[-73.55,43.55],"type":"Point"}
}