{
  "id": 7469975,
  "type": "Feature",
  "properties": {
    "tgn:hierarchy":[
        "tgn:7469975",
        "tgn:1000004",
        "tgn:7492971",
        "tgn:1000141",
        "tgn:7029392"
    ],
    "tgn:id":7469975,
    "tgn:name":"Xiacuo",
    "tgn:placetype":[
        "aat:300008347"
    ]
},
  "bbox": [],
  "geometry": {"coordinates":[120.528936,22.692436],"type":"Point"}
}