{
  "id": 2368710,
  "type": "Feature",
  "properties": {
    "tgn:hierarchy":[
        "tgn:2368710",
        "tgn:7006450",
        "tgn:1000001",
        "tgn:7012149",
        "tgn:2000089",
        "tgn:7029392"
    ],
    "tgn:id":2368710,
    "tgn:name":"Gull Island",
    "tgn:placetype":[
        "aat:300008791"
    ]
},
  "bbox": [],
  "geometry": {"coordinates":[-148.5167,66.15],"type":"Point"}
}