<<<<<<< HEAD
{
  "id": 7117426,
  "type": "Feature",
  "properties": {
    "tgn:hierarchy":[
        "tgn:7117426",
        "tgn:7003692",
        "tgn:1000003",
        "tgn:7000084",
        "tgn:7029392"
    ],
    "tgn:id":7117426,
    "tgn:name":"Oberstetterberg",
    "tgn:placetype":[
        "aat:300008863"
    ]
},
  "bbox": [],
  "geometry": {"coordinates":[9.05,48.05],"type":"Point"}
}
=======
{"geometry":{"type":"Point","coordinates":[9.050000,48.050000]},"type":"Feature","properties":{"hierarchy":["tgn:7117426","tgn:7003692","tgn:1000003","tgn:7000084","tgn:7029392"],"placetype":["aat:300008863"],"id":7117426,"name:xx":"Oberstetterberg"}}
>>>>>>> 03f74aca74312dbeaf24d7e61306dd6a786dc3d0
