{
  "id": 7452443,
  "type": "Feature",
  "properties": {
    "tgn:hierarchy":[
        "tgn:7452443",
        "tgn:7002443",
        "tgn:7018962",
        "tgn:1000003",
        "tgn:7008591",
        "tgn:7029392"
    ],
    "tgn:id":7452443,
    "tgn:name:en":"Ely",
    "tgn:placetype":[
        "aat:300000745"
    ]
},
  "bbox": [],
  "geometry": {"coordinates":[-3.231944,51.485],"type":"Point"}
}