{
  "id": 2361790,
  "type": "Feature",
  "properties": {
    "tgn:hierarchy":[
        "tgn:2361790",
        "tgn:7002659",
        "tgn:1000001",
        "tgn:7012149",
        "tgn:2000035",
        "tgn:7029392"
    ],
    "tgn:id":2361790,
    "tgn:name":"Gray Branch",
    "tgn:placetype":[
        "aat:300008699"
    ]
},
  "bbox": [],
  "geometry": {"coordinates":[-85.7167,34.85],"type":"Point"}
}