{
  "id": 7589107,
  "type": "Feature",
  "properties": {
    "tgn:hierarchy":[
        "tgn:7589107",
        "tgn:1000004",
        "tgn:7000198",
        "tgn:7000799",
        "tgn:7029392"
    ],
    "tgn:id":7589107,
    "tgn:name:en":"Dh\u0101r Gathun B\u0101uji",
    "tgn:placetype":[
        "aat:300008347"
    ]
},
  "bbox": [],
  "geometry": {"coordinates":[74.183333,33.583333],"type":"Point"}
}