<<<<<<< HEAD
{
  "id": 7112018,
  "type": "Feature",
  "properties": {
    "tgn:hierarchy":[
        "tgn:7112018",
        "tgn:7003669",
        "tgn:1000003",
        "tgn:7000084",
        "tgn:7029392"
    ],
    "tgn:id":7112018,
    "tgn:name":"Rohrberg",
    "tgn:placetype":[
        "aat:300008777"
    ]
},
  "bbox": [],
  "geometry": {"coordinates":[11.983333,50.05],"type":"Point"}
}
=======
{"geometry":{"type":"Point","coordinates":[11.983333,50.050000]},"type":"Feature","properties":{"hierarchy":["tgn:7112018","tgn:7003669","tgn:1000003","tgn:7000084","tgn:7029392"],"placetype":["aat:300008777"],"id":7112018,"name:xx":"Rohrberg"}}
>>>>>>> 03f74aca74312dbeaf24d7e61306dd6a786dc3d0
