{
  "id": 2209429,
  "type": "Feature",
  "properties": {
    "tgn:hierarchy":[
        "tgn:2209429",
        "tgn:1000001",
        "tgn:7012149",
        "tgn:2001509",
        "tgn:7007709",
        "tgn:7029392"
    ],
    "tgn:id":2209429,
    "tgn:name":"Burnt Stocking Branch",
    "tgn:placetype":[
        "aat:300008699"
    ]
},
  "bbox": [],
  "geometry": {"coordinates":[-78.2333,35.5333],"type":"Point"}
}