<<<<<<< HEAD
{
  "id": 7244195,
  "type": "Feature",
  "properties": {
    "tgn:hierarchy":[
        "tgn:7244195",
        "tgn:7003461",
        "tgn:1000003",
        "tgn:1000063",
        "tgn:7018236",
        "tgn:7029392"
    ],
    "tgn:id":7244195,
    "tgn:name":"Kanjelstraatbeek",
    "tgn:placetype":[
        "aat:300008699"
    ]
},
  "bbox": [],
  "geometry": {"coordinates":[5.683333,51.15],"type":"Point"}
}
=======
{"geometry":{"type":"Point","coordinates":[5.683333,51.150000]},"type":"Feature","properties":{"hierarchy":["tgn:7244195","tgn:7003461","tgn:1000003","tgn:1000063","tgn:7018236","tgn:7029392"],"placetype":["aat:300008699"],"id":7244195,"name:xx":"Kanjelstraatbeek"}}
>>>>>>> 03f74aca74312dbeaf24d7e61306dd6a786dc3d0
