{
  "id": 7481826,
  "type": "Feature",
  "properties": {
    "tgn:hierarchy":[
        "tgn:7481826",
        "tgn:1000004",
        "tgn:7490934",
        "tgn:1000141",
        "tgn:7029392"
    ],
    "tgn:id":7481826,
    "tgn:name":"Jishui Xikou",
    "tgn:placetype":[
        "aat:300387057"
    ]
},
  "bbox": [],
  "geometry": {"coordinates":[120.102778,23.298418],"type":"Point"}
}