<<<<<<< HEAD
{
  "id": 7481826,
  "type": "Feature",
  "properties": {
    "tgn:hierarchy":[
        "tgn:7481826",
        "tgn:1000004",
        "tgn:7490934",
        "tgn:1000141",
        "tgn:7029392"
    ],
    "tgn:id":7481826,
    "tgn:name":"Jishui Xikou",
    "tgn:placetype":[
        "aat:300387057"
    ]
},
  "bbox": [],
  "geometry": {"coordinates":[120.102778,23.298418],"type":"Point"}
}
=======
{"geometry":{"type":"Point","coordinates":[120.102778,23.298418]},"type":"Feature","properties":{"hierarchy":["tgn:7481826","tgn:1000004","tgn:7490934","tgn:1000141","tgn:7029392"],"placetype":["aat:300387057"],"id":7481826,"name:xx":"Jishui Xikou"}}
>>>>>>> 03f74aca74312dbeaf24d7e61306dd6a786dc3d0
