{
  "id": 1110474,
  "type": "Feature",
  "properties": {
    "tgn:hierarchy":[
        "tgn:1110474",
        "tgn:1000611",
        "tgn:1000002",
        "tgn:1000058",
        "tgn:7029392"
    ],
    "tgn:id":1110474,
    "tgn:name":"Cuchilla Grande Inferior",
    "tgn:placetype":[
        "aat:300008777",
        "aat:300266640"
    ]
},
  "bbox": [],
  "geometry": {"coordinates":[-56.166,-33.8333],"type":"Point"}
}