{
  "id": 1082663,
  "type": "Feature",
  "properties": {
    "tgn:hierarchy":[
        "tgn:1082663",
        "tgn:7000317",
        "tgn:1001899",
        "tgn:1000004",
        "tgn:1000128",
        "tgn:7029392"
    ],
    "tgn:id":1082663,
    "tgn:name":"Alor Gajah",
    "tgn:placetype":[
        "aat:300008347"
    ]
},
  "bbox": [],
  "geometry": {"coordinates":[102.2167,2.3833],"type":"Point"}
}