{
  "id": 7226011,
  "type": "Feature",
  "properties": {
    "tgn:hierarchy":[
        "tgn:7226011",
        "tgn:7011170",
        "tgn:7002715",
        "tgn:1000003",
        "tgn:1000074",
        "tgn:7029392"
    ],
    "tgn:id":7226011,
    "tgn:name":"Mousth\u00e9ni",
    "tgn:placetype":[
        "aat:300008347"
    ]
},
  "bbox": [],
  "geometry": {"coordinates":[24.116667,40.866667],"type":"Point"}
}