{
  "id": 2075628,
  "type": "Feature",
  "properties": {
    "tgn:hierarchy":[
        "tgn:2075628",
        "tgn:1000001",
        "tgn:7012149",
        "tgn:2001523",
        "tgn:7007709",
        "tgn:7029392"
    ],
    "tgn:id":2075628,
    "tgn:name":"Masonboro",
    "tgn:placetype":[
        "aat:300008347"
    ]
},
  "bbox": [],
  "geometry": {"coordinates":[-77.8333,34.1667],"type":"Point"}
}