{
  "id": 7308940,
  "type": "Feature",
  "properties": {
    "tgn:hierarchy":[
        "tgn:7308940",
        "tgn:1001657",
        "tgn:1000049",
        "tgn:1000002",
        "tgn:7029392"
    ],
    "tgn:id":7308940,
    "tgn:name":"Madrid, Morro",
    "tgn:placetype":[
        "aat:300008795"
    ]
},
  "bbox": [],
  "geometry": {"coordinates":[-71.35,-31.716667],"type":"Point"}
}