{
  "id": 2204000,
  "type": "Feature",
  "properties": {
    "tgn:hierarchy":[
        "tgn:2204000",
        "tgn:1000001",
        "tgn:7012149",
        "tgn:7007157",
        "tgn:2000185",
        "tgn:7029392"
    ],
    "tgn:id":2204000,
    "tgn:name":"Bud Creek",
    "tgn:placetype":[
        "aat:300008706"
    ]
},
  "bbox": [],
  "geometry": {"coordinates":[-123.35,39.5167],"type":"Point"}
}