{
  "id": 2665494,
  "type": "Feature",
  "properties": {
    "tgn:hierarchy":[
        "tgn:2665494",
        "tgn:1000001",
        "tgn:7012149",
        "tgn:2000472",
        "tgn:7007250",
        "tgn:7029392"
    ],
    "tgn:id":2665494,
    "tgn:name":"Sink Spring",
    "tgn:placetype":[
        "aat:300008697"
    ]
},
  "bbox": [],
  "geometry": {"coordinates":[-111.6667,42.3167],"type":"Point"}
}