{
  "id": 2515345,
  "type": "Feature",
  "properties": {
    "tgn:hierarchy":[
        "tgn:2515345",
        "tgn:1000001",
        "tgn:7012149",
        "tgn:1002555",
        "tgn:7007523",
        "tgn:7029392"
    ],
    "tgn:id":2515345,
    "tgn:name":"Million Creek",
    "tgn:placetype":[
        "aat:300008706"
    ]
},
  "bbox": [],
  "geometry": {"coordinates":[-92.0167,40.05],"type":"Point"}
}