{
  "id": 7577458,
  "type": "Feature",
  "properties": {
    "tgn:hierarchy":[
        "tgn:7577458",
        "tgn:1000004",
        "tgn:7000198",
        "tgn:1001895",
        "tgn:7029392"
    ],
    "tgn:id":7577458,
    "tgn:name:en":"Kherv\u0101di",
    "tgn:placetype":[
        "aat:300008347"
    ]
},
  "bbox": [],
  "geometry": {"coordinates":[73.966667,20.05],"type":"Point"}
}