{
  "id": 7492573,
  "type": "Feature",
  "properties": {
    "tgn:hierarchy":[
        "tgn:7492573",
        "tgn:1000004",
        "tgn:7001009",
        "tgn:1000141",
        "tgn:7029392"
    ],
    "tgn:id":7492573,
    "tgn:name":"Tanzi",
    "tgn:placetype":[
        "aat:300008347"
    ]
},
  "bbox": [],
  "geometry": {"coordinates":[120.706741,24.214366],"type":"Point"}
}