{
  "id": 1008189,
  "type": "Feature",
  "properties": {
    "tgn:hierarchy":[
        "tgn:1008189",
        "tgn:1000003",
        "tgn:7017304",
        "tgn:7006663",
        "tgn:7029392"
    ],
    "tgn:id":1008189,
    "tgn:name":"Molat",
    "tgn:placetype":[
        "aat:300008791"
    ]
},
  "bbox": [],
  "geometry": {"coordinates":[14.8333,44.2167],"type":"Point"}
}