{
  "id": 1017357,
  "type": "Feature",
  "properties": {
    "tgn:hierarchy":[
        "tgn:1017357",
        "tgn:1001853",
        "tgn:1000001",
        "tgn:7005560",
        "tgn:7029392"
    ],
    "tgn:id":1017357,
    "tgn:name":"Dolores",
    "tgn:placetype":[
        "aat:300008347"
    ]
},
  "bbox": [],
  "geometry": {"coordinates":[-101.483333,26.333333],"type":"Point"}
}