<<<<<<< HEAD
{
  "id": 2333031,
  "type": "Feature",
  "properties": {
    "tgn:hierarchy":[
        "tgn:2333031",
        "tgn:1000001",
        "tgn:7012149",
        "tgn:1002629",
        "tgn:7007523",
        "tgn:7029392"
    ],
    "tgn:id":2333031,
    "tgn:name":"Fly Creek",
    "tgn:placetype":[
        "aat:300008706"
    ]
},
  "bbox": [],
  "geometry": {"coordinates":[-92.0167,38.1],"type":"Point"}
}
=======
{"geometry":{"type":"Point","coordinates":[-92.016700,38.100000]},"type":"Feature","properties":{"hierarchy":["tgn:2333031","tgn:1000001","tgn:7012149","tgn:1002629","tgn:7007523","tgn:7029392"],"placetype":["aat:300008706"],"id":2333031,"name:xx":"Fly Creek"}}
>>>>>>> 03f74aca74312dbeaf24d7e61306dd6a786dc3d0
