<<<<<<< HEAD
{
  "id": 7357807,
  "type": "Feature",
  "properties": {
    "tgn:hierarchy":[
        "tgn:7357807",
        "tgn:1000001",
        "tgn:7005590",
        "tgn:7005560",
        "tgn:7029392"
    ],
    "tgn:id":7357807,
    "tgn:name":"Cupuyo",
    "tgn:placetype":[
        "aat:300008347"
    ]
},
  "bbox": [],
  "geometry": {"coordinates":[-100.933333,19.533333],"type":"Point"}
}
=======
{"geometry":{"type":"Point","coordinates":[-100.933333,19.533333]},"type":"Feature","properties":{"hierarchy":["tgn:7357807","tgn:1000001","tgn:7005590","tgn:7005560","tgn:7029392"],"placetype":["aat:300008347"],"id":7357807,"name:xx":"Cupuyo"}}
>>>>>>> 03f74aca74312dbeaf24d7e61306dd6a786dc3d0
