{
  "id": 2489834,
  "type": "Feature",
  "properties": {
    "tgn:hierarchy":[
        "tgn:2489834",
        "tgn:1000001",
        "tgn:7006451",
        "tgn:7012149",
        "tgn:2000099",
        "tgn:7029392"
    ],
    "tgn:id":2489834,
    "tgn:name":"Malpais Mesa",
    "tgn:placetype":[
        "aat:300008798"
    ]
},
  "bbox": [],
  "geometry": {"coordinates":[-110.1333,35.3333],"type":"Point"}
}