{
  "id": 2313786,
  "type": "Feature",
  "properties": {
    "tgn:hierarchy":[
        "tgn:2313786",
        "tgn:1000001",
        "tgn:2001411",
        "tgn:7012149",
        "tgn:7007526",
        "tgn:7029392"
    ],
    "tgn:id":2313786,
    "tgn:name":"Elevenmile Hill",
    "tgn:placetype":[
        "aat:300008798"
    ]
},
  "bbox": [],
  "geometry": {"coordinates":[-116.8833,41.5333],"type":"Point"}
}