{
  "id": 7175254,
  "type": "Feature",
  "properties": {
    "tgn:hierarchy":[
        "tgn:7175254",
        "tgn:1000003",
        "tgn:7003685",
        "tgn:7000084",
        "tgn:7029392"
    ],
    "tgn:id":7175254,
    "tgn:name":"Gro\u00dfer Casimir-Teich",
    "tgn:placetype":[
        "aat:300008688"
    ]
},
  "bbox": [],
  "geometry": {"coordinates":[14.316667,51.333333],"type":"Point"}
}