{
  "id": 7256279,
  "type": "Feature",
  "properties": {
    "tgn:concordances":{
        "gn:id":"2759771"
    },
    "tgn:hierarchy":[
        "tgn:7256279",
        "tgn:1000003",
        "tgn:7003626",
        "tgn:7016845",
        "tgn:7029392"
    ],
    "tgn:id":7256279,
    "tgn:name:nl":"Anerveen",
    "tgn:placetype":[
        "aat:300008347"
    ]
},
  "bbox": [],
  "geometry": {"coordinates":[6.666667,52.633333],"type":"Point"}
}