{
  "id": 1106644,
  "type": "Feature",
  "properties": {
    "tgn:hierarchy":[
        "tgn:1106644",
        "tgn:7016675",
        "tgn:1000004",
        "tgn:7000896",
        "tgn:1000120",
        "tgn:7029392"
    ],
    "tgn:id":1106644,
    "tgn:name":"Taishaku-zan",
    "tgn:placetype":[
        "aat:300008795"
    ]
},
  "bbox": [],
  "geometry": {"coordinates":[135.1167,34.7833],"type":"Point"}
}