{
  "id": 7590449,
  "type": "Feature",
  "properties": {
    "tgn:hierarchy":[
        "tgn:7590449",
        "tgn:1000004",
        "tgn:7000198",
        "tgn:7000799",
        "tgn:7029392"
    ],
    "tgn:id":7590449,
    "tgn:name:en":"Drohi N\u0101r",
    "tgn:placetype":[
        "aat:300008699"
    ]
},
  "bbox": [],
  "geometry": {"coordinates":[73.856315,34.370206],"type":"Point"}
}