{
  "id": 1016431,
  "type": "Feature",
  "properties": {
    "tgn:hierarchy":[
        "tgn:1016431",
        "tgn:1001521",
        "tgn:1000001",
        "tgn:7004624",
        "tgn:7029392"
    ],
    "tgn:id":1016431,
    "tgn:name":"Sancti-Sp\u00edritus",
    "tgn:placetype":[
        "aat:300008347",
        "aat:300008389",
        "aat:300387512",
        "aat:300387223"
    ]
},
  "bbox": [],
  "geometry": {"coordinates":[-79.4667,21.9167],"type":"Point"}
}