<<<<<<< HEAD
{
  "id": 2338257,
  "type": "Feature",
  "properties": {
    "tgn:hierarchy":[
        "tgn:2338257",
        "tgn:1000001",
        "tgn:7012149",
        "tgn:1003047",
        "tgn:7007710",
        "tgn:7029392"
    ],
    "tgn:id":2338257,
    "tgn:name":"Fox Run",
    "tgn:placetype":[
        "aat:300008699"
    ]
},
  "bbox": [],
  "geometry": {"coordinates":[-76.85,40.0333],"type":"Point"}
}
=======
{"geometry":{"type":"Point","coordinates":[-76.850000,40.033300]},"type":"Feature","properties":{"hierarchy":["tgn:2338257","tgn:1000001","tgn:7012149","tgn:1003047","tgn:7007710","tgn:7029392"],"placetype":["aat:300008699"],"id":2338257,"name:xx":"Fox Run"}}
>>>>>>> 03f74aca74312dbeaf24d7e61306dd6a786dc3d0
