{
  "id": 7325047,
  "type": "Feature",
  "properties": {
    "tgn:hierarchy":[
        "tgn:7325047",
        "tgn:7001158",
        "tgn:7002850",
        "tgn:1000003",
        "tgn:1000095",
        "tgn:7029392"
    ],
    "tgn:id":7325047,
    "tgn:name":"San Mart\u00edn de T\u00e1bara",
    "tgn:placetype":[
        "aat:300008347"
    ]
},
  "bbox": [],
  "geometry": {"coordinates":[-5.983333,41.75],"type":"Point"}
}