{
  "id": 2736248,
  "type": "Feature",
  "properties": {
    "tgn:hierarchy":[
        "tgn:2736248",
        "tgn:1000001",
        "tgn:7006451",
        "tgn:7012149",
        "tgn:2000099",
        "tgn:7029392"
    ],
    "tgn:id":2736248,
    "tgn:name":"Twin Oak Canyon",
    "tgn:placetype":[
        "aat:300008761"
    ]
},
  "bbox": [],
  "geometry": {"coordinates":[-110.3667,34.1667],"type":"Point"}
}