{
  "id": 7589589,
  "type": "Feature",
  "properties": {
    "tgn:hierarchy":[
        "tgn:7589589",
        "tgn:1000004",
        "tgn:7000198",
        "tgn:7000799",
        "tgn:7029392"
    ],
    "tgn:id":7589589,
    "tgn:name:en":"Neril",
    "tgn:placetype":[
        "aat:300008347"
    ]
},
  "bbox": [],
  "geometry": {"coordinates":[76.013889,34.666667],"type":"Point"}
}