{
  "id": 2061296,
  "type": "Feature",
  "properties": {
    "tgn:hierarchy":[
        "tgn:2061296",
        "tgn:1000001",
        "tgn:7012149",
        "tgn:2001301",
        "tgn:7007524",
        "tgn:7029392"
    ],
    "tgn:id":2061296,
    "tgn:name":"Fairview",
    "tgn:placetype":[
        "aat:300008347"
    ]
},
  "bbox": [],
  "geometry": {"coordinates":[-104.0333,47.85],"type":"Point"}
}