<<<<<<< HEAD
{
  "id": 7116811,
  "type": "Feature",
  "properties": {
    "tgn:hierarchy":[
        "tgn:7116811",
        "tgn:7003669",
        "tgn:1000003",
        "tgn:7000084",
        "tgn:7029392"
    ],
    "tgn:id":7116811,
    "tgn:name":"Ottenstall",
    "tgn:placetype":[
        "aat:300008347"
    ]
},
  "bbox": [],
  "geometry": {"coordinates":[10.183333,47.8],"type":"Point"}
}
=======
{"geometry":{"type":"Point","coordinates":[10.183333,47.800000]},"type":"Feature","properties":{"hierarchy":["tgn:7116811","tgn:7003669","tgn:1000003","tgn:7000084","tgn:7029392"],"placetype":["aat:300008347"],"id":7116811,"name:xx":"Ottenstall"}}
>>>>>>> 03f74aca74312dbeaf24d7e61306dd6a786dc3d0
