{
  "id": 7261645,
  "type": "Feature",
  "properties": {
    "tgn:concordances":{
        "gn:id":"2755027"
    },
    "tgn:hierarchy":[
        "tgn:7261645",
        "tgn:7003614",
        "tgn:1000003",
        "tgn:7016845",
        "tgn:7029392"
    ],
    "tgn:id":7261645,
    "tgn:name:nl":"Haakswold",
    "tgn:placetype":[
        "aat:300008347"
    ]
},
  "bbox": [],
  "geometry": {"coordinates":[6.25,52.716667],"type":"Point"}
}