{
  "id": 7315801,
  "type": "Feature",
  "properties": {
    "tgn:hierarchy":[
        "tgn:7315801",
        "tgn:7016598",
        "tgn:1000049",
        "tgn:1000002",
        "tgn:7029392"
    ],
    "tgn:id":7315801,
    "tgn:name":"Estaci\u00f3n Central",
    "tgn:placetype":[
        "aat:300007783"
    ]
},
  "bbox": [],
  "geometry": {"coordinates":[-69.55,-23.116667],"type":"Point"}
}