{
  "id": 2125872,
  "type": "Feature",
  "properties": {
    "tgn:hierarchy":[
        "tgn:2125872",
        "tgn:1000001",
        "tgn:7012149",
        "tgn:2000388",
        "tgn:7007248",
        "tgn:7029392"
    ],
    "tgn:id":2125872,
    "tgn:name":"Adams Lake",
    "tgn:placetype":[
        "aat:300006191"
    ]
},
  "bbox": [],
  "geometry": {"coordinates":[-83.2833,34.1667],"type":"Point"}
}