{
  "id": 2122720,
  "type": "Feature",
  "properties": {
    "tgn:hierarchy":[
        "tgn:2122720",
        "tgn:1000001",
        "tgn:1002316",
        "tgn:7012149",
        "tgn:7007922",
        "tgn:7029392"
    ],
    "tgn:id":2122720,
    "tgn:name":"Windsor",
    "tgn:placetype":[
        "aat:300008347"
    ]
},
  "bbox": [],
  "geometry": {"coordinates":[-89.3333,43.2167],"type":"Point"}
}