<<<<<<< HEAD
{
  "id": 2253145,
  "type": "Feature",
  "properties": {
    "tgn:hierarchy":[
        "tgn:2253145",
        "tgn:1000001",
        "tgn:7006451",
        "tgn:2000091",
        "tgn:7012149",
        "tgn:7029392"
    ],
    "tgn:id":2253145,
    "tgn:name":"Contention",
    "tgn:placetype":[
        "aat:300008347"
    ]
},
  "bbox": [],
  "geometry": {"coordinates":[-110.2,31.7667],"type":"Point"}
}
=======
{"geometry":{"type":"Point","coordinates":[-110.200000,31.766700]},"type":"Feature","properties":{"hierarchy":["tgn:2253145","tgn:1000001","tgn:7006451","tgn:2000091","tgn:7012149","tgn:7029392"],"placetype":["aat:300008347"],"id":2253145,"name:xx":"Contention"}}
>>>>>>> 03f74aca74312dbeaf24d7e61306dd6a786dc3d0
