{
  "id": 7576652,
  "type": "Feature",
  "properties": {
    "tgn:hierarchy":[
        "tgn:7576652",
        "tgn:1000004",
        "tgn:7000198",
        "tgn:1001894",
        "tgn:7029392"
    ],
    "tgn:id":7576652,
    "tgn:name:en":"Kothia",
    "tgn:placetype":[
        "aat:300008347"
    ]
},
  "bbox": [],
  "geometry": {"coordinates":[77.4811,24.627162],"type":"Point"}
}