<<<<<<< HEAD
{
  "id": 7022967,
  "type": "Feature",
  "properties": {
    "tgn:hierarchy":[
        "tgn:7022967",
        "tgn:1000001",
        "tgn:7012149",
        "tgn:1002751",
        "tgn:7007568",
        "tgn:7029392"
    ],
    "tgn:id":7022967,
    "tgn:name":"Fort Montgomery",
    "tgn:placetype":[
        "aat:300008347"
    ]
},
  "bbox": [],
  "geometry": {"coordinates":[-73.9833,41.3167],"type":"Point"}
}
=======
{"geometry":{"type":"Point","coordinates":[-73.983300,41.316700]},"type":"Feature","properties":{"hierarchy":["tgn:7022967","tgn:1000001","tgn:7012149","tgn:1002751","tgn:7007568","tgn:7029392"],"placetype":["aat:300008347"],"id":7022967,"name:xx":"Fort Montgomery"}}
>>>>>>> 03f74aca74312dbeaf24d7e61306dd6a786dc3d0
