{
  "id": 2485245,
  "type": "Feature",
  "properties": {
    "tgn:hierarchy":[
        "tgn:2485245",
        "tgn:1000001",
        "tgn:7012149",
        "tgn:7007254",
        "tgn:7029392"
    ],
    "tgn:id":2485245,
    "tgn:name":"Lawrence Creek",
    "tgn:placetype":[
        "aat:300008706"
    ]
},
  "bbox": [],
  "geometry": {"coordinates":[-98.8667,39.5333],"type":"Point"}
}