{
  "id": 7493190,
  "type": "Feature",
  "properties": {
    "tgn:hierarchy":[
        "tgn:7493190",
        "tgn:7468018",
        "tgn:1000004",
        "tgn:1000141",
        "tgn:7029392"
    ],
    "tgn:id":7493190,
    "tgn:name":"Zaozhi Xi",
    "tgn:placetype":[
        "aat:300008699"
    ]
},
  "bbox": [],
  "geometry": {"coordinates":[120.430614,23.617975],"type":"Point"}
}