{
  "id": 1058325,
  "type": "Feature",
  "properties": {
    "tgn:hierarchy":[
        "tgn:1058325",
        "tgn:1000004",
        "tgn:1003363",
        "tgn:7014786",
        "tgn:7029392"
    ],
    "tgn:id":1058325,
    "tgn:name":"Pervaja Maja",
    "tgn:placetype":[
        "aat:300008347"
    ]
},
  "bbox": [],
  "geometry": {"coordinates":[67.4167,48.9167],"type":"Point"}
}