{
  "id": 7498795,
  "type": "Feature",
  "properties": {
    "tgn:hierarchy":[
        "tgn:7498795",
        "tgn:1000004",
        "tgn:1000454",
        "tgn:1000141",
        "tgn:7029392"
    ],
    "tgn:id":7498795,
    "tgn:name":"Neigouwei",
    "tgn:placetype":[
        "aat:300008347"
    ]
},
  "bbox": [],
  "geometry": {"coordinates":[121.618161,25.095086],"type":"Point"}
}