{
  "id": 1114887,
  "type": "Feature",
  "properties": {
    "tgn:hierarchy":[
        "tgn:1114887",
        "tgn:1000225",
        "tgn:1000006",
        "tgn:7029392"
    ],
    "tgn:id":1114887,
    "tgn:name":"Lolvavana, Passage",
    "tgn:placetype":[
        "aat:300387217"
    ]
},
  "bbox": [],
  "geometry": {"coordinates":[168.1667,-15.4167],"type":"Point"}
}