{
  "id": 2298873,
  "type": "Feature",
  "properties": {
    "tgn:hierarchy":[
        "tgn:2298873",
        "tgn:1000001",
        "tgn:7012149",
        "tgn:7013941",
        "tgn:7007568",
        "tgn:7029392"
    ],
    "tgn:id":2298873,
    "tgn:name":"Duane Stream",
    "tgn:placetype":[
        "aat:300008699"
    ]
},
  "bbox": [],
  "geometry": {"coordinates":[-74.2333,44.6667],"type":"Point"}
}