<<<<<<< HEAD
{
  "id": 2409434,
  "type": "Feature",
  "properties": {
    "tgn:hierarchy":[
        "tgn:2409434",
        "tgn:1000001",
        "tgn:7012149",
        "tgn:2001717",
        "tgn:7007708",
        "tgn:7029392"
    ],
    "tgn:id":2409434,
    "tgn:name":"Idanha Log Pond",
    "tgn:placetype":[
        "aat:300006191"
    ]
},
  "bbox": [],
  "geometry": {"coordinates":[-122.0667,44.7],"type":"Point"}
}
=======
{"geometry":{"type":"Point","coordinates":[-122.066700,44.700000]},"type":"Feature","properties":{"hierarchy":["tgn:2409434","tgn:1000001","tgn:7012149","tgn:2001717","tgn:7007708","tgn:7029392"],"placetype":["aat:300006191"],"id":2409434,"name:xx":"Idanha Log Pond"}}
>>>>>>> 03f74aca74312dbeaf24d7e61306dd6a786dc3d0
