{
  "id": 2637829,
  "type": "Feature",
  "properties": {
    "tgn:hierarchy":[
        "tgn:2637829",
        "tgn:7006450",
        "tgn:1000001",
        "tgn:2124077",
        "tgn:7012149",
        "tgn:7029392"
    ],
    "tgn:id":2637829,
    "tgn:name":"Saksaia Glacier",
    "tgn:placetype":[
        "aat:300008835"
    ]
},
  "bbox": [],
  "geometry": {"coordinates":[-136.3833,59.3667],"type":"Point"}
}