{
  "id": 7334824,
  "type": "Feature",
  "properties": {
    "tgn:hierarchy":[
        "tgn:7334824",
        "tgn:7002829",
        "tgn:1000003",
        "tgn:7002786",
        "tgn:1000095",
        "tgn:7029392"
    ],
    "tgn:id":7334824,
    "tgn:name":"Gra\u00f1a",
    "tgn:placetype":[
        "aat:300008347"
    ]
},
  "bbox": [],
  "geometry": {"coordinates":[-7.483333,43.283333],"type":"Point"}
}