{
  "id": 2237756,
  "type": "Feature",
  "properties": {
    "tgn:hierarchy":[
        "tgn:2237756",
        "tgn:1000001",
        "tgn:7012149",
        "tgn:2001145",
        "tgn:7007522",
        "tgn:7029392"
    ],
    "tgn:id":2237756,
    "tgn:name":"Chinquapin Brake",
    "tgn:placetype":[
        "aat:300008905"
    ]
},
  "bbox": [],
  "geometry": {"coordinates":[-90.2333,34.3667],"type":"Point"}
}