<<<<<<< HEAD
{
  "id": 7488951,
  "type": "Feature",
  "properties": {
    "tgn:hierarchy":[
        "tgn:7488951",
        "tgn:1000004",
        "tgn:7491221",
        "tgn:1000141",
        "tgn:7029392"
    ],
    "tgn:id":7488951,
    "tgn:name":"Gongguan",
    "tgn:placetype":[
        "aat:300008347"
    ]
},
  "bbox": [],
  "geometry": {"coordinates":[121.491111,22.675],"type":"Point"}
}
=======
{"geometry":{"type":"Point","coordinates":[121.491111,22.675000]},"type":"Feature","properties":{"hierarchy":["tgn:7488951","tgn:1000004","tgn:7491221","tgn:1000141","tgn:7029392"],"placetype":["aat:300008347"],"id":7488951,"name:xx":"Gongguan"}}
>>>>>>> 03f74aca74312dbeaf24d7e61306dd6a786dc3d0
