{
  "id": 7488951,
  "type": "Feature",
  "properties": {
    "tgn:hierarchy":[
        "tgn:7488951",
        "tgn:1000004",
        "tgn:7491221",
        "tgn:1000141",
        "tgn:7029392"
    ],
    "tgn:id":7488951,
    "tgn:name":"Gongguan",
    "tgn:placetype":[
        "aat:300008347"
    ]
},
  "bbox": [],
  "geometry": {"coordinates":[121.491111,22.675],"type":"Point"}
}