<<<<<<< HEAD
{
  "id": 7173242,
  "type": "Feature",
  "properties": {
    "tgn:hierarchy":[
        "tgn:7173242",
        "tgn:1000003",
        "tgn:7003677",
        "tgn:7000084",
        "tgn:7029392"
    ],
    "tgn:id":7173242,
    "tgn:name":"Gro\u00dfer Storchschnabel",
    "tgn:placetype":[
        "aat:300008777"
    ]
},
  "bbox": [],
  "geometry": {"coordinates":[8.45,51.416667],"type":"Point"}
}
=======
{"geometry":{"type":"Point","coordinates":[8.450000,51.416667]},"type":"Feature","properties":{"hierarchy":["tgn:7173242","tgn:1000003","tgn:7003677","tgn:7000084","tgn:7029392"],"placetype":["aat:300008777"],"id":7173242,"name:xx":"Gro\u00dfer Storchschnabel"}}
>>>>>>> 03f74aca74312dbeaf24d7e61306dd6a786dc3d0
