{
  "id": 1096206,
  "type": "Feature",
  "properties": {
    "tgn:hierarchy":[
        "tgn:1096206",
        "tgn:7000490",
        "tgn:1000006",
        "tgn:7001828",
        "tgn:7029392"
    ],
    "tgn:id":1096206,
    "tgn:name":"Batlow",
    "tgn:placetype":[
        "aat:300008347"
    ]
},
  "bbox": [],
  "geometry": {"coordinates":[148.1667,-35.5333],"type":"Point"}
}