{
  "id": 7394135,
  "type": "Feature",
  "properties": {
    "tgn:hierarchy":[
        "tgn:7394135",
        "tgn:1000001",
        "tgn:7005589",
        "tgn:7005560",
        "tgn:7029392"
    ],
    "tgn:id":7394135,
    "tgn:name":"San Jos\u00e9, Ca\u00f1\u00f3n de",
    "tgn:placetype":[
        "aat:300008763"
    ]
},
  "bbox": [],
  "geometry": {"coordinates":[-99.871389,24.344444],"type":"Point"}
}