{
  "id": 2163103,
  "type": "Feature",
  "properties": {
    "tgn:hierarchy":[
        "tgn:2163103",
        "tgn:1000001",
        "tgn:2002255",
        "tgn:7012149",
        "tgn:7013961",
        "tgn:7029392"
    ],
    "tgn:id":2163103,
    "tgn:name":"Bennett Fork",
    "tgn:placetype":[
        "aat:300008699"
    ]
},
  "bbox": [],
  "geometry": {"coordinates":[-81.75,38.0333],"type":"Point"}
}