{
  "id": 7264286,
  "type": "Feature",
  "properties": {
    "tgn:hierarchy":[
        "tgn:7264286",
        "tgn:7003619",
        "tgn:1000003",
        "tgn:7016845",
        "tgn:7029392"
    ],
    "tgn:id":7264286,
    "tgn:name:nl":"Kattenbeek",
    "tgn:placetype":[
        "aat:300008699"
    ]
},
  "bbox": [],
  "geometry": {"coordinates":[6.483333,52.133333],"type":"Point"}
}