{
  "id": 2190503,
  "type": "Feature",
  "properties": {
    "tgn:hierarchy":[
        "tgn:2190503",
        "tgn:1000001",
        "tgn:7012149",
        "tgn:2000226",
        "tgn:7007158",
        "tgn:7029392"
    ],
    "tgn:id":2190503,
    "tgn:name":"Box Elder Reservoir Number 2",
    "tgn:placetype":[
        "aat:300006191"
    ]
},
  "bbox": [],
  "geometry": {"coordinates":[-105.05,40.7667],"type":"Point"}
}