<<<<<<< HEAD
{
  "id": 2400300,
  "type": "Feature",
  "properties": {
    "tgn:hierarchy":[
        "tgn:2400300",
        "tgn:1000001",
        "tgn:7012149",
        "tgn:2000476",
        "tgn:7007250",
        "tgn:7029392"
    ],
    "tgn:id":2400300,
    "tgn:name":"Horse Flat Creek",
    "tgn:placetype":[
        "aat:300008706"
    ]
},
  "bbox": [],
  "geometry": {"coordinates":[-115.4667,45.6],"type":"Point"}
}
=======
{"geometry":{"type":"Point","coordinates":[-115.466700,45.600000]},"type":"Feature","properties":{"hierarchy":["tgn:2400300","tgn:1000001","tgn:7012149","tgn:2000476","tgn:7007250","tgn:7029392"],"placetype":["aat:300008706"],"id":2400300,"name:xx":"Horse Flat Creek"}}
>>>>>>> 03f74aca74312dbeaf24d7e61306dd6a786dc3d0
