{
  "id": 7524500,
  "type": "Feature",
  "properties": {
    "tgn:hierarchy":[
        "tgn:7524500",
        "tgn:7001242",
        "tgn:7016833",
        "tgn:1001418",
        "tgn:7029392"
    ],
    "tgn:id":7524500,
    "tgn:name:en":"Al Washkah",
    "tgn:placetype":[
        "aat:300387200"
    ]
},
  "bbox": [],
  "geometry": {"coordinates":[24.952673,30.517119],"type":"Point"}
}