{
  "id": 2721632,
  "type": "Feature",
  "properties": {
    "tgn:hierarchy":[
        "tgn:2721632",
        "tgn:1000001",
        "tgn:1002261",
        "tgn:7012149",
        "tgn:7007568",
        "tgn:7029392"
    ],
    "tgn:id":2721632,
    "tgn:name":"Tilman Hill",
    "tgn:placetype":[
        "aat:300008798"
    ]
},
  "bbox": [],
  "geometry": {"coordinates":[-76.5833,42.0333],"type":"Point"}
}