{
  "id": 7254105,
  "type": "Feature",
  "properties": {
    "tgn:hierarchy":[
        "tgn:7254105",
        "tgn:7003466",
        "tgn:1000003",
        "tgn:1000063",
        "tgn:4012014",
        "tgn:7029392"
    ],
    "tgn:id":7254105,
    "tgn:name":"Vaux",
    "tgn:placetype":[
        "aat:300008699"
    ]
},
  "bbox": [],
  "geometry": {"coordinates":[4.433333,50.166667],"type":"Point"}
}