{
  "id": 7456600,
  "type": "Feature",
  "properties": {
    "tgn:hierarchy":[
        "tgn:7456600",
        "tgn:7002445",
        "tgn:7008116",
        "tgn:1000003",
        "tgn:7008591",
        "tgn:7029392"
    ],
    "tgn:id":7456600,
    "tgn:name:en":"Mawgan Porth",
    "tgn:placetype":[
        "aat:300132316"
    ]
},
  "bbox": [],
  "geometry": {"coordinates":[-5.033333,50.466667],"type":"Point"}
}