{
  "id": 7236403,
  "type": "Feature",
  "properties": {
    "tgn:hierarchy":[
        "tgn:7236403",
        "tgn:7002680",
        "tgn:7001395",
        "tgn:1000003",
        "tgn:1000074",
        "tgn:7029392"
    ],
    "tgn:id":7236403,
    "tgn:name":"Episkop\u00ed",
    "tgn:placetype":[
        "aat:300008347"
    ]
},
  "bbox": [],
  "geometry": {"coordinates":[20.933333,38.65],"type":"Point"}
}