{
  "id": 2759003,
  "type": "Feature",
  "properties": {
    "tgn:hierarchy":[
        "tgn:2759003",
        "tgn:1000001",
        "tgn:7012149",
        "tgn:2001722",
        "tgn:7007708",
        "tgn:7029392"
    ],
    "tgn:id":2759003,
    "tgn:name":"West Fork Basin Creek",
    "tgn:placetype":[
        "aat:300008706"
    ]
},
  "bbox": [],
  "geometry": {"coordinates":[-117.05,45.8833],"type":"Point"}
}