<<<<<<< HEAD
{
  "id": 2153241,
  "type": "Feature",
  "properties": {
    "tgn:hierarchy":[
        "tgn:2153241",
        "tgn:7002659",
        "tgn:1000001",
        "tgn:2000010",
        "tgn:7012149",
        "tgn:7029392"
    ],
    "tgn:id":2153241,
    "tgn:name":"Beam Branch",
    "tgn:placetype":[
        "aat:300008699"
    ]
},
  "bbox": [],
  "geometry": {"coordinates":[-86.8167,33.0],"type":"Point"}
}
=======
{"geometry":{"type":"Point","coordinates":[-86.816700,33.000000]},"type":"Feature","properties":{"hierarchy":["tgn:2153241","tgn:7002659","tgn:1000001","tgn:2000010","tgn:7012149","tgn:7029392"],"placetype":["aat:300008699"],"id":2153241,"name:xx":"Beam Branch"}}
>>>>>>> 03f74aca74312dbeaf24d7e61306dd6a786dc3d0
