{
  "id": 7580120,
  "type": "Feature",
  "properties": {
    "tgn:hierarchy":[
        "tgn:7580120",
        "tgn:1000004",
        "tgn:1001869",
        "tgn:7000198",
        "tgn:7029392"
    ],
    "tgn:id":7580120,
    "tgn:name:en":"Utr\u0101n",
    "tgn:placetype":[
        "aat:300007783"
    ]
},
  "bbox": [],
  "geometry": {"coordinates":[72.866667,21.25],"type":"Point"}
}