{
  "id": 2357740,
  "type": "Feature",
  "properties": {
    "tgn:hierarchy":[
        "tgn:2357740",
        "tgn:2000765",
        "tgn:1000001",
        "tgn:7012149",
        "tgn:7007255",
        "tgn:7029392"
    ],
    "tgn:id":2357740,
    "tgn:name":"Grace Ridge",
    "tgn:placetype":[
        "aat:300266640"
    ]
},
  "bbox": [],
  "geometry": {"coordinates":[-85.1333,37.2167],"type":"Point"}
}