{
  "id": 1126420,
  "type": "Feature",
  "properties": {
    "tgn:hierarchy":[
        "tgn:1126420",
        "tgn:7001242",
        "tgn:1000149",
        "tgn:7029392"
    ],
    "tgn:id":1126420,
    "tgn:name":"Luando",
    "tgn:placetype":[
        "aat:300008707"
    ]
},
  "bbox": [],
  "geometry": {"coordinates":[16.446,-10.347],"type":"Point"}
}