{
  "id": 2528712,
  "type": "Feature",
  "properties": {
    "tgn:hierarchy":[
        "tgn:2528712",
        "tgn:1000001",
        "tgn:2001816",
        "tgn:7012149",
        "tgn:7007713",
        "tgn:7029392"
    ],
    "tgn:id":2528712,
    "tgn:name":"Mud Butte",
    "tgn:placetype":[
        "aat:300008798"
    ]
},
  "bbox": [],
  "geometry": {"coordinates":[-102.4167,44.9667],"type":"Point"}
}