{
  "id": 2109368,
  "type": "Feature",
  "properties": {
    "tgn:hierarchy":[
        "tgn:2109368",
        "tgn:1000001",
        "tgn:2002102",
        "tgn:7012149",
        "tgn:7007827",
        "tgn:7029392"
    ],
    "tgn:id":2109368,
    "tgn:name":"Washakie Indian Reservation",
    "tgn:placetype":[
        "aat:300008347",
        "aat:300387324"
    ]
},
  "bbox": [],
  "geometry": {"coordinates":[-112.2167,41.9333],"type":"Point"}
}