{
  "id": 7397450,
  "type": "Feature",
  "properties": {
    "tgn:hierarchy":[
        "tgn:7397450",
        "tgn:1000001",
        "tgn:1001893",
        "tgn:7005560",
        "tgn:7029392"
    ],
    "tgn:id":7397450,
    "tgn:name":"San Miguel Zinacantepec",
    "tgn:placetype":[
        "aat:300008347"
    ]
},
  "bbox": [],
  "geometry": {"coordinates":[-99.738611,19.281944],"type":"Point"}
}