{
  "id": 7381521,
  "type": "Feature",
  "properties": {
    "tgn:hierarchy":[
        "tgn:7381521",
        "tgn:7005586",
        "tgn:1000001",
        "tgn:7005560",
        "tgn:7029392"
    ],
    "tgn:id":7381521,
    "tgn:name":"Los Mudos",
    "tgn:placetype":[
        "aat:300266554",
        "aat:300008699"
    ]
},
  "bbox": [],
  "geometry": {"coordinates":[-103.383333,19.516667],"type":"Point"}
}