{
  "id": 1063380,
  "type": "Feature",
  "properties": {
    "tgn:hierarchy":[
        "tgn:1063380",
        "tgn:1000003",
        "tgn:7003775",
        "tgn:1000097",
        "tgn:7029392"
    ],
    "tgn:id":1063380,
    "tgn:name":"Medevi",
    "tgn:placetype":[
        "aat:300008347"
    ]
},
  "bbox": [],
  "geometry": {"coordinates":[14.95,58.6667],"type":"Point"}
}