{
  "id": 7315635,
  "type": "Feature",
  "properties": {
    "tgn:hierarchy":[
        "tgn:7315635",
        "tgn:1001699",
        "tgn:1000049",
        "tgn:1000002",
        "tgn:7029392"
    ],
    "tgn:id":7315635,
    "tgn:name":"Chacao, Paso del",
    "tgn:placetype":[
        "aat:300387026"
    ]
},
  "bbox": [],
  "geometry": {"coordinates":[-73.656667,-44.145833],"type":"Point"}
}