{
  "id": 2519462,
  "type": "Feature",
  "properties": {
    "tgn:hierarchy":[
        "tgn:2519462",
        "tgn:2001610",
        "tgn:1000001",
        "tgn:7012149",
        "tgn:7007706",
        "tgn:7029392"
    ],
    "tgn:id":2519462,
    "tgn:name":"Modoc Run",
    "tgn:placetype":[
        "aat:300008699"
    ]
},
  "bbox": [],
  "geometry": {"coordinates":[-82.1333,39.4833],"type":"Point"}
}