{
  "id": 1079678,
  "type": "Feature",
  "properties": {
    "tgn:hierarchy":[
        "tgn:1079678",
        "tgn:7000895",
        "tgn:1000004",
        "tgn:1001031",
        "tgn:1000120",
        "tgn:7029392"
    ],
    "tgn:id":1079678,
    "tgn:name":"\u014chito",
    "tgn:placetype":[
        "aat:300008347"
    ]
},
  "bbox": [],
  "geometry": {"coordinates":[138.9333,34.9833],"type":"Point"}
}