{
  "id": 7411713,
  "type": "Feature",
  "properties": {
    "tgn:hierarchy":[
        "tgn:7411713",
        "tgn:7005580",
        "tgn:1000001",
        "tgn:7005560",
        "tgn:7029392"
    ],
    "tgn:id":7411713,
    "tgn:name":"Chincuita, R\u00edo",
    "tgn:placetype":[
        "aat:300008699"
    ]
},
  "bbox": [],
  "geometry": {"coordinates":[-91.541667,17.408333],"type":"Point"}
}