{
  "id": 7241620,
  "type": "Feature",
  "properties": {
    "tgn:hierarchy":[
        "tgn:7241620",
        "tgn:7003465",
        "tgn:1000003",
        "tgn:1000063",
        "tgn:4012014",
        "tgn:7029392"
    ],
    "tgn:id":7241620,
    "tgn:name":"La Cornette",
    "tgn:placetype":[
        "aat:300008347"
    ]
},
  "bbox": [],
  "geometry": {"coordinates":[5.15,49.816667],"type":"Point"}
}