<<<<<<< HEAD
{
  "id": 2400390,
  "type": "Feature",
  "properties": {
    "tgn:hierarchy":[
        "tgn:2400390",
        "tgn:1000001",
        "tgn:7012149",
        "tgn:2001712",
        "tgn:7007708",
        "tgn:7029392"
    ],
    "tgn:id":2400390,
    "tgn:name":"Horse Heaven Mountain",
    "tgn:placetype":[
        "aat:300008798"
    ]
},
  "bbox": [],
  "geometry": {"coordinates":[-120.4833,44.7],"type":"Point"}
}
=======
{"geometry":{"type":"Point","coordinates":[-120.483300,44.700000]},"type":"Feature","properties":{"hierarchy":["tgn:2400390","tgn:1000001","tgn:7012149","tgn:2001712","tgn:7007708","tgn:7029392"],"placetype":["aat:300008798"],"id":2400390,"name:xx":"Horse Heaven Mountain"}}
>>>>>>> 03f74aca74312dbeaf24d7e61306dd6a786dc3d0
