{
  "id": 2032597,
  "type": "Feature",
  "properties": {
    "tgn:hierarchy":[
        "tgn:2032597",
        "tgn:1000001",
        "tgn:7012149",
        "tgn:1002750",
        "tgn:7007252",
        "tgn:7029392"
    ],
    "tgn:id":2032597,
    "tgn:name":"Leipsic",
    "tgn:placetype":[
        "aat:300008347"
    ]
},
  "bbox": [],
  "geometry": {"coordinates":[-86.3667,38.6667],"type":"Point"}
}