{
  "id": 1027103,
  "type": "Feature",
  "properties": {
    "tgn:hierarchy":[
        "tgn:1027103",
        "tgn:7593919",
        "tgn:1000003",
        "tgn:1001780",
        "tgn:7029392"
    ],
    "tgn:id":1027103,
    "tgn:name":"Branka",
    "tgn:placetype":[
        "aat:300008347"
    ]
},
  "bbox": [],
  "geometry": {"coordinates":[12.5167,49.8333],"type":"Point"}
}