{
  "id": 7493959,
  "type": "Feature",
  "properties": {
    "tgn:hierarchy":[
        "tgn:7493959",
        "tgn:7001004",
        "tgn:1000004",
        "tgn:1000141",
        "tgn:7029392"
    ],
    "tgn:id":7493959,
    "tgn:name":"Chating",
    "tgn:placetype":[
        "aat:300008347"
    ]
},
  "bbox": [],
  "geometry": {"coordinates":[120.569676,22.992922],"type":"Point"}
}