<<<<<<< HEAD
{
  "id": 7355792,
  "type": "Feature",
  "properties": {
    "tgn:hierarchy":[
        "tgn:7355792",
        "tgn:1000001",
        "tgn:1001893",
        "tgn:7005560",
        "tgn:7029392"
    ],
    "tgn:id":7355792,
    "tgn:name":"Chico, R\u00edo",
    "tgn:placetype":[
        "aat:300008699"
    ]
},
  "bbox": [],
  "geometry": {"coordinates":[-103.85,21.066667],"type":"Point"}
}
=======
{"geometry":{"type":"Point","coordinates":[-103.850000,21.066667]},"type":"Feature","properties":{"hierarchy":["tgn:7355792","tgn:1000001","tgn:1001893","tgn:7005560","tgn:7029392"],"placetype":["aat:300008699"],"id":7355792,"name:xx":"Chico, R\u00edo"}}
>>>>>>> 03f74aca74312dbeaf24d7e61306dd6a786dc3d0
