<<<<<<< HEAD
{
  "id": 7375242,
  "type": "Feature",
  "properties": {
    "tgn:hierarchy":[
        "tgn:7375242",
        "tgn:1001835",
        "tgn:1000001",
        "tgn:7005560",
        "tgn:7029392"
    ],
    "tgn:id":7375242,
    "tgn:name":"Escuela Leonardo Abasolo",
    "tgn:placetype":[
        "aat:300006495"
    ]
},
  "bbox": [],
  "geometry": {"coordinates":[-115.317222,32.661111],"type":"Point"}
}
=======
{"geometry":{"type":"Point","coordinates":[-115.317222,32.661111]},"type":"Feature","properties":{"hierarchy":["tgn:7375242","tgn:1001835","tgn:1000001","tgn:7005560","tgn:7029392"],"placetype":["aat:300006495"],"id":7375242,"name:xx":"Escuela Leonardo Abasolo"}}
>>>>>>> 03f74aca74312dbeaf24d7e61306dd6a786dc3d0
