{
  "id": 7427640,
  "type": "Feature",
  "properties": {
    "tgn:hierarchy":[
        "tgn:7427640",
        "tgn:1000001",
        "tgn:7005594",
        "tgn:7005560",
        "tgn:7029392"
    ],
    "tgn:id":7427640,
    "tgn:name":"Ca\u00f1\u00f3n de Bledos",
    "tgn:placetype":[
        "aat:300008347"
    ]
},
  "bbox": [],
  "geometry": {"coordinates":[-101.083333,21.883333],"type":"Point"}
}