{
  "id": 2696557,
  "type": "Feature",
  "properties": {
    "tgn:hierarchy":[
        "tgn:2696557",
        "tgn:1000001",
        "tgn:7012149",
        "tgn:7007919",
        "tgn:7029392"
    ],
    "tgn:id":2696557,
    "tgn:name":"Stone Mountain",
    "tgn:placetype":[
        "aat:300386831"
    ]
},
  "bbox": [],
  "geometry": {"coordinates":[-82.8167,36.85],"type":"Point"}
}