{
  "id": 7503139,
  "type": "Feature",
  "properties": {
    "tgn:hierarchy":[
        "tgn:7503139",
        "tgn:1000004",
        "tgn:7004300",
        "tgn:1000141",
        "tgn:7029392"
    ],
    "tgn:id":7503139,
    "tgn:name":"Xi Shan",
    "tgn:placetype":[
        "aat:300008777"
    ]
},
  "bbox": [],
  "geometry": {"coordinates":[119.513333,23.485278],"type":"Point"}
}