{
  "id": 1079841,
  "type": "Feature",
  "properties": {
    "tgn:hierarchy":[
        "tgn:1079841",
        "tgn:7000895",
        "tgn:1000004",
        "tgn:1001031",
        "tgn:1000120",
        "tgn:7029392"
    ],
    "tgn:id":1079841,
    "tgn:name":"Atami",
    "tgn:placetype":[
        "aat:300008347"
    ]
},
  "bbox": [],
  "geometry": {"coordinates":[139.0667,35.1167],"type":"Point"}
}