{
  "id": 7224267,
  "type": "Feature",
  "properties": {
    "tgn:hierarchy":[
        "tgn:7224267",
        "tgn:7002692",
        "tgn:7012056",
        "tgn:1000003",
        "tgn:1000074",
        "tgn:7029392"
    ],
    "tgn:id":7224267,
    "tgn:name":"T\u00e9nda, \u00d3rmos",
    "tgn:placetype":[
        "aat:300132316"
    ]
},
  "bbox": [],
  "geometry": {"coordinates":[26.283333,35.283333],"type":"Point"}
}