{
  "id": 2643231,
  "type": "Feature",
  "properties": {
    "tgn:hierarchy":[
        "tgn:2643231",
        "tgn:1000001",
        "tgn:7012149",
        "tgn:7007253",
        "tgn:7029392"
    ],
    "tgn:id":2643231,
    "tgn:name":"Sandy Creek",
    "tgn:placetype":[
        "aat:300008706"
    ]
},
  "bbox": [],
  "geometry": {"coordinates":[-91.5833,43.0167],"type":"Point"}
}