{
  "id": 7076984,
  "type": "Feature",
  "properties": {
    "tgn:hierarchy":[
        "tgn:7076984",
        "tgn:1000003",
        "tgn:7003682",
        "tgn:7000084",
        "tgn:7029392"
    ],
    "tgn:id":7076984,
    "tgn:name":"Landkreis Neuwied",
    "tgn:placetype":[
        "aat:300387198"
    ]
},
  "bbox": [],
  "geometry": {"coordinates":[7.478056,50.539444],"type":"Point"}
}