<<<<<<< HEAD
{
  "id": 2251845,
  "type": "Feature",
  "properties": {
    "tgn:hierarchy":[
        "tgn:2251845",
        "tgn:1000001",
        "tgn:7012149",
        "tgn:1002567",
        "tgn:7007240",
        "tgn:7029392"
    ],
    "tgn:id":2251845,
    "tgn:name":"Conant",
    "tgn:placetype":[
        "aat:300008347"
    ]
},
  "bbox": [],
  "geometry": {"coordinates":[-81.9167,28.9333],"type":"Point"}
}
=======
{"geometry":{"type":"Point","coordinates":[-81.916700,28.933300]},"type":"Feature","properties":{"hierarchy":["tgn:2251845","tgn:1000001","tgn:7012149","tgn:1002567","tgn:7007240","tgn:7029392"],"placetype":["aat:300008347"],"id":2251845,"name:xx":"Conant"}}
>>>>>>> 03f74aca74312dbeaf24d7e61306dd6a786dc3d0
