{
  "id": 7464029,
  "type": "Feature",
  "properties": {
    "tgn:hierarchy":[
        "tgn:7464029",
        "tgn:7002448",
        "tgn:7008700",
        "tgn:1000003",
        "tgn:7008591",
        "tgn:7029392"
    ],
    "tgn:id":7464029,
    "tgn:name:en":"Ballagh Cross Roads",
    "tgn:placetype":[
        "aat:300008347"
    ]
},
  "bbox": [],
  "geometry": {"coordinates":[-7.333333,54.216667],"type":"Point"}
}