{
  "id": 2136768,
  "type": "Feature",
  "properties": {
    "tgn:hierarchy":[
        "tgn:2136768",
        "tgn:1000001",
        "tgn:7012149",
        "tgn:7014185",
        "tgn:7007710",
        "tgn:7029392"
    ],
    "tgn:id":2136768,
    "tgn:name":"Arensburg",
    "tgn:placetype":[
        "aat:300008347"
    ]
},
  "bbox": [],
  "geometry": {"coordinates":[-79.95,39.95],"type":"Point"}
}