{
  "id": 7121840,
  "type": "Feature",
  "properties": {
    "tgn:hierarchy":[
        "tgn:7121840",
        "tgn:1000003",
        "tgn:7000094",
        "tgn:7000084",
        "tgn:7029392"
    ],
    "tgn:id":7121840,
    "tgn:name":"Pinnow",
    "tgn:placetype":[
        "aat:300008347"
    ]
},
  "bbox": [],
  "geometry": {"coordinates":[13.133333,53.616667],"type":"Point"}
}