{
  "id": 7320421,
  "type": "Feature",
  "properties": {
    "tgn:hierarchy":[
        "tgn:7320421",
        "tgn:1001623",
        "tgn:1000049",
        "tgn:1000002",
        "tgn:7029392"
    ],
    "tgn:id":7320421,
    "tgn:name":"Block, Isla",
    "tgn:placetype":[
        "aat:300008791"
    ]
},
  "bbox": [],
  "geometry": {"coordinates":[-75.35,-46.833333],"type":"Point"}
}