{
  "id": 1040705,
  "type": "Feature",
  "properties": {
    "tgn:hierarchy":[
        "tgn:1040705",
        "tgn:1000003",
        "tgn:7003676",
        "tgn:7000084",
        "tgn:7029392"
    ],
    "tgn:id":1040705,
    "tgn:name":"Pattensen",
    "tgn:placetype":[
        "aat:300008347"
    ]
},
  "bbox": [],
  "geometry": {"coordinates":[9.766667,52.266667],"type":"Point"}
}