{
  "id": 7160834,
  "type": "Feature",
  "properties": {
    "tgn:hierarchy":[
        "tgn:7160834",
        "tgn:7003669",
        "tgn:1000003",
        "tgn:7000084",
        "tgn:7029392"
    ],
    "tgn:id":7160834,
    "tgn:name":"Hockenhof",
    "tgn:placetype":[
        "aat:300000206"
    ]
},
  "bbox": [],
  "geometry": {"coordinates":[9.283333,49.966667],"type":"Point"}
}