{
  "id": 1115860,
  "type": "Feature",
  "properties": {
    "tgn:hierarchy":[
        "tgn:1115860",
        "tgn:7002075",
        "tgn:1000004",
        "tgn:1000111",
        "tgn:7029392"
    ],
    "tgn:id":1115860,
    "tgn:name":"Chao Hu",
    "tgn:placetype":[
        "aat:300008680"
    ]
},
  "bbox": [],
  "geometry": {"coordinates":[117.55,31.5167],"type":"Point"}
}