{
  "id": 2130321,
  "type": "Feature",
  "properties": {
    "tgn:hierarchy":[
        "tgn:2130321",
        "tgn:1000001",
        "tgn:7012149",
        "tgn:2001983",
        "tgn:7007826",
        "tgn:7029392"
    ],
    "tgn:id":2130321,
    "tgn:name":"Allens Creek",
    "tgn:placetype":[
        "aat:300008706"
    ]
},
  "bbox": [],
  "geometry": {"coordinates":[-95.9333,33.5833],"type":"Point"}
}