{
  "id": 2534919,
  "type": "Feature",
  "properties": {
    "tgn:hierarchy":[
        "tgn:2534919",
        "tgn:1000001",
        "tgn:7012149",
        "tgn:7007248",
        "tgn:7029392"
    ],
    "tgn:id":2534919,
    "tgn:name":"Naked Creek",
    "tgn:placetype":[
        "aat:300008706"
    ]
},
  "bbox": [],
  "geometry": {"coordinates":[-82.4833,32.3667],"type":"Point"}
}