{
  "id": 7548777,
  "type": "Feature",
  "properties": {
    "tgn:hierarchy":[
        "tgn:7548777",
        "tgn:1000004",
        "tgn:1001842",
        "tgn:7000198",
        "tgn:7029392"
    ],
    "tgn:id":7548777,
    "tgn:name:en":"Burhi Gandak River",
    "tgn:placetype":[
        "aat:300008699"
    ]
},
  "bbox": [],
  "geometry": {"coordinates":[86.635462,25.322579],"type":"Point"}
}