{
  "id": 2317925,
  "type": "Feature",
  "properties": {
    "tgn:hierarchy":[
        "tgn:2317925",
        "tgn:7002659",
        "tgn:1000001",
        "tgn:7012149",
        "tgn:2000026",
        "tgn:7029392"
    ],
    "tgn:id":2317925,
    "tgn:name":"English Pond",
    "tgn:placetype":[
        "aat:300006191"
    ]
},
  "bbox": [],
  "geometry": {"coordinates":[-87.0333,31.0667],"type":"Point"}
}