{
  "id": 7370636,
  "type": "Feature",
  "properties": {
    "tgn:hierarchy":[
        "tgn:7370636",
        "tgn:1000001",
        "tgn:1001893",
        "tgn:7005560",
        "tgn:7029392"
    ],
    "tgn:id":7370636,
    "tgn:name":"Jazm\u00edn",
    "tgn:placetype":[
        "aat:300008347"
    ]
},
  "bbox": [],
  "geometry": {"coordinates":[-99.883333,20.033333],"type":"Point"}
}