{
  "id": 7310509,
  "type": "Feature",
  "properties": {
    "tgn:hierarchy":[
        "tgn:7310509",
        "tgn:1001708",
        "tgn:1000049",
        "tgn:1000002",
        "tgn:7029392"
    ],
    "tgn:id":7310509,
    "tgn:name":"Mina, Quebrada de la",
    "tgn:placetype":[
        "aat:300008699"
    ]
},
  "bbox": [],
  "geometry": {"coordinates":[-71.383333,-33.816667],"type":"Point"}
}