{
  "id": 7340559,
  "type": "Feature",
  "properties": {
    "tgn:hierarchy":[
        "tgn:7340559",
        "tgn:7002847",
        "tgn:1001647",
        "tgn:1000003",
        "tgn:1000095",
        "tgn:7029392"
    ],
    "tgn:id":7340559,
    "tgn:name":"Cantaelgallo, Arroyo de",
    "tgn:placetype":[
        "aat:300008699"
    ]
},
  "bbox": [],
  "geometry": {"coordinates":[-4.083333,40.033333],"type":"Point"}
}