<<<<<<< HEAD
{
  "id": 7374600,
  "type": "Feature",
  "properties": {
    "tgn:hierarchy":[
        "tgn:7374600",
        "tgn:1000001",
        "tgn:7005594",
        "tgn:7005560",
        "tgn:7029392"
    ],
    "tgn:id":7374600,
    "tgn:name":"Lagunita",
    "tgn:placetype":[
        "aat:300008347"
    ]
},
  "bbox": [],
  "geometry": {"coordinates":[-99.466667,22.15],"type":"Point"}
}
=======
{"geometry":{"type":"Point","coordinates":[-99.466667,22.150000]},"type":"Feature","properties":{"hierarchy":["tgn:7374600","tgn:1000001","tgn:7005594","tgn:7005560","tgn:7029392"],"placetype":["aat:300008347"],"id":7374600,"name:xx":"Lagunita"}}
>>>>>>> 03f74aca74312dbeaf24d7e61306dd6a786dc3d0
