{
  "id": 7285933,
  "type": "Feature",
  "properties": {
    "tgn:hierarchy":[
        "tgn:7285933",
        "tgn:7002464",
        "tgn:1000049",
        "tgn:1000002",
        "tgn:7029392"
    ],
    "tgn:id":7285933,
    "tgn:name":"Quebrada Blanca, Cerro",
    "tgn:placetype":[
        "aat:300008795"
    ]
},
  "bbox": [],
  "geometry": {"coordinates":[-68.85,-20.983333],"type":"Point"}
}