{
  "id": 7106852,
  "type": "Feature",
  "properties": {
    "tgn:hierarchy":[
        "tgn:7106852",
        "tgn:1000003",
        "tgn:7003685",
        "tgn:7000084",
        "tgn:7029392"
    ],
    "tgn:id":7106852,
    "tgn:name":"Schlauditz",
    "tgn:placetype":[
        "aat:300008347"
    ]
},
  "bbox": [],
  "geometry": {"coordinates":[12.366667,50.816667],"type":"Point"}
}