<<<<<<< HEAD
{
  "id": 2251727,
  "type": "Feature",
  "properties": {
    "tgn:hierarchy":[
        "tgn:2251727",
        "tgn:1000001",
        "tgn:7016172",
        "tgn:7012149",
        "tgn:2000133",
        "tgn:7029392"
    ],
    "tgn:id":2251727,
    "tgn:name":"Compton",
    "tgn:placetype":[
        "aat:300008347"
    ]
},
  "bbox": [],
  "geometry": {"coordinates":[-93.8,33.9167],"type":"Point"}
}
=======
{"geometry":{"type":"Point","coordinates":[-93.800000,33.916700]},"type":"Feature","properties":{"hierarchy":["tgn:2251727","tgn:1000001","tgn:7016172","tgn:7012149","tgn:2000133","tgn:7029392"],"placetype":["aat:300008347"],"id":2251727,"name:xx":"Compton"}}
>>>>>>> 03f74aca74312dbeaf24d7e61306dd6a786dc3d0
