<<<<<<< HEAD
{
  "id": 2252011,
  "type": "Feature",
  "properties": {
    "tgn:hierarchy":[
        "tgn:2252011",
        "tgn:1000001",
        "tgn:7012149",
        "tgn:2001284",
        "tgn:7007524",
        "tgn:7029392"
    ],
    "tgn:id":2252011,
    "tgn:name":"Concord Mountain",
    "tgn:placetype":[
        "aat:300008798"
    ]
},
  "bbox": [],
  "geometry": {"coordinates":[-113.0,47.2833],"type":"Point"}
}
=======
{"geometry":{"type":"Point","coordinates":[-113.000000,47.283300]},"type":"Feature","properties":{"hierarchy":["tgn:2252011","tgn:1000001","tgn:7012149","tgn:2001284","tgn:7007524","tgn:7029392"],"placetype":["aat:300008798"],"id":2252011,"name:xx":"Concord Mountain"}}
>>>>>>> 03f74aca74312dbeaf24d7e61306dd6a786dc3d0
