{
  "id": 7401079,
  "type": "Feature",
  "properties": {
    "tgn:hierarchy":[
        "tgn:7401079",
        "tgn:1000001",
        "tgn:7005599",
        "tgn:7005560",
        "tgn:7029392"
    ],
    "tgn:id":7401079,
    "tgn:name":"Cacahuatengo",
    "tgn:placetype":[
        "aat:300008347"
    ]
},
  "bbox": [],
  "geometry": {"coordinates":[-98.033333,20.783333],"type":"Point"}
}