{
  "id": 7499171,
  "type": "Feature",
  "properties": {
    "tgn:hierarchy":[
        "tgn:7499171",
        "tgn:1000957",
        "tgn:1000004",
        "tgn:1000141",
        "tgn:7029392"
    ],
    "tgn:id":7499171,
    "tgn:name":"Daoxuan Gong",
    "tgn:placetype":[
        "aat:300007595"
    ]
},
  "bbox": [],
  "geometry": {"coordinates":[121.752684,25.133315],"type":"Point"}
}