{
  "id": 2185309,
  "type": "Feature",
  "properties": {
    "tgn:hierarchy":[
        "tgn:2185309",
        "tgn:1000001",
        "tgn:7012149",
        "tgn:2000479",
        "tgn:7007250",
        "tgn:7029392"
    ],
    "tgn:id":2185309,
    "tgn:name":"Bogle Draw",
    "tgn:placetype":[
        "aat:300008761"
    ]
},
  "bbox": [],
  "geometry": {"coordinates":[-116.4833,47.6167],"type":"Point"}
}