{
  "id": 2597763,
  "type": "Feature",
  "properties": {
    "tgn:hierarchy":[
        "tgn:2597763",
        "tgn:1000001",
        "tgn:7006451",
        "tgn:2000092",
        "tgn:7012149",
        "tgn:7029392"
    ],
    "tgn:id":2597763,
    "tgn:name":"Pratt Reservoir",
    "tgn:placetype":[
        "aat:300006191"
    ]
},
  "bbox": [],
  "geometry": {"coordinates":[-112.4333,36.9333],"type":"Point"}
}