{
  "id": 2642759,
  "type": "Feature",
  "properties": {
    "tgn:hierarchy":[
        "tgn:2642759",
        "tgn:1000001",
        "tgn:7012149",
        "tgn:2000811",
        "tgn:7007255",
        "tgn:7029392"
    ],
    "tgn:id":2642759,
    "tgn:name":"Sandlick Branch",
    "tgn:placetype":[
        "aat:300008699"
    ]
},
  "bbox": [],
  "geometry": {"coordinates":[-83.4333,37.0833],"type":"Point"}
}