<<<<<<< HEAD
{
  "id": 2259041,
  "type": "Feature",
  "properties": {
    "tgn:hierarchy":[
        "tgn:2259041",
        "tgn:1000001",
        "tgn:7012149",
        "tgn:2002119",
        "tgn:7007827",
        "tgn:7029392"
    ],
    "tgn:id":2259041,
    "tgn:name":"Cottonwood Creek",
    "tgn:placetype":[
        "aat:300008706"
    ]
},
  "bbox": [],
  "geometry": {"coordinates":[-109.7333,37.8333],"type":"Point"}
}
=======
{"geometry":{"type":"Point","coordinates":[-109.733300,37.833300]},"type":"Feature","properties":{"hierarchy":["tgn:2259041","tgn:1000001","tgn:7012149","tgn:2002119","tgn:7007827","tgn:7029392"],"placetype":["aat:300008706"],"id":2259041,"name:xx":"Cottonwood Creek"}}
>>>>>>> 03f74aca74312dbeaf24d7e61306dd6a786dc3d0
