{
  "id": 7118699,
  "type": "Feature",
  "properties": {
    "tgn:hierarchy":[
        "tgn:7118699",
        "tgn:1000003",
        "tgn:7003676",
        "tgn:7000084",
        "tgn:7029392"
    ],
    "tgn:id":7118699,
    "tgn:name":"Peters-Berg",
    "tgn:placetype":[
        "aat:300008777"
    ]
},
  "bbox": [],
  "geometry": {"coordinates":[10.366667,51.583333],"type":"Point"}
}