{
  "id": 1021284,
  "type": "Feature",
  "properties": {
    "tgn:hierarchy":[
        "tgn:1021284",
        "tgn:1001925",
        "tgn:1000047",
        "tgn:7002458",
        "tgn:1000002",
        "tgn:7029392"
    ],
    "tgn:id":1021284,
    "tgn:name":"Cruzeiro do Oeste",
    "tgn:placetype":[
        "aat:300008347"
    ]
},
  "bbox": [],
  "geometry": {"coordinates":[-53.0667,-23.7667],"type":"Point"}
}