{
  "id": 1107093,
  "type": "Feature",
  "properties": {
    "tgn:hierarchy":[
        "tgn:1107093",
        "tgn:1000001",
        "tgn:7012149",
        "tgn:7007157",
        "tgn:1002684",
        "tgn:7029392"
    ],
    "tgn:id":1107093,
    "tgn:name":"Alder Peak",
    "tgn:placetype":[
        "aat:300008798"
    ]
},
  "bbox": [],
  "geometry": {"coordinates":[-121.3667,35.8833],"type":"Point"}
}