{
  "id": 2544386,
  "type": "Feature",
  "properties": {
    "tgn:hierarchy":[
        "tgn:2544386",
        "tgn:1000001",
        "tgn:7012149",
        "tgn:7007252",
        "tgn:7029392"
    ],
    "tgn:id":2544386,
    "tgn:name":"North Branch Turkey Creek",
    "tgn:placetype":[
        "aat:300008706"
    ]
},
  "bbox": [],
  "geometry": {"coordinates":[-85.2833,39.65],"type":"Point"}
}