{
  "id": 2161893,
  "type": "Feature",
  "properties": {
    "tgn:hierarchy":[
        "tgn:2161893",
        "tgn:1000001",
        "tgn:7012149",
        "tgn:2001067",
        "tgn:7007521",
        "tgn:7029392"
    ],
    "tgn:id":2161893,
    "tgn:name":"Bellow Creek",
    "tgn:placetype":[
        "aat:300008706"
    ]
},
  "bbox": [],
  "geometry": {"coordinates":[-92.15,48.0833],"type":"Point"}
}