<<<<<<< HEAD
{
  "id": 2336502,
  "type": "Feature",
  "properties": {
    "tgn:hierarchy":[
        "tgn:2336502",
        "tgn:1000001",
        "tgn:7012149",
        "tgn:1003044",
        "tgn:7007708",
        "tgn:7029392"
    ],
    "tgn:id":2336502,
    "tgn:name":"Four Corners",
    "tgn:placetype":[
        "aat:300008347"
    ]
},
  "bbox": [],
  "geometry": {"coordinates":[-123.0333,45.1167],"type":"Point"}
}
=======
{"geometry":{"type":"Point","coordinates":[-123.033300,45.116700]},"type":"Feature","properties":{"hierarchy":["tgn:2336502","tgn:1000001","tgn:7012149","tgn:1003044","tgn:7007708","tgn:7029392"],"placetype":["aat:300008347"],"id":2336502,"name:xx":"Four Corners"}}
>>>>>>> 03f74aca74312dbeaf24d7e61306dd6a786dc3d0
