{
  "id": 2336502,
  "type": "Feature",
  "properties": {
    "tgn:hierarchy":[
        "tgn:2336502",
        "tgn:1000001",
        "tgn:7012149",
        "tgn:1003044",
        "tgn:7007708",
        "tgn:7029392"
    ],
    "tgn:id":2336502,
    "tgn:name":"Four Corners",
    "tgn:placetype":[
        "aat:300008347"
    ]
},
  "bbox": [],
  "geometry": {"coordinates":[-123.0333,45.1167],"type":"Point"}
}