{
  "id": 2654254,
  "type": "Feature",
  "properties": {
    "tgn:hierarchy":[
        "tgn:2654254",
        "tgn:7006450",
        "tgn:1000001",
        "tgn:7012149",
        "tgn:2000086",
        "tgn:7029392"
    ],
    "tgn:id":2654254,
    "tgn:name":"Shady Cove",
    "tgn:placetype":[
        "aat:300132316"
    ]
},
  "bbox": [],
  "geometry": {"coordinates":[-148.4167,60.55],"type":"Point"}
}