<<<<<<< HEAD
{
  "id": 7484905,
  "type": "Feature",
  "properties": {
    "tgn:hierarchy":[
        "tgn:7484905",
        "tgn:1000004",
        "tgn:7490934",
        "tgn:1000141",
        "tgn:7029392"
    ],
    "tgn:id":7484905,
    "tgn:name":"Tandihu Qiao",
    "tgn:placetype":[
        "aat:300007836"
    ]
},
  "bbox": [],
  "geometry": {"coordinates":[120.361944,23.391944],"type":"Point"}
}
=======
{"geometry":{"type":"Point","coordinates":[120.361944,23.391944]},"type":"Feature","properties":{"hierarchy":["tgn:7484905","tgn:1000004","tgn:7490934","tgn:1000141","tgn:7029392"],"placetype":["aat:300007836"],"id":7484905,"name:xx":"Tandihu Qiao"}}
>>>>>>> 03f74aca74312dbeaf24d7e61306dd6a786dc3d0
