{
  "id": 2203277,
  "type": "Feature",
  "properties": {
    "tgn:hierarchy":[
        "tgn:2203277",
        "tgn:1000001",
        "tgn:7012149",
        "tgn:1002422",
        "tgn:7007251",
        "tgn:7029392"
    ],
    "tgn:id":2203277,
    "tgn:name":"Buckhorn Island",
    "tgn:placetype":[
        "aat:300008791"
    ]
},
  "bbox": [],
  "geometry": {"coordinates":[-90.5833,39.4833],"type":"Point"}
}