{
  "id": 2659547,
  "type": "Feature",
  "properties": {
    "tgn:hierarchy":[
        "tgn:2659547",
        "tgn:7006450",
        "tgn:1000001",
        "tgn:7012149",
        "tgn:2000088",
        "tgn:7029392"
    ],
    "tgn:id":2659547,
    "tgn:name":"Shingle Island",
    "tgn:placetype":[
        "aat:300008791"
    ]
},
  "bbox": [],
  "geometry": {"coordinates":[-133.3833,56.4333],"type":"Point"}
}