{
  "id": 2087785,
  "type": "Feature",
  "properties": {
    "tgn:hierarchy":[
        "tgn:2087785",
        "tgn:1000001",
        "tgn:7012149",
        "tgn:1002387",
        "tgn:7007710",
        "tgn:7029392"
    ],
    "tgn:id":2087785,
    "tgn:name":"Dickey",
    "tgn:placetype":[
        "aat:300008347",
        "aat:300387210"
    ]
},
  "bbox": [],
  "geometry": {"coordinates":[-77.8833,39.8667],"type":"Point"}
}