{
  "id": 2426565,
  "type": "Feature",
  "properties": {
    "tgn:hierarchy":[
        "tgn:2426565",
        "tgn:1000001",
        "tgn:7012149",
        "tgn:2001621",
        "tgn:7007706",
        "tgn:7029392"
    ],
    "tgn:id":2426565,
    "tgn:name":"Jones Hollow",
    "tgn:placetype":[
        "aat:300008761"
    ]
},
  "bbox": [],
  "geometry": {"coordinates":[-82.3333,39.2667],"type":"Point"}
}