{
  "id": 2600953,
  "type": "Feature",
  "properties": {
    "tgn:hierarchy":[
        "tgn:2600953",
        "tgn:1000001",
        "tgn:7012149",
        "tgn:2000406",
        "tgn:7007248",
        "tgn:7029392"
    ],
    "tgn:id":2600953,
    "tgn:name":"Pumpkin Pile Creek",
    "tgn:placetype":[
        "aat:300008706"
    ]
},
  "bbox": [],
  "geometry": {"coordinates":[-85.3667,33.9167],"type":"Point"}
}