{
  "id": 2272278,
  "type": "Feature",
  "properties": {
    "tgn:hierarchy":[
        "tgn:2272278",
        "tgn:1000001",
        "tgn:1002190",
        "tgn:7012149",
        "tgn:7007523",
        "tgn:7029392"
    ],
    "tgn:id":2272278,
    "tgn:name":"Curry Lake",
    "tgn:placetype":[
        "aat:300006191"
    ]
},
  "bbox": [],
  "geometry": {"coordinates":[-92.2333,38.8167],"type":"Point"}
}