<<<<<<< HEAD
{
  "id": 7110328,
  "type": "Feature",
  "properties": {
    "tgn:hierarchy":[
        "tgn:7110328",
        "tgn:7003669",
        "tgn:1000003",
        "tgn:7000084",
        "tgn:7029392"
    ],
    "tgn:id":7110328,
    "tgn:name":"Rauschen",
    "tgn:placetype":[
        "aat:300008777"
    ]
},
  "bbox": [],
  "geometry": {"coordinates":[9.15,49.7],"type":"Point"}
}
=======
{"geometry":{"type":"Point","coordinates":[9.150000,49.700000]},"type":"Feature","properties":{"hierarchy":["tgn:7110328","tgn:7003669","tgn:1000003","tgn:7000084","tgn:7029392"],"placetype":["aat:300008777"],"id":7110328,"name:xx":"Rauschen"}}
>>>>>>> 03f74aca74312dbeaf24d7e61306dd6a786dc3d0
