{
  "id": 7174812,
  "type": "Feature",
  "properties": {
    "tgn:hierarchy":[
        "tgn:7174812",
        "tgn:7003669",
        "tgn:1000003",
        "tgn:7000084",
        "tgn:7029392"
    ],
    "tgn:id":7174812,
    "tgn:name":"Gro\u00dfer Hammerweiher",
    "tgn:placetype":[
        "aat:300008680"
    ]
},
  "bbox": [],
  "geometry": {"coordinates":[12.533333,49.05],"type":"Point"}
}