{
  "id": 1098275,
  "type": "Feature",
  "properties": {
    "tgn:hierarchy":[
        "tgn:1098275",
        "tgn:7000490",
        "tgn:1000006",
        "tgn:7001828",
        "tgn:7029392"
    ],
    "tgn:id":1098275,
    "tgn:name":"Tarana",
    "tgn:placetype":[
        "aat:300008347"
    ]
},
  "bbox": [],
  "geometry": {"coordinates":[149.9167,-33.5167],"type":"Point"}
}