{
  "id": 2719151,
  "type": "Feature",
  "properties": {
    "tgn:hierarchy":[
        "tgn:2719151",
        "tgn:1000001",
        "tgn:7012149",
        "tgn:2001204",
        "tgn:7007523",
        "tgn:7029392"
    ],
    "tgn:id":2719151,
    "tgn:name":"Thorp Branch",
    "tgn:placetype":[
        "aat:300008699"
    ]
},
  "bbox": [],
  "geometry": {"coordinates":[-95.0833,39.95],"type":"Point"}
}