{
  "id": 7132035,
  "type": "Feature",
  "properties": {
    "tgn:hierarchy":[
        "tgn:7132035",
        "tgn:7003692",
        "tgn:1000003",
        "tgn:7000084",
        "tgn:7029392"
    ],
    "tgn:id":7132035,
    "tgn:name":"Misslinke",
    "tgn:placetype":[
        "aat:300000206"
    ]
},
  "bbox": [],
  "geometry": {"coordinates":[8.166667,48.366667],"type":"Point"}
}