{
  "id": 1022473,
  "type": "Feature",
  "properties": {
    "tgn:hierarchy":[
        "tgn:1022473",
        "tgn:1001941",
        "tgn:1000047",
        "tgn:7002458",
        "tgn:1000002",
        "tgn:7029392"
    ],
    "tgn:id":1022473,
    "tgn:name":"Pinheiro Machado",
    "tgn:placetype":[
        "aat:300008347"
    ]
},
  "bbox": [],
  "geometry": {"coordinates":[-53.3667,-31.5667],"type":"Point"}
}