{
  "id": 7045669,
  "type": "Feature",
  "properties": {
    "tgn:hierarchy":[
        "tgn:7045669",
        "tgn:7002996",
        "tgn:1000003",
        "tgn:7002997",
        "tgn:1000080",
        "tgn:7029392"
    ],
    "tgn:id":7045669,
    "tgn:name":"Castelcucco",
    "tgn:placetype":[
        "aat:300008347"
    ]
},
  "bbox": [],
  "geometry": {"coordinates":[11.866667,45.833333],"type":"Point"}
}