{
  "id": 1062833,
  "type": "Feature",
  "properties": {
    "tgn:hierarchy":[
        "tgn:1062833",
        "tgn:1000003",
        "tgn:7003779",
        "tgn:1000097",
        "tgn:7029392"
    ],
    "tgn:id":1062833,
    "tgn:name":"Bjurholm",
    "tgn:placetype":[
        "aat:300008347"
    ]
},
  "bbox": [],
  "geometry": {"coordinates":[19.1667,63.9333],"type":"Point"}
}