{
  "id": 1132952,
  "type": "Feature",
  "properties": {
    "tgn:hierarchy":[
        "tgn:1132952",
        "tgn:1000001",
        "tgn:7012149",
        "tgn:7007252",
        "tgn:7029392"
    ],
    "tgn:id":1132952,
    "tgn:name":"Crooked Creek",
    "tgn:placetype":[
        "aat:300008706"
    ]
},
  "bbox": [],
  "geometry": {"coordinates":[-86.6167,38.8333],"type":"Point"}
}