{
  "id": 2142416,
  "type": "Feature",
  "properties": {
    "tgn:hierarchy":[
        "tgn:2142416",
        "tgn:1000001",
        "tgn:7012149",
        "tgn:7007157",
        "tgn:2000188",
        "tgn:7029392"
    ],
    "tgn:id":2142416,
    "tgn:name":"Bacon Creek",
    "tgn:placetype":[
        "aat:300008706"
    ]
},
  "bbox": [],
  "geometry": {"coordinates":[-122.1833,40.7167],"type":"Point"}
}