{
  "id": 2349708,
  "type": "Feature",
  "properties": {
    "tgn:hierarchy":[
        "tgn:2349708",
        "tgn:7002659",
        "tgn:1000001",
        "tgn:7012149",
        "tgn:2000035",
        "tgn:7029392"
    ],
    "tgn:id":2349708,
    "tgn:name":"Gilliam Spring",
    "tgn:placetype":[
        "aat:300008697"
    ]
},
  "bbox": [],
  "geometry": {"coordinates":[-86.25,34.7167],"type":"Point"}
}