{
  "id": 7038411,
  "type": "Feature",
  "properties": {
    "tgn:hierarchy":[
        "tgn:7038411",
        "tgn:7003139",
        "tgn:1000003",
        "tgn:7003080",
        "tgn:1000080",
        "tgn:7029392"
    ],
    "tgn:id":7038411,
    "tgn:name":"Tonoco, Monte",
    "tgn:placetype":[
        "aat:300008795"
    ]
},
  "bbox": [],
  "geometry": {"coordinates":[11.866667,42.65],"type":"Point"}
}