{
  "id": 1065832,
  "type": "Feature",
  "properties": {
    "tgn:hierarchy":[
        "tgn:1065832",
        "tgn:1000004",
        "tgn:7000190",
        "tgn:1000105",
        "tgn:7029392"
    ],
    "tgn:id":1065832,
    "tgn:name":"Morrelganj",
    "tgn:placetype":[
        "aat:300008347"
    ]
},
  "bbox": [],
  "geometry": {"coordinates":[89.85,22.4667],"type":"Point"}
}