{
  "id": 7558249,
  "type": "Feature",
  "properties": {
    "tgn:hierarchy":[
        "tgn:7558249",
        "tgn:1001828",
        "tgn:1000004",
        "tgn:7000198",
        "tgn:7029392"
    ],
    "tgn:id":7558249,
    "tgn:name:en":"Puj\u0101rik\u0101ker",
    "tgn:placetype":[
        "aat:300008347"
    ]
},
  "bbox": [],
  "geometry": {"coordinates":[80.816667,18.333333],"type":"Point"}
}