{
  "id": 7494740,
  "type": "Feature",
  "properties": {
    "tgn:hierarchy":[
        "tgn:7494740",
        "tgn:7468018",
        "tgn:1000004",
        "tgn:1000141",
        "tgn:7029392"
    ],
    "tgn:id":7494740,
    "tgn:name":"Bao'an Gong",
    "tgn:placetype":[
        "aat:300007595"
    ]
},
  "bbox": [],
  "geometry": {"coordinates":[120.412887,23.562619],"type":"Point"}
}