{
  "id": 2142996,
  "type": "Feature",
  "properties": {
    "tgn:hierarchy":[
        "tgn:2142996",
        "tgn:1000001",
        "tgn:7016172",
        "tgn:2000109",
        "tgn:7012149",
        "tgn:7029392"
    ],
    "tgn:id":2142996,
    "tgn:name":"Bagget Hollow",
    "tgn:placetype":[
        "aat:300008761"
    ]
},
  "bbox": [],
  "geometry": {"coordinates":[-92.9333,36.3333],"type":"Point"}
}