{
  "id": 2248866,
  "type": "Feature",
  "properties": {
    "tgn:hierarchy":[
        "tgn:2248866",
        "tgn:1000001",
        "tgn:7012149",
        "tgn:2000342",
        "tgn:7007248",
        "tgn:7029392"
    ],
    "tgn:id":2248866,
    "tgn:name":"Coldbrook",
    "tgn:placetype":[
        "aat:300008347"
    ]
},
  "bbox": [],
  "geometry": {"coordinates":[-81.2333,32.2333],"type":"Point"}
}