{
  "id": 2760020,
  "type": "Feature",
  "properties": {
    "tgn:hierarchy":[
        "tgn:2760020",
        "tgn:1000001",
        "tgn:7012149",
        "tgn:7007825",
        "tgn:7029392"
    ],
    "tgn:id":2760020,
    "tgn:name":"West Fork Mulberry Creek",
    "tgn:placetype":[
        "aat:300008706"
    ]
},
  "bbox": [],
  "geometry": {"coordinates":[-86.5167,35.3167],"type":"Point"}
}