<<<<<<< HEAD
{
  "id": 2760020,
  "type": "Feature",
  "properties": {
    "tgn:hierarchy":[
        "tgn:2760020",
        "tgn:1000001",
        "tgn:7012149",
        "tgn:7007825",
        "tgn:7029392"
    ],
    "tgn:id":2760020,
    "tgn:name":"West Fork Mulberry Creek",
    "tgn:placetype":[
        "aat:300008706"
    ]
},
  "bbox": [],
  "geometry": {"coordinates":[-86.5167,35.3167],"type":"Point"}
}
=======
{"geometry":{"type":"Point","coordinates":[-86.516700,35.316700]},"type":"Feature","properties":{"hierarchy":["tgn:2760020","tgn:1000001","tgn:7012149","tgn:7007825","tgn:7029392"],"placetype":["aat:300008706"],"id":2760020,"name:xx":"West Fork Mulberry Creek"}}
>>>>>>> 03f74aca74312dbeaf24d7e61306dd6a786dc3d0
