{
  "id": 2181713,
  "type": "Feature",
  "properties": {
    "tgn:hierarchy":[
        "tgn:2181713",
        "tgn:1000001",
        "tgn:7012149",
        "tgn:2001237",
        "tgn:7007523",
        "tgn:7029392"
    ],
    "tgn:id":2181713,
    "tgn:name":"Blue Hole Spring",
    "tgn:placetype":[
        "aat:300008697"
    ]
},
  "bbox": [],
  "geometry": {"coordinates":[-91.05,36.7167],"type":"Point"}
}