{
  "id": 2706576,
  "type": "Feature",
  "properties": {
    "tgn:hierarchy":[
        "tgn:2706576",
        "tgn:1000001",
        "tgn:7012149",
        "tgn:2001161",
        "tgn:7007522",
        "tgn:7029392"
    ],
    "tgn:id":2706576,
    "tgn:name":"Swan Lake",
    "tgn:placetype":[
        "aat:300008905"
    ]
},
  "bbox": [],
  "geometry": {"coordinates":[-90.9667,33.1167],"type":"Point"}
}