{
  "id": 2562650,
  "type": "Feature",
  "properties": {
    "tgn:hierarchy":[
        "tgn:2562650",
        "tgn:1000001",
        "tgn:2000460",
        "tgn:7012149",
        "tgn:7007250",
        "tgn:7029392"
    ],
    "tgn:id":2562650,
    "tgn:name":"Outlet Mountain",
    "tgn:placetype":[
        "aat:300008798"
    ]
},
  "bbox": [],
  "geometry": {"coordinates":[-116.8833,48.4667],"type":"Point"}
}