{
  "id": 2745454,
  "type": "Feature",
  "properties": {
    "tgn:hierarchy":[
        "tgn:2745454",
        "tgn:7002659",
        "tgn:1000001",
        "tgn:7012149",
        "tgn:2000051",
        "tgn:7029392"
    ],
    "tgn:id":2745454,
    "tgn:name":"Vinsant Hollow",
    "tgn:placetype":[
        "aat:300008761"
    ]
},
  "bbox": [],
  "geometry": {"coordinates":[-86.85,34.4833],"type":"Point"}
}