{
  "id": 2323781,
  "type": "Feature",
  "properties": {
    "tgn:hierarchy":[
        "tgn:2323781",
        "tgn:2000919",
        "tgn:1000001",
        "tgn:7012149",
        "tgn:7007515",
        "tgn:7029392"
    ],
    "tgn:id":2323781,
    "tgn:name":"Faulkner Lake",
    "tgn:placetype":[
        "aat:300008680"
    ]
},
  "bbox": [],
  "geometry": {"coordinates":[-67.8833,45.7667],"type":"Point"}
}