{
  "id": 2265594,
  "type": "Feature",
  "properties": {
    "tgn:hierarchy":[
        "tgn:2265594",
        "tgn:1000001",
        "tgn:2000922",
        "tgn:7012149",
        "tgn:7007515",
        "tgn:7029392"
    ],
    "tgn:id":2265594,
    "tgn:name":"Cranes Corners",
    "tgn:placetype":[
        "aat:300008347"
    ]
},
  "bbox": [],
  "geometry": {"coordinates":[-68.7333,44.5333],"type":"Point"}
}