{
  "id": 7171442,
  "type": "Feature",
  "properties": {
    "tgn:hierarchy":[
        "tgn:7171442",
        "tgn:7003692",
        "tgn:1000003",
        "tgn:7000084",
        "tgn:7029392"
    ],
    "tgn:id":7171442,
    "tgn:name":"Hemsbach",
    "tgn:placetype":[
        "aat:300008347"
    ]
},
  "bbox": [],
  "geometry": {"coordinates":[8.646389,49.591667],"type":"Point"}
}