<<<<<<< HEAD
{
  "id": 2401389,
  "type": "Feature",
  "properties": {
    "tgn:hierarchy":[
        "tgn:2401389",
        "tgn:1000001",
        "tgn:7012149",
        "tgn:2000928",
        "tgn:7007515",
        "tgn:7029392"
    ],
    "tgn:id":2401389,
    "tgn:name":"Horserace Brook",
    "tgn:placetype":[
        "aat:300008699"
    ]
},
  "bbox": [],
  "geometry": {"coordinates":[-69.0833,45.85],"type":"Point"}
}
=======
{"geometry":{"type":"Point","coordinates":[-69.083300,45.850000]},"type":"Feature","properties":{"hierarchy":["tgn:2401389","tgn:1000001","tgn:7012149","tgn:2000928","tgn:7007515","tgn:7029392"],"placetype":["aat:300008699"],"id":2401389,"name:xx":"Horserace Brook"}}
>>>>>>> 03f74aca74312dbeaf24d7e61306dd6a786dc3d0
