{
  "id": 7047077,
  "type": "Feature",
  "properties": {
    "tgn:hierarchy":[
        "tgn:7047077",
        "tgn:7003137",
        "tgn:1000003",
        "tgn:7003080",
        "tgn:1000080",
        "tgn:7029392"
    ],
    "tgn:id":7047077,
    "tgn:name":"Favischio",
    "tgn:placetype":[
        "aat:300008347"
    ]
},
  "bbox": [],
  "geometry": {"coordinates":[13.066667,42.516667],"type":"Point"}
}