{
  "id": 2762552,
  "type": "Feature",
  "properties": {
    "tgn:hierarchy":[
        "tgn:2762552",
        "tgn:1000001",
        "tgn:7012149",
        "tgn:2000648",
        "tgn:7007253",
        "tgn:7029392"
    ],
    "tgn:id":2762552,
    "tgn:name":"West Wolf Creek",
    "tgn:placetype":[
        "aat:300008706"
    ]
},
  "bbox": [],
  "geometry": {"coordinates":[-94.0833,41.15],"type":"Point"}
}