{
  "id": 7499641,
  "type": "Feature",
  "properties": {
    "tgn:hierarchy":[
        "tgn:7499641",
        "tgn:1000004",
        "tgn:7492971",
        "tgn:1000141",
        "tgn:7029392"
    ],
    "tgn:id":7499641,
    "tgn:name":"Mingzheng Guozhong",
    "tgn:placetype":[
        "aat:300006495"
    ]
},
  "bbox": [],
  "geometry": {"coordinates":[120.4979,22.6803],"type":"Point"}
}