{
  "id": 2489377,
  "type": "Feature",
  "properties": {
    "tgn:hierarchy":[
        "tgn:2489377",
        "tgn:1000001",
        "tgn:7012149",
        "tgn:2001036",
        "tgn:7007521",
        "tgn:7029392"
    ],
    "tgn:id":2489377,
    "tgn:name":"Malberg Lake",
    "tgn:placetype":[
        "aat:300008680"
    ]
},
  "bbox": [],
  "geometry": {"coordinates":[-91.1167,47.95],"type":"Point"}
}