{
  "id": 7025780,
  "type": "Feature",
  "properties": {
    "tgn:hierarchy":[
        "tgn:7025780",
        "tgn:7002445",
        "tgn:1000003",
        "tgn:7012077",
        "tgn:7008591",
        "tgn:7029392"
    ],
    "tgn:id":7025780,
    "tgn:name":"Washford Pyne",
    "tgn:placetype":[
        "aat:300008347"
    ]
},
  "bbox": [],
  "geometry": {"coordinates":[-3.6833,50.8833],"type":"Point"}
}