{
  "id": 7588821,
  "type": "Feature",
  "properties": {
    "tgn:hierarchy":[
        "tgn:7588821",
        "tgn:1000004",
        "tgn:7000198",
        "tgn:1001894",
        "tgn:7029392"
    ],
    "tgn:id":7588821,
    "tgn:name:en":"Bamhniaw\u0101n",
    "tgn:placetype":[
        "aat:300008347"
    ]
},
  "bbox": [],
  "geometry": {"coordinates":[81.210403,27.566453],"type":"Point"}
}