{
  "id": 2233023,
  "type": "Feature",
  "properties": {
    "tgn:hierarchy":[
        "tgn:2233023",
        "tgn:1000001",
        "tgn:2002241",
        "tgn:7012149",
        "tgn:7007920",
        "tgn:7029392"
    ],
    "tgn:id":2233023,
    "tgn:name":"Chard Gulch",
    "tgn:placetype":[
        "aat:300008761"
    ]
},
  "bbox": [],
  "geometry": {"coordinates":[-117.85,46.5167],"type":"Point"}
}