<<<<<<< HEAD
{
  "id": 7174088,
  "type": "Feature",
  "properties": {
    "tgn:hierarchy":[
        "tgn:7174088",
        "tgn:1000003",
        "tgn:7003676",
        "tgn:7000084",
        "tgn:7029392"
    ],
    "tgn:id":7174088,
    "tgn:name":"Gro\u00df Lei\u00dfe",
    "tgn:placetype":[
        "aat:300000206"
    ]
},
  "bbox": [],
  "geometry": {"coordinates":[7.566667,53.2],"type":"Point"}
}
=======
{"geometry":{"type":"Point","coordinates":[7.566667,53.200000]},"type":"Feature","properties":{"hierarchy":["tgn:7174088","tgn:1000003","tgn:7003676","tgn:7000084","tgn:7029392"],"placetype":["aat:300000206"],"id":7174088,"name:xx":"Gro\u00df Lei\u00dfe"}}
>>>>>>> 03f74aca74312dbeaf24d7e61306dd6a786dc3d0
