{
  "id": 7448091,
  "type": "Feature",
  "properties": {
    "tgn:hierarchy":[
        "tgn:7448091",
        "tgn:7002445",
        "tgn:1000003",
        "tgn:7008185",
        "tgn:7008591",
        "tgn:7029392"
    ],
    "tgn:id":7448091,
    "tgn:name:en":"Rushbrooke",
    "tgn:placetype":[
        "aat:300008347"
    ]
},
  "bbox": [],
  "geometry": {"coordinates":[0.766667,52.216667],"type":"Point"}
}