{
  "id": 7504041,
  "type": "Feature",
  "properties": {
    "tgn:hierarchy":[
        "tgn:7504041",
        "tgn:1008380",
        "tgn:1000226",
        "tgn:7016827",
        "tgn:1000006",
        "tgn:7029392"
    ],
    "tgn:id":7504041,
    "tgn:name:en":"Werekino Stream",
    "tgn:placetype":[
        "aat:300008699"
    ]
},
  "bbox": [],
  "geometry": {"coordinates":[173.816667,-39.183333],"type":"Point"}
}