{
  "id": 2693219,
  "type": "Feature",
  "properties": {
    "tgn:hierarchy":[
        "tgn:2693219",
        "tgn:1000001",
        "tgn:7012149",
        "tgn:2002119",
        "tgn:7007827",
        "tgn:7029392"
    ],
    "tgn:id":2693219,
    "tgn:name":"Steer Gulch",
    "tgn:placetype":[
        "aat:300008761"
    ]
},
  "bbox": [],
  "geometry": {"coordinates":[-110.1833,37.4833],"type":"Point"}
}