{
  "id": 2746592,
  "type": "Feature",
  "properties": {
    "tgn:hierarchy":[
        "tgn:2746592",
        "tgn:1000001",
        "tgn:2000955",
        "tgn:7012149",
        "tgn:7007520",
        "tgn:7029392"
    ],
    "tgn:id":2746592,
    "tgn:name":"Waco Lake",
    "tgn:placetype":[
        "aat:300008680"
    ]
},
  "bbox": [],
  "geometry": {"coordinates":[-86.7333,46.0333],"type":"Point"}
}