{
  "id": 2298180,
  "type": "Feature",
  "properties": {
    "tgn:hierarchy":[
        "tgn:2298180",
        "tgn:1000001",
        "tgn:7012149",
        "tgn:2000205",
        "tgn:7007158",
        "tgn:7029392"
    ],
    "tgn:id":2298180,
    "tgn:name":"Dry Lakes",
    "tgn:placetype":[
        "aat:300008680"
    ]
},
  "bbox": [],
  "geometry": {"coordinates":[-105.5833,38.0167],"type":"Point"}
}