<<<<<<< HEAD
{
  "id": 2150607,
  "type": "Feature",
  "properties": {
    "tgn:hierarchy":[
        "tgn:2150607",
        "tgn:1000001",
        "tgn:1002284",
        "tgn:7012149",
        "tgn:7007568",
        "tgn:7029392"
    ],
    "tgn:id":2150607,
    "tgn:name":"Basin,the",
    "tgn:placetype":[
        "aat:300386845"
    ]
},
  "bbox": [],
  "geometry": {"coordinates":[-73.6167,44.8667],"type":"Point"}
}
=======
{"geometry":{"type":"Point","coordinates":[-73.616700,44.866700]},"type":"Feature","properties":{"hierarchy":["tgn:2150607","tgn:1000001","tgn:1002284","tgn:7012149","tgn:7007568","tgn:7029392"],"placetype":["aat:300386845"],"id":2150607,"name:xx":"Basin,the"}}
>>>>>>> 03f74aca74312dbeaf24d7e61306dd6a786dc3d0
