{
  "id": 7065667,
  "type": "Feature",
  "properties": {
    "tgn:hierarchy":[
        "tgn:7065667",
        "tgn:1000003",
        "tgn:7003676",
        "tgn:7000084",
        "tgn:7029392"
    ],
    "tgn:id":7065667,
    "tgn:name":"Stellmoor",
    "tgn:placetype":[
        "aat:300000206"
    ]
},
  "bbox": [],
  "geometry": {"coordinates":[9.366667,53.15],"type":"Point"}
}