{
  "id": 7300410,
  "type": "Feature",
  "properties": {
    "tgn:hierarchy":[
        "tgn:7300410",
        "tgn:7002835",
        "tgn:7001158",
        "tgn:1000003",
        "tgn:1000095",
        "tgn:7029392"
    ],
    "tgn:id":7300410,
    "tgn:name":"Torrecilla del R\u00edo",
    "tgn:placetype":[
        "aat:300008347"
    ]
},
  "bbox": [],
  "geometry": {"coordinates":[-5.866667,41.066667],"type":"Point"}
}