{
  "id": 7509508,
  "type": "Feature",
  "properties": {
    "tgn:hierarchy":[
        "tgn:7509508",
        "tgn:1008380",
        "tgn:1000226",
        "tgn:7016827",
        "tgn:1000006",
        "tgn:7029392"
    ],
    "tgn:id":7509508,
    "tgn:name:en":"Waikiekie",
    "tgn:placetype":[
        "aat:300008777"
    ]
},
  "bbox": [],
  "geometry": {"coordinates":[174.583333,-38.85],"type":"Point"}
}