{
  "id": 2242558,
  "type": "Feature",
  "properties": {
    "tgn:hierarchy":[
        "tgn:2242558",
        "tgn:1000001",
        "tgn:7016172",
        "tgn:7012149",
        "tgn:2000127",
        "tgn:7029392"
    ],
    "tgn:id":2242558,
    "tgn:name":"Clear Creek",
    "tgn:placetype":[
        "aat:300008706"
    ]
},
  "bbox": [],
  "geometry": {"coordinates":[-92.1167,35.3333],"type":"Point"}
}