{
  "id": 7078760,
  "type": "Feature",
  "properties": {
    "tgn:hierarchy":[
        "tgn:7078760",
        "tgn:1000003",
        "tgn:7000094",
        "tgn:7000084",
        "tgn:7029392"
    ],
    "tgn:id":7078760,
    "tgn:name":"Witsche-Berg",
    "tgn:placetype":[
        "aat:300008777"
    ]
},
  "bbox": [],
  "geometry": {"coordinates":[14.233333,53.716667],"type":"Point"}
}