{
  "id": 7549576,
  "type": "Feature",
  "properties": {
    "tgn:hierarchy":[
        "tgn:7549576",
        "tgn:1000004",
        "tgn:7000198",
        "tgn:7016788",
        "tgn:7029392"
    ],
    "tgn:id":7549576,
    "tgn:name:en":"Chalkoi",
    "tgn:placetype":[
        "aat:300008347"
    ]
},
  "bbox": [],
  "geometry": {"coordinates":[74.973171,28.520142],"type":"Point"}
}