{
  "id": 1050666,
  "type": "Feature",
  "properties": {
    "tgn:hierarchy":[
        "tgn:1050666",
        "tgn:5000432",
        "tgn:7002444",
        "tgn:1000003",
        "tgn:7008591",
        "tgn:7029392"
    ],
    "tgn:id":1050666,
    "tgn:name:en":"Fetterangus",
    "tgn:placetype":[
        "aat:300008347"
    ]
},
  "bbox": [],
  "geometry": {"coordinates":[-2.016667,57.55],"type":"Point"}
}