{
  "id": 7387494,
  "type": "Feature",
  "properties": {
    "tgn:hierarchy":[
        "tgn:7387494",
        "tgn:1000001",
        "tgn:7005590",
        "tgn:7005560",
        "tgn:7029392"
    ],
    "tgn:id":7387494,
    "tgn:name":"Puerta de Cojumatl\u00e1n",
    "tgn:placetype":[
        "aat:300008347"
    ]
},
  "bbox": [],
  "geometry": {"coordinates":[-102.783333,20.133333],"type":"Point"}
}