{
  "id": 7284068,
  "type": "Feature",
  "properties": {
    "tgn:hierarchy":[
        "tgn:7284068",
        "tgn:1001699",
        "tgn:1000049",
        "tgn:1000002",
        "tgn:7029392"
    ],
    "tgn:id":7284068,
    "tgn:name":"Quinchilca, Sierra de",
    "tgn:placetype":[
        "aat:300008795"
    ]
},
  "bbox": [],
  "geometry": {"coordinates":[-72.05,-39.683333],"type":"Point"}
}