{
  "id": 2726738,
  "type": "Feature",
  "properties": {
    "tgn:hierarchy":[
        "tgn:2726738",
        "tgn:1000001",
        "tgn:7012149",
        "tgn:1002879",
        "tgn:7007252",
        "tgn:7029392"
    ],
    "tgn:id":2726738,
    "tgn:name":"Town Run",
    "tgn:placetype":[
        "aat:300008699"
    ]
},
  "bbox": [],
  "geometry": {"coordinates":[-86.7833,38.6333],"type":"Point"}
}