{
  "id": 2481661,
  "type": "Feature",
  "properties": {
    "tgn:hierarchy":[
        "tgn:2481661",
        "tgn:1000001",
        "tgn:7012149",
        "tgn:1002773",
        "tgn:7007240",
        "tgn:7029392"
    ],
    "tgn:id":2481661,
    "tgn:name":"Land O' Lakes",
    "tgn:placetype":[
        "aat:300008347"
    ]
},
  "bbox": [],
  "geometry": {"coordinates":[-82.45,28.2167],"type":"Point"}
}