{
  "id": 2584379,
  "type": "Feature",
  "properties": {
    "tgn:hierarchy":[
        "tgn:2584379",
        "tgn:1002247",
        "tgn:1000001",
        "tgn:7012149",
        "tgn:7007516",
        "tgn:7029392"
    ],
    "tgn:id":2584379,
    "tgn:name":"Piney Creek",
    "tgn:placetype":[
        "aat:300008706"
    ]
},
  "bbox": [],
  "geometry": {"coordinates":[-75.9333,39.5167],"type":"Point"}
}