{
  "id": 7057498,
  "type": "Feature",
  "properties": {
    "tgn:hierarchy":[
        "tgn:7057498",
        "tgn:1000003",
        "tgn:7003236",
        "tgn:7003144",
        "tgn:1000080",
        "tgn:7029392"
    ],
    "tgn:id":7057498,
    "tgn:name":"Cadibona, Colle di",
    "tgn:placetype":[
        "aat:300259572"
    ]
},
  "bbox": [],
  "geometry": {"coordinates":[8.366667,44.333333],"type":"Point"}
}