{
  "id": 2524966,
  "type": "Feature",
  "properties": {
    "tgn:hierarchy":[
        "tgn:2524966",
        "tgn:1000001",
        "tgn:7012149",
        "tgn:2002195",
        "tgn:7007919",
        "tgn:7029392"
    ],
    "tgn:id":2524966,
    "tgn:name":"Morris Butt Cave",
    "tgn:placetype":[
        "aat:300008746"
    ]
},
  "bbox": [],
  "geometry": {"coordinates":[-82.7167,36.8333],"type":"Point"}
}