{
  "id": 7476464,
  "type": "Feature",
  "properties": {
    "tgn:hierarchy":[
        "tgn:7476464",
        "tgn:7488858",
        "tgn:1000004",
        "tgn:1000141",
        "tgn:7029392"
    ],
    "tgn:id":7476464,
    "tgn:name":"Ahualai Xi",
    "tgn:placetype":[
        "aat:300008699"
    ]
},
  "bbox": [],
  "geometry": {"coordinates":[120.938616,23.803361],"type":"Point"}
}