{
  "id": 7379004,
  "type": "Feature",
  "properties": {
    "tgn:hierarchy":[
        "tgn:7379004",
        "tgn:1000001",
        "tgn:7005599",
        "tgn:7005560",
        "tgn:7029392"
    ],
    "tgn:id":7379004,
    "tgn:name":"Los Robles",
    "tgn:placetype":[
        "aat:300008347"
    ]
},
  "bbox": [],
  "geometry": {"coordinates":[-96.35,18.733333],"type":"Point"}
}