<<<<<<< HEAD
{
  "id": 7379004,
  "type": "Feature",
  "properties": {
    "tgn:hierarchy":[
        "tgn:7379004",
        "tgn:1000001",
        "tgn:7005599",
        "tgn:7005560",
        "tgn:7029392"
    ],
    "tgn:id":7379004,
    "tgn:name":"Los Robles",
    "tgn:placetype":[
        "aat:300008347"
    ]
},
  "bbox": [],
  "geometry": {"coordinates":[-96.35,18.733333],"type":"Point"}
}
=======
{"geometry":{"type":"Point","coordinates":[-96.350000,18.733333]},"type":"Feature","properties":{"hierarchy":["tgn:7379004","tgn:1000001","tgn:7005599","tgn:7005560","tgn:7029392"],"placetype":["aat:300008347"],"id":7379004,"name:xx":"Los Robles"}}
>>>>>>> 03f74aca74312dbeaf24d7e61306dd6a786dc3d0
