{
  "id": 2722204,
  "type": "Feature",
  "properties": {
    "tgn:hierarchy":[
        "tgn:2722204",
        "tgn:1000001",
        "tgn:2001747",
        "tgn:7012149",
        "tgn:7007712",
        "tgn:7029392"
    ],
    "tgn:id":2722204,
    "tgn:name":"Timmons Pond",
    "tgn:placetype":[
        "aat:300006191"
    ]
},
  "bbox": [],
  "geometry": {"coordinates":[-82.5167,35.0167],"type":"Point"}
}