<<<<<<< HEAD
{
  "id": 7365091,
  "type": "Feature",
  "properties": {
    "tgn:hierarchy":[
        "tgn:7365091",
        "tgn:1000001",
        "tgn:7005597",
        "tgn:7005560",
        "tgn:7029392"
    ],
    "tgn:id":7365091,
    "tgn:name":"Rancho El Rame\u00f1o",
    "tgn:placetype":[
        "aat:300000241"
    ]
},
  "bbox": [],
  "geometry": {"coordinates":[-99.25,26.383333],"type":"Point"}
}
=======
{"geometry":{"type":"Point","coordinates":[-99.250000,26.383333]},"type":"Feature","properties":{"hierarchy":["tgn:7365091","tgn:1000001","tgn:7005597","tgn:7005560","tgn:7029392"],"placetype":["aat:300000241"],"id":7365091,"name:xx":"Rancho El Rame\u00f1o"}}
>>>>>>> 03f74aca74312dbeaf24d7e61306dd6a786dc3d0
