{
  "id": 7392287,
  "type": "Feature",
  "properties": {
    "tgn:hierarchy":[
        "tgn:7392287",
        "tgn:1000001",
        "tgn:1001937",
        "tgn:7005560",
        "tgn:7029392"
    ],
    "tgn:id":7392287,
    "tgn:name":"Rat\u00f3n, Cayo",
    "tgn:placetype":[
        "aat:300008791"
    ]
},
  "bbox": [],
  "geometry": {"coordinates":[-86.916667,21.466667],"type":"Point"}
}