{
  "id": 7027453,
  "type": "Feature",
  "properties": {
    "tgn:hierarchy":[
        "tgn:7027453",
        "tgn:7002445",
        "tgn:1000003",
        "tgn:7008154",
        "tgn:7008591",
        "tgn:7029392"
    ],
    "tgn:id":7027453,
    "tgn:name":"Downholland Cross",
    "tgn:placetype":[
        "aat:300008347",
        "aat:300008372"
    ]
},
  "bbox": [],
  "geometry": {"coordinates":[-2.9667,53.55],"type":"Point"}
}