{
  "id": 7321906,
  "type": "Feature",
  "properties": {
    "tgn:hierarchy":[
        "tgn:7321906",
        "tgn:1001699",
        "tgn:1000049",
        "tgn:1000002",
        "tgn:7029392"
    ],
    "tgn:id":7321906,
    "tgn:name":"Cal\u00e9n",
    "tgn:placetype":[
        "aat:300008347"
    ]
},
  "bbox": [],
  "geometry": {"coordinates":[-73.459722,-42.31],"type":"Point"}
}