{
  "id": 1064026,
  "type": "Feature",
  "properties": {
    "tgn:hierarchy":[
        "tgn:1064026",
        "tgn:1000003",
        "tgn:7003755",
        "tgn:7011731",
        "tgn:7029392"
    ],
    "tgn:id":1064026,
    "tgn:name":"Ebnat",
    "tgn:placetype":[
        "aat:300008347"
    ]
},
  "bbox": [],
  "geometry": {"coordinates":[9.1167,47.2667],"type":"Point"}
}