{
  "id": 7219026,
  "type": "Feature",
  "properties": {
    "tgn:hierarchy":[
        "tgn:7219026",
        "tgn:7002753",
        "tgn:7002756",
        "tgn:1000003",
        "tgn:1000074",
        "tgn:7029392"
    ],
    "tgn:id":7219026,
    "tgn:name":"Metax\u00e1des",
    "tgn:placetype":[
        "aat:300008347"
    ]
},
  "bbox": [],
  "geometry": {"coordinates":[26.225278,41.421944],"type":"Point"}
}