<<<<<<< HEAD
{
  "id": 7050733,
  "type": "Feature",
  "properties": {
    "tgn:hierarchy":[
        "tgn:7050733",
        "tgn:1000003",
        "tgn:7003122",
        "tgn:7003157",
        "tgn:1000080",
        "tgn:7029392"
    ],
    "tgn:id":7050733,
    "tgn:name":"Nizza di Sicilia",
    "tgn:placetype":[
        "aat:300008347"
    ]
},
  "bbox": [],
  "geometry": {"coordinates":[15.416667,37.983333],"type":"Point"}
}
=======
{"geometry":{"type":"Point","coordinates":[15.416667,37.983333]},"type":"Feature","properties":{"hierarchy":["tgn:7050733","tgn:1000003","tgn:7003122","tgn:7003157","tgn:1000080","tgn:7029392"],"placetype":["aat:300008347"],"id":7050733,"name:xx":"Nizza di Sicilia"}}
>>>>>>> 03f74aca74312dbeaf24d7e61306dd6a786dc3d0
