<<<<<<< HEAD
{
  "id": 2251365,
  "type": "Feature",
  "properties": {
    "tgn:hierarchy":[
        "tgn:2251365",
        "tgn:1000001",
        "tgn:7012149",
        "tgn:2002191",
        "tgn:7007919",
        "tgn:7029392"
    ],
    "tgn:id":2251365,
    "tgn:name":"Comers Branch",
    "tgn:placetype":[
        "aat:300008699"
    ]
},
  "bbox": [],
  "geometry": {"coordinates":[-81.7667,36.9333],"type":"Point"}
}
=======
{"geometry":{"type":"Point","coordinates":[-81.766700,36.933300]},"type":"Feature","properties":{"hierarchy":["tgn:2251365","tgn:1000001","tgn:7012149","tgn:2002191","tgn:7007919","tgn:7029392"],"placetype":["aat:300008699"],"id":2251365,"name:xx":"Comers Branch"}}
>>>>>>> 03f74aca74312dbeaf24d7e61306dd6a786dc3d0
