<<<<<<< HEAD
{
  "id": 2761758,
  "type": "Feature",
  "properties": {
    "tgn:hierarchy":[
        "tgn:2761758",
        "tgn:1000001",
        "tgn:7012149",
        "tgn:2001115",
        "tgn:7007522",
        "tgn:7029392"
    ],
    "tgn:id":2761758,
    "tgn:name":"West Prong Bayou Casotte",
    "tgn:placetype":[
        "aat:300008699"
    ]
},
  "bbox": [],
  "geometry": {"coordinates":[-88.5167,30.3667],"type":"Point"}
}
=======
{"geometry":{"type":"Point","coordinates":[-88.516700,30.366700]},"type":"Feature","properties":{"hierarchy":["tgn:2761758","tgn:1000001","tgn:7012149","tgn:2001115","tgn:7007522","tgn:7029392"],"placetype":["aat:300008699"],"id":2761758,"name:xx":"West Prong Bayou Casotte"}}
>>>>>>> 03f74aca74312dbeaf24d7e61306dd6a786dc3d0
