{
  "id": 2761758,
  "type": "Feature",
  "properties": {
    "tgn:hierarchy":[
        "tgn:2761758",
        "tgn:1000001",
        "tgn:7012149",
        "tgn:2001115",
        "tgn:7007522",
        "tgn:7029392"
    ],
    "tgn:id":2761758,
    "tgn:name":"West Prong Bayou Casotte",
    "tgn:placetype":[
        "aat:300008699"
    ]
},
  "bbox": [],
  "geometry": {"coordinates":[-88.5167,30.3667],"type":"Point"}
}