{
  "id": 2785796,
  "type": "Feature",
  "properties": {
    "tgn:hierarchy":[
        "tgn:2785796",
        "tgn:1000001",
        "tgn:2000201",
        "tgn:7012149",
        "tgn:7007158",
        "tgn:7029392"
    ],
    "tgn:id":2785796,
    "tgn:name":"York Gulch",
    "tgn:placetype":[
        "aat:300008761"
    ]
},
  "bbox": [],
  "geometry": {"coordinates":[-105.55,39.7833],"type":"Point"}
}