{
  "id": 7524059,
  "type": "Feature",
  "properties": {
    "tgn:hierarchy":[
        "tgn:7524059",
        "tgn:7001242",
        "tgn:7016833",
        "tgn:1001092",
        "tgn:7029392"
    ],
    "tgn:id":7524059,
    "tgn:name":"Al Manzalah",
    "tgn:placetype":[
        "aat:300008347"
    ]
},
  "bbox": [],
  "geometry": {"coordinates":[31.249462,30.339609],"type":"Point"}
}