{
  "id": 2754052,
  "type": "Feature",
  "properties": {
    "tgn:hierarchy":[
        "tgn:2754052",
        "tgn:1000001",
        "tgn:7012149",
        "tgn:2000346",
        "tgn:7007248",
        "tgn:7029392"
    ],
    "tgn:id":2754052,
    "tgn:name":"Watson Mountain",
    "tgn:placetype":[
        "aat:300008798"
    ]
},
  "bbox": [],
  "geometry": {"coordinates":[-84.2333,34.9667],"type":"Point"}
}