<<<<<<< HEAD
{
  "id": 2768948,
  "type": "Feature",
  "properties": {
    "tgn:hierarchy":[
        "tgn:2768948",
        "tgn:1000001",
        "tgn:7012149",
        "tgn:1002368",
        "tgn:7007919",
        "tgn:7029392"
    ],
    "tgn:id":2768948,
    "tgn:name":"Whitney State Forest",
    "tgn:placetype":[
        "aat:300008863"
    ]
},
  "bbox": [],
  "geometry": {"coordinates":[-77.8,38.6667],"type":"Point"}
}
=======
{"geometry":{"type":"Point","coordinates":[-77.800000,38.666700]},"type":"Feature","properties":{"hierarchy":["tgn:2768948","tgn:1000001","tgn:7012149","tgn:1002368","tgn:7007919","tgn:7029392"],"placetype":["aat:300008863"],"id":2768948,"name:xx":"Whitney State Forest"}}
>>>>>>> 03f74aca74312dbeaf24d7e61306dd6a786dc3d0
