{
  "id": 2378925,
  "type": "Feature",
  "properties": {
    "tgn:hierarchy":[
        "tgn:2378925",
        "tgn:1000001",
        "tgn:7012149",
        "tgn:2000227",
        "tgn:7007158",
        "tgn:7029392"
    ],
    "tgn:id":2378925,
    "tgn:name":"Hart Spring",
    "tgn:placetype":[
        "aat:300008697"
    ]
},
  "bbox": [],
  "geometry": {"coordinates":[-103.6833,37.0833],"type":"Point"}
}