{
  "id": 2104847,
  "type": "Feature",
  "properties": {
    "tgn:hierarchy":[
        "tgn:2104847",
        "tgn:1000001",
        "tgn:7012149",
        "tgn:2001997",
        "tgn:7007826",
        "tgn:7029392"
    ],
    "tgn:id":2104847,
    "tgn:name":"Hitchland",
    "tgn:placetype":[
        "aat:300008347",
        "aat:300387210"
    ]
},
  "bbox": [],
  "geometry": {"coordinates":[-101.3167,36.4833],"type":"Point"}
}