{
  "id": 7140399,
  "type": "Feature",
  "properties": {
    "tgn:hierarchy":[
        "tgn:7140399",
        "tgn:1000003",
        "tgn:7003677",
        "tgn:7000084",
        "tgn:7029392"
    ],
    "tgn:id":7140399,
    "tgn:name":"Lutternsche Egge",
    "tgn:placetype":[
        "aat:300008777"
    ]
},
  "bbox": [],
  "geometry": {"coordinates":[8.816667,52.266667],"type":"Point"}
}