{
  "id": 1075083,
  "type": "Feature",
  "properties": {
    "tgn:hierarchy":[
        "tgn:1075083",
        "tgn:1000004",
        "tgn:7000198",
        "tgn:7016788",
        "tgn:7029392"
    ],
    "tgn:id":1075083,
    "tgn:name:en":"Dausa",
    "tgn:placetype":[
        "aat:300008347"
    ]
},
  "bbox": [],
  "geometry": {"coordinates":[76.338594,26.892978],"type":"Point"}
}