{
  "id": 2675562,
  "type": "Feature",
  "properties": {
    "tgn:hierarchy":[
        "tgn:2675562",
        "tgn:1000001",
        "tgn:1002305",
        "tgn:7012149",
        "tgn:7007920",
        "tgn:7029392"
    ],
    "tgn:id":2675562,
    "tgn:name":"Solo, Mount",
    "tgn:placetype":[
        "aat:300008798"
    ]
},
  "bbox": [],
  "geometry": {"coordinates":[-122.9833,46.15],"type":"Point"}
}