{
  "id": 7223364,
  "type": "Feature",
  "properties": {
    "tgn:hierarchy":[
        "tgn:7223364",
        "tgn:7002728",
        "tgn:7002715",
        "tgn:1000003",
        "tgn:1000074",
        "tgn:7029392"
    ],
    "tgn:id":7223364,
    "tgn:name":"Plat\u00e1ni",
    "tgn:placetype":[
        "aat:300008347"
    ]
},
  "bbox": [],
  "geometry": {"coordinates":[22.046389,40.760833],"type":"Point"}
}