{
  "id": 2664871,
  "type": "Feature",
  "properties": {
    "tgn:hierarchy":[
        "tgn:2664871",
        "tgn:1000001",
        "tgn:7013677",
        "tgn:7012149",
        "tgn:7007712",
        "tgn:7029392"
    ],
    "tgn:id":2664871,
    "tgn:name":"Simons Lake",
    "tgn:placetype":[
        "aat:300006191"
    ]
},
  "bbox": [],
  "geometry": {"coordinates":[-81.8667,33.6333],"type":"Point"}
}