{
  "id": 7315983,
  "type": "Feature",
  "properties": {
    "tgn:hierarchy":[
        "tgn:7315983",
        "tgn:7002464",
        "tgn:1000049",
        "tgn:1000002",
        "tgn:7029392"
    ],
    "tgn:id":7315983,
    "tgn:name":"Caya, Quebrada de",
    "tgn:placetype":[
        "aat:300266554",
        "aat:300008699"
    ]
},
  "bbox": [],
  "geometry": {"coordinates":[-68.966667,-20.616667],"type":"Point"}
}