{
  "id": 7568069,
  "type": "Feature",
  "properties": {
    "tgn:hierarchy":[
        "tgn:7568069",
        "tgn:1000004",
        "tgn:1001869",
        "tgn:7000198",
        "tgn:7029392"
    ],
    "tgn:id":7568069,
    "tgn:name:en":"Roji Bet",
    "tgn:placetype":[
        "aat:300008791"
    ]
},
  "bbox": [],
  "geometry": {"coordinates":[69.427778,22.306111],"type":"Point"}
}