{
  "id": 7553710,
  "type": "Feature",
  "properties": {
    "tgn:hierarchy":[
        "tgn:7553710",
        "tgn:1000004",
        "tgn:7000198",
        "tgn:1001894",
        "tgn:7029392"
    ],
    "tgn:id":7553710,
    "tgn:name:en":"Murw\u0101ra",
    "tgn:placetype":[
        "aat:300008347"
    ]
},
  "bbox": [],
  "geometry": {"coordinates":[80.394824,23.836774],"type":"Point"}
}