{
  "id": 2368500,
  "type": "Feature",
  "properties": {
    "tgn:hierarchy":[
        "tgn:2368500",
        "tgn:1000001",
        "tgn:7012149",
        "tgn:2001750",
        "tgn:7007712",
        "tgn:7029392"
    ],
    "tgn:id":2368500,
    "tgn:name":"Guiton Crossing",
    "tgn:placetype":[
        "aat:300008347"
    ]
},
  "bbox": [],
  "geometry": {"coordinates":[-79.1333,33.85],"type":"Point"}
}