<<<<<<< HEAD
{
  "id": 2255161,
  "type": "Feature",
  "properties": {
    "tgn:hierarchy":[
        "tgn:2255161",
        "tgn:1000001",
        "tgn:7016172",
        "tgn:7012149",
        "tgn:2000147",
        "tgn:7029392"
    ],
    "tgn:id":2255161,
    "tgn:name":"Cooper Lake",
    "tgn:placetype":[
        "aat:300006191"
    ]
},
  "bbox": [],
  "geometry": {"coordinates":[-92.0333,34.9833],"type":"Point"}
}
=======
{"geometry":{"type":"Point","coordinates":[-92.033300,34.983300]},"type":"Feature","properties":{"hierarchy":["tgn:2255161","tgn:1000001","tgn:7016172","tgn:7012149","tgn:2000147","tgn:7029392"],"placetype":["aat:300006191"],"id":2255161,"name:xx":"Cooper Lake"}}
>>>>>>> 03f74aca74312dbeaf24d7e61306dd6a786dc3d0
