{
  "id": 7046045,
  "type": "Feature",
  "properties": {
    "tgn:hierarchy":[
        "tgn:7046045",
        "tgn:1003506",
        "tgn:1000003",
        "tgn:7002993",
        "tgn:1000080",
        "tgn:7029392"
    ],
    "tgn:id":7046045,
    "tgn:name":"Cassacco",
    "tgn:placetype":[
        "aat:300008347"
    ]
},
  "bbox": [],
  "geometry": {"coordinates":[13.156111,46.168056],"type":"Point"}
}