{
  "id": 7519710,
  "type": "Feature",
  "properties": {
    "tgn:hierarchy":[
        "tgn:7519710",
        "tgn:1009227",
        "tgn:1000226",
        "tgn:1000006",
        "tgn:7016850",
        "tgn:7029392"
    ],
    "tgn:id":7519710,
    "tgn:name:en":"Blackwater",
    "tgn:placetype":[
        "aat:300008347"
    ]
},
  "bbox": [],
  "geometry": {"coordinates":[171.766667,-42.25],"type":"Point"}
}