{
  "id": 7267886,
  "type": "Feature",
  "properties": {
    "tgn:concordances":{
        "gn:id":"2748116"
    },
    "tgn:hierarchy":[
        "tgn:7267886",
        "tgn:1000003",
        "tgn:7003632",
        "tgn:7016845",
        "tgn:7029392"
    ],
    "tgn:id":7267886,
    "tgn:name:nl":"Rijndijk",
    "tgn:placetype":[
        "aat:300008347"
    ]
},
  "bbox": [],
  "geometry": {"coordinates":[4.45,52.15],"type":"Point"}
}