{
  "id": 2639605,
  "type": "Feature",
  "properties": {
    "tgn:hierarchy":[
        "tgn:2639605",
        "tgn:1000001",
        "tgn:7012149",
        "tgn:7007712",
        "tgn:7029392"
    ],
    "tgn:id":2639605,
    "tgn:name":"Saluda Lake",
    "tgn:placetype":[
        "aat:300006191"
    ]
},
  "bbox": [],
  "geometry": {"coordinates":[-82.4833,34.85],"type":"Point"}
}