{
  "id": 2391756,
  "type": "Feature",
  "properties": {
    "tgn:hierarchy":[
        "tgn:2391756",
        "tgn:1000001",
        "tgn:7012149",
        "tgn:2000488",
        "tgn:7007250",
        "tgn:7029392"
    ],
    "tgn:id":2391756,
    "tgn:name":"Hillside Spring",
    "tgn:placetype":[
        "aat:300008697"
    ]
},
  "bbox": [],
  "geometry": {"coordinates":[-116.6667,42.5667],"type":"Point"}
}