<<<<<<< HEAD
{
  "id": 7020314,
  "type": "Feature",
  "properties": {
    "tgn:hierarchy":[
        "tgn:7020314",
        "tgn:1000001",
        "tgn:7012149",
        "tgn:2000837",
        "tgn:7007255",
        "tgn:7029392"
    ],
    "tgn:id":7020314,
    "tgn:name":"Newsome Branch",
    "tgn:placetype":[
        "aat:300008699"
    ]
},
  "bbox": [],
  "geometry": {"coordinates":[-82.5333,37.3167],"type":"Point"}
}
=======
{"geometry":{"type":"Point","coordinates":[-82.533300,37.316700]},"type":"Feature","properties":{"hierarchy":["tgn:7020314","tgn:1000001","tgn:7012149","tgn:2000837","tgn:7007255","tgn:7029392"],"placetype":["aat:300008699"],"id":7020314,"name:xx":"Newsome Branch"}}
>>>>>>> 03f74aca74312dbeaf24d7e61306dd6a786dc3d0
