{
  "id": 7218273,
  "type": "Feature",
  "properties": {
    "tgn:hierarchy":[
        "tgn:7218273",
        "tgn:7011171",
        "tgn:7001395",
        "tgn:1000003",
        "tgn:1000074",
        "tgn:7029392"
    ],
    "tgn:id":7218273,
    "tgn:name":"Dhiap\u00f3ri, Orm\u00edskos",
    "tgn:placetype":[
        "aat:300185707"
    ]
},
  "bbox": [],
  "geometry": {"coordinates":[24.515278,38.845833],"type":"Point"}
}