{
  "id": 2159494,
  "type": "Feature",
  "properties": {
    "tgn:hierarchy":[
        "tgn:2159494",
        "tgn:1000001",
        "tgn:7016172",
        "tgn:7012149",
        "tgn:2000179",
        "tgn:7029392"
    ],
    "tgn:id":2159494,
    "tgn:name":"Bee Knob",
    "tgn:placetype":[
        "aat:300008798"
    ]
},
  "bbox": [],
  "geometry": {"coordinates":[-93.6833,34.8167],"type":"Point"}
}