{
  "id": 7566210,
  "type": "Feature",
  "properties": {
    "tgn:hierarchy":[
        "tgn:7566210",
        "tgn:1000004",
        "tgn:7000198",
        "tgn:7016722",
        "tgn:7029392"
    ],
    "tgn:id":7566210,
    "tgn:name:en":"S\u0101ran",
    "tgn:placetype":[
        "aat:300008347"
    ]
},
  "bbox": [],
  "geometry": {"coordinates":[79.032518,25.711622],"type":"Point"}
}