<<<<<<< HEAD
{
  "id": 7058222,
  "type": "Feature",
  "properties": {
    "tgn:hierarchy":[
        "tgn:7058222",
        "tgn:7009084",
        "tgn:7004154",
        "tgn:1000003",
        "tgn:1000080",
        "tgn:7029392"
    ],
    "tgn:id":7058222,
    "tgn:name":"Antrosano",
    "tgn:placetype":[
        "aat:300008347"
    ]
},
  "bbox": [],
  "geometry": {"coordinates":[13.4,42.066667],"type":"Point"}
}
=======
{"geometry":{"type":"Point","coordinates":[13.400000,42.066667]},"type":"Feature","properties":{"hierarchy":["tgn:7058222","tgn:7009084","tgn:7004154","tgn:1000003","tgn:1000080","tgn:7029392"],"placetype":["aat:300008347"],"id":7058222,"name:xx":"Antrosano"}}
>>>>>>> 03f74aca74312dbeaf24d7e61306dd6a786dc3d0
