<<<<<<< HEAD
{
  "id": 7027111,
  "type": "Feature",
  "properties": {
    "tgn:hierarchy":[
        "tgn:7027111",
        "tgn:7002445",
        "tgn:1000003",
        "tgn:7008143",
        "tgn:7008591",
        "tgn:7029392"
    ],
    "tgn:id":7027111,
    "tgn:name:en":"Preston on Wye",
    "tgn:placetype":[
        "aat:300008347",
        "aat:300008372"
    ]
},
  "bbox": [],
  "geometry": {"coordinates":[-2.9,52.066667],"type":"Point"}
}
=======
{"geometry":{"type":"Point","coordinates":[-2.900000,52.066667]},"type":"Feature","properties":{"hierarchy":["tgn:7027111","tgn:7002445","tgn:1000003","tgn:7008143","tgn:7008591","tgn:7029392"],"placetype":["aat:300008347","aat:300008372"],"name:en":"Preston on Wye","id":7027111}}
>>>>>>> 03f74aca74312dbeaf24d7e61306dd6a786dc3d0
