{
  "id": 1076942,
  "type": "Feature",
  "properties": {
    "tgn:hierarchy":[
        "tgn:1076942",
        "tgn:1000004",
        "tgn:7000198",
        "tgn:7016722",
        "tgn:7029392"
    ],
    "tgn:id":1076942,
    "tgn:name:en":"Shikoh\u0101b\u0101d",
    "tgn:placetype":[
        "aat:300008347"
    ]
},
  "bbox": [],
  "geometry": {"coordinates":[78.586746,27.10813],"type":"Point"}
}