{
  "id": 2218674,
  "type": "Feature",
  "properties": {
    "tgn:hierarchy":[
        "tgn:2218674",
        "tgn:1000001",
        "tgn:7012149",
        "tgn:2001885",
        "tgn:7007825",
        "tgn:7029392"
    ],
    "tgn:id":2218674,
    "tgn:name":"Cane Creek Number Three Lake",
    "tgn:placetype":[
        "aat:300006191"
    ]
},
  "bbox": [],
  "geometry": {"coordinates":[-89.65,35.75],"type":"Point"}
}