{
  "id": 7272396,
  "type": "Feature",
  "properties": {
    "tgn:hierarchy":[
        "tgn:7272396",
        "tgn:1000003",
        "tgn:7003613",
        "tgn:7016845",
        "tgn:7029392"
    ],
    "tgn:id":7272396,
    "tgn:name:nl":"Vierhuizergat",
    "tgn:placetype":[
        "aat:300387026"
    ]
},
  "bbox": [],
  "geometry": {"coordinates":[6.266667,53.416667],"type":"Point"}
}