{
  "id": 1030559,
  "type": "Feature",
  "properties": {
    "tgn:hierarchy":[
        "tgn:1030559",
        "tgn:7002445",
        "tgn:1000003",
        "tgn:7008153",
        "tgn:7008591",
        "tgn:7029392"
    ],
    "tgn:id":1030559,
    "tgn:name:en":"Seal",
    "tgn:placetype":[
        "aat:300008347",
        "aat:300008372"
    ]
},
  "bbox": [],
  "geometry": {"coordinates":[0.216667,51.283333],"type":"Point"}
}