{
  "id": 2374392,
  "type": "Feature",
  "properties": {
    "tgn:hierarchy":[
        "tgn:2374392",
        "tgn:1000001",
        "tgn:7012149",
        "tgn:7007517",
        "tgn:7029392"
    ],
    "tgn:id":2374392,
    "tgn:name":"Hampton Ponds",
    "tgn:placetype":[
        "aat:300008680"
    ]
},
  "bbox": [],
  "geometry": {"coordinates":[-72.6833,42.1667],"type":"Point"}
}