{
  "id": 7277336,
  "type": "Feature",
  "properties": {
    "tgn:hierarchy":[
        "tgn:7277336",
        "tgn:1001702",
        "tgn:1000049",
        "tgn:1000002",
        "tgn:7029392"
    ],
    "tgn:id":7277336,
    "tgn:name":"Lauta, Seno",
    "tgn:placetype":[
        "aat:300008713"
    ]
},
  "bbox": [],
  "geometry": {"coordinates":[-67.633333,-54.933333],"type":"Point"}
}