{
  "id": 7400671,
  "type": "Feature",
  "properties": {
    "tgn:hierarchy":[
        "tgn:7400671",
        "tgn:1000001",
        "tgn:7005599",
        "tgn:7005560",
        "tgn:7029392"
    ],
    "tgn:id":7400671,
    "tgn:name":"Pago Gacho",
    "tgn:placetype":[
        "aat:300008347"
    ]
},
  "bbox": [],
  "geometry": {"coordinates":[-96.323611,18.75],"type":"Point"}
}