{
  "id": 2666518,
  "type": "Feature",
  "properties": {
    "tgn:hierarchy":[
        "tgn:2666518",
        "tgn:1000001",
        "tgn:2001430",
        "tgn:7012149",
        "tgn:7007566",
        "tgn:7029392"
    ],
    "tgn:id":2666518,
    "tgn:name":"Sixmile Hill",
    "tgn:placetype":[
        "aat:300266640"
    ]
},
  "bbox": [],
  "geometry": {"coordinates":[-104.6167,33.3833],"type":"Point"}
}