{
  "id": 2133781,
  "type": "Feature",
  "properties": {
    "tgn:hierarchy":[
        "tgn:2133781",
        "tgn:1000001",
        "tgn:7012149",
        "tgn:2001312",
        "tgn:7007524",
        "tgn:7029392"
    ],
    "tgn:id":2133781,
    "tgn:name":"Andys Spring",
    "tgn:placetype":[
        "aat:300008697"
    ]
},
  "bbox": [],
  "geometry": {"coordinates":[-107.1667,47.85],"type":"Point"}
}