{
  "id": 7381895,
  "type": "Feature",
  "properties": {
    "tgn:hierarchy":[
        "tgn:7381895",
        "tgn:1000001",
        "tgn:7005595",
        "tgn:7005560",
        "tgn:7029392"
    ],
    "tgn:id":7381895,
    "tgn:name":"Los Balamotes",
    "tgn:placetype":[
        "aat:300008347"
    ]
},
  "bbox": [],
  "geometry": {"coordinates":[-106.766111,24.440278],"type":"Point"}
}