<<<<<<< HEAD
{
  "id": 2762358,
  "type": "Feature",
  "properties": {
    "tgn:hierarchy":[
        "tgn:2762358",
        "tgn:1000001",
        "tgn:7006451",
        "tgn:7012149",
        "tgn:2000103",
        "tgn:7029392"
    ],
    "tgn:id":2762358,
    "tgn:name":"West Trick Tank",
    "tgn:placetype":[
        "aat:300006191"
    ]
},
  "bbox": [],
  "geometry": {"coordinates":[-112.4833,34.2667],"type":"Point"}
}
=======
{"geometry":{"type":"Point","coordinates":[-112.483300,34.266700]},"type":"Feature","properties":{"hierarchy":["tgn:2762358","tgn:1000001","tgn:7006451","tgn:7012149","tgn:2000103","tgn:7029392"],"placetype":["aat:300006191"],"id":2762358,"name:xx":"West Trick Tank"}}
>>>>>>> 03f74aca74312dbeaf24d7e61306dd6a786dc3d0
