{
  "id": 7386722,
  "type": "Feature",
  "properties": {
    "tgn:hierarchy":[
        "tgn:7386722",
        "tgn:1001835",
        "tgn:1000001",
        "tgn:7005560",
        "tgn:7029392"
    ],
    "tgn:id":7386722,
    "tgn:name":"Playa del Estero",
    "tgn:placetype":[
        "aat:300008347"
    ]
},
  "bbox": [],
  "geometry": {"coordinates":[-116.616667,31.766667],"type":"Point"}
}