<<<<<<< HEAD
{
  "id": 7356573,
  "type": "Feature",
  "properties": {
    "tgn:hierarchy":[
        "tgn:7356573",
        "tgn:1000001",
        "tgn:1001906",
        "tgn:7005560",
        "tgn:7029392"
    ],
    "tgn:id":7356573,
    "tgn:name":"Camich\u00edn de Jauja",
    "tgn:placetype":[
        "aat:300008347"
    ]
},
  "bbox": [],
  "geometry": {"coordinates":[-104.766667,21.016667],"type":"Point"}
}
=======
{"geometry":{"type":"Point","coordinates":[-104.766667,21.016667]},"type":"Feature","properties":{"hierarchy":["tgn:7356573","tgn:1000001","tgn:1001906","tgn:7005560","tgn:7029392"],"placetype":["aat:300008347"],"id":7356573,"name:xx":"Camich\u00edn de Jauja"}}
>>>>>>> 03f74aca74312dbeaf24d7e61306dd6a786dc3d0
