{
  "id": 2687963,
  "type": "Feature",
  "properties": {
    "tgn:hierarchy":[
        "tgn:2687963",
        "tgn:1000001",
        "tgn:2000923",
        "tgn:7012149",
        "tgn:7007515",
        "tgn:7029392"
    ],
    "tgn:id":2687963,
    "tgn:name":"Springer Hill",
    "tgn:placetype":[
        "aat:300008798"
    ]
},
  "bbox": [],
  "geometry": {"coordinates":[-69.95,44.15],"type":"Point"}
}