{
  "id": 7056620,
  "type": "Feature",
  "properties": {
    "tgn:hierarchy":[
        "tgn:7056620",
        "tgn:7003164",
        "tgn:1000003",
        "tgn:7009760",
        "tgn:1000080",
        "tgn:7029392"
    ],
    "tgn:id":7056620,
    "tgn:name":"Africa, Scoglio d'",
    "tgn:placetype":[
        "aat:300011692"
    ]
},
  "bbox": [],
  "geometry": {"coordinates":[10.066667,42.35],"type":"Point"}
}