{
  "id": 2503768,
  "type": "Feature",
  "properties": {
    "tgn:hierarchy":[
        "tgn:2503768",
        "tgn:1000001",
        "tgn:7012149",
        "tgn:2001493",
        "tgn:7007709",
        "tgn:7029392"
    ],
    "tgn:id":2503768,
    "tgn:name":"Meadow Brook",
    "tgn:placetype":[
        "aat:300008347"
    ]
},
  "bbox": [],
  "geometry": {"coordinates":[-77.75,35.9333],"type":"Point"}
}