{
  "id": 7030131,
  "type": "Feature",
  "properties": {
    "tgn:hierarchy":[
        "tgn:7030131",
        "tgn:7002445",
        "tgn:1000003",
        "tgn:7008154",
        "tgn:7008591",
        "tgn:7029392"
    ],
    "tgn:id":7030131,
    "tgn:name:ang":"Neuhuse",
    "tgn:placetype":[
        "aat:300008347"
    ]
},
  "bbox": [],
  "geometry": {"coordinates":[-2.237,53.951],"type":"Point"}
}