{
  "id": 7557866,
  "type": "Feature",
  "properties": {
    "tgn:hierarchy":[
        "tgn:7557866",
        "tgn:1000004",
        "tgn:7000198",
        "tgn:7016788",
        "tgn:7029392"
    ],
    "tgn:id":7557866,
    "tgn:name:en":"Ransigaon",
    "tgn:placetype":[
        "aat:300008347"
    ]
},
  "bbox": [],
  "geometry": {"coordinates":[73.752495,26.359022],"type":"Point"}
}