<<<<<<< HEAD
{
  "id": 2768940,
  "type": "Feature",
  "properties": {
    "tgn:hierarchy":[
        "tgn:2768940",
        "tgn:1000001",
        "tgn:1002278",
        "tgn:7012149",
        "tgn:7007710",
        "tgn:7029392"
    ],
    "tgn:id":2768940,
    "tgn:name":"Whitney Run",
    "tgn:placetype":[
        "aat:300008699"
    ]
},
  "bbox": [],
  "geometry": {"coordinates":[-78.5333,41.1167],"type":"Point"}
}
=======
{"geometry":{"type":"Point","coordinates":[-78.533300,41.116700]},"type":"Feature","properties":{"hierarchy":["tgn:2768940","tgn:1000001","tgn:1002278","tgn:7012149","tgn:7007710","tgn:7029392"],"placetype":["aat:300008699"],"id":2768940,"name:xx":"Whitney Run"}}
>>>>>>> 03f74aca74312dbeaf24d7e61306dd6a786dc3d0
