{
  "id": 7106312,
  "type": "Feature",
  "properties": {
    "tgn:hierarchy":[
        "tgn:7106312",
        "tgn:1000003",
        "tgn:7003687",
        "tgn:7000084",
        "tgn:7029392"
    ],
    "tgn:id":7106312,
    "tgn:name":"Schmiedeberger Stadtforst",
    "tgn:placetype":[
        "aat:300008863"
    ]
},
  "bbox": [],
  "geometry": {"coordinates":[12.666667,51.666667],"type":"Point"}
}