<<<<<<< HEAD
{
  "id": 7111903,
  "type": "Feature",
  "properties": {
    "tgn:hierarchy":[
        "tgn:7111903",
        "tgn:1000003",
        "tgn:7003676",
        "tgn:7000084",
        "tgn:7029392"
    ],
    "tgn:id":7111903,
    "tgn:name":"Ribbesb\u00fcttel",
    "tgn:placetype":[
        "aat:300008347"
    ]
},
  "bbox": [],
  "geometry": {"coordinates":[10.516667,52.433333],"type":"Point"}
}
=======
{"geometry":{"type":"Point","coordinates":[10.516667,52.433333]},"type":"Feature","properties":{"hierarchy":["tgn:7111903","tgn:1000003","tgn:7003676","tgn:7000084","tgn:7029392"],"placetype":["aat:300008347"],"id":7111903,"name:xx":"Ribbesb\u00fcttel"}}
>>>>>>> 03f74aca74312dbeaf24d7e61306dd6a786dc3d0
