{
  "id": 2502911,
  "type": "Feature",
  "properties": {
    "tgn:hierarchy":[
        "tgn:2502911",
        "tgn:1000001",
        "tgn:7012149",
        "tgn:2001950",
        "tgn:7007826",
        "tgn:7029392"
    ],
    "tgn:id":2502911,
    "tgn:name":"McMullen Lake",
    "tgn:placetype":[
        "aat:300008680"
    ]
},
  "bbox": [],
  "geometry": {"coordinates":[-96.7833,28.2333],"type":"Point"}
}