{
  "id": 7455593,
  "type": "Feature",
  "properties": {
    "tgn:hierarchy":[
        "tgn:7455593",
        "tgn:7002444",
        "tgn:1000003",
        "tgn:7008082",
        "tgn:7008591",
        "tgn:7029392"
    ],
    "tgn:id":7455593,
    "tgn:name:en":"Castle Girnigoe",
    "tgn:placetype":[
        "aat:300008057"
    ]
},
  "bbox": [],
  "geometry": {"coordinates":[-3.05,58.483333],"type":"Point"}
}