{
  "id": 7481415,
  "type": "Feature",
  "properties": {
    "tgn:hierarchy":[
        "tgn:7481415",
        "tgn:1000004",
        "tgn:7491221",
        "tgn:1000141",
        "tgn:7029392"
    ],
    "tgn:id":7481415,
    "tgn:name":"Gangkui Yan",
    "tgn:placetype":[
        "aat:300011692"
    ]
},
  "bbox": [],
  "geometry": {"coordinates":[121.597778,22.023889],"type":"Point"}
}