{
  "id": 2162360,
  "type": "Feature",
  "properties": {
    "tgn:hierarchy":[
        "tgn:2162360",
        "tgn:1000001",
        "tgn:7012149",
        "tgn:2002123",
        "tgn:7007827",
        "tgn:7029392"
    ],
    "tgn:id":2162360,
    "tgn:name":"Ben Allen Canyon",
    "tgn:placetype":[
        "aat:300008761"
    ]
},
  "bbox": [],
  "geometry": {"coordinates":[-112.4833,40.8667],"type":"Point"}
}