{
  "id": 7093744,
  "type": "Feature",
  "properties": {
    "tgn:hierarchy":[
        "tgn:7093744",
        "tgn:7000096",
        "tgn:1000003",
        "tgn:7000084",
        "tgn:7029392"
    ],
    "tgn:id":7093744,
    "tgn:name":"Schwabeck",
    "tgn:placetype":[
        "aat:300008347"
    ]
},
  "bbox": [],
  "geometry": {"coordinates":[12.816667,52.033333],"type":"Point"}
}