{
  "id": 2224938,
  "type": "Feature",
  "properties": {
    "tgn:hierarchy":[
        "tgn:2224938",
        "tgn:1000001",
        "tgn:7012149",
        "tgn:2001461",
        "tgn:7007568",
        "tgn:7029392"
    ],
    "tgn:id":2224938,
    "tgn:name":"Cassidy Brook",
    "tgn:placetype":[
        "aat:300008699"
    ]
},
  "bbox": [],
  "geometry": {"coordinates":[-73.5167,44.45],"type":"Point"}
}