{
  "id": 2107628,
  "type": "Feature",
  "properties": {
    "tgn:hierarchy":[
        "tgn:2107628",
        "tgn:1000001",
        "tgn:7012149",
        "tgn:1002456",
        "tgn:7007826",
        "tgn:7029392"
    ],
    "tgn:id":2107628,
    "tgn:name":"Sheldon",
    "tgn:placetype":[
        "aat:300008347"
    ]
},
  "bbox": [],
  "geometry": {"coordinates":[-95.1167,29.8667],"type":"Point"}
}