{
  "id": 2277967,
  "type": "Feature",
  "properties": {
    "tgn:hierarchy":[
        "tgn:2277967",
        "tgn:1000001",
        "tgn:7012149",
        "tgn:2001036",
        "tgn:7007521",
        "tgn:7029392"
    ],
    "tgn:id":2277967,
    "tgn:name":"Day Hill",
    "tgn:placetype":[
        "aat:300008798"
    ]
},
  "bbox": [],
  "geometry": {"coordinates":[-91.3833,47.1833],"type":"Point"}
}