{
  "id": 7259196,
  "type": "Feature",
  "properties": {
    "tgn:hierarchy":[
        "tgn:7259196",
        "tgn:7003456",
        "tgn:1000003",
        "tgn:1000063",
        "tgn:7018236",
        "tgn:7029392"
    ],
    "tgn:id":7259196,
    "tgn:name":"Vlimmeren",
    "tgn:placetype":[
        "aat:300008347"
    ]
},
  "bbox": [],
  "geometry": {"coordinates":[4.781535,51.297698],"type":"Point"}
}