<<<<<<< HEAD
{
  "id": 7242672,
  "type": "Feature",
  "properties": {
    "tgn:hierarchy":[
        "tgn:7242672",
        "tgn:7003460",
        "tgn:1000003",
        "tgn:1000063",
        "tgn:4012014",
        "tgn:7029392"
    ],
    "tgn:id":7242672,
    "tgn:name":"Lontzen",
    "tgn:placetype":[
        "aat:300008347"
    ]
},
  "bbox": [],
  "geometry": {"coordinates":[6.0,50.683333],"type":"Point"}
}
=======
{"geometry":{"type":"Point","coordinates":[6.000000,50.683333]},"type":"Feature","properties":{"hierarchy":["tgn:7242672","tgn:7003460","tgn:1000003","tgn:1000063","tgn:4012014","tgn:7029392"],"placetype":["aat:300008347"],"id":7242672,"name:xx":"Lontzen"}}
>>>>>>> 03f74aca74312dbeaf24d7e61306dd6a786dc3d0
