{
  "id": 2496258,
  "type": "Feature",
  "properties": {
    "tgn:hierarchy":[
        "tgn:2496258",
        "tgn:1000001",
        "tgn:7012149",
        "tgn:7007157",
        "tgn:7014475",
        "tgn:7029392"
    ],
    "tgn:id":2496258,
    "tgn:name":"Matadero Canal",
    "tgn:placetype":[
        "aat:300006075"
    ]
},
  "bbox": [],
  "geometry": {"coordinates":[-122.1167,37.4167],"type":"Point"}
}