{
  "id": 7356480,
  "type": "Feature",
  "properties": {
    "tgn:hierarchy":[
        "tgn:7356480",
        "tgn:1000001",
        "tgn:7005600",
        "tgn:7005560",
        "tgn:7029392"
    ],
    "tgn:id":7356480,
    "tgn:name":"Chimay",
    "tgn:placetype":[
        "aat:300008347"
    ]
},
  "bbox": [],
  "geometry": {"coordinates":[-88.966667,21.183333],"type":"Point"}
}