{
  "id": 1018890,
  "type": "Feature",
  "properties": {
    "tgn:hierarchy":[
        "tgn:1018890",
        "tgn:1001483",
        "tgn:1000001",
        "tgn:7005565",
        "tgn:7029392"
    ],
    "tgn:id":1018890,
    "tgn:name":"San Carlos",
    "tgn:placetype":[
        "aat:300008347"
    ]
},
  "bbox": [],
  "geometry": {"coordinates":[-79.9667,8.4833],"type":"Point"}
}