<<<<<<< HEAD
{
  "id": 7024286,
  "type": "Feature",
  "properties": {
    "tgn:hierarchy":[
        "tgn:7024286",
        "tgn:7017306",
        "tgn:1000003",
        "tgn:7006663",
        "tgn:7029392"
    ],
    "tgn:id":7024286,
    "tgn:name":"Danilo Biranj",
    "tgn:placetype":[
        "aat:300008347"
    ]
},
  "bbox": [],
  "geometry": {"coordinates":[16.0,43.7333],"type":"Point"}
}
=======
{"geometry":{"type":"Point","coordinates":[16.000000,43.733300]},"type":"Feature","properties":{"hierarchy":["tgn:7024286","tgn:7017306","tgn:1000003","tgn:7006663","tgn:7029392"],"placetype":["aat:300008347"],"id":7024286,"name:xx":"Danilo Biranj"}}
>>>>>>> 03f74aca74312dbeaf24d7e61306dd6a786dc3d0
