{
  "id": 7558474,
  "type": "Feature",
  "properties": {
    "tgn:hierarchy":[
        "tgn:7558474",
        "tgn:1000004",
        "tgn:7000198",
        "tgn:1001882",
        "tgn:7029392"
    ],
    "tgn:id":7558474,
    "tgn:name:en":"Santemarahalli",
    "tgn:placetype":[
        "aat:300008347"
    ]
},
  "bbox": [],
  "geometry": {"coordinates":[76.985278,12.047222],"type":"Point"}
}