{
  "id": 7342352,
  "type": "Feature",
  "properties": {
    "tgn:hierarchy":[
        "tgn:7342352",
        "tgn:7002759",
        "tgn:7002843",
        "tgn:1000003",
        "tgn:1000095",
        "tgn:7029392"
    ],
    "tgn:id":7342352,
    "tgn:name":"Carrascosa, Sierra",
    "tgn:placetype":[
        "aat:300008777"
    ]
},
  "bbox": [],
  "geometry": {"coordinates":[-0.45,40.65],"type":"Point"}
}