{
  "id": 1107227,
  "type": "Feature",
  "properties": {
    "tgn:hierarchy":[
        "tgn:1107227",
        "tgn:1000001",
        "tgn:7012149",
        "tgn:2002382",
        "tgn:7007923",
        "tgn:7029392"
    ],
    "tgn:id":1107227,
    "tgn:name":"Doubletop Peak",
    "tgn:placetype":[
        "aat:300008798"
    ]
},
  "bbox": [],
  "geometry": {"coordinates":[-110.2833,43.3333],"type":"Point"}
}