{
  "id": 2391369,
  "type": "Feature",
  "properties": {
    "tgn:hierarchy":[
        "tgn:2391369",
        "tgn:1000001",
        "tgn:7012149",
        "tgn:7007157",
        "tgn:1002608",
        "tgn:7029392"
    ],
    "tgn:id":2391369,
    "tgn:name":"Hillcrest Canyon",
    "tgn:placetype":[
        "aat:300008761"
    ]
},
  "bbox": [],
  "geometry": {"coordinates":[-118.25,34.1667],"type":"Point"}
}