{
  "id": 2776908,
  "type": "Feature",
  "properties": {
    "tgn:hierarchy":[
        "tgn:2776908",
        "tgn:7016099",
        "tgn:1000001",
        "tgn:7012149",
        "tgn:7007516",
        "tgn:7029392"
    ],
    "tgn:id":2776908,
    "tgn:name":"Windwood",
    "tgn:placetype":[
        "aat:300008347"
    ]
},
  "bbox": [],
  "geometry": {"coordinates":[-76.75,39.25],"type":"Point"}
}