{
  "id": 2292603,
  "type": "Feature",
  "properties": {
    "tgn:hierarchy":[
        "tgn:2292603",
        "tgn:7006450",
        "tgn:1000001",
        "tgn:7030547",
        "tgn:7012149",
        "tgn:7029392"
    ],
    "tgn:id":2292603,
    "tgn:name":"Dora Peak",
    "tgn:placetype":[
        "aat:300008798"
    ]
},
  "bbox": [],
  "geometry": {"coordinates":[-148.7167,63.8167],"type":"Point"}
}