{
  "id": 2542988,
  "type": "Feature",
  "properties": {
    "tgn:hierarchy":[
        "tgn:2542988",
        "tgn:1000001",
        "tgn:7006451",
        "tgn:7012149",
        "tgn:2000104",
        "tgn:7029392"
    ],
    "tgn:id":2542988,
    "tgn:name":"Nommel Place",
    "tgn:placetype":[
        "aat:300008347"
    ]
},
  "bbox": [],
  "geometry": {"coordinates":[-114.6833,33.0667],"type":"Point"}
}