{
  "id": 7366293,
  "type": "Feature",
  "properties": {
    "tgn:hierarchy":[
        "tgn:7366293",
        "tgn:7005587",
        "tgn:1000001",
        "tgn:7005560",
        "tgn:7029392"
    ],
    "tgn:id":7366293,
    "tgn:name":"Escondida de San Rafael",
    "tgn:placetype":[
        "aat:300008347"
    ]
},
  "bbox": [],
  "geometry": {"coordinates":[-99.016667,21.166667],"type":"Point"}
}