{
  "id": 2402321,
  "type": "Feature",
  "properties": {
    "tgn:hierarchy":[
        "tgn:2402321",
        "tgn:1000001",
        "tgn:7012149",
        "tgn:1002352",
        "tgn:7007710",
        "tgn:7029392"
    ],
    "tgn:id":2402321,
    "tgn:name":"Horton City",
    "tgn:placetype":[
        "aat:300008347"
    ]
},
  "bbox": [],
  "geometry": {"coordinates":[-78.7167,41.2833],"type":"Point"}
}