{
  "id": 7007295,
  "type": "Feature",
  "properties": {
    "tgn:hierarchy":[
        "tgn:7007295",
        "tgn:1000003",
        "tgn:7003758",
        "tgn:7011731",
        "tgn:7029392"
    ],
    "tgn:id":7007295,
    "tgn:name":"Solothurn",
    "tgn:placetype":[
        "aat:300008347",
        "aat:300387220",
        "aat:300008375"
    ]
},
  "bbox": [],
  "geometry": {"coordinates":[7.5333,47.2167],"type":"Point"}
}