{
  "id": 7182009,
  "type": "Feature",
  "properties": {
    "tgn:hierarchy":[
        "tgn:7182009",
        "tgn:1000003",
        "tgn:7003689",
        "tgn:7000084",
        "tgn:7029392"
    ],
    "tgn:id":7182009,
    "tgn:name":"Friesau-Bach",
    "tgn:placetype":[
        "aat:300008699"
    ]
},
  "bbox": [],
  "geometry": {"coordinates":[11.683333,50.45],"type":"Point"}
}