<<<<<<< HEAD
{
  "id": 2339575,
  "type": "Feature",
  "properties": {
    "tgn:hierarchy":[
        "tgn:2339575",
        "tgn:1000001",
        "tgn:7012149",
        "tgn:1002518",
        "tgn:7007568",
        "tgn:7029392"
    ],
    "tgn:id":2339575,
    "tgn:name":"Frederick Island",
    "tgn:placetype":[
        "aat:300008791"
    ]
},
  "bbox": [],
  "geometry": {"coordinates":[-76.0,44.2833],"type":"Point"}
}
=======
{"geometry":{"type":"Point","coordinates":[-76.000000,44.283300]},"type":"Feature","properties":{"hierarchy":["tgn:2339575","tgn:1000001","tgn:7012149","tgn:1002518","tgn:7007568","tgn:7029392"],"placetype":["aat:300008791"],"id":2339575,"name:xx":"Frederick Island"}}
>>>>>>> 03f74aca74312dbeaf24d7e61306dd6a786dc3d0
