{
  "id": 2280932,
  "type": "Feature",
  "properties": {
    "tgn:hierarchy":[
        "tgn:2280932",
        "tgn:1000001",
        "tgn:7012149",
        "tgn:7007157",
        "tgn:1002675",
        "tgn:7029392"
    ],
    "tgn:id":2280932,
    "tgn:name":"Deep Creek Mine",
    "tgn:placetype":[
        "aat:300000390"
    ]
},
  "bbox": [],
  "geometry": {"coordinates":[-119.45,38.45],"type":"Point"}
}