{
  "id": 1140325,
  "type": "Feature",
  "properties": {
    "tgn:hierarchy":[
        "tgn:1140325",
        "tgn:7000895",
        "tgn:1000004",
        "tgn:1000974",
        "tgn:1000120",
        "tgn:7029392"
    ],
    "tgn:id":1140325,
    "tgn:name":"Asahi",
    "tgn:placetype":[
        "aat:300008347"
    ]
},
  "bbox": [],
  "geometry": {"coordinates":[136.1167,35.9833],"type":"Point"}
}