{
  "id": 1072268,
  "type": "Feature",
  "properties": {
    "tgn:hierarchy":[
        "tgn:1072268",
        "tgn:1000004",
        "tgn:1001390",
        "tgn:1000111",
        "tgn:7029392"
    ],
    "tgn:id":1072268,
    "tgn:name":"Tieling",
    "tgn:placetype":[
        "aat:300008347"
    ]
},
  "bbox": [],
  "geometry": {"coordinates":[123.8667,42.3167],"type":"Point"}
}