{
  "id": 2681189,
  "type": "Feature",
  "properties": {
    "tgn:hierarchy":[
        "tgn:2681189",
        "tgn:1000001",
        "tgn:7012149",
        "tgn:7007523",
        "tgn:7029392"
    ],
    "tgn:id":2681189,
    "tgn:name":"South Mud Creek",
    "tgn:placetype":[
        "aat:300008706"
    ]
},
  "bbox": [],
  "geometry": {"coordinates":[-93.9167,39.55],"type":"Point"}
}