{
  "id": 2639539,
  "type": "Feature",
  "properties": {
    "tgn:hierarchy":[
        "tgn:2639539",
        "tgn:1000001",
        "tgn:7012149",
        "tgn:2001716",
        "tgn:7007708",
        "tgn:7029392"
    ],
    "tgn:id":2639539,
    "tgn:name":"Saltpeter Creek",
    "tgn:placetype":[
        "aat:300008706"
    ]
},
  "bbox": [],
  "geometry": {"coordinates":[-122.6167,43.75],"type":"Point"}
}