{
  "id": 7264083,
  "type": "Feature",
  "properties": {
    "tgn:concordances":{
        "gn:id":"2752415"
    },
    "tgn:hierarchy":[
        "tgn:7264083",
        "tgn:1000003",
        "tgn:7003622",
        "tgn:7016845",
        "tgn:7029392"
    ],
    "tgn:id":7264083,
    "tgn:name:nl":"Korte Heide",
    "tgn:placetype":[
        "aat:300008347"
    ]
},
  "bbox": [],
  "geometry": {"coordinates":[6.05,51.366667],"type":"Point"}
}