{
  "id": 2020763,
  "type": "Feature",
  "properties": {
    "tgn:hierarchy":[
        "tgn:2020763",
        "tgn:1000001",
        "tgn:7012149",
        "tgn:1002768",
        "tgn:7007240",
        "tgn:7029392"
    ],
    "tgn:id":2020763,
    "tgn:name":"Palm Springs",
    "tgn:placetype":[
        "aat:300008347"
    ]
},
  "bbox": [],
  "geometry": {"coordinates":[-80.0833,26.6333],"type":"Point"}
}