{
  "id": 7564198,
  "type": "Feature",
  "properties": {
    "tgn:hierarchy":[
        "tgn:7564198",
        "tgn:1000004",
        "tgn:7000198",
        "tgn:7016722",
        "tgn:7029392"
    ],
    "tgn:id":7564198,
    "tgn:name:en":"Purwa Lodhan",
    "tgn:placetype":[
        "aat:300008347"
    ]
},
  "bbox": [],
  "geometry": {"coordinates":[79.848325,26.522],"type":"Point"}
}