{
  "id": 2558521,
  "type": "Feature",
  "properties": {
    "tgn:hierarchy":[
        "tgn:2558521",
        "tgn:1000001",
        "tgn:7012149",
        "tgn:2001863",
        "tgn:7007825",
        "tgn:7029392"
    ],
    "tgn:id":2558521,
    "tgn:name":"Oliver Branch",
    "tgn:placetype":[
        "aat:300008699"
    ]
},
  "bbox": [],
  "geometry": {"coordinates":[-88.7833,35.8333],"type":"Point"}
}