{
  "id": 7321538,
  "type": "Feature",
  "properties": {
    "tgn:hierarchy":[
        "tgn:7321538",
        "tgn:1001702",
        "tgn:1000049",
        "tgn:1000002",
        "tgn:7029392"
    ],
    "tgn:id":7321538,
    "tgn:name":"Bennet, Punta",
    "tgn:placetype":[
        "aat:300386846"
    ]
},
  "bbox": [],
  "geometry": {"coordinates":[-71.466667,-52.65],"type":"Point"}
}