{
  "id": 2631508,
  "type": "Feature",
  "properties": {
    "tgn:hierarchy":[
        "tgn:2631508",
        "tgn:1000001",
        "tgn:1002328",
        "tgn:7012149",
        "tgn:7007568",
        "tgn:7029392"
    ],
    "tgn:id":2631508,
    "tgn:name":"Round Top",
    "tgn:placetype":[
        "aat:300008798"
    ]
},
  "bbox": [],
  "geometry": {"coordinates":[-74.6833,42.2667],"type":"Point"}
}