{
  "id": 7496976,
  "type": "Feature",
  "properties": {
    "tgn:hierarchy":[
        "tgn:7496976",
        "tgn:1000004",
        "tgn:1000959",
        "tgn:1000141",
        "tgn:7029392"
    ],
    "tgn:id":7496976,
    "tgn:name":"Quyuan Gong",
    "tgn:placetype":[
        "aat:300007595"
    ]
},
  "bbox": [],
  "geometry": {"coordinates":[121.505649,25.099397],"type":"Point"}
}