{
  "id": 2685473,
  "type": "Feature",
  "properties": {
    "tgn:hierarchy":[
        "tgn:2685473",
        "tgn:1002808",
        "tgn:1000001",
        "tgn:7012149",
        "tgn:7007711",
        "tgn:7029392"
    ],
    "tgn:id":2685473,
    "tgn:name":"Sprague Upper Reservoir",
    "tgn:placetype":[
        "aat:300006191"
    ]
},
  "bbox": [],
  "geometry": {"coordinates":[-71.55,41.8833],"type":"Point"}
}