<<<<<<< HEAD
{
  "id": 2250909,
  "type": "Feature",
  "properties": {
    "tgn:hierarchy":[
        "tgn:2250909",
        "tgn:1000001",
        "tgn:7012149",
        "tgn:2001713",
        "tgn:7007708",
        "tgn:7029392"
    ],
    "tgn:id":2250909,
    "tgn:name":"Columbia Mine",
    "tgn:placetype":[
        "aat:300000390"
    ]
},
  "bbox": [],
  "geometry": {"coordinates":[-123.25,42.4833],"type":"Point"}
}
=======
{"geometry":{"type":"Point","coordinates":[-123.250000,42.483300]},"type":"Feature","properties":{"hierarchy":["tgn:2250909","tgn:1000001","tgn:7012149","tgn:2001713","tgn:7007708","tgn:7029392"],"placetype":["aat:300000390"],"id":2250909,"name:xx":"Columbia Mine"}}
>>>>>>> 03f74aca74312dbeaf24d7e61306dd6a786dc3d0
