{
  "id": 7508920,
  "type": "Feature",
  "properties": {
    "tgn:hierarchy":[
        "tgn:7508920",
        "tgn:1009227",
        "tgn:1000226",
        "tgn:7016729",
        "tgn:1000006",
        "tgn:7029392"
    ],
    "tgn:id":7508920,
    "tgn:name:en":"Titirangi",
    "tgn:placetype":[
        "aat:300008347"
    ]
},
  "bbox": [],
  "geometry": {"coordinates":[174.666667,-36.933333],"type":"Point"}
}