{
  "id": 7549326,
  "type": "Feature",
  "properties": {
    "tgn:hierarchy":[
        "tgn:7549326",
        "tgn:1000004",
        "tgn:7000198",
        "tgn:1001894",
        "tgn:7029392"
    ],
    "tgn:id":7549326,
    "tgn:name:en":"Chachor",
    "tgn:placetype":[
        "aat:300008347"
    ]
},
  "bbox": [],
  "geometry": {"coordinates":[75.354769,24.375372],"type":"Point"}
}