{
  "id": 7099388,
  "type": "Feature",
  "properties": {
    "tgn:hierarchy":[
        "tgn:7099388",
        "tgn:1000003",
        "tgn:7003684",
        "tgn:7000084",
        "tgn:7029392"
    ],
    "tgn:id":7099388,
    "tgn:name":"Siersdorf",
    "tgn:placetype":[
        "aat:300008347"
    ]
},
  "bbox": [],
  "geometry": {"coordinates":[6.666667,49.366667],"type":"Point"}
}