{
  "id": 7429926,
  "type": "Feature",
  "properties": {
    "tgn:hierarchy":[
        "tgn:7429926",
        "tgn:1001835",
        "tgn:1000001",
        "tgn:7005560",
        "tgn:7029392"
    ],
    "tgn:id":7429926,
    "tgn:name":"El Palomar",
    "tgn:placetype":[
        "aat:300008347"
    ]
},
  "bbox": [],
  "geometry": {"coordinates":[-116.383333,31.55],"type":"Point"}
}