{
  "id": 2123170,
  "type": "Feature",
  "properties": {
    "tgn:hierarchy":[
        "tgn:2123170",
        "tgn:1000001",
        "tgn:7012149",
        "tgn:2002380",
        "tgn:7007923",
        "tgn:7029392"
    ],
    "tgn:id":2123170,
    "tgn:name":"Slater",
    "tgn:placetype":[
        "aat:300008347",
        "aat:300387210"
    ]
},
  "bbox": [],
  "geometry": {"coordinates":[-104.8167,41.8667],"type":"Point"}
}