{
  "id": 2544818,
  "type": "Feature",
  "properties": {
    "tgn:hierarchy":[
        "tgn:2544818",
        "tgn:1000001",
        "tgn:7012149",
        "tgn:2002119",
        "tgn:7007827",
        "tgn:7029392"
    ],
    "tgn:id":2544818,
    "tgn:name":"North Cottonwood Creek",
    "tgn:placetype":[
        "aat:300008706"
    ]
},
  "bbox": [],
  "geometry": {"coordinates":[-109.55,37.8333],"type":"Point"}
}