{
  "id": 7436850,
  "type": "Feature",
  "properties": {
    "tgn:hierarchy":[
        "tgn:7436850",
        "tgn:7005586",
        "tgn:1000001",
        "tgn:7005560",
        "tgn:7029392"
    ],
    "tgn:id":7436850,
    "tgn:name":"Teponahuasco",
    "tgn:placetype":[
        "aat:300008347"
    ]
},
  "bbox": [],
  "geometry": {"coordinates":[-103.033333,20.916667],"type":"Point"}
}