{
  "id": 7284372,
  "type": "Feature",
  "properties": {
    "tgn:hierarchy":[
        "tgn:7284372",
        "tgn:7016598",
        "tgn:1000049",
        "tgn:1000002",
        "tgn:7029392"
    ],
    "tgn:id":7284372,
    "tgn:name":"Punta del Hueso, Cerro",
    "tgn:placetype":[
        "aat:300008795"
    ]
},
  "bbox": [],
  "geometry": {"coordinates":[-69.25,-25.183333],"type":"Point"}
}