{
  "id": 2734705,
  "type": "Feature",
  "properties": {
    "tgn:hierarchy":[
        "tgn:2734705",
        "tgn:1000001",
        "tgn:7012149",
        "tgn:2000965",
        "tgn:7007520",
        "tgn:7029392"
    ],
    "tgn:id":2734705,
    "tgn:name":"Tuttle Ditch",
    "tgn:placetype":[
        "aat:300006075"
    ]
},
  "bbox": [],
  "geometry": {"coordinates":[-83.4667,44.3333],"type":"Point"}
}