{
  "id": 7405302,
  "type": "Feature",
  "properties": {
    "tgn:hierarchy":[
        "tgn:7405302",
        "tgn:7005585",
        "tgn:1000001",
        "tgn:7005560",
        "tgn:7029392"
    ],
    "tgn:id":7405302,
    "tgn:name":"Tecomazuchil",
    "tgn:placetype":[
        "aat:300008347"
    ]
},
  "bbox": [],
  "geometry": {"coordinates":[-100.05,17.625],"type":"Point"}
}