<<<<<<< HEAD
{
  "id": 7113577,
  "type": "Feature",
  "properties": {
    "tgn:hierarchy":[
        "tgn:7113577",
        "tgn:1000003",
        "tgn:7003685",
        "tgn:7000084",
        "tgn:7029392"
    ],
    "tgn:id":7113577,
    "tgn:name":"R\u00f6schenhaus",
    "tgn:placetype":[
        "aat:300000206"
    ]
},
  "bbox": [],
  "geometry": {"coordinates":[13.35,50.85],"type":"Point"}
}
=======
{"geometry":{"type":"Point","coordinates":[13.350000,50.850000]},"type":"Feature","properties":{"hierarchy":["tgn:7113577","tgn:1000003","tgn:7003685","tgn:7000084","tgn:7029392"],"placetype":["aat:300000206"],"id":7113577,"name:xx":"R\u00f6schenhaus"}}
>>>>>>> 03f74aca74312dbeaf24d7e61306dd6a786dc3d0
