<<<<<<< HEAD
{
  "id": 7240524,
  "type": "Feature",
  "properties": {
    "tgn:hierarchy":[
        "tgn:7240524",
        "tgn:7003460",
        "tgn:1000003",
        "tgn:1000063",
        "tgn:4012014",
        "tgn:7029392"
    ],
    "tgn:id":7240524,
    "tgn:name":"Fagne Esset",
    "tgn:placetype":[
        "aat:300008347"
    ]
},
  "bbox": [],
  "geometry": {"coordinates":[6.05,50.55],"type":"Point"}
}
=======
{"geometry":{"type":"Point","coordinates":[6.050000,50.550000]},"type":"Feature","properties":{"hierarchy":["tgn:7240524","tgn:7003460","tgn:1000003","tgn:1000063","tgn:4012014","tgn:7029392"],"placetype":["aat:300008347"],"id":7240524,"name:xx":"Fagne Esset"}}
>>>>>>> 03f74aca74312dbeaf24d7e61306dd6a786dc3d0
