{
  "id": 2785271,
  "type": "Feature",
  "properties": {
    "tgn:hierarchy":[
        "tgn:2785271",
        "tgn:1000001",
        "tgn:7012149",
        "tgn:7013517",
        "tgn:7007248",
        "tgn:7029392"
    ],
    "tgn:id":2785271,
    "tgn:name":"Yellow Water Branch",
    "tgn:placetype":[
        "aat:300008699"
    ]
},
  "bbox": [],
  "geometry": {"coordinates":[-84.4667,30.8333],"type":"Point"}
}