{
  "id": 2451268,
  "type": "Feature",
  "properties": {
    "tgn:hierarchy":[
        "tgn:2451268",
        "tgn:1000001",
        "tgn:1002218",
        "tgn:7012149",
        "tgn:7007157",
        "tgn:7029392"
    ],
    "tgn:id":2451268,
    "tgn:name":"Little Bald Rock",
    "tgn:placetype":[
        "aat:300008798"
    ]
},
  "bbox": [],
  "geometry": {"coordinates":[-121.3167,39.65],"type":"Point"}
}