{
  "id": 2272634,
  "type": "Feature",
  "properties": {
    "tgn:hierarchy":[
        "tgn:2272634",
        "tgn:1002157",
        "tgn:1000001",
        "tgn:7012149",
        "tgn:7007565",
        "tgn:7029392"
    ],
    "tgn:id":2272634,
    "tgn:name":"Cushman Lake",
    "tgn:placetype":[
        "aat:300006191"
    ]
},
  "bbox": [],
  "geometry": {"coordinates":[-74.8667,39.5833],"type":"Point"}
}