{
  "id": 2584081,
  "type": "Feature",
  "properties": {
    "tgn:hierarchy":[
        "tgn:2584081",
        "tgn:1000001",
        "tgn:7012149",
        "tgn:2001616",
        "tgn:7007706",
        "tgn:7029392"
    ],
    "tgn:id":2584081,
    "tgn:name":"Pinegrove",
    "tgn:placetype":[
        "aat:300008347"
    ]
},
  "bbox": [],
  "geometry": {"coordinates":[-81.8167,39.15],"type":"Point"}
}