{
  "id": 7034354,
  "type": "Feature",
  "properties": {
    "tgn:hierarchy":[
        "tgn:7034354",
        "tgn:1001641",
        "tgn:1000003",
        "tgn:7003121",
        "tgn:1000080",
        "tgn:7029392"
    ],
    "tgn:id":7034354,
    "tgn:name":"Quirra",
    "tgn:placetype":[
        "aat:300008347"
    ]
},
  "bbox": [],
  "geometry": {"coordinates":[9.606389,39.515278],"type":"Point"}
}