{
  "id": 7027941,
  "type": "Feature",
  "properties": {
    "tgn:hierarchy":[
        "tgn:7027941",
        "tgn:7002445",
        "tgn:1000003",
        "tgn:7008157",
        "tgn:7008591",
        "tgn:7029392"
    ],
    "tgn:id":7027941,
    "tgn:name:en":"Kelstern",
    "tgn:placetype":[
        "aat:300008347",
        "aat:300008372"
    ]
},
  "bbox": [],
  "geometry": {"coordinates":[-0.116667,53.383333],"type":"Point"}
}