{
  "id": 2578048,
  "type": "Feature",
  "properties": {
    "tgn:hierarchy":[
        "tgn:2578048",
        "tgn:1000001",
        "tgn:2001838",
        "tgn:7012149",
        "tgn:7007825",
        "tgn:7029392"
    ],
    "tgn:id":2578048,
    "tgn:name":"Pettus Branch",
    "tgn:placetype":[
        "aat:300008699"
    ]
},
  "bbox": [],
  "geometry": {"coordinates":[-86.4833,35.4833],"type":"Point"}
}