{
  "id": 7017415,
  "type": "Feature",
  "properties": {
    "tgn:hierarchy":[
        "tgn:7017415",
        "tgn:1000003",
        "tgn:7002877",
        "tgn:1000070",
        "tgn:7029392"
    ],
    "tgn:id":7017415,
    "tgn:name":"Bourges",
    "tgn:placetype":[
        "aat:300387236",
        "aat:300008347",
        "aat:300387218",
        "aat:300387225",
        "aat:300008389",
        "aat:300387223",
        "aat:300387302",
        "aat:300387285"
    ]
},
  "bbox": [],
  "geometry": {"coordinates":[2.3833,47.0833],"type":"Point"}
}