{
  "id": 7569307,
  "type": "Feature",
  "properties": {
    "tgn:hierarchy":[
        "tgn:7569307",
        "tgn:1000004",
        "tgn:7000198",
        "tgn:7016694",
        "tgn:7029392"
    ],
    "tgn:id":7569307,
    "tgn:name:en":"N\u0101chu\u0101ni Buru",
    "tgn:placetype":[
        "aat:300008777"
    ]
},
  "bbox": [],
  "geometry": {"coordinates":[86.1725,21.938333],"type":"Point"}
}