{
  "id": 7140151,
  "type": "Feature",
  "properties": {
    "tgn:hierarchy":[
        "tgn:7140151",
        "tgn:7003692",
        "tgn:1000003",
        "tgn:7000084",
        "tgn:7029392"
    ],
    "tgn:id":7140151,
    "tgn:name":"Lindich",
    "tgn:placetype":[
        "aat:300008863"
    ]
},
  "bbox": [],
  "geometry": {"coordinates":[10.283333,48.85],"type":"Point"}
}