<<<<<<< HEAD
{
  "id": 7056505,
  "type": "Feature",
  "properties": {
    "tgn:hierarchy":[
        "tgn:7056505",
        "tgn:7003007",
        "tgn:1000003",
        "tgn:7002997",
        "tgn:1000080",
        "tgn:7029392"
    ],
    "tgn:id":7056505,
    "tgn:name":"Bindella",
    "tgn:placetype":[
        "aat:300008347"
    ]
},
  "bbox": [],
  "geometry": {"coordinates":[11.25,45.233333],"type":"Point"}
}
=======
{"geometry":{"type":"Point","coordinates":[11.250000,45.233333]},"type":"Feature","properties":{"hierarchy":["tgn:7056505","tgn:7003007","tgn:1000003","tgn:7002997","tgn:1000080","tgn:7029392"],"placetype":["aat:300008347"],"id":7056505,"name:xx":"Bindella"}}
>>>>>>> 03f74aca74312dbeaf24d7e61306dd6a786dc3d0
