{
  "id": 7436302,
  "type": "Feature",
  "properties": {
    "tgn:hierarchy":[
        "tgn:7436302",
        "tgn:7005587",
        "tgn:1000001",
        "tgn:7005560",
        "tgn:7029392"
    ],
    "tgn:id":7436302,
    "tgn:name":"Soledad",
    "tgn:placetype":[
        "aat:300007783"
    ]
},
  "bbox": [],
  "geometry": {"coordinates":[-98.75,20.033333],"type":"Point"}
}