{
  "id": 2581670,
  "type": "Feature",
  "properties": {
    "tgn:hierarchy":[
        "tgn:2581670",
        "tgn:1000001",
        "tgn:7012149",
        "tgn:1002584",
        "tgn:7007826",
        "tgn:7029392"
    ],
    "tgn:id":2581670,
    "tgn:name":"Pin Oak Creek",
    "tgn:placetype":[
        "aat:300008706"
    ]
},
  "bbox": [],
  "geometry": {"coordinates":[-96.8333,30.1833],"type":"Point"}
}