<<<<<<< HEAD
{
  "id": 2156865,
  "type": "Feature",
  "properties": {
    "tgn:hierarchy":[
        "tgn:2156865",
        "tgn:1000001",
        "tgn:7012149",
        "tgn:2000964",
        "tgn:7007520",
        "tgn:7029392"
    ],
    "tgn:id":2156865,
    "tgn:name":"Beaubien Drain",
    "tgn:placetype":[
        "aat:300006075"
    ]
},
  "bbox": [],
  "geometry": {"coordinates":[-83.1667,43.75],"type":"Point"}
}
=======
{"geometry":{"type":"Point","coordinates":[-83.166700,43.750000]},"type":"Feature","properties":{"hierarchy":["tgn:2156865","tgn:1000001","tgn:7012149","tgn:2000964","tgn:7007520","tgn:7029392"],"placetype":["aat:300006075"],"id":2156865,"name:xx":"Beaubien Drain"}}
>>>>>>> 03f74aca74312dbeaf24d7e61306dd6a786dc3d0
