{
  "id": 7040743,
  "type": "Feature",
  "properties": {
    "tgn:hierarchy":[
        "tgn:7040743",
        "tgn:7002996",
        "tgn:1000003",
        "tgn:7002997",
        "tgn:1000080",
        "tgn:7029392"
    ],
    "tgn:id":7040743,
    "tgn:name":"Sant'Andr\u00e0",
    "tgn:placetype":[
        "aat:300008347"
    ]
},
  "bbox": [],
  "geometry": {"coordinates":[12.201111,45.747778],"type":"Point"}
}