<<<<<<< HEAD
{
  "id": 7178467,
  "type": "Feature",
  "properties": {
    "tgn:hierarchy":[
        "tgn:7178467",
        "tgn:1000003",
        "tgn:7003677",
        "tgn:7000084",
        "tgn:7029392"
    ],
    "tgn:id":7178467,
    "tgn:name":"Hamperfeld",
    "tgn:placetype":[
        "aat:300000206"
    ]
},
  "bbox": [],
  "geometry": {"coordinates":[7.5,51.3],"type":"Point"}
}
=======
{"geometry":{"type":"Point","coordinates":[7.500000,51.300000]},"type":"Feature","properties":{"hierarchy":["tgn:7178467","tgn:1000003","tgn:7003677","tgn:7000084","tgn:7029392"],"placetype":["aat:300000206"],"id":7178467,"name:xx":"Hamperfeld"}}
>>>>>>> 03f74aca74312dbeaf24d7e61306dd6a786dc3d0
