<<<<<<< HEAD
{
  "id": 2334007,
  "type": "Feature",
  "properties": {
    "tgn:hierarchy":[
        "tgn:2334007",
        "tgn:1000001",
        "tgn:2124025",
        "tgn:7012149",
        "tgn:7007516",
        "tgn:7029392"
    ],
    "tgn:id":2334007,
    "tgn:name":"Ford Landing",
    "tgn:placetype":[
        "aat:300008347"
    ]
},
  "bbox": [],
  "geometry": {"coordinates":[-75.8833,39.2333],"type":"Point"}
}
=======
{"geometry":{"type":"Point","coordinates":[-75.883300,39.233300]},"type":"Feature","properties":{"hierarchy":["tgn:2334007","tgn:1000001","tgn:2124025","tgn:7012149","tgn:7007516","tgn:7029392"],"placetype":["aat:300008347"],"id":2334007,"name:xx":"Ford Landing"}}
>>>>>>> 03f74aca74312dbeaf24d7e61306dd6a786dc3d0
