{
  "id": 2750212,
  "type": "Feature",
  "properties": {
    "tgn:hierarchy":[
        "tgn:2750212",
        "tgn:1000001",
        "tgn:7014352",
        "tgn:7012149",
        "tgn:7007564",
        "tgn:7029392"
    ],
    "tgn:id":2750212,
    "tgn:name":"Walton Landing",
    "tgn:placetype":[
        "aat:300008347"
    ]
},
  "bbox": [],
  "geometry": {"coordinates":[-70.8333,42.8833],"type":"Point"}
}