{
  "id": 7506864,
  "type": "Feature",
  "properties": {
    "tgn:hierarchy":[
        "tgn:7506864",
        "tgn:1008380",
        "tgn:1000226",
        "tgn:7016827",
        "tgn:1000006",
        "tgn:7029392"
    ],
    "tgn:id":7506864,
    "tgn:name:en":"Rata",
    "tgn:placetype":[
        "aat:300008795"
    ]
},
  "bbox": [],
  "geometry": {"coordinates":[174.066667,-39.216667],"type":"Point"}
}