{
  "id": 7367735,
  "type": "Feature",
  "properties": {
    "tgn:hierarchy":[
        "tgn:7367735",
        "tgn:7005583",
        "tgn:1000001",
        "tgn:7005560",
        "tgn:7029392"
    ],
    "tgn:id":7367735,
    "tgn:name":"El Salitre",
    "tgn:placetype":[
        "aat:300008347"
    ]
},
  "bbox": [],
  "geometry": {"coordinates":[-106.116667,25.85],"type":"Point"}
}