{
  "id": 7035203,
  "type": "Feature",
  "properties": {
    "tgn:hierarchy":[
        "tgn:7035203",
        "tgn:1003506",
        "tgn:1000003",
        "tgn:7002993",
        "tgn:1000080",
        "tgn:7029392"
    ],
    "tgn:id":7035203,
    "tgn:name":"Sonovich, Monte",
    "tgn:placetype":[
        "aat:300008795"
    ]
},
  "bbox": [],
  "geometry": {"coordinates":[13.410556,46.334444],"type":"Point"}
}