{
  "id": 2730772,
  "type": "Feature",
  "properties": {
    "tgn:hierarchy":[
        "tgn:2730772",
        "tgn:7006450",
        "tgn:2000069",
        "tgn:1000001",
        "tgn:7012149",
        "tgn:7029392"
    ],
    "tgn:id":2730772,
    "tgn:name":"Tsingigkalik Lake",
    "tgn:placetype":[
        "aat:300008680"
    ]
},
  "bbox": [],
  "geometry": {"coordinates":[-161.8333,59.7333],"type":"Point"}
}