{
  "id": 1076772,
  "type": "Feature",
  "properties": {
    "tgn:hierarchy":[
        "tgn:1076772",
        "tgn:1000004",
        "tgn:7000198",
        "tgn:7000799",
        "tgn:7029392"
    ],
    "tgn:id":1076772,
    "tgn:name":"Riasi",
    "tgn:placetype":[
        "aat:300008347"
    ]
},
  "bbox": [],
  "geometry": {"coordinates":[74.832424,33.081146],"type":"Point"}
}