<<<<<<< HEAD
{
  "id": 7486199,
  "type": "Feature",
  "properties": {
    "tgn:hierarchy":[
        "tgn:7486199",
        "tgn:7488858",
        "tgn:1000004",
        "tgn:1000141",
        "tgn:7029392"
    ],
    "tgn:id":7486199,
    "tgn:name":"Niumian",
    "tgn:placetype":[
        "aat:300008347"
    ]
},
  "bbox": [],
  "geometry": {"coordinates":[120.975439,23.993097],"type":"Point"}
}
=======
{"geometry":{"type":"Point","coordinates":[120.975439,23.993097]},"type":"Feature","properties":{"hierarchy":["tgn:7486199","tgn:7488858","tgn:1000004","tgn:1000141","tgn:7029392"],"placetype":["aat:300008347"],"id":7486199,"name:xx":"Niumian"}}
>>>>>>> 03f74aca74312dbeaf24d7e61306dd6a786dc3d0
