{
  "id": 7211333,
  "type": "Feature",
  "properties": {
    "tgn:hierarchy":[
        "tgn:7211333",
        "tgn:1000003",
        "tgn:7003676",
        "tgn:7000084",
        "tgn:7029392"
    ],
    "tgn:id":7211333,
    "tgn:name":"Bei der Marsch",
    "tgn:placetype":[
        "aat:300000206"
    ]
},
  "bbox": [],
  "geometry": {"coordinates":[8.016667,52.966667],"type":"Point"}
}