{
  "id": 7242012,
  "type": "Feature",
  "properties": {
    "tgn:hierarchy":[
        "tgn:7242012",
        "tgn:7003458",
        "tgn:1000003",
        "tgn:1000063",
        "tgn:7018236",
        "tgn:7029392"
    ],
    "tgn:id":7242012,
    "tgn:name":"Klemskerke",
    "tgn:placetype":[
        "aat:300008347"
    ]
},
  "bbox": [],
  "geometry": {"coordinates":[3.024015,51.242216],"type":"Point"}
}