{
  "id": 2685943,
  "type": "Feature",
  "properties": {
    "tgn:hierarchy":[
        "tgn:2685943",
        "tgn:1000001",
        "tgn:2002107",
        "tgn:7012149",
        "tgn:7007827",
        "tgn:7029392"
    ],
    "tgn:id":2685943,
    "tgn:name":"Spring Branch Creek",
    "tgn:placetype":[
        "aat:300008706"
    ]
},
  "bbox": [],
  "geometry": {"coordinates":[-110.1667,40.55],"type":"Point"}
}