{
  "id": 7380432,
  "type": "Feature",
  "properties": {
    "tgn:hierarchy":[
        "tgn:7380432",
        "tgn:1000001",
        "tgn:7005595",
        "tgn:7005560",
        "tgn:7029392"
    ],
    "tgn:id":7380432,
    "tgn:name":"Matap\u00e1n",
    "tgn:placetype":[
        "aat:300008347"
    ]
},
  "bbox": [],
  "geometry": {"coordinates":[-108.116667,25.866667],"type":"Point"}
}