{
  "id": 7474703,
  "type": "Feature",
  "properties": {
    "tgn:hierarchy":[
        "tgn:7474703",
        "tgn:7001004",
        "tgn:1000004",
        "tgn:1000141",
        "tgn:7029392"
    ],
    "tgn:id":7474703,
    "tgn:name":"Tuozhenzi",
    "tgn:placetype":[
        "aat:300008347"
    ]
},
  "bbox": [],
  "geometry": {"coordinates":[120.402778,22.814722],"type":"Point"}
}