{
  "id": 2274311,
  "type": "Feature",
  "properties": {
    "tgn:hierarchy":[
        "tgn:2274311",
        "tgn:1000001",
        "tgn:2001411",
        "tgn:7012149",
        "tgn:7007526",
        "tgn:7029392"
    ],
    "tgn:id":2274311,
    "tgn:name":"Dake Reservoir",
    "tgn:placetype":[
        "aat:300006191"
    ]
},
  "bbox": [],
  "geometry": {"coordinates":[-114.0833,41.35],"type":"Point"}
}