{
  "id": 2134290,
  "type": "Feature",
  "properties": {
    "tgn:hierarchy":[
        "tgn:2134290",
        "tgn:1000001",
        "tgn:7012149",
        "tgn:2001054",
        "tgn:7007521",
        "tgn:7029392"
    ],
    "tgn:id":2134290,
    "tgn:name":"Annalaide Lake Ditch",
    "tgn:placetype":[
        "aat:300006075"
    ]
},
  "bbox": [],
  "geometry": {"coordinates":[-95.1833,46.1833],"type":"Point"}
}