{
  "id": 7050127,
  "type": "Feature",
  "properties": {
    "tgn:hierarchy":[
        "tgn:7050127",
        "tgn:7003133",
        "tgn:1000003",
        "tgn:7008516",
        "tgn:1000080",
        "tgn:7029392"
    ],
    "tgn:id":7050127,
    "tgn:name":"La Valle",
    "tgn:placetype":[
        "aat:300008347"
    ]
},
  "bbox": [],
  "geometry": {"coordinates":[11.616667,44.15],"type":"Point"}
}