{
  "id": 2149072,
  "type": "Feature",
  "properties": {
    "tgn:hierarchy":[
        "tgn:2149072",
        "tgn:1000001",
        "tgn:7012149",
        "tgn:1002966",
        "tgn:7007826",
        "tgn:7029392"
    ],
    "tgn:id":2149072,
    "tgn:name":"Barnwell Mountains",
    "tgn:placetype":[
        "aat:300008798"
    ]
},
  "bbox": [],
  "geometry": {"coordinates":[-94.8667,32.7833],"type":"Point"}
}