<<<<<<< HEAD
{
  "id": 7482425,
  "type": "Feature",
  "properties": {
    "tgn:hierarchy":[
        "tgn:7482425",
        "tgn:1000004",
        "tgn:7490934",
        "tgn:1000141",
        "tgn:7029392"
    ],
    "tgn:id":7482425,
    "tgn:name":"Xinhua Gaogong",
    "tgn:placetype":[
        "aat:300006495"
    ]
},
  "bbox": [],
  "geometry": {"coordinates":[120.317814,23.036879],"type":"Point"}
}
=======
{"geometry":{"type":"Point","coordinates":[120.317814,23.036879]},"type":"Feature","properties":{"hierarchy":["tgn:7482425","tgn:1000004","tgn:7490934","tgn:1000141","tgn:7029392"],"placetype":["aat:300006495"],"id":7482425,"name:xx":"Xinhua Gaogong"}}
>>>>>>> 03f74aca74312dbeaf24d7e61306dd6a786dc3d0
