{
  "id": 7307202,
  "type": "Feature",
  "properties": {
    "tgn:hierarchy":[
        "tgn:7307202",
        "tgn:7007780",
        "tgn:1000003",
        "tgn:7009604",
        "tgn:1000095",
        "tgn:7029392"
    ],
    "tgn:id":7307202,
    "tgn:name":"Los M\u00e1rtires",
    "tgn:placetype":[
        "aat:300008347"
    ]
},
  "bbox": [],
  "geometry": {"coordinates":[-2.401427,43.15628],"type":"Point"}
}