{
  "id": 2675921,
  "type": "Feature",
  "properties": {
    "tgn:hierarchy":[
        "tgn:2675921",
        "tgn:1000001",
        "tgn:7012149",
        "tgn:2002374",
        "tgn:7007923",
        "tgn:7029392"
    ],
    "tgn:id":2675921,
    "tgn:name":"Sony Reservoir",
    "tgn:placetype":[
        "aat:300006191"
    ]
},
  "bbox": [],
  "geometry": {"coordinates":[-106.3833,44.4667],"type":"Point"}
}