{
  "id": 2541006,
  "type": "Feature",
  "properties": {
    "tgn:hierarchy":[
        "tgn:2541006",
        "tgn:1000001",
        "tgn:2001840",
        "tgn:7012149",
        "tgn:7007825",
        "tgn:7029392"
    ],
    "tgn:id":2541006,
    "tgn:name":"Nichols Mountain",
    "tgn:placetype":[
        "aat:300008798"
    ]
},
  "bbox": [],
  "geometry": {"coordinates":[-85.3667,35.4833],"type":"Point"}
}