{
  "id": 2673805,
  "type": "Feature",
  "properties": {
    "tgn:hierarchy":[
        "tgn:2673805",
        "tgn:1000001",
        "tgn:7012149",
        "tgn:1003021",
        "tgn:7007252",
        "tgn:7029392"
    ],
    "tgn:id":2673805,
    "tgn:name":"Snow Ditch",
    "tgn:placetype":[
        "aat:300006075"
    ]
},
  "bbox": [],
  "geometry": {"coordinates":[-86.8167,40.7167],"type":"Point"}
}