{
  "id": 1044171,
  "type": "Feature",
  "properties": {
    "tgn:hierarchy":[
        "tgn:1044171",
        "tgn:1003489",
        "tgn:7004610",
        "tgn:1000003",
        "tgn:1000080",
        "tgn:7029392"
    ],
    "tgn:id":1044171,
    "tgn:name":"Cersosimo",
    "tgn:placetype":[
        "aat:300008347"
    ]
},
  "bbox": [],
  "geometry": {"coordinates":[16.35,40.05],"type":"Point"}
}