{
  "id": 2676008,
  "type": "Feature",
  "properties": {
    "tgn:hierarchy":[
        "tgn:2676008",
        "tgn:1000001",
        "tgn:7012149",
        "tgn:7007158",
        "tgn:2000240",
        "tgn:7029392"
    ],
    "tgn:id":2676008,
    "tgn:name":"Sopris, Mount",
    "tgn:placetype":[
        "aat:300008798"
    ]
},
  "bbox": [],
  "geometry": {"coordinates":[-107.1667,39.25],"type":"Point"}
}