{
  "id": 7302732,
  "type": "Feature",
  "properties": {
    "tgn:hierarchy":[
        "tgn:7302732",
        "tgn:7002829",
        "tgn:1000003",
        "tgn:7002786",
        "tgn:1000095",
        "tgn:7029392"
    ],
    "tgn:id":7302732,
    "tgn:name":"Neira, R\u00edo",
    "tgn:placetype":[
        "aat:300008699"
    ]
},
  "bbox": [],
  "geometry": {"coordinates":[-7.533333,42.883333],"type":"Point"}
}