{
  "id": 7201585,
  "type": "Feature",
  "properties": {
    "tgn:hierarchy":[
        "tgn:7201585",
        "tgn:1000003",
        "tgn:7003677",
        "tgn:7000084",
        "tgn:7029392"
    ],
    "tgn:id":7201585,
    "tgn:name":"Bruch",
    "tgn:placetype":[
        "aat:300387200"
    ]
},
  "bbox": [],
  "geometry": {"coordinates":[8.866667,52.383333],"type":"Point"}
}