{
  "id": 2547824,
  "type": "Feature",
  "properties": {
    "tgn:hierarchy":[
        "tgn:2547824",
        "tgn:1000001",
        "tgn:7012149",
        "tgn:7007158",
        "tgn:2000251",
        "tgn:7029392"
    ],
    "tgn:id":2547824,
    "tgn:name":"North Fork Wilson Creek",
    "tgn:placetype":[
        "aat:300008706"
    ]
},
  "bbox": [],
  "geometry": {"coordinates":[-105.1167,38.7167],"type":"Point"}
}