<<<<<<< HEAD
{
  "id": 2339711,
  "type": "Feature",
  "properties": {
    "tgn:hierarchy":[
        "tgn:2339711",
        "tgn:1000001",
        "tgn:7012149",
        "tgn:2000473",
        "tgn:7007250",
        "tgn:7029392"
    ],
    "tgn:id":2339711,
    "tgn:name":"Free Use Canyon Number 2",
    "tgn:placetype":[
        "aat:300008761"
    ]
},
  "bbox": [],
  "geometry": {"coordinates":[-111.5167,44.2333],"type":"Point"}
}
=======
{"geometry":{"type":"Point","coordinates":[-111.516700,44.233300]},"type":"Feature","properties":{"hierarchy":["tgn:2339711","tgn:1000001","tgn:7012149","tgn:2000473","tgn:7007250","tgn:7029392"],"placetype":["aat:300008761"],"id":2339711,"name:xx":"Free Use Canyon Number 2"}}
>>>>>>> 03f74aca74312dbeaf24d7e61306dd6a786dc3d0
