{
  "id": 2404096,
  "type": "Feature",
  "properties": {
    "tgn:hierarchy":[
        "tgn:2404096",
        "tgn:1000001",
        "tgn:7012149",
        "tgn:2002372",
        "tgn:7007923",
        "tgn:7029392"
    ],
    "tgn:id":2404096,
    "tgn:name":"Howery Reservoir",
    "tgn:placetype":[
        "aat:300006191"
    ]
},
  "bbox": [],
  "geometry": {"coordinates":[-104.3167,41.75],"type":"Point"}
}