{
  "id": 1124050,
  "type": "Feature",
  "properties": {
    "tgn:hierarchy":[
        "tgn:1124050",
        "tgn:1001945",
        "tgn:1000047",
        "tgn:7002457",
        "tgn:1000002",
        "tgn:7029392"
    ],
    "tgn:id":1124050,
    "tgn:name":"Furuba",
    "tgn:placetype":[
        "aat:300008707"
    ]
},
  "bbox": [],
  "geometry": {"coordinates":[-44.95,-23.35],"type":"Point"}
}