{
  "id": 2477782,
  "type": "Feature",
  "properties": {
    "tgn:hierarchy":[
        "tgn:2477782",
        "tgn:2000001",
        "tgn:7002659",
        "tgn:1000001",
        "tgn:7012149",
        "tgn:7029392"
    ],
    "tgn:id":2477782,
    "tgn:name":"MacCartees Lake",
    "tgn:placetype":[
        "aat:300006191"
    ]
},
  "bbox": [],
  "geometry": {"coordinates":[-87.7833,30.5167],"type":"Point"}
}