{
  "id": 7505445,
  "type": "Feature",
  "properties": {
    "tgn:hierarchy":[
        "tgn:7505445",
        "tgn:7016670",
        "tgn:1008380",
        "tgn:1000226",
        "tgn:1000006",
        "tgn:7029392"
    ],
    "tgn:id":7505445,
    "tgn:name:en":"Whiri River",
    "tgn:placetype":[
        "aat:300008699"
    ]
},
  "bbox": [],
  "geometry": {"coordinates":[176.65,-38.733333],"type":"Point"}
}