{
  "id": 2267727,
  "type": "Feature",
  "properties": {
    "tgn:hierarchy":[
        "tgn:2267727",
        "tgn:1000001",
        "tgn:7012149",
        "tgn:2000979",
        "tgn:7007520",
        "tgn:7029392"
    ],
    "tgn:id":2267727,
    "tgn:name":"Cron Drain",
    "tgn:placetype":[
        "aat:300006075"
    ]
},
  "bbox": [],
  "geometry": {"coordinates":[-84.2167,43.5167],"type":"Point"}
}