{
  "id": 2370950,
  "type": "Feature",
  "properties": {
    "tgn:hierarchy":[
        "tgn:2370950",
        "tgn:1000001",
        "tgn:7012149",
        "tgn:2001189",
        "tgn:7007523",
        "tgn:7029392"
    ],
    "tgn:id":2370950,
    "tgn:name":"Hadley Branch",
    "tgn:placetype":[
        "aat:300008699"
    ]
},
  "bbox": [],
  "geometry": {"coordinates":[-92.6667,38.7167],"type":"Point"}
}