{
  "id": 7054316,
  "type": "Feature",
  "properties": {
    "tgn:hierarchy":[
        "tgn:7054316",
        "tgn:7003007",
        "tgn:1000003",
        "tgn:7002997",
        "tgn:1000080",
        "tgn:7029392"
    ],
    "tgn:id":7054316,
    "tgn:name":"Palazzolo",
    "tgn:placetype":[
        "aat:300008347"
    ]
},
  "bbox": [],
  "geometry": {"coordinates":[10.816667,45.45],"type":"Point"}
}