{
  "id": 7014002,
  "type": "Feature",
  "properties": {
    "tgn:hierarchy":[
        "tgn:7014002",
        "tgn:1000001",
        "tgn:7012149",
        "tgn:7007157",
        "tgn:7014004",
        "tgn:7029392"
    ],
    "tgn:id":7014002,
    "tgn:name":"Mariposa",
    "tgn:placetype":[
        "aat:300008347"
    ]
},
  "bbox": [],
  "geometry": {"coordinates":[-119.95,37.4833],"type":"Point"}
}