{
  "id": 7589286,
  "type": "Feature",
  "properties": {
    "tgn:hierarchy":[
        "tgn:7589286",
        "tgn:1000004",
        "tgn:7000198",
        "tgn:7000799",
        "tgn:7029392"
    ],
    "tgn:id":7589286,
    "tgn:name:en":"Ts\u016bnt Wali W\u0101r",
    "tgn:placetype":[
        "aat:300008347"
    ]
},
  "bbox": [],
  "geometry": {"coordinates":[74.742167,34.284509],"type":"Point"}
}