<<<<<<< HEAD
{
  "id": 2765953,
  "type": "Feature",
  "properties": {
    "tgn:hierarchy":[
        "tgn:2765953",
        "tgn:1000001",
        "tgn:7012149",
        "tgn:7022218",
        "tgn:7007919",
        "tgn:7029392"
    ],
    "tgn:id":2765953,
    "tgn:name":"White Hill Lake",
    "tgn:placetype":[
        "aat:300006191"
    ]
},
  "bbox": [],
  "geometry": {"coordinates":[-76.0167,36.9],"type":"Point"}
}
=======
{"geometry":{"type":"Point","coordinates":[-76.016700,36.900000]},"type":"Feature","properties":{"hierarchy":["tgn:2765953","tgn:1000001","tgn:7012149","tgn:7022218","tgn:7007919","tgn:7029392"],"placetype":["aat:300006191"],"id":2765953,"name:xx":"White Hill Lake"}}
>>>>>>> 03f74aca74312dbeaf24d7e61306dd6a786dc3d0
