{
  "id": 1012196,
  "type": "Feature",
  "properties": {
    "tgn:hierarchy":[
        "tgn:1012196",
        "tgn:7018592",
        "tgn:7005559",
        "tgn:1000001",
        "tgn:7005556",
        "tgn:7029392"
    ],
    "tgn:id":1012196,
    "tgn:name":"Morant Point",
    "tgn:placetype":[
        "aat:300386846"
    ]
},
  "bbox": [],
  "geometry": {"coordinates":[-76.183,17.912],"type":"Point"}
}