{
  "id": 7189463,
  "type": "Feature",
  "properties": {
    "tgn:hierarchy":[
        "tgn:7189463",
        "tgn:1000003",
        "tgn:7003688",
        "tgn:7000084",
        "tgn:7029392"
    ],
    "tgn:id":7189463,
    "tgn:name":"Elsen-See",
    "tgn:placetype":[
        "aat:300008680"
    ]
},
  "bbox": [],
  "geometry": {"coordinates":[9.916667,53.716667],"type":"Point"}
}