{
  "id": 7497424,
  "type": "Feature",
  "properties": {
    "tgn:hierarchy":[
        "tgn:7497424",
        "tgn:1000004",
        "tgn:7001013",
        "tgn:1000141",
        "tgn:7029392"
    ],
    "tgn:id":7497424,
    "tgn:name":"Luzhu Guoxiao",
    "tgn:placetype":[
        "aat:300006495"
    ]
},
  "bbox": [],
  "geometry": {"coordinates":[121.268141,25.051192],"type":"Point"}
}