<<<<<<< HEAD
{
  "id": 2154516,
  "type": "Feature",
  "properties": {
    "tgn:hierarchy":[
        "tgn:2154516",
        "tgn:1000001",
        "tgn:7012149",
        "tgn:7007524",
        "tgn:7029392"
    ],
    "tgn:id":2154516,
    "tgn:name":"Bear Creek Reservoir",
    "tgn:placetype":[
        "aat:300006191"
    ]
},
  "bbox": [],
  "geometry": {"coordinates":[-108.6667,47.2667],"type":"Point"}
}
=======
{"geometry":{"type":"Point","coordinates":[-108.666700,47.266700]},"type":"Feature","properties":{"hierarchy":["tgn:2154516","tgn:1000001","tgn:7012149","tgn:7007524","tgn:7029392"],"placetype":["aat:300006191"],"id":2154516,"name:xx":"Bear Creek Reservoir"}}
>>>>>>> 03f74aca74312dbeaf24d7e61306dd6a786dc3d0
