{
  "id": 2154516,
  "type": "Feature",
  "properties": {
    "tgn:hierarchy":[
        "tgn:2154516",
        "tgn:1000001",
        "tgn:7012149",
        "tgn:7007524",
        "tgn:7029392"
    ],
    "tgn:id":2154516,
    "tgn:name":"Bear Creek Reservoir",
    "tgn:placetype":[
        "aat:300006191"
    ]
},
  "bbox": [],
  "geometry": {"coordinates":[-108.6667,47.2667],"type":"Point"}
}