{
  "id": 7442766,
  "type": "Feature",
  "properties": {
    "tgn:hierarchy":[
        "tgn:7442766",
        "tgn:7002444",
        "tgn:1000003",
        "tgn:7008082",
        "tgn:7008591",
        "tgn:7029392"
    ],
    "tgn:id":7442766,
    "tgn:name:en":"Tirefour Castle",
    "tgn:placetype":[
        "aat:300008057"
    ]
},
  "bbox": [],
  "geometry": {"coordinates":[-5.466667,56.533333],"type":"Point"}
}