<<<<<<< HEAD
{
  "id": 2768357,
  "type": "Feature",
  "properties": {
    "tgn:hierarchy":[
        "tgn:2768357",
        "tgn:7002659",
        "tgn:1000001",
        "tgn:2000007",
        "tgn:7012149",
        "tgn:7029392"
    ],
    "tgn:id":2768357,
    "tgn:name":"Whiteside Spring",
    "tgn:placetype":[
        "aat:300008697"
    ]
},
  "bbox": [],
  "geometry": {"coordinates":[-85.65,33.7333],"type":"Point"}
}
=======
{"geometry":{"type":"Point","coordinates":[-85.650000,33.733300]},"type":"Feature","properties":{"hierarchy":["tgn:2768357","tgn:7002659","tgn:1000001","tgn:2000007","tgn:7012149","tgn:7029392"],"placetype":["aat:300008697"],"id":2768357,"name:xx":"Whiteside Spring"}}
>>>>>>> 03f74aca74312dbeaf24d7e61306dd6a786dc3d0
