{
  "id": 7479810,
  "type": "Feature",
  "properties": {
    "tgn:hierarchy":[
        "tgn:7479810",
        "tgn:1000004",
        "tgn:7490934",
        "tgn:1000141",
        "tgn:7029392"
    ],
    "tgn:id":7479810,
    "tgn:name":"Tumaikeng",
    "tgn:placetype":[
        "aat:300008699"
    ]
},
  "bbox": [],
  "geometry": {"coordinates":[120.418983,23.204191],"type":"Point"}
}