{
  "id": 1118016,
  "type": "Feature",
  "properties": {
    "tgn:hierarchy":[
        "tgn:1118016",
        "tgn:1000001",
        "tgn:7012149",
        "tgn:7007256",
        "tgn:7029392"
    ],
    "tgn:id":1118016,
    "tgn:name":"Salvador, Lake",
    "tgn:placetype":[
        "aat:300008680"
    ]
},
  "bbox": [],
  "geometry": {"coordinates":[-90.25,29.7167],"type":"Point"}
}