{
  "id": 1020594,
  "type": "Feature",
  "properties": {
    "tgn:hierarchy":[
        "tgn:1020594",
        "tgn:7006247",
        "tgn:1000047",
        "tgn:7002456",
        "tgn:1000002",
        "tgn:7029392"
    ],
    "tgn:id":1020594,
    "tgn:name":"Americano",
    "tgn:placetype":[
        "aat:300008347"
    ]
},
  "bbox": [],
  "geometry": {"coordinates":[-48.0667,-1.3167],"type":"Point"}
}