<<<<<<< HEAD
{
  "id": 7175536,
  "type": "Feature",
  "properties": {
    "tgn:hierarchy":[
        "tgn:7175536",
        "tgn:7003692",
        "tgn:1000003",
        "tgn:7000084",
        "tgn:7029392"
    ],
    "tgn:id":7175536,
    "tgn:name":"Griesers",
    "tgn:placetype":[
        "aat:300000206"
    ]
},
  "bbox": [],
  "geometry": {"coordinates":[9.9,48.033333],"type":"Point"}
}
=======
{"geometry":{"type":"Point","coordinates":[9.900000,48.033333]},"type":"Feature","properties":{"hierarchy":["tgn:7175536","tgn:7003692","tgn:1000003","tgn:7000084","tgn:7029392"],"placetype":["aat:300000206"],"id":7175536,"name:xx":"Griesers"}}
>>>>>>> 03f74aca74312dbeaf24d7e61306dd6a786dc3d0
