{
  "id": 5004190,
  "type": "Feature",
  "properties": {
    "tgn:hierarchy":[
        "tgn:5004190",
        "tgn:7003006",
        "tgn:1000003",
        "tgn:7002997",
        "tgn:1000080",
        "tgn:7018159",
        "tgn:7029392"
    ],
    "tgn:id":5004190,
    "tgn:name":"La Giudecca",
    "tgn:placetype":[
        "aat:300008791",
        "aat:300000874"
    ]
},
  "bbox": [],
  "geometry": {"coordinates":[12.333333,45.433333],"type":"Point"}
}