{
  "id": 7572692,
  "type": "Feature",
  "properties": {
    "tgn:hierarchy":[
        "tgn:7572692",
        "tgn:1000004",
        "tgn:7000198",
        "tgn:1001894",
        "tgn:7029392"
    ],
    "tgn:id":7572692,
    "tgn:name:en":"Howbagh",
    "tgn:placetype":[
        "aat:300007783"
    ]
},
  "bbox": [],
  "geometry": {"coordinates":[79.931636,23.155687],"type":"Point"}
}