{
  "id": 2649648,
  "type": "Feature",
  "properties": {
    "tgn:hierarchy":[
        "tgn:2649648",
        "tgn:1000001",
        "tgn:7012149",
        "tgn:2000969",
        "tgn:7007520",
        "tgn:7029392"
    ],
    "tgn:id":2649648,
    "tgn:name":"Scoville Point",
    "tgn:placetype":[
        "aat:300008850"
    ]
},
  "bbox": [],
  "geometry": {"coordinates":[-88.45,48.15],"type":"Point"}
}