<<<<<<< HEAD
{
  "id": 7488388,
  "type": "Feature",
  "properties": {
    "tgn:hierarchy":[
        "tgn:7488388",
        "tgn:1000004",
        "tgn:7490934",
        "tgn:1000141",
        "tgn:7029392"
    ],
    "tgn:id":7488388,
    "tgn:name":"Nanpou",
    "tgn:placetype":[
        "aat:300008347"
    ]
},
  "bbox": [],
  "geometry": {"coordinates":[120.306178,23.213182],"type":"Point"}
}
=======
{"geometry":{"type":"Point","coordinates":[120.306178,23.213182]},"type":"Feature","properties":{"hierarchy":["tgn:7488388","tgn:1000004","tgn:7490934","tgn:1000141","tgn:7029392"],"placetype":["aat:300008347"],"id":7488388,"name:xx":"Nanpou"}}
>>>>>>> 03f74aca74312dbeaf24d7e61306dd6a786dc3d0
