{
  "id": 7481152,
  "type": "Feature",
  "properties": {
    "tgn:hierarchy":[
        "tgn:7481152",
        "tgn:1000004",
        "tgn:7492971",
        "tgn:1000141",
        "tgn:7029392"
    ],
    "tgn:id":7481152,
    "tgn:name":"Nonggong Yicun",
    "tgn:placetype":[
        "aat:300000498"
    ]
},
  "bbox": [],
  "geometry": {"coordinates":[120.513023,22.663859],"type":"Point"}
}