<<<<<<< HEAD
{
  "id": 7481152,
  "type": "Feature",
  "properties": {
    "tgn:hierarchy":[
        "tgn:7481152",
        "tgn:1000004",
        "tgn:7492971",
        "tgn:1000141",
        "tgn:7029392"
    ],
    "tgn:id":7481152,
    "tgn:name":"Nonggong Yicun",
    "tgn:placetype":[
        "aat:300000498"
    ]
},
  "bbox": [],
  "geometry": {"coordinates":[120.513023,22.663859],"type":"Point"}
}
=======
{"geometry":{"type":"Point","coordinates":[120.513023,22.663859]},"type":"Feature","properties":{"hierarchy":["tgn:7481152","tgn:1000004","tgn:7492971","tgn:1000141","tgn:7029392"],"placetype":["aat:300000498"],"id":7481152,"name:xx":"Nonggong Yicun"}}
>>>>>>> 03f74aca74312dbeaf24d7e61306dd6a786dc3d0
