{
  "id": 7349379,
  "type": "Feature",
  "properties": {
    "tgn:hierarchy":[
        "tgn:7349379",
        "tgn:1001836",
        "tgn:1000001",
        "tgn:7005560",
        "tgn:7029392"
    ],
    "tgn:id":7349379,
    "tgn:name":"Agua Escondida",
    "tgn:placetype":[
        "aat:300008347"
    ]
},
  "bbox": [],
  "geometry": {"coordinates":[-110.966667,24.633333],"type":"Point"}
}