{
  "id": 2209320,
  "type": "Feature",
  "properties": {
    "tgn:hierarchy":[
        "tgn:2209320",
        "tgn:1000001",
        "tgn:7012149",
        "tgn:2001291",
        "tgn:7007524",
        "tgn:7029392"
    ],
    "tgn:id":2209320,
    "tgn:name":"Burnt Point Creek",
    "tgn:placetype":[
        "aat:300008706"
    ]
},
  "bbox": [],
  "geometry": {"coordinates":[-114.1833,47.1333],"type":"Point"}
}