<<<<<<< HEAD
{
  "id": 2405148,
  "type": "Feature",
  "properties": {
    "tgn:hierarchy":[
        "tgn:2405148",
        "tgn:1000001",
        "tgn:7012149",
        "tgn:7007157",
        "tgn:1002972",
        "tgn:7029392"
    ],
    "tgn:id":2405148,
    "tgn:name":"Hueneme Canyon",
    "tgn:placetype":[
        "aat:300132348"
    ]
},
  "bbox": [],
  "geometry": {"coordinates":[-119.2167,34.1167],"type":"Point"}
}
=======
{"geometry":{"type":"Point","coordinates":[-119.216700,34.116700]},"type":"Feature","properties":{"hierarchy":["tgn:2405148","tgn:1000001","tgn:7012149","tgn:7007157","tgn:1002972","tgn:7029392"],"placetype":["aat:300132348"],"id":2405148,"name:xx":"Hueneme Canyon"}}
>>>>>>> 03f74aca74312dbeaf24d7e61306dd6a786dc3d0
