{
  "id": 7306301,
  "type": "Feature",
  "properties": {
    "tgn:hierarchy":[
        "tgn:7306301",
        "tgn:7002825",
        "tgn:7016622",
        "tgn:1000003",
        "tgn:1000095",
        "tgn:7029392"
    ],
    "tgn:id":7306301,
    "tgn:name":"Los Sitios",
    "tgn:placetype":[
        "aat:300008347"
    ]
},
  "bbox": [],
  "geometry": {"coordinates":[-15.533333,27.866667],"type":"Point"}
}