<<<<<<< HEAD
{
  "id": 2409421,
  "type": "Feature",
  "properties": {
    "tgn:hierarchy":[
        "tgn:2409421",
        "tgn:1000001",
        "tgn:7012149",
        "tgn:2001899",
        "tgn:7007825",
        "tgn:7029392"
    ],
    "tgn:id":2409421,
    "tgn:name":"Idaho Spring",
    "tgn:placetype":[
        "aat:300008697"
    ]
},
  "bbox": [],
  "geometry": {"coordinates":[-87.2833,36.5333],"type":"Point"}
}
=======
{"geometry":{"type":"Point","coordinates":[-87.283300,36.533300]},"type":"Feature","properties":{"hierarchy":["tgn:2409421","tgn:1000001","tgn:7012149","tgn:2001899","tgn:7007825","tgn:7029392"],"placetype":["aat:300008697"],"id":2409421,"name:xx":"Idaho Spring"}}
>>>>>>> 03f74aca74312dbeaf24d7e61306dd6a786dc3d0
