{
  "id": 2463162,
  "type": "Feature",
  "properties": {
    "tgn:hierarchy":[
        "tgn:2463162",
        "tgn:1000001",
        "tgn:7012149",
        "tgn:2001293",
        "tgn:7007524",
        "tgn:7029392"
    ],
    "tgn:id":2463162,
    "tgn:name":"Livingston Island",
    "tgn:placetype":[
        "aat:300008791"
    ]
},
  "bbox": [],
  "geometry": {"coordinates":[-110.5333,45.65],"type":"Point"}
}