{
  "id": 2367408,
  "type": "Feature",
  "properties": {
    "tgn:hierarchy":[
        "tgn:2367408",
        "tgn:1000001",
        "tgn:7012149",
        "tgn:2001503",
        "tgn:7007709",
        "tgn:7029392"
    ],
    "tgn:id":2367408,
    "tgn:name":"Groundhog Creek",
    "tgn:placetype":[
        "aat:300008706"
    ]
},
  "bbox": [],
  "geometry": {"coordinates":[-83.0167,35.7667],"type":"Point"}
}