{
  "id": 7545722,
  "type": "Feature",
  "properties": {
    "tgn:hierarchy":[
        "tgn:7545722",
        "tgn:1000004",
        "tgn:1001832",
        "tgn:7000198",
        "tgn:7029392"
    ],
    "tgn:id":7545722,
    "tgn:name:en":"Baru\u0101gaon",
    "tgn:placetype":[
        "aat:300008347"
    ]
},
  "bbox": [],
  "geometry": {"coordinates":[94.083333,26.45],"type":"Point"}
}