{
  "id": 2281371,
  "type": "Feature",
  "properties": {
    "tgn:hierarchy":[
        "tgn:2281371",
        "tgn:1000001",
        "tgn:7012149",
        "tgn:1002691",
        "tgn:7007826",
        "tgn:7029392"
    ],
    "tgn:id":2281371,
    "tgn:name":"Deep White Pond",
    "tgn:placetype":[
        "aat:300008905"
    ]
},
  "bbox": [],
  "geometry": {"coordinates":[-95.3667,30.2167],"type":"Point"}
}