{
  "id": 7243708,
  "type": "Feature",
  "properties": {
    "tgn:hierarchy":[
        "tgn:7243708",
        "tgn:7003466",
        "tgn:1000003",
        "tgn:1000063",
        "tgn:4012014",
        "tgn:7029392"
    ],
    "tgn:id":7243708,
    "tgn:name":"Houyemont",
    "tgn:placetype":[
        "aat:300008347"
    ]
},
  "bbox": [],
  "geometry": {"coordinates":[4.971265,50.35153],"type":"Point"}
}