{
  "id": 1135052,
  "type": "Feature",
  "properties": {
    "tgn:hierarchy":[
        "tgn:1135052",
        "tgn:7016099",
        "tgn:1000001",
        "tgn:7012149",
        "tgn:7007516",
        "tgn:7029392"
    ],
    "tgn:id":1135052,
    "tgn:name":"Whitemarsh Run",
    "tgn:placetype":[
        "aat:300008706"
    ]
},
  "bbox": [],
  "geometry": {"coordinates":[-76.5333,39.3833],"type":"Point"}
}