{
  "id": 7466726,
  "type": "Feature",
  "properties": {
    "tgn:hierarchy":[
        "tgn:7466726",
        "tgn:7002445",
        "tgn:1000003",
        "tgn:7008157",
        "tgn:7008591",
        "tgn:7029392"
    ],
    "tgn:id":7466726,
    "tgn:name:en":"Broadholme",
    "tgn:placetype":[
        "aat:300008347"
    ]
},
  "bbox": [],
  "geometry": {"coordinates":[-0.666667,53.25],"type":"Point"}
}