{
  "id": 7416593,
  "type": "Feature",
  "properties": {
    "tgn:hierarchy":[
        "tgn:7416593",
        "tgn:1000001",
        "tgn:7005591",
        "tgn:7005560",
        "tgn:7029392"
    ],
    "tgn:id":7416593,
    "tgn:name:es":"La Libertad",
    "tgn:placetype":[
        "aat:300008347"
    ]
},
  "bbox": [],
  "geometry": {"coordinates":[-95.250278,17.588889],"type":"Point"}
}