{
  "id": 2136159,
  "type": "Feature",
  "properties": {
    "tgn:hierarchy":[
        "tgn:2136159",
        "tgn:1000001",
        "tgn:1002328",
        "tgn:7012149",
        "tgn:7007568",
        "tgn:7029392"
    ],
    "tgn:id":2136159,
    "tgn:name":"Arabia",
    "tgn:placetype":[
        "aat:300008347"
    ]
},
  "bbox": [],
  "geometry": {"coordinates":[-75.05,42.2833],"type":"Point"}
}