{
  "id": 1050312,
  "type": "Feature",
  "properties": {
    "tgn:hierarchy":[
        "tgn:1050312",
        "tgn:1000349",
        "tgn:1000003",
        "tgn:1000091",
        "tgn:7029392"
    ],
    "tgn:id":1050312,
    "tgn:name":"Tru\u0219e\u0219ti",
    "tgn:placetype":[
        "aat:300008347"
    ]
},
  "bbox": [],
  "geometry": {"coordinates":[27.0167,47.75],"type":"Point"}
}