{
  "id": 7513034,
  "type": "Feature",
  "properties": {
    "tgn:hierarchy":[
        "tgn:7513034",
        "tgn:7000508",
        "tgn:1008380",
        "tgn:1000226",
        "tgn:1000006",
        "tgn:7029392"
    ],
    "tgn:id":7513034,
    "tgn:name:en":"Hapapawera",
    "tgn:placetype":[
        "aat:300008795"
    ]
},
  "bbox": [],
  "geometry": {"coordinates":[175.583333,-36.683333],"type":"Point"}
}