{
  "id": 7274497,
  "type": "Feature",
  "properties": {
    "tgn:concordances":{
        "gn:id":"2743537"
    },
    "tgn:hierarchy":[
        "tgn:7274497",
        "tgn:7003619",
        "tgn:1000003",
        "tgn:7016845",
        "tgn:7029392"
    ],
    "tgn:id":7274497,
    "tgn:name:nl":"Zwarte Paard",
    "tgn:placetype":[
        "aat:300008347"
    ]
},
  "bbox": [],
  "geometry": {"coordinates":[5.45,51.95],"type":"Point"}
}