{
  "id": 1037620,
  "type": "Feature",
  "properties": {
    "tgn:hierarchy":[
        "tgn:1037620",
        "tgn:1000003",
        "tgn:7003689",
        "tgn:7000084",
        "tgn:7029392"
    ],
    "tgn:id":1037620,
    "tgn:name":"Ruhla",
    "tgn:placetype":[
        "aat:300008347"
    ]
},
  "bbox": [],
  "geometry": {"coordinates":[10.366667,50.883333],"type":"Point"}
}