{
  "id": 7088057,
  "type": "Feature",
  "properties": {
    "tgn:hierarchy":[
        "tgn:7088057",
        "tgn:7003692",
        "tgn:1000003",
        "tgn:7000084",
        "tgn:7029392"
    ],
    "tgn:id":7088057,
    "tgn:name":"Weckrieden",
    "tgn:placetype":[
        "aat:300008347"
    ]
},
  "bbox": [],
  "geometry": {"coordinates":[9.75,49.116667],"type":"Point"}
}