{
  "id": 2088173,
  "type": "Feature",
  "properties": {
    "tgn:hierarchy":[
        "tgn:2088173",
        "tgn:1000001",
        "tgn:7012149",
        "tgn:1003008",
        "tgn:7007710",
        "tgn:7029392"
    ],
    "tgn:id":2088173,
    "tgn:name":"Elk Lake",
    "tgn:placetype":[
        "aat:300006191"
    ]
},
  "bbox": [],
  "geometry": {"coordinates":[-75.3833,41.6167],"type":"Point"}
}