{
  "id": 7503650,
  "type": "Feature",
  "properties": {
    "tgn:hierarchy":[
        "tgn:7503650",
        "tgn:1000004",
        "tgn:7491221",
        "tgn:1000141",
        "tgn:7029392"
    ],
    "tgn:id":7503650,
    "tgn:name":"Zhiben Shan",
    "tgn:placetype":[
        "aat:300008798",
        "aat:300387002"
    ]
},
  "bbox": [],
  "geometry": {"coordinates":[121.006667,22.706667],"type":"Point"}
}