{
  "id": 2355492,
  "type": "Feature",
  "properties": {
    "tgn:hierarchy":[
        "tgn:2355492",
        "tgn:1000001",
        "tgn:7012149",
        "tgn:1002382",
        "tgn:7007255",
        "tgn:7029392"
    ],
    "tgn:id":2355492,
    "tgn:name":"Goose Creek",
    "tgn:placetype":[
        "aat:300008706"
    ]
},
  "bbox": [],
  "geometry": {"coordinates":[-84.9833,38.2667],"type":"Point"}
}