{
  "id": 7549428,
  "type": "Feature",
  "properties": {
    "tgn:hierarchy":[
        "tgn:7549428",
        "tgn:1000004",
        "tgn:7000198",
        "tgn:7016788",
        "tgn:7029392"
    ],
    "tgn:id":7549428,
    "tgn:name:en":"Dh\u0101nani",
    "tgn:placetype":[
        "aat:300008347"
    ]
},
  "bbox": [],
  "geometry": {"coordinates":[74.816152,27.778562],"type":"Point"}
}