{
  "id": 2023081,
  "type": "Feature",
  "properties": {
    "tgn:hierarchy":[
        "tgn:2023081",
        "tgn:2000294",
        "tgn:1000001",
        "tgn:7012149",
        "tgn:7007248",
        "tgn:7029392"
    ],
    "tgn:id":2023081,
    "tgn:name":"Guysie",
    "tgn:placetype":[
        "aat:300008347",
        "aat:300387210"
    ]
},
  "bbox": [],
  "geometry": {"coordinates":[-82.5167,31.5333],"type":"Point"}
}