{
  "id": 7386303,
  "type": "Feature",
  "properties": {
    "tgn:hierarchy":[
        "tgn:7386303",
        "tgn:1000001",
        "tgn:7005599",
        "tgn:7005560",
        "tgn:7029392"
    ],
    "tgn:id":7386303,
    "tgn:name":"Pe\u00f1a Loros, Punta",
    "tgn:placetype":[
        "aat:300386846"
    ]
},
  "bbox": [],
  "geometry": {"coordinates":[-94.65,18.316667],"type":"Point"}
}