{
  "id": 2326047,
  "type": "Feature",
  "properties": {
    "tgn:hierarchy":[
        "tgn:2326047",
        "tgn:1000001",
        "tgn:7006451",
        "tgn:2000092",
        "tgn:7012149",
        "tgn:7029392"
    ],
    "tgn:id":2326047,
    "tgn:name":"Fiftyfive Tank",
    "tgn:placetype":[
        "aat:300006191"
    ]
},
  "bbox": [],
  "geometry": {"coordinates":[-111.3333,34.7833],"type":"Point"}
}