<<<<<<< HEAD
{
  "id": 2250137,
  "type": "Feature",
  "properties": {
    "tgn:hierarchy":[
        "tgn:2250137",
        "tgn:1000001",
        "tgn:7012149",
        "tgn:7007566",
        "tgn:7029392"
    ],
    "tgn:id":2250137,
    "tgn:name":"Collins Draw",
    "tgn:placetype":[
        "aat:300008761"
    ]
},
  "bbox": [],
  "geometry": {"coordinates":[-105.2667,32.5],"type":"Point"}
}
=======
{"geometry":{"type":"Point","coordinates":[-105.266700,32.500000]},"type":"Feature","properties":{"hierarchy":["tgn:2250137","tgn:1000001","tgn:7012149","tgn:7007566","tgn:7029392"],"placetype":["aat:300008761"],"id":2250137,"name:xx":"Collins Draw"}}
>>>>>>> 03f74aca74312dbeaf24d7e61306dd6a786dc3d0
