{
  "id": 2504156,
  "type": "Feature",
  "properties": {
    "tgn:hierarchy":[
        "tgn:2504156",
        "tgn:1002165",
        "tgn:1000001",
        "tgn:7012149",
        "tgn:7007517",
        "tgn:7029392"
    ],
    "tgn:id":2504156,
    "tgn:name":"Meadow Neck",
    "tgn:placetype":[
        "aat:300008850"
    ]
},
  "bbox": [],
  "geometry": {"coordinates":[-70.5167,41.5667],"type":"Point"}
}