{
  "id": 7475560,
  "type": "Feature",
  "properties": {
    "tgn:hierarchy":[
        "tgn:7475560",
        "tgn:7487020",
        "tgn:1000004",
        "tgn:1000141",
        "tgn:7029392"
    ],
    "tgn:id":7475560,
    "tgn:name":"Xiaodonghe",
    "tgn:placetype":[
        "aat:300008798"
    ]
},
  "bbox": [],
  "geometry": {"coordinates":[120.996172,24.559327],"type":"Point"}
}