{
  "id": 1074200,
  "type": "Feature",
  "properties": {
    "tgn:hierarchy":[
        "tgn:1074200",
        "tgn:1000004",
        "tgn:7018118",
        "tgn:1000111",
        "tgn:7029392"
    ],
    "tgn:id":1074200,
    "tgn:name":"Zili",
    "tgn:placetype":[
        "aat:300008347"
    ]
},
  "bbox": [],
  "geometry": {"coordinates":[100.45,26.8333],"type":"Point"}
}