{
  "id": 7448632,
  "type": "Feature",
  "properties": {
    "tgn:hierarchy":[
        "tgn:7448632",
        "tgn:7002444",
        "tgn:1000003",
        "tgn:7008082",
        "tgn:7008591",
        "tgn:7029392"
    ],
    "tgn:id":7448632,
    "tgn:name:en":"Spey, Loch",
    "tgn:placetype":[
        "aat:300008680"
    ]
},
  "bbox": [],
  "geometry": {"coordinates":[-4.583333,57.033333],"type":"Point"}
}