{
  "id": 2317938,
  "type": "Feature",
  "properties": {
    "tgn:hierarchy":[
        "tgn:2317938",
        "tgn:1000001",
        "tgn:7012149",
        "tgn:2001442",
        "tgn:7007566",
        "tgn:7029392"
    ],
    "tgn:id":2317938,
    "tgn:name":"English Spring",
    "tgn:placetype":[
        "aat:300008697"
    ]
},
  "bbox": [],
  "geometry": {"coordinates":[-105.4667,33.45],"type":"Point"}
}