{
  "id": 7318342,
  "type": "Feature",
  "properties": {
    "tgn:hierarchy":[
        "tgn:7318342",
        "tgn:1001702",
        "tgn:1000049",
        "tgn:1000002",
        "tgn:7029392"
    ],
    "tgn:id":7318342,
    "tgn:name":"Cordillera, Arrecife",
    "tgn:placetype":[
        "aat:300008808"
    ]
},
  "bbox": [],
  "geometry": {"coordinates":[-75.366667,-51.05],"type":"Point"}
}