{
  "id": 7124133,
  "type": "Feature",
  "properties": {
    "tgn:hierarchy":[
        "tgn:7124133",
        "tgn:1000003",
        "tgn:7003676",
        "tgn:7000084",
        "tgn:7029392"
    ],
    "tgn:id":7124133,
    "tgn:name":"Neurhede",
    "tgn:placetype":[
        "aat:300008347"
    ]
},
  "bbox": [],
  "geometry": {"coordinates":[7.216667,53.033333],"type":"Point"}
}