{
  "id": 7587932,
  "type": "Feature",
  "properties": {
    "tgn:hierarchy":[
        "tgn:7587932",
        "tgn:1000004",
        "tgn:7000198",
        "tgn:7000799",
        "tgn:7029392"
    ],
    "tgn:id":7587932,
    "tgn:name:en":"Pirapur",
    "tgn:placetype":[
        "aat:300008347"
    ]
},
  "bbox": [],
  "geometry": {"coordinates":[74.568056,34.054167],"type":"Point"}
}