{
  "id": 2758898,
  "type": "Feature",
  "properties": {
    "tgn:hierarchy":[
        "tgn:2758898",
        "tgn:1000001",
        "tgn:7012149",
        "tgn:2001208",
        "tgn:7007523",
        "tgn:7029392"
    ],
    "tgn:id":2758898,
    "tgn:name":"West Fire Prairie Creek",
    "tgn:placetype":[
        "aat:300008706"
    ]
},
  "bbox": [],
  "geometry": {"coordinates":[-94.2667,39.05],"type":"Point"}
}