{
  "id": 2665975,
  "type": "Feature",
  "properties": {
    "tgn:hierarchy":[
        "tgn:2665975",
        "tgn:1000001",
        "tgn:7012149",
        "tgn:1002582",
        "tgn:7007240",
        "tgn:7029392"
    ],
    "tgn:id":2665975,
    "tgn:name":"Sister Keys",
    "tgn:placetype":[
        "aat:300008791"
    ]
},
  "bbox": [],
  "geometry": {"coordinates":[-82.05,26.4833],"type":"Point"}
}