{
  "id": 2741055,
  "type": "Feature",
  "properties": {
    "tgn:hierarchy":[
        "tgn:2741055",
        "tgn:1000001",
        "tgn:7012149",
        "tgn:2000490",
        "tgn:7007250",
        "tgn:7029392"
    ],
    "tgn:id":2741055,
    "tgn:name":"Upper Stump Canyon Reservoir",
    "tgn:placetype":[
        "aat:300006191"
    ]
},
  "bbox": [],
  "geometry": {"coordinates":[-112.6833,42.55],"type":"Point"}
}