{
  "id": 7090254,
  "type": "Feature",
  "properties": {
    "tgn:hierarchy":[
        "tgn:7090254",
        "tgn:1000003",
        "tgn:7003677",
        "tgn:7000084",
        "tgn:7029392"
    ],
    "tgn:id":7090254,
    "tgn:name":"Vennberg",
    "tgn:placetype":[
        "aat:300000745"
    ]
},
  "bbox": [],
  "geometry": {"coordinates":[6.183333,51.233333],"type":"Point"}
}