{
  "id": 7294610,
  "type": "Feature",
  "properties": {
    "tgn:hierarchy":[
        "tgn:7294610",
        "tgn:7002844",
        "tgn:7030216",
        "tgn:1000003",
        "tgn:1000095",
        "tgn:7029392"
    ],
    "tgn:id":7294610,
    "tgn:name":"Vallfogona de R\u00educorp",
    "tgn:placetype":[
        "aat:300008347"
    ]
},
  "bbox": [],
  "geometry": {"coordinates":[1.239275,41.562688],"type":"Point"}
}