{
  "id": 2689369,
  "type": "Feature",
  "properties": {
    "tgn:hierarchy":[
        "tgn:2689369",
        "tgn:1000001",
        "tgn:7012149",
        "tgn:2002115",
        "tgn:7007827",
        "tgn:7029392"
    ],
    "tgn:id":2689369,
    "tgn:name":"Squaw Creek",
    "tgn:placetype":[
        "aat:300008706"
    ]
},
  "bbox": [],
  "geometry": {"coordinates":[-111.2667,41.25],"type":"Point"}
}