{
  "id": 2596678,
  "type": "Feature",
  "properties": {
    "tgn:hierarchy":[
        "tgn:2596678",
        "tgn:1000001",
        "tgn:7012149",
        "tgn:7029392"
    ],
    "tgn:id":2596678,
    "tgn:name":"Powell Branch",
    "tgn:placetype":[
        "aat:300008699"
    ]
},
  "bbox": [],
  "geometry": {"coordinates":[-87.8833,36.6667],"type":"Point"}
}