{
  "id": 7457038,
  "type": "Feature",
  "properties": {
    "tgn:hierarchy":[
        "tgn:7457038",
        "tgn:7002443",
        "tgn:1000003",
        "tgn:7018956",
        "tgn:7008591",
        "tgn:7029392"
    ],
    "tgn:id":7457038,
    "tgn:name:en":"Marshfield",
    "tgn:placetype":[
        "aat:300008347"
    ]
},
  "bbox": [],
  "geometry": {"coordinates":[-3.073056,51.533889],"type":"Point"}
}