{
  "id": 2708949,
  "type": "Feature",
  "properties": {
    "tgn:hierarchy":[
        "tgn:2708949",
        "tgn:1000001",
        "tgn:7012149",
        "tgn:2001396",
        "tgn:7007525",
        "tgn:7029392"
    ],
    "tgn:id":2708949,
    "tgn:name":"T Briggs Lake",
    "tgn:placetype":[
        "aat:300008680"
    ]
},
  "bbox": [],
  "geometry": {"coordinates":[-102.5167,42.1667],"type":"Point"}
}