{
  "id": 2768385,
  "type": "Feature",
  "properties": {
    "tgn:hierarchy":[
        "tgn:2768385",
        "tgn:7006450",
        "tgn:1000001",
        "tgn:7012149",
        "tgn:2124002",
        "tgn:7029392"
    ],
    "tgn:id":2768385,
    "tgn:name":"Whitestone Point",
    "tgn:placetype":[
        "aat:300008850"
    ]
},
  "bbox": [],
  "geometry": {"coordinates":[-135.55,57.2333],"type":"Point"}
}