{
  "id": 2435630,
  "type": "Feature",
  "properties": {
    "tgn:hierarchy":[
        "tgn:2435630",
        "tgn:1000001",
        "tgn:7012149",
        "tgn:2000545",
        "tgn:7007252",
        "tgn:7029392"
    ],
    "tgn:id":2435630,
    "tgn:name":"Kessinger Ditch",
    "tgn:placetype":[
        "aat:300006075"
    ]
},
  "bbox": [],
  "geometry": {"coordinates":[-87.3167,38.6333],"type":"Point"}
}