{
  "id": 2496425,
  "type": "Feature",
  "properties": {
    "tgn:hierarchy":[
        "tgn:2496425",
        "tgn:1000001",
        "tgn:1002949",
        "tgn:7012149",
        "tgn:7007159",
        "tgn:7029392"
    ],
    "tgn:id":2496425,
    "tgn:name":"Mathews Pond",
    "tgn:placetype":[
        "aat:300006191"
    ]
},
  "bbox": [],
  "geometry": {"coordinates":[-72.2167,41.9667],"type":"Point"}
}