{
  "id": 7165753,
  "type": "Feature",
  "properties": {
    "tgn:hierarchy":[
        "tgn:7165753",
        "tgn:1000003",
        "tgn:7003677",
        "tgn:7000084",
        "tgn:7029392"
    ],
    "tgn:id":7165753,
    "tgn:name":"Hausweiler",
    "tgn:placetype":[
        "aat:300008347"
    ]
},
  "bbox": [],
  "geometry": {"coordinates":[6.816667,50.716667],"type":"Point"}
}