{
  "id": 7429634,
  "type": "Feature",
  "properties": {
    "tgn:hierarchy":[
        "tgn:7429634",
        "tgn:7005583",
        "tgn:1000001",
        "tgn:7005560",
        "tgn:7029392"
    ],
    "tgn:id":7429634,
    "tgn:name":"Estaci\u00f3n R\u00edo Chico",
    "tgn:placetype":[
        "aat:300007783"
    ]
},
  "bbox": [],
  "geometry": {"coordinates":[-104.966667,24.033333],"type":"Point"}
}