{
  "id": 7501030,
  "type": "Feature",
  "properties": {
    "tgn:hierarchy":[
        "tgn:7501030",
        "tgn:7487020",
        "tgn:1000004",
        "tgn:1000141",
        "tgn:7029392"
    ],
    "tgn:id":7501030,
    "tgn:name":"Daqiuyuan",
    "tgn:placetype":[
        "aat:300008347"
    ]
},
  "bbox": [],
  "geometry": {"coordinates":[120.698333,24.469722],"type":"Point"}
}