{
  "id": 7345300,
  "type": "Feature",
  "properties": {
    "tgn:hierarchy":[
        "tgn:7345300",
        "tgn:7002759",
        "tgn:7002845",
        "tgn:1000003",
        "tgn:1000095",
        "tgn:7029392"
    ],
    "tgn:id":7345300,
    "tgn:name":"Alforque",
    "tgn:placetype":[
        "aat:300008347"
    ]
},
  "bbox": [],
  "geometry": {"coordinates":[-0.383333,41.333333],"type":"Point"}
}