<<<<<<< HEAD
{
  "id": 2768751,
  "type": "Feature",
  "properties": {
    "tgn:hierarchy":[
        "tgn:2768751",
        "tgn:2000455",
        "tgn:1000001",
        "tgn:7012149",
        "tgn:7007250",
        "tgn:7029392"
    ],
    "tgn:id":2768751,
    "tgn:name":"Whitman Hollow",
    "tgn:placetype":[
        "aat:300008761"
    ]
},
  "bbox": [],
  "geometry": {"coordinates":[-111.1833,42.35],"type":"Point"}
}
=======
{"geometry":{"type":"Point","coordinates":[-111.183300,42.350000]},"type":"Feature","properties":{"hierarchy":["tgn:2768751","tgn:2000455","tgn:1000001","tgn:7012149","tgn:7007250","tgn:7029392"],"placetype":["aat:300008761"],"id":2768751,"name:xx":"Whitman Hollow"}}
>>>>>>> 03f74aca74312dbeaf24d7e61306dd6a786dc3d0
