<<<<<<< HEAD
{
  "id": 7056502,
  "type": "Feature",
  "properties": {
    "tgn:hierarchy":[
        "tgn:7056502",
        "tgn:1003506",
        "tgn:1000003",
        "tgn:7002993",
        "tgn:1000080",
        "tgn:7029392"
    ],
    "tgn:id":7056502,
    "tgn:name":"Mels",
    "tgn:placetype":[
        "aat:300008347"
    ]
},
  "bbox": [],
  "geometry": {"coordinates":[13.108611,46.179722],"type":"Point"}
}
=======
{"geometry":{"type":"Point","coordinates":[13.108611,46.179722]},"type":"Feature","properties":{"hierarchy":["tgn:7056502","tgn:1003506","tgn:1000003","tgn:7002993","tgn:1000080","tgn:7029392"],"placetype":["aat:300008347"],"id":7056502,"name:xx":"Mels"}}
>>>>>>> 03f74aca74312dbeaf24d7e61306dd6a786dc3d0
