{
  "id": 7056502,
  "type": "Feature",
  "properties": {
    "tgn:hierarchy":[
        "tgn:7056502",
        "tgn:1003506",
        "tgn:1000003",
        "tgn:7002993",
        "tgn:1000080",
        "tgn:7029392"
    ],
    "tgn:id":7056502,
    "tgn:name":"Mels",
    "tgn:placetype":[
        "aat:300008347"
    ]
},
  "bbox": [],
  "geometry": {"coordinates":[13.108611,46.179722],"type":"Point"}
}