{
  "id": 2708173,
  "type": "Feature",
  "properties": {
    "tgn:hierarchy":[
        "tgn:2708173",
        "tgn:1000001",
        "tgn:7012149",
        "tgn:2000488",
        "tgn:7007250",
        "tgn:7029392"
    ],
    "tgn:id":2708173,
    "tgn:name":"Swisher Ridge",
    "tgn:placetype":[
        "aat:300266640"
    ]
},
  "bbox": [],
  "geometry": {"coordinates":[-116.9333,43.0333],"type":"Point"}
}