<<<<<<< HEAD
{
  "id": 2151034,
  "type": "Feature",
  "properties": {
    "tgn:hierarchy":[
        "tgn:2151034",
        "tgn:1000001",
        "tgn:7012149",
        "tgn:2001455",
        "tgn:7007566",
        "tgn:7029392"
    ],
    "tgn:id":2151034,
    "tgn:name":"Basso Four Mine",
    "tgn:placetype":[
        "aat:300000390"
    ]
},
  "bbox": [],
  "geometry": {"coordinates":[-106.4667,33.4],"type":"Point"}
}
=======
{"geometry":{"type":"Point","coordinates":[-106.466700,33.400000]},"type":"Feature","properties":{"hierarchy":["tgn:2151034","tgn:1000001","tgn:7012149","tgn:2001455","tgn:7007566","tgn:7029392"],"placetype":["aat:300000390"],"id":2151034,"name:xx":"Basso Four Mine"}}
>>>>>>> 03f74aca74312dbeaf24d7e61306dd6a786dc3d0
