{
  "id": 7297158,
  "type": "Feature",
  "properties": {
    "tgn:hierarchy":[
        "tgn:7297158",
        "tgn:7002842",
        "tgn:7001158",
        "tgn:1000003",
        "tgn:1000095",
        "tgn:7029392"
    ],
    "tgn:id":7297158,
    "tgn:name":"Tardesillas",
    "tgn:placetype":[
        "aat:300008347"
    ]
},
  "bbox": [],
  "geometry": {"coordinates":[-2.466667,41.833333],"type":"Point"}
}