{
  "id": 7285047,
  "type": "Feature",
  "properties": {
    "tgn:hierarchy":[
        "tgn:7285047",
        "tgn:1001692",
        "tgn:1000049",
        "tgn:1000002",
        "tgn:7029392"
    ],
    "tgn:id":7285047,
    "tgn:name":"Puesco Bajo",
    "tgn:placetype":[
        "aat:300000206"
    ]
},
  "bbox": [],
  "geometry": {"coordinates":[-71.566667,-39.533333],"type":"Point"}
}