{
  "id": 2776710,
  "type": "Feature",
  "properties": {
    "tgn:hierarchy":[
        "tgn:2776710",
        "tgn:1000001",
        "tgn:7012149",
        "tgn:7014612",
        "tgn:7007568",
        "tgn:7029392"
    ],
    "tgn:id":2776710,
    "tgn:name":"Windmill Lake",
    "tgn:placetype":[
        "aat:300006191"
    ]
},
  "bbox": [],
  "geometry": {"coordinates":[-73.6667,41.1333],"type":"Point"}
}