{
  "id": 7575115,
  "type": "Feature",
  "properties": {
    "tgn:hierarchy":[
        "tgn:7575115",
        "tgn:7001819",
        "tgn:1000004",
        "tgn:7000198",
        "tgn:7029392"
    ],
    "tgn:id":7575115,
    "tgn:name:en":"Kebang",
    "tgn:placetype":[
        "aat:300008347"
    ]
},
  "bbox": [],
  "geometry": {"coordinates":[95.037271,28.159807],"type":"Point"}
}