{
  "id": 2340606,
  "type": "Feature",
  "properties": {
    "tgn:hierarchy":[
        "tgn:2340606",
        "tgn:1000001",
        "tgn:2001416",
        "tgn:7012149",
        "tgn:7007526",
        "tgn:7029392"
    ],
    "tgn:id":2340606,
    "tgn:name":"Frenchman Spring",
    "tgn:placetype":[
        "aat:300008697"
    ]
},
  "bbox": [],
  "geometry": {"coordinates":[-114.35,38.2333],"type":"Point"}
}