{
  "id": 7212715,
  "type": "Feature",
  "properties": {
    "tgn:hierarchy":[
        "tgn:7212715",
        "tgn:7003692",
        "tgn:1000003",
        "tgn:7000084",
        "tgn:7029392"
    ],
    "tgn:id":7212715,
    "tgn:name":"Boosen",
    "tgn:placetype":[
        "aat:300387502"
    ]
},
  "bbox": [],
  "geometry": {"coordinates":[9.65,47.95],"type":"Point"}
}