{
  "id": 7211538,
  "type": "Feature",
  "properties": {
    "tgn:hierarchy":[
        "tgn:7211538",
        "tgn:7000096",
        "tgn:1000003",
        "tgn:7000084",
        "tgn:7029392"
    ],
    "tgn:id":7211538,
    "tgn:name":"Behrensdorf Siedlung",
    "tgn:placetype":[
        "aat:300008347"
    ]
},
  "bbox": [],
  "geometry": {"coordinates":[14.033333,52.183333],"type":"Point"}
}