{
  "id": 7555368,
  "type": "Feature",
  "properties": {
    "tgn:hierarchy":[
        "tgn:7555368",
        "tgn:1000004",
        "tgn:7000198",
        "tgn:1001895",
        "tgn:7029392"
    ],
    "tgn:id":7555368,
    "tgn:name:en":"N\u0101ndari",
    "tgn:placetype":[
        "aat:300008347"
    ]
},
  "bbox": [],
  "geometry": {"coordinates":[75.186118,21.113618],"type":"Point"}
}