{
  "id": 7545718,
  "type": "Feature",
  "properties": {
    "tgn:hierarchy":[
        "tgn:7545718",
        "tgn:1000004",
        "tgn:7000198",
        "tgn:7016694",
        "tgn:7029392"
    ],
    "tgn:id":7545718,
    "tgn:name:en":"B\u0101ruda",
    "tgn:placetype":[
        "aat:300008347"
    ]
},
  "bbox": [],
  "geometry": {"coordinates":[84.616667,20.016667],"type":"Point"}
}