{
  "id": 7426213,
  "type": "Feature",
  "properties": {
    "tgn:hierarchy":[
        "tgn:7426213",
        "tgn:7005581",
        "tgn:1000001",
        "tgn:7005560",
        "tgn:7029392"
    ],
    "tgn:id":7426213,
    "tgn:name":"El Carbonero",
    "tgn:placetype":[
        "aat:300008347"
    ]
},
  "bbox": [],
  "geometry": {"coordinates":[-105.983333,27.35],"type":"Point"}
}