{
  "id": 7075193,
  "type": "Feature",
  "properties": {
    "tgn:hierarchy":[
        "tgn:7075193",
        "tgn:7000096",
        "tgn:1000003",
        "tgn:7000084",
        "tgn:7029392"
    ],
    "tgn:id":7075193,
    "tgn:name":"Zossen, Forst",
    "tgn:placetype":[
        "aat:300008863"
    ]
},
  "bbox": [],
  "geometry": {"coordinates":[13.483333,52.183333],"type":"Point"}
}