{
  "id": 2003507,
  "type": "Feature",
  "properties": {
    "tgn:hierarchy":[
        "tgn:2003507",
        "tgn:7002659",
        "tgn:1000001",
        "tgn:2000008",
        "tgn:7012149",
        "tgn:7029392"
    ],
    "tgn:id":2003507,
    "tgn:name":"Five Points",
    "tgn:placetype":[
        "aat:300008347"
    ]
},
  "bbox": [],
  "geometry": {"coordinates":[-85.35,33.0167],"type":"Point"}
}