{
  "id": 2089844,
  "type": "Feature",
  "properties": {
    "tgn:hierarchy":[
        "tgn:2089844",
        "tgn:1000001",
        "tgn:7012149",
        "tgn:1002612",
        "tgn:7007710",
        "tgn:7029392"
    ],
    "tgn:id":2089844,
    "tgn:name":"Koonsville",
    "tgn:placetype":[
        "aat:300008347"
    ]
},
  "bbox": [],
  "geometry": {"coordinates":[-76.15,41.1667],"type":"Point"}
}