{
  "id": 2463575,
  "type": "Feature",
  "properties": {
    "tgn:hierarchy":[
        "tgn:2463575",
        "tgn:1000001",
        "tgn:7012149",
        "tgn:2002003",
        "tgn:7007826",
        "tgn:7029392"
    ],
    "tgn:id":2463575,
    "tgn:name":"Lobo Lake",
    "tgn:placetype":[
        "aat:300008680"
    ]
},
  "bbox": [],
  "geometry": {"coordinates":[-102.3667,33.5667],"type":"Point"}
}