{
  "id": 2510734,
  "type": "Feature",
  "properties": {
    "tgn:hierarchy":[
        "tgn:2510734",
        "tgn:1000001",
        "tgn:2001472",
        "tgn:7012149",
        "tgn:7007709",
        "tgn:7029392"
    ],
    "tgn:id":2510734,
    "tgn:name":"Middleton, Lake",
    "tgn:placetype":[
        "aat:300008680"
    ]
},
  "bbox": [],
  "geometry": {"coordinates":[-78.0333,34.0167],"type":"Point"}
}