{
  "id": 7324535,
  "type": "Feature",
  "properties": {
    "tgn:hierarchy":[
        "tgn:7324535",
        "tgn:7002758",
        "tgn:7002841",
        "tgn:1000003",
        "tgn:1000095",
        "tgn:7029392"
    ],
    "tgn:id":7324535,
    "tgn:name":"San Pedro, Arroyo de",
    "tgn:placetype":[
        "aat:300008699"
    ]
},
  "bbox": [],
  "geometry": {"coordinates":[-5.733333,37.866667],"type":"Point"}
}