{
  "id": 7349106,
  "type": "Feature",
  "properties": {
    "tgn:hierarchy":[
        "tgn:7349106",
        "tgn:7005580",
        "tgn:1000001",
        "tgn:7005560",
        "tgn:7029392"
    ],
    "tgn:id":7349106,
    "tgn:name":"Aguacatenango",
    "tgn:placetype":[
        "aat:300008347"
    ]
},
  "bbox": [],
  "geometry": {"coordinates":[-92.466667,16.45],"type":"Point"}
}