<<<<<<< HEAD
{
  "id": 2332317,
  "type": "Feature",
  "properties": {
    "tgn:hierarchy":[
        "tgn:2332317",
        "tgn:1000001",
        "tgn:7012149",
        "tgn:2001076",
        "tgn:7007521",
        "tgn:7029392"
    ],
    "tgn:id":2332317,
    "tgn:name":"Flood Slough",
    "tgn:placetype":[
        "aat:300008905"
    ]
},
  "bbox": [],
  "geometry": {"coordinates":[-96.6833,45.6167],"type":"Point"}
}
=======
{"geometry":{"type":"Point","coordinates":[-96.683300,45.616700]},"type":"Feature","properties":{"hierarchy":["tgn:2332317","tgn:1000001","tgn:7012149","tgn:2001076","tgn:7007521","tgn:7029392"],"placetype":["aat:300008905"],"id":2332317,"name:xx":"Flood Slough"}}
>>>>>>> 03f74aca74312dbeaf24d7e61306dd6a786dc3d0
