{
  "id": 7291889,
  "type": "Feature",
  "properties": {
    "tgn:hierarchy":[
        "tgn:7291889",
        "tgn:1001623",
        "tgn:1000049",
        "tgn:1000002",
        "tgn:7029392"
    ],
    "tgn:id":7291889,
    "tgn:name":"Encadenados, Lagos",
    "tgn:placetype":[
        "aat:300008680"
    ]
},
  "bbox": [],
  "geometry": {"coordinates":[-72.616667,-48.333333],"type":"Point"}
}