<<<<<<< HEAD
{
  "id": 7480198,
  "type": "Feature",
  "properties": {
    "tgn:hierarchy":[
        "tgn:7480198",
        "tgn:1000004",
        "tgn:1000959",
        "tgn:1000141",
        "tgn:7029392"
    ],
    "tgn:id":7480198,
    "tgn:name":"Mengjia Qiao",
    "tgn:placetype":[
        "aat:300007836"
    ]
},
  "bbox": [],
  "geometry": {"coordinates":[121.452146,25.127036],"type":"Point"}
}
=======
{"geometry":{"type":"Point","coordinates":[121.452146,25.127036]},"type":"Feature","properties":{"hierarchy":["tgn:7480198","tgn:1000004","tgn:1000959","tgn:1000141","tgn:7029392"],"placetype":["aat:300007836"],"id":7480198,"name:xx":"Mengjia Qiao"}}
>>>>>>> 03f74aca74312dbeaf24d7e61306dd6a786dc3d0
