{
  "id": 7480198,
  "type": "Feature",
  "properties": {
    "tgn:hierarchy":[
        "tgn:7480198",
        "tgn:1000004",
        "tgn:1000959",
        "tgn:1000141",
        "tgn:7029392"
    ],
    "tgn:id":7480198,
    "tgn:name":"Mengjia Qiao",
    "tgn:placetype":[
        "aat:300007836"
    ]
},
  "bbox": [],
  "geometry": {"coordinates":[121.452146,25.127036],"type":"Point"}
}