{
  "id": 7008624,
  "type": "Feature",
  "properties": {
    "tgn:hierarchy":[
        "tgn:7008624",
        "tgn:7002759",
        "tgn:7008909",
        "tgn:1000003",
        "tgn:1000095",
        "tgn:7029392"
    ],
    "tgn:id":7008624,
    "tgn:name":"Santa Cruz de la Ser\u00f3s",
    "tgn:placetype":[
        "aat:300008347"
    ]
},
  "bbox": [],
  "geometry": {"coordinates":[-0.675146,42.522705],"type":"Point"}
}