{
  "id": 2432042,
  "type": "Feature",
  "properties": {
    "tgn:hierarchy":[
        "tgn:2432042",
        "tgn:1000001",
        "tgn:7006451",
        "tgn:7012149",
        "tgn:2000099",
        "tgn:7029392"
    ],
    "tgn:id":2432042,
    "tgn:name":"Kawaika-A",
    "tgn:placetype":[
        "aat:300008347"
    ]
},
  "bbox": [],
  "geometry": {"coordinates":[-110.2167,35.7333],"type":"Point"}
}