{
  "id": 2595082,
  "type": "Feature",
  "properties": {
    "tgn:hierarchy":[
        "tgn:2595082",
        "tgn:1000001",
        "tgn:7012149",
        "tgn:1002413",
        "tgn:7007826",
        "tgn:7029392"
    ],
    "tgn:id":2595082,
    "tgn:name":"Post Oak Hollow",
    "tgn:placetype":[
        "aat:300008761"
    ]
},
  "bbox": [],
  "geometry": {"coordinates":[-97.45,28.7167],"type":"Point"}
}