{
  "id": 1054813,
  "type": "Feature",
  "properties": {
    "tgn:hierarchy":[
        "tgn:1054813",
        "tgn:7006625",
        "tgn:7006632",
        "tgn:1000003",
        "tgn:7006540",
        "tgn:7029392"
    ],
    "tgn:id":1054813,
    "tgn:name":"K\u00f5rgessaare",
    "tgn:placetype":[
        "aat:300008347"
    ]
},
  "bbox": [],
  "geometry": {"coordinates":[22.474,58.982],"type":"Point"}
}