{
  "id": 7277057,
  "type": "Feature",
  "properties": {
    "tgn:hierarchy":[
        "tgn:7277057",
        "tgn:7002464",
        "tgn:1000049",
        "tgn:1000002",
        "tgn:7029392"
    ],
    "tgn:id":7277057,
    "tgn:name":"Charipujo",
    "tgn:placetype":[
        "aat:300008347"
    ]
},
  "bbox": [],
  "geometry": {"coordinates":[-69.883889,-17.923056],"type":"Point"}
}