{
  "id": 2659518,
  "type": "Feature",
  "properties": {
    "tgn:hierarchy":[
        "tgn:2659518",
        "tgn:1000001",
        "tgn:7012149",
        "tgn:2002121",
        "tgn:7007827",
        "tgn:7029392"
    ],
    "tgn:id":2659518,
    "tgn:name":"Shingle Creek",
    "tgn:placetype":[
        "aat:300008706"
    ]
},
  "bbox": [],
  "geometry": {"coordinates":[-112.0167,38.5833],"type":"Point"}
}