{
  "id": 7329766,
  "type": "Feature",
  "properties": {
    "tgn:hierarchy":[
        "tgn:7329766",
        "tgn:7002759",
        "tgn:7002843",
        "tgn:1000003",
        "tgn:1000095",
        "tgn:7029392"
    ],
    "tgn:id":7329766,
    "tgn:name":"La Cuba",
    "tgn:placetype":[
        "aat:300008347"
    ]
},
  "bbox": [],
  "geometry": {"coordinates":[-0.283333,40.583333],"type":"Point"}
}