{
  "id": 7512598,
  "type": "Feature",
  "properties": {
    "tgn:hierarchy":[
        "tgn:7512598",
        "tgn:1008380",
        "tgn:1000226",
        "tgn:7000512",
        "tgn:1000006",
        "tgn:7029392"
    ],
    "tgn:id":7512598,
    "tgn:name:en":"Holdsworth, Mount",
    "tgn:placetype":[
        "aat:300008795"
    ]
},
  "bbox": [],
  "geometry": {"coordinates":[175.416667,-40.866667],"type":"Point"}
}