{
  "id": 7070001,
  "type": "Feature",
  "properties": {
    "tgn:hierarchy":[
        "tgn:7070001",
        "tgn:1000003",
        "tgn:7003677",
        "tgn:7000084",
        "tgn:7029392"
    ],
    "tgn:id":7070001,
    "tgn:name":"Tift-Holz",
    "tgn:placetype":[
        "aat:300008863"
    ]
},
  "bbox": [],
  "geometry": {"coordinates":[9.133333,51.683333],"type":"Point"}
}