{
  "id": 2192156,
  "type": "Feature",
  "properties": {
    "tgn:hierarchy":[
        "tgn:2192156",
        "tgn:1000001",
        "tgn:7012149",
        "tgn:2000234",
        "tgn:7007158",
        "tgn:7029392"
    ],
    "tgn:id":2192156,
    "tgn:name":"Bramier Spring",
    "tgn:placetype":[
        "aat:300008697"
    ]
},
  "bbox": [],
  "geometry": {"coordinates":[-108.3333,38.3167],"type":"Point"}
}