{
  "id": 2174845,
  "type": "Feature",
  "properties": {
    "tgn:hierarchy":[
        "tgn:2174845",
        "tgn:1000001",
        "tgn:1002213",
        "tgn:7012149",
        "tgn:7007710",
        "tgn:7029392"
    ],
    "tgn:id":2174845,
    "tgn:name":"Bitts Hill",
    "tgn:placetype":[
        "aat:300008798"
    ]
},
  "bbox": [],
  "geometry": {"coordinates":[-75.2833,40.5333],"type":"Point"}
}