<<<<<<< HEAD
{
  "id": 7474634,
  "type": "Feature",
  "properties": {
    "tgn:hierarchy":[
        "tgn:7474634",
        "tgn:1000004",
        "tgn:7467799",
        "tgn:1000141",
        "tgn:7029392"
    ],
    "tgn:id":7474634,
    "tgn:name":"Youcuo Nongchang",
    "tgn:placetype":[
        "aat:300000206"
    ]
},
  "bbox": [],
  "geometry": {"coordinates":[120.348699,23.8541],"type":"Point"}
}
=======
{"geometry":{"type":"Point","coordinates":[120.348699,23.854100]},"type":"Feature","properties":{"hierarchy":["tgn:7474634","tgn:1000004","tgn:7467799","tgn:1000141","tgn:7029392"],"placetype":["aat:300000206"],"id":7474634,"name:xx":"Youcuo Nongchang"}}
>>>>>>> 03f74aca74312dbeaf24d7e61306dd6a786dc3d0
