{
  "id": 7182395,
  "type": "Feature",
  "properties": {
    "tgn:hierarchy":[
        "tgn:7182395",
        "tgn:1000003",
        "tgn:7003673",
        "tgn:7000084",
        "tgn:7029392"
    ],
    "tgn:id":7182395,
    "tgn:name":"F\u00fcrstenmoor",
    "tgn:placetype":[
        "aat:300386886"
    ]
},
  "bbox": [],
  "geometry": {"coordinates":[9.933333,53.483333],"type":"Point"}
}