{
  "id": 7367048,
  "type": "Feature",
  "properties": {
    "tgn:hierarchy":[
        "tgn:7367048",
        "tgn:7005586",
        "tgn:1000001",
        "tgn:7005560",
        "tgn:7029392"
    ],
    "tgn:id":7367048,
    "tgn:name":"El Platanillo",
    "tgn:placetype":[
        "aat:300008347"
    ]
},
  "bbox": [],
  "geometry": {"coordinates":[-104.633333,19.95],"type":"Point"}
}