{
  "id": 7408751,
  "type": "Feature",
  "properties": {
    "tgn:hierarchy":[
        "tgn:7408751",
        "tgn:1000001",
        "tgn:1001893",
        "tgn:7005560",
        "tgn:7029392"
    ],
    "tgn:id":7408751,
    "tgn:name":"Santa Ana",
    "tgn:placetype":[
        "aat:300008347"
    ]
},
  "bbox": [],
  "geometry": {"coordinates":[-98.654167,19.775],"type":"Point"}
}