{
  "id": 7067406,
  "type": "Feature",
  "properties": {
    "tgn:hierarchy":[
        "tgn:7067406",
        "tgn:7003692",
        "tgn:1000003",
        "tgn:7000084",
        "tgn:7029392"
    ],
    "tgn:id":7067406,
    "tgn:name":"Stocksberg",
    "tgn:placetype":[
        "aat:300008347"
    ]
},
  "bbox": [],
  "geometry": {"coordinates":[9.407222,49.07],"type":"Point"}
}