{
  "id": 7288195,
  "type": "Feature",
  "properties": {
    "tgn:hierarchy":[
        "tgn:7288195",
        "tgn:1001623",
        "tgn:1000049",
        "tgn:1000002",
        "tgn:7029392"
    ],
    "tgn:id":7288195,
    "tgn:name":"Humberto, Caleta",
    "tgn:placetype":[
        "aat:300132317"
    ]
},
  "bbox": [],
  "geometry": {"coordinates":[-75.283333,-48.233333],"type":"Point"}
}