{
  "id": 7502082,
  "type": "Feature",
  "properties": {
    "tgn:hierarchy":[
        "tgn:7502082",
        "tgn:1000004",
        "tgn:7001009",
        "tgn:1000141",
        "tgn:7029392"
    ],
    "tgn:id":7502082,
    "tgn:name":"Dawanjiao",
    "tgn:placetype":[
        "aat:300008347"
    ]
},
  "bbox": [],
  "geometry": {"coordinates":[120.775508,24.11019],"type":"Point"}
}