{
  "id": 2154258,
  "type": "Feature",
  "properties": {
    "tgn:hierarchy":[
        "tgn:2154258",
        "tgn:1000001",
        "tgn:7012149",
        "tgn:2001440",
        "tgn:7007566",
        "tgn:7029392"
    ],
    "tgn:id":2154258,
    "tgn:name":"Bear Creek",
    "tgn:placetype":[
        "aat:300008706"
    ]
},
  "bbox": [],
  "geometry": {"coordinates":[-108.35,31.4167],"type":"Point"}
}