{
  "id": 7235008,
  "type": "Feature",
  "properties": {
    "tgn:hierarchy":[
        "tgn:7235008",
        "tgn:7002681",
        "tgn:7001395",
        "tgn:1000003",
        "tgn:1000074",
        "tgn:7029392"
    ],
    "tgn:id":7235008,
    "tgn:name":"Fo\u00fandion, Nis\u00eds",
    "tgn:placetype":[
        "aat:300008791"
    ]
},
  "bbox": [],
  "geometry": {"coordinates":[24.25,38.033333],"type":"Point"}
}