{
  "id": 2114880,
  "type": "Feature",
  "properties": {
    "tgn:hierarchy":[
        "tgn:2114880",
        "tgn:1000001",
        "tgn:7012149",
        "tgn:2002174",
        "tgn:7007919",
        "tgn:7029392"
    ],
    "tgn:id":2114880,
    "tgn:name":"Virginia Polytechnic Institute",
    "tgn:placetype":[
        "aat:300132384"
    ]
},
  "bbox": [],
  "geometry": {"coordinates":[-80.4167,37.2167],"type":"Point"}
}