{
  "id": 7275476,
  "type": "Feature",
  "properties": {
    "tgn:hierarchy":[
        "tgn:7275476",
        "tgn:1001630",
        "tgn:1000049",
        "tgn:1000002",
        "tgn:7029392"
    ],
    "tgn:id":7275476,
    "tgn:name":"Tronador, Cerro",
    "tgn:placetype":[
        "aat:300008795"
    ]
},
  "bbox": [],
  "geometry": {"coordinates":[-70.65,-26.433333],"type":"Point"}
}