<<<<<<< HEAD
{
  "id": 7352281,
  "type": "Feature",
  "properties": {
    "tgn:hierarchy":[
        "tgn:7352281",
        "tgn:1000001",
        "tgn:7005599",
        "tgn:7005560",
        "tgn:7029392"
    ],
    "tgn:id":7352281,
    "tgn:name":"Barrancones",
    "tgn:placetype":[
        "aat:300008347"
    ]
},
  "bbox": [],
  "geometry": {"coordinates":[-97.083333,19.866667],"type":"Point"}
}
=======
{"geometry":{"type":"Point","coordinates":[-97.083333,19.866667]},"type":"Feature","properties":{"hierarchy":["tgn:7352281","tgn:1000001","tgn:7005599","tgn:7005560","tgn:7029392"],"placetype":["aat:300008347"],"id":7352281,"name:xx":"Barrancones"}}
>>>>>>> 03f74aca74312dbeaf24d7e61306dd6a786dc3d0
