{
  "id": 1047455,
  "type": "Feature",
  "properties": {
    "tgn:hierarchy":[
        "tgn:1047455",
        "tgn:7005126",
        "tgn:1000003",
        "tgn:7003120",
        "tgn:1000080",
        "tgn:7029392"
    ],
    "tgn:id":1047455,
    "tgn:name":"Villanova Mondov\u00ec",
    "tgn:placetype":[
        "aat:300008347"
    ]
},
  "bbox": [],
  "geometry": {"coordinates":[7.75,44.35],"type":"Point"}
}