{
  "id": 7562646,
  "type": "Feature",
  "properties": {
    "tgn:hierarchy":[
        "tgn:7562646",
        "tgn:1000004",
        "tgn:7000198",
        "tgn:7016722",
        "tgn:7029392"
    ],
    "tgn:id":7562646,
    "tgn:name:en":"Bindwa Khurd I Reserved Forest",
    "tgn:placetype":[
        "aat:300008865"
    ]
},
  "bbox": [],
  "geometry": {"coordinates":[79.091204,26.491649],"type":"Point"}
}