{
  "id": 2663873,
  "type": "Feature",
  "properties": {
    "tgn:hierarchy":[
        "tgn:2663873",
        "tgn:1000001",
        "tgn:7012149",
        "tgn:2002288",
        "tgn:7013961",
        "tgn:7029392"
    ],
    "tgn:id":2663873,
    "tgn:name":"Silver Lake",
    "tgn:placetype":[
        "aat:300006191"
    ]
},
  "bbox": [],
  "geometry": {"coordinates":[-79.4833,39.25],"type":"Point"}
}