{
  "id": 7005821,
  "type": "Feature",
  "properties": {
    "tgn:hierarchy":[
        "tgn:7005821",
        "tgn:1000670",
        "tgn:1000002",
        "tgn:1000056",
        "tgn:7029392"
    ],
    "tgn:id":7005821,
    "tgn:name":"Lima",
    "tgn:placetype":[
        "aat:300008347",
        "aat:300008389",
        "aat:300387266",
        "aat:300387219",
        "aat:300005135",
        "aat:300264742",
        "aat:300387512",
        "aat:300387220",
        "aat:300387302"
    ]
},
  "bbox": [],
  "geometry": {"coordinates":[-77.05,-12.05],"type":"Point"}
}