{
  "id": 7509301,
  "type": "Feature",
  "properties": {
    "tgn:hierarchy":[
        "tgn:7509301",
        "tgn:1009227",
        "tgn:1000226",
        "tgn:1000006",
        "tgn:7016850",
        "tgn:7029392"
    ],
    "tgn:id":7509301,
    "tgn:name:en":"Thomson",
    "tgn:placetype":[
        "aat:300008699"
    ]
},
  "bbox": [],
  "geometry": {"coordinates":[169.883333,-43.883333],"type":"Point"}
}