{
  "id": 7230130,
  "type": "Feature",
  "properties": {
    "tgn:hierarchy":[
        "tgn:7230130",
        "tgn:7011170",
        "tgn:7002715",
        "tgn:1000003",
        "tgn:1000074",
        "tgn:7029392"
    ],
    "tgn:id":7230130,
    "tgn:name":"Khr\u00edsa",
    "tgn:placetype":[
        "aat:300008347"
    ]
},
  "bbox": [],
  "geometry": {"coordinates":[24.866667,41.133333],"type":"Point"}
}