{
  "id": 2780281,
  "type": "Feature",
  "properties": {
    "tgn:hierarchy":[
        "tgn:2780281",
        "tgn:1000001",
        "tgn:7012149",
        "tgn:2000206",
        "tgn:7007158",
        "tgn:7029392"
    ],
    "tgn:id":2780281,
    "tgn:name":"Womack Reservoirs",
    "tgn:placetype":[
        "aat:300006191"
    ]
},
  "bbox": [],
  "geometry": {"coordinates":[-107.95,39.0167],"type":"Point"}
}