{
  "id": 2653169,
  "type": "Feature",
  "properties": {
    "tgn:hierarchy":[
        "tgn:2653169",
        "tgn:2001423",
        "tgn:1000001",
        "tgn:7012149",
        "tgn:7007564",
        "tgn:7029392"
    ],
    "tgn:id":2653169,
    "tgn:name":"Seven Sisters Islands",
    "tgn:placetype":[
        "aat:300386853"
    ]
},
  "bbox": [],
  "geometry": {"coordinates":[-71.1667,43.5833],"type":"Point"}
}