{
  "id": 7446566,
  "type": "Feature",
  "properties": {
    "tgn:hierarchy":[
        "tgn:7446566",
        "tgn:5000432",
        "tgn:7002444",
        "tgn:1000003",
        "tgn:7008591",
        "tgn:7029392"
    ],
    "tgn:id":7446566,
    "tgn:name:en":"Strahangles Point",
    "tgn:placetype":[
        "aat:300386846"
    ]
},
  "bbox": [],
  "geometry": {"coordinates":[-2.216667,57.683333],"type":"Point"}
}