{
  "id": 7324161,
  "type": "Feature",
  "properties": {
    "tgn:hierarchy":[
        "tgn:7324161",
        "tgn:7008911",
        "tgn:1000003",
        "tgn:7002763",
        "tgn:1000095",
        "tgn:7029392"
    ],
    "tgn:id":7324161,
    "tgn:name":"San Isidro, R\u00edo de",
    "tgn:placetype":[
        "aat:300008699"
    ]
},
  "bbox": [],
  "geometry": {"coordinates":[-5.566667,43.116667],"type":"Point"}
}