{
  "id": 2205934,
  "type": "Feature",
  "properties": {
    "tgn:hierarchy":[
        "tgn:2205934",
        "tgn:1000001",
        "tgn:7012149",
        "tgn:1002569",
        "tgn:7007252",
        "tgn:7029392"
    ],
    "tgn:id":2205934,
    "tgn:name":"Bull Run",
    "tgn:placetype":[
        "aat:300008699"
    ]
},
  "bbox": [],
  "geometry": {"coordinates":[-87.5167,41.4333],"type":"Point"}
}