{
  "id": 2546047,
  "type": "Feature",
  "properties": {
    "tgn:hierarchy":[
        "tgn:2546047",
        "tgn:1000001",
        "tgn:7012149",
        "tgn:2002382",
        "tgn:7007923",
        "tgn:7029392"
    ],
    "tgn:id":2546047,
    "tgn:name":"North Fork Dry Piney Creek",
    "tgn:placetype":[
        "aat:300008706"
    ]
},
  "bbox": [],
  "geometry": {"coordinates":[-110.3167,42.4167],"type":"Point"}
}