{
  "id": 2271557,
  "type": "Feature",
  "properties": {
    "tgn:hierarchy":[
        "tgn:2271557",
        "tgn:1000001",
        "tgn:1002194",
        "tgn:7012149",
        "tgn:7007710",
        "tgn:7029392"
    ],
    "tgn:id":2271557,
    "tgn:name":"Cumiskey",
    "tgn:placetype":[
        "aat:300008347"
    ]
},
  "bbox": [],
  "geometry": {"coordinates":[-76.3167,41.5667],"type":"Point"}
}