{
  "id": 2332446,
  "type": "Feature",
  "properties": {
    "tgn:hierarchy":[
        "tgn:2332446",
        "tgn:1000001",
        "tgn:7012149",
        "tgn:1002418",
        "tgn:7007920",
        "tgn:7029392"
    ],
    "tgn:id":2332446,
    "tgn:name":"Florence Creek",
    "tgn:placetype":[
        "aat:300008706"
    ]
},
  "bbox": [],
  "geometry": {"coordinates":[-123.85,46.8833],"type":"Point"}
}