{
  "id": 1027764,
  "type": "Feature",
  "properties": {
    "tgn:hierarchy":[
        "tgn:1027764",
        "tgn:7594006",
        "tgn:1000003",
        "tgn:1000066",
        "tgn:7029392"
    ],
    "tgn:id":1027764,
    "tgn:name":"Bryrup",
    "tgn:placetype":[
        "aat:300008347"
    ]
},
  "bbox": [],
  "geometry": {"coordinates":[9.5333,56.0333],"type":"Point"}
}