{
  "id": 1083937,
  "type": "Feature",
  "properties": {
    "tgn:hierarchy":[
        "tgn:1083937",
        "tgn:1000004",
        "tgn:1001611",
        "tgn:1000135",
        "tgn:7029392"
    ],
    "tgn:id":1083937,
    "tgn:name":"Alicia",
    "tgn:placetype":[
        "aat:300008347"
    ]
},
  "bbox": [],
  "geometry": {"coordinates":[122.9333,7.5167],"type":"Point"}
}