{
  "id": 2586888,
  "type": "Feature",
  "properties": {
    "tgn:hierarchy":[
        "tgn:2586888",
        "tgn:1000001",
        "tgn:7012149",
        "tgn:2002113",
        "tgn:7007827",
        "tgn:7029392"
    ],
    "tgn:id":2586888,
    "tgn:name":"Plains, The",
    "tgn:placetype":[
        "aat:300008805"
    ]
},
  "bbox": [],
  "geometry": {"coordinates":[-112.85,37.4667],"type":"Point"}
}