{
  "id": 1133859,
  "type": "Feature",
  "properties": {
    "tgn:hierarchy":[
        "tgn:1133859",
        "tgn:1000001",
        "tgn:7012149",
        "tgn:7007706",
        "tgn:7029392"
    ],
    "tgn:id":1133859,
    "tgn:name":"Mill Creek",
    "tgn:placetype":[
        "aat:300008706"
    ]
},
  "bbox": [],
  "geometry": {"coordinates":[-83.6333,40.45],"type":"Point"}
}