{
  "id": 2520990,
  "type": "Feature",
  "properties": {
    "tgn:hierarchy":[
        "tgn:2520990",
        "tgn:1000001",
        "tgn:7012149",
        "tgn:2000481",
        "tgn:7007250",
        "tgn:7029392"
    ],
    "tgn:id":2520990,
    "tgn:name":"Montana Canyon",
    "tgn:placetype":[
        "aat:300008761"
    ]
},
  "bbox": [],
  "geometry": {"coordinates":[-112.9833,44.4333],"type":"Point"}
}