{
  "id": 7464621,
  "type": "Feature",
  "properties": {
    "tgn:hierarchy":[
        "tgn:7464621",
        "tgn:7002444",
        "tgn:1000003",
        "tgn:5000451",
        "tgn:7008591",
        "tgn:7029392"
    ],
    "tgn:id":7464621,
    "tgn:name:en":"Braemoray, Knock of",
    "tgn:placetype":[
        "aat:300008795"
    ]
},
  "bbox": [],
  "geometry": {"coordinates":[-3.65,57.45],"type":"Point"}
}