{
  "id": 7493886,
  "type": "Feature",
  "properties": {
    "tgn:hierarchy":[
        "tgn:7493886",
        "tgn:7468018",
        "tgn:1000004",
        "tgn:1000141",
        "tgn:7029392"
    ],
    "tgn:id":7493886,
    "tgn:name":"Gongtian Wuhao Qiao",
    "tgn:placetype":[
        "aat:300007836"
    ]
},
  "bbox": [],
  "geometry": {"coordinates":[120.614299,23.350354],"type":"Point"}
}