{
  "id": 7466425,
  "type": "Feature",
  "properties": {
    "tgn:hierarchy":[
        "tgn:7466425",
        "tgn:7002444",
        "tgn:1000003",
        "tgn:7008082",
        "tgn:7008591",
        "tgn:7029392"
    ],
    "tgn:id":7466425,
    "tgn:name:en":"Applecross Forest",
    "tgn:placetype":[
        "aat:300008863"
    ]
},
  "bbox": [],
  "geometry": {"coordinates":[-5.75,57.466667],"type":"Point"}
}