{
  "id": 7565612,
  "type": "Feature",
  "properties": {
    "tgn:hierarchy":[
        "tgn:7565612",
        "tgn:1000004",
        "tgn:7000198",
        "tgn:7016788",
        "tgn:7029392"
    ],
    "tgn:id":7565612,
    "tgn:name:en":"P\u0101ncoron ka Khu",
    "tgn:placetype":[
        "aat:300008347"
    ]
},
  "bbox": [],
  "geometry": {"coordinates":[71.720794,27.549398],"type":"Point"}
}