{
  "id": 2242507,
  "type": "Feature",
  "properties": {
    "tgn:hierarchy":[
        "tgn:2242507",
        "tgn:1000001",
        "tgn:7012149",
        "tgn:2002066",
        "tgn:7007826",
        "tgn:7029392"
    ],
    "tgn:id":2242507,
    "tgn:name":"Clear Branch",
    "tgn:placetype":[
        "aat:300008699"
    ]
},
  "bbox": [],
  "geometry": {"coordinates":[-93.8667,31.1833],"type":"Point"}
}