{
  "id": 2062207,
  "type": "Feature",
  "properties": {
    "tgn:hierarchy":[
        "tgn:2062207",
        "tgn:1000001",
        "tgn:2001370",
        "tgn:7012149",
        "tgn:7007525",
        "tgn:7029392"
    ],
    "tgn:id":2062207,
    "tgn:name":"Hallam",
    "tgn:placetype":[
        "aat:300008347"
    ]
},
  "bbox": [],
  "geometry": {"coordinates":[-96.7833,40.5333],"type":"Point"}
}