{
  "id": 2780124,
  "type": "Feature",
  "properties": {
    "tgn:hierarchy":[
        "tgn:2780124",
        "tgn:1000001",
        "tgn:7012149",
        "tgn:1002742",
        "tgn:7007920",
        "tgn:7029392"
    ],
    "tgn:id":2780124,
    "tgn:name":"Wolframite Mountain",
    "tgn:placetype":[
        "aat:300008798"
    ]
},
  "bbox": [],
  "geometry": {"coordinates":[-120.1167,48.9833],"type":"Point"}
}