{
  "id": 2213252,
  "type": "Feature",
  "properties": {
    "tgn:hierarchy":[
        "tgn:2213252",
        "tgn:1002338",
        "tgn:1000001",
        "tgn:7012149",
        "tgn:7007516",
        "tgn:7029392"
    ],
    "tgn:id":2213252,
    "tgn:name":"Cabin Creek",
    "tgn:placetype":[
        "aat:300008706"
    ]
},
  "bbox": [],
  "geometry": {"coordinates":[-75.8667,38.6167],"type":"Point"}
}