{
  "id": 1062360,
  "type": "Feature",
  "properties": {
    "tgn:hierarchy":[
        "tgn:1062360",
        "tgn:7002849",
        "tgn:1000003",
        "tgn:7009604",
        "tgn:1000095",
        "tgn:7029392"
    ],
    "tgn:id":1062360,
    "tgn:name":"Portugalete",
    "tgn:placetype":[
        "aat:300008347"
    ]
},
  "bbox": [],
  "geometry": {"coordinates":[-3.020307,43.319379],"type":"Point"}
}