{
  "id": 7412093,
  "type": "Feature",
  "properties": {
    "tgn:hierarchy":[
        "tgn:7412093",
        "tgn:1000001",
        "tgn:7005596",
        "tgn:7005560",
        "tgn:7029392"
    ],
    "tgn:id":7412093,
    "tgn:name:es":"Buenavista R\u00edo Nuevo Cuarta Secci\u00f3n",
    "tgn:placetype":[
        "aat:300008347"
    ]
},
  "bbox": [],
  "geometry": {"coordinates":[-93.091667,17.95],"type":"Point"}
}