{
  "id": 7391569,
  "type": "Feature",
  "properties": {
    "tgn:hierarchy":[
        "tgn:7391569",
        "tgn:1001853",
        "tgn:1000001",
        "tgn:7005560",
        "tgn:7029392"
    ],
    "tgn:id":7391569,
    "tgn:name":"Rancho Santo Domingo",
    "tgn:placetype":[
        "aat:300008347"
    ]
},
  "bbox": [],
  "geometry": {"coordinates":[-103.483333,27.766667],"type":"Point"}
}