{
  "id": 7409095,
  "type": "Feature",
  "properties": {
    "tgn:hierarchy":[
        "tgn:7409095",
        "tgn:1000001",
        "tgn:7005590",
        "tgn:7005560",
        "tgn:7029392"
    ],
    "tgn:id":7409095,
    "tgn:name":"Palos Secos",
    "tgn:placetype":[
        "aat:300008347"
    ]
},
  "bbox": [],
  "geometry": {"coordinates":[-100.666667,19.697222],"type":"Point"}
}