<<<<<<< HEAD
{
  "id": 2766157,
  "type": "Feature",
  "properties": {
    "tgn:hierarchy":[
        "tgn:2766157",
        "tgn:7006450",
        "tgn:1000001",
        "tgn:7012149",
        "tgn:2000089",
        "tgn:7029392"
    ],
    "tgn:id":2766157,
    "tgn:name":"White Lake",
    "tgn:placetype":[
        "aat:300008680"
    ]
},
  "bbox": [],
  "geometry": {"coordinates":[-145.1,67.1333],"type":"Point"}
}
=======
{"geometry":{"type":"Point","coordinates":[-145.100000,67.133300]},"type":"Feature","properties":{"hierarchy":["tgn:2766157","tgn:7006450","tgn:1000001","tgn:7012149","tgn:2000089","tgn:7029392"],"placetype":["aat:300008680"],"id":2766157,"name:xx":"White Lake"}}
>>>>>>> 03f74aca74312dbeaf24d7e61306dd6a786dc3d0
