<<<<<<< HEAD
{
  "id": 7355376,
  "type": "Feature",
  "properties": {
    "tgn:hierarchy":[
        "tgn:7355376",
        "tgn:7005581",
        "tgn:1000001",
        "tgn:7005560",
        "tgn:7029392"
    ],
    "tgn:id":7355376,
    "tgn:name":"Ceja Grande, Sierra de la",
    "tgn:placetype":[
        "aat:300008795"
    ]
},
  "bbox": [],
  "geometry": {"coordinates":[-105.7,29.316667],"type":"Point"}
}
=======
{"geometry":{"type":"Point","coordinates":[-105.700000,29.316667]},"type":"Feature","properties":{"hierarchy":["tgn:7355376","tgn:7005581","tgn:1000001","tgn:7005560","tgn:7029392"],"placetype":["aat:300008795"],"id":7355376,"name:xx":"Ceja Grande, Sierra de la"}}
>>>>>>> 03f74aca74312dbeaf24d7e61306dd6a786dc3d0
