{
  "id": 2756823,
  "type": "Feature",
  "properties": {
    "tgn:hierarchy":[
        "tgn:2756823",
        "tgn:1000001",
        "tgn:2002103",
        "tgn:7012149",
        "tgn:7007827",
        "tgn:7029392"
    ],
    "tgn:id":2756823,
    "tgn:name":"Wellsville Canal",
    "tgn:placetype":[
        "aat:300006075"
    ]
},
  "bbox": [],
  "geometry": {"coordinates":[-111.8667,41.6167],"type":"Point"}
}