{
  "id": 2167522,
  "type": "Feature",
  "properties": {
    "tgn:hierarchy":[
        "tgn:2167522",
        "tgn:1000001",
        "tgn:2001092",
        "tgn:7012149",
        "tgn:7007522",
        "tgn:7029392"
    ],
    "tgn:id":2167522,
    "tgn:name":"Big Creek",
    "tgn:placetype":[
        "aat:300008706"
    ]
},
  "bbox": [],
  "geometry": {"coordinates":[-89.35,33.9333],"type":"Point"}
}