{
  "id": 2134458,
  "type": "Feature",
  "properties": {
    "tgn:hierarchy":[
        "tgn:2134458",
        "tgn:1000001",
        "tgn:2000922",
        "tgn:7012149",
        "tgn:7007515",
        "tgn:7029392"
    ],
    "tgn:id":2134458,
    "tgn:name":"Anns Point",
    "tgn:placetype":[
        "aat:300008850"
    ]
},
  "bbox": [],
  "geometry": {"coordinates":[-68.35,44.2333],"type":"Point"}
}