{
  "id": 7398083,
  "type": "Feature",
  "properties": {
    "tgn:hierarchy":[
        "tgn:7398083",
        "tgn:1000001",
        "tgn:1001960",
        "tgn:7005560",
        "tgn:7029392"
    ],
    "tgn:id":7398083,
    "tgn:name":"Bordo de Arriba",
    "tgn:placetype":[
        "aat:300006191"
    ]
},
  "bbox": [],
  "geometry": {"coordinates":[-110.521111,30.969722],"type":"Point"}
}