<<<<<<< HEAD
{
  "id": 2765555,
  "type": "Feature",
  "properties": {
    "tgn:hierarchy":[
        "tgn:2765555",
        "tgn:1000001",
        "tgn:2000921",
        "tgn:7012149",
        "tgn:7007515",
        "tgn:7029392"
    ],
    "tgn:id":2765555,
    "tgn:name":"White Cap Mountain",
    "tgn:placetype":[
        "aat:300008798"
    ]
},
  "bbox": [],
  "geometry": {"coordinates":[-70.8167,45.2333],"type":"Point"}
}
=======
{"geometry":{"type":"Point","coordinates":[-70.816700,45.233300]},"type":"Feature","properties":{"hierarchy":["tgn:2765555","tgn:1000001","tgn:2000921","tgn:7012149","tgn:7007515","tgn:7029392"],"placetype":["aat:300008798"],"id":2765555,"name:xx":"White Cap Mountain"}}
>>>>>>> 03f74aca74312dbeaf24d7e61306dd6a786dc3d0
