{
  "id": 7406543,
  "type": "Feature",
  "properties": {
    "tgn:hierarchy":[
        "tgn:7406543",
        "tgn:1000001",
        "tgn:1001906",
        "tgn:7005560",
        "tgn:7029392"
    ],
    "tgn:id":7406543,
    "tgn:name":"El Chacate, Arroyo",
    "tgn:placetype":[
        "aat:300008699"
    ]
},
  "bbox": [],
  "geometry": {"coordinates":[-104.966667,22.483333],"type":"Point"}
}