{
  "id": 2144726,
  "type": "Feature",
  "properties": {
    "tgn:hierarchy":[
        "tgn:2144726",
        "tgn:1000001",
        "tgn:1002664",
        "tgn:7012149",
        "tgn:7007159",
        "tgn:7029392"
    ],
    "tgn:id":2144726,
    "tgn:name":"Bald Hill",
    "tgn:placetype":[
        "aat:300008798"
    ]
},
  "bbox": [],
  "geometry": {"coordinates":[-72.4167,41.45],"type":"Point"}
}