{
  "id": 2389884,
  "type": "Feature",
  "properties": {
    "tgn:hierarchy":[
        "tgn:2389884",
        "tgn:1000001",
        "tgn:7012149",
        "tgn:2001718",
        "tgn:7007708",
        "tgn:7029392"
    ],
    "tgn:id":2389884,
    "tgn:name":"High Peak",
    "tgn:placetype":[
        "aat:300008798"
    ]
},
  "bbox": [],
  "geometry": {"coordinates":[-117.6833,42.1333],"type":"Point"}
}