{
  "id": 1073987,
  "type": "Feature",
  "properties": {
    "tgn:hierarchy":[
        "tgn:1073987",
        "tgn:1000004",
        "tgn:7002087",
        "tgn:1000111",
        "tgn:7029392"
    ],
    "tgn:id":1073987,
    "tgn:name":"Zhenjinqiao",
    "tgn:placetype":[
        "aat:300008347"
    ]
},
  "bbox": [],
  "geometry": {"coordinates":[104.3833,30.1833],"type":"Point"}
}