{
  "id": 1043476,
  "type": "Feature",
  "properties": {
    "tgn:hierarchy":[
        "tgn:1043476",
        "tgn:7015163",
        "tgn:1000003",
        "tgn:7003121",
        "tgn:1000080",
        "tgn:7029392"
    ],
    "tgn:id":1043476,
    "tgn:name":"Berchidda",
    "tgn:placetype":[
        "aat:300008347"
    ]
},
  "bbox": [],
  "geometry": {"coordinates":[9.166667,40.783333],"type":"Point"}
}