<<<<<<< HEAD
{
  "id": 7248858,
  "type": "Feature",
  "properties": {
    "tgn:hierarchy":[
        "tgn:7248858",
        "tgn:7003460",
        "tgn:1000003",
        "tgn:1000063",
        "tgn:4012014",
        "tgn:7029392"
    ],
    "tgn:id":7248858,
    "tgn:name":"Bois-et-Borsu",
    "tgn:placetype":[
        "aat:300008347"
    ]
},
  "bbox": [],
  "geometry": {"coordinates":[5.337996,50.398303],"type":"Point"}
}
=======
{"geometry":{"type":"Point","coordinates":[5.337996,50.398303]},"type":"Feature","properties":{"hierarchy":["tgn:7248858","tgn:7003460","tgn:1000003","tgn:1000063","tgn:4012014","tgn:7029392"],"placetype":["aat:300008347"],"id":7248858,"name:xx":"Bois-et-Borsu"}}
>>>>>>> 03f74aca74312dbeaf24d7e61306dd6a786dc3d0
