{
  "id": 2267547,
  "type": "Feature",
  "properties": {
    "tgn:hierarchy":[
        "tgn:2267547",
        "tgn:1000001",
        "tgn:7012149",
        "tgn:2000931",
        "tgn:7007515",
        "tgn:7029392"
    ],
    "tgn:id":2267547,
    "tgn:name":"Crockett Branch",
    "tgn:placetype":[
        "aat:300008699"
    ]
},
  "bbox": [],
  "geometry": {"coordinates":[-68.9667,44.3167],"type":"Point"}
}