{
  "id": 7017090,
  "type": "Feature",
  "properties": {
    "tgn:hierarchy":[
        "tgn:7017090",
        "tgn:1001942",
        "tgn:1000047",
        "tgn:7002457",
        "tgn:1000002",
        "tgn:7029392"
    ],
    "tgn:id":7017090,
    "tgn:name":"Maric\u00e1",
    "tgn:placetype":[
        "aat:300008347",
        "aat:300265612",
        "aat:300008375"
    ]
},
  "bbox": [],
  "geometry": {"coordinates":[-42.8167,-22.9167],"type":"Point"}
}