{
  "id": 7223375,
  "type": "Feature",
  "properties": {
    "tgn:hierarchy":[
        "tgn:7223375",
        "tgn:7002706",
        "tgn:7002705",
        "tgn:1000003",
        "tgn:1000074",
        "tgn:7029392"
    ],
    "tgn:id":7223375,
    "tgn:name":"Platan\u00e1kia",
    "tgn:placetype":[
        "aat:300008347"
    ]
},
  "bbox": [],
  "geometry": {"coordinates":[21.022222,39.366111],"type":"Point"}
}