{
  "id": 2480965,
  "type": "Feature",
  "properties": {
    "tgn:hierarchy":[
        "tgn:2480965",
        "tgn:1000001",
        "tgn:2001703",
        "tgn:7012149",
        "tgn:7007708",
        "tgn:7029392"
    ],
    "tgn:id":2480965,
    "tgn:name":"Lakin Place",
    "tgn:placetype":[
        "aat:300008347"
    ]
},
  "bbox": [],
  "geometry": {"coordinates":[-120.5833,44.4333],"type":"Point"}
}