{
  "id": 7054891,
  "type": "Feature",
  "properties": {
    "tgn:hierarchy":[
        "tgn:7054891",
        "tgn:1003429",
        "tgn:1000003",
        "tgn:7003240",
        "tgn:1000080",
        "tgn:7029392"
    ],
    "tgn:id":7054891,
    "tgn:name":"Molino Cesaretti",
    "tgn:placetype":[
        "aat:300008347"
    ]
},
  "bbox": [],
  "geometry": {"coordinates":[13.333333,43.616667],"type":"Point"}
}