{
  "id": 7588133,
  "type": "Feature",
  "properties": {
    "tgn:hierarchy":[
        "tgn:7588133",
        "tgn:1000004",
        "tgn:7000198",
        "tgn:7000799",
        "tgn:7029392"
    ],
    "tgn:id":7588133,
    "tgn:name:en":"Moniaw\u0101r",
    "tgn:placetype":[
        "aat:300000745"
    ]
},
  "bbox": [],
  "geometry": {"coordinates":[74.818056,34.081944],"type":"Point"}
}