<<<<<<< HEAD
{
  "id": 7362087,
  "type": "Feature",
  "properties": {
    "tgn:hierarchy":[
        "tgn:7362087",
        "tgn:1000001",
        "tgn:7005599",
        "tgn:7005560",
        "tgn:7029392"
    ],
    "tgn:id":7362087,
    "tgn:name":"El Palmar",
    "tgn:placetype":[
        "aat:300007783"
    ]
},
  "bbox": [],
  "geometry": {"coordinates":[-96.733333,19.4],"type":"Point"}
}
=======
{"geometry":{"type":"Point","coordinates":[-96.733333,19.400000]},"type":"Feature","properties":{"hierarchy":["tgn:7362087","tgn:1000001","tgn:7005599","tgn:7005560","tgn:7029392"],"placetype":["aat:300007783"],"id":7362087,"name:xx":"El Palmar"}}
>>>>>>> 03f74aca74312dbeaf24d7e61306dd6a786dc3d0
