{
  "id": 7011732,
  "type": "Feature",
  "properties": {
    "tgn:hierarchy":[
        "tgn:7011732",
        "tgn:7002445",
        "tgn:1000003",
        "tgn:7008175",
        "tgn:7008591",
        "tgn:7029392"
    ],
    "tgn:id":7011732,
    "tgn:name:en":"Dorking",
    "tgn:placetype":[
        "aat:300008347"
    ]
},
  "bbox": [],
  "geometry": {"coordinates":[-0.333333,51.216667],"type":"Point"}
}