{
  "id": 2452023,
  "type": "Feature",
  "properties": {
    "tgn:hierarchy":[
        "tgn:2452023",
        "tgn:1000001",
        "tgn:7012149",
        "tgn:2002275",
        "tgn:7013961",
        "tgn:7029392"
    ],
    "tgn:id":2452023,
    "tgn:name":"Little Bingamon Creek",
    "tgn:placetype":[
        "aat:300008706"
    ]
},
  "bbox": [],
  "geometry": {"coordinates":[-80.35,39.4833],"type":"Point"}
}