{
  "id": 2728486,
  "type": "Feature",
  "properties": {
    "tgn:hierarchy":[
        "tgn:2728486",
        "tgn:1000001",
        "tgn:1002209",
        "tgn:7012149",
        "tgn:7007252",
        "tgn:7029392"
    ],
    "tgn:id":2728486,
    "tgn:name":"Treaty Line Pond",
    "tgn:placetype":[
        "aat:300008680"
    ]
},
  "bbox": [],
  "geometry": {"coordinates":[-86.1167,39.05],"type":"Point"}
}