{
  "id": 7010306,
  "type": "Feature",
  "properties": {
    "tgn:hierarchy":[
        "tgn:7010306",
        "tgn:1000004",
        "tgn:7012941",
        "tgn:7018214",
        "tgn:7002435",
        "tgn:7029392"
    ],
    "tgn:id":7010306,
    "tgn:name":"Torzhok",
    "tgn:placetype":[
        "aat:300008347"
    ]
},
  "bbox": [],
  "geometry": {"coordinates":[34.85,57.0333],"type":"Point"}
}