{
  "id": 2596318,
  "type": "Feature",
  "properties": {
    "tgn:hierarchy":[
        "tgn:2596318",
        "tgn:1000001",
        "tgn:7006451",
        "tgn:2000092",
        "tgn:7012149",
        "tgn:7029392"
    ],
    "tgn:id":2596318,
    "tgn:name":"Pouquette Tank",
    "tgn:placetype":[
        "aat:300006191"
    ]
},
  "bbox": [],
  "geometry": {"coordinates":[-112.1167,35.2833],"type":"Point"}
}