{
  "id": 7586712,
  "type": "Feature",
  "properties": {
    "tgn:hierarchy":[
        "tgn:7586712",
        "tgn:1000004",
        "tgn:7000198",
        "tgn:7000799",
        "tgn:7029392"
    ],
    "tgn:id":7586712,
    "tgn:name:en":"Gagarbal",
    "tgn:placetype":[
        "aat:300008795"
    ]
},
  "bbox": [],
  "geometry": {"coordinates":[74.883984,34.490713],"type":"Point"}
}