{
  "id": 2116682,
  "type": "Feature",
  "properties": {
    "tgn:hierarchy":[
        "tgn:2116682",
        "tgn:1000001",
        "tgn:7012149",
        "tgn:7014510",
        "tgn:7007920",
        "tgn:7029392"
    ],
    "tgn:id":2116682,
    "tgn:name":"Samish Island",
    "tgn:placetype":[
        "aat:300008347"
    ]
},
  "bbox": [],
  "geometry": {"coordinates":[-122.5333,48.5667],"type":"Point"}
}