{
  "id": 7166405,
  "type": "Feature",
  "properties": {
    "tgn:hierarchy":[
        "tgn:7166405",
        "tgn:1000003",
        "tgn:7000094",
        "tgn:7000084",
        "tgn:7029392"
    ],
    "tgn:id":7166405,
    "tgn:name":"Heide-Berg",
    "tgn:placetype":[
        "aat:300008777"
    ]
},
  "bbox": [],
  "geometry": {"coordinates":[12.933333,53.866667],"type":"Point"}
}