<<<<<<< HEAD
{
  "id": 2255631,
  "type": "Feature",
  "properties": {
    "tgn:hierarchy":[
        "tgn:2255631",
        "tgn:1000001",
        "tgn:7012149",
        "tgn:7007526",
        "tgn:7029392"
    ],
    "tgn:id":2255631,
    "tgn:name":"Copenhagen Creek",
    "tgn:placetype":[
        "aat:300008706"
    ]
},
  "bbox": [],
  "geometry": {"coordinates":[-116.4,39.0667],"type":"Point"}
}
=======
{"geometry":{"type":"Point","coordinates":[-116.400000,39.066700]},"type":"Feature","properties":{"hierarchy":["tgn:2255631","tgn:1000001","tgn:7012149","tgn:7007526","tgn:7029392"],"placetype":["aat:300008706"],"id":2255631,"name:xx":"Copenhagen Creek"}}
>>>>>>> 03f74aca74312dbeaf24d7e61306dd6a786dc3d0
