{
  "id": 1098673,
  "type": "Feature",
  "properties": {
    "tgn:hierarchy":[
        "tgn:1098673",
        "tgn:7000490",
        "tgn:1000006",
        "tgn:7001829",
        "tgn:7029392"
    ],
    "tgn:id":1098673,
    "tgn:name":"Yuendumu",
    "tgn:placetype":[
        "aat:300008347"
    ]
},
  "bbox": [],
  "geometry": {"coordinates":[131.75,-22.3333],"type":"Point"}
}