{
  "id": 2366193,
  "type": "Feature",
  "properties": {
    "tgn:hierarchy":[
        "tgn:2366193",
        "tgn:7002659",
        "tgn:1000001",
        "tgn:7012149",
        "tgn:2000060",
        "tgn:7029392"
    ],
    "tgn:id":2366193,
    "tgn:name":"Griffin Branch",
    "tgn:placetype":[
        "aat:300008699"
    ]
},
  "bbox": [],
  "geometry": {"coordinates":[-86.35,33.25],"type":"Point"}
}