{
  "id": 2417936,
  "type": "Feature",
  "properties": {
    "tgn:hierarchy":[
        "tgn:2417936",
        "tgn:2000947",
        "tgn:1000001",
        "tgn:7012149",
        "tgn:7007520",
        "tgn:7029392"
    ],
    "tgn:id":2417936,
    "tgn:name":"Jackson Lakes",
    "tgn:placetype":[
        "aat:300008680"
    ]
},
  "bbox": [],
  "geometry": {"coordinates":[-88.4833,46.6667],"type":"Point"}
}