{
  "id": 7282272,
  "type": "Feature",
  "properties": {
    "tgn:hierarchy":[
        "tgn:7282272",
        "tgn:7016598",
        "tgn:1000049",
        "tgn:1000002",
        "tgn:7029392"
    ],
    "tgn:id":7282272,
    "tgn:name":"Putas, Cerro",
    "tgn:placetype":[
        "aat:300008795"
    ]
},
  "bbox": [],
  "geometry": {"coordinates":[-67.716667,-23.116667],"type":"Point"}
}