{
  "id": 2491644,
  "type": "Feature",
  "properties": {
    "tgn:hierarchy":[
        "tgn:2491644",
        "tgn:1000001",
        "tgn:7012149",
        "tgn:2002112",
        "tgn:7007827",
        "tgn:7029392"
    ],
    "tgn:id":2491644,
    "tgn:name":"Maple Spring",
    "tgn:placetype":[
        "aat:300008697"
    ]
},
  "bbox": [],
  "geometry": {"coordinates":[-111.7333,39.75],"type":"Point"}
}