{
  "id": 2012361,
  "type": "Feature",
  "properties": {
    "tgn:hierarchy":[
        "tgn:2012361",
        "tgn:1000001",
        "tgn:7012149",
        "tgn:7007157",
        "tgn:7023900",
        "tgn:1002608",
        "tgn:7029392"
    ],
    "tgn:id":2012361,
    "tgn:name":"Echo Park",
    "tgn:placetype":[
        "aat:300000745"
    ]
},
  "bbox": [],
  "geometry": {"coordinates":[-118.25,34.0667],"type":"Point"}
}