{
  "id": 7358270,
  "type": "Feature",
  "properties": {
    "tgn:hierarchy":[
        "tgn:7358270",
        "tgn:7005578",
        "tgn:1000001",
        "tgn:7005560",
        "tgn:7029392"
    ],
    "tgn:id":7358270,
    "tgn:name":"Dario Ahumada",
    "tgn:placetype":[
        "aat:300008347"
    ]
},
  "bbox": [],
  "geometry": {"coordinates":[-90.616667,18.416667],"type":"Point"}
}