{
  "id": 7500226,
  "type": "Feature",
  "properties": {
    "tgn:hierarchy":[
        "tgn:7500226",
        "tgn:1000004",
        "tgn:7491221",
        "tgn:1000141",
        "tgn:7029392"
    ],
    "tgn:id":7500226,
    "tgn:name":"Yuantian Gong",
    "tgn:placetype":[
        "aat:300007595"
    ]
},
  "bbox": [],
  "geometry": {"coordinates":[120.979444,22.591111],"type":"Point"}
}