{
  "id": 7458797,
  "type": "Feature",
  "properties": {
    "tgn:hierarchy":[
        "tgn:7458797",
        "tgn:7002445",
        "tgn:1000003",
        "tgn:7008160",
        "tgn:7008591",
        "tgn:7029392"
    ],
    "tgn:id":7458797,
    "tgn:name:en":"Newcome Sand",
    "tgn:placetype":[
        "aat:300387036"
    ]
},
  "bbox": [],
  "geometry": {"coordinates":[1.766667,52.433333],"type":"Point"}
}