<<<<<<< HEAD
{
  "id": 7379761,
  "type": "Feature",
  "properties": {
    "tgn:hierarchy":[
        "tgn:7379761",
        "tgn:1000001",
        "tgn:1001906",
        "tgn:7005560",
        "tgn:7029392"
    ],
    "tgn:id":7379761,
    "tgn:name":"Milpillas",
    "tgn:placetype":[
        "aat:300008347"
    ]
},
  "bbox": [],
  "geometry": {"coordinates":[-105.016667,22.966667],"type":"Point"}
}
=======
{"geometry":{"type":"Point","coordinates":[-105.016667,22.966667]},"type":"Feature","properties":{"hierarchy":["tgn:7379761","tgn:1000001","tgn:1001906","tgn:7005560","tgn:7029392"],"placetype":["aat:300008347"],"id":7379761,"name:xx":"Milpillas"}}
>>>>>>> 03f74aca74312dbeaf24d7e61306dd6a786dc3d0
