{
  "id": 7532592,
  "type": "Feature",
  "properties": {
    "tgn:hierarchy":[
        "tgn:7532592",
        "tgn:7001242",
        "tgn:7016833",
        "tgn:1001091",
        "tgn:7029392"
    ],
    "tgn:id":7532592,
    "tgn:name":"D\u0101r Mun\u0101sab\u0101t Ri'\u0101sat \u1e28ayy 'Ayn Shams",
    "tgn:placetype":[
        "aat:300004792"
    ]
},
  "bbox": [],
  "geometry": {"coordinates":[31.349576,30.136243],"type":"Point"}
}