{
  "id": 7215316,
  "type": "Feature",
  "properties": {
    "tgn:hierarchy":[
        "tgn:7215316",
        "tgn:1000003",
        "tgn:7003678",
        "tgn:7000084",
        "tgn:7029392"
    ],
    "tgn:id":7215316,
    "tgn:name":"Bingerwiesen-Kopf",
    "tgn:placetype":[
        "aat:300008777"
    ]
},
  "bbox": [],
  "geometry": {"coordinates":[8.666667,51.083333],"type":"Point"}
}