{
  "id": 7545688,
  "type": "Feature",
  "properties": {
    "tgn:hierarchy":[
        "tgn:7545688",
        "tgn:1000004",
        "tgn:7000198",
        "tgn:7016788",
        "tgn:7029392"
    ],
    "tgn:id":7545688,
    "tgn:name:en":"Bhiy\u0101r",
    "tgn:placetype":[
        "aat:300008347"
    ]
},
  "bbox": [],
  "geometry": {"coordinates":[71.463568,26.3155],"type":"Point"}
}