{
  "id": 2755956,
  "type": "Feature",
  "properties": {
    "tgn:hierarchy":[
        "tgn:2755956",
        "tgn:1000001",
        "tgn:7012149",
        "tgn:2002037",
        "tgn:7007826",
        "tgn:7029392"
    ],
    "tgn:id":2755956,
    "tgn:name":"Weideman Creek",
    "tgn:placetype":[
        "aat:300008706"
    ]
},
  "bbox": [],
  "geometry": {"coordinates":[-99.0333,30.5667],"type":"Point"}
}