{
  "id": 2235021,
  "type": "Feature",
  "properties": {
    "tgn:hierarchy":[
        "tgn:2235021",
        "tgn:1000001",
        "tgn:2001584",
        "tgn:7012149",
        "tgn:7007705",
        "tgn:7029392"
    ],
    "tgn:id":2235021,
    "tgn:name":"Cherry Lake",
    "tgn:placetype":[
        "aat:300008680"
    ]
},
  "bbox": [],
  "geometry": {"coordinates":[-100.9333,47.5167],"type":"Point"}
}