{
  "id": 7279194,
  "type": "Feature",
  "properties": {
    "tgn:hierarchy":[
        "tgn:7279194",
        "tgn:1001702",
        "tgn:1000049",
        "tgn:1000002",
        "tgn:7029392"
    ],
    "tgn:id":7279194,
    "tgn:name":"Rompiente, Roca",
    "tgn:placetype":[
        "aat:300011692"
    ]
},
  "bbox": [],
  "geometry": {"coordinates":[-72.033333,-54.516667],"type":"Point"}
}