{
  "id": 7583069,
  "type": "Feature",
  "properties": {
    "tgn:hierarchy":[
        "tgn:7583069",
        "tgn:1000004",
        "tgn:7000198",
        "tgn:7016788",
        "tgn:7029392"
    ],
    "tgn:id":7583069,
    "tgn:name:en":"Bh\u0101ne ka Gaon",
    "tgn:placetype":[
        "aat:300008347"
    ]
},
  "bbox": [],
  "geometry": {"coordinates":[72.801842,27.736064],"type":"Point"}
}