{
  "id": 2590181,
  "type": "Feature",
  "properties": {
    "tgn:hierarchy":[
        "tgn:2590181",
        "tgn:1000001",
        "tgn:7012149",
        "tgn:2001821",
        "tgn:7007713",
        "tgn:7029392"
    ],
    "tgn:id":2590181,
    "tgn:name":"Poison Weed Draw",
    "tgn:placetype":[
        "aat:300008761"
    ]
},
  "bbox": [],
  "geometry": {"coordinates":[-102.1833,44.3833],"type":"Point"}
}