{
  "id": 7475613,
  "type": "Feature",
  "properties": {
    "tgn:hierarchy":[
        "tgn:7475613",
        "tgn:1000004",
        "tgn:7489179",
        "tgn:1000141",
        "tgn:7029392"
    ],
    "tgn:id":7475613,
    "tgn:name":"Hudong",
    "tgn:placetype":[
        "aat:300008347"
    ]
},
  "bbox": [],
  "geometry": {"coordinates":[121.850854,24.577414],"type":"Point"}
}