{
  "id": 7016555,
  "type": "Feature",
  "properties": {
    "tgn:hierarchy":[
        "tgn:7016555",
        "tgn:1001143",
        "tgn:7001242",
        "tgn:1000159",
        "tgn:7029392"
    ],
    "tgn:id":7016555,
    "tgn:name":"Mwadi-Kalumba",
    "tgn:placetype":[
        "aat:300008347",
        "aat:300000810"
    ]
},
  "bbox": [],
  "geometry": {"coordinates":[18.7667,-7.8833],"type":"Point"}
}