{
  "id": 7342362,
  "type": "Feature",
  "properties": {
    "tgn:hierarchy":[
        "tgn:7342362",
        "tgn:1001439",
        "tgn:1000003",
        "tgn:7002797",
        "tgn:1000095",
        "tgn:7029392"
    ],
    "tgn:id":7342362,
    "tgn:name":"Carrascalejo",
    "tgn:placetype":[
        "aat:300008347"
    ]
},
  "bbox": [],
  "geometry": {"coordinates":[-1.033333,38.55],"type":"Point"}
}