{
  "id": 2660390,
  "type": "Feature",
  "properties": {
    "tgn:hierarchy":[
        "tgn:2660390",
        "tgn:1000001",
        "tgn:7012149",
        "tgn:2001456",
        "tgn:7007566",
        "tgn:7029392"
    ],
    "tgn:id":2660390,
    "tgn:name":"Shoe Tank",
    "tgn:placetype":[
        "aat:300006191"
    ]
},
  "bbox": [],
  "geometry": {"coordinates":[-107.3667,33.8167],"type":"Point"}
}