{
  "id": 7044613,
  "type": "Feature",
  "properties": {
    "tgn:hierarchy":[
        "tgn:7044613",
        "tgn:7002994",
        "tgn:1000003",
        "tgn:7002997",
        "tgn:1000080",
        "tgn:7029392"
    ],
    "tgn:id":7044613,
    "tgn:name":"Fossalta",
    "tgn:placetype":[
        "aat:300008347"
    ]
},
  "bbox": [],
  "geometry": {"coordinates":[12.005833,45.577778],"type":"Point"}
}