{
  "id": 7331776,
  "type": "Feature",
  "properties": {
    "tgn:hierarchy":[
        "tgn:7331776",
        "tgn:7002759",
        "tgn:7002843",
        "tgn:1000003",
        "tgn:1000095",
        "tgn:7029392"
    ],
    "tgn:id":7331776,
    "tgn:name":"La Iglesuela del Cid",
    "tgn:placetype":[
        "aat:300008347"
    ]
},
  "bbox": [],
  "geometry": {"coordinates":[-0.316667,40.483333],"type":"Point"}
}