{
  "id": 7478373,
  "type": "Feature",
  "properties": {
    "tgn:hierarchy":[
        "tgn:7478373",
        "tgn:1000004",
        "tgn:7467799",
        "tgn:1000141",
        "tgn:7029392"
    ],
    "tgn:id":7478373,
    "tgn:name":"Dazhuang Guoxiao",
    "tgn:placetype":[
        "aat:300006495"
    ]
},
  "bbox": [],
  "geometry": {"coordinates":[120.56657,23.81623],"type":"Point"}
}