<<<<<<< HEAD
{
  "id": 7478373,
  "type": "Feature",
  "properties": {
    "tgn:hierarchy":[
        "tgn:7478373",
        "tgn:1000004",
        "tgn:7467799",
        "tgn:1000141",
        "tgn:7029392"
    ],
    "tgn:id":7478373,
    "tgn:name":"Dazhuang Guoxiao",
    "tgn:placetype":[
        "aat:300006495"
    ]
},
  "bbox": [],
  "geometry": {"coordinates":[120.56657,23.81623],"type":"Point"}
}
=======
{"geometry":{"type":"Point","coordinates":[120.566570,23.816230]},"type":"Feature","properties":{"hierarchy":["tgn:7478373","tgn:1000004","tgn:7467799","tgn:1000141","tgn:7029392"],"placetype":["aat:300006495"],"id":7478373,"name:xx":"Dazhuang Guoxiao"}}
>>>>>>> 03f74aca74312dbeaf24d7e61306dd6a786dc3d0
