{
  "id": 2324195,
  "type": "Feature",
  "properties": {
    "tgn:hierarchy":[
        "tgn:2324195",
        "tgn:1000001",
        "tgn:7012149",
        "tgn:1002468",
        "tgn:7007252",
        "tgn:7029392"
    ],
    "tgn:id":2324195,
    "tgn:name":"Feather Fork",
    "tgn:placetype":[
        "aat:300008699"
    ]
},
  "bbox": [],
  "geometry": {"coordinates":[-85.4833,39.8833],"type":"Point"}
}