{
  "id": 2052809,
  "type": "Feature",
  "properties": {
    "tgn:hierarchy":[
        "tgn:2052809",
        "tgn:1000001",
        "tgn:7012149",
        "tgn:2000975",
        "tgn:7007520",
        "tgn:7029392"
    ],
    "tgn:id":2052809,
    "tgn:name":"Northland",
    "tgn:placetype":[
        "aat:300008347"
    ]
},
  "bbox": [],
  "geometry": {"coordinates":[-87.5833,46.0667],"type":"Point"}
}