{
  "id": 1077497,
  "type": "Feature",
  "properties": {
    "tgn:hierarchy":[
        "tgn:1077497",
        "tgn:1001319",
        "tgn:1000004",
        "tgn:1000116",
        "tgn:7029392"
    ],
    "tgn:id":1077497,
    "tgn:name":"Betung",
    "tgn:placetype":[
        "aat:300008347"
    ]
},
  "bbox": [],
  "geometry": {"coordinates":[103.2667,-1.8667],"type":"Point"}
}