<<<<<<< HEAD
{
  "id": 2338447,
  "type": "Feature",
  "properties": {
    "tgn:hierarchy":[
        "tgn:2338447",
        "tgn:1000001",
        "tgn:7012149",
        "tgn:2001455",
        "tgn:7007566",
        "tgn:7029392"
    ],
    "tgn:id":2338447,
    "tgn:name":"Fra Cristobal Range",
    "tgn:placetype":[
        "aat:300386831"
    ]
},
  "bbox": [],
  "geometry": {"coordinates":[-107.0833,33.3167],"type":"Point"}
}
=======
{"geometry":{"type":"Point","coordinates":[-107.083300,33.316700]},"type":"Feature","properties":{"hierarchy":["tgn:2338447","tgn:1000001","tgn:7012149","tgn:2001455","tgn:7007566","tgn:7029392"],"placetype":["aat:300386831"],"id":2338447,"name:xx":"Fra Cristobal Range"}}
>>>>>>> 03f74aca74312dbeaf24d7e61306dd6a786dc3d0
