{
  "id": 1089746,
  "type": "Feature",
  "properties": {
    "tgn:hierarchy":[
        "tgn:1089746",
        "tgn:7001242",
        "tgn:7017565",
        "tgn:7001658",
        "tgn:7029392"
    ],
    "tgn:id":1089746,
    "tgn:name":"B\u012bsha",
    "tgn:placetype":[
        "aat:300008347"
    ]
},
  "bbox": [],
  "geometry": {"coordinates":[37.55,15.4833],"type":"Point"}
}