{
  "id": 2777129,
  "type": "Feature",
  "properties": {
    "tgn:hierarchy":[
        "tgn:2777129",
        "tgn:1000001",
        "tgn:2000466",
        "tgn:7012149",
        "tgn:7007250",
        "tgn:7029392"
    ],
    "tgn:id":2777129,
    "tgn:name":"Windy Ridge",
    "tgn:placetype":[
        "aat:300266640"
    ]
},
  "bbox": [],
  "geometry": {"coordinates":[-111.8667,42.9167],"type":"Point"}
}