{
  "id": 1065096,
  "type": "Feature",
  "properties": {
    "tgn:hierarchy":[
        "tgn:1065096",
        "tgn:1000003",
        "tgn:7006669",
        "tgn:7029392"
    ],
    "tgn:id":1065096,
    "tgn:name":"Le\u0161nica",
    "tgn:placetype":[
        "aat:300008347"
    ]
},
  "bbox": [],
  "geometry": {"coordinates":[19.3333,44.6667],"type":"Point"}
}