<<<<<<< HEAD
{
  "id": 7029688,
  "type": "Feature",
  "properties": {
    "tgn:hierarchy":[
        "tgn:7029688",
        "tgn:1000004",
        "tgn:7024355",
        "tgn:1000111",
        "tgn:7029392"
    ],
    "tgn:id":7029688,
    "tgn:name":"Zhong Xian",
    "tgn:placetype":[
        "aat:300387198"
    ]
},
  "bbox": [],
  "geometry": {"coordinates":[108.033,30.3],"type":"Point"}
}
=======
{"geometry":{"type":"Point","coordinates":[108.033000,30.300000]},"type":"Feature","properties":{"hierarchy":["tgn:7029688","tgn:1000004","tgn:7024355","tgn:1000111","tgn:7029392"],"placetype":["aat:300387198"],"id":7029688,"name:xx":"Zhong Xian"}}
>>>>>>> 03f74aca74312dbeaf24d7e61306dd6a786dc3d0
