{
  "id": 2084501,
  "type": "Feature",
  "properties": {
    "tgn:hierarchy":[
        "tgn:2084501",
        "tgn:1000001",
        "tgn:1002270",
        "tgn:7012149",
        "tgn:7007708",
        "tgn:7029392"
    ],
    "tgn:id":2084501,
    "tgn:name":"Carver",
    "tgn:placetype":[
        "aat:300008347"
    ]
},
  "bbox": [],
  "geometry": {"coordinates":[-122.4833,45.3833],"type":"Point"}
}