{
  "id": 2172267,
  "type": "Feature",
  "properties": {
    "tgn:hierarchy":[
        "tgn:2172267",
        "tgn:7002659",
        "tgn:1000001",
        "tgn:7012149",
        "tgn:2000064",
        "tgn:7029392"
    ],
    "tgn:id":2172267,
    "tgn:name":"Bilbo Creek",
    "tgn:placetype":[
        "aat:300008706"
    ]
},
  "bbox": [],
  "geometry": {"coordinates":[-88.25,31.2833],"type":"Point"}
}