{
  "id": 7079264,
  "type": "Feature",
  "properties": {
    "tgn:hierarchy":[
        "tgn:7079264",
        "tgn:7000096",
        "tgn:1000003",
        "tgn:7000084",
        "tgn:7029392"
    ],
    "tgn:id":7079264,
    "tgn:name":"F\u00f6rsterei Wirchensee",
    "tgn:placetype":[
        "aat:300004792"
    ]
},
  "bbox": [],
  "geometry": {"coordinates":[14.483333,52.083333],"type":"Point"}
}