<<<<<<< HEAD
{
  "id": 2405462,
  "type": "Feature",
  "properties": {
    "tgn:hierarchy":[
        "tgn:2405462",
        "tgn:1000001",
        "tgn:7012149",
        "tgn:2000806",
        "tgn:7007255",
        "tgn:7029392"
    ],
    "tgn:id":2405462,
    "tgn:name":"Hughes Branch",
    "tgn:placetype":[
        "aat:300008699"
    ]
},
  "bbox": [],
  "geometry": {"coordinates":[-83.85,36.9333],"type":"Point"}
}
=======
{"geometry":{"type":"Point","coordinates":[-83.850000,36.933300]},"type":"Feature","properties":{"hierarchy":["tgn:2405462","tgn:1000001","tgn:7012149","tgn:2000806","tgn:7007255","tgn:7029392"],"placetype":["aat:300008699"],"id":2405462,"name:xx":"Hughes Branch"}}
>>>>>>> 03f74aca74312dbeaf24d7e61306dd6a786dc3d0
