{
  "id": 2405462,
  "type": "Feature",
  "properties": {
    "tgn:hierarchy":[
        "tgn:2405462",
        "tgn:1000001",
        "tgn:7012149",
        "tgn:2000806",
        "tgn:7007255",
        "tgn:7029392"
    ],
    "tgn:id":2405462,
    "tgn:name":"Hughes Branch",
    "tgn:placetype":[
        "aat:300008699"
    ]
},
  "bbox": [],
  "geometry": {"coordinates":[-83.85,36.9333],"type":"Point"}
}