<<<<<<< HEAD
{
  "id": 7371586,
  "type": "Feature",
  "properties": {
    "tgn:hierarchy":[
        "tgn:7371586",
        "tgn:1000001",
        "tgn:7005589",
        "tgn:7005560",
        "tgn:7029392"
    ],
    "tgn:id":7371586,
    "tgn:name":"Tanque La Mona",
    "tgn:placetype":[
        "aat:300006191"
    ]
},
  "bbox": [],
  "geometry": {"coordinates":[-100.8,27.15],"type":"Point"}
}
=======
{"geometry":{"type":"Point","coordinates":[-100.800000,27.150000]},"type":"Feature","properties":{"hierarchy":["tgn:7371586","tgn:1000001","tgn:7005589","tgn:7005560","tgn:7029392"],"placetype":["aat:300006191"],"id":7371586,"name:xx":"Tanque La Mona"}}
>>>>>>> 03f74aca74312dbeaf24d7e61306dd6a786dc3d0
