{
  "id": 2067521,
  "type": "Feature",
  "properties": {
    "tgn:hierarchy":[
        "tgn:2067521",
        "tgn:1000001",
        "tgn:2001435",
        "tgn:7012149",
        "tgn:7007566",
        "tgn:7029392"
    ],
    "tgn:id":2067521,
    "tgn:name":"Santo Tomas",
    "tgn:placetype":[
        "aat:300008347"
    ]
},
  "bbox": [],
  "geometry": {"coordinates":[-106.7333,32.1667],"type":"Point"}
}