<<<<<<< HEAD
{
  "id": 7488476,
  "type": "Feature",
  "properties": {
    "tgn:hierarchy":[
        "tgn:7488476",
        "tgn:7001004",
        "tgn:1000004",
        "tgn:1000141",
        "tgn:7029392"
    ],
    "tgn:id":7488476,
    "tgn:name":"Hongcuocheng",
    "tgn:placetype":[
        "aat:300008347"
    ]
},
  "bbox": [],
  "geometry": {"coordinates":[120.4061,22.6095],"type":"Point"}
}
=======
{"geometry":{"type":"Point","coordinates":[120.406100,22.609500]},"type":"Feature","properties":{"hierarchy":["tgn:7488476","tgn:7001004","tgn:1000004","tgn:1000141","tgn:7029392"],"placetype":["aat:300008347"],"id":7488476,"name:xx":"Hongcuocheng"}}
>>>>>>> 03f74aca74312dbeaf24d7e61306dd6a786dc3d0
