{
  "id": 2642293,
  "type": "Feature",
  "properties": {
    "tgn:hierarchy":[
        "tgn:2642293",
        "tgn:1000001",
        "tgn:7012149",
        "tgn:2001192",
        "tgn:7007523",
        "tgn:7029392"
    ],
    "tgn:id":2642293,
    "tgn:name":"Sand Spring",
    "tgn:placetype":[
        "aat:300008697"
    ]
},
  "bbox": [],
  "geometry": {"coordinates":[-92.85,37.7333],"type":"Point"}
}