{
  "id": 7508548,
  "type": "Feature",
  "properties": {
    "tgn:hierarchy":[
        "tgn:7508548",
        "tgn:1008380",
        "tgn:1000226",
        "tgn:7018426",
        "tgn:1000006",
        "tgn:7029392"
    ],
    "tgn:id":7508548,
    "tgn:name:en":"Otapu Creek",
    "tgn:placetype":[
        "aat:300008699"
    ]
},
  "bbox": [],
  "geometry": {"coordinates":[176.133333,-37.633333],"type":"Point"}
}