{
  "id": 7539710,
  "type": "Feature",
  "properties": {
    "tgn:hierarchy":[
        "tgn:7539710",
        "tgn:7001242",
        "tgn:7016833",
        "tgn:1001418",
        "tgn:7029392"
    ],
    "tgn:id":7539710,
    "tgn:name:en":"Markh\u012b, Tallat al",
    "tgn:placetype":[
        "aat:300008777"
    ]
},
  "bbox": [],
  "geometry": {"coordinates":[29.436466,30.556725],"type":"Point"}
}