{
  "id": 1086491,
  "type": "Feature",
  "properties": {
    "tgn:hierarchy":[
        "tgn:1086491",
        "tgn:1001511",
        "tgn:1000004",
        "tgn:7018453",
        "tgn:1000144",
        "tgn:7029392"
    ],
    "tgn:id":1086491,
    "tgn:name":"Akp\u0131nar",
    "tgn:placetype":[
        "aat:300008347"
    ]
},
  "bbox": [],
  "geometry": {"coordinates":[37.0167,39.0833],"type":"Point"}
}