{
  "id": 1084060,
  "type": "Feature",
  "properties": {
    "tgn:hierarchy":[
        "tgn:1084060",
        "tgn:1000004",
        "tgn:1001541",
        "tgn:1000135",
        "tgn:7029392"
    ],
    "tgn:id":1084060,
    "tgn:name":"Buayan",
    "tgn:placetype":[
        "aat:300008347"
    ]
},
  "bbox": [],
  "geometry": {"coordinates":[125.25,6.1167],"type":"Point"}
}