{
  "id": 7467936,
  "type": "Feature",
  "properties": {
    "tgn:hierarchy":[
        "tgn:7467936",
        "tgn:1000004",
        "tgn:7491221",
        "tgn:1000141",
        "tgn:7029392"
    ],
    "tgn:id":7467936,
    "tgn:name":"Chaoyong Xi",
    "tgn:placetype":[
        "aat:300008699"
    ]
},
  "bbox": [],
  "geometry": {"coordinates":[120.896667,22.339722],"type":"Point"}
}