{
  "id": 7509067,
  "type": "Feature",
  "properties": {
    "tgn:hierarchy":[
        "tgn:7509067",
        "tgn:1008380",
        "tgn:1000226",
        "tgn:7018426",
        "tgn:1000006",
        "tgn:7029392"
    ],
    "tgn:id":7509067,
    "tgn:name:en":"Tairua Harbour",
    "tgn:placetype":[
        "aat:300008678"
    ]
},
  "bbox": [],
  "geometry": {"coordinates":[175.85,-37.033333],"type":"Point"}
}