{
  "id": 1093701,
  "type": "Feature",
  "properties": {
    "tgn:hierarchy":[
        "tgn:1093701",
        "tgn:7001242",
        "tgn:7017576",
        "tgn:1000193",
        "tgn:7029392"
    ],
    "tgn:id":1093701,
    "tgn:name":"Tosca",
    "tgn:placetype":[
        "aat:300008347"
    ]
},
  "bbox": [],
  "geometry": {"coordinates":[23.9667,-25.8833],"type":"Point"}
}