{
  "id": 7558840,
  "type": "Feature",
  "properties": {
    "tgn:hierarchy":[
        "tgn:7558840",
        "tgn:1000004",
        "tgn:7000198",
        "tgn:7016788",
        "tgn:7029392"
    ],
    "tgn:id":7558840,
    "tgn:name:en":"Ret\u0101na",
    "tgn:placetype":[
        "aat:300008347"
    ]
},
  "bbox": [],
  "geometry": {"coordinates":[74.789855,28.539326],"type":"Point"}
}