<<<<<<< HEAD
{
  "id": 2157513,
  "type": "Feature",
  "properties": {
    "tgn:hierarchy":[
        "tgn:2157513",
        "tgn:1000001",
        "tgn:7012149",
        "tgn:2002291",
        "tgn:7013961",
        "tgn:7029392"
    ],
    "tgn:id":2157513,
    "tgn:name":"Beaver Creek",
    "tgn:placetype":[
        "aat:300008706"
    ]
},
  "bbox": [],
  "geometry": {"coordinates":[-79.95,38.5],"type":"Point"}
}
=======
{"geometry":{"type":"Point","coordinates":[-79.950000,38.500000]},"type":"Feature","properties":{"hierarchy":["tgn:2157513","tgn:1000001","tgn:7012149","tgn:2002291","tgn:7013961","tgn:7029392"],"placetype":["aat:300008706"],"id":2157513,"name:xx":"Beaver Creek"}}
>>>>>>> 03f74aca74312dbeaf24d7e61306dd6a786dc3d0
