{
  "id": 2130361,
  "type": "Feature",
  "properties": {
    "tgn:hierarchy":[
        "tgn:2130361",
        "tgn:1000001",
        "tgn:7012149",
        "tgn:2001530",
        "tgn:7007709",
        "tgn:7029392"
    ],
    "tgn:id":2130361,
    "tgn:name":"Allens Pond",
    "tgn:placetype":[
        "aat:300006191"
    ]
},
  "bbox": [],
  "geometry": {"coordinates":[-77.4833,35.65],"type":"Point"}
}