{
  "id": 7122523,
  "type": "Feature",
  "properties": {
    "tgn:hierarchy":[
        "tgn:7122523",
        "tgn:7000096",
        "tgn:1000003",
        "tgn:7000084",
        "tgn:7029392"
    ],
    "tgn:id":7122523,
    "tgn:name":"Neuwandlitz",
    "tgn:placetype":[
        "aat:300008347"
    ]
},
  "bbox": [],
  "geometry": {"coordinates":[13.45,52.733333],"type":"Point"}
}