{
  "id": 7395983,
  "type": "Feature",
  "properties": {
    "tgn:hierarchy":[
        "tgn:7395983",
        "tgn:1000001",
        "tgn:7005597",
        "tgn:7005560",
        "tgn:7029392"
    ],
    "tgn:id":7395983,
    "tgn:name":"San Juan",
    "tgn:placetype":[
        "aat:300008347"
    ]
},
  "bbox": [],
  "geometry": {"coordinates":[-98.55,24.916667],"type":"Point"}
}