{
  "id": 2546197,
  "type": "Feature",
  "properties": {
    "tgn:hierarchy":[
        "tgn:2546197",
        "tgn:1000001",
        "tgn:7012149",
        "tgn:2001544",
        "tgn:7007709",
        "tgn:7029392"
    ],
    "tgn:id":2546197,
    "tgn:name":"North Fork Flat Creek",
    "tgn:placetype":[
        "aat:300008706"
    ]
},
  "bbox": [],
  "geometry": {"coordinates":[-82.9167,35.15],"type":"Point"}
}