{
  "id": 7030708,
  "type": "Feature",
  "properties": {
    "tgn:hierarchy":[
        "tgn:7030708",
        "tgn:7002445",
        "tgn:1000003",
        "tgn:7008160",
        "tgn:7008591",
        "tgn:7029392"
    ],
    "tgn:id":7030708,
    "tgn:name":"West Bilney",
    "tgn:placetype":[
        "aat:300008347",
        "aat:300008372"
    ]
},
  "bbox": [],
  "geometry": {"coordinates":[0.542,52.701],"type":"Point"}
}