{
  "id": 2697817,
  "type": "Feature",
  "properties": {
    "tgn:hierarchy":[
        "tgn:2697817",
        "tgn:1000001",
        "tgn:7012149",
        "tgn:2000476",
        "tgn:7007250",
        "tgn:7029392"
    ],
    "tgn:id":2697817,
    "tgn:name":"Storm Ridge",
    "tgn:placetype":[
        "aat:300266640"
    ]
},
  "bbox": [],
  "geometry": {"coordinates":[-114.6167,45.5833],"type":"Point"}
}