{
  "id": 7542512,
  "type": "Feature",
  "properties": {
    "tgn:hierarchy":[
        "tgn:7542512",
        "tgn:7001242",
        "tgn:7016833",
        "tgn:7001312",
        "tgn:7029392"
    ],
    "tgn:id":7542512,
    "tgn:name:en":"Tir'at S\u0101m\u016bl",
    "tgn:placetype":[
        "aat:300006075"
    ]
},
  "bbox": [],
  "geometry": {"coordinates":[31.145809,31.00216],"type":"Point"}
}