{
  "id": 1072255,
  "type": "Feature",
  "properties": {
    "tgn:hierarchy":[
        "tgn:1072255",
        "tgn:1000004",
        "tgn:1001678",
        "tgn:1000111",
        "tgn:7029392"
    ],
    "tgn:id":1072255,
    "tgn:name":"Tianyang",
    "tgn:placetype":[
        "aat:300008347"
    ]
},
  "bbox": [],
  "geometry": {"coordinates":[106.5667,23.85],"type":"Point"}
}