{
  "id": 7395183,
  "type": "Feature",
  "properties": {
    "tgn:hierarchy":[
        "tgn:7395183",
        "tgn:7005585",
        "tgn:1000001",
        "tgn:7005560",
        "tgn:7029392"
    ],
    "tgn:id":7395183,
    "tgn:name":"San Crist\u00f3bal, R\u00edo",
    "tgn:placetype":[
        "aat:300008699"
    ]
},
  "bbox": [],
  "geometry": {"coordinates":[-99.683333,17.25],"type":"Point"}
}