{
  "id": 7570720,
  "type": "Feature",
  "properties": {
    "tgn:hierarchy":[
        "tgn:7570720",
        "tgn:1000004",
        "tgn:7000198",
        "tgn:1001895",
        "tgn:7029392"
    ],
    "tgn:id":7570720,
    "tgn:name:en":"Jalod",
    "tgn:placetype":[
        "aat:300008347"
    ]
},
  "bbox": [],
  "geometry": {"coordinates":[75.141854,21.163675],"type":"Point"}
}