{
  "id": 2405459,
  "type": "Feature",
  "properties": {
    "tgn:hierarchy":[
        "tgn:2405459",
        "tgn:1000001",
        "tgn:7012149",
        "tgn:7029392"
    ],
    "tgn:id":2405459,
    "tgn:name":"Hughes Branch",
    "tgn:placetype":[
        "aat:300008699"
    ]
},
  "bbox": [],
  "geometry": {"coordinates":[-84.8333,34.9833],"type":"Point"}
}