{
  "id": 2685629,
  "type": "Feature",
  "properties": {
    "tgn:hierarchy":[
        "tgn:2685629",
        "tgn:7002659",
        "tgn:1000001",
        "tgn:2000019",
        "tgn:7012149",
        "tgn:7029392"
    ],
    "tgn:id":2685629,
    "tgn:name":"Spring Branch",
    "tgn:placetype":[
        "aat:300008699"
    ]
},
  "bbox": [],
  "geometry": {"coordinates":[-86.45,31.1667],"type":"Point"}
}