{
  "id": 1055167,
  "type": "Feature",
  "properties": {
    "tgn:hierarchy":[
        "tgn:1055167",
        "tgn:1000004",
        "tgn:7011539",
        "tgn:7018214",
        "tgn:7002435",
        "tgn:7029392"
    ],
    "tgn:id":1055167,
    "tgn:name":"Kavalerovo",
    "tgn:placetype":[
        "aat:300008347"
    ]
},
  "bbox": [],
  "geometry": {"coordinates":[135.1333,44.3167],"type":"Point"}
}