{
  "id": 7439130,
  "type": "Feature",
  "properties": {
    "tgn:hierarchy":[
        "tgn:7439130",
        "tgn:7005580",
        "tgn:1000001",
        "tgn:7005560",
        "tgn:7029392"
    ],
    "tgn:id":7439130,
    "tgn:name":"Supac, Arroyo",
    "tgn:placetype":[
        "aat:300008699"
    ]
},
  "bbox": [],
  "geometry": {"coordinates":[-93.816667,17.083333],"type":"Point"}
}