{
  "id": 1081171,
  "type": "Feature",
  "properties": {
    "tgn:hierarchy":[
        "tgn:1081171",
        "tgn:7000895",
        "tgn:1000004",
        "tgn:1001031",
        "tgn:1000120",
        "tgn:7029392"
    ],
    "tgn:id":1081171,
    "tgn:name":"Sagara",
    "tgn:placetype":[
        "aat:300008347"
    ]
},
  "bbox": [],
  "geometry": {"coordinates":[138.1833,34.6333],"type":"Point"}
}