<<<<<<< HEAD
{
  "id": 2154296,
  "type": "Feature",
  "properties": {
    "tgn:hierarchy":[
        "tgn:2154296",
        "tgn:1000001",
        "tgn:7012149",
        "tgn:1002955",
        "tgn:7007706",
        "tgn:7029392"
    ],
    "tgn:id":2154296,
    "tgn:name":"Bear Creek",
    "tgn:placetype":[
        "aat:300008706"
    ]
},
  "bbox": [],
  "geometry": {"coordinates":[-80.9833,41.4167],"type":"Point"}
}
=======
{"geometry":{"type":"Point","coordinates":[-80.983300,41.416700]},"type":"Feature","properties":{"hierarchy":["tgn:2154296","tgn:1000001","tgn:7012149","tgn:1002955","tgn:7007706","tgn:7029392"],"placetype":["aat:300008706"],"id":2154296,"name:xx":"Bear Creek"}}
>>>>>>> 03f74aca74312dbeaf24d7e61306dd6a786dc3d0
