{
  "id": 2154296,
  "type": "Feature",
  "properties": {
    "tgn:hierarchy":[
        "tgn:2154296",
        "tgn:1000001",
        "tgn:7012149",
        "tgn:1002955",
        "tgn:7007706",
        "tgn:7029392"
    ],
    "tgn:id":2154296,
    "tgn:name":"Bear Creek",
    "tgn:placetype":[
        "aat:300008706"
    ]
},
  "bbox": [],
  "geometry": {"coordinates":[-80.9833,41.4167],"type":"Point"}
}