{
  "id": 2250673,
  "type": "Feature",
  "properties": {
    "tgn:hierarchy":[
        "tgn:2250673",
        "tgn:1000001",
        "tgn:2001431",
        "tgn:7012149",
        "tgn:7007566",
        "tgn:7029392"
    ],
    "tgn:id":2250673,
    "tgn:name":"Colorado, Cerro",
    "tgn:placetype":[
        "aat:300008798"
    ]
},
  "bbox": [],
  "geometry": {"coordinates":[-108.0333,35.1333],"type":"Point"}
}