<<<<<<< HEAD
{
  "id": 2250673,
  "type": "Feature",
  "properties": {
    "tgn:hierarchy":[
        "tgn:2250673",
        "tgn:1000001",
        "tgn:2001431",
        "tgn:7012149",
        "tgn:7007566",
        "tgn:7029392"
    ],
    "tgn:id":2250673,
    "tgn:name":"Colorado, Cerro",
    "tgn:placetype":[
        "aat:300008798"
    ]
},
  "bbox": [],
  "geometry": {"coordinates":[-108.0333,35.1333],"type":"Point"}
}
=======
{"geometry":{"type":"Point","coordinates":[-108.033300,35.133300]},"type":"Feature","properties":{"hierarchy":["tgn:2250673","tgn:1000001","tgn:2001431","tgn:7012149","tgn:7007566","tgn:7029392"],"placetype":["aat:300008798"],"id":2250673,"name:xx":"Colorado, Cerro"}}
>>>>>>> 03f74aca74312dbeaf24d7e61306dd6a786dc3d0
