{
  "id": 1073276,
  "type": "Feature",
  "properties": {
    "tgn:hierarchy":[
        "tgn:1073276",
        "tgn:1000004",
        "tgn:7002087",
        "tgn:1000111",
        "tgn:7029392"
    ],
    "tgn:id":1073276,
    "tgn:name":"Xuyong",
    "tgn:placetype":[
        "aat:300008347"
    ]
},
  "bbox": [],
  "geometry": {"coordinates":[105.35,28.2833],"type":"Point"}
}