{
  "id": 7233388,
  "type": "Feature",
  "properties": {
    "tgn:hierarchy":[
        "tgn:7233388",
        "tgn:7002750",
        "tgn:7001399",
        "tgn:1000003",
        "tgn:1000074",
        "tgn:7029392"
    ],
    "tgn:id":7233388,
    "tgn:name":"\u00c1yioi An\u00e1ryiroi",
    "tgn:placetype":[
        "aat:300008347"
    ]
},
  "bbox": [],
  "geometry": {"coordinates":[22.366667,39.533333],"type":"Point"}
}