{
  "id": 2628879,
  "type": "Feature",
  "properties": {
    "tgn:hierarchy":[
        "tgn:2628879",
        "tgn:1000001",
        "tgn:7012149",
        "tgn:7007253",
        "tgn:7029392"
    ],
    "tgn:id":2628879,
    "tgn:name":"Rose Branch",
    "tgn:placetype":[
        "aat:300008699"
    ]
},
  "bbox": [],
  "geometry": {"coordinates":[-94.7167,40.9167],"type":"Point"}
}