<<<<<<< HEAD
{
  "id": 2254724,
  "type": "Feature",
  "properties": {
    "tgn:hierarchy":[
        "tgn:2254724",
        "tgn:1000001",
        "tgn:7012149",
        "tgn:2001721",
        "tgn:7007708",
        "tgn:7029392"
    ],
    "tgn:id":2254724,
    "tgn:name":"Coon Ridge",
    "tgn:placetype":[
        "aat:300266640"
    ]
},
  "bbox": [],
  "geometry": {"coordinates":[-118.0833,45.4667],"type":"Point"}
}
=======
{"geometry":{"type":"Point","coordinates":[-118.083300,45.466700]},"type":"Feature","properties":{"hierarchy":["tgn:2254724","tgn:1000001","tgn:7012149","tgn:2001721","tgn:7007708","tgn:7029392"],"placetype":["aat:300266640"],"id":2254724,"name:xx":"Coon Ridge"}}
>>>>>>> 03f74aca74312dbeaf24d7e61306dd6a786dc3d0
