{
  "id": 7348100,
  "type": "Feature",
  "properties": {
    "tgn:hierarchy":[
        "tgn:7348100",
        "tgn:7002759",
        "tgn:7002845",
        "tgn:1000003",
        "tgn:1000095",
        "tgn:7029392"
    ],
    "tgn:id":7348100,
    "tgn:name":"Aladr\u00e9n",
    "tgn:placetype":[
        "aat:300008347"
    ]
},
  "bbox": [],
  "geometry": {"coordinates":[-1.15,41.25],"type":"Point"}
}