{
  "id": 2573940,
  "type": "Feature",
  "properties": {
    "tgn:hierarchy":[
        "tgn:2573940",
        "tgn:1000001",
        "tgn:7012149",
        "tgn:1002788",
        "tgn:7007706",
        "tgn:7029392"
    ],
    "tgn:id":2573940,
    "tgn:name":"Pee Pee Prairie",
    "tgn:placetype":[
        "aat:300055621"
    ]
},
  "bbox": [],
  "geometry": {"coordinates":[-82.9167,39.1667],"type":"Point"}
}