{
  "id": 7550255,
  "type": "Feature",
  "properties": {
    "tgn:hierarchy":[
        "tgn:7550255",
        "tgn:1000004",
        "tgn:7000198",
        "tgn:1001996",
        "tgn:7029392"
    ],
    "tgn:id":7550255,
    "tgn:name:en":"Chandru",
    "tgn:placetype":[
        "aat:300008347"
    ]
},
  "bbox": [],
  "geometry": {"coordinates":[76.267791,32.914259],"type":"Point"}
}