{
  "id": 2376107,
  "type": "Feature",
  "properties": {
    "tgn:hierarchy":[
        "tgn:2376107",
        "tgn:1000001",
        "tgn:7012149",
        "tgn:1002658",
        "tgn:7007706",
        "tgn:7029392"
    ],
    "tgn:id":2376107,
    "tgn:name":"Harbor Point",
    "tgn:placetype":[
        "aat:300008850"
    ]
},
  "bbox": [],
  "geometry": {"coordinates":[-84.5333,40.5333],"type":"Point"}
}