{
  "id": 2415583,
  "type": "Feature",
  "properties": {
    "tgn:hierarchy":[
        "tgn:2415583",
        "tgn:1000001",
        "tgn:7012149",
        "tgn:2002291",
        "tgn:7013961",
        "tgn:7029392"
    ],
    "tgn:id":2415583,
    "tgn:name":"Isner Creek",
    "tgn:placetype":[
        "aat:300008706"
    ]
},
  "bbox": [],
  "geometry": {"coordinates":[-79.7833,38.9333],"type":"Point"}
}