{
  "id": 7587036,
  "type": "Feature",
  "properties": {
    "tgn:hierarchy":[
        "tgn:7587036",
        "tgn:1000004",
        "tgn:7000198",
        "tgn:1001977",
        "tgn:7029392"
    ],
    "tgn:id":7587036,
    "tgn:name:en":"Alipur",
    "tgn:placetype":[
        "aat:300008347"
    ]
},
  "bbox": [],
  "geometry": {"coordinates":[88.470278,22.306389],"type":"Point"}
}