{
  "id": 2623988,
  "type": "Feature",
  "properties": {
    "tgn:hierarchy":[
        "tgn:2623988",
        "tgn:1000001",
        "tgn:7012149",
        "tgn:2000969",
        "tgn:7007520",
        "tgn:7029392"
    ],
    "tgn:id":2623988,
    "tgn:name":"Rock Harbor",
    "tgn:placetype":[
        "aat:300132316"
    ]
},
  "bbox": [],
  "geometry": {"coordinates":[-88.5333,48.1167],"type":"Point"}
}