{
  "id": 7399226,
  "type": "Feature",
  "properties": {
    "tgn:hierarchy":[
        "tgn:7399226",
        "tgn:1001835",
        "tgn:1000001",
        "tgn:7005560",
        "tgn:7029392"
    ],
    "tgn:id":7399226,
    "tgn:name":"Cinco de Mayo",
    "tgn:placetype":[
        "aat:300008347"
    ]
},
  "bbox": [],
  "geometry": {"coordinates":[-114.833333,32.616667],"type":"Point"}
}