{
  "id": 2577848,
  "type": "Feature",
  "properties": {
    "tgn:hierarchy":[
        "tgn:2577848",
        "tgn:1000001",
        "tgn:7016172",
        "tgn:7012149",
        "tgn:2000179",
        "tgn:7029392"
    ],
    "tgn:id":2577848,
    "tgn:name":"Petite Branch",
    "tgn:placetype":[
        "aat:300008699"
    ]
},
  "bbox": [],
  "geometry": {"coordinates":[-93.4667,35.0333],"type":"Point"}
}