{
  "id": 2341163,
  "type": "Feature",
  "properties": {
    "tgn:hierarchy":[
        "tgn:2341163",
        "tgn:7006450",
        "tgn:1000001",
        "tgn:7012149",
        "tgn:2000082",
        "tgn:7029392"
    ],
    "tgn:id":2341163,
    "tgn:name":"Fripo Island",
    "tgn:placetype":[
        "aat:300008791"
    ]
},
  "bbox": [],
  "geometry": {"coordinates":[-131.2167,55.0167],"type":"Point"}
}