{
  "id": 7525803,
  "type": "Feature",
  "properties": {
    "tgn:hierarchy":[
        "tgn:7525803",
        "tgn:7001242",
        "tgn:7016833",
        "tgn:1001088",
        "tgn:7029392"
    ],
    "tgn:id":7525803,
    "tgn:name:en":"Ban\u012b '\u0100mir",
    "tgn:placetype":[
        "aat:300008347"
    ]
},
  "bbox": [],
  "geometry": {"coordinates":[30.735034,28.662498],"type":"Point"}
}