{
  "id": 2278693,
  "type": "Feature",
  "properties": {
    "tgn:hierarchy":[
        "tgn:2278693",
        "tgn:1000001",
        "tgn:7012149",
        "tgn:7007157",
        "tgn:1002972",
        "tgn:7029392"
    ],
    "tgn:id":2278693,
    "tgn:name":"Dead Horse Creek",
    "tgn:placetype":[
        "aat:300008706"
    ]
},
  "bbox": [],
  "geometry": {"coordinates":[-118.8667,34.6333],"type":"Point"}
}