<<<<<<< HEAD
{
  "id": 7249597,
  "type": "Feature",
  "properties": {
    "tgn:hierarchy":[
        "tgn:7249597",
        "tgn:7007877",
        "tgn:1000003",
        "tgn:1000063",
        "tgn:4012014",
        "tgn:7029392"
    ],
    "tgn:id":7249597,
    "tgn:name":"Pont \u00e0 Chin",
    "tgn:placetype":[
        "aat:300008347"
    ]
},
  "bbox": [],
  "geometry": {"coordinates":[3.346113,50.642628],"type":"Point"}
}
=======
{"geometry":{"type":"Point","coordinates":[3.346113,50.642628]},"type":"Feature","properties":{"hierarchy":["tgn:7249597","tgn:7007877","tgn:1000003","tgn:1000063","tgn:4012014","tgn:7029392"],"placetype":["aat:300008347"],"id":7249597,"name:xx":"Pont \u00e0 Chin"}}
>>>>>>> 03f74aca74312dbeaf24d7e61306dd6a786dc3d0
