<<<<<<< HEAD
{
  "id": 7375974,
  "type": "Feature",
  "properties": {
    "tgn:hierarchy":[
        "tgn:7375974",
        "tgn:7005581",
        "tgn:1000001",
        "tgn:7005560",
        "tgn:7029392"
    ],
    "tgn:id":7375974,
    "tgn:name":"Rancho Las Varas",
    "tgn:placetype":[
        "aat:300000241"
    ]
},
  "bbox": [],
  "geometry": {"coordinates":[-104.95,27.816667],"type":"Point"}
}
=======
{"geometry":{"type":"Point","coordinates":[-104.950000,27.816667]},"type":"Feature","properties":{"hierarchy":["tgn:7375974","tgn:7005581","tgn:1000001","tgn:7005560","tgn:7029392"],"placetype":["aat:300000241"],"id":7375974,"name:xx":"Rancho Las Varas"}}
>>>>>>> 03f74aca74312dbeaf24d7e61306dd6a786dc3d0
