{
  "id": 2493570,
  "type": "Feature",
  "properties": {
    "tgn:hierarchy":[
        "tgn:2493570",
        "tgn:1000001",
        "tgn:7012149",
        "tgn:2002293",
        "tgn:7013961",
        "tgn:7029392"
    ],
    "tgn:id":2493570,
    "tgn:name":"Marsh Hart Knob",
    "tgn:placetype":[
        "aat:300008798"
    ]
},
  "bbox": [],
  "geometry": {"coordinates":[-81.5167,38.7667],"type":"Point"}
}