{
  "id": 2594550,
  "type": "Feature",
  "properties": {
    "tgn:hierarchy":[
        "tgn:2594550",
        "tgn:2000454",
        "tgn:1000001",
        "tgn:7012149",
        "tgn:7007250",
        "tgn:7029392"
    ],
    "tgn:id":2594550,
    "tgn:name":"Portneuf",
    "tgn:placetype":[
        "aat:300008347"
    ]
},
  "bbox": [],
  "geometry": {"coordinates":[-112.35,42.7833],"type":"Point"}
}