{
  "id": 7401195,
  "type": "Feature",
  "properties": {
    "tgn:hierarchy":[
        "tgn:7401195",
        "tgn:1000001",
        "tgn:7005599",
        "tgn:7005560",
        "tgn:7029392"
    ],
    "tgn:id":7401195,
    "tgn:name":"El Jacal",
    "tgn:placetype":[
        "aat:300008347"
    ]
},
  "bbox": [],
  "geometry": {"coordinates":[-97.233333,19.101389],"type":"Point"}
}