{
  "id": 7308845,
  "type": "Feature",
  "properties": {
    "tgn:hierarchy":[
        "tgn:7308845",
        "tgn:7016598",
        "tgn:1000049",
        "tgn:1000002",
        "tgn:7029392"
    ],
    "tgn:id":7308845,
    "tgn:name":"Los Tres Picos, Punta",
    "tgn:placetype":[
        "aat:300386846"
    ]
},
  "bbox": [],
  "geometry": {"coordinates":[-70.55,-24.333333],"type":"Point"}
}