{
  "id": 2320386,
  "type": "Feature",
  "properties": {
    "tgn:hierarchy":[
        "tgn:2320386",
        "tgn:1000001",
        "tgn:7012149",
        "tgn:7007525",
        "tgn:7029392"
    ],
    "tgn:id":2320386,
    "tgn:name":"Evergreen Creek",
    "tgn:placetype":[
        "aat:300008706"
    ]
},
  "bbox": [],
  "geometry": {"coordinates":[-100.5333,42.65],"type":"Point"}
}