{
  "id": 7513769,
  "type": "Feature",
  "properties": {
    "tgn:hierarchy":[
        "tgn:7513769",
        "tgn:1009227",
        "tgn:1000226",
        "tgn:7018437",
        "tgn:1000006",
        "tgn:7029392"
    ],
    "tgn:id":7513769,
    "tgn:name:en":"Florence Hill",
    "tgn:placetype":[
        "aat:300008777"
    ]
},
  "bbox": [],
  "geometry": {"coordinates":[169.466667,-46.566667],"type":"Point"}
}