{
  "id": 7285662,
  "type": "Feature",
  "properties": {
    "tgn:hierarchy":[
        "tgn:7285662",
        "tgn:1001699",
        "tgn:1000049",
        "tgn:1000002",
        "tgn:7029392"
    ],
    "tgn:id":7285662,
    "tgn:name":"Pichicullin",
    "tgn:placetype":[
        "aat:300000206"
    ]
},
  "bbox": [],
  "geometry": {"coordinates":[-73.316667,-39.633333],"type":"Point"}
}