<<<<<<< HEAD
{
  "id": 2250802,
  "type": "Feature",
  "properties": {
    "tgn:hierarchy":[
        "tgn:2250802",
        "tgn:1000001",
        "tgn:7019982",
        "tgn:7012149",
        "tgn:7007517",
        "tgn:7029392"
    ],
    "tgn:id":2250802,
    "tgn:name":"Colton Hollow",
    "tgn:placetype":[
        "aat:300008347"
    ]
},
  "bbox": [],
  "geometry": {"coordinates":[-72.35,42.1],"type":"Point"}
}
=======
{"geometry":{"type":"Point","coordinates":[-72.350000,42.100000]},"type":"Feature","properties":{"hierarchy":["tgn:2250802","tgn:1000001","tgn:7019982","tgn:7012149","tgn:7007517","tgn:7029392"],"placetype":["aat:300008347"],"id":2250802,"name:xx":"Colton Hollow"}}
>>>>>>> 03f74aca74312dbeaf24d7e61306dd6a786dc3d0
