{
  "id": 2231006,
  "type": "Feature",
  "properties": {
    "tgn:hierarchy":[
        "tgn:2231006",
        "tgn:1000001",
        "tgn:7006451",
        "tgn:7012149",
        "tgn:2000100",
        "tgn:7029392"
    ],
    "tgn:id":2231006,
    "tgn:name":"Cerro Colorado Tank",
    "tgn:placetype":[
        "aat:300006191"
    ]
},
  "bbox": [],
  "geometry": {"coordinates":[-111.25,31.6667],"type":"Point"}
}