{
  "id": 1098057,
  "type": "Feature",
  "properties": {
    "tgn:hierarchy":[
        "tgn:1098057",
        "tgn:7000490",
        "tgn:1000006",
        "tgn:7006238",
        "tgn:7029392"
    ],
    "tgn:id":1098057,
    "tgn:name":"Ringwood",
    "tgn:placetype":[
        "aat:300008347"
    ]
},
  "bbox": [],
  "geometry": {"coordinates":[145.25,-37.8167],"type":"Point"}
}