{
  "id": 7381176,
  "type": "Feature",
  "properties": {
    "tgn:hierarchy":[
        "tgn:7381176",
        "tgn:1000001",
        "tgn:7005597",
        "tgn:7005560",
        "tgn:7029392"
    ],
    "tgn:id":7381176,
    "tgn:name":"Lomita",
    "tgn:placetype":[
        "aat:300008347"
    ]
},
  "bbox": [],
  "geometry": {"coordinates":[-98.65,26.183333],"type":"Point"}
}