{
  "id": 7280121,
  "type": "Feature",
  "properties": {
    "tgn:hierarchy":[
        "tgn:7280121",
        "tgn:1001623",
        "tgn:1000049",
        "tgn:1000002",
        "tgn:7029392"
    ],
    "tgn:id":7280121,
    "tgn:name":"Resbal\u00f3n, R\u00edo",
    "tgn:placetype":[
        "aat:300008699"
    ]
},
  "bbox": [],
  "geometry": {"coordinates":[-72.866667,-48.15],"type":"Point"}
}