{
  "id": 7434736,
  "type": "Feature",
  "properties": {
    "tgn:hierarchy":[
        "tgn:7434736",
        "tgn:1000001",
        "tgn:7005600",
        "tgn:7005560",
        "tgn:7029392"
    ],
    "tgn:id":7434736,
    "tgn:name":"Xanab\u00e1",
    "tgn:placetype":[
        "aat:300008347"
    ]
},
  "bbox": [],
  "geometry": {"coordinates":[-89.016667,20.833333],"type":"Point"}
}