<<<<<<< HEAD
{
  "id": 7361499,
  "type": "Feature",
  "properties": {
    "tgn:hierarchy":[
        "tgn:7361499",
        "tgn:7005583",
        "tgn:1000001",
        "tgn:7005560",
        "tgn:7029392"
    ],
    "tgn:id":7361499,
    "tgn:name":"El Cortijo",
    "tgn:placetype":[
        "aat:300008347"
    ]
},
  "bbox": [],
  "geometry": {"coordinates":[-107.1,25.35],"type":"Point"}
}
=======
{"geometry":{"type":"Point","coordinates":[-107.100000,25.350000]},"type":"Feature","properties":{"hierarchy":["tgn:7361499","tgn:7005583","tgn:1000001","tgn:7005560","tgn:7029392"],"placetype":["aat:300008347"],"id":7361499,"name:xx":"El Cortijo"}}
>>>>>>> 03f74aca74312dbeaf24d7e61306dd6a786dc3d0
