{
  "id": 2287621,
  "type": "Feature",
  "properties": {
    "tgn:hierarchy":[
        "tgn:2287621",
        "tgn:1000001",
        "tgn:1002410",
        "tgn:7012149",
        "tgn:7007565",
        "tgn:7029392"
    ],
    "tgn:id":2287621,
    "tgn:name":"Dilkes Mills",
    "tgn:placetype":[
        "aat:300008347"
    ]
},
  "bbox": [],
  "geometry": {"coordinates":[-75.2667,39.7333],"type":"Point"}
}