{
  "id": 2145069,
  "type": "Feature",
  "properties": {
    "tgn:hierarchy":[
        "tgn:2145069",
        "tgn:1000001",
        "tgn:7012149",
        "tgn:7007157",
        "tgn:2000185",
        "tgn:7029392"
    ],
    "tgn:id":2145069,
    "tgn:name":"Bald Mountain",
    "tgn:placetype":[
        "aat:300008798"
    ]
},
  "bbox": [],
  "geometry": {"coordinates":[-123.1833,39.55],"type":"Point"}
}