{
  "id": 2063021,
  "type": "Feature",
  "properties": {
    "tgn:hierarchy":[
        "tgn:2063021",
        "tgn:1000001",
        "tgn:2001411",
        "tgn:7012149",
        "tgn:7007526",
        "tgn:7029392"
    ],
    "tgn:id":2063021,
    "tgn:name":"Moleen",
    "tgn:placetype":[
        "aat:300387016"
    ]
},
  "bbox": [],
  "geometry": {"coordinates":[-115.9333,40.7333],"type":"Point"}
}