{
  "id": 7250094,
  "type": "Feature",
  "properties": {
    "tgn:hierarchy":[
        "tgn:7250094",
        "tgn:7003458",
        "tgn:1000003",
        "tgn:1000063",
        "tgn:7018236",
        "tgn:7029392"
    ],
    "tgn:id":7250094,
    "tgn:name":"Moskou",
    "tgn:placetype":[
        "aat:300008347"
    ]
},
  "bbox": [],
  "geometry": {"coordinates":[2.958423,51.062884],"type":"Point"}
}