<<<<<<< HEAD
{
  "id": 2768199,
  "type": "Feature",
  "properties": {
    "tgn:hierarchy":[
        "tgn:2768199",
        "tgn:1000001",
        "tgn:7012149",
        "tgn:2002087",
        "tgn:7007826",
        "tgn:7029392"
    ],
    "tgn:id":2768199,
    "tgn:name":"Whites East Pit",
    "tgn:placetype":[
        "aat:300008680"
    ]
},
  "bbox": [],
  "geometry": {"coordinates":[-100.0,29.15],"type":"Point"}
}
=======
{"geometry":{"type":"Point","coordinates":[-100.000000,29.150000]},"type":"Feature","properties":{"hierarchy":["tgn:2768199","tgn:1000001","tgn:7012149","tgn:2002087","tgn:7007826","tgn:7029392"],"placetype":["aat:300008680"],"id":2768199,"name:xx":"Whites East Pit"}}
>>>>>>> 03f74aca74312dbeaf24d7e61306dd6a786dc3d0
