<<<<<<< HEAD
{
  "id": 2153756,
  "type": "Feature",
  "properties": {
    "tgn:hierarchy":[
        "tgn:2153756",
        "tgn:1000001",
        "tgn:7012149",
        "tgn:7007828",
        "tgn:7029392"
    ],
    "tgn:id":2153756,
    "tgn:name":"Bear Brook",
    "tgn:placetype":[
        "aat:300008699"
    ]
},
  "bbox": [],
  "geometry": {"coordinates":[-72.9333,43.8167],"type":"Point"}
}
=======
{"geometry":{"type":"Point","coordinates":[-72.933300,43.816700]},"type":"Feature","properties":{"hierarchy":["tgn:2153756","tgn:1000001","tgn:7012149","tgn:7007828","tgn:7029392"],"placetype":["aat:300008699"],"id":2153756,"name:xx":"Bear Brook"}}
>>>>>>> 03f74aca74312dbeaf24d7e61306dd6a786dc3d0
