{
  "id": 1053511,
  "type": "Feature",
  "properties": {
    "tgn:hierarchy":[
        "tgn:1053511",
        "tgn:1000004",
        "tgn:7011539",
        "tgn:7018214",
        "tgn:7002435",
        "tgn:7029392"
    ],
    "tgn:id":1053511,
    "tgn:name":"Dalnegorsk",
    "tgn:placetype":[
        "aat:300008347"
    ]
},
  "bbox": [],
  "geometry": {"coordinates":[135.5167,44.5167],"type":"Point"}
}