{
  "id": 7278421,
  "type": "Feature",
  "properties": {
    "tgn:hierarchy":[
        "tgn:7278421",
        "tgn:1001768",
        "tgn:1000049",
        "tgn:1000002",
        "tgn:7029392"
    ],
    "tgn:id":7278421,
    "tgn:name":"Los Molles, Pen\u00ednsula",
    "tgn:placetype":[
        "aat:300008804"
    ]
},
  "bbox": [],
  "geometry": {"coordinates":[-71.536667,-32.770278],"type":"Point"}
}