<<<<<<< HEAD
{
  "id": 7022902,
  "type": "Feature",
  "properties": {
    "tgn:hierarchy":[
        "tgn:7022902",
        "tgn:1000001",
        "tgn:7012149",
        "tgn:7029392"
    ],
    "tgn:id":7022902,
    "tgn:name":"Rubles Run",
    "tgn:placetype":[
        "aat:300008699"
    ]
},
  "bbox": [],
  "geometry": {"coordinates":[-79.75,39.7167],"type":"Point"}
}
=======
{"geometry":{"type":"Point","coordinates":[-79.750000,39.716700]},"type":"Feature","properties":{"hierarchy":["tgn:7022902","tgn:1000001","tgn:7012149","tgn:7029392"],"placetype":["aat:300008699"],"id":7022902,"name:xx":"Rubles Run"}}
>>>>>>> 03f74aca74312dbeaf24d7e61306dd6a786dc3d0
