{
  "id": 2124436,
  "type": "Feature",
  "properties": {
    "tgn:hierarchy":[
        "tgn:2124436",
        "tgn:1000001",
        "tgn:2001347",
        "tgn:7012149",
        "tgn:7007525",
        "tgn:7029392"
    ],
    "tgn:id":2124436,
    "tgn:name":"Aakenson Canyon",
    "tgn:placetype":[
        "aat:300008761"
    ]
},
  "bbox": [],
  "geometry": {"coordinates":[-100.5833,40.6833],"type":"Point"}
}