{
  "id": 7432860,
  "type": "Feature",
  "properties": {
    "tgn:hierarchy":[
        "tgn:7432860",
        "tgn:1000001",
        "tgn:1001960",
        "tgn:7005560",
        "tgn:7029392"
    ],
    "tgn:id":7432860,
    "tgn:name":"Tojibampo, Arroyo",
    "tgn:placetype":[
        "aat:300266554",
        "aat:300008699"
    ]
},
  "bbox": [],
  "geometry": {"coordinates":[-108.866667,27.466667],"type":"Point"}
}