{
  "id": 7504124,
  "type": "Feature",
  "properties": {
    "tgn:hierarchy":[
        "tgn:7504124",
        "tgn:1009227",
        "tgn:1000226",
        "tgn:7016729",
        "tgn:1000006",
        "tgn:7029392"
    ],
    "tgn:id":7504124,
    "tgn:name:en":"Water Hill",
    "tgn:placetype":[
        "aat:300008795"
    ]
},
  "bbox": [],
  "geometry": {"coordinates":[173.166667,-41.65],"type":"Point"}
}