{
  "id": 7224252,
  "type": "Feature",
  "properties": {
    "tgn:hierarchy":[
        "tgn:7224252",
        "tgn:7011170",
        "tgn:7002715",
        "tgn:1000003",
        "tgn:1000074",
        "tgn:7029392"
    ],
    "tgn:id":7224252,
    "tgn:name":"Terpsith\u00e9a",
    "tgn:placetype":[
        "aat:300008347"
    ]
},
  "bbox": [],
  "geometry": {"coordinates":[24.366667,41.166667],"type":"Point"}
}