{
  "id": 2237812,
  "type": "Feature",
  "properties": {
    "tgn:hierarchy":[
        "tgn:2237812",
        "tgn:1000001",
        "tgn:7012149",
        "tgn:2000430",
        "tgn:7007248",
        "tgn:7029392"
    ],
    "tgn:id":2237812,
    "tgn:name":"Chinquapin Ridge",
    "tgn:placetype":[
        "aat:300266640"
    ]
},
  "bbox": [],
  "geometry": {"coordinates":[-83.6667,34.8167],"type":"Point"}
}