<<<<<<< HEAD
{
  "id": 2705694,
  "type": "Feature",
  "properties": {
    "tgn:hierarchy":[
        "tgn:2705694",
        "tgn:1000001",
        "tgn:1002985",
        "tgn:7012149",
        "tgn:7007565",
        "tgn:7029392"
    ],
    "tgn:id":2705694,
    "tgn:name":"Susquehanna, Lake",
    "tgn:placetype":[
        "aat:300006191"
    ]
},
  "bbox": [],
  "geometry": {"coordinates":[-75.0,40.95],"type":"Point"}
}
=======
{"geometry":{"type":"Point","coordinates":[-75.000000,40.950000]},"type":"Feature","properties":{"hierarchy":["tgn:2705694","tgn:1000001","tgn:1002985","tgn:7012149","tgn:7007565","tgn:7029392"],"placetype":["aat:300006191"],"id":2705694,"name:xx":"Susquehanna, Lake"}}
>>>>>>> 03f74aca74312dbeaf24d7e61306dd6a786dc3d0
