{
  "id": 7516795,
  "type": "Feature",
  "properties": {
    "tgn:hierarchy":[
        "tgn:7516795",
        "tgn:1009227",
        "tgn:1000226",
        "tgn:7016729",
        "tgn:1000006",
        "tgn:7029392"
    ],
    "tgn:id":7516795,
    "tgn:name:en":"Kumutoto Bay",
    "tgn:placetype":[
        "aat:300132316"
    ]
},
  "bbox": [],
  "geometry": {"coordinates":[174.05,-41.216667],"type":"Point"}
}