{
  "id": 2579616,
  "type": "Feature",
  "properties": {
    "tgn:hierarchy":[
        "tgn:2579616",
        "tgn:1000001",
        "tgn:2000467",
        "tgn:7012149",
        "tgn:7007250",
        "tgn:7029392"
    ],
    "tgn:id":2579616,
    "tgn:name":"Picketts Upper Trough Spring",
    "tgn:placetype":[
        "aat:300008697"
    ]
},
  "bbox": [],
  "geometry": {"coordinates":[-114.1833,42.1167],"type":"Point"}
}