{
  "id": 2268449,
  "type": "Feature",
  "properties": {
    "tgn:hierarchy":[
        "tgn:2268449",
        "tgn:1000001",
        "tgn:2000459",
        "tgn:7012149",
        "tgn:7007250",
        "tgn:7029392"
    ],
    "tgn:id":2268449,
    "tgn:name":"Crooked Summit",
    "tgn:placetype":[
        "aat:300008798"
    ]
},
  "bbox": [],
  "geometry": {"coordinates":[-116.0333,43.6833],"type":"Point"}
}