<<<<<<< HEAD
{
  "id": 2769457,
  "type": "Feature",
  "properties": {
    "tgn:hierarchy":[
        "tgn:2769457",
        "tgn:1000001",
        "tgn:2002103",
        "tgn:7012149",
        "tgn:7007827",
        "tgn:7029392"
    ],
    "tgn:id":2769457,
    "tgn:name":"Wide Hollow",
    "tgn:placetype":[
        "aat:300008761"
    ]
},
  "bbox": [],
  "geometry": {"coordinates":[-111.9833,41.5667],"type":"Point"}
}
=======
{"geometry":{"type":"Point","coordinates":[-111.983300,41.566700]},"type":"Feature","properties":{"hierarchy":["tgn:2769457","tgn:1000001","tgn:2002103","tgn:7012149","tgn:7007827","tgn:7029392"],"placetype":["aat:300008761"],"id":2769457,"name:xx":"Wide Hollow"}}
>>>>>>> 03f74aca74312dbeaf24d7e61306dd6a786dc3d0
