{
  "id": 7166998,
  "type": "Feature",
  "properties": {
    "tgn:hierarchy":[
        "tgn:7166998",
        "tgn:7003692",
        "tgn:1000003",
        "tgn:7000084",
        "tgn:7029392"
    ],
    "tgn:id":7166998,
    "tgn:name":"Heinrichsweiler",
    "tgn:placetype":[
        "aat:300000206"
    ]
},
  "bbox": [],
  "geometry": {"coordinates":[9.05,47.85],"type":"Point"}
}