{
  "id": 1121961,
  "type": "Feature",
  "properties": {
    "tgn:hierarchy":[
        "tgn:1121961",
        "tgn:1000001",
        "tgn:1002228",
        "tgn:7012149",
        "tgn:7007709",
        "tgn:7029392"
    ],
    "tgn:id":1121961,
    "tgn:name":"Black",
    "tgn:placetype":[
        "aat:300008707"
    ]
},
  "bbox": [],
  "geometry": {"coordinates":[-75.9667,36.1833],"type":"Point"}
}