{
  "id": 2380051,
  "type": "Feature",
  "properties": {
    "tgn:hierarchy":[
        "tgn:2380051",
        "tgn:1000001",
        "tgn:7012149",
        "tgn:1002336",
        "tgn:7007919",
        "tgn:7029392"
    ],
    "tgn:id":2380051,
    "tgn:name":"Hatcher Run",
    "tgn:placetype":[
        "aat:300008699"
    ]
},
  "bbox": [],
  "geometry": {"coordinates":[-77.6833,37.15],"type":"Point"}
}