{
  "id": 7165981,
  "type": "Feature",
  "properties": {
    "tgn:hierarchy":[
        "tgn:7165981",
        "tgn:7003669",
        "tgn:1000003",
        "tgn:7000084",
        "tgn:7029392"
    ],
    "tgn:id":7165981,
    "tgn:name":"Hausmehring",
    "tgn:placetype":[
        "aat:300008347"
    ]
},
  "bbox": [],
  "geometry": {"coordinates":[11.816667,48.55],"type":"Point"}
}