{
  "id": 2287108,
  "type": "Feature",
  "properties": {
    "tgn:hierarchy":[
        "tgn:2287108",
        "tgn:1000001",
        "tgn:7012149",
        "tgn:2001489",
        "tgn:7007709",
        "tgn:7029392"
    ],
    "tgn:id":2287108,
    "tgn:name":"Dickerson Estates",
    "tgn:placetype":[
        "aat:300008347"
    ]
},
  "bbox": [],
  "geometry": {"coordinates":[-80.3167,35.8333],"type":"Point"}
}