{
  "id": 2657212,
  "type": "Feature",
  "properties": {
    "tgn:hierarchy":[
        "tgn:2657212",
        "tgn:1000001",
        "tgn:7006451",
        "tgn:2000092",
        "tgn:7012149",
        "tgn:7029392"
    ],
    "tgn:id":2657212,
    "tgn:name":"Sheep Spring",
    "tgn:placetype":[
        "aat:300008697"
    ]
},
  "bbox": [],
  "geometry": {"coordinates":[-110.7833,34.3167],"type":"Point"}
}