{
  "id": 7071922,
  "type": "Feature",
  "properties": {
    "tgn:hierarchy":[
        "tgn:7071922",
        "tgn:1000003",
        "tgn:7003687",
        "tgn:7000084",
        "tgn:7029392"
    ],
    "tgn:id":7071922,
    "tgn:name":"Theerh\u00fctte",
    "tgn:placetype":[
        "aat:300008347"
    ]
},
  "bbox": [],
  "geometry": {"coordinates":[11.516667,52.45],"type":"Point"}
}