{
  "id": 2340679,
  "type": "Feature",
  "properties": {
    "tgn:hierarchy":[
        "tgn:2340679",
        "tgn:1000001",
        "tgn:7012149",
        "tgn:1002296",
        "tgn:7007157",
        "tgn:7029392"
    ],
    "tgn:id":2340679,
    "tgn:name":"Frenzel Creek",
    "tgn:placetype":[
        "aat:300008706"
    ]
},
  "bbox": [],
  "geometry": {"coordinates":[-122.55,39.2667],"type":"Point"}
}