{
  "id": 2139129,
  "type": "Feature",
  "properties": {
    "tgn:hierarchy":[
        "tgn:2139129",
        "tgn:7013388",
        "tgn:1000001",
        "tgn:7012149",
        "tgn:7007517",
        "tgn:7029392"
    ],
    "tgn:id":2139129,
    "tgn:name":"Ashley, Mount",
    "tgn:placetype":[
        "aat:300008798"
    ]
},
  "bbox": [],
  "geometry": {"coordinates":[-73.4667,42.05],"type":"Point"}
}