{
  "id": 7349434,
  "type": "Feature",
  "properties": {
    "tgn:hierarchy":[
        "tgn:7349434",
        "tgn:1000001",
        "tgn:7005592",
        "tgn:7005560",
        "tgn:7029392"
    ],
    "tgn:id":7349434,
    "tgn:name":"Alseseca",
    "tgn:placetype":[
        "aat:300007783"
    ]
},
  "bbox": [],
  "geometry": {"coordinates":[-97.733333,18.833333],"type":"Point"}
}