{
  "id": 2107054,
  "type": "Feature",
  "properties": {
    "tgn:hierarchy":[
        "tgn:2107054",
        "tgn:1000001",
        "tgn:7012149",
        "tgn:2001986",
        "tgn:7007826",
        "tgn:7029392"
    ],
    "tgn:id":2107054,
    "tgn:name":"Rayland",
    "tgn:placetype":[
        "aat:300008347",
        "aat:300387210"
    ]
},
  "bbox": [],
  "geometry": {"coordinates":[-99.4667,34.05],"type":"Point"}
}