{
  "id": 2554256,
  "type": "Feature",
  "properties": {
    "tgn:hierarchy":[
        "tgn:2554256",
        "tgn:1000001",
        "tgn:7012149",
        "tgn:7007157",
        "tgn:1002828",
        "tgn:7029392"
    ],
    "tgn:id":2554256,
    "tgn:name":"Oak Street Creek Reservoir",
    "tgn:placetype":[
        "aat:300006191"
    ]
},
  "bbox": [],
  "geometry": {"coordinates":[-117.5833,33.8333],"type":"Point"}
}