{
  "id": 1005646,
  "type": "Feature",
  "properties": {
    "tgn:hierarchy":[
        "tgn:1005646",
        "tgn:1000003",
        "tgn:7003677",
        "tgn:7000084",
        "tgn:7029392"
    ],
    "tgn:id":1005646,
    "tgn:name":"Speckhorn",
    "tgn:placetype":[
        "aat:300000745"
    ]
},
  "bbox": [],
  "geometry": {"coordinates":[7.183333,51.65],"type":"Point"}
}