{
  "id": 2510173,
  "type": "Feature",
  "properties": {
    "tgn:hierarchy":[
        "tgn:2510173",
        "tgn:1000001",
        "tgn:7012149",
        "tgn:7007522",
        "tgn:7029392"
    ],
    "tgn:id":2510173,
    "tgn:name":"Middle Prong Silver Creek",
    "tgn:placetype":[
        "aat:300008706"
    ]
},
  "bbox": [],
  "geometry": {"coordinates":[-89.8833,31.8167],"type":"Point"}
}