{
  "id": 7504028,
  "type": "Feature",
  "properties": {
    "tgn:hierarchy":[
        "tgn:7504028",
        "tgn:1009227",
        "tgn:1000226",
        "tgn:7016822",
        "tgn:1000006",
        "tgn:7029392"
    ],
    "tgn:id":7504028,
    "tgn:name:en":"West Branch Elm Tree Creek",
    "tgn:placetype":[
        "aat:300008699"
    ]
},
  "bbox": [],
  "geometry": {"coordinates":[167.85,-45.583333],"type":"Point"}
}