{
  "id": 1086469,
  "type": "Feature",
  "properties": {
    "tgn:hierarchy":[
        "tgn:1086469",
        "tgn:7593737",
        "tgn:1000004",
        "tgn:7018454",
        "tgn:1000144",
        "tgn:7029392"
    ],
    "tgn:id":1086469,
    "tgn:name":"G\u00fcm\u00fc\u015fova",
    "tgn:placetype":[
        "aat:300008347"
    ]
},
  "bbox": [],
  "geometry": {"coordinates":[30.95,40.85],"type":"Point"}
}