{
  "id": 2055984,
  "type": "Feature",
  "properties": {
    "tgn:hierarchy":[
        "tgn:2055984",
        "tgn:1000001",
        "tgn:7012149",
        "tgn:2001148",
        "tgn:7007522",
        "tgn:7029392"
    ],
    "tgn:id":2055984,
    "tgn:name":"Blanton",
    "tgn:placetype":[
        "aat:300008347",
        "aat:300387210"
    ]
},
  "bbox": [],
  "geometry": {"coordinates":[-90.9167,32.7333],"type":"Point"}
}