<<<<<<< HEAD
{
  "id": 2407279,
  "type": "Feature",
  "properties": {
    "tgn:hierarchy":[
        "tgn:2407279",
        "tgn:1000001",
        "tgn:7014423",
        "tgn:7012149",
        "tgn:7007517",
        "tgn:7029392"
    ],
    "tgn:id":2407279,
    "tgn:name":"Hunting House Brook",
    "tgn:placetype":[
        "aat:300008699"
    ]
},
  "bbox": [],
  "geometry": {"coordinates":[-70.7833,41.9167],"type":"Point"}
}
=======
{"geometry":{"type":"Point","coordinates":[-70.783300,41.916700]},"type":"Feature","properties":{"hierarchy":["tgn:2407279","tgn:1000001","tgn:7014423","tgn:7012149","tgn:7007517","tgn:7029392"],"placetype":["aat:300008699"],"id":2407279,"name:xx":"Hunting House Brook"}}
>>>>>>> 03f74aca74312dbeaf24d7e61306dd6a786dc3d0
