{
  "id": 7243855,
  "type": "Feature",
  "properties": {
    "tgn:hierarchy":[
        "tgn:7243855",
        "tgn:7003461",
        "tgn:1000003",
        "tgn:1000063",
        "tgn:7018236",
        "tgn:7029392"
    ],
    "tgn:id":7243855,
    "tgn:name":"In de Hoven",
    "tgn:placetype":[
        "aat:300008347"
    ]
},
  "bbox": [],
  "geometry": {"coordinates":[5.583333,50.933333],"type":"Point"}
}