{
  "id": 2754840,
  "type": "Feature",
  "properties": {
    "tgn:hierarchy":[
        "tgn:2754840",
        "tgn:1000001",
        "tgn:7012149",
        "tgn:7007524",
        "tgn:7029392"
    ],
    "tgn:id":2754840,
    "tgn:name":"Weatherwax Creek",
    "tgn:placetype":[
        "aat:300008706"
    ]
},
  "bbox": [],
  "geometry": {"coordinates":[-110.6667,46.8333],"type":"Point"}
}