{
  "id": 2202676,
  "type": "Feature",
  "properties": {
    "tgn:hierarchy":[
        "tgn:2202676",
        "tgn:1000001",
        "tgn:7012149",
        "tgn:2000493",
        "tgn:7007250",
        "tgn:7029392"
    ],
    "tgn:id":2202676,
    "tgn:name":"Buck Trough Spring",
    "tgn:placetype":[
        "aat:300008697"
    ]
},
  "bbox": [],
  "geometry": {"coordinates":[-114.3833,42.1667],"type":"Point"}
}