<<<<<<< HEAD
{
  "id": 7113457,
  "type": "Feature",
  "properties": {
    "tgn:hierarchy":[
        "tgn:7113457",
        "tgn:1000003",
        "tgn:7003685",
        "tgn:7000084",
        "tgn:7029392"
    ],
    "tgn:id":7113457,
    "tgn:name":"Riesa-G\u00f6hlis",
    "tgn:placetype":[
        "aat:300008347"
    ]
},
  "bbox": [],
  "geometry": {"coordinates":[13.333333,51.3],"type":"Point"}
}
=======
{"geometry":{"type":"Point","coordinates":[13.333333,51.300000]},"type":"Feature","properties":{"hierarchy":["tgn:7113457","tgn:1000003","tgn:7003685","tgn:7000084","tgn:7029392"],"placetype":["aat:300008347"],"id":7113457,"name:xx":"Riesa-G\u00f6hlis"}}
>>>>>>> 03f74aca74312dbeaf24d7e61306dd6a786dc3d0
