{
  "id": 7072201,
  "type": "Feature",
  "properties": {
    "tgn:hierarchy":[
        "tgn:7072201",
        "tgn:1000003",
        "tgn:7003676",
        "tgn:7000084",
        "tgn:7029392"
    ],
    "tgn:id":7072201,
    "tgn:name":"F\u00f6rsterei Taubenberg",
    "tgn:placetype":[
        "aat:300004792"
    ]
},
  "bbox": [],
  "geometry": {"coordinates":[9.116667,52.166667],"type":"Point"}
}