{
  "id": 2222526,
  "type": "Feature",
  "properties": {
    "tgn:hierarchy":[
        "tgn:2222526",
        "tgn:1000001",
        "tgn:7012149",
        "tgn:2000972",
        "tgn:7007520",
        "tgn:7029392"
    ],
    "tgn:id":2222526,
    "tgn:name":"Carpenter Landing",
    "tgn:placetype":[
        "aat:300008347"
    ]
},
  "bbox": [],
  "geometry": {"coordinates":[-85.75,46.2833],"type":"Point"}
}