{
  "id": 2504031,
  "type": "Feature",
  "properties": {
    "tgn:hierarchy":[
        "tgn:2504031",
        "tgn:1000001",
        "tgn:7012149",
        "tgn:2002118",
        "tgn:7007827",
        "tgn:7029392"
    ],
    "tgn:id":2504031,
    "tgn:name":"Meadow Heights",
    "tgn:placetype":[
        "aat:300008347"
    ]
},
  "bbox": [],
  "geometry": {"coordinates":[-111.9667,40.6667],"type":"Point"}
}