<<<<<<< HEAD
{
  "id": 2338870,
  "type": "Feature",
  "properties": {
    "tgn:hierarchy":[
        "tgn:2338870",
        "tgn:1000001",
        "tgn:2001598",
        "tgn:7012149",
        "tgn:7007705",
        "tgn:7029392"
    ],
    "tgn:id":2338870,
    "tgn:name":"Frankhauser Lake",
    "tgn:placetype":[
        "aat:300008680"
    ]
},
  "bbox": [],
  "geometry": {"coordinates":[-100.3167,47.8],"type":"Point"}
}
=======
{"geometry":{"type":"Point","coordinates":[-100.316700,47.800000]},"type":"Feature","properties":{"hierarchy":["tgn:2338870","tgn:1000001","tgn:2001598","tgn:7012149","tgn:7007705","tgn:7029392"],"placetype":["aat:300008680"],"id":2338870,"name:xx":"Frankhauser Lake"}}
>>>>>>> 03f74aca74312dbeaf24d7e61306dd6a786dc3d0
