{
  "id": 7500786,
  "type": "Feature",
  "properties": {
    "tgn:hierarchy":[
        "tgn:7500786",
        "tgn:7001004",
        "tgn:1000004",
        "tgn:1000141",
        "tgn:7029392"
    ],
    "tgn:id":7500786,
    "tgn:name":"Lingshan Si",
    "tgn:placetype":[
        "aat:300007595"
    ]
},
  "bbox": [],
  "geometry": {"coordinates":[120.476111,22.885556],"type":"Point"}
}