{
  "id": 2715281,
  "type": "Feature",
  "properties": {
    "tgn:hierarchy":[
        "tgn:2715281",
        "tgn:1000001",
        "tgn:7006451",
        "tgn:2000091",
        "tgn:7012149",
        "tgn:7029392"
    ],
    "tgn:id":2715281,
    "tgn:name":"Teran Basin",
    "tgn:placetype":[
        "aat:300386845"
    ]
},
  "bbox": [],
  "geometry": {"coordinates":[-110.25,32.2833],"type":"Point"}
}