{
  "id": 2035928,
  "type": "Feature",
  "properties": {
    "tgn:hierarchy":[
        "tgn:2035928",
        "tgn:1000001",
        "tgn:2000604",
        "tgn:7012149",
        "tgn:7007253",
        "tgn:7029392"
    ],
    "tgn:id":2035928,
    "tgn:name":"Winfield",
    "tgn:placetype":[
        "aat:300008347"
    ]
},
  "bbox": [],
  "geometry": {"coordinates":[-91.4333,41.1167],"type":"Point"}
}