{
  "id": 7323274,
  "type": "Feature",
  "properties": {
    "tgn:hierarchy":[
        "tgn:7323274",
        "tgn:7002803",
        "tgn:1001647",
        "tgn:1000003",
        "tgn:1000095",
        "tgn:7029392"
    ],
    "tgn:id":7323274,
    "tgn:name":"Royo",
    "tgn:placetype":[
        "aat:300008347"
    ]
},
  "bbox": [],
  "geometry": {"coordinates":[-1.366667,38.966667],"type":"Point"}
}