{
  "id": 2571403,
  "type": "Feature",
  "properties": {
    "tgn:hierarchy":[
        "tgn:2571403",
        "tgn:2000858",
        "tgn:1000001",
        "tgn:7012149",
        "tgn:7007256",
        "tgn:7029392"
    ],
    "tgn:id":2571403,
    "tgn:name":"Paul, Lac a",
    "tgn:placetype":[
        "aat:300008680"
    ]
},
  "bbox": [],
  "geometry": {"coordinates":[-91.8667,31.1833],"type":"Point"}
}