{
  "id": 2374487,
  "type": "Feature",
  "properties": {
    "tgn:hierarchy":[
        "tgn:2374487",
        "tgn:1000001",
        "tgn:1002260",
        "tgn:7012149",
        "tgn:7007920",
        "tgn:7029392"
    ],
    "tgn:id":2374487,
    "tgn:name":"Hanan Canyon",
    "tgn:placetype":[
        "aat:300008761"
    ]
},
  "bbox": [],
  "geometry": {"coordinates":[-120.25,47.6667],"type":"Point"}
}