{
  "id": 7273263,
  "type": "Feature",
  "properties": {
    "tgn:concordances":{
        "gn:id":"2744745"
    },
    "tgn:hierarchy":[
        "tgn:7273263",
        "tgn:1000003",
        "tgn:7006951",
        "tgn:7016845",
        "tgn:7029392"
    ],
    "tgn:id":7273263,
    "tgn:name:nl":"Westergeest",
    "tgn:placetype":[
        "aat:300008347"
    ]
},
  "bbox": [],
  "geometry": {"coordinates":[4.816667,53.033333],"type":"Point"}
}