{
  "id": 1084108,
  "type": "Feature",
  "properties": {
    "tgn:hierarchy":[
        "tgn:1084108",
        "tgn:1000004",
        "tgn:7000373",
        "tgn:1000135",
        "tgn:7029392"
    ],
    "tgn:id":1084108,
    "tgn:name":"Caloocan",
    "tgn:placetype":[
        "aat:300008347",
        "aat:300008389",
        "aat:300000874",
        "aat:300265612",
        "aat:300387302"
    ]
},
  "bbox": [],
  "geometry": {"coordinates":[120.9667,14.6333],"type":"Point"}
}