{
  "id": 2174443,
  "type": "Feature",
  "properties": {
    "tgn:hierarchy":[
        "tgn:2174443",
        "tgn:1002808",
        "tgn:1000001",
        "tgn:7012149",
        "tgn:7007711",
        "tgn:7029392"
    ],
    "tgn:id":2174443,
    "tgn:name":"Bishop Heights",
    "tgn:placetype":[
        "aat:300008347"
    ]
},
  "bbox": [],
  "geometry": {"coordinates":[-71.55,41.8167],"type":"Point"}
}