<<<<<<< HEAD
{
  "id": 2259423,
  "type": "Feature",
  "properties": {
    "tgn:hierarchy":[
        "tgn:2259423",
        "tgn:1000001",
        "tgn:2001638",
        "tgn:7012149",
        "tgn:7007707",
        "tgn:7029392"
    ],
    "tgn:id":2259423,
    "tgn:name":"Cottonwood Spring",
    "tgn:placetype":[
        "aat:300008697"
    ]
},
  "bbox": [],
  "geometry": {"coordinates":[-98.75,34.7333],"type":"Point"}
}
=======
{"geometry":{"type":"Point","coordinates":[-98.750000,34.733300]},"type":"Feature","properties":{"hierarchy":["tgn:2259423","tgn:1000001","tgn:2001638","tgn:7012149","tgn:7007707","tgn:7029392"],"placetype":["aat:300008697"],"id":2259423,"name:xx":"Cottonwood Spring"}}
>>>>>>> 03f74aca74312dbeaf24d7e61306dd6a786dc3d0
