{
  "id": 7340929,
  "type": "Feature",
  "properties": {
    "tgn:hierarchy":[
        "tgn:7340929",
        "tgn:7002826",
        "tgn:7001158",
        "tgn:1000003",
        "tgn:1000095",
        "tgn:7029392"
    ],
    "tgn:id":7340929,
    "tgn:name":"Burro, Arroyo del",
    "tgn:placetype":[
        "aat:300266554",
        "aat:300008699"
    ]
},
  "bbox": [],
  "geometry": {"coordinates":[-5.316667,42.416667],"type":"Point"}
}