{
  "id": 2777268,
  "type": "Feature",
  "properties": {
    "tgn:hierarchy":[
        "tgn:2777268",
        "tgn:1000001",
        "tgn:2000778",
        "tgn:7012149",
        "tgn:7007255",
        "tgn:7029392"
    ],
    "tgn:id":2777268,
    "tgn:name":"Winford Pond",
    "tgn:placetype":[
        "aat:300008680"
    ]
},
  "bbox": [],
  "geometry": {"coordinates":[-89.05,36.9167],"type":"Point"}
}