{
  "id": 7418142,
  "type": "Feature",
  "properties": {
    "tgn:hierarchy":[
        "tgn:7418142",
        "tgn:7005580",
        "tgn:1000001",
        "tgn:7005560",
        "tgn:7029392"
    ],
    "tgn:id":7418142,
    "tgn:name":"La Herradura",
    "tgn:placetype":[
        "aat:300008347"
    ]
},
  "bbox": [],
  "geometry": {"coordinates":[-92.2225,14.576667],"type":"Point"}
}