{
  "id": 7181050,
  "type": "Feature",
  "properties": {
    "tgn:hierarchy":[
        "tgn:7181050",
        "tgn:7003692",
        "tgn:1000003",
        "tgn:7000084",
        "tgn:7029392"
    ],
    "tgn:id":7181050,
    "tgn:name":"Gaishauser Ried",
    "tgn:placetype":[
        "aat:300008903"
    ]
},
  "bbox": [],
  "geometry": {"coordinates":[9.783333,47.85],"type":"Point"}
}