{
  "id": 2287649,
  "type": "Feature",
  "properties": {
    "tgn:hierarchy":[
        "tgn:2287649",
        "tgn:1000001",
        "tgn:7012149",
        "tgn:2001758",
        "tgn:7007712",
        "tgn:7029392"
    ],
    "tgn:id":2287649,
    "tgn:name":"Dill Lake",
    "tgn:placetype":[
        "aat:300008680"
    ]
},
  "bbox": [],
  "geometry": {"coordinates":[-79.25,33.85],"type":"Point"}
}