<<<<<<< HEAD
{
  "id": 2765968,
  "type": "Feature",
  "properties": {
    "tgn:hierarchy":[
        "tgn:2765968",
        "tgn:1000001",
        "tgn:2001260",
        "tgn:7012149",
        "tgn:7007524",
        "tgn:7029392"
    ],
    "tgn:id":2765968,
    "tgn:name":"White Hills",
    "tgn:placetype":[
        "aat:300008697"
    ]
},
  "bbox": [],
  "geometry": {"coordinates":[-112.5167,44.8667],"type":"Point"}
}
=======
{"geometry":{"type":"Point","coordinates":[-112.516700,44.866700]},"type":"Feature","properties":{"hierarchy":["tgn:2765968","tgn:1000001","tgn:2001260","tgn:7012149","tgn:7007524","tgn:7029392"],"placetype":["aat:300008697"],"id":2765968,"name:xx":"White Hills"}}
>>>>>>> 03f74aca74312dbeaf24d7e61306dd6a786dc3d0
