{
  "id": 7298882,
  "type": "Feature",
  "properties": {
    "tgn:hierarchy":[
        "tgn:7298882",
        "tgn:7008912",
        "tgn:7030216",
        "tgn:1000003",
        "tgn:1000095",
        "tgn:7029392"
    ],
    "tgn:id":7298882,
    "tgn:name":"Tor",
    "tgn:placetype":[
        "aat:300008347"
    ]
},
  "bbox": [],
  "geometry": {"coordinates":[1.397073,42.571022],"type":"Point"}
}