{
  "id": 4010963,
  "type": "Feature",
  "properties": {
    "tgn:hierarchy":[
        "tgn:4010963",
        "tgn:7024123",
        "tgn:1000003",
        "tgn:7006366",
        "tgn:7029392"
    ],
    "tgn:id":4010963,
    "tgn:name":"Szklarska Pore\u031cba",
    "tgn:placetype":[
        "aat:300008347"
    ]
},
  "bbox": [],
  "geometry": {"coordinates":[15.55,50.8333],"type":"Point"}
}