<<<<<<< HEAD
{
  "id": 2403473,
  "type": "Feature",
  "properties": {
    "tgn:hierarchy":[
        "tgn:2403473",
        "tgn:1000001",
        "tgn:7012149",
        "tgn:2001692",
        "tgn:7007707",
        "tgn:7029392"
    ],
    "tgn:id":2403473,
    "tgn:name":"Hovey",
    "tgn:placetype":[
        "aat:300008347"
    ]
},
  "bbox": [],
  "geometry": {"coordinates":[-101.6667,36.85],"type":"Point"}
}
=======
{"geometry":{"type":"Point","coordinates":[-101.666700,36.850000]},"type":"Feature","properties":{"hierarchy":["tgn:2403473","tgn:1000001","tgn:7012149","tgn:2001692","tgn:7007707","tgn:7029392"],"placetype":["aat:300008347"],"id":2403473,"name:xx":"Hovey"}}
>>>>>>> 03f74aca74312dbeaf24d7e61306dd6a786dc3d0
