{
  "id": 2296749,
  "type": "Feature",
  "properties": {
    "tgn:hierarchy":[
        "tgn:2296749",
        "tgn:1000001",
        "tgn:2000470",
        "tgn:7012149",
        "tgn:7007250",
        "tgn:7029392"
    ],
    "tgn:id":2296749,
    "tgn:name":"Dry Creek",
    "tgn:placetype":[
        "aat:300008706"
    ]
},
  "bbox": [],
  "geometry": {"coordinates":[-115.0667,44.25],"type":"Point"}
}