<<<<<<< HEAD
{
  "id": 7379360,
  "type": "Feature",
  "properties": {
    "tgn:hierarchy":[
        "tgn:7379360",
        "tgn:1000001",
        "tgn:1001906",
        "tgn:7005560",
        "tgn:7029392"
    ],
    "tgn:id":7379360,
    "tgn:name":"Mariachi",
    "tgn:placetype":[
        "aat:300008347"
    ]
},
  "bbox": [],
  "geometry": {"coordinates":[-105.5,22.366667],"type":"Point"}
}
=======
{"geometry":{"type":"Point","coordinates":[-105.500000,22.366667]},"type":"Feature","properties":{"hierarchy":["tgn:7379360","tgn:1000001","tgn:1001906","tgn:7005560","tgn:7029392"],"placetype":["aat:300008347"],"id":7379360,"name:xx":"Mariachi"}}
>>>>>>> 03f74aca74312dbeaf24d7e61306dd6a786dc3d0
