{
  "id": 7555279,
  "type": "Feature",
  "properties": {
    "tgn:hierarchy":[
        "tgn:7555279",
        "tgn:1000004",
        "tgn:7000198",
        "tgn:1001894",
        "tgn:7029392"
    ],
    "tgn:id":7555279,
    "tgn:name:en":"Pabai",
    "tgn:placetype":[
        "aat:300008347"
    ]
},
  "bbox": [],
  "geometry": {"coordinates":[77.945988,23.754253],"type":"Point"}
}