{
  "id": 7500449,
  "type": "Feature",
  "properties": {
    "tgn:hierarchy":[
        "tgn:7500449",
        "tgn:7001004",
        "tgn:1000004",
        "tgn:1000141",
        "tgn:7029392"
    ],
    "tgn:id":7500449,
    "tgn:name":"Beishi Qiao",
    "tgn:placetype":[
        "aat:300007836"
    ]
},
  "bbox": [],
  "geometry": {"coordinates":[120.474722,22.874444],"type":"Point"}
}