{
  "id": 2326824,
  "type": "Feature",
  "properties": {
    "tgn:hierarchy":[
        "tgn:2326824",
        "tgn:1000001",
        "tgn:7012149",
        "tgn:1002742",
        "tgn:7007920",
        "tgn:7029392"
    ],
    "tgn:id":2326824,
    "tgn:name":"Fir Mountain",
    "tgn:placetype":[
        "aat:300008798"
    ]
},
  "bbox": [],
  "geometry": {"coordinates":[-118.9333,48.65],"type":"Point"}
}