{
  "id": 7045378,
  "type": "Feature",
  "properties": {
    "tgn:hierarchy":[
        "tgn:7045378",
        "tgn:1003432",
        "tgn:1000003",
        "tgn:7003240",
        "tgn:1000080",
        "tgn:7029392"
    ],
    "tgn:id":7045378,
    "tgn:name":"Forca",
    "tgn:placetype":[
        "aat:300008347"
    ]
},
  "bbox": [],
  "geometry": {"coordinates":[13.333333,42.816667],"type":"Point"}
}