{
  "id": 2474142,
  "type": "Feature",
  "properties": {
    "tgn:hierarchy":[
        "tgn:2474142",
        "tgn:1000001",
        "tgn:2001429",
        "tgn:7012149",
        "tgn:7007566",
        "tgn:7029392"
    ],
    "tgn:id":2474142,
    "tgn:name":"Lower Little Dry Creek Working",
    "tgn:placetype":[
        "aat:300000390"
    ]
},
  "bbox": [],
  "geometry": {"coordinates":[-108.7167,33.2333],"type":"Point"}
}