{
  "id": 7579643,
  "type": "Feature",
  "properties": {
    "tgn:hierarchy":[
        "tgn:7579643",
        "tgn:1000004",
        "tgn:1001832",
        "tgn:7000198",
        "tgn:7029392"
    ],
    "tgn:id":7579643,
    "tgn:name:en":"Son\u0101khira",
    "tgn:placetype":[
        "aat:300008347"
    ]
},
  "bbox": [],
  "geometry": {"coordinates":[92.28842,24.570637],"type":"Point"}
}