{
  "id": 7420996,
  "type": "Feature",
  "properties": {
    "tgn:hierarchy":[
        "tgn:7420996",
        "tgn:1000001",
        "tgn:7005589",
        "tgn:7005560",
        "tgn:7029392"
    ],
    "tgn:id":7420996,
    "tgn:name:es":"Ayancual, R\u00edo",
    "tgn:placetype":[
        "aat:300008699"
    ]
},
  "bbox": [],
  "geometry": {"coordinates":[-99.859167,25.6875],"type":"Point"}
}