<<<<<<< HEAD
{
  "id": 7243675,
  "type": "Feature",
  "properties": {
    "tgn:hierarchy":[
        "tgn:7243675",
        "tgn:7003466",
        "tgn:1000003",
        "tgn:1000063",
        "tgn:4012014",
        "tgn:7029392"
    ],
    "tgn:id":7243675,
    "tgn:name":"Hubeumont, Bois de",
    "tgn:placetype":[
        "aat:300008863"
    ]
},
  "bbox": [],
  "geometry": {"coordinates":[4.955731,50.496692],"type":"Point"}
}
=======
{"geometry":{"type":"Point","coordinates":[4.955731,50.496692]},"type":"Feature","properties":{"hierarchy":["tgn:7243675","tgn:7003466","tgn:1000003","tgn:1000063","tgn:4012014","tgn:7029392"],"placetype":["aat:300008863"],"id":7243675,"name:xx":"Hubeumont, Bois de"}}
>>>>>>> 03f74aca74312dbeaf24d7e61306dd6a786dc3d0
