{
  "id": 7562390,
  "type": "Feature",
  "properties": {
    "tgn:hierarchy":[
        "tgn:7562390",
        "tgn:1000004",
        "tgn:7000198",
        "tgn:1001894",
        "tgn:7029392"
    ],
    "tgn:id":7562390,
    "tgn:name:en":"R\u016bran",
    "tgn:placetype":[
        "aat:300008347"
    ]
},
  "bbox": [],
  "geometry": {"coordinates":[79.057043,26.474738],"type":"Point"}
}