{
  "id": 2765882,
  "type": "Feature",
  "properties": {
    "tgn:hierarchy":[
        "tgn:2765882",
        "tgn:2000090",
        "tgn:1000001",
        "tgn:7006451",
        "tgn:7012149",
        "tgn:7029392"
    ],
    "tgn:id":2765882,
    "tgn:name":"White Hair Spring",
    "tgn:placetype":[
        "aat:300008697"
    ]
},
  "bbox": [],
  "geometry": {"coordinates":[-109.3167,36.5167],"type":"Point"}
}