<<<<<<< HEAD
{
  "id": 2765882,
  "type": "Feature",
  "properties": {
    "tgn:hierarchy":[
        "tgn:2765882",
        "tgn:2000090",
        "tgn:1000001",
        "tgn:7006451",
        "tgn:7012149",
        "tgn:7029392"
    ],
    "tgn:id":2765882,
    "tgn:name":"White Hair Spring",
    "tgn:placetype":[
        "aat:300008697"
    ]
},
  "bbox": [],
  "geometry": {"coordinates":[-109.3167,36.5167],"type":"Point"}
}
=======
{"geometry":{"type":"Point","coordinates":[-109.316700,36.516700]},"type":"Feature","properties":{"hierarchy":["tgn:2765882","tgn:2000090","tgn:1000001","tgn:7006451","tgn:7012149","tgn:7029392"],"placetype":["aat:300008697"],"id":2765882,"name:xx":"White Hair Spring"}}
>>>>>>> 03f74aca74312dbeaf24d7e61306dd6a786dc3d0
