<<<<<<< HEAD
{
  "id": 2256316,
  "type": "Feature",
  "properties": {
    "tgn:hierarchy":[
        "tgn:2256316",
        "tgn:1000001",
        "tgn:7012149",
        "tgn:2001289",
        "tgn:7007524",
        "tgn:7029392"
    ],
    "tgn:id":2256316,
    "tgn:name":"Copperopolis Mine",
    "tgn:placetype":[
        "aat:300000390"
    ]
},
  "bbox": [],
  "geometry": {"coordinates":[-110.6167,46.6],"type":"Point"}
}
=======
{"geometry":{"type":"Point","coordinates":[-110.616700,46.600000]},"type":"Feature","properties":{"hierarchy":["tgn:2256316","tgn:1000001","tgn:7012149","tgn:2001289","tgn:7007524","tgn:7029392"],"placetype":["aat:300000390"],"id":2256316,"name:xx":"Copperopolis Mine"}}
>>>>>>> 03f74aca74312dbeaf24d7e61306dd6a786dc3d0
