{
  "id": 7561224,
  "type": "Feature",
  "properties": {
    "tgn:hierarchy":[
        "tgn:7561224",
        "tgn:1000004",
        "tgn:7000198",
        "tgn:7016722",
        "tgn:7029392"
    ],
    "tgn:id":7561224,
    "tgn:name:en":"Lokpur",
    "tgn:placetype":[
        "aat:300008347"
    ]
},
  "bbox": [],
  "geometry": {"coordinates":[79.164696,26.947772],"type":"Point"}
}