<<<<<<< HEAD
{
  "id": 2765779,
  "type": "Feature",
  "properties": {
    "tgn:hierarchy":[
        "tgn:2765779",
        "tgn:1000001",
        "tgn:7012149",
        "tgn:1002392",
        "tgn:7007157",
        "tgn:7029392"
    ],
    "tgn:id":2765779,
    "tgn:name":"White Divide",
    "tgn:placetype":[
        "aat:300266640"
    ]
},
  "bbox": [],
  "geometry": {"coordinates":[-118.7167,37.0167],"type":"Point"}
}
=======
{"geometry":{"type":"Point","coordinates":[-118.716700,37.016700]},"type":"Feature","properties":{"hierarchy":["tgn:2765779","tgn:1000001","tgn:7012149","tgn:1002392","tgn:7007157","tgn:7029392"],"placetype":["aat:300266640"],"id":2765779,"name:xx":"White Divide"}}
>>>>>>> 03f74aca74312dbeaf24d7e61306dd6a786dc3d0
