{
  "id": 2765779,
  "type": "Feature",
  "properties": {
    "tgn:hierarchy":[
        "tgn:2765779",
        "tgn:1000001",
        "tgn:7012149",
        "tgn:1002392",
        "tgn:7007157",
        "tgn:7029392"
    ],
    "tgn:id":2765779,
    "tgn:name":"White Divide",
    "tgn:placetype":[
        "aat:300266640"
    ]
},
  "bbox": [],
  "geometry": {"coordinates":[-118.7167,37.0167],"type":"Point"}
}