{
  "id": 7316300,
  "type": "Feature",
  "properties": {
    "tgn:hierarchy":[
        "tgn:7316300",
        "tgn:7016598",
        "tgn:1000049",
        "tgn:1000002",
        "tgn:7029392"
    ],
    "tgn:id":7316300,
    "tgn:name":"Card\u00f3n, Aguada",
    "tgn:placetype":[
        "aat:300008697"
    ]
},
  "bbox": [],
  "geometry": {"coordinates":[-70.533333,-24.75],"type":"Point"}
}