{
  "id": 7476570,
  "type": "Feature",
  "properties": {
    "tgn:hierarchy":[
        "tgn:7476570",
        "tgn:7488858",
        "tgn:1000004",
        "tgn:1000141",
        "tgn:7029392"
    ],
    "tgn:id":7476570,
    "tgn:name":"Zhongdong Qiao",
    "tgn:placetype":[
        "aat:300007836"
    ]
},
  "bbox": [],
  "geometry": {"coordinates":[120.758846,23.888046],"type":"Point"}
}