{
  "id": 7586189,
  "type": "Feature",
  "properties": {
    "tgn:hierarchy":[
        "tgn:7586189",
        "tgn:1000004",
        "tgn:7000198",
        "tgn:7000799",
        "tgn:7029392"
    ],
    "tgn:id":7586189,
    "tgn:name:en":"Wanye\u0101ram",
    "tgn:placetype":[
        "aat:300008347"
    ]
},
  "bbox": [],
  "geometry": {"coordinates":[74.942203,34.315793],"type":"Point"}
}