{
  "id": 2630542,
  "type": "Feature",
  "properties": {
    "tgn:hierarchy":[
        "tgn:2630542",
        "tgn:1000001",
        "tgn:7016172",
        "tgn:7012149",
        "tgn:2000169",
        "tgn:7029392"
    ],
    "tgn:id":2630542,
    "tgn:name":"Round Hill",
    "tgn:placetype":[
        "aat:300008798"
    ]
},
  "bbox": [],
  "geometry": {"coordinates":[-92.9333,35.8333],"type":"Point"}
}