{
  "id": 7124670,
  "type": "Feature",
  "properties": {
    "tgn:hierarchy":[
        "tgn:7124670",
        "tgn:1000003",
        "tgn:7000094",
        "tgn:7000084",
        "tgn:7029392"
    ],
    "tgn:id":7124670,
    "tgn:name":"Neu Gaarz",
    "tgn:placetype":[
        "aat:300008347"
    ]
},
  "bbox": [],
  "geometry": {"coordinates":[12.533333,53.583333],"type":"Point"}
}