{
  "id": 7347365,
  "type": "Feature",
  "properties": {
    "tgn:hierarchy":[
        "tgn:7347365",
        "tgn:7002805",
        "tgn:7002758",
        "tgn:1000003",
        "tgn:1000095",
        "tgn:7029392"
    ],
    "tgn:id":7347365,
    "tgn:name":"Bayarque",
    "tgn:placetype":[
        "aat:300008347"
    ]
},
  "bbox": [],
  "geometry": {"coordinates":[-2.433333,37.333333],"type":"Point"}
}