{
  "id": 1121068,
  "type": "Feature",
  "properties": {
    "tgn:hierarchy":[
        "tgn:1121068",
        "tgn:1000004",
        "tgn:7000198",
        "tgn:7029392"
    ],
    "tgn:id":1121068,
    "tgn:name":"Alaknanda",
    "tgn:placetype":[
        "aat:300008707"
    ]
},
  "bbox": [],
  "geometry": {"coordinates":[75.6667,30.1667],"type":"Point"}
}