{
  "id": 1077415,
  "type": "Feature",
  "properties": {
    "tgn:hierarchy":[
        "tgn:1077415",
        "tgn:7003964",
        "tgn:1000004",
        "tgn:1010065",
        "tgn:1001409",
        "tgn:1000116",
        "tgn:7029392"
    ],
    "tgn:id":1077415,
    "tgn:name":"Banda Elat",
    "tgn:placetype":[
        "aat:300008347"
    ]
},
  "bbox": [],
  "geometry": {"coordinates":[132.9833,-5.65],"type":"Point"}
}