{
  "id": 1006998,
  "type": "Feature",
  "properties": {
    "tgn:hierarchy":[
        "tgn:1006998",
        "tgn:1000001",
        "tgn:7021534",
        "tgn:7012149",
        "tgn:1002676",
        "tgn:7007240",
        "tgn:7029392"
    ],
    "tgn:id":1006998,
    "tgn:name":"Eagle Key",
    "tgn:placetype":[
        "aat:300008791"
    ]
},
  "bbox": [],
  "geometry": {"coordinates":[-80.5833,25.1667],"type":"Point"}
}