{
  "id": 2303774,
  "type": "Feature",
  "properties": {
    "tgn:hierarchy":[
        "tgn:2303774",
        "tgn:1000001",
        "tgn:2000315",
        "tgn:7012149",
        "tgn:7007248",
        "tgn:7029392"
    ],
    "tgn:id":2303774,
    "tgn:name":"Eagle Nest Lake",
    "tgn:placetype":[
        "aat:300008680"
    ]
},
  "bbox": [],
  "geometry": {"coordinates":[-82.15,30.85],"type":"Point"}
}