{
  "id": 2576101,
  "type": "Feature",
  "properties": {
    "tgn:hierarchy":[
        "tgn:2576101",
        "tgn:1000001",
        "tgn:7006451",
        "tgn:7012149",
        "tgn:2000099",
        "tgn:7029392"
    ],
    "tgn:id":2576101,
    "tgn:name":"Perkins Spring",
    "tgn:placetype":[
        "aat:300008697"
    ]
},
  "bbox": [],
  "geometry": {"coordinates":[-110.2667,34.3333],"type":"Point"}
}