<<<<<<< HEAD
{
  "id": 2151150,
  "type": "Feature",
  "properties": {
    "tgn:hierarchy":[
        "tgn:2151150",
        "tgn:1000001",
        "tgn:7012149",
        "tgn:2000969",
        "tgn:7007520",
        "tgn:7029392"
    ],
    "tgn:id":2151150,
    "tgn:name":"Bat Island",
    "tgn:placetype":[
        "aat:300008791"
    ]
},
  "bbox": [],
  "geometry": {"coordinates":[-88.45,48.1333],"type":"Point"}
}
=======
{"geometry":{"type":"Point","coordinates":[-88.450000,48.133300]},"type":"Feature","properties":{"hierarchy":["tgn:2151150","tgn:1000001","tgn:7012149","tgn:2000969","tgn:7007520","tgn:7029392"],"placetype":["aat:300008791"],"id":2151150,"name:xx":"Bat Island"}}
>>>>>>> 03f74aca74312dbeaf24d7e61306dd6a786dc3d0
