{
  "id": 7550895,
  "type": "Feature",
  "properties": {
    "tgn:hierarchy":[
        "tgn:7550895",
        "tgn:1000004",
        "tgn:7000198",
        "tgn:7016788",
        "tgn:7029392"
    ],
    "tgn:id":7550895,
    "tgn:name:en":"Bissau",
    "tgn:placetype":[
        "aat:300008347"
    ]
},
  "bbox": [],
  "geometry": {"coordinates":[75.076063,28.247179],"type":"Point"}
}