<<<<<<< HEAD
{
  "id": 2156978,
  "type": "Feature",
  "properties": {
    "tgn:hierarchy":[
        "tgn:2156978",
        "tgn:1000001",
        "tgn:7012149",
        "tgn:2002371",
        "tgn:7007923",
        "tgn:7029392"
    ],
    "tgn:id":2156978,
    "tgn:name":"Beauty Lake",
    "tgn:placetype":[
        "aat:300008680"
    ]
},
  "bbox": [],
  "geometry": {"coordinates":[-109.0167,42.8167],"type":"Point"}
}
=======
{"geometry":{"type":"Point","coordinates":[-109.016700,42.816700]},"type":"Feature","properties":{"hierarchy":["tgn:2156978","tgn:1000001","tgn:7012149","tgn:2002371","tgn:7007923","tgn:7029392"],"placetype":["aat:300008680"],"id":2156978,"name:xx":"Beauty Lake"}}
>>>>>>> 03f74aca74312dbeaf24d7e61306dd6a786dc3d0
