{
  "id": 2321051,
  "type": "Feature",
  "properties": {
    "tgn:hierarchy":[
        "tgn:2321051",
        "tgn:1000001",
        "tgn:7012149",
        "tgn:7022217",
        "tgn:7007919",
        "tgn:7029392"
    ],
    "tgn:id":2321051,
    "tgn:name":"Factory Hill",
    "tgn:placetype":[
        "aat:300008347"
    ]
},
  "bbox": [],
  "geometry": {"coordinates":[-76.85,36.55],"type":"Point"}
}