{
  "id": 7099565,
  "type": "Feature",
  "properties": {
    "tgn:hierarchy":[
        "tgn:7099565",
        "tgn:1000003",
        "tgn:7003678",
        "tgn:7000084",
        "tgn:7029392"
    ],
    "tgn:id":7099565,
    "tgn:name":"Somborn",
    "tgn:placetype":[
        "aat:300008347"
    ]
},
  "bbox": [],
  "geometry": {"coordinates":[9.116667,50.133333],"type":"Point"}
}