{
  "id": 7587270,
  "type": "Feature",
  "properties": {
    "tgn:hierarchy":[
        "tgn:7587270",
        "tgn:7001819",
        "tgn:1000004",
        "tgn:7000198",
        "tgn:7029392"
    ],
    "tgn:id":7587270,
    "tgn:name:en":"Gingba",
    "tgn:placetype":[
        "aat:300008347"
    ]
},
  "bbox": [],
  "geometry": {"coordinates":[93.868115,27.979526],"type":"Point"}
}