{
  "id": 2210565,
  "type": "Feature",
  "properties": {
    "tgn:hierarchy":[
        "tgn:2210565",
        "tgn:1000001",
        "tgn:2000584",
        "tgn:7012149",
        "tgn:7007253",
        "tgn:7029392"
    ],
    "tgn:id":2210565,
    "tgn:name":"Buss Creek",
    "tgn:placetype":[
        "aat:300008706"
    ]
},
  "bbox": [],
  "geometry": {"coordinates":[-95.5667,41.9667],"type":"Point"}
}