{
  "id": 7587415,
  "type": "Feature",
  "properties": {
    "tgn:hierarchy":[
        "tgn:7587415",
        "tgn:1000004",
        "tgn:7000198",
        "tgn:1001977",
        "tgn:7029392"
    ],
    "tgn:id":7587415,
    "tgn:name:en":"Basuld\u0101nga",
    "tgn:placetype":[
        "aat:300008347"
    ]
},
  "bbox": [],
  "geometry": {"coordinates":[88.238292,22.199556],"type":"Point"}
}