<<<<<<< HEAD
{
  "id": 2159701,
  "type": "Feature",
  "properties": {
    "tgn:hierarchy":[
        "tgn:2159701",
        "tgn:1000001",
        "tgn:7012149",
        "tgn:2001288",
        "tgn:7007524",
        "tgn:7029392"
    ],
    "tgn:id":2159701,
    "tgn:name":"Beebe Fork",
    "tgn:placetype":[
        "aat:300008699"
    ]
},
  "bbox": [],
  "geometry": {"coordinates":[-111.95,45.45],"type":"Point"}
}
=======
{"geometry":{"type":"Point","coordinates":[-111.950000,45.450000]},"type":"Feature","properties":{"hierarchy":["tgn:2159701","tgn:1000001","tgn:7012149","tgn:2001288","tgn:7007524","tgn:7029392"],"placetype":["aat:300008699"],"id":2159701,"name:xx":"Beebe Fork"}}
>>>>>>> 03f74aca74312dbeaf24d7e61306dd6a786dc3d0
