{
  "id": 1068353,
  "type": "Feature",
  "properties": {
    "tgn:hierarchy":[
        "tgn:1068353",
        "tgn:1000004",
        "tgn:1000960",
        "tgn:1000111",
        "tgn:7029392"
    ],
    "tgn:id":1068353,
    "tgn:name":"Goutou",
    "tgn:placetype":[
        "aat:300008347"
    ]
},
  "bbox": [],
  "geometry": {"coordinates":[117.1833,39.8167],"type":"Point"}
}