<<<<<<< HEAD
{
  "id": 2257332,
  "type": "Feature",
  "properties": {
    "tgn:hierarchy":[
        "tgn:2257332",
        "tgn:7014201",
        "tgn:1000001",
        "tgn:7012149",
        "tgn:7007239",
        "tgn:7029392"
    ],
    "tgn:id":2257332,
    "tgn:name":"Cornish Hills",
    "tgn:placetype":[
        "aat:300008347"
    ]
},
  "bbox": [],
  "geometry": {"coordinates":[-75.7,39.7667],"type":"Point"}
}
=======
{"geometry":{"type":"Point","coordinates":[-75.700000,39.766700]},"type":"Feature","properties":{"hierarchy":["tgn:2257332","tgn:7014201","tgn:1000001","tgn:7012149","tgn:7007239","tgn:7029392"],"placetype":["aat:300008347"],"id":2257332,"name:xx":"Cornish Hills"}}
>>>>>>> 03f74aca74312dbeaf24d7e61306dd6a786dc3d0
