{
  "id": 2110249,
  "type": "Feature",
  "properties": {
    "tgn:hierarchy":[
        "tgn:2110249",
        "tgn:1000001",
        "tgn:7012149",
        "tgn:2002180",
        "tgn:7007919",
        "tgn:7029392"
    ],
    "tgn:id":2110249,
    "tgn:name":"Ajax",
    "tgn:placetype":[
        "aat:300008347",
        "aat:300387210"
    ]
},
  "bbox": [],
  "geometry": {"coordinates":[-79.5667,36.9667],"type":"Point"}
}