{
  "id": 7234667,
  "type": "Feature",
  "properties": {
    "tgn:hierarchy":[
        "tgn:7234667",
        "tgn:7002711",
        "tgn:7001338",
        "tgn:1000003",
        "tgn:1000074",
        "tgn:7029392"
    ],
    "tgn:id":7234667,
    "tgn:name":"\u00c1fra",
    "tgn:placetype":[
        "aat:300008347"
    ]
},
  "bbox": [],
  "geometry": {"coordinates":[19.857778,39.619722],"type":"Point"}
}