{
  "id": 7546735,
  "type": "Feature",
  "properties": {
    "tgn:hierarchy":[
        "tgn:7546735",
        "tgn:1000004",
        "tgn:7000198",
        "tgn:7016883",
        "tgn:7029392"
    ],
    "tgn:id":7546735,
    "tgn:name:en":"Bela",
    "tgn:placetype":[
        "aat:300008347"
    ]
},
  "bbox": [],
  "geometry": {"coordinates":[76.407394,30.934297],"type":"Point"}
}