{
  "id": 2349237,
  "type": "Feature",
  "properties": {
    "tgn:hierarchy":[
        "tgn:2349237",
        "tgn:7016100",
        "tgn:1000001",
        "tgn:7012149",
        "tgn:7007516",
        "tgn:7029392"
    ],
    "tgn:id":2349237,
    "tgn:name":"Gilbert Swamp Run",
    "tgn:placetype":[
        "aat:300008699"
    ]
},
  "bbox": [],
  "geometry": {"coordinates":[-76.8333,38.4833],"type":"Point"}
}