{
  "id": 2196128,
  "type": "Feature",
  "properties": {
    "tgn:hierarchy":[
        "tgn:2196128",
        "tgn:1000001",
        "tgn:7012149",
        "tgn:1003038",
        "tgn:7007517",
        "tgn:7029392"
    ],
    "tgn:id":2196128,
    "tgn:name":"Brockway Corner",
    "tgn:placetype":[
        "aat:300008347"
    ]
},
  "bbox": [],
  "geometry": {"coordinates":[-71.55,42.4333],"type":"Point"}
}