{
  "id": 1056693,
  "type": "Feature",
  "properties": {
    "tgn:hierarchy":[
        "tgn:1056693",
        "tgn:7012935",
        "tgn:1000004",
        "tgn:7014786",
        "tgn:7029392"
    ],
    "tgn:id":1056693,
    "tgn:name":"Makinsk",
    "tgn:placetype":[
        "aat:300008347"
    ]
},
  "bbox": [],
  "geometry": {"coordinates":[70.4667,52.6667],"type":"Point"}
}