{
  "id": 2125424,
  "type": "Feature",
  "properties": {
    "tgn:hierarchy":[
        "tgn:2125424",
        "tgn:1000001",
        "tgn:7012149",
        "tgn:1002961",
        "tgn:7007568",
        "tgn:7029392"
    ],
    "tgn:id":2125424,
    "tgn:name":"Acorn Hill",
    "tgn:placetype":[
        "aat:300008798"
    ]
},
  "bbox": [],
  "geometry": {"coordinates":[-74.1667,42.0167],"type":"Point"}
}