{
  "id": 7437050,
  "type": "Feature",
  "properties": {
    "tgn:hierarchy":[
        "tgn:7437050",
        "tgn:1000001",
        "tgn:7005592",
        "tgn:7005560",
        "tgn:7029392"
    ],
    "tgn:id":7437050,
    "tgn:name":"Tepexco",
    "tgn:placetype":[
        "aat:300008347"
    ]
},
  "bbox": [],
  "geometry": {"coordinates":[-98.683333,18.633333],"type":"Point"}
}