{
  "id": 7446036,
  "type": "Feature",
  "properties": {
    "tgn:hierarchy":[
        "tgn:7446036",
        "tgn:7002445",
        "tgn:1000003",
        "tgn:7008166",
        "tgn:7008591",
        "tgn:7029392"
    ],
    "tgn:id":7446036,
    "tgn:name:en":"Riccal Dale",
    "tgn:placetype":[
        "aat:300008761"
    ]
},
  "bbox": [],
  "geometry": {"coordinates":[-1.033333,54.283333],"type":"Point"}
}