{
  "id": 7470934,
  "type": "Feature",
  "properties": {
    "tgn:hierarchy":[
        "tgn:7470934",
        "tgn:1000004",
        "tgn:7489179",
        "tgn:1000141",
        "tgn:7029392"
    ],
    "tgn:id":7470934,
    "tgn:name":"Erjie Cun",
    "tgn:placetype":[
        "aat:300387173"
    ]
},
  "bbox": [],
  "geometry": {"coordinates":[121.772514,24.703986],"type":"Point"}
}