{
  "id": 2284033,
  "type": "Feature",
  "properties": {
    "tgn:hierarchy":[
        "tgn:2284033",
        "tgn:1000001",
        "tgn:7012149",
        "tgn:2000808",
        "tgn:7007255",
        "tgn:7029392"
    ],
    "tgn:id":2284033,
    "tgn:name":"Denny Branch",
    "tgn:placetype":[
        "aat:300008699"
    ]
},
  "bbox": [],
  "geometry": {"coordinates":[-84.15,37.2667],"type":"Point"}
}