{
  "id": 2122073,
  "type": "Feature",
  "properties": {
    "tgn:hierarchy":[
        "tgn:2122073",
        "tgn:1000001",
        "tgn:7012149",
        "tgn:2002334",
        "tgn:7007922",
        "tgn:7029392"
    ],
    "tgn:id":2122073,
    "tgn:name":"Otis",
    "tgn:placetype":[
        "aat:300387016"
    ]
},
  "bbox": [],
  "geometry": {"coordinates":[-89.6833,45.2667],"type":"Point"}
}