{
  "id": 2771328,
  "type": "Feature",
  "properties": {
    "tgn:hierarchy":[
        "tgn:2771328",
        "tgn:1000001",
        "tgn:2001265",
        "tgn:7012149",
        "tgn:7007524",
        "tgn:7029392"
    ],
    "tgn:id":2771328,
    "tgn:name":"Wilder Butte",
    "tgn:placetype":[
        "aat:300008798"
    ]
},
  "bbox": [],
  "geometry": {"coordinates":[-104.5667,45.95],"type":"Point"}
}