{
  "id": 2221251,
  "type": "Feature",
  "properties": {
    "tgn:hierarchy":[
        "tgn:2221251",
        "tgn:1000001",
        "tgn:7012149",
        "tgn:2000479",
        "tgn:7007250",
        "tgn:7029392"
    ],
    "tgn:id":2221251,
    "tgn:name":"Cardin Creek",
    "tgn:placetype":[
        "aat:300008706"
    ]
},
  "bbox": [],
  "geometry": {"coordinates":[-116.6167,47.8333],"type":"Point"}
}