{
  "id": 2069915,
  "type": "Feature",
  "properties": {
    "tgn:hierarchy":[
        "tgn:2069915",
        "tgn:1000001",
        "tgn:7012149",
        "tgn:1003040",
        "tgn:7007568",
        "tgn:7029392"
    ],
    "tgn:id":2069915,
    "tgn:name":"Java Center",
    "tgn:placetype":[
        "aat:300008347"
    ]
},
  "bbox": [],
  "geometry": {"coordinates":[-78.3833,42.65],"type":"Point"}
}