{
  "id": 2107319,
  "type": "Feature",
  "properties": {
    "tgn:hierarchy":[
        "tgn:2107319",
        "tgn:1000001",
        "tgn:7012149",
        "tgn:2002011",
        "tgn:7007826",
        "tgn:7029392"
    ],
    "tgn:id":2107319,
    "tgn:name":"Sabine Pass",
    "tgn:placetype":[
        "aat:300008347"
    ]
},
  "bbox": [],
  "geometry": {"coordinates":[-93.8833,29.7333],"type":"Point"}
}