{
  "id": 2746952,
  "type": "Feature",
  "properties": {
    "tgn:hierarchy":[
        "tgn:2746952",
        "tgn:2000943",
        "tgn:1000001",
        "tgn:7012149",
        "tgn:7007520",
        "tgn:7029392"
    ],
    "tgn:id":2746952,
    "tgn:name":"Wagner Creek",
    "tgn:placetype":[
        "aat:300008706"
    ]
},
  "bbox": [],
  "geometry": {"coordinates":[-86.6167,46.3667],"type":"Point"}
}