{
  "id": 2341116,
  "type": "Feature",
  "properties": {
    "tgn:hierarchy":[
        "tgn:2341116",
        "tgn:1000001",
        "tgn:7012149",
        "tgn:2001457",
        "tgn:7007566",
        "tgn:7029392"
    ],
    "tgn:id":2341116,
    "tgn:name":"Frijoles Canyon",
    "tgn:placetype":[
        "aat:300008761"
    ]
},
  "bbox": [],
  "geometry": {"coordinates":[-105.4667,36.4833],"type":"Point"}
}