{
  "id": 7072317,
  "type": "Feature",
  "properties": {
    "tgn:hierarchy":[
        "tgn:7072317",
        "tgn:1000003",
        "tgn:7003688",
        "tgn:7000084",
        "tgn:7029392"
    ],
    "tgn:id":7072317,
    "tgn:name":"Stromholz",
    "tgn:placetype":[
        "aat:300000206"
    ]
},
  "bbox": [],
  "geometry": {"coordinates":[9.933333,54.55],"type":"Point"}
}