{
  "id": 2491306,
  "type": "Feature",
  "properties": {
    "tgn:hierarchy":[
        "tgn:2491306",
        "tgn:1000001",
        "tgn:7012149",
        "tgn:7029392"
    ],
    "tgn:id":2491306,
    "tgn:name":"Maple Creek",
    "tgn:placetype":[
        "aat:300008706"
    ]
},
  "bbox": [],
  "geometry": {"coordinates":[-99.7167,39.9667],"type":"Point"}
}