{
  "id": 2327294,
  "type": "Feature",
  "properties": {
    "tgn:hierarchy":[
        "tgn:2327294",
        "tgn:1000001",
        "tgn:7012149",
        "tgn:1002591",
        "tgn:7007255",
        "tgn:7029392"
    ],
    "tgn:id":2327294,
    "tgn:name":"First Hollow",
    "tgn:placetype":[
        "aat:300008761"
    ]
},
  "bbox": [],
  "geometry": {"coordinates":[-83.15,38.5833],"type":"Point"}
}