{
  "id": 7017168,
  "type": "Feature",
  "properties": {
    "tgn:hierarchy":[
        "tgn:7017168",
        "tgn:1000003",
        "tgn:7003687",
        "tgn:7000084",
        "tgn:7029392"
    ],
    "tgn:id":7017168,
    "tgn:name":"Halle",
    "tgn:placetype":[
        "aat:300387145",
        "aat:300387081"
    ]
},
  "bbox": [],
  "geometry": {"coordinates":[6.9167,52.45],"type":"Point"}
}