{
  "id": 2432288,
  "type": "Feature",
  "properties": {
    "tgn:hierarchy":[
        "tgn:2432288",
        "tgn:1007657",
        "tgn:1002534",
        "tgn:1000001",
        "tgn:7012149",
        "tgn:7007249",
        "tgn:7029392"
    ],
    "tgn:id":2432288,
    "tgn:name":"Kealia Forest Reserve",
    "tgn:placetype":[
        "aat:300008863"
    ]
},
  "bbox": [],
  "geometry": {"coordinates":[-159.3833,22.15],"type":"Point"}
}