{
  "id": 2734549,
  "type": "Feature",
  "properties": {
    "tgn:hierarchy":[
        "tgn:2734549",
        "tgn:1000001",
        "tgn:7012149",
        "tgn:7007157",
        "tgn:2000190",
        "tgn:7029392"
    ],
    "tgn:id":2734549,
    "tgn:name":"Tuscan Buttes",
    "tgn:placetype":[
        "aat:300008798"
    ]
},
  "bbox": [],
  "geometry": {"coordinates":[-122.0833,40.25],"type":"Point"}
}