<<<<<<< HEAD
{
  "id": 2330579,
  "type": "Feature",
  "properties": {
    "tgn:hierarchy":[
        "tgn:2330579",
        "tgn:1000001",
        "tgn:7012149",
        "tgn:7007708",
        "tgn:7029392"
    ],
    "tgn:id":2330579,
    "tgn:name":"Flat Creek",
    "tgn:placetype":[
        "aat:300008706"
    ]
},
  "bbox": [],
  "geometry": {"coordinates":[-122.45,43.0167],"type":"Point"}
}
=======
{"geometry":{"type":"Point","coordinates":[-122.450000,43.016700]},"type":"Feature","properties":{"hierarchy":["tgn:2330579","tgn:1000001","tgn:7012149","tgn:7007708","tgn:7029392"],"placetype":["aat:300008706"],"id":2330579,"name:xx":"Flat Creek"}}
>>>>>>> 03f74aca74312dbeaf24d7e61306dd6a786dc3d0
