{
  "id": 7012804,
  "type": "Feature",
  "properties": {
    "tgn:hierarchy":[
        "tgn:7012804",
        "tgn:1000003",
        "tgn:7003687",
        "tgn:7000084",
        "tgn:7029392"
    ],
    "tgn:id":7012804,
    "tgn:name":"Dessau",
    "tgn:placetype":[
        "aat:300008347",
        "aat:300387240",
        "aat:300008389",
        "aat:300005135",
        "aat:300264742",
        "aat:300387316",
        "aat:300387270",
        "aat:300387302",
        "aat:300120599",
        "aat:300387288"
    ]
},
  "bbox": [],
  "geometry": {"coordinates":[12.25,51.833333],"type":"Point"}
}