{
  "id": 2290724,
  "type": "Feature",
  "properties": {
    "tgn:hierarchy":[
        "tgn:2290724",
        "tgn:1000001",
        "tgn:7012149",
        "tgn:7007251",
        "tgn:7029392"
    ],
    "tgn:id":2290724,
    "tgn:name":"Dog Creek",
    "tgn:placetype":[
        "aat:300008706"
    ]
},
  "bbox": [],
  "geometry": {"coordinates":[-88.5333,37.1833],"type":"Point"}
}