<<<<<<< HEAD
{
  "id": 7242552,
  "type": "Feature",
  "properties": {
    "tgn:hierarchy":[
        "tgn:7242552",
        "tgn:7003456",
        "tgn:1000003",
        "tgn:1000063",
        "tgn:7018236",
        "tgn:7029392"
    ],
    "tgn:id":7242552,
    "tgn:name":"Fort van Koningshooikt",
    "tgn:placetype":[
        "aat:300006909"
    ]
},
  "bbox": [],
  "geometry": {"coordinates":[4.566667,51.083333],"type":"Point"}
}
=======
{"geometry":{"type":"Point","coordinates":[4.566667,51.083333]},"type":"Feature","properties":{"hierarchy":["tgn:7242552","tgn:7003456","tgn:1000003","tgn:1000063","tgn:7018236","tgn:7029392"],"placetype":["aat:300006909"],"id":7242552,"name:xx":"Fort van Koningshooikt"}}
>>>>>>> 03f74aca74312dbeaf24d7e61306dd6a786dc3d0
