{
  "id": 2725134,
  "type": "Feature",
  "properties": {
    "tgn:hierarchy":[
        "tgn:2725134",
        "tgn:1000001",
        "tgn:7012149",
        "tgn:7018871",
        "tgn:7007920",
        "tgn:7029392"
    ],
    "tgn:id":2725134,
    "tgn:name":"Tonga Ridge",
    "tgn:placetype":[
        "aat:300266640"
    ]
},
  "bbox": [],
  "geometry": {"coordinates":[-121.2333,47.6667],"type":"Point"}
}