{
  "id": 7048747,
  "type": "Feature",
  "properties": {
    "tgn:hierarchy":[
        "tgn:7048747",
        "tgn:1000003",
        "tgn:7003152",
        "tgn:7003237",
        "tgn:1000080",
        "tgn:7029392"
    ],
    "tgn:id":7048747,
    "tgn:name":"Dosso",
    "tgn:placetype":[
        "aat:300008347"
    ]
},
  "bbox": [],
  "geometry": {"coordinates":[10.216667,46.45],"type":"Point"}
}