{
  "id": 1061761,
  "type": "Feature",
  "properties": {
    "tgn:hierarchy":[
        "tgn:1061761",
        "tgn:7002844",
        "tgn:7030216",
        "tgn:1000003",
        "tgn:1000095",
        "tgn:7029392"
    ],
    "tgn:id":1061761,
    "tgn:name":"Amposta",
    "tgn:placetype":[
        "aat:300008347"
    ]
},
  "bbox": [],
  "geometry": {"coordinates":[0.583333,40.716667],"type":"Point"}
}