{
  "id": 7384693,
  "type": "Feature",
  "properties": {
    "tgn:hierarchy":[
        "tgn:7384693",
        "tgn:7005581",
        "tgn:1000001",
        "tgn:7005560",
        "tgn:7029392"
    ],
    "tgn:id":7384693,
    "tgn:name":"Rancho Ojitos",
    "tgn:placetype":[
        "aat:300000241"
    ]
},
  "bbox": [],
  "geometry": {"coordinates":[-108.533333,30.766667],"type":"Point"}
}