<<<<<<< HEAD
{
  "id": 7177522,
  "type": "Feature",
  "properties": {
    "tgn:hierarchy":[
        "tgn:7177522",
        "tgn:1000003",
        "tgn:7003676",
        "tgn:7000084",
        "tgn:7029392"
    ],
    "tgn:id":7177522,
    "tgn:name":"Hanstedter Vier",
    "tgn:placetype":[
        "aat:300008863"
    ]
},
  "bbox": [],
  "geometry": {"coordinates":[10.35,53.066667],"type":"Point"}
}
=======
{"geometry":{"type":"Point","coordinates":[10.350000,53.066667]},"type":"Feature","properties":{"hierarchy":["tgn:7177522","tgn:1000003","tgn:7003676","tgn:7000084","tgn:7029392"],"placetype":["aat:300008863"],"id":7177522,"name:xx":"Hanstedter Vier"}}
>>>>>>> 03f74aca74312dbeaf24d7e61306dd6a786dc3d0
