{
  "id": 2407671,
  "type": "Feature",
  "properties": {
    "tgn:hierarchy":[
        "tgn:2407671",
        "tgn:1000001",
        "tgn:7012149",
        "tgn:7007826",
        "tgn:7029392"
    ],
    "tgn:id":2407671,
    "tgn:name":"Hurley Hollow",
    "tgn:placetype":[
        "aat:300008761"
    ]
},
  "bbox": [],
  "geometry": {"coordinates":[-98.4333,31.05],"type":"Point"}
}