{
  "id": 7100027,
  "type": "Feature",
  "properties": {
    "tgn:hierarchy":[
        "tgn:7100027",
        "tgn:1000003",
        "tgn:7003677",
        "tgn:7000084",
        "tgn:7029392"
    ],
    "tgn:id":7100027,
    "tgn:name":"Bahnhof Solingen-Wald",
    "tgn:placetype":[
        "aat:300007783"
    ]
},
  "bbox": [],
  "geometry": {"coordinates":[7.033333,51.183333],"type":"Point"}
}