{
  "id": 2310988,
  "type": "Feature",
  "properties": {
    "tgn:hierarchy":[
        "tgn:2310988",
        "tgn:1000001",
        "tgn:7012149",
        "tgn:2001616",
        "tgn:7007706",
        "tgn:7029392"
    ],
    "tgn:id":2310988,
    "tgn:name":"Eden",
    "tgn:placetype":[
        "aat:300008347"
    ]
},
  "bbox": [],
  "geometry": {"coordinates":[-81.75,39.15],"type":"Point"}
}