{
  "id": 7258676,
  "type": "Feature",
  "properties": {
    "tgn:concordances":{
        "gn:id":"2758496"
    },
    "tgn:hierarchy":[
        "tgn:7258676",
        "tgn:1000003",
        "tgn:7003632",
        "tgn:7016845",
        "tgn:7029392"
    ],
    "tgn:id":7258676,
    "tgn:name:nl":"Bovenkerk",
    "tgn:placetype":[
        "aat:300008347"
    ]
},
  "bbox": [],
  "geometry": {"coordinates":[4.783333,51.983333],"type":"Point"}
}