{
  "id": 1014339,
  "type": "Feature",
  "properties": {
    "tgn:hierarchy":[
        "tgn:1014339",
        "tgn:7005685",
        "tgn:7005807",
        "tgn:1000001",
        "tgn:7005801",
        "tgn:7029392"
    ],
    "tgn:id":1014339,
    "tgn:name":"Trout River",
    "tgn:placetype":[
        "aat:300008347"
    ]
},
  "bbox": [],
  "geometry": {"coordinates":[-58.1333,49.4833],"type":"Point"}
}