{
  "id": 7116901,
  "type": "Feature",
  "properties": {
    "tgn:hierarchy":[
        "tgn:7116901",
        "tgn:7003669",
        "tgn:1000003",
        "tgn:7000084",
        "tgn:7029392"
    ],
    "tgn:id":7116901,
    "tgn:name":"Ort",
    "tgn:placetype":[
        "aat:300008347"
    ]
},
  "bbox": [],
  "geometry": {"coordinates":[13.216667,48.35],"type":"Point"}
}