{
  "id": 2636450,
  "type": "Feature",
  "properties": {
    "tgn:hierarchy":[
        "tgn:2636450",
        "tgn:1000001",
        "tgn:7012149",
        "tgn:7007157",
        "tgn:1002857",
        "tgn:7029392"
    ],
    "tgn:id":2636450,
    "tgn:name":"Sagamore Canyon",
    "tgn:placetype":[
        "aat:300008761"
    ]
},
  "bbox": [],
  "geometry": {"coordinates":[-115.2833,35.25],"type":"Point"}
}