{
  "id": 2455453,
  "type": "Feature",
  "properties": {
    "tgn:hierarchy":[
        "tgn:2455453",
        "tgn:7002659",
        "tgn:1000001",
        "tgn:7012149",
        "tgn:2000063",
        "tgn:7029392"
    ],
    "tgn:id":2455453,
    "tgn:name":"Little Frog Ague Creek",
    "tgn:placetype":[
        "aat:300008706"
    ]
},
  "bbox": [],
  "geometry": {"coordinates":[-87.2167,33.7667],"type":"Point"}
}