{
  "id": 2497023,
  "type": "Feature",
  "properties": {
    "tgn:hierarchy":[
        "tgn:2497023",
        "tgn:1000001",
        "tgn:7016172",
        "tgn:7012149",
        "tgn:2000164",
        "tgn:7029392"
    ],
    "tgn:id":2497023,
    "tgn:name":"Maumelle Pinnacles",
    "tgn:placetype":[
        "aat:300266640"
    ]
},
  "bbox": [],
  "geometry": {"coordinates":[-92.5167,34.8333],"type":"Point"}
}