<<<<<<< HEAD
{
  "id": 7367377,
  "type": "Feature",
  "properties": {
    "tgn:hierarchy":[
        "tgn:7367377",
        "tgn:7005586",
        "tgn:1000001",
        "tgn:7005560",
        "tgn:7029392"
    ],
    "tgn:id":7367377,
    "tgn:name":"El Tule",
    "tgn:placetype":[
        "aat:300006191"
    ]
},
  "bbox": [],
  "geometry": {"coordinates":[-102.416667,20.716667],"type":"Point"}
}
=======
{"geometry":{"type":"Point","coordinates":[-102.416667,20.716667]},"type":"Feature","properties":{"hierarchy":["tgn:7367377","tgn:7005586","tgn:1000001","tgn:7005560","tgn:7029392"],"placetype":["aat:300006191"],"id":7367377,"name:xx":"El Tule"}}
>>>>>>> 03f74aca74312dbeaf24d7e61306dd6a786dc3d0
