{
  "id": 2286955,
  "type": "Feature",
  "properties": {
    "tgn:hierarchy":[
        "tgn:2286955",
        "tgn:1000001",
        "tgn:7012149",
        "tgn:1002785",
        "tgn:7007920",
        "tgn:7029392"
    ],
    "tgn:id":2286955,
    "tgn:name":"Dick Creek",
    "tgn:placetype":[
        "aat:300008706"
    ]
},
  "bbox": [],
  "geometry": {"coordinates":[-121.75,46.9333],"type":"Point"}
}