{
  "id": 7047660,
  "type": "Feature",
  "properties": {
    "tgn:hierarchy":[
        "tgn:7047660",
        "tgn:7005023",
        "tgn:1000003",
        "tgn:7003237",
        "tgn:1000080",
        "tgn:7029392"
    ],
    "tgn:id":7047660,
    "tgn:name":"Cisano Bergamasco",
    "tgn:placetype":[
        "aat:300008347"
    ]
},
  "bbox": [],
  "geometry": {"coordinates":[9.483333,45.733333],"type":"Point"}
}