{
  "id": 2579626,
  "type": "Feature",
  "properties": {
    "tgn:hierarchy":[
        "tgn:2579626",
        "tgn:1000001",
        "tgn:2001417",
        "tgn:7012149",
        "tgn:7007526",
        "tgn:7029392"
    ],
    "tgn:id":2579626,
    "tgn:name":"Pickhandle Gulch",
    "tgn:placetype":[
        "aat:300008761"
    ]
},
  "bbox": [],
  "geometry": {"coordinates":[-118.0833,38.1333],"type":"Point"}
}