{
  "id": 2609165,
  "type": "Feature",
  "properties": {
    "tgn:hierarchy":[
        "tgn:2609165",
        "tgn:1000001",
        "tgn:7012149",
        "tgn:1002315",
        "tgn:7007826",
        "tgn:7029392"
    ],
    "tgn:id":2609165,
    "tgn:name":"Rawhide Creek",
    "tgn:placetype":[
        "aat:300008706"
    ]
},
  "bbox": [],
  "geometry": {"coordinates":[-96.8333,32.95],"type":"Point"}
}