{
  "id": 7008675,
  "type": "Feature",
  "properties": {
    "tgn:hierarchy":[
        "tgn:7008675",
        "tgn:1000003",
        "tgn:7002883",
        "tgn:1000070",
        "tgn:7029392"
    ],
    "tgn:id":7008675,
    "tgn:name":"Aulnay-sous-Bois",
    "tgn:placetype":[
        "aat:300008347",
        "aat:300387330",
        "aat:300008375"
    ]
},
  "bbox": [],
  "geometry": {"coordinates":[2.5167,48.95],"type":"Point"}
}