{
  "id": 2327907,
  "type": "Feature",
  "properties": {
    "tgn:hierarchy":[
        "tgn:2327907",
        "tgn:1000001",
        "tgn:2000260",
        "tgn:7012149",
        "tgn:7007240",
        "tgn:7029392"
    ],
    "tgn:id":2327907,
    "tgn:name":"Fish Lake",
    "tgn:placetype":[
        "aat:300008680"
    ]
},
  "bbox": [],
  "geometry": {"coordinates":[-85.0667,30.2667],"type":"Point"}
}