{
  "id": 2479826,
  "type": "Feature",
  "properties": {
    "tgn:hierarchy":[
        "tgn:2479826",
        "tgn:1000001",
        "tgn:7012149",
        "tgn:2002373",
        "tgn:7007923",
        "tgn:7029392"
    ],
    "tgn:id":2479826,
    "tgn:name":"Lake Creek",
    "tgn:placetype":[
        "aat:300008706"
    ]
},
  "bbox": [],
  "geometry": {"coordinates":[-107.7167,43.5833],"type":"Point"}
}