{
  "id": 2337503,
  "type": "Feature",
  "properties": {
    "tgn:hierarchy":[
        "tgn:2337503",
        "tgn:1000001",
        "tgn:2001424",
        "tgn:7012149",
        "tgn:7007564",
        "tgn:7029392"
    ],
    "tgn:id":2337503,
    "tgn:name":"Fowler River",
    "tgn:placetype":[
        "aat:300008707"
    ]
},
  "bbox": [],
  "geometry": {"coordinates":[-71.8167,43.6333],"type":"Point"}
}