{
  "id": 2518662,
  "type": "Feature",
  "properties": {
    "tgn:hierarchy":[
        "tgn:2518662",
        "tgn:1000001",
        "tgn:2000324",
        "tgn:7012149",
        "tgn:7007248",
        "tgn:7029392"
    ],
    "tgn:id":2518662,
    "tgn:name":"Mitchell Lake",
    "tgn:placetype":[
        "aat:300006191"
    ]
},
  "bbox": [],
  "geometry": {"coordinates":[-84.4167,34.0167],"type":"Point"}
}