<<<<<<< HEAD
{
  "id": 2157251,
  "type": "Feature",
  "properties": {
    "tgn:hierarchy":[
        "tgn:2157251",
        "tgn:1000001",
        "tgn:2000470",
        "tgn:7012149",
        "tgn:7007250",
        "tgn:7029392"
    ],
    "tgn:id":2157251,
    "tgn:name":"Beaver Creek",
    "tgn:placetype":[
        "aat:300008706"
    ]
},
  "bbox": [],
  "geometry": {"coordinates":[-114.95,44.5],"type":"Point"}
}
=======
{"geometry":{"type":"Point","coordinates":[-114.950000,44.500000]},"type":"Feature","properties":{"hierarchy":["tgn:2157251","tgn:1000001","tgn:2000470","tgn:7012149","tgn:7007250","tgn:7029392"],"placetype":["aat:300008706"],"id":2157251,"name:xx":"Beaver Creek"}}
>>>>>>> 03f74aca74312dbeaf24d7e61306dd6a786dc3d0
