{
  "id": 2536282,
  "type": "Feature",
  "properties": {
    "tgn:hierarchy":[
        "tgn:2536282",
        "tgn:1000001",
        "tgn:7012149",
        "tgn:2000656",
        "tgn:7007253",
        "tgn:7029392"
    ],
    "tgn:id":2536282,
    "tgn:name":"Navan",
    "tgn:placetype":[
        "aat:300008347"
    ]
},
  "bbox": [],
  "geometry": {"coordinates":[-92.05,43.0833],"type":"Point"}
}