{
  "id": 2267217,
  "type": "Feature",
  "properties": {
    "tgn:hierarchy":[
        "tgn:2267217",
        "tgn:1000001",
        "tgn:2001414",
        "tgn:7012149",
        "tgn:7007526",
        "tgn:7029392"
    ],
    "tgn:id":2267217,
    "tgn:name":"Cricket Spring",
    "tgn:placetype":[
        "aat:300008697"
    ]
},
  "bbox": [],
  "geometry": {"coordinates":[-118.35,41.3667],"type":"Point"}
}