<<<<<<< HEAD
{
  "id": 7359447,
  "type": "Feature",
  "properties": {
    "tgn:hierarchy":[
        "tgn:7359447",
        "tgn:7005586",
        "tgn:1000001",
        "tgn:7005560",
        "tgn:7029392"
    ],
    "tgn:id":7359447,
    "tgn:name":"Cuale",
    "tgn:placetype":[
        "aat:300008347"
    ]
},
  "bbox": [],
  "geometry": {"coordinates":[-105.016667,20.45],"type":"Point"}
}
=======
{"geometry":{"type":"Point","coordinates":[-105.016667,20.450000]},"type":"Feature","properties":{"hierarchy":["tgn:7359447","tgn:7005586","tgn:1000001","tgn:7005560","tgn:7029392"],"placetype":["aat:300008347"],"id":7359447,"name:xx":"Cuale"}}
>>>>>>> 03f74aca74312dbeaf24d7e61306dd6a786dc3d0
