{
  "id": 2342203,
  "type": "Feature",
  "properties": {
    "tgn:hierarchy":[
        "tgn:2342203",
        "tgn:1000001",
        "tgn:2002106",
        "tgn:7012149",
        "tgn:7007827",
        "tgn:7029392"
    ],
    "tgn:id":2342203,
    "tgn:name":"Fuit",
    "tgn:placetype":[
        "aat:300008347"
    ]
},
  "bbox": [],
  "geometry": {"coordinates":[-112.0833,41.1333],"type":"Point"}
}