{
  "id": 2196406,
  "type": "Feature",
  "properties": {
    "tgn:hierarchy":[
        "tgn:2196406",
        "tgn:1000001",
        "tgn:7012149",
        "tgn:2002093",
        "tgn:7007826",
        "tgn:7029392"
    ],
    "tgn:id":2196406,
    "tgn:name":"Bronc Tank",
    "tgn:placetype":[
        "aat:300006191"
    ]
},
  "bbox": [],
  "geometry": {"coordinates":[-99.2167,33.9833],"type":"Point"}
}