<<<<<<< HEAD
{
  "id": 2330217,
  "type": "Feature",
  "properties": {
    "tgn:hierarchy":[
        "tgn:2330217",
        "tgn:2001423",
        "tgn:1000001",
        "tgn:7012149",
        "tgn:7007564",
        "tgn:7029392"
    ],
    "tgn:id":2330217,
    "tgn:name":"Flanders Brook",
    "tgn:placetype":[
        "aat:300008699"
    ]
},
  "bbox": [],
  "geometry": {"coordinates":[-71.0333,43.7667],"type":"Point"}
}
=======
{"geometry":{"type":"Point","coordinates":[-71.033300,43.766700]},"type":"Feature","properties":{"hierarchy":["tgn:2330217","tgn:2001423","tgn:1000001","tgn:7012149","tgn:7007564","tgn:7029392"],"placetype":["aat:300008699"],"id":2330217,"name:xx":"Flanders Brook"}}
>>>>>>> 03f74aca74312dbeaf24d7e61306dd6a786dc3d0
