{
  "id": 2223628,
  "type": "Feature",
  "properties": {
    "tgn:hierarchy":[
        "tgn:2223628",
        "tgn:1000001",
        "tgn:2001745",
        "tgn:7012149",
        "tgn:7007712",
        "tgn:7029392"
    ],
    "tgn:id":2223628,
    "tgn:name":"Carter Creek",
    "tgn:placetype":[
        "aat:300008706"
    ]
},
  "bbox": [],
  "geometry": {"coordinates":[-79.75,34.0833],"type":"Point"}
}