{
  "id": 7258204,
  "type": "Feature",
  "properties": {
    "tgn:hierarchy":[
        "tgn:7258204",
        "tgn:7003457",
        "tgn:1000003",
        "tgn:1000063",
        "tgn:7018236",
        "tgn:7029392"
    ],
    "tgn:id":7258204,
    "tgn:name":"Zande",
    "tgn:placetype":[
        "aat:300008347"
    ]
},
  "bbox": [],
  "geometry": {"coordinates":[3.55,51.066667],"type":"Point"}
}