{
  "id": 2138116,
  "type": "Feature",
  "properties": {
    "tgn:hierarchy":[
        "tgn:2138116",
        "tgn:1000001",
        "tgn:7012149",
        "tgn:7007157",
        "tgn:1003046",
        "tgn:7029392"
    ],
    "tgn:id":2138116,
    "tgn:name":"Arroz",
    "tgn:placetype":[
        "aat:300008347"
    ]
},
  "bbox": [],
  "geometry": {"coordinates":[-121.9667,38.6167],"type":"Point"}
}