{
  "id": 1048672,
  "type": "Feature",
  "properties": {
    "tgn:hierarchy":[
        "tgn:1048672",
        "tgn:7003652",
        "tgn:1000003",
        "tgn:1000088",
        "tgn:7029392"
    ],
    "tgn:id":1048672,
    "tgn:name":"Nedstrand",
    "tgn:placetype":[
        "aat:300008347"
    ]
},
  "bbox": [],
  "geometry": {"coordinates":[5.8833,59.35],"type":"Point"}
}