{
  "id": 7561344,
  "type": "Feature",
  "properties": {
    "tgn:hierarchy":[
        "tgn:7561344",
        "tgn:1000004",
        "tgn:7000198",
        "tgn:7016722",
        "tgn:7029392"
    ],
    "tgn:id":7561344,
    "tgn:name:en":"Matehna",
    "tgn:placetype":[
        "aat:300008347"
    ]
},
  "bbox": [],
  "geometry": {"coordinates":[79.412154,27.157786],"type":"Point"}
}