{
  "id": 2255621,
  "type": "Feature",
  "properties": {
    "tgn:hierarchy":[
        "tgn:2255621",
        "tgn:1000001",
        "tgn:7012149",
        "tgn:2002270",
        "tgn:7013961",
        "tgn:7029392"
    ],
    "tgn:id":2255621,
    "tgn:name":"Copen Branch",
    "tgn:placetype":[
        "aat:300008699"
    ]
},
  "bbox": [],
  "geometry": {"coordinates":[-81.5833,38.4333],"type":"Point"}
}