{
  "id": 7133193,
  "type": "Feature",
  "properties": {
    "tgn:hierarchy":[
        "tgn:7133193",
        "tgn:1000003",
        "tgn:7003676",
        "tgn:7000084",
        "tgn:7029392"
    ],
    "tgn:id":7133193,
    "tgn:name":"M\u00fchlenbach",
    "tgn:placetype":[
        "aat:300008699"
    ]
},
  "bbox": [],
  "geometry": {"coordinates":[8.166667,52.383333],"type":"Point"}
}