{
  "id": 1102564,
  "type": "Feature",
  "properties": {
    "tgn:hierarchy":[
        "tgn:1102564",
        "tgn:7005735",
        "tgn:7005685",
        "tgn:1000001",
        "tgn:7013409",
        "tgn:7029392"
    ],
    "tgn:id":1102564,
    "tgn:name":"Goldstream Provincial Park",
    "tgn:placetype":[
        "aat:300008195"
    ]
},
  "bbox": [],
  "geometry": {"coordinates":[-123.55,48.4833],"type":"Point"}
}