{
  "id": 2311357,
  "type": "Feature",
  "properties": {
    "tgn:hierarchy":[
        "tgn:2311357",
        "tgn:1000001",
        "tgn:1002934",
        "tgn:7012149",
        "tgn:7007565",
        "tgn:7029392"
    ],
    "tgn:id":2311357,
    "tgn:name":"Edison Pond",
    "tgn:placetype":[
        "aat:300008680"
    ]
},
  "bbox": [],
  "geometry": {"coordinates":[-74.55,41.05],"type":"Point"}
}