{
  "id": 7469107,
  "type": "Feature",
  "properties": {
    "tgn:hierarchy":[
        "tgn:7469107",
        "tgn:1000004",
        "tgn:1000454",
        "tgn:1000141",
        "tgn:7029392"
    ],
    "tgn:id":7469107,
    "tgn:name":"Zhongxinlun",
    "tgn:placetype":[
        "aat:300008347"
    ]
},
  "bbox": [],
  "geometry": {"coordinates":[121.7825,24.948056],"type":"Point"}
}