{
  "id": 2553803,
  "type": "Feature",
  "properties": {
    "tgn:hierarchy":[
        "tgn:2553803",
        "tgn:1000001",
        "tgn:7012149",
        "tgn:2001886",
        "tgn:7007825",
        "tgn:7029392"
    ],
    "tgn:id":2553803,
    "tgn:name":"Oak Hill",
    "tgn:placetype":[
        "aat:300008347"
    ]
},
  "bbox": [],
  "geometry": {"coordinates":[-87.2667,35.15],"type":"Point"}
}