{
  "id": 7331507,
  "type": "Feature",
  "properties": {
    "tgn:hierarchy":[
        "tgn:7331507",
        "tgn:7008911",
        "tgn:1000003",
        "tgn:7002763",
        "tgn:1000095",
        "tgn:7029392"
    ],
    "tgn:id":7331507,
    "tgn:name":"La Portilla",
    "tgn:placetype":[
        "aat:300008347"
    ]
},
  "bbox": [],
  "geometry": {"coordinates":[-4.75,43.416667],"type":"Point"}
}