{
  "id": 1074618,
  "type": "Feature",
  "properties": {
    "tgn:hierarchy":[
        "tgn:1074618",
        "tgn:1000004",
        "tgn:7000198",
        "tgn:1001977",
        "tgn:7029392"
    ],
    "tgn:id":1074618,
    "tgn:name:en":"Baladbandh",
    "tgn:placetype":[
        "aat:300008347"
    ]
},
  "bbox": [],
  "geometry": {"coordinates":[88.109722,22.868611],"type":"Point"}
}