{
  "id": 2280616,
  "type": "Feature",
  "properties": {
    "tgn:hierarchy":[
        "tgn:2280616",
        "tgn:1000001",
        "tgn:7006451",
        "tgn:7012149",
        "tgn:2000103",
        "tgn:7029392"
    ],
    "tgn:id":2280616,
    "tgn:name":"Deep Canyon",
    "tgn:placetype":[
        "aat:300008761"
    ]
},
  "bbox": [],
  "geometry": {"coordinates":[-112.9833,34.9167],"type":"Point"}
}