<<<<<<< HEAD
{
  "id": 7472177,
  "type": "Feature",
  "properties": {
    "tgn:hierarchy":[
        "tgn:7472177",
        "tgn:1000004",
        "tgn:7467799",
        "tgn:1000141",
        "tgn:7029392"
    ],
    "tgn:id":7472177,
    "tgn:name":"Xiangsiliao",
    "tgn:placetype":[
        "aat:300008347"
    ]
},
  "bbox": [],
  "geometry": {"coordinates":[120.42587,23.933828],"type":"Point"}
}
=======
{"geometry":{"type":"Point","coordinates":[120.425870,23.933828]},"type":"Feature","properties":{"hierarchy":["tgn:7472177","tgn:1000004","tgn:7467799","tgn:1000141","tgn:7029392"],"placetype":["aat:300008347"],"id":7472177,"name:xx":"Xiangsiliao"}}
>>>>>>> 03f74aca74312dbeaf24d7e61306dd6a786dc3d0
