{
  "id": 7164925,
  "type": "Feature",
  "properties": {
    "tgn:hierarchy":[
        "tgn:7164925",
        "tgn:7003669",
        "tgn:1000003",
        "tgn:7000084",
        "tgn:7029392"
    ],
    "tgn:id":7164925,
    "tgn:name":"Illach",
    "tgn:placetype":[
        "aat:300008347"
    ]
},
  "bbox": [],
  "geometry": {"coordinates":[10.833333,47.716667],"type":"Point"}
}