{
  "id": 7326681,
  "type": "Feature",
  "properties": {
    "tgn:hierarchy":[
        "tgn:7326681",
        "tgn:7002758",
        "tgn:7002817",
        "tgn:1000003",
        "tgn:1000095",
        "tgn:7029392"
    ],
    "tgn:id":7326681,
    "tgn:name":"Estaci\u00f3n Pe\u00f1as Blancas",
    "tgn:placetype":[
        "aat:300007783"
    ]
},
  "bbox": [],
  "geometry": {"coordinates":[-5.083333,38.333333],"type":"Point"}
}