{
  "id": 7496790,
  "type": "Feature",
  "properties": {
    "tgn:hierarchy":[
        "tgn:7496790",
        "tgn:1000004",
        "tgn:1000454",
        "tgn:1000141",
        "tgn:7029392"
    ],
    "tgn:id":7496790,
    "tgn:name":"Yihao Qiao",
    "tgn:placetype":[
        "aat:300007836"
    ]
},
  "bbox": [],
  "geometry": {"coordinates":[121.429781,25.110988],"type":"Point"}
}