{
  "id": 2117595,
  "type": "Feature",
  "properties": {
    "tgn:hierarchy":[
        "tgn:2117595",
        "tgn:1000001",
        "tgn:7012149",
        "tgn:2002287",
        "tgn:7013961",
        "tgn:7029392"
    ],
    "tgn:id":2117595,
    "tgn:name":"Brownsburg",
    "tgn:placetype":[
        "aat:300008347",
        "aat:300387210"
    ]
},
  "bbox": [],
  "geometry": {"coordinates":[-80.0667,38.2667],"type":"Point"}
}