{
  "id": 2509629,
  "type": "Feature",
  "properties": {
    "tgn:hierarchy":[
        "tgn:2509629",
        "tgn:1000001",
        "tgn:7012149",
        "tgn:2000964",
        "tgn:7007520",
        "tgn:7029392"
    ],
    "tgn:id":2509629,
    "tgn:name":"Middle Grounds Island",
    "tgn:placetype":[
        "aat:300008791"
    ]
},
  "bbox": [],
  "geometry": {"coordinates":[-83.4167,43.8167],"type":"Point"}
}