<<<<<<< HEAD
{
  "id": 7474386,
  "type": "Feature",
  "properties": {
    "tgn:hierarchy":[
        "tgn:7474386",
        "tgn:1000004",
        "tgn:1000454",
        "tgn:1000141",
        "tgn:7029392"
    ],
    "tgn:id":7474386,
    "tgn:name":"Yuguiling",
    "tgn:placetype":[
        "aat:300008347"
    ]
},
  "bbox": [],
  "geometry": {"coordinates":[121.717653,24.994663],"type":"Point"}
}
=======
{"geometry":{"type":"Point","coordinates":[121.717653,24.994663]},"type":"Feature","properties":{"hierarchy":["tgn:7474386","tgn:1000004","tgn:1000454","tgn:1000141","tgn:7029392"],"placetype":["aat:300008347"],"id":7474386,"name:xx":"Yuguiling"}}
>>>>>>> 03f74aca74312dbeaf24d7e61306dd6a786dc3d0
