{
  "id": 7474386,
  "type": "Feature",
  "properties": {
    "tgn:hierarchy":[
        "tgn:7474386",
        "tgn:1000004",
        "tgn:1000454",
        "tgn:1000141",
        "tgn:7029392"
    ],
    "tgn:id":7474386,
    "tgn:name":"Yuguiling",
    "tgn:placetype":[
        "aat:300008347"
    ]
},
  "bbox": [],
  "geometry": {"coordinates":[121.717653,24.994663],"type":"Point"}
}