{
  "id": 2053355,
  "type": "Feature",
  "properties": {
    "tgn:hierarchy":[
        "tgn:2053355",
        "tgn:1000001",
        "tgn:7012149",
        "tgn:2000985",
        "tgn:7007520",
        "tgn:7029392"
    ],
    "tgn:id":2053355,
    "tgn:name":"South Branch",
    "tgn:placetype":[
        "aat:300008347"
    ]
},
  "bbox": [],
  "geometry": {"coordinates":[-83.8833,44.4667],"type":"Point"}
}