{
  "id": 7153564,
  "type": "Feature",
  "properties": {
    "tgn:hierarchy":[
        "tgn:7153564",
        "tgn:1000003",
        "tgn:7000094",
        "tgn:7000084",
        "tgn:7029392"
    ],
    "tgn:id":7153564,
    "tgn:name":"Ivenacker See",
    "tgn:placetype":[
        "aat:300008680"
    ]
},
  "bbox": [],
  "geometry": {"coordinates":[12.95,53.716667],"type":"Point"}
}