{
  "id": 7583180,
  "type": "Feature",
  "properties": {
    "tgn:hierarchy":[
        "tgn:7583180",
        "tgn:1000004",
        "tgn:1001871",
        "tgn:7000198",
        "tgn:7029392"
    ],
    "tgn:id":7583180,
    "tgn:name:en":"Har\u012bpur",
    "tgn:placetype":[
        "aat:300008347"
    ]
},
  "bbox": [],
  "geometry": {"coordinates":[76.834318,30.074202],"type":"Point"}
}