{
  "id": 2312374,
  "type": "Feature",
  "properties": {
    "tgn:hierarchy":[
        "tgn:2312374",
        "tgn:1000001",
        "tgn:7012149",
        "tgn:7007568",
        "tgn:7029392"
    ],
    "tgn:id":2312374,
    "tgn:name":"Eightmile Creek",
    "tgn:placetype":[
        "aat:300008706"
    ]
},
  "bbox": [],
  "geometry": {"coordinates":[-76.5333,43.3167],"type":"Point"}
}