<<<<<<< HEAD
{
  "id": 2331585,
  "type": "Feature",
  "properties": {
    "tgn:hierarchy":[
        "tgn:2331585",
        "tgn:1000001",
        "tgn:2001733",
        "tgn:7012149",
        "tgn:7007712",
        "tgn:7029392"
    ],
    "tgn:id":2331585,
    "tgn:name":"Flea Bite Creek",
    "tgn:placetype":[
        "aat:300008706"
    ]
},
  "bbox": [],
  "geometry": {"coordinates":[-80.7,33.6167],"type":"Point"}
}
=======
{"geometry":{"type":"Point","coordinates":[-80.700000,33.616700]},"type":"Feature","properties":{"hierarchy":["tgn:2331585","tgn:1000001","tgn:2001733","tgn:7012149","tgn:7007712","tgn:7029392"],"placetype":["aat:300008706"],"id":2331585,"name:xx":"Flea Bite Creek"}}
>>>>>>> 03f74aca74312dbeaf24d7e61306dd6a786dc3d0
