{
  "id": 7045474,
  "type": "Feature",
  "properties": {
    "tgn:hierarchy":[
        "tgn:7045474",
        "tgn:1003440",
        "tgn:1000003",
        "tgn:7003124",
        "tgn:1000080",
        "tgn:7029392"
    ],
    "tgn:id":7045474,
    "tgn:name":"Cornaiano",
    "tgn:placetype":[
        "aat:300008347"
    ]
},
  "bbox": [],
  "geometry": {"coordinates":[11.283333,46.466667],"type":"Point"}
}