{
  "id": 2309696,
  "type": "Feature",
  "properties": {
    "tgn:hierarchy":[
        "tgn:2309696",
        "tgn:1000001",
        "tgn:2001265",
        "tgn:7012149",
        "tgn:7007524",
        "tgn:7029392"
    ],
    "tgn:id":2309696,
    "tgn:name":"Easter Creek",
    "tgn:placetype":[
        "aat:300008706"
    ]
},
  "bbox": [],
  "geometry": {"coordinates":[-104.25,45.0333],"type":"Point"}
}