{
  "id": 2703205,
  "type": "Feature",
  "properties": {
    "tgn:hierarchy":[
        "tgn:2703205",
        "tgn:1000001",
        "tgn:1002289",
        "tgn:7012149",
        "tgn:7007240",
        "tgn:7029392"
    ],
    "tgn:id":2703205,
    "tgn:name":"Summerland Swamp",
    "tgn:placetype":[
        "aat:300008905"
    ]
},
  "bbox": [],
  "geometry": {"coordinates":[-81.35,26.3333],"type":"Point"}
}