{
  "id": 7312571,
  "type": "Feature",
  "properties": {
    "tgn:hierarchy":[
        "tgn:7312571",
        "tgn:1001768",
        "tgn:1000049",
        "tgn:1000002",
        "tgn:7029392"
    ],
    "tgn:id":7312571,
    "tgn:name":"La Mostaza",
    "tgn:placetype":[
        "aat:300387200"
    ]
},
  "bbox": [],
  "geometry": {"coordinates":[-70.683333,-32.433333],"type":"Point"}
}