{
  "id": 2600901,
  "type": "Feature",
  "properties": {
    "tgn:hierarchy":[
        "tgn:2600901",
        "tgn:2002131",
        "tgn:1000001",
        "tgn:7012149",
        "tgn:7007828",
        "tgn:7029392"
    ],
    "tgn:id":2600901,
    "tgn:name":"Pumpkin Hill",
    "tgn:placetype":[
        "aat:300008798"
    ]
},
  "bbox": [],
  "geometry": {"coordinates":[-72.0833,44.4167],"type":"Point"}
}