{
  "id": 2500204,
  "type": "Feature",
  "properties": {
    "tgn:hierarchy":[
        "tgn:2500204",
        "tgn:1000001",
        "tgn:7012149",
        "tgn:7007826",
        "tgn:7029392"
    ],
    "tgn:id":2500204,
    "tgn:name":"McCullum Creek",
    "tgn:placetype":[
        "aat:300008706"
    ]
},
  "bbox": [],
  "geometry": {"coordinates":[-101.2333,35.0167],"type":"Point"}
}