{
  "id": 2352953,
  "type": "Feature",
  "properties": {
    "tgn:hierarchy":[
        "tgn:2352953",
        "tgn:1000001",
        "tgn:7012149",
        "tgn:7007158",
        "tgn:2000253",
        "tgn:7029392"
    ],
    "tgn:id":2352953,
    "tgn:name":"Godding Dailey and Plumb Ditch",
    "tgn:placetype":[
        "aat:300006075"
    ]
},
  "bbox": [],
  "geometry": {"coordinates":[-105.0167,40.1167],"type":"Point"}
}