<<<<<<< HEAD
{
  "id": 2408676,
  "type": "Feature",
  "properties": {
    "tgn:hierarchy":[
        "tgn:2408676",
        "tgn:1000001",
        "tgn:7012149",
        "tgn:2000226",
        "tgn:7007158",
        "tgn:7029392"
    ],
    "tgn:id":2408676,
    "tgn:name":"Hyatt Hill",
    "tgn:placetype":[
        "aat:300008798"
    ]
},
  "bbox": [],
  "geometry": {"coordinates":[-105.35,40.5],"type":"Point"}
}
=======
{"geometry":{"type":"Point","coordinates":[-105.350000,40.500000]},"type":"Feature","properties":{"hierarchy":["tgn:2408676","tgn:1000001","tgn:7012149","tgn:2000226","tgn:7007158","tgn:7029392"],"placetype":["aat:300008798"],"id":2408676,"name:xx":"Hyatt Hill"}}
>>>>>>> 03f74aca74312dbeaf24d7e61306dd6a786dc3d0
