{
  "id": 1042627,
  "type": "Feature",
  "properties": {
    "tgn:hierarchy":[
        "tgn:1042627",
        "tgn:7003497",
        "tgn:7001201",
        "tgn:1000003",
        "tgn:1000078",
        "tgn:7029392"
    ],
    "tgn:id":1042627,
    "tgn:name":"Ballymakeery",
    "tgn:placetype":[
        "aat:300008347"
    ]
},
  "bbox": [],
  "geometry": {"coordinates":[-9.15,51.9167],"type":"Point"}
}