{
  "id": 7114462,
  "type": "Feature",
  "properties": {
    "tgn:hierarchy":[
        "tgn:7114462",
        "tgn:1000003",
        "tgn:7003685",
        "tgn:7000084",
        "tgn:7029392"
    ],
    "tgn:id":7114462,
    "tgn:name":"Rennersdorf",
    "tgn:placetype":[
        "aat:300008347"
    ]
},
  "bbox": [],
  "geometry": {"coordinates":[14.066667,51.066667],"type":"Point"}
}