{
  "id": 2079917,
  "type": "Feature",
  "properties": {
    "tgn:hierarchy":[
        "tgn:2079917",
        "tgn:1000001",
        "tgn:7012149",
        "tgn:1002917",
        "tgn:7007706",
        "tgn:7029392"
    ],
    "tgn:id":2079917,
    "tgn:name":"Hartville",
    "tgn:placetype":[
        "aat:300008347"
    ]
},
  "bbox": [],
  "geometry": {"coordinates":[-81.3167,40.95],"type":"Point"}
}