{
  "id": 1055702,
  "type": "Feature",
  "properties": {
    "tgn:hierarchy":[
        "tgn:1055702",
        "tgn:1000004",
        "tgn:1003379",
        "tgn:7018214",
        "tgn:7002435",
        "tgn:7029392"
    ],
    "tgn:id":1055702,
    "tgn:name":"Kotelnich",
    "tgn:placetype":[
        "aat:300008347"
    ]
},
  "bbox": [],
  "geometry": {"coordinates":[48.3333,58.1667],"type":"Point"}
}