{
  "id": 7332079,
  "type": "Feature",
  "properties": {
    "tgn:hierarchy":[
        "tgn:7332079",
        "tgn:7008911",
        "tgn:1000003",
        "tgn:7002763",
        "tgn:1000095",
        "tgn:7029392"
    ],
    "tgn:id":7332079,
    "tgn:name":"Labra",
    "tgn:placetype":[
        "aat:300008347"
    ]
},
  "bbox": [],
  "geometry": {"coordinates":[-5.05,43.366667],"type":"Point"}
}