<<<<<<< HEAD
{
  "id": 7375530,
  "type": "Feature",
  "properties": {
    "tgn:hierarchy":[
        "tgn:7375530",
        "tgn:1000001",
        "tgn:7005593",
        "tgn:7005560",
        "tgn:7029392"
    ],
    "tgn:id":7375530,
    "tgn:name":"Las Tepuzas",
    "tgn:placetype":[
        "aat:300008347"
    ]
},
  "bbox": [],
  "geometry": {"coordinates":[-100.366667,20.35],"type":"Point"}
}
=======
{"geometry":{"type":"Point","coordinates":[-100.366667,20.350000]},"type":"Feature","properties":{"hierarchy":["tgn:7375530","tgn:1000001","tgn:7005593","tgn:7005560","tgn:7029392"],"placetype":["aat:300008347"],"id":7375530,"name:xx":"Las Tepuzas"}}
>>>>>>> 03f74aca74312dbeaf24d7e61306dd6a786dc3d0
