{
  "id": 7031740,
  "type": "Feature",
  "properties": {
    "tgn:hierarchy":[
        "tgn:7031740",
        "tgn:7002758",
        "tgn:7002841",
        "tgn:1000003",
        "tgn:1000095",
        "tgn:7029392"
    ],
    "tgn:id":7031740,
    "tgn:name":"Castilleja de la Cuesta",
    "tgn:placetype":[
        "aat:300008347"
    ]
},
  "bbox": [],
  "geometry": {"coordinates":[-6.05,37.383333],"type":"Point"}
}