<<<<<<< HEAD
{
  "id": 2768128,
  "type": "Feature",
  "properties": {
    "tgn:hierarchy":[
        "tgn:2768128",
        "tgn:1000001",
        "tgn:7006451",
        "tgn:2000092",
        "tgn:7012149",
        "tgn:7029392"
    ],
    "tgn:id":2768128,
    "tgn:name":"Whites Butte",
    "tgn:placetype":[
        "aat:300008798"
    ]
},
  "bbox": [],
  "geometry": {"coordinates":[-112.2167,36.0833],"type":"Point"}
}
=======
{"geometry":{"type":"Point","coordinates":[-112.216700,36.083300]},"type":"Feature","properties":{"hierarchy":["tgn:2768128","tgn:1000001","tgn:7006451","tgn:2000092","tgn:7012149","tgn:7029392"],"placetype":["aat:300008798"],"id":2768128,"name:xx":"Whites Butte"}}
>>>>>>> 03f74aca74312dbeaf24d7e61306dd6a786dc3d0
