{
  "id": 2271563,
  "type": "Feature",
  "properties": {
    "tgn:hierarchy":[
        "tgn:2271563",
        "tgn:1000001",
        "tgn:7012149",
        "tgn:2000349",
        "tgn:7007248",
        "tgn:7029392"
    ],
    "tgn:id":2271563,
    "tgn:name":"Cumming Twin Lake Number Two",
    "tgn:placetype":[
        "aat:300006191"
    ]
},
  "bbox": [],
  "geometry": {"coordinates":[-84.1833,34.15],"type":"Point"}
}