{
  "id": 7195774,
  "type": "Feature",
  "properties": {
    "tgn:hierarchy":[
        "tgn:7195774",
        "tgn:1000003",
        "tgn:7003689",
        "tgn:7000084",
        "tgn:7029392"
    ],
    "tgn:id":7195774,
    "tgn:name":"Dorfstelle Huchelheim",
    "tgn:placetype":[
        "aat:300055621"
    ]
},
  "bbox": [],
  "geometry": {"coordinates":[10.383333,51.45],"type":"Point"}
}