{
  "id": 1091360,
  "type": "Feature",
  "properties": {
    "tgn:hierarchy":[
        "tgn:1091360",
        "tgn:7001242",
        "tgn:7593675",
        "tgn:1000179",
        "tgn:7029392"
    ],
    "tgn:id":1091360,
    "tgn:name":"Bou Izakarn",
    "tgn:placetype":[
        "aat:300008347"
    ]
},
  "bbox": [],
  "geometry": {"coordinates":[-9.7333,29.15],"type":"Point"}
}