{
  "id": 2191283,
  "type": "Feature",
  "properties": {
    "tgn:hierarchy":[
        "tgn:2191283",
        "tgn:1000001",
        "tgn:1002194",
        "tgn:7012149",
        "tgn:7007710",
        "tgn:7029392"
    ],
    "tgn:id":2191283,
    "tgn:name":"Brace Creek",
    "tgn:placetype":[
        "aat:300008706"
    ]
},
  "bbox": [],
  "geometry": {"coordinates":[-76.7667,41.8667],"type":"Point"}
}