{
  "id": 7049704,
  "type": "Feature",
  "properties": {
    "tgn:hierarchy":[
        "tgn:7049704",
        "tgn:1003506",
        "tgn:1000003",
        "tgn:7002993",
        "tgn:1000080",
        "tgn:7029392"
    ],
    "tgn:id":7049704,
    "tgn:name":"Cercivento",
    "tgn:placetype":[
        "aat:300008347"
    ]
},
  "bbox": [],
  "geometry": {"coordinates":[12.983333,48.533333],"type":"Point"}
}