<<<<<<< HEAD
{
  "id": 7483849,
  "type": "Feature",
  "properties": {
    "tgn:hierarchy":[
        "tgn:7483849",
        "tgn:1000004",
        "tgn:7001009",
        "tgn:1000141",
        "tgn:7029392"
    ],
    "tgn:id":7483849,
    "tgn:name":"Dianhouzhuang",
    "tgn:placetype":[
        "aat:300008347"
    ]
},
  "bbox": [],
  "geometry": {"coordinates":[120.687778,24.316111],"type":"Point"}
}
=======
{"geometry":{"type":"Point","coordinates":[120.687778,24.316111]},"type":"Feature","properties":{"hierarchy":["tgn:7483849","tgn:1000004","tgn:7001009","tgn:1000141","tgn:7029392"],"placetype":["aat:300008347"],"id":7483849,"name:xx":"Dianhouzhuang"}}
>>>>>>> 03f74aca74312dbeaf24d7e61306dd6a786dc3d0
