{
  "id": 2479246,
  "type": "Feature",
  "properties": {
    "tgn:hierarchy":[
        "tgn:2479246",
        "tgn:7002659",
        "tgn:1000001",
        "tgn:2000009",
        "tgn:7012149",
        "tgn:7029392"
    ],
    "tgn:id":2479246,
    "tgn:name":"Lagarde Number 2 Lake",
    "tgn:placetype":[
        "aat:300006191"
    ]
},
  "bbox": [],
  "geometry": {"coordinates":[-85.5333,33.95],"type":"Point"}
}