{
  "id": 2565653,
  "type": "Feature",
  "properties": {
    "tgn:hierarchy":[
        "tgn:2565653",
        "tgn:1000001",
        "tgn:7012149",
        "tgn:7007157",
        "tgn:7029392"
    ],
    "tgn:id":2565653,
    "tgn:name":"Pajaro, Mount",
    "tgn:placetype":[
        "aat:300008798"
    ]
},
  "bbox": [],
  "geometry": {"coordinates":[-121.6167,36.9167],"type":"Point"}
}