{
  "id": 2708975,
  "type": "Feature",
  "properties": {
    "tgn:hierarchy":[
        "tgn:2708975",
        "tgn:1000001",
        "tgn:7013368",
        "tgn:7012149",
        "tgn:7007709",
        "tgn:7029392"
    ],
    "tgn:id":2708975,
    "tgn:name":"T G Slimes Pond Number One",
    "tgn:placetype":[
        "aat:300006191"
    ]
},
  "bbox": [],
  "geometry": {"coordinates":[-76.7167,35.3333],"type":"Point"}
}