{
  "id": 1128923,
  "type": "Feature",
  "properties": {
    "tgn:hierarchy":[
        "tgn:1128923",
        "tgn:1001160",
        "tgn:7006477",
        "tgn:1000002",
        "tgn:7029392"
    ],
    "tgn:id":1128923,
    "tgn:name":"Quequ\u00e9n Salado, R\u00edo",
    "tgn:placetype":[
        "aat:300008707"
    ]
},
  "bbox": [],
  "geometry": {"coordinates":[-60.5167,-38.9333],"type":"Point"}
}