{
  "id": 7569894,
  "type": "Feature",
  "properties": {
    "tgn:hierarchy":[
        "tgn:7569894",
        "tgn:1000004",
        "tgn:7000198",
        "tgn:7031786",
        "tgn:7029392"
    ],
    "tgn:id":7569894,
    "tgn:name:en":"Kand\u0101khani",
    "tgn:placetype":[
        "aat:300008347"
    ]
},
  "bbox": [],
  "geometry": {"coordinates":[78.566652,29.935738],"type":"Point"}
}