{
  "id": 2118111,
  "type": "Feature",
  "properties": {
    "tgn:hierarchy":[
        "tgn:2118111",
        "tgn:1000001",
        "tgn:7012149",
        "tgn:2002296",
        "tgn:7013961",
        "tgn:7029392"
    ],
    "tgn:id":2118111,
    "tgn:name":"Elk",
    "tgn:placetype":[
        "aat:300008347",
        "aat:300387210"
    ]
},
  "bbox": [],
  "geometry": {"coordinates":[-79.5333,39.0167],"type":"Point"}
}