{
  "id": 7507392,
  "type": "Feature",
  "properties": {
    "tgn:hierarchy":[
        "tgn:7507392",
        "tgn:1009227",
        "tgn:1000226",
        "tgn:7018437",
        "tgn:1000006",
        "tgn:7029392"
    ],
    "tgn:id":7507392,
    "tgn:name:en":"Puke Karara",
    "tgn:placetype":[
        "aat:300008798"
    ]
},
  "bbox": [],
  "geometry": {"coordinates":[170.666667,-44.966667],"type":"Point"}
}