{
  "id": 2496681,
  "type": "Feature",
  "properties": {
    "tgn:hierarchy":[
        "tgn:2496681",
        "tgn:1000001",
        "tgn:2001799",
        "tgn:7012149",
        "tgn:7007713",
        "tgn:7029392"
    ],
    "tgn:id":2496681,
    "tgn:name":"Matter Lake",
    "tgn:placetype":[
        "aat:300008680"
    ]
},
  "bbox": [],
  "geometry": {"coordinates":[-99.1833,44.8833],"type":"Point"}
}