{
  "id": 1013465,
  "type": "Feature",
  "properties": {
    "tgn:hierarchy":[
        "tgn:1013465",
        "tgn:7005735",
        "tgn:7005685",
        "tgn:1000001",
        "tgn:7013409",
        "tgn:7029392"
    ],
    "tgn:id":1013465,
    "tgn:name":"Crofton",
    "tgn:placetype":[
        "aat:300008347"
    ]
},
  "bbox": [],
  "geometry": {"coordinates":[-123.65,48.8667],"type":"Point"}
}