{
  "id": 7508434,
  "type": "Feature",
  "properties": {
    "tgn:hierarchy":[
        "tgn:7508434",
        "tgn:7000508",
        "tgn:1008380",
        "tgn:1000226",
        "tgn:1000006",
        "tgn:7029392"
    ],
    "tgn:id":7508434,
    "tgn:name:en":"Pahurehure Inlet",
    "tgn:placetype":[
        "aat:300132316"
    ]
},
  "bbox": [],
  "geometry": {"coordinates":[174.866667,-37.05],"type":"Point"}
}