{
  "id": 2692475,
  "type": "Feature",
  "properties": {
    "tgn:hierarchy":[
        "tgn:2692475",
        "tgn:1000001",
        "tgn:2000466",
        "tgn:7012149",
        "tgn:7007250",
        "tgn:7029392"
    ],
    "tgn:id":2692475,
    "tgn:name":"Steamboat Hill",
    "tgn:placetype":[
        "aat:300008798"
    ]
},
  "bbox": [],
  "geometry": {"coordinates":[-111.6333,42.65],"type":"Point"}
}