{
  "id": 2172647,
  "type": "Feature",
  "properties": {
    "tgn:hierarchy":[
        "tgn:2172647",
        "tgn:1000001",
        "tgn:7012149",
        "tgn:2000410",
        "tgn:7007248",
        "tgn:7029392"
    ],
    "tgn:id":2172647,
    "tgn:name":"Billingsley Creek",
    "tgn:placetype":[
        "aat:300008706"
    ]
},
  "bbox": [],
  "geometry": {"coordinates":[-83.2333,34.9833],"type":"Point"}
}