{
  "id": 7273371,
  "type": "Feature",
  "properties": {
    "tgn:hierarchy":[
        "tgn:7273371",
        "tgn:1000003",
        "tgn:7006951",
        "tgn:7016845",
        "tgn:7029392"
    ],
    "tgn:id":7273371,
    "tgn:name:nl":"Westzanerpolder",
    "tgn:placetype":[
        "aat:300006163"
    ]
},
  "bbox": [],
  "geometry": {"coordinates":[4.766667,52.433333],"type":"Point"}
}