{
  "id": 7499219,
  "type": "Feature",
  "properties": {
    "tgn:hierarchy":[
        "tgn:7499219",
        "tgn:1000004",
        "tgn:7491221",
        "tgn:1000141",
        "tgn:7029392"
    ],
    "tgn:id":7499219,
    "tgn:name":"Bali Xi",
    "tgn:placetype":[
        "aat:300008699"
    ]
},
  "bbox": [],
  "geometry": {"coordinates":[121.247249,22.881563],"type":"Point"}
}