{
  "id": 7230949,
  "type": "Feature",
  "properties": {
    "tgn:hierarchy":[
        "tgn:7230949",
        "tgn:7002735",
        "tgn:7017076",
        "tgn:1000003",
        "tgn:1000074",
        "tgn:7029392"
    ],
    "tgn:id":7230949,
    "tgn:name":"Khan\u00edon R\u00e9ma",
    "tgn:placetype":[
        "aat:300008699"
    ]
},
  "bbox": [],
  "geometry": {"coordinates":[22.533333,36.866667],"type":"Point"}
}