<<<<<<< HEAD
{
  "id": 2255961,
  "type": "Feature",
  "properties": {
    "tgn:hierarchy":[
        "tgn:2255961",
        "tgn:1000001",
        "tgn:7006451",
        "tgn:2000093",
        "tgn:7012149",
        "tgn:7029392"
    ],
    "tgn:id":2255961,
    "tgn:name":"Copper Hill",
    "tgn:placetype":[
        "aat:300008347"
    ]
},
  "bbox": [],
  "geometry": {"coordinates":[-110.75,33.4167],"type":"Point"}
}
=======
{"geometry":{"type":"Point","coordinates":[-110.750000,33.416700]},"type":"Feature","properties":{"hierarchy":["tgn:2255961","tgn:1000001","tgn:7006451","tgn:2000093","tgn:7012149","tgn:7029392"],"placetype":["aat:300008347"],"id":2255961,"name:xx":"Copper Hill"}}
>>>>>>> 03f74aca74312dbeaf24d7e61306dd6a786dc3d0
