<<<<<<< HEAD
{
  "id": 2762030,
  "type": "Feature",
  "properties": {
    "tgn:hierarchy":[
        "tgn:2762030",
        "tgn:2000090",
        "tgn:1000001",
        "tgn:7006451",
        "tgn:7012149",
        "tgn:7029392"
    ],
    "tgn:id":2762030,
    "tgn:name":"West Section Thirty-five Tank",
    "tgn:placetype":[
        "aat:300006191"
    ]
},
  "bbox": [],
  "geometry": {"coordinates":[-109.15,33.95],"type":"Point"}
}
=======
{"geometry":{"type":"Point","coordinates":[-109.150000,33.950000]},"type":"Feature","properties":{"hierarchy":["tgn:2762030","tgn:2000090","tgn:1000001","tgn:7006451","tgn:7012149","tgn:7029392"],"placetype":["aat:300006191"],"id":2762030,"name:xx":"West Section Thirty-five Tank"}}
>>>>>>> 03f74aca74312dbeaf24d7e61306dd6a786dc3d0
