{
  "id": 7510569,
  "type": "Feature",
  "properties": {
    "tgn:hierarchy":[
        "tgn:7510569",
        "tgn:1008380",
        "tgn:7520093",
        "tgn:1000226",
        "tgn:1000006",
        "tgn:7029392"
    ],
    "tgn:id":7510569,
    "tgn:name:en":"Umutoi Creek",
    "tgn:placetype":[
        "aat:300008699"
    ]
},
  "bbox": [],
  "geometry": {"coordinates":[176.05,-39.95],"type":"Point"}
}