{
  "id": 7147572,
  "type": "Feature",
  "properties": {
    "tgn:hierarchy":[
        "tgn:7147572",
        "tgn:7003669",
        "tgn:1000003",
        "tgn:7000084",
        "tgn:7029392"
    ],
    "tgn:id":7147572,
    "tgn:name":"Kreuzstauden",
    "tgn:placetype":[
        "aat:300000206"
    ]
},
  "bbox": [],
  "geometry": {"coordinates":[11.866667,48.633333],"type":"Point"}
}