{
  "id": 7520348,
  "type": "Feature",
  "properties": {
    "tgn:hierarchy":[
        "tgn:7520348",
        "tgn:7001242",
        "tgn:7016833",
        "tgn:7000122",
        "tgn:7029392"
    ],
    "tgn:id":7520348,
    "tgn:name:en":"Man\u0101mat Ab\u016b Sir\u1e29\u0101n",
    "tgn:placetype":[
        "aat:300005926"
    ]
},
  "bbox": [],
  "geometry": {"coordinates":[32.916667,24.566667],"type":"Point"}
}