{
  "id": 7198927,
  "type": "Feature",
  "properties": {
    "tgn:hierarchy":[
        "tgn:7198927",
        "tgn:1000003",
        "tgn:7003677",
        "tgn:7000084",
        "tgn:7029392"
    ],
    "tgn:id":7198927,
    "tgn:name":"Eben\u00f6de",
    "tgn:placetype":[
        "aat:300008347"
    ]
},
  "bbox": [],
  "geometry": {"coordinates":[8.85,52.183333],"type":"Point"}
}