{
  "id": 7155029,
  "type": "Feature",
  "properties": {
    "tgn:hierarchy":[
        "tgn:7155029",
        "tgn:1000003",
        "tgn:7003688",
        "tgn:7000084",
        "tgn:7029392"
    ],
    "tgn:id":7155029,
    "tgn:name":"Kirchhorst",
    "tgn:placetype":[
        "aat:300000206"
    ]
},
  "bbox": [],
  "geometry": {"coordinates":[9.733333,54.416667],"type":"Point"}
}