{
  "id": 7563073,
  "type": "Feature",
  "properties": {
    "tgn:hierarchy":[
        "tgn:7563073",
        "tgn:1000004",
        "tgn:7000198",
        "tgn:7016722",
        "tgn:7029392"
    ],
    "tgn:id":7563073,
    "tgn:name:en":"\u016ancha",
    "tgn:placetype":[
        "aat:300008347"
    ]
},
  "bbox": [],
  "geometry": {"coordinates":[79.135994,26.316691],"type":"Point"}
}