{
  "id": 2341812,
  "type": "Feature",
  "properties": {
    "tgn:hierarchy":[
        "tgn:2341812",
        "tgn:1000001",
        "tgn:7012149",
        "tgn:2001544",
        "tgn:7007709",
        "tgn:7029392"
    ],
    "tgn:id":2341812,
    "tgn:name":"Frozen Creek",
    "tgn:placetype":[
        "aat:300008706"
    ]
},
  "bbox": [],
  "geometry": {"coordinates":[-82.8667,35.1167],"type":"Point"}
}