{
  "id": 7334850,
  "type": "Feature",
  "properties": {
    "tgn:hierarchy":[
        "tgn:7334850",
        "tgn:7002758",
        "tgn:1001316",
        "tgn:1000003",
        "tgn:1000095",
        "tgn:7029392"
    ],
    "tgn:id":7334850,
    "tgn:name":"Garc\u00edez-Jimena",
    "tgn:placetype":[
        "aat:300008347"
    ]
},
  "bbox": [],
  "geometry": {"coordinates":[-3.466667,37.916667],"type":"Point"}
}