{
  "id": 7045564,
  "type": "Feature",
  "properties": {
    "tgn:hierarchy":[
        "tgn:7045564",
        "tgn:7003007",
        "tgn:1000003",
        "tgn:7002997",
        "tgn:1000080",
        "tgn:7029392"
    ],
    "tgn:id":7045564,
    "tgn:name":"Contrada Ronchiel",
    "tgn:placetype":[
        "aat:300008347"
    ]
},
  "bbox": [],
  "geometry": {"coordinates":[11.166667,45.216667],"type":"Point"}
}