{
  "id": 2276911,
  "type": "Feature",
  "properties": {
    "tgn:hierarchy":[
        "tgn:2276911",
        "tgn:1000001",
        "tgn:7012149",
        "tgn:2002374",
        "tgn:7007923",
        "tgn:7029392"
    ],
    "tgn:id":2276911,
    "tgn:name":"Davis Branch",
    "tgn:placetype":[
        "aat:300008699"
    ]
},
  "bbox": [],
  "geometry": {"coordinates":[-106.25,43.5167],"type":"Point"}
}