{
  "id": 2718201,
  "type": "Feature",
  "properties": {
    "tgn:hierarchy":[
        "tgn:2718201",
        "tgn:1000001",
        "tgn:7012149",
        "tgn:2001274",
        "tgn:7007524",
        "tgn:7029392"
    ],
    "tgn:id":2718201,
    "tgn:name":"Thompson Creek",
    "tgn:placetype":[
        "aat:300008706"
    ]
},
  "bbox": [],
  "geometry": {"coordinates":[-113.6833,48.55],"type":"Point"}
}