{
  "id": 7516427,
  "type": "Feature",
  "properties": {
    "tgn:hierarchy":[
        "tgn:7516427",
        "tgn:7016670",
        "tgn:1008380",
        "tgn:1000226",
        "tgn:1000006",
        "tgn:7029392"
    ],
    "tgn:id":7516427,
    "tgn:name:en":"Ohuia Lagoon",
    "tgn:placetype":[
        "aat:300008679"
    ]
},
  "bbox": [],
  "geometry": {"coordinates":[177.483333,-39.05],"type":"Point"}
}