{
  "id": 7582942,
  "type": "Feature",
  "properties": {
    "tgn:hierarchy":[
        "tgn:7582942",
        "tgn:1000004",
        "tgn:7000198",
        "tgn:1001894",
        "tgn:7029392"
    ],
    "tgn:id":7582942,
    "tgn:name:en":"Gabh\u012briya Buzurg",
    "tgn:placetype":[
        "aat:300008347"
    ]
},
  "bbox": [],
  "geometry": {"coordinates":[78.375906,24.084094],"type":"Point"}
}