{
  "id": 7591081,
  "type": "Feature",
  "properties": {
    "tgn:hierarchy":[
        "tgn:7591081",
        "tgn:1000004",
        "tgn:7000198",
        "tgn:7000799",
        "tgn:7029392"
    ],
    "tgn:id":7591081,
    "tgn:name:en":"Kaj\u0101\u012ben de Kothe",
    "tgn:placetype":[
        "aat:300008347"
    ]
},
  "bbox": [],
  "geometry": {"coordinates":[74.901389,32.575],"type":"Point"}
}