{
  "id": 2068719,
  "type": "Feature",
  "properties": {
    "tgn:hierarchy":[
        "tgn:2068719",
        "tgn:1000001",
        "tgn:7012149",
        "tgn:1002681",
        "tgn:7007568",
        "tgn:7029392"
    ],
    "tgn:id":2068719,
    "tgn:name":"Crescent Beach",
    "tgn:placetype":[
        "aat:300008347"
    ]
},
  "bbox": [],
  "geometry": {"coordinates":[-77.65,43.2833],"type":"Point"}
}