<<<<<<< HEAD
{
  "id": 2407140,
  "type": "Feature",
  "properties": {
    "tgn:hierarchy":[
        "tgn:2407140",
        "tgn:7014651",
        "tgn:1000001",
        "tgn:7012149",
        "tgn:7007516",
        "tgn:7029392"
    ],
    "tgn:id":2407140,
    "tgn:name":"Hunters Harbor",
    "tgn:placetype":[
        "aat:300132316"
    ]
},
  "bbox": [],
  "geometry": {"coordinates":[-76.45,39.0833],"type":"Point"}
}
=======
{"geometry":{"type":"Point","coordinates":[-76.450000,39.083300]},"type":"Feature","properties":{"hierarchy":["tgn:2407140","tgn:7014651","tgn:1000001","tgn:7012149","tgn:7007516","tgn:7029392"],"placetype":["aat:300132316"],"id":2407140,"name:xx":"Hunters Harbor"}}
>>>>>>> 03f74aca74312dbeaf24d7e61306dd6a786dc3d0
