{
  "id": 7043414,
  "type": "Feature",
  "properties": {
    "tgn:hierarchy":[
        "tgn:7043414",
        "tgn:7003133",
        "tgn:1000003",
        "tgn:7008516",
        "tgn:1000080",
        "tgn:7029392"
    ],
    "tgn:id":7043414,
    "tgn:name":"Torre di Primaro",
    "tgn:placetype":[
        "aat:300004847"
    ]
},
  "bbox": [],
  "geometry": {"coordinates":[12.283333,44.583333],"type":"Point"}
}