{
  "id": 2300349,
  "type": "Feature",
  "properties": {
    "tgn:hierarchy":[
        "tgn:2300349",
        "tgn:1000001",
        "tgn:2001749",
        "tgn:7012149",
        "tgn:7007712",
        "tgn:7029392"
    ],
    "tgn:id":2300349,
    "tgn:name":"Dukes",
    "tgn:placetype":[
        "aat:300008347"
    ]
},
  "bbox": [],
  "geometry": {"coordinates":[-81.2333,32.8833],"type":"Point"}
}