{
  "id": 2225296,
  "type": "Feature",
  "properties": {
    "tgn:hierarchy":[
        "tgn:2225296",
        "tgn:7006450",
        "tgn:1000001",
        "tgn:7012149",
        "tgn:2000086",
        "tgn:7029392"
    ],
    "tgn:id":2225296,
    "tgn:name":"Castle Peak",
    "tgn:placetype":[
        "aat:300008798"
    ]
},
  "bbox": [],
  "geometry": {"coordinates":[-143.4333,61.5833],"type":"Point"}
}