{
  "id": 2256690,
  "type": "Feature",
  "properties": {
    "tgn:hierarchy":[
        "tgn:2256690",
        "tgn:1000001",
        "tgn:7012149",
        "tgn:2000227",
        "tgn:7007158",
        "tgn:7029392"
    ],
    "tgn:id":2256690,
    "tgn:name":"Cordova Tank",
    "tgn:placetype":[
        "aat:300006191"
    ]
},
  "bbox": [],
  "geometry": {"coordinates":[-104.45,37.6667],"type":"Point"}
}