{
  "id": 1133777,
  "type": "Feature",
  "properties": {
    "tgn:hierarchy":[
        "tgn:1133777",
        "tgn:1000001",
        "tgn:2001945",
        "tgn:7012149",
        "tgn:7007826",
        "tgn:7029392"
    ],
    "tgn:id":1133777,
    "tgn:name":"Maravillas Creek",
    "tgn:placetype":[
        "aat:300008706"
    ]
},
  "bbox": [],
  "geometry": {"coordinates":[-103.4667,30.2167],"type":"Point"}
}