<<<<<<< HEAD
{
  "id": 2159940,
  "type": "Feature",
  "properties": {
    "tgn:hierarchy":[
        "tgn:2159940",
        "tgn:1002300",
        "tgn:1000001",
        "tgn:7012149",
        "tgn:7007564",
        "tgn:7029392"
    ],
    "tgn:id":2159940,
    "tgn:name":"Beech Hill",
    "tgn:placetype":[
        "aat:300008798"
    ]
},
  "bbox": [],
  "geometry": {"coordinates":[-71.5833,44.2833],"type":"Point"}
}
=======
{"geometry":{"type":"Point","coordinates":[-71.583300,44.283300]},"type":"Feature","properties":{"hierarchy":["tgn:2159940","tgn:1002300","tgn:1000001","tgn:7012149","tgn:7007564","tgn:7029392"],"placetype":["aat:300008798"],"id":2159940,"name:xx":"Beech Hill"}}
>>>>>>> 03f74aca74312dbeaf24d7e61306dd6a786dc3d0
