<<<<<<< HEAD
{
  "id": 7473262,
  "type": "Feature",
  "properties": {
    "tgn:hierarchy":[
        "tgn:7473262",
        "tgn:1000004",
        "tgn:7492971",
        "tgn:1000141",
        "tgn:7029392"
    ],
    "tgn:id":7473262,
    "tgn:name":"Dianzikou",
    "tgn:placetype":[
        "aat:300008347"
    ]
},
  "bbox": [],
  "geometry": {"coordinates":[120.4638,22.5422],"type":"Point"}
}
=======
{"geometry":{"type":"Point","coordinates":[120.463800,22.542200]},"type":"Feature","properties":{"hierarchy":["tgn:7473262","tgn:1000004","tgn:7492971","tgn:1000141","tgn:7029392"],"placetype":["aat:300008347"],"id":7473262,"name:xx":"Dianzikou"}}
>>>>>>> 03f74aca74312dbeaf24d7e61306dd6a786dc3d0
