{
  "id": 2481353,
  "type": "Feature",
  "properties": {
    "tgn:hierarchy":[
        "tgn:2481353",
        "tgn:1000001",
        "tgn:7006451",
        "tgn:2000092",
        "tgn:7012149",
        "tgn:7029392"
    ],
    "tgn:id":2481353,
    "tgn:name":"Lambs Lake",
    "tgn:placetype":[
        "aat:300008680"
    ]
},
  "bbox": [],
  "geometry": {"coordinates":[-112.25,36.6833],"type":"Point"}
}