{
  "id": 7365669,
  "type": "Feature",
  "properties": {
    "tgn:hierarchy":[
        "tgn:7365669",
        "tgn:1000001",
        "tgn:7005599",
        "tgn:7005560",
        "tgn:7029392"
    ],
    "tgn:id":7365669,
    "tgn:name":"Encrucijada",
    "tgn:placetype":[
        "aat:300008347"
    ]
},
  "bbox": [],
  "geometry": {"coordinates":[-95.55,18.65],"type":"Point"}
}