<<<<<<< HEAD
{
  "id": 7355814,
  "type": "Feature",
  "properties": {
    "tgn:hierarchy":[
        "tgn:7355814",
        "tgn:1000001",
        "tgn:7005594",
        "tgn:7005560",
        "tgn:7029392"
    ],
    "tgn:id":7355814,
    "tgn:name":"Cerrito Colorado",
    "tgn:placetype":[
        "aat:300008347"
    ]
},
  "bbox": [],
  "geometry": {"coordinates":[-99.9,21.85],"type":"Point"}
}
=======
{"geometry":{"type":"Point","coordinates":[-99.900000,21.850000]},"type":"Feature","properties":{"hierarchy":["tgn:7355814","tgn:1000001","tgn:7005594","tgn:7005560","tgn:7029392"],"placetype":["aat:300008347"],"id":7355814,"name:xx":"Cerrito Colorado"}}
>>>>>>> 03f74aca74312dbeaf24d7e61306dd6a786dc3d0
