{
  "id": 2584278,
  "type": "Feature",
  "properties": {
    "tgn:hierarchy":[
        "tgn:2584278",
        "tgn:1000001",
        "tgn:7012149",
        "tgn:2000226",
        "tgn:7007158",
        "tgn:7029392"
    ],
    "tgn:id":2584278,
    "tgn:name":"Pinewood Lake",
    "tgn:placetype":[
        "aat:300006191"
    ]
},
  "bbox": [],
  "geometry": {"coordinates":[-105.2833,40.3667],"type":"Point"}
}