{
  "id": 2578442,
  "type": "Feature",
  "properties": {
    "tgn:hierarchy":[
        "tgn:2578442",
        "tgn:1000001",
        "tgn:7012149",
        "tgn:1002924",
        "tgn:7007568",
        "tgn:7029392"
    ],
    "tgn:id":2578442,
    "tgn:name":"Phelps Ledge",
    "tgn:placetype":[
        "aat:300132348"
    ]
},
  "bbox": [],
  "geometry": {"coordinates":[-71.8167,41.0667],"type":"Point"}
}