{
  "id": 7022492,
  "type": "Feature",
  "properties": {
    "tgn:hierarchy":[
        "tgn:7022492",
        "tgn:1000001",
        "tgn:7012149",
        "tgn:2001447",
        "tgn:7007566",
        "tgn:7029392"
    ],
    "tgn:id":7022492,
    "tgn:name":"Ysleta\u00f1o Canyon",
    "tgn:placetype":[
        "aat:300008761"
    ]
},
  "bbox": [],
  "geometry": {"coordinates":[-105.85,33.05],"type":"Point"}
}