<<<<<<< HEAD
{
  "id": 7022492,
  "type": "Feature",
  "properties": {
    "tgn:hierarchy":[
        "tgn:7022492",
        "tgn:1000001",
        "tgn:7012149",
        "tgn:2001447",
        "tgn:7007566",
        "tgn:7029392"
    ],
    "tgn:id":7022492,
    "tgn:name":"Ysleta\u00f1o Canyon",
    "tgn:placetype":[
        "aat:300008761"
    ]
},
  "bbox": [],
  "geometry": {"coordinates":[-105.85,33.05],"type":"Point"}
}
=======
{"geometry":{"type":"Point","coordinates":[-105.850000,33.050000]},"type":"Feature","properties":{"hierarchy":["tgn:7022492","tgn:1000001","tgn:7012149","tgn:2001447","tgn:7007566","tgn:7029392"],"placetype":["aat:300008761"],"id":7022492,"name:xx":"Ysleta\u00f1o Canyon"}}
>>>>>>> 03f74aca74312dbeaf24d7e61306dd6a786dc3d0
