<<<<<<< HEAD
{
  "id": 2339029,
  "type": "Feature",
  "properties": {
    "tgn:hierarchy":[
        "tgn:2339029",
        "tgn:1000001",
        "tgn:7012149",
        "tgn:2000491",
        "tgn:7007250",
        "tgn:7029392"
    ],
    "tgn:id":2339029,
    "tgn:name":"Franklin Mine",
    "tgn:placetype":[
        "aat:300000390"
    ]
},
  "bbox": [],
  "geometry": {"coordinates":[-115.9167,47.3],"type":"Point"}
}
=======
{"geometry":{"type":"Point","coordinates":[-115.916700,47.300000]},"type":"Feature","properties":{"hierarchy":["tgn:2339029","tgn:1000001","tgn:7012149","tgn:2000491","tgn:7007250","tgn:7029392"],"placetype":["aat:300000390"],"id":2339029,"name:xx":"Franklin Mine"}}
>>>>>>> 03f74aca74312dbeaf24d7e61306dd6a786dc3d0
