{
  "id": 7428715,
  "type": "Feature",
  "properties": {
    "tgn:hierarchy":[
        "tgn:7428715",
        "tgn:1000001",
        "tgn:7005601",
        "tgn:7005560",
        "tgn:7029392"
    ],
    "tgn:id":7428715,
    "tgn:name":"El Salitrillo",
    "tgn:placetype":[
        "aat:300008347"
    ]
},
  "bbox": [],
  "geometry": {"coordinates":[-101.116667,24.533333],"type":"Point"}
}