{
  "id": 2206432,
  "type": "Feature",
  "properties": {
    "tgn:hierarchy":[
        "tgn:2206432",
        "tgn:1000001",
        "tgn:7012149",
        "tgn:7007157",
        "tgn:7014475",
        "tgn:7029392"
    ],
    "tgn:id":2206432,
    "tgn:name":"Bullhead Canyon",
    "tgn:placetype":[
        "aat:300008761"
    ]
},
  "bbox": [],
  "geometry": {"coordinates":[-121.3167,37.1667],"type":"Point"}
}