{
  "id": 7070414,
  "type": "Feature",
  "properties": {
    "tgn:hierarchy":[
        "tgn:7070414",
        "tgn:7003669",
        "tgn:1000003",
        "tgn:7000084",
        "tgn:7029392"
    ],
    "tgn:id":7070414,
    "tgn:name":"Steinbach",
    "tgn:placetype":[
        "aat:300008347"
    ]
},
  "bbox": [],
  "geometry": {"coordinates":[13.033333,48.383333],"type":"Point"}
}