{
  "id": 7165607,
  "type": "Feature",
  "properties": {
    "tgn:hierarchy":[
        "tgn:7165607",
        "tgn:7003669",
        "tgn:1000003",
        "tgn:7000084",
        "tgn:7029392"
    ],
    "tgn:id":7165607,
    "tgn:name":"Harlachhof",
    "tgn:placetype":[
        "aat:300000206"
    ]
},
  "bbox": [],
  "geometry": {"coordinates":[12.033333,49.933333],"type":"Point"}
}