{
  "id": 7548877,
  "type": "Feature",
  "properties": {
    "tgn:hierarchy":[
        "tgn:7548877",
        "tgn:1000004",
        "tgn:7000198",
        "tgn:7016788",
        "tgn:7029392"
    ],
    "tgn:id":7548877,
    "tgn:name:en":"Busi",
    "tgn:placetype":[
        "aat:300008347"
    ]
},
  "bbox": [],
  "geometry": {"coordinates":[73.422827,25.563151],"type":"Point"}
}