{
  "id": 2644547,
  "type": "Feature",
  "properties": {
    "tgn:hierarchy":[
        "tgn:2644547",
        "tgn:1000001",
        "tgn:7012149",
        "tgn:7019676",
        "tgn:7007566",
        "tgn:7029392"
    ],
    "tgn:id":2644547,
    "tgn:name":"Sarcio, Mesa",
    "tgn:placetype":[
        "aat:300008798"
    ]
},
  "bbox": [],
  "geometry": {"coordinates":[-107.4833,35.5333],"type":"Point"}
}