{
  "id": 7195132,
  "type": "Feature",
  "properties": {
    "tgn:hierarchy":[
        "tgn:7195132",
        "tgn:7003692",
        "tgn:1000003",
        "tgn:7000084",
        "tgn:7029392"
    ],
    "tgn:id":7195132,
    "tgn:name":"Dobelbach",
    "tgn:placetype":[
        "aat:300008699"
    ]
},
  "bbox": [],
  "geometry": {"coordinates":[8.383333,48.566667],"type":"Point"}
}