{
  "id": 2444258,
  "type": "Feature",
  "properties": {
    "tgn:hierarchy":[
        "tgn:2444258",
        "tgn:1000001",
        "tgn:7013649",
        "tgn:7012149",
        "tgn:7007251",
        "tgn:7029392"
    ],
    "tgn:id":2444258,
    "tgn:name":"Lacey Lake",
    "tgn:placetype":[
        "aat:300008680"
    ]
},
  "bbox": [],
  "geometry": {"coordinates":[-88.1667,42.1333],"type":"Point"}
}