{
  "id": 7563326,
  "type": "Feature",
  "properties": {
    "tgn:hierarchy":[
        "tgn:7563326",
        "tgn:1000004",
        "tgn:7000198",
        "tgn:7016722",
        "tgn:7029392"
    ],
    "tgn:id":7563326,
    "tgn:name:en":"Daheli",
    "tgn:placetype":[
        "aat:300008347"
    ]
},
  "bbox": [],
  "geometry": {"coordinates":[79.863158,26.645546],"type":"Point"}
}