{
  "id": 7328813,
  "type": "Feature",
  "properties": {
    "tgn:hierarchy":[
        "tgn:7328813",
        "tgn:7008911",
        "tgn:1000003",
        "tgn:7002763",
        "tgn:1000095",
        "tgn:7029392"
    ],
    "tgn:id":7328813,
    "tgn:name":"Prada",
    "tgn:placetype":[
        "aat:300008347"
    ]
},
  "bbox": [],
  "geometry": {"coordinates":[-6.616667,43.233333],"type":"Point"}
}