{
  "id": 2332701,
  "type": "Feature",
  "properties": {
    "tgn:hierarchy":[
        "tgn:2332701",
        "tgn:1000001",
        "tgn:7012149",
        "tgn:2001503",
        "tgn:7007709",
        "tgn:7029392"
    ],
    "tgn:id":2332701,
    "tgn:name":"Flower Knob",
    "tgn:placetype":[
        "aat:300008798"
    ]
},
  "bbox": [],
  "geometry": {"coordinates":[-82.85,35.35],"type":"Point"}
}