{
  "id": 2162801,
  "type": "Feature",
  "properties": {
    "tgn:hierarchy":[
        "tgn:2162801",
        "tgn:1000001",
        "tgn:1002923",
        "tgn:7012149",
        "tgn:7007517",
        "tgn:7029392"
    ],
    "tgn:id":2162801,
    "tgn:name":"Benedict, Mount",
    "tgn:placetype":[
        "aat:300008798"
    ]
},
  "bbox": [],
  "geometry": {"coordinates":[-71.0667,42.3833],"type":"Point"}
}