{
  "id": 2446007,
  "type": "Feature",
  "properties": {
    "tgn:hierarchy":[
        "tgn:2446007",
        "tgn:1000001",
        "tgn:2000541",
        "tgn:7012149",
        "tgn:7007252",
        "tgn:7029392"
    ],
    "tgn:id":2446007,
    "tgn:name":"Lettsville",
    "tgn:placetype":[
        "aat:300008347"
    ]
},
  "bbox": [],
  "geometry": {"coordinates":[-87.1667,38.7167],"type":"Point"}
}