{
  "id": 7493549,
  "type": "Feature",
  "properties": {
    "tgn:hierarchy":[
        "tgn:7493549",
        "tgn:1000004",
        "tgn:7001013",
        "tgn:1000141",
        "tgn:7029392"
    ],
    "tgn:id":7493549,
    "tgn:name":"Hulukeng",
    "tgn:placetype":[
        "aat:300008347"
    ]
},
  "bbox": [],
  "geometry": {"coordinates":[121.272761,24.832333],"type":"Point"}
}