{
  "id": 2166116,
  "type": "Feature",
  "properties": {
    "tgn:hierarchy":[
        "tgn:2166116",
        "tgn:1000001",
        "tgn:7012149",
        "tgn:2001769",
        "tgn:7007712",
        "tgn:7029392"
    ],
    "tgn:id":2166116,
    "tgn:name":"Big Bay",
    "tgn:placetype":[
        "aat:300386845"
    ]
},
  "bbox": [],
  "geometry": {"coordinates":[-79.5333,33.55],"type":"Point"}
}