{
  "id": 2141002,
  "type": "Feature",
  "properties": {
    "tgn:hierarchy":[
        "tgn:2141002",
        "tgn:7002659",
        "tgn:1000001",
        "tgn:7012149",
        "tgn:2000042",
        "tgn:7029392"
    ],
    "tgn:id":2141002,
    "tgn:name":"Avinger Branch",
    "tgn:placetype":[
        "aat:300008699"
    ]
},
  "bbox": [],
  "geometry": {"coordinates":[-86.55,31.9833],"type":"Point"}
}