{
  "id": 7042918,
  "type": "Feature",
  "properties": {
    "tgn:hierarchy":[
        "tgn:7042918",
        "tgn:7003168",
        "tgn:1000003",
        "tgn:7009760",
        "tgn:1000080",
        "tgn:7029392"
    ],
    "tgn:id":7042918,
    "tgn:name":"Rigo, Torrente",
    "tgn:placetype":[
        "aat:300008699"
    ]
},
  "bbox": [],
  "geometry": {"coordinates":[11.766667,42.816667],"type":"Point"}
}