{
  "id": 7501909,
  "type": "Feature",
  "properties": {
    "tgn:hierarchy":[
        "tgn:7501909",
        "tgn:7488858",
        "tgn:1000004",
        "tgn:1000141",
        "tgn:7029392"
    ],
    "tgn:id":7501909,
    "tgn:name":"Beimeiguozhong",
    "tgn:placetype":[
        "aat:300008347"
    ]
},
  "bbox": [],
  "geometry": {"coordinates":[120.912778,24.056667],"type":"Point"}
}