{
  "id": 7069830,
  "type": "Feature",
  "properties": {
    "tgn:hierarchy":[
        "tgn:7069830",
        "tgn:1000003",
        "tgn:7003676",
        "tgn:7000084",
        "tgn:7029392"
    ],
    "tgn:id":7069830,
    "tgn:name":"Tod-Berg",
    "tgn:placetype":[
        "aat:300008795"
    ]
},
  "bbox": [],
  "geometry": {"coordinates":[10.383333,51.916667],"type":"Point"}
}