{
  "id": 7345701,
  "type": "Feature",
  "properties": {
    "tgn:hierarchy":[
        "tgn:7345701",
        "tgn:7002803",
        "tgn:1001647",
        "tgn:1000003",
        "tgn:1000095",
        "tgn:7029392"
    ],
    "tgn:id":7345701,
    "tgn:name":"Alborea",
    "tgn:placetype":[
        "aat:300008347"
    ]
},
  "bbox": [],
  "geometry": {"coordinates":[-1.383333,39.283333],"type":"Point"}
}