{
  "id": 7569560,
  "type": "Feature",
  "properties": {
    "tgn:hierarchy":[
        "tgn:7569560",
        "tgn:1000004",
        "tgn:7000198",
        "tgn:7031786",
        "tgn:7029392"
    ],
    "tgn:id":7569560,
    "tgn:name:en":"Mah\u0101r",
    "tgn:placetype":[
        "aat:300008347"
    ]
},
  "bbox": [],
  "geometry": {"coordinates":[78.718582,29.976628],"type":"Point"}
}