<<<<<<< HEAD
{
  "id": 7111730,
  "type": "Feature",
  "properties": {
    "tgn:hierarchy":[
        "tgn:7111730",
        "tgn:7003669",
        "tgn:1000003",
        "tgn:7000084",
        "tgn:7029392"
    ],
    "tgn:id":7111730,
    "tgn:name":"Ro\u00df Kopf",
    "tgn:placetype":[
        "aat:300008795"
    ]
},
  "bbox": [],
  "geometry": {"coordinates":[10.1,47.383333],"type":"Point"}
}
=======
{"geometry":{"type":"Point","coordinates":[10.100000,47.383333]},"type":"Feature","properties":{"hierarchy":["tgn:7111730","tgn:7003669","tgn:1000003","tgn:7000084","tgn:7029392"],"placetype":["aat:300008795"],"id":7111730,"name:xx":"Ro\u00df Kopf"}}
>>>>>>> 03f74aca74312dbeaf24d7e61306dd6a786dc3d0
