{
  "id": 2489455,
  "type": "Feature",
  "properties": {
    "tgn:hierarchy":[
        "tgn:2489455",
        "tgn:1000001",
        "tgn:7012149",
        "tgn:7007157",
        "tgn:1002608",
        "tgn:7029392"
    ],
    "tgn:id":2489455,
    "tgn:name":"Malibu Creek",
    "tgn:placetype":[
        "aat:300008706"
    ]
},
  "bbox": [],
  "geometry": {"coordinates":[-118.7833,34.1167],"type":"Point"}
}