{
  "id": 7534906,
  "type": "Feature",
  "properties": {
    "tgn:hierarchy":[
        "tgn:7534906",
        "tgn:7001242",
        "tgn:7001311",
        "tgn:7016833",
        "tgn:7029392"
    ],
    "tgn:id":7534906,
    "tgn:name":"Gh\u0101rib, Ra's",
    "tgn:placetype":[
        "aat:300386846"
    ]
},
  "bbox": [],
  "geometry": {"coordinates":[33.09929,28.361228],"type":"Point"}
}