{
  "id": 2703353,
  "type": "Feature",
  "properties": {
    "tgn:hierarchy":[
        "tgn:2703353",
        "tgn:7006450",
        "tgn:1000001",
        "tgn:7012149",
        "tgn:7029392"
    ],
    "tgn:id":2703353,
    "tgn:name":"Summit Creek",
    "tgn:placetype":[
        "aat:300008706"
    ]
},
  "bbox": [],
  "geometry": {"coordinates":[-136.1667,59.3333],"type":"Point"}
}