{
  "id": 1029959,
  "type": "Feature",
  "properties": {
    "tgn:hierarchy":[
        "tgn:1029959",
        "tgn:7002445",
        "tgn:7011980",
        "tgn:1000003",
        "tgn:7008591",
        "tgn:7029392"
    ],
    "tgn:id":1029959,
    "tgn:name:en":"Manea",
    "tgn:placetype":[
        "aat:300008347"
    ]
},
  "bbox": [],
  "geometry": {"coordinates":[0.183333,52.483333],"type":"Point"}
}