{
  "id": 2419356,
  "type": "Feature",
  "properties": {
    "tgn:hierarchy":[
        "tgn:2419356",
        "tgn:1000001",
        "tgn:7012149",
        "tgn:1002899",
        "tgn:7007920",
        "tgn:7029392"
    ],
    "tgn:id":2419356,
    "tgn:name":"Japanese Lake",
    "tgn:placetype":[
        "aat:300008680"
    ]
},
  "bbox": [],
  "geometry": {"coordinates":[-121.7833,47.9167],"type":"Point"}
}