{
  "id": 2428328,
  "type": "Feature",
  "properties": {
    "tgn:hierarchy":[
        "tgn:2428328",
        "tgn:1000001",
        "tgn:7012149",
        "tgn:7007521",
        "tgn:7029392"
    ],
    "tgn:id":2428328,
    "tgn:name":"Judicial Ditch Number Thirteen",
    "tgn:placetype":[
        "aat:300006075"
    ]
},
  "bbox": [],
  "geometry": {"coordinates":[-96.0667,44.2167],"type":"Point"}
}