{
  "id": 2309294,
  "type": "Feature",
  "properties": {
    "tgn:hierarchy":[
        "tgn:2309294",
        "tgn:1000001",
        "tgn:7012149",
        "tgn:2000514",
        "tgn:7007251",
        "tgn:7029392"
    ],
    "tgn:id":2309294,
    "tgn:name":"East Stockton",
    "tgn:placetype":[
        "aat:300008347"
    ]
},
  "bbox": [],
  "geometry": {"coordinates":[-89.9667,42.3333],"type":"Point"}
}