{
  "id": 2519357,
  "type": "Feature",
  "properties": {
    "tgn:hierarchy":[
        "tgn:2519357",
        "tgn:1000001",
        "tgn:7012149",
        "tgn:7007157",
        "tgn:1002828",
        "tgn:7029392"
    ],
    "tgn:id":2519357,
    "tgn:name":"Mockingbird Reservoir",
    "tgn:placetype":[
        "aat:300006191"
    ]
},
  "bbox": [],
  "geometry": {"coordinates":[-117.4167,33.8833],"type":"Point"}
}