{
  "id": 7088553,
  "type": "Feature",
  "properties": {
    "tgn:hierarchy":[
        "tgn:7088553",
        "tgn:1000003",
        "tgn:7003676",
        "tgn:7000084",
        "tgn:7029392"
    ],
    "tgn:id":7088553,
    "tgn:name":"Walshausen",
    "tgn:placetype":[
        "aat:300000206"
    ]
},
  "bbox": [],
  "geometry": {"coordinates":[10.016667,52.116667],"type":"Point"}
}