<<<<<<< HEAD
{
  "id": 7029909,
  "type": "Feature",
  "properties": {
    "tgn:hierarchy":[
        "tgn:7029909",
        "tgn:7019038",
        "tgn:7002445",
        "tgn:1000003",
        "tgn:7029507",
        "tgn:7008591",
        "tgn:7029392"
    ],
    "tgn:id":7029909,
    "tgn:name":"East Carlton",
    "tgn:placetype":[
        "aat:300008347",
        "aat:300008372"
    ]
},
  "bbox": [],
  "geometry": {"coordinates":[-1.66,53.883],"type":"Point"}
}
=======
{"geometry":{"type":"Point","coordinates":[-1.660000,53.883000]},"type":"Feature","properties":{"hierarchy":["tgn:7029909","tgn:7019038","tgn:7002445","tgn:1000003","tgn:7029507","tgn:7008591","tgn:7029392"],"placetype":["aat:300008347","aat:300008372"],"id":7029909,"name:xx":"East Carlton"}}
>>>>>>> 03f74aca74312dbeaf24d7e61306dd6a786dc3d0
