{
  "id": 7129230,
  "type": "Feature",
  "properties": {
    "tgn:hierarchy":[
        "tgn:7129230",
        "tgn:7000096",
        "tgn:1000003",
        "tgn:7000084",
        "tgn:7029392"
    ],
    "tgn:id":7129230,
    "tgn:name":"Mathildenhof",
    "tgn:placetype":[
        "aat:300000206"
    ]
},
  "bbox": [],
  "geometry": {"coordinates":[12.083333,53.316667],"type":"Point"}
}