{
  "id": 2143079,
  "type": "Feature",
  "properties": {
    "tgn:hierarchy":[
        "tgn:2143079",
        "tgn:7006450",
        "tgn:1000001",
        "tgn:7012149",
        "tgn:7029392"
    ],
    "tgn:id":2143079,
    "tgn:name":"Bagot, Mount",
    "tgn:placetype":[
        "aat:300008798"
    ]
},
  "bbox": [],
  "geometry": {"coordinates":[-135.0167,59.3333],"type":"Point"}
}