{
  "id": 2741167,
  "type": "Feature",
  "properties": {
    "tgn:hierarchy":[
        "tgn:2741167",
        "tgn:1000001",
        "tgn:7012149",
        "tgn:2000839",
        "tgn:7007255",
        "tgn:7029392"
    ],
    "tgn:id":2741167,
    "tgn:name":"Upper Troublesome Creek",
    "tgn:placetype":[
        "aat:300008706"
    ]
},
  "bbox": [],
  "geometry": {"coordinates":[-84.3667,37.0167],"type":"Point"}
}