{
  "id": 1050538,
  "type": "Feature",
  "properties": {
    "tgn:hierarchy":[
        "tgn:1050538",
        "tgn:7002444",
        "tgn:1000003",
        "tgn:7019085",
        "tgn:7008591",
        "tgn:7029392"
    ],
    "tgn:id":1050538,
    "tgn:name:en":"Colmonell",
    "tgn:placetype":[
        "aat:300008347"
    ]
},
  "bbox": [],
  "geometry": {"coordinates":[-4.916667,55.116667],"type":"Point"}
}