{
  "id": 7021660,
  "type": "Feature",
  "properties": {
    "tgn:hierarchy":[
        "tgn:7021660",
        "tgn:1000001",
        "tgn:2001736",
        "tgn:7012149",
        "tgn:7007712",
        "tgn:7029392"
    ],
    "tgn:id":7021660,
    "tgn:name":"Bull Run Creek",
    "tgn:placetype":[
        "aat:300008706"
    ]
},
  "bbox": [],
  "geometry": {"coordinates":[-81.1833,34.65],"type":"Point"}
}