<<<<<<< HEAD
{
  "id": 7021660,
  "type": "Feature",
  "properties": {
    "tgn:hierarchy":[
        "tgn:7021660",
        "tgn:1000001",
        "tgn:2001736",
        "tgn:7012149",
        "tgn:7007712",
        "tgn:7029392"
    ],
    "tgn:id":7021660,
    "tgn:name":"Bull Run Creek",
    "tgn:placetype":[
        "aat:300008706"
    ]
},
  "bbox": [],
  "geometry": {"coordinates":[-81.1833,34.65],"type":"Point"}
}
=======
{"geometry":{"type":"Point","coordinates":[-81.183300,34.650000]},"type":"Feature","properties":{"hierarchy":["tgn:7021660","tgn:1000001","tgn:2001736","tgn:7012149","tgn:7007712","tgn:7029392"],"placetype":["aat:300008706"],"id":7021660,"name:xx":"Bull Run Creek"}}
>>>>>>> 03f74aca74312dbeaf24d7e61306dd6a786dc3d0
