<<<<<<< HEAD
{
  "id": 2335589,
  "type": "Feature",
  "properties": {
    "tgn:hierarchy":[
        "tgn:2335589",
        "tgn:1000001",
        "tgn:1002923",
        "tgn:7012149",
        "tgn:7007517",
        "tgn:7029392"
    ],
    "tgn:id":2335589,
    "tgn:name":"Fort Winthrop",
    "tgn:placetype":[
        "aat:300386984",
        "aat:300006909"
    ]
},
  "bbox": [],
  "geometry": {"coordinates":[-71.0,42.35],"type":"Point"}
}
=======
{"geometry":{"type":"Point","coordinates":[-71.000000,42.350000]},"type":"Feature","properties":{"hierarchy":["tgn:2335589","tgn:1000001","tgn:1002923","tgn:7012149","tgn:7007517","tgn:7029392"],"placetype":["aat:300386984","aat:300006909"],"id":2335589,"name:xx":"Fort Winthrop"}}
>>>>>>> 03f74aca74312dbeaf24d7e61306dd6a786dc3d0
