{
  "id": 2678349,
  "type": "Feature",
  "properties": {
    "tgn:hierarchy":[
        "tgn:2678349",
        "tgn:1000001",
        "tgn:7012149",
        "tgn:1002636",
        "tgn:7007708",
        "tgn:7029392"
    ],
    "tgn:id":2678349,
    "tgn:name":"South Fork Cedar Creek",
    "tgn:placetype":[
        "aat:300008706"
    ]
},
  "bbox": [],
  "geometry": {"coordinates":[-122.5833,44.9167],"type":"Point"}
}