<<<<<<< HEAD
{
  "id": 2338163,
  "type": "Feature",
  "properties": {
    "tgn:hierarchy":[
        "tgn:2338163",
        "tgn:1008300",
        "tgn:1009982",
        "tgn:1000001",
        "tgn:1002344",
        "tgn:7012149",
        "tgn:7007517",
        "tgn:7029392"
    ],
    "tgn:id":2338163,
    "tgn:name":"Fox Point",
    "tgn:placetype":[
        "aat:300008850"
    ]
},
  "bbox": [],
  "geometry": {"coordinates":[-70.8333,41.4333],"type":"Point"}
}
=======
{"geometry":{"type":"Point","coordinates":[-70.833300,41.433300]},"type":"Feature","properties":{"hierarchy":["tgn:2338163","tgn:1008300","tgn:1009982","tgn:1000001","tgn:1002344","tgn:7012149","tgn:7007517","tgn:7029392"],"placetype":["aat:300008850"],"id":2338163,"name:xx":"Fox Point"}}
>>>>>>> 03f74aca74312dbeaf24d7e61306dd6a786dc3d0
