{
  "id": 7485866,
  "type": "Feature",
  "properties": {
    "tgn:hierarchy":[
        "tgn:7485866",
        "tgn:1000004",
        "tgn:7467799",
        "tgn:1000141",
        "tgn:7029392"
    ],
    "tgn:id":7485866,
    "tgn:name":"Daquwei",
    "tgn:placetype":[
        "aat:300008347"
    ]
},
  "bbox": [],
  "geometry": {"coordinates":[120.49,24.050278],"type":"Point"}
}