<<<<<<< HEAD
{
  "id": 7485866,
  "type": "Feature",
  "properties": {
    "tgn:hierarchy":[
        "tgn:7485866",
        "tgn:1000004",
        "tgn:7467799",
        "tgn:1000141",
        "tgn:7029392"
    ],
    "tgn:id":7485866,
    "tgn:name":"Daquwei",
    "tgn:placetype":[
        "aat:300008347"
    ]
},
  "bbox": [],
  "geometry": {"coordinates":[120.49,24.050278],"type":"Point"}
}
=======
{"geometry":{"type":"Point","coordinates":[120.490000,24.050278]},"type":"Feature","properties":{"hierarchy":["tgn:7485866","tgn:1000004","tgn:7467799","tgn:1000141","tgn:7029392"],"placetype":["aat:300008347"],"id":7485866,"name:xx":"Daquwei"}}
>>>>>>> 03f74aca74312dbeaf24d7e61306dd6a786dc3d0
