{
  "id": 2408953,
  "type": "Feature",
  "properties": {
    "tgn:hierarchy":[
        "tgn:2408953",
        "tgn:1000001",
        "tgn:7012149",
        "tgn:2000345",
        "tgn:7007248",
        "tgn:7029392"
    ],
    "tgn:id":2408953,
    "tgn:name":"I W De Loach Ponds",
    "tgn:placetype":[
        "aat:300006191"
    ]
},
  "bbox": [],
  "geometry": {"coordinates":[-81.8167,32.2167],"type":"Point"}
}