<<<<<<< HEAD
{
  "id": 7369544,
  "type": "Feature",
  "properties": {
    "tgn:hierarchy":[
        "tgn:7369544",
        "tgn:7005578",
        "tgn:1000001",
        "tgn:7005560",
        "tgn:7029392"
    ],
    "tgn:id":7369544,
    "tgn:name":"Kaxek",
    "tgn:placetype":[
        "aat:300008347"
    ]
},
  "bbox": [],
  "geometry": {"coordinates":[-89.85,20.016667],"type":"Point"}
}
=======
{"geometry":{"type":"Point","coordinates":[-89.850000,20.016667]},"type":"Feature","properties":{"hierarchy":["tgn:7369544","tgn:7005578","tgn:1000001","tgn:7005560","tgn:7029392"],"placetype":["aat:300008347"],"id":7369544,"name:xx":"Kaxek"}}
>>>>>>> 03f74aca74312dbeaf24d7e61306dd6a786dc3d0
