{
  "id": 2407364,
  "type": "Feature",
  "properties": {
    "tgn:hierarchy":[
        "tgn:2407364",
        "tgn:1000001",
        "tgn:7012149",
        "tgn:1002379",
        "tgn:7007826",
        "tgn:7029392"
    ],
    "tgn:id":2407364,
    "tgn:name":"Huntington Mound",
    "tgn:placetype":[
        "aat:300008798"
    ]
},
  "bbox": [],
  "geometry": {"coordinates":[-95.8667,29.6167],"type":"Point"}
}