<<<<<<< HEAD
{
  "id": 2407364,
  "type": "Feature",
  "properties": {
    "tgn:hierarchy":[
        "tgn:2407364",
        "tgn:1000001",
        "tgn:7012149",
        "tgn:1002379",
        "tgn:7007826",
        "tgn:7029392"
    ],
    "tgn:id":2407364,
    "tgn:name":"Huntington Mound",
    "tgn:placetype":[
        "aat:300008798"
    ]
},
  "bbox": [],
  "geometry": {"coordinates":[-95.8667,29.6167],"type":"Point"}
}
=======
{"geometry":{"type":"Point","coordinates":[-95.866700,29.616700]},"type":"Feature","properties":{"hierarchy":["tgn:2407364","tgn:1000001","tgn:7012149","tgn:1002379","tgn:7007826","tgn:7029392"],"placetype":["aat:300008798"],"id":2407364,"name:xx":"Huntington Mound"}}
>>>>>>> 03f74aca74312dbeaf24d7e61306dd6a786dc3d0
