{
  "id": 1033344,
  "type": "Feature",
  "properties": {
    "tgn:hierarchy":[
        "tgn:1033344",
        "tgn:1000003",
        "tgn:7002883",
        "tgn:1000070",
        "tgn:7029392"
    ],
    "tgn:id":1033344,
    "tgn:name":"Gretz-Armainvilliers",
    "tgn:placetype":[
        "aat:300008347"
    ]
},
  "bbox": [],
  "geometry": {"coordinates":[2.75,48.7333],"type":"Point"}
}