{
  "id": 7528619,
  "type": "Feature",
  "properties": {
    "tgn:hierarchy":[
        "tgn:7528619",
        "tgn:7001242",
        "tgn:7001311",
        "tgn:7016833",
        "tgn:7029392"
    ],
    "tgn:id":7528619,
    "tgn:name:en":"Sukkar\u012b, Jabal",
    "tgn:placetype":[
        "aat:300008795"
    ]
},
  "bbox": [],
  "geometry": {"coordinates":[34.721653,24.958827],"type":"Point"}
}