{
  "id": 7282398,
  "type": "Feature",
  "properties": {
    "tgn:hierarchy":[
        "tgn:7282398",
        "tgn:7002464",
        "tgn:1000049",
        "tgn:1000002",
        "tgn:7029392"
    ],
    "tgn:id":7282398,
    "tgn:name":"Pitausa, Pampa",
    "tgn:placetype":[
        "aat:300008805"
    ]
},
  "bbox": [],
  "geometry": {"coordinates":[-68.783333,-21.15],"type":"Point"}
}