{
  "id": 7386037,
  "type": "Feature",
  "properties": {
    "tgn:hierarchy":[
        "tgn:7386037",
        "tgn:7005581",
        "tgn:1000001",
        "tgn:7005560",
        "tgn:7029392"
    ],
    "tgn:id":7386037,
    "tgn:name":"Pelon, Cerro",
    "tgn:placetype":[
        "aat:300008777"
    ]
},
  "bbox": [],
  "geometry": {"coordinates":[-107.15,28.35],"type":"Point"}
}