{
  "id": 7187645,
  "type": "Feature",
  "properties": {
    "tgn:hierarchy":[
        "tgn:7187645",
        "tgn:1000003",
        "tgn:7003682",
        "tgn:7000084",
        "tgn:7029392"
    ],
    "tgn:id":7187645,
    "tgn:name":"Erlenbruch",
    "tgn:placetype":[
        "aat:300000206"
    ]
},
  "bbox": [],
  "geometry": {"coordinates":[7.816667,50.866667],"type":"Point"}
}