{
  "id": 7040091,
  "type": "Feature",
  "properties": {
    "tgn:hierarchy":[
        "tgn:7040091",
        "tgn:7002995",
        "tgn:1000003",
        "tgn:7002997",
        "tgn:1000080",
        "tgn:7029392"
    ],
    "tgn:id":7040091,
    "tgn:name":"Scardovari, Sacca dei",
    "tgn:placetype":[
        "aat:300008679"
    ]
},
  "bbox": [],
  "geometry": {"coordinates":[12.421111,44.8725],"type":"Point"}
}