{
  "id": 2687744,
  "type": "Feature",
  "properties": {
    "tgn:hierarchy":[
        "tgn:2687744",
        "tgn:2001563",
        "tgn:1000001",
        "tgn:7012149",
        "tgn:7007705",
        "tgn:7029392"
    ],
    "tgn:id":2687744,
    "tgn:name":"Spring Slough",
    "tgn:placetype":[
        "aat:300008680"
    ]
},
  "bbox": [],
  "geometry": {"coordinates":[-102.45,48.5833],"type":"Point"}
}