{
  "id": 2477480,
  "type": "Feature",
  "properties": {
    "tgn:hierarchy":[
        "tgn:2477480",
        "tgn:2001623",
        "tgn:1000001",
        "tgn:7012149",
        "tgn:7007707",
        "tgn:7029392"
    ],
    "tgn:id":2477480,
    "tgn:name":"Lyons Mountain",
    "tgn:placetype":[
        "aat:300008798"
    ]
},
  "bbox": [],
  "geometry": {"coordinates":[-94.7333,35.7333],"type":"Point"}
}