{
  "id": 2105814,
  "type": "Feature",
  "properties": {
    "tgn:hierarchy":[
        "tgn:2105814",
        "tgn:1000001",
        "tgn:2001936",
        "tgn:7012149",
        "tgn:7007826",
        "tgn:7029392"
    ],
    "tgn:id":2105814,
    "tgn:name":"Lytle",
    "tgn:placetype":[
        "aat:300008347"
    ]
},
  "bbox": [],
  "geometry": {"coordinates":[-98.7833,29.2167],"type":"Point"}
}