{
  "id": 7232433,
  "type": "Feature",
  "properties": {
    "tgn:hierarchy":[
        "tgn:7232433",
        "tgn:7002690",
        "tgn:7012056",
        "tgn:1000003",
        "tgn:1000074",
        "tgn:7029392"
    ],
    "tgn:id":7232433,
    "tgn:name":"K\u00e1vos",
    "tgn:placetype":[
        "aat:300008777"
    ]
},
  "bbox": [],
  "geometry": {"coordinates":[23.316667,35.883333],"type":"Point"}
}