{
  "id": 7568747,
  "type": "Feature",
  "properties": {
    "tgn:hierarchy":[
        "tgn:7568747",
        "tgn:1000004",
        "tgn:7000198",
        "tgn:1001996",
        "tgn:7029392"
    ],
    "tgn:id":7568747,
    "tgn:name:en":"Panjail",
    "tgn:placetype":[
        "aat:300008347"
    ]
},
  "bbox": [],
  "geometry": {"coordinates":[77.0175,31.151667],"type":"Point"}
}