<<<<<<< HEAD
{
  "id": 2255822,
  "type": "Feature",
  "properties": {
    "tgn:hierarchy":[
        "tgn:2255822",
        "tgn:1000001",
        "tgn:7006451",
        "tgn:7012149",
        "tgn:2000098",
        "tgn:7029392"
    ],
    "tgn:id":2255822,
    "tgn:name":"Copper Creek",
    "tgn:placetype":[
        "aat:300008706"
    ]
},
  "bbox": [],
  "geometry": {"coordinates":[-113.9,34.8667],"type":"Point"}
}
=======
{"geometry":{"type":"Point","coordinates":[-113.900000,34.866700]},"type":"Feature","properties":{"hierarchy":["tgn:2255822","tgn:1000001","tgn:7006451","tgn:7012149","tgn:2000098","tgn:7029392"],"placetype":["aat:300008706"],"id":2255822,"name:xx":"Copper Creek"}}
>>>>>>> 03f74aca74312dbeaf24d7e61306dd6a786dc3d0
