{
  "id": 7137546,
  "type": "Feature",
  "properties": {
    "tgn:hierarchy":[
        "tgn:7137546",
        "tgn:1000003",
        "tgn:7000094",
        "tgn:7000084",
        "tgn:7029392"
    ],
    "tgn:id":7137546,
    "tgn:name":"Lenz",
    "tgn:placetype":[
        "aat:300008347"
    ]
},
  "bbox": [],
  "geometry": {"coordinates":[13.633333,54.516667],"type":"Point"}
}