{
  "id": 7064982,
  "type": "Feature",
  "properties": {
    "tgn:hierarchy":[
        "tgn:7064982",
        "tgn:1000003",
        "tgn:7003685",
        "tgn:7000084",
        "tgn:7029392"
    ],
    "tgn:id":7064982,
    "tgn:name":"Steinp\u00f6hl",
    "tgn:placetype":[
        "aat:300008777"
    ]
},
  "bbox": [],
  "geometry": {"coordinates":[12.25,50.416667],"type":"Point"}
}