<<<<<<< HEAD
{
  "id": 2259334,
  "type": "Feature",
  "properties": {
    "tgn:hierarchy":[
        "tgn:2259334",
        "tgn:1000001",
        "tgn:7012149",
        "tgn:7007157",
        "tgn:1002856",
        "tgn:7029392"
    ],
    "tgn:id":2259334,
    "tgn:name":"Cottonwood Ridge",
    "tgn:placetype":[
        "aat:300266640"
    ]
},
  "bbox": [],
  "geometry": {"coordinates":[-120.95,36.4833],"type":"Point"}
}
=======
{"geometry":{"type":"Point","coordinates":[-120.950000,36.483300]},"type":"Feature","properties":{"hierarchy":["tgn:2259334","tgn:1000001","tgn:7012149","tgn:7007157","tgn:1002856","tgn:7029392"],"placetype":["aat:300266640"],"id":2259334,"name:xx":"Cottonwood Ridge"}}
>>>>>>> 03f74aca74312dbeaf24d7e61306dd6a786dc3d0
