<<<<<<< HEAD
{
  "id": 7481091,
  "type": "Feature",
  "properties": {
    "tgn:hierarchy":[
        "tgn:7481091",
        "tgn:7468018",
        "tgn:1000004",
        "tgn:1000141",
        "tgn:7029392"
    ],
    "tgn:id":7481091,
    "tgn:name":"Paishuilu Qiao",
    "tgn:placetype":[
        "aat:300007836"
    ]
},
  "bbox": [],
  "geometry": {"coordinates":[120.244837,23.4488],"type":"Point"}
}
=======
{"geometry":{"type":"Point","coordinates":[120.244837,23.448800]},"type":"Feature","properties":{"hierarchy":["tgn:7481091","tgn:7468018","tgn:1000004","tgn:1000141","tgn:7029392"],"placetype":["aat:300007836"],"id":7481091,"name:xx":"Paishuilu Qiao"}}
>>>>>>> 03f74aca74312dbeaf24d7e61306dd6a786dc3d0
