{
  "id": 7290793,
  "type": "Feature",
  "properties": {
    "tgn:hierarchy":[
        "tgn:7290793",
        "tgn:1001702",
        "tgn:1000049",
        "tgn:1000002",
        "tgn:7029392"
    ],
    "tgn:id":7290793,
    "tgn:name":"Cutter, Isla",
    "tgn:placetype":[
        "aat:300008791"
    ]
},
  "bbox": [],
  "geometry": {"coordinates":[-72.466667,-53.366667],"type":"Point"}
}