{
  "id": 7035767,
  "type": "Feature",
  "properties": {
    "tgn:hierarchy":[
        "tgn:7035767",
        "tgn:7002991",
        "tgn:1000003",
        "tgn:7002997",
        "tgn:1000080",
        "tgn:7029392"
    ],
    "tgn:id":7035767,
    "tgn:name":"Calleda, Val",
    "tgn:placetype":[
        "aat:300008761"
    ]
},
  "bbox": [],
  "geometry": {"coordinates":[12.072778,46.306389],"type":"Point"}
}