{
  "id": 7480224,
  "type": "Feature",
  "properties": {
    "tgn:hierarchy":[
        "tgn:7480224",
        "tgn:1000004",
        "tgn:1000454",
        "tgn:1000141",
        "tgn:7029392"
    ],
    "tgn:id":7480224,
    "tgn:name":"Danshui Guoxiao",
    "tgn:placetype":[
        "aat:300006495"
    ]
},
  "bbox": [],
  "geometry": {"coordinates":[121.441951,25.173727],"type":"Point"}
}