{
  "id": 7497401,
  "type": "Feature",
  "properties": {
    "tgn:hierarchy":[
        "tgn:7497401",
        "tgn:1000004",
        "tgn:7001013",
        "tgn:1000141",
        "tgn:7029392"
    ],
    "tgn:id":7497401,
    "tgn:name":"Jiulu Daqiao",
    "tgn:placetype":[
        "aat:300007836"
    ]
},
  "bbox": [],
  "geometry": {"coordinates":[121.362353,25.018272],"type":"Point"}
}