{
  "id": 7429899,
  "type": "Feature",
  "properties": {
    "tgn:hierarchy":[
        "tgn:7429899",
        "tgn:7005583",
        "tgn:1000001",
        "tgn:7005560",
        "tgn:7029392"
    ],
    "tgn:id":7429899,
    "tgn:name":"La Amapola",
    "tgn:placetype":[
        "aat:300008347"
    ]
},
  "bbox": [],
  "geometry": {"coordinates":[-104.533333,24.683333],"type":"Point"}
}