{
  "id": 7458847,
  "type": "Feature",
  "properties": {
    "tgn:hierarchy":[
        "tgn:7458847",
        "tgn:7011385",
        "tgn:7002445",
        "tgn:1000003",
        "tgn:7026528",
        "tgn:7008591",
        "tgn:7029392"
    ],
    "tgn:id":7458847,
    "tgn:name:en":"Millbrook",
    "tgn:placetype":[
        "aat:300007783"
    ]
},
  "bbox": [],
  "geometry": {"coordinates":[-1.45,50.916667],"type":"Point"}
}