{
  "id": 2507985,
  "type": "Feature",
  "properties": {
    "tgn:hierarchy":[
        "tgn:2507985",
        "tgn:1000001",
        "tgn:7012149",
        "tgn:1002986",
        "tgn:7007568",
        "tgn:7029392"
    ],
    "tgn:id":2507985,
    "tgn:name":"Middle Bay",
    "tgn:placetype":[
        "aat:300132316"
    ]
},
  "bbox": [],
  "geometry": {"coordinates":[-73.65,43.4667],"type":"Point"}
}