{
  "id": 2676274,
  "type": "Feature",
  "properties": {
    "tgn:hierarchy":[
        "tgn:2676274",
        "tgn:1000001",
        "tgn:7012149",
        "tgn:7018871",
        "tgn:7007920",
        "tgn:7029392"
    ],
    "tgn:id":2676274,
    "tgn:name":"Source Lake",
    "tgn:placetype":[
        "aat:300008680"
    ]
},
  "bbox": [],
  "geometry": {"coordinates":[-121.45,47.45],"type":"Point"}
}