{
  "id": 1066715,
  "type": "Feature",
  "properties": {
    "tgn:hierarchy":[
        "tgn:1066715",
        "tgn:1000004",
        "tgn:7001838",
        "tgn:1000111",
        "tgn:7029392"
    ],
    "tgn:id":1066715,
    "tgn:name":"Balihan",
    "tgn:placetype":[
        "aat:300008347"
    ]
},
  "bbox": [],
  "geometry": {"coordinates":[118.7667,41.35],"type":"Point"}
}