{
  "id": 2432858,
  "type": "Feature",
  "properties": {
    "tgn:hierarchy":[
        "tgn:2432858",
        "tgn:1000001",
        "tgn:7012149",
        "tgn:7007252",
        "tgn:7029392"
    ],
    "tgn:id":2432858,
    "tgn:name":"Keesling Run",
    "tgn:placetype":[
        "aat:300008699"
    ]
},
  "bbox": [],
  "geometry": {"coordinates":[-85.5667,40.05],"type":"Point"}
}