{
  "id": 2602663,
  "type": "Feature",
  "properties": {
    "tgn:hierarchy":[
        "tgn:2602663",
        "tgn:1000001",
        "tgn:7012149",
        "tgn:2002127",
        "tgn:7007827",
        "tgn:7029392"
    ],
    "tgn:id":2602663,
    "tgn:name":"Quail Reservoir",
    "tgn:placetype":[
        "aat:300006191"
    ]
},
  "bbox": [],
  "geometry": {"coordinates":[-113.75,37.0833],"type":"Point"}
}