{
  "id": 7359477,
  "type": "Feature",
  "properties": {
    "tgn:hierarchy":[
        "tgn:7359477",
        "tgn:7005586",
        "tgn:1000001",
        "tgn:7005560",
        "tgn:7029392"
    ],
    "tgn:id":7359477,
    "tgn:name":"Ciudad Granja",
    "tgn:placetype":[
        "aat:300008347"
    ]
},
  "bbox": [],
  "geometry": {"coordinates":[-103.433333,20.683333],"type":"Point"}
}