{
  "id": 2203437,
  "type": "Feature",
  "properties": {
    "tgn:hierarchy":[
        "tgn:2203437",
        "tgn:1000001",
        "tgn:7012149",
        "tgn:2002005",
        "tgn:7007826",
        "tgn:7029392"
    ],
    "tgn:id":2203437,
    "tgn:name":"Buckhorn Tank",
    "tgn:placetype":[
        "aat:300006191"
    ]
},
  "bbox": [],
  "geometry": {"coordinates":[-105.4167,30.9167],"type":"Point"}
}