{
  "id": 7502063,
  "type": "Feature",
  "properties": {
    "tgn:hierarchy":[
        "tgn:7502063",
        "tgn:1000004",
        "tgn:7001009",
        "tgn:1000141",
        "tgn:7029392"
    ],
    "tgn:id":7502063,
    "tgn:name":"Tancheping",
    "tgn:placetype":[
        "aat:300008347"
    ]
},
  "bbox": [],
  "geometry": {"coordinates":[120.798605,24.130198],"type":"Point"}
}