<<<<<<< HEAD
{
  "id": 7482558,
  "type": "Feature",
  "properties": {
    "tgn:hierarchy":[
        "tgn:7482558",
        "tgn:1000004",
        "tgn:7001014",
        "tgn:1000141",
        "tgn:7029392"
    ],
    "tgn:id":7482558,
    "tgn:name":"Feisha Guozhong",
    "tgn:placetype":[
        "aat:300006495"
    ]
},
  "bbox": [],
  "geometry": {"coordinates":[120.173056,23.642222],"type":"Point"}
}
=======
{"geometry":{"type":"Point","coordinates":[120.173056,23.642222]},"type":"Feature","properties":{"hierarchy":["tgn:7482558","tgn:1000004","tgn:7001014","tgn:1000141","tgn:7029392"],"placetype":["aat:300006495"],"id":7482558,"name:xx":"Feisha Guozhong"}}
>>>>>>> 03f74aca74312dbeaf24d7e61306dd6a786dc3d0
