{
  "id": 2420467,
  "type": "Feature",
  "properties": {
    "tgn:hierarchy":[
        "tgn:2420467",
        "tgn:1000001",
        "tgn:2001429",
        "tgn:7012149",
        "tgn:7007566",
        "tgn:7029392"
    ],
    "tgn:id":2420467,
    "tgn:name":"Jenkins Creek",
    "tgn:placetype":[
        "aat:300008706"
    ]
},
  "bbox": [],
  "geometry": {"coordinates":[-109.0167,33.9833],"type":"Point"}
}