{
  "id": 2244928,
  "type": "Feature",
  "properties": {
    "tgn:hierarchy":[
        "tgn:2244928",
        "tgn:1000001",
        "tgn:7012149",
        "tgn:2001308",
        "tgn:7007524",
        "tgn:7029392"
    ],
    "tgn:id":2244928,
    "tgn:name":"Clover Basin",
    "tgn:placetype":[
        "aat:300386845"
    ]
},
  "bbox": [],
  "geometry": {"coordinates":[-110.0167,45.5167],"type":"Point"}
}