{
  "id": 2741854,
  "type": "Feature",
  "properties": {
    "tgn:hierarchy":[
        "tgn:2741854",
        "tgn:1000001",
        "tgn:2001429",
        "tgn:7012149",
        "tgn:7007566",
        "tgn:7029392"
    ],
    "tgn:id":2741854,
    "tgn:name":"V-Cross-T Lake",
    "tgn:placetype":[
        "aat:300008680"
    ]
},
  "bbox": [],
  "geometry": {"coordinates":[-108.1167,33.4667],"type":"Point"}
}