<<<<<<< HEAD
{
  "id": 7362911,
  "type": "Feature",
  "properties": {
    "tgn:hierarchy":[
        "tgn:7362911",
        "tgn:1001853",
        "tgn:1000001",
        "tgn:7005560",
        "tgn:7029392"
    ],
    "tgn:id":7362911,
    "tgn:name":"Rancho El Masamitote",
    "tgn:placetype":[
        "aat:300000241"
    ]
},
  "bbox": [],
  "geometry": {"coordinates":[-102.716667,25.95],"type":"Point"}
}
=======
{"geometry":{"type":"Point","coordinates":[-102.716667,25.950000]},"type":"Feature","properties":{"hierarchy":["tgn:7362911","tgn:1001853","tgn:1000001","tgn:7005560","tgn:7029392"],"placetype":["aat:300000241"],"id":7362911,"name:xx":"Rancho El Masamitote"}}
>>>>>>> 03f74aca74312dbeaf24d7e61306dd6a786dc3d0
