{
  "id": 2577550,
  "type": "Feature",
  "properties": {
    "tgn:hierarchy":[
        "tgn:2577550",
        "tgn:1000001",
        "tgn:7012149",
        "tgn:7007250",
        "tgn:7029392"
    ],
    "tgn:id":2577550,
    "tgn:name":"Peterson Gulch",
    "tgn:placetype":[
        "aat:300008761"
    ]
},
  "bbox": [],
  "geometry": {"coordinates":[-116.2333,43.95],"type":"Point"}
}