{
  "id": 1107679,
  "type": "Feature",
  "properties": {
    "tgn:hierarchy":[
        "tgn:1107679",
        "tgn:1000566",
        "tgn:1000001",
        "tgn:7005562",
        "tgn:7029392"
    ],
    "tgn:id":1107679,
    "tgn:name":"Cosig\u00fcina, Volc\u00e1n",
    "tgn:placetype":[
        "aat:300132325"
    ]
},
  "bbox": [],
  "geometry": {"coordinates":[-87.566,12.981],"type":"Point"}
}