<<<<<<< HEAD
{
  "id": 7176265,
  "type": "Feature",
  "properties": {
    "tgn:hierarchy":[
        "tgn:7176265",
        "tgn:1000003",
        "tgn:7000094",
        "tgn:7000084",
        "tgn:7029392"
    ],
    "tgn:id":7176265,
    "tgn:name":"Gro\u00df Strummin-See",
    "tgn:placetype":[
        "aat:300185707"
    ]
},
  "bbox": [],
  "geometry": {"coordinates":[13.883333,54.05],"type":"Point"}
}
=======
{"geometry":{"type":"Point","coordinates":[13.883333,54.050000]},"type":"Feature","properties":{"hierarchy":["tgn:7176265","tgn:1000003","tgn:7000094","tgn:7000084","tgn:7029392"],"placetype":["aat:300185707"],"id":7176265,"name:xx":"Gro\u00df Strummin-See"}}
>>>>>>> 03f74aca74312dbeaf24d7e61306dd6a786dc3d0
