<<<<<<< HEAD
{
  "id": 7024394,
  "type": "Feature",
  "properties": {
    "tgn:hierarchy":[
        "tgn:7024394",
        "tgn:7003139",
        "tgn:1000003",
        "tgn:7003080",
        "tgn:1000080",
        "tgn:7029392"
    ],
    "tgn:id":7024394,
    "tgn:name":"Faleria",
    "tgn:placetype":[
        "aat:300008347"
    ]
},
  "bbox": [],
  "geometry": {"coordinates":[12.433333,42.233333],"type":"Point"}
}
=======
{"geometry":{"type":"Point","coordinates":[12.433333,42.233333]},"type":"Feature","properties":{"hierarchy":["tgn:7024394","tgn:7003139","tgn:1000003","tgn:7003080","tgn:1000080","tgn:7029392"],"placetype":["aat:300008347"],"id":7024394,"name:xx":"Faleria"}}
>>>>>>> 03f74aca74312dbeaf24d7e61306dd6a786dc3d0
