<<<<<<< HEAD
{
  "id": 7376903,
  "type": "Feature",
  "properties": {
    "tgn:hierarchy":[
        "tgn:7376903",
        "tgn:7005586",
        "tgn:1000001",
        "tgn:7005560",
        "tgn:7029392"
    ],
    "tgn:id":7376903,
    "tgn:name":"La Sanguijuela",
    "tgn:placetype":[
        "aat:300008347"
    ]
},
  "bbox": [],
  "geometry": {"coordinates":[-102.9,20.466667],"type":"Point"}
}
=======
{"geometry":{"type":"Point","coordinates":[-102.900000,20.466667]},"type":"Feature","properties":{"hierarchy":["tgn:7376903","tgn:7005586","tgn:1000001","tgn:7005560","tgn:7029392"],"placetype":["aat:300008347"],"id":7376903,"name:xx":"La Sanguijuela"}}
>>>>>>> 03f74aca74312dbeaf24d7e61306dd6a786dc3d0
