{
  "id": 2434377,
  "type": "Feature",
  "properties": {
    "tgn:hierarchy":[
        "tgn:2434377",
        "tgn:1000001",
        "tgn:7012149",
        "tgn:1003038",
        "tgn:7007517",
        "tgn:7029392"
    ],
    "tgn:id":2434377,
    "tgn:name":"Kendall Reservoir",
    "tgn:placetype":[
        "aat:300006191"
    ]
},
  "bbox": [],
  "geometry": {"coordinates":[-71.8833,42.3333],"type":"Point"}
}