{
  "id": 7014394,
  "type": "Feature",
  "properties": {
    "tgn:hierarchy":[
        "tgn:7014394",
        "tgn:1000001",
        "tgn:1002359",
        "tgn:7012149",
        "tgn:7007517",
        "tgn:7029392"
    ],
    "tgn:id":7014394,
    "tgn:name":"Peabody",
    "tgn:placetype":[
        "aat:300008347"
    ]
},
  "bbox": [],
  "geometry": {"coordinates":[-70.9167,42.5167],"type":"Point"}
}