{
  "id": 2008596,
  "type": "Feature",
  "properties": {
    "tgn:hierarchy":[
        "tgn:2008596",
        "tgn:1000001",
        "tgn:7016172",
        "tgn:2000122",
        "tgn:7012149",
        "tgn:7029392"
    ],
    "tgn:id":2008596,
    "tgn:name":"Jericho",
    "tgn:placetype":[
        "aat:300008347"
    ]
},
  "bbox": [],
  "geometry": {"coordinates":[-90.2167,35.2833],"type":"Point"}
}