{
  "id": 2325418,
  "type": "Feature",
  "properties": {
    "tgn:hierarchy":[
        "tgn:2325418",
        "tgn:1000001",
        "tgn:7012149",
        "tgn:2000490",
        "tgn:7007250",
        "tgn:7029392"
    ],
    "tgn:id":2325418,
    "tgn:name":"Ferry Hollow",
    "tgn:placetype":[
        "aat:300008761"
    ]
},
  "bbox": [],
  "geometry": {"coordinates":[-112.8167,42.75],"type":"Point"}
}