{
  "id": 2481287,
  "type": "Feature",
  "properties": {
    "tgn:hierarchy":[
        "tgn:2481287",
        "tgn:1000001",
        "tgn:2001480",
        "tgn:7012149",
        "tgn:7007709",
        "tgn:7029392"
    ],
    "tgn:id":2481287,
    "tgn:name":"Lambeth Mountain",
    "tgn:placetype":[
        "aat:300008798"
    ]
},
  "bbox": [],
  "geometry": {"coordinates":[-79.1167,35.7667],"type":"Point"}
}