{
  "id": 7081282,
  "type": "Feature",
  "properties": {
    "tgn:hierarchy":[
        "tgn:7081282",
        "tgn:7003692",
        "tgn:1000003",
        "tgn:7000084",
        "tgn:7029392"
    ],
    "tgn:id":7081282,
    "tgn:name":"Witznau",
    "tgn:placetype":[
        "aat:300008347"
    ]
},
  "bbox": [],
  "geometry": {"coordinates":[8.25,47.683333],"type":"Point"}
}