{
  "id": 7328311,
  "type": "Feature",
  "properties": {
    "tgn:hierarchy":[
        "tgn:7328311",
        "tgn:7002818",
        "tgn:1001647",
        "tgn:1000003",
        "tgn:1000095",
        "tgn:7029392"
    ],
    "tgn:id":7328311,
    "tgn:name":"Quintanar del Rey",
    "tgn:placetype":[
        "aat:300008347"
    ]
},
  "bbox": [],
  "geometry": {"coordinates":[-1.933333,39.333333],"type":"Point"}
}