{
  "id": 2292948,
  "type": "Feature",
  "properties": {
    "tgn:hierarchy":[
        "tgn:2292948",
        "tgn:1000001",
        "tgn:7012149",
        "tgn:1002911",
        "tgn:7007919",
        "tgn:7029392"
    ],
    "tgn:id":2292948,
    "tgn:name":"Dory",
    "tgn:placetype":[
        "aat:300008347"
    ]
},
  "bbox": [],
  "geometry": {"coordinates":[-77.0333,36.85],"type":"Point"}
}