{
  "id": 2167418,
  "type": "Feature",
  "properties": {
    "tgn:hierarchy":[
        "tgn:2167418",
        "tgn:1000001",
        "tgn:7016172",
        "tgn:7012149",
        "tgn:2000179",
        "tgn:7029392"
    ],
    "tgn:id":2167418,
    "tgn:name":"Big Creek",
    "tgn:placetype":[
        "aat:300008706"
    ]
},
  "bbox": [],
  "geometry": {"coordinates":[-93.4167,34.9833],"type":"Point"}
}