{
  "id": 2498261,
  "type": "Feature",
  "properties": {
    "tgn:hierarchy":[
        "tgn:2498261",
        "tgn:1000001",
        "tgn:7012149",
        "tgn:7007158",
        "tgn:2000240",
        "tgn:7029392"
    ],
    "tgn:id":2498261,
    "tgn:name":"Mc Cartney Mesa",
    "tgn:placetype":[
        "aat:300008798"
    ]
},
  "bbox": [],
  "geometry": {"coordinates":[-107.05,39.25],"type":"Point"}
}