{
  "id": 7268355,
  "type": "Feature",
  "properties": {
    "tgn:concordances":{
        "gn:id":"2748654"
    },
    "tgn:hierarchy":[
        "tgn:7268355",
        "tgn:1000003",
        "tgn:7006951",
        "tgn:7016845",
        "tgn:7029392"
    ],
    "tgn:id":7268355,
    "tgn:name:nl":"Penningsveer",
    "tgn:placetype":[
        "aat:300008347"
    ]
},
  "bbox": [],
  "geometry": {"coordinates":[4.683333,52.383333],"type":"Point"}
}