{
  "id": 7382118,
  "type": "Feature",
  "properties": {
    "tgn:hierarchy":[
        "tgn:7382118",
        "tgn:7005586",
        "tgn:1000001",
        "tgn:7005560",
        "tgn:7029392"
    ],
    "tgn:id":7382118,
    "tgn:name":"Los Pericos",
    "tgn:placetype":[
        "aat:300008347"
    ]
},
  "bbox": [],
  "geometry": {"coordinates":[-104.516667,20.566667],"type":"Point"}
}