<<<<<<< HEAD
{
  "id": 2334893,
  "type": "Feature",
  "properties": {
    "tgn:hierarchy":[
        "tgn:2334893",
        "tgn:1000001",
        "tgn:7012149",
        "tgn:2001145",
        "tgn:7007522",
        "tgn:7029392"
    ],
    "tgn:id":2334893,
    "tgn:name":"Forked Lake",
    "tgn:placetype":[
        "aat:300008680"
    ]
},
  "bbox": [],
  "geometry": {"coordinates":[-90.2667,34.4167],"type":"Point"}
}
=======
{"geometry":{"type":"Point","coordinates":[-90.266700,34.416700]},"type":"Feature","properties":{"hierarchy":["tgn:2334893","tgn:1000001","tgn:7012149","tgn:2001145","tgn:7007522","tgn:7029392"],"placetype":["aat:300008680"],"id":2334893,"name:xx":"Forked Lake"}}
>>>>>>> 03f74aca74312dbeaf24d7e61306dd6a786dc3d0
