{
  "id": 7238917,
  "type": "Feature",
  "properties": {
    "tgn:hierarchy":[
        "tgn:7238917",
        "tgn:7003457",
        "tgn:1000003",
        "tgn:1000063",
        "tgn:7018236",
        "tgn:7029392"
    ],
    "tgn:id":7238917,
    "tgn:name":"Hoeksken ter Hulst",
    "tgn:placetype":[
        "aat:300008347"
    ]
},
  "bbox": [],
  "geometry": {"coordinates":[3.784295,50.962688],"type":"Point"}
}