{
  "id": 2559626,
  "type": "Feature",
  "properties": {
    "tgn:hierarchy":[
        "tgn:2559626",
        "tgn:1002648",
        "tgn:1000001",
        "tgn:7019158",
        "tgn:7012149",
        "tgn:7007249",
        "tgn:7029392"
    ],
    "tgn:id":2559626,
    "tgn:name":"Opakalua Gulch",
    "tgn:placetype":[
        "aat:300008761"
    ]
},
  "bbox": [],
  "geometry": {"coordinates":[-156.1167,20.6667],"type":"Point"}
}