{
  "id": 2374767,
  "type": "Feature",
  "properties": {
    "tgn:hierarchy":[
        "tgn:2374767",
        "tgn:1000001",
        "tgn:7012149",
        "tgn:7007157",
        "tgn:2000190",
        "tgn:7029392"
    ],
    "tgn:id":2374767,
    "tgn:name":"Handy Camp Gulch",
    "tgn:placetype":[
        "aat:300008761"
    ]
},
  "bbox": [],
  "geometry": {"coordinates":[-122.8667,40.2167],"type":"Point"}
}