<<<<<<< HEAD
{
  "id": 7057522,
  "type": "Feature",
  "properties": {
    "tgn:hierarchy":[
        "tgn:7057522",
        "tgn:1003460",
        "tgn:1000003",
        "tgn:7009760",
        "tgn:1000080",
        "tgn:7029392"
    ],
    "tgn:id":7057522,
    "tgn:name":"Cacciarella, Punta",
    "tgn:placetype":[
        "aat:300386846"
    ]
},
  "bbox": [],
  "geometry": {"coordinates":[11.1,42.433333],"type":"Point"}
}
=======
{"geometry":{"type":"Point","coordinates":[11.100000,42.433333]},"type":"Feature","properties":{"hierarchy":["tgn:7057522","tgn:1003460","tgn:1000003","tgn:7009760","tgn:1000080","tgn:7029392"],"placetype":["aat:300386846"],"id":7057522,"name:xx":"Cacciarella, Punta"}}
>>>>>>> 03f74aca74312dbeaf24d7e61306dd6a786dc3d0
