{
  "id": 2591784,
  "type": "Feature",
  "properties": {
    "tgn:hierarchy":[
        "tgn:2591784",
        "tgn:1000001",
        "tgn:7012149",
        "tgn:2001226",
        "tgn:7007523",
        "tgn:7029392"
    ],
    "tgn:id":2591784,
    "tgn:name":"Pond Hollow",
    "tgn:placetype":[
        "aat:300008761"
    ]
},
  "bbox": [],
  "geometry": {"coordinates":[-92.15,36.6833],"type":"Point"}
}