{
  "id": 2236946,
  "type": "Feature",
  "properties": {
    "tgn:hierarchy":[
        "tgn:2236946",
        "tgn:7006450",
        "tgn:1000001",
        "tgn:2124077",
        "tgn:7012149",
        "tgn:7029392"
    ],
    "tgn:id":2236946,
    "tgn:name":"Chilkat Peninsula",
    "tgn:placetype":[
        "aat:300008850"
    ]
},
  "bbox": [],
  "geometry": {"coordinates":[-135.3667,59.1833],"type":"Point"}
}