{
  "id": 7064056,
  "type": "Feature",
  "properties": {
    "tgn:hierarchy":[
        "tgn:7064056",
        "tgn:7003669",
        "tgn:1000003",
        "tgn:7000084",
        "tgn:7029392"
    ],
    "tgn:id":7064056,
    "tgn:name":"Ansang",
    "tgn:placetype":[
        "aat:300008863"
    ]
},
  "bbox": [],
  "geometry": {"coordinates":[10.666667,48.383333],"type":"Point"}
}