{
  "id": 2708555,
  "type": "Feature",
  "properties": {
    "tgn:hierarchy":[
        "tgn:2708555",
        "tgn:1000001",
        "tgn:2002256",
        "tgn:7012149",
        "tgn:7013961",
        "tgn:7029392"
    ],
    "tgn:id":2708555,
    "tgn:name":"Sycamore Run",
    "tgn:placetype":[
        "aat:300008699"
    ]
},
  "bbox": [],
  "geometry": {"coordinates":[-80.7833,38.6667],"type":"Point"}
}