{
  "id": 7504229,
  "type": "Feature",
  "properties": {
    "tgn:hierarchy":[
        "tgn:7504229",
        "tgn:1008380",
        "tgn:7520093",
        "tgn:1000226",
        "tgn:1000006",
        "tgn:7029392"
    ],
    "tgn:id":7504229,
    "tgn:name:en":"Wakawaihine",
    "tgn:placetype":[
        "aat:300008699"
    ]
},
  "bbox": [],
  "geometry": {"coordinates":[176.416667,-40.566667],"type":"Point"}
}