{
  "id": 7109468,
  "type": "Feature",
  "properties": {
    "tgn:hierarchy":[
        "tgn:7109468",
        "tgn:1000003",
        "tgn:7003689",
        "tgn:7000084",
        "tgn:7029392"
    ],
    "tgn:id":7109468,
    "tgn:name":"Quer-Berg",
    "tgn:placetype":[
        "aat:300008777"
    ]
},
  "bbox": [],
  "geometry": {"coordinates":[10.616667,50.85],"type":"Point"}
}