{
  "id": 2371887,
  "type": "Feature",
  "properties": {
    "tgn:hierarchy":[
        "tgn:2371887",
        "tgn:1000001",
        "tgn:7012149",
        "tgn:2001854",
        "tgn:7007825",
        "tgn:7029392"
    ],
    "tgn:id":2371887,
    "tgn:name":"Haley Mountain",
    "tgn:placetype":[
        "aat:300008798"
    ]
},
  "bbox": [],
  "geometry": {"coordinates":[-84.8667,35.8667],"type":"Point"}
}