{
  "id": 7437652,
  "type": "Feature",
  "properties": {
    "tgn:hierarchy":[
        "tgn:7437652",
        "tgn:1000001",
        "tgn:7005597",
        "tgn:7005560",
        "tgn:7029392"
    ],
    "tgn:id":7437652,
    "tgn:name":"Seis de Enero",
    "tgn:placetype":[
        "aat:300008347"
    ]
},
  "bbox": [],
  "geometry": {"coordinates":[-98.016667,25.983333],"type":"Point"}
}