<<<<<<< HEAD
{
  "id": 2330012,
  "type": "Feature",
  "properties": {
    "tgn:hierarchy":[
        "tgn:2330012",
        "tgn:1000001",
        "tgn:7012149",
        "tgn:2001230",
        "tgn:7007523",
        "tgn:7029392"
    ],
    "tgn:id":2330012,
    "tgn:name":"Flag Spring",
    "tgn:placetype":[
        "aat:300008347"
    ]
},
  "bbox": [],
  "geometry": {"coordinates":[-91.6,38.0167],"type":"Point"}
}
=======
{"geometry":{"type":"Point","coordinates":[-91.600000,38.016700]},"type":"Feature","properties":{"hierarchy":["tgn:2330012","tgn:1000001","tgn:7012149","tgn:2001230","tgn:7007523","tgn:7029392"],"placetype":["aat:300008347"],"id":2330012,"name:xx":"Flag Spring"}}
>>>>>>> 03f74aca74312dbeaf24d7e61306dd6a786dc3d0
