{
  "id": 7424963,
  "type": "Feature",
  "properties": {
    "tgn:hierarchy":[
        "tgn:7424963",
        "tgn:1000001",
        "tgn:1001960",
        "tgn:7005560",
        "tgn:7029392"
    ],
    "tgn:id":7424963,
    "tgn:name":"Kan-Chun-Junga",
    "tgn:placetype":[
        "aat:300008347"
    ]
},
  "bbox": [],
  "geometry": {"coordinates":[-111.966667,29.65],"type":"Point"}
}