<<<<<<< HEAD
{
  "id": 7370952,
  "type": "Feature",
  "properties": {
    "tgn:hierarchy":[
        "tgn:7370952",
        "tgn:7005581",
        "tgn:1000001",
        "tgn:7005560",
        "tgn:7029392"
    ],
    "tgn:id":7370952,
    "tgn:name":"Guicharaibo",
    "tgn:placetype":[
        "aat:300008347"
    ]
},
  "bbox": [],
  "geometry": {"coordinates":[-108.6,27.916667],"type":"Point"}
}
=======
{"geometry":{"type":"Point","coordinates":[-108.600000,27.916667]},"type":"Feature","properties":{"hierarchy":["tgn:7370952","tgn:7005581","tgn:1000001","tgn:7005560","tgn:7029392"],"placetype":["aat:300008347"],"id":7370952,"name:xx":"Guicharaibo"}}
>>>>>>> 03f74aca74312dbeaf24d7e61306dd6a786dc3d0
