{
  "id": 2658751,
  "type": "Feature",
  "properties": {
    "tgn:hierarchy":[
        "tgn:2658751",
        "tgn:1000001",
        "tgn:7012149",
        "tgn:2000995",
        "tgn:7007520",
        "tgn:7029392"
    ],
    "tgn:id":2658751,
    "tgn:name":"Sherman Creek",
    "tgn:placetype":[
        "aat:300008706"
    ]
},
  "bbox": [],
  "geometry": {"coordinates":[-82.65,43.4333],"type":"Point"}
}