{
  "id": 1019471,
  "type": "Feature",
  "properties": {
    "tgn:hierarchy":[
        "tgn:1019471",
        "tgn:1001160",
        "tgn:7006477",
        "tgn:1000002",
        "tgn:7029392"
    ],
    "tgn:id":1019471,
    "tgn:name":"Francisco \u00c1lvarez",
    "tgn:placetype":[
        "aat:300008347"
    ]
},
  "bbox": [],
  "geometry": {"coordinates":[-58.8667,-34.6333],"type":"Point"}
}