{
  "id": 1064765,
  "type": "Feature",
  "properties": {
    "tgn:hierarchy":[
        "tgn:1064765",
        "tgn:7002443",
        "tgn:1000003",
        "tgn:7008050",
        "tgn:7008591",
        "tgn:7029392"
    ],
    "tgn:id":1064765,
    "tgn:name:en":"Newchurch",
    "tgn:placetype":[
        "aat:300008347"
    ]
},
  "bbox": [],
  "geometry": {"coordinates":[-3.15,52.15],"type":"Point"}
}