{
  "id": 7242205,
  "type": "Feature",
  "properties": {
    "tgn:hierarchy":[
        "tgn:7242205",
        "tgn:7007877",
        "tgn:1000003",
        "tgn:1000063",
        "tgn:4012014",
        "tgn:7029392"
    ],
    "tgn:id":7242205,
    "tgn:name":"Ferme de la Loge",
    "tgn:placetype":[
        "aat:300000206"
    ]
},
  "bbox": [],
  "geometry": {"coordinates":[4.25,50.283333],"type":"Point"}
}