{
  "id": 2283134,
  "type": "Feature",
  "properties": {
    "tgn:hierarchy":[
        "tgn:2283134",
        "tgn:1000001",
        "tgn:2001411",
        "tgn:7012149",
        "tgn:7007526",
        "tgn:7029392"
    ],
    "tgn:id":2283134,
    "tgn:name":"Delano",
    "tgn:placetype":[
        "aat:300008347"
    ]
},
  "bbox": [],
  "geometry": {"coordinates":[-114.2667,41.6667],"type":"Point"}
}