{
  "id": 1104537,
  "type": "Feature",
  "properties": {
    "tgn:hierarchy":[
        "tgn:1104537",
        "tgn:7003028",
        "tgn:1000003",
        "tgn:1000062",
        "tgn:7029392"
    ],
    "tgn:id":1104537,
    "tgn:name":"Elm",
    "tgn:placetype":[
        "aat:300008795"
    ]
},
  "bbox": [],
  "geometry": {"coordinates":[13.95,47.6667],"type":"Point"}
}