{
  "id": 7184385,
  "type": "Feature",
  "properties": {
    "tgn:hierarchy":[
        "tgn:7184385",
        "tgn:7000096",
        "tgn:1000003",
        "tgn:7000084",
        "tgn:7029392"
    ],
    "tgn:id":7184385,
    "tgn:name":"Gielsdorfer, Forst",
    "tgn:placetype":[
        "aat:300008863"
    ]
},
  "bbox": [],
  "geometry": {"coordinates":[13.866667,52.633333],"type":"Point"}
}