{
  "id": 7449678,
  "type": "Feature",
  "properties": {
    "tgn:hierarchy":[
        "tgn:7449678",
        "tgn:7002445",
        "tgn:1000003",
        "tgn:5000227",
        "tgn:7008591",
        "tgn:7029392"
    ],
    "tgn:id":7449678,
    "tgn:name:en":"Fladbury",
    "tgn:placetype":[
        "aat:300008347"
    ]
},
  "bbox": [],
  "geometry": {"coordinates":[-2.016667,52.116667],"type":"Point"}
}