{
  "id": 2762581,
  "type": "Feature",
  "properties": {
    "tgn:hierarchy":[
        "tgn:2762581",
        "tgn:7002659",
        "tgn:1000001",
        "tgn:7012149",
        "tgn:2000023",
        "tgn:7029392"
    ],
    "tgn:id":2762581,
    "tgn:name":"Westbrook",
    "tgn:placetype":[
        "aat:300008347"
    ]
},
  "bbox": [],
  "geometry": {"coordinates":[-87.3333,32.3167],"type":"Point"}
}