{
  "id": 2204005,
  "type": "Feature",
  "properties": {
    "tgn:hierarchy":[
        "tgn:2204005",
        "tgn:1000001",
        "tgn:7012149",
        "tgn:7007252",
        "tgn:7029392"
    ],
    "tgn:id":2204005,
    "tgn:name":"Bud Davis Hollow",
    "tgn:placetype":[
        "aat:300008761"
    ]
},
  "bbox": [],
  "geometry": {"coordinates":[-86.3667,39.3167],"type":"Point"}
}