{
  "id": 1005776,
  "type": "Feature",
  "properties": {
    "tgn:hierarchy":[
        "tgn:1005776",
        "tgn:7005575",
        "tgn:1000001",
        "tgn:7005560",
        "tgn:7029392"
    ],
    "tgn:id":1005776,
    "tgn:name":"Tulyehualco",
    "tgn:placetype":[
        "aat:300008347",
        "aat:300000745"
    ]
},
  "bbox": [],
  "geometry": {"coordinates":[-99.0167,19.25],"type":"Point"}
}