{
  "id": 7329521,
  "type": "Feature",
  "properties": {
    "tgn:hierarchy":[
        "tgn:7329521",
        "tgn:7002829",
        "tgn:1000003",
        "tgn:7002786",
        "tgn:1000095",
        "tgn:7029392"
    ],
    "tgn:id":7329521,
    "tgn:name":"Porto Noval, Punta",
    "tgn:placetype":[
        "aat:300386846"
    ]
},
  "bbox": [],
  "geometry": {"coordinates":[-7.75,43.75],"type":"Point"}
}