{
  "id": 7016893,
  "type": "Feature",
  "properties": {
    "tgn:hierarchy":[
        "tgn:7016893",
        "tgn:1000861",
        "tgn:1000004",
        "tgn:1000119",
        "tgn:7029392"
    ],
    "tgn:id":7016893,
    "tgn:name":"Sedom",
    "tgn:placetype":[
        "aat:300008347",
        "aat:300167671",
        "aat:300000833"
    ]
},
  "bbox": [],
  "geometry": {"coordinates":[35.3833,31.0667],"type":"Point"}
}