{
  "id": 2129214,
  "type": "Feature",
  "properties": {
    "tgn:hierarchy":[
        "tgn:2129214",
        "tgn:1000001",
        "tgn:7012149",
        "tgn:2000877",
        "tgn:7007256",
        "tgn:7029392"
    ],
    "tgn:id":2129214,
    "tgn:name":"Alhambra",
    "tgn:placetype":[
        "aat:300008347"
    ]
},
  "bbox": [],
  "geometry": {"coordinates":[-91.1167,30.1667],"type":"Point"}
}