{
  "id": 7289569,
  "type": "Feature",
  "properties": {
    "tgn:hierarchy":[
        "tgn:7289569",
        "tgn:1001623",
        "tgn:1000049",
        "tgn:1000002",
        "tgn:7029392"
    ],
    "tgn:id":7289569,
    "tgn:name":"Esperanza, Bah\u00eda",
    "tgn:placetype":[
        "aat:300132316"
    ]
},
  "bbox": [],
  "geometry": {"coordinates":[-73.016667,-48.416667],"type":"Point"}
}