<<<<<<< HEAD
{
  "id": 2409196,
  "type": "Feature",
  "properties": {
    "tgn:hierarchy":[
        "tgn:2409196",
        "tgn:1000001",
        "tgn:7012149",
        "tgn:1002965",
        "tgn:7007710",
        "tgn:7029392"
    ],
    "tgn:id":2409196,
    "tgn:name":"Ice Spring",
    "tgn:placetype":[
        "aat:300008697"
    ]
},
  "bbox": [],
  "geometry": {"coordinates":[-77.1667,40.95],"type":"Point"}
}
=======
{"geometry":{"type":"Point","coordinates":[-77.166700,40.950000]},"type":"Feature","properties":{"hierarchy":["tgn:2409196","tgn:1000001","tgn:7012149","tgn:1002965","tgn:7007710","tgn:7029392"],"placetype":["aat:300008697"],"id":2409196,"name:xx":"Ice Spring"}}
>>>>>>> 03f74aca74312dbeaf24d7e61306dd6a786dc3d0
