{
  "id": 2188241,
  "type": "Feature",
  "properties": {
    "tgn:hierarchy":[
        "tgn:2188241",
        "tgn:1000001",
        "tgn:2000199",
        "tgn:7012149",
        "tgn:7007158",
        "tgn:7029392"
    ],
    "tgn:id":2188241,
    "tgn:name":"Boss Lady Reservoir",
    "tgn:placetype":[
        "aat:300006191"
    ]
},
  "bbox": [],
  "geometry": {"coordinates":[-106.3167,38.55],"type":"Point"}
}