{
  "id": 7262750,
  "type": "Feature",
  "properties": {
    "tgn:hierarchy":[
        "tgn:7262750",
        "tgn:1000003",
        "tgn:7003627",
        "tgn:7016845",
        "tgn:7029392"
    ],
    "tgn:id":7262750,
    "tgn:name:nl":"Buurtsche Berg",
    "tgn:placetype":[
        "aat:300008777"
    ]
},
  "bbox": [],
  "geometry": {"coordinates":[5.55,51.983333],"type":"Point"}
}