{
  "id": 1134602,
  "type": "Feature",
  "properties": {
    "tgn:hierarchy":[
        "tgn:1134602",
        "tgn:1000001",
        "tgn:7012149",
        "tgn:1003042",
        "tgn:7007920",
        "tgn:7029392"
    ],
    "tgn:id":1134602,
    "tgn:name":"Simcoe Creek",
    "tgn:placetype":[
        "aat:300008706"
    ]
},
  "bbox": [],
  "geometry": {"coordinates":[-120.85,46.4333],"type":"Point"}
}