{
  "id": 7220340,
  "type": "Feature",
  "properties": {
    "tgn:hierarchy":[
        "tgn:7220340",
        "tgn:7002690",
        "tgn:7012056",
        "tgn:1000003",
        "tgn:1000074",
        "tgn:7029392"
    ],
    "tgn:id":7220340,
    "tgn:name":"Vath\u00edrrevma",
    "tgn:placetype":[
        "aat:300008347"
    ]
},
  "bbox": [],
  "geometry": {"coordinates":[23.616667,35.283333],"type":"Point"}
}