{
  "id": 7199914,
  "type": "Feature",
  "properties": {
    "tgn:hierarchy":[
        "tgn:7199914",
        "tgn:7003669",
        "tgn:1000003",
        "tgn:7000084",
        "tgn:7029392"
    ],
    "tgn:id":7199914,
    "tgn:name":"Eichel-Berg",
    "tgn:placetype":[
        "aat:300008777"
    ]
},
  "bbox": [],
  "geometry": {"coordinates":[9.816667,49.85],"type":"Point"}
}