{
  "id": 1052613,
  "type": "Feature",
  "properties": {
    "tgn:hierarchy":[
        "tgn:1052613",
        "tgn:1000004",
        "tgn:7012911",
        "tgn:7014786",
        "tgn:7029392"
    ],
    "tgn:id":1052613,
    "tgn:name":"Beyneu",
    "tgn:placetype":[
        "aat:300008347"
    ]
},
  "bbox": [],
  "geometry": {"coordinates":[55.0667,45.2667],"type":"Point"}
}