{
  "id": 7565956,
  "type": "Feature",
  "properties": {
    "tgn:hierarchy":[
        "tgn:7565956",
        "tgn:1000004",
        "tgn:7000198",
        "tgn:7016722",
        "tgn:7029392"
    ],
    "tgn:id":7565956,
    "tgn:name:en":"Jasu\u0101pur",
    "tgn:placetype":[
        "aat:300008347"
    ]
},
  "bbox": [],
  "geometry": {"coordinates":[79.299186,26.349129],"type":"Point"}
}