{
  "id": 7123697,
  "type": "Feature",
  "properties": {
    "tgn:hierarchy":[
        "tgn:7123697",
        "tgn:7003692",
        "tgn:1000003",
        "tgn:7000084",
        "tgn:7029392"
    ],
    "tgn:id":7123697,
    "tgn:name":"Neuschneller",
    "tgn:placetype":[
        "aat:300000206"
    ]
},
  "bbox": [],
  "geometry": {"coordinates":[9.916667,47.833333],"type":"Point"}
}