{
  "id": 7515051,
  "type": "Feature",
  "properties": {
    "tgn:hierarchy":[
        "tgn:7515051",
        "tgn:1009227",
        "tgn:1000226",
        "tgn:7016822",
        "tgn:1000006",
        "tgn:7029392"
    ],
    "tgn:id":7515051,
    "tgn:name:en":"Canister Cove",
    "tgn:placetype":[
        "aat:300132317"
    ]
},
  "bbox": [],
  "geometry": {"coordinates":[-176.216667,-44.333333],"type":"Point"}
}