{
  "id": 7164282,
  "type": "Feature",
  "properties": {
    "tgn:hierarchy":[
        "tgn:7164282",
        "tgn:1000003",
        "tgn:7003688",
        "tgn:7000084",
        "tgn:7029392"
    ],
    "tgn:id":7164282,
    "tgn:name":"Hunnigens\u00e4nde",
    "tgn:placetype":[
        "aat:300386970"
    ]
},
  "bbox": [],
  "geometry": {"coordinates":[8.483333,54.983333],"type":"Point"}
}