{
  "id": 2062418,
  "type": "Feature",
  "properties": {
    "tgn:hierarchy":[
        "tgn:2062418",
        "tgn:1000001",
        "tgn:2001361",
        "tgn:7012149",
        "tgn:7007525",
        "tgn:7029392"
    ],
    "tgn:id":2062418,
    "tgn:name":"Mullen",
    "tgn:placetype":[
        "aat:300008347"
    ]
},
  "bbox": [],
  "geometry": {"coordinates":[-101.0333,42.0333],"type":"Point"}
}