<<<<<<< HEAD
{
  "id": 7482385,
  "type": "Feature",
  "properties": {
    "tgn:hierarchy":[
        "tgn:7482385",
        "tgn:1000004",
        "tgn:7489179",
        "tgn:1000141",
        "tgn:7029392"
    ],
    "tgn:id":7482385,
    "tgn:name":"Meiyou Qiao",
    "tgn:placetype":[
        "aat:300007836"
    ]
},
  "bbox": [],
  "geometry": {"coordinates":[121.384167,24.444167],"type":"Point"}
}
=======
{"geometry":{"type":"Point","coordinates":[121.384167,24.444167]},"type":"Feature","properties":{"hierarchy":["tgn:7482385","tgn:1000004","tgn:7489179","tgn:1000141","tgn:7029392"],"placetype":["aat:300007836"],"id":7482385,"name:xx":"Meiyou Qiao"}}
>>>>>>> 03f74aca74312dbeaf24d7e61306dd6a786dc3d0
