{
  "id": 2214234,
  "type": "Feature",
  "properties": {
    "tgn:hierarchy":[
        "tgn:2214234",
        "tgn:7002659",
        "tgn:1000001",
        "tgn:7012149",
        "tgn:2000028",
        "tgn:7029392"
    ],
    "tgn:id":2214234,
    "tgn:name":"Cains Ridge Lake",
    "tgn:placetype":[
        "aat:300006191"
    ]
},
  "bbox": [],
  "geometry": {"coordinates":[-87.8333,33.65],"type":"Point"}
}