{
  "id": 1134047,
  "type": "Feature",
  "properties": {
    "tgn:hierarchy":[
        "tgn:1134047",
        "tgn:7003024",
        "tgn:1000003",
        "tgn:1000062",
        "tgn:7029392"
    ],
    "tgn:id":1134047,
    "tgn:name":"Olsabach",
    "tgn:placetype":[
        "aat:300008706"
    ]
},
  "bbox": [],
  "geometry": {"coordinates":[14.4167,46.9333],"type":"Point"}
}