{
  "id": 7466088,
  "type": "Feature",
  "properties": {
    "tgn:hierarchy":[
        "tgn:7466088",
        "tgn:7002444",
        "tgn:1000003",
        "tgn:7019152",
        "tgn:7008591",
        "tgn:7029392"
    ],
    "tgn:id":7466088,
    "tgn:name:en":"Blair Castle",
    "tgn:placetype":[
        "aat:300004792"
    ]
},
  "bbox": [],
  "geometry": {"coordinates":[-3.85,56.766667],"type":"Point"}
}