{
  "id": 7551916,
  "type": "Feature",
  "properties": {
    "tgn:hierarchy":[
        "tgn:7551916",
        "tgn:1000004",
        "tgn:7000198",
        "tgn:1001998",
        "tgn:7029392"
    ],
    "tgn:id":7551916,
    "tgn:name:en":"Chiahpui",
    "tgn:placetype":[
        "aat:300008347"
    ]
},
  "bbox": [],
  "geometry": {"coordinates":[93.18852,24.021957],"type":"Point"}
}