{
  "id": 2241900,
  "type": "Feature",
  "properties": {
    "tgn:hierarchy":[
        "tgn:2241900",
        "tgn:1000001",
        "tgn:7012149",
        "tgn:2001711",
        "tgn:7007708",
        "tgn:7029392"
    ],
    "tgn:id":2241900,
    "tgn:name":"Clawson",
    "tgn:placetype":[
        "aat:300008347"
    ]
},
  "bbox": [],
  "geometry": {"coordinates":[-122.65,42.1667],"type":"Point"}
}