{
  "id": 2508000,
  "type": "Feature",
  "properties": {
    "tgn:hierarchy":[
        "tgn:2508000",
        "tgn:1000001",
        "tgn:7012149",
        "tgn:1002379",
        "tgn:7007826",
        "tgn:7029392"
    ],
    "tgn:id":2508000,
    "tgn:name":"Middle Bayou",
    "tgn:placetype":[
        "aat:300008699"
    ]
},
  "bbox": [],
  "geometry": {"coordinates":[-95.7167,29.55],"type":"Point"}
}