{
  "id": 2044663,
  "type": "Feature",
  "properties": {
    "tgn:hierarchy":[
        "tgn:2044663",
        "tgn:2000918",
        "tgn:1000001",
        "tgn:7012149",
        "tgn:7007515",
        "tgn:7029392"
    ],
    "tgn:id":2044663,
    "tgn:name":"Crossman Corner",
    "tgn:placetype":[
        "aat:300008347",
        "aat:300387210"
    ]
},
  "bbox": [],
  "geometry": {"coordinates":[-70.05,43.9667],"type":"Point"}
}