{
  "id": 2378569,
  "type": "Feature",
  "properties": {
    "tgn:hierarchy":[
        "tgn:2378569",
        "tgn:1000001",
        "tgn:7012149",
        "tgn:2001869",
        "tgn:7007825",
        "tgn:7029392"
    ],
    "tgn:id":2378569,
    "tgn:name":"Harrison Prospect",
    "tgn:placetype":[
        "aat:300000390"
    ]
},
  "bbox": [],
  "geometry": {"coordinates":[-85.1667,35.15],"type":"Point"}
}