<<<<<<< HEAD
{
  "id": 2408563,
  "type": "Feature",
  "properties": {
    "tgn:hierarchy":[
        "tgn:2408563",
        "tgn:1000001",
        "tgn:7012149",
        "tgn:2002191",
        "tgn:7007919",
        "tgn:7029392"
    ],
    "tgn:id":2408563,
    "tgn:name":"Hutton Branch",
    "tgn:placetype":[
        "aat:300008699"
    ]
},
  "bbox": [],
  "geometry": {"coordinates":[-81.4,36.7333],"type":"Point"}
}
=======
{"geometry":{"type":"Point","coordinates":[-81.400000,36.733300]},"type":"Feature","properties":{"hierarchy":["tgn:2408563","tgn:1000001","tgn:7012149","tgn:2002191","tgn:7007919","tgn:7029392"],"placetype":["aat:300008699"],"id":2408563,"name:xx":"Hutton Branch"}}
>>>>>>> 03f74aca74312dbeaf24d7e61306dd6a786dc3d0
