{
  "id": 7208039,
  "type": "Feature",
  "properties": {
    "tgn:hierarchy":[
        "tgn:7208039",
        "tgn:1000003",
        "tgn:7003676",
        "tgn:7000084",
        "tgn:7029392"
    ],
    "tgn:id":7208039,
    "tgn:name":"B\u00fcngelshausen",
    "tgn:placetype":[
        "aat:300008347"
    ]
},
  "bbox": [],
  "geometry": {"coordinates":[9.083333,52.883333],"type":"Point"}
}