<<<<<<< HEAD
{
  "id": 7053286,
  "type": "Feature",
  "properties": {
    "tgn:hierarchy":[
        "tgn:7053286",
        "tgn:1001641",
        "tgn:1000003",
        "tgn:7003121",
        "tgn:1000080",
        "tgn:7029392"
    ],
    "tgn:id":7053286,
    "tgn:name":"Maggiore, Punta",
    "tgn:placetype":[
        "aat:300386846"
    ]
},
  "bbox": [],
  "geometry": {"coordinates":[8.35,39.083333],"type":"Point"}
}
=======
{"geometry":{"type":"Point","coordinates":[8.350000,39.083333]},"type":"Feature","properties":{"hierarchy":["tgn:7053286","tgn:1001641","tgn:1000003","tgn:7003121","tgn:1000080","tgn:7029392"],"placetype":["aat:300386846"],"id":7053286,"name:xx":"Maggiore, Punta"}}
>>>>>>> 03f74aca74312dbeaf24d7e61306dd6a786dc3d0
