{
  "id": 2621572,
  "type": "Feature",
  "properties": {
    "tgn:hierarchy":[
        "tgn:2621572",
        "tgn:1000001",
        "tgn:7012149",
        "tgn:2001709",
        "tgn:7007708",
        "tgn:7029392"
    ],
    "tgn:id":2621572,
    "tgn:name":"Roaring Spring",
    "tgn:placetype":[
        "aat:300008697"
    ]
},
  "bbox": [],
  "geometry": {"coordinates":[-119.3667,43.7833],"type":"Point"}
}