{
  "id": 2059559,
  "type": "Feature",
  "properties": {
    "tgn:hierarchy":[
        "tgn:2059559",
        "tgn:1000001",
        "tgn:2001182",
        "tgn:7012149",
        "tgn:7007523",
        "tgn:7029392"
    ],
    "tgn:id":2059559,
    "tgn:name":"Lisle",
    "tgn:placetype":[
        "aat:300008347",
        "aat:300387210"
    ]
},
  "bbox": [],
  "geometry": {"coordinates":[-94.5833,38.5333],"type":"Point"}
}