{
  "id": 2300687,
  "type": "Feature",
  "properties": {
    "tgn:hierarchy":[
        "tgn:2300687",
        "tgn:1000001",
        "tgn:7012149",
        "tgn:2002069",
        "tgn:7007826",
        "tgn:7029392"
    ],
    "tgn:id":2300687,
    "tgn:name":"Dunbar Tank",
    "tgn:placetype":[
        "aat:300006191"
    ]
},
  "bbox": [],
  "geometry": {"coordinates":[-98.8667,31.15],"type":"Point"}
}