{
  "id": 2452313,
  "type": "Feature",
  "properties": {
    "tgn:hierarchy":[
        "tgn:2452313",
        "tgn:1000001",
        "tgn:7012149",
        "tgn:1002582",
        "tgn:7007240",
        "tgn:7029392"
    ],
    "tgn:id":2452313,
    "tgn:name":"Little Bokeelia Bay",
    "tgn:placetype":[
        "aat:300132316"
    ]
},
  "bbox": [],
  "geometry": {"coordinates":[-82.1667,26.6833],"type":"Point"}
}