{
  "id": 2276821,
  "type": "Feature",
  "properties": {
    "tgn:hierarchy":[
        "tgn:2276821",
        "tgn:1000001",
        "tgn:7016172",
        "tgn:7012149",
        "tgn:2000139",
        "tgn:7029392"
    ],
    "tgn:id":2276821,
    "tgn:name":"Davis Bayou",
    "tgn:placetype":[
        "aat:300008699"
    ]
},
  "bbox": [],
  "geometry": {"coordinates":[-92.05,34.4833],"type":"Point"}
}