{
  "id": 2548742,
  "type": "Feature",
  "properties": {
    "tgn:hierarchy":[
        "tgn:2548742",
        "tgn:1000001",
        "tgn:2001431",
        "tgn:7012149",
        "tgn:7007566",
        "tgn:7029392"
    ],
    "tgn:id":2548742,
    "tgn:name":"North Pasture Tank",
    "tgn:placetype":[
        "aat:300006191"
    ]
},
  "bbox": [],
  "geometry": {"coordinates":[-107.95,34.75],"type":"Point"}
}