<<<<<<< HEAD
{
  "id": 7021424,
  "type": "Feature",
  "properties": {
    "tgn:hierarchy":[
        "tgn:7021424",
        "tgn:1000001",
        "tgn:7012149",
        "tgn:2002293",
        "tgn:7013961",
        "tgn:7029392"
    ],
    "tgn:id":7021424,
    "tgn:name":"Dry Fork",
    "tgn:placetype":[
        "aat:300008699"
    ]
},
  "bbox": [],
  "geometry": {"coordinates":[-81.35,38.6333],"type":"Point"}
}
=======
{"geometry":{"type":"Point","coordinates":[-81.350000,38.633300]},"type":"Feature","properties":{"hierarchy":["tgn:7021424","tgn:1000001","tgn:7012149","tgn:2002293","tgn:7013961","tgn:7029392"],"placetype":["aat:300008699"],"id":7021424,"name:xx":"Dry Fork"}}
>>>>>>> 03f74aca74312dbeaf24d7e61306dd6a786dc3d0
