{
  "id": 7021424,
  "type": "Feature",
  "properties": {
    "tgn:hierarchy":[
        "tgn:7021424",
        "tgn:1000001",
        "tgn:7012149",
        "tgn:2002293",
        "tgn:7013961",
        "tgn:7029392"
    ],
    "tgn:id":7021424,
    "tgn:name":"Dry Fork",
    "tgn:placetype":[
        "aat:300008699"
    ]
},
  "bbox": [],
  "geometry": {"coordinates":[-81.35,38.6333],"type":"Point"}
}