{
  "id": 2053499,
  "type": "Feature",
  "properties": {
    "tgn:hierarchy":[
        "tgn:2053499",
        "tgn:1000001",
        "tgn:7012149",
        "tgn:2000966",
        "tgn:7007520",
        "tgn:7029392"
    ],
    "tgn:id":2053499,
    "tgn:name":"Tobin Location",
    "tgn:placetype":[
        "aat:300008347"
    ]
},
  "bbox": [],
  "geometry": {"coordinates":[-88.35,46.0833],"type":"Point"}
}