{
  "id": 7125079,
  "type": "Feature",
  "properties": {
    "tgn:hierarchy":[
        "tgn:7125079",
        "tgn:1000003",
        "tgn:7003689",
        "tgn:7000084",
        "tgn:7029392"
    ],
    "tgn:id":7125079,
    "tgn:name":"Neumannsgrund",
    "tgn:placetype":[
        "aat:300008347"
    ]
},
  "bbox": [],
  "geometry": {"coordinates":[11.066667,50.466667],"type":"Point"}
}