<<<<<<< HEAD
{
  "id": 7353853,
  "type": "Feature",
  "properties": {
    "tgn:hierarchy":[
        "tgn:7353853",
        "tgn:7005580",
        "tgn:1000001",
        "tgn:7005560",
        "tgn:7029392"
    ],
    "tgn:id":7353853,
    "tgn:name":"Babilonia",
    "tgn:placetype":[
        "aat:300008347"
    ]
},
  "bbox": [],
  "geometry": {"coordinates":[-92.333333,14.766667],"type":"Point"}
}
=======
{"geometry":{"type":"Point","coordinates":[-92.333333,14.766667]},"type":"Feature","properties":{"hierarchy":["tgn:7353853","tgn:7005580","tgn:1000001","tgn:7005560","tgn:7029392"],"placetype":["aat:300008347"],"id":7353853,"name:xx":"Babilonia"}}
>>>>>>> 03f74aca74312dbeaf24d7e61306dd6a786dc3d0
