{
  "id": 2266889,
  "type": "Feature",
  "properties": {
    "tgn:hierarchy":[
        "tgn:2266889",
        "tgn:1000001",
        "tgn:7012149",
        "tgn:2001864",
        "tgn:7007825",
        "tgn:7029392"
    ],
    "tgn:id":2266889,
    "tgn:name":"Crescent View",
    "tgn:placetype":[
        "aat:300008347"
    ]
},
  "bbox": [],
  "geometry": {"coordinates":[-87.0167,35.15],"type":"Point"}
}