{
  "id": 7280846,
  "type": "Feature",
  "properties": {
    "tgn:hierarchy":[
        "tgn:7280846",
        "tgn:7002464",
        "tgn:1000049",
        "tgn:1000002",
        "tgn:7029392"
    ],
    "tgn:id":7280846,
    "tgn:name":"Santa Luc\u00eda, Cerro",
    "tgn:placetype":[
        "aat:300008795"
    ]
},
  "bbox": [],
  "geometry": {"coordinates":[-69.916667,-20.533333],"type":"Point"}
}