{
  "id": 7356100,
  "type": "Feature",
  "properties": {
    "tgn:hierarchy":[
        "tgn:7356100",
        "tgn:1000001",
        "tgn:1001906",
        "tgn:7005560",
        "tgn:7029392"
    ],
    "tgn:id":7356100,
    "tgn:name":"Camar\u00f3n, Punta",
    "tgn:placetype":[
        "aat:300386846"
    ]
},
  "bbox": [],
  "geometry": {"coordinates":[-105.266667,21.516667],"type":"Point"}
}