{
  "id": 7038889,
  "type": "Feature",
  "properties": {
    "tgn:hierarchy":[
        "tgn:7038889",
        "tgn:7003170",
        "tgn:1000003",
        "tgn:7003125",
        "tgn:1000080",
        "tgn:7029392"
    ],
    "tgn:id":7038889,
    "tgn:name":"Spina Nuova",
    "tgn:placetype":[
        "aat:300008347"
    ]
},
  "bbox": [],
  "geometry": {"coordinates":[12.85,42.85],"type":"Point"}
}