{
  "id": 7302099,
  "type": "Feature",
  "properties": {
    "tgn:hierarchy":[
        "tgn:7302099",
        "tgn:7002836",
        "tgn:7016622",
        "tgn:1000003",
        "tgn:1000095",
        "tgn:7029392"
    ],
    "tgn:id":7302099,
    "tgn:name":"M\u00e9dano, Punta del",
    "tgn:placetype":[
        "aat:300386846"
    ]
},
  "bbox": [],
  "geometry": {"coordinates":[-16.516667,28.033333],"type":"Point"}
}