<<<<<<< HEAD
{
  "id": 2152831,
  "type": "Feature",
  "properties": {
    "tgn:hierarchy":[
        "tgn:2152831",
        "tgn:1000001",
        "tgn:7012149",
        "tgn:2001909",
        "tgn:7007825",
        "tgn:7029392"
    ],
    "tgn:id":2152831,
    "tgn:name":"Bayside",
    "tgn:placetype":[
        "aat:300008347"
    ]
},
  "bbox": [],
  "geometry": {"coordinates":[-84.65,35.7333],"type":"Point"}
}
=======
{"geometry":{"type":"Point","coordinates":[-84.650000,35.733300]},"type":"Feature","properties":{"hierarchy":["tgn:2152831","tgn:1000001","tgn:7012149","tgn:2001909","tgn:7007825","tgn:7029392"],"placetype":["aat:300008347"],"id":2152831,"name:xx":"Bayside"}}
>>>>>>> 03f74aca74312dbeaf24d7e61306dd6a786dc3d0
