{
  "id": 2516369,
  "type": "Feature",
  "properties": {
    "tgn:hierarchy":[
        "tgn:2516369",
        "tgn:1000001",
        "tgn:2001704",
        "tgn:7012149",
        "tgn:7007708",
        "tgn:7029392"
    ],
    "tgn:id":2516369,
    "tgn:name":"Miner Gulch",
    "tgn:placetype":[
        "aat:300008761"
    ]
},
  "bbox": [],
  "geometry": {"coordinates":[-124.3333,42.1833],"type":"Point"}
}