{
  "id": 2029787,
  "type": "Feature",
  "properties": {
    "tgn:hierarchy":[
        "tgn:2029787",
        "tgn:1000001",
        "tgn:1002268",
        "tgn:7012149",
        "tgn:7007251",
        "tgn:7029392"
    ],
    "tgn:id":2029787,
    "tgn:name":"Radford",
    "tgn:placetype":[
        "aat:300008347",
        "aat:300387210"
    ]
},
  "bbox": [],
  "geometry": {"coordinates":[-89.0333,39.5667],"type":"Point"}
}