{
  "id": 7239058,
  "type": "Feature",
  "properties": {
    "tgn:hierarchy":[
        "tgn:7239058",
        "tgn:7003456",
        "tgn:1000003",
        "tgn:1000063",
        "tgn:7018236",
        "tgn:7029392"
    ],
    "tgn:id":7239058,
    "tgn:name":"Groot Schaddeken Dries",
    "tgn:placetype":[
        "aat:300008347"
    ]
},
  "bbox": [],
  "geometry": {"coordinates":[4.25,51.066667],"type":"Point"}
}