{
  "id": 7291098,
  "type": "Feature",
  "properties": {
    "tgn:hierarchy":[
        "tgn:7291098",
        "tgn:1001630",
        "tgn:1000049",
        "tgn:1000002",
        "tgn:7029392"
    ],
    "tgn:id":7291098,
    "tgn:name":"De Godoy",
    "tgn:placetype":[
        "aat:300008697"
    ]
},
  "bbox": [],
  "geometry": {"coordinates":[-69.533333,-26.733333],"type":"Point"}
}