{
  "id": 2439698,
  "type": "Feature",
  "properties": {
    "tgn:hierarchy":[
        "tgn:2439698",
        "tgn:1000001",
        "tgn:7012149",
        "tgn:7014612",
        "tgn:7007568",
        "tgn:7029392"
    ],
    "tgn:id":2439698,
    "tgn:name":"Kitchawan, Lake",
    "tgn:placetype":[
        "aat:300008680"
    ]
},
  "bbox": [],
  "geometry": {"coordinates":[-73.5333,41.2333],"type":"Point"}
}