{
  "id": 2429224,
  "type": "Feature",
  "properties": {
    "tgn:hierarchy":[
        "tgn:2429224",
        "tgn:1000001",
        "tgn:7012149",
        "tgn:2001202",
        "tgn:7007523",
        "tgn:7029392"
    ],
    "tgn:id":2429224,
    "tgn:name":"June-Bug Lake",
    "tgn:placetype":[
        "aat:300006191"
    ]
},
  "bbox": [],
  "geometry": {"coordinates":[-93.75,38.25],"type":"Point"}
}