<<<<<<< HEAD
{
  "id": 2152988,
  "type": "Feature",
  "properties": {
    "tgn:hierarchy":[
        "tgn:2152988",
        "tgn:1000001",
        "tgn:7014423",
        "tgn:7012149",
        "tgn:7007517",
        "tgn:7029392"
    ],
    "tgn:id":2152988,
    "tgn:name":"Beach Rocks",
    "tgn:placetype":[
        "aat:300132348"
    ]
},
  "bbox": [],
  "geometry": {"coordinates":[-70.7,41.7167],"type":"Point"}
}
=======
{"geometry":{"type":"Point","coordinates":[-70.700000,41.716700]},"type":"Feature","properties":{"hierarchy":["tgn:2152988","tgn:1000001","tgn:7014423","tgn:7012149","tgn:7007517","tgn:7029392"],"placetype":["aat:300132348"],"id":2152988,"name:xx":"Beach Rocks"}}
>>>>>>> 03f74aca74312dbeaf24d7e61306dd6a786dc3d0
