{
  "id": 2706138,
  "type": "Feature",
  "properties": {
    "tgn:hierarchy":[
        "tgn:2706138",
        "tgn:1000001",
        "tgn:2001014",
        "tgn:7012149",
        "tgn:7007521",
        "tgn:7029392"
    ],
    "tgn:id":2706138,
    "tgn:name":"Swallow Lake",
    "tgn:placetype":[
        "aat:300008680"
    ]
},
  "bbox": [],
  "geometry": {"coordinates":[-90.5667,48.0167],"type":"Point"}
}