<<<<<<< HEAD
{
  "id": 7025189,
  "type": "Feature",
  "properties": {
    "tgn:hierarchy":[
        "tgn:7025189",
        "tgn:7002445",
        "tgn:1000003",
        "tgn:7008118",
        "tgn:7008591",
        "tgn:7029392"
    ],
    "tgn:id":7025189,
    "tgn:name:ang":"Etewelle",
    "tgn:placetype":[
        "aat:300008347"
    ]
},
  "bbox": [],
  "geometry": {"coordinates":[-1.6,52.866667],"type":"Point"}
}
=======
{"geometry":{"type":"Point","coordinates":[-1.600000,52.866667]},"type":"Feature","properties":{"hierarchy":["tgn:7025189","tgn:7002445","tgn:1000003","tgn:7008118","tgn:7008591","tgn:7029392"],"placetype":["aat:300008347"],"id":7025189,"name:ang":"Etewelle"}}
>>>>>>> 03f74aca74312dbeaf24d7e61306dd6a786dc3d0
