<<<<<<< HEAD
{
  "id": 2152218,
  "type": "Feature",
  "properties": {
    "tgn:hierarchy":[
        "tgn:2152218",
        "tgn:1000001",
        "tgn:7013368",
        "tgn:7012149",
        "tgn:7007709",
        "tgn:7029392"
    ],
    "tgn:id":2152218,
    "tgn:name":"Bay Branch",
    "tgn:placetype":[
        "aat:300008699"
    ]
},
  "bbox": [],
  "geometry": {"coordinates":[-77.1,35.4667],"type":"Point"}
}
=======
{"geometry":{"type":"Point","coordinates":[-77.100000,35.466700]},"type":"Feature","properties":{"hierarchy":["tgn:2152218","tgn:1000001","tgn:7013368","tgn:7012149","tgn:7007709","tgn:7029392"],"placetype":["aat:300008699"],"id":2152218,"name:xx":"Bay Branch"}}
>>>>>>> 03f74aca74312dbeaf24d7e61306dd6a786dc3d0
