{
  "id": 7517101,
  "type": "Feature",
  "properties": {
    "tgn:hierarchy":[
        "tgn:7517101",
        "tgn:1008380",
        "tgn:7520093",
        "tgn:1000226",
        "tgn:1000006",
        "tgn:7029392"
    ],
    "tgn:id":7517101,
    "tgn:name:en":"Mangamahoe",
    "tgn:placetype":[
        "aat:300008347"
    ]
},
  "bbox": [],
  "geometry": {"coordinates":[175.716667,-40.733333],"type":"Point"}
}