{
  "id": 7170125,
  "type": "Feature",
  "properties": {
    "tgn:hierarchy":[
        "tgn:7170125",
        "tgn:7003669",
        "tgn:1000003",
        "tgn:7000084",
        "tgn:7029392"
    ],
    "tgn:id":7170125,
    "tgn:name":"Hochbauer",
    "tgn:placetype":[
        "aat:300000206"
    ]
},
  "bbox": [],
  "geometry": {"coordinates":[11.816667,48.616667],"type":"Point"}
}