<<<<<<< HEAD
{
  "id": 7371557,
  "type": "Feature",
  "properties": {
    "tgn:hierarchy":[
        "tgn:7371557",
        "tgn:7005581",
        "tgn:1000001",
        "tgn:7005560",
        "tgn:7029392"
    ],
    "tgn:id":7371557,
    "tgn:name":"Rancho La Cumbre",
    "tgn:placetype":[
        "aat:300000241"
    ]
},
  "bbox": [],
  "geometry": {"coordinates":[-108.45,27.7],"type":"Point"}
}
=======
{"geometry":{"type":"Point","coordinates":[-108.450000,27.700000]},"type":"Feature","properties":{"hierarchy":["tgn:7371557","tgn:7005581","tgn:1000001","tgn:7005560","tgn:7029392"],"placetype":["aat:300000241"],"id":7371557,"name:xx":"Rancho La Cumbre"}}
>>>>>>> 03f74aca74312dbeaf24d7e61306dd6a786dc3d0
