<<<<<<< HEAD
{
  "id": 2768634,
  "type": "Feature",
  "properties": {
    "tgn:hierarchy":[
        "tgn:2768634",
        "tgn:1000001",
        "tgn:7012149",
        "tgn:7016020",
        "tgn:7007710",
        "tgn:7029392"
    ],
    "tgn:id":2768634,
    "tgn:name":"Whiting Run",
    "tgn:placetype":[
        "aat:300008699"
    ]
},
  "bbox": [],
  "geometry": {"coordinates":[-78.8167,41.8],"type":"Point"}
}
=======
{"geometry":{"type":"Point","coordinates":[-78.816700,41.800000]},"type":"Feature","properties":{"hierarchy":["tgn:2768634","tgn:1000001","tgn:7012149","tgn:7016020","tgn:7007710","tgn:7029392"],"placetype":["aat:300008699"],"id":2768634,"name:xx":"Whiting Run"}}
>>>>>>> 03f74aca74312dbeaf24d7e61306dd6a786dc3d0
