{
  "id": 7199743,
  "type": "Feature",
  "properties": {
    "tgn:hierarchy":[
        "tgn:7199743",
        "tgn:7003669",
        "tgn:1000003",
        "tgn:7000084",
        "tgn:7029392"
    ],
    "tgn:id":7199743,
    "tgn:name":"Edling",
    "tgn:placetype":[
        "aat:300008347"
    ]
},
  "bbox": [],
  "geometry": {"coordinates":[12.55,48.033333],"type":"Point"}
}