{
  "id": 7502516,
  "type": "Feature",
  "properties": {
    "tgn:hierarchy":[
        "tgn:7502516",
        "tgn:1000004",
        "tgn:7001009",
        "tgn:1000141",
        "tgn:7029392"
    ],
    "tgn:id":7502516,
    "tgn:name":"Dongbiankeng Xi",
    "tgn:placetype":[
        "aat:300008699"
    ]
},
  "bbox": [],
  "geometry": {"coordinates":[120.765817,24.108711],"type":"Point"}
}