{
  "id": 2409512,
  "type": "Feature",
  "properties": {
    "tgn:hierarchy":[
        "tgn:2409512",
        "tgn:1000001",
        "tgn:7012149",
        "tgn:2000970",
        "tgn:7007520",
        "tgn:7029392"
    ],
    "tgn:id":2409512,
    "tgn:name":"Idlewild Lake",
    "tgn:placetype":[
        "aat:300008680"
    ]
},
  "bbox": [],
  "geometry": {"coordinates":[-85.7833,43.8833],"type":"Point"}
}