<<<<<<< HEAD
{
  "id": 2409512,
  "type": "Feature",
  "properties": {
    "tgn:hierarchy":[
        "tgn:2409512",
        "tgn:1000001",
        "tgn:7012149",
        "tgn:2000970",
        "tgn:7007520",
        "tgn:7029392"
    ],
    "tgn:id":2409512,
    "tgn:name":"Idlewild Lake",
    "tgn:placetype":[
        "aat:300008680"
    ]
},
  "bbox": [],
  "geometry": {"coordinates":[-85.7833,43.8833],"type":"Point"}
}
=======
{"geometry":{"type":"Point","coordinates":[-85.783300,43.883300]},"type":"Feature","properties":{"hierarchy":["tgn:2409512","tgn:1000001","tgn:7012149","tgn:2000970","tgn:7007520","tgn:7029392"],"placetype":["aat:300008680"],"id":2409512,"name:xx":"Idlewild Lake"}}
>>>>>>> 03f74aca74312dbeaf24d7e61306dd6a786dc3d0
