{
  "id": 2183298,
  "type": "Feature",
  "properties": {
    "tgn:hierarchy":[
        "tgn:2183298",
        "tgn:7002659",
        "tgn:1000001",
        "tgn:7012149",
        "tgn:2000047",
        "tgn:7029392"
    ],
    "tgn:id":2183298,
    "tgn:name":"Bluff Cave",
    "tgn:placetype":[
        "aat:300008746"
    ]
},
  "bbox": [],
  "geometry": {"coordinates":[-86.2833,34.45],"type":"Point"}
}