{
  "id": 2644760,
  "type": "Feature",
  "properties": {
    "tgn:hierarchy":[
        "tgn:2644760",
        "tgn:1000001",
        "tgn:7012149",
        "tgn:2001867",
        "tgn:7007825",
        "tgn:7029392"
    ],
    "tgn:id":2644760,
    "tgn:name":"Sartain Spring",
    "tgn:placetype":[
        "aat:300008697"
    ]
},
  "bbox": [],
  "geometry": {"coordinates":[-85.8333,35.3333],"type":"Point"}
}