{
  "id": 2320213,
  "type": "Feature",
  "properties": {
    "tgn:hierarchy":[
        "tgn:2320213",
        "tgn:1000001",
        "tgn:7012149",
        "tgn:2001834",
        "tgn:7007713",
        "tgn:7029392"
    ],
    "tgn:id":2320213,
    "tgn:name":"Evarts, Lake",
    "tgn:placetype":[
        "aat:300008680"
    ]
},
  "bbox": [],
  "geometry": {"coordinates":[-100.3167,45.4667],"type":"Point"}
}