{
  "id": 2079699,
  "type": "Feature",
  "properties": {
    "tgn:hierarchy":[
        "tgn:2079699",
        "tgn:1000001",
        "tgn:7012149",
        "tgn:1002797",
        "tgn:7007706",
        "tgn:7029392"
    ],
    "tgn:id":2079699,
    "tgn:name":"Garrettsville",
    "tgn:placetype":[
        "aat:300008347"
    ]
},
  "bbox": [],
  "geometry": {"coordinates":[-81.0833,41.2833],"type":"Point"}
}