{
  "id": 7531327,
  "type": "Feature",
  "properties": {
    "tgn:hierarchy":[
        "tgn:7531327",
        "tgn:7001242",
        "tgn:1001075",
        "tgn:7016833",
        "tgn:7029392"
    ],
    "tgn:id":7531327,
    "tgn:name:en":"Tur'at Shisht",
    "tgn:placetype":[
        "aat:300006075"
    ]
},
  "bbox": [],
  "geometry": {"coordinates":[30.750711,30.820534],"type":"Point"}
}