{
  "id": 2092450,
  "type": "Feature",
  "properties": {
    "tgn:hierarchy":[
        "tgn:2092450",
        "tgn:1000001",
        "tgn:7012149",
        "tgn:1002729",
        "tgn:7007710",
        "tgn:7029392"
    ],
    "tgn:id":2092450,
    "tgn:name":"Richmond",
    "tgn:placetype":[
        "aat:300008347"
    ]
},
  "bbox": [],
  "geometry": {"coordinates":[-75.1333,40.8333],"type":"Point"}
}