<<<<<<< HEAD
{
  "id": 2154860,
  "type": "Feature",
  "properties": {
    "tgn:hierarchy":[
        "tgn:2154860",
        "tgn:1000001",
        "tgn:7012149",
        "tgn:2000839",
        "tgn:7007255",
        "tgn:7029392"
    ],
    "tgn:id":2154860,
    "tgn:name":"Bear Hollow",
    "tgn:placetype":[
        "aat:300008761"
    ]
},
  "bbox": [],
  "geometry": {"coordinates":[-84.6333,36.95],"type":"Point"}
}
=======
{"geometry":{"type":"Point","coordinates":[-84.633300,36.950000]},"type":"Feature","properties":{"hierarchy":["tgn:2154860","tgn:1000001","tgn:7012149","tgn:2000839","tgn:7007255","tgn:7029392"],"placetype":["aat:300008761"],"id":2154860,"name:xx":"Bear Hollow"}}
>>>>>>> 03f74aca74312dbeaf24d7e61306dd6a786dc3d0
