<<<<<<< HEAD
{
  "id": 2764715,
  "type": "Feature",
  "properties": {
    "tgn:hierarchy":[
        "tgn:2764715",
        "tgn:1000001",
        "tgn:2001261",
        "tgn:7012149",
        "tgn:7007524",
        "tgn:7029392"
    ],
    "tgn:id":2764715,
    "tgn:name":"Whiskey Coulee",
    "tgn:placetype":[
        "aat:300008761"
    ]
},
  "bbox": [],
  "geometry": {"coordinates":[-108.0,45.15],"type":"Point"}
}
=======
{"geometry":{"type":"Point","coordinates":[-108.000000,45.150000]},"type":"Feature","properties":{"hierarchy":["tgn:2764715","tgn:1000001","tgn:2001261","tgn:7012149","tgn:7007524","tgn:7029392"],"placetype":["aat:300008761"],"id":2764715,"name:xx":"Whiskey Coulee"}}
>>>>>>> 03f74aca74312dbeaf24d7e61306dd6a786dc3d0
