{
  "id": 2692187,
  "type": "Feature",
  "properties": {
    "tgn:hierarchy":[
        "tgn:2692187",
        "tgn:1000001",
        "tgn:7012149",
        "tgn:2000472",
        "tgn:7007250",
        "tgn:7029392"
    ],
    "tgn:id":2692187,
    "tgn:name":"Station Creek",
    "tgn:placetype":[
        "aat:300008706"
    ]
},
  "bbox": [],
  "geometry": {"coordinates":[-111.6833,42.1833],"type":"Point"}
}