{
  "id": 1088726,
  "type": "Feature",
  "properties": {
    "tgn:hierarchy":[
        "tgn:1088726",
        "tgn:7001242",
        "tgn:1000972",
        "tgn:1000158",
        "tgn:7029392"
    ],
    "tgn:id":1088726,
    "tgn:name":"Owando",
    "tgn:placetype":[
        "aat:300008347",
        "aat:300387223",
        "aat:300008375"
    ]
},
  "bbox": [],
  "geometry": {"coordinates":[15.7333,-0.45],"type":"Point"}
}