{
  "id": 7278677,
  "type": "Feature",
  "properties": {
    "tgn:hierarchy":[
        "tgn:7278677",
        "tgn:1001699",
        "tgn:1000049",
        "tgn:1000002",
        "tgn:7029392"
    ],
    "tgn:id":7278677,
    "tgn:name":"Punie",
    "tgn:placetype":[
        "aat:300008347"
    ]
},
  "bbox": [],
  "geometry": {"coordinates":[-73.394722,-42.168056],"type":"Point"}
}