{
  "id": 7285570,
  "type": "Feature",
  "properties": {
    "tgn:hierarchy":[
        "tgn:7285570",
        "tgn:7016598",
        "tgn:1000049",
        "tgn:1000002",
        "tgn:7029392"
    ],
    "tgn:id":7285570,
    "tgn:name":"Playitas, Quebrada de",
    "tgn:placetype":[
        "aat:300266554",
        "aat:300008699"
    ]
},
  "bbox": [],
  "geometry": {"coordinates":[-68.666667,-21.683333],"type":"Point"}
}