{
  "id": 1107628,
  "type": "Feature",
  "properties": {
    "tgn:hierarchy":[
        "tgn:1107628",
        "tgn:1000001",
        "tgn:7012149",
        "tgn:2000217",
        "tgn:7007158",
        "tgn:7029392"
    ],
    "tgn:id":1107628,
    "tgn:name":"West Elk Peak",
    "tgn:placetype":[
        "aat:300008798"
    ]
},
  "bbox": [],
  "geometry": {"coordinates":[-107.1833,38.7167],"type":"Point"}
}