{
  "id": 7513077,
  "type": "Feature",
  "properties": {
    "tgn:hierarchy":[
        "tgn:7513077",
        "tgn:1009227",
        "tgn:1000226",
        "tgn:1000006",
        "tgn:7016850",
        "tgn:7029392"
    ],
    "tgn:id":7513077,
    "tgn:name:en":"Hall Creek",
    "tgn:placetype":[
        "aat:300008699"
    ]
},
  "bbox": [],
  "geometry": {"coordinates":[171.316667,-42.95],"type":"Point"}
}