{
  "id": 7546263,
  "type": "Feature",
  "properties": {
    "tgn:hierarchy":[
        "tgn:7546263",
        "tgn:1000004",
        "tgn:1001869",
        "tgn:7000198",
        "tgn:7029392"
    ],
    "tgn:id":7546263,
    "tgn:name:en":"\u0100nakhol",
    "tgn:placetype":[
        "aat:300007783"
    ]
},
  "bbox": [],
  "geometry": {"coordinates":[72.410263,23.276773],"type":"Point"}
}