{
  "id": 2567475,
  "type": "Feature",
  "properties": {
    "tgn:hierarchy":[
        "tgn:2567475",
        "tgn:1000001",
        "tgn:7012149",
        "tgn:7007919",
        "tgn:7029392"
    ],
    "tgn:id":2567475,
    "tgn:name":"Paper Mill Creek",
    "tgn:placetype":[
        "aat:300008706"
    ]
},
  "bbox": [],
  "geometry": {"coordinates":[-76.6833,37.2667],"type":"Point"}
}