{
  "id": 1077988,
  "type": "Feature",
  "properties": {
    "tgn:hierarchy":[
        "tgn:1077988",
        "tgn:1000004",
        "tgn:7003970",
        "tgn:1008168",
        "tgn:1000116",
        "tgn:7029392"
    ],
    "tgn:id":1077988,
    "tgn:name":"Lelintah",
    "tgn:placetype":[
        "aat:300008347"
    ]
},
  "bbox": [],
  "geometry": {"coordinates":[130.2667,-2.05],"type":"Point"}
}