{
  "id": 7114245,
  "type": "Feature",
  "properties": {
    "tgn:hierarchy":[
        "tgn:7114245",
        "tgn:1000003",
        "tgn:7003685",
        "tgn:7000084",
        "tgn:7029392"
    ],
    "tgn:id":7114245,
    "tgn:name":"Rentzm\u00fchlenh\u00e4user",
    "tgn:placetype":[
        "aat:300008347"
    ]
},
  "bbox": [],
  "geometry": {"coordinates":[12.166667,50.583333],"type":"Point"}
}