{
  "id": 7554334,
  "type": "Feature",
  "properties": {
    "tgn:hierarchy":[
        "tgn:7554334",
        "tgn:1000004",
        "tgn:7000198",
        "tgn:7016788",
        "tgn:7029392"
    ],
    "tgn:id":7554334,
    "tgn:name:en":"Mehidpur",
    "tgn:placetype":[
        "aat:300008347"
    ]
},
  "bbox": [],
  "geometry": {"coordinates":[75.666667,23.816667],"type":"Point"}
}