{
  "id": 2482433,
  "type": "Feature",
  "properties": {
    "tgn:hierarchy":[
        "tgn:2482433",
        "tgn:1000001",
        "tgn:7012149",
        "tgn:1002800",
        "tgn:7007710",
        "tgn:7029392"
    ],
    "tgn:id":2482433,
    "tgn:name":"Laninger Creek",
    "tgn:placetype":[
        "aat:300008706"
    ]
},
  "bbox": [],
  "geometry": {"coordinates":[-78.1667,41.7333],"type":"Point"}
}