<<<<<<< HEAD
{
  "id": 7375672,
  "type": "Feature",
  "properties": {
    "tgn:hierarchy":[
        "tgn:7375672",
        "tgn:1001853",
        "tgn:1000001",
        "tgn:7005560",
        "tgn:7029392"
    ],
    "tgn:id":7375672,
    "tgn:name":"La Ratita, Loma de",
    "tgn:placetype":[
        "aat:300008777"
    ]
},
  "bbox": [],
  "geometry": {"coordinates":[-101.166667,27.0],"type":"Point"}
}
=======
{"geometry":{"type":"Point","coordinates":[-101.166667,27.000000]},"type":"Feature","properties":{"hierarchy":["tgn:7375672","tgn:1001853","tgn:1000001","tgn:7005560","tgn:7029392"],"placetype":["aat:300008777"],"id":7375672,"name:xx":"La Ratita, Loma de"}}
>>>>>>> 03f74aca74312dbeaf24d7e61306dd6a786dc3d0
