{
  "id": 7361720,
  "type": "Feature",
  "properties": {
    "tgn:hierarchy":[
        "tgn:7361720",
        "tgn:1000001",
        "tgn:7005590",
        "tgn:7005560",
        "tgn:7029392"
    ],
    "tgn:id":7361720,
    "tgn:name":"El Junco",
    "tgn:placetype":[
        "aat:300008347"
    ]
},
  "bbox": [],
  "geometry": {"coordinates":[-102.266667,19.05],"type":"Point"}
}