{
  "id": 2263720,
  "type": "Feature",
  "properties": {
    "tgn:hierarchy":[
        "tgn:2263720",
        "tgn:1000001",
        "tgn:2002107",
        "tgn:7012149",
        "tgn:7007827",
        "tgn:7029392"
    ],
    "tgn:id":2263720,
    "tgn:name":"Coyote Canyon",
    "tgn:placetype":[
        "aat:300008761"
    ]
},
  "bbox": [],
  "geometry": {"coordinates":[-110.4833,40.0333],"type":"Point"}
}