{
  "id": 2223983,
  "type": "Feature",
  "properties": {
    "tgn:hierarchy":[
        "tgn:2223983",
        "tgn:1000001",
        "tgn:7012149",
        "tgn:2002273",
        "tgn:7013961",
        "tgn:7029392"
    ],
    "tgn:id":2223983,
    "tgn:name":"Cartwright Branch",
    "tgn:placetype":[
        "aat:300008699"
    ]
},
  "bbox": [],
  "geometry": {"coordinates":[-81.7333,37.7667],"type":"Point"}
}