{
  "id": 2527746,
  "type": "Feature",
  "properties": {
    "tgn:hierarchy":[
        "tgn:2527746",
        "tgn:1000001",
        "tgn:7012149",
        "tgn:2001497",
        "tgn:7007709",
        "tgn:7029392"
    ],
    "tgn:id":2527746,
    "tgn:name":"Mountain Creek",
    "tgn:placetype":[
        "aat:300008706"
    ]
},
  "bbox": [],
  "geometry": {"coordinates":[-83.7667,35.3667],"type":"Point"}
}