{
  "id": 1055296,
  "type": "Feature",
  "properties": {
    "tgn:hierarchy":[
        "tgn:1055296",
        "tgn:1000004",
        "tgn:7011572",
        "tgn:7018214",
        "tgn:7002435",
        "tgn:7029392"
    ],
    "tgn:id":1055296,
    "tgn:name":"Kingisepp",
    "tgn:placetype":[
        "aat:300008347"
    ]
},
  "bbox": [],
  "geometry": {"coordinates":[28.6667,59.3667],"type":"Point"}
}