{
  "id": 2691717,
  "type": "Feature",
  "properties": {
    "tgn:hierarchy":[
        "tgn:2691717",
        "tgn:1000001",
        "tgn:7012149",
        "tgn:2001764",
        "tgn:7007712",
        "tgn:7029392"
    ],
    "tgn:id":2691717,
    "tgn:name":"Starlite",
    "tgn:placetype":[
        "aat:300008347"
    ]
},
  "bbox": [],
  "geometry": {"coordinates":[-80.9667,33.9333],"type":"Point"}
}