<<<<<<< HEAD
{
  "id": 2257466,
  "type": "Feature",
  "properties": {
    "tgn:hierarchy":[
        "tgn:2257466",
        "tgn:1000001",
        "tgn:7006451",
        "tgn:2000092",
        "tgn:7012149",
        "tgn:7029392"
    ],
    "tgn:id":2257466,
    "tgn:name":"Coronado Butte",
    "tgn:placetype":[
        "aat:300008798"
    ]
},
  "bbox": [],
  "geometry": {"coordinates":[-111.9333,36.0],"type":"Point"}
}
=======
{"geometry":{"type":"Point","coordinates":[-111.933300,36.000000]},"type":"Feature","properties":{"hierarchy":["tgn:2257466","tgn:1000001","tgn:7006451","tgn:2000092","tgn:7012149","tgn:7029392"],"placetype":["aat:300008798"],"id":2257466,"name:xx":"Coronado Butte"}}
>>>>>>> 03f74aca74312dbeaf24d7e61306dd6a786dc3d0
