{
  "id": 2356611,
  "type": "Feature",
  "properties": {
    "tgn:hierarchy":[
        "tgn:2356611",
        "tgn:1000001",
        "tgn:7012149",
        "tgn:2002186",
        "tgn:7007919",
        "tgn:7029392"
    ],
    "tgn:id":2356611,
    "tgn:name":"Gordons Cave",
    "tgn:placetype":[
        "aat:300008746"
    ]
},
  "bbox": [],
  "geometry": {"coordinates":[-79.3167,37.9833],"type":"Point"}
}