{
  "id": 1078046,
  "type": "Feature",
  "properties": {
    "tgn:hierarchy":[
        "tgn:1078046",
        "tgn:1000004",
        "tgn:1001547",
        "tgn:1000116",
        "tgn:7029392"
    ],
    "tgn:id":1078046,
    "tgn:name":"Lumu",
    "tgn:placetype":[
        "aat:300008347"
    ]
},
  "bbox": [],
  "geometry": {"coordinates":[119.15,-2.1833],"type":"Point"}
}