{
  "id": 2321823,
  "type": "Feature",
  "properties": {
    "tgn:hierarchy":[
        "tgn:2321823",
        "tgn:1000001",
        "tgn:7012149",
        "tgn:2001284",
        "tgn:7007524",
        "tgn:7029392"
    ],
    "tgn:id":2321823,
    "tgn:name":"Faith Gulch",
    "tgn:placetype":[
        "aat:300008761"
    ]
},
  "bbox": [],
  "geometry": {"coordinates":[-112.4333,46.7167],"type":"Point"}
}