{
  "id": 2139297,
  "type": "Feature",
  "properties": {
    "tgn:hierarchy":[
        "tgn:2139297",
        "tgn:1000001",
        "tgn:7012149",
        "tgn:2001454",
        "tgn:7007566",
        "tgn:7029392"
    ],
    "tgn:id":2139297,
    "tgn:name":"Aspen Basin",
    "tgn:placetype":[
        "aat:300386845"
    ]
},
  "bbox": [],
  "geometry": {"coordinates":[-105.7833,35.7833],"type":"Point"}
}