{
  "id": 7225282,
  "type": "Feature",
  "properties": {
    "tgn:hierarchy":[
        "tgn:7225282",
        "tgn:7011161",
        "tgn:7002674",
        "tgn:1000003",
        "tgn:1000074",
        "tgn:7029392"
    ],
    "tgn:id":7225282,
    "tgn:name":"N\u00e9nita",
    "tgn:placetype":[
        "aat:300008347"
    ]
},
  "bbox": [],
  "geometry": {"coordinates":[26.093056,38.238889],"type":"Point"}
}