{
  "id": 7200446,
  "type": "Feature",
  "properties": {
    "tgn:hierarchy":[
        "tgn:7200446",
        "tgn:1000003",
        "tgn:7003677",
        "tgn:7000084",
        "tgn:7029392"
    ],
    "tgn:id":7200446,
    "tgn:name":"Eckringhausen",
    "tgn:placetype":[
        "aat:300008347"
    ]
},
  "bbox": [],
  "geometry": {"coordinates":[7.216667,51.116667],"type":"Point"}
}