{
  "id": 7408104,
  "type": "Feature",
  "properties": {
    "tgn:hierarchy":[
        "tgn:7408104",
        "tgn:1000001",
        "tgn:1001893",
        "tgn:7005560",
        "tgn:7029392"
    ],
    "tgn:id":7408104,
    "tgn:name":"Puerta de Santiago",
    "tgn:placetype":[
        "aat:300008347"
    ]
},
  "bbox": [],
  "geometry": {"coordinates":[-99.625,18.620833],"type":"Point"}
}