{
  "id": 7411372,
  "type": "Feature",
  "properties": {
    "tgn:hierarchy":[
        "tgn:7411372",
        "tgn:7005587",
        "tgn:1000001",
        "tgn:7005560",
        "tgn:7029392"
    ],
    "tgn:id":7411372,
    "tgn:name:es":"Amajac, R\u00edo",
    "tgn:placetype":[
        "aat:300008699"
    ]
},
  "bbox": [],
  "geometry": {"coordinates":[-98.95,20.808333],"type":"Point"}
}