{
  "id": 2594542,
  "type": "Feature",
  "properties": {
    "tgn:hierarchy":[
        "tgn:2594542",
        "tgn:1000001",
        "tgn:7006451",
        "tgn:7012149",
        "tgn:2000098",
        "tgn:7029392"
    ],
    "tgn:id":2594542,
    "tgn:name":"Portland Wash",
    "tgn:placetype":[
        "aat:300008699"
    ]
},
  "bbox": [],
  "geometry": {"coordinates":[-114.4833,35.3833],"type":"Point"}
}