<<<<<<< HEAD
{
  "id": 7248418,
  "type": "Feature",
  "properties": {
    "tgn:hierarchy":[
        "tgn:7248418",
        "tgn:7003466",
        "tgn:1000003",
        "tgn:1000063",
        "tgn:4012014",
        "tgn:7029392"
    ],
    "tgn:id":7248418,
    "tgn:name":"Bestin, Bois",
    "tgn:placetype":[
        "aat:300008863"
    ]
},
  "bbox": [],
  "geometry": {"coordinates":[5.15,50.15],"type":"Point"}
}
=======
{"geometry":{"type":"Point","coordinates":[5.150000,50.150000]},"type":"Feature","properties":{"hierarchy":["tgn:7248418","tgn:7003466","tgn:1000003","tgn:1000063","tgn:4012014","tgn:7029392"],"placetype":["aat:300008863"],"id":7248418,"name:xx":"Bestin, Bois"}}
>>>>>>> 03f74aca74312dbeaf24d7e61306dd6a786dc3d0
