{
  "id": 7556249,
  "type": "Feature",
  "properties": {
    "tgn:hierarchy":[
        "tgn:7556249",
        "tgn:1000004",
        "tgn:7000198",
        "tgn:7000799",
        "tgn:7029392"
    ],
    "tgn:id":7556249,
    "tgn:name:en":"Phe",
    "tgn:placetype":[
        "aat:300008347"
    ]
},
  "bbox": [],
  "geometry": {"coordinates":[76.712754,33.611098],"type":"Point"}
}