{
  "id": 2695764,
  "type": "Feature",
  "properties": {
    "tgn:hierarchy":[
        "tgn:2695764",
        "tgn:1000001",
        "tgn:2002369",
        "tgn:7012149",
        "tgn:7007923",
        "tgn:7029392"
    ],
    "tgn:id":2695764,
    "tgn:name":"Stivers Creek",
    "tgn:placetype":[
        "aat:300008706"
    ]
},
  "bbox": [],
  "geometry": {"coordinates":[-104.9167,43.2167],"type":"Point"}
}