<<<<<<< HEAD
{
  "id": 7486055,
  "type": "Feature",
  "properties": {
    "tgn:hierarchy":[
        "tgn:7486055",
        "tgn:1000004",
        "tgn:7001014",
        "tgn:1000141",
        "tgn:7029392"
    ],
    "tgn:id":7486055,
    "tgn:name":"Huichun Si",
    "tgn:placetype":[
        "aat:300007595"
    ]
},
  "bbox": [],
  "geometry": {"coordinates":[120.62,23.695],"type":"Point"}
}
=======
{"geometry":{"type":"Point","coordinates":[120.620000,23.695000]},"type":"Feature","properties":{"hierarchy":["tgn:7486055","tgn:1000004","tgn:7001014","tgn:1000141","tgn:7029392"],"placetype":["aat:300007595"],"id":7486055,"name:xx":"Huichun Si"}}
>>>>>>> 03f74aca74312dbeaf24d7e61306dd6a786dc3d0
