{
  "id": 1060524,
  "type": "Feature",
  "properties": {
    "tgn:hierarchy":[
        "tgn:1060524",
        "tgn:1000003",
        "tgn:7011664",
        "tgn:7006660",
        "tgn:7029392"
    ],
    "tgn:id":1060524,
    "tgn:name":"Turka",
    "tgn:placetype":[
        "aat:300008347"
    ]
},
  "bbox": [],
  "geometry": {"coordinates":[23.0333,49.1667],"type":"Point"}
}