{
  "id": 7572204,
  "type": "Feature",
  "properties": {
    "tgn:hierarchy":[
        "tgn:7572204",
        "tgn:1000004",
        "tgn:7000198",
        "tgn:1001894",
        "tgn:7029392"
    ],
    "tgn:id":7572204,
    "tgn:name:en":"Jhamtoli",
    "tgn:placetype":[
        "aat:300008347"
    ]
},
  "bbox": [],
  "geometry": {"coordinates":[79.786414,24.710163],"type":"Point"}
}