{
  "id": 2574940,
  "type": "Feature",
  "properties": {
    "tgn:hierarchy":[
        "tgn:2574940",
        "tgn:1000001",
        "tgn:7012149",
        "tgn:2000616",
        "tgn:7007253",
        "tgn:7029392"
    ],
    "tgn:id":2574940,
    "tgn:name":"Penitentiary Creek",
    "tgn:placetype":[
        "aat:300008706"
    ]
},
  "bbox": [],
  "geometry": {"coordinates":[-91.2833,40.6333],"type":"Point"}
}