<<<<<<< HEAD
{
  "id": 7372264,
  "type": "Feature",
  "properties": {
    "tgn:hierarchy":[
        "tgn:7372264",
        "tgn:1000001",
        "tgn:1001960",
        "tgn:7005560",
        "tgn:7029392"
    ],
    "tgn:id":7372264,
    "tgn:name":"La Canada de Santa Cruz",
    "tgn:placetype":[
        "aat:300008347"
    ]
},
  "bbox": [],
  "geometry": {"coordinates":[-109.966667,30.65],"type":"Point"}
}
=======
{"geometry":{"type":"Point","coordinates":[-109.966667,30.650000]},"type":"Feature","properties":{"hierarchy":["tgn:7372264","tgn:1000001","tgn:1001960","tgn:7005560","tgn:7029392"],"placetype":["aat:300008347"],"id":7372264,"name:xx":"La Canada de Santa Cruz"}}
>>>>>>> 03f74aca74312dbeaf24d7e61306dd6a786dc3d0
