{
  "id": 2606494,
  "type": "Feature",
  "properties": {
    "tgn:hierarchy":[
        "tgn:2606494",
        "tgn:1000001",
        "tgn:1002258",
        "tgn:7012149",
        "tgn:7007240",
        "tgn:7029392"
    ],
    "tgn:id":2606494,
    "tgn:name":"Rambler Hole",
    "tgn:placetype":[
        "aat:300132316"
    ]
},
  "bbox": [],
  "geometry": {"coordinates":[-82.2833,29.8333],"type":"Point"}
}