{
  "id": 7325261,
  "type": "Feature",
  "properties": {
    "tgn:hierarchy":[
        "tgn:7325261",
        "tgn:7002760",
        "tgn:1000003",
        "tgn:1000095",
        "tgn:7029392"
    ],
    "tgn:id":7325261,
    "tgn:name":"San Mart\u00edn de la Arena, R\u00eda de",
    "tgn:placetype":[
        "aat:300266571"
    ]
},
  "bbox": [],
  "geometry": {"coordinates":[-4.033333,43.45],"type":"Point"}
}