{
  "id": 1059063,
  "type": "Feature",
  "properties": {
    "tgn:hierarchy":[
        "tgn:1059063",
        "tgn:1000004",
        "tgn:7011565",
        "tgn:7018214",
        "tgn:7002435",
        "tgn:7029392"
    ],
    "tgn:id":1059063,
    "tgn:name":"Rybachiy",
    "tgn:placetype":[
        "aat:300008347"
    ]
},
  "bbox": [],
  "geometry": {"coordinates":[20.85,55.15],"type":"Point"}
}