{
  "id": 1071085,
  "type": "Feature",
  "properties": {
    "tgn:hierarchy":[
        "tgn:1071085",
        "tgn:7002075",
        "tgn:1000004",
        "tgn:1000111",
        "tgn:7029392"
    ],
    "tgn:id":1071085,
    "tgn:name":"Qinglongji",
    "tgn:placetype":[
        "aat:300008347"
    ]
},
  "bbox": [],
  "geometry": {"coordinates":[116.6333,34.0333],"type":"Point"}
}