{
  "id": 7164150,
  "type": "Feature",
  "properties": {
    "tgn:hierarchy":[
        "tgn:7164150",
        "tgn:7003669",
        "tgn:1000003",
        "tgn:7000084",
        "tgn:7029392"
    ],
    "tgn:id":7164150,
    "tgn:name":"Hub",
    "tgn:placetype":[
        "aat:300008347"
    ]
},
  "bbox": [],
  "geometry": {"coordinates":[11.233333,49.55],"type":"Point"}
}