{
  "id": 2172213,
  "type": "Feature",
  "properties": {
    "tgn:hierarchy":[
        "tgn:2172213",
        "tgn:1000001",
        "tgn:7012149",
        "tgn:1002564",
        "tgn:7007710",
        "tgn:7029392"
    ],
    "tgn:id":2172213,
    "tgn:name":"Biglin Shaft",
    "tgn:placetype":[
        "aat:300000390"
    ]
},
  "bbox": [],
  "geometry": {"coordinates":[-75.6167,41.4167],"type":"Point"}
}