{
  "id": 2586034,
  "type": "Feature",
  "properties": {
    "tgn:hierarchy":[
        "tgn:2586034",
        "tgn:1000001",
        "tgn:7012149",
        "tgn:2000897",
        "tgn:7007256",
        "tgn:7029392"
    ],
    "tgn:id":2586034,
    "tgn:name":"Pisana Lagoon",
    "tgn:placetype":[
        "aat:300008680"
    ]
},
  "bbox": [],
  "geometry": {"coordinates":[-89.5333,29.7667],"type":"Point"}
}