{
  "id": 1070124,
  "type": "Feature",
  "properties": {
    "tgn:hierarchy":[
        "tgn:1070124",
        "tgn:1000004",
        "tgn:7001319",
        "tgn:1000111",
        "tgn:7029392"
    ],
    "tgn:id":1070124,
    "tgn:name":"Longzi",
    "tgn:placetype":[
        "aat:300008347"
    ]
},
  "bbox": [],
  "geometry": {"coordinates":[92.5167,28.4167],"type":"Point"}
}