{
  "id": 7235324,
  "type": "Feature",
  "properties": {
    "tgn:hierarchy":[
        "tgn:7235324",
        "tgn:7002706",
        "tgn:7002705",
        "tgn:1000003",
        "tgn:1000074",
        "tgn:7029392"
    ],
    "tgn:id":7235324,
    "tgn:name":"Bend\u00e9nia",
    "tgn:placetype":[
        "aat:300008777"
    ]
},
  "bbox": [],
  "geometry": {"coordinates":[20.816667,38.883333],"type":"Point"}
}