{
  "id": 7533693,
  "type": "Feature",
  "properties": {
    "tgn:hierarchy":[
        "tgn:7533693",
        "tgn:7001242",
        "tgn:7016833",
        "tgn:1001087",
        "tgn:7029392"
    ],
    "tgn:id":7533693,
    "tgn:name":"Kafr Man\u015f\u016br",
    "tgn:placetype":[
        "aat:300008347"
    ]
},
  "bbox": [],
  "geometry": {"coordinates":[31.052881,30.225554],"type":"Point"}
}