{
  "id": 2756609,
  "type": "Feature",
  "properties": {
    "tgn:hierarchy":[
        "tgn:2756609",
        "tgn:1000001",
        "tgn:7012149",
        "tgn:2002195",
        "tgn:7007919",
        "tgn:7029392"
    ],
    "tgn:id":2756609,
    "tgn:name":"Wells",
    "tgn:placetype":[
        "aat:300008347"
    ]
},
  "bbox": [],
  "geometry": {"coordinates":[-82.6167,36.95],"type":"Point"}
}