<<<<<<< HEAD
{
  "id": 2256456,
  "type": "Feature",
  "properties": {
    "tgn:hierarchy":[
        "tgn:2256456",
        "tgn:1000001",
        "tgn:7012149",
        "tgn:7007710",
        "tgn:7029392"
    ],
    "tgn:id":2256456,
    "tgn:name":"Coral Run",
    "tgn:placetype":[
        "aat:300008699"
    ]
},
  "bbox": [],
  "geometry": {"coordinates":[-77.25,40.8167],"type":"Point"}
}
=======
{"geometry":{"type":"Point","coordinates":[-77.250000,40.816700]},"type":"Feature","properties":{"hierarchy":["tgn:2256456","tgn:1000001","tgn:7012149","tgn:7007710","tgn:7029392"],"placetype":["aat:300008699"],"id":2256456,"name:xx":"Coral Run"}}
>>>>>>> 03f74aca74312dbeaf24d7e61306dd6a786dc3d0
