<<<<<<< HEAD
{
  "id": 2406114,
  "type": "Feature",
  "properties": {
    "tgn:hierarchy":[
        "tgn:2406114",
        "tgn:1000001",
        "tgn:1002308",
        "tgn:7012149",
        "tgn:7007710",
        "tgn:7029392"
    ],
    "tgn:id":2406114,
    "tgn:name":"Hummer Creek",
    "tgn:placetype":[
        "aat:300008706"
    ]
},
  "bbox": [],
  "geometry": {"coordinates":[-79.6,41.7167],"type":"Point"}
}
=======
{"geometry":{"type":"Point","coordinates":[-79.600000,41.716700]},"type":"Feature","properties":{"hierarchy":["tgn:2406114","tgn:1000001","tgn:1002308","tgn:7012149","tgn:7007710","tgn:7029392"],"placetype":["aat:300008706"],"id":2406114,"name:xx":"Hummer Creek"}}
>>>>>>> 03f74aca74312dbeaf24d7e61306dd6a786dc3d0
