{
  "id": 2286833,
  "type": "Feature",
  "properties": {
    "tgn:hierarchy":[
        "tgn:2286833",
        "tgn:1000001",
        "tgn:2001418",
        "tgn:7012149",
        "tgn:7007526",
        "tgn:7029392"
    ],
    "tgn:id":2286833,
    "tgn:name":"Dianas Punch Bowl",
    "tgn:placetype":[
        "aat:300008697"
    ]
},
  "bbox": [],
  "geometry": {"coordinates":[-116.65,39.0167],"type":"Point"}
}