<<<<<<< HEAD
{
  "id": 2330456,
  "type": "Feature",
  "properties": {
    "tgn:hierarchy":[
        "tgn:2330456",
        "tgn:1000001",
        "tgn:7012149",
        "tgn:2001285",
        "tgn:7007524",
        "tgn:7029392"
    ],
    "tgn:id":2330456,
    "tgn:name":"Flat Coulee Oil And Gas Field",
    "tgn:placetype":[
        "aat:300055621"
    ]
},
  "bbox": [],
  "geometry": {"coordinates":[-111.05,48.9667],"type":"Point"}
}
=======
{"geometry":{"type":"Point","coordinates":[-111.050000,48.966700]},"type":"Feature","properties":{"hierarchy":["tgn:2330456","tgn:1000001","tgn:7012149","tgn:2001285","tgn:7007524","tgn:7029392"],"placetype":["aat:300055621"],"id":2330456,"name:xx":"Flat Coulee Oil And Gas Field"}}
>>>>>>> 03f74aca74312dbeaf24d7e61306dd6a786dc3d0
