{
  "id": 2597635,
  "type": "Feature",
  "properties": {
    "tgn:hierarchy":[
        "tgn:2597635",
        "tgn:1000001",
        "tgn:7012149",
        "tgn:2000446",
        "tgn:7007248",
        "tgn:7029392"
    ],
    "tgn:id":2597635,
    "tgn:name":"Prater Mill",
    "tgn:placetype":[
        "aat:300008347"
    ]
},
  "bbox": [],
  "geometry": {"coordinates":[-84.9167,34.8833],"type":"Point"}
}