{
  "id": 2472080,
  "type": "Feature",
  "properties": {
    "tgn:hierarchy":[
        "tgn:2472080",
        "tgn:1000001",
        "tgn:7012149",
        "tgn:2000975",
        "tgn:7007520",
        "tgn:7029392"
    ],
    "tgn:id":2472080,
    "tgn:name":"Lotto Lake",
    "tgn:placetype":[
        "aat:300008680"
    ]
},
  "bbox": [],
  "geometry": {"coordinates":[-88.0833,46.25],"type":"Point"}
}