<<<<<<< HEAD
{
  "id": 7175635,
  "type": "Feature",
  "properties": {
    "tgn:hierarchy":[
        "tgn:7175635",
        "tgn:1000003",
        "tgn:7003676",
        "tgn:7000084",
        "tgn:7029392"
    ],
    "tgn:id":7175635,
    "tgn:name":"Gro\u00dfes Renzeler Moor",
    "tgn:placetype":[
        "aat:300008903"
    ]
},
  "bbox": [],
  "geometry": {"coordinates":[8.75,52.583333],"type":"Point"}
}
=======
{"geometry":{"type":"Point","coordinates":[8.750000,52.583333]},"type":"Feature","properties":{"hierarchy":["tgn:7175635","tgn:1000003","tgn:7003676","tgn:7000084","tgn:7029392"],"placetype":["aat:300008903"],"id":7175635,"name:xx":"Gro\u00dfes Renzeler Moor"}}
>>>>>>> 03f74aca74312dbeaf24d7e61306dd6a786dc3d0
