{
  "id": 7175635,
  "type": "Feature",
  "properties": {
    "tgn:hierarchy":[
        "tgn:7175635",
        "tgn:1000003",
        "tgn:7003676",
        "tgn:7000084",
        "tgn:7029392"
    ],
    "tgn:id":7175635,
    "tgn:name":"Gro\u00dfes Renzeler Moor",
    "tgn:placetype":[
        "aat:300008903"
    ]
},
  "bbox": [],
  "geometry": {"coordinates":[8.75,52.583333],"type":"Point"}
}