{
  "id": 7480496,
  "type": "Feature",
  "properties": {
    "tgn:hierarchy":[
        "tgn:7480496",
        "tgn:7001010",
        "tgn:1000004",
        "tgn:1000141",
        "tgn:7029392"
    ],
    "tgn:id":7480496,
    "tgn:name":"Ganshu Qiao",
    "tgn:placetype":[
        "aat:300007836"
    ]
},
  "bbox": [],
  "geometry": {"coordinates":[121.594722,23.852778],"type":"Point"}
}