{
  "id": 2369521,
  "type": "Feature",
  "properties": {
    "tgn:hierarchy":[
        "tgn:2369521",
        "tgn:1000001",
        "tgn:1002601",
        "tgn:7012149",
        "tgn:7007159",
        "tgn:7029392"
    ],
    "tgn:id":2369521,
    "tgn:name":"Gunn Brook",
    "tgn:placetype":[
        "aat:300008699"
    ]
},
  "bbox": [],
  "geometry": {"coordinates":[-73.3333,41.7833],"type":"Point"}
}