{
  "id": 2642208,
  "type": "Feature",
  "properties": {
    "tgn:hierarchy":[
        "tgn:2642208",
        "tgn:2001726",
        "tgn:1000001",
        "tgn:7012149",
        "tgn:7007712",
        "tgn:7029392"
    ],
    "tgn:id":2642208,
    "tgn:name":"Sand River",
    "tgn:placetype":[
        "aat:300008707"
    ]
},
  "bbox": [],
  "geometry": {"coordinates":[-81.7167,33.5333],"type":"Point"}
}