{
  "id": 7521891,
  "type": "Feature",
  "properties": {
    "tgn:hierarchy":[
        "tgn:7521891",
        "tgn:7001242",
        "tgn:7001311",
        "tgn:7016833",
        "tgn:7029392"
    ],
    "tgn:id":7521891,
    "tgn:name:en":"Ab\u016b Marwah, Jabal",
    "tgn:placetype":[
        "aat:300008795"
    ]
},
  "bbox": [],
  "geometry": {"coordinates":[33.146326,27.395459],"type":"Point"}
}