{
  "id": 2427096,
  "type": "Feature",
  "properties": {
    "tgn:hierarchy":[
        "tgn:2427096",
        "tgn:1000001",
        "tgn:2000199",
        "tgn:7012149",
        "tgn:7007158",
        "tgn:7029392"
    ],
    "tgn:id":2427096,
    "tgn:name":"Jonesy Gulch",
    "tgn:placetype":[
        "aat:300008761"
    ]
},
  "bbox": [],
  "geometry": {"coordinates":[-106.35,38.7667],"type":"Point"}
}