<<<<<<< HEAD
{
  "id": 7240569,
  "type": "Feature",
  "properties": {
    "tgn:hierarchy":[
        "tgn:7240569",
        "tgn:7003460",
        "tgn:1000003",
        "tgn:1000063",
        "tgn:4012014",
        "tgn:7029392"
    ],
    "tgn:id":7240569,
    "tgn:name":"Lac d' Eupen",
    "tgn:placetype":[
        "aat:300006191"
    ]
},
  "bbox": [],
  "geometry": {"coordinates":[6.1,50.616667],"type":"Point"}
}
=======
{"geometry":{"type":"Point","coordinates":[6.100000,50.616667]},"type":"Feature","properties":{"hierarchy":["tgn:7240569","tgn:7003460","tgn:1000003","tgn:1000063","tgn:4012014","tgn:7029392"],"placetype":["aat:300006191"],"id":7240569,"name:xx":"Lac d' Eupen"}}
>>>>>>> 03f74aca74312dbeaf24d7e61306dd6a786dc3d0
