{
  "id": 2595418,
  "type": "Feature",
  "properties": {
    "tgn:hierarchy":[
        "tgn:2595418",
        "tgn:1000001",
        "tgn:7012149",
        "tgn:7007157",
        "tgn:1002867",
        "tgn:7029392"
    ],
    "tgn:id":2595418,
    "tgn:name":"Potato Harbor",
    "tgn:placetype":[
        "aat:300132316"
    ]
},
  "bbox": [],
  "geometry": {"coordinates":[-119.5833,34.0333],"type":"Point"}
}