<<<<<<< HEAD
{
  "id": 7350023,
  "type": "Feature",
  "properties": {
    "tgn:hierarchy":[
        "tgn:7350023",
        "tgn:7005580",
        "tgn:1000001",
        "tgn:7005560",
        "tgn:7029392"
    ],
    "tgn:id":7350023,
    "tgn:name":"Aguilar, R\u00edo",
    "tgn:placetype":[
        "aat:300008699"
    ]
},
  "bbox": [],
  "geometry": {"coordinates":[-90.7,16.483333],"type":"Point"}
}
=======
{"geometry":{"type":"Point","coordinates":[-90.700000,16.483333]},"type":"Feature","properties":{"hierarchy":["tgn:7350023","tgn:7005580","tgn:1000001","tgn:7005560","tgn:7029392"],"placetype":["aat:300008699"],"id":7350023,"name:xx":"Aguilar, R\u00edo"}}
>>>>>>> 03f74aca74312dbeaf24d7e61306dd6a786dc3d0
