<<<<<<< HEAD
{
  "id": 2766530,
  "type": "Feature",
  "properties": {
    "tgn:hierarchy":[
        "tgn:2766530",
        "tgn:1000001",
        "tgn:7012149",
        "tgn:1002350",
        "tgn:7007157",
        "tgn:7029392"
    ],
    "tgn:id":2766530,
    "tgn:name":"White Oak Creek",
    "tgn:placetype":[
        "aat:300008706"
    ]
},
  "bbox": [],
  "geometry": {"coordinates":[-120.9833,38.7167],"type":"Point"}
}
=======
{"geometry":{"type":"Point","coordinates":[-120.983300,38.716700]},"type":"Feature","properties":{"hierarchy":["tgn:2766530","tgn:1000001","tgn:7012149","tgn:1002350","tgn:7007157","tgn:7029392"],"placetype":["aat:300008706"],"id":2766530,"name:xx":"White Oak Creek"}}
>>>>>>> 03f74aca74312dbeaf24d7e61306dd6a786dc3d0
