{
  "id": 2168542,
  "type": "Feature",
  "properties": {
    "tgn:hierarchy":[
        "tgn:2168542",
        "tgn:1000001",
        "tgn:2000922",
        "tgn:7012149",
        "tgn:7007515",
        "tgn:7029392"
    ],
    "tgn:id":2168542,
    "tgn:name":"Big Hill",
    "tgn:placetype":[
        "aat:300008798"
    ]
},
  "bbox": [],
  "geometry": {"coordinates":[-68.55,44.6833],"type":"Point"}
}