{
  "id": 2226624,
  "type": "Feature",
  "properties": {
    "tgn:hierarchy":[
        "tgn:2226624",
        "tgn:1000001",
        "tgn:7012149",
        "tgn:2000494",
        "tgn:7007250",
        "tgn:7029392"
    ],
    "tgn:id":2226624,
    "tgn:name":"Caton Lake",
    "tgn:placetype":[
        "aat:300008680"
    ]
},
  "bbox": [],
  "geometry": {"coordinates":[-115.4167,44.8833],"type":"Point"}
}