{
  "id": 2601677,
  "type": "Feature",
  "properties": {
    "tgn:hierarchy":[
        "tgn:2601677",
        "tgn:1000001",
        "tgn:7012149",
        "tgn:2001461",
        "tgn:7007568",
        "tgn:7029392"
    ],
    "tgn:id":2601677,
    "tgn:name":"Putnam Brook",
    "tgn:placetype":[
        "aat:300008699"
    ]
},
  "bbox": [],
  "geometry": {"coordinates":[-73.7167,44.1667],"type":"Point"}
}