{
  "id": 2037990,
  "type": "Feature",
  "properties": {
    "tgn:hierarchy":[
        "tgn:2037990",
        "tgn:1000001",
        "tgn:7012149",
        "tgn:2000850",
        "tgn:7007255",
        "tgn:7029392"
    ],
    "tgn:id":2037990,
    "tgn:name":"Burfield",
    "tgn:placetype":[
        "aat:300008347",
        "aat:300387210"
    ]
},
  "bbox": [],
  "geometry": {"coordinates":[-84.7833,36.7167],"type":"Point"}
}