{
  "id": 2172748,
  "type": "Feature",
  "properties": {
    "tgn:hierarchy":[
        "tgn:2172748",
        "tgn:1000001",
        "tgn:2001429",
        "tgn:7012149",
        "tgn:7007566",
        "tgn:7029392"
    ],
    "tgn:id":2172748,
    "tgn:name":"Bills Hole Tank",
    "tgn:placetype":[
        "aat:300006191"
    ]
},
  "bbox": [],
  "geometry": {"coordinates":[-108.85,33.2167],"type":"Point"}
}