{
  "id": 7302829,
  "type": "Feature",
  "properties": {
    "tgn:hierarchy":[
        "tgn:7302829",
        "tgn:7002829",
        "tgn:1000003",
        "tgn:7002786",
        "tgn:1000095",
        "tgn:7029392"
    ],
    "tgn:id":7302829,
    "tgn:name":"P\u00e1jaro, Pico del",
    "tgn:placetype":[
        "aat:300008798"
    ]
},
  "bbox": [],
  "geometry": {"coordinates":[-7.133333,42.583333],"type":"Point"}
}