<<<<<<< HEAD
{
  "id": 2401130,
  "type": "Feature",
  "properties": {
    "tgn:hierarchy":[
        "tgn:2401130",
        "tgn:1000001",
        "tgn:7006451",
        "tgn:2000091",
        "tgn:7012149",
        "tgn:7029392"
    ],
    "tgn:id":2401130,
    "tgn:name":"Horsefall Canyon",
    "tgn:placetype":[
        "aat:300008761"
    ]
},
  "bbox": [],
  "geometry": {"coordinates":[-109.2667,31.95],"type":"Point"}
}
=======
{"geometry":{"type":"Point","coordinates":[-109.266700,31.950000]},"type":"Feature","properties":{"hierarchy":["tgn:2401130","tgn:1000001","tgn:7006451","tgn:2000091","tgn:7012149","tgn:7029392"],"placetype":["aat:300008761"],"id":2401130,"name:xx":"Horsefall Canyon"}}
>>>>>>> 03f74aca74312dbeaf24d7e61306dd6a786dc3d0
