{
  "id": 1053847,
  "type": "Feature",
  "properties": {
    "tgn:hierarchy":[
        "tgn:1053847",
        "tgn:1000004",
        "tgn:7012947",
        "tgn:7014786",
        "tgn:7029392"
    ],
    "tgn:id":1053847,
    "tgn:name":"Staryy Ikan",
    "tgn:placetype":[
        "aat:300008347"
    ]
},
  "bbox": [],
  "geometry": {"coordinates":[68.5333,43.1667],"type":"Point"}
}