{
  "id": 2708308,
  "type": "Feature",
  "properties": {
    "tgn:hierarchy":[
        "tgn:2708308",
        "tgn:2002365",
        "tgn:1000001",
        "tgn:7012149",
        "tgn:7007923",
        "tgn:7029392"
    ],
    "tgn:id":2708308,
    "tgn:name":"Sybille Springs",
    "tgn:placetype":[
        "aat:300008697"
    ]
},
  "bbox": [],
  "geometry": {"coordinates":[-105.5167,41.6833],"type":"Point"}
}