{
  "id": 7438936,
  "type": "Feature",
  "properties": {
    "tgn:hierarchy":[
        "tgn:7438936",
        "tgn:1000001",
        "tgn:7005595",
        "tgn:7005560",
        "tgn:7029392"
    ],
    "tgn:id":7438936,
    "tgn:name":"Tabala",
    "tgn:placetype":[
        "aat:300008347"
    ]
},
  "bbox": [],
  "geometry": {"coordinates":[-107.095,24.443056],"type":"Point"}
}