{
  "id": 2364973,
  "type": "Feature",
  "properties": {
    "tgn:hierarchy":[
        "tgn:2364973",
        "tgn:1000001",
        "tgn:2001485",
        "tgn:7012149",
        "tgn:7007709",
        "tgn:7029392"
    ],
    "tgn:id":2364973,
    "tgn:name":"Greenhouse Bay",
    "tgn:placetype":[
        "aat:300132316"
    ]
},
  "bbox": [],
  "geometry": {"coordinates":[-78.7667,34.2167],"type":"Point"}
}