{
  "id": 1028269,
  "type": "Feature",
  "properties": {
    "tgn:hierarchy":[
        "tgn:1028269",
        "tgn:1003572",
        "tgn:7002445",
        "tgn:1000003",
        "tgn:7026570",
        "tgn:7008591",
        "tgn:7029392"
    ],
    "tgn:id":1028269,
    "tgn:name":"Ainsworth",
    "tgn:placetype":[
        "aat:300008347"
    ]
},
  "bbox": [],
  "geometry": {"coordinates":[-2.3667,53.5833],"type":"Point"}
}