{
  "id": 2768048,
  "type": "Feature",
  "properties": {
    "tgn:hierarchy":[
        "tgn:2768048",
        "tgn:1000001",
        "tgn:2002148",
        "tgn:7012149",
        "tgn:7007919",
        "tgn:7029392"
    ],
    "tgn:id":2768048,
    "tgn:name":"Whiteplace Ridge",
    "tgn:placetype":[
        "aat:300266640"
    ]
},
  "bbox": [],
  "geometry": {"coordinates":[-81.8167,37.2333],"type":"Point"}
}