{
  "id": 2565401,
  "type": "Feature",
  "properties": {
    "tgn:hierarchy":[
        "tgn:2565401",
        "tgn:1000001",
        "tgn:7012149",
        "tgn:1009002",
        "tgn:7007157",
        "tgn:1002867",
        "tgn:7029392"
    ],
    "tgn:id":2565401,
    "tgn:name":"Painted Cave",
    "tgn:placetype":[
        "aat:300008746"
    ]
},
  "bbox": [],
  "geometry": {"coordinates":[-119.85,34.0667],"type":"Point"}
}