{
  "id": 7440430,
  "type": "Feature",
  "properties": {
    "tgn:hierarchy":[
        "tgn:7440430",
        "tgn:1000001",
        "tgn:7005597",
        "tgn:7005560",
        "tgn:7029392"
    ],
    "tgn:id":7440430,
    "tgn:name":"Santa Mar\u00eda, Boca",
    "tgn:placetype":[
        "aat:300185707"
    ]
},
  "bbox": [],
  "geometry": {"coordinates":[-97.516667,25.016667],"type":"Point"}
}