{
  "id": 7076856,
  "type": "Feature",
  "properties": {
    "tgn:hierarchy":[
        "tgn:7076856",
        "tgn:1000003",
        "tgn:7003676",
        "tgn:7000084",
        "tgn:7029392"
    ],
    "tgn:id":7076856,
    "tgn:name":"Landkreis Hannover",
    "tgn:placetype":[
        "aat:300387198"
    ]
},
  "bbox": [],
  "geometry": {"coordinates":[9.775556,52.391389],"type":"Point"}
}