{
  "id": 2126483,
  "type": "Feature",
  "properties": {
    "tgn:hierarchy":[
        "tgn:2126483",
        "tgn:1000001",
        "tgn:7012149",
        "tgn:2001447",
        "tgn:7007566",
        "tgn:7029392"
    ],
    "tgn:id":2126483,
    "tgn:name":"Ady",
    "tgn:placetype":[
        "aat:300000390"
    ]
},
  "bbox": [],
  "geometry": {"coordinates":[-105.8333,32.8667],"type":"Point"}
}