{
  "id": 1061919,
  "type": "Feature",
  "properties": {
    "tgn:hierarchy":[
        "tgn:1061919",
        "tgn:7010420",
        "tgn:1000003",
        "tgn:7002795",
        "tgn:1000095",
        "tgn:7029392"
    ],
    "tgn:id":1061919,
    "tgn:name":"Casa de la Torrecilla",
    "tgn:placetype":[
        "aat:300008347"
    ]
},
  "bbox": [],
  "geometry": {"coordinates":[-3.6167,40.3167],"type":"Point"}
}