{
  "id": 7311636,
  "type": "Feature",
  "properties": {
    "tgn:hierarchy":[
        "tgn:7311636",
        "tgn:1001699",
        "tgn:1000049",
        "tgn:1000002",
        "tgn:7029392"
    ],
    "tgn:id":7311636,
    "tgn:name":"Las Quemas",
    "tgn:placetype":[
        "aat:300000206"
    ]
},
  "bbox": [],
  "geometry": {"coordinates":[-73.116667,-41.433333],"type":"Point"}
}