{
  "id": 7589577,
  "type": "Feature",
  "properties": {
    "tgn:hierarchy":[
        "tgn:7589577",
        "tgn:1000004",
        "tgn:7000198",
        "tgn:7000799",
        "tgn:7029392"
    ],
    "tgn:id":7589577,
    "tgn:name:en":"K\u0101ldang Kildang La",
    "tgn:placetype":[
        "aat:300259572"
    ]
},
  "bbox": [],
  "geometry": {"coordinates":[76.361111,34.529167],"type":"Point"}
}