{
  "id": 7512251,
  "type": "Feature",
  "properties": {
    "tgn:hierarchy":[
        "tgn:7512251",
        "tgn:1008380",
        "tgn:7520093",
        "tgn:1000226",
        "tgn:1000006",
        "tgn:7029392"
    ],
    "tgn:id":7512251,
    "tgn:name:en":"Irirangi",
    "tgn:placetype":[
        "aat:300387200"
    ]
},
  "bbox": [],
  "geometry": {"coordinates":[175.666667,-39.533333],"type":"Point"}
}