{
  "id": 2735608,
  "type": "Feature",
  "properties": {
    "tgn:hierarchy":[
        "tgn:2735608",
        "tgn:1000001",
        "tgn:7012149",
        "tgn:1002950",
        "tgn:7007568",
        "tgn:7029392"
    ],
    "tgn:id":2735608,
    "tgn:name":"Twin Glens",
    "tgn:placetype":[
        "aat:300008761"
    ]
},
  "bbox": [],
  "geometry": {"coordinates":[-76.45,42.4833],"type":"Point"}
}