<<<<<<< HEAD
{
  "id": 7022030,
  "type": "Feature",
  "properties": {
    "tgn:hierarchy":[
        "tgn:7022030",
        "tgn:1000001",
        "tgn:7012149",
        "tgn:2001851",
        "tgn:7007825",
        "tgn:7029392"
    ],
    "tgn:id":7022030,
    "tgn:name":"Pigeonroost Hollow",
    "tgn:placetype":[
        "aat:300008761"
    ]
},
  "bbox": [],
  "geometry": {"coordinates":[-83.0667,35.9167],"type":"Point"}
}
=======
{"geometry":{"type":"Point","coordinates":[-83.066700,35.916700]},"type":"Feature","properties":{"hierarchy":["tgn:7022030","tgn:1000001","tgn:7012149","tgn:2001851","tgn:7007825","tgn:7029392"],"placetype":["aat:300008761"],"id":7022030,"name:xx":"Pigeonroost Hollow"}}
>>>>>>> 03f74aca74312dbeaf24d7e61306dd6a786dc3d0
