<<<<<<< HEAD
{
  "id": 2152993,
  "type": "Feature",
  "properties": {
    "tgn:hierarchy":[
        "tgn:2152993",
        "tgn:1000001",
        "tgn:7012149",
        "tgn:2002379",
        "tgn:7007923",
        "tgn:7029392"
    ],
    "tgn:id":2152993,
    "tgn:name":"Beach Springs",
    "tgn:placetype":[
        "aat:300008697"
    ]
},
  "bbox": [],
  "geometry": {"coordinates":[-110.3,44.55],"type":"Point"}
}
=======
{"geometry":{"type":"Point","coordinates":[-110.300000,44.550000]},"type":"Feature","properties":{"hierarchy":["tgn:2152993","tgn:1000001","tgn:7012149","tgn:2002379","tgn:7007923","tgn:7029392"],"placetype":["aat:300008697"],"id":2152993,"name:xx":"Beach Springs"}}
>>>>>>> 03f74aca74312dbeaf24d7e61306dd6a786dc3d0
