{
  "id": 7587084,
  "type": "Feature",
  "properties": {
    "tgn:hierarchy":[
        "tgn:7587084",
        "tgn:1000004",
        "tgn:7000198",
        "tgn:1001977",
        "tgn:7029392"
    ],
    "tgn:id":7587084,
    "tgn:name:en":"Puturia",
    "tgn:placetype":[
        "aat:300008347"
    ]
},
  "bbox": [],
  "geometry": {"coordinates":[88.081667,22.338056],"type":"Point"}
}