<<<<<<< HEAD
{
  "id": 2258590,
  "type": "Feature",
  "properties": {
    "tgn:hierarchy":[
        "tgn:2258590",
        "tgn:1000001",
        "tgn:7012149",
        "tgn:7021748",
        "tgn:7007826",
        "tgn:7029392"
    ],
    "tgn:id":2258590,
    "tgn:name":"Cottonwood",
    "tgn:placetype":[
        "aat:300008347"
    ]
},
  "bbox": [],
  "geometry": {"coordinates":[-97.0333,31.8167],"type":"Point"}
}
=======
{"geometry":{"type":"Point","coordinates":[-97.033300,31.816700]},"type":"Feature","properties":{"hierarchy":["tgn:2258590","tgn:1000001","tgn:7012149","tgn:7021748","tgn:7007826","tgn:7029392"],"placetype":["aat:300008347"],"id":2258590,"name:xx":"Cottonwood"}}
>>>>>>> 03f74aca74312dbeaf24d7e61306dd6a786dc3d0
