{
  "id": 2469552,
  "type": "Feature",
  "properties": {
    "tgn:hierarchy":[
        "tgn:2469552",
        "tgn:1000001",
        "tgn:7012149",
        "tgn:7014510",
        "tgn:7007920",
        "tgn:7029392"
    ],
    "tgn:id":2469552,
    "tgn:name":"Lookout Creek",
    "tgn:placetype":[
        "aat:300008706"
    ]
},
  "bbox": [],
  "geometry": {"coordinates":[-121.3167,48.55],"type":"Point"}
}