{
  "id": 7220253,
  "type": "Feature",
  "properties": {
    "tgn:hierarchy":[
        "tgn:7220253",
        "tgn:7011330",
        "tgn:7002674",
        "tgn:1000003",
        "tgn:1000074",
        "tgn:7029392"
    ],
    "tgn:id":7220253,
    "tgn:name":"Vel\u00f3na, Vrachonis\u00edda",
    "tgn:placetype":[
        "aat:300008791"
    ]
},
  "bbox": [],
  "geometry": {"coordinates":[26.891944,37.095278],"type":"Point"}
}