{
  "id": 7283622,
  "type": "Feature",
  "properties": {
    "tgn:hierarchy":[
        "tgn:7283622",
        "tgn:1001630",
        "tgn:1000049",
        "tgn:1000002",
        "tgn:7029392"
    ],
    "tgn:id":7283622,
    "tgn:name":"Panul, Aguada de",
    "tgn:placetype":[
        "aat:300008697"
    ]
},
  "bbox": [],
  "geometry": {"coordinates":[-69.666667,-26.383333],"type":"Point"}
}