{
  "id": 7072465,
  "type": "Feature",
  "properties": {
    "tgn:hierarchy":[
        "tgn:7072465",
        "tgn:7003669",
        "tgn:1000003",
        "tgn:7000084",
        "tgn:7029392"
    ],
    "tgn:id":7072465,
    "tgn:name":"Sulzbach",
    "tgn:placetype":[
        "aat:300008347"
    ]
},
  "bbox": [],
  "geometry": {"coordinates":[9.159167,49.910833],"type":"Point"}
}