{
  "id": 2645569,
  "type": "Feature",
  "properties": {
    "tgn:hierarchy":[
        "tgn:2645569",
        "tgn:1000001",
        "tgn:7012149",
        "tgn:2001161",
        "tgn:7007522",
        "tgn:7029392"
    ],
    "tgn:id":2645569,
    "tgn:name":"Sawgrass Lake",
    "tgn:placetype":[
        "aat:300008680"
    ]
},
  "bbox": [],
  "geometry": {"coordinates":[-91.1167,33.3333],"type":"Point"}
}