{
  "id": 7589617,
  "type": "Feature",
  "properties": {
    "tgn:hierarchy":[
        "tgn:7589617",
        "tgn:1000004",
        "tgn:1001871",
        "tgn:7000198",
        "tgn:7029392"
    ],
    "tgn:id":7589617,
    "tgn:name:en":"Dhammanheri",
    "tgn:placetype":[
        "aat:300008347"
    ]
},
  "bbox": [],
  "geometry": {"coordinates":[77.030052,29.867409],"type":"Point"}
}