{
  "id": 7037913,
  "type": "Feature",
  "properties": {
    "tgn:hierarchy":[
        "tgn:7037913",
        "tgn:7003162",
        "tgn:1000003",
        "tgn:7009760",
        "tgn:1000080",
        "tgn:7029392"
    ],
    "tgn:id":7037913,
    "tgn:name":"Valsavignone",
    "tgn:placetype":[
        "aat:300008347"
    ]
},
  "bbox": [],
  "geometry": {"coordinates":[12.016667,43.733333],"type":"Point"}
}