{
  "id": 2153018,
  "type": "Feature",
  "properties": {
    "tgn:hierarchy":[
        "tgn:2153018",
        "tgn:1000001",
        "tgn:1002539",
        "tgn:7012149",
        "tgn:7007516",
        "tgn:7029392"
    ],
    "tgn:id":2153018,
    "tgn:name":"Beachwood Glen",
    "tgn:placetype":[
        "aat:300008347"
    ]
},
  "bbox": [],
  "geometry": {"coordinates":[-75.85,39.35],"type":"Point"}
}