{
  "id": 2393496,
  "type": "Feature",
  "properties": {
    "tgn:hierarchy":[
        "tgn:2393496",
        "tgn:1000001",
        "tgn:7012149",
        "tgn:2002088",
        "tgn:7007826",
        "tgn:7029392"
    ],
    "tgn:id":2393496,
    "tgn:name":"Hog Canyon",
    "tgn:placetype":[
        "aat:300008761"
    ]
},
  "bbox": [],
  "geometry": {"coordinates":[-101.5333,30.0167],"type":"Point"}
}