{
  "id": 1096751,
  "type": "Feature",
  "properties": {
    "tgn:hierarchy":[
        "tgn:1096751",
        "tgn:7000490",
        "tgn:1000006",
        "tgn:7001992",
        "tgn:7029392"
    ],
    "tgn:id":1096751,
    "tgn:name":"Devonport",
    "tgn:placetype":[
        "aat:300008347",
        "aat:300387308",
        "aat:300008375"
    ]
},
  "bbox": [],
  "geometry": {"coordinates":[146.2667,-41.15],"type":"Point"}
}