{
  "id": 2206155,
  "type": "Feature",
  "properties": {
    "tgn:hierarchy":[
        "tgn:2206155",
        "tgn:1000001",
        "tgn:7012149",
        "tgn:2001447",
        "tgn:7007566",
        "tgn:7029392"
    ],
    "tgn:id":2206155,
    "tgn:name":"Bull Tank",
    "tgn:placetype":[
        "aat:300006191"
    ]
},
  "bbox": [],
  "geometry": {"coordinates":[-105.2333,32.1667],"type":"Point"}
}