{
  "id": 2345241,
  "type": "Feature",
  "properties": {
    "tgn:hierarchy":[
        "tgn:2345241",
        "tgn:1000001",
        "tgn:2001417",
        "tgn:7012149",
        "tgn:7007526",
        "tgn:7029392"
    ],
    "tgn:id":2345241,
    "tgn:name":"Garfield Reservoir Number Two",
    "tgn:placetype":[
        "aat:300006191"
    ]
},
  "bbox": [],
  "geometry": {"coordinates":[-118.2833,38.3667],"type":"Point"}
}