{
  "id": 7591143,
  "type": "Feature",
  "properties": {
    "tgn:hierarchy":[
        "tgn:7591143",
        "tgn:1000004",
        "tgn:7000198",
        "tgn:7031786",
        "tgn:7029392"
    ],
    "tgn:id":7591143,
    "tgn:name:en":"Udiab\u0101gh Tea Garden",
    "tgn:placetype":[
        "aat:300000240"
    ]
},
  "bbox": [],
  "geometry": {"coordinates":[77.764021,30.453551],"type":"Point"}
}