{
  "id": 2525987,
  "type": "Feature",
  "properties": {
    "tgn:hierarchy":[
        "tgn:2525987",
        "tgn:2000256",
        "tgn:1000001",
        "tgn:7012149",
        "tgn:7007240",
        "tgn:7029392"
    ],
    "tgn:id":2525987,
    "tgn:name":"Mosquito Bay",
    "tgn:placetype":[
        "aat:300008905"
    ]
},
  "bbox": [],
  "geometry": {"coordinates":[-82.1667,29.55],"type":"Point"}
}