{
  "id": 7133944,
  "type": "Feature",
  "properties": {
    "tgn:hierarchy":[
        "tgn:7133944",
        "tgn:1000003",
        "tgn:7003676",
        "tgn:7000084",
        "tgn:7029392"
    ],
    "tgn:id":7133944,
    "tgn:name":"Moortief",
    "tgn:placetype":[
        "aat:300008699"
    ]
},
  "bbox": [],
  "geometry": {"coordinates":[7.416667,53.65],"type":"Point"}
}