{
  "id": 2189043,
  "type": "Feature",
  "properties": {
    "tgn:hierarchy":[
        "tgn:2189043",
        "tgn:1000001",
        "tgn:7012149",
        "tgn:2001718",
        "tgn:7007708",
        "tgn:7029392"
    ],
    "tgn:id":2189043,
    "tgn:name":"Boulder Spring",
    "tgn:placetype":[
        "aat:300008697"
    ]
},
  "bbox": [],
  "geometry": {"coordinates":[-118.0667,43.85],"type":"Point"}
}