{
  "id": 7197609,
  "type": "Feature",
  "properties": {
    "tgn:hierarchy":[
        "tgn:7197609",
        "tgn:1000003",
        "tgn:7003676",
        "tgn:7000084",
        "tgn:7029392"
    ],
    "tgn:id":7197609,
    "tgn:name":"D\u00fcmmerlohausen",
    "tgn:placetype":[
        "aat:300008347"
    ]
},
  "bbox": [],
  "geometry": {"coordinates":[8.283333,52.533333],"type":"Point"}
}