{
  "id": 7384182,
  "type": "Feature",
  "properties": {
    "tgn:hierarchy":[
        "tgn:7384182",
        "tgn:7005586",
        "tgn:1000001",
        "tgn:7005560",
        "tgn:7029392"
    ],
    "tgn:id":7384182,
    "tgn:name":"Pachon, Cerro el",
    "tgn:placetype":[
        "aat:300008795"
    ]
},
  "bbox": [],
  "geometry": {"coordinates":[-104.833333,20.133333],"type":"Point"}
}