{
  "id": 7091487,
  "type": "Feature",
  "properties": {
    "tgn:hierarchy":[
        "tgn:7091487",
        "tgn:1000003",
        "tgn:7003682",
        "tgn:7000084",
        "tgn:7029392"
    ],
    "tgn:id":7091487,
    "tgn:name":"Unterpetersb\u00e4chlerhof",
    "tgn:placetype":[
        "aat:300000206"
    ]
},
  "bbox": [],
  "geometry": {"coordinates":[7.716667,49.066667],"type":"Point"}
}