{
  "id": 7558220,
  "type": "Feature",
  "properties": {
    "tgn:hierarchy":[
        "tgn:7558220",
        "tgn:1000004",
        "tgn:7000198",
        "tgn:1001895",
        "tgn:7029392"
    ],
    "tgn:id":7558220,
    "tgn:name:en":"S\u0101nglud Khurd",
    "tgn:placetype":[
        "aat:300008347"
    ]
},
  "bbox": [],
  "geometry": {"coordinates":[77.116667,20.75],"type":"Point"}
}