{
  "id": 7152661,
  "type": "Feature",
  "properties": {
    "tgn:hierarchy":[
        "tgn:7152661",
        "tgn:1000003",
        "tgn:7003682",
        "tgn:7000084",
        "tgn:7029392"
    ],
    "tgn:id":7152661,
    "tgn:name":"J\u00e4gerthal",
    "tgn:placetype":[
        "aat:300008347"
    ]
},
  "bbox": [],
  "geometry": {"coordinates":[8.066667,49.45],"type":"Point"}
}