{
  "id": 7082610,
  "type": "Feature",
  "properties": {
    "tgn:hierarchy":[
        "tgn:7082610",
        "tgn:1000003",
        "tgn:7000094",
        "tgn:7000084",
        "tgn:7029392"
    ],
    "tgn:id":7082610,
    "tgn:name":"Wendisch Waren",
    "tgn:placetype":[
        "aat:300008347"
    ]
},
  "bbox": [],
  "geometry": {"coordinates":[12.133333,53.566667],"type":"Point"}
}