{
  "id": 2659113,
  "type": "Feature",
  "properties": {
    "tgn:hierarchy":[
        "tgn:2659113",
        "tgn:1000001",
        "tgn:7012149",
        "tgn:2001867",
        "tgn:7007825",
        "tgn:7029392"
    ],
    "tgn:id":2659113,
    "tgn:name":"Shetter Quarry",
    "tgn:placetype":[
        "aat:300000390"
    ]
},
  "bbox": [],
  "geometry": {"coordinates":[-85.85,35.2667],"type":"Point"}
}