{
  "id": 2524455,
  "type": "Feature",
  "properties": {
    "tgn:hierarchy":[
        "tgn:2524455",
        "tgn:1000001",
        "tgn:7012149",
        "tgn:2001901",
        "tgn:7007825",
        "tgn:7029392"
    ],
    "tgn:id":2524455,
    "tgn:name":"Morgan State Forest",
    "tgn:placetype":[
        "aat:300008863"
    ]
},
  "bbox": [],
  "geometry": {"coordinates":[-84.4833,36.1167],"type":"Point"}
}