{
  "id": 1084446,
  "type": "Feature",
  "properties": {
    "tgn:hierarchy":[
        "tgn:1084446",
        "tgn:1000004",
        "tgn:1001609",
        "tgn:1000135",
        "tgn:7029392"
    ],
    "tgn:id":1084446,
    "tgn:name":"Masinloc",
    "tgn:placetype":[
        "aat:300008347"
    ]
},
  "bbox": [],
  "geometry": {"coordinates":[119.9667,15.5333],"type":"Point"}
}