{
  "id": 1014005,
  "type": "Feature",
  "properties": {
    "tgn:hierarchy":[
        "tgn:1014005",
        "tgn:7005685",
        "tgn:1000001",
        "tgn:7005734",
        "tgn:7029392"
    ],
    "tgn:id":1014005,
    "tgn:name":"Sainte Rose du Lac",
    "tgn:placetype":[
        "aat:300008347"
    ]
},
  "bbox": [],
  "geometry": {"coordinates":[-99.5167,51.0667],"type":"Point"}
}