{
  "id": 2170853,
  "type": "Feature",
  "properties": {
    "tgn:hierarchy":[
        "tgn:2170853",
        "tgn:1000001",
        "tgn:2000463",
        "tgn:7012149",
        "tgn:7007250",
        "tgn:7029392"
    ],
    "tgn:id":2170853,
    "tgn:name":"Big Sink Waterhole",
    "tgn:placetype":[
        "aat:300008680"
    ]
},
  "bbox": [],
  "geometry": {"coordinates":[-113.55,43.4333],"type":"Point"}
}