{
  "id": 1109482,
  "type": "Feature",
  "properties": {
    "tgn:hierarchy":[
        "tgn:1109482",
        "tgn:1000001",
        "tgn:1001960",
        "tgn:7005560",
        "tgn:7029392"
    ],
    "tgn:id":1109482,
    "tgn:name":"Pinitos, Sierra de",
    "tgn:placetype":[
        "aat:300008795"
    ]
},
  "bbox": [],
  "geometry": {"coordinates":[-110.833333,31.183333],"type":"Point"}
}