{
  "id": 7443848,
  "type": "Feature",
  "properties": {
    "tgn:hierarchy":[
        "tgn:7443848",
        "tgn:7002444",
        "tgn:1000003",
        "tgn:7008072",
        "tgn:7008591",
        "tgn:7029392"
    ],
    "tgn:id":7443848,
    "tgn:name:en":"Yetholm Loch",
    "tgn:placetype":[
        "aat:300008680"
    ]
},
  "bbox": [],
  "geometry": {"coordinates":[-2.316667,55.55],"type":"Point"}
}