{
  "id": 7409139,
  "type": "Feature",
  "properties": {
    "tgn:hierarchy":[
        "tgn:7409139",
        "tgn:1000001",
        "tgn:7005592",
        "tgn:7005560",
        "tgn:7029392"
    ],
    "tgn:id":7409139,
    "tgn:name":"Chiazumba",
    "tgn:placetype":[
        "aat:300008347"
    ]
},
  "bbox": [],
  "geometry": {"coordinates":[-98.536111,18.35],"type":"Point"}
}