{
  "id": 7469635,
  "type": "Feature",
  "properties": {
    "tgn:hierarchy":[
        "tgn:7469635",
        "tgn:1000004",
        "tgn:7490934",
        "tgn:1000141",
        "tgn:7029392"
    ],
    "tgn:id":7469635,
    "tgn:name":"Haichengli",
    "tgn:placetype":[
        "aat:300008347"
    ]
},
  "bbox": [],
  "geometry": {"coordinates":[120.15,23.183333],"type":"Point"}
}