{
  "id": 2383181,
  "type": "Feature",
  "properties": {
    "tgn:hierarchy":[
        "tgn:2383181",
        "tgn:1000001",
        "tgn:7012149",
        "tgn:2000807",
        "tgn:7007255",
        "tgn:7029392"
    ],
    "tgn:id":2383181,
    "tgn:name":"Heady Spring",
    "tgn:placetype":[
        "aat:300008697"
    ]
},
  "bbox": [],
  "geometry": {"coordinates":[-85.8167,37.5667],"type":"Point"}
}