<<<<<<< HEAD
{
  "id": 7371897,
  "type": "Feature",
  "properties": {
    "tgn:hierarchy":[
        "tgn:7371897",
        "tgn:7005580",
        "tgn:1000001",
        "tgn:7005560",
        "tgn:7029392"
    ],
    "tgn:id":7371897,
    "tgn:name":"La Escalera, R\u00edo de",
    "tgn:placetype":[
        "aat:300008699"
    ]
},
  "bbox": [],
  "geometry": {"coordinates":[-92.95,16.5],"type":"Point"}
}
=======
{"geometry":{"type":"Point","coordinates":[-92.950000,16.500000]},"type":"Feature","properties":{"hierarchy":["tgn:7371897","tgn:7005580","tgn:1000001","tgn:7005560","tgn:7029392"],"placetype":["aat:300008699"],"id":7371897,"name:xx":"La Escalera, R\u00edo de"}}
>>>>>>> 03f74aca74312dbeaf24d7e61306dd6a786dc3d0
