{
  "id": 7341587,
  "type": "Feature",
  "properties": {
    "tgn:hierarchy":[
        "tgn:7341587",
        "tgn:1001439",
        "tgn:1000003",
        "tgn:7002797",
        "tgn:1000095",
        "tgn:7029392"
    ],
    "tgn:id":7341587,
    "tgn:name":"Blanca, Cala",
    "tgn:placetype":[
        "aat:300132317"
    ]
},
  "bbox": [],
  "geometry": {"coordinates":[-1.45,37.483333],"type":"Point"}
}