{
  "id": 7468234,
  "type": "Feature",
  "properties": {
    "tgn:hierarchy":[
        "tgn:7468234",
        "tgn:7498210",
        "tgn:1000004",
        "tgn:1000141",
        "tgn:7029392"
    ],
    "tgn:id":7468234,
    "tgn:name":"Qiaozicun",
    "tgn:placetype":[
        "aat:300008347"
    ]
},
  "bbox": [],
  "geometry": {"coordinates":[119.994167,26.2325],"type":"Point"}
}