{
  "id": 7490325,
  "type": "Feature",
  "properties": {
    "tgn:hierarchy":[
        "tgn:7490325",
        "tgn:1000004",
        "tgn:7001013",
        "tgn:1000141",
        "tgn:7029392"
    ],
    "tgn:id":7490325,
    "tgn:name":"Dazhukeng",
    "tgn:placetype":[
        "aat:300008347"
    ]
},
  "bbox": [],
  "geometry": {"coordinates":[121.239444,24.799444],"type":"Point"}
}