{
  "id": 2562998,
  "type": "Feature",
  "properties": {
    "tgn:hierarchy":[
        "tgn:2562998",
        "tgn:1000001",
        "tgn:7012149",
        "tgn:2000410",
        "tgn:7007248",
        "tgn:7029392"
    ],
    "tgn:id":2562998,
    "tgn:name":"Owen Mountain",
    "tgn:placetype":[
        "aat:300008798"
    ]
},
  "bbox": [],
  "geometry": {"coordinates":[-83.4167,34.9833],"type":"Point"}
}