{
  "id": 2622374,
  "type": "Feature",
  "properties": {
    "tgn:hierarchy":[
        "tgn:2622374",
        "tgn:1000001",
        "tgn:7012149",
        "tgn:7007157",
        "tgn:1002791",
        "tgn:7029392"
    ],
    "tgn:id":2622374,
    "tgn:name":"Robie Point",
    "tgn:placetype":[
        "aat:300008798"
    ]
},
  "bbox": [],
  "geometry": {"coordinates":[-121.05,38.8833],"type":"Point"}
}