{
  "id": 1053049,
  "type": "Feature",
  "properties": {
    "tgn:hierarchy":[
        "tgn:1053049",
        "tgn:1000004",
        "tgn:1003418",
        "tgn:7018214",
        "tgn:7002435",
        "tgn:7029392"
    ],
    "tgn:id":1053049,
    "tgn:name":"Borozdino",
    "tgn:placetype":[
        "aat:300008347"
    ]
},
  "bbox": [],
  "geometry": {"coordinates":[38.3667,54.1167],"type":"Point"}
}