{
  "id": 7421611,
  "type": "Feature",
  "properties": {
    "tgn:hierarchy":[
        "tgn:7421611",
        "tgn:7005584",
        "tgn:1000001",
        "tgn:7005560",
        "tgn:7029392"
    ],
    "tgn:id":7421611,
    "tgn:name":"Cuatralba, Sierra",
    "tgn:placetype":[
        "aat:300008795"
    ]
},
  "bbox": [],
  "geometry": {"coordinates":[-101.531111,21.250278],"type":"Point"}
}