{
  "id": 2633787,
  "type": "Feature",
  "properties": {
    "tgn:hierarchy":[
        "tgn:2633787",
        "tgn:1000001",
        "tgn:2000589",
        "tgn:7012149",
        "tgn:7007253",
        "tgn:7029392"
    ],
    "tgn:id":2633787,
    "tgn:name":"Rush Island",
    "tgn:placetype":[
        "aat:300008791"
    ]
},
  "bbox": [],
  "geometry": {"coordinates":[-91.0667,40.8333],"type":"Point"}
}