{
  "id": 7147521,
  "type": "Feature",
  "properties": {
    "tgn:hierarchy":[
        "tgn:7147521",
        "tgn:1000003",
        "tgn:7003676",
        "tgn:7000084",
        "tgn:7029392"
    ],
    "tgn:id":7147521,
    "tgn:name":"Kuckucks-Berg",
    "tgn:placetype":[
        "aat:300008777"
    ]
},
  "bbox": [],
  "geometry": {"coordinates":[10.466667,51.966667],"type":"Point"}
}