{
  "id": 2771927,
  "type": "Feature",
  "properties": {
    "tgn:hierarchy":[
        "tgn:2771927",
        "tgn:1000001",
        "tgn:7012149",
        "tgn:2001717",
        "tgn:7007708",
        "tgn:7029392"
    ],
    "tgn:id":2771927,
    "tgn:name":"Wilkes Reservoir",
    "tgn:placetype":[
        "aat:300006191"
    ]
},
  "bbox": [],
  "geometry": {"coordinates":[-122.6167,44.7333],"type":"Point"}
}