{
  "id": 2257787,
  "type": "Feature",
  "properties": {
    "tgn:hierarchy":[
        "tgn:2257787",
        "tgn:1000001",
        "tgn:7012149",
        "tgn:7007157",
        "tgn:1002791",
        "tgn:7029392"
    ],
    "tgn:id":2257787,
    "tgn:name":"Corral Spring",
    "tgn:placetype":[
        "aat:300008697"
    ]
},
  "bbox": [],
  "geometry": {"coordinates":[-120.65,39.1667],"type":"Point"}
}