{
  "id": 2706907,
  "type": "Feature",
  "properties": {
    "tgn:hierarchy":[
        "tgn:2706907",
        "tgn:1000001",
        "tgn:7006451",
        "tgn:7012149",
        "tgn:2000098",
        "tgn:7029392"
    ],
    "tgn:id":2706907,
    "tgn:name":"Swapp Reservoir",
    "tgn:placetype":[
        "aat:300006191"
    ]
},
  "bbox": [],
  "geometry": {"coordinates":[-112.9667,36.5333],"type":"Point"}
}