{
  "id": 7049208,
  "type": "Feature",
  "properties": {
    "tgn:hierarchy":[
        "tgn:7049208",
        "tgn:7003134",
        "tgn:1000003",
        "tgn:7008516",
        "tgn:1000080",
        "tgn:7029392"
    ],
    "tgn:id":7049208,
    "tgn:name":"Canale Derivatore",
    "tgn:placetype":[
        "aat:300006075"
    ]
},
  "bbox": [],
  "geometry": {"coordinates":[10.633333,44.883333],"type":"Point"}
}