{
  "id": 2730455,
  "type": "Feature",
  "properties": {
    "tgn:hierarchy":[
        "tgn:2730455",
        "tgn:1000001",
        "tgn:7016172",
        "tgn:7012149",
        "tgn:2000143",
        "tgn:7029392"
    ],
    "tgn:id":2730455,
    "tgn:name":"True Love Bar",
    "tgn:placetype":[
        "aat:300132348"
    ]
},
  "bbox": [],
  "geometry": {"coordinates":[-90.65,34.8333],"type":"Point"}
}