{
  "id": 2782583,
  "type": "Feature",
  "properties": {
    "tgn:hierarchy":[
        "tgn:2782583",
        "tgn:1000001",
        "tgn:7012149",
        "tgn:2001116",
        "tgn:7007522",
        "tgn:7029392"
    ],
    "tgn:id":2782583,
    "tgn:name":"Wooten Branch",
    "tgn:placetype":[
        "aat:300008699"
    ]
},
  "bbox": [],
  "geometry": {"coordinates":[-89.2667,32.05],"type":"Point"}
}