{
  "id": 7467833,
  "type": "Feature",
  "properties": {
    "tgn:hierarchy":[
        "tgn:7467833",
        "tgn:1000004",
        "tgn:7471332",
        "tgn:1000141",
        "tgn:7029392"
    ],
    "tgn:id":7467833,
    "tgn:name":"Zhaori",
    "tgn:placetype":[
        "aat:300008347"
    ]
},
  "bbox": [],
  "geometry": {"coordinates":[121.210833,24.556111],"type":"Point"}
}