{
  "id": 2426116,
  "type": "Feature",
  "properties": {
    "tgn:hierarchy":[
        "tgn:2426116",
        "tgn:1000001",
        "tgn:7012149",
        "tgn:2000933",
        "tgn:7007515",
        "tgn:7029392"
    ],
    "tgn:id":2426116,
    "tgn:name":"Jones Brook",
    "tgn:placetype":[
        "aat:300008699"
    ]
},
  "bbox": [],
  "geometry": {"coordinates":[-70.8333,43.55],"type":"Point"}
}