{
  "id": 2654055,
  "type": "Feature",
  "properties": {
    "tgn:hierarchy":[
        "tgn:2654055",
        "tgn:1000001",
        "tgn:7012149",
        "tgn:7007157",
        "tgn:1002956",
        "tgn:7029392"
    ],
    "tgn:id":2654055,
    "tgn:name":"Shadequarter Mountain",
    "tgn:placetype":[
        "aat:300008798"
    ]
},
  "bbox": [],
  "geometry": {"coordinates":[-118.9667,36.55],"type":"Point"}
}