{
  "id": 7279154,
  "type": "Feature",
  "properties": {
    "tgn:hierarchy":[
        "tgn:7279154",
        "tgn:1001702",
        "tgn:1000049",
        "tgn:1000002",
        "tgn:7029392"
    ],
    "tgn:id":7279154,
    "tgn:name":"Rosario, Puerto",
    "tgn:placetype":[
        "aat:300132317"
    ]
},
  "bbox": [],
  "geometry": {"coordinates":[-75.161667,-50.016667],"type":"Point"}
}