{
  "id": 2628095,
  "type": "Feature",
  "properties": {
    "tgn:hierarchy":[
        "tgn:2628095",
        "tgn:1000001",
        "tgn:2124001",
        "tgn:7012149",
        "tgn:7007516",
        "tgn:7029392"
    ],
    "tgn:id":2628095,
    "tgn:name":"Rolling View",
    "tgn:placetype":[
        "aat:300008347"
    ]
},
  "bbox": [],
  "geometry": {"coordinates":[-76.85,38.95],"type":"Point"}
}