{
  "id": 7395654,
  "type": "Feature",
  "properties": {
    "tgn:hierarchy":[
        "tgn:7395654",
        "tgn:1000001",
        "tgn:7005601",
        "tgn:7005560",
        "tgn:7029392"
    ],
    "tgn:id":7395654,
    "tgn:name":"San Isidro",
    "tgn:placetype":[
        "aat:300007783"
    ]
},
  "bbox": [],
  "geometry": {"coordinates":[-102.45,25.533333],"type":"Point"}
}