<<<<<<< HEAD
{
  "id": 2330307,
  "type": "Feature",
  "properties": {
    "tgn:hierarchy":[
        "tgn:2330307",
        "tgn:1000001",
        "tgn:7012149",
        "tgn:1002379",
        "tgn:7007826",
        "tgn:7029392"
    ],
    "tgn:id":2330307,
    "tgn:name":"Flat Bank Creek",
    "tgn:placetype":[
        "aat:300008706"
    ]
},
  "bbox": [],
  "geometry": {"coordinates":[-95.5333,29.5333],"type":"Point"}
}
=======
{"geometry":{"type":"Point","coordinates":[-95.533300,29.533300]},"type":"Feature","properties":{"hierarchy":["tgn:2330307","tgn:1000001","tgn:7012149","tgn:1002379","tgn:7007826","tgn:7029392"],"placetype":["aat:300008706"],"id":2330307,"name:xx":"Flat Bank Creek"}}
>>>>>>> 03f74aca74312dbeaf24d7e61306dd6a786dc3d0
