{
  "id": 7573440,
  "type": "Feature",
  "properties": {
    "tgn:hierarchy":[
        "tgn:7573440",
        "tgn:1000004",
        "tgn:7000198",
        "tgn:7016722",
        "tgn:7029392"
    ],
    "tgn:id":7573440,
    "tgn:name:en":"Kachnoda Kal\u0101n",
    "tgn:placetype":[
        "aat:300008347"
    ]
},
  "bbox": [],
  "geometry": {"coordinates":[78.563653,24.742411],"type":"Point"}
}