{
  "id": 7450102,
  "type": "Feature",
  "properties": {
    "tgn:hierarchy":[
        "tgn:7450102",
        "tgn:7002443",
        "tgn:1000003",
        "tgn:7018973",
        "tgn:7008591",
        "tgn:7029392"
    ],
    "tgn:id":7450102,
    "tgn:name:en":"Glais",
    "tgn:placetype":[
        "aat:300008347"
    ]
},
  "bbox": [],
  "geometry": {"coordinates":[-3.883333,51.683333],"type":"Point"}
}