<<<<<<< HEAD
{
  "id": 7117973,
  "type": "Feature",
  "properties": {
    "tgn:hierarchy":[
        "tgn:7117973",
        "tgn:1000003",
        "tgn:7003677",
        "tgn:7000084",
        "tgn:7029392"
    ],
    "tgn:id":7117973,
    "tgn:name":"\u00d6stertalsperre",
    "tgn:placetype":[
        "aat:300006191"
    ]
},
  "bbox": [],
  "geometry": {"coordinates":[7.8,51.166667],"type":"Point"}
}
=======
{"geometry":{"type":"Point","coordinates":[7.800000,51.166667]},"type":"Feature","properties":{"hierarchy":["tgn:7117973","tgn:1000003","tgn:7003677","tgn:7000084","tgn:7029392"],"placetype":["aat:300006191"],"id":7117973,"name:xx":"\u00d6stertalsperre"}}
>>>>>>> 03f74aca74312dbeaf24d7e61306dd6a786dc3d0
