{
  "id": 7268640,
  "type": "Feature",
  "properties": {
    "tgn:hierarchy":[
        "tgn:7268640",
        "tgn:7003619",
        "tgn:1000003",
        "tgn:7016845",
        "tgn:7029392"
    ],
    "tgn:id":7268640,
    "tgn:name:nl":"Noord Ginkel",
    "tgn:placetype":[
        "aat:300387502"
    ]
},
  "bbox": [],
  "geometry": {"coordinates":[5.766667,52.05],"type":"Point"}
}