{
  "id": 2633236,
  "type": "Feature",
  "properties": {
    "tgn:hierarchy":[
        "tgn:2633236",
        "tgn:1000001",
        "tgn:1002293",
        "tgn:7012149",
        "tgn:7007708",
        "tgn:7029392"
    ],
    "tgn:id":2633236,
    "tgn:name":"Ruley",
    "tgn:placetype":[
        "aat:300008347"
    ]
},
  "bbox": [],
  "geometry": {"coordinates":[-122.9667,45.8167],"type":"Point"}
}