{
  "id": 7273201,
  "type": "Feature",
  "properties": {
    "tgn:concordances":{
        "gn:id":"2744811"
    },
    "tgn:hierarchy":[
        "tgn:7273201",
        "tgn:1000003",
        "tgn:7003613",
        "tgn:7016845",
        "tgn:7029392"
    ],
    "tgn:id":7273201,
    "tgn:name:nl":"Wessinghuizen",
    "tgn:placetype":[
        "aat:300008347"
    ]
},
  "bbox": [],
  "geometry": {"coordinates":[7.083333,53.05],"type":"Point"}
}