{
  "id": 2474688,
  "type": "Feature",
  "properties": {
    "tgn:hierarchy":[
        "tgn:2474688",
        "tgn:2002240",
        "tgn:1000001",
        "tgn:7012149",
        "tgn:7007920",
        "tgn:7029392"
    ],
    "tgn:id":2474688,
    "tgn:name":"Lower Snively Spring",
    "tgn:placetype":[
        "aat:300008697"
    ]
},
  "bbox": [],
  "geometry": {"coordinates":[-119.7167,46.45],"type":"Point"}
}