{
  "id": 7076670,
  "type": "Feature",
  "properties": {
    "tgn:hierarchy":[
        "tgn:7076670",
        "tgn:1000003",
        "tgn:7003687",
        "tgn:7000084",
        "tgn:7029392"
    ],
    "tgn:id":7076670,
    "tgn:name":"Ziethnitz",
    "tgn:placetype":[
        "aat:300008347"
    ]
},
  "bbox": [],
  "geometry": {"coordinates":[11.133333,52.833333],"type":"Point"}
}