{
  "id": 2463790,
  "type": "Feature",
  "properties": {
    "tgn:hierarchy":[
        "tgn:2463790",
        "tgn:2001422",
        "tgn:1000001",
        "tgn:7012149",
        "tgn:7007564",
        "tgn:7029392"
    ],
    "tgn:id":2463790,
    "tgn:name":"Lockes Hill",
    "tgn:placetype":[
        "aat:300008798"
    ]
},
  "bbox": [],
  "geometry": {"coordinates":[-71.3667,43.5667],"type":"Point"}
}