<<<<<<< HEAD
{
  "id": 2332206,
  "type": "Feature",
  "properties": {
    "tgn:hierarchy":[
        "tgn:2332206",
        "tgn:1000001",
        "tgn:7012149",
        "tgn:2000986",
        "tgn:7007520",
        "tgn:7029392"
    ],
    "tgn:id":2332206,
    "tgn:name":"Flintsteel River",
    "tgn:placetype":[
        "aat:300008707"
    ]
},
  "bbox": [],
  "geometry": {"coordinates":[-89.0833,46.75],"type":"Point"}
}
=======
{"geometry":{"type":"Point","coordinates":[-89.083300,46.750000]},"type":"Feature","properties":{"hierarchy":["tgn:2332206","tgn:1000001","tgn:7012149","tgn:2000986","tgn:7007520","tgn:7029392"],"placetype":["aat:300008707"],"id":2332206,"name:xx":"Flintsteel River"}}
>>>>>>> 03f74aca74312dbeaf24d7e61306dd6a786dc3d0
