{
  "id": 2658034,
  "type": "Feature",
  "properties": {
    "tgn:hierarchy":[
        "tgn:2658034",
        "tgn:1000001",
        "tgn:2000677",
        "tgn:7012149",
        "tgn:7007254",
        "tgn:7029392"
    ],
    "tgn:id":2658034,
    "tgn:name":"Shellrock Creek",
    "tgn:placetype":[
        "aat:300008706"
    ]
},
  "bbox": [],
  "geometry": {"coordinates":[-96.75,37.0667],"type":"Point"}
}