<<<<<<< HEAD
{
  "id": 7360309,
  "type": "Feature",
  "properties": {
    "tgn:hierarchy":[
        "tgn:7360309",
        "tgn:7005583",
        "tgn:1000001",
        "tgn:7005560",
        "tgn:7029392"
    ],
    "tgn:id":7360309,
    "tgn:name":"Cuencam\u00e9, Arroyo de",
    "tgn:placetype":[
        "aat:300008699"
    ]
},
  "bbox": [],
  "geometry": {"coordinates":[-103.783333,25.266667],"type":"Point"}
}
=======
{"geometry":{"type":"Point","coordinates":[-103.783333,25.266667]},"type":"Feature","properties":{"hierarchy":["tgn:7360309","tgn:7005583","tgn:1000001","tgn:7005560","tgn:7029392"],"placetype":["aat:300008699"],"id":7360309,"name:xx":"Cuencam\u00e9, Arroyo de"}}
>>>>>>> 03f74aca74312dbeaf24d7e61306dd6a786dc3d0
