{
  "id": 1082336,
  "type": "Feature",
  "properties": {
    "tgn:hierarchy":[
        "tgn:1082336",
        "tgn:1001194",
        "tgn:1000004",
        "tgn:7000299",
        "tgn:7029392"
    ],
    "tgn:id":1082336,
    "tgn:name":"Puan",
    "tgn:placetype":[
        "aat:300008347"
    ]
},
  "bbox": [],
  "geometry": {"coordinates":[126.7333,35.7333],"type":"Point"}
}