{
  "id": 7388954,
  "type": "Feature",
  "properties": {
    "tgn:hierarchy":[
        "tgn:7388954",
        "tgn:7005586",
        "tgn:1000001",
        "tgn:7005560",
        "tgn:7029392"
    ],
    "tgn:id":7388954,
    "tgn:name":"Pilas",
    "tgn:placetype":[
        "aat:300008347"
    ]
},
  "bbox": [],
  "geometry": {"coordinates":[-102.033333,20.95],"type":"Point"}
}