{
  "id": 7188267,
  "type": "Feature",
  "properties": {
    "tgn:hierarchy":[
        "tgn:7188267",
        "tgn:1000003",
        "tgn:7003682",
        "tgn:7000084",
        "tgn:7029392"
    ],
    "tgn:id":7188267,
    "tgn:name":"E\u00dfweiler",
    "tgn:placetype":[
        "aat:300008347"
    ]
},
  "bbox": [],
  "geometry": {"coordinates":[7.566667,49.55],"type":"Point"}
}