{
  "id": 2517510,
  "type": "Feature",
  "properties": {
    "tgn:hierarchy":[
        "tgn:2517510",
        "tgn:1000001",
        "tgn:2000322",
        "tgn:7012149",
        "tgn:7007248",
        "tgn:7029392"
    ],
    "tgn:id":2517510,
    "tgn:name":"Minska Pinska Lake",
    "tgn:placetype":[
        "aat:300006191"
    ]
},
  "bbox": [],
  "geometry": {"coordinates":[-84.2833,33.5333],"type":"Point"}
}