{
  "id": 7310815,
  "type": "Feature",
  "properties": {
    "tgn:hierarchy":[
        "tgn:7310815",
        "tgn:7002464",
        "tgn:1000049",
        "tgn:1000002",
        "tgn:7029392"
    ],
    "tgn:id":7310815,
    "tgn:name":"Oficina Trinidad",
    "tgn:placetype":[
        "aat:300008057"
    ]
},
  "bbox": [],
  "geometry": {"coordinates":[-70.083333,-19.55],"type":"Point"}
}