{
  "id": 2516074,
  "type": "Feature",
  "properties": {
    "tgn:hierarchy":[
        "tgn:2516074",
        "tgn:1000001",
        "tgn:2001476",
        "tgn:7012149",
        "tgn:7007709",
        "tgn:7029392"
    ],
    "tgn:id":2516074,
    "tgn:name":"Mine Branch",
    "tgn:placetype":[
        "aat:300008699"
    ]
},
  "bbox": [],
  "geometry": {"coordinates":[-81.5833,36.0833],"type":"Point"}
}