{
  "id": 7252674,
  "type": "Feature",
  "properties": {
    "tgn:hierarchy":[
        "tgn:7252674",
        "tgn:7003458",
        "tgn:1000003",
        "tgn:1000063",
        "tgn:7018236",
        "tgn:7029392"
    ],
    "tgn:id":7252674,
    "tgn:name":"Stokveld",
    "tgn:placetype":[
        "aat:300000206"
    ]
},
  "bbox": [],
  "geometry": {"coordinates":[3.220277,51.171552],"type":"Point"}
}