{
  "id": 7535037,
  "type": "Feature",
  "properties": {
    "tgn:hierarchy":[
        "tgn:7535037",
        "tgn:7001242",
        "tgn:7016833",
        "tgn:1001113",
        "tgn:7029392"
    ],
    "tgn:id":7535037,
    "tgn:name":"Kafr Ab\u016b \u0162ar\u012byah",
    "tgn:placetype":[
        "aat:300008347"
    ]
},
  "bbox": [],
  "geometry": {"coordinates":[31.533218,30.799398],"type":"Point"}
}