<<<<<<< HEAD
{
  "id": 7370925,
  "type": "Feature",
  "properties": {
    "tgn:hierarchy":[
        "tgn:7370925",
        "tgn:1001835",
        "tgn:1000001",
        "tgn:7005560",
        "tgn:7029392"
    ],
    "tgn:id":7370925,
    "tgn:name":"Jes\u00fas, Cerro",
    "tgn:placetype":[
        "aat:300008795"
    ]
},
  "bbox": [],
  "geometry": {"coordinates":[-115.95,32.35],"type":"Point"}
}
=======
{"geometry":{"type":"Point","coordinates":[-115.950000,32.350000]},"type":"Feature","properties":{"hierarchy":["tgn:7370925","tgn:1001835","tgn:1000001","tgn:7005560","tgn:7029392"],"placetype":["aat:300008795"],"id":7370925,"name:xx":"Jes\u00fas, Cerro"}}
>>>>>>> 03f74aca74312dbeaf24d7e61306dd6a786dc3d0
