{
  "id": 7236454,
  "type": "Feature",
  "properties": {
    "tgn:hierarchy":[
        "tgn:7236454",
        "tgn:1042193",
        "tgn:7002705",
        "tgn:1000003",
        "tgn:1000074",
        "tgn:7029392"
    ],
    "tgn:id":7236454,
    "tgn:name":"Ag\u00edou Nikol\u00e1ou, Nis\u00edda",
    "tgn:placetype":[
        "aat:300008791"
    ]
},
  "bbox": [],
  "geometry": {"coordinates":[20.416111,39.270833],"type":"Point"}
}