{
  "id": 7214432,
  "type": "Feature",
  "properties": {
    "tgn:hierarchy":[
        "tgn:7214432",
        "tgn:1000003",
        "tgn:7003676",
        "tgn:7000084",
        "tgn:7029392"
    ],
    "tgn:id":7214432,
    "tgn:name":"Birkenbusch",
    "tgn:placetype":[
        "aat:300008347"
    ]
},
  "bbox": [],
  "geometry": {"coordinates":[8.333333,52.766667],"type":"Point"}
}