{
  "id": 7135848,
  "type": "Feature",
  "properties": {
    "tgn:hierarchy":[
        "tgn:7135848",
        "tgn:7003669",
        "tgn:1000003",
        "tgn:7000084",
        "tgn:7029392"
    ],
    "tgn:id":7135848,
    "tgn:name":"Nacht-Wand",
    "tgn:placetype":[
        "aat:300008749"
    ]
},
  "bbox": [],
  "geometry": {"coordinates":[12.966667,47.683333],"type":"Point"}
}