{
  "id": 2320613,
  "type": "Feature",
  "properties": {
    "tgn:hierarchy":[
        "tgn:2320613",
        "tgn:1000001",
        "tgn:7012149",
        "tgn:2001716",
        "tgn:7007708",
        "tgn:7029392"
    ],
    "tgn:id":2320613,
    "tgn:name":"Ewing Creek",
    "tgn:placetype":[
        "aat:300008706"
    ]
},
  "bbox": [],
  "geometry": {"coordinates":[-123.1167,43.65],"type":"Point"}
}