{
  "id": 2246875,
  "type": "Feature",
  "properties": {
    "tgn:hierarchy":[
        "tgn:2246875",
        "tgn:1000001",
        "tgn:2000460",
        "tgn:7012149",
        "tgn:7007250",
        "tgn:7029392"
    ],
    "tgn:id":2246875,
    "tgn:name":"Cochran Creek",
    "tgn:placetype":[
        "aat:300008706"
    ]
},
  "bbox": [],
  "geometry": {"coordinates":[-116.2833,48.2667],"type":"Point"}
}