{
  "id": 2347697,
  "type": "Feature",
  "properties": {
    "tgn:hierarchy":[
        "tgn:2347697",
        "tgn:1000001",
        "tgn:7006451",
        "tgn:7012149",
        "tgn:2000098",
        "tgn:7029392"
    ],
    "tgn:id":2347697,
    "tgn:name":"Georges Spring",
    "tgn:placetype":[
        "aat:300008697"
    ]
},
  "bbox": [],
  "geometry": {"coordinates":[-113.3167,36.1667],"type":"Point"}
}