{
  "id": 7335272,
  "type": "Feature",
  "properties": {
    "tgn:hierarchy":[
        "tgn:7335272",
        "tgn:7002758",
        "tgn:7002841",
        "tgn:1000003",
        "tgn:1000095",
        "tgn:7029392"
    ],
    "tgn:id":7335272,
    "tgn:name":"Gordo, Cerro",
    "tgn:placetype":[
        "aat:300008777"
    ]
},
  "bbox": [],
  "geometry": {"coordinates":[-5.333333,37.35],"type":"Point"}
}