<<<<<<< HEAD
{
  "id": 2153324,
  "type": "Feature",
  "properties": {
    "tgn:hierarchy":[
        "tgn:2153324",
        "tgn:1000001",
        "tgn:2000469",
        "tgn:7012149",
        "tgn:7007250",
        "tgn:7029392"
    ],
    "tgn:id":2153324,
    "tgn:name":"Bean Creek",
    "tgn:placetype":[
        "aat:300008706"
    ]
},
  "bbox": [],
  "geometry": {"coordinates":[-115.3333,46.8667],"type":"Point"}
}
=======
{"geometry":{"type":"Point","coordinates":[-115.333300,46.866700]},"type":"Feature","properties":{"hierarchy":["tgn:2153324","tgn:1000001","tgn:2000469","tgn:7012149","tgn:7007250","tgn:7029392"],"placetype":["aat:300008706"],"id":2153324,"name:xx":"Bean Creek"}}
>>>>>>> 03f74aca74312dbeaf24d7e61306dd6a786dc3d0
