{
  "id": 2471886,
  "type": "Feature",
  "properties": {
    "tgn:hierarchy":[
        "tgn:2471886",
        "tgn:1000001",
        "tgn:7012149",
        "tgn:2002095",
        "tgn:7007826",
        "tgn:7029392"
    ],
    "tgn:id":2471886,
    "tgn:name":"Lost Spring Hollow",
    "tgn:placetype":[
        "aat:300008761"
    ]
},
  "bbox": [],
  "geometry": {"coordinates":[-98.1833,29.25],"type":"Point"}
}