{
  "id": 7166267,
  "type": "Feature",
  "properties": {
    "tgn:hierarchy":[
        "tgn:7166267",
        "tgn:7003669",
        "tgn:1000003",
        "tgn:7000084",
        "tgn:7029392"
    ],
    "tgn:id":7166267,
    "tgn:name":"Hasen-Berg",
    "tgn:placetype":[
        "aat:300008777"
    ]
},
  "bbox": [],
  "geometry": {"coordinates":[11.266667,50.266667],"type":"Point"}
}