{
  "id": 2093051,
  "type": "Feature",
  "properties": {
    "tgn:hierarchy":[
        "tgn:2093051",
        "tgn:1000001",
        "tgn:7012149",
        "tgn:1002876",
        "tgn:7007710",
        "tgn:7029392"
    ],
    "tgn:id":2093051,
    "tgn:name":"Shoemakers",
    "tgn:placetype":[
        "aat:300008347"
    ]
},
  "bbox": [],
  "geometry": {"coordinates":[-76.1167,40.8167],"type":"Point"}
}