{
  "id": 7109912,
  "type": "Feature",
  "properties": {
    "tgn:hierarchy":[
        "tgn:7109912",
        "tgn:7003669",
        "tgn:1000003",
        "tgn:7000084",
        "tgn:7029392"
    ],
    "tgn:id":7109912,
    "tgn:name":"Rammertshof",
    "tgn:placetype":[
        "aat:300000206"
    ]
},
  "bbox": [],
  "geometry": {"coordinates":[11.983333,49.266667],"type":"Point"}
}