{
  "id": 2715297,
  "type": "Feature",
  "properties": {
    "tgn:hierarchy":[
        "tgn:2715297",
        "tgn:1000001",
        "tgn:7012149",
        "tgn:2001288",
        "tgn:7007524",
        "tgn:7029392"
    ],
    "tgn:id":2715297,
    "tgn:name":"Teresa Mine",
    "tgn:placetype":[
        "aat:300000390"
    ]
},
  "bbox": [],
  "geometry": {"coordinates":[-111.9667,45.2667],"type":"Point"}
}