{
  "id": 2300644,
  "type": "Feature",
  "properties": {
    "tgn:hierarchy":[
        "tgn:2300644",
        "tgn:1000001",
        "tgn:7012149",
        "tgn:2001917",
        "tgn:7007825",
        "tgn:7029392"
    ],
    "tgn:id":2300644,
    "tgn:name":"Dunbar Branch",
    "tgn:placetype":[
        "aat:300008699"
    ]
},
  "bbox": [],
  "geometry": {"coordinates":[-87.6333,36.45],"type":"Point"}
}