{
  "id": 7411668,
  "type": "Feature",
  "properties": {
    "tgn:hierarchy":[
        "tgn:7411668",
        "tgn:1000001",
        "tgn:7005596",
        "tgn:7005560",
        "tgn:7029392"
    ],
    "tgn:id":7411668,
    "tgn:name:es":"Las Gaviotas Sur",
    "tgn:placetype":[
        "aat:300008347"
    ]
},
  "bbox": [],
  "geometry": {"coordinates":[-92.891667,17.966667],"type":"Point"}
}