{
  "id": 2280539,
  "type": "Feature",
  "properties": {
    "tgn:hierarchy":[
        "tgn:2280539",
        "tgn:1000001",
        "tgn:7012149",
        "tgn:2001304",
        "tgn:7007524",
        "tgn:7029392"
    ],
    "tgn:id":2280539,
    "tgn:name":"Deemer Peak",
    "tgn:placetype":[
        "aat:300008798"
    ]
},
  "bbox": [],
  "geometry": {"coordinates":[-114.7667,47.4833],"type":"Point"}
}