{
  "id": 7322091,
  "type": "Feature",
  "properties": {
    "tgn:hierarchy":[
        "tgn:7322091",
        "tgn:1001637",
        "tgn:1000049",
        "tgn:1000002",
        "tgn:7029392"
    ],
    "tgn:id":7322091,
    "tgn:name":"Atacalco, Paso",
    "tgn:placetype":[
        "aat:300259572"
    ]
},
  "bbox": [],
  "geometry": {"coordinates":[-71.166667,-37.233333],"type":"Point"}
}