<<<<<<< HEAD
{
  "id": 7364846,
  "type": "Feature",
  "properties": {
    "tgn:hierarchy":[
        "tgn:7364846",
        "tgn:7005587",
        "tgn:1000001",
        "tgn:7005560",
        "tgn:7029392"
    ],
    "tgn:id":7364846,
    "tgn:name":"El Zapote",
    "tgn:placetype":[
        "aat:300007783"
    ]
},
  "bbox": [],
  "geometry": {"coordinates":[-99.7,20.383333],"type":"Point"}
}
=======
{"geometry":{"type":"Point","coordinates":[-99.700000,20.383333]},"type":"Feature","properties":{"hierarchy":["tgn:7364846","tgn:7005587","tgn:1000001","tgn:7005560","tgn:7029392"],"placetype":["aat:300007783"],"id":7364846,"name:xx":"El Zapote"}}
>>>>>>> 03f74aca74312dbeaf24d7e61306dd6a786dc3d0
