{
  "id": 2562491,
  "type": "Feature",
  "properties": {
    "tgn:hierarchy":[
        "tgn:2562491",
        "tgn:1000001",
        "tgn:7012149",
        "tgn:2002124",
        "tgn:7007827",
        "tgn:7029392"
    ],
    "tgn:id":2562491,
    "tgn:name":"Ouray Park Canal",
    "tgn:placetype":[
        "aat:300006075"
    ]
},
  "bbox": [],
  "geometry": {"coordinates":[-109.7667,40.2833],"type":"Point"}
}