{
  "id": 7417764,
  "type": "Feature",
  "properties": {
    "tgn:hierarchy":[
        "tgn:7417764",
        "tgn:1000001",
        "tgn:7005591",
        "tgn:7005560",
        "tgn:7029392"
    ],
    "tgn:id":7417764,
    "tgn:name:es":"Xiquila, R\u00edo",
    "tgn:placetype":[
        "aat:300008699"
    ]
},
  "bbox": [],
  "geometry": {"coordinates":[-97.218611,18.030833],"type":"Point"}
}