{
  "id": 7416626,
  "type": "Feature",
  "properties": {
    "tgn:hierarchy":[
        "tgn:7416626",
        "tgn:1000001",
        "tgn:7005591",
        "tgn:7005560",
        "tgn:7029392"
    ],
    "tgn:id":7416626,
    "tgn:name:es":"Tavehua",
    "tgn:placetype":[
        "aat:300008347"
    ]
},
  "bbox": [],
  "geometry": {"coordinates":[-96.216667,17.25],"type":"Point"}
}