{
  "id": 2560920,
  "type": "Feature",
  "properties": {
    "tgn:hierarchy":[
        "tgn:2560920",
        "tgn:1000001",
        "tgn:7012149",
        "tgn:2001457",
        "tgn:7007566",
        "tgn:7029392"
    ],
    "tgn:id":2560920,
    "tgn:name":"Oro Grande Company of Pennsylvania",
    "tgn:placetype":[
        "aat:300000390"
    ]
},
  "bbox": [],
  "geometry": {"coordinates":[-105.8167,36.2333],"type":"Point"}
}