{
  "id": 7501683,
  "type": "Feature",
  "properties": {
    "tgn:hierarchy":[
        "tgn:7501683",
        "tgn:1000004",
        "tgn:7471332",
        "tgn:1000141",
        "tgn:7029392"
    ],
    "tgn:id":7501683,
    "tgn:name":"Long'en Zhen",
    "tgn:placetype":[
        "aat:300006075"
    ]
},
  "bbox": [],
  "geometry": {"coordinates":[121.001667,24.802778],"type":"Point"}
}