{
  "id": 2618872,
  "type": "Feature",
  "properties": {
    "tgn:hierarchy":[
        "tgn:2618872",
        "tgn:1000001",
        "tgn:7012149",
        "tgn:2002111",
        "tgn:7007827",
        "tgn:7029392"
    ],
    "tgn:id":2618872,
    "tgn:name":"Right Hand Creek",
    "tgn:placetype":[
        "aat:300008706"
    ]
},
  "bbox": [],
  "geometry": {"coordinates":[-112.9667,37.5833],"type":"Point"}
}