{
  "id": 7559200,
  "type": "Feature",
  "properties": {
    "tgn:hierarchy":[
        "tgn:7559200",
        "tgn:1000004",
        "tgn:7000198",
        "tgn:1001894",
        "tgn:7029392"
    ],
    "tgn:id":7559200,
    "tgn:name:en":"Rahatia",
    "tgn:placetype":[
        "aat:300008347"
    ]
},
  "bbox": [],
  "geometry": {"coordinates":[75.136407,21.860355],"type":"Point"}
}