{
  "id": 2619344,
  "type": "Feature",
  "properties": {
    "tgn:hierarchy":[
        "tgn:2619344",
        "tgn:1000001",
        "tgn:7012149",
        "tgn:2000234",
        "tgn:7007158",
        "tgn:7029392"
    ],
    "tgn:id":2619344,
    "tgn:name":"Rim Rock Mine",
    "tgn:placetype":[
        "aat:300000390"
    ]
},
  "bbox": [],
  "geometry": {"coordinates":[-108.85,38.15],"type":"Point"}
}