{
  "id": 2634694,
  "type": "Feature",
  "properties": {
    "tgn:hierarchy":[
        "tgn:2634694",
        "tgn:1000001",
        "tgn:7012149",
        "tgn:1002992",
        "tgn:7007252",
        "tgn:7029392"
    ],
    "tgn:id":2634694,
    "tgn:name":"Rutherford Hollow",
    "tgn:placetype":[
        "aat:300008761"
    ]
},
  "bbox": [],
  "geometry": {"coordinates":[-86.0833,38.65],"type":"Point"}
}