{
  "id": 7513030,
  "type": "Feature",
  "properties": {
    "tgn:hierarchy":[
        "tgn:7513030",
        "tgn:1009227",
        "tgn:1000226",
        "tgn:1000006",
        "tgn:7016850",
        "tgn:7029392"
    ],
    "tgn:id":7513030,
    "tgn:name:en":"Happy Valley",
    "tgn:placetype":[
        "aat:300008761"
    ]
},
  "bbox": [],
  "geometry": {"coordinates":[170.783333,-43.05],"type":"Point"}
}