{
  "id": 2733670,
  "type": "Feature",
  "properties": {
    "tgn:hierarchy":[
        "tgn:2733670",
        "tgn:1000001",
        "tgn:7012149",
        "tgn:2001718",
        "tgn:7007708",
        "tgn:7029392"
    ],
    "tgn:id":2733670,
    "tgn:name":"Turnbull Mountain",
    "tgn:placetype":[
        "aat:300008798"
    ]
},
  "bbox": [],
  "geometry": {"coordinates":[-117.85,43.3333],"type":"Point"}
}