{
  "id": 7483546,
  "type": "Feature",
  "properties": {
    "tgn:hierarchy":[
        "tgn:7483546",
        "tgn:7001004",
        "tgn:1000004",
        "tgn:1000141",
        "tgn:7029392"
    ],
    "tgn:id":7483546,
    "tgn:name":"Tudigonglun",
    "tgn:placetype":[
        "aat:300387002"
    ]
},
  "bbox": [],
  "geometry": {"coordinates":[120.635833,23.025556],"type":"Point"}
}