<<<<<<< HEAD
{
  "id": 7483546,
  "type": "Feature",
  "properties": {
    "tgn:hierarchy":[
        "tgn:7483546",
        "tgn:7001004",
        "tgn:1000004",
        "tgn:1000141",
        "tgn:7029392"
    ],
    "tgn:id":7483546,
    "tgn:name":"Tudigonglun",
    "tgn:placetype":[
        "aat:300387002"
    ]
},
  "bbox": [],
  "geometry": {"coordinates":[120.635833,23.025556],"type":"Point"}
}
=======
{"geometry":{"type":"Point","coordinates":[120.635833,23.025556]},"type":"Feature","properties":{"hierarchy":["tgn:7483546","tgn:7001004","tgn:1000004","tgn:1000141","tgn:7029392"],"placetype":["aat:300387002"],"id":7483546,"name:xx":"Tudigonglun"}}
>>>>>>> 03f74aca74312dbeaf24d7e61306dd6a786dc3d0
