{
  "id": 7581432,
  "type": "Feature",
  "properties": {
    "tgn:hierarchy":[
        "tgn:7581432",
        "tgn:1000004",
        "tgn:7000198",
        "tgn:7001797",
        "tgn:7029392"
    ],
    "tgn:id":7581432,
    "tgn:name:en":"Tiruv\u0101d\u016br",
    "tgn:placetype":[
        "aat:300008347"
    ]
},
  "bbox": [],
  "geometry": {"coordinates":[78.316667,9.966667],"type":"Point"}
}