{
  "id": 2398541,
  "type": "Feature",
  "properties": {
    "tgn:hierarchy":[
        "tgn:2398541",
        "tgn:1000001",
        "tgn:7012149",
        "tgn:2002273",
        "tgn:7013961",
        "tgn:7029392"
    ],
    "tgn:id":2398541,
    "tgn:name":"Hoover Fork",
    "tgn:placetype":[
        "aat:300008699"
    ]
},
  "bbox": [],
  "geometry": {"coordinates":[-82.1833,37.9333],"type":"Point"}
}