{
  "id": 7030071,
  "type": "Feature",
  "properties": {
    "tgn:hierarchy":[
        "tgn:7030071",
        "tgn:7002445",
        "tgn:1000003",
        "tgn:7008166",
        "tgn:7008591",
        "tgn:7029392"
    ],
    "tgn:id":7030071,
    "tgn:name":"Leathley",
    "tgn:name:ang":"Ledelai",
    "tgn:placetype":[
        "aat:300008347",
        "aat:300008372"
    ]
},
  "bbox": [],
  "geometry": {"coordinates":[-1.65,53.916667],"type":"Point"}
}