{
  "id": 7281002,
  "type": "Feature",
  "properties": {
    "tgn:hierarchy":[
        "tgn:7281002",
        "tgn:7016598",
        "tgn:1000049",
        "tgn:1000002",
        "tgn:7029392"
    ],
    "tgn:id":7281002,
    "tgn:name":"Sierra Aguilar",
    "tgn:placetype":[
        "aat:300387033"
    ]
},
  "bbox": [],
  "geometry": {"coordinates":[-69.633333,-25.55],"type":"Point"}
}