<<<<<<< HEAD
{
  "id": 7051555,
  "type": "Feature",
  "properties": {
    "tgn:hierarchy":[
        "tgn:7051555",
        "tgn:1000003",
        "tgn:7003122",
        "tgn:1000080",
        "tgn:7029392"
    ],
    "tgn:id":7051555,
    "tgn:name":"Muto, Torrente",
    "tgn:placetype":[
        "aat:300008699"
    ]
},
  "bbox": [],
  "geometry": {"coordinates":[15.3,38.2],"type":"Point"}
}
=======
{"geometry":{"type":"Point","coordinates":[15.300000,38.200000]},"type":"Feature","properties":{"hierarchy":["tgn:7051555","tgn:1000003","tgn:7003122","tgn:1000080","tgn:7029392"],"placetype":["aat:300008699"],"id":7051555,"name:xx":"Muto, Torrente"}}
>>>>>>> 03f74aca74312dbeaf24d7e61306dd6a786dc3d0
