{
  "id": 7412031,
  "type": "Feature",
  "properties": {
    "tgn:hierarchy":[
        "tgn:7412031",
        "tgn:7005587",
        "tgn:1000001",
        "tgn:7005560",
        "tgn:7029392"
    ],
    "tgn:id":7412031,
    "tgn:name:es":"Pepeyoca de Cabrera",
    "tgn:placetype":[
        "aat:300008347"
    ]
},
  "bbox": [],
  "geometry": {"coordinates":[-98.219444,20.980556],"type":"Point"}
}