{
  "id": 2715186,
  "type": "Feature",
  "properties": {
    "tgn:hierarchy":[
        "tgn:2715186",
        "tgn:1000001",
        "tgn:7012149",
        "tgn:2001291",
        "tgn:7007524",
        "tgn:7029392"
    ],
    "tgn:id":2715186,
    "tgn:name":"Tepee Creek",
    "tgn:placetype":[
        "aat:300008706"
    ]
},
  "bbox": [],
  "geometry": {"coordinates":[-114.5333,46.8167],"type":"Point"}
}