{
  "id": 7076729,
  "type": "Feature",
  "properties": {
    "tgn:hierarchy":[
        "tgn:7076729",
        "tgn:1000003",
        "tgn:7003682",
        "tgn:7000084",
        "tgn:7029392"
    ],
    "tgn:id":7076729,
    "tgn:name":"Zellertal",
    "tgn:placetype":[
        "aat:300387173"
    ]
},
  "bbox": [],
  "geometry": {"coordinates":[8.117778,49.641111],"type":"Point"}
}