{
  "id": 2224099,
  "type": "Feature",
  "properties": {
    "tgn:hierarchy":[
        "tgn:2224099",
        "tgn:1000001",
        "tgn:7012149",
        "tgn:1002384",
        "tgn:7007523",
        "tgn:7029392"
    ],
    "tgn:id":2224099,
    "tgn:name":"Carvers Lake",
    "tgn:placetype":[
        "aat:300006191"
    ]
},
  "bbox": [],
  "geometry": {"coordinates":[-91.0333,38.3167],"type":"Point"}
}