{
  "id": 2169417,
  "type": "Feature",
  "properties": {
    "tgn:hierarchy":[
        "tgn:2169417",
        "tgn:1000001",
        "tgn:2000772",
        "tgn:7012149",
        "tgn:7007255",
        "tgn:7029392"
    ],
    "tgn:id":2169417,
    "tgn:name":"Big Leslie Branch",
    "tgn:placetype":[
        "aat:300008699"
    ]
},
  "bbox": [],
  "geometry": {"coordinates":[-83.3333,37.6167],"type":"Point"}
}