{
  "id": 7592942,
  "type": "Feature",
  "properties": {
    "tgn:hierarchy":[
        "tgn:7592942",
        "tgn:1000004",
        "tgn:7000198",
        "tgn:7000799",
        "tgn:7029392"
    ],
    "tgn:id":7592942,
    "tgn:name:en":"Tikri",
    "tgn:placetype":[
        "aat:300008347"
    ]
},
  "bbox": [],
  "geometry": {"coordinates":[74.763889,32.755556],"type":"Point"}
}