{
  "id": 7443821,
  "type": "Feature",
  "properties": {
    "tgn:hierarchy":[
        "tgn:7443821",
        "tgn:7002443",
        "tgn:1000003",
        "tgn:7029493",
        "tgn:7008591",
        "tgn:7029392"
    ],
    "tgn:id":7443821,
    "tgn:name:en":"Yr Eifl Head",
    "tgn:placetype":[
        "aat:300387499"
    ]
},
  "bbox": [],
  "geometry": {"coordinates":[-4.466667,52.983333],"type":"Point"}
}