{
  "id": 2725131,
  "type": "Feature",
  "properties": {
    "tgn:hierarchy":[
        "tgn:2725131",
        "tgn:1000001",
        "tgn:7012149",
        "tgn:2000997",
        "tgn:7007520",
        "tgn:7029392"
    ],
    "tgn:id":2725131,
    "tgn:name":"Tong Branch",
    "tgn:placetype":[
        "aat:300006075"
    ]
},
  "bbox": [],
  "geometry": {"coordinates":[-83.2333,43.4167],"type":"Point"}
}