{
  "id": 2491275,
  "type": "Feature",
  "properties": {
    "tgn:hierarchy":[
        "tgn:2491275",
        "tgn:1000001",
        "tgn:7012149",
        "tgn:2002125",
        "tgn:7007827",
        "tgn:7029392"
    ],
    "tgn:id":2491275,
    "tgn:name":"Maple Canyon",
    "tgn:placetype":[
        "aat:300008761"
    ]
},
  "bbox": [],
  "geometry": {"coordinates":[-112.1833,40.4167],"type":"Point"}
}