{
  "id": 2294274,
  "type": "Feature",
  "properties": {
    "tgn:hierarchy":[
        "tgn:2294274",
        "tgn:1000001",
        "tgn:7012149",
        "tgn:2000388",
        "tgn:7007248",
        "tgn:7029392"
    ],
    "tgn:id":2294274,
    "tgn:name":"Dowdy",
    "tgn:placetype":[
        "aat:300008347"
    ]
},
  "bbox": [],
  "geometry": {"coordinates":[-83.2667,34.0167],"type":"Point"}
}