{
  "id": 2262857,
  "type": "Feature",
  "properties": {
    "tgn:hierarchy":[
        "tgn:2262857",
        "tgn:1000001",
        "tgn:7012149",
        "tgn:7007826",
        "tgn:7029392"
    ],
    "tgn:id":2262857,
    "tgn:name":"Cowboy Creek",
    "tgn:placetype":[
        "aat:300008706"
    ]
},
  "bbox": [],
  "geometry": {"coordinates":[-100.5667,35.55],"type":"Point"}
}