{
  "id": 2771790,
  "type": "Feature",
  "properties": {
    "tgn:hierarchy":[
        "tgn:2771790",
        "tgn:1000001",
        "tgn:7012149",
        "tgn:2000206",
        "tgn:7007158",
        "tgn:7029392"
    ],
    "tgn:id":2771790,
    "tgn:name":"Wiley Springs",
    "tgn:placetype":[
        "aat:300008697"
    ]
},
  "bbox": [],
  "geometry": {"coordinates":[-107.5667,38.75],"type":"Point"}
}