{
  "id": 2256549,
  "type": "Feature",
  "properties": {
    "tgn:hierarchy":[
        "tgn:2256549",
        "tgn:1000001",
        "tgn:7012149",
        "tgn:1002667",
        "tgn:7007919",
        "tgn:7029392"
    ],
    "tgn:id":2256549,
    "tgn:name":"Corbin Hall Farm Pond",
    "tgn:placetype":[
        "aat:300006191"
    ]
},
  "bbox": [],
  "geometry": {"coordinates":[-76.5833,37.6667],"type":"Point"}
}