<<<<<<< HEAD
{
  "id": 2256549,
  "type": "Feature",
  "properties": {
    "tgn:hierarchy":[
        "tgn:2256549",
        "tgn:1000001",
        "tgn:7012149",
        "tgn:1002667",
        "tgn:7007919",
        "tgn:7029392"
    ],
    "tgn:id":2256549,
    "tgn:name":"Corbin Hall Farm Pond",
    "tgn:placetype":[
        "aat:300006191"
    ]
},
  "bbox": [],
  "geometry": {"coordinates":[-76.5833,37.6667],"type":"Point"}
}
=======
{"geometry":{"type":"Point","coordinates":[-76.583300,37.666700]},"type":"Feature","properties":{"hierarchy":["tgn:2256549","tgn:1000001","tgn:7012149","tgn:1002667","tgn:7007919","tgn:7029392"],"placetype":["aat:300006191"],"id":2256549,"name:xx":"Corbin Hall Farm Pond"}}
>>>>>>> 03f74aca74312dbeaf24d7e61306dd6a786dc3d0
