{
  "id": 2572753,
  "type": "Feature",
  "properties": {
    "tgn:hierarchy":[
        "tgn:2572753",
        "tgn:1000001",
        "tgn:2001264",
        "tgn:7012149",
        "tgn:7007524",
        "tgn:7029392"
    ],
    "tgn:id":2572753,
    "tgn:name":"Peal, Mount",
    "tgn:placetype":[
        "aat:300008798"
    ]
},
  "bbox": [],
  "geometry": {"coordinates":[-109.7667,45.15],"type":"Point"}
}