{
  "id": 1007509,
  "type": "Feature",
  "properties": {
    "tgn:hierarchy":[
        "tgn:1007509",
        "tgn:1000001",
        "tgn:1001906",
        "tgn:7005560",
        "tgn:7029392"
    ],
    "tgn:id":1007509,
    "tgn:name":"Isabela, Isla",
    "tgn:placetype":[
        "aat:300008791"
    ]
},
  "bbox": [],
  "geometry": {"coordinates":[-105.916667,21.85],"type":"Point"}
}