{
  "id": 2270449,
  "type": "Feature",
  "properties": {
    "tgn:hierarchy":[
        "tgn:2270449",
        "tgn:1000001",
        "tgn:7012149",
        "tgn:2001608",
        "tgn:7007705",
        "tgn:7029392"
    ],
    "tgn:id":2270449,
    "tgn:name":"Crystal Lake",
    "tgn:placetype":[
        "aat:300008680"
    ]
},
  "bbox": [],
  "geometry": {"coordinates":[-99.9667,47.5167],"type":"Point"}
}