<<<<<<< HEAD
{
  "id": 7364384,
  "type": "Feature",
  "properties": {
    "tgn:hierarchy":[
        "tgn:7364384",
        "tgn:1001853",
        "tgn:1000001",
        "tgn:7005560",
        "tgn:7029392"
    ],
    "tgn:id":7364384,
    "tgn:name":"El Cobre",
    "tgn:placetype":[
        "aat:300007783"
    ]
},
  "bbox": [],
  "geometry": {"coordinates":[-101.083333,25.066667],"type":"Point"}
}
=======
{"geometry":{"type":"Point","coordinates":[-101.083333,25.066667]},"type":"Feature","properties":{"hierarchy":["tgn:7364384","tgn:1001853","tgn:1000001","tgn:7005560","tgn:7029392"],"placetype":["aat:300007783"],"id":7364384,"name:xx":"El Cobre"}}
>>>>>>> 03f74aca74312dbeaf24d7e61306dd6a786dc3d0
