{
  "id": 7470671,
  "type": "Feature",
  "properties": {
    "tgn:hierarchy":[
        "tgn:7470671",
        "tgn:7469009",
        "tgn:1000004",
        "tgn:1000141",
        "tgn:7029392"
    ],
    "tgn:id":7470671,
    "tgn:name":"Qing Shan",
    "tgn:placetype":[
        "aat:300008777"
    ]
},
  "bbox": [],
  "geometry": {"coordinates":[118.320556,24.3925],"type":"Point"}
}