{
  "id": 7529151,
  "type": "Feature",
  "properties": {
    "tgn:hierarchy":[
        "tgn:7529151",
        "tgn:7001242",
        "tgn:7016833",
        "tgn:1001123",
        "tgn:7029392"
    ],
    "tgn:id":7529151,
    "tgn:name:en":"S\u00eedi el-Gindi Tomb",
    "tgn:placetype":[
        "aat:300005926"
    ]
},
  "bbox": [],
  "geometry": {"coordinates":[32.031111,31.364444],"type":"Point"}
}