<<<<<<< HEAD
{
  "id": 2762091,
  "type": "Feature",
  "properties": {
    "tgn:hierarchy":[
        "tgn:2762091",
        "tgn:1000001",
        "tgn:7012149",
        "tgn:2002129",
        "tgn:7007827",
        "tgn:7029392"
    ],
    "tgn:id":2762091,
    "tgn:name":"West Side Estates",
    "tgn:placetype":[
        "aat:300008347"
    ]
},
  "bbox": [],
  "geometry": {"coordinates":[-112.1,41.2333],"type":"Point"}
}
=======
{"geometry":{"type":"Point","coordinates":[-112.100000,41.233300]},"type":"Feature","properties":{"hierarchy":["tgn:2762091","tgn:1000001","tgn:7012149","tgn:2002129","tgn:7007827","tgn:7029392"],"placetype":["aat:300008347"],"id":2762091,"name:xx":"West Side Estates"}}
>>>>>>> 03f74aca74312dbeaf24d7e61306dd6a786dc3d0
