{
  "id": 2211647,
  "type": "Feature",
  "properties": {
    "tgn:hierarchy":[
        "tgn:2211647",
        "tgn:1000001",
        "tgn:2001414",
        "tgn:7012149",
        "tgn:7007526",
        "tgn:7029392"
    ],
    "tgn:id":2211647,
    "tgn:name":"Buttermilk Springs",
    "tgn:placetype":[
        "aat:300008697"
    ]
},
  "bbox": [],
  "geometry": {"coordinates":[-117.4667,41.5833],"type":"Point"}
}