{
  "id": 7262951,
  "type": "Feature",
  "properties": {
    "tgn:concordances":{
        "gn:id":"2757860"
    },
    "tgn:hierarchy":[
        "tgn:7262951",
        "tgn:7003619",
        "tgn:1000003",
        "tgn:7016845",
        "tgn:7029392"
    ],
    "tgn:id":7262951,
    "tgn:name:nl":"Dale",
    "tgn:placetype":[
        "aat:300008347"
    ]
},
  "bbox": [],
  "geometry": {"coordinates":[6.566667,51.95],"type":"Point"}
}