{
  "id": 2592599,
  "type": "Feature",
  "properties": {
    "tgn:hierarchy":[
        "tgn:2592599",
        "tgn:1000001",
        "tgn:7012149",
        "tgn:2001873",
        "tgn:7007825",
        "tgn:7029392"
    ],
    "tgn:id":2592599,
    "tgn:name":"Poor Valley Shoals",
    "tgn:placetype":[
        "aat:300132348"
    ]
},
  "bbox": [],
  "geometry": {"coordinates":[-83.1667,36.3167],"type":"Point"}
}