{
  "id": 7254449,
  "type": "Feature",
  "properties": {
    "tgn:hierarchy":[
        "tgn:7254449",
        "tgn:7003461",
        "tgn:1000003",
        "tgn:1000063",
        "tgn:7018236",
        "tgn:7029392"
    ],
    "tgn:id":7254449,
    "tgn:name":"Schulen",
    "tgn:placetype":[
        "aat:300008347"
    ]
},
  "bbox": [],
  "geometry": {"coordinates":[5.166667,50.95],"type":"Point"}
}