{
  "id": 2396433,
  "type": "Feature",
  "properties": {
    "tgn:hierarchy":[
        "tgn:2396433",
        "tgn:1000001",
        "tgn:2001476",
        "tgn:7012149",
        "tgn:7007709",
        "tgn:7029392"
    ],
    "tgn:id":2396433,
    "tgn:name":"Holsclaw Creek",
    "tgn:placetype":[
        "aat:300008706"
    ]
},
  "bbox": [],
  "geometry": {"coordinates":[-81.3667,35.95],"type":"Point"}
}