<<<<<<< HEAD
{
  "id": 2408991,
  "type": "Feature",
  "properties": {
    "tgn:hierarchy":[
        "tgn:2408991",
        "tgn:1000001",
        "tgn:7012149",
        "tgn:2001507",
        "tgn:7007709",
        "tgn:7029392"
    ],
    "tgn:id":2408991,
    "tgn:name":"Ian Joy Acres",
    "tgn:placetype":[
        "aat:300008347"
    ]
},
  "bbox": [],
  "geometry": {"coordinates":[-80.8333,35.7833],"type":"Point"}
}
=======
{"geometry":{"type":"Point","coordinates":[-80.833300,35.783300]},"type":"Feature","properties":{"hierarchy":["tgn:2408991","tgn:1000001","tgn:7012149","tgn:2001507","tgn:7007709","tgn:7029392"],"placetype":["aat:300008347"],"id":2408991,"name:xx":"Ian Joy Acres"}}
>>>>>>> 03f74aca74312dbeaf24d7e61306dd6a786dc3d0
