{
  "id": 2593028,
  "type": "Feature",
  "properties": {
    "tgn:hierarchy":[
        "tgn:2593028",
        "tgn:1000001",
        "tgn:7012149",
        "tgn:7007706",
        "tgn:7029392"
    ],
    "tgn:id":2593028,
    "tgn:name":"Poplar Fork",
    "tgn:placetype":[
        "aat:300008699"
    ]
},
  "bbox": [],
  "geometry": {"coordinates":[-82.7333,38.6833],"type":"Point"}
}