{
  "id": 2131939,
  "type": "Feature",
  "properties": {
    "tgn:hierarchy":[
        "tgn:2131939",
        "tgn:2001000",
        "tgn:1000001",
        "tgn:7012149",
        "tgn:7007521",
        "tgn:7029392"
    ],
    "tgn:id":2131939,
    "tgn:name":"Amelia Lake",
    "tgn:placetype":[
        "aat:300008680"
    ]
},
  "bbox": [],
  "geometry": {"coordinates":[-93.05,45.1167],"type":"Point"}
}