{
  "id": 7336682,
  "type": "Feature",
  "properties": {
    "tgn:hierarchy":[
        "tgn:7336682",
        "tgn:7002807",
        "tgn:1000003",
        "tgn:7003837",
        "tgn:1000095",
        "tgn:7029392"
    ],
    "tgn:id":7336682,
    "tgn:name":"Gato, Charca del",
    "tgn:placetype":[
        "aat:300008688"
    ]
},
  "bbox": [],
  "geometry": {"coordinates":[-6.383333,39.016667],"type":"Point"}
}