{
  "id": 1098957,
  "type": "Feature",
  "properties": {
    "tgn:hierarchy":[
        "tgn:1098957",
        "tgn:1009227",
        "tgn:1000226",
        "tgn:7016729",
        "tgn:1000006",
        "tgn:7029392"
    ],
    "tgn:id":1098957,
    "tgn:name:en":"Havelock",
    "tgn:placetype":[
        "aat:300008347"
    ]
},
  "bbox": [],
  "geometry": {"coordinates":[173.766667,-41.283333],"type":"Point"}
}