{
  "id": 2354375,
  "type": "Feature",
  "properties": {
    "tgn:hierarchy":[
        "tgn:2354375",
        "tgn:1000001",
        "tgn:7012149",
        "tgn:2000410",
        "tgn:7007248",
        "tgn:7029392"
    ],
    "tgn:id":2354375,
    "tgn:name":"Goldmine Branch",
    "tgn:placetype":[
        "aat:300008699"
    ]
},
  "bbox": [],
  "geometry": {"coordinates":[-83.1667,34.9667],"type":"Point"}
}