{
  "id": 1097089,
  "type": "Feature",
  "properties": {
    "tgn:hierarchy":[
        "tgn:1097089",
        "tgn:7000490",
        "tgn:1000006",
        "tgn:7001831",
        "tgn:7029392"
    ],
    "tgn:id":1097089,
    "tgn:name":"Hawker",
    "tgn:placetype":[
        "aat:300008347"
    ]
},
  "bbox": [],
  "geometry": {"coordinates":[138.4167,-31.7167],"type":"Point"}
}