{
  "id": 7053632,
  "type": "Feature",
  "properties": {
    "tgn:hierarchy":[
        "tgn:7053632",
        "tgn:7003008",
        "tgn:1000003",
        "tgn:7002997",
        "tgn:1000080",
        "tgn:7029392"
    ],
    "tgn:id":7053632,
    "tgn:name":"Monte di Malo",
    "tgn:placetype":[
        "aat:300008347"
    ]
},
  "bbox": [],
  "geometry": {"coordinates":[11.366667,45.65],"type":"Point"}
}