{
  "id": 2478424,
  "type": "Feature",
  "properties": {
    "tgn:hierarchy":[
        "tgn:2478424",
        "tgn:1000001",
        "tgn:1002260",
        "tgn:7012149",
        "tgn:7007920",
        "tgn:7029392"
    ],
    "tgn:id":2478424,
    "tgn:name":"Mad Lake",
    "tgn:placetype":[
        "aat:300008680"
    ]
},
  "bbox": [],
  "geometry": {"coordinates":[-120.65,47.9333],"type":"Point"}
}