{
  "id": 2682749,
  "type": "Feature",
  "properties": {
    "tgn:hierarchy":[
        "tgn:2682749",
        "tgn:1000001",
        "tgn:7012149",
        "tgn:2001453",
        "tgn:7007566",
        "tgn:7029392"
    ],
    "tgn:id":2682749,
    "tgn:name":"Southwest 1 Conchas",
    "tgn:placetype":[
        "aat:300000390"
    ]
},
  "bbox": [],
  "geometry": {"coordinates":[-104.6833,35.65],"type":"Point"}
}