{
  "id": 7398835,
  "type": "Feature",
  "properties": {
    "tgn:hierarchy":[
        "tgn:7398835",
        "tgn:1000001",
        "tgn:1001893",
        "tgn:7005560",
        "tgn:7029392"
    ],
    "tgn:id":7398835,
    "tgn:name":"San Antonio Bonixi",
    "tgn:placetype":[
        "aat:300008347"
    ]
},
  "bbox": [],
  "geometry": {"coordinates":[-99.730278,19.490833],"type":"Point"}
}