{
  "id": 7296119,
  "type": "Feature",
  "properties": {
    "tgn:hierarchy":[
        "tgn:7296119",
        "tgn:7002847",
        "tgn:1001647",
        "tgn:1000003",
        "tgn:1000095",
        "tgn:7029392"
    ],
    "tgn:id":7296119,
    "tgn:name":"Villarrubia de Santiago",
    "tgn:placetype":[
        "aat:300008347"
    ]
},
  "bbox": [],
  "geometry": {"coordinates":[-3.366667,39.983333],"type":"Point"}
}