{
  "id": 2479885,
  "type": "Feature",
  "properties": {
    "tgn:hierarchy":[
        "tgn:2479885",
        "tgn:1000001",
        "tgn:7012149",
        "tgn:2001770",
        "tgn:7007712",
        "tgn:7029392"
    ],
    "tgn:id":2479885,
    "tgn:name":"Lake Elliot Dam",
    "tgn:placetype":[
        "aat:300006191"
    ]
},
  "bbox": [],
  "geometry": {"coordinates":[-80.9667,35.0167],"type":"Point"}
}