<<<<<<< HEAD
{
  "id": 2330828,
  "type": "Feature",
  "properties": {
    "tgn:hierarchy":[
        "tgn:2330828",
        "tgn:7002659",
        "tgn:1000001",
        "tgn:7012149",
        "tgn:2000048",
        "tgn:7029392"
    ],
    "tgn:id":2330828,
    "tgn:name":"Flat Point",
    "tgn:placetype":[
        "aat:300008850"
    ]
},
  "bbox": [],
  "geometry": {"coordinates":[-87.9833,31.05],"type":"Point"}
}
=======
{"geometry":{"type":"Point","coordinates":[-87.983300,31.050000]},"type":"Feature","properties":{"hierarchy":["tgn:2330828","tgn:7002659","tgn:1000001","tgn:7012149","tgn:2000048","tgn:7029392"],"placetype":["aat:300008850"],"id":2330828,"name:xx":"Flat Point"}}
>>>>>>> 03f74aca74312dbeaf24d7e61306dd6a786dc3d0
