<<<<<<< HEAD
{
  "id": 2339676,
  "type": "Feature",
  "properties": {
    "tgn:hierarchy":[
        "tgn:2339676",
        "tgn:1000001",
        "tgn:7012149",
        "tgn:2001291",
        "tgn:7007524",
        "tgn:7029392"
    ],
    "tgn:id":2339676,
    "tgn:name":"Free Creek",
    "tgn:placetype":[
        "aat:300008706"
    ]
},
  "bbox": [],
  "geometry": {"coordinates":[-114.5167,47.0667],"type":"Point"}
}
=======
{"geometry":{"type":"Point","coordinates":[-114.516700,47.066700]},"type":"Feature","properties":{"hierarchy":["tgn:2339676","tgn:1000001","tgn:7012149","tgn:2001291","tgn:7007524","tgn:7029392"],"placetype":["aat:300008706"],"id":2339676,"name:xx":"Free Creek"}}
>>>>>>> 03f74aca74312dbeaf24d7e61306dd6a786dc3d0
