{
  "id": 7524189,
  "type": "Feature",
  "properties": {
    "tgn:hierarchy":[
        "tgn:7524189",
        "tgn:7001242",
        "tgn:7001311",
        "tgn:7016833",
        "tgn:7029392"
    ],
    "tgn:id":7524189,
    "tgn:name:en":"Biririg, W\u00e2di",
    "tgn:placetype":[
        "aat:300379998"
    ]
},
  "bbox": [],
  "geometry": {"coordinates":[34.400603,25.379571],"type":"Point"}
}