{
  "id": 7522702,
  "type": "Feature",
  "properties": {
    "tgn:hierarchy":[
        "tgn:7522702",
        "tgn:7001242",
        "tgn:7016833",
        "tgn:1001142",
        "tgn:7029392"
    ],
    "tgn:id":7522702,
    "tgn:name:en":"A\u015ffar, At Tall al",
    "tgn:placetype":[
        "aat:300008777"
    ]
},
  "bbox": [],
  "geometry": {"coordinates":[31.083333,29.05],"type":"Point"}
}