{
  "id": 1025606,
  "type": "Feature",
  "properties": {
    "tgn:hierarchy":[
        "tgn:1025606",
        "tgn:7003025",
        "tgn:1000003",
        "tgn:1000062",
        "tgn:7029392"
    ],
    "tgn:id":1025606,
    "tgn:name":"Gross Gerungs",
    "tgn:placetype":[
        "aat:300008347"
    ]
},
  "bbox": [],
  "geometry": {"coordinates":[14.9667,48.5833],"type":"Point"}
}