{
  "id": 7414109,
  "type": "Feature",
  "properties": {
    "tgn:hierarchy":[
        "tgn:7414109",
        "tgn:1000001",
        "tgn:7005596",
        "tgn:7005560",
        "tgn:7029392"
    ],
    "tgn:id":7414109,
    "tgn:name:es":"San Rom\u00e1n",
    "tgn:placetype":[
        "aat:300008347"
    ]
},
  "bbox": [],
  "geometry": {"coordinates":[-91.275,17.833333],"type":"Point"}
}