{
  "id": 2641833,
  "type": "Feature",
  "properties": {
    "tgn:hierarchy":[
        "tgn:2641833",
        "tgn:1000001",
        "tgn:7012149",
        "tgn:1002418",
        "tgn:7007920",
        "tgn:7029392"
    ],
    "tgn:id":2641833,
    "tgn:name":"Sand Island Shoal",
    "tgn:placetype":[
        "aat:300132348"
    ]
},
  "bbox": [],
  "geometry": {"coordinates":[-124.05,46.95],"type":"Point"}
}