{
  "id": 7333161,
  "type": "Feature",
  "properties": {
    "tgn:hierarchy":[
        "tgn:7333161",
        "tgn:7002758",
        "tgn:7002817",
        "tgn:1000003",
        "tgn:1000095",
        "tgn:7029392"
    ],
    "tgn:id":7333161,
    "tgn:name":"Ladrones, Pe\u00f1a",
    "tgn:placetype":[
        "aat:300008798"
    ]
},
  "bbox": [],
  "geometry": {"coordinates":[-5.116667,38.283333],"type":"Point"}
}