{
  "id": 2710323,
  "type": "Feature",
  "properties": {
    "tgn:hierarchy":[
        "tgn:2710323",
        "tgn:1000001",
        "tgn:7012149",
        "tgn:2002303",
        "tgn:7013961",
        "tgn:7029392"
    ],
    "tgn:id":2710323,
    "tgn:name":"Tallyho",
    "tgn:placetype":[
        "aat:300008347"
    ]
},
  "bbox": [],
  "geometry": {"coordinates":[-81.4333,39.2667],"type":"Point"}
}