{
  "id": 7471823,
  "type": "Feature",
  "properties": {
    "tgn:hierarchy":[
        "tgn:7471823",
        "tgn:1000004",
        "tgn:7492971",
        "tgn:1000141",
        "tgn:7029392"
    ],
    "tgn:id":7471823,
    "tgn:name":"Fanzicuo",
    "tgn:placetype":[
        "aat:300008347"
    ]
},
  "bbox": [],
  "geometry": {"coordinates":[120.560284,22.523645],"type":"Point"}
}