{
  "id": 7275905,
  "type": "Feature",
  "properties": {
    "tgn:hierarchy":[
        "tgn:7275905",
        "tgn:1001702",
        "tgn:1000049",
        "tgn:1000002",
        "tgn:7029392"
    ],
    "tgn:id":7275905,
    "tgn:name":"Theo, Islote",
    "tgn:placetype":[
        "aat:300008791"
    ]
},
  "bbox": [],
  "geometry": {"coordinates":[-71.883333,-53.85],"type":"Point"}
}