{
  "id": 2190731,
  "type": "Feature",
  "properties": {
    "tgn:hierarchy":[
        "tgn:2190731",
        "tgn:1000001",
        "tgn:2000780",
        "tgn:7012149",
        "tgn:7007255",
        "tgn:7029392"
    ],
    "tgn:id":2190731,
    "tgn:name":"Boxley, Lake",
    "tgn:placetype":[
        "aat:300006191"
    ]
},
  "bbox": [],
  "geometry": {"coordinates":[-87.4333,36.8833],"type":"Point"}
}