<<<<<<< HEAD
{
  "id": 2155657,
  "type": "Feature",
  "properties": {
    "tgn:hierarchy":[
        "tgn:2155657",
        "tgn:1000001",
        "tgn:2002104",
        "tgn:7012149",
        "tgn:7007827",
        "tgn:7029392"
    ],
    "tgn:id":2155657,
    "tgn:name":"Bear Spring",
    "tgn:placetype":[
        "aat:300008697"
    ]
},
  "bbox": [],
  "geometry": {"coordinates":[-111.2333,39.7833],"type":"Point"}
}
=======
{"geometry":{"type":"Point","coordinates":[-111.233300,39.783300]},"type":"Feature","properties":{"hierarchy":["tgn:2155657","tgn:1000001","tgn:2002104","tgn:7012149","tgn:7007827","tgn:7029392"],"placetype":["aat:300008697"],"id":2155657,"name:xx":"Bear Spring"}}
>>>>>>> 03f74aca74312dbeaf24d7e61306dd6a786dc3d0
