{
  "id": 2155657,
  "type": "Feature",
  "properties": {
    "tgn:hierarchy":[
        "tgn:2155657",
        "tgn:1000001",
        "tgn:2002104",
        "tgn:7012149",
        "tgn:7007827",
        "tgn:7029392"
    ],
    "tgn:id":2155657,
    "tgn:name":"Bear Spring",
    "tgn:placetype":[
        "aat:300008697"
    ]
},
  "bbox": [],
  "geometry": {"coordinates":[-111.2333,39.7833],"type":"Point"}
}