{
  "id": 7488968,
  "type": "Feature",
  "properties": {
    "tgn:hierarchy":[
        "tgn:7488968",
        "tgn:1000004",
        "tgn:1000454",
        "tgn:1000141",
        "tgn:7029392"
    ],
    "tgn:id":7488968,
    "tgn:name":"Jiugongqiao",
    "tgn:placetype":[
        "aat:300008347"
    ]
},
  "bbox": [],
  "geometry": {"coordinates":[121.833732,25.094892],"type":"Point"}
}