<<<<<<< HEAD
{
  "id": 7488968,
  "type": "Feature",
  "properties": {
    "tgn:hierarchy":[
        "tgn:7488968",
        "tgn:1000004",
        "tgn:1000454",
        "tgn:1000141",
        "tgn:7029392"
    ],
    "tgn:id":7488968,
    "tgn:name":"Jiugongqiao",
    "tgn:placetype":[
        "aat:300008347"
    ]
},
  "bbox": [],
  "geometry": {"coordinates":[121.833732,25.094892],"type":"Point"}
}
=======
{"geometry":{"type":"Point","coordinates":[121.833732,25.094892]},"type":"Feature","properties":{"hierarchy":["tgn:7488968","tgn:1000004","tgn:1000454","tgn:1000141","tgn:7029392"],"placetype":["aat:300008347"],"id":7488968,"name:xx":"Jiugongqiao"}}
>>>>>>> 03f74aca74312dbeaf24d7e61306dd6a786dc3d0
