{
  "id": 2535018,
  "type": "Feature",
  "properties": {
    "tgn:hierarchy":[
        "tgn:2535018",
        "tgn:1000001",
        "tgn:7012149",
        "tgn:1002952",
        "tgn:7007826",
        "tgn:7029392"
    ],
    "tgn:id":2535018,
    "tgn:name":"Nameless Hollow",
    "tgn:placetype":[
        "aat:300008761"
    ]
},
  "bbox": [],
  "geometry": {"coordinates":[-97.9167,30.5333],"type":"Point"}
}