{
  "id": 7575832,
  "type": "Feature",
  "properties": {
    "tgn:hierarchy":[
        "tgn:7575832",
        "tgn:1000004",
        "tgn:7000198",
        "tgn:1001997",
        "tgn:7029392"
    ],
    "tgn:id":7575832,
    "tgn:name:en":"Kanjang",
    "tgn:placetype":[
        "aat:300008347"
    ]
},
  "bbox": [],
  "geometry": {"coordinates":[93.915445,25.478002],"type":"Point"}
}