{
  "id": 2526861,
  "type": "Feature",
  "properties": {
    "tgn:hierarchy":[
        "tgn:2526861",
        "tgn:1000001",
        "tgn:7012149",
        "tgn:2002126",
        "tgn:7007827",
        "tgn:7029392"
    ],
    "tgn:id":2526861,
    "tgn:name":"Mound City",
    "tgn:placetype":[
        "aat:300008347"
    ]
},
  "bbox": [],
  "geometry": {"coordinates":[-111.4833,40.5167],"type":"Point"}
}