{
  "id": 2764189,
  "type": "Feature",
  "properties": {
    "tgn:hierarchy":[
        "tgn:2764189",
        "tgn:7002659",
        "tgn:1000001",
        "tgn:7012149",
        "tgn:2000041",
        "tgn:7029392"
    ],
    "tgn:id":2764189,
    "tgn:name":"Wheeler Reservoir",
    "tgn:placetype":[
        "aat:300006191"
    ]
},
  "bbox": [],
  "geometry": {"coordinates":[-87.1167,34.8833],"type":"Point"}
}