{
  "id": 7003013,
  "type": "Feature",
  "properties": {
    "tgn:hierarchy":[
        "tgn:7003013",
        "tgn:7003005",
        "tgn:1000003",
        "tgn:1000080",
        "tgn:7029392"
    ],
    "tgn:id":7003013,
    "tgn:name":"Napoli",
    "tgn:placetype":[
        "aat:300387145",
        "aat:300000774"
    ]
},
  "bbox": [],
  "geometry": {"coordinates":[14.416667,40.883333],"type":"Point"}
}