{
  "id": 2114148,
  "type": "Feature",
  "properties": {
    "tgn:hierarchy":[
        "tgn:2114148",
        "tgn:1000001",
        "tgn:7012149",
        "tgn:2002192",
        "tgn:7007919",
        "tgn:7029392"
    ],
    "tgn:id":2114148,
    "tgn:name":"Sayersville",
    "tgn:placetype":[
        "aat:300008347",
        "aat:300387210"
    ]
},
  "bbox": [],
  "geometry": {"coordinates":[-81.6167,37.1667],"type":"Point"}
}