{
  "id": 2385172,
  "type": "Feature",
  "properties": {
    "tgn:hierarchy":[
        "tgn:2385172",
        "tgn:1000001",
        "tgn:1002294",
        "tgn:7012149",
        "tgn:7007710",
        "tgn:7029392"
    ],
    "tgn:id":2385172,
    "tgn:name":"Hemlock Creek",
    "tgn:placetype":[
        "aat:300008706"
    ]
},
  "bbox": [],
  "geometry": {"coordinates":[-76.55,41.0667],"type":"Point"}
}