<<<<<<< HEAD
{
  "id": 7057373,
  "type": "Feature",
  "properties": {
    "tgn:hierarchy":[
        "tgn:7057373",
        "tgn:1003489",
        "tgn:7004610",
        "tgn:1000003",
        "tgn:1000080",
        "tgn:7029392"
    ],
    "tgn:id":7057373,
    "tgn:name":"Avigliano, Fiumara di",
    "tgn:placetype":[
        "aat:300008699"
    ]
},
  "bbox": [],
  "geometry": {"coordinates":[15.65,40.716667],"type":"Point"}
}
=======
{"geometry":{"type":"Point","coordinates":[15.650000,40.716667]},"type":"Feature","properties":{"hierarchy":["tgn:7057373","tgn:1003489","tgn:7004610","tgn:1000003","tgn:1000080","tgn:7029392"],"placetype":["aat:300008699"],"id":7057373,"name:xx":"Avigliano, Fiumara di"}}
>>>>>>> 03f74aca74312dbeaf24d7e61306dd6a786dc3d0
