{
  "id": 7544945,
  "type": "Feature",
  "properties": {
    "tgn:hierarchy":[
        "tgn:7544945",
        "tgn:1000004",
        "tgn:1001842",
        "tgn:7000198",
        "tgn:7029392"
    ],
    "tgn:id":7544945,
    "tgn:name:en":"Bar\u0101ri Gh\u0101t",
    "tgn:placetype":[
        "aat:300007928"
    ]
},
  "bbox": [],
  "geometry": {"coordinates":[87.030844,25.268086],"type":"Point"}
}