{
  "id": 7417127,
  "type": "Feature",
  "properties": {
    "tgn:hierarchy":[
        "tgn:7417127",
        "tgn:1000001",
        "tgn:7005591",
        "tgn:7005560",
        "tgn:7029392"
    ],
    "tgn:id":7417127,
    "tgn:name:es":"Yerbabuena",
    "tgn:placetype":[
        "aat:300008347"
    ]
},
  "bbox": [],
  "geometry": {"coordinates":[-97.430278,16.195833],"type":"Point"}
}