{
  "id": 2660815,
  "type": "Feature",
  "properties": {
    "tgn:hierarchy":[
        "tgn:2660815",
        "tgn:7006450",
        "tgn:1000001",
        "tgn:7012149",
        "tgn:2000086",
        "tgn:7029392"
    ],
    "tgn:id":2660815,
    "tgn:name":"Short Arm Bay of Isles",
    "tgn:placetype":[
        "aat:300132316"
    ]
},
  "bbox": [],
  "geometry": {"coordinates":[-147.6667,60.3667],"type":"Point"}
}