{
  "id": 2405926,
  "type": "Feature",
  "properties": {
    "tgn:hierarchy":[
        "tgn:2405926",
        "tgn:1000001",
        "tgn:7012149",
        "tgn:2000491",
        "tgn:7007250",
        "tgn:7029392"
    ],
    "tgn:id":2405926,
    "tgn:name":"Hultman Gulch",
    "tgn:placetype":[
        "aat:300008761"
    ]
},
  "bbox": [],
  "geometry": {"coordinates":[-116.2167,47.5833],"type":"Point"}
}