{
  "id": 2562581,
  "type": "Feature",
  "properties": {
    "tgn:hierarchy":[
        "tgn:2562581",
        "tgn:1000001",
        "tgn:7012149",
        "tgn:2002048",
        "tgn:7007826",
        "tgn:7029392"
    ],
    "tgn:id":2562581,
    "tgn:name":"Outlaw Canyon",
    "tgn:placetype":[
        "aat:300008761"
    ]
},
  "bbox": [],
  "geometry": {"coordinates":[-100.25,32.4167],"type":"Point"}
}