{
  "id": 2544495,
  "type": "Feature",
  "properties": {
    "tgn:hierarchy":[
        "tgn:2544495",
        "tgn:1000001",
        "tgn:2002368",
        "tgn:7012149",
        "tgn:7007923",
        "tgn:7029392"
    ],
    "tgn:id":2544495,
    "tgn:name":"North Brush Creek",
    "tgn:placetype":[
        "aat:300008706"
    ]
},
  "bbox": [],
  "geometry": {"coordinates":[-106.35,41.3833],"type":"Point"}
}