{
  "id": 2515374,
  "type": "Feature",
  "properties": {
    "tgn:hierarchy":[
        "tgn:2515374",
        "tgn:1000001",
        "tgn:2001477",
        "tgn:7012149",
        "tgn:7007709",
        "tgn:7029392"
    ],
    "tgn:id":2515374,
    "tgn:name":"Millis Swamp",
    "tgn:placetype":[
        "aat:300008699"
    ]
},
  "bbox": [],
  "geometry": {"coordinates":[-76.9667,34.75],"type":"Point"}
}