{
  "id": 7298885,
  "type": "Feature",
  "properties": {
    "tgn:hierarchy":[
        "tgn:7298885",
        "tgn:7002836",
        "tgn:7016622",
        "tgn:1000003",
        "tgn:1000095",
        "tgn:7029392"
    ],
    "tgn:id":7298885,
    "tgn:name":"Topuerque, Playa del",
    "tgn:placetype":[
        "aat:300008816"
    ]
},
  "bbox": [],
  "geometry": {"coordinates":[-16.383333,28.216667],"type":"Point"}
}