{
  "id": 1090815,
  "type": "Feature",
  "properties": {
    "tgn:hierarchy":[
        "tgn:1090815",
        "tgn:7001242",
        "tgn:1001575",
        "tgn:1000173",
        "tgn:7029392"
    ],
    "tgn:id":1090815,
    "tgn:name":"Ankilimalinika",
    "tgn:placetype":[
        "aat:300008347"
    ]
},
  "bbox": [],
  "geometry": {"coordinates":[43.5833,-22.95],"type":"Point"}
}