{
  "id": 7582194,
  "type": "Feature",
  "properties": {
    "tgn:hierarchy":[
        "tgn:7582194",
        "tgn:1000004",
        "tgn:7000198",
        "tgn:7016788",
        "tgn:7029392"
    ],
    "tgn:id":7582194,
    "tgn:name:en":"Abb\u0101no Johra",
    "tgn:placetype":[
        "aat:300008688"
    ]
},
  "bbox": [],
  "geometry": {"coordinates":[75.622325,28.446407],"type":"Point"}
}