{
  "id": 1091015,
  "type": "Feature",
  "properties": {
    "tgn:hierarchy":[
        "tgn:1091015",
        "tgn:7001242",
        "tgn:1001575",
        "tgn:1000173",
        "tgn:7029392"
    ],
    "tgn:id":1091015,
    "tgn:name":"Toliara",
    "tgn:placetype":[
        "aat:300008347",
        "aat:300387223",
        "aat:300008375",
        "aat:300120599"
    ]
},
  "bbox": [],
  "geometry": {"coordinates":[43.6833,-23.3333],"type":"Point"}
}