{
  "id": 1034332,
  "type": "Feature",
  "properties": {
    "tgn:hierarchy":[
        "tgn:1034332",
        "tgn:1000003",
        "tgn:7012216",
        "tgn:1000070",
        "tgn:7029392"
    ],
    "tgn:id":1034332,
    "tgn:name":"Mauron",
    "tgn:placetype":[
        "aat:300008347"
    ]
},
  "bbox": [],
  "geometry": {"coordinates":[-2.2833,48.0833],"type":"Point"}
}