<<<<<<< HEAD
{
  "id": 7116636,
  "type": "Feature",
  "properties": {
    "tgn:hierarchy":[
        "tgn:7116636",
        "tgn:7003692",
        "tgn:1000003",
        "tgn:7000084",
        "tgn:7029392"
    ],
    "tgn:id":7116636,
    "tgn:name":"\u00d6schelbronn",
    "tgn:placetype":[
        "aat:300008347"
    ]
},
  "bbox": [],
  "geometry": {"coordinates":[8.8,48.55],"type":"Point"}
}
=======
{"geometry":{"type":"Point","coordinates":[8.800000,48.550000]},"type":"Feature","properties":{"hierarchy":["tgn:7116636","tgn:7003692","tgn:1000003","tgn:7000084","tgn:7029392"],"placetype":["aat:300008347"],"id":7116636,"name:xx":"\u00d6schelbronn"}}
>>>>>>> 03f74aca74312dbeaf24d7e61306dd6a786dc3d0
