{
  "id": 7521231,
  "type": "Feature",
  "properties": {
    "tgn:hierarchy":[
        "tgn:7521231",
        "tgn:7001242",
        "tgn:7001311",
        "tgn:7016833",
        "tgn:7029392"
    ],
    "tgn:id":7521231,
    "tgn:name:en":"Aiy\u016bb, Naqb",
    "tgn:placetype":[
        "aat:300259572"
    ]
},
  "bbox": [],
  "geometry": {"coordinates":[31.827414,26.617241],"type":"Point"}
}