<<<<<<< HEAD
{
  "id": 2333485,
  "type": "Feature",
  "properties": {
    "tgn:hierarchy":[
        "tgn:2333485",
        "tgn:1000001",
        "tgn:1002359",
        "tgn:7012149",
        "tgn:7007517",
        "tgn:7029392"
    ],
    "tgn:id":2333485,
    "tgn:name":"Folly Hill",
    "tgn:placetype":[
        "aat:300008798"
    ]
},
  "bbox": [],
  "geometry": {"coordinates":[-70.9,42.55],"type":"Point"}
}
=======
{"geometry":{"type":"Point","coordinates":[-70.900000,42.550000]},"type":"Feature","properties":{"hierarchy":["tgn:2333485","tgn:1000001","tgn:1002359","tgn:7012149","tgn:7007517","tgn:7029392"],"placetype":["aat:300008798"],"id":2333485,"name:xx":"Folly Hill"}}
>>>>>>> 03f74aca74312dbeaf24d7e61306dd6a786dc3d0
