<<<<<<< HEAD
{
  "id": 2409037,
  "type": "Feature",
  "properties": {
    "tgn:hierarchy":[
        "tgn:2409037",
        "tgn:1000001",
        "tgn:2000467",
        "tgn:7012149",
        "tgn:7007250",
        "tgn:7029392"
    ],
    "tgn:id":2409037,
    "tgn:name":"Ibex Peak",
    "tgn:placetype":[
        "aat:300008798"
    ]
},
  "bbox": [],
  "geometry": {"coordinates":[-114.0667,42.1],"type":"Point"}
}
=======
{"geometry":{"type":"Point","coordinates":[-114.066700,42.100000]},"type":"Feature","properties":{"hierarchy":["tgn:2409037","tgn:1000001","tgn:2000467","tgn:7012149","tgn:7007250","tgn:7029392"],"placetype":["aat:300008798"],"id":2409037,"name:xx":"Ibex Peak"}}
>>>>>>> 03f74aca74312dbeaf24d7e61306dd6a786dc3d0
