{
  "id": 7236274,
  "type": "Feature",
  "properties": {
    "tgn:hierarchy":[
        "tgn:7236274",
        "tgn:7002690",
        "tgn:7012056",
        "tgn:1000003",
        "tgn:1000074",
        "tgn:7029392"
    ],
    "tgn:id":7236274,
    "tgn:name":"\u00c1no Pouli\u00e1",
    "tgn:placetype":[
        "aat:300008347"
    ]
},
  "bbox": [],
  "geometry": {"coordinates":[25.266667,35.116667],"type":"Point"}
}