{
  "id": 7112344,
  "type": "Feature",
  "properties": {
    "tgn:hierarchy":[
        "tgn:7112344",
        "tgn:7003692",
        "tgn:1000003",
        "tgn:7000084",
        "tgn:7029392"
    ],
    "tgn:id":7112344,
    "tgn:name":"Rindersteig",
    "tgn:placetype":[
        "aat:300000206"
    ]
},
  "bbox": [],
  "geometry": {"coordinates":[9.816667,48.683333],"type":"Point"}
}