{
  "id": 1085784,
  "type": "Feature",
  "properties": {
    "tgn:hierarchy":[
        "tgn:1085784",
        "tgn:1001167",
        "tgn:1000004",
        "tgn:7018450",
        "tgn:1000144",
        "tgn:7029392"
    ],
    "tgn:id":1085784,
    "tgn:name":"Harmanc\u0131k",
    "tgn:placetype":[
        "aat:300008347"
    ]
},
  "bbox": [],
  "geometry": {"coordinates":[29.1667,39.6833],"type":"Point"}
}