{
  "id": 2415726,
  "type": "Feature",
  "properties": {
    "tgn:hierarchy":[
        "tgn:2415726",
        "tgn:1000001",
        "tgn:2002133",
        "tgn:7012149",
        "tgn:7007828",
        "tgn:7029392"
    ],
    "tgn:id":2415726,
    "tgn:name":"Ithiel Falls",
    "tgn:placetype":[
        "aat:300008347"
    ]
},
  "bbox": [],
  "geometry": {"coordinates":[-72.7167,44.6333],"type":"Point"}
}