{
  "id": 1042069,
  "type": "Feature",
  "properties": {
    "tgn:hierarchy":[
        "tgn:1042069",
        "tgn:7011169",
        "tgn:7001338",
        "tgn:7011374",
        "tgn:1000003",
        "tgn:1000074",
        "tgn:7029392"
    ],
    "tgn:id":1042069,
    "tgn:name":"Ker\u00edon",
    "tgn:placetype":[
        "aat:300008347",
        "aat:300008375"
    ]
},
  "bbox": [],
  "geometry": {"coordinates":[20.816667,37.666667],"type":"Point"}
}