{
  "id": 7579372,
  "type": "Feature",
  "properties": {
    "tgn:hierarchy":[
        "tgn:7579372",
        "tgn:1001828",
        "tgn:1000004",
        "tgn:7000198",
        "tgn:7029392"
    ],
    "tgn:id":7579372,
    "tgn:name:en":"Sokal Eru",
    "tgn:placetype":[
        "aat:300008699"
    ]
},
  "bbox": [],
  "geometry": {"coordinates":[81.383333,17.716667],"type":"Point"}
}