{
  "id": 7134654,
  "type": "Feature",
  "properties": {
    "tgn:hierarchy":[
        "tgn:7134654",
        "tgn:7003669",
        "tgn:1000003",
        "tgn:7000084",
        "tgn:7029392"
    ],
    "tgn:id":7134654,
    "tgn:name":"M\u00f6ning",
    "tgn:placetype":[
        "aat:300008347"
    ]
},
  "bbox": [],
  "geometry": {"coordinates":[11.333333,49.233333],"type":"Point"}
}