<<<<<<< HEAD
{
  "id": 2257502,
  "type": "Feature",
  "properties": {
    "tgn:hierarchy":[
        "tgn:2257502",
        "tgn:1000001",
        "tgn:7012149",
        "tgn:7007158",
        "tgn:2000250",
        "tgn:7029392"
    ],
    "tgn:id":2257502,
    "tgn:name":"Corporal Mine",
    "tgn:placetype":[
        "aat:300000390"
    ]
},
  "bbox": [],
  "geometry": {"coordinates":[-105.9833,39.4667],"type":"Point"}
}
=======
{"geometry":{"type":"Point","coordinates":[-105.983300,39.466700]},"type":"Feature","properties":{"hierarchy":["tgn:2257502","tgn:1000001","tgn:7012149","tgn:7007158","tgn:2000250","tgn:7029392"],"placetype":["aat:300000390"],"id":2257502,"name:xx":"Corporal Mine"}}
>>>>>>> 03f74aca74312dbeaf24d7e61306dd6a786dc3d0
