{
  "id": 7361172,
  "type": "Feature",
  "properties": {
    "tgn:hierarchy":[
        "tgn:7361172",
        "tgn:1000001",
        "tgn:1001906",
        "tgn:7005560",
        "tgn:7029392"
    ],
    "tgn:id":7361172,
    "tgn:name":"El Ocotillo",
    "tgn:placetype":[
        "aat:300008347"
    ]
},
  "bbox": [],
  "geometry": {"coordinates":[-104.633333,21.216667],"type":"Point"}
}