{
  "id": 2148869,
  "type": "Feature",
  "properties": {
    "tgn:hierarchy":[
        "tgn:2148869",
        "tgn:1000001",
        "tgn:7012149",
        "tgn:7014612",
        "tgn:7007568",
        "tgn:7029392"
    ],
    "tgn:id":2148869,
    "tgn:name":"Barney Brook",
    "tgn:placetype":[
        "aat:300008699"
    ]
},
  "bbox": [],
  "geometry": {"coordinates":[-73.8333,41.0333],"type":"Point"}
}