{
  "id": 1122177,
  "type": "Feature",
  "properties": {
    "tgn:hierarchy":[
        "tgn:1122177",
        "tgn:7005685",
        "tgn:1000001",
        "tgn:7013154",
        "tgn:7029392"
    ],
    "tgn:id":1122177,
    "tgn:name":"Boyne",
    "tgn:placetype":[
        "aat:300008707"
    ]
},
  "bbox": [],
  "geometry": {"coordinates":[-79.8167,44.1667],"type":"Point"}
}