{
  "id": 7518332,
  "type": "Feature",
  "properties": {
    "tgn:hierarchy":[
        "tgn:7518332",
        "tgn:1009227",
        "tgn:1000226",
        "tgn:7016822",
        "tgn:1000006",
        "tgn:7029392"
    ],
    "tgn:id":7518332,
    "tgn:name:en":"Native Island",
    "tgn:placetype":[
        "aat:300008791"
    ]
},
  "bbox": [],
  "geometry": {"coordinates":[168.15,-46.916667],"type":"Point"}
}