{
  "id": 7246517,
  "type": "Feature",
  "properties": {
    "tgn:hierarchy":[
        "tgn:7246517",
        "tgn:7018239",
        "tgn:1000003",
        "tgn:1000063",
        "tgn:7018236",
        "tgn:7029392"
    ],
    "tgn:id":7246517,
    "tgn:name":"Boskant",
    "tgn:placetype":[
        "aat:300008347"
    ]
},
  "bbox": [],
  "geometry": {"coordinates":[4.858759,50.865096],"type":"Point"}
}