<<<<<<< HEAD
{
  "id": 7364005,
  "type": "Feature",
  "properties": {
    "tgn:hierarchy":[
        "tgn:7364005",
        "tgn:1000001",
        "tgn:7005589",
        "tgn:7005560",
        "tgn:7029392"
    ],
    "tgn:id":7364005,
    "tgn:name":"El Guajolote",
    "tgn:placetype":[
        "aat:300008347"
    ]
},
  "bbox": [],
  "geometry": {"coordinates":[-99.532778,24.677778],"type":"Point"}
}
=======
{"geometry":{"type":"Point","coordinates":[-99.532778,24.677778]},"type":"Feature","properties":{"hierarchy":["tgn:7364005","tgn:1000001","tgn:7005589","tgn:7005560","tgn:7029392"],"placetype":["aat:300008347"],"id":7364005,"name:xx":"El Guajolote"}}
>>>>>>> 03f74aca74312dbeaf24d7e61306dd6a786dc3d0
