{
  "id": 7218571,
  "type": "Feature",
  "properties": {
    "tgn:hierarchy":[
        "tgn:7218571",
        "tgn:7011330",
        "tgn:7002674",
        "tgn:1000003",
        "tgn:1000074",
        "tgn:7029392"
    ],
    "tgn:id":7218571,
    "tgn:name":"Limen\u00e1ri, \u00c1kra",
    "tgn:placetype":[
        "aat:300008850"
    ]
},
  "bbox": [],
  "geometry": {"coordinates":[29.571667,36.154444],"type":"Point"}
}