{
  "id": 2230348,
  "type": "Feature",
  "properties": {
    "tgn:hierarchy":[
        "tgn:2230348",
        "tgn:1000001",
        "tgn:7012149",
        "tgn:7007157",
        "tgn:1002791",
        "tgn:7029392"
    ],
    "tgn:id":2230348,
    "tgn:name":"Centennial Mine",
    "tgn:placetype":[
        "aat:300000390"
    ]
},
  "bbox": [],
  "geometry": {"coordinates":[-120.9333,38.9333],"type":"Point"}
}