{
  "id": 7410520,
  "type": "Feature",
  "properties": {
    "tgn:hierarchy":[
        "tgn:7410520",
        "tgn:1000001",
        "tgn:7005592",
        "tgn:7005560",
        "tgn:7029392"
    ],
    "tgn:id":7410520,
    "tgn:name":"Tlacomulco",
    "tgn:placetype":[
        "aat:300008347"
    ]
},
  "bbox": [],
  "geometry": {"coordinates":[-98.116667,20.145833],"type":"Point"}
}