{
  "id": 1088246,
  "type": "Feature",
  "properties": {
    "tgn:hierarchy":[
        "tgn:1088246",
        "tgn:1001245",
        "tgn:7001242",
        "tgn:1000153",
        "tgn:7029392"
    ],
    "tgn:id":1088246,
    "tgn:name":"Moloundou",
    "tgn:placetype":[
        "aat:300008347"
    ]
},
  "bbox": [],
  "geometry": {"coordinates":[15.2333,2.05],"type":"Point"}
}