{
  "id": 1062361,
  "type": "Feature",
  "properties": {
    "tgn:hierarchy":[
        "tgn:1062361",
        "tgn:7002816",
        "tgn:1001647",
        "tgn:1000003",
        "tgn:1000095",
        "tgn:7029392"
    ],
    "tgn:id":1062361,
    "tgn:name":"Porzuna",
    "tgn:placetype":[
        "aat:300008347"
    ]
},
  "bbox": [],
  "geometry": {"coordinates":[-4.15,39.15],"type":"Point"}
}