{
  "id": 2076924,
  "type": "Feature",
  "properties": {
    "tgn:hierarchy":[
        "tgn:2076924",
        "tgn:1000001",
        "tgn:7012149",
        "tgn:2001491",
        "tgn:7007709",
        "tgn:7029392"
    ],
    "tgn:id":2076924,
    "tgn:name":"Tin City",
    "tgn:placetype":[
        "aat:300008347",
        "aat:300387210"
    ]
},
  "bbox": [],
  "geometry": {"coordinates":[-77.9667,34.7333],"type":"Point"}
}