{
  "id": 7197991,
  "type": "Feature",
  "properties": {
    "tgn:hierarchy":[
        "tgn:7197991",
        "tgn:7003669",
        "tgn:1000003",
        "tgn:7000084",
        "tgn:7029392"
    ],
    "tgn:id":7197991,
    "tgn:name":"Echterspfahl",
    "tgn:placetype":[
        "aat:300000206"
    ]
},
  "bbox": [],
  "geometry": {"coordinates":[9.333333,49.916667],"type":"Point"}
}