{
  "id": 2676739,
  "type": "Feature",
  "properties": {
    "tgn:hierarchy":[
        "tgn:2676739",
        "tgn:1000001",
        "tgn:7012149",
        "tgn:7007705",
        "tgn:7029392"
    ],
    "tgn:id":2676739,
    "tgn:name":"South Branch Beaver Creek",
    "tgn:placetype":[
        "aat:300008706"
    ]
},
  "bbox": [],
  "geometry": {"coordinates":[-99.7333,46.2333],"type":"Point"}
}