{
  "id": 7005185,
  "type": "Feature",
  "properties": {
    "tgn:hierarchy":[
        "tgn:7005185",
        "tgn:7003692",
        "tgn:1000003",
        "tgn:7000084",
        "tgn:7029392"
    ],
    "tgn:id":7005185,
    "tgn:name:de":"Reichenau",
    "tgn:name:en":"Reichenau",
    "tgn:placetype":[
        "aat:300387273",
        "aat:300008791",
        "aat:300005135"
    ]
},
  "bbox": [],
  "geometry": {"coordinates":[9.066667,47.683333],"type":"Point"}
}