{
  "id": 2604870,
  "type": "Feature",
  "properties": {
    "tgn:hierarchy":[
        "tgn:2604870",
        "tgn:1000001",
        "tgn:7012149",
        "tgn:7007157",
        "tgn:1003050",
        "tgn:7029392"
    ],
    "tgn:id":2604870,
    "tgn:name":"Race Track Point",
    "tgn:placetype":[
        "aat:300008850"
    ]
},
  "bbox": [],
  "geometry": {"coordinates":[-121.0833,39.5167],"type":"Point"}
}