{
  "id": 1067474,
  "type": "Feature",
  "properties": {
    "tgn:hierarchy":[
        "tgn:1067474",
        "tgn:1000004",
        "tgn:7001745",
        "tgn:1000111",
        "tgn:7029392"
    ],
    "tgn:id":1067474,
    "tgn:name":"Danahu",
    "tgn:placetype":[
        "aat:300008347"
    ]
},
  "bbox": [],
  "geometry": {"coordinates":[93.4667,42.5833],"type":"Point"}
}