<<<<<<< HEAD
{
  "id": 7479079,
  "type": "Feature",
  "properties": {
    "tgn:hierarchy":[
        "tgn:7479079",
        "tgn:1000004",
        "tgn:7001009",
        "tgn:1000141",
        "tgn:7029392"
    ],
    "tgn:id":7479079,
    "tgn:name":"Songbai Nongchang",
    "tgn:placetype":[
        "aat:300000206"
    ]
},
  "bbox": [],
  "geometry": {"coordinates":[121.282222,24.322778],"type":"Point"}
}
=======
{"geometry":{"type":"Point","coordinates":[121.282222,24.322778]},"type":"Feature","properties":{"hierarchy":["tgn:7479079","tgn:1000004","tgn:7001009","tgn:1000141","tgn:7029392"],"placetype":["aat:300000206"],"id":7479079,"name:xx":"Songbai Nongchang"}}
>>>>>>> 03f74aca74312dbeaf24d7e61306dd6a786dc3d0
