{
  "id": 2312353,
  "type": "Feature",
  "properties": {
    "tgn:hierarchy":[
        "tgn:2312353",
        "tgn:1000001",
        "tgn:7012149",
        "tgn:2000393",
        "tgn:7007248",
        "tgn:7029392"
    ],
    "tgn:id":2312353,
    "tgn:name":"Eightmile Creek",
    "tgn:placetype":[
        "aat:300008706"
    ]
},
  "bbox": [],
  "geometry": {"coordinates":[-83.95,33.1833],"type":"Point"}
}