{
  "id": 7218235,
  "type": "Feature",
  "properties": {
    "tgn:hierarchy":[
        "tgn:7218235",
        "tgn:7002711",
        "tgn:7001338",
        "tgn:1000003",
        "tgn:1000074",
        "tgn:7029392"
    ],
    "tgn:id":7218235,
    "tgn:name":"Ag\u00edou Spyr\u00eddonos, \u00c1kra",
    "tgn:placetype":[
        "aat:300008850"
    ]
},
  "bbox": [],
  "geometry": {"coordinates":[19.866667,39.816667],"type":"Point"}
}