{
  "id": 2778144,
  "type": "Feature",
  "properties": {
    "tgn:hierarchy":[
        "tgn:2778144",
        "tgn:1000001",
        "tgn:7012149",
        "tgn:2000400",
        "tgn:7007248",
        "tgn:7029392"
    ],
    "tgn:id":2778144,
    "tgn:name":"Wise",
    "tgn:placetype":[
        "aat:300008347"
    ]
},
  "bbox": [],
  "geometry": {"coordinates":[-82.9667,33.85],"type":"Point"}
}