{
  "id": 7282087,
  "type": "Feature",
  "properties": {
    "tgn:hierarchy":[
        "tgn:7282087",
        "tgn:1001692",
        "tgn:1000049",
        "tgn:1000002",
        "tgn:7029392"
    ],
    "tgn:id":7282087,
    "tgn:name":"Salto, Estero del",
    "tgn:placetype":[
        "aat:300008699"
    ]
},
  "bbox": [],
  "geometry": {"coordinates":[-71.366667,-38.483333],"type":"Point"}
}