{
  "id": 1107846,
  "type": "Feature",
  "properties": {
    "tgn:hierarchy":[
        "tgn:1107846",
        "tgn:7001242",
        "tgn:7016833",
        "tgn:1001418",
        "tgn:7029392"
    ],
    "tgn:id":1107846,
    "tgn:name:en":"Ash Sh\u0101'ib",
    "tgn:placetype":[
        "aat:300008777"
    ]
},
  "bbox": [],
  "geometry": {"coordinates":[30.940506,29.833399],"type":"Point"}
}