{
  "id": 2712556,
  "type": "Feature",
  "properties": {
    "tgn:hierarchy":[
        "tgn:2712556",
        "tgn:1000001",
        "tgn:2001838",
        "tgn:7012149",
        "tgn:7007825",
        "tgn:7029392"
    ],
    "tgn:id":2712556,
    "tgn:name":"Taylor Branch",
    "tgn:placetype":[
        "aat:300008699"
    ]
},
  "bbox": [],
  "geometry": {"coordinates":[-86.5667,35.6833],"type":"Point"}
}