{
  "id": 7229742,
  "type": "Feature",
  "properties": {
    "tgn:hierarchy":[
        "tgn:7229742",
        "tgn:7002745",
        "tgn:7017076",
        "tgn:1000003",
        "tgn:1000074",
        "tgn:7029392"
    ],
    "tgn:id":7229742,
    "tgn:name":"Kin\u00e9sta, \u00cdfalos",
    "tgn:placetype":[
        "aat:300008808"
    ]
},
  "bbox": [],
  "geometry": {"coordinates":[22.416667,36.416667],"type":"Point"}
}