<<<<<<< HEAD
{
  "id": 2400242,
  "type": "Feature",
  "properties": {
    "tgn:hierarchy":[
        "tgn:2400242",
        "tgn:1000001",
        "tgn:7012149",
        "tgn:2000481",
        "tgn:7007250",
        "tgn:7029392"
    ],
    "tgn:id":2400242,
    "tgn:name":"Horse Creek Butte",
    "tgn:placetype":[
        "aat:300008798"
    ]
},
  "bbox": [],
  "geometry": {"coordinates":[-114.5,45.4167],"type":"Point"}
}
=======
{"geometry":{"type":"Point","coordinates":[-114.500000,45.416700]},"type":"Feature","properties":{"hierarchy":["tgn:2400242","tgn:1000001","tgn:7012149","tgn:2000481","tgn:7007250","tgn:7029392"],"placetype":["aat:300008798"],"id":2400242,"name:xx":"Horse Creek Butte"}}
>>>>>>> 03f74aca74312dbeaf24d7e61306dd6a786dc3d0
