{
  "id": 7106920,
  "type": "Feature",
  "properties": {
    "tgn:hierarchy":[
        "tgn:7106920",
        "tgn:1000003",
        "tgn:7003688",
        "tgn:7000084",
        "tgn:7029392"
    ],
    "tgn:id":7106920,
    "tgn:name":"Schellingh\u00f6rn",
    "tgn:placetype":[
        "aat:300008347"
    ]
},
  "bbox": [],
  "geometry": {"coordinates":[8.416667,54.883333],"type":"Point"}
}