{
  "id": 2743835,
  "type": "Feature",
  "properties": {
    "tgn:hierarchy":[
        "tgn:2743835",
        "tgn:1000001",
        "tgn:7012149",
        "tgn:2001453",
        "tgn:7007566",
        "tgn:7029392"
    ],
    "tgn:id":2743835,
    "tgn:name":"Vegoso, Arroyo",
    "tgn:placetype":[
        "aat:300008699"
    ]
},
  "bbox": [],
  "geometry": {"coordinates":[-105.1167,35.55],"type":"Point"}
}