{
  "id": 7539361,
  "type": "Feature",
  "properties": {
    "tgn:hierarchy":[
        "tgn:7539361",
        "tgn:7001242",
        "tgn:7016833",
        "tgn:7000124",
        "tgn:7029392"
    ],
    "tgn:id":7539361,
    "tgn:name:en":"Maz\u0101tat ash Shaykh Jabr",
    "tgn:placetype":[
        "aat:300008347"
    ]
},
  "bbox": [],
  "geometry": {"coordinates":[31.91317,26.305032],"type":"Point"}
}