{
  "id": 1043750,
  "type": "Feature",
  "properties": {
    "tgn:hierarchy":[
        "tgn:1043750",
        "tgn:1003489",
        "tgn:7004610",
        "tgn:1000003",
        "tgn:1000080",
        "tgn:7029392"
    ],
    "tgn:id":1043750,
    "tgn:name":"Calvello",
    "tgn:placetype":[
        "aat:300008347"
    ]
},
  "bbox": [],
  "geometry": {"coordinates":[15.85,40.466667],"type":"Point"}
}