{
  "id": 7155866,
  "type": "Feature",
  "properties": {
    "tgn:hierarchy":[
        "tgn:7155866",
        "tgn:7000096",
        "tgn:1000003",
        "tgn:7000084",
        "tgn:7029392"
    ],
    "tgn:id":7155866,
    "tgn:name":"Klein Beuchow",
    "tgn:placetype":[
        "aat:300008347"
    ]
},
  "bbox": [],
  "geometry": {"coordinates":[13.916667,51.85],"type":"Point"}
}