{
  "id": 2690604,
  "type": "Feature",
  "properties": {
    "tgn:hierarchy":[
        "tgn:2690604",
        "tgn:1002176",
        "tgn:1000001",
        "tgn:7012149",
        "tgn:7007828",
        "tgn:7029392"
    ],
    "tgn:id":2690604,
    "tgn:name":"Stamford Stream",
    "tgn:placetype":[
        "aat:300008699"
    ]
},
  "bbox": [],
  "geometry": {"coordinates":[-73.0833,42.8333],"type":"Point"}
}