{
  "id": 7328716,
  "type": "Feature",
  "properties": {
    "tgn:hierarchy":[
        "tgn:7328716",
        "tgn:7008911",
        "tgn:1000003",
        "tgn:7002763",
        "tgn:1000095",
        "tgn:7029392"
    ],
    "tgn:id":7328716,
    "tgn:name":"Regato, Punta del",
    "tgn:placetype":[
        "aat:300386846"
    ]
},
  "bbox": [],
  "geometry": {"coordinates":[-5.733333,43.566667],"type":"Point"}
}