{
  "id": 2224766,
  "type": "Feature",
  "properties": {
    "tgn:hierarchy":[
        "tgn:2224766",
        "tgn:1000001",
        "tgn:7012149",
        "tgn:2001273",
        "tgn:7007524",
        "tgn:7029392"
    ],
    "tgn:id":2224766,
    "tgn:name":"Casino Creek",
    "tgn:placetype":[
        "aat:300008706"
    ]
},
  "bbox": [],
  "geometry": {"coordinates":[-109.3833,46.9167],"type":"Point"}
}