{
  "id": 7153012,
  "type": "Feature",
  "properties": {
    "tgn:hierarchy":[
        "tgn:7153012",
        "tgn:7003692",
        "tgn:1000003",
        "tgn:7000084",
        "tgn:7029392"
    ],
    "tgn:id":7153012,
    "tgn:name":"Kaltenbach",
    "tgn:placetype":[
        "aat:300008347"
    ]
},
  "bbox": [],
  "geometry": {"coordinates":[7.733333,47.75],"type":"Point"}
}