{
  "id": 1072939,
  "type": "Feature",
  "properties": {
    "tgn:hierarchy":[
        "tgn:1072939",
        "tgn:1000004",
        "tgn:7001796",
        "tgn:1000111",
        "tgn:7029392"
    ],
    "tgn:id":1072939,
    "tgn:name":"Xiazhuang",
    "tgn:placetype":[
        "aat:300008347"
    ]
},
  "bbox": [],
  "geometry": {"coordinates":[119.0167,27.3667],"type":"Point"}
}