{
  "id": 7497048,
  "type": "Feature",
  "properties": {
    "tgn:hierarchy":[
        "tgn:7497048",
        "tgn:7001004",
        "tgn:1000004",
        "tgn:1000141",
        "tgn:7029392"
    ],
    "tgn:id":7497048,
    "tgn:name":"Wenzao N\u00fczi Waiyu Xueyuan",
    "tgn:placetype":[
        "aat:300006610"
    ]
},
  "bbox": [],
  "geometry": {"coordinates":[120.319175,22.669626],"type":"Point"}
}