{
  "id": 7515914,
  "type": "Feature",
  "properties": {
    "tgn:hierarchy":[
        "tgn:7515914",
        "tgn:1008380",
        "tgn:7000507",
        "tgn:1000226",
        "tgn:1000006",
        "tgn:7029392"
    ],
    "tgn:id":7515914,
    "tgn:name:en":"Omapere",
    "tgn:placetype":[
        "aat:300008347"
    ]
},
  "bbox": [],
  "geometry": {"coordinates":[173.383333,-35.533333],"type":"Point"}
}