{
  "id": 7264852,
  "type": "Feature",
  "properties": {
    "tgn:concordances":{
        "gn:id":"2753577"
    },
    "tgn:hierarchy":[
        "tgn:7264852",
        "tgn:7003619",
        "tgn:1000003",
        "tgn:7016845",
        "tgn:7029392"
    ],
    "tgn:id":7264852,
    "tgn:name:nl":"Horsthoek",
    "tgn:placetype":[
        "aat:300008347"
    ]
},
  "bbox": [],
  "geometry": {"coordinates":[6.033333,52.366667],"type":"Point"}
}