{
  "id": 1060629,
  "type": "Feature",
  "properties": {
    "tgn:hierarchy":[
        "tgn:1060629",
        "tgn:1000003",
        "tgn:7006614",
        "tgn:7006542",
        "tgn:7029392"
    ],
    "tgn:id":1060629,
    "tgn:name":"Ukmerg\u0117",
    "tgn:placetype":[
        "aat:300008347",
        "aat:300387222"
    ]
},
  "bbox": [],
  "geometry": {"coordinates":[24.8167,55.2333],"type":"Point"}
}