<<<<<<< HEAD
{
  "id": 2338289,
  "type": "Feature",
  "properties": {
    "tgn:hierarchy":[
        "tgn:2338289",
        "tgn:1000001",
        "tgn:7012149",
        "tgn:2001442",
        "tgn:7007566",
        "tgn:7029392"
    ],
    "tgn:id":2338289,
    "tgn:name":"Fox Spring Canyon",
    "tgn:placetype":[
        "aat:300008761"
    ]
},
  "bbox": [],
  "geometry": {"coordinates":[-105.7167,33.4333],"type":"Point"}
}
=======
{"geometry":{"type":"Point","coordinates":[-105.716700,33.433300]},"type":"Feature","properties":{"hierarchy":["tgn:2338289","tgn:1000001","tgn:7012149","tgn:2001442","tgn:7007566","tgn:7029392"],"placetype":["aat:300008761"],"id":2338289,"name:xx":"Fox Spring Canyon"}}
>>>>>>> 03f74aca74312dbeaf24d7e61306dd6a786dc3d0
