{
  "id": 2110561,
  "type": "Feature",
  "properties": {
    "tgn:hierarchy":[
        "tgn:2110561",
        "tgn:1000001",
        "tgn:1002267",
        "tgn:7012149",
        "tgn:7007919",
        "tgn:7029392"
    ],
    "tgn:id":2110561,
    "tgn:name":"Beach",
    "tgn:placetype":[
        "aat:300008347",
        "aat:300387210"
    ]
},
  "bbox": [],
  "geometry": {"coordinates":[-77.5833,37.35],"type":"Point"}
}