{
  "id": 7579360,
  "type": "Feature",
  "properties": {
    "tgn:hierarchy":[
        "tgn:7579360",
        "tgn:1000004",
        "tgn:7018318",
        "tgn:7000198",
        "tgn:7029392"
    ],
    "tgn:id":7579360,
    "tgn:name:en":"Solim",
    "tgn:placetype":[
        "aat:300008347"
    ]
},
  "bbox": [],
  "geometry": {"coordinates":[73.766667,15.616667],"type":"Point"}
}