{
  "id": 7470108,
  "type": "Feature",
  "properties": {
    "tgn:hierarchy":[
        "tgn:7470108",
        "tgn:1000004",
        "tgn:7467799",
        "tgn:1000141",
        "tgn:7029392"
    ],
    "tgn:id":7470108,
    "tgn:name":"Hanbao",
    "tgn:placetype":[
        "aat:300008347"
    ]
},
  "bbox": [],
  "geometry": {"coordinates":[120.383333,24.006111],"type":"Point"}
}