{
  "id": 7274431,
  "type": "Feature",
  "properties": {
    "tgn:hierarchy":[
        "tgn:7274431",
        "tgn:1000003",
        "tgn:7006951",
        "tgn:7016845",
        "tgn:7029392"
    ],
    "tgn:id":7274431,
    "tgn:name:nl":"Zuurvenspolder",
    "tgn:placetype":[
        "aat:300006163"
    ]
},
  "bbox": [],
  "geometry": {"coordinates":[4.733333,52.666667],"type":"Point"}
}