<<<<<<< HEAD
{
  "id": 2401385,
  "type": "Feature",
  "properties": {
    "tgn:hierarchy":[
        "tgn:2401385",
        "tgn:1000001",
        "tgn:2001471",
        "tgn:7012149",
        "tgn:7007709",
        "tgn:7029392"
    ],
    "tgn:id":2401385,
    "tgn:name":"Horsepen Swamp",
    "tgn:placetype":[
        "aat:300008905"
    ]
},
  "bbox": [],
  "geometry": {"coordinates":[-78.7667,34.4833],"type":"Point"}
}
=======
{"geometry":{"type":"Point","coordinates":[-78.766700,34.483300]},"type":"Feature","properties":{"hierarchy":["tgn:2401385","tgn:1000001","tgn:2001471","tgn:7012149","tgn:7007709","tgn:7029392"],"placetype":["aat:300008905"],"id":2401385,"name:xx":"Horsepen Swamp"}}
>>>>>>> 03f74aca74312dbeaf24d7e61306dd6a786dc3d0
