{
  "id": 2241554,
  "type": "Feature",
  "properties": {
    "tgn:hierarchy":[
        "tgn:2241554",
        "tgn:1000001",
        "tgn:7012149",
        "tgn:1002999",
        "tgn:7007526",
        "tgn:7029392"
    ],
    "tgn:id":2241554,
    "tgn:name":"Clarks",
    "tgn:placetype":[
        "aat:300008347",
        "aat:300167671"
    ]
},
  "bbox": [],
  "geometry": {"coordinates":[-119.45,39.5833],"type":"Point"}
}