<<<<<<< HEAD
{
  "id": 7171865,
  "type": "Feature",
  "properties": {
    "tgn:hierarchy":[
        "tgn:7171865",
        "tgn:1000003",
        "tgn:7003677",
        "tgn:7000084",
        "tgn:7029392"
    ],
    "tgn:id":7171865,
    "tgn:name":"Herrn-Berg",
    "tgn:placetype":[
        "aat:300008795"
    ]
},
  "bbox": [],
  "geometry": {"coordinates":[8.5,51.1],"type":"Point"}
}
=======
{"geometry":{"type":"Point","coordinates":[8.500000,51.100000]},"type":"Feature","properties":{"hierarchy":["tgn:7171865","tgn:1000003","tgn:7003677","tgn:7000084","tgn:7029392"],"placetype":["aat:300008795"],"id":7171865,"name:xx":"Herrn-Berg"}}
>>>>>>> 03f74aca74312dbeaf24d7e61306dd6a786dc3d0
