{
  "id": 2386725,
  "type": "Feature",
  "properties": {
    "tgn:hierarchy":[
        "tgn:2386725",
        "tgn:1000001",
        "tgn:7016098",
        "tgn:7012149",
        "tgn:7007516",
        "tgn:7029392"
    ],
    "tgn:id":2386725,
    "tgn:name":"Hermanville",
    "tgn:placetype":[
        "aat:300008347"
    ]
},
  "bbox": [],
  "geometry": {"coordinates":[-76.4167,38.2333],"type":"Point"}
}