{
  "id": 7023597,
  "type": "Feature",
  "properties": {
    "tgn:hierarchy":[
        "tgn:7023597",
        "tgn:1000001",
        "tgn:7012149",
        "tgn:7007712",
        "tgn:7029392"
    ],
    "tgn:id":7023597,
    "tgn:name":"Oakie Branch",
    "tgn:placetype":[
        "aat:300008699"
    ]
},
  "bbox": [],
  "geometry": {"coordinates":[-79.75,33.0833],"type":"Point"}
}