<<<<<<< HEAD
{
  "id": 7023597,
  "type": "Feature",
  "properties": {
    "tgn:hierarchy":[
        "tgn:7023597",
        "tgn:1000001",
        "tgn:7012149",
        "tgn:7007712",
        "tgn:7029392"
    ],
    "tgn:id":7023597,
    "tgn:name":"Oakie Branch",
    "tgn:placetype":[
        "aat:300008699"
    ]
},
  "bbox": [],
  "geometry": {"coordinates":[-79.75,33.0833],"type":"Point"}
}
=======
{"geometry":{"type":"Point","coordinates":[-79.750000,33.083300]},"type":"Feature","properties":{"hierarchy":["tgn:7023597","tgn:1000001","tgn:7012149","tgn:7007712","tgn:7029392"],"placetype":["aat:300008699"],"id":7023597,"name:xx":"Oakie Branch"}}
>>>>>>> 03f74aca74312dbeaf24d7e61306dd6a786dc3d0
