{
  "id": 2267491,
  "type": "Feature",
  "properties": {
    "tgn:hierarchy":[
        "tgn:2267491",
        "tgn:7002659",
        "tgn:1000001",
        "tgn:7012149",
        "tgn:2000036",
        "tgn:7029392"
    ],
    "tgn:id":2267491,
    "tgn:name":"Crocker Hill",
    "tgn:placetype":[
        "aat:300008798"
    ]
},
  "bbox": [],
  "geometry": {"coordinates":[-86.8833,33.65],"type":"Point"}
}