<<<<<<< HEAD
{
  "id": 2258913,
  "type": "Feature",
  "properties": {
    "tgn:hierarchy":[
        "tgn:2258913",
        "tgn:1000001",
        "tgn:7012149",
        "tgn:2001389",
        "tgn:7007525",
        "tgn:7029392"
    ],
    "tgn:id":2258913,
    "tgn:name":"Cottonwood Creek",
    "tgn:placetype":[
        "aat:300008706"
    ]
},
  "bbox": [],
  "geometry": {"coordinates":[-95.85,40.1],"type":"Point"}
}
=======
{"geometry":{"type":"Point","coordinates":[-95.850000,40.100000]},"type":"Feature","properties":{"hierarchy":["tgn:2258913","tgn:1000001","tgn:7012149","tgn:2001389","tgn:7007525","tgn:7029392"],"placetype":["aat:300008706"],"id":2258913,"name:xx":"Cottonwood Creek"}}
>>>>>>> 03f74aca74312dbeaf24d7e61306dd6a786dc3d0
