{
  "id": 7517992,
  "type": "Feature",
  "properties": {
    "tgn:hierarchy":[
        "tgn:7517992",
        "tgn:1008380",
        "tgn:7520093",
        "tgn:1000226",
        "tgn:1000006",
        "tgn:7029392"
    ],
    "tgn:id":7517992,
    "tgn:name:en":"Maukuku",
    "tgn:placetype":[
        "aat:300008795"
    ]
},
  "bbox": [],
  "geometry": {"coordinates":[175.383333,-39.616667],"type":"Point"}
}