{
  "id": 1091125,
  "type": "Feature",
  "properties": {
    "tgn:hierarchy":[
        "tgn:1091125",
        "tgn:7001242",
        "tgn:1001710",
        "tgn:1000175",
        "tgn:7029392"
    ],
    "tgn:id":1091125,
    "tgn:name":"Diafarab\u00e9",
    "tgn:placetype":[
        "aat:300008347"
    ]
},
  "bbox": [],
  "geometry": {"coordinates":[-5.0167,14.15],"type":"Point"}
}