{
  "id": 7216686,
  "type": "Feature",
  "properties": {
    "tgn:hierarchy":[
        "tgn:7216686",
        "tgn:1000003",
        "tgn:7003677",
        "tgn:7000084",
        "tgn:7029392"
    ],
    "tgn:id":7216686,
    "tgn:name":"Altes Moor",
    "tgn:placetype":[
        "aat:300008903"
    ]
},
  "bbox": [],
  "geometry": {"coordinates":[8.683333,52.333333],"type":"Point"}
}