{
  "id": 7327976,
  "type": "Feature",
  "properties": {
    "tgn:hierarchy":[
        "tgn:7327976",
        "tgn:1001439",
        "tgn:1000003",
        "tgn:7002797",
        "tgn:1000095",
        "tgn:7029392"
    ],
    "tgn:id":7327976,
    "tgn:name":"Ponce, Sierra de",
    "tgn:placetype":[
        "aat:300266640"
    ]
},
  "bbox": [],
  "geometry": {"coordinates":[-1.716667,37.916667],"type":"Point"}
}