{
  "id": 2298907,
  "type": "Feature",
  "properties": {
    "tgn:hierarchy":[
        "tgn:2298907",
        "tgn:1000001",
        "tgn:7012149",
        "tgn:1002567",
        "tgn:7007240",
        "tgn:7029392"
    ],
    "tgn:id":2298907,
    "tgn:name":"Dublin",
    "tgn:placetype":[
        "aat:300008347"
    ]
},
  "bbox": [],
  "geometry": {"coordinates":[-81.6167,28.7833],"type":"Point"}
}