{
  "id": 7363359,
  "type": "Feature",
  "properties": {
    "tgn:hierarchy":[
        "tgn:7363359",
        "tgn:1000001",
        "tgn:1001960",
        "tgn:7005560",
        "tgn:7029392"
    ],
    "tgn:id":7363359,
    "tgn:name":"El Mezquite, Cerro",
    "tgn:placetype":[
        "aat:300008795"
    ]
},
  "bbox": [],
  "geometry": {"coordinates":[-109.333333,29.066667],"type":"Point"}
}