<<<<<<< HEAD
{
  "id": 2766697,
  "type": "Feature",
  "properties": {
    "tgn:hierarchy":[
        "tgn:2766697",
        "tgn:1000001",
        "tgn:7016172",
        "tgn:2000109",
        "tgn:7012149",
        "tgn:7029392"
    ],
    "tgn:id":2766697,
    "tgn:name":"White Oak Mountain",
    "tgn:placetype":[
        "aat:300008798"
    ]
},
  "bbox": [],
  "geometry": {"coordinates":[-93.05,36.4],"type":"Point"}
}
=======
{"geometry":{"type":"Point","coordinates":[-93.050000,36.400000]},"type":"Feature","properties":{"hierarchy":["tgn:2766697","tgn:1000001","tgn:7016172","tgn:2000109","tgn:7012149","tgn:7029392"],"placetype":["aat:300008798"],"id":2766697,"name:xx":"White Oak Mountain"}}
>>>>>>> 03f74aca74312dbeaf24d7e61306dd6a786dc3d0
