{
  "id": 1021897,
  "type": "Feature",
  "properties": {
    "tgn:hierarchy":[
        "tgn:1021897",
        "tgn:7006257",
        "tgn:1000047",
        "tgn:7002455",
        "tgn:1000002",
        "tgn:7029392"
    ],
    "tgn:id":1021897,
    "tgn:name":"Jucurutu",
    "tgn:placetype":[
        "aat:300008347"
    ]
},
  "bbox": [],
  "geometry": {"coordinates":[-37.0167,-6.0333],"type":"Point"}
}