<<<<<<< HEAD
{
  "id": 7486805,
  "type": "Feature",
  "properties": {
    "tgn:hierarchy":[
        "tgn:7486805",
        "tgn:1000004",
        "tgn:1000454",
        "tgn:1000141",
        "tgn:7029392"
    ],
    "tgn:id":7486805,
    "tgn:name":"Liandong Li",
    "tgn:placetype":[
        "aat:300387173"
    ]
},
  "bbox": [],
  "geometry": {"coordinates":[121.8573,25.1214],"type":"Point"}
}
=======
{"geometry":{"type":"Point","coordinates":[121.857300,25.121400]},"type":"Feature","properties":{"hierarchy":["tgn:7486805","tgn:1000004","tgn:1000454","tgn:1000141","tgn:7029392"],"placetype":["aat:300387173"],"id":7486805,"name:xx":"Liandong Li"}}
>>>>>>> 03f74aca74312dbeaf24d7e61306dd6a786dc3d0
