{
  "id": 2653355,
  "type": "Feature",
  "properties": {
    "tgn:hierarchy":[
        "tgn:2653355",
        "tgn:1000001",
        "tgn:7012149",
        "tgn:2001525",
        "tgn:7007709",
        "tgn:7029392"
    ],
    "tgn:id":2653355,
    "tgn:name":"Sevenmile Creek",
    "tgn:placetype":[
        "aat:300008706"
    ]
},
  "bbox": [],
  "geometry": {"coordinates":[-79.2167,36.0333],"type":"Point"}
}