{
  "id": 2727821,
  "type": "Feature",
  "properties": {
    "tgn:hierarchy":[
        "tgn:2727821",
        "tgn:1000001",
        "tgn:7012149",
        "tgn:2000281",
        "tgn:7007240",
        "tgn:7029392"
    ],
    "tgn:id":2727821,
    "tgn:name":"Trammel Creek",
    "tgn:placetype":[
        "aat:300008706"
    ]
},
  "bbox": [],
  "geometry": {"coordinates":[-86.5833,30.75],"type":"Point"}
}