{
  "id": 7010329,
  "type": "Feature",
  "properties": {
    "tgn:hierarchy":[
        "tgn:7010329",
        "tgn:7011438",
        "tgn:1000004",
        "tgn:7006646",
        "tgn:7029392"
    ],
    "tgn:id":7010329,
    "tgn:name":"Zakataly",
    "tgn:placetype":[
        "aat:300008347"
    ]
},
  "bbox": [],
  "geometry": {"coordinates":[46.65,41.6333],"type":"Point"}
}