{
  "id": 2255490,
  "type": "Feature",
  "properties": {
    "tgn:hierarchy":[
        "tgn:2255490",
        "tgn:1000001",
        "tgn:7012149",
        "tgn:2001870",
        "tgn:7007825",
        "tgn:7029392"
    ],
    "tgn:id":2255490,
    "tgn:name":"Cope Hollow",
    "tgn:placetype":[
        "aat:300008761"
    ]
},
  "bbox": [],
  "geometry": {"coordinates":[-83.2667,36.4333],"type":"Point"}
}