{
  "id": 2352590,
  "type": "Feature",
  "properties": {
    "tgn:hierarchy":[
        "tgn:2352590",
        "tgn:1000001",
        "tgn:1002260",
        "tgn:7012149",
        "tgn:7007920",
        "tgn:7029392"
    ],
    "tgn:id":2352590,
    "tgn:name":"Goat Pass Canyon",
    "tgn:placetype":[
        "aat:300008761"
    ]
},
  "bbox": [],
  "geometry": {"coordinates":[-120.4667,48.1667],"type":"Point"}
}