{
  "id": 2183888,
  "type": "Feature",
  "properties": {
    "tgn:hierarchy":[
        "tgn:2183888",
        "tgn:1000001",
        "tgn:7012149",
        "tgn:1002904",
        "tgn:7007710",
        "tgn:7029392"
    ],
    "tgn:id":2183888,
    "tgn:name":"Boardman Ridge",
    "tgn:placetype":[
        "aat:300266640"
    ]
},
  "bbox": [],
  "geometry": {"coordinates":[-79.2667,39.75],"type":"Point"}
}