{
  "id": 2305645,
  "type": "Feature",
  "properties": {
    "tgn:hierarchy":[
        "tgn:2305645",
        "tgn:1000001",
        "tgn:7012149",
        "tgn:7007158",
        "tgn:2000241",
        "tgn:7029392"
    ],
    "tgn:id":2305645,
    "tgn:name":"East Clay Creek",
    "tgn:placetype":[
        "aat:300008706"
    ]
},
  "bbox": [],
  "geometry": {"coordinates":[-102.65,37.6833],"type":"Point"}
}