{
  "id": 7410178,
  "type": "Feature",
  "properties": {
    "tgn:hierarchy":[
        "tgn:7410178",
        "tgn:1000001",
        "tgn:7005590",
        "tgn:7005560",
        "tgn:7029392"
    ],
    "tgn:id":7410178,
    "tgn:name":"San Pedro Baraja",
    "tgn:placetype":[
        "aat:300008347"
    ]
},
  "bbox": [],
  "geometry": {"coordinates":[-102.058333,18.783333],"type":"Point"}
}