{
  "id": 2523060,
  "type": "Feature",
  "properties": {
    "tgn:hierarchy":[
        "tgn:2523060",
        "tgn:1000001",
        "tgn:7012149",
        "tgn:2002010",
        "tgn:7007826",
        "tgn:7029392"
    ],
    "tgn:id":2523060,
    "tgn:name":"Moore Slough",
    "tgn:placetype":[
        "aat:300008699"
    ]
},
  "bbox": [],
  "geometry": {"coordinates":[-104.3167,30.6333],"type":"Point"}
}