{
  "id": 2054139,
  "type": "Feature",
  "properties": {
    "tgn:hierarchy":[
        "tgn:2054139",
        "tgn:1000001",
        "tgn:7012149",
        "tgn:2001075",
        "tgn:7007521",
        "tgn:7029392"
    ],
    "tgn:id":2054139,
    "tgn:name":"Clarissa",
    "tgn:placetype":[
        "aat:300008347"
    ]
},
  "bbox": [],
  "geometry": {"coordinates":[-94.9333,46.1167],"type":"Point"}
}