{
  "id": 2679571,
  "type": "Feature",
  "properties": {
    "tgn:hierarchy":[
        "tgn:2679571",
        "tgn:1000001",
        "tgn:2001779",
        "tgn:7012149",
        "tgn:7007713",
        "tgn:7029392"
    ],
    "tgn:id":2679571,
    "tgn:name":"South Fork Owl Creek",
    "tgn:placetype":[
        "aat:300008706"
    ]
},
  "bbox": [],
  "geometry": {"coordinates":[-104.0333,44.85],"type":"Point"}
}