{
  "id": 2363226,
  "type": "Feature",
  "properties": {
    "tgn:hierarchy":[
        "tgn:2363226",
        "tgn:1000001",
        "tgn:7012149",
        "tgn:2000816",
        "tgn:7007255",
        "tgn:7029392"
    ],
    "tgn:id":2363226,
    "tgn:name":"Green Branch",
    "tgn:placetype":[
        "aat:300008699"
    ]
},
  "bbox": [],
  "geometry": {"coordinates":[-88.0667,36.9333],"type":"Point"}
}