<<<<<<< HEAD
{
  "id": 7470865,
  "type": "Feature",
  "properties": {
    "tgn:hierarchy":[
        "tgn:7470865",
        "tgn:7001004",
        "tgn:1000004",
        "tgn:1000141",
        "tgn:7029392"
    ],
    "tgn:id":7470865,
    "tgn:name":"Jiuqu Cun",
    "tgn:placetype":[
        "aat:300387173"
    ]
},
  "bbox": [],
  "geometry": {"coordinates":[120.427908,22.653576],"type":"Point"}
}
=======
{"geometry":{"type":"Point","coordinates":[120.427908,22.653576]},"type":"Feature","properties":{"hierarchy":["tgn:7470865","tgn:7001004","tgn:1000004","tgn:1000141","tgn:7029392"],"placetype":["aat:300387173"],"id":7470865,"name:xx":"Jiuqu Cun"}}
>>>>>>> 03f74aca74312dbeaf24d7e61306dd6a786dc3d0
