{
  "id": 1112792,
  "type": "Feature",
  "properties": {
    "tgn:hierarchy":[
        "tgn:1112792",
        "tgn:7017471",
        "tgn:1000001",
        "tgn:7004773",
        "tgn:7029392"
    ],
    "tgn:id":1112792,
    "tgn:name":"Chateaubelair Bay",
    "tgn:placetype":[
        "aat:300132316"
    ]
},
  "bbox": [],
  "geometry": {"coordinates":[-61.2333,13.2833],"type":"Point"}
}