{
  "id": 2353175,
  "type": "Feature",
  "properties": {
    "tgn:hierarchy":[
        "tgn:2353175",
        "tgn:1000001",
        "tgn:2000952",
        "tgn:7012149",
        "tgn:7007520",
        "tgn:7029392"
    ],
    "tgn:id":2353175,
    "tgn:name":"Gogomain Swamp",
    "tgn:placetype":[
        "aat:300008905"
    ]
},
  "bbox": [],
  "geometry": {"coordinates":[-84.15,46.1167],"type":"Point"}
}