{
  "id": 2759129,
  "type": "Feature",
  "properties": {
    "tgn:hierarchy":[
        "tgn:2759129",
        "tgn:1000001",
        "tgn:7012149",
        "tgn:2001451",
        "tgn:7007566",
        "tgn:7029392"
    ],
    "tgn:id":2759129,
    "tgn:name":"West Fork Borrego Canyon",
    "tgn:placetype":[
        "aat:300008699"
    ]
},
  "bbox": [],
  "geometry": {"coordinates":[-106.5667,35.7167],"type":"Point"}
}