{
  "id": 2409952,
  "type": "Feature",
  "properties": {
    "tgn:hierarchy":[
        "tgn:2409952",
        "tgn:7006450",
        "tgn:1000001",
        "tgn:7012149",
        "tgn:2124002",
        "tgn:7029392"
    ],
    "tgn:id":2409952,
    "tgn:name":"Impassible Island",
    "tgn:placetype":[
        "aat:300008791"
    ]
},
  "bbox": [],
  "geometry": {"coordinates":[-135.5333,56.8167],"type":"Point"}
}