{
  "id": 2600117,
  "type": "Feature",
  "properties": {
    "tgn:hierarchy":[
        "tgn:2600117",
        "tgn:7006450",
        "tgn:2000069",
        "tgn:1000001",
        "tgn:7012149",
        "tgn:7029392"
    ],
    "tgn:id":2600117,
    "tgn:name":"Ptarmigan Creek",
    "tgn:placetype":[
        "aat:300008706"
    ]
},
  "bbox": [],
  "geometry": {"coordinates":[-153.152,61.915],"type":"Point"}
}