{
  "id": 7591489,
  "type": "Feature",
  "properties": {
    "tgn:hierarchy":[
        "tgn:7591489",
        "tgn:1000004",
        "tgn:7000198",
        "tgn:7000799",
        "tgn:7029392"
    ],
    "tgn:id":7591489,
    "tgn:name:en":"Dula da Pail",
    "tgn:placetype":[
        "aat:300008347"
    ]
},
  "bbox": [],
  "geometry": {"coordinates":[74.622889,32.966383],"type":"Point"}
}