{
  "id": 2144456,
  "type": "Feature",
  "properties": {
    "tgn:hierarchy":[
        "tgn:2144456",
        "tgn:1000001",
        "tgn:7012149",
        "tgn:2001615",
        "tgn:7007706",
        "tgn:7029392"
    ],
    "tgn:id":2144456,
    "tgn:name":"Bakers Fork Buffalo Creek",
    "tgn:placetype":[
        "aat:300008706"
    ]
},
  "bbox": [],
  "geometry": {"coordinates":[-82.55,38.7167],"type":"Point"}
}