<<<<<<< HEAD
{
  "id": 7470000,
  "type": "Feature",
  "properties": {
    "tgn:hierarchy":[
        "tgn:7470000",
        "tgn:1000004",
        "tgn:1000959",
        "tgn:1000141",
        "tgn:7029392"
    ],
    "tgn:id":7470000,
    "tgn:name":"Jungongkeng",
    "tgn:placetype":[
        "aat:300008347"
    ]
},
  "bbox": [],
  "geometry": {"coordinates":[121.573069,25.001352],"type":"Point"}
}
=======
{"geometry":{"type":"Point","coordinates":[121.573069,25.001352]},"type":"Feature","properties":{"hierarchy":["tgn:7470000","tgn:1000004","tgn:1000959","tgn:1000141","tgn:7029392"],"placetype":["aat:300008347"],"id":7470000,"name:xx":"Jungongkeng"}}
>>>>>>> 03f74aca74312dbeaf24d7e61306dd6a786dc3d0
