{
  "id": 7480286,
  "type": "Feature",
  "properties": {
    "tgn:hierarchy":[
        "tgn:7480286",
        "tgn:1000004",
        "tgn:7490934",
        "tgn:1000141",
        "tgn:7029392"
    ],
    "tgn:id":7480286,
    "tgn:name":"Sanlin",
    "tgn:placetype":[
        "aat:300008347"
    ]
},
  "bbox": [],
  "geometry": {"coordinates":[120.421996,23.176139],"type":"Point"}
}