<<<<<<< HEAD
{
  "id": 2402688,
  "type": "Feature",
  "properties": {
    "tgn:hierarchy":[
        "tgn:2402688",
        "tgn:1000001",
        "tgn:7012149",
        "tgn:2001708",
        "tgn:7007708",
        "tgn:7029392"
    ],
    "tgn:id":2402688,
    "tgn:name":"Hot Spring",
    "tgn:placetype":[
        "aat:300008697"
    ]
},
  "bbox": [],
  "geometry": {"coordinates":[-118.7333,44.3667],"type":"Point"}
}
=======
{"geometry":{"type":"Point","coordinates":[-118.733300,44.366700]},"type":"Feature","properties":{"hierarchy":["tgn:2402688","tgn:1000001","tgn:7012149","tgn:2001708","tgn:7007708","tgn:7029392"],"placetype":["aat:300008697"],"id":2402688,"name:xx":"Hot Spring"}}
>>>>>>> 03f74aca74312dbeaf24d7e61306dd6a786dc3d0
