{
  "id": 7254043,
  "type": "Feature",
  "properties": {
    "tgn:hierarchy":[
        "tgn:7254043",
        "tgn:7003456",
        "tgn:1000003",
        "tgn:1000063",
        "tgn:7018236",
        "tgn:7029392"
    ],
    "tgn:id":7254043,
    "tgn:name":"Spaans Kasteel",
    "tgn:placetype":[
        "aat:300005567"
    ]
},
  "bbox": [],
  "geometry": {"coordinates":[4.331031,51.031463],"type":"Point"}
}