{
  "id": 7588314,
  "type": "Feature",
  "properties": {
    "tgn:hierarchy":[
        "tgn:7588314",
        "tgn:1000004",
        "tgn:7000198",
        "tgn:7000799",
        "tgn:7029392"
    ],
    "tgn:id":7588314,
    "tgn:name:en":"S\u0101ratpur",
    "tgn:placetype":[
        "aat:300008347"
    ]
},
  "bbox": [],
  "geometry": {"coordinates":[74.6625,34.033333],"type":"Point"}
}