{
  "id": 1076045,
  "type": "Feature",
  "properties": {
    "tgn:hierarchy":[
        "tgn:1076045",
        "tgn:1000004",
        "tgn:7000198",
        "tgn:1001977",
        "tgn:7029392"
    ],
    "tgn:id":1076045,
    "tgn:name":"Madharihat",
    "tgn:placetype":[
        "aat:300008347"
    ]
},
  "bbox": [],
  "geometry": {"coordinates":[89.281455,26.695229],"type":"Point"}
}