{
  "id": 1028587,
  "type": "Feature",
  "properties": {
    "tgn:hierarchy":[
        "tgn:1028587",
        "tgn:7002445",
        "tgn:1000003",
        "tgn:7012031",
        "tgn:7008591",
        "tgn:7029392"
    ],
    "tgn:id":1028587,
    "tgn:name:en":"Brackley",
    "tgn:placetype":[
        "aat:300008347",
        "aat:300008375"
    ]
},
  "bbox": [],
  "geometry": {"coordinates":[-1.15,52.033333],"type":"Point"}
}