{
  "id": 1072772,
  "type": "Feature",
  "properties": {
    "tgn:hierarchy":[
        "tgn:1072772",
        "tgn:1000004",
        "tgn:7002077",
        "tgn:1000111",
        "tgn:7029392"
    ],
    "tgn:id":1072772,
    "tgn:name":"Xianghe",
    "tgn:placetype":[
        "aat:300008347"
    ]
},
  "bbox": [],
  "geometry": {"coordinates":[117.0167,39.7833],"type":"Point"}
}