{
  "id": 7509538,
  "type": "Feature",
  "properties": {
    "tgn:hierarchy":[
        "tgn:7509538",
        "tgn:1009227",
        "tgn:1000226",
        "tgn:7016822",
        "tgn:1000006",
        "tgn:7029392"
    ],
    "tgn:id":7509538,
    "tgn:name:en":"Waikauia",
    "tgn:placetype":[
        "aat:300008699"
    ]
},
  "bbox": [],
  "geometry": {"coordinates":[-176.633333,-43.733333],"type":"Point"}
}