{
  "id": 7423825,
  "type": "Feature",
  "properties": {
    "tgn:hierarchy":[
        "tgn:7423825",
        "tgn:1000001",
        "tgn:1001960",
        "tgn:7005560",
        "tgn:7029392"
    ],
    "tgn:id":7423825,
    "tgn:name":"Kino Nuevo",
    "tgn:placetype":[
        "aat:300008347"
    ]
},
  "bbox": [],
  "geometry": {"coordinates":[-112.033333,28.866667],"type":"Point"}
}