{
  "id": 7565734,
  "type": "Feature",
  "properties": {
    "tgn:hierarchy":[
        "tgn:7565734",
        "tgn:1000004",
        "tgn:7000198",
        "tgn:7016722",
        "tgn:7029392"
    ],
    "tgn:id":7565734,
    "tgn:name:en":"Nibh\u0101r",
    "tgn:placetype":[
        "aat:300008347"
    ]
},
  "bbox": [],
  "geometry": {"coordinates":[79.658045,26.799574],"type":"Point"}
}