<<<<<<< HEAD
{
  "id": 7472985,
  "type": "Feature",
  "properties": {
    "tgn:hierarchy":[
        "tgn:7472985",
        "tgn:7488858",
        "tgn:1000004",
        "tgn:1000141",
        "tgn:7029392"
    ],
    "tgn:id":7472985,
    "tgn:name":"Dongxinmin",
    "tgn:placetype":[
        "aat:300008347"
    ]
},
  "bbox": [],
  "geometry": {"coordinates":[120.705522,23.823575],"type":"Point"}
}
=======
{"geometry":{"type":"Point","coordinates":[120.705522,23.823575]},"type":"Feature","properties":{"hierarchy":["tgn:7472985","tgn:7488858","tgn:1000004","tgn:1000141","tgn:7029392"],"placetype":["aat:300008347"],"id":7472985,"name:xx":"Dongxinmin"}}
>>>>>>> 03f74aca74312dbeaf24d7e61306dd6a786dc3d0
