<<<<<<< HEAD
{
  "id": 2253479,
  "type": "Feature",
  "properties": {
    "tgn:hierarchy":[
        "tgn:2253479",
        "tgn:1000001",
        "tgn:2000469",
        "tgn:7012149",
        "tgn:7007250",
        "tgn:7029392"
    ],
    "tgn:id":2253479,
    "tgn:name":"Cook Creek",
    "tgn:placetype":[
        "aat:300008706"
    ]
},
  "bbox": [],
  "geometry": {"coordinates":[-116.0167,46.45],"type":"Point"}
}
=======
{"geometry":{"type":"Point","coordinates":[-116.016700,46.450000]},"type":"Feature","properties":{"hierarchy":["tgn:2253479","tgn:1000001","tgn:2000469","tgn:7012149","tgn:7007250","tgn:7029392"],"placetype":["aat:300008706"],"id":2253479,"name:xx":"Cook Creek"}}
>>>>>>> 03f74aca74312dbeaf24d7e61306dd6a786dc3d0
