<<<<<<< HEAD
{
  "id": 2405620,
  "type": "Feature",
  "properties": {
    "tgn:hierarchy":[
        "tgn:2405620",
        "tgn:1000001",
        "tgn:2000779",
        "tgn:7012149",
        "tgn:7007255",
        "tgn:7029392"
    ],
    "tgn:id":2405620,
    "tgn:name":"Hughes Ridge",
    "tgn:placetype":[
        "aat:300266640"
    ]
},
  "bbox": [],
  "geometry": {"coordinates":[-84.8,37.1833],"type":"Point"}
}
=======
{"geometry":{"type":"Point","coordinates":[-84.800000,37.183300]},"type":"Feature","properties":{"hierarchy":["tgn:2405620","tgn:1000001","tgn:2000779","tgn:7012149","tgn:7007255","tgn:7029392"],"placetype":["aat:300266640"],"id":2405620,"name:xx":"Hughes Ridge"}}
>>>>>>> 03f74aca74312dbeaf24d7e61306dd6a786dc3d0
