<<<<<<< HEAD
{
  "id": 2254329,
  "type": "Feature",
  "properties": {
    "tgn:hierarchy":[
        "tgn:2254329",
        "tgn:1000001",
        "tgn:7012149",
        "tgn:1002639",
        "tgn:7007251",
        "tgn:7029392"
    ],
    "tgn:id":2254329,
    "tgn:name":"Coon Creek",
    "tgn:placetype":[
        "aat:300008706"
    ]
},
  "bbox": [],
  "geometry": {"coordinates":[-89.4833,40.9667],"type":"Point"}
}
=======
{"geometry":{"type":"Point","coordinates":[-89.483300,40.966700]},"type":"Feature","properties":{"hierarchy":["tgn:2254329","tgn:1000001","tgn:7012149","tgn:1002639","tgn:7007251","tgn:7029392"],"placetype":["aat:300008706"],"id":2254329,"name:xx":"Coon Creek"}}
>>>>>>> 03f74aca74312dbeaf24d7e61306dd6a786dc3d0
