{
  "id": 2274250,
  "type": "Feature",
  "properties": {
    "tgn:hierarchy":[
        "tgn:2274250",
        "tgn:1000001",
        "tgn:7012149",
        "tgn:2001288",
        "tgn:7007524",
        "tgn:7029392"
    ],
    "tgn:id":2274250,
    "tgn:name":"Daisy Creek",
    "tgn:placetype":[
        "aat:300008706"
    ]
},
  "bbox": [],
  "geometry": {"coordinates":[-111.8667,45.4333],"type":"Point"}
}