{
  "id": 2244063,
  "type": "Feature",
  "properties": {
    "tgn:hierarchy":[
        "tgn:2244063",
        "tgn:1000001",
        "tgn:2000469",
        "tgn:7012149",
        "tgn:7007250",
        "tgn:7029392"
    ],
    "tgn:id":2244063,
    "tgn:name":"Cliff Lake",
    "tgn:placetype":[
        "aat:300008680"
    ]
},
  "bbox": [],
  "geometry": {"coordinates":[-115.4833,46.8667],"type":"Point"}
}