<<<<<<< HEAD
{
  "id": 2409667,
  "type": "Feature",
  "properties": {
    "tgn:hierarchy":[
        "tgn:2409667",
        "tgn:1000001",
        "tgn:7006451",
        "tgn:2000092",
        "tgn:7012149",
        "tgn:7029392"
    ],
    "tgn:id":2409667,
    "tgn:name":"Ike Smith Tank",
    "tgn:placetype":[
        "aat:300006191"
    ]
},
  "bbox": [],
  "geometry": {"coordinates":[-112.2667,36.0],"type":"Point"}
}
=======
{"geometry":{"type":"Point","coordinates":[-112.266700,36.000000]},"type":"Feature","properties":{"hierarchy":["tgn:2409667","tgn:1000001","tgn:7006451","tgn:2000092","tgn:7012149","tgn:7029392"],"placetype":["aat:300006191"],"id":2409667,"name:xx":"Ike Smith Tank"}}
>>>>>>> 03f74aca74312dbeaf24d7e61306dd6a786dc3d0
