{
  "id": 7306618,
  "type": "Feature",
  "properties": {
    "tgn:hierarchy":[
        "tgn:7306618",
        "tgn:7002826",
        "tgn:7001158",
        "tgn:1000003",
        "tgn:1000095",
        "tgn:7029392"
    ],
    "tgn:id":7306618,
    "tgn:name":"Lomba",
    "tgn:placetype":[
        "aat:300008347"
    ]
},
  "bbox": [],
  "geometry": {"coordinates":[-6.666667,42.35],"type":"Point"}
}