{
  "id": 7579369,
  "type": "Feature",
  "properties": {
    "tgn:hierarchy":[
        "tgn:7579369",
        "tgn:1000004",
        "tgn:7000198",
        "tgn:7000799",
        "tgn:7029392"
    ],
    "tgn:id":7579369,
    "tgn:name:en":"Sokhniz",
    "tgn:placetype":[
        "aat:300008347"
    ]
},
  "bbox": [],
  "geometry": {"coordinates":[75.51491,33.983242],"type":"Point"}
}