{
  "id": 7564276,
  "type": "Feature",
  "properties": {
    "tgn:hierarchy":[
        "tgn:7564276",
        "tgn:1000004",
        "tgn:7000198",
        "tgn:1001894",
        "tgn:7029392"
    ],
    "tgn:id":7564276,
    "tgn:name:en":"Bhelsi",
    "tgn:placetype":[
        "aat:300008347"
    ]
},
  "bbox": [],
  "geometry": {"coordinates":[79.390555,24.830266],"type":"Point"}
}