{
  "id": 7477971,
  "type": "Feature",
  "properties": {
    "tgn:hierarchy":[
        "tgn:7477971",
        "tgn:7487020",
        "tgn:1000004",
        "tgn:1000141",
        "tgn:7029392"
    ],
    "tgn:id":7477971,
    "tgn:name":"Fuxing Qiao",
    "tgn:placetype":[
        "aat:300007836"
    ]
},
  "bbox": [],
  "geometry": {"coordinates":[120.866986,24.691972],"type":"Point"}
}