{
  "id": 2616883,
  "type": "Feature",
  "properties": {
    "tgn:hierarchy":[
        "tgn:2616883",
        "tgn:1000001",
        "tgn:2001474",
        "tgn:7012149",
        "tgn:7007709",
        "tgn:7029392"
    ],
    "tgn:id":2616883,
    "tgn:name":"Rich Mountain",
    "tgn:placetype":[
        "aat:300008798"
    ]
},
  "bbox": [],
  "geometry": {"coordinates":[-81.6667,35.5667],"type":"Point"}
}