<<<<<<< HEAD
{
  "id": 7112504,
  "type": "Feature",
  "properties": {
    "tgn:hierarchy":[
        "tgn:7112504",
        "tgn:1000003",
        "tgn:7003682",
        "tgn:7000084",
        "tgn:7029392"
    ],
    "tgn:id":7112504,
    "tgn:name":"R\u00f6hl-Berg",
    "tgn:placetype":[
        "aat:300008777"
    ]
},
  "bbox": [],
  "geometry": {"coordinates":[7.983333,49.133333],"type":"Point"}
}
=======
{"geometry":{"type":"Point","coordinates":[7.983333,49.133333]},"type":"Feature","properties":{"hierarchy":["tgn:7112504","tgn:1000003","tgn:7003682","tgn:7000084","tgn:7029392"],"placetype":["aat:300008777"],"id":7112504,"name:xx":"R\u00f6hl-Berg"}}
>>>>>>> 03f74aca74312dbeaf24d7e61306dd6a786dc3d0
