{
  "id": 2328649,
  "type": "Feature",
  "properties": {
    "tgn:hierarchy":[
        "tgn:2328649",
        "tgn:1000001",
        "tgn:7012149",
        "tgn:2002327",
        "tgn:7007922",
        "tgn:7029392"
    ],
    "tgn:id":2328649,
    "tgn:name":"Fishermans Landing",
    "tgn:placetype":[
        "aat:300008347"
    ]
},
  "bbox": [],
  "geometry": {"coordinates":[-90.1667,46.0833],"type":"Point"}
}