<<<<<<< HEAD
{
  "id": 2761950,
  "type": "Feature",
  "properties": {
    "tgn:hierarchy":[
        "tgn:2761950",
        "tgn:1000001",
        "tgn:7012149",
        "tgn:1002521",
        "tgn:7007920",
        "tgn:7029392"
    ],
    "tgn:id":2761950,
    "tgn:name":"West Rock",
    "tgn:placetype":[
        "aat:300008798"
    ]
},
  "bbox": [],
  "geometry": {"coordinates":[-123.0667,47.6167],"type":"Point"}
}
=======
{"geometry":{"type":"Point","coordinates":[-123.066700,47.616700]},"type":"Feature","properties":{"hierarchy":["tgn:2761950","tgn:1000001","tgn:7012149","tgn:1002521","tgn:7007920","tgn:7029392"],"placetype":["aat:300008798"],"id":2761950,"name:xx":"West Rock"}}
>>>>>>> 03f74aca74312dbeaf24d7e61306dd6a786dc3d0
