{
  "id": 7422815,
  "type": "Feature",
  "properties": {
    "tgn:hierarchy":[
        "tgn:7422815",
        "tgn:1000001",
        "tgn:7005601",
        "tgn:7005560",
        "tgn:7029392"
    ],
    "tgn:id":7422815,
    "tgn:name":"La Higuera",
    "tgn:placetype":[
        "aat:300008347"
    ]
},
  "bbox": [],
  "geometry": {"coordinates":[-102.833333,21.75],"type":"Point"}
}