{
  "id": 7522145,
  "type": "Feature",
  "properties": {
    "tgn:hierarchy":[
        "tgn:7522145",
        "tgn:7001242",
        "tgn:7016833",
        "tgn:7001335",
        "tgn:7029392"
    ],
    "tgn:id":7522145,
    "tgn:name:en":"Ab\u016b Rujm, W\u0101d\u012b",
    "tgn:placetype":[
        "aat:300379998"
    ]
},
  "bbox": [],
  "geometry": {"coordinates":[33.646371,30.305921],"type":"Point"}
}