{
  "id": 7408499,
  "type": "Feature",
  "properties": {
    "tgn:hierarchy":[
        "tgn:7408499",
        "tgn:1000001",
        "tgn:1001893",
        "tgn:7005560",
        "tgn:7029392"
    ],
    "tgn:id":7408499,
    "tgn:name":"El Bosque",
    "tgn:placetype":[
        "aat:300008347"
    ]
},
  "bbox": [],
  "geometry": {"coordinates":[-99.875,20.041667],"type":"Point"}
}