{
  "id": 2410768,
  "type": "Feature",
  "properties": {
    "tgn:hierarchy":[
        "tgn:2410768",
        "tgn:1000001",
        "tgn:7012149",
        "tgn:1002763",
        "tgn:7007255",
        "tgn:7029392"
    ],
    "tgn:id":2410768,
    "tgn:name":"Indian Creek",
    "tgn:placetype":[
        "aat:300008706"
    ]
},
  "bbox": [],
  "geometry": {"coordinates":[-84.75,38.4167],"type":"Point"}
}