{
  "id": 2767015,
  "type": "Feature",
  "properties": {
    "tgn:hierarchy":[
        "tgn:2767015",
        "tgn:7006450",
        "tgn:1000001",
        "tgn:2124076",
        "tgn:7012149",
        "tgn:7029392"
    ],
    "tgn:id":2767015,
    "tgn:name":"White River",
    "tgn:placetype":[
        "aat:300008707"
    ]
},
  "bbox": [],
  "geometry": {"coordinates":[-131.6167,55.4167],"type":"Point"}
}