{
  "id": 7057134,
  "type": "Feature",
  "properties": {
    "tgn:hierarchy":[
        "tgn:7057134",
        "tgn:1003488",
        "tgn:1000003",
        "tgn:7002993",
        "tgn:1000080",
        "tgn:7029392"
    ],
    "tgn:id":7057134,
    "tgn:name":"Bando",
    "tgn:placetype":[
        "aat:300008347"
    ]
},
  "bbox": [],
  "geometry": {"coordinates":[12.913889,45.879167],"type":"Point"}
}