{
  "id": 2635602,
  "type": "Feature",
  "properties": {
    "tgn:hierarchy":[
        "tgn:2635602",
        "tgn:1000001",
        "tgn:7012149",
        "tgn:2001281",
        "tgn:7007524",
        "tgn:7029392"
    ],
    "tgn:id":2635602,
    "tgn:name":"SW SW Section 22 Mine",
    "tgn:placetype":[
        "aat:300000390"
    ]
},
  "bbox": [],
  "geometry": {"coordinates":[-112.0833,46.3333],"type":"Point"}
}