{
  "id": 2662170,
  "type": "Feature",
  "properties": {
    "tgn:hierarchy":[
        "tgn:2662170",
        "tgn:1000001",
        "tgn:7012149",
        "tgn:2002114",
        "tgn:7007827",
        "tgn:7029392"
    ],
    "tgn:id":2662170,
    "tgn:name":"Side Canyon",
    "tgn:placetype":[
        "aat:300008761"
    ]
},
  "bbox": [],
  "geometry": {"coordinates":[-113.3667,39.1667],"type":"Point"}
}