{
  "id": 1116211,
  "type": "Feature",
  "properties": {
    "tgn:hierarchy":[
        "tgn:1116211",
        "tgn:7005685",
        "tgn:1000001",
        "tgn:7013154",
        "tgn:7029392"
    ],
    "tgn:id":1116211,
    "tgn:name":"Elephant Lake",
    "tgn:placetype":[
        "aat:300008680"
    ]
},
  "bbox": [],
  "geometry": {"coordinates":[-78.1167,45.1333],"type":"Point"}
}