{
  "id": 1012074,
  "type": "Feature",
  "properties": {
    "tgn:hierarchy":[
        "tgn:1012074",
        "tgn:7015035",
        "tgn:1000001",
        "tgn:7005870",
        "tgn:7029392"
    ],
    "tgn:id":1012074,
    "tgn:name":"La Mare, Pointe",
    "tgn:placetype":[
        "aat:300386846"
    ]
},
  "bbox": [],
  "geometry": {"coordinates":[-61.2167,14.7833],"type":"Point"}
}