{
  "id": 7025042,
  "type": "Feature",
  "properties": {
    "tgn:hierarchy":[
        "tgn:7025042",
        "tgn:7002445",
        "tgn:7008104",
        "tgn:1000003",
        "tgn:7008591",
        "tgn:7029392"
    ],
    "tgn:id":7025042,
    "tgn:name:ang":"Euressel",
    "tgn:placetype":[
        "aat:300008863"
    ]
},
  "bbox": [],
  "geometry": {"coordinates":[-1.05,52.0333],"type":"Point"}
}