{
  "id": 2622934,
  "type": "Feature",
  "properties": {
    "tgn:hierarchy":[
        "tgn:2622934",
        "tgn:1000001",
        "tgn:7012149",
        "tgn:1002928",
        "tgn:7007706",
        "tgn:7029392"
    ],
    "tgn:id":2622934,
    "tgn:name":"Robinson Run",
    "tgn:placetype":[
        "aat:300008699"
    ]
},
  "bbox": [],
  "geometry": {"coordinates":[-81.5333,41.1833],"type":"Point"}
}