<<<<<<< HEAD
{
  "id": 7026837,
  "type": "Feature",
  "properties": {
    "tgn:hierarchy":[
        "tgn:7026837",
        "tgn:7002445",
        "tgn:1000003",
        "tgn:7008139",
        "tgn:7008591",
        "tgn:7029392"
    ],
    "tgn:id":7026837,
    "tgn:name:en":"East Wellow",
    "tgn:placetype":[
        "aat:300008347",
        "aat:300008372"
    ]
},
  "bbox": [],
  "geometry": {"coordinates":[-1.566667,50.966667],"type":"Point"}
}
=======
{"geometry":{"type":"Point","coordinates":[-1.566667,50.966667]},"type":"Feature","properties":{"hierarchy":["tgn:7026837","tgn:7002445","tgn:1000003","tgn:7008139","tgn:7008591","tgn:7029392"],"placetype":["aat:300008347","aat:300008372"],"name:en":"East Wellow","id":7026837}}
>>>>>>> 03f74aca74312dbeaf24d7e61306dd6a786dc3d0
