{
  "id": 7574294,
  "type": "Feature",
  "properties": {
    "tgn:hierarchy":[
        "tgn:7574294",
        "tgn:1000004",
        "tgn:7000198",
        "tgn:1001882",
        "tgn:7029392"
    ],
    "tgn:id":7574294,
    "tgn:name:en":"Halge",
    "tgn:placetype":[
        "aat:300008347"
    ]
},
  "bbox": [],
  "geometry": {"coordinates":[74.233333,14.883333],"type":"Point"}
}