{
  "id": 7591851,
  "type": "Feature",
  "properties": {
    "tgn:hierarchy":[
        "tgn:7591851",
        "tgn:1000004",
        "tgn:7000198",
        "tgn:7031786",
        "tgn:7029392"
    ],
    "tgn:id":7591851,
    "tgn:name:en":"Aunl\u012bw\u0101la",
    "tgn:placetype":[
        "aat:300008347"
    ]
},
  "bbox": [],
  "geometry": {"coordinates":[77.827864,30.348488],"type":"Point"}
}