{
  "id": 2001055,
  "type": "Feature",
  "properties": {
    "tgn:hierarchy":[
        "tgn:2001055",
        "tgn:1000001",
        "tgn:7012149",
        "tgn:7007521",
        "tgn:7029392"
    ],
    "tgn:id":2001055,
    "tgn:name":"Pennington",
    "tgn:placetype":[
        "aat:300387145",
        "aat:300000771"
    ]
},
  "bbox": [],
  "geometry": {"coordinates":[-96.0333,48.0667],"type":"Point"}
}