{
  "id": 2286749,
  "type": "Feature",
  "properties": {
    "tgn:hierarchy":[
        "tgn:2286749",
        "tgn:1000001",
        "tgn:7012149",
        "tgn:2001898",
        "tgn:7007825",
        "tgn:7029392"
    ],
    "tgn:id":2286749,
    "tgn:name":"Diamond Shoals",
    "tgn:placetype":[
        "aat:300132348"
    ]
},
  "bbox": [],
  "geometry": {"coordinates":[-84.1167,35.5667],"type":"Point"}
}