{
  "id": 1120291,
  "type": "Feature",
  "properties": {
    "tgn:hierarchy":[
        "tgn:1120291",
        "tgn:1000004",
        "tgn:1000138",
        "tgn:7000381",
        "tgn:7029392"
    ],
    "tgn:id":1120291,
    "tgn:name":"Pierce Reservoir",
    "tgn:placetype":[
        "aat:300006191"
    ]
},
  "bbox": [],
  "geometry": {"coordinates":[103.8167,1.3667],"type":"Point"}
}