{
  "id": 2304371,
  "type": "Feature",
  "properties": {
    "tgn:hierarchy":[
        "tgn:2304371",
        "tgn:1000001",
        "tgn:2001749",
        "tgn:7012149",
        "tgn:7007712",
        "tgn:7029392"
    ],
    "tgn:id":2304371,
    "tgn:name":"Early Branch",
    "tgn:placetype":[
        "aat:300008699"
    ]
},
  "bbox": [],
  "geometry": {"coordinates":[-80.9167,32.7333],"type":"Point"}
}