{
  "id": 7247091,
  "type": "Feature",
  "properties": {
    "tgn:hierarchy":[
        "tgn:7247091",
        "tgn:7003458",
        "tgn:1000003",
        "tgn:1000063",
        "tgn:7018236",
        "tgn:7029392"
    ],
    "tgn:id":7247091,
    "tgn:name":"Doornhoek",
    "tgn:placetype":[
        "aat:300008347"
    ]
},
  "bbox": [],
  "geometry": {"coordinates":[2.978519,51.165251],"type":"Point"}
}