{
  "id": 2669165,
  "type": "Feature",
  "properties": {
    "tgn:hierarchy":[
        "tgn:2669165",
        "tgn:1000001",
        "tgn:7012149",
        "tgn:2001552",
        "tgn:7007709",
        "tgn:7029392"
    ],
    "tgn:id":2669165,
    "tgn:name":"Sleepy Creek Lake Upper",
    "tgn:placetype":[
        "aat:300006191"
    ]
},
  "bbox": [],
  "geometry": {"coordinates":[-77.95,35.25],"type":"Point"}
}