{
  "id": 1098840,
  "type": "Feature",
  "properties": {
    "tgn:hierarchy":[
        "tgn:1098840",
        "tgn:1006275",
        "tgn:1002120",
        "tgn:1000225",
        "tgn:1000006",
        "tgn:7029392"
    ],
    "tgn:id":1098840,
    "tgn:name":"Port Patrick",
    "tgn:placetype":[
        "aat:300008347"
    ]
},
  "bbox": [],
  "geometry": {"coordinates":[169.7833,-20.1333],"type":"Point"}
}