<<<<<<< HEAD
{
  "id": 2256718,
  "type": "Feature",
  "properties": {
    "tgn:hierarchy":[
        "tgn:2256718",
        "tgn:1000001",
        "tgn:7012149",
        "tgn:2001420",
        "tgn:7007526",
        "tgn:7029392"
    ],
    "tgn:id":2256718,
    "tgn:name":"Corduroy Mountain",
    "tgn:placetype":[
        "aat:300008798"
    ]
},
  "bbox": [],
  "geometry": {"coordinates":[-115.4,38.9667],"type":"Point"}
}
=======
{"geometry":{"type":"Point","coordinates":[-115.400000,38.966700]},"type":"Feature","properties":{"hierarchy":["tgn:2256718","tgn:1000001","tgn:7012149","tgn:2001420","tgn:7007526","tgn:7029392"],"placetype":["aat:300008798"],"id":2256718,"name:xx":"Corduroy Mountain"}}
>>>>>>> 03f74aca74312dbeaf24d7e61306dd6a786dc3d0
