{
  "id": 2192107,
  "type": "Feature",
  "properties": {
    "tgn:hierarchy":[
        "tgn:2192107",
        "tgn:1000001",
        "tgn:2000463",
        "tgn:7012149",
        "tgn:7007250",
        "tgn:7029392"
    ],
    "tgn:id":2192107,
    "tgn:name":"Braithwaite Canyon",
    "tgn:placetype":[
        "aat:300008761"
    ]
},
  "bbox": [],
  "geometry": {"coordinates":[-113.1833,43.65],"type":"Point"}
}