{
  "id": 2276765,
  "type": "Feature",
  "properties": {
    "tgn:hierarchy":[
        "tgn:2276765",
        "tgn:1000001",
        "tgn:7012149",
        "tgn:2001504",
        "tgn:7007709",
        "tgn:7029392"
    ],
    "tgn:id":2276765,
    "tgn:name":"Davie Mountain",
    "tgn:placetype":[
        "aat:300008798"
    ]
},
  "bbox": [],
  "geometry": {"coordinates":[-82.6333,35.3833],"type":"Point"}
}