{
  "id": 2422213,
  "type": "Feature",
  "properties": {
    "tgn:hierarchy":[
        "tgn:2422213",
        "tgn:1000001",
        "tgn:7016172",
        "tgn:7012149",
        "tgn:2000155",
        "tgn:7029392"
    ],
    "tgn:id":2422213,
    "tgn:name":"Jim Rush Hollow",
    "tgn:placetype":[
        "aat:300008761"
    ]
},
  "bbox": [],
  "geometry": {"coordinates":[-93.1333,35.9667],"type":"Point"}
}