{
  "id": 2109749,
  "type": "Feature",
  "properties": {
    "tgn:hierarchy":[
        "tgn:2109749",
        "tgn:1000001",
        "tgn:1002361",
        "tgn:7012149",
        "tgn:7007828",
        "tgn:7029392"
    ],
    "tgn:id":2109749,
    "tgn:name":"Lake",
    "tgn:placetype":[
        "aat:300387016"
    ]
},
  "bbox": [],
  "geometry": {"coordinates":[-71.8333,44.95],"type":"Point"}
}