{
  "id": 2741589,
  "type": "Feature",
  "properties": {
    "tgn:hierarchy":[
        "tgn:2741589",
        "tgn:1000001",
        "tgn:7012149",
        "tgn:2000375",
        "tgn:7007248",
        "tgn:7029392"
    ],
    "tgn:id":2741589,
    "tgn:name":"Ussery Lake",
    "tgn:placetype":[
        "aat:300006191"
    ]
},
  "bbox": [],
  "geometry": {"coordinates":[-83.5333,33.0333],"type":"Point"}
}