{
  "id": 2519218,
  "type": "Feature",
  "properties": {
    "tgn:hierarchy":[
        "tgn:2519218",
        "tgn:1000001",
        "tgn:7012149",
        "tgn:2001698",
        "tgn:7007707",
        "tgn:7029392"
    ],
    "tgn:id":2519218,
    "tgn:name":"Moccasin Creek",
    "tgn:placetype":[
        "aat:300008706"
    ]
},
  "bbox": [],
  "geometry": {"coordinates":[-99.1333,36.95],"type":"Point"}
}