{
  "id": 7126116,
  "type": "Feature",
  "properties": {
    "tgn:hierarchy":[
        "tgn:7126116",
        "tgn:1000003",
        "tgn:7003685",
        "tgn:7000084",
        "tgn:7029392"
    ],
    "tgn:id":7126116,
    "tgn:name":"Bahnhof Oberholz",
    "tgn:placetype":[
        "aat:300007783"
    ]
},
  "bbox": [],
  "geometry": {"coordinates":[12.505833,51.257778],"type":"Point"}
}