{
  "id": 2243067,
  "type": "Feature",
  "properties": {
    "tgn:hierarchy":[
        "tgn:2243067",
        "tgn:1000001",
        "tgn:7012149",
        "tgn:2001040",
        "tgn:7007521",
        "tgn:7029392"
    ],
    "tgn:id":2243067,
    "tgn:name":"Clear Lake",
    "tgn:placetype":[
        "aat:300008680"
    ]
},
  "bbox": [],
  "geometry": {"coordinates":[-95.95,44.3167],"type":"Point"}
}