<<<<<<< HEAD
{
  "id": 7376680,
  "type": "Feature",
  "properties": {
    "tgn:hierarchy":[
        "tgn:7376680",
        "tgn:7005581",
        "tgn:1000001",
        "tgn:7005560",
        "tgn:7029392"
    ],
    "tgn:id":7376680,
    "tgn:name":"Lo de Pablo",
    "tgn:placetype":[
        "aat:300008347"
    ]
},
  "bbox": [],
  "geometry": {"coordinates":[-107.216667,25.933333],"type":"Point"}
}
=======
{"geometry":{"type":"Point","coordinates":[-107.216667,25.933333]},"type":"Feature","properties":{"hierarchy":["tgn:7376680","tgn:7005581","tgn:1000001","tgn:7005560","tgn:7029392"],"placetype":["aat:300008347"],"id":7376680,"name:xx":"Lo de Pablo"}}
>>>>>>> 03f74aca74312dbeaf24d7e61306dd6a786dc3d0
