{
  "id": 7568171,
  "type": "Feature",
  "properties": {
    "tgn:hierarchy":[
        "tgn:7568171",
        "tgn:1001828",
        "tgn:1000004",
        "tgn:7000198",
        "tgn:7029392"
    ],
    "tgn:id":7568171,
    "tgn:name:en":"Dommarapochampalli",
    "tgn:placetype":[
        "aat:300008347"
    ]
},
  "bbox": [],
  "geometry": {"coordinates":[78.415556,17.590278],"type":"Point"}
}