{
  "id": 2414824,
  "type": "Feature",
  "properties": {
    "tgn:hierarchy":[
        "tgn:2414824",
        "tgn:1000001",
        "tgn:7012149",
        "tgn:2001190",
        "tgn:7007523",
        "tgn:7029392"
    ],
    "tgn:id":2414824,
    "tgn:name":"Isabella Iron Bank",
    "tgn:placetype":[
        "aat:300000390"
    ]
},
  "bbox": [],
  "geometry": {"coordinates":[-91.45,38.05],"type":"Point"}
}