{
  "id": 7007234,
  "type": "Feature",
  "properties": {
    "tgn:hierarchy":[
        "tgn:7007234",
        "tgn:7003497",
        "tgn:7001201",
        "tgn:1000003",
        "tgn:1000078",
        "tgn:7029392"
    ],
    "tgn:id":7007234,
    "tgn:name:en":"Cloyne",
    "tgn:placetype":[
        "aat:300008347",
        "aat:300387235",
        "aat:300008375"
    ]
},
  "bbox": [],
  "geometry": {"coordinates":[-8.1167,51.8667],"type":"Point"}
}