{
  "id": 4011919,
  "type": "Feature",
  "properties": {
    "tgn:hierarchy":[
        "tgn:4011919",
        "tgn:1000003",
        "tgn:4011927",
        "tgn:7006669",
        "tgn:7029392"
    ],
    "tgn:id":4011919,
    "tgn:name":"Vlajkovac",
    "tgn:placetype":[
        "aat:300008347"
    ]
},
  "bbox": [],
  "geometry": {"coordinates":[21.2167,45.0667],"type":"Point"}
}