{
  "id": 1082363,
  "type": "Feature",
  "properties": {
    "tgn:hierarchy":[
        "tgn:1082363",
        "tgn:1000004",
        "tgn:1001372",
        "tgn:7000299",
        "tgn:7029392"
    ],
    "tgn:id":1082363,
    "tgn:name":"Sinny\u014fng",
    "tgn:placetype":[
        "aat:300008347"
    ]
},
  "bbox": [],
  "geometry": {"coordinates":[128.7833,36.0333],"type":"Point"}
}