{
  "id": 7497765,
  "type": "Feature",
  "properties": {
    "tgn:hierarchy":[
        "tgn:7497765",
        "tgn:7001004",
        "tgn:1000004",
        "tgn:1000141",
        "tgn:7029392"
    ],
    "tgn:id":7497765,
    "tgn:name":"Dadong Qiao",
    "tgn:placetype":[
        "aat:300007836"
    ]
},
  "bbox": [],
  "geometry": {"coordinates":[120.365315,22.624429],"type":"Point"}
}