{
  "id": 7275183,
  "type": "Feature",
  "properties": {
    "tgn:hierarchy":[
        "tgn:7275183",
        "tgn:7002464",
        "tgn:1000049",
        "tgn:1000002",
        "tgn:7029392"
    ],
    "tgn:id":7275183,
    "tgn:name":"Utalacata, Cerro",
    "tgn:placetype":[
        "aat:300008795"
    ]
},
  "bbox": [],
  "geometry": {"coordinates":[-69.333333,-18.833333],"type":"Point"}
}