{
  "id": 2625352,
  "type": "Feature",
  "properties": {
    "tgn:hierarchy":[
        "tgn:2625352",
        "tgn:1000001",
        "tgn:7012149",
        "tgn:2001892",
        "tgn:7007825",
        "tgn:7029392"
    ],
    "tgn:id":2625352,
    "tgn:name":"Rockhouse Hollow",
    "tgn:placetype":[
        "aat:300008761"
    ]
},
  "bbox": [],
  "geometry": {"coordinates":[-85.8667,36.4667],"type":"Point"}
}