{
  "id": 7444482,
  "type": "Feature",
  "properties": {
    "tgn:hierarchy":[
        "tgn:7444482",
        "tgn:7002445",
        "tgn:1000003",
        "tgn:7008180",
        "tgn:7008591",
        "tgn:7029392"
    ],
    "tgn:id":7444482,
    "tgn:name:en":"Kingston Deverill",
    "tgn:placetype":[
        "aat:300008347"
    ]
},
  "bbox": [],
  "geometry": {"coordinates":[-2.220278,51.133056],"type":"Point"}
}