{
  "id": 2671715,
  "type": "Feature",
  "properties": {
    "tgn:hierarchy":[
        "tgn:2671715",
        "tgn:1000001",
        "tgn:7012149",
        "tgn:2000183",
        "tgn:7007157",
        "tgn:7029392"
    ],
    "tgn:id":2671715,
    "tgn:name":"Smith Mountain",
    "tgn:placetype":[
        "aat:300008798"
    ]
},
  "bbox": [],
  "geometry": {"coordinates":[-116.6833,36.0167],"type":"Point"}
}