{
  "id": 2705752,
  "type": "Feature",
  "properties": {
    "tgn:hierarchy":[
        "tgn:2705752",
        "tgn:1000001",
        "tgn:7006451",
        "tgn:7012149",
        "tgn:2000100",
        "tgn:7029392"
    ],
    "tgn:id":2705752,
    "tgn:name":"Sutherland Ridge",
    "tgn:placetype":[
        "aat:300266640"
    ]
},
  "bbox": [],
  "geometry": {"coordinates":[-110.85,32.4167],"type":"Point"}
}