{
  "id": 7354474,
  "type": "Feature",
  "properties": {
    "tgn:hierarchy":[
        "tgn:7354474",
        "tgn:1000001",
        "tgn:7005597",
        "tgn:7005560",
        "tgn:7029392"
    ],
    "tgn:id":7354474,
    "tgn:name":"Chapote",
    "tgn:placetype":[
        "aat:300008347"
    ]
},
  "bbox": [],
  "geometry": {"coordinates":[-99.266667,26.716667],"type":"Point"}
}