{
  "id": 7559972,
  "type": "Feature",
  "properties": {
    "tgn:hierarchy":[
        "tgn:7559972",
        "tgn:1000004",
        "tgn:7000198",
        "tgn:7016722",
        "tgn:7029392"
    ],
    "tgn:id":7559972,
    "tgn:name:en":"Chor\u0101n",
    "tgn:placetype":[
        "aat:300008347"
    ]
},
  "bbox": [],
  "geometry": {"coordinates":[79.698254,27.68035],"type":"Point"}
}