{
  "id": 2311818,
  "type": "Feature",
  "properties": {
    "tgn:hierarchy":[
        "tgn:2311818",
        "tgn:7006450",
        "tgn:1000001",
        "tgn:7012149",
        "tgn:2000082",
        "tgn:7029392"
    ],
    "tgn:id":2311818,
    "tgn:name":"Eek Lake",
    "tgn:placetype":[
        "aat:300008680"
    ]
},
  "bbox": [],
  "geometry": {"coordinates":[-132.6667,55.1667],"type":"Point"}
}