{
  "id": 7539465,
  "type": "Feature",
  "properties": {
    "tgn:hierarchy":[
        "tgn:7539465",
        "tgn:7001242",
        "tgn:7016833",
        "tgn:7001334",
        "tgn:7029392"
    ],
    "tgn:id":7539465,
    "tgn:name:en":"\u015eakhrat 'Aysh al Ghur\u0101b",
    "tgn:placetype":[
        "aat:300008777"
    ]
},
  "bbox": [],
  "geometry": {"coordinates":[25.066667,23.733333],"type":"Point"}
}