{
  "id": 2484592,
  "type": "Feature",
  "properties": {
    "tgn:hierarchy":[
        "tgn:2484592",
        "tgn:1000001",
        "tgn:7012149",
        "tgn:7007157",
        "tgn:1002957",
        "tgn:7029392"
    ],
    "tgn:id":2484592,
    "tgn:name":"Laurel Lake",
    "tgn:placetype":[
        "aat:300008680"
    ]
},
  "bbox": [],
  "geometry": {"coordinates":[-119.7833,37.9833],"type":"Point"}
}