{
  "id": 7497317,
  "type": "Feature",
  "properties": {
    "tgn:hierarchy":[
        "tgn:7497317",
        "tgn:7001004",
        "tgn:1000004",
        "tgn:1000141",
        "tgn:7029392"
    ],
    "tgn:id":7497317,
    "tgn:name":"Nanxingjihua Tiantuqu",
    "tgn:placetype":[
        "aat:300006163"
    ]
},
  "bbox": [],
  "geometry": {"coordinates":[120.3378,22.5224],"type":"Point"}
}