{
  "id": 7591254,
  "type": "Feature",
  "properties": {
    "tgn:hierarchy":[
        "tgn:7591254",
        "tgn:1000004",
        "tgn:7000198",
        "tgn:7031786",
        "tgn:7029392"
    ],
    "tgn:id":7591254,
    "tgn:name:en":"Fatehpur",
    "tgn:placetype":[
        "aat:300008347"
    ]
},
  "bbox": [],
  "geometry": {"coordinates":[77.753893,30.440837],"type":"Point"}
}