{
  "id": 7593555,
  "type": "Feature",
  "properties": {
    "tgn:hierarchy":[
        "tgn:7593555",
        "tgn:7005424",
        "tgn:1000001",
        "tgn:7005388",
        "tgn:7029392"
    ],
    "tgn:id":7593555,
    "tgn:name":"Laguna Salada",
    "tgn:placetype":[
        "aat:300008347"
    ]
},
  "bbox": [],
  "geometry": {"coordinates":[-71.094,19.648],"type":"Point"}
}