{
  "id": 2754932,
  "type": "Feature",
  "properties": {
    "tgn:hierarchy":[
        "tgn:2754932",
        "tgn:1000001",
        "tgn:7012149",
        "tgn:2001290",
        "tgn:7007524",
        "tgn:7029392"
    ],
    "tgn:id":2754932,
    "tgn:name":"Weaver Gulch",
    "tgn:placetype":[
        "aat:300008761"
    ]
},
  "bbox": [],
  "geometry": {"coordinates":[-114.8167,47.0167],"type":"Point"}
}