{
  "id": 2363681,
  "type": "Feature",
  "properties": {
    "tgn:hierarchy":[
        "tgn:2363681",
        "tgn:1000001",
        "tgn:7012149",
        "tgn:2000448",
        "tgn:7007248",
        "tgn:7029392"
    ],
    "tgn:id":2363681,
    "tgn:name":"Green Island",
    "tgn:placetype":[
        "aat:300008791"
    ]
},
  "bbox": [],
  "geometry": {"coordinates":[-82.6667,33.9833],"type":"Point"}
}