{
  "id": 7428229,
  "type": "Feature",
  "properties": {
    "tgn:hierarchy":[
        "tgn:7428229",
        "tgn:1000001",
        "tgn:7005601",
        "tgn:7005560",
        "tgn:7029392"
    ],
    "tgn:id":7428229,
    "tgn:name":"Pinares",
    "tgn:placetype":[
        "aat:300008347"
    ]
},
  "bbox": [],
  "geometry": {"coordinates":[-103.583333,23.75],"type":"Point"}
}