{
  "id": 2379918,
  "type": "Feature",
  "properties": {
    "tgn:hierarchy":[
        "tgn:2379918",
        "tgn:1000001",
        "tgn:7012149",
        "tgn:2001718",
        "tgn:7007708",
        "tgn:7029392"
    ],
    "tgn:id":2379918,
    "tgn:name":"Hat Top",
    "tgn:placetype":[
        "aat:300008798"
    ]
},
  "bbox": [],
  "geometry": {"coordinates":[-117.8167,43.6333],"type":"Point"}
}