{
  "id": 7369752,
  "type": "Feature",
  "properties": {
    "tgn:hierarchy":[
        "tgn:7369752",
        "tgn:1000001",
        "tgn:7005595",
        "tgn:7005560",
        "tgn:7029392"
    ],
    "tgn:id":7369752,
    "tgn:name":"Jahuara",
    "tgn:placetype":[
        "aat:300008347"
    ]
},
  "bbox": [],
  "geometry": {"coordinates":[-108.933333,25.983333],"type":"Point"}
}