{
  "id": 2359418,
  "type": "Feature",
  "properties": {
    "tgn:hierarchy":[
        "tgn:2359418",
        "tgn:1000001",
        "tgn:7012149",
        "tgn:2000641",
        "tgn:7007253",
        "tgn:7029392"
    ],
    "tgn:id":2359418,
    "tgn:name":"Grant City",
    "tgn:placetype":[
        "aat:300008347"
    ]
},
  "bbox": [],
  "geometry": {"coordinates":[-94.8833,42.2667],"type":"Point"}
}