{
  "id": 7405296,
  "type": "Feature",
  "properties": {
    "tgn:hierarchy":[
        "tgn:7405296",
        "tgn:7005585",
        "tgn:1000001",
        "tgn:7005560",
        "tgn:7029392"
    ],
    "tgn:id":7405296,
    "tgn:name":"Las Culebras, R\u00edo",
    "tgn:placetype":[
        "aat:300008699"
    ]
},
  "bbox": [],
  "geometry": {"coordinates":[-100.116667,17.533333],"type":"Point"}
}