{
  "id": 7280434,
  "type": "Feature",
  "properties": {
    "tgn:hierarchy":[
        "tgn:7280434",
        "tgn:7002464",
        "tgn:1000049",
        "tgn:1000002",
        "tgn:7029392"
    ],
    "tgn:id":7280434,
    "tgn:name":"San Juan de la Soledad",
    "tgn:placetype":[
        "aat:300387033"
    ]
},
  "bbox": [],
  "geometry": {"coordinates":[-69.983333,-20.483333],"type":"Point"}
}