{
  "id": 1014284,
  "type": "Feature",
  "properties": {
    "tgn:hierarchy":[
        "tgn:1014284",
        "tgn:7005685",
        "tgn:7005807",
        "tgn:1000001",
        "tgn:7005801",
        "tgn:7029392"
    ],
    "tgn:id":1014284,
    "tgn:name":"Port Blandford",
    "tgn:placetype":[
        "aat:300008347"
    ]
},
  "bbox": [],
  "geometry": {"coordinates":[-54.1667,48.35],"type":"Point"}
}