<<<<<<< HEAD
{
  "id": 2157754,
  "type": "Feature",
  "properties": {
    "tgn:hierarchy":[
        "tgn:2157754",
        "tgn:1000001",
        "tgn:7012149",
        "tgn:2001750",
        "tgn:7007712",
        "tgn:7029392"
    ],
    "tgn:id":2157754,
    "tgn:name":"Beaver Hole Swamp",
    "tgn:placetype":[
        "aat:300008699"
    ]
},
  "bbox": [],
  "geometry": {"coordinates":[-79.1,33.8333],"type":"Point"}
}
=======
{"geometry":{"type":"Point","coordinates":[-79.100000,33.833300]},"type":"Feature","properties":{"hierarchy":["tgn:2157754","tgn:1000001","tgn:7012149","tgn:2001750","tgn:7007712","tgn:7029392"],"placetype":["aat:300008699"],"id":2157754,"name:xx":"Beaver Hole Swamp"}}
>>>>>>> 03f74aca74312dbeaf24d7e61306dd6a786dc3d0
