{
  "id": 2150052,
  "type": "Feature",
  "properties": {
    "tgn:hierarchy":[
        "tgn:2150052",
        "tgn:1000001",
        "tgn:7012149",
        "tgn:7007826",
        "tgn:7029392"
    ],
    "tgn:id":2150052,
    "tgn:name":"Barton Creek",
    "tgn:placetype":[
        "aat:300008706"
    ]
},
  "bbox": [],
  "geometry": {"coordinates":[-100.5833,36.0833],"type":"Point"}
}