{
  "id": 2467797,
  "type": "Feature",
  "properties": {
    "tgn:hierarchy":[
        "tgn:2467797",
        "tgn:1000001",
        "tgn:7012149",
        "tgn:2002265",
        "tgn:7013961",
        "tgn:7029392"
    ],
    "tgn:id":2467797,
    "tgn:name":"Long Knob",
    "tgn:placetype":[
        "aat:300008798"
    ]
},
  "bbox": [],
  "geometry": {"coordinates":[-78.85,39.2167],"type":"Point"}
}