{
  "id": 7376956,
  "type": "Feature",
  "properties": {
    "tgn:hierarchy":[
        "tgn:7376956",
        "tgn:7005583",
        "tgn:1000001",
        "tgn:7005560",
        "tgn:7029392"
    ],
    "tgn:id":7376956,
    "tgn:name":"Las Milpas",
    "tgn:placetype":[
        "aat:300008347"
    ]
},
  "bbox": [],
  "geometry": {"coordinates":[-106.816667,25.383333],"type":"Point"}
}