{
  "id": 2509025,
  "type": "Feature",
  "properties": {
    "tgn:hierarchy":[
        "tgn:2509025",
        "tgn:7006450",
        "tgn:2000069",
        "tgn:1000001",
        "tgn:7012149",
        "tgn:7029392"
    ],
    "tgn:id":2509025,
    "tgn:name":"Middle Fork Goodnews River",
    "tgn:placetype":[
        "aat:300008707"
    ]
},
  "bbox": [],
  "geometry": {"coordinates":[-160.4333,59.45],"type":"Point"}
}