{
  "id": 2127505,
  "type": "Feature",
  "properties": {
    "tgn:hierarchy":[
        "tgn:2127505",
        "tgn:7006450",
        "tgn:1000001",
        "tgn:7012149",
        "tgn:2124005",
        "tgn:7029392"
    ],
    "tgn:id":2127505,
    "tgn:name":"Akuliak Lake",
    "tgn:placetype":[
        "aat:300008680"
    ]
},
  "bbox": [],
  "geometry": {"coordinates":[-156.7833,68.2333],"type":"Point"}
}