{
  "id": 7202417,
  "type": "Feature",
  "properties": {
    "tgn:hierarchy":[
        "tgn:7202417",
        "tgn:1000003",
        "tgn:7003684",
        "tgn:7000084",
        "tgn:7029392"
    ],
    "tgn:id":7202417,
    "tgn:name":"Bubach",
    "tgn:placetype":[
        "aat:300008347"
    ]
},
  "bbox": [],
  "geometry": {"coordinates":[6.933333,49.416667],"type":"Point"}
}