{
  "id": 2358602,
  "type": "Feature",
  "properties": {
    "tgn:hierarchy":[
        "tgn:2358602",
        "tgn:1000001",
        "tgn:2000470",
        "tgn:7012149",
        "tgn:7007250",
        "tgn:7029392"
    ],
    "tgn:id":2358602,
    "tgn:name":"Grandjean",
    "tgn:placetype":[
        "aat:300008347"
    ]
},
  "bbox": [],
  "geometry": {"coordinates":[-115.1667,44.15],"type":"Point"}
}