{
  "id": 2634664,
  "type": "Feature",
  "properties": {
    "tgn:hierarchy":[
        "tgn:2634664",
        "tgn:1000001",
        "tgn:1002260",
        "tgn:7012149",
        "tgn:7007920",
        "tgn:7029392"
    ],
    "tgn:id":2634664,
    "tgn:name":"Ruth, Lake",
    "tgn:placetype":[
        "aat:300008680"
    ]
},
  "bbox": [],
  "geometry": {"coordinates":[-120.85,47.5667],"type":"Point"}
}