<<<<<<< HEAD
{
  "id": 7363598,
  "type": "Feature",
  "properties": {
    "tgn:hierarchy":[
        "tgn:7363598",
        "tgn:7005583",
        "tgn:1000001",
        "tgn:7005560",
        "tgn:7029392"
    ],
    "tgn:id":7363598,
    "tgn:name":"El Molino",
    "tgn:placetype":[
        "aat:300008347"
    ]
},
  "bbox": [],
  "geometry": {"coordinates":[-104.25,23.933333],"type":"Point"}
}
=======
{"geometry":{"type":"Point","coordinates":[-104.250000,23.933333]},"type":"Feature","properties":{"hierarchy":["tgn:7363598","tgn:7005583","tgn:1000001","tgn:7005560","tgn:7029392"],"placetype":["aat:300008347"],"id":7363598,"name:xx":"El Molino"}}
>>>>>>> 03f74aca74312dbeaf24d7e61306dd6a786dc3d0
