{
  "id": 7363598,
  "type": "Feature",
  "properties": {
    "tgn:hierarchy":[
        "tgn:7363598",
        "tgn:7005583",
        "tgn:1000001",
        "tgn:7005560",
        "tgn:7029392"
    ],
    "tgn:id":7363598,
    "tgn:name":"El Molino",
    "tgn:placetype":[
        "aat:300008347"
    ]
},
  "bbox": [],
  "geometry": {"coordinates":[-104.25,23.933333],"type":"Point"}
}