<<<<<<< HEAD
{
  "id": 7479677,
  "type": "Feature",
  "properties": {
    "tgn:hierarchy":[
        "tgn:7479677",
        "tgn:1000004",
        "tgn:7001013",
        "tgn:1000141",
        "tgn:7029392"
    ],
    "tgn:id":7479677,
    "tgn:name":"Qiucuo",
    "tgn:placetype":[
        "aat:300008347"
    ]
},
  "bbox": [],
  "geometry": {"coordinates":[121.094722,24.974722],"type":"Point"}
}
=======
{"geometry":{"type":"Point","coordinates":[121.094722,24.974722]},"type":"Feature","properties":{"hierarchy":["tgn:7479677","tgn:1000004","tgn:7001013","tgn:1000141","tgn:7029392"],"placetype":["aat:300008347"],"id":7479677,"name:xx":"Qiucuo"}}
>>>>>>> 03f74aca74312dbeaf24d7e61306dd6a786dc3d0
