{
  "id": 2653322,
  "type": "Feature",
  "properties": {
    "tgn:hierarchy":[
        "tgn:2653322",
        "tgn:1000001",
        "tgn:7012149",
        "tgn:2000226",
        "tgn:7007158",
        "tgn:7029392"
    ],
    "tgn:id":2653322,
    "tgn:name":"Sevenmile Creek",
    "tgn:placetype":[
        "aat:300008706"
    ]
},
  "bbox": [],
  "geometry": {"coordinates":[-105.6833,40.7333],"type":"Point"}
}