{
  "id": 7529457,
  "type": "Feature",
  "properties": {
    "tgn:hierarchy":[
        "tgn:7529457",
        "tgn:7001242",
        "tgn:7001311",
        "tgn:7016833",
        "tgn:7029392"
    ],
    "tgn:id":7529457,
    "tgn:name:en":"Umm \u0162unay\u1e11ib ash Sham\u0101l\u012b, W\u0101d\u012b",
    "tgn:placetype":[
        "aat:300379998"
    ]
},
  "bbox": [],
  "geometry": {"coordinates":[34.270262,22.259402],"type":"Point"}
}