{
  "id": 2126274,
  "type": "Feature",
  "properties": {
    "tgn:hierarchy":[
        "tgn:2126274",
        "tgn:1000001",
        "tgn:2001603",
        "tgn:7012149",
        "tgn:7007705",
        "tgn:7029392"
    ],
    "tgn:id":2126274,
    "tgn:name":"Adkinson Lake",
    "tgn:placetype":[
        "aat:300008680"
    ]
},
  "bbox": [],
  "geometry": {"coordinates":[-98.9333,46.8833],"type":"Point"}
}