{
  "id": 2309949,
  "type": "Feature",
  "properties": {
    "tgn:hierarchy":[
        "tgn:2309949",
        "tgn:1000001",
        "tgn:7012149",
        "tgn:7007157",
        "tgn:1002864",
        "tgn:7029392"
    ],
    "tgn:id":2309949,
    "tgn:name":"Easton Creek",
    "tgn:placetype":[
        "aat:300008706"
    ]
},
  "bbox": [],
  "geometry": {"coordinates":[-122.3833,37.5667],"type":"Point"}
}