{
  "id": 7333174,
  "type": "Feature",
  "properties": {
    "tgn:hierarchy":[
        "tgn:7333174",
        "tgn:7002808",
        "tgn:7030216",
        "tgn:1000003",
        "tgn:1000095",
        "tgn:7029392"
    ],
    "tgn:id":7333174,
    "tgn:name":"La Desenrocada, Punta",
    "tgn:placetype":[
        "aat:300386846"
    ]
},
  "bbox": [],
  "geometry": {"coordinates":[1.761688,41.218702],"type":"Point"}
}