{
  "id": 2460972,
  "type": "Feature",
  "properties": {
    "tgn:hierarchy":[
        "tgn:2460972",
        "tgn:1000001",
        "tgn:7012149",
        "tgn:7007157",
        "tgn:2000189",
        "tgn:7029392"
    ],
    "tgn:id":2460972,
    "tgn:name":"Little Smoky Creek",
    "tgn:placetype":[
        "aat:300008706"
    ]
},
  "bbox": [],
  "geometry": {"coordinates":[-122.7833,41.9667],"type":"Point"}
}