{
  "id": 7417134,
  "type": "Feature",
  "properties": {
    "tgn:hierarchy":[
        "tgn:7417134",
        "tgn:1000001",
        "tgn:7005591",
        "tgn:7005560",
        "tgn:7029392"
    ],
    "tgn:id":7417134,
    "tgn:name:es":"Agua Fr\u00eda, Cerro",
    "tgn:placetype":[
        "aat:300008795"
    ]
},
  "bbox": [],
  "geometry": {"coordinates":[-97.546667,16.365],"type":"Point"}
}