{
  "id": 7357565,
  "type": "Feature",
  "properties": {
    "tgn:hierarchy":[
        "tgn:7357565",
        "tgn:7005583",
        "tgn:1000001",
        "tgn:7005560",
        "tgn:7029392"
    ],
    "tgn:id":7357565,
    "tgn:name":"Corralitos",
    "tgn:placetype":[
        "aat:300008347"
    ]
},
  "bbox": [],
  "geometry": {"coordinates":[-105.366667,23.416667],"type":"Point"}
}