{
  "id": 7583708,
  "type": "Feature",
  "properties": {
    "tgn:hierarchy":[
        "tgn:7583708",
        "tgn:1000004",
        "tgn:7000198",
        "tgn:7016788",
        "tgn:7029392"
    ],
    "tgn:id":7583708,
    "tgn:name:en":"B\u0101jla",
    "tgn:placetype":[
        "aat:300008347"
    ]
},
  "bbox": [],
  "geometry": {"coordinates":[75.375936,28.263107],"type":"Point"}
}