{
  "id": 2214913,
  "type": "Feature",
  "properties": {
    "tgn:hierarchy":[
        "tgn:2214913",
        "tgn:1000001",
        "tgn:7012149",
        "tgn:2002029",
        "tgn:7007826",
        "tgn:7029392"
    ],
    "tgn:id":2214913,
    "tgn:name":"Caliche Tank",
    "tgn:placetype":[
        "aat:300006191"
    ]
},
  "bbox": [],
  "geometry": {"coordinates":[-98.25,28.1833],"type":"Point"}
}