{
  "id": 2615001,
  "type": "Feature",
  "properties": {
    "tgn:hierarchy":[
        "tgn:2615001",
        "tgn:1000001",
        "tgn:7006451",
        "tgn:7012149",
        "tgn:2000101",
        "tgn:7029392"
    ],
    "tgn:id":2615001,
    "tgn:name":"Represo Tank",
    "tgn:placetype":[
        "aat:300006191"
    ]
},
  "bbox": [],
  "geometry": {"coordinates":[-110.9167,32.5333],"type":"Point"}
}