{
  "id": 2037890,
  "type": "Feature",
  "properties": {
    "tgn:hierarchy":[
        "tgn:2037890",
        "tgn:1000001",
        "tgn:7012149",
        "tgn:1002544",
        "tgn:7007255",
        "tgn:7029392"
    ],
    "tgn:id":2037890,
    "tgn:name":"Bracht",
    "tgn:placetype":[
        "aat:300008347",
        "aat:300387210"
    ]
},
  "bbox": [],
  "geometry": {"coordinates":[-84.5833,38.8167],"type":"Point"}
}