{
  "id": 7089805,
  "type": "Feature",
  "properties": {
    "tgn:hierarchy":[
        "tgn:7089805",
        "tgn:1000003",
        "tgn:7003677",
        "tgn:7000084",
        "tgn:7029392"
    ],
    "tgn:id":7089805,
    "tgn:name":"Verse-Talsperre",
    "tgn:placetype":[
        "aat:300006191"
    ]
},
  "bbox": [],
  "geometry": {"coordinates":[7.683333,51.183333],"type":"Point"}
}