{
  "id": 2002990,
  "type": "Feature",
  "properties": {
    "tgn:hierarchy":[
        "tgn:2002990",
        "tgn:7002659",
        "tgn:1000001",
        "tgn:7012149",
        "tgn:2000044",
        "tgn:7029392"
    ],
    "tgn:id":2002990,
    "tgn:name":"Carter Grove",
    "tgn:placetype":[
        "aat:300008347",
        "aat:300387210"
    ]
},
  "bbox": [],
  "geometry": {"coordinates":[-86.6833,34.9333],"type":"Point"}
}