{
  "id": 2609636,
  "type": "Feature",
  "properties": {
    "tgn:hierarchy":[
        "tgn:2609636",
        "tgn:1000001",
        "tgn:7012149",
        "tgn:2001315",
        "tgn:7007524",
        "tgn:7029392"
    ],
    "tgn:id":2609636,
    "tgn:name":"Razor Creek",
    "tgn:placetype":[
        "aat:300008706"
    ]
},
  "bbox": [],
  "geometry": {"coordinates":[-108.4667,46.25],"type":"Point"}
}