{
  "id": 7567943,
  "type": "Feature",
  "properties": {
    "tgn:hierarchy":[
        "tgn:7567943",
        "tgn:1000004",
        "tgn:7000198",
        "tgn:7031786",
        "tgn:7029392"
    ],
    "tgn:id":7567943,
    "tgn:name:en":"Dhaniy\u0101kot",
    "tgn:placetype":[
        "aat:300008347"
    ]
},
  "bbox": [],
  "geometry": {"coordinates":[78.735278,29.796111],"type":"Point"}
}