{
  "id": 2696093,
  "type": "Feature",
  "properties": {
    "tgn:hierarchy":[
        "tgn:2696093",
        "tgn:1000001",
        "tgn:7012149",
        "tgn:2001516",
        "tgn:7007709",
        "tgn:7029392"
    ],
    "tgn:id":2696093,
    "tgn:name":"Stokely Hollow",
    "tgn:placetype":[
        "aat:300008761"
    ]
},
  "bbox": [],
  "geometry": {"coordinates":[-82.8333,35.8833],"type":"Point"}
}