{
  "id": 2008238,
  "type": "Feature",
  "properties": {
    "tgn:hierarchy":[
        "tgn:2008238",
        "tgn:1000001",
        "tgn:7016172",
        "tgn:7012149",
        "tgn:2000131",
        "tgn:7029392"
    ],
    "tgn:id":2008238,
    "tgn:name":"Fenter",
    "tgn:placetype":[
        "aat:300008347",
        "aat:300387210"
    ]
},
  "bbox": [],
  "geometry": {"coordinates":[-92.6333,34.3667],"type":"Point"}
}