{
  "id": 7486997,
  "type": "Feature",
  "properties": {
    "tgn:hierarchy":[
        "tgn:7486997",
        "tgn:1000004",
        "tgn:7492971",
        "tgn:1000141",
        "tgn:7029392"
    ],
    "tgn:id":7486997,
    "tgn:name":"Lilongxia Shan",
    "tgn:placetype":[
        "aat:300008798"
    ]
},
  "bbox": [],
  "geometry": {"coordinates":[120.702222,22.175],"type":"Point"}
}