{
  "id": 7494892,
  "type": "Feature",
  "properties": {
    "tgn:hierarchy":[
        "tgn:7494892",
        "tgn:7468018",
        "tgn:1000004",
        "tgn:1000141",
        "tgn:7029392"
    ],
    "tgn:id":7494892,
    "tgn:name":"Baolin Chansi",
    "tgn:placetype":[
        "aat:300007595"
    ]
},
  "bbox": [],
  "geometry": {"coordinates":[120.503605,23.540318],"type":"Point"}
}