{
  "id": 7513439,
  "type": "Feature",
  "properties": {
    "tgn:hierarchy":[
        "tgn:7513439",
        "tgn:7016670",
        "tgn:1008380",
        "tgn:1000226",
        "tgn:1000006",
        "tgn:7029392"
    ],
    "tgn:id":7513439,
    "tgn:name:en":"Glenross",
    "tgn:placetype":[
        "aat:300000206"
    ]
},
  "bbox": [],
  "geometry": {"coordinates":[176.466667,-39.45],"type":"Point"}
}