{
  "id": 2222932,
  "type": "Feature",
  "properties": {
    "tgn:hierarchy":[
        "tgn:2222932",
        "tgn:1000001",
        "tgn:7012149",
        "tgn:2002166",
        "tgn:7007919",
        "tgn:7029392"
    ],
    "tgn:id":2222932,
    "tgn:name":"Carrington",
    "tgn:placetype":[
        "aat:300008347"
    ]
},
  "bbox": [],
  "geometry": {"coordinates":[-78.8333,36.8667],"type":"Point"}
}