{
  "id": 2606683,
  "type": "Feature",
  "properties": {
    "tgn:hierarchy":[
        "tgn:2606683",
        "tgn:1000001",
        "tgn:7012149",
        "tgn:2001925",
        "tgn:7007825",
        "tgn:7029392"
    ],
    "tgn:id":2606683,
    "tgn:name":"Rams Creek",
    "tgn:placetype":[
        "aat:300008706"
    ]
},
  "bbox": [],
  "geometry": {"coordinates":[-85.6667,35.65],"type":"Point"}
}