{
  "id": 1031139,
  "type": "Feature",
  "properties": {
    "tgn:hierarchy":[
        "tgn:1031139",
        "tgn:7002445",
        "tgn:1000003",
        "tgn:7008118",
        "tgn:7008591",
        "tgn:7029392"
    ],
    "tgn:id":1031139,
    "tgn:name:ang":"Willetune",
    "tgn:placetype":[
        "aat:300008347"
    ]
},
  "bbox": [],
  "geometry": {"coordinates":[-1.55,52.833333],"type":"Point"}
}