<<<<<<< HEAD
{
  "id": 2336887,
  "type": "Feature",
  "properties": {
    "tgn:hierarchy":[
        "tgn:2336887",
        "tgn:1000001",
        "tgn:7012149",
        "tgn:2000723",
        "tgn:7007254",
        "tgn:7029392"
    ],
    "tgn:id":2336887,
    "tgn:name":"Fourmile Creek",
    "tgn:placetype":[
        "aat:300008706"
    ]
},
  "bbox": [],
  "geometry": {"coordinates":[-96.7,38.6333],"type":"Point"}
}
=======
{"geometry":{"type":"Point","coordinates":[-96.700000,38.633300]},"type":"Feature","properties":{"hierarchy":["tgn:2336887","tgn:1000001","tgn:7012149","tgn:2000723","tgn:7007254","tgn:7029392"],"placetype":["aat:300008706"],"id":2336887,"name:xx":"Fourmile Creek"}}
>>>>>>> 03f74aca74312dbeaf24d7e61306dd6a786dc3d0
