{
  "id": 2141435,
  "type": "Feature",
  "properties": {
    "tgn:hierarchy":[
        "tgn:2141435",
        "tgn:1000001",
        "tgn:2001410",
        "tgn:7012149",
        "tgn:7007526",
        "tgn:7029392"
    ],
    "tgn:id":2141435,
    "tgn:name":"Aztec Wash",
    "tgn:placetype":[
        "aat:300008699"
    ]
},
  "bbox": [],
  "geometry": {"coordinates":[-114.8333,35.65],"type":"Point"}
}