{
  "id": 7543899,
  "type": "Feature",
  "properties": {
    "tgn:hierarchy":[
        "tgn:7543899",
        "tgn:7001242",
        "tgn:7016833",
        "tgn:1001088",
        "tgn:7029392"
    ],
    "tgn:id":7543899,
    "tgn:name:en":"Tir'at N\u0101shid",
    "tgn:placetype":[
        "aat:300006075"
    ]
},
  "bbox": [],
  "geometry": {"coordinates":[30.670461,28.484428],"type":"Point"}
}