{
  "id": 2525609,
  "type": "Feature",
  "properties": {
    "tgn:hierarchy":[
        "tgn:2525609",
        "tgn:1000001",
        "tgn:7012149",
        "tgn:2000181",
        "tgn:7007157",
        "tgn:7029392"
    ],
    "tgn:id":2525609,
    "tgn:name":"Morton Grove",
    "tgn:placetype":[
        "aat:300132451"
    ]
},
  "bbox": [],
  "geometry": {"coordinates":[-123.9167,40.3667],"type":"Point"}
}