{
  "id": 2200861,
  "type": "Feature",
  "properties": {
    "tgn:hierarchy":[
        "tgn:2200861",
        "tgn:1000001",
        "tgn:2001430",
        "tgn:7012149",
        "tgn:7007566",
        "tgn:7029392"
    ],
    "tgn:id":2200861,
    "tgn:name":"Bryant Canyon",
    "tgn:placetype":[
        "aat:300008761"
    ]
},
  "bbox": [],
  "geometry": {"coordinates":[-105.2667,32.9667],"type":"Point"}
}