{
  "id": 7555325,
  "type": "Feature",
  "properties": {
    "tgn:hierarchy":[
        "tgn:7555325",
        "tgn:1000004",
        "tgn:1001871",
        "tgn:7000198",
        "tgn:7029392"
    ],
    "tgn:id":7555325,
    "tgn:name:en":"Mit\u0101thal",
    "tgn:placetype":[
        "aat:300008347"
    ]
},
  "bbox": [],
  "geometry": {"coordinates":[76.182204,28.88232],"type":"Point"}
}