{
  "id": 1015066,
  "type": "Feature",
  "properties": {
    "tgn:hierarchy":[
        "tgn:1015066",
        "tgn:7005685",
        "tgn:1000001",
        "tgn:7013154",
        "tgn:7029392"
    ],
    "tgn:id":1015066,
    "tgn:name":"Rockland",
    "tgn:placetype":[
        "aat:300008347"
    ]
},
  "bbox": [],
  "geometry": {"coordinates":[-75.3167,45.5333],"type":"Point"}
}