{
  "id": 7480702,
  "type": "Feature",
  "properties": {
    "tgn:hierarchy":[
        "tgn:7480702",
        "tgn:1000004",
        "tgn:7490934",
        "tgn:1000141",
        "tgn:7029392"
    ],
    "tgn:id":7480702,
    "tgn:name":"Nanxi Beiqiao",
    "tgn:placetype":[
        "aat:300007836"
    ]
},
  "bbox": [],
  "geometry": {"coordinates":[120.491007,23.186007],"type":"Point"}
}