{
  "id": 2234371,
  "type": "Feature",
  "properties": {
    "tgn:hierarchy":[
        "tgn:2234371",
        "tgn:1000001",
        "tgn:2002261",
        "tgn:7012149",
        "tgn:7013961",
        "tgn:7029392"
    ],
    "tgn:id":2234371,
    "tgn:name":"Cheney Knob",
    "tgn:placetype":[
        "aat:300008798"
    ]
},
  "bbox": [],
  "geometry": {"coordinates":[-80.8833,37.85],"type":"Point"}
}