{
  "id": 2561869,
  "type": "Feature",
  "properties": {
    "tgn:hierarchy":[
        "tgn:2561869",
        "tgn:1000001",
        "tgn:7012149",
        "tgn:1003033",
        "tgn:7007706",
        "tgn:7029392"
    ],
    "tgn:id":2561869,
    "tgn:name":"Otsego",
    "tgn:placetype":[
        "aat:300008347"
    ]
},
  "bbox": [],
  "geometry": {"coordinates":[-83.7667,41.4333],"type":"Point"}
}