{
  "id": 2343108,
  "type": "Feature",
  "properties": {
    "tgn:hierarchy":[
        "tgn:2343108",
        "tgn:1000001",
        "tgn:7012149",
        "tgn:1002877",
        "tgn:7007706",
        "tgn:7029392"
    ],
    "tgn:id":2343108,
    "tgn:name":"Gabe Run",
    "tgn:placetype":[
        "aat:300008699"
    ]
},
  "bbox": [],
  "geometry": {"coordinates":[-83.2167,38.6833],"type":"Point"}
}