{
  "id": 7483188,
  "type": "Feature",
  "properties": {
    "tgn:hierarchy":[
        "tgn:7483188",
        "tgn:1000004",
        "tgn:7001014",
        "tgn:1000141",
        "tgn:7029392"
    ],
    "tgn:id":7483188,
    "tgn:name":"Dongshi Qiao",
    "tgn:placetype":[
        "aat:300007836"
    ]
},
  "bbox": [],
  "geometry": {"coordinates":[120.244444,23.683889],"type":"Point"}
}