{
  "id": 7319385,
  "type": "Feature",
  "properties": {
    "tgn:hierarchy":[
        "tgn:7319385",
        "tgn:1001657",
        "tgn:1000049",
        "tgn:1000002",
        "tgn:7029392"
    ],
    "tgn:id":7319385,
    "tgn:name":"Amarilla, Loma",
    "tgn:placetype":[
        "aat:300008795"
    ]
},
  "bbox": [],
  "geometry": {"coordinates":[-70.916667,-30.15],"type":"Point"}
}