{
  "id": 7591983,
  "type": "Feature",
  "properties": {
    "tgn:hierarchy":[
        "tgn:7591983",
        "tgn:1000004",
        "tgn:7000198",
        "tgn:7000799",
        "tgn:7029392"
    ],
    "tgn:id":7591983,
    "tgn:name:en":"Ph\u0101re Forest",
    "tgn:placetype":[
        "aat:300008863"
    ]
},
  "bbox": [],
  "geometry": {"coordinates":[74.883333,32.966667],"type":"Point"}
}