{
  "id": 2625999,
  "type": "Feature",
  "properties": {
    "tgn:hierarchy":[
        "tgn:2625999",
        "tgn:1000001",
        "tgn:2002367",
        "tgn:7012149",
        "tgn:7007923",
        "tgn:7029392"
    ],
    "tgn:id":2625999,
    "tgn:name":"Rocky Butte Gulch",
    "tgn:placetype":[
        "aat:300008761"
    ]
},
  "bbox": [],
  "geometry": {"coordinates":[-105.6167,43.7333],"type":"Point"}
}