{
  "id": 2288832,
  "type": "Feature",
  "properties": {
    "tgn:hierarchy":[
        "tgn:2288832",
        "tgn:1000001",
        "tgn:7012149",
        "tgn:2000654",
        "tgn:7007253",
        "tgn:7029392"
    ],
    "tgn:id":2288832,
    "tgn:name":"Ditch Number 48",
    "tgn:placetype":[
        "aat:300006075"
    ]
},
  "bbox": [],
  "geometry": {"coordinates":[-94.2167,42.2667],"type":"Point"}
}