{
  "id": 7194549,
  "type": "Feature",
  "properties": {
    "tgn:hierarchy":[
        "tgn:7194549",
        "tgn:1000003",
        "tgn:7003678",
        "tgn:7000084",
        "tgn:7029392"
    ],
    "tgn:id":7194549,
    "tgn:name":"Diemenrode",
    "tgn:placetype":[
        "aat:300008347"
    ]
},
  "bbox": [],
  "geometry": {"coordinates":[9.85,51.066667],"type":"Point"}
}