<<<<<<< HEAD
{
  "id": 2761814,
  "type": "Feature",
  "properties": {
    "tgn:hierarchy":[
        "tgn:2761814",
        "tgn:1000001",
        "tgn:2001938",
        "tgn:7012149",
        "tgn:7007826",
        "tgn:7029392"
    ],
    "tgn:id":2761814,
    "tgn:name":"West Prong Medina River",
    "tgn:placetype":[
        "aat:300008707"
    ]
},
  "bbox": [],
  "geometry": {"coordinates":[-99.4333,29.75],"type":"Point"}
}
=======
{"geometry":{"type":"Point","coordinates":[-99.433300,29.750000]},"type":"Feature","properties":{"hierarchy":["tgn:2761814","tgn:1000001","tgn:2001938","tgn:7012149","tgn:7007826","tgn:7029392"],"placetype":["aat:300008707"],"id":2761814,"name:xx":"West Prong Medina River"}}
>>>>>>> 03f74aca74312dbeaf24d7e61306dd6a786dc3d0
