{
  "id": 2761597,
  "type": "Feature",
  "properties": {
    "tgn:hierarchy":[
        "tgn:2761597",
        "tgn:1002300",
        "tgn:1000001",
        "tgn:7012149",
        "tgn:7007564",
        "tgn:7029392"
    ],
    "tgn:id":2761597,
    "tgn:name":"West Peak",
    "tgn:placetype":[
        "aat:300008798"
    ]
},
  "bbox": [],
  "geometry": {"coordinates":[-71.4833,44.75],"type":"Point"}
}