<<<<<<< HEAD
{
  "id": 2761597,
  "type": "Feature",
  "properties": {
    "tgn:hierarchy":[
        "tgn:2761597",
        "tgn:1002300",
        "tgn:1000001",
        "tgn:7012149",
        "tgn:7007564",
        "tgn:7029392"
    ],
    "tgn:id":2761597,
    "tgn:name":"West Peak",
    "tgn:placetype":[
        "aat:300008798"
    ]
},
  "bbox": [],
  "geometry": {"coordinates":[-71.4833,44.75],"type":"Point"}
}
=======
{"geometry":{"type":"Point","coordinates":[-71.483300,44.750000]},"type":"Feature","properties":{"hierarchy":["tgn:2761597","tgn:1002300","tgn:1000001","tgn:7012149","tgn:7007564","tgn:7029392"],"placetype":["aat:300008798"],"id":2761597,"name:xx":"West Peak"}}
>>>>>>> 03f74aca74312dbeaf24d7e61306dd6a786dc3d0
