{
  "id": 2169043,
  "type": "Feature",
  "properties": {
    "tgn:hierarchy":[
        "tgn:2169043",
        "tgn:1000001",
        "tgn:7012149",
        "tgn:2002346",
        "tgn:7007922",
        "tgn:7029392"
    ],
    "tgn:id":2169043,
    "tgn:name":"Big Island",
    "tgn:placetype":[
        "aat:300008791"
    ]
},
  "bbox": [],
  "geometry": {"coordinates":[-92.4167,45.45],"type":"Point"}
}