{
  "id": 2105510,
  "type": "Feature",
  "properties": {
    "tgn:hierarchy":[
        "tgn:2105510",
        "tgn:1000001",
        "tgn:7012149",
        "tgn:2001983",
        "tgn:7007826",
        "tgn:7029392"
    ],
    "tgn:id":2105510,
    "tgn:name":"Lamasco",
    "tgn:placetype":[
        "aat:300008347"
    ]
},
  "bbox": [],
  "geometry": {"coordinates":[-96.05,33.6833],"type":"Point"}
}