<<<<<<< HEAD
{
  "id": 7057667,
  "type": "Feature",
  "properties": {
    "tgn:hierarchy":[
        "tgn:7057667",
        "tgn:7003139",
        "tgn:1000003",
        "tgn:7003080",
        "tgn:1000080",
        "tgn:7029392"
    ],
    "tgn:id":7057667,
    "tgn:name":"Arroncino, Fosso",
    "tgn:placetype":[
        "aat:300008699"
    ]
},
  "bbox": [],
  "geometry": {"coordinates":[11.75,42.416667],"type":"Point"}
}
=======
{"geometry":{"type":"Point","coordinates":[11.750000,42.416667]},"type":"Feature","properties":{"hierarchy":["tgn:7057667","tgn:7003139","tgn:1000003","tgn:7003080","tgn:1000080","tgn:7029392"],"placetype":["aat:300008699"],"id":7057667,"name:xx":"Arroncino, Fosso"}}
>>>>>>> 03f74aca74312dbeaf24d7e61306dd6a786dc3d0
