{
  "id": 7540013,
  "type": "Feature",
  "properties": {
    "tgn:hierarchy":[
        "tgn:7540013",
        "tgn:7001242",
        "tgn:7016833",
        "tgn:7001334",
        "tgn:7029392"
    ],
    "tgn:id":7540013,
    "tgn:name:en":"San\u0101, W\u0101d\u012b as",
    "tgn:placetype":[
        "aat:300379998"
    ]
},
  "bbox": [],
  "geometry": {"coordinates":[32.533333,23.583333],"type":"Point"}
}