{
  "id": 2701731,
  "type": "Feature",
  "properties": {
    "tgn:hierarchy":[
        "tgn:2701731",
        "tgn:1000001",
        "tgn:7012149",
        "tgn:2001711",
        "tgn:7007708",
        "tgn:7029392"
    ],
    "tgn:id":2701731,
    "tgn:name":"Sugarloaf",
    "tgn:placetype":[
        "aat:300008798"
    ]
},
  "bbox": [],
  "geometry": {"coordinates":[-122.5333,42.2167],"type":"Point"}
}