{
  "id": 1037905,
  "type": "Feature",
  "properties": {
    "tgn:hierarchy":[
        "tgn:1037905",
        "tgn:1000003",
        "tgn:7000094",
        "tgn:7000084",
        "tgn:7029392"
    ],
    "tgn:id":1037905,
    "tgn:name":"Vogelsang",
    "tgn:placetype":[
        "aat:300008347"
    ]
},
  "bbox": [],
  "geometry": {"coordinates":[14.166667,53.733333],"type":"Point"}
}