{
  "id": 2529523,
  "type": "Feature",
  "properties": {
    "tgn:hierarchy":[
        "tgn:2529523",
        "tgn:1000001",
        "tgn:2001808",
        "tgn:7012149",
        "tgn:7007713",
        "tgn:7029392"
    ],
    "tgn:id":2529523,
    "tgn:name":"Mud Lake",
    "tgn:placetype":[
        "aat:300008680"
    ]
},
  "bbox": [],
  "geometry": {"coordinates":[-97.5833,44.4667],"type":"Point"}
}