{
  "id": 2173677,
  "type": "Feature",
  "properties": {
    "tgn:hierarchy":[
        "tgn:2173677",
        "tgn:1000001",
        "tgn:7012149",
        "tgn:2001440",
        "tgn:7007566",
        "tgn:7029392"
    ],
    "tgn:id":2173677,
    "tgn:name":"Birchfield",
    "tgn:placetype":[
        "aat:300008347"
    ]
},
  "bbox": [],
  "geometry": {"coordinates":[-108.85,31.6167],"type":"Point"}
}