{
  "id": 1007946,
  "type": "Feature",
  "properties": {
    "tgn:hierarchy":[
        "tgn:1007946",
        "tgn:7011270",
        "tgn:7002674",
        "tgn:1000003",
        "tgn:1000074",
        "tgn:7029392"
    ],
    "tgn:id":1007946,
    "tgn:name:en":"M\u00fdkonos, N\u00edsos",
    "tgn:placetype":[
        "aat:300008791"
    ]
},
  "bbox": [],
  "geometry": {"coordinates":[25.383333,37.45],"type":"Point"}
}