{
  "id": 7258965,
  "type": "Feature",
  "properties": {
    "tgn:hierarchy":[
        "tgn:7258965",
        "tgn:7003460",
        "tgn:1000003",
        "tgn:1000063",
        "tgn:4012014",
        "tgn:7029392"
    ],
    "tgn:id":7258965,
    "tgn:name":"Ville-en-Hesbaye",
    "tgn:placetype":[
        "aat:300008347"
    ]
},
  "bbox": [],
  "geometry": {"coordinates":[5.115055,50.618532],"type":"Point"}
}