<<<<<<< HEAD
{
  "id": 2330738,
  "type": "Feature",
  "properties": {
    "tgn:hierarchy":[
        "tgn:2330738",
        "tgn:2000105",
        "tgn:1000001",
        "tgn:7016172",
        "tgn:7012149",
        "tgn:7029392"
    ],
    "tgn:id":2330738,
    "tgn:name":"Flat Lake",
    "tgn:placetype":[
        "aat:300008680"
    ]
},
  "bbox": [],
  "geometry": {"coordinates":[-91.2167,34.0333],"type":"Point"}
}
=======
{"geometry":{"type":"Point","coordinates":[-91.216700,34.033300]},"type":"Feature","properties":{"hierarchy":["tgn:2330738","tgn:2000105","tgn:1000001","tgn:7016172","tgn:7012149","tgn:7029392"],"placetype":["aat:300008680"],"id":2330738,"name:xx":"Flat Lake"}}
>>>>>>> 03f74aca74312dbeaf24d7e61306dd6a786dc3d0
