{
  "id": 4011406,
  "type": "Feature",
  "properties": {
    "tgn:hierarchy":[
        "tgn:4011406",
        "tgn:7002445",
        "tgn:1000003",
        "tgn:7008185",
        "tgn:7008591",
        "tgn:7029392"
    ],
    "tgn:id":4011406,
    "tgn:name:en":"Tuddenham",
    "tgn:placetype":[
        "aat:300008347"
    ]
},
  "bbox": [],
  "geometry": {"coordinates":[0.55,52.316667],"type":"Point"}
}