<<<<<<< HEAD
{
  "id": 7028571,
  "type": "Feature",
  "properties": {
    "tgn:hierarchy":[
        "tgn:7028571",
        "tgn:7002445",
        "tgn:1000003",
        "tgn:7008160",
        "tgn:7008591",
        "tgn:7029392"
    ],
    "tgn:id":7028571,
    "tgn:name":"Rockland All Saints",
    "tgn:placetype":[
        "aat:300008347",
        "aat:300008372"
    ]
},
  "bbox": [],
  "geometry": {"coordinates":[0.948,52.518],"type":"Point"}
}
=======
{"geometry":{"type":"Point","coordinates":[0.948000,52.518000]},"type":"Feature","properties":{"hierarchy":["tgn:7028571","tgn:7002445","tgn:1000003","tgn:7008160","tgn:7008591","tgn:7029392"],"placetype":["aat:300008347","aat:300008372"],"id":7028571,"name:xx":"Rockland All Saints"}}
>>>>>>> 03f74aca74312dbeaf24d7e61306dd6a786dc3d0
