{
  "id": 7028571,
  "type": "Feature",
  "properties": {
    "tgn:hierarchy":[
        "tgn:7028571",
        "tgn:7002445",
        "tgn:1000003",
        "tgn:7008160",
        "tgn:7008591",
        "tgn:7029392"
    ],
    "tgn:id":7028571,
    "tgn:name":"Rockland All Saints",
    "tgn:placetype":[
        "aat:300008347",
        "aat:300008372"
    ]
},
  "bbox": [],
  "geometry": {"coordinates":[0.948,52.518],"type":"Point"}
}