{
  "id": 7207552,
  "type": "Feature",
  "properties": {
    "tgn:hierarchy":[
        "tgn:7207552",
        "tgn:7003669",
        "tgn:1000003",
        "tgn:7000084",
        "tgn:7029392"
    ],
    "tgn:id":7207552,
    "tgn:name":"B\u00fcrg",
    "tgn:placetype":[
        "aat:300008347"
    ]
},
  "bbox": [],
  "geometry": {"coordinates":[12.316667,48.433333],"type":"Point"}
}