{
  "id": 7031734,
  "type": "Feature",
  "properties": {
    "tgn:hierarchy":[
        "tgn:7031734",
        "tgn:7005852",
        "tgn:1000003",
        "tgn:7003237",
        "tgn:1000080",
        "tgn:7029392"
    ],
    "tgn:id":7031734,
    "tgn:name":"Griante",
    "tgn:placetype":[
        "aat:300008347"
    ]
},
  "bbox": [],
  "geometry": {"coordinates":[9.216667,45.983333],"type":"Point"}
}