{
  "id": 7276895,
  "type": "Feature",
  "properties": {
    "tgn:hierarchy":[
        "tgn:7276895",
        "tgn:1001699",
        "tgn:1000049",
        "tgn:1000002",
        "tgn:7029392"
    ],
    "tgn:id":7276895,
    "tgn:name":"Yolque, Estero",
    "tgn:placetype":[
        "aat:300008699"
    ]
},
  "bbox": [],
  "geometry": {"coordinates":[-72.166667,-40.333333],"type":"Point"}
}