{
  "id": 2476565,
  "type": "Feature",
  "properties": {
    "tgn:hierarchy":[
        "tgn:2476565",
        "tgn:1000001",
        "tgn:7006451",
        "tgn:2000092",
        "tgn:7012149",
        "tgn:7029392"
    ],
    "tgn:id":2476565,
    "tgn:name":"Lute Hart Tank",
    "tgn:placetype":[
        "aat:300006191"
    ]
},
  "bbox": [],
  "geometry": {"coordinates":[-111.1167,34.7833],"type":"Point"}
}