{
  "id": 2661113,
  "type": "Feature",
  "properties": {
    "tgn:hierarchy":[
        "tgn:2661113",
        "tgn:1000001",
        "tgn:7012149",
        "tgn:2001714",
        "tgn:7007708",
        "tgn:7029392"
    ],
    "tgn:id":2661113,
    "tgn:name":"Short Lake",
    "tgn:placetype":[
        "aat:300008680"
    ]
},
  "bbox": [],
  "geometry": {"coordinates":[-121.4167,42.2333],"type":"Point"}
}