{
  "id": 7359043,
  "type": "Feature",
  "properties": {
    "tgn:hierarchy":[
        "tgn:7359043",
        "tgn:1000001",
        "tgn:7005601",
        "tgn:7005560",
        "tgn:7029392"
    ],
    "tgn:id":7359043,
    "tgn:name":"El \u00c1guila",
    "tgn:placetype":[
        "aat:300008347"
    ]
},
  "bbox": [],
  "geometry": {"coordinates":[-103.183333,23.366667],"type":"Point"}
}