{
  "id": 2578440,
  "type": "Feature",
  "properties": {
    "tgn:hierarchy":[
        "tgn:2578440",
        "tgn:1000001",
        "tgn:7012149",
        "tgn:2002384",
        "tgn:7007923",
        "tgn:7029392"
    ],
    "tgn:id":2578440,
    "tgn:name":"Phelps Lake",
    "tgn:placetype":[
        "aat:300008680"
    ]
},
  "bbox": [],
  "geometry": {"coordinates":[-110.7833,43.6333],"type":"Point"}
}