{
  "id": 7218764,
  "type": "Feature",
  "properties": {
    "tgn:hierarchy":[
        "tgn:7218764",
        "tgn:7011163",
        "tgn:7002674",
        "tgn:1000003",
        "tgn:1000074",
        "tgn:7029392"
    ],
    "tgn:id":7218764,
    "tgn:name":"Tho\u00farion",
    "tgn:placetype":[
        "aat:300008347"
    ]
},
  "bbox": [],
  "geometry": {"coordinates":[26.55,41.433333],"type":"Point"}
}