{
  "id": 1096266,
  "type": "Feature",
  "properties": {
    "tgn:hierarchy":[
        "tgn:1096266",
        "tgn:7000490",
        "tgn:1000006",
        "tgn:7001828",
        "tgn:7029392"
    ],
    "tgn:id":1096266,
    "tgn:name":"Beverly Hills",
    "tgn:placetype":[
        "aat:300008347"
    ]
},
  "bbox": [],
  "geometry": {"coordinates":[151.0833,-33.95],"type":"Point"}
}