{
  "id": 7335972,
  "type": "Feature",
  "properties": {
    "tgn:hierarchy":[
        "tgn:7335972",
        "tgn:7008912",
        "tgn:7030216",
        "tgn:1000003",
        "tgn:1000095",
        "tgn:7029392"
    ],
    "tgn:id":7335972,
    "tgn:name":"Ginestarre",
    "tgn:placetype":[
        "aat:300008347"
    ]
},
  "bbox": [],
  "geometry": {"coordinates":[1.262884,42.597002],"type":"Point"}
}