<<<<<<< HEAD
{
  "id": 7360857,
  "type": "Feature",
  "properties": {
    "tgn:hierarchy":[
        "tgn:7360857",
        "tgn:1000001",
        "tgn:1001906",
        "tgn:7005560",
        "tgn:7029392"
    ],
    "tgn:id":7360857,
    "tgn:name":"Cohuipa",
    "tgn:placetype":[
        "aat:300008347"
    ]
},
  "bbox": [],
  "geometry": {"coordinates":[-105.033333,21.816667],"type":"Point"}
}
=======
{"geometry":{"type":"Point","coordinates":[-105.033333,21.816667]},"type":"Feature","properties":{"hierarchy":["tgn:7360857","tgn:1000001","tgn:1001906","tgn:7005560","tgn:7029392"],"placetype":["aat:300008347"],"id":7360857,"name:xx":"Cohuipa"}}
>>>>>>> 03f74aca74312dbeaf24d7e61306dd6a786dc3d0
