{
  "id": 2191356,
  "type": "Feature",
  "properties": {
    "tgn:hierarchy":[
        "tgn:2191356",
        "tgn:1000001",
        "tgn:2001424",
        "tgn:7012149",
        "tgn:7007564",
        "tgn:7029392"
    ],
    "tgn:id":2191356,
    "tgn:name":"Brackett Brook",
    "tgn:placetype":[
        "aat:300008699"
    ]
},
  "bbox": [],
  "geometry": {"coordinates":[-71.9833,43.85],"type":"Point"}
}