{
  "id": 7224372,
  "type": "Feature",
  "properties": {
    "tgn:hierarchy":[
        "tgn:7224372",
        "tgn:7011330",
        "tgn:7002674",
        "tgn:1000003",
        "tgn:1000074",
        "tgn:7029392"
    ],
    "tgn:id":7224372,
    "tgn:name":"K\u00f3rfos, Orm\u00edskos",
    "tgn:placetype":[
        "aat:300132316"
    ]
},
  "bbox": [],
  "geometry": {"coordinates":[27.132222,36.570278],"type":"Point"}
}