{
  "id": 2661227,
  "type": "Feature",
  "properties": {
    "tgn:hierarchy":[
        "tgn:2661227",
        "tgn:1000001",
        "tgn:7012149",
        "tgn:2002297",
        "tgn:7013961",
        "tgn:7029392"
    ],
    "tgn:id":2661227,
    "tgn:name":"Short Run",
    "tgn:placetype":[
        "aat:300008699"
    ]
},
  "bbox": [],
  "geometry": {"coordinates":[-80.8833,39.3167],"type":"Point"}
}