{
  "id": 2731512,
  "type": "Feature",
  "properties": {
    "tgn:hierarchy":[
        "tgn:2731512",
        "tgn:1000001",
        "tgn:2001429",
        "tgn:7012149",
        "tgn:7007566",
        "tgn:7029392"
    ],
    "tgn:id":2731512,
    "tgn:name":"Tularosa Tank",
    "tgn:placetype":[
        "aat:300006191"
    ]
},
  "bbox": [],
  "geometry": {"coordinates":[-108.5333,33.9167],"type":"Point"}
}