{
  "id": 7267132,
  "type": "Feature",
  "properties": {
    "tgn:hierarchy":[
        "tgn:7267132",
        "tgn:1000003",
        "tgn:7003626",
        "tgn:7016845",
        "tgn:7029392"
    ],
    "tgn:id":7267132,
    "tgn:name:nl":"Oldenhof",
    "tgn:placetype":[
        "aat:300387502"
    ]
},
  "bbox": [],
  "geometry": {"coordinates":[5.983333,52.666667],"type":"Point"}
}