{
  "id": 7463499,
  "type": "Feature",
  "properties": {
    "tgn:hierarchy":[
        "tgn:7463499",
        "tgn:7002445",
        "tgn:1000003",
        "tgn:7008160",
        "tgn:7008591",
        "tgn:7029392"
    ],
    "tgn:id":7463499,
    "tgn:name:en":"Leman Bank",
    "tgn:placetype":[
        "aat:300386970"
    ]
},
  "bbox": [],
  "geometry": {"coordinates":[1.95,53.116667],"type":"Point"}
}