{
  "id": 2204978,
  "type": "Feature",
  "properties": {
    "tgn:hierarchy":[
        "tgn:2204978",
        "tgn:1000001",
        "tgn:7012149",
        "tgn:2002359",
        "tgn:7007922",
        "tgn:7029392"
    ],
    "tgn:id":2204978,
    "tgn:name":"Bug Lake",
    "tgn:placetype":[
        "aat:300008680"
    ]
},
  "bbox": [],
  "geometry": {"coordinates":[-89.65,45.9333],"type":"Point"}
}