{
  "id": 1048382,
  "type": "Feature",
  "properties": {
    "tgn:hierarchy":[
        "tgn:1048382",
        "tgn:7002448",
        "tgn:7019187",
        "tgn:1000003",
        "tgn:7008591",
        "tgn:7029392"
    ],
    "tgn:id":1048382,
    "tgn:name:en":"Lisburn",
    "tgn:placetype":[
        "aat:300008347",
        "aat:300387220"
    ]
},
  "bbox": [],
  "geometry": {"coordinates":[-6.066667,54.516667],"type":"Point"}
}