{
  "id": 2735609,
  "type": "Feature",
  "properties": {
    "tgn:hierarchy":[
        "tgn:2735609",
        "tgn:1000001",
        "tgn:7012149",
        "tgn:7019015",
        "tgn:7007251",
        "tgn:7029392"
    ],
    "tgn:id":2735609,
    "tgn:name":"Twin Grove",
    "tgn:placetype":[
        "aat:300008347"
    ]
},
  "bbox": [],
  "geometry": {"coordinates":[-89.0667,40.4833],"type":"Point"}
}