{
  "id": 1136367,
  "type": "Feature",
  "properties": {
    "tgn:hierarchy":[
        "tgn:1136367",
        "tgn:1000001",
        "tgn:7005589",
        "tgn:7005560",
        "tgn:7029392"
    ],
    "tgn:id":1136367,
    "tgn:name":"San Rafael",
    "tgn:placetype":[
        "aat:300008347"
    ]
},
  "bbox": [],
  "geometry": {"coordinates":[-100.55,25.016667],"type":"Point"}
}