{
  "id": 2098462,
  "type": "Feature",
  "properties": {
    "tgn:hierarchy":[
        "tgn:2098462",
        "tgn:1000001",
        "tgn:7012149",
        "tgn:2001866",
        "tgn:7007825",
        "tgn:7029392"
    ],
    "tgn:id":2098462,
    "tgn:name":"Chestnut Ridge",
    "tgn:placetype":[
        "aat:300008347",
        "aat:300387210"
    ]
},
  "bbox": [],
  "geometry": {"coordinates":[-82.6833,36.1333],"type":"Point"}
}