{
  "id": 7056581,
  "type": "Feature",
  "properties": {
    "tgn:hierarchy":[
        "tgn:7056581",
        "tgn:7003170",
        "tgn:1000003",
        "tgn:7003125",
        "tgn:1000080",
        "tgn:7029392"
    ],
    "tgn:id":7056581,
    "tgn:name":"Bevano, Torrente",
    "tgn:placetype":[
        "aat:300008699"
    ]
},
  "bbox": [],
  "geometry": {"coordinates":[12.616667,43.466667],"type":"Point"}
}