{
  "id": 2571377,
  "type": "Feature",
  "properties": {
    "tgn:hierarchy":[
        "tgn:2571377",
        "tgn:7014010",
        "tgn:1000001",
        "tgn:1002344",
        "tgn:7012149",
        "tgn:7007517",
        "tgn:7029392"
    ],
    "tgn:id":2571377,
    "tgn:name":"Paul Point",
    "tgn:placetype":[
        "aat:300008850"
    ]
},
  "bbox": [],
  "geometry": {"coordinates":[-70.6833,41.4333],"type":"Point"}
}