{
  "id": 1140522,
  "type": "Feature",
  "properties": {
    "tgn:hierarchy":[
        "tgn:1140522",
        "tgn:7000895",
        "tgn:1000004",
        "tgn:1001014",
        "tgn:1000120",
        "tgn:7029392"
    ],
    "tgn:id":1140522,
    "tgn:name":"Nakaj\u014d",
    "tgn:placetype":[
        "aat:300008347"
    ]
},
  "bbox": [],
  "geometry": {"coordinates":[139.3667,38.0333],"type":"Point"}
}