{
  "id": 2509549,
  "type": "Feature",
  "properties": {
    "tgn:hierarchy":[
        "tgn:2509549",
        "tgn:1000001",
        "tgn:7012149",
        "tgn:7007158",
        "tgn:7029392"
    ],
    "tgn:id":2509549,
    "tgn:name":"Middle Fork Wolf Creek",
    "tgn:placetype":[
        "aat:300008706"
    ]
},
  "bbox": [],
  "geometry": {"coordinates":[-108.5333,40.3167],"type":"Point"}
}