{
  "id": 2199073,
  "type": "Feature",
  "properties": {
    "tgn:hierarchy":[
        "tgn:2199073",
        "tgn:2000857",
        "tgn:1000001",
        "tgn:7012149",
        "tgn:7007256",
        "tgn:7029392"
    ],
    "tgn:id":2199073,
    "tgn:name":"Brulie Maurin",
    "tgn:placetype":[
        "aat:300008347"
    ]
},
  "bbox": [],
  "geometry": {"coordinates":[-90.9833,30.0333],"type":"Point"}
}