{
  "id": 7172208,
  "type": "Feature",
  "properties": {
    "tgn:hierarchy":[
        "tgn:7172208",
        "tgn:1000003",
        "tgn:7003682",
        "tgn:7000084",
        "tgn:7029392"
    ],
    "tgn:id":7172208,
    "tgn:name":"Hinterwald",
    "tgn:placetype":[
        "aat:300008347"
    ]
},
  "bbox": [],
  "geometry": {"coordinates":[7.716667,50.283333],"type":"Point"}
}