{
  "id": 1071367,
  "type": "Feature",
  "properties": {
    "tgn:hierarchy":[
        "tgn:1071367",
        "tgn:1000004",
        "tgn:7002084",
        "tgn:1000111",
        "tgn:7029392"
    ],
    "tgn:id":1071367,
    "tgn:name":"Sanyuan",
    "tgn:placetype":[
        "aat:300008347"
    ]
},
  "bbox": [],
  "geometry": {"coordinates":[108.9333,34.6667],"type":"Point"}
}