{
  "id": 2286064,
  "type": "Feature",
  "properties": {
    "tgn:hierarchy":[
        "tgn:2286064",
        "tgn:1000001",
        "tgn:7012149",
        "tgn:1002549",
        "tgn:7007919",
        "tgn:7029392"
    ],
    "tgn:id":2286064,
    "tgn:name":"Dew Pond",
    "tgn:placetype":[
        "aat:300006191"
    ]
},
  "bbox": [],
  "geometry": {"coordinates":[-76.85,37.7833],"type":"Point"}
}