{
  "id": 2201745,
  "type": "Feature",
  "properties": {
    "tgn:hierarchy":[
        "tgn:2201745",
        "tgn:1000001",
        "tgn:7012149",
        "tgn:1002554",
        "tgn:7007920",
        "tgn:7029392"
    ],
    "tgn:id":2201745,
    "tgn:name":"Buck Creek",
    "tgn:placetype":[
        "aat:300008706"
    ]
},
  "bbox": [],
  "geometry": {"coordinates":[-121.5667,45.85],"type":"Point"}
}