{
  "id": 2255563,
  "type": "Feature",
  "properties": {
    "tgn:hierarchy":[
        "tgn:2255563",
        "tgn:1000001",
        "tgn:7012149",
        "tgn:2001900",
        "tgn:7007825",
        "tgn:7029392"
    ],
    "tgn:id":2255563,
    "tgn:name":"Copeland Hill",
    "tgn:placetype":[
        "aat:300008798"
    ]
},
  "bbox": [],
  "geometry": {"coordinates":[-86.3667,35.15],"type":"Point"}
}