{
  "id": 7364328,
  "type": "Feature",
  "properties": {
    "tgn:hierarchy":[
        "tgn:7364328",
        "tgn:1000001",
        "tgn:1001960",
        "tgn:7005560",
        "tgn:7029392"
    ],
    "tgn:id":7364328,
    "tgn:name":"Rancho El Naranjo",
    "tgn:placetype":[
        "aat:300000241"
    ]
},
  "bbox": [],
  "geometry": {"coordinates":[-111.15,30.55],"type":"Point"}
}