<<<<<<< HEAD
{
  "id": 7364328,
  "type": "Feature",
  "properties": {
    "tgn:hierarchy":[
        "tgn:7364328",
        "tgn:1000001",
        "tgn:1001960",
        "tgn:7005560",
        "tgn:7029392"
    ],
    "tgn:id":7364328,
    "tgn:name":"Rancho El Naranjo",
    "tgn:placetype":[
        "aat:300000241"
    ]
},
  "bbox": [],
  "geometry": {"coordinates":[-111.15,30.55],"type":"Point"}
}
=======
{"geometry":{"type":"Point","coordinates":[-111.150000,30.550000]},"type":"Feature","properties":{"hierarchy":["tgn:7364328","tgn:1000001","tgn:1001960","tgn:7005560","tgn:7029392"],"placetype":["aat:300000241"],"id":7364328,"name:xx":"Rancho El Naranjo"}}
>>>>>>> 03f74aca74312dbeaf24d7e61306dd6a786dc3d0
