{
  "id": 2528460,
  "type": "Feature",
  "properties": {
    "tgn:hierarchy":[
        "tgn:2528460",
        "tgn:1000001",
        "tgn:7012149",
        "tgn:7007920",
        "tgn:7029392"
    ],
    "tgn:id":2528460,
    "tgn:name":"Mox Chehalis Creek",
    "tgn:placetype":[
        "aat:300008706"
    ]
},
  "bbox": [],
  "geometry": {"coordinates":[-123.1667,47.05],"type":"Point"}
}