<<<<<<< HEAD
{
  "id": 2760706,
  "type": "Feature",
  "properties": {
    "tgn:hierarchy":[
        "tgn:2760706",
        "tgn:1000001",
        "tgn:7012149",
        "tgn:2001275",
        "tgn:7007524",
        "tgn:7029392"
    ],
    "tgn:id":2760706,
    "tgn:name":"West Gallatin",
    "tgn:placetype":[
        "aat:300008347"
    ]
},
  "bbox": [],
  "geometry": {"coordinates":[-111.2167,45.7],"type":"Point"}
}
=======
{"geometry":{"type":"Point","coordinates":[-111.216700,45.700000]},"type":"Feature","properties":{"hierarchy":["tgn:2760706","tgn:1000001","tgn:7012149","tgn:2001275","tgn:7007524","tgn:7029392"],"placetype":["aat:300008347"],"id":2760706,"name:xx":"West Gallatin"}}
>>>>>>> 03f74aca74312dbeaf24d7e61306dd6a786dc3d0
