{
  "id": 2350489,
  "type": "Feature",
  "properties": {
    "tgn:hierarchy":[
        "tgn:2350489",
        "tgn:2001623",
        "tgn:1000001",
        "tgn:7012149",
        "tgn:7007707",
        "tgn:7029392"
    ],
    "tgn:id":2350489,
    "tgn:name":"Gittin Down Mountain",
    "tgn:placetype":[
        "aat:300008798"
    ]
},
  "bbox": [],
  "geometry": {"coordinates":[-94.7333,35.75],"type":"Point"}
}