{
  "id": 7549734,
  "type": "Feature",
  "properties": {
    "tgn:hierarchy":[
        "tgn:7549734",
        "tgn:1000004",
        "tgn:7000198",
        "tgn:7016788",
        "tgn:7029392"
    ],
    "tgn:id":7549734,
    "tgn:name:en":"Ch\u0101manderi",
    "tgn:placetype":[
        "aat:300008347"
    ]
},
  "bbox": [],
  "geometry": {"coordinates":[73.108558,24.942485],"type":"Point"}
}