{
  "id": 2565466,
  "type": "Feature",
  "properties": {
    "tgn:hierarchy":[
        "tgn:2565466",
        "tgn:1000001",
        "tgn:7012149",
        "tgn:7007157",
        "tgn:2000188",
        "tgn:7029392"
    ],
    "tgn:id":2565466,
    "tgn:name":"Painter Creek",
    "tgn:placetype":[
        "aat:300008706"
    ]
},
  "bbox": [],
  "geometry": {"coordinates":[-122.1667,40.7167],"type":"Point"}
}