{
  "id": 2527680,
  "type": "Feature",
  "properties": {
    "tgn:hierarchy":[
        "tgn:2527680",
        "tgn:1000001",
        "tgn:1002284",
        "tgn:7012149",
        "tgn:7007568",
        "tgn:7029392"
    ],
    "tgn:id":2527680,
    "tgn:name":"Mountain Brook",
    "tgn:placetype":[
        "aat:300008699"
    ]
},
  "bbox": [],
  "geometry": {"coordinates":[-73.7833,44.6833],"type":"Point"}
}