{
  "id": 2021804,
  "type": "Feature",
  "properties": {
    "tgn:hierarchy":[
        "tgn:2021804",
        "tgn:2000256",
        "tgn:1000001",
        "tgn:7012149",
        "tgn:7007240",
        "tgn:7029392"
    ],
    "tgn:id":2021804,
    "tgn:name":"Windsor",
    "tgn:placetype":[
        "aat:300008347",
        "aat:300387210"
    ]
},
  "bbox": [],
  "geometry": {"coordinates":[-82.1833,29.6333],"type":"Point"}
}