{
  "id": 2272858,
  "type": "Feature",
  "properties": {
    "tgn:hierarchy":[
        "tgn:2272858",
        "tgn:1000001",
        "tgn:7012149",
        "tgn:2000217",
        "tgn:7007158",
        "tgn:7029392"
    ],
    "tgn:id":2272858,
    "tgn:name":"Cutler Draw",
    "tgn:placetype":[
        "aat:300008761"
    ]
},
  "bbox": [],
  "geometry": {"coordinates":[-107.25,38.3333],"type":"Point"}
}