{
  "id": 1118622,
  "type": "Feature",
  "properties": {
    "tgn:hierarchy":[
        "tgn:1118622",
        "tgn:7005685",
        "tgn:1000001",
        "tgn:7005805",
        "tgn:7029392"
    ],
    "tgn:id":1118622,
    "tgn:name":"Wakaw Lake",
    "tgn:placetype":[
        "aat:300008680"
    ]
},
  "bbox": [],
  "geometry": {"coordinates":[-105.5833,52.6667],"type":"Point"}
}