{
  "id": 2578948,
  "type": "Feature",
  "properties": {
    "tgn:hierarchy":[
        "tgn:2578948",
        "tgn:1000001",
        "tgn:7012149",
        "tgn:2002167",
        "tgn:7007919",
        "tgn:7029392"
    ],
    "tgn:id":2578948,
    "tgn:name":"Philpott Lake",
    "tgn:placetype":[
        "aat:300006191"
    ]
},
  "bbox": [],
  "geometry": {"coordinates":[-80.0167,36.7833],"type":"Point"}
}