{
  "id": 2451640,
  "type": "Feature",
  "properties": {
    "tgn:hierarchy":[
        "tgn:2451640",
        "tgn:1000001",
        "tgn:7012149",
        "tgn:7007708",
        "tgn:7029392"
    ],
    "tgn:id":2451640,
    "tgn:name":"Little Bear Creek",
    "tgn:placetype":[
        "aat:300008706"
    ]
},
  "bbox": [],
  "geometry": {"coordinates":[-120.6667,42.65],"type":"Point"}
}