{
  "id": 2430942,
  "type": "Feature",
  "properties": {
    "tgn:hierarchy":[
        "tgn:2430942",
        "tgn:7030516",
        "tgn:7006450",
        "tgn:1000001",
        "tgn:7012149",
        "tgn:7029392"
    ],
    "tgn:id":2430942,
    "tgn:name":"Kanaton Ridge",
    "tgn:placetype":[
        "aat:300266640"
    ]
},
  "bbox": [],
  "geometry": {"coordinates":[-177.1333,51.8833],"type":"Point"}
}