{
  "id": 7462227,
  "type": "Feature",
  "properties": {
    "tgn:hierarchy":[
        "tgn:7462227",
        "tgn:7002444",
        "tgn:1000003",
        "tgn:7008082",
        "tgn:7008591",
        "tgn:7029392"
    ],
    "tgn:id":7462227,
    "tgn:name:en":"Invercannich",
    "tgn:placetype":[
        "aat:300008347"
    ]
},
  "bbox": [],
  "geometry": {"coordinates":[-4.733333,57.35],"type":"Point"}
}