{
  "id": 7234708,
  "type": "Feature",
  "properties": {
    "tgn:hierarchy":[
        "tgn:7234708",
        "tgn:7002681",
        "tgn:7001395",
        "tgn:1000003",
        "tgn:1000074",
        "tgn:7029392"
    ],
    "tgn:id":7234708,
    "tgn:name":"Dam\u00e1ri, \u00c1kra",
    "tgn:placetype":[
        "aat:300008850"
    ]
},
  "bbox": [],
  "geometry": {"coordinates":[23.35,37.35],"type":"Point"}
}