{
  "id": 2553820,
  "type": "Feature",
  "properties": {
    "tgn:hierarchy":[
        "tgn:2553820",
        "tgn:1000001",
        "tgn:7012149",
        "tgn:1003042",
        "tgn:7007920",
        "tgn:7029392"
    ],
    "tgn:id":2553820,
    "tgn:name":"Oak Hill",
    "tgn:placetype":[
        "aat:300008798"
    ]
},
  "bbox": [],
  "geometry": {"coordinates":[-121.1167,46.1167],"type":"Point"}
}