{
  "id": 7570371,
  "type": "Feature",
  "properties": {
    "tgn:hierarchy":[
        "tgn:7570371",
        "tgn:1000004",
        "tgn:7000198",
        "tgn:7016788",
        "tgn:7029392"
    ],
    "tgn:id":7570371,
    "tgn:name:en":"B\u0101mol\u0101ya",
    "tgn:placetype":[
        "aat:300008347"
    ]
},
  "bbox": [],
  "geometry": {"coordinates":[75.660544,25.826947],"type":"Point"}
}