{
  "id": 2580908,
  "type": "Feature",
  "properties": {
    "tgn:hierarchy":[
        "tgn:2580908",
        "tgn:1000001",
        "tgn:7012149",
        "tgn:1002392",
        "tgn:7007157",
        "tgn:7029392"
    ],
    "tgn:id":2580908,
    "tgn:name":"Pika Lake",
    "tgn:placetype":[
        "aat:300008680"
    ]
},
  "bbox": [],
  "geometry": {"coordinates":[-118.95,37.55],"type":"Point"}
}