{
  "id": 7388760,
  "type": "Feature",
  "properties": {
    "tgn:hierarchy":[
        "tgn:7388760",
        "tgn:1000001",
        "tgn:1001960",
        "tgn:7005560",
        "tgn:7029392"
    ],
    "tgn:id":7388760,
    "tgn:name":"Pozo Coyote",
    "tgn:placetype":[
        "aat:300000206",
        "aat:300386984"
    ]
},
  "bbox": [],
  "geometry": {"coordinates":[-112.35,29.616667],"type":"Point"}
}