<<<<<<< HEAD
{
  "id": 7473656,
  "type": "Feature",
  "properties": {
    "tgn:hierarchy":[
        "tgn:7473656",
        "tgn:1000004",
        "tgn:7001009",
        "tgn:1000141",
        "tgn:7029392"
    ],
    "tgn:id":7473656,
    "tgn:name":"Yingbu Cun",
    "tgn:placetype":[
        "aat:300387200"
    ]
},
  "bbox": [],
  "geometry": {"coordinates":[120.553983,24.123561],"type":"Point"}
}
=======
{"geometry":{"type":"Point","coordinates":[120.553983,24.123561]},"type":"Feature","properties":{"hierarchy":["tgn:7473656","tgn:1000004","tgn:7001009","tgn:1000141","tgn:7029392"],"placetype":["aat:300387200"],"id":7473656,"name:xx":"Yingbu Cun"}}
>>>>>>> 03f74aca74312dbeaf24d7e61306dd6a786dc3d0
