{
  "id": 7473656,
  "type": "Feature",
  "properties": {
    "tgn:hierarchy":[
        "tgn:7473656",
        "tgn:1000004",
        "tgn:7001009",
        "tgn:1000141",
        "tgn:7029392"
    ],
    "tgn:id":7473656,
    "tgn:name":"Yingbu Cun",
    "tgn:placetype":[
        "aat:300387200"
    ]
},
  "bbox": [],
  "geometry": {"coordinates":[120.553983,24.123561],"type":"Point"}
}