{
  "id": 2115297,
  "type": "Feature",
  "properties": {
    "tgn:hierarchy":[
        "tgn:2115297",
        "tgn:1000001",
        "tgn:7012149",
        "tgn:1002521",
        "tgn:7007920",
        "tgn:7029392"
    ],
    "tgn:id":2115297,
    "tgn:name":"Beaver Valley",
    "tgn:placetype":[
        "aat:300008347",
        "aat:300387210"
    ]
},
  "bbox": [],
  "geometry": {"coordinates":[-122.7167,47.9167],"type":"Point"}
}