{
  "id": 7471270,
  "type": "Feature",
  "properties": {
    "tgn:hierarchy":[
        "tgn:7471270",
        "tgn:1000004",
        "tgn:1000959",
        "tgn:1000141",
        "tgn:7029392"
    ],
    "tgn:id":7471270,
    "tgn:name":"Houshankeng",
    "tgn:placetype":[
        "aat:300008347"
    ]
},
  "bbox": [],
  "geometry": {"coordinates":[121.595795,24.9924],"type":"Point"}
}