{
  "id": 2174186,
  "type": "Feature",
  "properties": {
    "tgn:hierarchy":[
        "tgn:2174186",
        "tgn:1000001",
        "tgn:2001266",
        "tgn:7012149",
        "tgn:7007524",
        "tgn:7029392"
    ],
    "tgn:id":2174186,
    "tgn:name":"Birdtail Butte",
    "tgn:placetype":[
        "aat:300008798"
    ]
},
  "bbox": [],
  "geometry": {"coordinates":[-111.95,47.3333],"type":"Point"}
}