{
  "id": 1085781,
  "type": "Feature",
  "properties": {
    "tgn:hierarchy":[
        "tgn:1085781",
        "tgn:1001053",
        "tgn:1000004",
        "tgn:7018451",
        "tgn:1000144",
        "tgn:7029392"
    ],
    "tgn:id":1085781,
    "tgn:name":"\u00c7andarl\u0131",
    "tgn:placetype":[
        "aat:300008347"
    ]
},
  "bbox": [],
  "geometry": {"coordinates":[26.95,38.9333],"type":"Point"}
}