{
  "id": 2065246,
  "type": "Feature",
  "properties": {
    "tgn:hierarchy":[
        "tgn:2065246",
        "tgn:2065243",
        "tgn:1000001",
        "tgn:1002360",
        "tgn:7012149",
        "tgn:7007565",
        "tgn:7029392"
    ],
    "tgn:id":2065246,
    "tgn:name":"Morehousetown",
    "tgn:placetype":[
        "aat:300000745"
    ]
},
  "bbox": [],
  "geometry": {"coordinates":[-74.3333,40.7833],"type":"Point"}
}