{
  "id": 7478254,
  "type": "Feature",
  "properties": {
    "tgn:hierarchy":[
        "tgn:7478254",
        "tgn:1000004",
        "tgn:7001014",
        "tgn:1000141",
        "tgn:7029392"
    ],
    "tgn:id":7478254,
    "tgn:name":"Dingyouche Qiao",
    "tgn:placetype":[
        "aat:300007836"
    ]
},
  "bbox": [],
  "geometry": {"coordinates":[120.537459,23.750552],"type":"Point"}
}