{
  "id": 2349126,
  "type": "Feature",
  "properties": {
    "tgn:hierarchy":[
        "tgn:2349126",
        "tgn:1000001",
        "tgn:7012149",
        "tgn:2000792",
        "tgn:7007255",
        "tgn:7029392"
    ],
    "tgn:id":2349126,
    "tgn:name":"Gilbert Creek",
    "tgn:placetype":[
        "aat:300008706"
    ]
},
  "bbox": [],
  "geometry": {"coordinates":[-88.7167,36.8167],"type":"Point"}
}