{
  "id": 7353866,
  "type": "Feature",
  "properties": {
    "tgn:hierarchy":[
        "tgn:7353866",
        "tgn:7005581",
        "tgn:1000001",
        "tgn:7005560",
        "tgn:7029392"
    ],
    "tgn:id":7353866,
    "tgn:name":"Babanori",
    "tgn:placetype":[
        "aat:300008347"
    ]
},
  "bbox": [],
  "geometry": {"coordinates":[-108.883333,28.116667],"type":"Point"}
}