<<<<<<< HEAD
{
  "id": 2259652,
  "type": "Feature",
  "properties": {
    "tgn:hierarchy":[
        "tgn:2259652",
        "tgn:1000001",
        "tgn:7012149",
        "tgn:7007157",
        "tgn:1002608",
        "tgn:7029392"
    ],
    "tgn:id":2259652,
    "tgn:name":"Cougar Canyon",
    "tgn:placetype":[
        "aat:300008761"
    ]
},
  "bbox": [],
  "geometry": {"coordinates":[-118.4,34.3333],"type":"Point"}
}
=======
{"geometry":{"type":"Point","coordinates":[-118.400000,34.333300]},"type":"Feature","properties":{"hierarchy":["tgn:2259652","tgn:1000001","tgn:7012149","tgn:7007157","tgn:1002608","tgn:7029392"],"placetype":["aat:300008761"],"id":2259652,"name:xx":"Cougar Canyon"}}
>>>>>>> 03f74aca74312dbeaf24d7e61306dd6a786dc3d0
