{
  "id": 7489614,
  "type": "Feature",
  "properties": {
    "tgn:hierarchy":[
        "tgn:7489614",
        "tgn:1000004",
        "tgn:7490934",
        "tgn:1000141",
        "tgn:7029392"
    ],
    "tgn:id":7489614,
    "tgn:name":"Cailiao",
    "tgn:placetype":[
        "aat:300008347"
    ]
},
  "bbox": [],
  "geometry": {"coordinates":[120.435278,22.996944],"type":"Point"}
}