<<<<<<< HEAD
{
  "id": 7489614,
  "type": "Feature",
  "properties": {
    "tgn:hierarchy":[
        "tgn:7489614",
        "tgn:1000004",
        "tgn:7490934",
        "tgn:1000141",
        "tgn:7029392"
    ],
    "tgn:id":7489614,
    "tgn:name":"Cailiao",
    "tgn:placetype":[
        "aat:300008347"
    ]
},
  "bbox": [],
  "geometry": {"coordinates":[120.435278,22.996944],"type":"Point"}
}
=======
{"geometry":{"type":"Point","coordinates":[120.435278,22.996944]},"type":"Feature","properties":{"hierarchy":["tgn:7489614","tgn:1000004","tgn:7490934","tgn:1000141","tgn:7029392"],"placetype":["aat:300008347"],"id":7489614,"name:xx":"Cailiao"}}
>>>>>>> 03f74aca74312dbeaf24d7e61306dd6a786dc3d0
