{
  "id": 7316343,
  "type": "Feature",
  "properties": {
    "tgn:hierarchy":[
        "tgn:7316343",
        "tgn:1001768",
        "tgn:1000049",
        "tgn:1000002",
        "tgn:7029392"
    ],
    "tgn:id":7316343,
    "tgn:name":"Casuto",
    "tgn:placetype":[
        "aat:300387200"
    ]
},
  "bbox": [],
  "geometry": {"coordinates":[-71.15,-32.65],"type":"Point"}
}