{
  "id": 7147741,
  "type": "Feature",
  "properties": {
    "tgn:hierarchy":[
        "tgn:7147741",
        "tgn:7003669",
        "tgn:1000003",
        "tgn:7000084",
        "tgn:7029392"
    ],
    "tgn:id":7147741,
    "tgn:name":"Kuchlhof",
    "tgn:placetype":[
        "aat:300000206"
    ]
},
  "bbox": [],
  "geometry": {"coordinates":[12.533333,49.066667],"type":"Point"}
}