{
  "id": 2309236,
  "type": "Feature",
  "properties": {
    "tgn:hierarchy":[
        "tgn:2309236",
        "tgn:1000001",
        "tgn:7016172",
        "tgn:7012149",
        "tgn:2000179",
        "tgn:7029392"
    ],
    "tgn:id":2309236,
    "tgn:name":"East Spiller Creek",
    "tgn:placetype":[
        "aat:300008706"
    ]
},
  "bbox": [],
  "geometry": {"coordinates":[-93.65,34.8167],"type":"Point"}
}