{
  "id": 7188910,
  "type": "Feature",
  "properties": {
    "tgn:hierarchy":[
        "tgn:7188910",
        "tgn:7003692",
        "tgn:1000003",
        "tgn:7000084",
        "tgn:7029392"
    ],
    "tgn:id":7188910,
    "tgn:name":"Espan",
    "tgn:placetype":[
        "aat:300000206"
    ]
},
  "bbox": [],
  "geometry": {"coordinates":[8.283333,47.85],"type":"Point"}
}