{
  "id": 2270679,
  "type": "Feature",
  "properties": {
    "tgn:hierarchy":[
        "tgn:2270679",
        "tgn:1000001",
        "tgn:7012149",
        "tgn:2000475",
        "tgn:7007250",
        "tgn:7029392"
    ],
    "tgn:id":2270679,
    "tgn:name":"Crystal Springs",
    "tgn:placetype":[
        "aat:300008697"
    ]
},
  "bbox": [],
  "geometry": {"coordinates":[-114.6333,42.65],"type":"Point"}
}