{
  "id": 7262411,
  "type": "Feature",
  "properties": {
    "tgn:hierarchy":[
        "tgn:7262411",
        "tgn:7003619",
        "tgn:1000003",
        "tgn:7016845",
        "tgn:7029392"
    ],
    "tgn:id":7262411,
    "tgn:name:nl":"Broekdijkerbeek",
    "tgn:placetype":[
        "aat:300008699"
    ]
},
  "bbox": [],
  "geometry": {"coordinates":[5.85,52.433333],"type":"Point"}
}