{
  "id": 7541049,
  "type": "Feature",
  "properties": {
    "tgn:hierarchy":[
        "tgn:7541049",
        "tgn:7001242",
        "tgn:7016833",
        "tgn:1001092",
        "tgn:7029392"
    ],
    "tgn:id":7541049,
    "tgn:name":"Man\u0163\u012b",
    "tgn:placetype":[
        "aat:300008347"
    ]
},
  "bbox": [],
  "geometry": {"coordinates":[31.247141,30.143267],"type":"Point"}
}