{
  "id": 2413234,
  "type": "Feature",
  "properties": {
    "tgn:hierarchy":[
        "tgn:2413234",
        "tgn:1000001",
        "tgn:7012149",
        "tgn:2001710",
        "tgn:7007708",
        "tgn:7029392"
    ],
    "tgn:id":2413234,
    "tgn:name":"Inspiration Point",
    "tgn:placetype":[
        "aat:300266640"
    ]
},
  "bbox": [],
  "geometry": {"coordinates":[-121.6333,45.4167],"type":"Point"}
}