{
  "id": 2592112,
  "type": "Feature",
  "properties": {
    "tgn:hierarchy":[
        "tgn:2592112",
        "tgn:1000001",
        "tgn:7006451",
        "tgn:7012149",
        "tgn:2000100",
        "tgn:7029392"
    ],
    "tgn:id":2592112,
    "tgn:name":"Pontatoc Ridge",
    "tgn:placetype":[
        "aat:300266640"
    ]
},
  "bbox": [],
  "geometry": {"coordinates":[-110.8833,32.3333],"type":"Point"}
}