{
  "id": 7314715,
  "type": "Feature",
  "properties": {
    "tgn:hierarchy":[
        "tgn:7314715",
        "tgn:1001657",
        "tgn:1000049",
        "tgn:1000002",
        "tgn:7029392"
    ],
    "tgn:id":7314715,
    "tgn:name":"Limar\u00ed Sur, Punta",
    "tgn:placetype":[
        "aat:300386846"
    ]
},
  "bbox": [],
  "geometry": {"coordinates":[-71.700833,-30.733889],"type":"Point"}
}