{
  "id": 2524466,
  "type": "Feature",
  "properties": {
    "tgn:hierarchy":[
        "tgn:2524466",
        "tgn:1000001",
        "tgn:7012149",
        "tgn:2000406",
        "tgn:7007248",
        "tgn:7029392"
    ],
    "tgn:id":2524466,
    "tgn:name":"Morgan Valley",
    "tgn:placetype":[
        "aat:300008761"
    ]
},
  "bbox": [],
  "geometry": {"coordinates":[-85.1667,33.9333],"type":"Point"}
}