<<<<<<< HEAD
{
  "id": 2332299,
  "type": "Feature",
  "properties": {
    "tgn:hierarchy":[
        "tgn:2332299",
        "tgn:1000001",
        "tgn:7012149",
        "tgn:2001307",
        "tgn:7007524",
        "tgn:7029392"
    ],
    "tgn:id":2332299,
    "tgn:name":"Flood Creek",
    "tgn:placetype":[
        "aat:300008706"
    ]
},
  "bbox": [],
  "geometry": {"coordinates":[-110.05,45.25],"type":"Point"}
}
=======
{"geometry":{"type":"Point","coordinates":[-110.050000,45.250000]},"type":"Feature","properties":{"hierarchy":["tgn:2332299","tgn:1000001","tgn:7012149","tgn:2001307","tgn:7007524","tgn:7029392"],"placetype":["aat:300008706"],"id":2332299,"name:xx":"Flood Creek"}}
>>>>>>> 03f74aca74312dbeaf24d7e61306dd6a786dc3d0
