{
  "id": 7070665,
  "type": "Feature",
  "properties": {
    "tgn:hierarchy":[
        "tgn:7070665",
        "tgn:7003692",
        "tgn:1000003",
        "tgn:7000084",
        "tgn:7029392"
    ],
    "tgn:id":7070665,
    "tgn:name":"Steinenbach",
    "tgn:placetype":[
        "aat:300008347"
    ]
},
  "bbox": [],
  "geometry": {"coordinates":[9.683333,47.633333],"type":"Point"}
}