{
  "id": 7016126,
  "type": "Feature",
  "properties": {
    "tgn:hierarchy":[
        "tgn:7016126",
        "tgn:7006450",
        "tgn:1000001",
        "tgn:7012149",
        "tgn:2000082",
        "tgn:7019648",
        "tgn:7029392"
    ],
    "tgn:id":7016126,
    "tgn:name":"Klawock",
    "tgn:placetype":[
        "aat:300008347"
    ]
},
  "bbox": [],
  "geometry": {"coordinates":[-133.0833,55.55],"type":"Point"}
}