{
  "id": 7240207,
  "type": "Feature",
  "properties": {
    "tgn:hierarchy":[
        "tgn:7240207",
        "tgn:7003457",
        "tgn:1000003",
        "tgn:1000063",
        "tgn:7018236",
        "tgn:7029392"
    ],
    "tgn:id":7240207,
    "tgn:name":"Eiksken",
    "tgn:placetype":[
        "aat:300008347"
    ]
},
  "bbox": [],
  "geometry": {"coordinates":[3.646434,51.12999],"type":"Point"}
}