{
  "id": 2680676,
  "type": "Feature",
  "properties": {
    "tgn:hierarchy":[
        "tgn:2680676",
        "tgn:1000001",
        "tgn:1002259",
        "tgn:7012149",
        "tgn:7007568",
        "tgn:7029392"
    ],
    "tgn:id":2680676,
    "tgn:name":"South Hill",
    "tgn:placetype":[
        "aat:300008798"
    ]
},
  "bbox": [],
  "geometry": {"coordinates":[-79.15,42.3167],"type":"Point"}
}