{
  "id": 7237404,
  "type": "Feature",
  "properties": {
    "tgn:hierarchy":[
        "tgn:7237404",
        "tgn:7011369",
        "tgn:7017076",
        "tgn:1000003",
        "tgn:1000074",
        "tgn:7029392"
    ],
    "tgn:id":7237404,
    "tgn:name":"Ammoudher\u00f3n",
    "tgn:placetype":[
        "aat:300008347"
    ]
},
  "bbox": [],
  "geometry": {"coordinates":[21.833333,37.116667],"type":"Point"}
}