{
  "id": 2439584,
  "type": "Feature",
  "properties": {
    "tgn:hierarchy":[
        "tgn:2439584",
        "tgn:1000001",
        "tgn:7012149",
        "tgn:2002188",
        "tgn:7007919",
        "tgn:7029392"
    ],
    "tgn:id":2439584,
    "tgn:name":"Kisers Cave",
    "tgn:placetype":[
        "aat:300008746"
    ]
},
  "bbox": [],
  "geometry": {"coordinates":[-82.3333,36.85],"type":"Point"}
}