{
  "id": 2358567,
  "type": "Feature",
  "properties": {
    "tgn:hierarchy":[
        "tgn:2358567",
        "tgn:1000001",
        "tgn:2001429",
        "tgn:7012149",
        "tgn:7007566",
        "tgn:7029392"
    ],
    "tgn:id":2358567,
    "tgn:name":"Grande, Arroyo",
    "tgn:placetype":[
        "aat:300008699"
    ]
},
  "bbox": [],
  "geometry": {"coordinates":[-108.8833,34.0167],"type":"Point"}
}