{
  "id": 2010426,
  "type": "Feature",
  "properties": {
    "tgn:hierarchy":[
        "tgn:2010426",
        "tgn:1000001",
        "tgn:7012149",
        "tgn:7007157",
        "tgn:1002861",
        "tgn:7029392"
    ],
    "tgn:id":2010426,
    "tgn:name":"Burnham",
    "tgn:placetype":[
        "aat:300387016"
    ]
},
  "bbox": [],
  "geometry": {"coordinates":[-121.1333,37.8833],"type":"Point"}
}