{
  "id": 1011578,
  "type": "Feature",
  "properties": {
    "tgn:hierarchy":[
        "tgn:1011578",
        "tgn:1001836",
        "tgn:1000001",
        "tgn:7005560",
        "tgn:7029392"
    ],
    "tgn:id":1011578,
    "tgn:name":"Arena de la Ventana, Punta",
    "tgn:placetype":[
        "aat:300386846"
    ]
},
  "bbox": [],
  "geometry": {"coordinates":[-109.866667,24.066667],"type":"Point"}
}