{
  "id": 2584370,
  "type": "Feature",
  "properties": {
    "tgn:hierarchy":[
        "tgn:2584370",
        "tgn:1000001",
        "tgn:7012149",
        "tgn:2000234",
        "tgn:7007158",
        "tgn:7029392"
    ],
    "tgn:id":2584370,
    "tgn:name":"Piney Creek",
    "tgn:placetype":[
        "aat:300008706"
    ]
},
  "bbox": [],
  "geometry": {"coordinates":[-108.1667,38.35],"type":"Point"}
}