{
  "id": 2305222,
  "type": "Feature",
  "properties": {
    "tgn:hierarchy":[
        "tgn:2305222",
        "tgn:1000001",
        "tgn:7012149",
        "tgn:1002815",
        "tgn:7007922",
        "tgn:7029392"
    ],
    "tgn:id":2305222,
    "tgn:name":"East Branch Root River Canal",
    "tgn:placetype":[
        "aat:300006075"
    ]
},
  "bbox": [],
  "geometry": {"coordinates":[-87.9667,42.7167],"type":"Point"}
}