{
  "id": 7465719,
  "type": "Feature",
  "properties": {
    "tgn:hierarchy":[
        "tgn:7465719",
        "tgn:7002445",
        "tgn:1000003",
        "tgn:7008117",
        "tgn:7008591",
        "tgn:7029392"
    ],
    "tgn:id":7465719,
    "tgn:name:en":"Bassenthwaite Lake Station",
    "tgn:placetype":[
        "aat:300007783"
    ]
},
  "bbox": [],
  "geometry": {"coordinates":[-3.233333,54.666667],"type":"Point"}
}