{
  "id": 2353416,
  "type": "Feature",
  "properties": {
    "tgn:hierarchy":[
        "tgn:2353416",
        "tgn:1000001",
        "tgn:7012149",
        "tgn:1002742",
        "tgn:7007920",
        "tgn:7029392"
    ],
    "tgn:id":2353416,
    "tgn:name":"Gold Creek",
    "tgn:placetype":[
        "aat:300008706"
    ]
},
  "bbox": [],
  "geometry": {"coordinates":[-120.15,48.1833],"type":"Point"}
}