{
  "id": 2260126,
  "type": "Feature",
  "properties": {
    "tgn:hierarchy":[
        "tgn:2260126",
        "tgn:1000001",
        "tgn:7012149",
        "tgn:2001959",
        "tgn:7007826",
        "tgn:7029392"
    ],
    "tgn:id":2260126,
    "tgn:name":"Country Club Lake",
    "tgn:placetype":[
        "aat:300006191"
    ]
},
  "bbox": [],
  "geometry": {"coordinates":[-99.45,31.7667],"type":"Point"}
}