{
  "id": 2737890,
  "type": "Feature",
  "properties": {
    "tgn:hierarchy":[
        "tgn:2737890",
        "tgn:1000001",
        "tgn:7006451",
        "tgn:7012149",
        "tgn:2000097",
        "tgn:7029392"
    ],
    "tgn:id":2737890,
    "tgn:name":"U S Tank",
    "tgn:placetype":[
        "aat:300006191"
    ]
},
  "bbox": [],
  "geometry": {"coordinates":[-113.0167,33.7333],"type":"Point"}
}