{
  "id": 7567734,
  "type": "Feature",
  "properties": {
    "tgn:hierarchy":[
        "tgn:7567734",
        "tgn:1001828",
        "tgn:1000004",
        "tgn:7000198",
        "tgn:7029392"
    ],
    "tgn:id":7567734,
    "tgn:name:en":"Ratnapur",
    "tgn:placetype":[
        "aat:300008347"
    ]
},
  "bbox": [],
  "geometry": {"coordinates":[78.344167,17.825833],"type":"Point"}
}