{
  "id": 7351198,
  "type": "Feature",
  "properties": {
    "tgn:hierarchy":[
        "tgn:7351198",
        "tgn:1000001",
        "tgn:1001960",
        "tgn:7005560",
        "tgn:7029392"
    ],
    "tgn:id":7351198,
    "tgn:name":"Bocana, Cerro",
    "tgn:placetype":[
        "aat:300008795"
    ]
},
  "bbox": [],
  "geometry": {"coordinates":[-111.45,28.366667],"type":"Point"}
}