<<<<<<< HEAD
{
  "id": 7351198,
  "type": "Feature",
  "properties": {
    "tgn:hierarchy":[
        "tgn:7351198",
        "tgn:1000001",
        "tgn:1001960",
        "tgn:7005560",
        "tgn:7029392"
    ],
    "tgn:id":7351198,
    "tgn:name":"Bocana, Cerro",
    "tgn:placetype":[
        "aat:300008795"
    ]
},
  "bbox": [],
  "geometry": {"coordinates":[-111.45,28.366667],"type":"Point"}
}
=======
{"geometry":{"type":"Point","coordinates":[-111.450000,28.366667]},"type":"Feature","properties":{"hierarchy":["tgn:7351198","tgn:1000001","tgn:1001960","tgn:7005560","tgn:7029392"],"placetype":["aat:300008795"],"id":7351198,"name:xx":"Bocana, Cerro"}}
>>>>>>> 03f74aca74312dbeaf24d7e61306dd6a786dc3d0
