{
  "id": 1057733,
  "type": "Feature",
  "properties": {
    "tgn:hierarchy":[
        "tgn:1057733",
        "tgn:1003351",
        "tgn:1000004",
        "tgn:7018214",
        "tgn:7002435",
        "tgn:7029392"
    ],
    "tgn:id":1057733,
    "tgn:name":"Novopavlovskoye",
    "tgn:placetype":[
        "aat:300008347"
    ]
},
  "bbox": [],
  "geometry": {"coordinates":[111.5833,50.9833],"type":"Point"}
}