{
  "id": 2456555,
  "type": "Feature",
  "properties": {
    "tgn:hierarchy":[
        "tgn:2456555",
        "tgn:1000001",
        "tgn:7012149",
        "tgn:2000930",
        "tgn:7007515",
        "tgn:7029392"
    ],
    "tgn:id":2456555,
    "tgn:name":"Little Indian Stream",
    "tgn:placetype":[
        "aat:300008699"
    ]
},
  "bbox": [],
  "geometry": {"coordinates":[-69.8167,45.4167],"type":"Point"}
}