{
  "id": 7131793,
  "type": "Feature",
  "properties": {
    "tgn:hierarchy":[
        "tgn:7131793",
        "tgn:7003669",
        "tgn:1000003",
        "tgn:7000084",
        "tgn:7029392"
    ],
    "tgn:id":7131793,
    "tgn:name":"Mittel Berg",
    "tgn:placetype":[
        "aat:300008777"
    ]
},
  "bbox": [],
  "geometry": {"coordinates":[11.533333,50.166667],"type":"Point"}
}