{
  "id": 2455331,
  "type": "Feature",
  "properties": {
    "tgn:hierarchy":[
        "tgn:2455331",
        "tgn:1000001",
        "tgn:7012149",
        "tgn:1002629",
        "tgn:7007523",
        "tgn:7029392"
    ],
    "tgn:id":2455331,
    "tgn:name":"Little Fly Creek",
    "tgn:placetype":[
        "aat:300008706"
    ]
},
  "bbox": [],
  "geometry": {"coordinates":[-91.9833,38.1167],"type":"Point"}
}