{
  "id": 7181737,
  "type": "Feature",
  "properties": {
    "tgn:hierarchy":[
        "tgn:7181737",
        "tgn:7003669",
        "tgn:1000003",
        "tgn:7000084",
        "tgn:7029392"
    ],
    "tgn:id":7181737,
    "tgn:name":"Gabersberg",
    "tgn:placetype":[
        "aat:300008777"
    ]
},
  "bbox": [],
  "geometry": {"coordinates":[10.483333,49.65],"type":"Point"}
}