{
  "id": 7386008,
  "type": "Feature",
  "properties": {
    "tgn:hierarchy":[
        "tgn:7386008",
        "tgn:7005581",
        "tgn:1000001",
        "tgn:7005560",
        "tgn:7029392"
    ],
    "tgn:id":7386008,
    "tgn:name":"Prieta, Laguna",
    "tgn:placetype":[
        "aat:300387087"
    ]
},
  "bbox": [],
  "geometry": {"coordinates":[-107.733333,30.366667],"type":"Point"}
}