{
  "id": 2613418,
  "type": "Feature",
  "properties": {
    "tgn:hierarchy":[
        "tgn:2613418",
        "tgn:1000001",
        "tgn:7012149",
        "tgn:2000483",
        "tgn:7007250",
        "tgn:7029392"
    ],
    "tgn:id":2613418,
    "tgn:name":"Reed Lake",
    "tgn:placetype":[
        "aat:300008680"
    ]
},
  "bbox": [],
  "geometry": {"coordinates":[-114.0667,42.85],"type":"Point"}
}