<<<<<<< HEAD
{
  "id": 7481580,
  "type": "Feature",
  "properties": {
    "tgn:hierarchy":[
        "tgn:7481580",
        "tgn:7487020",
        "tgn:1000004",
        "tgn:1000141",
        "tgn:7029392"
    ],
    "tgn:id":7481580,
    "tgn:name":"Daxue Shan Beifeng",
    "tgn:placetype":[
        "aat:300008798"
    ]
},
  "bbox": [],
  "geometry": {"coordinates":[121.124722,24.341944],"type":"Point"}
}
=======
{"geometry":{"type":"Point","coordinates":[121.124722,24.341944]},"type":"Feature","properties":{"hierarchy":["tgn:7481580","tgn:7487020","tgn:1000004","tgn:1000141","tgn:7029392"],"placetype":["aat:300008798"],"id":7481580,"name:xx":"Daxue Shan Beifeng"}}
>>>>>>> 03f74aca74312dbeaf24d7e61306dd6a786dc3d0
