{
  "id": 2584472,
  "type": "Feature",
  "properties": {
    "tgn:hierarchy":[
        "tgn:2584472",
        "tgn:1000001",
        "tgn:1002410",
        "tgn:7012149",
        "tgn:7007565",
        "tgn:7029392"
    ],
    "tgn:id":2584472,
    "tgn:name":"Piney Hollow",
    "tgn:placetype":[
        "aat:300008347"
    ]
},
  "bbox": [],
  "geometry": {"coordinates":[-74.9167,39.5833],"type":"Point"}
}