{
  "id": 1021239,
  "type": "Feature",
  "properties": {
    "tgn:hierarchy":[
        "tgn:1021239",
        "tgn:7006237",
        "tgn:1000047",
        "tgn:7002457",
        "tgn:1000002",
        "tgn:7029392"
    ],
    "tgn:id":1021239,
    "tgn:name":"Coronel Murta",
    "tgn:placetype":[
        "aat:300008347"
    ]
},
  "bbox": [],
  "geometry": {"coordinates":[-42.1833,-16.6167],"type":"Point"}
}