{
  "id": 7557649,
  "type": "Feature",
  "properties": {
    "tgn:hierarchy":[
        "tgn:7557649",
        "tgn:1000004",
        "tgn:7018318",
        "tgn:7000198",
        "tgn:7029392"
    ],
    "tgn:id":7557649,
    "tgn:name:en":"Pomburpa",
    "tgn:placetype":[
        "aat:300008347"
    ]
},
  "bbox": [],
  "geometry": {"coordinates":[73.85,15.55],"type":"Point"}
}