{
  "id": 2697085,
  "type": "Feature",
  "properties": {
    "tgn:hierarchy":[
        "tgn:2697085",
        "tgn:1002201",
        "tgn:1000001",
        "tgn:7012149",
        "tgn:7007517",
        "tgn:7029392"
    ],
    "tgn:id":2697085,
    "tgn:name":"Stony Brook",
    "tgn:placetype":[
        "aat:300008699"
    ]
},
  "bbox": [],
  "geometry": {"coordinates":[-71.1333,41.6167],"type":"Point"}
}