{
  "id": 1105250,
  "type": "Feature",
  "properties": {
    "tgn:hierarchy":[
        "tgn:1105250",
        "tgn:7002444",
        "tgn:1000003",
        "tgn:7008082",
        "tgn:7008591",
        "tgn:7029392"
    ],
    "tgn:id":1105250,
    "tgn:name:en":"Klibreck, Ben",
    "tgn:placetype":[
        "aat:300008795"
    ]
},
  "bbox": [],
  "geometry": {"coordinates":[-4.366667,58.233333],"type":"Point"}
}