{
  "id": 2330160,
  "type": "Feature",
  "properties": {
    "tgn:hierarchy":[
        "tgn:2330160",
        "tgn:1000001",
        "tgn:7012149",
        "tgn:2002359",
        "tgn:7007922",
        "tgn:7029392"
    ],
    "tgn:id":2330160,
    "tgn:name":"Flambeau Lake",
    "tgn:placetype":[
        "aat:300008680"
    ]
},
  "bbox": [],
  "geometry": {"coordinates":[-89.9167,45.95],"type":"Point"}
}