{
  "id": 2506029,
  "type": "Feature",
  "properties": {
    "tgn:hierarchy":[
        "tgn:2506029",
        "tgn:1000001",
        "tgn:7012149",
        "tgn:2001854",
        "tgn:7007825",
        "tgn:7029392"
    ],
    "tgn:id":2506029,
    "tgn:name":"Meridian",
    "tgn:placetype":[
        "aat:300008347"
    ]
},
  "bbox": [],
  "geometry": {"coordinates":[-84.9167,35.8833],"type":"Point"}
}