{
  "id": 1008557,
  "type": "Feature",
  "properties": {
    "tgn:hierarchy":[
        "tgn:1008557",
        "tgn:1000001",
        "tgn:7012149",
        "tgn:7006050",
        "tgn:7029392"
    ],
    "tgn:id":1008557,
    "tgn:name":"Peale Island",
    "tgn:placetype":[
        "aat:300008791"
    ]
},
  "bbox": [],
  "geometry": {"coordinates":[166.6333,19.3167],"type":"Point"}
}