{
  "id": 2570652,
  "type": "Feature",
  "properties": {
    "tgn:hierarchy":[
        "tgn:2570652",
        "tgn:1000001",
        "tgn:7012149",
        "tgn:2001284",
        "tgn:7007524",
        "tgn:7029392"
    ],
    "tgn:id":2570652,
    "tgn:name":"Patricks Basin",
    "tgn:placetype":[
        "aat:300386845"
    ]
},
  "bbox": [],
  "geometry": {"coordinates":[-112.8333,47.55],"type":"Point"}
}