{
  "id": 7540760,
  "type": "Feature",
  "properties": {
    "tgn:hierarchy":[
        "tgn:7540760",
        "tgn:7001242",
        "tgn:7016833",
        "tgn:1001335",
        "tgn:7029392"
    ],
    "tgn:id":7540760,
    "tgn:name":"Tur'at R\u0101ghib",
    "tgn:placetype":[
        "aat:300006075"
    ]
},
  "bbox": [],
  "geometry": {"coordinates":[31.138835,31.285387],"type":"Point"}
}