{
  "id": 7239349,
  "type": "Feature",
  "properties": {
    "tgn:hierarchy":[
        "tgn:7239349",
        "tgn:7003456",
        "tgn:1000003",
        "tgn:1000063",
        "tgn:7018236",
        "tgn:7029392"
    ],
    "tgn:id":7239349,
    "tgn:name":"Grote Bremelshoeve",
    "tgn:placetype":[
        "aat:300000206"
    ]
},
  "bbox": [],
  "geometry": {"coordinates":[5.033333,51.266667],"type":"Point"}
}