{
  "id": 7531497,
  "type": "Feature",
  "properties": {
    "tgn:hierarchy":[
        "tgn:7531497",
        "tgn:7001242",
        "tgn:7016833",
        "tgn:1001091",
        "tgn:7029392"
    ],
    "tgn:id":7531497,
    "tgn:name":"Al Masjid as \u015e\u016bf\u012b",
    "tgn:placetype":[
        "aat:300007544"
    ]
},
  "bbox": [],
  "geometry": {"coordinates":[31.278076,30.096634],"type":"Point"}
}