{
  "id": 7174588,
  "type": "Feature",
  "properties": {
    "tgn:hierarchy":[
        "tgn:7174588",
        "tgn:1000003",
        "tgn:7003689",
        "tgn:7000084",
        "tgn:7029392"
    ],
    "tgn:id":7174588,
    "tgn:name":"Gro\u00dfer Inselsberg",
    "tgn:placetype":[
        "aat:300387200"
    ]
},
  "bbox": [],
  "geometry": {"coordinates":[10.466667,50.85],"type":"Point"}
}