{
  "id": 2331196,
  "type": "Feature",
  "properties": {
    "tgn:hierarchy":[
        "tgn:2331196",
        "tgn:7006450",
        "tgn:2000069",
        "tgn:1000001",
        "tgn:7012149",
        "tgn:7029392"
    ],
    "tgn:id":2331196,
    "tgn:name":"Flat Top Mountain",
    "tgn:placetype":[
        "aat:300008798"
    ]
},
  "bbox": [],
  "geometry": {"coordinates":[-158.85,60.8833],"type":"Point"}
}