{
  "id": 7542525,
  "type": "Feature",
  "properties": {
    "tgn:hierarchy":[
        "tgn:7542525",
        "tgn:7001242",
        "tgn:7016833",
        "tgn:7001335",
        "tgn:7029392"
    ],
    "tgn:id":7542525,
    "tgn:name:en":"Khurayq, W\u0101d\u012b al",
    "tgn:placetype":[
        "aat:300379998"
    ]
},
  "bbox": [],
  "geometry": {"coordinates":[33.284444,30.695833],"type":"Point"}
}