{
  "id": 7568570,
  "type": "Feature",
  "properties": {
    "tgn:hierarchy":[
        "tgn:7568570",
        "tgn:1000004",
        "tgn:7000198",
        "tgn:1001996",
        "tgn:7029392"
    ],
    "tgn:id":7568570,
    "tgn:name:en":"Mandap",
    "tgn:placetype":[
        "aat:300008347"
    ]
},
  "bbox": [],
  "geometry": {"coordinates":[77.087778,31.171111],"type":"Point"}
}