{
  "id": 2011021,
  "type": "Feature",
  "properties": {
    "tgn:hierarchy":[
        "tgn:2011021",
        "tgn:1000001",
        "tgn:7012149",
        "tgn:7007157",
        "tgn:1002684",
        "tgn:7029392"
    ],
    "tgn:id":2011021,
    "tgn:name":"Del Rey Oaks",
    "tgn:placetype":[
        "aat:300008347"
    ]
},
  "bbox": [],
  "geometry": {"coordinates":[-121.8333,36.5833],"type":"Point"}
}