{
  "id": 7445574,
  "type": "Feature",
  "properties": {
    "tgn:hierarchy":[
        "tgn:7445574",
        "tgn:7019094",
        "tgn:7002444",
        "tgn:1000003",
        "tgn:7008591",
        "tgn:7029392"
    ],
    "tgn:id":7445574,
    "tgn:name:en":"Roan Bogha",
    "tgn:placetype":[
        "aat:300011692"
    ]
},
  "bbox": [],
  "geometry": {"coordinates":[-6.666667,56.55],"type":"Point"}
}