{
  "id": 2513247,
  "type": "Feature",
  "properties": {
    "tgn:hierarchy":[
        "tgn:2513247",
        "tgn:1000001",
        "tgn:2002102",
        "tgn:7012149",
        "tgn:7007827",
        "tgn:7029392"
    ],
    "tgn:id":2513247,
    "tgn:name":"Mill Ditch",
    "tgn:placetype":[
        "aat:300006075"
    ]
},
  "bbox": [],
  "geometry": {"coordinates":[-112.1833,41.65],"type":"Point"}
}