<<<<<<< HEAD
{
  "id": 7024059,
  "type": "Feature",
  "properties": {
    "tgn:hierarchy":[
        "tgn:7024059",
        "tgn:7017974",
        "tgn:1000004",
        "tgn:7006651",
        "tgn:7029392"
    ],
    "tgn:id":7024059,
    "tgn:name:en":"Gekhadzor",
    "tgn:placetype":[
        "aat:300008347"
    ]
},
  "bbox": [],
  "geometry": {"coordinates":[44.169,40.632],"type":"Point"}
}
=======
{"geometry":{"type":"Point","coordinates":[44.169000,40.632000]},"type":"Feature","properties":{"hierarchy":["tgn:7024059","tgn:7017974","tgn:1000004","tgn:7006651","tgn:7029392"],"placetype":["aat:300008347"],"name:en":"Gekhadzor","id":7024059}}
>>>>>>> 03f74aca74312dbeaf24d7e61306dd6a786dc3d0
