{
  "id": 2782040,
  "type": "Feature",
  "properties": {
    "tgn:hierarchy":[
        "tgn:2782040",
        "tgn:7013272",
        "tgn:1000001",
        "tgn:7012149",
        "tgn:7007710",
        "tgn:7029392"
    ],
    "tgn:id":2782040,
    "tgn:name":"Woods Run",
    "tgn:placetype":[
        "aat:300008347"
    ]
},
  "bbox": [],
  "geometry": {"coordinates":[-80.0167,40.4667],"type":"Point"}
}