{
  "id": 7303703,
  "type": "Feature",
  "properties": {
    "tgn:hierarchy":[
        "tgn:7303703",
        "tgn:7008911",
        "tgn:1000003",
        "tgn:7002763",
        "tgn:1000095",
        "tgn:7029392"
    ],
    "tgn:id":7303703,
    "tgn:name":"Morz\u00f3",
    "tgn:placetype":[
        "aat:300008347"
    ]
},
  "bbox": [],
  "geometry": {"coordinates":[-6.533333,43.116667],"type":"Point"}
}