{
  "id": 1044870,
  "type": "Feature",
  "properties": {
    "tgn:hierarchy":[
        "tgn:1044870",
        "tgn:7003127",
        "tgn:1000003",
        "tgn:7008516",
        "tgn:1000080",
        "tgn:7029392"
    ],
    "tgn:id":1044870,
    "tgn:name":"Granarolo dell'Emilia",
    "tgn:placetype":[
        "aat:300008347"
    ]
},
  "bbox": [],
  "geometry": {"coordinates":[11.4333,44.55],"type":"Point"}
}