<<<<<<< HEAD
{
  "id": 2409898,
  "type": "Feature",
  "properties": {
    "tgn:hierarchy":[
        "tgn:2409898",
        "tgn:7006450",
        "tgn:1000001",
        "tgn:7012149",
        "tgn:2124014",
        "tgn:7029392"
    ],
    "tgn:id":2409898,
    "tgn:name":"Imikruk Lagoon",
    "tgn:placetype":[
        "aat:300008680"
    ]
},
  "bbox": [],
  "geometry": {"coordinates":[-164.3,67.6667],"type":"Point"}
}
=======
{"geometry":{"type":"Point","coordinates":[-164.300000,67.666700]},"type":"Feature","properties":{"hierarchy":["tgn:2409898","tgn:7006450","tgn:1000001","tgn:7012149","tgn:2124014","tgn:7029392"],"placetype":["aat:300008680"],"id":2409898,"name:xx":"Imikruk Lagoon"}}
>>>>>>> 03f74aca74312dbeaf24d7e61306dd6a786dc3d0
