{
  "id": 1074602,
  "type": "Feature",
  "properties": {
    "tgn:hierarchy":[
        "tgn:1074602",
        "tgn:1000004",
        "tgn:7000198",
        "tgn:7031786",
        "tgn:7029392"
    ],
    "tgn:id":1074602,
    "tgn:name:en":"Baijn\u0101th",
    "tgn:placetype":[
        "aat:300008347"
    ]
},
  "bbox": [],
  "geometry": {"coordinates":[79.615929,29.906431],"type":"Point"}
}