<<<<<<< HEAD
{
  "id": 7363452,
  "type": "Feature",
  "properties": {
    "tgn:hierarchy":[
        "tgn:7363452",
        "tgn:1001853",
        "tgn:1000001",
        "tgn:7005560",
        "tgn:7029392"
    ],
    "tgn:id":7363452,
    "tgn:name":"Tanque El Chapote",
    "tgn:placetype":[
        "aat:300006191"
    ]
},
  "bbox": [],
  "geometry": {"coordinates":[-100.0,27.683333],"type":"Point"}
}
=======
{"geometry":{"type":"Point","coordinates":[-100.000000,27.683333]},"type":"Feature","properties":{"hierarchy":["tgn:7363452","tgn:1001853","tgn:1000001","tgn:7005560","tgn:7029392"],"placetype":["aat:300006191"],"id":7363452,"name:xx":"Tanque El Chapote"}}
>>>>>>> 03f74aca74312dbeaf24d7e61306dd6a786dc3d0
