{
  "id": 2497577,
  "type": "Feature",
  "properties": {
    "tgn:hierarchy":[
        "tgn:2497577",
        "tgn:1000001",
        "tgn:7012149",
        "tgn:1003020",
        "tgn:7007920",
        "tgn:7029392"
    ],
    "tgn:id":2497577,
    "tgn:name":"May Creek",
    "tgn:placetype":[
        "aat:300008706"
    ]
},
  "bbox": [],
  "geometry": {"coordinates":[-120.95,48.7833],"type":"Point"}
}