{
  "id": 2667724,
  "type": "Feature",
  "properties": {
    "tgn:hierarchy":[
        "tgn:2667724",
        "tgn:1000001",
        "tgn:7012149",
        "tgn:2001859",
        "tgn:7007825",
        "tgn:7029392"
    ],
    "tgn:id":2667724,
    "tgn:name":"Skullbone Bar",
    "tgn:placetype":[
        "aat:300132348"
    ]
},
  "bbox": [],
  "geometry": {"coordinates":[-89.6667,36.0833],"type":"Point"}
}