{
  "id": 7319571,
  "type": "Feature",
  "properties": {
    "tgn:hierarchy":[
        "tgn:7319571",
        "tgn:7002464",
        "tgn:1000049",
        "tgn:1000002",
        "tgn:7029392"
    ],
    "tgn:id":7319571,
    "tgn:name":"Alpajeres, Cerros de",
    "tgn:placetype":[
        "aat:300008795"
    ]
},
  "bbox": [],
  "geometry": {"coordinates":[-68.916667,-19.15],"type":"Point"}
}