{
  "id": 7406083,
  "type": "Feature",
  "properties": {
    "tgn:hierarchy":[
        "tgn:7406083",
        "tgn:1000001",
        "tgn:1001906",
        "tgn:7005560",
        "tgn:7029392"
    ],
    "tgn:id":7406083,
    "tgn:name":"Las Cucarachas",
    "tgn:placetype":[
        "aat:300008347"
    ]
},
  "bbox": [],
  "geometry": {"coordinates":[-105.058333,22.1625],"type":"Point"}
}