{
  "id": 2650254,
  "type": "Feature",
  "properties": {
    "tgn:hierarchy":[
        "tgn:2650254",
        "tgn:7002659",
        "tgn:1000001",
        "tgn:7012149",
        "tgn:2000029",
        "tgn:7029392"
    ],
    "tgn:id":2650254,
    "tgn:name":"Seal Spring",
    "tgn:placetype":[
        "aat:300008697"
    ]
},
  "bbox": [],
  "geometry": {"coordinates":[-87.7167,34.5333],"type":"Point"}
}