<<<<<<< HEAD
{
  "id": 2404019,
  "type": "Feature",
  "properties": {
    "tgn:hierarchy":[
        "tgn:2404019",
        "tgn:1000001",
        "tgn:7012149",
        "tgn:1002795",
        "tgn:7007826",
        "tgn:7029392"
    ],
    "tgn:id":2404019,
    "tgn:name":"Howell Lake",
    "tgn:placetype":[
        "aat:300008680"
    ]
},
  "bbox": [],
  "geometry": {"coordinates":[-94.6167,31.05],"type":"Point"}
}
=======
{"geometry":{"type":"Point","coordinates":[-94.616700,31.050000]},"type":"Feature","properties":{"hierarchy":["tgn:2404019","tgn:1000001","tgn:7012149","tgn:1002795","tgn:7007826","tgn:7029392"],"placetype":["aat:300008680"],"id":2404019,"name:xx":"Howell Lake"}}
>>>>>>> 03f74aca74312dbeaf24d7e61306dd6a786dc3d0
