{
  "id": 2284221,
  "type": "Feature",
  "properties": {
    "tgn:hierarchy":[
        "tgn:2284221",
        "tgn:1000001",
        "tgn:7012149",
        "tgn:7022542",
        "tgn:7007825",
        "tgn:7029392"
    ],
    "tgn:id":2284221,
    "tgn:name":"Denton Spring",
    "tgn:placetype":[
        "aat:300008697"
    ]
},
  "bbox": [],
  "geometry": {"coordinates":[-84.5667,35.5333],"type":"Point"}
}