{
  "id": 7249582,
  "type": "Feature",
  "properties": {
    "tgn:hierarchy":[
        "tgn:7249582",
        "tgn:7007877",
        "tgn:1000003",
        "tgn:1000063",
        "tgn:4012014",
        "tgn:7029392"
    ],
    "tgn:id":7249582,
    "tgn:name":"Pont du Lion Sart",
    "tgn:placetype":[
        "aat:300008347"
    ]
},
  "bbox": [],
  "geometry": {"coordinates":[4.183333,50.35],"type":"Point"}
}