{
  "id": 2530545,
  "type": "Feature",
  "properties": {
    "tgn:hierarchy":[
        "tgn:2530545",
        "tgn:1000001",
        "tgn:7012149",
        "tgn:1002356",
        "tgn:7007568",
        "tgn:7029392"
    ],
    "tgn:id":2530545,
    "tgn:name":"Muddy Creek",
    "tgn:placetype":[
        "aat:300008706"
    ]
},
  "bbox": [],
  "geometry": {"coordinates":[-79.0167,42.5667],"type":"Point"}
}