{
  "id": 2209418,
  "type": "Feature",
  "properties": {
    "tgn:hierarchy":[
        "tgn:2209418",
        "tgn:1000001",
        "tgn:7012149",
        "tgn:2002062",
        "tgn:7007826",
        "tgn:7029392"
    ],
    "tgn:id":2209418,
    "tgn:name":"Burnt Spring Hills",
    "tgn:placetype":[
        "aat:300008798"
    ]
},
  "bbox": [],
  "geometry": {"coordinates":[-104.0167,31.4167],"type":"Point"}
}