{
  "id": 7378565,
  "type": "Feature",
  "properties": {
    "tgn:hierarchy":[
        "tgn:7378565",
        "tgn:1000001",
        "tgn:7005597",
        "tgn:7005560",
        "tgn:7029392"
    ],
    "tgn:id":7378565,
    "tgn:name":"Mangana, Arroyo de",
    "tgn:placetype":[
        "aat:300266554",
        "aat:300008699"
    ]
},
  "bbox": [],
  "geometry": {"coordinates":[-98.883333,24.466667],"type":"Point"}
}