{
  "id": 2202164,
  "type": "Feature",
  "properties": {
    "tgn:hierarchy":[
        "tgn:2202164",
        "tgn:1000001",
        "tgn:2001414",
        "tgn:7012149",
        "tgn:7007526",
        "tgn:7029392"
    ],
    "tgn:id":2202164,
    "tgn:name":"Buck Lake",
    "tgn:placetype":[
        "aat:300008680"
    ]
},
  "bbox": [],
  "geometry": {"coordinates":[-119.15,41.8333],"type":"Point"}
}