{
  "id": 7077485,
  "type": "Feature",
  "properties": {
    "tgn:hierarchy":[
        "tgn:7077485",
        "tgn:1000003",
        "tgn:7003677",
        "tgn:7000084",
        "tgn:7029392"
    ],
    "tgn:id":7077485,
    "tgn:name":"Holzkamp",
    "tgn:placetype":[
        "aat:300008347"
    ]
},
  "bbox": [],
  "geometry": {"coordinates":[8.683333,51.983333],"type":"Point"}
}