{
  "id": 7347530,
  "type": "Feature",
  "properties": {
    "tgn:hierarchy":[
        "tgn:7347530",
        "tgn:7002758",
        "tgn:1001316",
        "tgn:1000003",
        "tgn:1000095",
        "tgn:7029392"
    ],
    "tgn:id":7347530,
    "tgn:name":"Arroyo Molinos",
    "tgn:placetype":[
        "aat:300008347"
    ]
},
  "bbox": [],
  "geometry": {"coordinates":[-3.016667,37.733333],"type":"Point"}
}