<<<<<<< HEAD
{
  "id": 7374564,
  "type": "Feature",
  "properties": {
    "tgn:hierarchy":[
        "tgn:7374564",
        "tgn:1000001",
        "tgn:7005599",
        "tgn:7005560",
        "tgn:7029392"
    ],
    "tgn:id":7374564,
    "tgn:name":"La Costa",
    "tgn:placetype":[
        "aat:300008347"
    ]
},
  "bbox": [],
  "geometry": {"coordinates":[-98.0,22.3],"type":"Point"}
}
=======
{"geometry":{"type":"Point","coordinates":[-98.000000,22.300000]},"type":"Feature","properties":{"hierarchy":["tgn:7374564","tgn:1000001","tgn:7005599","tgn:7005560","tgn:7029392"],"placetype":["aat:300008347"],"id":7374564,"name:xx":"La Costa"}}
>>>>>>> 03f74aca74312dbeaf24d7e61306dd6a786dc3d0
