{
  "id": 7322506,
  "type": "Feature",
  "properties": {
    "tgn:hierarchy":[
        "tgn:7322506",
        "tgn:7002760",
        "tgn:1000003",
        "tgn:1000095",
        "tgn:7029392"
    ],
    "tgn:id":7322506,
    "tgn:name":"San Rom\u00e1n",
    "tgn:placetype":[
        "aat:300008347"
    ]
},
  "bbox": [],
  "geometry": {"coordinates":[-3.85,43.466667],"type":"Point"}
}