{
  "id": 7134163,
  "type": "Feature",
  "properties": {
    "tgn:hierarchy":[
        "tgn:7134163",
        "tgn:1000003",
        "tgn:7003676",
        "tgn:7000084",
        "tgn:7029392"
    ],
    "tgn:id":7134163,
    "tgn:name":"Moorkanal",
    "tgn:placetype":[
        "aat:300006075"
    ]
},
  "bbox": [],
  "geometry": {"coordinates":[8.633333,52.55],"type":"Point"}
}