{
  "id": 7312000,
  "type": "Feature",
  "properties": {
    "tgn:hierarchy":[
        "tgn:7312000",
        "tgn:1001768",
        "tgn:1000049",
        "tgn:1000002",
        "tgn:7029392"
    ],
    "tgn:id":7312000,
    "tgn:name":"Las Garras",
    "tgn:placetype":[
        "aat:300387200"
    ]
},
  "bbox": [],
  "geometry": {"coordinates":[-71.166667,-32.483333],"type":"Point"}
}