{
  "id": 7030196,
  "type": "Feature",
  "properties": {
    "tgn:hierarchy":[
        "tgn:7030196",
        "tgn:1000003",
        "tgn:7002881",
        "tgn:1000070",
        "tgn:7029392"
    ],
    "tgn:id":7030196,
    "tgn:name":"Chalain, Lac de",
    "tgn:placetype":[
        "aat:300008680"
    ]
},
  "bbox": [],
  "geometry": {"coordinates":[5.813,46.666],"type":"Point"}
}