<<<<<<< HEAD
{
  "id": 2259775,
  "type": "Feature",
  "properties": {
    "tgn:hierarchy":[
        "tgn:2259775",
        "tgn:1000001",
        "tgn:1002276",
        "tgn:7012149",
        "tgn:7007708",
        "tgn:7029392"
    ],
    "tgn:id":2259775,
    "tgn:name":"Cougar Mountain",
    "tgn:placetype":[
        "aat:300008798"
    ]
},
  "bbox": [],
  "geometry": {"coordinates":[-123.6167,45.8333],"type":"Point"}
}
=======
{"geometry":{"type":"Point","coordinates":[-123.616700,45.833300]},"type":"Feature","properties":{"hierarchy":["tgn:2259775","tgn:1000001","tgn:1002276","tgn:7012149","tgn:7007708","tgn:7029392"],"placetype":["aat:300008798"],"id":2259775,"name:xx":"Cougar Mountain"}}
>>>>>>> 03f74aca74312dbeaf24d7e61306dd6a786dc3d0
