{
  "id": 2259775,
  "type": "Feature",
  "properties": {
    "tgn:hierarchy":[
        "tgn:2259775",
        "tgn:1000001",
        "tgn:1002276",
        "tgn:7012149",
        "tgn:7007708",
        "tgn:7029392"
    ],
    "tgn:id":2259775,
    "tgn:name":"Cougar Mountain",
    "tgn:placetype":[
        "aat:300008798"
    ]
},
  "bbox": [],
  "geometry": {"coordinates":[-123.6167,45.8333],"type":"Point"}
}