{
  "id": 7145413,
  "type": "Feature",
  "properties": {
    "tgn:hierarchy":[
        "tgn:7145413",
        "tgn:1000003",
        "tgn:7003687",
        "tgn:7000084",
        "tgn:7029392"
    ],
    "tgn:id":7145413,
    "tgn:name":"Kossebau",
    "tgn:placetype":[
        "aat:300008347"
    ]
},
  "bbox": [],
  "geometry": {"coordinates":[11.566667,52.816667],"type":"Point"}
}