{
  "id": 2739687,
  "type": "Feature",
  "properties": {
    "tgn:hierarchy":[
        "tgn:2739687",
        "tgn:1000001",
        "tgn:7012149",
        "tgn:7014589",
        "tgn:7007515",
        "tgn:7029392"
    ],
    "tgn:id":2739687,
    "tgn:name":"Upper Cranberry Lake",
    "tgn:placetype":[
        "aat:300008680"
    ]
},
  "bbox": [],
  "geometry": {"coordinates":[-67.95,44.9167],"type":"Point"}
}