{
  "id": 7513388,
  "type": "Feature",
  "properties": {
    "tgn:hierarchy":[
        "tgn:7513388",
        "tgn:1009227",
        "tgn:1000226",
        "tgn:7520095",
        "tgn:1000006",
        "tgn:7029392"
    ],
    "tgn:id":7513388,
    "tgn:name:en":"Golden Downs",
    "tgn:placetype":[
        "aat:300008347"
    ]
},
  "bbox": [],
  "geometry": {"coordinates":[172.883333,-41.583333],"type":"Point"}
}