{
  "id": 7592888,
  "type": "Feature",
  "properties": {
    "tgn:hierarchy":[
        "tgn:7592888",
        "tgn:1000004",
        "tgn:7000198",
        "tgn:7000799",
        "tgn:7029392"
    ],
    "tgn:id":7592888,
    "tgn:name:en":"M\u012bnka",
    "tgn:placetype":[
        "aat:300008347"
    ]
},
  "bbox": [],
  "geometry": {"coordinates":[74.33777,33.050032],"type":"Point"}
}