{
  "id": 7287878,
  "type": "Feature",
  "properties": {
    "tgn:hierarchy":[
        "tgn:7287878",
        "tgn:7016598",
        "tgn:1000049",
        "tgn:1000002",
        "tgn:7029392"
    ],
    "tgn:id":7287878,
    "tgn:name":"Julia, Pique",
    "tgn:placetype":[
        "aat:300008697"
    ]
},
  "bbox": [],
  "geometry": {"coordinates":[-69.733333,-25.383333],"type":"Point"}
}