<<<<<<< HEAD
{
  "id": 7020557,
  "type": "Feature",
  "properties": {
    "tgn:hierarchy":[
        "tgn:7020557",
        "tgn:1000001",
        "tgn:7012149",
        "tgn:2001286",
        "tgn:7007524",
        "tgn:7029392"
    ],
    "tgn:id":7020557,
    "tgn:name":"Kilbrennan Lake",
    "tgn:placetype":[
        "aat:300008680"
    ]
},
  "bbox": [],
  "geometry": {"coordinates":[-115.8833,48.5833],"type":"Point"}
}
=======
{"geometry":{"type":"Point","coordinates":[-115.883300,48.583300]},"type":"Feature","properties":{"hierarchy":["tgn:7020557","tgn:1000001","tgn:7012149","tgn:2001286","tgn:7007524","tgn:7029392"],"placetype":["aat:300008680"],"id":7020557,"name:xx":"Kilbrennan Lake"}}
>>>>>>> 03f74aca74312dbeaf24d7e61306dd6a786dc3d0
