{
  "id": 7020557,
  "type": "Feature",
  "properties": {
    "tgn:hierarchy":[
        "tgn:7020557",
        "tgn:1000001",
        "tgn:7012149",
        "tgn:2001286",
        "tgn:7007524",
        "tgn:7029392"
    ],
    "tgn:id":7020557,
    "tgn:name":"Kilbrennan Lake",
    "tgn:placetype":[
        "aat:300008680"
    ]
},
  "bbox": [],
  "geometry": {"coordinates":[-115.8833,48.5833],"type":"Point"}
}