{
  "id": 2049616,
  "type": "Feature",
  "properties": {
    "tgn:hierarchy":[
        "tgn:2049616",
        "tgn:1000001",
        "tgn:7012149",
        "tgn:1003038",
        "tgn:7007517",
        "tgn:7029392"
    ],
    "tgn:id":2049616,
    "tgn:name":"Clinton",
    "tgn:placetype":[
        "aat:300008347"
    ]
},
  "bbox": [],
  "geometry": {"coordinates":[-71.6833,42.4167],"type":"Point"}
}