{
  "id": 2385437,
  "type": "Feature",
  "properties": {
    "tgn:hierarchy":[
        "tgn:2385437",
        "tgn:1000001",
        "tgn:7012149",
        "tgn:7007826",
        "tgn:7029392"
    ],
    "tgn:id":2385437,
    "tgn:name":"Henderson Branch",
    "tgn:placetype":[
        "aat:300008699"
    ]
},
  "bbox": [],
  "geometry": {"coordinates":[-99.2333,30.15],"type":"Point"}
}