{
  "id": 7532380,
  "type": "Feature",
  "properties": {
    "tgn:hierarchy":[
        "tgn:7532380",
        "tgn:7001242",
        "tgn:7016833",
        "tgn:1001092",
        "tgn:7029392"
    ],
    "tgn:id":7532380,
    "tgn:name":"K\u016bbr\u012b al Maz\u0327all\u0101t",
    "tgn:placetype":[
        "aat:300007836"
    ]
},
  "bbox": [],
  "geometry": {"coordinates":[31.246328,30.105882],"type":"Point"}
}