{
  "id": 1129554,
  "type": "Feature",
  "properties": {
    "tgn:hierarchy":[
        "tgn:1129554",
        "tgn:1000050",
        "tgn:1000002",
        "tgn:7029392"
    ],
    "tgn:id":1129554,
    "tgn:name":"San Jorge, R\u00edo",
    "tgn:placetype":[
        "aat:300008707"
    ]
},
  "bbox": [],
  "geometry": {"coordinates":[-74.75,9.114],"type":"Point"}
}