{
  "id": 7060504,
  "type": "Feature",
  "properties": {
    "tgn:hierarchy":[
        "tgn:7060504",
        "tgn:1000003",
        "tgn:7003687",
        "tgn:7000084",
        "tgn:7029392"
    ],
    "tgn:id":7060504,
    "tgn:name":"Altenburg",
    "tgn:placetype":[
        "aat:300008777"
    ]
},
  "bbox": [],
  "geometry": {"coordinates":[10.916667,51.833333],"type":"Point"}
}