{
  "id": 7177587,
  "type": "Feature",
  "properties": {
    "tgn:hierarchy":[
        "tgn:7177587",
        "tgn:1000003",
        "tgn:7003677",
        "tgn:7000084",
        "tgn:7029392"
    ],
    "tgn:id":7177587,
    "tgn:name":"Haks-Berg",
    "tgn:placetype":[
        "aat:300008777"
    ]
},
  "bbox": [],
  "geometry": {"coordinates":[9.15,51.766667],"type":"Point"}
}