<<<<<<< HEAD
{
  "id": 7177587,
  "type": "Feature",
  "properties": {
    "tgn:hierarchy":[
        "tgn:7177587",
        "tgn:1000003",
        "tgn:7003677",
        "tgn:7000084",
        "tgn:7029392"
    ],
    "tgn:id":7177587,
    "tgn:name":"Haks-Berg",
    "tgn:placetype":[
        "aat:300008777"
    ]
},
  "bbox": [],
  "geometry": {"coordinates":[9.15,51.766667],"type":"Point"}
}
=======
{"geometry":{"type":"Point","coordinates":[9.150000,51.766667]},"type":"Feature","properties":{"hierarchy":["tgn:7177587","tgn:1000003","tgn:7003677","tgn:7000084","tgn:7029392"],"placetype":["aat:300008777"],"id":7177587,"name:xx":"Haks-Berg"}}
>>>>>>> 03f74aca74312dbeaf24d7e61306dd6a786dc3d0
