{
  "id": 7313056,
  "type": "Feature",
  "properties": {
    "tgn:hierarchy":[
        "tgn:7313056",
        "tgn:1001695",
        "tgn:1000049",
        "tgn:1000002",
        "tgn:7029392"
    ],
    "tgn:id":7313056,
    "tgn:name":"Los Cipreses, Quebrada",
    "tgn:placetype":[
        "aat:300008699"
    ]
},
  "bbox": [],
  "geometry": {"coordinates":[-70.483333,-34.016667],"type":"Point"}
}