{
  "id": 2445373,
  "type": "Feature",
  "properties": {
    "tgn:hierarchy":[
        "tgn:2445373",
        "tgn:1000001",
        "tgn:1002243",
        "tgn:7012149",
        "tgn:7007520",
        "tgn:7029392"
    ],
    "tgn:id":2445373,
    "tgn:name":"Leninger Lake",
    "tgn:placetype":[
        "aat:300008680"
    ]
},
  "bbox": [],
  "geometry": {"coordinates":[-85.9667,41.85],"type":"Point"}
}