<<<<<<< HEAD
{
  "id": 7354728,
  "type": "Feature",
  "properties": {
    "tgn:hierarchy":[
        "tgn:7354728",
        "tgn:7005581",
        "tgn:1000001",
        "tgn:7005560",
        "tgn:7029392"
    ],
    "tgn:id":7354728,
    "tgn:name":"Rancho Charco de Piedra",
    "tgn:placetype":[
        "aat:300000241"
    ]
},
  "bbox": [],
  "geometry": {"coordinates":[-104.25,28.716667],"type":"Point"}
}
=======
{"geometry":{"type":"Point","coordinates":[-104.250000,28.716667]},"type":"Feature","properties":{"hierarchy":["tgn:7354728","tgn:7005581","tgn:1000001","tgn:7005560","tgn:7029392"],"placetype":["aat:300000241"],"id":7354728,"name:xx":"Rancho Charco de Piedra"}}
>>>>>>> 03f74aca74312dbeaf24d7e61306dd6a786dc3d0
