{
  "id": 1010165,
  "type": "Feature",
  "properties": {
    "tgn:hierarchy":[
        "tgn:1010165",
        "tgn:7000895",
        "tgn:1000004",
        "tgn:1000988",
        "tgn:1000120",
        "tgn:7029392"
    ],
    "tgn:id":1010165,
    "tgn:name":"Nanatsu-jima",
    "tgn:placetype":[
        "aat:300008791"
    ]
},
  "bbox": [],
  "geometry": {"coordinates":[136.9167,37.6667],"type":"Point"}
}