{
  "id": 7070027,
  "type": "Feature",
  "properties": {
    "tgn:hierarchy":[
        "tgn:7070027",
        "tgn:1000003",
        "tgn:7003678",
        "tgn:7000084",
        "tgn:7029392"
    ],
    "tgn:id":7070027,
    "tgn:name":"F\u00f6rsterei Tiergarten",
    "tgn:placetype":[
        "aat:300004792"
    ]
},
  "bbox": [],
  "geometry": {"coordinates":[8.333333,50.483333],"type":"Point"}
}