{
  "id": 2286625,
  "type": "Feature",
  "properties": {
    "tgn:hierarchy":[
        "tgn:2286625",
        "tgn:1000001",
        "tgn:2002107",
        "tgn:7012149",
        "tgn:7007827",
        "tgn:7029392"
    ],
    "tgn:id":2286625,
    "tgn:name":"Diamond Lake",
    "tgn:placetype":[
        "aat:300008680"
    ]
},
  "bbox": [],
  "geometry": {"coordinates":[-110.65,40.6167],"type":"Point"}
}