{
  "id": 2002253,
  "type": "Feature",
  "properties": {
    "tgn:hierarchy":[
        "tgn:2002253",
        "tgn:1000001",
        "tgn:7012149",
        "tgn:7013961",
        "tgn:7029392"
    ],
    "tgn:id":2002253,
    "tgn:name":"Barbour",
    "tgn:placetype":[
        "aat:300387145",
        "aat:300000771"
    ]
},
  "bbox": [],
  "geometry": {"coordinates":[-80.0333,39.1333],"type":"Point"}
}