{
  "id": 2383351,
  "type": "Feature",
  "properties": {
    "tgn:hierarchy":[
        "tgn:2383351",
        "tgn:1000001",
        "tgn:7012149",
        "tgn:2001288",
        "tgn:7007524",
        "tgn:7029392"
    ],
    "tgn:id":2383351,
    "tgn:name":"Heart Lake",
    "tgn:placetype":[
        "aat:300008680"
    ]
},
  "bbox": [],
  "geometry": {"coordinates":[-111.8667,45.2333],"type":"Point"}
}