{
  "id": 7517215,
  "type": "Feature",
  "properties": {
    "tgn:hierarchy":[
        "tgn:7517215",
        "tgn:7000508",
        "tgn:1008380",
        "tgn:1000226",
        "tgn:1000006",
        "tgn:7029392"
    ],
    "tgn:id":7517215,
    "tgn:name:en":"Kopukanui",
    "tgn:placetype":[
        "aat:300008777"
    ]
},
  "bbox": [],
  "geometry": {"coordinates":[174.633333,-37.216667],"type":"Point"}
}