{
  "id": 2488227,
  "type": "Feature",
  "properties": {
    "tgn:hierarchy":[
        "tgn:2488227",
        "tgn:1000001",
        "tgn:2000467",
        "tgn:7012149",
        "tgn:7007250",
        "tgn:7029392"
    ],
    "tgn:id":2488227,
    "tgn:name":"Magpie Basin",
    "tgn:placetype":[
        "aat:300386845"
    ]
},
  "bbox": [],
  "geometry": {"coordinates":[-114.25,42.25],"type":"Point"}
}