{
  "id": 2731126,
  "type": "Feature",
  "properties": {
    "tgn:hierarchy":[
        "tgn:2731126",
        "tgn:1000001",
        "tgn:7012149",
        "tgn:2001217",
        "tgn:7007523",
        "tgn:7029392"
    ],
    "tgn:id":2731126,
    "tgn:name":"Tucker Creek",
    "tgn:placetype":[
        "aat:300008706"
    ]
},
  "bbox": [],
  "geometry": {"coordinates":[-90.1833,37.55],"type":"Point"}
}