{
  "id": 2303750,
  "type": "Feature",
  "properties": {
    "tgn:hierarchy":[
        "tgn:2303750",
        "tgn:1000001",
        "tgn:7012149",
        "tgn:1002440",
        "tgn:7007568",
        "tgn:7029392"
    ],
    "tgn:id":2303750,
    "tgn:name":"Eagle Nest",
    "tgn:placetype":[
        "aat:300008347"
    ]
},
  "bbox": [],
  "geometry": {"coordinates":[-74.4833,43.8333],"type":"Point"}
}