{
  "id": 2012714,
  "type": "Feature",
  "properties": {
    "tgn:hierarchy":[
        "tgn:2012714",
        "tgn:1000001",
        "tgn:7012149",
        "tgn:7007157",
        "tgn:2000188",
        "tgn:7029392"
    ],
    "tgn:id":2012714,
    "tgn:name":"Millville",
    "tgn:placetype":[
        "aat:300008347"
    ]
},
  "bbox": [],
  "geometry": {"coordinates":[-122.1667,40.5333],"type":"Point"}
}