{
  "id": 2049479,
  "type": "Feature",
  "properties": {
    "tgn:hierarchy":[
        "tgn:2049479",
        "tgn:7013445",
        "tgn:1000001",
        "tgn:1002923",
        "tgn:7012149",
        "tgn:7007517",
        "tgn:7029392"
    ],
    "tgn:id":2049479,
    "tgn:name":"North Brighton",
    "tgn:placetype":[
        "aat:300000745"
    ]
},
  "bbox": [],
  "geometry": {"coordinates":[-71.1333,42.35],"type":"Point"}
}