{
  "id": 7404941,
  "type": "Feature",
  "properties": {
    "tgn:hierarchy":[
        "tgn:7404941",
        "tgn:7005578",
        "tgn:1000001",
        "tgn:7005560",
        "tgn:7029392"
    ],
    "tgn:id":7404941,
    "tgn:name":"La Valeriana, Laguna",
    "tgn:placetype":[
        "aat:300008680"
    ]
},
  "bbox": [],
  "geometry": {"coordinates":[-89.266667,18.916667],"type":"Point"}
}