{
  "id": 7307725,
  "type": "Feature",
  "properties": {
    "tgn:hierarchy":[
        "tgn:7307725",
        "tgn:7002825",
        "tgn:7016622",
        "tgn:1000003",
        "tgn:1000095",
        "tgn:7029392"
    ],
    "tgn:id":7307725,
    "tgn:name":"Llanos de la Concepci\u00f3n",
    "tgn:placetype":[
        "aat:300008347"
    ]
},
  "bbox": [],
  "geometry": {"coordinates":[-14.016667,28.466667],"type":"Point"}
}