<<<<<<< HEAD
{
  "id": 2153351,
  "type": "Feature",
  "properties": {
    "tgn:hierarchy":[
        "tgn:2153351",
        "tgn:1000001",
        "tgn:7012149",
        "tgn:1002897",
        "tgn:7007920",
        "tgn:7029392"
    ],
    "tgn:id":2153351,
    "tgn:name":"Bean Creek",
    "tgn:placetype":[
        "aat:300008706"
    ]
},
  "bbox": [],
  "geometry": {"coordinates":[-122.0833,46.2833],"type":"Point"}
}
=======
{"geometry":{"type":"Point","coordinates":[-122.083300,46.283300]},"type":"Feature","properties":{"hierarchy":["tgn:2153351","tgn:1000001","tgn:7012149","tgn:1002897","tgn:7007920","tgn:7029392"],"placetype":["aat:300008706"],"id":2153351,"name:xx":"Bean Creek"}}
>>>>>>> 03f74aca74312dbeaf24d7e61306dd6a786dc3d0
