{
  "id": 2500035,
  "type": "Feature",
  "properties": {
    "tgn:hierarchy":[
        "tgn:2500035",
        "tgn:1000001",
        "tgn:7012149",
        "tgn:2001531",
        "tgn:7007709",
        "tgn:7029392"
    ],
    "tgn:id":2500035,
    "tgn:name":"McCraw Mountain",
    "tgn:placetype":[
        "aat:300008798"
    ]
},
  "bbox": [],
  "geometry": {"coordinates":[-82.2833,35.3167],"type":"Point"}
}