{
  "id": 7333242,
  "type": "Feature",
  "properties": {
    "tgn:hierarchy":[
        "tgn:7333242",
        "tgn:7007780",
        "tgn:1000003",
        "tgn:7009604",
        "tgn:1000095",
        "tgn:7029392"
    ],
    "tgn:id":7333242,
    "tgn:name":"Garin",
    "tgn:placetype":[
        "aat:300008347"
    ]
},
  "bbox": [],
  "geometry": {"coordinates":[-2.225707,43.077243],"type":"Point"}
}