{
  "id": 7497912,
  "type": "Feature",
  "properties": {
    "tgn:hierarchy":[
        "tgn:7497912",
        "tgn:1000004",
        "tgn:7492971",
        "tgn:1000141",
        "tgn:7029392"
    ],
    "tgn:id":7497912,
    "tgn:name":"Diliuhao Qiao",
    "tgn:placetype":[
        "aat:300007836"
    ]
},
  "bbox": [],
  "geometry": {"coordinates":[120.489028,22.691734],"type":"Point"}
}