{
  "id": 2515004,
  "type": "Feature",
  "properties": {
    "tgn:hierarchy":[
        "tgn:2515004",
        "tgn:1000001",
        "tgn:7012149",
        "tgn:7007157",
        "tgn:2000188",
        "tgn:7029392"
    ],
    "tgn:id":2515004,
    "tgn:name":"Miller Valley",
    "tgn:placetype":[
        "aat:300008761"
    ]
},
  "bbox": [],
  "geometry": {"coordinates":[-121.8333,40.65],"type":"Point"}
}