{
  "id": 2769400,
  "type": "Feature",
  "properties": {
    "tgn:hierarchy":[
        "tgn:2769400",
        "tgn:1000001",
        "tgn:1002199",
        "tgn:7012149",
        "tgn:7007826",
        "tgn:7029392"
    ],
    "tgn:id":2769400,
    "tgn:name":"Wickson Lake",
    "tgn:placetype":[
        "aat:300008680"
    ]
},
  "bbox": [],
  "geometry": {"coordinates":[-96.1667,30.75],"type":"Point"}
}