<<<<<<< HEAD
{
  "id": 2769400,
  "type": "Feature",
  "properties": {
    "tgn:hierarchy":[
        "tgn:2769400",
        "tgn:1000001",
        "tgn:1002199",
        "tgn:7012149",
        "tgn:7007826",
        "tgn:7029392"
    ],
    "tgn:id":2769400,
    "tgn:name":"Wickson Lake",
    "tgn:placetype":[
        "aat:300008680"
    ]
},
  "bbox": [],
  "geometry": {"coordinates":[-96.1667,30.75],"type":"Point"}
}
=======
{"geometry":{"type":"Point","coordinates":[-96.166700,30.750000]},"type":"Feature","properties":{"hierarchy":["tgn:2769400","tgn:1000001","tgn:1002199","tgn:7012149","tgn:7007826","tgn:7029392"],"placetype":["aat:300008680"],"id":2769400,"name:xx":"Wickson Lake"}}
>>>>>>> 03f74aca74312dbeaf24d7e61306dd6a786dc3d0
