{
  "id": 2561461,
  "type": "Feature",
  "properties": {
    "tgn:hierarchy":[
        "tgn:2561461",
        "tgn:1000001",
        "tgn:2001808",
        "tgn:7012149",
        "tgn:7007713",
        "tgn:7029392"
    ],
    "tgn:id":2561461,
    "tgn:name":"Osceola Lake",
    "tgn:placetype":[
        "aat:300006191"
    ]
},
  "bbox": [],
  "geometry": {"coordinates":[-97.8167,44.4667],"type":"Point"}
}