{
  "id": 2649665,
  "type": "Feature",
  "properties": {
    "tgn:hierarchy":[
        "tgn:2649665",
        "tgn:1000001",
        "tgn:1002738",
        "tgn:7012149",
        "tgn:7007565",
        "tgn:7029392"
    ],
    "tgn:id":2649665,
    "tgn:name":"Scow Landing",
    "tgn:placetype":[
        "aat:300008347"
    ]
},
  "bbox": [],
  "geometry": {"coordinates":[-74.3333,39.5833],"type":"Point"}
}