<<<<<<< HEAD
{
  "id": 2337018,
  "type": "Feature",
  "properties": {
    "tgn:hierarchy":[
        "tgn:2337018",
        "tgn:1000001",
        "tgn:7012149",
        "tgn:1002582",
        "tgn:7007240",
        "tgn:7029392"
    ],
    "tgn:id":2337018,
    "tgn:name":"Fourmile Island",
    "tgn:placetype":[
        "aat:300008791"
    ]
},
  "bbox": [],
  "geometry": {"coordinates":[-81.9167,26.6],"type":"Point"}
}
=======
{"geometry":{"type":"Point","coordinates":[-81.916700,26.600000]},"type":"Feature","properties":{"hierarchy":["tgn:2337018","tgn:1000001","tgn:7012149","tgn:1002582","tgn:7007240","tgn:7029392"],"placetype":["aat:300008791"],"id":2337018,"name:xx":"Fourmile Island"}}
>>>>>>> 03f74aca74312dbeaf24d7e61306dd6a786dc3d0
