{
  "id": 2592249,
  "type": "Feature",
  "properties": {
    "tgn:hierarchy":[
        "tgn:2592249",
        "tgn:1000001",
        "tgn:7012149",
        "tgn:1002513",
        "tgn:7007252",
        "tgn:7029392"
    ],
    "tgn:id":2592249,
    "tgn:name":"Pony Run",
    "tgn:placetype":[
        "aat:300008699"
    ]
},
  "bbox": [],
  "geometry": {"coordinates":[-85.0667,40.4833],"type":"Point"}
}