{
  "id": 2234901,
  "type": "Feature",
  "properties": {
    "tgn:hierarchy":[
        "tgn:2234901",
        "tgn:1000001",
        "tgn:7012149",
        "tgn:2001750",
        "tgn:7007712",
        "tgn:7029392"
    ],
    "tgn:id":2234901,
    "tgn:name":"Cherry Grove Inlet",
    "tgn:placetype":[
        "aat:300132316"
    ]
},
  "bbox": [],
  "geometry": {"coordinates":[-78.6333,33.8167],"type":"Point"}
}