{
  "id": 2163321,
  "type": "Feature",
  "properties": {
    "tgn:hierarchy":[
        "tgn:2163321",
        "tgn:1000001",
        "tgn:2000460",
        "tgn:7012149",
        "tgn:7007250",
        "tgn:7029392"
    ],
    "tgn:id":2163321,
    "tgn:name":"Benning Mountain",
    "tgn:placetype":[
        "aat:300008798"
    ]
},
  "bbox": [],
  "geometry": {"coordinates":[-116.0667,48.3333],"type":"Point"}
}