<<<<<<< HEAD
{
  "id": 2252119,
  "type": "Feature",
  "properties": {
    "tgn:hierarchy":[
        "tgn:2252119",
        "tgn:1000001",
        "tgn:7012149",
        "tgn:1002362",
        "tgn:7007919",
        "tgn:7029392"
    ],
    "tgn:id":2252119,
    "tgn:name":"Cone Creek",
    "tgn:placetype":[
        "aat:300008706"
    ]
},
  "bbox": [],
  "geometry": {"coordinates":[-77.0833,38.15],"type":"Point"}
}
=======
{"geometry":{"type":"Point","coordinates":[-77.083300,38.150000]},"type":"Feature","properties":{"hierarchy":["tgn:2252119","tgn:1000001","tgn:7012149","tgn:1002362","tgn:7007919","tgn:7029392"],"placetype":["aat:300008706"],"id":2252119,"name:xx":"Cone Creek"}}
>>>>>>> 03f74aca74312dbeaf24d7e61306dd6a786dc3d0
