<<<<<<< HEAD
{
  "id": 2768579,
  "type": "Feature",
  "properties": {
    "tgn:hierarchy":[
        "tgn:2768579",
        "tgn:1000001",
        "tgn:2000270",
        "tgn:7012149",
        "tgn:7007240",
        "tgn:7029392"
    ],
    "tgn:id":2768579,
    "tgn:name":"Whitfield Slough",
    "tgn:placetype":[
        "aat:300008905"
    ]
},
  "bbox": [],
  "geometry": {"coordinates":[-85.25,29.95],"type":"Point"}
}
=======
{"geometry":{"type":"Point","coordinates":[-85.250000,29.950000]},"type":"Feature","properties":{"hierarchy":["tgn:2768579","tgn:1000001","tgn:2000270","tgn:7012149","tgn:7007240","tgn:7029392"],"placetype":["aat:300008905"],"id":2768579,"name:xx":"Whitfield Slough"}}
>>>>>>> 03f74aca74312dbeaf24d7e61306dd6a786dc3d0
