{
  "id": 2768579,
  "type": "Feature",
  "properties": {
    "tgn:hierarchy":[
        "tgn:2768579",
        "tgn:1000001",
        "tgn:2000270",
        "tgn:7012149",
        "tgn:7007240",
        "tgn:7029392"
    ],
    "tgn:id":2768579,
    "tgn:name":"Whitfield Slough",
    "tgn:placetype":[
        "aat:300008905"
    ]
},
  "bbox": [],
  "geometry": {"coordinates":[-85.25,29.95],"type":"Point"}
}