{
  "id": 2238387,
  "type": "Feature",
  "properties": {
    "tgn:hierarchy":[
        "tgn:2238387",
        "tgn:1000001",
        "tgn:2002241",
        "tgn:7012149",
        "tgn:7007920",
        "tgn:7029392"
    ],
    "tgn:id":2238387,
    "tgn:name":"Choke Cherry Spring",
    "tgn:placetype":[
        "aat:300008697"
    ]
},
  "bbox": [],
  "geometry": {"coordinates":[-118.1333,46.55],"type":"Point"}
}