{
  "id": 1072008,
  "type": "Feature",
  "properties": {
    "tgn:hierarchy":[
        "tgn:1072008",
        "tgn:1000004",
        "tgn:1001390",
        "tgn:1000111",
        "tgn:7029392"
    ],
    "tgn:id":1072008,
    "tgn:name":"Suizhong",
    "tgn:placetype":[
        "aat:300008347"
    ]
},
  "bbox": [],
  "geometry": {"coordinates":[120.35,40.35],"type":"Point"}
}