{
  "id": 7301893,
  "type": "Feature",
  "properties": {
    "tgn:hierarchy":[
        "tgn:7301893",
        "tgn:7002813",
        "tgn:7002758",
        "tgn:1000003",
        "tgn:1000095",
        "tgn:7029392"
    ],
    "tgn:id":7301893,
    "tgn:name":"Miel, R\u00edo de la",
    "tgn:placetype":[
        "aat:300008699"
    ]
},
  "bbox": [],
  "geometry": {"coordinates":[-5.433333,36.116667],"type":"Point"}
}