<<<<<<< HEAD
{
  "id": 7365070,
  "type": "Feature",
  "properties": {
    "tgn:hierarchy":[
        "tgn:7365070",
        "tgn:7005586",
        "tgn:1000001",
        "tgn:7005560",
        "tgn:7029392"
    ],
    "tgn:id":7365070,
    "tgn:name":"El Sauz",
    "tgn:placetype":[
        "aat:300000241"
    ]
},
  "bbox": [],
  "geometry": {"coordinates":[-103.0,19.483333],"type":"Point"}
}
=======
{"geometry":{"type":"Point","coordinates":[-103.000000,19.483333]},"type":"Feature","properties":{"hierarchy":["tgn:7365070","tgn:7005586","tgn:1000001","tgn:7005560","tgn:7029392"],"placetype":["aat:300000241"],"id":7365070,"name:xx":"El Sauz"}}
>>>>>>> 03f74aca74312dbeaf24d7e61306dd6a786dc3d0
