{
  "id": 7361180,
  "type": "Feature",
  "properties": {
    "tgn:hierarchy":[
        "tgn:7361180",
        "tgn:7005587",
        "tgn:1000001",
        "tgn:7005560",
        "tgn:7029392"
    ],
    "tgn:id":7361180,
    "tgn:name":"El Ocote",
    "tgn:placetype":[
        "aat:300008347"
    ]
},
  "bbox": [],
  "geometry": {"coordinates":[-98.383333,20.216667],"type":"Point"}
}