<<<<<<< HEAD
{
  "id": 2159436,
  "type": "Feature",
  "properties": {
    "tgn:hierarchy":[
        "tgn:2159436",
        "tgn:1000001",
        "tgn:7012149",
        "tgn:7007920",
        "tgn:7029392"
    ],
    "tgn:id":2159436,
    "tgn:name":"Bee Creek",
    "tgn:placetype":[
        "aat:300008706"
    ]
},
  "bbox": [],
  "geometry": {"coordinates":[-124.0333,47.85],"type":"Point"}
}
=======
{"geometry":{"type":"Point","coordinates":[-124.033300,47.850000]},"type":"Feature","properties":{"hierarchy":["tgn:2159436","tgn:1000001","tgn:7012149","tgn:7007920","tgn:7029392"],"placetype":["aat:300008706"],"id":2159436,"name:xx":"Bee Creek"}}
>>>>>>> 03f74aca74312dbeaf24d7e61306dd6a786dc3d0
