{
  "id": 7588871,
  "type": "Feature",
  "properties": {
    "tgn:hierarchy":[
        "tgn:7588871",
        "tgn:1000004",
        "tgn:7000198",
        "tgn:7000799",
        "tgn:7029392"
    ],
    "tgn:id":7588871,
    "tgn:name:en":"Jijot Bahraui",
    "tgn:placetype":[
        "aat:300008347"
    ]
},
  "bbox": [],
  "geometry": {"coordinates":[74.096726,33.29021],"type":"Point"}
}