{
  "id": 2120073,
  "type": "Feature",
  "properties": {
    "tgn:hierarchy":[
        "tgn:2120073",
        "tgn:1000001",
        "tgn:2002258",
        "tgn:7012149",
        "tgn:7013961",
        "tgn:7029392"
    ],
    "tgn:id":2120073,
    "tgn:name":"Stinson",
    "tgn:placetype":[
        "aat:300008347",
        "aat:300387210"
    ]
},
  "bbox": [],
  "geometry": {"coordinates":[-81.0667,38.65],"type":"Point"}
}