{
  "id": 7383283,
  "type": "Feature",
  "properties": {
    "tgn:hierarchy":[
        "tgn:7383283",
        "tgn:1000001",
        "tgn:7005597",
        "tgn:7005560",
        "tgn:7029392"
    ],
    "tgn:id":7383283,
    "tgn:name":"Panales, Arroyo",
    "tgn:placetype":[
        "aat:300266554",
        "aat:300008699"
    ]
},
  "bbox": [],
  "geometry": {"coordinates":[-98.116667,24.233333],"type":"Point"}
}