{
  "id": 2049794,
  "type": "Feature",
  "properties": {
    "tgn:hierarchy":[
        "tgn:2049794",
        "tgn:1000001",
        "tgn:1002665",
        "tgn:7012149",
        "tgn:7013936",
        "tgn:7007517",
        "tgn:7029392"
    ],
    "tgn:id":2049794,
    "tgn:name":"Framingham Center",
    "tgn:placetype":[
        "aat:300000745"
    ]
},
  "bbox": [],
  "geometry": {"coordinates":[-71.4333,42.2833],"type":"Point"}
}