{
  "id": 7235998,
  "type": "Feature",
  "properties": {
    "tgn:hierarchy":[
        "tgn:7235998",
        "tgn:7002681",
        "tgn:7001395",
        "tgn:1000003",
        "tgn:1000074",
        "tgn:7029392"
    ],
    "tgn:id":7235998,
    "tgn:name":"Antho\u00fapolis",
    "tgn:placetype":[
        "aat:300008347"
    ]
},
  "bbox": [],
  "geometry": {"coordinates":[24.05,38.383333],"type":"Point"}
}