{
  "id": 7503738,
  "type": "Feature",
  "properties": {
    "tgn:hierarchy":[
        "tgn:7503738",
        "tgn:7001004",
        "tgn:1000004",
        "tgn:1000141",
        "tgn:7029392"
    ],
    "tgn:id":7503738,
    "tgn:name":"Longfeng Gong",
    "tgn:placetype":[
        "aat:300007595"
    ]
},
  "bbox": [],
  "geometry": {"coordinates":[120.505278,22.988056],"type":"Point"}
}