{
  "id": 7408193,
  "type": "Feature",
  "properties": {
    "tgn:hierarchy":[
        "tgn:7408193",
        "tgn:1000001",
        "tgn:7005590",
        "tgn:7005560",
        "tgn:7029392"
    ],
    "tgn:id":7408193,
    "tgn:name":"Estaci\u00f3n Lago Zirahuen",
    "tgn:placetype":[
        "aat:300007783"
    ]
},
  "bbox": [],
  "geometry": {"coordinates":[-101.766667,19.45],"type":"Point"}
}