{
  "id": 1053776,
  "type": "Feature",
  "properties": {
    "tgn:hierarchy":[
        "tgn:1053776",
        "tgn:7019034",
        "tgn:1000004",
        "tgn:1003406",
        "tgn:7018214",
        "tgn:7002435",
        "tgn:7029392"
    ],
    "tgn:id":1053776,
    "tgn:name":"Due",
    "tgn:placetype":[
        "aat:300008347"
    ]
},
  "bbox": [],
  "geometry": {"coordinates":[142.1667,50.8333],"type":"Point"}
}