{
  "id": 2117056,
  "type": "Feature",
  "properties": {
    "tgn:hierarchy":[
        "tgn:2117056",
        "tgn:1000001",
        "tgn:2002242",
        "tgn:7012149",
        "tgn:7007920",
        "tgn:7029392"
    ],
    "tgn:id":2117056,
    "tgn:name":"Voltage",
    "tgn:placetype":[
        "aat:300387016"
    ]
},
  "bbox": [],
  "geometry": {"coordinates":[-120.0833,47.3333],"type":"Point"}
}