{
  "id": 2455314,
  "type": "Feature",
  "properties": {
    "tgn:hierarchy":[
        "tgn:2455314",
        "tgn:7002659",
        "tgn:1000001",
        "tgn:7012149",
        "tgn:2000062",
        "tgn:7029392"
    ],
    "tgn:id":2455314,
    "tgn:name":"Little Flint Branch",
    "tgn:placetype":[
        "aat:300008699"
    ]
},
  "bbox": [],
  "geometry": {"coordinates":[-87.3667,33.1333],"type":"Point"}
}