{
  "id": 7128360,
  "type": "Feature",
  "properties": {
    "tgn:hierarchy":[
        "tgn:7128360",
        "tgn:1000003",
        "tgn:7003677",
        "tgn:7000084",
        "tgn:7029392"
    ],
    "tgn:id":7128360,
    "tgn:name":"L\u00f6rick",
    "tgn:placetype":[
        "aat:300000745"
    ]
},
  "bbox": [],
  "geometry": {"coordinates":[6.716667,51.25],"type":"Point"}
}