{
  "id": 2272115,
  "type": "Feature",
  "properties": {
    "tgn:hierarchy":[
        "tgn:2272115",
        "tgn:1000001",
        "tgn:7012149",
        "tgn:2002381",
        "tgn:7007923",
        "tgn:7029392"
    ],
    "tgn:id":2272115,
    "tgn:name":"Currant Draw",
    "tgn:placetype":[
        "aat:300008761"
    ]
},
  "bbox": [],
  "geometry": {"coordinates":[-107.35,44.8833],"type":"Point"}
}