{
  "id": 1084570,
  "type": "Feature",
  "properties": {
    "tgn:hierarchy":[
        "tgn:1084570",
        "tgn:1008634",
        "tgn:1000004",
        "tgn:1010220",
        "tgn:1001496",
        "tgn:1000135",
        "tgn:7029392"
    ],
    "tgn:id":1084570,
    "tgn:name":"Polillo",
    "tgn:placetype":[
        "aat:300008347"
    ]
},
  "bbox": [],
  "geometry": {"coordinates":[121.9333,14.7167],"type":"Point"}
}