{
  "id": 2029848,
  "type": "Feature",
  "properties": {
    "tgn:hierarchy":[
        "tgn:2029848",
        "tgn:1000001",
        "tgn:7012149",
        "tgn:1002991",
        "tgn:7007251",
        "tgn:7029392"
    ],
    "tgn:id":2029848,
    "tgn:name":"Richview",
    "tgn:placetype":[
        "aat:300008347"
    ]
},
  "bbox": [],
  "geometry": {"coordinates":[-89.1667,38.3667],"type":"Point"}
}