{
  "id": 7093859,
  "type": "Feature",
  "properties": {
    "tgn:hierarchy":[
        "tgn:7093859",
        "tgn:7000096",
        "tgn:1000003",
        "tgn:7000084",
        "tgn:7029392"
    ],
    "tgn:id":7093859,
    "tgn:name":"Seehof",
    "tgn:placetype":[
        "aat:300008347"
    ]
},
  "bbox": [],
  "geometry": {"coordinates":[14.65,51.916667],"type":"Point"}
}