{
  "id": 2488773,
  "type": "Feature",
  "properties": {
    "tgn:hierarchy":[
        "tgn:2488773",
        "tgn:1000001",
        "tgn:7012149",
        "tgn:1002548",
        "tgn:7007919",
        "tgn:7029392"
    ],
    "tgn:id":2488773,
    "tgn:name":"Mailboat Harbor",
    "tgn:placetype":[
        "aat:300132316"
    ]
},
  "bbox": [],
  "geometry": {"coordinates":[-75.9833,37.8167],"type":"Point"}
}