{
  "id": 7565407,
  "type": "Feature",
  "properties": {
    "tgn:hierarchy":[
        "tgn:7565407",
        "tgn:1000004",
        "tgn:7000198",
        "tgn:7016788",
        "tgn:7029392"
    ],
    "tgn:id":7565407,
    "tgn:name:en":"Ratan Thal",
    "tgn:placetype":[
        "aat:300008347"
    ]
},
  "bbox": [],
  "geometry": {"coordinates":[71.736283,27.74546],"type":"Point"}
}