{
  "id": 1020459,
  "type": "Feature",
  "properties": {
    "tgn:hierarchy":[
        "tgn:1020459",
        "tgn:1000525",
        "tgn:1000046",
        "tgn:1000002",
        "tgn:7029392"
    ],
    "tgn:id":1020459,
    "tgn:name":"Villa Bella",
    "tgn:placetype":[
        "aat:300008347"
    ]
},
  "bbox": [],
  "geometry": {"coordinates":[-65.3667,-10.3667],"type":"Point"}
}