{
  "id": 7188825,
  "type": "Feature",
  "properties": {
    "tgn:hierarchy":[
        "tgn:7188825",
        "tgn:1000003",
        "tgn:7003677",
        "tgn:7000084",
        "tgn:7029392"
    ],
    "tgn:id":7188825,
    "tgn:name":"Embken",
    "tgn:placetype":[
        "aat:300008347"
    ]
},
  "bbox": [],
  "geometry": {"coordinates":[6.566667,50.683333],"type":"Point"}
}