{
  "id": 2108754,
  "type": "Feature",
  "properties": {
    "tgn:hierarchy":[
        "tgn:2108754",
        "tgn:1000001",
        "tgn:2002108",
        "tgn:7012149",
        "tgn:7007827",
        "tgn:7029392"
    ],
    "tgn:id":2108754,
    "tgn:name":"Cedar",
    "tgn:placetype":[
        "aat:300387016"
    ]
},
  "bbox": [],
  "geometry": {"coordinates":[-110.45,39.3833],"type":"Point"}
}