{
  "id": 2481106,
  "type": "Feature",
  "properties": {
    "tgn:hierarchy":[
        "tgn:2481106",
        "tgn:1000001",
        "tgn:7012149",
        "tgn:2001903",
        "tgn:7007825",
        "tgn:7029392"
    ],
    "tgn:id":2481106,
    "tgn:name":"Lamb Fork Creek",
    "tgn:placetype":[
        "aat:300008706"
    ]
},
  "bbox": [],
  "geometry": {"coordinates":[-85.2333,36.3333],"type":"Point"}
}