{
  "id": 7388593,
  "type": "Feature",
  "properties": {
    "tgn:hierarchy":[
        "tgn:7388593",
        "tgn:1000001",
        "tgn:7005599",
        "tgn:7005560",
        "tgn:7029392"
    ],
    "tgn:id":7388593,
    "tgn:name":"Poxtla",
    "tgn:placetype":[
        "aat:300008347"
    ]
},
  "bbox": [],
  "geometry": {"coordinates":[-96.95,19.266667],"type":"Point"}
}