{
  "id": 1001317,
  "type": "Feature",
  "properties": {
    "tgn:hierarchy":[
        "tgn:1001317",
        "tgn:1000004",
        "tgn:1000126",
        "tgn:7029392"
    ],
    "tgn:id":1001317,
    "tgn:name":"Mont-Liban, Mohafazat",
    "tgn:placetype":[
        "aat:300387064",
        "aat:300235093"
    ]
},
  "bbox": [],
  "geometry": {"coordinates":[35.6667,33.916],"type":"Point"}
}