{
  "id": 7449411,
  "type": "Feature",
  "properties": {
    "tgn:hierarchy":[
        "tgn:7449411",
        "tgn:7002444",
        "tgn:1000003",
        "tgn:7008072",
        "tgn:7008591",
        "tgn:7029392"
    ],
    "tgn:id":7449411,
    "tgn:name:en":"Glenrath Burn",
    "tgn:placetype":[
        "aat:300008699"
    ]
},
  "bbox": [],
  "geometry": {"coordinates":[-3.25,55.583333],"type":"Point"}
}