{
  "id": 7557086,
  "type": "Feature",
  "properties": {
    "tgn:hierarchy":[
        "tgn:7557086",
        "tgn:1000004",
        "tgn:7031781",
        "tgn:7000198",
        "tgn:7029392"
    ],
    "tgn:id":7557086,
    "tgn:name:en":"Pirhap\u0101l",
    "tgn:placetype":[
        "aat:300008347"
    ]
},
  "bbox": [],
  "geometry": {"coordinates":[81.333333,20.216667],"type":"Point"}
}