{
  "id": 2453524,
  "type": "Feature",
  "properties": {
    "tgn:hierarchy":[
        "tgn:2453524",
        "tgn:1000001",
        "tgn:7012149",
        "tgn:7013961",
        "tgn:7029392"
    ],
    "tgn:id":2453524,
    "tgn:name":"Little Coal River",
    "tgn:placetype":[
        "aat:300008707"
    ]
},
  "bbox": [],
  "geometry": {"coordinates":[-81.8167,38.05],"type":"Point"}
}