<<<<<<< HEAD
{
  "id": 2763364,
  "type": "Feature",
  "properties": {
    "tgn:hierarchy":[
        "tgn:2763364",
        "tgn:1000001",
        "tgn:7012149",
        "tgn:1002521",
        "tgn:7007920",
        "tgn:7029392"
    ],
    "tgn:id":2763364,
    "tgn:name":"Wet Weather Creek",
    "tgn:placetype":[
        "aat:300008706"
    ]
},
  "bbox": [],
  "geometry": {"coordinates":[-123.0333,47.8333],"type":"Point"}
}
=======
{"geometry":{"type":"Point","coordinates":[-123.033300,47.833300]},"type":"Feature","properties":{"hierarchy":["tgn:2763364","tgn:1000001","tgn:7012149","tgn:1002521","tgn:7007920","tgn:7029392"],"placetype":["aat:300008706"],"id":2763364,"name:xx":"Wet Weather Creek"}}
>>>>>>> 03f74aca74312dbeaf24d7e61306dd6a786dc3d0
