{
  "id": 1090977,
  "type": "Feature",
  "properties": {
    "tgn:hierarchy":[
        "tgn:1090977",
        "tgn:7001242",
        "tgn:1001573",
        "tgn:1000173",
        "tgn:7029392"
    ],
    "tgn:id":1090977,
    "tgn:name":"Miarinarivo",
    "tgn:placetype":[
        "aat:300008347"
    ]
},
  "bbox": [],
  "geometry": {"coordinates":[48.25,-16.5833],"type":"Point"}
}