{
  "id": 2390338,
  "type": "Feature",
  "properties": {
    "tgn:hierarchy":[
        "tgn:2390338",
        "tgn:1000001",
        "tgn:7012149",
        "tgn:7007157",
        "tgn:1002566",
        "tgn:7029392"
    ],
    "tgn:id":2390338,
    "tgn:name":"Highland Creek",
    "tgn:placetype":[
        "aat:300008706"
    ]
},
  "bbox": [],
  "geometry": {"coordinates":[-122.95,38.95],"type":"Point"}
}