{
  "id": 7227283,
  "type": "Feature",
  "properties": {
    "tgn:hierarchy":[
        "tgn:7227283",
        "tgn:7002735",
        "tgn:7017076",
        "tgn:1000003",
        "tgn:1000074",
        "tgn:7029392"
    ],
    "tgn:id":7227283,
    "tgn:name":"K\u00e1to Koll\u00ednai",
    "tgn:placetype":[
        "aat:300008347"
    ]
},
  "bbox": [],
  "geometry": {"coordinates":[22.35,37.283333],"type":"Point"}
}