{
  "id": 7194276,
  "type": "Feature",
  "properties": {
    "tgn:hierarchy":[
        "tgn:7194276",
        "tgn:1000003",
        "tgn:7003676",
        "tgn:7000084",
        "tgn:7029392"
    ],
    "tgn:id":7194276,
    "tgn:name":"D\u00f6hlen",
    "tgn:placetype":[
        "aat:300008347"
    ]
},
  "bbox": [],
  "geometry": {"coordinates":[8.25,52.966667],"type":"Point"}
}