{
  "id": 2367900,
  "type": "Feature",
  "properties": {
    "tgn:hierarchy":[
        "tgn:2367900",
        "tgn:1000001",
        "tgn:7012149",
        "tgn:1002290",
        "tgn:7007826",
        "tgn:7029392"
    ],
    "tgn:id":2367900,
    "tgn:name":"Groves Creek",
    "tgn:placetype":[
        "aat:300008706"
    ]
},
  "bbox": [],
  "geometry": {"coordinates":[-96.3333,33.1667],"type":"Point"}
}