{
  "id": 7314578,
  "type": "Feature",
  "properties": {
    "tgn:hierarchy":[
        "tgn:7314578",
        "tgn:1001695",
        "tgn:1000049",
        "tgn:1000002",
        "tgn:7029392"
    ],
    "tgn:id":7314578,
    "tgn:name":"Las Varillas",
    "tgn:placetype":[
        "aat:300387200"
    ]
},
  "bbox": [],
  "geometry": {"coordinates":[-71.483333,-34.033333],"type":"Point"}
}