{
  "id": 2264810,
  "type": "Feature",
  "properties": {
    "tgn:hierarchy":[
        "tgn:2264810",
        "tgn:1000001",
        "tgn:7012149",
        "tgn:2001201",
        "tgn:7007523",
        "tgn:7029392"
    ],
    "tgn:id":2264810,
    "tgn:name":"Craig Lake",
    "tgn:placetype":[
        "aat:300006191"
    ]
},
  "bbox": [],
  "geometry": {"coordinates":[-94.0167,40.3833],"type":"Point"}
}