{
  "id": 2561007,
  "type": "Feature",
  "properties": {
    "tgn:hierarchy":[
        "tgn:2561007",
        "tgn:1000001",
        "tgn:2001705",
        "tgn:7012149",
        "tgn:7007708",
        "tgn:7029392"
    ],
    "tgn:id":2561007,
    "tgn:name":"Orphan Butte",
    "tgn:placetype":[
        "aat:300008798"
    ]
},
  "bbox": [],
  "geometry": {"coordinates":[-121.1167,43.7833],"type":"Point"}
}