{
  "id": 2770441,
  "type": "Feature",
  "properties": {
    "tgn:hierarchy":[
        "tgn:2770441",
        "tgn:1000001",
        "tgn:7006451",
        "tgn:2000092",
        "tgn:7012149",
        "tgn:7029392"
    ],
    "tgn:id":2770441,
    "tgn:name":"Wild Horse Spring",
    "tgn:placetype":[
        "aat:300008697"
    ]
},
  "bbox": [],
  "geometry": {"coordinates":[-112.15,35.0833],"type":"Point"}
}