<<<<<<< HEAD
{
  "id": 2156448,
  "type": "Feature",
  "properties": {
    "tgn:hierarchy":[
        "tgn:2156448",
        "tgn:1000001",
        "tgn:1002284",
        "tgn:7012149",
        "tgn:7007568",
        "tgn:7029392"
    ],
    "tgn:id":2156448,
    "tgn:name":"Beartown",
    "tgn:placetype":[
        "aat:300008347"
    ]
},
  "bbox": [],
  "geometry": {"coordinates":[-73.5667,44.75],"type":"Point"}
}
=======
{"geometry":{"type":"Point","coordinates":[-73.566700,44.750000]},"type":"Feature","properties":{"hierarchy":["tgn:2156448","tgn:1000001","tgn:1002284","tgn:7012149","tgn:7007568","tgn:7029392"],"placetype":["aat:300008347"],"id":2156448,"name:xx":"Beartown"}}
>>>>>>> 03f74aca74312dbeaf24d7e61306dd6a786dc3d0
