{
  "id": 2548472,
  "type": "Feature",
  "properties": {
    "tgn:hierarchy":[
        "tgn:2548472",
        "tgn:1000001",
        "tgn:7012149",
        "tgn:1002554",
        "tgn:7007920",
        "tgn:7029392"
    ],
    "tgn:id":2548472,
    "tgn:name":"North Luna Creek",
    "tgn:placetype":[
        "aat:300008706"
    ]
},
  "bbox": [],
  "geometry": {"coordinates":[-120.65,45.85],"type":"Point"}
}