{
  "id": 2697543,
  "type": "Feature",
  "properties": {
    "tgn:hierarchy":[
        "tgn:2697543",
        "tgn:1000001",
        "tgn:1002233",
        "tgn:7012149",
        "tgn:7007710",
        "tgn:7029392"
    ],
    "tgn:id":2697543,
    "tgn:name":"Stony Ridge",
    "tgn:placetype":[
        "aat:300266640"
    ]
},
  "bbox": [],
  "geometry": {"coordinates":[-75.5833,40.9667],"type":"Point"}
}