{
  "id": 2016002,
  "type": "Feature",
  "properties": {
    "tgn:hierarchy":[
        "tgn:2016002",
        "tgn:1000001",
        "tgn:7012149",
        "tgn:7007158",
        "tgn:2000250",
        "tgn:7029392"
    ],
    "tgn:id":2016002,
    "tgn:name":"Montezuma",
    "tgn:placetype":[
        "aat:300008347"
    ]
},
  "bbox": [],
  "geometry": {"coordinates":[-105.8667,39.5667],"type":"Point"}
}