<<<<<<< HEAD
{
  "id": 2332221,
  "type": "Feature",
  "properties": {
    "tgn:hierarchy":[
        "tgn:2332221",
        "tgn:1000001",
        "tgn:7012149",
        "tgn:7007919",
        "tgn:7029392"
    ],
    "tgn:id":2332221,
    "tgn:name":"Flippins Creek",
    "tgn:placetype":[
        "aat:300008706"
    ]
},
  "bbox": [],
  "geometry": {"coordinates":[-79.7,36.7667],"type":"Point"}
}
=======
{"geometry":{"type":"Point","coordinates":[-79.700000,36.766700]},"type":"Feature","properties":{"hierarchy":["tgn:2332221","tgn:1000001","tgn:7012149","tgn:7007919","tgn:7029392"],"placetype":["aat:300008706"],"id":2332221,"name:xx":"Flippins Creek"}}
>>>>>>> 03f74aca74312dbeaf24d7e61306dd6a786dc3d0
