{
  "id": 1083532,
  "type": "Feature",
  "properties": {
    "tgn:hierarchy":[
        "tgn:1083532",
        "tgn:1000004",
        "tgn:7000198",
        "tgn:7016883",
        "tgn:7029392"
    ],
    "tgn:id":1083532,
    "tgn:name":"K\u0101hna",
    "tgn:placetype":[
        "aat:300008347"
    ]
},
  "bbox": [],
  "geometry": {"coordinates":[74.3667,31.3667],"type":"Point"}
}