{
  "id": 2356874,
  "type": "Feature",
  "properties": {
    "tgn:hierarchy":[
        "tgn:2356874",
        "tgn:1000001",
        "tgn:7012149",
        "tgn:2001112",
        "tgn:7007522",
        "tgn:7029392"
    ],
    "tgn:id":2356874,
    "tgn:name":"Goshen Lake",
    "tgn:placetype":[
        "aat:300008680"
    ]
},
  "bbox": [],
  "geometry": {"coordinates":[-90.55,32.9333],"type":"Point"}
}