{
  "id": 1015259,
  "type": "Feature",
  "properties": {
    "tgn:hierarchy":[
        "tgn:1015259",
        "tgn:7005685",
        "tgn:1000001",
        "tgn:7005803",
        "tgn:7029392"
    ],
    "tgn:id":1015259,
    "tgn:name":"Saint Eleanor's",
    "tgn:placetype":[
        "aat:300008347"
    ]
},
  "bbox": [],
  "geometry": {"coordinates":[-63.8167,46.4167],"type":"Point"}
}