{
  "id": 2714584,
  "type": "Feature",
  "properties": {
    "tgn:hierarchy":[
        "tgn:2714584",
        "tgn:1000001",
        "tgn:1002840",
        "tgn:7012149",
        "tgn:7007828",
        "tgn:7029392"
    ],
    "tgn:id":2714584,
    "tgn:name":"Ten Kilns Brook",
    "tgn:placetype":[
        "aat:300008699"
    ]
},
  "bbox": [],
  "geometry": {"coordinates":[-72.8833,43.3667],"type":"Point"}
}