{
  "id": 2160772,
  "type": "Feature",
  "properties": {
    "tgn:hierarchy":[
        "tgn:2160772",
        "tgn:7013388",
        "tgn:1000001",
        "tgn:7012149",
        "tgn:7007517",
        "tgn:7029392"
    ],
    "tgn:id":2160772,
    "tgn:name":"Belden Hill",
    "tgn:placetype":[
        "aat:300008798"
    ]
},
  "bbox": [],
  "geometry": {"coordinates":[-73.0833,42.15],"type":"Point"}
}