{
  "id": 7393402,
  "type": "Feature",
  "properties": {
    "tgn:hierarchy":[
        "tgn:7393402",
        "tgn:7005586",
        "tgn:1000001",
        "tgn:7005560",
        "tgn:7029392"
    ],
    "tgn:id":7393402,
    "tgn:name":"San Francisco",
    "tgn:placetype":[
        "aat:300000241"
    ]
},
  "bbox": [],
  "geometry": {"coordinates":[-102.983333,19.266667],"type":"Point"}
}