{
  "id": 2536942,
  "type": "Feature",
  "properties": {
    "tgn:hierarchy":[
        "tgn:2536942",
        "tgn:1000001",
        "tgn:7012149",
        "tgn:2002372",
        "tgn:7007923",
        "tgn:7029392"
    ],
    "tgn:id":2536942,
    "tgn:name":"Needle Rock",
    "tgn:placetype":[
        "aat:300008798"
    ]
},
  "bbox": [],
  "geometry": {"coordinates":[-104.4667,41.7833],"type":"Point"}
}