{
  "id": 2716431,
  "type": "Feature",
  "properties": {
    "tgn:hierarchy":[
        "tgn:2716431",
        "tgn:1000001",
        "tgn:7006451",
        "tgn:7012149",
        "tgn:2000101",
        "tgn:7029392"
    ],
    "tgn:id":2716431,
    "tgn:name":"The Hendrickson",
    "tgn:placetype":[
        "aat:300000390"
    ]
},
  "bbox": [],
  "geometry": {"coordinates":[-110.4833,32.75],"type":"Point"}
}