{
  "id": 2614989,
  "type": "Feature",
  "properties": {
    "tgn:hierarchy":[
        "tgn:2614989",
        "tgn:7030516",
        "tgn:7006450",
        "tgn:1000001",
        "tgn:7012149",
        "tgn:7029392"
    ],
    "tgn:id":2614989,
    "tgn:name":"Repetition Point",
    "tgn:placetype":[
        "aat:300008850"
    ]
},
  "bbox": [],
  "geometry": {"coordinates":[-167.0167,53.45],"type":"Point"}
}