<<<<<<< HEAD
{
  "id": 7483555,
  "type": "Feature",
  "properties": {
    "tgn:hierarchy":[
        "tgn:7483555",
        "tgn:1000004",
        "tgn:7471332",
        "tgn:1000141",
        "tgn:7029392"
    ],
    "tgn:id":7483555,
    "tgn:name":"Baidi Qiao",
    "tgn:placetype":[
        "aat:300007836"
    ]
},
  "bbox": [],
  "geometry": {"coordinates":[120.943611,24.843611],"type":"Point"}
}
=======
{"geometry":{"type":"Point","coordinates":[120.943611,24.843611]},"type":"Feature","properties":{"hierarchy":["tgn:7483555","tgn:1000004","tgn:7471332","tgn:1000141","tgn:7029392"],"placetype":["aat:300007836"],"id":7483555,"name:xx":"Baidi Qiao"}}
>>>>>>> 03f74aca74312dbeaf24d7e61306dd6a786dc3d0
