{
  "id": 7495044,
  "type": "Feature",
  "properties": {
    "tgn:hierarchy":[
        "tgn:7495044",
        "tgn:7488858",
        "tgn:1000004",
        "tgn:1000141",
        "tgn:7029392"
    ],
    "tgn:id":7495044,
    "tgn:name":"Linzitou Qiao",
    "tgn:placetype":[
        "aat:300007836"
    ]
},
  "bbox": [],
  "geometry": {"coordinates":[120.6778,23.9686],"type":"Point"}
}