{
  "id": 7277701,
  "type": "Feature",
  "properties": {
    "tgn:hierarchy":[
        "tgn:7277701",
        "tgn:1001623",
        "tgn:1000049",
        "tgn:1000002",
        "tgn:7029392"
    ],
    "tgn:id":7277701,
    "tgn:name":"R\u00edo Santo Domingo",
    "tgn:placetype":[
        "aat:300008699"
    ]
},
  "bbox": [],
  "geometry": {"coordinates":[-73.085,-43.928333],"type":"Point"}
}