{
  "id": 2632826,
  "type": "Feature",
  "properties": {
    "tgn:hierarchy":[
        "tgn:2632826",
        "tgn:1000001",
        "tgn:7012149",
        "tgn:7007526",
        "tgn:7029392"
    ],
    "tgn:id":2632826,
    "tgn:name":"Ruby Mountain Ranger District",
    "tgn:placetype":[
        "aat:300008863"
    ]
},
  "bbox": [],
  "geometry": {"coordinates":[-115.4167,40.55],"type":"Point"}
}