{
  "id": 2512836,
  "type": "Feature",
  "properties": {
    "tgn:hierarchy":[
        "tgn:2512836",
        "tgn:1000001",
        "tgn:7012149",
        "tgn:2001553",
        "tgn:7007709",
        "tgn:7029392"
    ],
    "tgn:id":2512836,
    "tgn:name":"Mill Creek",
    "tgn:placetype":[
        "aat:300008706"
    ]
},
  "bbox": [],
  "geometry": {"coordinates":[-81.4333,36.1833],"type":"Point"}
}