{
  "id": 2043294,
  "type": "Feature",
  "properties": {
    "tgn:hierarchy":[
        "tgn:2043294",
        "tgn:1000001",
        "tgn:7012149",
        "tgn:2000909",
        "tgn:7007256",
        "tgn:7029392"
    ],
    "tgn:id":2043294,
    "tgn:name":"Litroe",
    "tgn:placetype":[
        "aat:300008347",
        "aat:300387210"
    ]
},
  "bbox": [],
  "geometry": {"coordinates":[-92.1833,32.9833],"type":"Point"}
}