{
  "id": 2342110,
  "type": "Feature",
  "properties": {
    "tgn:hierarchy":[
        "tgn:2342110",
        "tgn:1000001",
        "tgn:7012149",
        "tgn:2001444",
        "tgn:7007566",
        "tgn:7029392"
    ],
    "tgn:id":2342110,
    "tgn:name":"Fryingpan Spring",
    "tgn:placetype":[
        "aat:300008697"
    ]
},
  "bbox": [],
  "geometry": {"coordinates":[-107.6833,32.45],"type":"Point"}
}