{
  "id": 2357357,
  "type": "Feature",
  "properties": {
    "tgn:hierarchy":[
        "tgn:2357357",
        "tgn:1000001",
        "tgn:7012149",
        "tgn:2002124",
        "tgn:7007827",
        "tgn:7029392"
    ],
    "tgn:id":2357357,
    "tgn:name":"Government Creek",
    "tgn:placetype":[
        "aat:300008706"
    ]
},
  "bbox": [],
  "geometry": {"coordinates":[-109.6333,40.75],"type":"Point"}
}