{
  "id": 7431133,
  "type": "Feature",
  "properties": {
    "tgn:hierarchy":[
        "tgn:7431133",
        "tgn:1000001",
        "tgn:7005595",
        "tgn:7005560",
        "tgn:7029392"
    ],
    "tgn:id":7431133,
    "tgn:name":"El Arco",
    "tgn:placetype":[
        "aat:300008347"
    ]
},
  "bbox": [],
  "geometry": {"coordinates":[-108.183333,26.883333],"type":"Point"}
}