{
  "id": 7056311,
  "type": "Feature",
  "properties": {
    "tgn:hierarchy":[
        "tgn:7056311",
        "tgn:1003450",
        "tgn:7007850",
        "tgn:1000003",
        "tgn:1000080",
        "tgn:7029392"
    ],
    "tgn:id":7056311,
    "tgn:name":"Oliva, Fiume",
    "tgn:placetype":[
        "aat:300008699"
    ]
},
  "bbox": [],
  "geometry": {"coordinates":[16.066667,39.083333],"type":"Point"}
}