<<<<<<< HEAD
{
  "id": 7056311,
  "type": "Feature",
  "properties": {
    "tgn:hierarchy":[
        "tgn:7056311",
        "tgn:1003450",
        "tgn:7007850",
        "tgn:1000003",
        "tgn:1000080",
        "tgn:7029392"
    ],
    "tgn:id":7056311,
    "tgn:name":"Oliva, Fiume",
    "tgn:placetype":[
        "aat:300008699"
    ]
},
  "bbox": [],
  "geometry": {"coordinates":[16.066667,39.083333],"type":"Point"}
}
=======
{"geometry":{"type":"Point","coordinates":[16.066667,39.083333]},"type":"Feature","properties":{"hierarchy":["tgn:7056311","tgn:1003450","tgn:7007850","tgn:1000003","tgn:1000080","tgn:7029392"],"placetype":["aat:300008699"],"id":7056311,"name:xx":"Oliva, Fiume"}}
>>>>>>> 03f74aca74312dbeaf24d7e61306dd6a786dc3d0
