{
  "id": 2454444,
  "type": "Feature",
  "properties": {
    "tgn:hierarchy":[
        "tgn:2454444",
        "tgn:1000001",
        "tgn:7012149",
        "tgn:7016166",
        "tgn:7007523",
        "tgn:7029392"
    ],
    "tgn:id":2454444,
    "tgn:name":"Little Dardenne Creek",
    "tgn:placetype":[
        "aat:300008706"
    ]
},
  "bbox": [],
  "geometry": {"coordinates":[-90.95,38.7333],"type":"Point"}
}