{
  "id": 2657587,
  "type": "Feature",
  "properties": {
    "tgn:hierarchy":[
        "tgn:2657587",
        "tgn:1000001",
        "tgn:1002329",
        "tgn:7012149",
        "tgn:7007706",
        "tgn:7029392"
    ],
    "tgn:id":2657587,
    "tgn:name":"Shelbourne Forest",
    "tgn:placetype":[
        "aat:300008347"
    ]
},
  "bbox": [],
  "geometry": {"coordinates":[-83.0667,40.3167],"type":"Point"}
}