{
  "id": 7164771,
  "type": "Feature",
  "properties": {
    "tgn:hierarchy":[
        "tgn:7164771",
        "tgn:7003669",
        "tgn:1000003",
        "tgn:7000084",
        "tgn:7029392"
    ],
    "tgn:id":7164771,
    "tgn:name":"Hundzell",
    "tgn:placetype":[
        "aat:300008347"
    ]
},
  "bbox": [],
  "geometry": {"coordinates":[12.95,49.216667],"type":"Point"}
}