{
  "id": 2779235,
  "type": "Feature",
  "properties": {
    "tgn:hierarchy":[
        "tgn:2779235",
        "tgn:7002659",
        "tgn:1000001",
        "tgn:2000016",
        "tgn:7012149",
        "tgn:7029392"
    ],
    "tgn:id":2779235,
    "tgn:name":"Wolf Den Branch",
    "tgn:placetype":[
        "aat:300008699"
    ]
},
  "bbox": [],
  "geometry": {"coordinates":[-87.9833,34.6333],"type":"Point"}
}