{
  "id": 2007322,
  "type": "Feature",
  "properties": {
    "tgn:hierarchy":[
        "tgn:2007322",
        "tgn:1000001",
        "tgn:7006451",
        "tgn:7012149",
        "tgn:2000103",
        "tgn:7029392"
    ],
    "tgn:id":2007322,
    "tgn:name":"Seligman",
    "tgn:placetype":[
        "aat:300008347"
    ]
},
  "bbox": [],
  "geometry": {"coordinates":[-112.8667,35.3167],"type":"Point"}
}