{
  "id": 2655773,
  "type": "Feature",
  "properties": {
    "tgn:hierarchy":[
        "tgn:2655773",
        "tgn:1000001",
        "tgn:7012149",
        "tgn:7007157",
        "tgn:1002566",
        "tgn:7029392"
    ],
    "tgn:id":2655773,
    "tgn:name":"Shaul Valley",
    "tgn:placetype":[
        "aat:300386845"
    ]
},
  "bbox": [],
  "geometry": {"coordinates":[-122.7833,38.9333],"type":"Point"}
}