{
  "id": 2499641,
  "type": "Feature",
  "properties": {
    "tgn:hierarchy":[
        "tgn:2499641",
        "tgn:2000919",
        "tgn:1000001",
        "tgn:7012149",
        "tgn:7007515",
        "tgn:7029392"
    ],
    "tgn:id":2499641,
    "tgn:name":"McConnell Brook",
    "tgn:placetype":[
        "aat:300008699"
    ]
},
  "bbox": [],
  "geometry": {"coordinates":[-68.6667,46.65],"type":"Point"}
}