{
  "id": 2671790,
  "type": "Feature",
  "properties": {
    "tgn:hierarchy":[
        "tgn:2671790",
        "tgn:1000001",
        "tgn:7012149",
        "tgn:1002769",
        "tgn:7007826",
        "tgn:7029392"
    ],
    "tgn:id":2671790,
    "tgn:name":"Smith Point",
    "tgn:placetype":[
        "aat:300008850"
    ]
},
  "bbox": [],
  "geometry": {"coordinates":[-94.45,32.0333],"type":"Point"}
}