{
  "id": 2193165,
  "type": "Feature",
  "properties": {
    "tgn:hierarchy":[
        "tgn:2193165",
        "tgn:1000001",
        "tgn:7012149",
        "tgn:2001105",
        "tgn:7007522",
        "tgn:7029392"
    ],
    "tgn:id":2193165,
    "tgn:name":"Bream Lake",
    "tgn:placetype":[
        "aat:300008680"
    ]
},
  "bbox": [],
  "geometry": {"coordinates":[-88.6833,30.7833],"type":"Point"}
}