{
  "id": 7484954,
  "type": "Feature",
  "properties": {
    "tgn:hierarchy":[
        "tgn:7484954",
        "tgn:1000004",
        "tgn:7490934",
        "tgn:1000141",
        "tgn:7029392"
    ],
    "tgn:id":7484954,
    "tgn:name":"Shibiliao",
    "tgn:placetype":[
        "aat:300008347"
    ]
},
  "bbox": [],
  "geometry": {"coordinates":[120.558889,23.112778],"type":"Point"}
}