{
  "id": 7531729,
  "type": "Feature",
  "properties": {
    "tgn:hierarchy":[
        "tgn:7531729",
        "tgn:7001242",
        "tgn:7016833",
        "tgn:1001091",
        "tgn:7029392"
    ],
    "tgn:id":7531729,
    "tgn:name":"Mas\u0101kin Hay'at at Ta'\u0101wun\u012by\u0101t",
    "tgn:placetype":[
        "aat:300000745"
    ]
},
  "bbox": [],
  "geometry": {"coordinates":[31.362337,30.057469],"type":"Point"}
}