{
  "id": 7339160,
  "type": "Feature",
  "properties": {
    "tgn:hierarchy":[
        "tgn:7339160",
        "tgn:7002834",
        "tgn:1000003",
        "tgn:7002786",
        "tgn:1000095",
        "tgn:7029392"
    ],
    "tgn:id":7339160,
    "tgn:name":"Corbeiro, Punta",
    "tgn:placetype":[
        "aat:300386846"
    ]
},
  "bbox": [],
  "geometry": {"coordinates":[-8.833333,42.25],"type":"Point"}
}