{
  "id": 7497999,
  "type": "Feature",
  "properties": {
    "tgn:hierarchy":[
        "tgn:7497999",
        "tgn:1000004",
        "tgn:1000454",
        "tgn:1000141",
        "tgn:7029392"
    ],
    "tgn:id":7497999,
    "tgn:name":"Dahuge Suidao",
    "tgn:placetype":[
        "aat:300007899"
    ]
},
  "bbox": [],
  "geometry": {"coordinates":[121.697882,25.019765],"type":"Point"}
}