<<<<<<< HEAD
{
  "id": 7029655,
  "type": "Feature",
  "properties": {
    "tgn:hierarchy":[
        "tgn:7029655",
        "tgn:7002832",
        "tgn:7001158",
        "tgn:1000003",
        "tgn:1000095",
        "tgn:7029392"
    ],
    "tgn:id":7029655,
    "tgn:name":"Arconada",
    "tgn:placetype":[
        "aat:300008347"
    ]
},
  "bbox": [],
  "geometry": {"coordinates":[-3.516667,42.6],"type":"Point"}
}
=======
{"geometry":{"type":"Point","coordinates":[-3.516667,42.600000]},"type":"Feature","properties":{"hierarchy":["tgn:7029655","tgn:7002832","tgn:7001158","tgn:1000003","tgn:1000095","tgn:7029392"],"placetype":["aat:300008347"],"id":7029655,"name:xx":"Arconada"}}
>>>>>>> 03f74aca74312dbeaf24d7e61306dd6a786dc3d0
