{
  "id": 2248150,
  "type": "Feature",
  "properties": {
    "tgn:hierarchy":[
        "tgn:2248150",
        "tgn:1000001",
        "tgn:7012149",
        "tgn:2002129",
        "tgn:7007827",
        "tgn:7029392"
    ],
    "tgn:id":2248150,
    "tgn:name":"Cold Canyon",
    "tgn:placetype":[
        "aat:300008761"
    ]
},
  "bbox": [],
  "geometry": {"coordinates":[-111.9333,41.3667],"type":"Point"}
}