{
  "id": 2705783,
  "type": "Feature",
  "properties": {
    "tgn:hierarchy":[
        "tgn:2705783",
        "tgn:1000001",
        "tgn:7012149",
        "tgn:7007157",
        "tgn:1002859",
        "tgn:7029392"
    ],
    "tgn:id":2705783,
    "tgn:name":"Sutro, Mount",
    "tgn:placetype":[
        "aat:300008798"
    ]
},
  "bbox": [],
  "geometry": {"coordinates":[-122.45,37.75],"type":"Point"}
}