<<<<<<< HEAD
{
  "id": 2251549,
  "type": "Feature",
  "properties": {
    "tgn:hierarchy":[
        "tgn:2251549",
        "tgn:1000001",
        "tgn:7012149",
        "tgn:2001715",
        "tgn:7007708",
        "tgn:7029392"
    ],
    "tgn:id":2251549,
    "tgn:name":"Commodore Ridge",
    "tgn:placetype":[
        "aat:300266640"
    ]
},
  "bbox": [],
  "geometry": {"coordinates":[-120.0333,42.7167],"type":"Point"}
}
=======
{"geometry":{"type":"Point","coordinates":[-120.033300,42.716700]},"type":"Feature","properties":{"hierarchy":["tgn:2251549","tgn:1000001","tgn:7012149","tgn:2001715","tgn:7007708","tgn:7029392"],"placetype":["aat:300266640"],"id":2251549,"name:xx":"Commodore Ridge"}}
>>>>>>> 03f74aca74312dbeaf24d7e61306dd6a786dc3d0
