<<<<<<< HEAD
{
  "id": 2254859,
  "type": "Feature",
  "properties": {
    "tgn:hierarchy":[
        "tgn:2254859",
        "tgn:1000001",
        "tgn:7012149",
        "tgn:2000237",
        "tgn:7007158",
        "tgn:7029392"
    ],
    "tgn:id":2254859,
    "tgn:name":"Coons Reservoir",
    "tgn:placetype":[
        "aat:300006191"
    ]
},
  "bbox": [],
  "geometry": {"coordinates":[-107.6333,38.2667],"type":"Point"}
}
=======
{"geometry":{"type":"Point","coordinates":[-107.633300,38.266700]},"type":"Feature","properties":{"hierarchy":["tgn:2254859","tgn:1000001","tgn:7012149","tgn:2000237","tgn:7007158","tgn:7029392"],"placetype":["aat:300006191"],"id":2254859,"name:xx":"Coons Reservoir"}}
>>>>>>> 03f74aca74312dbeaf24d7e61306dd6a786dc3d0
