{
  "id": 2399393,
  "type": "Feature",
  "properties": {
    "tgn:hierarchy":[
        "tgn:2399393",
        "tgn:1000001",
        "tgn:7012149",
        "tgn:1002403",
        "tgn:7007709",
        "tgn:7029392"
    ],
    "tgn:id":2399393,
    "tgn:name":"Horn Point",
    "tgn:placetype":[
        "aat:300008850"
    ]
},
  "bbox": [],
  "geometry": {"coordinates":[-76.7333,36.3167],"type":"Point"}
}