<<<<<<< HEAD
{
  "id": 7172368,
  "type": "Feature",
  "properties": {
    "tgn:hierarchy":[
        "tgn:7172368",
        "tgn:7003669",
        "tgn:1000003",
        "tgn:7000084",
        "tgn:7029392"
    ],
    "tgn:id":7172368,
    "tgn:name":"Helmau",
    "tgn:placetype":[
        "aat:300000206"
    ]
},
  "bbox": [],
  "geometry": {"coordinates":[10.8,47.7],"type":"Point"}
}
=======
{"geometry":{"type":"Point","coordinates":[10.800000,47.700000]},"type":"Feature","properties":{"hierarchy":["tgn:7172368","tgn:7003669","tgn:1000003","tgn:7000084","tgn:7029392"],"placetype":["aat:300000206"],"id":7172368,"name:xx":"Helmau"}}
>>>>>>> 03f74aca74312dbeaf24d7e61306dd6a786dc3d0
