{
  "id": 2575704,
  "type": "Feature",
  "properties": {
    "tgn:hierarchy":[
        "tgn:2575704",
        "tgn:1000001",
        "tgn:7012149",
        "tgn:2000905",
        "tgn:7007256",
        "tgn:7029392"
    ],
    "tgn:id":2575704,
    "tgn:name":"Perch Lake",
    "tgn:placetype":[
        "aat:300008680"
    ]
},
  "bbox": [],
  "geometry": {"coordinates":[-89.6333,30.3167],"type":"Point"}
}