{
  "id": 1049267,
  "type": "Feature",
  "properties": {
    "tgn:hierarchy":[
        "tgn:1049267",
        "tgn:1000003",
        "tgn:7024118",
        "tgn:7006366",
        "tgn:7029392"
    ],
    "tgn:id":1049267,
    "tgn:name":"Mra\u031cgowo",
    "tgn:placetype":[
        "aat:300008347"
    ]
},
  "bbox": [],
  "geometry": {"coordinates":[21.3167,53.8833],"type":"Point"}
}