{
  "id": 2017587,
  "type": "Feature",
  "properties": {
    "tgn:hierarchy":[
        "tgn:2017587",
        "tgn:1000001",
        "tgn:1002461",
        "tgn:7012149",
        "tgn:7007159",
        "tgn:7029392"
    ],
    "tgn:id":2017587,
    "tgn:name":"West Suffield",
    "tgn:placetype":[
        "aat:300008347"
    ]
},
  "bbox": [],
  "geometry": {"coordinates":[-72.6833,41.9833],"type":"Point"}
}