{
  "id": 7221291,
  "type": "Feature",
  "properties": {
    "tgn:hierarchy":[
        "tgn:7221291",
        "tgn:7002715",
        "tgn:7002731",
        "tgn:1000003",
        "tgn:1000074",
        "tgn:7029392"
    ],
    "tgn:id":7221291,
    "tgn:name":"\u00c1gia Sof\u00eda",
    "tgn:placetype":[
        "aat:300007466"
    ]
},
  "bbox": [],
  "geometry": {"coordinates":[22.947018,40.632821],"type":"Point"}
}