{
  "id": 7521729,
  "type": "Feature",
  "properties": {
    "tgn:hierarchy":[
        "tgn:7521729",
        "tgn:7001242",
        "tgn:7016833",
        "tgn:1001418",
        "tgn:7029392"
    ],
    "tgn:id":7521729,
    "tgn:name:en":"Ab\u016b Lahw, Ra's",
    "tgn:placetype":[
        "aat:300386846"
    ]
},
  "bbox": [],
  "geometry": {"coordinates":[27.003265,31.427047],"type":"Point"}
}