{
  "id": 2655442,
  "type": "Feature",
  "properties": {
    "tgn:hierarchy":[
        "tgn:2655442",
        "tgn:1000001",
        "tgn:7012149",
        "tgn:2002118",
        "tgn:7007827",
        "tgn:7029392"
    ],
    "tgn:id":2655442,
    "tgn:name":"Sharp",
    "tgn:placetype":[
        "aat:300008347"
    ]
},
  "bbox": [],
  "geometry": {"coordinates":[-111.9167,40.7167],"type":"Point"}
}