<<<<<<< HEAD
{
  "id": 2765112,
  "type": "Feature",
  "properties": {
    "tgn:hierarchy":[
        "tgn:2765112",
        "tgn:1000001",
        "tgn:7012149",
        "tgn:2001929",
        "tgn:7007825",
        "tgn:7029392"
    ],
    "tgn:id":2765112,
    "tgn:name":"Whispering Hills",
    "tgn:placetype":[
        "aat:300008347"
    ]
},
  "bbox": [],
  "geometry": {"coordinates":[-85.4667,35.95],"type":"Point"}
}
=======
{"geometry":{"type":"Point","coordinates":[-85.466700,35.950000]},"type":"Feature","properties":{"hierarchy":["tgn:2765112","tgn:1000001","tgn:7012149","tgn:2001929","tgn:7007825","tgn:7029392"],"placetype":["aat:300008347"],"id":2765112,"name:xx":"Whispering Hills"}}
>>>>>>> 03f74aca74312dbeaf24d7e61306dd6a786dc3d0
