{
  "id": 2310813,
  "type": "Feature",
  "properties": {
    "tgn:hierarchy":[
        "tgn:2310813",
        "tgn:1000001",
        "tgn:7012149",
        "tgn:1002886",
        "tgn:7007252",
        "tgn:7029392"
    ],
    "tgn:id":2310813,
    "tgn:name":"Ed Clark Ditch",
    "tgn:placetype":[
        "aat:300006075"
    ]
},
  "bbox": [],
  "geometry": {"coordinates":[-85.8167,39.55],"type":"Point"}
}