{
  "id": 2495640,
  "type": "Feature",
  "properties": {
    "tgn:hierarchy":[
        "tgn:2495640",
        "tgn:1000001",
        "tgn:2000308",
        "tgn:7012149",
        "tgn:7007248",
        "tgn:7029392"
    ],
    "tgn:id":2495640,
    "tgn:name":"Mash Pond",
    "tgn:placetype":[
        "aat:300006191"
    ]
},
  "bbox": [],
  "geometry": {"coordinates":[-81.6833,33.0667],"type":"Point"}
}