{
  "id": 1081418,
  "type": "Feature",
  "properties": {
    "tgn:hierarchy":[
        "tgn:1081418",
        "tgn:7016687",
        "tgn:1000004",
        "tgn:7000893",
        "tgn:1000120",
        "tgn:7029392"
    ],
    "tgn:id":1081418,
    "tgn:name":"T\u014dno",
    "tgn:placetype":[
        "aat:300008347"
    ]
},
  "bbox": [],
  "geometry": {"coordinates":[141.5167,39.3333],"type":"Point"}
}