{
  "id": 2542303,
  "type": "Feature",
  "properties": {
    "tgn:hierarchy":[
        "tgn:2542303",
        "tgn:1000001",
        "tgn:7012149",
        "tgn:2001922",
        "tgn:7007825",
        "tgn:7029392"
    ],
    "tgn:id":2542303,
    "tgn:name":"No Business Knob",
    "tgn:placetype":[
        "aat:300008798"
    ]
},
  "bbox": [],
  "geometry": {"coordinates":[-82.4333,36.05],"type":"Point"}
}