{
  "id": 1050950,
  "type": "Feature",
  "properties": {
    "tgn:hierarchy":[
        "tgn:1050950",
        "tgn:7002444",
        "tgn:7008074",
        "tgn:1000003",
        "tgn:7008591",
        "tgn:7029392"
    ],
    "tgn:id":1050950,
    "tgn:name:en":"New Abbey",
    "tgn:placetype":[
        "aat:300008347"
    ]
},
  "bbox": [],
  "geometry": {"coordinates":[-3.616667,54.983333],"type":"Point"}
}