{
  "id": 2467933,
  "type": "Feature",
  "properties": {
    "tgn:hierarchy":[
        "tgn:2467933",
        "tgn:2000945",
        "tgn:1000001",
        "tgn:7012149",
        "tgn:7007520",
        "tgn:7029392"
    ],
    "tgn:id":2467933,
    "tgn:name":"Long Lake",
    "tgn:placetype":[
        "aat:300008680"
    ]
},
  "bbox": [],
  "geometry": {"coordinates":[-84.85,45.05],"type":"Point"}
}