{
  "id": 2615177,
  "type": "Feature",
  "properties": {
    "tgn:hierarchy":[
        "tgn:2615177",
        "tgn:2000297",
        "tgn:1000001",
        "tgn:7012149",
        "tgn:7007248",
        "tgn:7029392"
    ],
    "tgn:id":2615177,
    "tgn:name":"Reservoir 33",
    "tgn:placetype":[
        "aat:300006191"
    ]
},
  "bbox": [],
  "geometry": {"coordinates":[-83.5167,34.25],"type":"Point"}
}