<<<<<<< HEAD
{
  "id": 7173523,
  "type": "Feature",
  "properties": {
    "tgn:hierarchy":[
        "tgn:7173523",
        "tgn:1000003",
        "tgn:7003689",
        "tgn:7000084",
        "tgn:7029392"
    ],
    "tgn:id":7173523,
    "tgn:name":"Gro\u00dfbreitenbach",
    "tgn:placetype":[
        "aat:300008347"
    ]
},
  "bbox": [],
  "geometry": {"coordinates":[11.033333,50.583333],"type":"Point"}
}
=======
{"geometry":{"type":"Point","coordinates":[11.033333,50.583333]},"type":"Feature","properties":{"hierarchy":["tgn:7173523","tgn:1000003","tgn:7003689","tgn:7000084","tgn:7029392"],"placetype":["aat:300008347"],"id":7173523,"name:xx":"Gro\u00dfbreitenbach"}}
>>>>>>> 03f74aca74312dbeaf24d7e61306dd6a786dc3d0
