{
  "id": 2006178,
  "type": "Feature",
  "properties": {
    "tgn:hierarchy":[
        "tgn:2006178",
        "tgn:7006450",
        "tgn:1000001",
        "tgn:7012149",
        "tgn:2124014",
        "tgn:7029392"
    ],
    "tgn:id":2006178,
    "tgn:name":"Kiana",
    "tgn:placetype":[
        "aat:300008347"
    ]
},
  "bbox": [],
  "geometry": {"coordinates":[-160.4167,66.9667],"type":"Point"}
}