{
  "id": 7469174,
  "type": "Feature",
  "properties": {
    "tgn:hierarchy":[
        "tgn:7469174",
        "tgn:7001001",
        "tgn:1000004",
        "tgn:1000141",
        "tgn:7029392"
    ],
    "tgn:id":7469174,
    "tgn:name":"Niuchouxi",
    "tgn:placetype":[
        "aat:300008347"
    ]
},
  "bbox": [],
  "geometry": {"coordinates":[120.425476,23.510168],"type":"Point"}
}