<<<<<<< HEAD
{
  "id": 7477422,
  "type": "Feature",
  "properties": {
    "tgn:hierarchy":[
        "tgn:7477422",
        "tgn:7001010",
        "tgn:1000004",
        "tgn:1000141",
        "tgn:7029392"
    ],
    "tgn:id":7477422,
    "tgn:name":"Qingshui Xi Qiao",
    "tgn:placetype":[
        "aat:300007836"
    ]
},
  "bbox": [],
  "geometry": {"coordinates":[121.439579,23.800211],"type":"Point"}
}
=======
{"geometry":{"type":"Point","coordinates":[121.439579,23.800211]},"type":"Feature","properties":{"hierarchy":["tgn:7477422","tgn:7001010","tgn:1000004","tgn:1000141","tgn:7029392"],"placetype":["aat:300007836"],"id":7477422,"name:xx":"Qingshui Xi Qiao"}}
>>>>>>> 03f74aca74312dbeaf24d7e61306dd6a786dc3d0
