{
  "id": 7466658,
  "type": "Feature",
  "properties": {
    "tgn:hierarchy":[
        "tgn:7466658",
        "tgn:7008696",
        "tgn:7002448",
        "tgn:1000003",
        "tgn:7008591",
        "tgn:7029392"
    ],
    "tgn:id":7466658,
    "tgn:name:en":"Annamoy House",
    "tgn:placetype":[
        "aat:300004792"
    ]
},
  "bbox": [],
  "geometry": {"coordinates":[-6.716667,54.383333],"type":"Point"}
}