{
  "id": 1012295,
  "type": "Feature",
  "properties": {
    "tgn:hierarchy":[
        "tgn:1012295",
        "tgn:7000406",
        "tgn:1000004",
        "tgn:1000110",
        "tgn:7029392"
    ],
    "tgn:id":1012295,
    "tgn:name":"Pedro Point",
    "tgn:placetype":[
        "aat:300386846"
    ]
},
  "bbox": [],
  "geometry": {"coordinates":[-80.2333,9.8333],"type":"Point"}
}