{
  "id": 7167713,
  "type": "Feature",
  "properties": {
    "tgn:hierarchy":[
        "tgn:7167713",
        "tgn:7003669",
        "tgn:1000003",
        "tgn:7000084",
        "tgn:7029392"
    ],
    "tgn:id":7167713,
    "tgn:name":"Heimenhalden",
    "tgn:placetype":[
        "aat:300000206"
    ]
},
  "bbox": [],
  "geometry": {"coordinates":[10.45,47.833333],"type":"Point"}
}