{
  "id": 7071397,
  "type": "Feature",
  "properties": {
    "tgn:hierarchy":[
        "tgn:7071397",
        "tgn:7003669",
        "tgn:1000003",
        "tgn:7000084",
        "tgn:7029392"
    ],
    "tgn:id":7071397,
    "tgn:name":"St\u00fcckstein",
    "tgn:placetype":[
        "aat:300008795"
    ]
},
  "bbox": [],
  "geometry": {"coordinates":[12.533333,49.533333],"type":"Point"}
}