{
  "id": 7193781,
  "type": "Feature",
  "properties": {
    "tgn:hierarchy":[
        "tgn:7193781",
        "tgn:7003692",
        "tgn:1000003",
        "tgn:7000084",
        "tgn:7029392"
    ],
    "tgn:id":7193781,
    "tgn:name":"Fischreute",
    "tgn:placetype":[
        "aat:300000206"
    ]
},
  "bbox": [],
  "geometry": {"coordinates":[9.85,47.75],"type":"Point"}
}