{
  "id": 7391848,
  "type": "Feature",
  "properties": {
    "tgn:hierarchy":[
        "tgn:7391848",
        "tgn:1000001",
        "tgn:1001960",
        "tgn:7005560",
        "tgn:7029392"
    ],
    "tgn:id":7391848,
    "tgn:name":"Rancho Tiznado",
    "tgn:placetype":[
        "aat:300008347"
    ]
},
  "bbox": [],
  "geometry": {"coordinates":[-112.033333,30.683333],"type":"Point"}
}