{
  "id": 7219425,
  "type": "Feature",
  "properties": {
    "tgn:hierarchy":[
        "tgn:7219425",
        "tgn:7011330",
        "tgn:7002674",
        "tgn:1000003",
        "tgn:1000074",
        "tgn:7029392"
    ],
    "tgn:id":7219425,
    "tgn:name":"Bal\u00e1mou, Vrachonis\u00eddes",
    "tgn:placetype":[
        "aat:300011692"
    ]
},
  "bbox": [],
  "geometry": {"coordinates":[26.597222,37.365278],"type":"Point"}
}