{
  "id": 2042841,
  "type": "Feature",
  "properties": {
    "tgn:hierarchy":[
        "tgn:2042841",
        "tgn:1000001",
        "tgn:7012149",
        "tgn:2000904",
        "tgn:7007256",
        "tgn:7029392"
    ],
    "tgn:id":2042841,
    "tgn:name":"Garden City",
    "tgn:placetype":[
        "aat:300008347"
    ]
},
  "bbox": [],
  "geometry": {"coordinates":[-91.45,29.75],"type":"Point"}
}