{
  "id": 2687971,
  "type": "Feature",
  "properties": {
    "tgn:hierarchy":[
        "tgn:2687971",
        "tgn:1000001",
        "tgn:7012149",
        "tgn:1002942",
        "tgn:7007920",
        "tgn:7029392"
    ],
    "tgn:id":2687971,
    "tgn:name":"Springer Lake",
    "tgn:placetype":[
        "aat:300008680"
    ]
},
  "bbox": [],
  "geometry": {"coordinates":[-122.8667,46.9333],"type":"Point"}
}