<<<<<<< HEAD
{
  "id": 7358833,
  "type": "Feature",
  "properties": {
    "tgn:hierarchy":[
        "tgn:7358833",
        "tgn:7005581",
        "tgn:1000001",
        "tgn:7005560",
        "tgn:7029392"
    ],
    "tgn:id":7358833,
    "tgn:name":"Colorado, Cerro",
    "tgn:placetype":[
        "aat:300008795"
    ]
},
  "bbox": [],
  "geometry": {"coordinates":[-106.0,26.916667],"type":"Point"}
}
=======
{"geometry":{"type":"Point","coordinates":[-106.000000,26.916667]},"type":"Feature","properties":{"hierarchy":["tgn:7358833","tgn:7005581","tgn:1000001","tgn:7005560","tgn:7029392"],"placetype":["aat:300008795"],"id":7358833,"name:xx":"Colorado, Cerro"}}
>>>>>>> 03f74aca74312dbeaf24d7e61306dd6a786dc3d0
