{
  "id": 7131063,
  "type": "Feature",
  "properties": {
    "tgn:hierarchy":[
        "tgn:7131063",
        "tgn:1000003",
        "tgn:7003687",
        "tgn:7000084",
        "tgn:7029392"
    ],
    "tgn:id":7131063,
    "tgn:name":"Markfriedersdorf",
    "tgn:placetype":[
        "aat:300000206"
    ]
},
  "bbox": [],
  "geometry": {"coordinates":[12.916667,51.916667],"type":"Point"}
}