{
  "id": 7299618,
  "type": "Feature",
  "properties": {
    "tgn:hierarchy":[
        "tgn:7299618",
        "tgn:7002822",
        "tgn:1001647",
        "tgn:1000003",
        "tgn:1000095",
        "tgn:7029392"
    ],
    "tgn:id":7299618,
    "tgn:name":"Valderrebollo",
    "tgn:placetype":[
        "aat:300008347"
    ]
},
  "bbox": [],
  "geometry": {"coordinates":[-2.716667,40.816667],"type":"Point"}
}