<<<<<<< HEAD
{
  "id": 7357026,
  "type": "Feature",
  "properties": {
    "tgn:hierarchy":[
        "tgn:7357026",
        "tgn:1000001",
        "tgn:7005591",
        "tgn:7005560",
        "tgn:7029392"
    ],
    "tgn:id":7357026,
    "tgn:name":"Chiquito, R\u00edo",
    "tgn:placetype":[
        "aat:300008699"
    ]
},
  "bbox": [],
  "geometry": {"coordinates":[-95.883333,17.666667],"type":"Point"}
}
=======
{"geometry":{"type":"Point","coordinates":[-95.883333,17.666667]},"type":"Feature","properties":{"hierarchy":["tgn:7357026","tgn:1000001","tgn:7005591","tgn:7005560","tgn:7029392"],"placetype":["aat:300008699"],"id":7357026,"name:xx":"Chiquito, R\u00edo"}}
>>>>>>> 03f74aca74312dbeaf24d7e61306dd6a786dc3d0
