{
  "id": 7288412,
  "type": "Feature",
  "properties": {
    "tgn:hierarchy":[
        "tgn:7288412",
        "tgn:7002464",
        "tgn:1000049",
        "tgn:1000002",
        "tgn:7029392"
    ],
    "tgn:id":7288412,
    "tgn:name":"Huinchuta, Cerro",
    "tgn:placetype":[
        "aat:300008795"
    ]
},
  "bbox": [],
  "geometry": {"coordinates":[-69.033333,-19.083333],"type":"Point"}
}