{
  "id": 2528493,
  "type": "Feature",
  "properties": {
    "tgn:hierarchy":[
        "tgn:2528493",
        "tgn:1000001",
        "tgn:7012149",
        "tgn:2001868",
        "tgn:7007825",
        "tgn:7029392"
    ],
    "tgn:id":2528493,
    "tgn:name":"Moyer Branch",
    "tgn:placetype":[
        "aat:300008699"
    ]
},
  "bbox": [],
  "geometry": {"coordinates":[-83.3333,36.2167],"type":"Point"}
}