{
  "id": 2470678,
  "type": "Feature",
  "properties": {
    "tgn:hierarchy":[
        "tgn:2470678",
        "tgn:1000001",
        "tgn:1002347",
        "tgn:7012149",
        "tgn:7007568",
        "tgn:7029392"
    ],
    "tgn:id":2470678,
    "tgn:name":"Lossing Hill",
    "tgn:placetype":[
        "aat:300008798"
    ]
},
  "bbox": [],
  "geometry": {"coordinates":[-73.5833,41.7167],"type":"Point"}
}