{
  "id": 7458076,
  "type": "Feature",
  "properties": {
    "tgn:hierarchy":[
        "tgn:7458076",
        "tgn:7002445",
        "tgn:7008114",
        "tgn:1000003",
        "tgn:7008591",
        "tgn:7029392"
    ],
    "tgn:id":7458076,
    "tgn:name:en":"Norcott Brook",
    "tgn:placetype":[
        "aat:300000206"
    ]
},
  "bbox": [],
  "geometry": {"coordinates":[-2.583333,53.316667],"type":"Point"}
}