{
  "id": 1037343,
  "type": "Feature",
  "properties": {
    "tgn:hierarchy":[
        "tgn:1037343",
        "tgn:1000003",
        "tgn:7000094",
        "tgn:7000084",
        "tgn:7029392"
    ],
    "tgn:id":1037343,
    "tgn:name":"Neu Kaliss",
    "tgn:placetype":[
        "aat:300008347"
    ]
},
  "bbox": [],
  "geometry": {"coordinates":[11.3167,53.1833],"type":"Point"}
}