{
  "id": 2311785,
  "type": "Feature",
  "properties": {
    "tgn:hierarchy":[
        "tgn:2311785",
        "tgn:7002659",
        "tgn:1000001",
        "tgn:2000007",
        "tgn:7012149",
        "tgn:7029392"
    ],
    "tgn:id":2311785,
    "tgn:name":"Edwards Spring",
    "tgn:placetype":[
        "aat:300008697"
    ]
},
  "bbox": [],
  "geometry": {"coordinates":[-85.7667,33.8333],"type":"Point"}
}