<<<<<<< HEAD
{
  "id": 7110634,
  "type": "Feature",
  "properties": {
    "tgn:hierarchy":[
        "tgn:7110634",
        "tgn:1000003",
        "tgn:7003685",
        "tgn:7000084",
        "tgn:7029392"
    ],
    "tgn:id":7110634,
    "tgn:name":"P\u00fclswerda",
    "tgn:placetype":[
        "aat:300008347"
    ]
},
  "bbox": [],
  "geometry": {"coordinates":[13.066667,51.533333],"type":"Point"}
}
=======
{"geometry":{"type":"Point","coordinates":[13.066667,51.533333]},"type":"Feature","properties":{"hierarchy":["tgn:7110634","tgn:1000003","tgn:7003685","tgn:7000084","tgn:7029392"],"placetype":["aat:300008347"],"id":7110634,"name:xx":"P\u00fclswerda"}}
>>>>>>> 03f74aca74312dbeaf24d7e61306dd6a786dc3d0
