{
  "id": 2627333,
  "type": "Feature",
  "properties": {
    "tgn:hierarchy":[
        "tgn:2627333",
        "tgn:1002165",
        "tgn:1000001",
        "tgn:7012149",
        "tgn:7007517",
        "tgn:7029392"
    ],
    "tgn:id":2627333,
    "tgn:name":"Rodgers Shoal",
    "tgn:placetype":[
        "aat:300132348"
    ]
},
  "bbox": [],
  "geometry": {"coordinates":[-70.0167,41.55],"type":"Point"}
}