<<<<<<< HEAD
{
  "id": 7244565,
  "type": "Feature",
  "properties": {
    "tgn:hierarchy":[
        "tgn:7244565",
        "tgn:7003466",
        "tgn:1000003",
        "tgn:1000063",
        "tgn:4012014",
        "tgn:7029392"
    ],
    "tgn:id":7244565,
    "tgn:name":"Lesve",
    "tgn:placetype":[
        "aat:300008347"
    ]
},
  "bbox": [],
  "geometry": {"coordinates":[4.779223,50.375336],"type":"Point"}
}
=======
{"geometry":{"type":"Point","coordinates":[4.779223,50.375336]},"type":"Feature","properties":{"hierarchy":["tgn:7244565","tgn:7003466","tgn:1000003","tgn:1000063","tgn:4012014","tgn:7029392"],"placetype":["aat:300008347"],"id":7244565,"name:xx":"Lesve"}}
>>>>>>> 03f74aca74312dbeaf24d7e61306dd6a786dc3d0
