{
  "id": 2268784,
  "type": "Feature",
  "properties": {
    "tgn:hierarchy":[
        "tgn:2268784",
        "tgn:1000001",
        "tgn:7012149",
        "tgn:2000907",
        "tgn:7007256",
        "tgn:7029392"
    ],
    "tgn:id":2268784,
    "tgn:name":"Cross Keys",
    "tgn:placetype":[
        "aat:300008347"
    ]
},
  "bbox": [],
  "geometry": {"coordinates":[-91.35,31.8833],"type":"Point"}
}