{
  "id": 7527630,
  "type": "Feature",
  "properties": {
    "tgn:hierarchy":[
        "tgn:7527630",
        "tgn:7001242",
        "tgn:7001311",
        "tgn:7016833",
        "tgn:7029392"
    ],
    "tgn:id":7527630,
    "tgn:name:en":"Umm Ajaw\u012bsh, Juzur",
    "tgn:placetype":[
        "aat:300008791"
    ]
},
  "bbox": [],
  "geometry": {"coordinates":[33.866667,27.15],"type":"Point"}
}