{
  "id": 7172127,
  "type": "Feature",
  "properties": {
    "tgn:hierarchy":[
        "tgn:7172127",
        "tgn:7003692",
        "tgn:1000003",
        "tgn:7000084",
        "tgn:7029392"
    ],
    "tgn:id":7172127,
    "tgn:name":"Helmsheim",
    "tgn:placetype":[
        "aat:300008347"
    ]
},
  "bbox": [],
  "geometry": {"coordinates":[8.6425,49.085278],"type":"Point"}
}