{
  "id": 2516406,
  "type": "Feature",
  "properties": {
    "tgn:hierarchy":[
        "tgn:2516406",
        "tgn:1000001",
        "tgn:2000199",
        "tgn:7012149",
        "tgn:7007158",
        "tgn:7029392"
    ],
    "tgn:id":2516406,
    "tgn:name":"Mineral Basin",
    "tgn:placetype":[
        "aat:300386845"
    ]
},
  "bbox": [],
  "geometry": {"coordinates":[-106.3833,38.75],"type":"Point"}
}