{
  "id": 7051163,
  "type": "Feature",
  "properties": {
    "tgn:hierarchy":[
        "tgn:7051163",
        "tgn:1003460",
        "tgn:1000003",
        "tgn:7009760",
        "tgn:1000080",
        "tgn:7029392"
    ],
    "tgn:id":7051163,
    "tgn:name":"Nebbiello, Monte",
    "tgn:placetype":[
        "aat:300008777"
    ]
},
  "bbox": [],
  "geometry": {"coordinates":[11.333333,42.466667],"type":"Point"}
}