{
  "id": 2263446,
  "type": "Feature",
  "properties": {
    "tgn:hierarchy":[
        "tgn:2263446",
        "tgn:1000001",
        "tgn:7012149",
        "tgn:2000403",
        "tgn:7007248",
        "tgn:7029392"
    ],
    "tgn:id":2263446,
    "tgn:name":"Cox Mountain",
    "tgn:placetype":[
        "aat:300008798"
    ]
},
  "bbox": [],
  "geometry": {"coordinates":[-84.2833,34.4333],"type":"Point"}
}