{
  "id": 2276010,
  "type": "Feature",
  "properties": {
    "tgn:hierarchy":[
        "tgn:2276010",
        "tgn:1000001",
        "tgn:2000470",
        "tgn:7012149",
        "tgn:7007250",
        "tgn:7029392"
    ],
    "tgn:id":2276010,
    "tgn:name":"Darling Creek",
    "tgn:placetype":[
        "aat:300008706"
    ]
},
  "bbox": [],
  "geometry": {"coordinates":[-114.35,44.6667],"type":"Point"}
}