{
  "id": 2267572,
  "type": "Feature",
  "properties": {
    "tgn:hierarchy":[
        "tgn:2267572",
        "tgn:1000001",
        "tgn:7012149",
        "tgn:1003026",
        "tgn:7007826",
        "tgn:7029392"
    ],
    "tgn:id":2267572,
    "tgn:name":"Crockett Gardens",
    "tgn:placetype":[
        "aat:300055621"
    ]
},
  "bbox": [],
  "geometry": {"coordinates":[-97.75,30.65],"type":"Point"}
}