{
  "id": 2242645,
  "type": "Feature",
  "properties": {
    "tgn:hierarchy":[
        "tgn:2242645",
        "tgn:1000001",
        "tgn:7012149",
        "tgn:2000911",
        "tgn:7007256",
        "tgn:7029392"
    ],
    "tgn:id":2242645,
    "tgn:name":"Clear Creek",
    "tgn:placetype":[
        "aat:300008706"
    ]
},
  "bbox": [],
  "geometry": {"coordinates":[-93.4167,30.9833],"type":"Point"}
}