{
  "id": 2425990,
  "type": "Feature",
  "properties": {
    "tgn:hierarchy":[
        "tgn:2425990",
        "tgn:1000001",
        "tgn:7012149",
        "tgn:1002862",
        "tgn:7007920",
        "tgn:7029392"
    ],
    "tgn:id":2425990,
    "tgn:name":"Jones Bay",
    "tgn:placetype":[
        "aat:300132316"
    ]
},
  "bbox": [],
  "geometry": {"coordinates":[-122.8833,48.4333],"type":"Point"}
}