{
  "id": 7156874,
  "type": "Feature",
  "properties": {
    "tgn:hierarchy":[
        "tgn:7156874",
        "tgn:7003692",
        "tgn:1000003",
        "tgn:7000084",
        "tgn:7029392"
    ],
    "tgn:id":7156874,
    "tgn:name":"Killer",
    "tgn:placetype":[
        "aat:300008347"
    ]
},
  "bbox": [],
  "geometry": {"coordinates":[9.066667,48.316667],"type":"Point"}
}