{
  "id": 2629824,
  "type": "Feature",
  "properties": {
    "tgn:hierarchy":[
        "tgn:2629824",
        "tgn:1000001",
        "tgn:7012149",
        "tgn:2000474",
        "tgn:7007250",
        "tgn:7029392"
    ],
    "tgn:id":2629824,
    "tgn:name":"Ross Island",
    "tgn:placetype":[
        "aat:300008791"
    ]
},
  "bbox": [],
  "geometry": {"coordinates":[-116.4833,43.8667],"type":"Point"}
}