<<<<<<< HEAD
{
  "id": 7114325,
  "type": "Feature",
  "properties": {
    "tgn:hierarchy":[
        "tgn:7114325",
        "tgn:1000003",
        "tgn:7003676",
        "tgn:7000084",
        "tgn:7029392"
    ],
    "tgn:id":7114325,
    "tgn:name":"R\u00f6cke",
    "tgn:placetype":[
        "aat:300008347"
    ]
},
  "bbox": [],
  "geometry": {"coordinates":[9.0,52.266667],"type":"Point"}
}
=======
{"geometry":{"type":"Point","coordinates":[9.000000,52.266667]},"type":"Feature","properties":{"hierarchy":["tgn:7114325","tgn:1000003","tgn:7003676","tgn:7000084","tgn:7029392"],"placetype":["aat:300008347"],"id":7114325,"name:xx":"R\u00f6cke"}}
>>>>>>> 03f74aca74312dbeaf24d7e61306dd6a786dc3d0
