{
  "id": 2437720,
  "type": "Feature",
  "properties": {
    "tgn:hierarchy":[
        "tgn:2437720",
        "tgn:2000945",
        "tgn:1000001",
        "tgn:7012149",
        "tgn:7007520",
        "tgn:7029392"
    ],
    "tgn:id":2437720,
    "tgn:name":"King Creek",
    "tgn:placetype":[
        "aat:300008706"
    ]
},
  "bbox": [],
  "geometry": {"coordinates":[-85.2833,45.1667],"type":"Point"}
}