{
  "id": 7002861,
  "type": "Feature",
  "properties": {
    "tgn:hierarchy":[
        "tgn:7002861",
        "tgn:1001084",
        "tgn:1000004",
        "tgn:1000126",
        "tgn:7029392"
    ],
    "tgn:id":7002861,
    "tgn:name:en":"Sidon",
    "tgn:placetype":[
        "aat:300008347",
        "aat:300008389",
        "aat:300387235",
        "aat:300387220",
        "aat:300120599",
        "aat:300387286"
    ]
},
  "bbox": [],
  "geometry": {"coordinates":[35.3667,33.55],"type":"Point"}
}