{
  "id": 7226462,
  "type": "Feature",
  "properties": {
    "tgn:hierarchy":[
        "tgn:7226462",
        "tgn:7002743",
        "tgn:7017076",
        "tgn:1000003",
        "tgn:1000074",
        "tgn:7029392"
    ],
    "tgn:id":7226462,
    "tgn:name":"S\u00f3stion",
    "tgn:placetype":[
        "aat:300008347"
    ]
},
  "bbox": [],
  "geometry": {"coordinates":[21.35,37.866667],"type":"Point"}
}