{
  "id": 2486930,
  "type": "Feature",
  "properties": {
    "tgn:hierarchy":[
        "tgn:2486930",
        "tgn:1002933",
        "tgn:1000001",
        "tgn:7012149",
        "tgn:7007239",
        "tgn:7029392"
    ],
    "tgn:id":2486930,
    "tgn:name":"Lee Joseph Creek",
    "tgn:placetype":[
        "aat:300008706"
    ]
},
  "bbox": [],
  "geometry": {"coordinates":[-75.1167,38.6167],"type":"Point"}
}