<<<<<<< HEAD
{
  "id": 2765449,
  "type": "Feature",
  "properties": {
    "tgn:hierarchy":[
        "tgn:2765449",
        "tgn:1000001",
        "tgn:7012149",
        "tgn:1002837",
        "tgn:7007255",
        "tgn:7029392"
    ],
    "tgn:id":2765449,
    "tgn:name":"White Branch",
    "tgn:placetype":[
        "aat:300008699"
    ]
},
  "bbox": [],
  "geometry": {"coordinates":[-83.3667,38.3],"type":"Point"}
}
=======
{"geometry":{"type":"Point","coordinates":[-83.366700,38.300000]},"type":"Feature","properties":{"hierarchy":["tgn:2765449","tgn:1000001","tgn:7012149","tgn:1002837","tgn:7007255","tgn:7029392"],"placetype":["aat:300008699"],"id":2765449,"name:xx":"White Branch"}}
>>>>>>> 03f74aca74312dbeaf24d7e61306dd6a786dc3d0
