{
  "id": 7481159,
  "type": "Feature",
  "properties": {
    "tgn:hierarchy":[
        "tgn:7481159",
        "tgn:1000004",
        "tgn:7492971",
        "tgn:1000141",
        "tgn:7029392"
    ],
    "tgn:id":7481159,
    "tgn:name":"Fenyang Xincun",
    "tgn:placetype":[
        "aat:300000498"
    ]
},
  "bbox": [],
  "geometry": {"coordinates":[120.62247,22.696696],"type":"Point"}
}