<<<<<<< HEAD
{
  "id": 2760185,
  "type": "Feature",
  "properties": {
    "tgn:hierarchy":[
        "tgn:2760185",
        "tgn:1000001",
        "tgn:7012149",
        "tgn:2001717",
        "tgn:7007708",
        "tgn:7029392"
    ],
    "tgn:id":2760185,
    "tgn:name":"West Fork Quartzville Creek",
    "tgn:placetype":[
        "aat:300008706"
    ]
},
  "bbox": [],
  "geometry": {"coordinates":[-122.4333,44.6167],"type":"Point"}
}
=======
{"geometry":{"type":"Point","coordinates":[-122.433300,44.616700]},"type":"Feature","properties":{"hierarchy":["tgn:2760185","tgn:1000001","tgn:7012149","tgn:2001717","tgn:7007708","tgn:7029392"],"placetype":["aat:300008706"],"id":2760185,"name:xx":"West Fork Quartzville Creek"}}
>>>>>>> 03f74aca74312dbeaf24d7e61306dd6a786dc3d0
