{
  "id": 7468989,
  "type": "Feature",
  "properties": {
    "tgn:hierarchy":[
        "tgn:7468989",
        "tgn:1000004",
        "tgn:7467799",
        "tgn:1000141",
        "tgn:7029392"
    ],
    "tgn:id":7468989,
    "tgn:name":"Xiangshan",
    "tgn:placetype":[
        "aat:300008347"
    ]
},
  "bbox": [],
  "geometry": {"coordinates":[120.604221,23.840665],"type":"Point"}
}