<<<<<<< HEAD
{
  "id": 7111114,
  "type": "Feature",
  "properties": {
    "tgn:hierarchy":[
        "tgn:7111114",
        "tgn:1000003",
        "tgn:7003676",
        "tgn:7000084",
        "tgn:7029392"
    ],
    "tgn:id":7111114,
    "tgn:name":"Rolfsb\u00fcttel",
    "tgn:placetype":[
        "aat:300008347"
    ]
},
  "bbox": [],
  "geometry": {"coordinates":[10.416667,52.4],"type":"Point"}
}
=======
{"geometry":{"type":"Point","coordinates":[10.416667,52.400000]},"type":"Feature","properties":{"hierarchy":["tgn:7111114","tgn:1000003","tgn:7003676","tgn:7000084","tgn:7029392"],"placetype":["aat:300008347"],"id":7111114,"name:xx":"Rolfsb\u00fcttel"}}
>>>>>>> 03f74aca74312dbeaf24d7e61306dd6a786dc3d0
