{
  "id": 1123417,
  "type": "Feature",
  "properties": {
    "tgn:hierarchy":[
        "tgn:1123417",
        "tgn:1000003",
        "tgn:7003678",
        "tgn:7000084",
        "tgn:7029392"
    ],
    "tgn:id":1123417,
    "tgn:name":"Dill",
    "tgn:placetype":[
        "aat:300008707",
        "aat:300008699"
    ]
},
  "bbox": [],
  "geometry": {"coordinates":[8.483333,50.55],"type":"Point"}
}