{
  "id": 2694678,
  "type": "Feature",
  "properties": {
    "tgn:hierarchy":[
        "tgn:2694678",
        "tgn:1000001",
        "tgn:7012149",
        "tgn:2000444",
        "tgn:7007248",
        "tgn:7029392"
    ],
    "tgn:id":2694678,
    "tgn:name":"Stewart Pond",
    "tgn:placetype":[
        "aat:300006191"
    ]
},
  "bbox": [],
  "geometry": {"coordinates":[-82.65,32.0333],"type":"Point"}
}