{
  "id": 2110672,
  "type": "Feature",
  "properties": {
    "tgn:hierarchy":[
        "tgn:2110672",
        "tgn:1000001",
        "tgn:7012149",
        "tgn:2002166",
        "tgn:7007919",
        "tgn:7029392"
    ],
    "tgn:id":2110672,
    "tgn:name":"Birchland Park",
    "tgn:placetype":[
        "aat:300008347",
        "aat:300387210"
    ]
},
  "bbox": [],
  "geometry": {"coordinates":[-79.1667,36.7167],"type":"Point"}
}