{
  "id": 2564812,
  "type": "Feature",
  "properties": {
    "tgn:hierarchy":[
        "tgn:2564812",
        "tgn:1000001",
        "tgn:7012149",
        "tgn:1002612",
        "tgn:7007710",
        "tgn:7029392"
    ],
    "tgn:id":2564812,
    "tgn:name":"Paddy Run",
    "tgn:placetype":[
        "aat:300008699"
    ]
},
  "bbox": [],
  "geometry": {"coordinates":[-76.1333,41.1333],"type":"Point"}
}