{
  "id": 7572781,
  "type": "Feature",
  "properties": {
    "tgn:hierarchy":[
        "tgn:7572781",
        "tgn:1000004",
        "tgn:7000198",
        "tgn:1001996",
        "tgn:7029392"
    ],
    "tgn:id":7572781,
    "tgn:name:en":"Gr\u0101mag",
    "tgn:placetype":[
        "aat:300008347"
    ]
},
  "bbox": [],
  "geometry": {"coordinates":[77.015088,32.014131],"type":"Point"}
}