<<<<<<< HEAD
{
  "id": 7359269,
  "type": "Feature",
  "properties": {
    "tgn:hierarchy":[
        "tgn:7359269",
        "tgn:1000001",
        "tgn:7005590",
        "tgn:7005560",
        "tgn:7029392"
    ],
    "tgn:id":7359269,
    "tgn:name":"Comanja",
    "tgn:placetype":[
        "aat:300008347"
    ]
},
  "bbox": [],
  "geometry": {"coordinates":[-101.7,19.733333],"type":"Point"}
}
=======
{"geometry":{"type":"Point","coordinates":[-101.700000,19.733333]},"type":"Feature","properties":{"hierarchy":["tgn:7359269","tgn:1000001","tgn:7005590","tgn:7005560","tgn:7029392"],"placetype":["aat:300008347"],"id":7359269,"name:xx":"Comanja"}}
>>>>>>> 03f74aca74312dbeaf24d7e61306dd6a786dc3d0
