{
  "id": 2397881,
  "type": "Feature",
  "properties": {
    "tgn:hierarchy":[
        "tgn:2397881",
        "tgn:1000001",
        "tgn:7012149",
        "tgn:1002525",
        "tgn:7007252",
        "tgn:7029392"
    ],
    "tgn:id":2397881,
    "tgn:name":"Hood Lake",
    "tgn:placetype":[
        "aat:300006191"
    ]
},
  "bbox": [],
  "geometry": {"coordinates":[-86.1167,39.3333],"type":"Point"}
}