<<<<<<< HEAD
{
  "id": 7114500,
  "type": "Feature",
  "properties": {
    "tgn:hierarchy":[
        "tgn:7114500",
        "tgn:1000003",
        "tgn:7003682",
        "tgn:7000084",
        "tgn:7029392"
    ],
    "tgn:id":7114500,
    "tgn:name":"Rom",
    "tgn:placetype":[
        "aat:300008347"
    ]
},
  "bbox": [],
  "geometry": {"coordinates":[6.666667,50.166667],"type":"Point"}
}
=======
{"geometry":{"type":"Point","coordinates":[6.666667,50.166667]},"type":"Feature","properties":{"hierarchy":["tgn:7114500","tgn:1000003","tgn:7003682","tgn:7000084","tgn:7029392"],"placetype":["aat:300008347"],"id":7114500,"name:xx":"Rom"}}
>>>>>>> 03f74aca74312dbeaf24d7e61306dd6a786dc3d0
