{
  "id": 7590173,
  "type": "Feature",
  "properties": {
    "tgn:hierarchy":[
        "tgn:7590173",
        "tgn:1000004",
        "tgn:7000198",
        "tgn:7000799",
        "tgn:7029392"
    ],
    "tgn:id":7590173,
    "tgn:name:en":"Khilla",
    "tgn:placetype":[
        "aat:300008347"
    ]
},
  "bbox": [],
  "geometry": {"coordinates":[73.960257,34.034006],"type":"Point"}
}