{
  "id": 2165881,
  "type": "Feature",
  "properties": {
    "tgn:hierarchy":[
        "tgn:2165881",
        "tgn:1000001",
        "tgn:7012149",
        "tgn:2000891",
        "tgn:7007256",
        "tgn:7029392"
    ],
    "tgn:id":2165881,
    "tgn:name":"Bienvenue Outside Pond",
    "tgn:placetype":[
        "aat:300132316"
    ]
},
  "bbox": [],
  "geometry": {"coordinates":[-89.1333,29.2833],"type":"Point"}
}