{
  "id": 7417146,
  "type": "Feature",
  "properties": {
    "tgn:hierarchy":[
        "tgn:7417146",
        "tgn:1000001",
        "tgn:7005591",
        "tgn:7005560",
        "tgn:7029392"
    ],
    "tgn:id":7417146,
    "tgn:name:es":"El Guayabo",
    "tgn:placetype":[
        "aat:300008347"
    ]
},
  "bbox": [],
  "geometry": {"coordinates":[-97.796667,16.1875],"type":"Point"}
}