<<<<<<< HEAD
{
  "id": 7175901,
  "type": "Feature",
  "properties": {
    "tgn:hierarchy":[
        "tgn:7175901",
        "tgn:7000096",
        "tgn:1000003",
        "tgn:7000084",
        "tgn:7029392"
    ],
    "tgn:id":7175901,
    "tgn:name":"Gro\u00dfer Zeschsee",
    "tgn:placetype":[
        "aat:300008680"
    ]
},
  "bbox": [],
  "geometry": {"coordinates":[13.516667,52.116667],"type":"Point"}
}
=======
{"geometry":{"type":"Point","coordinates":[13.516667,52.116667]},"type":"Feature","properties":{"hierarchy":["tgn:7175901","tgn:7000096","tgn:1000003","tgn:7000084","tgn:7029392"],"placetype":["aat:300008680"],"id":7175901,"name:xx":"Gro\u00dfer Zeschsee"}}
>>>>>>> 03f74aca74312dbeaf24d7e61306dd6a786dc3d0
