{
  "id": 1121282,
  "type": "Feature",
  "properties": {
    "tgn:hierarchy":[
        "tgn:1121282",
        "tgn:1000001",
        "tgn:7012149",
        "tgn:2001714",
        "tgn:7007708",
        "tgn:7029392"
    ],
    "tgn:id":1121282,
    "tgn:name":"Applegate",
    "tgn:placetype":[
        "aat:300008707"
    ]
},
  "bbox": [],
  "geometry": {"coordinates":[-121.5167,42.2833],"type":"Point"}
}