{
  "id": 7317287,
  "type": "Feature",
  "properties": {
    "tgn:hierarchy":[
        "tgn:7317287",
        "tgn:1001623",
        "tgn:1000049",
        "tgn:1000002",
        "tgn:7029392"
    ],
    "tgn:id":7317287,
    "tgn:name":"Cock, Morro",
    "tgn:placetype":[
        "aat:300387499"
    ]
},
  "bbox": [],
  "geometry": {"coordinates":[-74.566667,-48.283333],"type":"Point"}
}