{
  "id": 7431774,
  "type": "Feature",
  "properties": {
    "tgn:hierarchy":[
        "tgn:7431774",
        "tgn:7005586",
        "tgn:1000001",
        "tgn:7005560",
        "tgn:7029392"
    ],
    "tgn:id":7431774,
    "tgn:name":"Rinc\u00f3n de Guzm\u00e1n",
    "tgn:placetype":[
        "aat:300008347"
    ]
},
  "bbox": [],
  "geometry": {"coordinates":[-102.633333,21.25],"type":"Point"}
}