{
  "id": 7374709,
  "type": "Feature",
  "properties": {
    "tgn:hierarchy":[
        "tgn:7374709",
        "tgn:1000001",
        "tgn:1001906",
        "tgn:7005560",
        "tgn:7029392"
    ],
    "tgn:id":7374709,
    "tgn:name":"La Mesa",
    "tgn:placetype":[
        "aat:300008347"
    ]
},
  "bbox": [],
  "geometry": {"coordinates":[-105.166667,22.533333],"type":"Point"}
}