<<<<<<< HEAD
{
  "id": 7379118,
  "type": "Feature",
  "properties": {
    "tgn:hierarchy":[
        "tgn:7379118",
        "tgn:1000001",
        "tgn:1001960",
        "tgn:7005560",
        "tgn:7029392"
    ],
    "tgn:id":7379118,
    "tgn:name":"Los Chinos",
    "tgn:placetype":[
        "aat:300008347"
    ]
},
  "bbox": [],
  "geometry": {"coordinates":[-111.1,29.783333],"type":"Point"}
}
=======
{"geometry":{"type":"Point","coordinates":[-111.100000,29.783333]},"type":"Feature","properties":{"hierarchy":["tgn:7379118","tgn:1000001","tgn:1001960","tgn:7005560","tgn:7029392"],"placetype":["aat:300008347"],"id":7379118,"name:xx":"Los Chinos"}}
>>>>>>> 03f74aca74312dbeaf24d7e61306dd6a786dc3d0
