{
  "id": 2470099,
  "type": "Feature",
  "properties": {
    "tgn:hierarchy":[
        "tgn:2470099",
        "tgn:1000001",
        "tgn:2001014",
        "tgn:7012149",
        "tgn:7007521",
        "tgn:7029392"
    ],
    "tgn:id":2470099,
    "tgn:name":"Loop Lake",
    "tgn:placetype":[
        "aat:300008680"
    ]
},
  "bbox": [],
  "geometry": {"coordinates":[-90.9167,48.0833],"type":"Point"}
}