{
  "id": 2772196,
  "type": "Feature",
  "properties": {
    "tgn:hierarchy":[
        "tgn:2772196",
        "tgn:1000001",
        "tgn:7012149",
        "tgn:1002454",
        "tgn:7007826",
        "tgn:7029392"
    ],
    "tgn:id":2772196,
    "tgn:name":"Willard Lake",
    "tgn:placetype":[
        "aat:300008680"
    ]
},
  "bbox": [],
  "geometry": {"coordinates":[-94.15,30.25],"type":"Point"}
}