{
  "id": 1030831,
  "type": "Feature",
  "properties": {
    "tgn:hierarchy":[
        "tgn:1030831",
        "tgn:7002445",
        "tgn:1000003",
        "tgn:7008175",
        "tgn:7008591",
        "tgn:7029392"
    ],
    "tgn:id":1030831,
    "tgn:name:en":"Tandridge",
    "tgn:placetype":[
        "aat:300008347"
    ]
},
  "bbox": [],
  "geometry": {"coordinates":[-0.033333,51.233333],"type":"Point"}
}