{
  "id": 2703094,
  "type": "Feature",
  "properties": {
    "tgn:hierarchy":[
        "tgn:2703094",
        "tgn:7002659",
        "tgn:1000001",
        "tgn:7012149",
        "tgn:2000035",
        "tgn:7029392"
    ],
    "tgn:id":2703094,
    "tgn:name":"Summer Cave",
    "tgn:placetype":[
        "aat:300008746"
    ]
},
  "bbox": [],
  "geometry": {"coordinates":[-85.7667,34.9333],"type":"Point"}
}