{
  "id": 7052716,
  "type": "Feature",
  "properties": {
    "tgn:hierarchy":[
        "tgn:7052716",
        "tgn:7003164",
        "tgn:1000003",
        "tgn:7009760",
        "tgn:1000080",
        "tgn:7029392"
    ],
    "tgn:id":7052716,
    "tgn:name":"Montioni Allumiera",
    "tgn:placetype":[
        "aat:300008347"
    ]
},
  "bbox": [],
  "geometry": {"coordinates":[10.75,43.016667],"type":"Point"}
}