{
  "id": 7390993,
  "type": "Feature",
  "properties": {
    "tgn:hierarchy":[
        "tgn:7390993",
        "tgn:7005583",
        "tgn:1000001",
        "tgn:7005560",
        "tgn:7029392"
    ],
    "tgn:id":7390993,
    "tgn:name":"R\u00edo Verde",
    "tgn:placetype":[
        "aat:300008347"
    ]
},
  "bbox": [],
  "geometry": {"coordinates":[-104.996667,24.272222],"type":"Point"}
}