{
  "id": 7564307,
  "type": "Feature",
  "properties": {
    "tgn:hierarchy":[
        "tgn:7564307",
        "tgn:1000004",
        "tgn:7000198",
        "tgn:7016722",
        "tgn:7029392"
    ],
    "tgn:id":7564307,
    "tgn:name:en":"Purwa L\u0101lchand",
    "tgn:placetype":[
        "aat:300008347"
    ]
},
  "bbox": [],
  "geometry": {"coordinates":[79.77923,26.52823],"type":"Point"}
}