<<<<<<< HEAD
{
  "id": 7240604,
  "type": "Feature",
  "properties": {
    "tgn:hierarchy":[
        "tgn:7240604",
        "tgn:7003465",
        "tgn:1000003",
        "tgn:1000063",
        "tgn:4012014",
        "tgn:7029392"
    ],
    "tgn:id":7240604,
    "tgn:name":"Fange",
    "tgn:placetype":[
        "aat:300008699"
    ]
},
  "bbox": [],
  "geometry": {"coordinates":[5.9,50.166667],"type":"Point"}
}
=======
{"geometry":{"type":"Point","coordinates":[5.900000,50.166667]},"type":"Feature","properties":{"hierarchy":["tgn:7240604","tgn:7003465","tgn:1000003","tgn:1000063","tgn:4012014","tgn:7029392"],"placetype":["aat:300008699"],"id":7240604,"name:xx":"Fange"}}
>>>>>>> 03f74aca74312dbeaf24d7e61306dd6a786dc3d0
