{
  "id": 7044155,
  "type": "Feature",
  "properties": {
    "tgn:hierarchy":[
        "tgn:7044155",
        "tgn:1003478",
        "tgn:1000003",
        "tgn:7003120",
        "tgn:1000080",
        "tgn:7029392"
    ],
    "tgn:id":7044155,
    "tgn:name":"Fruer, Lago",
    "tgn:placetype":[
        "aat:300008680"
    ]
},
  "bbox": [],
  "geometry": {"coordinates":[8.35,46.383333],"type":"Point"}
}