{
  "id": 2265861,
  "type": "Feature",
  "properties": {
    "tgn:hierarchy":[
        "tgn:2265861",
        "tgn:7006450",
        "tgn:1000001",
        "tgn:7019698",
        "tgn:7012149",
        "tgn:7029392"
    ],
    "tgn:id":2265861,
    "tgn:name":"Crater Peak Glacier",
    "tgn:placetype":[
        "aat:300008835"
    ]
},
  "bbox": [],
  "geometry": {"coordinates":[-151.2167,61.2167],"type":"Point"}
}