{
  "id": 2001791,
  "type": "Feature",
  "properties": {
    "tgn:hierarchy":[
        "tgn:2001791",
        "tgn:1000001",
        "tgn:7012149",
        "tgn:7007713",
        "tgn:7029392"
    ],
    "tgn:id":2001791,
    "tgn:name":"Douglas",
    "tgn:placetype":[
        "aat:300387145",
        "aat:300000771"
    ]
},
  "bbox": [],
  "geometry": {"coordinates":[-98.3667,43.3833],"type":"Point"}
}