<<<<<<< HEAD
{
  "id": 2767656,
  "type": "Feature",
  "properties": {
    "tgn:hierarchy":[
        "tgn:2767656",
        "tgn:1000001",
        "tgn:2002261",
        "tgn:7012149",
        "tgn:7013961",
        "tgn:7029392"
    ],
    "tgn:id":2767656,
    "tgn:name":"Whiteface Hollow",
    "tgn:placetype":[
        "aat:300008761"
    ]
},
  "bbox": [],
  "geometry": {"coordinates":[-81.1833,38.2],"type":"Point"}
}
=======
{"geometry":{"type":"Point","coordinates":[-81.183300,38.200000]},"type":"Feature","properties":{"hierarchy":["tgn:2767656","tgn:1000001","tgn:2002261","tgn:7012149","tgn:7013961","tgn:7029392"],"placetype":["aat:300008761"],"id":2767656,"name:xx":"Whiteface Hollow"}}
>>>>>>> 03f74aca74312dbeaf24d7e61306dd6a786dc3d0
