{
  "id": 7500354,
  "type": "Feature",
  "properties": {
    "tgn:hierarchy":[
        "tgn:7500354",
        "tgn:1000004",
        "tgn:7001009",
        "tgn:1000141",
        "tgn:7029392"
    ],
    "tgn:id":7500354,
    "tgn:name":"Lingdong Shangzhuan",
    "tgn:placetype":[
        "aat:300006610"
    ]
},
  "bbox": [],
  "geometry": {"coordinates":[120.608701,24.137651],"type":"Point"}
}