{
  "id": 7175379,
  "type": "Feature",
  "properties": {
    "tgn:hierarchy":[
        "tgn:7175379",
        "tgn:1000003",
        "tgn:7000094",
        "tgn:7000084",
        "tgn:7029392"
    ],
    "tgn:id":7175379,
    "tgn:name":"Gr\u00f6thagen",
    "tgn:placetype":[
        "aat:300000206"
    ]
},
  "bbox": [],
  "geometry": {"coordinates":[13.166667,54.533333],"type":"Point"}
}