<<<<<<< HEAD
{
  "id": 2404793,
  "type": "Feature",
  "properties": {
    "tgn:hierarchy":[
        "tgn:2404793",
        "tgn:1000001",
        "tgn:7012149",
        "tgn:7007157",
        "tgn:2000188",
        "tgn:7029392"
    ],
    "tgn:id":2404793,
    "tgn:name":"Huckleberry Mountain",
    "tgn:placetype":[
        "aat:300008798"
    ]
},
  "bbox": [],
  "geometry": {"coordinates":[-121.65,40.6333],"type":"Point"}
}
=======
{"geometry":{"type":"Point","coordinates":[-121.650000,40.633300]},"type":"Feature","properties":{"hierarchy":["tgn:2404793","tgn:1000001","tgn:7012149","tgn:7007157","tgn:2000188","tgn:7029392"],"placetype":["aat:300008798"],"id":2404793,"name:xx":"Huckleberry Mountain"}}
>>>>>>> 03f74aca74312dbeaf24d7e61306dd6a786dc3d0
