{
  "id": 2480829,
  "type": "Feature",
  "properties": {
    "tgn:hierarchy":[
        "tgn:2480829",
        "tgn:1000001",
        "tgn:7012149",
        "tgn:2001714",
        "tgn:7007708",
        "tgn:7029392"
    ],
    "tgn:id":2480829,
    "tgn:name":"Lakeview Mountain",
    "tgn:placetype":[
        "aat:300008798"
    ]
},
  "bbox": [],
  "geometry": {"coordinates":[-122.0333,43.5167],"type":"Point"}
}