{
  "id": 2510980,
  "type": "Feature",
  "properties": {
    "tgn:hierarchy":[
        "tgn:2510980",
        "tgn:1000001",
        "tgn:7012149",
        "tgn:2001692",
        "tgn:7007707",
        "tgn:7029392"
    ],
    "tgn:id":2510980,
    "tgn:name":"Midway",
    "tgn:placetype":[
        "aat:300008347"
    ]
},
  "bbox": [],
  "geometry": {"coordinates":[-101.35,36.8667],"type":"Point"}
}