{
  "id": 7416373,
  "type": "Feature",
  "properties": {
    "tgn:hierarchy":[
        "tgn:7416373",
        "tgn:1000001",
        "tgn:7005591",
        "tgn:7005560",
        "tgn:7029392"
    ],
    "tgn:id":7416373,
    "tgn:name:es":"Soledad",
    "tgn:placetype":[
        "aat:300008347"
    ]
},
  "bbox": [],
  "geometry": {"coordinates":[-95.176389,17.225833],"type":"Point"}
}