{
  "id": 2692496,
  "type": "Feature",
  "properties": {
    "tgn:hierarchy":[
        "tgn:2692496",
        "tgn:1000001",
        "tgn:7012149",
        "tgn:7007158",
        "tgn:2000245",
        "tgn:7029392"
    ],
    "tgn:id":2692496,
    "tgn:name":"Steamboat Lake",
    "tgn:placetype":[
        "aat:300006191"
    ]
},
  "bbox": [],
  "geometry": {"coordinates":[-106.9333,40.7833],"type":"Point"}
}