{
  "id": 7395653,
  "type": "Feature",
  "properties": {
    "tgn:hierarchy":[
        "tgn:7395653",
        "tgn:7005581",
        "tgn:1000001",
        "tgn:7005560",
        "tgn:7029392"
    ],
    "tgn:id":7395653,
    "tgn:name":"San Isidro",
    "tgn:placetype":[
        "aat:300007783"
    ]
},
  "bbox": [],
  "geometry": {"coordinates":[-107.45,28.566667],"type":"Point"}
}