{
  "id": 7464867,
  "type": "Feature",
  "properties": {
    "tgn:hierarchy":[
        "tgn:7464867",
        "tgn:7002444",
        "tgn:7008074",
        "tgn:1000003",
        "tgn:7008591",
        "tgn:7029392"
    ],
    "tgn:id":7464867,
    "tgn:name:en":"Boyken Burn",
    "tgn:placetype":[
        "aat:300008699"
    ]
},
  "bbox": [],
  "geometry": {"coordinates":[-3.066667,55.183333],"type":"Point"}
}