{
  "id": 2427353,
  "type": "Feature",
  "properties": {
    "tgn:hierarchy":[
        "tgn:2427353",
        "tgn:1002300",
        "tgn:1000001",
        "tgn:7012149",
        "tgn:7007564",
        "tgn:7029392"
    ],
    "tgn:id":2427353,
    "tgn:name":"Jordan Hill",
    "tgn:placetype":[
        "aat:300008798"
    ]
},
  "bbox": [],
  "geometry": {"coordinates":[-71.5167,44.8333],"type":"Point"}
}