{
  "id": 2472484,
  "type": "Feature",
  "properties": {
    "tgn:hierarchy":[
        "tgn:2472484",
        "tgn:1000001",
        "tgn:7014423",
        "tgn:7012149",
        "tgn:7007517",
        "tgn:7029392"
    ],
    "tgn:id":2472484,
    "tgn:name":"Lout Pond",
    "tgn:placetype":[
        "aat:300008680"
    ]
},
  "bbox": [],
  "geometry": {"coordinates":[-70.6667,41.9333],"type":"Point"}
}