{
  "id": 2190661,
  "type": "Feature",
  "properties": {
    "tgn:hierarchy":[
        "tgn:2190661",
        "tgn:1000001",
        "tgn:7006451",
        "tgn:7012149",
        "tgn:2000098",
        "tgn:7029392"
    ],
    "tgn:id":2190661,
    "tgn:name":"Box, The",
    "tgn:placetype":[
        "aat:300008798"
    ]
},
  "bbox": [],
  "geometry": {"coordinates":[-113.95,36.25],"type":"Point"}
}