<<<<<<< HEAD
{
  "id": 2155179,
  "type": "Feature",
  "properties": {
    "tgn:hierarchy":[
        "tgn:2155179",
        "tgn:1000001",
        "tgn:7012149",
        "tgn:2001275",
        "tgn:7007524",
        "tgn:7029392"
    ],
    "tgn:id":2155179,
    "tgn:name":"Bear Lakes",
    "tgn:placetype":[
        "aat:300008680"
    ]
},
  "bbox": [],
  "geometry": {"coordinates":[-110.85,45.55],"type":"Point"}
}
=======
{"geometry":{"type":"Point","coordinates":[-110.850000,45.550000]},"type":"Feature","properties":{"hierarchy":["tgn:2155179","tgn:1000001","tgn:7012149","tgn:2001275","tgn:7007524","tgn:7029392"],"placetype":["aat:300008680"],"id":2155179,"name:xx":"Bear Lakes"}}
>>>>>>> 03f74aca74312dbeaf24d7e61306dd6a786dc3d0
