{
  "id": 2439645,
  "type": "Feature",
  "properties": {
    "tgn:hierarchy":[
        "tgn:2439645",
        "tgn:1000001",
        "tgn:2001260",
        "tgn:7012149",
        "tgn:7007524",
        "tgn:7029392"
    ],
    "tgn:id":2439645,
    "tgn:name":"Kissick Canyon",
    "tgn:placetype":[
        "aat:300008761"
    ]
},
  "bbox": [],
  "geometry": {"coordinates":[-112.9333,44.8833],"type":"Point"}
}