{
  "id": 7031028,
  "type": "Feature",
  "properties": {
    "tgn:hierarchy":[
        "tgn:7031028",
        "tgn:7002445",
        "tgn:1000003",
        "tgn:7008167",
        "tgn:7008591",
        "tgn:7029392"
    ],
    "tgn:id":7031028,
    "tgn:name:en":"Coddington",
    "tgn:placetype":[
        "aat:300008347",
        "aat:300008372"
    ]
},
  "bbox": [],
  "geometry": {"coordinates":[-0.75,53.083333],"type":"Point"}
}