{
  "id": 7088519,
  "type": "Feature",
  "properties": {
    "tgn:hierarchy":[
        "tgn:7088519",
        "tgn:7003669",
        "tgn:1000003",
        "tgn:7000084",
        "tgn:7029392"
    ],
    "tgn:id":7088519,
    "tgn:name":"Waltenrieth",
    "tgn:placetype":[
        "aat:300000206"
    ]
},
  "bbox": [],
  "geometry": {"coordinates":[12.416667,49.566667],"type":"Point"}
}