{
  "id": 2288161,
  "type": "Feature",
  "properties": {
    "tgn:hierarchy":[
        "tgn:2288161",
        "tgn:1000001",
        "tgn:7012149",
        "tgn:7007158",
        "tgn:7029392"
    ],
    "tgn:id":2288161,
    "tgn:name":"Diorite Peak",
    "tgn:placetype":[
        "aat:300008798"
    ]
},
  "bbox": [],
  "geometry": {"coordinates":[-108.05,37.4333],"type":"Point"}
}