{
  "id": 7388194,
  "type": "Feature",
  "properties": {
    "tgn:hierarchy":[
        "tgn:7388194",
        "tgn:1000001",
        "tgn:7005595",
        "tgn:7005560",
        "tgn:7029392"
    ],
    "tgn:id":7388194,
    "tgn:name":"Paredones",
    "tgn:placetype":[
        "aat:300008347"
    ]
},
  "bbox": [],
  "geometry": {"coordinates":[-107.483611,24.982778],"type":"Point"}
}