{
  "id": 2617490,
  "type": "Feature",
  "properties": {
    "tgn:hierarchy":[
        "tgn:2617490",
        "tgn:1000001",
        "tgn:7016172",
        "tgn:7012149",
        "tgn:2000147",
        "tgn:7029392"
    ],
    "tgn:id":2617490,
    "tgn:name":"Richmond Pond",
    "tgn:placetype":[
        "aat:300006191"
    ]
},
  "bbox": [],
  "geometry": {"coordinates":[-91.95,34.95],"type":"Point"}
}