{
  "id": 7496293,
  "type": "Feature",
  "properties": {
    "tgn:hierarchy":[
        "tgn:7496293",
        "tgn:1000004",
        "tgn:1000454",
        "tgn:1000141",
        "tgn:7029392"
    ],
    "tgn:id":7496293,
    "tgn:name":"Qingxin Nongchang",
    "tgn:placetype":[
        "aat:300000206"
    ]
},
  "bbox": [],
  "geometry": {"coordinates":[121.495633,24.879921],"type":"Point"}
}