{
  "id": 7004320,
  "type": "Feature",
  "properties": {
    "tgn:hierarchy":[
        "tgn:7004320",
        "tgn:7007850",
        "tgn:1003491",
        "tgn:1000003",
        "tgn:1000080",
        "tgn:7029392"
    ],
    "tgn:id":7004320,
    "tgn:name":"Gerace",
    "tgn:placetype":[
        "aat:300008347"
    ]
},
  "bbox": [],
  "geometry": {"coordinates":[16.216667,38.266667],"type":"Point"}
}