{
  "id": 2394507,
  "type": "Feature",
  "properties": {
    "tgn:hierarchy":[
        "tgn:2394507",
        "tgn:1000001",
        "tgn:7012149",
        "tgn:2001756",
        "tgn:7007712",
        "tgn:7029392"
    ],
    "tgn:id":2394507,
    "tgn:name":"Hogpen Branch",
    "tgn:placetype":[
        "aat:300008699"
    ]
},
  "bbox": [],
  "geometry": {"coordinates":[-81.3167,33.9667],"type":"Point"}
}