{
  "id": 7332945,
  "type": "Feature",
  "properties": {
    "tgn:hierarchy":[
        "tgn:7332945",
        "tgn:7002758",
        "tgn:7002821",
        "tgn:1000003",
        "tgn:1000095",
        "tgn:7029392"
    ],
    "tgn:id":7332945,
    "tgn:name":"La Estaci\u00f3n",
    "tgn:placetype":[
        "aat:300008347"
    ]
},
  "bbox": [],
  "geometry": {"coordinates":[-2.833333,37.183333],"type":"Point"}
}