{
  "id": 7336648,
  "type": "Feature",
  "properties": {
    "tgn:hierarchy":[
        "tgn:7336648",
        "tgn:7002836",
        "tgn:7016622",
        "tgn:1000003",
        "tgn:1000095",
        "tgn:7029392"
    ],
    "tgn:id":7336648,
    "tgn:name":"Gaviotas, Boca de las",
    "tgn:placetype":[
        "aat:300132317"
    ]
},
  "bbox": [],
  "geometry": {"coordinates":[-17.883333,27.833333],"type":"Point"}
}