{
  "id": 2189909,
  "type": "Feature",
  "properties": {
    "tgn:hierarchy":[
        "tgn:2189909",
        "tgn:1000001",
        "tgn:7012149",
        "tgn:2002166",
        "tgn:7007919",
        "tgn:7029392"
    ],
    "tgn:id":2189909,
    "tgn:name":"Bowle Spring Branch",
    "tgn:placetype":[
        "aat:300008699"
    ]
},
  "bbox": [],
  "geometry": {"coordinates":[-78.95,36.6167],"type":"Point"}
}