{
  "id": 1131470,
  "type": "Feature",
  "properties": {
    "tgn:hierarchy":[
        "tgn:1131470",
        "tgn:1000003",
        "tgn:7002885",
        "tgn:1000070",
        "tgn:7029392"
    ],
    "tgn:id":1131470,
    "tgn:name":"Vidourle",
    "tgn:placetype":[
        "aat:300008707"
    ]
},
  "bbox": [],
  "geometry": {"coordinates":[4.1333,43.5333],"type":"Point"}
}