{
  "id": 7558037,
  "type": "Feature",
  "properties": {
    "tgn:hierarchy":[
        "tgn:7558037",
        "tgn:1000004",
        "tgn:7000198",
        "tgn:7016788",
        "tgn:7029392"
    ],
    "tgn:id":7558037,
    "tgn:name:en":"P\u0101nhori",
    "tgn:placetype":[
        "aat:300008347"
    ]
},
  "bbox": [],
  "geometry": {"coordinates":[77.24992,27.447912],"type":"Point"}
}