{
  "id": 7555203,
  "type": "Feature",
  "properties": {
    "tgn:hierarchy":[
        "tgn:7555203",
        "tgn:7001819",
        "tgn:1000004",
        "tgn:7000198",
        "tgn:7029392"
    ],
    "tgn:id":7555203,
    "tgn:name:en":"Namkha Chu",
    "tgn:placetype":[
        "aat:300008699"
    ]
},
  "bbox": [],
  "geometry": {"coordinates":[91.733333,27.783333],"type":"Point"}
}