<<<<<<< HEAD
{
  "id": 2259631,
  "type": "Feature",
  "properties": {
    "tgn:hierarchy":[
        "tgn:2259631",
        "tgn:1000001",
        "tgn:7012149",
        "tgn:2002164",
        "tgn:7007919",
        "tgn:7029392"
    ],
    "tgn:id":2259631,
    "tgn:name":"Couchs Knob",
    "tgn:placetype":[
        "aat:300008798"
    ]
},
  "bbox": [],
  "geometry": {"coordinates":[-81.35,36.6167],"type":"Point"}
}
=======
{"geometry":{"type":"Point","coordinates":[-81.350000,36.616700]},"type":"Feature","properties":{"hierarchy":["tgn:2259631","tgn:1000001","tgn:7012149","tgn:2002164","tgn:7007919","tgn:7029392"],"placetype":["aat:300008798"],"id":2259631,"name:xx":"Couchs Knob"}}
>>>>>>> 03f74aca74312dbeaf24d7e61306dd6a786dc3d0
