{
  "id": 7403874,
  "type": "Feature",
  "properties": {
    "tgn:hierarchy":[
        "tgn:7403874",
        "tgn:1000001",
        "tgn:1001906",
        "tgn:7005560",
        "tgn:7029392"
    ],
    "tgn:id":7403874,
    "tgn:name":"El Azafr\u00e1n",
    "tgn:placetype":[
        "aat:300008347"
    ]
},
  "bbox": [],
  "geometry": {"coordinates":[-105.416667,22.933333],"type":"Point"}
}