{
  "id": 1062877,
  "type": "Feature",
  "properties": {
    "tgn:hierarchy":[
        "tgn:1062877",
        "tgn:1000003",
        "tgn:1000462",
        "tgn:1000097",
        "tgn:7029392"
    ],
    "tgn:id":1062877,
    "tgn:name":"Brunna",
    "tgn:placetype":[
        "aat:300008347"
    ]
},
  "bbox": [],
  "geometry": {"coordinates":[17.4333,59.85],"type":"Point"}
}