{
  "id": 7218920,
  "type": "Feature",
  "properties": {
    "tgn:hierarchy":[
        "tgn:7218920",
        "tgn:7011170",
        "tgn:7002715",
        "tgn:1000003",
        "tgn:1000074",
        "tgn:7029392"
    ],
    "tgn:id":7218920,
    "tgn:name":"Vras\u00eddas, \u00c1kra",
    "tgn:placetype":[
        "aat:300008850"
    ]
},
  "bbox": [],
  "geometry": {"coordinates":[24.340278,40.826389],"type":"Point"}
}