{
  "id": 2216637,
  "type": "Feature",
  "properties": {
    "tgn:hierarchy":[
        "tgn:2216637",
        "tgn:1000001",
        "tgn:7012149",
        "tgn:1002897",
        "tgn:7007920",
        "tgn:7029392"
    ],
    "tgn:id":2216637,
    "tgn:name":"Camp Creek",
    "tgn:placetype":[
        "aat:300008706"
    ]
},
  "bbox": [],
  "geometry": {"coordinates":[-121.7667,46.35],"type":"Point"}
}