{
  "id": 2741065,
  "type": "Feature",
  "properties": {
    "tgn:hierarchy":[
        "tgn:2741065",
        "tgn:1000001",
        "tgn:7012149",
        "tgn:1002795",
        "tgn:7007826",
        "tgn:7029392"
    ],
    "tgn:id":2741065,
    "tgn:name":"Upper Sulphur Creek",
    "tgn:placetype":[
        "aat:300008706"
    ]
},
  "bbox": [],
  "geometry": {"coordinates":[-94.8833,31.0833],"type":"Point"}
}