{
  "id": 7495923,
  "type": "Feature",
  "properties": {
    "tgn:hierarchy":[
        "tgn:7495923",
        "tgn:7487020",
        "tgn:1000004",
        "tgn:1000141",
        "tgn:7029392"
    ],
    "tgn:id":7495923,
    "tgn:name":"Huihuang Qiao",
    "tgn:placetype":[
        "aat:300007836"
    ]
},
  "bbox": [],
  "geometry": {"coordinates":[120.834815,24.300696],"type":"Point"}
}