{
  "id": 7390178,
  "type": "Feature",
  "properties": {
    "tgn:hierarchy":[
        "tgn:7390178",
        "tgn:1001853",
        "tgn:1000001",
        "tgn:7005560",
        "tgn:7029392"
    ],
    "tgn:id":7390178,
    "tgn:name":"Salsipuedes, Sierra de",
    "tgn:placetype":[
        "aat:300008795"
    ]
},
  "bbox": [],
  "geometry": {"coordinates":[-102.766667,27.933333],"type":"Point"}
}