{
  "id": 7039469,
  "type": "Feature",
  "properties": {
    "tgn:hierarchy":[
        "tgn:7039469",
        "tgn:7002995",
        "tgn:1000003",
        "tgn:7002997",
        "tgn:1000080",
        "tgn:7029392"
    ],
    "tgn:id":7039469,
    "tgn:name":"Stienta",
    "tgn:placetype":[
        "aat:300008347"
    ]
},
  "bbox": [],
  "geometry": {"coordinates":[11.533333,44.933333],"type":"Point"}
}