{
  "id": 2715034,
  "type": "Feature",
  "properties": {
    "tgn:hierarchy":[
        "tgn:2715034",
        "tgn:7002659",
        "tgn:1000001",
        "tgn:7012149",
        "tgn:2000035",
        "tgn:7029392"
    ],
    "tgn:id":2715034,
    "tgn:name":"Tennessee Valley Mine",
    "tgn:placetype":[
        "aat:300000390"
    ]
},
  "bbox": [],
  "geometry": {"coordinates":[-85.85,34.9333],"type":"Point"}
}