{
  "id": 7533554,
  "type": "Feature",
  "properties": {
    "tgn:hierarchy":[
        "tgn:7533554",
        "tgn:7001242",
        "tgn:7016833",
        "tgn:1001418",
        "tgn:7029392"
    ],
    "tgn:id":7533554,
    "tgn:name:en":"\u1e28amr\u0101', Al Q\u0101r\u0101t al",
    "tgn:placetype":[
        "aat:300008777"
    ]
},
  "bbox": [],
  "geometry": {"coordinates":[25.301165,31.083003],"type":"Point"}
}