<<<<<<< HEAD
{
  "id": 7376810,
  "type": "Feature",
  "properties": {
    "tgn:hierarchy":[
        "tgn:7376810",
        "tgn:1001853",
        "tgn:1000001",
        "tgn:7005560",
        "tgn:7029392"
    ],
    "tgn:id":7376810,
    "tgn:name":"Las Mangas",
    "tgn:placetype":[
        "aat:300008347"
    ]
},
  "bbox": [],
  "geometry": {"coordinates":[-101.1,24.9],"type":"Point"}
}
=======
{"geometry":{"type":"Point","coordinates":[-101.100000,24.900000]},"type":"Feature","properties":{"hierarchy":["tgn:7376810","tgn:1001853","tgn:1000001","tgn:7005560","tgn:7029392"],"placetype":["aat:300008347"],"id":7376810,"name:xx":"Las Mangas"}}
>>>>>>> 03f74aca74312dbeaf24d7e61306dd6a786dc3d0
