{
  "id": 2059236,
  "type": "Feature",
  "properties": {
    "tgn:hierarchy":[
        "tgn:2059236",
        "tgn:1000001",
        "tgn:7012149",
        "tgn:1002384",
        "tgn:7007523",
        "tgn:7029392"
    ],
    "tgn:id":2059236,
    "tgn:name":"Jeffriesburg",
    "tgn:placetype":[
        "aat:300387016"
    ]
},
  "bbox": [],
  "geometry": {"coordinates":[-91.0833,38.4333],"type":"Point"}
}