<<<<<<< HEAD
{
  "id": 2338556,
  "type": "Feature",
  "properties": {
    "tgn:hierarchy":[
        "tgn:2338556",
        "tgn:1000001",
        "tgn:7012149",
        "tgn:1002525",
        "tgn:7007252",
        "tgn:7029392"
    ],
    "tgn:id":2338556,
    "tgn:name":"Frances",
    "tgn:placetype":[
        "aat:300008347"
    ]
},
  "bbox": [],
  "geometry": {"coordinates":[-86.1667,39.6],"type":"Point"}
}
=======
{"geometry":{"type":"Point","coordinates":[-86.166700,39.600000]},"type":"Feature","properties":{"hierarchy":["tgn:2338556","tgn:1000001","tgn:7012149","tgn:1002525","tgn:7007252","tgn:7029392"],"placetype":["aat:300008347"],"id":2338556,"name:xx":"Frances"}}
>>>>>>> 03f74aca74312dbeaf24d7e61306dd6a786dc3d0
