{
  "id": 2645480,
  "type": "Feature",
  "properties": {
    "tgn:hierarchy":[
        "tgn:2645480",
        "tgn:1000001",
        "tgn:2000457",
        "tgn:7012149",
        "tgn:7007250",
        "tgn:7029392"
    ],
    "tgn:id":2645480,
    "tgn:name":"Saw Log Basin",
    "tgn:placetype":[
        "aat:300386845"
    ]
},
  "bbox": [],
  "geometry": {"coordinates":[-111.95,43.2833],"type":"Point"}
}