{
  "id": 7574251,
  "type": "Feature",
  "properties": {
    "tgn:hierarchy":[
        "tgn:7574251",
        "tgn:1000004",
        "tgn:7000198",
        "tgn:1001882",
        "tgn:7029392"
    ],
    "tgn:id":7574251,
    "tgn:name:en":"Hamp\u0101s\u0101garam",
    "tgn:placetype":[
        "aat:300008347"
    ]
},
  "bbox": [],
  "geometry": {"coordinates":[76.05,15.15],"type":"Point"}
}