{
  "id": 7317487,
  "type": "Feature",
  "properties": {
    "tgn:hierarchy":[
        "tgn:7317487",
        "tgn:7002464",
        "tgn:1000049",
        "tgn:1000002",
        "tgn:7029392"
    ],
    "tgn:id":7317487,
    "tgn:name":"Cochantari",
    "tgn:placetype":[
        "aat:300008347"
    ]
},
  "bbox": [],
  "geometry": {"coordinates":[-69.35,-18.033333],"type":"Point"}
}