{
  "id": 2566090,
  "type": "Feature",
  "properties": {
    "tgn:hierarchy":[
        "tgn:2566090",
        "tgn:1000001",
        "tgn:7012149",
        "tgn:1002540",
        "tgn:7007520",
        "tgn:7029392"
    ],
    "tgn:id":2566090,
    "tgn:name":"Palmer Lake",
    "tgn:placetype":[
        "aat:300008680"
    ]
},
  "bbox": [],
  "geometry": {"coordinates":[-85.3833,42.8333],"type":"Point"}
}