{
  "id": 7481970,
  "type": "Feature",
  "properties": {
    "tgn:hierarchy":[
        "tgn:7481970",
        "tgn:1000004",
        "tgn:7490934",
        "tgn:1000141",
        "tgn:7029392"
    ],
    "tgn:id":7481970,
    "tgn:name":"Liufenliao Nongchang",
    "tgn:placetype":[
        "aat:300000206"
    ]
},
  "bbox": [],
  "geometry": {"coordinates":[120.291786,23.165682],"type":"Point"}
}