{
  "id": 7590011,
  "type": "Feature",
  "properties": {
    "tgn:hierarchy":[
        "tgn:7590011",
        "tgn:1000004",
        "tgn:7000198",
        "tgn:7000799",
        "tgn:7029392"
    ],
    "tgn:id":7590011,
    "tgn:name:en":"Singer",
    "tgn:placetype":[
        "aat:300387033"
    ]
},
  "bbox": [],
  "geometry": {"coordinates":[73.998611,34.559722],"type":"Point"}
}