{
  "id": 7297941,
  "type": "Feature",
  "properties": {
    "tgn:hierarchy":[
        "tgn:7297941",
        "tgn:7002824",
        "tgn:1000003",
        "tgn:7002786",
        "tgn:1000095",
        "tgn:7029392"
    ],
    "tgn:id":7297941,
    "tgn:name":"Silvari\u00f1o, Monte",
    "tgn:placetype":[
        "aat:300008795"
    ]
},
  "bbox": [],
  "geometry": {"coordinates":[-8.766667,42.983333],"type":"Point"}
}