{
  "id": 7385414,
  "type": "Feature",
  "properties": {
    "tgn:hierarchy":[
        "tgn:7385414",
        "tgn:1000001",
        "tgn:7005597",
        "tgn:7005560",
        "tgn:7029392"
    ],
    "tgn:id":7385414,
    "tgn:name":"Nogales",
    "tgn:placetype":[
        "aat:300008347"
    ]
},
  "bbox": [],
  "geometry": {"coordinates":[-99.440278,24.321667],"type":"Point"}
}