{
  "id": 1052255,
  "type": "Feature",
  "properties": {
    "tgn:hierarchy":[
        "tgn:1052255",
        "tgn:1000004",
        "tgn:7012911",
        "tgn:7014786",
        "tgn:7029392"
    ],
    "tgn:id":1052255,
    "tgn:name":"Araldy",
    "tgn:placetype":[
        "aat:300008347"
    ]
},
  "bbox": [],
  "geometry": {"coordinates":[50.3833,44.3167],"type":"Point"}
}