{
  "id": 7225425,
  "type": "Feature",
  "properties": {
    "tgn:hierarchy":[
        "tgn:7225425",
        "tgn:7002690",
        "tgn:7012056",
        "tgn:1000003",
        "tgn:1000074",
        "tgn:7029392"
    ],
    "tgn:id":7225425,
    "tgn:name":"Stavr\u00e1kia",
    "tgn:placetype":[
        "aat:300008347"
    ]
},
  "bbox": [],
  "geometry": {"coordinates":[25.066667,35.25],"type":"Point"}
}