{
  "id": 7469460,
  "type": "Feature",
  "properties": {
    "tgn:hierarchy":[
        "tgn:7469460",
        "tgn:1000004",
        "tgn:1000454",
        "tgn:1000141",
        "tgn:7029392"
    ],
    "tgn:id":7469460,
    "tgn:name":"Wazi",
    "tgn:placetype":[
        "aat:300008347"
    ]
},
  "bbox": [],
  "geometry": {"coordinates":[121.950689,25.02016],"type":"Point"}
}