{
  "id": 1127056,
  "type": "Feature",
  "properties": {
    "tgn:hierarchy":[
        "tgn:1127056",
        "tgn:7003025",
        "tgn:1000003",
        "tgn:1000062",
        "tgn:7029392"
    ],
    "tgn:id":1127056,
    "tgn:name":"Melk",
    "tgn:placetype":[
        "aat:300008707"
    ]
},
  "bbox": [],
  "geometry": {"coordinates":[15.3167,48.2333],"type":"Point"}
}