{
  "id": 7564255,
  "type": "Feature",
  "properties": {
    "tgn:hierarchy":[
        "tgn:7564255",
        "tgn:1000004",
        "tgn:7000198",
        "tgn:1001894",
        "tgn:7029392"
    ],
    "tgn:id":7564255,
    "tgn:name:en":"Kheron",
    "tgn:placetype":[
        "aat:300008347"
    ]
},
  "bbox": [],
  "geometry": {"coordinates":[79.4565,24.7789],"type":"Point"}
}