{
  "id": 7086937,
  "type": "Feature",
  "properties": {
    "tgn:hierarchy":[
        "tgn:7086937",
        "tgn:7003692",
        "tgn:1000003",
        "tgn:7000084",
        "tgn:7029392"
    ],
    "tgn:id":7086937,
    "tgn:name":"Warmtal",
    "tgn:placetype":[
        "aat:300008347"
    ]
},
  "bbox": [],
  "geometry": {"coordinates":[9.333333,48.166667],"type":"Point"}
}