<<<<<<< HEAD
{
  "id": 2332851,
  "type": "Feature",
  "properties": {
    "tgn:hierarchy":[
        "tgn:2332851",
        "tgn:1000001",
        "tgn:7012149",
        "tgn:2000915",
        "tgn:7007256",
        "tgn:7029392"
    ],
    "tgn:id":2332851,
    "tgn:name":"Floyd Landing",
    "tgn:placetype":[
        "aat:300008347"
    ]
},
  "bbox": [],
  "geometry": {"coordinates":[-91.4,32.6667],"type":"Point"}
}
=======
{"geometry":{"type":"Point","coordinates":[-91.400000,32.666700]},"type":"Feature","properties":{"hierarchy":["tgn:2332851","tgn:1000001","tgn:7012149","tgn:2000915","tgn:7007256","tgn:7029392"],"placetype":["aat:300008347"],"id":2332851,"name:xx":"Floyd Landing"}}
>>>>>>> 03f74aca74312dbeaf24d7e61306dd6a786dc3d0
