{
  "id": 2351311,
  "type": "Feature",
  "properties": {
    "tgn:hierarchy":[
        "tgn:2351311",
        "tgn:1000001",
        "tgn:7012149",
        "tgn:2000397",
        "tgn:7007248",
        "tgn:7029392"
    ],
    "tgn:id":2351311,
    "tgn:name":"Glen Arden",
    "tgn:placetype":[
        "aat:300008347"
    ]
},
  "bbox": [],
  "geometry": {"coordinates":[-84.9167,32.4667],"type":"Point"}
}