<<<<<<< HEAD
{
  "id": 7354364,
  "type": "Feature",
  "properties": {
    "tgn:hierarchy":[
        "tgn:7354364",
        "tgn:1000001",
        "tgn:1001960",
        "tgn:7005560",
        "tgn:7029392"
    ],
    "tgn:id":7354364,
    "tgn:name":"Chueca, Punta",
    "tgn:placetype":[
        "aat:300386846"
    ]
},
  "bbox": [],
  "geometry": {"coordinates":[-112.166667,29.016667],"type":"Point"}
}
=======
{"geometry":{"type":"Point","coordinates":[-112.166667,29.016667]},"type":"Feature","properties":{"hierarchy":["tgn:7354364","tgn:1000001","tgn:1001960","tgn:7005560","tgn:7029392"],"placetype":["aat:300386846"],"id":7354364,"name:xx":"Chueca, Punta"}}
>>>>>>> 03f74aca74312dbeaf24d7e61306dd6a786dc3d0
