{
  "id": 7354364,
  "type": "Feature",
  "properties": {
    "tgn:hierarchy":[
        "tgn:7354364",
        "tgn:1000001",
        "tgn:1001960",
        "tgn:7005560",
        "tgn:7029392"
    ],
    "tgn:id":7354364,
    "tgn:name":"Chueca, Punta",
    "tgn:placetype":[
        "aat:300386846"
    ]
},
  "bbox": [],
  "geometry": {"coordinates":[-112.166667,29.016667],"type":"Point"}
}