{
  "id": 1065762,
  "type": "Feature",
  "properties": {
    "tgn:hierarchy":[
        "tgn:1065762",
        "tgn:1000004",
        "tgn:7000191",
        "tgn:1000105",
        "tgn:7029392"
    ],
    "tgn:id":1065762,
    "tgn:name":"K\u0101sing\u0101thpur",
    "tgn:placetype":[
        "aat:300008347"
    ]
},
  "bbox": [],
  "geometry": {"coordinates":[89.6167,23.9667],"type":"Point"}
}