{
  "id": 7476619,
  "type": "Feature",
  "properties": {
    "tgn:hierarchy":[
        "tgn:7476619",
        "tgn:1000004",
        "tgn:7004300",
        "tgn:1000141",
        "tgn:7029392"
    ],
    "tgn:id":7476619,
    "tgn:name":"Weijiao",
    "tgn:placetype":[
        "aat:300386846"
    ]
},
  "bbox": [],
  "geometry": {"coordinates":[119.671769,23.683199],"type":"Point"}
}