{
  "id": 7573673,
  "type": "Feature",
  "properties": {
    "tgn:hierarchy":[
        "tgn:7573673",
        "tgn:1000004",
        "tgn:7000198",
        "tgn:1001894",
        "tgn:7029392"
    ],
    "tgn:id":7573673,
    "tgn:name:en":"Garethi",
    "tgn:placetype":[
        "aat:300008347"
    ]
},
  "bbox": [],
  "geometry": {"coordinates":[74.797164,23.496624],"type":"Point"}
}