<<<<<<< HEAD
{
  "id": 2254545,
  "type": "Feature",
  "properties": {
    "tgn:hierarchy":[
        "tgn:2254545",
        "tgn:1000001",
        "tgn:7012149",
        "tgn:1002564",
        "tgn:7007710",
        "tgn:7029392"
    ],
    "tgn:id":2254545,
    "tgn:name":"Coon Hill",
    "tgn:placetype":[
        "aat:300008798"
    ]
},
  "bbox": [],
  "geometry": {"coordinates":[-75.6167,41.35],"type":"Point"}
}
=======
{"geometry":{"type":"Point","coordinates":[-75.616700,41.350000]},"type":"Feature","properties":{"hierarchy":["tgn:2254545","tgn:1000001","tgn:7012149","tgn:1002564","tgn:7007710","tgn:7029392"],"placetype":["aat:300008798"],"id":2254545,"name:xx":"Coon Hill"}}
>>>>>>> 03f74aca74312dbeaf24d7e61306dd6a786dc3d0
