<<<<<<< HEAD
{
  "id": 7476416,
  "type": "Feature",
  "properties": {
    "tgn:hierarchy":[
        "tgn:7476416",
        "tgn:7487020",
        "tgn:1000004",
        "tgn:1000141",
        "tgn:7029392"
    ],
    "tgn:id":7476416,
    "tgn:name":"Pitoumian",
    "tgn:placetype":[
        "aat:300008347"
    ]
},
  "bbox": [],
  "geometry": {"coordinates":[120.767779,24.529986],"type":"Point"}
}
=======
{"geometry":{"type":"Point","coordinates":[120.767779,24.529986]},"type":"Feature","properties":{"hierarchy":["tgn:7476416","tgn:7487020","tgn:1000004","tgn:1000141","tgn:7029392"],"placetype":["aat:300008347"],"id":7476416,"name:xx":"Pitoumian"}}
>>>>>>> 03f74aca74312dbeaf24d7e61306dd6a786dc3d0
