{
  "id": 7572852,
  "type": "Feature",
  "properties": {
    "tgn:hierarchy":[
        "tgn:7572852",
        "tgn:1000004",
        "tgn:7000198",
        "tgn:7016694",
        "tgn:7029392"
    ],
    "tgn:id":7572852,
    "tgn:name:en":"Humma",
    "tgn:placetype":[
        "aat:300007783"
    ]
},
  "bbox": [],
  "geometry": {"coordinates":[85.066667,19.45],"type":"Point"}
}