{
  "id": 1034419,
  "type": "Feature",
  "properties": {
    "tgn:hierarchy":[
        "tgn:1034419",
        "tgn:1000003",
        "tgn:7002892",
        "tgn:1000070",
        "tgn:7029392"
    ],
    "tgn:id":1034419,
    "tgn:name":"Moncoutant",
    "tgn:placetype":[
        "aat:300008347"
    ]
},
  "bbox": [],
  "geometry": {"coordinates":[-0.5833,46.7167],"type":"Point"}
}