{
  "id": 7544779,
  "type": "Feature",
  "properties": {
    "tgn:hierarchy":[
        "tgn:7544779",
        "tgn:1000004",
        "tgn:1001869",
        "tgn:7000198",
        "tgn:7029392"
    ],
    "tgn:id":7544779,
    "tgn:name:en":"Alia Bada",
    "tgn:placetype":[
        "aat:300007783"
    ]
},
  "bbox": [],
  "geometry": {"coordinates":[70.216667,22.45],"type":"Point"}
}