{
  "id": 2247761,
  "type": "Feature",
  "properties": {
    "tgn:hierarchy":[
        "tgn:2247761",
        "tgn:1002309",
        "tgn:1000001",
        "tgn:7012149",
        "tgn:7007565",
        "tgn:7029392"
    ],
    "tgn:id":2247761,
    "tgn:name":"Cohansey Point",
    "tgn:placetype":[
        "aat:300008850"
    ]
},
  "bbox": [],
  "geometry": {"coordinates":[-75.35,39.3333],"type":"Point"}
}