<<<<<<< HEAD
{
  "id": 2257851,
  "type": "Feature",
  "properties": {
    "tgn:hierarchy":[
        "tgn:2257851",
        "tgn:1000001",
        "tgn:7012149",
        "tgn:2001451",
        "tgn:7007566",
        "tgn:7029392"
    ],
    "tgn:id":2257851,
    "tgn:name":"Corrales Main Canal",
    "tgn:placetype":[
        "aat:300006075"
    ]
},
  "bbox": [],
  "geometry": {"coordinates":[-106.6333,35.2167],"type":"Point"}
}
=======
{"geometry":{"type":"Point","coordinates":[-106.633300,35.216700]},"type":"Feature","properties":{"hierarchy":["tgn:2257851","tgn:1000001","tgn:7012149","tgn:2001451","tgn:7007566","tgn:7029392"],"placetype":["aat:300006075"],"id":2257851,"name:xx":"Corrales Main Canal"}}
>>>>>>> 03f74aca74312dbeaf24d7e61306dd6a786dc3d0
