<<<<<<< HEAD
{
  "id": 7026560,
  "type": "Feature",
  "properties": {
    "tgn:hierarchy":[
        "tgn:7026560",
        "tgn:7002445",
        "tgn:1000003",
        "tgn:7008132",
        "tgn:7008591",
        "tgn:7029392"
    ],
    "tgn:id":7026560,
    "tgn:name":"Baunton",
    "tgn:placetype":[
        "aat:300008347",
        "aat:300008372"
    ]
},
  "bbox": [],
  "geometry": {"coordinates":[-1.9667,51.7333],"type":"Point"}
}
=======
{"geometry":{"type":"Point","coordinates":[-1.966700,51.733300]},"type":"Feature","properties":{"hierarchy":["tgn:7026560","tgn:7002445","tgn:1000003","tgn:7008132","tgn:7008591","tgn:7029392"],"placetype":["aat:300008347","aat:300008372"],"id":7026560,"name:xx":"Baunton"}}
>>>>>>> 03f74aca74312dbeaf24d7e61306dd6a786dc3d0
