{
  "id": 2353557,
  "type": "Feature",
  "properties": {
    "tgn:hierarchy":[
        "tgn:2353557",
        "tgn:1000001",
        "tgn:7012149",
        "tgn:2001711",
        "tgn:7007708",
        "tgn:7029392"
    ],
    "tgn:id":2353557,
    "tgn:name":"Gold Hill",
    "tgn:placetype":[
        "aat:300008798"
    ]
},
  "bbox": [],
  "geometry": {"coordinates":[-123.0167,42.4333],"type":"Point"}
}