{
  "id": 7544372,
  "type": "Feature",
  "properties": {
    "tgn:hierarchy":[
        "tgn:7544372",
        "tgn:7001242",
        "tgn:7016833",
        "tgn:7001336",
        "tgn:7029392"
    ],
    "tgn:id":7544372,
    "tgn:name:en":"Maqtila, Gebel",
    "tgn:placetype":[
        "aat:300008795"
    ]
},
  "bbox": [],
  "geometry": {"coordinates":[34.172997,28.704224],"type":"Point"}
}