{
  "id": 7531916,
  "type": "Feature",
  "properties": {
    "tgn:hierarchy":[
        "tgn:7531916",
        "tgn:7001242",
        "tgn:7016833",
        "tgn:1001091",
        "tgn:7029392"
    ],
    "tgn:id":7531916,
    "tgn:name":"Mustashf\u00e1 Shubr\u0101 al '\u0100mm",
    "tgn:placetype":[
        "aat:300006676"
    ]
},
  "bbox": [],
  "geometry": {"coordinates":[31.252573,30.073029],"type":"Point"}
}