{
  "id": 7076350,
  "type": "Feature",
  "properties": {
    "tgn:hierarchy":[
        "tgn:7076350",
        "tgn:7003692",
        "tgn:1000003",
        "tgn:7000084",
        "tgn:7029392"
    ],
    "tgn:id":7076350,
    "tgn:name":"Emmingen-Liptingen",
    "tgn:placetype":[
        "aat:300008347"
    ]
},
  "bbox": [],
  "geometry": {"coordinates":[8.883333,47.933333],"type":"Point"}
}