{
  "id": 2326919,
  "type": "Feature",
  "properties": {
    "tgn:hierarchy":[
        "tgn:2326919",
        "tgn:7006450",
        "tgn:1000001",
        "tgn:7019698",
        "tgn:7012149",
        "tgn:7029392"
    ],
    "tgn:id":2326919,
    "tgn:name":"Fire Lake",
    "tgn:placetype":[
        "aat:300008680"
    ]
},
  "bbox": [],
  "geometry": {"coordinates":[-150.55,60.4333],"type":"Point"}
}