{
  "id": 7593917,
  "type": "Feature",
  "properties": {
    "tgn:hierarchy":[
        "tgn:7593917",
        "tgn:1000003",
        "tgn:1001780",
        "tgn:7029392"
    ],
    "tgn:id":7593917,
    "tgn:name":"Olomouck\u00fd Kraj",
    "tgn:placetype":[
        "aat:300387064",
        "aat:300236112"
    ]
},
  "bbox": [],
  "geometry": {"coordinates":[17.166,49.75],"type":"Point"}
}