{
  "id": 7586747,
  "type": "Feature",
  "properties": {
    "tgn:hierarchy":[
        "tgn:7586747",
        "tgn:1000004",
        "tgn:7000198",
        "tgn:7000799",
        "tgn:7029392"
    ],
    "tgn:id":7586747,
    "tgn:name:en":"Poslut",
    "tgn:placetype":[
        "aat:300008795"
    ]
},
  "bbox": [],
  "geometry": {"coordinates":[74.479674,34.499042],"type":"Point"}
}