{
  "id": 7245405,
  "type": "Feature",
  "properties": {
    "tgn:hierarchy":[
        "tgn:7245405",
        "tgn:7003465",
        "tgn:1000003",
        "tgn:1000063",
        "tgn:4012014",
        "tgn:7029392"
    ],
    "tgn:id":7245405,
    "tgn:name":"Battincourt",
    "tgn:placetype":[
        "aat:300008347"
    ]
},
  "bbox": [],
  "geometry": {"coordinates":[5.766667,49.583333],"type":"Point"}
}