{
  "id": 2134305,
  "type": "Feature",
  "properties": {
    "tgn:hierarchy":[
        "tgn:2134305",
        "tgn:1002996",
        "tgn:1000001",
        "tgn:7012149",
        "tgn:7007711",
        "tgn:7029392"
    ],
    "tgn:id":2134305,
    "tgn:name":"Annaquatucket Reservoir",
    "tgn:placetype":[
        "aat:300006191"
    ]
},
  "bbox": [],
  "geometry": {"coordinates":[-71.4333,41.55],"type":"Point"}
}