{
  "id": 7429504,
  "type": "Feature",
  "properties": {
    "tgn:hierarchy":[
        "tgn:7429504",
        "tgn:1001835",
        "tgn:1000001",
        "tgn:7005560",
        "tgn:7029392"
    ],
    "tgn:id":7429504,
    "tgn:name":"Guata",
    "tgn:placetype":[
        "aat:300008347"
    ]
},
  "bbox": [],
  "geometry": {"coordinates":[-115.633333,31.383333],"type":"Point"}
}