{
  "id": 2493370,
  "type": "Feature",
  "properties": {
    "tgn:hierarchy":[
        "tgn:2493370",
        "tgn:1000001",
        "tgn:7012149",
        "tgn:1002251",
        "tgn:7007826",
        "tgn:7029392"
    ],
    "tgn:id":2493370,
    "tgn:name":"Marrow Marsh",
    "tgn:placetype":[
        "aat:300008905"
    ]
},
  "bbox": [],
  "geometry": {"coordinates":[-94.9167,29.6667],"type":"Point"}
}