{
  "id": 2178695,
  "type": "Feature",
  "properties": {
    "tgn:hierarchy":[
        "tgn:2178695",
        "tgn:1000001",
        "tgn:7012149",
        "tgn:2000216",
        "tgn:7007158",
        "tgn:7029392"
    ],
    "tgn:id":2178695,
    "tgn:name":"Blacktail Creek",
    "tgn:placetype":[
        "aat:300008706"
    ]
},
  "bbox": [],
  "geometry": {"coordinates":[-106.5667,40.0833],"type":"Point"}
}