{
  "id": 2710695,
  "type": "Feature",
  "properties": {
    "tgn:hierarchy":[
        "tgn:2710695",
        "tgn:1000001",
        "tgn:7012149",
        "tgn:2001915",
        "tgn:7007825",
        "tgn:7029392"
    ],
    "tgn:id":2710695,
    "tgn:name":"Tan Yard Bayou",
    "tgn:placetype":[
        "aat:300008699"
    ]
},
  "bbox": [],
  "geometry": {"coordinates":[-90.0333,35.1333],"type":"Point"}
}