{
  "id": 7351702,
  "type": "Feature",
  "properties": {
    "tgn:hierarchy":[
        "tgn:7351702",
        "tgn:7005581",
        "tgn:1000001",
        "tgn:7005560",
        "tgn:7029392"
    ],
    "tgn:id":7351702,
    "tgn:name":"Caimero",
    "tgn:placetype":[
        "aat:300387007"
    ]
},
  "bbox": [],
  "geometry": {"coordinates":[-108.283333,27.233333],"type":"Point"}
}