{
  "id": 2150243,
  "type": "Feature",
  "properties": {
    "tgn:hierarchy":[
        "tgn:2150243",
        "tgn:1000001",
        "tgn:7012149",
        "tgn:1002699",
        "tgn:7007708",
        "tgn:7029392"
    ],
    "tgn:id":2150243,
    "tgn:name":"Base Line",
    "tgn:placetype":[
        "aat:300008347"
    ]
},
  "bbox": [],
  "geometry": {"coordinates":[-122.45,45.5167],"type":"Point"}
}