{
  "id": 2182595,
  "type": "Feature",
  "properties": {
    "tgn:hierarchy":[
        "tgn:2182595",
        "tgn:1000001",
        "tgn:2000272",
        "tgn:7012149",
        "tgn:7007240",
        "tgn:7029392"
    ],
    "tgn:id":2182595,
    "tgn:name":"Blue Spring",
    "tgn:placetype":[
        "aat:300008697"
    ]
},
  "bbox": [],
  "geometry": {"coordinates":[-85.8833,30.85],"type":"Point"}
}