{
  "id": 7398632,
  "type": "Feature",
  "properties": {
    "tgn:hierarchy":[
        "tgn:7398632",
        "tgn:1000001",
        "tgn:7005593",
        "tgn:7005560",
        "tgn:7029392"
    ],
    "tgn:id":7398632,
    "tgn:name":"Rancho Nuevo",
    "tgn:placetype":[
        "aat:300008347"
    ]
},
  "bbox": [],
  "geometry": {"coordinates":[-99.916667,20.545833],"type":"Point"}
}