<<<<<<< HEAD
{
  "id": 7050373,
  "type": "Feature",
  "properties": {
    "tgn:hierarchy":[
        "tgn:7050373",
        "tgn:1001724",
        "tgn:1000003",
        "tgn:7003121",
        "tgn:1000080",
        "tgn:7029392"
    ],
    "tgn:id":7050373,
    "tgn:name":"Nostra Signora de su Monte",
    "tgn:placetype":[
        "aat:300007558"
    ]
},
  "bbox": [],
  "geometry": {"coordinates":[9.25,40.083333],"type":"Point"}
}
=======
{"geometry":{"type":"Point","coordinates":[9.250000,40.083333]},"type":"Feature","properties":{"hierarchy":["tgn:7050373","tgn:1001724","tgn:1000003","tgn:7003121","tgn:1000080","tgn:7029392"],"placetype":["aat:300007558"],"id":7050373,"name:xx":"Nostra Signora de su Monte"}}
>>>>>>> 03f74aca74312dbeaf24d7e61306dd6a786dc3d0
