<<<<<<< HEAD
{
  "id": 7373154,
  "type": "Feature",
  "properties": {
    "tgn:hierarchy":[
        "tgn:7373154",
        "tgn:1000001",
        "tgn:1001906",
        "tgn:7005560",
        "tgn:7029392"
    ],
    "tgn:id":7373154,
    "tgn:name":"La Palmilla",
    "tgn:placetype":[
        "aat:300008699"
    ]
},
  "bbox": [],
  "geometry": {"coordinates":[-104.433333,21.416667],"type":"Point"}
}
=======
{"geometry":{"type":"Point","coordinates":[-104.433333,21.416667]},"type":"Feature","properties":{"hierarchy":["tgn:7373154","tgn:1000001","tgn:1001906","tgn:7005560","tgn:7029392"],"placetype":["aat:300008699"],"id":7373154,"name:xx":"La Palmilla"}}
>>>>>>> 03f74aca74312dbeaf24d7e61306dd6a786dc3d0
