{
  "id": 7365646,
  "type": "Feature",
  "properties": {
    "tgn:hierarchy":[
        "tgn:7365646",
        "tgn:7005580",
        "tgn:1000001",
        "tgn:7005560",
        "tgn:7029392"
    ],
    "tgn:id":7365646,
    "tgn:name":"Frontera Comalapa",
    "tgn:placetype":[
        "aat:300008347"
    ]
},
  "bbox": [],
  "geometry": {"coordinates":[-92.133333,15.65],"type":"Point"}
}