<<<<<<< HEAD
{
  "id": 2767353,
  "type": "Feature",
  "properties": {
    "tgn:hierarchy":[
        "tgn:2767353",
        "tgn:1000001",
        "tgn:7012149",
        "tgn:2000208",
        "tgn:7007158",
        "tgn:7029392"
    ],
    "tgn:id":2767353,
    "tgn:name":"White Sands Spring",
    "tgn:placetype":[
        "aat:300008697"
    ]
},
  "bbox": [],
  "geometry": {"coordinates":[-108.6667,37.8167],"type":"Point"}
}
=======
{"geometry":{"type":"Point","coordinates":[-108.666700,37.816700]},"type":"Feature","properties":{"hierarchy":["tgn:2767353","tgn:1000001","tgn:7012149","tgn:2000208","tgn:7007158","tgn:7029392"],"placetype":["aat:300008697"],"id":2767353,"name:xx":"White Sands Spring"}}
>>>>>>> 03f74aca74312dbeaf24d7e61306dd6a786dc3d0
