{
  "id": 2267667,
  "type": "Feature",
  "properties": {
    "tgn:hierarchy":[
        "tgn:2267667",
        "tgn:1000001",
        "tgn:7012149",
        "tgn:1002636",
        "tgn:7007708",
        "tgn:7029392"
    ],
    "tgn:id":2267667,
    "tgn:name":"Croisan Ridge",
    "tgn:placetype":[
        "aat:300266640"
    ]
},
  "bbox": [],
  "geometry": {"coordinates":[-123.0833,44.8833],"type":"Point"}
}