{
  "id": 1139597,
  "type": "Feature",
  "properties": {
    "tgn:hierarchy":[
        "tgn:1139597",
        "tgn:1000004",
        "tgn:7002077",
        "tgn:1000111",
        "tgn:7029392"
    ],
    "tgn:id":1139597,
    "tgn:name":"Shiting",
    "tgn:placetype":[
        "aat:300008347"
    ]
},
  "bbox": [],
  "geometry": {"coordinates":[115.7167,39.5167],"type":"Point"}
}