{
  "id": 2503627,
  "type": "Feature",
  "properties": {
    "tgn:hierarchy":[
        "tgn:2503627",
        "tgn:1000001",
        "tgn:2000952",
        "tgn:7012149",
        "tgn:7007520",
        "tgn:7029392"
    ],
    "tgn:id":2503627,
    "tgn:name":"Meade Island",
    "tgn:placetype":[
        "aat:300008791"
    ]
},
  "bbox": [],
  "geometry": {"coordinates":[-83.6333,45.9333],"type":"Point"}
}