{
  "id": 7051714,
  "type": "Feature",
  "properties": {
    "tgn:hierarchy":[
        "tgn:7051714",
        "tgn:7003164",
        "tgn:1000003",
        "tgn:7009760",
        "tgn:1000080",
        "tgn:7029392"
    ],
    "tgn:id":7051714,
    "tgn:name":"Marchese, Punta del",
    "tgn:placetype":[
        "aat:300386846"
    ]
},
  "bbox": [],
  "geometry": {"coordinates":[10.083333,42.616667],"type":"Point"}
}