{
  "id": 1105613,
  "type": "Feature",
  "properties": {
    "tgn:hierarchy":[
        "tgn:1105613",
        "tgn:7006477",
        "tgn:1001519",
        "tgn:1000002",
        "tgn:7029392"
    ],
    "tgn:id":1105613,
    "tgn:name":"Mercedario, Cerro",
    "tgn:placetype":[
        "aat:300008795"
    ]
},
  "bbox": [],
  "geometry": {"coordinates":[-70.1667,-31.9833],"type":"Point"}
}