{
  "id": 7362474,
  "type": "Feature",
  "properties": {
    "tgn:hierarchy":[
        "tgn:7362474",
        "tgn:7005583",
        "tgn:1000001",
        "tgn:7005560",
        "tgn:7029392"
    ],
    "tgn:id":7362474,
    "tgn:name":"El Durazno",
    "tgn:placetype":[
        "aat:300008347"
    ]
},
  "bbox": [],
  "geometry": {"coordinates":[-106.366667,25.233333],"type":"Point"}
}