{
  "id": 7456680,
  "type": "Feature",
  "properties": {
    "tgn:hierarchy":[
        "tgn:7456680",
        "tgn:7002444",
        "tgn:1000003",
        "tgn:7008094",
        "tgn:7008591",
        "tgn:7029392"
    ],
    "tgn:id":7456680,
    "tgn:name:en":"Obbe, The",
    "tgn:placetype":[
        "aat:300132316"
    ]
},
  "bbox": [],
  "geometry": {"coordinates":[-7.05,57.766667],"type":"Point"}
}