{
  "id": 7011190,
  "type": "Feature",
  "properties": {
    "tgn:hierarchy":[
        "tgn:7011190",
        "tgn:7011270",
        "tgn:7002674",
        "tgn:1000003",
        "tgn:1000074",
        "tgn:7029392"
    ],
    "tgn:id":7011190,
    "tgn:name:en":"Syros",
    "tgn:placetype":[
        "aat:300008791"
    ]
},
  "bbox": [],
  "geometry": {"coordinates":[24.916667,37.433333],"type":"Point"}
}