{
  "id": 7076377,
  "type": "Feature",
  "properties": {
    "tgn:hierarchy":[
        "tgn:7076377",
        "tgn:1000003",
        "tgn:7003677",
        "tgn:7000084",
        "tgn:7029392"
    ],
    "tgn:id":7076377,
    "tgn:name":"Wehr",
    "tgn:placetype":[
        "aat:300008347"
    ]
},
  "bbox": [],
  "geometry": {"coordinates":[5.916667,50.983333],"type":"Point"}
}