{
  "id": 7589823,
  "type": "Feature",
  "properties": {
    "tgn:hierarchy":[
        "tgn:7589823",
        "tgn:1000004",
        "tgn:1001871",
        "tgn:7000198",
        "tgn:7029392"
    ],
    "tgn:id":7589823,
    "tgn:name:en":"Janesron Jh\u012bl",
    "tgn:placetype":[
        "aat:300008905"
    ]
},
  "bbox": [],
  "geometry": {"coordinates":[77.034078,29.845949],"type":"Point"}
}