{
  "id": 2716844,
  "type": "Feature",
  "properties": {
    "tgn:hierarchy":[
        "tgn:2716844",
        "tgn:2002239",
        "tgn:1000001",
        "tgn:7012149",
        "tgn:7007920",
        "tgn:7029392"
    ],
    "tgn:id":2716844,
    "tgn:name":"Theon",
    "tgn:placetype":[
        "aat:300008347"
    ]
},
  "bbox": [],
  "geometry": {"coordinates":[-117.0833,46.15],"type":"Point"}
}