<<<<<<< HEAD
{
  "id": 7475301,
  "type": "Feature",
  "properties": {
    "tgn:hierarchy":[
        "tgn:7475301",
        "tgn:1000004",
        "tgn:1000454",
        "tgn:1000141",
        "tgn:7029392"
    ],
    "tgn:id":7475301,
    "tgn:name":"Chencuokeng Qiao",
    "tgn:placetype":[
        "aat:300007836"
    ]
},
  "bbox": [],
  "geometry": {"coordinates":[121.516538,25.255033],"type":"Point"}
}
=======
{"geometry":{"type":"Point","coordinates":[121.516538,25.255033]},"type":"Feature","properties":{"hierarchy":["tgn:7475301","tgn:1000004","tgn:1000454","tgn:1000141","tgn:7029392"],"placetype":["aat:300007836"],"id":7475301,"name:xx":"Chencuokeng Qiao"}}
>>>>>>> 03f74aca74312dbeaf24d7e61306dd6a786dc3d0
