{
  "id": 7215789,
  "type": "Feature",
  "properties": {
    "tgn:hierarchy":[
        "tgn:7215789",
        "tgn:1000003",
        "tgn:7003682",
        "tgn:7000084",
        "tgn:7029392"
    ],
    "tgn:id":7215789,
    "tgn:name":"Altlay",
    "tgn:placetype":[
        "aat:300008347"
    ]
},
  "bbox": [],
  "geometry": {"coordinates":[7.266667,49.983333],"type":"Point"}
}