{
  "id": 2693098,
  "type": "Feature",
  "properties": {
    "tgn:hierarchy":[
        "tgn:2693098",
        "tgn:1000001",
        "tgn:7012149",
        "tgn:7007522",
        "tgn:7029392"
    ],
    "tgn:id":2693098,
    "tgn:name":"Steep Hill Creek",
    "tgn:placetype":[
        "aat:300008706"
    ]
},
  "bbox": [],
  "geometry": {"coordinates":[-90.7833,31.6333],"type":"Point"}
}