{
  "id": 1110068,
  "type": "Feature",
  "properties": {
    "tgn:hierarchy":[
        "tgn:1110068",
        "tgn:1000001",
        "tgn:7012149",
        "tgn:7007250",
        "tgn:7029392"
    ],
    "tgn:id":1110068,
    "tgn:name":"Lost River Range",
    "tgn:placetype":[
        "aat:300386831"
    ]
},
  "bbox": [],
  "geometry": {"coordinates":[-113.3833,43.9833],"type":"Point"}
}