{
  "id": 2756767,
  "type": "Feature",
  "properties": {
    "tgn:hierarchy":[
        "tgn:2756767",
        "tgn:7006450",
        "tgn:1000001",
        "tgn:2124053",
        "tgn:7012149",
        "tgn:7029392"
    ],
    "tgn:id":2756767,
    "tgn:name":"Wells Mountain",
    "tgn:placetype":[
        "aat:300008798"
    ]
},
  "bbox": [],
  "geometry": {"coordinates":[-149.2167,62.4167],"type":"Point"}
}