<<<<<<< HEAD
{
  "id": 2404111,
  "type": "Feature",
  "properties": {
    "tgn:hierarchy":[
        "tgn:2404111",
        "tgn:1000001",
        "tgn:7012149",
        "tgn:2001297",
        "tgn:7007524",
        "tgn:7029392"
    ],
    "tgn:id":2404111,
    "tgn:name":"Howes Reservoir",
    "tgn:placetype":[
        "aat:300006191"
    ]
},
  "bbox": [],
  "geometry": {"coordinates":[-106.0833,45.2333],"type":"Point"}
}
=======
{"geometry":{"type":"Point","coordinates":[-106.083300,45.233300]},"type":"Feature","properties":{"hierarchy":["tgn:2404111","tgn:1000001","tgn:7012149","tgn:2001297","tgn:7007524","tgn:7029392"],"placetype":["aat:300006191"],"id":2404111,"name:xx":"Howes Reservoir"}}
>>>>>>> 03f74aca74312dbeaf24d7e61306dd6a786dc3d0
