{
  "id": 2633215,
  "type": "Feature",
  "properties": {
    "tgn:hierarchy":[
        "tgn:2633215",
        "tgn:1000001",
        "tgn:7012149",
        "tgn:2000483",
        "tgn:7007250",
        "tgn:7029392"
    ],
    "tgn:id":2633215,
    "tgn:name":"Ruiz Lake",
    "tgn:placetype":[
        "aat:300008680"
    ]
},
  "bbox": [],
  "geometry": {"coordinates":[-114.2333,42.9833],"type":"Point"}
}