{
  "id": 1134459,
  "type": "Feature",
  "properties": {
    "tgn:hierarchy":[
        "tgn:1134459",
        "tgn:1000001",
        "tgn:7012149",
        "tgn:7007826",
        "tgn:7029392"
    ],
    "tgn:id":1134459,
    "tgn:name":"San Diego Creek",
    "tgn:placetype":[
        "aat:300008706"
    ]
},
  "bbox": [],
  "geometry": {"coordinates":[-98.4667,28.0333],"type":"Point"}
}