{
  "id": 1112924,
  "type": "Feature",
  "properties": {
    "tgn:hierarchy":[
        "tgn:1112924",
        "tgn:7002448",
        "tgn:7008698",
        "tgn:1000003",
        "tgn:7008591",
        "tgn:7029392"
    ],
    "tgn:id":1112924,
    "tgn:name:en":"Dundrum Bay",
    "tgn:placetype":[
        "aat:300132316"
    ]
},
  "bbox": [],
  "geometry": {"coordinates":[-5.75,54.233333],"type":"Point"}
}