{
  "id": 7286767,
  "type": "Feature",
  "properties": {
    "tgn:hierarchy":[
        "tgn:7286767",
        "tgn:7002464",
        "tgn:1000049",
        "tgn:1000002",
        "tgn:7029392"
    ],
    "tgn:id":7286767,
    "tgn:name":"Gua\u00f1oco, Pampa",
    "tgn:placetype":[
        "aat:300008805"
    ]
},
  "bbox": [],
  "geometry": {"coordinates":[-69.283333,-18.033333],"type":"Point"}
}