{
  "id": 7336019,
  "type": "Feature",
  "properties": {
    "tgn:hierarchy":[
        "tgn:7336019",
        "tgn:7001122",
        "tgn:1000003",
        "tgn:7002765",
        "tgn:1000095",
        "tgn:7029392"
    ],
    "tgn:id":7336019,
    "tgn:name":"Gabina, Isla",
    "tgn:placetype":[
        "aat:300008791"
    ]
},
  "bbox": [],
  "geometry": {"coordinates":[2.983333,39.333333],"type":"Point"}
}