{
  "id": 7068927,
  "type": "Feature",
  "properties": {
    "tgn:hierarchy":[
        "tgn:7068927",
        "tgn:7003669",
        "tgn:1000003",
        "tgn:7000084",
        "tgn:7029392"
    ],
    "tgn:id":7068927,
    "tgn:name":"Steibis",
    "tgn:placetype":[
        "aat:300008347"
    ]
},
  "bbox": [],
  "geometry": {"coordinates":[10.016667,47.533333],"type":"Point"}
}