{
  "id": 2301197,
  "type": "Feature",
  "properties": {
    "tgn:hierarchy":[
        "tgn:2301197",
        "tgn:1000001",
        "tgn:2001260",
        "tgn:7012149",
        "tgn:7007524",
        "tgn:7029392"
    ],
    "tgn:id":2301197,
    "tgn:name":"Dunkwaden Flats",
    "tgn:placetype":[
        "aat:300008905"
    ]
},
  "bbox": [],
  "geometry": {"coordinates":[-113.3833,45.2333],"type":"Point"}
}