{
  "id": 7258887,
  "type": "Feature",
  "properties": {
    "tgn:hierarchy":[
        "tgn:7258887",
        "tgn:1000003",
        "tgn:7003613",
        "tgn:7016845",
        "tgn:7029392"
    ],
    "tgn:id":7258887,
    "tgn:name:nl":"Beppegat",
    "tgn:placetype":[
        "aat:300132317"
    ]
},
  "bbox": [],
  "geometry": {"coordinates":[6.883333,53.383333],"type":"Point"}
}