{
  "id": 7455347,
  "type": "Feature",
  "properties": {
    "tgn:hierarchy":[
        "tgn:7455347",
        "tgn:7019094",
        "tgn:7002444",
        "tgn:1000003",
        "tgn:7008591",
        "tgn:7029392"
    ],
    "tgn:id":7455347,
    "tgn:name:en":"C\u00e0th Sgeir",
    "tgn:placetype":[
        "aat:300008808"
    ]
},
  "bbox": [],
  "geometry": {"coordinates":[-5.783333,55.666667],"type":"Point"}
}