{
  "id": 2719499,
  "type": "Feature",
  "properties": {
    "tgn:hierarchy":[
        "tgn:2719499",
        "tgn:1000001",
        "tgn:7012149",
        "tgn:2000346",
        "tgn:7007248",
        "tgn:7029392"
    ],
    "tgn:id":2719499,
    "tgn:name":"Three Forks",
    "tgn:placetype":[
        "aat:300008347"
    ]
},
  "bbox": [],
  "geometry": {"coordinates":[-84.1833,34.65],"type":"Point"}
}