{
  "id": 2026092,
  "type": "Feature",
  "properties": {
    "tgn:hierarchy":[
        "tgn:2026092",
        "tgn:1000001",
        "tgn:7012149",
        "tgn:2000485",
        "tgn:7007250",
        "tgn:7029392"
    ],
    "tgn:id":2026092,
    "tgn:name":"Rupert",
    "tgn:placetype":[
        "aat:300008347"
    ]
},
  "bbox": [],
  "geometry": {"coordinates":[-113.6667,42.6167],"type":"Point"}
}