<<<<<<< HEAD
{
  "id": 2154034,
  "type": "Feature",
  "properties": {
    "tgn:hierarchy":[
        "tgn:2154034",
        "tgn:1000001",
        "tgn:7012149",
        "tgn:1002545",
        "tgn:7007157",
        "tgn:7029392"
    ],
    "tgn:id":2154034,
    "tgn:name":"Bear Creek",
    "tgn:placetype":[
        "aat:300008706"
    ]
},
  "bbox": [],
  "geometry": {"coordinates":[-118.5667,35.6833],"type":"Point"}
}
=======
{"geometry":{"type":"Point","coordinates":[-118.566700,35.683300]},"type":"Feature","properties":{"hierarchy":["tgn:2154034","tgn:1000001","tgn:7012149","tgn:1002545","tgn:7007157","tgn:7029392"],"placetype":["aat:300008706"],"id":2154034,"name:xx":"Bear Creek"}}
>>>>>>> 03f74aca74312dbeaf24d7e61306dd6a786dc3d0
