{
  "id": 7443074,
  "type": "Feature",
  "properties": {
    "tgn:hierarchy":[
        "tgn:7443074",
        "tgn:7002445",
        "tgn:1000003",
        "tgn:7008153",
        "tgn:7008591",
        "tgn:7029392"
    ],
    "tgn:id":7443074,
    "tgn:name:en":"Cliff End Banks",
    "tgn:placetype":[
        "aat:300387036"
    ]
},
  "bbox": [],
  "geometry": {"coordinates":[1.283333,51.398611],"type":"Point"}
}