{
  "id": 2365891,
  "type": "Feature",
  "properties": {
    "tgn:hierarchy":[
        "tgn:2365891",
        "tgn:2000919",
        "tgn:1000001",
        "tgn:7012149",
        "tgn:7007515",
        "tgn:7029392"
    ],
    "tgn:id":2365891,
    "tgn:name":"Grew Island",
    "tgn:placetype":[
        "aat:300008791"
    ]
},
  "bbox": [],
  "geometry": {"coordinates":[-68.8833,47.1667],"type":"Point"}
}