{
  "id": 2396729,
  "type": "Feature",
  "properties": {
    "tgn:hierarchy":[
        "tgn:2396729",
        "tgn:1002134",
        "tgn:1000001",
        "tgn:7012149",
        "tgn:7007251",
        "tgn:7029392"
    ],
    "tgn:id":2396729,
    "tgn:name":"Homan Creek",
    "tgn:placetype":[
        "aat:300008706"
    ]
},
  "bbox": [],
  "geometry": {"coordinates":[-91.3167,39.9667],"type":"Point"}
}