{
  "id": 2528708,
  "type": "Feature",
  "properties": {
    "tgn:hierarchy":[
        "tgn:2528708",
        "tgn:1000001",
        "tgn:2001265",
        "tgn:7012149",
        "tgn:7007524",
        "tgn:7029392"
    ],
    "tgn:id":2528708,
    "tgn:name":"Mud Butte",
    "tgn:placetype":[
        "aat:300008798"
    ]
},
  "bbox": [],
  "geometry": {"coordinates":[-104.0667,45.4667],"type":"Point"}
}