{
  "id": 2631338,
  "type": "Feature",
  "properties": {
    "tgn:hierarchy":[
        "tgn:2631338",
        "tgn:1000001",
        "tgn:7012149",
        "tgn:1002961",
        "tgn:7007568",
        "tgn:7029392"
    ],
    "tgn:id":2631338,
    "tgn:name":"Round Pond",
    "tgn:placetype":[
        "aat:300008680"
    ]
},
  "bbox": [],
  "geometry": {"coordinates":[-74.5833,41.9333],"type":"Point"}
}