{
  "id": 2427010,
  "type": "Feature",
  "properties": {
    "tgn:hierarchy":[
        "tgn:2427010",
        "tgn:1000001",
        "tgn:7006451",
        "tgn:7012149",
        "tgn:2000103",
        "tgn:7029392"
    ],
    "tgn:id":2427010,
    "tgn:name":"Jones Tank",
    "tgn:placetype":[
        "aat:300006191"
    ]
},
  "bbox": [],
  "geometry": {"coordinates":[-111.85,34.6833],"type":"Point"}
}