{
  "id": 2772989,
  "type": "Feature",
  "properties": {
    "tgn:hierarchy":[
        "tgn:2772989",
        "tgn:1000001",
        "tgn:2000469",
        "tgn:7012149",
        "tgn:7007250",
        "tgn:7029392"
    ],
    "tgn:id":2772989,
    "tgn:name":"Williams Peak",
    "tgn:placetype":[
        "aat:300008798"
    ]
},
  "bbox": [],
  "geometry": {"coordinates":[-114.7833,46.65],"type":"Point"}
}