{
  "id": 2760681,
  "type": "Feature",
  "properties": {
    "tgn:hierarchy":[
        "tgn:2760681",
        "tgn:1000001",
        "tgn:2001409",
        "tgn:7012149",
        "tgn:7007526",
        "tgn:7029392"
    ],
    "tgn:id":2760681,
    "tgn:name":"West Fork of Old River",
    "tgn:placetype":[
        "aat:300008707"
    ]
},
  "bbox": [],
  "geometry": {"coordinates":[-118.7167,39.5667],"type":"Point"}
}