<<<<<<< HEAD
{
  "id": 2760681,
  "type": "Feature",
  "properties": {
    "tgn:hierarchy":[
        "tgn:2760681",
        "tgn:1000001",
        "tgn:2001409",
        "tgn:7012149",
        "tgn:7007526",
        "tgn:7029392"
    ],
    "tgn:id":2760681,
    "tgn:name":"West Fork of Old River",
    "tgn:placetype":[
        "aat:300008707"
    ]
},
  "bbox": [],
  "geometry": {"coordinates":[-118.7167,39.5667],"type":"Point"}
}
=======
{"geometry":{"type":"Point","coordinates":[-118.716700,39.566700]},"type":"Feature","properties":{"hierarchy":["tgn:2760681","tgn:1000001","tgn:2001409","tgn:7012149","tgn:7007526","tgn:7029392"],"placetype":["aat:300008707"],"id":2760681,"name:xx":"West Fork of Old River"}}
>>>>>>> 03f74aca74312dbeaf24d7e61306dd6a786dc3d0
