{
  "id": 7318257,
  "type": "Feature",
  "properties": {
    "tgn:hierarchy":[
        "tgn:7318257",
        "tgn:1001630",
        "tgn:1000049",
        "tgn:1000002",
        "tgn:7029392"
    ],
    "tgn:id":7318257,
    "tgn:name":"Checo, Cerro",
    "tgn:placetype":[
        "aat:300008795"
    ]
},
  "bbox": [],
  "geometry": {"coordinates":[-70.083333,-27.516667],"type":"Point"}
}