{
  "id": 7385661,
  "type": "Feature",
  "properties": {
    "tgn:hierarchy":[
        "tgn:7385661",
        "tgn:7005581",
        "tgn:1000001",
        "tgn:7005560",
        "tgn:7029392"
    ],
    "tgn:id":7385661,
    "tgn:name":"Pi\u00f1ones, Arroyo de los",
    "tgn:placetype":[
        "aat:300008699"
    ]
},
  "bbox": [],
  "geometry": {"coordinates":[-106.266667,29.033333],"type":"Point"}
}