{
  "id": 7136294,
  "type": "Feature",
  "properties": {
    "tgn:hierarchy":[
        "tgn:7136294",
        "tgn:7003669",
        "tgn:1000003",
        "tgn:7000084",
        "tgn:7029392"
    ],
    "tgn:id":7136294,
    "tgn:name":"Muthmannsreuth",
    "tgn:placetype":[
        "aat:300008347"
    ]
},
  "bbox": [],
  "geometry": {"coordinates":[11.483333,49.866667],"type":"Point"}
}