{
  "id": 2489144,
  "type": "Feature",
  "properties": {
    "tgn:hierarchy":[
        "tgn:2489144",
        "tgn:1000001",
        "tgn:7012149",
        "tgn:2001195",
        "tgn:7007523",
        "tgn:7029392"
    ],
    "tgn:id":2489144,
    "tgn:name":"Majors Hollow",
    "tgn:placetype":[
        "aat:300008761"
    ]
},
  "bbox": [],
  "geometry": {"coordinates":[-91.3667,37.6333],"type":"Point"}
}