{
  "id": 7477326,
  "type": "Feature",
  "properties": {
    "tgn:hierarchy":[
        "tgn:7477326",
        "tgn:1000004",
        "tgn:7001013",
        "tgn:1000141",
        "tgn:7029392"
    ],
    "tgn:id":7477326,
    "tgn:name":"Anhe Qiao",
    "tgn:placetype":[
        "aat:300007836"
    ]
},
  "bbox": [],
  "geometry": {"coordinates":[121.133157,25.040663],"type":"Point"}
}