<<<<<<< HEAD
{
  "id": 2255540,
  "type": "Feature",
  "properties": {
    "tgn:hierarchy":[
        "tgn:2255540",
        "tgn:1000001",
        "tgn:7012149",
        "tgn:2000361",
        "tgn:7007248",
        "tgn:7029392"
    ],
    "tgn:id":2255540,
    "tgn:name":"Copeland Creek",
    "tgn:placetype":[
        "aat:300008706"
    ]
},
  "bbox": [],
  "geometry": {"coordinates":[-83.0,33.4667],"type":"Point"}
}
=======
{"geometry":{"type":"Point","coordinates":[-83.000000,33.466700]},"type":"Feature","properties":{"hierarchy":["tgn:2255540","tgn:1000001","tgn:7012149","tgn:2000361","tgn:7007248","tgn:7029392"],"placetype":["aat:300008706"],"id":2255540,"name:xx":"Copeland Creek"}}
>>>>>>> 03f74aca74312dbeaf24d7e61306dd6a786dc3d0
