{
  "id": 2126794,
  "type": "Feature",
  "properties": {
    "tgn:hierarchy":[
        "tgn:2126794",
        "tgn:7030516",
        "tgn:7006450",
        "tgn:1000001",
        "tgn:7012149",
        "tgn:7029392"
    ],
    "tgn:id":2126794,
    "tgn:name":"Agony Point",
    "tgn:placetype":[
        "aat:300008850"
    ]
},
  "bbox": [],
  "geometry": {"coordinates":[-176.0833,51.7833],"type":"Point"}
}