<<<<<<< HEAD
{
  "id": 2707053,
  "type": "Feature",
  "properties": {
    "tgn:hierarchy":[
        "tgn:2707053",
        "tgn:1000001",
        "tgn:7012149",
        "tgn:2002125",
        "tgn:7007827",
        "tgn:7029392"
    ],
    "tgn:id":2707053,
    "tgn:name":"Sweat Creek",
    "tgn:placetype":[
        "aat:300008706"
    ]
},
  "bbox": [],
  "geometry": {"coordinates":[-111.45,39.9167],"type":"Point"}
}
=======
{"geometry":{"type":"Point","coordinates":[-111.450000,39.916700]},"type":"Feature","properties":{"hierarchy":["tgn:2707053","tgn:1000001","tgn:7012149","tgn:2002125","tgn:7007827","tgn:7029392"],"placetype":["aat:300008706"],"id":2707053,"name:xx":"Sweat Creek"}}
>>>>>>> 03f74aca74312dbeaf24d7e61306dd6a786dc3d0
