{
  "id": 7540715,
  "type": "Feature",
  "properties": {
    "tgn:hierarchy":[
        "tgn:7540715",
        "tgn:7001242",
        "tgn:7001311",
        "tgn:7016833",
        "tgn:7029392"
    ],
    "tgn:id":7540715,
    "tgn:name:en":"Shabana, R\u00f4d",
    "tgn:placetype":[
        "aat:300379998"
    ]
},
  "bbox": [],
  "geometry": {"coordinates":[34.15,24.05],"type":"Point"}
}