{
  "id": 2030091,
  "type": "Feature",
  "properties": {
    "tgn:hierarchy":[
        "tgn:2030091",
        "tgn:1000001",
        "tgn:7012149",
        "tgn:2000518",
        "tgn:7007251",
        "tgn:7029392"
    ],
    "tgn:id":2030091,
    "tgn:name":"Sciota",
    "tgn:placetype":[
        "aat:300008347"
    ]
},
  "bbox": [],
  "geometry": {"coordinates":[-90.75,40.55],"type":"Point"}
}