{
  "id": 2379422,
  "type": "Feature",
  "properties": {
    "tgn:hierarchy":[
        "tgn:2379422",
        "tgn:1000001",
        "tgn:7012149",
        "tgn:2001931",
        "tgn:7007825",
        "tgn:7029392"
    ],
    "tgn:id":2379422,
    "tgn:name":"Harvey Hollow",
    "tgn:placetype":[
        "aat:300008761"
    ]
},
  "bbox": [],
  "geometry": {"coordinates":[-86.0833,36.0167],"type":"Point"}
}