{
  "id": 2743155,
  "type": "Feature",
  "properties": {
    "tgn:hierarchy":[
        "tgn:2743155",
        "tgn:1000001",
        "tgn:7012149",
        "tgn:2002168",
        "tgn:7007919",
        "tgn:7029392"
    ],
    "tgn:id":2743155,
    "tgn:name":"Vance Hollow",
    "tgn:placetype":[
        "aat:300008761"
    ]
},
  "bbox": [],
  "geometry": {"coordinates":[-79.4833,38.2833],"type":"Point"}
}