{
  "id": 7377830,
  "type": "Feature",
  "properties": {
    "tgn:hierarchy":[
        "tgn:7377830",
        "tgn:7005583",
        "tgn:1000001",
        "tgn:7005560",
        "tgn:7029392"
    ],
    "tgn:id":7377830,
    "tgn:name":"La Placita",
    "tgn:placetype":[
        "aat:300008347"
    ]
},
  "bbox": [],
  "geometry": {"coordinates":[-105.933333,25.15],"type":"Point"}
}