{
  "id": 2693830,
  "type": "Feature",
  "properties": {
    "tgn:hierarchy":[
        "tgn:2693830",
        "tgn:1000001",
        "tgn:7012149",
        "tgn:2002125",
        "tgn:7007827",
        "tgn:7029392"
    ],
    "tgn:id":2693830,
    "tgn:name":"Sterling Hollow",
    "tgn:placetype":[
        "aat:300008761"
    ]
},
  "bbox": [],
  "geometry": {"coordinates":[-111.5167,40.0833],"type":"Point"}
}