{
  "id": 1054930,
  "type": "Feature",
  "properties": {
    "tgn:hierarchy":[
        "tgn:1054930",
        "tgn:1000004",
        "tgn:7002435",
        "tgn:7011526",
        "tgn:7029392"
    ],
    "tgn:id":1054930,
    "tgn:name":"Kama",
    "tgn:placetype":[
        "aat:300008347"
    ]
},
  "bbox": [],
  "geometry": {"coordinates":[54.1333,56.3333],"type":"Point"}
}