{
  "id": 7498967,
  "type": "Feature",
  "properties": {
    "tgn:hierarchy":[
        "tgn:7498967",
        "tgn:1000004",
        "tgn:7001009",
        "tgn:1000141",
        "tgn:7029392"
    ],
    "tgn:id":7498967,
    "tgn:name":"Jingzhuang",
    "tgn:placetype":[
        "aat:300008347"
    ]
},
  "bbox": [],
  "geometry": {"coordinates":[120.688614,24.083788],"type":"Point"}
}