{
  "id": 2573678,
  "type": "Feature",
  "properties": {
    "tgn:hierarchy":[
        "tgn:2573678",
        "tgn:1000001",
        "tgn:7012149",
        "tgn:2001196",
        "tgn:7007523",
        "tgn:7029392"
    ],
    "tgn:id":2573678,
    "tgn:name":"Peckerwood Hollow",
    "tgn:placetype":[
        "aat:300008761"
    ]
},
  "bbox": [],
  "geometry": {"coordinates":[-92.7833,36.8667],"type":"Point"}
}