<<<<<<< HEAD
{
  "id": 2407880,
  "type": "Feature",
  "properties": {
    "tgn:hierarchy":[
        "tgn:2407880",
        "tgn:1000001",
        "tgn:7012149",
        "tgn:7029392"
    ],
    "tgn:id":2407880,
    "tgn:name":"Hurricane Creek",
    "tgn:placetype":[
        "aat:300008706"
    ]
},
  "bbox": [],
  "geometry": {"coordinates":[-88.0333,34.3667],"type":"Point"}
}
=======
{"geometry":{"type":"Point","coordinates":[-88.033300,34.366700]},"type":"Feature","properties":{"hierarchy":["tgn:2407880","tgn:1000001","tgn:7012149","tgn:7029392"],"placetype":["aat:300008706"],"id":2407880,"name:xx":"Hurricane Creek"}}
>>>>>>> 03f74aca74312dbeaf24d7e61306dd6a786dc3d0
