{
  "id": 2407880,
  "type": "Feature",
  "properties": {
    "tgn:hierarchy":[
        "tgn:2407880",
        "tgn:1000001",
        "tgn:7012149",
        "tgn:7029392"
    ],
    "tgn:id":2407880,
    "tgn:name":"Hurricane Creek",
    "tgn:placetype":[
        "aat:300008706"
    ]
},
  "bbox": [],
  "geometry": {"coordinates":[-88.0333,34.3667],"type":"Point"}
}