{
  "id": 2753544,
  "type": "Feature",
  "properties": {
    "tgn:hierarchy":[
        "tgn:2753544",
        "tgn:1000001",
        "tgn:2001411",
        "tgn:7012149",
        "tgn:7007526",
        "tgn:7029392"
    ],
    "tgn:id":2753544,
    "tgn:name":"Watermelon Spring",
    "tgn:placetype":[
        "aat:300008697"
    ]
},
  "bbox": [],
  "geometry": {"coordinates":[-115.3167,40.5833],"type":"Point"}
}