{
  "id": 7464571,
  "type": "Feature",
  "properties": {
    "tgn:hierarchy":[
        "tgn:7464571",
        "tgn:7002444",
        "tgn:1000003",
        "tgn:5000451",
        "tgn:7008591",
        "tgn:7029392"
    ],
    "tgn:id":7464571,
    "tgn:name:en":"Ailnack, Water of",
    "tgn:placetype":[
        "aat:300008699"
    ]
},
  "bbox": [],
  "geometry": {"coordinates":[-3.383333,57.233333],"type":"Point"}
}