{
  "id": 7213669,
  "type": "Feature",
  "properties": {
    "tgn:hierarchy":[
        "tgn:7213669",
        "tgn:7003692",
        "tgn:1000003",
        "tgn:7000084",
        "tgn:7029392"
    ],
    "tgn:id":7213669,
    "tgn:name":"Bl\u00fcmle",
    "tgn:placetype":[
        "aat:300000206"
    ]
},
  "bbox": [],
  "geometry": {"coordinates":[10.033333,48.816667],"type":"Point"}
}