{
  "id": 2545295,
  "type": "Feature",
  "properties": {
    "tgn:hierarchy":[
        "tgn:2545295",
        "tgn:1000001",
        "tgn:7012149",
        "tgn:7007920",
        "tgn:7029392"
    ],
    "tgn:id":2545295,
    "tgn:name":"North Fork Asotin Creek",
    "tgn:placetype":[
        "aat:300008706"
    ]
},
  "bbox": [],
  "geometry": {"coordinates":[-117.5667,46.1833],"type":"Point"}
}