{
  "id": 2420793,
  "type": "Feature",
  "properties": {
    "tgn:hierarchy":[
        "tgn:2420793",
        "tgn:1000001",
        "tgn:7012149",
        "tgn:7013941",
        "tgn:7007568",
        "tgn:7029392"
    ],
    "tgn:id":2420793,
    "tgn:name":"Jennings Mountain",
    "tgn:placetype":[
        "aat:300008798"
    ]
},
  "bbox": [],
  "geometry": {"coordinates":[-74.3833,44.5333],"type":"Point"}
}