{
  "id": 2544536,
  "type": "Feature",
  "properties": {
    "tgn:hierarchy":[
        "tgn:2544536",
        "tgn:1000001",
        "tgn:7012149",
        "tgn:2001712",
        "tgn:7007708",
        "tgn:7029392"
    ],
    "tgn:id":2544536,
    "tgn:name":"North Butte",
    "tgn:placetype":[
        "aat:300008798"
    ]
},
  "bbox": [],
  "geometry": {"coordinates":[-121.6167,44.7667],"type":"Point"}
}