{
  "id": 7570611,
  "type": "Feature",
  "properties": {
    "tgn:hierarchy":[
        "tgn:7570611",
        "tgn:1009838",
        "tgn:7000204",
        "tgn:1000004",
        "tgn:7000198",
        "tgn:7029392"
    ],
    "tgn:id":7570611,
    "tgn:name:en":"Kalara",
    "tgn:placetype":[
        "aat:300266571"
    ]
},
  "bbox": [],
  "geometry": {"coordinates":[92.916667,13.05],"type":"Point"}
}