{
  "id": 2635130,
  "type": "Feature",
  "properties": {
    "tgn:hierarchy":[
        "tgn:2635130",
        "tgn:1000001",
        "tgn:7012149",
        "tgn:2002382",
        "tgn:7007923",
        "tgn:7029392"
    ],
    "tgn:id":2635130,
    "tgn:name":"Ryegrass Draw",
    "tgn:placetype":[
        "aat:300008761"
    ]
},
  "bbox": [],
  "geometry": {"coordinates":[-110.2333,42.8833],"type":"Point"}
}