<<<<<<< HEAD
{
  "id": 7111870,
  "type": "Feature",
  "properties": {
    "tgn:hierarchy":[
        "tgn:7111870",
        "tgn:1000003",
        "tgn:7003688",
        "tgn:7000084",
        "tgn:7029392"
    ],
    "tgn:id":7111870,
    "tgn:name":"Rinkesh\u00f6rn",
    "tgn:placetype":[
        "aat:300000206"
    ]
},
  "bbox": [],
  "geometry": {"coordinates":[8.766667,54.866667],"type":"Point"}
}
=======
{"geometry":{"type":"Point","coordinates":[8.766667,54.866667]},"type":"Feature","properties":{"hierarchy":["tgn:7111870","tgn:1000003","tgn:7003688","tgn:7000084","tgn:7029392"],"placetype":["aat:300000206"],"id":7111870,"name:xx":"Rinkesh\u00f6rn"}}
>>>>>>> 03f74aca74312dbeaf24d7e61306dd6a786dc3d0
