{
  "id": 2105859,
  "type": "Feature",
  "properties": {
    "tgn:hierarchy":[
        "tgn:2105859",
        "tgn:1000001",
        "tgn:7012149",
        "tgn:1002244",
        "tgn:7007826",
        "tgn:7029392"
    ],
    "tgn:id":2105859,
    "tgn:name":"McLeod",
    "tgn:placetype":[
        "aat:300008347"
    ]
},
  "bbox": [],
  "geometry": {"coordinates":[-94.0667,32.9333],"type":"Point"}
}