{
  "id": 7499595,
  "type": "Feature",
  "properties": {
    "tgn:hierarchy":[
        "tgn:7499595",
        "tgn:7488858",
        "tgn:1000004",
        "tgn:1000141",
        "tgn:7029392"
    ],
    "tgn:id":7499595,
    "tgn:name":"Junbei Shan",
    "tgn:placetype":[
        "aat:300008798"
    ]
},
  "bbox": [],
  "geometry": {"coordinates":[121.106381,23.643206],"type":"Point"}
}