{
  "id": 1024666,
  "type": "Feature",
  "properties": {
    "tgn:hierarchy":[
        "tgn:1024666",
        "tgn:1000518",
        "tgn:1000002",
        "tgn:1000056",
        "tgn:7029392"
    ],
    "tgn:id":1024666,
    "tgn:name":"Paico",
    "tgn:placetype":[
        "aat:300008347"
    ]
},
  "bbox": [],
  "geometry": {"coordinates":[-73.6333,-14.0333],"type":"Point"}
}