{
  "id": 1124028,
  "type": "Feature",
  "properties": {
    "tgn:hierarchy":[
        "tgn:1124028",
        "tgn:1000001",
        "tgn:7012149",
        "tgn:7007826",
        "tgn:7029392"
    ],
    "tgn:id":1124028,
    "tgn:name":"Frio",
    "tgn:placetype":[
        "aat:300008707"
    ]
},
  "bbox": [],
  "geometry": {"coordinates":[-99.75,29.7333],"type":"Point"}
}