<<<<<<< HEAD
{
  "id": 2337194,
  "type": "Feature",
  "properties": {
    "tgn:hierarchy":[
        "tgn:2337194",
        "tgn:1000001",
        "tgn:7012149",
        "tgn:7007568",
        "tgn:7029392"
    ],
    "tgn:id":2337194,
    "tgn:name":"Fourth Creek",
    "tgn:placetype":[
        "aat:300008706"
    ]
},
  "bbox": [],
  "geometry": {"coordinates":[-75.05,43.8167],"type":"Point"}
}
=======
{"geometry":{"type":"Point","coordinates":[-75.050000,43.816700]},"type":"Feature","properties":{"hierarchy":["tgn:2337194","tgn:1000001","tgn:7012149","tgn:7007568","tgn:7029392"],"placetype":["aat:300008706"],"id":2337194,"name:xx":"Fourth Creek"}}
>>>>>>> 03f74aca74312dbeaf24d7e61306dd6a786dc3d0
