{
  "id": 2337194,
  "type": "Feature",
  "properties": {
    "tgn:hierarchy":[
        "tgn:2337194",
        "tgn:1000001",
        "tgn:7012149",
        "tgn:7007568",
        "tgn:7029392"
    ],
    "tgn:id":2337194,
    "tgn:name":"Fourth Creek",
    "tgn:placetype":[
        "aat:300008706"
    ]
},
  "bbox": [],
  "geometry": {"coordinates":[-75.05,43.8167],"type":"Point"}
}