{
  "id": 7268842,
  "type": "Feature",
  "properties": {
    "tgn:hierarchy":[
        "tgn:7268842",
        "tgn:1000003",
        "tgn:7006951",
        "tgn:7016845",
        "tgn:7029392"
    ],
    "tgn:id":7268842,
    "tgn:name:nl":"Noordhollandsch Kanaal",
    "tgn:placetype":[
        "aat:300006075"
    ]
},
  "bbox": [],
  "geometry": {"coordinates":[4.916667,52.383333],"type":"Point"}
}