<<<<<<< HEAD
{
  "id": 2250926,
  "type": "Feature",
  "properties": {
    "tgn:hierarchy":[
        "tgn:2250926",
        "tgn:1000001",
        "tgn:1002923",
        "tgn:7012149",
        "tgn:7007517",
        "tgn:7029392"
    ],
    "tgn:id":2250926,
    "tgn:name":"Columbia Point",
    "tgn:placetype":[
        "aat:300008850"
    ]
},
  "bbox": [],
  "geometry": {"coordinates":[-71.0333,42.3167],"type":"Point"}
}
=======
{"geometry":{"type":"Point","coordinates":[-71.033300,42.316700]},"type":"Feature","properties":{"hierarchy":["tgn:2250926","tgn:1000001","tgn:1002923","tgn:7012149","tgn:7007517","tgn:7029392"],"placetype":["aat:300008850"],"id":2250926,"name:xx":"Columbia Point"}}
>>>>>>> 03f74aca74312dbeaf24d7e61306dd6a786dc3d0
