{
  "id": 7574177,
  "type": "Feature",
  "properties": {
    "tgn:hierarchy":[
        "tgn:7574177",
        "tgn:1000004",
        "tgn:1001842",
        "tgn:7000198",
        "tgn:7029392"
    ],
    "tgn:id":7574177,
    "tgn:name:en":"Hald\u012bkhora",
    "tgn:placetype":[
        "aat:300008347"
    ]
},
  "bbox": [],
  "geometry": {"coordinates":[87.739289,26.193021],"type":"Point"}
}