{
  "id": 7181875,
  "type": "Feature",
  "properties": {
    "tgn:hierarchy":[
        "tgn:7181875",
        "tgn:7003669",
        "tgn:1000003",
        "tgn:7000084",
        "tgn:7029392"
    ],
    "tgn:id":7181875,
    "tgn:name":"G\u00e4nswies",
    "tgn:placetype":[
        "aat:300000206"
    ]
},
  "bbox": [],
  "geometry": {"coordinates":[13.733333,48.75],"type":"Point"}
}