{
  "id": 1064703,
  "type": "Feature",
  "properties": {
    "tgn:hierarchy":[
        "tgn:1064703",
        "tgn:7008532",
        "tgn:7002443",
        "tgn:1000003",
        "tgn:7008591",
        "tgn:7029392"
    ],
    "tgn:id":1064703,
    "tgn:name:en":"Llanfaethlu",
    "tgn:placetype":[
        "aat:300008347"
    ]
},
  "bbox": [],
  "geometry": {"coordinates":[-4.533333,53.35],"type":"Point"}
}