{
  "id": 2550139,
  "type": "Feature",
  "properties": {
    "tgn:hierarchy":[
        "tgn:2550139",
        "tgn:1000001",
        "tgn:2001948",
        "tgn:7012149",
        "tgn:7007826",
        "tgn:7029392"
    ],
    "tgn:id":2550139,
    "tgn:name":"Northeast Lateral Watershed Number Five",
    "tgn:placetype":[
        "aat:300006191"
    ]
},
  "bbox": [],
  "geometry": {"coordinates":[-98.9667,31.5333],"type":"Point"}
}