{
  "id": 1044668,
  "type": "Feature",
  "properties": {
    "tgn:hierarchy":[
        "tgn:1044668",
        "tgn:7003128",
        "tgn:1000003",
        "tgn:7008516",
        "tgn:1000080",
        "tgn:7029392"
    ],
    "tgn:id":1044668,
    "tgn:name":"Formignana",
    "tgn:placetype":[
        "aat:300008347"
    ]
},
  "bbox": [],
  "geometry": {"coordinates":[11.85,44.833333],"type":"Point"}
}