{
  "id": 2492924,
  "type": "Feature",
  "properties": {
    "tgn:hierarchy":[
        "tgn:2492924",
        "tgn:1000001",
        "tgn:7012149",
        "tgn:7014350",
        "tgn:7007922",
        "tgn:7029392"
    ],
    "tgn:id":2492924,
    "tgn:name":"Markham Creek",
    "tgn:placetype":[
        "aat:300008706"
    ]
},
  "bbox": [],
  "geometry": {"coordinates":[-89.1333,42.6833],"type":"Point"}
}