{
  "id": 2650613,
  "type": "Feature",
  "properties": {
    "tgn:hierarchy":[
        "tgn:2650613",
        "tgn:1000001",
        "tgn:2001431",
        "tgn:7012149",
        "tgn:7007566",
        "tgn:7029392"
    ],
    "tgn:id":2650613,
    "tgn:name":"Seboyetita Creek",
    "tgn:placetype":[
        "aat:300008706"
    ]
},
  "bbox": [],
  "geometry": {"coordinates":[-107.55,35.25],"type":"Point"}
}