{
  "id": 2282225,
  "type": "Feature",
  "properties": {
    "tgn:hierarchy":[
        "tgn:2282225",
        "tgn:1000001",
        "tgn:7012149",
        "tgn:1002553",
        "tgn:7007920",
        "tgn:7029392"
    ],
    "tgn:id":2282225,
    "tgn:name":"Deer Lakes",
    "tgn:placetype":[
        "aat:300008680"
    ]
},
  "bbox": [],
  "geometry": {"coordinates":[-121.1333,47.5333],"type":"Point"}
}