{
  "id": 1047888,
  "type": "Feature",
  "properties": {
    "tgn:concordances":{
        "gn:id":"2752600"
    },
    "tgn:hierarchy":[
        "tgn:1047888",
        "tgn:1000003",
        "tgn:7003624",
        "tgn:7016845",
        "tgn:7029392"
    ],
    "tgn:id":1047888,
    "tgn:name:nl":"Klundert",
    "tgn:placetype":[
        "aat:300008347"
    ]
},
  "bbox": [],
  "geometry": {"coordinates":[4.533333,51.666667],"type":"Point"}
}