{
  "id": 7513724,
  "type": "Feature",
  "properties": {
    "tgn:hierarchy":[
        "tgn:7513724",
        "tgn:1009227",
        "tgn:1000226",
        "tgn:1000006",
        "tgn:7016850",
        "tgn:7029392"
    ],
    "tgn:id":7513724,
    "tgn:name:en":"Fossil Creek",
    "tgn:placetype":[
        "aat:300008699"
    ]
},
  "bbox": [],
  "geometry": {"coordinates":[171.45,-42.066667],"type":"Point"}
}