{
  "id": 2012911,
  "type": "Feature",
  "properties": {
    "tgn:hierarchy":[
        "tgn:2012911",
        "tgn:1000001",
        "tgn:7012149",
        "tgn:1002298",
        "tgn:7007157",
        "tgn:7029392"
    ],
    "tgn:id":2012911,
    "tgn:name":"Nevada Dock",
    "tgn:placetype":[
        "aat:300387016"
    ]
},
  "bbox": [],
  "geometry": {"coordinates":[-122.1667,38.0333],"type":"Point"}
}