{
  "id": 2432188,
  "type": "Feature",
  "properties": {
    "tgn:hierarchy":[
        "tgn:2432188",
        "tgn:1000001",
        "tgn:7006451",
        "tgn:2000093",
        "tgn:7012149",
        "tgn:7029392"
    ],
    "tgn:id":2432188,
    "tgn:name":"Kayler Butte",
    "tgn:placetype":[
        "aat:300008798"
    ]
},
  "bbox": [],
  "geometry": {"coordinates":[-111.2833,33.9333],"type":"Point"}
}