{
  "id": 2781981,
  "type": "Feature",
  "properties": {
    "tgn:hierarchy":[
        "tgn:2781981",
        "tgn:1000001",
        "tgn:7012149",
        "tgn:2001767",
        "tgn:7007712",
        "tgn:7029392"
    ],
    "tgn:id":2781981,
    "tgn:name":"Woods Millpond",
    "tgn:placetype":[
        "aat:300008905"
    ]
},
  "bbox": [],
  "geometry": {"coordinates":[-79.9833,33.9333],"type":"Point"}
}