{
  "id": 2012528,
  "type": "Feature",
  "properties": {
    "tgn:hierarchy":[
        "tgn:2012528",
        "tgn:1000001",
        "tgn:7012149",
        "tgn:7007157",
        "tgn:2000187",
        "tgn:7029392"
    ],
    "tgn:id":2012528,
    "tgn:name":"Mabie",
    "tgn:placetype":[
        "aat:300387016"
    ]
},
  "bbox": [],
  "geometry": {"coordinates":[-120.5167,39.7833],"type":"Point"}
}