{
  "id": 2291553,
  "type": "Feature",
  "properties": {
    "tgn:hierarchy":[
        "tgn:2291553",
        "tgn:1000001",
        "tgn:2000458",
        "tgn:7012149",
        "tgn:7007250",
        "tgn:7029392"
    ],
    "tgn:id":2291553,
    "tgn:name":"Dollar Lake",
    "tgn:placetype":[
        "aat:300008680"
    ]
},
  "bbox": [],
  "geometry": {"coordinates":[-114.4167,43.6833],"type":"Point"}
}