{
  "id": 7502014,
  "type": "Feature",
  "properties": {
    "tgn:hierarchy":[
        "tgn:7502014",
        "tgn:1000004",
        "tgn:7491221",
        "tgn:1000141",
        "tgn:7029392"
    ],
    "tgn:id":7502014,
    "tgn:name":"Tawa Xikou",
    "tgn:placetype":[
        "aat:300387057"
    ]
},
  "bbox": [],
  "geometry": {"coordinates":[120.896667,22.245],"type":"Point"}
}