{
  "id": 2733102,
  "type": "Feature",
  "properties": {
    "tgn:hierarchy":[
        "tgn:2733102",
        "tgn:1000001",
        "tgn:7006451",
        "tgn:2000092",
        "tgn:7012149",
        "tgn:7029392"
    ],
    "tgn:id":2733102,
    "tgn:name":"Turkey Mountain",
    "tgn:placetype":[
        "aat:300008798"
    ]
},
  "bbox": [],
  "geometry": {"coordinates":[-111.2667,34.6833],"type":"Point"}
}