{
  "id": 7316683,
  "type": "Feature",
  "properties": {
    "tgn:hierarchy":[
        "tgn:7316683",
        "tgn:1001708",
        "tgn:1000049",
        "tgn:1000002",
        "tgn:7029392"
    ],
    "tgn:id":7316683,
    "tgn:name":"Cuesta Arena, Quebrada",
    "tgn:placetype":[
        "aat:300266554",
        "aat:300008699"
    ]
},
  "bbox": [],
  "geometry": {"coordinates":[-71.866667,-34.05],"type":"Point"}
}