{
  "id": 2632441,
  "type": "Feature",
  "properties": {
    "tgn:hierarchy":[
        "tgn:2632441",
        "tgn:1000001",
        "tgn:1002188",
        "tgn:7012149",
        "tgn:7007252",
        "tgn:7029392"
    ],
    "tgn:id":2632441,
    "tgn:name":"Royal Run",
    "tgn:placetype":[
        "aat:300008699"
    ]
},
  "bbox": [],
  "geometry": {"coordinates":[-86.3333,39.9333],"type":"Point"}
}