<<<<<<< HEAD
{
  "id": 7175620,
  "type": "Feature",
  "properties": {
    "tgn:hierarchy":[
        "tgn:7175620",
        "tgn:1000003",
        "tgn:7003687",
        "tgn:7000084",
        "tgn:7029392"
    ],
    "tgn:id":7175620,
    "tgn:name":"Gro\u00dfwig",
    "tgn:placetype":[
        "aat:300008347"
    ]
},
  "bbox": [],
  "geometry": {"coordinates":[12.7,51.683333],"type":"Point"}
}
=======
{"geometry":{"type":"Point","coordinates":[12.700000,51.683333]},"type":"Feature","properties":{"hierarchy":["tgn:7175620","tgn:1000003","tgn:7003687","tgn:7000084","tgn:7029392"],"placetype":["aat:300008347"],"id":7175620,"name:xx":"Gro\u00dfwig"}}
>>>>>>> 03f74aca74312dbeaf24d7e61306dd6a786dc3d0
