{
  "id": 2427323,
  "type": "Feature",
  "properties": {
    "tgn:hierarchy":[
        "tgn:2427323",
        "tgn:1000001",
        "tgn:2002242",
        "tgn:7012149",
        "tgn:7007920",
        "tgn:7029392"
    ],
    "tgn:id":2427323,
    "tgn:name":"Jordan Creek",
    "tgn:placetype":[
        "aat:300008706"
    ]
},
  "bbox": [],
  "geometry": {"coordinates":[-119.5167,47.9833],"type":"Point"}
}