{
  "id": 2748391,
  "type": "Feature",
  "properties": {
    "tgn:hierarchy":[
        "tgn:2748391",
        "tgn:1000001",
        "tgn:7012149",
        "tgn:2002371",
        "tgn:7007923",
        "tgn:7029392"
    ],
    "tgn:id":2748391,
    "tgn:name":"Walker Ditch",
    "tgn:placetype":[
        "aat:300006075"
    ]
},
  "bbox": [],
  "geometry": {"coordinates":[-108.7833,42.7333],"type":"Point"}
}