{
  "id": 7306060,
  "type": "Feature",
  "properties": {
    "tgn:hierarchy":[
        "tgn:7306060",
        "tgn:7002824",
        "tgn:1000003",
        "tgn:7002786",
        "tgn:1000095",
        "tgn:7029392"
    ],
    "tgn:id":7306060,
    "tgn:name":"Loureda",
    "tgn:placetype":[
        "aat:300008347"
    ]
},
  "bbox": [],
  "geometry": {"coordinates":[-8.416667,42.866667],"type":"Point"}
}