{
  "id": 2410661,
  "type": "Feature",
  "properties": {
    "tgn:hierarchy":[
        "tgn:2410661",
        "tgn:1000001",
        "tgn:7012149",
        "tgn:7007157",
        "tgn:1002828",
        "tgn:7029392"
    ],
    "tgn:id":2410661,
    "tgn:name":"Indian Creek",
    "tgn:placetype":[
        "aat:300008706"
    ]
},
  "bbox": [],
  "geometry": {"coordinates":[-116.75,33.8167],"type":"Point"}
}