<<<<<<< HEAD
{
  "id": 7375122,
  "type": "Feature",
  "properties": {
    "tgn:hierarchy":[
        "tgn:7375122",
        "tgn:1000001",
        "tgn:7005597",
        "tgn:7005560",
        "tgn:7029392"
    ],
    "tgn:id":7375122,
    "tgn:name":"La Puerta",
    "tgn:placetype":[
        "aat:300266554",
        "aat:300008699"
    ]
},
  "bbox": [],
  "geometry": {"coordinates":[-97.766667,23.683333],"type":"Point"}
}
=======
{"geometry":{"type":"Point","coordinates":[-97.766667,23.683333]},"type":"Feature","properties":{"hierarchy":["tgn:7375122","tgn:1000001","tgn:7005597","tgn:7005560","tgn:7029392"],"placetype":["aat:300266554","aat:300008699"],"id":7375122,"name:xx":"La Puerta"}}
>>>>>>> 03f74aca74312dbeaf24d7e61306dd6a786dc3d0
