{
  "id": 2392822,
  "type": "Feature",
  "properties": {
    "tgn:hierarchy":[
        "tgn:2392822",
        "tgn:1000001",
        "tgn:7012149",
        "tgn:7007157",
        "tgn:2000191",
        "tgn:7029392"
    ],
    "tgn:id":2392822,
    "tgn:name":"Hobel Creek",
    "tgn:placetype":[
        "aat:300008706"
    ]
},
  "bbox": [],
  "geometry": {"coordinates":[-122.7167,40.95],"type":"Point"}
}