{
  "id": 7173343,
  "type": "Feature",
  "properties": {
    "tgn:hierarchy":[
        "tgn:7173343",
        "tgn:1000003",
        "tgn:7003677",
        "tgn:7000084",
        "tgn:7029392"
    ],
    "tgn:id":7173343,
    "tgn:name":"Gr\u00fcnenthal",
    "tgn:placetype":[
        "aat:300000206"
    ]
},
  "bbox": [],
  "geometry": {"coordinates":[7.283333,51.216667],"type":"Point"}
}