{
  "id": 7315330,
  "type": "Feature",
  "properties": {
    "tgn:hierarchy":[
        "tgn:7315330",
        "tgn:7002464",
        "tgn:1000049",
        "tgn:1000002",
        "tgn:7029392"
    ],
    "tgn:id":7315330,
    "tgn:name":"Cha\u00f1opalca",
    "tgn:placetype":[
        "aat:300008347"
    ]
},
  "bbox": [],
  "geometry": {"coordinates":[-69.266667,-18.066667],"type":"Point"}
}