{
  "id": 2608504,
  "type": "Feature",
  "properties": {
    "tgn:hierarchy":[
        "tgn:2608504",
        "tgn:1000001",
        "tgn:7012149",
        "tgn:1002352",
        "tgn:7007710",
        "tgn:7029392"
    ],
    "tgn:id":2608504,
    "tgn:name":"Rattlesnake Hill",
    "tgn:placetype":[
        "aat:300008798"
    ]
},
  "bbox": [],
  "geometry": {"coordinates":[-78.5667,41.2833],"type":"Point"}
}