{
  "id": 2425182,
  "type": "Feature",
  "properties": {
    "tgn:hierarchy":[
        "tgn:2425182",
        "tgn:1000001",
        "tgn:7012149",
        "tgn:2002328",
        "tgn:7007922",
        "tgn:7029392"
    ],
    "tgn:id":2425182,
    "tgn:name":"Johnson Marsh",
    "tgn:placetype":[
        "aat:300008905"
    ]
},
  "bbox": [],
  "geometry": {"coordinates":[-90.5167,44.3333],"type":"Point"}
}