<<<<<<< HEAD
{
  "id": 2766799,
  "type": "Feature",
  "properties": {
    "tgn:hierarchy":[
        "tgn:2766799",
        "tgn:1000001",
        "tgn:7012149",
        "tgn:2001444",
        "tgn:7007566",
        "tgn:7029392"
    ],
    "tgn:id":2766799,
    "tgn:name":"White Oaks",
    "tgn:placetype":[
        "aat:300000390"
    ]
},
  "bbox": [],
  "geometry": {"coordinates":[-107.7167,32.55],"type":"Point"}
}
=======
{"geometry":{"type":"Point","coordinates":[-107.716700,32.550000]},"type":"Feature","properties":{"hierarchy":["tgn:2766799","tgn:1000001","tgn:7012149","tgn:2001444","tgn:7007566","tgn:7029392"],"placetype":["aat:300000390"],"id":2766799,"name:xx":"White Oaks"}}
>>>>>>> 03f74aca74312dbeaf24d7e61306dd6a786dc3d0
