{
  "id": 2588280,
  "type": "Feature",
  "properties": {
    "tgn:hierarchy":[
        "tgn:2588280",
        "tgn:1000001",
        "tgn:7012149",
        "tgn:2000760",
        "tgn:7007254",
        "tgn:7029392"
    ],
    "tgn:id":2588280,
    "tgn:name":"Plum Creek",
    "tgn:placetype":[
        "aat:300008706"
    ]
},
  "bbox": [],
  "geometry": {"coordinates":[-97.05,39.8333],"type":"Point"}
}