{
  "id": 7589169,
  "type": "Feature",
  "properties": {
    "tgn:hierarchy":[
        "tgn:7589169",
        "tgn:1000004",
        "tgn:7000198",
        "tgn:7000799",
        "tgn:7029392"
    ],
    "tgn:id":7589169,
    "tgn:name:en":"D\u0101kil",
    "tgn:placetype":[
        "aat:300008699"
    ]
},
  "bbox": [],
  "geometry": {"coordinates":[74.388839,34.252414],"type":"Point"}
}