{
  "id": 2206576,
  "type": "Feature",
  "properties": {
    "tgn:hierarchy":[
        "tgn:2206576",
        "tgn:1000001",
        "tgn:2001410",
        "tgn:7012149",
        "tgn:7007526",
        "tgn:7029392"
    ],
    "tgn:id":2206576,
    "tgn:name":"Bullion Mine",
    "tgn:placetype":[
        "aat:300000390"
    ]
},
  "bbox": [],
  "geometry": {"coordinates":[-115.4333,35.75],"type":"Point"}
}