{
  "id": 7368703,
  "type": "Feature",
  "properties": {
    "tgn:hierarchy":[
        "tgn:7368703",
        "tgn:1000001",
        "tgn:1001960",
        "tgn:7005560",
        "tgn:7029392"
    ],
    "tgn:id":7368703,
    "tgn:name":"Rancho Juan D\u00edego",
    "tgn:placetype":[
        "aat:300000241"
    ]
},
  "bbox": [],
  "geometry": {"coordinates":[-109.35,27.333333],"type":"Point"}
}