<<<<<<< HEAD
{
  "id": 2766857,
  "type": "Feature",
  "properties": {
    "tgn:hierarchy":[
        "tgn:2766857",
        "tgn:1000001",
        "tgn:7012149",
        "tgn:2002122",
        "tgn:7007827",
        "tgn:7029392"
    ],
    "tgn:id":2766857,
    "tgn:name":"White Pine Creek",
    "tgn:placetype":[
        "aat:300008706"
    ]
},
  "bbox": [],
  "geometry": {"coordinates":[-111.1833,40.7],"type":"Point"}
}
=======
{"geometry":{"type":"Point","coordinates":[-111.183300,40.700000]},"type":"Feature","properties":{"hierarchy":["tgn:2766857","tgn:1000001","tgn:7012149","tgn:2002122","tgn:7007827","tgn:7029392"],"placetype":["aat:300008706"],"id":2766857,"name:xx":"White Pine Creek"}}
>>>>>>> 03f74aca74312dbeaf24d7e61306dd6a786dc3d0
