{
  "id": 1052863,
  "type": "Feature",
  "properties": {
    "tgn:hierarchy":[
        "tgn:1052863",
        "tgn:1000003",
        "tgn:7011661",
        "tgn:7006660",
        "tgn:7029392"
    ],
    "tgn:id":1052863,
    "tgn:name":"Boyarka",
    "tgn:placetype":[
        "aat:300008347"
    ]
},
  "bbox": [],
  "geometry": {"coordinates":[30.4333,50.3333],"type":"Point"}
}