{
  "id": 7553197,
  "type": "Feature",
  "properties": {
    "tgn:hierarchy":[
        "tgn:7553197",
        "tgn:1000004",
        "tgn:1001869",
        "tgn:7000198",
        "tgn:7029392"
    ],
    "tgn:id":7553197,
    "tgn:name:en":"Mulila",
    "tgn:placetype":[
        "aat:300008347"
    ]
},
  "bbox": [],
  "geometry": {"coordinates":[70.383333,22.133333],"type":"Point"}
}