<<<<<<< HEAD
{
  "id": 7110847,
  "type": "Feature",
  "properties": {
    "tgn:hierarchy":[
        "tgn:7110847",
        "tgn:7000096",
        "tgn:1000003",
        "tgn:7000084",
        "tgn:7029392"
    ],
    "tgn:id":7110847,
    "tgn:name":"R\u00e4hden-See",
    "tgn:placetype":[
        "aat:300008680"
    ]
},
  "bbox": [],
  "geometry": {"coordinates":[14.45,52.066667],"type":"Point"}
}
=======
{"geometry":{"type":"Point","coordinates":[14.450000,52.066667]},"type":"Feature","properties":{"hierarchy":["tgn:7110847","tgn:7000096","tgn:1000003","tgn:7000084","tgn:7029392"],"placetype":["aat:300008680"],"id":7110847,"name:xx":"R\u00e4hden-See"}}
>>>>>>> 03f74aca74312dbeaf24d7e61306dd6a786dc3d0
