{
  "id": 2596998,
  "type": "Feature",
  "properties": {
    "tgn:hierarchy":[
        "tgn:2596998",
        "tgn:1000001",
        "tgn:7012149",
        "tgn:2000208",
        "tgn:7007158",
        "tgn:7029392"
    ],
    "tgn:id":2596998,
    "tgn:name":"Powerline Number Three Reservoir",
    "tgn:placetype":[
        "aat:300006191"
    ]
},
  "bbox": [],
  "geometry": {"coordinates":[-108.7333,37.7333],"type":"Point"}
}