{
  "id": 2143981,
  "type": "Feature",
  "properties": {
    "tgn:hierarchy":[
        "tgn:2143981",
        "tgn:1000001",
        "tgn:7012149",
        "tgn:2001300",
        "tgn:7007524",
        "tgn:7029392"
    ],
    "tgn:id":2143981,
    "tgn:name":"Baker Creek",
    "tgn:placetype":[
        "aat:300008706"
    ]
},
  "bbox": [],
  "geometry": {"coordinates":[-114.25,45.8833],"type":"Point"}
}