{
  "id": 7305066,
  "type": "Feature",
  "properties": {
    "tgn:hierarchy":[
        "tgn:7305066",
        "tgn:7002836",
        "tgn:7016622",
        "tgn:1000003",
        "tgn:1000095",
        "tgn:7029392"
    ],
    "tgn:id":7305066,
    "tgn:name":"Las Rosas",
    "tgn:placetype":[
        "aat:300008347"
    ]
},
  "bbox": [],
  "geometry": {"coordinates":[-16.633333,28.366667],"type":"Point"}
}