{
  "id": 2366935,
  "type": "Feature",
  "properties": {
    "tgn:hierarchy":[
        "tgn:2366935",
        "tgn:1000001",
        "tgn:7012149",
        "tgn:7007713",
        "tgn:7029392"
    ],
    "tgn:id":2366935,
    "tgn:name":"Grizzly Bear Creek",
    "tgn:placetype":[
        "aat:300008706"
    ]
},
  "bbox": [],
  "geometry": {"coordinates":[-103.5167,43.85],"type":"Point"}
}