{
  "id": 7219395,
  "type": "Feature",
  "properties": {
    "tgn:hierarchy":[
        "tgn:7219395",
        "tgn:7011164",
        "tgn:7002674",
        "tgn:1000003",
        "tgn:1000074",
        "tgn:7029392"
    ],
    "tgn:id":7219395,
    "tgn:name":"Prason\u00edsi, Vrachonis\u00edda",
    "tgn:placetype":[
        "aat:300008791"
    ]
},
  "bbox": [],
  "geometry": {"coordinates":[26.962778,37.7975],"type":"Point"}
}