{
  "id": 2196926,
  "type": "Feature",
  "properties": {
    "tgn:hierarchy":[
        "tgn:2196926",
        "tgn:1000001",
        "tgn:1002500",
        "tgn:7012149",
        "tgn:7007240",
        "tgn:7029392"
    ],
    "tgn:id":2196926,
    "tgn:name":"Brookside",
    "tgn:placetype":[
        "aat:300008347"
    ]
},
  "bbox": [],
  "geometry": {"coordinates":[-80.55,27.7667],"type":"Point"}
}