{
  "id": 7248589,
  "type": "Feature",
  "properties": {
    "tgn:hierarchy":[
        "tgn:7248589",
        "tgn:7007877",
        "tgn:1000003",
        "tgn:1000063",
        "tgn:4012014",
        "tgn:7029392"
    ],
    "tgn:id":7248589,
    "tgn:name":"Blaimont, Bois de",
    "tgn:placetype":[
        "aat:300008863"
    ]
},
  "bbox": [],
  "geometry": {"coordinates":[4.366667,50.066667],"type":"Point"}
}