{
  "id": 1111843,
  "type": "Feature",
  "properties": {
    "tgn:hierarchy":[
        "tgn:1111843",
        "tgn:7001242",
        "tgn:1001755",
        "tgn:1000176",
        "tgn:7029392"
    ],
    "tgn:id":1111843,
    "tgn:name":"Adafer",
    "tgn:placetype":[
        "aat:300387346"
    ]
},
  "bbox": [],
  "geometry": {"coordinates":[-10.0833,19.5833],"type":"Point"}
}