{
  "id": 2117908,
  "type": "Feature",
  "properties": {
    "tgn:hierarchy":[
        "tgn:2117908",
        "tgn:1000001",
        "tgn:7012149",
        "tgn:2002284",
        "tgn:7013961",
        "tgn:7029392"
    ],
    "tgn:id":2117908,
    "tgn:name":"Craigsville",
    "tgn:placetype":[
        "aat:300008347"
    ]
},
  "bbox": [],
  "geometry": {"coordinates":[-80.65,38.3167],"type":"Point"}
}