{
  "id": 2170643,
  "type": "Feature",
  "properties": {
    "tgn:hierarchy":[
        "tgn:2170643",
        "tgn:7006450",
        "tgn:1000001",
        "tgn:7012149",
        "tgn:7029392"
    ],
    "tgn:id":2170643,
    "tgn:name":"Big Salmon Fork",
    "tgn:placetype":[
        "aat:300008699"
    ]
},
  "bbox": [],
  "geometry": {"coordinates":[-152.9833,62.5833],"type":"Point"}
}