{
  "id": 2151359,
  "type": "Feature",
  "properties": {
    "tgn:hierarchy":[
        "tgn:2151359",
        "tgn:1000001",
        "tgn:2001733",
        "tgn:7012149",
        "tgn:7007712",
        "tgn:7029392"
    ],
    "tgn:id":2151359,
    "tgn:name":"Bates Mill Creek",
    "tgn:placetype":[
        "aat:300008706"
    ]
},
  "bbox": [],
  "geometry": {"coordinates":[-80.8333,33.6833],"type":"Point"}
}