{
  "id": 2188322,
  "type": "Feature",
  "properties": {
    "tgn:hierarchy":[
        "tgn:2188322",
        "tgn:1000001",
        "tgn:7013638",
        "tgn:7012149",
        "tgn:7007568",
        "tgn:7029392"
    ],
    "tgn:id":2188322,
    "tgn:name":"Boston Corner",
    "tgn:placetype":[
        "aat:300008347"
    ]
},
  "bbox": [],
  "geometry": {"coordinates":[-73.5167,42.05],"type":"Point"}
}