{
  "id": 2559948,
  "type": "Feature",
  "properties": {
    "tgn:hierarchy":[
        "tgn:2559948",
        "tgn:1000001",
        "tgn:7012149",
        "tgn:7029392"
    ],
    "tgn:id":2559948,
    "tgn:name":"Opossum Hollow",
    "tgn:placetype":[
        "aat:300008761"
    ]
},
  "bbox": [],
  "geometry": {"coordinates":[-86.2333,34.9833],"type":"Point"}
}