<<<<<<< HEAD
{
  "id": 2332348,
  "type": "Feature",
  "properties": {
    "tgn:hierarchy":[
        "tgn:2332348",
        "tgn:1000001",
        "tgn:2000953",
        "tgn:7012149",
        "tgn:7007520",
        "tgn:7029392"
    ],
    "tgn:id":2332348,
    "tgn:name":"Floodwood Swamp Reservoir",
    "tgn:placetype":[
        "aat:300006191"
    ]
},
  "bbox": [],
  "geometry": {"coordinates":[-84.9167,44.1],"type":"Point"}
}
=======
{"geometry":{"type":"Point","coordinates":[-84.916700,44.100000]},"type":"Feature","properties":{"hierarchy":["tgn:2332348","tgn:1000001","tgn:2000953","tgn:7012149","tgn:7007520","tgn:7029392"],"placetype":["aat:300006191"],"id":2332348,"name:xx":"Floodwood Swamp Reservoir"}}
>>>>>>> 03f74aca74312dbeaf24d7e61306dd6a786dc3d0
