{
  "id": 1048921,
  "type": "Feature",
  "properties": {
    "tgn:hierarchy":[
        "tgn:1048921",
        "tgn:1000003",
        "tgn:7024114",
        "tgn:7006366",
        "tgn:7029392"
    ],
    "tgn:id":1048921,
    "tgn:name":"Bia\u0142y B\u00f3r",
    "tgn:placetype":[
        "aat:300008347"
    ]
},
  "bbox": [],
  "geometry": {"coordinates":[16.8333,53.8833],"type":"Point"}
}