<<<<<<< HEAD
{
  "id": 7485756,
  "type": "Feature",
  "properties": {
    "tgn:hierarchy":[
        "tgn:7485756",
        "tgn:7468018",
        "tgn:1000004",
        "tgn:1000141",
        "tgn:7029392"
    ],
    "tgn:id":7485756,
    "tgn:name":"Jiuxiongkeng Xi",
    "tgn:placetype":[
        "aat:300008699"
    ]
},
  "bbox": [],
  "geometry": {"coordinates":[120.533889,23.556111],"type":"Point"}
}
=======
{"geometry":{"type":"Point","coordinates":[120.533889,23.556111]},"type":"Feature","properties":{"hierarchy":["tgn:7485756","tgn:7468018","tgn:1000004","tgn:1000141","tgn:7029392"],"placetype":["aat:300008699"],"id":7485756,"name:xx":"Jiuxiongkeng Xi"}}
>>>>>>> 03f74aca74312dbeaf24d7e61306dd6a786dc3d0
