{
  "id": 7009542,
  "type": "Feature",
  "properties": {
    "tgn:hierarchy":[
        "tgn:7009542",
        "tgn:7002444",
        "tgn:7019115",
        "tgn:1000003",
        "tgn:7008591",
        "tgn:7029392"
    ],
    "tgn:id":7009542,
    "tgn:name:en":"Haddington",
    "tgn:placetype":[
        "aat:300008347",
        "aat:300387220"
    ]
},
  "bbox": [],
  "geometry": {"coordinates":[-2.766667,55.933333],"type":"Point"}
}