{
  "id": 7592792,
  "type": "Feature",
  "properties": {
    "tgn:hierarchy":[
        "tgn:7592792",
        "tgn:1000004",
        "tgn:7000198",
        "tgn:7000799",
        "tgn:7029392"
    ],
    "tgn:id":7592792,
    "tgn:name:en":"Nadhuw\u0101l",
    "tgn:placetype":[
        "aat:300008347"
    ]
},
  "bbox": [],
  "geometry": {"coordinates":[74.825,32.877778],"type":"Point"}
}