<<<<<<< HEAD
{
  "id": 7025511,
  "type": "Feature",
  "properties": {
    "tgn:hierarchy":[
        "tgn:7025511",
        "tgn:7002445",
        "tgn:1000003",
        "tgn:7012077",
        "tgn:7008591",
        "tgn:7029392"
    ],
    "tgn:id":7025511,
    "tgn:name":"Cookbury Wick",
    "tgn:placetype":[
        "aat:300008347"
    ]
},
  "bbox": [],
  "geometry": {"coordinates":[-4.2833,50.8167],"type":"Point"}
}
=======
{"geometry":{"type":"Point","coordinates":[-4.283300,50.816700]},"type":"Feature","properties":{"hierarchy":["tgn:7025511","tgn:7002445","tgn:1000003","tgn:7012077","tgn:7008591","tgn:7029392"],"placetype":["aat:300008347"],"id":7025511,"name:xx":"Cookbury Wick"}}
>>>>>>> 03f74aca74312dbeaf24d7e61306dd6a786dc3d0
