{
  "id": 1046265,
  "type": "Feature",
  "properties": {
    "tgn:hierarchy":[
        "tgn:1046265",
        "tgn:7003158",
        "tgn:1000003",
        "tgn:7003124",
        "tgn:1000080",
        "tgn:7029392"
    ],
    "tgn:id":1046265,
    "tgn:name":"Rev\u00f2",
    "tgn:placetype":[
        "aat:300008347"
    ]
},
  "bbox": [],
  "geometry": {"coordinates":[11.05,46.383333],"type":"Point"}
}