{
  "id": 2035830,
  "type": "Feature",
  "properties": {
    "tgn:hierarchy":[
        "tgn:2035830",
        "tgn:1000001",
        "tgn:2000593",
        "tgn:7012149",
        "tgn:7007253",
        "tgn:7029392"
    ],
    "tgn:id":2035830,
    "tgn:name":"Wadena",
    "tgn:placetype":[
        "aat:300008347"
    ]
},
  "bbox": [],
  "geometry": {"coordinates":[-91.65,42.8333],"type":"Point"}
}