{
  "id": 7566218,
  "type": "Feature",
  "properties": {
    "tgn:hierarchy":[
        "tgn:7566218",
        "tgn:1000004",
        "tgn:7000198",
        "tgn:7016722",
        "tgn:7029392"
    ],
    "tgn:id":7566218,
    "tgn:name:en":"Jujh\u0101rpura",
    "tgn:placetype":[
        "aat:300008347"
    ]
},
  "bbox": [],
  "geometry": {"coordinates":[79.058233,25.72347],"type":"Point"}
}