{
  "id": 2683083,
  "type": "Feature",
  "properties": {
    "tgn:hierarchy":[
        "tgn:2683083",
        "tgn:1000001",
        "tgn:7012149",
        "tgn:2000430",
        "tgn:7007248",
        "tgn:7029392"
    ],
    "tgn:id":2683083,
    "tgn:name":"Spaniard Mountain",
    "tgn:placetype":[
        "aat:300008798"
    ]
},
  "bbox": [],
  "geometry": {"coordinates":[-83.75,34.8333],"type":"Point"}
}