{
  "id": 2220008,
  "type": "Feature",
  "properties": {
    "tgn:hierarchy":[
        "tgn:2220008",
        "tgn:1000001",
        "tgn:7012149",
        "tgn:2001315",
        "tgn:7007524",
        "tgn:7029392"
    ],
    "tgn:id":2220008,
    "tgn:name":"Canyon Creek",
    "tgn:placetype":[
        "aat:300008706"
    ]
},
  "bbox": [],
  "geometry": {"coordinates":[-108.7667,45.85],"type":"Point"}
}