{
  "id": 7328682,
  "type": "Feature",
  "properties": {
    "tgn:hierarchy":[
        "tgn:7328682",
        "tgn:7002826",
        "tgn:7001158",
        "tgn:1000003",
        "tgn:1000095",
        "tgn:7029392"
    ],
    "tgn:id":7328682,
    "tgn:name":"Regueras de Abajo",
    "tgn:placetype":[
        "aat:300008347"
    ]
},
  "bbox": [],
  "geometry": {"coordinates":[-5.85,42.283333],"type":"Point"}
}