{
  "id": 7475654,
  "type": "Feature",
  "properties": {
    "tgn:hierarchy":[
        "tgn:7475654",
        "tgn:7488858",
        "tgn:1000004",
        "tgn:1000141",
        "tgn:7029392"
    ],
    "tgn:id":7475654,
    "tgn:name":"Litoujian",
    "tgn:placetype":[
        "aat:300008347"
    ]
},
  "bbox": [],
  "geometry": {"coordinates":[120.9846,23.967004],"type":"Point"}
}