<<<<<<< HEAD
{
  "id": 7475654,
  "type": "Feature",
  "properties": {
    "tgn:hierarchy":[
        "tgn:7475654",
        "tgn:7488858",
        "tgn:1000004",
        "tgn:1000141",
        "tgn:7029392"
    ],
    "tgn:id":7475654,
    "tgn:name":"Litoujian",
    "tgn:placetype":[
        "aat:300008347"
    ]
},
  "bbox": [],
  "geometry": {"coordinates":[120.9846,23.967004],"type":"Point"}
}
=======
{"geometry":{"type":"Point","coordinates":[120.984600,23.967004]},"type":"Feature","properties":{"hierarchy":["tgn:7475654","tgn:7488858","tgn:1000004","tgn:1000141","tgn:7029392"],"placetype":["aat:300008347"],"id":7475654,"name:xx":"Litoujian"}}
>>>>>>> 03f74aca74312dbeaf24d7e61306dd6a786dc3d0
