{
  "id": 2716667,
  "type": "Feature",
  "properties": {
    "tgn:hierarchy":[
        "tgn:2716667",
        "tgn:1000001",
        "tgn:7006451",
        "tgn:7012149",
        "tgn:2000097",
        "tgn:7029392"
    ],
    "tgn:id":2716667,
    "tgn:name":"The Preserve",
    "tgn:placetype":[
        "aat:300008347"
    ]
},
  "bbox": [],
  "geometry": {"coordinates":[-112.0167,33.5667],"type":"Point"}
}