{
  "id": 7475383,
  "type": "Feature",
  "properties": {
    "tgn:hierarchy":[
        "tgn:7475383",
        "tgn:1000004",
        "tgn:7001009",
        "tgn:1000141",
        "tgn:7029392"
    ],
    "tgn:id":7475383,
    "tgn:name":"Wenliaozhuang",
    "tgn:placetype":[
        "aat:300008347"
    ]
},
  "bbox": [],
  "geometry": {"coordinates":[120.585556,24.373611],"type":"Point"}
}