{
  "id": 2150428,
  "type": "Feature",
  "properties": {
    "tgn:hierarchy":[
        "tgn:2150428",
        "tgn:1000001",
        "tgn:7012149",
        "tgn:7007157",
        "tgn:1002608",
        "tgn:7029392"
    ],
    "tgn:id":2150428,
    "tgn:name":"Basin E",
    "tgn:placetype":[
        "aat:300008678"
    ]
},
  "bbox": [],
  "geometry": {"coordinates":[-118.45,33.9667],"type":"Point"}
}