{
  "id": 2349595,
  "type": "Feature",
  "properties": {
    "tgn:hierarchy":[
        "tgn:2349595",
        "tgn:1000001",
        "tgn:7006451",
        "tgn:2000094",
        "tgn:7012149",
        "tgn:7029392"
    ],
    "tgn:id":2349595,
    "tgn:name":"Gillespie Mountain",
    "tgn:placetype":[
        "aat:300008798"
    ]
},
  "bbox": [],
  "geometry": {"coordinates":[-109.7167,32.5667],"type":"Point"}
}