{
  "id": 7420055,
  "type": "Feature",
  "properties": {
    "tgn:hierarchy":[
        "tgn:7420055",
        "tgn:1000001",
        "tgn:7005589",
        "tgn:7005560",
        "tgn:7029392"
    ],
    "tgn:id":7420055,
    "tgn:name:es":"Los Velas",
    "tgn:placetype":[
        "aat:300008347"
    ]
},
  "bbox": [],
  "geometry": {"coordinates":[-99.8125,26.414444],"type":"Point"}
}