{
  "id": 2552430,
  "type": "Feature",
  "properties": {
    "tgn:hierarchy":[
        "tgn:2552430",
        "tgn:1000001",
        "tgn:7012149",
        "tgn:1003038",
        "tgn:7007517",
        "tgn:7029392"
    ],
    "tgn:id":2552430,
    "tgn:name":"Number Two Reservoir",
    "tgn:placetype":[
        "aat:300006191"
    ]
},
  "bbox": [],
  "geometry": {"coordinates":[-72.05,42.0667],"type":"Point"}
}