<<<<<<< HEAD
{
  "id": 7053080,
  "type": "Feature",
  "properties": {
    "tgn:hierarchy":[
        "tgn:7053080",
        "tgn:7003133",
        "tgn:1000003",
        "tgn:7008516",
        "tgn:1000080",
        "tgn:7029392"
    ],
    "tgn:id":7053080,
    "tgn:name":"Primaro",
    "tgn:placetype":[
        "aat:300008347"
    ]
},
  "bbox": [],
  "geometry": {"coordinates":[12.266667,44.583333],"type":"Point"}
}
=======
{"geometry":{"type":"Point","coordinates":[12.266667,44.583333]},"type":"Feature","properties":{"hierarchy":["tgn:7053080","tgn:7003133","tgn:1000003","tgn:7008516","tgn:1000080","tgn:7029392"],"placetype":["aat:300008347"],"id":7053080,"name:xx":"Primaro"}}
>>>>>>> 03f74aca74312dbeaf24d7e61306dd6a786dc3d0
