{
  "id": 2434525,
  "type": "Feature",
  "properties": {
    "tgn:hierarchy":[
        "tgn:2434525",
        "tgn:1000001",
        "tgn:7012149",
        "tgn:2001241",
        "tgn:7007523",
        "tgn:7029392"
    ],
    "tgn:id":2434525,
    "tgn:name":"Kennedy Branch",
    "tgn:placetype":[
        "aat:300008699"
    ]
},
  "bbox": [],
  "geometry": {"coordinates":[-90.4167,37.7833],"type":"Point"}
}