{
  "id": 2378517,
  "type": "Feature",
  "properties": {
    "tgn:hierarchy":[
        "tgn:2378517",
        "tgn:7006450",
        "tgn:1000001",
        "tgn:2124053",
        "tgn:7012149",
        "tgn:7029392"
    ],
    "tgn:id":2378517,
    "tgn:name":"Harrison Lake",
    "tgn:placetype":[
        "aat:300008680"
    ]
},
  "bbox": [],
  "geometry": {"coordinates":[-148.4833,61.7833],"type":"Point"}
}