<<<<<<< HEAD
{
  "id": 7025459,
  "type": "Feature",
  "properties": {
    "tgn:hierarchy":[
        "tgn:7025459",
        "tgn:7002445",
        "tgn:1000003",
        "tgn:7012077",
        "tgn:7008591",
        "tgn:7029392"
    ],
    "tgn:id":7025459,
    "tgn:name:en":"Butterleigh",
    "tgn:placetype":[
        "aat:300008347"
    ]
},
  "bbox": [],
  "geometry": {"coordinates":[-3.45,50.866667],"type":"Point"}
}
=======
{"geometry":{"type":"Point","coordinates":[-3.450000,50.866667]},"type":"Feature","properties":{"hierarchy":["tgn:7025459","tgn:7002445","tgn:1000003","tgn:7012077","tgn:7008591","tgn:7029392"],"placetype":["aat:300008347"],"name:en":"Butterleigh","id":7025459}}
>>>>>>> 03f74aca74312dbeaf24d7e61306dd6a786dc3d0
