{
  "id": 7025459,
  "type": "Feature",
  "properties": {
    "tgn:hierarchy":[
        "tgn:7025459",
        "tgn:7002445",
        "tgn:1000003",
        "tgn:7012077",
        "tgn:7008591",
        "tgn:7029392"
    ],
    "tgn:id":7025459,
    "tgn:name:en":"Butterleigh",
    "tgn:placetype":[
        "aat:300008347"
    ]
},
  "bbox": [],
  "geometry": {"coordinates":[-3.45,50.866667],"type":"Point"}
}