{
  "id": 2652324,
  "type": "Feature",
  "properties": {
    "tgn:hierarchy":[
        "tgn:2652324",
        "tgn:1000001",
        "tgn:7012149",
        "tgn:7007157",
        "tgn:2000191",
        "tgn:7029392"
    ],
    "tgn:id":2652324,
    "tgn:name":"Semore Gulch",
    "tgn:placetype":[
        "aat:300008761"
    ]
},
  "bbox": [],
  "geometry": {"coordinates":[-123.25,40.9667],"type":"Point"}
}