{
  "id": 7506836,
  "type": "Feature",
  "properties": {
    "tgn:hierarchy":[
        "tgn:7506836",
        "tgn:1009227",
        "tgn:1000226",
        "tgn:7520095",
        "tgn:1000006",
        "tgn:7029392"
    ],
    "tgn:id":7506836,
    "tgn:name:en":"Raukawa Stream",
    "tgn:placetype":[
        "aat:300008699"
    ]
},
  "bbox": [],
  "geometry": {"coordinates":[172.283333,-40.75],"type":"Point"}
}