{
  "id": 7077096,
  "type": "Feature",
  "properties": {
    "tgn:hierarchy":[
        "tgn:7077096",
        "tgn:7003669",
        "tgn:1000003",
        "tgn:7000084",
        "tgn:7029392"
    ],
    "tgn:id":7077096,
    "tgn:name":"Landkreis Neustadt an der Waldnaab",
    "tgn:placetype":[
        "aat:300387198"
    ]
},
  "bbox": [],
  "geometry": {"coordinates":[12.087222,49.711667],"type":"Point"}
}