{
  "id": 2694883,
  "type": "Feature",
  "properties": {
    "tgn:hierarchy":[
        "tgn:2694883",
        "tgn:1000001",
        "tgn:1002191",
        "tgn:7012149",
        "tgn:7007826",
        "tgn:7029392"
    ],
    "tgn:id":2694883,
    "tgn:name":"Stiffy Hollow",
    "tgn:placetype":[
        "aat:300008761"
    ]
},
  "bbox": [],
  "geometry": {"coordinates":[-97.7833,31.85],"type":"Point"}
}