{
  "id": 1096672,
  "type": "Feature",
  "properties": {
    "tgn:hierarchy":[
        "tgn:1096672",
        "tgn:7000490",
        "tgn:1000006",
        "tgn:7001829",
        "tgn:7029392"
    ],
    "tgn:id":1096672,
    "tgn:name":"Creswell Downs",
    "tgn:placetype":[
        "aat:300008347"
    ]
},
  "bbox": [],
  "geometry": {"coordinates":[135.8333,-17.85],"type":"Point"}
}