{
  "id": 1089275,
  "type": "Feature",
  "properties": {
    "tgn:hierarchy":[
        "tgn:1089275",
        "tgn:7001242",
        "tgn:7016706",
        "tgn:1000159",
        "tgn:7029392"
    ],
    "tgn:id":1089275,
    "tgn:name":"Luvua",
    "tgn:placetype":[
        "aat:300008347"
    ]
},
  "bbox": [],
  "geometry": {"coordinates":[25.3167,-8.8167],"type":"Point"}
}