<<<<<<< HEAD
{
  "id": 7178512,
  "type": "Feature",
  "properties": {
    "tgn:hierarchy":[
        "tgn:7178512",
        "tgn:7003669",
        "tgn:1000003",
        "tgn:7000084",
        "tgn:7029392"
    ],
    "tgn:id":7178512,
    "tgn:name":"Haimbuch",
    "tgn:placetype":[
        "aat:300387200"
    ]
},
  "bbox": [],
  "geometry": {"coordinates":[13.233333,48.6],"type":"Point"}
}
=======
{"geometry":{"type":"Point","coordinates":[13.233333,48.600000]},"type":"Feature","properties":{"hierarchy":["tgn:7178512","tgn:7003669","tgn:1000003","tgn:7000084","tgn:7029392"],"placetype":["aat:300387200"],"id":7178512,"name:xx":"Haimbuch"}}
>>>>>>> 03f74aca74312dbeaf24d7e61306dd6a786dc3d0
