{
  "id": 2568589,
  "type": "Feature",
  "properties": {
    "tgn:hierarchy":[
        "tgn:2568589",
        "tgn:1000001",
        "tgn:7012149",
        "tgn:1002314",
        "tgn:7007240",
        "tgn:7029392"
    ],
    "tgn:id":2568589,
    "tgn:name":"Park View Island",
    "tgn:placetype":[
        "aat:300008791"
    ]
},
  "bbox": [],
  "geometry": {"coordinates":[-80.1167,25.85],"type":"Point"}
}