{
  "id": 2301020,
  "type": "Feature",
  "properties": {
    "tgn:hierarchy":[
        "tgn:2301020",
        "tgn:1000001",
        "tgn:7012149",
        "tgn:2000488",
        "tgn:7007250",
        "tgn:7029392"
    ],
    "tgn:id":2301020,
    "tgn:name":"Dunes Lake",
    "tgn:placetype":[
        "aat:300008680"
    ]
},
  "bbox": [],
  "geometry": {"coordinates":[-115.6833,42.8833],"type":"Point"}
}