{
  "id": 7072422,
  "type": "Feature",
  "properties": {
    "tgn:hierarchy":[
        "tgn:7072422",
        "tgn:1000003",
        "tgn:7003676",
        "tgn:7000084",
        "tgn:7029392"
    ],
    "tgn:id":7072422,
    "tgn:name":"T\u00e4tenhorst",
    "tgn:placetype":[
        "aat:300000206"
    ]
},
  "bbox": [],
  "geometry": {"coordinates":[8.866667,52.433333],"type":"Point"}
}