{
  "id": 7111897,
  "type": "Feature",
  "properties": {
    "tgn:hierarchy":[
        "tgn:7111897",
        "tgn:1000003",
        "tgn:7000094",
        "tgn:7000084",
        "tgn:7029392"
    ],
    "tgn:id":7111897,
    "tgn:name":"Ribnitzer Forst",
    "tgn:placetype":[
        "aat:300008863"
    ]
},
  "bbox": [],
  "geometry": {"coordinates":[12.316667,54.216667],"type":"Point"}
}