{
  "id": 7486330,
  "type": "Feature",
  "properties": {
    "tgn:hierarchy":[
        "tgn:7486330",
        "tgn:1000004",
        "tgn:1000959",
        "tgn:1000141",
        "tgn:7029392"
    ],
    "tgn:id":7486330,
    "tgn:name":"Mamingtan",
    "tgn:placetype":[
        "aat:300000745"
    ]
},
  "bbox": [],
  "geometry": {"coordinates":[121.559021,24.994771],"type":"Point"}
}