{
  "id": 7328001,
  "type": "Feature",
  "properties": {
    "tgn:hierarchy":[
        "tgn:7328001",
        "tgn:7002836",
        "tgn:7016622",
        "tgn:1000003",
        "tgn:1000095",
        "tgn:7029392"
    ],
    "tgn:id":7328001,
    "tgn:name":"Restinga, Punta de la",
    "tgn:placetype":[
        "aat:300386846"
    ]
},
  "bbox": [],
  "geometry": {"coordinates":[-17.966667,27.633333],"type":"Point"}
}