{
  "id": 7275800,
  "type": "Feature",
  "properties": {
    "tgn:hierarchy":[
        "tgn:7275800",
        "tgn:1001699",
        "tgn:1000049",
        "tgn:1000002",
        "tgn:7029392"
    ],
    "tgn:id":7275800,
    "tgn:name":"Trahuilco, R\u00edo",
    "tgn:placetype":[
        "aat:300008699"
    ]
},
  "bbox": [],
  "geometry": {"coordinates":[-73.75,-40.316667],"type":"Point"}
}