{
  "id": 7477118,
  "type": "Feature",
  "properties": {
    "tgn:hierarchy":[
        "tgn:7477118",
        "tgn:1000004",
        "tgn:1000454",
        "tgn:1000141",
        "tgn:7029392"
    ],
    "tgn:id":7477118,
    "tgn:name":"Lunziwei",
    "tgn:placetype":[
        "aat:300008347"
    ]
},
  "bbox": [],
  "geometry": {"coordinates":[121.914086,25.017261],"type":"Point"}
}