<<<<<<< HEAD
{
  "id": 7477118,
  "type": "Feature",
  "properties": {
    "tgn:hierarchy":[
        "tgn:7477118",
        "tgn:1000004",
        "tgn:1000454",
        "tgn:1000141",
        "tgn:7029392"
    ],
    "tgn:id":7477118,
    "tgn:name":"Lunziwei",
    "tgn:placetype":[
        "aat:300008347"
    ]
},
  "bbox": [],
  "geometry": {"coordinates":[121.914086,25.017261],"type":"Point"}
}
=======
{"geometry":{"type":"Point","coordinates":[121.914086,25.017261]},"type":"Feature","properties":{"hierarchy":["tgn:7477118","tgn:1000004","tgn:1000454","tgn:1000141","tgn:7029392"],"placetype":["aat:300008347"],"id":7477118,"name:xx":"Lunziwei"}}
>>>>>>> 03f74aca74312dbeaf24d7e61306dd6a786dc3d0
