{
  "id": 7064962,
  "type": "Feature",
  "properties": {
    "tgn:hierarchy":[
        "tgn:7064962",
        "tgn:1000003",
        "tgn:7003676",
        "tgn:7000084",
        "tgn:7029392"
    ],
    "tgn:id":7064962,
    "tgn:name":"Steinriede",
    "tgn:placetype":[
        "aat:300008863"
    ]
},
  "bbox": [],
  "geometry": {"coordinates":[9.816667,52.566667],"type":"Point"}
}