{
  "id": 7113372,
  "type": "Feature",
  "properties": {
    "tgn:hierarchy":[
        "tgn:7113372",
        "tgn:7003669",
        "tgn:1000003",
        "tgn:7000084",
        "tgn:7029392"
    ],
    "tgn:id":7113372,
    "tgn:name":"Rosenau",
    "tgn:placetype":[
        "aat:300008347"
    ]
},
  "bbox": [],
  "geometry": {"coordinates":[13.416667,48.866667],"type":"Point"}
}