{
  "id": 7557154,
  "type": "Feature",
  "properties": {
    "tgn:hierarchy":[
        "tgn:7557154",
        "tgn:1000004",
        "tgn:7000198",
        "tgn:7016883",
        "tgn:7029392"
    ],
    "tgn:id":7557154,
    "tgn:name:en":"R\u0101mpura",
    "tgn:placetype":[
        "aat:300008347"
    ]
},
  "bbox": [],
  "geometry": {"coordinates":[75.240645,30.255061],"type":"Point"}
}