{
  "id": 2668362,
  "type": "Feature",
  "properties": {
    "tgn:hierarchy":[
        "tgn:2668362",
        "tgn:1000001",
        "tgn:2001260",
        "tgn:7012149",
        "tgn:7007524",
        "tgn:7029392"
    ],
    "tgn:id":2668362,
    "tgn:name":"Slag-a-melt Lakes",
    "tgn:placetype":[
        "aat:300008680"
    ]
},
  "bbox": [],
  "geometry": {"coordinates":[-113.7167,45.35],"type":"Point"}
}