{
  "id": 2438387,
  "type": "Feature",
  "properties": {
    "tgn:hierarchy":[
        "tgn:2438387",
        "tgn:1000001",
        "tgn:2000304",
        "tgn:7012149",
        "tgn:7007248",
        "tgn:7029392"
    ],
    "tgn:id":2438387,
    "tgn:name":"Kings Lake",
    "tgn:placetype":[
        "aat:300008680"
    ]
},
  "bbox": [],
  "geometry": {"coordinates":[-81.8667,31.1333],"type":"Point"}
}