{
  "id": 2307417,
  "type": "Feature",
  "properties": {
    "tgn:hierarchy":[
        "tgn:2307417",
        "tgn:1000001",
        "tgn:7012149",
        "tgn:2002112",
        "tgn:7007827",
        "tgn:7029392"
    ],
    "tgn:id":2307417,
    "tgn:name":"East Fork Sage Valley",
    "tgn:placetype":[
        "aat:300008761"
    ]
},
  "bbox": [],
  "geometry": {"coordinates":[-111.95,39.5833],"type":"Point"}
}