{
  "id": 7181239,
  "type": "Feature",
  "properties": {
    "tgn:hierarchy":[
        "tgn:7181239",
        "tgn:7003669",
        "tgn:1000003",
        "tgn:7000084",
        "tgn:7029392"
    ],
    "tgn:id":7181239,
    "tgn:name":"Garscham",
    "tgn:placetype":[
        "aat:300008347"
    ]
},
  "bbox": [],
  "geometry": {"coordinates":[12.683333,47.95],"type":"Point"}
}