{
  "id": 2625341,
  "type": "Feature",
  "properties": {
    "tgn:hierarchy":[
        "tgn:2625341",
        "tgn:7002659",
        "tgn:1000001",
        "tgn:7012149",
        "tgn:2000036",
        "tgn:7029392"
    ],
    "tgn:id":2625341,
    "tgn:name":"Rockhouse Hollow",
    "tgn:placetype":[
        "aat:300008761"
    ]
},
  "bbox": [],
  "geometry": {"coordinates":[-86.9667,33.4833],"type":"Point"}
}