{
  "id": 2630013,
  "type": "Feature",
  "properties": {
    "tgn:hierarchy":[
        "tgn:2630013",
        "tgn:1000001",
        "tgn:7016172",
        "tgn:7012149",
        "tgn:2000128",
        "tgn:7029392"
    ],
    "tgn:id":2630013,
    "tgn:name":"Rosson Hollow",
    "tgn:placetype":[
        "aat:300008761"
    ]
},
  "bbox": [],
  "geometry": {"coordinates":[-93.8667,35.65],"type":"Point"}
}