{
  "id": 7359598,
  "type": "Feature",
  "properties": {
    "tgn:hierarchy":[
        "tgn:7359598",
        "tgn:1000001",
        "tgn:7005594",
        "tgn:7005560",
        "tgn:7029392"
    ],
    "tgn:id":7359598,
    "tgn:name":"Cuatez\u00f3n",
    "tgn:placetype":[
        "aat:300008347"
    ]
},
  "bbox": [],
  "geometry": {"coordinates":[-100.283333,21.916667],"type":"Point"}
}