{
  "id": 7424114,
  "type": "Feature",
  "properties": {
    "tgn:hierarchy":[
        "tgn:7424114",
        "tgn:1000001",
        "tgn:7005597",
        "tgn:7005560",
        "tgn:7029392"
    ],
    "tgn:id":7424114,
    "tgn:name":"Rancho Nuevo",
    "tgn:placetype":[
        "aat:300008347"
    ]
},
  "bbox": [],
  "geometry": {"coordinates":[-99.683333,22.733333],"type":"Point"}
}