{
  "id": 2037942,
  "type": "Feature",
  "properties": {
    "tgn:hierarchy":[
        "tgn:2037942",
        "tgn:1000001",
        "tgn:7012149",
        "tgn:2000832",
        "tgn:7007255",
        "tgn:7029392"
    ],
    "tgn:id":2037942,
    "tgn:name":"Browder",
    "tgn:placetype":[
        "aat:300008347"
    ]
},
  "bbox": [],
  "geometry": {"coordinates":[-87.0333,37.1833],"type":"Point"}
}