{
  "id": 2286494,
  "type": "Feature",
  "properties": {
    "tgn:hierarchy":[
        "tgn:2286494",
        "tgn:1000001",
        "tgn:7012149",
        "tgn:2002371",
        "tgn:7007923",
        "tgn:7029392"
    ],
    "tgn:id":2286494,
    "tgn:name":"Diamond Ditch",
    "tgn:placetype":[
        "aat:300006075"
    ]
},
  "bbox": [],
  "geometry": {"coordinates":[-109.5167,43.4833],"type":"Point"}
}