{
  "id": 2731996,
  "type": "Feature",
  "properties": {
    "tgn:hierarchy":[
        "tgn:2731996",
        "tgn:1000001",
        "tgn:7012149",
        "tgn:2000916",
        "tgn:7007256",
        "tgn:7029392"
    ],
    "tgn:id":2731996,
    "tgn:name":"Tunica Hills",
    "tgn:placetype":[
        "aat:300386831"
    ]
},
  "bbox": [],
  "geometry": {"coordinates":[-91.55,30.9667],"type":"Point"}
}