{
  "id": 1021720,
  "type": "Feature",
  "properties": {
    "tgn:hierarchy":[
        "tgn:1021720",
        "tgn:7006237",
        "tgn:1000047",
        "tgn:7002457",
        "tgn:1000002",
        "tgn:7029392"
    ],
    "tgn:id":1021720,
    "tgn:name":"Itambacuri",
    "tgn:placetype":[
        "aat:300008347"
    ]
},
  "bbox": [],
  "geometry": {"coordinates":[-41.6833,-18.05],"type":"Point"}
}