{
  "id": 2367380,
  "type": "Feature",
  "properties": {
    "tgn:hierarchy":[
        "tgn:2367380",
        "tgn:1000001",
        "tgn:7012149",
        "tgn:2000494",
        "tgn:7007250",
        "tgn:7029392"
    ],
    "tgn:id":2367380,
    "tgn:name":"Ground Hog Creek",
    "tgn:placetype":[
        "aat:300008706"
    ]
},
  "bbox": [],
  "geometry": {"coordinates":[-115.8667,44.4167],"type":"Point"}
}