<<<<<<< HEAD
{
  "id": 7174563,
  "type": "Feature",
  "properties": {
    "tgn:hierarchy":[
        "tgn:7174563",
        "tgn:1000003",
        "tgn:7000094",
        "tgn:7000084",
        "tgn:7029392"
    ],
    "tgn:id":7174563,
    "tgn:name":"Der Gro\u00dfe Kiever See",
    "tgn:placetype":[
        "aat:300008680"
    ]
},
  "bbox": [],
  "geometry": {"coordinates":[12.616667,53.266667],"type":"Point"}
}
=======
{"geometry":{"type":"Point","coordinates":[12.616667,53.266667]},"type":"Feature","properties":{"hierarchy":["tgn:7174563","tgn:1000003","tgn:7000094","tgn:7000084","tgn:7029392"],"placetype":["aat:300008680"],"id":7174563,"name:xx":"Der Gro\u00dfe Kiever See"}}
>>>>>>> 03f74aca74312dbeaf24d7e61306dd6a786dc3d0
