{
  "id": 7260659,
  "type": "Feature",
  "properties": {
    "tgn:concordances":{
        "gn:id":"2757320"
    },
    "tgn:hierarchy":[
        "tgn:7260659",
        "tgn:1000003",
        "tgn:7003626",
        "tgn:7016845",
        "tgn:7029392"
    ],
    "tgn:id":7260659,
    "tgn:name:nl":"De Lutte",
    "tgn:placetype":[
        "aat:300008347"
    ]
},
  "bbox": [],
  "geometry": {"coordinates":[6.983333,52.316667],"type":"Point"}
}