{
  "id": 7295104,
  "type": "Feature",
  "properties": {
    "tgn:hierarchy":[
        "tgn:7295104",
        "tgn:7002834",
        "tgn:1000003",
        "tgn:7002786",
        "tgn:1000095",
        "tgn:7029392"
    ],
    "tgn:id":7295104,
    "tgn:name":"Peque\u00f1o, Cabo",
    "tgn:placetype":[
        "aat:300386846"
    ]
},
  "bbox": [],
  "geometry": {"coordinates":[-8.859722,42.252778],"type":"Point"}
}