{
  "id": 2675007,
  "type": "Feature",
  "properties": {
    "tgn:hierarchy":[
        "tgn:2675007",
        "tgn:1000001",
        "tgn:7012149",
        "tgn:7007158",
        "tgn:2000250",
        "tgn:7029392"
    ],
    "tgn:id":2675007,
    "tgn:name":"Soda Spring",
    "tgn:placetype":[
        "aat:300008697"
    ]
},
  "bbox": [],
  "geometry": {"coordinates":[-105.8667,39.5833],"type":"Point"}
}