{
  "id": 2315704,
  "type": "Feature",
  "properties": {
    "tgn:hierarchy":[
        "tgn:2315704",
        "tgn:1000001",
        "tgn:7006451",
        "tgn:2000093",
        "tgn:7012149",
        "tgn:7029392"
    ],
    "tgn:id":2315704,
    "tgn:name":"Ellison Creek Estates Subdivision",
    "tgn:placetype":[
        "aat:300008347"
    ]
},
  "bbox": [],
  "geometry": {"coordinates":[-111.1833,34.35],"type":"Point"}
}