{
  "id": 7523462,
  "type": "Feature",
  "properties": {
    "tgn:hierarchy":[
        "tgn:7523462",
        "tgn:7001242",
        "tgn:7016833",
        "tgn:1001418",
        "tgn:7029392"
    ],
    "tgn:id":7523462,
    "tgn:name:en":"Duy\u016br, Q\u0101rat ad",
    "tgn:placetype":[
        "aat:300008777"
    ]
},
  "bbox": [],
  "geometry": {"coordinates":[26.077947,28.87452],"type":"Point"}
}