{
  "id": 2219773,
  "type": "Feature",
  "properties": {
    "tgn:hierarchy":[
        "tgn:2219773",
        "tgn:1000001",
        "tgn:7012149",
        "tgn:2001716",
        "tgn:7007708",
        "tgn:7029392"
    ],
    "tgn:id":2219773,
    "tgn:name":"Canterbury Creek",
    "tgn:placetype":[
        "aat:300008706"
    ]
},
  "bbox": [],
  "geometry": {"coordinates":[-123.0833,44.1167],"type":"Point"}
}