{
  "id": 1070986,
  "type": "Feature",
  "properties": {
    "tgn:hierarchy":[
        "tgn:1070986",
        "tgn:1000004",
        "tgn:1001390",
        "tgn:1000111",
        "tgn:7029392"
    ],
    "tgn:id":1070986,
    "tgn:name":"Qianyamen",
    "tgn:placetype":[
        "aat:300008347"
    ]
},
  "bbox": [],
  "geometry": {"coordinates":[121.4333,42.0667],"type":"Point"}
}