{
  "id": 7567480,
  "type": "Feature",
  "properties": {
    "tgn:hierarchy":[
        "tgn:7567480",
        "tgn:1001828",
        "tgn:1000004",
        "tgn:7000198",
        "tgn:7029392"
    ],
    "tgn:id":7567480,
    "tgn:name:en":"Min\u0101j\u012bpet",
    "tgn:placetype":[
        "aat:300008347"
    ]
},
  "bbox": [],
  "geometry": {"coordinates":[78.546111,17.769444],"type":"Point"}
}