{
  "id": 7001705,
  "type": "Feature",
  "properties": {
    "tgn:hierarchy":[
        "tgn:7001705",
        "tgn:1000004",
        "tgn:1001678",
        "tgn:1000111",
        "tgn:7029392"
    ],
    "tgn:id":7001705,
    "tgn:name":"Weizhou Dao",
    "tgn:placetype":[
        "aat:300008791"
    ]
},
  "bbox": [],
  "geometry": {"coordinates":[109.0333,21.05],"type":"Point"}
}