{
  "id": 2022275,
  "type": "Feature",
  "properties": {
    "tgn:hierarchy":[
        "tgn:2022275",
        "tgn:1000001",
        "tgn:7012149",
        "tgn:2000349",
        "tgn:7007248",
        "tgn:7029392"
    ],
    "tgn:id":2022275,
    "tgn:name":"Brookwood",
    "tgn:placetype":[
        "aat:300008347",
        "aat:300387210"
    ]
},
  "bbox": [],
  "geometry": {"coordinates":[-84.1667,34.0833],"type":"Point"}
}