{
  "id": 1099173,
  "type": "Feature",
  "properties": {
    "tgn:hierarchy":[
        "tgn:1099173",
        "tgn:7000508",
        "tgn:1008380",
        "tgn:1000226",
        "tgn:1000006",
        "tgn:1007257",
        "tgn:7029392"
    ],
    "tgn:id":1099173,
    "tgn:name:en":"Port Fitzroy",
    "tgn:placetype":[
        "aat:300008347"
    ]
},
  "bbox": [],
  "geometry": {"coordinates":[175.35,-36.166667],"type":"Point"}
}