{
  "id": 7573716,
  "type": "Feature",
  "properties": {
    "tgn:hierarchy":[
        "tgn:7573716",
        "tgn:1000004",
        "tgn:7000198",
        "tgn:1001895",
        "tgn:7029392"
    ],
    "tgn:id":7573716,
    "tgn:name:en":"Kadus",
    "tgn:placetype":[
        "aat:300008347"
    ]
},
  "bbox": [],
  "geometry": {"coordinates":[73.816667,18.883333],"type":"Point"}
}