<<<<<<< HEAD
{
  "id": 7370007,
  "type": "Feature",
  "properties": {
    "tgn:hierarchy":[
        "tgn:7370007",
        "tgn:7005583",
        "tgn:1000001",
        "tgn:7005560",
        "tgn:7029392"
    ],
    "tgn:id":7370007,
    "tgn:name":"Gato, Sierra del",
    "tgn:placetype":[
        "aat:300008795"
    ]
},
  "bbox": [],
  "geometry": {"coordinates":[-104.233333,25.916667],"type":"Point"}
}
=======
{"geometry":{"type":"Point","coordinates":[-104.233333,25.916667]},"type":"Feature","properties":{"hierarchy":["tgn:7370007","tgn:7005583","tgn:1000001","tgn:7005560","tgn:7029392"],"placetype":["aat:300008795"],"id":7370007,"name:xx":"Gato, Sierra del"}}
>>>>>>> 03f74aca74312dbeaf24d7e61306dd6a786dc3d0
