{
  "id": 7387839,
  "type": "Feature",
  "properties": {
    "tgn:hierarchy":[
        "tgn:7387839",
        "tgn:1000001",
        "tgn:7005590",
        "tgn:7005560",
        "tgn:7029392"
    ],
    "tgn:id":7387839,
    "tgn:name":"Paso Ancho",
    "tgn:placetype":[
        "aat:300008347"
    ]
},
  "bbox": [],
  "geometry": {"coordinates":[-100.45,19.033333],"type":"Point"}
}