{
  "id": 2772391,
  "type": "Feature",
  "properties": {
    "tgn:hierarchy":[
        "tgn:2772391",
        "tgn:7006450",
        "tgn:1000001",
        "tgn:7012149",
        "tgn:2000082",
        "tgn:7029392"
    ],
    "tgn:id":2772391,
    "tgn:name":"William, Lake",
    "tgn:placetype":[
        "aat:300008680"
    ]
},
  "bbox": [],
  "geometry": {"coordinates":[-132.0333,55.1333],"type":"Point"}
}