{
  "id": 2648097,
  "type": "Feature",
  "properties": {
    "tgn:hierarchy":[
        "tgn:2648097",
        "tgn:1000001",
        "tgn:1002271",
        "tgn:7012149",
        "tgn:7007920",
        "tgn:7029392"
    ],
    "tgn:id":2648097,
    "tgn:name":"Schoolhouse Point",
    "tgn:placetype":[
        "aat:300008850"
    ]
},
  "bbox": [],
  "geometry": {"coordinates":[-123.0167,48.0333],"type":"Point"}
}