{
  "id": 7091162,
  "type": "Feature",
  "properties": {
    "tgn:hierarchy":[
        "tgn:7091162",
        "tgn:7003669",
        "tgn:1000003",
        "tgn:7000084",
        "tgn:7029392"
    ],
    "tgn:id":7091162,
    "tgn:name":"Vogelherd",
    "tgn:placetype":[
        "aat:300055621"
    ]
},
  "bbox": [],
  "geometry": {"coordinates":[10.983333,49.716667],"type":"Point"}
}