{
  "id": 7389997,
  "type": "Feature",
  "properties": {
    "tgn:hierarchy":[
        "tgn:7389997",
        "tgn:7005583",
        "tgn:1000001",
        "tgn:7005560",
        "tgn:7029392"
    ],
    "tgn:id":7389997,
    "tgn:name":"Rancho Floreno",
    "tgn:placetype":[
        "aat:300008347"
    ]
},
  "bbox": [],
  "geometry": {"coordinates":[-102.483333,24.433333],"type":"Point"}
}