<<<<<<< HEAD
{
  "id": 2766144,
  "type": "Feature",
  "properties": {
    "tgn:hierarchy":[
        "tgn:2766144",
        "tgn:1000001",
        "tgn:2001268",
        "tgn:7012149",
        "tgn:7007524",
        "tgn:7029392"
    ],
    "tgn:id":2766144,
    "tgn:name":"White Knob Creek",
    "tgn:placetype":[
        "aat:300008706"
    ]
},
  "bbox": [],
  "geometry": {"coordinates":[-105.05,46.3],"type":"Point"}
}
=======
{"geometry":{"type":"Point","coordinates":[-105.050000,46.300000]},"type":"Feature","properties":{"hierarchy":["tgn:2766144","tgn:1000001","tgn:2001268","tgn:7012149","tgn:7007524","tgn:7029392"],"placetype":["aat:300008706"],"id":2766144,"name:xx":"White Knob Creek"}}
>>>>>>> 03f74aca74312dbeaf24d7e61306dd6a786dc3d0
