{
  "id": 7050388,
  "type": "Feature",
  "properties": {
    "tgn:hierarchy":[
        "tgn:7050388",
        "tgn:1003429",
        "tgn:1000003",
        "tgn:7003240",
        "tgn:1000080",
        "tgn:7029392"
    ],
    "tgn:id":7050388,
    "tgn:name":"Mazzangrugno, Fosso di",
    "tgn:placetype":[
        "aat:300008699"
    ]
},
  "bbox": [],
  "geometry": {"coordinates":[13.333333,43.55],"type":"Point"}
}