<<<<<<< HEAD
{
  "id": 2156369,
  "type": "Feature",
  "properties": {
    "tgn:hierarchy":[
        "tgn:2156369",
        "tgn:1000001",
        "tgn:7012149",
        "tgn:2001285",
        "tgn:7007524",
        "tgn:7029392"
    ],
    "tgn:id":2156369,
    "tgn:name":"Bears Den",
    "tgn:placetype":[
        "aat:300386845"
    ]
},
  "bbox": [],
  "geometry": {"coordinates":[-110.9833,48.8833],"type":"Point"}
}
=======
{"geometry":{"type":"Point","coordinates":[-110.983300,48.883300]},"type":"Feature","properties":{"hierarchy":["tgn:2156369","tgn:1000001","tgn:7012149","tgn:2001285","tgn:7007524","tgn:7029392"],"placetype":["aat:300386845"],"id":2156369,"name:xx":"Bears Den"}}
>>>>>>> 03f74aca74312dbeaf24d7e61306dd6a786dc3d0
