{
  "id": 2156369,
  "type": "Feature",
  "properties": {
    "tgn:hierarchy":[
        "tgn:2156369",
        "tgn:1000001",
        "tgn:7012149",
        "tgn:2001285",
        "tgn:7007524",
        "tgn:7029392"
    ],
    "tgn:id":2156369,
    "tgn:name":"Bears Den",
    "tgn:placetype":[
        "aat:300386845"
    ]
},
  "bbox": [],
  "geometry": {"coordinates":[-110.9833,48.8833],"type":"Point"}
}