{
  "id": 2151492,
  "type": "Feature",
  "properties": {
    "tgn:hierarchy":[
        "tgn:2151492",
        "tgn:1000001",
        "tgn:7012149",
        "tgn:2000882",
        "tgn:7007256",
        "tgn:7029392"
    ],
    "tgn:id":2151492,
    "tgn:name":"Baton Pilon, Bayou",
    "tgn:placetype":[
        "aat:300008699"
    ]
},
  "bbox": [],
  "geometry": {"coordinates":[-90.7167,29.85],"type":"Point"}
}