{
  "id": 7388582,
  "type": "Feature",
  "properties": {
    "tgn:hierarchy":[
        "tgn:7388582",
        "tgn:1000001",
        "tgn:7005596",
        "tgn:7005560",
        "tgn:7029392"
    ],
    "tgn:id":7388582,
    "tgn:name":"Poza del Muerto",
    "tgn:placetype":[
        "aat:300008347"
    ]
},
  "bbox": [],
  "geometry": {"coordinates":[-91.066667,17.55],"type":"Point"}
}