{
  "id": 7047950,
  "type": "Feature",
  "properties": {
    "tgn:hierarchy":[
        "tgn:7047950",
        "tgn:7002994",
        "tgn:1000003",
        "tgn:7002997",
        "tgn:1000080",
        "tgn:7029392"
    ],
    "tgn:id":7047950,
    "tgn:name":"Canale d' Este",
    "tgn:placetype":[
        "aat:300006075"
    ]
},
  "bbox": [],
  "geometry": {"coordinates":[11.716667,45.216667],"type":"Point"}
}