{
  "id": 2700394,
  "type": "Feature",
  "properties": {
    "tgn:hierarchy":[
        "tgn:2700394",
        "tgn:1000001",
        "tgn:7012149",
        "tgn:2002181",
        "tgn:7007919",
        "tgn:7029392"
    ],
    "tgn:id":2700394,
    "tgn:name":"Subletts",
    "tgn:placetype":[
        "aat:300008347"
    ]
},
  "bbox": [],
  "geometry": {"coordinates":[-77.7333,37.5833],"type":"Point"}
}