{
  "id": 2307395,
  "type": "Feature",
  "properties": {
    "tgn:hierarchy":[
        "tgn:2307395",
        "tgn:1000001",
        "tgn:7012149",
        "tgn:7007826",
        "tgn:7029392"
    ],
    "tgn:id":2307395,
    "tgn:name":"East Fork Rocky Creek",
    "tgn:placetype":[
        "aat:300008706"
    ]
},
  "bbox": [],
  "geometry": {"coordinates":[-98.4833,30.1667],"type":"Point"}
}