{
  "id": 7412469,
  "type": "Feature",
  "properties": {
    "tgn:hierarchy":[
        "tgn:7412469",
        "tgn:7005587",
        "tgn:1000001",
        "tgn:7005560",
        "tgn:7029392"
    ],
    "tgn:id":7412469,
    "tgn:name:es":"Vicente Guerrero",
    "tgn:placetype":[
        "aat:300008347"
    ]
},
  "bbox": [],
  "geometry": {"coordinates":[-99.056944,20.172222],"type":"Point"}
}