{
  "id": 7335292,
  "type": "Feature",
  "properties": {
    "tgn:hierarchy":[
        "tgn:7335292",
        "tgn:7002825",
        "tgn:7016622",
        "tgn:1000003",
        "tgn:1000095",
        "tgn:7029392"
    ],
    "tgn:id":7335292,
    "tgn:name":"Gorda, Punta",
    "tgn:placetype":[
        "aat:300386846"
    ]
},
  "bbox": [],
  "geometry": {"coordinates":[-13.733333,28.866667],"type":"Point"}
}