{
  "id": 7531827,
  "type": "Feature",
  "properties": {
    "tgn:hierarchy":[
        "tgn:7531827",
        "tgn:7001242",
        "tgn:7016833",
        "tgn:1001091",
        "tgn:7029392"
    ],
    "tgn:id":7531827,
    "tgn:name:en":"Saint Theresa",
    "tgn:placetype":[
        "aat:300007780"
    ]
},
  "bbox": [],
  "geometry": {"coordinates":[31.24543,30.089126],"type":"Point"}
}