{
  "id": 7380907,
  "type": "Feature",
  "properties": {
    "tgn:hierarchy":[
        "tgn:7380907",
        "tgn:1000001",
        "tgn:1001960",
        "tgn:7005560",
        "tgn:7029392"
    ],
    "tgn:id":7380907,
    "tgn:name":"Los \u00c1lamos",
    "tgn:placetype":[
        "aat:300008347"
    ]
},
  "bbox": [],
  "geometry": {"coordinates":[-110.816667,30.333333],"type":"Point"}
}