{
  "id": 2659379,
  "type": "Feature",
  "properties": {
    "tgn:hierarchy":[
        "tgn:2659379",
        "tgn:1008293",
        "tgn:1000001",
        "tgn:1002705",
        "tgn:7012149",
        "tgn:7007517",
        "tgn:7029392"
    ],
    "tgn:id":2659379,
    "tgn:name":"Shimmo Pond",
    "tgn:placetype":[
        "aat:300008680"
    ]
},
  "bbox": [],
  "geometry": {"coordinates":[-70.05,41.2833],"type":"Point"}
}