{
  "id": 7033284,
  "type": "Feature",
  "properties": {
    "tgn:hierarchy":[
        "tgn:7033284",
        "tgn:1003505",
        "tgn:1000003",
        "tgn:7002993",
        "tgn:1000080",
        "tgn:7029392"
    ],
    "tgn:id":7033284,
    "tgn:name":"Visogljano",
    "tgn:placetype":[
        "aat:300008347"
    ]
},
  "bbox": [],
  "geometry": {"coordinates":[13.65,45.783333],"type":"Point"}
}