<<<<<<< HEAD
{
  "id": 2407449,
  "type": "Feature",
  "properties": {
    "tgn:hierarchy":[
        "tgn:2407449",
        "tgn:1000001",
        "tgn:7012149",
        "tgn:7029392"
    ],
    "tgn:id":2407449,
    "tgn:name":"Huntoon Creek",
    "tgn:placetype":[
        "aat:300008706"
    ]
},
  "bbox": [],
  "geometry": {"coordinates":[-118.6833,38.0833],"type":"Point"}
}
=======
{"geometry":{"type":"Point","coordinates":[-118.683300,38.083300]},"type":"Feature","properties":{"hierarchy":["tgn:2407449","tgn:1000001","tgn:7012149","tgn:7029392"],"placetype":["aat:300008706"],"id":2407449,"name:xx":"Huntoon Creek"}}
>>>>>>> 03f74aca74312dbeaf24d7e61306dd6a786dc3d0
