{
  "id": 2366295,
  "type": "Feature",
  "properties": {
    "tgn:hierarchy":[
        "tgn:2366295",
        "tgn:7002659",
        "tgn:1000001",
        "tgn:7012149",
        "tgn:2000033",
        "tgn:7029392"
    ],
    "tgn:id":2366295,
    "tgn:name":"Griffin Mine",
    "tgn:placetype":[
        "aat:300000390"
    ]
},
  "bbox": [],
  "geometry": {"coordinates":[-85.2167,31.6833],"type":"Point"}
}