<<<<<<< HEAD
{
  "id": 7477574,
  "type": "Feature",
  "properties": {
    "tgn:hierarchy":[
        "tgn:7477574",
        "tgn:1000004",
        "tgn:1000454",
        "tgn:1000141",
        "tgn:7029392"
    ],
    "tgn:id":7477574,
    "tgn:name":"Sirui Di'er Suidao",
    "tgn:placetype":[
        "aat:300007899"
    ]
},
  "bbox": [],
  "geometry": {"coordinates":[121.781455,25.104221],"type":"Point"}
}
=======
{"geometry":{"type":"Point","coordinates":[121.781455,25.104221]},"type":"Feature","properties":{"hierarchy":["tgn:7477574","tgn:1000004","tgn:1000454","tgn:1000141","tgn:7029392"],"placetype":["aat:300007899"],"id":7477574,"name:xx":"Sirui Di'er Suidao"}}
>>>>>>> 03f74aca74312dbeaf24d7e61306dd6a786dc3d0
