{
  "id": 7470713,
  "type": "Feature",
  "properties": {
    "tgn:hierarchy":[
        "tgn:7470713",
        "tgn:1000004",
        "tgn:7001014",
        "tgn:1000141",
        "tgn:7029392"
    ],
    "tgn:id":7470713,
    "tgn:name":"Houbiliao",
    "tgn:placetype":[
        "aat:300008347"
    ]
},
  "bbox": [],
  "geometry": {"coordinates":[120.423286,23.716593],"type":"Point"}
}