{
  "id": 1128466,
  "type": "Feature",
  "properties": {
    "tgn:hierarchy":[
        "tgn:1128466",
        "tgn:1000573",
        "tgn:1000001",
        "tgn:7005554",
        "tgn:7029392"
    ],
    "tgn:id":1128466,
    "tgn:name":"Paulaya, R\u00edo",
    "tgn:placetype":[
        "aat:300008707"
    ]
},
  "bbox": [],
  "geometry": {"coordinates":[-85.016,15.85],"type":"Point"}
}