{
  "id": 2610951,
  "type": "Feature",
  "properties": {
    "tgn:hierarchy":[
        "tgn:2610951",
        "tgn:1000001",
        "tgn:7012149",
        "tgn:2001195",
        "tgn:7007523",
        "tgn:7029392"
    ],
    "tgn:id":2610951,
    "tgn:name":"Red Hill",
    "tgn:placetype":[
        "aat:300008798"
    ]
},
  "bbox": [],
  "geometry": {"coordinates":[-91.2333,37.4833],"type":"Point"}
}