<<<<<<< HEAD
{
  "id": 2253801,
  "type": "Feature",
  "properties": {
    "tgn:hierarchy":[
        "tgn:2253801",
        "tgn:1000001",
        "tgn:7012149",
        "tgn:1002898",
        "tgn:7007826",
        "tgn:7029392"
    ],
    "tgn:id":2253801,
    "tgn:name":"Cooks Creek",
    "tgn:placetype":[
        "aat:300008706"
    ]
},
  "bbox": [],
  "geometry": {"coordinates":[-95.3667,32.4667],"type":"Point"}
}
=======
{"geometry":{"type":"Point","coordinates":[-95.366700,32.466700]},"type":"Feature","properties":{"hierarchy":["tgn:2253801","tgn:1000001","tgn:7012149","tgn:1002898","tgn:7007826","tgn:7029392"],"placetype":["aat:300008706"],"id":2253801,"name:xx":"Cooks Creek"}}
>>>>>>> 03f74aca74312dbeaf24d7e61306dd6a786dc3d0
