{
  "id": 2681812,
  "type": "Feature",
  "properties": {
    "tgn:hierarchy":[
        "tgn:2681812",
        "tgn:1000001",
        "tgn:7019560",
        "tgn:7012149",
        "tgn:7007566",
        "tgn:7029392"
    ],
    "tgn:id":2681812,
    "tgn:name":"South Sandhills Tank",
    "tgn:placetype":[
        "aat:300006191"
    ]
},
  "bbox": [],
  "geometry": {"coordinates":[-104.8167,34.1833],"type":"Point"}
}