{
  "id": 2145789,
  "type": "Feature",
  "properties": {
    "tgn:hierarchy":[
        "tgn:2145789",
        "tgn:1000001",
        "tgn:7012149",
        "tgn:7007158",
        "tgn:2000245",
        "tgn:7029392"
    ],
    "tgn:id":2145789,
    "tgn:name":"Baldy Peak",
    "tgn:placetype":[
        "aat:300008798"
    ]
},
  "bbox": [],
  "geometry": {"coordinates":[-107.2333,40.7333],"type":"Point"}
}