<<<<<<< HEAD
{
  "id": 2334613,
  "type": "Feature",
  "properties": {
    "tgn:hierarchy":[
        "tgn:2334613",
        "tgn:1000001",
        "tgn:7012149",
        "tgn:2001869",
        "tgn:7007825",
        "tgn:7029392"
    ],
    "tgn:id":2334613,
    "tgn:name":"Forestwood",
    "tgn:placetype":[
        "aat:300008347"
    ]
},
  "bbox": [],
  "geometry": {"coordinates":[-85.2167,35.1667],"type":"Point"}
}
=======
{"geometry":{"type":"Point","coordinates":[-85.216700,35.166700]},"type":"Feature","properties":{"hierarchy":["tgn:2334613","tgn:1000001","tgn:7012149","tgn:2001869","tgn:7007825","tgn:7029392"],"placetype":["aat:300008347"],"id":2334613,"name:xx":"Forestwood"}}
>>>>>>> 03f74aca74312dbeaf24d7e61306dd6a786dc3d0
