{
  "id": 2334613,
  "type": "Feature",
  "properties": {
    "tgn:hierarchy":[
        "tgn:2334613",
        "tgn:1000001",
        "tgn:7012149",
        "tgn:2001869",
        "tgn:7007825",
        "tgn:7029392"
    ],
    "tgn:id":2334613,
    "tgn:name":"Forestwood",
    "tgn:placetype":[
        "aat:300008347"
    ]
},
  "bbox": [],
  "geometry": {"coordinates":[-85.2167,35.1667],"type":"Point"}
}