{
  "id": 7203276,
  "type": "Feature",
  "properties": {
    "tgn:hierarchy":[
        "tgn:7203276",
        "tgn:1000003",
        "tgn:7003676",
        "tgn:7000084",
        "tgn:7029392"
    ],
    "tgn:id":7203276,
    "tgn:name":"Brunnen-Berg",
    "tgn:placetype":[
        "aat:300008777"
    ]
},
  "bbox": [],
  "geometry": {"coordinates":[9.216667,52.45],"type":"Point"}
}