<<<<<<< HEAD
{
  "id": 2152660,
  "type": "Feature",
  "properties": {
    "tgn:hierarchy":[
        "tgn:2152660",
        "tgn:1000001",
        "tgn:7012149",
        "tgn:7018871",
        "tgn:7007920",
        "tgn:7029392"
    ],
    "tgn:id":2152660,
    "tgn:name":"Bayne Junction",
    "tgn:placetype":[
        "aat:300008347"
    ]
},
  "bbox": [],
  "geometry": {"coordinates":[-121.9,47.3],"type":"Point"}
}
=======
{"geometry":{"type":"Point","coordinates":[-121.900000,47.300000]},"type":"Feature","properties":{"hierarchy":["tgn:2152660","tgn:1000001","tgn:7012149","tgn:7018871","tgn:7007920","tgn:7029392"],"placetype":["aat:300008347"],"id":2152660,"name:xx":"Bayne Junction"}}
>>>>>>> 03f74aca74312dbeaf24d7e61306dd6a786dc3d0
