{
  "id": 7281327,
  "type": "Feature",
  "properties": {
    "tgn:hierarchy":[
        "tgn:7281327",
        "tgn:7002464",
        "tgn:1000049",
        "tgn:1000002",
        "tgn:7029392"
    ],
    "tgn:id":7281327,
    "tgn:name":"Santa Catalina",
    "tgn:placetype":[
        "aat:300004792"
    ]
},
  "bbox": [],
  "geometry": {"coordinates":[-69.916667,-19.716667],"type":"Point"}
}