<<<<<<< HEAD
{
  "id": 2769967,
  "type": "Feature",
  "properties": {
    "tgn:hierarchy":[
        "tgn:2769967",
        "tgn:1000001",
        "tgn:7012149",
        "tgn:2000916",
        "tgn:7007256",
        "tgn:7029392"
    ],
    "tgn:id":2769967,
    "tgn:name":"Wilcox",
    "tgn:placetype":[
        "aat:300008347"
    ]
},
  "bbox": [],
  "geometry": {"coordinates":[-91.3833,30.8167],"type":"Point"}
}
=======
{"geometry":{"type":"Point","coordinates":[-91.383300,30.816700]},"type":"Feature","properties":{"hierarchy":["tgn:2769967","tgn:1000001","tgn:7012149","tgn:2000916","tgn:7007256","tgn:7029392"],"placetype":["aat:300008347"],"id":2769967,"name:xx":"Wilcox"}}
>>>>>>> 03f74aca74312dbeaf24d7e61306dd6a786dc3d0
