{
  "id": 2379304,
  "type": "Feature",
  "properties": {
    "tgn:hierarchy":[
        "tgn:2379304",
        "tgn:1000001",
        "tgn:7012149",
        "tgn:2000430",
        "tgn:7007248",
        "tgn:7029392"
    ],
    "tgn:id":2379304,
    "tgn:name":"Harve Clark Cove",
    "tgn:placetype":[
        "aat:300008761"
    ]
},
  "bbox": [],
  "geometry": {"coordinates":[-83.6833,34.8833],"type":"Point"}
}