{
  "id": 2689342,
  "type": "Feature",
  "properties": {
    "tgn:hierarchy":[
        "tgn:2689342",
        "tgn:1000001",
        "tgn:7012149",
        "tgn:2001723",
        "tgn:7007708",
        "tgn:7029392"
    ],
    "tgn:id":2689342,
    "tgn:name":"Squaw Creek",
    "tgn:placetype":[
        "aat:300008706"
    ]
},
  "bbox": [],
  "geometry": {"coordinates":[-119.7833,44.3333],"type":"Point"}
}