{
  "id": 7470977,
  "type": "Feature",
  "properties": {
    "tgn:hierarchy":[
        "tgn:7470977",
        "tgn:1000004",
        "tgn:1000454",
        "tgn:1000141",
        "tgn:7029392"
    ],
    "tgn:id":7470977,
    "tgn:name":"Houliao",
    "tgn:placetype":[
        "aat:300008347"
    ]
},
  "bbox": [],
  "geometry": {"coordinates":[121.829167,24.983611],"type":"Point"}
}