{
  "id": 2755865,
  "type": "Feature",
  "properties": {
    "tgn:hierarchy":[
        "tgn:2755865",
        "tgn:1000001",
        "tgn:2001411",
        "tgn:7012149",
        "tgn:7007526",
        "tgn:7029392"
    ],
    "tgn:id":2755865,
    "tgn:name":"Weeks Reservoir",
    "tgn:placetype":[
        "aat:300006191"
    ]
},
  "bbox": [],
  "geometry": {"coordinates":[-114.9333,40.8667],"type":"Point"}
}