{
  "id": 7007399,
  "type": "Feature",
  "properties": {
    "tgn:hierarchy":[
        "tgn:7007399",
        "tgn:7003740",
        "tgn:1000003",
        "tgn:7011731",
        "tgn:7029392"
    ],
    "tgn:id":7007399,
    "tgn:name":"Liestal",
    "tgn:placetype":[
        "aat:300008347",
        "aat:300387220",
        "aat:300008375"
    ]
},
  "bbox": [],
  "geometry": {"coordinates":[7.7167,47.4833],"type":"Point"}
}