{
  "id": 2505628,
  "type": "Feature",
  "properties": {
    "tgn:hierarchy":[
        "tgn:2505628",
        "tgn:1000001",
        "tgn:7012149",
        "tgn:2000484",
        "tgn:7007250",
        "tgn:7029392"
    ],
    "tgn:id":2505628,
    "tgn:name":"Menan Buttes",
    "tgn:placetype":[
        "aat:300008798"
    ]
},
  "bbox": [],
  "geometry": {"coordinates":[-111.9667,43.7833],"type":"Point"}
}