{
  "id": 7357493,
  "type": "Feature",
  "properties": {
    "tgn:hierarchy":[
        "tgn:7357493",
        "tgn:7005581",
        "tgn:1000001",
        "tgn:7005560",
        "tgn:7029392"
    ],
    "tgn:id":7357493,
    "tgn:name":"Cologachi, Arroyo",
    "tgn:placetype":[
        "aat:300008699"
    ]
},
  "bbox": [],
  "geometry": {"coordinates":[-107.466667,29.033333],"type":"Point"}
}