<<<<<<< HEAD
{
  "id": 7245433,
  "type": "Feature",
  "properties": {
    "tgn:hierarchy":[
        "tgn:7245433",
        "tgn:7003457",
        "tgn:1000003",
        "tgn:1000063",
        "tgn:7018236",
        "tgn:7029392"
    ],
    "tgn:id":7245433,
    "tgn:name":"Bassevelde",
    "tgn:placetype":[
        "aat:300008347"
    ]
},
  "bbox": [],
  "geometry": {"coordinates":[3.677984,51.23103],"type":"Point"}
}
=======
{"geometry":{"type":"Point","coordinates":[3.677984,51.231030]},"type":"Feature","properties":{"hierarchy":["tgn:7245433","tgn:7003457","tgn:1000003","tgn:1000063","tgn:7018236","tgn:7029392"],"placetype":["aat:300008347"],"id":7245433,"name:xx":"Bassevelde"}}
>>>>>>> 03f74aca74312dbeaf24d7e61306dd6a786dc3d0
