<<<<<<< HEAD
{
  "id": 7357761,
  "type": "Feature",
  "properties": {
    "tgn:hierarchy":[
        "tgn:7357761",
        "tgn:7005581",
        "tgn:1000001",
        "tgn:7005560",
        "tgn:7029392"
    ],
    "tgn:id":7357761,
    "tgn:name":"Rancho Corralitos",
    "tgn:placetype":[
        "aat:300000241"
    ]
},
  "bbox": [],
  "geometry": {"coordinates":[-107.933333,30.35],"type":"Point"}
}
=======
{"geometry":{"type":"Point","coordinates":[-107.933333,30.350000]},"type":"Feature","properties":{"hierarchy":["tgn:7357761","tgn:7005581","tgn:1000001","tgn:7005560","tgn:7029392"],"placetype":["aat:300000241"],"id":7357761,"name:xx":"Rancho Corralitos"}}
>>>>>>> 03f74aca74312dbeaf24d7e61306dd6a786dc3d0
