{
  "id": 2777465,
  "type": "Feature",
  "properties": {
    "tgn:hierarchy":[
        "tgn:2777465",
        "tgn:1000001",
        "tgn:7012149",
        "tgn:2001506",
        "tgn:7007709",
        "tgn:7029392"
    ],
    "tgn:id":2777465,
    "tgn:name":"Winn Bay",
    "tgn:placetype":[
        "aat:300132316"
    ]
},
  "bbox": [],
  "geometry": {"coordinates":[-76.0833,35.65],"type":"Point"}
}