{
  "id": 2024300,
  "type": "Feature",
  "properties": {
    "tgn:hierarchy":[
        "tgn:2024300",
        "tgn:1000001",
        "tgn:7012149",
        "tgn:2000386",
        "tgn:7007248",
        "tgn:7029392"
    ],
    "tgn:id":2024300,
    "tgn:name":"Shellman Bluff",
    "tgn:placetype":[
        "aat:300008347"
    ]
},
  "bbox": [],
  "geometry": {"coordinates":[-81.3167,31.5667],"type":"Point"}
}