{
  "id": 7480600,
  "type": "Feature",
  "properties": {
    "tgn:hierarchy":[
        "tgn:7480600",
        "tgn:1000004",
        "tgn:7001013",
        "tgn:1000141",
        "tgn:7029392"
    ],
    "tgn:id":7480600,
    "tgn:name":"Shanziding",
    "tgn:placetype":[
        "aat:300387033"
    ]
},
  "bbox": [],
  "geometry": {"coordinates":[121.209444,24.891944],"type":"Point"}
}