{
  "id": 1055626,
  "type": "Feature",
  "properties": {
    "tgn:hierarchy":[
        "tgn:1055626",
        "tgn:7017335",
        "tgn:1000003",
        "tgn:7006656",
        "tgn:7029392"
    ],
    "tgn:id":1055626,
    "tgn:name":"Corjeu\u0163i",
    "tgn:placetype":[
        "aat:300008347"
    ]
},
  "bbox": [],
  "geometry": {"coordinates":[27.05,48.2333],"type":"Point"}
}