{
  "id": 2382701,
  "type": "Feature",
  "properties": {
    "tgn:hierarchy":[
        "tgn:2382701",
        "tgn:1000001",
        "tgn:7012149",
        "tgn:7007157",
        "tgn:1002791",
        "tgn:7029392"
    ],
    "tgn:id":2382701,
    "tgn:name":"Hazard Mine",
    "tgn:placetype":[
        "aat:300000390"
    ]
},
  "bbox": [],
  "geometry": {"coordinates":[-120.75,39.0333],"type":"Point"}
}