{
  "id": 7589332,
  "type": "Feature",
  "properties": {
    "tgn:hierarchy":[
        "tgn:7589332",
        "tgn:1000004",
        "tgn:7000198",
        "tgn:1001977",
        "tgn:7029392"
    ],
    "tgn:id":7589332,
    "tgn:name:en":"S\u0101gar Flat",
    "tgn:placetype":[
        "aat:300386885"
    ]
},
  "bbox": [],
  "geometry": {"coordinates":[88.044444,21.702778],"type":"Point"}
}