{
  "id": 1134976,
  "type": "Feature",
  "properties": {
    "tgn:hierarchy":[
        "tgn:1134976",
        "tgn:7005735",
        "tgn:7005685",
        "tgn:1000001",
        "tgn:7013409",
        "tgn:7029392"
    ],
    "tgn:id":1134976,
    "tgn:name":"Walbran Creek",
    "tgn:placetype":[
        "aat:300008706"
    ]
},
  "bbox": [],
  "geometry": {"coordinates":[-124.6667,48.5667],"type":"Point"}
}