{
  "id": 2686828,
  "type": "Feature",
  "properties": {
    "tgn:hierarchy":[
        "tgn:2686828",
        "tgn:1000001",
        "tgn:7012149",
        "tgn:2001871",
        "tgn:7007825",
        "tgn:7029392"
    ],
    "tgn:id":2686828,
    "tgn:name":"Spring Creek Ranch Lake Number One",
    "tgn:placetype":[
        "aat:300006191"
    ]
},
  "bbox": [],
  "geometry": {"coordinates":[-89.0167,35.1333],"type":"Point"}
}