<<<<<<< HEAD
{
  "id": 7473874,
  "type": "Feature",
  "properties": {
    "tgn:hierarchy":[
        "tgn:7473874",
        "tgn:7001004",
        "tgn:1000004",
        "tgn:1000141",
        "tgn:7029392"
    ],
    "tgn:id":7473874,
    "tgn:name":"Tunzi Shan",
    "tgn:placetype":[
        "aat:300008798"
    ]
},
  "bbox": [],
  "geometry": {"coordinates":[120.761018,22.91057],"type":"Point"}
}
=======
{"geometry":{"type":"Point","coordinates":[120.761018,22.910570]},"type":"Feature","properties":{"hierarchy":["tgn:7473874","tgn:7001004","tgn:1000004","tgn:1000141","tgn:7029392"],"placetype":["aat:300008798"],"id":7473874,"name:xx":"Tunzi Shan"}}
>>>>>>> 03f74aca74312dbeaf24d7e61306dd6a786dc3d0
