{
  "id": 7210678,
  "type": "Feature",
  "properties": {
    "tgn:hierarchy":[
        "tgn:7210678",
        "tgn:1000003",
        "tgn:7003688",
        "tgn:7000084",
        "tgn:7029392"
    ],
    "tgn:id":7210678,
    "tgn:name":"Bekstrom",
    "tgn:placetype":[
        "aat:300008699"
    ]
},
  "bbox": [],
  "geometry": {"coordinates":[8.683333,54.516667],"type":"Point"}
}