{
  "id": 2274553,
  "type": "Feature",
  "properties": {
    "tgn:hierarchy":[
        "tgn:2274553",
        "tgn:1000001",
        "tgn:7012149",
        "tgn:1002732",
        "tgn:7007710",
        "tgn:7029392"
    ],
    "tgn:id":2274553,
    "tgn:name":"Dalmatia Creek",
    "tgn:placetype":[
        "aat:300008706"
    ]
},
  "bbox": [],
  "geometry": {"coordinates":[-76.8333,40.65],"type":"Point"}
}