{
  "id": 7093080,
  "type": "Feature",
  "properties": {
    "tgn:hierarchy":[
        "tgn:7093080",
        "tgn:1000003",
        "tgn:7003676",
        "tgn:7000084",
        "tgn:7029392"
    ],
    "tgn:id":7093080,
    "tgn:name":"Sch\u00f6ttel-Bach",
    "tgn:placetype":[
        "aat:300008699"
    ]
},
  "bbox": [],
  "geometry": {"coordinates":[9.833333,51.65],"type":"Point"}
}