{
  "id": 7334749,
  "type": "Feature",
  "properties": {
    "tgn:hierarchy":[
        "tgn:7334749",
        "tgn:7002758",
        "tgn:7002821",
        "tgn:1000003",
        "tgn:1000095",
        "tgn:7029392"
    ],
    "tgn:id":7334749,
    "tgn:name":"El Pozuelo",
    "tgn:placetype":[
        "aat:300008347"
    ]
},
  "bbox": [],
  "geometry": {"coordinates":[-3.15,36.75],"type":"Point"}
}