{
  "id": 1057435,
  "type": "Feature",
  "properties": {
    "tgn:hierarchy":[
        "tgn:1057435",
        "tgn:1000004",
        "tgn:6004412",
        "tgn:7018214",
        "tgn:7002435",
        "tgn:7029392"
    ],
    "tgn:id":1057435,
    "tgn:name":"Nizhnyaya Omka",
    "tgn:placetype":[
        "aat:300008347"
    ]
},
  "bbox": [],
  "geometry": {"coordinates":[74.9667,55.4667],"type":"Point"}
}