{
  "id": 7500474,
  "type": "Feature",
  "properties": {
    "tgn:hierarchy":[
        "tgn:7500474",
        "tgn:7001010",
        "tgn:1000004",
        "tgn:1000141",
        "tgn:7029392"
    ],
    "tgn:id":7500474,
    "tgn:name":"Gong Shan",
    "tgn:placetype":[
        "aat:300008798"
    ]
},
  "bbox": [],
  "geometry": {"coordinates":[121.107222,23.448611],"type":"Point"}
}