{
  "id": 2125006,
  "type": "Feature",
  "properties": {
    "tgn:hierarchy":[
        "tgn:2125006",
        "tgn:2002130",
        "tgn:1000001",
        "tgn:7012149",
        "tgn:7007828",
        "tgn:7029392"
    ],
    "tgn:id":2125006,
    "tgn:name":"Abraham, Mount",
    "tgn:placetype":[
        "aat:300008798"
    ]
},
  "bbox": [],
  "geometry": {"coordinates":[-72.9333,44.1167],"type":"Point"}
}