{
  "id": 2776900,
  "type": "Feature",
  "properties": {
    "tgn:hierarchy":[
        "tgn:2776900",
        "tgn:1000001",
        "tgn:2001417",
        "tgn:7012149",
        "tgn:7007526",
        "tgn:7029392"
    ],
    "tgn:id":2776900,
    "tgn:name":"Windup Mine",
    "tgn:placetype":[
        "aat:300000390"
    ]
},
  "bbox": [],
  "geometry": {"coordinates":[-118.2167,38.4833],"type":"Point"}
}