{
  "id": 2757750,
  "type": "Feature",
  "properties": {
    "tgn:hierarchy":[
        "tgn:2757750",
        "tgn:7002659",
        "tgn:1000001",
        "tgn:7012149",
        "tgn:2000057",
        "tgn:7029392"
    ],
    "tgn:id":2757750,
    "tgn:name":"West Branch Fishing Creek",
    "tgn:placetype":[
        "aat:300008706"
    ]
},
  "bbox": [],
  "geometry": {"coordinates":[-86.2667,33.6167],"type":"Point"}
}