{
  "id": 2565900,
  "type": "Feature",
  "properties": {
    "tgn:hierarchy":[
        "tgn:2565900",
        "tgn:1000001",
        "tgn:7012149",
        "tgn:1002870",
        "tgn:7007240",
        "tgn:7029392"
    ],
    "tgn:id":2565900,
    "tgn:name":"Palm Island",
    "tgn:placetype":[
        "aat:300008791"
    ]
},
  "bbox": [],
  "geometry": {"coordinates":[-82.55,27.2667],"type":"Point"}
}