{
  "id": 7345458,
  "type": "Feature",
  "properties": {
    "tgn:hierarchy":[
        "tgn:7345458",
        "tgn:7008912",
        "tgn:7030216",
        "tgn:1000003",
        "tgn:1000095",
        "tgn:7029392"
    ],
    "tgn:id":7345458,
    "tgn:name":"Alentorn",
    "tgn:placetype":[
        "aat:300008347"
    ]
},
  "bbox": [],
  "geometry": {"coordinates":[1.063841,41.925317],"type":"Point"}
}