{
  "id": 7461517,
  "type": "Feature",
  "properties": {
    "tgn:hierarchy":[
        "tgn:7461517",
        "tgn:7002444",
        "tgn:1000003",
        "tgn:7019109",
        "tgn:7008591",
        "tgn:7029392"
    ],
    "tgn:id":7461517,
    "tgn:name:en":"Joppa",
    "tgn:placetype":[
        "aat:300000745"
    ]
},
  "bbox": [],
  "geometry": {"coordinates":[-3.083333,55.95],"type":"Point"}
}