{
  "id": 2050923,
  "type": "Feature",
  "properties": {
    "tgn:hierarchy":[
        "tgn:2050923",
        "tgn:1000001",
        "tgn:7013686",
        "tgn:7012149",
        "tgn:7007517",
        "tgn:7029392"
    ],
    "tgn:id":2050923,
    "tgn:name":"West Pelham",
    "tgn:placetype":[
        "aat:300008347"
    ]
},
  "bbox": [],
  "geometry": {"coordinates":[-72.4667,42.3667],"type":"Point"}
}