{
  "id": 2552872,
  "type": "Feature",
  "properties": {
    "tgn:hierarchy":[
        "tgn:2552872",
        "tgn:1000001",
        "tgn:7012149",
        "tgn:2001290",
        "tgn:7007524",
        "tgn:7029392"
    ],
    "tgn:id":2552872,
    "tgn:name":"O R and N Mine",
    "tgn:placetype":[
        "aat:300000390"
    ]
},
  "bbox": [],
  "geometry": {"coordinates":[-114.9333,47.2667],"type":"Point"}
}