{
  "id": 7517654,
  "type": "Feature",
  "properties": {
    "tgn:hierarchy":[
        "tgn:7517654",
        "tgn:7520092",
        "tgn:1008380",
        "tgn:1000226",
        "tgn:1000006",
        "tgn:7029392"
    ],
    "tgn:id":7517654,
    "tgn:name:en":"Makaretu Stream",
    "tgn:placetype":[
        "aat:300008699"
    ]
},
  "bbox": [],
  "geometry": {"coordinates":[177.616667,-38.533333],"type":"Point"}
}