<<<<<<< HEAD
{
  "id": 2252481,
  "type": "Feature",
  "properties": {
    "tgn:hierarchy":[
        "tgn:2252481",
        "tgn:1000001",
        "tgn:2001009",
        "tgn:7012149",
        "tgn:7007521",
        "tgn:7029392"
    ],
    "tgn:id":2252481,
    "tgn:name":"Conklin Lake",
    "tgn:placetype":[
        "aat:300008680"
    ]
},
  "bbox": [],
  "geometry": {"coordinates":[-94.5167,47.05],"type":"Point"}
}
=======
{"geometry":{"type":"Point","coordinates":[-94.516700,47.050000]},"type":"Feature","properties":{"hierarchy":["tgn:2252481","tgn:1000001","tgn:2001009","tgn:7012149","tgn:7007521","tgn:7029392"],"placetype":["aat:300008680"],"id":2252481,"name:xx":"Conklin Lake"}}
>>>>>>> 03f74aca74312dbeaf24d7e61306dd6a786dc3d0
