<<<<<<< HEAD
{
  "id": 2768489,
  "type": "Feature",
  "properties": {
    "tgn:hierarchy":[
        "tgn:2768489",
        "tgn:7006450",
        "tgn:1000001",
        "tgn:7012149",
        "tgn:7019760",
        "tgn:7029392"
    ],
    "tgn:id":2768489,
    "tgn:name":"Whitewater Bay",
    "tgn:placetype":[
        "aat:300132316"
    ]
},
  "bbox": [],
  "geometry": {"coordinates":[-134.5833,57.2333],"type":"Point"}
}
=======
{"geometry":{"type":"Point","coordinates":[-134.583300,57.233300]},"type":"Feature","properties":{"hierarchy":["tgn:2768489","tgn:7006450","tgn:1000001","tgn:7012149","tgn:7019760","tgn:7029392"],"placetype":["aat:300132316"],"id":2768489,"name:xx":"Whitewater Bay"}}
>>>>>>> 03f74aca74312dbeaf24d7e61306dd6a786dc3d0
