{
  "id": 2106637,
  "type": "Feature",
  "properties": {
    "tgn:hierarchy":[
        "tgn:2106637",
        "tgn:1000001",
        "tgn:7012149",
        "tgn:1002464",
        "tgn:7007826",
        "tgn:7029392"
    ],
    "tgn:id":2106637,
    "tgn:name":"Pauline",
    "tgn:placetype":[
        "aat:300008347",
        "aat:300387210"
    ]
},
  "bbox": [],
  "geometry": {"coordinates":[-96.05,32.3333],"type":"Point"}
}