{
  "id": 1075429,
  "type": "Feature",
  "properties": {
    "tgn:hierarchy":[
        "tgn:1075429",
        "tgn:1000004",
        "tgn:7000198",
        "tgn:7016722",
        "tgn:7029392"
    ],
    "tgn:id":1075429,
    "tgn:name:en":"H\u0101thras",
    "tgn:placetype":[
        "aat:300008347"
    ]
},
  "bbox": [],
  "geometry": {"coordinates":[78.052373,27.59621],"type":"Point"}
}