{
  "id": 7519325,
  "type": "Feature",
  "properties": {
    "tgn:hierarchy":[
        "tgn:7519325",
        "tgn:1009227",
        "tgn:7001866",
        "tgn:1000226",
        "tgn:1000006",
        "tgn:7029392"
    ],
    "tgn:id":7519325,
    "tgn:name:en":"Alma Creek",
    "tgn:placetype":[
        "aat:300008699"
    ]
},
  "bbox": [],
  "geometry": {"coordinates":[170.816667,-43.533333],"type":"Point"}
}