{
  "id": 7537901,
  "type": "Feature",
  "properties": {
    "tgn:hierarchy":[
        "tgn:7537901",
        "tgn:7001242",
        "tgn:7001311",
        "tgn:7016833",
        "tgn:7029392"
    ],
    "tgn:id":7537901,
    "tgn:name:en":"Raqabah, W\u0101d\u012b ar",
    "tgn:placetype":[
        "aat:300379998"
    ]
},
  "bbox": [],
  "geometry": {"coordinates":[32.765346,26.758951],"type":"Point"}
}