<<<<<<< HEAD
{
  "id": 7028790,
  "type": "Feature",
  "properties": {
    "tgn:hierarchy":[
        "tgn:7028790",
        "tgn:7002445",
        "tgn:1000003",
        "tgn:7019057",
        "tgn:7008591",
        "tgn:7029392"
    ],
    "tgn:id":7028790,
    "tgn:name":"Anlaby",
    "tgn:placetype":[
        "aat:300008347",
        "aat:300008372"
    ]
},
  "bbox": [],
  "geometry": {"coordinates":[-0.433333,53.733333],"type":"Point"}
}
=======
{"geometry":{"type":"Point","coordinates":[-0.433333,53.733333]},"type":"Feature","properties":{"hierarchy":["tgn:7028790","tgn:7002445","tgn:1000003","tgn:7019057","tgn:7008591","tgn:7029392"],"placetype":["aat:300008347","aat:300008372"],"id":7028790,"name:xx":"Anlaby"}}
>>>>>>> 03f74aca74312dbeaf24d7e61306dd6a786dc3d0
