{
  "id": 2254922,
  "type": "Feature",
  "properties": {
    "tgn:hierarchy":[
        "tgn:2254922",
        "tgn:1000001",
        "tgn:1002415",
        "tgn:7012149",
        "tgn:7007828",
        "tgn:7029392"
    ],
    "tgn:id":2254922,
    "tgn:name":"Cooper Bay",
    "tgn:placetype":[
        "aat:300132316"
    ]
},
  "bbox": [],
  "geometry": {"coordinates":[-73.2833,44.6833],"type":"Point"}
}