{
  "id": 2697599,
  "type": "Feature",
  "properties": {
    "tgn:hierarchy":[
        "tgn:2697599",
        "tgn:1000001",
        "tgn:2002146",
        "tgn:7012149",
        "tgn:7007919",
        "tgn:7029392"
    ],
    "tgn:id":2697599,
    "tgn:name":"Stony Run",
    "tgn:placetype":[
        "aat:300008699"
    ]
},
  "bbox": [],
  "geometry": {"coordinates":[-79.9333,37.6833],"type":"Point"}
}