{
  "id": 7572067,
  "type": "Feature",
  "properties": {
    "tgn:hierarchy":[
        "tgn:7572067",
        "tgn:1000004",
        "tgn:7000198",
        "tgn:7016722",
        "tgn:7029392"
    ],
    "tgn:id":7572067,
    "tgn:name:en":"Gona",
    "tgn:placetype":[
        "aat:300008347"
    ]
},
  "bbox": [],
  "geometry": {"coordinates":[78.531543,24.413438],"type":"Point"}
}