{
  "id": 1031385,
  "type": "Feature",
  "properties": {
    "tgn:hierarchy":[
        "tgn:1031385",
        "tgn:1001385",
        "tgn:1000003",
        "tgn:1000069",
        "tgn:7029392"
    ],
    "tgn:id":1031385,
    "tgn:name":"Kolari",
    "tgn:placetype":[
        "aat:300008347"
    ]
},
  "bbox": [],
  "geometry": {"coordinates":[23.8333,67.3667],"type":"Point"}
}