{
  "id": 7588104,
  "type": "Feature",
  "properties": {
    "tgn:hierarchy":[
        "tgn:7588104",
        "tgn:1000004",
        "tgn:7000198",
        "tgn:7016722",
        "tgn:7029392"
    ],
    "tgn:id":7588104,
    "tgn:name:en":"Khori\u0101",
    "tgn:placetype":[
        "aat:300008347"
    ]
},
  "bbox": [],
  "geometry": {"coordinates":[78.942225,27.301951],"type":"Point"}
}