<<<<<<< HEAD
{
  "id": 2336676,
  "type": "Feature",
  "properties": {
    "tgn:hierarchy":[
        "tgn:2336676",
        "tgn:1000001",
        "tgn:7012149",
        "tgn:2001029",
        "tgn:7007521",
        "tgn:7029392"
    ],
    "tgn:id":2336676,
    "tgn:name":"Four Town Lake",
    "tgn:placetype":[
        "aat:300008680"
    ]
},
  "bbox": [],
  "geometry": {"coordinates":[-93.8833,47.6667],"type":"Point"}
}
=======
{"geometry":{"type":"Point","coordinates":[-93.883300,47.666700]},"type":"Feature","properties":{"hierarchy":["tgn:2336676","tgn:1000001","tgn:7012149","tgn:2001029","tgn:7007521","tgn:7029392"],"placetype":["aat:300008680"],"id":2336676,"name:xx":"Four Town Lake"}}
>>>>>>> 03f74aca74312dbeaf24d7e61306dd6a786dc3d0
