<<<<<<< HEAD
{
  "id": 7482897,
  "type": "Feature",
  "properties": {
    "tgn:hierarchy":[
        "tgn:7482897",
        "tgn:1000004",
        "tgn:7001014",
        "tgn:1000141",
        "tgn:7029392"
    ],
    "tgn:id":7482897,
    "tgn:name":"Dahudi Shan",
    "tgn:placetype":[
        "aat:300387002"
    ]
},
  "bbox": [],
  "geometry": {"coordinates":[120.598889,23.602778],"type":"Point"}
}
=======
{"geometry":{"type":"Point","coordinates":[120.598889,23.602778]},"type":"Feature","properties":{"hierarchy":["tgn:7482897","tgn:1000004","tgn:7001014","tgn:1000141","tgn:7029392"],"placetype":["aat:300387002"],"id":7482897,"name:xx":"Dahudi Shan"}}
>>>>>>> 03f74aca74312dbeaf24d7e61306dd6a786dc3d0
