{
  "id": 7272765,
  "type": "Feature",
  "properties": {
    "tgn:concordances":{
        "gn:id":"2745278"
    },
    "tgn:hierarchy":[
        "tgn:7272765",
        "tgn:7003619",
        "tgn:1000003",
        "tgn:7016845",
        "tgn:7029392"
    ],
    "tgn:id":7272765,
    "tgn:name:nl":"Voorstonden",
    "tgn:placetype":[
        "aat:300008347"
    ]
},
  "bbox": [],
  "geometry": {"coordinates":[6.15,52.133333],"type":"Point"}
}