{
  "id": 7202301,
  "type": "Feature",
  "properties": {
    "tgn:hierarchy":[
        "tgn:7202301",
        "tgn:1000003",
        "tgn:7003682",
        "tgn:7000084",
        "tgn:7029392"
    ],
    "tgn:id":7202301,
    "tgn:name":"Breiten-Berg",
    "tgn:placetype":[
        "aat:300266640"
    ]
},
  "bbox": [],
  "geometry": {"coordinates":[7.85,49.216667],"type":"Point"}
}