{
  "id": 7108076,
  "type": "Feature",
  "properties": {
    "tgn:hierarchy":[
        "tgn:7108076",
        "tgn:1000003",
        "tgn:7003677",
        "tgn:7000084",
        "tgn:7029392"
    ],
    "tgn:id":7108076,
    "tgn:name":"Rathshof",
    "tgn:placetype":[
        "aat:300000206"
    ]
},
  "bbox": [],
  "geometry": {"coordinates":[6.35,51.766667],"type":"Point"}
}