{
  "id": 2319454,
  "type": "Feature",
  "properties": {
    "tgn:hierarchy":[
        "tgn:2319454",
        "tgn:1000001",
        "tgn:7012149",
        "tgn:2002332",
        "tgn:7007922",
        "tgn:7029392"
    ],
    "tgn:id":2319454,
    "tgn:name":"Etna",
    "tgn:placetype":[
        "aat:300008347"
    ]
},
  "bbox": [],
  "geometry": {"coordinates":[-90.3167,42.55],"type":"Point"}
}