{
  "id": 7533244,
  "type": "Feature",
  "properties": {
    "tgn:hierarchy":[
        "tgn:7533244",
        "tgn:7001242",
        "tgn:7016833",
        "tgn:1001091",
        "tgn:7029392"
    ],
    "tgn:id":7533244,
    "tgn:name":"K\u016bbr\u012b Ab\u016b ar R\u012bsh",
    "tgn:placetype":[
        "aat:300007836"
    ]
},
  "bbox": [],
  "geometry": {"coordinates":[31.236062,30.028417],"type":"Point"}
}