{
  "id": 7165949,
  "type": "Feature",
  "properties": {
    "tgn:hierarchy":[
        "tgn:7165949",
        "tgn:1000003",
        "tgn:7003677",
        "tgn:7000084",
        "tgn:7029392"
    ],
    "tgn:id":7165949,
    "tgn:name":"Heiden",
    "tgn:placetype":[
        "aat:300008347"
    ]
},
  "bbox": [],
  "geometry": {"coordinates":[6.933333,51.833333],"type":"Point"}
}