{
  "id": 2235239,
  "type": "Feature",
  "properties": {
    "tgn:hierarchy":[
        "tgn:2235239",
        "tgn:1000001",
        "tgn:7012149",
        "tgn:2002118",
        "tgn:7007827",
        "tgn:7029392"
    ],
    "tgn:id":2235239,
    "tgn:name":"Cherry Tree Lane",
    "tgn:placetype":[
        "aat:300008347"
    ]
},
  "bbox": [],
  "geometry": {"coordinates":[-111.8333,40.6167],"type":"Point"}
}