{
  "id": 7486523,
  "type": "Feature",
  "properties": {
    "tgn:hierarchy":[
        "tgn:7486523",
        "tgn:1000004",
        "tgn:1000454",
        "tgn:1000141",
        "tgn:7029392"
    ],
    "tgn:id":7486523,
    "tgn:name":"Lengshuiku",
    "tgn:placetype":[
        "aat:300008347"
    ]
},
  "bbox": [],
  "geometry": {"coordinates":[121.602807,25.139868],"type":"Point"}
}