<<<<<<< HEAD
{
  "id": 7487602,
  "type": "Feature",
  "properties": {
    "tgn:hierarchy":[
        "tgn:7487602",
        "tgn:1000004",
        "tgn:7490934",
        "tgn:1000141",
        "tgn:7029392"
    ],
    "tgn:id":7487602,
    "tgn:name":"Liujiadian",
    "tgn:placetype":[
        "aat:300008347"
    ]
},
  "bbox": [],
  "geometry": {"coordinates":[120.268615,22.992266],"type":"Point"}
}
=======
{"geometry":{"type":"Point","coordinates":[120.268615,22.992266]},"type":"Feature","properties":{"hierarchy":["tgn:7487602","tgn:1000004","tgn:7490934","tgn:1000141","tgn:7029392"],"placetype":["aat:300008347"],"id":7487602,"name:xx":"Liujiadian"}}
>>>>>>> 03f74aca74312dbeaf24d7e61306dd6a786dc3d0
