{
  "id": 7180911,
  "type": "Feature",
  "properties": {
    "tgn:hierarchy":[
        "tgn:7180911",
        "tgn:1000003",
        "tgn:7000094",
        "tgn:7000084",
        "tgn:7029392"
    ],
    "tgn:id":7180911,
    "tgn:name":"Gell Ort",
    "tgn:placetype":[
        "aat:300386846"
    ]
},
  "bbox": [],
  "geometry": {"coordinates":[13.433333,54.683333],"type":"Point"}
}