{
  "id": 2063085,
  "type": "Feature",
  "properties": {
    "tgn:hierarchy":[
        "tgn:2063085",
        "tgn:1000001",
        "tgn:2001418",
        "tgn:7012149",
        "tgn:7007526",
        "tgn:7029392"
    ],
    "tgn:id":2063085,
    "tgn:name":"Reese River",
    "tgn:placetype":[
        "aat:300008347",
        "aat:300387210"
    ]
},
  "bbox": [],
  "geometry": {"coordinates":[-117.4667,38.9833],"type":"Point"}
}