{
  "id": 2493592,
  "type": "Feature",
  "properties": {
    "tgn:hierarchy":[
        "tgn:2493592",
        "tgn:1000001",
        "tgn:2000316",
        "tgn:7012149",
        "tgn:7007248",
        "tgn:7029392"
    ],
    "tgn:id":2493592,
    "tgn:name":"Marsh Island",
    "tgn:placetype":[
        "aat:300008791"
    ]
},
  "bbox": [],
  "geometry": {"coordinates":[-81.0667,31.9167],"type":"Point"}
}