<<<<<<< HEAD
{
  "id": 7483246,
  "type": "Feature",
  "properties": {
    "tgn:hierarchy":[
        "tgn:7483246",
        "tgn:1000004",
        "tgn:7490934",
        "tgn:1000141",
        "tgn:7029392"
    ],
    "tgn:id":7483246,
    "tgn:name":"Fanbao Jianshan",
    "tgn:placetype":[
        "aat:300008798"
    ]
},
  "bbox": [],
  "geometry": {"coordinates":[120.572222,23.19],"type":"Point"}
}
=======
{"geometry":{"type":"Point","coordinates":[120.572222,23.190000]},"type":"Feature","properties":{"hierarchy":["tgn:7483246","tgn:1000004","tgn:7490934","tgn:1000141","tgn:7029392"],"placetype":["aat:300008798"],"id":7483246,"name:xx":"Fanbao Jianshan"}}
>>>>>>> 03f74aca74312dbeaf24d7e61306dd6a786dc3d0
