<<<<<<< HEAD
{
  "id": 7023877,
  "type": "Feature",
  "properties": {
    "tgn:hierarchy":[
        "tgn:7023877",
        "tgn:1000004",
        "tgn:7001319",
        "tgn:1000111",
        "tgn:7029392"
    ],
    "tgn:id":7023877,
    "tgn:name":"Nam Co",
    "tgn:placetype":[
        "aat:300008680"
    ]
},
  "bbox": [],
  "geometry": {"coordinates":[90.5,30.75],"type":"Point"}
}
=======
{"geometry":{"type":"Point","coordinates":[90.500000,30.750000]},"type":"Feature","properties":{"hierarchy":["tgn:7023877","tgn:1000004","tgn:7001319","tgn:1000111","tgn:7029392"],"placetype":["aat:300008680"],"id":7023877,"name:xx":"Nam Co"}}
>>>>>>> 03f74aca74312dbeaf24d7e61306dd6a786dc3d0
