{
  "id": 1074306,
  "type": "Feature",
  "properties": {
    "tgn:hierarchy":[
        "tgn:1074306",
        "tgn:7018487",
        "tgn:1007810",
        "tgn:1000004",
        "tgn:7004542",
        "tgn:1000111",
        "tgn:7029392"
    ],
    "tgn:id":1074306,
    "tgn:name":"Tai O",
    "tgn:placetype":[
        "aat:300008347"
    ]
},
  "bbox": [],
  "geometry": {"coordinates":[113.8667,22.25],"type":"Point"}
}