{
  "id": 7501182,
  "type": "Feature",
  "properties": {
    "tgn:hierarchy":[
        "tgn:7501182",
        "tgn:1000004",
        "tgn:7467799",
        "tgn:1000141",
        "tgn:7029392"
    ],
    "tgn:id":7501182,
    "tgn:name":"Yongle Qiao",
    "tgn:placetype":[
        "aat:300007836"
    ]
},
  "bbox": [],
  "geometry": {"coordinates":[120.440556,24.005833],"type":"Point"}
}