<<<<<<< HEAD
{
  "id": 7021286,
  "type": "Feature",
  "properties": {
    "tgn:hierarchy":[
        "tgn:7021286",
        "tgn:1000001",
        "tgn:7012149",
        "tgn:2002287",
        "tgn:7013961",
        "tgn:7029392"
    ],
    "tgn:id":7021286,
    "tgn:name":"Cold Springs",
    "tgn:placetype":[
        "aat:300008697"
    ]
},
  "bbox": [],
  "geometry": {"coordinates":[-80.0833,38.1333],"type":"Point"}
}
=======
{"geometry":{"type":"Point","coordinates":[-80.083300,38.133300]},"type":"Feature","properties":{"hierarchy":["tgn:7021286","tgn:1000001","tgn:7012149","tgn:2002287","tgn:7013961","tgn:7029392"],"placetype":["aat:300008697"],"id":7021286,"name:xx":"Cold Springs"}}
>>>>>>> 03f74aca74312dbeaf24d7e61306dd6a786dc3d0
