{
  "id": 7561232,
  "type": "Feature",
  "properties": {
    "tgn:hierarchy":[
        "tgn:7561232",
        "tgn:1000004",
        "tgn:7000198",
        "tgn:7016722",
        "tgn:7029392"
    ],
    "tgn:id":7561232,
    "tgn:name:en":"Dahilia",
    "tgn:placetype":[
        "aat:300008347"
    ]
},
  "bbox": [],
  "geometry": {"coordinates":[79.754,27.2475],"type":"Point"}
}