{
  "id": 7497515,
  "type": "Feature",
  "properties": {
    "tgn:hierarchy":[
        "tgn:7497515",
        "tgn:1000004",
        "tgn:7001009",
        "tgn:1000141",
        "tgn:7029392"
    ],
    "tgn:id":7497515,
    "tgn:name":"Shenglin Qiao",
    "tgn:placetype":[
        "aat:300007836"
    ]
},
  "bbox": [],
  "geometry": {"coordinates":[120.627451,24.201514],"type":"Point"}
}