{
  "id": 7104064,
  "type": "Feature",
  "properties": {
    "tgn:hierarchy":[
        "tgn:7104064",
        "tgn:7000096",
        "tgn:1000003",
        "tgn:7000084",
        "tgn:7029392"
    ],
    "tgn:id":7104064,
    "tgn:name":"Schmachtenhagen",
    "tgn:placetype":[
        "aat:300008347"
    ]
},
  "bbox": [],
  "geometry": {"coordinates":[13.316667,52.766667],"type":"Point"}
}