<<<<<<< HEAD
{
  "id": 2155849,
  "type": "Feature",
  "properties": {
    "tgn:hierarchy":[
        "tgn:2155849",
        "tgn:1000001",
        "tgn:7012149",
        "tgn:2002381",
        "tgn:7007923",
        "tgn:7029392"
    ],
    "tgn:id":2155849,
    "tgn:name":"Bear Trap Creek",
    "tgn:placetype":[
        "aat:300008706"
    ]
},
  "bbox": [],
  "geometry": {"coordinates":[-107.7,44.8333],"type":"Point"}
}
=======
{"geometry":{"type":"Point","coordinates":[-107.700000,44.833300]},"type":"Feature","properties":{"hierarchy":["tgn:2155849","tgn:1000001","tgn:7012149","tgn:2002381","tgn:7007923","tgn:7029392"],"placetype":["aat:300008706"],"id":2155849,"name:xx":"Bear Trap Creek"}}
>>>>>>> 03f74aca74312dbeaf24d7e61306dd6a786dc3d0
