<<<<<<< HEAD
{
  "id": 7112982,
  "type": "Feature",
  "properties": {
    "tgn:hierarchy":[
        "tgn:7112982",
        "tgn:1000003",
        "tgn:7003678",
        "tgn:7000084",
        "tgn:7029392"
    ],
    "tgn:id":7112982,
    "tgn:name":"Rodheim vor der H\u00f6he",
    "tgn:placetype":[
        "aat:300008347"
    ]
},
  "bbox": [],
  "geometry": {"coordinates":[8.7,50.266667],"type":"Point"}
}
=======
{"geometry":{"type":"Point","coordinates":[8.700000,50.266667]},"type":"Feature","properties":{"hierarchy":["tgn:7112982","tgn:1000003","tgn:7003678","tgn:7000084","tgn:7029392"],"placetype":["aat:300008347"],"id":7112982,"name:xx":"Rodheim vor der H\u00f6he"}}
>>>>>>> 03f74aca74312dbeaf24d7e61306dd6a786dc3d0
