{
  "id": 2315277,
  "type": "Feature",
  "properties": {
    "tgn:hierarchy":[
        "tgn:2315277",
        "tgn:1000001",
        "tgn:7012149",
        "tgn:2001236",
        "tgn:7007523",
        "tgn:7029392"
    ],
    "tgn:id":2315277,
    "tgn:name":"Ellington Creek",
    "tgn:placetype":[
        "aat:300008706"
    ]
},
  "bbox": [],
  "geometry": {"coordinates":[-90.9667,37.1667],"type":"Point"}
}