{
  "id": 2497064,
  "type": "Feature",
  "properties": {
    "tgn:hierarchy":[
        "tgn:2497064",
        "tgn:1000001",
        "tgn:1002712",
        "tgn:7012149",
        "tgn:7007159",
        "tgn:7029392"
    ],
    "tgn:id":2497064,
    "tgn:name":"Maupas Pond",
    "tgn:placetype":[
        "aat:300008680"
    ]
},
  "bbox": [],
  "geometry": {"coordinates":[-72.6833,41.3333],"type":"Point"}
}