{
  "id": 2313524,
  "type": "Feature",
  "properties": {
    "tgn:hierarchy":[
        "tgn:2313524",
        "tgn:1000001",
        "tgn:7012149",
        "tgn:2001032",
        "tgn:7007521",
        "tgn:7029392"
    ],
    "tgn:id":2313524,
    "tgn:name":"Eleanor, Lake",
    "tgn:placetype":[
        "aat:300008680"
    ]
},
  "bbox": [],
  "geometry": {"coordinates":[-94.9833,45.0667],"type":"Point"}
}