{
  "id": 1134079,
  "type": "Feature",
  "properties": {
    "tgn:hierarchy":[
        "tgn:1134079",
        "tgn:1000001",
        "tgn:7012149",
        "tgn:7007157",
        "tgn:7029392"
    ],
    "tgn:id":1134079,
    "tgn:name":"Owens Creek",
    "tgn:placetype":[
        "aat:300008706"
    ]
},
  "bbox": [],
  "geometry": {"coordinates":[-120.0667,37.4667],"type":"Point"}
}