{
  "id": 7483699,
  "type": "Feature",
  "properties": {
    "tgn:hierarchy":[
        "tgn:7483699",
        "tgn:1000004",
        "tgn:7490934",
        "tgn:1000141",
        "tgn:7029392"
    ],
    "tgn:id":7483699,
    "tgn:name":"Pengzihu",
    "tgn:placetype":[
        "aat:300008347"
    ]
},
  "bbox": [],
  "geometry": {"coordinates":[120.520556,23.138611],"type":"Point"}
}