{
  "id": 2228033,
  "type": "Feature",
  "properties": {
    "tgn:hierarchy":[
        "tgn:2228033",
        "tgn:1000001",
        "tgn:7012149",
        "tgn:2002383",
        "tgn:7007923",
        "tgn:7029392"
    ],
    "tgn:id":2228033,
    "tgn:name":"Cedar Breaks Draw",
    "tgn:placetype":[
        "aat:300008761"
    ]
},
  "bbox": [],
  "geometry": {"coordinates":[-108.0167,41.0667],"type":"Point"}
}