{
  "id": 7083353,
  "type": "Feature",
  "properties": {
    "tgn:hierarchy":[
        "tgn:7083353",
        "tgn:7003669",
        "tgn:1000003",
        "tgn:7000084",
        "tgn:7029392"
    ],
    "tgn:id":7083353,
    "tgn:name":"Willenreuth",
    "tgn:placetype":[
        "aat:300008347"
    ]
},
  "bbox": [],
  "geometry": {"coordinates":[11.466667,49.75],"type":"Point"}
}