{
  "id": 2015774,
  "type": "Feature",
  "properties": {
    "tgn:hierarchy":[
        "tgn:2015774",
        "tgn:1000001",
        "tgn:7012149",
        "tgn:2000206",
        "tgn:7007158",
        "tgn:7029392"
    ],
    "tgn:id":2015774,
    "tgn:name":"Hotchkiss",
    "tgn:placetype":[
        "aat:300008347"
    ]
},
  "bbox": [],
  "geometry": {"coordinates":[-107.7167,38.7833],"type":"Point"}
}