{
  "id": 7094539,
  "type": "Feature",
  "properties": {
    "tgn:hierarchy":[
        "tgn:7094539",
        "tgn:7000096",
        "tgn:1000003",
        "tgn:7000084",
        "tgn:7029392"
    ],
    "tgn:id":7094539,
    "tgn:name":"Seebruch",
    "tgn:placetype":[
        "aat:300008903"
    ]
},
  "bbox": [],
  "geometry": {"coordinates":[13.716667,53.183333],"type":"Point"}
}