<<<<<<< HEAD
{
  "id": 7361662,
  "type": "Feature",
  "properties": {
    "tgn:hierarchy":[
        "tgn:7361662",
        "tgn:7005581",
        "tgn:1000001",
        "tgn:7005560",
        "tgn:7029392"
    ],
    "tgn:id":7361662,
    "tgn:name":"Rancho El Coyote",
    "tgn:placetype":[
        "aat:300000241"
    ]
},
  "bbox": [],
  "geometry": {"coordinates":[-108.516667,27.833333],"type":"Point"}
}
=======
{"geometry":{"type":"Point","coordinates":[-108.516667,27.833333]},"type":"Feature","properties":{"hierarchy":["tgn:7361662","tgn:7005581","tgn:1000001","tgn:7005560","tgn:7029392"],"placetype":["aat:300000241"],"id":7361662,"name:xx":"Rancho El Coyote"}}
>>>>>>> 03f74aca74312dbeaf24d7e61306dd6a786dc3d0
