<<<<<<< HEAD
{
  "id": 2400748,
  "type": "Feature",
  "properties": {
    "tgn:hierarchy":[
        "tgn:2400748",
        "tgn:1000001",
        "tgn:1002249",
        "tgn:7012149",
        "tgn:7007710",
        "tgn:7029392"
    ],
    "tgn:id":2400748,
    "tgn:name":"Horse Path Spring",
    "tgn:placetype":[
        "aat:300008697"
    ]
},
  "bbox": [],
  "geometry": {"coordinates":[-77.2667,40.95],"type":"Point"}
}
=======
{"geometry":{"type":"Point","coordinates":[-77.266700,40.950000]},"type":"Feature","properties":{"hierarchy":["tgn:2400748","tgn:1000001","tgn:1002249","tgn:7012149","tgn:7007710","tgn:7029392"],"placetype":["aat:300008697"],"id":2400748,"name:xx":"Horse Path Spring"}}
>>>>>>> 03f74aca74312dbeaf24d7e61306dd6a786dc3d0
