<<<<<<< HEAD
{
  "id": 2333627,
  "type": "Feature",
  "properties": {
    "tgn:hierarchy":[
        "tgn:2333627",
        "tgn:1000001",
        "tgn:7012149",
        "tgn:7007524",
        "tgn:7029392"
    ],
    "tgn:id":2333627,
    "tgn:name":"Fool Creek",
    "tgn:placetype":[
        "aat:300008706"
    ]
},
  "bbox": [],
  "geometry": {"coordinates":[-112.9667,47.95],"type":"Point"}
}
=======
{"geometry":{"type":"Point","coordinates":[-112.966700,47.950000]},"type":"Feature","properties":{"hierarchy":["tgn:2333627","tgn:1000001","tgn:7012149","tgn:7007524","tgn:7029392"],"placetype":["aat:300008706"],"id":2333627,"name:xx":"Fool Creek"}}
>>>>>>> 03f74aca74312dbeaf24d7e61306dd6a786dc3d0
