{
  "id": 2534248,
  "type": "Feature",
  "properties": {
    "tgn:hierarchy":[
        "tgn:2534248",
        "tgn:1000001",
        "tgn:1002714",
        "tgn:7012149",
        "tgn:7007159",
        "tgn:7029392"
    ],
    "tgn:id":2534248,
    "tgn:name":"Mystic Harbor",
    "tgn:placetype":[
        "aat:300132316"
    ]
},
  "bbox": [],
  "geometry": {"coordinates":[-71.9667,41.3333],"type":"Point"}
}