{
  "id": 2035323,
  "type": "Feature",
  "properties": {
    "tgn:hierarchy":[
        "tgn:2035323",
        "tgn:1000001",
        "tgn:7012149",
        "tgn:2000645",
        "tgn:7007253",
        "tgn:7029392"
    ],
    "tgn:id":2035323,
    "tgn:name":"Nevada",
    "tgn:placetype":[
        "aat:300008347"
    ]
},
  "bbox": [],
  "geometry": {"coordinates":[-93.45,42.0167],"type":"Point"}
}