{
  "id": 2348841,
  "type": "Feature",
  "properties": {
    "tgn:hierarchy":[
        "tgn:2348841",
        "tgn:1000001",
        "tgn:7012149",
        "tgn:2001770",
        "tgn:7007712",
        "tgn:7029392"
    ],
    "tgn:id":2348841,
    "tgn:name":"Gibson Pond",
    "tgn:placetype":[
        "aat:300006191"
    ]
},
  "bbox": [],
  "geometry": {"coordinates":[-80.9667,35.0333],"type":"Point"}
}