{
  "id": 7013091,
  "type": "Feature",
  "properties": {
    "tgn:hierarchy":[
        "tgn:7013091",
        "tgn:7005685",
        "tgn:1000001",
        "tgn:7013154",
        "tgn:7029392"
    ],
    "tgn:id":7013091,
    "tgn:name":"Peterborough",
    "tgn:placetype":[
        "aat:300008347"
    ]
},
  "bbox": [],
  "geometry": {"coordinates":[-78.3333,44.3333],"type":"Point"}
}