{
  "id": 2415334,
  "type": "Feature",
  "properties": {
    "tgn:hierarchy":[
        "tgn:2415334",
        "tgn:1000001",
        "tgn:7016172",
        "tgn:2000113",
        "tgn:7012149",
        "tgn:7029392"
    ],
    "tgn:id":2415334,
    "tgn:name":"Island Number 81",
    "tgn:placetype":[
        "aat:300008791"
    ]
},
  "bbox": [],
  "geometry": {"coordinates":[-91.2167,33.4667],"type":"Point"}
}