{
  "id": 1080730,
  "type": "Feature",
  "properties": {
    "tgn:hierarchy":[
        "tgn:1080730",
        "tgn:7000895",
        "tgn:1000004",
        "tgn:7016854",
        "tgn:1000120",
        "tgn:7029392"
    ],
    "tgn:id":1080730,
    "tgn:name":"Masuho",
    "tgn:placetype":[
        "aat:300008347"
    ]
},
  "bbox": [],
  "geometry": {"coordinates":[138.4667,35.5667],"type":"Point"}
}