{
  "id": 2283191,
  "type": "Feature",
  "properties": {
    "tgn:hierarchy":[
        "tgn:2283191",
        "tgn:1000001",
        "tgn:7012149",
        "tgn:2001990",
        "tgn:7007826",
        "tgn:7029392"
    ],
    "tgn:id":2283191,
    "tgn:name":"Delaware Creek",
    "tgn:placetype":[
        "aat:300008706"
    ]
},
  "bbox": [],
  "geometry": {"coordinates":[-99.05,30.1833],"type":"Point"}
}