{
  "id": 2371162,
  "type": "Feature",
  "properties": {
    "tgn:hierarchy":[
        "tgn:2371162",
        "tgn:1000001",
        "tgn:7012149",
        "tgn:2001714",
        "tgn:7007708",
        "tgn:7029392"
    ],
    "tgn:id":2371162,
    "tgn:name":"Hagerhorst Mountains",
    "tgn:placetype":[
        "aat:300386831"
    ]
},
  "bbox": [],
  "geometry": {"coordinates":[-120.9167,42.4667],"type":"Point"}
}