{
  "id": 7124375,
  "type": "Feature",
  "properties": {
    "tgn:hierarchy":[
        "tgn:7124375",
        "tgn:1000003",
        "tgn:7000094",
        "tgn:7000084",
        "tgn:7029392"
    ],
    "tgn:id":7124375,
    "tgn:name":"Neu Pennewitt",
    "tgn:placetype":[
        "aat:300008347"
    ]
},
  "bbox": [],
  "geometry": {"coordinates":[11.75,53.85],"type":"Point"}
}