{
  "id": 7561833,
  "type": "Feature",
  "properties": {
    "tgn:hierarchy":[
        "tgn:7561833",
        "tgn:1000004",
        "tgn:7000198",
        "tgn:7016722",
        "tgn:7029392"
    ],
    "tgn:id":7561833,
    "tgn:name:en":"Bagulahia",
    "tgn:placetype":[
        "aat:300008347"
    ]
},
  "bbox": [],
  "geometry": {"coordinates":[79.9408,27.1844],"type":"Point"}
}