{
  "id": 2527161,
  "type": "Feature",
  "properties": {
    "tgn:hierarchy":[
        "tgn:2527161",
        "tgn:1000001",
        "tgn:7012149",
        "tgn:7007248",
        "tgn:7029392"
    ],
    "tgn:id":2527161,
    "tgn:name":"Mount Hope Creek",
    "tgn:placetype":[
        "aat:300008706"
    ]
},
  "bbox": [],
  "geometry": {"coordinates":[-81.4333,31.9333],"type":"Point"}
}