<<<<<<< HEAD
{
  "id": 7376809,
  "type": "Feature",
  "properties": {
    "tgn:hierarchy":[
        "tgn:7376809",
        "tgn:7005583",
        "tgn:1000001",
        "tgn:7005560",
        "tgn:7029392"
    ],
    "tgn:id":7376809,
    "tgn:name":"Las Mangas",
    "tgn:placetype":[
        "aat:300008347"
    ]
},
  "bbox": [],
  "geometry": {"coordinates":[-104.2,25.133333],"type":"Point"}
}
=======
{"geometry":{"type":"Point","coordinates":[-104.200000,25.133333]},"type":"Feature","properties":{"hierarchy":["tgn:7376809","tgn:7005583","tgn:1000001","tgn:7005560","tgn:7029392"],"placetype":["aat:300008347"],"id":7376809,"name:xx":"Las Mangas"}}
>>>>>>> 03f74aca74312dbeaf24d7e61306dd6a786dc3d0
