{
  "id": 2554218,
  "type": "Feature",
  "properties": {
    "tgn:hierarchy":[
        "tgn:2554218",
        "tgn:1000001",
        "tgn:2001418",
        "tgn:7012149",
        "tgn:7007526",
        "tgn:7029392"
    ],
    "tgn:id":2554218,
    "tgn:name":"Oak Spring Butte",
    "tgn:placetype":[
        "aat:300008798"
    ]
},
  "bbox": [],
  "geometry": {"coordinates":[-116.05,37.25],"type":"Point"}
}