{
  "id": 7276414,
  "type": "Feature",
  "properties": {
    "tgn:hierarchy":[
        "tgn:7276414",
        "tgn:1001702",
        "tgn:1000049",
        "tgn:1000002",
        "tgn:7029392"
    ],
    "tgn:id":7276414,
    "tgn:name":"Thorn, Roca",
    "tgn:placetype":[
        "aat:300011692"
    ]
},
  "bbox": [],
  "geometry": {"coordinates":[-75.126111,-50.013056],"type":"Point"}
}