{
  "id": 7212791,
  "type": "Feature",
  "properties": {
    "tgn:hierarchy":[
        "tgn:7212791",
        "tgn:1000003",
        "tgn:7003688",
        "tgn:7000084",
        "tgn:7029392"
    ],
    "tgn:id":7212791,
    "tgn:name":"Bockhorst Berg",
    "tgn:placetype":[
        "aat:300008777"
    ]
},
  "bbox": [],
  "geometry": {"coordinates":[9.683333,54.233333],"type":"Point"}
}