{
  "id": 7343475,
  "type": "Feature",
  "properties": {
    "tgn:hierarchy":[
        "tgn:7343475",
        "tgn:7002803",
        "tgn:1001647",
        "tgn:1000003",
        "tgn:1000095",
        "tgn:7029392"
    ],
    "tgn:id":7343475,
    "tgn:name":"Casas del R\u00edo",
    "tgn:placetype":[
        "aat:300008347"
    ]
},
  "bbox": [],
  "geometry": {"coordinates":[-1.95,39.183333],"type":"Point"}
}