{
  "id": 7569691,
  "type": "Feature",
  "properties": {
    "tgn:hierarchy":[
        "tgn:7569691",
        "tgn:1000004",
        "tgn:7000198",
        "tgn:7031786",
        "tgn:7029392"
    ],
    "tgn:id":7569691,
    "tgn:name:en":"Kur\u012bgaon",
    "tgn:placetype":[
        "aat:300008347"
    ]
},
  "bbox": [],
  "geometry": {"coordinates":[78.723147,29.945718],"type":"Point"}
}