{
  "id": 2615783,
  "type": "Feature",
  "properties": {
    "tgn:hierarchy":[
        "tgn:2615783",
        "tgn:2000858",
        "tgn:1000001",
        "tgn:7012149",
        "tgn:7007256",
        "tgn:7029392"
    ],
    "tgn:id":2615783,
    "tgn:name":"Reynolds",
    "tgn:placetype":[
        "aat:300008347"
    ]
},
  "bbox": [],
  "geometry": {"coordinates":[-92.2167,31.2167],"type":"Point"}
}