<<<<<<< HEAD
{
  "id": 7023516,
  "type": "Feature",
  "properties": {
    "tgn:hierarchy":[
        "tgn:7023516",
        "tgn:1000001",
        "tgn:7012149",
        "tgn:7029392"
    ],
    "tgn:id":7023516,
    "tgn:name":"Muldoon Mountain",
    "tgn:placetype":[
        "aat:300008798"
    ]
},
  "bbox": [],
  "geometry": {"coordinates":[-120.6833,41.9833],"type":"Point"}
}
=======
{"geometry":{"type":"Point","coordinates":[-120.683300,41.983300]},"type":"Feature","properties":{"hierarchy":["tgn:7023516","tgn:1000001","tgn:7012149","tgn:7029392"],"placetype":["aat:300008798"],"id":7023516,"name:xx":"Muldoon Mountain"}}
>>>>>>> 03f74aca74312dbeaf24d7e61306dd6a786dc3d0
