{
  "id": 7023516,
  "type": "Feature",
  "properties": {
    "tgn:hierarchy":[
        "tgn:7023516",
        "tgn:1000001",
        "tgn:7012149",
        "tgn:7029392"
    ],
    "tgn:id":7023516,
    "tgn:name":"Muldoon Mountain",
    "tgn:placetype":[
        "aat:300008798"
    ]
},
  "bbox": [],
  "geometry": {"coordinates":[-120.6833,41.9833],"type":"Point"}
}