{
  "id": 2529420,
  "type": "Feature",
  "properties": {
    "tgn:hierarchy":[
        "tgn:2529420",
        "tgn:1000001",
        "tgn:7012149",
        "tgn:2001031",
        "tgn:7007521",
        "tgn:7029392"
    ],
    "tgn:id":2529420,
    "tgn:name":"Mud Lake",
    "tgn:placetype":[
        "aat:300008680"
    ]
},
  "bbox": [],
  "geometry": {"coordinates":[-93.1667,45.8833],"type":"Point"}
}