<<<<<<< HEAD
{
  "id": 7054924,
  "type": "Feature",
  "properties": {
    "tgn:hierarchy":[
        "tgn:7054924",
        "tgn:7003162",
        "tgn:1000003",
        "tgn:7009760",
        "tgn:1000080",
        "tgn:7029392"
    ],
    "tgn:id":7054924,
    "tgn:name":"Molinaccio, Fosso del",
    "tgn:placetype":[
        "aat:300008699"
    ]
},
  "bbox": [],
  "geometry": {"coordinates":[11.966667,43.233333],"type":"Point"}
}
=======
{"geometry":{"type":"Point","coordinates":[11.966667,43.233333]},"type":"Feature","properties":{"hierarchy":["tgn:7054924","tgn:7003162","tgn:1000003","tgn:7009760","tgn:1000080","tgn:7029392"],"placetype":["aat:300008699"],"id":7054924,"name:xx":"Molinaccio, Fosso del"}}
>>>>>>> 03f74aca74312dbeaf24d7e61306dd6a786dc3d0
