{
  "id": 7259754,
  "type": "Feature",
  "properties": {
    "tgn:hierarchy":[
        "tgn:7259754",
        "tgn:7003457",
        "tgn:1000003",
        "tgn:1000063",
        "tgn:7018236",
        "tgn:7029392"
    ],
    "tgn:id":7259754,
    "tgn:name":"Welle",
    "tgn:placetype":[
        "aat:300008347"
    ]
},
  "bbox": [],
  "geometry": {"coordinates":[4.052829,50.893501],"type":"Point"}
}