{
  "id": 2211461,
  "type": "Feature",
  "properties": {
    "tgn:hierarchy":[
        "tgn:2211461",
        "tgn:1000001",
        "tgn:7012149",
        "tgn:2002118",
        "tgn:7007827",
        "tgn:7029392"
    ],
    "tgn:id":2211461,
    "tgn:name":"Butterfield Canyon",
    "tgn:placetype":[
        "aat:300008761"
    ]
},
  "bbox": [],
  "geometry": {"coordinates":[-112.15,40.4833],"type":"Point"}
}