{
  "id": 2249104,
  "type": "Feature",
  "properties": {
    "tgn:hierarchy":[
        "tgn:2249104",
        "tgn:1000001",
        "tgn:7012149",
        "tgn:1002403",
        "tgn:7007709",
        "tgn:7029392"
    ],
    "tgn:id":2249104,
    "tgn:name":"Cole Creek",
    "tgn:placetype":[
        "aat:300008706"
    ]
},
  "bbox": [],
  "geometry": {"coordinates":[-76.7667,36.4667],"type":"Point"}
}