{
  "id": 7048735,
  "type": "Feature",
  "properties": {
    "tgn:hierarchy":[
        "tgn:7048735",
        "tgn:1003473",
        "tgn:1000003",
        "tgn:7009760",
        "tgn:1000080",
        "tgn:7029392"
    ],
    "tgn:id":7048735,
    "tgn:name":"Dozzano",
    "tgn:placetype":[
        "aat:300008347"
    ]
},
  "bbox": [],
  "geometry": {"coordinates":[9.85,44.366667],"type":"Point"}
}