{
  "id": 1051438,
  "type": "Feature",
  "properties": {
    "tgn:hierarchy":[
        "tgn:1051438",
        "tgn:1003357",
        "tgn:1000003",
        "tgn:7006657",
        "tgn:7029392"
    ],
    "tgn:id":1051438,
    "tgn:name":"\u010cudin",
    "tgn:placetype":[
        "aat:300008347"
    ]
},
  "bbox": [],
  "geometry": {"coordinates":[26.9833,52.7333],"type":"Point"}
}