{
  "id": 2397433,
  "type": "Feature",
  "properties": {
    "tgn:hierarchy":[
        "tgn:2397433",
        "tgn:1000001",
        "tgn:7012149",
        "tgn:2002352",
        "tgn:7007922",
        "tgn:7029392"
    ],
    "tgn:id":2397433,
    "tgn:name":"Honey Creek",
    "tgn:placetype":[
        "aat:300008706"
    ]
},
  "bbox": [],
  "geometry": {"coordinates":[-90.0333,43.3833],"type":"Point"}
}