{
  "id": 7499842,
  "type": "Feature",
  "properties": {
    "tgn:hierarchy":[
        "tgn:7499842",
        "tgn:1000004",
        "tgn:1000454",
        "tgn:1000141",
        "tgn:7029392"
    ],
    "tgn:id":7499842,
    "tgn:name":"Jiushe",
    "tgn:placetype":[
        "aat:300008347"
    ]
},
  "bbox": [],
  "geometry": {"coordinates":[121.389025,25.128154],"type":"Point"}
}