<<<<<<< HEAD
{
  "id": 7176453,
  "type": "Feature",
  "properties": {
    "tgn:hierarchy":[
        "tgn:7176453",
        "tgn:7003669",
        "tgn:1000003",
        "tgn:7000084",
        "tgn:7029392"
    ],
    "tgn:id":7176453,
    "tgn:name":"Hals K\u00f6pfl",
    "tgn:placetype":[
        "aat:300008798"
    ]
},
  "bbox": [],
  "geometry": {"coordinates":[12.966667,47.516667],"type":"Point"}
}
=======
{"geometry":{"type":"Point","coordinates":[12.966667,47.516667]},"type":"Feature","properties":{"hierarchy":["tgn:7176453","tgn:7003669","tgn:1000003","tgn:7000084","tgn:7029392"],"placetype":["aat:300008798"],"id":7176453,"name:xx":"Hals K\u00f6pfl"}}
>>>>>>> 03f74aca74312dbeaf24d7e61306dd6a786dc3d0
