{
  "id": 7477917,
  "type": "Feature",
  "properties": {
    "tgn:hierarchy":[
        "tgn:7477917",
        "tgn:1000004",
        "tgn:7467799",
        "tgn:1000141",
        "tgn:7029392"
    ],
    "tgn:id":7477917,
    "tgn:name":"Beidou Gaozhong",
    "tgn:placetype":[
        "aat:300006495"
    ]
},
  "bbox": [],
  "geometry": {"coordinates":[120.521641,23.878522],"type":"Point"}
}