{
  "id": 7478509,
  "type": "Feature",
  "properties": {
    "tgn:hierarchy":[
        "tgn:7478509",
        "tgn:1000004",
        "tgn:7467799",
        "tgn:1000141",
        "tgn:7029392"
    ],
    "tgn:id":7478509,
    "tgn:name":"Zhongxing Er Qiao",
    "tgn:placetype":[
        "aat:300007836"
    ]
},
  "bbox": [],
  "geometry": {"coordinates":[120.548,23.886927],"type":"Point"}
}