{
  "id": 2697421,
  "type": "Feature",
  "properties": {
    "tgn:hierarchy":[
        "tgn:2697421",
        "tgn:2001732",
        "tgn:1000001",
        "tgn:7012149",
        "tgn:7007712",
        "tgn:7029392"
    ],
    "tgn:id":2697421,
    "tgn:name":"Stony Landing",
    "tgn:placetype":[
        "aat:300008347"
    ]
},
  "bbox": [],
  "geometry": {"coordinates":[-79.9667,33.1833],"type":"Point"}
}