{
  "id": 2521795,
  "type": "Feature",
  "properties": {
    "tgn:hierarchy":[
        "tgn:2521795",
        "tgn:1000001",
        "tgn:2000952",
        "tgn:7012149",
        "tgn:7007520",
        "tgn:7029392"
    ],
    "tgn:id":2521795,
    "tgn:name":"Monument Lake",
    "tgn:placetype":[
        "aat:300008680"
    ]
},
  "bbox": [],
  "geometry": {"coordinates":[-84.85,46.35],"type":"Point"}
}