{
  "id": 7182890,
  "type": "Feature",
  "properties": {
    "tgn:hierarchy":[
        "tgn:7182890",
        "tgn:1000003",
        "tgn:7003678",
        "tgn:7000084",
        "tgn:7029392"
    ],
    "tgn:id":7182890,
    "tgn:name":"Friedrichsfeld",
    "tgn:placetype":[
        "aat:300008347"
    ]
},
  "bbox": [],
  "geometry": {"coordinates":[9.466667,51.566667],"type":"Point"}
}