{
  "id": 2309053,
  "type": "Feature",
  "properties": {
    "tgn:hierarchy":[
        "tgn:2309053",
        "tgn:1000001",
        "tgn:7012149",
        "tgn:2001717",
        "tgn:7007708",
        "tgn:7029392"
    ],
    "tgn:id":2309053,
    "tgn:name":"East Rock Creek",
    "tgn:placetype":[
        "aat:300008706"
    ]
},
  "bbox": [],
  "geometry": {"coordinates":[-122.3333,44.6667],"type":"Point"}
}