{
  "id": 2301526,
  "type": "Feature",
  "properties": {
    "tgn:hierarchy":[
        "tgn:2301526",
        "tgn:1000001",
        "tgn:7012149",
        "tgn:2000902",
        "tgn:7007256",
        "tgn:7029392"
    ],
    "tgn:id":2301526,
    "tgn:name":"Dunns Lake",
    "tgn:placetype":[
        "aat:300008680"
    ]
},
  "bbox": [],
  "geometry": {"coordinates":[-91.9833,30.8333],"type":"Point"}
}