{
  "id": 2709037,
  "type": "Feature",
  "properties": {
    "tgn:hierarchy":[
        "tgn:2709037",
        "tgn:1000001",
        "tgn:7012149",
        "tgn:2002010",
        "tgn:7007826",
        "tgn:7029392"
    ],
    "tgn:id":2709037,
    "tgn:name":"T and P Lake",
    "tgn:placetype":[
        "aat:300008680"
    ]
},
  "bbox": [],
  "geometry": {"coordinates":[-103.8333,30.7833],"type":"Point"}
}