{
  "id": 7564852,
  "type": "Feature",
  "properties": {
    "tgn:hierarchy":[
        "tgn:7564852",
        "tgn:1000004",
        "tgn:7000198",
        "tgn:7016722",
        "tgn:7029392"
    ],
    "tgn:id":7564852,
    "tgn:name:en":"Purwa Kah\u0101r\u0101n",
    "tgn:placetype":[
        "aat:300008347"
    ]
},
  "bbox": [],
  "geometry": {"coordinates":[79.677509,26.91118],"type":"Point"}
}