{
  "id": 2028336,
  "type": "Feature",
  "properties": {
    "tgn:hierarchy":[
        "tgn:2028336",
        "tgn:1000001",
        "tgn:7013649",
        "tgn:7012149",
        "tgn:7007251",
        "tgn:7029392"
    ],
    "tgn:id":2028336,
    "tgn:name":"Hines",
    "tgn:placetype":[
        "aat:300387016"
    ]
},
  "bbox": [],
  "geometry": {"coordinates":[-87.8333,41.85],"type":"Point"}
}