<<<<<<< HEAD
{
  "id": 7118851,
  "type": "Feature",
  "properties": {
    "tgn:hierarchy":[
        "tgn:7118851",
        "tgn:1000003",
        "tgn:7003676",
        "tgn:7000084",
        "tgn:7029392"
    ],
    "tgn:id":7118851,
    "tgn:name":"Polder",
    "tgn:placetype":[
        "aat:300000206"
    ]
},
  "bbox": [],
  "geometry": {"coordinates":[7.6,53.4],"type":"Point"}
}
=======
{"geometry":{"type":"Point","coordinates":[7.600000,53.400000]},"type":"Feature","properties":{"hierarchy":["tgn:7118851","tgn:1000003","tgn:7003676","tgn:7000084","tgn:7029392"],"placetype":["aat:300000206"],"id":7118851,"name:xx":"Polder"}}
>>>>>>> 03f74aca74312dbeaf24d7e61306dd6a786dc3d0
