<<<<<<< HEAD
{
  "id": 7480991,
  "type": "Feature",
  "properties": {
    "tgn:hierarchy":[
        "tgn:7480991",
        "tgn:1000004",
        "tgn:7492971",
        "tgn:1000141",
        "tgn:7029392"
    ],
    "tgn:id":7480991,
    "tgn:name":"Xintian",
    "tgn:placetype":[
        "aat:300008347"
    ]
},
  "bbox": [],
  "geometry": {"coordinates":[120.53668,22.662489],"type":"Point"}
}
=======
{"geometry":{"type":"Point","coordinates":[120.536680,22.662489]},"type":"Feature","properties":{"hierarchy":["tgn:7480991","tgn:1000004","tgn:7492971","tgn:1000141","tgn:7029392"],"placetype":["aat:300008347"],"id":7480991,"name:xx":"Xintian"}}
>>>>>>> 03f74aca74312dbeaf24d7e61306dd6a786dc3d0
