{
  "id": 7050827,
  "type": "Feature",
  "properties": {
    "tgn:hierarchy":[
        "tgn:7050827",
        "tgn:1003440",
        "tgn:1000003",
        "tgn:7003124",
        "tgn:1000080",
        "tgn:7029392"
    ],
    "tgn:id":7050827,
    "tgn:name":"Masobello",
    "tgn:placetype":[
        "aat:300008347"
    ]
},
  "bbox": [],
  "geometry": {"coordinates":[12.183333,46.75],"type":"Point"}
}