{
  "id": 7568141,
  "type": "Feature",
  "properties": {
    "tgn:hierarchy":[
        "tgn:7568141",
        "tgn:1000004",
        "tgn:7000198",
        "tgn:1001996",
        "tgn:7029392"
    ],
    "tgn:id":7568141,
    "tgn:name:en":"Ghar\u0101khru Protected Forest",
    "tgn:placetype":[
        "aat:300008863"
    ]
},
  "bbox": [],
  "geometry": {"coordinates":[76.985283,31.198573],"type":"Point"}
}