{
  "id": 7130237,
  "type": "Feature",
  "properties": {
    "tgn:hierarchy":[
        "tgn:7130237",
        "tgn:7003669",
        "tgn:1000003",
        "tgn:7000084",
        "tgn:7029392"
    ],
    "tgn:id":7130237,
    "tgn:name":"Meyfried",
    "tgn:placetype":[
        "aat:300008347"
    ]
},
  "bbox": [],
  "geometry": {"coordinates":[10.816667,48.666667],"type":"Point"}
}