{
  "id": 2692419,
  "type": "Feature",
  "properties": {
    "tgn:hierarchy":[
        "tgn:2692419",
        "tgn:1000001",
        "tgn:7012149",
        "tgn:1002789",
        "tgn:7007710",
        "tgn:7029392"
    ],
    "tgn:id":2692419,
    "tgn:name":"Steam Mill Run",
    "tgn:placetype":[
        "aat:300008699"
    ]
},
  "bbox": [],
  "geometry": {"coordinates":[-75.0667,41.4167],"type":"Point"}
}