{
  "id": 2124676,
  "type": "Feature",
  "properties": {
    "tgn:hierarchy":[
        "tgn:2124676",
        "tgn:1002933",
        "tgn:1000001",
        "tgn:7012149",
        "tgn:7007239",
        "tgn:7029392"
    ],
    "tgn:id":2124676,
    "tgn:name":"Abbotts Pond",
    "tgn:placetype":[
        "aat:300006191"
    ]
},
  "bbox": [],
  "geometry": {"coordinates":[-75.4667,38.8833],"type":"Point"}
}