<<<<<<< HEAD
{
  "id": 7117933,
  "type": "Feature",
  "properties": {
    "tgn:hierarchy":[
        "tgn:7117933",
        "tgn:1000003",
        "tgn:7003677",
        "tgn:7000084",
        "tgn:7029392"
    ],
    "tgn:id":7117933,
    "tgn:name":"Obersdorf",
    "tgn:placetype":[
        "aat:300008347"
    ]
},
  "bbox": [],
  "geometry": {"coordinates":[8.066667,50.833333],"type":"Point"}
}
=======
{"geometry":{"type":"Point","coordinates":[8.066667,50.833333]},"type":"Feature","properties":{"hierarchy":["tgn:7117933","tgn:1000003","tgn:7003677","tgn:7000084","tgn:7029392"],"placetype":["aat:300008347"],"id":7117933,"name:xx":"Obersdorf"}}
>>>>>>> 03f74aca74312dbeaf24d7e61306dd6a786dc3d0
