{
  "id": 7521611,
  "type": "Feature",
  "properties": {
    "tgn:hierarchy":[
        "tgn:7521611",
        "tgn:7001242",
        "tgn:7016833",
        "tgn:1001123",
        "tgn:7029392"
    ],
    "tgn:id":7521611,
    "tgn:name":"Ab\u016b Janb, B\u016bgh\u0101z",
    "tgn:placetype":[
        "aat:300008713"
    ]
},
  "bbox": [],
  "geometry": {"coordinates":[32.213333,31.203333],"type":"Point"}
}