{
  "id": 7256757,
  "type": "Feature",
  "properties": {
    "tgn:hierarchy":[
        "tgn:7256757",
        "tgn:7593113",
        "tgn:7016620",
        "tgn:7593112",
        "tgn:1000001",
        "tgn:7029392"
    ],
    "tgn:id":7256757,
    "tgn:name:nl":"Blauwe Pan",
    "tgn:placetype":[
        "aat:300386871"
    ]
},
  "bbox": [],
  "geometry": {"coordinates":[-68.283333,12.083333],"type":"Point"}
}