{
  "id": 7520796,
  "type": "Feature",
  "properties": {
    "tgn:hierarchy":[
        "tgn:7520796",
        "tgn:7001242",
        "tgn:1001059",
        "tgn:7016833",
        "tgn:7029392"
    ],
    "tgn:id":7520796,
    "tgn:name:en":"Al Khash\u0101shinah",
    "tgn:placetype":[
        "aat:300008347"
    ]
},
  "bbox": [],
  "geometry": {"coordinates":[31.566667,31.066667],"type":"Point"}
}