{
  "id": 2238209,
  "type": "Feature",
  "properties": {
    "tgn:hierarchy":[
        "tgn:2238209",
        "tgn:1000001",
        "tgn:7006451",
        "tgn:7012149",
        "tgn:2000100",
        "tgn:7029392"
    ],
    "tgn:id":2238209,
    "tgn:name":"Chiweton Hill",
    "tgn:placetype":[
        "aat:300008798"
    ]
},
  "bbox": [],
  "geometry": {"coordinates":[-112.1833,31.8667],"type":"Point"}
}