{
  "id": 7399109,
  "type": "Feature",
  "properties": {
    "tgn:hierarchy":[
        "tgn:7399109",
        "tgn:1000001",
        "tgn:1001893",
        "tgn:7005560",
        "tgn:7029392"
    ],
    "tgn:id":7399109,
    "tgn:name":"Los Padres",
    "tgn:placetype":[
        "aat:300008347"
    ]
},
  "bbox": [],
  "geometry": {"coordinates":[-99.944722,19.453056],"type":"Point"}
}