<<<<<<< HEAD
{
  "id": 7028089,
  "type": "Feature",
  "properties": {
    "tgn:hierarchy":[
        "tgn:7028089",
        "tgn:7002445",
        "tgn:1000003",
        "tgn:7008157",
        "tgn:7008591",
        "tgn:7029392"
    ],
    "tgn:id":7028089,
    "tgn:name":"Snarford",
    "tgn:placetype":[
        "aat:300008347",
        "aat:300008372"
    ]
},
  "bbox": [],
  "geometry": {"coordinates":[-0.4167,53.3333],"type":"Point"}
}
=======
{"geometry":{"type":"Point","coordinates":[-0.416700,53.333300]},"type":"Feature","properties":{"hierarchy":["tgn:7028089","tgn:7002445","tgn:1000003","tgn:7008157","tgn:7008591","tgn:7029392"],"placetype":["aat:300008347","aat:300008372"],"id":7028089,"name:xx":"Snarford"}}
>>>>>>> 03f74aca74312dbeaf24d7e61306dd6a786dc3d0
