{
  "id": 7532682,
  "type": "Feature",
  "properties": {
    "tgn:hierarchy":[
        "tgn:7532682",
        "tgn:7001242",
        "tgn:7016833",
        "tgn:1001123",
        "tgn:7029392"
    ],
    "tgn:id":7532682,
    "tgn:name":"Al \u1e28usayniyyah",
    "tgn:placetype":[
        "aat:300008347"
    ]
},
  "bbox": [],
  "geometry": {"coordinates":[32.154107,31.140344],"type":"Point"}
}