{
  "id": 7340983,
  "type": "Feature",
  "properties": {
    "tgn:hierarchy":[
        "tgn:7340983",
        "tgn:7002826",
        "tgn:7001158",
        "tgn:1000003",
        "tgn:1000095",
        "tgn:7029392"
    ],
    "tgn:id":7340983,
    "tgn:name":"Burbia, R\u00edo",
    "tgn:placetype":[
        "aat:300008699"
    ]
},
  "bbox": [],
  "geometry": {"coordinates":[-6.766667,42.533333],"type":"Point"}
}