{
  "id": 7232221,
  "type": "Feature",
  "properties": {
    "tgn:hierarchy":[
        "tgn:7232221",
        "tgn:7011330",
        "tgn:7002674",
        "tgn:1000003",
        "tgn:1000074",
        "tgn:7029392"
    ],
    "tgn:id":7232221,
    "tgn:name":"Makr\u00edyialos, \u00d3rmos",
    "tgn:placetype":[
        "aat:300132316"
    ]
},
  "bbox": [],
  "geometry": {"coordinates":[27.166667,35.433333],"type":"Point"}
}