{
  "id": 2427430,
  "type": "Feature",
  "properties": {
    "tgn:hierarchy":[
        "tgn:2427430",
        "tgn:1000001",
        "tgn:7012149",
        "tgn:2002118",
        "tgn:7007827",
        "tgn:7029392"
    ],
    "tgn:id":2427430,
    "tgn:name":"Jordan Point",
    "tgn:placetype":[
        "aat:300008347"
    ]
},
  "bbox": [],
  "geometry": {"coordinates":[-111.8333,40.5333],"type":"Point"}
}