{
  "id": 7588527,
  "type": "Feature",
  "properties": {
    "tgn:hierarchy":[
        "tgn:7588527",
        "tgn:1000004",
        "tgn:7000198",
        "tgn:1001894",
        "tgn:7029392"
    ],
    "tgn:id":7588527,
    "tgn:name:en":"Sunw\u0101ni Kalan",
    "tgn:placetype":[
        "aat:300008347"
    ]
},
  "bbox": [],
  "geometry": {"coordinates":[79.893769,24.35799],"type":"Point"}
}