{
  "id": 2497828,
  "type": "Feature",
  "properties": {
    "tgn:hierarchy":[
        "tgn:2497828",
        "tgn:1000001",
        "tgn:2000470",
        "tgn:7012149",
        "tgn:7007250",
        "tgn:7029392"
    ],
    "tgn:id":2497828,
    "tgn:name":"Mayfield Creek",
    "tgn:placetype":[
        "aat:300008706"
    ]
},
  "bbox": [],
  "geometry": {"coordinates":[-114.7833,44.5333],"type":"Point"}
}