{
  "id": 1092234,
  "type": "Feature",
  "properties": {
    "tgn:hierarchy":[
        "tgn:1092234",
        "tgn:7001242",
        "tgn:1001919",
        "tgn:1000182",
        "tgn:7029392"
    ],
    "tgn:id":1092234,
    "tgn:name":"Ore",
    "tgn:placetype":[
        "aat:300008347"
    ]
},
  "bbox": [],
  "geometry": {"coordinates":[4.8667,6.75],"type":"Point"}
}