{
  "id": 2378768,
  "type": "Feature",
  "properties": {
    "tgn:hierarchy":[
        "tgn:2378768",
        "tgn:1000001",
        "tgn:7016172",
        "tgn:7012149",
        "tgn:2000177",
        "tgn:7029392"
    ],
    "tgn:id":2378768,
    "tgn:name":"Harston Branch",
    "tgn:placetype":[
        "aat:300008699"
    ]
},
  "bbox": [],
  "geometry": {"coordinates":[-92.0167,35.1167],"type":"Point"}
}