{
  "id": 2217981,
  "type": "Feature",
  "properties": {
    "tgn:hierarchy":[
        "tgn:2217981",
        "tgn:1000001",
        "tgn:7012149",
        "tgn:1002485",
        "tgn:7007826",
        "tgn:7029392"
    ],
    "tgn:id":2217981,
    "tgn:name":"Camps Lake",
    "tgn:placetype":[
        "aat:300006191"
    ]
},
  "bbox": [],
  "geometry": {"coordinates":[-95.6333,33.0833],"type":"Point"}
}