{
  "id": 2241654,
  "type": "Feature",
  "properties": {
    "tgn:hierarchy":[
        "tgn:2241654",
        "tgn:1000001",
        "tgn:7012149",
        "tgn:2000933",
        "tgn:7007515",
        "tgn:7029392"
    ],
    "tgn:id":2241654,
    "tgn:name":"Clarks Island",
    "tgn:placetype":[
        "aat:300008791"
    ]
},
  "bbox": [],
  "geometry": {"coordinates":[-70.7167,43.0667],"type":"Point"}
}