{
  "id": 2355608,
  "type": "Feature",
  "properties": {
    "tgn:hierarchy":[
        "tgn:2355608",
        "tgn:1000001",
        "tgn:7012149",
        "tgn:2002349",
        "tgn:7007922",
        "tgn:7029392"
    ],
    "tgn:id":2355608,
    "tgn:name":"Goose Creek",
    "tgn:placetype":[
        "aat:300008706"
    ]
},
  "bbox": [],
  "geometry": {"coordinates":[-90.5833,43.5167],"type":"Point"}
}