{
  "id": 2525721,
  "type": "Feature",
  "properties": {
    "tgn:hierarchy":[
        "tgn:2525721",
        "tgn:1000001",
        "tgn:7012149",
        "tgn:2000183",
        "tgn:7007157",
        "tgn:7029392"
    ],
    "tgn:id":2525721,
    "tgn:name":"Moscow Spring",
    "tgn:placetype":[
        "aat:300008697"
    ]
},
  "bbox": [],
  "geometry": {"coordinates":[-117.4667,35.8667],"type":"Point"}
}