{
  "id": 1079609,
  "type": "Feature",
  "properties": {
    "tgn:hierarchy":[
        "tgn:1079609",
        "tgn:1000004",
        "tgn:1000939",
        "tgn:1000119",
        "tgn:7029392"
    ],
    "tgn:id":1079609,
    "tgn:name":"Ramat HaSharon",
    "tgn:placetype":[
        "aat:300008347"
    ]
},
  "bbox": [],
  "geometry": {"coordinates":[34.85,32.1333],"type":"Point"}
}