<<<<<<< HEAD
{
  "id": 7471286,
  "type": "Feature",
  "properties": {
    "tgn:hierarchy":[
        "tgn:7471286",
        "tgn:7001010",
        "tgn:1000004",
        "tgn:1000141",
        "tgn:7029392"
    ],
    "tgn:id":7471286,
    "tgn:name":"Zhuole",
    "tgn:placetype":[
        "aat:300008347"
    ]
},
  "bbox": [],
  "geometry": {"coordinates":[121.27092,23.276365],"type":"Point"}
}
=======
{"geometry":{"type":"Point","coordinates":[121.270920,23.276365]},"type":"Feature","properties":{"hierarchy":["tgn:7471286","tgn:7001010","tgn:1000004","tgn:1000141","tgn:7029392"],"placetype":["aat:300008347"],"id":7471286,"name:xx":"Zhuole"}}
>>>>>>> 03f74aca74312dbeaf24d7e61306dd6a786dc3d0
