{
  "id": 7471286,
  "type": "Feature",
  "properties": {
    "tgn:hierarchy":[
        "tgn:7471286",
        "tgn:7001010",
        "tgn:1000004",
        "tgn:1000141",
        "tgn:7029392"
    ],
    "tgn:id":7471286,
    "tgn:name":"Zhuole",
    "tgn:placetype":[
        "aat:300008347"
    ]
},
  "bbox": [],
  "geometry": {"coordinates":[121.27092,23.276365],"type":"Point"}
}