{
  "id": 7449484,
  "type": "Feature",
  "properties": {
    "tgn:hierarchy":[
        "tgn:7449484",
        "tgn:7002445",
        "tgn:1000003",
        "tgn:7012077",
        "tgn:7008591",
        "tgn:7029392"
    ],
    "tgn:id":7449484,
    "tgn:name:en":"Eggesford",
    "tgn:placetype":[
        "aat:300008347"
    ]
},
  "bbox": [],
  "geometry": {"coordinates":[-3.866667,50.883333],"type":"Point"}
}