{
  "id": 7026255,
  "type": "Feature",
  "properties": {
    "tgn:hierarchy":[
        "tgn:7026255",
        "tgn:7002445",
        "tgn:1000003",
        "tgn:7008131",
        "tgn:7008591",
        "tgn:7029392"
    ],
    "tgn:id":7026255,
    "tgn:name":"Little Leighs",
    "tgn:placetype":[
        "aat:300008347",
        "aat:300008369"
    ]
},
  "bbox": [],
  "geometry": {"coordinates":[0.4833,51.8167],"type":"Point"}
}