{
  "id": 2388893,
  "type": "Feature",
  "properties": {
    "tgn:hierarchy":[
        "tgn:2388893",
        "tgn:1000001",
        "tgn:7012149",
        "tgn:2001291",
        "tgn:7007524",
        "tgn:7029392"
    ],
    "tgn:id":2388893,
    "tgn:name":"Hidden Lake",
    "tgn:placetype":[
        "aat:300008680"
    ]
},
  "bbox": [],
  "geometry": {"coordinates":[-113.5667,47.1333],"type":"Point"}
}