{
  "id": 2066656,
  "type": "Feature",
  "properties": {
    "tgn:hierarchy":[
        "tgn:2066656",
        "tgn:1000001",
        "tgn:7012149",
        "tgn:7019676",
        "tgn:7007566",
        "tgn:7029392"
    ],
    "tgn:id":2066656,
    "tgn:name":"Allison",
    "tgn:placetype":[
        "aat:300008347"
    ]
},
  "bbox": [],
  "geometry": {"coordinates":[-108.7833,35.5167],"type":"Point"}
}