{
  "id": 2508269,
  "type": "Feature",
  "properties": {
    "tgn:hierarchy":[
        "tgn:2508269",
        "tgn:1000001",
        "tgn:2000920",
        "tgn:7012149",
        "tgn:7007515",
        "tgn:7029392"
    ],
    "tgn:id":2508269,
    "tgn:name":"Middle Brook Bog",
    "tgn:placetype":[
        "aat:300008905"
    ]
},
  "bbox": [],
  "geometry": {"coordinates":[-70.5333,44.05],"type":"Point"}
}