{
  "id": 7445572,
  "type": "Feature",
  "properties": {
    "tgn:hierarchy":[
        "tgn:7445572",
        "tgn:5000432",
        "tgn:7002444",
        "tgn:1000003",
        "tgn:7008591",
        "tgn:7029392"
    ],
    "tgn:id":7445572,
    "tgn:name:en":"Roan Heads",
    "tgn:placetype":[
        "aat:300011692"
    ]
},
  "bbox": [],
  "geometry": {"coordinates":[-1.766667,57.516667],"type":"Point"}
}