{
  "id": 7303779,
  "type": "Feature",
  "properties": {
    "tgn:hierarchy":[
        "tgn:7303779",
        "tgn:7007088",
        "tgn:1000003",
        "tgn:7009604",
        "tgn:1000095",
        "tgn:7029392"
    ],
    "tgn:id":7303779,
    "tgn:name":"Osma",
    "tgn:placetype":[
        "aat:300008347"
    ]
},
  "bbox": [],
  "geometry": {"coordinates":[-3.064009,42.890775],"type":"Point"}
}