<<<<<<< HEAD
{
  "id": 2764015,
  "type": "Feature",
  "properties": {
    "tgn:hierarchy":[
        "tgn:2764015",
        "tgn:1000001",
        "tgn:7012149",
        "tgn:2001713",
        "tgn:7007708",
        "tgn:7029392"
    ],
    "tgn:id":2764015,
    "tgn:name":"Wheeler City",
    "tgn:placetype":[
        "aat:300008347"
    ]
},
  "bbox": [],
  "geometry": {"coordinates":[-123.7167,42.2833],"type":"Point"}
}
=======
{"geometry":{"type":"Point","coordinates":[-123.716700,42.283300]},"type":"Feature","properties":{"hierarchy":["tgn:2764015","tgn:1000001","tgn:7012149","tgn:2001713","tgn:7007708","tgn:7029392"],"placetype":["aat:300008347"],"id":2764015,"name:xx":"Wheeler City"}}
>>>>>>> 03f74aca74312dbeaf24d7e61306dd6a786dc3d0
