{
  "id": 1093963,
  "type": "Feature",
  "properties": {
    "tgn:hierarchy":[
        "tgn:1093963",
        "tgn:7001242",
        "tgn:7030582",
        "tgn:1000198",
        "tgn:7029392"
    ],
    "tgn:id":1093963,
    "tgn:name":"Lupala",
    "tgn:placetype":[
        "aat:300055621",
        "aat:300008347"
    ]
},
  "bbox": [],
  "geometry": {"coordinates":[19.0833,-17.8333],"type":"Point"}
}