{
  "id": 2645119,
  "type": "Feature",
  "properties": {
    "tgn:hierarchy":[
        "tgn:2645119",
        "tgn:1000001",
        "tgn:7012149",
        "tgn:2001931",
        "tgn:7007825",
        "tgn:7029392"
    ],
    "tgn:id":2645119,
    "tgn:name":"Saulsbury",
    "tgn:placetype":[
        "aat:300008347"
    ]
},
  "bbox": [],
  "geometry": {"coordinates":[-86.1167,36.1667],"type":"Point"}
}