{
  "id": 2636562,
  "type": "Feature",
  "properties": {
    "tgn:hierarchy":[
        "tgn:2636562",
        "tgn:1000001",
        "tgn:7012149",
        "tgn:7007826",
        "tgn:7029392"
    ],
    "tgn:id":2636562,
    "tgn:name":"Sage Draw",
    "tgn:placetype":[
        "aat:300008761"
    ]
},
  "bbox": [],
  "geometry": {"coordinates":[-100.7333,33.4833],"type":"Point"}
}