{
  "id": 2428421,
  "type": "Feature",
  "properties": {
    "tgn:hierarchy":[
        "tgn:2428421",
        "tgn:1000001",
        "tgn:7012149",
        "tgn:2000785",
        "tgn:7007255",
        "tgn:7029392"
    ],
    "tgn:id":2428421,
    "tgn:name":"Judio Creek",
    "tgn:placetype":[
        "aat:300008706"
    ]
},
  "bbox": [],
  "geometry": {"coordinates":[-85.4333,36.6667],"type":"Point"}
}