{
  "id": 2518346,
  "type": "Feature",
  "properties": {
    "tgn:hierarchy":[
        "tgn:2518346",
        "tgn:1000001",
        "tgn:7006451",
        "tgn:2000093",
        "tgn:7012149",
        "tgn:7029392"
    ],
    "tgn:id":2518346,
    "tgn:name":"Mistake Peak",
    "tgn:placetype":[
        "aat:300008798"
    ]
},
  "bbox": [],
  "geometry": {"coordinates":[-111.15,33.9167],"type":"Point"}
}