{
  "id": 2768018,
  "type": "Feature",
  "properties": {
    "tgn:hierarchy":[
        "tgn:2768018",
        "tgn:1000001",
        "tgn:7012149",
        "tgn:2001846",
        "tgn:7007825",
        "tgn:7029392"
    ],
    "tgn:id":2768018,
    "tgn:name":"Whiteoak Ridge",
    "tgn:placetype":[
        "aat:300266640"
    ]
},
  "bbox": [],
  "geometry": {"coordinates":[-82.0167,36.2333],"type":"Point"}
}