<<<<<<< HEAD
{
  "id": 2768018,
  "type": "Feature",
  "properties": {
    "tgn:hierarchy":[
        "tgn:2768018",
        "tgn:1000001",
        "tgn:7012149",
        "tgn:2001846",
        "tgn:7007825",
        "tgn:7029392"
    ],
    "tgn:id":2768018,
    "tgn:name":"Whiteoak Ridge",
    "tgn:placetype":[
        "aat:300266640"
    ]
},
  "bbox": [],
  "geometry": {"coordinates":[-82.0167,36.2333],"type":"Point"}
}
=======
{"geometry":{"type":"Point","coordinates":[-82.016700,36.233300]},"type":"Feature","properties":{"hierarchy":["tgn:2768018","tgn:1000001","tgn:7012149","tgn:2001846","tgn:7007825","tgn:7029392"],"placetype":["aat:300266640"],"id":2768018,"name:xx":"Whiteoak Ridge"}}
>>>>>>> 03f74aca74312dbeaf24d7e61306dd6a786dc3d0
