{
  "id": 1066007,
  "type": "Feature",
  "properties": {
    "tgn:hierarchy":[
        "tgn:1066007",
        "tgn:7002185",
        "tgn:1000004",
        "tgn:1000108",
        "tgn:7029392"
    ],
    "tgn:id":1066007,
    "tgn:name":"Chakwad\u0101m",
    "tgn:placetype":[
        "aat:300008347"
    ]
},
  "bbox": [],
  "geometry": {"coordinates":[98.5167,27.4833],"type":"Point"}
}