<<<<<<< HEAD
{
  "id": 7170213,
  "type": "Feature",
  "properties": {
    "tgn:hierarchy":[
        "tgn:7170213",
        "tgn:1000003",
        "tgn:7003678",
        "tgn:7000084",
        "tgn:7029392"
    ],
    "tgn:id":7170213,
    "tgn:name":"Hinter-Berg",
    "tgn:placetype":[
        "aat:300008777"
    ]
},
  "bbox": [],
  "geometry": {"coordinates":[9.233333,51.183333],"type":"Point"}
}
=======
{"geometry":{"type":"Point","coordinates":[9.233333,51.183333]},"type":"Feature","properties":{"hierarchy":["tgn:7170213","tgn:1000003","tgn:7003678","tgn:7000084","tgn:7029392"],"placetype":["aat:300008777"],"id":7170213,"name:xx":"Hinter-Berg"}}
>>>>>>> 03f74aca74312dbeaf24d7e61306dd6a786dc3d0
