{
  "id": 7264368,
  "type": "Feature",
  "properties": {
    "tgn:hierarchy":[
        "tgn:7264368",
        "tgn:1000003",
        "tgn:7003635",
        "tgn:7016845",
        "tgn:7029392"
    ],
    "tgn:id":7264368,
    "tgn:name:nl":"Kraagbrug",
    "tgn:placetype":[
        "aat:300007836"
    ]
},
  "bbox": [],
  "geometry": {"coordinates":[3.866667,51.316667],"type":"Point"}
}