<<<<<<< HEAD
{
  "id": 7113758,
  "type": "Feature",
  "properties": {
    "tgn:hierarchy":[
        "tgn:7113758",
        "tgn:7003669",
        "tgn:1000003",
        "tgn:7000084",
        "tgn:7029392"
    ],
    "tgn:id":7113758,
    "tgn:name":"Rettenbach",
    "tgn:placetype":[
        "aat:300008347"
    ]
},
  "bbox": [],
  "geometry": {"coordinates":[11.25,48.533333],"type":"Point"}
}
=======
{"geometry":{"type":"Point","coordinates":[11.250000,48.533333]},"type":"Feature","properties":{"hierarchy":["tgn:7113758","tgn:7003669","tgn:1000003","tgn:7000084","tgn:7029392"],"placetype":["aat:300008347"],"id":7113758,"name:xx":"Rettenbach"}}
>>>>>>> 03f74aca74312dbeaf24d7e61306dd6a786dc3d0
