{
  "id": 2627832,
  "type": "Feature",
  "properties": {
    "tgn:hierarchy":[
        "tgn:2627832",
        "tgn:1000001",
        "tgn:7012149",
        "tgn:1003007",
        "tgn:7007706",
        "tgn:7029392"
    ],
    "tgn:id":2627832,
    "tgn:name":"Rogue Hollow",
    "tgn:placetype":[
        "aat:300008761"
    ]
},
  "bbox": [],
  "geometry": {"coordinates":[-81.6667,40.95],"type":"Point"}
}