{
  "id": 7258402,
  "type": "Feature",
  "properties": {
    "tgn:hierarchy":[
        "tgn:7258402",
        "tgn:1000003",
        "tgn:7006951",
        "tgn:7016845",
        "tgn:7029392"
    ],
    "tgn:id":7258402,
    "tgn:name:nl":"Bos en Lommer",
    "tgn:placetype":[
        "aat:300000745"
    ]
},
  "bbox": [],
  "geometry": {"coordinates":[4.85,52.383333],"type":"Point"}
}