{
  "id": 7408263,
  "type": "Feature",
  "properties": {
    "tgn:hierarchy":[
        "tgn:7408263",
        "tgn:7005580",
        "tgn:1000001",
        "tgn:7005560",
        "tgn:7029392"
    ],
    "tgn:id":7408263,
    "tgn:name":"La Victoria",
    "tgn:placetype":[
        "aat:300008347"
    ]
},
  "bbox": [],
  "geometry": {"coordinates":[-91.638889,16.802778],"type":"Point"}
}