{
  "id": 1124576,
  "type": "Feature",
  "properties": {
    "tgn:hierarchy":[
        "tgn:1124576",
        "tgn:1000003",
        "tgn:7003689",
        "tgn:7000084",
        "tgn:7029392"
    ],
    "tgn:id":1124576,
    "tgn:name":"Hasel",
    "tgn:placetype":[
        "aat:300008707",
        "aat:300008699"
    ]
},
  "bbox": [],
  "geometry": {"coordinates":[9.916667,51.05],"type":"Point"}
}