{
  "id": 7297634,
  "type": "Feature",
  "properties": {
    "tgn:hierarchy":[
        "tgn:7297634",
        "tgn:7008911",
        "tgn:1000003",
        "tgn:7002763",
        "tgn:1000095",
        "tgn:7029392"
    ],
    "tgn:id":7297634,
    "tgn:name":"Soto de los Infantes",
    "tgn:placetype":[
        "aat:300008347"
    ]
},
  "bbox": [],
  "geometry": {"coordinates":[-6.266667,43.366667],"type":"Point"}
}