{
  "id": 1018036,
  "type": "Feature",
  "properties": {
    "tgn:hierarchy":[
        "tgn:1018036",
        "tgn:7005581",
        "tgn:1000001",
        "tgn:7005560",
        "tgn:7029392"
    ],
    "tgn:id":1018036,
    "tgn:name":"Pilares",
    "tgn:placetype":[
        "aat:300008347"
    ]
},
  "bbox": [],
  "geometry": {"coordinates":[-104.866667,30.416667],"type":"Point"}
}