<<<<<<< HEAD
{
  "id": 7363270,
  "type": "Feature",
  "properties": {
    "tgn:hierarchy":[
        "tgn:7363270",
        "tgn:1000001",
        "tgn:7005601",
        "tgn:7005560",
        "tgn:7029392"
    ],
    "tgn:id":7363270,
    "tgn:name":"El Fraile",
    "tgn:placetype":[
        "aat:300008347"
    ]
},
  "bbox": [],
  "geometry": {"coordinates":[-102.366667,23.25],"type":"Point"}
}
=======
{"geometry":{"type":"Point","coordinates":[-102.366667,23.250000]},"type":"Feature","properties":{"hierarchy":["tgn:7363270","tgn:1000001","tgn:7005601","tgn:7005560","tgn:7029392"],"placetype":["aat:300008347"],"id":7363270,"name:xx":"El Fraile"}}
>>>>>>> 03f74aca74312dbeaf24d7e61306dd6a786dc3d0
