{
  "id": 2336762,
  "type": "Feature",
  "properties": {
    "tgn:hierarchy":[
        "tgn:2336762",
        "tgn:7002659",
        "tgn:1000001",
        "tgn:7012149",
        "tgn:2000041",
        "tgn:7029392"
    ],
    "tgn:id":2336762,
    "tgn:name":"Fourmile Branch",
    "tgn:placetype":[
        "aat:300008699"
    ]
},
  "bbox": [],
  "geometry": {"coordinates":[-86.9833,34.85],"type":"Point"}
}