{
  "id": 1075904,
  "type": "Feature",
  "properties": {
    "tgn:hierarchy":[
        "tgn:1075904",
        "tgn:1000004",
        "tgn:7000198",
        "tgn:7001797",
        "tgn:7029392"
    ],
    "tgn:id":1075904,
    "tgn:name:en":"Kolachel",
    "tgn:placetype":[
        "aat:300008347"
    ]
},
  "bbox": [],
  "geometry": {"coordinates":[77.25,8.166667],"type":"Point"}
}