{
  "id": 1093859,
  "type": "Feature",
  "properties": {
    "tgn:hierarchy":[
        "tgn:1093859",
        "tgn:7001242",
        "tgn:7017583",
        "tgn:1000193",
        "tgn:7029392"
    ],
    "tgn:id":1093859,
    "tgn:name":"Bell",
    "tgn:placetype":[
        "aat:300008347"
    ]
},
  "bbox": [],
  "geometry": {"coordinates":[27.3333,-33.25],"type":"Point"}
}