{
  "id": 2097374,
  "type": "Feature",
  "properties": {
    "tgn:hierarchy":[
        "tgn:2097374",
        "tgn:1000001",
        "tgn:2001793",
        "tgn:7012149",
        "tgn:7007713",
        "tgn:7029392"
    ],
    "tgn:id":2097374,
    "tgn:name":"Minnekahta",
    "tgn:placetype":[
        "aat:300387016"
    ]
},
  "bbox": [],
  "geometry": {"coordinates":[-103.6833,43.4167],"type":"Point"}
}