{
  "id": 2442381,
  "type": "Feature",
  "properties": {
    "tgn:hierarchy":[
        "tgn:2442381",
        "tgn:1002146",
        "tgn:1000001",
        "tgn:7012149",
        "tgn:7007157",
        "tgn:7029392"
    ],
    "tgn:id":2442381,
    "tgn:name":"Kreth Ditch",
    "tgn:placetype":[
        "aat:300006075"
    ]
},
  "bbox": [],
  "geometry": {"coordinates":[-120.8667,38.2667],"type":"Point"}
}