{
  "id": 2085446,
  "type": "Feature",
  "properties": {
    "tgn:hierarchy":[
        "tgn:2085446",
        "tgn:1000001",
        "tgn:7012149",
        "tgn:1002636",
        "tgn:7007708",
        "tgn:7029392"
    ],
    "tgn:id":2085446,
    "tgn:name":"Rockie Four Corners",
    "tgn:placetype":[
        "aat:300008347",
        "aat:300387210"
    ]
},
  "bbox": [],
  "geometry": {"coordinates":[-122.7167,45.0333],"type":"Point"}
}