{
  "id": 2278694,
  "type": "Feature",
  "properties": {
    "tgn:hierarchy":[
        "tgn:2278694",
        "tgn:1000001",
        "tgn:7012149",
        "tgn:7007158",
        "tgn:2000248",
        "tgn:7029392"
    ],
    "tgn:id":2278694,
    "tgn:name":"Dead Horse Creek",
    "tgn:placetype":[
        "aat:300008706"
    ]
},
  "bbox": [],
  "geometry": {"coordinates":[-108.5167,37.9667],"type":"Point"}
}