{
  "id": 1058770,
  "type": "Feature",
  "properties": {
    "tgn:hierarchy":[
        "tgn:1058770",
        "tgn:7006635",
        "tgn:1000003",
        "tgn:7006540",
        "tgn:7029392"
    ],
    "tgn:id":1058770,
    "tgn:name:en":"Puurmani",
    "tgn:placetype":[
        "aat:300008347"
    ]
},
  "bbox": [],
  "geometry": {"coordinates":[26.271,58.578],"type":"Point"}
}