{
  "id": 7224130,
  "type": "Feature",
  "properties": {
    "tgn:hierarchy":[
        "tgn:7224130",
        "tgn:7011270",
        "tgn:7002674",
        "tgn:1000003",
        "tgn:1000074",
        "tgn:7029392"
    ],
    "tgn:id":7224130,
    "tgn:name":"Pirg\u00e1ri, \u00c1kra",
    "tgn:placetype":[
        "aat:300008850"
    ]
},
  "bbox": [],
  "geometry": {"coordinates":[25.383333,36.65],"type":"Point"}
}