{
  "id": 2753546,
  "type": "Feature",
  "properties": {
    "tgn:hierarchy":[
        "tgn:2753546",
        "tgn:1000001",
        "tgn:7012149",
        "tgn:2002055",
        "tgn:7007826",
        "tgn:7029392"
    ],
    "tgn:id":2753546,
    "tgn:name":"Watermelon Water Tank",
    "tgn:placetype":[
        "aat:300006191"
    ]
},
  "bbox": [],
  "geometry": {"coordinates":[-102.75,30.4667],"type":"Point"}
}