{
  "id": 7418840,
  "type": "Feature",
  "properties": {
    "tgn:hierarchy":[
        "tgn:7418840",
        "tgn:1001835",
        "tgn:1000001",
        "tgn:7005560",
        "tgn:7029392"
    ],
    "tgn:id":7418840,
    "tgn:name":"La Ara\u00f1a, Cerro",
    "tgn:placetype":[
        "aat:300008777"
    ]
},
  "bbox": [],
  "geometry": {"coordinates":[-116.095278,32.126389],"type":"Point"}
}