{
  "id": 2724230,
  "type": "Feature",
  "properties": {
    "tgn:hierarchy":[
        "tgn:2724230",
        "tgn:1000001",
        "tgn:7012149",
        "tgn:2000494",
        "tgn:7007250",
        "tgn:7029392"
    ],
    "tgn:id":2724230,
    "tgn:name":"Tom Creek",
    "tgn:placetype":[
        "aat:300008706"
    ]
},
  "bbox": [],
  "geometry": {"coordinates":[-114.8333,44.8167],"type":"Point"}
}