{
  "id": 2403173,
  "type": "Feature",
  "properties": {
    "tgn:hierarchy":[
        "tgn:2403173",
        "tgn:1000001",
        "tgn:7012149",
        "tgn:2001990",
        "tgn:7007826",
        "tgn:7029392"
    ],
    "tgn:id":2403173,
    "tgn:name":"House Hollow",
    "tgn:placetype":[
        "aat:300008761"
    ]
},
  "bbox": [],
  "geometry": {"coordinates":[-99.25,30.45],"type":"Point"}
}