{
  "id": 2593987,
  "type": "Feature",
  "properties": {
    "tgn:hierarchy":[
        "tgn:2593987",
        "tgn:1000001",
        "tgn:7012149",
        "tgn:7014510",
        "tgn:7007920",
        "tgn:7029392"
    ],
    "tgn:id":2593987,
    "tgn:name":"Portage",
    "tgn:placetype":[
        "aat:300008347"
    ]
},
  "bbox": [],
  "geometry": {"coordinates":[-121.3833,48.5833],"type":"Point"}
}