{
  "id": 2586777,
  "type": "Feature",
  "properties": {
    "tgn:hierarchy":[
        "tgn:2586777",
        "tgn:1000001",
        "tgn:7012149",
        "tgn:7007157",
        "tgn:1002894",
        "tgn:7029392"
    ],
    "tgn:id":2586777,
    "tgn:name":"Placer Mine",
    "tgn:placetype":[
        "aat:300000390"
    ]
},
  "bbox": [],
  "geometry": {"coordinates":[-120.5833,39.6167],"type":"Point"}
}