{
  "id": 2207862,
  "type": "Feature",
  "properties": {
    "tgn:hierarchy":[
        "tgn:2207862",
        "tgn:1000001",
        "tgn:7012149",
        "tgn:7007825",
        "tgn:7029392"
    ],
    "tgn:id":2207862,
    "tgn:name":"Burgess Hollow",
    "tgn:placetype":[
        "aat:300008761"
    ]
},
  "bbox": [],
  "geometry": {"coordinates":[-86.8333,35.2833],"type":"Point"}
}