{
  "id": 7590764,
  "type": "Feature",
  "properties": {
    "tgn:hierarchy":[
        "tgn:7590764",
        "tgn:1000004",
        "tgn:7000198",
        "tgn:7000799",
        "tgn:7029392"
    ],
    "tgn:id":7590764,
    "tgn:name:en":"Gop\u012bw\u0101la N\u0101la",
    "tgn:placetype":[
        "aat:300266554",
        "aat:300008699"
    ]
},
  "bbox": [],
  "geometry": {"coordinates":[74.594444,32.888889],"type":"Point"}
}