<<<<<<< HEAD
{
  "id": 7118671,
  "type": "Feature",
  "properties": {
    "tgn:hierarchy":[
        "tgn:7118671",
        "tgn:1000003",
        "tgn:7003687",
        "tgn:7000084",
        "tgn:7029392"
    ],
    "tgn:id":7118671,
    "tgn:name":"Pietzen-Graben",
    "tgn:placetype":[
        "aat:300008699"
    ]
},
  "bbox": [],
  "geometry": {"coordinates":[11.866667,52.5],"type":"Point"}
}
=======
{"geometry":{"type":"Point","coordinates":[11.866667,52.500000]},"type":"Feature","properties":{"hierarchy":["tgn:7118671","tgn:1000003","tgn:7003687","tgn:7000084","tgn:7029392"],"placetype":["aat:300008699"],"id":7118671,"name:xx":"Pietzen-Graben"}}
>>>>>>> 03f74aca74312dbeaf24d7e61306dd6a786dc3d0
