{
  "id": 2377725,
  "type": "Feature",
  "properties": {
    "tgn:hierarchy":[
        "tgn:2377725",
        "tgn:1000001",
        "tgn:7016172",
        "tgn:2000111",
        "tgn:7012149",
        "tgn:7029392"
    ],
    "tgn:id":2377725,
    "tgn:name":"Harrell Lake",
    "tgn:placetype":[
        "aat:300006191"
    ]
},
  "bbox": [],
  "geometry": {"coordinates":[-92.3333,33.5167],"type":"Point"}
}