{
  "id": 2428919,
  "type": "Feature",
  "properties": {
    "tgn:hierarchy":[
        "tgn:2428919",
        "tgn:1000001",
        "tgn:7012149",
        "tgn:1002929",
        "tgn:7007240",
        "tgn:7029392"
    ],
    "tgn:id":2428919,
    "tgn:name":"Jumper Creek Canal",
    "tgn:placetype":[
        "aat:300006075"
    ]
},
  "bbox": [],
  "geometry": {"coordinates":[-82.0667,28.6833],"type":"Point"}
}