{
  "id": 2747036,
  "type": "Feature",
  "properties": {
    "tgn:hierarchy":[
        "tgn:2747036",
        "tgn:1000001",
        "tgn:2001414",
        "tgn:7012149",
        "tgn:7007526",
        "tgn:7029392"
    ],
    "tgn:id":2747036,
    "tgn:name":"Wagner Springs",
    "tgn:placetype":[
        "aat:300008697"
    ]
},
  "bbox": [],
  "geometry": {"coordinates":[-119.1333,41.1333],"type":"Point"}
}