{
  "id": 2730621,
  "type": "Feature",
  "properties": {
    "tgn:hierarchy":[
        "tgn:2730621",
        "tgn:7030516",
        "tgn:7006450",
        "tgn:1000001",
        "tgn:7012149",
        "tgn:7029392"
    ],
    "tgn:id":2730621,
    "tgn:name":"Trunk Point",
    "tgn:placetype":[
        "aat:300008850"
    ]
},
  "bbox": [],
  "geometry": {"coordinates":[-177.7833,51.7667],"type":"Point"}
}