{
  "id": 7585786,
  "type": "Feature",
  "properties": {
    "tgn:hierarchy":[
        "tgn:7585786",
        "tgn:1000004",
        "tgn:7000198",
        "tgn:7000799",
        "tgn:7029392"
    ],
    "tgn:id":7585786,
    "tgn:name:en":"Ahadio",
    "tgn:placetype":[
        "aat:300008347"
    ]
},
  "bbox": [],
  "geometry": {"coordinates":[74.11182,34.323674],"type":"Point"}
}