{
  "id": 2352991,
  "type": "Feature",
  "properties": {
    "tgn:hierarchy":[
        "tgn:2352991",
        "tgn:1002366",
        "tgn:1000001",
        "tgn:7012149",
        "tgn:7007159",
        "tgn:7029392"
    ],
    "tgn:id":2352991,
    "tgn:name":"Godfrey Pond",
    "tgn:placetype":[
        "aat:300008680"
    ]
},
  "bbox": [],
  "geometry": {"coordinates":[-73.3833,41.2333],"type":"Point"}
}