{
  "id": 2438906,
  "type": "Feature",
  "properties": {
    "tgn:hierarchy":[
        "tgn:2438906",
        "tgn:1000001",
        "tgn:7012149",
        "tgn:2001274",
        "tgn:7007524",
        "tgn:7029392"
    ],
    "tgn:id":2438906,
    "tgn:name":"Kinnimiki Creek",
    "tgn:placetype":[
        "aat:300008706"
    ]
},
  "bbox": [],
  "geometry": {"coordinates":[-114.2833,48.5333],"type":"Point"}
}