{
  "id": 7485566,
  "type": "Feature",
  "properties": {
    "tgn:hierarchy":[
        "tgn:7485566",
        "tgn:1000004",
        "tgn:7467799",
        "tgn:1000141",
        "tgn:7029392"
    ],
    "tgn:id":7485566,
    "tgn:name":"Guanyucuo Qiao",
    "tgn:placetype":[
        "aat:300007836"
    ]
},
  "bbox": [],
  "geometry": {"coordinates":[120.410833,24.026667],"type":"Point"}
}