{
  "id": 1124719,
  "type": "Feature",
  "properties": {
    "tgn:hierarchy":[
        "tgn:1124719",
        "tgn:1000004",
        "tgn:1009319",
        "tgn:1000141",
        "tgn:7029392"
    ],
    "tgn:id":1124719,
    "tgn:name":"Huang Ch'i",
    "tgn:placetype":[
        "aat:300008707",
        "aat:300008699"
    ]
},
  "bbox": [],
  "geometry": {"coordinates":[121.648232,25.22892],"type":"Point"}
}