{
  "id": 7201501,
  "type": "Feature",
  "properties": {
    "tgn:hierarchy":[
        "tgn:7201501",
        "tgn:1000003",
        "tgn:7000094",
        "tgn:7000084",
        "tgn:7029392"
    ],
    "tgn:id":7201501,
    "tgn:name":"Borkenhagen",
    "tgn:placetype":[
        "aat:300008347"
    ]
},
  "bbox": [],
  "geometry": {"coordinates":[11.066667,53.95],"type":"Point"}
}