<<<<<<< HEAD
{
  "id": 2765743,
  "type": "Feature",
  "properties": {
    "tgn:hierarchy":[
        "tgn:2765743",
        "tgn:1000001",
        "tgn:7012149",
        "tgn:2000997",
        "tgn:7007520",
        "tgn:7029392"
    ],
    "tgn:id":2765743,
    "tgn:name":"White Creek Drain",
    "tgn:placetype":[
        "aat:300006075"
    ]
},
  "bbox": [],
  "geometry": {"coordinates":[-83.1333,43.4],"type":"Point"}
}
=======
{"geometry":{"type":"Point","coordinates":[-83.133300,43.400000]},"type":"Feature","properties":{"hierarchy":["tgn:2765743","tgn:1000001","tgn:7012149","tgn:2000997","tgn:7007520","tgn:7029392"],"placetype":["aat:300006075"],"id":2765743,"name:xx":"White Creek Drain"}}
>>>>>>> 03f74aca74312dbeaf24d7e61306dd6a786dc3d0
