<<<<<<< HEAD
{
  "id": 7249779,
  "type": "Feature",
  "properties": {
    "tgn:hierarchy":[
        "tgn:7249779",
        "tgn:7003458",
        "tgn:1000003",
        "tgn:1000063",
        "tgn:7018236",
        "tgn:7029392"
    ],
    "tgn:id":7249779,
    "tgn:name":"Poorterhoek",
    "tgn:placetype":[
        "aat:300008347"
    ]
},
  "bbox": [],
  "geometry": {"coordinates":[3.1,51.083333],"type":"Point"}
}
=======
{"geometry":{"type":"Point","coordinates":[3.100000,51.083333]},"type":"Feature","properties":{"hierarchy":["tgn:7249779","tgn:7003458","tgn:1000003","tgn:1000063","tgn:7018236","tgn:7029392"],"placetype":["aat:300008347"],"id":7249779,"name:xx":"Poorterhoek"}}
>>>>>>> 03f74aca74312dbeaf24d7e61306dd6a786dc3d0
