{
  "id": 7564980,
  "type": "Feature",
  "properties": {
    "tgn:hierarchy":[
        "tgn:7564980",
        "tgn:1000004",
        "tgn:7000198",
        "tgn:7000799",
        "tgn:7029392"
    ],
    "tgn:id":7564980,
    "tgn:name:en":"Dadi\u0101l",
    "tgn:placetype":[
        "aat:300008347"
    ]
},
  "bbox": [],
  "geometry": {"coordinates":[74.956609,32.486765],"type":"Point"}
}