{
  "id": 7004276,
  "type": "Feature",
  "properties": {
    "tgn:hierarchy":[
        "tgn:7004276",
        "tgn:1000003",
        "tgn:1000091",
        "tgn:7029392"
    ],
    "tgn:id":7004276,
    "tgn:name":"Giurgiu",
    "tgn:placetype":[
        "aat:300387064",
        "aat:300000771"
    ]
},
  "bbox": [],
  "geometry": {"coordinates":[25.9167,44.1667],"type":"Point"}
}