{
  "id": 7339185,
  "type": "Feature",
  "properties": {
    "tgn:hierarchy":[
        "tgn:7339185",
        "tgn:7001165",
        "tgn:1000003",
        "tgn:7002793",
        "tgn:1000095",
        "tgn:7029392"
    ],
    "tgn:id":7339185,
    "tgn:name":"El Carrascal",
    "tgn:placetype":[
        "aat:300387200"
    ]
},
  "bbox": [],
  "geometry": {"coordinates":[-1.183333,39.75],"type":"Point"}
}