{
  "id": 1086757,
  "type": "Feature",
  "properties": {
    "tgn:hierarchy":[
        "tgn:1086757",
        "tgn:1001052",
        "tgn:1000004",
        "tgn:7018450",
        "tgn:1000144",
        "tgn:7029392"
    ],
    "tgn:id":1086757,
    "tgn:name":"Pirin\u00e7\u00e7\u0131",
    "tgn:placetype":[
        "aat:300008347"
    ]
},
  "bbox": [],
  "geometry": {"coordinates":[28.8333,41.1667],"type":"Point"}
}