{
  "id": 2691715,
  "type": "Feature",
  "properties": {
    "tgn:hierarchy":[
        "tgn:2691715",
        "tgn:1000001",
        "tgn:2000307",
        "tgn:7012149",
        "tgn:7007248",
        "tgn:7029392"
    ],
    "tgn:id":2691715,
    "tgn:name":"Starlins Pond",
    "tgn:placetype":[
        "aat:300008680"
    ]
},
  "bbox": [],
  "geometry": {"coordinates":[-81.6333,32.2167],"type":"Point"}
}