{
  "id": 1009401,
  "type": "Feature",
  "properties": {
    "tgn:hierarchy":[
        "tgn:1009401",
        "tgn:1000004",
        "tgn:7000381",
        "tgn:7029392"
    ],
    "tgn:id":1009401,
    "tgn:name":"Tekong Kechil, Pulau",
    "tgn:placetype":[
        "aat:300008791"
    ]
},
  "bbox": [],
  "geometry": {"coordinates":[104.0167,1.4167],"type":"Point"}
}