{
  "id": 7232128,
  "type": "Feature",
  "properties": {
    "tgn:hierarchy":[
        "tgn:7232128",
        "tgn:7002751",
        "tgn:7001399",
        "tgn:1000003",
        "tgn:1000074",
        "tgn:7029392"
    ],
    "tgn:id":7232128,
    "tgn:name":"Kal\u00e1mi",
    "tgn:placetype":[
        "aat:300008347"
    ]
},
  "bbox": [],
  "geometry": {"coordinates":[23.283333,39.233333],"type":"Point"}
}