{
  "id": 2619116,
  "type": "Feature",
  "properties": {
    "tgn:hierarchy":[
        "tgn:2619116",
        "tgn:1000001",
        "tgn:1003037",
        "tgn:7012149",
        "tgn:7007516",
        "tgn:7029392"
    ],
    "tgn:id":2619116,
    "tgn:name":"Riley Cove",
    "tgn:placetype":[
        "aat:300132316"
    ]
},
  "bbox": [],
  "geometry": {"coordinates":[-75.3667,38.0333],"type":"Point"}
}