{
  "id": 2368879,
  "type": "Feature",
  "properties": {
    "tgn:hierarchy":[
        "tgn:2368879",
        "tgn:1000001",
        "tgn:2000303",
        "tgn:7012149",
        "tgn:7007248",
        "tgn:7029392"
    ],
    "tgn:id":2368879,
    "tgn:name":"Gully Branch",
    "tgn:placetype":[
        "aat:300008699"
    ]
},
  "bbox": [],
  "geometry": {"coordinates":[-83.3167,32.4833],"type":"Point"}
}