{
  "id": 2225643,
  "type": "Feature",
  "properties": {
    "tgn:hierarchy":[
        "tgn:2225643",
        "tgn:1000001",
        "tgn:7012149",
        "tgn:2001982",
        "tgn:7007826",
        "tgn:7029392"
    ],
    "tgn:id":2225643,
    "tgn:name":"Cat Branch",
    "tgn:placetype":[
        "aat:300008699"
    ]
},
  "bbox": [],
  "geometry": {"coordinates":[-98.35,32.1333],"type":"Point"}
}