{
  "id": 2014617,
  "type": "Feature",
  "properties": {
    "tgn:hierarchy":[
        "tgn:2014617",
        "tgn:1000001",
        "tgn:7012149",
        "tgn:7007157",
        "tgn:1002861",
        "tgn:7029392"
    ],
    "tgn:id":2014617,
    "tgn:name":"Tomspur",
    "tgn:placetype":[
        "aat:300387016"
    ]
},
  "bbox": [],
  "geometry": {"coordinates":[-121.2667,38.05],"type":"Point"}
}