{
  "id": 7377774,
  "type": "Feature",
  "properties": {
    "tgn:hierarchy":[
        "tgn:7377774",
        "tgn:1000001",
        "tgn:7005589",
        "tgn:7005560",
        "tgn:7029392"
    ],
    "tgn:id":7377774,
    "tgn:name":"La Ventura",
    "tgn:placetype":[
        "aat:300008347"
    ]
},
  "bbox": [],
  "geometry": {"coordinates":[-99.683333,26.466667],"type":"Point"}
}