{
  "id": 7133497,
  "type": "Feature",
  "properties": {
    "tgn:hierarchy":[
        "tgn:7133497",
        "tgn:7003669",
        "tgn:1000003",
        "tgn:7000084",
        "tgn:7029392"
    ],
    "tgn:id":7133497,
    "tgn:name":"Moosbach",
    "tgn:placetype":[
        "aat:300008347"
    ]
},
  "bbox": [],
  "geometry": {"coordinates":[12.783333,49.116667],"type":"Point"}
}