{
  "id": 7211817,
  "type": "Feature",
  "properties": {
    "tgn:hierarchy":[
        "tgn:7211817",
        "tgn:7003692",
        "tgn:1000003",
        "tgn:7000084",
        "tgn:7029392"
    ],
    "tgn:id":7211817,
    "tgn:name":"Betenbrunn",
    "tgn:placetype":[
        "aat:300008347"
    ]
},
  "bbox": [],
  "geometry": {"coordinates":[9.35,47.816667],"type":"Point"}
}