{
  "id": 2219936,
  "type": "Feature",
  "properties": {
    "tgn:hierarchy":[
        "tgn:2219936",
        "tgn:1000001",
        "tgn:7012149",
        "tgn:2001708",
        "tgn:7007708",
        "tgn:7029392"
    ],
    "tgn:id":2219936,
    "tgn:name":"Canyon City Municipal Watershed",
    "tgn:placetype":[
        "aat:300386845"
    ]
},
  "bbox": [],
  "geometry": {"coordinates":[-118.9167,44.35],"type":"Point"}
}