{
  "id": 2530052,
  "type": "Feature",
  "properties": {
    "tgn:hierarchy":[
        "tgn:2530052",
        "tgn:1000001",
        "tgn:7012149",
        "tgn:2002040",
        "tgn:7007826",
        "tgn:7029392"
    ],
    "tgn:id":2530052,
    "tgn:name":"Mud Spring",
    "tgn:placetype":[
        "aat:300008697"
    ]
},
  "bbox": [],
  "geometry": {"coordinates":[-99.5667,30.8333],"type":"Point"}
}