{
  "id": 1097884,
  "type": "Feature",
  "properties": {
    "tgn:hierarchy":[
        "tgn:1097884",
        "tgn:7000490",
        "tgn:1000006",
        "tgn:7001828",
        "tgn:7029392"
    ],
    "tgn:id":1097884,
    "tgn:name":"Ourimbah",
    "tgn:placetype":[
        "aat:300008347"
    ]
},
  "bbox": [],
  "geometry": {"coordinates":[151.4333,-33.3667],"type":"Point"}
}