{
  "id": 2352754,
  "type": "Feature",
  "properties": {
    "tgn:hierarchy":[
        "tgn:2352754",
        "tgn:1000001",
        "tgn:7012149",
        "tgn:2001958",
        "tgn:7007826",
        "tgn:7029392"
    ],
    "tgn:id":2352754,
    "tgn:name":"Gobbler Creek",
    "tgn:placetype":[
        "aat:300008706"
    ]
},
  "bbox": [],
  "geometry": {"coordinates":[-100.4667,32.0167],"type":"Point"}
}