{
  "id": 1007985,
  "type": "Feature",
  "properties": {
    "tgn:hierarchy":[
        "tgn:1007985",
        "tgn:7001635",
        "tgn:7001242",
        "tgn:7001632",
        "tgn:7029392"
    ],
    "tgn:id":1007985,
    "tgn:name":"Maio",
    "tgn:placetype":[
        "aat:300387145",
        "aat:300008791",
        "aat:300000771"
    ]
},
  "bbox": [],
  "geometry": {"coordinates":[-23.1667,15.25],"type":"Point"}
}