<<<<<<< HEAD
{
  "id": 7052314,
  "type": "Feature",
  "properties": {
    "tgn:hierarchy":[
        "tgn:7052314",
        "tgn:7003006",
        "tgn:1000003",
        "tgn:7002997",
        "tgn:1000080",
        "tgn:7029392"
    ],
    "tgn:id":7052314,
    "tgn:name":"Pellestrina, Litorale di",
    "tgn:placetype":[
        "aat:300008816"
    ]
},
  "bbox": [],
  "geometry": {"coordinates":[12.303889,45.278056],"type":"Point"}
}
=======
{"geometry":{"type":"Point","coordinates":[12.303889,45.278056]},"type":"Feature","properties":{"hierarchy":["tgn:7052314","tgn:7003006","tgn:1000003","tgn:7002997","tgn:1000080","tgn:7029392"],"placetype":["aat:300008816"],"id":7052314,"name:xx":"Pellestrina, Litorale di"}}
>>>>>>> 03f74aca74312dbeaf24d7e61306dd6a786dc3d0
