{
  "id": 7003046,
  "type": "Feature",
  "properties": {
    "tgn:hierarchy":[
        "tgn:7003046",
        "tgn:7002996",
        "tgn:1000003",
        "tgn:7002997",
        "tgn:1000080",
        "tgn:7029392"
    ],
    "tgn:id":7003046,
    "tgn:name":"Motta di Livenza",
    "tgn:placetype":[
        "aat:300008347"
    ]
},
  "bbox": [],
  "geometry": {"coordinates":[12.602778,45.778056],"type":"Point"}
}