{
  "id": 2260119,
  "type": "Feature",
  "properties": {
    "tgn:hierarchy":[
        "tgn:2260119",
        "tgn:2001089",
        "tgn:1000001",
        "tgn:7012149",
        "tgn:7007522",
        "tgn:7029392"
    ],
    "tgn:id":2260119,
    "tgn:name":"Country Club Lake",
    "tgn:placetype":[
        "aat:300006191"
    ]
},
  "bbox": [],
  "geometry": {"coordinates":[-89.6167,33.0167],"type":"Point"}
}