{
  "id": 7072801,
  "type": "Feature",
  "properties": {
    "tgn:hierarchy":[
        "tgn:7072801",
        "tgn:1000003",
        "tgn:7003685",
        "tgn:7000084",
        "tgn:7029392"
    ],
    "tgn:id":7072801,
    "tgn:name":"Striegnitz",
    "tgn:placetype":[
        "aat:300008347"
    ]
},
  "bbox": [],
  "geometry": {"coordinates":[13.283333,51.233333],"type":"Point"}
}