{
  "id": 2565335,
  "type": "Feature",
  "properties": {
    "tgn:hierarchy":[
        "tgn:2565335",
        "tgn:1000001",
        "tgn:2001945",
        "tgn:7012149",
        "tgn:7007826",
        "tgn:7029392"
    ],
    "tgn:id":2565335,
    "tgn:name":"Paint Gap Hills",
    "tgn:placetype":[
        "aat:300008798"
    ]
},
  "bbox": [],
  "geometry": {"coordinates":[-103.2833,29.3833],"type":"Point"}
}