{
  "id": 7336045,
  "type": "Feature",
  "properties": {
    "tgn:hierarchy":[
        "tgn:7336045",
        "tgn:7001122",
        "tgn:1000003",
        "tgn:7002765",
        "tgn:1000095",
        "tgn:7029392"
    ],
    "tgn:id":7336045,
    "tgn:name":"Furn\u00e1s",
    "tgn:placetype":[
        "aat:300008798"
    ]
},
  "bbox": [],
  "geometry": {"coordinates":[1.516667,39.066667],"type":"Point"}
}