{
  "id": 7475870,
  "type": "Feature",
  "properties": {
    "tgn:hierarchy":[
        "tgn:7475870",
        "tgn:1000004",
        "tgn:7489179",
        "tgn:1000141",
        "tgn:7029392"
    ],
    "tgn:id":7475870,
    "tgn:name":"Cihui Si",
    "tgn:placetype":[
        "aat:300007595"
    ]
},
  "bbox": [],
  "geometry": {"coordinates":[121.722979,24.740248],"type":"Point"}
}