{
  "id": 7282572,
  "type": "Feature",
  "properties": {
    "tgn:hierarchy":[
        "tgn:7282572",
        "tgn:1001637",
        "tgn:1000049",
        "tgn:1000002",
        "tgn:7029392"
    ],
    "tgn:id":7282572,
    "tgn:name":"Perilla, Cerro",
    "tgn:placetype":[
        "aat:300008795"
    ]
},
  "bbox": [],
  "geometry": {"coordinates":[-71.366667,-37.133333],"type":"Point"}
}