{
  "id": 7037135,
  "type": "Feature",
  "properties": {
    "tgn:hierarchy":[
        "tgn:7037135",
        "tgn:7003168",
        "tgn:1000003",
        "tgn:7009760",
        "tgn:1000080",
        "tgn:7029392"
    ],
    "tgn:id":7037135,
    "tgn:name":"Vico d'Arbia",
    "tgn:placetype":[
        "aat:300008347"
    ]
},
  "bbox": [],
  "geometry": {"coordinates":[11.416667,43.333333],"type":"Point"}
}