{
  "id": 2507005,
  "type": "Feature",
  "properties": {
    "tgn:hierarchy":[
        "tgn:2507005",
        "tgn:7002659",
        "tgn:1000001",
        "tgn:7012149",
        "tgn:2000033",
        "tgn:7029392"
    ],
    "tgn:id":2507005,
    "tgn:name":"Messick Pond",
    "tgn:placetype":[
        "aat:300006191"
    ]
},
  "bbox": [],
  "geometry": {"coordinates":[-85.2167,31.55],"type":"Point"}
}