<<<<<<< HEAD
{
  "id": 2332820,
  "type": "Feature",
  "properties": {
    "tgn:hierarchy":[
        "tgn:2332820",
        "tgn:7002659",
        "tgn:1000001",
        "tgn:2000004",
        "tgn:7012149",
        "tgn:7029392"
    ],
    "tgn:id":2332820,
    "tgn:name":"Floyd Creek",
    "tgn:placetype":[
        "aat:300008706"
    ]
},
  "bbox": [],
  "geometry": {"coordinates":[-86.5167,33.9],"type":"Point"}
}
=======
{"geometry":{"type":"Point","coordinates":[-86.516700,33.900000]},"type":"Feature","properties":{"hierarchy":["tgn:2332820","tgn:7002659","tgn:1000001","tgn:2000004","tgn:7012149","tgn:7029392"],"placetype":["aat:300008706"],"id":2332820,"name:xx":"Floyd Creek"}}
>>>>>>> 03f74aca74312dbeaf24d7e61306dd6a786dc3d0
