<<<<<<< HEAD
{
  "id": 2156081,
  "type": "Feature",
  "properties": {
    "tgn:hierarchy":[
        "tgn:2156081",
        "tgn:1000001",
        "tgn:7012149",
        "tgn:7014589",
        "tgn:7007515",
        "tgn:7029392"
    ],
    "tgn:id":2156081,
    "tgn:name":"Bearce Lake",
    "tgn:placetype":[
        "aat:300008680"
    ]
},
  "bbox": [],
  "geometry": {"coordinates":[-67.3167,45.0667],"type":"Point"}
}
=======
{"geometry":{"type":"Point","coordinates":[-67.316700,45.066700]},"type":"Feature","properties":{"hierarchy":["tgn:2156081","tgn:1000001","tgn:7012149","tgn:7014589","tgn:7007515","tgn:7029392"],"placetype":["aat:300008680"],"id":2156081,"name:xx":"Bearce Lake"}}
>>>>>>> 03f74aca74312dbeaf24d7e61306dd6a786dc3d0
