{
  "id": 7584063,
  "type": "Feature",
  "properties": {
    "tgn:hierarchy":[
        "tgn:7584063",
        "tgn:1000004",
        "tgn:7000198",
        "tgn:7016883",
        "tgn:7029392"
    ],
    "tgn:id":7584063,
    "tgn:name:en":"Bah\u0101durpur",
    "tgn:placetype":[
        "aat:300008347"
    ]
},
  "bbox": [],
  "geometry": {"coordinates":[76.582046,30.223162],"type":"Point"}
}