<<<<<<< HEAD
{
  "id": 7480774,
  "type": "Feature",
  "properties": {
    "tgn:hierarchy":[
        "tgn:7480774",
        "tgn:7001010",
        "tgn:1000004",
        "tgn:1000141",
        "tgn:7029392"
    ],
    "tgn:id":7480774,
    "tgn:name":"Heyi Tang",
    "tgn:placetype":[
        "aat:300007595"
    ]
},
  "bbox": [],
  "geometry": {"coordinates":[121.513611,23.941389],"type":"Point"}
}
=======
{"geometry":{"type":"Point","coordinates":[121.513611,23.941389]},"type":"Feature","properties":{"hierarchy":["tgn:7480774","tgn:7001010","tgn:1000004","tgn:1000141","tgn:7029392"],"placetype":["aat:300007595"],"id":7480774,"name:xx":"Heyi Tang"}}
>>>>>>> 03f74aca74312dbeaf24d7e61306dd6a786dc3d0
