{
  "id": 7578379,
  "type": "Feature",
  "properties": {
    "tgn:hierarchy":[
        "tgn:7578379",
        "tgn:1000004",
        "tgn:7031781",
        "tgn:7000198",
        "tgn:7029392"
    ],
    "tgn:id":7578379,
    "tgn:name:en":"Tumnar",
    "tgn:placetype":[
        "aat:300008347"
    ]
},
  "bbox": [],
  "geometry": {"coordinates":[81.25,19.033333],"type":"Point"}
}