{
  "id": 7339971,
  "type": "Feature",
  "properties": {
    "tgn:hierarchy":[
        "tgn:7339971",
        "tgn:7002758",
        "tgn:7002823",
        "tgn:1000003",
        "tgn:1000095",
        "tgn:7029392"
    ],
    "tgn:id":7339971,
    "tgn:name":"Cumbres de en Medio",
    "tgn:placetype":[
        "aat:300008347"
    ]
},
  "bbox": [],
  "geometry": {"coordinates":[-6.683333,38.066667],"type":"Point"}
}