<<<<<<< HEAD
{
  "id": 7054874,
  "type": "Feature",
  "properties": {
    "tgn:hierarchy":[
        "tgn:7054874",
        "tgn:1003429",
        "tgn:1000003",
        "tgn:7003240",
        "tgn:1000080",
        "tgn:7029392"
    ],
    "tgn:id":7054874,
    "tgn:name":"Molino di Ripe",
    "tgn:placetype":[
        "aat:300008347"
    ]
},
  "bbox": [],
  "geometry": {"coordinates":[13.116667,43.65],"type":"Point"}
}
=======
{"geometry":{"type":"Point","coordinates":[13.116667,43.650000]},"type":"Feature","properties":{"hierarchy":["tgn:7054874","tgn:1003429","tgn:1000003","tgn:7003240","tgn:1000080","tgn:7029392"],"placetype":["aat:300008347"],"id":7054874,"name:xx":"Molino di Ripe"}}
>>>>>>> 03f74aca74312dbeaf24d7e61306dd6a786dc3d0
