{
  "id": 7476814,
  "type": "Feature",
  "properties": {
    "tgn:hierarchy":[
        "tgn:7476814",
        "tgn:1000004",
        "tgn:7004300",
        "tgn:1000141",
        "tgn:7029392"
    ],
    "tgn:id":7476814,
    "tgn:name":"Dabaisha Yu",
    "tgn:placetype":[
        "aat:300008791"
    ]
},
  "bbox": [],
  "geometry": {"coordinates":[119.564365,23.695038],"type":"Point"}
}