<<<<<<< HEAD
{
  "id": 7476814,
  "type": "Feature",
  "properties": {
    "tgn:hierarchy":[
        "tgn:7476814",
        "tgn:1000004",
        "tgn:7004300",
        "tgn:1000141",
        "tgn:7029392"
    ],
    "tgn:id":7476814,
    "tgn:name":"Dabaisha Yu",
    "tgn:placetype":[
        "aat:300008791"
    ]
},
  "bbox": [],
  "geometry": {"coordinates":[119.564365,23.695038],"type":"Point"}
}
=======
{"geometry":{"type":"Point","coordinates":[119.564365,23.695038]},"type":"Feature","properties":{"hierarchy":["tgn:7476814","tgn:1000004","tgn:7004300","tgn:1000141","tgn:7029392"],"placetype":["aat:300008791"],"id":7476814,"name:xx":"Dabaisha Yu"}}
>>>>>>> 03f74aca74312dbeaf24d7e61306dd6a786dc3d0
