{
  "id": 2625637,
  "type": "Feature",
  "properties": {
    "tgn:hierarchy":[
        "tgn:2625637",
        "tgn:1000001",
        "tgn:7012149",
        "tgn:2001255",
        "tgn:7007523",
        "tgn:7029392"
    ],
    "tgn:id":2625637,
    "tgn:name":"Rockwood Point",
    "tgn:placetype":[
        "aat:300008850"
    ]
},
  "bbox": [],
  "geometry": {"coordinates":[-90.2833,36.9167],"type":"Point"}
}