<<<<<<< HEAD
{
  "id": 2760657,
  "type": "Feature",
  "properties": {
    "tgn:hierarchy":[
        "tgn:2760657",
        "tgn:1000001",
        "tgn:7012149",
        "tgn:7007708",
        "tgn:7029392"
    ],
    "tgn:id":2760657,
    "tgn:name":"West Fork Wolf Creek",
    "tgn:placetype":[
        "aat:300008706"
    ]
},
  "bbox": [],
  "geometry": {"coordinates":[-118.7833,44.0667],"type":"Point"}
}
=======
{"geometry":{"type":"Point","coordinates":[-118.783300,44.066700]},"type":"Feature","properties":{"hierarchy":["tgn:2760657","tgn:1000001","tgn:7012149","tgn:7007708","tgn:7029392"],"placetype":["aat:300008706"],"id":2760657,"name:xx":"West Fork Wolf Creek"}}
>>>>>>> 03f74aca74312dbeaf24d7e61306dd6a786dc3d0
