{
  "id": 1041233,
  "type": "Feature",
  "properties": {
    "tgn:hierarchy":[
        "tgn:1041233",
        "tgn:7003669",
        "tgn:1000003",
        "tgn:7000084",
        "tgn:7029392"
    ],
    "tgn:id":1041233,
    "tgn:name":"Simmerberg",
    "tgn:placetype":[
        "aat:300008347"
    ]
},
  "bbox": [],
  "geometry": {"coordinates":[9.95,47.5833],"type":"Point"}
}