<<<<<<< HEAD
{
  "id": 7170796,
  "type": "Feature",
  "properties": {
    "tgn:hierarchy":[
        "tgn:7170796",
        "tgn:1000003",
        "tgn:7003685",
        "tgn:7000084",
        "tgn:7029392"
    ],
    "tgn:id":7170796,
    "tgn:name":"Henneberg",
    "tgn:placetype":[
        "aat:300000206"
    ]
},
  "bbox": [],
  "geometry": {"coordinates":[12.683333,50.416667],"type":"Point"}
}
=======
{"geometry":{"type":"Point","coordinates":[12.683333,50.416667]},"type":"Feature","properties":{"hierarchy":["tgn:7170796","tgn:1000003","tgn:7003685","tgn:7000084","tgn:7029392"],"placetype":["aat:300000206"],"id":7170796,"name:xx":"Henneberg"}}
>>>>>>> 03f74aca74312dbeaf24d7e61306dd6a786dc3d0
