{
  "id": 7568724,
  "type": "Feature",
  "properties": {
    "tgn:hierarchy":[
        "tgn:7568724",
        "tgn:1000004",
        "tgn:7000198",
        "tgn:7016788",
        "tgn:7029392"
    ],
    "tgn:id":7568724,
    "tgn:name:en":"Jor\u0101warpura",
    "tgn:placetype":[
        "aat:300008347"
    ]
},
  "bbox": [],
  "geometry": {"coordinates":[74.705793,28.475891],"type":"Point"}
}