{
  "id": 7180443,
  "type": "Feature",
  "properties": {
    "tgn:hierarchy":[
        "tgn:7180443",
        "tgn:7000096",
        "tgn:1000003",
        "tgn:7000084",
        "tgn:7029392"
    ],
    "tgn:id":7180443,
    "tgn:name":"Fuchs-Berg",
    "tgn:placetype":[
        "aat:300008777"
    ]
},
  "bbox": [],
  "geometry": {"coordinates":[12.033333,53.133333],"type":"Point"}
}