{
  "id": 2282107,
  "type": "Feature",
  "properties": {
    "tgn:hierarchy":[
        "tgn:2282107",
        "tgn:1000001",
        "tgn:7012149",
        "tgn:7013855",
        "tgn:7007251",
        "tgn:7029392"
    ],
    "tgn:id":2282107,
    "tgn:name":"Deer Lake",
    "tgn:placetype":[
        "aat:300008680"
    ]
},
  "bbox": [],
  "geometry": {"coordinates":[-88.0333,42.4833],"type":"Point"}
}