{
  "id": 2457106,
  "type": "Feature",
  "properties": {
    "tgn:hierarchy":[
        "tgn:2457106",
        "tgn:1000001",
        "tgn:7012149",
        "tgn:2000983",
        "tgn:7007520",
        "tgn:7029392"
    ],
    "tgn:id":2457106,
    "tgn:name":"Little Lake",
    "tgn:placetype":[
        "aat:300008680"
    ]
},
  "bbox": [],
  "geometry": {"coordinates":[-85.85,43.4667],"type":"Point"}
}