{
  "id": 2750840,
  "type": "Feature",
  "properties": {
    "tgn:hierarchy":[
        "tgn:2750840",
        "tgn:1000001",
        "tgn:7012149",
        "tgn:1002790",
        "tgn:7007240",
        "tgn:7029392"
    ],
    "tgn:id":2750840,
    "tgn:name":"Ward Island",
    "tgn:placetype":[
        "aat:300008791"
    ]
},
  "bbox": [],
  "geometry": {"coordinates":[-82.7833,28.05],"type":"Point"}
}