{
  "id": 2547077,
  "type": "Feature",
  "properties": {
    "tgn:hierarchy":[
        "tgn:2547077",
        "tgn:7006450",
        "tgn:1000001",
        "tgn:7012149",
        "tgn:2000088",
        "tgn:7029392"
    ],
    "tgn:id":2547077,
    "tgn:name":"North Fork Porterfield Creek",
    "tgn:placetype":[
        "aat:300008706"
    ]
},
  "bbox": [],
  "geometry": {"coordinates":[-132.1167,56.5333],"type":"Point"}
}