{
  "id": 2564681,
  "type": "Feature",
  "properties": {
    "tgn:hierarchy":[
        "tgn:2564681",
        "tgn:1000001",
        "tgn:7012149",
        "tgn:7007826",
        "tgn:7029392"
    ],
    "tgn:id":2564681,
    "tgn:name":"Packwood Creek",
    "tgn:placetype":[
        "aat:300008706"
    ]
},
  "bbox": [],
  "geometry": {"coordinates":[-96.8833,31.75],"type":"Point"}
}