{
  "id": 1096180,
  "type": "Feature",
  "properties": {
    "tgn:hierarchy":[
        "tgn:1096180",
        "tgn:7000490",
        "tgn:1000006",
        "tgn:7006238",
        "tgn:7029392"
    ],
    "tgn:id":1096180,
    "tgn:name":"Bangholme",
    "tgn:placetype":[
        "aat:300008347"
    ]
},
  "bbox": [],
  "geometry": {"coordinates":[145.1833,-38.0333],"type":"Point"}
}