{
  "id": 2207311,
  "type": "Feature",
  "properties": {
    "tgn:hierarchy":[
        "tgn:2207311",
        "tgn:1000001",
        "tgn:2002368",
        "tgn:7012149",
        "tgn:7007923",
        "tgn:7029392"
    ],
    "tgn:id":2207311,
    "tgn:name":"Bunker Hill",
    "tgn:placetype":[
        "aat:300008798"
    ]
},
  "bbox": [],
  "geometry": {"coordinates":[-106.7833,42.2167],"type":"Point"}
}