{
  "id": 2132294,
  "type": "Feature",
  "properties": {
    "tgn:hierarchy":[
        "tgn:2132294",
        "tgn:1000001",
        "tgn:2002318",
        "tgn:7012149",
        "tgn:7007922",
        "tgn:7029392"
    ],
    "tgn:id":2132294,
    "tgn:name":"Amik Island",
    "tgn:placetype":[
        "aat:300008791"
    ]
},
  "bbox": [],
  "geometry": {"coordinates":[-92.2667,46.65],"type":"Point"}
}