{
  "id": 7193393,
  "type": "Feature",
  "properties": {
    "tgn:hierarchy":[
        "tgn:7193393",
        "tgn:7003692",
        "tgn:1000003",
        "tgn:7000084",
        "tgn:7029392"
    ],
    "tgn:id":7193393,
    "tgn:name":"Felixenhof",
    "tgn:placetype":[
        "aat:300000206"
    ]
},
  "bbox": [],
  "geometry": {"coordinates":[9.633333,47.816667],"type":"Point"}
}