{
  "id": 2410360,
  "type": "Feature",
  "properties": {
    "tgn:hierarchy":[
        "tgn:2410360",
        "tgn:1000001",
        "tgn:7012149",
        "tgn:7007826",
        "tgn:7029392"
    ],
    "tgn:id":2410360,
    "tgn:name":"Indian Branch",
    "tgn:placetype":[
        "aat:300008699"
    ]
},
  "bbox": [],
  "geometry": {"coordinates":[-99.15,30.15],"type":"Point"}
}