{
  "id": 7471413,
  "type": "Feature",
  "properties": {
    "tgn:hierarchy":[
        "tgn:7471413",
        "tgn:1000004",
        "tgn:1000454",
        "tgn:1000141",
        "tgn:7029392"
    ],
    "tgn:id":7471413,
    "tgn:name":"Xiajiadong",
    "tgn:placetype":[
        "aat:300008347"
    ]
},
  "bbox": [],
  "geometry": {"coordinates":[121.45,25.116667],"type":"Point"}
}