<<<<<<< HEAD
{
  "id": 7051961,
  "type": "Feature",
  "properties": {
    "tgn:hierarchy":[
        "tgn:7051961",
        "tgn:7003154",
        "tgn:1000003",
        "tgn:7003120",
        "tgn:1000080",
        "tgn:7029392"
    ],
    "tgn:id":7051961,
    "tgn:name":"Mucrone, Lago",
    "tgn:placetype":[
        "aat:300008680"
    ]
},
  "bbox": [],
  "geometry": {"coordinates":[7.95,45.616667],"type":"Point"}
}
=======
{"geometry":{"type":"Point","coordinates":[7.950000,45.616667]},"type":"Feature","properties":{"hierarchy":["tgn:7051961","tgn:7003154","tgn:1000003","tgn:7003120","tgn:1000080","tgn:7029392"],"placetype":["aat:300008680"],"id":7051961,"name:xx":"Mucrone, Lago"}}
>>>>>>> 03f74aca74312dbeaf24d7e61306dd6a786dc3d0
