{
  "id": 7051961,
  "type": "Feature",
  "properties": {
    "tgn:hierarchy":[
        "tgn:7051961",
        "tgn:7003154",
        "tgn:1000003",
        "tgn:7003120",
        "tgn:1000080",
        "tgn:7029392"
    ],
    "tgn:id":7051961,
    "tgn:name":"Mucrone, Lago",
    "tgn:placetype":[
        "aat:300008680"
    ]
},
  "bbox": [],
  "geometry": {"coordinates":[7.95,45.616667],"type":"Point"}
}