{
  "id": 2754344,
  "type": "Feature",
  "properties": {
    "tgn:hierarchy":[
        "tgn:2754344",
        "tgn:1002138",
        "tgn:1000001",
        "tgn:7012149",
        "tgn:7007157",
        "tgn:7029392"
    ],
    "tgn:id":2754344,
    "tgn:name":"Wauhab Ridge",
    "tgn:placetype":[
        "aat:300266640"
    ]
},
  "bbox": [],
  "geometry": {"coordinates":[-121.75,37.5333],"type":"Point"}
}