{
  "id": 7073407,
  "type": "Feature",
  "properties": {
    "tgn:hierarchy":[
        "tgn:7073407",
        "tgn:1000003",
        "tgn:7003688",
        "tgn:7000084",
        "tgn:7029392"
    ],
    "tgn:id":7073407,
    "tgn:name":"S\u00fcdfeddersb\u00fcll",
    "tgn:placetype":[
        "aat:300000206"
    ]
},
  "bbox": [],
  "geometry": {"coordinates":[8.65,54.816667],"type":"Point"}
}