{
  "id": 7292842,
  "type": "Feature",
  "properties": {
    "tgn:hierarchy":[
        "tgn:7292842",
        "tgn:7016598",
        "tgn:1000049",
        "tgn:1000002",
        "tgn:7029392"
    ],
    "tgn:id":7292842,
    "tgn:name":"El Morrito",
    "tgn:placetype":[
        "aat:300387200"
    ]
},
  "bbox": [],
  "geometry": {"coordinates":[-70.45,-25.133333],"type":"Point"}
}