<<<<<<< HEAD
{
  "id": 2765005,
  "type": "Feature",
  "properties": {
    "tgn:hierarchy":[
        "tgn:2765005",
        "tgn:1000001",
        "tgn:7012149",
        "tgn:2001714",
        "tgn:7007708",
        "tgn:7029392"
    ],
    "tgn:id":2765005,
    "tgn:name":"Whisky Creek",
    "tgn:placetype":[
        "aat:300008706"
    ]
},
  "bbox": [],
  "geometry": {"coordinates":[-121.35,42.35],"type":"Point"}
}
=======
{"geometry":{"type":"Point","coordinates":[-121.350000,42.350000]},"type":"Feature","properties":{"hierarchy":["tgn:2765005","tgn:1000001","tgn:7012149","tgn:2001714","tgn:7007708","tgn:7029392"],"placetype":["aat:300008706"],"id":2765005,"name:xx":"Whisky Creek"}}
>>>>>>> 03f74aca74312dbeaf24d7e61306dd6a786dc3d0
