{
  "id": 7419305,
  "type": "Feature",
  "properties": {
    "tgn:hierarchy":[
        "tgn:7419305",
        "tgn:1000001",
        "tgn:1001937",
        "tgn:7005560",
        "tgn:7029392"
    ],
    "tgn:id":7419305,
    "tgn:name":"Cozumel, Banco",
    "tgn:placetype":[
        "aat:300386970"
    ]
},
  "bbox": [],
  "geometry": {"coordinates":[-86.833333,20.622222],"type":"Point"}
}