{
  "id": 7267726,
  "type": "Feature",
  "properties": {
    "tgn:hierarchy":[
        "tgn:7267726",
        "tgn:7003616",
        "tgn:1000003",
        "tgn:7016845",
        "tgn:7029392"
    ],
    "tgn:id":7267726,
    "tgn:name:nl":"Oostergo",
    "tgn:placetype":[
        "aat:300387346"
    ]
},
  "bbox": [],
  "geometry": {"coordinates":[5.916667,53.25],"type":"Point"}
}