{
  "id": 7402179,
  "type": "Feature",
  "properties": {
    "tgn:hierarchy":[
        "tgn:7402179",
        "tgn:1000001",
        "tgn:7005599",
        "tgn:7005560",
        "tgn:7029392"
    ],
    "tgn:id":7402179,
    "tgn:name":"Coyolar",
    "tgn:placetype":[
        "aat:300008347"
    ]
},
  "bbox": [],
  "geometry": {"coordinates":[-96.616667,19.283333],"type":"Point"}
}