{
  "id": 2257157,
  "type": "Feature",
  "properties": {
    "tgn:hierarchy":[
        "tgn:2257157",
        "tgn:1000001",
        "tgn:7012149",
        "tgn:2001047",
        "tgn:7007521",
        "tgn:7029392"
    ],
    "tgn:id":2257157,
    "tgn:name":"Corner Lake",
    "tgn:placetype":[
        "aat:300008680"
    ]
},
  "bbox": [],
  "geometry": {"coordinates":[-94.6167,46.1667],"type":"Point"}
}