<<<<<<< HEAD
{
  "id": 2339147,
  "type": "Feature",
  "properties": {
    "tgn:hierarchy":[
        "tgn:2339147",
        "tgn:1000001",
        "tgn:7012149",
        "tgn:2000812",
        "tgn:7007255",
        "tgn:7029392"
    ],
    "tgn:id":2339147,
    "tgn:name":"Franks Creek",
    "tgn:placetype":[
        "aat:300008706"
    ]
},
  "bbox": [],
  "geometry": {"coordinates":[-82.8,37.0],"type":"Point"}
}
=======
{"geometry":{"type":"Point","coordinates":[-82.800000,37.000000]},"type":"Feature","properties":{"hierarchy":["tgn:2339147","tgn:1000001","tgn:7012149","tgn:2000812","tgn:7007255","tgn:7029392"],"placetype":["aat:300008706"],"id":2339147,"name:xx":"Franks Creek"}}
>>>>>>> 03f74aca74312dbeaf24d7e61306dd6a786dc3d0
