{
  "id": 2757818,
  "type": "Feature",
  "properties": {
    "tgn:hierarchy":[
        "tgn:2757818",
        "tgn:1000001",
        "tgn:7012149",
        "tgn:2001155",
        "tgn:7007522",
        "tgn:7029392"
    ],
    "tgn:id":2757818,
    "tgn:name":"West Branch Jasper Creek",
    "tgn:placetype":[
        "aat:300008706"
    ]
},
  "bbox": [],
  "geometry": {"coordinates":[-89.0333,34.6333],"type":"Point"}
}