{
  "id": 1028006,
  "type": "Feature",
  "properties": {
    "tgn:hierarchy":[
        "tgn:1028006",
        "tgn:1000003",
        "tgn:7594009",
        "tgn:1000066",
        "tgn:7029392"
    ],
    "tgn:id":1028006,
    "tgn:name":"Lundeborg",
    "tgn:placetype":[
        "aat:300008347"
    ]
},
  "bbox": [],
  "geometry": {"coordinates":[10.7833,55.1333],"type":"Point"}
}