{
  "id": 2541690,
  "type": "Feature",
  "properties": {
    "tgn:hierarchy":[
        "tgn:2541690",
        "tgn:1000001",
        "tgn:7012149",
        "tgn:7007827",
        "tgn:7029392"
    ],
    "tgn:id":2541690,
    "tgn:name":"Ninemile Canyon",
    "tgn:placetype":[
        "aat:300008761"
    ]
},
  "bbox": [],
  "geometry": {"coordinates":[-110.5333,39.7167],"type":"Point"}
}