<<<<<<< HEAD
{
  "id": 2400901,
  "type": "Feature",
  "properties": {
    "tgn:hierarchy":[
        "tgn:2400901",
        "tgn:1000001",
        "tgn:7014449",
        "tgn:7012149",
        "tgn:7007565",
        "tgn:7029392"
    ],
    "tgn:id":2400901,
    "tgn:name":"Horse Run",
    "tgn:placetype":[
        "aat:300008699"
    ]
},
  "bbox": [],
  "geometry": {"coordinates":[-75.3,39.5],"type":"Point"}
}
=======
{"geometry":{"type":"Point","coordinates":[-75.300000,39.500000]},"type":"Feature","properties":{"hierarchy":["tgn:2400901","tgn:1000001","tgn:7014449","tgn:7012149","tgn:7007565","tgn:7029392"],"placetype":["aat:300008699"],"id":2400901,"name:xx":"Horse Run"}}
>>>>>>> 03f74aca74312dbeaf24d7e61306dd6a786dc3d0
