<<<<<<< HEAD
{
  "id": 2765223,
  "type": "Feature",
  "properties": {
    "tgn:hierarchy":[
        "tgn:2765223",
        "tgn:1000001",
        "tgn:7012149",
        "tgn:2000476",
        "tgn:7007250",
        "tgn:7029392"
    ],
    "tgn:id":2765223,
    "tgn:name":"Whistling Pig Creek",
    "tgn:placetype":[
        "aat:300008706"
    ]
},
  "bbox": [],
  "geometry": {"coordinates":[-114.9333,46.15],"type":"Point"}
}
=======
{"geometry":{"type":"Point","coordinates":[-114.933300,46.150000]},"type":"Feature","properties":{"hierarchy":["tgn:2765223","tgn:1000001","tgn:7012149","tgn:2000476","tgn:7007250","tgn:7029392"],"placetype":["aat:300008706"],"id":2765223,"name:xx":"Whistling Pig Creek"}}
>>>>>>> 03f74aca74312dbeaf24d7e61306dd6a786dc3d0
