{
  "id": 2692036,
  "type": "Feature",
  "properties": {
    "tgn:hierarchy":[
        "tgn:2692036",
        "tgn:1000001",
        "tgn:7012149",
        "tgn:1002999",
        "tgn:7007526",
        "tgn:7029392"
    ],
    "tgn:id":2692036,
    "tgn:name":"State Line Peak",
    "tgn:placetype":[
        "aat:300008798"
    ]
},
  "bbox": [],
  "geometry": {"coordinates":[-119.9667,40.0167],"type":"Point"}
}