{
  "id": 7385754,
  "type": "Feature",
  "properties": {
    "tgn:hierarchy":[
        "tgn:7385754",
        "tgn:1000001",
        "tgn:7005590",
        "tgn:7005560",
        "tgn:7029392"
    ],
    "tgn:id":7385754,
    "tgn:name":"Presa",
    "tgn:placetype":[
        "aat:300008347"
    ]
},
  "bbox": [],
  "geometry": {"coordinates":[-101.65,19.75],"type":"Point"}
}