{
  "id": 2662026,
  "type": "Feature",
  "properties": {
    "tgn:hierarchy":[
        "tgn:2662026",
        "tgn:1000001",
        "tgn:2000469",
        "tgn:7012149",
        "tgn:7007250",
        "tgn:7029392"
    ],
    "tgn:id":2662026,
    "tgn:name":"Siberia Creek",
    "tgn:placetype":[
        "aat:300008706"
    ]
},
  "bbox": [],
  "geometry": {"coordinates":[-115.6833,46.4167],"type":"Point"}
}