{
  "id": 2389582,
  "type": "Feature",
  "properties": {
    "tgn:hierarchy":[
        "tgn:2389582",
        "tgn:1000001",
        "tgn:7012149",
        "tgn:1002593",
        "tgn:7007568",
        "tgn:7029392"
    ],
    "tgn:id":2389582,
    "tgn:name":"High Falls",
    "tgn:placetype":[
        "aat:300008347"
    ]
},
  "bbox": [],
  "geometry": {"coordinates":[-75.3667,43.9167],"type":"Point"}
}