{
  "id": 7521097,
  "type": "Feature",
  "properties": {
    "tgn:hierarchy":[
        "tgn:7521097",
        "tgn:7001242",
        "tgn:1001075",
        "tgn:7016833",
        "tgn:7029392"
    ],
    "tgn:id":7521097,
    "tgn:name:en":"Al Makh\u0101'i\u1e11",
    "tgn:placetype":[
        "aat:300008347"
    ]
},
  "bbox": [],
  "geometry": {"coordinates":[30.45,30.966667],"type":"Point"}
}