{
  "id": 7510927,
  "type": "Feature",
  "properties": {
    "tgn:hierarchy":[
        "tgn:7510927",
        "tgn:1008380",
        "tgn:1000226",
        "tgn:7000512",
        "tgn:1000006",
        "tgn:7029392"
    ],
    "tgn:id":7510927,
    "tgn:name:en":"Turere Creek",
    "tgn:placetype":[
        "aat:300008699"
    ]
},
  "bbox": [],
  "geometry": {"coordinates":[174.983333,-41.333333],"type":"Point"}
}