{
  "id": 7301459,
  "type": "Feature",
  "properties": {
    "tgn:hierarchy":[
        "tgn:7301459",
        "tgn:7002758",
        "tgn:7002841",
        "tgn:1000003",
        "tgn:1000095",
        "tgn:7029392"
    ],
    "tgn:id":7301459,
    "tgn:name":"Molinos, Arroyo",
    "tgn:placetype":[
        "aat:300008699"
    ]
},
  "bbox": [],
  "geometry": {"coordinates":[-6.016667,37.483333],"type":"Point"}
}