{
  "id": 2146337,
  "type": "Feature",
  "properties": {
    "tgn:hierarchy":[
        "tgn:2146337",
        "tgn:1000001",
        "tgn:7012149",
        "tgn:2001660",
        "tgn:7007707",
        "tgn:7029392"
    ],
    "tgn:id":2146337,
    "tgn:name":"Bally Mountain",
    "tgn:placetype":[
        "aat:300008798"
    ]
},
  "bbox": [],
  "geometry": {"coordinates":[-98.6667,34.95],"type":"Point"}
}