{
  "id": 2622084,
  "type": "Feature",
  "properties": {
    "tgn:hierarchy":[
        "tgn:2622084",
        "tgn:1000001",
        "tgn:7012149",
        "tgn:2001459",
        "tgn:7007566",
        "tgn:7029392"
    ],
    "tgn:id":2622084,
    "tgn:name":"Roberts Ditch",
    "tgn:placetype":[
        "aat:300006075"
    ]
},
  "bbox": [],
  "geometry": {"coordinates":[-103.0833,36.9167],"type":"Point"}
}