{
  "id": 7577409,
  "type": "Feature",
  "properties": {
    "tgn:hierarchy":[
        "tgn:7577409",
        "tgn:1000004",
        "tgn:7000198",
        "tgn:1001895",
        "tgn:7029392"
    ],
    "tgn:id":7577409,
    "tgn:name:en":"Lohi",
    "tgn:placetype":[
        "aat:300008347"
    ]
},
  "bbox": [],
  "geometry": {"coordinates":[77.666667,20.433333],"type":"Point"}
}