{
  "id": 2377511,
  "type": "Feature",
  "properties": {
    "tgn:hierarchy":[
        "tgn:2377511",
        "tgn:1000001",
        "tgn:7012149",
        "tgn:2001123",
        "tgn:7007522",
        "tgn:7029392"
    ],
    "tgn:id":2377511,
    "tgn:name":"Harper Creek",
    "tgn:placetype":[
        "aat:300008706"
    ]
},
  "bbox": [],
  "geometry": {"coordinates":[-88.85,32.4333],"type":"Point"}
}