{
  "id": 2771301,
  "type": "Feature",
  "properties": {
    "tgn:hierarchy":[
        "tgn:2771301",
        "tgn:1000001",
        "tgn:7012149",
        "tgn:2001715",
        "tgn:7007708",
        "tgn:7029392"
    ],
    "tgn:id":2771301,
    "tgn:name":"Wildcat Waterhole",
    "tgn:placetype":[
        "aat:300006191"
    ]
},
  "bbox": [],
  "geometry": {"coordinates":[-120.4333,42.8333],"type":"Point"}
}