{
  "id": 7468903,
  "type": "Feature",
  "properties": {
    "tgn:hierarchy":[
        "tgn:7468903",
        "tgn:7001010",
        "tgn:1000004",
        "tgn:1000141",
        "tgn:7029392"
    ],
    "tgn:id":7468903,
    "tgn:name":"Xinshe Shan",
    "tgn:placetype":[
        "aat:300008795"
    ]
},
  "bbox": [],
  "geometry": {"coordinates":[121.533333,23.666667],"type":"Point"}
}