<<<<<<< HEAD
{
  "id": 7486075,
  "type": "Feature",
  "properties": {
    "tgn:hierarchy":[
        "tgn:7486075",
        "tgn:1000004",
        "tgn:7471332",
        "tgn:1000141",
        "tgn:7029392"
    ],
    "tgn:id":7486075,
    "tgn:name":"Laku",
    "tgn:placetype":[
        "aat:300387002"
    ]
},
  "bbox": [],
  "geometry": {"coordinates":[121.267222,24.729167],"type":"Point"}
}
=======
{"geometry":{"type":"Point","coordinates":[121.267222,24.729167]},"type":"Feature","properties":{"hierarchy":["tgn:7486075","tgn:1000004","tgn:7471332","tgn:1000141","tgn:7029392"],"placetype":["aat:300387002"],"id":7486075,"name:xx":"Laku"}}
>>>>>>> 03f74aca74312dbeaf24d7e61306dd6a786dc3d0
