{
  "id": 7062255,
  "type": "Feature",
  "properties": {
    "tgn:hierarchy":[
        "tgn:7062255",
        "tgn:1000003",
        "tgn:7003689",
        "tgn:7000084",
        "tgn:7029392"
    ],
    "tgn:id":7062255,
    "tgn:name":"Arnsbachtal",
    "tgn:placetype":[
        "aat:300008761"
    ]
},
  "bbox": [],
  "geometry": {"coordinates":[11.25,50.516667],"type":"Point"}
}