{
  "id": 1108138,
  "type": "Feature",
  "properties": {
    "tgn:hierarchy":[
        "tgn:1108138",
        "tgn:7001242",
        "tgn:7001311",
        "tgn:7016833",
        "tgn:7029392"
    ],
    "tgn:id":1108138,
    "tgn:name:en":"Mush\u0101sh, Jabal al",
    "tgn:placetype":[
        "aat:300008777",
        "aat:300008795"
    ]
},
  "bbox": [],
  "geometry": {"coordinates":[31.221108,28.897645],"type":"Point"}
}