{
  "id": 7261962,
  "type": "Feature",
  "properties": {
    "tgn:concordances":{
        "gn:id":"2755001"
    },
    "tgn:hierarchy":[
        "tgn:7261962",
        "tgn:1000003",
        "tgn:7006951",
        "tgn:7016845",
        "tgn:7029392"
    ],
    "tgn:id":7261962,
    "tgn:name:nl":"Haarlemmerliede",
    "tgn:placetype":[
        "aat:300008347"
    ]
},
  "bbox": [],
  "geometry": {"coordinates":[4.683333,52.383333],"type":"Point"}
}