{
  "id": 1109277,
  "type": "Feature",
  "properties": {
    "tgn:hierarchy":[
        "tgn:1109277",
        "tgn:1000004",
        "tgn:1000111",
        "tgn:7029392"
    ],
    "tgn:id":1109277,
    "tgn:name":"Liupan Shan",
    "tgn:placetype":[
        "aat:300386831"
    ]
},
  "bbox": [],
  "geometry": {"coordinates":[106.203,35.659],"type":"Point"}
}