{
  "id": 2159215,
  "type": "Feature",
  "properties": {
    "tgn:hierarchy":[
        "tgn:2159215",
        "tgn:1000001",
        "tgn:7016172",
        "tgn:7012149",
        "tgn:2000158",
        "tgn:7029392"
    ],
    "tgn:id":2159215,
    "tgn:name":"Bee Bayou",
    "tgn:placetype":[
        "aat:300008699"
    ]
},
  "bbox": [],
  "geometry": {"coordinates":[-91.0167,34.1667],"type":"Point"}
}