{
  "id": 2283097,
  "type": "Feature",
  "properties": {
    "tgn:hierarchy":[
        "tgn:2283097",
        "tgn:1000001",
        "tgn:7012149",
        "tgn:2001918",
        "tgn:7007825",
        "tgn:7029392"
    ],
    "tgn:id":2283097,
    "tgn:name":"Delaney Branch",
    "tgn:placetype":[
        "aat:300008699"
    ]
},
  "bbox": [],
  "geometry": {"coordinates":[-82.15,36.4167],"type":"Point"}
}