{
  "id": 7157267,
  "type": "Feature",
  "properties": {
    "tgn:hierarchy":[
        "tgn:7157267",
        "tgn:7000096",
        "tgn:1000003",
        "tgn:7000084",
        "tgn:7029392"
    ],
    "tgn:id":7157267,
    "tgn:name":"Klandorf",
    "tgn:placetype":[
        "aat:300008347"
    ]
},
  "bbox": [],
  "geometry": {"coordinates":[13.566667,52.883333],"type":"Point"}
}