{
  "id": 2011274,
  "type": "Feature",
  "properties": {
    "tgn:hierarchy":[
        "tgn:2011274",
        "tgn:1000001",
        "tgn:7012149",
        "tgn:7007157",
        "tgn:1002915",
        "tgn:7029392"
    ],
    "tgn:id":2011274,
    "tgn:name":"Eugene",
    "tgn:placetype":[
        "aat:300008347",
        "aat:300387210"
    ]
},
  "bbox": [],
  "geometry": {"coordinates":[-120.8333,37.8833],"type":"Point"}
}