{
  "id": 2592729,
  "type": "Feature",
  "properties": {
    "tgn:hierarchy":[
        "tgn:2592729",
        "tgn:1000001",
        "tgn:7012149",
        "tgn:1002743",
        "tgn:7007240",
        "tgn:7029392"
    ],
    "tgn:id":2592729,
    "tgn:name":"Popash Slough",
    "tgn:placetype":[
        "aat:300008699"
    ]
},
  "bbox": [],
  "geometry": {"coordinates":[-80.9167,27.2667],"type":"Point"}
}