{
  "id": 2339144,
  "type": "Feature",
  "properties": {
    "tgn:hierarchy":[
        "tgn:2339144",
        "tgn:7002659",
        "tgn:1000001",
        "tgn:2000012",
        "tgn:7012149",
        "tgn:7029392"
    ],
    "tgn:id":2339144,
    "tgn:name":"Franks Creek",
    "tgn:placetype":[
        "aat:300008706"
    ]
},
  "bbox": [],
  "geometry": {"coordinates":[-87.8667,31.8667],"type":"Point"}
}