<<<<<<< HEAD
{
  "id": 2339144,
  "type": "Feature",
  "properties": {
    "tgn:hierarchy":[
        "tgn:2339144",
        "tgn:7002659",
        "tgn:1000001",
        "tgn:2000012",
        "tgn:7012149",
        "tgn:7029392"
    ],
    "tgn:id":2339144,
    "tgn:name":"Franks Creek",
    "tgn:placetype":[
        "aat:300008706"
    ]
},
  "bbox": [],
  "geometry": {"coordinates":[-87.8667,31.8667],"type":"Point"}
}
=======
{"geometry":{"type":"Point","coordinates":[-87.866700,31.866700]},"type":"Feature","properties":{"hierarchy":["tgn:2339144","tgn:7002659","tgn:1000001","tgn:2000012","tgn:7012149","tgn:7029392"],"placetype":["aat:300008706"],"id":2339144,"name:xx":"Franks Creek"}}
>>>>>>> 03f74aca74312dbeaf24d7e61306dd6a786dc3d0
