{
  "id": 2631512,
  "type": "Feature",
  "properties": {
    "tgn:hierarchy":[
        "tgn:2631512",
        "tgn:1000001",
        "tgn:7012149",
        "tgn:1002472",
        "tgn:7007568",
        "tgn:7029392"
    ],
    "tgn:id":2631512,
    "tgn:name":"Round Top",
    "tgn:placetype":[
        "aat:300008798"
    ]
},
  "bbox": [],
  "geometry": {"coordinates":[-75.1333,42.8667],"type":"Point"}
}