{
  "id": 2399243,
  "type": "Feature",
  "properties": {
    "tgn:hierarchy":[
        "tgn:2399243",
        "tgn:1000001",
        "tgn:7012149",
        "tgn:1002986",
        "tgn:7007568",
        "tgn:7029392"
    ],
    "tgn:id":2399243,
    "tgn:name":"Horicon Island",
    "tgn:placetype":[
        "aat:300008791"
    ]
},
  "bbox": [],
  "geometry": {"coordinates":[-73.5333,43.6167],"type":"Point"}
}