{
  "id": 1058075,
  "type": "Feature",
  "properties": {
    "tgn:hierarchy":[
        "tgn:1058075",
        "tgn:1000004",
        "tgn:1003405",
        "tgn:7018214",
        "tgn:7002435",
        "tgn:7029392"
    ],
    "tgn:id":1058075,
    "tgn:name":"Ostrov'anskij",
    "tgn:placetype":[
        "aat:300008347"
    ]
},
  "bbox": [],
  "geometry": {"coordinates":[42.2167,46.75],"type":"Point"}
}