{
  "id": 2448302,
  "type": "Feature",
  "properties": {
    "tgn:hierarchy":[
        "tgn:2448302",
        "tgn:1000001",
        "tgn:7012149",
        "tgn:1002357",
        "tgn:7007706",
        "tgn:7029392"
    ],
    "tgn:id":2448302,
    "tgn:name":"Liles Ditch",
    "tgn:placetype":[
        "aat:300006075"
    ]
},
  "bbox": [],
  "geometry": {"coordinates":[-82.7333,41.3833],"type":"Point"}
}