{
  "id": 2402566,
  "type": "Feature",
  "properties": {
    "tgn:hierarchy":[
        "tgn:2402566",
        "tgn:2002101",
        "tgn:1000001",
        "tgn:7012149",
        "tgn:7007827",
        "tgn:7029392"
    ],
    "tgn:id":2402566,
    "tgn:name":"Hospital Spring",
    "tgn:placetype":[
        "aat:300008697"
    ]
},
  "bbox": [],
  "geometry": {"coordinates":[-113.5333,38.3333],"type":"Point"}
}