{
  "id": 2715532,
  "type": "Feature",
  "properties": {
    "tgn:hierarchy":[
        "tgn:2715532",
        "tgn:1000001",
        "tgn:7012149",
        "tgn:1002598",
        "tgn:7007523",
        "tgn:7029392"
    ],
    "tgn:id":2715532,
    "tgn:name":"Terrell Lake",
    "tgn:placetype":[
        "aat:300006191"
    ]
},
  "bbox": [],
  "geometry": {"coordinates":[-90.85,39.0667],"type":"Point"}
}