{
  "id": 7533499,
  "type": "Feature",
  "properties": {
    "tgn:hierarchy":[
        "tgn:7533499",
        "tgn:7001242",
        "tgn:7016833",
        "tgn:1001418",
        "tgn:7029392"
    ],
    "tgn:id":7533499,
    "tgn:name:en":"Lorgiba, Gebel",
    "tgn:placetype":[
        "aat:300008777"
    ]
},
  "bbox": [],
  "geometry": {"coordinates":[26.690415,28.762919],"type":"Point"}
}