{
  "id": 2033934,
  "type": "Feature",
  "properties": {
    "tgn:hierarchy":[
        "tgn:2033934",
        "tgn:1000001",
        "tgn:7012149",
        "tgn:1002579",
        "tgn:7007252",
        "tgn:7029392"
    ],
    "tgn:id":2033934,
    "tgn:name":"Tunnelton",
    "tgn:placetype":[
        "aat:300008347"
    ]
},
  "bbox": [],
  "geometry": {"coordinates":[-86.3333,38.7667],"type":"Point"}
}