{
  "id": 7149760,
  "type": "Feature",
  "properties": {
    "tgn:hierarchy":[
        "tgn:7149760",
        "tgn:1000003",
        "tgn:7003685",
        "tgn:7000084",
        "tgn:7029392"
    ],
    "tgn:id":7149760,
    "tgn:name":"K\u00fchnitzsch",
    "tgn:placetype":[
        "aat:300008347"
    ]
},
  "bbox": [],
  "geometry": {"coordinates":[12.833333,51.383333],"type":"Point"}
}