{
  "id": 7165228,
  "type": "Feature",
  "properties": {
    "tgn:hierarchy":[
        "tgn:7165228",
        "tgn:7003669",
        "tgn:1000003",
        "tgn:7000084",
        "tgn:7029392"
    ],
    "tgn:id":7165228,
    "tgn:name":"Hundham",
    "tgn:placetype":[
        "aat:300000206"
    ]
},
  "bbox": [],
  "geometry": {"coordinates":[12.366667,48.516667],"type":"Point"}
}