{
  "id": 1070269,
  "type": "Feature",
  "properties": {
    "tgn:hierarchy":[
        "tgn:1070269",
        "tgn:1000004",
        "tgn:7002082",
        "tgn:1000111",
        "tgn:7029392"
    ],
    "tgn:id":1070269,
    "tgn:name":"Madang",
    "tgn:placetype":[
        "aat:300008347"
    ]
},
  "bbox": [],
  "geometry": {"coordinates":[116.65,29.9833],"type":"Point"}
}