{
  "id": 7356848,
  "type": "Feature",
  "properties": {
    "tgn:hierarchy":[
        "tgn:7356848",
        "tgn:1000001",
        "tgn:7005600",
        "tgn:7005560",
        "tgn:7029392"
    ],
    "tgn:id":7356848,
    "tgn:name":"Chac\u00f3n",
    "tgn:placetype":[
        "aat:300008347"
    ]
},
  "bbox": [],
  "geometry": {"coordinates":[-89.033333,20.95],"type":"Point"}
}