{
  "id": 7467754,
  "type": "Feature",
  "properties": {
    "tgn:hierarchy":[
        "tgn:7467754",
        "tgn:1000004",
        "tgn:7489179",
        "tgn:1000141",
        "tgn:7029392"
    ],
    "tgn:id":7467754,
    "tgn:name":"Zhangshu Shan",
    "tgn:placetype":[
        "aat:300008798"
    ]
},
  "bbox": [],
  "geometry": {"coordinates":[121.775833,24.420278],"type":"Point"}
}