{
  "id": 7593622,
  "type": "Feature",
  "properties": {
    "tgn:hierarchy":[
        "tgn:7593622",
        "tgn:1000001",
        "tgn:7004787",
        "tgn:7029392"
    ],
    "tgn:id":7593622,
    "tgn:name":"Tobago",
    "tgn:placetype":[
        "aat:300387064"
    ]
},
  "bbox": [],
  "geometry": {"coordinates":[-60.666,11.25],"type":"Point"}
}