{
  "id": 2554094,
  "type": "Feature",
  "properties": {
    "tgn:hierarchy":[
        "tgn:2554094",
        "tgn:1000001",
        "tgn:7012149",
        "tgn:7007158",
        "tgn:2000242",
        "tgn:7029392"
    ],
    "tgn:id":2554094,
    "tgn:name":"Oak Ridge",
    "tgn:placetype":[
        "aat:300266640"
    ]
},
  "bbox": [],
  "geometry": {"coordinates":[-105.0167,38.0833],"type":"Point"}
}