{
  "id": 2496695,
  "type": "Feature",
  "properties": {
    "tgn:hierarchy":[
        "tgn:2496695",
        "tgn:2001610",
        "tgn:1000001",
        "tgn:7012149",
        "tgn:7007706",
        "tgn:7029392"
    ],
    "tgn:id":2496695,
    "tgn:name":"Matters Pond",
    "tgn:placetype":[
        "aat:300006191"
    ]
},
  "bbox": [],
  "geometry": {"coordinates":[-82.1167,39.3333],"type":"Point"}
}