{
  "id": 2537932,
  "type": "Feature",
  "properties": {
    "tgn:hierarchy":[
        "tgn:2537932",
        "tgn:1000001",
        "tgn:1002949",
        "tgn:7012149",
        "tgn:7007159",
        "tgn:7029392"
    ],
    "tgn:id":2537932,
    "tgn:name":"Nelson Brook",
    "tgn:placetype":[
        "aat:300008699"
    ]
},
  "bbox": [],
  "geometry": {"coordinates":[-72.2833,41.8333],"type":"Point"}
}