{
  "id": 2449250,
  "type": "Feature",
  "properties": {
    "tgn:hierarchy":[
        "tgn:2449250",
        "tgn:1000001",
        "tgn:7012149",
        "tgn:2000553",
        "tgn:7007252",
        "tgn:7029392"
    ],
    "tgn:id":2449250,
    "tgn:name":"Limestone Creek",
    "tgn:placetype":[
        "aat:300008706"
    ]
},
  "bbox": [],
  "geometry": {"coordinates":[-86.8333,39.5667],"type":"Point"}
}