{
  "id": 1097187,
  "type": "Feature",
  "properties": {
    "tgn:hierarchy":[
        "tgn:1097187",
        "tgn:7000490",
        "tgn:1000006",
        "tgn:7001830",
        "tgn:7029392"
    ],
    "tgn:id":1097187,
    "tgn:name":"Jandowae",
    "tgn:placetype":[
        "aat:300008347"
    ]
},
  "bbox": [],
  "geometry": {"coordinates":[151.05,-26.7667],"type":"Point"}
}