{
  "id": 2451052,
  "type": "Feature",
  "properties": {
    "tgn:hierarchy":[
        "tgn:2451052",
        "tgn:1000001",
        "tgn:7012149",
        "tgn:2002252",
        "tgn:7007920",
        "tgn:7029392"
    ],
    "tgn:id":2451052,
    "tgn:name":"Little Alkali Flat Creek",
    "tgn:placetype":[
        "aat:300008706"
    ]
},
  "bbox": [],
  "geometry": {"coordinates":[-117.5833,46.7667],"type":"Point"}
}