{
  "id": 2719266,
  "type": "Feature",
  "properties": {
    "tgn:hierarchy":[
        "tgn:2719266",
        "tgn:1000001",
        "tgn:7012149",
        "tgn:2000277",
        "tgn:7007240",
        "tgn:7029392"
    ],
    "tgn:id":2719266,
    "tgn:name":"Thousandmile Creek",
    "tgn:placetype":[
        "aat:300008706"
    ]
},
  "bbox": [],
  "geometry": {"coordinates":[-82.7333,29.0667],"type":"Point"}
}