{
  "id": 2228114,
  "type": "Feature",
  "properties": {
    "tgn:hierarchy":[
        "tgn:2228114",
        "tgn:1000001",
        "tgn:2001436",
        "tgn:7012149",
        "tgn:7007566",
        "tgn:7029392"
    ],
    "tgn:id":2228114,
    "tgn:name":"Cedar Canyon",
    "tgn:placetype":[
        "aat:300008761"
    ]
},
  "bbox": [],
  "geometry": {"coordinates":[-103.8833,32.1667],"type":"Point"}
}