{
  "id": 7259441,
  "type": "Feature",
  "properties": {
    "tgn:hierarchy":[
        "tgn:7259441",
        "tgn:7003458",
        "tgn:1000003",
        "tgn:1000063",
        "tgn:7018236",
        "tgn:7029392"
    ],
    "tgn:id":7259441,
    "tgn:name":"Wakken",
    "tgn:placetype":[
        "aat:300008347"
    ]
},
  "bbox": [],
  "geometry": {"coordinates":[3.397425,50.933036],"type":"Point"}
}