{
  "id": 2355988,
  "type": "Feature",
  "properties": {
    "tgn:hierarchy":[
        "tgn:2355988",
        "tgn:1002933",
        "tgn:1000001",
        "tgn:7012149",
        "tgn:7007239",
        "tgn:7029392"
    ],
    "tgn:id":2355988,
    "tgn:name":"Goose Pond",
    "tgn:placetype":[
        "aat:300008680"
    ]
},
  "bbox": [],
  "geometry": {"coordinates":[-75.05,38.4833],"type":"Point"}
}