{
  "id": 2622942,
  "type": "Feature",
  "properties": {
    "tgn:hierarchy":[
        "tgn:2622942",
        "tgn:1000001",
        "tgn:2002256",
        "tgn:7012149",
        "tgn:7013961",
        "tgn:7029392"
    ],
    "tgn:id":2622942,
    "tgn:name":"Robinson Run",
    "tgn:placetype":[
        "aat:300008699"
    ]
},
  "bbox": [],
  "geometry": {"coordinates":[-80.5333,38.6333],"type":"Point"}
}