{
  "id": 1053523,
  "type": "Feature",
  "properties": {
    "tgn:hierarchy":[
        "tgn:1053523",
        "tgn:1000004",
        "tgn:7011573",
        "tgn:7018214",
        "tgn:7002435",
        "tgn:7029392"
    ],
    "tgn:id":1053523,
    "tgn:name":"Danki",
    "tgn:placetype":[
        "aat:300008347"
    ]
},
  "bbox": [],
  "geometry": {"coordinates":[37.5667,54.9167],"type":"Point"}
}