{
  "id": 2144869,
  "type": "Feature",
  "properties": {
    "tgn:hierarchy":[
        "tgn:2144869",
        "tgn:1000001",
        "tgn:7012149",
        "tgn:2000181",
        "tgn:7007157",
        "tgn:7029392"
    ],
    "tgn:id":2144869,
    "tgn:name":"Bald Jesse",
    "tgn:placetype":[
        "aat:300008798"
    ]
},
  "bbox": [],
  "geometry": {"coordinates":[-123.8667,40.5333],"type":"Point"}
}