{
  "id": 7560052,
  "type": "Feature",
  "properties": {
    "tgn:hierarchy":[
        "tgn:7560052",
        "tgn:1000004",
        "tgn:7000198",
        "tgn:7016722",
        "tgn:7029392"
    ],
    "tgn:id":7560052,
    "tgn:name:en":"Matiy\u0101rpura",
    "tgn:placetype":[
        "aat:300008347"
    ]
},
  "bbox": [],
  "geometry": {"coordinates":[79.211773,26.905557],"type":"Point"}
}