{
  "id": 7323712,
  "type": "Feature",
  "properties": {
    "tgn:hierarchy":[
        "tgn:7323712",
        "tgn:7002820",
        "tgn:7030216",
        "tgn:1000003",
        "tgn:1000095",
        "tgn:7029392"
    ],
    "tgn:id":7323712,
    "tgn:name":"Riudaura, Riera de",
    "tgn:placetype":[
        "aat:300008699"
    ]
},
  "bbox": [],
  "geometry": {"coordinates":[2.485903,42.21474],"type":"Point"}
}