{
  "id": 7221436,
  "type": "Feature",
  "properties": {
    "tgn:hierarchy":[
        "tgn:7221436",
        "tgn:7011161",
        "tgn:7002674",
        "tgn:1000003",
        "tgn:1000074",
        "tgn:7029392"
    ],
    "tgn:id":7221436,
    "tgn:name":"Kimin\u00e1s",
    "tgn:placetype":[
        "aat:300008798"
    ]
},
  "bbox": [],
  "geometry": {"coordinates":[25.966389,38.506111],"type":"Point"}
}