<<<<<<< HEAD
{
  "id": 7368652,
  "type": "Feature",
  "properties": {
    "tgn:hierarchy":[
        "tgn:7368652",
        "tgn:1000001",
        "tgn:7005589",
        "tgn:7005560",
        "tgn:7029392"
    ],
    "tgn:id":7368652,
    "tgn:name":"Infiernillo, Cerro",
    "tgn:placetype":[
        "aat:300008795"
    ]
},
  "bbox": [],
  "geometry": {"coordinates":[-99.941667,24.518056],"type":"Point"}
}
=======
{"geometry":{"type":"Point","coordinates":[-99.941667,24.518056]},"type":"Feature","properties":{"hierarchy":["tgn:7368652","tgn:1000001","tgn:7005589","tgn:7005560","tgn:7029392"],"placetype":["aat:300008795"],"id":7368652,"name:xx":"Infiernillo, Cerro"}}
>>>>>>> 03f74aca74312dbeaf24d7e61306dd6a786dc3d0
