{
  "id": 7515712,
  "type": "Feature",
  "properties": {
    "tgn:hierarchy":[
        "tgn:7515712",
        "tgn:1009227",
        "tgn:1000226",
        "tgn:7016822",
        "tgn:1000006",
        "tgn:7029392"
    ],
    "tgn:id":7515712,
    "tgn:name:en":"Manukau",
    "tgn:placetype":[
        "aat:300386846"
    ]
},
  "bbox": [],
  "geometry": {"coordinates":[-176.333333,-44.033333],"type":"Point"}
}