{
  "id": 7524770,
  "type": "Feature",
  "properties": {
    "tgn:hierarchy":[
        "tgn:7524770",
        "tgn:7001242",
        "tgn:7016833",
        "tgn:7001335",
        "tgn:7029392"
    ],
    "tgn:id":7524770,
    "tgn:name":"Maz\u0101r",
    "tgn:placetype":[
        "aat:300008347"
    ]
},
  "bbox": [],
  "geometry": {"coordinates":[33.381418,31.040888],"type":"Point"}
}