{
  "id": 2629650,
  "type": "Feature",
  "properties": {
    "tgn:hierarchy":[
        "tgn:2629650",
        "tgn:1000001",
        "tgn:7012149",
        "tgn:2000388",
        "tgn:7007248",
        "tgn:7029392"
    ],
    "tgn:id":2629650,
    "tgn:name":"Ross",
    "tgn:placetype":[
        "aat:300008347"
    ]
},
  "bbox": [],
  "geometry": {"coordinates":[-83.0667,34.0333],"type":"Point"}
}