{
  "id": 2586745,
  "type": "Feature",
  "properties": {
    "tgn:hierarchy":[
        "tgn:2586745",
        "tgn:1000001",
        "tgn:7012149",
        "tgn:2000491",
        "tgn:7007250",
        "tgn:7029392"
    ],
    "tgn:id":2586745,
    "tgn:name":"Placer Creek",
    "tgn:placetype":[
        "aat:300008706"
    ]
},
  "bbox": [],
  "geometry": {"coordinates":[-115.1833,46.95],"type":"Point"}
}