{
  "id": 7530724,
  "type": "Feature",
  "properties": {
    "tgn:hierarchy":[
        "tgn:7530724",
        "tgn:7001242",
        "tgn:7016833",
        "tgn:1001335",
        "tgn:7029392"
    ],
    "tgn:id":7530724,
    "tgn:name:en":"Tir'at ash Sharq\u0101w\u012byah",
    "tgn:placetype":[
        "aat:300006075"
    ]
},
  "bbox": [],
  "geometry": {"coordinates":[31.172678,31.163516],"type":"Point"}
}