{
  "id": 2515327,
  "type": "Feature",
  "properties": {
    "tgn:hierarchy":[
        "tgn:2515327",
        "tgn:2000942",
        "tgn:1000001",
        "tgn:7012149",
        "tgn:7007520",
        "tgn:7029392"
    ],
    "tgn:id":2515327,
    "tgn:name":"Millikin Lake",
    "tgn:placetype":[
        "aat:300008680"
    ]
},
  "bbox": [],
  "geometry": {"coordinates":[-83.3833,44.7333],"type":"Point"}
}