{
  "id": 7222971,
  "type": "Feature",
  "properties": {
    "tgn:hierarchy":[
        "tgn:7222971",
        "tgn:7002681",
        "tgn:7001395",
        "tgn:1000003",
        "tgn:1000074",
        "tgn:7029392"
    ],
    "tgn:id":7222971,
    "tgn:name":"Playi\u00e1",
    "tgn:placetype":[
        "aat:300008347"
    ]
},
  "bbox": [],
  "geometry": {"coordinates":[24.383333,38.15],"type":"Point"}
}