{
  "id": 7365474,
  "type": "Feature",
  "properties": {
    "tgn:hierarchy":[
        "tgn:7365474",
        "tgn:1000001",
        "tgn:7005591",
        "tgn:7005560",
        "tgn:7029392"
    ],
    "tgn:id":7365474,
    "tgn:name:es":"Fresnillo de Trujano",
    "tgn:placetype":[
        "aat:300008347"
    ]
},
  "bbox": [],
  "geometry": {"coordinates":[-98.125,17.946667],"type":"Point"}
}