{
  "id": 2134307,
  "type": "Feature",
  "properties": {
    "tgn:hierarchy":[
        "tgn:2134307",
        "tgn:1000001",
        "tgn:7012149",
        "tgn:1002645",
        "tgn:7007920",
        "tgn:7029392"
    ],
    "tgn:id":2134307,
    "tgn:name":"Annas Bay",
    "tgn:placetype":[
        "aat:300132316"
    ]
},
  "bbox": [],
  "geometry": {"coordinates":[-123.1333,47.35],"type":"Point"}
}