<<<<<<< HEAD
{
  "id": 2767973,
  "type": "Feature",
  "properties": {
    "tgn:hierarchy":[
        "tgn:2767973",
        "tgn:1000001",
        "tgn:7012149",
        "tgn:7007825",
        "tgn:7029392"
    ],
    "tgn:id":2767973,
    "tgn:name":"Whiteoak Branch",
    "tgn:placetype":[
        "aat:300008699"
    ]
},
  "bbox": [],
  "geometry": {"coordinates":[-85.1,36.2],"type":"Point"}
}
=======
{"geometry":{"type":"Point","coordinates":[-85.100000,36.200000]},"type":"Feature","properties":{"hierarchy":["tgn:2767973","tgn:1000001","tgn:7012149","tgn:7007825","tgn:7029392"],"placetype":["aat:300008699"],"id":2767973,"name:xx":"Whiteoak Branch"}}
>>>>>>> 03f74aca74312dbeaf24d7e61306dd6a786dc3d0
