{
  "id": 2712448,
  "type": "Feature",
  "properties": {
    "tgn:hierarchy":[
        "tgn:2712448",
        "tgn:1000001",
        "tgn:7012149",
        "tgn:7007157",
        "tgn:1002956",
        "tgn:7029392"
    ],
    "tgn:id":2712448,
    "tgn:name":"Tawny Point",
    "tgn:placetype":[
        "aat:300008798"
    ]
},
  "bbox": [],
  "geometry": {"coordinates":[-118.3667,36.6167],"type":"Point"}
}