{
  "id": 2495675,
  "type": "Feature",
  "properties": {
    "tgn:hierarchy":[
        "tgn:2495675",
        "tgn:1000001",
        "tgn:7016172",
        "tgn:7012149",
        "tgn:2000129",
        "tgn:7029392"
    ],
    "tgn:id":2495675,
    "tgn:name":"Mashie Hollow",
    "tgn:placetype":[
        "aat:300008761"
    ]
},
  "bbox": [],
  "geometry": {"coordinates":[-91.9833,36.4167],"type":"Point"}
}