{
  "id": 2736975,
  "type": "Feature",
  "properties": {
    "tgn:hierarchy":[
        "tgn:2736975",
        "tgn:1000001",
        "tgn:7012149",
        "tgn:7014589",
        "tgn:7007515",
        "tgn:7029392"
    ],
    "tgn:id":2736975,
    "tgn:name":"Two Hour Rock",
    "tgn:placetype":[
        "aat:300008791"
    ]
},
  "bbox": [],
  "geometry": {"coordinates":[-67.1167,44.9167],"type":"Point"}
}