{
  "id": 7482039,
  "type": "Feature",
  "properties": {
    "tgn:hierarchy":[
        "tgn:7482039",
        "tgn:1000004",
        "tgn:7492971",
        "tgn:1000141",
        "tgn:7029392"
    ],
    "tgn:id":7482039,
    "tgn:name":"Linzhi",
    "tgn:placetype":[
        "aat:300000745"
    ]
},
  "bbox": [],
  "geometry": {"coordinates":[120.524671,22.651329],"type":"Point"}
}