{
  "id": 7586358,
  "type": "Feature",
  "properties": {
    "tgn:hierarchy":[
        "tgn:7586358",
        "tgn:1000004",
        "tgn:7000198",
        "tgn:1001977",
        "tgn:7029392"
    ],
    "tgn:id":7586358,
    "tgn:name:en":"Chakapara",
    "tgn:placetype":[
        "aat:300008347"
    ]
},
  "bbox": [],
  "geometry": {"coordinates":[88.348611,22.632222],"type":"Point"}
}