{
  "id": 2359613,
  "type": "Feature",
  "properties": {
    "tgn:hierarchy":[
        "tgn:2359613",
        "tgn:1000001",
        "tgn:7012149",
        "tgn:2001201",
        "tgn:7007523",
        "tgn:7029392"
    ],
    "tgn:id":2359613,
    "tgn:name":"Grants Lake",
    "tgn:placetype":[
        "aat:300006191"
    ]
},
  "bbox": [],
  "geometry": {"coordinates":[-93.85,40.3833],"type":"Point"}
}