{
  "id": 7363759,
  "type": "Feature",
  "properties": {
    "tgn:hierarchy":[
        "tgn:7363759",
        "tgn:7005586",
        "tgn:1000001",
        "tgn:7005560",
        "tgn:7029392"
    ],
    "tgn:id":7363759,
    "tgn:name":"El Morisco",
    "tgn:placetype":[
        "aat:300008347"
    ]
},
  "bbox": [],
  "geometry": {"coordinates":[-102.516667,21.283333],"type":"Point"}
}