{
  "id": 2387563,
  "type": "Feature",
  "properties": {
    "tgn:hierarchy":[
        "tgn:2387563",
        "tgn:1000001",
        "tgn:7012149",
        "tgn:7007157",
        "tgn:1002863",
        "tgn:7029392"
    ],
    "tgn:id":2387563,
    "tgn:name":"Hi Mountain",
    "tgn:placetype":[
        "aat:300008798"
    ]
},
  "bbox": [],
  "geometry": {"coordinates":[-120.4167,35.25],"type":"Point"}
}