{
  "id": 7313868,
  "type": "Feature",
  "properties": {
    "tgn:hierarchy":[
        "tgn:7313868",
        "tgn:7016598",
        "tgn:1000049",
        "tgn:1000002",
        "tgn:7029392"
    ],
    "tgn:id":7313868,
    "tgn:name":"Lavata, Punta",
    "tgn:placetype":[
        "aat:300386846"
    ]
},
  "bbox": [],
  "geometry": {"coordinates":[-70.666667,-25.666667],"type":"Point"}
}