{
  "id": 7193544,
  "type": "Feature",
  "properties": {
    "tgn:hierarchy":[
        "tgn:7193544",
        "tgn:7003669",
        "tgn:1000003",
        "tgn:7000084",
        "tgn:7029392"
    ],
    "tgn:id":7193544,
    "tgn:name":"Frankenwinheim",
    "tgn:placetype":[
        "aat:300008347"
    ]
},
  "bbox": [],
  "geometry": {"coordinates":[10.316667,49.883333],"type":"Point"}
}