{
  "id": 1007686,
  "type": "Feature",
  "properties": {
    "tgn:hierarchy":[
        "tgn:1007686",
        "tgn:1010234",
        "tgn:7016730",
        "tgn:1000006",
        "tgn:7029392"
    ],
    "tgn:id":1007686,
    "tgn:name":"Kili",
    "tgn:placetype":[
        "aat:300008791"
    ]
},
  "bbox": [],
  "geometry": {"coordinates":[169.0833,5.6667],"type":"Point"}
}