<<<<<<< HEAD
{
  "id": 2334768,
  "type": "Feature",
  "properties": {
    "tgn:hierarchy":[
        "tgn:2334768",
        "tgn:1000001",
        "tgn:7012149",
        "tgn:2002264",
        "tgn:7013961",
        "tgn:7029392"
    ],
    "tgn:id":2334768,
    "tgn:name":"Fork Mountain",
    "tgn:placetype":[
        "aat:300008798"
    ]
},
  "bbox": [],
  "geometry": {"coordinates":[-80.3833,38.1833],"type":"Point"}
}
=======
{"geometry":{"type":"Point","coordinates":[-80.383300,38.183300]},"type":"Feature","properties":{"hierarchy":["tgn:2334768","tgn:1000001","tgn:7012149","tgn:2002264","tgn:7013961","tgn:7029392"],"placetype":["aat:300008798"],"id":2334768,"name:xx":"Fork Mountain"}}
>>>>>>> 03f74aca74312dbeaf24d7e61306dd6a786dc3d0
