<<<<<<< HEAD
{
  "id": 2256866,
  "type": "Feature",
  "properties": {
    "tgn:hierarchy":[
        "tgn:2256866",
        "tgn:1000001",
        "tgn:7012149",
        "tgn:2001456",
        "tgn:7007566",
        "tgn:7029392"
    ],
    "tgn:id":2256866,
    "tgn:name":"Corkscrew Canyon",
    "tgn:placetype":[
        "aat:300008761"
    ]
},
  "bbox": [],
  "geometry": {"coordinates":[-107.4,34.25],"type":"Point"}
}
=======
{"geometry":{"type":"Point","coordinates":[-107.400000,34.250000]},"type":"Feature","properties":{"hierarchy":["tgn:2256866","tgn:1000001","tgn:7012149","tgn:2001456","tgn:7007566","tgn:7029392"],"placetype":["aat:300008761"],"id":2256866,"name:xx":"Corkscrew Canyon"}}
>>>>>>> 03f74aca74312dbeaf24d7e61306dd6a786dc3d0
