{
  "id": 2125175,
  "type": "Feature",
  "properties": {
    "tgn:hierarchy":[
        "tgn:2125175",
        "tgn:1000001",
        "tgn:7006451",
        "tgn:7012149",
        "tgn:2000099",
        "tgn:7029392"
    ],
    "tgn:id":2125175,
    "tgn:name":"Accord Tank",
    "tgn:placetype":[
        "aat:300006191"
    ]
},
  "bbox": [],
  "geometry": {"coordinates":[-109.9167,34.25],"type":"Point"}
}