{
  "id": 7545582,
  "type": "Feature",
  "properties": {
    "tgn:hierarchy":[
        "tgn:7545582",
        "tgn:1000004",
        "tgn:7018318",
        "tgn:7000198",
        "tgn:7029392"
    ],
    "tgn:id":7545582,
    "tgn:name:en":"Ambora",
    "tgn:placetype":[
        "aat:300008347"
    ]
},
  "bbox": [],
  "geometry": {"coordinates":[73.983333,15.316667],"type":"Point"}
}