{
  "id": 7452939,
  "type": "Feature",
  "properties": {
    "tgn:hierarchy":[
        "tgn:7452939",
        "tgn:7002448",
        "tgn:7019157",
        "tgn:1000003",
        "tgn:7008591",
        "tgn:7029392"
    ],
    "tgn:id":7452939,
    "tgn:name:en":"Doon Point",
    "tgn:placetype":[
        "aat:300386846"
    ]
},
  "bbox": [],
  "geometry": {"coordinates":[-6.183333,55.266667],"type":"Point"}
}