{
  "id": 2564742,
  "type": "Feature",
  "properties": {
    "tgn:hierarchy":[
        "tgn:2564742",
        "tgn:7006450",
        "tgn:1000001",
        "tgn:7012149",
        "tgn:2000089",
        "tgn:7029392"
    ],
    "tgn:id":2564742,
    "tgn:name":"Paddle Mountain",
    "tgn:placetype":[
        "aat:300008798"
    ]
},
  "bbox": [],
  "geometry": {"coordinates":[-145.6833,68.1333],"type":"Point"}
}