{
  "id": 7484472,
  "type": "Feature",
  "properties": {
    "tgn:hierarchy":[
        "tgn:7484472",
        "tgn:1000004",
        "tgn:7001009",
        "tgn:1000141",
        "tgn:7029392"
    ],
    "tgn:id":7484472,
    "tgn:name":"Qingxiu Qiao",
    "tgn:placetype":[
        "aat:300007836"
    ]
},
  "bbox": [],
  "geometry": {"coordinates":[120.566944,24.270833],"type":"Point"}
}