{
  "id": 2488505,
  "type": "Feature",
  "properties": {
    "tgn:hierarchy":[
        "tgn:2488505",
        "tgn:1000001",
        "tgn:2002108",
        "tgn:7012149",
        "tgn:7007827",
        "tgn:7029392"
    ],
    "tgn:id":2488505,
    "tgn:name":"Mahogany Point",
    "tgn:placetype":[
        "aat:300008798"
    ]
},
  "bbox": [],
  "geometry": {"coordinates":[-111.1667,39.25],"type":"Point"}
}