{
  "id": 2561165,
  "type": "Feature",
  "properties": {
    "tgn:hierarchy":[
        "tgn:2561165",
        "tgn:1000001",
        "tgn:7012149",
        "tgn:1002990",
        "tgn:7007708",
        "tgn:7029392"
    ],
    "tgn:id":2561165,
    "tgn:name":"Ortley",
    "tgn:placetype":[
        "aat:300008347"
    ]
},
  "bbox": [],
  "geometry": {"coordinates":[-121.2833,45.65],"type":"Point"}
}