{
  "id": 2279617,
  "type": "Feature",
  "properties": {
    "tgn:hierarchy":[
        "tgn:2279617",
        "tgn:1000001",
        "tgn:7012149",
        "tgn:2002339",
        "tgn:7007922",
        "tgn:7029392"
    ],
    "tgn:id":2279617,
    "tgn:name":"Deadman Spring",
    "tgn:placetype":[
        "aat:300008697"
    ]
},
  "bbox": [],
  "geometry": {"coordinates":[-88.6833,45.0833],"type":"Point"}
}