{
  "id": 7221608,
  "type": "Feature",
  "properties": {
    "tgn:hierarchy":[
        "tgn:7221608",
        "tgn:7011170",
        "tgn:7002715",
        "tgn:1000003",
        "tgn:1000074",
        "tgn:7029392"
    ],
    "tgn:id":7221608,
    "tgn:name":"Zilot\u00ed",
    "tgn:placetype":[
        "aat:300008347"
    ]
},
  "bbox": [],
  "geometry": {"coordinates":[24.833333,40.933333],"type":"Point"}
}