{
  "id": 2550917,
  "type": "Feature",
  "properties": {
    "tgn:hierarchy":[
        "tgn:2550917",
        "tgn:7013388",
        "tgn:1000001",
        "tgn:7012149",
        "tgn:7007517",
        "tgn:7029392"
    ],
    "tgn:id":2550917,
    "tgn:name":"Notch Brook",
    "tgn:placetype":[
        "aat:300008699"
    ]
},
  "bbox": [],
  "geometry": {"coordinates":[-73.1333,42.6333],"type":"Point"}
}