{
  "id": 2448577,
  "type": "Feature",
  "properties": {
    "tgn:hierarchy":[
        "tgn:2448577",
        "tgn:1000001",
        "tgn:7012149",
        "tgn:2001396",
        "tgn:7007525",
        "tgn:7029392"
    ],
    "tgn:id":2448577,
    "tgn:name":"Lily Lake",
    "tgn:placetype":[
        "aat:300008680"
    ]
},
  "bbox": [],
  "geometry": {"coordinates":[-102.5667,42.0833],"type":"Point"}
}