{
  "id": 2556302,
  "type": "Feature",
  "properties": {
    "tgn:hierarchy":[
        "tgn:2556302",
        "tgn:1000001",
        "tgn:2000321",
        "tgn:7012149",
        "tgn:7007248",
        "tgn:7029392"
    ],
    "tgn:id":2556302,
    "tgn:name":"Oketeyeconne",
    "tgn:placetype":[
        "aat:300008347",
        "aat:300167671"
    ]
},
  "bbox": [],
  "geometry": {"coordinates":[-85.0667,31.6333],"type":"Point"}
}