{
  "id": 7467480,
  "type": "Feature",
  "properties": {
    "tgn:hierarchy":[
        "tgn:7467480",
        "tgn:1000004",
        "tgn:7001013",
        "tgn:1000141",
        "tgn:7029392"
    ],
    "tgn:id":7467480,
    "tgn:name":"Amuping",
    "tgn:placetype":[
        "aat:300008347"
    ]
},
  "bbox": [],
  "geometry": {"coordinates":[121.311808,24.817792],"type":"Point"}
}