{
  "id": 7145247,
  "type": "Feature",
  "properties": {
    "tgn:hierarchy":[
        "tgn:7145247",
        "tgn:1000003",
        "tgn:7003687",
        "tgn:7000084",
        "tgn:7029392"
    ],
    "tgn:id":7145247,
    "tgn:name":"Kolonie Etzdorf",
    "tgn:placetype":[
        "aat:300008347"
    ]
},
  "bbox": [],
  "geometry": {"coordinates":[11.733333,51.433333],"type":"Point"}
}