{
  "id": 7046550,
  "type": "Feature",
  "properties": {
    "tgn:hierarchy":[
        "tgn:7046550",
        "tgn:7004597",
        "tgn:1000003",
        "tgn:7008516",
        "tgn:1000080",
        "tgn:7029392"
    ],
    "tgn:id":7046550,
    "tgn:name":"Calcara",
    "tgn:placetype":[
        "aat:300008347"
    ]
},
  "bbox": [],
  "geometry": {"coordinates":[11.116667,44.55],"type":"Point"}
}