{
  "id": 7279938,
  "type": "Feature",
  "properties": {
    "tgn:hierarchy":[
        "tgn:7279938",
        "tgn:1001702",
        "tgn:1000049",
        "tgn:1000002",
        "tgn:7029392"
    ],
    "tgn:id":7279938,
    "tgn:name":"Richardson, Isla",
    "tgn:placetype":[
        "aat:300008791"
    ]
},
  "bbox": [],
  "geometry": {"coordinates":[-73.45,-53.033333],"type":"Point"}
}