{
  "id": 7507411,
  "type": "Feature",
  "properties": {
    "tgn:hierarchy":[
        "tgn:7507411",
        "tgn:1008380",
        "tgn:1000226",
        "tgn:7018426",
        "tgn:1000006",
        "tgn:7029392"
    ],
    "tgn:id":7507411,
    "tgn:name:en":"Pukehou",
    "tgn:placetype":[
        "aat:300008795"
    ]
},
  "bbox": [],
  "geometry": {"coordinates":[176.016667,-37.766667],"type":"Point"}
}