<<<<<<< HEAD
{
  "id": 2337723,
  "type": "Feature",
  "properties": {
    "tgn:hierarchy":[
        "tgn:2337723",
        "tgn:1000001",
        "tgn:2000469",
        "tgn:7012149",
        "tgn:7007250",
        "tgn:7029392"
    ],
    "tgn:id":2337723,
    "tgn:name":"Fox Creek",
    "tgn:placetype":[
        "aat:300008706"
    ]
},
  "bbox": [],
  "geometry": {"coordinates":[-115.3,46.5833],"type":"Point"}
}
=======
{"geometry":{"type":"Point","coordinates":[-115.300000,46.583300]},"type":"Feature","properties":{"hierarchy":["tgn:2337723","tgn:1000001","tgn:2000469","tgn:7012149","tgn:7007250","tgn:7029392"],"placetype":["aat:300008706"],"id":2337723,"name:xx":"Fox Creek"}}
>>>>>>> 03f74aca74312dbeaf24d7e61306dd6a786dc3d0
