{
  "id": 1061509,
  "type": "Feature",
  "properties": {
    "tgn:hierarchy":[
        "tgn:1061509",
        "tgn:1000004",
        "tgn:1003397",
        "tgn:7018214",
        "tgn:7002435",
        "tgn:7029392"
    ],
    "tgn:id":1061509,
    "tgn:name":"Zalegoshch",
    "tgn:placetype":[
        "aat:300008347"
    ]
},
  "bbox": [],
  "geometry": {"coordinates":[36.8833,52.8667],"type":"Point"}
}