{
  "id": 7291313,
  "type": "Feature",
  "properties": {
    "tgn:hierarchy":[
        "tgn:7291313",
        "tgn:1001637",
        "tgn:1000049",
        "tgn:1000002",
        "tgn:7029392"
    ],
    "tgn:id":7291313,
    "tgn:name":"El Macho, Cerro",
    "tgn:placetype":[
        "aat:300008795"
    ]
},
  "bbox": [],
  "geometry": {"coordinates":[-71.35,-37.316667],"type":"Point"}
}