{
  "id": 7228659,
  "type": "Feature",
  "properties": {
    "tgn:hierarchy":[
        "tgn:7228659",
        "tgn:7002735",
        "tgn:7017076",
        "tgn:1000003",
        "tgn:1000074",
        "tgn:7029392"
    ],
    "tgn:id":7228659,
    "tgn:name":"Kokkali\u00e1ris R\u00e9ma",
    "tgn:placetype":[
        "aat:300008699"
    ]
},
  "bbox": [],
  "geometry": {"coordinates":[22.583333,36.983333],"type":"Point"}
}