{
  "id": 7088079,
  "type": "Feature",
  "properties": {
    "tgn:hierarchy":[
        "tgn:7088079",
        "tgn:1000003",
        "tgn:7003676",
        "tgn:7000084",
        "tgn:7029392"
    ],
    "tgn:id":7088079,
    "tgn:name":"Wam-Bach",
    "tgn:placetype":[
        "aat:300008699"
    ]
},
  "bbox": [],
  "geometry": {"coordinates":[9.95,51.833333],"type":"Point"}
}