{
  "id": 2661163,
  "type": "Feature",
  "properties": {
    "tgn:hierarchy":[
        "tgn:2661163",
        "tgn:1000001",
        "tgn:7012149",
        "tgn:7013961",
        "tgn:7029392"
    ],
    "tgn:id":2661163,
    "tgn:name":"Short Mountain",
    "tgn:placetype":[
        "aat:300008798"
    ]
},
  "bbox": [],
  "geometry": {"coordinates":[-78.7333,39.0833],"type":"Point"}
}