<<<<<<< HEAD
{
  "id": 7374185,
  "type": "Feature",
  "properties": {
    "tgn:hierarchy":[
        "tgn:7374185",
        "tgn:7005583",
        "tgn:1000001",
        "tgn:7005560",
        "tgn:7029392"
    ],
    "tgn:id":7374185,
    "tgn:name":"Rancho Laguna de El Macho",
    "tgn:placetype":[
        "aat:300000241"
    ]
},
  "bbox": [],
  "geometry": {"coordinates":[-106.016667,26.783333],"type":"Point"}
}
=======
{"geometry":{"type":"Point","coordinates":[-106.016667,26.783333]},"type":"Feature","properties":{"hierarchy":["tgn:7374185","tgn:7005583","tgn:1000001","tgn:7005560","tgn:7029392"],"placetype":["aat:300000241"],"id":7374185,"name:xx":"Rancho Laguna de El Macho"}}
>>>>>>> 03f74aca74312dbeaf24d7e61306dd6a786dc3d0
