{
  "id": 7206158,
  "type": "Feature",
  "properties": {
    "tgn:hierarchy":[
        "tgn:7206158",
        "tgn:1000003",
        "tgn:7000094",
        "tgn:7000084",
        "tgn:7029392"
    ],
    "tgn:id":7206158,
    "tgn:name":"Carlshof",
    "tgn:placetype":[
        "aat:300008347"
    ]
},
  "bbox": [],
  "geometry": {"coordinates":[12.533333,53.366667],"type":"Point"}
}