<<<<<<< HEAD
{
  "id": 2253376,
  "type": "Feature",
  "properties": {
    "tgn:hierarchy":[
        "tgn:2253376",
        "tgn:1000001",
        "tgn:2000459",
        "tgn:7012149",
        "tgn:7007250",
        "tgn:7029392"
    ],
    "tgn:id":2253376,
    "tgn:name":"Cony Peak",
    "tgn:placetype":[
        "aat:300008798"
    ]
},
  "bbox": [],
  "geometry": {"coordinates":[-115.05,44.05],"type":"Point"}
}
=======
{"geometry":{"type":"Point","coordinates":[-115.050000,44.050000]},"type":"Feature","properties":{"hierarchy":["tgn:2253376","tgn:1000001","tgn:2000459","tgn:7012149","tgn:7007250","tgn:7029392"],"placetype":["aat:300008798"],"id":2253376,"name:xx":"Cony Peak"}}
>>>>>>> 03f74aca74312dbeaf24d7e61306dd6a786dc3d0
