{
  "id": 2744811,
  "type": "Feature",
  "properties": {
    "tgn:hierarchy":[
        "tgn:2744811",
        "tgn:1000001",
        "tgn:7012149",
        "tgn:1002966",
        "tgn:7007826",
        "tgn:7029392"
    ],
    "tgn:id":2744811,
    "tgn:name":"Victory Branch",
    "tgn:placetype":[
        "aat:300008699"
    ]
},
  "bbox": [],
  "geometry": {"coordinates":[-94.9167,32.5667],"type":"Point"}
}