{
  "id": 2145272,
  "type": "Feature",
  "properties": {
    "tgn:hierarchy":[
        "tgn:2145272",
        "tgn:1000001",
        "tgn:7012149",
        "tgn:2002030",
        "tgn:7007826",
        "tgn:7029392"
    ],
    "tgn:id":2145272,
    "tgn:name":"Bald Mountain Hollow",
    "tgn:placetype":[
        "aat:300008761"
    ]
},
  "bbox": [],
  "geometry": {"coordinates":[-98.65,30.6667],"type":"Point"}
}