{
  "id": 7561645,
  "type": "Feature",
  "properties": {
    "tgn:hierarchy":[
        "tgn:7561645",
        "tgn:1000004",
        "tgn:7000198",
        "tgn:7016722",
        "tgn:7029392"
    ],
    "tgn:id":7561645,
    "tgn:name:en":"R\u0101mpur N\u0101oli",
    "tgn:placetype":[
        "aat:300008347"
    ]
},
  "bbox": [],
  "geometry": {"coordinates":[79.064307,26.772569],"type":"Point"}
}