{
  "id": 2446519,
  "type": "Feature",
  "properties": {
    "tgn:hierarchy":[
        "tgn:2446519",
        "tgn:1000001",
        "tgn:2001184",
        "tgn:7012149",
        "tgn:7007523",
        "tgn:7029392"
    ],
    "tgn:id":2446519,
    "tgn:name":"Lewis Mill",
    "tgn:placetype":[
        "aat:300008347"
    ]
},
  "bbox": [],
  "geometry": {"coordinates":[-92.85,39.25],"type":"Point"}
}