{
  "id": 7022006,
  "type": "Feature",
  "properties": {
    "tgn:hierarchy":[
        "tgn:7022006",
        "tgn:1000001",
        "tgn:1002235",
        "tgn:7012149",
        "tgn:7007919",
        "tgn:7029392"
    ],
    "tgn:id":7022006,
    "tgn:name":"Old Grays Pond",
    "tgn:placetype":[
        "aat:300006191"
    ]
},
  "bbox": [],
  "geometry": {"coordinates":[-77.4167,38.0167],"type":"Point"}
}