{
  "id": 2468260,
  "type": "Feature",
  "properties": {
    "tgn:hierarchy":[
        "tgn:2468260",
        "tgn:2001172",
        "tgn:1000001",
        "tgn:7012149",
        "tgn:7007523",
        "tgn:7029392"
    ],
    "tgn:id":2468260,
    "tgn:name":"Long Mound",
    "tgn:placetype":[
        "aat:300008798"
    ]
},
  "bbox": [],
  "geometry": {"coordinates":[-94.2667,38.3333],"type":"Point"}
}