{
  "id": 2214745,
  "type": "Feature",
  "properties": {
    "tgn:hierarchy":[
        "tgn:2214745",
        "tgn:1000001",
        "tgn:7012149",
        "tgn:1002742",
        "tgn:7007920",
        "tgn:7029392"
    ],
    "tgn:id":2214745,
    "tgn:name":"Calf Creek",
    "tgn:placetype":[
        "aat:300008706"
    ]
},
  "bbox": [],
  "geometry": {"coordinates":[-120.3167,48.6167],"type":"Point"}
}