{
  "id": 2686466,
  "type": "Feature",
  "properties": {
    "tgn:hierarchy":[
        "tgn:2686466",
        "tgn:1000001",
        "tgn:2001261",
        "tgn:7012149",
        "tgn:7007524",
        "tgn:7029392"
    ],
    "tgn:id":2686466,
    "tgn:name":"Spring Creek",
    "tgn:placetype":[
        "aat:300008706"
    ]
},
  "bbox": [],
  "geometry": {"coordinates":[-107.5833,45.0167],"type":"Point"}
}