{
  "id": 2365748,
  "type": "Feature",
  "properties": {
    "tgn:hierarchy":[
        "tgn:2365748",
        "tgn:1000001",
        "tgn:7012149",
        "tgn:7014128",
        "tgn:7007709",
        "tgn:7029392"
    ],
    "tgn:id":2365748,
    "tgn:name":"Gregory Lake",
    "tgn:placetype":[
        "aat:300006191"
    ]
},
  "bbox": [],
  "geometry": {"coordinates":[-78.7167,36.4333],"type":"Point"}
}