{
  "id": 2553805,
  "type": "Feature",
  "properties": {
    "tgn:hierarchy":[
        "tgn:2553805",
        "tgn:1000001",
        "tgn:7012149",
        "tgn:2001901",
        "tgn:7007825",
        "tgn:7029392"
    ],
    "tgn:id":2553805,
    "tgn:name":"Oak Hill",
    "tgn:placetype":[
        "aat:300008347"
    ]
},
  "bbox": [],
  "geometry": {"coordinates":[-84.5167,36.1667],"type":"Point"}
}