{
  "id": 7081374,
  "type": "Feature",
  "properties": {
    "tgn:hierarchy":[
        "tgn:7081374",
        "tgn:1000003",
        "tgn:7003677",
        "tgn:7000084",
        "tgn:7029392"
    ],
    "tgn:id":7081374,
    "tgn:name":"Xanten",
    "tgn:placetype":[
        "aat:300008347"
    ]
},
  "bbox": [],
  "geometry": {"coordinates":[6.45,51.666667],"type":"Point"}
}