{
  "id": 2106924,
  "type": "Feature",
  "properties": {
    "tgn:hierarchy":[
        "tgn:2106924",
        "tgn:1000001",
        "tgn:7012149",
        "tgn:2001993",
        "tgn:7007826",
        "tgn:7029392"
    ],
    "tgn:id":2106924,
    "tgn:name":"Pottsboro",
    "tgn:placetype":[
        "aat:300008347"
    ]
},
  "bbox": [],
  "geometry": {"coordinates":[-96.6667,33.75],"type":"Point"}
}