{
  "id": 7268771,
  "type": "Feature",
  "properties": {
    "tgn:hierarchy":[
        "tgn:7268771",
        "tgn:1000003",
        "tgn:7003613",
        "tgn:7016845",
        "tgn:7029392"
    ],
    "tgn:id":7268771,
    "tgn:name:nl":"Rottumerbult",
    "tgn:placetype":[
        "aat:300387036"
    ]
},
  "bbox": [],
  "geometry": {"coordinates":[6.416667,53.583333],"type":"Point"}
}