{
  "id": 7020553,
  "type": "Feature",
  "properties": {
    "tgn:hierarchy":[
        "tgn:7020553",
        "tgn:1000001",
        "tgn:7012149",
        "tgn:2001284",
        "tgn:7007524",
        "tgn:7029392"
    ],
    "tgn:id":7020553,
    "tgn:name":"Twin Buttes Creek",
    "tgn:placetype":[
        "aat:300008706"
    ]
},
  "bbox": [],
  "geometry": {"coordinates":[-112.5167,47.2167],"type":"Point"}
}