{
  "id": 7040838,
  "type": "Feature",
  "properties": {
    "tgn:hierarchy":[
        "tgn:7040838",
        "tgn:7003136",
        "tgn:1000003",
        "tgn:7003080",
        "tgn:1000080",
        "tgn:7029392"
    ],
    "tgn:id":7040838,
    "tgn:name":"Santo Stefano, Monte",
    "tgn:placetype":[
        "aat:300008795"
    ]
},
  "bbox": [],
  "geometry": {"coordinates":[13.283333,41.333333],"type":"Point"}
}