{
  "id": 2211917,
  "type": "Feature",
  "properties": {
    "tgn:hierarchy":[
        "tgn:2211917",
        "tgn:1000001",
        "tgn:1002480",
        "tgn:7012149",
        "tgn:7007564",
        "tgn:7029392"
    ],
    "tgn:id":2211917,
    "tgn:name":"Buxton Brook",
    "tgn:placetype":[
        "aat:300008699"
    ]
},
  "bbox": [],
  "geometry": {"coordinates":[-71.7667,43.0333],"type":"Point"}
}