{
  "id": 1057064,
  "type": "Feature",
  "properties": {
    "tgn:hierarchy":[
        "tgn:1057064",
        "tgn:1000004",
        "tgn:1003404",
        "tgn:7018214",
        "tgn:7002435",
        "tgn:7029392"
    ],
    "tgn:id":1057064,
    "tgn:name":"Mozhary",
    "tgn:placetype":[
        "aat:300008347"
    ]
},
  "bbox": [],
  "geometry": {"coordinates":[41.0333,53.8833],"type":"Point"}
}