{
  "id": 2640467,
  "type": "Feature",
  "properties": {
    "tgn:hierarchy":[
        "tgn:2640467",
        "tgn:1000001",
        "tgn:2001941",
        "tgn:7012149",
        "tgn:7007826",
        "tgn:7029392"
    ],
    "tgn:id":2640467,
    "tgn:name":"San Jose",
    "tgn:placetype":[
        "aat:300008347"
    ]
},
  "bbox": [],
  "geometry": {"coordinates":[-98.5167,29.3333],"type":"Point"}
}