{
  "id": 2050901,
  "type": "Feature",
  "properties": {
    "tgn:hierarchy":[
        "tgn:2050901",
        "tgn:1000001",
        "tgn:7014423",
        "tgn:7012149",
        "tgn:7007517",
        "tgn:7029392"
    ],
    "tgn:id":2050901,
    "tgn:name":"West Hanover",
    "tgn:placetype":[
        "aat:300008347"
    ]
},
  "bbox": [],
  "geometry": {"coordinates":[-70.8833,42.1167],"type":"Point"}
}