<<<<<<< HEAD
{
  "id": 7485281,
  "type": "Feature",
  "properties": {
    "tgn:hierarchy":[
        "tgn:7485281",
        "tgn:1000004",
        "tgn:7492971",
        "tgn:1000141",
        "tgn:7029392"
    ],
    "tgn:id":7485281,
    "tgn:name":"Fenglin Guoxiao",
    "tgn:placetype":[
        "aat:300006495"
    ]
},
  "bbox": [],
  "geometry": {"coordinates":[120.707222,22.2],"type":"Point"}
}
=======
{"geometry":{"type":"Point","coordinates":[120.707222,22.200000]},"type":"Feature","properties":{"hierarchy":["tgn:7485281","tgn:1000004","tgn:7492971","tgn:1000141","tgn:7029392"],"placetype":["aat:300006495"],"id":7485281,"name:xx":"Fenglin Guoxiao"}}
>>>>>>> 03f74aca74312dbeaf24d7e61306dd6a786dc3d0
