{
  "id": 7420362,
  "type": "Feature",
  "properties": {
    "tgn:hierarchy":[
        "tgn:7420362",
        "tgn:1001836",
        "tgn:1000001",
        "tgn:7005560",
        "tgn:7029392"
    ],
    "tgn:id":7420362,
    "tgn:name":"Los Corrales, Sierra",
    "tgn:placetype":[
        "aat:300008795"
    ]
},
  "bbox": [],
  "geometry": {"coordinates":[-111.171667,25.609167],"type":"Point"}
}