{
  "id": 7131566,
  "type": "Feature",
  "properties": {
    "tgn:hierarchy":[
        "tgn:7131566",
        "tgn:7003692",
        "tgn:1000003",
        "tgn:7000084",
        "tgn:7029392"
    ],
    "tgn:id":7131566,
    "tgn:name":"Mittelberg",
    "tgn:placetype":[
        "aat:300008795"
    ]
},
  "bbox": [],
  "geometry": {"coordinates":[9.183333,48.383333],"type":"Point"}
}