{
  "id": 7213659,
  "type": "Feature",
  "properties": {
    "tgn:hierarchy":[
        "tgn:7213659",
        "tgn:1000003",
        "tgn:7003688",
        "tgn:7000084",
        "tgn:7029392"
    ],
    "tgn:id":7213659,
    "tgn:name":"Blunker See",
    "tgn:placetype":[
        "aat:300008680"
    ]
},
  "bbox": [],
  "geometry": {"coordinates":[10.333333,54.016667],"type":"Point"}
}