{
  "id": 2639114,
  "type": "Feature",
  "properties": {
    "tgn:hierarchy":[
        "tgn:2639114",
        "tgn:1000001",
        "tgn:7012149",
        "tgn:7007157",
        "tgn:2000190",
        "tgn:7029392"
    ],
    "tgn:id":2639114,
    "tgn:name":"Salt Lick",
    "tgn:placetype":[
        "aat:300008697"
    ]
},
  "bbox": [],
  "geometry": {"coordinates":[-122.7167,40.15],"type":"Point"}
}