{
  "id": 2509491,
  "type": "Feature",
  "properties": {
    "tgn:hierarchy":[
        "tgn:2509491",
        "tgn:1000001",
        "tgn:7012149",
        "tgn:2002374",
        "tgn:7007923",
        "tgn:7029392"
    ],
    "tgn:id":2509491,
    "tgn:name":"Middle Fork Trabing Dry Creek",
    "tgn:placetype":[
        "aat:300008706"
    ]
},
  "bbox": [],
  "geometry": {"coordinates":[-106.4667,43.9333],"type":"Point"}
}