{
  "id": 2606932,
  "type": "Feature",
  "properties": {
    "tgn:hierarchy":[
        "tgn:2606932",
        "tgn:1000001",
        "tgn:7012149",
        "tgn:7007251",
        "tgn:7029392"
    ],
    "tgn:id":2606932,
    "tgn:name":"Ranbarger Hollow",
    "tgn:placetype":[
        "aat:300008761"
    ]
},
  "bbox": [],
  "geometry": {"coordinates":[-89.3667,37.55],"type":"Point"}
}