{
  "id": 7151161,
  "type": "Feature",
  "properties": {
    "tgn:hierarchy":[
        "tgn:7151161",
        "tgn:1000003",
        "tgn:7003689",
        "tgn:7000084",
        "tgn:7029392"
    ],
    "tgn:id":7151161,
    "tgn:name":"Kanzel",
    "tgn:placetype":[
        "aat:300011692"
    ]
},
  "bbox": [],
  "geometry": {"coordinates":[10.016667,50.683333],"type":"Point"}
}