{
  "id": 7252191,
  "type": "Feature",
  "properties": {
    "tgn:hierarchy":[
        "tgn:7252191",
        "tgn:7003457",
        "tgn:1000003",
        "tgn:1000063",
        "tgn:7018236",
        "tgn:7029392"
    ],
    "tgn:id":7252191,
    "tgn:name":"Meulenbeek",
    "tgn:placetype":[
        "aat:300008699"
    ]
},
  "bbox": [],
  "geometry": {"coordinates":[3.685799,50.964707],"type":"Point"}
}