{
  "id": 2345638,
  "type": "Feature",
  "properties": {
    "tgn:hierarchy":[
        "tgn:2345638",
        "tgn:7006450",
        "tgn:1000001",
        "tgn:7012149",
        "tgn:7029392"
    ],
    "tgn:id":2345638,
    "tgn:name":"Garrett Creek",
    "tgn:placetype":[
        "aat:300008706"
    ]
},
  "bbox": [],
  "geometry": {"coordinates":[-145.8167,63.1167],"type":"Point"}
}