{
  "id": 7133893,
  "type": "Feature",
  "properties": {
    "tgn:hierarchy":[
        "tgn:7133893",
        "tgn:1000003",
        "tgn:7003678",
        "tgn:7000084",
        "tgn:7029392"
    ],
    "tgn:id":7133893,
    "tgn:name":"M\u00fchl-Berg",
    "tgn:placetype":[
        "aat:300008777"
    ]
},
  "bbox": [],
  "geometry": {"coordinates":[9.533333,50.433333],"type":"Point"}
}