{
  "id": 2069388,
  "type": "Feature",
  "properties": {
    "tgn:hierarchy":[
        "tgn:2069388",
        "tgn:1000001",
        "tgn:7012149",
        "tgn:1002821",
        "tgn:7007568",
        "tgn:7029392"
    ],
    "tgn:id":2069388,
    "tgn:name":"Glass Lake",
    "tgn:placetype":[
        "aat:300008347"
    ]
},
  "bbox": [],
  "geometry": {"coordinates":[-73.5167,42.6167],"type":"Point"}
}