{
  "id": 7358691,
  "type": "Feature",
  "properties": {
    "tgn:hierarchy":[
        "tgn:7358691",
        "tgn:7005578",
        "tgn:1000001",
        "tgn:7005560",
        "tgn:7029392"
    ],
    "tgn:id":7358691,
    "tgn:name":"Desempe\u00f1o",
    "tgn:placetype":[
        "aat:300008347"
    ]
},
  "bbox": [],
  "geometry": {"coordinates":[-90.283333,19.15],"type":"Point"}
}