{
  "id": 2465045,
  "type": "Feature",
  "properties": {
    "tgn:hierarchy":[
        "tgn:2465045",
        "tgn:1000001",
        "tgn:7012149",
        "tgn:2000903",
        "tgn:7007256",
        "tgn:7029392"
    ],
    "tgn:id":2465045,
    "tgn:name":"Loin, Bayou",
    "tgn:placetype":[
        "aat:300008699"
    ]
},
  "bbox": [],
  "geometry": {"coordinates":[-91.7167,30.2833],"type":"Point"}
}