{
  "id": 7562197,
  "type": "Feature",
  "properties": {
    "tgn:hierarchy":[
        "tgn:7562197",
        "tgn:1000004",
        "tgn:7000198",
        "tgn:7016722",
        "tgn:7029392"
    ],
    "tgn:id":7562197,
    "tgn:name:en":"Nagla R\u0101ml\u0101l",
    "tgn:placetype":[
        "aat:300008347"
    ]
},
  "bbox": [],
  "geometry": {"coordinates":[79.206871,26.791174],"type":"Point"}
}