{
  "id": 2070382,
  "type": "Feature",
  "properties": {
    "tgn:hierarchy":[
        "tgn:2070382",
        "tgn:1000001",
        "tgn:7012149",
        "tgn:1002747",
        "tgn:7007568",
        "tgn:7029392"
    ],
    "tgn:id":2070382,
    "tgn:name":"Manchester",
    "tgn:placetype":[
        "aat:300008347"
    ]
},
  "bbox": [],
  "geometry": {"coordinates":[-77.2167,42.9667],"type":"Point"}
}