{
  "id": 2268674,
  "type": "Feature",
  "properties": {
    "tgn:hierarchy":[
        "tgn:2268674",
        "tgn:2000090",
        "tgn:1000001",
        "tgn:7006451",
        "tgn:7012149",
        "tgn:7029392"
    ],
    "tgn:id":2268674,
    "tgn:name":"Cross Canyon",
    "tgn:placetype":[
        "aat:300008761"
    ]
},
  "bbox": [],
  "geometry": {"coordinates":[-109.3667,35.65],"type":"Point"}
}