{
  "id": 7420490,
  "type": "Feature",
  "properties": {
    "tgn:hierarchy":[
        "tgn:7420490",
        "tgn:7005584",
        "tgn:1000001",
        "tgn:7005560",
        "tgn:7029392"
    ],
    "tgn:id":7420490,
    "tgn:name":"El Toreador de Abajo",
    "tgn:placetype":[
        "aat:300008347"
    ]
},
  "bbox": [],
  "geometry": {"coordinates":[-100.545556,21.325833],"type":"Point"}
}