{
  "id": 2739881,
  "type": "Feature",
  "properties": {
    "tgn:hierarchy":[
        "tgn:2739881",
        "tgn:1000001",
        "tgn:2001009",
        "tgn:7012149",
        "tgn:7007521",
        "tgn:7029392"
    ],
    "tgn:id":2739881,
    "tgn:name":"Upper Fifth Lake",
    "tgn:placetype":[
        "aat:300008680"
    ]
},
  "bbox": [],
  "geometry": {"coordinates":[-94.6167,47.05],"type":"Point"}
}