{
  "id": 2355961,
  "type": "Feature",
  "properties": {
    "tgn:hierarchy":[
        "tgn:2355961",
        "tgn:1000001",
        "tgn:2000939",
        "tgn:7012149",
        "tgn:7007516",
        "tgn:7029392"
    ],
    "tgn:id":2355961,
    "tgn:name":"Goose Point",
    "tgn:placetype":[
        "aat:300008850"
    ]
},
  "bbox": [],
  "geometry": {"coordinates":[-75.9833,38.5833],"type":"Point"}
}