{
  "id": 2702687,
  "type": "Feature",
  "properties": {
    "tgn:hierarchy":[
        "tgn:2702687",
        "tgn:2000944",
        "tgn:1000001",
        "tgn:7012149",
        "tgn:7007520",
        "tgn:7029392"
    ],
    "tgn:id":2702687,
    "tgn:name":"Sulphur Island",
    "tgn:placetype":[
        "aat:300008791"
    ]
},
  "bbox": [],
  "geometry": {"coordinates":[-83.4167,44.9833],"type":"Point"}
}