{
  "id": 7362193,
  "type": "Feature",
  "properties": {
    "tgn:hierarchy":[
        "tgn:7362193",
        "tgn:1000001",
        "tgn:1001937",
        "tgn:7005560",
        "tgn:7029392"
    ],
    "tgn:id":7362193,
    "tgn:name":"El Diez",
    "tgn:placetype":[
        "aat:300008347"
    ]
},
  "bbox": [],
  "geometry": {"coordinates":[-87.283333,21.016667],"type":"Point"}
}