{
  "id": 2540871,
  "type": "Feature",
  "properties": {
    "tgn:hierarchy":[
        "tgn:2540871",
        "tgn:1000001",
        "tgn:7012149",
        "tgn:7014600",
        "tgn:7007568",
        "tgn:7029392"
    ],
    "tgn:id":2540871,
    "tgn:name":"Nicholas Point",
    "tgn:placetype":[
        "aat:300008850"
    ]
},
  "bbox": [],
  "geometry": {"coordinates":[-76.95,43.2333],"type":"Point"}
}