{
  "id": 2189234,
  "type": "Feature",
  "properties": {
    "tgn:hierarchy":[
        "tgn:2189234",
        "tgn:7006450",
        "tgn:1000001",
        "tgn:2124077",
        "tgn:7012149",
        "tgn:7029392"
    ],
    "tgn:id":2189234,
    "tgn:name":"Boundary Peak 104",
    "tgn:placetype":[
        "aat:300008798"
    ]
},
  "bbox": [],
  "geometry": {"coordinates":[-134.6667,59.1833],"type":"Point"}
}