{
  "id": 2186961,
  "type": "Feature",
  "properties": {
    "tgn:hierarchy":[
        "tgn:2186961",
        "tgn:1000001",
        "tgn:2000304",
        "tgn:7012149",
        "tgn:7007248",
        "tgn:7029392"
    ],
    "tgn:id":2186961,
    "tgn:name":"Bonnet Lake",
    "tgn:placetype":[
        "aat:300008680"
    ]
},
  "bbox": [],
  "geometry": {"coordinates":[-81.9667,31.2833],"type":"Point"}
}