{
  "id": 2182264,
  "type": "Feature",
  "properties": {
    "tgn:hierarchy":[
        "tgn:2182264",
        "tgn:1000001",
        "tgn:7012149",
        "tgn:2001288",
        "tgn:7007524",
        "tgn:7029392"
    ],
    "tgn:id":2182264,
    "tgn:name":"Blue Paradise Lake",
    "tgn:placetype":[
        "aat:300008680"
    ]
},
  "bbox": [],
  "geometry": {"coordinates":[-111.4333,44.9333],"type":"Point"}
}