{
  "id": 2248718,
  "type": "Feature",
  "properties": {
    "tgn:hierarchy":[
        "tgn:2248718",
        "tgn:1000001",
        "tgn:7012149",
        "tgn:1002794",
        "tgn:7007708",
        "tgn:7029392"
    ],
    "tgn:id":2248718,
    "tgn:name":"Cold Springs",
    "tgn:placetype":[
        "aat:300008697"
    ]
},
  "bbox": [],
  "geometry": {"coordinates":[-123.5167,44.8167],"type":"Point"}
}