{
  "id": 7333248,
  "type": "Feature",
  "properties": {
    "tgn:hierarchy":[
        "tgn:7333248",
        "tgn:7010420",
        "tgn:1000003",
        "tgn:7002795",
        "tgn:1000095",
        "tgn:7029392"
    ],
    "tgn:id":7333248,
    "tgn:name":"Garg\u00fcera, Arroyo",
    "tgn:placetype":[
        "aat:300008699"
    ]
},
  "bbox": [],
  "geometry": {"coordinates":[-3.666667,40.783333],"type":"Point"}
}