{
  "id": 7440831,
  "type": "Feature",
  "properties": {
    "tgn:hierarchy":[
        "tgn:7440831",
        "tgn:1000001",
        "tgn:1001960",
        "tgn:7005560",
        "tgn:7029392"
    ],
    "tgn:id":7440831,
    "tgn:name":"Rancho San Luis",
    "tgn:placetype":[
        "aat:300000241"
    ]
},
  "bbox": [],
  "geometry": {"coordinates":[-110.883333,30.65],"type":"Point"}
}