{
  "id": 2655301,
  "type": "Feature",
  "properties": {
    "tgn:hierarchy":[
        "tgn:2655301",
        "tgn:1000001",
        "tgn:7012149",
        "tgn:2000928",
        "tgn:7007515",
        "tgn:7029392"
    ],
    "tgn:id":2655301,
    "tgn:name":"Shanty Mountain Brook",
    "tgn:placetype":[
        "aat:300008699"
    ]
},
  "bbox": [],
  "geometry": {"coordinates":[-69.1667,45.5333],"type":"Point"}
}