{
  "id": 7399570,
  "type": "Feature",
  "properties": {
    "tgn:hierarchy":[
        "tgn:7399570",
        "tgn:1000001",
        "tgn:7005599",
        "tgn:7005560",
        "tgn:7029392"
    ],
    "tgn:id":7399570,
    "tgn:name":"Pe\u00f1a Hermosa",
    "tgn:placetype":[
        "aat:300008347"
    ]
},
  "bbox": [],
  "geometry": {"coordinates":[-94.677778,18.358333],"type":"Point"}
}