{
  "id": 7300192,
  "type": "Feature",
  "properties": {
    "tgn:hierarchy":[
        "tgn:7300192",
        "tgn:7001158",
        "tgn:7002848",
        "tgn:1000003",
        "tgn:1000095",
        "tgn:7029392"
    ],
    "tgn:id":7300192,
    "tgn:name":"Torre de Pe\u00f1afiel",
    "tgn:placetype":[
        "aat:300008347"
    ]
},
  "bbox": [],
  "geometry": {"coordinates":[-4.083333,41.533333],"type":"Point"}
}