{
  "id": 7022536,
  "type": "Feature",
  "properties": {
    "tgn:hierarchy":[
        "tgn:7022536",
        "tgn:1000001",
        "tgn:7012149",
        "tgn:7029392"
    ],
    "tgn:id":7022536,
    "tgn:name":"Cinder Gulch",
    "tgn:placetype":[
        "aat:300008761"
    ]
},
  "bbox": [],
  "geometry": {"coordinates":[-108.1333,36.9667],"type":"Point"}
}