<<<<<<< HEAD
{
  "id": 7022536,
  "type": "Feature",
  "properties": {
    "tgn:hierarchy":[
        "tgn:7022536",
        "tgn:1000001",
        "tgn:7012149",
        "tgn:7029392"
    ],
    "tgn:id":7022536,
    "tgn:name":"Cinder Gulch",
    "tgn:placetype":[
        "aat:300008761"
    ]
},
  "bbox": [],
  "geometry": {"coordinates":[-108.1333,36.9667],"type":"Point"}
}
=======
{"geometry":{"type":"Point","coordinates":[-108.133300,36.966700]},"type":"Feature","properties":{"hierarchy":["tgn:7022536","tgn:1000001","tgn:7012149","tgn:7029392"],"placetype":["aat:300008761"],"id":7022536,"name:xx":"Cinder Gulch"}}
>>>>>>> 03f74aca74312dbeaf24d7e61306dd6a786dc3d0
