{
  "id": 2276476,
  "type": "Feature",
  "properties": {
    "tgn:hierarchy":[
        "tgn:2276476",
        "tgn:1000001",
        "tgn:7012149",
        "tgn:2001717",
        "tgn:7007708",
        "tgn:7029392"
    ],
    "tgn:id":2276476,
    "tgn:name":"Davenport Pond",
    "tgn:placetype":[
        "aat:300006191"
    ]
},
  "bbox": [],
  "geometry": {"coordinates":[-122.7667,44.5833],"type":"Point"}
}