{
  "id": 2061344,
  "type": "Feature",
  "properties": {
    "tgn:hierarchy":[
        "tgn:2061344",
        "tgn:1000001",
        "tgn:7012149",
        "tgn:2001273",
        "tgn:7007524",
        "tgn:7029392"
    ],
    "tgn:id":2061344,
    "tgn:name":"Garneill",
    "tgn:placetype":[
        "aat:300008347"
    ]
},
  "bbox": [],
  "geometry": {"coordinates":[-109.75,46.75],"type":"Point"}
}