{
  "id": 2215198,
  "type": "Feature",
  "properties": {
    "tgn:hierarchy":[
        "tgn:2215198",
        "tgn:1000001",
        "tgn:2002313",
        "tgn:7012149",
        "tgn:7007922",
        "tgn:7029392"
    ],
    "tgn:id":2215198,
    "tgn:name":"Calkins Lake",
    "tgn:placetype":[
        "aat:300008680"
    ]
},
  "bbox": [],
  "geometry": {"coordinates":[-91.4333,45.2667],"type":"Point"}
}