{
  "id": 2708820,
  "type": "Feature",
  "properties": {
    "tgn:hierarchy":[
        "tgn:2708820",
        "tgn:7006450",
        "tgn:1000001",
        "tgn:7012149",
        "tgn:7019760",
        "tgn:7029392"
    ],
    "tgn:id":2708820,
    "tgn:name":"Sylvia Creek",
    "tgn:placetype":[
        "aat:300008706"
    ]
},
  "bbox": [],
  "geometry": {"coordinates":[-133.2333,57.55],"type":"Point"}
}