{
  "id": 2733580,
  "type": "Feature",
  "properties": {
    "tgn:hierarchy":[
        "tgn:2733580",
        "tgn:1000001",
        "tgn:7012149",
        "tgn:1002671",
        "tgn:7007523",
        "tgn:7029392"
    ],
    "tgn:id":2733580,
    "tgn:name":"Turn Back Ridge",
    "tgn:placetype":[
        "aat:300266640"
    ]
},
  "bbox": [],
  "geometry": {"coordinates":[-92.3833,38.2167],"type":"Point"}
}