{
  "id": 7572927,
  "type": "Feature",
  "properties": {
    "tgn:hierarchy":[
        "tgn:7572927",
        "tgn:1000004",
        "tgn:1001871",
        "tgn:7000198",
        "tgn:7029392"
    ],
    "tgn:id":7572927,
    "tgn:name:en":"Jodhka",
    "tgn:placetype":[
        "aat:300008347"
    ]
},
  "bbox": [],
  "geometry": {"coordinates":[75.222853,29.496692],"type":"Point"}
}