{
  "id": 7075973,
  "type": "Feature",
  "properties": {
    "tgn:hierarchy":[
        "tgn:7075973",
        "tgn:7000096",
        "tgn:1000003",
        "tgn:7000084",
        "tgn:7029392"
    ],
    "tgn:id":7075973,
    "tgn:name":"Neuenhagener Oderinsel",
    "tgn:placetype":[
        "aat:300008791"
    ]
},
  "bbox": [],
  "geometry": {"coordinates":[14.066667,52.85],"type":"Point"}
}