{
  "id": 7283976,
  "type": "Feature",
  "properties": {
    "tgn:hierarchy":[
        "tgn:7283976",
        "tgn:1001705",
        "tgn:1000049",
        "tgn:1000002",
        "tgn:7029392"
    ],
    "tgn:id":7283976,
    "tgn:name":"Poza, Quebrada la",
    "tgn:placetype":[
        "aat:300008699"
    ]
},
  "bbox": [],
  "geometry": {"coordinates":[-72.033333,-34.916667],"type":"Point"}
}