{
  "id": 2268586,
  "type": "Feature",
  "properties": {
    "tgn:hierarchy":[
        "tgn:2268586",
        "tgn:1000001",
        "tgn:2000921",
        "tgn:7012149",
        "tgn:7007515",
        "tgn:7029392"
    ],
    "tgn:id":2268586,
    "tgn:name":"Crosby Pond",
    "tgn:placetype":[
        "aat:300008680"
    ]
},
  "bbox": [],
  "geometry": {"coordinates":[-70.7667,45.3833],"type":"Point"}
}