<<<<<<< HEAD
{
  "id": 7178523,
  "type": "Feature",
  "properties": {
    "tgn:hierarchy":[
        "tgn:7178523",
        "tgn:7003669",
        "tgn:1000003",
        "tgn:7000084",
        "tgn:7029392"
    ],
    "tgn:id":7178523,
    "tgn:name":"Haiholz",
    "tgn:placetype":[
        "aat:300000206"
    ]
},
  "bbox": [],
  "geometry": {"coordinates":[12.516667,48.7],"type":"Point"}
}
=======
{"geometry":{"type":"Point","coordinates":[12.516667,48.700000]},"type":"Feature","properties":{"hierarchy":["tgn:7178523","tgn:7003669","tgn:1000003","tgn:7000084","tgn:7029392"],"placetype":["aat:300000206"],"id":7178523,"name:xx":"Haiholz"}}
>>>>>>> 03f74aca74312dbeaf24d7e61306dd6a786dc3d0
