{
  "id": 1094526,
  "type": "Feature",
  "properties": {
    "tgn:hierarchy":[
        "tgn:1094526",
        "tgn:7015151",
        "tgn:7001242",
        "tgn:7001725",
        "tgn:7029392"
    ],
    "tgn:id":1094526,
    "tgn:name":"Bulembu",
    "tgn:placetype":[
        "aat:300008347"
    ]
},
  "bbox": [],
  "geometry": {"coordinates":[31.1333,-25.9667],"type":"Point"}
}