{
  "id": 7278574,
  "type": "Feature",
  "properties": {
    "tgn:hierarchy":[
        "tgn:7278574",
        "tgn:1001702",
        "tgn:1000049",
        "tgn:1000002",
        "tgn:7029392"
    ],
    "tgn:id":7278574,
    "tgn:name":"Vio, Bah\u00eda",
    "tgn:placetype":[
        "aat:300132316"
    ]
},
  "bbox": [],
  "geometry": {"coordinates":[-74.366667,-52.916667],"type":"Point"}
}