{
  "id": 7408822,
  "type": "Feature",
  "properties": {
    "tgn:hierarchy":[
        "tgn:7408822",
        "tgn:1000001",
        "tgn:1001893",
        "tgn:7005560",
        "tgn:7029392"
    ],
    "tgn:id":7408822,
    "tgn:name":"Cerro Mel",
    "tgn:placetype":[
        "aat:300008347"
    ]
},
  "bbox": [],
  "geometry": {"coordinates":[-100.175,18.520833],"type":"Point"}
}