<<<<<<< HEAD
{
  "id": 7482738,
  "type": "Feature",
  "properties": {
    "tgn:hierarchy":[
        "tgn:7482738",
        "tgn:1000004",
        "tgn:7001014",
        "tgn:1000141",
        "tgn:7029392"
    ],
    "tgn:id":7482738,
    "tgn:name":"Dishi'er Gongmu",
    "tgn:placetype":[
        "aat:300266755"
    ]
},
  "bbox": [],
  "geometry": {"coordinates":[120.190278,23.535556],"type":"Point"}
}
=======
{"geometry":{"type":"Point","coordinates":[120.190278,23.535556]},"type":"Feature","properties":{"hierarchy":["tgn:7482738","tgn:1000004","tgn:7001014","tgn:1000141","tgn:7029392"],"placetype":["aat:300266755"],"id":7482738,"name:xx":"Dishi'er Gongmu"}}
>>>>>>> 03f74aca74312dbeaf24d7e61306dd6a786dc3d0
