{
  "id": 2533461,
  "type": "Feature",
  "properties": {
    "tgn:hierarchy":[
        "tgn:2533461",
        "tgn:1000001",
        "tgn:7012149",
        "tgn:7007826",
        "tgn:7029392"
    ],
    "tgn:id":2533461,
    "tgn:name":"Musquiz Canyon",
    "tgn:placetype":[
        "aat:300008761"
    ]
},
  "bbox": [],
  "geometry": {"coordinates":[-103.8833,30.4833],"type":"Point"}
}