{
  "id": 7396146,
  "type": "Feature",
  "properties": {
    "tgn:hierarchy":[
        "tgn:7396146",
        "tgn:7005581",
        "tgn:1000001",
        "tgn:7005560",
        "tgn:7029392"
    ],
    "tgn:id":7396146,
    "tgn:name":"San Juan",
    "tgn:placetype":[
        "aat:300008347"
    ]
},
  "bbox": [],
  "geometry": {"coordinates":[-108.55,28.883333],"type":"Point"}
}