{
  "id": 2548127,
  "type": "Feature",
  "properties": {
    "tgn:hierarchy":[
        "tgn:2548127",
        "tgn:1000001",
        "tgn:1002245",
        "tgn:7012149",
        "tgn:7007568",
        "tgn:7029392"
    ],
    "tgn:id":2548127,
    "tgn:name":"North Hollow",
    "tgn:placetype":[
        "aat:300008761"
    ]
},
  "bbox": [],
  "geometry": {"coordinates":[-78.4833,42.25],"type":"Point"}
}