{
  "id": 4001360,
  "type": "Feature",
  "properties": {
    "tgn:hierarchy":[
        "tgn:4001360",
        "tgn:7003460",
        "tgn:1000003",
        "tgn:1000063",
        "tgn:4012014",
        "tgn:7029392"
    ],
    "tgn:id":4001360,
    "tgn:name":"Bellaire",
    "tgn:placetype":[
        "aat:300008347"
    ]
},
  "bbox": [],
  "geometry": {"coordinates":[5.666667,50.65],"type":"Point"}
}