{
  "id": 2554174,
  "type": "Feature",
  "properties": {
    "tgn:hierarchy":[
        "tgn:2554174",
        "tgn:1000001",
        "tgn:7006451",
        "tgn:7012149",
        "tgn:2000101",
        "tgn:7029392"
    ],
    "tgn:id":2554174,
    "tgn:name":"Oak Spring",
    "tgn:placetype":[
        "aat:300008697"
    ]
},
  "bbox": [],
  "geometry": {"coordinates":[-111.0667,33.45],"type":"Point"}
}