{
  "id": 2652419,
  "type": "Feature",
  "properties": {
    "tgn:hierarchy":[
        "tgn:2652419",
        "tgn:1000001",
        "tgn:7012149",
        "tgn:1002971",
        "tgn:7007710",
        "tgn:7029392"
    ],
    "tgn:id":2652419,
    "tgn:name":"Seneca Run",
    "tgn:placetype":[
        "aat:300008699"
    ]
},
  "bbox": [],
  "geometry": {"coordinates":[-79.75,41.3833],"type":"Point"}
}