<<<<<<< HEAD
{
  "id": 7024119,
  "type": "Feature",
  "properties": {
    "tgn:hierarchy":[
        "tgn:7024119",
        "tgn:1000003",
        "tgn:7006366",
        "tgn:7029392"
    ],
    "tgn:id":7024119,
    "tgn:name":"Wielkopolskie",
    "tgn:placetype":[
        "aat:300387064",
        "aat:300235112"
    ]
},
  "bbox": [],
  "geometry": {"coordinates":[17.0,52.25],"type":"Point"}
}
=======
{"geometry":{"type":"Point","coordinates":[17.000000,52.250000]},"type":"Feature","properties":{"hierarchy":["tgn:7024119","tgn:1000003","tgn:7006366","tgn:7029392"],"placetype":["aat:300387064","aat:300235112"],"id":7024119,"name:xx":"Wielkopolskie"}}
>>>>>>> 03f74aca74312dbeaf24d7e61306dd6a786dc3d0
