{
  "id": 7075317,
  "type": "Feature",
  "properties": {
    "tgn:hierarchy":[
        "tgn:7075317",
        "tgn:1000003",
        "tgn:7003676",
        "tgn:7000084",
        "tgn:7029392"
    ],
    "tgn:id":7075317,
    "tgn:name":"Hohenesch",
    "tgn:placetype":[
        "aat:300008347"
    ]
},
  "bbox": [],
  "geometry": {"coordinates":[9.366667,53.116667],"type":"Point"}
}