{
  "id": 1111128,
  "type": "Feature",
  "properties": {
    "tgn:hierarchy":[
        "tgn:1111128",
        "tgn:7001242",
        "tgn:1000179",
        "tgn:7593681",
        "tgn:7029392"
    ],
    "tgn:id":1111128,
    "tgn:name":"Charef, Oued",
    "tgn:placetype":[
        "aat:300387091"
    ]
},
  "bbox": [],
  "geometry": {"coordinates":[-2.05,34.0833],"type":"Point"}
}