{
  "id": 7287724,
  "type": "Feature",
  "properties": {
    "tgn:hierarchy":[
        "tgn:7287724",
        "tgn:1001699",
        "tgn:1000049",
        "tgn:1000002",
        "tgn:7029392"
    ],
    "tgn:id":7287724,
    "tgn:name":"Ilto, Bah\u00eda",
    "tgn:placetype":[
        "aat:300132316"
    ]
},
  "bbox": [],
  "geometry": {"coordinates":[-73.142778,-41.896111],"type":"Point"}
}