<<<<<<< HEAD
{
  "id": 2769636,
  "type": "Feature",
  "properties": {
    "tgn:hierarchy":[
        "tgn:2769636",
        "tgn:1000001",
        "tgn:7012149",
        "tgn:2001220",
        "tgn:7007523",
        "tgn:7029392"
    ],
    "tgn:id":2769636,
    "tgn:name":"Wieneke Branch",
    "tgn:placetype":[
        "aat:300008699"
    ]
},
  "bbox": [],
  "geometry": {"coordinates":[-92.5,38.5833],"type":"Point"}
}
=======
{"geometry":{"type":"Point","coordinates":[-92.500000,38.583300]},"type":"Feature","properties":{"hierarchy":["tgn:2769636","tgn:1000001","tgn:7012149","tgn:2001220","tgn:7007523","tgn:7029392"],"placetype":["aat:300008699"],"id":2769636,"name:xx":"Wieneke Branch"}}
>>>>>>> 03f74aca74312dbeaf24d7e61306dd6a786dc3d0
