{
  "id": 7559290,
  "type": "Feature",
  "properties": {
    "tgn:hierarchy":[
        "tgn:7559290",
        "tgn:1000004",
        "tgn:7000198",
        "tgn:7016694",
        "tgn:7029392"
    ],
    "tgn:id":7559290,
    "tgn:name:en":"Raikia",
    "tgn:placetype":[
        "aat:300008347"
    ]
},
  "bbox": [],
  "geometry": {"coordinates":[84.233333,20.066667],"type":"Point"}
}