{
  "id": 7157037,
  "type": "Feature",
  "properties": {
    "tgn:hierarchy":[
        "tgn:7157037",
        "tgn:1000003",
        "tgn:7003677",
        "tgn:7000084",
        "tgn:7029392"
    ],
    "tgn:id":7157037,
    "tgn:name":"Klasvorbeck",
    "tgn:placetype":[
        "aat:300000206"
    ]
},
  "bbox": [],
  "geometry": {"coordinates":[8.533333,51.833333],"type":"Point"}
}