{
  "id": 2265833,
  "type": "Feature",
  "properties": {
    "tgn:hierarchy":[
        "tgn:2265833",
        "tgn:1000001",
        "tgn:7012149",
        "tgn:2000215",
        "tgn:7007158",
        "tgn:7029392"
    ],
    "tgn:id":2265833,
    "tgn:name":"Crater Lakes",
    "tgn:placetype":[
        "aat:300008680"
    ]
},
  "bbox": [],
  "geometry": {"coordinates":[-105.6667,39.8833],"type":"Point"}
}