{
  "id": 2558349,
  "type": "Feature",
  "properties": {
    "tgn:hierarchy":[
        "tgn:2558349",
        "tgn:1000001",
        "tgn:7012149",
        "tgn:2000989",
        "tgn:7007520",
        "tgn:7029392"
    ],
    "tgn:id":2558349,
    "tgn:name":"Oley Lake",
    "tgn:placetype":[
        "aat:300008680"
    ]
},
  "bbox": [],
  "geometry": {"coordinates":[-84.5667,44.9833],"type":"Point"}
}