{
  "id": 2258301,
  "type": "Feature",
  "properties": {
    "tgn:hierarchy":[
        "tgn:2258301",
        "tgn:1000001",
        "tgn:7012149",
        "tgn:7007568",
        "tgn:7029392"
    ],
    "tgn:id":2258301,
    "tgn:name":"Cotter Brook",
    "tgn:placetype":[
        "aat:300008699"
    ]
},
  "bbox": [],
  "geometry": {"coordinates":[-74.1333,43.4667],"type":"Point"}
}