{
  "id": 2369449,
  "type": "Feature",
  "properties": {
    "tgn:hierarchy":[
        "tgn:2369449",
        "tgn:1000001",
        "tgn:7012149",
        "tgn:2000372",
        "tgn:7007248",
        "tgn:7029392"
    ],
    "tgn:id":2369449,
    "tgn:name":"Gun Pond",
    "tgn:placetype":[
        "aat:300008905"
    ]
},
  "bbox": [],
  "geometry": {"coordinates":[-82.3333,33.1333],"type":"Point"}
}