{
  "id": 2168189,
  "type": "Feature",
  "properties": {
    "tgn:hierarchy":[
        "tgn:2168189",
        "tgn:1000001",
        "tgn:2001429",
        "tgn:7012149",
        "tgn:7007566",
        "tgn:7029392"
    ],
    "tgn:id":2168189,
    "tgn:name":"Big Flat Tank",
    "tgn:placetype":[
        "aat:300006191"
    ]
},
  "bbox": [],
  "geometry": {"coordinates":[-108.7167,33.8667],"type":"Point"}
}