{
  "id": 7067951,
  "type": "Feature",
  "properties": {
    "tgn:hierarchy":[
        "tgn:7067951",
        "tgn:1000003",
        "tgn:7003685",
        "tgn:7000084",
        "tgn:7029392"
    ],
    "tgn:id":7067951,
    "tgn:name":"Torfhaus",
    "tgn:placetype":[
        "aat:300008347"
    ]
},
  "bbox": [],
  "geometry": {"coordinates":[12.75,51.566667],"type":"Point"}
}