{
  "id": 7333210,
  "type": "Feature",
  "properties": {
    "tgn:hierarchy":[
        "tgn:7333210",
        "tgn:7002758",
        "tgn:7002830",
        "tgn:1000003",
        "tgn:1000095",
        "tgn:7029392"
    ],
    "tgn:id":7333210,
    "tgn:name":"Jubrique",
    "tgn:placetype":[
        "aat:300008347"
    ]
},
  "bbox": [],
  "geometry": {"coordinates":[-5.216667,36.566667],"type":"Point"}
}