{
  "id": 7381258,
  "type": "Feature",
  "properties": {
    "tgn:hierarchy":[
        "tgn:7381258",
        "tgn:1000001",
        "tgn:7005595",
        "tgn:7005560",
        "tgn:7029392"
    ],
    "tgn:id":7381258,
    "tgn:name":"Los Mecates",
    "tgn:placetype":[
        "aat:300008347"
    ]
},
  "bbox": [],
  "geometry": {"coordinates":[-106.889167,24.191667],"type":"Point"}
}