{
  "id": 2149987,
  "type": "Feature",
  "properties": {
    "tgn:hierarchy":[
        "tgn:2149987",
        "tgn:1000001",
        "tgn:7016172",
        "tgn:7012149",
        "tgn:2000165",
        "tgn:7029392"
    ],
    "tgn:id":2149987,
    "tgn:name":"Bartley Hollow",
    "tgn:placetype":[
        "aat:300008761"
    ]
},
  "bbox": [],
  "geometry": {"coordinates":[-91.2333,36.4667],"type":"Point"}
}