{
  "id": 1096552,
  "type": "Feature",
  "properties": {
    "tgn:hierarchy":[
        "tgn:1096552",
        "tgn:7000490",
        "tgn:1000006",
        "tgn:7001834",
        "tgn:7029392"
    ],
    "tgn:id":1096552,
    "tgn:name":"City Beach",
    "tgn:placetype":[
        "aat:300008347"
    ]
},
  "bbox": [],
  "geometry": {"coordinates":[115.75,-31.9333],"type":"Point"}
}