<<<<<<< HEAD
{
  "id": 7368285,
  "type": "Feature",
  "properties": {
    "tgn:hierarchy":[
        "tgn:7368285",
        "tgn:7016644",
        "tgn:1000001",
        "tgn:7005560",
        "tgn:7029392"
    ],
    "tgn:id":7368285,
    "tgn:name":"Hermoso, Llano",
    "tgn:placetype":[
        "aat:300008805"
    ]
},
  "bbox": [],
  "geometry": {"coordinates":[-111.0,18.733333],"type":"Point"}
}
=======
{"geometry":{"type":"Point","coordinates":[-111.000000,18.733333]},"type":"Feature","properties":{"hierarchy":["tgn:7368285","tgn:7016644","tgn:1000001","tgn:7005560","tgn:7029392"],"placetype":["aat:300008805"],"id":7368285,"name:xx":"Hermoso, Llano"}}
>>>>>>> 03f74aca74312dbeaf24d7e61306dd6a786dc3d0
