{
  "id": 2233822,
  "type": "Feature",
  "properties": {
    "tgn:hierarchy":[
        "tgn:2233822",
        "tgn:1000001",
        "tgn:7012149",
        "tgn:2002118",
        "tgn:7007827",
        "tgn:7029392"
    ],
    "tgn:id":2233822,
    "tgn:name":"Chateau Village",
    "tgn:placetype":[
        "aat:300008347"
    ]
},
  "bbox": [],
  "geometry": {"coordinates":[-112.0167,40.65],"type":"Point"}
}