{
  "id": 1099171,
  "type": "Feature",
  "properties": {
    "tgn:hierarchy":[
        "tgn:1099171",
        "tgn:1008380",
        "tgn:1000226",
        "tgn:7000512",
        "tgn:1000006",
        "tgn:7029392"
    ],
    "tgn:id":1099171,
    "tgn:name:en":"Porirua",
    "tgn:placetype":[
        "aat:300008347"
    ]
},
  "bbox": [],
  "geometry": {"coordinates":[174.85,-41.133333],"type":"Point"}
}