{
  "id": 7333388,
  "type": "Feature",
  "properties": {
    "tgn:hierarchy":[
        "tgn:7333388",
        "tgn:7002829",
        "tgn:1000003",
        "tgn:7002786",
        "tgn:1000095",
        "tgn:7029392"
    ],
    "tgn:id":7333388,
    "tgn:name":"Folgueira",
    "tgn:placetype":[
        "aat:300008347"
    ]
},
  "bbox": [],
  "geometry": {"coordinates":[-7.566667,43.133333],"type":"Point"}
}