{
  "id": 2078769,
  "type": "Feature",
  "properties": {
    "tgn:hierarchy":[
        "tgn:2078769",
        "tgn:1000001",
        "tgn:7012149",
        "tgn:1003007",
        "tgn:7007706",
        "tgn:7029392"
    ],
    "tgn:id":2078769,
    "tgn:name":"Cedar Valley",
    "tgn:placetype":[
        "aat:300008347"
    ]
},
  "bbox": [],
  "geometry": {"coordinates":[-82.0167,40.8667],"type":"Point"}
}