{
  "id": 2450671,
  "type": "Feature",
  "properties": {
    "tgn:hierarchy":[
        "tgn:2450671",
        "tgn:1000001",
        "tgn:7006451",
        "tgn:7012149",
        "tgn:2000102",
        "tgn:7029392"
    ],
    "tgn:id":2450671,
    "tgn:name":"Lion Mountain",
    "tgn:placetype":[
        "aat:300008798"
    ]
},
  "bbox": [],
  "geometry": {"coordinates":[-111.0833,31.45],"type":"Point"}
}