{
  "id": 7560519,
  "type": "Feature",
  "properties": {
    "tgn:hierarchy":[
        "tgn:7560519",
        "tgn:1000004",
        "tgn:7000198",
        "tgn:7016722",
        "tgn:7029392"
    ],
    "tgn:id":7560519,
    "tgn:name:en":"Ism\u0101ilpur",
    "tgn:placetype":[
        "aat:300008347"
    ]
},
  "bbox": [],
  "geometry": {"coordinates":[79.554709,27.654976],"type":"Point"}
}