<<<<<<< HEAD
{
  "id": 7241538,
  "type": "Feature",
  "properties": {
    "tgn:hierarchy":[
        "tgn:7241538",
        "tgn:7003461",
        "tgn:1000003",
        "tgn:1000063",
        "tgn:7018236",
        "tgn:7029392"
    ],
    "tgn:id":7241538,
    "tgn:name":"Kleinen Demer",
    "tgn:placetype":[
        "aat:300008699"
    ]
},
  "bbox": [],
  "geometry": {"coordinates":[5.3,50.95],"type":"Point"}
}
=======
{"geometry":{"type":"Point","coordinates":[5.300000,50.950000]},"type":"Feature","properties":{"hierarchy":["tgn:7241538","tgn:7003461","tgn:1000003","tgn:1000063","tgn:7018236","tgn:7029392"],"placetype":["aat:300008699"],"id":7241538,"name:xx":"Kleinen Demer"}}
>>>>>>> 03f74aca74312dbeaf24d7e61306dd6a786dc3d0
