{
  "id": 2273556,
  "type": "Feature",
  "properties": {
    "tgn:hierarchy":[
        "tgn:2273556",
        "tgn:1000001",
        "tgn:7013368",
        "tgn:7012149",
        "tgn:7007709",
        "tgn:7029392"
    ],
    "tgn:id":2273556,
    "tgn:name":"Cypress Run",
    "tgn:placetype":[
        "aat:300008699"
    ]
},
  "bbox": [],
  "geometry": {"coordinates":[-76.8167,35.2667],"type":"Point"}
}