{
  "id": 7507831,
  "type": "Feature",
  "properties": {
    "tgn:hierarchy":[
        "tgn:7507831",
        "tgn:1008380",
        "tgn:7000507",
        "tgn:1000226",
        "tgn:1000006",
        "tgn:7029392"
    ],
    "tgn:id":7507831,
    "tgn:name:en":"Pihoe",
    "tgn:placetype":[
        "aat:300008777"
    ]
},
  "bbox": [],
  "geometry": {"coordinates":[174.016667,-35.216667],"type":"Point"}
}