{
  "id": 2354943,
  "type": "Feature",
  "properties": {
    "tgn:hierarchy":[
        "tgn:2354943",
        "tgn:1000001",
        "tgn:7012149",
        "tgn:1002747",
        "tgn:7007568",
        "tgn:7029392"
    ],
    "tgn:id":2354943,
    "tgn:name":"Gooding Point",
    "tgn:placetype":[
        "aat:300008850"
    ]
},
  "bbox": [],
  "geometry": {"coordinates":[-77.2667,42.7833],"type":"Point"}
}