{
  "id": 7585975,
  "type": "Feature",
  "properties": {
    "tgn:hierarchy":[
        "tgn:7585975",
        "tgn:1000004",
        "tgn:7000198",
        "tgn:7000799",
        "tgn:7029392"
    ],
    "tgn:id":7585975,
    "tgn:name:en":"Buna Wadar",
    "tgn:placetype":[
        "aat:300008347"
    ]
},
  "bbox": [],
  "geometry": {"coordinates":[74.142341,34.37708],"type":"Point"}
}