{
  "id": 7522903,
  "type": "Feature",
  "properties": {
    "tgn:hierarchy":[
        "tgn:7522903",
        "tgn:7001242",
        "tgn:7016833",
        "tgn:7000124",
        "tgn:7029392"
    ],
    "tgn:id":7522903,
    "tgn:name:en":"A\u015ffar, W\u0101d\u012b al",
    "tgn:placetype":[
        "aat:300379998"
    ]
},
  "bbox": [],
  "geometry": {"coordinates":[31.333333,26.816667],"type":"Point"}
}