{
  "id": 2057681,
  "type": "Feature",
  "properties": {
    "tgn:hierarchy":[
        "tgn:2057681",
        "tgn:1000001",
        "tgn:2001100",
        "tgn:7012149",
        "tgn:7007522",
        "tgn:7029392"
    ],
    "tgn:id":2057681,
    "tgn:name":"Utica Junior College",
    "tgn:placetype":[
        "aat:300006495"
    ]
},
  "bbox": [],
  "geometry": {"coordinates":[-90.6167,32.0333],"type":"Point"}
}