{
  "id": 7376470,
  "type": "Feature",
  "properties": {
    "tgn:hierarchy":[
        "tgn:7376470",
        "tgn:7005580",
        "tgn:1000001",
        "tgn:7005560",
        "tgn:7029392"
    ],
    "tgn:id":7376470,
    "tgn:name":"Larrainzar",
    "tgn:placetype":[
        "aat:300008347"
    ]
},
  "bbox": [],
  "geometry": {"coordinates":[-92.708333,16.883333],"type":"Point"}
}