{
  "id": 2307935,
  "type": "Feature",
  "properties": {
    "tgn:hierarchy":[
        "tgn:2307935",
        "tgn:1000001",
        "tgn:7012149",
        "tgn:7007157",
        "tgn:2000189",
        "tgn:7029392"
    ],
    "tgn:id":2307935,
    "tgn:name":"East Gulch",
    "tgn:placetype":[
        "aat:300008761"
    ]
},
  "bbox": [],
  "geometry": {"coordinates":[-122.6333,41.5167],"type":"Point"}
}