{
  "id": 7389495,
  "type": "Feature",
  "properties": {
    "tgn:hierarchy":[
        "tgn:7389495",
        "tgn:1000001",
        "tgn:1001960",
        "tgn:7005560",
        "tgn:7029392"
    ],
    "tgn:id":7389495,
    "tgn:name":"Salada, Sierra de la",
    "tgn:placetype":[
        "aat:300008795"
    ]
},
  "bbox": [],
  "geometry": {"coordinates":[-113.15,31.95],"type":"Point"}
}