<<<<<<< HEAD
{
  "id": 2251968,
  "type": "Feature",
  "properties": {
    "tgn:hierarchy":[
        "tgn:2251968",
        "tgn:1000001",
        "tgn:7012149",
        "tgn:1002356",
        "tgn:7007568",
        "tgn:7029392"
    ],
    "tgn:id":2251968,
    "tgn:name":"Concord",
    "tgn:placetype":[
        "aat:300008347"
    ]
},
  "bbox": [],
  "geometry": {"coordinates":[-78.7167,42.5333],"type":"Point"}
}
=======
{"geometry":{"type":"Point","coordinates":[-78.716700,42.533300]},"type":"Feature","properties":{"hierarchy":["tgn:2251968","tgn:1000001","tgn:7012149","tgn:1002356","tgn:7007568","tgn:7029392"],"placetype":["aat:300008347"],"id":2251968,"name:xx":"Concord"}}
>>>>>>> 03f74aca74312dbeaf24d7e61306dd6a786dc3d0
