{
  "id": 2251968,
  "type": "Feature",
  "properties": {
    "tgn:hierarchy":[
        "tgn:2251968",
        "tgn:1000001",
        "tgn:7012149",
        "tgn:1002356",
        "tgn:7007568",
        "tgn:7029392"
    ],
    "tgn:id":2251968,
    "tgn:name":"Concord",
    "tgn:placetype":[
        "aat:300008347"
    ]
},
  "bbox": [],
  "geometry": {"coordinates":[-78.7167,42.5333],"type":"Point"}
}