{
  "id": 7487213,
  "type": "Feature",
  "properties": {
    "tgn:hierarchy":[
        "tgn:7487213",
        "tgn:7468018",
        "tgn:1000004",
        "tgn:1000141",
        "tgn:7029392"
    ],
    "tgn:id":7487213,
    "tgn:name":"Mifengong",
    "tgn:placetype":[
        "aat:300008347"
    ]
},
  "bbox": [],
  "geometry": {"coordinates":[120.400968,23.610412],"type":"Point"}
}