{
  "id": 7434478,
  "type": "Feature",
  "properties": {
    "tgn:hierarchy":[
        "tgn:7434478",
        "tgn:1000001",
        "tgn:7005600",
        "tgn:7005560",
        "tgn:7029392"
    ],
    "tgn:id":7434478,
    "tgn:name":"Xkanh\u00e1 Arce",
    "tgn:placetype":[
        "aat:300008347"
    ]
},
  "bbox": [],
  "geometry": {"coordinates":[-88.516667,21.283333],"type":"Point"}
}