<<<<<<< HEAD
{
  "id": 7470462,
  "type": "Feature",
  "properties": {
    "tgn:hierarchy":[
        "tgn:7470462",
        "tgn:7488858",
        "tgn:1000004",
        "tgn:1000141",
        "tgn:7029392"
    ],
    "tgn:id":7470462,
    "tgn:name":"Dingcheng",
    "tgn:placetype":[
        "aat:300008347"
    ]
},
  "bbox": [],
  "geometry": {"coordinates":[120.803658,23.862],"type":"Point"}
}
=======
{"geometry":{"type":"Point","coordinates":[120.803658,23.862000]},"type":"Feature","properties":{"hierarchy":["tgn:7470462","tgn:7488858","tgn:1000004","tgn:1000141","tgn:7029392"],"placetype":["aat:300008347"],"id":7470462,"name:xx":"Dingcheng"}}
>>>>>>> 03f74aca74312dbeaf24d7e61306dd6a786dc3d0
