{
  "id": 2501745,
  "type": "Feature",
  "properties": {
    "tgn:hierarchy":[
        "tgn:2501745",
        "tgn:1000001",
        "tgn:2001945",
        "tgn:7012149",
        "tgn:7007826",
        "tgn:7029392"
    ],
    "tgn:id":2501745,
    "tgn:name":"McIntyre Creek",
    "tgn:placetype":[
        "aat:300008706"
    ]
},
  "bbox": [],
  "geometry": {"coordinates":[-103.75,30.2833],"type":"Point"}
}