{
  "id": 7372045,
  "type": "Feature",
  "properties": {
    "tgn:hierarchy":[
        "tgn:7372045",
        "tgn:1000001",
        "tgn:7005597",
        "tgn:7005560",
        "tgn:7029392"
    ],
    "tgn:id":7372045,
    "tgn:name":"Lajilla, Arroyo",
    "tgn:placetype":[
        "aat:300008699"
    ]
},
  "bbox": [],
  "geometry": {"coordinates":[-98.816667,23.466667],"type":"Point"}
}