{
  "id": 7055351,
  "type": "Feature",
  "properties": {
    "tgn:hierarchy":[
        "tgn:7055351",
        "tgn:1003506",
        "tgn:1000003",
        "tgn:7002993",
        "tgn:1000080",
        "tgn:7029392"
    ],
    "tgn:id":7055351,
    "tgn:name":"Lignano, Porto",
    "tgn:placetype":[
        "aat:300008678"
    ]
},
  "bbox": [],
  "geometry": {"coordinates":[13.1575,45.697778],"type":"Point"}
}