<<<<<<< HEAD
{
  "id": 7055351,
  "type": "Feature",
  "properties": {
    "tgn:hierarchy":[
        "tgn:7055351",
        "tgn:1003506",
        "tgn:1000003",
        "tgn:7002993",
        "tgn:1000080",
        "tgn:7029392"
    ],
    "tgn:id":7055351,
    "tgn:name":"Lignano, Porto",
    "tgn:placetype":[
        "aat:300008678"
    ]
},
  "bbox": [],
  "geometry": {"coordinates":[13.1575,45.697778],"type":"Point"}
}
=======
{"geometry":{"type":"Point","coordinates":[13.157500,45.697778]},"type":"Feature","properties":{"hierarchy":["tgn:7055351","tgn:1003506","tgn:1000003","tgn:7002993","tgn:1000080","tgn:7029392"],"placetype":["aat:300008678"],"id":7055351,"name:xx":"Lignano, Porto"}}
>>>>>>> 03f74aca74312dbeaf24d7e61306dd6a786dc3d0
