{
  "id": 7342849,
  "type": "Feature",
  "properties": {
    "tgn:hierarchy":[
        "tgn:7342849",
        "tgn:7002758",
        "tgn:7002817",
        "tgn:1000003",
        "tgn:1000095",
        "tgn:7029392"
    ],
    "tgn:id":7342849,
    "tgn:name":"Cardenchosilla, Arroyo de la",
    "tgn:placetype":[
        "aat:300266554",
        "aat:300008699"
    ]
},
  "bbox": [],
  "geometry": {"coordinates":[-5.35,38.25],"type":"Point"}
}