{
  "id": 2560961,
  "type": "Feature",
  "properties": {
    "tgn:hierarchy":[
        "tgn:2560961",
        "tgn:1000001",
        "tgn:1002218",
        "tgn:7012149",
        "tgn:7007157",
        "tgn:7029392"
    ],
    "tgn:id":2560961,
    "tgn:name":"Orofino Mine",
    "tgn:placetype":[
        "aat:300000390"
    ]
},
  "bbox": [],
  "geometry": {"coordinates":[-121.6167,39.8667],"type":"Point"}
}