<<<<<<< HEAD
{
  "id": 2257087,
  "type": "Feature",
  "properties": {
    "tgn:hierarchy":[
        "tgn:2257087",
        "tgn:1000001",
        "tgn:7012149",
        "tgn:2002127",
        "tgn:7007827",
        "tgn:7029392"
    ],
    "tgn:id":2257087,
    "tgn:name":"Cornelius Wash",
    "tgn:placetype":[
        "aat:300008761"
    ]
},
  "bbox": [],
  "geometry": {"coordinates":[-113.2,37.1333],"type":"Point"}
}
=======
{"geometry":{"type":"Point","coordinates":[-113.200000,37.133300]},"type":"Feature","properties":{"hierarchy":["tgn:2257087","tgn:1000001","tgn:7012149","tgn:2002127","tgn:7007827","tgn:7029392"],"placetype":["aat:300008761"],"id":2257087,"name:xx":"Cornelius Wash"}}
>>>>>>> 03f74aca74312dbeaf24d7e61306dd6a786dc3d0
