{
  "id": 1019254,
  "type": "Feature",
  "properties": {
    "tgn:hierarchy":[
        "tgn:1019254",
        "tgn:7006477",
        "tgn:1001526",
        "tgn:1000002",
        "tgn:7029392"
    ],
    "tgn:id":1019254,
    "tgn:name":"Campo Gallo",
    "tgn:placetype":[
        "aat:300008347"
    ]
},
  "bbox": [],
  "geometry": {"coordinates":[-62.85,-26.5333],"type":"Point"}
}