{
  "id": 1134714,
  "type": "Feature",
  "properties": {
    "tgn:hierarchy":[
        "tgn:1134714",
        "tgn:1000001",
        "tgn:7012149",
        "tgn:7007710",
        "tgn:7029392"
    ],
    "tgn:id":1134714,
    "tgn:name":"Stony Run",
    "tgn:placetype":[
        "aat:300008706"
    ]
},
  "bbox": [],
  "geometry": {"coordinates":[-75.45,40.4167],"type":"Point"}
}