<<<<<<< HEAD
{
  "id": 2400092,
  "type": "Feature",
  "properties": {
    "tgn:hierarchy":[
        "tgn:2400092",
        "tgn:1000001",
        "tgn:7012149",
        "tgn:7007523",
        "tgn:7029392"
    ],
    "tgn:id":2400092,
    "tgn:name":"Horse Creek",
    "tgn:placetype":[
        "aat:300008706"
    ]
},
  "bbox": [],
  "geometry": {"coordinates":[-93.95,37.3333],"type":"Point"}
}
=======
{"geometry":{"type":"Point","coordinates":[-93.950000,37.333300]},"type":"Feature","properties":{"hierarchy":["tgn:2400092","tgn:1000001","tgn:7012149","tgn:7007523","tgn:7029392"],"placetype":["aat:300008706"],"id":2400092,"name:xx":"Horse Creek"}}
>>>>>>> 03f74aca74312dbeaf24d7e61306dd6a786dc3d0
