<<<<<<< HEAD
{
  "id": 7057748,
  "type": "Feature",
  "properties": {
    "tgn:hierarchy":[
        "tgn:7057748",
        "tgn:7003168",
        "tgn:1000003",
        "tgn:7009760",
        "tgn:1000080",
        "tgn:7029392"
    ],
    "tgn:id":7057748,
    "tgn:name":"Bufalaia, Piano della",
    "tgn:placetype":[
        "aat:300008805"
    ]
},
  "bbox": [],
  "geometry": {"coordinates":[11.116667,43.35],"type":"Point"}
}
=======
{"geometry":{"type":"Point","coordinates":[11.116667,43.350000]},"type":"Feature","properties":{"hierarchy":["tgn:7057748","tgn:7003168","tgn:1000003","tgn:7009760","tgn:1000080","tgn:7029392"],"placetype":["aat:300008805"],"id":7057748,"name:xx":"Bufalaia, Piano della"}}
>>>>>>> 03f74aca74312dbeaf24d7e61306dd6a786dc3d0
