{
  "id": 2513976,
  "type": "Feature",
  "properties": {
    "tgn:hierarchy":[
        "tgn:2513976",
        "tgn:1000001",
        "tgn:7012149",
        "tgn:2001420",
        "tgn:7007526",
        "tgn:7029392"
    ],
    "tgn:id":2513976,
    "tgn:name":"Millard Spring",
    "tgn:placetype":[
        "aat:300008697"
    ]
},
  "bbox": [],
  "geometry": {"coordinates":[-114.8833,38.95],"type":"Point"}
}