{
  "id": 2736722,
  "type": "Feature",
  "properties": {
    "tgn:hierarchy":[
        "tgn:2736722",
        "tgn:2002307",
        "tgn:1000001",
        "tgn:7012149",
        "tgn:7007922",
        "tgn:7029392"
    ],
    "tgn:id":2736722,
    "tgn:name":"Twin Town",
    "tgn:placetype":[
        "aat:300008347"
    ]
},
  "bbox": [],
  "geometry": {"coordinates":[-92.0167,45.35],"type":"Point"}
}