{
  "id": 7298514,
  "type": "Feature",
  "properties": {
    "tgn:hierarchy":[
        "tgn:7298514",
        "tgn:7002822",
        "tgn:1001647",
        "tgn:1000003",
        "tgn:1000095",
        "tgn:7029392"
    ],
    "tgn:id":7298514,
    "tgn:name":"Valbueno",
    "tgn:placetype":[
        "aat:300008347"
    ]
},
  "bbox": [],
  "geometry": {"coordinates":[-3.266667,40.633333],"type":"Point"}
}