{
  "id": 2245067,
  "type": "Feature",
  "properties": {
    "tgn:hierarchy":[
        "tgn:2245067",
        "tgn:1000001",
        "tgn:7012149",
        "tgn:2000488",
        "tgn:7007250",
        "tgn:7029392"
    ],
    "tgn:id":2245067,
    "tgn:name":"Clover Mountain",
    "tgn:placetype":[
        "aat:300008798"
    ]
},
  "bbox": [],
  "geometry": {"coordinates":[-116.4167,42.7333],"type":"Point"}
}