<<<<<<< HEAD
{
  "id": 7249024,
  "type": "Feature",
  "properties": {
    "tgn:hierarchy":[
        "tgn:7249024",
        "tgn:7018239",
        "tgn:1000003",
        "tgn:1000063",
        "tgn:7018236",
        "tgn:7029392"
    ],
    "tgn:id":7249024,
    "tgn:name":"Plantsoen Bos",
    "tgn:placetype":[
        "aat:300008863"
    ]
},
  "bbox": [],
  "geometry": {"coordinates":[4.583333,50.883333],"type":"Point"}
}
=======
{"geometry":{"type":"Point","coordinates":[4.583333,50.883333]},"type":"Feature","properties":{"hierarchy":["tgn:7249024","tgn:7018239","tgn:1000003","tgn:1000063","tgn:7018236","tgn:7029392"],"placetype":["aat:300008863"],"id":7249024,"name:xx":"Plantsoen Bos"}}
>>>>>>> 03f74aca74312dbeaf24d7e61306dd6a786dc3d0
