{
  "id": 7588370,
  "type": "Feature",
  "properties": {
    "tgn:hierarchy":[
        "tgn:7588370",
        "tgn:7001819",
        "tgn:1000004",
        "tgn:7000198",
        "tgn:7029392"
    ],
    "tgn:id":7588370,
    "tgn:name:en":"Sicham",
    "tgn:placetype":[
        "aat:300008347"
    ]
},
  "bbox": [],
  "geometry": {"coordinates":[92.576719,27.143544],"type":"Point"}
}