{
  "id": 7476655,
  "type": "Feature",
  "properties": {
    "tgn:hierarchy":[
        "tgn:7476655",
        "tgn:1000004",
        "tgn:7489179",
        "tgn:1000141",
        "tgn:7029392"
    ],
    "tgn:id":7476655,
    "tgn:name":"Lubucheng",
    "tgn:placetype":[
        "aat:300008347"
    ]
},
  "bbox": [],
  "geometry": {"coordinates":[121.740383,24.678885],"type":"Point"}
}