<<<<<<< HEAD
{
  "id": 7476655,
  "type": "Feature",
  "properties": {
    "tgn:hierarchy":[
        "tgn:7476655",
        "tgn:1000004",
        "tgn:7489179",
        "tgn:1000141",
        "tgn:7029392"
    ],
    "tgn:id":7476655,
    "tgn:name":"Lubucheng",
    "tgn:placetype":[
        "aat:300008347"
    ]
},
  "bbox": [],
  "geometry": {"coordinates":[121.740383,24.678885],"type":"Point"}
}
=======
{"geometry":{"type":"Point","coordinates":[121.740383,24.678885]},"type":"Feature","properties":{"hierarchy":["tgn:7476655","tgn:1000004","tgn:7489179","tgn:1000141","tgn:7029392"],"placetype":["aat:300008347"],"id":7476655,"name:xx":"Lubucheng"}}
>>>>>>> 03f74aca74312dbeaf24d7e61306dd6a786dc3d0
