{
  "id": 2121318,
  "type": "Feature",
  "properties": {
    "tgn:hierarchy":[
        "tgn:2121318",
        "tgn:1000001",
        "tgn:7012149",
        "tgn:2002355",
        "tgn:7007922",
        "tgn:7029392"
    ],
    "tgn:id":2121318,
    "tgn:name":"Greenbush",
    "tgn:placetype":[
        "aat:300008347"
    ]
},
  "bbox": [],
  "geometry": {"coordinates":[-88.0833,43.7667],"type":"Point"}
}