{
  "id": 2055380,
  "type": "Feature",
  "properties": {
    "tgn:hierarchy":[
        "tgn:2055380",
        "tgn:1000001",
        "tgn:2001013",
        "tgn:7012149",
        "tgn:7007521",
        "tgn:7029392"
    ],
    "tgn:id":2055380,
    "tgn:name":"Roy Lake",
    "tgn:placetype":[
        "aat:300008347"
    ]
},
  "bbox": [],
  "geometry": {"coordinates":[-95.55,47.3167],"type":"Point"}
}