{
  "id": 2057809,
  "type": "Feature",
  "properties": {
    "tgn:hierarchy":[
        "tgn:2057809",
        "tgn:1000001",
        "tgn:2001094",
        "tgn:7012149",
        "tgn:7007522",
        "tgn:7029392"
    ],
    "tgn:id":2057809,
    "tgn:name":"Woodland",
    "tgn:placetype":[
        "aat:300008347"
    ]
},
  "bbox": [],
  "geometry": {"coordinates":[-89.05,33.7667],"type":"Point"}
}