{
  "id": 1015621,
  "type": "Feature",
  "properties": {
    "tgn:hierarchy":[
        "tgn:1015621",
        "tgn:7005685",
        "tgn:1000001",
        "tgn:7005804",
        "tgn:7029392"
    ],
    "tgn:id":1015621,
    "tgn:name":"Saint-Apollinaire",
    "tgn:placetype":[
        "aat:300008347"
    ]
},
  "bbox": [],
  "geometry": {"coordinates":[-71.5167,46.6167],"type":"Point"}
}