{
  "id": 7468388,
  "type": "Feature",
  "properties": {
    "tgn:hierarchy":[
        "tgn:7468388",
        "tgn:1000004",
        "tgn:7001013",
        "tgn:1000141",
        "tgn:7029392"
    ],
    "tgn:id":7468388,
    "tgn:name":"Qiedongkeng",
    "tgn:placetype":[
        "aat:300008347"
    ]
},
  "bbox": [],
  "geometry": {"coordinates":[121.078775,25.014499],"type":"Point"}
}