{
  "id": 2764652,
  "type": "Feature",
  "properties": {
    "tgn:hierarchy":[
        "tgn:2764652",
        "tgn:7006450",
        "tgn:1000001",
        "tgn:7012149",
        "tgn:2000089",
        "tgn:7029392"
    ],
    "tgn:id":2764652,
    "tgn:name":"Whirlpool Slough",
    "tgn:placetype":[
        "aat:300008699"
    ]
},
  "bbox": [],
  "geometry": {"coordinates":[-147.6333,66.2833],"type":"Point"}
}