{
  "id": 2524677,
  "type": "Feature",
  "properties": {
    "tgn:hierarchy":[
        "tgn:2524677",
        "tgn:1000001",
        "tgn:2000275",
        "tgn:7012149",
        "tgn:7007240",
        "tgn:7029392"
    ],
    "tgn:id":2524677,
    "tgn:name":"Mormon Key",
    "tgn:placetype":[
        "aat:300008791"
    ]
},
  "bbox": [],
  "geometry": {"coordinates":[-81.2833,25.6667],"type":"Point"}
}