{
  "id": 1120581,
  "type": "Feature",
  "properties": {
    "tgn:hierarchy":[
        "tgn:1120581",
        "tgn:7000490",
        "tgn:1000006",
        "tgn:7001828",
        "tgn:7029392"
    ],
    "tgn:id":1120581,
    "tgn:name":"Tooma Reservoir",
    "tgn:placetype":[
        "aat:300006191"
    ]
},
  "bbox": [],
  "geometry": {"coordinates":[148.2667,-36.0667],"type":"Point"}
}