{
  "id": 7132992,
  "type": "Feature",
  "properties": {
    "tgn:hierarchy":[
        "tgn:7132992",
        "tgn:1000003",
        "tgn:7003677",
        "tgn:7000084",
        "tgn:7029392"
    ],
    "tgn:id":7132992,
    "tgn:name":"F\u00f6rsterei Moosspring",
    "tgn:placetype":[
        "aat:300004792"
    ]
},
  "bbox": [],
  "geometry": {"coordinates":[8.466667,51.45],"type":"Point"}
}