{
  "id": 2301714,
  "type": "Feature",
  "properties": {
    "tgn:hierarchy":[
        "tgn:2301714",
        "tgn:1000001",
        "tgn:7012149",
        "tgn:7007157",
        "tgn:1002828",
        "tgn:7029392"
    ],
    "tgn:id":2301714,
    "tgn:name":"Durasno Valley",
    "tgn:placetype":[
        "aat:300008761"
    ]
},
  "bbox": [],
  "geometry": {"coordinates":[-116.6667,33.4667],"type":"Point"}
}