{
  "id": 7147122,
  "type": "Feature",
  "properties": {
    "tgn:hierarchy":[
        "tgn:7147122",
        "tgn:7000096",
        "tgn:1000003",
        "tgn:7000084",
        "tgn:7029392"
    ],
    "tgn:id":7147122,
    "tgn:name":"Kohlen-Berg",
    "tgn:placetype":[
        "aat:300008777"
    ]
},
  "bbox": [],
  "geometry": {"coordinates":[13.583333,52.966667],"type":"Point"}
}