{
  "id": 2438644,
  "type": "Feature",
  "properties": {
    "tgn:hierarchy":[
        "tgn:2438644",
        "tgn:1000001",
        "tgn:7012149",
        "tgn:2002116",
        "tgn:7007827",
        "tgn:7029392"
    ],
    "tgn:id":2438644,
    "tgn:name":"Kingston Canyon",
    "tgn:placetype":[
        "aat:300008761"
    ]
},
  "bbox": [],
  "geometry": {"coordinates":[-112.0167,38.15],"type":"Point"}
}