{
  "id": 7591357,
  "type": "Feature",
  "properties": {
    "tgn:hierarchy":[
        "tgn:7591357",
        "tgn:1000004",
        "tgn:7000198",
        "tgn:7000799",
        "tgn:7029392"
    ],
    "tgn:id":7591357,
    "tgn:name:en":"Marh\u016b\u012bn",
    "tgn:placetype":[
        "aat:300008347"
    ]
},
  "bbox": [],
  "geometry": {"coordinates":[74.948333,32.588361],"type":"Point"}
}