{
  "id": 7496221,
  "type": "Feature",
  "properties": {
    "tgn:hierarchy":[
        "tgn:7496221",
        "tgn:7487020",
        "tgn:1000004",
        "tgn:1000141",
        "tgn:7029392"
    ],
    "tgn:id":7496221,
    "tgn:name":"Ankeng",
    "tgn:placetype":[
        "aat:300008699"
    ]
},
  "bbox": [],
  "geometry": {"coordinates":[120.871218,24.419546],"type":"Point"}
}