{
  "id": 2429456,
  "type": "Feature",
  "properties": {
    "tgn:hierarchy":[
        "tgn:2429456",
        "tgn:1000001",
        "tgn:7006451",
        "tgn:7012149",
        "tgn:2000099",
        "tgn:7029392"
    ],
    "tgn:id":2429456,
    "tgn:name":"Juniper Grove Wash",
    "tgn:placetype":[
        "aat:300008761"
    ]
},
  "bbox": [],
  "geometry": {"coordinates":[-110.3833,36.3333],"type":"Point"}
}