{
  "id": 2556892,
  "type": "Feature",
  "properties": {
    "tgn:hierarchy":[
        "tgn:2556892",
        "tgn:1000001",
        "tgn:7006451",
        "tgn:7012149",
        "tgn:2000103",
        "tgn:7029392"
    ],
    "tgn:id":2556892,
    "tgn:name":"Old East Side Tank",
    "tgn:placetype":[
        "aat:300006191"
    ]
},
  "bbox": [],
  "geometry": {"coordinates":[-112.0167,34.4167],"type":"Point"}
}