{
  "id": 2521592,
  "type": "Feature",
  "properties": {
    "tgn:hierarchy":[
        "tgn:2521592",
        "tgn:2000296",
        "tgn:1000001",
        "tgn:7012149",
        "tgn:7007248",
        "tgn:7029392"
    ],
    "tgn:id":2521592,
    "tgn:name":"Montpelier",
    "tgn:placetype":[
        "aat:300008347"
    ]
},
  "bbox": [],
  "geometry": {"coordinates":[-83.15,33.0667],"type":"Point"}
}