<<<<<<< HEAD
{
  "id": 2765088,
  "type": "Feature",
  "properties": {
    "tgn:hierarchy":[
        "tgn:2765088",
        "tgn:1000001",
        "tgn:7012149",
        "tgn:2001717",
        "tgn:7007708",
        "tgn:7029392"
    ],
    "tgn:id":2765088,
    "tgn:name":"Whisky Springs",
    "tgn:placetype":[
        "aat:300008697"
    ]
},
  "bbox": [],
  "geometry": {"coordinates":[-122.6,44.3667],"type":"Point"}
}
=======
{"geometry":{"type":"Point","coordinates":[-122.600000,44.366700]},"type":"Feature","properties":{"hierarchy":["tgn:2765088","tgn:1000001","tgn:7012149","tgn:2001717","tgn:7007708","tgn:7029392"],"placetype":["aat:300008697"],"id":2765088,"name:xx":"Whisky Springs"}}
>>>>>>> 03f74aca74312dbeaf24d7e61306dd6a786dc3d0
