{
  "id": 1008995,
  "type": "Feature",
  "properties": {
    "tgn:hierarchy":[
        "tgn:1008995",
        "tgn:1003468",
        "tgn:1000003",
        "tgn:7010380",
        "tgn:1000080",
        "tgn:7029392"
    ],
    "tgn:id":1008995,
    "tgn:name":"Sant'Andrea, Isola",
    "tgn:placetype":[
        "aat:300008791"
    ]
},
  "bbox": [],
  "geometry": {"coordinates":[17.949167,40.049167],"type":"Point"}
}