<<<<<<< HEAD
{
  "id": 2258023,
  "type": "Feature",
  "properties": {
    "tgn:hierarchy":[
        "tgn:2258023",
        "tgn:1000001",
        "tgn:7012149",
        "tgn:1002409",
        "tgn:7007157",
        "tgn:7029392"
    ],
    "tgn:id":2258023,
    "tgn:name":"Cory",
    "tgn:placetype":[
        "aat:300008347"
    ]
},
  "bbox": [],
  "geometry": {"coordinates":[-122.1333,39.7667],"type":"Point"}
}
=======
{"geometry":{"type":"Point","coordinates":[-122.133300,39.766700]},"type":"Feature","properties":{"hierarchy":["tgn:2258023","tgn:1000001","tgn:7012149","tgn:1002409","tgn:7007157","tgn:7029392"],"placetype":["aat:300008347"],"id":2258023,"name:xx":"Cory"}}
>>>>>>> 03f74aca74312dbeaf24d7e61306dd6a786dc3d0
