{
  "id": 7529786,
  "type": "Feature",
  "properties": {
    "tgn:hierarchy":[
        "tgn:7529786",
        "tgn:7001242",
        "tgn:7016833",
        "tgn:1001083",
        "tgn:7029392"
    ],
    "tgn:id":7529786,
    "tgn:name":"Masjid \u015eal\u0101\u1e29 ad D\u012bn",
    "tgn:placetype":[
        "aat:300007544"
    ]
},
  "bbox": [],
  "geometry": {"coordinates":[31.225025,30.028732],"type":"Point"}
}