{
  "id": 7278289,
  "type": "Feature",
  "properties": {
    "tgn:hierarchy":[
        "tgn:7278289",
        "tgn:1001630",
        "tgn:1000049",
        "tgn:1000002",
        "tgn:7029392"
    ],
    "tgn:id":7278289,
    "tgn:name":"Vizcachitas",
    "tgn:placetype":[
        "aat:300007783"
    ]
},
  "bbox": [],
  "geometry": {"coordinates":[-70.783333,-28.833333],"type":"Point"}
}