{
  "id": 7287177,
  "type": "Feature",
  "properties": {
    "tgn:hierarchy":[
        "tgn:7287177",
        "tgn:7016598",
        "tgn:1000049",
        "tgn:1000002",
        "tgn:7029392"
    ],
    "tgn:id":7287177,
    "tgn:name":"Garri Muerto, Pampa",
    "tgn:placetype":[
        "aat:300008805"
    ]
},
  "bbox": [],
  "geometry": {"coordinates":[-68.533333,-21.85],"type":"Point"}
}