{
  "id": 7566849,
  "type": "Feature",
  "properties": {
    "tgn:hierarchy":[
        "tgn:7566849",
        "tgn:1001828",
        "tgn:1000004",
        "tgn:7000198",
        "tgn:7029392"
    ],
    "tgn:id":7566849,
    "tgn:name:en":"Jagampet",
    "tgn:placetype":[
        "aat:300008347"
    ]
},
  "bbox": [],
  "geometry": {"coordinates":[78.153889,17.825833],"type":"Point"}
}