{
  "id": 2563006,
  "type": "Feature",
  "properties": {
    "tgn:hierarchy":[
        "tgn:2563006",
        "tgn:1000001",
        "tgn:7012149",
        "tgn:1003017",
        "tgn:7007710",
        "tgn:7029392"
    ],
    "tgn:id":2563006,
    "tgn:name":"Owen Reservoir",
    "tgn:placetype":[
        "aat:300006191"
    ]
},
  "bbox": [],
  "geometry": {"coordinates":[-79.5667,40.5833],"type":"Point"}
}