<<<<<<< HEAD
{
  "id": 2330948,
  "type": "Feature",
  "properties": {
    "tgn:hierarchy":[
        "tgn:2330948",
        "tgn:1000001",
        "tgn:2001583",
        "tgn:7012149",
        "tgn:7007705",
        "tgn:7029392"
    ],
    "tgn:id":2330948,
    "tgn:name":"Flat Rock Butte",
    "tgn:placetype":[
        "aat:300008798"
    ]
},
  "bbox": [],
  "geometry": {"coordinates":[-103.85,47.4333],"type":"Point"}
}
=======
{"geometry":{"type":"Point","coordinates":[-103.850000,47.433300]},"type":"Feature","properties":{"hierarchy":["tgn:2330948","tgn:1000001","tgn:2001583","tgn:7012149","tgn:7007705","tgn:7029392"],"placetype":["aat:300008798"],"id":2330948,"name:xx":"Flat Rock Butte"}}
>>>>>>> 03f74aca74312dbeaf24d7e61306dd6a786dc3d0
