{
  "id": 7583076,
  "type": "Feature",
  "properties": {
    "tgn:hierarchy":[
        "tgn:7583076",
        "tgn:1000004",
        "tgn:7000198",
        "tgn:7016788",
        "tgn:7029392"
    ],
    "tgn:id":7583076,
    "tgn:name:en":"Syon\u0101thpura",
    "tgn:placetype":[
        "aat:300008347"
    ]
},
  "bbox": [],
  "geometry": {"coordinates":[75.577409,28.014209],"type":"Point"}
}