{
  "id": 1010662,
  "type": "Feature",
  "properties": {
    "tgn:hierarchy":[
        "tgn:1010662",
        "tgn:7005402",
        "tgn:1000001",
        "tgn:7005388",
        "tgn:7029392"
    ],
    "tgn:id":1010662,
    "tgn:name":"Enga\u00f1o, Cabo",
    "tgn:placetype":[
        "aat:300008850"
    ]
},
  "bbox": [],
  "geometry": {"coordinates":[-68.327,18.616],"type":"Point"}
}