{
  "id": 2322220,
  "type": "Feature",
  "properties": {
    "tgn:hierarchy":[
        "tgn:2322220",
        "tgn:1000001",
        "tgn:7013942",
        "tgn:7012149",
        "tgn:7007517",
        "tgn:7029392"
    ],
    "tgn:id":2322220,
    "tgn:name":"Fall River Reservoir",
    "tgn:placetype":[
        "aat:300006191"
    ]
},
  "bbox": [],
  "geometry": {"coordinates":[-72.5333,42.6167],"type":"Point"}
}