{
  "id": 2106673,
  "type": "Feature",
  "properties": {
    "tgn:hierarchy":[
        "tgn:2106673",
        "tgn:1000001",
        "tgn:2001936",
        "tgn:7012149",
        "tgn:7007826",
        "tgn:7029392"
    ],
    "tgn:id":2106673,
    "tgn:name":"Peggy",
    "tgn:placetype":[
        "aat:300008347"
    ]
},
  "bbox": [],
  "geometry": {"coordinates":[-98.1667,28.7333],"type":"Point"}
}