{
  "id": 7348669,
  "type": "Feature",
  "properties": {
    "tgn:hierarchy":[
        "tgn:7348669",
        "tgn:1001853",
        "tgn:1000001",
        "tgn:7005560",
        "tgn:7029392"
    ],
    "tgn:id":7348669,
    "tgn:name":"Rancho Agritos",
    "tgn:placetype":[
        "aat:300000241"
    ]
},
  "bbox": [],
  "geometry": {"coordinates":[-102.833333,28.083333],"type":"Point"}
}