<<<<<<< HEAD
{
  "id": 7116425,
  "type": "Feature",
  "properties": {
    "tgn:hierarchy":[
        "tgn:7116425",
        "tgn:1000003",
        "tgn:7003687",
        "tgn:7000084",
        "tgn:7029392"
    ],
    "tgn:id":7116425,
    "tgn:name":"Osendorf",
    "tgn:placetype":[
        "aat:300008347"
    ]
},
  "bbox": [],
  "geometry": {"coordinates":[12.016667,51.416667],"type":"Point"}
}
=======
{"geometry":{"type":"Point","coordinates":[12.016667,51.416667]},"type":"Feature","properties":{"hierarchy":["tgn:7116425","tgn:1000003","tgn:7003687","tgn:7000084","tgn:7029392"],"placetype":["aat:300008347"],"id":7116425,"name:xx":"Osendorf"}}
>>>>>>> 03f74aca74312dbeaf24d7e61306dd6a786dc3d0
