{
  "id": 1013406,
  "type": "Feature",
  "properties": {
    "tgn:hierarchy":[
        "tgn:1013406",
        "tgn:7005735",
        "tgn:7005685",
        "tgn:1000001",
        "tgn:7013409",
        "tgn:7029392"
    ],
    "tgn:id":1013406,
    "tgn:name":"Brentwood Bay",
    "tgn:placetype":[
        "aat:300008347"
    ]
},
  "bbox": [],
  "geometry": {"coordinates":[-123.4667,48.5833],"type":"Point"}
}