{
  "id": 2718438,
  "type": "Feature",
  "properties": {
    "tgn:hierarchy":[
        "tgn:2718438",
        "tgn:1000001",
        "tgn:7012149",
        "tgn:2000559",
        "tgn:7007252",
        "tgn:7029392"
    ],
    "tgn:id":2718438,
    "tgn:name":"Thompson Lake",
    "tgn:placetype":[
        "aat:300006191"
    ]
},
  "bbox": [],
  "geometry": {"coordinates":[-87.3333,39.4333],"type":"Point"}
}