{
  "id": 2051348,
  "type": "Feature",
  "properties": {
    "tgn:hierarchy":[
        "tgn:2051348",
        "tgn:1000001",
        "tgn:7012149",
        "tgn:1002679",
        "tgn:7007520",
        "tgn:7029392"
    ],
    "tgn:id":2051348,
    "tgn:name":"Bolles Harbor",
    "tgn:placetype":[
        "aat:300008347"
    ]
},
  "bbox": [],
  "geometry": {"coordinates":[-83.3833,41.8667],"type":"Point"}
}