{
  "id": 2717000,
  "type": "Feature",
  "properties": {
    "tgn:hierarchy":[
        "tgn:2717000",
        "tgn:1000001",
        "tgn:7012149",
        "tgn:2002357",
        "tgn:7007922",
        "tgn:7029392"
    ],
    "tgn:id":2717000,
    "tgn:name":"Thimble Peak",
    "tgn:placetype":[
        "aat:300008798"
    ]
},
  "bbox": [],
  "geometry": {"coordinates":[-91.2167,44.1667],"type":"Point"}
}