{
  "id": 2645310,
  "type": "Feature",
  "properties": {
    "tgn:hierarchy":[
        "tgn:2645310",
        "tgn:1000001",
        "tgn:2001412",
        "tgn:7012149",
        "tgn:7007526",
        "tgn:7029392"
    ],
    "tgn:id":2645310,
    "tgn:name":"Savage Mine",
    "tgn:placetype":[
        "aat:300000390"
    ]
},
  "bbox": [],
  "geometry": {"coordinates":[-117.35,37.7167],"type":"Point"}
}