{
  "id": 7097392,
  "type": "Feature",
  "properties": {
    "tgn:hierarchy":[
        "tgn:7097392",
        "tgn:1000003",
        "tgn:7003684",
        "tgn:7000084",
        "tgn:7029392"
    ],
    "tgn:id":7097392,
    "tgn:name":"Seyweiler",
    "tgn:placetype":[
        "aat:300008347"
    ]
},
  "bbox": [],
  "geometry": {"coordinates":[7.266667,49.15],"type":"Point"}
}