{
  "id": 7372938,
  "type": "Feature",
  "properties": {
    "tgn:hierarchy":[
        "tgn:7372938",
        "tgn:1000001",
        "tgn:7005595",
        "tgn:7005560",
        "tgn:7029392"
    ],
    "tgn:id":7372938,
    "tgn:name":"La Laguna",
    "tgn:placetype":[
        "aat:300008347"
    ]
},
  "bbox": [],
  "geometry": {"coordinates":[-108.456389,26.5825],"type":"Point"}
}