{
  "id": 7486450,
  "type": "Feature",
  "properties": {
    "tgn:hierarchy":[
        "tgn:7486450",
        "tgn:1000004",
        "tgn:7489179",
        "tgn:1000141",
        "tgn:7029392"
    ],
    "tgn:id":7486450,
    "tgn:name":"Gangkou",
    "tgn:placetype":[
        "aat:300008347"
    ]
},
  "bbox": [],
  "geometry": {"coordinates":[121.835556,24.871111],"type":"Point"}
}