{
  "id": 7588757,
  "type": "Feature",
  "properties": {
    "tgn:hierarchy":[
        "tgn:7588757",
        "tgn:1000004",
        "tgn:7000198",
        "tgn:7000799",
        "tgn:7029392"
    ],
    "tgn:id":7588757,
    "tgn:name:en":"Balh\u0101r",
    "tgn:placetype":[
        "aat:300008347"
    ]
},
  "bbox": [],
  "geometry": {"coordinates":[74.045677,33.660053],"type":"Point"}
}