{
  "id": 1048801,
  "type": "Feature",
  "properties": {
    "tgn:hierarchy":[
        "tgn:1048801",
        "tgn:7003656",
        "tgn:1000003",
        "tgn:1000088",
        "tgn:7029392"
    ],
    "tgn:id":1048801,
    "tgn:name":"Tonstad",
    "tgn:placetype":[
        "aat:300008347"
    ]
},
  "bbox": [],
  "geometry": {"coordinates":[6.7167,58.6667],"type":"Point"}
}