{
  "id": 2657723,
  "type": "Feature",
  "properties": {
    "tgn:hierarchy":[
        "tgn:2657723",
        "tgn:1000001",
        "tgn:7012149",
        "tgn:2001300",
        "tgn:7007524",
        "tgn:7029392"
    ],
    "tgn:id":2657723,
    "tgn:name":"Shelf Lake",
    "tgn:placetype":[
        "aat:300008680"
    ]
},
  "bbox": [],
  "geometry": {"coordinates":[-114.1667,45.7333],"type":"Point"}
}