{
  "id": 2703777,
  "type": "Feature",
  "properties": {
    "tgn:hierarchy":[
        "tgn:2703777",
        "tgn:1000001",
        "tgn:2001266",
        "tgn:7012149",
        "tgn:7007524",
        "tgn:7029392"
    ],
    "tgn:id":2703777,
    "tgn:name":"Sun Mountain",
    "tgn:placetype":[
        "aat:300008798"
    ]
},
  "bbox": [],
  "geometry": {"coordinates":[-110.7667,47.05],"type":"Point"}
}