{
  "id": 7297362,
  "type": "Feature",
  "properties": {
    "tgn:hierarchy":[
        "tgn:7297362",
        "tgn:7002759",
        "tgn:7002843",
        "tgn:1000003",
        "tgn:1000095",
        "tgn:7029392"
    ],
    "tgn:id":7297362,
    "tgn:name":"Tajo, Barranco del",
    "tgn:placetype":[
        "aat:300266554",
        "aat:300008699"
    ]
},
  "bbox": [],
  "geometry": {"coordinates":[-0.55,40.516667],"type":"Point"}
}