{
  "id": 2549226,
  "type": "Feature",
  "properties": {
    "tgn:hierarchy":[
        "tgn:2549226",
        "tgn:7002659",
        "tgn:1000001",
        "tgn:7012149",
        "tgn:2000062",
        "tgn:7029392"
    ],
    "tgn:id":2549226,
    "tgn:name":"North River Country Club Estates",
    "tgn:placetype":[
        "aat:300008347"
    ]
},
  "bbox": [],
  "geometry": {"coordinates":[-87.55,33.35],"type":"Point"}
}