{
  "id": 7080348,
  "type": "Feature",
  "properties": {
    "tgn:hierarchy":[
        "tgn:7080348",
        "tgn:7003692",
        "tgn:1000003",
        "tgn:7000084",
        "tgn:7029392"
    ],
    "tgn:id":7080348,
    "tgn:name":"Wolfental",
    "tgn:placetype":[
        "aat:300008761"
    ]
},
  "bbox": [],
  "geometry": {"coordinates":[9.766667,48.083333],"type":"Point"}
}