{
  "id": 7034984,
  "type": "Feature",
  "properties": {
    "tgn:hierarchy":[
        "tgn:7034984",
        "tgn:7003006",
        "tgn:1000003",
        "tgn:7002997",
        "tgn:1000080",
        "tgn:7029392"
    ],
    "tgn:id":7034984,
    "tgn:name":"Alvisopoli",
    "tgn:placetype":[
        "aat:300008347"
    ]
},
  "bbox": [],
  "geometry": {"coordinates":[12.92,45.805833],"type":"Point"}
}