{
  "id": 7183587,
  "type": "Feature",
  "properties": {
    "tgn:hierarchy":[
        "tgn:7183587",
        "tgn:7000096",
        "tgn:1000003",
        "tgn:7000084",
        "tgn:7029392"
    ],
    "tgn:id":7183587,
    "tgn:name":"Gottssee",
    "tgn:placetype":[
        "aat:300008680"
    ]
},
  "bbox": [],
  "geometry": {"coordinates":[13.666667,53.083333],"type":"Point"}
}