{
  "id": 7539084,
  "type": "Feature",
  "properties": {
    "tgn:hierarchy":[
        "tgn:7539084",
        "tgn:7001242",
        "tgn:7016833",
        "tgn:1001335",
        "tgn:7029392"
    ],
    "tgn:id":7539084,
    "tgn:name:en":"Murta\u1e0da",
    "tgn:placetype":[
        "aat:300008347"
    ]
},
  "bbox": [],
  "geometry": {"coordinates":[31.064167,31.592222],"type":"Point"}
}