{
  "id": 7052866,
  "type": "Feature",
  "properties": {
    "tgn:hierarchy":[
        "tgn:7052866",
        "tgn:1000003",
        "tgn:7003152",
        "tgn:7003237",
        "tgn:1000080",
        "tgn:7029392"
    ],
    "tgn:id":7052866,
    "tgn:name":"Malenco, Val",
    "tgn:placetype":[
        "aat:300008761"
    ]
},
  "bbox": [],
  "geometry": {"coordinates":[9.85,46.25],"type":"Point"}
}