{
  "id": 1013767,
  "type": "Feature",
  "properties": {
    "tgn:hierarchy":[
        "tgn:1013767",
        "tgn:7005735",
        "tgn:7005685",
        "tgn:1000001",
        "tgn:7029392"
    ],
    "tgn:id":1013767,
    "tgn:name":"South Slocan",
    "tgn:placetype":[
        "aat:300008347"
    ]
},
  "bbox": [],
  "geometry": {"coordinates":[-117.5333,49.4667],"type":"Point"}
}