{
  "id": 2669559,
  "type": "Feature",
  "properties": {
    "tgn:hierarchy":[
        "tgn:2669559",
        "tgn:1000001",
        "tgn:7012149",
        "tgn:2000471",
        "tgn:7007250",
        "tgn:7029392"
    ],
    "tgn:id":2669559,
    "tgn:name":"Slide Lake",
    "tgn:placetype":[
        "aat:300008680"
    ]
},
  "bbox": [],
  "geometry": {"coordinates":[-115.1167,43.9333],"type":"Point"}
}