{
  "id": 2170964,
  "type": "Feature",
  "properties": {
    "tgn:hierarchy":[
        "tgn:2170964",
        "tgn:1000001",
        "tgn:2001014",
        "tgn:7012149",
        "tgn:7007521",
        "tgn:7029392"
    ],
    "tgn:id":2170964,
    "tgn:name":"Big Snow Lake",
    "tgn:placetype":[
        "aat:300008680"
    ]
},
  "bbox": [],
  "geometry": {"coordinates":[-90.9667,47.7833],"type":"Point"}
}