{
  "id": 2639365,
  "type": "Feature",
  "properties": {
    "tgn:hierarchy":[
        "tgn:2639365",
        "tgn:1000001",
        "tgn:7006451",
        "tgn:7012149",
        "tgn:2000099",
        "tgn:7029392"
    ],
    "tgn:id":2639365,
    "tgn:name":"Salt Water Spring",
    "tgn:placetype":[
        "aat:300008697"
    ]
},
  "bbox": [],
  "geometry": {"coordinates":[-110.0167,36.2167],"type":"Point"}
}