{
  "id": 7543794,
  "type": "Feature",
  "properties": {
    "tgn:hierarchy":[
        "tgn:7543794",
        "tgn:7001242",
        "tgn:1001059",
        "tgn:7016833",
        "tgn:7029392"
    ],
    "tgn:id":7543794,
    "tgn:name":"Tur'at al F\u0101\u015fil",
    "tgn:placetype":[
        "aat:300006075"
    ]
},
  "bbox": [],
  "geometry": {"coordinates":[31.504733,31.292258],"type":"Point"}
}