<<<<<<< HEAD
{
  "id": 2336580,
  "type": "Feature",
  "properties": {
    "tgn:hierarchy":[
        "tgn:2336580",
        "tgn:1000001",
        "tgn:1002245",
        "tgn:7012149",
        "tgn:7007568",
        "tgn:7029392"
    ],
    "tgn:id":2336580,
    "tgn:name":"Four Mile",
    "tgn:placetype":[
        "aat:300008347"
    ]
},
  "bbox": [],
  "geometry": {"coordinates":[-78.45,42.0167],"type":"Point"}
}
=======
{"geometry":{"type":"Point","coordinates":[-78.450000,42.016700]},"type":"Feature","properties":{"hierarchy":["tgn:2336580","tgn:1000001","tgn:1002245","tgn:7012149","tgn:7007568","tgn:7029392"],"placetype":["aat:300008347"],"id":2336580,"name:xx":"Four Mile"}}
>>>>>>> 03f74aca74312dbeaf24d7e61306dd6a786dc3d0
