{
  "id": 7161637,
  "type": "Feature",
  "properties": {
    "tgn:hierarchy":[
        "tgn:7161637",
        "tgn:7000096",
        "tgn:1000003",
        "tgn:7000084",
        "tgn:7029392"
    ],
    "tgn:id":7161637,
    "tgn:name":"Hoher Berg",
    "tgn:placetype":[
        "aat:300008777"
    ]
},
  "bbox": [],
  "geometry": {"coordinates":[14.583333,51.616667],"type":"Point"}
}