<<<<<<< HEAD
{
  "id": 7056878,
  "type": "Feature",
  "properties": {
    "tgn:hierarchy":[
        "tgn:7056878",
        "tgn:7003168",
        "tgn:1000003",
        "tgn:7009760",
        "tgn:1000080",
        "tgn:7029392"
    ],
    "tgn:id":7056878,
    "tgn:name":"Abadia a Isola",
    "tgn:placetype":[
        "aat:300008347"
    ]
},
  "bbox": [],
  "geometry": {"coordinates":[11.2,43.383333],"type":"Point"}
}
=======
{"geometry":{"type":"Point","coordinates":[11.200000,43.383333]},"type":"Feature","properties":{"hierarchy":["tgn:7056878","tgn:7003168","tgn:1000003","tgn:7009760","tgn:1000080","tgn:7029392"],"placetype":["aat:300008347"],"id":7056878,"name:xx":"Abadia a Isola"}}
>>>>>>> 03f74aca74312dbeaf24d7e61306dd6a786dc3d0
