{
  "id": 2166002,
  "type": "Feature",
  "properties": {
    "tgn:hierarchy":[
        "tgn:2166002",
        "tgn:1000001",
        "tgn:7012149",
        "tgn:2002112",
        "tgn:7007827",
        "tgn:7029392"
    ],
    "tgn:id":2166002,
    "tgn:name":"Big Baldy",
    "tgn:placetype":[
        "aat:300008798"
    ]
},
  "bbox": [],
  "geometry": {"coordinates":[-111.75,39.3833],"type":"Point"}
}