{
  "id": 2144434,
  "type": "Feature",
  "properties": {
    "tgn:hierarchy":[
        "tgn:2144434",
        "tgn:1000001",
        "tgn:7012149",
        "tgn:1002439",
        "tgn:7007252",
        "tgn:7029392"
    ],
    "tgn:id":2144434,
    "tgn:name":"Bakers Corner",
    "tgn:placetype":[
        "aat:300008347"
    ]
},
  "bbox": [],
  "geometry": {"coordinates":[-86.1333,40.1167],"type":"Point"}
}