{
  "id": 2551983,
  "type": "Feature",
  "properties": {
    "tgn:hierarchy":[
        "tgn:2551983",
        "tgn:1000001",
        "tgn:7012149",
        "tgn:1002468",
        "tgn:7007252",
        "tgn:7029392"
    ],
    "tgn:id":2551983,
    "tgn:name":"Number Four Arm",
    "tgn:placetype":[
        "aat:300008699"
    ]
},
  "bbox": [],
  "geometry": {"coordinates":[-85.2167,39.9833],"type":"Point"}
}