{
  "id": 7562393,
  "type": "Feature",
  "properties": {
    "tgn:hierarchy":[
        "tgn:7562393",
        "tgn:1000004",
        "tgn:7000198",
        "tgn:1001894",
        "tgn:7029392"
    ],
    "tgn:id":7562393,
    "tgn:name:en":"Rampura",
    "tgn:placetype":[
        "aat:300008347"
    ]
},
  "bbox": [],
  "geometry": {"coordinates":[79.034955,26.488065],"type":"Point"}
}