{
  "id": 2553639,
  "type": "Feature",
  "properties": {
    "tgn:hierarchy":[
        "tgn:2553639",
        "tgn:1000001",
        "tgn:1002270",
        "tgn:7012149",
        "tgn:7007708",
        "tgn:7029392"
    ],
    "tgn:id":2553639,
    "tgn:name":"Oak Grove",
    "tgn:placetype":[
        "aat:300055621"
    ]
},
  "bbox": [],
  "geometry": {"coordinates":[-122.0333,45.0833],"type":"Point"}
}