{
  "id": 2222888,
  "type": "Feature",
  "properties": {
    "tgn:hierarchy":[
        "tgn:2222888",
        "tgn:1000001",
        "tgn:7006451",
        "tgn:7012149",
        "tgn:2000101",
        "tgn:7029392"
    ],
    "tgn:id":2222888,
    "tgn:name":"Carrico Spring",
    "tgn:placetype":[
        "aat:300008697"
    ]
},
  "bbox": [],
  "geometry": {"coordinates":[-110.6167,32.8833],"type":"Point"}
}