{
  "id": 2197561,
  "type": "Feature",
  "properties": {
    "tgn:hierarchy":[
        "tgn:2197561",
        "tgn:1000001",
        "tgn:7012149",
        "tgn:2000928",
        "tgn:7007515",
        "tgn:7029392"
    ],
    "tgn:id":2197561,
    "tgn:name":"Brown Hill",
    "tgn:placetype":[
        "aat:300008798"
    ]
},
  "bbox": [],
  "geometry": {"coordinates":[-69.4833,45.1833],"type":"Point"}
}