{
  "id": 7579439,
  "type": "Feature",
  "properties": {
    "tgn:hierarchy":[
        "tgn:7579439",
        "tgn:1000004",
        "tgn:7031781",
        "tgn:7000198",
        "tgn:7029392"
    ],
    "tgn:id":7579439,
    "tgn:name:en":"T\u0101tedh\u0101r",
    "tgn:placetype":[
        "aat:300008347"
    ]
},
  "bbox": [],
  "geometry": {"coordinates":[81.886599,22.573794],"type":"Point"}
}