{
  "id": 7439209,
  "type": "Feature",
  "properties": {
    "tgn:hierarchy":[
        "tgn:7439209",
        "tgn:1000001",
        "tgn:7005597",
        "tgn:7005560",
        "tgn:7029392"
    ],
    "tgn:id":7439209,
    "tgn:name":"San Vicente, Barra",
    "tgn:placetype":[
        "aat:300386885"
    ]
},
  "bbox": [],
  "geometry": {"coordinates":[-97.75,23.266667],"type":"Point"}
}