<<<<<<< HEAD
{
  "id": 2255334,
  "type": "Feature",
  "properties": {
    "tgn:hierarchy":[
        "tgn:2255334",
        "tgn:7014201",
        "tgn:1000001",
        "tgn:7012149",
        "tgn:7007239",
        "tgn:7029392"
    ],
    "tgn:id":2255334,
    "tgn:name":"Coopers Island",
    "tgn:placetype":[
        "aat:300008791"
    ]
},
  "bbox": [],
  "geometry": {"coordinates":[-75.5667,39.7167],"type":"Point"}
}
=======
{"geometry":{"type":"Point","coordinates":[-75.566700,39.716700]},"type":"Feature","properties":{"hierarchy":["tgn:2255334","tgn:7014201","tgn:1000001","tgn:7012149","tgn:7007239","tgn:7029392"],"placetype":["aat:300008791"],"id":2255334,"name:xx":"Coopers Island"}}
>>>>>>> 03f74aca74312dbeaf24d7e61306dd6a786dc3d0
