{
  "id": 2255334,
  "type": "Feature",
  "properties": {
    "tgn:hierarchy":[
        "tgn:2255334",
        "tgn:7014201",
        "tgn:1000001",
        "tgn:7012149",
        "tgn:7007239",
        "tgn:7029392"
    ],
    "tgn:id":2255334,
    "tgn:name":"Coopers Island",
    "tgn:placetype":[
        "aat:300008791"
    ]
},
  "bbox": [],
  "geometry": {"coordinates":[-75.5667,39.7167],"type":"Point"}
}