{
  "id": 7001601,
  "type": "Feature",
  "properties": {
    "tgn:hierarchy":[
        "tgn:7001601",
        "tgn:7001242",
        "tgn:1000149",
        "tgn:7000392",
        "tgn:7029392"
    ],
    "tgn:id":7001601,
    "tgn:name":"Namibe",
    "tgn:placetype":[
        "aat:300008347",
        "aat:300387223",
        "aat:300008375",
        "aat:300120599"
    ]
},
  "bbox": [],
  "geometry": {"coordinates":[12.15,-15.1667],"type":"Point"}
}