{
  "id": 2187498,
  "type": "Feature",
  "properties": {
    "tgn:hierarchy":[
        "tgn:2187498",
        "tgn:1000001",
        "tgn:7012149",
        "tgn:2001144",
        "tgn:7007522",
        "tgn:7029392"
    ],
    "tgn:id":2187498,
    "tgn:name":"Booneville Lake",
    "tgn:placetype":[
        "aat:300006191"
    ]
},
  "bbox": [],
  "geometry": {"coordinates":[-88.55,34.6333],"type":"Point"}
}