{
  "id": 2537204,
  "type": "Feature",
  "properties": {
    "tgn:hierarchy":[
        "tgn:2537204",
        "tgn:1000001",
        "tgn:7012149",
        "tgn:2001901",
        "tgn:7007825",
        "tgn:7029392"
    ],
    "tgn:id":2537204,
    "tgn:name":"Negro Branch",
    "tgn:placetype":[
        "aat:300008699"
    ]
},
  "bbox": [],
  "geometry": {"coordinates":[-84.65,36.2167],"type":"Point"}
}