{
  "id": 7557975,
  "type": "Feature",
  "properties": {
    "tgn:hierarchy":[
        "tgn:7557975",
        "tgn:1000004",
        "tgn:7000198",
        "tgn:7016694",
        "tgn:7029392"
    ],
    "tgn:id":7557975,
    "tgn:name:en":"Rarb\u0101h\u0101l",
    "tgn:placetype":[
        "aat:300008347"
    ]
},
  "bbox": [],
  "geometry": {"coordinates":[83.05,20.566667],"type":"Point"}
}