{
  "id": 7069661,
  "type": "Feature",
  "properties": {
    "tgn:hierarchy":[
        "tgn:7069661",
        "tgn:7003669",
        "tgn:1000003",
        "tgn:7000084",
        "tgn:7029392"
    ],
    "tgn:id":7069661,
    "tgn:name":"Thonbach",
    "tgn:placetype":[
        "aat:300008347"
    ]
},
  "bbox": [],
  "geometry": {"coordinates":[12.15,48.15],"type":"Point"}
}