{
  "id": 7094529,
  "type": "Feature",
  "properties": {
    "tgn:hierarchy":[
        "tgn:7094529",
        "tgn:1000003",
        "tgn:7003688",
        "tgn:7000084",
        "tgn:7029392"
    ],
    "tgn:id":7094529,
    "tgn:name":"Seeb\u00fcll",
    "tgn:placetype":[
        "aat:300000206"
    ]
},
  "bbox": [],
  "geometry": {"coordinates":[8.783333,54.883333],"type":"Point"}
}