{
  "id": 2433602,
  "type": "Feature",
  "properties": {
    "tgn:hierarchy":[
        "tgn:2433602",
        "tgn:1000001",
        "tgn:2001429",
        "tgn:7012149",
        "tgn:7007566",
        "tgn:7029392"
    ],
    "tgn:id":2433602,
    "tgn:name":"Kelly Brushy Tank",
    "tgn:placetype":[
        "aat:300006191"
    ]
},
  "bbox": [],
  "geometry": {"coordinates":[-108.8333,33.5333],"type":"Point"}
}