{
  "id": 2214108,
  "type": "Feature",
  "properties": {
    "tgn:hierarchy":[
        "tgn:2214108",
        "tgn:1000001",
        "tgn:7012149",
        "tgn:7007157",
        "tgn:1002864",
        "tgn:7029392"
    ],
    "tgn:id":2214108,
    "tgn:name":"Cahill Ridge",
    "tgn:placetype":[
        "aat:300266640"
    ]
},
  "bbox": [],
  "geometry": {"coordinates":[-122.3833,37.5167],"type":"Point"}
}