{
  "id": 2474661,
  "type": "Feature",
  "properties": {
    "tgn:hierarchy":[
        "tgn:2474661",
        "tgn:1000001",
        "tgn:1003037",
        "tgn:7012149",
        "tgn:7007516",
        "tgn:7029392"
    ],
    "tgn:id":2474661,
    "tgn:name":"Lower Sinepuxent Neck",
    "tgn:placetype":[
        "aat:300008850"
    ]
},
  "bbox": [],
  "geometry": {"coordinates":[-75.1667,38.2333],"type":"Point"}
}