{
  "id": 2613179,
  "type": "Feature",
  "properties": {
    "tgn:hierarchy":[
        "tgn:2613179",
        "tgn:1000001",
        "tgn:7012149",
        "tgn:7007157",
        "tgn:1002869",
        "tgn:7029392"
    ],
    "tgn:id":2613179,
    "tgn:name":"Redwood Springs",
    "tgn:placetype":[
        "aat:300008697"
    ]
},
  "bbox": [],
  "geometry": {"coordinates":[-122.05,37.05],"type":"Point"}
}