{
  "id": 2097414,
  "type": "Feature",
  "properties": {
    "tgn:hierarchy":[
        "tgn:2097414",
        "tgn:1000001",
        "tgn:2001793",
        "tgn:7012149",
        "tgn:7007713",
        "tgn:7029392"
    ],
    "tgn:id":2097414,
    "tgn:name":"Oelrichs",
    "tgn:placetype":[
        "aat:300008347"
    ]
},
  "bbox": [],
  "geometry": {"coordinates":[-103.2167,43.1667],"type":"Point"}
}