{
  "id": 7302608,
  "type": "Feature",
  "properties": {
    "tgn:hierarchy":[
        "tgn:7302608",
        "tgn:7002806",
        "tgn:7001158",
        "tgn:1000003",
        "tgn:1000095",
        "tgn:7029392"
    ],
    "tgn:id":7302608,
    "tgn:name":"Palacios Rubios",
    "tgn:placetype":[
        "aat:300008347"
    ]
},
  "bbox": [],
  "geometry": {"coordinates":[-4.766667,41.016667],"type":"Point"}
}