{
  "id": 7079407,
  "type": "Feature",
  "properties": {
    "tgn:hierarchy":[
        "tgn:7079407",
        "tgn:1000003",
        "tgn:7003678",
        "tgn:7000084",
        "tgn:7029392"
    ],
    "tgn:id":7079407,
    "tgn:name":"Wolfsburg",
    "tgn:placetype":[
        "aat:300004792"
    ]
},
  "bbox": [],
  "geometry": {"coordinates":[9.766667,51.366667],"type":"Point"}
}