{
  "id": 2413515,
  "type": "Feature",
  "properties": {
    "tgn:hierarchy":[
        "tgn:2413515",
        "tgn:1000001",
        "tgn:7012149",
        "tgn:1002785",
        "tgn:7007920",
        "tgn:7029392"
    ],
    "tgn:id":2413515,
    "tgn:name":"Ipsut Creek",
    "tgn:placetype":[
        "aat:300008706"
    ]
},
  "bbox": [],
  "geometry": {"coordinates":[-121.8667,46.95],"type":"Point"}
}