<<<<<<< HEAD
{
  "id": 2156111,
  "type": "Feature",
  "properties": {
    "tgn:hierarchy":[
        "tgn:2156111",
        "tgn:7002659",
        "tgn:1000001",
        "tgn:7012149",
        "tgn:2000064",
        "tgn:7029392"
    ],
    "tgn:id":2156111,
    "tgn:name":"Beard Hill",
    "tgn:placetype":[
        "aat:300008798"
    ]
},
  "bbox": [],
  "geometry": {"coordinates":[-88.1,31.3],"type":"Point"}
}
=======
{"geometry":{"type":"Point","coordinates":[-88.100000,31.300000]},"type":"Feature","properties":{"hierarchy":["tgn:2156111","tgn:7002659","tgn:1000001","tgn:7012149","tgn:2000064","tgn:7029392"],"placetype":["aat:300008798"],"id":2156111,"name:xx":"Beard Hill"}}
>>>>>>> 03f74aca74312dbeaf24d7e61306dd6a786dc3d0
