{
  "id": 2016110,
  "type": "Feature",
  "properties": {
    "tgn:hierarchy":[
        "tgn:2016110",
        "tgn:1000001",
        "tgn:2000198",
        "tgn:7012149",
        "tgn:7007158",
        "tgn:7029392"
    ],
    "tgn:id":2016110,
    "tgn:name":"Peaceful Valley",
    "tgn:placetype":[
        "aat:300008347",
        "aat:300387247"
    ]
},
  "bbox": [],
  "geometry": {"coordinates":[-105.4833,40.1167],"type":"Point"}
}