{
  "id": 2572644,
  "type": "Feature",
  "properties": {
    "tgn:hierarchy":[
        "tgn:2572644",
        "tgn:1000001",
        "tgn:7012149",
        "tgn:7007919",
        "tgn:7029392"
    ],
    "tgn:id":2572644,
    "tgn:name":"Peak Creek",
    "tgn:placetype":[
        "aat:300008706"
    ]
},
  "bbox": [],
  "geometry": {"coordinates":[-80.95,37.0167],"type":"Point"}
}