{
  "id": 7285740,
  "type": "Feature",
  "properties": {
    "tgn:hierarchy":[
        "tgn:7285740",
        "tgn:1001699",
        "tgn:1000049",
        "tgn:1000002",
        "tgn:7029392"
    ],
    "tgn:id":7285740,
    "tgn:name":"Pucatrihue",
    "tgn:placetype":[
        "aat:300000547"
    ]
},
  "bbox": [],
  "geometry": {"coordinates":[-73.716667,-40.466667],"type":"Point"}
}