{
  "id": 2543249,
  "type": "Feature",
  "properties": {
    "tgn:hierarchy":[
        "tgn:2543249",
        "tgn:1000001",
        "tgn:7012149",
        "tgn:2001219",
        "tgn:7007523",
        "tgn:7029392"
    ],
    "tgn:id":2543249,
    "tgn:name":"Norfolk",
    "tgn:placetype":[
        "aat:300008347"
    ]
},
  "bbox": [],
  "geometry": {"coordinates":[-89.1167,36.9167],"type":"Point"}
}