{
  "id": 7348627,
  "type": "Feature",
  "properties": {
    "tgn:hierarchy":[
        "tgn:7348627",
        "tgn:7005583",
        "tgn:1000001",
        "tgn:7005560",
        "tgn:7029392"
    ],
    "tgn:id":7348627,
    "tgn:name":"Agua Blanca",
    "tgn:placetype":[
        "aat:300008347"
    ]
},
  "bbox": [],
  "geometry": {"coordinates":[-105.766667,24.416667],"type":"Point"}
}