{
  "id": 1126594,
  "type": "Feature",
  "properties": {
    "tgn:hierarchy":[
        "tgn:1126594",
        "tgn:7016612",
        "tgn:1000004",
        "tgn:1001291",
        "tgn:7029392"
    ],
    "tgn:id":1126594,
    "tgn:name":"Musa Qaleh",
    "tgn:placetype":[
        "aat:300008707"
    ]
},
  "bbox": [],
  "geometry": {"coordinates":[64.8333,32.0833],"type":"Point"}
}