{
  "id": 7339837,
  "type": "Feature",
  "properties": {
    "tgn:hierarchy":[
        "tgn:7339837",
        "tgn:7002847",
        "tgn:1001647",
        "tgn:1000003",
        "tgn:1000095",
        "tgn:7029392"
    ],
    "tgn:id":7339837,
    "tgn:name":"Comendador, Puerto del",
    "tgn:placetype":[
        "aat:300259572"
    ]
},
  "bbox": [],
  "geometry": {"coordinates":[-3.966667,39.416667],"type":"Point"}
}