{
  "id": 1079521,
  "type": "Feature",
  "properties": {
    "tgn:hierarchy":[
        "tgn:1079521",
        "tgn:1000004",
        "tgn:1000939",
        "tgn:1000119",
        "tgn:7029392"
    ],
    "tgn:id":1079521,
    "tgn:name":"Giv\u02bbatayim",
    "tgn:placetype":[
        "aat:300008347",
        "aat:300008389",
        "aat:300387302"
    ]
},
  "bbox": [],
  "geometry": {"coordinates":[34.8167,32.0667],"type":"Point"}
}