{
  "id": 7157940,
  "type": "Feature",
  "properties": {
    "tgn:hierarchy":[
        "tgn:7157940",
        "tgn:7003692",
        "tgn:1000003",
        "tgn:7000084",
        "tgn:7029392"
    ],
    "tgn:id":7157940,
    "tgn:name":"Kirschgartshausen",
    "tgn:placetype":[
        "aat:300000206"
    ]
},
  "bbox": [],
  "geometry": {"coordinates":[8.444722,49.581389],"type":"Point"}
}