{
  "id": 7323027,
  "type": "Feature",
  "properties": {
    "tgn:hierarchy":[
        "tgn:7323027",
        "tgn:7002759",
        "tgn:7002843",
        "tgn:1000003",
        "tgn:1000095",
        "tgn:7029392"
    ],
    "tgn:id":7323027,
    "tgn:name":"Sabinar, Fuente del",
    "tgn:placetype":[
        "aat:300008697"
    ]
},
  "bbox": [],
  "geometry": {"coordinates":[-1.116667,40.116667],"type":"Point"}
}