<<<<<<< HEAD
{
  "id": 7354361,
  "type": "Feature",
  "properties": {
    "tgn:hierarchy":[
        "tgn:7354361",
        "tgn:1000001",
        "tgn:7005600",
        "tgn:7005560",
        "tgn:7029392"
    ],
    "tgn:id":7354361,
    "tgn:name":"Chuhuas",
    "tgn:placetype":[
        "aat:300008347"
    ]
},
  "bbox": [],
  "geometry": {"coordinates":[-89.0,21.1],"type":"Point"}
}
=======
{"geometry":{"type":"Point","coordinates":[-89.000000,21.100000]},"type":"Feature","properties":{"hierarchy":["tgn:7354361","tgn:1000001","tgn:7005600","tgn:7005560","tgn:7029392"],"placetype":["aat:300008347"],"id":7354361,"name:xx":"Chuhuas"}}
>>>>>>> 03f74aca74312dbeaf24d7e61306dd6a786dc3d0
