{
  "id": 7059168,
  "type": "Feature",
  "properties": {
    "tgn:hierarchy":[
        "tgn:7059168",
        "tgn:1000984",
        "tgn:7000897",
        "tgn:1000004",
        "tgn:1007520",
        "tgn:1000120",
        "tgn:7029392"
    ],
    "tgn:id":7059168,
    "tgn:name":"Itsukushima Jinja",
    "tgn:placetype":[
        "aat:300007558",
        "aat:300263063"
    ]
},
  "bbox": [],
  "geometry": {"coordinates":[132.321,34.294],"type":"Point"}
}