<<<<<<< HEAD
{
  "id": 7059168,
  "type": "Feature",
  "properties": {
    "tgn:hierarchy":[
        "tgn:7059168",
        "tgn:1000984",
        "tgn:7000897",
        "tgn:1000004",
        "tgn:1007520",
        "tgn:1000120",
        "tgn:7029392"
    ],
    "tgn:id":7059168,
    "tgn:name":"Itsukushima Jinja",
    "tgn:placetype":[
        "aat:300007558",
        "aat:300263063"
    ]
},
  "bbox": [],
  "geometry": {"coordinates":[132.321,34.294],"type":"Point"}
}
=======
{"geometry":{"type":"Point","coordinates":[132.321000,34.294000]},"type":"Feature","properties":{"hierarchy":["tgn:7059168","tgn:1000984","tgn:7000897","tgn:1000004","tgn:1007520","tgn:1000120","tgn:7029392"],"placetype":["aat:300007558","aat:300263063"],"id":7059168,"name:xx":"Itsukushima Jinja"}}
>>>>>>> 03f74aca74312dbeaf24d7e61306dd6a786dc3d0
