{
  "id": 2705063,
  "type": "Feature",
  "properties": {
    "tgn:hierarchy":[
        "tgn:2705063",
        "tgn:1000001",
        "tgn:7012149",
        "tgn:1002732",
        "tgn:7007710",
        "tgn:7029392"
    ],
    "tgn:id":2705063,
    "tgn:name":"Sunshine Fines Pond",
    "tgn:placetype":[
        "aat:300006191"
    ]
},
  "bbox": [],
  "geometry": {"coordinates":[-76.7333,40.7667],"type":"Point"}
}