<<<<<<< HEAD
{
  "id": 7117901,
  "type": "Feature",
  "properties": {
    "tgn:hierarchy":[
        "tgn:7117901",
        "tgn:1000003",
        "tgn:7003676",
        "tgn:7000084",
        "tgn:7029392"
    ],
    "tgn:id":7117901,
    "tgn:name":"Obershagen",
    "tgn:placetype":[
        "aat:300008347"
    ]
},
  "bbox": [],
  "geometry": {"coordinates":[10.05,52.5],"type":"Point"}
}
=======
{"geometry":{"type":"Point","coordinates":[10.050000,52.500000]},"type":"Feature","properties":{"hierarchy":["tgn:7117901","tgn:1000003","tgn:7003676","tgn:7000084","tgn:7029392"],"placetype":["aat:300008347"],"id":7117901,"name:xx":"Obershagen"}}
>>>>>>> 03f74aca74312dbeaf24d7e61306dd6a786dc3d0
