{
  "id": 2390524,
  "type": "Feature",
  "properties": {
    "tgn:hierarchy":[
        "tgn:2390524",
        "tgn:1000001",
        "tgn:7012149",
        "tgn:1002928",
        "tgn:7007706",
        "tgn:7029392"
    ],
    "tgn:id":2390524,
    "tgn:name":"Highland Springs",
    "tgn:placetype":[
        "aat:300008347"
    ]
},
  "bbox": [],
  "geometry": {"coordinates":[-81.4667,41.25],"type":"Point"}
}