{
  "id": 7586938,
  "type": "Feature",
  "properties": {
    "tgn:hierarchy":[
        "tgn:7586938",
        "tgn:1000004",
        "tgn:7000198",
        "tgn:7000799",
        "tgn:7029392"
    ],
    "tgn:id":7586938,
    "tgn:name:en":"Dusilparichrakh",
    "tgn:placetype":[
        "aat:300008347"
    ]
},
  "bbox": [],
  "geometry": {"coordinates":[74.613889,34.169444],"type":"Point"}
}