{
  "id": 7534578,
  "type": "Feature",
  "properties": {
    "tgn:hierarchy":[
        "tgn:7534578",
        "tgn:7001242",
        "tgn:7016833",
        "tgn:1001418",
        "tgn:7029392"
    ],
    "tgn:id":7534578,
    "tgn:name:en":"Kakar, 'Alam el-",
    "tgn:placetype":[
        "aat:300008777"
    ]
},
  "bbox": [],
  "geometry": {"coordinates":[25.322848,30.93663],"type":"Point"}
}