{
  "id": 7279714,
  "type": "Feature",
  "properties": {
    "tgn:hierarchy":[
        "tgn:7279714",
        "tgn:1001708",
        "tgn:1000049",
        "tgn:1000002",
        "tgn:7029392"
    ],
    "tgn:id":7279714,
    "tgn:name":"Ranchillo",
    "tgn:placetype":[
        "aat:300008777"
    ]
},
  "bbox": [],
  "geometry": {"coordinates":[-71.566667,-33.816667],"type":"Point"}
}