{
  "id": 7400009,
  "type": "Feature",
  "properties": {
    "tgn:hierarchy":[
        "tgn:7400009",
        "tgn:1000001",
        "tgn:7005593",
        "tgn:7005560",
        "tgn:7029392"
    ],
    "tgn:id":7400009,
    "tgn:name":"El Venado",
    "tgn:placetype":[
        "aat:300008347"
    ]
},
  "bbox": [],
  "geometry": {"coordinates":[-99.622222,21.288889],"type":"Point"}
}