{
  "id": 2420281,
  "type": "Feature",
  "properties": {
    "tgn:hierarchy":[
        "tgn:2420281",
        "tgn:1000001",
        "tgn:2001264",
        "tgn:7012149",
        "tgn:7007524",
        "tgn:7029392"
    ],
    "tgn:id":2420281,
    "tgn:name":"Jeffrey Ditch",
    "tgn:placetype":[
        "aat:300006075"
    ]
},
  "bbox": [],
  "geometry": {"coordinates":[-109.1833,45.25],"type":"Point"}
}