{
  "id": 7192992,
  "type": "Feature",
  "properties": {
    "tgn:hierarchy":[
        "tgn:7192992",
        "tgn:1000003",
        "tgn:7003677",
        "tgn:7000084",
        "tgn:7029392"
    ],
    "tgn:id":7192992,
    "tgn:name":"Felsenkeller",
    "tgn:placetype":[
        "aat:300000206"
    ]
},
  "bbox": [],
  "geometry": {"coordinates":[8.983333,52.166667],"type":"Point"}
}