<<<<<<< HEAD
{
  "id": 2336916,
  "type": "Feature",
  "properties": {
    "tgn:hierarchy":[
        "tgn:2336916",
        "tgn:1000001",
        "tgn:2001599",
        "tgn:7012149",
        "tgn:7007705",
        "tgn:7029392"
    ],
    "tgn:id":2336916,
    "tgn:name":"Fourmile Creek",
    "tgn:placetype":[
        "aat:300008706"
    ]
},
  "bbox": [],
  "geometry": {"coordinates":[-100.8167,46.1],"type":"Point"}
}
=======
{"geometry":{"type":"Point","coordinates":[-100.816700,46.100000]},"type":"Feature","properties":{"hierarchy":["tgn:2336916","tgn:1000001","tgn:2001599","tgn:7012149","tgn:7007705","tgn:7029392"],"placetype":["aat:300008706"],"id":2336916,"name:xx":"Fourmile Creek"}}
>>>>>>> 03f74aca74312dbeaf24d7e61306dd6a786dc3d0
