{
  "id": 7399771,
  "type": "Feature",
  "properties": {
    "tgn:hierarchy":[
        "tgn:7399771",
        "tgn:1000001",
        "tgn:7005593",
        "tgn:7005560",
        "tgn:7029392"
    ],
    "tgn:id":7399771,
    "tgn:name":"El Suspiro",
    "tgn:placetype":[
        "aat:300008347"
    ]
},
  "bbox": [],
  "geometry": {"coordinates":[-99.566667,20.866667],"type":"Point"}
}