{
  "id": 1135369,
  "type": "Feature",
  "properties": {
    "tgn:hierarchy":[
        "tgn:1135369",
        "tgn:1000003",
        "tgn:7002883",
        "tgn:1000070",
        "tgn:7029392"
    ],
    "tgn:id":1135369,
    "tgn:name":"Rosne, Ruisseau le",
    "tgn:placetype":[
        "aat:300008703"
    ]
},
  "bbox": [],
  "geometry": {"coordinates":[2.4167,48.9667],"type":"Point"}
}