{
  "id": 7578893,
  "type": "Feature",
  "properties": {
    "tgn:hierarchy":[
        "tgn:7578893",
        "tgn:1000004",
        "tgn:7000198",
        "tgn:1001895",
        "tgn:7029392"
    ],
    "tgn:id":7578893,
    "tgn:name:en":"W\u0101hegaon",
    "tgn:placetype":[
        "aat:300008347"
    ]
},
  "bbox": [],
  "geometry": {"coordinates":[75.683333,19.766667],"type":"Point"}
}