{
  "id": 7353226,
  "type": "Feature",
  "properties": {
    "tgn:hierarchy":[
        "tgn:7353226",
        "tgn:1000001",
        "tgn:7005595",
        "tgn:7005560",
        "tgn:7029392"
    ],
    "tgn:id":7353226,
    "tgn:name":"Bebelamas",
    "tgn:placetype":[
        "aat:300008347"
    ]
},
  "bbox": [],
  "geometry": {"coordinates":[-107.170556,24.620833],"type":"Point"}
}