<<<<<<< HEAD
{
  "id": 7369932,
  "type": "Feature",
  "properties": {
    "tgn:hierarchy":[
        "tgn:7369932",
        "tgn:1000001",
        "tgn:7005592",
        "tgn:7005560",
        "tgn:7029392"
    ],
    "tgn:id":7369932,
    "tgn:name":"Jalapasco",
    "tgn:placetype":[
        "aat:300008347"
    ]
},
  "bbox": [],
  "geometry": {"coordinates":[-97.516667,19.433333],"type":"Point"}
}
=======
{"geometry":{"type":"Point","coordinates":[-97.516667,19.433333]},"type":"Feature","properties":{"hierarchy":["tgn:7369932","tgn:1000001","tgn:7005592","tgn:7005560","tgn:7029392"],"placetype":["aat:300008347"],"id":7369932,"name:xx":"Jalapasco"}}
>>>>>>> 03f74aca74312dbeaf24d7e61306dd6a786dc3d0
