{
  "id": 7591389,
  "type": "Feature",
  "properties": {
    "tgn:hierarchy":[
        "tgn:7591389",
        "tgn:1000004",
        "tgn:7000198",
        "tgn:7000799",
        "tgn:7029392"
    ],
    "tgn:id":7591389,
    "tgn:name:en":"Baintrewali Dhakki",
    "tgn:placetype":[
        "aat:300008699"
    ]
},
  "bbox": [],
  "geometry": {"coordinates":[74.5125,32.913889],"type":"Point"}
}