{
  "id": 2504830,
  "type": "Feature",
  "properties": {
    "tgn:hierarchy":[
        "tgn:2504830",
        "tgn:1000001",
        "tgn:7012149",
        "tgn:2001453",
        "tgn:7007566",
        "tgn:7029392"
    ],
    "tgn:id":2504830,
    "tgn:name":"Medina Mesa",
    "tgn:placetype":[
        "aat:300008798"
    ]
},
  "bbox": [],
  "geometry": {"coordinates":[-103.8167,35.3833],"type":"Point"}
}