{
  "id": 7591187,
  "type": "Feature",
  "properties": {
    "tgn:hierarchy":[
        "tgn:7591187",
        "tgn:1000004",
        "tgn:7000198",
        "tgn:7000799",
        "tgn:7029392"
    ],
    "tgn:id":7591187,
    "tgn:name:en":"Salehr",
    "tgn:placetype":[
        "aat:300008347"
    ]
},
  "bbox": [],
  "geometry": {"coordinates":[74.820396,32.560867],"type":"Point"}
}