{
  "id": 7236275,
  "type": "Feature",
  "properties": {
    "tgn:hierarchy":[
        "tgn:7236275",
        "tgn:7002725",
        "tgn:7002715",
        "tgn:1000003",
        "tgn:1000074",
        "tgn:7029392"
    ],
    "tgn:id":7236275,
    "tgn:name":"\u00c1no Potami\u00e1",
    "tgn:placetype":[
        "aat:300008347"
    ]
},
  "bbox": [],
  "geometry": {"coordinates":[22.923333,40.967222],"type":"Point"}
}