{
  "id": 1034501,
  "type": "Feature",
  "properties": {
    "tgn:hierarchy":[
        "tgn:1034501",
        "tgn:1000003",
        "tgn:7002883",
        "tgn:1000070",
        "tgn:7029392"
    ],
    "tgn:id":1034501,
    "tgn:name":"Montlignon",
    "tgn:placetype":[
        "aat:300008347"
    ]
},
  "bbox": [],
  "geometry": {"coordinates":[2.2833,49.0167],"type":"Point"}
}