<<<<<<< HEAD
{
  "id": 2762814,
  "type": "Feature",
  "properties": {
    "tgn:hierarchy":[
        "tgn:2762814",
        "tgn:1000001",
        "tgn:2001786",
        "tgn:7012149",
        "tgn:7007713",
        "tgn:7029392"
    ],
    "tgn:id":2762814,
    "tgn:name":"Western Star Mine",
    "tgn:placetype":[
        "aat:300000390"
    ]
},
  "bbox": [],
  "geometry": {"coordinates":[-103.7333,43.7833],"type":"Point"}
}
=======
{"geometry":{"type":"Point","coordinates":[-103.733300,43.783300]},"type":"Feature","properties":{"hierarchy":["tgn:2762814","tgn:1000001","tgn:2001786","tgn:7012149","tgn:7007713","tgn:7029392"],"placetype":["aat:300000390"],"id":2762814,"name:xx":"Western Star Mine"}}
>>>>>>> 03f74aca74312dbeaf24d7e61306dd6a786dc3d0
