<<<<<<< HEAD
{
  "id": 7478974,
  "type": "Feature",
  "properties": {
    "tgn:hierarchy":[
        "tgn:7478974",
        "tgn:1000004",
        "tgn:7001009",
        "tgn:1000141",
        "tgn:7029392"
    ],
    "tgn:id":7478974,
    "tgn:name":"Minzhuang",
    "tgn:placetype":[
        "aat:300008347"
    ]
},
  "bbox": [],
  "geometry": {"coordinates":[121.307222,24.394722],"type":"Point"}
}
=======
{"geometry":{"type":"Point","coordinates":[121.307222,24.394722]},"type":"Feature","properties":{"hierarchy":["tgn:7478974","tgn:1000004","tgn:7001009","tgn:1000141","tgn:7029392"],"placetype":["aat:300008347"],"id":7478974,"name:xx":"Minzhuang"}}
>>>>>>> 03f74aca74312dbeaf24d7e61306dd6a786dc3d0
