<<<<<<< HEAD
{
  "id": 2154862,
  "type": "Feature",
  "properties": {
    "tgn:hierarchy":[
        "tgn:2154862",
        "tgn:1000001",
        "tgn:7012149",
        "tgn:7007255",
        "tgn:7029392"
    ],
    "tgn:id":2154862,
    "tgn:name":"Bear Hollow",
    "tgn:placetype":[
        "aat:300008761"
    ]
},
  "bbox": [],
  "geometry": {"coordinates":[-82.8333,37.7167],"type":"Point"}
}
=======
{"geometry":{"type":"Point","coordinates":[-82.833300,37.716700]},"type":"Feature","properties":{"hierarchy":["tgn:2154862","tgn:1000001","tgn:7012149","tgn:7007255","tgn:7029392"],"placetype":["aat:300008761"],"id":2154862,"name:xx":"Bear Hollow"}}
>>>>>>> 03f74aca74312dbeaf24d7e61306dd6a786dc3d0
