{
  "id": 2537093,
  "type": "Feature",
  "properties": {
    "tgn:hierarchy":[
        "tgn:2537093",
        "tgn:1000001",
        "tgn:7012149",
        "tgn:1003038",
        "tgn:7007517",
        "tgn:7029392"
    ],
    "tgn:id":2537093,
    "tgn:name":"Neeseponsett Pond",
    "tgn:placetype":[
        "aat:300008680"
    ]
},
  "bbox": [],
  "geometry": {"coordinates":[-72.2833,42.4667],"type":"Point"}
}