{
  "id": 7019349,
  "type": "Feature",
  "properties": {
    "tgn:hierarchy":[
        "tgn:7019349",
        "tgn:1000001",
        "tgn:7012149",
        "tgn:2000359",
        "tgn:7007248",
        "tgn:7029392"
    ],
    "tgn:id":7019349,
    "tgn:name":"Reservoir 21",
    "tgn:placetype":[
        "aat:300006191"
    ]
},
  "bbox": [],
  "geometry": {"coordinates":[-83.4667,34.55],"type":"Point"}
}