{
  "id": 7247381,
  "type": "Feature",
  "properties": {
    "tgn:hierarchy":[
        "tgn:7247381",
        "tgn:7007877",
        "tgn:1000003",
        "tgn:1000063",
        "tgn:4012014",
        "tgn:7029392"
    ],
    "tgn:id":7247381,
    "tgn:name":"Chapelle-\u00e0-Oie",
    "tgn:placetype":[
        "aat:300008347"
    ]
},
  "bbox": [],
  "geometry": {"coordinates":[3.670421,50.596693],"type":"Point"}
}