{
  "id": 2594939,
  "type": "Feature",
  "properties": {
    "tgn:hierarchy":[
        "tgn:2594939",
        "tgn:1000001",
        "tgn:7012149",
        "tgn:7007157",
        "tgn:1002863",
        "tgn:7029392"
    ],
    "tgn:id":2594939,
    "tgn:name":"Post Canyon",
    "tgn:placetype":[
        "aat:300008761"
    ]
},
  "bbox": [],
  "geometry": {"coordinates":[-119.7833,35.0667],"type":"Point"}
}