<<<<<<< HEAD
{
  "id": 7244622,
  "type": "Feature",
  "properties": {
    "tgn:hierarchy":[
        "tgn:7244622",
        "tgn:7003466",
        "tgn:1000003",
        "tgn:1000063",
        "tgn:4012014",
        "tgn:7029392"
    ],
    "tgn:id":7244622,
    "tgn:name":"Annevoie, Ruisseau d'",
    "tgn:placetype":[
        "aat:300008699"
    ]
},
  "bbox": [],
  "geometry": {"coordinates":[4.851726,50.346884],"type":"Point"}
}
=======
{"geometry":{"type":"Point","coordinates":[4.851726,50.346884]},"type":"Feature","properties":{"hierarchy":["tgn:7244622","tgn:7003466","tgn:1000003","tgn:1000063","tgn:4012014","tgn:7029392"],"placetype":["aat:300008699"],"id":7244622,"name:xx":"Annevoie, Ruisseau d'"}}
>>>>>>> 03f74aca74312dbeaf24d7e61306dd6a786dc3d0
