{
  "id": 2434033,
  "type": "Feature",
  "properties": {
    "tgn:hierarchy":[
        "tgn:2434033",
        "tgn:7006450",
        "tgn:1000001",
        "tgn:7012149",
        "tgn:2000082",
        "tgn:7029392"
    ],
    "tgn:id":2434033,
    "tgn:name":"Kelp Island Anchorage",
    "tgn:placetype":[
        "aat:300132316"
    ]
},
  "bbox": [],
  "geometry": {"coordinates":[-131.25,54.8667],"type":"Point"}
}