{
  "id": 1099909,
  "type": "Feature",
  "properties": {
    "tgn:hierarchy":[
        "tgn:1099909",
        "tgn:1000004",
        "tgn:1003384",
        "tgn:7014786",
        "tgn:7029392"
    ],
    "tgn:id":1099909,
    "tgn:name":"Sirykrabet",
    "tgn:placetype":[
        "aat:300008347",
        "aat:300167671"
    ]
},
  "bbox": [],
  "geometry": {"coordinates":[62.5833,44.1167],"type":"Point"}
}