{
  "id": 7503617,
  "type": "Feature",
  "properties": {
    "tgn:hierarchy":[
        "tgn:7503617",
        "tgn:1000004",
        "tgn:7471332",
        "tgn:1000141",
        "tgn:7029392"
    ],
    "tgn:id":7503617,
    "tgn:name":"Dawolang Shan",
    "tgn:placetype":[
        "aat:300008798"
    ]
},
  "bbox": [],
  "geometry": {"coordinates":[121.0875,24.66],"type":"Point"}
}