{
  "id": 2777499,
  "type": "Feature",
  "properties": {
    "tgn:hierarchy":[
        "tgn:2777499",
        "tgn:1000001",
        "tgn:7012149",
        "tgn:2001026",
        "tgn:7007521",
        "tgn:7029392"
    ],
    "tgn:id":2777499,
    "tgn:name":"Winnebago Creek",
    "tgn:placetype":[
        "aat:300008706"
    ]
},
  "bbox": [],
  "geometry": {"coordinates":[-91.5667,43.5833],"type":"Point"}
}