{
  "id": 2109701,
  "type": "Feature",
  "properties": {
    "tgn:hierarchy":[
        "tgn:2109701",
        "tgn:1000001",
        "tgn:2002136",
        "tgn:7012149",
        "tgn:7007828",
        "tgn:7029392"
    ],
    "tgn:id":2109701,
    "tgn:name":"Hartland",
    "tgn:placetype":[
        "aat:300008347"
    ]
},
  "bbox": [],
  "geometry": {"coordinates":[-72.3833,43.5333],"type":"Point"}
}