{
  "id": 7583156,
  "type": "Feature",
  "properties": {
    "tgn:hierarchy":[
        "tgn:7583156",
        "tgn:1000004",
        "tgn:1001871",
        "tgn:7000198",
        "tgn:7029392"
    ],
    "tgn:id":7583156,
    "tgn:name:en":"Bagrat",
    "tgn:placetype":[
        "aat:300008347"
    ]
},
  "bbox": [],
  "geometry": {"coordinates":[76.968752,30.042458],"type":"Point"}
}