{
  "id": 2294620,
  "type": "Feature",
  "properties": {
    "tgn:hierarchy":[
        "tgn:2294620",
        "tgn:2000002",
        "tgn:7002659",
        "tgn:1000001",
        "tgn:7012149",
        "tgn:7029392"
    ],
    "tgn:id":2294620,
    "tgn:name":"Doziers Pond",
    "tgn:placetype":[
        "aat:300006191"
    ]
},
  "bbox": [],
  "geometry": {"coordinates":[-85.15,31.9333],"type":"Point"}
}