{
  "id": 7138662,
  "type": "Feature",
  "properties": {
    "tgn:hierarchy":[
        "tgn:7138662",
        "tgn:7003669",
        "tgn:1000003",
        "tgn:7000084",
        "tgn:7029392"
    ],
    "tgn:id":7138662,
    "tgn:name":"Leitzgrundbach",
    "tgn:placetype":[
        "aat:300008699"
    ]
},
  "bbox": [],
  "geometry": {"coordinates":[10.583333,49.783333],"type":"Point"}
}