{
  "id": 7309534,
  "type": "Feature",
  "properties": {
    "tgn:hierarchy":[
        "tgn:7309534",
        "tgn:1001692",
        "tgn:1000049",
        "tgn:1000002",
        "tgn:7029392"
    ],
    "tgn:id":7309534,
    "tgn:name":"Naranjo, R\u00edo",
    "tgn:placetype":[
        "aat:300008699"
    ]
},
  "bbox": [],
  "geometry": {"coordinates":[-71.366667,-38.433333],"type":"Point"}
}