{
  "id": 7425263,
  "type": "Feature",
  "properties": {
    "tgn:hierarchy":[
        "tgn:7425263",
        "tgn:7005581",
        "tgn:1000001",
        "tgn:7005560",
        "tgn:7029392"
    ],
    "tgn:id":7425263,
    "tgn:name":"Santa In\u00e9s",
    "tgn:placetype":[
        "aat:300008347"
    ]
},
  "bbox": [],
  "geometry": {"coordinates":[-107.866667,26.666667],"type":"Point"}
}