{
  "id": 2101907,
  "type": "Feature",
  "properties": {
    "tgn:hierarchy":[
        "tgn:2101907",
        "tgn:1000001",
        "tgn:7012149",
        "tgn:2001901",
        "tgn:7007825",
        "tgn:7029392"
    ],
    "tgn:id":2101907,
    "tgn:name":"Union",
    "tgn:placetype":[
        "aat:300008347",
        "aat:300387210"
    ]
},
  "bbox": [],
  "geometry": {"coordinates":[-84.4833,36.0667],"type":"Point"}
}