{
  "id": 2305765,
  "type": "Feature",
  "properties": {
    "tgn:hierarchy":[
        "tgn:2305765",
        "tgn:1000001",
        "tgn:7012149",
        "tgn:2001667",
        "tgn:7007707",
        "tgn:7029392"
    ],
    "tgn:id":2305765,
    "tgn:name":"East Creek",
    "tgn:placetype":[
        "aat:300008706"
    ]
},
  "bbox": [],
  "geometry": {"coordinates":[-94.85,34.4833],"type":"Point"}
}