{
  "id": 1041127,
  "type": "Feature",
  "properties": {
    "tgn:hierarchy":[
        "tgn:1041127",
        "tgn:7003669",
        "tgn:1000003",
        "tgn:7000084",
        "tgn:7029392"
    ],
    "tgn:id":1041127,
    "tgn:name":"Schnaittach",
    "tgn:placetype":[
        "aat:300008347"
    ]
},
  "bbox": [],
  "geometry": {"coordinates":[11.343056,49.559167],"type":"Point"}
}