{
  "id": 1091067,
  "type": "Feature",
  "properties": {
    "tgn:hierarchy":[
        "tgn:1091067",
        "tgn:1001186",
        "tgn:7001242",
        "tgn:7000726",
        "tgn:7029392"
    ],
    "tgn:id":1091067,
    "tgn:name":"Lilongwe",
    "tgn:placetype":[
        "aat:300008347",
        "aat:300008389",
        "aat:300387219",
        "aat:300387220"
    ]
},
  "bbox": [],
  "geometry": {"coordinates":[33.8167,-13.9667],"type":"Point"}
}