{
  "id": 7335583,
  "type": "Feature",
  "properties": {
    "tgn:hierarchy":[
        "tgn:7335583",
        "tgn:7002804",
        "tgn:1000003",
        "tgn:7002793",
        "tgn:1000095",
        "tgn:7029392"
    ],
    "tgn:id":7335583,
    "tgn:name":"Torre de la Galera",
    "tgn:placetype":[
        "aat:300004847"
    ]
},
  "bbox": [],
  "geometry": {"coordinates":[-0.016667,38.633333],"type":"Point"}
}