{
  "id": 2115880,
  "type": "Feature",
  "properties": {
    "tgn:hierarchy":[
        "tgn:2115880",
        "tgn:1000001",
        "tgn:7012149",
        "tgn:1003042",
        "tgn:7007920",
        "tgn:7029392"
    ],
    "tgn:id":2115880,
    "tgn:name":"Granger",
    "tgn:placetype":[
        "aat:300008347"
    ]
},
  "bbox": [],
  "geometry": {"coordinates":[-120.1833,46.3333],"type":"Point"}
}