{
  "id": 7218414,
  "type": "Feature",
  "properties": {
    "tgn:hierarchy":[
        "tgn:7218414",
        "tgn:7011270",
        "tgn:7002674",
        "tgn:1000003",
        "tgn:1000074",
        "tgn:7029392"
    ],
    "tgn:id":7218414,
    "tgn:name":"To\u00farlos, \u00c1kra",
    "tgn:placetype":[
        "aat:300008850"
    ]
},
  "bbox": [],
  "geometry": {"coordinates":[25.316667,37.466667],"type":"Point"}
}