{
  "id": 2374910,
  "type": "Feature",
  "properties": {
    "tgn:hierarchy":[
        "tgn:2374910",
        "tgn:1000001",
        "tgn:7012149",
        "tgn:1003020",
        "tgn:7007920",
        "tgn:7029392"
    ],
    "tgn:id":2374910,
    "tgn:name":"Hanging Lake",
    "tgn:placetype":[
        "aat:300008680"
    ]
},
  "bbox": [],
  "geometry": {"coordinates":[-121.45,48.9833],"type":"Point"}
}