{
  "id": 7578293,
  "type": "Feature",
  "properties": {
    "tgn:hierarchy":[
        "tgn:7578293",
        "tgn:1000004",
        "tgn:7000198",
        "tgn:1001895",
        "tgn:7029392"
    ],
    "tgn:id":7578293,
    "tgn:name:en":"Talni",
    "tgn:placetype":[
        "aat:300008347"
    ]
},
  "bbox": [],
  "geometry": {"coordinates":[76.483333,19.883333],"type":"Point"}
}