{
  "id": 2133673,
  "type": "Feature",
  "properties": {
    "tgn:hierarchy":[
        "tgn:2133673",
        "tgn:1000001",
        "tgn:7012149",
        "tgn:2001441",
        "tgn:7007566",
        "tgn:7029392"
    ],
    "tgn:id":2133673,
    "tgn:name":"Andrews West Tank",
    "tgn:placetype":[
        "aat:300006191"
    ]
},
  "bbox": [],
  "geometry": {"coordinates":[-103.4333,32.0167],"type":"Point"}
}