{
  "id": 7259249,
  "type": "Feature",
  "properties": {
    "tgn:hierarchy":[
        "tgn:7259249",
        "tgn:7003456",
        "tgn:1000003",
        "tgn:1000063",
        "tgn:7018236",
        "tgn:7029392"
    ],
    "tgn:id":7259249,
    "tgn:name":"Voorste Nete",
    "tgn:placetype":[
        "aat:300008699"
    ]
},
  "bbox": [],
  "geometry": {"coordinates":[5.116667,51.233333],"type":"Point"}
}