{
  "id": 2287305,
  "type": "Feature",
  "properties": {
    "tgn:hierarchy":[
        "tgn:2287305",
        "tgn:1000001",
        "tgn:7012149",
        "tgn:2001520",
        "tgn:7007709",
        "tgn:7029392"
    ],
    "tgn:id":2287305,
    "tgn:name":"Dicks Creek",
    "tgn:placetype":[
        "aat:300008706"
    ]
},
  "bbox": [],
  "geometry": {"coordinates":[-79.7833,35.3833],"type":"Point"}
}