{
  "id": 2677171,
  "type": "Feature",
  "properties": {
    "tgn:hierarchy":[
        "tgn:2677171",
        "tgn:1000001",
        "tgn:2000920",
        "tgn:7012149",
        "tgn:7007515",
        "tgn:7029392"
    ],
    "tgn:id":2677171,
    "tgn:name":"South Branch Stroudwater River",
    "tgn:placetype":[
        "aat:300008707"
    ]
},
  "bbox": [],
  "geometry": {"coordinates":[-70.45,43.6167],"type":"Point"}
}