{
  "id": 1016422,
  "type": "Feature",
  "properties": {
    "tgn:hierarchy":[
        "tgn:1016422",
        "tgn:1001296",
        "tgn:1000001",
        "tgn:7004624",
        "tgn:7029392"
    ],
    "tgn:id":1016422,
    "tgn:name":"Sagua de T\u00e1namo",
    "tgn:placetype":[
        "aat:300008347"
    ]
},
  "bbox": [],
  "geometry": {"coordinates":[-75.2333,20.6333],"type":"Point"}
}