{
  "id": 2346958,
  "type": "Feature",
  "properties": {
    "tgn:hierarchy":[
        "tgn:2346958",
        "tgn:1000001",
        "tgn:2001419",
        "tgn:7012149",
        "tgn:7007526",
        "tgn:7029392"
    ],
    "tgn:id":2346958,
    "tgn:name":"Gem Mine",
    "tgn:placetype":[
        "aat:300000390"
    ]
},
  "bbox": [],
  "geometry": {"coordinates":[-117.8333,40.7167],"type":"Point"}
}