{
  "id": 2067938,
  "type": "Feature",
  "properties": {
    "tgn:hierarchy":[
        "tgn:2067938",
        "tgn:1000001",
        "tgn:7012149",
        "tgn:1002873",
        "tgn:7007568",
        "tgn:7029392"
    ],
    "tgn:id":2067938,
    "tgn:name":"Barnerville",
    "tgn:placetype":[
        "aat:300008347"
    ]
},
  "bbox": [],
  "geometry": {"coordinates":[-74.4167,42.6833],"type":"Point"}
}