{
  "id": 1105067,
  "type": "Feature",
  "properties": {
    "tgn:hierarchy":[
        "tgn:1105067",
        "tgn:1000001",
        "tgn:7012149",
        "tgn:1003020",
        "tgn:7007920",
        "tgn:7029392"
    ],
    "tgn:id":1105067,
    "tgn:name":"Jack Mountain",
    "tgn:placetype":[
        "aat:300008795"
    ]
},
  "bbox": [],
  "geometry": {"coordinates":[-120.95,48.7667],"type":"Point"}
}