<<<<<<< HEAD
{
  "id": 7052158,
  "type": "Feature",
  "properties": {
    "tgn:hierarchy":[
        "tgn:7052158",
        "tgn:7005880",
        "tgn:1000003",
        "tgn:7003237",
        "tgn:1000080",
        "tgn:7029392"
    ],
    "tgn:id":7052158,
    "tgn:name":"La Boccalona",
    "tgn:placetype":[
        "aat:300008347"
    ]
},
  "bbox": [],
  "geometry": {"coordinates":[10.6,44.95],"type":"Point"}
}
=======
{"geometry":{"type":"Point","coordinates":[10.600000,44.950000]},"type":"Feature","properties":{"hierarchy":["tgn:7052158","tgn:7005880","tgn:1000003","tgn:7003237","tgn:1000080","tgn:7029392"],"placetype":["aat:300008347"],"id":7052158,"name:xx":"La Boccalona"}}
>>>>>>> 03f74aca74312dbeaf24d7e61306dd6a786dc3d0
