{
  "id": 7590736,
  "type": "Feature",
  "properties": {
    "tgn:hierarchy":[
        "tgn:7590736",
        "tgn:1000004",
        "tgn:7000198",
        "tgn:7000799",
        "tgn:7029392"
    ],
    "tgn:id":7590736,
    "tgn:name:en":"Lassi Banna",
    "tgn:placetype":[
        "aat:300008347"
    ]
},
  "bbox": [],
  "geometry": {"coordinates":[73.967639,34.406486],"type":"Point"}
}