{
  "id": 1067701,
  "type": "Feature",
  "properties": {
    "tgn:hierarchy":[
        "tgn:1067701",
        "tgn:7002075",
        "tgn:1000004",
        "tgn:1000111",
        "tgn:7029392"
    ],
    "tgn:id":1067701,
    "tgn:name":"Dicun",
    "tgn:placetype":[
        "aat:300008347"
    ]
},
  "bbox": [],
  "geometry": {"coordinates":[117.5333,33.7667],"type":"Point"}
}