{
  "id": 7447373,
  "type": "Feature",
  "properties": {
    "tgn:hierarchy":[
        "tgn:7447373",
        "tgn:7002445",
        "tgn:1000003",
        "tgn:7008134",
        "tgn:7008591",
        "tgn:7029392"
    ],
    "tgn:id":7447373,
    "tgn:name:en":"Saint Leonards Forest",
    "tgn:placetype":[
        "aat:300008863"
    ]
},
  "bbox": [],
  "geometry": {"coordinates":[-0.25,51.066667],"type":"Point"}
}