{
  "id": 7245508,
  "type": "Feature",
  "properties": {
    "tgn:hierarchy":[
        "tgn:7245508",
        "tgn:7003460",
        "tgn:1000003",
        "tgn:1000063",
        "tgn:4012014",
        "tgn:7029392"
    ],
    "tgn:id":7245508,
    "tgn:name":"Andenelle",
    "tgn:placetype":[
        "aat:300008347"
    ]
},
  "bbox": [],
  "geometry": {"coordinates":[5.112301,50.494811],"type":"Point"}
}