{
  "id": 2585586,
  "type": "Feature",
  "properties": {
    "tgn:hierarchy":[
        "tgn:2585586",
        "tgn:1000001",
        "tgn:2000470",
        "tgn:7012149",
        "tgn:7007250",
        "tgn:7029392"
    ],
    "tgn:id":2585586,
    "tgn:name":"Pioneer Creek",
    "tgn:placetype":[
        "aat:300008706"
    ]
},
  "bbox": [],
  "geometry": {"coordinates":[-114.85,44.45],"type":"Point"}
}