{
  "id": 1114840,
  "type": "Feature",
  "properties": {
    "tgn:hierarchy":[
        "tgn:1114840",
        "tgn:7001242",
        "tgn:1000168",
        "tgn:7029392"
    ],
    "tgn:id":1114840,
    "tgn:name":"Tadio, Lagune",
    "tgn:placetype":[
        "aat:300008679"
    ]
},
  "bbox": [],
  "geometry": {"coordinates":[-5.25,5.1833],"type":"Point"}
}