{
  "id": 1110582,
  "type": "Feature",
  "properties": {
    "tgn:hierarchy":[
        "tgn:1110582",
        "tgn:1000001",
        "tgn:7012149",
        "tgn:7007157",
        "tgn:1002608",
        "tgn:7029392"
    ],
    "tgn:id":1110582,
    "tgn:name":"San Jose Hills",
    "tgn:placetype":[
        "aat:300008777"
    ]
},
  "bbox": [],
  "geometry": {"coordinates":[-117.8333,34.05],"type":"Point"}
}