{
  "id": 7267316,
  "type": "Feature",
  "properties": {
    "tgn:hierarchy":[
        "tgn:7267316",
        "tgn:7003614",
        "tgn:1000003",
        "tgn:7016845",
        "tgn:7029392"
    ],
    "tgn:id":7267316,
    "tgn:name:nl":"Nieuwe Schuttingkanaal",
    "tgn:placetype":[
        "aat:300006075"
    ]
},
  "bbox": [],
  "geometry": {"coordinates":[7.016667,52.816667],"type":"Point"}
}