{
  "id": 1012334,
  "type": "Feature",
  "properties": {
    "tgn:hierarchy":[
        "tgn:1012334",
        "tgn:1001668",
        "tgn:7001242",
        "tgn:1000164",
        "tgn:7029392"
    ],
    "tgn:id":1012334,
    "tgn:name":"Pongara, Pointe",
    "tgn:placetype":[
        "aat:300386846"
    ]
},
  "bbox": [],
  "geometry": {"coordinates":[9.3333,0.3833],"type":"Point"}
}