{
  "id": 1080877,
  "type": "Feature",
  "properties": {
    "tgn:hierarchy":[
        "tgn:1080877",
        "tgn:7000895",
        "tgn:1000004",
        "tgn:7016854",
        "tgn:1000120",
        "tgn:7029392"
    ],
    "tgn:id":1080877,
    "tgn:name":"Mukawa",
    "tgn:placetype":[
        "aat:300008347"
    ]
},
  "bbox": [],
  "geometry": {"coordinates":[138.3833,35.7833],"type":"Point"}
}