{
  "id": 7420267,
  "type": "Feature",
  "properties": {
    "tgn:hierarchy":[
        "tgn:7420267",
        "tgn:7005584",
        "tgn:1000001",
        "tgn:7005560",
        "tgn:7029392"
    ],
    "tgn:id":7420267,
    "tgn:name":"Llano Grande",
    "tgn:placetype":[
        "aat:300008347"
    ]
},
  "bbox": [],
  "geometry": {"coordinates":[-100.068056,21.255556],"type":"Point"}
}