{
  "id": 2281307,
  "type": "Feature",
  "properties": {
    "tgn:hierarchy":[
        "tgn:2281307",
        "tgn:1000001",
        "tgn:7012149",
        "tgn:7007256",
        "tgn:7029392"
    ],
    "tgn:id":2281307,
    "tgn:name":"Deep Slough",
    "tgn:placetype":[
        "aat:300008699"
    ]
},
  "bbox": [],
  "geometry": {"coordinates":[-93.0333,30.8667],"type":"Point"}
}