{
  "id": 7275333,
  "type": "Feature",
  "properties": {
    "tgn:hierarchy":[
        "tgn:7275333",
        "tgn:1001708",
        "tgn:1000049",
        "tgn:1000002",
        "tgn:7029392"
    ],
    "tgn:id":7275333,
    "tgn:name":"Tupungato, Cerro",
    "tgn:placetype":[
        "aat:300008795"
    ]
},
  "bbox": [],
  "geometry": {"coordinates":[-69.783333,-33.366667],"type":"Point"}
}