{
  "id": 2143443,
  "type": "Feature",
  "properties": {
    "tgn:hierarchy":[
        "tgn:2143443",
        "tgn:1000001",
        "tgn:7012149",
        "tgn:2000277",
        "tgn:7007240",
        "tgn:7029392"
    ],
    "tgn:id":2143443,
    "tgn:name":"Bailey Mine",
    "tgn:placetype":[
        "aat:300000390"
    ]
},
  "bbox": [],
  "geometry": {"coordinates":[-82.55,29.4667],"type":"Point"}
}