<<<<<<< HEAD
{
  "id": 7484834,
  "type": "Feature",
  "properties": {
    "tgn:hierarchy":[
        "tgn:7484834",
        "tgn:7488858",
        "tgn:1000004",
        "tgn:1000141",
        "tgn:7029392"
    ],
    "tgn:id":7484834,
    "tgn:name":"Baigou Shan",
    "tgn:placetype":[
        "aat:300387033"
    ]
},
  "bbox": [],
  "geometry": {"coordinates":[121.168611,24.121944],"type":"Point"}
}
=======
{"geometry":{"type":"Point","coordinates":[121.168611,24.121944]},"type":"Feature","properties":{"hierarchy":["tgn:7484834","tgn:7488858","tgn:1000004","tgn:1000141","tgn:7029392"],"placetype":["aat:300387033"],"id":7484834,"name:xx":"Baigou Shan"}}
>>>>>>> 03f74aca74312dbeaf24d7e61306dd6a786dc3d0
