{
  "id": 2140490,
  "type": "Feature",
  "properties": {
    "tgn:hierarchy":[
        "tgn:2140490",
        "tgn:1000001",
        "tgn:7016172",
        "tgn:2000123",
        "tgn:7012149",
        "tgn:7029392"
    ],
    "tgn:id":2140490,
    "tgn:name":"Austell, Lake",
    "tgn:placetype":[
        "aat:300006191"
    ]
},
  "bbox": [],
  "geometry": {"coordinates":[-90.7167,35.15],"type":"Point"}
}