{
  "id": 2595152,
  "type": "Feature",
  "properties": {
    "tgn:hierarchy":[
        "tgn:2595152",
        "tgn:1000001",
        "tgn:7012149",
        "tgn:7029392"
    ],
    "tgn:id":2595152,
    "tgn:name":"Posten Bayou",
    "tgn:placetype":[
        "aat:300008699"
    ]
},
  "bbox": [],
  "geometry": {"coordinates":[-93.7167,33.15],"type":"Point"}
}