{
  "id": 2000129,
  "type": "Feature",
  "properties": {
    "tgn:hierarchy":[
        "tgn:2000129",
        "tgn:1000001",
        "tgn:7016172",
        "tgn:7012149",
        "tgn:7029392"
    ],
    "tgn:id":2000129,
    "tgn:name":"Fulton",
    "tgn:placetype":[
        "aat:300387145",
        "aat:300000771"
    ]
},
  "bbox": [],
  "geometry": {"coordinates":[-91.8333,36.3667],"type":"Point"}
}