{
  "id": 2669927,
  "type": "Feature",
  "properties": {
    "tgn:hierarchy":[
        "tgn:2669927",
        "tgn:1000001",
        "tgn:7012149",
        "tgn:2001225",
        "tgn:7007523",
        "tgn:7029392"
    ],
    "tgn:id":2669927,
    "tgn:name":"Sloan Ford",
    "tgn:placetype":[
        "aat:300008347"
    ]
},
  "bbox": [],
  "geometry": {"coordinates":[-91.5333,36.5667],"type":"Point"}
}