{
  "id": 2079137,
  "type": "Feature",
  "properties": {
    "tgn:hierarchy":[
        "tgn:2079137",
        "tgn:1000001",
        "tgn:7012149",
        "tgn:1002658",
        "tgn:7007706",
        "tgn:7029392"
    ],
    "tgn:id":2079137,
    "tgn:name":"Cranberry Prairie",
    "tgn:placetype":[
        "aat:300008347",
        "aat:300387210"
    ]
},
  "bbox": [],
  "geometry": {"coordinates":[-84.5667,40.3833],"type":"Point"}
}