{
  "id": 2182885,
  "type": "Feature",
  "properties": {
    "tgn:hierarchy":[
        "tgn:2182885",
        "tgn:1000001",
        "tgn:7006451",
        "tgn:7012149",
        "tgn:2000097",
        "tgn:7029392"
    ],
    "tgn:id":2182885,
    "tgn:name":"Blue Wash",
    "tgn:placetype":[
        "aat:300008699"
    ]
},
  "bbox": [],
  "geometry": {"coordinates":[-112.95,33.65],"type":"Point"}
}