{
  "id": 2170545,
  "type": "Feature",
  "properties": {
    "tgn:hierarchy":[
        "tgn:2170545",
        "tgn:1000001",
        "tgn:7012149",
        "tgn:1002955",
        "tgn:7007706",
        "tgn:7029392"
    ],
    "tgn:id":2170545,
    "tgn:name":"Big Run",
    "tgn:placetype":[
        "aat:300008699"
    ]
},
  "bbox": [],
  "geometry": {"coordinates":[-80.6667,41.2833],"type":"Point"}
}