{
  "id": 1114036,
  "type": "Feature",
  "properties": {
    "tgn:hierarchy":[
        "tgn:1114036",
        "tgn:1000009",
        "tgn:1000001",
        "tgn:7029392"
    ],
    "tgn:id":1114036,
    "tgn:name":"Willoughby Bay",
    "tgn:placetype":[
        "aat:300132316"
    ]
},
  "bbox": [],
  "geometry": {"coordinates":[-61.7333,17.0333],"type":"Point"}
}