{
  "id": 2036560,
  "type": "Feature",
  "properties": {
    "tgn:hierarchy":[
        "tgn:2036560",
        "tgn:2000663",
        "tgn:1000001",
        "tgn:7012149",
        "tgn:7007254",
        "tgn:7029392"
    ],
    "tgn:id":2036560,
    "tgn:name":"Isabel",
    "tgn:placetype":[
        "aat:300008347"
    ]
},
  "bbox": [],
  "geometry": {"coordinates":[-98.55,37.4667],"type":"Point"}
}