{
  "id": 1052720,
  "type": "Feature",
  "properties": {
    "tgn:hierarchy":[
        "tgn:1052720",
        "tgn:7011450",
        "tgn:1000004",
        "tgn:7014786",
        "tgn:7029392"
    ],
    "tgn:id":1052720,
    "tgn:name":"Berchogur",
    "tgn:placetype":[
        "aat:300008347"
    ]
},
  "bbox": [],
  "geometry": {"coordinates":[58.7167,48.45],"type":"Point"}
}