{
  "id": 7582423,
  "type": "Feature",
  "properties": {
    "tgn:hierarchy":[
        "tgn:7582423",
        "tgn:1000004",
        "tgn:7000198",
        "tgn:1001894",
        "tgn:7029392"
    ],
    "tgn:id":7582423,
    "tgn:name:en":"Khand\u0101ri",
    "tgn:placetype":[
        "aat:300008347"
    ]
},
  "bbox": [],
  "geometry": {"coordinates":[78.892096,24.001157],"type":"Point"}
}