<<<<<<< HEAD
{
  "id": 7050452,
  "type": "Feature",
  "properties": {
    "tgn:hierarchy":[
        "tgn:7050452",
        "tgn:1000003",
        "tgn:7003155",
        "tgn:7003122",
        "tgn:1000080",
        "tgn:7029392"
    ],
    "tgn:id":7050452,
    "tgn:name":"Masseria Speciale",
    "tgn:placetype":[
        "aat:300008347"
    ]
},
  "bbox": [],
  "geometry": {"coordinates":[14.616667,37.55],"type":"Point"}
}
=======
{"geometry":{"type":"Point","coordinates":[14.616667,37.550000]},"type":"Feature","properties":{"hierarchy":["tgn:7050452","tgn:1000003","tgn:7003155","tgn:7003122","tgn:1000080","tgn:7029392"],"placetype":["aat:300008347"],"id":7050452,"name:xx":"Masseria Speciale"}}
>>>>>>> 03f74aca74312dbeaf24d7e61306dd6a786dc3d0
