{
  "id": 1015154,
  "type": "Feature",
  "properties": {
    "tgn:hierarchy":[
        "tgn:1015154",
        "tgn:7005685",
        "tgn:1000001",
        "tgn:7013154",
        "tgn:7029392"
    ],
    "tgn:id":1015154,
    "tgn:name":"Teston",
    "tgn:placetype":[
        "aat:300008347"
    ]
},
  "bbox": [],
  "geometry": {"coordinates":[-79.5333,43.8667],"type":"Point"}
}