{
  "id": 7117701,
  "type": "Feature",
  "properties": {
    "tgn:hierarchy":[
        "tgn:7117701",
        "tgn:7003692",
        "tgn:1000003",
        "tgn:7000084",
        "tgn:7029392"
    ],
    "tgn:id":7117701,
    "tgn:name":"Obersontheim",
    "tgn:placetype":[
        "aat:300008347"
    ]
},
  "bbox": [],
  "geometry": {"coordinates":[9.899167,49.056667],"type":"Point"}
}