{
  "id": 2715694,
  "type": "Feature",
  "properties": {
    "tgn:hierarchy":[
        "tgn:2715694",
        "tgn:1000001",
        "tgn:2001786",
        "tgn:7012149",
        "tgn:7007713",
        "tgn:7029392"
    ],
    "tgn:id":2715694,
    "tgn:name":"Terry and Terry Number 1 Claims Mine",
    "tgn:placetype":[
        "aat:300000390"
    ]
},
  "bbox": [],
  "geometry": {"coordinates":[-103.55,43.7667],"type":"Point"}
}