{
  "id": 2477974,
  "type": "Feature",
  "properties": {
    "tgn:hierarchy":[
        "tgn:2477974",
        "tgn:1000001",
        "tgn:7012149",
        "tgn:2001254",
        "tgn:7007523",
        "tgn:7029392"
    ],
    "tgn:id":2477974,
    "tgn:name":"Machell Hollow",
    "tgn:placetype":[
        "aat:300008761"
    ]
},
  "bbox": [],
  "geometry": {"coordinates":[-91.0167,37.8833],"type":"Point"}
}