{
  "id": 1073265,
  "type": "Feature",
  "properties": {
    "tgn:hierarchy":[
        "tgn:1073265",
        "tgn:1000004",
        "tgn:7016672",
        "tgn:1000111",
        "tgn:7029392"
    ],
    "tgn:id":1073265,
    "tgn:name":"Xunxian",
    "tgn:placetype":[
        "aat:300008347"
    ]
},
  "bbox": [],
  "geometry": {"coordinates":[114.5667,35.65],"type":"Point"}
}