{
  "id": 1119406,
  "type": "Feature",
  "properties": {
    "tgn:hierarchy":[
        "tgn:1119406",
        "tgn:1000001",
        "tgn:1002217",
        "tgn:7012149",
        "tgn:7007710",
        "tgn:7029392"
    ],
    "tgn:id":1119406,
    "tgn:name":"Arthur, Lake",
    "tgn:placetype":[
        "aat:300006191"
    ]
},
  "bbox": [],
  "geometry": {"coordinates":[-80.1167,40.95],"type":"Point"}
}