{
  "id": 2604457,
  "type": "Feature",
  "properties": {
    "tgn:hierarchy":[
        "tgn:2604457",
        "tgn:1000001",
        "tgn:2002241",
        "tgn:7012149",
        "tgn:7007920",
        "tgn:7029392"
    ],
    "tgn:id":2604457,
    "tgn:name":"Rabbit Hollow",
    "tgn:placetype":[
        "aat:300008761"
    ]
},
  "bbox": [],
  "geometry": {"coordinates":[-117.9167,46.5833],"type":"Point"}
}