{
  "id": 7517242,
  "type": "Feature",
  "properties": {
    "tgn:hierarchy":[
        "tgn:7517242",
        "tgn:1009227",
        "tgn:1000226",
        "tgn:7018437",
        "tgn:1000006",
        "tgn:7029392"
    ],
    "tgn:id":7517242,
    "tgn:name:en":"Kononi",
    "tgn:placetype":[
        "aat:300008347"
    ]
},
  "bbox": [],
  "geometry": {"coordinates":[169.533333,-45.966667],"type":"Point"}
}