{
  "id": 7305021,
  "type": "Feature",
  "properties": {
    "tgn:hierarchy":[
        "tgn:7305021",
        "tgn:7002810",
        "tgn:7001158",
        "tgn:1000003",
        "tgn:1000095",
        "tgn:7029392"
    ],
    "tgn:id":7305021,
    "tgn:name":"Lastra de las Eras",
    "tgn:placetype":[
        "aat:300008347"
    ]
},
  "bbox": [],
  "geometry": {"coordinates":[-3.433333,43.05],"type":"Point"}
}