{
  "id": 2538349,
  "type": "Feature",
  "properties": {
    "tgn:hierarchy":[
        "tgn:2538349",
        "tgn:1000001",
        "tgn:7012149",
        "tgn:7007253",
        "tgn:7029392"
    ],
    "tgn:id":2538349,
    "tgn:name":"Neola Creek",
    "tgn:placetype":[
        "aat:300008706"
    ]
},
  "bbox": [],
  "geometry": {"coordinates":[-95.6333,41.5167],"type":"Point"}
}