<<<<<<< HEAD
{
  "id": 7476622,
  "type": "Feature",
  "properties": {
    "tgn:hierarchy":[
        "tgn:7476622",
        "tgn:1000004",
        "tgn:7004300",
        "tgn:1000141",
        "tgn:7029392"
    ],
    "tgn:id":7476622,
    "tgn:name":"Niaochaowo",
    "tgn:placetype":[
        "aat:300387033"
    ]
},
  "bbox": [],
  "geometry": {"coordinates":[119.666028,23.662039],"type":"Point"}
}
=======
{"geometry":{"type":"Point","coordinates":[119.666028,23.662039]},"type":"Feature","properties":{"hierarchy":["tgn:7476622","tgn:1000004","tgn:7004300","tgn:1000141","tgn:7029392"],"placetype":["aat:300387033"],"id":7476622,"name:xx":"Niaochaowo"}}
>>>>>>> 03f74aca74312dbeaf24d7e61306dd6a786dc3d0
