{
  "id": 7099771,
  "type": "Feature",
  "properties": {
    "tgn:hierarchy":[
        "tgn:7099771",
        "tgn:7003669",
        "tgn:1000003",
        "tgn:7000084",
        "tgn:7029392"
    ],
    "tgn:id":7099771,
    "tgn:name":"Solomann",
    "tgn:placetype":[
        "aat:300000206"
    ]
},
  "bbox": [],
  "geometry": {"coordinates":[12.033333,48.566667],"type":"Point"}
}