{
  "id": 7099164,
  "type": "Feature",
  "properties": {
    "tgn:hierarchy":[
        "tgn:7099164",
        "tgn:1000003",
        "tgn:7003688",
        "tgn:7000084",
        "tgn:7029392"
    ],
    "tgn:id":7099164,
    "tgn:name":"Sievershagen",
    "tgn:placetype":[
        "aat:300008347"
    ]
},
  "bbox": [],
  "geometry": {"coordinates":[10.916667,54.183333],"type":"Point"}
}