{
  "id": 7012458,
  "type": "Feature",
  "properties": {
    "tgn:hierarchy":[
        "tgn:7012458",
        "tgn:1000003",
        "tgn:7003682",
        "tgn:7000084",
        "tgn:7029392"
    ],
    "tgn:id":7012458,
    "tgn:name":"Frankenthal",
    "tgn:placetype":[
        "aat:300008347"
    ]
},
  "bbox": [],
  "geometry": {"coordinates":[8.355,49.537222],"type":"Point"}
}