{
  "id": 1063248,
  "type": "Feature",
  "properties": {
    "tgn:hierarchy":[
        "tgn:1063248",
        "tgn:7003767",
        "tgn:1000003",
        "tgn:1000097",
        "tgn:7029392"
    ],
    "tgn:id":1063248,
    "tgn:name":"Kristianopel",
    "tgn:placetype":[
        "aat:300008347"
    ]
},
  "bbox": [],
  "geometry": {"coordinates":[16.0833,56.25],"type":"Point"}
}