{
  "id": 7550869,
  "type": "Feature",
  "properties": {
    "tgn:hierarchy":[
        "tgn:7550869",
        "tgn:1000004",
        "tgn:7000198",
        "tgn:1001957",
        "tgn:7029392"
    ],
    "tgn:id":7550869,
    "tgn:name:en":"Damthang",
    "tgn:placetype":[
        "aat:300008347"
    ]
},
  "bbox": [],
  "geometry": {"coordinates":[88.398773,27.215258],"type":"Point"}
}