{
  "id": 2716742,
  "type": "Feature",
  "properties": {
    "tgn:hierarchy":[
        "tgn:2716742",
        "tgn:7014201",
        "tgn:1000001",
        "tgn:7012149",
        "tgn:7007239",
        "tgn:7029392"
    ],
    "tgn:id":2716742,
    "tgn:name":"The Villa",
    "tgn:placetype":[
        "aat:300008347"
    ]
},
  "bbox": [],
  "geometry": {"coordinates":[-75.6333,39.65],"type":"Point"}
}