<<<<<<< HEAD
{
  "id": 2767124,
  "type": "Feature",
  "properties": {
    "tgn:hierarchy":[
        "tgn:2767124",
        "tgn:1000001",
        "tgn:7012149",
        "tgn:2001459",
        "tgn:7007566",
        "tgn:7029392"
    ],
    "tgn:id":2767124,
    "tgn:name":"White Rock Canyon",
    "tgn:placetype":[
        "aat:300008761"
    ]
},
  "bbox": [],
  "geometry": {"coordinates":[-103.5833,36.8833],"type":"Point"}
}
=======
{"geometry":{"type":"Point","coordinates":[-103.583300,36.883300]},"type":"Feature","properties":{"hierarchy":["tgn:2767124","tgn:1000001","tgn:7012149","tgn:2001459","tgn:7007566","tgn:7029392"],"placetype":["aat:300008761"],"id":2767124,"name:xx":"White Rock Canyon"}}
>>>>>>> 03f74aca74312dbeaf24d7e61306dd6a786dc3d0
