{
  "id": 7143366,
  "type": "Feature",
  "properties": {
    "tgn:hierarchy":[
        "tgn:7143366",
        "tgn:1000003",
        "tgn:7003688",
        "tgn:7000084",
        "tgn:7029392"
    ],
    "tgn:id":7143366,
    "tgn:name":"Maasb\u00fcllhof",
    "tgn:placetype":[
        "aat:300000206"
    ]
},
  "bbox": [],
  "geometry": {"coordinates":[9.533333,54.766667],"type":"Point"}
}