{
  "id": 2366889,
  "type": "Feature",
  "properties": {
    "tgn:hierarchy":[
        "tgn:2366889",
        "tgn:1000001",
        "tgn:7012149",
        "tgn:7019014",
        "tgn:7007251",
        "tgn:7029392"
    ],
    "tgn:id":2366889,
    "tgn:name":"Griswold Lake",
    "tgn:placetype":[
        "aat:300008680"
    ]
},
  "bbox": [],
  "geometry": {"coordinates":[-88.2167,42.2833],"type":"Point"}
}