{
  "id": 7483716,
  "type": "Feature",
  "properties": {
    "tgn:hierarchy":[
        "tgn:7483716",
        "tgn:7001001",
        "tgn:1000004",
        "tgn:1000141",
        "tgn:7029392"
    ],
    "tgn:id":7483716,
    "tgn:name":"Xinhua Zhongxue",
    "tgn:placetype":[
        "aat:300006495"
    ]
},
  "bbox": [],
  "geometry": {"coordinates":[120.462222,23.489167],"type":"Point"}
}