{
  "id": 2729487,
  "type": "Feature",
  "properties": {
    "tgn:hierarchy":[
        "tgn:2729487",
        "tgn:1000001",
        "tgn:7012149",
        "tgn:2002122",
        "tgn:7007827",
        "tgn:7029392"
    ],
    "tgn:id":2729487,
    "tgn:name":"Tristram Creek",
    "tgn:placetype":[
        "aat:300008706"
    ]
},
  "bbox": [],
  "geometry": {"coordinates":[-111.2167,41.1333],"type":"Point"}
}