{
  "id": 2708954,
  "type": "Feature",
  "properties": {
    "tgn:hierarchy":[
        "tgn:2708954",
        "tgn:1000001",
        "tgn:7012149",
        "tgn:2001714",
        "tgn:7007708",
        "tgn:7029392"
    ],
    "tgn:id":2708954,
    "tgn:name":"T Canal",
    "tgn:placetype":[
        "aat:300006075"
    ]
},
  "bbox": [],
  "geometry": {"coordinates":[-121.3833,42.0333],"type":"Point"}
}