{
  "id": 2602563,
  "type": "Feature",
  "properties": {
    "tgn:hierarchy":[
        "tgn:2602563",
        "tgn:1000001",
        "tgn:2000920",
        "tgn:7012149",
        "tgn:7007515",
        "tgn:7029392"
    ],
    "tgn:id":2602563,
    "tgn:name":"Quahog Bay",
    "tgn:placetype":[
        "aat:300132316"
    ]
},
  "bbox": [],
  "geometry": {"coordinates":[-69.9167,43.7833],"type":"Point"}
}