{
  "id": 2733147,
  "type": "Feature",
  "properties": {
    "tgn:hierarchy":[
        "tgn:2733147",
        "tgn:1000001",
        "tgn:2001429",
        "tgn:7012149",
        "tgn:7007566",
        "tgn:7029392"
    ],
    "tgn:id":2733147,
    "tgn:name":"Turkey Park Spring",
    "tgn:placetype":[
        "aat:300008697"
    ]
},
  "bbox": [],
  "geometry": {"coordinates":[-107.9667,34.1333],"type":"Point"}
}