{
  "id": 2545506,
  "type": "Feature",
  "properties": {
    "tgn:hierarchy":[
        "tgn:2545506",
        "tgn:1000001",
        "tgn:7012149",
        "tgn:2001286",
        "tgn:7007524",
        "tgn:7029392"
    ],
    "tgn:id":2545506,
    "tgn:name":"North Fork Bristow Creek",
    "tgn:placetype":[
        "aat:300008706"
    ]
},
  "bbox": [],
  "geometry": {"coordinates":[-115.4333,48.5667],"type":"Point"}
}