{
  "id": 7326293,
  "type": "Feature",
  "properties": {
    "tgn:hierarchy":[
        "tgn:7326293",
        "tgn:7002758",
        "tgn:7002841",
        "tgn:1000003",
        "tgn:1000095",
        "tgn:7029392"
    ],
    "tgn:id":7326293,
    "tgn:name":"Pie de Palo, Arroyo de",
    "tgn:placetype":[
        "aat:300266554",
        "aat:300008699"
    ]
},
  "bbox": [],
  "geometry": {"coordinates":[-6.033333,37.45],"type":"Point"}
}