{
  "id": 7264897,
  "type": "Feature",
  "properties": {
    "tgn:concordances":{
        "gn:id":"2751513"
    },
    "tgn:hierarchy":[
        "tgn:7264897",
        "tgn:1000003",
        "tgn:7003627",
        "tgn:7016845",
        "tgn:7029392"
    ],
    "tgn:id":7264897,
    "tgn:name:nl":"Loerik",
    "tgn:placetype":[
        "aat:300008347"
    ]
},
  "bbox": [],
  "geometry": {"coordinates":[5.183333,52.033333],"type":"Point"}
}