{
  "id": 2156173,
  "type": "Feature",
  "properties": {
    "tgn:hierarchy":[
        "tgn:2156173",
        "tgn:1000001",
        "tgn:7012149",
        "tgn:2001154",
        "tgn:7007522",
        "tgn:7029392"
    ],
    "tgn:id":2156173,
    "tgn:name":"Beards Creek",
    "tgn:placetype":[
        "aat:300008706"
    ]
},
  "bbox": [],
  "geometry": {"coordinates":[-89.75,34.7333],"type":"Point"}
}