{
  "id": 2446439,
  "type": "Feature",
  "properties": {
    "tgn:hierarchy":[
        "tgn:2446439",
        "tgn:1000001",
        "tgn:7012149",
        "tgn:1002961",
        "tgn:7007568",
        "tgn:7029392"
    ],
    "tgn:id":2446439,
    "tgn:name":"Lewis Hollow",
    "tgn:placetype":[
        "aat:300008761"
    ]
},
  "bbox": [],
  "geometry": {"coordinates":[-74.0833,42.0833],"type":"Point"}
}