{
  "id": 7381910,
  "type": "Feature",
  "properties": {
    "tgn:hierarchy":[
        "tgn:7381910",
        "tgn:1001853",
        "tgn:1000001",
        "tgn:7005560",
        "tgn:7029392"
    ],
    "tgn:id":7381910,
    "tgn:name":"Manga del Nopal",
    "tgn:placetype":[
        "aat:300008347"
    ]
},
  "bbox": [],
  "geometry": {"coordinates":[-101.433333,29.083333],"type":"Point"}
}