{
  "id": 7226662,
  "type": "Feature",
  "properties": {
    "tgn:hierarchy":[
        "tgn:7226662",
        "tgn:7011270",
        "tgn:7002674",
        "tgn:1000003",
        "tgn:1000074",
        "tgn:7029392"
    ],
    "tgn:id":7226662,
    "tgn:name":"Parth\u00e9nos, \u00c1kra",
    "tgn:placetype":[
        "aat:300008850"
    ]
},
  "bbox": [],
  "geometry": {"coordinates":[25.366667,37.016667],"type":"Point"}
}