{
  "id": 2073124,
  "type": "Feature",
  "properties": {
    "tgn:hierarchy":[
        "tgn:2073124",
        "tgn:1000001",
        "tgn:7013638",
        "tgn:7012149",
        "tgn:7007568",
        "tgn:7029392"
    ],
    "tgn:id":2073124,
    "tgn:name":"West Lebanon",
    "tgn:placetype":[
        "aat:300008347"
    ]
},
  "bbox": [],
  "geometry": {"coordinates":[-73.4667,42.4833],"type":"Point"}
}