{
  "id": 2617517,
  "type": "Feature",
  "properties": {
    "tgn:hierarchy":[
        "tgn:2617517",
        "tgn:1000001",
        "tgn:2000924",
        "tgn:7012149",
        "tgn:7007515",
        "tgn:7029392"
    ],
    "tgn:id":2617517,
    "tgn:name":"Richs Ledge",
    "tgn:placetype":[
        "aat:300132348"
    ]
},
  "bbox": [],
  "geometry": {"coordinates":[-68.5833,44.0667],"type":"Point"}
}