{
  "id": 7537838,
  "type": "Feature",
  "properties": {
    "tgn:hierarchy":[
        "tgn:7537838",
        "tgn:7001242",
        "tgn:7016833",
        "tgn:7000124",
        "tgn:7029392"
    ],
    "tgn:id":7537838,
    "tgn:name:en":"Nazlat 'Abd All\u0101h",
    "tgn:placetype":[
        "aat:300008347"
    ]
},
  "bbox": [],
  "geometry": {"coordinates":[31.416667,26.883333],"type":"Point"}
}