{
  "id": 2550457,
  "type": "Feature",
  "properties": {
    "tgn:hierarchy":[
        "tgn:2550457",
        "tgn:1000001",
        "tgn:7012149",
        "tgn:1002924",
        "tgn:7007568",
        "tgn:7029392"
    ],
    "tgn:id":2550457,
    "tgn:name":"Northwest Woods",
    "tgn:placetype":[
        "aat:300132451"
    ]
},
  "bbox": [],
  "geometry": {"coordinates":[-72.2167,41.0333],"type":"Point"}
}