<<<<<<< HEAD
{
  "id": 7240206,
  "type": "Feature",
  "properties": {
    "tgn:hierarchy":[
        "tgn:7240206",
        "tgn:7003457",
        "tgn:1000003",
        "tgn:1000063",
        "tgn:7018236",
        "tgn:7029392"
    ],
    "tgn:id":7240206,
    "tgn:name":"Eiland",
    "tgn:placetype":[
        "aat:300008347"
    ]
},
  "bbox": [],
  "geometry": {"coordinates":[4.01733,50.892926],"type":"Point"}
}
=======
{"geometry":{"type":"Point","coordinates":[4.017330,50.892926]},"type":"Feature","properties":{"hierarchy":["tgn:7240206","tgn:7003457","tgn:1000003","tgn:1000063","tgn:7018236","tgn:7029392"],"placetype":["aat:300008347"],"id":7240206,"name:xx":"Eiland"}}
>>>>>>> 03f74aca74312dbeaf24d7e61306dd6a786dc3d0
