{
  "id": 1053009,
  "type": "Feature",
  "properties": {
    "tgn:hierarchy":[
        "tgn:1053009",
        "tgn:1003354",
        "tgn:1000004",
        "tgn:7018214",
        "tgn:7002435",
        "tgn:7029392"
    ],
    "tgn:id":1053009,
    "tgn:name":"Bomnak",
    "tgn:placetype":[
        "aat:300008347"
    ]
},
  "bbox": [],
  "geometry": {"coordinates":[128.9167,54.7667],"type":"Point"}
}