{
  "id": 7263538,
  "type": "Feature",
  "properties": {
    "tgn:hierarchy":[
        "tgn:7263538",
        "tgn:7003614",
        "tgn:1000003",
        "tgn:7016845",
        "tgn:7029392"
    ],
    "tgn:id":7263538,
    "tgn:name:nl":"Leembrug",
    "tgn:placetype":[
        "aat:300007836"
    ]
},
  "bbox": [],
  "geometry": {"coordinates":[6.416667,52.933333],"type":"Point"}
}