{
  "id": 2780860,
  "type": "Feature",
  "properties": {
    "tgn:hierarchy":[
        "tgn:2780860",
        "tgn:1000001",
        "tgn:7012149",
        "tgn:2002372",
        "tgn:7007923",
        "tgn:7029392"
    ],
    "tgn:id":2780860,
    "tgn:name":"Woodard Ditch",
    "tgn:placetype":[
        "aat:300006075"
    ]
},
  "bbox": [],
  "geometry": {"coordinates":[-104.3167,41.8167],"type":"Point"}
}