{
  "id": 2393515,
  "type": "Feature",
  "properties": {
    "tgn:hierarchy":[
        "tgn:2393515",
        "tgn:1000001",
        "tgn:7012149",
        "tgn:2001247",
        "tgn:7007523",
        "tgn:7029392"
    ],
    "tgn:id":2393515,
    "tgn:name":"Hog Cave Hollow",
    "tgn:placetype":[
        "aat:300008761"
    ]
},
  "bbox": [],
  "geometry": {"coordinates":[-91.25,37.1167],"type":"Point"}
}