{
  "id": 2786211,
  "type": "Feature",
  "properties": {
    "tgn:hierarchy":[
        "tgn:2786211",
        "tgn:1000001",
        "tgn:1002276",
        "tgn:7012149",
        "tgn:7007708",
        "tgn:7029392"
    ],
    "tgn:id":2786211,
    "tgn:name":"Youngs Bay",
    "tgn:placetype":[
        "aat:300132316"
    ]
},
  "bbox": [],
  "geometry": {"coordinates":[-123.85,46.1667],"type":"Point"}
}