{
  "id": 1009527,
  "type": "Feature",
  "properties": {
    "tgn:hierarchy":[
        "tgn:1009527",
        "tgn:7498210",
        "tgn:1000004",
        "tgn:1000141",
        "tgn:7029392"
    ],
    "tgn:id":1009527,
    "tgn:name":"Dongquan Dao",
    "tgn:placetype":[
        "aat:300008791"
    ]
},
  "bbox": [],
  "geometry": {"coordinates":[119.975,25.959444],"type":"Point"}
}