{
  "id": 2739082,
  "type": "Feature",
  "properties": {
    "tgn:hierarchy":[
        "tgn:2739082",
        "tgn:1000001",
        "tgn:7012149",
        "tgn:1003017",
        "tgn:7007710",
        "tgn:7029392"
    ],
    "tgn:id":2739082,
    "tgn:name":"Unity Run",
    "tgn:placetype":[
        "aat:300008699"
    ]
},
  "bbox": [],
  "geometry": {"coordinates":[-79.4167,40.3167],"type":"Point"}
}