{
  "id": 7283265,
  "type": "Feature",
  "properties": {
    "tgn:hierarchy":[
        "tgn:7283265",
        "tgn:1001702",
        "tgn:1000049",
        "tgn:1000002",
        "tgn:7029392"
    ],
    "tgn:id":7283265,
    "tgn:name":"Parr, Punta",
    "tgn:placetype":[
        "aat:300386846"
    ]
},
  "bbox": [],
  "geometry": {"coordinates":[-75.355,-50.010833],"type":"Point"}
}