{
  "id": 7228979,
  "type": "Feature",
  "properties": {
    "tgn:hierarchy":[
        "tgn:7228979",
        "tgn:7011330",
        "tgn:7002674",
        "tgn:1000003",
        "tgn:1000074",
        "tgn:7029392"
    ],
    "tgn:id":7228979,
    "tgn:name":"L\u00e9rou, Dh\u00edavlos",
    "tgn:placetype":[
        "aat:300266559"
    ]
},
  "bbox": [],
  "geometry": {"coordinates":[26.883333,37.083333],"type":"Point"}
}