{
  "id": 2385880,
  "type": "Feature",
  "properties": {
    "tgn:hierarchy":[
        "tgn:2385880",
        "tgn:1000001",
        "tgn:7012149",
        "tgn:7007157",
        "tgn:1002957",
        "tgn:7029392"
    ],
    "tgn:id":2385880,
    "tgn:name":"Henning Mine",
    "tgn:placetype":[
        "aat:300000390"
    ]
},
  "bbox": [],
  "geometry": {"coordinates":[-120.4333,38.0333],"type":"Point"}
}