{
  "id": 1096174,
  "type": "Feature",
  "properties": {
    "tgn:hierarchy":[
        "tgn:1096174",
        "tgn:7000490",
        "tgn:1000006",
        "tgn:7006238",
        "tgn:7029392"
    ],
    "tgn:id":1096174,
    "tgn:name":"Balwyn",
    "tgn:placetype":[
        "aat:300008347"
    ]
},
  "bbox": [],
  "geometry": {"coordinates":[145.0667,-37.8167],"type":"Point"}
}