{
  "id": 2306366,
  "type": "Feature",
  "properties": {
    "tgn:hierarchy":[
        "tgn:2306366",
        "tgn:1000001",
        "tgn:2001432",
        "tgn:7012149",
        "tgn:7007566",
        "tgn:7029392"
    ],
    "tgn:id":2306366,
    "tgn:name":"East Fork Chicorica Creek",
    "tgn:placetype":[
        "aat:300008706"
    ]
},
  "bbox": [],
  "geometry": {"coordinates":[-104.2667,36.9333],"type":"Point"}
}