{
  "id": 1086996,
  "type": "Feature",
  "properties": {
    "tgn:hierarchy":[
        "tgn:1086996",
        "tgn:1001586",
        "tgn:1000004",
        "tgn:7018456",
        "tgn:1000144",
        "tgn:7029392"
    ],
    "tgn:id":1086996,
    "tgn:name":"Yaylak",
    "tgn:placetype":[
        "aat:300008347"
    ]
},
  "bbox": [],
  "geometry": {"coordinates":[38.3333,37.3833],"type":"Point"}
}