<<<<<<< HEAD
{
  "id": 2407948,
  "type": "Feature",
  "properties": {
    "tgn:hierarchy":[
        "tgn:2407948",
        "tgn:1000001",
        "tgn:7012149",
        "tgn:2001124",
        "tgn:7007522",
        "tgn:7029392"
    ],
    "tgn:id":2407948,
    "tgn:name":"Hurricane Creek",
    "tgn:placetype":[
        "aat:300008706"
    ]
},
  "bbox": [],
  "geometry": {"coordinates":[-90.0667,31.6833],"type":"Point"}
}
=======
{"geometry":{"type":"Point","coordinates":[-90.066700,31.683300]},"type":"Feature","properties":{"hierarchy":["tgn:2407948","tgn:1000001","tgn:7012149","tgn:2001124","tgn:7007522","tgn:7029392"],"placetype":["aat:300008706"],"id":2407948,"name:xx":"Hurricane Creek"}}
>>>>>>> 03f74aca74312dbeaf24d7e61306dd6a786dc3d0
