<<<<<<< HEAD
{
  "id": 2339150,
  "type": "Feature",
  "properties": {
    "tgn:hierarchy":[
        "tgn:2339150",
        "tgn:1000001",
        "tgn:2001411",
        "tgn:7012149",
        "tgn:7007526",
        "tgn:7029392"
    ],
    "tgn:id":2339150,
    "tgn:name":"Franks Creek",
    "tgn:placetype":[
        "aat:300008706"
    ]
},
  "bbox": [],
  "geometry": {"coordinates":[-115.8667,41.2833],"type":"Point"}
}
=======
{"geometry":{"type":"Point","coordinates":[-115.866700,41.283300]},"type":"Feature","properties":{"hierarchy":["tgn:2339150","tgn:1000001","tgn:2001411","tgn:7012149","tgn:7007526","tgn:7029392"],"placetype":["aat:300008706"],"id":2339150,"name:xx":"Franks Creek"}}
>>>>>>> 03f74aca74312dbeaf24d7e61306dd6a786dc3d0
