{
  "id": 2339150,
  "type": "Feature",
  "properties": {
    "tgn:hierarchy":[
        "tgn:2339150",
        "tgn:1000001",
        "tgn:2001411",
        "tgn:7012149",
        "tgn:7007526",
        "tgn:7029392"
    ],
    "tgn:id":2339150,
    "tgn:name":"Franks Creek",
    "tgn:placetype":[
        "aat:300008706"
    ]
},
  "bbox": [],
  "geometry": {"coordinates":[-115.8667,41.2833],"type":"Point"}
}