{
  "id": 7151861,
  "type": "Feature",
  "properties": {
    "tgn:hierarchy":[
        "tgn:7151861",
        "tgn:7003692",
        "tgn:1000003",
        "tgn:7000084",
        "tgn:7029392"
    ],
    "tgn:id":7151861,
    "tgn:name":"Kammerhof",
    "tgn:placetype":[
        "aat:300008347"
    ]
},
  "bbox": [],
  "geometry": {"coordinates":[9.716667,47.733333],"type":"Point"}
}