{
  "id": 2354750,
  "type": "Feature",
  "properties": {
    "tgn:hierarchy":[
        "tgn:2354750",
        "tgn:7006450",
        "tgn:1000001",
        "tgn:7012149",
        "tgn:7019760",
        "tgn:7029392"
    ],
    "tgn:id":2354750,
    "tgn:name":"Good Island",
    "tgn:placetype":[
        "aat:300008791"
    ]
},
  "bbox": [],
  "geometry": {"coordinates":[-133.8833,57.4833],"type":"Point"}
}