{
  "id": 7447284,
  "type": "Feature",
  "properties": {
    "tgn:hierarchy":[
        "tgn:7447284",
        "tgn:7019182",
        "tgn:7002448",
        "tgn:1000003",
        "tgn:7008591",
        "tgn:7029392"
    ],
    "tgn:id":7447284,
    "tgn:name:en":"Six Road Ends",
    "tgn:placetype":[
        "aat:300008347"
    ]
},
  "bbox": [],
  "geometry": {"coordinates":[-5.633333,54.616667],"type":"Point"}
}