{
  "id": 7581724,
  "type": "Feature",
  "properties": {
    "tgn:hierarchy":[
        "tgn:7581724",
        "tgn:1000004",
        "tgn:7000198",
        "tgn:1001895",
        "tgn:7029392"
    ],
    "tgn:id":7581724,
    "tgn:name:en":"Sindkhed",
    "tgn:placetype":[
        "aat:300008347"
    ]
},
  "bbox": [],
  "geometry": {"coordinates":[76.133333,19.966667],"type":"Point"}
}