{
  "id": 1023847,
  "type": "Feature",
  "properties": {
    "tgn:hierarchy":[
        "tgn:1023847",
        "tgn:1000050",
        "tgn:1000704",
        "tgn:1000002",
        "tgn:7029392"
    ],
    "tgn:id":1023847,
    "tgn:name":"La Cruz",
    "tgn:placetype":[
        "aat:300008347"
    ]
},
  "bbox": [],
  "geometry": {"coordinates":[-76.9667,1.5833],"type":"Point"}
}