{
  "id": 1058196,
  "type": "Feature",
  "properties": {
    "tgn:hierarchy":[
        "tgn:1058196",
        "tgn:1000003",
        "tgn:7011662",
        "tgn:7006660",
        "tgn:7029392"
    ],
    "tgn:id":1058196,
    "tgn:name":"Pantayevka",
    "tgn:placetype":[
        "aat:300008347"
    ]
},
  "bbox": [],
  "geometry": {"coordinates":[32.8667,48.7333],"type":"Point"}
}