{
  "id": 7419363,
  "type": "Feature",
  "properties": {
    "tgn:hierarchy":[
        "tgn:7419363",
        "tgn:1000001",
        "tgn:7005589",
        "tgn:7005560",
        "tgn:7029392"
    ],
    "tgn:id":7419363,
    "tgn:name:es":"El Popo",
    "tgn:placetype":[
        "aat:300008347"
    ]
},
  "bbox": [],
  "geometry": {"coordinates":[-100.4875,27.296667],"type":"Point"}
}