{
  "id": 1083785,
  "type": "Feature",
  "properties": {
    "tgn:hierarchy":[
        "tgn:1083785",
        "tgn:7002460",
        "tgn:1000004",
        "tgn:1000133",
        "tgn:7029392"
    ],
    "tgn:id":1083785,
    "tgn:name":"Shabqadar",
    "tgn:placetype":[
        "aat:300008347"
    ]
},
  "bbox": [],
  "geometry": {"coordinates":[71.5667,34.2167],"type":"Point"}
}