<<<<<<< HEAD
{
  "id": 7485625,
  "type": "Feature",
  "properties": {
    "tgn:hierarchy":[
        "tgn:7485625",
        "tgn:1000004",
        "tgn:7490934",
        "tgn:1000141",
        "tgn:7029392"
    ],
    "tgn:id":7485625,
    "tgn:name":"Tainan Yizhong",
    "tgn:placetype":[
        "aat:300006495"
    ]
},
  "bbox": [],
  "geometry": {"coordinates":[120.216667,22.995278],"type":"Point"}
}
=======
{"geometry":{"type":"Point","coordinates":[120.216667,22.995278]},"type":"Feature","properties":{"hierarchy":["tgn:7485625","tgn:1000004","tgn:7490934","tgn:1000141","tgn:7029392"],"placetype":["aat:300006495"],"id":7485625,"name:xx":"Tainan Yizhong"}}
>>>>>>> 03f74aca74312dbeaf24d7e61306dd6a786dc3d0
