{
  "id": 7468271,
  "type": "Feature",
  "properties": {
    "tgn:hierarchy":[
        "tgn:7468271",
        "tgn:1000004",
        "tgn:7467799",
        "tgn:1000141",
        "tgn:7029392"
    ],
    "tgn:id":7468271,
    "tgn:name":"Qiedongjiao",
    "tgn:placetype":[
        "aat:300000745"
    ]
},
  "bbox": [],
  "geometry": {"coordinates":[120.539991,24.021967],"type":"Point"}
}