{
  "id": 7000787,
  "type": "Feature",
  "properties": {
    "tgn:hierarchy":[
        "tgn:7000787",
        "tgn:1009881",
        "tgn:7001242",
        "tgn:7014990",
        "tgn:1000183",
        "tgn:7029392"
    ],
    "tgn:id":7000787,
    "tgn:name":"Bubaque, Ilha de",
    "tgn:placetype":[
        "aat:300008791"
    ]
},
  "bbox": [],
  "geometry": {"coordinates":[-15.8667,11.25],"type":"Point"}
}