{
  "id": 7093837,
  "type": "Feature",
  "properties": {
    "tgn:hierarchy":[
        "tgn:7093837",
        "tgn:7003669",
        "tgn:1000003",
        "tgn:7000084",
        "tgn:7029392"
    ],
    "tgn:id":7093837,
    "tgn:name":"Seekarkreuz",
    "tgn:placetype":[
        "aat:300008795"
    ]
},
  "bbox": [],
  "geometry": {"coordinates":[11.65,47.65],"type":"Point"}
}