{
  "id": 2042891,
  "type": "Feature",
  "properties": {
    "tgn:hierarchy":[
        "tgn:2042891",
        "tgn:1000001",
        "tgn:7012149",
        "tgn:2000882",
        "tgn:7007256",
        "tgn:7029392"
    ],
    "tgn:id":2042891,
    "tgn:name":"Grandbois",
    "tgn:placetype":[
        "aat:300008347"
    ]
},
  "bbox": [],
  "geometry": {"coordinates":[-90.5333,29.55],"type":"Point"}
}