{
  "id": 2594570,
  "type": "Feature",
  "properties": {
    "tgn:hierarchy":[
        "tgn:2594570",
        "tgn:1000001",
        "tgn:2001477",
        "tgn:7012149",
        "tgn:7007709",
        "tgn:7029392"
    ],
    "tgn:id":2594570,
    "tgn:name":"Portsmouth Island",
    "tgn:placetype":[
        "aat:300008791"
    ]
},
  "bbox": [],
  "geometry": {"coordinates":[-76.1333,34.9833],"type":"Point"}
}