{
  "id": 2470436,
  "type": "Feature",
  "properties": {
    "tgn:hierarchy":[
        "tgn:2470436",
        "tgn:1000001",
        "tgn:7012149",
        "tgn:1002821",
        "tgn:7007568",
        "tgn:7029392"
    ],
    "tgn:id":2470436,
    "tgn:name":"Lorraine, Lake",
    "tgn:placetype":[
        "aat:300008680"
    ]
},
  "bbox": [],
  "geometry": {"coordinates":[-73.4167,42.85],"type":"Point"}
}