{
  "id": 7236669,
  "type": "Feature",
  "properties": {
    "tgn:hierarchy":[
        "tgn:7236669",
        "tgn:7002752",
        "tgn:7001399",
        "tgn:1000003",
        "tgn:1000074",
        "tgn:7029392"
    ],
    "tgn:id":7236669,
    "tgn:name":"Ellin\u00f3kastron",
    "tgn:placetype":[
        "aat:300008347"
    ]
},
  "bbox": [],
  "geometry": {"coordinates":[21.796944,39.689722],"type":"Point"}
}