{
  "id": 7404505,
  "type": "Feature",
  "properties": {
    "tgn:hierarchy":[
        "tgn:7404505",
        "tgn:7005578",
        "tgn:1000001",
        "tgn:7005560",
        "tgn:7029392"
    ],
    "tgn:id":7404505,
    "tgn:name":"San Pablito",
    "tgn:placetype":[
        "aat:300008347"
    ]
},
  "bbox": [],
  "geometry": {"coordinates":[-91.083333,19.033333],"type":"Point"}
}