<<<<<<< HEAD
{
  "id": 2401791,
  "type": "Feature",
  "properties": {
    "tgn:hierarchy":[
        "tgn:2401791",
        "tgn:1000001",
        "tgn:7012149",
        "tgn:2001211",
        "tgn:7007523",
        "tgn:7029392"
    ],
    "tgn:id":2401791,
    "tgn:name":"Horseshoe Lake",
    "tgn:placetype":[
        "aat:300008680"
    ]
},
  "bbox": [],
  "geometry": {"coordinates":[-92.65,37.65],"type":"Point"}
}
=======
{"geometry":{"type":"Point","coordinates":[-92.650000,37.650000]},"type":"Feature","properties":{"hierarchy":["tgn:2401791","tgn:1000001","tgn:7012149","tgn:2001211","tgn:7007523","tgn:7029392"],"placetype":["aat:300008680"],"id":2401791,"name:xx":"Horseshoe Lake"}}
>>>>>>> 03f74aca74312dbeaf24d7e61306dd6a786dc3d0
