{
  "id": 2082150,
  "type": "Feature",
  "properties": {
    "tgn:hierarchy":[
        "tgn:2082150",
        "tgn:1000001",
        "tgn:7012149",
        "tgn:1002784",
        "tgn:7007706",
        "tgn:7029392"
    ],
    "tgn:id":2082150,
    "tgn:name":"Tarlton",
    "tgn:placetype":[
        "aat:300008347"
    ]
},
  "bbox": [],
  "geometry": {"coordinates":[-82.7667,39.55],"type":"Point"}
}