<<<<<<< HEAD
{
  "id": 2335450,
  "type": "Feature",
  "properties": {
    "tgn:hierarchy":[
        "tgn:2335450",
        "tgn:1000001",
        "tgn:7012149",
        "tgn:1002397",
        "tgn:7007568",
        "tgn:7029392"
    ],
    "tgn:id":2335450,
    "tgn:name":"Fort Plain Reservoir",
    "tgn:placetype":[
        "aat:300006191"
    ]
},
  "bbox": [],
  "geometry": {"coordinates":[-74.5667,43.0167],"type":"Point"}
}
=======
{"geometry":{"type":"Point","coordinates":[-74.566700,43.016700]},"type":"Feature","properties":{"hierarchy":["tgn:2335450","tgn:1000001","tgn:7012149","tgn:1002397","tgn:7007568","tgn:7029392"],"placetype":["aat:300006191"],"id":2335450,"name:xx":"Fort Plain Reservoir"}}
>>>>>>> 03f74aca74312dbeaf24d7e61306dd6a786dc3d0
