{
  "id": 2477383,
  "type": "Feature",
  "properties": {
    "tgn:hierarchy":[
        "tgn:2477383",
        "tgn:1000001",
        "tgn:1002328",
        "tgn:7012149",
        "tgn:7007568",
        "tgn:7029392"
    ],
    "tgn:id":2477383,
    "tgn:name":"Lyon Mountain",
    "tgn:placetype":[
        "aat:300008798"
    ]
},
  "bbox": [],
  "geometry": {"coordinates":[-74.6667,42.3333],"type":"Point"}
}