{
  "id": 2557220,
  "type": "Feature",
  "properties": {
    "tgn:hierarchy":[
        "tgn:2557220",
        "tgn:1000001",
        "tgn:2001810",
        "tgn:7012149",
        "tgn:7007713",
        "tgn:7029392"
    ],
    "tgn:id":2557220,
    "tgn:name":"Old Ironsides Mine",
    "tgn:placetype":[
        "aat:300000390"
    ]
},
  "bbox": [],
  "geometry": {"coordinates":[-103.8667,44.35],"type":"Point"}
}