{
  "id": 7311391,
  "type": "Feature",
  "properties": {
    "tgn:hierarchy":[
        "tgn:7311391",
        "tgn:1001630",
        "tgn:1000049",
        "tgn:1000002",
        "tgn:7029392"
    ],
    "tgn:id":7311391,
    "tgn:name":"Monos, Quebrada de los",
    "tgn:placetype":[
        "aat:300266554",
        "aat:300008699"
    ]
},
  "bbox": [],
  "geometry": {"coordinates":[-69.783333,-27.783333],"type":"Point"}
}