{
  "id": 2451319,
  "type": "Feature",
  "properties": {
    "tgn:hierarchy":[
        "tgn:2451319",
        "tgn:2002142",
        "tgn:1000001",
        "tgn:7012149",
        "tgn:7007919",
        "tgn:7029392"
    ],
    "tgn:id":2451319,
    "tgn:name":"Little Baltimore",
    "tgn:placetype":[
        "aat:300008347"
    ]
},
  "bbox": [],
  "geometry": {"coordinates":[-79.3667,38.1833],"type":"Point"}
}