{
  "id": 7275330,
  "type": "Feature",
  "properties": {
    "tgn:hierarchy":[
        "tgn:7275330",
        "tgn:1001708",
        "tgn:1000049",
        "tgn:1000002",
        "tgn:7029392"
    ],
    "tgn:id":7275330,
    "tgn:name":"Tupungato, Quebrada del",
    "tgn:placetype":[
        "aat:300008699"
    ]
},
  "bbox": [],
  "geometry": {"coordinates":[-69.916667,-33.366667],"type":"Point"}
}