{
  "id": 1060943,
  "type": "Feature",
  "properties": {
    "tgn:hierarchy":[
        "tgn:1060943",
        "tgn:1000004",
        "tgn:1003405",
        "tgn:7018214",
        "tgn:7002435",
        "tgn:7029392"
    ],
    "tgn:id":1060943,
    "tgn:name":"Varenovka",
    "tgn:placetype":[
        "aat:300008347"
    ]
},
  "bbox": [],
  "geometry": {"coordinates":[39.0167,47.2833],"type":"Point"}
}