{
  "id": 7232483,
  "type": "Feature",
  "properties": {
    "tgn:hierarchy":[
        "tgn:7232483",
        "tgn:7011167",
        "tgn:7001338",
        "tgn:1000003",
        "tgn:1000074",
        "tgn:7029392"
    ],
    "tgn:id":7232483,
    "tgn:name":"Kak\u00e1ta, \u00c1kra",
    "tgn:placetype":[
        "aat:300008850"
    ]
},
  "bbox": [],
  "geometry": {"coordinates":[20.433333,38.366667],"type":"Point"}
}