{
  "id": 2183621,
  "type": "Feature",
  "properties": {
    "tgn:hierarchy":[
        "tgn:2183621",
        "tgn:1000001",
        "tgn:7012149",
        "tgn:1002800",
        "tgn:7007710",
        "tgn:7029392"
    ],
    "tgn:id":2183621,
    "tgn:name":"Blumenthal Hollow",
    "tgn:placetype":[
        "aat:300008761"
    ]
},
  "bbox": [],
  "geometry": {"coordinates":[-77.6833,41.6333],"type":"Point"}
}