{
  "id": 2354629,
  "type": "Feature",
  "properties": {
    "tgn:hierarchy":[
        "tgn:2354629",
        "tgn:1000001",
        "tgn:7012149",
        "tgn:1002636",
        "tgn:7007708",
        "tgn:7029392"
    ],
    "tgn:id":2354629,
    "tgn:name":"Goober Creek",
    "tgn:placetype":[
        "aat:300008706"
    ]
},
  "bbox": [],
  "geometry": {"coordinates":[-122.55,44.9333],"type":"Point"}
}