<<<<<<< HEAD
{
  "id": 7025131,
  "type": "Feature",
  "properties": {
    "tgn:hierarchy":[
        "tgn:7025131",
        "tgn:7002445",
        "tgn:1000003",
        "tgn:7008118",
        "tgn:7008591",
        "tgn:7029392"
    ],
    "tgn:id":7025131,
    "tgn:name:ang":"Aisseford",
    "tgn:placetype":[
        "aat:300008347"
    ]
},
  "bbox": [],
  "geometry": {"coordinates":[-1.716667,53.216667],"type":"Point"}
}
=======
{"geometry":{"type":"Point","coordinates":[-1.716667,53.216667]},"type":"Feature","properties":{"hierarchy":["tgn:7025131","tgn:7002445","tgn:1000003","tgn:7008118","tgn:7008591","tgn:7029392"],"placetype":["aat:300008347"],"id":7025131,"name:ang":"Aisseford"}}
>>>>>>> 03f74aca74312dbeaf24d7e61306dd6a786dc3d0
