<<<<<<< HEAD
{
  "id": 2405457,
  "type": "Feature",
  "properties": {
    "tgn:hierarchy":[
        "tgn:2405457",
        "tgn:7002659",
        "tgn:1000001",
        "tgn:7012149",
        "tgn:2000029",
        "tgn:7029392"
    ],
    "tgn:id":2405457,
    "tgn:name":"Hughes Branch",
    "tgn:placetype":[
        "aat:300008699"
    ]
},
  "bbox": [],
  "geometry": {"coordinates":[-87.9333,34.4833],"type":"Point"}
}
=======
{"geometry":{"type":"Point","coordinates":[-87.933300,34.483300]},"type":"Feature","properties":{"hierarchy":["tgn:2405457","tgn:7002659","tgn:1000001","tgn:7012149","tgn:2000029","tgn:7029392"],"placetype":["aat:300008699"],"id":2405457,"name:xx":"Hughes Branch"}}
>>>>>>> 03f74aca74312dbeaf24d7e61306dd6a786dc3d0
