{
  "id": 2245514,
  "type": "Feature",
  "properties": {
    "tgn:hierarchy":[
        "tgn:2245514",
        "tgn:1000001",
        "tgn:7012149",
        "tgn:2000981",
        "tgn:7007520",
        "tgn:7029392"
    ],
    "tgn:id":2245514,
    "tgn:name":"Coady Lake",
    "tgn:placetype":[
        "aat:300008680"
    ]
},
  "bbox": [],
  "geometry": {"coordinates":[-85.3667,43.35],"type":"Point"}
}