<<<<<<< HEAD
{
  "id": 2255917,
  "type": "Feature",
  "properties": {
    "tgn:hierarchy":[
        "tgn:2255917",
        "tgn:1000001",
        "tgn:2002134",
        "tgn:7012149",
        "tgn:7007828",
        "tgn:7029392"
    ],
    "tgn:id":2255917,
    "tgn:name":"Copper Flat",
    "tgn:placetype":[
        "aat:300008347"
    ]
},
  "bbox": [],
  "geometry": {"coordinates":[-72.3333,43.8333],"type":"Point"}
}
=======
{"geometry":{"type":"Point","coordinates":[-72.333300,43.833300]},"type":"Feature","properties":{"hierarchy":["tgn:2255917","tgn:1000001","tgn:2002134","tgn:7012149","tgn:7007828","tgn:7029392"],"placetype":["aat:300008347"],"id":2255917,"name:xx":"Copper Flat"}}
>>>>>>> 03f74aca74312dbeaf24d7e61306dd6a786dc3d0
