{
  "id": 2255917,
  "type": "Feature",
  "properties": {
    "tgn:hierarchy":[
        "tgn:2255917",
        "tgn:1000001",
        "tgn:2002134",
        "tgn:7012149",
        "tgn:7007828",
        "tgn:7029392"
    ],
    "tgn:id":2255917,
    "tgn:name":"Copper Flat",
    "tgn:placetype":[
        "aat:300008347"
    ]
},
  "bbox": [],
  "geometry": {"coordinates":[-72.3333,43.8333],"type":"Point"}
}