{
  "id": 2751338,
  "type": "Feature",
  "properties": {
    "tgn:hierarchy":[
        "tgn:2751338",
        "tgn:1000001",
        "tgn:7012149",
        "tgn:2002382",
        "tgn:7007923",
        "tgn:7029392"
    ],
    "tgn:id":2751338,
    "tgn:name":"Warm Spring",
    "tgn:placetype":[
        "aat:300008697"
    ]
},
  "bbox": [],
  "geometry": {"coordinates":[-110.0167,43.2667],"type":"Point"}
}