{
  "id": 7310363,
  "type": "Feature",
  "properties": {
    "tgn:hierarchy":[
        "tgn:7310363",
        "tgn:1001623",
        "tgn:1000049",
        "tgn:1000002",
        "tgn:7029392"
    ],
    "tgn:id":7310363,
    "tgn:name":"Oma, Isla",
    "tgn:placetype":[
        "aat:300008791"
    ]
},
  "bbox": [],
  "geometry": {"coordinates":[-73.666667,-46.05],"type":"Point"}
}