{
  "id": 7090608,
  "type": "Feature",
  "properties": {
    "tgn:hierarchy":[
        "tgn:7090608",
        "tgn:1000003",
        "tgn:7000094",
        "tgn:7000084",
        "tgn:7029392"
    ],
    "tgn:id":7090608,
    "tgn:name":"Vo\u00df-Berg",
    "tgn:placetype":[
        "aat:300008777"
    ]
},
  "bbox": [],
  "geometry": {"coordinates":[12.016667,54.016667],"type":"Point"}
}