{
  "id": 2214943,
  "type": "Feature",
  "properties": {
    "tgn:hierarchy":[
        "tgn:2214943",
        "tgn:1000001",
        "tgn:7012149",
        "tgn:2001716",
        "tgn:7007708",
        "tgn:7029392"
    ],
    "tgn:id":2214943,
    "tgn:name":"Calico Creek",
    "tgn:placetype":[
        "aat:300008706"
    ]
},
  "bbox": [],
  "geometry": {"coordinates":[-123.1333,43.7833],"type":"Point"}
}