{
  "id": 2188381,
  "type": "Feature",
  "properties": {
    "tgn:hierarchy":[
        "tgn:2188381",
        "tgn:1000001",
        "tgn:7012149",
        "tgn:2000476",
        "tgn:7007250",
        "tgn:7029392"
    ],
    "tgn:id":2188381,
    "tgn:name":"Boston Mountain",
    "tgn:placetype":[
        "aat:300008798"
    ]
},
  "bbox": [],
  "geometry": {"coordinates":[-115.1833,45.6333],"type":"Point"}
}