{
  "id": 2752452,
  "type": "Feature",
  "properties": {
    "tgn:hierarchy":[
        "tgn:2752452",
        "tgn:1000001",
        "tgn:7012149",
        "tgn:2002354",
        "tgn:7007922",
        "tgn:7029392"
    ],
    "tgn:id":2752452,
    "tgn:name":"Washington Lake",
    "tgn:placetype":[
        "aat:300008680"
    ]
},
  "bbox": [],
  "geometry": {"coordinates":[-88.4833,44.8167],"type":"Point"}
}