<<<<<<< HEAD
{
  "id": 2255644,
  "type": "Feature",
  "properties": {
    "tgn:hierarchy":[
        "tgn:2255644",
        "tgn:1000001",
        "tgn:7012149",
        "tgn:7014318",
        "tgn:7007568",
        "tgn:7029392"
    ],
    "tgn:id":2255644,
    "tgn:name":"Copes Corner",
    "tgn:placetype":[
        "aat:300008347"
    ]
},
  "bbox": [],
  "geometry": {"coordinates":[-75.3333,42.4333],"type":"Point"}
}
=======
{"geometry":{"type":"Point","coordinates":[-75.333300,42.433300]},"type":"Feature","properties":{"hierarchy":["tgn:2255644","tgn:1000001","tgn:7012149","tgn:7014318","tgn:7007568","tgn:7029392"],"placetype":["aat:300008347"],"id":2255644,"name:xx":"Copes Corner"}}
>>>>>>> 03f74aca74312dbeaf24d7e61306dd6a786dc3d0
