{
  "id": 2372947,
  "type": "Feature",
  "properties": {
    "tgn:hierarchy":[
        "tgn:2372947",
        "tgn:2000105",
        "tgn:1000001",
        "tgn:7016172",
        "tgn:7012149",
        "tgn:7029392"
    ],
    "tgn:id":2372947,
    "tgn:name":"Halliburton Branch",
    "tgn:placetype":[
        "aat:300008699"
    ]
},
  "bbox": [],
  "geometry": {"coordinates":[-91.25,34.2333],"type":"Point"}
}