{
  "id": 2221288,
  "type": "Feature",
  "properties": {
    "tgn:hierarchy":[
        "tgn:2221288",
        "tgn:1000001",
        "tgn:7012149",
        "tgn:2002377",
        "tgn:7007923",
        "tgn:7029392"
    ],
    "tgn:id":2221288,
    "tgn:name":"Cardine-Keith Reservoir",
    "tgn:placetype":[
        "aat:300006191"
    ]
},
  "bbox": [],
  "geometry": {"coordinates":[-106.1167,42.6833],"type":"Point"}
}