{
  "id": 7152052,
  "type": "Feature",
  "properties": {
    "tgn:hierarchy":[
        "tgn:7152052",
        "tgn:7003669",
        "tgn:1000003",
        "tgn:7000084",
        "tgn:7029392"
    ],
    "tgn:id":7152052,
    "tgn:name":"Kammerforst",
    "tgn:placetype":[
        "aat:300008863"
    ]
},
  "bbox": [],
  "geometry": {"coordinates":[10.683333,49.766667],"type":"Point"}
}