<<<<<<< HEAD
{
  "id": 7054908,
  "type": "Feature",
  "properties": {
    "tgn:hierarchy":[
        "tgn:7054908",
        "tgn:1000003",
        "tgn:7003122",
        "tgn:1000080",
        "tgn:7029392"
    ],
    "tgn:id":7054908,
    "tgn:name":"Molini, Torrente dei",
    "tgn:placetype":[
        "aat:300008699"
    ]
},
  "bbox": [],
  "geometry": {"coordinates":[14.133333,37.916667],"type":"Point"}
}
=======
{"geometry":{"type":"Point","coordinates":[14.133333,37.916667]},"type":"Feature","properties":{"hierarchy":["tgn:7054908","tgn:1000003","tgn:7003122","tgn:1000080","tgn:7029392"],"placetype":["aat:300008699"],"id":7054908,"name:xx":"Molini, Torrente dei"}}
>>>>>>> 03f74aca74312dbeaf24d7e61306dd6a786dc3d0
