{
  "id": 2435263,
  "type": "Feature",
  "properties": {
    "tgn:hierarchy":[
        "tgn:2435263",
        "tgn:1007657",
        "tgn:1002534",
        "tgn:1000001",
        "tgn:7012149",
        "tgn:7007249",
        "tgn:7029392"
    ],
    "tgn:id":2435263,
    "tgn:name":"Keopaweo",
    "tgn:placetype":[
        "aat:300008798"
    ]
},
  "bbox": [],
  "geometry": {"coordinates":[-159.35,21.9333],"type":"Point"}
}