<<<<<<< HEAD
{
  "id": 7178962,
  "type": "Feature",
  "properties": {
    "tgn:hierarchy":[
        "tgn:7178962",
        "tgn:1000003",
        "tgn:7003689",
        "tgn:7000084",
        "tgn:7029392"
    ],
    "tgn:id":7178962,
    "tgn:name":"Haidekoppe",
    "tgn:placetype":[
        "aat:300008777"
    ]
},
  "bbox": [],
  "geometry": {"coordinates":[11.533333,50.45],"type":"Point"}
}
=======
{"geometry":{"type":"Point","coordinates":[11.533333,50.450000]},"type":"Feature","properties":{"hierarchy":["tgn:7178962","tgn:1000003","tgn:7003689","tgn:7000084","tgn:7029392"],"placetype":["aat:300008777"],"id":7178962,"name:xx":"Haidekoppe"}}
>>>>>>> 03f74aca74312dbeaf24d7e61306dd6a786dc3d0
