{
  "id": 7222590,
  "type": "Feature",
  "properties": {
    "tgn:hierarchy":[
        "tgn:7222590",
        "tgn:7011170",
        "tgn:7002715",
        "tgn:1000003",
        "tgn:1000074",
        "tgn:7029392"
    ],
    "tgn:id":7222590,
    "tgn:name":"Sikorr\u00e1khi",
    "tgn:placetype":[
        "aat:300008347"
    ]
},
  "bbox": [],
  "geometry": {"coordinates":[25.716667,40.966667],"type":"Point"}
}