{
  "id": 2211462,
  "type": "Feature",
  "properties": {
    "tgn:hierarchy":[
        "tgn:2211462",
        "tgn:1000001",
        "tgn:7012149",
        "tgn:7014589",
        "tgn:7007515",
        "tgn:7029392"
    ],
    "tgn:id":2211462,
    "tgn:name":"Butterfield Cove",
    "tgn:placetype":[
        "aat:300132316"
    ]
},
  "bbox": [],
  "geometry": {"coordinates":[-67.7833,45.5167],"type":"Point"}
}