{
  "id": 1088462,
  "type": "Feature",
  "properties": {
    "tgn:hierarchy":[
        "tgn:1088462",
        "tgn:7001242",
        "tgn:1000968",
        "tgn:1000156",
        "tgn:7029392"
    ],
    "tgn:id":1088462,
    "tgn:name":"Aozou",
    "tgn:placetype":[
        "aat:300008347"
    ]
},
  "bbox": [],
  "geometry": {"coordinates":[17.4667,21.75],"type":"Point"}
}