{
  "id": 7140953,
  "type": "Feature",
  "properties": {
    "tgn:hierarchy":[
        "tgn:7140953",
        "tgn:1000003",
        "tgn:7003688",
        "tgn:7000084",
        "tgn:7029392"
    ],
    "tgn:id":7140953,
    "tgn:name":"Lorenzensplate",
    "tgn:placetype":[
        "aat:300386970"
    ]
},
  "bbox": [],
  "geometry": {"coordinates":[8.633333,54.416667],"type":"Point"}
}