<<<<<<< HEAD
{
  "id": 2254205,
  "type": "Feature",
  "properties": {
    "tgn:hierarchy":[
        "tgn:2254205",
        "tgn:1000001",
        "tgn:7012149",
        "tgn:2000931",
        "tgn:7007515",
        "tgn:7029392"
    ],
    "tgn:id":2254205,
    "tgn:name":"Coombs Point",
    "tgn:placetype":[
        "aat:300008850"
    ]
},
  "bbox": [],
  "geometry": {"coordinates":[-68.85,44.35],"type":"Point"}
}
=======
{"geometry":{"type":"Point","coordinates":[-68.850000,44.350000]},"type":"Feature","properties":{"hierarchy":["tgn:2254205","tgn:1000001","tgn:7012149","tgn:2000931","tgn:7007515","tgn:7029392"],"placetype":["aat:300008850"],"id":2254205,"name:xx":"Coombs Point"}}
>>>>>>> 03f74aca74312dbeaf24d7e61306dd6a786dc3d0
