{
  "id": 2733881,
  "type": "Feature",
  "properties": {
    "tgn:hierarchy":[
        "tgn:2733881",
        "tgn:1000001",
        "tgn:7012149",
        "tgn:2000362",
        "tgn:7007248",
        "tgn:7029392"
    ],
    "tgn:id":2733881,
    "tgn:name":"Turner Lake",
    "tgn:placetype":[
        "aat:300006191"
    ]
},
  "bbox": [],
  "geometry": {"coordinates":[-85.1167,33.6833],"type":"Point"}
}