{
  "id": 7414194,
  "type": "Feature",
  "properties": {
    "tgn:hierarchy":[
        "tgn:7414194",
        "tgn:7005580",
        "tgn:1000001",
        "tgn:7005560",
        "tgn:7029392"
    ],
    "tgn:id":7414194,
    "tgn:name":"La Sombra",
    "tgn:placetype":[
        "aat:300008347"
    ]
},
  "bbox": [],
  "geometry": {"coordinates":[-93.85,16.85],"type":"Point"}
}