{
  "id": 2666830,
  "type": "Feature",
  "properties": {
    "tgn:hierarchy":[
        "tgn:2666830",
        "tgn:1000001",
        "tgn:7012149",
        "tgn:1003020",
        "tgn:7007920",
        "tgn:7029392"
    ],
    "tgn:id":2666830,
    "tgn:name":"Skagit Range",
    "tgn:placetype":[
        "aat:300386831"
    ]
},
  "bbox": [],
  "geometry": {"coordinates":[-121.55,48.9167],"type":"Point"}
}