{
  "id": 7591688,
  "type": "Feature",
  "properties": {
    "tgn:hierarchy":[
        "tgn:7591688",
        "tgn:1000004",
        "tgn:7000198",
        "tgn:7031786",
        "tgn:7029392"
    ],
    "tgn:id":7591688,
    "tgn:name:en":"B\u0101nsw\u0101li Rao",
    "tgn:placetype":[
        "aat:300008699"
    ]
},
  "bbox": [],
  "geometry": {"coordinates":[77.773439,30.39204],"type":"Point"}
}