{
  "id": 2108600,
  "type": "Feature",
  "properties": {
    "tgn:hierarchy":[
        "tgn:2108600",
        "tgn:1000001",
        "tgn:7012149",
        "tgn:1002478",
        "tgn:7007826",
        "tgn:7029392"
    ],
    "tgn:id":2108600,
    "tgn:name":"Woodbury",
    "tgn:placetype":[
        "aat:300008347"
    ]
},
  "bbox": [],
  "geometry": {"coordinates":[-97.2167,32.0333],"type":"Point"}
}