{
  "id": 2515288,
  "type": "Feature",
  "properties": {
    "tgn:hierarchy":[
        "tgn:2515288",
        "tgn:1000001",
        "tgn:7012149",
        "tgn:2000277",
        "tgn:7007240",
        "tgn:7029392"
    ],
    "tgn:id":2515288,
    "tgn:name":"Milligan Pond",
    "tgn:placetype":[
        "aat:300008680"
    ]
},
  "bbox": [],
  "geometry": {"coordinates":[-82.55,29.5167],"type":"Point"}
}