{
  "id": 2291980,
  "type": "Feature",
  "properties": {
    "tgn:hierarchy":[
        "tgn:2291980",
        "tgn:1000001",
        "tgn:7012149",
        "tgn:2001712",
        "tgn:7007708",
        "tgn:7029392"
    ],
    "tgn:id":2291980,
    "tgn:name":"Domogalla Canyon",
    "tgn:placetype":[
        "aat:300008761"
    ]
},
  "bbox": [],
  "geometry": {"coordinates":[-120.45,44.7333],"type":"Point"}
}