{
  "id": 2464720,
  "type": "Feature",
  "properties": {
    "tgn:hierarchy":[
        "tgn:2464720",
        "tgn:1000001",
        "tgn:7012149",
        "tgn:7007157",
        "tgn:1002710",
        "tgn:7029392"
    ],
    "tgn:id":2464720,
    "tgn:name":"Logan Canyon",
    "tgn:placetype":[
        "aat:300008761"
    ]
},
  "bbox": [],
  "geometry": {"coordinates":[-120.8333,39.3833],"type":"Point"}
}