<<<<<<< HEAD
{
  "id": 2768344,
  "type": "Feature",
  "properties": {
    "tgn:hierarchy":[
        "tgn:2768344",
        "tgn:1000001",
        "tgn:7012149",
        "tgn:2000238",
        "tgn:7007158",
        "tgn:7029392"
    ],
    "tgn:id":2768344,
    "tgn:name":"Whiteside Gulch",
    "tgn:placetype":[
        "aat:300008761"
    ]
},
  "bbox": [],
  "geometry": {"coordinates":[-105.7,39.4667],"type":"Point"}
}
=======
{"geometry":{"type":"Point","coordinates":[-105.700000,39.466700]},"type":"Feature","properties":{"hierarchy":["tgn:2768344","tgn:1000001","tgn:7012149","tgn:2000238","tgn:7007158","tgn:7029392"],"placetype":["aat:300008761"],"id":2768344,"name:xx":"Whiteside Gulch"}}
>>>>>>> 03f74aca74312dbeaf24d7e61306dd6a786dc3d0
