{
  "id": 7402770,
  "type": "Feature",
  "properties": {
    "tgn:hierarchy":[
        "tgn:7402770",
        "tgn:1000001",
        "tgn:1001937",
        "tgn:7005560",
        "tgn:7029392"
    ],
    "tgn:id":7402770,
    "tgn:name":"San Isidro",
    "tgn:placetype":[
        "aat:300008347"
    ]
},
  "bbox": [],
  "geometry": {"coordinates":[-86.875,20.904167],"type":"Point"}
}