{
  "id": 7417068,
  "type": "Feature",
  "properties": {
    "tgn:hierarchy":[
        "tgn:7417068",
        "tgn:1000001",
        "tgn:7005591",
        "tgn:7005560",
        "tgn:7029392"
    ],
    "tgn:id":7417068,
    "tgn:name:es":"Celestina Gasca",
    "tgn:placetype":[
        "aat:300008347"
    ]
},
  "bbox": [],
  "geometry": {"coordinates":[-95.952778,18.031111],"type":"Point"}
}