{
  "id": 7576191,
  "type": "Feature",
  "properties": {
    "tgn:hierarchy":[
        "tgn:7576191",
        "tgn:1000004",
        "tgn:7000198",
        "tgn:7016722",
        "tgn:7029392"
    ],
    "tgn:id":7576191,
    "tgn:name:en":"L\u0101lpura",
    "tgn:placetype":[
        "aat:300008347"
    ]
},
  "bbox": [],
  "geometry": {"coordinates":[80.043909,25.863412],"type":"Point"}
}