{
  "id": 7509098,
  "type": "Feature",
  "properties": {
    "tgn:hierarchy":[
        "tgn:7509098",
        "tgn:1009227",
        "tgn:1000226",
        "tgn:7018437",
        "tgn:1000006",
        "tgn:7029392"
    ],
    "tgn:id":7509098,
    "tgn:name:en":"Taieri Beach",
    "tgn:placetype":[
        "aat:300008347"
    ]
},
  "bbox": [],
  "geometry": {"coordinates":[170.183333,-46.083333],"type":"Point"}
}