{
  "id": 7162277,
  "type": "Feature",
  "properties": {
    "tgn:hierarchy":[
        "tgn:7162277",
        "tgn:1000003",
        "tgn:7003677",
        "tgn:7000084",
        "tgn:7029392"
    ],
    "tgn:id":7162277,
    "tgn:name":"Hum-Berg",
    "tgn:placetype":[
        "aat:300008777"
    ]
},
  "bbox": [],
  "geometry": {"coordinates":[7.95,51.383333],"type":"Point"}
}