{
  "id": 2504347,
  "type": "Feature",
  "properties": {
    "tgn:hierarchy":[
        "tgn:2504347",
        "tgn:2000456",
        "tgn:1000001",
        "tgn:7012149",
        "tgn:7007250",
        "tgn:7029392"
    ],
    "tgn:id":2504347,
    "tgn:name":"Meadowhurst",
    "tgn:placetype":[
        "aat:300008347"
    ]
},
  "bbox": [],
  "geometry": {"coordinates":[-116.55,47.3167],"type":"Point"}
}