<<<<<<< HEAD
{
  "id": 7363198,
  "type": "Feature",
  "properties": {
    "tgn:hierarchy":[
        "tgn:7363198",
        "tgn:1000001",
        "tgn:7005590",
        "tgn:7005560",
        "tgn:7029392"
    ],
    "tgn:id":7363198,
    "tgn:name":"El Cerezo",
    "tgn:placetype":[
        "aat:300000241"
    ]
},
  "bbox": [],
  "geometry": {"coordinates":[-101.966667,19.766667],"type":"Point"}
}
=======
{"geometry":{"type":"Point","coordinates":[-101.966667,19.766667]},"type":"Feature","properties":{"hierarchy":["tgn:7363198","tgn:1000001","tgn:7005590","tgn:7005560","tgn:7029392"],"placetype":["aat:300000241"],"id":7363198,"name:xx":"El Cerezo"}}
>>>>>>> 03f74aca74312dbeaf24d7e61306dd6a786dc3d0
