<<<<<<< HEAD
{
  "id": 2404524,
  "type": "Feature",
  "properties": {
    "tgn:hierarchy":[
        "tgn:2404524",
        "tgn:1000001",
        "tgn:7013942",
        "tgn:7012149",
        "tgn:7007517",
        "tgn:7029392"
    ],
    "tgn:id":2404524,
    "tgn:name":"Hubbards Pond",
    "tgn:placetype":[
        "aat:300006191"
    ]
},
  "bbox": [],
  "geometry": {"coordinates":[-72.3167,42.6333],"type":"Point"}
}
=======
{"geometry":{"type":"Point","coordinates":[-72.316700,42.633300]},"type":"Feature","properties":{"hierarchy":["tgn:2404524","tgn:1000001","tgn:7013942","tgn:7012149","tgn:7007517","tgn:7029392"],"placetype":["aat:300006191"],"id":2404524,"name:xx":"Hubbards Pond"}}
>>>>>>> 03f74aca74312dbeaf24d7e61306dd6a786dc3d0
