{
  "id": 2191472,
  "type": "Feature",
  "properties": {
    "tgn:hierarchy":[
        "tgn:2191472",
        "tgn:1000001",
        "tgn:7012149",
        "tgn:2001843",
        "tgn:7007825",
        "tgn:7029392"
    ],
    "tgn:id":2191472,
    "tgn:name":"Braden Mountain",
    "tgn:placetype":[
        "aat:300008798"
    ]
},
  "bbox": [],
  "geometry": {"coordinates":[-84.3333,36.4167],"type":"Point"}
}