{
  "id": 2631728,
  "type": "Feature",
  "properties": {
    "tgn:hierarchy":[
        "tgn:2631728",
        "tgn:1000001",
        "tgn:7012149",
        "tgn:2002268",
        "tgn:7013961",
        "tgn:7029392"
    ],
    "tgn:id":2631728,
    "tgn:name":"Roundknob",
    "tgn:placetype":[
        "aat:300008798"
    ]
},
  "bbox": [],
  "geometry": {"coordinates":[-81.7833,38.7667],"type":"Point"}
}