{
  "id": 7519100,
  "type": "Feature",
  "properties": {
    "tgn:hierarchy":[
        "tgn:7519100",
        "tgn:1009227",
        "tgn:1000226",
        "tgn:7520095",
        "tgn:1000006",
        "tgn:7029392"
    ],
    "tgn:id":7519100,
    "tgn:name:en":"Appleby",
    "tgn:placetype":[
        "aat:300007783"
    ]
},
  "bbox": [],
  "geometry": {"coordinates":[173.166667,-41.35],"type":"Point"}
}