{
  "id": 7583345,
  "type": "Feature",
  "properties": {
    "tgn:hierarchy":[
        "tgn:7583345",
        "tgn:1000004",
        "tgn:7000198",
        "tgn:7016883",
        "tgn:7029392"
    ],
    "tgn:id":7583345,
    "tgn:name:en":"Salaudi",
    "tgn:placetype":[
        "aat:300008347"
    ]
},
  "bbox": [],
  "geometry": {"coordinates":[76.219015,30.750809],"type":"Point"}
}