<<<<<<< HEAD
{
  "id": 7350644,
  "type": "Feature",
  "properties": {
    "tgn:hierarchy":[
        "tgn:7350644",
        "tgn:1000001",
        "tgn:7005597",
        "tgn:7005560",
        "tgn:7029392"
    ],
    "tgn:id":7350644,
    "tgn:name":"Caballos, Arroyo",
    "tgn:placetype":[
        "aat:300008699"
    ]
},
  "bbox": [],
  "geometry": {"coordinates":[-98.216667,24.883333],"type":"Point"}
}
=======
{"geometry":{"type":"Point","coordinates":[-98.216667,24.883333]},"type":"Feature","properties":{"hierarchy":["tgn:7350644","tgn:1000001","tgn:7005597","tgn:7005560","tgn:7029392"],"placetype":["aat:300008699"],"id":7350644,"name:xx":"Caballos, Arroyo"}}
>>>>>>> 03f74aca74312dbeaf24d7e61306dd6a786dc3d0
