{
  "id": 7517621,
  "type": "Feature",
  "properties": {
    "tgn:hierarchy":[
        "tgn:7517621",
        "tgn:1009227",
        "tgn:7001866",
        "tgn:1000226",
        "tgn:1000006",
        "tgn:7029392"
    ],
    "tgn:id":7517621,
    "tgn:name:en":"Makikihi River",
    "tgn:placetype":[
        "aat:300008699"
    ]
},
  "bbox": [],
  "geometry": {"coordinates":[171.15,-44.633333],"type":"Point"}
}