{
  "id": 7522611,
  "type": "Feature",
  "properties": {
    "tgn:hierarchy":[
        "tgn:7522611",
        "tgn:7001242",
        "tgn:7016833",
        "tgn:7029392"
    ],
    "tgn:id":7522611,
    "tgn:name":"Ar R\u016bways\u0101t",
    "tgn:placetype":[
        "aat:300008777"
    ]
},
  "bbox": [],
  "geometry": {"coordinates":[31.582252,29.941222],"type":"Point"}
}