{
  "id": 7277338,
  "type": "Feature",
  "properties": {
    "tgn:hierarchy":[
        "tgn:7277338",
        "tgn:1001702",
        "tgn:1000049",
        "tgn:1000002",
        "tgn:7029392"
    ],
    "tgn:id":7277338,
    "tgn:name":"Mackinlay, Punta",
    "tgn:placetype":[
        "aat:300386846"
    ]
},
  "bbox": [],
  "geometry": {"coordinates":[-68.425,-54.916667],"type":"Point"}
}