{
  "id": 2687234,
  "type": "Feature",
  "properties": {
    "tgn:hierarchy":[
        "tgn:2687234",
        "tgn:1000001",
        "tgn:1002317",
        "tgn:7012149",
        "tgn:7007706",
        "tgn:7029392"
    ],
    "tgn:id":2687234,
    "tgn:name":"Spring Knoll Lakes",
    "tgn:placetype":[
        "aat:300008680"
    ]
},
  "bbox": [],
  "geometry": {"coordinates":[-84.7333,40.0167],"type":"Point"}
}