{
  "id": 2332103,
  "type": "Feature",
  "properties": {
    "tgn:hierarchy":[
        "tgn:2332103",
        "tgn:1000001",
        "tgn:7012149",
        "tgn:7014589",
        "tgn:7007515",
        "tgn:7029392"
    ],
    "tgn:id":2332103,
    "tgn:name":"Flint Island",
    "tgn:placetype":[
        "aat:300008791"
    ]
},
  "bbox": [],
  "geometry": {"coordinates":[-67.7833,44.4667],"type":"Point"}
}