{
  "id": 7512547,
  "type": "Feature",
  "properties": {
    "tgn:hierarchy":[
        "tgn:7512547",
        "tgn:1009227",
        "tgn:1000226",
        "tgn:7018437",
        "tgn:1000006",
        "tgn:7029392"
    ],
    "tgn:id":7512547,
    "tgn:name:en":"Hope Blue River Range",
    "tgn:placetype":[
        "aat:300008795"
    ]
},
  "bbox": [],
  "geometry": {"coordinates":[168.466667,-44.15],"type":"Point"}
}