{
  "id": 2557209,
  "type": "Feature",
  "properties": {
    "tgn:hierarchy":[
        "tgn:2557209",
        "tgn:1000001",
        "tgn:7012149",
        "tgn:2001233",
        "tgn:7007523",
        "tgn:7029392"
    ],
    "tgn:id":2557209,
    "tgn:name":"Old Indian Lead Mine",
    "tgn:placetype":[
        "aat:300000390"
    ]
},
  "bbox": [],
  "geometry": {"coordinates":[-92.15,37.75],"type":"Point"}
}