<<<<<<< HEAD
{
  "id": 2254513,
  "type": "Feature",
  "properties": {
    "tgn:hierarchy":[
        "tgn:2254513",
        "tgn:1000001",
        "tgn:7012149",
        "tgn:7007826",
        "tgn:7029392"
    ],
    "tgn:id":2254513,
    "tgn:name":"Coon Dive Draw",
    "tgn:placetype":[
        "aat:300008761"
    ]
},
  "bbox": [],
  "geometry": {"coordinates":[-101.05,31.55],"type":"Point"}
}
=======
{"geometry":{"type":"Point","coordinates":[-101.050000,31.550000]},"type":"Feature","properties":{"hierarchy":["tgn:2254513","tgn:1000001","tgn:7012149","tgn:7007826","tgn:7029392"],"placetype":["aat:300008761"],"id":2254513,"name:xx":"Coon Dive Draw"}}
>>>>>>> 03f74aca74312dbeaf24d7e61306dd6a786dc3d0
