{
  "id": 7031308,
  "type": "Feature",
  "properties": {
    "tgn:hierarchy":[
        "tgn:7031308",
        "tgn:7002445",
        "tgn:1000003",
        "tgn:7008168",
        "tgn:7008591",
        "tgn:7029392"
    ],
    "tgn:id":7031308,
    "tgn:name":"Horspath",
    "tgn:placetype":[
        "aat:300008347",
        "aat:300008372"
    ]
},
  "bbox": [],
  "geometry": {"coordinates":[-1.169,51.733],"type":"Point"}
}