{
  "id": 2618270,
  "type": "Feature",
  "properties": {
    "tgn:hierarchy":[
        "tgn:2618270",
        "tgn:1000001",
        "tgn:7012149",
        "tgn:2000818",
        "tgn:7007255",
        "tgn:7029392"
    ],
    "tgn:id":2618270,
    "tgn:name":"Riggs Branch",
    "tgn:placetype":[
        "aat:300008699"
    ]
},
  "bbox": [],
  "geometry": {"coordinates":[-84.3167,36.65],"type":"Point"}
}