{
  "id": 7366507,
  "type": "Feature",
  "properties": {
    "tgn:hierarchy":[
        "tgn:7366507",
        "tgn:7005579",
        "tgn:1000001",
        "tgn:7005560",
        "tgn:7029392"
    ],
    "tgn:id":7366507,
    "tgn:name":"El Pino",
    "tgn:placetype":[
        "aat:300008347"
    ]
},
  "bbox": [],
  "geometry": {"coordinates":[-102.416667,22.016667],"type":"Point"}
}