<<<<<<< HEAD
{
  "id": 2250799,
  "type": "Feature",
  "properties": {
    "tgn:hierarchy":[
        "tgn:2250799",
        "tgn:1000001",
        "tgn:7012149",
        "tgn:7016021",
        "tgn:7007568",
        "tgn:7029392"
    ],
    "tgn:id":2250799,
    "tgn:name":"Colton Hill",
    "tgn:placetype":[
        "aat:300008798"
    ]
},
  "bbox": [],
  "geometry": {"coordinates":[-75.0833,44.2],"type":"Point"}
}
=======
{"geometry":{"type":"Point","coordinates":[-75.083300,44.200000]},"type":"Feature","properties":{"hierarchy":["tgn:2250799","tgn:1000001","tgn:7012149","tgn:7016021","tgn:7007568","tgn:7029392"],"placetype":["aat:300008798"],"id":2250799,"name:xx":"Colton Hill"}}
>>>>>>> 03f74aca74312dbeaf24d7e61306dd6a786dc3d0
