<<<<<<< HEAD
{
  "id": 2151324,
  "type": "Feature",
  "properties": {
    "tgn:hierarchy":[
        "tgn:2151324",
        "tgn:1000001",
        "tgn:1003028",
        "tgn:7012149",
        "tgn:7007159",
        "tgn:7029392"
    ],
    "tgn:id":2151324,
    "tgn:name":"Bates Hill",
    "tgn:placetype":[
        "aat:300008798"
    ]
},
  "bbox": [],
  "geometry": {"coordinates":[-71.8833,41.9167],"type":"Point"}
}
=======
{"geometry":{"type":"Point","coordinates":[-71.883300,41.916700]},"type":"Feature","properties":{"hierarchy":["tgn:2151324","tgn:1000001","tgn:1003028","tgn:7012149","tgn:7007159","tgn:7029392"],"placetype":["aat:300008798"],"id":2151324,"name:xx":"Bates Hill"}}
>>>>>>> 03f74aca74312dbeaf24d7e61306dd6a786dc3d0
