{
  "id": 2564327,
  "type": "Feature",
  "properties": {
    "tgn:hierarchy":[
        "tgn:2564327",
        "tgn:1000001",
        "tgn:7012149",
        "tgn:7015666",
        "tgn:7007825",
        "tgn:7029392"
    ],
    "tgn:id":2564327,
    "tgn:name":"Paces Island",
    "tgn:placetype":[
        "aat:300008791"
    ]
},
  "bbox": [],
  "geometry": {"coordinates":[-87.4833,35.75],"type":"Point"}
}