{
  "id": 2761325,
  "type": "Feature",
  "properties": {
    "tgn:hierarchy":[
        "tgn:2761325",
        "tgn:7006450",
        "tgn:1000001",
        "tgn:7012149",
        "tgn:2000089",
        "tgn:7029392"
    ],
    "tgn:id":2761325,
    "tgn:name":"West Middle River",
    "tgn:placetype":[
        "aat:300008707"
    ]
},
  "bbox": [],
  "geometry": {"coordinates":[-149.2833,64.4833],"type":"Point"}
}