{
  "id": 2495878,
  "type": "Feature",
  "properties": {
    "tgn:hierarchy":[
        "tgn:2495878",
        "tgn:1000001",
        "tgn:7012149",
        "tgn:7007922",
        "tgn:7029392"
    ],
    "tgn:id":2495878,
    "tgn:name":"Mason Lake",
    "tgn:placetype":[
        "aat:300006191"
    ]
},
  "bbox": [],
  "geometry": {"coordinates":[-89.5833,43.65],"type":"Point"}
}