<<<<<<< HEAD
{
  "id": 2331059,
  "type": "Feature",
  "properties": {
    "tgn:hierarchy":[
        "tgn:2331059",
        "tgn:2000106",
        "tgn:1000001",
        "tgn:7016172",
        "tgn:7012149",
        "tgn:7029392"
    ],
    "tgn:id":2331059,
    "tgn:name":"Flat Slough",
    "tgn:placetype":[
        "aat:300008905"
    ]
},
  "bbox": [],
  "geometry": {"coordinates":[-91.65,33.0667],"type":"Point"}
}
=======
{"geometry":{"type":"Point","coordinates":[-91.650000,33.066700]},"type":"Feature","properties":{"hierarchy":["tgn:2331059","tgn:2000106","tgn:1000001","tgn:7016172","tgn:7012149","tgn:7029392"],"placetype":["aat:300008905"],"id":2331059,"name:xx":"Flat Slough"}}
>>>>>>> 03f74aca74312dbeaf24d7e61306dd6a786dc3d0
