{
  "id": 2425420,
  "type": "Feature",
  "properties": {
    "tgn:hierarchy":[
        "tgn:2425420",
        "tgn:1000001",
        "tgn:7019013",
        "tgn:7012149",
        "tgn:7007251",
        "tgn:7029392"
    ],
    "tgn:id":2425420,
    "tgn:name":"Johnson Slough",
    "tgn:placetype":[
        "aat:300008680"
    ]
},
  "bbox": [],
  "geometry": {"coordinates":[-87.9333,41.7833],"type":"Point"}
}