<<<<<<< HEAD
{
  "id": 2769220,
  "type": "Feature",
  "properties": {
    "tgn:hierarchy":[
        "tgn:2769220",
        "tgn:1000001",
        "tgn:7012149",
        "tgn:1002557",
        "tgn:7007252",
        "tgn:7029392"
    ],
    "tgn:id":2769220,
    "tgn:name":"Whyland Lake",
    "tgn:placetype":[
        "aat:300008680"
    ]
},
  "bbox": [],
  "geometry": {"coordinates":[-85.7667,41.1833],"type":"Point"}
}
=======
{"geometry":{"type":"Point","coordinates":[-85.766700,41.183300]},"type":"Feature","properties":{"hierarchy":["tgn:2769220","tgn:1000001","tgn:7012149","tgn:1002557","tgn:7007252","tgn:7029392"],"placetype":["aat:300008680"],"id":2769220,"name:xx":"Whyland Lake"}}
>>>>>>> 03f74aca74312dbeaf24d7e61306dd6a786dc3d0
