{
  "id": 7310344,
  "type": "Feature",
  "properties": {
    "tgn:hierarchy":[
        "tgn:7310344",
        "tgn:1001699",
        "tgn:1000049",
        "tgn:1000002",
        "tgn:7029392"
    ],
    "tgn:id":7310344,
    "tgn:name":"Oppisso, Isla",
    "tgn:placetype":[
        "aat:300008791"
    ]
},
  "bbox": [],
  "geometry": {"coordinates":[-73.623333,-44.539444],"type":"Point"}
}