{
  "id": 2115586,
  "type": "Feature",
  "properties": {
    "tgn:hierarchy":[
        "tgn:2115586",
        "tgn:1000001",
        "tgn:7012149",
        "tgn:7018871",
        "tgn:7007920",
        "tgn:7029392"
    ],
    "tgn:id":2115586,
    "tgn:name":"Cumberland",
    "tgn:placetype":[
        "aat:300008347"
    ]
},
  "bbox": [],
  "geometry": {"coordinates":[-121.9167,47.2667],"type":"Point"}
}