{
  "id": 2000593,
  "type": "Feature",
  "properties": {
    "tgn:hierarchy":[
        "tgn:2000593",
        "tgn:1000001",
        "tgn:7012149",
        "tgn:7007253",
        "tgn:7029392"
    ],
    "tgn:id":2000593,
    "tgn:name":"Fayette",
    "tgn:placetype":[
        "aat:300387145",
        "aat:300000771"
    ]
},
  "bbox": [],
  "geometry": {"coordinates":[-91.85,42.8667],"type":"Point"}
}