{
  "id": 7186426,
  "type": "Feature",
  "properties": {
    "tgn:hierarchy":[
        "tgn:7186426",
        "tgn:7003669",
        "tgn:1000003",
        "tgn:7000084",
        "tgn:7029392"
    ],
    "tgn:id":7186426,
    "tgn:name":"Gradelh\u00f6he",
    "tgn:placetype":[
        "aat:300008795"
    ]
},
  "bbox": [],
  "geometry": {"coordinates":[12.583333,49.533333],"type":"Point"}
}