{
  "id": 2279987,
  "type": "Feature",
  "properties": {
    "tgn:hierarchy":[
        "tgn:2279987",
        "tgn:1000001",
        "tgn:7012149",
        "tgn:2001711",
        "tgn:7007708",
        "tgn:7029392"
    ],
    "tgn:id":2279987,
    "tgn:name":"Dean Reservoir",
    "tgn:placetype":[
        "aat:300006191"
    ]
},
  "bbox": [],
  "geometry": {"coordinates":[-122.95,42.3833],"type":"Point"}
}