{
  "id": 7340354,
  "type": "Feature",
  "properties": {
    "tgn:hierarchy":[
        "tgn:7340354",
        "tgn:7002829",
        "tgn:1000003",
        "tgn:7002786",
        "tgn:1000095",
        "tgn:7029392"
    ],
    "tgn:id":7340354,
    "tgn:name":"Edramo, Sierra do",
    "tgn:placetype":[
        "aat:300266640"
    ]
},
  "bbox": [],
  "geometry": {"coordinates":[-7.333333,42.716667],"type":"Point"}
}