{
  "id": 2716102,
  "type": "Feature",
  "properties": {
    "tgn:hierarchy":[
        "tgn:2716102",
        "tgn:1000001",
        "tgn:7012149",
        "tgn:2000420",
        "tgn:7007248",
        "tgn:7029392"
    ],
    "tgn:id":2716102,
    "tgn:name":"Thalean",
    "tgn:placetype":[
        "aat:300008347"
    ]
},
  "bbox": [],
  "geometry": {"coordinates":[-84.2833,32.0167],"type":"Point"}
}