{
  "id": 7070712,
  "type": "Feature",
  "properties": {
    "tgn:hierarchy":[
        "tgn:7070712",
        "tgn:7003669",
        "tgn:1000003",
        "tgn:7000084",
        "tgn:7029392"
    ],
    "tgn:id":7070712,
    "tgn:name":"Steindlberg",
    "tgn:placetype":[
        "aat:300000206"
    ]
},
  "bbox": [],
  "geometry": {"coordinates":[13.766667,48.483333],"type":"Point"}
}