{
  "id": 2176628,
  "type": "Feature",
  "properties": {
    "tgn:hierarchy":[
        "tgn:2176628",
        "tgn:1000001",
        "tgn:2001179",
        "tgn:7012149",
        "tgn:7007523",
        "tgn:7029392"
    ],
    "tgn:id":2176628,
    "tgn:name":"Black Land Bottom",
    "tgn:placetype":[
        "aat:300055621"
    ]
},
  "bbox": [],
  "geometry": {"coordinates":[-89.5333,37.25],"type":"Point"}
}