{
  "id": 2411182,
  "type": "Feature",
  "properties": {
    "tgn:hierarchy":[
        "tgn:2411182",
        "tgn:1000001",
        "tgn:7012149",
        "tgn:2000181",
        "tgn:7007157",
        "tgn:7029392"
    ],
    "tgn:id":2411182,
    "tgn:name":"Indian Field Ridge",
    "tgn:placetype":[
        "aat:300266640"
    ]
},
  "bbox": [],
  "geometry": {"coordinates":[-123.75,40.95],"type":"Point"}
}