{
  "id": 7233108,
  "type": "Feature",
  "properties": {
    "tgn:hierarchy":[
        "tgn:7233108",
        "tgn:7002690",
        "tgn:7012056",
        "tgn:1000003",
        "tgn:1000074",
        "tgn:7029392"
    ],
    "tgn:id":7233108,
    "tgn:name":"K\u00f3rakas, \u00c1kra",
    "tgn:placetype":[
        "aat:300008850"
    ]
},
  "bbox": [],
  "geometry": {"coordinates":[23.55,35.416667],"type":"Point"}
}