{
  "id": 7316965,
  "type": "Feature",
  "properties": {
    "tgn:hierarchy":[
        "tgn:7316965",
        "tgn:1001623",
        "tgn:1000049",
        "tgn:1000002",
        "tgn:7029392"
    ],
    "tgn:id":7316965,
    "tgn:name":"Confluencia, Laguna",
    "tgn:placetype":[
        "aat:300008680"
    ]
},
  "bbox": [],
  "geometry": {"coordinates":[-72.533333,-47.516667],"type":"Point"}
}