{
  "id": 7005723,
  "type": "Feature",
  "properties": {
    "tgn:hierarchy":[
        "tgn:7005723",
        "tgn:7003154",
        "tgn:1000003",
        "tgn:7003120",
        "tgn:1000080",
        "tgn:7029392"
    ],
    "tgn:id":7005723,
    "tgn:name":"Novalesa",
    "tgn:placetype":[
        "aat:300008347"
    ]
},
  "bbox": [],
  "geometry": {"coordinates":[7.016667,45.183333],"type":"Point"}
}