{
  "id": 7323074,
  "type": "Feature",
  "properties": {
    "tgn:hierarchy":[
        "tgn:7323074",
        "tgn:7002758",
        "tgn:1001316",
        "tgn:1000003",
        "tgn:1000095",
        "tgn:7029392"
    ],
    "tgn:id":7323074,
    "tgn:name":"Rus",
    "tgn:placetype":[
        "aat:300008347"
    ]
},
  "bbox": [],
  "geometry": {"coordinates":[-3.45,38.05],"type":"Point"}
}