{
  "id": 2216981,
  "type": "Feature",
  "properties": {
    "tgn:hierarchy":[
        "tgn:2216981",
        "tgn:1000001",
        "tgn:7012149",
        "tgn:1002691",
        "tgn:7007826",
        "tgn:7029392"
    ],
    "tgn:id":2216981,
    "tgn:name":"Camp Letcher Pond",
    "tgn:placetype":[
        "aat:300008680"
    ]
},
  "bbox": [],
  "geometry": {"coordinates":[-95.6167,30.4667],"type":"Point"}
}