{
  "id": 2007795,
  "type": "Feature",
  "properties": {
    "tgn:hierarchy":[
        "tgn:2007795",
        "tgn:1000001",
        "tgn:7016172",
        "tgn:7012149",
        "tgn:2000168",
        "tgn:7029392"
    ],
    "tgn:id":2007795,
    "tgn:name":"Boothe",
    "tgn:placetype":[
        "aat:300008347",
        "aat:300387210"
    ]
},
  "bbox": [],
  "geometry": {"coordinates":[-94.1167,35.0333],"type":"Point"}
}