{
  "id": 2042836,
  "type": "Feature",
  "properties": {
    "tgn:hierarchy":[
        "tgn:2042836",
        "tgn:1000001",
        "tgn:7012149",
        "tgn:2000882",
        "tgn:7007256",
        "tgn:7029392"
    ],
    "tgn:id":2042836,
    "tgn:name":"Galliano",
    "tgn:placetype":[
        "aat:300008347"
    ]
},
  "bbox": [],
  "geometry": {"coordinates":[-90.2833,29.4333],"type":"Point"}
}