{
  "id": 2472617,
  "type": "Feature",
  "properties": {
    "tgn:hierarchy":[
        "tgn:2472617",
        "tgn:1000001",
        "tgn:7012149",
        "tgn:7029392"
    ],
    "tgn:id":2472617,
    "tgn:name":"Love, Mount",
    "tgn:placetype":[
        "aat:300008798"
    ]
},
  "bbox": [],
  "geometry": {"coordinates":[-83.4833,35.5667],"type":"Point"}
}