{
  "id": 2191197,
  "type": "Feature",
  "properties": {
    "tgn:hierarchy":[
        "tgn:2191197",
        "tgn:1002149",
        "tgn:1000001",
        "tgn:7012149",
        "tgn:7007826",
        "tgn:7029392"
    ],
    "tgn:id":2191197,
    "tgn:name":"Boynton",
    "tgn:placetype":[
        "aat:300008347"
    ]
},
  "bbox": [],
  "geometry": {"coordinates":[-94.4167,31.2333],"type":"Point"}
}