{
  "id": 2013526,
  "type": "Feature",
  "properties": {
    "tgn:hierarchy":[
        "tgn:2013526",
        "tgn:1000001",
        "tgn:7012149",
        "tgn:7007157",
        "tgn:1002608",
        "tgn:7029392"
    ],
    "tgn:id":2013526,
    "tgn:name":"Ravenna",
    "tgn:placetype":[
        "aat:300387016"
    ]
},
  "bbox": [],
  "geometry": {"coordinates":[-118.2167,34.4333],"type":"Point"}
}