{
  "id": 7258400,
  "type": "Feature",
  "properties": {
    "tgn:concordances":{
        "gn:id":"2758562"
    },
    "tgn:hierarchy":[
        "tgn:7258400",
        "tgn:7003619",
        "tgn:1000003",
        "tgn:7016845",
        "tgn:7029392"
    ],
    "tgn:id":7258400,
    "tgn:name:nl":"Boshoek",
    "tgn:placetype":[
        "aat:300008347"
    ]
},
  "bbox": [],
  "geometry": {"coordinates":[6.033333,52.333333],"type":"Point"}
}