{
  "id": 2201248,
  "type": "Feature",
  "properties": {
    "tgn:hierarchy":[
        "tgn:2201248",
        "tgn:1000001",
        "tgn:7012149",
        "tgn:7007710",
        "tgn:7029392"
    ],
    "tgn:id":2201248,
    "tgn:name":"Buchanan Run",
    "tgn:placetype":[
        "aat:300008699"
    ]
},
  "bbox": [],
  "geometry": {"coordinates":[-80.3667,41.1333],"type":"Point"}
}