{
  "id": 1025224,
  "type": "Feature",
  "properties": {
    "tgn:hierarchy":[
        "tgn:1025224",
        "tgn:1001831",
        "tgn:1000002",
        "tgn:1000059",
        "tgn:7029392"
    ],
    "tgn:id":1025224,
    "tgn:name":"Palo Negro",
    "tgn:placetype":[
        "aat:300008347"
    ]
},
  "bbox": [],
  "geometry": {"coordinates":[-67.55,10.1833],"type":"Point"}
}