{
  "id": 2708460,
  "type": "Feature",
  "properties": {
    "tgn:hierarchy":[
        "tgn:2708460",
        "tgn:1000001",
        "tgn:7012149",
        "tgn:2002304",
        "tgn:7013961",
        "tgn:7029392"
    ],
    "tgn:id":2708460,
    "tgn:name":"Sycamore Creek",
    "tgn:placetype":[
        "aat:300008706"
    ]
},
  "bbox": [],
  "geometry": {"coordinates":[-81.6333,37.7667],"type":"Point"}
}