<<<<<<< HEAD
{
  "id": 2157500,
  "type": "Feature",
  "properties": {
    "tgn:hierarchy":[
        "tgn:2157500",
        "tgn:1000001",
        "tgn:7012149",
        "tgn:1002767",
        "tgn:7007920",
        "tgn:7029392"
    ],
    "tgn:id":2157500,
    "tgn:name":"Beaver Creek",
    "tgn:placetype":[
        "aat:300008706"
    ]
},
  "bbox": [],
  "geometry": {"coordinates":[-123.5,46.4],"type":"Point"}
}
=======
{"geometry":{"type":"Point","coordinates":[-123.500000,46.400000]},"type":"Feature","properties":{"hierarchy":["tgn:2157500","tgn:1000001","tgn:7012149","tgn:1002767","tgn:7007920","tgn:7029392"],"placetype":["aat:300008706"],"id":2157500,"name:xx":"Beaver Creek"}}
>>>>>>> 03f74aca74312dbeaf24d7e61306dd6a786dc3d0
