{
  "id": 7586606,
  "type": "Feature",
  "properties": {
    "tgn:hierarchy":[
        "tgn:7586606",
        "tgn:1000004",
        "tgn:7000198",
        "tgn:7000799",
        "tgn:7029392"
    ],
    "tgn:id":7586606,
    "tgn:name:en":"Logul Sar",
    "tgn:placetype":[
        "aat:300008688"
    ]
},
  "bbox": [],
  "geometry": {"coordinates":[74.909722,34.448611],"type":"Point"}
}