{
  "id": 7398181,
  "type": "Feature",
  "properties": {
    "tgn:hierarchy":[
        "tgn:7398181",
        "tgn:1000001",
        "tgn:1001960",
        "tgn:7005560",
        "tgn:7029392"
    ],
    "tgn:id":7398181,
    "tgn:name":"El Carricito",
    "tgn:placetype":[
        "aat:300266554",
        "aat:300008699"
    ]
},
  "bbox": [],
  "geometry": {"coordinates":[-111.223889,30.771111],"type":"Point"}
}