{
  "id": 2144493,
  "type": "Feature",
  "properties": {
    "tgn:hierarchy":[
        "tgn:2144493",
        "tgn:1000001",
        "tgn:7012149",
        "tgn:2001855",
        "tgn:7007825",
        "tgn:7029392"
    ],
    "tgn:id":2144493,
    "tgn:name":"Bakers Station Cave",
    "tgn:placetype":[
        "aat:300008746"
    ]
},
  "bbox": [],
  "geometry": {"coordinates":[-86.75,36.3667],"type":"Point"}
}