{
  "id": 2339089,
  "type": "Feature",
  "properties": {
    "tgn:hierarchy":[
        "tgn:2339089",
        "tgn:1000001",
        "tgn:1003037",
        "tgn:7012149",
        "tgn:7007516",
        "tgn:7029392"
    ],
    "tgn:id":2339089,
    "tgn:name":"Franklin Swamp",
    "tgn:placetype":[
        "aat:300008905"
    ]
},
  "bbox": [],
  "geometry": {"coordinates":[-75.2833,38.3333],"type":"Point"}
}