<<<<<<< HEAD
{
  "id": 2339089,
  "type": "Feature",
  "properties": {
    "tgn:hierarchy":[
        "tgn:2339089",
        "tgn:1000001",
        "tgn:1003037",
        "tgn:7012149",
        "tgn:7007516",
        "tgn:7029392"
    ],
    "tgn:id":2339089,
    "tgn:name":"Franklin Swamp",
    "tgn:placetype":[
        "aat:300008905"
    ]
},
  "bbox": [],
  "geometry": {"coordinates":[-75.2833,38.3333],"type":"Point"}
}
=======
{"geometry":{"type":"Point","coordinates":[-75.283300,38.333300]},"type":"Feature","properties":{"hierarchy":["tgn:2339089","tgn:1000001","tgn:1003037","tgn:7012149","tgn:7007516","tgn:7029392"],"placetype":["aat:300008905"],"id":2339089,"name:xx":"Franklin Swamp"}}
>>>>>>> 03f74aca74312dbeaf24d7e61306dd6a786dc3d0
