{
  "id": 2148597,
  "type": "Feature",
  "properties": {
    "tgn:hierarchy":[
        "tgn:2148597",
        "tgn:1000001",
        "tgn:7012149",
        "tgn:2000834",
        "tgn:7007255",
        "tgn:7029392"
    ],
    "tgn:id":2148597,
    "tgn:name":"Barnes Hill",
    "tgn:placetype":[
        "aat:300008798"
    ]
},
  "bbox": [],
  "geometry": {"coordinates":[-86.8167,37.45],"type":"Point"}
}