<<<<<<< HEAD
{
  "id": 7059200,
  "type": "Feature",
  "properties": {
    "tgn:hierarchy":[
        "tgn:7059200",
        "tgn:7001242",
        "tgn:7593770",
        "tgn:1000169",
        "tgn:7029392"
    ],
    "tgn:id":7059200,
    "tgn:name":"Gede",
    "tgn:placetype":[
        "aat:300008347"
    ]
},
  "bbox": [],
  "geometry": {"coordinates":[40.016,-3.3],"type":"Point"}
}
=======
{"geometry":{"type":"Point","coordinates":[40.016000,-3.300000]},"type":"Feature","properties":{"hierarchy":["tgn:7059200","tgn:7001242","tgn:7593770","tgn:1000169","tgn:7029392"],"placetype":["aat:300008347"],"id":7059200,"name:xx":"Gede"}}
>>>>>>> 03f74aca74312dbeaf24d7e61306dd6a786dc3d0
