{
  "id": 2753116,
  "type": "Feature",
  "properties": {
    "tgn:hierarchy":[
        "tgn:2753116",
        "tgn:1000001",
        "tgn:2001747",
        "tgn:7012149",
        "tgn:7007712",
        "tgn:7029392"
    ],
    "tgn:id":2753116,
    "tgn:name":"Water Shed Number One",
    "tgn:placetype":[
        "aat:300006191"
    ]
},
  "bbox": [],
  "geometry": {"coordinates":[-82.3333,34.6833],"type":"Point"}
}