<<<<<<< HEAD
{
  "id": 7054730,
  "type": "Feature",
  "properties": {
    "tgn:hierarchy":[
        "tgn:7054730",
        "tgn:7003005",
        "tgn:7003014",
        "tgn:1000003",
        "tgn:1000080",
        "tgn:7029392"
    ],
    "tgn:id":7054730,
    "tgn:name":"Paestum",
    "tgn:placetype":[
        "aat:300008347",
        "aat:300387007",
        "aat:300000810",
        "aat:300167671",
        "aat:300263063"
    ]
},
  "bbox": [],
  "geometry": {"coordinates":[15.0,40.416667],"type":"Point"}
}
=======
{"geometry":{"type":"Point","coordinates":[15.000000,40.416667]},"type":"Feature","properties":{"hierarchy":["tgn:7054730","tgn:7003005","tgn:7003014","tgn:1000003","tgn:1000080","tgn:7029392"],"placetype":["aat:300008347","aat:300387007","aat:300000810","aat:300167671","aat:300263063"],"id":7054730,"name:xx":"Paestum"}}
>>>>>>> 03f74aca74312dbeaf24d7e61306dd6a786dc3d0
