{
  "id": 2478906,
  "type": "Feature",
  "properties": {
    "tgn:hierarchy":[
        "tgn:2478906",
        "tgn:1000001",
        "tgn:2001025",
        "tgn:7012149",
        "tgn:7007521",
        "tgn:7029392"
    ],
    "tgn:id":2478906,
    "tgn:name":"Magda, Lake",
    "tgn:placetype":[
        "aat:300008680"
    ]
},
  "bbox": [],
  "geometry": {"coordinates":[-93.3833,45.0667],"type":"Point"}
}