{
  "id": 7419149,
  "type": "Feature",
  "properties": {
    "tgn:hierarchy":[
        "tgn:7419149",
        "tgn:1000001",
        "tgn:7005589",
        "tgn:7005560",
        "tgn:7029392"
    ],
    "tgn:id":7419149,
    "tgn:name:es":"La Carretera, Laguna",
    "tgn:placetype":[
        "aat:300008680"
    ]
},
  "bbox": [],
  "geometry": {"coordinates":[-100.249444,27.46],"type":"Point"}
}