<<<<<<< HEAD
{
  "id": 2252062,
  "type": "Feature",
  "properties": {
    "tgn:hierarchy":[
        "tgn:2252062",
        "tgn:1000001",
        "tgn:7012149",
        "tgn:2002118",
        "tgn:7007827",
        "tgn:7029392"
    ],
    "tgn:id":2252062,
    "tgn:name":"Condie",
    "tgn:placetype":[
        "aat:300008347"
    ]
},
  "bbox": [],
  "geometry": {"coordinates":[-112.0,40.6667],"type":"Point"}
}
=======
{"geometry":{"type":"Point","coordinates":[-112.000000,40.666700]},"type":"Feature","properties":{"hierarchy":["tgn:2252062","tgn:1000001","tgn:7012149","tgn:2002118","tgn:7007827","tgn:7029392"],"placetype":["aat:300008347"],"id":2252062,"name:xx":"Condie"}}
>>>>>>> 03f74aca74312dbeaf24d7e61306dd6a786dc3d0
