{
  "id": 7550310,
  "type": "Feature",
  "properties": {
    "tgn:hierarchy":[
        "tgn:7550310",
        "tgn:1000004",
        "tgn:1001869",
        "tgn:7000198",
        "tgn:7029392"
    ],
    "tgn:id":7550310,
    "tgn:name:en":"Dahinsara",
    "tgn:placetype":[
        "aat:300008347"
    ]
},
  "bbox": [],
  "geometry": {"coordinates":[70.616667,22.966667],"type":"Point"}
}