{
  "id": 7589066,
  "type": "Feature",
  "properties": {
    "tgn:hierarchy":[
        "tgn:7589066",
        "tgn:1000004",
        "tgn:1001869",
        "tgn:7000198",
        "tgn:7029392"
    ],
    "tgn:id":7589066,
    "tgn:name:en":"Tora",
    "tgn:placetype":[
        "aat:300008347"
    ]
},
  "bbox": [],
  "geometry": {"coordinates":[70.390245,22.064965],"type":"Point"}
}