{
  "id": 7455647,
  "type": "Feature",
  "properties": {
    "tgn:hierarchy":[
        "tgn:7455647",
        "tgn:7019094",
        "tgn:7002444",
        "tgn:1000003",
        "tgn:7008591",
        "tgn:7029392"
    ],
    "tgn:id":7455647,
    "tgn:name:en":"Dubh Sgeir",
    "tgn:placetype":[
        "aat:300011692"
    ]
},
  "bbox": [],
  "geometry": {"coordinates":[-7.033333,56.516667],"type":"Point"}
}