{
  "id": 2327762,
  "type": "Feature",
  "properties": {
    "tgn:hierarchy":[
        "tgn:2327762",
        "tgn:1000001",
        "tgn:1002270",
        "tgn:7012149",
        "tgn:7007708",
        "tgn:7029392"
    ],
    "tgn:id":2327762,
    "tgn:name":"Fish Creek Divide",
    "tgn:placetype":[
        "aat:300266640"
    ]
},
  "bbox": [],
  "geometry": {"coordinates":[-122.1167,45.0667],"type":"Point"}
}