{
  "id": 7230428,
  "type": "Feature",
  "properties": {
    "tgn:hierarchy":[
        "tgn:7230428",
        "tgn:7002725",
        "tgn:7002715",
        "tgn:1000003",
        "tgn:1000074",
        "tgn:7029392"
    ],
    "tgn:id":7230428,
    "tgn:name":"Krist\u00f3ni",
    "tgn:placetype":[
        "aat:300008347"
    ]
},
  "bbox": [],
  "geometry": {"coordinates":[22.855278,40.955556],"type":"Point"}
}