{
  "id": 7222251,
  "type": "Feature",
  "properties": {
    "tgn:hierarchy":[
        "tgn:7222251",
        "tgn:7002681",
        "tgn:7001395",
        "tgn:1000003",
        "tgn:1000074",
        "tgn:7029392"
    ],
    "tgn:id":7222251,
    "tgn:name":"Pors\u00edras R\u00e9ma",
    "tgn:placetype":[
        "aat:300008699"
    ]
},
  "bbox": [],
  "geometry": {"coordinates":[24.45,38.15],"type":"Point"}
}