{
  "id": 1107210,
  "type": "Feature",
  "properties": {
    "tgn:hierarchy":[
        "tgn:1107210",
        "tgn:1000004",
        "tgn:1003394",
        "tgn:7006655",
        "tgn:7029392"
    ],
    "tgn:id":1107210,
    "tgn:name":"Dankova, Pik",
    "tgn:placetype":[
        "aat:300008798"
    ]
},
  "bbox": [],
  "geometry": {"coordinates":[77.6333,41.0833],"type":"Point"}
}