{
  "id": 1101698,
  "type": "Feature",
  "properties": {
    "tgn:hierarchy":[
        "tgn:1101698",
        "tgn:1001094",
        "tgn:1000004",
        "tgn:1000135",
        "tgn:7029392"
    ],
    "tgn:id":1101698,
    "tgn:name":"Mayon Volcano National Park",
    "tgn:placetype":[
        "aat:300008189"
    ]
},
  "bbox": [],
  "geometry": {"coordinates":[123.65,13.2667],"type":"Point"}
}