<<<<<<< HEAD
{
  "id": 7354257,
  "type": "Feature",
  "properties": {
    "tgn:hierarchy":[
        "tgn:7354257",
        "tgn:1001835",
        "tgn:1000001",
        "tgn:7005560",
        "tgn:7029392"
    ],
    "tgn:id":7354257,
    "tgn:name":"Chucho Prieto, Mesa de",
    "tgn:placetype":[
        "aat:300008811"
    ]
},
  "bbox": [],
  "geometry": {"coordinates":[-115.633333,31.416667],"type":"Point"}
}
=======
{"geometry":{"type":"Point","coordinates":[-115.633333,31.416667]},"type":"Feature","properties":{"hierarchy":["tgn:7354257","tgn:1001835","tgn:1000001","tgn:7005560","tgn:7029392"],"placetype":["aat:300008811"],"id":7354257,"name:xx":"Chucho Prieto, Mesa de"}}
>>>>>>> 03f74aca74312dbeaf24d7e61306dd6a786dc3d0
