{
  "id": 7437453,
  "type": "Feature",
  "properties": {
    "tgn:hierarchy":[
        "tgn:7437453",
        "tgn:7005580",
        "tgn:1000001",
        "tgn:7005560",
        "tgn:7029392"
    ],
    "tgn:id":7437453,
    "tgn:name":"Santiago",
    "tgn:placetype":[
        "aat:300008347"
    ]
},
  "bbox": [],
  "geometry": {"coordinates":[-92.083333,16.633333],"type":"Point"}
}