{
  "id": 2465079,
  "type": "Feature",
  "properties": {
    "tgn:hierarchy":[
        "tgn:2465079",
        "tgn:1000001",
        "tgn:2000298",
        "tgn:7012149",
        "tgn:7007248",
        "tgn:7029392"
    ],
    "tgn:id":2465079,
    "tgn:name":"Lokeys Lake",
    "tgn:placetype":[
        "aat:300006191"
    ]
},
  "bbox": [],
  "geometry": {"coordinates":[-83.75,33.9167],"type":"Point"}
}