{
  "id": 2125606,
  "type": "Feature",
  "properties": {
    "tgn:hierarchy":[
        "tgn:2125606",
        "tgn:1002338",
        "tgn:1000001",
        "tgn:7012149",
        "tgn:7007516",
        "tgn:7029392"
    ],
    "tgn:id":2125606,
    "tgn:name":"Adam Island",
    "tgn:placetype":[
        "aat:300008791"
    ]
},
  "bbox": [],
  "geometry": {"coordinates":[-76.0833,38.1333],"type":"Point"}
}