{
  "id": 2361169,
  "type": "Feature",
  "properties": {
    "tgn:hierarchy":[
        "tgn:2361169",
        "tgn:1000001",
        "tgn:7012149",
        "tgn:2001420",
        "tgn:7007526",
        "tgn:7029392"
    ],
    "tgn:id":2361169,
    "tgn:name":"Gravel Canyon",
    "tgn:placetype":[
        "aat:300008761"
    ]
},
  "bbox": [],
  "geometry": {"coordinates":[-114.0833,39.7667],"type":"Point"}
}