{
  "id": 2566270,
  "type": "Feature",
  "properties": {
    "tgn:hierarchy":[
        "tgn:2566270",
        "tgn:1000001",
        "tgn:7012149",
        "tgn:2000329",
        "tgn:7007248",
        "tgn:7029392"
    ],
    "tgn:id":2566270,
    "tgn:name":"Palmetto Pines",
    "tgn:placetype":[
        "aat:300008347"
    ]
},
  "bbox": [],
  "geometry": {"coordinates":[-84.6167,33.4833],"type":"Point"}
}