{
  "id": 2182959,
  "type": "Feature",
  "properties": {
    "tgn:hierarchy":[
        "tgn:2182959",
        "tgn:1000001",
        "tgn:7012149",
        "tgn:2001991",
        "tgn:7007826",
        "tgn:7029392"
    ],
    "tgn:id":2182959,
    "tgn:name":"Bluebell Tank",
    "tgn:placetype":[
        "aat:300006191"
    ]
},
  "bbox": [],
  "geometry": {"coordinates":[-101.65,31.9833],"type":"Point"}
}