{
  "id": 2592979,
  "type": "Feature",
  "properties": {
    "tgn:hierarchy":[
        "tgn:2592979",
        "tgn:1000001",
        "tgn:7012149",
        "tgn:2001103",
        "tgn:7007522",
        "tgn:7029392"
    ],
    "tgn:id":2592979,
    "tgn:name":"Poplar Creek",
    "tgn:placetype":[
        "aat:300008706"
    ]
},
  "bbox": [],
  "geometry": {"coordinates":[-89.1333,31.15],"type":"Point"}
}