{
  "id": 7041359,
  "type": "Feature",
  "properties": {
    "tgn:hierarchy":[
        "tgn:7041359",
        "tgn:7003165",
        "tgn:1000003",
        "tgn:7009760",
        "tgn:1000080",
        "tgn:7029392"
    ],
    "tgn:id":7041359,
    "tgn:name":"San Martino in Freddana",
    "tgn:placetype":[
        "aat:300008347"
    ]
},
  "bbox": [],
  "geometry": {"coordinates":[10.45,43.916667],"type":"Point"}
}