{
  "id": 7358574,
  "type": "Feature",
  "properties": {
    "tgn:hierarchy":[
        "tgn:7358574",
        "tgn:7005581",
        "tgn:1000001",
        "tgn:7005560",
        "tgn:7029392"
    ],
    "tgn:id":7358574,
    "tgn:name":"Rancho El Agua Caliente",
    "tgn:placetype":[
        "aat:300000241"
    ]
},
  "bbox": [],
  "geometry": {"coordinates":[-106.183333,27.416667],"type":"Point"}
}