{
  "id": 1065376,
  "type": "Feature",
  "properties": {
    "tgn:hierarchy":[
        "tgn:1065376",
        "tgn:7016612",
        "tgn:1000004",
        "tgn:1001362",
        "tgn:7029392"
    ],
    "tgn:id":1065376,
    "tgn:name":"Asad\u0101b\u0101d",
    "tgn:placetype":[
        "aat:300008347",
        "aat:300387223",
        "aat:300008375"
    ]
},
  "bbox": [],
  "geometry": {"coordinates":[71.1333,34.8667],"type":"Point"}
}