{
  "id": 2542285,
  "type": "Feature",
  "properties": {
    "tgn:hierarchy":[
        "tgn:2542285",
        "tgn:7002659",
        "tgn:1000001",
        "tgn:7012149",
        "tgn:2000055",
        "tgn:7029392"
    ],
    "tgn:id":2542285,
    "tgn:name":"No Business Creek",
    "tgn:placetype":[
        "aat:300008706"
    ]
},
  "bbox": [],
  "geometry": {"coordinates":[-85.5167,33.1833],"type":"Point"}
}