{
  "id": 7150709,
  "type": "Feature",
  "properties": {
    "tgn:hierarchy":[
        "tgn:7150709",
        "tgn:1000003",
        "tgn:7003684",
        "tgn:7000084",
        "tgn:7029392"
    ],
    "tgn:id":7150709,
    "tgn:name":"Kuh-Berg",
    "tgn:placetype":[
        "aat:300008777"
    ]
},
  "bbox": [],
  "geometry": {"coordinates":[7.25,49.45],"type":"Point"}
}