{
  "id": 7419247,
  "type": "Feature",
  "properties": {
    "tgn:hierarchy":[
        "tgn:7419247",
        "tgn:7005579",
        "tgn:1000001",
        "tgn:7005560",
        "tgn:7029392"
    ],
    "tgn:id":7419247,
    "tgn:name":"Palo Alto, R\u00edo",
    "tgn:placetype":[
        "aat:300266554",
        "aat:300008699"
    ]
},
  "bbox": [],
  "geometry": {"coordinates":[-102.666667,22.066667],"type":"Point"}
}