{
  "id": 7324989,
  "type": "Feature",
  "properties": {
    "tgn:hierarchy":[
        "tgn:7324989",
        "tgn:7002758",
        "tgn:7002823",
        "tgn:1000003",
        "tgn:1000095",
        "tgn:7029392"
    ],
    "tgn:id":7324989,
    "tgn:name":"Santa Eulalia, Rivera de",
    "tgn:placetype":[
        "aat:300008699"
    ]
},
  "bbox": [],
  "geometry": {"coordinates":[-6.633333,37.783333],"type":"Point"}
}