{
  "id": 7547240,
  "type": "Feature",
  "properties": {
    "tgn:hierarchy":[
        "tgn:7547240",
        "tgn:1000004",
        "tgn:7000198",
        "tgn:1001886",
        "tgn:7029392"
    ],
    "tgn:id":7547240,
    "tgn:name:en":"Arukutti",
    "tgn:placetype":[
        "aat:300008347"
    ]
},
  "bbox": [],
  "geometry": {"coordinates":[76.35,9.866667],"type":"Point"}
}