{
  "id": 7480456,
  "type": "Feature",
  "properties": {
    "tgn:hierarchy":[
        "tgn:7480456",
        "tgn:1000004",
        "tgn:7490934",
        "tgn:1000141",
        "tgn:7029392"
    ],
    "tgn:id":7480456,
    "tgn:name":"Danei Erhao Qiao",
    "tgn:placetype":[
        "aat:300007836"
    ]
},
  "bbox": [],
  "geometry": {"coordinates":[120.350693,23.144201],"type":"Point"}
}