<<<<<<< HEAD
{
  "id": 7478248,
  "type": "Feature",
  "properties": {
    "tgn:hierarchy":[
        "tgn:7478248",
        "tgn:7487020",
        "tgn:1000004",
        "tgn:1000141",
        "tgn:7029392"
    ],
    "tgn:id":7478248,
    "tgn:name":"Jianfeng Qiao",
    "tgn:placetype":[
        "aat:300007836"
    ]
},
  "bbox": [],
  "geometry": {"coordinates":[120.882839,24.640495],"type":"Point"}
}
=======
{"geometry":{"type":"Point","coordinates":[120.882839,24.640495]},"type":"Feature","properties":{"hierarchy":["tgn:7478248","tgn:7487020","tgn:1000004","tgn:1000141","tgn:7029392"],"placetype":["aat:300007836"],"id":7478248,"name:xx":"Jianfeng Qiao"}}
>>>>>>> 03f74aca74312dbeaf24d7e61306dd6a786dc3d0
