{
  "id": 7382736,
  "type": "Feature",
  "properties": {
    "tgn:hierarchy":[
        "tgn:7382736",
        "tgn:1000001",
        "tgn:1001960",
        "tgn:7005560",
        "tgn:7029392"
    ],
    "tgn:id":7382736,
    "tgn:name":"Ongojori, Estero",
    "tgn:placetype":[
        "aat:300008679"
    ]
},
  "bbox": [],
  "geometry": {"coordinates":[-109.866667,26.816667],"type":"Point"}
}