{
  "id": 2328574,
  "type": "Feature",
  "properties": {
    "tgn:hierarchy":[
        "tgn:2328574",
        "tgn:1000001",
        "tgn:7006451",
        "tgn:2000092",
        "tgn:7012149",
        "tgn:7029392"
    ],
    "tgn:id":2328574,
    "tgn:name":"Fisher Spring",
    "tgn:placetype":[
        "aat:300008697"
    ]
},
  "bbox": [],
  "geometry": {"coordinates":[-111.6333,36.8667],"type":"Point"}
}