<<<<<<< HEAD
{
  "id": 2250210,
  "type": "Feature",
  "properties": {
    "tgn:hierarchy":[
        "tgn:2250210",
        "tgn:1000001",
        "tgn:1002480",
        "tgn:7012149",
        "tgn:7007564",
        "tgn:7029392"
    ],
    "tgn:id":2250210,
    "tgn:name":"Collins Ledge",
    "tgn:placetype":[
        "aat:300008798"
    ]
},
  "bbox": [],
  "geometry": {"coordinates":[-71.7833,43.1],"type":"Point"}
}
=======
{"geometry":{"type":"Point","coordinates":[-71.783300,43.100000]},"type":"Feature","properties":{"hierarchy":["tgn:2250210","tgn:1000001","tgn:1002480","tgn:7012149","tgn:7007564","tgn:7029392"],"placetype":["aat:300008798"],"id":2250210,"name:xx":"Collins Ledge"}}
>>>>>>> 03f74aca74312dbeaf24d7e61306dd6a786dc3d0
