{
  "id": 7431480,
  "type": "Feature",
  "properties": {
    "tgn:hierarchy":[
        "tgn:7431480",
        "tgn:7005581",
        "tgn:1000001",
        "tgn:7005560",
        "tgn:7029392"
    ],
    "tgn:id":7431480,
    "tgn:name":"Agua Dulce",
    "tgn:placetype":[
        "aat:300008347"
    ]
},
  "bbox": [],
  "geometry": {"coordinates":[-105.75,31.016667],"type":"Point"}
}