<<<<<<< HEAD
{
  "id": 7366742,
  "type": "Feature",
  "properties": {
    "tgn:hierarchy":[
        "tgn:7366742",
        "tgn:1000001",
        "tgn:7005599",
        "tgn:7005560",
        "tgn:7029392"
    ],
    "tgn:id":7366742,
    "tgn:name":"Espinal",
    "tgn:placetype":[
        "aat:300008347"
    ]
},
  "bbox": [],
  "geometry": {"coordinates":[-97.4,20.266667],"type":"Point"}
}
=======
{"geometry":{"type":"Point","coordinates":[-97.400000,20.266667]},"type":"Feature","properties":{"hierarchy":["tgn:7366742","tgn:1000001","tgn:7005599","tgn:7005560","tgn:7029392"],"placetype":["aat:300008347"],"id":7366742,"name:xx":"Espinal"}}
>>>>>>> 03f74aca74312dbeaf24d7e61306dd6a786dc3d0
