{
  "id": 2530253,
  "type": "Feature",
  "properties": {
    "tgn:hierarchy":[
        "tgn:2530253",
        "tgn:1000001",
        "tgn:7012149",
        "tgn:2001281",
        "tgn:7007524",
        "tgn:7029392"
    ],
    "tgn:id":2530253,
    "tgn:name":"Mud Springs Creek",
    "tgn:placetype":[
        "aat:300008706"
    ]
},
  "bbox": [],
  "geometry": {"coordinates":[-112.3167,45.8167],"type":"Point"}
}