{
  "id": 2649892,
  "type": "Feature",
  "properties": {
    "tgn:hierarchy":[
        "tgn:2649892",
        "tgn:1000001",
        "tgn:7012149",
        "tgn:2001119",
        "tgn:7007522",
        "tgn:7029392"
    ],
    "tgn:id":2649892,
    "tgn:name":"Scruggs Lake",
    "tgn:placetype":[
        "aat:300008680"
    ]
},
  "bbox": [],
  "geometry": {"coordinates":[-89.3833,31.6667],"type":"Point"}
}