{
  "id": 2452126,
  "type": "Feature",
  "properties": {
    "tgn:hierarchy":[
        "tgn:2452126",
        "tgn:1000001",
        "tgn:2000951",
        "tgn:7012149",
        "tgn:7007520",
        "tgn:7029392"
    ],
    "tgn:id":2452126,
    "tgn:name":"Little Black River",
    "tgn:placetype":[
        "aat:300008707"
    ]
},
  "bbox": [],
  "geometry": {"coordinates":[-84.5833,45.6667],"type":"Point"}
}