{
  "id": 2420149,
  "type": "Feature",
  "properties": {
    "tgn:hierarchy":[
        "tgn:2420149",
        "tgn:1002300",
        "tgn:1000001",
        "tgn:7012149",
        "tgn:7007564",
        "tgn:7029392"
    ],
    "tgn:id":2420149,
    "tgn:name":"Jefferson Brook",
    "tgn:placetype":[
        "aat:300008699"
    ]
},
  "bbox": [],
  "geometry": {"coordinates":[-71.3167,44.2833],"type":"Point"}
}