{
  "id": 7521034,
  "type": "Feature",
  "properties": {
    "tgn:hierarchy":[
        "tgn:7521034",
        "tgn:7001242",
        "tgn:7016833",
        "tgn:7001312",
        "tgn:7029392"
    ],
    "tgn:id":7521034,
    "tgn:name:en":"Afn\u00eesh",
    "tgn:placetype":[
        "aat:300008347"
    ]
},
  "bbox": [],
  "geometry": {"coordinates":[31.248889,31.060833],"type":"Point"}
}