{
  "id": 2757783,
  "type": "Feature",
  "properties": {
    "tgn:hierarchy":[
        "tgn:2757783",
        "tgn:1000001",
        "tgn:1002328",
        "tgn:7012149",
        "tgn:7007568",
        "tgn:7029392"
    ],
    "tgn:id":2757783,
    "tgn:name":"West Branch Handsome Brook",
    "tgn:placetype":[
        "aat:300008699"
    ]
},
  "bbox": [],
  "geometry": {"coordinates":[-75.0667,42.2667],"type":"Point"}
}