{
  "id": 7393138,
  "type": "Feature",
  "properties": {
    "tgn:hierarchy":[
        "tgn:7393138",
        "tgn:7005583",
        "tgn:1000001",
        "tgn:7005560",
        "tgn:7029392"
    ],
    "tgn:id":7393138,
    "tgn:name":"San Francisco",
    "tgn:placetype":[
        "aat:300008347"
    ]
},
  "bbox": [],
  "geometry": {"coordinates":[-105.686944,24.035],"type":"Point"}
}