{
  "id": 7342351,
  "type": "Feature",
  "properties": {
    "tgn:hierarchy":[
        "tgn:7342351",
        "tgn:7002842",
        "tgn:7001158",
        "tgn:1000003",
        "tgn:1000095",
        "tgn:7029392"
    ],
    "tgn:id":7342351,
    "tgn:name":"Carrascosa de Abajo",
    "tgn:placetype":[
        "aat:300008347"
    ]
},
  "bbox": [],
  "geometry": {"coordinates":[-3.083333,41.416667],"type":"Point"}
}