{
  "id": 2494510,
  "type": "Feature",
  "properties": {
    "tgn:hierarchy":[
        "tgn:2494510",
        "tgn:1000001",
        "tgn:7012149",
        "tgn:7007157",
        "tgn:2000188",
        "tgn:7029392"
    ],
    "tgn:id":2494510,
    "tgn:name":"Martin Gulch",
    "tgn:placetype":[
        "aat:300008761"
    ]
},
  "bbox": [],
  "geometry": {"coordinates":[-122.8667,40.3833],"type":"Point"}
}