{
  "id": 7087540,
  "type": "Feature",
  "properties": {
    "tgn:hierarchy":[
        "tgn:7087540",
        "tgn:1000003",
        "tgn:7003677",
        "tgn:7000084",
        "tgn:7029392"
    ],
    "tgn:id":7087540,
    "tgn:name":"Weh-Bach",
    "tgn:placetype":[
        "aat:300008699"
    ]
},
  "bbox": [],
  "geometry": {"coordinates":[6.35,50.85],"type":"Point"}
}