{
  "id": 7190331,
  "type": "Feature",
  "properties": {
    "tgn:hierarchy":[
        "tgn:7190331",
        "tgn:7003669",
        "tgn:1000003",
        "tgn:7000084",
        "tgn:7029392"
    ],
    "tgn:id":7190331,
    "tgn:name":"Engkofen",
    "tgn:placetype":[
        "aat:300008347"
    ]
},
  "bbox": [],
  "geometry": {"coordinates":[12.25,48.533333],"type":"Point"}
}