{
  "id": 7499560,
  "type": "Feature",
  "properties": {
    "tgn:hierarchy":[
        "tgn:7499560",
        "tgn:1000004",
        "tgn:1000959",
        "tgn:1000141",
        "tgn:7029392"
    ],
    "tgn:id":7499560,
    "tgn:name":"Taibei Huli Xueyuan",
    "tgn:placetype":[
        "aat:300006610"
    ]
},
  "bbox": [],
  "geometry": {"coordinates":[121.520622,25.116938],"type":"Point"}
}