<<<<<<< HEAD
{
  "id": 2766092,
  "type": "Feature",
  "properties": {
    "tgn:hierarchy":[
        "tgn:2766092",
        "tgn:1000001",
        "tgn:2001429",
        "tgn:7012149",
        "tgn:7007566",
        "tgn:7029392"
    ],
    "tgn:id":2766092,
    "tgn:name":"White House Canyon",
    "tgn:placetype":[
        "aat:300008761"
    ]
},
  "bbox": [],
  "geometry": {"coordinates":[-107.9333,34.25],"type":"Point"}
}
=======
{"geometry":{"type":"Point","coordinates":[-107.933300,34.250000]},"type":"Feature","properties":{"hierarchy":["tgn:2766092","tgn:1000001","tgn:2001429","tgn:7012149","tgn:7007566","tgn:7029392"],"placetype":["aat:300008761"],"id":2766092,"name:xx":"White House Canyon"}}
>>>>>>> 03f74aca74312dbeaf24d7e61306dd6a786dc3d0
