<<<<<<< HEAD
{
  "id": 7472182,
  "type": "Feature",
  "properties": {
    "tgn:hierarchy":[
        "tgn:7472182",
        "tgn:1000004",
        "tgn:7467799",
        "tgn:1000141",
        "tgn:7029392"
    ],
    "tgn:id":7472182,
    "tgn:name":"Shaluntou",
    "tgn:placetype":[
        "aat:300008347"
    ]
},
  "bbox": [],
  "geometry": {"coordinates":[120.453648,23.925217],"type":"Point"}
}
=======
{"geometry":{"type":"Point","coordinates":[120.453648,23.925217]},"type":"Feature","properties":{"hierarchy":["tgn:7472182","tgn:1000004","tgn:7467799","tgn:1000141","tgn:7029392"],"placetype":["aat:300008347"],"id":7472182,"name:xx":"Shaluntou"}}
>>>>>>> 03f74aca74312dbeaf24d7e61306dd6a786dc3d0
