{
  "id": 7472182,
  "type": "Feature",
  "properties": {
    "tgn:hierarchy":[
        "tgn:7472182",
        "tgn:1000004",
        "tgn:7467799",
        "tgn:1000141",
        "tgn:7029392"
    ],
    "tgn:id":7472182,
    "tgn:name":"Shaluntou",
    "tgn:placetype":[
        "aat:300008347"
    ]
},
  "bbox": [],
  "geometry": {"coordinates":[120.453648,23.925217],"type":"Point"}
}