{
  "id": 7408271,
  "type": "Feature",
  "properties": {
    "tgn:hierarchy":[
        "tgn:7408271",
        "tgn:1000001",
        "tgn:1001893",
        "tgn:7005560",
        "tgn:7029392"
    ],
    "tgn:id":7408271,
    "tgn:name":"Endej\u00e9",
    "tgn:placetype":[
        "aat:300008347"
    ]
},
  "bbox": [],
  "geometry": {"coordinates":[-99.825,19.966667],"type":"Point"}
}