<<<<<<< HEAD
{
  "id": 2402770,
  "type": "Feature",
  "properties": {
    "tgn:hierarchy":[
        "tgn:2402770",
        "tgn:1000001",
        "tgn:2001945",
        "tgn:7012149",
        "tgn:7007826",
        "tgn:7029392"
    ],
    "tgn:id":2402770,
    "tgn:name":"Hot Springs Canyon",
    "tgn:placetype":[
        "aat:300008761"
    ]
},
  "bbox": [],
  "geometry": {"coordinates":[-102.9833,29.1833],"type":"Point"}
}
=======
{"geometry":{"type":"Point","coordinates":[-102.983300,29.183300]},"type":"Feature","properties":{"hierarchy":["tgn:2402770","tgn:1000001","tgn:2001945","tgn:7012149","tgn:7007826","tgn:7029392"],"placetype":["aat:300008761"],"id":2402770,"name:xx":"Hot Springs Canyon"}}
>>>>>>> 03f74aca74312dbeaf24d7e61306dd6a786dc3d0
