{
  "id": 2644910,
  "type": "Feature",
  "properties": {
    "tgn:hierarchy":[
        "tgn:2644910",
        "tgn:1000001",
        "tgn:7012149",
        "tgn:7007158",
        "tgn:7029392"
    ],
    "tgn:id":2644910,
    "tgn:name":"Satanta Canal",
    "tgn:placetype":[
        "aat:300006075"
    ]
},
  "bbox": [],
  "geometry": {"coordinates":[-102.7333,38.2333],"type":"Point"}
}