{
  "id": 7109942,
  "type": "Feature",
  "properties": {
    "tgn:hierarchy":[
        "tgn:7109942",
        "tgn:1000003",
        "tgn:7003682",
        "tgn:7000084",
        "tgn:7029392"
    ],
    "tgn:id":7109942,
    "tgn:name":"Pyrmonterh\u00f6fe",
    "tgn:placetype":[
        "aat:300008347"
    ]
},
  "bbox": [],
  "geometry": {"coordinates":[7.266667,50.25],"type":"Point"}
}