{
  "id": 7035711,
  "type": "Feature",
  "properties": {
    "tgn:hierarchy":[
        "tgn:7035711",
        "tgn:7002996",
        "tgn:1000003",
        "tgn:7002997",
        "tgn:1000080",
        "tgn:7029392"
    ],
    "tgn:id":7035711,
    "tgn:name":"San Daniele",
    "tgn:placetype":[
        "aat:300008347"
    ]
},
  "bbox": [],
  "geometry": {"coordinates":[12.353611,46.017778],"type":"Point"}
}