{
  "id": 7318060,
  "type": "Feature",
  "properties": {
    "tgn:hierarchy":[
        "tgn:7318060",
        "tgn:1001699",
        "tgn:1000049",
        "tgn:1000002",
        "tgn:7029392"
    ],
    "tgn:id":7318060,
    "tgn:name":"Chel\u00edn",
    "tgn:placetype":[
        "aat:300008347"
    ]
},
  "bbox": [],
  "geometry": {"coordinates":[-73.517778,-42.585278],"type":"Point"}
}