{
  "id": 7381873,
  "type": "Feature",
  "properties": {
    "tgn:hierarchy":[
        "tgn:7381873",
        "tgn:7005586",
        "tgn:1000001",
        "tgn:7005560",
        "tgn:7029392"
    ],
    "tgn:id":7381873,
    "tgn:name":"Los Ocotes",
    "tgn:placetype":[
        "aat:300000241"
    ]
},
  "bbox": [],
  "geometry": {"coordinates":[-103.233333,19.216667],"type":"Point"}
}