<<<<<<< HEAD
{
  "id": 7247479,
  "type": "Feature",
  "properties": {
    "tgn:hierarchy":[
        "tgn:7247479",
        "tgn:7003466",
        "tgn:1000003",
        "tgn:1000063",
        "tgn:4012014",
        "tgn:7029392"
    ],
    "tgn:id":7247479,
    "tgn:name":"Charneuse",
    "tgn:placetype":[
        "aat:300008347"
    ]
},
  "bbox": [],
  "geometry": {"coordinates":[4.933333,49.933333],"type":"Point"}
}
=======
{"geometry":{"type":"Point","coordinates":[4.933333,49.933333]},"type":"Feature","properties":{"hierarchy":["tgn:7247479","tgn:7003466","tgn:1000003","tgn:1000063","tgn:4012014","tgn:7029392"],"placetype":["aat:300008347"],"id":7247479,"name:xx":"Charneuse"}}
>>>>>>> 03f74aca74312dbeaf24d7e61306dd6a786dc3d0
