{
  "id": 2563836,
  "type": "Feature",
  "properties": {
    "tgn:hierarchy":[
        "tgn:2563836",
        "tgn:1000001",
        "tgn:7012149",
        "tgn:2002188",
        "tgn:7007919",
        "tgn:7029392"
    ],
    "tgn:id":2563836,
    "tgn:name":"Oxendynes Cave",
    "tgn:placetype":[
        "aat:300008746"
    ]
},
  "bbox": [],
  "geometry": {"coordinates":[-82.2167,36.8833],"type":"Point"}
}