{
  "id": 7202497,
  "type": "Feature",
  "properties": {
    "tgn:hierarchy":[
        "tgn:7202497",
        "tgn:7003669",
        "tgn:1000003",
        "tgn:7000084",
        "tgn:7029392"
    ],
    "tgn:id":7202497,
    "tgn:name":"Breiten Berg",
    "tgn:placetype":[
        "aat:300008777"
    ]
},
  "bbox": [],
  "geometry": {"coordinates":[11.366667,49.583333],"type":"Point"}
}