{
  "id": 7276853,
  "type": "Feature",
  "properties": {
    "tgn:hierarchy":[
        "tgn:7276853",
        "tgn:1001705",
        "tgn:1000049",
        "tgn:1000002",
        "tgn:7029392"
    ],
    "tgn:id":7276853,
    "tgn:name":"Las Cruces, Ensenada",
    "tgn:placetype":[
        "aat:300132317"
    ]
},
  "bbox": [],
  "geometry": {"coordinates":[-72.05,-34.591667],"type":"Point"}
}