{
  "id": 2571931,
  "type": "Feature",
  "properties": {
    "tgn:hierarchy":[
        "tgn:2571931",
        "tgn:1000001",
        "tgn:7012149",
        "tgn:2001910",
        "tgn:7007825",
        "tgn:7029392"
    ],
    "tgn:id":2571931,
    "tgn:name":"Payne Hill",
    "tgn:placetype":[
        "aat:300008798"
    ]
},
  "bbox": [],
  "geometry": {"coordinates":[-86.6833,36.5167],"type":"Point"}
}