<<<<<<< HEAD
{
  "id": 7023027,
  "type": "Feature",
  "properties": {
    "tgn:hierarchy":[
        "tgn:7023027",
        "tgn:1000001",
        "tgn:7012149",
        "tgn:7029392"
    ],
    "tgn:id":7023027,
    "tgn:name":"Glenns Run",
    "tgn:placetype":[
        "aat:300008699"
    ]
},
  "bbox": [],
  "geometry": {"coordinates":[-80.6667,40.1167],"type":"Point"}
}
=======
{"geometry":{"type":"Point","coordinates":[-80.666700,40.116700]},"type":"Feature","properties":{"hierarchy":["tgn:7023027","tgn:1000001","tgn:7012149","tgn:7029392"],"placetype":["aat:300008699"],"id":7023027,"name:xx":"Glenns Run"}}
>>>>>>> 03f74aca74312dbeaf24d7e61306dd6a786dc3d0
