{
  "id": 7510944,
  "type": "Feature",
  "properties": {
    "tgn:hierarchy":[
        "tgn:7510944",
        "tgn:7016670",
        "tgn:1008380",
        "tgn:1000226",
        "tgn:1000006",
        "tgn:7029392"
    ],
    "tgn:id":7510944,
    "tgn:name:en":"Tupari",
    "tgn:placetype":[
        "aat:300008795"
    ]
},
  "bbox": [],
  "geometry": {"coordinates":[176.183333,-39.683333],"type":"Point"}
}