{
  "id": 2180163,
  "type": "Feature",
  "properties": {
    "tgn:hierarchy":[
        "tgn:2180163",
        "tgn:1000001",
        "tgn:7012149",
        "tgn:1002397",
        "tgn:7007568",
        "tgn:7029392"
    ],
    "tgn:id":2180163,
    "tgn:name":"Bliss Corner",
    "tgn:placetype":[
        "aat:300008347"
    ]
},
  "bbox": [],
  "geometry": {"coordinates":[-74.6667,43.15],"type":"Point"}
}