{
  "id": 1012477,
  "type": "Feature",
  "properties": {
    "tgn:hierarchy":[
        "tgn:1012477",
        "tgn:1002366",
        "tgn:1000001",
        "tgn:7012149",
        "tgn:7007159",
        "tgn:7029392"
    ],
    "tgn:id":1012477,
    "tgn:name":"Shippan Point",
    "tgn:placetype":[
        "aat:300386846"
    ]
},
  "bbox": [],
  "geometry": {"coordinates":[-73.5167,41.0167],"type":"Point"}
}