{
  "id": 7553033,
  "type": "Feature",
  "properties": {
    "tgn:hierarchy":[
        "tgn:7553033",
        "tgn:1000004",
        "tgn:7000198",
        "tgn:1001894",
        "tgn:7029392"
    ],
    "tgn:id":7553033,
    "tgn:name:en":"Mukhti\u0101ra",
    "tgn:placetype":[
        "aat:300007783"
    ]
},
  "bbox": [],
  "geometry": {"coordinates":[75.97852,22.38218],"type":"Point"}
}