{
  "id": 7306768,
  "type": "Feature",
  "properties": {
    "tgn:hierarchy":[
        "tgn:7306768",
        "tgn:7002758",
        "tgn:7002821",
        "tgn:1000003",
        "tgn:1000095",
        "tgn:7029392"
    ],
    "tgn:id":7306768,
    "tgn:name":"Los Pallares",
    "tgn:placetype":[
        "aat:300008347"
    ]
},
  "bbox": [],
  "geometry": {"coordinates":[-3.283333,36.833333],"type":"Point"}
}