{
  "id": 2115338,
  "type": "Feature",
  "properties": {
    "tgn:hierarchy":[
        "tgn:2115338",
        "tgn:1000001",
        "tgn:7012149",
        "tgn:2002251",
        "tgn:7007920",
        "tgn:7029392"
    ],
    "tgn:id":2115338,
    "tgn:name":"Berryman",
    "tgn:placetype":[
        "aat:300387016"
    ]
},
  "bbox": [],
  "geometry": {"coordinates":[-118.3833,46.2167],"type":"Point"}
}