{
  "id": 2239835,
  "type": "Feature",
  "properties": {
    "tgn:hierarchy":[
        "tgn:2239835",
        "tgn:1000001",
        "tgn:7012149",
        "tgn:2001447",
        "tgn:7007566",
        "tgn:7029392"
    ],
    "tgn:id":2239835,
    "tgn:name":"Cienegita Springs",
    "tgn:placetype":[
        "aat:300008697"
    ]
},
  "bbox": [],
  "geometry": {"coordinates":[-105.7833,33.3167],"type":"Point"}
}