{
  "id": 7524788,
  "type": "Feature",
  "properties": {
    "tgn:hierarchy":[
        "tgn:7524788",
        "tgn:7001242",
        "tgn:7016833",
        "tgn:7001336",
        "tgn:7029392"
    ],
    "tgn:id":7524788,
    "tgn:name:en":"Burqah, Ra's al",
    "tgn:placetype":[
        "aat:300386846"
    ]
},
  "bbox": [],
  "geometry": {"coordinates":[34.738244,29.209866],"type":"Point"}
}