{
  "id": 1107115,
  "type": "Feature",
  "properties": {
    "tgn:hierarchy":[
        "tgn:1107115",
        "tgn:1000001",
        "tgn:7012149",
        "tgn:1003020",
        "tgn:7007920",
        "tgn:7029392"
    ],
    "tgn:id":1107115,
    "tgn:name":"Bacon Peak",
    "tgn:placetype":[
        "aat:300008798"
    ]
},
  "bbox": [],
  "geometry": {"coordinates":[-121.5167,48.65],"type":"Point"}
}