{
  "id": 7088406,
  "type": "Feature",
  "properties": {
    "tgn:hierarchy":[
        "tgn:7088406",
        "tgn:1000003",
        "tgn:7003682",
        "tgn:7000084",
        "tgn:7029392"
    ],
    "tgn:id":7088406,
    "tgn:name":"Ruine Weilach",
    "tgn:placetype":[
        "aat:300008057"
    ]
},
  "bbox": [],
  "geometry": {"coordinates":[8.133333,49.483333],"type":"Point"}
}