{
  "id": 2172505,
  "type": "Feature",
  "properties": {
    "tgn:hierarchy":[
        "tgn:2172505",
        "tgn:1000001",
        "tgn:2001481",
        "tgn:7012149",
        "tgn:7007709",
        "tgn:7029392"
    ],
    "tgn:id":2172505,
    "tgn:name":"Bill Top",
    "tgn:placetype":[
        "aat:300008798"
    ]
},
  "bbox": [],
  "geometry": {"coordinates":[-84.1333,35.1667],"type":"Point"}
}