{
  "id": 7405678,
  "type": "Feature",
  "properties": {
    "tgn:hierarchy":[
        "tgn:7405678",
        "tgn:7016644",
        "tgn:1000001",
        "tgn:7005560",
        "tgn:7029392"
    ],
    "tgn:id":7405678,
    "tgn:name":"La Canoa",
    "tgn:placetype":[
        "aat:300008347"
    ]
},
  "bbox": [],
  "geometry": {"coordinates":[-104.466667,19.229167],"type":"Point"}
}