{
  "id": 1055827,
  "type": "Feature",
  "properties": {
    "tgn:hierarchy":[
        "tgn:1055827",
        "tgn:1000004",
        "tgn:7013412",
        "tgn:7018214",
        "tgn:7002435",
        "tgn:7029392"
    ],
    "tgn:id":1055827,
    "tgn:name":"Krasnokamsk",
    "tgn:placetype":[
        "aat:300008347"
    ]
},
  "bbox": [],
  "geometry": {"coordinates":[55.8167,58.0833],"type":"Point"}
}