{
  "id": 7478930,
  "type": "Feature",
  "properties": {
    "tgn:hierarchy":[
        "tgn:7478930",
        "tgn:1000004",
        "tgn:7489179",
        "tgn:1000141",
        "tgn:7029392"
    ],
    "tgn:id":7478930,
    "tgn:name":"Xinma",
    "tgn:placetype":[
        "aat:300008347"
    ]
},
  "bbox": [],
  "geometry": {"coordinates":[121.833761,24.617062],"type":"Point"}
}