<<<<<<< HEAD
{
  "id": 7056513,
  "type": "Feature",
  "properties": {
    "tgn:hierarchy":[
        "tgn:7056513",
        "tgn:1003473",
        "tgn:1000003",
        "tgn:7009760",
        "tgn:1000080",
        "tgn:7029392"
    ],
    "tgn:id":7056513,
    "tgn:name":"Bigliolo",
    "tgn:placetype":[
        "aat:300008347"
    ]
},
  "bbox": [],
  "geometry": {"coordinates":[10.05,44.233333],"type":"Point"}
}
=======
{"geometry":{"type":"Point","coordinates":[10.050000,44.233333]},"type":"Feature","properties":{"hierarchy":["tgn:7056513","tgn:1003473","tgn:1000003","tgn:7009760","tgn:1000080","tgn:7029392"],"placetype":["aat:300008347"],"id":7056513,"name:xx":"Bigliolo"}}
>>>>>>> 03f74aca74312dbeaf24d7e61306dd6a786dc3d0
