{
  "id": 2051444,
  "type": "Feature",
  "properties": {
    "tgn:hierarchy":[
        "tgn:2051444",
        "tgn:1000001",
        "tgn:7012149",
        "tgn:1002700",
        "tgn:7007520",
        "tgn:7029392"
    ],
    "tgn:id":2051444,
    "tgn:name":"Canada Corners",
    "tgn:placetype":[
        "aat:300008347",
        "aat:300387210"
    ]
},
  "bbox": [],
  "geometry": {"coordinates":[-85.8333,43.2333],"type":"Point"}
}