<<<<<<< HEAD
{
  "id": 7179524,
  "type": "Feature",
  "properties": {
    "tgn:hierarchy":[
        "tgn:7179524",
        "tgn:1000003",
        "tgn:7003688",
        "tgn:7000084",
        "tgn:7029392"
    ],
    "tgn:id":7179524,
    "tgn:name":"Gruskuhl",
    "tgn:placetype":[
        "aat:300000206"
    ]
},
  "bbox": [],
  "geometry": {"coordinates":[9.6,54.7],"type":"Point"}
}
=======
{"geometry":{"type":"Point","coordinates":[9.600000,54.700000]},"type":"Feature","properties":{"hierarchy":["tgn:7179524","tgn:1000003","tgn:7003688","tgn:7000084","tgn:7029392"],"placetype":["aat:300000206"],"id":7179524,"name:xx":"Gruskuhl"}}
>>>>>>> 03f74aca74312dbeaf24d7e61306dd6a786dc3d0
