{
  "id": 2696648,
  "type": "Feature",
  "properties": {
    "tgn:hierarchy":[
        "tgn:2696648",
        "tgn:1000001",
        "tgn:1002249",
        "tgn:7012149",
        "tgn:7007710",
        "tgn:7029392"
    ],
    "tgn:id":2696648,
    "tgn:name":"Stone Run",
    "tgn:placetype":[
        "aat:300008699"
    ]
},
  "bbox": [],
  "geometry": {"coordinates":[-77.7167,41.0167],"type":"Point"}
}