{
  "id": 7469737,
  "type": "Feature",
  "properties": {
    "tgn:hierarchy":[
        "tgn:7469737",
        "tgn:1000004",
        "tgn:7467799",
        "tgn:1000141",
        "tgn:7029392"
    ],
    "tgn:id":7469737,
    "tgn:name":"Chenggong",
    "tgn:placetype":[
        "aat:300008347"
    ]
},
  "bbox": [],
  "geometry": {"coordinates":[120.5455,23.8272],"type":"Point"}
}