{
  "id": 7203318,
  "type": "Feature",
  "properties": {
    "tgn:hierarchy":[
        "tgn:7203318",
        "tgn:7003669",
        "tgn:1000003",
        "tgn:7000084",
        "tgn:7029392"
    ],
    "tgn:id":7203318,
    "tgn:name":"Brunnbach",
    "tgn:placetype":[
        "aat:300008699"
    ]
},
  "bbox": [],
  "geometry": {"coordinates":[10.283333,49.916667],"type":"Point"}
}