{
  "id": 2526319,
  "type": "Feature",
  "properties": {
    "tgn:hierarchy":[
        "tgn:2526319",
        "tgn:1000001",
        "tgn:7012149",
        "tgn:2001715",
        "tgn:7007708",
        "tgn:7029392"
    ],
    "tgn:id":2526319,
    "tgn:name":"Moss Flat",
    "tgn:placetype":[
        "aat:300008905"
    ]
},
  "bbox": [],
  "geometry": {"coordinates":[-120.4167,42.4167],"type":"Point"}
}