<<<<<<< HEAD
{
  "id": 2153170,
  "type": "Feature",
  "properties": {
    "tgn:hierarchy":[
        "tgn:2153170",
        "tgn:1000001",
        "tgn:7016172",
        "tgn:7012149",
        "tgn:2000164",
        "tgn:7029392"
    ],
    "tgn:id":2153170,
    "tgn:name":"Beal Lake",
    "tgn:placetype":[
        "aat:300006191"
    ]
},
  "bbox": [],
  "geometry": {"coordinates":[-92.2,34.8667],"type":"Point"}
}
=======
{"geometry":{"type":"Point","coordinates":[-92.200000,34.866700]},"type":"Feature","properties":{"hierarchy":["tgn:2153170","tgn:1000001","tgn:7016172","tgn:7012149","tgn:2000164","tgn:7029392"],"placetype":["aat:300006191"],"id":2153170,"name:xx":"Beal Lake"}}
>>>>>>> 03f74aca74312dbeaf24d7e61306dd6a786dc3d0
