{
  "id": 1041419,
  "type": "Feature",
  "properties": {
    "tgn:hierarchy":[
        "tgn:1041419",
        "tgn:7003669",
        "tgn:1000003",
        "tgn:7000084",
        "tgn:7029392"
    ],
    "tgn:id":1041419,
    "tgn:name":"Tiefenbach",
    "tgn:placetype":[
        "aat:300008347"
    ]
},
  "bbox": [],
  "geometry": {"coordinates":[12.583333,49.433333],"type":"Point"}
}