{
  "id": 7590668,
  "type": "Feature",
  "properties": {
    "tgn:hierarchy":[
        "tgn:7590668",
        "tgn:1000004",
        "tgn:7000198",
        "tgn:7000799",
        "tgn:7029392"
    ],
    "tgn:id":7590668,
    "tgn:name:en":"Jerara",
    "tgn:placetype":[
        "aat:300008347"
    ]
},
  "bbox": [],
  "geometry": {"coordinates":[74.892745,32.499955],"type":"Point"}
}