{
  "id": 7588921,
  "type": "Feature",
  "properties": {
    "tgn:hierarchy":[
        "tgn:7588921",
        "tgn:1000004",
        "tgn:7000198",
        "tgn:7000799",
        "tgn:7029392"
    ],
    "tgn:id":7588921,
    "tgn:name:en":"Dhara",
    "tgn:placetype":[
        "aat:300008347"
    ]
},
  "bbox": [],
  "geometry": {"coordinates":[74.198032,33.732006],"type":"Point"}
}