{
  "id": 2384042,
  "type": "Feature",
  "properties": {
    "tgn:hierarchy":[
        "tgn:2384042",
        "tgn:1000001",
        "tgn:7012149",
        "tgn:2001713",
        "tgn:7007708",
        "tgn:7029392"
    ],
    "tgn:id":2384042,
    "tgn:name":"Hegan Creek",
    "tgn:placetype":[
        "aat:300008706"
    ]
},
  "bbox": [],
  "geometry": {"coordinates":[-123.6167,42.25],"type":"Point"}
}