{
  "id": 7403869,
  "type": "Feature",
  "properties": {
    "tgn:hierarchy":[
        "tgn:7403869",
        "tgn:1000001",
        "tgn:1001906",
        "tgn:7005560",
        "tgn:7029392"
    ],
    "tgn:id":7403869,
    "tgn:name":"La Mina",
    "tgn:placetype":[
        "aat:300008347"
    ]
},
  "bbox": [],
  "geometry": {"coordinates":[-105.266667,22.858333],"type":"Point"}
}