{
  "id": 7338611,
  "type": "Feature",
  "properties": {
    "tgn:hierarchy":[
        "tgn:7338611",
        "tgn:7002835",
        "tgn:7001158",
        "tgn:1000003",
        "tgn:1000095",
        "tgn:7029392"
    ],
    "tgn:id":7338611,
    "tgn:name":"Cu\u00e9llar",
    "tgn:placetype":[
        "aat:300008347"
    ]
},
  "bbox": [],
  "geometry": {"coordinates":[-6.65,40.633333],"type":"Point"}
}