{
  "id": 2459278,
  "type": "Feature",
  "properties": {
    "tgn:hierarchy":[
        "tgn:2459278",
        "tgn:1000001",
        "tgn:7012149",
        "tgn:2002126",
        "tgn:7007827",
        "tgn:7029392"
    ],
    "tgn:id":2459278,
    "tgn:name":"Little Pole Canyon",
    "tgn:placetype":[
        "aat:300008761"
    ]
},
  "bbox": [],
  "geometry": {"coordinates":[-111.35,40.55],"type":"Point"}
}