{
  "id": 2606870,
  "type": "Feature",
  "properties": {
    "tgn:hierarchy":[
        "tgn:2606870",
        "tgn:1000001",
        "tgn:2001936",
        "tgn:7012149",
        "tgn:7007826",
        "tgn:7029392"
    ],
    "tgn:id":2606870,
    "tgn:name":"Ramsey Tank",
    "tgn:placetype":[
        "aat:300006191"
    ]
},
  "bbox": [],
  "geometry": {"coordinates":[-98.5167,28.6667],"type":"Point"}
}