{
  "id": 2726843,
  "type": "Feature",
  "properties": {
    "tgn:hierarchy":[
        "tgn:2726843",
        "tgn:1002300",
        "tgn:1000001",
        "tgn:7012149",
        "tgn:7007564",
        "tgn:7029392"
    ],
    "tgn:id":2726843,
    "tgn:name":"Townline Brook",
    "tgn:placetype":[
        "aat:300008699"
    ]
},
  "bbox": [],
  "geometry": {"coordinates":[-71.1833,44.3167],"type":"Point"}
}