{
  "id": 7325471,
  "type": "Feature",
  "properties": {
    "tgn:hierarchy":[
        "tgn:7325471",
        "tgn:7007780",
        "tgn:1000003",
        "tgn:7009604",
        "tgn:1000095",
        "tgn:7029392"
    ],
    "tgn:id":7325471,
    "tgn:name":"San Mart\u00edn",
    "tgn:placetype":[
        "aat:300008347"
    ]
},
  "bbox": [],
  "geometry": {"coordinates":[-2.066667,43.05],"type":"Point"}
}