<<<<<<< HEAD
{
  "id": 7377792,
  "type": "Feature",
  "properties": {
    "tgn:hierarchy":[
        "tgn:7377792",
        "tgn:7005583",
        "tgn:1000001",
        "tgn:7005560",
        "tgn:7029392"
    ],
    "tgn:id":7377792,
    "tgn:name":"Las Carolinas",
    "tgn:placetype":[
        "aat:300008347"
    ]
},
  "bbox": [],
  "geometry": {"coordinates":[-104.1,26.2],"type":"Point"}
}
=======
{"geometry":{"type":"Point","coordinates":[-104.100000,26.200000]},"type":"Feature","properties":{"hierarchy":["tgn:7377792","tgn:7005583","tgn:1000001","tgn:7005560","tgn:7029392"],"placetype":["aat:300008347"],"id":7377792,"name:xx":"Las Carolinas"}}
>>>>>>> 03f74aca74312dbeaf24d7e61306dd6a786dc3d0
