{
  "id": 7052981,
  "type": "Feature",
  "properties": {
    "tgn:hierarchy":[
        "tgn:7052981",
        "tgn:7003163",
        "tgn:1000003",
        "tgn:7009760",
        "tgn:1000080",
        "tgn:7029392"
    ],
    "tgn:id":7052981,
    "tgn:name":"Idoli, Lago degli",
    "tgn:placetype":[
        "aat:300008688"
    ]
},
  "bbox": [],
  "geometry": {"coordinates":[11.683333,43.866667],"type":"Point"}
}