{
  "id": 7419044,
  "type": "Feature",
  "properties": {
    "tgn:hierarchy":[
        "tgn:7419044",
        "tgn:7005579",
        "tgn:1000001",
        "tgn:7005560",
        "tgn:7029392"
    ],
    "tgn:id":7419044,
    "tgn:name":"Los Sotoles, Arroyo",
    "tgn:placetype":[
        "aat:300266554",
        "aat:300008699"
    ]
},
  "bbox": [],
  "geometry": {"coordinates":[-102.541667,22.066667],"type":"Point"}
}