{
  "id": 7507602,
  "type": "Feature",
  "properties": {
    "tgn:hierarchy":[
        "tgn:7507602",
        "tgn:1008380",
        "tgn:7000507",
        "tgn:1000226",
        "tgn:1000006",
        "tgn:7029392"
    ],
    "tgn:id":7507602,
    "tgn:name:en":"Poroti",
    "tgn:placetype":[
        "aat:300008347"
    ]
},
  "bbox": [],
  "geometry": {"coordinates":[174.133333,-35.733333],"type":"Point"}
}