{
  "id": 2194094,
  "type": "Feature",
  "properties": {
    "tgn:hierarchy":[
        "tgn:2194094",
        "tgn:1000001",
        "tgn:7012149",
        "tgn:2002189",
        "tgn:7007919",
        "tgn:7029392"
    ],
    "tgn:id":2194094,
    "tgn:name":"Brickey Spring",
    "tgn:placetype":[
        "aat:300008697"
    ]
},
  "bbox": [],
  "geometry": {"coordinates":[-82.5833,36.7833],"type":"Point"}
}