{
  "id": 7588659,
  "type": "Feature",
  "properties": {
    "tgn:hierarchy":[
        "tgn:7588659",
        "tgn:1000004",
        "tgn:7000198",
        "tgn:7000799",
        "tgn:7029392"
    ],
    "tgn:id":7588659,
    "tgn:name:en":"Sal\u0101m\u0101b\u0101d",
    "tgn:placetype":[
        "aat:300008347"
    ]
},
  "bbox": [],
  "geometry": {"coordinates":[74.184771,33.80941],"type":"Point"}
}