{
  "id": 7138485,
  "type": "Feature",
  "properties": {
    "tgn:hierarchy":[
        "tgn:7138485",
        "tgn:7003692",
        "tgn:1000003",
        "tgn:7000084",
        "tgn:7029392"
    ],
    "tgn:id":7138485,
    "tgn:name":"Lebersteinhof",
    "tgn:placetype":[
        "aat:300000206"
    ]
},
  "bbox": [],
  "geometry": {"coordinates":[8.016667,48.216667],"type":"Point"}
}