{
  "id": 7185008,
  "type": "Feature",
  "properties": {
    "tgn:hierarchy":[
        "tgn:7185008",
        "tgn:7003669",
        "tgn:1000003",
        "tgn:7000084",
        "tgn:7029392"
    ],
    "tgn:id":7185008,
    "tgn:name":"Glockengraben",
    "tgn:placetype":[
        "aat:300055621"
    ]
},
  "bbox": [],
  "geometry": {"coordinates":[10.566667,49.866667],"type":"Point"}
}