<<<<<<< HEAD
{
  "id": 2401759,
  "type": "Feature",
  "properties": {
    "tgn:hierarchy":[
        "tgn:2401759",
        "tgn:1000001",
        "tgn:2001019",
        "tgn:7012149",
        "tgn:7007521",
        "tgn:7029392"
    ],
    "tgn:id":2401759,
    "tgn:name":"Horseshoe Lake",
    "tgn:placetype":[
        "aat:300008680"
    ]
},
  "bbox": [],
  "geometry": {"coordinates":[-95.6833,46.0167],"type":"Point"}
}
=======
{"geometry":{"type":"Point","coordinates":[-95.683300,46.016700]},"type":"Feature","properties":{"hierarchy":["tgn:2401759","tgn:1000001","tgn:2001019","tgn:7012149","tgn:7007521","tgn:7029392"],"placetype":["aat:300008680"],"id":2401759,"name:xx":"Horseshoe Lake"}}
>>>>>>> 03f74aca74312dbeaf24d7e61306dd6a786dc3d0
