{
  "id": 7333967,
  "type": "Feature",
  "properties": {
    "tgn:hierarchy":[
        "tgn:7333967",
        "tgn:7002829",
        "tgn:1000003",
        "tgn:7002786",
        "tgn:1000095",
        "tgn:7029392"
    ],
    "tgn:id":7333967,
    "tgn:name":"Encrucilladas",
    "tgn:placetype":[
        "aat:300008347"
    ]
},
  "bbox": [],
  "geometry": {"coordinates":[-7.233333,42.783333],"type":"Point"}
}