{
  "id": 2129079,
  "type": "Feature",
  "properties": {
    "tgn:hierarchy":[
        "tgn:2129079",
        "tgn:1000001",
        "tgn:7012149",
        "tgn:2001617",
        "tgn:7007706",
        "tgn:7029392"
    ],
    "tgn:id":2129079,
    "tgn:name":"Alexis",
    "tgn:placetype":[
        "aat:300008347"
    ]
},
  "bbox": [],
  "geometry": {"coordinates":[-81.0167,39.6333],"type":"Point"}
}