<<<<<<< HEAD
{
  "id": 7052486,
  "type": "Feature",
  "properties": {
    "tgn:hierarchy":[
        "tgn:7052486",
        "tgn:1003450",
        "tgn:7007850",
        "tgn:1000003",
        "tgn:1000080",
        "tgn:7029392"
    ],
    "tgn:id":7052486,
    "tgn:name":"Mancini",
    "tgn:placetype":[
        "aat:300008347"
    ]
},
  "bbox": [],
  "geometry": {"coordinates":[16.166667,40.033333],"type":"Point"}
}
=======
{"geometry":{"type":"Point","coordinates":[16.166667,40.033333]},"type":"Feature","properties":{"hierarchy":["tgn:7052486","tgn:1003450","tgn:7007850","tgn:1000003","tgn:1000080","tgn:7029392"],"placetype":["aat:300008347"],"id":7052486,"name:xx":"Mancini"}}
>>>>>>> 03f74aca74312dbeaf24d7e61306dd6a786dc3d0
