{
  "id": 1098010,
  "type": "Feature",
  "properties": {
    "tgn:hierarchy":[
        "tgn:1098010",
        "tgn:7000490",
        "tgn:1000006",
        "tgn:7001830",
        "tgn:7029392"
    ],
    "tgn:id":1098010,
    "tgn:name":"Proston",
    "tgn:placetype":[
        "aat:300008347"
    ]
},
  "bbox": [],
  "geometry": {"coordinates":[151.5333,-26.1333],"type":"Point"}
}