{
  "id": 2561809,
  "type": "Feature",
  "properties": {
    "tgn:hierarchy":[
        "tgn:2561809",
        "tgn:1000001",
        "tgn:2000696",
        "tgn:7012149",
        "tgn:7007254",
        "tgn:7029392"
    ],
    "tgn:id":2561809,
    "tgn:name":"Otis Creek",
    "tgn:placetype":[
        "aat:300008706"
    ]
},
  "bbox": [],
  "geometry": {"coordinates":[-96.4667,38.0167],"type":"Point"}
}