<<<<<<< HEAD
{
  "id": 7114266,
  "type": "Feature",
  "properties": {
    "tgn:hierarchy":[
        "tgn:7114266",
        "tgn:7003669",
        "tgn:1000003",
        "tgn:7000084",
        "tgn:7029392"
    ],
    "tgn:id":7114266,
    "tgn:name":"R\u00f6mersreuth",
    "tgn:placetype":[
        "aat:300008347"
    ]
},
  "bbox": [],
  "geometry": {"coordinates":[11.533333,50.2],"type":"Point"}
}
=======
{"geometry":{"type":"Point","coordinates":[11.533333,50.200000]},"type":"Feature","properties":{"hierarchy":["tgn:7114266","tgn:7003669","tgn:1000003","tgn:7000084","tgn:7029392"],"placetype":["aat:300008347"],"id":7114266,"name:xx":"R\u00f6mersreuth"}}
>>>>>>> 03f74aca74312dbeaf24d7e61306dd6a786dc3d0
