{
  "id": 2149411,
  "type": "Feature",
  "properties": {
    "tgn:hierarchy":[
        "tgn:2149411",
        "tgn:1000001",
        "tgn:1003023",
        "tgn:7012149",
        "tgn:7007516",
        "tgn:7029392"
    ],
    "tgn:id":2149411,
    "tgn:name":"Barren Pond",
    "tgn:placetype":[
        "aat:300006191"
    ]
},
  "bbox": [],
  "geometry": {"coordinates":[-75.7333,38.45],"type":"Point"}
}