{
  "id": 7157527,
  "type": "Feature",
  "properties": {
    "tgn:hierarchy":[
        "tgn:7157527",
        "tgn:1000003",
        "tgn:7000094",
        "tgn:7000084",
        "tgn:7029392"
    ],
    "tgn:id":7157527,
    "tgn:name":"Kienhorst",
    "tgn:placetype":[
        "aat:300008777"
    ]
},
  "bbox": [],
  "geometry": {"coordinates":[12.866667,53.35],"type":"Point"}
}