{
  "id": 2672534,
  "type": "Feature",
  "properties": {
    "tgn:hierarchy":[
        "tgn:2672534",
        "tgn:1000001",
        "tgn:2001945",
        "tgn:7012149",
        "tgn:7007826",
        "tgn:7029392"
    ],
    "tgn:id":2672534,
    "tgn:name":"Smoky Spring",
    "tgn:placetype":[
        "aat:300008697"
    ]
},
  "bbox": [],
  "geometry": {"coordinates":[-103.3667,29.1333],"type":"Point"}
}