<<<<<<< HEAD
{
  "id": 7170860,
  "type": "Feature",
  "properties": {
    "tgn:hierarchy":[
        "tgn:7170860",
        "tgn:1000003",
        "tgn:7003676",
        "tgn:7000084",
        "tgn:7029392"
    ],
    "tgn:id":7170860,
    "tgn:name":"Himmigerode",
    "tgn:placetype":[
        "aat:300000206"
    ]
},
  "bbox": [],
  "geometry": {"coordinates":[10.133333,51.5],"type":"Point"}
}
=======
{"geometry":{"type":"Point","coordinates":[10.133333,51.500000]},"type":"Feature","properties":{"hierarchy":["tgn:7170860","tgn:1000003","tgn:7003676","tgn:7000084","tgn:7029392"],"placetype":["aat:300000206"],"id":7170860,"name:xx":"Himmigerode"}}
>>>>>>> 03f74aca74312dbeaf24d7e61306dd6a786dc3d0
