{
  "id": 1013479,
  "type": "Feature",
  "properties": {
    "tgn:hierarchy":[
        "tgn:1013479",
        "tgn:7005735",
        "tgn:7005685",
        "tgn:1000001",
        "tgn:7029392"
    ],
    "tgn:id":1013479,
    "tgn:name":"Douglas Lake",
    "tgn:placetype":[
        "aat:300008347"
    ]
},
  "bbox": [],
  "geometry": {"coordinates":[-120.1833,50.15],"type":"Point"}
}