{
  "id": 7204922,
  "type": "Feature",
  "properties": {
    "tgn:hierarchy":[
        "tgn:7204922",
        "tgn:1000003",
        "tgn:7003676",
        "tgn:7000084",
        "tgn:7029392"
    ],
    "tgn:id":7204922,
    "tgn:name":"Bullen-Berg",
    "tgn:placetype":[
        "aat:300008777"
    ]
},
  "bbox": [],
  "geometry": {"coordinates":[9.116667,53.616667],"type":"Point"}
}