{
  "id": 1061440,
  "type": "Feature",
  "properties": {
    "tgn:hierarchy":[
        "tgn:1061440",
        "tgn:1000004",
        "tgn:7011531",
        "tgn:7018214",
        "tgn:7002435",
        "tgn:7029392"
    ],
    "tgn:id":1061440,
    "tgn:name":"Vyselki",
    "tgn:placetype":[
        "aat:300008347"
    ]
},
  "bbox": [],
  "geometry": {"coordinates":[39.65,45.5833],"type":"Point"}
}