<<<<<<< HEAD
{
  "id": 7027626,
  "type": "Feature",
  "properties": {
    "tgn:hierarchy":[
        "tgn:7027626",
        "tgn:7002445",
        "tgn:1000003",
        "tgn:7008155",
        "tgn:7008591",
        "tgn:7029392"
    ],
    "tgn:id":7027626,
    "tgn:name:en":"Old Dalby",
    "tgn:placetype":[
        "aat:300008347",
        "aat:300008372"
    ]
},
  "bbox": [],
  "geometry": {"coordinates":[-0.983333,52.8],"type":"Point"}
}
=======
{"geometry":{"type":"Point","coordinates":[-0.983333,52.800000]},"type":"Feature","properties":{"hierarchy":["tgn:7027626","tgn:7002445","tgn:1000003","tgn:7008155","tgn:7008591","tgn:7029392"],"placetype":["aat:300008347","aat:300008372"],"name:en":"Old Dalby","id":7027626}}
>>>>>>> 03f74aca74312dbeaf24d7e61306dd6a786dc3d0
