{
  "id": 7589288,
  "type": "Feature",
  "properties": {
    "tgn:hierarchy":[
        "tgn:7589288",
        "tgn:1000004",
        "tgn:7000198",
        "tgn:7000799",
        "tgn:7029392"
    ],
    "tgn:id":7589288,
    "tgn:name:en":"Ch\u0101nthan Gul\u0101bpura",
    "tgn:placetype":[
        "aat:300008347"
    ]
},
  "bbox": [],
  "geometry": {"coordinates":[74.753891,34.280794],"type":"Point"}
}