{
  "id": 2092676,
  "type": "Feature",
  "properties": {
    "tgn:hierarchy":[
        "tgn:2092676",
        "tgn:1000001",
        "tgn:7012149",
        "tgn:1003041",
        "tgn:7007710",
        "tgn:7029392"
    ],
    "tgn:id":2092676,
    "tgn:name":"Ruggles",
    "tgn:placetype":[
        "aat:300008347",
        "aat:300387210"
    ]
},
  "bbox": [],
  "geometry": {"coordinates":[-76.05,41.3833],"type":"Point"}
}