{
  "id": 2458889,
  "type": "Feature",
  "properties": {
    "tgn:hierarchy":[
        "tgn:2458889",
        "tgn:1000001",
        "tgn:7012149",
        "tgn:2001854",
        "tgn:7007825",
        "tgn:7029392"
    ],
    "tgn:id":2458889,
    "tgn:name":"Little Peavine Mountain",
    "tgn:placetype":[
        "aat:300008798"
    ]
},
  "bbox": [],
  "geometry": {"coordinates":[-84.8167,36.05],"type":"Point"}
}