{
  "id": 7381811,
  "type": "Feature",
  "properties": {
    "tgn:hierarchy":[
        "tgn:7381811",
        "tgn:7005581",
        "tgn:1000001",
        "tgn:7005560",
        "tgn:7029392"
    ],
    "tgn:id":7381811,
    "tgn:name":"Los Arados, Sierra",
    "tgn:placetype":[
        "aat:300008795"
    ]
},
  "bbox": [],
  "geometry": {"coordinates":[-106.683333,30.05],"type":"Point"}
}