{
  "id": 7281790,
  "type": "Feature",
  "properties": {
    "tgn:hierarchy":[
        "tgn:7281790",
        "tgn:1001623",
        "tgn:1000049",
        "tgn:1000002",
        "tgn:7029392"
    ],
    "tgn:id":7281790,
    "tgn:name":"San Quint\u00edn, Bajo",
    "tgn:placetype":[
        "aat:300387036"
    ]
},
  "bbox": [],
  "geometry": {"coordinates":[-74.583333,-46.816667],"type":"Point"}
}