{
  "id": 2336198,
  "type": "Feature",
  "properties": {
    "tgn:hierarchy":[
        "tgn:2336198",
        "tgn:1000001",
        "tgn:2000920",
        "tgn:7012149",
        "tgn:7007515",
        "tgn:7029392"
    ],
    "tgn:id":2336198,
    "tgn:name":"Foster Pond",
    "tgn:placetype":[
        "aat:300008680"
    ]
},
  "bbox": [],
  "geometry": {"coordinates":[-70.6833,43.9667],"type":"Point"}
}