<<<<<<< HEAD
{
  "id": 2336198,
  "type": "Feature",
  "properties": {
    "tgn:hierarchy":[
        "tgn:2336198",
        "tgn:1000001",
        "tgn:2000920",
        "tgn:7012149",
        "tgn:7007515",
        "tgn:7029392"
    ],
    "tgn:id":2336198,
    "tgn:name":"Foster Pond",
    "tgn:placetype":[
        "aat:300008680"
    ]
},
  "bbox": [],
  "geometry": {"coordinates":[-70.6833,43.9667],"type":"Point"}
}
=======
{"geometry":{"type":"Point","coordinates":[-70.683300,43.966700]},"type":"Feature","properties":{"hierarchy":["tgn:2336198","tgn:1000001","tgn:2000920","tgn:7012149","tgn:7007515","tgn:7029392"],"placetype":["aat:300008680"],"id":2336198,"name:xx":"Foster Pond"}}
>>>>>>> 03f74aca74312dbeaf24d7e61306dd6a786dc3d0
