{
  "id": 1099184,
  "type": "Feature",
  "properties": {
    "tgn:hierarchy":[
        "tgn:1099184",
        "tgn:1009227",
        "tgn:7001866",
        "tgn:1000226",
        "tgn:1000006",
        "tgn:7029392"
    ],
    "tgn:id":1099184,
    "tgn:name:en":"Rakaia",
    "tgn:placetype":[
        "aat:300008347"
    ]
},
  "bbox": [],
  "geometry": {"coordinates":[172.016667,-43.75],"type":"Point"}
}