{
  "id": 2621361,
  "type": "Feature",
  "properties": {
    "tgn:hierarchy":[
        "tgn:2621361",
        "tgn:1002300",
        "tgn:1000001",
        "tgn:7012149",
        "tgn:7007564",
        "tgn:7029392"
    ],
    "tgn:id":2621361,
    "tgn:name":"Roaring Brook",
    "tgn:placetype":[
        "aat:300008699"
    ]
},
  "bbox": [],
  "geometry": {"coordinates":[-71.4167,44.6333],"type":"Point"}
}