{
  "id": 2324153,
  "type": "Feature",
  "properties": {
    "tgn:hierarchy":[
        "tgn:2324153",
        "tgn:1000001",
        "tgn:1002328",
        "tgn:7012149",
        "tgn:7007568",
        "tgn:7029392"
    ],
    "tgn:id":2324153,
    "tgn:name":"Feak Hollow",
    "tgn:placetype":[
        "aat:300008761"
    ]
},
  "bbox": [],
  "geometry": {"coordinates":[-75.0333,42.2333],"type":"Point"}
}