{
  "id": 2657177,
  "type": "Feature",
  "properties": {
    "tgn:hierarchy":[
        "tgn:2657177",
        "tgn:1000001",
        "tgn:2001473",
        "tgn:7012149",
        "tgn:7007709",
        "tgn:7029392"
    ],
    "tgn:id":2657177,
    "tgn:name":"Sheep Rock",
    "tgn:placetype":[
        "aat:300008798"
    ]
},
  "bbox": [],
  "geometry": {"coordinates":[-82.6667,35.4833],"type":"Point"}
}