{
  "id": 7023357,
  "type": "Feature",
  "properties": {
    "tgn:hierarchy":[
        "tgn:7023357",
        "tgn:1000001",
        "tgn:7012149",
        "tgn:7007520",
        "tgn:7029392"
    ],
    "tgn:id":7023357,
    "tgn:name":"South Fox Island Shoals",
    "tgn:placetype":[
        "aat:300132348"
    ]
},
  "bbox": [],
  "geometry": {"coordinates":[-85.85,45.2833],"type":"Point"}
}