{
  "id": 7538409,
  "type": "Feature",
  "properties": {
    "tgn:hierarchy":[
        "tgn:7538409",
        "tgn:7001242",
        "tgn:7016833",
        "tgn:1001114",
        "tgn:7029392"
    ],
    "tgn:id":7538409,
    "tgn:name:en":"Shaqalq\u012bl",
    "tgn:placetype":[
        "aat:300008347"
    ]
},
  "bbox": [],
  "geometry": {"coordinates":[31.019035,27.320824],"type":"Point"}
}