{
  "id": 2362076,
  "type": "Feature",
  "properties": {
    "tgn:hierarchy":[
        "tgn:2362076",
        "tgn:1000001",
        "tgn:2001409",
        "tgn:7012149",
        "tgn:7007526",
        "tgn:7029392"
    ],
    "tgn:id":2362076,
    "tgn:name":"Grayback",
    "tgn:placetype":[
        "aat:300008798"
    ]
},
  "bbox": [],
  "geometry": {"coordinates":[-117.8833,39.1833],"type":"Point"}
}