{
  "id": 2224116,
  "type": "Feature",
  "properties": {
    "tgn:hierarchy":[
        "tgn:2224116",
        "tgn:1000001",
        "tgn:7016172",
        "tgn:2000120",
        "tgn:7012149",
        "tgn:7029392"
    ],
    "tgn:id":2224116,
    "tgn:name":"Cary",
    "tgn:placetype":[
        "aat:300008347"
    ]
},
  "bbox": [],
  "geometry": {"coordinates":[-90.6833,35.7167],"type":"Point"}
}