{
  "id": 1100220,
  "type": "Feature",
  "properties": {
    "tgn:hierarchy":[
        "tgn:1100220",
        "tgn:1000003",
        "tgn:7002883",
        "tgn:1000070",
        "tgn:7029392"
    ],
    "tgn:id":1100220,
    "tgn:name":"\u00c9couen, Ch\u00e2teau d'",
    "tgn:placetype":[
        "aat:300006891"
    ]
},
  "bbox": [],
  "geometry": {"coordinates":[2.3833,49.0167],"type":"Point"}
}