<<<<<<< HEAD
{
  "id": 7355639,
  "type": "Feature",
  "properties": {
    "tgn:hierarchy":[
        "tgn:7355639",
        "tgn:1000001",
        "tgn:7005600",
        "tgn:7005560",
        "tgn:7029392"
    ],
    "tgn:id":7355639,
    "tgn:name":"Ruinas Chich\u00e9n-Itz\u00e1",
    "tgn:placetype":[
        "aat:300008057"
    ]
},
  "bbox": [],
  "geometry": {"coordinates":[-88.6,20.666667],"type":"Point"}
}
=======
{"geometry":{"type":"Point","coordinates":[-88.600000,20.666667]},"type":"Feature","properties":{"hierarchy":["tgn:7355639","tgn:1000001","tgn:7005600","tgn:7005560","tgn:7029392"],"placetype":["aat:300008057"],"id":7355639,"name:xx":"Ruinas Chich\u00e9n-Itz\u00e1"}}
>>>>>>> 03f74aca74312dbeaf24d7e61306dd6a786dc3d0
