{
  "id": 2751801,
  "type": "Feature",
  "properties": {
    "tgn:hierarchy":[
        "tgn:2751801",
        "tgn:1000001",
        "tgn:7012149",
        "tgn:2000931",
        "tgn:7007515",
        "tgn:7029392"
    ],
    "tgn:id":2751801,
    "tgn:name":"Warren Island",
    "tgn:placetype":[
        "aat:300008791"
    ]
},
  "bbox": [],
  "geometry": {"coordinates":[-68.9333,44.2667],"type":"Point"}
}