{
  "id": 7310695,
  "type": "Feature",
  "properties": {
    "tgn:hierarchy":[
        "tgn:7310695",
        "tgn:1001702",
        "tgn:1000049",
        "tgn:1000002",
        "tgn:7029392"
    ],
    "tgn:id":7310695,
    "tgn:name":"Morritos, Islote",
    "tgn:placetype":[
        "aat:300008791"
    ]
},
  "bbox": [],
  "geometry": {"coordinates":[-71.35,-54.75],"type":"Point"}
}