{
  "id": 7549573,
  "type": "Feature",
  "properties": {
    "tgn:hierarchy":[
        "tgn:7549573",
        "tgn:1001828",
        "tgn:1000004",
        "tgn:7000198",
        "tgn:7029392"
    ],
    "tgn:id":7549573,
    "tgn:name:en":"Challapalle",
    "tgn:placetype":[
        "aat:300008347"
    ]
},
  "bbox": [],
  "geometry": {"coordinates":[80.933333,16.116667],"type":"Point"}
}