{
  "id": 2172651,
  "type": "Feature",
  "properties": {
    "tgn:hierarchy":[
        "tgn:2172651",
        "tgn:1000001",
        "tgn:7006451",
        "tgn:7012149",
        "tgn:2000103",
        "tgn:7029392"
    ],
    "tgn:id":2172651,
    "tgn:name":"Billingsley Reservoir Number Three",
    "tgn:placetype":[
        "aat:300006191"
    ]
},
  "bbox": [],
  "geometry": {"coordinates":[-112.85,34.2333],"type":"Point"}
}