<<<<<<< HEAD
{
  "id": 7481284,
  "type": "Feature",
  "properties": {
    "tgn:hierarchy":[
        "tgn:7481284",
        "tgn:1000004",
        "tgn:7471332",
        "tgn:1000141",
        "tgn:7029392"
    ],
    "tgn:id":7481284,
    "tgn:name":"Longfeng Qiao",
    "tgn:placetype":[
        "aat:300007836"
    ]
},
  "bbox": [],
  "geometry": {"coordinates":[121.091111,24.758889],"type":"Point"}
}
=======
{"geometry":{"type":"Point","coordinates":[121.091111,24.758889]},"type":"Feature","properties":{"hierarchy":["tgn:7481284","tgn:1000004","tgn:7471332","tgn:1000141","tgn:7029392"],"placetype":["aat:300007836"],"id":7481284,"name:xx":"Longfeng Qiao"}}
>>>>>>> 03f74aca74312dbeaf24d7e61306dd6a786dc3d0
