{
  "id": 7498248,
  "type": "Feature",
  "properties": {
    "tgn:hierarchy":[
        "tgn:7498248",
        "tgn:1000004",
        "tgn:7467799",
        "tgn:1000141",
        "tgn:7029392"
    ],
    "tgn:id":7498248,
    "tgn:name":"Taihe Guoxiao",
    "tgn:placetype":[
        "aat:300006495"
    ]
},
  "bbox": [],
  "geometry": {"coordinates":[120.551449,24.09199],"type":"Point"}
}