{
  "id": 2396182,
  "type": "Feature",
  "properties": {
    "tgn:hierarchy":[
        "tgn:2396182",
        "tgn:1002933",
        "tgn:1000001",
        "tgn:7012149",
        "tgn:7007239",
        "tgn:7029392"
    ],
    "tgn:id":2396182,
    "tgn:name":"Hollywoods Park",
    "tgn:placetype":[
        "aat:300008347"
    ]
},
  "bbox": [],
  "geometry": {"coordinates":[-75.5833,38.5333],"type":"Point"}
}