{
  "id": 7298649,
  "type": "Feature",
  "properties": {
    "tgn:hierarchy":[
        "tgn:7298649",
        "tgn:7002822",
        "tgn:1001647",
        "tgn:1000003",
        "tgn:1000095",
        "tgn:7029392"
    ],
    "tgn:id":7298649,
    "tgn:name":"Torija",
    "tgn:placetype":[
        "aat:300008347"
    ]
},
  "bbox": [],
  "geometry": {"coordinates":[-3.033333,40.75],"type":"Point"}
}