{
  "id": 1085783,
  "type": "Feature",
  "properties": {
    "tgn:hierarchy":[
        "tgn:1085783",
        "tgn:1000004",
        "tgn:1001517",
        "tgn:7018454",
        "tgn:1000144",
        "tgn:7029392"
    ],
    "tgn:id":1085783,
    "tgn:name":"\u00c7ar\u015famba",
    "tgn:placetype":[
        "aat:300008347"
    ]
},
  "bbox": [],
  "geometry": {"coordinates":[36.7167,41.2167],"type":"Point"}
}