<<<<<<< HEAD
{
  "id": 7377256,
  "type": "Feature",
  "properties": {
    "tgn:hierarchy":[
        "tgn:7377256",
        "tgn:1001853",
        "tgn:1000001",
        "tgn:7005560",
        "tgn:7029392"
    ],
    "tgn:id":7377256,
    "tgn:name":"Las Moras",
    "tgn:placetype":[
        "aat:300007783"
    ]
},
  "bbox": [],
  "geometry": {"coordinates":[-101.1,25.916667],"type":"Point"}
}
=======
{"geometry":{"type":"Point","coordinates":[-101.100000,25.916667]},"type":"Feature","properties":{"hierarchy":["tgn:7377256","tgn:1001853","tgn:1000001","tgn:7005560","tgn:7029392"],"placetype":["aat:300007783"],"id":7377256,"name:xx":"Las Moras"}}
>>>>>>> 03f74aca74312dbeaf24d7e61306dd6a786dc3d0
