{
  "id": 2587610,
  "type": "Feature",
  "properties": {
    "tgn:hierarchy":[
        "tgn:2587610",
        "tgn:1000001",
        "tgn:2000108",
        "tgn:7016172",
        "tgn:7012149",
        "tgn:7029392"
    ],
    "tgn:id":2587610,
    "tgn:name":"Pleasant Ridge",
    "tgn:placetype":[
        "aat:300266640"
    ]
},
  "bbox": [],
  "geometry": {"coordinates":[-94.05,36.3167],"type":"Point"}
}