{
  "id": 2681972,
  "type": "Feature",
  "properties": {
    "tgn:hierarchy":[
        "tgn:2681972",
        "tgn:1000001",
        "tgn:7012149",
        "tgn:2000181",
        "tgn:7007157",
        "tgn:7029392"
    ],
    "tgn:id":2681972,
    "tgn:name":"South Spit",
    "tgn:placetype":[
        "aat:300132348"
    ]
},
  "bbox": [],
  "geometry": {"coordinates":[-124.2333,40.7333],"type":"Point"}
}