{
  "id": 7047074,
  "type": "Feature",
  "properties": {
    "tgn:hierarchy":[
        "tgn:7047074",
        "tgn:7015163",
        "tgn:1000003",
        "tgn:7003121",
        "tgn:1000080",
        "tgn:7029392"
    ],
    "tgn:id":7047074,
    "tgn:name":"Fazzini, Riu",
    "tgn:placetype":[
        "aat:300008699"
    ]
},
  "bbox": [],
  "geometry": {"coordinates":[8.916667,40.883333],"type":"Point"}
}