{
  "id": 2275465,
  "type": "Feature",
  "properties": {
    "tgn:hierarchy":[
        "tgn:2275465",
        "tgn:1000001",
        "tgn:7012149",
        "tgn:2002385",
        "tgn:7007923",
        "tgn:7029392"
    ],
    "tgn:id":2275465,
    "tgn:name":"Dans Nipple",
    "tgn:placetype":[
        "aat:300008798"
    ]
},
  "bbox": [],
  "geometry": {"coordinates":[-110.4833,41.1333],"type":"Point"}
}