<<<<<<< HEAD
{
  "id": 7178184,
  "type": "Feature",
  "properties": {
    "tgn:hierarchy":[
        "tgn:7178184",
        "tgn:7003692",
        "tgn:1000003",
        "tgn:7000084",
        "tgn:7029392"
    ],
    "tgn:id":7178184,
    "tgn:name":"Hangen",
    "tgn:placetype":[
        "aat:300008347"
    ]
},
  "bbox": [],
  "geometry": {"coordinates":[9.5,47.966667],"type":"Point"}
}
=======
{"geometry":{"type":"Point","coordinates":[9.500000,47.966667]},"type":"Feature","properties":{"hierarchy":["tgn:7178184","tgn:7003692","tgn:1000003","tgn:7000084","tgn:7029392"],"placetype":["aat:300008347"],"id":7178184,"name:xx":"Hangen"}}
>>>>>>> 03f74aca74312dbeaf24d7e61306dd6a786dc3d0
