{
  "id": 7586423,
  "type": "Feature",
  "properties": {
    "tgn:hierarchy":[
        "tgn:7586423",
        "tgn:1000004",
        "tgn:7000198",
        "tgn:7000799",
        "tgn:7029392"
    ],
    "tgn:id":7586423,
    "tgn:name:en":"Erin",
    "tgn:placetype":[
        "aat:300008699"
    ]
},
  "bbox": [],
  "geometry": {"coordinates":[74.766667,34.408333],"type":"Point"}
}