{
  "id": 2776871,
  "type": "Feature",
  "properties": {
    "tgn:hierarchy":[
        "tgn:2776871",
        "tgn:7013388",
        "tgn:1000001",
        "tgn:7012149",
        "tgn:7007517",
        "tgn:7029392"
    ],
    "tgn:id":2776871,
    "tgn:name":"Windsor Pond",
    "tgn:placetype":[
        "aat:300008680"
    ]
},
  "bbox": [],
  "geometry": {"coordinates":[-72.9667,42.7333],"type":"Point"}
}