{
  "id": 7314808,
  "type": "Feature",
  "properties": {
    "tgn:hierarchy":[
        "tgn:7314808",
        "tgn:7016598",
        "tgn:1000049",
        "tgn:1000002",
        "tgn:7029392"
    ],
    "tgn:id":7314808,
    "tgn:name":"Las T\u00f3rtolas, Cerro",
    "tgn:placetype":[
        "aat:300008777",
        "aat:300008795"
    ]
},
  "bbox": [],
  "geometry": {"coordinates":[-69.95,-24.816667],"type":"Point"}
}