<<<<<<< HEAD
{
  "id": 7365636,
  "type": "Feature",
  "properties": {
    "tgn:hierarchy":[
        "tgn:7365636",
        "tgn:7005583",
        "tgn:1000001",
        "tgn:7005560",
        "tgn:7029392"
    ],
    "tgn:id":7365636,
    "tgn:name":"Front\u00f3n de los Reyes, Cerro",
    "tgn:placetype":[
        "aat:300008795"
    ]
},
  "bbox": [],
  "geometry": {"coordinates":[-105.833333,25.5],"type":"Point"}
}
=======
{"geometry":{"type":"Point","coordinates":[-105.833333,25.500000]},"type":"Feature","properties":{"hierarchy":["tgn:7365636","tgn:7005583","tgn:1000001","tgn:7005560","tgn:7029392"],"placetype":["aat:300008795"],"id":7365636,"name:xx":"Front\u00f3n de los Reyes, Cerro"}}
>>>>>>> 03f74aca74312dbeaf24d7e61306dd6a786dc3d0
