{
  "id": 2318365,
  "type": "Feature",
  "properties": {
    "tgn:hierarchy":[
        "tgn:2318365",
        "tgn:1000001",
        "tgn:7012149",
        "tgn:1002607",
        "tgn:7007706",
        "tgn:7029392"
    ],
    "tgn:id":2318365,
    "tgn:name":"Eppley Pond",
    "tgn:placetype":[
        "aat:300006191"
    ]
},
  "bbox": [],
  "geometry": {"coordinates":[-82.05,41.2167],"type":"Point"}
}