{
  "id": 2438043,
  "type": "Feature",
  "properties": {
    "tgn:hierarchy":[
        "tgn:2438043",
        "tgn:1000001",
        "tgn:2001745",
        "tgn:7012149",
        "tgn:7007712",
        "tgn:7029392"
    ],
    "tgn:id":2438043,
    "tgn:name":"King River Pond",
    "tgn:placetype":[
        "aat:300006191"
    ]
},
  "bbox": [],
  "geometry": {"coordinates":[-79.4167,33.8833],"type":"Point"}
}