{
  "id": 2733017,
  "type": "Feature",
  "properties": {
    "tgn:hierarchy":[
        "tgn:2733017",
        "tgn:1000001",
        "tgn:7012149",
        "tgn:2000650",
        "tgn:7007253",
        "tgn:7029392"
    ],
    "tgn:id":2733017,
    "tgn:name":"Turkey Island",
    "tgn:placetype":[
        "aat:300008791"
    ]
},
  "bbox": [],
  "geometry": {"coordinates":[-92.4167,41.0167],"type":"Point"}
}