{
  "id": 7585792,
  "type": "Feature",
  "properties": {
    "tgn:hierarchy":[
        "tgn:7585792",
        "tgn:1000004",
        "tgn:7000198",
        "tgn:7000799",
        "tgn:7029392"
    ],
    "tgn:id":7585792,
    "tgn:name:en":"Bangas Gali",
    "tgn:placetype":[
        "aat:300259572"
    ]
},
  "bbox": [],
  "geometry": {"coordinates":[74.089245,34.347788],"type":"Point"}
}