<<<<<<< HEAD
{
  "id": 7361410,
  "type": "Feature",
  "properties": {
    "tgn:hierarchy":[
        "tgn:7361410",
        "tgn:1000001",
        "tgn:1001960",
        "tgn:7005560",
        "tgn:7029392"
    ],
    "tgn:id":7361410,
    "tgn:name":"Rancho El Cajon del Diablo",
    "tgn:placetype":[
        "aat:300000241"
    ]
},
  "bbox": [],
  "geometry": {"coordinates":[-111.05,28.466667],"type":"Point"}
}
=======
{"geometry":{"type":"Point","coordinates":[-111.050000,28.466667]},"type":"Feature","properties":{"hierarchy":["tgn:7361410","tgn:1000001","tgn:1001960","tgn:7005560","tgn:7029392"],"placetype":["aat:300000241"],"id":7361410,"name:xx":"Rancho El Cajon del Diablo"}}
>>>>>>> 03f74aca74312dbeaf24d7e61306dd6a786dc3d0
