{
  "id": 2377507,
  "type": "Feature",
  "properties": {
    "tgn:hierarchy":[
        "tgn:2377507",
        "tgn:1000001",
        "tgn:7012149",
        "tgn:2000985",
        "tgn:7007520",
        "tgn:7029392"
    ],
    "tgn:id":2377507,
    "tgn:name":"Harper Creek",
    "tgn:placetype":[
        "aat:300008706"
    ]
},
  "bbox": [],
  "geometry": {"coordinates":[-83.9167,44.4833],"type":"Point"}
}