{
  "id": 7276969,
  "type": "Feature",
  "properties": {
    "tgn:hierarchy":[
        "tgn:7276969",
        "tgn:1001637",
        "tgn:1000049",
        "tgn:1000002",
        "tgn:7029392"
    ],
    "tgn:id":7276969,
    "tgn:name":"Viejo, R\u00edo",
    "tgn:placetype":[
        "aat:300008699"
    ]
},
  "bbox": [],
  "geometry": {"coordinates":[-72.15,-36.633333],"type":"Point"}
}