<<<<<<< HEAD
{
  "id": 2406280,
  "type": "Feature",
  "properties": {
    "tgn:hierarchy":[
        "tgn:2406280",
        "tgn:1000001",
        "tgn:7012149",
        "tgn:2000231",
        "tgn:7007158",
        "tgn:7029392"
    ],
    "tgn:id":2406280,
    "tgn:name":"Humphreys, Lake",
    "tgn:placetype":[
        "aat:300006191"
    ]
},
  "bbox": [],
  "geometry": {"coordinates":[-106.85,37.6667],"type":"Point"}
}
=======
{"geometry":{"type":"Point","coordinates":[-106.850000,37.666700]},"type":"Feature","properties":{"hierarchy":["tgn:2406280","tgn:1000001","tgn:7012149","tgn:2000231","tgn:7007158","tgn:7029392"],"placetype":["aat:300006191"],"id":2406280,"name:xx":"Humphreys, Lake"}}
>>>>>>> 03f74aca74312dbeaf24d7e61306dd6a786dc3d0
