<<<<<<< HEAD
{
  "id": 2764574,
  "type": "Feature",
  "properties": {
    "tgn:hierarchy":[
        "tgn:2764574",
        "tgn:1000001",
        "tgn:7012149",
        "tgn:2000822",
        "tgn:7007255",
        "tgn:7029392"
    ],
    "tgn:id":2764574,
    "tgn:name":"Whippoorwill Branch",
    "tgn:placetype":[
        "aat:300008699"
    ]
},
  "bbox": [],
  "geometry": {"coordinates":[-85.05,37.4167],"type":"Point"}
}
=======
{"geometry":{"type":"Point","coordinates":[-85.050000,37.416700]},"type":"Feature","properties":{"hierarchy":["tgn:2764574","tgn:1000001","tgn:7012149","tgn:2000822","tgn:7007255","tgn:7029392"],"placetype":["aat:300008699"],"id":2764574,"name:xx":"Whippoorwill Branch"}}
>>>>>>> 03f74aca74312dbeaf24d7e61306dd6a786dc3d0
