{
  "id": 7138979,
  "type": "Feature",
  "properties": {
    "tgn:hierarchy":[
        "tgn:7138979",
        "tgn:7003669",
        "tgn:1000003",
        "tgn:7000084",
        "tgn:7029392"
    ],
    "tgn:id":7138979,
    "tgn:name":"Lauterbach",
    "tgn:placetype":[
        "aat:300008347"
    ]
},
  "bbox": [],
  "geometry": {"coordinates":[10.883333,47.716667],"type":"Point"}
}