{
  "id": 2154545,
  "type": "Feature",
  "properties": {
    "tgn:hierarchy":[
        "tgn:2154545",
        "tgn:2000855",
        "tgn:1000001",
        "tgn:7012149",
        "tgn:7007256",
        "tgn:7029392"
    ],
    "tgn:id":2154545,
    "tgn:name":"Bear Creek Watershed Number 1",
    "tgn:placetype":[
        "aat:300006191"
    ]
},
  "bbox": [],
  "geometry": {"coordinates":[-93.0167,30.5667],"type":"Point"}
}