{
  "id": 2473286,
  "type": "Feature",
  "properties": {
    "tgn:hierarchy":[
        "tgn:2473286",
        "tgn:1002366",
        "tgn:1000001",
        "tgn:7012149",
        "tgn:7007159",
        "tgn:7029392"
    ],
    "tgn:id":2473286,
    "tgn:name":"Lower Belden Hill",
    "tgn:placetype":[
        "aat:300008798"
    ]
},
  "bbox": [],
  "geometry": {"coordinates":[-73.4333,41.15],"type":"Point"}
}