{
  "id": 7155034,
  "type": "Feature",
  "properties": {
    "tgn:hierarchy":[
        "tgn:7155034",
        "tgn:7003669",
        "tgn:1000003",
        "tgn:7000084",
        "tgn:7029392"
    ],
    "tgn:id":7155034,
    "tgn:name":"Kirch Holz",
    "tgn:placetype":[
        "aat:300008863"
    ]
},
  "bbox": [],
  "geometry": {"coordinates":[13.766667,48.583333],"type":"Point"}
}