{
  "id": 2366486,
  "type": "Feature",
  "properties": {
    "tgn:hierarchy":[
        "tgn:2366486",
        "tgn:1000001",
        "tgn:7012149",
        "tgn:7007157",
        "tgn:2000187",
        "tgn:7029392"
    ],
    "tgn:id":2366486,
    "tgn:name":"Grigsby Spring",
    "tgn:placetype":[
        "aat:300008697"
    ]
},
  "bbox": [],
  "geometry": {"coordinates":[-120.2167,39.9333],"type":"Point"}
}