{
  "id": 1040199,
  "type": "Feature",
  "properties": {
    "tgn:hierarchy":[
        "tgn:1040199",
        "tgn:1000003",
        "tgn:7003678",
        "tgn:7000084",
        "tgn:7029392"
    ],
    "tgn:id":1040199,
    "tgn:name":"M\u00fchlheim",
    "tgn:placetype":[
        "aat:300008347"
    ]
},
  "bbox": [],
  "geometry": {"coordinates":[8.833333,50.116667],"type":"Point"}
}