{
  "id": 7551172,
  "type": "Feature",
  "properties": {
    "tgn:hierarchy":[
        "tgn:7551172",
        "tgn:7001819",
        "tgn:1000004",
        "tgn:7000198",
        "tgn:7029392"
    ],
    "tgn:id":7551172,
    "tgn:name:en":"Dir\u0101ng",
    "tgn:placetype":[
        "aat:300008347"
    ]
},
  "bbox": [],
  "geometry": {"coordinates":[92.266667,27.333333],"type":"Point"}
}