{
  "id": 2523573,
  "type": "Feature",
  "properties": {
    "tgn:hierarchy":[
        "tgn:2523573",
        "tgn:1000001",
        "tgn:2000923",
        "tgn:7012149",
        "tgn:7007515",
        "tgn:7029392"
    ],
    "tgn:id":2523573,
    "tgn:name":"Moose Pond",
    "tgn:placetype":[
        "aat:300008680"
    ]
},
  "bbox": [],
  "geometry": {"coordinates":[-69.95,44.4667],"type":"Point"}
}