<<<<<<< HEAD
{
  "id": 7367557,
  "type": "Feature",
  "properties": {
    "tgn:hierarchy":[
        "tgn:7367557",
        "tgn:1000001",
        "tgn:1001960",
        "tgn:7005560",
        "tgn:7029392"
    ],
    "tgn:id":7367557,
    "tgn:name":"El Valiente",
    "tgn:placetype":[
        "aat:300008347"
    ]
},
  "bbox": [],
  "geometry": {"coordinates":[-110.95,28.016667],"type":"Point"}
}
=======
{"geometry":{"type":"Point","coordinates":[-110.950000,28.016667]},"type":"Feature","properties":{"hierarchy":["tgn:7367557","tgn:1000001","tgn:1001960","tgn:7005560","tgn:7029392"],"placetype":["aat:300008347"],"id":7367557,"name:xx":"El Valiente"}}
>>>>>>> 03f74aca74312dbeaf24d7e61306dd6a786dc3d0
