{
  "id": 7448537,
  "type": "Feature",
  "properties": {
    "tgn:hierarchy":[
        "tgn:7448537",
        "tgn:7002445",
        "tgn:1000003",
        "tgn:7008180",
        "tgn:7008591",
        "tgn:7029392"
    ],
    "tgn:id":7448537,
    "tgn:name:en":"Rowde",
    "tgn:placetype":[
        "aat:300008347"
    ]
},
  "bbox": [],
  "geometry": {"coordinates":[-2.033889,51.363056],"type":"Point"}
}