{
  "id": 2532722,
  "type": "Feature",
  "properties": {
    "tgn:hierarchy":[
        "tgn:2532722",
        "tgn:1000001",
        "tgn:7012149",
        "tgn:2000800",
        "tgn:7007255",
        "tgn:7029392"
    ],
    "tgn:id":2532722,
    "tgn:name":"Murphy Pond",
    "tgn:placetype":[
        "aat:300008680"
    ]
},
  "bbox": [],
  "geometry": {"coordinates":[-88.85,36.7333],"type":"Point"}
}