{
  "id": 7237332,
  "type": "Feature",
  "properties": {
    "tgn:hierarchy":[
        "tgn:7237332",
        "tgn:7002680",
        "tgn:7001395",
        "tgn:1000003",
        "tgn:1000074",
        "tgn:7029392"
    ],
    "tgn:id":7237332,
    "tgn:name":"\u00c1yioi The\u00f3dhoroi",
    "tgn:placetype":[
        "aat:300008347"
    ]
},
  "bbox": [],
  "geometry": {"coordinates":[21.316667,38.966667],"type":"Point"}
}