{
  "id": 1043437,
  "type": "Feature",
  "properties": {
    "tgn:hierarchy":[
        "tgn:1043437",
        "tgn:1003505",
        "tgn:1000003",
        "tgn:7002993",
        "tgn:1000080",
        "tgn:7029392"
    ],
    "tgn:id":1043437,
    "tgn:name":"Basovizza",
    "tgn:placetype":[
        "aat:300008347"
    ]
},
  "bbox": [],
  "geometry": {"coordinates":[13.863889,45.643889],"type":"Point"}
}