{
  "id": 2218362,
  "type": "Feature",
  "properties": {
    "tgn:hierarchy":[
        "tgn:2218362",
        "tgn:1000001",
        "tgn:7012149",
        "tgn:2001714",
        "tgn:7007708",
        "tgn:7029392"
    ],
    "tgn:id":2218362,
    "tgn:name":"Canby Mountains",
    "tgn:placetype":[
        "aat:300386831"
    ]
},
  "bbox": [],
  "geometry": {"coordinates":[-121.8167,42.5167],"type":"Point"}
}