{
  "id": 2138964,
  "type": "Feature",
  "properties": {
    "tgn:hierarchy":[
        "tgn:2138964",
        "tgn:1000001",
        "tgn:7012149",
        "tgn:1002617",
        "tgn:7007520",
        "tgn:7029392"
    ],
    "tgn:id":2138964,
    "tgn:name":"Ashery Creek",
    "tgn:placetype":[
        "aat:300008706"
    ]
},
  "bbox": [],
  "geometry": {"coordinates":[-82.85,42.8833],"type":"Point"}
}