{
  "id": 7014258,
  "type": "Feature",
  "properties": {
    "tgn:hierarchy":[
        "tgn:7014258",
        "tgn:1000001",
        "tgn:7016172",
        "tgn:7012149",
        "tgn:2000176",
        "tgn:7029392"
    ],
    "tgn:id":7014258,
    "tgn:name":"Fayetteville",
    "tgn:placetype":[
        "aat:300387277",
        "aat:300008347",
        "aat:300008416",
        "aat:300008389",
        "aat:300387308",
        "aat:300264742",
        "aat:300000547"
    ]
},
  "bbox": [],
  "geometry": {"coordinates":[-94.15,36.05],"type":"Point"}
}