{
  "id": 2340725,
  "type": "Feature",
  "properties": {
    "tgn:hierarchy":[
        "tgn:2340725",
        "tgn:7013313",
        "tgn:1000001",
        "tgn:7012149",
        "tgn:7007826",
        "tgn:7029392"
    ],
    "tgn:id":2340725,
    "tgn:name":"Fresh Water Lake",
    "tgn:placetype":[
        "aat:300008680"
    ]
},
  "bbox": [],
  "geometry": {"coordinates":[-97.1833,28.0167],"type":"Point"}
}