{
  "id": 7428420,
  "type": "Feature",
  "properties": {
    "tgn:hierarchy":[
        "tgn:7428420",
        "tgn:7005581",
        "tgn:1000001",
        "tgn:7005560",
        "tgn:7029392"
    ],
    "tgn:id":7428420,
    "tgn:name":"Guadalupe Saucer\u00eda",
    "tgn:placetype":[
        "aat:300008347"
    ]
},
  "bbox": [],
  "geometry": {"coordinates":[-106.65,27.966667],"type":"Point"}
}