{
  "id": 1025845,
  "type": "Feature",
  "properties": {
    "tgn:hierarchy":[
        "tgn:1025845",
        "tgn:7003029",
        "tgn:1000003",
        "tgn:1000062",
        "tgn:7029392"
    ],
    "tgn:id":1025845,
    "tgn:name":"Mayrhofen",
    "tgn:placetype":[
        "aat:300008347"
    ]
},
  "bbox": [],
  "geometry": {"coordinates":[11.8667,47.1667],"type":"Point"}
}