{
  "id": 2500773,
  "type": "Feature",
  "properties": {
    "tgn:hierarchy":[
        "tgn:2500773",
        "tgn:1000001",
        "tgn:7012149",
        "tgn:2001223",
        "tgn:7007523",
        "tgn:7029392"
    ],
    "tgn:id":2500773,
    "tgn:name":"McElhany",
    "tgn:placetype":[
        "aat:300008347"
    ]
},
  "bbox": [],
  "geometry": {"coordinates":[-94.3833,36.7833],"type":"Point"}
}