{
  "id": 2691787,
  "type": "Feature",
  "properties": {
    "tgn:hierarchy":[
        "tgn:2691787",
        "tgn:7006450",
        "tgn:1000001",
        "tgn:2124012",
        "tgn:7012149",
        "tgn:7029392"
    ],
    "tgn:id":2691787,
    "tgn:name":"Starr Point",
    "tgn:placetype":[
        "aat:300008850"
    ]
},
  "bbox": [],
  "geometry": {"coordinates":[-153.35,57.75],"type":"Point"}
}