{
  "id": 2649831,
  "type": "Feature",
  "properties": {
    "tgn:hierarchy":[
        "tgn:2649831",
        "tgn:1000001",
        "tgn:7012149",
        "tgn:2000421",
        "tgn:7007248",
        "tgn:7029392"
    ],
    "tgn:id":2649831,
    "tgn:name":"Scroggins Branch",
    "tgn:placetype":[
        "aat:300008699"
    ]
},
  "bbox": [],
  "geometry": {"coordinates":[-84.6167,32.6333],"type":"Point"}
}