<<<<<<< HEAD
{
  "id": 7052138,
  "type": "Feature",
  "properties": {
    "tgn:hierarchy":[
        "tgn:7052138",
        "tgn:7003166",
        "tgn:1000003",
        "tgn:7009760",
        "tgn:1000080",
        "tgn:7029392"
    ],
    "tgn:id":7052138,
    "tgn:name":"La Casetta",
    "tgn:placetype":[
        "aat:300008347"
    ]
},
  "bbox": [],
  "geometry": {"coordinates":[10.683333,43.5],"type":"Point"}
}
=======
{"geometry":{"type":"Point","coordinates":[10.683333,43.500000]},"type":"Feature","properties":{"hierarchy":["tgn:7052138","tgn:7003166","tgn:1000003","tgn:7009760","tgn:1000080","tgn:7029392"],"placetype":["aat:300008347"],"id":7052138,"name:xx":"La Casetta"}}
>>>>>>> 03f74aca74312dbeaf24d7e61306dd6a786dc3d0
