<<<<<<< HEAD
{
  "id": 7053747,
  "type": "Feature",
  "properties": {
    "tgn:hierarchy":[
        "tgn:7053747",
        "tgn:1003500",
        "tgn:1000003",
        "tgn:7010380",
        "tgn:1000080",
        "tgn:7029392"
    ],
    "tgn:id":7053747,
    "tgn:name":"Macchiapiana, Lago",
    "tgn:placetype":[
        "aat:300008680"
    ]
},
  "bbox": [],
  "geometry": {"coordinates":[16.8,40.5],"type":"Point"}
}
=======
{"geometry":{"type":"Point","coordinates":[16.800000,40.500000]},"type":"Feature","properties":{"hierarchy":["tgn:7053747","tgn:1003500","tgn:1000003","tgn:7010380","tgn:1000080","tgn:7029392"],"placetype":["aat:300008680"],"id":7053747,"name:xx":"Macchiapiana, Lago"}}
>>>>>>> 03f74aca74312dbeaf24d7e61306dd6a786dc3d0
