{
  "id": 2579734,
  "type": "Feature",
  "properties": {
    "tgn:hierarchy":[
        "tgn:2579734",
        "tgn:1000001",
        "tgn:7016172",
        "tgn:7012149",
        "tgn:2000137",
        "tgn:7029392"
    ],
    "tgn:id":2579734,
    "tgn:name":"Picnic Hollow",
    "tgn:placetype":[
        "aat:300008761"
    ]
},
  "bbox": [],
  "geometry": {"coordinates":[-92.1667,36.1167],"type":"Point"}
}