{
  "id": 2220631,
  "type": "Feature",
  "properties": {
    "tgn:hierarchy":[
        "tgn:2220631",
        "tgn:1000001",
        "tgn:7012149",
        "tgn:7014318",
        "tgn:7007568",
        "tgn:7029392"
    ],
    "tgn:id":2220631,
    "tgn:name":"Cape Wykoff",
    "tgn:placetype":[
        "aat:300008798"
    ]
},
  "bbox": [],
  "geometry": {"coordinates":[-74.7833,42.8167],"type":"Point"}
}