{
  "id": 7485302,
  "type": "Feature",
  "properties": {
    "tgn:hierarchy":[
        "tgn:7485302",
        "tgn:1000004",
        "tgn:7467799",
        "tgn:1000141",
        "tgn:7029392"
    ],
    "tgn:id":7485302,
    "tgn:name":"Maxing Qiao",
    "tgn:placetype":[
        "aat:300007836"
    ]
},
  "bbox": [],
  "geometry": {"coordinates":[120.496111,24.06],"type":"Point"}
}