{
  "id": 7217895,
  "type": "Feature",
  "properties": {
    "tgn:hierarchy":[
        "tgn:7217895",
        "tgn:7011161",
        "tgn:7002674",
        "tgn:1000003",
        "tgn:1000074",
        "tgn:7029392"
    ],
    "tgn:id":7217895,
    "tgn:name":"\u00c1gios Is\u00eddoros",
    "tgn:placetype":[
        "aat:300008347"
    ]
},
  "bbox": [],
  "geometry": {"coordinates":[26.026944,38.461111],"type":"Point"}
}