{
  "id": 2754069,
  "type": "Feature",
  "properties": {
    "tgn:hierarchy":[
        "tgn:2754069",
        "tgn:1000001",
        "tgn:7012149",
        "tgn:2000344",
        "tgn:7007248",
        "tgn:7029392"
    ],
    "tgn:id":2754069,
    "tgn:name":"Watson Pond",
    "tgn:placetype":[
        "aat:300006191"
    ]
},
  "bbox": [],
  "geometry": {"coordinates":[-82.1167,32.5333],"type":"Point"}
}