{
  "id": 7035227,
  "type": "Feature",
  "properties": {
    "tgn:hierarchy":[
        "tgn:7035227",
        "tgn:7002995",
        "tgn:1000003",
        "tgn:7002997",
        "tgn:1000080",
        "tgn:7029392"
    ],
    "tgn:id":7035227,
    "tgn:name":"Polesano",
    "tgn:placetype":[
        "aat:300008760"
    ]
},
  "bbox": [],
  "geometry": {"coordinates":[12.1525,45.031111],"type":"Point"}
}