{
  "id": 7589393,
  "type": "Feature",
  "properties": {
    "tgn:hierarchy":[
        "tgn:7589393",
        "tgn:1000004",
        "tgn:7000198",
        "tgn:7000799",
        "tgn:7029392"
    ],
    "tgn:id":7589393,
    "tgn:name:en":"Gutilb\u0101gh Forest",
    "tgn:placetype":[
        "aat:300008863"
    ]
},
  "bbox": [],
  "geometry": {"coordinates":[74.841667,34.277778],"type":"Point"}
}