{
  "id": 2657992,
  "type": "Feature",
  "properties": {
    "tgn:hierarchy":[
        "tgn:2657992",
        "tgn:1000001",
        "tgn:2000952",
        "tgn:7012149",
        "tgn:7007520",
        "tgn:7029392"
    ],
    "tgn:id":2657992,
    "tgn:name":"Shelldrake River",
    "tgn:placetype":[
        "aat:300008707"
    ]
},
  "bbox": [],
  "geometry": {"coordinates":[-85.2333,46.6333],"type":"Point"}
}