{
  "id": 7594329,
  "type": "Feature",
  "properties": {
    "tgn:hierarchy":[
        "tgn:7594329",
        "tgn:1000003",
        "tgn:7006667",
        "tgn:7029392"
    ],
    "tgn:id":7594329,
    "tgn:name":"Demir Kapija",
    "tgn:placetype":[
        "aat:300387064",
        "aat:300265612"
    ]
},
  "bbox": [],
  "geometry": {"coordinates":[22.25,41.383333],"type":"Point"}
}