<<<<<<< HEAD
{
  "id": 2257657,
  "type": "Feature",
  "properties": {
    "tgn:hierarchy":[
        "tgn:2257657",
        "tgn:1000001",
        "tgn:7012149",
        "tgn:2001711",
        "tgn:7007708",
        "tgn:7029392"
    ],
    "tgn:id":2257657,
    "tgn:name":"Corral Creek",
    "tgn:placetype":[
        "aat:300008706"
    ]
},
  "bbox": [],
  "geometry": {"coordinates":[-122.4167,42.1333],"type":"Point"}
}
=======
{"geometry":{"type":"Point","coordinates":[-122.416700,42.133300]},"type":"Feature","properties":{"hierarchy":["tgn:2257657","tgn:1000001","tgn:7012149","tgn:2001711","tgn:7007708","tgn:7029392"],"placetype":["aat:300008706"],"id":2257657,"name:xx":"Corral Creek"}}
>>>>>>> 03f74aca74312dbeaf24d7e61306dd6a786dc3d0
