{
  "id": 2104485,
  "type": "Feature",
  "properties": {
    "tgn:hierarchy":[
        "tgn:2104485",
        "tgn:1000001",
        "tgn:7012149",
        "tgn:2002024",
        "tgn:7007826",
        "tgn:7029392"
    ],
    "tgn:id":2104485,
    "tgn:name":"Glory",
    "tgn:placetype":[
        "aat:300008347",
        "aat:300387210"
    ]
},
  "bbox": [],
  "geometry": {"coordinates":[-95.5333,33.5333],"type":"Point"}
}