{
  "id": 7053036,
  "type": "Feature",
  "properties": {
    "tgn:hierarchy":[
        "tgn:7053036",
        "tgn:1003468",
        "tgn:1000003",
        "tgn:7010380",
        "tgn:1000080",
        "tgn:7029392"
    ],
    "tgn:id":7053036,
    "tgn:name":"Pat\u00f9",
    "tgn:placetype":[
        "aat:300008347"
    ]
},
  "bbox": [],
  "geometry": {"coordinates":[18.333333,39.833333],"type":"Point"}
}