{
  "id": 7593907,
  "type": "Feature",
  "properties": {
    "tgn:hierarchy":[
        "tgn:7593907",
        "tgn:7005583",
        "tgn:1000001",
        "tgn:7005560",
        "tgn:7029392"
    ],
    "tgn:id":7593907,
    "tgn:name":"San Pedro de los Pinos",
    "tgn:placetype":[
        "aat:300008347"
    ]
},
  "bbox": [],
  "geometry": {"coordinates":[-104.885922,23.815982],"type":"Point"}
}