{
  "id": 2501999,
  "type": "Feature",
  "properties": {
    "tgn:hierarchy":[
        "tgn:2501999",
        "tgn:1000001",
        "tgn:7012149",
        "tgn:7007256",
        "tgn:7029392"
    ],
    "tgn:id":2501999,
    "tgn:name":"McKemb Branch",
    "tgn:placetype":[
        "aat:300008699"
    ]
},
  "bbox": [],
  "geometry": {"coordinates":[-92.5667,30.9333],"type":"Point"}
}