{
  "id": 2467536,
  "type": "Feature",
  "properties": {
    "tgn:hierarchy":[
        "tgn:2467536",
        "tgn:1000001",
        "tgn:7012149",
        "tgn:2001856",
        "tgn:7007825",
        "tgn:7029392"
    ],
    "tgn:id":2467536,
    "tgn:name":"Long Hollow",
    "tgn:placetype":[
        "aat:300008761"
    ]
},
  "bbox": [],
  "geometry": {"coordinates":[-88.05,35.4833],"type":"Point"}
}