{
  "id": 7405475,
  "type": "Feature",
  "properties": {
    "tgn:hierarchy":[
        "tgn:7405475",
        "tgn:7005585",
        "tgn:1000001",
        "tgn:7005560",
        "tgn:7029392"
    ],
    "tgn:id":7405475,
    "tgn:name":"El Encanto, Barranca",
    "tgn:placetype":[
        "aat:300008767"
    ]
},
  "bbox": [],
  "geometry": {"coordinates":[-100.033333,17.65],"type":"Point"}
}