{
  "id": 2263490,
  "type": "Feature",
  "properties": {
    "tgn:hierarchy":[
        "tgn:2263490",
        "tgn:1000001",
        "tgn:1002218",
        "tgn:7012149",
        "tgn:7007157",
        "tgn:7029392"
    ],
    "tgn:id":2263490,
    "tgn:name":"Cox Spillway",
    "tgn:placetype":[
        "aat:300006075"
    ]
},
  "bbox": [],
  "geometry": {"coordinates":[-121.6333,39.3333],"type":"Point"}
}