{
  "id": 2684797,
  "type": "Feature",
  "properties": {
    "tgn:hierarchy":[
        "tgn:2684797",
        "tgn:1000001",
        "tgn:7012149",
        "tgn:2000232",
        "tgn:7007158",
        "tgn:7029392"
    ],
    "tgn:id":2684797,
    "tgn:name":"Spitzie Spring",
    "tgn:placetype":[
        "aat:300008697"
    ]
},
  "bbox": [],
  "geometry": {"coordinates":[-108.9333,40.9167],"type":"Point"}
}