{
  "id": 2355468,
  "type": "Feature",
  "properties": {
    "tgn:hierarchy":[
        "tgn:2355468",
        "tgn:1002177",
        "tgn:1000001",
        "tgn:7012149",
        "tgn:7007252",
        "tgn:7029392"
    ],
    "tgn:id":2355468,
    "tgn:name":"Goose Creek",
    "tgn:placetype":[
        "aat:300008706"
    ]
},
  "bbox": [],
  "geometry": {"coordinates":[-87.3833,40.4833],"type":"Point"}
}