{
  "id": 1049112,
  "type": "Feature",
  "properties": {
    "tgn:hierarchy":[
        "tgn:1049112",
        "tgn:1000003",
        "tgn:7024115",
        "tgn:7006366",
        "tgn:7029392"
    ],
    "tgn:id":1049112,
    "tgn:name":"Ke\u031cpice",
    "tgn:placetype":[
        "aat:300008347"
    ]
},
  "bbox": [],
  "geometry": {"coordinates":[16.8667,54.2333],"type":"Point"}
}