{
  "id": 7171181,
  "type": "Feature",
  "properties": {
    "tgn:hierarchy":[
        "tgn:7171181",
        "tgn:1000003",
        "tgn:7000094",
        "tgn:7000084",
        "tgn:7029392"
    ],
    "tgn:id":7171181,
    "tgn:name":"Herzberg",
    "tgn:placetype":[
        "aat:300008347"
    ]
},
  "bbox": [],
  "geometry": {"coordinates":[11.933333,53.533333],"type":"Point"}
}