{
  "id": 7355906,
  "type": "Feature",
  "properties": {
    "tgn:hierarchy":[
        "tgn:7355906",
        "tgn:7005583",
        "tgn:1000001",
        "tgn:7005560",
        "tgn:7029392"
    ],
    "tgn:id":7355906,
    "tgn:name":"Carboneras",
    "tgn:placetype":[
        "aat:300008347"
    ]
},
  "bbox": [],
  "geometry": {"coordinates":[-103.961111,24.191111],"type":"Point"}
}