{
  "id": 2261439,
  "type": "Feature",
  "properties": {
    "tgn:hierarchy":[
        "tgn:2261439",
        "tgn:1000001",
        "tgn:7012149",
        "tgn:1002667",
        "tgn:7007919",
        "tgn:7029392"
    ],
    "tgn:id":2261439,
    "tgn:name":"Courthouse Swamp",
    "tgn:placetype":[
        "aat:300008699"
    ]
},
  "bbox": [],
  "geometry": {"coordinates":[-76.5667,37.5833],"type":"Point"}
}