{
  "id": 2078060,
  "type": "Feature",
  "properties": {
    "tgn:hierarchy":[
        "tgn:2078060",
        "tgn:1000001",
        "tgn:2001594",
        "tgn:7012149",
        "tgn:7007705",
        "tgn:7029392"
    ],
    "tgn:id":2078060,
    "tgn:name":"Tolley",
    "tgn:placetype":[
        "aat:300008347"
    ]
},
  "bbox": [],
  "geometry": {"coordinates":[-101.8167,48.7167],"type":"Point"}
}