{
  "id": 2376004,
  "type": "Feature",
  "properties": {
    "tgn:hierarchy":[
        "tgn:2376004",
        "tgn:1000001",
        "tgn:7012149",
        "tgn:7007157",
        "tgn:1002566",
        "tgn:7029392"
    ],
    "tgn:id":2376004,
    "tgn:name":"Harbin Mountain",
    "tgn:placetype":[
        "aat:300008798"
    ]
},
  "bbox": [],
  "geometry": {"coordinates":[-122.6333,38.7833],"type":"Point"}
}