{
  "id": 7025492,
  "type": "Feature",
  "properties": {
    "tgn:hierarchy":[
        "tgn:7025492",
        "tgn:7002445",
        "tgn:1000003",
        "tgn:7012077",
        "tgn:7008591",
        "tgn:7029392"
    ],
    "tgn:id":7025492,
    "tgn:name:ang":"Clist",
    "tgn:placetype":[
        "aat:300008347"
    ]
},
  "bbox": [],
  "geometry": {"coordinates":[-3.4333,50.6833],"type":"Point"}
}