{
  "id": 7279794,
  "type": "Feature",
  "properties": {
    "tgn:hierarchy":[
        "tgn:7279794",
        "tgn:1001699",
        "tgn:1000049",
        "tgn:1000002",
        "tgn:7029392"
    ],
    "tgn:id":7279794,
    "tgn:name":"Remehue, R\u00edo",
    "tgn:placetype":[
        "aat:300008699"
    ]
},
  "bbox": [],
  "geometry": {"coordinates":[-72.516667,-39.966667],"type":"Point"}
}