{
  "id": 7415050,
  "type": "Feature",
  "properties": {
    "tgn:hierarchy":[
        "tgn:7415050",
        "tgn:1000001",
        "tgn:7005591",
        "tgn:7005560",
        "tgn:7029392"
    ],
    "tgn:id":7415050,
    "tgn:name:es":"Tepehuaje",
    "tgn:placetype":[
        "aat:300008347"
    ]
},
  "bbox": [],
  "geometry": {"coordinates":[-96.630556,16.544444],"type":"Point"}
}