{
  "id": 7183488,
  "type": "Feature",
  "properties": {
    "tgn:hierarchy":[
        "tgn:7183488",
        "tgn:1000003",
        "tgn:7003676",
        "tgn:7000084",
        "tgn:7029392"
    ],
    "tgn:id":7183488,
    "tgn:name":"Gilmerdingen",
    "tgn:placetype":[
        "aat:300008347"
    ]
},
  "bbox": [],
  "geometry": {"coordinates":[9.733333,53.05],"type":"Point"}
}