<<<<<<< HEAD
{
  "id": 2259215,
  "type": "Feature",
  "properties": {
    "tgn:hierarchy":[
        "tgn:2259215",
        "tgn:1000001",
        "tgn:2001331",
        "tgn:7012149",
        "tgn:7007525",
        "tgn:7029392"
    ],
    "tgn:id":2259215,
    "tgn:name":"Cottonwood Lake",
    "tgn:placetype":[
        "aat:300008680"
    ]
},
  "bbox": [],
  "geometry": {"coordinates":[-101.6833,42.4167],"type":"Point"}
}
=======
{"geometry":{"type":"Point","coordinates":[-101.683300,42.416700]},"type":"Feature","properties":{"hierarchy":["tgn:2259215","tgn:1000001","tgn:2001331","tgn:7012149","tgn:7007525","tgn:7029392"],"placetype":["aat:300008680"],"id":2259215,"name:xx":"Cottonwood Lake"}}
>>>>>>> 03f74aca74312dbeaf24d7e61306dd6a786dc3d0
