{
  "id": 1029199,
  "type": "Feature",
  "properties": {
    "tgn:hierarchy":[
        "tgn:1029199",
        "tgn:7002445",
        "tgn:1000003",
        "tgn:7008185",
        "tgn:7008591",
        "tgn:7029392"
    ],
    "tgn:id":1029199,
    "tgn:name:en":"Exning",
    "tgn:placetype":[
        "aat:300008347"
    ]
},
  "bbox": [],
  "geometry": {"coordinates":[0.35,52.266667],"type":"Point"}
}