<<<<<<< HEAD
{
  "id": 2258118,
  "type": "Feature",
  "properties": {
    "tgn:hierarchy":[
        "tgn:2258118",
        "tgn:1000001",
        "tgn:7012149",
        "tgn:2002249",
        "tgn:7007920",
        "tgn:7029392"
    ],
    "tgn:id":2258118,
    "tgn:name":"Cossalman Lake",
    "tgn:placetype":[
        "aat:300008680"
    ]
},
  "bbox": [],
  "geometry": {"coordinates":[-117.5833,47.4333],"type":"Point"}
}
=======
{"geometry":{"type":"Point","coordinates":[-117.583300,47.433300]},"type":"Feature","properties":{"hierarchy":["tgn:2258118","tgn:1000001","tgn:7012149","tgn:2002249","tgn:7007920","tgn:7029392"],"placetype":["aat:300008680"],"id":2258118,"name:xx":"Cossalman Lake"}}
>>>>>>> 03f74aca74312dbeaf24d7e61306dd6a786dc3d0
