{
  "id": 2258118,
  "type": "Feature",
  "properties": {
    "tgn:hierarchy":[
        "tgn:2258118",
        "tgn:1000001",
        "tgn:7012149",
        "tgn:2002249",
        "tgn:7007920",
        "tgn:7029392"
    ],
    "tgn:id":2258118,
    "tgn:name":"Cossalman Lake",
    "tgn:placetype":[
        "aat:300008680"
    ]
},
  "bbox": [],
  "geometry": {"coordinates":[-117.5833,47.4333],"type":"Point"}
}