{
  "id": 7133168,
  "type": "Feature",
  "properties": {
    "tgn:hierarchy":[
        "tgn:7133168",
        "tgn:1000003",
        "tgn:7003676",
        "tgn:7000084",
        "tgn:7029392"
    ],
    "tgn:id":7133168,
    "tgn:name":"M\u00fchlenbach",
    "tgn:placetype":[
        "aat:300008699"
    ]
},
  "bbox": [],
  "geometry": {"coordinates":[10.133333,53.366667],"type":"Point"}
}