{
  "id": 1089306,
  "type": "Feature",
  "properties": {
    "tgn:hierarchy":[
        "tgn:1089306",
        "tgn:7001242",
        "tgn:7016755",
        "tgn:1000159",
        "tgn:7029392"
    ],
    "tgn:id":1089306,
    "tgn:name":"Mambasa",
    "tgn:placetype":[
        "aat:300008347"
    ]
},
  "bbox": [],
  "geometry": {"coordinates":[29.0833,1.3333],"type":"Point"}
}