{
  "id": 2698758,
  "type": "Feature",
  "properties": {
    "tgn:hierarchy":[
        "tgn:2698758",
        "tgn:1000001",
        "tgn:7012149",
        "tgn:1003038",
        "tgn:7007517",
        "tgn:7029392"
    ],
    "tgn:id":2698758,
    "tgn:name":"Straw Hollow",
    "tgn:placetype":[
        "aat:300008905"
    ]
},
  "bbox": [],
  "geometry": {"coordinates":[-71.6833,42.3333],"type":"Point"}
}