{
  "id": 2729482,
  "type": "Feature",
  "properties": {
    "tgn:hierarchy":[
        "tgn:2729482",
        "tgn:1000001",
        "tgn:2000265",
        "tgn:7012149",
        "tgn:7007240",
        "tgn:7029392"
    ],
    "tgn:id":2729482,
    "tgn:name":"Tristan Village",
    "tgn:placetype":[
        "aat:300008347"
    ]
},
  "bbox": [],
  "geometry": {"coordinates":[-87.25,30.45],"type":"Point"}
}