{
  "id": 2357859,
  "type": "Feature",
  "properties": {
    "tgn:hierarchy":[
        "tgn:2357859",
        "tgn:1000001",
        "tgn:7012149",
        "tgn:1002607",
        "tgn:7007706",
        "tgn:7029392"
    ],
    "tgn:id":2357859,
    "tgn:name":"Grafton Reservoir",
    "tgn:placetype":[
        "aat:300006191"
    ]
},
  "bbox": [],
  "geometry": {"coordinates":[-82.0333,41.2667],"type":"Point"}
}