{
  "id": 2689451,
  "type": "Feature",
  "properties": {
    "tgn:hierarchy":[
        "tgn:2689451",
        "tgn:1000001",
        "tgn:7012149",
        "tgn:2001713",
        "tgn:7007708",
        "tgn:7029392"
    ],
    "tgn:id":2689451,
    "tgn:name":"Squaw Gulch",
    "tgn:placetype":[
        "aat:300008761"
    ]
},
  "bbox": [],
  "geometry": {"coordinates":[-123.5167,42.3667],"type":"Point"}
}