{
  "id": 1135712,
  "type": "Feature",
  "properties": {
    "tgn:hierarchy":[
        "tgn:1135712",
        "tgn:1001944",
        "tgn:1000047",
        "tgn:7002456",
        "tgn:1000002",
        "tgn:7029392"
    ],
    "tgn:id":1135712,
    "tgn:name":"Tracaj\u00e1, Cachoeira",
    "tgn:placetype":[
        "aat:300008736"
    ]
},
  "bbox": [],
  "geometry": {"coordinates":[-64.0833,-10.4833],"type":"Point"}
}