{
  "id": 2198388,
  "type": "Feature",
  "properties": {
    "tgn:hierarchy":[
        "tgn:2198388",
        "tgn:1000001",
        "tgn:2001816",
        "tgn:7012149",
        "tgn:7007713",
        "tgn:7029392"
    ],
    "tgn:id":2198388,
    "tgn:name":"Browns Draw",
    "tgn:placetype":[
        "aat:300008761"
    ]
},
  "bbox": [],
  "geometry": {"coordinates":[-102.95,44.5333],"type":"Point"}
}