{
  "id": 2534435,
  "type": "Feature",
  "properties": {
    "tgn:hierarchy":[
        "tgn:2534435",
        "tgn:1000001",
        "tgn:7012149",
        "tgn:2001306",
        "tgn:7007524",
        "tgn:7029392"
    ],
    "tgn:id":2534435,
    "tgn:name":"NE SE Section 6 Mine",
    "tgn:placetype":[
        "aat:300000390"
    ]
},
  "bbox": [],
  "geometry": {"coordinates":[-112.6333,46.85],"type":"Point"}
}