{
  "id": 7561367,
  "type": "Feature",
  "properties": {
    "tgn:hierarchy":[
        "tgn:7561367",
        "tgn:1000004",
        "tgn:7000198",
        "tgn:7016722",
        "tgn:7029392"
    ],
    "tgn:id":7561367,
    "tgn:name:en":"Ganeshpur",
    "tgn:placetype":[
        "aat:300008347"
    ]
},
  "bbox": [],
  "geometry": {"coordinates":[79.405046,27.095413],"type":"Point"}
}