{
  "id": 2290186,
  "type": "Feature",
  "properties": {
    "tgn:hierarchy":[
        "tgn:2290186",
        "tgn:2000766",
        "tgn:1000001",
        "tgn:7012149",
        "tgn:7007255",
        "tgn:7029392"
    ],
    "tgn:id":2290186,
    "tgn:name":"Doddy Branch",
    "tgn:placetype":[
        "aat:300008699"
    ]
},
  "bbox": [],
  "geometry": {"coordinates":[-86.1333,36.6667],"type":"Point"}
}