{
  "id": 7019374,
  "type": "Feature",
  "properties": {
    "tgn:hierarchy":[
        "tgn:7019374",
        "tgn:1000001",
        "tgn:2001436",
        "tgn:7012149",
        "tgn:7007566",
        "tgn:7029392"
    ],
    "tgn:id":7019374,
    "tgn:name":"Nash Draw Mine",
    "tgn:placetype":[
        "aat:300000390"
    ]
},
  "bbox": [],
  "geometry": {"coordinates":[-103.8667,32.35],"type":"Point"}
}