{
  "id": 2600391,
  "type": "Feature",
  "properties": {
    "tgn:hierarchy":[
        "tgn:2600391",
        "tgn:1000001",
        "tgn:7012149",
        "tgn:2001450",
        "tgn:7007566",
        "tgn:7029392"
    ],
    "tgn:id":2600391,
    "tgn:name":"Puertecita, Arroyo",
    "tgn:placetype":[
        "aat:300008699"
    ]
},
  "bbox": [],
  "geometry": {"coordinates":[-107.2833,35.25],"type":"Point"}
}