{
  "id": 7122915,
  "type": "Feature",
  "properties": {
    "tgn:hierarchy":[
        "tgn:7122915",
        "tgn:7003669",
        "tgn:1000003",
        "tgn:7000084",
        "tgn:7029392"
    ],
    "tgn:id":7122915,
    "tgn:name":"Niedernberg",
    "tgn:placetype":[
        "aat:300008347"
    ]
},
  "bbox": [],
  "geometry": {"coordinates":[9.136944,49.912222],"type":"Point"}
}