{
  "id": 2459407,
  "type": "Feature",
  "properties": {
    "tgn:hierarchy":[
        "tgn:2459407",
        "tgn:1000001",
        "tgn:7012149",
        "tgn:1002545",
        "tgn:7007157",
        "tgn:7029392"
    ],
    "tgn:id":2459407,
    "tgn:name":"Little Poso Creek",
    "tgn:placetype":[
        "aat:300008706"
    ]
},
  "bbox": [],
  "geometry": {"coordinates":[-118.5833,35.6667],"type":"Point"}
}