{
  "id": 2476331,
  "type": "Feature",
  "properties": {
    "tgn:hierarchy":[
        "tgn:2476331",
        "tgn:1000001",
        "tgn:7012149",
        "tgn:2001312",
        "tgn:7007524",
        "tgn:7029392"
    ],
    "tgn:id":2476331,
    "tgn:name":"Lunch Reservoir",
    "tgn:placetype":[
        "aat:300006191"
    ]
},
  "bbox": [],
  "geometry": {"coordinates":[-106.7833,48.1167],"type":"Point"}
}