{
  "id": 1010665,
  "type": "Feature",
  "properties": {
    "tgn:hierarchy":[
        "tgn:1010665",
        "tgn:1000985",
        "tgn:7016529",
        "tgn:7016531",
        "tgn:1000004",
        "tgn:1000120",
        "tgn:7029392"
    ],
    "tgn:id":1010665,
    "tgn:name":"Erimo-misaki",
    "tgn:placetype":[
        "aat:300008850"
    ]
},
  "bbox": [],
  "geometry": {"coordinates":[143.2167,41.9167],"type":"Point"}
}