{
  "id": 7045396,
  "type": "Feature",
  "properties": {
    "tgn:hierarchy":[
        "tgn:7045396",
        "tgn:1003483",
        "tgn:1000003",
        "tgn:7003240",
        "tgn:1000080",
        "tgn:7029392"
    ],
    "tgn:id":7045396,
    "tgn:name":"Fontecorniale",
    "tgn:placetype":[
        "aat:300008347"
    ]
},
  "bbox": [],
  "geometry": {"coordinates":[12.816667,43.766667],"type":"Point"}
}