{
  "id": 7031811,
  "type": "Feature",
  "properties": {
    "tgn:hierarchy":[
        "tgn:7031811",
        "tgn:1000004",
        "tgn:7005019",
        "tgn:7029392"
    ],
    "tgn:id":7031811,
    "tgn:name:en":"Macau Island",
    "tgn:name:pt":"Macau, Ilha de",
    "tgn:placetype":[
        "aat:300008791"
    ]
},
  "bbox": [],
  "geometry": {"coordinates":[113.546,22.199],"type":"Point"}
}