{
  "id": 2439488,
  "type": "Feature",
  "properties": {
    "tgn:hierarchy":[
        "tgn:2439488",
        "tgn:1000001",
        "tgn:7012149",
        "tgn:2000906",
        "tgn:7007256",
        "tgn:7029392"
    ],
    "tgn:id":2439488,
    "tgn:name":"Kirkville",
    "tgn:placetype":[
        "aat:300008347"
    ]
},
  "bbox": [],
  "geometry": {"coordinates":[-90.4667,30.9833],"type":"Point"}
}