{
  "id": 2052549,
  "type": "Feature",
  "properties": {
    "tgn:hierarchy":[
        "tgn:2052549",
        "tgn:1000001",
        "tgn:7012149",
        "tgn:2000986",
        "tgn:7007520",
        "tgn:7029392"
    ],
    "tgn:id":2052549,
    "tgn:name":"McKeever",
    "tgn:placetype":[
        "aat:300387016"
    ]
},
  "bbox": [],
  "geometry": {"coordinates":[-89.05,46.7333],"type":"Point"}
}