{
  "id": 7521912,
  "type": "Feature",
  "properties": {
    "tgn:hierarchy":[
        "tgn:7521912",
        "tgn:7001242",
        "tgn:7001311",
        "tgn:7016833",
        "tgn:7029392"
    ],
    "tgn:id":7521912,
    "tgn:name:en":"Abu Murr\u00e2t, W\u00e2di",
    "tgn:placetype":[
        "aat:300379998"
    ]
},
  "bbox": [],
  "geometry": {"coordinates":[33.840337,26.84563],"type":"Point"}
}