{
  "id": 2153027,
  "type": "Feature",
  "properties": {
    "tgn:hierarchy":[
        "tgn:2153027",
        "tgn:1000001",
        "tgn:7012149",
        "tgn:1002401",
        "tgn:7007826",
        "tgn:7029392"
    ],
    "tgn:id":2153027,
    "tgn:name":"Beacon Bayou",
    "tgn:placetype":[
        "aat:300008699"
    ]
},
  "bbox": [],
  "geometry": {"coordinates":[-94.7167,29.3833],"type":"Point"}
}