{
  "id": 2347288,
  "type": "Feature",
  "properties": {
    "tgn:hierarchy":[
        "tgn:2347288",
        "tgn:1000001",
        "tgn:2001473",
        "tgn:7012149",
        "tgn:7007709",
        "tgn:7029392"
    ],
    "tgn:id":2347288,
    "tgn:name":"George Branch",
    "tgn:placetype":[
        "aat:300008699"
    ]
},
  "bbox": [],
  "geometry": {"coordinates":[-82.7667,35.55],"type":"Point"}
}