{
  "id": 2124864,
  "type": "Feature",
  "properties": {
    "tgn:hierarchy":[
        "tgn:2124864",
        "tgn:1000001",
        "tgn:7012149",
        "tgn:2001312",
        "tgn:7007524",
        "tgn:7029392"
    ],
    "tgn:id":2124864,
    "tgn:name":"Abey Reservoir",
    "tgn:placetype":[
        "aat:300006191"
    ]
},
  "bbox": [],
  "geometry": {"coordinates":[-106.8833,48.55],"type":"Point"}
}