{
  "id": 2716386,
  "type": "Feature",
  "properties": {
    "tgn:hierarchy":[
        "tgn:2716386",
        "tgn:1000001",
        "tgn:2001476",
        "tgn:7012149",
        "tgn:7007709",
        "tgn:7029392"
    ],
    "tgn:id":2716386,
    "tgn:name":"The Forest at Blowing Rock",
    "tgn:placetype":[
        "aat:300008347"
    ]
},
  "bbox": [],
  "geometry": {"coordinates":[-81.7167,36.1167],"type":"Point"}
}