{
  "id": 2244965,
  "type": "Feature",
  "properties": {
    "tgn:hierarchy":[
        "tgn:2244965",
        "tgn:1000001",
        "tgn:2001414",
        "tgn:7012149",
        "tgn:7007526",
        "tgn:7029392"
    ],
    "tgn:id":2244965,
    "tgn:name":"Clover Creek",
    "tgn:placetype":[
        "aat:300008706"
    ]
},
  "bbox": [],
  "geometry": {"coordinates":[-118.5333,41.2167],"type":"Point"}
}