{
  "id": 2280733,
  "type": "Feature",
  "properties": {
    "tgn:hierarchy":[
        "tgn:2280733",
        "tgn:1000001",
        "tgn:7012149",
        "tgn:1002977",
        "tgn:7007240",
        "tgn:7029392"
    ],
    "tgn:id":2280733,
    "tgn:name":"Deep Creek",
    "tgn:placetype":[
        "aat:300008706"
    ]
},
  "bbox": [],
  "geometry": {"coordinates":[-81.3333,29.2167],"type":"Point"}
}