{
  "id": 1068740,
  "type": "Feature",
  "properties": {
    "tgn:hierarchy":[
        "tgn:1068740",
        "tgn:1000004",
        "tgn:7002081",
        "tgn:1000111",
        "tgn:7029392"
    ],
    "tgn:id":1068740,
    "tgn:name":"Hexingjie",
    "tgn:placetype":[
        "aat:300008347"
    ]
},
  "bbox": [],
  "geometry": {"coordinates":[120.5833,31.9167],"type":"Point"}
}