<<<<<<< HEAD
{
  "id": 2257190,
  "type": "Feature",
  "properties": {
    "tgn:hierarchy":[
        "tgn:2257190",
        "tgn:1000001",
        "tgn:2001473",
        "tgn:7012149",
        "tgn:7007709",
        "tgn:7029392"
    ],
    "tgn:id":2257190,
    "tgn:name":"Corner Rock Creek",
    "tgn:placetype":[
        "aat:300008706"
    ]
},
  "bbox": [],
  "geometry": {"coordinates":[-82.35,35.7667],"type":"Point"}
}
=======
{"geometry":{"type":"Point","coordinates":[-82.350000,35.766700]},"type":"Feature","properties":{"hierarchy":["tgn:2257190","tgn:1000001","tgn:2001473","tgn:7012149","tgn:7007709","tgn:7029392"],"placetype":["aat:300008706"],"id":2257190,"name:xx":"Corner Rock Creek"}}
>>>>>>> 03f74aca74312dbeaf24d7e61306dd6a786dc3d0
