{
  "id": 7232452,
  "type": "Feature",
  "properties": {
    "tgn:hierarchy":[
        "tgn:7232452",
        "tgn:7002690",
        "tgn:7012056",
        "tgn:1000003",
        "tgn:1000074",
        "tgn:7029392"
    ],
    "tgn:id":7232452,
    "tgn:name":"K\u00e1vallos",
    "tgn:placetype":[
        "aat:300008347"
    ]
},
  "bbox": [],
  "geometry": {"coordinates":[24.283333,35.333333],"type":"Point"}
}