<<<<<<< HEAD
{
  "id": 7246948,
  "type": "Feature",
  "properties": {
    "tgn:hierarchy":[
        "tgn:7246948",
        "tgn:7003465",
        "tgn:1000003",
        "tgn:1000063",
        "tgn:4012014",
        "tgn:7029392"
    ],
    "tgn:id":7246948,
    "tgn:name":"Carri\u00e8res, Bois des",
    "tgn:placetype":[
        "aat:300008863"
    ]
},
  "bbox": [],
  "geometry": {"coordinates":[5.916667,50.266667],"type":"Point"}
}
=======
{"geometry":{"type":"Point","coordinates":[5.916667,50.266667]},"type":"Feature","properties":{"hierarchy":["tgn:7246948","tgn:7003465","tgn:1000003","tgn:1000063","tgn:4012014","tgn:7029392"],"placetype":["aat:300008863"],"id":7246948,"name:xx":"Carri\u00e8res, Bois des"}}
>>>>>>> 03f74aca74312dbeaf24d7e61306dd6a786dc3d0
