{
  "id": 2514350,
  "type": "Feature",
  "properties": {
    "tgn:hierarchy":[
        "tgn:2514350",
        "tgn:1000001",
        "tgn:7012149",
        "tgn:2001440",
        "tgn:7007566",
        "tgn:7029392"
    ],
    "tgn:id":2514350,
    "tgn:name":"Miller Creek",
    "tgn:placetype":[
        "aat:300008706"
    ]
},
  "bbox": [],
  "geometry": {"coordinates":[-109.0333,31.4667],"type":"Point"}
}