{
  "id": 7338729,
  "type": "Feature",
  "properties": {
    "tgn:hierarchy":[
        "tgn:7338729",
        "tgn:7002758",
        "tgn:7002821",
        "tgn:1000003",
        "tgn:1000095",
        "tgn:7029392"
    ],
    "tgn:id":7338729,
    "tgn:name":"El Collado",
    "tgn:placetype":[
        "aat:300008347"
    ]
},
  "bbox": [],
  "geometry": {"coordinates":[-3.15,36.833333],"type":"Point"}
}