{
  "id": 7342304,
  "type": "Feature",
  "properties": {
    "tgn:hierarchy":[
        "tgn:7342304",
        "tgn:7002759",
        "tgn:7008909",
        "tgn:1000003",
        "tgn:1000095",
        "tgn:7029392"
    ],
    "tgn:id":7342304,
    "tgn:name":"Castellazo",
    "tgn:placetype":[
        "aat:300008347"
    ]
},
  "bbox": [],
  "geometry": {"coordinates":[0.059105,42.333409],"type":"Point"}
}