{
  "id": 2169250,
  "type": "Feature",
  "properties": {
    "tgn:hierarchy":[
        "tgn:2169250",
        "tgn:1000001",
        "tgn:7012149",
        "tgn:1002768",
        "tgn:7007240",
        "tgn:7029392"
    ],
    "tgn:id":2169250,
    "tgn:name":"Big Lake",
    "tgn:placetype":[
        "aat:300008680"
    ]
},
  "bbox": [],
  "geometry": {"coordinates":[-80.2833,26.4167],"type":"Point"}
}