{
  "id": 2499196,
  "type": "Feature",
  "properties": {
    "tgn:hierarchy":[
        "tgn:2499196",
        "tgn:1000001",
        "tgn:7012149",
        "tgn:7007157",
        "tgn:2000187",
        "tgn:7029392"
    ],
    "tgn:id":2499196,
    "tgn:name":"McCellan Canyon",
    "tgn:placetype":[
        "aat:300008761"
    ]
},
  "bbox": [],
  "geometry": {"coordinates":[-120.4167,40.05],"type":"Point"}
}