{
  "id": 2132147,
  "type": "Feature",
  "properties": {
    "tgn:hierarchy":[
        "tgn:2132147",
        "tgn:1000001",
        "tgn:7006451",
        "tgn:7012149",
        "tgn:2000102",
        "tgn:7029392"
    ],
    "tgn:id":2132147,
    "tgn:name":"American Peak",
    "tgn:placetype":[
        "aat:300008798"
    ]
},
  "bbox": [],
  "geometry": {"coordinates":[-110.7167,31.4333],"type":"Point"}
}