{
  "id": 7454634,
  "type": "Feature",
  "properties": {
    "tgn:hierarchy":[
        "tgn:7454634",
        "tgn:7019094",
        "tgn:7002444",
        "tgn:1000003",
        "tgn:7008591",
        "tgn:7029392"
    ],
    "tgn:id":7454634,
    "tgn:name:en":"Connel Sound",
    "tgn:placetype":[
        "aat:300266559"
    ]
},
  "bbox": [],
  "geometry": {"coordinates":[-5.383333,56.45],"type":"Point"}
}