{
  "id": 2176757,
  "type": "Feature",
  "properties": {
    "tgn:hierarchy":[
        "tgn:2176757",
        "tgn:7006450",
        "tgn:1000001",
        "tgn:2124076",
        "tgn:7012149",
        "tgn:7029392"
    ],
    "tgn:id":2176757,
    "tgn:name":"Black Mountain",
    "tgn:placetype":[
        "aat:300008798"
    ]
},
  "bbox": [],
  "geometry": {"coordinates":[-131.3833,55.2667],"type":"Point"}
}