{
  "id": 1052014,
  "type": "Feature",
  "properties": {
    "tgn:hierarchy":[
        "tgn:1052014",
        "tgn:1000004",
        "tgn:1003398",
        "tgn:7018214",
        "tgn:7002435",
        "tgn:7029392"
    ],
    "tgn:id":1052014,
    "tgn:name":"Akkermanovka",
    "tgn:placetype":[
        "aat:300008347"
    ]
},
  "bbox": [],
  "geometry": {"coordinates":[58.25,51.25],"type":"Point"}
}