{
  "id": 2606074,
  "type": "Feature",
  "properties": {
    "tgn:hierarchy":[
        "tgn:2606074",
        "tgn:1000001",
        "tgn:7012149",
        "tgn:7007826",
        "tgn:7029392"
    ],
    "tgn:id":2606074,
    "tgn:name":"Rainey Creek",
    "tgn:placetype":[
        "aat:300008706"
    ]
},
  "bbox": [],
  "geometry": {"coordinates":[-97.6333,31.5333],"type":"Point"}
}