<<<<<<< HEAD
{
  "id": 2333732,
  "type": "Feature",
  "properties": {
    "tgn:hierarchy":[
        "tgn:2333732",
        "tgn:1000001",
        "tgn:7012149",
        "tgn:2001722",
        "tgn:7007708",
        "tgn:7029392"
    ],
    "tgn:id":2333732,
    "tgn:name":"Footbridge Mine",
    "tgn:placetype":[
        "aat:300000390"
    ]
},
  "bbox": [],
  "geometry": {"coordinates":[-116.75,45.8],"type":"Point"}
}
=======
{"geometry":{"type":"Point","coordinates":[-116.750000,45.800000]},"type":"Feature","properties":{"hierarchy":["tgn:2333732","tgn:1000001","tgn:7012149","tgn:2001722","tgn:7007708","tgn:7029392"],"placetype":["aat:300000390"],"id":2333732,"name:xx":"Footbridge Mine"}}
>>>>>>> 03f74aca74312dbeaf24d7e61306dd6a786dc3d0
