<<<<<<< HEAD
{
  "id": 7023069,
  "type": "Feature",
  "properties": {
    "tgn:hierarchy":[
        "tgn:7023069",
        "tgn:1000001",
        "tgn:7012149",
        "tgn:7007517",
        "tgn:7029392"
    ],
    "tgn:id":7023069,
    "tgn:name":"Hampshire and Hampden Canal",
    "tgn:placetype":[
        "aat:300006075"
    ]
},
  "bbox": [],
  "geometry": {"coordinates":[-72.7167,42.0833],"type":"Point"}
}
=======
{"geometry":{"type":"Point","coordinates":[-72.716700,42.083300]},"type":"Feature","properties":{"hierarchy":["tgn:7023069","tgn:1000001","tgn:7012149","tgn:7007517","tgn:7029392"],"placetype":["aat:300006075"],"id":7023069,"name:xx":"Hampshire and Hampden Canal"}}
>>>>>>> 03f74aca74312dbeaf24d7e61306dd6a786dc3d0
