{
  "id": 2667031,
  "type": "Feature",
  "properties": {
    "tgn:hierarchy":[
        "tgn:2667031",
        "tgn:1000001",
        "tgn:2001473",
        "tgn:7012149",
        "tgn:7007709",
        "tgn:7029392"
    ],
    "tgn:id":2667031,
    "tgn:name":"Skelton Twin Lakes",
    "tgn:placetype":[
        "aat:300006191"
    ]
},
  "bbox": [],
  "geometry": {"coordinates":[-82.4667,35.4833],"type":"Point"}
}