{
  "id": 7416423,
  "type": "Feature",
  "properties": {
    "tgn:hierarchy":[
        "tgn:7416423",
        "tgn:1000001",
        "tgn:7005591",
        "tgn:7005560",
        "tgn:7029392"
    ],
    "tgn:id":7416423,
    "tgn:name:es":"Trinidad Buenavista",
    "tgn:placetype":[
        "aat:300008347"
    ]
},
  "bbox": [],
  "geometry": {"coordinates":[-96.565278,15.967222],"type":"Point"}
}