{
  "id": 2433327,
  "type": "Feature",
  "properties": {
    "tgn:hierarchy":[
        "tgn:2433327",
        "tgn:1000001",
        "tgn:2001260",
        "tgn:7012149",
        "tgn:7007524",
        "tgn:7029392"
    ],
    "tgn:id":2433327,
    "tgn:name":"Kelley Creek",
    "tgn:placetype":[
        "aat:300008706"
    ]
},
  "bbox": [],
  "geometry": {"coordinates":[-113.1833,45.65],"type":"Point"}
}