{
  "id": 7222901,
  "type": "Feature",
  "properties": {
    "tgn:hierarchy":[
        "tgn:7222901",
        "tgn:7002735",
        "tgn:7017076",
        "tgn:1000003",
        "tgn:1000074",
        "tgn:7029392"
    ],
    "tgn:id":7222901,
    "tgn:name":"Sikar\u00e1kion",
    "tgn:placetype":[
        "aat:300008347"
    ]
},
  "bbox": [],
  "geometry": {"coordinates":[22.416667,37.05],"type":"Point"}
}