{
  "id": 2634501,
  "type": "Feature",
  "properties": {
    "tgn:hierarchy":[
        "tgn:2634501",
        "tgn:1000001",
        "tgn:7012149",
        "tgn:1002835",
        "tgn:7007706",
        "tgn:7029392"
    ],
    "tgn:id":2634501,
    "tgn:name":"Rustic Acres Lake",
    "tgn:placetype":[
        "aat:300006191"
    ]
},
  "bbox": [],
  "geometry": {"coordinates":[-83.05,39.4167],"type":"Point"}
}