{
  "id": 7490761,
  "type": "Feature",
  "properties": {
    "tgn:hierarchy":[
        "tgn:7490761",
        "tgn:1000004",
        "tgn:1000141",
        "tgn:7029392"
    ],
    "tgn:id":7490761,
    "tgn:name":"Taizhong Xian",
    "tgn:placetype":[
        "aat:300387179"
    ]
},
  "bbox": [],
  "geometry": {"coordinates":[120.90944,24.20916],"type":"Point"}
}