{
  "id": 2705060,
  "type": "Feature",
  "properties": {
    "tgn:hierarchy":[
        "tgn:2705060",
        "tgn:1000001",
        "tgn:7012149",
        "tgn:2002252",
        "tgn:7007920",
        "tgn:7029392"
    ],
    "tgn:id":2705060,
    "tgn:name":"Sunshine Creek",
    "tgn:placetype":[
        "aat:300008706"
    ]
},
  "bbox": [],
  "geometry": {"coordinates":[-117.0667,46.7167],"type":"Point"}
}