{
  "id": 2217632,
  "type": "Feature",
  "properties": {
    "tgn:hierarchy":[
        "tgn:2217632",
        "tgn:1000001",
        "tgn:7012149",
        "tgn:1002771",
        "tgn:7007826",
        "tgn:7029392"
    ],
    "tgn:id":2217632,
    "tgn:name":"Campbell Island",
    "tgn:placetype":[
        "aat:300008791"
    ]
},
  "bbox": [],
  "geometry": {"coordinates":[-97.8333,32.5667],"type":"Point"}
}