{
  "id": 2291975,
  "type": "Feature",
  "properties": {
    "tgn:hierarchy":[
        "tgn:2291975",
        "tgn:1000001",
        "tgn:1002260",
        "tgn:7012149",
        "tgn:7007920",
        "tgn:7029392"
    ],
    "tgn:id":2291975,
    "tgn:name":"Domke Lake",
    "tgn:placetype":[
        "aat:300008680"
    ]
},
  "bbox": [],
  "geometry": {"coordinates":[-120.5833,48.1667],"type":"Point"}
}