{
  "id": 7097642,
  "type": "Feature",
  "properties": {
    "tgn:hierarchy":[
        "tgn:7097642",
        "tgn:7000096",
        "tgn:1000003",
        "tgn:7000084",
        "tgn:7029392"
    ],
    "tgn:id":7097642,
    "tgn:name":"Spring-Berge",
    "tgn:placetype":[
        "aat:300008777"
    ]
},
  "bbox": [],
  "geometry": {"coordinates":[13.95,52.65],"type":"Point"}
}