<<<<<<< HEAD
{
  "id": 7360476,
  "type": "Feature",
  "properties": {
    "tgn:hierarchy":[
        "tgn:7360476",
        "tgn:1000001",
        "tgn:1001960",
        "tgn:7005560",
        "tgn:7029392"
    ],
    "tgn:id":7360476,
    "tgn:name":"Cuesta Blanca",
    "tgn:placetype":[
        "aat:300008347"
    ]
},
  "bbox": [],
  "geometry": {"coordinates":[-109.316667,28.3],"type":"Point"}
}
=======
{"geometry":{"type":"Point","coordinates":[-109.316667,28.300000]},"type":"Feature","properties":{"hierarchy":["tgn:7360476","tgn:1000001","tgn:1001960","tgn:7005560","tgn:7029392"],"placetype":["aat:300008347"],"id":7360476,"name:xx":"Cuesta Blanca"}}
>>>>>>> 03f74aca74312dbeaf24d7e61306dd6a786dc3d0
