{
  "id": 2067839,
  "type": "Feature",
  "properties": {
    "tgn:hierarchy":[
        "tgn:2067839",
        "tgn:1000001",
        "tgn:7012149",
        "tgn:1002961",
        "tgn:7007568",
        "tgn:7029392"
    ],
    "tgn:id":2067839,
    "tgn:name":"Ardonia",
    "tgn:placetype":[
        "aat:300008347"
    ]
},
  "bbox": [],
  "geometry": {"coordinates":[-74.0667,41.6667],"type":"Point"}
}