{
  "id": 2272080,
  "type": "Feature",
  "properties": {
    "tgn:hierarchy":[
        "tgn:2272080",
        "tgn:1000001",
        "tgn:7012149",
        "tgn:2001290",
        "tgn:7007524",
        "tgn:7029392"
    ],
    "tgn:id":2272080,
    "tgn:name":"Curran Gulch",
    "tgn:placetype":[
        "aat:300008761"
    ]
},
  "bbox": [],
  "geometry": {"coordinates":[-114.9333,47.15],"type":"Point"}
}