{
  "id": 7353320,
  "type": "Feature",
  "properties": {
    "tgn:hierarchy":[
        "tgn:7353320",
        "tgn:1000001",
        "tgn:1001960",
        "tgn:7005560",
        "tgn:7029392"
    ],
    "tgn:id":7353320,
    "tgn:name":"Avispas, Cerro",
    "tgn:placetype":[
        "aat:300008795"
    ]
},
  "bbox": [],
  "geometry": {"coordinates":[-110.266667,28.716667],"type":"Point"}
}