{
  "id": 7457913,
  "type": "Feature",
  "properties": {
    "tgn:hierarchy":[
        "tgn:7457913",
        "tgn:7019163",
        "tgn:7002448",
        "tgn:1000003",
        "tgn:7008591",
        "tgn:7029392"
    ],
    "tgn:id":7457913,
    "tgn:name:en":"Moore Lodge",
    "tgn:placetype":[
        "aat:300004792"
    ]
},
  "bbox": [],
  "geometry": {"coordinates":[-6.533333,54.966667],"type":"Point"}
}