<<<<<<< HEAD
{
  "id": 7026947,
  "type": "Feature",
  "properties": {
    "tgn:hierarchy":[
        "tgn:7026947",
        "tgn:7002445",
        "tgn:1000003",
        "tgn:7008139",
        "tgn:7008591",
        "tgn:7029392"
    ],
    "tgn:id":7026947,
    "tgn:name:en":"Warnford",
    "tgn:placetype":[
        "aat:300008347",
        "aat:300008372"
    ]
},
  "bbox": [],
  "geometry": {"coordinates":[-1.1,51.0],"type":"Point"}
}
=======
{"geometry":{"type":"Point","coordinates":[-1.100000,51.000000]},"type":"Feature","properties":{"hierarchy":["tgn:7026947","tgn:7002445","tgn:1000003","tgn:7008139","tgn:7008591","tgn:7029392"],"placetype":["aat:300008347","aat:300008372"],"name:en":"Warnford","id":7026947}}
>>>>>>> 03f74aca74312dbeaf24d7e61306dd6a786dc3d0
