{
  "id": 7017432,
  "type": "Feature",
  "properties": {
    "tgn:hierarchy":[
        "tgn:7017432",
        "tgn:1000003",
        "tgn:7012216",
        "tgn:1000070",
        "tgn:7029392"
    ],
    "tgn:id":7017432,
    "tgn:name":"Guichen",
    "tgn:placetype":[
        "aat:300387273",
        "aat:300008347",
        "aat:300008375"
    ]
},
  "bbox": [],
  "geometry": {"coordinates":[-1.7833,47.9667],"type":"Point"}
}