{
  "id": 2468809,
  "type": "Feature",
  "properties": {
    "tgn:hierarchy":[
        "tgn:2468809",
        "tgn:1000001",
        "tgn:7012149",
        "tgn:2001721",
        "tgn:7007708",
        "tgn:7029392"
    ],
    "tgn:id":2468809,
    "tgn:name":"Long Ridge",
    "tgn:placetype":[
        "aat:300266640"
    ]
},
  "bbox": [],
  "geometry": {"coordinates":[-117.65,45.3167],"type":"Point"}
}