{
  "id": 7294229,
  "type": "Feature",
  "properties": {
    "tgn:hierarchy":[
        "tgn:7294229",
        "tgn:7002826",
        "tgn:7001158",
        "tgn:1000003",
        "tgn:1000095",
        "tgn:7029392"
    ],
    "tgn:id":7294229,
    "tgn:name":"Valverde de la Sierra",
    "tgn:placetype":[
        "aat:300008347"
    ]
},
  "bbox": [],
  "geometry": {"coordinates":[-4.833333,42.933333],"type":"Point"}
}