{
  "id": 1079192,
  "type": "Feature",
  "properties": {
    "tgn:hierarchy":[
        "tgn:1079192",
        "tgn:1000004",
        "tgn:1001403",
        "tgn:7000231",
        "tgn:7029392"
    ],
    "tgn:id":1079192,
    "tgn:name":"Mar\u0101veh Tappeh",
    "tgn:placetype":[
        "aat:300008347"
    ]
},
  "bbox": [],
  "geometry": {"coordinates":[55.95,37.8833],"type":"Point"}
}