{
  "id": 1080144,
  "type": "Feature",
  "properties": {
    "tgn:hierarchy":[
        "tgn:1080144",
        "tgn:1000961",
        "tgn:1000004",
        "tgn:7000901",
        "tgn:1000120",
        "tgn:7029392"
    ],
    "tgn:id":1080144,
    "tgn:name":"Hita",
    "tgn:placetype":[
        "aat:300008347"
    ]
},
  "bbox": [],
  "geometry": {"coordinates":[130.9167,33.3167],"type":"Point"}
}