{
  "id": 7223486,
  "type": "Feature",
  "properties": {
    "tgn:hierarchy":[
        "tgn:7223486",
        "tgn:1042193",
        "tgn:7002705",
        "tgn:1000003",
        "tgn:1000074",
        "tgn:7029392"
    ],
    "tgn:id":7223486,
    "tgn:name":"Orop\u00f3s",
    "tgn:placetype":[
        "aat:300008347"
    ]
},
  "bbox": [],
  "geometry": {"coordinates":[20.718333,39.163611],"type":"Point"}
}