<<<<<<< HEAD
{
  "id": 2333217,
  "type": "Feature",
  "properties": {
    "tgn:hierarchy":[
        "tgn:2333217",
        "tgn:1000001",
        "tgn:1002724",
        "tgn:7012149",
        "tgn:7007517",
        "tgn:7029392"
    ],
    "tgn:id":2333217,
    "tgn:name":"Flynns Pond",
    "tgn:placetype":[
        "aat:300008680"
    ]
},
  "bbox": [],
  "geometry": {"coordinates":[-71.2667,42.15],"type":"Point"}
}
=======
{"geometry":{"type":"Point","coordinates":[-71.266700,42.150000]},"type":"Feature","properties":{"hierarchy":["tgn:2333217","tgn:1000001","tgn:1002724","tgn:7012149","tgn:7007517","tgn:7029392"],"placetype":["aat:300008680"],"id":2333217,"name:xx":"Flynns Pond"}}
>>>>>>> 03f74aca74312dbeaf24d7e61306dd6a786dc3d0
