{
  "id": 2384718,
  "type": "Feature",
  "properties": {
    "tgn:hierarchy":[
        "tgn:2384718",
        "tgn:1000001",
        "tgn:2000460",
        "tgn:7012149",
        "tgn:7007250",
        "tgn:7029392"
    ],
    "tgn:id":2384718,
    "tgn:name":"Hellroaring Creek",
    "tgn:placetype":[
        "aat:300008706"
    ]
},
  "bbox": [],
  "geometry": {"coordinates":[-116.6833,48.4667],"type":"Point"}
}