{
  "id": 2023999,
  "type": "Feature",
  "properties": {
    "tgn:hierarchy":[
        "tgn:2023999",
        "tgn:1000001",
        "tgn:7012149",
        "tgn:2000410",
        "tgn:7007248",
        "tgn:7029392"
    ],
    "tgn:id":2023999,
    "tgn:name":"Rabun Gap",
    "tgn:placetype":[
        "aat:300008347"
    ]
},
  "bbox": [],
  "geometry": {"coordinates":[-83.3833,34.95],"type":"Point"}
}