{
  "id": 2462878,
  "type": "Feature",
  "properties": {
    "tgn:hierarchy":[
        "tgn:2462878",
        "tgn:1000001",
        "tgn:7012149",
        "tgn:1002375",
        "tgn:7007255",
        "tgn:7029392"
    ],
    "tgn:id":2462878,
    "tgn:name":"Littleton Branch",
    "tgn:placetype":[
        "aat:300008699"
    ]
},
  "bbox": [],
  "geometry": {"coordinates":[-83.6167,38.3167],"type":"Point"}
}