{
  "id": 7287882,
  "type": "Feature",
  "properties": {
    "tgn:hierarchy":[
        "tgn:7287882",
        "tgn:1001702",
        "tgn:1000049",
        "tgn:1000002",
        "tgn:7029392"
    ],
    "tgn:id":7287882,
    "tgn:name":"Julia, Isla",
    "tgn:placetype":[
        "aat:300008791"
    ]
},
  "bbox": [],
  "geometry": {"coordinates":[-74.266667,-49.783333],"type":"Point"}
}