{
  "id": 7528001,
  "type": "Feature",
  "properties": {
    "tgn:hierarchy":[
        "tgn:7528001",
        "tgn:7001242",
        "tgn:7016833",
        "tgn:1001087",
        "tgn:7029392"
    ],
    "tgn:id":7528001,
    "tgn:name":"Sihw\u0101j",
    "tgn:placetype":[
        "aat:300008347"
    ]
},
  "bbox": [],
  "geometry": {"coordinates":[31.088211,30.274438],"type":"Point"}
}