{
  "id": 2165210,
  "type": "Feature",
  "properties": {
    "tgn:hierarchy":[
        "tgn:2165210",
        "tgn:1000001",
        "tgn:7012149",
        "tgn:2001763",
        "tgn:7007712",
        "tgn:7029392"
    ],
    "tgn:id":2165210,
    "tgn:name":"Betsy Akin Branch",
    "tgn:placetype":[
        "aat:300008699"
    ]
},
  "bbox": [],
  "geometry": {"coordinates":[-82.8667,34.9667],"type":"Point"}
}