{
  "id": 7547321,
  "type": "Feature",
  "properties": {
    "tgn:hierarchy":[
        "tgn:7547321",
        "tgn:1000004",
        "tgn:7000198",
        "tgn:1001882",
        "tgn:7029392"
    ],
    "tgn:id":7547321,
    "tgn:name:en":"Banav\u0101si",
    "tgn:placetype":[
        "aat:300008347"
    ]
},
  "bbox": [],
  "geometry": {"coordinates":[75.016667,14.55],"type":"Point"}
}