{
  "id": 7477742,
  "type": "Feature",
  "properties": {
    "tgn:hierarchy":[
        "tgn:7477742",
        "tgn:1000004",
        "tgn:7001013",
        "tgn:1000141",
        "tgn:7029392"
    ],
    "tgn:id":7477742,
    "tgn:name":"Fulin Xikou",
    "tgn:placetype":[
        "aat:300387057"
    ]
},
  "bbox": [],
  "geometry": {"coordinates":[121.120805,25.072528],"type":"Point"}
}