{
  "id": 2048061,
  "type": "Feature",
  "properties": {
    "tgn:hierarchy":[
        "tgn:2048061",
        "tgn:1000001",
        "tgn:7016104",
        "tgn:7012149",
        "tgn:7007516",
        "tgn:7029392"
    ],
    "tgn:id":2048061,
    "tgn:name":"New Hampshire Estates",
    "tgn:placetype":[
        "aat:300008347"
    ]
},
  "bbox": [],
  "geometry": {"coordinates":[-76.9833,38.9833],"type":"Point"}
}