{
  "id": 2514180,
  "type": "Feature",
  "properties": {
    "tgn:hierarchy":[
        "tgn:2514180",
        "tgn:1000001",
        "tgn:7012149",
        "tgn:7007828",
        "tgn:7029392"
    ],
    "tgn:id":2514180,
    "tgn:name":"Miller Brook",
    "tgn:placetype":[
        "aat:300008699"
    ]
},
  "bbox": [],
  "geometry": {"coordinates":[-72.8333,44.45],"type":"Point"}
}