{
  "id": 7220446,
  "type": "Feature",
  "properties": {
    "tgn:hierarchy":[
        "tgn:7220446",
        "tgn:7011330",
        "tgn:7002674",
        "tgn:1000003",
        "tgn:1000074",
        "tgn:7029392"
    ],
    "tgn:id":7220446,
    "tgn:name":"\u00c1gios St\u00e9fanos, \u00c1kra",
    "tgn:placetype":[
        "aat:300386846"
    ]
},
  "bbox": [],
  "geometry": {"coordinates":[26.988611,36.752222],"type":"Point"}
}