{
  "id": 7532267,
  "type": "Feature",
  "properties": {
    "tgn:hierarchy":[
        "tgn:7532267",
        "tgn:7001242",
        "tgn:7016833",
        "tgn:1001091",
        "tgn:7029392"
    ],
    "tgn:id":7532267,
    "tgn:name":"Mas\u0101kin ash Shirkah al Mi\u015fr\u012byah as Su'\u016bd\u012byah lil Ta'm\u012br",
    "tgn:placetype":[
        "aat:300000745"
    ]
},
  "bbox": [],
  "geometry": {"coordinates":[31.340673,30.075726],"type":"Point"}
}