{
  "id": 2187447,
  "type": "Feature",
  "properties": {
    "tgn:hierarchy":[
        "tgn:2187447",
        "tgn:1000001",
        "tgn:2000670",
        "tgn:7012149",
        "tgn:7007254",
        "tgn:7029392"
    ],
    "tgn:id":2187447,
    "tgn:name":"Boone Lake",
    "tgn:placetype":[
        "aat:300008680"
    ]
},
  "bbox": [],
  "geometry": {"coordinates":[-95.05,37.0333],"type":"Point"}
}