{
  "id": 7362204,
  "type": "Feature",
  "properties": {
    "tgn:hierarchy":[
        "tgn:7362204",
        "tgn:1001835",
        "tgn:1000001",
        "tgn:7005560",
        "tgn:7029392"
    ],
    "tgn:id":7362204,
    "tgn:name":"El Diablo",
    "tgn:placetype":[
        "aat:300008347"
    ]
},
  "bbox": [],
  "geometry": {"coordinates":[-116.45,32.466667],"type":"Point"}
}