{
  "id": 7398793,
  "type": "Feature",
  "properties": {
    "tgn:hierarchy":[
        "tgn:7398793",
        "tgn:1000001",
        "tgn:1001893",
        "tgn:7005560",
        "tgn:7029392"
    ],
    "tgn:id":7398793,
    "tgn:name":"San Mar\u00eda Totoltepec",
    "tgn:placetype":[
        "aat:300008347"
    ]
},
  "bbox": [],
  "geometry": {"coordinates":[-99.5925,19.305],"type":"Point"}
}