{
  "id": 2769862,
  "type": "Feature",
  "properties": {
    "tgn:hierarchy":[
        "tgn:2769862",
        "tgn:1000001",
        "tgn:7012149",
        "tgn:2000914",
        "tgn:7007256",
        "tgn:7029392"
    ],
    "tgn:id":2769862,
    "tgn:name":"Wilbert",
    "tgn:placetype":[
        "aat:300008347"
    ]
},
  "bbox": [],
  "geometry": {"coordinates":[-91.3167,30.45],"type":"Point"}
}