{
  "id": 7591901,
  "type": "Feature",
  "properties": {
    "tgn:hierarchy":[
        "tgn:7591901",
        "tgn:1000004",
        "tgn:7000198",
        "tgn:7000799",
        "tgn:7029392"
    ],
    "tgn:id":7591901,
    "tgn:name:en":"Dehra",
    "tgn:placetype":[
        "aat:300008347"
    ]
},
  "bbox": [],
  "geometry": {"coordinates":[74.222222,33.161111],"type":"Point"}
}