{
  "id": 2407682,
  "type": "Feature",
  "properties": {
    "tgn:hierarchy":[
        "tgn:2407682",
        "tgn:1000001",
        "tgn:7012149",
        "tgn:1002742",
        "tgn:7007920",
        "tgn:7029392"
    ],
    "tgn:id":2407682,
    "tgn:name":"Hurley Peak",
    "tgn:placetype":[
        "aat:300008798"
    ]
},
  "bbox": [],
  "geometry": {"coordinates":[-119.7667,48.9667],"type":"Point"}
}