<<<<<<< HEAD
{
  "id": 7370501,
  "type": "Feature",
  "properties": {
    "tgn:hierarchy":[
        "tgn:7370501",
        "tgn:1000001",
        "tgn:7005595",
        "tgn:7005560",
        "tgn:7029392"
    ],
    "tgn:id":7370501,
    "tgn:name":"Guayabo",
    "tgn:placetype":[
        "aat:300008347"
    ]
},
  "bbox": [],
  "geometry": {"coordinates":[-108.433333,25.65],"type":"Point"}
}
=======
{"geometry":{"type":"Point","coordinates":[-108.433333,25.650000]},"type":"Feature","properties":{"hierarchy":["tgn:7370501","tgn:1000001","tgn:7005595","tgn:7005560","tgn:7029392"],"placetype":["aat:300008347"],"id":7370501,"name:xx":"Guayabo"}}
>>>>>>> 03f74aca74312dbeaf24d7e61306dd6a786dc3d0
