{
  "id": 2423474,
  "type": "Feature",
  "properties": {
    "tgn:hierarchy":[
        "tgn:2423474",
        "tgn:1000001",
        "tgn:2001702",
        "tgn:7012149",
        "tgn:7007708",
        "tgn:7029392"
    ],
    "tgn:id":2423474,
    "tgn:name":"John Fetters Creek",
    "tgn:placetype":[
        "aat:300008706"
    ]
},
  "bbox": [],
  "geometry": {"coordinates":[-123.8833,43.0167],"type":"Point"}
}