{
  "id": 7298229,
  "type": "Feature",
  "properties": {
    "tgn:hierarchy":[
        "tgn:7298229",
        "tgn:7002831",
        "tgn:1000003",
        "tgn:7002786",
        "tgn:1000095",
        "tgn:7029392"
    ],
    "tgn:id":7298229,
    "tgn:name":"Sobreosmui\u00f1os",
    "tgn:placetype":[
        "aat:300008347"
    ]
},
  "bbox": [],
  "geometry": {"coordinates":[-7.05,42.033333],"type":"Point"}
}