{
  "id": 2297173,
  "type": "Feature",
  "properties": {
    "tgn:hierarchy":[
        "tgn:2297173",
        "tgn:1000001",
        "tgn:7012149",
        "tgn:2002381",
        "tgn:7007923",
        "tgn:7029392"
    ],
    "tgn:id":2297173,
    "tgn:name":"Dry Creek",
    "tgn:placetype":[
        "aat:300008706"
    ]
},
  "bbox": [],
  "geometry": {"coordinates":[-106.5667,44.65],"type":"Point"}
}