{
  "id": 7428624,
  "type": "Feature",
  "properties": {
    "tgn:hierarchy":[
        "tgn:7428624",
        "tgn:7005581",
        "tgn:1000001",
        "tgn:7005560",
        "tgn:7029392"
    ],
    "tgn:id":7428624,
    "tgn:name":"Estaci\u00f3n Posada",
    "tgn:placetype":[
        "aat:300007783"
    ]
},
  "bbox": [],
  "geometry": {"coordinates":[-107.833333,27.483333],"type":"Point"}
}