<<<<<<< HEAD
{
  "id": 2333346,
  "type": "Feature",
  "properties": {
    "tgn:hierarchy":[
        "tgn:2333346",
        "tgn:1000001",
        "tgn:7012149",
        "tgn:2002184",
        "tgn:7007919",
        "tgn:7029392"
    ],
    "tgn:id":2333346,
    "tgn:name":"Fogg Mountain",
    "tgn:placetype":[
        "aat:300008798"
    ]
},
  "bbox": [],
  "geometry": {"coordinates":[-78.0667,38.75],"type":"Point"}
}
=======
{"geometry":{"type":"Point","coordinates":[-78.066700,38.750000]},"type":"Feature","properties":{"hierarchy":["tgn:2333346","tgn:1000001","tgn:7012149","tgn:2002184","tgn:7007919","tgn:7029392"],"placetype":["aat:300008798"],"id":2333346,"name:xx":"Fogg Mountain"}}
>>>>>>> 03f74aca74312dbeaf24d7e61306dd6a786dc3d0
