<<<<<<< HEAD
{
  "id": 2336763,
  "type": "Feature",
  "properties": {
    "tgn:hierarchy":[
        "tgn:2336763",
        "tgn:1000001",
        "tgn:7012149",
        "tgn:2000395",
        "tgn:7007248",
        "tgn:7029392"
    ],
    "tgn:id":2336763,
    "tgn:name":"Fourmile Branch",
    "tgn:placetype":[
        "aat:300008699"
    ]
},
  "bbox": [],
  "geometry": {"coordinates":[-83.4833,33.5833],"type":"Point"}
}
=======
{"geometry":{"type":"Point","coordinates":[-83.483300,33.583300]},"type":"Feature","properties":{"hierarchy":["tgn:2336763","tgn:1000001","tgn:7012149","tgn:2000395","tgn:7007248","tgn:7029392"],"placetype":["aat:300008699"],"id":2336763,"name:xx":"Fourmile Branch"}}
>>>>>>> 03f74aca74312dbeaf24d7e61306dd6a786dc3d0
