{
  "id": 1095167,
  "type": "Feature",
  "properties": {
    "tgn:hierarchy":[
        "tgn:1095167",
        "tgn:7001242",
        "tgn:1001075",
        "tgn:7016833",
        "tgn:7029392"
    ],
    "tgn:id":1095167,
    "tgn:name:en":"Abu \u1e24ummu\u1e63",
    "tgn:placetype":[
        "aat:300008347"
    ]
},
  "bbox": [],
  "geometry": {"coordinates":[30.311926,31.083873],"type":"Point"}
}