{
  "id": 7269275,
  "type": "Feature",
  "properties": {
    "tgn:concordances":{
        "gn:id":"2749751"
    },
    "tgn:hierarchy":[
        "tgn:7269275",
        "tgn:1000003",
        "tgn:7003626",
        "tgn:7016845",
        "tgn:7029392"
    ],
    "tgn:id":7269275,
    "tgn:name:nl":"Nutter",
    "tgn:placetype":[
        "aat:300008347"
    ]
},
  "bbox": [],
  "geometry": {"coordinates":[6.883333,52.416667],"type":"Point"}
}