{
  "id": 7438614,
  "type": "Feature",
  "properties": {
    "tgn:hierarchy":[
        "tgn:7438614",
        "tgn:1000001",
        "tgn:7005594",
        "tgn:7005560",
        "tgn:7029392"
    ],
    "tgn:id":7438614,
    "tgn:name":"Tierra Blanca",
    "tgn:placetype":[
        "aat:300008347"
    ]
},
  "bbox": [],
  "geometry": {"coordinates":[-100.983333,22.116667],"type":"Point"}
}