{
  "id": 7540538,
  "type": "Feature",
  "properties": {
    "tgn:hierarchy":[
        "tgn:7540538",
        "tgn:7001242",
        "tgn:7001311",
        "tgn:7016833",
        "tgn:7029392"
    ],
    "tgn:id":7540538,
    "tgn:name:en":"Qirsha",
    "tgn:placetype":[
        "aat:300055621"
    ]
},
  "bbox": [],
  "geometry": {"coordinates":[33.016667,23.25],"type":"Point"}
}