{
  "id": 7282320,
  "type": "Feature",
  "properties": {
    "tgn:hierarchy":[
        "tgn:7282320",
        "tgn:1001623",
        "tgn:1000049",
        "tgn:1000002",
        "tgn:7029392"
    ],
    "tgn:id":7282320,
    "tgn:name":"Promontorio, Roca",
    "tgn:placetype":[
        "aat:300011692"
    ]
},
  "bbox": [],
  "geometry": {"coordinates":[-75.583333,-48.433333],"type":"Point"}
}