{
  "id": 7342386,
  "type": "Feature",
  "properties": {
    "tgn:hierarchy":[
        "tgn:7342386",
        "tgn:7007088",
        "tgn:1000003",
        "tgn:7009604",
        "tgn:1000095",
        "tgn:7029392"
    ],
    "tgn:id":7342386,
    "tgn:name":"Carralogro\u00f1o, Laguna de",
    "tgn:placetype":[
        "aat:300008688"
    ]
},
  "bbox": [],
  "geometry": {"coordinates":[-2.566313,42.542827],"type":"Point"}
}