{
  "id": 7018866,
  "type": "Feature",
  "properties": {
    "tgn:hierarchy":[
        "tgn:7018866",
        "tgn:1000004",
        "tgn:7018118",
        "tgn:1000111",
        "tgn:7029392"
    ],
    "tgn:id":7018866,
    "tgn:name":"Dali",
    "tgn:placetype":[
        "aat:300008347"
    ]
},
  "bbox": [],
  "geometry": {"coordinates":[100.15,25.55],"type":"Point"}
}