<<<<<<< HEAD
{
  "id": 7053172,
  "type": "Feature",
  "properties": {
    "tgn:hierarchy":[
        "tgn:7053172",
        "tgn:1003500",
        "tgn:1000003",
        "tgn:7010380",
        "tgn:1000080",
        "tgn:7029392"
    ],
    "tgn:id":7053172,
    "tgn:name":"Monteparano",
    "tgn:placetype":[
        "aat:300008347"
    ]
},
  "bbox": [],
  "geometry": {"coordinates":[17.416667,40.45],"type":"Point"}
}
=======
{"geometry":{"type":"Point","coordinates":[17.416667,40.450000]},"type":"Feature","properties":{"hierarchy":["tgn:7053172","tgn:1003500","tgn:1000003","tgn:7010380","tgn:1000080","tgn:7029392"],"placetype":["aat:300008347"],"id":7053172,"name:xx":"Monteparano"}}
>>>>>>> 03f74aca74312dbeaf24d7e61306dd6a786dc3d0
