{
  "id": 7217631,
  "type": "Feature",
  "properties": {
    "tgn:hierarchy":[
        "tgn:7217631",
        "tgn:7011164",
        "tgn:7002674",
        "tgn:1000003",
        "tgn:1000074",
        "tgn:7029392"
    ],
    "tgn:id":7217631,
    "tgn:name":"\u00d3rmos Kouma\u00ed\u00efkon",
    "tgn:placetype":[
        "aat:300008347"
    ]
},
  "bbox": [],
  "geometry": {"coordinates":[26.746111,37.699444],"type":"Point"}
}