<<<<<<< HEAD
{
  "id": 7173825,
  "type": "Feature",
  "properties": {
    "tgn:hierarchy":[
        "tgn:7173825",
        "tgn:1000003",
        "tgn:7003677",
        "tgn:7000084",
        "tgn:7029392"
    ],
    "tgn:id":7173825,
    "tgn:name":"Grund",
    "tgn:placetype":[
        "aat:300008347"
    ]
},
  "bbox": [],
  "geometry": {"coordinates":[7.9,50.883333],"type":"Point"}
}
=======
{"geometry":{"type":"Point","coordinates":[7.900000,50.883333]},"type":"Feature","properties":{"hierarchy":["tgn:7173825","tgn:1000003","tgn:7003677","tgn:7000084","tgn:7029392"],"placetype":["aat:300008347"],"id":7173825,"name:xx":"Grund"}}
>>>>>>> 03f74aca74312dbeaf24d7e61306dd6a786dc3d0
