{
  "id": 7235038,
  "type": "Feature",
  "properties": {
    "tgn:hierarchy":[
        "tgn:7235038",
        "tgn:7002741",
        "tgn:7017076",
        "tgn:1000003",
        "tgn:1000074",
        "tgn:7029392"
    ],
    "tgn:id":7235038,
    "tgn:name":"Foni\u00e1s, Nis\u00eds",
    "tgn:placetype":[
        "aat:300008791"
    ]
},
  "bbox": [],
  "geometry": {"coordinates":[22.95,38.166667],"type":"Point"}
}