{
  "id": 2453875,
  "type": "Feature",
  "properties": {
    "tgn:hierarchy":[
        "tgn:2453875",
        "tgn:1000001",
        "tgn:7012149",
        "tgn:2000495",
        "tgn:7007250",
        "tgn:7029392"
    ],
    "tgn:id":2453875,
    "tgn:name":"Little Crane Creek Reservoir",
    "tgn:placetype":[
        "aat:300006191"
    ]
},
  "bbox": [],
  "geometry": {"coordinates":[-116.65,44.3667],"type":"Point"}
}