{
  "id": 7402828,
  "type": "Feature",
  "properties": {
    "tgn:hierarchy":[
        "tgn:7402828",
        "tgn:1000001",
        "tgn:1001937",
        "tgn:7005560",
        "tgn:7029392"
    ],
    "tgn:id":7402828,
    "tgn:name":"Uni\u00f3n",
    "tgn:placetype":[
        "aat:300008347"
    ]
},
  "bbox": [],
  "geometry": {"coordinates":[-87.241667,21.258333],"type":"Point"}
}