{
  "id": 1008468,
  "type": "Feature",
  "properties": {
    "tgn:hierarchy":[
        "tgn:1008468",
        "tgn:1000223",
        "tgn:1000006",
        "tgn:7029392"
    ],
    "tgn:id":1008468,
    "tgn:name":"Ouen",
    "tgn:placetype":[
        "aat:300008791"
    ]
},
  "bbox": [],
  "geometry": {"coordinates":[166.85,-22.4167],"type":"Point"}
}