{
  "id": 7141773,
  "type": "Feature",
  "properties": {
    "tgn:hierarchy":[
        "tgn:7141773",
        "tgn:7003669",
        "tgn:1000003",
        "tgn:7000084",
        "tgn:7029392"
    ],
    "tgn:id":7141773,
    "tgn:name":"L\u00fclsbach",
    "tgn:placetype":[
        "aat:300008699"
    ]
},
  "bbox": [],
  "geometry": {"coordinates":[10.316667,49.883333],"type":"Point"}
}