{
  "id": 5004309,
  "type": "Feature",
  "properties": {
    "tgn:hierarchy":[
        "tgn:5004309",
        "tgn:1003468",
        "tgn:1000003",
        "tgn:7010380",
        "tgn:1000080",
        "tgn:7029392"
    ],
    "tgn:id":5004309,
    "tgn:name":"Rudiae",
    "tgn:placetype":[
        "aat:300008347",
        "aat:300000810",
        "aat:300167671"
    ]
},
  "bbox": [],
  "geometry": {"coordinates":[18.18,40.38],"type":"Point"}
}