{
  "id": 7461307,
  "type": "Feature",
  "properties": {
    "tgn:hierarchy":[
        "tgn:7461307",
        "tgn:7002445",
        "tgn:1000003",
        "tgn:7008118",
        "tgn:7008591",
        "tgn:7029392"
    ],
    "tgn:id":7461307,
    "tgn:name:en":"Hipper, River",
    "tgn:placetype":[
        "aat:300008699"
    ]
},
  "bbox": [],
  "geometry": {"coordinates":[-1.433333,53.233333],"type":"Point"}
}