{
  "id": 7113414,
  "type": "Feature",
  "properties": {
    "tgn:hierarchy":[
        "tgn:7113414",
        "tgn:1000003",
        "tgn:7000094",
        "tgn:7000084",
        "tgn:7029392"
    ],
    "tgn:id":7113414,
    "tgn:name":"Rodenwalde",
    "tgn:placetype":[
        "aat:300008347"
    ]
},
  "bbox": [],
  "geometry": {"coordinates":[10.933333,53.433333],"type":"Point"}
}