{
  "id": 2118755,
  "type": "Feature",
  "properties": {
    "tgn:hierarchy":[
        "tgn:2118755",
        "tgn:1000001",
        "tgn:7012149",
        "tgn:2002265",
        "tgn:7013961",
        "tgn:7029392"
    ],
    "tgn:id":2118755,
    "tgn:name":"Johnson",
    "tgn:placetype":[
        "aat:300387016"
    ]
},
  "bbox": [],
  "geometry": {"coordinates":[-78.8167,39.2667],"type":"Point"}
}