{
  "id": 7494649,
  "type": "Feature",
  "properties": {
    "tgn:hierarchy":[
        "tgn:7494649",
        "tgn:7001010",
        "tgn:1000004",
        "tgn:1000141",
        "tgn:7029392"
    ],
    "tgn:id":7494649,
    "tgn:name":"Fuyuan Guoxiao",
    "tgn:placetype":[
        "aat:300006495"
    ]
},
  "bbox": [],
  "geometry": {"coordinates":[121.375269,23.578574],"type":"Point"}
}