{
  "id": 2635800,
  "type": "Feature",
  "properties": {
    "tgn:hierarchy":[
        "tgn:2635800",
        "tgn:1000001",
        "tgn:2001436",
        "tgn:7012149",
        "tgn:7007566",
        "tgn:7029392"
    ],
    "tgn:id":2635800,
    "tgn:name":"Sacahuiste Draw",
    "tgn:placetype":[
        "aat:300008761"
    ]
},
  "bbox": [],
  "geometry": {"coordinates":[-104.5667,32.3333],"type":"Point"}
}