{
  "id": 2557006,
  "type": "Feature",
  "properties": {
    "tgn:hierarchy":[
        "tgn:2557006",
        "tgn:1000001",
        "tgn:7012149",
        "tgn:2000236",
        "tgn:7007158",
        "tgn:7029392"
    ],
    "tgn:id":2557006,
    "tgn:name":"Old Fort Bent",
    "tgn:placetype":[
        "aat:300008347"
    ]
},
  "bbox": [],
  "geometry": {"coordinates":[-103.4167,38.0333],"type":"Point"}
}