{
  "id": 2111546,
  "type": "Feature",
  "properties": {
    "tgn:hierarchy":[
        "tgn:2111546",
        "tgn:1000001",
        "tgn:7012149",
        "tgn:7014160",
        "tgn:7007919",
        "tgn:7029392"
    ],
    "tgn:id":2111546,
    "tgn:name":"Dunn Loring Woods",
    "tgn:placetype":[
        "aat:300008347"
    ]
},
  "bbox": [],
  "geometry": {"coordinates":[-77.2333,38.8667],"type":"Point"}
}