{
  "id": 2398093,
  "type": "Feature",
  "properties": {
    "tgn:hierarchy":[
        "tgn:2398093",
        "tgn:1000001",
        "tgn:7006451",
        "tgn:2000094",
        "tgn:7012149",
        "tgn:7029392"
    ],
    "tgn:id":2398093,
    "tgn:name":"Hooker Butte",
    "tgn:placetype":[
        "aat:300008798"
    ]
},
  "bbox": [],
  "geometry": {"coordinates":[-110.0667,32.4833],"type":"Point"}
}