{
  "id": 2007920,
  "type": "Feature",
  "properties": {
    "tgn:hierarchy":[
        "tgn:2007920",
        "tgn:1000001",
        "tgn:7016172",
        "tgn:7012149",
        "tgn:2000127",
        "tgn:7029392"
    ],
    "tgn:id":2007920,
    "tgn:name":"Cato",
    "tgn:placetype":[
        "aat:300008347",
        "aat:300387210"
    ]
},
  "bbox": [],
  "geometry": {"coordinates":[-92.25,34.9167],"type":"Point"}
}