{
  "id": 2415261,
  "type": "Feature",
  "properties": {
    "tgn:hierarchy":[
        "tgn:2415261",
        "tgn:1000001",
        "tgn:1002316",
        "tgn:7012149",
        "tgn:7007922",
        "tgn:7029392"
    ],
    "tgn:id":2415261,
    "tgn:name":"Island Lake",
    "tgn:placetype":[
        "aat:300008680"
    ]
},
  "bbox": [],
  "geometry": {"coordinates":[-89.2833,42.9167],"type":"Point"}
}