{
  "id": 1033633,
  "type": "Feature",
  "properties": {
    "tgn:hierarchy":[
        "tgn:1033633",
        "tgn:1000003",
        "tgn:1000070",
        "tgn:7002895",
        "tgn:7029392"
    ],
    "tgn:id":1033633,
    "tgn:name":"Crau, la",
    "tgn:placetype":[
        "aat:300008347"
    ]
},
  "bbox": [],
  "geometry": {"coordinates":[6.0667,43.15],"type":"Point"}
}