{
  "id": 7253316,
  "type": "Feature",
  "properties": {
    "tgn:hierarchy":[
        "tgn:7253316",
        "tgn:7003457",
        "tgn:1000003",
        "tgn:1000063",
        "tgn:7018236",
        "tgn:7029392"
    ],
    "tgn:id":7253316,
    "tgn:name":"Sluipe",
    "tgn:placetype":[
        "aat:300008347"
    ]
},
  "bbox": [],
  "geometry": {"coordinates":[3.566667,50.783333],"type":"Point"}
}