{
  "id": 7503177,
  "type": "Feature",
  "properties": {
    "tgn:hierarchy":[
        "tgn:7503177",
        "tgn:1000004",
        "tgn:7471332",
        "tgn:1000141",
        "tgn:7029392"
    ],
    "tgn:id":7503177,
    "tgn:name":"Chuqigan Shan",
    "tgn:placetype":[
        "aat:300008795"
    ]
},
  "bbox": [],
  "geometry": {"coordinates":[121.149444,24.711944],"type":"Point"}
}