{
  "id": 7500898,
  "type": "Feature",
  "properties": {
    "tgn:hierarchy":[
        "tgn:7500898",
        "tgn:7001004",
        "tgn:1000004",
        "tgn:1000141",
        "tgn:7029392"
    ],
    "tgn:id":7500898,
    "tgn:name":"Guanyin Qiao",
    "tgn:placetype":[
        "aat:300007836"
    ]
},
  "bbox": [],
  "geometry": {"coordinates":[120.444722,22.907778],"type":"Point"}
}