{
  "id": 2079588,
  "type": "Feature",
  "properties": {
    "tgn:hierarchy":[
        "tgn:2079588",
        "tgn:1000001",
        "tgn:7012149",
        "tgn:1002883",
        "tgn:7007706",
        "tgn:7029392"
    ],
    "tgn:id":2079588,
    "tgn:name":"Flat Rock",
    "tgn:placetype":[
        "aat:300008347"
    ]
},
  "bbox": [],
  "geometry": {"coordinates":[-82.85,41.2333],"type":"Point"}
}