{
  "id": 7254993,
  "type": "Feature",
  "properties": {
    "tgn:hierarchy":[
        "tgn:7254993",
        "tgn:7003456",
        "tgn:1000003",
        "tgn:1000063",
        "tgn:7018236",
        "tgn:7029392"
    ],
    "tgn:id":7254993,
    "tgn:name":"Quatre, Darse",
    "tgn:placetype":[
        "aat:300120801"
    ]
},
  "bbox": [],
  "geometry": {"coordinates":[4.369113,51.254604],"type":"Point"}
}