{
  "id": 7214135,
  "type": "Feature",
  "properties": {
    "tgn:hierarchy":[
        "tgn:7214135",
        "tgn:1000003",
        "tgn:7003687",
        "tgn:7000084",
        "tgn:7029392"
    ],
    "tgn:id":7214135,
    "tgn:name":"Blons-Berg",
    "tgn:placetype":[
        "aat:300008777"
    ]
},
  "bbox": [],
  "geometry": {"coordinates":[11.933333,51.583333],"type":"Point"}
}