{
  "id": 7498195,
  "type": "Feature",
  "properties": {
    "tgn:hierarchy":[
        "tgn:7498195",
        "tgn:7001004",
        "tgn:1000004",
        "tgn:1000141",
        "tgn:7029392"
    ],
    "tgn:id":7498195,
    "tgn:name":"Mei Qiao",
    "tgn:placetype":[
        "aat:300007836"
    ]
},
  "bbox": [],
  "geometry": {"coordinates":[120.825632,23.271203],"type":"Point"}
}