{
  "id": 2053736,
  "type": "Feature",
  "properties": {
    "tgn:hierarchy":[
        "tgn:2053736",
        "tgn:1000001",
        "tgn:7012149",
        "tgn:1002603",
        "tgn:7007520",
        "tgn:7029392"
    ],
    "tgn:id":2053736,
    "tgn:name":"Williamsville",
    "tgn:placetype":[
        "aat:300008347",
        "aat:300387210"
    ]
},
  "bbox": [],
  "geometry": {"coordinates":[-84.0833,42.4333],"type":"Point"}
}