{
  "id": 2767740,
  "type": "Feature",
  "properties": {
    "tgn:hierarchy":[
        "tgn:2767740",
        "tgn:1000001",
        "tgn:7012149",
        "tgn:1002492",
        "tgn:7007826",
        "tgn:7029392"
    ],
    "tgn:id":2767740,
    "tgn:name":"Whitehead",
    "tgn:placetype":[
        "aat:300008347"
    ]
},
  "bbox": [],
  "geometry": {"coordinates":[-96.25,32.8667],"type":"Point"}
}