{
  "id": 2720243,
  "type": "Feature",
  "properties": {
    "tgn:hierarchy":[
        "tgn:2720243",
        "tgn:1000001",
        "tgn:1002286",
        "tgn:7012149",
        "tgn:7007710",
        "tgn:7029392"
    ],
    "tgn:id":2720243,
    "tgn:name":"Threepoint Hollow",
    "tgn:placetype":[
        "aat:300008761"
    ]
},
  "bbox": [],
  "geometry": {"coordinates":[-77.9167,41.3333],"type":"Point"}
}