{
  "id": 7587626,
  "type": "Feature",
  "properties": {
    "tgn:hierarchy":[
        "tgn:7587626",
        "tgn:1000004",
        "tgn:7000198",
        "tgn:7000799",
        "tgn:7029392"
    ],
    "tgn:id":7587626,
    "tgn:name:en":"Tengpur",
    "tgn:placetype":[
        "aat:300008347"
    ]
},
  "bbox": [],
  "geometry": {"coordinates":[74.780215,34.060882],"type":"Point"}
}