{
  "id": 7488689,
  "type": "Feature",
  "properties": {
    "tgn:hierarchy":[
        "tgn:7488689",
        "tgn:1000004",
        "tgn:7490934",
        "tgn:1000141",
        "tgn:7029392"
    ],
    "tgn:id":7488689,
    "tgn:name":"Guidan",
    "tgn:placetype":[
        "aat:300008347"
    ]
},
  "bbox": [],
  "geometry": {"coordinates":[120.496209,23.133802],"type":"Point"}
}