{
  "id": 7574532,
  "type": "Feature",
  "properties": {
    "tgn:hierarchy":[
        "tgn:7574532",
        "tgn:1000004",
        "tgn:7000198",
        "tgn:1001894",
        "tgn:7029392"
    ],
    "tgn:id":7574532,
    "tgn:name:en":"Kunwar Kotri",
    "tgn:placetype":[
        "aat:300008347"
    ]
},
  "bbox": [],
  "geometry": {"coordinates":[76.91492,23.671885],"type":"Point"}
}