{
  "id": 2559109,
  "type": "Feature",
  "properties": {
    "tgn:hierarchy":[
        "tgn:2559109",
        "tgn:1000001",
        "tgn:7012149",
        "tgn:7007157",
        "tgn:1002857",
        "tgn:7029392"
    ],
    "tgn:id":2559109,
    "tgn:name":"One Hole Spring",
    "tgn:placetype":[
        "aat:300008697"
    ]
},
  "bbox": [],
  "geometry": {"coordinates":[-116.6333,34.3333],"type":"Point"}
}