{
  "id": 7577371,
  "type": "Feature",
  "properties": {
    "tgn:hierarchy":[
        "tgn:7577371",
        "tgn:1000004",
        "tgn:7000198",
        "tgn:7016788",
        "tgn:7029392"
    ],
    "tgn:id":7577371,
    "tgn:name:en":"Karnesar",
    "tgn:placetype":[
        "aat:300008347"
    ]
},
  "bbox": [],
  "geometry": {"coordinates":[72.49327,27.995709],"type":"Point"}
}