{
  "id": 2425344,
  "type": "Feature",
  "properties": {
    "tgn:hierarchy":[
        "tgn:2425344",
        "tgn:1000001",
        "tgn:7012149",
        "tgn:2000483",
        "tgn:7007250",
        "tgn:7029392"
    ],
    "tgn:id":2425344,
    "tgn:name":"Johnson Reservoir",
    "tgn:placetype":[
        "aat:300006191"
    ]
},
  "bbox": [],
  "geometry": {"coordinates":[-114.1833,43.1833],"type":"Point"}
}