{
  "id": 1098890,
  "type": "Feature",
  "properties": {
    "tgn:hierarchy":[
        "tgn:1098890",
        "tgn:7016670",
        "tgn:1008380",
        "tgn:1000226",
        "tgn:1000006",
        "tgn:7029392"
    ],
    "tgn:id":1098890,
    "tgn:name:en":"Clive",
    "tgn:placetype":[
        "aat:300008347"
    ]
},
  "bbox": [],
  "geometry": {"coordinates":[176.916667,-39.583333],"type":"Point"}
}