<<<<<<< HEAD
{
  "id": 7471619,
  "type": "Feature",
  "properties": {
    "tgn:hierarchy":[
        "tgn:7471619",
        "tgn:7001004",
        "tgn:1000004",
        "tgn:1000141",
        "tgn:7029392"
    ],
    "tgn:id":7471619,
    "tgn:name":"Xiaqingshui",
    "tgn:placetype":[
        "aat:300008347"
    ]
},
  "bbox": [],
  "geometry": {"coordinates":[120.506667,22.865278],"type":"Point"}
}
=======
{"geometry":{"type":"Point","coordinates":[120.506667,22.865278]},"type":"Feature","properties":{"hierarchy":["tgn:7471619","tgn:7001004","tgn:1000004","tgn:1000141","tgn:7029392"],"placetype":["aat:300008347"],"id":7471619,"name:xx":"Xiaqingshui"}}
>>>>>>> 03f74aca74312dbeaf24d7e61306dd6a786dc3d0
