{
  "id": 2379021,
  "type": "Feature",
  "properties": {
    "tgn:hierarchy":[
        "tgn:2379021",
        "tgn:1002172",
        "tgn:1000001",
        "tgn:7012149",
        "tgn:7007710",
        "tgn:7029392"
    ],
    "tgn:id":2379021,
    "tgn:name":"Hartley",
    "tgn:placetype":[
        "aat:300008347"
    ]
},
  "bbox": [],
  "geometry": {"coordinates":[-78.45,40.0167],"type":"Point"}
}