{
  "id": 7296443,
  "type": "Feature",
  "properties": {
    "tgn:hierarchy":[
        "tgn:7296443",
        "tgn:7001165",
        "tgn:1000003",
        "tgn:7002793",
        "tgn:1000095",
        "tgn:7029392"
    ],
    "tgn:id":7296443,
    "tgn:name":"Villamarchante",
    "tgn:placetype":[
        "aat:300008347"
    ]
},
  "bbox": [],
  "geometry": {"coordinates":[-0.616667,39.566667],"type":"Point"}
}