{
  "id": 1055028,
  "type": "Feature",
  "properties": {
    "tgn:hierarchy":[
        "tgn:1055028",
        "tgn:7011436",
        "tgn:1000004",
        "tgn:7006646",
        "tgn:7029392"
    ],
    "tgn:id":1055028,
    "tgn:name":"Karabaglyar",
    "tgn:placetype":[
        "aat:300008347"
    ]
},
  "bbox": [],
  "geometry": {"coordinates":[45.1833,39.4167],"type":"Point"}
}