{
  "id": 7590770,
  "type": "Feature",
  "properties": {
    "tgn:hierarchy":[
        "tgn:7590770",
        "tgn:1000004",
        "tgn:7000198",
        "tgn:7000799",
        "tgn:7029392"
    ],
    "tgn:id":7590770,
    "tgn:name:en":"D\u0101bra",
    "tgn:placetype":[
        "aat:300008347"
    ]
},
  "bbox": [],
  "geometry": {"coordinates":[74.625064,32.857111],"type":"Point"}
}