{
  "id": 2762207,
  "type": "Feature",
  "properties": {
    "tgn:hierarchy":[
        "tgn:2762207",
        "tgn:1000001",
        "tgn:7012149",
        "tgn:2002039",
        "tgn:7007826",
        "tgn:7029392"
    ],
    "tgn:id":2762207,
    "tgn:name":"West Squirrel Creek",
    "tgn:placetype":[
        "aat:300008706"
    ]
},
  "bbox": [],
  "geometry": {"coordinates":[-99.3333,29.3333],"type":"Point"}
}