<<<<<<< HEAD
{
  "id": 2762207,
  "type": "Feature",
  "properties": {
    "tgn:hierarchy":[
        "tgn:2762207",
        "tgn:1000001",
        "tgn:7012149",
        "tgn:2002039",
        "tgn:7007826",
        "tgn:7029392"
    ],
    "tgn:id":2762207,
    "tgn:name":"West Squirrel Creek",
    "tgn:placetype":[
        "aat:300008706"
    ]
},
  "bbox": [],
  "geometry": {"coordinates":[-99.3333,29.3333],"type":"Point"}
}
=======
{"geometry":{"type":"Point","coordinates":[-99.333300,29.333300]},"type":"Feature","properties":{"hierarchy":["tgn:2762207","tgn:1000001","tgn:7012149","tgn:2002039","tgn:7007826","tgn:7029392"],"placetype":["aat:300008706"],"id":2762207,"name:xx":"West Squirrel Creek"}}
>>>>>>> 03f74aca74312dbeaf24d7e61306dd6a786dc3d0
