{
  "id": 2623733,
  "type": "Feature",
  "properties": {
    "tgn:hierarchy":[
        "tgn:2623733",
        "tgn:1000001",
        "tgn:1002308",
        "tgn:7012149",
        "tgn:7007710",
        "tgn:7029392"
    ],
    "tgn:id":2623733,
    "tgn:name":"Rock Creek",
    "tgn:placetype":[
        "aat:300008706"
    ]
},
  "bbox": [],
  "geometry": {"coordinates":[-80.15,41.4833],"type":"Point"}
}