{
  "id": 7382115,
  "type": "Feature",
  "properties": {
    "tgn:hierarchy":[
        "tgn:7382115",
        "tgn:7005586",
        "tgn:1000001",
        "tgn:7005560",
        "tgn:7029392"
    ],
    "tgn:id":7382115,
    "tgn:name":"Los Pericos, Cerro",
    "tgn:placetype":[
        "aat:300008795"
    ]
},
  "bbox": [],
  "geometry": {"coordinates":[-104.133333,20.616667],"type":"Point"}
}