{
  "id": 7175510,
  "type": "Feature",
  "properties": {
    "tgn:hierarchy":[
        "tgn:7175510",
        "tgn:1000003",
        "tgn:7003685",
        "tgn:7000084",
        "tgn:7029392"
    ],
    "tgn:id":7175510,
    "tgn:name":"Gro\u00dfer Affenstein",
    "tgn:placetype":[
        "aat:300011692"
    ]
},
  "bbox": [],
  "geometry": {"coordinates":[12.333333,50.433333],"type":"Point"}
}