{
  "id": 2741013,
  "type": "Feature",
  "properties": {
    "tgn:hierarchy":[
        "tgn:2741013",
        "tgn:1000001",
        "tgn:7012149",
        "tgn:7007709",
        "tgn:7029392"
    ],
    "tgn:id":2741013,
    "tgn:name":"Upper Spring Creek",
    "tgn:placetype":[
        "aat:300008706"
    ]
},
  "bbox": [],
  "geometry": {"coordinates":[-76.55,35.25],"type":"Point"}
}