{
  "id": 2467115,
  "type": "Feature",
  "properties": {
    "tgn:hierarchy":[
        "tgn:2467115",
        "tgn:1000001",
        "tgn:7012149",
        "tgn:2001526",
        "tgn:7007709",
        "tgn:7029392"
    ],
    "tgn:id":2467115,
    "tgn:name":"Long Creek",
    "tgn:placetype":[
        "aat:300008706"
    ]
},
  "bbox": [],
  "geometry": {"coordinates":[-76.55,35.1333],"type":"Point"}
}