{
  "id": 1052701,
  "type": "Feature",
  "properties": {
    "tgn:hierarchy":[
        "tgn:1052701",
        "tgn:1000004",
        "tgn:7011573",
        "tgn:7018214",
        "tgn:7002435",
        "tgn:7029392"
    ],
    "tgn:id":1052701,
    "tgn:name":"Belyye Stolby",
    "tgn:placetype":[
        "aat:300008347"
    ]
},
  "bbox": [],
  "geometry": {"coordinates":[37.85,55.3333],"type":"Point"}
}