{
  "id": 7089171,
  "type": "Feature",
  "properties": {
    "tgn:hierarchy":[
        "tgn:7089171",
        "tgn:1000003",
        "tgn:7003685",
        "tgn:7000084",
        "tgn:7029392"
    ],
    "tgn:id":7089171,
    "tgn:name":"Unterwuchs-Berge",
    "tgn:placetype":[
        "aat:300008777"
    ]
},
  "bbox": [],
  "geometry": {"coordinates":[14.666667,51.45],"type":"Point"}
}