{
  "id": 2056443,
  "type": "Feature",
  "properties": {
    "tgn:hierarchy":[
        "tgn:2056443",
        "tgn:1000001",
        "tgn:7012149",
        "tgn:2001164",
        "tgn:7007522",
        "tgn:7029392"
    ],
    "tgn:id":2056443,
    "tgn:name":"Fort Adams",
    "tgn:placetype":[
        "aat:300008347"
    ]
},
  "bbox": [],
  "geometry": {"coordinates":[-91.5333,31.0833],"type":"Point"}
}