{
  "id": 7319247,
  "type": "Feature",
  "properties": {
    "tgn:hierarchy":[
        "tgn:7319247",
        "tgn:7016598",
        "tgn:1000049",
        "tgn:1000002",
        "tgn:7029392"
    ],
    "tgn:id":7319247,
    "tgn:name":"Andamito, Cerro de",
    "tgn:placetype":[
        "aat:300008777"
    ]
},
  "bbox": [],
  "geometry": {"coordinates":[-69.883333,-21.466667],"type":"Point"}
}