{
  "id": 7115142,
  "type": "Feature",
  "properties": {
    "tgn:hierarchy":[
        "tgn:7115142",
        "tgn:7003669",
        "tgn:1000003",
        "tgn:7000084",
        "tgn:7029392"
    ],
    "tgn:id":7115142,
    "tgn:name":"Ochsenbrunn",
    "tgn:placetype":[
        "aat:300008347"
    ]
},
  "bbox": [],
  "geometry": {"coordinates":[11.666667,50.233333],"type":"Point"}
}