<<<<<<< HEAD
{
  "id": 7028035,
  "type": "Feature",
  "properties": {
    "tgn:hierarchy":[
        "tgn:7028035",
        "tgn:7002445",
        "tgn:1000003",
        "tgn:7008157",
        "tgn:7008591",
        "tgn:7029392"
    ],
    "tgn:id":7028035,
    "tgn:name:en":"Raithby",
    "tgn:placetype":[
        "aat:300008347",
        "aat:300008372"
    ]
},
  "bbox": [],
  "geometry": {"coordinates":[0.066667,53.166667],"type":"Point"}
}
=======
{"geometry":{"type":"Point","coordinates":[0.066667,53.166667]},"type":"Feature","properties":{"hierarchy":["tgn:7028035","tgn:7002445","tgn:1000003","tgn:7008157","tgn:7008591","tgn:7029392"],"placetype":["aat:300008347","aat:300008372"],"name:en":"Raithby","id":7028035}}
>>>>>>> 03f74aca74312dbeaf24d7e61306dd6a786dc3d0
