{
  "id": 2615374,
  "type": "Feature",
  "properties": {
    "tgn:hierarchy":[
        "tgn:2615374",
        "tgn:1000001",
        "tgn:7012149",
        "tgn:1002994",
        "tgn:7007708",
        "tgn:7029392"
    ],
    "tgn:id":2615374,
    "tgn:name":"Reservoir Number Two",
    "tgn:placetype":[
        "aat:300006191"
    ]
},
  "bbox": [],
  "geometry": {"coordinates":[-122.9833,45.45],"type":"Point"}
}