<<<<<<< HEAD
{
  "id": 7472816,
  "type": "Feature",
  "properties": {
    "tgn:hierarchy":[
        "tgn:7472816",
        "tgn:1000004",
        "tgn:7467799",
        "tgn:1000141",
        "tgn:7029392"
    ],
    "tgn:id":7472816,
    "tgn:name":"Yongxing Haibu Xinshengdi Haiti",
    "tgn:placetype":[
        "aat:300006156"
    ]
},
  "bbox": [],
  "geometry": {"coordinates":[120.312989,23.9546],"type":"Point"}
}
=======
{"geometry":{"type":"Point","coordinates":[120.312989,23.954600]},"type":"Feature","properties":{"hierarchy":["tgn:7472816","tgn:1000004","tgn:7467799","tgn:1000141","tgn:7029392"],"placetype":["aat:300006156"],"id":7472816,"name:xx":"Yongxing Haibu Xinshengdi Haiti"}}
>>>>>>> 03f74aca74312dbeaf24d7e61306dd6a786dc3d0
