{
  "id": 7492667,
  "type": "Feature",
  "properties": {
    "tgn:hierarchy":[
        "tgn:7492667",
        "tgn:1000004",
        "tgn:7492971",
        "tgn:1000141",
        "tgn:7029392"
    ],
    "tgn:id":7492667,
    "tgn:name":"Wan'an Cun",
    "tgn:placetype":[
        "aat:300387173"
    ]
},
  "bbox": [],
  "geometry": {"coordinates":[120.642948,22.631563],"type":"Point"}
}