{
  "id": 1071630,
  "type": "Feature",
  "properties": {
    "tgn:hierarchy":[
        "tgn:1071630",
        "tgn:7002075",
        "tgn:1000004",
        "tgn:1000111",
        "tgn:7029392"
    ],
    "tgn:id":1071630,
    "tgn:name":"Shiba",
    "tgn:placetype":[
        "aat:300008347"
    ]
},
  "bbox": [],
  "geometry": {"coordinates":[118.1167,32.75],"type":"Point"}
}