{
  "id": 2083625,
  "type": "Feature",
  "properties": {
    "tgn:hierarchy":[
        "tgn:2083625",
        "tgn:1000001",
        "tgn:7012149",
        "tgn:2001662",
        "tgn:7007707",
        "tgn:7029392"
    ],
    "tgn:id":2083625,
    "tgn:name":"Monroe",
    "tgn:placetype":[
        "aat:300008347"
    ]
},
  "bbox": [],
  "geometry": {"coordinates":[-94.5167,34.9833],"type":"Point"}
}