{
  "id": 2008397,
  "type": "Feature",
  "properties": {
    "tgn:hierarchy":[
        "tgn:2008397",
        "tgn:1000001",
        "tgn:7016172",
        "tgn:2000115",
        "tgn:7012149",
        "tgn:7029392"
    ],
    "tgn:id":2008397,
    "tgn:name":"Greenway",
    "tgn:placetype":[
        "aat:300008347"
    ]
},
  "bbox": [],
  "geometry": {"coordinates":[-90.2167,36.3333],"type":"Point"}
}