{
  "id": 7416877,
  "type": "Feature",
  "properties": {
    "tgn:hierarchy":[
        "tgn:7416877",
        "tgn:1000001",
        "tgn:7005591",
        "tgn:7005560",
        "tgn:7029392"
    ],
    "tgn:id":7416877,
    "tgn:name:es":"Soledad Piedra",
    "tgn:placetype":[
        "aat:300008347"
    ]
},
  "bbox": [],
  "geometry": {"coordinates":[-97.036667,16.131944],"type":"Point"}
}