{
  "id": 2343861,
  "type": "Feature",
  "properties": {
    "tgn:hierarchy":[
        "tgn:2343861",
        "tgn:1000001",
        "tgn:7012149",
        "tgn:1002961",
        "tgn:7007568",
        "tgn:7029392"
    ],
    "tgn:id":2343861,
    "tgn:name":"Gallis Hill",
    "tgn:placetype":[
        "aat:300008798"
    ]
},
  "bbox": [],
  "geometry": {"coordinates":[-74.0667,41.95],"type":"Point"}
}