{
  "id": 7305792,
  "type": "Feature",
  "properties": {
    "tgn:hierarchy":[
        "tgn:7305792",
        "tgn:7002816",
        "tgn:1001647",
        "tgn:1000003",
        "tgn:1000095",
        "tgn:7029392"
    ],
    "tgn:id":7305792,
    "tgn:name":"Manzaire, Sierra del",
    "tgn:placetype":[
        "aat:300008795"
    ]
},
  "bbox": [],
  "geometry": {"coordinates":[-4.683333,38.716667],"type":"Point"}
}