<<<<<<< HEAD
{
  "id": 2335532,
  "type": "Feature",
  "properties": {
    "tgn:hierarchy":[
        "tgn:2335532",
        "tgn:1000001",
        "tgn:2001435",
        "tgn:7012149",
        "tgn:7007566",
        "tgn:7029392"
    ],
    "tgn:id":2335532,
    "tgn:name":"Fort Selden",
    "tgn:placetype":[
        "aat:300008347"
    ]
},
  "bbox": [],
  "geometry": {"coordinates":[-106.9,32.4833],"type":"Point"}
}
=======
{"geometry":{"type":"Point","coordinates":[-106.900000,32.483300]},"type":"Feature","properties":{"hierarchy":["tgn:2335532","tgn:1000001","tgn:2001435","tgn:7012149","tgn:7007566","tgn:7029392"],"placetype":["aat:300008347"],"id":2335532,"name:xx":"Fort Selden"}}
>>>>>>> 03f74aca74312dbeaf24d7e61306dd6a786dc3d0
