{
  "id": 2570086,
  "type": "Feature",
  "properties": {
    "tgn:hierarchy":[
        "tgn:2570086",
        "tgn:1000001",
        "tgn:2000199",
        "tgn:7012149",
        "tgn:7007158",
        "tgn:7029392"
    ],
    "tgn:id":2570086,
    "tgn:name":"Pass Creek Lake",
    "tgn:placetype":[
        "aat:300008680"
    ]
},
  "bbox": [],
  "geometry": {"coordinates":[-106.2167,38.45],"type":"Point"}
}