<<<<<<< HEAD
{
  "id": 2337394,
  "type": "Feature",
  "properties": {
    "tgn:hierarchy":[
        "tgn:2337394",
        "tgn:1000001",
        "tgn:7012149",
        "tgn:2000931",
        "tgn:7007515",
        "tgn:7029392"
    ],
    "tgn:id":2337394,
    "tgn:name":"Fowler Bog",
    "tgn:placetype":[
        "aat:300008905"
    ]
},
  "bbox": [],
  "geometry": {"coordinates":[-69.4,44.55],"type":"Point"}
}
=======
{"geometry":{"type":"Point","coordinates":[-69.400000,44.550000]},"type":"Feature","properties":{"hierarchy":["tgn:2337394","tgn:1000001","tgn:7012149","tgn:2000931","tgn:7007515","tgn:7029392"],"placetype":["aat:300008905"],"id":2337394,"name:xx":"Fowler Bog"}}
>>>>>>> 03f74aca74312dbeaf24d7e61306dd6a786dc3d0
