{
  "id": 2425336,
  "type": "Feature",
  "properties": {
    "tgn:hierarchy":[
        "tgn:2425336",
        "tgn:1000001",
        "tgn:7012149",
        "tgn:7007157",
        "tgn:2000187",
        "tgn:7029392"
    ],
    "tgn:id":2425336,
    "tgn:name":"Johnson Ravine",
    "tgn:placetype":[
        "aat:300008761"
    ]
},
  "bbox": [],
  "geometry": {"coordinates":[-121.0833,40.0667],"type":"Point"}
}