{
  "id": 7308913,
  "type": "Feature",
  "properties": {
    "tgn:hierarchy":[
        "tgn:7308913",
        "tgn:1001692",
        "tgn:1000049",
        "tgn:1000002",
        "tgn:7029392"
    ],
    "tgn:id":7308913,
    "tgn:name":"Mallenco, Estero",
    "tgn:placetype":[
        "aat:300008699"
    ]
},
  "bbox": [],
  "geometry": {"coordinates":[-72.433333,-38.25],"type":"Point"}
}