<<<<<<< HEAD
{
  "id": 2333254,
  "type": "Feature",
  "properties": {
    "tgn:hierarchy":[
        "tgn:2333254",
        "tgn:1000001",
        "tgn:7012149",
        "tgn:2002184",
        "tgn:7007919",
        "tgn:7029392"
    ],
    "tgn:id":2333254,
    "tgn:name":"Fodder Stack Mountain",
    "tgn:placetype":[
        "aat:300008798"
    ]
},
  "bbox": [],
  "geometry": {"coordinates":[-78.1333,38.7333],"type":"Point"}
}
=======
{"geometry":{"type":"Point","coordinates":[-78.133300,38.733300]},"type":"Feature","properties":{"hierarchy":["tgn:2333254","tgn:1000001","tgn:7012149","tgn:2002184","tgn:7007919","tgn:7029392"],"placetype":["aat:300008798"],"id":2333254,"name:xx":"Fodder Stack Mountain"}}
>>>>>>> 03f74aca74312dbeaf24d7e61306dd6a786dc3d0
