{
  "id": 2663030,
  "type": "Feature",
  "properties": {
    "tgn:hierarchy":[
        "tgn:2663030",
        "tgn:1000001",
        "tgn:7012149",
        "tgn:2002344",
        "tgn:7007922",
        "tgn:7029392"
    ],
    "tgn:id":2663030,
    "tgn:name":"Silver Birch Lake",
    "tgn:placetype":[
        "aat:300008680"
    ]
},
  "bbox": [],
  "geometry": {"coordinates":[-92.0167,44.5833],"type":"Point"}
}