{
  "id": 2074850,
  "type": "Feature",
  "properties": {
    "tgn:hierarchy":[
        "tgn:2074850",
        "tgn:2001466",
        "tgn:1000001",
        "tgn:7012149",
        "tgn:7007709",
        "tgn:7029392"
    ],
    "tgn:id":2074850,
    "tgn:name":"Gravelton",
    "tgn:placetype":[
        "aat:300387016"
    ]
},
  "bbox": [],
  "geometry": {"coordinates":[-79.9167,34.9333],"type":"Point"}
}