{
  "id": 1036049,
  "type": "Feature",
  "properties": {
    "tgn:hierarchy":[
        "tgn:1036049",
        "tgn:1000003",
        "tgn:7002880",
        "tgn:1000070",
        "tgn:7029392"
    ],
    "tgn:id":1036049,
    "tgn:name":"Vendeuvre-sur-Barse",
    "tgn:placetype":[
        "aat:300008347"
    ]
},
  "bbox": [],
  "geometry": {"coordinates":[4.4833,48.2333],"type":"Point"}
}