{
  "id": 7289108,
  "type": "Feature",
  "properties": {
    "tgn:hierarchy":[
        "tgn:7289108",
        "tgn:7002464",
        "tgn:1000049",
        "tgn:1000002",
        "tgn:7029392"
    ],
    "tgn:id":7289108,
    "tgn:name":"Estaci\u00f3n Huemul",
    "tgn:placetype":[
        "aat:300007783"
    ]
},
  "bbox": [],
  "geometry": {"coordinates":[-69.983333,-20.366667],"type":"Point"}
}