{
  "id": 7575458,
  "type": "Feature",
  "properties": {
    "tgn:hierarchy":[
        "tgn:7575458",
        "tgn:1000004",
        "tgn:7000198",
        "tgn:1001894",
        "tgn:7029392"
    ],
    "tgn:id":7575458,
    "tgn:name:en":"Mah\u0101r\u0101jpur",
    "tgn:placetype":[
        "aat:300008347"
    ]
},
  "bbox": [],
  "geometry": {"coordinates":[77.982152,26.469105],"type":"Point"}
}