{
  "id": 2727143,
  "type": "Feature",
  "properties": {
    "tgn:hierarchy":[
        "tgn:2727143",
        "tgn:1000001",
        "tgn:7012149",
        "tgn:2000844",
        "tgn:7007255",
        "tgn:7029392"
    ],
    "tgn:id":2727143,
    "tgn:name":"Trace Fork",
    "tgn:placetype":[
        "aat:300008699"
    ]
},
  "bbox": [],
  "geometry": {"coordinates":[-85.2833,37.4167],"type":"Point"}
}