{
  "id": 2718486,
  "type": "Feature",
  "properties": {
    "tgn:hierarchy":[
        "tgn:2718486",
        "tgn:1000001",
        "tgn:7012149",
        "tgn:7007157",
        "tgn:1002915",
        "tgn:7029392"
    ],
    "tgn:id":2718486,
    "tgn:name":"Thompson Lateral",
    "tgn:placetype":[
        "aat:300006075"
    ]
},
  "bbox": [],
  "geometry": {"coordinates":[-120.8667,37.6833],"type":"Point"}
}