{
  "id": 7552938,
  "type": "Feature",
  "properties": {
    "tgn:hierarchy":[
        "tgn:7552938",
        "tgn:1000004",
        "tgn:7000198",
        "tgn:1001894",
        "tgn:7029392"
    ],
    "tgn:id":7552938,
    "tgn:name:en":"Muhammadgarh",
    "tgn:placetype":[
        "aat:300008347"
    ]
},
  "bbox": [],
  "geometry": {"coordinates":[78.164894,23.643848],"type":"Point"}
}