{
  "id": 2742318,
  "type": "Feature",
  "properties": {
    "tgn:hierarchy":[
        "tgn:2742318",
        "tgn:1000001",
        "tgn:7012149",
        "tgn:1009002",
        "tgn:7007157",
        "tgn:1002867",
        "tgn:7029392"
    ],
    "tgn:id":2742318,
    "tgn:name":"Valley Anchorage",
    "tgn:placetype":[
        "aat:300132316"
    ]
},
  "bbox": [],
  "geometry": {"coordinates":[-119.65,33.9833],"type":"Point"}
}