{
  "id": 1085118,
  "type": "Feature",
  "properties": {
    "tgn:hierarchy":[
        "tgn:1085118",
        "tgn:1002075",
        "tgn:1000004",
        "tgn:1000140",
        "tgn:7029392"
    ],
    "tgn:id":1085118,
    "tgn:name":"Bu\u1e63ayrah",
    "tgn:placetype":[
        "aat:300008347"
    ]
},
  "bbox": [],
  "geometry": {"coordinates":[40.4333,35.1667],"type":"Point"}
}