<<<<<<< HEAD
{
  "id": 2401673,
  "type": "Feature",
  "properties": {
    "tgn:hierarchy":[
        "tgn:2401673",
        "tgn:1000001",
        "tgn:2000272",
        "tgn:7012149",
        "tgn:7007240",
        "tgn:7029392"
    ],
    "tgn:id":2401673,
    "tgn:name":"Horseshoe Lake",
    "tgn:placetype":[
        "aat:300008680"
    ]
},
  "bbox": [],
  "geometry": {"coordinates":[-85.8667,30.8667],"type":"Point"}
}
=======
{"geometry":{"type":"Point","coordinates":[-85.866700,30.866700]},"type":"Feature","properties":{"hierarchy":["tgn:2401673","tgn:1000001","tgn:2000272","tgn:7012149","tgn:7007240","tgn:7029392"],"placetype":["aat:300008680"],"id":2401673,"name:xx":"Horseshoe Lake"}}
>>>>>>> 03f74aca74312dbeaf24d7e61306dd6a786dc3d0
