{
  "id": 2401673,
  "type": "Feature",
  "properties": {
    "tgn:hierarchy":[
        "tgn:2401673",
        "tgn:1000001",
        "tgn:2000272",
        "tgn:7012149",
        "tgn:7007240",
        "tgn:7029392"
    ],
    "tgn:id":2401673,
    "tgn:name":"Horseshoe Lake",
    "tgn:placetype":[
        "aat:300008680"
    ]
},
  "bbox": [],
  "geometry": {"coordinates":[-85.8667,30.8667],"type":"Point"}
}