<<<<<<< HEAD
{
  "id": 2763332,
  "type": "Feature",
  "properties": {
    "tgn:hierarchy":[
        "tgn:2763332",
        "tgn:1002145",
        "tgn:1000001",
        "tgn:7012149",
        "tgn:7007157",
        "tgn:7029392"
    ],
    "tgn:id":2763332,
    "tgn:name":"Wet Meadows Reservoir",
    "tgn:placetype":[
        "aat:300006191"
    ]
},
  "bbox": [],
  "geometry": {"coordinates":[-119.85,38.6],"type":"Point"}
}
=======
{"geometry":{"type":"Point","coordinates":[-119.850000,38.600000]},"type":"Feature","properties":{"hierarchy":["tgn:2763332","tgn:1002145","tgn:1000001","tgn:7012149","tgn:7007157","tgn:7029392"],"placetype":["aat:300006191"],"id":2763332,"name:xx":"Wet Meadows Reservoir"}}
>>>>>>> 03f74aca74312dbeaf24d7e61306dd6a786dc3d0
