{
  "id": 7305219,
  "type": "Feature",
  "properties": {
    "tgn:hierarchy":[
        "tgn:7305219",
        "tgn:7002820",
        "tgn:7030216",
        "tgn:1000003",
        "tgn:1000095",
        "tgn:7029392"
    ],
    "tgn:id":7305219,
    "tgn:name":"La Sellera de Ter",
    "tgn:placetype":[
        "aat:300008347"
    ]
},
  "bbox": [],
  "geometry": {"coordinates":[2.620412,41.968434],"type":"Point"}
}