{
  "id": 7046111,
  "type": "Feature",
  "properties": {
    "tgn:hierarchy":[
        "tgn:7046111",
        "tgn:7015163",
        "tgn:1000003",
        "tgn:7003121",
        "tgn:1000080",
        "tgn:7029392"
    ],
    "tgn:id":7046111,
    "tgn:name":"Regione Campeda",
    "tgn:placetype":[
        "aat:300055621"
    ]
},
  "bbox": [],
  "geometry": {"coordinates":[8.766667,40.366667],"type":"Point"}
}