{
  "id": 1042757,
  "type": "Feature",
  "properties": {
    "tgn:hierarchy":[
        "tgn:1042757",
        "tgn:7003497",
        "tgn:7001201",
        "tgn:1000003",
        "tgn:1000078",
        "tgn:7029392"
    ],
    "tgn:id":1042757,
    "tgn:name":"Donoughmore",
    "tgn:placetype":[
        "aat:300008347"
    ]
},
  "bbox": [],
  "geometry": {"coordinates":[-8.75,51.95],"type":"Point"}
}