{
  "id": 2082933,
  "type": "Feature",
  "properties": {
    "tgn:hierarchy":[
        "tgn:2082933",
        "tgn:1000001",
        "tgn:2001642",
        "tgn:7012149",
        "tgn:7007707",
        "tgn:7029392"
    ],
    "tgn:id":2082933,
    "tgn:name":"Butler",
    "tgn:placetype":[
        "aat:300008347"
    ]
},
  "bbox": [],
  "geometry": {"coordinates":[-99.1833,35.6333],"type":"Point"}
}