<<<<<<< HEAD
{
  "id": 7472277,
  "type": "Feature",
  "properties": {
    "tgn:hierarchy":[
        "tgn:7472277",
        "tgn:1000004",
        "tgn:7467799",
        "tgn:1000141",
        "tgn:7029392"
    ],
    "tgn:id":7472277,
    "tgn:name":"Cuozi",
    "tgn:placetype":[
        "aat:300008347"
    ]
},
  "bbox": [],
  "geometry": {"coordinates":[120.449985,23.90802],"type":"Point"}
}
=======
{"geometry":{"type":"Point","coordinates":[120.449985,23.908020]},"type":"Feature","properties":{"hierarchy":["tgn:7472277","tgn:1000004","tgn:7467799","tgn:1000141","tgn:7029392"],"placetype":["aat:300008347"],"id":7472277,"name:xx":"Cuozi"}}
>>>>>>> 03f74aca74312dbeaf24d7e61306dd6a786dc3d0
