{
  "id": 7472277,
  "type": "Feature",
  "properties": {
    "tgn:hierarchy":[
        "tgn:7472277",
        "tgn:1000004",
        "tgn:7467799",
        "tgn:1000141",
        "tgn:7029392"
    ],
    "tgn:id":7472277,
    "tgn:name":"Cuozi",
    "tgn:placetype":[
        "aat:300008347"
    ]
},
  "bbox": [],
  "geometry": {"coordinates":[120.449985,23.90802],"type":"Point"}
}