{
  "id": 7337635,
  "type": "Feature",
  "properties": {
    "tgn:hierarchy":[
        "tgn:7337635",
        "tgn:7002813",
        "tgn:7002758",
        "tgn:1000003",
        "tgn:1000095",
        "tgn:7029392"
    ],
    "tgn:id":7337635,
    "tgn:name":"Charcos, Arroyo de los",
    "tgn:placetype":[
        "aat:300008699"
    ]
},
  "bbox": [],
  "geometry": {"coordinates":[-5.85,36.75],"type":"Point"}
}