{
  "id": 2632065,
  "type": "Feature",
  "properties": {
    "tgn:hierarchy":[
        "tgn:2632065",
        "tgn:1000001",
        "tgn:7012149",
        "tgn:2000226",
        "tgn:7007158",
        "tgn:7029392"
    ],
    "tgn:id":2632065,
    "tgn:name":"Rowe Mountain",
    "tgn:placetype":[
        "aat:300008798"
    ]
},
  "bbox": [],
  "geometry": {"coordinates":[-105.6333,40.4833],"type":"Point"}
}