{
  "id": 7291077,
  "type": "Feature",
  "properties": {
    "tgn:hierarchy":[
        "tgn:7291077",
        "tgn:1001702",
        "tgn:1000049",
        "tgn:1000002",
        "tgn:7029392"
    ],
    "tgn:id":7291077,
    "tgn:name":"Delia, Isla",
    "tgn:placetype":[
        "aat:300008791"
    ]
},
  "bbox": [],
  "geometry": {"coordinates":[-67.333333,-54.916667],"type":"Point"}
}