{
  "id": 2081283,
  "type": "Feature",
  "properties": {
    "tgn:hierarchy":[
        "tgn:2081283",
        "tgn:1000001",
        "tgn:7012149",
        "tgn:2001617",
        "tgn:7007706",
        "tgn:7029392"
    ],
    "tgn:id":2081283,
    "tgn:name":"Ozark",
    "tgn:placetype":[
        "aat:300008347"
    ]
},
  "bbox": [],
  "geometry": {"coordinates":[-81.0667,39.8167],"type":"Point"}
}