{
  "id": 2213693,
  "type": "Feature",
  "properties": {
    "tgn:hierarchy":[
        "tgn:2213693",
        "tgn:1000001",
        "tgn:7012149",
        "tgn:2002252",
        "tgn:7007920",
        "tgn:7029392"
    ],
    "tgn:id":2213693,
    "tgn:name":"Cache Creek",
    "tgn:placetype":[
        "aat:300008706"
    ]
},
  "bbox": [],
  "geometry": {"coordinates":[-117.35,47.15],"type":"Point"}
}