{
  "id": 7364275,
  "type": "Feature",
  "properties": {
    "tgn:hierarchy":[
        "tgn:7364275",
        "tgn:1000001",
        "tgn:7005597",
        "tgn:7005560",
        "tgn:7029392"
    ],
    "tgn:id":7364275,
    "tgn:name":"El Bordo",
    "tgn:placetype":[
        "aat:300008347"
    ]
},
  "bbox": [],
  "geometry": {"coordinates":[-98.833333,26.35],"type":"Point"}
}