{
  "id": 2193261,
  "type": "Feature",
  "properties": {
    "tgn:hierarchy":[
        "tgn:2193261",
        "tgn:7002659",
        "tgn:1000001",
        "tgn:7012149",
        "tgn:2000051",
        "tgn:7029392"
    ],
    "tgn:id":2193261,
    "tgn:name":"Breeding Mountain",
    "tgn:placetype":[
        "aat:300266640"
    ]
},
  "bbox": [],
  "geometry": {"coordinates":[-86.7167,34.5167],"type":"Point"}
}