{
  "id": 7588665,
  "type": "Feature",
  "properties": {
    "tgn:hierarchy":[
        "tgn:7588665",
        "tgn:1000004",
        "tgn:7000198",
        "tgn:7000799",
        "tgn:7029392"
    ],
    "tgn:id":7588665,
    "tgn:name:en":"Pol Padar",
    "tgn:placetype":[
        "aat:300008347"
    ]
},
  "bbox": [],
  "geometry": {"coordinates":[74.227778,33.827778],"type":"Point"}
}