<<<<<<< HEAD
{
  "id": 2403240,
  "type": "Feature",
  "properties": {
    "tgn:hierarchy":[
        "tgn:2403240",
        "tgn:1000001",
        "tgn:7012149",
        "tgn:2000546",
        "tgn:7007252",
        "tgn:7029392"
    ],
    "tgn:id":2403240,
    "tgn:name":"House Rock Branch",
    "tgn:placetype":[
        "aat:300008699"
    ]
},
  "bbox": [],
  "geometry": {"coordinates":[-86.75,38.6833],"type":"Point"}
}
=======
{"geometry":{"type":"Point","coordinates":[-86.750000,38.683300]},"type":"Feature","properties":{"hierarchy":["tgn:2403240","tgn:1000001","tgn:7012149","tgn:2000546","tgn:7007252","tgn:7029392"],"placetype":["aat:300008699"],"id":2403240,"name:xx":"House Rock Branch"}}
>>>>>>> 03f74aca74312dbeaf24d7e61306dd6a786dc3d0
