{
  "id": 2727690,
  "type": "Feature",
  "properties": {
    "tgn:hierarchy":[
        "tgn:2727690",
        "tgn:1000001",
        "tgn:7012149",
        "tgn:2002187",
        "tgn:7007919",
        "tgn:7029392"
    ],
    "tgn:id":2727690,
    "tgn:name":"Trail Ridge",
    "tgn:placetype":[
        "aat:300266640"
    ]
},
  "bbox": [],
  "geometry": {"coordinates":[-79.0167,38.5667],"type":"Point"}
}