{
  "id": 7432882,
  "type": "Feature",
  "properties": {
    "tgn:hierarchy":[
        "tgn:7432882",
        "tgn:1000001",
        "tgn:7005591",
        "tgn:7005560",
        "tgn:7029392"
    ],
    "tgn:id":7432882,
    "tgn:name":"Yucuquini",
    "tgn:placetype":[
        "aat:300008347"
    ]
},
  "bbox": [],
  "geometry": {"coordinates":[-97.866667,17.65],"type":"Point"}
}