<<<<<<< HEAD
{
  "id": 7478483,
  "type": "Feature",
  "properties": {
    "tgn:hierarchy":[
        "tgn:7478483",
        "tgn:1000004",
        "tgn:7489179",
        "tgn:1000141",
        "tgn:7029392"
    ],
    "tgn:id":7478483,
    "tgn:name":"Sanhao Qiao",
    "tgn:placetype":[
        "aat:300007836"
    ]
},
  "bbox": [],
  "geometry": {"coordinates":[121.7913,24.6731],"type":"Point"}
}
=======
{"geometry":{"type":"Point","coordinates":[121.791300,24.673100]},"type":"Feature","properties":{"hierarchy":["tgn:7478483","tgn:1000004","tgn:7489179","tgn:1000141","tgn:7029392"],"placetype":["aat:300007836"],"id":7478483,"name:xx":"Sanhao Qiao"}}
>>>>>>> 03f74aca74312dbeaf24d7e61306dd6a786dc3d0
