{
  "id": 7152570,
  "type": "Feature",
  "properties": {
    "tgn:hierarchy":[
        "tgn:7152570",
        "tgn:1000003",
        "tgn:7000094",
        "tgn:7000084",
        "tgn:7029392"
    ],
    "tgn:id":7152570,
    "tgn:name":"Kaase-Wiese",
    "tgn:placetype":[
        "aat:300386990"
    ]
},
  "bbox": [],
  "geometry": {"coordinates":[13.766667,54.166667],"type":"Point"}
}