{
  "id": 2590050,
  "type": "Feature",
  "properties": {
    "tgn:hierarchy":[
        "tgn:2590050",
        "tgn:1000001",
        "tgn:2002109",
        "tgn:7012149",
        "tgn:7007827",
        "tgn:7029392"
    ],
    "tgn:id":2590050,
    "tgn:name":"Poison Creek Reservoir Number 2",
    "tgn:placetype":[
        "aat:300006191"
    ]
},
  "bbox": [],
  "geometry": {"coordinates":[-111.8833,38.05],"type":"Point"}
}