{
  "id": 2376529,
  "type": "Feature",
  "properties": {
    "tgn:hierarchy":[
        "tgn:2376529",
        "tgn:2000453",
        "tgn:1000001",
        "tgn:7012149",
        "tgn:7007250",
        "tgn:7029392"
    ],
    "tgn:id":2376529,
    "tgn:name":"Hardrock Gulch",
    "tgn:placetype":[
        "aat:300008761"
    ]
},
  "bbox": [],
  "geometry": {"coordinates":[-116.6167,45.1667],"type":"Point"}
}