{
  "id": 7540043,
  "type": "Feature",
  "properties": {
    "tgn:hierarchy":[
        "tgn:7540043",
        "tgn:7001242",
        "tgn:7016833",
        "tgn:7000124",
        "tgn:7029392"
    ],
    "tgn:id":7540043,
    "tgn:name:en":"Nag' Hamm\u00fb'de",
    "tgn:placetype":[
        "aat:300008347"
    ]
},
  "bbox": [],
  "geometry": {"coordinates":[31.466667,26.766667],"type":"Point"}
}