{
  "id": 2372295,
  "type": "Feature",
  "properties": {
    "tgn:hierarchy":[
        "tgn:2372295",
        "tgn:1000001",
        "tgn:7012149",
        "tgn:2000878",
        "tgn:7007256",
        "tgn:7029392"
    ],
    "tgn:id":2372295,
    "tgn:name":"Halfway Creek",
    "tgn:placetype":[
        "aat:300008706"
    ]
},
  "bbox": [],
  "geometry": {"coordinates":[-92.6167,32.2667],"type":"Point"}
}