<<<<<<< HEAD
{
  "id": 2338182,
  "type": "Feature",
  "properties": {
    "tgn:hierarchy":[
        "tgn:2338182",
        "tgn:1000001",
        "tgn:7012149",
        "tgn:1002508",
        "tgn:7007252",
        "tgn:7029392"
    ],
    "tgn:id":2338182,
    "tgn:name":"Fox Pond",
    "tgn:placetype":[
        "aat:300008680"
    ]
},
  "bbox": [],
  "geometry": {"coordinates":[-86.1167,39.0333],"type":"Point"}
}
=======
{"geometry":{"type":"Point","coordinates":[-86.116700,39.033300]},"type":"Feature","properties":{"hierarchy":["tgn:2338182","tgn:1000001","tgn:7012149","tgn:1002508","tgn:7007252","tgn:7029392"],"placetype":["aat:300008680"],"id":2338182,"name:xx":"Fox Pond"}}
>>>>>>> 03f74aca74312dbeaf24d7e61306dd6a786dc3d0
