{
  "id": 7463812,
  "type": "Feature",
  "properties": {
    "tgn:hierarchy":[
        "tgn:7463812",
        "tgn:7002444",
        "tgn:1000003",
        "tgn:7029508",
        "tgn:7008591",
        "tgn:7029392"
    ],
    "tgn:id":7463812,
    "tgn:name:en":"Houss Ness",
    "tgn:placetype":[
        "aat:300008804"
    ]
},
  "bbox": [],
  "geometry": {"coordinates":[-1.333333,60.05],"type":"Point"}
}