{
  "id": 2697304,
  "type": "Feature",
  "properties": {
    "tgn:hierarchy":[
        "tgn:2697304",
        "tgn:1000001",
        "tgn:2002317",
        "tgn:7012149",
        "tgn:7007922",
        "tgn:7029392"
    ],
    "tgn:id":2697304,
    "tgn:name":"Stony Creek Swamp",
    "tgn:placetype":[
        "aat:300008905"
    ]
},
  "bbox": [],
  "geometry": {"coordinates":[-87.4333,44.7667],"type":"Point"}
}