{
  "id": 7291267,
  "type": "Feature",
  "properties": {
    "tgn:hierarchy":[
        "tgn:7291267",
        "tgn:1001708",
        "tgn:1000049",
        "tgn:1000002",
        "tgn:7029392"
    ],
    "tgn:id":7291267,
    "tgn:name":"El Retiro",
    "tgn:placetype":[
        "aat:300000206"
    ]
},
  "bbox": [],
  "geometry": {"coordinates":[-70.65,-33.633333],"type":"Point"}
}