{
  "id": 2746672,
  "type": "Feature",
  "properties": {
    "tgn:hierarchy":[
        "tgn:2746672",
        "tgn:1000001",
        "tgn:7012149",
        "tgn:2001911",
        "tgn:7007825",
        "tgn:7029392"
    ],
    "tgn:id":2746672,
    "tgn:name":"Wade",
    "tgn:placetype":[
        "aat:300008347"
    ]
},
  "bbox": [],
  "geometry": {"coordinates":[-86.4833,35.95],"type":"Point"}
}