{
  "id": 2625028,
  "type": "Feature",
  "properties": {
    "tgn:hierarchy":[
        "tgn:2625028",
        "tgn:1000001",
        "tgn:7012149",
        "tgn:2001228",
        "tgn:7007523",
        "tgn:7029392"
    ],
    "tgn:id":2625028,
    "tgn:name":"Rock Valley Lake",
    "tgn:placetype":[
        "aat:300006191"
    ]
},
  "bbox": [],
  "geometry": {"coordinates":[-89.9167,37.7667],"type":"Point"}
}