{
  "id": 2317711,
  "type": "Feature",
  "properties": {
    "tgn:hierarchy":[
        "tgn:2317711",
        "tgn:1000001",
        "tgn:7012149",
        "tgn:2001280",
        "tgn:7007524",
        "tgn:7029392"
    ],
    "tgn:id":2317711,
    "tgn:name":"England Coulee",
    "tgn:placetype":[
        "aat:300008761"
    ]
},
  "bbox": [],
  "geometry": {"coordinates":[-110.45,48.5833],"type":"Point"}
}