{
  "id": 7281413,
  "type": "Feature",
  "properties": {
    "tgn:hierarchy":[
        "tgn:7281413",
        "tgn:1001702",
        "tgn:1000049",
        "tgn:1000002",
        "tgn:7029392"
    ],
    "tgn:id":7281413,
    "tgn:name":"Sur, Roca",
    "tgn:placetype":[
        "aat:300011692"
    ]
},
  "bbox": [],
  "geometry": {"coordinates":[-75.447222,-50.698056],"type":"Point"}
}