{
  "id": 7011797,
  "type": "Feature",
  "properties": {
    "tgn:hierarchy":[
        "tgn:7011797",
        "tgn:7018908",
        "tgn:7002445",
        "tgn:1000003",
        "tgn:7008136",
        "tgn:7008591",
        "tgn:7029392"
    ],
    "tgn:id":7011797,
    "tgn:name":"Crayford",
    "tgn:placetype":[
        "aat:300000745",
        "aat:300387302"
    ]
},
  "bbox": [],
  "geometry": {"coordinates":[0.1833,51.45],"type":"Point"}
}