{
  "id": 7315018,
  "type": "Feature",
  "properties": {
    "tgn:hierarchy":[
        "tgn:7315018",
        "tgn:1001630",
        "tgn:1000049",
        "tgn:1000002",
        "tgn:7029392"
    ],
    "tgn:id":7315018,
    "tgn:name":"Las Tapias, Cerro",
    "tgn:placetype":[
        "aat:300008795"
    ]
},
  "bbox": [],
  "geometry": {"coordinates":[-70.633333,-26.066667],"type":"Point"}
}