<<<<<<< HEAD
{
  "id": 2251275,
  "type": "Feature",
  "properties": {
    "tgn:hierarchy":[
        "tgn:2251275",
        "tgn:1000001",
        "tgn:7006451",
        "tgn:7012149",
        "tgn:2000103",
        "tgn:7029392"
    ],
    "tgn:id":2251275,
    "tgn:name":"Combination Mine",
    "tgn:placetype":[
        "aat:300000390"
    ]
},
  "bbox": [],
  "geometry": {"coordinates":[-112.3667,34.4333],"type":"Point"}
}
=======
{"geometry":{"type":"Point","coordinates":[-112.366700,34.433300]},"type":"Feature","properties":{"hierarchy":["tgn:2251275","tgn:1000001","tgn:7006451","tgn:7012149","tgn:2000103","tgn:7029392"],"placetype":["aat:300000390"],"id":2251275,"name:xx":"Combination Mine"}}
>>>>>>> 03f74aca74312dbeaf24d7e61306dd6a786dc3d0
