{
  "id": 2430135,
  "type": "Feature",
  "properties": {
    "tgn:hierarchy":[
        "tgn:2430135",
        "tgn:7002659",
        "tgn:1000001",
        "tgn:7012149",
        "tgn:2000060",
        "tgn:7029392"
    ],
    "tgn:id":2430135,
    "tgn:name":"Kahatchee Mountain",
    "tgn:placetype":[
        "aat:300008798"
    ]
},
  "bbox": [],
  "geometry": {"coordinates":[-86.35,33.2167],"type":"Point"}
}