<<<<<<< HEAD
{
  "id": 2155210,
  "type": "Feature",
  "properties": {
    "tgn:hierarchy":[
        "tgn:2155210",
        "tgn:1000001",
        "tgn:7006451",
        "tgn:2000095",
        "tgn:7012149",
        "tgn:7029392"
    ],
    "tgn:id":2155210,
    "tgn:name":"Bear Mountain",
    "tgn:placetype":[
        "aat:300008798"
    ]
},
  "bbox": [],
  "geometry": {"coordinates":[-109.1333,33.5333],"type":"Point"}
}
=======
{"geometry":{"type":"Point","coordinates":[-109.133300,33.533300]},"type":"Feature","properties":{"hierarchy":["tgn:2155210","tgn:1000001","tgn:7006451","tgn:2000095","tgn:7012149","tgn:7029392"],"placetype":["aat:300008798"],"id":2155210,"name:xx":"Bear Mountain"}}
>>>>>>> 03f74aca74312dbeaf24d7e61306dd6a786dc3d0
