{
  "id": 2784940,
  "type": "Feature",
  "properties": {
    "tgn:hierarchy":[
        "tgn:2784940",
        "tgn:1000001",
        "tgn:7012149",
        "tgn:7007250",
        "tgn:7029392"
    ],
    "tgn:id":2784940,
    "tgn:name":"Yellow Dog Creek",
    "tgn:placetype":[
        "aat:300008706"
    ]
},
  "bbox": [],
  "geometry": {"coordinates":[-112.4167,42.5333],"type":"Point"}
}