{
  "id": 7191264,
  "type": "Feature",
  "properties": {
    "tgn:hierarchy":[
        "tgn:7191264",
        "tgn:1000003",
        "tgn:7003676",
        "tgn:7000084",
        "tgn:7029392"
    ],
    "tgn:id":7191264,
    "tgn:name":"Fresenh\u00f6rne",
    "tgn:placetype":[
        "aat:300000206"
    ]
},
  "bbox": [],
  "geometry": {"coordinates":[8.816667,53.766667],"type":"Point"}
}