{
  "id": 2395791,
  "type": "Feature",
  "properties": {
    "tgn:hierarchy":[
        "tgn:2395791",
        "tgn:1000001",
        "tgn:7012149",
        "tgn:2002164",
        "tgn:7007919",
        "tgn:7029392"
    ],
    "tgn:id":2395791,
    "tgn:name":"Hollow Rock Hollow",
    "tgn:placetype":[
        "aat:300008761"
    ]
},
  "bbox": [],
  "geometry": {"coordinates":[-81.2167,36.65],"type":"Point"}
}