{
  "id": 2591820,
  "type": "Feature",
  "properties": {
    "tgn:hierarchy":[
        "tgn:2591820",
        "tgn:1000001",
        "tgn:7012149",
        "tgn:2001442",
        "tgn:7007566",
        "tgn:7029392"
    ],
    "tgn:id":2591820,
    "tgn:name":"Pond Lake",
    "tgn:placetype":[
        "aat:300008680"
    ]
},
  "bbox": [],
  "geometry": {"coordinates":[-104.9667,33.1667],"type":"Point"}
}