{
  "id": 7419441,
  "type": "Feature",
  "properties": {
    "tgn:hierarchy":[
        "tgn:7419441",
        "tgn:1001836",
        "tgn:1000001",
        "tgn:7005560",
        "tgn:7029392"
    ],
    "tgn:id":7419441,
    "tgn:name":"Santo Domingo, R\u00edo",
    "tgn:placetype":[
        "aat:300008699"
    ]
},
  "bbox": [],
  "geometry": {"coordinates":[-109.713889,23.718611],"type":"Point"}
}