{
  "id": 2347225,
  "type": "Feature",
  "properties": {
    "tgn:hierarchy":[
        "tgn:2347225",
        "tgn:1000001",
        "tgn:7012149",
        "tgn:2001922",
        "tgn:7007825",
        "tgn:7029392"
    ],
    "tgn:id":2347225,
    "tgn:name":"Gentry Hollow",
    "tgn:placetype":[
        "aat:300008761"
    ]
},
  "bbox": [],
  "geometry": {"coordinates":[-82.5333,36.0167],"type":"Point"}
}