{
  "id": 2623767,
  "type": "Feature",
  "properties": {
    "tgn:hierarchy":[
        "tgn:2623767",
        "tgn:1000001",
        "tgn:1002174",
        "tgn:7012149",
        "tgn:7007826",
        "tgn:7029392"
    ],
    "tgn:id":2623767,
    "tgn:name":"Rock Creek",
    "tgn:placetype":[
        "aat:300008706"
    ]
},
  "bbox": [],
  "geometry": {"coordinates":[-97.7333,31.0333],"type":"Point"}
}