{
  "id": 7380080,
  "type": "Feature",
  "properties": {
    "tgn:hierarchy":[
        "tgn:7380080",
        "tgn:7005586",
        "tgn:1000001",
        "tgn:7005560",
        "tgn:7029392"
    ],
    "tgn:id":7380080,
    "tgn:name":"Los Guajes, Cerro",
    "tgn:placetype":[
        "aat:300008777"
    ]
},
  "bbox": [],
  "geometry": {"coordinates":[-103.516667,19.816667],"type":"Point"}
}