<<<<<<< HEAD
{
  "id": 2159247,
  "type": "Feature",
  "properties": {
    "tgn:hierarchy":[
        "tgn:2159247",
        "tgn:1000001",
        "tgn:7012149",
        "tgn:1002632",
        "tgn:7007251",
        "tgn:7029392"
    ],
    "tgn:id":2159247,
    "tgn:name":"Bee Branch",
    "tgn:placetype":[
        "aat:300008699"
    ]
},
  "bbox": [],
  "geometry": {"coordinates":[-88.8,38.7],"type":"Point"}
}
=======
{"geometry":{"type":"Point","coordinates":[-88.800000,38.700000]},"type":"Feature","properties":{"hierarchy":["tgn:2159247","tgn:1000001","tgn:7012149","tgn:1002632","tgn:7007251","tgn:7029392"],"placetype":["aat:300008699"],"id":2159247,"name:xx":"Bee Branch"}}
>>>>>>> 03f74aca74312dbeaf24d7e61306dd6a786dc3d0
