{
  "id": 7579328,
  "type": "Feature",
  "properties": {
    "tgn:hierarchy":[
        "tgn:7579328",
        "tgn:1000004",
        "tgn:7000198",
        "tgn:1003539",
        "tgn:7029392"
    ],
    "tgn:id":7579328,
    "tgn:name:en":"Umlaiteng",
    "tgn:placetype":[
        "aat:300008347"
    ]
},
  "bbox": [],
  "geometry": {"coordinates":[92.066756,25.796412],"type":"Point"}
}