<<<<<<< HEAD
{
  "id": 2159954,
  "type": "Feature",
  "properties": {
    "tgn:hierarchy":[
        "tgn:2159954",
        "tgn:1000001",
        "tgn:2000922",
        "tgn:7012149",
        "tgn:7007515",
        "tgn:7029392"
    ],
    "tgn:id":2159954,
    "tgn:name":"Beech Hill Point",
    "tgn:placetype":[
        "aat:300008850"
    ]
},
  "bbox": [],
  "geometry": {"coordinates":[-68.3833,44.6],"type":"Point"}
}
=======
{"geometry":{"type":"Point","coordinates":[-68.383300,44.600000]},"type":"Feature","properties":{"hierarchy":["tgn:2159954","tgn:1000001","tgn:2000922","tgn:7012149","tgn:7007515","tgn:7029392"],"placetype":["aat:300008850"],"id":2159954,"name:xx":"Beech Hill Point"}}
>>>>>>> 03f74aca74312dbeaf24d7e61306dd6a786dc3d0
