{
  "id": 7472297,
  "type": "Feature",
  "properties": {
    "tgn:hierarchy":[
        "tgn:7472297",
        "tgn:1000004",
        "tgn:7467799",
        "tgn:1000141",
        "tgn:7029392"
    ],
    "tgn:id":7472297,
    "tgn:name":"Zhongjue",
    "tgn:placetype":[
        "aat:300008347"
    ]
},
  "bbox": [],
  "geometry": {"coordinates":[120.488824,23.947661],"type":"Point"}
}