{
  "id": 7335917,
  "type": "Feature",
  "properties": {
    "tgn:hierarchy":[
        "tgn:7335917",
        "tgn:1001439",
        "tgn:1000003",
        "tgn:7002797",
        "tgn:1000095",
        "tgn:7029392"
    ],
    "tgn:id":7335917,
    "tgn:name":"Fatares, Barranco",
    "tgn:placetype":[
        "aat:300266554",
        "aat:300008699"
    ]
},
  "bbox": [],
  "geometry": {"coordinates":[-1.033333,37.583333],"type":"Point"}
}