{
  "id": 2714617,
  "type": "Feature",
  "properties": {
    "tgn:hierarchy":[
        "tgn:2714617",
        "tgn:1002201",
        "tgn:1000001",
        "tgn:7012149",
        "tgn:7007517",
        "tgn:7029392"
    ],
    "tgn:id":2714617,
    "tgn:name":"Ten Mile River Reservoir",
    "tgn:placetype":[
        "aat:300006191"
    ]
},
  "bbox": [],
  "geometry": {"coordinates":[-71.3167,41.8833],"type":"Point"}
}