{
  "id": 2427008,
  "type": "Feature",
  "properties": {
    "tgn:hierarchy":[
        "tgn:2427008",
        "tgn:1000001",
        "tgn:7006451",
        "tgn:7012149",
        "tgn:2000097",
        "tgn:7029392"
    ],
    "tgn:id":2427008,
    "tgn:name":"Jones Tank",
    "tgn:placetype":[
        "aat:300006191"
    ]
},
  "bbox": [],
  "geometry": {"coordinates":[-112.8333,33.5833],"type":"Point"}
}