{
  "id": 7335073,
  "type": "Feature",
  "properties": {
    "tgn:hierarchy":[
        "tgn:7335073",
        "tgn:7002825",
        "tgn:7016622",
        "tgn:1000003",
        "tgn:1000095",
        "tgn:7029392"
    ],
    "tgn:id":7335073,
    "tgn:name":"Goroy, Barranco de",
    "tgn:placetype":[
        "aat:300266554",
        "aat:300008699"
    ]
},
  "bbox": [],
  "geometry": {"coordinates":[-13.85,28.433333],"type":"Point"}
}