{
  "id": 2664153,
  "type": "Feature",
  "properties": {
    "tgn:hierarchy":[
        "tgn:2664153",
        "tgn:7006450",
        "tgn:1000001",
        "tgn:7019698",
        "tgn:7012149",
        "tgn:7029392"
    ],
    "tgn:id":2664153,
    "tgn:name":"Silver Salmon Creek",
    "tgn:placetype":[
        "aat:300008706"
    ]
},
  "bbox": [],
  "geometry": {"coordinates":[-153.2667,59.8667],"type":"Point"}
}