{
  "id": 7577728,
  "type": "Feature",
  "properties": {
    "tgn:hierarchy":[
        "tgn:7577728",
        "tgn:1000004",
        "tgn:7000198",
        "tgn:1001894",
        "tgn:7029392"
    ],
    "tgn:id":7577728,
    "tgn:name:en":"Khokara Kal\u0101n",
    "tgn:placetype":[
        "aat:300008347"
    ]
},
  "bbox": [],
  "geometry": {"coordinates":[76.951863,23.427669],"type":"Point"}
}