{
  "id": 2381316,
  "type": "Feature",
  "properties": {
    "tgn:hierarchy":[
        "tgn:2381316",
        "tgn:1000001",
        "tgn:7013649",
        "tgn:7012149",
        "tgn:7007251",
        "tgn:7029392"
    ],
    "tgn:id":2381316,
    "tgn:name":"Hawthorn Lake",
    "tgn:placetype":[
        "aat:300008680"
    ]
},
  "bbox": [],
  "geometry": {"coordinates":[-88.1333,42.1333],"type":"Point"}
}