{
  "id": 7220979,
  "type": "Feature",
  "properties": {
    "tgn:hierarchy":[
        "tgn:7220979",
        "tgn:7011164",
        "tgn:7002674",
        "tgn:1000003",
        "tgn:1000074",
        "tgn:7029392"
    ],
    "tgn:id":7220979,
    "tgn:name":"P\u00e1ndroson",
    "tgn:placetype":[
        "aat:300008347"
    ]
},
  "bbox": [],
  "geometry": {"coordinates":[26.829444,37.730833],"type":"Point"}
}