{
  "id": 2192351,
  "type": "Feature",
  "properties": {
    "tgn:hierarchy":[
        "tgn:2192351",
        "tgn:1000001",
        "tgn:7012149",
        "tgn:2000825",
        "tgn:7007255",
        "tgn:7029392"
    ],
    "tgn:id":2192351,
    "tgn:name":"Brandenburg Station",
    "tgn:placetype":[
        "aat:300008347"
    ]
},
  "bbox": [],
  "geometry": {"coordinates":[-86.1333,37.9667],"type":"Point"}
}