{
  "id": 1069888,
  "type": "Feature",
  "properties": {
    "tgn:hierarchy":[
        "tgn:1069888",
        "tgn:1000004",
        "tgn:1001390",
        "tgn:1000111",
        "tgn:7029392"
    ],
    "tgn:id":1069888,
    "tgn:name":"Linjiatai",
    "tgn:placetype":[
        "aat:300008347"
    ]
},
  "bbox": [],
  "geometry": {"coordinates":[123.9333,40.65],"type":"Point"}
}