<<<<<<< HEAD
{
  "id": 2402589,
  "type": "Feature",
  "properties": {
    "tgn:hierarchy":[
        "tgn:2402589",
        "tgn:1000001",
        "tgn:7012149",
        "tgn:7029392"
    ],
    "tgn:id":2402589,
    "tgn:name":"Hosteen Tso Canyon",
    "tgn:placetype":[
        "aat:300008761"
    ]
},
  "bbox": [],
  "geometry": {"coordinates":[-109.7833,36.9333],"type":"Point"}
}
=======
{"geometry":{"type":"Point","coordinates":[-109.783300,36.933300]},"type":"Feature","properties":{"hierarchy":["tgn:2402589","tgn:1000001","tgn:7012149","tgn:7029392"],"placetype":["aat:300008761"],"id":2402589,"name:xx":"Hosteen Tso Canyon"}}
>>>>>>> 03f74aca74312dbeaf24d7e61306dd6a786dc3d0
