{
  "id": 1028489,
  "type": "Feature",
  "properties": {
    "tgn:hierarchy":[
        "tgn:1028489",
        "tgn:7002445",
        "tgn:1000003",
        "tgn:7008134",
        "tgn:7008591",
        "tgn:7029392"
    ],
    "tgn:id":1028489,
    "tgn:name:en":"Billingshurst",
    "tgn:placetype":[
        "aat:300008347"
    ]
},
  "bbox": [],
  "geometry": {"coordinates":[-0.45,51.016667],"type":"Point"}
}