{
  "id": 2490749,
  "type": "Feature",
  "properties": {
    "tgn:hierarchy":[
        "tgn:2490749",
        "tgn:1000001",
        "tgn:7012149",
        "tgn:2002157",
        "tgn:7007919",
        "tgn:7029392"
    ],
    "tgn:id":2490749,
    "tgn:name":"Manns Branch",
    "tgn:placetype":[
        "aat:300008699"
    ]
},
  "bbox": [],
  "geometry": {"coordinates":[-82.2333,37.05],"type":"Point"}
}