{
  "id": 7360991,
  "type": "Feature",
  "properties": {
    "tgn:hierarchy":[
        "tgn:7360991",
        "tgn:7005584",
        "tgn:1000001",
        "tgn:7005560",
        "tgn:7029392"
    ],
    "tgn:id":7360991,
    "tgn:name":"El Bosque",
    "tgn:placetype":[
        "aat:300008347"
    ]
},
  "bbox": [],
  "geometry": {"coordinates":[-101.466667,20.95],"type":"Point"}
}