<<<<<<< HEAD
{
  "id": 2256845,
  "type": "Feature",
  "properties": {
    "tgn:hierarchy":[
        "tgn:2256845",
        "tgn:2002101",
        "tgn:1000001",
        "tgn:7012149",
        "tgn:7007827",
        "tgn:7029392"
    ],
    "tgn:id":2256845,
    "tgn:name":"Cork Ridge",
    "tgn:placetype":[
        "aat:300266640"
    ]
},
  "bbox": [],
  "geometry": {"coordinates":[-112.5,38.3667],"type":"Point"}
}
=======
{"geometry":{"type":"Point","coordinates":[-112.500000,38.366700]},"type":"Feature","properties":{"hierarchy":["tgn:2256845","tgn:2002101","tgn:1000001","tgn:7012149","tgn:7007827","tgn:7029392"],"placetype":["aat:300266640"],"id":2256845,"name:xx":"Cork Ridge"}}
>>>>>>> 03f74aca74312dbeaf24d7e61306dd6a786dc3d0
