{
  "id": 2169620,
  "type": "Feature",
  "properties": {
    "tgn:hierarchy":[
        "tgn:2169620",
        "tgn:1000001",
        "tgn:7012149",
        "tgn:1002440",
        "tgn:7007568",
        "tgn:7029392"
    ],
    "tgn:id":2169620,
    "tgn:name":"Big Metcalf Lake",
    "tgn:placetype":[
        "aat:300008680"
    ]
},
  "bbox": [],
  "geometry": {"coordinates":[-74.7167,43.2833],"type":"Point"}
}