{
  "id": 7149979,
  "type": "Feature",
  "properties": {
    "tgn:hierarchy":[
        "tgn:7149979",
        "tgn:1000003",
        "tgn:7000094",
        "tgn:7000084",
        "tgn:7029392"
    ],
    "tgn:id":7149979,
    "tgn:name":"Kuhlrade",
    "tgn:placetype":[
        "aat:300008347"
    ]
},
  "bbox": [],
  "geometry": {"coordinates":[10.916667,53.75],"type":"Point"}
}