{
  "id": 1029787,
  "type": "Feature",
  "properties": {
    "tgn:hierarchy":[
        "tgn:1029787",
        "tgn:7002445",
        "tgn:1000003",
        "tgn:7012032",
        "tgn:7008591",
        "tgn:7029392"
    ],
    "tgn:id":1029787,
    "tgn:name:en":"Langport",
    "tgn:placetype":[
        "aat:300008347"
    ]
},
  "bbox": [],
  "geometry": {"coordinates":[-2.828056,51.037778],"type":"Point"}
}