{
  "id": 2137672,
  "type": "Feature",
  "properties": {
    "tgn:hierarchy":[
        "tgn:2137672",
        "tgn:1000001",
        "tgn:7012149",
        "tgn:2002372",
        "tgn:7007923",
        "tgn:7029392"
    ],
    "tgn:id":2137672,
    "tgn:name":"Arnold Reservoir",
    "tgn:placetype":[
        "aat:300006191"
    ]
},
  "bbox": [],
  "geometry": {"coordinates":[-104.1333,42.0667],"type":"Point"}
}