{
  "id": 7537471,
  "type": "Feature",
  "properties": {
    "tgn:hierarchy":[
        "tgn:7537471",
        "tgn:7001242",
        "tgn:1001059",
        "tgn:7016833",
        "tgn:7029392"
    ],
    "tgn:id":7537471,
    "tgn:name:en":"M\u012bt a\u015f \u015e\u0101rim",
    "tgn:placetype":[
        "aat:300008347"
    ]
},
  "bbox": [],
  "geometry": {"coordinates":[31.413713,31.026895],"type":"Point"}
}