{
  "id": 7416141,
  "type": "Feature",
  "properties": {
    "tgn:hierarchy":[
        "tgn:7416141",
        "tgn:1000001",
        "tgn:7005591",
        "tgn:7005560",
        "tgn:7029392"
    ],
    "tgn:id":7416141,
    "tgn:name:es":"El Ba\u00fal, Cord\u00f3n",
    "tgn:placetype":[
        "aat:300008795"
    ]
},
  "bbox": [],
  "geometry": {"coordinates":[-94.156111,16.656111],"type":"Point"}
}