{
  "id": 7449182,
  "type": "Feature",
  "properties": {
    "tgn:hierarchy":[
        "tgn:7449182",
        "tgn:7002448",
        "tgn:7019200",
        "tgn:1000003",
        "tgn:7008591",
        "tgn:7029392"
    ],
    "tgn:id":7449182,
    "tgn:name:en":"Seagoe",
    "tgn:placetype":[
        "aat:300008347"
    ]
},
  "bbox": [],
  "geometry": {"coordinates":[-6.416667,54.433333],"type":"Point"}
}