{
  "id": 2747400,
  "type": "Feature",
  "properties": {
    "tgn:hierarchy":[
        "tgn:2747400",
        "tgn:1007657",
        "tgn:1002534",
        "tgn:1000001",
        "tgn:7012149",
        "tgn:7007249",
        "tgn:7029392"
    ],
    "tgn:id":2747400,
    "tgn:name":"Waiahi Iliiliula Ditch",
    "tgn:placetype":[
        "aat:300006075"
    ]
},
  "bbox": [],
  "geometry": {"coordinates":[-159.45,22.0333],"type":"Point"}
}