{
  "id": 7574337,
  "type": "Feature",
  "properties": {
    "tgn:hierarchy":[
        "tgn:7574337",
        "tgn:1000004",
        "tgn:7031781",
        "tgn:7000198",
        "tgn:7029392"
    ],
    "tgn:id":7574337,
    "tgn:name:en":"Jaitgiri",
    "tgn:placetype":[
        "aat:300008347"
    ]
},
  "bbox": [],
  "geometry": {"coordinates":[82.166667,19.333333],"type":"Point"}
}