{
  "id": 7402504,
  "type": "Feature",
  "properties": {
    "tgn:hierarchy":[
        "tgn:7402504",
        "tgn:1000001",
        "tgn:1001937",
        "tgn:7005560",
        "tgn:7029392"
    ],
    "tgn:id":7402504,
    "tgn:name":"Nuevo Plan de la Noria",
    "tgn:placetype":[
        "aat:300008347"
    ]
},
  "bbox": [],
  "geometry": {"coordinates":[-88.65,19.308333],"type":"Point"}
}