{
  "id": 2656628,
  "type": "Feature",
  "properties": {
    "tgn:hierarchy":[
        "tgn:2656628",
        "tgn:7006450",
        "tgn:1000001",
        "tgn:7019674",
        "tgn:7012149",
        "tgn:7029392"
    ],
    "tgn:id":2656628,
    "tgn:name":"Sheep Creek",
    "tgn:placetype":[
        "aat:300008706"
    ]
},
  "bbox": [],
  "geometry": {"coordinates":[-148.0333,64.8667],"type":"Point"}
}