{
  "id": 7167885,
  "type": "Feature",
  "properties": {
    "tgn:hierarchy":[
        "tgn:7167885",
        "tgn:7003669",
        "tgn:1000003",
        "tgn:7000084",
        "tgn:7029392"
    ],
    "tgn:id":7167885,
    "tgn:name":"Harthausen",
    "tgn:placetype":[
        "aat:300008347"
    ]
},
  "bbox": [],
  "geometry": {"coordinates":[12.033333,47.866667],"type":"Point"}
}