{
  "id": 2163521,
  "type": "Feature",
  "properties": {
    "tgn:hierarchy":[
        "tgn:2163521",
        "tgn:1000001",
        "tgn:7012149",
        "tgn:1002402",
        "tgn:7007523",
        "tgn:7029392"
    ],
    "tgn:id":2163521,
    "tgn:name":"Benson Lake",
    "tgn:placetype":[
        "aat:300006191"
    ]
},
  "bbox": [],
  "geometry": {"coordinates":[-91.4667,38.6333],"type":"Point"}
}