{
  "id": 2318083,
  "type": "Feature",
  "properties": {
    "tgn:hierarchy":[
        "tgn:2318083",
        "tgn:1000001",
        "tgn:7012149",
        "tgn:2001131",
        "tgn:7007522",
        "tgn:7029392"
    ],
    "tgn:id":2318083,
    "tgn:name":"Enon",
    "tgn:placetype":[
        "aat:300008347"
    ]
},
  "bbox": [],
  "geometry": {"coordinates":[-89.6667,31.25],"type":"Point"}
}