{
  "id": 2775056,
  "type": "Feature",
  "properties": {
    "tgn:hierarchy":[
        "tgn:2775056",
        "tgn:1000001",
        "tgn:7012149",
        "tgn:7007157",
        "tgn:1002972",
        "tgn:7029392"
    ],
    "tgn:id":2775056,
    "tgn:name":"Wills Canyon",
    "tgn:placetype":[
        "aat:300008761"
    ]
},
  "bbox": [],
  "geometry": {"coordinates":[-119.3167,34.45],"type":"Point"}
}