{
  "id": 2147729,
  "type": "Feature",
  "properties": {
    "tgn:hierarchy":[
        "tgn:2147729",
        "tgn:1000001",
        "tgn:1002359",
        "tgn:7012149",
        "tgn:7007517",
        "tgn:7029392"
    ],
    "tgn:id":2147729,
    "tgn:name":"Bare Meadow Brook",
    "tgn:placetype":[
        "aat:300008699"
    ]
},
  "bbox": [],
  "geometry": {"coordinates":[-71.15,42.7333],"type":"Point"}
}