{
  "id": 2311543,
  "type": "Feature",
  "properties": {
    "tgn:hierarchy":[
        "tgn:2311543",
        "tgn:1000001",
        "tgn:7012149",
        "tgn:2000802",
        "tgn:7007255",
        "tgn:7029392"
    ],
    "tgn:id":2311543,
    "tgn:name":"Eds Lick",
    "tgn:placetype":[
        "aat:300008699"
    ]
},
  "bbox": [],
  "geometry": {"coordinates":[-83.8333,37.35],"type":"Point"}
}