{
  "id": 2188085,
  "type": "Feature",
  "properties": {
    "tgn:hierarchy":[
        "tgn:2188085",
        "tgn:1000001",
        "tgn:7012149",
        "tgn:2001451",
        "tgn:7007566",
        "tgn:7029392"
    ],
    "tgn:id":2188085,
    "tgn:name":"Borrego Canyon",
    "tgn:placetype":[
        "aat:300008761"
    ]
},
  "bbox": [],
  "geometry": {"coordinates":[-106.5833,35.65],"type":"Point"}
}