{
  "id": 7262002,
  "type": "Feature",
  "properties": {
    "tgn:hierarchy":[
        "tgn:7262002",
        "tgn:7003619",
        "tgn:1000003",
        "tgn:7016845",
        "tgn:7029392"
    ],
    "tgn:id":7262002,
    "tgn:name:nl":"De Voorst",
    "tgn:placetype":[
        "aat:300006891"
    ]
},
  "bbox": [],
  "geometry": {"coordinates":[6.25,52.15],"type":"Point"}
}