<<<<<<< HEAD
{
  "id": 7029411,
  "type": "Feature",
  "properties": {
    "tgn:hierarchy":[
        "tgn:7029411",
        "tgn:7002445",
        "tgn:1000003",
        "tgn:7019057",
        "tgn:7008591",
        "tgn:7029392"
    ],
    "tgn:id":7029411,
    "tgn:name":"Towthorpe",
    "tgn:placetype":[
        "aat:300008347",
        "aat:300008372"
    ]
},
  "bbox": [],
  "geometry": {"coordinates":[-0.626,54.05],"type":"Point"}
}
=======
{"geometry":{"type":"Point","coordinates":[-0.626000,54.050000]},"type":"Feature","properties":{"hierarchy":["tgn:7029411","tgn:7002445","tgn:1000003","tgn:7019057","tgn:7008591","tgn:7029392"],"placetype":["aat:300008347","aat:300008372"],"id":7029411,"name:xx":"Towthorpe"}}
>>>>>>> 03f74aca74312dbeaf24d7e61306dd6a786dc3d0
