{
  "id": 1114614,
  "type": "Feature",
  "properties": {
    "tgn:hierarchy":[
        "tgn:1114614",
        "tgn:1000001",
        "tgn:7012149",
        "tgn:1002768",
        "tgn:7007240",
        "tgn:7029392"
    ],
    "tgn:id":1114614,
    "tgn:name":"Jupiter Inlet",
    "tgn:placetype":[
        "aat:300185707"
    ]
},
  "bbox": [],
  "geometry": {"coordinates":[-80.0667,26.9333],"type":"Point"}
}