{
  "id": 7327912,
  "type": "Feature",
  "properties": {
    "tgn:hierarchy":[
        "tgn:7327912",
        "tgn:7010420",
        "tgn:1000003",
        "tgn:7002795",
        "tgn:1000095",
        "tgn:7029392"
    ],
    "tgn:id":7327912,
    "tgn:name":"Puebla, Arroyo de la",
    "tgn:placetype":[
        "aat:300008699"
    ]
},
  "bbox": [],
  "geometry": {"coordinates":[-4.316667,40.45],"type":"Point"}
}