{
  "id": 7067135,
  "type": "Feature",
  "properties": {
    "tgn:hierarchy":[
        "tgn:7067135",
        "tgn:7000096",
        "tgn:1000003",
        "tgn:7000084",
        "tgn:7029392"
    ],
    "tgn:id":7067135,
    "tgn:name":"F\u00f6rsterei St\u00f6ritzsee",
    "tgn:placetype":[
        "aat:300004792"
    ]
},
  "bbox": [],
  "geometry": {"coordinates":[13.85,52.383333],"type":"Point"}
}