<<<<<<< HEAD
{
  "id": 7241806,
  "type": "Feature",
  "properties": {
    "tgn:hierarchy":[
        "tgn:7241806",
        "tgn:7007877",
        "tgn:1000003",
        "tgn:1000063",
        "tgn:4012014",
        "tgn:7029392"
    ],
    "tgn:id":7241806,
    "tgn:name":"La D\u00eeme",
    "tgn:placetype":[
        "aat:300008347"
    ]
},
  "bbox": [],
  "geometry": {"coordinates":[3.581456,50.585478],"type":"Point"}
}
=======
{"geometry":{"type":"Point","coordinates":[3.581456,50.585478]},"type":"Feature","properties":{"hierarchy":["tgn:7241806","tgn:7007877","tgn:1000003","tgn:1000063","tgn:4012014","tgn:7029392"],"placetype":["aat:300008347"],"id":7241806,"name:xx":"La D\u00eeme"}}
>>>>>>> 03f74aca74312dbeaf24d7e61306dd6a786dc3d0
