{
  "id": 1023634,
  "type": "Feature",
  "properties": {
    "tgn:hierarchy":[
        "tgn:1023634",
        "tgn:1001657",
        "tgn:1000049",
        "tgn:1000002",
        "tgn:7029392"
    ],
    "tgn:id":1023634,
    "tgn:name":"San Marcos",
    "tgn:placetype":[
        "aat:300008347"
    ]
},
  "bbox": [],
  "geometry": {"coordinates":[-71.05,-30.933333],"type":"Point"}
}