{
  "id": 1076939,
  "type": "Feature",
  "properties": {
    "tgn:hierarchy":[
        "tgn:1076939",
        "tgn:1000004",
        "tgn:7000198",
        "tgn:1001895",
        "tgn:7029392"
    ],
    "tgn:id":1076939,
    "tgn:name:en":"Sheva",
    "tgn:placetype":[
        "aat:300008347"
    ]
},
  "bbox": [],
  "geometry": {"coordinates":[72.9575,18.942778],"type":"Point"}
}