{
  "id": 2599848,
  "type": "Feature",
  "properties": {
    "tgn:hierarchy":[
        "tgn:2599848",
        "tgn:1000001",
        "tgn:7012149",
        "tgn:7007522",
        "tgn:7029392"
    ],
    "tgn:id":2599848,
    "tgn:name":"Providence Creek",
    "tgn:placetype":[
        "aat:300008706"
    ]
},
  "bbox": [],
  "geometry": {"coordinates":[-89.35,31.4833],"type":"Point"}
}