{
  "id": 2420821,
  "type": "Feature",
  "properties": {
    "tgn:hierarchy":[
        "tgn:2420821",
        "tgn:1000001",
        "tgn:2001016",
        "tgn:7012149",
        "tgn:7007521",
        "tgn:7029392"
    ],
    "tgn:id":2420821,
    "tgn:name":"Jennison Lake",
    "tgn:placetype":[
        "aat:300008680"
    ]
},
  "bbox": [],
  "geometry": {"coordinates":[-93.8167,46.2333],"type":"Point"}
}