{
  "id": 7249048,
  "type": "Feature",
  "properties": {
    "tgn:hierarchy":[
        "tgn:7249048",
        "tgn:7018239",
        "tgn:1000003",
        "tgn:1000063",
        "tgn:7018236",
        "tgn:7029392"
    ],
    "tgn:id":7249048,
    "tgn:name":"Den Hoek",
    "tgn:placetype":[
        "aat:300008347"
    ]
},
  "bbox": [],
  "geometry": {"coordinates":[4.166667,50.783333],"type":"Point"}
}