{
  "id": 1056856,
  "type": "Feature",
  "properties": {
    "tgn:hierarchy":[
        "tgn:1056856",
        "tgn:1000004",
        "tgn:7011589",
        "tgn:7018214",
        "tgn:7002435",
        "tgn:7029392"
    ],
    "tgn:id":1056856,
    "tgn:name":"Maslyanino",
    "tgn:placetype":[
        "aat:300008347"
    ]
},
  "bbox": [],
  "geometry": {"coordinates":[84.2167,54.3333],"type":"Point"}
}