{
  "id": 2434727,
  "type": "Feature",
  "properties": {
    "tgn:hierarchy":[
        "tgn:2434727",
        "tgn:1000001",
        "tgn:7012149",
        "tgn:2001883",
        "tgn:7007825",
        "tgn:7029392"
    ],
    "tgn:id":2434727,
    "tgn:name":"Kennedys Shoals",
    "tgn:placetype":[
        "aat:300132348"
    ]
},
  "bbox": [],
  "geometry": {"coordinates":[-83.7833,35.9333],"type":"Point"}
}