{
  "id": 1024392,
  "type": "Feature",
  "properties": {
    "tgn:hierarchy":[
        "tgn:1024392",
        "tgn:1000638",
        "tgn:1000002",
        "tgn:1000056",
        "tgn:7029392"
    ],
    "tgn:id":1024392,
    "tgn:name":"C\u00f3rdova",
    "tgn:placetype":[
        "aat:300008347"
    ]
},
  "bbox": [],
  "geometry": {"coordinates":[-75.1667,-14.0167],"type":"Point"}
}