{
  "id": 2657203,
  "type": "Feature",
  "properties": {
    "tgn:hierarchy":[
        "tgn:2657203",
        "tgn:1000001",
        "tgn:7012149",
        "tgn:2002301",
        "tgn:7013961",
        "tgn:7029392"
    ],
    "tgn:id":2657203,
    "tgn:name":"Sheep Run",
    "tgn:placetype":[
        "aat:300008699"
    ]
},
  "bbox": [],
  "geometry": {"coordinates":[-80.5833,39.55],"type":"Point"}
}