{
  "id": 2409960,
  "type": "Feature",
  "properties": {
    "tgn:hierarchy":[
        "tgn:2409960",
        "tgn:1000001",
        "tgn:7012149",
        "tgn:2002055",
        "tgn:7007826",
        "tgn:7029392"
    ],
    "tgn:id":2409960,
    "tgn:name":"Imperial Ditch",
    "tgn:placetype":[
        "aat:300006075"
    ]
},
  "bbox": [],
  "geometry": {"coordinates":[-102.95,31.3167],"type":"Point"}
}