{
  "id": 7322037,
  "type": "Feature",
  "properties": {
    "tgn:hierarchy":[
        "tgn:7322037",
        "tgn:1001705",
        "tgn:1000049",
        "tgn:1000002",
        "tgn:7029392"
    ],
    "tgn:id":7322037,
    "tgn:name":"Batuco, Estero",
    "tgn:placetype":[
        "aat:300008699"
    ]
},
  "bbox": [],
  "geometry": {"coordinates":[-72.066667,-35.283333],"type":"Point"}
}