<<<<<<< HEAD
{
  "id": 7481234,
  "type": "Feature",
  "properties": {
    "tgn:hierarchy":[
        "tgn:7481234",
        "tgn:1000004",
        "tgn:7004300",
        "tgn:1000141",
        "tgn:7029392"
    ],
    "tgn:id":7481234,
    "tgn:name":"Kan'an Gang",
    "tgn:placetype":[
        "aat:300008678"
    ]
},
  "bbox": [],
  "geometry": {"coordinates":[119.415556,23.208333],"type":"Point"}
}
=======
{"geometry":{"type":"Point","coordinates":[119.415556,23.208333]},"type":"Feature","properties":{"hierarchy":["tgn:7481234","tgn:1000004","tgn:7004300","tgn:1000141","tgn:7029392"],"placetype":["aat:300008678"],"id":7481234,"name:xx":"Kan'an Gang"}}
>>>>>>> 03f74aca74312dbeaf24d7e61306dd6a786dc3d0
