{
  "id": 2655360,
  "type": "Feature",
  "properties": {
    "tgn:hierarchy":[
        "tgn:2655360",
        "tgn:1000001",
        "tgn:7012149",
        "tgn:1002676",
        "tgn:7007240",
        "tgn:7029392"
    ],
    "tgn:id":2655360,
    "tgn:name":"Shark River Island",
    "tgn:placetype":[
        "aat:300008791"
    ]
},
  "bbox": [],
  "geometry": {"coordinates":[-81.1333,25.3333],"type":"Point"}
}