{
  "id": 7230127,
  "type": "Feature",
  "properties": {
    "tgn:hierarchy":[
        "tgn:7230127",
        "tgn:7002752",
        "tgn:7001399",
        "tgn:1000003",
        "tgn:1000074",
        "tgn:7029392"
    ],
    "tgn:id":7230127,
    "tgn:name":"Chrysavg\u00ed",
    "tgn:placetype":[
        "aat:300008347"
    ]
},
  "bbox": [],
  "geometry": {"coordinates":[21.854444,39.585833],"type":"Point"}
}