<<<<<<< HEAD
{
  "id": 2250008,
  "type": "Feature",
  "properties": {
    "tgn:hierarchy":[
        "tgn:2250008",
        "tgn:1000001",
        "tgn:7012149",
        "tgn:2001552",
        "tgn:7007709",
        "tgn:7029392"
    ],
    "tgn:id":2250008,
    "tgn:name":"Collingwood Estates",
    "tgn:placetype":[
        "aat:300008347"
    ]
},
  "bbox": [],
  "geometry": {"coordinates":[-77.9833,35.5],"type":"Point"}
}
=======
{"geometry":{"type":"Point","coordinates":[-77.983300,35.500000]},"type":"Feature","properties":{"hierarchy":["tgn:2250008","tgn:1000001","tgn:7012149","tgn:2001552","tgn:7007709","tgn:7029392"],"placetype":["aat:300008347"],"id":2250008,"name:xx":"Collingwood Estates"}}
>>>>>>> 03f74aca74312dbeaf24d7e61306dd6a786dc3d0
