<<<<<<< HEAD
{
  "id": 7369967,
  "type": "Feature",
  "properties": {
    "tgn:hierarchy":[
        "tgn:7369967",
        "tgn:7005587",
        "tgn:1000001",
        "tgn:7005560",
        "tgn:7029392"
    ],
    "tgn:id":7369967,
    "tgn:name:es":"Huazalingo",
    "tgn:placetype":[
        "aat:300008347"
    ]
},
  "bbox": [],
  "geometry": {"coordinates":[-98.501389,20.983333],"type":"Point"}
}
=======
{"geometry":{"type":"Point","coordinates":[-98.501389,20.983333]},"type":"Feature","properties":{"hierarchy":["tgn:7369967","tgn:7005587","tgn:1000001","tgn:7005560","tgn:7029392"],"placetype":["aat:300008347"],"id":7369967,"name:es":"Huazalingo"}}
>>>>>>> 03f74aca74312dbeaf24d7e61306dd6a786dc3d0
