{
  "id": 7501314,
  "type": "Feature",
  "properties": {
    "tgn:hierarchy":[
        "tgn:7501314",
        "tgn:1000004",
        "tgn:7490934",
        "tgn:1000141",
        "tgn:7029392"
    ],
    "tgn:id":7501314,
    "tgn:name":"Datan Guoxiao",
    "tgn:placetype":[
        "aat:300006495"
    ]
},
  "bbox": [],
  "geometry": {"coordinates":[120.272222,22.913611],"type":"Point"}
}