{
  "id": 2477952,
  "type": "Feature",
  "properties": {
    "tgn:hierarchy":[
        "tgn:2477952",
        "tgn:1000001",
        "tgn:7012149",
        "tgn:2001916",
        "tgn:7007825",
        "tgn:7029392"
    ],
    "tgn:id":2477952,
    "tgn:name":"Macey",
    "tgn:placetype":[
        "aat:300008347"
    ]
},
  "bbox": [],
  "geometry": {"coordinates":[-85.9833,36.3667],"type":"Point"}
}