{
  "id": 7413291,
  "type": "Feature",
  "properties": {
    "tgn:hierarchy":[
        "tgn:7413291",
        "tgn:1000001",
        "tgn:7005598",
        "tgn:7005560",
        "tgn:7029392"
    ],
    "tgn:id":7413291,
    "tgn:name":"Venustiano Carranza",
    "tgn:placetype":[
        "aat:300008347"
    ]
},
  "bbox": [],
  "geometry": {"coordinates":[-98.029167,19.395833],"type":"Point"}
}