{
  "id": 7575158,
  "type": "Feature",
  "properties": {
    "tgn:hierarchy":[
        "tgn:7575158",
        "tgn:1000004",
        "tgn:1001842",
        "tgn:7000198",
        "tgn:7029392"
    ],
    "tgn:id":7575158,
    "tgn:name:en":"Koili",
    "tgn:placetype":[
        "aat:300008347"
    ]
},
  "bbox": [],
  "geometry": {"coordinates":[85.641914,26.438783],"type":"Point"}
}