{
  "id": 2409575,
  "type": "Feature",
  "properties": {
    "tgn:hierarchy":[
        "tgn:2409575",
        "tgn:7006450",
        "tgn:1000001",
        "tgn:7012149",
        "tgn:2124005",
        "tgn:7029392"
    ],
    "tgn:id":2409575,
    "tgn:name":"Igklo River",
    "tgn:placetype":[
        "aat:300008707"
    ]
},
  "bbox": [],
  "geometry": {"coordinates":[-159.5167,70.7667],"type":"Point"}
}