<<<<<<< HEAD
{
  "id": 2255700,
  "type": "Feature",
  "properties": {
    "tgn:hierarchy":[
        "tgn:2255700",
        "tgn:1000001",
        "tgn:7012149",
        "tgn:2002251",
        "tgn:7007920",
        "tgn:7029392"
    ],
    "tgn:id":2255700,
    "tgn:name":"Coppei Springs",
    "tgn:placetype":[
        "aat:300008697"
    ]
},
  "bbox": [],
  "geometry": {"coordinates":[-118.0333,46.15],"type":"Point"}
}
=======
{"geometry":{"type":"Point","coordinates":[-118.033300,46.150000]},"type":"Feature","properties":{"hierarchy":["tgn:2255700","tgn:1000001","tgn:7012149","tgn:2002251","tgn:7007920","tgn:7029392"],"placetype":["aat:300008697"],"id":2255700,"name:xx":"Coppei Springs"}}
>>>>>>> 03f74aca74312dbeaf24d7e61306dd6a786dc3d0
