{
  "id": 4002584,
  "type": "Feature",
  "properties": {
    "tgn:hierarchy":[
        "tgn:4002584",
        "tgn:1000003",
        "tgn:7002893",
        "tgn:1000070",
        "tgn:7029392"
    ],
    "tgn:id":4002584,
    "tgn:name":"Chenu",
    "tgn:placetype":[
        "aat:300008347"
    ]
},
  "bbox": [],
  "geometry": {"coordinates":[0.3333,47.6167],"type":"Point"}
}