{
  "id": 2133038,
  "type": "Feature",
  "properties": {
    "tgn:hierarchy":[
        "tgn:2133038",
        "tgn:1000001",
        "tgn:7012149",
        "tgn:7020792",
        "tgn:7007524",
        "tgn:7029392"
    ],
    "tgn:id":2133038,
    "tgn:name":"Anderson Ditch",
    "tgn:placetype":[
        "aat:300006075"
    ]
},
  "bbox": [],
  "geometry": {"coordinates":[-113.2333,45.8833],"type":"Point"}
}