{
  "id": 2586182,
  "type": "Feature",
  "properties": {
    "tgn:hierarchy":[
        "tgn:2586182",
        "tgn:1000001",
        "tgn:7012149",
        "tgn:2000887",
        "tgn:7007256",
        "tgn:7029392"
    ],
    "tgn:id":2586182,
    "tgn:name":"Pistol Brake",
    "tgn:placetype":[
        "aat:300008905"
    ]
},
  "bbox": [],
  "geometry": {"coordinates":[-92.05,32.9167],"type":"Point"}
}