<<<<<<< HEAD
{
  "id": 7487339,
  "type": "Feature",
  "properties": {
    "tgn:hierarchy":[
        "tgn:7487339",
        "tgn:7001004",
        "tgn:1000004",
        "tgn:1000141",
        "tgn:7029392"
    ],
    "tgn:id":7487339,
    "tgn:name":"Neikengnei",
    "tgn:placetype":[
        "aat:300008347"
    ]
},
  "bbox": [],
  "geometry": {"coordinates":[120.4303,22.727],"type":"Point"}
}
=======
{"geometry":{"type":"Point","coordinates":[120.430300,22.727000]},"type":"Feature","properties":{"hierarchy":["tgn:7487339","tgn:7001004","tgn:1000004","tgn:1000141","tgn:7029392"],"placetype":["aat:300008347"],"id":7487339,"name:xx":"Neikengnei"}}
>>>>>>> 03f74aca74312dbeaf24d7e61306dd6a786dc3d0
