{
  "id": 7343103,
  "type": "Feature",
  "properties": {
    "tgn:hierarchy":[
        "tgn:7343103",
        "tgn:7002804",
        "tgn:1000003",
        "tgn:7002793",
        "tgn:1000095",
        "tgn:7029392"
    ],
    "tgn:id":7343103,
    "tgn:name":"Ca\u00f1adas de Don Ciro",
    "tgn:placetype":[
        "aat:300008347"
    ]
},
  "bbox": [],
  "geometry": {"coordinates":[-0.966667,38.466667],"type":"Point"}
}