<<<<<<< HEAD
{
  "id": 2402169,
  "type": "Feature",
  "properties": {
    "tgn:hierarchy":[
        "tgn:2402169",
        "tgn:1000001",
        "tgn:7012149",
        "tgn:7007157",
        "tgn:7014475",
        "tgn:7029392"
    ],
    "tgn:id":2402169,
    "tgn:name":"Horsethief Canyon",
    "tgn:placetype":[
        "aat:300008761"
    ]
},
  "bbox": [],
  "geometry": {"coordinates":[-121.5,37.4167],"type":"Point"}
}
=======
{"geometry":{"type":"Point","coordinates":[-121.500000,37.416700]},"type":"Feature","properties":{"hierarchy":["tgn:2402169","tgn:1000001","tgn:7012149","tgn:7007157","tgn:7014475","tgn:7029392"],"placetype":["aat:300008761"],"id":2402169,"name:xx":"Horsethief Canyon"}}
>>>>>>> 03f74aca74312dbeaf24d7e61306dd6a786dc3d0
