{
  "id": 7502440,
  "type": "Feature",
  "properties": {
    "tgn:hierarchy":[
        "tgn:7502440",
        "tgn:7001010",
        "tgn:1000004",
        "tgn:1000141",
        "tgn:7029392"
    ],
    "tgn:id":7502440,
    "tgn:name":"Xinji Suidao",
    "tgn:placetype":[
        "aat:300007899"
    ]
},
  "bbox": [],
  "geometry": {"coordinates":[121.545556,23.675],"type":"Point"}
}