{
  "id": 7001287,
  "type": "Feature",
  "properties": {
    "tgn:hierarchy":[
        "tgn:7001287",
        "tgn:7001242",
        "tgn:7016833",
        "tgn:1001113",
        "tgn:7029392"
    ],
    "tgn:id":7001287,
    "tgn:name":"Bubastis",
    "tgn:placetype":[
        "aat:300008347",
        "aat:300387007",
        "aat:300000810",
        "aat:300167671",
        "aat:300387219"
    ]
},
  "bbox": [],
  "geometry": {"coordinates":[31.516,30.566],"type":"Point"}
}