{
  "id": 7402009,
  "type": "Feature",
  "properties": {
    "tgn:hierarchy":[
        "tgn:7402009",
        "tgn:1000001",
        "tgn:7005600",
        "tgn:7005560",
        "tgn:7029392"
    ],
    "tgn:id":7402009,
    "tgn:name":"Becanch\u00e9n",
    "tgn:placetype":[
        "aat:300008347"
    ]
},
  "bbox": [],
  "geometry": {"coordinates":[-89.225,19.875],"type":"Point"}
}