{
  "id": 7064309,
  "type": "Feature",
  "properties": {
    "tgn:hierarchy":[
        "tgn:7064309",
        "tgn:1000003",
        "tgn:7003678",
        "tgn:7000084",
        "tgn:7029392"
    ],
    "tgn:id":7064309,
    "tgn:name":"Unterdassen",
    "tgn:placetype":[
        "aat:300000206"
    ]
},
  "bbox": [],
  "geometry": {"coordinates":[9.766667,50.516667],"type":"Point"}
}