{
  "id": 1096353,
  "type": "Feature",
  "properties": {
    "tgn:hierarchy":[
        "tgn:1096353",
        "tgn:7000490",
        "tgn:1000006",
        "tgn:7001831",
        "tgn:7029392"
    ],
    "tgn:id":1096353,
    "tgn:name":"Bowmans",
    "tgn:placetype":[
        "aat:300008347"
    ]
},
  "bbox": [],
  "geometry": {"coordinates":[138.2667,-34.15],"type":"Point"}
}