{
  "id": 7528876,
  "type": "Feature",
  "properties": {
    "tgn:hierarchy":[
        "tgn:7528876",
        "tgn:7001242",
        "tgn:7016833",
        "tgn:7001336",
        "tgn:7029392"
    ],
    "tgn:id":7528876,
    "tgn:name:en":"Umm Kitath, Jabal",
    "tgn:placetype":[
        "aat:300008795"
    ]
},
  "bbox": [],
  "geometry": {"coordinates":[34.185677,28.473741],"type":"Point"}
}