<<<<<<< HEAD
{
  "id": 2764597,
  "type": "Feature",
  "properties": {
    "tgn:hierarchy":[
        "tgn:2764597",
        "tgn:1000001",
        "tgn:7012149",
        "tgn:2000363",
        "tgn:7007248",
        "tgn:7029392"
    ],
    "tgn:id":2764597,
    "tgn:name":"Whippoorwill Lake",
    "tgn:placetype":[
        "aat:300008680"
    ]
},
  "bbox": [],
  "geometry": {"coordinates":[-84.8333,32.8167],"type":"Point"}
}
=======
{"geometry":{"type":"Point","coordinates":[-84.833300,32.816700]},"type":"Feature","properties":{"hierarchy":["tgn:2764597","tgn:1000001","tgn:7012149","tgn:2000363","tgn:7007248","tgn:7029392"],"placetype":["aat:300008680"],"id":2764597,"name:xx":"Whippoorwill Lake"}}
>>>>>>> 03f74aca74312dbeaf24d7e61306dd6a786dc3d0
