{
  "id": 7130913,
  "type": "Feature",
  "properties": {
    "tgn:hierarchy":[
        "tgn:7130913",
        "tgn:7003669",
        "tgn:1000003",
        "tgn:7000084",
        "tgn:7029392"
    ],
    "tgn:id":7130913,
    "tgn:name":"Mettenheim",
    "tgn:placetype":[
        "aat:300008347"
    ]
},
  "bbox": [],
  "geometry": {"coordinates":[12.466667,48.266667],"type":"Point"}
}