{
  "id": 2025841,
  "type": "Feature",
  "properties": {
    "tgn:hierarchy":[
        "tgn:2025841",
        "tgn:1000001",
        "tgn:7012149",
        "tgn:2000477",
        "tgn:7007250",
        "tgn:7029392"
    ],
    "tgn:id":2025841,
    "tgn:name":"Lorenzo",
    "tgn:placetype":[
        "aat:300008347"
    ]
},
  "bbox": [],
  "geometry": {"coordinates":[-111.8667,43.7167],"type":"Point"}
}