{
  "id": 1077307,
  "type": "Feature",
  "properties": {
    "tgn:hierarchy":[
        "tgn:1077307",
        "tgn:1000004",
        "tgn:7000198",
        "tgn:1001895",
        "tgn:7029392"
    ],
    "tgn:id":1077307,
    "tgn:name:en":"Wai",
    "tgn:placetype":[
        "aat:300008347"
    ]
},
  "bbox": [],
  "geometry": {"coordinates":[73.89,17.952],"type":"Point"}
}