{
  "id": 2562341,
  "type": "Feature",
  "properties": {
    "tgn:hierarchy":[
        "tgn:2562341",
        "tgn:1000001",
        "tgn:7012149",
        "tgn:2000488",
        "tgn:7007250",
        "tgn:7029392"
    ],
    "tgn:id":2562341,
    "tgn:name":"Otter Springs",
    "tgn:placetype":[
        "aat:300008697"
    ]
},
  "bbox": [],
  "geometry": {"coordinates":[-116.0167,42.1333],"type":"Point"}
}