{
  "id": 7323939,
  "type": "Feature",
  "properties": {
    "tgn:hierarchy":[
        "tgn:7323939",
        "tgn:7008911",
        "tgn:1000003",
        "tgn:7002763",
        "tgn:1000095",
        "tgn:7029392"
    ],
    "tgn:id":7323939,
    "tgn:name":"Ribadesella, R\u00eda de",
    "tgn:placetype":[
        "aat:300266571"
    ]
},
  "bbox": [],
  "geometry": {"coordinates":[-5.066667,43.466667],"type":"Point"}
}