{
  "id": 1098093,
  "type": "Feature",
  "properties": {
    "tgn:hierarchy":[
        "tgn:1098093",
        "tgn:7000490",
        "tgn:1000006",
        "tgn:7001830",
        "tgn:7029392"
    ],
    "tgn:id":1098093,
    "tgn:name":"Rosedale",
    "tgn:placetype":[
        "aat:300008347"
    ]
},
  "bbox": [],
  "geometry": {"coordinates":[151.85,-24.5833],"type":"Point"}
}