{
  "id": 2310766,
  "type": "Feature",
  "properties": {
    "tgn:hierarchy":[
        "tgn:2310766",
        "tgn:2000090",
        "tgn:1000001",
        "tgn:7006451",
        "tgn:7012149",
        "tgn:7029392"
    ],
    "tgn:id":2310766,
    "tgn:name":"Ecks Mountain",
    "tgn:placetype":[
        "aat:300008798"
    ]
},
  "bbox": [],
  "geometry": {"coordinates":[-109.75,34.2167],"type":"Point"}
}