{
  "id": 2630982,
  "type": "Feature",
  "properties": {
    "tgn:hierarchy":[
        "tgn:2630982",
        "tgn:1000001",
        "tgn:2002318",
        "tgn:7012149",
        "tgn:7007922",
        "tgn:7029392"
    ],
    "tgn:id":2630982,
    "tgn:name":"Round Lake",
    "tgn:placetype":[
        "aat:300008680"
    ]
},
  "bbox": [],
  "geometry": {"coordinates":[-91.9333,46.2167],"type":"Point"}
}