{
  "id": 2601631,
  "type": "Feature",
  "properties": {
    "tgn:hierarchy":[
        "tgn:2601631",
        "tgn:1000001",
        "tgn:1002395",
        "tgn:7012149",
        "tgn:7007251",
        "tgn:7029392"
    ],
    "tgn:id":2601631,
    "tgn:name":"Put Creek",
    "tgn:placetype":[
        "aat:300008706"
    ]
},
  "bbox": [],
  "geometry": {"coordinates":[-90.0833,40.6167],"type":"Point"}
}