{
  "id": 7122257,
  "type": "Feature",
  "properties": {
    "tgn:hierarchy":[
        "tgn:7122257",
        "tgn:1000003",
        "tgn:7003676",
        "tgn:7000084",
        "tgn:7029392"
    ],
    "tgn:id":7122257,
    "tgn:name":"Nellinghof",
    "tgn:placetype":[
        "aat:300008347"
    ]
},
  "bbox": [],
  "geometry": {"coordinates":[8.083333,52.533333],"type":"Point"}
}