{
  "id": 2635175,
  "type": "Feature",
  "properties": {
    "tgn:hierarchy":[
        "tgn:2635175",
        "tgn:1000001",
        "tgn:7012149",
        "tgn:2001914",
        "tgn:7007825",
        "tgn:7029392"
    ],
    "tgn:id":2635175,
    "tgn:name":"Rymel Branch",
    "tgn:placetype":[
        "aat:300008699"
    ]
},
  "bbox": [],
  "geometry": {"coordinates":[-83.5833,35.7167],"type":"Point"}
}