{
  "id": 1133811,
  "type": "Feature",
  "properties": {
    "tgn:hierarchy":[
        "tgn:1133811",
        "tgn:1000001",
        "tgn:2002242",
        "tgn:7012149",
        "tgn:7007920",
        "tgn:7029392"
    ],
    "tgn:id":1133811,
    "tgn:name":"McCarteney Creek",
    "tgn:placetype":[
        "aat:300008706"
    ]
},
  "bbox": [],
  "geometry": {"coordinates":[-119.5833,47.6333],"type":"Point"}
}