{
  "id": 7121326,
  "type": "Feature",
  "properties": {
    "tgn:hierarchy":[
        "tgn:7121326",
        "tgn:7000096",
        "tgn:1000003",
        "tgn:7000084",
        "tgn:7029392"
    ],
    "tgn:id":7121326,
    "tgn:name":"Porep",
    "tgn:placetype":[
        "aat:300008347"
    ]
},
  "bbox": [],
  "geometry": {"coordinates":[12.033333,53.316667],"type":"Point"}
}