{
  "id": 7568461,
  "type": "Feature",
  "properties": {
    "tgn:hierarchy":[
        "tgn:7568461",
        "tgn:1000004",
        "tgn:7000198",
        "tgn:7016788",
        "tgn:7029392"
    ],
    "tgn:id":7568461,
    "tgn:name:en":"Serpura",
    "tgn:placetype":[
        "aat:300008347"
    ]
},
  "bbox": [],
  "geometry": {"coordinates":[73.916483,28.766345],"type":"Point"}
}