{
  "id": 2137527,
  "type": "Feature",
  "properties": {
    "tgn:hierarchy":[
        "tgn:2137527",
        "tgn:1000001",
        "tgn:2002367",
        "tgn:7012149",
        "tgn:7007923",
        "tgn:7029392"
    ],
    "tgn:id":2137527,
    "tgn:name":"Arno Spring Reservoir",
    "tgn:placetype":[
        "aat:300006191"
    ]
},
  "bbox": [],
  "geometry": {"coordinates":[-105.7667,44.0167],"type":"Point"}
}