{
  "id": 7507477,
  "type": "Feature",
  "properties": {
    "tgn:hierarchy":[
        "tgn:7507477",
        "tgn:1009227",
        "tgn:1000226",
        "tgn:7016729",
        "tgn:1000006",
        "tgn:7029392"
    ],
    "tgn:id":7507477,
    "tgn:name:en":"Pudding Hill",
    "tgn:placetype":[
        "aat:300008795"
    ]
},
  "bbox": [],
  "geometry": {"coordinates":[173.483333,-41.816667],"type":"Point"}
}