{
  "id": 1140995,
  "type": "Feature",
  "properties": {
    "tgn:hierarchy":[
        "tgn:1140995",
        "tgn:7000490",
        "tgn:1000006",
        "tgn:7006238",
        "tgn:7029392"
    ],
    "tgn:id":1140995,
    "tgn:name":"Melton",
    "tgn:placetype":[
        "aat:300008347"
    ]
},
  "bbox": [],
  "geometry": {"coordinates":[144.5833,-37.6833],"type":"Point"}
}