<<<<<<< HEAD
{
  "id": 7050832,
  "type": "Feature",
  "properties": {
    "tgn:hierarchy":[
        "tgn:7050832",
        "tgn:7003128",
        "tgn:1000003",
        "tgn:7008516",
        "tgn:1000080",
        "tgn:7029392"
    ],
    "tgn:id":7050832,
    "tgn:name":"Masi Torello",
    "tgn:placetype":[
        "aat:300008347"
    ]
},
  "bbox": [],
  "geometry": {"coordinates":[11.783333,44.8],"type":"Point"}
}
=======
{"geometry":{"type":"Point","coordinates":[11.783333,44.800000]},"type":"Feature","properties":{"hierarchy":["tgn:7050832","tgn:7003128","tgn:1000003","tgn:7008516","tgn:1000080","tgn:7029392"],"placetype":["aat:300008347"],"id":7050832,"name:xx":"Masi Torello"}}
>>>>>>> 03f74aca74312dbeaf24d7e61306dd6a786dc3d0
