{
  "id": 2661739,
  "type": "Feature",
  "properties": {
    "tgn:hierarchy":[
        "tgn:2661739",
        "tgn:7006450",
        "tgn:1000001",
        "tgn:7012149",
        "tgn:2000088",
        "tgn:7029392"
    ],
    "tgn:id":2661739,
    "tgn:name":"Shuktusa Creek",
    "tgn:placetype":[
        "aat:300008706"
    ]
},
  "bbox": [],
  "geometry": {"coordinates":[-132.1167,56.65],"type":"Point"}
}