{
  "id": 7406114,
  "type": "Feature",
  "properties": {
    "tgn:hierarchy":[
        "tgn:7406114",
        "tgn:7005585",
        "tgn:1000001",
        "tgn:7005560",
        "tgn:7029392"
    ],
    "tgn:id":7406114,
    "tgn:name":"La Mesa de Bravo",
    "tgn:placetype":[
        "aat:300008347"
    ]
},
  "bbox": [],
  "geometry": {"coordinates":[-101.333333,17.85],"type":"Point"}
}