{
  "id": 7524879,
  "type": "Feature",
  "properties": {
    "tgn:hierarchy":[
        "tgn:7524879",
        "tgn:7001242",
        "tgn:1001059",
        "tgn:7016833",
        "tgn:7029392"
    ],
    "tgn:id":7524879,
    "tgn:name:en":"Bu\u0163\u016bn\u012b al Kab\u012brah, 'Al\u0101w\u012b al",
    "tgn:placetype":[
        "aat:300008791"
    ]
},
  "bbox": [],
  "geometry": {"coordinates":[31.930348,31.288294],"type":"Point"}
}