{
  "id": 2066730,
  "type": "Feature",
  "properties": {
    "tgn:hierarchy":[
        "tgn:2066730",
        "tgn:1000001",
        "tgn:7012149",
        "tgn:2001460",
        "tgn:7007566",
        "tgn:7029392"
    ],
    "tgn:id":2066730,
    "tgn:name":"Bodega",
    "tgn:placetype":[
        "aat:300387016"
    ]
},
  "bbox": [],
  "geometry": {"coordinates":[-106.6667,34.55],"type":"Point"}
}