{
  "id": 2701996,
  "type": "Feature",
  "properties": {
    "tgn:hierarchy":[
        "tgn:2701996",
        "tgn:1000001",
        "tgn:2001429",
        "tgn:7012149",
        "tgn:7007566",
        "tgn:7029392"
    ],
    "tgn:id":2701996,
    "tgn:name":"Sugarloaf Spring",
    "tgn:placetype":[
        "aat:300008697"
    ]
},
  "bbox": [],
  "geometry": {"coordinates":[-107.9833,34.1167],"type":"Point"}
}