{
  "id": 7295974,
  "type": "Feature",
  "properties": {
    "tgn:hierarchy":[
        "tgn:7295974",
        "tgn:7002849",
        "tgn:1000003",
        "tgn:7009604",
        "tgn:1000095",
        "tgn:7029392"
    ],
    "tgn:id":7295974,
    "tgn:name":"Villano, Cabo",
    "tgn:placetype":[
        "aat:300008850"
    ]
},
  "bbox": [],
  "geometry": {"coordinates":[-2.94667,43.435964],"type":"Point"}
}