<<<<<<< HEAD
{
  "id": 2406742,
  "type": "Feature",
  "properties": {
    "tgn:hierarchy":[
        "tgn:2406742",
        "tgn:1000001",
        "tgn:7012149",
        "tgn:7018871",
        "tgn:7007920",
        "tgn:7029392"
    ],
    "tgn:id":2406742,
    "tgn:name":"Hunt Point",
    "tgn:placetype":[
        "aat:300008850"
    ]
},
  "bbox": [],
  "geometry": {"coordinates":[-122.2167,47.65],"type":"Point"}
}
=======
{"geometry":{"type":"Point","coordinates":[-122.216700,47.650000]},"type":"Feature","properties":{"hierarchy":["tgn:2406742","tgn:1000001","tgn:7012149","tgn:7018871","tgn:7007920","tgn:7029392"],"placetype":["aat:300008850"],"id":2406742,"name:xx":"Hunt Point"}}
>>>>>>> 03f74aca74312dbeaf24d7e61306dd6a786dc3d0
