{
  "id": 1125093,
  "type": "Feature",
  "properties": {
    "tgn:hierarchy":[
        "tgn:1125093",
        "tgn:1001945",
        "tgn:1000047",
        "tgn:7002457",
        "tgn:1000002",
        "tgn:7029392"
    ],
    "tgn:id":1125093,
    "tgn:name":"Jaguari-Mirim",
    "tgn:placetype":[
        "aat:300008707"
    ]
},
  "bbox": [],
  "geometry": {"coordinates":[-47.2833,-21.9833],"type":"Point"}
}