{
  "id": 2019424,
  "type": "Feature",
  "properties": {
    "tgn:hierarchy":[
        "tgn:2019424",
        "tgn:1000001",
        "tgn:1002473",
        "tgn:7012149",
        "tgn:7007240",
        "tgn:7029392"
    ],
    "tgn:id":2019424,
    "tgn:name":"Garden Grove",
    "tgn:placetype":[
        "aat:300008347"
    ]
},
  "bbox": [],
  "geometry": {"coordinates":[-82.4333,28.4667],"type":"Point"}
}