{
  "id": 2307977,
  "type": "Feature",
  "properties": {
    "tgn:hierarchy":[
        "tgn:2307977",
        "tgn:1000001",
        "tgn:7012149",
        "tgn:7022201",
        "tgn:7007919",
        "tgn:7029392"
    ],
    "tgn:id":2307977,
    "tgn:name":"East Haven",
    "tgn:placetype":[
        "aat:300008347"
    ]
},
  "bbox": [],
  "geometry": {"coordinates":[-76.2667,36.8833],"type":"Point"}
}