{
  "id": 7003811,
  "type": "Feature",
  "properties": {
    "tgn:hierarchy":[
        "tgn:7003811",
        "tgn:1001622",
        "tgn:1000003",
        "tgn:7003122",
        "tgn:1000080",
        "tgn:7029392"
    ],
    "tgn:id":7003811,
    "tgn:name":"Palma di Montechiaro",
    "tgn:placetype":[
        "aat:300008347"
    ]
},
  "bbox": [],
  "geometry": {"coordinates":[13.766667,37.183333],"type":"Point"}
}