{
  "id": 2230762,
  "type": "Feature",
  "properties": {
    "tgn:hierarchy":[
        "tgn:2230762",
        "tgn:1000001",
        "tgn:7012149",
        "tgn:2001714",
        "tgn:7007708",
        "tgn:7029392"
    ],
    "tgn:id":2230762,
    "tgn:name":"Central Canal",
    "tgn:placetype":[
        "aat:300006075"
    ]
},
  "bbox": [],
  "geometry": {"coordinates":[-122.0167,42.6333],"type":"Point"}
}