<<<<<<< HEAD
{
  "id": 2331752,
  "type": "Feature",
  "properties": {
    "tgn:hierarchy":[
        "tgn:2331752",
        "tgn:1000001",
        "tgn:7012149",
        "tgn:1002501",
        "tgn:7007710",
        "tgn:7029392"
    ],
    "tgn:id":2331752,
    "tgn:name":"Fleming Summit",
    "tgn:placetype":[
        "aat:300008347"
    ]
},
  "bbox": [],
  "geometry": {"coordinates":[-78.9,40.7167],"type":"Point"}
}
=======
{"geometry":{"type":"Point","coordinates":[-78.900000,40.716700]},"type":"Feature","properties":{"hierarchy":["tgn:2331752","tgn:1000001","tgn:7012149","tgn:1002501","tgn:7007710","tgn:7029392"],"placetype":["aat:300008347"],"id":2331752,"name:xx":"Fleming Summit"}}
>>>>>>> 03f74aca74312dbeaf24d7e61306dd6a786dc3d0
