{
  "id": 7003743,
  "type": "Feature",
  "properties": {
    "tgn:hierarchy":[
        "tgn:7003743",
        "tgn:1000003",
        "tgn:7011731",
        "tgn:7029392"
    ],
    "tgn:id":7003743,
    "tgn:name":"Appenzell Ausserrhoden",
    "tgn:placetype":[
        "aat:300387064",
        "aat:300000769"
    ]
},
  "bbox": [],
  "geometry": {"coordinates":[9.398,47.389],"type":"Point"}
}