<<<<<<< HEAD
{
  "id": 2409875,
  "type": "Feature",
  "properties": {
    "tgn:hierarchy":[
        "tgn:2409875",
        "tgn:7006450",
        "tgn:1000001",
        "tgn:7012149",
        "tgn:2124005",
        "tgn:7029392"
    ],
    "tgn:id":2409875,
    "tgn:name":"Imakruak Lake",
    "tgn:placetype":[
        "aat:300008680"
    ]
},
  "bbox": [],
  "geometry": {"coordinates":[-153.9833,70.7667],"type":"Point"}
}
=======
{"geometry":{"type":"Point","coordinates":[-153.983300,70.766700]},"type":"Feature","properties":{"hierarchy":["tgn:2409875","tgn:7006450","tgn:1000001","tgn:7012149","tgn:2124005","tgn:7029392"],"placetype":["aat:300008680"],"id":2409875,"name:xx":"Imakruak Lake"}}
>>>>>>> 03f74aca74312dbeaf24d7e61306dd6a786dc3d0
