{
  "id": 7006468,
  "type": "Feature",
  "properties": {
    "tgn:hierarchy":[
        "tgn:7006468",
        "tgn:1000003",
        "tgn:7011765",
        "tgn:7029392"
    ],
    "tgn:id":7006468,
    "tgn:name":"Stredoslovensk\u00fd Kraj",
    "tgn:placetype":[
        "aat:300387179",
        "aat:300236112"
    ]
},
  "bbox": [],
  "geometry": {"coordinates":[19.1667,48.6667],"type":"Point"}
}