{
  "id": 7434992,
  "type": "Feature",
  "properties": {
    "tgn:hierarchy":[
        "tgn:7434992",
        "tgn:1000001",
        "tgn:7005589",
        "tgn:7005560",
        "tgn:7029392"
    ],
    "tgn:id":7434992,
    "tgn:name":"Valle Perdido",
    "tgn:placetype":[
        "aat:300008347"
    ]
},
  "bbox": [],
  "geometry": {"coordinates":[-99.983333,24.233333],"type":"Point"}
}