{
  "id": 2122535,
  "type": "Feature",
  "properties": {
    "tgn:hierarchy":[
        "tgn:2122535",
        "tgn:1000001",
        "tgn:7012149",
        "tgn:2002354",
        "tgn:7007922",
        "tgn:7029392"
    ],
    "tgn:id":2122535,
    "tgn:name":"Tigerton",
    "tgn:placetype":[
        "aat:300008347"
    ]
},
  "bbox": [],
  "geometry": {"coordinates":[-89.05,44.7333],"type":"Point"}
}