{
  "id": 7493358,
  "type": "Feature",
  "properties": {
    "tgn:hierarchy":[
        "tgn:7493358",
        "tgn:1000004",
        "tgn:1000454",
        "tgn:1000141",
        "tgn:7029392"
    ],
    "tgn:id":7493358,
    "tgn:name":"Donglu Shan",
    "tgn:placetype":[
        "aat:300008798"
    ]
},
  "bbox": [],
  "geometry": {"coordinates":[121.419012,24.849955],"type":"Point"}
}