{
  "id": 7537255,
  "type": "Feature",
  "properties": {
    "tgn:hierarchy":[
        "tgn:7537255",
        "tgn:7001242",
        "tgn:7016833",
        "tgn:1001418",
        "tgn:7029392"
    ],
    "tgn:id":7537255,
    "tgn:name:en":"Shamal, Tall\u0101t ash",
    "tgn:placetype":[
        "aat:300008777"
    ]
},
  "bbox": [],
  "geometry": {"coordinates":[29.633333,30.583333],"type":"Point"}
}