{
  "id": 7014248,
  "type": "Feature",
  "properties": {
    "tgn:hierarchy":[
        "tgn:7014248",
        "tgn:1000001",
        "tgn:7012149",
        "tgn:7007157",
        "tgn:1002684",
        "tgn:7029392"
    ],
    "tgn:id":7014248,
    "tgn:name":"Soledad",
    "tgn:placetype":[
        "aat:300387277",
        "aat:300008347",
        "aat:300008486",
        "aat:300008375"
    ]
},
  "bbox": [],
  "geometry": {"coordinates":[-121.3167,36.4167],"type":"Point"}
}