<<<<<<< HEAD
{
  "id": 7246120,
  "type": "Feature",
  "properties": {
    "tgn:hierarchy":[
        "tgn:7246120",
        "tgn:7007877",
        "tgn:1000003",
        "tgn:1000063",
        "tgn:4012014",
        "tgn:7029392"
    ],
    "tgn:id":7246120,
    "tgn:name":"Comte, Bois du",
    "tgn:placetype":[
        "aat:300008863"
    ]
},
  "bbox": [],
  "geometry": {"coordinates":[4.133333,50.283333],"type":"Point"}
}
=======
{"geometry":{"type":"Point","coordinates":[4.133333,50.283333]},"type":"Feature","properties":{"hierarchy":["tgn:7246120","tgn:7007877","tgn:1000003","tgn:1000063","tgn:4012014","tgn:7029392"],"placetype":["aat:300008863"],"id":7246120,"name:xx":"Comte, Bois du"}}
>>>>>>> 03f74aca74312dbeaf24d7e61306dd6a786dc3d0
