{
  "id": 7402518,
  "type": "Feature",
  "properties": {
    "tgn:hierarchy":[
        "tgn:7402518",
        "tgn:1000001",
        "tgn:1001937",
        "tgn:7005560",
        "tgn:7029392"
    ],
    "tgn:id":7402518,
    "tgn:name":"Nuevo Conduc\u00e1n",
    "tgn:placetype":[
        "aat:300008347"
    ]
},
  "bbox": [],
  "geometry": {"coordinates":[-88.766667,19.358333],"type":"Point"}
}