{
  "id": 7417149,
  "type": "Feature",
  "properties": {
    "tgn:hierarchy":[
        "tgn:7417149",
        "tgn:1000001",
        "tgn:7005591",
        "tgn:7005560",
        "tgn:7029392"
    ],
    "tgn:id":7417149,
    "tgn:name:es":"Dos Caminos",
    "tgn:placetype":[
        "aat:300008347"
    ]
},
  "bbox": [],
  "geometry": {"coordinates":[-97.797778,16.384167],"type":"Point"}
}