{
  "id": 2328375,
  "type": "Feature",
  "properties": {
    "tgn:hierarchy":[
        "tgn:2328375",
        "tgn:1000001",
        "tgn:7012149",
        "tgn:1002943",
        "tgn:7007708",
        "tgn:7029392"
    ],
    "tgn:id":2328375,
    "tgn:name":"Fisher Creek",
    "tgn:placetype":[
        "aat:300008706"
    ]
},
  "bbox": [],
  "geometry": {"coordinates":[-123.8667,45.6833],"type":"Point"}
}