{
  "id": 2732607,
  "type": "Feature",
  "properties": {
    "tgn:hierarchy":[
        "tgn:2732607",
        "tgn:1000001",
        "tgn:7012149",
        "tgn:2000611",
        "tgn:7007253",
        "tgn:7029392"
    ],
    "tgn:id":2732607,
    "tgn:name":"Turkey Creek",
    "tgn:placetype":[
        "aat:300008706"
    ]
},
  "bbox": [],
  "geometry": {"coordinates":[-91.8167,41.0333],"type":"Point"}
}