{
  "id": 7588654,
  "type": "Feature",
  "properties": {
    "tgn:hierarchy":[
        "tgn:7588654",
        "tgn:1000004",
        "tgn:7000198",
        "tgn:7000799",
        "tgn:7029392"
    ],
    "tgn:id":7588654,
    "tgn:name:en":"Skarket",
    "tgn:placetype":[
        "aat:300008347"
    ]
},
  "bbox": [],
  "geometry": {"coordinates":[74.052778,33.819444],"type":"Point"}
}