{
  "id": 1117496,
  "type": "Feature",
  "properties": {
    "tgn:hierarchy":[
        "tgn:1117496",
        "tgn:7005685",
        "tgn:1000001",
        "tgn:7013154",
        "tgn:7029392"
    ],
    "tgn:id":1117496,
    "tgn:name":"Nikip Lake",
    "tgn:placetype":[
        "aat:300008680"
    ]
},
  "bbox": [],
  "geometry": {"coordinates":[-91.8833,52.8833],"type":"Point"}
}