{
  "id": 7304194,
  "type": "Feature",
  "properties": {
    "tgn:hierarchy":[
        "tgn:7304194",
        "tgn:7007088",
        "tgn:1000003",
        "tgn:7009604",
        "tgn:1000095",
        "tgn:7029392"
    ],
    "tgn:id":7304194,
    "tgn:name":"Manzanos",
    "tgn:placetype":[
        "aat:300008347"
    ]
},
  "bbox": [],
  "geometry": {"coordinates":[-2.8757,42.741853],"type":"Point"}
}