{
  "id": 7284347,
  "type": "Feature",
  "properties": {
    "tgn:hierarchy":[
        "tgn:7284347",
        "tgn:7002464",
        "tgn:1000049",
        "tgn:1000002",
        "tgn:7029392"
    ],
    "tgn:id":7284347,
    "tgn:name":"Punta Madrid, Cerro",
    "tgn:placetype":[
        "aat:300008795"
    ]
},
  "bbox": [],
  "geometry": {"coordinates":[-70.283333,-18.95],"type":"Point"}
}