{
  "id": 7141725,
  "type": "Feature",
  "properties": {
    "tgn:hierarchy":[
        "tgn:7141725",
        "tgn:1000003",
        "tgn:7003678",
        "tgn:7000084",
        "tgn:7029392"
    ],
    "tgn:id":7141725,
    "tgn:name":"Main-Taunus-Kreis",
    "tgn:placetype":[
        "aat:300387198"
    ]
},
  "bbox": [],
  "geometry": {"coordinates":[8.434167,50.109722],"type":"Point"}
}