{
  "id": 2664828,
  "type": "Feature",
  "properties": {
    "tgn:hierarchy":[
        "tgn:2664828",
        "tgn:1000001",
        "tgn:7012149",
        "tgn:2001297",
        "tgn:7007524",
        "tgn:7029392"
    ],
    "tgn:id":2664828,
    "tgn:name":"Simon Reservoir",
    "tgn:placetype":[
        "aat:300006191"
    ]
},
  "bbox": [],
  "geometry": {"coordinates":[-106.2167,45.3333],"type":"Point"}
}