{
  "id": 7311474,
  "type": "Feature",
  "properties": {
    "tgn:hierarchy":[
        "tgn:7311474",
        "tgn:1001695",
        "tgn:1000049",
        "tgn:1000002",
        "tgn:7029392"
    ],
    "tgn:id":7311474,
    "tgn:name":"Los Colihues, Cerro",
    "tgn:placetype":[
        "aat:300008795"
    ]
},
  "bbox": [],
  "geometry": {"coordinates":[-70.55,-34.166667],"type":"Point"}
}