{
  "id": 2519817,
  "type": "Feature",
  "properties": {
    "tgn:hierarchy":[
        "tgn:2519817",
        "tgn:1000001",
        "tgn:7012149",
        "tgn:2002251",
        "tgn:7007920",
        "tgn:7029392"
    ],
    "tgn:id":2519817,
    "tgn:name":"Mojonnier",
    "tgn:placetype":[
        "aat:300008347"
    ]
},
  "bbox": [],
  "geometry": {"coordinates":[-118.4167,46.0167],"type":"Point"}
}