<<<<<<< HEAD
{
  "id": 2333893,
  "type": "Feature",
  "properties": {
    "tgn:hierarchy":[
        "tgn:2333893",
        "tgn:7006450",
        "tgn:1000001",
        "tgn:7012149",
        "tgn:2124002",
        "tgn:7029392"
    ],
    "tgn:id":2333893,
    "tgn:name":"Ford Arm",
    "tgn:placetype":[
        "aat:300132316"
    ]
},
  "bbox": [],
  "geometry": {"coordinates":[-135.95,57.5667],"type":"Point"}
}
=======
{"geometry":{"type":"Point","coordinates":[-135.950000,57.566700]},"type":"Feature","properties":{"hierarchy":["tgn:2333893","tgn:7006450","tgn:1000001","tgn:7012149","tgn:2124002","tgn:7029392"],"placetype":["aat:300132316"],"id":2333893,"name:xx":"Ford Arm"}}
>>>>>>> 03f74aca74312dbeaf24d7e61306dd6a786dc3d0
