{
  "id": 2749715,
  "type": "Feature",
  "properties": {
    "tgn:hierarchy":[
        "tgn:2749715",
        "tgn:1000001",
        "tgn:7012149",
        "tgn:1002426",
        "tgn:7007255",
        "tgn:7029392"
    ],
    "tgn:id":2749715,
    "tgn:name":"Walnut Grove Hollow",
    "tgn:placetype":[
        "aat:300008761"
    ]
},
  "bbox": [],
  "geometry": {"coordinates":[-83.05,38.5167],"type":"Point"}
}