{
  "id": 7574751,
  "type": "Feature",
  "properties": {
    "tgn:hierarchy":[
        "tgn:7574751",
        "tgn:1000004",
        "tgn:7000198",
        "tgn:1001895",
        "tgn:7029392"
    ],
    "tgn:id":7574751,
    "tgn:name:en":"Madh",
    "tgn:placetype":[
        "aat:300008347"
    ]
},
  "bbox": [],
  "geometry": {"coordinates":[73.833333,19.316667],"type":"Point"}
}