<<<<<<< HEAD
{
  "id": 2401271,
  "type": "Feature",
  "properties": {
    "tgn:hierarchy":[
        "tgn:2401271",
        "tgn:1000001",
        "tgn:2000772",
        "tgn:7012149",
        "tgn:7007255",
        "tgn:7029392"
    ],
    "tgn:id":2401271,
    "tgn:name":"Horsemill Branch",
    "tgn:placetype":[
        "aat:300008699"
    ]
},
  "bbox": [],
  "geometry": {"coordinates":[-83.3167,37.5333],"type":"Point"}
}
=======
{"geometry":{"type":"Point","coordinates":[-83.316700,37.533300]},"type":"Feature","properties":{"hierarchy":["tgn:2401271","tgn:1000001","tgn:2000772","tgn:7012149","tgn:7007255","tgn:7029392"],"placetype":["aat:300008699"],"id":2401271,"name:xx":"Horsemill Branch"}}
>>>>>>> 03f74aca74312dbeaf24d7e61306dd6a786dc3d0
