{
  "id": 2401271,
  "type": "Feature",
  "properties": {
    "tgn:hierarchy":[
        "tgn:2401271",
        "tgn:1000001",
        "tgn:2000772",
        "tgn:7012149",
        "tgn:7007255",
        "tgn:7029392"
    ],
    "tgn:id":2401271,
    "tgn:name":"Horsemill Branch",
    "tgn:placetype":[
        "aat:300008699"
    ]
},
  "bbox": [],
  "geometry": {"coordinates":[-83.3167,37.5333],"type":"Point"}
}