{
  "id": 2640688,
  "type": "Feature",
  "properties": {
    "tgn:hierarchy":[
        "tgn:2640688",
        "tgn:1000001",
        "tgn:7012149",
        "tgn:7019676",
        "tgn:7007566",
        "tgn:7029392"
    ],
    "tgn:id":2640688,
    "tgn:name":"San Miguel Canyon",
    "tgn:placetype":[
        "aat:300008761"
    ]
},
  "bbox": [],
  "geometry": {"coordinates":[-107.4667,35.3833],"type":"Point"}
}