{
  "id": 7231788,
  "type": "Feature",
  "properties": {
    "tgn:hierarchy":[
        "tgn:7231788",
        "tgn:7002748",
        "tgn:7001399",
        "tgn:1000003",
        "tgn:1000074",
        "tgn:7029392"
    ],
    "tgn:id":7231788,
    "tgn:name":"Kalantza\u00ed\u00efka",
    "tgn:placetype":[
        "aat:300008347"
    ]
},
  "bbox": [],
  "geometry": {"coordinates":[21.706944,39.316389],"type":"Point"}
}