{
  "id": 7338455,
  "type": "Feature",
  "properties": {
    "tgn:hierarchy":[
        "tgn:7338455",
        "tgn:7002758",
        "tgn:7002841",
        "tgn:1000003",
        "tgn:1000095",
        "tgn:7029392"
    ],
    "tgn:id":7338455,
    "tgn:name":"Castillejo, Arroyo de",
    "tgn:placetype":[
        "aat:300008699"
    ]
},
  "bbox": [],
  "geometry": {"coordinates":[-5.716667,37.933333],"type":"Point"}
}