{
  "id": 2579244,
  "type": "Feature",
  "properties": {
    "tgn:hierarchy":[
        "tgn:2579244",
        "tgn:1000001",
        "tgn:7012149",
        "tgn:2001254",
        "tgn:7007523",
        "tgn:7029392"
    ],
    "tgn:id":2579244,
    "tgn:name":"Picayune Lead Diggings",
    "tgn:placetype":[
        "aat:300000390"
    ]
},
  "bbox": [],
  "geometry": {"coordinates":[-91.0167,37.8667],"type":"Point"}
}