{
  "id": 7545194,
  "type": "Feature",
  "properties": {
    "tgn:hierarchy":[
        "tgn:7545194",
        "tgn:1000004",
        "tgn:7000198",
        "tgn:7016722",
        "tgn:7029392"
    ],
    "tgn:id":7545194,
    "tgn:name:en":"Bargon Sharqi",
    "tgn:placetype":[
        "aat:300008347"
    ]
},
  "bbox": [],
  "geometry": {"coordinates":[83.191315,26.512892],"type":"Point"}
}