{
  "id": 7273332,
  "type": "Feature",
  "properties": {
    "tgn:concordances":{
        "gn:id":"2744686"
    },
    "tgn:hierarchy":[
        "tgn:7273332",
        "tgn:1000003",
        "tgn:7003613",
        "tgn:7016845",
        "tgn:7029392"
    ],
    "tgn:id":7273332,
    "tgn:name:nl":"Westervalge",
    "tgn:placetype":[
        "aat:300008347"
    ]
},
  "bbox": [],
  "geometry": {"coordinates":[6.55,53.383333],"type":"Point"}
}