{
  "id": 7031228,
  "type": "Feature",
  "properties": {
    "tgn:hierarchy":[
        "tgn:7031228",
        "tgn:7016849",
        "tgn:1000004",
        "tgn:1000119",
        "tgn:7029392"
    ],
    "tgn:id":7031228,
    "tgn:name":"Tell Jezer",
    "tgn:placetype":[
        "aat:300008347",
        "aat:300000810",
        "aat:300167671",
        "aat:300008545",
        "aat:300008389"
    ]
},
  "bbox": [],
  "geometry": {"coordinates":[34.919,31.859],"type":"Point"}
}