{
  "id": 7236028,
  "type": "Feature",
  "properties": {
    "tgn:hierarchy":[
        "tgn:7236028",
        "tgn:7002735",
        "tgn:7017076",
        "tgn:1000003",
        "tgn:1000074",
        "tgn:7029392"
    ],
    "tgn:id":7236028,
    "tgn:name":"An\u00f3yia",
    "tgn:placetype":[
        "aat:300008347"
    ]
},
  "bbox": [],
  "geometry": {"coordinates":[22.433333,36.983333],"type":"Point"}
}