{
  "id": 2343891,
  "type": "Feature",
  "properties": {
    "tgn:hierarchy":[
        "tgn:2343891",
        "tgn:1000001",
        "tgn:1002923",
        "tgn:7012149",
        "tgn:7007517",
        "tgn:7029392"
    ],
    "tgn:id":2343891,
    "tgn:name":"Gallops Island",
    "tgn:placetype":[
        "aat:300008791"
    ]
},
  "bbox": [],
  "geometry": {"coordinates":[-70.9333,42.3167],"type":"Point"}
}