{
  "id": 2597335,
  "type": "Feature",
  "properties": {
    "tgn:hierarchy":[
        "tgn:2597335",
        "tgn:1000001",
        "tgn:7012149",
        "tgn:7007522",
        "tgn:7029392"
    ],
    "tgn:id":2597335,
    "tgn:name":"Prairie Creek",
    "tgn:placetype":[
        "aat:300008706"
    ]
},
  "bbox": [],
  "geometry": {"coordinates":[-89.0333,33.7667],"type":"Point"}
}