{
  "id": 2746939,
  "type": "Feature",
  "properties": {
    "tgn:hierarchy":[
        "tgn:2746939",
        "tgn:1000001",
        "tgn:7012149",
        "tgn:2001711",
        "tgn:7007708",
        "tgn:7029392"
    ],
    "tgn:id":2746939,
    "tgn:name":"Wagner Butte",
    "tgn:placetype":[
        "aat:300008798"
    ]
},
  "bbox": [],
  "geometry": {"coordinates":[-122.7667,42.1167],"type":"Point"}
}