{
  "id": 2011974,
  "type": "Feature",
  "properties": {
    "tgn:hierarchy":[
        "tgn:2011974",
        "tgn:1000001",
        "tgn:7012149",
        "tgn:7007157",
        "tgn:1002857",
        "tgn:7029392"
    ],
    "tgn:id":2011974,
    "tgn:name":"Keenbrook",
    "tgn:placetype":[
        "aat:300387016"
    ]
},
  "bbox": [],
  "geometry": {"coordinates":[-117.45,34.2333],"type":"Point"}
}