{
  "id": 2036578,
  "type": "Feature",
  "properties": {
    "tgn:hierarchy":[
        "tgn:2036578",
        "tgn:1000001",
        "tgn:2000695",
        "tgn:7012149",
        "tgn:7007254",
        "tgn:7029392"
    ],
    "tgn:id":2036578,
    "tgn:name":"Kanco",
    "tgn:placetype":[
        "aat:300387016"
    ]
},
  "bbox": [],
  "geometry": {"coordinates":[-102.0333,38.4667],"type":"Point"}
}