<<<<<<< HEAD
{
  "id": 7371744,
  "type": "Feature",
  "properties": {
    "tgn:hierarchy":[
        "tgn:7371744",
        "tgn:7005581",
        "tgn:1000001",
        "tgn:7005560",
        "tgn:7029392"
    ],
    "tgn:id":7371744,
    "tgn:name":"La Cal, Arroyo de",
    "tgn:placetype":[
        "aat:300266554",
        "aat:300008699"
    ]
},
  "bbox": [],
  "geometry": {"coordinates":[-106.2,21.133333],"type":"Point"}
}
=======
{"geometry":{"type":"Point","coordinates":[-106.200000,21.133333]},"type":"Feature","properties":{"hierarchy":["tgn:7371744","tgn:7005581","tgn:1000001","tgn:7005560","tgn:7029392"],"placetype":["aat:300266554","aat:300008699"],"id":7371744,"name:xx":"La Cal, Arroyo de"}}
>>>>>>> 03f74aca74312dbeaf24d7e61306dd6a786dc3d0
