{
  "id": 2508235,
  "type": "Feature",
  "properties": {
    "tgn:hierarchy":[
        "tgn:2508235",
        "tgn:1000001",
        "tgn:7012149",
        "tgn:7007253",
        "tgn:7029392"
    ],
    "tgn:id":2508235,
    "tgn:name":"Middle Branch Wapsinonoc Creek",
    "tgn:placetype":[
        "aat:300008706"
    ]
},
  "bbox": [],
  "geometry": {"coordinates":[-91.2833,41.7167],"type":"Point"}
}