{
  "id": 7414880,
  "type": "Feature",
  "properties": {
    "tgn:hierarchy":[
        "tgn:7414880",
        "tgn:1000001",
        "tgn:7005591",
        "tgn:7005560",
        "tgn:7029392"
    ],
    "tgn:id":7414880,
    "tgn:name:es":"Coicoyan, R\u00edo",
    "tgn:placetype":[
        "aat:300008699"
    ]
},
  "bbox": [],
  "geometry": {"coordinates":[-98.264167,17.445278],"type":"Point"}
}