{
  "id": 2641656,
  "type": "Feature",
  "properties": {
    "tgn:hierarchy":[
        "tgn:2641656",
        "tgn:1000001",
        "tgn:7012149",
        "tgn:7007826",
        "tgn:7029392"
    ],
    "tgn:id":2641656,
    "tgn:name":"Sand Hill",
    "tgn:placetype":[
        "aat:300008798"
    ]
},
  "bbox": [],
  "geometry": {"coordinates":[-95.9167,32.3667],"type":"Point"}
}