{
  "id": 7539375,
  "type": "Feature",
  "properties": {
    "tgn:hierarchy":[
        "tgn:7539375",
        "tgn:7001242",
        "tgn:7001105",
        "tgn:7016833",
        "tgn:7029392"
    ],
    "tgn:id":7539375,
    "tgn:name:en":"Qalh\u0101nah",
    "tgn:placetype":[
        "aat:300008347"
    ]
},
  "bbox": [],
  "geometry": {"coordinates":[30.839983,29.232677],"type":"Point"}
}