{
  "id": 1104227,
  "type": "Feature",
  "properties": {
    "tgn:hierarchy":[
        "tgn:1104227",
        "tgn:1000004",
        "tgn:7029392"
    ],
    "tgn:id":1104227,
    "tgn:name":"Chomiomo",
    "tgn:placetype":[
        "aat:300008795"
    ]
},
  "bbox": [],
  "geometry": {"coordinates":[88.5167,28.0167],"type":"Point"}
}