<<<<<<< HEAD
{
  "id": 7369213,
  "type": "Feature",
  "properties": {
    "tgn:hierarchy":[
        "tgn:7369213",
        "tgn:1000001",
        "tgn:1001960",
        "tgn:7005560",
        "tgn:7029392"
    ],
    "tgn:id":7369213,
    "tgn:name":"Guadalupe, Ca\u00f1\u00f3n de",
    "tgn:placetype":[
        "aat:300008699"
    ]
},
  "bbox": [],
  "geometry": {"coordinates":[-109.15,31.116667],"type":"Point"}
}
=======
{"geometry":{"type":"Point","coordinates":[-109.150000,31.116667]},"type":"Feature","properties":{"hierarchy":["tgn:7369213","tgn:1000001","tgn:1001960","tgn:7005560","tgn:7029392"],"placetype":["aat:300008699"],"id":7369213,"name:xx":"Guadalupe, Ca\u00f1\u00f3n de"}}
>>>>>>> 03f74aca74312dbeaf24d7e61306dd6a786dc3d0
