<<<<<<< HEAD
{
  "id": 2765663,
  "type": "Feature",
  "properties": {
    "tgn:hierarchy":[
        "tgn:2765663",
        "tgn:1000001",
        "tgn:7012149",
        "tgn:2000219",
        "tgn:7007158",
        "tgn:7029392"
    ],
    "tgn:id":2765663,
    "tgn:name":"White Creek",
    "tgn:placetype":[
        "aat:300008706"
    ]
},
  "bbox": [],
  "geometry": {"coordinates":[-105.0333,37.3333],"type":"Point"}
}
=======
{"geometry":{"type":"Point","coordinates":[-105.033300,37.333300]},"type":"Feature","properties":{"hierarchy":["tgn:2765663","tgn:1000001","tgn:7012149","tgn:2000219","tgn:7007158","tgn:7029392"],"placetype":["aat:300008706"],"id":2765663,"name:xx":"White Creek"}}
>>>>>>> 03f74aca74312dbeaf24d7e61306dd6a786dc3d0
