{
  "id": 7472831,
  "type": "Feature",
  "properties": {
    "tgn:hierarchy":[
        "tgn:7472831",
        "tgn:1000004",
        "tgn:1000454",
        "tgn:1000141",
        "tgn:7029392"
    ],
    "tgn:id":7472831,
    "tgn:name":"Dunan Qiao",
    "tgn:placetype":[
        "aat:300007836"
    ]
},
  "bbox": [],
  "geometry": {"coordinates":[121.69,24.9323],"type":"Point"}
}