{
  "id": 2497907,
  "type": "Feature",
  "properties": {
    "tgn:hierarchy":[
        "tgn:2497907",
        "tgn:2000192",
        "tgn:1000001",
        "tgn:7012149",
        "tgn:7007158",
        "tgn:7029392"
    ],
    "tgn:id":2497907,
    "tgn:name":"Mayham Lake",
    "tgn:placetype":[
        "aat:300008680"
    ]
},
  "bbox": [],
  "geometry": {"coordinates":[-105.0333,39.8167],"type":"Point"}
}