{
  "id": 2603773,
  "type": "Feature",
  "properties": {
    "tgn:hierarchy":[
        "tgn:2603773",
        "tgn:1000001",
        "tgn:7012149",
        "tgn:2001718",
        "tgn:7007708",
        "tgn:7029392"
    ],
    "tgn:id":2603773,
    "tgn:name":"Quicksand Reservoir",
    "tgn:placetype":[
        "aat:300006191"
    ]
},
  "bbox": [],
  "geometry": {"coordinates":[-117.55,43.6667],"type":"Point"}
}