{
  "id": 2484691,
  "type": "Feature",
  "properties": {
    "tgn:hierarchy":[
        "tgn:2484691",
        "tgn:2001467",
        "tgn:1000001",
        "tgn:7012149",
        "tgn:7007709",
        "tgn:7029392"
    ],
    "tgn:id":2484691,
    "tgn:name":"Laurel Ridge",
    "tgn:placetype":[
        "aat:300266640"
    ]
},
  "bbox": [],
  "geometry": {"coordinates":[-81.25,36.3667],"type":"Point"}
}