{
  "id": 2297489,
  "type": "Feature",
  "properties": {
    "tgn:hierarchy":[
        "tgn:2297489",
        "tgn:1000001",
        "tgn:7012149",
        "tgn:2002125",
        "tgn:7007827",
        "tgn:7029392"
    ],
    "tgn:id":2297489,
    "tgn:name":"Dry Fork",
    "tgn:placetype":[
        "aat:300008761"
    ]
},
  "bbox": [],
  "geometry": {"coordinates":[-111.5833,40.5667],"type":"Point"}
}