{
  "id": 7591829,
  "type": "Feature",
  "properties": {
    "tgn:hierarchy":[
        "tgn:7591829",
        "tgn:1000004",
        "tgn:7000198",
        "tgn:7000799",
        "tgn:7029392"
    ],
    "tgn:id":7591829,
    "tgn:name:en":"Targ\u0101h",
    "tgn:placetype":[
        "aat:300008347"
    ]
},
  "bbox": [],
  "geometry": {"coordinates":[74.755456,32.957832],"type":"Point"}
}