<<<<<<< HEAD
{
  "id": 7050779,
  "type": "Feature",
  "properties": {
    "tgn:hierarchy":[
        "tgn:7050779",
        "tgn:7003154",
        "tgn:1000003",
        "tgn:7003120",
        "tgn:1000080",
        "tgn:7029392"
    ],
    "tgn:id":7050779,
    "tgn:name":"Netro",
    "tgn:placetype":[
        "aat:300008347"
    ]
},
  "bbox": [],
  "geometry": {"coordinates":[7.95,45.533333],"type":"Point"}
}
=======
{"geometry":{"type":"Point","coordinates":[7.950000,45.533333]},"type":"Feature","properties":{"hierarchy":["tgn:7050779","tgn:7003154","tgn:1000003","tgn:7003120","tgn:1000080","tgn:7029392"],"placetype":["aat:300008347"],"id":7050779,"name:xx":"Netro"}}
>>>>>>> 03f74aca74312dbeaf24d7e61306dd6a786dc3d0
