{
  "id": 7138732,
  "type": "Feature",
  "properties": {
    "tgn:hierarchy":[
        "tgn:7138732",
        "tgn:1000003",
        "tgn:7003689",
        "tgn:7000084",
        "tgn:7029392"
    ],
    "tgn:id":7138732,
    "tgn:name":"Lauters-H\u00fcgel",
    "tgn:placetype":[
        "aat:300008777"
    ]
},
  "bbox": [],
  "geometry": {"coordinates":[11.133333,51.116667],"type":"Point"}
}