<<<<<<< HEAD
{
  "id": 2250969,
  "type": "Feature",
  "properties": {
    "tgn:hierarchy":[
        "tgn:2250969",
        "tgn:1000001",
        "tgn:7012149",
        "tgn:2000220",
        "tgn:7007158",
        "tgn:7029392"
    ],
    "tgn:id":2250969,
    "tgn:name":"Columbine Ditch",
    "tgn:placetype":[
        "aat:300006075"
    ]
},
  "bbox": [],
  "geometry": {"coordinates":[-106.5833,40.6],"type":"Point"}
}
=======
{"geometry":{"type":"Point","coordinates":[-106.583300,40.600000]},"type":"Feature","properties":{"hierarchy":["tgn:2250969","tgn:1000001","tgn:7012149","tgn:2000220","tgn:7007158","tgn:7029392"],"placetype":["aat:300006075"],"id":2250969,"name:xx":"Columbine Ditch"}}
>>>>>>> 03f74aca74312dbeaf24d7e61306dd6a786dc3d0
