{
  "id": 4005978,
  "type": "Feature",
  "properties": {
    "tgn:hierarchy":[
        "tgn:4005978",
        "tgn:1003474",
        "tgn:7004610",
        "tgn:1000003",
        "tgn:1000080",
        "tgn:7029392"
    ],
    "tgn:id":4005978,
    "tgn:name":"La Mart\u00e9lla",
    "tgn:placetype":[
        "aat:300008347"
    ]
},
  "bbox": [],
  "geometry": {"coordinates":[16.55,40.666667],"type":"Point"}
}