{
  "id": 7373480,
  "type": "Feature",
  "properties": {
    "tgn:hierarchy":[
        "tgn:7373480",
        "tgn:1000001",
        "tgn:1001893",
        "tgn:7005560",
        "tgn:7029392"
    ],
    "tgn:id":7373480,
    "tgn:name":"La Gavia",
    "tgn:placetype":[
        "aat:300008347"
    ]
},
  "bbox": [],
  "geometry": {"coordinates":[-99.899167,19.390833],"type":"Point"}
}