{
  "id": 2668676,
  "type": "Feature",
  "properties": {
    "tgn:hierarchy":[
        "tgn:2668676",
        "tgn:1000001",
        "tgn:1002273",
        "tgn:7012149",
        "tgn:7007252",
        "tgn:7029392"
    ],
    "tgn:id":2668676,
    "tgn:name":"Slatecut",
    "tgn:placetype":[
        "aat:300008347"
    ]
},
  "bbox": [],
  "geometry": {"coordinates":[-85.75,38.4333],"type":"Point"}
}