{
  "id": 7551103,
  "type": "Feature",
  "properties": {
    "tgn:hierarchy":[
        "tgn:7551103",
        "tgn:1000004",
        "tgn:1001869",
        "tgn:7000198",
        "tgn:7029392"
    ],
    "tgn:id":7551103,
    "tgn:name:en":"Dihor",
    "tgn:placetype":[
        "aat:300008347"
    ]
},
  "bbox": [],
  "geometry": {"coordinates":[72.033333,21.483333],"type":"Point"}
}