{
  "id": 7145609,
  "type": "Feature",
  "properties": {
    "tgn:hierarchy":[
        "tgn:7145609",
        "tgn:7003669",
        "tgn:1000003",
        "tgn:7000084",
        "tgn:7029392"
    ],
    "tgn:id":7145609,
    "tgn:name":"Klein Wachenroth",
    "tgn:placetype":[
        "aat:300000206"
    ]
},
  "bbox": [],
  "geometry": {"coordinates":[10.716667,49.75],"type":"Point"}
}