{
  "id": 7511729,
  "type": "Feature",
  "properties": {
    "tgn:hierarchy":[
        "tgn:7511729",
        "tgn:1008380",
        "tgn:1000226",
        "tgn:7018426",
        "tgn:1000006",
        "tgn:7029392"
    ],
    "tgn:id":7511729,
    "tgn:name:en":"Katikati Entrance",
    "tgn:placetype":[
        "aat:300008713"
    ]
},
  "bbox": [],
  "geometry": {"coordinates":[175.983333,-37.483333],"type":"Point"}
}