{
  "id": 7502423,
  "type": "Feature",
  "properties": {
    "tgn:hierarchy":[
        "tgn:7502423",
        "tgn:7001010",
        "tgn:1000004",
        "tgn:1000141",
        "tgn:7029392"
    ],
    "tgn:id":7502423,
    "tgn:name":"Yongfeng Qiao",
    "tgn:placetype":[
        "aat:300007836"
    ]
},
  "bbox": [],
  "geometry": {"coordinates":[121.529722,23.626389],"type":"Point"}
}