<<<<<<< HEAD
{
  "id": 7370379,
  "type": "Feature",
  "properties": {
    "tgn:hierarchy":[
        "tgn:7370379",
        "tgn:7005587",
        "tgn:1000001",
        "tgn:7005560",
        "tgn:7029392"
    ],
    "tgn:id":7370379,
    "tgn:name":"Hueyapa",
    "tgn:placetype":[
        "aat:300008347"
    ]
},
  "bbox": [],
  "geometry": {"coordinates":[-98.683333,21.1],"type":"Point"}
}
=======
{"geometry":{"type":"Point","coordinates":[-98.683333,21.100000]},"type":"Feature","properties":{"hierarchy":["tgn:7370379","tgn:7005587","tgn:1000001","tgn:7005560","tgn:7029392"],"placetype":["aat:300008347"],"id":7370379,"name:xx":"Hueyapa"}}
>>>>>>> 03f74aca74312dbeaf24d7e61306dd6a786dc3d0
