{
  "id": 7240833,
  "type": "Feature",
  "properties": {
    "tgn:hierarchy":[
        "tgn:7240833",
        "tgn:7003465",
        "tgn:1000003",
        "tgn:1000063",
        "tgn:4012014",
        "tgn:7029392"
    ],
    "tgn:id":7240833,
    "tgn:name":"Fonsan, \u00c9tang de",
    "tgn:placetype":[
        "aat:300008688"
    ]
},
  "bbox": [],
  "geometry": {"coordinates":[5.566667,49.883333],"type":"Point"}
}