{
  "id": 2371645,
  "type": "Feature",
  "properties": {
    "tgn:hierarchy":[
        "tgn:2371645",
        "tgn:1000001",
        "tgn:7012149",
        "tgn:2000930",
        "tgn:7007515",
        "tgn:7029392"
    ],
    "tgn:id":2371645,
    "tgn:name":"Hale Brook",
    "tgn:placetype":[
        "aat:300008699"
    ]
},
  "bbox": [],
  "geometry": {"coordinates":[-70.1833,45.8167],"type":"Point"}
}