{
  "id": 7124604,
  "type": "Feature",
  "properties": {
    "tgn:hierarchy":[
        "tgn:7124604",
        "tgn:7003692",
        "tgn:1000003",
        "tgn:7000084",
        "tgn:7029392"
    ],
    "tgn:id":7124604,
    "tgn:name":"Neunkirchen",
    "tgn:placetype":[
        "aat:300008347"
    ]
},
  "bbox": [],
  "geometry": {"coordinates":[9.625278,49.1175],"type":"Point"}
}