{
  "id": 2282699,
  "type": "Feature",
  "properties": {
    "tgn:hierarchy":[
        "tgn:2282699",
        "tgn:1000001",
        "tgn:7012149",
        "tgn:1002567",
        "tgn:7007240",
        "tgn:7029392"
    ],
    "tgn:id":2282699,
    "tgn:name":"Deerhaven Lake",
    "tgn:placetype":[
        "aat:300008680"
    ]
},
  "bbox": [],
  "geometry": {"coordinates":[-81.4667,29.0333],"type":"Point"}
}