{
  "id": 2682423,
  "type": "Feature",
  "properties": {
    "tgn:hierarchy":[
        "tgn:2682423",
        "tgn:1000001",
        "tgn:2001415",
        "tgn:7012149",
        "tgn:7007526",
        "tgn:7029392"
    ],
    "tgn:id":2682423,
    "tgn:name":"Southall and O'Kane Mine",
    "tgn:placetype":[
        "aat:300000390"
    ]
},
  "bbox": [],
  "geometry": {"coordinates":[-117.05,39.5333],"type":"Point"}
}