{
  "id": 1078475,
  "type": "Feature",
  "properties": {
    "tgn:hierarchy":[
        "tgn:1078475",
        "tgn:1001137",
        "tgn:1008579",
        "tgn:1000004",
        "tgn:1000116",
        "tgn:7029392"
    ],
    "tgn:id":1078475,
    "tgn:name":"Sampalan",
    "tgn:placetype":[
        "aat:300008347"
    ]
},
  "bbox": [],
  "geometry": {"coordinates":[115.5667,-8.6833],"type":"Point"}
}