{
  "id": 2207230,
  "type": "Feature",
  "properties": {
    "tgn:hierarchy":[
        "tgn:2207230",
        "tgn:1000001",
        "tgn:7012149",
        "tgn:2000545",
        "tgn:7007252",
        "tgn:7029392"
    ],
    "tgn:id":2207230,
    "tgn:name":"Bunker Hill",
    "tgn:placetype":[
        "aat:300008798"
    ]
},
  "bbox": [],
  "geometry": {"coordinates":[-87.5333,38.65],"type":"Point"}
}