<<<<<<< HEAD
{
  "id": 7378838,
  "type": "Feature",
  "properties": {
    "tgn:hierarchy":[
        "tgn:7378838",
        "tgn:7005581",
        "tgn:1000001",
        "tgn:7005560",
        "tgn:7029392"
    ],
    "tgn:id":7378838,
    "tgn:name":"Manzana",
    "tgn:placetype":[
        "aat:300008347"
    ]
},
  "bbox": [],
  "geometry": {"coordinates":[-107.983333,27.2],"type":"Point"}
}
=======
{"geometry":{"type":"Point","coordinates":[-107.983333,27.200000]},"type":"Feature","properties":{"hierarchy":["tgn:7378838","tgn:7005581","tgn:1000001","tgn:7005560","tgn:7029392"],"placetype":["aat:300008347"],"id":7378838,"name:xx":"Manzana"}}
>>>>>>> 03f74aca74312dbeaf24d7e61306dd6a786dc3d0
