{
  "id": 2105380,
  "type": "Feature",
  "properties": {
    "tgn:hierarchy":[
        "tgn:2105380",
        "tgn:1000001",
        "tgn:7012149",
        "tgn:1002456",
        "tgn:7007826",
        "tgn:7029392"
    ],
    "tgn:id":2105380,
    "tgn:name":"Klein",
    "tgn:placetype":[
        "aat:300008347"
    ]
},
  "bbox": [],
  "geometry": {"coordinates":[-95.5167,30.0333],"type":"Point"}
}