{
  "id": 7060785,
  "type": "Feature",
  "properties": {
    "tgn:hierarchy":[
        "tgn:7060785",
        "tgn:7003669",
        "tgn:1000003",
        "tgn:7000084",
        "tgn:7029392"
    ],
    "tgn:id":7060785,
    "tgn:name":"Angern",
    "tgn:placetype":[
        "aat:300008347"
    ]
},
  "bbox": [],
  "geometry": {"coordinates":[11.733333,49.05],"type":"Point"}
}