{
  "id": 7265863,
  "type": "Feature",
  "properties": {
    "tgn:concordances":{
        "gn:id":"2753340"
    },
    "tgn:hierarchy":[
        "tgn:7265863",
        "tgn:7003619",
        "tgn:1000003",
        "tgn:7016845",
        "tgn:7029392"
    ],
    "tgn:id":7265863,
    "tgn:name:nl":"IJzerlo",
    "tgn:placetype":[
        "aat:300008347"
    ]
},
  "bbox": [],
  "geometry": {"coordinates":[6.533333,51.883333],"type":"Point"}
}