{
  "id": 2124224,
  "type": "Feature",
  "properties": {
    "tgn:hierarchy":[
        "tgn:2124224",
        "tgn:1000001",
        "tgn:7012149",
        "tgn:2001497",
        "tgn:7007709",
        "tgn:7029392"
    ],
    "tgn:id":2124224,
    "tgn:name":"373 Land Tract",
    "tgn:placetype":[
        "aat:300055621"
    ]
},
  "bbox": [],
  "geometry": {"coordinates":[-83.8667,35.3167],"type":"Point"}
}