{
  "id": 2786192,
  "type": "Feature",
  "properties": {
    "tgn:hierarchy":[
        "tgn:2786192",
        "tgn:7006450",
        "tgn:1000001",
        "tgn:7012149",
        "tgn:2000085",
        "tgn:7029392"
    ],
    "tgn:id":2786192,
    "tgn:name":"Younger Creek",
    "tgn:placetype":[
        "aat:300008706"
    ]
},
  "bbox": [],
  "geometry": {"coordinates":[-141.0333,64.05],"type":"Point"}
}