{
  "id": 1125819,
  "type": "Feature",
  "properties": {
    "tgn:hierarchy":[
        "tgn:1125819",
        "tgn:7001242",
        "tgn:7029392"
    ],
    "tgn:id":1125819,
    "tgn:name":"Kuruman",
    "tgn:placetype":[
        "aat:300008707"
    ]
},
  "bbox": [],
  "geometry": {"coordinates":[21.65,-26.9333],"type":"Point"}
}