{
  "id": 2231709,
  "type": "Feature",
  "properties": {
    "tgn:hierarchy":[
        "tgn:2231709",
        "tgn:1000001",
        "tgn:7012149",
        "tgn:2002252",
        "tgn:7007920",
        "tgn:7029392"
    ],
    "tgn:id":2231709,
    "tgn:name":"Chamber",
    "tgn:placetype":[
        "aat:300008347"
    ]
},
  "bbox": [],
  "geometry": {"coordinates":[-117.1833,46.6333],"type":"Point"}
}