{
  "id": 2569366,
  "type": "Feature",
  "properties": {
    "tgn:hierarchy":[
        "tgn:2569366",
        "tgn:7002659",
        "tgn:1000001",
        "tgn:7012149",
        "tgn:2000048",
        "tgn:7029392"
    ],
    "tgn:id":2569366,
    "tgn:name":"Parkwood",
    "tgn:placetype":[
        "aat:300008347"
    ]
},
  "bbox": [],
  "geometry": {"coordinates":[-88.15,30.75],"type":"Point"}
}