{
  "id": 1055686,
  "type": "Feature",
  "properties": {
    "tgn:hierarchy":[
        "tgn:1055686",
        "tgn:7011650",
        "tgn:1000003",
        "tgn:7006660",
        "tgn:7029392"
    ],
    "tgn:id":1055686,
    "tgn:name":"Kosiv",
    "tgn:placetype":[
        "aat:300008347"
    ]
},
  "bbox": [],
  "geometry": {"coordinates":[25.0833,48.3167],"type":"Point"}
}