{
  "id": 2374568,
  "type": "Feature",
  "properties": {
    "tgn:hierarchy":[
        "tgn:2374568",
        "tgn:1000001",
        "tgn:7012149",
        "tgn:7007157",
        "tgn:2000189",
        "tgn:7029392"
    ],
    "tgn:id":2374568,
    "tgn:name":"Hancock Creek",
    "tgn:placetype":[
        "aat:300008706"
    ]
},
  "bbox": [],
  "geometry": {"coordinates":[-123.2167,41.4167],"type":"Point"}
}