{
  "id": 7246965,
  "type": "Feature",
  "properties": {
    "tgn:hierarchy":[
        "tgn:7246965",
        "tgn:7007877",
        "tgn:1000003",
        "tgn:1000063",
        "tgn:4012014",
        "tgn:7029392"
    ],
    "tgn:id":7246965,
    "tgn:name":"Bouleng",
    "tgn:placetype":[
        "aat:300008347"
    ]
},
  "bbox": [],
  "geometry": {"coordinates":[4.185849,50.53604],"type":"Point"}
}