{
  "id": 7295342,
  "type": "Feature",
  "properties": {
    "tgn:hierarchy":[
        "tgn:7295342",
        "tgn:7002808",
        "tgn:7030216",
        "tgn:1000003",
        "tgn:1000095",
        "tgn:7029392"
    ],
    "tgn:id":7295342,
    "tgn:name":"Mongat, Playa",
    "tgn:placetype":[
        "aat:300008816"
    ]
},
  "bbox": [],
  "geometry": {"coordinates":[2.283333,41.475],"type":"Point"}
}