{
  "id": 2356302,
  "type": "Feature",
  "properties": {
    "tgn:hierarchy":[
        "tgn:2356302",
        "tgn:1000001",
        "tgn:7012149",
        "tgn:2002125",
        "tgn:7007827",
        "tgn:7029392"
    ],
    "tgn:id":2356302,
    "tgn:name":"Goosenest Canyon",
    "tgn:placetype":[
        "aat:300008761"
    ]
},
  "bbox": [],
  "geometry": {"coordinates":[-111.9333,39.85],"type":"Point"}
}