{
  "id": 7068586,
  "type": "Feature",
  "properties": {
    "tgn:hierarchy":[
        "tgn:7068586",
        "tgn:1000003",
        "tgn:7000094",
        "tgn:7000084",
        "tgn:7029392"
    ],
    "tgn:id":7068586,
    "tgn:name":"Klein Stallberg",
    "tgn:placetype":[
        "aat:300008347"
    ]
},
  "bbox": [],
  "geometry": {"coordinates":[14.05,53.583333],"type":"Point"}
}