{
  "id": 7112322,
  "type": "Feature",
  "properties": {
    "tgn:hierarchy":[
        "tgn:7112322",
        "tgn:7003669",
        "tgn:1000003",
        "tgn:7000084",
        "tgn:7029392"
    ],
    "tgn:id":7112322,
    "tgn:name":"Ringdobl",
    "tgn:placetype":[
        "aat:300000206"
    ]
},
  "bbox": [],
  "geometry": {"coordinates":[13.083333,48.516667],"type":"Point"}
}