{
  "id": 7434353,
  "type": "Feature",
  "properties": {
    "tgn:hierarchy":[
        "tgn:7434353",
        "tgn:7005580",
        "tgn:1000001",
        "tgn:7005560",
        "tgn:7029392"
    ],
    "tgn:id":7434353,
    "tgn:name":"Tres Naciones",
    "tgn:placetype":[
        "aat:300387007"
    ]
},
  "bbox": [],
  "geometry": {"coordinates":[-90.683333,16.583333],"type":"Point"}
}