{
  "id": 2689196,
  "type": "Feature",
  "properties": {
    "tgn:hierarchy":[
        "tgn:2689196",
        "tgn:1000001",
        "tgn:7012149",
        "tgn:2001721",
        "tgn:7007708",
        "tgn:7029392"
    ],
    "tgn:id":2689196,
    "tgn:name":"Squaw Butte",
    "tgn:placetype":[
        "aat:300008798"
    ]
},
  "bbox": [],
  "geometry": {"coordinates":[-117.5667,45.1667],"type":"Point"}
}