<<<<<<< HEAD
{
  "id": 7178950,
  "type": "Feature",
  "properties": {
    "tgn:hierarchy":[
        "tgn:7178950",
        "tgn:7003669",
        "tgn:1000003",
        "tgn:7000084",
        "tgn:7029392"
    ],
    "tgn:id":7178950,
    "tgn:name":"Haidenburg",
    "tgn:placetype":[
        "aat:300008347"
    ]
},
  "bbox": [],
  "geometry": {"coordinates":[13.033333,48.566667],"type":"Point"}
}
=======
{"geometry":{"type":"Point","coordinates":[13.033333,48.566667]},"type":"Feature","properties":{"hierarchy":["tgn:7178950","tgn:7003669","tgn:1000003","tgn:7000084","tgn:7029392"],"placetype":["aat:300008347"],"id":7178950,"name:xx":"Haidenburg"}}
>>>>>>> 03f74aca74312dbeaf24d7e61306dd6a786dc3d0
