{
  "id": 7034174,
  "type": "Feature",
  "properties": {
    "tgn:hierarchy":[
        "tgn:7034174",
        "tgn:1003468",
        "tgn:1000003",
        "tgn:7010380",
        "tgn:1000080",
        "tgn:7029392"
    ],
    "tgn:id":7034174,
    "tgn:name":"Masseria Puzzella",
    "tgn:placetype":[
        "aat:300000206"
    ]
},
  "bbox": [],
  "geometry": {"coordinates":[18.175278,40.454722],"type":"Point"}
}