{
  "id": 2734860,
  "type": "Feature",
  "properties": {
    "tgn:hierarchy":[
        "tgn:2734860",
        "tgn:1000001",
        "tgn:7019982",
        "tgn:7012149",
        "tgn:7007517",
        "tgn:7029392"
    ],
    "tgn:id":2734860,
    "tgn:name":"Twelvemile Brook",
    "tgn:placetype":[
        "aat:300008699"
    ]
},
  "bbox": [],
  "geometry": {"coordinates":[-72.35,42.0833],"type":"Point"}
}