<<<<<<< HEAD
{
  "id": 7174426,
  "type": "Feature",
  "properties": {
    "tgn:hierarchy":[
        "tgn:7174426",
        "tgn:7003669",
        "tgn:1000003",
        "tgn:7000084",
        "tgn:7029392"
    ],
    "tgn:id":7174426,
    "tgn:name":"Gr\u00f6lzing",
    "tgn:placetype":[
        "aat:300000206"
    ]
},
  "bbox": [],
  "geometry": {"coordinates":[12.533333,48.4],"type":"Point"}
}
=======
{"geometry":{"type":"Point","coordinates":[12.533333,48.400000]},"type":"Feature","properties":{"hierarchy":["tgn:7174426","tgn:7003669","tgn:1000003","tgn:7000084","tgn:7029392"],"placetype":["aat:300000206"],"id":7174426,"name:xx":"Gr\u00f6lzing"}}
>>>>>>> 03f74aca74312dbeaf24d7e61306dd6a786dc3d0
