{
  "id": 2347749,
  "type": "Feature",
  "properties": {
    "tgn:hierarchy":[
        "tgn:2347749",
        "tgn:1002171",
        "tgn:1000001",
        "tgn:7012149",
        "tgn:7007710",
        "tgn:7029392"
    ],
    "tgn:id":2347749,
    "tgn:name":"Georgetown Island",
    "tgn:placetype":[
        "aat:300008791"
    ]
},
  "bbox": [],
  "geometry": {"coordinates":[-80.4667,40.6333],"type":"Point"}
}