{
  "id": 7054297,
  "type": "Feature",
  "properties": {
    "tgn:hierarchy":[
        "tgn:7054297",
        "tgn:1001730",
        "tgn:1000003",
        "tgn:7003121",
        "tgn:1000080",
        "tgn:7029392"
    ],
    "tgn:id":7054297,
    "tgn:name":"Ponte Merchis, Riu",
    "tgn:placetype":[
        "aat:300008699"
    ]
},
  "bbox": [],
  "geometry": {"coordinates":[8.816667,40.15],"type":"Point"}
}