{
  "id": 2708211,
  "type": "Feature",
  "properties": {
    "tgn:hierarchy":[
        "tgn:2708211",
        "tgn:1000001",
        "tgn:2000469",
        "tgn:7012149",
        "tgn:7007250",
        "tgn:7029392"
    ],
    "tgn:id":2708211,
    "tgn:name":"Switchback Hill",
    "tgn:placetype":[
        "aat:300008798"
    ]
},
  "bbox": [],
  "geometry": {"coordinates":[-115.1667,46.6333],"type":"Point"}
}