{
  "id": 2322260,
  "type": "Feature",
  "properties": {
    "tgn:hierarchy":[
        "tgn:2322260",
        "tgn:1000001",
        "tgn:7012149",
        "tgn:7029392"
    ],
    "tgn:id":2322260,
    "tgn:name":"Fallbush Mountain",
    "tgn:placetype":[
        "aat:300008798"
    ]
},
  "bbox": [],
  "geometry": {"coordinates":[-78.95,38.8167],"type":"Point"}
}