{
  "id": 7287705,
  "type": "Feature",
  "properties": {
    "tgn:hierarchy":[
        "tgn:7287705",
        "tgn:1001699",
        "tgn:1000049",
        "tgn:1000002",
        "tgn:7029392"
    ],
    "tgn:id":7287705,
    "tgn:name":"Imulfudi",
    "tgn:placetype":[
        "aat:300000206"
    ]
},
  "bbox": [],
  "geometry": {"coordinates":[-72.85,-39.466667],"type":"Point"}
}