{
  "id": 2392250,
  "type": "Feature",
  "properties": {
    "tgn:hierarchy":[
        "tgn:2392250",
        "tgn:1000001",
        "tgn:7012149",
        "tgn:2002353",
        "tgn:7007922",
        "tgn:7029392"
    ],
    "tgn:id":2392250,
    "tgn:name":"Hinton Bay",
    "tgn:placetype":[
        "aat:300132316"
    ]
},
  "bbox": [],
  "geometry": {"coordinates":[-91.3167,46.0167],"type":"Point"}
}