{
  "id": 2487035,
  "type": "Feature",
  "properties": {
    "tgn:hierarchy":[
        "tgn:2487035",
        "tgn:1000001",
        "tgn:7012149",
        "tgn:2001277",
        "tgn:7007524",
        "tgn:7029392"
    ],
    "tgn:id":2487035,
    "tgn:name":"Lee Ridge",
    "tgn:placetype":[
        "aat:300266640"
    ]
},
  "bbox": [],
  "geometry": {"coordinates":[-113.65,48.9333],"type":"Point"}
}