{
  "id": 7322711,
  "type": "Feature",
  "properties": {
    "tgn:hierarchy":[
        "tgn:7322711",
        "tgn:7002847",
        "tgn:1001647",
        "tgn:1000003",
        "tgn:1000095",
        "tgn:7029392"
    ],
    "tgn:id":7322711,
    "tgn:name":"Salmoroso, Vado de",
    "tgn:placetype":[
        "aat:300387042"
    ]
},
  "bbox": [],
  "geometry": {"coordinates":[-4.533333,40.066667],"type":"Point"}
}