{
  "id": 7551270,
  "type": "Feature",
  "properties": {
    "tgn:hierarchy":[
        "tgn:7551270",
        "tgn:1000004",
        "tgn:1001869",
        "tgn:7000198",
        "tgn:7029392"
    ],
    "tgn:id":7551270,
    "tgn:name:en":"Daru Creek",
    "tgn:placetype":[
        "aat:300266571"
    ]
},
  "bbox": [],
  "geometry": {"coordinates":[71.083333,20.75],"type":"Point"}
}