{
  "id": 7469941,
  "type": "Feature",
  "properties": {
    "tgn:hierarchy":[
        "tgn:7469941",
        "tgn:7001010",
        "tgn:1000004",
        "tgn:1000141",
        "tgn:7029392"
    ],
    "tgn:id":7469941,
    "tgn:name":"Qingchang Shan",
    "tgn:placetype":[
        "aat:300008798"
    ]
},
  "bbox": [],
  "geometry": {"coordinates":[121.381101,23.875139],"type":"Point"}
}