{
  "id": 2175565,
  "type": "Feature",
  "properties": {
    "tgn:hierarchy":[
        "tgn:2175565",
        "tgn:1000001",
        "tgn:7012149",
        "tgn:7007158",
        "tgn:2000246",
        "tgn:7029392"
    ],
    "tgn:id":2175565,
    "tgn:name":"Black Cat Mine",
    "tgn:placetype":[
        "aat:300000390"
    ]
},
  "bbox": [],
  "geometry": {"coordinates":[-106.7667,38.3833],"type":"Point"}
}