{
  "id": 7553414,
  "type": "Feature",
  "properties": {
    "tgn:hierarchy":[
        "tgn:7553414",
        "tgn:1000004",
        "tgn:7000198",
        "tgn:1001895",
        "tgn:7029392"
    ],
    "tgn:id":7553414,
    "tgn:name:en":"Marsul",
    "tgn:placetype":[
        "aat:300007783"
    ]
},
  "bbox": [],
  "geometry": {"coordinates":[77.116667,19.233333],"type":"Point"}
}