{
  "id": 7307952,
  "type": "Feature",
  "properties": {
    "tgn:hierarchy":[
        "tgn:7307952",
        "tgn:1001630",
        "tgn:1000049",
        "tgn:1000002",
        "tgn:7029392"
    ],
    "tgn:id":7307952,
    "tgn:name":"Monardes, Quebrada",
    "tgn:placetype":[
        "aat:300266554",
        "aat:300008699"
    ]
},
  "bbox": [],
  "geometry": {"coordinates":[-69.416667,-27.45],"type":"Point"}
}