{
  "id": 7049941,
  "type": "Feature",
  "properties": {
    "tgn:hierarchy":[
        "tgn:7049941",
        "tgn:7003170",
        "tgn:1000003",
        "tgn:7003125",
        "tgn:1000080",
        "tgn:7029392"
    ],
    "tgn:id":7049941,
    "tgn:name":"Gallo",
    "tgn:placetype":[
        "aat:300008347"
    ]
},
  "bbox": [],
  "geometry": {"coordinates":[12.666667,42.866667],"type":"Point"}
}