{
  "id": 2476149,
  "type": "Feature",
  "properties": {
    "tgn:hierarchy":[
        "tgn:2476149",
        "tgn:1000001",
        "tgn:7012149",
        "tgn:2002382",
        "tgn:7007923",
        "tgn:7029392"
    ],
    "tgn:id":2476149,
    "tgn:name":"Luman Reservoir Number 2",
    "tgn:placetype":[
        "aat:300006191"
    ]
},
  "bbox": [],
  "geometry": {"coordinates":[-109.7833,42.4667],"type":"Point"}
}