{
  "id": 2738138,
  "type": "Feature",
  "properties": {
    "tgn:hierarchy":[
        "tgn:2738138",
        "tgn:1000001",
        "tgn:7012149",
        "tgn:1002376",
        "tgn:7007252",
        "tgn:7029392"
    ],
    "tgn:id":2738138,
    "tgn:name":"Ulmer Ridge",
    "tgn:placetype":[
        "aat:300266640"
    ]
},
  "bbox": [],
  "geometry": {"coordinates":[-85.9167,38.25],"type":"Point"}
}