{
  "id": 7409593,
  "type": "Feature",
  "properties": {
    "tgn:hierarchy":[
        "tgn:7409593",
        "tgn:1000001",
        "tgn:7005592",
        "tgn:7005560",
        "tgn:7029392"
    ],
    "tgn:id":7409593,
    "tgn:name":"San Juan Acozac",
    "tgn:placetype":[
        "aat:300008347"
    ]
},
  "bbox": [],
  "geometry": {"coordinates":[-97.656944,18.966667],"type":"Point"}
}