{
  "id": 2718222,
  "type": "Feature",
  "properties": {
    "tgn:hierarchy":[
        "tgn:2718222",
        "tgn:1000001",
        "tgn:1002276",
        "tgn:7012149",
        "tgn:7007708",
        "tgn:7029392"
    ],
    "tgn:id":2718222,
    "tgn:name":"Thompson Creek",
    "tgn:placetype":[
        "aat:300008706"
    ]
},
  "bbox": [],
  "geometry": {"coordinates":[-123.8667,45.9833],"type":"Point"}
}