{
  "id": 2060848,
  "type": "Feature",
  "properties": {
    "tgn:hierarchy":[
        "tgn:2060848",
        "tgn:2001170",
        "tgn:1000001",
        "tgn:7012149",
        "tgn:7007523",
        "tgn:7029392"
    ],
    "tgn:id":2060848,
    "tgn:name":"Wayne",
    "tgn:placetype":[
        "aat:300008347"
    ]
},
  "bbox": [],
  "geometry": {"coordinates":[-93.95,36.6333],"type":"Point"}
}