{
  "id": 7345747,
  "type": "Feature",
  "properties": {
    "tgn:hierarchy":[
        "tgn:7345747",
        "tgn:7002824",
        "tgn:1000003",
        "tgn:7002786",
        "tgn:1000095",
        "tgn:7029392"
    ],
    "tgn:id":7345747,
    "tgn:name":"Benza",
    "tgn:placetype":[
        "aat:300008347"
    ]
},
  "bbox": [],
  "geometry": {"coordinates":[-8.583333,43.016667],"type":"Point"}
}