{
  "id": 2121093,
  "type": "Feature",
  "properties": {
    "tgn:hierarchy":[
        "tgn:2121093",
        "tgn:1000001",
        "tgn:2002313",
        "tgn:7012149",
        "tgn:7007922",
        "tgn:7029392"
    ],
    "tgn:id":2121093,
    "tgn:name":"Eagle Point",
    "tgn:placetype":[
        "aat:300387016"
    ]
},
  "bbox": [],
  "geometry": {"coordinates":[-91.3833,45.0167],"type":"Point"}
}