{
  "id": 2359205,
  "type": "Feature",
  "properties": {
    "tgn:hierarchy":[
        "tgn:2359205",
        "tgn:1000001",
        "tgn:2001419",
        "tgn:7012149",
        "tgn:7007526",
        "tgn:7029392"
    ],
    "tgn:id":2359205,
    "tgn:name":"Granite Spring",
    "tgn:placetype":[
        "aat:300008697"
    ]
},
  "bbox": [],
  "geometry": {"coordinates":[-119.05,40.0667],"type":"Point"}
}