{
  "id": 1131721,
  "type": "Feature",
  "properties": {
    "tgn:hierarchy":[
        "tgn:1131721",
        "tgn:7005685",
        "tgn:1000001",
        "tgn:7005802",
        "tgn:7029392"
    ],
    "tgn:id":1131721,
    "tgn:name":"West Saint Marys",
    "tgn:placetype":[
        "aat:300008707"
    ]
},
  "bbox": [],
  "geometry": {"coordinates":[-62.0667,45.25],"type":"Point"}
}