{
  "id": 2363618,
  "type": "Feature",
  "properties": {
    "tgn:hierarchy":[
        "tgn:2363618",
        "tgn:1000001",
        "tgn:2002106",
        "tgn:7012149",
        "tgn:7007827",
        "tgn:7029392"
    ],
    "tgn:id":2363618,
    "tgn:name":"Green Hill Acres",
    "tgn:placetype":[
        "aat:300008347"
    ]
},
  "bbox": [],
  "geometry": {"coordinates":[-112.0333,41.1167],"type":"Point"}
}