{
  "id": 2488804,
  "type": "Feature",
  "properties": {
    "tgn:hierarchy":[
        "tgn:2488804",
        "tgn:7006450",
        "tgn:1000001",
        "tgn:7012149",
        "tgn:2000086",
        "tgn:7029392"
    ],
    "tgn:id":2488804,
    "tgn:name":"Main Bay",
    "tgn:placetype":[
        "aat:300132316"
    ]
},
  "bbox": [],
  "geometry": {"coordinates":[-148.05,60.5333],"type":"Point"}
}