{
  "id": 2500681,
  "type": "Feature",
  "properties": {
    "tgn:hierarchy":[
        "tgn:2500681",
        "tgn:1000001",
        "tgn:7012149",
        "tgn:7007712",
        "tgn:7029392"
    ],
    "tgn:id":2500681,
    "tgn:name":"McDow Creek",
    "tgn:placetype":[
        "aat:300008706"
    ]
},
  "bbox": [],
  "geometry": {"coordinates":[-80.7833,34.5167],"type":"Point"}
}