{
  "id": 2191453,
  "type": "Feature",
  "properties": {
    "tgn:hierarchy":[
        "tgn:2191453",
        "tgn:1000001",
        "tgn:7012149",
        "tgn:2000283",
        "tgn:7007240",
        "tgn:7029392"
    ],
    "tgn:id":2191453,
    "tgn:name":"Braddocks Point",
    "tgn:placetype":[
        "aat:300008850"
    ]
},
  "bbox": [],
  "geometry": {"coordinates":[-81.2667,29.75],"type":"Point"}
}