{
  "id": 2032873,
  "type": "Feature",
  "properties": {
    "tgn:hierarchy":[
        "tgn:2032873",
        "tgn:1000001",
        "tgn:7012149",
        "tgn:1002416",
        "tgn:7007252",
        "tgn:7029392"
    ],
    "tgn:id":2032873,
    "tgn:name":"Mier",
    "tgn:placetype":[
        "aat:300008347"
    ]
},
  "bbox": [],
  "geometry": {"coordinates":[-85.8167,40.5667],"type":"Point"}
}