{
  "id": 2367552,
  "type": "Feature",
  "properties": {
    "tgn:hierarchy":[
        "tgn:2367552",
        "tgn:1000001",
        "tgn:2002102",
        "tgn:7012149",
        "tgn:7007827",
        "tgn:7029392"
    ],
    "tgn:id":2367552,
    "tgn:name":"Grouse Creek Mountains",
    "tgn:placetype":[
        "aat:300386831"
    ]
},
  "bbox": [],
  "geometry": {"coordinates":[-113.75,41.65],"type":"Point"}
}