{
  "id": 2254019,
  "type": "Feature",
  "properties": {
    "tgn:hierarchy":[
        "tgn:2254019",
        "tgn:1000001",
        "tgn:2002147",
        "tgn:7012149",
        "tgn:7007919",
        "tgn:7029392"
    ],
    "tgn:id":2254019,
    "tgn:name":"Cool Spring",
    "tgn:placetype":[
        "aat:300008347"
    ]
},
  "bbox": [],
  "geometry": {"coordinates":[-77.8167,36.8333],"type":"Point"}
}