{
  "id": 2438652,
  "type": "Feature",
  "properties": {
    "tgn:hierarchy":[
        "tgn:2438652",
        "tgn:1000001",
        "tgn:2000870",
        "tgn:7012149",
        "tgn:7007256",
        "tgn:7029392"
    ],
    "tgn:id":2438652,
    "tgn:name":"Kingston Estates",
    "tgn:placetype":[
        "aat:300008347"
    ]
},
  "bbox": [],
  "geometry": {"coordinates":[-91.15,30.55],"type":"Point"}
}