{
  "id": 7413157,
  "type": "Feature",
  "properties": {
    "tgn:hierarchy":[
        "tgn:7413157",
        "tgn:7005587",
        "tgn:1000001",
        "tgn:7005560",
        "tgn:7029392"
    ],
    "tgn:id":7413157,
    "tgn:name:es":"Banganoh\u00f3",
    "tgn:placetype":[
        "aat:300008347"
    ]
},
  "bbox": [],
  "geometry": {"coordinates":[-99.148611,20.483333],"type":"Point"}
}