{
  "id": 7428720,
  "type": "Feature",
  "properties": {
    "tgn:hierarchy":[
        "tgn:7428720",
        "tgn:1000001",
        "tgn:7005601",
        "tgn:7005560",
        "tgn:7029392"
    ],
    "tgn:id":7428720,
    "tgn:name":"El Borroso, Sierra",
    "tgn:placetype":[
        "aat:300008795"
    ]
},
  "bbox": [],
  "geometry": {"coordinates":[-101.616667,24.266667],"type":"Point"}
}