{
  "id": 2692641,
  "type": "Feature",
  "properties": {
    "tgn:hierarchy":[
        "tgn:2692641",
        "tgn:1000001",
        "tgn:7012149",
        "tgn:1002529",
        "tgn:7007520",
        "tgn:7029392"
    ],
    "tgn:id":2692641,
    "tgn:name":"Stears Lake",
    "tgn:placetype":[
        "aat:300008680"
    ]
},
  "bbox": [],
  "geometry": {"coordinates":[-85.5167,42.3167],"type":"Point"}
}