{
  "id": 1090270,
  "type": "Feature",
  "properties": {
    "tgn:hierarchy":[
        "tgn:1090270",
        "tgn:7001242",
        "tgn:7000792",
        "tgn:1000167",
        "tgn:7029392"
    ],
    "tgn:id":1090270,
    "tgn:name":"Moribaya",
    "tgn:placetype":[
        "aat:300008347"
    ]
},
  "bbox": [],
  "geometry": {"coordinates":[9.55,9.8833],"type":"Point"}
}