{
  "id": 2402923,
  "type": "Feature",
  "properties": {
    "tgn:hierarchy":[
        "tgn:2402923",
        "tgn:1000001",
        "tgn:7006451",
        "tgn:2000092",
        "tgn:7012149",
        "tgn:7029392"
    ],
    "tgn:id":2402923,
    "tgn:name":"Houck Draw",
    "tgn:placetype":[
        "aat:300008761"
    ]
},
  "bbox": [],
  "geometry": {"coordinates":[-110.7667,34.4667],"type":"Point"}
}