{
  "id": 2518084,
  "type": "Feature",
  "properties": {
    "tgn:hierarchy":[
        "tgn:2518084",
        "tgn:1000001",
        "tgn:2001261",
        "tgn:7012149",
        "tgn:7007524",
        "tgn:7029392"
    ],
    "tgn:id":2518084,
    "tgn:name":"Mission Creek",
    "tgn:placetype":[
        "aat:300008706"
    ]
},
  "bbox": [],
  "geometry": {"coordinates":[-107.55,46.0167],"type":"Point"}
}