{
  "id": 7093651,
  "type": "Feature",
  "properties": {
    "tgn:hierarchy":[
        "tgn:7093651",
        "tgn:7003669",
        "tgn:1000003",
        "tgn:7000084",
        "tgn:7029392"
    ],
    "tgn:id":7093651,
    "tgn:name":"Schweibern",
    "tgn:placetype":[
        "aat:300000206"
    ]
},
  "bbox": [],
  "geometry": {"coordinates":[12.266667,47.683333],"type":"Point"}
}