<<<<<<< HEAD
{
  "id": 2768707,
  "type": "Feature",
  "properties": {
    "tgn:hierarchy":[
        "tgn:2768707",
        "tgn:1000001",
        "tgn:7012149",
        "tgn:7014589",
        "tgn:7007515",
        "tgn:7029392"
    ],
    "tgn:id":2768707,
    "tgn:name":"Whitlocks Mill",
    "tgn:placetype":[
        "aat:300008347"
    ]
},
  "bbox": [],
  "geometry": {"coordinates":[-67.2167,45.15],"type":"Point"}
}
=======
{"geometry":{"type":"Point","coordinates":[-67.216700,45.150000]},"type":"Feature","properties":{"hierarchy":["tgn:2768707","tgn:1000001","tgn:7012149","tgn:7014589","tgn:7007515","tgn:7029392"],"placetype":["aat:300008347"],"id":2768707,"name:xx":"Whitlocks Mill"}}
>>>>>>> 03f74aca74312dbeaf24d7e61306dd6a786dc3d0
