{
  "id": 7323859,
  "type": "Feature",
  "properties": {
    "tgn:hierarchy":[
        "tgn:7323859",
        "tgn:7002758",
        "tgn:7002823",
        "tgn:1000003",
        "tgn:1000095",
        "tgn:7029392"
    ],
    "tgn:id":7323859,
    "tgn:name":"Estaci\u00f3n de R\u00edotinto",
    "tgn:placetype":[
        "aat:300007783"
    ]
},
  "bbox": [],
  "geometry": {"coordinates":[-6.65,37.666667],"type":"Point"}
}