{
  "id": 2691261,
  "type": "Feature",
  "properties": {
    "tgn:hierarchy":[
        "tgn:2691261",
        "tgn:1000001",
        "tgn:7012149",
        "tgn:2000219",
        "tgn:7007158",
        "tgn:7029392"
    ],
    "tgn:id":2691261,
    "tgn:name":"Staplin Creek",
    "tgn:placetype":[
        "aat:300008706"
    ]
},
  "bbox": [],
  "geometry": {"coordinates":[-104.9833,37.3833],"type":"Point"}
}