{
  "id": 2274699,
  "type": "Feature",
  "properties": {
    "tgn:hierarchy":[
        "tgn:2274699",
        "tgn:1000001",
        "tgn:2002102",
        "tgn:7012149",
        "tgn:7007827",
        "tgn:7029392"
    ],
    "tgn:id":2274699,
    "tgn:name":"Dam Creek",
    "tgn:placetype":[
        "aat:300008706"
    ]
},
  "bbox": [],
  "geometry": {"coordinates":[-111.9333,41.5167],"type":"Point"}
}