{
  "id": 7587453,
  "type": "Feature",
  "properties": {
    "tgn:hierarchy":[
        "tgn:7587453",
        "tgn:1000004",
        "tgn:7000198",
        "tgn:7000799",
        "tgn:7029392"
    ],
    "tgn:id":7587453,
    "tgn:name:en":"Gil Sar",
    "tgn:placetype":[
        "aat:300008347"
    ]
},
  "bbox": [],
  "geometry": {"coordinates":[74.815278,34.126389],"type":"Point"}
}