<<<<<<< HEAD
{
  "id": 2408665,
  "type": "Feature",
  "properties": {
    "tgn:hierarchy":[
        "tgn:2408665",
        "tgn:1000001",
        "tgn:7012149",
        "tgn:2001447",
        "tgn:7007566",
        "tgn:7029392"
    ],
    "tgn:id":2408665,
    "tgn:name":"Hyatt Canyon",
    "tgn:placetype":[
        "aat:300008761"
    ]
},
  "bbox": [],
  "geometry": {"coordinates":[-105.65,32.9167],"type":"Point"}
}
=======
{"geometry":{"type":"Point","coordinates":[-105.650000,32.916700]},"type":"Feature","properties":{"hierarchy":["tgn:2408665","tgn:1000001","tgn:7012149","tgn:2001447","tgn:7007566","tgn:7029392"],"placetype":["aat:300008761"],"id":2408665,"name:xx":"Hyatt Canyon"}}
>>>>>>> 03f74aca74312dbeaf24d7e61306dd6a786dc3d0
