{
  "id": 7522133,
  "type": "Feature",
  "properties": {
    "tgn:hierarchy":[
        "tgn:7522133",
        "tgn:7001242",
        "tgn:7016833",
        "tgn:1001110",
        "tgn:7029392"
    ],
    "tgn:id":7522133,
    "tgn:name:en":"Abu R\u00eesha, W\u00e2di",
    "tgn:placetype":[
        "aat:300379998"
    ]
},
  "bbox": [],
  "geometry": {"coordinates":[31.933333,29.15],"type":"Point"}
}