{
  "id": 2458104,
  "type": "Feature",
  "properties": {
    "tgn:hierarchy":[
        "tgn:2458104",
        "tgn:1000001",
        "tgn:7012149",
        "tgn:7007158",
        "tgn:2000245",
        "tgn:7029392"
    ],
    "tgn:id":2458104,
    "tgn:name":"Little Mountain",
    "tgn:placetype":[
        "aat:300008798"
    ]
},
  "bbox": [],
  "geometry": {"coordinates":[-106.9333,40.8167],"type":"Point"}
}