{
  "id": 7586487,
  "type": "Feature",
  "properties": {
    "tgn:hierarchy":[
        "tgn:7586487",
        "tgn:1000004",
        "tgn:7000198",
        "tgn:7000799",
        "tgn:7029392"
    ],
    "tgn:id":7586487,
    "tgn:name:en":"Kh\u0101npur",
    "tgn:placetype":[
        "aat:300008347"
    ]
},
  "bbox": [],
  "geometry": {"coordinates":[74.269476,34.439858],"type":"Point"}
}