<<<<<<< HEAD
{
  "id": 7354065,
  "type": "Feature",
  "properties": {
    "tgn:hierarchy":[
        "tgn:7354065",
        "tgn:7005581",
        "tgn:1000001",
        "tgn:7005560",
        "tgn:7029392"
    ],
    "tgn:id":7354065,
    "tgn:name":"Campo 31",
    "tgn:placetype":[
        "aat:300008347"
    ]
},
  "bbox": [],
  "geometry": {"coordinates":[-106.833333,28.783333],"type":"Point"}
}
=======
{"geometry":{"type":"Point","coordinates":[-106.833333,28.783333]},"type":"Feature","properties":{"hierarchy":["tgn:7354065","tgn:7005581","tgn:1000001","tgn:7005560","tgn:7029392"],"placetype":["aat:300008347"],"id":7354065,"name:xx":"Campo 31"}}
>>>>>>> 03f74aca74312dbeaf24d7e61306dd6a786dc3d0
