{
  "id": 2559448,
  "type": "Feature",
  "properties": {
    "tgn:hierarchy":[
        "tgn:2559448",
        "tgn:1000001",
        "tgn:7012149",
        "tgn:7007157",
        "tgn:2000187",
        "tgn:7029392"
    ],
    "tgn:id":2559448,
    "tgn:name":"Onion Valley Reservoir",
    "tgn:placetype":[
        "aat:300006191"
    ]
},
  "bbox": [],
  "geometry": {"coordinates":[-120.8667,39.7833],"type":"Point"}
}