{
  "id": 2053590,
  "type": "Feature",
  "properties": {
    "tgn:hierarchy":[
        "tgn:2053590",
        "tgn:1000001",
        "tgn:7012149",
        "tgn:2000986",
        "tgn:7007520",
        "tgn:7029392"
    ],
    "tgn:id":2053590,
    "tgn:name":"Victoria",
    "tgn:placetype":[
        "aat:300008347"
    ]
},
  "bbox": [],
  "geometry": {"coordinates":[-89.2167,46.6833],"type":"Point"}
}