{
  "id": 2155445,
  "type": "Feature",
  "properties": {
    "tgn:hierarchy":[
        "tgn:2155445",
        "tgn:1000001",
        "tgn:7012149",
        "tgn:7007522",
        "tgn:7029392"
    ],
    "tgn:id":2155445,
    "tgn:name":"Bear Pond Branch",
    "tgn:placetype":[
        "aat:300008699"
    ]
},
  "bbox": [],
  "geometry": {"coordinates":[-88.6167,30.9833],"type":"Point"}
}