<<<<<<< HEAD
{
  "id": 2155445,
  "type": "Feature",
  "properties": {
    "tgn:hierarchy":[
        "tgn:2155445",
        "tgn:1000001",
        "tgn:7012149",
        "tgn:7007522",
        "tgn:7029392"
    ],
    "tgn:id":2155445,
    "tgn:name":"Bear Pond Branch",
    "tgn:placetype":[
        "aat:300008699"
    ]
},
  "bbox": [],
  "geometry": {"coordinates":[-88.6167,30.9833],"type":"Point"}
}
=======
{"geometry":{"type":"Point","coordinates":[-88.616700,30.983300]},"type":"Feature","properties":{"hierarchy":["tgn:2155445","tgn:1000001","tgn:7012149","tgn:7007522","tgn:7029392"],"placetype":["aat:300008699"],"id":2155445,"name:xx":"Bear Pond Branch"}}
>>>>>>> 03f74aca74312dbeaf24d7e61306dd6a786dc3d0
