{
  "id": 2055272,
  "type": "Feature",
  "properties": {
    "tgn:hierarchy":[
        "tgn:2055272",
        "tgn:1000001",
        "tgn:2001023",
        "tgn:7012149",
        "tgn:7007521",
        "tgn:7029392"
    ],
    "tgn:id":2055272,
    "tgn:name":"Prairie Island Indian Reservation",
    "tgn:placetype":[
        "aat:300008347",
        "aat:300387324"
    ]
},
  "bbox": [],
  "geometry": {"coordinates":[-92.65,44.6333],"type":"Point"}
}