{
  "id": 2385856,
  "type": "Feature",
  "properties": {
    "tgn:hierarchy":[
        "tgn:2385856",
        "tgn:1000001",
        "tgn:7012149",
        "tgn:1002424",
        "tgn:7007706",
        "tgn:7029392"
    ],
    "tgn:id":2385856,
    "tgn:name":"Hennessee",
    "tgn:placetype":[
        "aat:300008347"
    ]
},
  "bbox": [],
  "geometry": {"coordinates":[-83.9833,39.8333],"type":"Point"}
}