{
  "id": 7141435,
  "type": "Feature",
  "properties": {
    "tgn:hierarchy":[
        "tgn:7141435",
        "tgn:7003669",
        "tgn:1000003",
        "tgn:7000084",
        "tgn:7029392"
    ],
    "tgn:id":7141435,
    "tgn:name":"Lintlhammer",
    "tgn:placetype":[
        "aat:300000206"
    ]
},
  "bbox": [],
  "geometry": {"coordinates":[12.65,49.433333],"type":"Point"}
}