<<<<<<< HEAD
{
  "id": 2154570,
  "type": "Feature",
  "properties": {
    "tgn:hierarchy":[
        "tgn:2154570",
        "tgn:1000001",
        "tgn:7012149",
        "tgn:2000230",
        "tgn:7007158",
        "tgn:7029392"
    ],
    "tgn:id":2154570,
    "tgn:name":"Bear Den Ditch",
    "tgn:placetype":[
        "aat:300006075"
    ]
},
  "bbox": [],
  "geometry": {"coordinates":[-107.7,39.2333],"type":"Point"}
}
=======
{"geometry":{"type":"Point","coordinates":[-107.700000,39.233300]},"type":"Feature","properties":{"hierarchy":["tgn:2154570","tgn:1000001","tgn:7012149","tgn:2000230","tgn:7007158","tgn:7029392"],"placetype":["aat:300006075"],"id":2154570,"name:xx":"Bear Den Ditch"}}
>>>>>>> 03f74aca74312dbeaf24d7e61306dd6a786dc3d0
