{
  "id": 2371318,
  "type": "Feature",
  "properties": {
    "tgn:hierarchy":[
        "tgn:2371318",
        "tgn:1000001",
        "tgn:7012149",
        "tgn:2001752",
        "tgn:7007712",
        "tgn:7029392"
    ],
    "tgn:id":2371318,
    "tgn:name":"Haig Creek",
    "tgn:placetype":[
        "aat:300008706"
    ]
},
  "bbox": [],
  "geometry": {"coordinates":[-80.75,34.1667],"type":"Point"}
}