{
  "id": 2376422,
  "type": "Feature",
  "properties": {
    "tgn:hierarchy":[
        "tgn:2376422",
        "tgn:1000001",
        "tgn:7012149",
        "tgn:2001706",
        "tgn:7007708",
        "tgn:7029392"
    ],
    "tgn:id":2376422,
    "tgn:name":"Harding Butte",
    "tgn:placetype":[
        "aat:300008798"
    ]
},
  "bbox": [],
  "geometry": {"coordinates":[-122.5333,43.35],"type":"Point"}
}