<<<<<<< HEAD
{
  "id": 7370230,
  "type": "Feature",
  "properties": {
    "tgn:hierarchy":[
        "tgn:7370230",
        "tgn:7005581",
        "tgn:1000001",
        "tgn:7005560",
        "tgn:7029392"
    ],
    "tgn:id":7370230,
    "tgn:name":"Hu\u00e9rfano, Cerro",
    "tgn:placetype":[
        "aat:300008777"
    ]
},
  "bbox": [],
  "geometry": {"coordinates":[-106.733333,30.383333],"type":"Point"}
}
=======
{"geometry":{"type":"Point","coordinates":[-106.733333,30.383333]},"type":"Feature","properties":{"hierarchy":["tgn:7370230","tgn:7005581","tgn:1000001","tgn:7005560","tgn:7029392"],"placetype":["aat:300008777"],"id":7370230,"name:xx":"Hu\u00e9rfano, Cerro"}}
>>>>>>> 03f74aca74312dbeaf24d7e61306dd6a786dc3d0
