{
  "id": 2480360,
  "type": "Feature",
  "properties": {
    "tgn:hierarchy":[
        "tgn:2480360",
        "tgn:1000001",
        "tgn:7012149",
        "tgn:2000905",
        "tgn:7007256",
        "tgn:7029392"
    ],
    "tgn:id":2480360,
    "tgn:name":"Lake Shore Village",
    "tgn:placetype":[
        "aat:300008347"
    ]
},
  "bbox": [],
  "geometry": {"coordinates":[-89.7833,30.25],"type":"Point"}
}