{
  "id": 2582043,
  "type": "Feature",
  "properties": {
    "tgn:hierarchy":[
        "tgn:2582043",
        "tgn:1000001",
        "tgn:7012149",
        "tgn:2001449",
        "tgn:7007566",
        "tgn:7029392"
    ],
    "tgn:id":2582043,
    "tgn:name":"Pine Canyon Tank",
    "tgn:placetype":[
        "aat:300006191"
    ]
},
  "bbox": [],
  "geometry": {"coordinates":[-106.2667,36.3333],"type":"Point"}
}