{
  "id": 2343380,
  "type": "Feature",
  "properties": {
    "tgn:hierarchy":[
        "tgn:2343380",
        "tgn:1000001",
        "tgn:7012149",
        "tgn:2000291",
        "tgn:7007240",
        "tgn:7029392"
    ],
    "tgn:id":2343380,
    "tgn:name":"Gainer Lake",
    "tgn:placetype":[
        "aat:300008905"
    ]
},
  "bbox": [],
  "geometry": {"coordinates":[-85.5667,30.6667],"type":"Point"}
}