{
  "id": 2419225,
  "type": "Feature",
  "properties": {
    "tgn:hierarchy":[
        "tgn:2419225",
        "tgn:1000001",
        "tgn:2002370",
        "tgn:7012149",
        "tgn:7007923",
        "tgn:7029392"
    ],
    "tgn:id":2419225,
    "tgn:name":"Jane Draw",
    "tgn:placetype":[
        "aat:300008761"
    ]
},
  "bbox": [],
  "geometry": {"coordinates":[-104.2167,44.6667],"type":"Point"}
}