{
  "id": 2329020,
  "type": "Feature",
  "properties": {
    "tgn:hierarchy":[
        "tgn:2329020",
        "tgn:1000001",
        "tgn:7014423",
        "tgn:7012149",
        "tgn:7007517",
        "tgn:7029392"
    ],
    "tgn:id":2329020,
    "tgn:name":"Fiske Bogs",
    "tgn:placetype":[
        "aat:300008905"
    ]
},
  "bbox": [],
  "geometry": {"coordinates":[-70.7167,41.7833],"type":"Point"}
}