{
  "id": 1101422,
  "type": "Feature",
  "properties": {
    "tgn:hierarchy":[
        "tgn:1101422",
        "tgn:7000490",
        "tgn:1000006",
        "tgn:7001834",
        "tgn:7029392"
    ],
    "tgn:id":1101422,
    "tgn:name":"Boorabbin National Park",
    "tgn:placetype":[
        "aat:300008189"
    ]
},
  "bbox": [],
  "geometry": {"coordinates":[120.3333,-31.2167],"type":"Point"}
}