{
  "id": 7523760,
  "type": "Feature",
  "properties": {
    "tgn:hierarchy":[
        "tgn:7523760",
        "tgn:7001242",
        "tgn:7016833",
        "tgn:1001335",
        "tgn:7029392"
    ],
    "tgn:id":7523760,
    "tgn:name:en":"As Sayy\u0101r",
    "tgn:placetype":[
        "aat:300008347"
    ]
},
  "bbox": [],
  "geometry": {"coordinates":[31.041667,31.591944],"type":"Point"}
}