{
  "id": 2325153,
  "type": "Feature",
  "properties": {
    "tgn:hierarchy":[
        "tgn:2325153",
        "tgn:1000001",
        "tgn:2000922",
        "tgn:7012149",
        "tgn:7007515",
        "tgn:7029392"
    ],
    "tgn:id":2325153,
    "tgn:name":"Fern Spring",
    "tgn:placetype":[
        "aat:300008697"
    ]
},
  "bbox": [],
  "geometry": {"coordinates":[-68.2667,44.3333],"type":"Point"}
}