{
  "id": 7572484,
  "type": "Feature",
  "properties": {
    "tgn:hierarchy":[
        "tgn:7572484",
        "tgn:1000004",
        "tgn:7031781",
        "tgn:7000198",
        "tgn:7029392"
    ],
    "tgn:id":7572484,
    "tgn:name:en":"Jhilmili",
    "tgn:placetype":[
        "aat:300008347"
    ]
},
  "bbox": [],
  "geometry": {"coordinates":[82.850051,23.397322],"type":"Point"}
}