{
  "id": 2116448,
  "type": "Feature",
  "properties": {
    "tgn:hierarchy":[
        "tgn:2116448",
        "tgn:1000001",
        "tgn:1002271",
        "tgn:7012149",
        "tgn:7007920",
        "tgn:7029392"
    ],
    "tgn:id":2116448,
    "tgn:name":"Ozette",
    "tgn:placetype":[
        "aat:300008347",
        "aat:300387210"
    ]
},
  "bbox": [],
  "geometry": {"coordinates":[-124.65,48.15],"type":"Point"}
}