{
  "id": 2172281,
  "type": "Feature",
  "properties": {
    "tgn:hierarchy":[
        "tgn:2172281",
        "tgn:1000001",
        "tgn:1002213",
        "tgn:7012149",
        "tgn:7007710",
        "tgn:7029392"
    ],
    "tgn:id":2172281,
    "tgn:name":"Biles Creek",
    "tgn:placetype":[
        "aat:300008706"
    ]
},
  "bbox": [],
  "geometry": {"coordinates":[-74.75,40.1833],"type":"Point"}
}