{
  "id": 2158463,
  "type": "Feature",
  "properties": {
    "tgn:hierarchy":[
        "tgn:2158463",
        "tgn:1000001",
        "tgn:2001473",
        "tgn:7012149",
        "tgn:7007709",
        "tgn:7029392"
    ],
    "tgn:id":2158463,
    "tgn:name":"Beaverdam Creek",
    "tgn:placetype":[
        "aat:300008706"
    ]
},
  "bbox": [],
  "geometry": {"coordinates":[-82.5167,35.65],"type":"Point"}
}