<<<<<<< HEAD
{
  "id": 2158463,
  "type": "Feature",
  "properties": {
    "tgn:hierarchy":[
        "tgn:2158463",
        "tgn:1000001",
        "tgn:2001473",
        "tgn:7012149",
        "tgn:7007709",
        "tgn:7029392"
    ],
    "tgn:id":2158463,
    "tgn:name":"Beaverdam Creek",
    "tgn:placetype":[
        "aat:300008706"
    ]
},
  "bbox": [],
  "geometry": {"coordinates":[-82.5167,35.65],"type":"Point"}
}
=======
{"geometry":{"type":"Point","coordinates":[-82.516700,35.650000]},"type":"Feature","properties":{"hierarchy":["tgn:2158463","tgn:1000001","tgn:2001473","tgn:7012149","tgn:7007709","tgn:7029392"],"placetype":["aat:300008706"],"id":2158463,"name:xx":"Beaverdam Creek"}}
>>>>>>> 03f74aca74312dbeaf24d7e61306dd6a786dc3d0
