{
  "id": 2411369,
  "type": "Feature",
  "properties": {
    "tgn:hierarchy":[
        "tgn:2411369",
        "tgn:1000001",
        "tgn:7012149",
        "tgn:1002785",
        "tgn:7007920",
        "tgn:7029392"
    ],
    "tgn:id":2411369,
    "tgn:name":"Indian Henrys Hunting Ground",
    "tgn:placetype":[
        "aat:300055621"
    ]
},
  "bbox": [],
  "geometry": {"coordinates":[-121.8333,46.7833],"type":"Point"}
}