{
  "id": 7175012,
  "type": "Feature",
  "properties": {
    "tgn:hierarchy":[
        "tgn:7175012",
        "tgn:1000003",
        "tgn:7003678",
        "tgn:7000084",
        "tgn:7029392"
    ],
    "tgn:id":7175012,
    "tgn:name":"Gro\u00dfer Geis-Kopf",
    "tgn:placetype":[
        "aat:300008777"
    ]
},
  "bbox": [],
  "geometry": {"coordinates":[8.716667,50.933333],"type":"Point"}
}