{
  "id": 2535591,
  "type": "Feature",
  "properties": {
    "tgn:hierarchy":[
        "tgn:2535591",
        "tgn:1000001",
        "tgn:7012149",
        "tgn:1002582",
        "tgn:7007240",
        "tgn:7029392"
    ],
    "tgn:id":2535591,
    "tgn:name":"Narrows Key",
    "tgn:placetype":[
        "aat:300008791"
    ]
},
  "bbox": [],
  "geometry": {"coordinates":[-82.2167,26.6333],"type":"Point"}
}