{
  "id": 2481849,
  "type": "Feature",
  "properties": {
    "tgn:hierarchy":[
        "tgn:2481849",
        "tgn:1000001",
        "tgn:7012149",
        "tgn:2001952",
        "tgn:7007826",
        "tgn:7029392"
    ],
    "tgn:id":2481849,
    "tgn:name":"Landrum",
    "tgn:placetype":[
        "aat:300008347"
    ]
},
  "bbox": [],
  "geometry": {"coordinates":[-97.6833,26.0333],"type":"Point"}
}