{
  "id": 2414810,
  "type": "Feature",
  "properties": {
    "tgn:hierarchy":[
        "tgn:2414810",
        "tgn:1000001",
        "tgn:7012149",
        "tgn:2001105",
        "tgn:7007522",
        "tgn:7029392"
    ],
    "tgn:id":2414810,
    "tgn:name":"Isabell",
    "tgn:placetype":[
        "aat:300008347"
    ]
},
  "bbox": [],
  "geometry": {"coordinates":[-88.6167,30.9333],"type":"Point"}
}