{
  "id": 7478387,
  "type": "Feature",
  "properties": {
    "tgn:hierarchy":[
        "tgn:7478387",
        "tgn:1000004",
        "tgn:7001013",
        "tgn:1000141",
        "tgn:7029392"
    ],
    "tgn:id":7478387,
    "tgn:name":"Fangcuo",
    "tgn:placetype":[
        "aat:300008347"
    ]
},
  "bbox": [],
  "geometry": {"coordinates":[121.238239,25.100787],"type":"Point"}
}