<<<<<<< HEAD
{
  "id": 7478387,
  "type": "Feature",
  "properties": {
    "tgn:hierarchy":[
        "tgn:7478387",
        "tgn:1000004",
        "tgn:7001013",
        "tgn:1000141",
        "tgn:7029392"
    ],
    "tgn:id":7478387,
    "tgn:name":"Fangcuo",
    "tgn:placetype":[
        "aat:300008347"
    ]
},
  "bbox": [],
  "geometry": {"coordinates":[121.238239,25.100787],"type":"Point"}
}
=======
{"geometry":{"type":"Point","coordinates":[121.238239,25.100787]},"type":"Feature","properties":{"hierarchy":["tgn:7478387","tgn:1000004","tgn:7001013","tgn:1000141","tgn:7029392"],"placetype":["aat:300008347"],"id":7478387,"name:xx":"Fangcuo"}}
>>>>>>> 03f74aca74312dbeaf24d7e61306dd6a786dc3d0
