{
  "id": 2574313,
  "type": "Feature",
  "properties": {
    "tgn:hierarchy":[
        "tgn:2574313",
        "tgn:7002659",
        "tgn:1000001",
        "tgn:7012149",
        "tgn:2000048",
        "tgn:7029392"
    ],
    "tgn:id":2574313,
    "tgn:name":"Pelican Bay",
    "tgn:placetype":[
        "aat:300132316"
    ]
},
  "bbox": [],
  "geometry": {"coordinates":[-88.0833,30.2167],"type":"Point"}
}