{
  "id": 2456142,
  "type": "Feature",
  "properties": {
    "tgn:hierarchy":[
        "tgn:2456142",
        "tgn:1000001",
        "tgn:7012149",
        "tgn:1002999",
        "tgn:7007526",
        "tgn:7029392"
    ],
    "tgn:id":2456142,
    "tgn:name":"Little High Rock Reservoir",
    "tgn:placetype":[
        "aat:300006191"
    ]
},
  "bbox": [],
  "geometry": {"coordinates":[-119.4333,41.25],"type":"Point"}
}