{
  "id": 7339734,
  "type": "Feature",
  "properties": {
    "tgn:hierarchy":[
        "tgn:7339734",
        "tgn:7002827",
        "tgn:1000003",
        "tgn:7002789",
        "tgn:1000095",
        "tgn:7029392"
    ],
    "tgn:id":7339734,
    "tgn:name":"Cuzcurrita-R\u00edo Tir\u00f3n",
    "tgn:placetype":[
        "aat:300008347"
    ]
},
  "bbox": [],
  "geometry": {"coordinates":[-2.964215,42.541507],"type":"Point"}
}