<<<<<<< HEAD
{
  "id": 2767061,
  "type": "Feature",
  "properties": {
    "tgn:hierarchy":[
        "tgn:2767061",
        "tgn:1000001",
        "tgn:7012149",
        "tgn:2000181",
        "tgn:7007157",
        "tgn:7029392"
    ],
    "tgn:id":2767061,
    "tgn:name":"White Rock",
    "tgn:placetype":[
        "aat:300008791"
    ]
},
  "bbox": [],
  "geometry": {"coordinates":[-124.15,41.0833],"type":"Point"}
}
=======
{"geometry":{"type":"Point","coordinates":[-124.150000,41.083300]},"type":"Feature","properties":{"hierarchy":["tgn:2767061","tgn:1000001","tgn:7012149","tgn:2000181","tgn:7007157","tgn:7029392"],"placetype":["aat:300008791"],"id":2767061,"name:xx":"White Rock"}}
>>>>>>> 03f74aca74312dbeaf24d7e61306dd6a786dc3d0
