{
  "id": 7297234,
  "type": "Feature",
  "properties": {
    "tgn:hierarchy":[
        "tgn:7297234",
        "tgn:7002758",
        "tgn:1001316",
        "tgn:1000003",
        "tgn:1000095",
        "tgn:7029392"
    ],
    "tgn:id":7297234,
    "tgn:name":"Tamujoso, Arroyo del",
    "tgn:placetype":[
        "aat:300008699"
    ]
},
  "bbox": [],
  "geometry": {"coordinates":[-4.25,38.083333],"type":"Point"}
}