{
  "id": 2336629,
  "type": "Feature",
  "properties": {
    "tgn:hierarchy":[
        "tgn:2336629",
        "tgn:1000001",
        "tgn:7012149",
        "tgn:2000440",
        "tgn:7007248",
        "tgn:7029392"
    ],
    "tgn:id":2336629,
    "tgn:name":"Four Points",
    "tgn:placetype":[
        "aat:300008347"
    ]
},
  "bbox": [],
  "geometry": {"coordinates":[-82.7333,33.2833],"type":"Point"}
}