<<<<<<< HEAD
{
  "id": 2336629,
  "type": "Feature",
  "properties": {
    "tgn:hierarchy":[
        "tgn:2336629",
        "tgn:1000001",
        "tgn:7012149",
        "tgn:2000440",
        "tgn:7007248",
        "tgn:7029392"
    ],
    "tgn:id":2336629,
    "tgn:name":"Four Points",
    "tgn:placetype":[
        "aat:300008347"
    ]
},
  "bbox": [],
  "geometry": {"coordinates":[-82.7333,33.2833],"type":"Point"}
}
=======
{"geometry":{"type":"Point","coordinates":[-82.733300,33.283300]},"type":"Feature","properties":{"hierarchy":["tgn:2336629","tgn:1000001","tgn:7012149","tgn:2000440","tgn:7007248","tgn:7029392"],"placetype":["aat:300008347"],"id":2336629,"name:xx":"Four Points"}}
>>>>>>> 03f74aca74312dbeaf24d7e61306dd6a786dc3d0
