{
  "id": 7127389,
  "type": "Feature",
  "properties": {
    "tgn:hierarchy":[
        "tgn:7127389",
        "tgn:7000096",
        "tgn:1000003",
        "tgn:7000084",
        "tgn:7029392"
    ],
    "tgn:id":7127389,
    "tgn:name":"Niewitzwiese",
    "tgn:placetype":[
        "aat:300008903"
    ]
},
  "bbox": [],
  "geometry": {"coordinates":[12.75,52.466667],"type":"Point"}
}