{
  "id": 7483712,
  "type": "Feature",
  "properties": {
    "tgn:hierarchy":[
        "tgn:7483712",
        "tgn:7468018",
        "tgn:1000004",
        "tgn:1000141",
        "tgn:7029392"
    ],
    "tgn:id":7483712,
    "tgn:name":"Yuanchong Guoxiao",
    "tgn:placetype":[
        "aat:300006495"
    ]
},
  "bbox": [],
  "geometry": {"coordinates":[120.504167,23.489167],"type":"Point"}
}