{
  "id": 7592525,
  "type": "Feature",
  "properties": {
    "tgn:hierarchy":[
        "tgn:7592525",
        "tgn:1000004",
        "tgn:7000198",
        "tgn:7000799",
        "tgn:7029392"
    ],
    "tgn:id":7592525,
    "tgn:name:en":"Dhamot N\u0101la",
    "tgn:placetype":[
        "aat:300008699"
    ]
},
  "bbox": [],
  "geometry": {"coordinates":[74.933333,32.840278],"type":"Point"}
}