<<<<<<< HEAD
{
  "id": 7352800,
  "type": "Feature",
  "properties": {
    "tgn:hierarchy":[
        "tgn:7352800",
        "tgn:1000001",
        "tgn:7005590",
        "tgn:7005560",
        "tgn:7029392"
    ],
    "tgn:id":7352800,
    "tgn:name":"Alvarado",
    "tgn:placetype":[
        "aat:300007783"
    ]
},
  "bbox": [],
  "geometry": {"coordinates":[-100.4,19.666667],"type":"Point"}
}
=======
{"geometry":{"type":"Point","coordinates":[-100.400000,19.666667]},"type":"Feature","properties":{"hierarchy":["tgn:7352800","tgn:1000001","tgn:7005590","tgn:7005560","tgn:7029392"],"placetype":["aat:300007783"],"id":7352800,"name:xx":"Alvarado"}}
>>>>>>> 03f74aca74312dbeaf24d7e61306dd6a786dc3d0
