<<<<<<< HEAD
{
  "id": 7174887,
  "type": "Feature",
  "properties": {
    "tgn:hierarchy":[
        "tgn:7174887",
        "tgn:1000003",
        "tgn:7003682",
        "tgn:7000084",
        "tgn:7029392"
    ],
    "tgn:id":7174887,
    "tgn:name":"Grindel",
    "tgn:placetype":[
        "aat:300008347"
    ]
},
  "bbox": [],
  "geometry": {"coordinates":[7.866667,50.8],"type":"Point"}
}
=======
{"geometry":{"type":"Point","coordinates":[7.866667,50.800000]},"type":"Feature","properties":{"hierarchy":["tgn:7174887","tgn:1000003","tgn:7003682","tgn:7000084","tgn:7029392"],"placetype":["aat:300008347"],"id":7174887,"name:xx":"Grindel"}}
>>>>>>> 03f74aca74312dbeaf24d7e61306dd6a786dc3d0
