{
  "id": 7238627,
  "type": "Feature",
  "properties": {
    "tgn:hierarchy":[
        "tgn:7238627",
        "tgn:7003457",
        "tgn:1000003",
        "tgn:1000063",
        "tgn:7018236",
        "tgn:7029392"
    ],
    "tgn:id":7238627,
    "tgn:name":"Grauwensteen",
    "tgn:placetype":[
        "aat:300008347"
    ]
},
  "bbox": [],
  "geometry": {"coordinates":[4.106619,51.205416],"type":"Point"}
}