{
  "id": 2726204,
  "type": "Feature",
  "properties": {
    "tgn:hierarchy":[
        "tgn:2726204",
        "tgn:1000001",
        "tgn:7012149",
        "tgn:2002379",
        "tgn:7007923",
        "tgn:7029392"
    ],
    "tgn:id":2726204,
    "tgn:name":"Tower Creek",
    "tgn:placetype":[
        "aat:300008706"
    ]
},
  "bbox": [],
  "geometry": {"coordinates":[-110.55,44.7667],"type":"Point"}
}