{
  "id": 7482432,
  "type": "Feature",
  "properties": {
    "tgn:hierarchy":[
        "tgn:7482432",
        "tgn:1000004",
        "tgn:7490934",
        "tgn:1000141",
        "tgn:7029392"
    ],
    "tgn:id":7482432,
    "tgn:name":"Qianniao Qiao",
    "tgn:placetype":[
        "aat:300007836"
    ]
},
  "bbox": [],
  "geometry": {"coordinates":[120.358093,23.072016],"type":"Point"}
}