{
  "id": 2708977,
  "type": "Feature",
  "properties": {
    "tgn:hierarchy":[
        "tgn:2708977",
        "tgn:1000001",
        "tgn:7012149",
        "tgn:2002386",
        "tgn:7007923",
        "tgn:7029392"
    ],
    "tgn:id":2708977,
    "tgn:name":"T H Reservoir",
    "tgn:placetype":[
        "aat:300006191"
    ]
},
  "bbox": [],
  "geometry": {"coordinates":[-107.6833,44.1167],"type":"Point"}
}