{
  "id": 7359224,
  "type": "Feature",
  "properties": {
    "tgn:hierarchy":[
        "tgn:7359224",
        "tgn:7005581",
        "tgn:1000001",
        "tgn:7005560",
        "tgn:7029392"
    ],
    "tgn:id":7359224,
    "tgn:name":"Doctor Belisario Dom\u00ednguez",
    "tgn:placetype":[
        "aat:300008347"
    ]
},
  "bbox": [],
  "geometry": {"coordinates":[-106.483333,28.15],"type":"Point"}
}