<<<<<<< HEAD
{
  "id": 2337329,
  "type": "Feature",
  "properties": {
    "tgn:hierarchy":[
        "tgn:2337329",
        "tgn:1000001",
        "tgn:7012149",
        "tgn:2001298",
        "tgn:7007524",
        "tgn:7029392"
    ],
    "tgn:id":2337329,
    "tgn:name":"Fourth of July Ridge",
    "tgn:placetype":[
        "aat:300266640"
    ]
},
  "bbox": [],
  "geometry": {"coordinates":[-112.8667,46.7167],"type":"Point"}
}
=======
{"geometry":{"type":"Point","coordinates":[-112.866700,46.716700]},"type":"Feature","properties":{"hierarchy":["tgn:2337329","tgn:1000001","tgn:7012149","tgn:2001298","tgn:7007524","tgn:7029392"],"placetype":["aat:300266640"],"id":2337329,"name:xx":"Fourth of July Ridge"}}
>>>>>>> 03f74aca74312dbeaf24d7e61306dd6a786dc3d0
