{
  "id": 7519169,
  "type": "Feature",
  "properties": {
    "tgn:hierarchy":[
        "tgn:7519169",
        "tgn:1009227",
        "tgn:1000226",
        "tgn:7016822",
        "tgn:1000006",
        "tgn:7029392"
    ],
    "tgn:id":7519169,
    "tgn:name:en":"Anchorage Cove",
    "tgn:placetype":[
        "aat:300132317"
    ]
},
  "bbox": [],
  "geometry": {"coordinates":[167.433333,-44.916667],"type":"Point"}
}