{
  "id": 7415435,
  "type": "Feature",
  "properties": {
    "tgn:hierarchy":[
        "tgn:7415435",
        "tgn:7005584",
        "tgn:1000001",
        "tgn:7005560",
        "tgn:7029392"
    ],
    "tgn:id":7415435,
    "tgn:name":"San Jos\u00e9, R\u00edo",
    "tgn:placetype":[
        "aat:300008699"
    ]
},
  "bbox": [],
  "geometry": {"coordinates":[-101.6075,21.5625],"type":"Point"}
}