{
  "id": 7512445,
  "type": "Feature",
  "properties": {
    "tgn:hierarchy":[
        "tgn:7512445",
        "tgn:7000508",
        "tgn:1008380",
        "tgn:1000226",
        "tgn:1000006",
        "tgn:7029392"
    ],
    "tgn:id":7512445,
    "tgn:name:en":"Howick",
    "tgn:placetype":[
        "aat:300008347"
    ]
},
  "bbox": [],
  "geometry": {"coordinates":[174.933333,-36.883333],"type":"Point"}
}