{
  "id": 7529130,
  "type": "Feature",
  "properties": {
    "tgn:hierarchy":[
        "tgn:7529130",
        "tgn:7001242",
        "tgn:7016833",
        "tgn:1001110",
        "tgn:7029392"
    ],
    "tgn:id":7529130,
    "tgn:name:en":"Umm Rimth, W\u0101d\u012b",
    "tgn:placetype":[
        "aat:300379998"
    ]
},
  "bbox": [],
  "geometry": {"coordinates":[32.256348,29.873556],"type":"Point"}
}