{
  "id": 2460162,
  "type": "Feature",
  "properties": {
    "tgn:hierarchy":[
        "tgn:2460162",
        "tgn:1000001",
        "tgn:7012149",
        "tgn:2000803",
        "tgn:7007255",
        "tgn:7029392"
    ],
    "tgn:id":2460162,
    "tgn:name":"Little Round Mountain",
    "tgn:placetype":[
        "aat:300008798"
    ]
},
  "bbox": [],
  "geometry": {"coordinates":[-83.85,37.9167],"type":"Point"}
}