{
  "id": 1094264,
  "type": "Feature",
  "properties": {
    "tgn:hierarchy":[
        "tgn:1094264",
        "tgn:7001242",
        "tgn:1001081",
        "tgn:7441551",
        "tgn:7029392"
    ],
    "tgn:id":1094264,
    "tgn:name":"Ibba",
    "tgn:placetype":[
        "aat:300008347"
    ]
},
  "bbox": [],
  "geometry": {"coordinates":[29.0333,4.7333],"type":"Point"}
}