{
  "id": 7091952,
  "type": "Feature",
  "properties": {
    "tgn:hierarchy":[
        "tgn:7091952",
        "tgn:7003669",
        "tgn:1000003",
        "tgn:7000084",
        "tgn:7029392"
    ],
    "tgn:id":7091952,
    "tgn:name":"Untermimberg",
    "tgn:placetype":[
        "aat:300000745"
    ]
},
  "bbox": [],
  "geometry": {"coordinates":[11.266667,49.35],"type":"Point"}
}