{
  "id": 7537383,
  "type": "Feature",
  "properties": {
    "tgn:hierarchy":[
        "tgn:7537383",
        "tgn:7001242",
        "tgn:7016833",
        "tgn:1001418",
        "tgn:7029392"
    ],
    "tgn:id":7537383,
    "tgn:name:en":"Qu\u015fayr, Minq\u0101r al",
    "tgn:placetype":[
        "aat:300008749"
    ]
},
  "bbox": [],
  "geometry": {"coordinates":[26.901007,30.74715],"type":"Point"}
}