{
  "id": 2290220,
  "type": "Feature",
  "properties": {
    "tgn:hierarchy":[
        "tgn:2290220",
        "tgn:7006450",
        "tgn:1000001",
        "tgn:7012149",
        "tgn:2000089",
        "tgn:7029392"
    ],
    "tgn:id":2290220,
    "tgn:name":"Dodge Creek",
    "tgn:placetype":[
        "aat:300008706"
    ]
},
  "bbox": [],
  "geometry": {"coordinates":[-156.6167,63.0667],"type":"Point"}
}