{
  "id": 2460916,
  "type": "Feature",
  "properties": {
    "tgn:hierarchy":[
        "tgn:2460916",
        "tgn:1000001",
        "tgn:2001331",
        "tgn:7012149",
        "tgn:7007525",
        "tgn:7029392"
    ],
    "tgn:id":2460916,
    "tgn:name":"Little Skull Lake",
    "tgn:placetype":[
        "aat:300008680"
    ]
},
  "bbox": [],
  "geometry": {"coordinates":[-100.2667,42.3833],"type":"Point"}
}