{
  "id": 7257517,
  "type": "Feature",
  "properties": {
    "tgn:hierarchy":[
        "tgn:7257517",
        "tgn:1000003",
        "tgn:7003635",
        "tgn:7016845",
        "tgn:7029392"
    ],
    "tgn:id":7257517,
    "tgn:name:nl":"Bloois- en Oud-Bommenede, Polder",
    "tgn:placetype":[
        "aat:300006163"
    ]
},
  "bbox": [],
  "geometry": {"coordinates":[3.933333,51.716667],"type":"Point"}
}