<<<<<<< HEAD
{
  "id": 7351957,
  "type": "Feature",
  "properties": {
    "tgn:hierarchy":[
        "tgn:7351957",
        "tgn:1000001",
        "tgn:1001960",
        "tgn:7005560",
        "tgn:7029392"
    ],
    "tgn:id":7351957,
    "tgn:name":"Calabazas, Sierra",
    "tgn:placetype":[
        "aat:300008795"
    ]
},
  "bbox": [],
  "geometry": {"coordinates":[-109.85,29.35],"type":"Point"}
}
=======
{"geometry":{"type":"Point","coordinates":[-109.850000,29.350000]},"type":"Feature","properties":{"hierarchy":["tgn:7351957","tgn:1000001","tgn:1001960","tgn:7005560","tgn:7029392"],"placetype":["aat:300008795"],"id":7351957,"name:xx":"Calabazas, Sierra"}}
>>>>>>> 03f74aca74312dbeaf24d7e61306dd6a786dc3d0
