{
  "id": 2184154,
  "type": "Feature",
  "properties": {
    "tgn:hierarchy":[
        "tgn:2184154",
        "tgn:1000001",
        "tgn:7012149",
        "tgn:2000229",
        "tgn:7007158",
        "tgn:7029392"
    ],
    "tgn:id":2184154,
    "tgn:name":"Bob Eaton Canyon",
    "tgn:placetype":[
        "aat:300008761"
    ]
},
  "bbox": [],
  "geometry": {"coordinates":[-103.45,40.9667],"type":"Point"}
}