{
  "id": 2265738,
  "type": "Feature",
  "properties": {
    "tgn:hierarchy":[
        "tgn:2265738",
        "tgn:7030516",
        "tgn:7006450",
        "tgn:1000001",
        "tgn:7012149",
        "tgn:7029392"
    ],
    "tgn:id":2265738,
    "tgn:name":"Crater Cove",
    "tgn:placetype":[
        "aat:300132316"
    ]
},
  "bbox": [],
  "geometry": {"coordinates":[-176.2667,51.75],"type":"Point"}
}