{
  "id": 7368669,
  "type": "Feature",
  "properties": {
    "tgn:hierarchy":[
        "tgn:7368669",
        "tgn:1000001",
        "tgn:7005599",
        "tgn:7005560",
        "tgn:7029392"
    ],
    "tgn:id":7368669,
    "tgn:name":"Guadalupe",
    "tgn:placetype":[
        "aat:300008347"
    ]
},
  "bbox": [],
  "geometry": {"coordinates":[-96.033333,19.033333],"type":"Point"}
}