{
  "id": 7246870,
  "type": "Feature",
  "properties": {
    "tgn:hierarchy":[
        "tgn:7246870",
        "tgn:7003465",
        "tgn:1000003",
        "tgn:1000063",
        "tgn:4012014",
        "tgn:7029392"
    ],
    "tgn:id":7246870,
    "tgn:name":"Boucats",
    "tgn:placetype":[
        "aat:300008347"
    ]
},
  "bbox": [],
  "geometry": {"coordinates":[5.166667,50.016667],"type":"Point"}
}