{
  "id": 2662655,
  "type": "Feature",
  "properties": {
    "tgn:hierarchy":[
        "tgn:2662655",
        "tgn:2000192",
        "tgn:1000001",
        "tgn:7012149",
        "tgn:7007158",
        "tgn:7029392"
    ],
    "tgn:id":2662655,
    "tgn:name":"Signal Reservoir Number 1",
    "tgn:placetype":[
        "aat:300006191"
    ]
},
  "bbox": [],
  "geometry": {"coordinates":[-104.8833,39.9833],"type":"Point"}
}