<<<<<<< HEAD
{
  "id": 2339742,
  "type": "Feature",
  "properties": {
    "tgn:hierarchy":[
        "tgn:2339742",
        "tgn:1000001",
        "tgn:7012149",
        "tgn:1002797",
        "tgn:7007706",
        "tgn:7029392"
    ],
    "tgn:id":2339742,
    "tgn:name":"Freedom Dam",
    "tgn:placetype":[
        "aat:300008347"
    ]
},
  "bbox": [],
  "geometry": {"coordinates":[-81.2833,41.2333],"type":"Point"}
}
=======
{"geometry":{"type":"Point","coordinates":[-81.283300,41.233300]},"type":"Feature","properties":{"hierarchy":["tgn:2339742","tgn:1000001","tgn:7012149","tgn:1002797","tgn:7007706","tgn:7029392"],"placetype":["aat:300008347"],"id":2339742,"name:xx":"Freedom Dam"}}
>>>>>>> 03f74aca74312dbeaf24d7e61306dd6a786dc3d0
