{
  "id": 7541366,
  "type": "Feature",
  "properties": {
    "tgn:hierarchy":[
        "tgn:7541366",
        "tgn:7001242",
        "tgn:7016833",
        "tgn:7001336",
        "tgn:7029392"
    ],
    "tgn:id":7541366,
    "tgn:name:en":"Biy\u0101r, W\u0101d\u012b",
    "tgn:placetype":[
        "aat:300379998"
    ]
},
  "bbox": [],
  "geometry": {"coordinates":[34.654287,29.54022],"type":"Point"}
}