{
  "id": 2372029,
  "type": "Feature",
  "properties": {
    "tgn:hierarchy":[
        "tgn:2372029",
        "tgn:2000256",
        "tgn:1000001",
        "tgn:7012149",
        "tgn:7007240",
        "tgn:7029392"
    ],
    "tgn:id":2372029,
    "tgn:name":"Half Moon Pond",
    "tgn:placetype":[
        "aat:300008680"
    ]
},
  "bbox": [],
  "geometry": {"coordinates":[-82.5667,29.5833],"type":"Point"}
}