{
  "id": 2276360,
  "type": "Feature",
  "properties": {
    "tgn:hierarchy":[
        "tgn:2276360",
        "tgn:7002659",
        "tgn:1000001",
        "tgn:7012149",
        "tgn:2000039",
        "tgn:7029392"
    ],
    "tgn:id":2276360,
    "tgn:name":"Dave Cave",
    "tgn:placetype":[
        "aat:300008746"
    ]
},
  "bbox": [],
  "geometry": {"coordinates":[-87.35,34.35],"type":"Point"}
}