{
  "id": 2246410,
  "type": "Feature",
  "properties": {
    "tgn:hierarchy":[
        "tgn:2246410",
        "tgn:1000001",
        "tgn:7012149",
        "tgn:7014612",
        "tgn:7007568",
        "tgn:7029392"
    ],
    "tgn:id":2246410,
    "tgn:name":"Cobamong Pond",
    "tgn:placetype":[
        "aat:300008680"
    ]
},
  "bbox": [],
  "geometry": {"coordinates":[-73.6667,41.15],"type":"Point"}
}