{
  "id": 1024736,
  "type": "Feature",
  "properties": {
    "tgn:hierarchy":[
        "tgn:1024736",
        "tgn:1000749",
        "tgn:1000002",
        "tgn:1000056",
        "tgn:7029392"
    ],
    "tgn:id":1024736,
    "tgn:name":"San Antonio",
    "tgn:placetype":[
        "aat:300008347"
    ]
},
  "bbox": [],
  "geometry": {"coordinates":[-76.35,-6.3667],"type":"Point"}
}