{
  "id": 1085755,
  "type": "Feature",
  "properties": {
    "tgn:hierarchy":[
        "tgn:1085755",
        "tgn:1001214",
        "tgn:1000004",
        "tgn:7018456",
        "tgn:1000144",
        "tgn:7029392"
    ],
    "tgn:id":1085755,
    "tgn:name":"\u00c7\u0131nar",
    "tgn:placetype":[
        "aat:300008347"
    ]
},
  "bbox": [],
  "geometry": {"coordinates":[40.3667,37.75],"type":"Point"}
}