{
  "id": 2369852,
  "type": "Feature",
  "properties": {
    "tgn:hierarchy":[
        "tgn:2369852",
        "tgn:1000001",
        "tgn:1002223",
        "tgn:7012149",
        "tgn:7007523",
        "tgn:7029392"
    ],
    "tgn:id":2369852,
    "tgn:name":"Gurwit and Lewis Lake",
    "tgn:placetype":[
        "aat:300006191"
    ]
},
  "bbox": [],
  "geometry": {"coordinates":[-92.1667,38.6167],"type":"Point"}
}