{
  "id": 2236208,
  "type": "Feature",
  "properties": {
    "tgn:hierarchy":[
        "tgn:2236208",
        "tgn:7006450",
        "tgn:1000001",
        "tgn:2124053",
        "tgn:7012149",
        "tgn:7029392"
    ],
    "tgn:id":2236208,
    "tgn:name":"Chickaloon",
    "tgn:placetype":[
        "aat:300008347"
    ]
},
  "bbox": [],
  "geometry": {"coordinates":[-148.45,61.7833],"type":"Point"}
}