{
  "id": 7557028,
  "type": "Feature",
  "properties": {
    "tgn:hierarchy":[
        "tgn:7557028",
        "tgn:1000004",
        "tgn:7000198",
        "tgn:7016694",
        "tgn:7029392"
    ],
    "tgn:id":7557028,
    "tgn:name:en":"Sesikhaliu",
    "tgn:placetype":[
        "aat:300008347"
    ]
},
  "bbox": [],
  "geometry": {"coordinates":[83.433333,19.016667],"type":"Point"}
}