{
  "id": 7448901,
  "type": "Feature",
  "properties": {
    "tgn:hierarchy":[
        "tgn:7448901",
        "tgn:7002448",
        "tgn:1000003",
        "tgn:7019206",
        "tgn:7008591",
        "tgn:7029392"
    ],
    "tgn:id":7448901,
    "tgn:name:en":"Seskinore",
    "tgn:placetype":[
        "aat:300008347"
    ]
},
  "bbox": [],
  "geometry": {"coordinates":[-7.25,54.516667],"type":"Point"}
}