{
  "id": 7069196,
  "type": "Feature",
  "properties": {
    "tgn:hierarchy":[
        "tgn:7069196",
        "tgn:1000003",
        "tgn:7003688",
        "tgn:7000084",
        "tgn:7029392"
    ],
    "tgn:id":7069196,
    "tgn:name":"Tielenhemme",
    "tgn:placetype":[
        "aat:300387173"
    ]
},
  "bbox": [],
  "geometry": {"coordinates":[9.366667,54.266667],"type":"Point"}
}