{
  "id": 2281416,
  "type": "Feature",
  "properties": {
    "tgn:hierarchy":[
        "tgn:2281416",
        "tgn:1000001",
        "tgn:7012149",
        "tgn:1002631",
        "tgn:7007240",
        "tgn:7029392"
    ],
    "tgn:id":2281416,
    "tgn:name":"Deer Back Lake",
    "tgn:placetype":[
        "aat:300008680"
    ]
},
  "bbox": [],
  "geometry": {"coordinates":[-81.9667,29.4833],"type":"Point"}
}