<<<<<<< HEAD
{
  "id": 2250235,
  "type": "Feature",
  "properties": {
    "tgn:hierarchy":[
        "tgn:2250235",
        "tgn:1000001",
        "tgn:7012149",
        "tgn:2000181",
        "tgn:7007157",
        "tgn:7029392"
    ],
    "tgn:id":2250235,
    "tgn:name":"Collins Point",
    "tgn:placetype":[
        "aat:300008850"
    ]
},
  "bbox": [],
  "geometry": {"coordinates":[-124.3333,40.3],"type":"Point"}
}
=======
{"geometry":{"type":"Point","coordinates":[-124.333300,40.300000]},"type":"Feature","properties":{"hierarchy":["tgn:2250235","tgn:1000001","tgn:7012149","tgn:2000181","tgn:7007157","tgn:7029392"],"placetype":["aat:300008850"],"id":2250235,"name:xx":"Collins Point"}}
>>>>>>> 03f74aca74312dbeaf24d7e61306dd6a786dc3d0
