{
  "id": 2216020,
  "type": "Feature",
  "properties": {
    "tgn:hierarchy":[
        "tgn:2216020",
        "tgn:1000001",
        "tgn:7012149",
        "tgn:2001821",
        "tgn:7007713",
        "tgn:7029392"
    ],
    "tgn:id":2216020,
    "tgn:name":"Cameron Pond",
    "tgn:placetype":[
        "aat:300008680"
    ]
},
  "bbox": [],
  "geometry": {"coordinates":[-103.8667,43.9167],"type":"Point"}
}