{
  "id": 2432861,
  "type": "Feature",
  "properties": {
    "tgn:hierarchy":[
        "tgn:2432861",
        "tgn:1000001",
        "tgn:7012149",
        "tgn:2002264",
        "tgn:7013961",
        "tgn:7029392"
    ],
    "tgn:id":2432861,
    "tgn:name":"Keester Ridge",
    "tgn:placetype":[
        "aat:300266640"
    ]
},
  "bbox": [],
  "geometry": {"coordinates":[-80.8333,38.0833],"type":"Point"}
}