<<<<<<< HEAD
{
  "id": 7053836,
  "type": "Feature",
  "properties": {
    "tgn:hierarchy":[
        "tgn:7053836",
        "tgn:7003248",
        "tgn:1000003",
        "tgn:7010380",
        "tgn:1000080",
        "tgn:7029392"
    ],
    "tgn:id":7053836,
    "tgn:name":"Porto, Cala del",
    "tgn:placetype":[
        "aat:300132317"
    ]
},
  "bbox": [],
  "geometry": {"coordinates":[17.3,40.95],"type":"Point"}
}
=======
{"geometry":{"type":"Point","coordinates":[17.300000,40.950000]},"type":"Feature","properties":{"hierarchy":["tgn:7053836","tgn:7003248","tgn:1000003","tgn:7010380","tgn:1000080","tgn:7029392"],"placetype":["aat:300132317"],"id":7053836,"name:xx":"Porto, Cala del"}}
>>>>>>> 03f74aca74312dbeaf24d7e61306dd6a786dc3d0
