{
  "id": 2610614,
  "type": "Feature",
  "properties": {
    "tgn:hierarchy":[
        "tgn:2610614",
        "tgn:1000001",
        "tgn:7012149",
        "tgn:7007157",
        "tgn:7029392"
    ],
    "tgn:id":2610614,
    "tgn:name":"Red Creek",
    "tgn:placetype":[
        "aat:300008706"
    ]
},
  "bbox": [],
  "geometry": {"coordinates":[-119.4167,37.65],"type":"Point"}
}