{
  "id": 2471718,
  "type": "Feature",
  "properties": {
    "tgn:hierarchy":[
        "tgn:2471718",
        "tgn:1000001",
        "tgn:7012149",
        "tgn:2001447",
        "tgn:7007566",
        "tgn:7029392"
    ],
    "tgn:id":2471718,
    "tgn:name":"Lost Pond",
    "tgn:placetype":[
        "aat:300008680"
    ]
},
  "bbox": [],
  "geometry": {"coordinates":[-105.1667,32.0833],"type":"Point"}
}