{
  "id": 7300487,
  "type": "Feature",
  "properties": {
    "tgn:hierarchy":[
        "tgn:7300487",
        "tgn:7002826",
        "tgn:7001158",
        "tgn:1000003",
        "tgn:1000095",
        "tgn:7029392"
    ],
    "tgn:id":7300487,
    "tgn:name":"Tejeira",
    "tgn:placetype":[
        "aat:300008347"
    ]
},
  "bbox": [],
  "geometry": {"coordinates":[-6.85,42.75],"type":"Point"}
}