{
  "id": 2436306,
  "type": "Feature",
  "properties": {
    "tgn:hierarchy":[
        "tgn:2436306",
        "tgn:7006450",
        "tgn:1000001",
        "tgn:7012149",
        "tgn:2000089",
        "tgn:7029392"
    ],
    "tgn:id":2436306,
    "tgn:name":"Khotol River",
    "tgn:placetype":[
        "aat:300008707"
    ]
},
  "bbox": [],
  "geometry": {"coordinates":[-157.8667,64.45],"type":"Point"}
}