{
  "id": 2313853,
  "type": "Feature",
  "properties": {
    "tgn:hierarchy":[
        "tgn:2313853",
        "tgn:1000001",
        "tgn:7012149",
        "tgn:2002019",
        "tgn:7007826",
        "tgn:7029392"
    ],
    "tgn:id":2313853,
    "tgn:name":"Eli Hollow",
    "tgn:placetype":[
        "aat:300008761"
    ]
},
  "bbox": [],
  "geometry": {"coordinates":[-99.6167,30.3833],"type":"Point"}
}