{
  "id": 7204819,
  "type": "Feature",
  "properties": {
    "tgn:hierarchy":[
        "tgn:7204819",
        "tgn:1000003",
        "tgn:7003676",
        "tgn:7000084",
        "tgn:7029392"
    ],
    "tgn:id":7204819,
    "tgn:name":"Cluvenhagen",
    "tgn:placetype":[
        "aat:300008347"
    ]
},
  "bbox": [],
  "geometry": {"coordinates":[9.15,52.983333],"type":"Point"}
}