{
  "id": 1035231,
  "type": "Feature",
  "properties": {
    "tgn:hierarchy":[
        "tgn:1035231",
        "tgn:1000003",
        "tgn:1000070",
        "tgn:7002895",
        "tgn:7029392"
    ],
    "tgn:id":1035231,
    "tgn:name":"Saint \u00c9tienne",
    "tgn:placetype":[
        "aat:300008347"
    ]
},
  "bbox": [],
  "geometry": {"coordinates":[5.7833,44.0333],"type":"Point"}
}