{
  "id": 2715323,
  "type": "Feature",
  "properties": {
    "tgn:hierarchy":[
        "tgn:2715323",
        "tgn:1000001",
        "tgn:7012149",
        "tgn:2002379",
        "tgn:7007923",
        "tgn:7029392"
    ],
    "tgn:id":2715323,
    "tgn:name":"Tern Lake",
    "tgn:placetype":[
        "aat:300008680"
    ]
},
  "bbox": [],
  "geometry": {"coordinates":[-110.2667,44.65],"type":"Point"}
}