<<<<<<< HEAD
{
  "id": 2253967,
  "type": "Feature",
  "properties": {
    "tgn:hierarchy":[
        "tgn:2253967",
        "tgn:1000001",
        "tgn:7012149",
        "tgn:2001865",
        "tgn:7007825",
        "tgn:7029392"
    ],
    "tgn:id":2253967,
    "tgn:name":"Cool Branch",
    "tgn:placetype":[
        "aat:300008699"
    ]
},
  "bbox": [],
  "geometry": {"coordinates":[-83.6,36.3167],"type":"Point"}
}
=======
{"geometry":{"type":"Point","coordinates":[-83.600000,36.316700]},"type":"Feature","properties":{"hierarchy":["tgn:2253967","tgn:1000001","tgn:7012149","tgn:2001865","tgn:7007825","tgn:7029392"],"placetype":["aat:300008699"],"id":2253967,"name:xx":"Cool Branch"}}
>>>>>>> 03f74aca74312dbeaf24d7e61306dd6a786dc3d0
