{
  "id": 2051526,
  "type": "Feature",
  "properties": {
    "tgn:hierarchy":[
        "tgn:2051526",
        "tgn:1000001",
        "tgn:7012149",
        "tgn:2000977",
        "tgn:7007520",
        "tgn:7029392"
    ],
    "tgn:id":2051526,
    "tgn:name":"Chippewa Vista",
    "tgn:placetype":[
        "aat:300008347"
    ]
},
  "bbox": [],
  "geometry": {"coordinates":[-85.0833,43.7333],"type":"Point"}
}