{
  "id": 2469464,
  "type": "Feature",
  "properties": {
    "tgn:hierarchy":[
        "tgn:2469464",
        "tgn:1000001",
        "tgn:2001841",
        "tgn:7012149",
        "tgn:7007825",
        "tgn:7029392"
    ],
    "tgn:id":2469464,
    "tgn:name":"Look Rock",
    "tgn:placetype":[
        "aat:300008798"
    ]
},
  "bbox": [],
  "geometry": {"coordinates":[-83.9333,35.6167],"type":"Point"}
}