{
  "id": 7396311,
  "type": "Feature",
  "properties": {
    "tgn:hierarchy":[
        "tgn:7396311",
        "tgn:7005575",
        "tgn:1000001",
        "tgn:7005560",
        "tgn:7029392"
    ],
    "tgn:id":7396311,
    "tgn:name":"San Felipe de Jes\u00fas",
    "tgn:placetype":[
        "aat:300000745"
    ]
},
  "bbox": [],
  "geometry": {"coordinates":[-99.083333,19.516667],"type":"Point"}
}