{
  "id": 2576894,
  "type": "Feature",
  "properties": {
    "tgn:hierarchy":[
        "tgn:2576894",
        "tgn:1000001",
        "tgn:7012149",
        "tgn:2001968",
        "tgn:7007826",
        "tgn:7029392"
    ],
    "tgn:id":2576894,
    "tgn:name":"Pete Creek",
    "tgn:placetype":[
        "aat:300008706"
    ]
},
  "bbox": [],
  "geometry": {"coordinates":[-101.05,33.6167],"type":"Point"}
}