{
  "id": 7522533,
  "type": "Feature",
  "properties": {
    "tgn:hierarchy":[
        "tgn:7522533",
        "tgn:7001242",
        "tgn:7016833",
        "tgn:7001334",
        "tgn:7029392"
    ],
    "tgn:id":7522533,
    "tgn:name:en":"Ban\u012b \u1e28umayl, W\u0101d\u012b",
    "tgn:placetype":[
        "aat:300379998"
    ]
},
  "bbox": [],
  "geometry": {"coordinates":[31.946229,26.126572],"type":"Point"}
}