{
  "id": 7121012,
  "type": "Feature",
  "properties": {
    "tgn:hierarchy":[
        "tgn:7121012",
        "tgn:1000003",
        "tgn:7003677",
        "tgn:7000084",
        "tgn:7029392"
    ],
    "tgn:id":7121012,
    "tgn:name":"Pa\u00dflick",
    "tgn:placetype":[
        "aat:300000206"
    ]
},
  "bbox": [],
  "geometry": {"coordinates":[7.166667,52.233333],"type":"Point"}
}