{
  "id": 2688922,
  "type": "Feature",
  "properties": {
    "tgn:hierarchy":[
        "tgn:2688922",
        "tgn:1000001",
        "tgn:7012149",
        "tgn:2001274",
        "tgn:7007524",
        "tgn:7029392"
    ],
    "tgn:id":2688922,
    "tgn:name":"Spy Creek",
    "tgn:placetype":[
        "aat:300008706"
    ]
},
  "bbox": [],
  "geometry": {"coordinates":[-113.4333,48.0167],"type":"Point"}
}