{
  "id": 7063155,
  "type": "Feature",
  "properties": {
    "tgn:hierarchy":[
        "tgn:7063155",
        "tgn:7003669",
        "tgn:1000003",
        "tgn:7000084",
        "tgn:7029392"
    ],
    "tgn:id":7063155,
    "tgn:name":"Apprant",
    "tgn:placetype":[
        "aat:300000206"
    ]
},
  "bbox": [],
  "geometry": {"coordinates":[12.233333,49.116667],"type":"Point"}
}