{
  "id": 2340340,
  "type": "Feature",
  "properties": {
    "tgn:hierarchy":[
        "tgn:2340340",
        "tgn:1000001",
        "tgn:7012149",
        "tgn:7007158",
        "tgn:2000250",
        "tgn:7029392"
    ],
    "tgn:id":2340340,
    "tgn:name":"French Gulch",
    "tgn:placetype":[
        "aat:300008761"
    ]
},
  "bbox": [],
  "geometry": {"coordinates":[-105.95,39.4333],"type":"Point"}
}