{
  "id": 7497948,
  "type": "Feature",
  "properties": {
    "tgn:hierarchy":[
        "tgn:7497948",
        "tgn:7001004",
        "tgn:1000004",
        "tgn:1000141",
        "tgn:7029392"
    ],
    "tgn:id":7497948,
    "tgn:name":"Shezi Qiao",
    "tgn:placetype":[
        "aat:300007836"
    ]
},
  "bbox": [],
  "geometry": {"coordinates":[120.341484,22.744131],"type":"Point"}
}