{
  "id": 2472942,
  "type": "Feature",
  "properties": {
    "tgn:hierarchy":[
        "tgn:2472942",
        "tgn:1000001",
        "tgn:7012149",
        "tgn:2000837",
        "tgn:7007255",
        "tgn:7029392"
    ],
    "tgn:id":2472942,
    "tgn:name":"Low Gap Fork",
    "tgn:placetype":[
        "aat:300008699"
    ]
},
  "bbox": [],
  "geometry": {"coordinates":[-82.3667,37.7167],"type":"Point"}
}