{
  "id": 2545414,
  "type": "Feature",
  "properties": {
    "tgn:hierarchy":[
        "tgn:2545414",
        "tgn:7006450",
        "tgn:1000001",
        "tgn:7019698",
        "tgn:7012149",
        "tgn:7029392"
    ],
    "tgn:id":2545414,
    "tgn:name":"North Fork Big River",
    "tgn:placetype":[
        "aat:300008707"
    ]
},
  "bbox": [],
  "geometry": {"coordinates":[-152.6833,60.8167],"type":"Point"}
}