{
  "id": 7372414,
  "type": "Feature",
  "properties": {
    "tgn:hierarchy":[
        "tgn:7372414",
        "tgn:7005579",
        "tgn:1000001",
        "tgn:7005560",
        "tgn:7029392"
    ],
    "tgn:id":7372414,
    "tgn:name":"La Estancia",
    "tgn:placetype":[
        "aat:300008347"
    ]
},
  "bbox": [],
  "geometry": {"coordinates":[-102.35,22.083333],"type":"Point"}
}