{
  "id": 1090240,
  "type": "Feature",
  "properties": {
    "tgn:hierarchy":[
        "tgn:1090240",
        "tgn:7000791",
        "tgn:7001242",
        "tgn:1000167",
        "tgn:7029392"
    ],
    "tgn:id":1090240,
    "tgn:name":"Friguia",
    "tgn:placetype":[
        "aat:300008347"
    ]
},
  "bbox": [],
  "geometry": {"coordinates":[10.9333,12.05],"type":"Point"}
}