{
  "id": 2517311,
  "type": "Feature",
  "properties": {
    "tgn:hierarchy":[
        "tgn:2517311",
        "tgn:1000001",
        "tgn:7012149",
        "tgn:7007158",
        "tgn:2000248",
        "tgn:7029392"
    ],
    "tgn:id":2517311,
    "tgn:name":"Minnie Gulch",
    "tgn:placetype":[
        "aat:300008761"
    ]
},
  "bbox": [],
  "geometry": {"coordinates":[-107.8667,37.8167],"type":"Point"}
}