{
  "id": 7477801,
  "type": "Feature",
  "properties": {
    "tgn:hierarchy":[
        "tgn:7477801",
        "tgn:1000004",
        "tgn:7004300",
        "tgn:1000141",
        "tgn:7029392"
    ],
    "tgn:id":7477801,
    "tgn:name":"Kong Miao",
    "tgn:placetype":[
        "aat:300007595"
    ]
},
  "bbox": [],
  "geometry": {"coordinates":[119.58413,23.565366],"type":"Point"}
}