<<<<<<< HEAD
{
  "id": 7477801,
  "type": "Feature",
  "properties": {
    "tgn:hierarchy":[
        "tgn:7477801",
        "tgn:1000004",
        "tgn:7004300",
        "tgn:1000141",
        "tgn:7029392"
    ],
    "tgn:id":7477801,
    "tgn:name":"Kong Miao",
    "tgn:placetype":[
        "aat:300007595"
    ]
},
  "bbox": [],
  "geometry": {"coordinates":[119.58413,23.565366],"type":"Point"}
}
=======
{"geometry":{"type":"Point","coordinates":[119.584130,23.565366]},"type":"Feature","properties":{"hierarchy":["tgn:7477801","tgn:1000004","tgn:7004300","tgn:1000141","tgn:7029392"],"placetype":["aat:300007595"],"id":7477801,"name:xx":"Kong Miao"}}
>>>>>>> 03f74aca74312dbeaf24d7e61306dd6a786dc3d0
