{
  "id": 1028352,
  "type": "Feature",
  "properties": {
    "tgn:hierarchy":[
        "tgn:1028352",
        "tgn:7002445",
        "tgn:1003664",
        "tgn:1000003",
        "tgn:7026570",
        "tgn:7008591",
        "tgn:7029392"
    ],
    "tgn:id":1028352,
    "tgn:name":"Astley Green",
    "tgn:placetype":[
        "aat:300008347"
    ]
},
  "bbox": [],
  "geometry": {"coordinates":[-2.45,53.4833],"type":"Point"}
}