{
  "id": 2179332,
  "type": "Feature",
  "properties": {
    "tgn:hierarchy":[
        "tgn:2179332",
        "tgn:1000001",
        "tgn:7016172",
        "tgn:2000117",
        "tgn:7012149",
        "tgn:7029392"
    ],
    "tgn:id":2179332,
    "tgn:name":"Blakey Creek",
    "tgn:placetype":[
        "aat:300008706"
    ]
},
  "bbox": [],
  "geometry": {"coordinates":[-92.0167,33.8333],"type":"Point"}
}