{
  "id": 1059061,
  "type": "Feature",
  "properties": {
    "tgn:hierarchy":[
        "tgn:1059061",
        "tgn:1000004",
        "tgn:7011600",
        "tgn:7018214",
        "tgn:7002435",
        "tgn:7029392"
    ],
    "tgn:id":1059061,
    "tgn:name":"Ry\u010dkovo",
    "tgn:placetype":[
        "aat:300008347"
    ]
},
  "bbox": [],
  "geometry": {"coordinates":[61.7167,58.15],"type":"Point"}
}