{
  "id": 2364542,
  "type": "Feature",
  "properties": {
    "tgn:hierarchy":[
        "tgn:2364542",
        "tgn:1000001",
        "tgn:1002266",
        "tgn:7012149",
        "tgn:7007710",
        "tgn:7029392"
    ],
    "tgn:id":2364542,
    "tgn:name":"Green Valley Farms Lake",
    "tgn:placetype":[
        "aat:300006191"
    ]
},
  "bbox": [],
  "geometry": {"coordinates":[-75.7667,39.8167],"type":"Point"}
}