{
  "id": 7420959,
  "type": "Feature",
  "properties": {
    "tgn:hierarchy":[
        "tgn:7420959",
        "tgn:7005584",
        "tgn:1000001",
        "tgn:7005560",
        "tgn:7029392"
    ],
    "tgn:id":7420959,
    "tgn:name":"La Palma",
    "tgn:placetype":[
        "aat:300008347"
    ]
},
  "bbox": [],
  "geometry": {"coordinates":[-101.151111,21.357778],"type":"Point"}
}