<<<<<<< HEAD
{
  "id": 2255236,
  "type": "Feature",
  "properties": {
    "tgn:hierarchy":[
        "tgn:2255236",
        "tgn:2002365",
        "tgn:1000001",
        "tgn:7012149",
        "tgn:7007923",
        "tgn:7029392"
    ],
    "tgn:id":2255236,
    "tgn:name":"Cooper Reservoir",
    "tgn:placetype":[
        "aat:300006191"
    ]
},
  "bbox": [],
  "geometry": {"coordinates":[-105.9167,41.6],"type":"Point"}
}
=======
{"geometry":{"type":"Point","coordinates":[-105.916700,41.600000]},"type":"Feature","properties":{"hierarchy":["tgn:2255236","tgn:2002365","tgn:1000001","tgn:7012149","tgn:7007923","tgn:7029392"],"placetype":["aat:300006191"],"id":2255236,"name:xx":"Cooper Reservoir"}}
>>>>>>> 03f74aca74312dbeaf24d7e61306dd6a786dc3d0
