{
  "id": 7214123,
  "type": "Feature",
  "properties": {
    "tgn:hierarchy":[
        "tgn:7214123",
        "tgn:1000003",
        "tgn:7003689",
        "tgn:7000084",
        "tgn:7029392"
    ],
    "tgn:id":7214123,
    "tgn:name":"Bl\u00f6\u00df-Berg",
    "tgn:placetype":[
        "aat:300008777"
    ]
},
  "bbox": [],
  "geometry": {"coordinates":[11.05,50.45],"type":"Point"}
}