{
  "id": 2770597,
  "type": "Feature",
  "properties": {
    "tgn:hierarchy":[
        "tgn:2770597",
        "tgn:1000001",
        "tgn:7016172",
        "tgn:2000122",
        "tgn:7012149",
        "tgn:7029392"
    ],
    "tgn:id":2770597,
    "tgn:name":"Wildcat Bayou",
    "tgn:placetype":[
        "aat:300008699"
    ]
},
  "bbox": [],
  "geometry": {"coordinates":[-90.4833,35.2333],"type":"Point"}
}