{
  "id": 1002268,
  "type": "Feature",
  "properties": {
    "tgn:hierarchy":[
        "tgn:1002268",
        "tgn:1000001",
        "tgn:7012149",
        "tgn:7007251",
        "tgn:7029392"
    ],
    "tgn:id":1002268,
    "tgn:name":"Christian",
    "tgn:placetype":[
        "aat:300387145",
        "aat:300000771"
    ]
},
  "bbox": [],
  "geometry": {"coordinates":[-89.2833,39.55],"type":"Point"}
}