<<<<<<< HEAD
{
  "id": 2760400,
  "type": "Feature",
  "properties": {
    "tgn:hierarchy":[
        "tgn:2760400",
        "tgn:1000001",
        "tgn:7012149",
        "tgn:2002377",
        "tgn:7007923",
        "tgn:7029392"
    ],
    "tgn:id":2760400,
    "tgn:name":"West Fork Soldier Creek",
    "tgn:placetype":[
        "aat:300008706"
    ]
},
  "bbox": [],
  "geometry": {"coordinates":[-106.1,42.5667],"type":"Point"}
}
=======
{"geometry":{"type":"Point","coordinates":[-106.100000,42.566700]},"type":"Feature","properties":{"hierarchy":["tgn:2760400","tgn:1000001","tgn:7012149","tgn:2002377","tgn:7007923","tgn:7029392"],"placetype":["aat:300008706"],"id":2760400,"name:xx":"West Fork Soldier Creek"}}
>>>>>>> 03f74aca74312dbeaf24d7e61306dd6a786dc3d0
