<<<<<<< HEAD
{
  "id": 2401635,
  "type": "Feature",
  "properties": {
    "tgn:hierarchy":[
        "tgn:2401635",
        "tgn:1000001",
        "tgn:7016172",
        "tgn:7012149",
        "tgn:2000164",
        "tgn:7029392"
    ],
    "tgn:id":2401635,
    "tgn:name":"Horseshoe Lake",
    "tgn:placetype":[
        "aat:300008680"
    ]
},
  "bbox": [],
  "geometry": {"coordinates":[-92.1,34.6833],"type":"Point"}
}
=======
{"geometry":{"type":"Point","coordinates":[-92.100000,34.683300]},"type":"Feature","properties":{"hierarchy":["tgn:2401635","tgn:1000001","tgn:7016172","tgn:7012149","tgn:2000164","tgn:7029392"],"placetype":["aat:300008680"],"id":2401635,"name:xx":"Horseshoe Lake"}}
>>>>>>> 03f74aca74312dbeaf24d7e61306dd6a786dc3d0
