{
  "id": 7237109,
  "type": "Feature",
  "properties": {
    "tgn:hierarchy":[
        "tgn:7237109",
        "tgn:7002711",
        "tgn:7001338",
        "tgn:1000003",
        "tgn:1000074",
        "tgn:7029392"
    ],
    "tgn:id":7237109,
    "tgn:name":"Antiperno\u00ed",
    "tgn:placetype":[
        "aat:300008347"
    ]
},
  "bbox": [],
  "geometry": {"coordinates":[19.741111,39.774167],"type":"Point"}
}