{
  "id": 4009236,
  "type": "Feature",
  "properties": {
    "tgn:hierarchy":[
        "tgn:4009236",
        "tgn:7002443",
        "tgn:1000003",
        "tgn:7018974",
        "tgn:7008591",
        "tgn:7029392"
    ],
    "tgn:id":4009236,
    "tgn:name":"Rheola",
    "tgn:placetype":[
        "aat:300008347"
    ]
},
  "bbox": [],
  "geometry": {"coordinates":[-3.2333,51.7167],"type":"Point"}
}