{
  "id": 1088682,
  "type": "Feature",
  "properties": {
    "tgn:hierarchy":[
        "tgn:1088682",
        "tgn:7001242",
        "tgn:1000972",
        "tgn:1000158",
        "tgn:7029392"
    ],
    "tgn:id":1088682,
    "tgn:name":"Makoua",
    "tgn:placetype":[
        "aat:300008347"
    ]
},
  "bbox": [],
  "geometry": {"coordinates":[15.6667,-0.0167],"type":"Point"}
}