{
  "id": 2217739,
  "type": "Feature",
  "properties": {
    "tgn:hierarchy":[
        "tgn:2217739",
        "tgn:1000001",
        "tgn:7012149",
        "tgn:1002794",
        "tgn:7007708",
        "tgn:7029392"
    ],
    "tgn:id":2217739,
    "tgn:name":"Campbell Reservoir",
    "tgn:placetype":[
        "aat:300006191"
    ]
},
  "bbox": [],
  "geometry": {"coordinates":[-123.2833,45.05],"type":"Point"}
}