<<<<<<< HEAD
{
  "id": 7027441,
  "type": "Feature",
  "properties": {
    "tgn:hierarchy":[
        "tgn:7027441",
        "tgn:7002445",
        "tgn:1000003",
        "tgn:7008154",
        "tgn:7008591",
        "tgn:7029392"
    ],
    "tgn:id":7027441,
    "tgn:name:en":"Barton",
    "tgn:placetype":[
        "aat:300008347",
        "aat:300008372"
    ]
},
  "bbox": [],
  "geometry": {"coordinates":[-2.733333,53.816667],"type":"Point"}
}
=======
{"geometry":{"type":"Point","coordinates":[-2.733333,53.816667]},"type":"Feature","properties":{"hierarchy":["tgn:7027441","tgn:7002445","tgn:1000003","tgn:7008154","tgn:7008591","tgn:7029392"],"placetype":["aat:300008347","aat:300008372"],"name:en":"Barton","id":7027441}}
>>>>>>> 03f74aca74312dbeaf24d7e61306dd6a786dc3d0
