{
  "id": 7227003,
  "type": "Feature",
  "properties": {
    "tgn:hierarchy":[
        "tgn:7227003",
        "tgn:7002681",
        "tgn:7001395",
        "tgn:1000003",
        "tgn:1000074",
        "tgn:7029392"
    ],
    "tgn:id":7227003,
    "tgn:name":"Paral\u00eda Avl\u00eddhos",
    "tgn:placetype":[
        "aat:300008347"
    ]
},
  "bbox": [],
  "geometry": {"coordinates":[23.633333,38.383333],"type":"Point"}
}