{
  "id": 1098269,
  "type": "Feature",
  "properties": {
    "tgn:hierarchy":[
        "tgn:1098269",
        "tgn:7000490",
        "tgn:1000006",
        "tgn:7001829",
        "tgn:7029392"
    ],
    "tgn:id":1098269,
    "tgn:name":"Tanami",
    "tgn:placetype":[
        "aat:300008347"
    ]
},
  "bbox": [],
  "geometry": {"coordinates":[129.7167,-19.9667],"type":"Point"}
}