{
  "id": 2571513,
  "type": "Feature",
  "properties": {
    "tgn:hierarchy":[
        "tgn:2571513",
        "tgn:7006450",
        "tgn:1000001",
        "tgn:2124012",
        "tgn:7012149",
        "tgn:7029392"
    ],
    "tgn:id":2571513,
    "tgn:name":"Pauls Lake",
    "tgn:placetype":[
        "aat:300008680"
    ]
},
  "bbox": [],
  "geometry": {"coordinates":[-152.3167,58.3667],"type":"Point"}
}