{
  "id": 7459660,
  "type": "Feature",
  "properties": {
    "tgn:hierarchy":[
        "tgn:7459660",
        "tgn:7002445",
        "tgn:1000003",
        "tgn:7008180",
        "tgn:7008591",
        "tgn:7029392"
    ],
    "tgn:id":7459660,
    "tgn:name:en":"Orcheston",
    "tgn:placetype":[
        "aat:300008347"
    ]
},
  "bbox": [],
  "geometry": {"coordinates":[-1.916667,51.216667],"type":"Point"}
}