{
  "id": 7507948,
  "type": "Feature",
  "properties": {
    "tgn:hierarchy":[
        "tgn:7507948",
        "tgn:1009227",
        "tgn:1000226",
        "tgn:7018437",
        "tgn:1000006",
        "tgn:7029392"
    ],
    "tgn:id":7507948,
    "tgn:name:en":"Pegleg Gully",
    "tgn:placetype":[
        "aat:300008767"
    ]
},
  "bbox": [],
  "geometry": {"coordinates":[169.883333,-44.916667],"type":"Point"}
}