{
  "id": 7437429,
  "type": "Feature",
  "properties": {
    "tgn:hierarchy":[
        "tgn:7437429",
        "tgn:1000001",
        "tgn:7005597",
        "tgn:7005560",
        "tgn:7029392"
    ],
    "tgn:id":7437429,
    "tgn:name":"Severo",
    "tgn:placetype":[
        "aat:300008347"
    ]
},
  "bbox": [],
  "geometry": {"coordinates":[-99.016667,26.316667],"type":"Point"}
}