<<<<<<< HEAD
{
  "id": 7247270,
  "type": "Feature",
  "properties": {
    "tgn:hierarchy":[
        "tgn:7247270",
        "tgn:7007877",
        "tgn:1000003",
        "tgn:1000063",
        "tgn:4012014",
        "tgn:7029392"
    ],
    "tgn:id":7247270,
    "tgn:name":"Ferme Daumerie",
    "tgn:placetype":[
        "aat:300000206"
    ]
},
  "bbox": [],
  "geometry": {"coordinates":[3.8,50.633333],"type":"Point"}
}
=======
{"geometry":{"type":"Point","coordinates":[3.800000,50.633333]},"type":"Feature","properties":{"hierarchy":["tgn:7247270","tgn:7007877","tgn:1000003","tgn:1000063","tgn:4012014","tgn:7029392"],"placetype":["aat:300000206"],"id":7247270,"name:xx":"Ferme Daumerie"}}
>>>>>>> 03f74aca74312dbeaf24d7e61306dd6a786dc3d0
