{
  "id": 2675961,
  "type": "Feature",
  "properties": {
    "tgn:hierarchy":[
        "tgn:2675961",
        "tgn:1000001",
        "tgn:2000324",
        "tgn:7012149",
        "tgn:7007248",
        "tgn:7029392"
    ],
    "tgn:id":2675961,
    "tgn:name":"Sope Creek",
    "tgn:placetype":[
        "aat:300008706"
    ]
},
  "bbox": [],
  "geometry": {"coordinates":[-84.5333,33.95],"type":"Point"}
}