{
  "id": 2223177,
  "type": "Feature",
  "properties": {
    "tgn:hierarchy":[
        "tgn:2223177",
        "tgn:1000001",
        "tgn:7012149",
        "tgn:1002913",
        "tgn:7007919",
        "tgn:7029392"
    ],
    "tgn:id":2223177,
    "tgn:name":"Carroll, Lake",
    "tgn:placetype":[
        "aat:300006191"
    ]
},
  "bbox": [],
  "geometry": {"coordinates":[-77.4167,38.2833],"type":"Point"}
}