{
  "id": 2314263,
  "type": "Feature",
  "properties": {
    "tgn:hierarchy":[
        "tgn:2314263",
        "tgn:1000001",
        "tgn:7012149",
        "tgn:1002767",
        "tgn:7007920",
        "tgn:7029392"
    ],
    "tgn:id":2314263,
    "tgn:name":"Elk Creek",
    "tgn:placetype":[
        "aat:300008706"
    ]
},
  "bbox": [],
  "geometry": {"coordinates":[-123.65,46.7167],"type":"Point"}
}