{
  "id": 2438007,
  "type": "Feature",
  "properties": {
    "tgn:hierarchy":[
        "tgn:2438007",
        "tgn:1000001",
        "tgn:7012149",
        "tgn:1002929",
        "tgn:7007240",
        "tgn:7029392"
    ],
    "tgn:id":2438007,
    "tgn:name":"King Pond",
    "tgn:placetype":[
        "aat:300008680"
    ]
},
  "bbox": [],
  "geometry": {"coordinates":[-82.1333,28.6667],"type":"Point"}
}