{
  "id": 2280561,
  "type": "Feature",
  "properties": {
    "tgn:hierarchy":[
        "tgn:2280561",
        "tgn:1000001",
        "tgn:7012149",
        "tgn:7007256",
        "tgn:7029392"
    ],
    "tgn:id":2280561,
    "tgn:name":"Deep Bayou",
    "tgn:placetype":[
        "aat:300008699"
    ]
},
  "bbox": [],
  "geometry": {"coordinates":[-91.5167,32.2167],"type":"Point"}
}