{
  "id": 7297223,
  "type": "Feature",
  "properties": {
    "tgn:hierarchy":[
        "tgn:7297223",
        "tgn:7002760",
        "tgn:1000003",
        "tgn:1000095",
        "tgn:7029392"
    ],
    "tgn:id":7297223,
    "tgn:name":"Tanea, R\u00edo",
    "tgn:placetype":[
        "aat:300008699"
    ]
},
  "bbox": [],
  "geometry": {"coordinates":[-4.483333,43.25],"type":"Point"}
}