{
  "id": 2340211,
  "type": "Feature",
  "properties": {
    "tgn:hierarchy":[
        "tgn:2340211",
        "tgn:7013388",
        "tgn:1000001",
        "tgn:7012149",
        "tgn:7007517",
        "tgn:7029392"
    ],
    "tgn:id":2340211,
    "tgn:name":"French Cave",
    "tgn:placetype":[
        "aat:300008746"
    ]
},
  "bbox": [],
  "geometry": {"coordinates":[-73.3833,42.25],"type":"Point"}
}