{
  "id": 2514969,
  "type": "Feature",
  "properties": {
    "tgn:hierarchy":[
        "tgn:2514969",
        "tgn:1000001",
        "tgn:7012149",
        "tgn:2002371",
        "tgn:7007923",
        "tgn:7029392"
    ],
    "tgn:id":2514969,
    "tgn:name":"Miller Spring",
    "tgn:placetype":[
        "aat:300008697"
    ]
},
  "bbox": [],
  "geometry": {"coordinates":[-108.4333,42.55],"type":"Point"}
}