<<<<<<< HEAD
{
  "id": 2339926,
  "type": "Feature",
  "properties": {
    "tgn:hierarchy":[
        "tgn:2339926",
        "tgn:1000001",
        "tgn:7006451",
        "tgn:7012149",
        "tgn:2000102",
        "tgn:7029392"
    ],
    "tgn:id":2339926,
    "tgn:name":"Freeman Spring",
    "tgn:placetype":[
        "aat:300008697"
    ]
},
  "bbox": [],
  "geometry": {"coordinates":[-110.5333,31.5667],"type":"Point"}
}
=======
{"geometry":{"type":"Point","coordinates":[-110.533300,31.566700]},"type":"Feature","properties":{"hierarchy":["tgn:2339926","tgn:1000001","tgn:7006451","tgn:7012149","tgn:2000102","tgn:7029392"],"placetype":["aat:300008697"],"id":2339926,"name:xx":"Freeman Spring"}}
>>>>>>> 03f74aca74312dbeaf24d7e61306dd6a786dc3d0
