{
  "id": 5003072,
  "type": "Feature",
  "properties": {
    "tgn:hierarchy":[
        "tgn:5003072",
        "tgn:7003170",
        "tgn:1000003",
        "tgn:7003125",
        "tgn:1000080",
        "tgn:7029392"
    ],
    "tgn:id":5003072,
    "tgn:name":"Campello sul Clitunno",
    "tgn:placetype":[
        "aat:300008347"
    ]
},
  "bbox": [],
  "geometry": {"coordinates":[12.783333,42.816667],"type":"Point"}
}