{
  "id": 7119249,
  "type": "Feature",
  "properties": {
    "tgn:hierarchy":[
        "tgn:7119249",
        "tgn:1000003",
        "tgn:7003687",
        "tgn:7000084",
        "tgn:7029392"
    ],
    "tgn:id":7119249,
    "tgn:name":"Priesdorf",
    "tgn:placetype":[
        "aat:300008347"
    ]
},
  "bbox": [],
  "geometry": {"coordinates":[12.066667,51.65],"type":"Point"}
}