{
  "id": 2640917,
  "type": "Feature",
  "properties": {
    "tgn:hierarchy":[
        "tgn:2640917",
        "tgn:1000001",
        "tgn:1002473",
        "tgn:7012149",
        "tgn:7007240",
        "tgn:7029392"
    ],
    "tgn:id":2640917,
    "tgn:name":"Sancher Pond",
    "tgn:placetype":[
        "aat:300008680"
    ]
},
  "bbox": [],
  "geometry": {"coordinates":[-82.1833,28.5833],"type":"Point"}
}