{
  "id": 2301063,
  "type": "Feature",
  "properties": {
    "tgn:hierarchy":[
        "tgn:2301063",
        "tgn:1000001",
        "tgn:1002359",
        "tgn:7012149",
        "tgn:7007517",
        "tgn:7029392"
    ],
    "tgn:id":2301063,
    "tgn:name":"Dungeon Rock",
    "tgn:placetype":[
        "aat:300008798"
    ]
},
  "bbox": [],
  "geometry": {"coordinates":[-70.9833,42.4833],"type":"Point"}
}