{
  "id": 2672868,
  "type": "Feature",
  "properties": {
    "tgn:hierarchy":[
        "tgn:2672868",
        "tgn:1000001",
        "tgn:1002249",
        "tgn:7012149",
        "tgn:7007710",
        "tgn:7029392"
    ],
    "tgn:id":2672868,
    "tgn:name":"Snake Cave",
    "tgn:placetype":[
        "aat:300008746"
    ]
},
  "bbox": [],
  "geometry": {"coordinates":[-77.75,40.9167],"type":"Point"}
}