{
  "id": 2217578,
  "type": "Feature",
  "properties": {
    "tgn:hierarchy":[
        "tgn:2217578",
        "tgn:1000001",
        "tgn:2000299",
        "tgn:7012149",
        "tgn:7007248",
        "tgn:7029392"
    ],
    "tgn:id":2217578,
    "tgn:name":"Campbell Hill",
    "tgn:placetype":[
        "aat:300008798"
    ]
},
  "bbox": [],
  "geometry": {"coordinates":[-84.65,34.1833],"type":"Point"}
}