{
  "id": 2296644,
  "type": "Feature",
  "properties": {
    "tgn:hierarchy":[
        "tgn:2296644",
        "tgn:7006450",
        "tgn:1000001",
        "tgn:7030517",
        "tgn:7012149",
        "tgn:7029392"
    ],
    "tgn:id":2296644,
    "tgn:name":"Dry Creek",
    "tgn:placetype":[
        "aat:300008706"
    ]
},
  "bbox": [],
  "geometry": {"coordinates":[-158.2667,56.5333],"type":"Point"}
}