{
  "id": 7436963,
  "type": "Feature",
  "properties": {
    "tgn:hierarchy":[
        "tgn:7436963",
        "tgn:7005580",
        "tgn:1000001",
        "tgn:7005560",
        "tgn:7029392"
    ],
    "tgn:id":7436963,
    "tgn:name":"Sin Pensar",
    "tgn:placetype":[
        "aat:300008347"
    ]
},
  "bbox": [],
  "geometry": {"coordinates":[-93.833333,15.95],"type":"Point"}
}