<<<<<<< HEAD
{
  "id": 2766294,
  "type": "Feature",
  "properties": {
    "tgn:hierarchy":[
        "tgn:2766294",
        "tgn:1000001",
        "tgn:1002902",
        "tgn:7012149",
        "tgn:7007516",
        "tgn:7029392"
    ],
    "tgn:id":2766294,
    "tgn:name":"White Marsh Branch",
    "tgn:placetype":[
        "aat:300008699"
    ]
},
  "bbox": [],
  "geometry": {"coordinates":[-75.65,38.2],"type":"Point"}
}
=======
{"geometry":{"type":"Point","coordinates":[-75.650000,38.200000]},"type":"Feature","properties":{"hierarchy":["tgn:2766294","tgn:1000001","tgn:1002902","tgn:7012149","tgn:7007516","tgn:7029392"],"placetype":["aat:300008699"],"id":2766294,"name:xx":"White Marsh Branch"}}
>>>>>>> 03f74aca74312dbeaf24d7e61306dd6a786dc3d0
