{
  "id": 7313848,
  "type": "Feature",
  "properties": {
    "tgn:hierarchy":[
        "tgn:7313848",
        "tgn:1001705",
        "tgn:1000049",
        "tgn:1000002",
        "tgn:7029392"
    ],
    "tgn:id":7313848,
    "tgn:name":"La Verde, Estero",
    "tgn:placetype":[
        "aat:300008699"
    ]
},
  "bbox": [],
  "geometry": {"coordinates":[-72.083333,-35.316667],"type":"Point"}
}