{
  "id": 2111793,
  "type": "Feature",
  "properties": {
    "tgn:hierarchy":[
        "tgn:2111793",
        "tgn:1000001",
        "tgn:2002144",
        "tgn:7012149",
        "tgn:7007919",
        "tgn:7029392"
    ],
    "tgn:id":2111793,
    "tgn:name":"Flint Hill",
    "tgn:placetype":[
        "aat:300008347",
        "aat:300387210"
    ]
},
  "bbox": [],
  "geometry": {"coordinates":[-79.6333,37.25],"type":"Point"}
}