{
  "id": 7280734,
  "type": "Feature",
  "properties": {
    "tgn:hierarchy":[
        "tgn:7280734",
        "tgn:1001637",
        "tgn:1000049",
        "tgn:1000002",
        "tgn:7029392"
    ],
    "tgn:id":7280734,
    "tgn:name":"Talcam\u00e1vida",
    "tgn:placetype":[
        "aat:300008347"
    ]
},
  "bbox": [],
  "geometry": {"coordinates":[-72.75,-36.083333],"type":"Point"}
}