{
  "id": 2731536,
  "type": "Feature",
  "properties": {
    "tgn:hierarchy":[
        "tgn:2731536",
        "tgn:1000001",
        "tgn:7012149",
        "tgn:7007157",
        "tgn:1002972",
        "tgn:7029392"
    ],
    "tgn:id":2731536,
    "tgn:name":"Tule Creek",
    "tgn:placetype":[
        "aat:300008706"
    ]
},
  "bbox": [],
  "geometry": {"coordinates":[-119.3333,34.55],"type":"Point"}
}