{
  "id": 6003090,
  "type": "Feature",
  "properties": {
    "tgn:hierarchy":[
        "tgn:6003090",
        "tgn:1000003",
        "tgn:1003381",
        "tgn:7006660",
        "tgn:7029392"
    ],
    "tgn:id":6003090,
    "tgn:name":"Kiik-Koba",
    "tgn:placetype":[
        "aat:300008347",
        "aat:300000810",
        "aat:300167671",
        "aat:300008746"
    ]
},
  "bbox": [],
  "geometry": {"coordinates":[34.35,44.9667],"type":"Point"}
}