{
  "id": 2180286,
  "type": "Feature",
  "properties": {
    "tgn:hierarchy":[
        "tgn:2180286",
        "tgn:1000001",
        "tgn:7012149",
        "tgn:2002113",
        "tgn:7007827",
        "tgn:7029392"
    ],
    "tgn:id":2180286,
    "tgn:name":"Block Mesas",
    "tgn:placetype":[
        "aat:300008798"
    ]
},
  "bbox": [],
  "geometry": {"coordinates":[-112.75,37.1167],"type":"Point"}
}