{
  "id": 7583373,
  "type": "Feature",
  "properties": {
    "tgn:hierarchy":[
        "tgn:7583373",
        "tgn:1000004",
        "tgn:7000198",
        "tgn:7016883",
        "tgn:7029392"
    ],
    "tgn:id":7583373,
    "tgn:name:en":"Kal\u0101l Mazra",
    "tgn:placetype":[
        "aat:300008347"
    ]
},
  "bbox": [],
  "geometry": {"coordinates":[76.162915,30.653803],"type":"Point"}
}