{
  "id": 7367448,
  "type": "Feature",
  "properties": {
    "tgn:hierarchy":[
        "tgn:7367448",
        "tgn:1001853",
        "tgn:1000001",
        "tgn:7005560",
        "tgn:7029392"
    ],
    "tgn:id":7367448,
    "tgn:name":"Estanque de Falc\u00f3n",
    "tgn:placetype":[
        "aat:300008347"
    ]
},
  "bbox": [],
  "geometry": {"coordinates":[-102.316667,27.683333],"type":"Point"}
}