{
  "id": 2200449,
  "type": "Feature",
  "properties": {
    "tgn:hierarchy":[
        "tgn:2200449",
        "tgn:1000001",
        "tgn:7012149",
        "tgn:1002795",
        "tgn:7007826",
        "tgn:7029392"
    ],
    "tgn:id":2200449,
    "tgn:name":"Brushy Lake",
    "tgn:placetype":[
        "aat:300008680"
    ]
},
  "bbox": [],
  "geometry": {"coordinates":[-94.85,30.4833],"type":"Point"}
}