<<<<<<< HEAD
{
  "id": 7376912,
  "type": "Feature",
  "properties": {
    "tgn:hierarchy":[
        "tgn:7376912",
        "tgn:1000001",
        "tgn:7005597",
        "tgn:7005560",
        "tgn:7029392"
    ],
    "tgn:id":7376912,
    "tgn:name":"Las Anacuas",
    "tgn:placetype":[
        "aat:300008347"
    ]
},
  "bbox": [],
  "geometry": {"coordinates":[-98.233333,25.233333],"type":"Point"}
}
=======
{"geometry":{"type":"Point","coordinates":[-98.233333,25.233333]},"type":"Feature","properties":{"hierarchy":["tgn:7376912","tgn:1000001","tgn:7005597","tgn:7005560","tgn:7029392"],"placetype":["aat:300008347"],"id":7376912,"name:xx":"Las Anacuas"}}
>>>>>>> 03f74aca74312dbeaf24d7e61306dd6a786dc3d0
