{
  "id": 7532357,
  "type": "Feature",
  "properties": {
    "tgn:hierarchy":[
        "tgn:7532357",
        "tgn:7001242",
        "tgn:7016833",
        "tgn:1001092",
        "tgn:7029392"
    ],
    "tgn:id":7532357,
    "tgn:name":"Mustashf\u00e1 Shubr\u0101 al Khaymah al Markaz\u012b",
    "tgn:placetype":[
        "aat:300006676"
    ]
},
  "bbox": [],
  "geometry": {"coordinates":[31.230965,30.129754],"type":"Point"}
}