{
  "id": 7449704,
  "type": "Feature",
  "properties": {
    "tgn:hierarchy":[
        "tgn:7449704",
        "tgn:7002443",
        "tgn:1000003",
        "tgn:7018993",
        "tgn:7008591",
        "tgn:7029392"
    ],
    "tgn:id":7449704,
    "tgn:name:en":"Fishguard Bay",
    "tgn:placetype":[
        "aat:300132316"
    ]
},
  "bbox": [],
  "geometry": {"coordinates":[-4.933333,52.016667],"type":"Point"}
}