{
  "id": 2511860,
  "type": "Feature",
  "properties": {
    "tgn:hierarchy":[
        "tgn:2511860",
        "tgn:2000452",
        "tgn:1000001",
        "tgn:7012149",
        "tgn:7007250",
        "tgn:7029392"
    ],
    "tgn:id":2511860,
    "tgn:name":"Milk Lateral",
    "tgn:placetype":[
        "aat:300006075"
    ]
},
  "bbox": [],
  "geometry": {"coordinates":[-116.3333,43.6167],"type":"Point"}
}