{
  "id": 7235430,
  "type": "Feature",
  "properties": {
    "tgn:hierarchy":[
        "tgn:7235430",
        "tgn:7002690",
        "tgn:7012056",
        "tgn:1000003",
        "tgn:1000074",
        "tgn:7029392"
    ],
    "tgn:id":7235430,
    "tgn:name":"Arkhondik\u00ed",
    "tgn:placetype":[
        "aat:300008347"
    ]
},
  "bbox": [],
  "geometry": {"coordinates":[24.333333,35.316667],"type":"Point"}
}