{
  "id": 2006120,
  "type": "Feature",
  "properties": {
    "tgn:hierarchy":[
        "tgn:2006120",
        "tgn:7006450",
        "tgn:1000001",
        "tgn:7019698",
        "tgn:7012149",
        "tgn:7029392"
    ],
    "tgn:id":2006120,
    "tgn:name":"Hope",
    "tgn:placetype":[
        "aat:300008347"
    ]
},
  "bbox": [],
  "geometry": {"coordinates":[-149.6333,60.9167],"type":"Point"}
}