<<<<<<< HEAD
{
  "id": 2336352,
  "type": "Feature",
  "properties": {
    "tgn:hierarchy":[
        "tgn:2336352",
        "tgn:2002142",
        "tgn:1000001",
        "tgn:7012149",
        "tgn:7007919",
        "tgn:7029392"
    ],
    "tgn:id":2336352,
    "tgn:name":"Fountain Cave",
    "tgn:placetype":[
        "aat:300008746"
    ]
},
  "bbox": [],
  "geometry": {"coordinates":[-78.8333,38.25],"type":"Point"}
}
=======
{"geometry":{"type":"Point","coordinates":[-78.833300,38.250000]},"type":"Feature","properties":{"hierarchy":["tgn:2336352","tgn:2002142","tgn:1000001","tgn:7012149","tgn:7007919","tgn:7029392"],"placetype":["aat:300008746"],"id":2336352,"name:xx":"Fountain Cave"}}
>>>>>>> 03f74aca74312dbeaf24d7e61306dd6a786dc3d0
