{
  "id": 2242589,
  "type": "Feature",
  "properties": {
    "tgn:hierarchy":[
        "tgn:2242589",
        "tgn:2000258",
        "tgn:1000001",
        "tgn:7012149",
        "tgn:7007240",
        "tgn:7029392"
    ],
    "tgn:id":2242589,
    "tgn:name":"Clear Creek",
    "tgn:placetype":[
        "aat:300008706"
    ]
},
  "bbox": [],
  "geometry": {"coordinates":[-85.4667,30.2833],"type":"Point"}
}