<<<<<<< HEAD
{
  "id": 7471692,
  "type": "Feature",
  "properties": {
    "tgn:hierarchy":[
        "tgn:7471692",
        "tgn:7488858",
        "tgn:1000004",
        "tgn:1000141",
        "tgn:7029392"
    ],
    "tgn:id":7471692,
    "tgn:name":"Xiaxizhou",
    "tgn:placetype":[
        "aat:300008347"
    ]
},
  "bbox": [],
  "geometry": {"coordinates":[120.65,23.966667],"type":"Point"}
}
=======
{"geometry":{"type":"Point","coordinates":[120.650000,23.966667]},"type":"Feature","properties":{"hierarchy":["tgn:7471692","tgn:7488858","tgn:1000004","tgn:1000141","tgn:7029392"],"placetype":["aat:300008347"],"id":7471692,"name:xx":"Xiaxizhou"}}
>>>>>>> 03f74aca74312dbeaf24d7e61306dd6a786dc3d0
