{
  "id": 7471692,
  "type": "Feature",
  "properties": {
    "tgn:hierarchy":[
        "tgn:7471692",
        "tgn:7488858",
        "tgn:1000004",
        "tgn:1000141",
        "tgn:7029392"
    ],
    "tgn:id":7471692,
    "tgn:name":"Xiaxizhou",
    "tgn:placetype":[
        "aat:300008347"
    ]
},
  "bbox": [],
  "geometry": {"coordinates":[120.65,23.966667],"type":"Point"}
}