{
  "id": 2193914,
  "type": "Feature",
  "properties": {
    "tgn:hierarchy":[
        "tgn:2193914",
        "tgn:1000001",
        "tgn:7012149",
        "tgn:2001864",
        "tgn:7007825",
        "tgn:7029392"
    ],
    "tgn:id":2193914,
    "tgn:name":"Briar Ridge",
    "tgn:placetype":[
        "aat:300266640"
    ]
},
  "bbox": [],
  "geometry": {"coordinates":[-87.1167,35.3667],"type":"Point"}
}