{
  "id": 7001382,
  "type": "Feature",
  "properties": {
    "tgn:hierarchy":[
        "tgn:7001382",
        "tgn:1000861",
        "tgn:1000004",
        "tgn:1000119",
        "tgn:7029392"
    ],
    "tgn:id":7001382,
    "tgn:name":"Elat",
    "tgn:placetype":[
        "aat:300008347",
        "aat:300008389",
        "aat:300387511",
        "aat:300387291"
    ]
},
  "bbox": [],
  "geometry": {"coordinates":[34.95,29.55],"type":"Point"}
}