{
  "id": 7417402,
  "type": "Feature",
  "properties": {
    "tgn:hierarchy":[
        "tgn:7417402",
        "tgn:7005584",
        "tgn:1000001",
        "tgn:7005560",
        "tgn:7029392"
    ],
    "tgn:id":7417402,
    "tgn:name":"Grande, Cerro",
    "tgn:placetype":[
        "aat:300008795"
    ]
},
  "bbox": [],
  "geometry": {"coordinates":[-101.201944,20.726111],"type":"Point"}
}