{
  "id": 1090508,
  "type": "Feature",
  "properties": {
    "tgn:hierarchy":[
        "tgn:1090508",
        "tgn:7001242",
        "tgn:7593795",
        "tgn:1000169",
        "tgn:7029392"
    ],
    "tgn:id":1090508,
    "tgn:name":"Maungu",
    "tgn:placetype":[
        "aat:300008347"
    ]
},
  "bbox": [],
  "geometry": {"coordinates":[38.7667,-3.5667],"type":"Point"}
}