{
  "id": 2061744,
  "type": "Feature",
  "properties": {
    "tgn:hierarchy":[
        "tgn:2061744",
        "tgn:1000001",
        "tgn:7012149",
        "tgn:2001293",
        "tgn:7007524",
        "tgn:7029392"
    ],
    "tgn:id":2061744,
    "tgn:name":"Springdale",
    "tgn:placetype":[
        "aat:300008347"
    ]
},
  "bbox": [],
  "geometry": {"coordinates":[-110.2167,45.7333],"type":"Point"}
}