{
  "id": 7085300,
  "type": "Feature",
  "properties": {
    "tgn:hierarchy":[
        "tgn:7085300",
        "tgn:7003672",
        "tgn:1000003",
        "tgn:7000084",
        "tgn:7029392"
    ],
    "tgn:id":7085300,
    "tgn:name":"Werfthafen",
    "tgn:placetype":[
        "aat:300008678"
    ]
},
  "bbox": [],
  "geometry": {"coordinates":[8.583333,53.533333],"type":"Point"}
}