{
  "id": 7284745,
  "type": "Feature",
  "properties": {
    "tgn:hierarchy":[
        "tgn:7284745",
        "tgn:1001702",
        "tgn:1000049",
        "tgn:1000002",
        "tgn:7029392"
    ],
    "tgn:id":7284745,
    "tgn:name":"Pierce, Cabo",
    "tgn:placetype":[
        "aat:300386846"
    ]
},
  "bbox": [],
  "geometry": {"coordinates":[-73.616667,-52.266667],"type":"Point"}
}