{
  "id": 2621326,
  "type": "Feature",
  "properties": {
    "tgn:hierarchy":[
        "tgn:2621326",
        "tgn:1000001",
        "tgn:7012149",
        "tgn:2000397",
        "tgn:7007248",
        "tgn:7029392"
    ],
    "tgn:id":2621326,
    "tgn:name":"Roaring Branch",
    "tgn:placetype":[
        "aat:300008699"
    ]
},
  "bbox": [],
  "geometry": {"coordinates":[-84.95,32.55],"type":"Point"}
}