{
  "id": 2104565,
  "type": "Feature",
  "properties": {
    "tgn:hierarchy":[
        "tgn:2104565",
        "tgn:1000001",
        "tgn:7012149",
        "tgn:1002535",
        "tgn:7007826",
        "tgn:7029392"
    ],
    "tgn:id":2104565,
    "tgn:name":"Grays Prairie",
    "tgn:placetype":[
        "aat:300008347"
    ]
},
  "bbox": [],
  "geometry": {"coordinates":[-96.3333,32.4667],"type":"Point"}
}