{
  "id": 2753289,
  "type": "Feature",
  "properties": {
    "tgn:hierarchy":[
        "tgn:2753289",
        "tgn:1000001",
        "tgn:7012149",
        "tgn:2000231",
        "tgn:7007158",
        "tgn:7029392"
    ],
    "tgn:id":2753289,
    "tgn:name":"Waterfall Creek",
    "tgn:placetype":[
        "aat:300008706"
    ]
},
  "bbox": [],
  "geometry": {"coordinates":[-106.7667,37.4333],"type":"Point"}
}