{
  "id": 2523629,
  "type": "Feature",
  "properties": {
    "tgn:hierarchy":[
        "tgn:2523629",
        "tgn:7006450",
        "tgn:1000001",
        "tgn:7012149",
        "tgn:2000089",
        "tgn:7029392"
    ],
    "tgn:id":2523629,
    "tgn:name":"Moosehead Rack",
    "tgn:placetype":[
        "aat:300008798"
    ]
},
  "bbox": [],
  "geometry": {"coordinates":[-151.25,65.25],"type":"Point"}
}