{
  "id": 2514557,
  "type": "Feature",
  "properties": {
    "tgn:hierarchy":[
        "tgn:2514557",
        "tgn:1000001",
        "tgn:7012149",
        "tgn:7007706",
        "tgn:7029392"
    ],
    "tgn:id":2514557,
    "tgn:name":"Miller Hill",
    "tgn:placetype":[
        "aat:300008798"
    ]
},
  "bbox": [],
  "geometry": {"coordinates":[-82.4667,38.7167],"type":"Point"}
}