{
  "id": 2392628,
  "type": "Feature",
  "properties": {
    "tgn:hierarchy":[
        "tgn:2392628",
        "tgn:1000001",
        "tgn:7012149",
        "tgn:7007706",
        "tgn:7029392"
    ],
    "tgn:id":2392628,
    "tgn:name":"Hoaglin Creek",
    "tgn:placetype":[
        "aat:300008706"
    ]
},
  "bbox": [],
  "geometry": {"coordinates":[-84.7667,40.8333],"type":"Point"}
}