{
  "id": 7035599,
  "type": "Feature",
  "properties": {
    "tgn:hierarchy":[
        "tgn:7035599",
        "tgn:7002991",
        "tgn:1000003",
        "tgn:7002997",
        "tgn:1000080",
        "tgn:7029392"
    ],
    "tgn:id":7035599,
    "tgn:name":"Staol",
    "tgn:placetype":[
        "aat:300008347"
    ]
},
  "bbox": [],
  "geometry": {"coordinates":[12.362222,46.183056],"type":"Point"}
}