{
  "id": 2529670,
  "type": "Feature",
  "properties": {
    "tgn:hierarchy":[
        "tgn:2529670",
        "tgn:1000001",
        "tgn:2000782",
        "tgn:7012149",
        "tgn:7007255",
        "tgn:7029392"
    ],
    "tgn:id":2529670,
    "tgn:name":"Mud Lick",
    "tgn:placetype":[
        "aat:300008699"
    ]
},
  "bbox": [],
  "geometry": {"coordinates":[-83.65,37.0333],"type":"Point"}
}