<<<<<<< HEAD
{
  "id": 7476610,
  "type": "Feature",
  "properties": {
    "tgn:hierarchy":[
        "tgn:7476610",
        "tgn:7487020",
        "tgn:1000004",
        "tgn:1000141",
        "tgn:7029392"
    ],
    "tgn:id":7476610,
    "tgn:name":"Huangwuhuofang",
    "tgn:placetype":[
        "aat:300008347"
    ]
},
  "bbox": [],
  "geometry": {"coordinates":[120.908293,24.587607],"type":"Point"}
}
=======
{"geometry":{"type":"Point","coordinates":[120.908293,24.587607]},"type":"Feature","properties":{"hierarchy":["tgn:7476610","tgn:7487020","tgn:1000004","tgn:1000141","tgn:7029392"],"placetype":["aat:300008347"],"id":7476610,"name:xx":"Huangwuhuofang"}}
>>>>>>> 03f74aca74312dbeaf24d7e61306dd6a786dc3d0
