{
  "id": 7476610,
  "type": "Feature",
  "properties": {
    "tgn:hierarchy":[
        "tgn:7476610",
        "tgn:7487020",
        "tgn:1000004",
        "tgn:1000141",
        "tgn:7029392"
    ],
    "tgn:id":7476610,
    "tgn:name":"Huangwuhuofang",
    "tgn:placetype":[
        "aat:300008347"
    ]
},
  "bbox": [],
  "geometry": {"coordinates":[120.908293,24.587607],"type":"Point"}
}