{
  "id": 1003041,
  "type": "Feature",
  "properties": {
    "tgn:hierarchy":[
        "tgn:1003041",
        "tgn:1000001",
        "tgn:7012149",
        "tgn:7007710",
        "tgn:7029392"
    ],
    "tgn:id":1003041,
    "tgn:name":"Wyoming",
    "tgn:placetype":[
        "aat:300387145",
        "aat:300000771"
    ]
},
  "bbox": [],
  "geometry": {"coordinates":[-76.1167,41.6167],"type":"Point"}
}