{
  "id": 7351456,
  "type": "Feature",
  "properties": {
    "tgn:hierarchy":[
        "tgn:7351456",
        "tgn:1000001",
        "tgn:1001960",
        "tgn:7005560",
        "tgn:7029392"
    ],
    "tgn:id":7351456,
    "tgn:name":"Bomi Melones",
    "tgn:placetype":[
        "aat:300008347"
    ]
},
  "bbox": [],
  "geometry": {"coordinates":[-109.633333,28.983333],"type":"Point"}
}