{
  "id": 7217271,
  "type": "Feature",
  "properties": {
    "tgn:hierarchy":[
        "tgn:7217271",
        "tgn:7011161",
        "tgn:7002674",
        "tgn:1000003",
        "tgn:1000074",
        "tgn:7029392"
    ],
    "tgn:id":7217271,
    "tgn:name":"Ts\u00f3mpos",
    "tgn:placetype":[
        "aat:300008798"
    ]
},
  "bbox": [],
  "geometry": {"coordinates":[25.987778,38.523056],"type":"Point"}
}