{
  "id": 2548650,
  "type": "Feature",
  "properties": {
    "tgn:hierarchy":[
        "tgn:2548650",
        "tgn:1000001",
        "tgn:1002174",
        "tgn:7012149",
        "tgn:7007826",
        "tgn:7029392"
    ],
    "tgn:id":2548650,
    "tgn:name":"North Nolan Creek",
    "tgn:placetype":[
        "aat:300008706"
    ]
},
  "bbox": [],
  "geometry": {"coordinates":[-97.6667,31.15],"type":"Point"}
}