{
  "id": 7145124,
  "type": "Feature",
  "properties": {
    "tgn:hierarchy":[
        "tgn:7145124",
        "tgn:1000003",
        "tgn:7003677",
        "tgn:7000084",
        "tgn:7029392"
    ],
    "tgn:id":7145124,
    "tgn:name":"Klemenshof",
    "tgn:placetype":[
        "aat:300008347"
    ]
},
  "bbox": [],
  "geometry": {"coordinates":[6.666667,50.833333],"type":"Point"}
}