{
  "id": 7268902,
  "type": "Feature",
  "properties": {
    "tgn:hierarchy":[
        "tgn:7268902",
        "tgn:1000003",
        "tgn:7003635",
        "tgn:7016845",
        "tgn:7029392"
    ],
    "tgn:id":7268902,
    "tgn:name:nl":"Oud-beoosten-Blij-bezuidenpolder",
    "tgn:placetype":[
        "aat:300006163"
    ]
},
  "bbox": [],
  "geometry": {"coordinates":[3.95,51.233333],"type":"Point"}
}