<<<<<<< HEAD
{
  "id": 2255283,
  "type": "Feature",
  "properties": {
    "tgn:hierarchy":[
        "tgn:2255283",
        "tgn:1000001",
        "tgn:7012149",
        "tgn:2001456",
        "tgn:7007566",
        "tgn:7029392"
    ],
    "tgn:id":2255283,
    "tgn:name":"Cooper Tank",
    "tgn:placetype":[
        "aat:300006191"
    ]
},
  "bbox": [],
  "geometry": {"coordinates":[-106.2,33.9333],"type":"Point"}
}
=======
{"geometry":{"type":"Point","coordinates":[-106.200000,33.933300]},"type":"Feature","properties":{"hierarchy":["tgn:2255283","tgn:1000001","tgn:7012149","tgn:2001456","tgn:7007566","tgn:7029392"],"placetype":["aat:300006191"],"id":2255283,"name:xx":"Cooper Tank"}}
>>>>>>> 03f74aca74312dbeaf24d7e61306dd6a786dc3d0
