{
  "id": 2672311,
  "type": "Feature",
  "properties": {
    "tgn:hierarchy":[
        "tgn:2672311",
        "tgn:7006450",
        "tgn:1000001",
        "tgn:7012149",
        "tgn:7029392"
    ],
    "tgn:id":2672311,
    "tgn:name":"Smoke Creek",
    "tgn:placetype":[
        "aat:300008706"
    ]
},
  "bbox": [],
  "geometry": {"coordinates":[-147.1833,68.3667],"type":"Point"}
}