{
  "id": 2697123,
  "type": "Feature",
  "properties": {
    "tgn:hierarchy":[
        "tgn:2697123",
        "tgn:1000001",
        "tgn:7012149",
        "tgn:2001706",
        "tgn:7007708",
        "tgn:7029392"
    ],
    "tgn:id":2697123,
    "tgn:name":"Stony Brook",
    "tgn:placetype":[
        "aat:300008699"
    ]
},
  "bbox": [],
  "geometry": {"coordinates":[-123.65,43.6833],"type":"Point"}
}