{
  "id": 2748280,
  "type": "Feature",
  "properties": {
    "tgn:hierarchy":[
        "tgn:2748280",
        "tgn:7002659",
        "tgn:1000001",
        "tgn:2000016",
        "tgn:7012149",
        "tgn:7029392"
    ],
    "tgn:id":2748280,
    "tgn:name":"Walker Chapel Hollow",
    "tgn:placetype":[
        "aat:300008761"
    ]
},
  "bbox": [],
  "geometry": {"coordinates":[-88.0333,34.8333],"type":"Point"}
}