<<<<<<< HEAD
{
  "id": 7357172,
  "type": "Feature",
  "properties": {
    "tgn:hierarchy":[
        "tgn:7357172",
        "tgn:7005581",
        "tgn:1000001",
        "tgn:7005560",
        "tgn:7029392"
    ],
    "tgn:id":7357172,
    "tgn:name":"Campo 66",
    "tgn:placetype":[
        "aat:300008347"
    ]
},
  "bbox": [],
  "geometry": {"coordinates":[-106.733333,29.033333],"type":"Point"}
}
=======
{"geometry":{"type":"Point","coordinates":[-106.733333,29.033333]},"type":"Feature","properties":{"hierarchy":["tgn:7357172","tgn:7005581","tgn:1000001","tgn:7005560","tgn:7029392"],"placetype":["aat:300008347"],"id":7357172,"name:xx":"Campo 66"}}
>>>>>>> 03f74aca74312dbeaf24d7e61306dd6a786dc3d0
