{
  "id": 2436350,
  "type": "Feature",
  "properties": {
    "tgn:hierarchy":[
        "tgn:2436350",
        "tgn:7013388",
        "tgn:1000001",
        "tgn:7012149",
        "tgn:7007517",
        "tgn:7029392"
    ],
    "tgn:id":2436350,
    "tgn:name":"Kibbe Point",
    "tgn:placetype":[
        "aat:300008850"
    ]
},
  "bbox": [],
  "geometry": {"coordinates":[-73.0333,42.15],"type":"Point"}
}