{
  "id": 2369000,
  "type": "Feature",
  "properties": {
    "tgn:hierarchy":[
        "tgn:2369000",
        "tgn:1000001",
        "tgn:7012149",
        "tgn:2001858",
        "tgn:7007825",
        "tgn:7029392"
    ],
    "tgn:id":2369000,
    "tgn:name":"Gum Branch",
    "tgn:placetype":[
        "aat:300008699"
    ]
},
  "bbox": [],
  "geometry": {"coordinates":[-87.3333,36.0167],"type":"Point"}
}