{
  "id": 7520706,
  "type": "Feature",
  "properties": {
    "tgn:hierarchy":[
        "tgn:7520706",
        "tgn:7001242",
        "tgn:7016833",
        "tgn:7000124",
        "tgn:7029392"
    ],
    "tgn:id":7520706,
    "tgn:name:en":"Al Kawm al A\u1e29mar",
    "tgn:placetype":[
        "aat:300008347"
    ]
},
  "bbox": [],
  "geometry": {"coordinates":[31.383333,26.766667],"type":"Point"}
}