{
  "id": 2046065,
  "type": "Feature",
  "properties": {
    "tgn:hierarchy":[
        "tgn:2046065",
        "tgn:7013352",
        "tgn:7021987",
        "tgn:1000001",
        "tgn:7012149",
        "tgn:7007516",
        "tgn:7029392"
    ],
    "tgn:id":2046065,
    "tgn:name":"Fort McHenry",
    "tgn:placetype":[
        "aat:300008189",
        "aat:300007037",
        "aat:300386960",
        "aat:300006460",
        "aat:300386977",
        "aat:300008187",
        "aat:300386978",
        "aat:300008063",
        "aat:300006909",
        "aat:300000833"
    ]
},
  "bbox": [],
  "geometry": {"coordinates":[-76.5667,39.25],"type":"Point"}
}