{
  "id": 7047664,
  "type": "Feature",
  "properties": {
    "tgn:hierarchy":[
        "tgn:7047664",
        "tgn:1003440",
        "tgn:1000003",
        "tgn:7003124",
        "tgn:1000080",
        "tgn:7029392"
    ],
    "tgn:id":7047664,
    "tgn:name":"Cirlano",
    "tgn:placetype":[
        "aat:300008347"
    ]
},
  "bbox": [],
  "geometry": {"coordinates":[10.983333,46.633333],"type":"Point"}
}