{
  "id": 2689232,
  "type": "Feature",
  "properties": {
    "tgn:hierarchy":[
        "tgn:2689232",
        "tgn:7002659",
        "tgn:1000001",
        "tgn:7012149",
        "tgn:2000066",
        "tgn:7029392"
    ],
    "tgn:id":2689232,
    "tgn:name":"Squaw Creek",
    "tgn:placetype":[
        "aat:300008706"
    ]
},
  "bbox": [],
  "geometry": {"coordinates":[-87.4667,34.1167],"type":"Point"}
}