{
  "id": 2584805,
  "type": "Feature",
  "properties": {
    "tgn:hierarchy":[
        "tgn:2584805",
        "tgn:1000001",
        "tgn:7012149",
        "tgn:7007248",
        "tgn:7029392"
    ],
    "tgn:id":2584805,
    "tgn:name":"Pink Creek",
    "tgn:placetype":[
        "aat:300008706"
    ]
},
  "bbox": [],
  "geometry": {"coordinates":[-85.1167,33.4167],"type":"Point"}
}