{
  "id": 2352190,
  "type": "Feature",
  "properties": {
    "tgn:hierarchy":[
        "tgn:2352190",
        "tgn:1000001",
        "tgn:7012149",
        "tgn:1002468",
        "tgn:7007252",
        "tgn:7029392"
    ],
    "tgn:id":2352190,
    "tgn:name":"Glue Run",
    "tgn:placetype":[
        "aat:300008699"
    ]
},
  "bbox": [],
  "geometry": {"coordinates":[-85.2333,39.8667],"type":"Point"}
}