{
  "id": 2241488,
  "type": "Feature",
  "properties": {
    "tgn:hierarchy":[
        "tgn:2241488",
        "tgn:1000001",
        "tgn:7012149",
        "tgn:2001157",
        "tgn:7007522",
        "tgn:7029392"
    ],
    "tgn:id":2241488,
    "tgn:name":"Clark Towhead",
    "tgn:placetype":[
        "aat:300055621"
    ]
},
  "bbox": [],
  "geometry": {"coordinates":[-90.4167,34.75],"type":"Point"}
}