{
  "id": 2716380,
  "type": "Feature",
  "properties": {
    "tgn:hierarchy":[
        "tgn:2716380",
        "tgn:1000001",
        "tgn:1002359",
        "tgn:7012149",
        "tgn:7007517",
        "tgn:7029392"
    ],
    "tgn:id":2716380,
    "tgn:name":"The Five Sisters",
    "tgn:placetype":[
        "aat:300008791"
    ]
},
  "bbox": [],
  "geometry": {"coordinates":[-70.95,42.3667],"type":"Point"}
}