<<<<<<< HEAD
{
  "id": 7022125,
  "type": "Feature",
  "properties": {
    "tgn:hierarchy":[
        "tgn:7022125",
        "tgn:1000001",
        "tgn:7012149",
        "tgn:1002362",
        "tgn:7007919",
        "tgn:7029392"
    ],
    "tgn:id":7022125,
    "tgn:name":"Jones Point",
    "tgn:placetype":[
        "aat:300008850"
    ]
},
  "bbox": [],
  "geometry": {"coordinates":[-76.6667,37.7667],"type":"Point"}
}
=======
{"geometry":{"type":"Point","coordinates":[-76.666700,37.766700]},"type":"Feature","properties":{"hierarchy":["tgn:7022125","tgn:1000001","tgn:7012149","tgn:1002362","tgn:7007919","tgn:7029392"],"placetype":["aat:300008850"],"id":7022125,"name:xx":"Jones Point"}}
>>>>>>> 03f74aca74312dbeaf24d7e61306dd6a786dc3d0
