<<<<<<< HEAD
{
  "id": 7175513,
  "type": "Feature",
  "properties": {
    "tgn:hierarchy":[
        "tgn:7175513",
        "tgn:7000096",
        "tgn:1000003",
        "tgn:7000084",
        "tgn:7029392"
    ],
    "tgn:id":7175513,
    "tgn:name":"Gro\u00dfe Raben-Wiese",
    "tgn:placetype":[
        "aat:300386990"
    ]
},
  "bbox": [],
  "geometry": {"coordinates":[13.6,52.833333],"type":"Point"}
}
=======
{"geometry":{"type":"Point","coordinates":[13.600000,52.833333]},"type":"Feature","properties":{"hierarchy":["tgn:7175513","tgn:7000096","tgn:1000003","tgn:7000084","tgn:7029392"],"placetype":["aat:300386990"],"id":7175513,"name:xx":"Gro\u00dfe Raben-Wiese"}}
>>>>>>> 03f74aca74312dbeaf24d7e61306dd6a786dc3d0
