{
  "id": 7476061,
  "type": "Feature",
  "properties": {
    "tgn:hierarchy":[
        "tgn:7476061",
        "tgn:1000004",
        "tgn:7489179",
        "tgn:1000141",
        "tgn:7029392"
    ],
    "tgn:id":7476061,
    "tgn:name":"Wanchangchun Qiao",
    "tgn:placetype":[
        "aat:300007836"
    ]
},
  "bbox": [],
  "geometry": {"coordinates":[121.742311,24.685756],"type":"Point"}
}