{
  "id": 1096866,
  "type": "Feature",
  "properties": {
    "tgn:hierarchy":[
        "tgn:1096866",
        "tgn:7000490",
        "tgn:1000006",
        "tgn:7006238",
        "tgn:7029392"
    ],
    "tgn:id":1096866,
    "tgn:name":"Essendon",
    "tgn:placetype":[
        "aat:300008347",
        "aat:300265612"
    ]
},
  "bbox": [],
  "geometry": {"coordinates":[144.9167,-37.7667],"type":"Point"}
}