{
  "id": 7157819,
  "type": "Feature",
  "properties": {
    "tgn:hierarchy":[
        "tgn:7157819",
        "tgn:7000096",
        "tgn:1000003",
        "tgn:7000084",
        "tgn:7029392"
    ],
    "tgn:id":7157819,
    "tgn:name":"Kauels Berg",
    "tgn:placetype":[
        "aat:300008777"
    ]
},
  "bbox": [],
  "geometry": {"coordinates":[13.966667,53.116667],"type":"Point"}
}