{
  "id": 7433047,
  "type": "Feature",
  "properties": {
    "tgn:hierarchy":[
        "tgn:7433047",
        "tgn:1000001",
        "tgn:7005599",
        "tgn:7005560",
        "tgn:7029392"
    ],
    "tgn:id":7433047,
    "tgn:name":"Tocuila",
    "tgn:placetype":[
        "aat:300008347"
    ]
},
  "bbox": [],
  "geometry": {"coordinates":[-97.016667,18.95],"type":"Point"}
}