{
  "id": 2696009,
  "type": "Feature",
  "properties": {
    "tgn:hierarchy":[
        "tgn:2696009",
        "tgn:1000001",
        "tgn:7012149",
        "tgn:2001461",
        "tgn:7007568",
        "tgn:7029392"
    ],
    "tgn:id":2696009,
    "tgn:name":"Stockwell Mountain",
    "tgn:placetype":[
        "aat:300008798"
    ]
},
  "bbox": [],
  "geometry": {"coordinates":[-73.4667,44.1167],"type":"Point"}
}