<<<<<<< HEAD
{
  "id": 7246378,
  "type": "Feature",
  "properties": {
    "tgn:hierarchy":[
        "tgn:7246378",
        "tgn:7018238",
        "tgn:1000003",
        "tgn:1000063",
        "tgn:4012014",
        "tgn:7029392"
    ],
    "tgn:id":7246378,
    "tgn:name":"Cortil-Noirmont",
    "tgn:placetype":[
        "aat:300008347"
    ]
},
  "bbox": [],
  "geometry": {"coordinates":[4.65,50.583333],"type":"Point"}
}
=======
{"geometry":{"type":"Point","coordinates":[4.650000,50.583333]},"type":"Feature","properties":{"hierarchy":["tgn:7246378","tgn:7018238","tgn:1000003","tgn:1000063","tgn:4012014","tgn:7029392"],"placetype":["aat:300008347"],"id":7246378,"name:xx":"Cortil-Noirmont"}}
>>>>>>> 03f74aca74312dbeaf24d7e61306dd6a786dc3d0
