{
  "id": 2272369,
  "type": "Feature",
  "properties": {
    "tgn:hierarchy":[
        "tgn:2272369",
        "tgn:1002996",
        "tgn:1000001",
        "tgn:7012149",
        "tgn:7007711",
        "tgn:7029392"
    ],
    "tgn:id":2272369,
    "tgn:name":"Curtis Corner",
    "tgn:placetype":[
        "aat:300008347"
    ]
},
  "bbox": [],
  "geometry": {"coordinates":[-71.5167,41.45],"type":"Point"}
}