{
  "id": 2413429,
  "type": "Feature",
  "properties": {
    "tgn:hierarchy":[
        "tgn:2413429",
        "tgn:1000001",
        "tgn:7012149",
        "tgn:2002123",
        "tgn:7007827",
        "tgn:7029392"
    ],
    "tgn:id":2413429,
    "tgn:name":"Iosepa",
    "tgn:placetype":[
        "aat:300008347",
        "aat:300000810",
        "aat:300167671"
    ]
},
  "bbox": [],
  "geometry": {"coordinates":[-112.7333,40.5333],"type":"Point"}
}