{
  "id": 7329994,
  "type": "Feature",
  "properties": {
    "tgn:hierarchy":[
        "tgn:7329994",
        "tgn:7002803",
        "tgn:1001647",
        "tgn:1000003",
        "tgn:1000095",
        "tgn:7029392"
    ],
    "tgn:id":7329994,
    "tgn:name":"Huerta, Sierra de",
    "tgn:placetype":[
        "aat:300008795"
    ]
},
  "bbox": [],
  "geometry": {"coordinates":[-1.65,38.616667],"type":"Point"}
}