{
  "id": 2334882,
  "type": "Feature",
  "properties": {
    "tgn:hierarchy":[
        "tgn:2334882",
        "tgn:1000001",
        "tgn:2001178",
        "tgn:7012149",
        "tgn:7007523",
        "tgn:7029392"
    ],
    "tgn:id":2334882,
    "tgn:name":"Forked Hollow Cove",
    "tgn:placetype":[
        "aat:300132316"
    ]
},
  "bbox": [],
  "geometry": {"coordinates":[-92.6833,38.1667],"type":"Point"}
}