<<<<<<< HEAD
{
  "id": 7246662,
  "type": "Feature",
  "properties": {
    "tgn:hierarchy":[
        "tgn:7246662",
        "tgn:7003460",
        "tgn:1000003",
        "tgn:1000063",
        "tgn:4012014",
        "tgn:7029392"
    ],
    "tgn:id":7246662,
    "tgn:name":"Cabendes",
    "tgn:placetype":[
        "aat:300008347"
    ]
},
  "bbox": [],
  "geometry": {"coordinates":[5.281855,50.562621],"type":"Point"}
}
=======
{"geometry":{"type":"Point","coordinates":[5.281855,50.562621]},"type":"Feature","properties":{"hierarchy":["tgn:7246662","tgn:7003460","tgn:1000003","tgn:1000063","tgn:4012014","tgn:7029392"],"placetype":["aat:300008347"],"id":7246662,"name:xx":"Cabendes"}}
>>>>>>> 03f74aca74312dbeaf24d7e61306dd6a786dc3d0
