{
  "id": 2212196,
  "type": "Feature",
  "properties": {
    "tgn:hierarchy":[
        "tgn:2212196",
        "tgn:1000001",
        "tgn:7012149",
        "tgn:2002159",
        "tgn:7007919",
        "tgn:7029392"
    ],
    "tgn:id":2212196,
    "tgn:name":"Buzzard Rock",
    "tgn:placetype":[
        "aat:300008798"
    ]
},
  "bbox": [],
  "geometry": {"coordinates":[-78.1833,37.7833],"type":"Point"}
}