{
  "id": 2205453,
  "type": "Feature",
  "properties": {
    "tgn:hierarchy":[
        "tgn:2205453",
        "tgn:1000001",
        "tgn:7012149",
        "tgn:2001286",
        "tgn:7007524",
        "tgn:7029392"
    ],
    "tgn:id":2205453,
    "tgn:name":"Bull Creek",
    "tgn:placetype":[
        "aat:300008706"
    ]
},
  "bbox": [],
  "geometry": {"coordinates":[-115.55,48.5167],"type":"Point"}
}