{
  "id": 7176231,
  "type": "Feature",
  "properties": {
    "tgn:hierarchy":[
        "tgn:7176231",
        "tgn:7003669",
        "tgn:1000003",
        "tgn:7000084",
        "tgn:7029392"
    ],
    "tgn:id":7176231,
    "tgn:name":"Gresslbach",
    "tgn:placetype":[
        "aat:300000206"
    ]
},
  "bbox": [],
  "geometry": {"coordinates":[12.533333,48.683333],"type":"Point"}
}