{
  "id": 2705081,
  "type": "Feature",
  "properties": {
    "tgn:hierarchy":[
        "tgn:2705081",
        "tgn:1000001",
        "tgn:2001797",
        "tgn:7012149",
        "tgn:7007713",
        "tgn:7029392"
    ],
    "tgn:id":2705081,
    "tgn:name":"Sunshine Lake",
    "tgn:placetype":[
        "aat:300008680"
    ]
},
  "bbox": [],
  "geometry": {"coordinates":[-101.6333,44.05],"type":"Point"}
}