{
  "id": 2492189,
  "type": "Feature",
  "properties": {
    "tgn:hierarchy":[
        "tgn:2492189",
        "tgn:7002659",
        "tgn:1000001",
        "tgn:7012149",
        "tgn:2000060",
        "tgn:7029392"
    ],
    "tgn:id":2492189,
    "tgn:name":"Mardisville",
    "tgn:placetype":[
        "aat:300008347"
    ]
},
  "bbox": [],
  "geometry": {"coordinates":[-86.15,33.3833],"type":"Point"}
}