{
  "id": 7141275,
  "type": "Feature",
  "properties": {
    "tgn:hierarchy":[
        "tgn:7141275",
        "tgn:1000003",
        "tgn:7000094",
        "tgn:7000084",
        "tgn:7029392"
    ],
    "tgn:id":7141275,
    "tgn:name":"Malchow",
    "tgn:placetype":[
        "aat:300008347"
    ]
},
  "bbox": [],
  "geometry": {"coordinates":[11.766667,53.45],"type":"Point"}
}