{
  "id": 1011884,
  "type": "Feature",
  "properties": {
    "tgn:hierarchy":[
        "tgn:1011884",
        "tgn:7004576",
        "tgn:7018313",
        "tgn:1000001",
        "tgn:7004545",
        "tgn:7029392"
    ],
    "tgn:id":1011884,
    "tgn:name":"Folle Anse, Pointe de",
    "tgn:placetype":[
        "aat:300386846"
    ]
},
  "bbox": [],
  "geometry": {"coordinates":[-61.3333,15.95],"type":"Point"}
}