{
  "id": 2686068,
  "type": "Feature",
  "properties": {
    "tgn:hierarchy":[
        "tgn:2686068",
        "tgn:1000001",
        "tgn:7012149",
        "tgn:2000226",
        "tgn:7007158",
        "tgn:7029392"
    ],
    "tgn:id":2686068,
    "tgn:name":"Spring Canyon",
    "tgn:placetype":[
        "aat:300008761"
    ]
},
  "bbox": [],
  "geometry": {"coordinates":[-105.1833,40.5333],"type":"Point"}
}