{
  "id": 7340796,
  "type": "Feature",
  "properties": {
    "tgn:hierarchy":[
        "tgn:7340796",
        "tgn:7002839",
        "tgn:7001158",
        "tgn:1000003",
        "tgn:1000095",
        "tgn:7029392"
    ],
    "tgn:id":7340796,
    "tgn:name":"Caballar",
    "tgn:placetype":[
        "aat:300008347"
    ]
},
  "bbox": [],
  "geometry": {"coordinates":[-3.966667,41.116667],"type":"Point"}
}