<<<<<<< HEAD
{
  "id": 7353424,
  "type": "Feature",
  "properties": {
    "tgn:hierarchy":[
        "tgn:7353424",
        "tgn:7005584",
        "tgn:1000001",
        "tgn:7005560",
        "tgn:7029392"
    ],
    "tgn:id":7353424,
    "tgn:name":"Buenos Aires",
    "tgn:placetype":[
        "aat:300008347"
    ]
},
  "bbox": [],
  "geometry": {"coordinates":[-101.833333,20.383333],"type":"Point"}
}
=======
{"geometry":{"type":"Point","coordinates":[-101.833333,20.383333]},"type":"Feature","properties":{"hierarchy":["tgn:7353424","tgn:7005584","tgn:1000001","tgn:7005560","tgn:7029392"],"placetype":["aat:300008347"],"id":7353424,"name:xx":"Buenos Aires"}}
>>>>>>> 03f74aca74312dbeaf24d7e61306dd6a786dc3d0
