{
  "id": 7426264,
  "type": "Feature",
  "properties": {
    "tgn:hierarchy":[
        "tgn:7426264",
        "tgn:7005581",
        "tgn:1000001",
        "tgn:7005560",
        "tgn:7029392"
    ],
    "tgn:id":7426264,
    "tgn:name":"El Aguaje",
    "tgn:placetype":[
        "aat:300008347"
    ]
},
  "bbox": [],
  "geometry": {"coordinates":[-107.25,27.066667],"type":"Point"}
}