<<<<<<< HEAD
{
  "id": 7473805,
  "type": "Feature",
  "properties": {
    "tgn:hierarchy":[
        "tgn:7473805",
        "tgn:1000004",
        "tgn:7001014",
        "tgn:1000141",
        "tgn:7029392"
    ],
    "tgn:id":7473805,
    "tgn:name":"Tianliao",
    "tgn:placetype":[
        "aat:300008347"
    ]
},
  "bbox": [],
  "geometry": {"coordinates":[120.350359,23.768806],"type":"Point"}
}
=======
{"geometry":{"type":"Point","coordinates":[120.350359,23.768806]},"type":"Feature","properties":{"hierarchy":["tgn:7473805","tgn:1000004","tgn:7001014","tgn:1000141","tgn:7029392"],"placetype":["aat:300008347"],"id":7473805,"name:xx":"Tianliao"}}
>>>>>>> 03f74aca74312dbeaf24d7e61306dd6a786dc3d0
