{
  "id": 7473805,
  "type": "Feature",
  "properties": {
    "tgn:hierarchy":[
        "tgn:7473805",
        "tgn:1000004",
        "tgn:7001014",
        "tgn:1000141",
        "tgn:7029392"
    ],
    "tgn:id":7473805,
    "tgn:name":"Tianliao",
    "tgn:placetype":[
        "aat:300008347"
    ]
},
  "bbox": [],
  "geometry": {"coordinates":[120.350359,23.768806],"type":"Point"}
}