{
  "id": 7504547,
  "type": "Feature",
  "properties": {
    "tgn:hierarchy":[
        "tgn:7504547",
        "tgn:1008380",
        "tgn:7000507",
        "tgn:1000226",
        "tgn:1000006",
        "tgn:7029392"
    ],
    "tgn:id":7504547,
    "tgn:name:en":"Fertilizer Wharf",
    "tgn:placetype":[
        "aat:300120786"
    ]
},
  "bbox": [],
  "geometry": {"coordinates":[174.347222,-35.751389],"type":"Point"}
}