{
  "id": 2757469,
  "type": "Feature",
  "properties": {
    "tgn:hierarchy":[
        "tgn:2757469",
        "tgn:1000001",
        "tgn:7012149",
        "tgn:7007157",
        "tgn:1002828",
        "tgn:7029392"
    ],
    "tgn:id":2757469,
    "tgn:name":"West Berdoo Canyon",
    "tgn:placetype":[
        "aat:300008761"
    ]
},
  "bbox": [],
  "geometry": {"coordinates":[-116.1667,33.8333],"type":"Point"}
}