{
  "id": 2147705,
  "type": "Feature",
  "properties": {
    "tgn:hierarchy":[
        "tgn:2147705",
        "tgn:1000001",
        "tgn:7012149",
        "tgn:2001488",
        "tgn:7007709",
        "tgn:7029392"
    ],
    "tgn:id":2147705,
    "tgn:name":"Bare Hill",
    "tgn:placetype":[
        "aat:300008798"
    ]
},
  "bbox": [],
  "geometry": {"coordinates":[-75.65,35.2167],"type":"Point"}
}