{
  "id": 2688855,
  "type": "Feature",
  "properties": {
    "tgn:hierarchy":[
        "tgn:2688855",
        "tgn:1000001",
        "tgn:7012149",
        "tgn:2001914",
        "tgn:7007825",
        "tgn:7029392"
    ],
    "tgn:id":2688855,
    "tgn:name":"Spurgeon Hollow",
    "tgn:placetype":[
        "aat:300008761"
    ]
},
  "bbox": [],
  "geometry": {"coordinates":[-83.3333,35.8667],"type":"Point"}
}