<<<<<<< HEAD
{
  "id": 7242524,
  "type": "Feature",
  "properties": {
    "tgn:hierarchy":[
        "tgn:7242524",
        "tgn:7003460",
        "tgn:1000003",
        "tgn:1000063",
        "tgn:4012014",
        "tgn:7029392"
    ],
    "tgn:id":7242524,
    "tgn:name":"Lamine",
    "tgn:placetype":[
        "aat:300008347"
    ]
},
  "bbox": [],
  "geometry": {"coordinates":[5.334087,50.687448],"type":"Point"}
}
=======
{"geometry":{"type":"Point","coordinates":[5.334087,50.687448]},"type":"Feature","properties":{"hierarchy":["tgn:7242524","tgn:7003460","tgn:1000003","tgn:1000063","tgn:4012014","tgn:7029392"],"placetype":["aat:300008347"],"id":7242524,"name:xx":"Lamine"}}
>>>>>>> 03f74aca74312dbeaf24d7e61306dd6a786dc3d0
