{
  "id": 7242524,
  "type": "Feature",
  "properties": {
    "tgn:hierarchy":[
        "tgn:7242524",
        "tgn:7003460",
        "tgn:1000003",
        "tgn:1000063",
        "tgn:4012014",
        "tgn:7029392"
    ],
    "tgn:id":7242524,
    "tgn:name":"Lamine",
    "tgn:placetype":[
        "aat:300008347"
    ]
},
  "bbox": [],
  "geometry": {"coordinates":[5.334087,50.687448],"type":"Point"}
}