{
  "id": 7134667,
  "type": "Feature",
  "properties": {
    "tgn:hierarchy":[
        "tgn:7134667",
        "tgn:7000096",
        "tgn:1000003",
        "tgn:7000084",
        "tgn:7029392"
    ],
    "tgn:id":7134667,
    "tgn:name":"Nauener Stadtforst",
    "tgn:placetype":[
        "aat:300008863"
    ]
},
  "bbox": [],
  "geometry": {"coordinates":[12.966667,52.633333],"type":"Point"}
}