{
  "id": 2527961,
  "type": "Feature",
  "properties": {
    "tgn:hierarchy":[
        "tgn:2527961",
        "tgn:1002145",
        "tgn:1000001",
        "tgn:7012149",
        "tgn:7007157",
        "tgn:7029392"
    ],
    "tgn:id":2527961,
    "tgn:name":"Mountain Mine",
    "tgn:placetype":[
        "aat:300000390"
    ]
},
  "bbox": [],
  "geometry": {"coordinates":[-119.7667,38.5833],"type":"Point"}
}