<<<<<<< HEAD
{
  "id": 7489755,
  "type": "Feature",
  "properties": {
    "tgn:hierarchy":[
        "tgn:7489755",
        "tgn:1000004",
        "tgn:7467799",
        "tgn:1000141",
        "tgn:7029392"
    ],
    "tgn:id":7489755,
    "tgn:name":"Pitou Xiang",
    "tgn:placetype":[
        "aat:300387173"
    ]
},
  "bbox": [],
  "geometry": {"coordinates":[120.466667,23.883333],"type":"Point"}
}
=======
{"geometry":{"type":"Point","coordinates":[120.466667,23.883333]},"type":"Feature","properties":{"hierarchy":["tgn:7489755","tgn:1000004","tgn:7467799","tgn:1000141","tgn:7029392"],"placetype":["aat:300387173"],"id":7489755,"name:xx":"Pitou Xiang"}}
>>>>>>> 03f74aca74312dbeaf24d7e61306dd6a786dc3d0
