<<<<<<< HEAD
{
  "id": 7365497,
  "type": "Feature",
  "properties": {
    "tgn:hierarchy":[
        "tgn:7365497",
        "tgn:7005580",
        "tgn:1000001",
        "tgn:7005560",
        "tgn:7029392"
    ],
    "tgn:id":7365497,
    "tgn:name":"El Tabl\u00f3n, R\u00edo",
    "tgn:placetype":[
        "aat:300008699"
    ]
},
  "bbox": [],
  "geometry": {"coordinates":[-93.483333,16.383333],"type":"Point"}
}
=======
{"geometry":{"type":"Point","coordinates":[-93.483333,16.383333]},"type":"Feature","properties":{"hierarchy":["tgn:7365497","tgn:7005580","tgn:1000001","tgn:7005560","tgn:7029392"],"placetype":["aat:300008699"],"id":7365497,"name:xx":"El Tabl\u00f3n, R\u00edo"}}
>>>>>>> 03f74aca74312dbeaf24d7e61306dd6a786dc3d0
