{
  "id": 7191647,
  "type": "Feature",
  "properties": {
    "tgn:hierarchy":[
        "tgn:7191647",
        "tgn:7003669",
        "tgn:1000003",
        "tgn:7000084",
        "tgn:7029392"
    ],
    "tgn:id":7191647,
    "tgn:name":"Farren Berg",
    "tgn:placetype":[
        "aat:300008795"
    ]
},
  "bbox": [],
  "geometry": {"coordinates":[13.55,48.95],"type":"Point"}
}