{
  "id": 1125718,
  "type": "Feature",
  "properties": {
    "tgn:hierarchy":[
        "tgn:1125718",
        "tgn:7001242",
        "tgn:1000155",
        "tgn:7029392"
    ],
    "tgn:id":1125718,
    "tgn:name":"Kotto",
    "tgn:placetype":[
        "aat:300008707"
    ]
},
  "bbox": [],
  "geometry": {"coordinates":[22.0333,4.2333],"type":"Point"}
}