{
  "id": 7019056,
  "type": "Feature",
  "properties": {
    "tgn:hierarchy":[
        "tgn:7019056",
        "tgn:7002445",
        "tgn:1000003",
        "tgn:7008591",
        "tgn:7029392"
    ],
    "tgn:id":7019056,
    "tgn:name:en":"Kingston upon Hull",
    "tgn:placetype":[
        "aat:300387064",
        "aat:300387145",
        "aat:300387071"
    ]
},
  "bbox": [],
  "geometry": {"coordinates":[-0.3333,53.75],"type":"Point"}
}