{
  "id": 7557915,
  "type": "Feature",
  "properties": {
    "tgn:hierarchy":[
        "tgn:7557915",
        "tgn:1000004",
        "tgn:7000198",
        "tgn:1001894",
        "tgn:7029392"
    ],
    "tgn:id":7557915,
    "tgn:name:en":"S\u0101ng\u0101kher\u0101",
    "tgn:placetype":[
        "aat:300008347"
    ]
},
  "bbox": [],
  "geometry": {"coordinates":[77.814016,22.794753],"type":"Point"}
}