<<<<<<< HEAD
{
  "id": 7359103,
  "type": "Feature",
  "properties": {
    "tgn:hierarchy":[
        "tgn:7359103",
        "tgn:1000001",
        "tgn:1001906",
        "tgn:7005560",
        "tgn:7029392"
    ],
    "tgn:id":7359103,
    "tgn:name":"Colorin, Cerro",
    "tgn:placetype":[
        "aat:300008795"
    ]
},
  "bbox": [],
  "geometry": {"coordinates":[-105.033333,21.416667],"type":"Point"}
}
=======
{"geometry":{"type":"Point","coordinates":[-105.033333,21.416667]},"type":"Feature","properties":{"hierarchy":["tgn:7359103","tgn:1000001","tgn:1001906","tgn:7005560","tgn:7029392"],"placetype":["aat:300008795"],"id":7359103,"name:xx":"Colorin, Cerro"}}
>>>>>>> 03f74aca74312dbeaf24d7e61306dd6a786dc3d0
