{
  "id": 2674032,
  "type": "Feature",
  "properties": {
    "tgn:hierarchy":[
        "tgn:2674032",
        "tgn:1000001",
        "tgn:2001413",
        "tgn:7012149",
        "tgn:7007526",
        "tgn:7029392"
    ],
    "tgn:id":2674032,
    "tgn:name":"Snow Water Canyon",
    "tgn:placetype":[
        "aat:300008761"
    ]
},
  "bbox": [],
  "geometry": {"coordinates":[-116.5667,39.7333],"type":"Point"}
}