{
  "id": 2445518,
  "type": "Feature",
  "properties": {
    "tgn:hierarchy":[
        "tgn:2445518",
        "tgn:1000001",
        "tgn:7012149",
        "tgn:2002332",
        "tgn:7007922",
        "tgn:7029392"
    ],
    "tgn:id":2445518,
    "tgn:name":"Leo V Mine",
    "tgn:placetype":[
        "aat:300000390"
    ]
},
  "bbox": [],
  "geometry": {"coordinates":[-90.35,42.65],"type":"Point"}
}