{
  "id": 7548759,
  "type": "Feature",
  "properties": {
    "tgn:hierarchy":[
        "tgn:7548759",
        "tgn:1000004",
        "tgn:7000198",
        "tgn:7000799",
        "tgn:7029392"
    ],
    "tgn:id":7548759,
    "tgn:name:en":"Deshkit",
    "tgn:placetype":[
        "aat:300008347"
    ]
},
  "bbox": [],
  "geometry": {"coordinates":[77.552538,34.549493],"type":"Point"}
}