<<<<<<< HEAD
{
  "id": 2403673,
  "type": "Feature",
  "properties": {
    "tgn:hierarchy":[
        "tgn:2403673",
        "tgn:7006450",
        "tgn:1000001",
        "tgn:7012149",
        "tgn:2000089",
        "tgn:7029392"
    ],
    "tgn:id":2403673,
    "tgn:name":"Howard Lake",
    "tgn:placetype":[
        "aat:300008680"
    ]
},
  "bbox": [],
  "geometry": {"coordinates":[-147.7333,66.6167],"type":"Point"}
}
=======
{"geometry":{"type":"Point","coordinates":[-147.733300,66.616700]},"type":"Feature","properties":{"hierarchy":["tgn:2403673","tgn:7006450","tgn:1000001","tgn:7012149","tgn:2000089","tgn:7029392"],"placetype":["aat:300008680"],"id":2403673,"name:xx":"Howard Lake"}}
>>>>>>> 03f74aca74312dbeaf24d7e61306dd6a786dc3d0
