{
  "id": 2148400,
  "type": "Feature",
  "properties": {
    "tgn:hierarchy":[
        "tgn:2148400",
        "tgn:1000001",
        "tgn:1002359",
        "tgn:7012149",
        "tgn:7007517",
        "tgn:7029392"
    ],
    "tgn:id":2148400,
    "tgn:name":"Barn Rocks",
    "tgn:placetype":[
        "aat:300132348"
    ]
},
  "bbox": [],
  "geometry": {"coordinates":[-70.6833,42.65],"type":"Point"}
}