{
  "id": 2607650,
  "type": "Feature",
  "properties": {
    "tgn:hierarchy":[
        "tgn:2607650",
        "tgn:1000001",
        "tgn:1002272",
        "tgn:7012149",
        "tgn:7007710",
        "tgn:7029392"
    ],
    "tgn:id":2607650,
    "tgn:name":"Rapp Run",
    "tgn:placetype":[
        "aat:300008699"
    ]
},
  "bbox": [],
  "geometry": {"coordinates":[-79.3833,41.25],"type":"Point"}
}