{
  "id": 2141635,
  "type": "Feature",
  "properties": {
    "tgn:hierarchy":[
        "tgn:2141635",
        "tgn:1000001",
        "tgn:7006451",
        "tgn:2000092",
        "tgn:7012149",
        "tgn:7029392"
    ],
    "tgn:id":2141635,
    "tgn:name":"Baah Lokaa Ridge",
    "tgn:placetype":[
        "aat:300266640"
    ]
},
  "bbox": [],
  "geometry": {"coordinates":[-111.2833,35.65],"type":"Point"}
}