{
  "id": 2124989,
  "type": "Feature",
  "properties": {
    "tgn:hierarchy":[
        "tgn:2124989",
        "tgn:7006450",
        "tgn:1000001",
        "tgn:7012149",
        "tgn:2000088",
        "tgn:7029392"
    ],
    "tgn:id":2124989,
    "tgn:name":"Abraham Islands",
    "tgn:placetype":[
        "aat:300386853"
    ]
},
  "bbox": [],
  "geometry": {"coordinates":[-132.6667,56.05],"type":"Point"}
}