{
  "id": 2213602,
  "type": "Feature",
  "properties": {
    "tgn:hierarchy":[
        "tgn:2213602",
        "tgn:1000001",
        "tgn:2000462",
        "tgn:7012149",
        "tgn:7007250",
        "tgn:7029392"
    ],
    "tgn:id":2213602,
    "tgn:name":"Caboose Creek",
    "tgn:placetype":[
        "aat:300008706"
    ]
},
  "bbox": [],
  "geometry": {"coordinates":[-116.15,48.6167],"type":"Point"}
}