{
  "id": 2209398,
  "type": "Feature",
  "properties": {
    "tgn:hierarchy":[
        "tgn:2209398",
        "tgn:1000001",
        "tgn:7012149",
        "tgn:7007523",
        "tgn:7029392"
    ],
    "tgn:id":2209398,
    "tgn:name":"Burnt Shirt Branch",
    "tgn:placetype":[
        "aat:300008699"
    ]
},
  "bbox": [],
  "geometry": {"coordinates":[-91.95,40.5833],"type":"Point"}
}