{
  "id": 2539646,
  "type": "Feature",
  "properties": {
    "tgn:hierarchy":[
        "tgn:2539646",
        "tgn:2001728",
        "tgn:1000001",
        "tgn:7012149",
        "tgn:7007712",
        "tgn:7029392"
    ],
    "tgn:id":2539646,
    "tgn:name":"New Salem",
    "tgn:placetype":[
        "aat:300008347"
    ]
},
  "bbox": [],
  "geometry": {"coordinates":[-82.7167,34.55],"type":"Point"}
}