{
  "id": 1052740,
  "type": "Feature",
  "properties": {
    "tgn:hierarchy":[
        "tgn:1052740",
        "tgn:1000003",
        "tgn:7011661",
        "tgn:7006660",
        "tgn:7029392"
    ],
    "tgn:id":1052740,
    "tgn:name":"Berezan",
    "tgn:placetype":[
        "aat:300008347"
    ]
},
  "bbox": [],
  "geometry": {"coordinates":[31.5333,50.3833],"type":"Point"}
}