{
  "id": 7235887,
  "type": "Feature",
  "properties": {
    "tgn:hierarchy":[
        "tgn:7235887",
        "tgn:7011167",
        "tgn:7001338",
        "tgn:1000003",
        "tgn:1000074",
        "tgn:7029392"
    ],
    "tgn:id":7235887,
    "tgn:name":"\u00c1yios Ye\u00f3ryios, \u00c1kra",
    "tgn:placetype":[
        "aat:300008850"
    ]
},
  "bbox": [],
  "geometry": {"coordinates":[20.433333,38.166667],"type":"Point"}
}