{
  "id": 7470293,
  "type": "Feature",
  "properties": {
    "tgn:hierarchy":[
        "tgn:7470293",
        "tgn:7488858",
        "tgn:1000004",
        "tgn:1000141",
        "tgn:7029392"
    ],
    "tgn:id":7470293,
    "tgn:name":"Zhuzijiao",
    "tgn:placetype":[
        "aat:300008347"
    ]
},
  "bbox": [],
  "geometry": {"coordinates":[120.855452,23.761829],"type":"Point"}
}