{
  "id": 7453954,
  "type": "Feature",
  "properties": {
    "tgn:hierarchy":[
        "tgn:7453954",
        "tgn:7002445",
        "tgn:1000003",
        "tgn:7012032",
        "tgn:7008591",
        "tgn:7029392"
    ],
    "tgn:id":7453954,
    "tgn:name:en":"Chillington",
    "tgn:placetype":[
        "aat:300008347"
    ]
},
  "bbox": [],
  "geometry": {"coordinates":[-2.866667,50.883333],"type":"Point"}
}