<<<<<<< HEAD
{
  "id": 2256369,
  "type": "Feature",
  "properties": {
    "tgn:hierarchy":[
        "tgn:2256369",
        "tgn:1000001",
        "tgn:7012149",
        "tgn:2000965",
        "tgn:7007520",
        "tgn:7029392"
    ],
    "tgn:id":2256369,
    "tgn:name":"Coppler Creek",
    "tgn:placetype":[
        "aat:300008706"
    ]
},
  "bbox": [],
  "geometry": {"coordinates":[-83.4667,44.4667],"type":"Point"}
}
=======
{"geometry":{"type":"Point","coordinates":[-83.466700,44.466700]},"type":"Feature","properties":{"hierarchy":["tgn:2256369","tgn:1000001","tgn:7012149","tgn:2000965","tgn:7007520","tgn:7029392"],"placetype":["aat:300008706"],"id":2256369,"name:xx":"Coppler Creek"}}
>>>>>>> 03f74aca74312dbeaf24d7e61306dd6a786dc3d0
