{
  "id": 7442605,
  "type": "Feature",
  "properties": {
    "tgn:hierarchy":[
        "tgn:7442605",
        "tgn:7002445",
        "tgn:1000003",
        "tgn:7008160",
        "tgn:7008591",
        "tgn:7029392"
    ],
    "tgn:id":7442605,
    "tgn:name:en":"Caister Shoal",
    "tgn:placetype":[
        "aat:300387036"
    ]
},
  "bbox": [],
  "geometry": {"coordinates":[1.75,52.666667],"type":"Point"}
}