{
  "id": 2100888,
  "type": "Feature",
  "properties": {
    "tgn:hierarchy":[
        "tgn:2100888",
        "tgn:1000001",
        "tgn:7012149",
        "tgn:2001895",
        "tgn:7007825",
        "tgn:7029392"
    ],
    "tgn:id":2100888,
    "tgn:name":"Ostella",
    "tgn:placetype":[
        "aat:300008347"
    ]
},
  "bbox": [],
  "geometry": {"coordinates":[-86.7833,35.3167],"type":"Point"}
}