<<<<<<< HEAD
{
  "id": 2251822,
  "type": "Feature",
  "properties": {
    "tgn:hierarchy":[
        "tgn:2251822",
        "tgn:1000001",
        "tgn:7006451",
        "tgn:7012149",
        "tgn:2000103",
        "tgn:7029392"
    ],
    "tgn:id":2251822,
    "tgn:name":"Comstock-Dexter Mine",
    "tgn:placetype":[
        "aat:300000390"
    ]
},
  "bbox": [],
  "geometry": {"coordinates":[-113.2,34.6167],"type":"Point"}
}
=======
{"geometry":{"type":"Point","coordinates":[-113.200000,34.616700]},"type":"Feature","properties":{"hierarchy":["tgn:2251822","tgn:1000001","tgn:7006451","tgn:7012149","tgn:2000103","tgn:7029392"],"placetype":["aat:300000390"],"id":2251822,"name:xx":"Comstock-Dexter Mine"}}
>>>>>>> 03f74aca74312dbeaf24d7e61306dd6a786dc3d0
