{
  "id": 2031917,
  "type": "Feature",
  "properties": {
    "tgn:hierarchy":[
        "tgn:2031917",
        "tgn:1002143",
        "tgn:1000001",
        "tgn:7012149",
        "tgn:7007252",
        "tgn:7029392"
    ],
    "tgn:id":2031917,
    "tgn:name":"Gar Creek",
    "tgn:placetype":[
        "aat:300387210",
        "aat:300008707"
    ]
},
  "bbox": [],
  "geometry": {"coordinates":[-84.9333,41.0833],"type":"Point"}
}