{
  "id": 7014028,
  "type": "Feature",
  "properties": {
    "tgn:hierarchy":[
        "tgn:7014028",
        "tgn:1000001",
        "tgn:7014090",
        "tgn:7012149",
        "tgn:7007565",
        "tgn:7029392"
    ],
    "tgn:id":7014028,
    "tgn:name":"Freehold",
    "tgn:placetype":[
        "aat:300008347"
    ]
},
  "bbox": [],
  "geometry": {"coordinates":[-74.2667,40.25],"type":"Point"}
}