<<<<<<< HEAD
{
  "id": 2405120,
  "type": "Feature",
  "properties": {
    "tgn:hierarchy":[
        "tgn:2405120",
        "tgn:1000001",
        "tgn:7012149",
        "tgn:2001983",
        "tgn:7007826",
        "tgn:7029392"
    ],
    "tgn:id":2405120,
    "tgn:name":"Hudsonville",
    "tgn:placetype":[
        "aat:300008347"
    ]
},
  "bbox": [],
  "geometry": {"coordinates":[-96.0333,33.7],"type":"Point"}
}
=======
{"geometry":{"type":"Point","coordinates":[-96.033300,33.700000]},"type":"Feature","properties":{"hierarchy":["tgn:2405120","tgn:1000001","tgn:7012149","tgn:2001983","tgn:7007826","tgn:7029392"],"placetype":["aat:300008347"],"id":2405120,"name:xx":"Hudsonville"}}
>>>>>>> 03f74aca74312dbeaf24d7e61306dd6a786dc3d0
