{
  "id": 2238340,
  "type": "Feature",
  "properties": {
    "tgn:hierarchy":[
        "tgn:2238340",
        "tgn:7002659",
        "tgn:1000001",
        "tgn:2000011",
        "tgn:7012149",
        "tgn:7029392"
    ],
    "tgn:id":2238340,
    "tgn:name":"Choctaw County School Lake",
    "tgn:placetype":[
        "aat:300006191"
    ]
},
  "bbox": [],
  "geometry": {"coordinates":[-87.2333,32.0667],"type":"Point"}
}