<<<<<<< HEAD
{
  "id": 7114088,
  "type": "Feature",
  "properties": {
    "tgn:hierarchy":[
        "tgn:7114088",
        "tgn:1000003",
        "tgn:7003689",
        "tgn:7000084",
        "tgn:7029392"
    ],
    "tgn:id":7114088,
    "tgn:name":"Roda",
    "tgn:placetype":[
        "aat:300008347"
    ]
},
  "bbox": [],
  "geometry": {"coordinates":[10.9,50.7],"type":"Point"}
}
=======
{"geometry":{"type":"Point","coordinates":[10.900000,50.700000]},"type":"Feature","properties":{"hierarchy":["tgn:7114088","tgn:1000003","tgn:7003689","tgn:7000084","tgn:7029392"],"placetype":["aat:300008347"],"id":7114088,"name:xx":"Roda"}}
>>>>>>> 03f74aca74312dbeaf24d7e61306dd6a786dc3d0
