<<<<<<< HEAD
{
  "id": 2153530,
  "type": "Feature",
  "properties": {
    "tgn:hierarchy":[
        "tgn:2153530",
        "tgn:1000001",
        "tgn:7012149",
        "tgn:2000278",
        "tgn:7007240",
        "tgn:7029392"
    ],
    "tgn:id":2153530,
    "tgn:name":"Bear Bay",
    "tgn:placetype":[
        "aat:300008905"
    ]
},
  "bbox": [],
  "geometry": {"coordinates":[-84.9333,30.1],"type":"Point"}
}
=======
{"geometry":{"type":"Point","coordinates":[-84.933300,30.100000]},"type":"Feature","properties":{"hierarchy":["tgn:2153530","tgn:1000001","tgn:7012149","tgn:2000278","tgn:7007240","tgn:7029392"],"placetype":["aat:300008905"],"id":2153530,"name:xx":"Bear Bay"}}
>>>>>>> 03f74aca74312dbeaf24d7e61306dd6a786dc3d0
