{
  "id": 2379311,
  "type": "Feature",
  "properties": {
    "tgn:hierarchy":[
        "tgn:2379311",
        "tgn:1000001",
        "tgn:7012149",
        "tgn:2002191",
        "tgn:7007919",
        "tgn:7029392"
    ],
    "tgn:id":2379311,
    "tgn:name":"Harvel Creek",
    "tgn:placetype":[
        "aat:300008706"
    ]
},
  "bbox": [],
  "geometry": {"coordinates":[-81.25,36.75],"type":"Point"}
}