{
  "id": 7571226,
  "type": "Feature",
  "properties": {
    "tgn:hierarchy":[
        "tgn:7571226",
        "tgn:1000004",
        "tgn:7031781",
        "tgn:7000198",
        "tgn:7029392"
    ],
    "tgn:id":7571226,
    "tgn:name:en":"Ghungar\u012b",
    "tgn:placetype":[
        "aat:300008347"
    ]
},
  "bbox": [],
  "geometry": {"coordinates":[82.933333,22.483333],"type":"Point"}
}