{
  "id": 7034889,
  "type": "Feature",
  "properties": {
    "tgn:hierarchy":[
        "tgn:7034889",
        "tgn:1003500",
        "tgn:1000003",
        "tgn:7010380",
        "tgn:1000080",
        "tgn:7029392"
    ],
    "tgn:id":7034889,
    "tgn:name":"Casa Galeone",
    "tgn:placetype":[
        "aat:300008347"
    ]
},
  "bbox": [],
  "geometry": {"coordinates":[17.268611,40.485278],"type":"Point"}
}