{
  "id": 7068016,
  "type": "Feature",
  "properties": {
    "tgn:hierarchy":[
        "tgn:7068016",
        "tgn:7003669",
        "tgn:1000003",
        "tgn:7000084",
        "tgn:7029392"
    ],
    "tgn:id":7068016,
    "tgn:name":"Trobelsdorf",
    "tgn:placetype":[
        "aat:300008347"
    ]
},
  "bbox": [],
  "geometry": {"coordinates":[12.55,49.35],"type":"Point"}
}