{
  "id": 2291526,
  "type": "Feature",
  "properties": {
    "tgn:hierarchy":[
        "tgn:2291526",
        "tgn:1000001",
        "tgn:7012149",
        "tgn:7007825",
        "tgn:7029392"
    ],
    "tgn:id":2291526,
    "tgn:name":"Dollar Creek",
    "tgn:placetype":[
        "aat:300008706"
    ]
},
  "bbox": [],
  "geometry": {"coordinates":[-88.3833,35.2667],"type":"Point"}
}