<<<<<<< HEAD
{
  "id": 7028195,
  "type": "Feature",
  "properties": {
    "tgn:hierarchy":[
        "tgn:7028195",
        "tgn:7002445",
        "tgn:1000003",
        "tgn:7008157",
        "tgn:7008591",
        "tgn:7029392"
    ],
    "tgn:id":7028195,
    "tgn:name:en":"Welby",
    "tgn:placetype":[
        "aat:300008347",
        "aat:300008372"
    ]
},
  "bbox": [],
  "geometry": {"coordinates":[-0.55,52.916667],"type":"Point"}
}
=======
{"geometry":{"type":"Point","coordinates":[-0.550000,52.916667]},"type":"Feature","properties":{"hierarchy":["tgn:7028195","tgn:7002445","tgn:1000003","tgn:7008157","tgn:7008591","tgn:7029392"],"placetype":["aat:300008347","aat:300008372"],"name:en":"Welby","id":7028195}}
>>>>>>> 03f74aca74312dbeaf24d7e61306dd6a786dc3d0
