{
  "id": 7376043,
  "type": "Feature",
  "properties": {
    "tgn:hierarchy":[
        "tgn:7376043",
        "tgn:1000001",
        "tgn:1001960",
        "tgn:7005560",
        "tgn:7029392"
    ],
    "tgn:id":7376043,
    "tgn:name":"Rancho La Reforma",
    "tgn:placetype":[
        "aat:300000241"
    ]
},
  "bbox": [],
  "geometry": {"coordinates":[-110.25,30.033333],"type":"Point"}
}