{
  "id": 7344240,
  "type": "Feature",
  "properties": {
    "tgn:hierarchy":[
        "tgn:7344240",
        "tgn:7002810",
        "tgn:7001158",
        "tgn:1000003",
        "tgn:1000095",
        "tgn:7029392"
    ],
    "tgn:id":7344240,
    "tgn:name":"Barrio de D\u00edaz Ruiz",
    "tgn:placetype":[
        "aat:300008347"
    ]
},
  "bbox": [],
  "geometry": {"coordinates":[-3.35,42.65],"type":"Point"}
}