{
  "id": 2177493,
  "type": "Feature",
  "properties": {
    "tgn:hierarchy":[
        "tgn:2177493",
        "tgn:1000001",
        "tgn:7012149",
        "tgn:7019676",
        "tgn:7007566",
        "tgn:7029392"
    ],
    "tgn:id":2177493,
    "tgn:name":"Black Rock Reservoir",
    "tgn:placetype":[
        "aat:300006191"
    ]
},
  "bbox": [],
  "geometry": {"coordinates":[-108.7667,35.0833],"type":"Point"}
}