{
  "id": 1120380,
  "type": "Feature",
  "properties": {
    "tgn:hierarchy":[
        "tgn:1120380",
        "tgn:1001945",
        "tgn:1000047",
        "tgn:7002457",
        "tgn:1000002",
        "tgn:7029392"
    ],
    "tgn:id":1120380,
    "tgn:name":"Rio Sorocaba, Repr\u00easa do",
    "tgn:placetype":[
        "aat:300006191"
    ]
},
  "bbox": [],
  "geometry": {"coordinates":[-47.2667,-23.6167],"type":"Point"}
}