{
  "id": 7088568,
  "type": "Feature",
  "properties": {
    "tgn:hierarchy":[
        "tgn:7088568",
        "tgn:7003669",
        "tgn:1000003",
        "tgn:7000084",
        "tgn:7029392"
    ],
    "tgn:id":7088568,
    "tgn:name":"Walpertshofen",
    "tgn:placetype":[
        "aat:300008347"
    ]
},
  "bbox": [],
  "geometry": {"coordinates":[11.433333,48.283333],"type":"Point"}
}