{
  "id": 2046659,
  "type": "Feature",
  "properties": {
    "tgn:hierarchy":[
        "tgn:2046659",
        "tgn:1000001",
        "tgn:1002539",
        "tgn:7012149",
        "tgn:7007516",
        "tgn:7029392"
    ],
    "tgn:id":2046659,
    "tgn:name":"Cliffs City",
    "tgn:placetype":[
        "aat:300008347"
    ]
},
  "bbox": [],
  "geometry": {"coordinates":[-76.15,39.1167],"type":"Point"}
}