{
  "id": 7149809,
  "type": "Feature",
  "properties": {
    "tgn:hierarchy":[
        "tgn:7149809",
        "tgn:7003669",
        "tgn:1000003",
        "tgn:7000084",
        "tgn:7029392"
    ],
    "tgn:id":7149809,
    "tgn:name":"Kronungen",
    "tgn:placetype":[
        "aat:300008347"
    ]
},
  "bbox": [],
  "geometry": {"coordinates":[10.15,50.083333],"type":"Point"}
}