{
  "id": 7318072,
  "type": "Feature",
  "properties": {
    "tgn:hierarchy":[
        "tgn:7318072",
        "tgn:1001768",
        "tgn:1000049",
        "tgn:1000002",
        "tgn:7029392"
    ],
    "tgn:id":7318072,
    "tgn:name":"Corrales de la Chupalla",
    "tgn:placetype":[
        "aat:300387200"
    ]
},
  "bbox": [],
  "geometry": {"coordinates":[-70.566667,-32.316667],"type":"Point"}
}