{
  "id": 2219157,
  "type": "Feature",
  "properties": {
    "tgn:hierarchy":[
        "tgn:2219157",
        "tgn:1000001",
        "tgn:7012149",
        "tgn:2001516",
        "tgn:7007709",
        "tgn:7029392"
    ],
    "tgn:id":2219157,
    "tgn:name":"Caney Fork",
    "tgn:placetype":[
        "aat:300008699"
    ]
},
  "bbox": [],
  "geometry": {"coordinates":[-82.7167,35.75],"type":"Point"}
}