{
  "id": 2701199,
  "type": "Feature",
  "properties": {
    "tgn:hierarchy":[
        "tgn:2701199",
        "tgn:1002153",
        "tgn:1000001",
        "tgn:7012149",
        "tgn:7007710",
        "tgn:7029392"
    ],
    "tgn:id":2701199,
    "tgn:name":"Sugar Hollow",
    "tgn:placetype":[
        "aat:300008761"
    ]
},
  "bbox": [],
  "geometry": {"coordinates":[-79.5333,40.5833],"type":"Point"}
}