{
  "id": 2452173,
  "type": "Feature",
  "properties": {
    "tgn:hierarchy":[
        "tgn:2452173",
        "tgn:1000001",
        "tgn:7016172",
        "tgn:7012149",
        "tgn:2000130",
        "tgn:7029392"
    ],
    "tgn:id":2452173,
    "tgn:name":"Little Blakely Creek",
    "tgn:placetype":[
        "aat:300008706"
    ]
},
  "bbox": [],
  "geometry": {"coordinates":[-93.0833,34.6667],"type":"Point"}
}