{
  "id": 2549053,
  "type": "Feature",
  "properties": {
    "tgn:hierarchy":[
        "tgn:2549053",
        "tgn:1000001",
        "tgn:7012149",
        "tgn:2001861",
        "tgn:7007825",
        "tgn:7029392"
    ],
    "tgn:id":2549053,
    "tgn:name":"North Prong Horse Creek",
    "tgn:placetype":[
        "aat:300008706"
    ]
},
  "bbox": [],
  "geometry": {"coordinates":[-84.9167,36.2667],"type":"Point"}
}