{
  "id": 7501099,
  "type": "Feature",
  "properties": {
    "tgn:hierarchy":[
        "tgn:7501099",
        "tgn:7488858",
        "tgn:1000004",
        "tgn:1000141",
        "tgn:7029392"
    ],
    "tgn:id":7501099,
    "tgn:name":"Minhe Qiao",
    "tgn:placetype":[
        "aat:300007836"
    ]
},
  "bbox": [],
  "geometry": {"coordinates":[120.866111,23.5625],"type":"Point"}
}