{
  "id": 2248169,
  "type": "Feature",
  "properties": {
    "tgn:hierarchy":[
        "tgn:2248169",
        "tgn:1000001",
        "tgn:7012149",
        "tgn:7007157",
        "tgn:1002566",
        "tgn:7029392"
    ],
    "tgn:id":2248169,
    "tgn:name":"Cold Creek",
    "tgn:placetype":[
        "aat:300008706"
    ]
},
  "bbox": [],
  "geometry": {"coordinates":[-122.7333,39.4667],"type":"Point"}
}