{
  "id": 7485786,
  "type": "Feature",
  "properties": {
    "tgn:hierarchy":[
        "tgn:7485786",
        "tgn:1000004",
        "tgn:7001014",
        "tgn:1000141",
        "tgn:7029392"
    ],
    "tgn:id":7485786,
    "tgn:name":"Shikeng",
    "tgn:placetype":[
        "aat:300008347"
    ]
},
  "bbox": [],
  "geometry": {"coordinates":[120.601111,23.665833],"type":"Point"}
}