{
  "id": 2539259,
  "type": "Feature",
  "properties": {
    "tgn:hierarchy":[
        "tgn:2539259",
        "tgn:1000001",
        "tgn:7012149",
        "tgn:2000894",
        "tgn:7007256",
        "tgn:7029392"
    ],
    "tgn:id":2539259,
    "tgn:name":"New Hope",
    "tgn:placetype":[
        "aat:300008347"
    ]
},
  "bbox": [],
  "geometry": {"coordinates":[-93.4167,32.1333],"type":"Point"}
}