{
  "id": 1102382,
  "type": "Feature",
  "properties": {
    "tgn:hierarchy":[
        "tgn:1102382",
        "tgn:1000001",
        "tgn:7012149",
        "tgn:1002562",
        "tgn:7007251",
        "tgn:7029392"
    ],
    "tgn:id":1102382,
    "tgn:name":"Matthiessen State Park",
    "tgn:placetype":[
        "aat:300008192"
    ]
},
  "bbox": [],
  "geometry": {"coordinates":[-89.0167,41.2833],"type":"Point"}
}