{
  "id": 2268401,
  "type": "Feature",
  "properties": {
    "tgn:hierarchy":[
        "tgn:2268401",
        "tgn:1000001",
        "tgn:7012149",
        "tgn:1002876",
        "tgn:7007710",
        "tgn:7029392"
    ],
    "tgn:id":2268401,
    "tgn:name":"Crooked Run",
    "tgn:placetype":[
        "aat:300008699"
    ]
},
  "bbox": [],
  "geometry": {"coordinates":[-76.2667,40.8833],"type":"Point"}
}