<<<<<<< HEAD
{
  "id": 2152337,
  "type": "Feature",
  "properties": {
    "tgn:hierarchy":[
        "tgn:2152337",
        "tgn:7006450",
        "tgn:1000001",
        "tgn:7012149",
        "tgn:2000082",
        "tgn:7029392"
    ],
    "tgn:id":2152337,
    "tgn:name":"Bay Islands",
    "tgn:placetype":[
        "aat:300386853"
    ]
},
  "bbox": [],
  "geometry": {"coordinates":[-132.8167,54.8333],"type":"Point"}
}
=======
{"geometry":{"type":"Point","coordinates":[-132.816700,54.833300]},"type":"Feature","properties":{"hierarchy":["tgn:2152337","tgn:7006450","tgn:1000001","tgn:7012149","tgn:2000082","tgn:7029392"],"placetype":["aat:300386853"],"id":2152337,"name:xx":"Bay Islands"}}
>>>>>>> 03f74aca74312dbeaf24d7e61306dd6a786dc3d0
