{
  "id": 2333926,
  "type": "Feature",
  "properties": {
    "tgn:hierarchy":[
        "tgn:2333926",
        "tgn:1000001",
        "tgn:7012149",
        "tgn:7007158",
        "tgn:2000246",
        "tgn:7029392"
    ],
    "tgn:id":2333926,
    "tgn:name":"Ford Creek",
    "tgn:placetype":[
        "aat:300008706"
    ]
},
  "bbox": [],
  "geometry": {"coordinates":[-106.1833,38.2333],"type":"Point"}
}