{
  "id": 2522413,
  "type": "Feature",
  "properties": {
    "tgn:hierarchy":[
        "tgn:2522413",
        "tgn:1000001",
        "tgn:7012149",
        "tgn:2001195",
        "tgn:7007523",
        "tgn:7029392"
    ],
    "tgn:id":2522413,
    "tgn:name":"Mooney Lake",
    "tgn:placetype":[
        "aat:300006191"
    ]
},
  "bbox": [],
  "geometry": {"coordinates":[-91.4833,37.6833],"type":"Point"}
}