{
  "id": 1018096,
  "type": "Feature",
  "properties": {
    "tgn:hierarchy":[
        "tgn:1018096",
        "tgn:1000001",
        "tgn:1001893",
        "tgn:7005560",
        "tgn:7029392"
    ],
    "tgn:id":1018096,
    "tgn:name":"R\u00edo Hondo",
    "tgn:placetype":[
        "aat:300008347"
    ]
},
  "bbox": [],
  "geometry": {"coordinates":[-99.2667,19.4167],"type":"Point"}
}