{
  "id": 7010490,
  "type": "Feature",
  "properties": {
    "tgn:hierarchy":[
        "tgn:7010490",
        "tgn:1000348",
        "tgn:1000003",
        "tgn:7006278",
        "tgn:7029392"
    ],
    "tgn:id":7010490,
    "tgn:name":"Mez\u0151cs\u00e1t",
    "tgn:placetype":[
        "aat:300008347"
    ]
},
  "bbox": [],
  "geometry": {"coordinates":[20.9167,47.8333],"type":"Point"}
}