{
  "id": 2291081,
  "type": "Feature",
  "properties": {
    "tgn:hierarchy":[
        "tgn:2291081",
        "tgn:1000001",
        "tgn:7012149",
        "tgn:1002965",
        "tgn:7007710",
        "tgn:7029392"
    ],
    "tgn:id":2291081,
    "tgn:name":"Dogback Mountain",
    "tgn:placetype":[
        "aat:300008798"
    ]
},
  "bbox": [],
  "geometry": {"coordinates":[-77.1833,40.95],"type":"Point"}
}