{
  "id": 7485788,
  "type": "Feature",
  "properties": {
    "tgn:hierarchy":[
        "tgn:7485788",
        "tgn:1000004",
        "tgn:7001014",
        "tgn:1000141",
        "tgn:7029392"
    ],
    "tgn:id":7485788,
    "tgn:name":"Ankengzi",
    "tgn:placetype":[
        "aat:300008347"
    ]
},
  "bbox": [],
  "geometry": {"coordinates":[120.615556,23.661111],"type":"Point"}
}