{
  "id": 7224895,
  "type": "Feature",
  "properties": {
    "tgn:hierarchy":[
        "tgn:7224895",
        "tgn:7002680",
        "tgn:7001395",
        "tgn:1000003",
        "tgn:1000074",
        "tgn:7029392"
    ],
    "tgn:id":7224895,
    "tgn:name":"N\u00e9os Galat\u00e1s",
    "tgn:placetype":[
        "aat:300008347"
    ]
},
  "bbox": [],
  "geometry": {"coordinates":[21.566667,38.366667],"type":"Point"}
}