{
  "id": 1096920,
  "type": "Feature",
  "properties": {
    "tgn:hierarchy":[
        "tgn:1096920",
        "tgn:7000490",
        "tgn:1000006",
        "tgn:7006238",
        "tgn:7029392"
    ],
    "tgn:id":1096920,
    "tgn:name":"Frankston",
    "tgn:placetype":[
        "aat:300008347"
    ]
},
  "bbox": [],
  "geometry": {"coordinates":[145.1167,-38.1333],"type":"Point"}
}