{
  "id": 2468289,
  "type": "Feature",
  "properties": {
    "tgn:hierarchy":[
        "tgn:2468289",
        "tgn:1002300",
        "tgn:1000001",
        "tgn:7012149",
        "tgn:7007564",
        "tgn:7029392"
    ],
    "tgn:id":2468289,
    "tgn:name":"Long Mountain",
    "tgn:placetype":[
        "aat:300266640"
    ]
},
  "bbox": [],
  "geometry": {"coordinates":[-71.3667,44.6667],"type":"Point"}
}