<<<<<<< HEAD
{
  "id": 7354901,
  "type": "Feature",
  "properties": {
    "tgn:hierarchy":[
        "tgn:7354901",
        "tgn:1000001",
        "tgn:7005594",
        "tgn:7005560",
        "tgn:7029392"
    ],
    "tgn:id":7354901,
    "tgn:name":"Charquillo",
    "tgn:placetype":[
        "aat:300008347"
    ]
},
  "bbox": [],
  "geometry": {"coordinates":[-101.0,22.85],"type":"Point"}
}
=======
{"geometry":{"type":"Point","coordinates":[-101.000000,22.850000]},"type":"Feature","properties":{"hierarchy":["tgn:7354901","tgn:1000001","tgn:7005594","tgn:7005560","tgn:7029392"],"placetype":["aat:300008347"],"id":7354901,"name:xx":"Charquillo"}}
>>>>>>> 03f74aca74312dbeaf24d7e61306dd6a786dc3d0
