{
  "id": 7180879,
  "type": "Feature",
  "properties": {
    "tgn:hierarchy":[
        "tgn:7180879",
        "tgn:7003692",
        "tgn:1000003",
        "tgn:7000084",
        "tgn:7029392"
    ],
    "tgn:id":7180879,
    "tgn:name":"Fr\u00fchmesshof",
    "tgn:placetype":[
        "aat:300008347"
    ]
},
  "bbox": [],
  "geometry": {"coordinates":[9.35,48.966667],"type":"Point"}
}