{
  "id": 7512558,
  "type": "Feature",
  "properties": {
    "tgn:hierarchy":[
        "tgn:7512558",
        "tgn:7000508",
        "tgn:1008380",
        "tgn:1000226",
        "tgn:1000006",
        "tgn:7029392"
    ],
    "tgn:id":7512558,
    "tgn:name:en":"Hooks Bay",
    "tgn:placetype":[
        "aat:300132316"
    ]
},
  "bbox": [],
  "geometry": {"coordinates":[175.183333,-36.733333],"type":"Point"}
}