{
  "id": 7565932,
  "type": "Feature",
  "properties": {
    "tgn:hierarchy":[
        "tgn:7565932",
        "tgn:1000004",
        "tgn:7000198",
        "tgn:7016722",
        "tgn:7029392"
    ],
    "tgn:id":7565932,
    "tgn:name:en":"Dh\u0101sak N\u0101la",
    "tgn:placetype":[
        "aat:300008699"
    ]
},
  "bbox": [],
  "geometry": {"coordinates":[79.486002,26.385457],"type":"Point"}
}