{
  "id": 7540373,
  "type": "Feature",
  "properties": {
    "tgn:hierarchy":[
        "tgn:7540373",
        "tgn:7001242",
        "tgn:7016833",
        "tgn:7000122",
        "tgn:7029392"
    ],
    "tgn:id":7540373,
    "tgn:name:en":"Qib\u0101b, W\u0101d\u012b al",
    "tgn:placetype":[
        "aat:300379998"
    ]
},
  "bbox": [],
  "geometry": {"coordinates":[32.835442,23.312158],"type":"Point"}
}