<<<<<<< HEAD
{
  "id": 2763510,
  "type": "Feature",
  "properties": {
    "tgn:hierarchy":[
        "tgn:2763510",
        "tgn:1000001",
        "tgn:7012149",
        "tgn:2000926",
        "tgn:7007515",
        "tgn:7029392"
    ],
    "tgn:id":2763510,
    "tgn:name":"Weymouth Pond",
    "tgn:placetype":[
        "aat:300008680"
    ]
},
  "bbox": [],
  "geometry": {"coordinates":[-70.8,44.2167],"type":"Point"}
}
=======
{"geometry":{"type":"Point","coordinates":[-70.800000,44.216700]},"type":"Feature","properties":{"hierarchy":["tgn:2763510","tgn:1000001","tgn:7012149","tgn:2000926","tgn:7007515","tgn:7029392"],"placetype":["aat:300008680"],"id":2763510,"name:xx":"Weymouth Pond"}}
>>>>>>> 03f74aca74312dbeaf24d7e61306dd6a786dc3d0
