{
  "id": 2741310,
  "type": "Feature",
  "properties": {
    "tgn:hierarchy":[
        "tgn:2741310",
        "tgn:1000001",
        "tgn:7012149",
        "tgn:1003008",
        "tgn:7007710",
        "tgn:7029392"
    ],
    "tgn:id":2741310,
    "tgn:name":"Upper Wilcox Pond",
    "tgn:placetype":[
        "aat:300006191"
    ]
},
  "bbox": [],
  "geometry": {"coordinates":[-75.2167,41.6333],"type":"Point"}
}