{
  "id": 7069023,
  "type": "Feature",
  "properties": {
    "tgn:hierarchy":[
        "tgn:7069023",
        "tgn:1000003",
        "tgn:7003688",
        "tgn:7000084",
        "tgn:7029392"
    ],
    "tgn:id":7069023,
    "tgn:name":"Steenfeld",
    "tgn:placetype":[
        "aat:300008347"
    ]
},
  "bbox": [],
  "geometry": {"coordinates":[9.366667,54.15],"type":"Point"}
}