{
  "id": 7592690,
  "type": "Feature",
  "properties": {
    "tgn:hierarchy":[
        "tgn:7592690",
        "tgn:1000004",
        "tgn:7000198",
        "tgn:7000799",
        "tgn:7029392"
    ],
    "tgn:id":7592690,
    "tgn:name:en":"Luh\u0101khi",
    "tgn:placetype":[
        "aat:300008347"
    ]
},
  "bbox": [],
  "geometry": {"coordinates":[74.836724,32.891849],"type":"Point"}
}