{
  "id": 2008220,
  "type": "Feature",
  "properties": {
    "tgn:hierarchy":[
        "tgn:2008220",
        "tgn:1000001",
        "tgn:7016172",
        "tgn:7012149",
        "tgn:2000171",
        "tgn:7029392"
    ],
    "tgn:id":2008220,
    "tgn:name":"Falls Chapel",
    "tgn:placetype":[
        "aat:300008347",
        "aat:300387210"
    ]
},
  "bbox": [],
  "geometry": {"coordinates":[-94.15,33.85],"type":"Point"}
}