{
  "id": 2543862,
  "type": "Feature",
  "properties": {
    "tgn:hierarchy":[
        "tgn:2543862",
        "tgn:1000001",
        "tgn:7012149",
        "tgn:2001458",
        "tgn:7007566",
        "tgn:7029392"
    ],
    "tgn:id":2543862,
    "tgn:name":"North Bosque Peak",
    "tgn:placetype":[
        "aat:300008798"
    ]
},
  "bbox": [],
  "geometry": {"coordinates":[-106.4333,34.7667],"type":"Point"}
}