{
  "id": 2772690,
  "type": "Feature",
  "properties": {
    "tgn:hierarchy":[
        "tgn:2772690",
        "tgn:1000001",
        "tgn:7012149",
        "tgn:1002547",
        "tgn:7007919",
        "tgn:7029392"
    ],
    "tgn:id":2772690,
    "tgn:name":"Williams Creek",
    "tgn:placetype":[
        "aat:300008706"
    ]
},
  "bbox": [],
  "geometry": {"coordinates":[-77.0833,38.35],"type":"Point"}
}