{
  "id": 7019840,
  "type": "Feature",
  "properties": {
    "tgn:hierarchy":[
        "tgn:7019840",
        "tgn:1000001",
        "tgn:7012149",
        "tgn:2002375",
        "tgn:7007923",
        "tgn:7029392"
    ],
    "tgn:id":7019840,
    "tgn:name":"Wyoming Hereford Ranch Reservoir Number 1",
    "tgn:placetype":[
        "aat:300006191"
    ]
},
  "bbox": [],
  "geometry": {"coordinates":[-104.7333,41.1167],"type":"Point"}
}