{
  "id": 2756565,
  "type": "Feature",
  "properties": {
    "tgn:hierarchy":[
        "tgn:2756565",
        "tgn:1000001",
        "tgn:7012149",
        "tgn:2002250",
        "tgn:7007920",
        "tgn:7029392"
    ],
    "tgn:id":2756565,
    "tgn:name":"Wellington Peak",
    "tgn:placetype":[
        "aat:300008798"
    ]
},
  "bbox": [],
  "geometry": {"coordinates":[-118.0667,48.25],"type":"Point"}
}