{
  "id": 7521462,
  "type": "Feature",
  "properties": {
    "tgn:hierarchy":[
        "tgn:7521462",
        "tgn:7001242",
        "tgn:7001311",
        "tgn:7016833",
        "tgn:7029392"
    ],
    "tgn:id":7521462,
    "tgn:name:en":"Abu Heita, W\u00e2di",
    "tgn:placetype":[
        "aat:300379998"
    ]
},
  "bbox": [],
  "geometry": {"coordinates":[33.466097,25.35154],"type":"Point"}
}