{
  "id": 7577063,
  "type": "Feature",
  "properties": {
    "tgn:hierarchy":[
        "tgn:7577063",
        "tgn:1000004",
        "tgn:7000198",
        "tgn:1001977",
        "tgn:7029392"
    ],
    "tgn:id":7577063,
    "tgn:name:en":"Krishnapur",
    "tgn:placetype":[
        "aat:300008347"
    ]
},
  "bbox": [],
  "geometry": {"coordinates":[88.259176,24.412467],"type":"Point"}
}