{
  "id": 2735082,
  "type": "Feature",
  "properties": {
    "tgn:hierarchy":[
        "tgn:2735082",
        "tgn:1000001",
        "tgn:7012149",
        "tgn:2000476",
        "tgn:7007250",
        "tgn:7029392"
    ],
    "tgn:id":2735082,
    "tgn:name":"Twentymile Bar",
    "tgn:placetype":[
        "aat:300132348"
    ]
},
  "bbox": [],
  "geometry": {"coordinates":[-115.45,46.0833],"type":"Point"}
}