{
  "id": 2674448,
  "type": "Feature",
  "properties": {
    "tgn:hierarchy":[
        "tgn:2674448",
        "tgn:1000001",
        "tgn:7012149",
        "tgn:2001882",
        "tgn:7007825",
        "tgn:7029392"
    ],
    "tgn:id":2674448,
    "tgn:name":"Snyder Branch",
    "tgn:placetype":[
        "aat:300008699"
    ]
},
  "bbox": [],
  "geometry": {"coordinates":[-81.7333,36.4167],"type":"Point"}
}