{
  "id": 2546034,
  "type": "Feature",
  "properties": {
    "tgn:hierarchy":[
        "tgn:2546034",
        "tgn:1000001",
        "tgn:7012149",
        "tgn:2001722",
        "tgn:7007708",
        "tgn:7029392"
    ],
    "tgn:id":2546034,
    "tgn:name":"North Fork Dry Creek",
    "tgn:placetype":[
        "aat:300008706"
    ]
},
  "bbox": [],
  "geometry": {"coordinates":[-116.8333,45.1667],"type":"Point"}
}