{
  "id": 2731813,
  "type": "Feature",
  "properties": {
    "tgn:hierarchy":[
        "tgn:2731813",
        "tgn:1000001",
        "tgn:7012149",
        "tgn:1002553",
        "tgn:7007920",
        "tgn:7029392"
    ],
    "tgn:id":2731813,
    "tgn:name":"Tumble Creek",
    "tgn:placetype":[
        "aat:300008706"
    ]
},
  "bbox": [],
  "geometry": {"coordinates":[-121.05,47.35],"type":"Point"}
}