{
  "id": 7563285,
  "type": "Feature",
  "properties": {
    "tgn:hierarchy":[
        "tgn:7563285",
        "tgn:1000004",
        "tgn:7000198",
        "tgn:7016722",
        "tgn:7029392"
    ],
    "tgn:id":7563285,
    "tgn:name:en":"Kandrauli Kachhoha",
    "tgn:placetype":[
        "aat:300008347"
    ]
},
  "bbox": [],
  "geometry": {"coordinates":[79.9279,27.0704],"type":"Point"}
}