{
  "id": 7306426,
  "type": "Feature",
  "properties": {
    "tgn:hierarchy":[
        "tgn:7306426",
        "tgn:7002842",
        "tgn:7001158",
        "tgn:1000003",
        "tgn:1000095",
        "tgn:7029392"
    ],
    "tgn:id":7306426,
    "tgn:name":"Mata, Sierra de la",
    "tgn:placetype":[
        "aat:300266640"
    ]
},
  "bbox": [],
  "geometry": {"coordinates":[-2.383333,41.266667],"type":"Point"}
}