{
  "id": 7384130,
  "type": "Feature",
  "properties": {
    "tgn:hierarchy":[
        "tgn:7384130",
        "tgn:1001853",
        "tgn:1000001",
        "tgn:7005560",
        "tgn:7029392"
    ],
    "tgn:id":7384130,
    "tgn:name":"Moca, Lomerio de la",
    "tgn:placetype":[
        "aat:300008795"
    ]
},
  "bbox": [],
  "geometry": {"coordinates":[-102.416667,27.783333],"type":"Point"}
}