<<<<<<< HEAD
{
  "id": 7356557,
  "type": "Feature",
  "properties": {
    "tgn:hierarchy":[
        "tgn:7356557",
        "tgn:1000001",
        "tgn:7005592",
        "tgn:7005560",
        "tgn:7029392"
    ],
    "tgn:id":7356557,
    "tgn:name":"Camocuautla",
    "tgn:placetype":[
        "aat:300008347"
    ]
},
  "bbox": [],
  "geometry": {"coordinates":[-97.766667,20.05],"type":"Point"}
}
=======
{"geometry":{"type":"Point","coordinates":[-97.766667,20.050000]},"type":"Feature","properties":{"hierarchy":["tgn:7356557","tgn:1000001","tgn:7005592","tgn:7005560","tgn:7029392"],"placetype":["aat:300008347"],"id":7356557,"name:xx":"Camocuautla"}}
>>>>>>> 03f74aca74312dbeaf24d7e61306dd6a786dc3d0
