{
  "id": 2297622,
  "type": "Feature",
  "properties": {
    "tgn:hierarchy":[
        "tgn:2297622",
        "tgn:1000001",
        "tgn:7012149",
        "tgn:7007923",
        "tgn:7029392"
    ],
    "tgn:id":2297622,
    "tgn:name":"Dry Fork Powder River",
    "tgn:placetype":[
        "aat:300008707"
    ]
},
  "bbox": [],
  "geometry": {"coordinates":[-106.0167,43.4833],"type":"Point"}
}