{
  "id": 2329741,
  "type": "Feature",
  "properties": {
    "tgn:hierarchy":[
        "tgn:2329741",
        "tgn:1000001",
        "tgn:7012149",
        "tgn:1002986",
        "tgn:7007568",
        "tgn:7029392"
    ],
    "tgn:id":2329741,
    "tgn:name":"Fivemile Mountain",
    "tgn:placetype":[
        "aat:300008798"
    ]
},
  "bbox": [],
  "geometry": {"coordinates":[-73.5667,43.6333],"type":"Point"}
}