{
  "id": 2250219,
  "type": "Feature",
  "properties": {
    "tgn:hierarchy":[
        "tgn:2250219",
        "tgn:1000001",
        "tgn:7012149",
        "tgn:2001451",
        "tgn:7007566",
        "tgn:7029392"
    ],
    "tgn:id":2250219,
    "tgn:name":"Collins Mine",
    "tgn:placetype":[
        "aat:300000390"
    ]
},
  "bbox": [],
  "geometry": {"coordinates":[-106.8833,35.6667],"type":"Point"}
}