{
  "id": 2525125,
  "type": "Feature",
  "properties": {
    "tgn:hierarchy":[
        "tgn:2525125",
        "tgn:1000001",
        "tgn:7012149",
        "tgn:7007157",
        "tgn:7014516",
        "tgn:7029392"
    ],
    "tgn:id":2525125,
    "tgn:name":"Morris Peak",
    "tgn:placetype":[
        "aat:300008798"
    ]
},
  "bbox": [],
  "geometry": {"coordinates":[-123.1167,38.8167],"type":"Point"}
}