{
  "id": 1065324,
  "type": "Feature",
  "properties": {
    "tgn:hierarchy":[
        "tgn:1065324",
        "tgn:1000003",
        "tgn:7017307",
        "tgn:7006663",
        "tgn:7029392"
    ],
    "tgn:id":1065324,
    "tgn:name":"Vinkovci",
    "tgn:placetype":[
        "aat:300008347",
        "aat:300008375"
    ]
},
  "bbox": [],
  "geometry": {"coordinates":[18.8167,45.2667],"type":"Point"}
}