{
  "id": 7477327,
  "type": "Feature",
  "properties": {
    "tgn:hierarchy":[
        "tgn:7477327",
        "tgn:1000004",
        "tgn:7001013",
        "tgn:1000141",
        "tgn:7029392"
    ],
    "tgn:id":7477327,
    "tgn:name":"Caota Guozhong",
    "tgn:placetype":[
        "aat:300006495"
    ]
},
  "bbox": [],
  "geometry": {"coordinates":[121.140827,25.043076],"type":"Point"}
}