{
  "id": 7301840,
  "type": "Feature",
  "properties": {
    "tgn:hierarchy":[
        "tgn:7301840",
        "tgn:7002834",
        "tgn:1000003",
        "tgn:7002786",
        "tgn:1000095",
        "tgn:7029392"
    ],
    "tgn:id":7301840,
    "tgn:name":"Moa\u00f1a",
    "tgn:placetype":[
        "aat:300008347"
    ]
},
  "bbox": [],
  "geometry": {"coordinates":[-8.75,42.216667],"type":"Point"}
}