{
  "id": 7253440,
  "type": "Feature",
  "properties": {
    "tgn:hierarchy":[
        "tgn:7253440",
        "tgn:7003457",
        "tgn:1000003",
        "tgn:1000063",
        "tgn:7018236",
        "tgn:7029392"
    ],
    "tgn:id":7253440,
    "tgn:name":"Schaar",
    "tgn:placetype":[
        "aat:300008347"
    ]
},
  "bbox": [],
  "geometry": {"coordinates":[3.680659,51.252674],"type":"Point"}
}