{
  "id": 2649213,
  "type": "Feature",
  "properties": {
    "tgn:hierarchy":[
        "tgn:2649213",
        "tgn:1000001",
        "tgn:7012149",
        "tgn:7007919",
        "tgn:7029392"
    ],
    "tgn:id":2649213,
    "tgn:name":"Scott Mountain",
    "tgn:placetype":[
        "aat:300008798"
    ]
},
  "bbox": [],
  "geometry": {"coordinates":[-78.8167,38.05],"type":"Point"}
}