{
  "id": 7466943,
  "type": "Feature",
  "properties": {
    "tgn:hierarchy":[
        "tgn:7466943",
        "tgn:7002444",
        "tgn:1000003",
        "tgn:7009907",
        "tgn:7008591",
        "tgn:7029392"
    ],
    "tgn:id":7466943,
    "tgn:name:en":"Brims Ness",
    "tgn:placetype":[
        "aat:300386846"
    ]
},
  "bbox": [],
  "geometry": {"coordinates":[-3.233333,58.783333],"type":"Point"}
}