<<<<<<< HEAD
{
  "id": 7358124,
  "type": "Feature",
  "properties": {
    "tgn:hierarchy":[
        "tgn:7358124",
        "tgn:1000001",
        "tgn:7005601",
        "tgn:7005560",
        "tgn:7029392"
    ],
    "tgn:id":7358124,
    "tgn:name":"Sam Agustin de Mellilla",
    "tgn:placetype":[
        "aat:300008347"
    ]
},
  "bbox": [],
  "geometry": {"coordinates":[-102.883333,24.116667],"type":"Point"}
}
=======
{"geometry":{"type":"Point","coordinates":[-102.883333,24.116667]},"type":"Feature","properties":{"hierarchy":["tgn:7358124","tgn:1000001","tgn:7005601","tgn:7005560","tgn:7029392"],"placetype":["aat:300008347"],"id":7358124,"name:xx":"Sam Agustin de Mellilla"}}
>>>>>>> 03f74aca74312dbeaf24d7e61306dd6a786dc3d0
