{
  "id": 7480381,
  "type": "Feature",
  "properties": {
    "tgn:hierarchy":[
        "tgn:7480381",
        "tgn:7001010",
        "tgn:1000004",
        "tgn:1000141",
        "tgn:7029392"
    ],
    "tgn:id":7480381,
    "tgn:name":"Hezhong Jiaohui",
    "tgn:placetype":[
        "aat:300007466"
    ]
},
  "bbox": [],
  "geometry": {"coordinates":[121.740425,24.269749],"type":"Point"}
}