{
  "id": 7497977,
  "type": "Feature",
  "properties": {
    "tgn:hierarchy":[
        "tgn:7497977",
        "tgn:1000957",
        "tgn:1000004",
        "tgn:1000141",
        "tgn:7029392"
    ],
    "tgn:id":7497977,
    "tgn:name":"Daye Suidao",
    "tgn:placetype":[
        "aat:300007899"
    ]
},
  "bbox": [],
  "geometry": {"coordinates":[121.733611,25.1201],"type":"Point"}
}