{
  "id": 2455379,
  "type": "Feature",
  "properties": {
    "tgn:hierarchy":[
        "tgn:2455379",
        "tgn:1000001",
        "tgn:2001411",
        "tgn:7012149",
        "tgn:7007526",
        "tgn:7029392"
    ],
    "tgn:id":2455379,
    "tgn:name":"Little Fork Willow Creek",
    "tgn:placetype":[
        "aat:300008706"
    ]
},
  "bbox": [],
  "geometry": {"coordinates":[-115.4333,41.6833],"type":"Point"}
}