<<<<<<< HEAD
{
  "id": 7350190,
  "type": "Feature",
  "properties": {
    "tgn:hierarchy":[
        "tgn:7350190",
        "tgn:1000001",
        "tgn:7005592",
        "tgn:7005560",
        "tgn:7029392"
    ],
    "tgn:id":7350190,
    "tgn:name":"Ahuatepec",
    "tgn:placetype":[
        "aat:300008347"
    ]
},
  "bbox": [],
  "geometry": {"coordinates":[-96.983333,18.233333],"type":"Point"}
}
=======
{"geometry":{"type":"Point","coordinates":[-96.983333,18.233333]},"type":"Feature","properties":{"hierarchy":["tgn:7350190","tgn:1000001","tgn:7005592","tgn:7005560","tgn:7029392"],"placetype":["aat:300008347"],"id":7350190,"name:xx":"Ahuatepec"}}
>>>>>>> 03f74aca74312dbeaf24d7e61306dd6a786dc3d0
