{
  "id": 2231150,
  "type": "Feature",
  "properties": {
    "tgn:hierarchy":[
        "tgn:2231150",
        "tgn:1000001",
        "tgn:7012149",
        "tgn:2001763",
        "tgn:7007712",
        "tgn:7029392"
    ],
    "tgn:id":2231150,
    "tgn:name":"Chadwick",
    "tgn:placetype":[
        "aat:300008347"
    ]
},
  "bbox": [],
  "geometry": {"coordinates":[-82.55,34.8167],"type":"Point"}
}