{
  "id": 2370577,
  "type": "Feature",
  "properties": {
    "tgn:hierarchy":[
        "tgn:2370577",
        "tgn:1000001",
        "tgn:7012149",
        "tgn:2000228",
        "tgn:7007158",
        "tgn:7029392"
    ],
    "tgn:id":2370577,
    "tgn:name":"Hackberry Creek",
    "tgn:placetype":[
        "aat:300008706"
    ]
},
  "bbox": [],
  "geometry": {"coordinates":[-103.4833,39.2667],"type":"Point"}
}