{
  "id": 2495029,
  "type": "Feature",
  "properties": {
    "tgn:hierarchy":[
        "tgn:2495029",
        "tgn:1000001",
        "tgn:7012149",
        "tgn:2001237",
        "tgn:7007523",
        "tgn:7029392"
    ],
    "tgn:id":2495029,
    "tgn:name":"Martinsburg",
    "tgn:placetype":[
        "aat:300008347"
    ]
},
  "bbox": [],
  "geometry": {"coordinates":[-90.6833,36.5833],"type":"Point"}
}