{
  "id": 2522960,
  "type": "Feature",
  "properties": {
    "tgn:hierarchy":[
        "tgn:2522960",
        "tgn:1000001",
        "tgn:7012149",
        "tgn:2001290",
        "tgn:7007524",
        "tgn:7029392"
    ],
    "tgn:id":2522960,
    "tgn:name":"Moore Lake",
    "tgn:placetype":[
        "aat:300008680"
    ]
},
  "bbox": [],
  "geometry": {"coordinates":[-115.25,47.1667],"type":"Point"}
}