{
  "id": 2632258,
  "type": "Feature",
  "properties": {
    "tgn:hierarchy":[
        "tgn:2632258",
        "tgn:1000001",
        "tgn:7016172",
        "tgn:7012149",
        "tgn:2000151",
        "tgn:7029392"
    ],
    "tgn:id":2632258,
    "tgn:name":"Roy",
    "tgn:placetype":[
        "aat:300008347"
    ]
},
  "bbox": [],
  "geometry": {"coordinates":[-90.0833,35.65],"type":"Point"}
}