{
  "id": 2586157,
  "type": "Feature",
  "properties": {
    "tgn:hierarchy":[
        "tgn:2586157",
        "tgn:1000001",
        "tgn:2001369",
        "tgn:7012149",
        "tgn:7007525",
        "tgn:7029392"
    ],
    "tgn:id":2586157,
    "tgn:name":"Pishelville Island",
    "tgn:placetype":[
        "aat:300008791"
    ]
},
  "bbox": [],
  "geometry": {"coordinates":[-98.1833,42.7167],"type":"Point"}
}