{
  "id": 2292380,
  "type": "Feature",
  "properties": {
    "tgn:hierarchy":[
        "tgn:2292380",
        "tgn:1000001",
        "tgn:2001741",
        "tgn:7012149",
        "tgn:7007712",
        "tgn:7029392"
    ],
    "tgn:id":2292380,
    "tgn:name":"Donohoe Bay",
    "tgn:placetype":[
        "aat:300008905"
    ]
},
  "bbox": [],
  "geometry": {"coordinates":[-79.4833,34.5167],"type":"Point"}
}