{
  "id": 7576157,
  "type": "Feature",
  "properties": {
    "tgn:hierarchy":[
        "tgn:7576157",
        "tgn:1000004",
        "tgn:7000198",
        "tgn:1001894",
        "tgn:7029392"
    ],
    "tgn:id":7576157,
    "tgn:name:en":"Karanpath\u0101r",
    "tgn:placetype":[
        "aat:300008347"
    ]
},
  "bbox": [],
  "geometry": {"coordinates":[81.32063,22.97924],"type":"Point"}
}