{
  "id": 2494444,
  "type": "Feature",
  "properties": {
    "tgn:hierarchy":[
        "tgn:2494444",
        "tgn:1000001",
        "tgn:7012149",
        "tgn:1002691",
        "tgn:7007826",
        "tgn:7029392"
    ],
    "tgn:id":2494444,
    "tgn:name":"Martin Creek",
    "tgn:placetype":[
        "aat:300008706"
    ]
},
  "bbox": [],
  "geometry": {"coordinates":[-95.65,30.35],"type":"Point"}
}