{
  "id": 7279456,
  "type": "Feature",
  "properties": {
    "tgn:hierarchy":[
        "tgn:7279456",
        "tgn:1001702",
        "tgn:1000049",
        "tgn:1000002",
        "tgn:7029392"
    ],
    "tgn:id":7279456,
    "tgn:name":"R\u00edo Fr\u00edo, Puerto",
    "tgn:placetype":[
        "aat:300008678"
    ]
},
  "bbox": [],
  "geometry": {"coordinates":[-74.433333,-49.216667],"type":"Point"}
}