{
  "id": 7558747,
  "type": "Feature",
  "properties": {
    "tgn:hierarchy":[
        "tgn:7558747",
        "tgn:1000004",
        "tgn:7000198",
        "tgn:1001977",
        "tgn:7029392"
    ],
    "tgn:id":7558747,
    "tgn:name:en":"Pyramid Peak",
    "tgn:placetype":[
        "aat:300008795"
    ]
},
  "bbox": [],
  "geometry": {"coordinates":[88.183333,27.816667],"type":"Point"}
}