{
  "id": 7141006,
  "type": "Feature",
  "properties": {
    "tgn:hierarchy":[
        "tgn:7141006",
        "tgn:7003692",
        "tgn:1000003",
        "tgn:7000084",
        "tgn:7029392"
    ],
    "tgn:id":7141006,
    "tgn:name":"Lipplesberg",
    "tgn:placetype":[
        "aat:300008777"
    ]
},
  "bbox": [],
  "geometry": {"coordinates":[8.85,49.116667],"type":"Point"}
}