{
  "id": 2469517,
  "type": "Feature",
  "properties": {
    "tgn:hierarchy":[
        "tgn:2469517",
        "tgn:1000001",
        "tgn:7012149",
        "tgn:2001714",
        "tgn:7007708",
        "tgn:7029392"
    ],
    "tgn:id":2469517,
    "tgn:name":"Lookout Butte",
    "tgn:placetype":[
        "aat:300008798"
    ]
},
  "bbox": [],
  "geometry": {"coordinates":[-121.9333,42.9833],"type":"Point"}
}