{
  "id": 2385757,
  "type": "Feature",
  "properties": {
    "tgn:hierarchy":[
        "tgn:2385757",
        "tgn:1000001",
        "tgn:7012149",
        "tgn:7007157",
        "tgn:7014475",
        "tgn:7029392"
    ],
    "tgn:id":2385757,
    "tgn:name":"Hendrys Creek",
    "tgn:placetype":[
        "aat:300008706"
    ]
},
  "bbox": [],
  "geometry": {"coordinates":[-121.9333,37.1667],"type":"Point"}
}