<<<<<<< HEAD
{
  "id": 2767114,
  "type": "Feature",
  "properties": {
    "tgn:hierarchy":[
        "tgn:2767114",
        "tgn:1000001",
        "tgn:7012149",
        "tgn:7007157",
        "tgn:1002566",
        "tgn:7029392"
    ],
    "tgn:id":2767114,
    "tgn:name":"White Rock Canyon",
    "tgn:placetype":[
        "aat:300008761"
    ]
},
  "bbox": [],
  "geometry": {"coordinates":[-122.9,39.2167],"type":"Point"}
}
=======
{"geometry":{"type":"Point","coordinates":[-122.900000,39.216700]},"type":"Feature","properties":{"hierarchy":["tgn:2767114","tgn:1000001","tgn:7012149","tgn:7007157","tgn:1002566","tgn:7029392"],"placetype":["aat:300008761"],"id":2767114,"name:xx":"White Rock Canyon"}}
>>>>>>> 03f74aca74312dbeaf24d7e61306dd6a786dc3d0
