<<<<<<< HEAD
{
  "id": 2338023,
  "type": "Feature",
  "properties": {
    "tgn:hierarchy":[
        "tgn:2338023",
        "tgn:1000001",
        "tgn:1002359",
        "tgn:7012149",
        "tgn:7007517",
        "tgn:7029392"
    ],
    "tgn:id":2338023,
    "tgn:name":"Fox Island Creek",
    "tgn:placetype":[
        "aat:300008706"
    ]
},
  "bbox": [],
  "geometry": {"coordinates":[-70.8333,42.8167],"type":"Point"}
}
=======
{"geometry":{"type":"Point","coordinates":[-70.833300,42.816700]},"type":"Feature","properties":{"hierarchy":["tgn:2338023","tgn:1000001","tgn:1002359","tgn:7012149","tgn:7007517","tgn:7029392"],"placetype":["aat:300008706"],"id":2338023,"name:xx":"Fox Island Creek"}}
>>>>>>> 03f74aca74312dbeaf24d7e61306dd6a786dc3d0
