{
  "id": 7280507,
  "type": "Feature",
  "properties": {
    "tgn:hierarchy":[
        "tgn:7280507",
        "tgn:1001630",
        "tgn:1000049",
        "tgn:1000002",
        "tgn:7029392"
    ],
    "tgn:id":7280507,
    "tgn:name":"Tamber\u00eda",
    "tgn:placetype":[
        "aat:300008347"
    ]
},
  "bbox": [],
  "geometry": {"coordinates":[-69.466667,-27.866667],"type":"Point"}
}