{
  "id": 2756338,
  "type": "Feature",
  "properties": {
    "tgn:hierarchy":[
        "tgn:2756338",
        "tgn:1000001",
        "tgn:7012149",
        "tgn:2002068",
        "tgn:7007826",
        "tgn:7029392"
    ],
    "tgn:id":2756338,
    "tgn:name":"Welder Point",
    "tgn:placetype":[
        "aat:300008850"
    ]
},
  "bbox": [],
  "geometry": {"coordinates":[-97.2167,27.8333],"type":"Point"}
}