{
  "id": 7590701,
  "type": "Feature",
  "properties": {
    "tgn:hierarchy":[
        "tgn:7590701",
        "tgn:1000004",
        "tgn:7000198",
        "tgn:7000799",
        "tgn:7029392"
    ],
    "tgn:id":7590701,
    "tgn:name:en":"Tad",
    "tgn:placetype":[
        "aat:300008347"
    ]
},
  "bbox": [],
  "geometry": {"coordinates":[73.818814,34.353517],"type":"Point"}
}