{
  "id": 7281323,
  "type": "Feature",
  "properties": {
    "tgn:hierarchy":[
        "tgn:7281323",
        "tgn:1001768",
        "tgn:1000049",
        "tgn:1000002",
        "tgn:7029392"
    ],
    "tgn:id":7281323,
    "tgn:name":"Santa Catalina, Morro",
    "tgn:placetype":[
        "aat:300008798"
    ]
},
  "bbox": [],
  "geometry": {"coordinates":[-70.966667,-32.633333],"type":"Point"}
}