{
  "id": 7577558,
  "type": "Feature",
  "properties": {
    "tgn:hierarchy":[
        "tgn:7577558",
        "tgn:1000004",
        "tgn:7000198",
        "tgn:7016788",
        "tgn:7029392"
    ],
    "tgn:id":7577558,
    "tgn:name:en":"Kh\u012bnd\u0101sar",
    "tgn:placetype":[
        "aat:300008347"
    ]
},
  "bbox": [],
  "geometry": {"coordinates":[72.9176,27.5148],"type":"Point"}
}