{
  "id": 7032088,
  "type": "Feature",
  "properties": {
    "tgn:hierarchy":[
        "tgn:7032088",
        "tgn:1000003",
        "tgn:7003515",
        "tgn:7029392"
    ],
    "tgn:id":7032088,
    "tgn:name":"Vaduz",
    "tgn:placetype":[
        "aat:300387064",
        "aat:300387330"
    ]
},
  "bbox": [],
  "geometry": {"coordinates":[9.526,47.145],"type":"Point"}
}