<<<<<<< HEAD
{
  "id": 7475446,
  "type": "Feature",
  "properties": {
    "tgn:hierarchy":[
        "tgn:7475446",
        "tgn:1000004",
        "tgn:7467799",
        "tgn:1000141",
        "tgn:7029392"
    ],
    "tgn:id":7475446,
    "tgn:name":"Liujiahu",
    "tgn:placetype":[
        "aat:300000745"
    ]
},
  "bbox": [],
  "geometry": {"coordinates":[120.5791,23.9695],"type":"Point"}
}
=======
{"geometry":{"type":"Point","coordinates":[120.579100,23.969500]},"type":"Feature","properties":{"hierarchy":["tgn:7475446","tgn:1000004","tgn:7467799","tgn:1000141","tgn:7029392"],"placetype":["aat:300000745"],"id":7475446,"name:xx":"Liujiahu"}}
>>>>>>> 03f74aca74312dbeaf24d7e61306dd6a786dc3d0
