{
  "id": 7475446,
  "type": "Feature",
  "properties": {
    "tgn:hierarchy":[
        "tgn:7475446",
        "tgn:1000004",
        "tgn:7467799",
        "tgn:1000141",
        "tgn:7029392"
    ],
    "tgn:id":7475446,
    "tgn:name":"Liujiahu",
    "tgn:placetype":[
        "aat:300000745"
    ]
},
  "bbox": [],
  "geometry": {"coordinates":[120.5791,23.9695],"type":"Point"}
}