{
  "id": 7230424,
  "type": "Feature",
  "properties": {
    "tgn:hierarchy":[
        "tgn:7230424",
        "tgn:7011170",
        "tgn:7002715",
        "tgn:1000003",
        "tgn:1000074",
        "tgn:7029392"
    ],
    "tgn:id":7230424,
    "tgn:name":"Er\u00edpia Krithar\u00edtsa",
    "tgn:placetype":[
        "aat:300008057"
    ]
},
  "bbox": [],
  "geometry": {"coordinates":[24.133333,41.466667],"type":"Point"}
}