{
  "id": 2497804,
  "type": "Feature",
  "properties": {
    "tgn:hierarchy":[
        "tgn:2497804",
        "tgn:1000001",
        "tgn:7012149",
        "tgn:1002732",
        "tgn:7007710",
        "tgn:7029392"
    ],
    "tgn:id":2497804,
    "tgn:name":"Mayfair",
    "tgn:placetype":[
        "aat:300008347"
    ]
},
  "bbox": [],
  "geometry": {"coordinates":[-76.6167,40.85],"type":"Point"}
}