{
  "id": 2689380,
  "type": "Feature",
  "properties": {
    "tgn:hierarchy":[
        "tgn:2689380",
        "tgn:1000001",
        "tgn:7012149",
        "tgn:2002339",
        "tgn:7007922",
        "tgn:7029392"
    ],
    "tgn:id":2689380,
    "tgn:name":"Squaw Creek",
    "tgn:placetype":[
        "aat:300008706"
    ]
},
  "bbox": [],
  "geometry": {"coordinates":[-88.8167,45.0667],"type":"Point"}
}