{
  "id": 7291294,
  "type": "Feature",
  "properties": {
    "tgn:hierarchy":[
        "tgn:7291294",
        "tgn:1001708",
        "tgn:1000049",
        "tgn:1000002",
        "tgn:7029392"
    ],
    "tgn:id":7291294,
    "tgn:name":"El Mait\u00e9n, Cerro",
    "tgn:placetype":[
        "aat:300008795"
    ]
},
  "bbox": [],
  "geometry": {"coordinates":[-71.15,-33.95],"type":"Point"}
}