{
  "id": 2262781,
  "type": "Feature",
  "properties": {
    "tgn:hierarchy":[
        "tgn:2262781",
        "tgn:1000001",
        "tgn:1002313",
        "tgn:7012149",
        "tgn:7007706",
        "tgn:7029392"
    ],
    "tgn:id":2262781,
    "tgn:name":"Cowans",
    "tgn:placetype":[
        "aat:300008347"
    ]
},
  "bbox": [],
  "geometry": {"coordinates":[-81.4833,41.3667],"type":"Point"}
}