{
  "id": 7582083,
  "type": "Feature",
  "properties": {
    "tgn:hierarchy":[
        "tgn:7582083",
        "tgn:1000004",
        "tgn:7000198",
        "tgn:7016722",
        "tgn:7029392"
    ],
    "tgn:id":7582083,
    "tgn:name:en":"Chak",
    "tgn:placetype":[
        "aat:300008347"
    ]
},
  "bbox": [],
  "geometry": {"coordinates":[78.343515,24.882869],"type":"Point"}
}