{
  "id": 1069568,
  "type": "Feature",
  "properties": {
    "tgn:hierarchy":[
        "tgn:1069568",
        "tgn:1000004",
        "tgn:1001390",
        "tgn:1000111",
        "tgn:7029392"
    ],
    "tgn:id":1069568,
    "tgn:name":"Kuandian",
    "tgn:placetype":[
        "aat:300008347"
    ]
},
  "bbox": [],
  "geometry": {"coordinates":[124.7667,40.75],"type":"Point"}
}