{
  "id": 2424300,
  "type": "Feature",
  "properties": {
    "tgn:hierarchy":[
        "tgn:2424300",
        "tgn:1000001",
        "tgn:7012149",
        "tgn:2000434",
        "tgn:7007248",
        "tgn:7029392"
    ],
    "tgn:id":2424300,
    "tgn:name":"Johnson Branch",
    "tgn:placetype":[
        "aat:300008699"
    ]
},
  "bbox": [],
  "geometry": {"coordinates":[-83.3667,32.5833],"type":"Point"}
}