{
  "id": 2683138,
  "type": "Feature",
  "properties": {
    "tgn:hierarchy":[
        "tgn:2683138",
        "tgn:1000001",
        "tgn:2001414",
        "tgn:7012149",
        "tgn:7007526",
        "tgn:7029392"
    ],
    "tgn:id":2683138,
    "tgn:name":"Spanish Girl Mine",
    "tgn:placetype":[
        "aat:300000390"
    ]
},
  "bbox": [],
  "geometry": {"coordinates":[-117.9833,41.2667],"type":"Point"}
}