{
  "id": 7509002,
  "type": "Feature",
  "properties": {
    "tgn:hierarchy":[
        "tgn:7509002",
        "tgn:1008380",
        "tgn:1000226",
        "tgn:7016827",
        "tgn:1000006",
        "tgn:7029392"
    ],
    "tgn:id":7509002,
    "tgn:name:en":"Tangarakau",
    "tgn:placetype":[
        "aat:300008347"
    ]
},
  "bbox": [],
  "geometry": {"coordinates":[174.85,-39.016667],"type":"Point"}
}