{
  "id": 2191126,
  "type": "Feature",
  "properties": {
    "tgn:hierarchy":[
        "tgn:2191126",
        "tgn:1000001",
        "tgn:7012149",
        "tgn:1002913",
        "tgn:7007919",
        "tgn:7029392"
    ],
    "tgn:id":2191126,
    "tgn:name":"Boykins Island",
    "tgn:placetype":[
        "aat:300008791"
    ]
},
  "bbox": [],
  "geometry": {"coordinates":[-77.3167,38.3333],"type":"Point"}
}