{
  "id": 7224308,
  "type": "Feature",
  "properties": {
    "tgn:hierarchy":[
        "tgn:7224308",
        "tgn:7002739",
        "tgn:7017076",
        "tgn:1000003",
        "tgn:1000074",
        "tgn:7029392"
    ],
    "tgn:id":7224308,
    "tgn:name":"Tasoula\u00edika",
    "tgn:placetype":[
        "aat:300008347"
    ]
},
  "bbox": [],
  "geometry": {"coordinates":[23.083333,37.533333],"type":"Point"}
}