{
  "id": 2610124,
  "type": "Feature",
  "properties": {
    "tgn:hierarchy":[
        "tgn:2610124",
        "tgn:1000001",
        "tgn:2000264",
        "tgn:7012149",
        "tgn:7007240",
        "tgn:7029392"
    ],
    "tgn:id":2610124,
    "tgn:name":"Red Bay Branch",
    "tgn:placetype":[
        "aat:300008699"
    ]
},
  "bbox": [],
  "geometry": {"coordinates":[-81.5833,30.35],"type":"Point"}
}