{
  "id": 7322539,
  "type": "Feature",
  "properties": {
    "tgn:hierarchy":[
        "tgn:7322539",
        "tgn:7002820",
        "tgn:7030216",
        "tgn:1000003",
        "tgn:1000095",
        "tgn:7029392"
    ],
    "tgn:id":7322539,
    "tgn:name":"San Juan de Balps",
    "tgn:placetype":[
        "aat:300008347"
    ]
},
  "bbox": [],
  "geometry": {"coordinates":[2.426908,42.171664],"type":"Point"}
}