{
  "id": 2721749,
  "type": "Feature",
  "properties": {
    "tgn:hierarchy":[
        "tgn:2721749",
        "tgn:7006450",
        "tgn:1000001",
        "tgn:7012149",
        "tgn:2000085",
        "tgn:7029392"
    ],
    "tgn:id":2721749,
    "tgn:name":"Timber Creek",
    "tgn:placetype":[
        "aat:300008706"
    ]
},
  "bbox": [],
  "geometry": {"coordinates":[-143.65,63.0167],"type":"Point"}
}