<<<<<<< HEAD
{
  "id": 7476275,
  "type": "Feature",
  "properties": {
    "tgn:hierarchy":[
        "tgn:7476275",
        "tgn:7488858",
        "tgn:1000004",
        "tgn:1000141",
        "tgn:7029392"
    ],
    "tgn:id":7476275,
    "tgn:name":"Hongren Guozhong",
    "tgn:placetype":[
        "aat:300006495"
    ]
},
  "bbox": [],
  "geometry": {"coordinates":[120.973112,23.962072],"type":"Point"}
}
=======
{"geometry":{"type":"Point","coordinates":[120.973112,23.962072]},"type":"Feature","properties":{"hierarchy":["tgn:7476275","tgn:7488858","tgn:1000004","tgn:1000141","tgn:7029392"],"placetype":["aat:300006495"],"id":7476275,"name:xx":"Hongren Guozhong"}}
>>>>>>> 03f74aca74312dbeaf24d7e61306dd6a786dc3d0
