{
  "id": 2050935,
  "type": "Feature",
  "properties": {
    "tgn:hierarchy":[
        "tgn:2050935",
        "tgn:7014010",
        "tgn:1000001",
        "tgn:1002344",
        "tgn:7012149",
        "tgn:7007517",
        "tgn:7029392"
    ],
    "tgn:id":2050935,
    "tgn:name":"West Tisbury",
    "tgn:placetype":[
        "aat:300008347"
    ]
},
  "bbox": [],
  "geometry": {"coordinates":[-70.6667,41.3667],"type":"Point"}
}