<<<<<<< HEAD
{
  "id": 7111187,
  "type": "Feature",
  "properties": {
    "tgn:hierarchy":[
        "tgn:7111187",
        "tgn:1000003",
        "tgn:7000094",
        "tgn:7000084",
        "tgn:7029392"
    ],
    "tgn:id":7111187,
    "tgn:name":"Rittermannsh\u00e4ger Holz",
    "tgn:placetype":[
        "aat:300008863"
    ]
},
  "bbox": [],
  "geometry": {"coordinates":[12.716667,53.616667],"type":"Point"}
}
=======
{"geometry":{"type":"Point","coordinates":[12.716667,53.616667]},"type":"Feature","properties":{"hierarchy":["tgn:7111187","tgn:1000003","tgn:7000094","tgn:7000084","tgn:7029392"],"placetype":["aat:300008863"],"id":7111187,"name:xx":"Rittermannsh\u00e4ger Holz"}}
>>>>>>> 03f74aca74312dbeaf24d7e61306dd6a786dc3d0
