{
  "id": 2728958,
  "type": "Feature",
  "properties": {
    "tgn:hierarchy":[
        "tgn:2728958",
        "tgn:7002659",
        "tgn:1000001",
        "tgn:7012149",
        "tgn:2000031",
        "tgn:7029392"
    ],
    "tgn:id":2728958,
    "tgn:name":"Trice Lake",
    "tgn:placetype":[
        "aat:300006191"
    ]
},
  "bbox": [],
  "geometry": {"coordinates":[-88.0333,32.7667],"type":"Point"}
}