<<<<<<< HEAD
{
  "id": 7486393,
  "type": "Feature",
  "properties": {
    "tgn:hierarchy":[
        "tgn:7486393",
        "tgn:1000004",
        "tgn:7001009",
        "tgn:1000141",
        "tgn:7029392"
    ],
    "tgn:id":7486393,
    "tgn:name":"Niubucuo",
    "tgn:placetype":[
        "aat:300008347"
    ]
},
  "bbox": [],
  "geometry": {"coordinates":[120.551111,24.267778],"type":"Point"}
}
=======
{"geometry":{"type":"Point","coordinates":[120.551111,24.267778]},"type":"Feature","properties":{"hierarchy":["tgn:7486393","tgn:1000004","tgn:7001009","tgn:1000141","tgn:7029392"],"placetype":["aat:300008347"],"id":7486393,"name:xx":"Niubucuo"}}
>>>>>>> 03f74aca74312dbeaf24d7e61306dd6a786dc3d0
