{
  "id": 7526400,
  "type": "Feature",
  "properties": {
    "tgn:hierarchy":[
        "tgn:7526400",
        "tgn:7001242",
        "tgn:7016833",
        "tgn:7000124",
        "tgn:7029392"
    ],
    "tgn:id":7526400,
    "tgn:name:en":"S\u012bd\u012b Makhl\u016bf",
    "tgn:placetype":[
        "aat:300005926"
    ]
},
  "bbox": [],
  "geometry": {"coordinates":[31.55,26.783333],"type":"Point"}
}