{
  "id": 7281243,
  "type": "Feature",
  "properties": {
    "tgn:hierarchy":[
        "tgn:7281243",
        "tgn:1001702",
        "tgn:1000049",
        "tgn:1000002",
        "tgn:7029392"
    ],
    "tgn:id":7281243,
    "tgn:name":"Serrano, Paso",
    "tgn:placetype":[
        "aat:300387026"
    ]
},
  "bbox": [],
  "geometry": {"coordinates":[-74.333333,-51.95],"type":"Point"}
}