{
  "id": 7089674,
  "type": "Feature",
  "properties": {
    "tgn:hierarchy":[
        "tgn:7089674",
        "tgn:7000096",
        "tgn:1000003",
        "tgn:7000084",
        "tgn:7029392"
    ],
    "tgn:id":7089674,
    "tgn:name":"Wachtel-Berg",
    "tgn:placetype":[
        "aat:300008777"
    ]
},
  "bbox": [],
  "geometry": {"coordinates":[13.05,51.933333],"type":"Point"}
}