{
  "id": 1011650,
  "type": "Feature",
  "properties": {
    "tgn:hierarchy":[
        "tgn:1011650",
        "tgn:1000001",
        "tgn:2000939",
        "tgn:7012149",
        "tgn:7007516",
        "tgn:7029392"
    ],
    "tgn:id":1011650,
    "tgn:name":"Blackwalnut Point",
    "tgn:placetype":[
        "aat:300386846"
    ]
},
  "bbox": [],
  "geometry": {"coordinates":[-76.3333,38.6667],"type":"Point"}
}