{
  "id": 7236151,
  "type": "Feature",
  "properties": {
    "tgn:hierarchy":[
        "tgn:7236151",
        "tgn:7011170",
        "tgn:7002715",
        "tgn:1000003",
        "tgn:1000074",
        "tgn:7029392"
    ],
    "tgn:id":7236151,
    "tgn:name":"Mon\u00ed Esfigm\u00e9nou",
    "tgn:placetype":[
        "aat:300000641"
    ]
},
  "bbox": [],
  "geometry": {"coordinates":[24.133333,40.35],"type":"Point"}
}