{
  "id": 7413104,
  "type": "Feature",
  "properties": {
    "tgn:hierarchy":[
        "tgn:7413104",
        "tgn:1000001",
        "tgn:7005598",
        "tgn:7005560",
        "tgn:7029392"
    ],
    "tgn:id":7413104,
    "tgn:name":"Quimicho, Cerro",
    "tgn:placetype":[
        "aat:300008795"
    ]
},
  "bbox": [],
  "geometry": {"coordinates":[-97.997222,19.397222],"type":"Point"}
}