{
  "id": 7546503,
  "type": "Feature",
  "properties": {
    "tgn:hierarchy":[
        "tgn:7546503",
        "tgn:1000004",
        "tgn:7000198",
        "tgn:1001996",
        "tgn:7029392"
    ],
    "tgn:id":7546503,
    "tgn:name:en":"Ani",
    "tgn:placetype":[
        "aat:300008347"
    ]
},
  "bbox": [],
  "geometry": {"coordinates":[77.417098,31.434106],"type":"Point"}
}