{
  "id": 1107392,
  "type": "Feature",
  "properties": {
    "tgn:hierarchy":[
        "tgn:1107392",
        "tgn:1000003",
        "tgn:7029392"
    ],
    "tgn:id":1107392,
    "tgn:name:es":"Mauberme, Pico",
    "tgn:name:fr":"Mauberm\u00e9, Pic de",
    "tgn:placetype":[
        "aat:300008798"
    ]
},
  "bbox": [],
  "geometry": {"coordinates":[0.9167,42.7833],"type":"Point"}
}