{
  "id": 2375213,
  "type": "Feature",
  "properties": {
    "tgn:hierarchy":[
        "tgn:2375213",
        "tgn:1000001",
        "tgn:7012149",
        "tgn:1003034",
        "tgn:7007826",
        "tgn:7029392"
    ],
    "tgn:id":2375213,
    "tgn:name":"Hannah Lake",
    "tgn:placetype":[
        "aat:300008680"
    ]
},
  "bbox": [],
  "geometry": {"coordinates":[-95.45,32.75],"type":"Point"}
}