{
  "id": 7333682,
  "type": "Feature",
  "properties": {
    "tgn:hierarchy":[
        "tgn:7333682",
        "tgn:7002759",
        "tgn:7002843",
        "tgn:1000003",
        "tgn:1000095",
        "tgn:7029392"
    ],
    "tgn:id":7333682,
    "tgn:name":"Escriche, Rambla de",
    "tgn:placetype":[
        "aat:300266554",
        "aat:300008699"
    ]
},
  "bbox": [],
  "geometry": {"coordinates":[-0.983333,40.366667],"type":"Point"}
}