{
  "id": 7310716,
  "type": "Feature",
  "properties": {
    "tgn:hierarchy":[
        "tgn:7310716",
        "tgn:1001702",
        "tgn:1000049",
        "tgn:1000002",
        "tgn:7029392"
    ],
    "tgn:id":7310716,
    "tgn:name":"Moritz, R\u00edo",
    "tgn:placetype":[
        "aat:300008699"
    ]
},
  "bbox": [],
  "geometry": {"coordinates":[-69.933333,-53.683333],"type":"Point"}
}