{
  "id": 7398434,
  "type": "Feature",
  "properties": {
    "tgn:hierarchy":[
        "tgn:7398434",
        "tgn:1000001",
        "tgn:1001893",
        "tgn:7005560",
        "tgn:7029392"
    ],
    "tgn:id":7398434,
    "tgn:name":"Estaci\u00f3n San Juan de Arag\u00f3n",
    "tgn:placetype":[
        "aat:300007783"
    ]
},
  "bbox": [],
  "geometry": {"coordinates":[-99.054722,19.468889],"type":"Point"}
}