{
  "id": 7288735,
  "type": "Feature",
  "properties": {
    "tgn:hierarchy":[
        "tgn:7288735",
        "tgn:1001630",
        "tgn:1000049",
        "tgn:1000002",
        "tgn:7029392"
    ],
    "tgn:id":7288735,
    "tgn:name":"Laguna Chica, R\u00edo",
    "tgn:placetype":[
        "aat:300008699"
    ]
},
  "bbox": [],
  "geometry": {"coordinates":[-70.059167,-28.890278],"type":"Point"}
}