{
  "id": 2083802,
  "type": "Feature",
  "properties": {
    "tgn:hierarchy":[
        "tgn:2083802",
        "tgn:1000001",
        "tgn:7012149",
        "tgn:2001665",
        "tgn:7007707",
        "tgn:7029392"
    ],
    "tgn:id":2083802,
    "tgn:name":"Overbrook",
    "tgn:placetype":[
        "aat:300008347"
    ]
},
  "bbox": [],
  "geometry": {"coordinates":[-97.1333,34.0667],"type":"Point"}
}