{
  "id": 7147254,
  "type": "Feature",
  "properties": {
    "tgn:hierarchy":[
        "tgn:7147254",
        "tgn:7003669",
        "tgn:1000003",
        "tgn:7000084",
        "tgn:7029392"
    ],
    "tgn:id":7147254,
    "tgn:name":"K\u00f6nigsstein",
    "tgn:placetype":[
        "aat:300008777"
    ]
},
  "bbox": [],
  "geometry": {"coordinates":[9.116667,50.033333],"type":"Point"}
}