{
  "id": 7498199,
  "type": "Feature",
  "properties": {
    "tgn:hierarchy":[
        "tgn:7498199",
        "tgn:7468018",
        "tgn:1000004",
        "tgn:1000141",
        "tgn:7029392"
    ],
    "tgn:id":7498199,
    "tgn:name":"Houdabu Xi",
    "tgn:placetype":[
        "aat:300008699"
    ]
},
  "bbox": [],
  "geometry": {"coordinates":[120.758891,23.472624],"type":"Point"}
}