{
  "id": 1054514,
  "type": "Feature",
  "properties": {
    "tgn:hierarchy":[
        "tgn:1054514",
        "tgn:1000004",
        "tgn:6003034",
        "tgn:7018214",
        "tgn:7002435",
        "tgn:7029392"
    ],
    "tgn:id":1054514,
    "tgn:name":"Yagunovskiy",
    "tgn:placetype":[
        "aat:300008347"
    ]
},
  "bbox": [],
  "geometry": {"coordinates":[85.9833,55.3167],"type":"Point"}
}