<<<<<<< HEAD
{
  "id": 2760273,
  "type": "Feature",
  "properties": {
    "tgn:hierarchy":[
        "tgn:2760273",
        "tgn:1000001",
        "tgn:7012149",
        "tgn:2002124",
        "tgn:7007827",
        "tgn:7029392"
    ],
    "tgn:id":2760273,
    "tgn:name":"West Fork Saddletree Draw",
    "tgn:placetype":[
        "aat:300008761"
    ]
},
  "bbox": [],
  "geometry": {"coordinates":[-109.3167,39.8167],"type":"Point"}
}
=======
{"geometry":{"type":"Point","coordinates":[-109.316700,39.816700]},"type":"Feature","properties":{"hierarchy":["tgn:2760273","tgn:1000001","tgn:7012149","tgn:2002124","tgn:7007827","tgn:7029392"],"placetype":["aat:300008761"],"id":2760273,"name:xx":"West Fork Saddletree Draw"}}
>>>>>>> 03f74aca74312dbeaf24d7e61306dd6a786dc3d0
