{
  "id": 2760273,
  "type": "Feature",
  "properties": {
    "tgn:hierarchy":[
        "tgn:2760273",
        "tgn:1000001",
        "tgn:7012149",
        "tgn:2002124",
        "tgn:7007827",
        "tgn:7029392"
    ],
    "tgn:id":2760273,
    "tgn:name":"West Fork Saddletree Draw",
    "tgn:placetype":[
        "aat:300008761"
    ]
},
  "bbox": [],
  "geometry": {"coordinates":[-109.3167,39.8167],"type":"Point"}
}