{
  "id": 2246452,
  "type": "Feature",
  "properties": {
    "tgn:hierarchy":[
        "tgn:2246452",
        "tgn:1000001",
        "tgn:7012149",
        "tgn:7007248",
        "tgn:7029392"
    ],
    "tgn:id":2246452,
    "tgn:name":"Cobb Creek",
    "tgn:placetype":[
        "aat:300008706"
    ]
},
  "bbox": [],
  "geometry": {"coordinates":[-84.25,34.2333],"type":"Point"}
}