<<<<<<< HEAD
{
  "id": 7057570,
  "type": "Feature",
  "properties": {
    "tgn:hierarchy":[
        "tgn:7057570",
        "tgn:7003168",
        "tgn:1000003",
        "tgn:7009760",
        "tgn:1000080",
        "tgn:7029392"
    ],
    "tgn:id":7057570,
    "tgn:name":"Asso, Torrente",
    "tgn:placetype":[
        "aat:300008699"
    ]
},
  "bbox": [],
  "geometry": {"coordinates":[11.55,43.016667],"type":"Point"}
}
=======
{"geometry":{"type":"Point","coordinates":[11.550000,43.016667]},"type":"Feature","properties":{"hierarchy":["tgn:7057570","tgn:7003168","tgn:1000003","tgn:7009760","tgn:1000080","tgn:7029392"],"placetype":["aat:300008699"],"id":7057570,"name:xx":"Asso, Torrente"}}
>>>>>>> 03f74aca74312dbeaf24d7e61306dd6a786dc3d0
