<<<<<<< HEAD
{
  "id": 2331967,
  "type": "Feature",
  "properties": {
    "tgn:hierarchy":[
        "tgn:2331967",
        "tgn:1000001",
        "tgn:7012149",
        "tgn:2001461",
        "tgn:7007568",
        "tgn:7029392"
    ],
    "tgn:id":2331967,
    "tgn:name":"Fleury Mountain",
    "tgn:placetype":[
        "aat:300008798"
    ]
},
  "bbox": [],
  "geometry": {"coordinates":[-73.5667,44.3167],"type":"Point"}
}
=======
{"geometry":{"type":"Point","coordinates":[-73.566700,44.316700]},"type":"Feature","properties":{"hierarchy":["tgn:2331967","tgn:1000001","tgn:7012149","tgn:2001461","tgn:7007568","tgn:7029392"],"placetype":["aat:300008798"],"id":2331967,"name:xx":"Fleury Mountain"}}
>>>>>>> 03f74aca74312dbeaf24d7e61306dd6a786dc3d0
