{
  "id": 7261969,
  "type": "Feature",
  "properties": {
    "tgn:hierarchy":[
        "tgn:7261969",
        "tgn:7003619",
        "tgn:1000003",
        "tgn:7016845",
        "tgn:7029392"
    ],
    "tgn:id":7261969,
    "tgn:name:nl":"Egelbeek",
    "tgn:placetype":[
        "aat:300008699"
    ]
},
  "bbox": [],
  "geometry": {"coordinates":[5.983333,52.283333],"type":"Point"}
}