<<<<<<< HEAD
{
  "id": 2407829,
  "type": "Feature",
  "properties": {
    "tgn:hierarchy":[
        "tgn:2407829",
        "tgn:1000001",
        "tgn:7012149",
        "tgn:2001887",
        "tgn:7007825",
        "tgn:7029392"
    ],
    "tgn:id":2407829,
    "tgn:name":"Hurricane Branch",
    "tgn:placetype":[
        "aat:300008699"
    ]
},
  "bbox": [],
  "geometry": {"coordinates":[-87.4833,35.4833],"type":"Point"}
}
=======
{"geometry":{"type":"Point","coordinates":[-87.483300,35.483300]},"type":"Feature","properties":{"hierarchy":["tgn:2407829","tgn:1000001","tgn:7012149","tgn:2001887","tgn:7007825","tgn:7029392"],"placetype":["aat:300008699"],"id":2407829,"name:xx":"Hurricane Branch"}}
>>>>>>> 03f74aca74312dbeaf24d7e61306dd6a786dc3d0
