{
  "id": 7357312,
  "type": "Feature",
  "properties": {
    "tgn:hierarchy":[
        "tgn:7357312",
        "tgn:1000001",
        "tgn:7005599",
        "tgn:7005560",
        "tgn:7029392"
    ],
    "tgn:id":7357312,
    "tgn:name":"Corozal",
    "tgn:placetype":[
        "aat:300008347"
    ]
},
  "bbox": [],
  "geometry": {"coordinates":[-98.533333,21.55],"type":"Point"}
}