{
  "id": 1049429,
  "type": "Feature",
  "properties": {
    "tgn:hierarchy":[
        "tgn:1049429",
        "tgn:1000003",
        "tgn:7024126",
        "tgn:7006366",
        "tgn:7029392"
    ],
    "tgn:id":1049429,
    "tgn:name":"Rymanow",
    "tgn:placetype":[
        "aat:300008347"
    ]
},
  "bbox": [],
  "geometry": {"coordinates":[21.85,49.5833],"type":"Point"}
}