{
  "id": 7121738,
  "type": "Feature",
  "properties": {
    "tgn:hierarchy":[
        "tgn:7121738",
        "tgn:1000003",
        "tgn:7000094",
        "tgn:7000084",
        "tgn:7029392"
    ],
    "tgn:id":7121738,
    "tgn:name":"Papendorf",
    "tgn:placetype":[
        "aat:300008347"
    ]
},
  "bbox": [],
  "geometry": {"coordinates":[12.133333,54.033333],"type":"Point"}
}