<<<<<<< HEAD
{
  "id": 2253667,
  "type": "Feature",
  "properties": {
    "tgn:hierarchy":[
        "tgn:2253667",
        "tgn:1000001",
        "tgn:7012149",
        "tgn:2001310",
        "tgn:7007524",
        "tgn:7029392"
    ],
    "tgn:id":2253667,
    "tgn:name":"Cook Reservoir",
    "tgn:placetype":[
        "aat:300006191"
    ]
},
  "bbox": [],
  "geometry": {"coordinates":[-111.3167,48.9833],"type":"Point"}
}
=======
{"geometry":{"type":"Point","coordinates":[-111.316700,48.983300]},"type":"Feature","properties":{"hierarchy":["tgn:2253667","tgn:1000001","tgn:7012149","tgn:2001310","tgn:7007524","tgn:7029392"],"placetype":["aat:300006191"],"id":2253667,"name:xx":"Cook Reservoir"}}
>>>>>>> 03f74aca74312dbeaf24d7e61306dd6a786dc3d0
