{
  "id": 7042693,
  "type": "Feature",
  "properties": {
    "tgn:hierarchy":[
        "tgn:7042693",
        "tgn:7003138",
        "tgn:1000003",
        "tgn:7003080",
        "tgn:1000080",
        "tgn:7029392"
    ],
    "tgn:id":7042693,
    "tgn:name":"Prati, Fosso dei",
    "tgn:placetype":[
        "aat:300008699"
    ]
},
  "bbox": [],
  "geometry": {"coordinates":[12.766667,41.95],"type":"Point"}
}