<<<<<<< HEAD
{
  "id": 2158830,
  "type": "Feature",
  "properties": {
    "tgn:hierarchy":[
        "tgn:2158830",
        "tgn:1000001",
        "tgn:1002182",
        "tgn:7012149",
        "tgn:7007520",
        "tgn:7029392"
    ],
    "tgn:id":2158830,
    "tgn:name":"Becker Drain",
    "tgn:placetype":[
        "aat:300006075"
    ]
},
  "bbox": [],
  "geometry": {"coordinates":[-86.5,41.9],"type":"Point"}
}
=======
{"geometry":{"type":"Point","coordinates":[-86.500000,41.900000]},"type":"Feature","properties":{"hierarchy":["tgn:2158830","tgn:1000001","tgn:1002182","tgn:7012149","tgn:7007520","tgn:7029392"],"placetype":["aat:300006075"],"id":2158830,"name:xx":"Becker Drain"}}
>>>>>>> 03f74aca74312dbeaf24d7e61306dd6a786dc3d0
