{
  "id": 7449073,
  "type": "Feature",
  "properties": {
    "tgn:hierarchy":[
        "tgn:7449073",
        "tgn:7002445",
        "tgn:7019021",
        "tgn:1000003",
        "tgn:7008591",
        "tgn:7029392"
    ],
    "tgn:id":7449073,
    "tgn:name:en":"Upper Swainswick",
    "tgn:placetype":[
        "aat:300008347"
    ]
},
  "bbox": [],
  "geometry": {"coordinates":[-2.350556,51.415556],"type":"Point"}
}