{
  "id": 7389245,
  "type": "Feature",
  "properties": {
    "tgn:hierarchy":[
        "tgn:7389245",
        "tgn:1000001",
        "tgn:1001906",
        "tgn:7005560",
        "tgn:7029392"
    ],
    "tgn:id":7389245,
    "tgn:name":"Pimientillo",
    "tgn:placetype":[
        "aat:300008347"
    ]
},
  "bbox": [],
  "geometry": {"coordinates":[-105.4075,22.015278],"type":"Point"}
}