{
  "id": 2466094,
  "type": "Feature",
  "properties": {
    "tgn:hierarchy":[
        "tgn:2466094",
        "tgn:1000001",
        "tgn:7016172",
        "tgn:7012149",
        "tgn:2000158",
        "tgn:7029392"
    ],
    "tgn:id":2466094,
    "tgn:name":"Lone Willow Point",
    "tgn:placetype":[
        "aat:300008850"
    ]
},
  "bbox": [],
  "geometry": {"coordinates":[-91.0667,34.2667],"type":"Point"}
}