{
  "id": 7477771,
  "type": "Feature",
  "properties": {
    "tgn:hierarchy":[
        "tgn:7477771",
        "tgn:1000004",
        "tgn:7001013",
        "tgn:1000141",
        "tgn:7029392"
    ],
    "tgn:id":7477771,
    "tgn:name":"Dayuan Guoxiao",
    "tgn:placetype":[
        "aat:300006495"
    ]
},
  "bbox": [],
  "geometry": {"coordinates":[121.20221,25.059225],"type":"Point"}
}