<<<<<<< HEAD
{
  "id": 2153706,
  "type": "Feature",
  "properties": {
    "tgn:hierarchy":[
        "tgn:2153706",
        "tgn:1000001",
        "tgn:7012149",
        "tgn:2002026",
        "tgn:7007826",
        "tgn:7029392"
    ],
    "tgn:id":2153706,
    "tgn:name":"Bear Branch",
    "tgn:placetype":[
        "aat:300008699"
    ]
},
  "bbox": [],
  "geometry": {"coordinates":[-98.0667,31.25],"type":"Point"}
}
=======
{"geometry":{"type":"Point","coordinates":[-98.066700,31.250000]},"type":"Feature","properties":{"hierarchy":["tgn:2153706","tgn:1000001","tgn:7012149","tgn:2002026","tgn:7007826","tgn:7029392"],"placetype":["aat:300008699"],"id":2153706,"name:xx":"Bear Branch"}}
>>>>>>> 03f74aca74312dbeaf24d7e61306dd6a786dc3d0
