{
  "id": 7560595,
  "type": "Feature",
  "properties": {
    "tgn:hierarchy":[
        "tgn:7560595",
        "tgn:1000004",
        "tgn:7000198",
        "tgn:7016722",
        "tgn:7029392"
    ],
    "tgn:id":7560595,
    "tgn:name:en":"Sukhl\u0101l ka Nagla",
    "tgn:placetype":[
        "aat:300008347"
    ]
},
  "bbox": [],
  "geometry": {"coordinates":[79.230771,26.788904],"type":"Point"}
}