{
  "id": 2465466,
  "type": "Feature",
  "properties": {
    "tgn:hierarchy":[
        "tgn:2465466",
        "tgn:1000001",
        "tgn:7012149",
        "tgn:1002999",
        "tgn:7007526",
        "tgn:7029392"
    ],
    "tgn:id":2465466,
    "tgn:name":"Lone Juniper Spring",
    "tgn:placetype":[
        "aat:300008697"
    ]
},
  "bbox": [],
  "geometry": {"coordinates":[-119.6167,41.4167],"type":"Point"}
}