{
  "id": 2164045,
  "type": "Feature",
  "properties": {
    "tgn:hierarchy":[
        "tgn:2164045",
        "tgn:1000001",
        "tgn:7012149",
        "tgn:2001552",
        "tgn:7007709",
        "tgn:7029392"
    ],
    "tgn:id":2164045,
    "tgn:name":"Berkeley Village",
    "tgn:placetype":[
        "aat:300008347"
    ]
},
  "bbox": [],
  "geometry": {"coordinates":[-77.9333,35.35],"type":"Point"}
}