{
  "id": 1107576,
  "type": "Feature",
  "properties": {
    "tgn:hierarchy":[
        "tgn:1107576",
        "tgn:1000001",
        "tgn:7012149",
        "tgn:2000183",
        "tgn:7007157",
        "tgn:7029392"
    ],
    "tgn:id":1107576,
    "tgn:name":"Telescope Peak",
    "tgn:placetype":[
        "aat:300008798"
    ]
},
  "bbox": [],
  "geometry": {"coordinates":[-117.0833,36.1667],"type":"Point"}
}