{
  "id": 2394506,
  "type": "Feature",
  "properties": {
    "tgn:hierarchy":[
        "tgn:2394506",
        "tgn:1000001",
        "tgn:7012149",
        "tgn:2001537",
        "tgn:7007709",
        "tgn:7029392"
    ],
    "tgn:id":2394506,
    "tgn:name":"Hogpen Branch",
    "tgn:placetype":[
        "aat:300008699"
    ]
},
  "bbox": [],
  "geometry": {"coordinates":[-81.8167,35.2333],"type":"Point"}
}