{
  "id": 7545016,
  "type": "Feature",
  "properties": {
    "tgn:hierarchy":[
        "tgn:7545016",
        "tgn:1000004",
        "tgn:7000198",
        "tgn:7000799",
        "tgn:7029392"
    ],
    "tgn:id":7545016,
    "tgn:name:en":"Bhart",
    "tgn:placetype":[
        "aat:300008347"
    ]
},
  "bbox": [],
  "geometry": {"coordinates":[75.601734,33.249665],"type":"Point"}
}