{
  "id": 1137258,
  "type": "Feature",
  "properties": {
    "tgn:hierarchy":[
        "tgn:1137258",
        "tgn:1000004",
        "tgn:7012943",
        "tgn:7014786",
        "tgn:7029392"
    ],
    "tgn:id":1137258,
    "tgn:name":"Belousovka",
    "tgn:placetype":[
        "aat:300008347"
    ]
},
  "bbox": [],
  "geometry": {"coordinates":[82.5167,50.1333],"type":"Point"}
}