{
  "id": 7246080,
  "type": "Feature",
  "properties": {
    "tgn:hierarchy":[
        "tgn:7246080",
        "tgn:7003465",
        "tgn:1000003",
        "tgn:1000063",
        "tgn:4012014",
        "tgn:7029392"
    ],
    "tgn:id":7246080,
    "tgn:name":"Core, Bois del",
    "tgn:placetype":[
        "aat:300008863"
    ]
},
  "bbox": [],
  "geometry": {"coordinates":[5.531421,50.228807],"type":"Point"}
}