{
  "id": 2644099,
  "type": "Feature",
  "properties": {
    "tgn:hierarchy":[
        "tgn:2644099",
        "tgn:1000001",
        "tgn:7012149",
        "tgn:7007157",
        "tgn:7014516",
        "tgn:7029392"
    ],
    "tgn:id":2644099,
    "tgn:name":"Santa Nella",
    "tgn:placetype":[
        "aat:300008347"
    ]
},
  "bbox": [],
  "geometry": {"coordinates":[-122.95,38.4833],"type":"Point"}
}