{
  "id": 2140758,
  "type": "Feature",
  "properties": {
    "tgn:hierarchy":[
        "tgn:2140758",
        "tgn:1000001",
        "tgn:7012149",
        "tgn:2001274",
        "tgn:7007524",
        "tgn:7029392"
    ],
    "tgn:id":2140758,
    "tgn:name":"Avalanche Basin",
    "tgn:placetype":[
        "aat:300386845"
    ]
},
  "bbox": [],
  "geometry": {"coordinates":[-113.7667,48.65],"type":"Point"}
}