{
  "id": 2152657,
  "type": "Feature",
  "properties": {
    "tgn:hierarchy":[
        "tgn:2152657",
        "tgn:1000001",
        "tgn:7012149",
        "tgn:1002729",
        "tgn:7007710",
        "tgn:7029392"
    ],
    "tgn:id":2152657,
    "tgn:name":"Baynard Park",
    "tgn:placetype":[
        "aat:300008347"
    ]
},
  "bbox": [],
  "geometry": {"coordinates":[-75.3333,40.6333],"type":"Point"}
}