{
  "id": 1124555,
  "type": "Feature",
  "properties": {
    "tgn:hierarchy":[
        "tgn:1124555",
        "tgn:7013003",
        "tgn:7005685",
        "tgn:1000001",
        "tgn:7024197",
        "tgn:7029392"
    ],
    "tgn:id":1124555,
    "tgn:name":"Hantzsch",
    "tgn:placetype":[
        "aat:300008707"
    ]
},
  "bbox": [],
  "geometry": {"coordinates":[-72.4333,67.5333],"type":"Point"}
}