{
  "id": 7296261,
  "type": "Feature",
  "properties": {
    "tgn:hierarchy":[
        "tgn:7296261",
        "tgn:7002758",
        "tgn:7002841",
        "tgn:1000003",
        "tgn:1000095",
        "tgn:7029392"
    ],
    "tgn:id":7296261,
    "tgn:name":"El Puntal",
    "tgn:placetype":[
        "aat:300387200"
    ]
},
  "bbox": [],
  "geometry": {"coordinates":[-6.281667,36.908056],"type":"Point"}
}