{
  "id": 7154291,
  "type": "Feature",
  "properties": {
    "tgn:hierarchy":[
        "tgn:7154291",
        "tgn:1000003",
        "tgn:7003682",
        "tgn:7000084",
        "tgn:7029392"
    ],
    "tgn:id":7154291,
    "tgn:name":"Irsch",
    "tgn:placetype":[
        "aat:300008347"
    ]
},
  "bbox": [],
  "geometry": {"coordinates":[6.55,49.983333],"type":"Point"}
}