{
  "id": 2567912,
  "type": "Feature",
  "properties": {
    "tgn:hierarchy":[
        "tgn:2567912",
        "tgn:1000001",
        "tgn:2000925",
        "tgn:7012149",
        "tgn:7007515",
        "tgn:7029392"
    ],
    "tgn:id":2567912,
    "tgn:name":"Paradise Point",
    "tgn:placetype":[
        "aat:300008850"
    ]
},
  "bbox": [],
  "geometry": {"coordinates":[-69.5833,43.85],"type":"Point"}
}