{
  "id": 2698796,
  "type": "Feature",
  "properties": {
    "tgn:hierarchy":[
        "tgn:2698796",
        "tgn:1000001",
        "tgn:7012149",
        "tgn:2000181",
        "tgn:7007157",
        "tgn:7029392"
    ],
    "tgn:id":2698796,
    "tgn:name":"Strawberry Creek",
    "tgn:placetype":[
        "aat:300008706"
    ]
},
  "bbox": [],
  "geometry": {"coordinates":[-124.05,40.9667],"type":"Point"}
}