{
  "id": 1057033,
  "type": "Feature",
  "properties": {
    "tgn:hierarchy":[
        "tgn:1057033",
        "tgn:7011648",
        "tgn:1000003",
        "tgn:7006660",
        "tgn:7029392"
    ],
    "tgn:id":1057033,
    "tgn:name":"Mirove",
    "tgn:placetype":[
        "aat:300008347"
    ]
},
  "bbox": [],
  "geometry": {"coordinates":[34.75,47.75],"type":"Point"}
}