{
  "id": 2220429,
  "type": "Feature",
  "properties": {
    "tgn:hierarchy":[
        "tgn:2220429",
        "tgn:1000001",
        "tgn:7012149",
        "tgn:1002599",
        "tgn:7007708",
        "tgn:7029392"
    ],
    "tgn:id":2220429,
    "tgn:name":"Cape Horn Ridge",
    "tgn:placetype":[
        "aat:300266640"
    ]
},
  "bbox": [],
  "geometry": {"coordinates":[-123.8167,44.5167],"type":"Point"}
}