{
  "id": 2663915,
  "type": "Feature",
  "properties": {
    "tgn:hierarchy":[
        "tgn:2663915",
        "tgn:1000001",
        "tgn:7012149",
        "tgn:7020792",
        "tgn:7007524",
        "tgn:7029392"
    ],
    "tgn:id":2663915,
    "tgn:name":"Silver Lake Millsite",
    "tgn:placetype":[
        "aat:300000390"
    ]
},
  "bbox": [],
  "geometry": {"coordinates":[-113.2333,46.15],"type":"Point"}
}