{
  "id": 2194924,
  "type": "Feature",
  "properties": {
    "tgn:hierarchy":[
        "tgn:2194924",
        "tgn:1000001",
        "tgn:7012149",
        "tgn:2002119",
        "tgn:7007827",
        "tgn:7029392"
    ],
    "tgn:id":2194924,
    "tgn:name":"Brighams Tomb",
    "tgn:placetype":[
        "aat:300008798"
    ]
},
  "bbox": [],
  "geometry": {"coordinates":[-110.0833,37.0333],"type":"Point"}
}