{
  "id": 7021863,
  "type": "Feature",
  "properties": {
    "tgn:hierarchy":[
        "tgn:7021863",
        "tgn:1000001",
        "tgn:2001185",
        "tgn:7012149",
        "tgn:7007523",
        "tgn:7029392"
    ],
    "tgn:id":7021863,
    "tgn:name":"Bald Knobbers Cave",
    "tgn:placetype":[
        "aat:300008746"
    ]
},
  "bbox": [],
  "geometry": {"coordinates":[-93.05,36.95],"type":"Point"}
}