{
  "id": 2293552,
  "type": "Feature",
  "properties": {
    "tgn:hierarchy":[
        "tgn:2293552",
        "tgn:1000001",
        "tgn:7012149",
        "tgn:2001236",
        "tgn:7007523",
        "tgn:7029392"
    ],
    "tgn:id":2293552,
    "tgn:name":"Double Springs Hollow",
    "tgn:placetype":[
        "aat:300008761"
    ]
},
  "bbox": [],
  "geometry": {"coordinates":[-90.9333,37.4667],"type":"Point"}
}