<<<<<<< HEAD
{
  "id": 2330246,
  "type": "Feature",
  "properties": {
    "tgn:hierarchy":[
        "tgn:2330246",
        "tgn:1000001",
        "tgn:7012149",
        "tgn:2001896",
        "tgn:7007825",
        "tgn:7029392"
    ],
    "tgn:id":2330246,
    "tgn:name":"Flanigan Hill",
    "tgn:placetype":[
        "aat:300008798"
    ]
},
  "bbox": [],
  "geometry": {"coordinates":[-87.1167,35.45],"type":"Point"}
}
=======
{"geometry":{"type":"Point","coordinates":[-87.116700,35.450000]},"type":"Feature","properties":{"hierarchy":["tgn:2330246","tgn:1000001","tgn:7012149","tgn:2001896","tgn:7007825","tgn:7029392"],"placetype":["aat:300008798"],"id":2330246,"name:xx":"Flanigan Hill"}}
>>>>>>> 03f74aca74312dbeaf24d7e61306dd6a786dc3d0
