<<<<<<< HEAD
{
  "id": 2408107,
  "type": "Feature",
  "properties": {
    "tgn:hierarchy":[
        "tgn:2408107",
        "tgn:1000001",
        "tgn:7012149",
        "tgn:2001824",
        "tgn:7007713",
        "tgn:7029392"
    ],
    "tgn:id":2408107,
    "tgn:name":"Hurricane Lake",
    "tgn:placetype":[
        "aat:300008680"
    ]
},
  "bbox": [],
  "geometry": {"coordinates":[-97.1333,45.4],"type":"Point"}
}
=======
{"geometry":{"type":"Point","coordinates":[-97.133300,45.400000]},"type":"Feature","properties":{"hierarchy":["tgn:2408107","tgn:1000001","tgn:7012149","tgn:2001824","tgn:7007713","tgn:7029392"],"placetype":["aat:300008680"],"id":2408107,"name:xx":"Hurricane Lake"}}
>>>>>>> 03f74aca74312dbeaf24d7e61306dd6a786dc3d0
