<<<<<<< HEAD
{
  "id": 7480505,
  "type": "Feature",
  "properties": {
    "tgn:hierarchy":[
        "tgn:7480505",
        "tgn:7001010",
        "tgn:1000004",
        "tgn:1000141",
        "tgn:7029392"
    ],
    "tgn:id":7480505,
    "tgn:name":"Shoufeng Kaikenqu",
    "tgn:placetype":[
        "aat:300006163"
    ]
},
  "bbox": [],
  "geometry": {"coordinates":[121.539167,23.873333],"type":"Point"}
}
=======
{"geometry":{"type":"Point","coordinates":[121.539167,23.873333]},"type":"Feature","properties":{"hierarchy":["tgn:7480505","tgn:7001010","tgn:1000004","tgn:1000141","tgn:7029392"],"placetype":["aat:300006163"],"id":7480505,"name:xx":"Shoufeng Kaikenqu"}}
>>>>>>> 03f74aca74312dbeaf24d7e61306dd6a786dc3d0
