{
  "id": 7480505,
  "type": "Feature",
  "properties": {
    "tgn:hierarchy":[
        "tgn:7480505",
        "tgn:7001010",
        "tgn:1000004",
        "tgn:1000141",
        "tgn:7029392"
    ],
    "tgn:id":7480505,
    "tgn:name":"Shoufeng Kaikenqu",
    "tgn:placetype":[
        "aat:300006163"
    ]
},
  "bbox": [],
  "geometry": {"coordinates":[121.539167,23.873333],"type":"Point"}
}