{
  "id": 2741806,
  "type": "Feature",
  "properties": {
    "tgn:hierarchy":[
        "tgn:2741806",
        "tgn:7006450",
        "tgn:1000001",
        "tgn:7012149",
        "tgn:2124014",
        "tgn:7029392"
    ],
    "tgn:id":2741806,
    "tgn:name":"Uyon Lakes",
    "tgn:placetype":[
        "aat:300008680"
    ]
},
  "bbox": [],
  "geometry": {"coordinates":[-160.1833,67.9667],"type":"Point"}
}