<<<<<<< HEAD
{
  "id": 7114971,
  "type": "Feature",
  "properties": {
    "tgn:hierarchy":[
        "tgn:7114971",
        "tgn:7003692",
        "tgn:1000003",
        "tgn:7000084",
        "tgn:7029392"
    ],
    "tgn:id":7114971,
    "tgn:name":"Obers\u00e4ckingen",
    "tgn:placetype":[
        "aat:300008347"
    ]
},
  "bbox": [],
  "geometry": {"coordinates":[7.966667,47.566667],"type":"Point"}
}
=======
{"geometry":{"type":"Point","coordinates":[7.966667,47.566667]},"type":"Feature","properties":{"hierarchy":["tgn:7114971","tgn:7003692","tgn:1000003","tgn:7000084","tgn:7029392"],"placetype":["aat:300008347"],"id":7114971,"name:xx":"Obers\u00e4ckingen"}}
>>>>>>> 03f74aca74312dbeaf24d7e61306dd6a786dc3d0
