{
  "id": 2529997,
  "type": "Feature",
  "properties": {
    "tgn:hierarchy":[
        "tgn:2529997",
        "tgn:1000001",
        "tgn:2000463",
        "tgn:7012149",
        "tgn:7007250",
        "tgn:7029392"
    ],
    "tgn:id":2529997,
    "tgn:name":"Mud Spring",
    "tgn:placetype":[
        "aat:300008697"
    ]
},
  "bbox": [],
  "geometry": {"coordinates":[-113.1833,44.15],"type":"Point"}
}