{
  "id": 2196068,
  "type": "Feature",
  "properties": {
    "tgn:hierarchy":[
        "tgn:2196068",
        "tgn:1000001",
        "tgn:7012149",
        "tgn:2001713",
        "tgn:7007708",
        "tgn:7029392"
    ],
    "tgn:id":2196068,
    "tgn:name":"Brockhurst Creek",
    "tgn:placetype":[
        "aat:300008706"
    ]
},
  "bbox": [],
  "geometry": {"coordinates":[-123.5333,41.45],"type":"Point"}
}