{
  "id": 2383256,
  "type": "Feature",
  "properties": {
    "tgn:hierarchy":[
        "tgn:2383256",
        "tgn:2002137",
        "tgn:1000001",
        "tgn:7012149",
        "tgn:7007919",
        "tgn:7029392"
    ],
    "tgn:id":2383256,
    "tgn:name":"Heard Mountain",
    "tgn:placetype":[
        "aat:300008798"
    ]
},
  "bbox": [],
  "geometry": {"coordinates":[-78.7333,37.9167],"type":"Point"}
}