{
  "id": 2143231,
  "type": "Feature",
  "properties": {
    "tgn:hierarchy":[
        "tgn:2143231",
        "tgn:1002716",
        "tgn:1000001",
        "tgn:7012149",
        "tgn:7007711",
        "tgn:7029392"
    ],
    "tgn:id":2143231,
    "tgn:name":"Bailey Brook",
    "tgn:placetype":[
        "aat:300008699"
    ]
},
  "bbox": [],
  "geometry": {"coordinates":[-71.2833,41.5333],"type":"Point"}
}