{
  "id": 2478925,
  "type": "Feature",
  "properties": {
    "tgn:hierarchy":[
        "tgn:2478925",
        "tgn:1000001",
        "tgn:7012149",
        "tgn:2000910",
        "tgn:7007256",
        "tgn:7029392"
    ],
    "tgn:id":2478925,
    "tgn:name":"Magee Canal",
    "tgn:placetype":[
        "aat:300006075"
    ]
},
  "bbox": [],
  "geometry": {"coordinates":[-92.0833,29.8333],"type":"Point"}
}