{
  "id": 2398589,
  "type": "Feature",
  "properties": {
    "tgn:hierarchy":[
        "tgn:2398589",
        "tgn:1000001",
        "tgn:1002184",
        "tgn:7012149",
        "tgn:7007252",
        "tgn:7029392"
    ],
    "tgn:id":2398589,
    "tgn:name":"Hoover Park",
    "tgn:placetype":[
        "aat:300008347"
    ]
},
  "bbox": [],
  "geometry": {"coordinates":[-85.35,40.45],"type":"Point"}
}