{
  "id": 7132845,
  "type": "Feature",
  "properties": {
    "tgn:hierarchy":[
        "tgn:7132845",
        "tgn:7003669",
        "tgn:1000003",
        "tgn:7000084",
        "tgn:7029392"
    ],
    "tgn:id":7132845,
    "tgn:name":"M\u00f6dingen",
    "tgn:placetype":[
        "aat:300008347"
    ]
},
  "bbox": [],
  "geometry": {"coordinates":[10.433333,48.65],"type":"Point"}
}