{
  "id": 2136599,
  "type": "Feature",
  "properties": {
    "tgn:hierarchy":[
        "tgn:2136599",
        "tgn:1000001",
        "tgn:7012149",
        "tgn:7029392"
    ],
    "tgn:id":2136599,
    "tgn:name":"Archie Creek",
    "tgn:placetype":[
        "aat:300008706"
    ]
},
  "bbox": [],
  "geometry": {"coordinates":[-110.5167,40.9333],"type":"Point"}
}