<<<<<<< HEAD
{
  "id": 2764533,
  "type": "Feature",
  "properties": {
    "tgn:hierarchy":[
        "tgn:2764533",
        "tgn:1000001",
        "tgn:7012149",
        "tgn:7013941",
        "tgn:7007568",
        "tgn:7029392"
    ],
    "tgn:id":2764533,
    "tgn:name":"Whipple Hill",
    "tgn:placetype":[
        "aat:300008798"
    ]
},
  "bbox": [],
  "geometry": {"coordinates":[-74.1,44.7167],"type":"Point"}
}
=======
{"geometry":{"type":"Point","coordinates":[-74.100000,44.716700]},"type":"Feature","properties":{"hierarchy":["tgn:2764533","tgn:1000001","tgn:7012149","tgn:7013941","tgn:7007568","tgn:7029392"],"placetype":["aat:300008798"],"id":2764533,"name:xx":"Whipple Hill"}}
>>>>>>> 03f74aca74312dbeaf24d7e61306dd6a786dc3d0
