{
  "id": 2364621,
  "type": "Feature",
  "properties": {
    "tgn:hierarchy":[
        "tgn:2364621",
        "tgn:1000001",
        "tgn:2000307",
        "tgn:7012149",
        "tgn:7007248",
        "tgn:7029392"
    ],
    "tgn:id":2364621,
    "tgn:name":"Greenbriar",
    "tgn:placetype":[
        "aat:300008347"
    ]
},
  "bbox": [],
  "geometry": {"coordinates":[-81.7667,32.4167],"type":"Point"}
}