{
  "id": 7500079,
  "type": "Feature",
  "properties": {
    "tgn:hierarchy":[
        "tgn:7500079",
        "tgn:7001004",
        "tgn:1000004",
        "tgn:1000141",
        "tgn:7029392"
    ],
    "tgn:id":7500079,
    "tgn:name":"Mingcheng Qiao",
    "tgn:placetype":[
        "aat:300007836"
    ]
},
  "bbox": [],
  "geometry": {"coordinates":[120.31595,22.659738],"type":"Point"}
}