{
  "id": 2127361,
  "type": "Feature",
  "properties": {
    "tgn:hierarchy":[
        "tgn:2127361",
        "tgn:1000001",
        "tgn:7012149",
        "tgn:7007158",
        "tgn:2000248",
        "tgn:7029392"
    ],
    "tgn:id":2127361,
    "tgn:name":"Ajax Peak",
    "tgn:placetype":[
        "aat:300008798"
    ]
},
  "bbox": [],
  "geometry": {"coordinates":[-107.75,37.9167],"type":"Point"}
}