<<<<<<< HEAD
{
  "id": 2409303,
  "type": "Feature",
  "properties": {
    "tgn:hierarchy":[
        "tgn:2409303",
        "tgn:1000001",
        "tgn:7012149",
        "tgn:2000238",
        "tgn:7007158",
        "tgn:7029392"
    ],
    "tgn:id":2409303,
    "tgn:name":"Icy Gulch",
    "tgn:placetype":[
        "aat:300008761"
    ]
},
  "bbox": [],
  "geometry": {"coordinates":[-105.7167,39.4833],"type":"Point"}
}
=======
{"geometry":{"type":"Point","coordinates":[-105.716700,39.483300]},"type":"Feature","properties":{"hierarchy":["tgn:2409303","tgn:1000001","tgn:7012149","tgn:2000238","tgn:7007158","tgn:7029392"],"placetype":["aat:300008761"],"id":2409303,"name:xx":"Icy Gulch"}}
>>>>>>> 03f74aca74312dbeaf24d7e61306dd6a786dc3d0
