{
  "id": 7239013,
  "type": "Feature",
  "properties": {
    "tgn:hierarchy":[
        "tgn:7239013",
        "tgn:7018239",
        "tgn:1000003",
        "tgn:1000063",
        "tgn:7018236",
        "tgn:7029392"
    ],
    "tgn:id":7239013,
    "tgn:name":"Gellenberg",
    "tgn:placetype":[
        "aat:300005567"
    ]
},
  "bbox": [],
  "geometry": {"coordinates":[4.834276,50.887547],"type":"Point"}
}