{
  "id": 2178045,
  "type": "Feature",
  "properties": {
    "tgn:hierarchy":[
        "tgn:2178045",
        "tgn:1000001",
        "tgn:2000465",
        "tgn:7012149",
        "tgn:7007250",
        "tgn:7029392"
    ],
    "tgn:id":2178045,
    "tgn:name":"Blackburn Island",
    "tgn:placetype":[
        "aat:300008791"
    ]
},
  "bbox": [],
  "geometry": {"coordinates":[-116.7167,43.4333],"type":"Point"}
}