{
  "id": 7325384,
  "type": "Feature",
  "properties": {
    "tgn:hierarchy":[
        "tgn:7325384",
        "tgn:1001439",
        "tgn:1000003",
        "tgn:7002797",
        "tgn:1000095",
        "tgn:7029392"
    ],
    "tgn:id":7325384,
    "tgn:name":"Santomera",
    "tgn:placetype":[
        "aat:300008347"
    ]
},
  "bbox": [],
  "geometry": {"coordinates":[-1.05,38.066667],"type":"Point"}
}