{
  "id": 2576896,
  "type": "Feature",
  "properties": {
    "tgn:hierarchy":[
        "tgn:2576896",
        "tgn:1000001",
        "tgn:7012149",
        "tgn:1002742",
        "tgn:7007920",
        "tgn:7029392"
    ],
    "tgn:id":2576896,
    "tgn:name":"Pete Creek",
    "tgn:placetype":[
        "aat:300008706"
    ]
},
  "bbox": [],
  "geometry": {"coordinates":[-120.2333,48.5333],"type":"Point"}
}