<<<<<<< HEAD
{
  "id": 2768281,
  "type": "Feature",
  "properties": {
    "tgn:hierarchy":[
        "tgn:2768281",
        "tgn:1000001",
        "tgn:7012149",
        "tgn:2001767",
        "tgn:7007712",
        "tgn:7029392"
    ],
    "tgn:id":2768281,
    "tgn:name":"Whites Pond Crossroad",
    "tgn:placetype":[
        "aat:300008347"
    ]
},
  "bbox": [],
  "geometry": {"coordinates":[-80.3167,33.9667],"type":"Point"}
}
=======
{"geometry":{"type":"Point","coordinates":[-80.316700,33.966700]},"type":"Feature","properties":{"hierarchy":["tgn:2768281","tgn:1000001","tgn:7012149","tgn:2001767","tgn:7007712","tgn:7029392"],"placetype":["aat:300008347"],"id":2768281,"name:xx":"Whites Pond Crossroad"}}
>>>>>>> 03f74aca74312dbeaf24d7e61306dd6a786dc3d0
