{
  "id": 1021809,
  "type": "Feature",
  "properties": {
    "tgn:hierarchy":[
        "tgn:1021809",
        "tgn:7006260",
        "tgn:7002454",
        "tgn:1000047",
        "tgn:1000002",
        "tgn:7029392"
    ],
    "tgn:id":1021809,
    "tgn:name":"Jaciara",
    "tgn:placetype":[
        "aat:300008347"
    ]
},
  "bbox": [],
  "geometry": {"coordinates":[-54.95,-15.9833],"type":"Point"}
}