{
  "id": 2589721,
  "type": "Feature",
  "properties": {
    "tgn:hierarchy":[
        "tgn:2589721",
        "tgn:1000001",
        "tgn:7012149",
        "tgn:2001616",
        "tgn:7007706",
        "tgn:7029392"
    ],
    "tgn:id":2589721,
    "tgn:name":"Point Rock",
    "tgn:placetype":[
        "aat:300008347"
    ]
},
  "bbox": [],
  "geometry": {"coordinates":[-82.2833,39.1333],"type":"Point"}
}