{
  "id": 2537072,
  "type": "Feature",
  "properties": {
    "tgn:hierarchy":[
        "tgn:2537072",
        "tgn:1000001",
        "tgn:7012149",
        "tgn:2001716",
        "tgn:7007708",
        "tgn:7029392"
    ],
    "tgn:id":2537072,
    "tgn:name":"Neely Mountain",
    "tgn:placetype":[
        "aat:300008798"
    ]
},
  "bbox": [],
  "geometry": {"coordinates":[-123.8833,44.0333],"type":"Point"}
}