{
  "id": 7423592,
  "type": "Feature",
  "properties": {
    "tgn:hierarchy":[
        "tgn:7423592",
        "tgn:1000001",
        "tgn:1001960",
        "tgn:7005560",
        "tgn:7029392"
    ],
    "tgn:id":7423592,
    "tgn:name":"La Honda, R\u00edo",
    "tgn:placetype":[
        "aat:300008699"
    ]
},
  "bbox": [],
  "geometry": {"coordinates":[-111.166667,28.616667],"type":"Point"}
}