{
  "id": 7480330,
  "type": "Feature",
  "properties": {
    "tgn:hierarchy":[
        "tgn:7480330",
        "tgn:7001010",
        "tgn:1000004",
        "tgn:1000141",
        "tgn:7029392"
    ],
    "tgn:id":7480330,
    "tgn:name":"Fuxingdongcun",
    "tgn:placetype":[
        "aat:300008347"
    ]
},
  "bbox": [],
  "geometry": {"coordinates":[121.583333,23.956389],"type":"Point"}
}