{
  "id": 1069559,
  "type": "Feature",
  "properties": {
    "tgn:hierarchy":[
        "tgn:1069559",
        "tgn:1000004",
        "tgn:7002077",
        "tgn:1000111",
        "tgn:7029392"
    ],
    "tgn:id":1069559,
    "tgn:name":"Konglongshan",
    "tgn:placetype":[
        "aat:300008347"
    ]
},
  "bbox": [],
  "geometry": {"coordinates":[117.2833,40.55],"type":"Point"}
}