{
  "id": 2580119,
  "type": "Feature",
  "properties": {
    "tgn:hierarchy":[
        "tgn:2580119",
        "tgn:2000452",
        "tgn:1000001",
        "tgn:7012149",
        "tgn:7007250",
        "tgn:7029392"
    ],
    "tgn:id":2580119,
    "tgn:name":"Pierce Gulch",
    "tgn:placetype":[
        "aat:300008761"
    ]
},
  "bbox": [],
  "geometry": {"coordinates":[-116.2167,43.6833],"type":"Point"}
}