{
  "id": 2268655,
  "type": "Feature",
  "properties": {
    "tgn:hierarchy":[
        "tgn:2268655",
        "tgn:1000001",
        "tgn:7012149",
        "tgn:1002837",
        "tgn:7007255",
        "tgn:7029392"
    ],
    "tgn:id":2268655,
    "tgn:name":"Cross Branch",
    "tgn:placetype":[
        "aat:300008699"
    ]
},
  "bbox": [],
  "geometry": {"coordinates":[-83.35,38.0667],"type":"Point"}
}