{
  "id": 2223514,
  "type": "Feature",
  "properties": {
    "tgn:hierarchy":[
        "tgn:2223514",
        "tgn:1000001",
        "tgn:7012149",
        "tgn:2001872",
        "tgn:7007825",
        "tgn:7029392"
    ],
    "tgn:id":2223514,
    "tgn:name":"Carter Branch",
    "tgn:placetype":[
        "aat:300008699"
    ]
},
  "bbox": [],
  "geometry": {"coordinates":[-88.2167,35.3833],"type":"Point"}
}