{
  "id": 7257161,
  "type": "Feature",
  "properties": {
    "tgn:hierarchy":[
        "tgn:7257161",
        "tgn:7016796",
        "tgn:7593115",
        "tgn:7593112",
        "tgn:1000001",
        "tgn:7029392"
    ],
    "tgn:id":7257161,
    "tgn:name:nl":"Marys Point",
    "tgn:placetype":[
        "aat:300387200"
    ]
},
  "bbox": [],
  "geometry": {"coordinates":[-63.233333,17.65],"type":"Point"}
}