{
  "id": 7221002,
  "type": "Feature",
  "properties": {
    "tgn:hierarchy":[
        "tgn:7221002",
        "tgn:7002711",
        "tgn:7001338",
        "tgn:1000003",
        "tgn:1000074",
        "tgn:7029392"
    ],
    "tgn:id":7221002,
    "tgn:name":"Koulo\u00fara",
    "tgn:placetype":[
        "aat:300008347"
    ]
},
  "bbox": [],
  "geometry": {"coordinates":[19.938889,39.748889],"type":"Point"}
}