{
  "id": 2391393,
  "type": "Feature",
  "properties": {
    "tgn:hierarchy":[
        "tgn:2391393",
        "tgn:1000001",
        "tgn:7012149",
        "tgn:2001762",
        "tgn:7007712",
        "tgn:7029392"
    ],
    "tgn:id":2391393,
    "tgn:name":"Hilldale",
    "tgn:placetype":[
        "aat:300008347"
    ]
},
  "bbox": [],
  "geometry": {"coordinates":[-80.85,33.5333],"type":"Point"}
}