{
  "id": 2037642,
  "type": "Feature",
  "properties": {
    "tgn:hierarchy":[
        "tgn:2037642",
        "tgn:1000001",
        "tgn:7012149",
        "tgn:2000806",
        "tgn:7007255",
        "tgn:7029392"
    ],
    "tgn:id":2037642,
    "tgn:name":"Bearville",
    "tgn:placetype":[
        "aat:300008347"
    ]
},
  "bbox": [],
  "geometry": {"coordinates":[-83.0667,37.3667],"type":"Point"}
}