{
  "id": 2749467,
  "type": "Feature",
  "properties": {
    "tgn:hierarchy":[
        "tgn:2749467",
        "tgn:1000001",
        "tgn:7012149",
        "tgn:7007707",
        "tgn:7029392"
    ],
    "tgn:id":2749467,
    "tgn:name":"Walnut Bayou",
    "tgn:placetype":[
        "aat:300008699"
    ]
},
  "bbox": [],
  "geometry": {"coordinates":[-97.3167,34.15],"type":"Point"}
}