{
  "id": 2395612,
  "type": "Feature",
  "properties": {
    "tgn:hierarchy":[
        "tgn:2395612",
        "tgn:1000001",
        "tgn:7012149",
        "tgn:7007706",
        "tgn:7029392"
    ],
    "tgn:id":2395612,
    "tgn:name":"Holliday Run",
    "tgn:placetype":[
        "aat:300008699"
    ]
},
  "bbox": [],
  "geometry": {"coordinates":[-83.4167,39.3667],"type":"Point"}
}