{
  "id": 7432293,
  "type": "Feature",
  "properties": {
    "tgn:hierarchy":[
        "tgn:7432293",
        "tgn:7005583",
        "tgn:1000001",
        "tgn:7005560",
        "tgn:7029392"
    ],
    "tgn:id":7432293,
    "tgn:name":"Las Espinas",
    "tgn:placetype":[
        "aat:300008347"
    ]
},
  "bbox": [],
  "geometry": {"coordinates":[-104.483333,22.65],"type":"Point"}
}