{
  "id": 7544857,
  "type": "Feature",
  "properties": {
    "tgn:hierarchy":[
        "tgn:7544857",
        "tgn:1000004",
        "tgn:7000198",
        "tgn:7016722",
        "tgn:7029392"
    ],
    "tgn:id":7544857,
    "tgn:name:en":"B\u0101bai",
    "tgn:placetype":[
        "aat:300008347"
    ]
},
  "bbox": [],
  "geometry": {"coordinates":[79.460868,26.171249],"type":"Point"}
}