{
  "id": 2118212,
  "type": "Feature",
  "properties": {
    "tgn:hierarchy":[
        "tgn:2118212",
        "tgn:1000001",
        "tgn:7012149",
        "tgn:2002273",
        "tgn:7013961",
        "tgn:7029392"
    ],
    "tgn:id":2118212,
    "tgn:name":"Fanco",
    "tgn:placetype":[
        "aat:300008347"
    ]
},
  "bbox": [],
  "geometry": {"coordinates":[-81.8167,37.7667],"type":"Point"}
}