{
  "id": 7110261,
  "type": "Feature",
  "properties": {
    "tgn:hierarchy":[
        "tgn:7110261",
        "tgn:1000003",
        "tgn:7003676",
        "tgn:7000084",
        "tgn:7029392"
    ],
    "tgn:id":7110261,
    "tgn:name":"Reidump",
    "tgn:placetype":[
        "aat:300008347"
    ]
},
  "bbox": [],
  "geometry": {"coordinates":[7.466667,53.65],"type":"Point"}
}