{
  "id": 1042057,
  "type": "Feature",
  "properties": {
    "tgn:hierarchy":[
        "tgn:1042057",
        "tgn:7002681",
        "tgn:7001395",
        "tgn:1000003",
        "tgn:1000074",
        "tgn:7010869",
        "tgn:7029392"
    ],
    "tgn:id":1042057,
    "tgn:name":"Karav\u00e1s",
    "tgn:placetype":[
        "aat:300008347"
    ]
},
  "bbox": [],
  "geometry": {"coordinates":[22.95,36.35],"type":"Point"}
}