<<<<<<< HEAD
{
  "id": 7470477,
  "type": "Feature",
  "properties": {
    "tgn:hierarchy":[
        "tgn:7470477",
        "tgn:1000004",
        "tgn:7490934",
        "tgn:1000141",
        "tgn:7029392"
    ],
    "tgn:id":7470477,
    "tgn:name":"Zhutoupai",
    "tgn:placetype":[
        "aat:300008347"
    ]
},
  "bbox": [],
  "geometry": {"coordinates":[120.4825,23.283611],"type":"Point"}
}
=======
{"geometry":{"type":"Point","coordinates":[120.482500,23.283611]},"type":"Feature","properties":{"hierarchy":["tgn:7470477","tgn:1000004","tgn:7490934","tgn:1000141","tgn:7029392"],"placetype":["aat:300008347"],"id":7470477,"name:xx":"Zhutoupai"}}
>>>>>>> 03f74aca74312dbeaf24d7e61306dd6a786dc3d0
