<<<<<<< HEAD
{
  "id": 2257056,
  "type": "Feature",
  "properties": {
    "tgn:hierarchy":[
        "tgn:2257056",
        "tgn:1000001",
        "tgn:7012149",
        "tgn:2000659",
        "tgn:7007253",
        "tgn:7029392"
    ],
    "tgn:id":2257056,
    "tgn:name":"Cornelia, Lake",
    "tgn:placetype":[
        "aat:300008680"
    ]
},
  "bbox": [],
  "geometry": {"coordinates":[-93.6833,42.7833],"type":"Point"}
}
=======
{"geometry":{"type":"Point","coordinates":[-93.683300,42.783300]},"type":"Feature","properties":{"hierarchy":["tgn:2257056","tgn:1000001","tgn:7012149","tgn:2000659","tgn:7007253","tgn:7029392"],"placetype":["aat:300008680"],"id":2257056,"name:xx":"Cornelia, Lake"}}
>>>>>>> 03f74aca74312dbeaf24d7e61306dd6a786dc3d0
