{
  "id": 2719899,
  "type": "Feature",
  "properties": {
    "tgn:hierarchy":[
        "tgn:2719899",
        "tgn:1000001",
        "tgn:1002185",
        "tgn:7012149",
        "tgn:7007710",
        "tgn:7029392"
    ],
    "tgn:id":2719899,
    "tgn:name":"Three Springs Run",
    "tgn:placetype":[
        "aat:300008699"
    ]
},
  "bbox": [],
  "geometry": {"coordinates":[-78.3333,40.7167],"type":"Point"}
}