{
  "id": 1093434,
  "type": "Feature",
  "properties": {
    "tgn:hierarchy":[
        "tgn:1093434",
        "tgn:7001242",
        "tgn:7017583",
        "tgn:1000193",
        "tgn:7029392"
    ],
    "tgn:id":1093434,
    "tgn:name":"Nieu Bethesda",
    "tgn:placetype":[
        "aat:300008347"
    ]
},
  "bbox": [],
  "geometry": {"coordinates":[24.5667,-31.8667],"type":"Point"}
}