{
  "id": 7589466,
  "type": "Feature",
  "properties": {
    "tgn:hierarchy":[
        "tgn:7589466",
        "tgn:1000004",
        "tgn:7000198",
        "tgn:7000799",
        "tgn:7029392"
    ],
    "tgn:id":7589466,
    "tgn:name:en":"P\u012br Badesar",
    "tgn:placetype":[
        "aat:300008347"
    ]
},
  "bbox": [],
  "geometry": {"coordinates":[74.152778,33.302778],"type":"Point"}
}