<<<<<<< HEAD
{
  "id": 2252598,
  "type": "Feature",
  "properties": {
    "tgn:hierarchy":[
        "tgn:2252598",
        "tgn:1000001",
        "tgn:7012149",
        "tgn:2001437",
        "tgn:7007566",
        "tgn:7029392"
    ],
    "tgn:id":2252598,
    "tgn:name":"Connecticut",
    "tgn:placetype":[
        "aat:300000390"
    ]
},
  "bbox": [],
  "geometry": {"coordinates":[-108.2667,32.7667],"type":"Point"}
}
=======
{"geometry":{"type":"Point","coordinates":[-108.266700,32.766700]},"type":"Feature","properties":{"hierarchy":["tgn:2252598","tgn:1000001","tgn:7012149","tgn:2001437","tgn:7007566","tgn:7029392"],"placetype":["aat:300000390"],"id":2252598,"name:xx":"Connecticut"}}
>>>>>>> 03f74aca74312dbeaf24d7e61306dd6a786dc3d0
