{
  "id": 7553903,
  "type": "Feature",
  "properties": {
    "tgn:hierarchy":[
        "tgn:7553903",
        "tgn:1000004",
        "tgn:7000198",
        "tgn:7001797",
        "tgn:7029392"
    ],
    "tgn:id":7553903,
    "tgn:name:en":"Musiri",
    "tgn:placetype":[
        "aat:300008347"
    ]
},
  "bbox": [],
  "geometry": {"coordinates":[78.45,10.933333],"type":"Point"}
}