{
  "id": 2357396,
  "type": "Feature",
  "properties": {
    "tgn:hierarchy":[
        "tgn:2357396",
        "tgn:1000001",
        "tgn:1002724",
        "tgn:7012149",
        "tgn:7007517",
        "tgn:7029392"
    ],
    "tgn:id":2357396,
    "tgn:name":"Government Island",
    "tgn:placetype":[
        "aat:300008850"
    ]
},
  "bbox": [],
  "geometry": {"coordinates":[-70.7833,42.2333],"type":"Point"}
}