<<<<<<< HEAD
{
  "id": 2251391,
  "type": "Feature",
  "properties": {
    "tgn:hierarchy":[
        "tgn:2251391",
        "tgn:1000001",
        "tgn:7012149",
        "tgn:1002387",
        "tgn:7007710",
        "tgn:7029392"
    ],
    "tgn:id":2251391,
    "tgn:name":"Comet Lake",
    "tgn:placetype":[
        "aat:300006191"
    ]
},
  "bbox": [],
  "geometry": {"coordinates":[-77.5,39.7333],"type":"Point"}
}
=======
{"geometry":{"type":"Point","coordinates":[-77.500000,39.733300]},"type":"Feature","properties":{"hierarchy":["tgn:2251391","tgn:1000001","tgn:7012149","tgn:1002387","tgn:7007710","tgn:7029392"],"placetype":["aat:300006191"],"id":2251391,"name:xx":"Comet Lake"}}
>>>>>>> 03f74aca74312dbeaf24d7e61306dd6a786dc3d0
