<<<<<<< HEAD
{
  "id": 2259801,
  "type": "Feature",
  "properties": {
    "tgn:hierarchy":[
        "tgn:2259801",
        "tgn:1000001",
        "tgn:7012149",
        "tgn:2001723",
        "tgn:7007708",
        "tgn:7029392"
    ],
    "tgn:id":2259801,
    "tgn:name":"Cougar Ridge",
    "tgn:placetype":[
        "aat:300266640"
    ]
},
  "bbox": [],
  "geometry": {"coordinates":[-119.6833,44.3833],"type":"Point"}
}
=======
{"geometry":{"type":"Point","coordinates":[-119.683300,44.383300]},"type":"Feature","properties":{"hierarchy":["tgn:2259801","tgn:1000001","tgn:7012149","tgn:2001723","tgn:7007708","tgn:7029392"],"placetype":["aat:300266640"],"id":2259801,"name:xx":"Cougar Ridge"}}
>>>>>>> 03f74aca74312dbeaf24d7e61306dd6a786dc3d0
