{
  "id": 2259801,
  "type": "Feature",
  "properties": {
    "tgn:hierarchy":[
        "tgn:2259801",
        "tgn:1000001",
        "tgn:7012149",
        "tgn:2001723",
        "tgn:7007708",
        "tgn:7029392"
    ],
    "tgn:id":2259801,
    "tgn:name":"Cougar Ridge",
    "tgn:placetype":[
        "aat:300266640"
    ]
},
  "bbox": [],
  "geometry": {"coordinates":[-119.6833,44.3833],"type":"Point"}
}