{
  "id": 2475198,
  "type": "Feature",
  "properties": {
    "tgn:hierarchy":[
        "tgn:2475198",
        "tgn:1000001",
        "tgn:2002202",
        "tgn:7012149",
        "tgn:7007919",
        "tgn:7029392"
    ],
    "tgn:id":2475198,
    "tgn:name":"Loxley Gardens",
    "tgn:placetype":[
        "aat:300008347"
    ]
},
  "bbox": [],
  "geometry": {"coordinates":[-76.3333,36.7667],"type":"Point"}
}