<<<<<<< HEAD
{
  "id": 2767804,
  "type": "Feature",
  "properties": {
    "tgn:hierarchy":[
        "tgn:2767804",
        "tgn:1000001",
        "tgn:7012149",
        "tgn:2000641",
        "tgn:7007253",
        "tgn:7029392"
    ],
    "tgn:id":2767804,
    "tgn:name":"Whitehorse Access Public Hunting Area",
    "tgn:placetype":[
        "aat:300055621"
    ]
},
  "bbox": [],
  "geometry": {"coordinates":[-94.9,42.3],"type":"Point"}
}
=======
{"geometry":{"type":"Point","coordinates":[-94.900000,42.300000]},"type":"Feature","properties":{"hierarchy":["tgn:2767804","tgn:1000001","tgn:7012149","tgn:2000641","tgn:7007253","tgn:7029392"],"placetype":["aat:300055621"],"id":2767804,"name:xx":"Whitehorse Access Public Hunting Area"}}
>>>>>>> 03f74aca74312dbeaf24d7e61306dd6a786dc3d0
