{
  "id": 7543478,
  "type": "Feature",
  "properties": {
    "tgn:hierarchy":[
        "tgn:7543478",
        "tgn:7001242",
        "tgn:7016833",
        "tgn:1001225",
        "tgn:7029392"
    ],
    "tgn:id":7543478,
    "tgn:name:en":"Tir'at ash Sharq\u0101w\u012byah",
    "tgn:placetype":[
        "aat:300006075"
    ]
},
  "bbox": [],
  "geometry": {"coordinates":[31.783115,31.399328],"type":"Point"}
}