{
  "id": 7134090,
  "type": "Feature",
  "properties": {
    "tgn:hierarchy":[
        "tgn:7134090",
        "tgn:7003669",
        "tgn:1000003",
        "tgn:7000084",
        "tgn:7029392"
    ],
    "tgn:id":7134090,
    "tgn:name":"M\u00fchlberg",
    "tgn:placetype":[
        "aat:300008777"
    ]
},
  "bbox": [],
  "geometry": {"coordinates":[12.166667,49.416667],"type":"Point"}
}