{
  "id": 7387990,
  "type": "Feature",
  "properties": {
    "tgn:hierarchy":[
        "tgn:7387990",
        "tgn:1000001",
        "tgn:7005599",
        "tgn:7005560",
        "tgn:7029392"
    ],
    "tgn:id":7387990,
    "tgn:name":"Paso del Correo",
    "tgn:placetype":[
        "aat:300008347"
    ]
},
  "bbox": [],
  "geometry": {"coordinates":[-97.283333,20.316667],"type":"Point"}
}