{
  "id": 1091652,
  "type": "Feature",
  "properties": {
    "tgn:hierarchy":[
        "tgn:1091652",
        "tgn:1000821",
        "tgn:7001242",
        "tgn:1000180",
        "tgn:7029392"
    ],
    "tgn:id":1091652,
    "tgn:name":"Nangade",
    "tgn:placetype":[
        "aat:300008347"
    ]
},
  "bbox": [],
  "geometry": {"coordinates":[39.6167,11.0833],"type":"Point"}
}