{
  "id": 7519254,
  "type": "Feature",
  "properties": {
    "tgn:hierarchy":[
        "tgn:7519254",
        "tgn:1009227",
        "tgn:1000226",
        "tgn:7018437",
        "tgn:1000006",
        "tgn:7029392"
    ],
    "tgn:id":7519254,
    "tgn:name:en":"Brewster Glacier",
    "tgn:placetype":[
        "aat:300008835"
    ]
},
  "bbox": [],
  "geometry": {"coordinates":[169.433333,-44.083333],"type":"Point"}
}