{
  "id": 7570428,
  "type": "Feature",
  "properties": {
    "tgn:hierarchy":[
        "tgn:7570428",
        "tgn:1000004",
        "tgn:7000198",
        "tgn:7031786",
        "tgn:7029392"
    ],
    "tgn:id":7570428,
    "tgn:name:en":"Bhairgaon Walla",
    "tgn:placetype":[
        "aat:300008347"
    ]
},
  "bbox": [],
  "geometry": {"coordinates":[78.645618,29.880401],"type":"Point"}
}