{
  "id": 7031209,
  "type": "Feature",
  "properties": {
    "tgn:hierarchy":[
        "tgn:7031209",
        "tgn:7002445",
        "tgn:1000003",
        "tgn:7008168",
        "tgn:7008591",
        "tgn:7029392"
    ],
    "tgn:id":7031209,
    "tgn:name:en":"Ambrosden",
    "tgn:placetype":[
        "aat:300008347",
        "aat:300008372"
    ]
},
  "bbox": [],
  "geometry": {"coordinates":[-1.116667,51.85],"type":"Point"}
}