{
  "id": 2508246,
  "type": "Feature",
  "properties": {
    "tgn:hierarchy":[
        "tgn:2508246",
        "tgn:1000001",
        "tgn:7012149",
        "tgn:7007710",
        "tgn:7029392"
    ],
    "tgn:id":2508246,
    "tgn:name":"Middle Branch Wilson Run",
    "tgn:placetype":[
        "aat:300008699"
    ]
},
  "bbox": [],
  "geometry": {"coordinates":[-78.6167,41.25],"type":"Point"}
}