{
  "id": 7435335,
  "type": "Feature",
  "properties": {
    "tgn:hierarchy":[
        "tgn:7435335",
        "tgn:1000001",
        "tgn:7005595",
        "tgn:7005560",
        "tgn:7029392"
    ],
    "tgn:id":7435335,
    "tgn:name":"Zapotillo",
    "tgn:placetype":[
        "aat:300008347"
    ]
},
  "bbox": [],
  "geometry": {"coordinates":[-107.45,24.65],"type":"Point"}
}