{
  "id": 2280883,
  "type": "Feature",
  "properties": {
    "tgn:hierarchy":[
        "tgn:2280883",
        "tgn:1000001",
        "tgn:7012149",
        "tgn:2002123",
        "tgn:7007827",
        "tgn:7029392"
    ],
    "tgn:id":2280883,
    "tgn:name":"Deep Creek",
    "tgn:placetype":[
        "aat:300008706"
    ]
},
  "bbox": [],
  "geometry": {"coordinates":[-113.9833,40.0167],"type":"Point"}
}