{
  "id": 7199762,
  "type": "Feature",
  "properties": {
    "tgn:hierarchy":[
        "tgn:7199762",
        "tgn:7003669",
        "tgn:1000003",
        "tgn:7000084",
        "tgn:7029392"
    ],
    "tgn:id":7199762,
    "tgn:name":"Edhof",
    "tgn:placetype":[
        "aat:300000206"
    ]
},
  "bbox": [],
  "geometry": {"coordinates":[13.05,48.85],"type":"Point"}
}