{
  "id": 1006340,
  "type": "Feature",
  "properties": {
    "tgn:hierarchy":[
        "tgn:1006340",
        "tgn:7016712",
        "tgn:1000004",
        "tgn:1003406",
        "tgn:7018214",
        "tgn:7002435",
        "tgn:7029392"
    ],
    "tgn:id":1006340,
    "tgn:name":"Atlasova, Ostrov",
    "tgn:placetype":[
        "aat:300008791"
    ]
},
  "bbox": [],
  "geometry": {"coordinates":[155.4667,50.8833],"type":"Point"}
}