{
  "id": 7119694,
  "type": "Feature",
  "properties": {
    "tgn:hierarchy":[
        "tgn:7119694",
        "tgn:1000003",
        "tgn:7003682",
        "tgn:7000084",
        "tgn:7029392"
    ],
    "tgn:id":7119694,
    "tgn:name":"Presten Berg",
    "tgn:placetype":[
        "aat:300008777"
    ]
},
  "bbox": [],
  "geometry": {"coordinates":[7.95,49.25],"type":"Point"}
}