<<<<<<< HEAD
{
  "id": 7119694,
  "type": "Feature",
  "properties": {
    "tgn:hierarchy":[
        "tgn:7119694",
        "tgn:1000003",
        "tgn:7003682",
        "tgn:7000084",
        "tgn:7029392"
    ],
    "tgn:id":7119694,
    "tgn:name":"Presten Berg",
    "tgn:placetype":[
        "aat:300008777"
    ]
},
  "bbox": [],
  "geometry": {"coordinates":[7.95,49.25],"type":"Point"}
}
=======
{"geometry":{"type":"Point","coordinates":[7.950000,49.250000]},"type":"Feature","properties":{"hierarchy":["tgn:7119694","tgn:1000003","tgn:7003682","tgn:7000084","tgn:7029392"],"placetype":["aat:300008777"],"id":7119694,"name:xx":"Presten Berg"}}
>>>>>>> 03f74aca74312dbeaf24d7e61306dd6a786dc3d0
