<<<<<<< HEAD
{
  "id": 2251514,
  "type": "Feature",
  "properties": {
    "tgn:hierarchy":[
        "tgn:2251514",
        "tgn:1000001",
        "tgn:7012149",
        "tgn:2001917",
        "tgn:7007825",
        "tgn:7029392"
    ],
    "tgn:id":2251514,
    "tgn:name":"Commissary Ridge",
    "tgn:placetype":[
        "aat:300266640"
    ]
},
  "bbox": [],
  "geometry": {"coordinates":[-87.7167,36.4833],"type":"Point"}
}
=======
{"geometry":{"type":"Point","coordinates":[-87.716700,36.483300]},"type":"Feature","properties":{"hierarchy":["tgn:2251514","tgn:1000001","tgn:7012149","tgn:2001917","tgn:7007825","tgn:7029392"],"placetype":["aat:300266640"],"id":2251514,"name:xx":"Commissary Ridge"}}
>>>>>>> 03f74aca74312dbeaf24d7e61306dd6a786dc3d0
