{
  "id": 7415792,
  "type": "Feature",
  "properties": {
    "tgn:hierarchy":[
        "tgn:7415792",
        "tgn:1000001",
        "tgn:7005591",
        "tgn:7005560",
        "tgn:7029392"
    ],
    "tgn:id":7415792,
    "tgn:name:es":"El Papalote, Cerro",
    "tgn:placetype":[
        "aat:300008795"
    ]
},
  "bbox": [],
  "geometry": {"coordinates":[-98.072222,16.766944],"type":"Point"}
}