{
  "id": 7500114,
  "type": "Feature",
  "properties": {
    "tgn:hierarchy":[
        "tgn:7500114",
        "tgn:7001004",
        "tgn:1000004",
        "tgn:1000141",
        "tgn:7029392"
    ],
    "tgn:id":7500114,
    "tgn:name":"Dajiao Si",
    "tgn:placetype":[
        "aat:300007595"
    ]
},
  "bbox": [],
  "geometry": {"coordinates":[120.3716,22.7291],"type":"Point"}
}