<<<<<<< HEAD
{
  "id": 7352645,
  "type": "Feature",
  "properties": {
    "tgn:hierarchy":[
        "tgn:7352645",
        "tgn:7005587",
        "tgn:1000001",
        "tgn:7005560",
        "tgn:7029392"
    ],
    "tgn:id":7352645,
    "tgn:name":"Atengo",
    "tgn:placetype":[
        "aat:300008347"
    ]
},
  "bbox": [],
  "geometry": {"coordinates":[-99.333333,20.166667],"type":"Point"}
}
=======
{"geometry":{"type":"Point","coordinates":[-99.333333,20.166667]},"type":"Feature","properties":{"hierarchy":["tgn:7352645","tgn:7005587","tgn:1000001","tgn:7005560","tgn:7029392"],"placetype":["aat:300008347"],"id":7352645,"name:xx":"Atengo"}}
>>>>>>> 03f74aca74312dbeaf24d7e61306dd6a786dc3d0
