{
  "id": 7352645,
  "type": "Feature",
  "properties": {
    "tgn:hierarchy":[
        "tgn:7352645",
        "tgn:7005587",
        "tgn:1000001",
        "tgn:7005560",
        "tgn:7029392"
    ],
    "tgn:id":7352645,
    "tgn:name":"Atengo",
    "tgn:placetype":[
        "aat:300008347"
    ]
},
  "bbox": [],
  "geometry": {"coordinates":[-99.333333,20.166667],"type":"Point"}
}