{
  "id": 7497341,
  "type": "Feature",
  "properties": {
    "tgn:hierarchy":[
        "tgn:7497341",
        "tgn:1000004",
        "tgn:7001009",
        "tgn:1000141",
        "tgn:7029392"
    ],
    "tgn:id":7497341,
    "tgn:name":"Fenggu Guoxiao",
    "tgn:placetype":[
        "aat:300006495"
    ]
},
  "bbox": [],
  "geometry": {"coordinates":[120.7247,24.0339],"type":"Point"}
}