{
  "id": 7449867,
  "type": "Feature",
  "properties": {
    "tgn:hierarchy":[
        "tgn:7449867",
        "tgn:7002444",
        "tgn:7019088",
        "tgn:1000003",
        "tgn:7008591",
        "tgn:7029392"
    ],
    "tgn:id":7449867,
    "tgn:name:en":"Glazert Burn",
    "tgn:placetype":[
        "aat:300008699"
    ]
},
  "bbox": [],
  "geometry": {"coordinates":[-4.566667,55.65],"type":"Point"}
}