{
  "id": 1077624,
  "type": "Feature",
  "properties": {
    "tgn:hierarchy":[
        "tgn:1077624",
        "tgn:1000004",
        "tgn:1001338",
        "tgn:1000116",
        "tgn:7029392"
    ],
    "tgn:id":1077624,
    "tgn:name":"Dayu",
    "tgn:placetype":[
        "aat:300008347"
    ]
},
  "bbox": [],
  "geometry": {"coordinates":[115.0667,-1.9833],"type":"Point"}
}