{
  "id": 7580477,
  "type": "Feature",
  "properties": {
    "tgn:hierarchy":[
        "tgn:7580477",
        "tgn:1000004",
        "tgn:7000198",
        "tgn:1001998",
        "tgn:7029392"
    ],
    "tgn:id":7580477,
    "tgn:name:en":"Thor\u0101ng Tl\u0101ng",
    "tgn:placetype":[
        "aat:300008795"
    ]
},
  "bbox": [],
  "geometry": {"coordinates":[92.539862,23.250551],"type":"Point"}
}