{
  "id": 1009107,
  "type": "Feature",
  "properties": {
    "tgn:hierarchy":[
        "tgn:1009107",
        "tgn:7006247",
        "tgn:1000047",
        "tgn:7002456",
        "tgn:1000002",
        "tgn:7029392"
    ],
    "tgn:id":1009107,
    "tgn:name":"Serpa, Ilha da",
    "tgn:placetype":[
        "aat:300008791"
    ]
},
  "bbox": [],
  "geometry": {"coordinates":[-58.3167,-3.1167],"type":"Point"}
}