{
  "id": 2779744,
  "type": "Feature",
  "properties": {
    "tgn:hierarchy":[
        "tgn:2779744",
        "tgn:1000001",
        "tgn:7012149",
        "tgn:2000623",
        "tgn:7007253",
        "tgn:7029392"
    ],
    "tgn:id":2779744,
    "tgn:name":"Wolf Run",
    "tgn:placetype":[
        "aat:300008699"
    ]
},
  "bbox": [],
  "geometry": {"coordinates":[-93.0833,41.2167],"type":"Point"}
}