{
  "id": 7577351,
  "type": "Feature",
  "properties": {
    "tgn:hierarchy":[
        "tgn:7577351",
        "tgn:1000004",
        "tgn:7000198",
        "tgn:7031783",
        "tgn:7029392"
    ],
    "tgn:id":7577351,
    "tgn:name:en":"Kud\u0101da",
    "tgn:placetype":[
        "aat:300008347"
    ]
},
  "bbox": [],
  "geometry": {"coordinates":[86.204184,22.706729],"type":"Point"}
}