{
  "id": 7257842,
  "type": "Feature",
  "properties": {
    "tgn:hierarchy":[
        "tgn:7257842",
        "tgn:7003458",
        "tgn:1000003",
        "tgn:1000063",
        "tgn:7018236",
        "tgn:7029392"
    ],
    "tgn:id":7257842,
    "tgn:name":"Wulpendamme",
    "tgn:placetype":[
        "aat:300008347"
    ]
},
  "bbox": [],
  "geometry": {"coordinates":[2.69711,51.085332],"type":"Point"}
}