<<<<<<< HEAD
{
  "id": 2336953,
  "type": "Feature",
  "properties": {
    "tgn:hierarchy":[
        "tgn:2336953",
        "tgn:1000001",
        "tgn:7012149",
        "tgn:1003020",
        "tgn:7007920",
        "tgn:7029392"
    ],
    "tgn:id":2336953,
    "tgn:name":"Fourmile Creek",
    "tgn:placetype":[
        "aat:300008706"
    ]
},
  "bbox": [],
  "geometry": {"coordinates":[-122.3833,48.8833],"type":"Point"}
}
=======
{"geometry":{"type":"Point","coordinates":[-122.383300,48.883300]},"type":"Feature","properties":{"hierarchy":["tgn:2336953","tgn:1000001","tgn:7012149","tgn:1003020","tgn:7007920","tgn:7029392"],"placetype":["aat:300008706"],"id":2336953,"name:xx":"Fourmile Creek"}}
>>>>>>> 03f74aca74312dbeaf24d7e61306dd6a786dc3d0
