{
  "id": 1012566,
  "type": "Feature",
  "properties": {
    "tgn:hierarchy":[
        "tgn:1012566",
        "tgn:7002445",
        "tgn:1000003",
        "tgn:7008131",
        "tgn:7008591",
        "tgn:7029392"
    ],
    "tgn:id":1012566,
    "tgn:name:en":"The Naze",
    "tgn:placetype":[
        "aat:300008850",
        "aat:300386846"
    ]
},
  "bbox": [],
  "geometry": {"coordinates":[1.283333,51.866667],"type":"Point"}
}