{
  "id": 1022655,
  "type": "Feature",
  "properties": {
    "tgn:hierarchy":[
        "tgn:1022655",
        "tgn:1001941",
        "tgn:1000047",
        "tgn:7002458",
        "tgn:1000002",
        "tgn:7029392"
    ],
    "tgn:id":1022655,
    "tgn:name":"Restinga Seca",
    "tgn:placetype":[
        "aat:300008347"
    ]
},
  "bbox": [],
  "geometry": {"coordinates":[-53.4167,-29.9167],"type":"Point"}
}