{
  "id": 2777396,
  "type": "Feature",
  "properties": {
    "tgn:hierarchy":[
        "tgn:2777396",
        "tgn:1000001",
        "tgn:7012149",
        "tgn:2002382",
        "tgn:7007923",
        "tgn:7029392"
    ],
    "tgn:id":2777396,
    "tgn:name":"Winifred Peak",
    "tgn:placetype":[
        "aat:300008798"
    ]
},
  "bbox": [],
  "geometry": {"coordinates":[-109.65,43.15],"type":"Point"}
}