{
  "id": 2665417,
  "type": "Feature",
  "properties": {
    "tgn:hierarchy":[
        "tgn:2665417",
        "tgn:1000001",
        "tgn:7012149",
        "tgn:2002038",
        "tgn:7007826",
        "tgn:7029392"
    ],
    "tgn:id":2665417,
    "tgn:name":"Singleton Tank",
    "tgn:placetype":[
        "aat:300006191"
    ]
},
  "bbox": [],
  "geometry": {"coordinates":[-100.1833,28.75],"type":"Point"}
}