{
  "id": 2738743,
  "type": "Feature",
  "properties": {
    "tgn:hierarchy":[
        "tgn:2738743",
        "tgn:1000001",
        "tgn:7012149",
        "tgn:2000213",
        "tgn:7007158",
        "tgn:7029392"
    ],
    "tgn:id":2738743,
    "tgn:name":"Union Ditch",
    "tgn:placetype":[
        "aat:300006075"
    ]
},
  "bbox": [],
  "geometry": {"coordinates":[-105.1167,38.3833],"type":"Point"}
}