{
  "id": 2690483,
  "type": "Feature",
  "properties": {
    "tgn:hierarchy":[
        "tgn:2690483",
        "tgn:1000001",
        "tgn:7012149",
        "tgn:2001719",
        "tgn:7007708",
        "tgn:7029392"
    ],
    "tgn:id":2690483,
    "tgn:name":"Stalder Creek",
    "tgn:placetype":[
        "aat:300008706"
    ]
},
  "bbox": [],
  "geometry": {"coordinates":[-119.2833,45.0833],"type":"Point"}
}