{
  "id": 2342642,
  "type": "Feature",
  "properties": {
    "tgn:hierarchy":[
        "tgn:2342642",
        "tgn:1002165",
        "tgn:1000001",
        "tgn:7012149",
        "tgn:7007517",
        "tgn:7029392"
    ],
    "tgn:id":2342642,
    "tgn:name":"Fund Pond",
    "tgn:placetype":[
        "aat:300008680"
    ]
},
  "bbox": [],
  "geometry": {"coordinates":[-70.15,41.7333],"type":"Point"}
}