{
  "id": 2500797,
  "type": "Feature",
  "properties": {
    "tgn:hierarchy":[
        "tgn:2500797",
        "tgn:1000001",
        "tgn:7012149",
        "tgn:2001769",
        "tgn:7007712",
        "tgn:7029392"
    ],
    "tgn:id":2500797,
    "tgn:name":"McElroy Branch",
    "tgn:placetype":[
        "aat:300008699"
    ]
},
  "bbox": [],
  "geometry": {"coordinates":[-79.7833,33.5667],"type":"Point"}
}