{
  "id": 2700851,
  "type": "Feature",
  "properties": {
    "tgn:hierarchy":[
        "tgn:2700851",
        "tgn:1000001",
        "tgn:7016172",
        "tgn:7012149",
        "tgn:2000173",
        "tgn:7029392"
    ],
    "tgn:id":2700851,
    "tgn:name":"Sugar Camp Hollow",
    "tgn:placetype":[
        "aat:300008761"
    ]
},
  "bbox": [],
  "geometry": {"coordinates":[-92.1333,35.7167],"type":"Point"}
}