{
  "id": 7041892,
  "type": "Feature",
  "properties": {
    "tgn:hierarchy":[
        "tgn:7041892",
        "tgn:1003430",
        "tgn:1000003",
        "tgn:7003126",
        "tgn:1000080",
        "tgn:7029392"
    ],
    "tgn:id":7041892,
    "tgn:name":"Saguignod",
    "tgn:placetype":[
        "aat:300008347"
    ]
},
  "bbox": [],
  "geometry": {"coordinates":[7.483333,45.783333],"type":"Point"}
}