{
  "id": 7312004,
  "type": "Feature",
  "properties": {
    "tgn:hierarchy":[
        "tgn:7312004",
        "tgn:1001630",
        "tgn:1000049",
        "tgn:1000002",
        "tgn:7029392"
    ],
    "tgn:id":7312004,
    "tgn:name":"Las Frazadas, Quebrada",
    "tgn:placetype":[
        "aat:300266554",
        "aat:300008699"
    ]
},
  "bbox": [],
  "geometry": {"coordinates":[-69.533333,-26.666667],"type":"Point"}
}