{
  "id": 7258004,
  "type": "Feature",
  "properties": {
    "tgn:hierarchy":[
        "tgn:7258004",
        "tgn:7003461",
        "tgn:1000003",
        "tgn:1000063",
        "tgn:7018236",
        "tgn:7029392"
    ],
    "tgn:id":7258004,
    "tgn:name":"Zammelen",
    "tgn:placetype":[
        "aat:300008347"
    ]
},
  "bbox": [],
  "geometry": {"coordinates":[5.406772,50.81401],"type":"Point"}
}