{
  "id": 7228589,
  "type": "Feature",
  "properties": {
    "tgn:hierarchy":[
        "tgn:7228589",
        "tgn:7002707",
        "tgn:7002705",
        "tgn:1000003",
        "tgn:1000074",
        "tgn:7029392"
    ],
    "tgn:id":7228589,
    "tgn:name":"M\u00fdloi",
    "tgn:placetype":[
        "aat:300008347"
    ]
},
  "bbox": [],
  "geometry": {"coordinates":[21.098333,39.778889],"type":"Point"}
}