{
  "id": 2117406,
  "type": "Feature",
  "properties": {
    "tgn:hierarchy":[
        "tgn:2117406",
        "tgn:1000001",
        "tgn:7012149",
        "tgn:2002296",
        "tgn:7013961",
        "tgn:7029392"
    ],
    "tgn:id":2117406,
    "tgn:name":"Benbush",
    "tgn:placetype":[
        "aat:300008347"
    ]
},
  "bbox": [],
  "geometry": {"coordinates":[-79.5167,39.15],"type":"Point"}
}