{
  "id": 7301649,
  "type": "Feature",
  "properties": {
    "tgn:hierarchy":[
        "tgn:7301649",
        "tgn:7001122",
        "tgn:1000003",
        "tgn:7002765",
        "tgn:1000095",
        "tgn:7029392"
    ],
    "tgn:id":7301649,
    "tgn:name":"Mola, Cabo de la",
    "tgn:placetype":[
        "aat:300008850"
    ]
},
  "bbox": [],
  "geometry": {"coordinates":[4.333333,39.883333],"type":"Point"}
}