{
  "id": 2369731,
  "type": "Feature",
  "properties": {
    "tgn:hierarchy":[
        "tgn:2369731",
        "tgn:1000001",
        "tgn:7012149",
        "tgn:2002186",
        "tgn:7007919",
        "tgn:7029392"
    ],
    "tgn:id":2369731,
    "tgn:name":"Gunter Ridge",
    "tgn:placetype":[
        "aat:300266640"
    ]
},
  "bbox": [],
  "geometry": {"coordinates":[-79.4667,37.5833],"type":"Point"}
}