{
  "id": 1060251,
  "type": "Feature",
  "properties": {
    "tgn:hierarchy":[
        "tgn:1060251",
        "tgn:1000004",
        "tgn:1003418",
        "tgn:7018214",
        "tgn:7002435",
        "tgn:7029392"
    ],
    "tgn:id":1060251,
    "tgn:name":"Terebush",
    "tgn:placetype":[
        "aat:300008347"
    ]
},
  "bbox": [],
  "geometry": {"coordinates":[38.1667,54.35],"type":"Point"}
}