<<<<<<< HEAD
{
  "id": 2408742,
  "type": "Feature",
  "properties": {
    "tgn:hierarchy":[
        "tgn:2408742",
        "tgn:1000001",
        "tgn:2001701",
        "tgn:7012149",
        "tgn:7007708",
        "tgn:7029392"
    ],
    "tgn:id":2408742,
    "tgn:name":"Hyde Creek",
    "tgn:placetype":[
        "aat:300008706"
    ]
},
  "bbox": [],
  "geometry": {"coordinates":[-123.4833,44.4833],"type":"Point"}
}
=======
{"geometry":{"type":"Point","coordinates":[-123.483300,44.483300]},"type":"Feature","properties":{"hierarchy":["tgn:2408742","tgn:1000001","tgn:2001701","tgn:7012149","tgn:7007708","tgn:7029392"],"placetype":["aat:300008706"],"id":2408742,"name:xx":"Hyde Creek"}}
>>>>>>> 03f74aca74312dbeaf24d7e61306dd6a786dc3d0
