{
  "id": 7025242,
  "type": "Feature",
  "properties": {
    "tgn:hierarchy":[
        "tgn:7025242",
        "tgn:7002445",
        "tgn:1000003",
        "tgn:7008118",
        "tgn:7008591",
        "tgn:7029392"
    ],
    "tgn:id":7025242,
    "tgn:name:ang":"Machenie",
    "tgn:placetype":[
        "aat:300008347"
    ]
},
  "bbox": [],
  "geometry": {"coordinates":[-1.4667,52.9833],"type":"Point"}
}