{
  "id": 2307842,
  "type": "Feature",
  "properties": {
    "tgn:hierarchy":[
        "tgn:2307842",
        "tgn:1000001",
        "tgn:2002242",
        "tgn:7012149",
        "tgn:7007920",
        "tgn:7029392"
    ],
    "tgn:id":2307842,
    "tgn:name":"East Foster Creek",
    "tgn:placetype":[
        "aat:300008706"
    ]
},
  "bbox": [],
  "geometry": {"coordinates":[-119.25,47.8833],"type":"Point"}
}