{
  "id": 7536836,
  "type": "Feature",
  "properties": {
    "tgn:hierarchy":[
        "tgn:7536836",
        "tgn:7001242",
        "tgn:7001311",
        "tgn:7016833",
        "tgn:7029392"
    ],
    "tgn:id":7536836,
    "tgn:name:en":"\u1e28ajar, Tal'at al",
    "tgn:placetype":[
        "aat:300008749"
    ]
},
  "bbox": [],
  "geometry": {"coordinates":[31.316667,27.283333],"type":"Point"}
}