<<<<<<< HEAD
{
  "id": 7027205,
  "type": "Feature",
  "properties": {
    "tgn:hierarchy":[
        "tgn:7027205",
        "tgn:7002804",
        "tgn:1000003",
        "tgn:7002793",
        "tgn:1000095",
        "tgn:7029392"
    ],
    "tgn:id":7027205,
    "tgn:name":"Santa Pola",
    "tgn:placetype":[
        "aat:300008347",
        "aat:300000810",
        "aat:300008372"
    ]
},
  "bbox": [],
  "geometry": {"coordinates":[0.5333,38.2],"type":"Point"}
}
=======
{"geometry":{"type":"Point","coordinates":[0.533300,38.200000]},"type":"Feature","properties":{"hierarchy":["tgn:7027205","tgn:7002804","tgn:1000003","tgn:7002793","tgn:1000095","tgn:7029392"],"placetype":["aat:300008347","aat:300000810","aat:300008372"],"id":7027205,"name:xx":"Santa Pola"}}
>>>>>>> 03f74aca74312dbeaf24d7e61306dd6a786dc3d0
