{
  "id": 1045278,
  "type": "Feature",
  "properties": {
    "tgn:hierarchy":[
        "tgn:1045278",
        "tgn:7003163",
        "tgn:1000003",
        "tgn:7009760",
        "tgn:1000080",
        "tgn:7029392"
    ],
    "tgn:id":1045278,
    "tgn:name":"Marradi",
    "tgn:placetype":[
        "aat:300008347"
    ]
},
  "bbox": [],
  "geometry": {"coordinates":[11.616667,44.066667],"type":"Point"}
}