{
  "id": 1001616,
  "type": "Feature",
  "properties": {
    "tgn:hierarchy":[
        "tgn:1001616",
        "tgn:1000004",
        "tgn:7018454",
        "tgn:1000144",
        "tgn:7029392"
    ],
    "tgn:id":1001616,
    "tgn:name":"Zonguldak",
    "tgn:placetype":[
        "aat:300387064",
        "aat:300000774"
    ]
},
  "bbox": [],
  "geometry": {"coordinates":[31.833,41.25],"type":"Point"}
}