{
  "id": 2041023,
  "type": "Feature",
  "properties": {
    "tgn:hierarchy":[
        "tgn:2041023",
        "tgn:1000001",
        "tgn:7012149",
        "tgn:2000801",
        "tgn:7007255",
        "tgn:7029392"
    ],
    "tgn:id":2041023,
    "tgn:name":"Richland",
    "tgn:placetype":[
        "aat:300008347"
    ]
},
  "bbox": [],
  "geometry": {"coordinates":[-87.5833,37.2667],"type":"Point"}
}