{
  "id": 7389662,
  "type": "Feature",
  "properties": {
    "tgn:hierarchy":[
        "tgn:7389662",
        "tgn:7005586",
        "tgn:1000001",
        "tgn:7005560",
        "tgn:7029392"
    ],
    "tgn:id":7389662,
    "tgn:name":"Salatillo",
    "tgn:placetype":[
        "aat:300008347"
    ]
},
  "bbox": [],
  "geometry": {"coordinates":[-104.133333,20.183333],"type":"Point"}
}