<<<<<<< HEAD
{
  "id": 2330214,
  "type": "Feature",
  "properties": {
    "tgn:hierarchy":[
        "tgn:2330214",
        "tgn:1000001",
        "tgn:2000922",
        "tgn:7012149",
        "tgn:7007515",
        "tgn:7029392"
    ],
    "tgn:id":2330214,
    "tgn:name":"Flanders Bay",
    "tgn:placetype":[
        "aat:300132316"
    ]
},
  "bbox": [],
  "geometry": {"coordinates":[-68.1333,44.4667],"type":"Point"}
}
=======
{"geometry":{"type":"Point","coordinates":[-68.133300,44.466700]},"type":"Feature","properties":{"hierarchy":["tgn:2330214","tgn:1000001","tgn:2000922","tgn:7012149","tgn:7007515","tgn:7029392"],"placetype":["aat:300132316"],"id":2330214,"name:xx":"Flanders Bay"}}
>>>>>>> 03f74aca74312dbeaf24d7e61306dd6a786dc3d0
