{
  "id": 2110544,
  "type": "Feature",
  "properties": {
    "tgn:hierarchy":[
        "tgn:2110544",
        "tgn:1000001",
        "tgn:7012149",
        "tgn:2002173",
        "tgn:7007919",
        "tgn:7029392"
    ],
    "tgn:id":2110544,
    "tgn:name":"Baskerville",
    "tgn:placetype":[
        "aat:300008347"
    ]
},
  "bbox": [],
  "geometry": {"coordinates":[-78.2667,36.6833],"type":"Point"}
}