{
  "id": 7534938,
  "type": "Feature",
  "properties": {
    "tgn:hierarchy":[
        "tgn:7534938",
        "tgn:7001242",
        "tgn:7016833",
        "tgn:1001335",
        "tgn:7029392"
    ],
    "tgn:id":7534938,
    "tgn:name":"Kawm al \u1e28ajar",
    "tgn:placetype":[
        "aat:300008347"
    ]
},
  "bbox": [],
  "geometry": {"coordinates":[31.139244,31.349226],"type":"Point"}
}