{
  "id": 7340029,
  "type": "Feature",
  "properties": {
    "tgn:hierarchy":[
        "tgn:7340029",
        "tgn:7002759",
        "tgn:7008909",
        "tgn:1000003",
        "tgn:1000095",
        "tgn:7029392"
    ],
    "tgn:id":7340029,
    "tgn:name":"Coscoll\u00e1, Sierra de",
    "tgn:placetype":[
        "aat:300266640"
    ]
},
  "bbox": [],
  "geometry": {"coordinates":[0.416667,41.933333],"type":"Point"}
}