<<<<<<< HEAD
{
  "id": 2330052,
  "type": "Feature",
  "properties": {
    "tgn:hierarchy":[
        "tgn:2330052",
        "tgn:1000001",
        "tgn:2001635",
        "tgn:7012149",
        "tgn:7007707",
        "tgn:7029392"
    ],
    "tgn:id":2330052,
    "tgn:name":"Flagg Springs",
    "tgn:placetype":[
        "aat:300008697"
    ]
},
  "bbox": [],
  "geometry": {"coordinates":[-102.5333,36.85],"type":"Point"}
}
=======
{"geometry":{"type":"Point","coordinates":[-102.533300,36.850000]},"type":"Feature","properties":{"hierarchy":["tgn:2330052","tgn:1000001","tgn:2001635","tgn:7012149","tgn:7007707","tgn:7029392"],"placetype":["aat:300008697"],"id":2330052,"name:xx":"Flagg Springs"}}
>>>>>>> 03f74aca74312dbeaf24d7e61306dd6a786dc3d0
