{
  "id": 2548073,
  "type": "Feature",
  "properties": {
    "tgn:hierarchy":[
        "tgn:2548073",
        "tgn:1000001",
        "tgn:7012149",
        "tgn:1002875",
        "tgn:7007568",
        "tgn:7029392"
    ],
    "tgn:id":2548073,
    "tgn:name":"North Hill",
    "tgn:placetype":[
        "aat:300008798"
    ]
},
  "bbox": [],
  "geometry": {"coordinates":[-76.7667,42.4833],"type":"Point"}
}