{
  "id": 7228566,
  "type": "Feature",
  "properties": {
    "tgn:hierarchy":[
        "tgn:7228566",
        "tgn:7011163",
        "tgn:7002674",
        "tgn:1000003",
        "tgn:1000074",
        "tgn:7029392"
    ],
    "tgn:id":7228566,
    "tgn:name":"L\u00edkhna, \u00c1kra",
    "tgn:placetype":[
        "aat:300008850"
    ]
},
  "bbox": [],
  "geometry": {"coordinates":[25.266667,39.883333],"type":"Point"}
}