{
  "id": 7034230,
  "type": "Feature",
  "properties": {
    "tgn:hierarchy":[
        "tgn:7034230",
        "tgn:1003442",
        "tgn:1000003",
        "tgn:7010380",
        "tgn:1000080",
        "tgn:7029392"
    ],
    "tgn:id":7034230,
    "tgn:name":"Masseria Cefalo Nuovo",
    "tgn:placetype":[
        "aat:300000206"
    ]
},
  "bbox": [],
  "geometry": {"coordinates":[18.011667,40.576389],"type":"Point"}
}