{
  "id": 2269809,
  "type": "Feature",
  "properties": {
    "tgn:hierarchy":[
        "tgn:2269809",
        "tgn:1000001",
        "tgn:7012149",
        "tgn:2002010",
        "tgn:7007826",
        "tgn:7029392"
    ],
    "tgn:id":2269809,
    "tgn:name":"Crows Nest Hill",
    "tgn:placetype":[
        "aat:300008798"
    ]
},
  "bbox": [],
  "geometry": {"coordinates":[-104.1833,30.5333],"type":"Point"}
}