{
  "id": 1002137,
  "type": "Feature",
  "properties": {
    "tgn:hierarchy":[
        "tgn:1002137",
        "tgn:1000001",
        "tgn:7012149",
        "tgn:7007710",
        "tgn:7029392"
    ],
    "tgn:id":1002137,
    "tgn:name":"Adams",
    "tgn:placetype":[
        "aat:300387145",
        "aat:300000771"
    ]
},
  "bbox": [],
  "geometry": {"coordinates":[-77.3667,39.75],"type":"Point"}
}