<<<<<<< HEAD
{
  "id": 7242228,
  "type": "Feature",
  "properties": {
    "tgn:hierarchy":[
        "tgn:7242228",
        "tgn:7003458",
        "tgn:1000003",
        "tgn:1000063",
        "tgn:7018236",
        "tgn:7029392"
    ],
    "tgn:id":7242228,
    "tgn:name":"Lobrug",
    "tgn:placetype":[
        "aat:300008347"
    ]
},
  "bbox": [],
  "geometry": {"coordinates":[2.733333,50.983333],"type":"Point"}
}
=======
{"geometry":{"type":"Point","coordinates":[2.733333,50.983333]},"type":"Feature","properties":{"hierarchy":["tgn:7242228","tgn:7003458","tgn:1000003","tgn:1000063","tgn:7018236","tgn:7029392"],"placetype":["aat:300008347"],"id":7242228,"name:xx":"Lobrug"}}
>>>>>>> 03f74aca74312dbeaf24d7e61306dd6a786dc3d0
