{
  "id": 2322088,
  "type": "Feature",
  "properties": {
    "tgn:hierarchy":[
        "tgn:2322088",
        "tgn:1000001",
        "tgn:7012149",
        "tgn:2001664",
        "tgn:7007707",
        "tgn:7029392"
    ],
    "tgn:id":2322088,
    "tgn:name":"Fall Creek",
    "tgn:placetype":[
        "aat:300008706"
    ]
},
  "bbox": [],
  "geometry": {"coordinates":[-97.2667,35.7833],"type":"Point"}
}