<<<<<<< HEAD
{
  "id": 2257372,
  "type": "Feature",
  "properties": {
    "tgn:hierarchy":[
        "tgn:2257372",
        "tgn:1000001",
        "tgn:2001411",
        "tgn:7012149",
        "tgn:7007526",
        "tgn:7029392"
    ],
    "tgn:id":2257372,
    "tgn:name":"Cornucopia Mine",
    "tgn:placetype":[
        "aat:300000390"
    ]
},
  "bbox": [],
  "geometry": {"coordinates":[-116.2833,41.5333],"type":"Point"}
}
=======
{"geometry":{"type":"Point","coordinates":[-116.283300,41.533300]},"type":"Feature","properties":{"hierarchy":["tgn:2257372","tgn:1000001","tgn:2001411","tgn:7012149","tgn:7007526","tgn:7029392"],"placetype":["aat:300000390"],"id":2257372,"name:xx":"Cornucopia Mine"}}
>>>>>>> 03f74aca74312dbeaf24d7e61306dd6a786dc3d0
