{
  "id": 2154654,
  "type": "Feature",
  "properties": {
    "tgn:hierarchy":[
        "tgn:2154654",
        "tgn:1000001",
        "tgn:7012149",
        "tgn:2001989",
        "tgn:7007826",
        "tgn:7029392"
    ],
    "tgn:id":2154654,
    "tgn:name":"Bear Grass Tank",
    "tgn:placetype":[
        "aat:300006191"
    ]
},
  "bbox": [],
  "geometry": {"coordinates":[-101.0667,33.15],"type":"Point"}
}