{
  "id": 1082475,
  "type": "Feature",
  "properties": {
    "tgn:hierarchy":[
        "tgn:1082475",
        "tgn:1000004",
        "tgn:7000846",
        "tgn:1000125",
        "tgn:7029392"
    ],
    "tgn:id":1082475,
    "tgn:name":"Ban Thanoun",
    "tgn:placetype":[
        "aat:300008347"
    ]
},
  "bbox": [],
  "geometry": {"coordinates":[101.4833,19.8333],"type":"Point"}
}