{
  "id": 7495304,
  "type": "Feature",
  "properties": {
    "tgn:hierarchy":[
        "tgn:7495304",
        "tgn:1000004",
        "tgn:7492971",
        "tgn:1000141",
        "tgn:7029392"
    ],
    "tgn:id":7495304,
    "tgn:name":"Tianling Gong",
    "tgn:placetype":[
        "aat:300007595"
    ]
},
  "bbox": [],
  "geometry": {"coordinates":[120.566794,22.575434],"type":"Point"}
}