{
  "id": 7340965,
  "type": "Feature",
  "properties": {
    "tgn:hierarchy":[
        "tgn:7340965",
        "tgn:7002836",
        "tgn:7016622",
        "tgn:1000003",
        "tgn:1000095",
        "tgn:7029392"
    ],
    "tgn:id":7340965,
    "tgn:name":"Burgado, Baja del",
    "tgn:placetype":[
        "aat:300386846"
    ]
},
  "bbox": [],
  "geometry": {"coordinates":[-17.316667,28.183333],"type":"Point"}
}