{
  "id": 1052536,
  "type": "Feature",
  "properties": {
    "tgn:hierarchy":[
        "tgn:1052536",
        "tgn:1000004",
        "tgn:7011573",
        "tgn:7018214",
        "tgn:7002435",
        "tgn:7029392"
    ],
    "tgn:id":1052536,
    "tgn:name":"Baranovskoye",
    "tgn:placetype":[
        "aat:300008347"
    ]
},
  "bbox": [],
  "geometry": {"coordinates":[38.75,55.4167],"type":"Point"}
}