{
  "id": 7513583,
  "type": "Feature",
  "properties": {
    "tgn:hierarchy":[
        "tgn:7513583",
        "tgn:1009227",
        "tgn:1000226",
        "tgn:1000006",
        "tgn:7016850",
        "tgn:7029392"
    ],
    "tgn:id":7513583,
    "tgn:name:en":"Garvey Creek",
    "tgn:placetype":[
        "aat:300008699"
    ]
},
  "bbox": [],
  "geometry": {"coordinates":[171.933333,-42.166667],"type":"Point"}
}