{
  "id": 7520676,
  "type": "Feature",
  "properties": {
    "tgn:hierarchy":[
        "tgn:7520676",
        "tgn:7001242",
        "tgn:7016833",
        "tgn:1001418",
        "tgn:7029392"
    ],
    "tgn:id":7520676,
    "tgn:name:en":"Abr\u0101m, Minq\u0101r al",
    "tgn:placetype":[
        "aat:300008749"
    ]
},
  "bbox": [],
  "geometry": {"coordinates":[25.097292,30.957278],"type":"Point"}
}