<<<<<<< HEAD
{
  "id": 2765493,
  "type": "Feature",
  "properties": {
    "tgn:hierarchy":[
        "tgn:2765493",
        "tgn:7019618",
        "tgn:1000001",
        "tgn:7012149",
        "tgn:7007564",
        "tgn:7029392"
    ],
    "tgn:id":2765493,
    "tgn:name":"White Brook",
    "tgn:placetype":[
        "aat:300008699"
    ]
},
  "bbox": [],
  "geometry": {"coordinates":[-72.3333,42.9333],"type":"Point"}
}
=======
{"geometry":{"type":"Point","coordinates":[-72.333300,42.933300]},"type":"Feature","properties":{"hierarchy":["tgn:2765493","tgn:7019618","tgn:1000001","tgn:7012149","tgn:7007564","tgn:7029392"],"placetype":["aat:300008699"],"id":2765493,"name:xx":"White Brook"}}
>>>>>>> 03f74aca74312dbeaf24d7e61306dd6a786dc3d0
