{
  "id": 2765493,
  "type": "Feature",
  "properties": {
    "tgn:hierarchy":[
        "tgn:2765493",
        "tgn:7019618",
        "tgn:1000001",
        "tgn:7012149",
        "tgn:7007564",
        "tgn:7029392"
    ],
    "tgn:id":2765493,
    "tgn:name":"White Brook",
    "tgn:placetype":[
        "aat:300008699"
    ]
},
  "bbox": [],
  "geometry": {"coordinates":[-72.3333,42.9333],"type":"Point"}
}