{
  "id": 7032094,
  "type": "Feature",
  "properties": {
    "tgn:hierarchy":[
        "tgn:7032094",
        "tgn:7001242",
        "tgn:1000160",
        "tgn:7029392"
    ],
    "tgn:id":7032094,
    "tgn:name":"Donga",
    "tgn:placetype":[
        "aat:300387064",
        "aat:300000772"
    ]
},
  "bbox": [],
  "geometry": {"coordinates":[1.847,9.166],"type":"Point"}
}