{
  "id": 7582636,
  "type": "Feature",
  "properties": {
    "tgn:hierarchy":[
        "tgn:7582636",
        "tgn:1000004",
        "tgn:7000198",
        "tgn:7016788",
        "tgn:7029392"
    ],
    "tgn:id":7582636,
    "tgn:name:en":"Aj\u012btpura",
    "tgn:placetype":[
        "aat:300008347"
    ]
},
  "bbox": [],
  "geometry": {"coordinates":[75.565631,28.225693],"type":"Point"}
}