{
  "id": 2498125,
  "type": "Feature",
  "properties": {
    "tgn:hierarchy":[
        "tgn:2498125",
        "tgn:1000001",
        "tgn:2002135",
        "tgn:7012149",
        "tgn:7007828",
        "tgn:7029392"
    ],
    "tgn:id":2498125,
    "tgn:name":"Mays Mountain",
    "tgn:placetype":[
        "aat:300008798"
    ]
},
  "bbox": [],
  "geometry": {"coordinates":[-72.3333,44.3333],"type":"Point"}
}