{
  "id": 1094975,
  "type": "Feature",
  "properties": {
    "tgn:hierarchy":[
        "tgn:1094975",
        "tgn:7001242",
        "tgn:1002070",
        "tgn:1000205",
        "tgn:7029392"
    ],
    "tgn:id":1094975,
    "tgn:name":"Menzel Bourguiba",
    "tgn:placetype":[
        "aat:300008347",
        "aat:300008375"
    ]
},
  "bbox": [],
  "geometry": {"coordinates":[9.8167,37.1667],"type":"Point"}
}