<<<<<<< HEAD
{
  "id": 7053876,
  "type": "Feature",
  "properties": {
    "tgn:hierarchy":[
        "tgn:7053876",
        "tgn:7005765",
        "tgn:1000003",
        "tgn:7003237",
        "tgn:1000080",
        "tgn:7029392"
    ],
    "tgn:id":7053876,
    "tgn:name":"Porle",
    "tgn:placetype":[
        "aat:300008347"
    ]
},
  "bbox": [],
  "geometry": {"coordinates":[10.366667,45.6],"type":"Point"}
}
=======
{"geometry":{"type":"Point","coordinates":[10.366667,45.600000]},"type":"Feature","properties":{"hierarchy":["tgn:7053876","tgn:7005765","tgn:1000003","tgn:7003237","tgn:1000080","tgn:7029392"],"placetype":["aat:300008347"],"id":7053876,"name:xx":"Porle"}}
>>>>>>> 03f74aca74312dbeaf24d7e61306dd6a786dc3d0
