{
  "id": 7270707,
  "type": "Feature",
  "properties": {
    "tgn:hierarchy":[
        "tgn:7270707",
        "tgn:7003616",
        "tgn:1000003",
        "tgn:7016845",
        "tgn:7029392"
    ],
    "tgn:id":7270707,
    "tgn:name:nl":"Sierdswiel",
    "tgn:placetype":[
        "aat:300008680"
    ]
},
  "bbox": [],
  "geometry": {"coordinates":[5.866667,53.233333],"type":"Point"}
}