{
  "id": 7312475,
  "type": "Feature",
  "properties": {
    "tgn:hierarchy":[
        "tgn:7312475",
        "tgn:1001708",
        "tgn:1000049",
        "tgn:1000002",
        "tgn:7029392"
    ],
    "tgn:id":7312475,
    "tgn:name":"La Plata",
    "tgn:placetype":[
        "aat:300008795"
    ]
},
  "bbox": [],
  "geometry": {"coordinates":[-71.316667,-34.05],"type":"Point"}
}