{
  "id": 2686469,
  "type": "Feature",
  "properties": {
    "tgn:hierarchy":[
        "tgn:2686469",
        "tgn:1000001",
        "tgn:2001265",
        "tgn:7012149",
        "tgn:7007524",
        "tgn:7029392"
    ],
    "tgn:id":2686469,
    "tgn:name":"Spring Creek",
    "tgn:placetype":[
        "aat:300008706"
    ]
},
  "bbox": [],
  "geometry": {"coordinates":[-104.85,45.35],"type":"Point"}
}