{
  "id": 2378093,
  "type": "Feature",
  "properties": {
    "tgn:hierarchy":[
        "tgn:2378093",
        "tgn:1000001",
        "tgn:7012149",
        "tgn:7007706",
        "tgn:7029392"
    ],
    "tgn:id":2378093,
    "tgn:name":"Harris Ditch",
    "tgn:placetype":[
        "aat:300006075"
    ]
},
  "bbox": [],
  "geometry": {"coordinates":[-83.8167,41.4667],"type":"Point"}
}