{
  "id": 7409059,
  "type": "Feature",
  "properties": {
    "tgn:hierarchy":[
        "tgn:7409059",
        "tgn:1000001",
        "tgn:7005590",
        "tgn:7005560",
        "tgn:7029392"
    ],
    "tgn:id":7409059,
    "tgn:name":"Las Ollas, Cerro",
    "tgn:placetype":[
        "aat:300008795"
    ]
},
  "bbox": [],
  "geometry": {"coordinates":[-102.466667,18.123611],"type":"Point"}
}