{
  "id": 2165696,
  "type": "Feature",
  "properties": {
    "tgn:hierarchy":[
        "tgn:2165696",
        "tgn:1000001",
        "tgn:7012149",
        "tgn:2002268",
        "tgn:7013961",
        "tgn:7029392"
    ],
    "tgn:id":2165696,
    "tgn:name":"Bibbee Ridge",
    "tgn:placetype":[
        "aat:300266640"
    ]
},
  "bbox": [],
  "geometry": {"coordinates":[-81.6833,38.65],"type":"Point"}
}