{
  "id": 2593650,
  "type": "Feature",
  "properties": {
    "tgn:hierarchy":[
        "tgn:2593650",
        "tgn:1000001",
        "tgn:7012149",
        "tgn:1002971",
        "tgn:7007710",
        "tgn:7029392"
    ],
    "tgn:id":2593650,
    "tgn:name":"Porcupine Run",
    "tgn:placetype":[
        "aat:300008699"
    ]
},
  "bbox": [],
  "geometry": {"coordinates":[-79.75,41.2833],"type":"Point"}
}