<<<<<<< HEAD
{
  "id": 2401879,
  "type": "Feature",
  "properties": {
    "tgn:hierarchy":[
        "tgn:2401879",
        "tgn:1000001",
        "tgn:7012149",
        "tgn:1002703",
        "tgn:7007826",
        "tgn:7029392"
    ],
    "tgn:id":2401879,
    "tgn:name":"Horseshoe Lake",
    "tgn:placetype":[
        "aat:300008680"
    ]
},
  "bbox": [],
  "geometry": {"coordinates":[-94.3333,31.25],"type":"Point"}
}
=======
{"geometry":{"type":"Point","coordinates":[-94.333300,31.250000]},"type":"Feature","properties":{"hierarchy":["tgn:2401879","tgn:1000001","tgn:7012149","tgn:1002703","tgn:7007826","tgn:7029392"],"placetype":["aat:300008680"],"id":2401879,"name:xx":"Horseshoe Lake"}}
>>>>>>> 03f74aca74312dbeaf24d7e61306dd6a786dc3d0
