{
  "id": 7167261,
  "type": "Feature",
  "properties": {
    "tgn:hierarchy":[
        "tgn:7167261",
        "tgn:7000096",
        "tgn:1000003",
        "tgn:7000084",
        "tgn:7029392"
    ],
    "tgn:id":7167261,
    "tgn:name":"Heinersdorfer See",
    "tgn:placetype":[
        "aat:300008680"
    ]
},
  "bbox": [],
  "geometry": {"coordinates":[14.216667,52.466667],"type":"Point"}
}