{
  "id": 7525306,
  "type": "Feature",
  "properties": {
    "tgn:hierarchy":[
        "tgn:7525306",
        "tgn:7001242",
        "tgn:7016833",
        "tgn:1001087",
        "tgn:7029392"
    ],
    "tgn:id":7525306,
    "tgn:name:en":"Dalham\u016b",
    "tgn:placetype":[
        "aat:300008347"
    ]
},
  "bbox": [],
  "geometry": {"coordinates":[30.852659,30.343208],"type":"Point"}
}