{
  "id": 7280201,
  "type": "Feature",
  "properties": {
    "tgn:hierarchy":[
        "tgn:7280201",
        "tgn:1001705",
        "tgn:1000049",
        "tgn:1000002",
        "tgn:7029392"
    ],
    "tgn:id":7280201,
    "tgn:name":"Quito",
    "tgn:placetype":[
        "aat:300000206"
    ]
},
  "bbox": [],
  "geometry": {"coordinates":[-71.666667,-36.216667],"type":"Point"}
}