{
  "id": 2753862,
  "type": "Feature",
  "properties": {
    "tgn:hierarchy":[
        "tgn:2753862",
        "tgn:1000001",
        "tgn:2002367",
        "tgn:7012149",
        "tgn:7007923",
        "tgn:7029392"
    ],
    "tgn:id":2753862,
    "tgn:name":"Watson Basin",
    "tgn:placetype":[
        "aat:300386845"
    ]
},
  "bbox": [],
  "geometry": {"coordinates":[-105.9667,44.9333],"type":"Point"}
}