<<<<<<< HEAD
{
  "id": 2257782,
  "type": "Feature",
  "properties": {
    "tgn:hierarchy":[
        "tgn:2257782",
        "tgn:1000001",
        "tgn:7006451",
        "tgn:2000094",
        "tgn:7012149",
        "tgn:7029392"
    ],
    "tgn:id":2257782,
    "tgn:name":"Corral Spring",
    "tgn:placetype":[
        "aat:300008697"
    ]
},
  "bbox": [],
  "geometry": {"coordinates":[-110.3167,32.6333],"type":"Point"}
}
=======
{"geometry":{"type":"Point","coordinates":[-110.316700,32.633300]},"type":"Feature","properties":{"hierarchy":["tgn:2257782","tgn:1000001","tgn:7006451","tgn:2000094","tgn:7012149","tgn:7029392"],"placetype":["aat:300008697"],"id":2257782,"name:xx":"Corral Spring"}}
>>>>>>> 03f74aca74312dbeaf24d7e61306dd6a786dc3d0
