{
  "id": 2727384,
  "type": "Feature",
  "properties": {
    "tgn:hierarchy":[
        "tgn:2727384",
        "tgn:1000001",
        "tgn:2001358",
        "tgn:7012149",
        "tgn:7007525",
        "tgn:7029392"
    ],
    "tgn:id":2727384,
    "tgn:name":"Trail Canyon",
    "tgn:placetype":[
        "aat:300008761"
    ]
},
  "bbox": [],
  "geometry": {"coordinates":[-101.2667,40.4167],"type":"Point"}
}