{
  "id": 7434551,
  "type": "Feature",
  "properties": {
    "tgn:hierarchy":[
        "tgn:7434551",
        "tgn:7005580",
        "tgn:1000001",
        "tgn:7005560",
        "tgn:7029392"
    ],
    "tgn:id":7434551,
    "tgn:name":"Veinte de Noviembre",
    "tgn:placetype":[
        "aat:300008347"
    ]
},
  "bbox": [],
  "geometry": {"coordinates":[-92.25,14.716667],"type":"Point"}
}