{
  "id": 2366405,
  "type": "Feature",
  "properties": {
    "tgn:hierarchy":[
        "tgn:2366405",
        "tgn:1000001",
        "tgn:7012149",
        "tgn:2001912",
        "tgn:7007825",
        "tgn:7029392"
    ],
    "tgn:id":2366405,
    "tgn:name":"Griffith Mountain",
    "tgn:placetype":[
        "aat:300008798"
    ]
},
  "bbox": [],
  "geometry": {"coordinates":[-84.5333,36.2333],"type":"Point"}
}