{
  "id": 2082880,
  "type": "Feature",
  "properties": {
    "tgn:hierarchy":[
        "tgn:2082880",
        "tgn:1000001",
        "tgn:7012149",
        "tgn:2001667",
        "tgn:7007707",
        "tgn:7029392"
    ],
    "tgn:id":2082880,
    "tgn:name":"Bokhoma",
    "tgn:placetype":[
        "aat:300008347"
    ]
},
  "bbox": [],
  "geometry": {"coordinates":[-94.5667,33.8167],"type":"Point"}
}