<<<<<<< HEAD
{
  "id": 7024785,
  "type": "Feature",
  "properties": {
    "tgn:hierarchy":[
        "tgn:7024785",
        "tgn:7002445",
        "tgn:7008104",
        "tgn:1000003",
        "tgn:7008591",
        "tgn:7029392"
    ],
    "tgn:id":7024785,
    "tgn:name:en":"Akeley",
    "tgn:placetype":[
        "aat:300008347"
    ]
},
  "bbox": [],
  "geometry": {"coordinates":[-0.966667,52.033333],"type":"Point"}
}
=======
{"geometry":{"type":"Point","coordinates":[-0.966667,52.033333]},"type":"Feature","properties":{"hierarchy":["tgn:7024785","tgn:7002445","tgn:7008104","tgn:1000003","tgn:7008591","tgn:7029392"],"placetype":["aat:300008347"],"name:en":"Akeley","id":7024785}}
>>>>>>> 03f74aca74312dbeaf24d7e61306dd6a786dc3d0
