{
  "id": 2614830,
  "type": "Feature",
  "properties": {
    "tgn:hierarchy":[
        "tgn:2614830",
        "tgn:1000001",
        "tgn:7012149",
        "tgn:2001455",
        "tgn:7007566",
        "tgn:7029392"
    ],
    "tgn:id":2614830,
    "tgn:name":"Renick Tank",
    "tgn:placetype":[
        "aat:300006191"
    ]
},
  "bbox": [],
  "geometry": {"coordinates":[-106.8333,32.95],"type":"Point"}
}