{
  "id": 2415100,
  "type": "Feature",
  "properties": {
    "tgn:hierarchy":[
        "tgn:2415100",
        "tgn:1000001",
        "tgn:7012149",
        "tgn:2001906",
        "tgn:7007825",
        "tgn:7029392"
    ],
    "tgn:id":2415100,
    "tgn:name":"Island Creek",
    "tgn:placetype":[
        "aat:300008706"
    ]
},
  "bbox": [],
  "geometry": {"coordinates":[-84.5833,35.0667],"type":"Point"}
}