{
  "id": 7202321,
  "type": "Feature",
  "properties": {
    "tgn:hierarchy":[
        "tgn:7202321",
        "tgn:1000003",
        "tgn:7003687",
        "tgn:7000084",
        "tgn:7029392"
    ],
    "tgn:id":7202321,
    "tgn:name":"Brambach",
    "tgn:placetype":[
        "aat:300055621"
    ]
},
  "bbox": [],
  "geometry": {"coordinates":[12.166667,51.766667],"type":"Point"}
}