<<<<<<< HEAD
{
  "id": 2763716,
  "type": "Feature",
  "properties": {
    "tgn:hierarchy":[
        "tgn:2763716",
        "tgn:1000001",
        "tgn:2001016",
        "tgn:7012149",
        "tgn:7007521",
        "tgn:7029392"
    ],
    "tgn:id":2763716,
    "tgn:name":"Whang Lake",
    "tgn:placetype":[
        "aat:300008680"
    ]
},
  "bbox": [],
  "geometry": {"coordinates":[-93.9,46.4167],"type":"Point"}
}
=======
{"geometry":{"type":"Point","coordinates":[-93.900000,46.416700]},"type":"Feature","properties":{"hierarchy":["tgn:2763716","tgn:1000001","tgn:2001016","tgn:7012149","tgn:7007521","tgn:7029392"],"placetype":["aat:300008680"],"id":2763716,"name:xx":"Whang Lake"}}
>>>>>>> 03f74aca74312dbeaf24d7e61306dd6a786dc3d0
