{
  "id": 2670778,
  "type": "Feature",
  "properties": {
    "tgn:hierarchy":[
        "tgn:2670778",
        "tgn:1002149",
        "tgn:1000001",
        "tgn:7012149",
        "tgn:7007826",
        "tgn:7029392"
    ],
    "tgn:id":2670778,
    "tgn:name":"Smith Branch",
    "tgn:placetype":[
        "aat:300008699"
    ]
},
  "bbox": [],
  "geometry": {"coordinates":[-94.4167,31.2167],"type":"Point"}
}