{
  "id": 2510270,
  "type": "Feature",
  "properties": {
    "tgn:hierarchy":[
        "tgn:2510270",
        "tgn:1000001",
        "tgn:7012149",
        "tgn:2001873",
        "tgn:7007825",
        "tgn:7029392"
    ],
    "tgn:id":2510270,
    "tgn:name":"Middle Ridge",
    "tgn:placetype":[
        "aat:300266640"
    ]
},
  "bbox": [],
  "geometry": {"coordinates":[-83.1167,36.4833],"type":"Point"}
}