{
  "id": 7503912,
  "type": "Feature",
  "properties": {
    "tgn:hierarchy":[
        "tgn:7503912",
        "tgn:1000004",
        "tgn:1000131",
        "tgn:7029392"
    ],
    "tgn:id":7503912,
    "tgn:name":"Bat",
    "tgn:placetype":[
        "aat:300008347",
        "aat:300387007",
        "aat:300000810",
        "aat:300387004",
        "aat:300263063"
    ]
},
  "bbox": [],
  "geometry": {"coordinates":[56.745,23.269],"type":"Point"}
}