{
  "id": 1050345,
  "type": "Feature",
  "properties": {
    "tgn:hierarchy":[
        "tgn:1050345",
        "tgn:1000003",
        "tgn:1000456",
        "tgn:1000091",
        "tgn:7029392"
    ],
    "tgn:id":1050345,
    "tgn:name":"Zimnicea",
    "tgn:placetype":[
        "aat:300008347"
    ]
},
  "bbox": [],
  "geometry": {"coordinates":[25.35,43.65],"type":"Point"}
}