{
  "id": 2381135,
  "type": "Feature",
  "properties": {
    "tgn:hierarchy":[
        "tgn:2381135",
        "tgn:1000001",
        "tgn:7012149",
        "tgn:2001708",
        "tgn:7007708",
        "tgn:7029392"
    ],
    "tgn:id":2381135,
    "tgn:name":"Hawkins Spring",
    "tgn:placetype":[
        "aat:300008697"
    ]
},
  "bbox": [],
  "geometry": {"coordinates":[-118.3833,44.1833],"type":"Point"}
}