{
  "id": 2321728,
  "type": "Feature",
  "properties": {
    "tgn:hierarchy":[
        "tgn:2321728",
        "tgn:1000001",
        "tgn:7012149",
        "tgn:2002358",
        "tgn:7007922",
        "tgn:7029392"
    ],
    "tgn:id":2321728,
    "tgn:name":"Fairview Ridge",
    "tgn:placetype":[
        "aat:300266640"
    ]
},
  "bbox": [],
  "geometry": {"coordinates":[-90.7333,43.5833],"type":"Point"}
}