{
  "id": 7135109,
  "type": "Feature",
  "properties": {
    "tgn:hierarchy":[
        "tgn:7135109",
        "tgn:1000003",
        "tgn:7003685",
        "tgn:7000084",
        "tgn:7029392"
    ],
    "tgn:id":7135109,
    "tgn:name":"F\u00f6rsterei M\u00f6nchenfei",
    "tgn:placetype":[
        "aat:300004792"
    ]
},
  "bbox": [],
  "geometry": {"coordinates":[13.316667,50.833333],"type":"Point"}
}