{
  "id": 7478561,
  "type": "Feature",
  "properties": {
    "tgn:hierarchy":[
        "tgn:7478561",
        "tgn:1000004",
        "tgn:7492971",
        "tgn:1000141",
        "tgn:7029392"
    ],
    "tgn:id":7478561,
    "tgn:name":"Xinjie",
    "tgn:placetype":[
        "aat:300008347"
    ]
},
  "bbox": [],
  "geometry": {"coordinates":[120.459687,22.475427],"type":"Point"}
}