{
  "id": 2779513,
  "type": "Feature",
  "properties": {
    "tgn:hierarchy":[
        "tgn:2779513",
        "tgn:7006450",
        "tgn:1000001",
        "tgn:2124053",
        "tgn:7012149",
        "tgn:7029392"
    ],
    "tgn:id":2779513,
    "tgn:name":"Wolf Lakes",
    "tgn:placetype":[
        "aat:300008680"
    ]
},
  "bbox": [],
  "geometry": {"coordinates":[-151.0667,61.6333],"type":"Point"}
}