{
  "id": 2528727,
  "type": "Feature",
  "properties": {
    "tgn:hierarchy":[
        "tgn:2528727",
        "tgn:1000001",
        "tgn:2002109",
        "tgn:7012149",
        "tgn:7007827",
        "tgn:7029392"
    ],
    "tgn:id":2528727,
    "tgn:name":"Mud Canyon Butte",
    "tgn:placetype":[
        "aat:300008798"
    ]
},
  "bbox": [],
  "geometry": {"coordinates":[-112.2167,37.55],"type":"Point"}
}