{
  "id": 7446282,
  "type": "Feature",
  "properties": {
    "tgn:hierarchy":[
        "tgn:7446282",
        "tgn:7002444",
        "tgn:1000003",
        "tgn:7008082",
        "tgn:7008591",
        "tgn:7029392"
    ],
    "tgn:id":7446282,
    "tgn:name:en":"Rhiconich",
    "tgn:placetype":[
        "aat:300008347"
    ]
},
  "bbox": [],
  "geometry": {"coordinates":[-4.983333,58.416667],"type":"Point"}
}