{
  "id": 7529111,
  "type": "Feature",
  "properties": {
    "tgn:hierarchy":[
        "tgn:7529111",
        "tgn:7001242",
        "tgn:7001311",
        "tgn:7016833",
        "tgn:7029392"
    ],
    "tgn:id":7529111,
    "tgn:name:en":"Umm Sal\u0101mah, W\u0101d\u012b",
    "tgn:placetype":[
        "aat:300008761"
    ]
},
  "bbox": [],
  "geometry": {"coordinates":[33.118479,24.884965],"type":"Point"}
}