{
  "id": 2593578,
  "type": "Feature",
  "properties": {
    "tgn:hierarchy":[
        "tgn:2593578",
        "tgn:1000001",
        "tgn:7012149",
        "tgn:1002352",
        "tgn:7007710",
        "tgn:7029392"
    ],
    "tgn:id":2593578,
    "tgn:name":"Porcupine Hollow",
    "tgn:placetype":[
        "aat:300008761"
    ]
},
  "bbox": [],
  "geometry": {"coordinates":[-78.3667,41.3333],"type":"Point"}
}