{
  "id": 7033403,
  "type": "Feature",
  "properties": {
    "tgn:hierarchy":[
        "tgn:7033403",
        "tgn:7003006",
        "tgn:1000003",
        "tgn:7002997",
        "tgn:1000080",
        "tgn:7029392"
    ],
    "tgn:id":7033403,
    "tgn:name":"Vada",
    "tgn:placetype":[
        "aat:300008347"
    ]
},
  "bbox": [],
  "geometry": {"coordinates":[12.921667,45.773056],"type":"Point"}
}