{
  "id": 2056338,
  "type": "Feature",
  "properties": {
    "tgn:hierarchy":[
        "tgn:2056338",
        "tgn:1000001",
        "tgn:7012149",
        "tgn:2001152",
        "tgn:7007522",
        "tgn:7029392"
    ],
    "tgn:id":2056338,
    "tgn:name":"Dwyer",
    "tgn:placetype":[
        "aat:300008347",
        "aat:300387210"
    ]
},
  "bbox": [],
  "geometry": {"coordinates":[-90.5167,33.55],"type":"Point"}
}