{
  "id": 2464206,
  "type": "Feature",
  "properties": {
    "tgn:hierarchy":[
        "tgn:2464206",
        "tgn:1000001",
        "tgn:7012149",
        "tgn:1002900",
        "tgn:7007710",
        "tgn:7029392"
    ],
    "tgn:id":2464206,
    "tgn:name":"Locust Ridge",
    "tgn:placetype":[
        "aat:300266640"
    ]
},
  "bbox": [],
  "geometry": {"coordinates":[-77.3167,40.7833],"type":"Point"}
}