{
  "id": 7125282,
  "type": "Feature",
  "properties": {
    "tgn:hierarchy":[
        "tgn:7125282",
        "tgn:1000003",
        "tgn:7003673",
        "tgn:7000084",
        "tgn:7029392"
    ],
    "tgn:id":7125282,
    "tgn:name":"Neu Lokstedt",
    "tgn:placetype":[
        "aat:300008347"
    ]
},
  "bbox": [],
  "geometry": {"coordinates":[9.95,53.583333],"type":"Point"}
}