{
  "id": 7495291,
  "type": "Feature",
  "properties": {
    "tgn:hierarchy":[
        "tgn:7495291",
        "tgn:1000004",
        "tgn:7492971",
        "tgn:1000141",
        "tgn:7029392"
    ],
    "tgn:id":7495291,
    "tgn:name":"Dijiu Gongmu",
    "tgn:placetype":[
        "aat:300266755"
    ]
},
  "bbox": [],
  "geometry": {"coordinates":[120.593912,22.566958],"type":"Point"}
}