{
  "id": 7533069,
  "type": "Feature",
  "properties": {
    "tgn:hierarchy":[
        "tgn:7533069",
        "tgn:7001242",
        "tgn:7016833",
        "tgn:1001091",
        "tgn:7029392"
    ],
    "tgn:id":7533069,
    "tgn:name":"Bar\u012bd Jaz\u012brat Badr\u0101n",
    "tgn:placetype":[
        "aat:300006036"
    ]
},
  "bbox": [],
  "geometry": {"coordinates":[31.238773,30.066982],"type":"Point"}
}