{
  "id": 2623794,
  "type": "Feature",
  "properties": {
    "tgn:hierarchy":[
        "tgn:2623794",
        "tgn:1000001",
        "tgn:1002275",
        "tgn:7012149",
        "tgn:7007920",
        "tgn:7029392"
    ],
    "tgn:id":2623794,
    "tgn:name":"Rock Creek",
    "tgn:placetype":[
        "aat:300008706"
    ]
},
  "bbox": [],
  "geometry": {"coordinates":[-122.4333,45.8167],"type":"Point"}
}