{
  "id": 2169026,
  "type": "Feature",
  "properties": {
    "tgn:hierarchy":[
        "tgn:2169026",
        "tgn:1000001",
        "tgn:2001736",
        "tgn:7012149",
        "tgn:7007712",
        "tgn:7029392"
    ],
    "tgn:id":2169026,
    "tgn:name":"Big Island",
    "tgn:placetype":[
        "aat:300008791"
    ]
},
  "bbox": [],
  "geometry": {"coordinates":[-80.8833,34.55],"type":"Point"}
}