{
  "id": 7043002,
  "type": "Feature",
  "properties": {
    "tgn:hierarchy":[
        "tgn:7043002",
        "tgn:7003154",
        "tgn:1000003",
        "tgn:7003120",
        "tgn:1000080",
        "tgn:7029392"
    ],
    "tgn:id":7043002,
    "tgn:name":"Revigliasco",
    "tgn:placetype":[
        "aat:300008347"
    ]
},
  "bbox": [],
  "geometry": {"coordinates":[7.733333,45.016667],"type":"Point"}
}