{
  "id": 7307279,
  "type": "Feature",
  "properties": {
    "tgn:hierarchy":[
        "tgn:7307279",
        "tgn:7008912",
        "tgn:7030216",
        "tgn:1000003",
        "tgn:1000095",
        "tgn:7029392"
    ],
    "tgn:id":7307279,
    "tgn:name":"Llosas, Lagunas",
    "tgn:placetype":[
        "aat:300008688"
    ]
},
  "bbox": [],
  "geometry": {"coordinates":[0.979683,42.591614],"type":"Point"}
}