<<<<<<< HEAD
{
  "id": 7364724,
  "type": "Feature",
  "properties": {
    "tgn:hierarchy":[
        "tgn:7364724",
        "tgn:1000001",
        "tgn:7005597",
        "tgn:7005560",
        "tgn:7029392"
    ],
    "tgn:id":7364724,
    "tgn:name":"Flores, Rinc\u00f3n de las",
    "tgn:placetype":[
        "aat:300008679"
    ]
},
  "bbox": [],
  "geometry": {"coordinates":[-97.533333,25.433333],"type":"Point"}
}
=======
{"geometry":{"type":"Point","coordinates":[-97.533333,25.433333]},"type":"Feature","properties":{"hierarchy":["tgn:7364724","tgn:1000001","tgn:7005597","tgn:7005560","tgn:7029392"],"placetype":["aat:300008679"],"id":7364724,"name:xx":"Flores, Rinc\u00f3n de las"}}
>>>>>>> 03f74aca74312dbeaf24d7e61306dd6a786dc3d0
