{
  "id": 7517551,
  "type": "Feature",
  "properties": {
    "tgn:hierarchy":[
        "tgn:7517551",
        "tgn:1008380",
        "tgn:7000507",
        "tgn:1000226",
        "tgn:1000006",
        "tgn:7029392"
    ],
    "tgn:id":7517551,
    "tgn:name:en":"Mamaranui",
    "tgn:placetype":[
        "aat:300008347"
    ]
},
  "bbox": [],
  "geometry": {"coordinates":[173.75,-35.833333],"type":"Point"}
}