<<<<<<< HEAD
{
  "id": 7115301,
  "type": "Feature",
  "properties": {
    "tgn:hierarchy":[
        "tgn:7115301",
        "tgn:1000003",
        "tgn:7003676",
        "tgn:7000084",
        "tgn:7029392"
    ],
    "tgn:id":7115301,
    "tgn:name":"Oldenburger Moor",
    "tgn:placetype":[
        "aat:300386886"
    ]
},
  "bbox": [],
  "geometry": {"coordinates":[7.7,52.666667],"type":"Point"}
}
=======
{"geometry":{"type":"Point","coordinates":[7.700000,52.666667]},"type":"Feature","properties":{"hierarchy":["tgn:7115301","tgn:1000003","tgn:7003676","tgn:7000084","tgn:7029392"],"placetype":["aat:300386886"],"id":7115301,"name:xx":"Oldenburger Moor"}}
>>>>>>> 03f74aca74312dbeaf24d7e61306dd6a786dc3d0
