{
  "id": 2732422,
  "type": "Feature",
  "properties": {
    "tgn:hierarchy":[
        "tgn:2732422",
        "tgn:1000001",
        "tgn:7012149",
        "tgn:1002778",
        "tgn:7007255",
        "tgn:7029392"
    ],
    "tgn:id":2732422,
    "tgn:name":"Turkey Branch",
    "tgn:placetype":[
        "aat:300008699"
    ]
},
  "bbox": [],
  "geometry": {"coordinates":[-84.2167,38.7333],"type":"Point"}
}