{
  "id": 7180870,
  "type": "Feature",
  "properties": {
    "tgn:hierarchy":[
        "tgn:7180870",
        "tgn:7003669",
        "tgn:1000003",
        "tgn:7000084",
        "tgn:7029392"
    ],
    "tgn:id":7180870,
    "tgn:name":"Fuchsau",
    "tgn:placetype":[
        "aat:300008347"
    ]
},
  "bbox": [],
  "geometry": {"coordinates":[12.666667,47.75],"type":"Point"}
}