{
  "id": 1010144,
  "type": "Feature",
  "properties": {
    "tgn:hierarchy":[
        "tgn:1010144",
        "tgn:1008380",
        "tgn:1000226",
        "tgn:7018426",
        "tgn:1000006",
        "tgn:7029392"
    ],
    "tgn:id":1010144,
    "tgn:name":"Mercury Islands",
    "tgn:placetype":[
        "aat:300008791",
        "aat:300386853"
    ]
},
  "bbox": [],
  "geometry": {"coordinates":[175.916667,-36.583333],"type":"Point"}
}