{
  "id": 7562229,
  "type": "Feature",
  "properties": {
    "tgn:hierarchy":[
        "tgn:7562229",
        "tgn:1000004",
        "tgn:7000198",
        "tgn:7016722",
        "tgn:7029392"
    ],
    "tgn:id":7562229,
    "tgn:name:en":"Nagla Mangad",
    "tgn:placetype":[
        "aat:300008347"
    ]
},
  "bbox": [],
  "geometry": {"coordinates":[79.259025,27.0221],"type":"Point"}
}