{
  "id": 2364816,
  "type": "Feature",
  "properties": {
    "tgn:hierarchy":[
        "tgn:2364816",
        "tgn:7016099",
        "tgn:1000001",
        "tgn:7012149",
        "tgn:7007516",
        "tgn:7029392"
    ],
    "tgn:id":2364816,
    "tgn:name":"Greene Tree",
    "tgn:placetype":[
        "aat:300008347"
    ]
},
  "bbox": [],
  "geometry": {"coordinates":[-76.7333,39.3833],"type":"Point"}
}