<<<<<<< HEAD
{
  "id": 7351088,
  "type": "Feature",
  "properties": {
    "tgn:hierarchy":[
        "tgn:7351088",
        "tgn:1000001",
        "tgn:1001960",
        "tgn:7005560",
        "tgn:7029392"
    ],
    "tgn:id":7351088,
    "tgn:name":"Cabullona",
    "tgn:placetype":[
        "aat:300008347"
    ]
},
  "bbox": [],
  "geometry": {"coordinates":[-109.566667,31.166667],"type":"Point"}
}
=======
{"geometry":{"type":"Point","coordinates":[-109.566667,31.166667]},"type":"Feature","properties":{"hierarchy":["tgn:7351088","tgn:1000001","tgn:1001960","tgn:7005560","tgn:7029392"],"placetype":["aat:300008347"],"id":7351088,"name:xx":"Cabullona"}}
>>>>>>> 03f74aca74312dbeaf24d7e61306dd6a786dc3d0
