{
  "id": 2236872,
  "type": "Feature",
  "properties": {
    "tgn:hierarchy":[
        "tgn:2236872",
        "tgn:7002659",
        "tgn:1000001",
        "tgn:7012149",
        "tgn:2000051",
        "tgn:7029392"
    ],
    "tgn:id":2236872,
    "tgn:name":"Childs Hollow",
    "tgn:placetype":[
        "aat:300008761"
    ]
},
  "bbox": [],
  "geometry": {"coordinates":[-86.8167,34.3833],"type":"Point"}
}