{
  "id": 7584519,
  "type": "Feature",
  "properties": {
    "tgn:hierarchy":[
        "tgn:7584519",
        "tgn:1000004",
        "tgn:1001871",
        "tgn:7000198",
        "tgn:7029392"
    ],
    "tgn:id":7584519,
    "tgn:name:en":"Kangw\u0101l",
    "tgn:placetype":[
        "aat:300008347"
    ]
},
  "bbox": [],
  "geometry": {"coordinates":[76.632405,30.138518],"type":"Point"}
}