{
  "id": 1118665,
  "type": "Feature",
  "properties": {
    "tgn:hierarchy":[
        "tgn:1118665",
        "tgn:7005685",
        "tgn:1000001",
        "tgn:7005734",
        "tgn:7029392"
    ],
    "tgn:id":1118665,
    "tgn:name":"Waterhen Lake",
    "tgn:placetype":[
        "aat:300008680"
    ]
},
  "bbox": [],
  "geometry": {"coordinates":[-99.5833,52.0833],"type":"Point"}
}