{
  "id": 1060795,
  "type": "Feature",
  "properties": {
    "tgn:hierarchy":[
        "tgn:1060795",
        "tgn:1000004",
        "tgn:6003149",
        "tgn:7002435",
        "tgn:7029392"
    ],
    "tgn:id":1060795,
    "tgn:name":"Ust Lyzha",
    "tgn:placetype":[
        "aat:300008347"
    ]
},
  "bbox": [],
  "geometry": {"coordinates":[56.6333,65.75],"type":"Point"}
}