<<<<<<< HEAD
{
  "id": 2257864,
  "type": "Feature",
  "properties": {
    "tgn:hierarchy":[
        "tgn:2257864",
        "tgn:1000001",
        "tgn:7012149",
        "tgn:7007157",
        "tgn:7029392"
    ],
    "tgn:id":2257864,
    "tgn:name":"Correco Canyon",
    "tgn:placetype":[
        "aat:300008761"
    ]
},
  "bbox": [],
  "geometry": {"coordinates":[-120.15,39.7],"type":"Point"}
}
=======
{"geometry":{"type":"Point","coordinates":[-120.150000,39.700000]},"type":"Feature","properties":{"hierarchy":["tgn:2257864","tgn:1000001","tgn:7012149","tgn:7007157","tgn:7029392"],"placetype":["aat:300008761"],"id":2257864,"name:xx":"Correco Canyon"}}
>>>>>>> 03f74aca74312dbeaf24d7e61306dd6a786dc3d0
