{
  "id": 7291542,
  "type": "Feature",
  "properties": {
    "tgn:hierarchy":[
        "tgn:7291542",
        "tgn:1001768",
        "tgn:1000049",
        "tgn:1000002",
        "tgn:7029392"
    ],
    "tgn:id":7291542,
    "tgn:name":"El Laberinto",
    "tgn:placetype":[
        "aat:300000206"
    ]
},
  "bbox": [],
  "geometry": {"coordinates":[-70.633333,-32.816667],"type":"Point"}
}