{
  "id": 7563888,
  "type": "Feature",
  "properties": {
    "tgn:hierarchy":[
        "tgn:7563888",
        "tgn:1000004",
        "tgn:7000198",
        "tgn:7016788",
        "tgn:7029392"
    ],
    "tgn:id":7563888,
    "tgn:name:en":"Chhatt\u0101sar",
    "tgn:placetype":[
        "aat:300008347"
    ]
},
  "bbox": [],
  "geometry": {"coordinates":[74.004082,28.482801],"type":"Point"}
}