{
  "id": 2353132,
  "type": "Feature",
  "properties": {
    "tgn:hierarchy":[
        "tgn:2353132",
        "tgn:1000001",
        "tgn:7012149",
        "tgn:7022246",
        "tgn:7007825",
        "tgn:7029392"
    ],
    "tgn:id":2353132,
    "tgn:name":"Goff Ridge",
    "tgn:placetype":[
        "aat:300266640"
    ]
},
  "bbox": [],
  "geometry": {"coordinates":[-85.6667,36.0167],"type":"Point"}
}