{
  "id": 7473395,
  "type": "Feature",
  "properties": {
    "tgn:hierarchy":[
        "tgn:7473395",
        "tgn:1000004",
        "tgn:1000959",
        "tgn:1000141",
        "tgn:7029392"
    ],
    "tgn:id":7473395,
    "tgn:name":"Yanjijie",
    "tgn:placetype":[
        "aat:300008347"
    ]
},
  "bbox": [],
  "geometry": {"coordinates":[121.55,25.05],"type":"Point"}
}