<<<<<<< HEAD
{
  "id": 7473395,
  "type": "Feature",
  "properties": {
    "tgn:hierarchy":[
        "tgn:7473395",
        "tgn:1000004",
        "tgn:1000959",
        "tgn:1000141",
        "tgn:7029392"
    ],
    "tgn:id":7473395,
    "tgn:name":"Yanjijie",
    "tgn:placetype":[
        "aat:300008347"
    ]
},
  "bbox": [],
  "geometry": {"coordinates":[121.55,25.05],"type":"Point"}
}
=======
{"geometry":{"type":"Point","coordinates":[121.550000,25.050000]},"type":"Feature","properties":{"hierarchy":["tgn:7473395","tgn:1000004","tgn:1000959","tgn:1000141","tgn:7029392"],"placetype":["aat:300008347"],"id":7473395,"name:xx":"Yanjijie"}}
>>>>>>> 03f74aca74312dbeaf24d7e61306dd6a786dc3d0
