<<<<<<< HEAD
{
  "id": 7174765,
  "type": "Feature",
  "properties": {
    "tgn:hierarchy":[
        "tgn:7174765",
        "tgn:1000003",
        "tgn:7003688",
        "tgn:7000084",
        "tgn:7029392"
    ],
    "tgn:id":7174765,
    "tgn:name":"Gro\u00df Hevenbruch",
    "tgn:placetype":[
        "aat:300008863"
    ]
},
  "bbox": [],
  "geometry": {"coordinates":[10.533333,53.633333],"type":"Point"}
}
=======
{"geometry":{"type":"Point","coordinates":[10.533333,53.633333]},"type":"Feature","properties":{"hierarchy":["tgn:7174765","tgn:1000003","tgn:7003688","tgn:7000084","tgn:7029392"],"placetype":["aat:300008863"],"id":7174765,"name:xx":"Gro\u00df Hevenbruch"}}
>>>>>>> 03f74aca74312dbeaf24d7e61306dd6a786dc3d0
