{
  "id": 7290669,
  "type": "Feature",
  "properties": {
    "tgn:hierarchy":[
        "tgn:7290669",
        "tgn:1001708",
        "tgn:1000049",
        "tgn:1000002",
        "tgn:7029392"
    ],
    "tgn:id":7290669,
    "tgn:name":"Cuncum\u00e9n Bajo",
    "tgn:placetype":[
        "aat:300000206"
    ]
},
  "bbox": [],
  "geometry": {"coordinates":[-71.466667,-33.75],"type":"Point"}
}