{
  "id": 1028267,
  "type": "Feature",
  "properties": {
    "tgn:hierarchy":[
        "tgn:1028267",
        "tgn:7019053",
        "tgn:7002445",
        "tgn:1000003",
        "tgn:7029505",
        "tgn:7008591",
        "tgn:7029392"
    ],
    "tgn:id":1028267,
    "tgn:name:en":"Adwick le Street",
    "tgn:placetype":[
        "aat:300008347",
        "aat:300008372"
    ]
},
  "bbox": [],
  "geometry": {"coordinates":[-1.183333,53.566667],"type":"Point"}
}