<<<<<<< HEAD
{
  "id": 7027181,
  "type": "Feature",
  "properties": {
    "tgn:hierarchy":[
        "tgn:7027181",
        "tgn:7002445",
        "tgn:1000003",
        "tgn:7008143",
        "tgn:7008591",
        "tgn:7029392"
    ],
    "tgn:id":7027181,
    "tgn:name:en":"Yatton",
    "tgn:placetype":[
        "aat:300008347",
        "aat:300008372"
    ]
},
  "bbox": [],
  "geometry": {"coordinates":[-2.85,52.3],"type":"Point"}
}
=======
{"geometry":{"type":"Point","coordinates":[-2.850000,52.300000]},"type":"Feature","properties":{"hierarchy":["tgn:7027181","tgn:7002445","tgn:1000003","tgn:7008143","tgn:7008591","tgn:7029392"],"placetype":["aat:300008347","aat:300008372"],"name:en":"Yatton","id":7027181}}
>>>>>>> 03f74aca74312dbeaf24d7e61306dd6a786dc3d0
