{
  "id": 2325282,
  "type": "Feature",
  "properties": {
    "tgn:hierarchy":[
        "tgn:2325282",
        "tgn:1000001",
        "tgn:7016172",
        "tgn:7012149",
        "tgn:2000148",
        "tgn:7029392"
    ],
    "tgn:id":2325282,
    "tgn:name":"Ferrel Creek",
    "tgn:placetype":[
        "aat:300008706"
    ]
},
  "bbox": [],
  "geometry": {"coordinates":[-93.7667,35.9667],"type":"Point"}
}