<<<<<<< HEAD
{
  "id": 7366620,
  "type": "Feature",
  "properties": {
    "tgn:hierarchy":[
        "tgn:7366620",
        "tgn:1001853",
        "tgn:1000001",
        "tgn:7005560",
        "tgn:7029392"
    ],
    "tgn:id":7366620,
    "tgn:name":"Rancho El Pino",
    "tgn:placetype":[
        "aat:300000241"
    ]
},
  "bbox": [],
  "geometry": {"coordinates":[-101.816667,28.783333],"type":"Point"}
}
=======
{"geometry":{"type":"Point","coordinates":[-101.816667,28.783333]},"type":"Feature","properties":{"hierarchy":["tgn:7366620","tgn:1001853","tgn:1000001","tgn:7005560","tgn:7029392"],"placetype":["aat:300000241"],"id":7366620,"name:xx":"Rancho El Pino"}}
>>>>>>> 03f74aca74312dbeaf24d7e61306dd6a786dc3d0
