{
  "id": 2153861,
  "type": "Feature",
  "properties": {
    "tgn:hierarchy":[
        "tgn:2153861",
        "tgn:1000001",
        "tgn:7012149",
        "tgn:2002110",
        "tgn:7007827",
        "tgn:7029392"
    ],
    "tgn:id":2153861,
    "tgn:name":"Bear Canyon",
    "tgn:placetype":[
        "aat:300008761"
    ]
},
  "bbox": [],
  "geometry": {"coordinates":[-109.5667,39.1167],"type":"Point"}
}