{
  "id": 2692326,
  "type": "Feature",
  "properties": {
    "tgn:hierarchy":[
        "tgn:2692326",
        "tgn:1000001",
        "tgn:2000920",
        "tgn:7012149",
        "tgn:7007515",
        "tgn:7029392"
    ],
    "tgn:id":2692326,
    "tgn:name":"Stave Island Ledge",
    "tgn:placetype":[
        "aat:300132348"
    ]
},
  "bbox": [],
  "geometry": {"coordinates":[-70.0667,43.7167],"type":"Point"}
}