{
  "id": 2038698,
  "type": "Feature",
  "properties": {
    "tgn:hierarchy":[
        "tgn:2038698",
        "tgn:1000001",
        "tgn:7012149",
        "tgn:2000821",
        "tgn:7007255",
        "tgn:7029392"
    ],
    "tgn:id":2038698,
    "tgn:name":"Elsie",
    "tgn:placetype":[
        "aat:300008347"
    ]
},
  "bbox": [],
  "geometry": {"coordinates":[-83.1333,37.7667],"type":"Point"}
}