{
  "id": 2783450,
  "type": "Feature",
  "properties": {
    "tgn:hierarchy":[
        "tgn:2783450",
        "tgn:1000001",
        "tgn:7012149",
        "tgn:2000210",
        "tgn:7007158",
        "tgn:7029392"
    ],
    "tgn:id":2783450,
    "tgn:name":"Wurts Ditch",
    "tgn:placetype":[
        "aat:300006075"
    ]
},
  "bbox": [],
  "geometry": {"coordinates":[-106.3333,39.4167],"type":"Point"}
}