{
  "id": 7485336,
  "type": "Feature",
  "properties": {
    "tgn:hierarchy":[
        "tgn:7485336",
        "tgn:7468018",
        "tgn:1000004",
        "tgn:1000141",
        "tgn:7029392"
    ],
    "tgn:id":7485336,
    "tgn:name":"Xiazhanghu",
    "tgn:placetype":[
        "aat:300008347"
    ]
},
  "bbox": [],
  "geometry": {"coordinates":[120.603611,23.578333],"type":"Point"}
}