{
  "id": 2394616,
  "type": "Feature",
  "properties": {
    "tgn:hierarchy":[
        "tgn:2394616",
        "tgn:1000001",
        "tgn:2000782",
        "tgn:7012149",
        "tgn:7007255",
        "tgn:7029392"
    ],
    "tgn:id":2394616,
    "tgn:name":"Hogskin Branch",
    "tgn:placetype":[
        "aat:300008699"
    ]
},
  "bbox": [],
  "geometry": {"coordinates":[-83.8167,37.2167],"type":"Point"}
}