{
  "id": 2294266,
  "type": "Feature",
  "properties": {
    "tgn:hierarchy":[
        "tgn:2294266",
        "tgn:1000001",
        "tgn:2002134",
        "tgn:7012149",
        "tgn:7007828",
        "tgn:7029392"
    ],
    "tgn:id":2294266,
    "tgn:name":"Dowdey Corner",
    "tgn:placetype":[
        "aat:300008347"
    ]
},
  "bbox": [],
  "geometry": {"coordinates":[-72.6167,43.8833],"type":"Point"}
}