{
  "id": 2162912,
  "type": "Feature",
  "properties": {
    "tgn:hierarchy":[
        "tgn:2162912",
        "tgn:1000001",
        "tgn:7012149",
        "tgn:2001715",
        "tgn:7007708",
        "tgn:7029392"
    ],
    "tgn:id":2162912,
    "tgn:name":"Benjamin Point",
    "tgn:placetype":[
        "aat:300266640"
    ]
},
  "bbox": [],
  "geometry": {"coordinates":[-120.3167,43.5333],"type":"Point"}
}