{
  "id": 7034246,
  "type": "Feature",
  "properties": {
    "tgn:hierarchy":[
        "tgn:7034246",
        "tgn:1001641",
        "tgn:1000003",
        "tgn:7003121",
        "tgn:1000080",
        "tgn:7029392"
    ],
    "tgn:id":7034246,
    "tgn:name":"Maccioni, Monte",
    "tgn:placetype":[
        "aat:300008795"
    ]
},
  "bbox": [],
  "geometry": {"coordinates":[9.533333,39.183333],"type":"Point"}
}