{
  "id": 7427982,
  "type": "Feature",
  "properties": {
    "tgn:hierarchy":[
        "tgn:7427982",
        "tgn:7005581",
        "tgn:1000001",
        "tgn:7005560",
        "tgn:7029392"
    ],
    "tgn:id":7427982,
    "tgn:name":"La Concordia",
    "tgn:placetype":[
        "aat:300008347"
    ]
},
  "bbox": [],
  "geometry": {"coordinates":[-106.016667,28.666667],"type":"Point"}
}