{
  "id": 2278971,
  "type": "Feature",
  "properties": {
    "tgn:hierarchy":[
        "tgn:2278971",
        "tgn:1000001",
        "tgn:7012149",
        "tgn:7007157",
        "tgn:2000189",
        "tgn:7029392"
    ],
    "tgn:id":2278971,
    "tgn:name":"Dead Mule Gulch",
    "tgn:placetype":[
        "aat:300008761"
    ]
},
  "bbox": [],
  "geometry": {"coordinates":[-123.3167,41.2667],"type":"Point"}
}