{
  "id": 2650075,
  "type": "Feature",
  "properties": {
    "tgn:hierarchy":[
        "tgn:2650075",
        "tgn:1000001",
        "tgn:7012149",
        "tgn:2002276",
        "tgn:7013961",
        "tgn:7029392"
    ],
    "tgn:id":2650075,
    "tgn:name":"Seabright Hollow",
    "tgn:placetype":[
        "aat:300008761"
    ]
},
  "bbox": [],
  "geometry": {"coordinates":[-80.6667,39.9833],"type":"Point"}
}