{
  "id": 2442654,
  "type": "Feature",
  "properties": {
    "tgn:hierarchy":[
        "tgn:2442654",
        "tgn:1000001",
        "tgn:2001584",
        "tgn:7012149",
        "tgn:7007705",
        "tgn:7029392"
    ],
    "tgn:id":2442654,
    "tgn:name":"Kugler Mine",
    "tgn:placetype":[
        "aat:300000390"
    ]
},
  "bbox": [],
  "geometry": {"coordinates":[-101.1167,47.3167],"type":"Point"}
}