{
  "id": 7496283,
  "type": "Feature",
  "properties": {
    "tgn:hierarchy":[
        "tgn:7496283",
        "tgn:1000004",
        "tgn:7001013",
        "tgn:1000141",
        "tgn:7029392"
    ],
    "tgn:id":7496283,
    "tgn:name":"Dazhenjiao",
    "tgn:placetype":[
        "aat:300008347"
    ]
},
  "bbox": [],
  "geometry": {"coordinates":[121.275748,24.972903],"type":"Point"}
}