{
  "id": 2246261,
  "type": "Feature",
  "properties": {
    "tgn:hierarchy":[
        "tgn:2246261",
        "tgn:2002142",
        "tgn:1000001",
        "tgn:7012149",
        "tgn:7007919",
        "tgn:7029392"
    ],
    "tgn:id":2246261,
    "tgn:name":"Coalpit Knob",
    "tgn:placetype":[
        "aat:300008798"
    ]
},
  "bbox": [],
  "geometry": {"coordinates":[-79.2833,38.25],"type":"Point"}
}