{
  "id": 2374840,
  "type": "Feature",
  "properties": {
    "tgn:hierarchy":[
        "tgn:2374840",
        "tgn:1000001",
        "tgn:7012149",
        "tgn:2001706",
        "tgn:7007708",
        "tgn:7029392"
    ],
    "tgn:id":2374840,
    "tgn:name":"Haney Creek",
    "tgn:placetype":[
        "aat:300008706"
    ]
},
  "bbox": [],
  "geometry": {"coordinates":[-123.5167,43.8333],"type":"Point"}
}