{
  "id": 7318062,
  "type": "Feature",
  "properties": {
    "tgn:hierarchy":[
        "tgn:7318062",
        "tgn:1001657",
        "tgn:1000049",
        "tgn:1000002",
        "tgn:7029392"
    ],
    "tgn:id":7318062,
    "tgn:name":"Corral Mu\u00f1oz",
    "tgn:placetype":[
        "aat:300008347"
    ]
},
  "bbox": [],
  "geometry": {"coordinates":[-70.260833,-30.325],"type":"Point"}
}