{
  "id": 7072533,
  "type": "Feature",
  "properties": {
    "tgn:hierarchy":[
        "tgn:7072533",
        "tgn:1000003",
        "tgn:7003676",
        "tgn:7000084",
        "tgn:7029392"
    ],
    "tgn:id":7072533,
    "tgn:name":"Str\u00f6hen",
    "tgn:placetype":[
        "aat:300000745"
    ]
},
  "bbox": [],
  "geometry": {"coordinates":[8.616667,53.066667],"type":"Point"}
}