{
  "id": 7067358,
  "type": "Feature",
  "properties": {
    "tgn:hierarchy":[
        "tgn:7067358",
        "tgn:1000003",
        "tgn:7003688",
        "tgn:7000084",
        "tgn:7029392"
    ],
    "tgn:id":7067358,
    "tgn:name":"F\u00f6rsterei Stodthagen",
    "tgn:placetype":[
        "aat:300004792"
    ]
},
  "bbox": [],
  "geometry": {"coordinates":[10.066667,54.416667],"type":"Point"}
}