{
  "id": 7487436,
  "type": "Feature",
  "properties": {
    "tgn:hierarchy":[
        "tgn:7487436",
        "tgn:1000004",
        "tgn:7001014",
        "tgn:1000141",
        "tgn:7029392"
    ],
    "tgn:id":7487436,
    "tgn:name":"Linzitou",
    "tgn:placetype":[
        "aat:300008347"
    ]
},
  "bbox": [],
  "geometry": {"coordinates":[120.569167,23.718611],"type":"Point"}
}