{
  "id": 2424128,
  "type": "Feature",
  "properties": {
    "tgn:hierarchy":[
        "tgn:2424128",
        "tgn:1000001",
        "tgn:1002775",
        "tgn:7012149",
        "tgn:7007565",
        "tgn:7029392"
    ],
    "tgn:id":2424128,
    "tgn:name":"Johns Lake",
    "tgn:placetype":[
        "aat:300008680"
    ]
},
  "bbox": [],
  "geometry": {"coordinates":[-74.3833,41.0167],"type":"Point"}
}