{
  "id": 7437489,
  "type": "Feature",
  "properties": {
    "tgn:hierarchy":[
        "tgn:7437489",
        "tgn:1001853",
        "tgn:1000001",
        "tgn:7005560",
        "tgn:7029392"
    ],
    "tgn:id":7437489,
    "tgn:name":"Rancho Santa Teresa",
    "tgn:placetype":[
        "aat:300000241"
    ]
},
  "bbox": [],
  "geometry": {"coordinates":[-103.616667,27.716667],"type":"Point"}
}