<<<<<<< HEAD
{
  "id": 2158930,
  "type": "Feature",
  "properties": {
    "tgn:hierarchy":[
        "tgn:2158930",
        "tgn:1000001",
        "tgn:7014352",
        "tgn:7012149",
        "tgn:7007564",
        "tgn:7029392"
    ],
    "tgn:id":2158930,
    "tgn:name":"Beckmans Pond",
    "tgn:placetype":[
        "aat:300008680"
    ]
},
  "bbox": [],
  "geometry": {"coordinates":[-70.85,42.8833],"type":"Point"}
}
=======
{"geometry":{"type":"Point","coordinates":[-70.850000,42.883300]},"type":"Feature","properties":{"hierarchy":["tgn:2158930","tgn:1000001","tgn:7014352","tgn:7012149","tgn:7007564","tgn:7029392"],"placetype":["aat:300008680"],"id":2158930,"name:xx":"Beckmans Pond"}}
>>>>>>> 03f74aca74312dbeaf24d7e61306dd6a786dc3d0
