{
  "id": 2538680,
  "type": "Feature",
  "properties": {
    "tgn:hierarchy":[
        "tgn:2538680",
        "tgn:7006450",
        "tgn:1000001",
        "tgn:7012149",
        "tgn:2000085",
        "tgn:7029392"
    ],
    "tgn:id":2538680,
    "tgn:name":"Neuberger, Mount",
    "tgn:placetype":[
        "aat:300008798"
    ]
},
  "bbox": [],
  "geometry": {"coordinates":[-143.4167,63.2667],"type":"Point"}
}