{
  "id": 7131286,
  "type": "Feature",
  "properties": {
    "tgn:hierarchy":[
        "tgn:7131286",
        "tgn:1000003",
        "tgn:7003687",
        "tgn:7000084",
        "tgn:7029392"
    ],
    "tgn:id":7131286,
    "tgn:name":"Markau",
    "tgn:placetype":[
        "aat:300008347"
    ]
},
  "bbox": [],
  "geometry": {"coordinates":[10.816667,52.816667],"type":"Point"}
}