{
  "id": 7262251,
  "type": "Feature",
  "properties": {
    "tgn:concordances":{
        "gn:id":"2756244"
    },
    "tgn:hierarchy":[
        "tgn:7262251",
        "tgn:1000003",
        "tgn:7003627",
        "tgn:7016845",
        "tgn:7029392"
    ],
    "tgn:id":7262251,
    "tgn:name:nl":"Eiteren",
    "tgn:placetype":[
        "aat:300008347"
    ]
},
  "bbox": [],
  "geometry": {"coordinates":[5.033333,52.033333],"type":"Point"}
}