{
  "id": 7515428,
  "type": "Feature",
  "properties": {
    "tgn:hierarchy":[
        "tgn:7515428",
        "tgn:1009227",
        "tgn:7001866",
        "tgn:1000226",
        "tgn:1000006",
        "tgn:7029392"
    ],
    "tgn:id":7515428,
    "tgn:name:en":"Cass",
    "tgn:placetype":[
        "aat:300008347"
    ]
},
  "bbox": [],
  "geometry": {"coordinates":[171.75,-43.033333],"type":"Point"}
}