{
  "id": 2451144,
  "type": "Feature",
  "properties": {
    "tgn:hierarchy":[
        "tgn:2451144",
        "tgn:1000001",
        "tgn:2001179",
        "tgn:7012149",
        "tgn:7007523",
        "tgn:7029392"
    ],
    "tgn:id":2451144,
    "tgn:name":"Little Apple Creek",
    "tgn:placetype":[
        "aat:300008706"
    ]
},
  "bbox": [],
  "geometry": {"coordinates":[-89.7833,37.5167],"type":"Point"}
}