{
  "id": 2165025,
  "type": "Feature",
  "properties": {
    "tgn:hierarchy":[
        "tgn:2165025",
        "tgn:1000001",
        "tgn:7016172",
        "tgn:7012149",
        "tgn:2000126",
        "tgn:7029392"
    ],
    "tgn:id":2165025,
    "tgn:name":"Bethel",
    "tgn:placetype":[
        "aat:300008347"
    ]
},
  "bbox": [],
  "geometry": {"coordinates":[-91.9333,33.7833],"type":"Point"}
}