{
  "id": 2385601,
  "type": "Feature",
  "properties": {
    "tgn:hierarchy":[
        "tgn:2385601",
        "tgn:1000001",
        "tgn:2001431",
        "tgn:7012149",
        "tgn:7007566",
        "tgn:7029392"
    ],
    "tgn:id":2385601,
    "tgn:name":"Henderson Reservoir",
    "tgn:placetype":[
        "aat:300006191"
    ]
},
  "bbox": [],
  "geometry": {"coordinates":[-107.5833,34.6333],"type":"Point"}
}