{
  "id": 7182997,
  "type": "Feature",
  "properties": {
    "tgn:hierarchy":[
        "tgn:7182997",
        "tgn:1000003",
        "tgn:7003682",
        "tgn:7000084",
        "tgn:7029392"
    ],
    "tgn:id":7182997,
    "tgn:name":"Galgenh\u00f6he",
    "tgn:placetype":[
        "aat:300008777"
    ]
},
  "bbox": [],
  "geometry": {"coordinates":[7.35,50.05],"type":"Point"}
}