{
  "id": 1108382,
  "type": "Feature",
  "properties": {
    "tgn:hierarchy":[
        "tgn:1108382",
        "tgn:1000004",
        "tgn:7029392"
    ],
    "tgn:id":1108382,
    "tgn:name":"Durbet-Daba, Pereval",
    "tgn:placetype":[
        "aat:300259572"
    ]
},
  "bbox": [],
  "geometry": {"coordinates":[89.4167,49.6167],"type":"Point"}
}