{
  "id": 2286098,
  "type": "Feature",
  "properties": {
    "tgn:hierarchy":[
        "tgn:2286098",
        "tgn:1000001",
        "tgn:2001945",
        "tgn:7012149",
        "tgn:7007826",
        "tgn:7029392"
    ],
    "tgn:id":2286098,
    "tgn:name":"Dewees Tank",
    "tgn:placetype":[
        "aat:300006191"
    ]
},
  "bbox": [],
  "geometry": {"coordinates":[-103.5667,29.7333],"type":"Point"}
}