{
  "id": 2586476,
  "type": "Feature",
  "properties": {
    "tgn:hierarchy":[
        "tgn:2586476",
        "tgn:1000001",
        "tgn:7012149",
        "tgn:2001716",
        "tgn:7007708",
        "tgn:7029392"
    ],
    "tgn:id":2586476,
    "tgn:name":"Pittenger Creek",
    "tgn:placetype":[
        "aat:300008706"
    ]
},
  "bbox": [],
  "geometry": {"coordinates":[-123.5333,43.9667],"type":"Point"}
}