{
  "id": 2067124,
  "type": "Feature",
  "properties": {
    "tgn:hierarchy":[
        "tgn:2067124",
        "tgn:1000001",
        "tgn:2001435",
        "tgn:7012149",
        "tgn:7007566",
        "tgn:7029392"
    ],
    "tgn:id":2067124,
    "tgn:name":"Leasburg",
    "tgn:placetype":[
        "aat:300387016"
    ]
},
  "bbox": [],
  "geometry": {"coordinates":[-106.8667,32.45],"type":"Point"}
}