{
  "id": 2536409,
  "type": "Feature",
  "properties": {
    "tgn:hierarchy":[
        "tgn:2536409",
        "tgn:1000001",
        "tgn:7012149",
        "tgn:7014021",
        "tgn:7007709",
        "tgn:7029392"
    ],
    "tgn:id":2536409,
    "tgn:name":"Neal Branch",
    "tgn:placetype":[
        "aat:300008699"
    ]
},
  "bbox": [],
  "geometry": {"coordinates":[-80.9667,35.1167],"type":"Point"}
}