{
  "id": 2664389,
  "type": "Feature",
  "properties": {
    "tgn:hierarchy":[
        "tgn:2664389",
        "tgn:1000001",
        "tgn:7012149",
        "tgn:2000839",
        "tgn:7007255",
        "tgn:7029392"
    ],
    "tgn:id":2664389,
    "tgn:name":"Silvers Hollow",
    "tgn:placetype":[
        "aat:300008761"
    ]
},
  "bbox": [],
  "geometry": {"coordinates":[-84.3833,37.0167],"type":"Point"}
}