{
  "id": 7526039,
  "type": "Feature",
  "properties": {
    "tgn:hierarchy":[
        "tgn:7526039",
        "tgn:7001242",
        "tgn:7016833",
        "tgn:7001334",
        "tgn:7029392"
    ],
    "tgn:id":7526039,
    "tgn:name:en":"Tar\u0101kiwah, 'Ayn",
    "tgn:placetype":[
        "aat:300008697"
    ]
},
  "bbox": [],
  "geometry": {"coordinates":[30.612569,25.589505],"type":"Point"}
}