{
  "id": 2549545,
  "type": "Feature",
  "properties": {
    "tgn:hierarchy":[
        "tgn:2549545",
        "tgn:1000001",
        "tgn:7012149",
        "tgn:7007827",
        "tgn:7029392"
    ],
    "tgn:id":2549545,
    "tgn:name":"North Spring Wash",
    "tgn:placetype":[
        "aat:300008761"
    ]
},
  "bbox": [],
  "geometry": {"coordinates":[-110.2833,38.45],"type":"Point"}
}