{
  "id": 2149337,
  "type": "Feature",
  "properties": {
    "tgn:hierarchy":[
        "tgn:2149337",
        "tgn:1000001",
        "tgn:1002266",
        "tgn:7012149",
        "tgn:7007710",
        "tgn:7029392"
    ],
    "tgn:id":2149337,
    "tgn:name":"Barren Brook",
    "tgn:placetype":[
        "aat:300008699"
    ]
},
  "bbox": [],
  "geometry": {"coordinates":[-75.95,39.7167],"type":"Point"}
}