{
  "id": 2653897,
  "type": "Feature",
  "properties": {
    "tgn:hierarchy":[
        "tgn:2653897",
        "tgn:1002366",
        "tgn:1000001",
        "tgn:7012149",
        "tgn:7007159",
        "tgn:7029392"
    ],
    "tgn:id":2653897,
    "tgn:name":"Seymour Rock",
    "tgn:placetype":[
        "aat:300008798"
    ]
},
  "bbox": [],
  "geometry": {"coordinates":[-73.35,41.0833],"type":"Point"}
}