{
  "id": 7573635,
  "type": "Feature",
  "properties": {
    "tgn:hierarchy":[
        "tgn:7573635",
        "tgn:1000004",
        "tgn:1001871",
        "tgn:7000198",
        "tgn:7029392"
    ],
    "tgn:id":7573635,
    "tgn:name:en":"Isr\u0101na",
    "tgn:placetype":[
        "aat:300007783"
    ]
},
  "bbox": [],
  "geometry": {"coordinates":[76.833333,29.283333],"type":"Point"}
}