<<<<<<< HEAD
{
  "id": 2150123,
  "type": "Feature",
  "properties": {
    "tgn:hierarchy":[
        "tgn:2150123",
        "tgn:1000001",
        "tgn:7012149",
        "tgn:2000476",
        "tgn:7007250",
        "tgn:7029392"
    ],
    "tgn:id":2150123,
    "tgn:name":"Barton Spring",
    "tgn:placetype":[
        "aat:300008697"
    ]
},
  "bbox": [],
  "geometry": {"coordinates":[-116.4833,45.3667],"type":"Point"}
}
=======
{"geometry":{"type":"Point","coordinates":[-116.483300,45.366700]},"type":"Feature","properties":{"hierarchy":["tgn:2150123","tgn:1000001","tgn:7012149","tgn:2000476","tgn:7007250","tgn:7029392"],"placetype":["aat:300008697"],"id":2150123,"name:xx":"Barton Spring"}}
>>>>>>> 03f74aca74312dbeaf24d7e61306dd6a786dc3d0
