{
  "id": 7496005,
  "type": "Feature",
  "properties": {
    "tgn:hierarchy":[
        "tgn:7496005",
        "tgn:1000004",
        "tgn:1000454",
        "tgn:1000141",
        "tgn:7029392"
    ],
    "tgn:id":7496005,
    "tgn:name":"Xiongkong Xi",
    "tgn:placetype":[
        "aat:300008699"
    ]
},
  "bbox": [],
  "geometry": {"coordinates":[121.448008,24.847451],"type":"Point"}
}