<<<<<<< HEAD
{
  "id": 7365008,
  "type": "Feature",
  "properties": {
    "tgn:hierarchy":[
        "tgn:7365008",
        "tgn:1001853",
        "tgn:1000001",
        "tgn:7005560",
        "tgn:7029392"
    ],
    "tgn:id":7365008,
    "tgn:name":"Fraile, Sierra del",
    "tgn:placetype":[
        "aat:300266640"
    ]
},
  "bbox": [],
  "geometry": {"coordinates":[-101.283333,25.0],"type":"Point"}
}
=======
{"geometry":{"type":"Point","coordinates":[-101.283333,25.000000]},"type":"Feature","properties":{"hierarchy":["tgn:7365008","tgn:1001853","tgn:1000001","tgn:7005560","tgn:7029392"],"placetype":["aat:300266640"],"id":7365008,"name:xx":"Fraile, Sierra del"}}
>>>>>>> 03f74aca74312dbeaf24d7e61306dd6a786dc3d0
