<<<<<<< HEAD
{
  "id": 2332111,
  "type": "Feature",
  "properties": {
    "tgn:hierarchy":[
        "tgn:2332111",
        "tgn:1000001",
        "tgn:7006451",
        "tgn:7012149",
        "tgn:2000099",
        "tgn:7029392"
    ],
    "tgn:id":2332111,
    "tgn:name":"Flint Knoll",
    "tgn:placetype":[
        "aat:300008798"
    ]
},
  "bbox": [],
  "geometry": {"coordinates":[-110.0,34.4333],"type":"Point"}
}
=======
{"geometry":{"type":"Point","coordinates":[-110.000000,34.433300]},"type":"Feature","properties":{"hierarchy":["tgn:2332111","tgn:1000001","tgn:7006451","tgn:7012149","tgn:2000099","tgn:7029392"],"placetype":["aat:300008798"],"id":2332111,"name:xx":"Flint Knoll"}}
>>>>>>> 03f74aca74312dbeaf24d7e61306dd6a786dc3d0
