{
  "id": 7254772,
  "type": "Feature",
  "properties": {
    "tgn:hierarchy":[
        "tgn:7254772",
        "tgn:7018239",
        "tgn:1000003",
        "tgn:1000063",
        "tgn:7018236",
        "tgn:7029392"
    ],
    "tgn:id":7254772,
    "tgn:name":"Steenhuffel",
    "tgn:placetype":[
        "aat:300008347"
    ]
},
  "bbox": [],
  "geometry": {"coordinates":[4.267877,50.995392],"type":"Point"}
}