{
  "id": 7236775,
  "type": "Feature",
  "properties": {
    "tgn:hierarchy":[
        "tgn:7236775",
        "tgn:7011168",
        "tgn:7001338",
        "tgn:1000003",
        "tgn:1000074",
        "tgn:7029392"
    ],
    "tgn:id":7236775,
    "tgn:name":"\u00c1gios Io\u00e1nnis, \u00c1kra",
    "tgn:placetype":[
        "aat:300008850"
    ]
},
  "bbox": [],
  "geometry": {"coordinates":[20.65,38.833333],"type":"Point"}
}