{
  "id": 1050937,
  "type": "Feature",
  "properties": {
    "tgn:hierarchy":[
        "tgn:1050937",
        "tgn:7002444",
        "tgn:1000003",
        "tgn:7008082",
        "tgn:7008591",
        "tgn:7029392"
    ],
    "tgn:id":1050937,
    "tgn:name:en":"Muir of Ord",
    "tgn:placetype":[
        "aat:300008347"
    ]
},
  "bbox": [],
  "geometry": {"coordinates":[-4.45,57.516667],"type":"Point"}
}