{
  "id": 7223075,
  "type": "Feature",
  "properties": {
    "tgn:hierarchy":[
        "tgn:7223075",
        "tgn:7002711",
        "tgn:7001338",
        "tgn:1000003",
        "tgn:1000074",
        "tgn:7029392"
    ],
    "tgn:id":7223075,
    "tgn:name":"Palaiokastr\u00edtsa",
    "tgn:placetype":[
        "aat:300008804"
    ]
},
  "bbox": [],
  "geometry": {"coordinates":[19.683333,39.666667],"type":"Point"}
}