{
  "id": 2610925,
  "type": "Feature",
  "properties": {
    "tgn:hierarchy":[
        "tgn:2610925",
        "tgn:1000001",
        "tgn:7012149",
        "tgn:7007157",
        "tgn:1002956",
        "tgn:7029392"
    ],
    "tgn:id":2610925,
    "tgn:name":"Red Hill",
    "tgn:placetype":[
        "aat:300008798"
    ]
},
  "bbox": [],
  "geometry": {"coordinates":[-118.8333,36.4667],"type":"Point"}
}