{
  "id": 2006310,
  "type": "Feature",
  "properties": {
    "tgn:hierarchy":[
        "tgn:2006310",
        "tgn:7006450",
        "tgn:1000001",
        "tgn:7012149",
        "tgn:2000087",
        "tgn:7029392"
    ],
    "tgn:id":2006310,
    "tgn:name":"Pilot Station",
    "tgn:placetype":[
        "aat:300008347"
    ]
},
  "bbox": [],
  "geometry": {"coordinates":[-162.8667,61.9333],"type":"Point"}
}