{
  "id": 7362800,
  "type": "Feature",
  "properties": {
    "tgn:hierarchy":[
        "tgn:7362800",
        "tgn:1000001",
        "tgn:1001893",
        "tgn:7005560",
        "tgn:7029392"
    ],
    "tgn:id":7362800,
    "tgn:name":"El \u00c1lamo",
    "tgn:placetype":[
        "aat:300008347"
    ]
},
  "bbox": [],
  "geometry": {"coordinates":[-99.766667,20.216667],"type":"Point"}
}