{
  "id": 2637688,
  "type": "Feature",
  "properties": {
    "tgn:hierarchy":[
        "tgn:2637688",
        "tgn:1000001",
        "tgn:7012149",
        "tgn:2001304",
        "tgn:7007524",
        "tgn:7029392"
    ],
    "tgn:id":2637688,
    "tgn:name":"Saint Paul Lake",
    "tgn:placetype":[
        "aat:300008680"
    ]
},
  "bbox": [],
  "geometry": {"coordinates":[-115.65,48.0833],"type":"Point"}
}