{
  "id": 7235772,
  "type": "Feature",
  "properties": {
    "tgn:hierarchy":[
        "tgn:7235772",
        "tgn:7002706",
        "tgn:7002705",
        "tgn:1000003",
        "tgn:1000074",
        "tgn:7029392"
    ],
    "tgn:id":7235772,
    "tgn:name":"Ap\u00f3meron",
    "tgn:placetype":[
        "aat:300008347"
    ]
},
  "bbox": [],
  "geometry": {"coordinates":[20.941111,39.077222],"type":"Point"}
}