{
  "id": 1087926,
  "type": "Feature",
  "properties": {
    "tgn:hierarchy":[
        "tgn:1087926",
        "tgn:7001242",
        "tgn:1000149",
        "tgn:1000888",
        "tgn:7029392"
    ],
    "tgn:id":1087926,
    "tgn:name":"Mussolo",
    "tgn:placetype":[
        "aat:300008347"
    ]
},
  "bbox": [],
  "geometry": {"coordinates":[17.3333,-10.0167],"type":"Point"}
}