{
  "id": 2415609,
  "type": "Feature",
  "properties": {
    "tgn:hierarchy":[
        "tgn:2415609",
        "tgn:1000001",
        "tgn:7012149",
        "tgn:2002125",
        "tgn:7007827",
        "tgn:7029392"
    ],
    "tgn:id":2415609,
    "tgn:name":"Israel Canyon",
    "tgn:placetype":[
        "aat:300008761"
    ]
},
  "bbox": [],
  "geometry": {"coordinates":[-111.95,40.2833],"type":"Point"}
}