{
  "id": 7057810,
  "type": "Feature",
  "properties": {
    "tgn:hierarchy":[
        "tgn:7057810",
        "tgn:1000003",
        "tgn:7003122",
        "tgn:1001762",
        "tgn:1000080",
        "tgn:7029392"
    ],
    "tgn:id":7057810,
    "tgn:name":"Arini",
    "tgn:placetype":[
        "aat:300008347"
    ]
},
  "bbox": [],
  "geometry": {"coordinates":[12.483333,37.816667],"type":"Point"}
}