<<<<<<< HEAD
{
  "id": 2338114,
  "type": "Feature",
  "properties": {
    "tgn:hierarchy":[
        "tgn:2338114",
        "tgn:1000001",
        "tgn:7012149",
        "tgn:1002917",
        "tgn:7007706",
        "tgn:7029392"
    ],
    "tgn:id":2338114,
    "tgn:name":"Fox Mine",
    "tgn:placetype":[
        "aat:300000390"
    ]
},
  "bbox": [],
  "geometry": {"coordinates":[-81.5333,40.6833],"type":"Point"}
}
=======
{"geometry":{"type":"Point","coordinates":[-81.533300,40.683300]},"type":"Feature","properties":{"hierarchy":["tgn:2338114","tgn:1000001","tgn:7012149","tgn:1002917","tgn:7007706","tgn:7029392"],"placetype":["aat:300000390"],"id":2338114,"name:xx":"Fox Mine"}}
>>>>>>> 03f74aca74312dbeaf24d7e61306dd6a786dc3d0
