{
  "id": 2313987,
  "type": "Feature",
  "properties": {
    "tgn:hierarchy":[
        "tgn:2313987",
        "tgn:1000001",
        "tgn:7012149",
        "tgn:7007517",
        "tgn:7029392"
    ],
    "tgn:id":2313987,
    "tgn:name":"Elizabeth Brook",
    "tgn:placetype":[
        "aat:300008699"
    ]
},
  "bbox": [],
  "geometry": {"coordinates":[-71.55,42.4833],"type":"Point"}
}