{
  "id": 2145031,
  "type": "Feature",
  "properties": {
    "tgn:hierarchy":[
        "tgn:2145031",
        "tgn:1000001",
        "tgn:7012149",
        "tgn:2000926",
        "tgn:7007515",
        "tgn:7029392"
    ],
    "tgn:id":2145031,
    "tgn:name":"Bald Ledge",
    "tgn:placetype":[
        "aat:300008798"
    ]
},
  "bbox": [],
  "geometry": {"coordinates":[-70.9667,43.85],"type":"Point"}
}