{
  "id": 2777255,
  "type": "Feature",
  "properties": {
    "tgn:hierarchy":[
        "tgn:2777255",
        "tgn:1000001",
        "tgn:7012149",
        "tgn:1002920",
        "tgn:7007568",
        "tgn:7029392"
    ],
    "tgn:id":2777255,
    "tgn:name":"Winfield Creek",
    "tgn:placetype":[
        "aat:300008706"
    ]
},
  "bbox": [],
  "geometry": {"coordinates":[-76.9833,42.15],"type":"Point"}
}