{
  "id": 7418832,
  "type": "Feature",
  "properties": {
    "tgn:hierarchy":[
        "tgn:7418832",
        "tgn:1001835",
        "tgn:1000001",
        "tgn:7005560",
        "tgn:7029392"
    ],
    "tgn:id":7418832,
    "tgn:name":"Grande, Cerro",
    "tgn:placetype":[
        "aat:300008795"
    ]
},
  "bbox": [],
  "geometry": {"coordinates":[-116.066667,32.026944],"type":"Point"}
}