{
  "id": 2701861,
  "type": "Feature",
  "properties": {
    "tgn:hierarchy":[
        "tgn:2701861",
        "tgn:1000001",
        "tgn:7012149",
        "tgn:7007157",
        "tgn:7014475",
        "tgn:7029392"
    ],
    "tgn:id":2701861,
    "tgn:name":"Sugarloaf Mountain",
    "tgn:placetype":[
        "aat:300008798"
    ]
},
  "bbox": [],
  "geometry": {"coordinates":[-121.55,37.3333],"type":"Point"}
}