{
  "id": 7365051,
  "type": "Feature",
  "properties": {
    "tgn:hierarchy":[
        "tgn:7365051",
        "tgn:1000001",
        "tgn:7005593",
        "tgn:7005560",
        "tgn:7029392"
    ],
    "tgn:id":7365051,
    "tgn:name":"El Sauz Tequisquiapan",
    "tgn:placetype":[
        "aat:300008347"
    ]
},
  "bbox": [],
  "geometry": {"coordinates":[-99.866667,20.516667],"type":"Point"}
}