{
  "id": 2648537,
  "type": "Feature",
  "properties": {
    "tgn:hierarchy":[
        "tgn:2648537",
        "tgn:1000001",
        "tgn:7012149",
        "tgn:2001048",
        "tgn:7007521",
        "tgn:7029392"
    ],
    "tgn:id":2648537,
    "tgn:name":"Schwerin Creek",
    "tgn:placetype":[
        "aat:300008706"
    ]
},
  "bbox": [],
  "geometry": {"coordinates":[-92.6667,43.65],"type":"Point"}
}