{
  "id": 1121554,
  "type": "Feature",
  "properties": {
    "tgn:hierarchy":[
        "tgn:1121554",
        "tgn:7001242",
        "tgn:1000180",
        "tgn:7029392"
    ],
    "tgn:id":1121554,
    "tgn:name":"B\u00fazi",
    "tgn:placetype":[
        "aat:300008707"
    ]
},
  "bbox": [],
  "geometry": {"coordinates":[34.75,-19.9167],"type":"Point"}
}