{
  "id": 7476745,
  "type": "Feature",
  "properties": {
    "tgn:hierarchy":[
        "tgn:7476745",
        "tgn:7488858",
        "tgn:1000004",
        "tgn:1000141",
        "tgn:7029392"
    ],
    "tgn:id":7476745,
    "tgn:name":"Toushe Qiao",
    "tgn:placetype":[
        "aat:300007836"
    ]
},
  "bbox": [],
  "geometry": {"coordinates":[120.895557,23.832777],"type":"Point"}
}