{
  "id": 7347596,
  "type": "Feature",
  "properties": {
    "tgn:hierarchy":[
        "tgn:7347596",
        "tgn:7002824",
        "tgn:1000003",
        "tgn:7002786",
        "tgn:1000095",
        "tgn:7029392"
    ],
    "tgn:id":7347596,
    "tgn:name":"Bascoy",
    "tgn:placetype":[
        "aat:300008347"
    ]
},
  "bbox": [],
  "geometry": {"coordinates":[-8.216667,43.116667],"type":"Point"}
}