{
  "id": 7063342,
  "type": "Feature",
  "properties": {
    "tgn:hierarchy":[
        "tgn:7063342",
        "tgn:7003669",
        "tgn:1000003",
        "tgn:7000084",
        "tgn:7029392"
    ],
    "tgn:id":7063342,
    "tgn:name":"Atzen-Berg",
    "tgn:placetype":[
        "aat:300008777"
    ]
},
  "bbox": [],
  "geometry": {"coordinates":[11.133333,47.733333],"type":"Point"}
}