{
  "id": 1011765,
  "type": "Feature",
  "properties": {
    "tgn:hierarchy":[
        "tgn:1011765",
        "tgn:1006652",
        "tgn:1000004",
        "tgn:1009908",
        "tgn:1001481",
        "tgn:1000135",
        "tgn:7029392"
    ],
    "tgn:id":1011765,
    "tgn:name":"Conconongon Point",
    "tgn:placetype":[
        "aat:300386846"
    ]
},
  "bbox": [],
  "geometry": {"coordinates":[120.2167,12.2333],"type":"Point"}
}