{
  "id": 2329712,
  "type": "Feature",
  "properties": {
    "tgn:hierarchy":[
        "tgn:2329712",
        "tgn:1000001",
        "tgn:2001938",
        "tgn:7012149",
        "tgn:7007826",
        "tgn:7029392"
    ],
    "tgn:id":2329712,
    "tgn:name":"Fivemile Hill",
    "tgn:placetype":[
        "aat:300008798"
    ]
},
  "bbox": [],
  "geometry": {"coordinates":[-98.9833,29.6833],"type":"Point"}
}