{
  "id": 2505280,
  "type": "Feature",
  "properties": {
    "tgn:hierarchy":[
        "tgn:2505280",
        "tgn:1000001",
        "tgn:7012149",
        "tgn:2000509",
        "tgn:7007251",
        "tgn:7029392"
    ],
    "tgn:id":2505280,
    "tgn:name":"Melcher Hills",
    "tgn:placetype":[
        "aat:300008798"
    ]
},
  "bbox": [],
  "geometry": {"coordinates":[-88.3833,37.4333],"type":"Point"}
}