{
  "id": 2266131,
  "type": "Feature",
  "properties": {
    "tgn:hierarchy":[
        "tgn:2266131",
        "tgn:1000001",
        "tgn:7012149",
        "tgn:2000286",
        "tgn:7007240",
        "tgn:7029392"
    ],
    "tgn:id":2266131,
    "tgn:name":"Crawford Lake",
    "tgn:placetype":[
        "aat:300008680"
    ]
},
  "bbox": [],
  "geometry": {"coordinates":[-82.9167,30.15],"type":"Point"}
}