{
  "id": 7420102,
  "type": "Feature",
  "properties": {
    "tgn:hierarchy":[
        "tgn:7420102",
        "tgn:1000001",
        "tgn:7005589",
        "tgn:7005560",
        "tgn:7029392"
    ],
    "tgn:id":7420102,
    "tgn:name:es":"San Carlos",
    "tgn:placetype":[
        "aat:300008347"
    ]
},
  "bbox": [],
  "geometry": {"coordinates":[-99.5625,26.315278],"type":"Point"}
}