{
  "id": 7428785,
  "type": "Feature",
  "properties": {
    "tgn:hierarchy":[
        "tgn:7428785",
        "tgn:1001835",
        "tgn:1000001",
        "tgn:7005560",
        "tgn:7029392"
    ],
    "tgn:id":7428785,
    "tgn:name":"Juarez",
    "tgn:placetype":[
        "aat:300008347"
    ]
},
  "bbox": [],
  "geometry": {"coordinates":[-114.116667,28.833333],"type":"Point"}
}