{
  "id": 2542371,
  "type": "Feature",
  "properties": {
    "tgn:hierarchy":[
        "tgn:2542371",
        "tgn:1000001",
        "tgn:7012149",
        "tgn:2001831",
        "tgn:7007713",
        "tgn:7029392"
    ],
    "tgn:id":2542371,
    "tgn:name":"No Moccasin Creek",
    "tgn:placetype":[
        "aat:300008706"
    ]
},
  "bbox": [],
  "geometry": {"coordinates":[-99.6333,43.45],"type":"Point"}
}