<<<<<<< HEAD
{
  "id": 2251255,
  "type": "Feature",
  "properties": {
    "tgn:hierarchy":[
        "tgn:2251255",
        "tgn:1000001",
        "tgn:7012149",
        "tgn:2001923",
        "tgn:7007825",
        "tgn:7029392"
    ],
    "tgn:id":2251255,
    "tgn:name":"Comb Ridge",
    "tgn:placetype":[
        "aat:300266640"
    ]
},
  "bbox": [],
  "geometry": {"coordinates":[-83.8167,36.2],"type":"Point"}
}
=======
{"geometry":{"type":"Point","coordinates":[-83.816700,36.200000]},"type":"Feature","properties":{"hierarchy":["tgn:2251255","tgn:1000001","tgn:7012149","tgn:2001923","tgn:7007825","tgn:7029392"],"placetype":["aat:300266640"],"id":2251255,"name:xx":"Comb Ridge"}}
>>>>>>> 03f74aca74312dbeaf24d7e61306dd6a786dc3d0
