{
  "id": 7584032,
  "type": "Feature",
  "properties": {
    "tgn:hierarchy":[
        "tgn:7584032",
        "tgn:1000004",
        "tgn:7000198",
        "tgn:1001894",
        "tgn:7029392"
    ],
    "tgn:id":7584032,
    "tgn:name:en":"Pirozpura",
    "tgn:placetype":[
        "aat:300008347"
    ]
},
  "bbox": [],
  "geometry": {"coordinates":[78.815675,25.048996],"type":"Point"}
}