{
  "id": 1024677,
  "type": "Feature",
  "properties": {
    "tgn:hierarchy":[
        "tgn:1024677",
        "tgn:1000670",
        "tgn:1000002",
        "tgn:1000056",
        "tgn:7029392"
    ],
    "tgn:id":1024677,
    "tgn:name":"Paramonga",
    "tgn:placetype":[
        "aat:300008347"
    ]
},
  "bbox": [],
  "geometry": {"coordinates":[-77.8333,-10.6667],"type":"Point"}
}