<<<<<<< HEAD
{
  "id": 2765967,
  "type": "Feature",
  "properties": {
    "tgn:hierarchy":[
        "tgn:2765967",
        "tgn:1000001",
        "tgn:7012149",
        "tgn:2001036",
        "tgn:7007521",
        "tgn:7029392"
    ],
    "tgn:id":2765967,
    "tgn:name":"White Hills",
    "tgn:placetype":[
        "aat:300008798"
    ]
},
  "bbox": [],
  "geometry": {"coordinates":[-91.7667,47.9833],"type":"Point"}
}
=======
{"geometry":{"type":"Point","coordinates":[-91.766700,47.983300]},"type":"Feature","properties":{"hierarchy":["tgn:2765967","tgn:1000001","tgn:7012149","tgn:2001036","tgn:7007521","tgn:7029392"],"placetype":["aat:300008798"],"id":2765967,"name:xx":"White Hills"}}
>>>>>>> 03f74aca74312dbeaf24d7e61306dd6a786dc3d0
