{
  "id": 2448408,
  "type": "Feature",
  "properties": {
    "tgn:hierarchy":[
        "tgn:2448408",
        "tgn:1000001",
        "tgn:1002753",
        "tgn:7012149",
        "tgn:7007828",
        "tgn:7029392"
    ],
    "tgn:id":2448408,
    "tgn:name":"Lilly Branch",
    "tgn:placetype":[
        "aat:300008699"
    ]
},
  "bbox": [],
  "geometry": {"coordinates":[-72.35,44.85],"type":"Point"}
}