{
  "id": 1085108,
  "type": "Feature",
  "properties": {
    "tgn:hierarchy":[
        "tgn:1085108",
        "tgn:1002074",
        "tgn:1000004",
        "tgn:1000140",
        "tgn:7029392"
    ],
    "tgn:id":1085108,
    "tgn:name":"Ash Shaykh Sa\u02bbd",
    "tgn:placetype":[
        "aat:300008347"
    ]
},
  "bbox": [],
  "geometry": {"coordinates":[36.0333,32.8333],"type":"Point"}
}