{
  "id": 2116863,
  "type": "Feature",
  "properties": {
    "tgn:hierarchy":[
        "tgn:2116863",
        "tgn:1000001",
        "tgn:7012149",
        "tgn:7018871",
        "tgn:7007920",
        "tgn:7029392"
    ],
    "tgn:id":2116863,
    "tgn:name":"Spring Glen",
    "tgn:placetype":[
        "aat:300008347"
    ]
},
  "bbox": [],
  "geometry": {"coordinates":[-121.85,47.55],"type":"Point"}
}