{
  "id": 2579333,
  "type": "Feature",
  "properties": {
    "tgn:hierarchy":[
        "tgn:2579333",
        "tgn:1000001",
        "tgn:7012149",
        "tgn:2002286",
        "tgn:7013961",
        "tgn:7029392"
    ],
    "tgn:id":2579333,
    "tgn:name":"Pickens Run",
    "tgn:placetype":[
        "aat:300008699"
    ]
},
  "bbox": [],
  "geometry": {"coordinates":[-81.2667,39.35],"type":"Point"}
}