{
  "id": 7068648,
  "type": "Feature",
  "properties": {
    "tgn:hierarchy":[
        "tgn:7068648",
        "tgn:1000003",
        "tgn:7594165",
        "tgn:7000084",
        "tgn:7029392"
    ],
    "tgn:id":7068648,
    "tgn:name":"Stahlberg",
    "tgn:placetype":[
        "aat:300008347"
    ]
},
  "bbox": [],
  "geometry": {"coordinates":[13.016667,50.05],"type":"Point"}
}