{
  "id": 7510125,
  "type": "Feature",
  "properties": {
    "tgn:hierarchy":[
        "tgn:7510125",
        "tgn:1009227",
        "tgn:1000226",
        "tgn:1000006",
        "tgn:7016850",
        "tgn:7029392"
    ],
    "tgn:id":7510125,
    "tgn:name:en":"Steele, Mount",
    "tgn:placetype":[
        "aat:300008795"
    ]
},
  "bbox": [],
  "geometry": {"coordinates":[171.733333,-42.05],"type":"Point"}
}