{
  "id": 7502680,
  "type": "Feature",
  "properties": {
    "tgn:hierarchy":[
        "tgn:7502680",
        "tgn:7001004",
        "tgn:1000004",
        "tgn:1000141",
        "tgn:7029392"
    ],
    "tgn:id":7502680,
    "tgn:name":"Jianguo",
    "tgn:placetype":[
        "aat:300008347"
    ]
},
  "bbox": [],
  "geometry": {"coordinates":[120.349722,22.873889],"type":"Point"}
}