{
  "id": 1139944,
  "type": "Feature",
  "properties": {
    "tgn:hierarchy":[
        "tgn:1139944",
        "tgn:1000004",
        "tgn:7002077",
        "tgn:1000111",
        "tgn:7029392"
    ],
    "tgn:id":1139944,
    "tgn:name":"Yangji",
    "tgn:placetype":[
        "aat:300008347"
    ]
},
  "bbox": [],
  "geometry": {"coordinates":[113.9333,36.7333],"type":"Point"}
}