{
  "id": 7225885,
  "type": "Feature",
  "properties": {
    "tgn:hierarchy":[
        "tgn:7225885",
        "tgn:7011167",
        "tgn:7001338",
        "tgn:1000003",
        "tgn:1000074",
        "tgn:7029392"
    ],
    "tgn:id":7225885,
    "tgn:name":"Prov\u00e1ti, Nis\u00edda",
    "tgn:placetype":[
        "aat:300008791"
    ]
},
  "bbox": [],
  "geometry": {"coordinates":[21.047778,38.464722],"type":"Point"}
}