{
  "id": 2082510,
  "type": "Feature",
  "properties": {
    "tgn:hierarchy":[
        "tgn:2082510",
        "tgn:1000001",
        "tgn:7012149",
        "tgn:1003025",
        "tgn:7007706",
        "tgn:7029392"
    ],
    "tgn:id":2082510,
    "tgn:name":"West Jefferson",
    "tgn:placetype":[
        "aat:300008347"
    ]
},
  "bbox": [],
  "geometry": {"coordinates":[-84.55,41.5667],"type":"Point"}
}