{
  "id": 2541937,
  "type": "Feature",
  "properties": {
    "tgn:hierarchy":[
        "tgn:2541937",
        "tgn:7006450",
        "tgn:1000001",
        "tgn:7012149",
        "tgn:2000089",
        "tgn:7029392"
    ],
    "tgn:id":2541937,
    "tgn:name":"Ninety-two Hunter Creek",
    "tgn:placetype":[
        "aat:300008706"
    ]
},
  "bbox": [],
  "geometry": {"coordinates":[-149.85,65.3833],"type":"Point"}
}