{
  "id": 7455376,
  "type": "Feature",
  "properties": {
    "tgn:hierarchy":[
        "tgn:7455376",
        "tgn:7019094",
        "tgn:7002444",
        "tgn:1000003",
        "tgn:7008591",
        "tgn:7029392"
    ],
    "tgn:id":7455376,
    "tgn:name:en":"Castle Toward",
    "tgn:placetype":[
        "aat:300387502"
    ]
},
  "bbox": [],
  "geometry": {"coordinates":[-5.016667,55.866667],"type":"Point"}
}