{
  "id": 2353021,
  "type": "Feature",
  "properties": {
    "tgn:hierarchy":[
        "tgn:2353021",
        "tgn:1000001",
        "tgn:2001411",
        "tgn:7012149",
        "tgn:7007526",
        "tgn:7029392"
    ],
    "tgn:id":2353021,
    "tgn:name":"Gods Pocket Peak",
    "tgn:placetype":[
        "aat:300008798"
    ]
},
  "bbox": [],
  "geometry": {"coordinates":[-115.2833,41.7833],"type":"Point"}
}