{
  "id": 2574784,
  "type": "Feature",
  "properties": {
    "tgn:hierarchy":[
        "tgn:2574784",
        "tgn:1000001",
        "tgn:7012149",
        "tgn:2001075",
        "tgn:7007521",
        "tgn:7029392"
    ],
    "tgn:id":2574784,
    "tgn:name":"Pendergast Lake",
    "tgn:placetype":[
        "aat:300008680"
    ]
},
  "bbox": [],
  "geometry": {"coordinates":[-95.1167,46.1667],"type":"Point"}
}