{
  "id": 7333896,
  "type": "Feature",
  "properties": {
    "tgn:hierarchy":[
        "tgn:7333896",
        "tgn:7002824",
        "tgn:1000003",
        "tgn:7002786",
        "tgn:1000095",
        "tgn:7029392"
    ],
    "tgn:id":7333896,
    "tgn:name":"Entrecruces",
    "tgn:placetype":[
        "aat:300008347"
    ]
},
  "bbox": [],
  "geometry": {"coordinates":[-8.683333,43.133333],"type":"Point"}
}