{
  "id": 7572655,
  "type": "Feature",
  "properties": {
    "tgn:hierarchy":[
        "tgn:7572655",
        "tgn:1000004",
        "tgn:1001869",
        "tgn:7000198",
        "tgn:7029392"
    ],
    "tgn:id":7572655,
    "tgn:name:en":"Jhuran",
    "tgn:placetype":[
        "aat:300008347"
    ]
},
  "bbox": [],
  "geometry": {"coordinates":[70.000504,23.368081],"type":"Point"}
}