{
  "id": 7050994,
  "type": "Feature",
  "properties": {
    "tgn:hierarchy":[
        "tgn:7050994",
        "tgn:7003166",
        "tgn:1000003",
        "tgn:7009760",
        "tgn:1000080",
        "tgn:7029392"
    ],
    "tgn:id":7050994,
    "tgn:name":"Laj\u00e0tico",
    "tgn:placetype":[
        "aat:300008347"
    ]
},
  "bbox": [],
  "geometry": {"coordinates":[10.716667,43.483333],"type":"Point"}
}