{
  "id": 2569478,
  "type": "Feature",
  "properties": {
    "tgn:hierarchy":[
        "tgn:2569478",
        "tgn:1000001",
        "tgn:7012149",
        "tgn:7007157",
        "tgn:1002858",
        "tgn:7029392"
    ],
    "tgn:id":2569478,
    "tgn:name":"Paroli Spring",
    "tgn:placetype":[
        "aat:300008697"
    ]
},
  "bbox": [],
  "geometry": {"coordinates":[-116.55,33.15],"type":"Point"}
}