{
  "id": 7551891,
  "type": "Feature",
  "properties": {
    "tgn:hierarchy":[
        "tgn:7551891",
        "tgn:1000004",
        "tgn:7000198",
        "tgn:7000799",
        "tgn:7029392"
    ],
    "tgn:id":7551891,
    "tgn:name:en":"Doru",
    "tgn:placetype":[
        "aat:300008347"
    ]
},
  "bbox": [],
  "geometry": {"coordinates":[75.223042,33.576716],"type":"Point"}
}