{
  "id": 1043838,
  "type": "Feature",
  "properties": {
    "tgn:hierarchy":[
        "tgn:1043838",
        "tgn:7003006",
        "tgn:1000003",
        "tgn:7002997",
        "tgn:1000080",
        "tgn:7029392"
    ],
    "tgn:id":1043838,
    "tgn:name":"Caorle",
    "tgn:placetype":[
        "aat:300008347"
    ]
},
  "bbox": [],
  "geometry": {"coordinates":[12.883889,45.599722],"type":"Point"}
}