{
  "id": 1135588,
  "type": "Feature",
  "properties": {
    "tgn:hierarchy":[
        "tgn:1135588",
        "tgn:7001242",
        "tgn:7016833",
        "tgn:1001335",
        "tgn:7029392"
    ],
    "tgn:id":1135588,
    "tgn:name":"Rash\u012bd, Ma\u1e63abb",
    "tgn:placetype":[
        "aat:300387057"
    ]
},
  "bbox": [],
  "geometry": {"coordinates":[30.360556,31.485833],"type":"Point"}
}