{
  "id": 7387924,
  "type": "Feature",
  "properties": {
    "tgn:hierarchy":[
        "tgn:7387924",
        "tgn:7005584",
        "tgn:1000001",
        "tgn:7005560",
        "tgn:7029392"
    ],
    "tgn:id":7387924,
    "tgn:name":"Puerto de Ferrer",
    "tgn:placetype":[
        "aat:300008347"
    ]
},
  "bbox": [],
  "geometry": {"coordinates":[-100.733333,20.183333],"type":"Point"}
}