{
  "id": 7400034,
  "type": "Feature",
  "properties": {
    "tgn:hierarchy":[
        "tgn:7400034",
        "tgn:1000001",
        "tgn:7005593",
        "tgn:7005560",
        "tgn:7029392"
    ],
    "tgn:id":7400034,
    "tgn:name":"Puerto de Huilotla",
    "tgn:placetype":[
        "aat:300008347"
    ]
},
  "bbox": [],
  "geometry": {"coordinates":[-99.583333,21.166667],"type":"Point"}
}