{
  "id": 1075220,
  "type": "Feature",
  "properties": {
    "tgn:hierarchy":[
        "tgn:1075220",
        "tgn:1000004",
        "tgn:7000198",
        "tgn:7000799",
        "tgn:7029392"
    ],
    "tgn:id":1075220,
    "tgn:name":"Dras",
    "tgn:placetype":[
        "aat:300008347"
    ]
},
  "bbox": [],
  "geometry": {"coordinates":[75.753919,34.430713],"type":"Point"}
}