<<<<<<< HEAD
{
  "id": 2150526,
  "type": "Feature",
  "properties": {
    "tgn:hierarchy":[
        "tgn:2150526",
        "tgn:1000001",
        "tgn:7006451",
        "tgn:7012149",
        "tgn:2000100",
        "tgn:7029392"
    ],
    "tgn:id":2150526,
    "tgn:name":"Basin Spring",
    "tgn:placetype":[
        "aat:300008697"
    ]
},
  "bbox": [],
  "geometry": {"coordinates":[-110.7667,31.8],"type":"Point"}
}
=======
{"geometry":{"type":"Point","coordinates":[-110.766700,31.800000]},"type":"Feature","properties":{"hierarchy":["tgn:2150526","tgn:1000001","tgn:7006451","tgn:7012149","tgn:2000100","tgn:7029392"],"placetype":["aat:300008697"],"id":2150526,"name:xx":"Basin Spring"}}
>>>>>>> 03f74aca74312dbeaf24d7e61306dd6a786dc3d0
