{
  "id": 7395018,
  "type": "Feature",
  "properties": {
    "tgn:hierarchy":[
        "tgn:7395018",
        "tgn:7005583",
        "tgn:1000001",
        "tgn:7005560",
        "tgn:7029392"
    ],
    "tgn:id":7395018,
    "tgn:name":"San Jos\u00e9del Barranco",
    "tgn:placetype":[
        "aat:300008347"
    ]
},
  "bbox": [],
  "geometry": {"coordinates":[-105.116667,25.783333],"type":"Point"}
}