{
  "id": 7584308,
  "type": "Feature",
  "properties": {
    "tgn:hierarchy":[
        "tgn:7584308",
        "tgn:1000004",
        "tgn:7000198",
        "tgn:1001894",
        "tgn:7029392"
    ],
    "tgn:id":7584308,
    "tgn:name:en":"Bothi",
    "tgn:placetype":[
        "aat:300008347"
    ]
},
  "bbox": [],
  "geometry": {"coordinates":[78.060744,24.221082],"type":"Point"}
}