{
  "id": 7202470,
  "type": "Feature",
  "properties": {
    "tgn:hierarchy":[
        "tgn:7202470",
        "tgn:1000003",
        "tgn:7003677",
        "tgn:7000084",
        "tgn:7029392"
    ],
    "tgn:id":7202470,
    "tgn:name":"Broicherseite",
    "tgn:placetype":[
        "aat:300008347"
    ]
},
  "bbox": [],
  "geometry": {"coordinates":[6.65,51.25],"type":"Point"}
}