<<<<<<< HEAD
{
  "id": 7023149,
  "type": "Feature",
  "properties": {
    "tgn:hierarchy":[
        "tgn:7023149",
        "tgn:1000001",
        "tgn:7012149",
        "tgn:7029392"
    ],
    "tgn:id":7023149,
    "tgn:name":"Inkpot Lake",
    "tgn:placetype":[
        "aat:300008680"
    ]
},
  "bbox": [],
  "geometry": {"coordinates":[-89.5,46.2167],"type":"Point"}
}
=======
{"geometry":{"type":"Point","coordinates":[-89.500000,46.216700]},"type":"Feature","properties":{"hierarchy":["tgn:7023149","tgn:1000001","tgn:7012149","tgn:7029392"],"placetype":["aat:300008680"],"id":7023149,"name:xx":"Inkpot Lake"}}
>>>>>>> 03f74aca74312dbeaf24d7e61306dd6a786dc3d0
