{
  "id": 2149894,
  "type": "Feature",
  "properties": {
    "tgn:hierarchy":[
        "tgn:2149894",
        "tgn:7006450",
        "tgn:1000001",
        "tgn:7019698",
        "tgn:7012149",
        "tgn:7029392"
    ],
    "tgn:id":2149894,
    "tgn:name":"Bartlett Glacier",
    "tgn:placetype":[
        "aat:300008835"
    ]
},
  "bbox": [],
  "geometry": {"coordinates":[-148.9667,60.6167],"type":"Point"}
}