<<<<<<< HEAD
{
  "id": 2403854,
  "type": "Feature",
  "properties": {
    "tgn:hierarchy":[
        "tgn:2403854",
        "tgn:1000001",
        "tgn:2001091",
        "tgn:7012149",
        "tgn:7007522",
        "tgn:7029392"
    ],
    "tgn:id":2403854,
    "tgn:name":"Howden Lake",
    "tgn:placetype":[
        "aat:300008680"
    ]
},
  "bbox": [],
  "geometry": {"coordinates":[-90.6833,34.05],"type":"Point"}
}
=======
{"geometry":{"type":"Point","coordinates":[-90.683300,34.050000]},"type":"Feature","properties":{"hierarchy":["tgn:2403854","tgn:1000001","tgn:2001091","tgn:7012149","tgn:7007522","tgn:7029392"],"placetype":["aat:300008680"],"id":2403854,"name:xx":"Howden Lake"}}
>>>>>>> 03f74aca74312dbeaf24d7e61306dd6a786dc3d0
