{
  "id": 7252717,
  "type": "Feature",
  "properties": {
    "tgn:hierarchy":[
        "tgn:7252717",
        "tgn:7003458",
        "tgn:1000003",
        "tgn:1000063",
        "tgn:7018236",
        "tgn:7029392"
    ],
    "tgn:id":7252717,
    "tgn:name":"Saint Jean, Ruisseau",
    "tgn:placetype":[
        "aat:300008699"
    ]
},
  "bbox": [],
  "geometry": {"coordinates":[2.825893,50.957362],"type":"Point"}
}