{
  "id": 7564280,
  "type": "Feature",
  "properties": {
    "tgn:hierarchy":[
        "tgn:7564280",
        "tgn:1000004",
        "tgn:7000198",
        "tgn:1001894",
        "tgn:7029392"
    ],
    "tgn:id":7564280,
    "tgn:name:en":"Nivariya",
    "tgn:placetype":[
        "aat:300008347"
    ]
},
  "bbox": [],
  "geometry": {"coordinates":[79.446289,24.841326],"type":"Point"}
}