{
  "id": 2397046,
  "type": "Feature",
  "properties": {
    "tgn:hierarchy":[
        "tgn:2397046",
        "tgn:1000001",
        "tgn:7012149",
        "tgn:2001196",
        "tgn:7007523",
        "tgn:7029392"
    ],
    "tgn:id":2397046,
    "tgn:name":"Homestead Hollow",
    "tgn:placetype":[
        "aat:300008761"
    ]
},
  "bbox": [],
  "geometry": {"coordinates":[-92.85,36.8167],"type":"Point"}
}