{
  "id": 7226022,
  "type": "Feature",
  "properties": {
    "tgn:hierarchy":[
        "tgn:7226022",
        "tgn:7011171",
        "tgn:7001395",
        "tgn:1000003",
        "tgn:1000074",
        "tgn:7029392"
    ],
    "tgn:id":7226022,
    "tgn:name":"Mourti\u00e1, \u00d3rmos",
    "tgn:placetype":[
        "aat:300132316"
    ]
},
  "bbox": [],
  "geometry": {"coordinates":[23.833333,39.15],"type":"Point"}
}