{
  "id": 7402162,
  "type": "Feature",
  "properties": {
    "tgn:hierarchy":[
        "tgn:7402162",
        "tgn:1000001",
        "tgn:7005600",
        "tgn:7005560",
        "tgn:7029392"
    ],
    "tgn:id":7402162,
    "tgn:name":"Yaxalao, Cenote",
    "tgn:placetype":[
        "aat:300343547"
    ]
},
  "bbox": [],
  "geometry": {"coordinates":[-89.233333,20.658333],"type":"Point"}
}