{
  "id": 2625720,
  "type": "Feature",
  "properties": {
    "tgn:hierarchy":[
        "tgn:2625720",
        "tgn:7002659",
        "tgn:1000001",
        "tgn:7012149",
        "tgn:2000039",
        "tgn:7029392"
    ],
    "tgn:id":2625720,
    "tgn:name":"Rocky Branch",
    "tgn:placetype":[
        "aat:300008699"
    ]
},
  "bbox": [],
  "geometry": {"coordinates":[-87.3833,34.4333],"type":"Point"}
}