{
  "id": 2161792,
  "type": "Feature",
  "properties": {
    "tgn:hierarchy":[
        "tgn:2161792",
        "tgn:1000001",
        "tgn:7012149",
        "tgn:7007158",
        "tgn:7029392"
    ],
    "tgn:id":2161792,
    "tgn:name":"Belleview Mountain",
    "tgn:placetype":[
        "aat:300008798"
    ]
},
  "bbox": [],
  "geometry": {"coordinates":[-106.9833,39.0333],"type":"Point"}
}