{
  "id": 2475991,
  "type": "Feature",
  "properties": {
    "tgn:hierarchy":[
        "tgn:2475991",
        "tgn:1000001",
        "tgn:7012149",
        "tgn:7007157",
        "tgn:1002608",
        "tgn:7029392"
    ],
    "tgn:id":2475991,
    "tgn:name":"Luguna Channel",
    "tgn:placetype":[
        "aat:300008699"
    ]
},
  "bbox": [],
  "geometry": {"coordinates":[-118.15,34.0667],"type":"Point"}
}