{
  "id": 7215687,
  "type": "Feature",
  "properties": {
    "tgn:hierarchy":[
        "tgn:7215687",
        "tgn:1000003",
        "tgn:7003676",
        "tgn:7000084",
        "tgn:7029392"
    ],
    "tgn:id":7215687,
    "tgn:name":"Acker-Berg",
    "tgn:placetype":[
        "aat:300008777"
    ]
},
  "bbox": [],
  "geometry": {"coordinates":[9.05,53.483333],"type":"Point"}
}