{
  "id": 2502323,
  "type": "Feature",
  "properties": {
    "tgn:hierarchy":[
        "tgn:2502323",
        "tgn:1000001",
        "tgn:7012149",
        "tgn:2001761",
        "tgn:7007712",
        "tgn:7029392"
    ],
    "tgn:id":2502323,
    "tgn:name":"McKinney Mountain",
    "tgn:placetype":[
        "aat:300008798"
    ]
},
  "bbox": [],
  "geometry": {"coordinates":[-82.8667,34.9333],"type":"Point"}
}