<<<<<<< HEAD
{
  "id": 7115798,
  "type": "Feature",
  "properties": {
    "tgn:hierarchy":[
        "tgn:7115798",
        "tgn:1000003",
        "tgn:7003688",
        "tgn:7000084",
        "tgn:7029392"
    ],
    "tgn:id":7115798,
    "tgn:name":"Oholz",
    "tgn:placetype":[
        "aat:300000206"
    ]
},
  "bbox": [],
  "geometry": {"coordinates":[10.5,54.216667],"type":"Point"}
}
=======
{"geometry":{"type":"Point","coordinates":[10.500000,54.216667]},"type":"Feature","properties":{"hierarchy":["tgn:7115798","tgn:1000003","tgn:7003688","tgn:7000084","tgn:7029392"],"placetype":["aat:300000206"],"id":7115798,"name:xx":"Oholz"}}
>>>>>>> 03f74aca74312dbeaf24d7e61306dd6a786dc3d0
