{
  "id": 2654721,
  "type": "Feature",
  "properties": {
    "tgn:hierarchy":[
        "tgn:2654721",
        "tgn:7006450",
        "tgn:1000001",
        "tgn:7012149",
        "tgn:2000088",
        "tgn:7029392"
    ],
    "tgn:id":2654721,
    "tgn:name":"Shakes Lake",
    "tgn:placetype":[
        "aat:300008680"
    ]
},
  "bbox": [],
  "geometry": {"coordinates":[-132.1167,56.7667],"type":"Point"}
}