{
  "id": 2165694,
  "type": "Feature",
  "properties": {
    "tgn:hierarchy":[
        "tgn:2165694",
        "tgn:7006450",
        "tgn:1000001",
        "tgn:7012149",
        "tgn:2000088",
        "tgn:7029392"
    ],
    "tgn:id":2165694,
    "tgn:name":"Bibb Shoal",
    "tgn:placetype":[
        "aat:300132348"
    ]
},
  "bbox": [],
  "geometry": {"coordinates":[-134.3667,56.8667],"type":"Point"}
}