{
  "id": 2264471,
  "type": "Feature",
  "properties": {
    "tgn:hierarchy":[
        "tgn:2264471",
        "tgn:1000001",
        "tgn:7012149",
        "tgn:7014589",
        "tgn:7007515",
        "tgn:7029392"
    ],
    "tgn:id":2264471,
    "tgn:name":"Crabtree Bog",
    "tgn:placetype":[
        "aat:300008905"
    ]
},
  "bbox": [],
  "geometry": {"coordinates":[-67.8667,45.45],"type":"Point"}
}