{
  "id": 7250734,
  "type": "Feature",
  "properties": {
    "tgn:hierarchy":[
        "tgn:7250734",
        "tgn:7003465",
        "tgn:1000003",
        "tgn:1000063",
        "tgn:4012014",
        "tgn:7029392"
    ],
    "tgn:id":7250734,
    "tgn:name":"Muno, For\u00eat de",
    "tgn:placetype":[
        "aat:300008863"
    ]
},
  "bbox": [],
  "geometry": {"coordinates":[5.25,49.733333],"type":"Point"}
}