<<<<<<< HEAD
{
  "id": 2155812,
  "type": "Feature",
  "properties": {
    "tgn:hierarchy":[
        "tgn:2155812",
        "tgn:1000001",
        "tgn:7006451",
        "tgn:2000092",
        "tgn:7012149",
        "tgn:7029392"
    ],
    "tgn:id":2155812,
    "tgn:name":"Bear Tank Number Two",
    "tgn:placetype":[
        "aat:300006191"
    ]
},
  "bbox": [],
  "geometry": {"coordinates":[-112.2167,35.15],"type":"Point"}
}
=======
{"geometry":{"type":"Point","coordinates":[-112.216700,35.150000]},"type":"Feature","properties":{"hierarchy":["tgn:2155812","tgn:1000001","tgn:7006451","tgn:2000092","tgn:7012149","tgn:7029392"],"placetype":["aat:300006191"],"id":2155812,"name:xx":"Bear Tank Number Two"}}
>>>>>>> 03f74aca74312dbeaf24d7e61306dd6a786dc3d0
