{
  "id": 1022693,
  "type": "Feature",
  "properties": {
    "tgn:hierarchy":[
        "tgn:1022693",
        "tgn:7016581",
        "tgn:1000047",
        "tgn:7002455",
        "tgn:1000002",
        "tgn:7029392"
    ],
    "tgn:id":1022693,
    "tgn:name":"Rio Largo",
    "tgn:placetype":[
        "aat:300008347"
    ]
},
  "bbox": [],
  "geometry": {"coordinates":[-35.8333,-9.4667],"type":"Point"}
}