{
  "id": 2613671,
  "type": "Feature",
  "properties": {
    "tgn:hierarchy":[
        "tgn:2613671",
        "tgn:1000001",
        "tgn:7006451",
        "tgn:7012149",
        "tgn:2000098",
        "tgn:7029392"
    ],
    "tgn:id":2613671,
    "tgn:name":"Reeds Reservoir",
    "tgn:placetype":[
        "aat:300006191"
    ]
},
  "bbox": [],
  "geometry": {"coordinates":[-113.1833,36.9667],"type":"Point"}
}