{
  "id": 1100364,
  "type": "Feature",
  "properties": {
    "tgn:hierarchy":[
        "tgn:1100364",
        "tgn:1000003",
        "tgn:1000462",
        "tgn:1000097",
        "tgn:7029392"
    ],
    "tgn:id":1100364,
    "tgn:name":"Vik",
    "tgn:placetype":[
        "aat:300006891"
    ]
},
  "bbox": [],
  "geometry": {"coordinates":[17.45,59.7333],"type":"Point"}
}