{
  "id": 2737842,
  "type": "Feature",
  "properties": {
    "tgn:hierarchy":[
        "tgn:2737842",
        "tgn:7002659",
        "tgn:1000001",
        "tgn:7012149",
        "tgn:2000043",
        "tgn:7029392"
    ],
    "tgn:id":2737842,
    "tgn:name":"Tysons Lake",
    "tgn:placetype":[
        "aat:300006191"
    ]
},
  "bbox": [],
  "geometry": {"coordinates":[-85.6167,32.3333],"type":"Point"}
}