{
  "id": 2435611,
  "type": "Feature",
  "properties": {
    "tgn:hierarchy":[
        "tgn:2435611",
        "tgn:1002165",
        "tgn:1000001",
        "tgn:7012149",
        "tgn:7007517",
        "tgn:7029392"
    ],
    "tgn:id":2435611,
    "tgn:name":"Kescayo Gansett Pond",
    "tgn:placetype":[
        "aat:300008680"
    ]
},
  "bbox": [],
  "geometry": {"coordinates":[-69.9667,41.7667],"type":"Point"}
}