<<<<<<< HEAD
{
  "id": 7362876,
  "type": "Feature",
  "properties": {
    "tgn:hierarchy":[
        "tgn:7362876",
        "tgn:1000001",
        "tgn:7005597",
        "tgn:7005560",
        "tgn:7029392"
    ],
    "tgn:id":7362876,
    "tgn:name":"El Mentidero",
    "tgn:placetype":[
        "aat:300008699"
    ]
},
  "bbox": [],
  "geometry": {"coordinates":[-97.95,23.1],"type":"Point"}
}
=======
{"geometry":{"type":"Point","coordinates":[-97.950000,23.100000]},"type":"Feature","properties":{"hierarchy":["tgn:7362876","tgn:1000001","tgn:7005597","tgn:7005560","tgn:7029392"],"placetype":["aat:300008699"],"id":7362876,"name:xx":"El Mentidero"}}
>>>>>>> 03f74aca74312dbeaf24d7e61306dd6a786dc3d0
