{
  "id": 7266296,
  "type": "Feature",
  "properties": {
    "tgn:concordances":{
        "gn:id":"2754579"
    },
    "tgn:hierarchy":[
        "tgn:7266296",
        "tgn:7003619",
        "tgn:1000003",
        "tgn:7016845",
        "tgn:7029392"
    ],
    "tgn:id":7266296,
    "tgn:name:nl":"Heidenhoek",
    "tgn:placetype":[
        "aat:300008347"
    ]
},
  "bbox": [],
  "geometry": {"coordinates":[6.35,51.983333],"type":"Point"}
}