<<<<<<< HEAD
{
  "id": 7359255,
  "type": "Feature",
  "properties": {
    "tgn:hierarchy":[
        "tgn:7359255",
        "tgn:7005579",
        "tgn:1000001",
        "tgn:7005560",
        "tgn:7029392"
    ],
    "tgn:id":7359255,
    "tgn:name":"Divisadero, Cerro",
    "tgn:placetype":[
        "aat:300008795"
    ]
},
  "bbox": [],
  "geometry": {"coordinates":[-102.6,21.85],"type":"Point"}
}
=======
{"geometry":{"type":"Point","coordinates":[-102.600000,21.850000]},"type":"Feature","properties":{"hierarchy":["tgn:7359255","tgn:7005579","tgn:1000001","tgn:7005560","tgn:7029392"],"placetype":["aat:300008795"],"id":7359255,"name:xx":"Divisadero, Cerro"}}
>>>>>>> 03f74aca74312dbeaf24d7e61306dd6a786dc3d0
