{
  "id": 7367069,
  "type": "Feature",
  "properties": {
    "tgn:hierarchy":[
        "tgn:7367069",
        "tgn:1000001",
        "tgn:1001960",
        "tgn:7005560",
        "tgn:7029392"
    ],
    "tgn:id":7367069,
    "tgn:name":"El Picacho",
    "tgn:placetype":[
        "aat:300008347"
    ]
},
  "bbox": [],
  "geometry": {"coordinates":[-111.266667,30.316667],"type":"Point"}
}