<<<<<<< HEAD
{
  "id": 2331088,
  "type": "Feature",
  "properties": {
    "tgn:hierarchy":[
        "tgn:2331088",
        "tgn:1000001",
        "tgn:2001470",
        "tgn:7012149",
        "tgn:7007709",
        "tgn:7029392"
    ],
    "tgn:id":2331088,
    "tgn:name":"Flat Swamp Creek",
    "tgn:placetype":[
        "aat:300008706"
    ]
},
  "bbox": [],
  "geometry": {"coordinates":[-76.8167,36.1],"type":"Point"}
}
=======
{"geometry":{"type":"Point","coordinates":[-76.816700,36.100000]},"type":"Feature","properties":{"hierarchy":["tgn:2331088","tgn:1000001","tgn:2001470","tgn:7012149","tgn:7007709","tgn:7029392"],"placetype":["aat:300008706"],"id":2331088,"name:xx":"Flat Swamp Creek"}}
>>>>>>> 03f74aca74312dbeaf24d7e61306dd6a786dc3d0
