{
  "id": 2157029,
  "type": "Feature",
  "properties": {
    "tgn:hierarchy":[
        "tgn:2157029",
        "tgn:1000001",
        "tgn:7016172",
        "tgn:7012149",
        "tgn:2000158",
        "tgn:7029392"
    ],
    "tgn:id":2157029,
    "tgn:name":"Beaver Bayou Ditch",
    "tgn:placetype":[
        "aat:300006075"
    ]
},
  "bbox": [],
  "geometry": {"coordinates":[-90.7833,34.4333],"type":"Point"}
}