<<<<<<< HEAD
{
  "id": 2157029,
  "type": "Feature",
  "properties": {
    "tgn:hierarchy":[
        "tgn:2157029",
        "tgn:1000001",
        "tgn:7016172",
        "tgn:7012149",
        "tgn:2000158",
        "tgn:7029392"
    ],
    "tgn:id":2157029,
    "tgn:name":"Beaver Bayou Ditch",
    "tgn:placetype":[
        "aat:300006075"
    ]
},
  "bbox": [],
  "geometry": {"coordinates":[-90.7833,34.4333],"type":"Point"}
}
=======
{"geometry":{"type":"Point","coordinates":[-90.783300,34.433300]},"type":"Feature","properties":{"hierarchy":["tgn:2157029","tgn:1000001","tgn:7016172","tgn:7012149","tgn:2000158","tgn:7029392"],"placetype":["aat:300006075"],"id":2157029,"name:xx":"Beaver Bayou Ditch"}}
>>>>>>> 03f74aca74312dbeaf24d7e61306dd6a786dc3d0
