{
  "id": 2325688,
  "type": "Feature",
  "properties": {
    "tgn:hierarchy":[
        "tgn:2325688",
        "tgn:1000001",
        "tgn:2000666",
        "tgn:7012149",
        "tgn:7007254",
        "tgn:7029392"
    ],
    "tgn:id":2325688,
    "tgn:name":"Fidelity",
    "tgn:placetype":[
        "aat:300008347"
    ]
},
  "bbox": [],
  "geometry": {"coordinates":[-95.7833,39.7833],"type":"Point"}
}