<<<<<<< HEAD
{
  "id": 2337484,
  "type": "Feature",
  "properties": {
    "tgn:hierarchy":[
        "tgn:2337484",
        "tgn:1000001",
        "tgn:7012149",
        "tgn:2000352",
        "tgn:7007248",
        "tgn:7029392"
    ],
    "tgn:id":2337484,
    "tgn:name":"Fowler Mountain",
    "tgn:placetype":[
        "aat:300008798"
    ]
},
  "bbox": [],
  "geometry": {"coordinates":[-84.4833,34.8],"type":"Point"}
}
=======
{"geometry":{"type":"Point","coordinates":[-84.483300,34.800000]},"type":"Feature","properties":{"hierarchy":["tgn:2337484","tgn:1000001","tgn:7012149","tgn:2000352","tgn:7007248","tgn:7029392"],"placetype":["aat:300008798"],"id":2337484,"name:xx":"Fowler Mountain"}}
>>>>>>> 03f74aca74312dbeaf24d7e61306dd6a786dc3d0
