<<<<<<< HEAD
{
  "id": 2159204,
  "type": "Feature",
  "properties": {
    "tgn:hierarchy":[
        "tgn:2159204",
        "tgn:1000001",
        "tgn:7012149",
        "tgn:2001662",
        "tgn:7007707",
        "tgn:7029392"
    ],
    "tgn:id":2159204,
    "tgn:name":"Bedwell",
    "tgn:placetype":[
        "aat:300008347"
    ]
},
  "bbox": [],
  "geometry": {"coordinates":[-94.7167,35.15],"type":"Point"}
}
=======
{"geometry":{"type":"Point","coordinates":[-94.716700,35.150000]},"type":"Feature","properties":{"hierarchy":["tgn:2159204","tgn:1000001","tgn:7012149","tgn:2001662","tgn:7007707","tgn:7029392"],"placetype":["aat:300008347"],"id":2159204,"name:xx":"Bedwell"}}
>>>>>>> 03f74aca74312dbeaf24d7e61306dd6a786dc3d0
