{
  "id": 2123210,
  "type": "Feature",
  "properties": {
    "tgn:hierarchy":[
        "tgn:2123210",
        "tgn:1000001",
        "tgn:7012149",
        "tgn:2002381",
        "tgn:7007923",
        "tgn:7029392"
    ],
    "tgn:id":2123210,
    "tgn:name":"Ulm",
    "tgn:placetype":[
        "aat:300008347",
        "aat:300387210"
    ]
},
  "bbox": [],
  "geometry": {"coordinates":[-106.5833,44.65],"type":"Point"}
}