{
  "id": 2031914,
  "type": "Feature",
  "properties": {
    "tgn:hierarchy":[
        "tgn:2031914",
        "tgn:1000001",
        "tgn:7012149",
        "tgn:1002376",
        "tgn:7007252",
        "tgn:7029392"
    ],
    "tgn:id":2031914,
    "tgn:name":"Galena",
    "tgn:placetype":[
        "aat:300008347"
    ]
},
  "bbox": [],
  "geometry": {"coordinates":[-85.9333,38.35],"type":"Point"}
}