{
  "id": 7278906,
  "type": "Feature",
  "properties": {
    "tgn:hierarchy":[
        "tgn:7278906",
        "tgn:1001657",
        "tgn:1000049",
        "tgn:1000002",
        "tgn:7029392"
    ],
    "tgn:id":7278906,
    "tgn:name":"Salinas, Punta",
    "tgn:placetype":[
        "aat:300386846"
    ]
},
  "bbox": [],
  "geometry": {"coordinates":[-71.534167,-32.136111],"type":"Point"}
}