{
  "id": 2173597,
  "type": "Feature",
  "properties": {
    "tgn:hierarchy":[
        "tgn:2173597",
        "tgn:1000001",
        "tgn:7012149",
        "tgn:2001461",
        "tgn:7007568",
        "tgn:7029392"
    ],
    "tgn:id":2173597,
    "tgn:name":"Birch Pond",
    "tgn:placetype":[
        "aat:300008680"
    ]
},
  "bbox": [],
  "geometry": {"coordinates":[-73.6333,44.0833],"type":"Point"}
}