{
  "id": 7540150,
  "type": "Feature",
  "properties": {
    "tgn:hierarchy":[
        "tgn:7540150",
        "tgn:7001242",
        "tgn:1001075",
        "tgn:7016833",
        "tgn:7029392"
    ],
    "tgn:id":7540150,
    "tgn:name:en":"Jann\u0101b\u012byat as Sa'r\u0101n\u012byah",
    "tgn:placetype":[
        "aat:300006075"
    ]
},
  "bbox": [],
  "geometry": {"coordinates":[30.15,31.133333],"type":"Point"}
}