{
  "id": 2646838,
  "type": "Feature",
  "properties": {
    "tgn:hierarchy":[
        "tgn:2646838",
        "tgn:1000001",
        "tgn:7012149",
        "tgn:1002750",
        "tgn:7007252",
        "tgn:7029392"
    ],
    "tgn:id":2646838,
    "tgn:name":"Scarlet",
    "tgn:placetype":[
        "aat:300008347"
    ]
},
  "bbox": [],
  "geometry": {"coordinates":[-86.6667,38.65],"type":"Point"}
}