{
  "id": 7590038,
  "type": "Feature",
  "properties": {
    "tgn:hierarchy":[
        "tgn:7590038",
        "tgn:1000004",
        "tgn:1001871",
        "tgn:7000198",
        "tgn:7029392"
    ],
    "tgn:id":7590038,
    "tgn:name:en":"Sam\u0101ni",
    "tgn:placetype":[
        "aat:300008347"
    ]
},
  "bbox": [],
  "geometry": {"coordinates":[76.913398,29.922678],"type":"Point"}
}