{
  "id": 1029216,
  "type": "Feature",
  "properties": {
    "tgn:hierarchy":[
        "tgn:1029216",
        "tgn:7002445",
        "tgn:1000003",
        "tgn:7008175",
        "tgn:7008591",
        "tgn:7029392"
    ],
    "tgn:id":1029216,
    "tgn:name:en":"Farleigh",
    "tgn:placetype":[
        "aat:300008347"
    ]
},
  "bbox": [],
  "geometry": {"coordinates":[-0.033333,51.316667],"type":"Point"}
}