<<<<<<< HEAD
{
  "id": 2252110,
  "type": "Feature",
  "properties": {
    "tgn:hierarchy":[
        "tgn:2252110",
        "tgn:1000001",
        "tgn:7012149",
        "tgn:2001273",
        "tgn:7007524",
        "tgn:7029392"
    ],
    "tgn:id":2252110,
    "tgn:name":"Cone Butte",
    "tgn:placetype":[
        "aat:300008798"
    ]
},
  "bbox": [],
  "geometry": {"coordinates":[-109.0667,47.25],"type":"Point"}
}
=======
{"geometry":{"type":"Point","coordinates":[-109.066700,47.250000]},"type":"Feature","properties":{"hierarchy":["tgn:2252110","tgn:1000001","tgn:7012149","tgn:2001273","tgn:7007524","tgn:7029392"],"placetype":["aat:300008798"],"id":2252110,"name:xx":"Cone Butte"}}
>>>>>>> 03f74aca74312dbeaf24d7e61306dd6a786dc3d0
