{
  "id": 2529672,
  "type": "Feature",
  "properties": {
    "tgn:hierarchy":[
        "tgn:2529672",
        "tgn:1002147",
        "tgn:1000001",
        "tgn:7012149",
        "tgn:7007255",
        "tgn:7029392"
    ],
    "tgn:id":2529672,
    "tgn:name":"Mud Lick",
    "tgn:placetype":[
        "aat:300008699"
    ]
},
  "bbox": [],
  "geometry": {"coordinates":[-85.0833,37.9333],"type":"Point"}
}