{
  "id": 7416864,
  "type": "Feature",
  "properties": {
    "tgn:hierarchy":[
        "tgn:7416864",
        "tgn:1000001",
        "tgn:7005591",
        "tgn:7005560",
        "tgn:7029392"
    ],
    "tgn:id":7416864,
    "tgn:name:es":"Arroyo de Banco",
    "tgn:placetype":[
        "aat:300008347"
    ]
},
  "bbox": [],
  "geometry": {"coordinates":[-96.343611,17.804167],"type":"Point"}
}