{
  "id": 7518313,
  "type": "Feature",
  "properties": {
    "tgn:hierarchy":[
        "tgn:7518313",
        "tgn:1009227",
        "tgn:1000226",
        "tgn:7018437",
        "tgn:1000006",
        "tgn:7029392"
    ],
    "tgn:id":7518313,
    "tgn:name:en":"Neilson Creek",
    "tgn:placetype":[
        "aat:300008699"
    ]
},
  "bbox": [],
  "geometry": {"coordinates":[169.283333,-43.933333],"type":"Point"}
}