{
  "id": 7564981,
  "type": "Feature",
  "properties": {
    "tgn:hierarchy":[
        "tgn:7564981",
        "tgn:1000004",
        "tgn:7000198",
        "tgn:7000799",
        "tgn:7029392"
    ],
    "tgn:id":7564981,
    "tgn:name:en":"Mandli\u0101l",
    "tgn:placetype":[
        "aat:300008347"
    ]
},
  "bbox": [],
  "geometry": {"coordinates":[74.953402,32.49228],"type":"Point"}
}