{
  "id": 2153560,
  "type": "Feature",
  "properties": {
    "tgn:hierarchy":[
        "tgn:2153560",
        "tgn:1000001",
        "tgn:7012149",
        "tgn:2002073",
        "tgn:7007826",
        "tgn:7029392"
    ],
    "tgn:id":2153560,
    "tgn:name":"Bear Bayou",
    "tgn:placetype":[
        "aat:300008699"
    ]
},
  "bbox": [],
  "geometry": {"coordinates":[-94.3333,31.8333],"type":"Point"}
}