{
  "id": 2029366,
  "type": "Feature",
  "properties": {
    "tgn:hierarchy":[
        "tgn:2029366",
        "tgn:1000001",
        "tgn:7012149",
        "tgn:1002531",
        "tgn:7007251",
        "tgn:7029392"
    ],
    "tgn:id":2029366,
    "tgn:name":"North Plato",
    "tgn:placetype":[
        "aat:300008347",
        "aat:300387210"
    ]
},
  "bbox": [],
  "geometry": {"coordinates":[-88.45,42.05],"type":"Point"}
}