<<<<<<< HEAD
{
  "id": 2158964,
  "type": "Feature",
  "properties": {
    "tgn:hierarchy":[
        "tgn:2158964",
        "tgn:1000001",
        "tgn:7012149",
        "tgn:7007920",
        "tgn:7029392"
    ],
    "tgn:id":2158964,
    "tgn:name":"Beckstrom Hill",
    "tgn:placetype":[
        "aat:300008798"
    ]
},
  "bbox": [],
  "geometry": {"coordinates":[-122.2,47.7667],"type":"Point"}
}
=======
{"geometry":{"type":"Point","coordinates":[-122.200000,47.766700]},"type":"Feature","properties":{"hierarchy":["tgn:2158964","tgn:1000001","tgn:7012149","tgn:7007920","tgn:7029392"],"placetype":["aat:300008798"],"id":2158964,"name:xx":"Beckstrom Hill"}}
>>>>>>> 03f74aca74312dbeaf24d7e61306dd6a786dc3d0
