{
  "id": 7143762,
  "type": "Feature",
  "properties": {
    "tgn:hierarchy":[
        "tgn:7143762",
        "tgn:1000003",
        "tgn:7003687",
        "tgn:7000084",
        "tgn:7029392"
    ],
    "tgn:id":7143762,
    "tgn:name":"Kl\u00f6den",
    "tgn:placetype":[
        "aat:300008347"
    ]
},
  "bbox": [],
  "geometry": {"coordinates":[12.833333,51.766667],"type":"Point"}
}