{
  "id": 2289975,
  "type": "Feature",
  "properties": {
    "tgn:hierarchy":[
        "tgn:2289975",
        "tgn:1000001",
        "tgn:7012149",
        "tgn:2001152",
        "tgn:7007522",
        "tgn:7029392"
    ],
    "tgn:id":2289975,
    "tgn:name":"Dockery",
    "tgn:placetype":[
        "aat:300008347"
    ]
},
  "bbox": [],
  "geometry": {"coordinates":[-90.6167,33.7167],"type":"Point"}
}