{
  "id": 2701683,
  "type": "Feature",
  "properties": {
    "tgn:hierarchy":[
        "tgn:2701683",
        "tgn:1000001",
        "tgn:7012149",
        "tgn:7007157",
        "tgn:1002566",
        "tgn:7029392"
    ],
    "tgn:id":2701683,
    "tgn:name":"Sugarloaf",
    "tgn:placetype":[
        "aat:300008798"
    ]
},
  "bbox": [],
  "geometry": {"coordinates":[-122.65,38.75],"type":"Point"}
}