{
  "id": 7146649,
  "type": "Feature",
  "properties": {
    "tgn:hierarchy":[
        "tgn:7146649",
        "tgn:1000003",
        "tgn:7003677",
        "tgn:7000084",
        "tgn:7029392"
    ],
    "tgn:id":7146649,
    "tgn:name":"Kohlsberg",
    "tgn:placetype":[
        "aat:300000206"
    ]
},
  "bbox": [],
  "geometry": {"coordinates":[7.033333,51.133333],"type":"Point"}
}