{
  "id": 2597201,
  "type": "Feature",
  "properties": {
    "tgn:hierarchy":[
        "tgn:2597201",
        "tgn:1000001",
        "tgn:7016172",
        "tgn:7012149",
        "tgn:2000131",
        "tgn:7029392"
    ],
    "tgn:id":2597201,
    "tgn:name":"Prague",
    "tgn:placetype":[
        "aat:300008347"
    ]
},
  "bbox": [],
  "geometry": {"coordinates":[-92.2667,34.2833],"type":"Point"}
}