{
  "id": 2564380,
  "type": "Feature",
  "properties": {
    "tgn:hierarchy":[
        "tgn:2564380",
        "tgn:1000001",
        "tgn:7012149",
        "tgn:7007157",
        "tgn:1002608",
        "tgn:7029392"
    ],
    "tgn:id":2564380,
    "tgn:name":"Pacific Crest Reservoir",
    "tgn:placetype":[
        "aat:300006191"
    ]
},
  "bbox": [],
  "geometry": {"coordinates":[-117.6833,34.35],"type":"Point"}
}