{
  "id": 2188293,
  "type": "Feature",
  "properties": {
    "tgn:hierarchy":[
        "tgn:2188293",
        "tgn:7002659",
        "tgn:1000001",
        "tgn:2000019",
        "tgn:7012149",
        "tgn:7029392"
    ],
    "tgn:id":2188293,
    "tgn:name":"Boston",
    "tgn:placetype":[
        "aat:300008347"
    ]
},
  "bbox": [],
  "geometry": {"coordinates":[-86.4667,31.4667],"type":"Point"}
}