{
  "id": 2321722,
  "type": "Feature",
  "properties": {
    "tgn:hierarchy":[
        "tgn:2321722",
        "tgn:1000001",
        "tgn:7012149",
        "tgn:2000550",
        "tgn:7007252",
        "tgn:7029392"
    ],
    "tgn:id":2321722,
    "tgn:name":"Fairview Ridge",
    "tgn:placetype":[
        "aat:300266640"
    ]
},
  "bbox": [],
  "geometry": {"coordinates":[-86.5667,38.1833],"type":"Point"}
}