{
  "id": 7546085,
  "type": "Feature",
  "properties": {
    "tgn:hierarchy":[
        "tgn:7546085",
        "tgn:1001828",
        "tgn:1000004",
        "tgn:7000198",
        "tgn:7029392"
    ],
    "tgn:id":7546085,
    "tgn:name:en":"Baireddipalle",
    "tgn:placetype":[
        "aat:300008347"
    ]
},
  "bbox": [],
  "geometry": {"coordinates":[78.616667,13.083333],"type":"Point"}
}