{
  "id": 1018836,
  "type": "Feature",
  "properties": {
    "tgn:hierarchy":[
        "tgn:1018836",
        "tgn:1001208",
        "tgn:1000001",
        "tgn:7005565",
        "tgn:7029392"
    ],
    "tgn:id":1018836,
    "tgn:name":"Escobal",
    "tgn:placetype":[
        "aat:300008347"
    ]
},
  "bbox": [],
  "geometry": {"coordinates":[-79.9833,9.1833],"type":"Point"}
}