{
  "id": 2169705,
  "type": "Feature",
  "properties": {
    "tgn:hierarchy":[
        "tgn:2169705",
        "tgn:1000001",
        "tgn:7012149",
        "tgn:2000410",
        "tgn:7007248",
        "tgn:7029392"
    ],
    "tgn:id":2169705,
    "tgn:name":"Big Mountain",
    "tgn:placetype":[
        "aat:300266640"
    ]
},
  "bbox": [],
  "geometry": {"coordinates":[-83.1333,34.9333],"type":"Point"}
}