{
  "id": 2494456,
  "type": "Feature",
  "properties": {
    "tgn:hierarchy":[
        "tgn:2494456",
        "tgn:1000001",
        "tgn:2002321",
        "tgn:7012149",
        "tgn:7007922",
        "tgn:7029392"
    ],
    "tgn:id":2494456,
    "tgn:name":"Martin Creek",
    "tgn:placetype":[
        "aat:300008706"
    ]
},
  "bbox": [],
  "geometry": {"coordinates":[-88.6667,45.7667],"type":"Point"}
}