{
  "id": 7242456,
  "type": "Feature",
  "properties": {
    "tgn:hierarchy":[
        "tgn:7242456",
        "tgn:7003461",
        "tgn:1000003",
        "tgn:1000063",
        "tgn:7018236",
        "tgn:7029392"
    ],
    "tgn:id":7242456,
    "tgn:name":"Koleneind",
    "tgn:placetype":[
        "aat:300008347"
    ]
},
  "bbox": [],
  "geometry": {"coordinates":[5.533333,51.25],"type":"Point"}
}