{
  "id": 7048991,
  "type": "Feature",
  "properties": {
    "tgn:hierarchy":[
        "tgn:7048991",
        "tgn:1003447",
        "tgn:7007850",
        "tgn:1000003",
        "tgn:1000080",
        "tgn:7029392"
    ],
    "tgn:id":7048991,
    "tgn:name":"Chiriaco",
    "tgn:placetype":[
        "aat:300008347"
    ]
},
  "bbox": [],
  "geometry": {"coordinates":[16.35,38.883333],"type":"Point"}
}