{
  "id": 2608415,
  "type": "Feature",
  "properties": {
    "tgn:hierarchy":[
        "tgn:2608415",
        "tgn:1000001",
        "tgn:7012149",
        "tgn:1002742",
        "tgn:7007920",
        "tgn:7029392"
    ],
    "tgn:id":2608415,
    "tgn:name":"Rattlesnake Draw",
    "tgn:placetype":[
        "aat:300008761"
    ]
},
  "bbox": [],
  "geometry": {"coordinates":[-119.6667,48.8333],"type":"Point"}
}