{
  "id": 7319650,
  "type": "Feature",
  "properties": {
    "tgn:hierarchy":[
        "tgn:7319650",
        "tgn:1001708",
        "tgn:1000049",
        "tgn:1000002",
        "tgn:7029392"
    ],
    "tgn:id":7319650,
    "tgn:name":"Agua del Laurel",
    "tgn:placetype":[
        "aat:300008699"
    ]
},
  "bbox": [],
  "geometry": {"coordinates":[-70.233333,-33.516667],"type":"Point"}
}