{
  "id": 2518732,
  "type": "Feature",
  "properties": {
    "tgn:hierarchy":[
        "tgn:2518732",
        "tgn:1000001",
        "tgn:7006451",
        "tgn:2000095",
        "tgn:7012149",
        "tgn:7029392"
    ],
    "tgn:id":2518732,
    "tgn:name":"Mitchell Peak",
    "tgn:placetype":[
        "aat:300008798"
    ]
},
  "bbox": [],
  "geometry": {"coordinates":[-109.3667,33.2167],"type":"Point"}
}