{
  "id": 2344446,
  "type": "Feature",
  "properties": {
    "tgn:hierarchy":[
        "tgn:2344446",
        "tgn:1000001",
        "tgn:7012149",
        "tgn:2002190",
        "tgn:7007919",
        "tgn:7029392"
    ],
    "tgn:id":2344446,
    "tgn:name":"Gap Creek",
    "tgn:placetype":[
        "aat:300008706"
    ]
},
  "bbox": [],
  "geometry": {"coordinates":[-78.5667,38.7333],"type":"Point"}
}