{
  "id": 7419133,
  "type": "Feature",
  "properties": {
    "tgn:hierarchy":[
        "tgn:7419133",
        "tgn:1000001",
        "tgn:7005589",
        "tgn:7005560",
        "tgn:7029392"
    ],
    "tgn:id":7419133,
    "tgn:name:es":"La Puerta",
    "tgn:placetype":[
        "aat:300008347"
    ]
},
  "bbox": [],
  "geometry": {"coordinates":[-100.046667,27.5625],"type":"Point"}
}