{
  "id": 2736720,
  "type": "Feature",
  "properties": {
    "tgn:hierarchy":[
        "tgn:2736720",
        "tgn:1000001",
        "tgn:7012149",
        "tgn:2000982",
        "tgn:7007520",
        "tgn:7029392"
    ],
    "tgn:id":2736720,
    "tgn:name":"Twin Tomahawk Lakes",
    "tgn:placetype":[
        "aat:300008680"
    ]
},
  "bbox": [],
  "geometry": {"coordinates":[-84.1333,45.1667],"type":"Point"}
}