{
  "id": 2169577,
  "type": "Feature",
  "properties": {
    "tgn:hierarchy":[
        "tgn:2169577",
        "tgn:1000001",
        "tgn:2002107",
        "tgn:7012149",
        "tgn:7007827",
        "tgn:7029392"
    ],
    "tgn:id":2169577,
    "tgn:name":"Big Meadow",
    "tgn:placetype":[
        "aat:300055621"
    ]
},
  "bbox": [],
  "geometry": {"coordinates":[-110.6667,40.6333],"type":"Point"}
}