{
  "id": 2653545,
  "type": "Feature",
  "properties": {
    "tgn:hierarchy":[
        "tgn:2653545",
        "tgn:1000001",
        "tgn:2000457",
        "tgn:7012149",
        "tgn:7007250",
        "tgn:7029392"
    ],
    "tgn:id":2653545,
    "tgn:name":"Seventy Creek",
    "tgn:placetype":[
        "aat:300008706"
    ]
},
  "bbox": [],
  "geometry": {"coordinates":[-111.8167,43.1833],"type":"Point"}
}