{
  "id": 2436216,
  "type": "Feature",
  "properties": {
    "tgn:hierarchy":[
        "tgn:2436216",
        "tgn:1000001",
        "tgn:2001637",
        "tgn:7012149",
        "tgn:7007707",
        "tgn:7029392"
    ],
    "tgn:id":2436216,
    "tgn:name":"Keystone Mine",
    "tgn:placetype":[
        "aat:300000390"
    ]
},
  "bbox": [],
  "geometry": {"coordinates":[-96.25,34.5167],"type":"Point"}
}