{
  "id": 7546332,
  "type": "Feature",
  "properties": {
    "tgn:hierarchy":[
        "tgn:7546332",
        "tgn:1000004",
        "tgn:7000198",
        "tgn:7016883",
        "tgn:7029392"
    ],
    "tgn:id":7546332,
    "tgn:name:en":"Abohar Branch",
    "tgn:placetype":[
        "aat:300006075"
    ]
},
  "bbox": [],
  "geometry": {"coordinates":[75.254066,30.675891],"type":"Point"}
}