{
  "id": 2686364,
  "type": "Feature",
  "properties": {
    "tgn:hierarchy":[
        "tgn:2686364",
        "tgn:1000001",
        "tgn:2000698",
        "tgn:7012149",
        "tgn:7007254",
        "tgn:7029392"
    ],
    "tgn:id":2686364,
    "tgn:name":"Spring Creek",
    "tgn:placetype":[
        "aat:300008706"
    ]
},
  "bbox": [],
  "geometry": {"coordinates":[-97.9833,37.3833],"type":"Point"}
}