{
  "id": 2285220,
  "type": "Feature",
  "properties": {
    "tgn:hierarchy":[
        "tgn:2285220",
        "tgn:1000001",
        "tgn:7012149",
        "tgn:7007157",
        "tgn:2000191",
        "tgn:7029392"
    ],
    "tgn:id":2285220,
    "tgn:name":"Devils Canyon",
    "tgn:placetype":[
        "aat:300008761"
    ]
},
  "bbox": [],
  "geometry": {"coordinates":[-122.9833,40.9833],"type":"Point"}
}