{
  "id": 7588437,
  "type": "Feature",
  "properties": {
    "tgn:hierarchy":[
        "tgn:7588437",
        "tgn:1000004",
        "tgn:7000198",
        "tgn:1001977",
        "tgn:7029392"
    ],
    "tgn:id":7588437,
    "tgn:name:en":"\u0100mb\u0101ria",
    "tgn:placetype":[
        "aat:300008347"
    ]
},
  "bbox": [],
  "geometry": {"coordinates":[88.968056,22.418889],"type":"Point"}
}