{
  "id": 2516006,
  "type": "Feature",
  "properties": {
    "tgn:hierarchy":[
        "tgn:2516006",
        "tgn:2001002",
        "tgn:1000001",
        "tgn:7012149",
        "tgn:7007521",
        "tgn:7029392"
    ],
    "tgn:id":2516006,
    "tgn:name":"Mina Lake",
    "tgn:placetype":[
        "aat:300008680"
    ]
},
  "bbox": [],
  "geometry": {"coordinates":[-95.05,47.7667],"type":"Point"}
}