{
  "id": 7065235,
  "type": "Feature",
  "properties": {
    "tgn:hierarchy":[
        "tgn:7065235",
        "tgn:1000003",
        "tgn:7003677",
        "tgn:7000084",
        "tgn:7029392"
    ],
    "tgn:id":7065235,
    "tgn:name":"Bahnhof Steinhelle",
    "tgn:placetype":[
        "aat:300007783"
    ]
},
  "bbox": [],
  "geometry": {"coordinates":[8.483333,51.333333],"type":"Point"}
}