{
  "id": 2226269,
  "type": "Feature",
  "properties": {
    "tgn:hierarchy":[
        "tgn:2226269",
        "tgn:1000001",
        "tgn:7012149",
        "tgn:7007157",
        "tgn:1002684",
        "tgn:7029392"
    ],
    "tgn:id":2226269,
    "tgn:name":"Catfish Lake",
    "tgn:placetype":[
        "aat:300008680"
    ]
},
  "bbox": [],
  "geometry": {"coordinates":[-120.4333,35.95],"type":"Point"}
}