{
  "id": 7469419,
  "type": "Feature",
  "properties": {
    "tgn:hierarchy":[
        "tgn:7469419",
        "tgn:7001004",
        "tgn:1000004",
        "tgn:1000141",
        "tgn:7029392"
    ],
    "tgn:id":7469419,
    "tgn:name":"Xiaoshan",
    "tgn:placetype":[
        "aat:300008347"
    ]
},
  "bbox": [],
  "geometry": {"coordinates":[120.558601,22.874473],"type":"Point"}
}