{
  "id": 7410533,
  "type": "Feature",
  "properties": {
    "tgn:hierarchy":[
        "tgn:7410533",
        "tgn:1000001",
        "tgn:7005592",
        "tgn:7005560",
        "tgn:7029392"
    ],
    "tgn:id":7410533,
    "tgn:name":"Las Pilas",
    "tgn:placetype":[
        "aat:300008347"
    ]
},
  "bbox": [],
  "geometry": {"coordinates":[-97.948611,20.330556],"type":"Point"}
}