{
  "id": 7426129,
  "type": "Feature",
  "properties": {
    "tgn:hierarchy":[
        "tgn:7426129",
        "tgn:1000001",
        "tgn:7005594",
        "tgn:7005560",
        "tgn:7029392"
    ],
    "tgn:id":7426129,
    "tgn:name":"El Sauz, R\u00edo",
    "tgn:placetype":[
        "aat:300008699"
    ]
},
  "bbox": [],
  "geometry": {"coordinates":[-100.15,22.516667],"type":"Point"}
}