{
  "id": 7539508,
  "type": "Feature",
  "properties": {
    "tgn:hierarchy":[
        "tgn:7539508",
        "tgn:7001242",
        "tgn:7001105",
        "tgn:7016833",
        "tgn:7029392"
    ],
    "tgn:id":7539508,
    "tgn:name:en":"Gann\u00e2b\u00eeyet el-Maqr\u00e2nt",
    "tgn:placetype":[
        "aat:300006075"
    ]
},
  "bbox": [],
  "geometry": {"coordinates":[30.633333,29.266667],"type":"Point"}
}