<<<<<<< HEAD
{
  "id": 2703925,
  "type": "Feature",
  "properties": {
    "tgn:hierarchy":[
        "tgn:2703925",
        "tgn:1000001",
        "tgn:7012149",
        "tgn:1002742",
        "tgn:7007920",
        "tgn:7029392"
    ],
    "tgn:id":2703925,
    "tgn:name":"Sunday Creek",
    "tgn:placetype":[
        "aat:300008706"
    ]
},
  "bbox": [],
  "geometry": {"coordinates":[-119.85,48.9167],"type":"Point"}
}
=======
{"geometry":{"type":"Point","coordinates":[-119.850000,48.916700]},"type":"Feature","properties":{"hierarchy":["tgn:2703925","tgn:1000001","tgn:7012149","tgn:1002742","tgn:7007920","tgn:7029392"],"placetype":["aat:300008706"],"id":2703925,"name:xx":"Sunday Creek"}}
>>>>>>> 03f74aca74312dbeaf24d7e61306dd6a786dc3d0
