{
  "id": 7162879,
  "type": "Feature",
  "properties": {
    "tgn:hierarchy":[
        "tgn:7162879",
        "tgn:7003669",
        "tgn:1000003",
        "tgn:7000084",
        "tgn:7029392"
    ],
    "tgn:id":7162879,
    "tgn:name":"In der Elmau",
    "tgn:placetype":[
        "aat:300008761"
    ]
},
  "bbox": [],
  "geometry": {"coordinates":[10.983333,47.516667],"type":"Point"}
}