{
  "id": 7114165,
  "type": "Feature",
  "properties": {
    "tgn:hierarchy":[
        "tgn:7114165",
        "tgn:1000003",
        "tgn:7003682",
        "tgn:7000084",
        "tgn:7029392"
    ],
    "tgn:id":7114165,
    "tgn:name":"Riedhof",
    "tgn:placetype":[
        "aat:300000206"
    ]
},
  "bbox": [],
  "geometry": {"coordinates":[8.483333,49.416667],"type":"Point"}
}