{
  "id": 7024502,
  "type": "Feature",
  "properties": {
    "tgn:hierarchy":[
        "tgn:7024502",
        "tgn:7593552",
        "tgn:1000001",
        "tgn:7024573",
        "tgn:7029392"
    ],
    "tgn:id":7024502,
    "tgn:name":"Peary Gletscher",
    "tgn:placetype":[
        "aat:300008835"
    ]
},
  "bbox": [],
  "geometry": {"coordinates":[-60.4667,76.1167],"type":"Point"}
}