{
  "id": 7291219,
  "type": "Feature",
  "properties": {
    "tgn:hierarchy":[
        "tgn:7291219",
        "tgn:1001702",
        "tgn:1000049",
        "tgn:1000002",
        "tgn:7029392"
    ],
    "tgn:id":7291219,
    "tgn:name":"Escarpado, Morro",
    "tgn:placetype":[
        "aat:300387499"
    ]
},
  "bbox": [],
  "geometry": {"coordinates":[-74.25,-49.55],"type":"Point"}
}