{
  "id": 7031592,
  "type": "Feature",
  "properties": {
    "tgn:hierarchy":[
        "tgn:7031592",
        "tgn:7005332",
        "tgn:7593502",
        "tgn:1000001",
        "tgn:7029392"
    ],
    "tgn:id":7031592,
    "tgn:name":"Cooper's Town",
    "tgn:placetype":[
        "aat:300008347"
    ]
},
  "bbox": [],
  "geometry": {"coordinates":[-77.525,26.866],"type":"Point"}
}