{
  "id": 7103018,
  "type": "Feature",
  "properties": {
    "tgn:hierarchy":[
        "tgn:7103018",
        "tgn:7003669",
        "tgn:1000003",
        "tgn:7000084",
        "tgn:7029392"
    ],
    "tgn:id":7103018,
    "tgn:name":"Sachsenhausen",
    "tgn:placetype":[
        "aat:300008347"
    ]
},
  "bbox": [],
  "geometry": {"coordinates":[11.466667,47.933333],"type":"Point"}
}