{
  "id": 2487046,
  "type": "Feature",
  "properties": {
    "tgn:hierarchy":[
        "tgn:2487046",
        "tgn:1000001",
        "tgn:2001429",
        "tgn:7012149",
        "tgn:7007566",
        "tgn:7029392"
    ],
    "tgn:id":2487046,
    "tgn:name":"Lee Russell Spring",
    "tgn:placetype":[
        "aat:300008697"
    ]
},
  "bbox": [],
  "geometry": {"coordinates":[-108.6667,33.9167],"type":"Point"}
}