{
  "id": 2133936,
  "type": "Feature",
  "properties": {
    "tgn:hierarchy":[
        "tgn:2133936",
        "tgn:2000496",
        "tgn:1000001",
        "tgn:7012149",
        "tgn:7007251",
        "tgn:7029392"
    ],
    "tgn:id":2133936,
    "tgn:name":"Angelo Towhead",
    "tgn:placetype":[
        "aat:300008791"
    ]
},
  "bbox": [],
  "geometry": {"coordinates":[-89.1667,36.9667],"type":"Point"}
}