{
  "id": 7456840,
  "type": "Feature",
  "properties": {
    "tgn:hierarchy":[
        "tgn:7456840",
        "tgn:7002445",
        "tgn:1000003",
        "tgn:7008185",
        "tgn:7008591",
        "tgn:7029392"
    ],
    "tgn:id":7456840,
    "tgn:name:en":"Playford",
    "tgn:placetype":[
        "aat:300008347"
    ]
},
  "bbox": [],
  "geometry": {"coordinates":[1.233333,52.083333],"type":"Point"}
}