{
  "id": 2517335,
  "type": "Feature",
  "properties": {
    "tgn:hierarchy":[
        "tgn:2517335",
        "tgn:1000001",
        "tgn:7012149",
        "tgn:1002897",
        "tgn:7007920",
        "tgn:7029392"
    ],
    "tgn:id":2517335,
    "tgn:name":"Minnie Lee Mine",
    "tgn:placetype":[
        "aat:300000390"
    ]
},
  "bbox": [],
  "geometry": {"coordinates":[-122.1333,46.3667],"type":"Point"}
}