{
  "id": 2655799,
  "type": "Feature",
  "properties": {
    "tgn:hierarchy":[
        "tgn:2655799",
        "tgn:1000001",
        "tgn:7012149",
        "tgn:1002494",
        "tgn:7007710",
        "tgn:7029392"
    ],
    "tgn:id":2655799,
    "tgn:name":"Shaver Creek",
    "tgn:placetype":[
        "aat:300008706"
    ]
},
  "bbox": [],
  "geometry": {"coordinates":[-77.85,40.7167],"type":"Point"}
}