{
  "id": 2480754,
  "type": "Feature",
  "properties": {
    "tgn:hierarchy":[
        "tgn:2480754",
        "tgn:7006450",
        "tgn:1000001",
        "tgn:7019698",
        "tgn:7012149",
        "tgn:7029392"
    ],
    "tgn:id":2480754,
    "tgn:name":"Lakeview",
    "tgn:placetype":[
        "aat:300008347"
    ]
},
  "bbox": [],
  "geometry": {"coordinates":[-149.35,60.35],"type":"Point"}
}