{
  "id": 2686907,
  "type": "Feature",
  "properties": {
    "tgn:hierarchy":[
        "tgn:2686907",
        "tgn:1000001",
        "tgn:7012149",
        "tgn:7013961",
        "tgn:7029392"
    ],
    "tgn:id":2686907,
    "tgn:name":"Spring Gap Mountain",
    "tgn:placetype":[
        "aat:300008798"
    ]
},
  "bbox": [],
  "geometry": {"coordinates":[-78.4667,39.45],"type":"Point"}
}