{
  "id": 2313905,
  "type": "Feature",
  "properties": {
    "tgn:hierarchy":[
        "tgn:2313905",
        "tgn:1000001",
        "tgn:7012149",
        "tgn:2001713",
        "tgn:7007708",
        "tgn:7029392"
    ],
    "tgn:id":2313905,
    "tgn:name":"Elijah, Mount",
    "tgn:placetype":[
        "aat:300008798"
    ]
},
  "bbox": [],
  "geometry": {"coordinates":[-123.3667,42.0833],"type":"Point"}
}