{
  "id": 7372881,
  "type": "Feature",
  "properties": {
    "tgn:hierarchy":[
        "tgn:7372881",
        "tgn:1000001",
        "tgn:7005599",
        "tgn:7005560",
        "tgn:7029392"
    ],
    "tgn:id":7372881,
    "tgn:name":"La Flor",
    "tgn:placetype":[
        "aat:300008347"
    ]
},
  "bbox": [],
  "geometry": {"coordinates":[-95.316667,18.083333],"type":"Point"}
}