{
  "id": 2572966,
  "type": "Feature",
  "properties": {
    "tgn:hierarchy":[
        "tgn:2572966",
        "tgn:1000001",
        "tgn:2000460",
        "tgn:7012149",
        "tgn:7007250",
        "tgn:7029392"
    ],
    "tgn:id":2572966,
    "tgn:name":"Pearl Island",
    "tgn:placetype":[
        "aat:300008791"
    ]
},
  "bbox": [],
  "geometry": {"coordinates":[-116.3167,48.2167],"type":"Point"}
}