{
  "id": 7330223,
  "type": "Feature",
  "properties": {
    "tgn:hierarchy":[
        "tgn:7330223",
        "tgn:7002827",
        "tgn:1000003",
        "tgn:7002789",
        "tgn:1000095",
        "tgn:7029392"
    ],
    "tgn:id":7330223,
    "tgn:name":"Hormilla",
    "tgn:placetype":[
        "aat:300008347"
    ]
},
  "bbox": [],
  "geometry": {"coordinates":[-2.77447,42.438281],"type":"Point"}
}