{
  "id": 2333524,
  "type": "Feature",
  "properties": {
    "tgn:hierarchy":[
        "tgn:2333524",
        "tgn:2002131",
        "tgn:1000001",
        "tgn:7012149",
        "tgn:7007828",
        "tgn:7029392"
    ],
    "tgn:id":2333524,
    "tgn:name":"Folsom",
    "tgn:placetype":[
        "aat:300008347"
    ]
},
  "bbox": [],
  "geometry": {"coordinates":[-71.9667,44.5833],"type":"Point"}
}