<<<<<<< HEAD
{
  "id": 2333524,
  "type": "Feature",
  "properties": {
    "tgn:hierarchy":[
        "tgn:2333524",
        "tgn:2002131",
        "tgn:1000001",
        "tgn:7012149",
        "tgn:7007828",
        "tgn:7029392"
    ],
    "tgn:id":2333524,
    "tgn:name":"Folsom",
    "tgn:placetype":[
        "aat:300008347"
    ]
},
  "bbox": [],
  "geometry": {"coordinates":[-71.9667,44.5833],"type":"Point"}
}
=======
{"geometry":{"type":"Point","coordinates":[-71.966700,44.583300]},"type":"Feature","properties":{"hierarchy":["tgn:2333524","tgn:2002131","tgn:1000001","tgn:7012149","tgn:7007828","tgn:7029392"],"placetype":["aat:300008347"],"id":2333524,"name:xx":"Folsom"}}
>>>>>>> 03f74aca74312dbeaf24d7e61306dd6a786dc3d0
