{
  "id": 7374092,
  "type": "Feature",
  "properties": {
    "tgn:hierarchy":[
        "tgn:7374092",
        "tgn:1000001",
        "tgn:7005599",
        "tgn:7005560",
        "tgn:7029392"
    ],
    "tgn:id":7374092,
    "tgn:name":"La Concepci\u00f3n",
    "tgn:placetype":[
        "aat:300008347"
    ]
},
  "bbox": [],
  "geometry": {"coordinates":[-94.616667,17.816667],"type":"Point"}
}