{
  "id": 1086608,
  "type": "Feature",
  "properties": {
    "tgn:hierarchy":[
        "tgn:1086608",
        "tgn:1001471",
        "tgn:1000004",
        "tgn:7018454",
        "tgn:1000144",
        "tgn:7029392"
    ],
    "tgn:id":1086608,
    "tgn:name":"Korgan",
    "tgn:placetype":[
        "aat:300008347"
    ]
},
  "bbox": [],
  "geometry": {"coordinates":[37.2167,40.7333],"type":"Point"}
}