{
  "id": 2064798,
  "type": "Feature",
  "properties": {
    "tgn:hierarchy":[
        "tgn:2064798",
        "tgn:1000001",
        "tgn:1002410",
        "tgn:7012149",
        "tgn:7007565",
        "tgn:7029392"
    ],
    "tgn:id":2064798,
    "tgn:name":"Gardenville",
    "tgn:placetype":[
        "aat:300008347"
    ]
},
  "bbox": [],
  "geometry": {"coordinates":[-75.1167,39.8167],"type":"Point"}
}