{
  "id": 7044197,
  "type": "Feature",
  "properties": {
    "tgn:hierarchy":[
        "tgn:7044197",
        "tgn:7009084",
        "tgn:7004154",
        "tgn:1000003",
        "tgn:1000080",
        "tgn:7029392"
    ],
    "tgn:id":7044197,
    "tgn:name":"Frattura",
    "tgn:placetype":[
        "aat:300008347"
    ]
},
  "bbox": [],
  "geometry": {"coordinates":[13.866667,41.933333],"type":"Point"}
}