{
  "id": 2776592,
  "type": "Feature",
  "properties": {
    "tgn:hierarchy":[
        "tgn:2776592",
        "tgn:1000001",
        "tgn:7012149",
        "tgn:1002898",
        "tgn:7007826",
        "tgn:7029392"
    ],
    "tgn:id":2776592,
    "tgn:name":"Winding Branch",
    "tgn:placetype":[
        "aat:300008699"
    ]
},
  "bbox": [],
  "geometry": {"coordinates":[-95.4833,32.5667],"type":"Point"}
}