<<<<<<< HEAD
{
  "id": 2252695,
  "type": "Feature",
  "properties": {
    "tgn:hierarchy":[
        "tgn:2252695",
        "tgn:2001423",
        "tgn:1000001",
        "tgn:7012149",
        "tgn:7007564",
        "tgn:7029392"
    ],
    "tgn:id":2252695,
    "tgn:name":"Conner Pond",
    "tgn:placetype":[
        "aat:300008680"
    ]
},
  "bbox": [],
  "geometry": {"coordinates":[-71.2333,43.7667],"type":"Point"}
}
=======
{"geometry":{"type":"Point","coordinates":[-71.233300,43.766700]},"type":"Feature","properties":{"hierarchy":["tgn:2252695","tgn:2001423","tgn:1000001","tgn:7012149","tgn:7007564","tgn:7029392"],"placetype":["aat:300008680"],"id":2252695,"name:xx":"Conner Pond"}}
>>>>>>> 03f74aca74312dbeaf24d7e61306dd6a786dc3d0
