<<<<<<< HEAD
{
  "id": 2254032,
  "type": "Feature",
  "properties": {
    "tgn:hierarchy":[
        "tgn:2254032",
        "tgn:1000001",
        "tgn:7012149",
        "tgn:1002911",
        "tgn:7007919",
        "tgn:7029392"
    ],
    "tgn:id":2254032,
    "tgn:name":"Cool Spring Island",
    "tgn:placetype":[
        "aat:300008791"
    ]
},
  "bbox": [],
  "geometry": {"coordinates":[-76.9167,36.6667],"type":"Point"}
}
=======
{"geometry":{"type":"Point","coordinates":[-76.916700,36.666700]},"type":"Feature","properties":{"hierarchy":["tgn:2254032","tgn:1000001","tgn:7012149","tgn:1002911","tgn:7007919","tgn:7029392"],"placetype":["aat:300008791"],"id":2254032,"name:xx":"Cool Spring Island"}}
>>>>>>> 03f74aca74312dbeaf24d7e61306dd6a786dc3d0
