{
  "id": 7158639,
  "type": "Feature",
  "properties": {
    "tgn:hierarchy":[
        "tgn:7158639",
        "tgn:1000003",
        "tgn:7003687",
        "tgn:7000084",
        "tgn:7029392"
    ],
    "tgn:id":7158639,
    "tgn:name":"H\u00f6llenklippe",
    "tgn:placetype":[
        "aat:300008749"
    ]
},
  "bbox": [],
  "geometry": {"coordinates":[10.683333,51.783333],"type":"Point"}
}