{
  "id": 2287522,
  "type": "Feature",
  "properties": {
    "tgn:hierarchy":[
        "tgn:2287522",
        "tgn:1000001",
        "tgn:7012149",
        "tgn:7007157",
        "tgn:1002867",
        "tgn:7029392"
    ],
    "tgn:id":2287522,
    "tgn:name":"Difficult Spring",
    "tgn:placetype":[
        "aat:300008697"
    ]
},
  "bbox": [],
  "geometry": {"coordinates":[-120.1333,34.8833],"type":"Point"}
}