{
  "id": 6005888,
  "type": "Feature",
  "properties": {
    "tgn:hierarchy":[
        "tgn:6005888",
        "tgn:1000001",
        "tgn:1001893",
        "tgn:7005560",
        "tgn:7029392"
    ],
    "tgn:id":6005888,
    "tgn:name":"Tepexpan",
    "tgn:placetype":[
        "aat:300008347",
        "aat:300008372",
        "aat:300387006"
    ]
},
  "bbox": [],
  "geometry": {"coordinates":[-99.704167,19.568056],"type":"Point"}
}