{
  "id": 1129824,
  "type": "Feature",
  "properties": {
    "tgn:hierarchy":[
        "tgn:1129824",
        "tgn:7003005",
        "tgn:1000003",
        "tgn:1000080",
        "tgn:7029392"
    ],
    "tgn:id":1129824,
    "tgn:name":"Sele",
    "tgn:placetype":[
        "aat:300008707",
        "aat:300008699"
    ]
},
  "bbox": [],
  "geometry": {"coordinates":[14.933333,40.483333],"type":"Point"}
}