{
  "id": 7194579,
  "type": "Feature",
  "properties": {
    "tgn:hierarchy":[
        "tgn:7194579",
        "tgn:7003669",
        "tgn:1000003",
        "tgn:7000084",
        "tgn:7029392"
    ],
    "tgn:id":7194579,
    "tgn:name":"Denkenreuth",
    "tgn:placetype":[
        "aat:300008347"
    ]
},
  "bbox": [],
  "geometry": {"coordinates":[12.166667,49.766667],"type":"Point"}
}