{
  "id": 2107871,
  "type": "Feature",
  "properties": {
    "tgn:hierarchy":[
        "tgn:2107871",
        "tgn:1000001",
        "tgn:7012149",
        "tgn:1002535",
        "tgn:7007826",
        "tgn:7029392"
    ],
    "tgn:id":2107871,
    "tgn:name":"Styx",
    "tgn:placetype":[
        "aat:300008347",
        "aat:300387210"
    ]
},
  "bbox": [],
  "geometry": {"coordinates":[-96.3167,32.35],"type":"Point"}
}