{
  "id": 7084486,
  "type": "Feature",
  "properties": {
    "tgn:hierarchy":[
        "tgn:7084486",
        "tgn:1000003",
        "tgn:7003688",
        "tgn:7000084",
        "tgn:7029392"
    ],
    "tgn:id":7084486,
    "tgn:name":"Wildhagen",
    "tgn:placetype":[
        "aat:300000206"
    ]
},
  "bbox": [],
  "geometry": {"coordinates":[10.116667,54.083333],"type":"Point"}
}