{
  "id": 7211439,
  "type": "Feature",
  "properties": {
    "tgn:hierarchy":[
        "tgn:7211439",
        "tgn:7003692",
        "tgn:1000003",
        "tgn:7000084",
        "tgn:7029392"
    ],
    "tgn:id":7211439,
    "tgn:name":"Baindter Wald",
    "tgn:placetype":[
        "aat:300008863"
    ]
},
  "bbox": [],
  "geometry": {"coordinates":[9.683333,47.866667],"type":"Point"}
}