{
  "id": 7430777,
  "type": "Feature",
  "properties": {
    "tgn:hierarchy":[
        "tgn:7430777",
        "tgn:7005583",
        "tgn:1000001",
        "tgn:7005560",
        "tgn:7029392"
    ],
    "tgn:id":7430777,
    "tgn:name":"La Vega",
    "tgn:placetype":[
        "aat:300008347"
    ]
},
  "bbox": [],
  "geometry": {"coordinates":[-106.816667,25.216667],"type":"Point"}
}