<<<<<<< HEAD
{
  "id": 7028221,
  "type": "Feature",
  "properties": {
    "tgn:hierarchy":[
        "tgn:7028221",
        "tgn:7002445",
        "tgn:1000003",
        "tgn:7008157",
        "tgn:7008591",
        "tgn:7029392"
    ],
    "tgn:id":7028221,
    "tgn:name":"Winceby",
    "tgn:placetype":[
        "aat:300008347",
        "aat:300008372"
    ]
},
  "bbox": [],
  "geometry": {"coordinates":[-0.016,53.185],"type":"Point"}
}
=======
{"geometry":{"type":"Point","coordinates":[-0.016000,53.185000]},"type":"Feature","properties":{"hierarchy":["tgn:7028221","tgn:7002445","tgn:1000003","tgn:7008157","tgn:7008591","tgn:7029392"],"placetype":["aat:300008347","aat:300008372"],"id":7028221,"name:xx":"Winceby"}}
>>>>>>> 03f74aca74312dbeaf24d7e61306dd6a786dc3d0
