{
  "id": 7028221,
  "type": "Feature",
  "properties": {
    "tgn:hierarchy":[
        "tgn:7028221",
        "tgn:7002445",
        "tgn:1000003",
        "tgn:7008157",
        "tgn:7008591",
        "tgn:7029392"
    ],
    "tgn:id":7028221,
    "tgn:name":"Winceby",
    "tgn:placetype":[
        "aat:300008347",
        "aat:300008372"
    ]
},
  "bbox": [],
  "geometry": {"coordinates":[-0.016,53.185],"type":"Point"}
}