{
  "id": 2504859,
  "type": "Feature",
  "properties": {
    "tgn:hierarchy":[
        "tgn:2504859",
        "tgn:1000001",
        "tgn:7012149",
        "tgn:2001457",
        "tgn:7007566",
        "tgn:7029392"
    ],
    "tgn:id":2504859,
    "tgn:name":"Medio, Rito del",
    "tgn:placetype":[
        "aat:300008699"
    ]
},
  "bbox": [],
  "geometry": {"coordinates":[-105.4833,36.7833],"type":"Point"}
}