{
  "id": 7421468,
  "type": "Feature",
  "properties": {
    "tgn:hierarchy":[
        "tgn:7421468",
        "tgn:1000001",
        "tgn:7005589",
        "tgn:7005560",
        "tgn:7029392"
    ],
    "tgn:id":7421468,
    "tgn:name:es":"Bordo Las Tunas",
    "tgn:placetype":[
        "aat:300006191"
    ]
},
  "bbox": [],
  "geometry": {"coordinates":[-99.46,25.172778],"type":"Point"}
}