<<<<<<< HEAD
{
  "id": 7176864,
  "type": "Feature",
  "properties": {
    "tgn:hierarchy":[
        "tgn:7176864",
        "tgn:1000003",
        "tgn:7003682",
        "tgn:7000084",
        "tgn:7029392"
    ],
    "tgn:id":7176864,
    "tgn:name":"Hardt",
    "tgn:placetype":[
        "aat:300000206"
    ]
},
  "bbox": [],
  "geometry": {"coordinates":[7.5,50.65],"type":"Point"}
}
=======
{"geometry":{"type":"Point","coordinates":[7.500000,50.650000]},"type":"Feature","properties":{"hierarchy":["tgn:7176864","tgn:1000003","tgn:7003682","tgn:7000084","tgn:7029392"],"placetype":["aat:300000206"],"id":7176864,"name:xx":"Hardt"}}
>>>>>>> 03f74aca74312dbeaf24d7e61306dd6a786dc3d0
