{
  "id": 2219205,
  "type": "Feature",
  "properties": {
    "tgn:hierarchy":[
        "tgn:2219205",
        "tgn:1000001",
        "tgn:7016172",
        "tgn:7012149",
        "tgn:2000146",
        "tgn:7029392"
    ],
    "tgn:id":2219205,
    "tgn:name":"Caney Lake",
    "tgn:placetype":[
        "aat:300006191"
    ]
},
  "bbox": [],
  "geometry": {"coordinates":[-93.8833,35.2333],"type":"Point"}
}