{
  "id": 2007239,
  "type": "Feature",
  "properties": {
    "tgn:hierarchy":[
        "tgn:2007239",
        "tgn:2000090",
        "tgn:1000001",
        "tgn:7006451",
        "tgn:7012149",
        "tgn:7029392"
    ],
    "tgn:id":2007239,
    "tgn:name":"Red Mesa",
    "tgn:placetype":[
        "aat:300008347"
    ]
},
  "bbox": [],
  "geometry": {"coordinates":[-109.3667,36.9833],"type":"Point"}
}