{
  "id": 2616800,
  "type": "Feature",
  "properties": {
    "tgn:hierarchy":[
        "tgn:2616800",
        "tgn:1000001",
        "tgn:7012149",
        "tgn:2000479",
        "tgn:7007250",
        "tgn:7029392"
    ],
    "tgn:id":2616800,
    "tgn:name":"Rich Hill",
    "tgn:placetype":[
        "aat:300008798"
    ]
},
  "bbox": [],
  "geometry": {"coordinates":[-116.8833,47.6167],"type":"Point"}
}