{
  "id": 7008680,
  "type": "Feature",
  "properties": {
    "tgn:hierarchy":[
        "tgn:7008680",
        "tgn:7002822",
        "tgn:1001647",
        "tgn:1000003",
        "tgn:1000095",
        "tgn:7029392"
    ],
    "tgn:id":7008680,
    "tgn:name":"Sig\u00fcenza",
    "tgn:placetype":[
        "aat:300008347"
    ]
},
  "bbox": [],
  "geometry": {"coordinates":[-2.633333,41.066667],"type":"Point"}
}