{
  "id": 7349971,
  "type": "Feature",
  "properties": {
    "tgn:hierarchy":[
        "tgn:7349971",
        "tgn:7005587",
        "tgn:1000001",
        "tgn:7005560",
        "tgn:7029392"
    ],
    "tgn:id":7349971,
    "tgn:name":"Acuapa",
    "tgn:placetype":[
        "aat:300008347"
    ]
},
  "bbox": [],
  "geometry": {"coordinates":[-98.266667,20.933333],"type":"Point"}
}