{
  "id": 2594668,
  "type": "Feature",
  "properties": {
    "tgn:hierarchy":[
        "tgn:2594668",
        "tgn:7002659",
        "tgn:1000001",
        "tgn:2000019",
        "tgn:7012149",
        "tgn:7029392"
    ],
    "tgn:id":2594668,
    "tgn:name":"Posey Pond",
    "tgn:placetype":[
        "aat:300006191"
    ]
},
  "bbox": [],
  "geometry": {"coordinates":[-86.5833,31.35],"type":"Point"}
}