{
  "id": 7365960,
  "type": "Feature",
  "properties": {
    "tgn:hierarchy":[
        "tgn:7365960",
        "tgn:7005581",
        "tgn:1000001",
        "tgn:7005560",
        "tgn:7029392"
    ],
    "tgn:id":7365960,
    "tgn:name":"El Refugio",
    "tgn:placetype":[
        "aat:300008347"
    ]
},
  "bbox": [],
  "geometry": {"coordinates":[-107.283333,28.833333],"type":"Point"}
}