{
  "id": 7496555,
  "type": "Feature",
  "properties": {
    "tgn:hierarchy":[
        "tgn:7496555",
        "tgn:7487020",
        "tgn:1000004",
        "tgn:1000141",
        "tgn:7029392"
    ],
    "tgn:id":7496555,
    "tgn:name":"Zhangyanwo",
    "tgn:placetype":[
        "aat:300008347"
    ]
},
  "bbox": [],
  "geometry": {"coordinates":[120.866963,24.372908],"type":"Point"}
}