{
  "id": 7040053,
  "type": "Feature",
  "properties": {
    "tgn:hierarchy":[
        "tgn:7040053",
        "tgn:1003429",
        "tgn:1000003",
        "tgn:7003240",
        "tgn:1000080",
        "tgn:7029392"
    ],
    "tgn:id":7040053,
    "tgn:name":"Schiavi, Grotta degli",
    "tgn:placetype":[
        "aat:300008746"
    ]
},
  "bbox": [],
  "geometry": {"coordinates":[13.616667,43.55],"type":"Point"}
}