<<<<<<< HEAD
{
  "id": 7245269,
  "type": "Feature",
  "properties": {
    "tgn:hierarchy":[
        "tgn:7245269",
        "tgn:7007877",
        "tgn:1000003",
        "tgn:1000063",
        "tgn:4012014",
        "tgn:7029392"
    ],
    "tgn:id":7245269,
    "tgn:name":"Bas Pr\u00e9au",
    "tgn:placetype":[
        "aat:300008347"
    ]
},
  "bbox": [],
  "geometry": {"coordinates":[3.303141,50.523734],"type":"Point"}
}
=======
{"geometry":{"type":"Point","coordinates":[3.303141,50.523734]},"type":"Feature","properties":{"hierarchy":["tgn:7245269","tgn:7007877","tgn:1000003","tgn:1000063","tgn:4012014","tgn:7029392"],"placetype":["aat:300008347"],"id":7245269,"name:xx":"Bas Pr\u00e9au"}}
>>>>>>> 03f74aca74312dbeaf24d7e61306dd6a786dc3d0
