<<<<<<< HEAD
{
  "id": 7172480,
  "type": "Feature",
  "properties": {
    "tgn:hierarchy":[
        "tgn:7172480",
        "tgn:1000003",
        "tgn:7003676",
        "tgn:7000084",
        "tgn:7029392"
    ],
    "tgn:id":7172480,
    "tgn:name":"Hibben",
    "tgn:placetype":[
        "aat:300008347"
    ]
},
  "bbox": [],
  "geometry": {"coordinates":[9.033333,52.5],"type":"Point"}
}
=======
{"geometry":{"type":"Point","coordinates":[9.033333,52.500000]},"type":"Feature","properties":{"hierarchy":["tgn:7172480","tgn:1000003","tgn:7003676","tgn:7000084","tgn:7029392"],"placetype":["aat:300008347"],"id":7172480,"name:xx":"Hibben"}}
>>>>>>> 03f74aca74312dbeaf24d7e61306dd6a786dc3d0
