{
  "id": 7330631,
  "type": "Feature",
  "properties": {
    "tgn:hierarchy":[
        "tgn:7330631",
        "tgn:7002811",
        "tgn:1000003",
        "tgn:7003837",
        "tgn:1000095",
        "tgn:7029392"
    ],
    "tgn:id":7330631,
    "tgn:name":"Guijo de Santa B\u00e1rbara",
    "tgn:placetype":[
        "aat:300008347"
    ]
},
  "bbox": [],
  "geometry": {"coordinates":[-5.65,40.15],"type":"Point"}
}