<<<<<<< HEAD
{
  "id": 7472675,
  "type": "Feature",
  "properties": {
    "tgn:hierarchy":[
        "tgn:7472675",
        "tgn:1000004",
        "tgn:1000959",
        "tgn:1000141",
        "tgn:7029392"
    ],
    "tgn:id":7472675,
    "tgn:name":"Jiugan Gong",
    "tgn:placetype":[
        "aat:300007595"
    ]
},
  "bbox": [],
  "geometry": {"coordinates":[121.575224,24.973831],"type":"Point"}
}
=======
{"geometry":{"type":"Point","coordinates":[121.575224,24.973831]},"type":"Feature","properties":{"hierarchy":["tgn:7472675","tgn:1000004","tgn:1000959","tgn:1000141","tgn:7029392"],"placetype":["aat:300007595"],"id":7472675,"name:xx":"Jiugan Gong"}}
>>>>>>> 03f74aca74312dbeaf24d7e61306dd6a786dc3d0
