<<<<<<< HEAD
{
  "id": 2403721,
  "type": "Feature",
  "properties": {
    "tgn:hierarchy":[
        "tgn:2403721",
        "tgn:1000001",
        "tgn:7012149",
        "tgn:2001461",
        "tgn:7007568",
        "tgn:7029392"
    ],
    "tgn:id":2403721,
    "tgn:name":"Howard Mountain",
    "tgn:placetype":[
        "aat:300008798"
    ]
},
  "bbox": [],
  "geometry": {"coordinates":[-73.6167,44.05],"type":"Point"}
}
=======
{"geometry":{"type":"Point","coordinates":[-73.616700,44.050000]},"type":"Feature","properties":{"hierarchy":["tgn:2403721","tgn:1000001","tgn:7012149","tgn:2001461","tgn:7007568","tgn:7029392"],"placetype":["aat:300008798"],"id":2403721,"name:xx":"Howard Mountain"}}
>>>>>>> 03f74aca74312dbeaf24d7e61306dd6a786dc3d0
