{
  "id": 7428527,
  "type": "Feature",
  "properties": {
    "tgn:hierarchy":[
        "tgn:7428527",
        "tgn:1000001",
        "tgn:7005594",
        "tgn:7005560",
        "tgn:7029392"
    ],
    "tgn:id":7428527,
    "tgn:name":"El Charco",
    "tgn:placetype":[
        "aat:300008347"
    ]
},
  "bbox": [],
  "geometry": {"coordinates":[-100.333333,22.033333],"type":"Point"}
}