{
  "id": 1091693,
  "type": "Feature",
  "properties": {
    "tgn:hierarchy":[
        "tgn:1091693",
        "tgn:7001242",
        "tgn:1000906",
        "tgn:1000180",
        "tgn:7029392"
    ],
    "tgn:id":1091693,
    "tgn:name":"Unango",
    "tgn:placetype":[
        "aat:300008347"
    ]
},
  "bbox": [],
  "geometry": {"coordinates":[35.3833,-12.85],"type":"Point"}
}