<<<<<<< HEAD
{
  "id": 7482090,
  "type": "Feature",
  "properties": {
    "tgn:hierarchy":[
        "tgn:7482090",
        "tgn:1000004",
        "tgn:7490934",
        "tgn:1000141",
        "tgn:7029392"
    ],
    "tgn:id":7482090,
    "tgn:name":"Cilian Si",
    "tgn:placetype":[
        "aat:300007595"
    ]
},
  "bbox": [],
  "geometry": {"coordinates":[120.268904,23.137694],"type":"Point"}
}
=======
{"geometry":{"type":"Point","coordinates":[120.268904,23.137694]},"type":"Feature","properties":{"hierarchy":["tgn:7482090","tgn:1000004","tgn:7490934","tgn:1000141","tgn:7029392"],"placetype":["aat:300007595"],"id":7482090,"name:xx":"Cilian Si"}}
>>>>>>> 03f74aca74312dbeaf24d7e61306dd6a786dc3d0
