{
  "id": 2167666,
  "type": "Feature",
  "properties": {
    "tgn:hierarchy":[
        "tgn:2167666",
        "tgn:1000001",
        "tgn:7012149",
        "tgn:2001898",
        "tgn:7007825",
        "tgn:7029392"
    ],
    "tgn:id":2167666,
    "tgn:name":"Big Creek Knobs",
    "tgn:placetype":[
        "aat:300266640"
    ]
},
  "bbox": [],
  "geometry": {"coordinates":[-84.3167,35.4333],"type":"Point"}
}