{
  "id": 2755317,
  "type": "Feature",
  "properties": {
    "tgn:hierarchy":[
        "tgn:2755317",
        "tgn:1000001",
        "tgn:2002147",
        "tgn:7012149",
        "tgn:7007919",
        "tgn:7029392"
    ],
    "tgn:id":2755317,
    "tgn:name":"Webbs Mill",
    "tgn:placetype":[
        "aat:300008347"
    ]
},
  "bbox": [],
  "geometry": {"coordinates":[-77.6833,36.7333],"type":"Point"}
}