{
  "id": 7033829,
  "type": "Feature",
  "properties": {
    "tgn:hierarchy":[
        "tgn:7033829",
        "tgn:1000003",
        "tgn:7003236",
        "tgn:1000080",
        "tgn:7029392"
    ],
    "tgn:id":7033829,
    "tgn:name":"Cervara, Punta della",
    "tgn:placetype":[
        "aat:300386846"
    ]
},
  "bbox": [],
  "geometry": {"coordinates":[9.216667,44.316667],"type":"Point"}
}