{
  "id": 2358312,
  "type": "Feature",
  "properties": {
    "tgn:hierarchy":[
        "tgn:2358312",
        "tgn:1000001",
        "tgn:7012149",
        "tgn:7007157",
        "tgn:1002841",
        "tgn:7029392"
    ],
    "tgn:id":2358312,
    "tgn:name":"Grand Island",
    "tgn:placetype":[
        "aat:300008791"
    ]
},
  "bbox": [],
  "geometry": {"coordinates":[-121.5667,38.2333],"type":"Point"}
}