<<<<<<< HEAD
{
  "id": 7481239,
  "type": "Feature",
  "properties": {
    "tgn:hierarchy":[
        "tgn:7481239",
        "tgn:1000004",
        "tgn:7004300",
        "tgn:1000141",
        "tgn:7029392"
    ],
    "tgn:id":7481239,
    "tgn:name":"Qimei Shuiku",
    "tgn:placetype":[
        "aat:300006191"
    ]
},
  "bbox": [],
  "geometry": {"coordinates":[119.435278,23.2125],"type":"Point"}
}
=======
{"geometry":{"type":"Point","coordinates":[119.435278,23.212500]},"type":"Feature","properties":{"hierarchy":["tgn:7481239","tgn:1000004","tgn:7004300","tgn:1000141","tgn:7029392"],"placetype":["aat:300006191"],"id":7481239,"name:xx":"Qimei Shuiku"}}
>>>>>>> 03f74aca74312dbeaf24d7e61306dd6a786dc3d0
