{
  "id": 2446136,
  "type": "Feature",
  "properties": {
    "tgn:hierarchy":[
        "tgn:2446136",
        "tgn:1000001",
        "tgn:7012149",
        "tgn:1002819",
        "tgn:7007523",
        "tgn:7029392"
    ],
    "tgn:id":2446136,
    "tgn:name":"Levick Mill",
    "tgn:placetype":[
        "aat:300008347"
    ]
},
  "bbox": [],
  "geometry": {"coordinates":[-92.3333,39.5667],"type":"Point"}
}