{
  "id": 2725179,
  "type": "Feature",
  "properties": {
    "tgn:hierarchy":[
        "tgn:2725179",
        "tgn:1000001",
        "tgn:7012149",
        "tgn:7007158",
        "tgn:2000245",
        "tgn:7029392"
    ],
    "tgn:id":2725179,
    "tgn:name":"Tonier Gulch Reservoir",
    "tgn:placetype":[
        "aat:300006191"
    ]
},
  "bbox": [],
  "geometry": {"coordinates":[-106.7333,40.0833],"type":"Point"}
}