{
  "id": 1102599,
  "type": "Feature",
  "properties": {
    "tgn:hierarchy":[
        "tgn:1102599",
        "tgn:7005735",
        "tgn:7005685",
        "tgn:1000001",
        "tgn:7029392"
    ],
    "tgn:id":1102599,
    "tgn:name":"Mount Seymour Provincial Park",
    "tgn:placetype":[
        "aat:300008195"
    ]
},
  "bbox": [],
  "geometry": {"coordinates":[-122.95,49.3833],"type":"Point"}
}