{
  "id": 2486324,
  "type": "Feature",
  "properties": {
    "tgn:hierarchy":[
        "tgn:2486324",
        "tgn:1000001",
        "tgn:7012149",
        "tgn:2000927",
        "tgn:7007515",
        "tgn:7029392"
    ],
    "tgn:id":2486324,
    "tgn:name":"Leathers Corner",
    "tgn:placetype":[
        "aat:300008347"
    ]
},
  "bbox": [],
  "geometry": {"coordinates":[-68.9167,44.8167],"type":"Point"}
}