{
  "id": 7224140,
  "type": "Feature",
  "properties": {
    "tgn:hierarchy":[
        "tgn:7224140",
        "tgn:7002718",
        "tgn:7002715",
        "tgn:1000003",
        "tgn:1000074",
        "tgn:7029392"
    ],
    "tgn:id":7224140,
    "tgn:name":"Oin\u00f3\u00ef",
    "tgn:placetype":[
        "aat:300008347"
    ]
},
  "bbox": [],
  "geometry": {"coordinates":[21.916667,40.316667],"type":"Point"}
}