{
  "id": 7550600,
  "type": "Feature",
  "properties": {
    "tgn:hierarchy":[
        "tgn:7550600",
        "tgn:1000004",
        "tgn:7000198",
        "tgn:7016883",
        "tgn:7029392"
    ],
    "tgn:id":7550600,
    "tgn:name:en":"Dalew\u0101la",
    "tgn:placetype":[
        "aat:300008347"
    ]
},
  "bbox": [],
  "geometry": {"coordinates":[75.414964,29.829451],"type":"Point"}
}