{
  "id": 2752838,
  "type": "Feature",
  "properties": {
    "tgn:hierarchy":[
        "tgn:2752838",
        "tgn:1000001",
        "tgn:7012149",
        "tgn:2001713",
        "tgn:7007708",
        "tgn:7029392"
    ],
    "tgn:id":2752838,
    "tgn:name":"Water Branch",
    "tgn:placetype":[
        "aat:300008699"
    ]
},
  "bbox": [],
  "geometry": {"coordinates":[-123.2667,42.5667],"type":"Point"}
}