{
  "id": 7307177,
  "type": "Feature",
  "properties": {
    "tgn:hierarchy":[
        "tgn:7307177",
        "tgn:7002811",
        "tgn:1000003",
        "tgn:7003837",
        "tgn:1000095",
        "tgn:7029392"
    ],
    "tgn:id":7307177,
    "tgn:name":"Madrigal de la Vera",
    "tgn:placetype":[
        "aat:300008347"
    ]
},
  "bbox": [],
  "geometry": {"coordinates":[-5.366667,40.15],"type":"Point"}
}