{
  "id": 7135986,
  "type": "Feature",
  "properties": {
    "tgn:hierarchy":[
        "tgn:7135986",
        "tgn:1000003",
        "tgn:7003688",
        "tgn:7000084",
        "tgn:7029392"
    ],
    "tgn:id":7135986,
    "tgn:name":"Morsum Odde",
    "tgn:placetype":[
        "aat:300008850"
    ]
},
  "bbox": [],
  "geometry": {"coordinates":[8.416667,54.85],"type":"Point"}
}