{
  "id": 2352494,
  "type": "Feature",
  "properties": {
    "tgn:hierarchy":[
        "tgn:2352494",
        "tgn:1000001",
        "tgn:7012149",
        "tgn:7014510",
        "tgn:7007920",
        "tgn:7029392"
    ],
    "tgn:id":2352494,
    "tgn:name":"Goat Island",
    "tgn:placetype":[
        "aat:300008791"
    ]
},
  "bbox": [],
  "geometry": {"coordinates":[-122.5167,48.35],"type":"Point"}
}