{
  "id": 7501600,
  "type": "Feature",
  "properties": {
    "tgn:hierarchy":[
        "tgn:7501600",
        "tgn:1000004",
        "tgn:7490934",
        "tgn:1000141",
        "tgn:7029392"
    ],
    "tgn:id":7501600,
    "tgn:name":"Xincuo",
    "tgn:placetype":[
        "aat:300008347"
    ]
},
  "bbox": [],
  "geometry": {"coordinates":[120.2625,22.977222],"type":"Point"}
}