{
  "id": 7197078,
  "type": "Feature",
  "properties": {
    "tgn:hierarchy":[
        "tgn:7197078",
        "tgn:1000003",
        "tgn:7003688",
        "tgn:7000084",
        "tgn:7029392"
    ],
    "tgn:id":7197078,
    "tgn:name":"Darry",
    "tgn:placetype":[
        "aat:300008347"
    ]
},
  "bbox": [],
  "geometry": {"coordinates":[10.583333,54.316667],"type":"Point"}
}