{
  "id": 7267324,
  "type": "Feature",
  "properties": {
    "tgn:hierarchy":[
        "tgn:7267324",
        "tgn:1000003",
        "tgn:7003613",
        "tgn:7016845",
        "tgn:7029392"
    ],
    "tgn:id":7267324,
    "tgn:name:nl":"Nieuwe Ruigezandsterpolder",
    "tgn:placetype":[
        "aat:300006163"
    ]
},
  "bbox": [],
  "geometry": {"coordinates":[6.283333,53.316667],"type":"Point"}
}