{
  "id": 2498682,
  "type": "Feature",
  "properties": {
    "tgn:hierarchy":[
        "tgn:2498682",
        "tgn:1000001",
        "tgn:7012149",
        "tgn:1002877",
        "tgn:7007706",
        "tgn:7029392"
    ],
    "tgn:id":2498682,
    "tgn:name":"McBride Lake",
    "tgn:placetype":[
        "aat:300006191"
    ]
},
  "bbox": [],
  "geometry": {"coordinates":[-83.1667,38.65],"type":"Point"}
}