{
  "id": 2679863,
  "type": "Feature",
  "properties": {
    "tgn:hierarchy":[
        "tgn:2679863",
        "tgn:1000001",
        "tgn:7012149",
        "tgn:7007158",
        "tgn:2000246",
        "tgn:7029392"
    ],
    "tgn:id":2679863,
    "tgn:name":"South Fork Saguache Creek",
    "tgn:placetype":[
        "aat:300008706"
    ]
},
  "bbox": [],
  "geometry": {"coordinates":[-106.75,37.8833],"type":"Point"}
}