{
  "id": 7317443,
  "type": "Feature",
  "properties": {
    "tgn:hierarchy":[
        "tgn:7317443",
        "tgn:1001657",
        "tgn:1000049",
        "tgn:1000002",
        "tgn:7029392"
    ],
    "tgn:id":7317443,
    "tgn:name":"Comunidad La Higuera",
    "tgn:placetype":[
        "aat:300008347"
    ]
},
  "bbox": [],
  "geometry": {"coordinates":[-71.216667,-29.45],"type":"Point"}
}