{
  "id": 2400081,
  "type": "Feature",
  "properties": {
    "tgn:hierarchy":[
        "tgn:2400081",
        "tgn:1000001",
        "tgn:1002902",
        "tgn:7012149",
        "tgn:7007516",
        "tgn:7029392"
    ],
    "tgn:id":2400081,
    "tgn:name":"Horse Creek",
    "tgn:placetype":[
        "aat:300008706"
    ]
},
  "bbox": [],
  "geometry": {"coordinates":[-75.7833,37.9833],"type":"Point"}
}