<<<<<<< HEAD
{
  "id": 7020359,
  "type": "Feature",
  "properties": {
    "tgn:hierarchy":[
        "tgn:7020359",
        "tgn:1000001",
        "tgn:2001260",
        "tgn:7012149",
        "tgn:7007524",
        "tgn:7029392"
    ],
    "tgn:id":7020359,
    "tgn:name":"Moose Horn Mine",
    "tgn:placetype":[
        "aat:300000390"
    ]
},
  "bbox": [],
  "geometry": {"coordinates":[-113.7167,45.55],"type":"Point"}
}
=======
{"geometry":{"type":"Point","coordinates":[-113.716700,45.550000]},"type":"Feature","properties":{"hierarchy":["tgn:7020359","tgn:1000001","tgn:2001260","tgn:7012149","tgn:7007524","tgn:7029392"],"placetype":["aat:300000390"],"id":7020359,"name:xx":"Moose Horn Mine"}}
>>>>>>> 03f74aca74312dbeaf24d7e61306dd6a786dc3d0
