{
  "id": 2331491,
  "type": "Feature",
  "properties": {
    "tgn:hierarchy":[
        "tgn:2331491",
        "tgn:1000001",
        "tgn:7012149",
        "tgn:7007919",
        "tgn:7029392"
    ],
    "tgn:id":2331491,
    "tgn:name":"Flattop Mountain",
    "tgn:placetype":[
        "aat:300008798"
    ]
},
  "bbox": [],
  "geometry": {"coordinates":[-81.75,36.9333],"type":"Point"}
}