{
  "id": 7223429,
  "type": "Feature",
  "properties": {
    "tgn:hierarchy":[
        "tgn:7223429",
        "tgn:4003773",
        "tgn:7001395",
        "tgn:1000003",
        "tgn:1000074",
        "tgn:7029392"
    ],
    "tgn:id":7223429,
    "tgn:name":"Oxi\u00e1 \u00d3ros",
    "tgn:placetype":[
        "aat:300008795"
    ]
},
  "bbox": [],
  "geometry": {"coordinates":[21.95,38.783333],"type":"Point"}
}