<<<<<<< HEAD
{
  "id": 7481198,
  "type": "Feature",
  "properties": {
    "tgn:hierarchy":[
        "tgn:7481198",
        "tgn:1000004",
        "tgn:7471332",
        "tgn:1000141",
        "tgn:7029392"
    ],
    "tgn:id":7481198,
    "tgn:name":"Pitouwo",
    "tgn:placetype":[
        "aat:300008347"
    ]
},
  "bbox": [],
  "geometry": {"coordinates":[121.146389,24.841944],"type":"Point"}
}
=======
{"geometry":{"type":"Point","coordinates":[121.146389,24.841944]},"type":"Feature","properties":{"hierarchy":["tgn:7481198","tgn:1000004","tgn:7471332","tgn:1000141","tgn:7029392"],"placetype":["aat:300008347"],"id":7481198,"name:xx":"Pitouwo"}}
>>>>>>> 03f74aca74312dbeaf24d7e61306dd6a786dc3d0
