{
  "id": 7029051,
  "type": "Feature",
  "properties": {
    "tgn:hierarchy":[
        "tgn:7029051",
        "tgn:7016849",
        "tgn:1000004",
        "tgn:1000119",
        "tgn:7029392"
    ],
    "tgn:id":7029051,
    "tgn:name:en":"Jelazoun",
    "tgn:placetype":[
        "aat:300008347",
        "aat:300120676",
        "aat:300008375"
    ]
},
  "bbox": [],
  "geometry": {"coordinates":[35.216,31.95],"type":"Point"}
}