<<<<<<< HEAD
{
  "id": 7029051,
  "type": "Feature",
  "properties": {
    "tgn:hierarchy":[
        "tgn:7029051",
        "tgn:7016849",
        "tgn:1000004",
        "tgn:1000119",
        "tgn:7029392"
    ],
    "tgn:id":7029051,
    "tgn:name:en":"Jelazoun",
    "tgn:placetype":[
        "aat:300008347",
        "aat:300120676",
        "aat:300008375"
    ]
},
  "bbox": [],
  "geometry": {"coordinates":[35.216,31.95],"type":"Point"}
}
=======
{"geometry":{"type":"Point","coordinates":[35.216000,31.950000]},"type":"Feature","properties":{"hierarchy":["tgn:7029051","tgn:7016849","tgn:1000004","tgn:1000119","tgn:7029392"],"placetype":["aat:300008347","aat:300120676","aat:300008375"],"name:en":"Jelazoun","id":7029051}}
>>>>>>> 03f74aca74312dbeaf24d7e61306dd6a786dc3d0
