{
  "id": 7587131,
  "type": "Feature",
  "properties": {
    "tgn:hierarchy":[
        "tgn:7587131",
        "tgn:1000004",
        "tgn:7000198",
        "tgn:7000799",
        "tgn:7029392"
    ],
    "tgn:id":7587131,
    "tgn:name:en":"Saidapor Hamchi",
    "tgn:placetype":[
        "aat:300008347"
    ]
},
  "bbox": [],
  "geometry": {"coordinates":[74.841158,34.173427],"type":"Point"}
}