{
  "id": 7382267,
  "type": "Feature",
  "properties": {
    "tgn:hierarchy":[
        "tgn:7382267",
        "tgn:1000001",
        "tgn:1001960",
        "tgn:7005560",
        "tgn:7029392"
    ],
    "tgn:id":7382267,
    "tgn:name":"Monumento, Punta",
    "tgn:placetype":[
        "aat:300386846"
    ]
},
  "bbox": [],
  "geometry": {"coordinates":[-112.35,28.75],"type":"Point"}
}