{
  "id": 7592462,
  "type": "Feature",
  "properties": {
    "tgn:hierarchy":[
        "tgn:7592462",
        "tgn:1000004",
        "tgn:7000198",
        "tgn:7000799",
        "tgn:7029392"
    ],
    "tgn:id":7592462,
    "tgn:name:en":"Bhajnoa",
    "tgn:placetype":[
        "aat:300008347"
    ]
},
  "bbox": [],
  "geometry": {"coordinates":[74.202524,33.132285],"type":"Point"}
}