{
  "id": 7364107,
  "type": "Feature",
  "properties": {
    "tgn:hierarchy":[
        "tgn:7364107",
        "tgn:1001853",
        "tgn:1000001",
        "tgn:7005560",
        "tgn:7029392"
    ],
    "tgn:id":7364107,
    "tgn:name":"El Chupadero",
    "tgn:placetype":[
        "aat:300008347"
    ]
},
  "bbox": [],
  "geometry": {"coordinates":[-100.85,28.25],"type":"Point"}
}