{
  "id": 2488282,
  "type": "Feature",
  "properties": {
    "tgn:hierarchy":[
        "tgn:2488282",
        "tgn:1000001",
        "tgn:2001411",
        "tgn:7012149",
        "tgn:7007526",
        "tgn:7029392"
    ],
    "tgn:id":2488282,
    "tgn:name":"Magpie Spring",
    "tgn:placetype":[
        "aat:300008697"
    ]
},
  "bbox": [],
  "geometry": {"coordinates":[-115.2667,40.8667],"type":"Point"}
}