{
  "id": 2446665,
  "type": "Feature",
  "properties": {
    "tgn:hierarchy":[
        "tgn:2446665",
        "tgn:1000001",
        "tgn:7012149",
        "tgn:2001307",
        "tgn:7007524",
        "tgn:7029392"
    ],
    "tgn:id":2446665,
    "tgn:name":"Lewis-Hudson-Fowler Ditch",
    "tgn:placetype":[
        "aat:300006075"
    ]
},
  "bbox": [],
  "geometry": {"coordinates":[-109.6667,45.3833],"type":"Point"}
}