{
  "id": 1022745,
  "type": "Feature",
  "properties": {
    "tgn:hierarchy":[
        "tgn:1022745",
        "tgn:1001945",
        "tgn:1000047",
        "tgn:7002457",
        "tgn:1000002",
        "tgn:7029392"
    ],
    "tgn:id":1022745,
    "tgn:name":"Rudge Ramos",
    "tgn:placetype":[
        "aat:300008347"
    ]
},
  "bbox": [],
  "geometry": {"coordinates":[-46.5667,-23.6833],"type":"Point"}
}