{
  "id": 2079566,
  "type": "Feature",
  "properties": {
    "tgn:hierarchy":[
        "tgn:2079566",
        "tgn:1000001",
        "tgn:7012149",
        "tgn:1002448",
        "tgn:7007706",
        "tgn:7029392"
    ],
    "tgn:id":2079566,
    "tgn:name":"Findlay",
    "tgn:placetype":[
        "aat:300008347"
    ]
},
  "bbox": [],
  "geometry": {"coordinates":[-83.65,41.0333],"type":"Point"}
}