<<<<<<< HEAD
{
  "id": 2400817,
  "type": "Feature",
  "properties": {
    "tgn:hierarchy":[
        "tgn:2400817",
        "tgn:1000001",
        "tgn:7012149",
        "tgn:2001861",
        "tgn:7007825",
        "tgn:7029392"
    ],
    "tgn:id":2400817,
    "tgn:name":"Horse Pound, The",
    "tgn:placetype":[
        "aat:300008798"
    ]
},
  "bbox": [],
  "geometry": {"coordinates":[-85.05,36.25],"type":"Point"}
}
=======
{"geometry":{"type":"Point","coordinates":[-85.050000,36.250000]},"type":"Feature","properties":{"hierarchy":["tgn:2400817","tgn:1000001","tgn:7012149","tgn:2001861","tgn:7007825","tgn:7029392"],"placetype":["aat:300008798"],"id":2400817,"name:xx":"Horse Pound, The"}}
>>>>>>> 03f74aca74312dbeaf24d7e61306dd6a786dc3d0
