{
  "id": 2229923,
  "type": "Feature",
  "properties": {
    "tgn:hierarchy":[
        "tgn:2229923",
        "tgn:1000001",
        "tgn:7012149",
        "tgn:1003042",
        "tgn:7007920",
        "tgn:7029392"
    ],
    "tgn:id":2229923,
    "tgn:name":"Cedar Valley",
    "tgn:placetype":[
        "aat:300386845"
    ]
},
  "bbox": [],
  "geometry": {"coordinates":[-121.1333,46.0833],"type":"Point"}
}