{
  "id": 1081660,
  "type": "Feature",
  "properties": {
    "tgn:hierarchy":[
        "tgn:1081660",
        "tgn:7016675",
        "tgn:1000004",
        "tgn:7000896",
        "tgn:1000120",
        "tgn:7029392"
    ],
    "tgn:id":1081660,
    "tgn:name":"Umaze",
    "tgn:placetype":[
        "aat:300008347"
    ]
},
  "bbox": [],
  "geometry": {"coordinates":[135.05,34.95],"type":"Point"}
}