{
  "id": 2237501,
  "type": "Feature",
  "properties": {
    "tgn:hierarchy":[
        "tgn:2237501",
        "tgn:1000001",
        "tgn:7012149",
        "tgn:7007157",
        "tgn:1002863",
        "tgn:7029392"
    ],
    "tgn:id":2237501,
    "tgn:name":"China Harbor",
    "tgn:placetype":[
        "aat:300132316"
    ]
},
  "bbox": [],
  "geometry": {"coordinates":[-120.9833,35.45],"type":"Point"}
}