{
  "id": 7580849,
  "type": "Feature",
  "properties": {
    "tgn:hierarchy":[
        "tgn:7580849",
        "tgn:1000004",
        "tgn:7000198",
        "tgn:1001894",
        "tgn:7029392"
    ],
    "tgn:id":7580849,
    "tgn:name:en":"Sumer",
    "tgn:placetype":[
        "aat:300007783"
    ]
},
  "bbox": [],
  "geometry": {"coordinates":[77.879953,23.625815],"type":"Point"}
}