{
  "id": 2375649,
  "type": "Feature",
  "properties": {
    "tgn:hierarchy":[
        "tgn:2375649",
        "tgn:1000001",
        "tgn:7006451",
        "tgn:7012149",
        "tgn:2000101",
        "tgn:7029392"
    ],
    "tgn:id":2375649,
    "tgn:name":"Happy Camp Canyon",
    "tgn:placetype":[
        "aat:300008761"
    ]
},
  "bbox": [],
  "geometry": {"coordinates":[-111.1167,33.3167],"type":"Point"}
}