{
  "id": 1127393,
  "type": "Feature",
  "properties": {
    "tgn:hierarchy":[
        "tgn:1127393",
        "tgn:7001242",
        "tgn:1001001",
        "tgn:1000158",
        "tgn:7029392"
    ],
    "tgn:id":1127393,
    "tgn:name":"Moudongouma",
    "tgn:placetype":[
        "aat:300008707"
    ]
},
  "bbox": [],
  "geometry": {"coordinates":[17.35,-1.6167],"type":"Point"}
}