{
  "id": 2710017,
  "type": "Feature",
  "properties": {
    "tgn:hierarchy":[
        "tgn:2710017",
        "tgn:1000001",
        "tgn:7012149",
        "tgn:7007516",
        "tgn:7029392"
    ],
    "tgn:id":2710017,
    "tgn:name":"Talbot Branch",
    "tgn:placetype":[
        "aat:300008699"
    ]
},
  "bbox": [],
  "geometry": {"coordinates":[-77.0833,39.45],"type":"Point"}
}