{
  "id": 1097601,
  "type": "Feature",
  "properties": {
    "tgn:hierarchy":[
        "tgn:1097601",
        "tgn:7000490",
        "tgn:1000006",
        "tgn:7001828",
        "tgn:7029392"
    ],
    "tgn:id":1097601,
    "tgn:name":"Moorebank",
    "tgn:placetype":[
        "aat:300008347"
    ]
},
  "bbox": [],
  "geometry": {"coordinates":[150.9333,-33.9333],"type":"Point"}
}