{
  "id": 2565531,
  "type": "Feature",
  "properties": {
    "tgn:hierarchy":[
        "tgn:2565531",
        "tgn:1000001",
        "tgn:7012149",
        "tgn:2001622",
        "tgn:7007706",
        "tgn:7029392"
    ],
    "tgn:id":2565531,
    "tgn:name":"Painter Run",
    "tgn:placetype":[
        "aat:300008699"
    ]
},
  "bbox": [],
  "geometry": {"coordinates":[-81.5833,39.4667],"type":"Point"}
}