{
  "id": 1092955,
  "type": "Feature",
  "properties": {
    "tgn:hierarchy":[
        "tgn:1092955",
        "tgn:7001242",
        "tgn:7017584",
        "tgn:1000193",
        "tgn:7029392"
    ],
    "tgn:id":1092955,
    "tgn:name":"Ceres",
    "tgn:placetype":[
        "aat:300008347"
    ]
},
  "bbox": [],
  "geometry": {"coordinates":[19.3167,-33.3833],"type":"Point"}
}