{
  "id": 1024258,
  "type": "Feature",
  "properties": {
    "tgn:hierarchy":[
        "tgn:1024258",
        "tgn:7002637",
        "tgn:1000578",
        "tgn:1000002",
        "tgn:1000055",
        "tgn:7029392"
    ],
    "tgn:id":1024258,
    "tgn:name":"Caraguatay",
    "tgn:placetype":[
        "aat:300008347"
    ]
},
  "bbox": [],
  "geometry": {"coordinates":[-56.8167,-25.2333],"type":"Point"}
}