{
  "id": 2667253,
  "type": "Feature",
  "properties": {
    "tgn:hierarchy":[
        "tgn:2667253",
        "tgn:1000001",
        "tgn:1002328",
        "tgn:7012149",
        "tgn:7007568",
        "tgn:7029392"
    ],
    "tgn:id":2667253,
    "tgn:name":"Skink Hollow",
    "tgn:placetype":[
        "aat:300008761"
    ]
},
  "bbox": [],
  "geometry": {"coordinates":[-74.85,42.1833],"type":"Point"}
}