{
  "id": 1053236,
  "type": "Feature",
  "properties": {
    "tgn:hierarchy":[
        "tgn:1053236",
        "tgn:1000004",
        "tgn:1003399",
        "tgn:7018214",
        "tgn:7002435",
        "tgn:7029392"
    ],
    "tgn:id":1053236,
    "tgn:name":"Tsarevshchina",
    "tgn:placetype":[
        "aat:300008347"
    ]
},
  "bbox": [],
  "geometry": {"coordinates":[44.75,53.6167],"type":"Point"}
}