{
  "id": 7373967,
  "type": "Feature",
  "properties": {
    "tgn:hierarchy":[
        "tgn:7373967",
        "tgn:7005586",
        "tgn:1000001",
        "tgn:7005560",
        "tgn:7029392"
    ],
    "tgn:id":7373967,
    "tgn:name":"La Madrastra",
    "tgn:placetype":[
        "aat:300000241"
    ]
},
  "bbox": [],
  "geometry": {"coordinates":[-102.266667,20.716667],"type":"Point"}
}