{
  "id": 2475467,
  "type": "Feature",
  "properties": {
    "tgn:hierarchy":[
        "tgn:2475467",
        "tgn:1000001",
        "tgn:7012149",
        "tgn:2001714",
        "tgn:7007708",
        "tgn:7029392"
    ],
    "tgn:id":2475467,
    "tgn:name":"Lucifer",
    "tgn:placetype":[
        "aat:300008798"
    ]
},
  "bbox": [],
  "geometry": {"coordinates":[-122.2167,42.6333],"type":"Point"}
}