{
  "id": 7273954,
  "type": "Feature",
  "properties": {
    "tgn:concordances":{
        "gn:id":"2744021"
    },
    "tgn:hierarchy":[
        "tgn:7273954",
        "tgn:7003614",
        "tgn:1000003",
        "tgn:7016845",
        "tgn:7029392"
    ],
    "tgn:id":7273954,
    "tgn:name:nl":"Zeegse",
    "tgn:placetype":[
        "aat:300008347"
    ]
},
  "bbox": [],
  "geometry": {"coordinates":[6.65,53.066667],"type":"Point"}
}