<<<<<<< HEAD
{
  "id": 7051914,
  "type": "Feature",
  "properties": {
    "tgn:hierarchy":[
        "tgn:7051914",
        "tgn:7003005",
        "tgn:7003014",
        "tgn:1000003",
        "tgn:1000080",
        "tgn:7029392"
    ],
    "tgn:id":7051914,
    "tgn:name":"Pertosa",
    "tgn:placetype":[
        "aat:300008347"
    ]
},
  "bbox": [],
  "geometry": {"coordinates":[15.433333,40.55],"type":"Point"}
}
=======
{"geometry":{"type":"Point","coordinates":[15.433333,40.550000]},"type":"Feature","properties":{"hierarchy":["tgn:7051914","tgn:7003005","tgn:7003014","tgn:1000003","tgn:1000080","tgn:7029392"],"placetype":["aat:300008347"],"id":7051914,"name:xx":"Pertosa"}}
>>>>>>> 03f74aca74312dbeaf24d7e61306dd6a786dc3d0
