{
  "id": 7396244,
  "type": "Feature",
  "properties": {
    "tgn:hierarchy":[
        "tgn:7396244",
        "tgn:1000001",
        "tgn:1001960",
        "tgn:7005560",
        "tgn:7029392"
    ],
    "tgn:id":7396244,
    "tgn:name":"San Antonio",
    "tgn:placetype":[
        "aat:300008347"
    ]
},
  "bbox": [],
  "geometry": {"coordinates":[-110.966667,29.716667],"type":"Point"}
}