{
  "id": 2388915,
  "type": "Feature",
  "properties": {
    "tgn:hierarchy":[
        "tgn:2388915",
        "tgn:1000001",
        "tgn:1002270",
        "tgn:7012149",
        "tgn:7007708",
        "tgn:7029392"
    ],
    "tgn:id":2388915,
    "tgn:name":"Hidden Lake",
    "tgn:placetype":[
        "aat:300008680"
    ]
},
  "bbox": [],
  "geometry": {"coordinates":[-121.7667,45.3167],"type":"Point"}
}