{
  "id": 2682951,
  "type": "Feature",
  "properties": {
    "tgn:hierarchy":[
        "tgn:2682951",
        "tgn:1000001",
        "tgn:7012149",
        "tgn:1003026",
        "tgn:7007826",
        "tgn:7029392"
    ],
    "tgn:id":2682951,
    "tgn:name":"Sowes Branch",
    "tgn:placetype":[
        "aat:300008699"
    ]
},
  "bbox": [],
  "geometry": {"coordinates":[-97.85,30.65],"type":"Point"}
}