{
  "id": 1104493,
  "type": "Feature",
  "properties": {
    "tgn:hierarchy":[
        "tgn:1104493",
        "tgn:7016674",
        "tgn:1000004",
        "tgn:1000120",
        "tgn:7029392"
    ],
    "tgn:id":1104493,
    "tgn:name":"Eboshi-yama",
    "tgn:placetype":[
        "aat:300008795"
    ]
},
  "bbox": [],
  "geometry": {"coordinates":[133.05,35.0667],"type":"Point"}
}