{
  "id": 2578099,
  "type": "Feature",
  "properties": {
    "tgn:hierarchy":[
        "tgn:2578099",
        "tgn:1000001",
        "tgn:7012149",
        "tgn:1002603",
        "tgn:7007520",
        "tgn:7029392"
    ],
    "tgn:id":2578099,
    "tgn:name":"Pettys Lake",
    "tgn:placetype":[
        "aat:300008680"
    ]
},
  "bbox": [],
  "geometry": {"coordinates":[-84.0333,42.7667],"type":"Point"}
}