{
  "id": 7202707,
  "type": "Feature",
  "properties": {
    "tgn:hierarchy":[
        "tgn:7202707",
        "tgn:1000003",
        "tgn:7003678",
        "tgn:7000084",
        "tgn:7029392"
    ],
    "tgn:id":7202707,
    "tgn:name":"Brodberg",
    "tgn:placetype":[
        "aat:300008777"
    ]
},
  "bbox": [],
  "geometry": {"coordinates":[9.933333,51.05],"type":"Point"}
}