{
  "id": 2156984,
  "type": "Feature",
  "properties": {
    "tgn:hierarchy":[
        "tgn:2156984",
        "tgn:1000001",
        "tgn:7012149",
        "tgn:2002384",
        "tgn:7007923",
        "tgn:7029392"
    ],
    "tgn:id":2156984,
    "tgn:name":"Beauty Park Creek",
    "tgn:placetype":[
        "aat:300008706"
    ]
},
  "bbox": [],
  "geometry": {"coordinates":[-110.1167,43.6833],"type":"Point"}
}