{
  "id": 2094875,
  "type": "Feature",
  "properties": {
    "tgn:hierarchy":[
        "tgn:2094875",
        "tgn:1002808",
        "tgn:1000001",
        "tgn:7012149",
        "tgn:7007711",
        "tgn:7029392"
    ],
    "tgn:id":2094875,
    "tgn:name":"Chopmist",
    "tgn:placetype":[
        "aat:300008347",
        "aat:300387210"
    ]
},
  "bbox": [],
  "geometry": {"coordinates":[-71.6667,41.8167],"type":"Point"}
}