{
  "id": 7331167,
  "type": "Feature",
  "properties": {
    "tgn:hierarchy":[
        "tgn:7331167",
        "tgn:7002834",
        "tgn:1000003",
        "tgn:7002786",
        "tgn:1000095",
        "tgn:7029392"
    ],
    "tgn:id":7331167,
    "tgn:name":"Guadarina, R\u00edo de",
    "tgn:placetype":[
        "aat:300008699"
    ]
},
  "bbox": [],
  "geometry": {"coordinates":[-8.716667,42.216667],"type":"Point"}
}