{
  "id": 1130436,
  "type": "Feature",
  "properties": {
    "tgn:hierarchy":[
        "tgn:1130436",
        "tgn:1000004",
        "tgn:7006655",
        "tgn:7029392"
    ],
    "tgn:id":1130436,
    "tgn:name":"Susamyr",
    "tgn:placetype":[
        "aat:300008707"
    ]
},
  "bbox": [],
  "geometry": {"coordinates":[73.9833,42.1333],"type":"Point"}
}