{
  "id": 7217496,
  "type": "Feature",
  "properties": {
    "tgn:hierarchy":[
        "tgn:7217496",
        "tgn:7002724",
        "tgn:7002715",
        "tgn:1000003",
        "tgn:1000074",
        "tgn:7029392"
    ],
    "tgn:id":7217496,
    "tgn:name":"Ts\u00e1koni",
    "tgn:placetype":[
        "aat:300008347"
    ]
},
  "bbox": [],
  "geometry": {"coordinates":[21.166667,40.483333],"type":"Point"}
}