{
  "id": 2706262,
  "type": "Feature",
  "properties": {
    "tgn:hierarchy":[
        "tgn:2706262",
        "tgn:1000001",
        "tgn:7012149",
        "tgn:2001304",
        "tgn:7007524",
        "tgn:7029392"
    ],
    "tgn:id":2706262,
    "tgn:name":"Swamp Creek Ditch",
    "tgn:placetype":[
        "aat:300006075"
    ]
},
  "bbox": [],
  "geometry": {"coordinates":[-115.6167,47.8833],"type":"Point"}
}