<<<<<<< HEAD
{
  "id": 2402340,
  "type": "Feature",
  "properties": {
    "tgn:hierarchy":[
        "tgn:2402340",
        "tgn:1000001",
        "tgn:7012149",
        "tgn:2001526",
        "tgn:7007709",
        "tgn:7029392"
    ],
    "tgn:id":2402340,
    "tgn:name":"Horton Creek",
    "tgn:placetype":[
        "aat:300008706"
    ]
},
  "bbox": [],
  "geometry": {"coordinates":[-76.6,35.1333],"type":"Point"}
}
=======
{"geometry":{"type":"Point","coordinates":[-76.600000,35.133300]},"type":"Feature","properties":{"hierarchy":["tgn:2402340","tgn:1000001","tgn:7012149","tgn:2001526","tgn:7007709","tgn:7029392"],"placetype":["aat:300008706"],"id":2402340,"name:xx":"Horton Creek"}}
>>>>>>> 03f74aca74312dbeaf24d7e61306dd6a786dc3d0
