<<<<<<< HEAD
{
  "id": 7115745,
  "type": "Feature",
  "properties": {
    "tgn:hierarchy":[
        "tgn:7115745",
        "tgn:7003669",
        "tgn:1000003",
        "tgn:7000084",
        "tgn:7029392"
    ],
    "tgn:id":7115745,
    "tgn:name":"Osterbach",
    "tgn:placetype":[
        "aat:300008699"
    ]
},
  "bbox": [],
  "geometry": {"coordinates":[10.15,47.65],"type":"Point"}
}
=======
{"geometry":{"type":"Point","coordinates":[10.150000,47.650000]},"type":"Feature","properties":{"hierarchy":["tgn:7115745","tgn:7003669","tgn:1000003","tgn:7000084","tgn:7029392"],"placetype":["aat:300008699"],"id":7115745,"name:xx":"Osterbach"}}
>>>>>>> 03f74aca74312dbeaf24d7e61306dd6a786dc3d0
