{
  "id": 2541063,
  "type": "Feature",
  "properties": {
    "tgn:hierarchy":[
        "tgn:2541063",
        "tgn:1000001",
        "tgn:7012149",
        "tgn:7007920",
        "tgn:7029392"
    ],
    "tgn:id":2541063,
    "tgn:name":"Nicholson Creek",
    "tgn:placetype":[
        "aat:300008706"
    ]
},
  "bbox": [],
  "geometry": {"coordinates":[-118.95,48.95],"type":"Point"}
}