{
  "id": 7116818,
  "type": "Feature",
  "properties": {
    "tgn:hierarchy":[
        "tgn:7116818",
        "tgn:7003692",
        "tgn:1000003",
        "tgn:7000084",
        "tgn:7029392"
    ],
    "tgn:id":7116818,
    "tgn:name":"Ottenried",
    "tgn:placetype":[
        "aat:300008347"
    ]
},
  "bbox": [],
  "geometry": {"coordinates":[9.816667,48.916667],"type":"Point"}
}