{
  "id": 2527340,
  "type": "Feature",
  "properties": {
    "tgn:hierarchy":[
        "tgn:2527340",
        "tgn:1000001",
        "tgn:7016172",
        "tgn:2000109",
        "tgn:7012149",
        "tgn:7029392"
    ],
    "tgn:id":2527340,
    "tgn:name":"Mount Pleasant",
    "tgn:placetype":[
        "aat:300008347"
    ]
},
  "bbox": [],
  "geometry": {"coordinates":[-93.0333,36.1667],"type":"Point"}
}