{
  "id": 2198522,
  "type": "Feature",
  "properties": {
    "tgn:hierarchy":[
        "tgn:2198522",
        "tgn:1000001",
        "tgn:7012149",
        "tgn:1002945",
        "tgn:7007710",
        "tgn:7029392"
    ],
    "tgn:id":2198522,
    "tgn:name":"Browns Lake",
    "tgn:placetype":[
        "aat:300006191"
    ]
},
  "bbox": [],
  "geometry": {"coordinates":[-77.3833,41.6833],"type":"Point"}
}