<<<<<<< HEAD
{
  "id": 2158321,
  "type": "Feature",
  "properties": {
    "tgn:hierarchy":[
        "tgn:2158321",
        "tgn:1000001",
        "tgn:7012149",
        "tgn:1002378",
        "tgn:7007710",
        "tgn:7029392"
    ],
    "tgn:id":2158321,
    "tgn:name":"Beaver Valley",
    "tgn:placetype":[
        "aat:300008761"
    ]
},
  "bbox": [],
  "geometry": {"coordinates":[-79.3,41.5833],"type":"Point"}
}
=======
{"geometry":{"type":"Point","coordinates":[-79.300000,41.583300]},"type":"Feature","properties":{"hierarchy":["tgn:2158321","tgn:1000001","tgn:7012149","tgn:1002378","tgn:7007710","tgn:7029392"],"placetype":["aat:300008761"],"id":2158321,"name:xx":"Beaver Valley"}}
>>>>>>> 03f74aca74312dbeaf24d7e61306dd6a786dc3d0
