{
  "id": 1068832,
  "type": "Feature",
  "properties": {
    "tgn:hierarchy":[
        "tgn:1068832",
        "tgn:1000004",
        "tgn:7002076",
        "tgn:1000111",
        "tgn:7029392"
    ],
    "tgn:id":1068832,
    "tgn:name":"Houxijie",
    "tgn:placetype":[
        "aat:300008347"
    ]
},
  "bbox": [],
  "geometry": {"coordinates":[118.7667,28.8333],"type":"Point"}
}