{
  "id": 2731807,
  "type": "Feature",
  "properties": {
    "tgn:hierarchy":[
        "tgn:2731807",
        "tgn:1000001",
        "tgn:7012149",
        "tgn:2001293",
        "tgn:7007524",
        "tgn:7029392"
    ],
    "tgn:id":2731807,
    "tgn:name":"Tumble Creek",
    "tgn:placetype":[
        "aat:300008706"
    ]
},
  "bbox": [],
  "geometry": {"coordinates":[-110.45,45.4167],"type":"Point"}
}