{
  "id": 2492357,
  "type": "Feature",
  "properties": {
    "tgn:hierarchy":[
        "tgn:2492357",
        "tgn:1000001",
        "tgn:7012149",
        "tgn:2001075",
        "tgn:7007521",
        "tgn:7029392"
    ],
    "tgn:id":2492357,
    "tgn:name":"Marge Lake",
    "tgn:placetype":[
        "aat:300008680"
    ]
},
  "bbox": [],
  "geometry": {"coordinates":[-95.0167,45.8833],"type":"Point"}
}