{
  "id": 2444650,
  "type": "Feature",
  "properties": {
    "tgn:hierarchy":[
        "tgn:2444650",
        "tgn:1000001",
        "tgn:7012149",
        "tgn:7007158",
        "tgn:2000246",
        "tgn:7029392"
    ],
    "tgn:id":2444650,
    "tgn:name":"Legal Tender Mine",
    "tgn:placetype":[
        "aat:300000390"
    ]
},
  "bbox": [],
  "geometry": {"coordinates":[-106.1167,38.3333],"type":"Point"}
}