{
  "id": 1048715,
  "type": "Feature",
  "properties": {
    "tgn:hierarchy":[
        "tgn:1048715",
        "tgn:7003647",
        "tgn:1000003",
        "tgn:1000088",
        "tgn:7029392"
    ],
    "tgn:id":1048715,
    "tgn:name":"Rindal",
    "tgn:placetype":[
        "aat:300008347"
    ]
},
  "bbox": [],
  "geometry": {"coordinates":[9.2167,63.0667],"type":"Point"}
}