{
  "id": 7427460,
  "type": "Feature",
  "properties": {
    "tgn:hierarchy":[
        "tgn:7427460",
        "tgn:1000001",
        "tgn:7005594",
        "tgn:7005560",
        "tgn:7029392"
    ],
    "tgn:id":7427460,
    "tgn:name":"Noria Pinta",
    "tgn:placetype":[
        "aat:300008347"
    ]
},
  "bbox": [],
  "geometry": {"coordinates":[-101.266667,23.183333],"type":"Point"}
}