{
  "id": 7226736,
  "type": "Feature",
  "properties": {
    "tgn:hierarchy":[
        "tgn:7226736",
        "tgn:7011330",
        "tgn:7002674",
        "tgn:1000003",
        "tgn:1000074",
        "tgn:7029392"
    ],
    "tgn:id":7226736,
    "tgn:name":"Monakho\u00fa, \u00c1kra",
    "tgn:placetype":[
        "aat:300008850"
    ]
},
  "bbox": [],
  "geometry": {"coordinates":[27.25,35.816667],"type":"Point"}
}