<<<<<<< HEAD
{
  "id": 2254950,
  "type": "Feature",
  "properties": {
    "tgn:hierarchy":[
        "tgn:2254950",
        "tgn:1000001",
        "tgn:2001476",
        "tgn:7012149",
        "tgn:7007709",
        "tgn:7029392"
    ],
    "tgn:id":2254950,
    "tgn:name":"Cooper Branch",
    "tgn:placetype":[
        "aat:300008699"
    ]
},
  "bbox": [],
  "geometry": {"coordinates":[-81.7167,36.0333],"type":"Point"}
}
=======
{"geometry":{"type":"Point","coordinates":[-81.716700,36.033300]},"type":"Feature","properties":{"hierarchy":["tgn:2254950","tgn:1000001","tgn:2001476","tgn:7012149","tgn:7007709","tgn:7029392"],"placetype":["aat:300008699"],"id":2254950,"name:xx":"Cooper Branch"}}
>>>>>>> 03f74aca74312dbeaf24d7e61306dd6a786dc3d0
