{
  "id": 7538908,
  "type": "Feature",
  "properties": {
    "tgn:hierarchy":[
        "tgn:7538908",
        "tgn:7001242",
        "tgn:7016833",
        "tgn:1001225",
        "tgn:7029392"
    ],
    "tgn:id":7538908,
    "tgn:name:en":"Murayya\u1e29, Jaz\u012brat al",
    "tgn:placetype":[
        "aat:300008791"
    ]
},
  "bbox": [],
  "geometry": {"coordinates":[31.879722,31.431389],"type":"Point"}
}