{
  "id": 2516083,
  "type": "Feature",
  "properties": {
    "tgn:hierarchy":[
        "tgn:2516083",
        "tgn:1000001",
        "tgn:1002664",
        "tgn:7012149",
        "tgn:7007159",
        "tgn:7029392"
    ],
    "tgn:id":2516083,
    "tgn:name":"Mine Brook",
    "tgn:placetype":[
        "aat:300008699"
    ]
},
  "bbox": [],
  "geometry": {"coordinates":[-72.5333,41.5833],"type":"Point"}
}