{
  "id": 1026861,
  "type": "Feature",
  "properties": {
    "tgn:hierarchy":[
        "tgn:1026861",
        "tgn:7018766",
        "tgn:1000003",
        "tgn:7006413",
        "tgn:7029392"
    ],
    "tgn:id":1026861,
    "tgn:name":"Tsenovo",
    "tgn:placetype":[
        "aat:300008347"
    ]
},
  "bbox": [],
  "geometry": {"coordinates":[25.65,43.5333],"type":"Point"}
}