{
  "id": 2741358,
  "type": "Feature",
  "properties": {
    "tgn:hierarchy":[
        "tgn:2741358",
        "tgn:1000001",
        "tgn:7012149",
        "tgn:1002862",
        "tgn:7007920",
        "tgn:7029392"
    ],
    "tgn:id":2741358,
    "tgn:name":"Upright Head",
    "tgn:placetype":[
        "aat:300008798"
    ]
},
  "bbox": [],
  "geometry": {"coordinates":[-122.8833,48.5667],"type":"Point"}
}