{
  "id": 7057519,
  "type": "Feature",
  "properties": {
    "tgn:hierarchy":[
        "tgn:7057519",
        "tgn:7003006",
        "tgn:1000003",
        "tgn:7002997",
        "tgn:1000080",
        "tgn:7029392"
    ],
    "tgn:id":7057519,
    "tgn:name":"Ca Corniani",
    "tgn:placetype":[
        "aat:300008347"
    ]
},
  "bbox": [],
  "geometry": {"coordinates":[12.855,45.614444],"type":"Point"}
}