{
  "id": 7593572,
  "type": "Feature",
  "properties": {
    "tgn:hierarchy":[
        "tgn:7593572",
        "tgn:7005509",
        "tgn:1000001",
        "tgn:7005502",
        "tgn:7029392"
    ],
    "tgn:id":7593572,
    "tgn:name":"Grande Saline",
    "tgn:placetype":[
        "aat:300008347"
    ]
},
  "bbox": [],
  "geometry": {"coordinates":[-72.783,19.25],"type":"Point"}
}