{
  "id": 7534022,
  "type": "Feature",
  "properties": {
    "tgn:hierarchy":[
        "tgn:7534022",
        "tgn:7001242",
        "tgn:7016833",
        "tgn:7000122",
        "tgn:7029392"
    ],
    "tgn:id":7534022,
    "tgn:name:en":"Canal Haran",
    "tgn:placetype":[
        "aat:300006075"
    ]
},
  "bbox": [],
  "geometry": {"coordinates":[32.958178,24.566469],"type":"Point"}
}