<<<<<<< HEAD
{
  "id": 2251890,
  "type": "Feature",
  "properties": {
    "tgn:hierarchy":[
        "tgn:2251890",
        "tgn:1000001",
        "tgn:7012149",
        "tgn:1002789",
        "tgn:7007710",
        "tgn:7029392"
    ],
    "tgn:id":2251890,
    "tgn:name":"Conashaugh",
    "tgn:placetype":[
        "aat:300008347"
    ]
},
  "bbox": [],
  "geometry": {"coordinates":[-74.8333,41.2667],"type":"Point"}
}
=======
{"geometry":{"type":"Point","coordinates":[-74.833300,41.266700]},"type":"Feature","properties":{"hierarchy":["tgn:2251890","tgn:1000001","tgn:7012149","tgn:1002789","tgn:7007710","tgn:7029392"],"placetype":["aat:300008347"],"id":2251890,"name:xx":"Conashaugh"}}
>>>>>>> 03f74aca74312dbeaf24d7e61306dd6a786dc3d0
