<<<<<<< HEAD
{
  "id": 2254284,
  "type": "Feature",
  "properties": {
    "tgn:hierarchy":[
        "tgn:2254284",
        "tgn:1000001",
        "tgn:7012149",
        "tgn:7007524",
        "tgn:7029392"
    ],
    "tgn:id":2254284,
    "tgn:name":"Coon Coulee",
    "tgn:placetype":[
        "aat:300008761"
    ]
},
  "bbox": [],
  "geometry": {"coordinates":[-107.3667,48.2667],"type":"Point"}
}
=======
{"geometry":{"type":"Point","coordinates":[-107.366700,48.266700]},"type":"Feature","properties":{"hierarchy":["tgn:2254284","tgn:1000001","tgn:7012149","tgn:7007524","tgn:7029392"],"placetype":["aat:300008761"],"id":2254284,"name:xx":"Coon Coulee"}}
>>>>>>> 03f74aca74312dbeaf24d7e61306dd6a786dc3d0
