{
  "id": 2313399,
  "type": "Feature",
  "properties": {
    "tgn:hierarchy":[
        "tgn:2313399",
        "tgn:1000001",
        "tgn:7012149",
        "tgn:2002248",
        "tgn:7007920",
        "tgn:7029392"
    ],
    "tgn:id":2313399,
    "tgn:name":"Eldorado Creek",
    "tgn:placetype":[
        "aat:300008706"
    ]
},
  "bbox": [],
  "geometry": {"coordinates":[-117.25,48.9833],"type":"Point"}
}