{
  "id": 2190244,
  "type": "Feature",
  "properties": {
    "tgn:hierarchy":[
        "tgn:2190244",
        "tgn:1000001",
        "tgn:2001636",
        "tgn:7012149",
        "tgn:7007707",
        "tgn:7029392"
    ],
    "tgn:id":2190244,
    "tgn:name":"Box",
    "tgn:placetype":[
        "aat:300008347"
    ]
},
  "bbox": [],
  "geometry": {"coordinates":[-97.1333,34.9667],"type":"Point"}
}