{
  "id": 7396270,
  "type": "Feature",
  "properties": {
    "tgn:hierarchy":[
        "tgn:7396270",
        "tgn:1000001",
        "tgn:7005601",
        "tgn:7005560",
        "tgn:7029392"
    ],
    "tgn:id":7396270,
    "tgn:name":"San Fernando",
    "tgn:placetype":[
        "aat:300008347"
    ]
},
  "bbox": [],
  "geometry": {"coordinates":[-102.533333,22.516667],"type":"Point"}
}