{
  "id": 7205429,
  "type": "Feature",
  "properties": {
    "tgn:hierarchy":[
        "tgn:7205429",
        "tgn:1000003",
        "tgn:7000094",
        "tgn:7000084",
        "tgn:7029392"
    ],
    "tgn:id":7205429,
    "tgn:name":"Damerower Forst",
    "tgn:placetype":[
        "aat:300008863"
    ]
},
  "bbox": [],
  "geometry": {"coordinates":[12.233333,53.55],"type":"Point"}
}