{
  "id": 2129178,
  "type": "Feature",
  "properties": {
    "tgn:hierarchy":[
        "tgn:2129178",
        "tgn:1000001",
        "tgn:7012149",
        "tgn:1002613",
        "tgn:7007710",
        "tgn:7029392"
    ],
    "tgn:id":2129178,
    "tgn:name":"Algerine Swamp Bog",
    "tgn:placetype":[
        "aat:300008905"
    ]
},
  "bbox": [],
  "geometry": {"coordinates":[-77.4833,41.5333],"type":"Point"}
}