{
  "id": 7552441,
  "type": "Feature",
  "properties": {
    "tgn:hierarchy":[
        "tgn:7552441",
        "tgn:1000004",
        "tgn:7000198",
        "tgn:7001797",
        "tgn:7029392"
    ],
    "tgn:id":7552441,
    "tgn:name:en":"Maniy\u0101chchi",
    "tgn:placetype":[
        "aat:300008347"
    ]
},
  "bbox": [],
  "geometry": {"coordinates":[77.916667,8.85],"type":"Point"}
}