<<<<<<< HEAD
{
  "id": 2761544,
  "type": "Feature",
  "properties": {
    "tgn:hierarchy":[
        "tgn:2761544",
        "tgn:1000001",
        "tgn:7012149",
        "tgn:1002768",
        "tgn:7007240",
        "tgn:7029392"
    ],
    "tgn:id":2761544,
    "tgn:name":"West Palm Beach Farms",
    "tgn:placetype":[
        "aat:300008347"
    ]
},
  "bbox": [],
  "geometry": {"coordinates":[-80.1167,26.6667],"type":"Point"}
}
=======
{"geometry":{"type":"Point","coordinates":[-80.116700,26.666700]},"type":"Feature","properties":{"hierarchy":["tgn:2761544","tgn:1000001","tgn:7012149","tgn:1002768","tgn:7007240","tgn:7029392"],"placetype":["aat:300008347"],"id":2761544,"name:xx":"West Palm Beach Farms"}}
>>>>>>> 03f74aca74312dbeaf24d7e61306dd6a786dc3d0
