<<<<<<< HEAD
{
  "id": 7350481,
  "type": "Feature",
  "properties": {
    "tgn:hierarchy":[
        "tgn:7350481",
        "tgn:7005581",
        "tgn:1000001",
        "tgn:7005560",
        "tgn:7029392"
    ],
    "tgn:id":7350481,
    "tgn:name":"Blanca",
    "tgn:placetype":[
        "aat:300008347"
    ]
},
  "bbox": [],
  "geometry": {"coordinates":[-106.333333,28.183333],"type":"Point"}
}
=======
{"geometry":{"type":"Point","coordinates":[-106.333333,28.183333]},"type":"Feature","properties":{"hierarchy":["tgn:7350481","tgn:7005581","tgn:1000001","tgn:7005560","tgn:7029392"],"placetype":["aat:300008347"],"id":7350481,"name:xx":"Blanca"}}
>>>>>>> 03f74aca74312dbeaf24d7e61306dd6a786dc3d0
