{
  "id": 7591348,
  "type": "Feature",
  "properties": {
    "tgn:hierarchy":[
        "tgn:7591348",
        "tgn:1000004",
        "tgn:7000198",
        "tgn:7000799",
        "tgn:7029392"
    ],
    "tgn:id":7591348,
    "tgn:name:en":"Mih\u012bn Ch\u0101rk\u0101n",
    "tgn:placetype":[
        "aat:300008347"
    ]
},
  "bbox": [],
  "geometry": {"coordinates":[74.948611,32.625],"type":"Point"}
}