{
  "id": 7099018,
  "type": "Feature",
  "properties": {
    "tgn:hierarchy":[
        "tgn:7099018",
        "tgn:7003692",
        "tgn:1000003",
        "tgn:7000084",
        "tgn:7029392"
    ],
    "tgn:id":7099018,
    "tgn:name":"Spitalwald",
    "tgn:placetype":[
        "aat:300008863"
    ]
},
  "bbox": [],
  "geometry": {"coordinates":[8.833333,47.95],"type":"Point"}
}