<<<<<<< HEAD
{
  "id": 2760373,
  "type": "Feature",
  "properties": {
    "tgn:hierarchy":[
        "tgn:2760373",
        "tgn:1000001",
        "tgn:7012149",
        "tgn:2000494",
        "tgn:7007250",
        "tgn:7029392"
    ],
    "tgn:id":2760373,
    "tgn:name":"West Fork Sixmile Creek",
    "tgn:placetype":[
        "aat:300008706"
    ]
},
  "bbox": [],
  "geometry": {"coordinates":[-115.9833,44.2667],"type":"Point"}
}
=======
{"geometry":{"type":"Point","coordinates":[-115.983300,44.266700]},"type":"Feature","properties":{"hierarchy":["tgn:2760373","tgn:1000001","tgn:7012149","tgn:2000494","tgn:7007250","tgn:7029392"],"placetype":["aat:300008706"],"id":2760373,"name:xx":"West Fork Sixmile Creek"}}
>>>>>>> 03f74aca74312dbeaf24d7e61306dd6a786dc3d0
