{
  "id": 2015802,
  "type": "Feature",
  "properties": {
    "tgn:hierarchy":[
        "tgn:2015802",
        "tgn:1000001",
        "tgn:7012149",
        "tgn:7007158",
        "tgn:2000254",
        "tgn:7029392"
    ],
    "tgn:id":2015802,
    "tgn:name":"Joes",
    "tgn:placetype":[
        "aat:300008347"
    ]
},
  "bbox": [],
  "geometry": {"coordinates":[-102.6667,39.65],"type":"Point"}
}