<<<<<<< HEAD
{
  "id": 7020978,
  "type": "Feature",
  "properties": {
    "tgn:hierarchy":[
        "tgn:7020978",
        "tgn:1000001",
        "tgn:7012149",
        "tgn:2000488",
        "tgn:7007250",
        "tgn:7029392"
    ],
    "tgn:id":7020978,
    "tgn:name":"Willinicker Spring",
    "tgn:placetype":[
        "aat:300008697"
    ]
},
  "bbox": [],
  "geometry": {"coordinates":[-116.8833,43.05],"type":"Point"}
}
=======
{"geometry":{"type":"Point","coordinates":[-116.883300,43.050000]},"type":"Feature","properties":{"hierarchy":["tgn:7020978","tgn:1000001","tgn:7012149","tgn:2000488","tgn:7007250","tgn:7029392"],"placetype":["aat:300008697"],"id":7020978,"name:xx":"Willinicker Spring"}}
>>>>>>> 03f74aca74312dbeaf24d7e61306dd6a786dc3d0
