{
  "id": 2534915,
  "type": "Feature",
  "properties": {
    "tgn:hierarchy":[
        "tgn:2534915",
        "tgn:7006450",
        "tgn:1000001",
        "tgn:7012149",
        "tgn:2000082",
        "tgn:7029392"
    ],
    "tgn:id":2534915,
    "tgn:name":"Nakat Mountain",
    "tgn:placetype":[
        "aat:300008798"
    ]
},
  "bbox": [],
  "geometry": {"coordinates":[-130.6333,54.8667],"type":"Point"}
}