{
  "id": 2742373,
  "type": "Feature",
  "properties": {
    "tgn:hierarchy":[
        "tgn:2742373",
        "tgn:1000001",
        "tgn:1002271",
        "tgn:7012149",
        "tgn:7007920",
        "tgn:7029392"
    ],
    "tgn:id":2742373,
    "tgn:name":"Valley Creek",
    "tgn:placetype":[
        "aat:300008706"
    ]
},
  "bbox": [],
  "geometry": {"coordinates":[-123.4333,48.05],"type":"Point"}
}