{
  "id": 7011839,
  "type": "Feature",
  "properties": {
    "tgn:hierarchy":[
        "tgn:7011839",
        "tgn:7002445",
        "tgn:7011781",
        "tgn:7018933",
        "tgn:1000003",
        "tgn:7008136",
        "tgn:7008591",
        "tgn:7029392"
    ],
    "tgn:id":7011839,
    "tgn:name:en":"Roehampton",
    "tgn:placetype":[
        "aat:300000745"
    ]
},
  "bbox": [],
  "geometry": {"coordinates":[-0.254756,51.457971],"type":"Point"}
}