{
  "id": 7098504,
  "type": "Feature",
  "properties": {
    "tgn:hierarchy":[
        "tgn:7098504",
        "tgn:1000003",
        "tgn:7003677",
        "tgn:7000084",
        "tgn:7029392"
    ],
    "tgn:id":7098504,
    "tgn:name":"Oberf\u00f6rsterei Senden",
    "tgn:placetype":[
        "aat:300004792"
    ]
},
  "bbox": [],
  "geometry": {"coordinates":[7.516667,51.866667],"type":"Point"}
}