{
  "id": 1058513,
  "type": "Feature",
  "properties": {
    "tgn:hierarchy":[
        "tgn:1058513",
        "tgn:1003391",
        "tgn:1000003",
        "tgn:7006657",
        "tgn:7029392"
    ],
    "tgn:id":1058513,
    "tgn:name":"Pogost",
    "tgn:placetype":[
        "aat:300008347",
        "aat:300008375"
    ]
},
  "bbox": [],
  "geometry": {"coordinates":[27.65,52.85],"type":"Point"}
}