{
  "id": 7164098,
  "type": "Feature",
  "properties": {
    "tgn:hierarchy":[
        "tgn:7164098",
        "tgn:1000003",
        "tgn:7003676",
        "tgn:7000084",
        "tgn:7029392"
    ],
    "tgn:id":7164098,
    "tgn:name":"H\u00fcnschen",
    "tgn:placetype":[
        "aat:300000206"
    ]
},
  "bbox": [],
  "geometry": {"coordinates":[8.35,53.516667],"type":"Point"}
}