<<<<<<< HEAD
{
  "id": 2407591,
  "type": "Feature",
  "properties": {
    "tgn:hierarchy":[
        "tgn:2407591",
        "tgn:1000001",
        "tgn:7012149",
        "tgn:2000928",
        "tgn:7007515",
        "tgn:7029392"
    ],
    "tgn:id":2407591,
    "tgn:name":"Hurd Corner",
    "tgn:placetype":[
        "aat:300008347"
    ]
},
  "bbox": [],
  "geometry": {"coordinates":[-69.1833,45.1167],"type":"Point"}
}
=======
{"geometry":{"type":"Point","coordinates":[-69.183300,45.116700]},"type":"Feature","properties":{"hierarchy":["tgn:2407591","tgn:1000001","tgn:7012149","tgn:2000928","tgn:7007515","tgn:7029392"],"placetype":["aat:300008347"],"id":2407591,"name:xx":"Hurd Corner"}}
>>>>>>> 03f74aca74312dbeaf24d7e61306dd6a786dc3d0
