{
  "id": 7313011,
  "type": "Feature",
  "properties": {
    "tgn:hierarchy":[
        "tgn:7313011",
        "tgn:1001637",
        "tgn:1000049",
        "tgn:1000002",
        "tgn:7029392"
    ],
    "tgn:id":7313011,
    "tgn:name":"Los Pinos, Cerro",
    "tgn:placetype":[
        "aat:300008795"
    ]
},
  "bbox": [],
  "geometry": {"coordinates":[-71.666667,-37.483333],"type":"Point"}
}