{
  "id": 2574025,
  "type": "Feature",
  "properties": {
    "tgn:hierarchy":[
        "tgn:2574025",
        "tgn:2001089",
        "tgn:1000001",
        "tgn:7012149",
        "tgn:7007522",
        "tgn:7029392"
    ],
    "tgn:id":2574025,
    "tgn:name":"Peeler Branch",
    "tgn:placetype":[
        "aat:300008699"
    ]
},
  "bbox": [],
  "geometry": {"coordinates":[-89.4167,32.95],"type":"Point"}
}