{
  "id": 7578537,
  "type": "Feature",
  "properties": {
    "tgn:hierarchy":[
        "tgn:7578537",
        "tgn:1000004",
        "tgn:7000198",
        "tgn:1001882",
        "tgn:7029392"
    ],
    "tgn:id":7578537,
    "tgn:name:en":"T\u016brk Madhw\u0101ram",
    "tgn:placetype":[
        "aat:300008347"
    ]
},
  "bbox": [],
  "geometry": {"coordinates":[77.333333,16.633333],"type":"Point"}
}