<<<<<<< HEAD
{
  "id": 2151507,
  "type": "Feature",
  "properties": {
    "tgn:hierarchy":[
        "tgn:2151507",
        "tgn:1000001",
        "tgn:7012149",
        "tgn:1002468",
        "tgn:7007252",
        "tgn:7029392"
    ],
    "tgn:id":2151507,
    "tgn:name":"Batson Drain",
    "tgn:placetype":[
        "aat:300008699"
    ]
},
  "bbox": [],
  "geometry": {"coordinates":[-85.25,39.9],"type":"Point"}
}
=======
{"geometry":{"type":"Point","coordinates":[-85.250000,39.900000]},"type":"Feature","properties":{"hierarchy":["tgn:2151507","tgn:1000001","tgn:7012149","tgn:1002468","tgn:7007252","tgn:7029392"],"placetype":["aat:300008699"],"id":2151507,"name:xx":"Batson Drain"}}
>>>>>>> 03f74aca74312dbeaf24d7e61306dd6a786dc3d0
