{
  "id": 2600466,
  "type": "Feature",
  "properties": {
    "tgn:hierarchy":[
        "tgn:2600466",
        "tgn:1000001",
        "tgn:7012149",
        "tgn:2000927",
        "tgn:7007515",
        "tgn:7029392"
    ],
    "tgn:id":2600466,
    "tgn:name":"Pug Brook",
    "tgn:placetype":[
        "aat:300008699"
    ]
},
  "bbox": [],
  "geometry": {"coordinates":[-68.8833,44.7833],"type":"Point"}
}