<<<<<<< HEAD
{
  "id": 2336609,
  "type": "Feature",
  "properties": {
    "tgn:hierarchy":[
        "tgn:2336609",
        "tgn:1000001",
        "tgn:7012149",
        "tgn:2000182",
        "tgn:7007157",
        "tgn:7029392"
    ],
    "tgn:id":2336609,
    "tgn:name":"Four Palms Spring",
    "tgn:placetype":[
        "aat:300008697"
    ]
},
  "bbox": [],
  "geometry": {"coordinates":[-116.0167,33.2667],"type":"Point"}
}
=======
{"geometry":{"type":"Point","coordinates":[-116.016700,33.266700]},"type":"Feature","properties":{"hierarchy":["tgn:2336609","tgn:1000001","tgn:7012149","tgn:2000182","tgn:7007157","tgn:7029392"],"placetype":["aat:300008697"],"id":2336609,"name:xx":"Four Palms Spring"}}
>>>>>>> 03f74aca74312dbeaf24d7e61306dd6a786dc3d0
