{
  "id": 2372818,
  "type": "Feature",
  "properties": {
    "tgn:hierarchy":[
        "tgn:2372818",
        "tgn:1000001",
        "tgn:7012149",
        "tgn:2000933",
        "tgn:7007515",
        "tgn:7029392"
    ],
    "tgn:id":2372818,
    "tgn:name":"Hall Ponds",
    "tgn:placetype":[
        "aat:300008680"
    ]
},
  "bbox": [],
  "geometry": {"coordinates":[-70.85,43.2667],"type":"Point"}
}