{
  "id": 2290481,
  "type": "Feature",
  "properties": {
    "tgn:hierarchy":[
        "tgn:2290481",
        "tgn:1000001",
        "tgn:7012149",
        "tgn:7007157",
        "tgn:2000188",
        "tgn:7029392"
    ],
    "tgn:id":2290481,
    "tgn:name":"Doe Gulch",
    "tgn:placetype":[
        "aat:300008761"
    ]
},
  "bbox": [],
  "geometry": {"coordinates":[-122.2833,40.9167],"type":"Point"}
}