{
  "id": 2353442,
  "type": "Feature",
  "properties": {
    "tgn:hierarchy":[
        "tgn:2353442",
        "tgn:1000001",
        "tgn:2001411",
        "tgn:7012149",
        "tgn:7007526",
        "tgn:7029392"
    ],
    "tgn:id":2353442,
    "tgn:name":"Gold Crown Mine",
    "tgn:placetype":[
        "aat:300000390"
    ]
},
  "bbox": [],
  "geometry": {"coordinates":[-116.7833,41.2333],"type":"Point"}
}