{
  "id": 7034834,
  "type": "Feature",
  "properties": {
    "tgn:hierarchy":[
        "tgn:7034834",
        "tgn:1000003",
        "tgn:7003141",
        "tgn:7003236",
        "tgn:1000080",
        "tgn:7029392"
    ],
    "tgn:id":7034834,
    "tgn:name":"San Bernardo",
    "tgn:placetype":[
        "aat:300008347"
    ]
},
  "bbox": [],
  "geometry": {"coordinates":[9.075,44.383333],"type":"Point"}
}