{
  "id": 2073268,
  "type": "Feature",
  "properties": {
    "tgn:hierarchy":[
        "tgn:2073268",
        "tgn:1000001",
        "tgn:7012149",
        "tgn:2001461",
        "tgn:7007568",
        "tgn:7029392"
    ],
    "tgn:id":2073268,
    "tgn:name":"Willsboro",
    "tgn:placetype":[
        "aat:300008347"
    ]
},
  "bbox": [],
  "geometry": {"coordinates":[-73.3833,44.35],"type":"Point"}
}