{
  "id": 2133101,
  "type": "Feature",
  "properties": {
    "tgn:hierarchy":[
        "tgn:2133101",
        "tgn:1000001",
        "tgn:7012149",
        "tgn:2001252",
        "tgn:7007523",
        "tgn:7029392"
    ],
    "tgn:id":2133101,
    "tgn:name":"Anderson Hollow",
    "tgn:placetype":[
        "aat:300008761"
    ]
},
  "bbox": [],
  "geometry": {"coordinates":[-92.0833,37.5167],"type":"Point"}
}