{
  "id": 7587218,
  "type": "Feature",
  "properties": {
    "tgn:hierarchy":[
        "tgn:7587218",
        "tgn:1000004",
        "tgn:7000198",
        "tgn:7000799",
        "tgn:7029392"
    ],
    "tgn:id":7587218,
    "tgn:name:en":"Son\u0101w\u0101ri",
    "tgn:placetype":[
        "aat:300008347"
    ]
},
  "bbox": [],
  "geometry": {"coordinates":[74.6375,34.238889],"type":"Point"}
}