{
  "id": 2278187,
  "type": "Feature",
  "properties": {
    "tgn:hierarchy":[
        "tgn:2278187",
        "tgn:1000001",
        "tgn:7012149",
        "tgn:2001438",
        "tgn:7007566",
        "tgn:7029392"
    ],
    "tgn:id":2278187,
    "tgn:name":"De Baca Tank",
    "tgn:placetype":[
        "aat:300006191"
    ]
},
  "bbox": [],
  "geometry": {"coordinates":[-104.2333,35.1167],"type":"Point"}
}