<<<<<<< HEAD
{
  "id": 7472444,
  "type": "Feature",
  "properties": {
    "tgn:hierarchy":[
        "tgn:7472444",
        "tgn:1000004",
        "tgn:7467799",
        "tgn:1000141",
        "tgn:7029392"
    ],
    "tgn:id":7472444,
    "tgn:name":"Xihu Qiao",
    "tgn:placetype":[
        "aat:300007836"
    ]
},
  "bbox": [],
  "geometry": {"coordinates":[120.450556,24.003333],"type":"Point"}
}
=======
{"geometry":{"type":"Point","coordinates":[120.450556,24.003333]},"type":"Feature","properties":{"hierarchy":["tgn:7472444","tgn:1000004","tgn:7467799","tgn:1000141","tgn:7029392"],"placetype":["aat:300007836"],"id":7472444,"name:xx":"Xihu Qiao"}}
>>>>>>> 03f74aca74312dbeaf24d7e61306dd6a786dc3d0
