{
  "id": 7472444,
  "type": "Feature",
  "properties": {
    "tgn:hierarchy":[
        "tgn:7472444",
        "tgn:1000004",
        "tgn:7467799",
        "tgn:1000141",
        "tgn:7029392"
    ],
    "tgn:id":7472444,
    "tgn:name":"Xihu Qiao",
    "tgn:placetype":[
        "aat:300007836"
    ]
},
  "bbox": [],
  "geometry": {"coordinates":[120.450556,24.003333],"type":"Point"}
}