{
  "id": 1141025,
  "type": "Feature",
  "properties": {
    "tgn:hierarchy":[
        "tgn:1141025",
        "tgn:7000490",
        "tgn:1000006",
        "tgn:7001828",
        "tgn:7029392"
    ],
    "tgn:id":1141025,
    "tgn:name":"White Cliffs",
    "tgn:placetype":[
        "aat:300008347"
    ]
},
  "bbox": [],
  "geometry": {"coordinates":[143.1333,-30.8333],"type":"Point"}
}