<<<<<<< HEAD
{
  "id": 2408162,
  "type": "Feature",
  "properties": {
    "tgn:hierarchy":[
        "tgn:2408162",
        "tgn:1000001",
        "tgn:7012149",
        "tgn:2001879",
        "tgn:7007825",
        "tgn:7029392"
    ],
    "tgn:id":2408162,
    "tgn:name":"Hurricane Rock Spring",
    "tgn:placetype":[
        "aat:300008697"
    ]
},
  "bbox": [],
  "geometry": {"coordinates":[-87.8667,36.0],"type":"Point"}
}
=======
{"geometry":{"type":"Point","coordinates":[-87.866700,36.000000]},"type":"Feature","properties":{"hierarchy":["tgn:2408162","tgn:1000001","tgn:7012149","tgn:2001879","tgn:7007825","tgn:7029392"],"placetype":["aat:300008697"],"id":2408162,"name:xx":"Hurricane Rock Spring"}}
>>>>>>> 03f74aca74312dbeaf24d7e61306dd6a786dc3d0
