<<<<<<< HEAD
{
  "id": 7023619,
  "type": "Feature",
  "properties": {
    "tgn:hierarchy":[
        "tgn:7023619",
        "tgn:1000001",
        "tgn:7029392"
    ],
    "tgn:id":7023619,
    "tgn:name":"Osoyoos Lake",
    "tgn:placetype":[
        "aat:300008680"
    ]
},
  "bbox": [],
  "geometry": {"coordinates":[-119.4667,49.0],"type":"Point"}
}
=======
{"geometry":{"type":"Point","coordinates":[-119.466700,49.000000]},"type":"Feature","properties":{"hierarchy":["tgn:7023619","tgn:1000001","tgn:7029392"],"placetype":["aat:300008680"],"id":7023619,"name:xx":"Osoyoos Lake"}}
>>>>>>> 03f74aca74312dbeaf24d7e61306dd6a786dc3d0
