{
  "id": 1106429,
  "type": "Feature",
  "properties": {
    "tgn:hierarchy":[
        "tgn:1106429",
        "tgn:1000001",
        "tgn:7012149",
        "tgn:2001452",
        "tgn:7007566",
        "tgn:7029392"
    ],
    "tgn:id":1106429,
    "tgn:name":"Ship Rock",
    "tgn:placetype":[
        "aat:300008795"
    ]
},
  "bbox": [],
  "geometry": {"coordinates":[-108.8333,36.6833],"type":"Point"}
}