{
  "id": 2534225,
  "type": "Feature",
  "properties": {
    "tgn:hierarchy":[
        "tgn:2534225",
        "tgn:1000001",
        "tgn:2001417",
        "tgn:7012149",
        "tgn:7007526",
        "tgn:7029392"
    ],
    "tgn:id":2534225,
    "tgn:name":"Mystery Ridge",
    "tgn:placetype":[
        "aat:300266640"
    ]
},
  "bbox": [],
  "geometry": {"coordinates":[-118.2167,38.7833],"type":"Point"}
}