{
  "id": 7420116,
  "type": "Feature",
  "properties": {
    "tgn:hierarchy":[
        "tgn:7420116",
        "tgn:1001836",
        "tgn:1000001",
        "tgn:7005560",
        "tgn:7029392"
    ],
    "tgn:id":7420116,
    "tgn:name":"Santa In\u00e9s, R\u00edo",
    "tgn:placetype":[
        "aat:300008699"
    ]
},
  "bbox": [],
  "geometry": {"coordinates":[-110.578056,23.625],"type":"Point"}
}