{
  "id": 2247748,
  "type": "Feature",
  "properties": {
    "tgn:hierarchy":[
        "tgn:2247748",
        "tgn:1000001",
        "tgn:7012149",
        "tgn:2001715",
        "tgn:7007708",
        "tgn:7029392"
    ],
    "tgn:id":2247748,
    "tgn:name":"Cogswell Creek",
    "tgn:placetype":[
        "aat:300008706"
    ]
},
  "bbox": [],
  "geometry": {"coordinates":[-120.2833,42.0667],"type":"Point"}
}