<<<<<<< HEAD
{
  "id": 2255892,
  "type": "Feature",
  "properties": {
    "tgn:hierarchy":[
        "tgn:2255892",
        "tgn:1000001",
        "tgn:7012149",
        "tgn:1002899",
        "tgn:7007920",
        "tgn:7029392"
    ],
    "tgn:id":2255892,
    "tgn:name":"Copper Creek",
    "tgn:placetype":[
        "aat:300008706"
    ]
},
  "bbox": [],
  "geometry": {"coordinates":[-121.6667,48.15],"type":"Point"}
}
=======
{"geometry":{"type":"Point","coordinates":[-121.666700,48.150000]},"type":"Feature","properties":{"hierarchy":["tgn:2255892","tgn:1000001","tgn:7012149","tgn:1002899","tgn:7007920","tgn:7029392"],"placetype":["aat:300008706"],"id":2255892,"name:xx":"Copper Creek"}}
>>>>>>> 03f74aca74312dbeaf24d7e61306dd6a786dc3d0
