{
  "id": 2125209,
  "type": "Feature",
  "properties": {
    "tgn:hierarchy":[
        "tgn:2125209",
        "tgn:1000001",
        "tgn:7012149",
        "tgn:2001457",
        "tgn:7007566",
        "tgn:7029392"
    ],
    "tgn:id":2125209,
    "tgn:name":"Acequia Madre Del Norte Del Canon",
    "tgn:placetype":[
        "aat:300008761"
    ]
},
  "bbox": [],
  "geometry": {"coordinates":[-105.5667,36.3667],"type":"Point"}
}