{
  "id": 7293235,
  "type": "Feature",
  "properties": {
    "tgn:hierarchy":[
        "tgn:7293235",
        "tgn:7002758",
        "tgn:7002823",
        "tgn:1000003",
        "tgn:1000095",
        "tgn:7029392"
    ],
    "tgn:id":7293235,
    "tgn:name":"Faro El Picacho de la Barra",
    "tgn:placetype":[
        "aat:300008347"
    ]
},
  "bbox": [],
  "geometry": {"coordinates":[-6.823889,37.136667],"type":"Point"}
}