{
  "id": 7244421,
  "type": "Feature",
  "properties": {
    "tgn:hierarchy":[
        "tgn:7244421",
        "tgn:7003457",
        "tgn:1000003",
        "tgn:1000063",
        "tgn:7018236",
        "tgn:7029392"
    ],
    "tgn:id":7244421,
    "tgn:name":"Kruisstraat",
    "tgn:placetype":[
        "aat:300008347"
    ]
},
  "bbox": [],
  "geometry": {"coordinates":[3.936582,51.202708],"type":"Point"}
}