{
  "id": 7117163,
  "type": "Feature",
  "properties": {
    "tgn:hierarchy":[
        "tgn:7117163",
        "tgn:1000003",
        "tgn:7003682",
        "tgn:7000084",
        "tgn:7029392"
    ],
    "tgn:id":7117163,
    "tgn:name":"Oellingen",
    "tgn:placetype":[
        "aat:300008347"
    ]
},
  "bbox": [],
  "geometry": {"coordinates":[7.983333,50.616667],"type":"Point"}
}