{
  "id": 1088764,
  "type": "Feature",
  "properties": {
    "tgn:hierarchy":[
        "tgn:1088764",
        "tgn:7001242",
        "tgn:7016755",
        "tgn:1000159",
        "tgn:7029392"
    ],
    "tgn:id":1088764,
    "tgn:name":"Bafwabaka",
    "tgn:placetype":[
        "aat:300008347"
    ]
},
  "bbox": [],
  "geometry": {"coordinates":[27.65,2.1667],"type":"Point"}
}