<<<<<<< HEAD
{
  "id": 7481083,
  "type": "Feature",
  "properties": {
    "tgn:hierarchy":[
        "tgn:7481083",
        "tgn:7468018",
        "tgn:1000004",
        "tgn:1000141",
        "tgn:7029392"
    ],
    "tgn:id":7481083,
    "tgn:name":"Guishe Qiao",
    "tgn:placetype":[
        "aat:300007836"
    ]
},
  "bbox": [],
  "geometry": {"coordinates":[120.216403,23.425774],"type":"Point"}
}
=======
{"geometry":{"type":"Point","coordinates":[120.216403,23.425774]},"type":"Feature","properties":{"hierarchy":["tgn:7481083","tgn:7468018","tgn:1000004","tgn:1000141","tgn:7029392"],"placetype":["aat:300007836"],"id":7481083,"name:xx":"Guishe Qiao"}}
>>>>>>> 03f74aca74312dbeaf24d7e61306dd6a786dc3d0
