{
  "id": 7064314,
  "type": "Feature",
  "properties": {
    "tgn:hierarchy":[
        "tgn:7064314",
        "tgn:7003669",
        "tgn:1000003",
        "tgn:7000084",
        "tgn:7029392"
    ],
    "tgn:id":7064314,
    "tgn:name":"Unterdaching",
    "tgn:placetype":[
        "aat:300008347"
    ]
},
  "bbox": [],
  "geometry": {"coordinates":[12.566667,48.716667],"type":"Point"}
}