{
  "id": 1093109,
  "type": "Feature",
  "properties": {
    "tgn:hierarchy":[
        "tgn:1093109",
        "tgn:7001242",
        "tgn:7017583",
        "tgn:1000193",
        "tgn:7029392"
    ],
    "tgn:id":1093109,
    "tgn:name":"Graaff-Reinet",
    "tgn:placetype":[
        "aat:300008347"
    ]
},
  "bbox": [],
  "geometry": {"coordinates":[24.5333,-32.25],"type":"Point"}
}