<<<<<<< HEAD
{
  "id": 2334762,
  "type": "Feature",
  "properties": {
    "tgn:hierarchy":[
        "tgn:2334762",
        "tgn:1000001",
        "tgn:7012149",
        "tgn:2002184",
        "tgn:7007919",
        "tgn:7029392"
    ],
    "tgn:id":2334762,
    "tgn:name":"Fork Mountain",
    "tgn:placetype":[
        "aat:300008798"
    ]
},
  "bbox": [],
  "geometry": {"coordinates":[-78.2667,38.7],"type":"Point"}
}
=======
{"geometry":{"type":"Point","coordinates":[-78.266700,38.700000]},"type":"Feature","properties":{"hierarchy":["tgn:2334762","tgn:1000001","tgn:7012149","tgn:2002184","tgn:7007919","tgn:7029392"],"placetype":["aat:300008798"],"id":2334762,"name:xx":"Fork Mountain"}}
>>>>>>> 03f74aca74312dbeaf24d7e61306dd6a786dc3d0
