<<<<<<< HEAD
{
  "id": 7372828,
  "type": "Feature",
  "properties": {
    "tgn:hierarchy":[
        "tgn:7372828",
        "tgn:1000001",
        "tgn:7005599",
        "tgn:7005560",
        "tgn:7029392"
    ],
    "tgn:id":7372828,
    "tgn:name":"La Carolina",
    "tgn:placetype":[
        "aat:300007783"
    ]
},
  "bbox": [],
  "geometry": {"coordinates":[-96.066667,18.266667],"type":"Point"}
}
=======
{"geometry":{"type":"Point","coordinates":[-96.066667,18.266667]},"type":"Feature","properties":{"hierarchy":["tgn:7372828","tgn:1000001","tgn:7005599","tgn:7005560","tgn:7029392"],"placetype":["aat:300007783"],"id":7372828,"name:xx":"La Carolina"}}
>>>>>>> 03f74aca74312dbeaf24d7e61306dd6a786dc3d0
