{
  "id": 7579926,
  "type": "Feature",
  "properties": {
    "tgn:hierarchy":[
        "tgn:7579926",
        "tgn:1000004",
        "tgn:7000198",
        "tgn:1001996",
        "tgn:7029392"
    ],
    "tgn:id":7579926,
    "tgn:name:en":"Shirir",
    "tgn:placetype":[
        "aat:300008347"
    ]
},
  "bbox": [],
  "geometry": {"coordinates":[77.123252,32.066795],"type":"Point"}
}