{
  "id": 7342297,
  "type": "Feature",
  "properties": {
    "tgn:hierarchy":[
        "tgn:7342297",
        "tgn:7008912",
        "tgn:7030216",
        "tgn:1000003",
        "tgn:1000095",
        "tgn:7029392"
    ],
    "tgn:id":7342297,
    "tgn:name":"Castelld\u00e1ns",
    "tgn:placetype":[
        "aat:300008347"
    ]
},
  "bbox": [],
  "geometry": {"coordinates":[0.765658,41.498525],"type":"Point"}
}