{
  "id": 2592963,
  "type": "Feature",
  "properties": {
    "tgn:hierarchy":[
        "tgn:2592963",
        "tgn:1000001",
        "tgn:7016172",
        "tgn:7012149",
        "tgn:2000132",
        "tgn:7029392"
    ],
    "tgn:id":2592963,
    "tgn:name":"Poplar Creek",
    "tgn:placetype":[
        "aat:300008706"
    ]
},
  "bbox": [],
  "geometry": {"coordinates":[-90.6167,36.0333],"type":"Point"}
}