{
  "id": 1017023,
  "type": "Feature",
  "properties": {
    "tgn:hierarchy":[
        "tgn:1017023",
        "tgn:1000001",
        "tgn:1001960",
        "tgn:7005560",
        "tgn:7029392"
    ],
    "tgn:id":1017023,
    "tgn:name":"Arizpe",
    "tgn:placetype":[
        "aat:300008347"
    ]
},
  "bbox": [],
  "geometry": {"coordinates":[-110.166667,30.333333],"type":"Point"}
}