<<<<<<< HEAD
{
  "id": 7021472,
  "type": "Feature",
  "properties": {
    "tgn:hierarchy":[
        "tgn:7021472",
        "tgn:1000001",
        "tgn:7012149",
        "tgn:2002300",
        "tgn:7013961",
        "tgn:7029392"
    ],
    "tgn:id":7021472,
    "tgn:name":"Lick Branch",
    "tgn:placetype":[
        "aat:300008699"
    ]
},
  "bbox": [],
  "geometry": {"coordinates":[-80.3833,38.3],"type":"Point"}
}
=======
{"geometry":{"type":"Point","coordinates":[-80.383300,38.300000]},"type":"Feature","properties":{"hierarchy":["tgn:7021472","tgn:1000001","tgn:7012149","tgn:2002300","tgn:7013961","tgn:7029392"],"placetype":["aat:300008699"],"id":7021472,"name:xx":"Lick Branch"}}
>>>>>>> 03f74aca74312dbeaf24d7e61306dd6a786dc3d0
