{
  "id": 7434175,
  "type": "Feature",
  "properties": {
    "tgn:hierarchy":[
        "tgn:7434175",
        "tgn:1001835",
        "tgn:1000001",
        "tgn:7005560",
        "tgn:7029392"
    ],
    "tgn:id":7434175,
    "tgn:name":"Rodr\u00edguez",
    "tgn:placetype":[
        "aat:300008347"
    ]
},
  "bbox": [],
  "geometry": {"coordinates":[-115.040278,32.451667],"type":"Point"}
}