{
  "id": 2658661,
  "type": "Feature",
  "properties": {
    "tgn:hierarchy":[
        "tgn:2658661",
        "tgn:1000001",
        "tgn:7012149",
        "tgn:2000982",
        "tgn:7007520",
        "tgn:7029392"
    ],
    "tgn:id":2658661,
    "tgn:name":"Sheridan Valley Ski Area",
    "tgn:placetype":[
        "aat:300055621"
    ]
},
  "bbox": [],
  "geometry": {"coordinates":[-84.2333,44.9167],"type":"Point"}
}