{
  "id": 7549906,
  "type": "Feature",
  "properties": {
    "tgn:hierarchy":[
        "tgn:7549906",
        "tgn:1009838",
        "tgn:7000204",
        "tgn:1000004",
        "tgn:7000198",
        "tgn:7029392"
    ],
    "tgn:id":7549906,
    "tgn:name:en":"Corbyns Cove South",
    "tgn:placetype":[
        "aat:300132317"
    ]
},
  "bbox": [],
  "geometry": {"coordinates":[92.766667,11.633333],"type":"Point"}
}