{
  "id": 7294424,
  "type": "Feature",
  "properties": {
    "tgn:hierarchy":[
        "tgn:7294424",
        "tgn:7002832",
        "tgn:7001158",
        "tgn:1000003",
        "tgn:1000095",
        "tgn:7029392"
    ],
    "tgn:id":7294424,
    "tgn:name":"Valoria de Aguilar",
    "tgn:placetype":[
        "aat:300008347"
    ]
},
  "bbox": [],
  "geometry": {"coordinates":[-4.266667,42.766667],"type":"Point"}
}