{
  "id": 2102749,
  "type": "Feature",
  "properties": {
    "tgn:hierarchy":[
        "tgn:2102749",
        "tgn:1000001",
        "tgn:7012149",
        "tgn:1002214",
        "tgn:7007826",
        "tgn:7029392"
    ],
    "tgn:id":2102749,
    "tgn:name":"Birch",
    "tgn:placetype":[
        "aat:300008347",
        "aat:300387210"
    ]
},
  "bbox": [],
  "geometry": {"coordinates":[-96.6667,30.3667],"type":"Point"}
}