{
  "id": 7234165,
  "type": "Feature",
  "properties": {
    "tgn:hierarchy":[
        "tgn:7234165",
        "tgn:7002707",
        "tgn:7002705",
        "tgn:1000003",
        "tgn:1000074",
        "tgn:7029392"
    ],
    "tgn:id":7234165,
    "tgn:name":"Delvinak\u00f3poulon",
    "tgn:placetype":[
        "aat:300008347"
    ]
},
  "bbox": [],
  "geometry": {"coordinates":[20.655556,39.661667],"type":"Point"}
}