{
  "id": 2231067,
  "type": "Feature",
  "properties": {
    "tgn:hierarchy":[
        "tgn:2231067",
        "tgn:1000001",
        "tgn:7012149",
        "tgn:2001274",
        "tgn:7007524",
        "tgn:7029392"
    ],
    "tgn:id":2231067,
    "tgn:name":"Cerulean Ridge",
    "tgn:placetype":[
        "aat:300266640"
    ]
},
  "bbox": [],
  "geometry": {"coordinates":[-114.1167,48.8333],"type":"Point"}
}