{
  "id": 2692200,
  "type": "Feature",
  "properties": {
    "tgn:hierarchy":[
        "tgn:2692200",
        "tgn:1000001",
        "tgn:7012149",
        "tgn:2001706",
        "tgn:7007708",
        "tgn:7029392"
    ],
    "tgn:id":2692200,
    "tgn:name":"Station Creek",
    "tgn:placetype":[
        "aat:300008706"
    ]
},
  "bbox": [],
  "geometry": {"coordinates":[-122.7333,43.3167],"type":"Point"}
}