{
  "id": 2328138,
  "type": "Feature",
  "properties": {
    "tgn:hierarchy":[
        "tgn:2328138",
        "tgn:1000001",
        "tgn:7012149",
        "tgn:2001721",
        "tgn:7007708",
        "tgn:7029392"
    ],
    "tgn:id":2328138,
    "tgn:name":"Fish Reservoir",
    "tgn:placetype":[
        "aat:300006191"
    ]
},
  "bbox": [],
  "geometry": {"coordinates":[-117.6667,45.0333],"type":"Point"}
}