{
  "id": 2299113,
  "type": "Feature",
  "properties": {
    "tgn:hierarchy":[
        "tgn:2299113",
        "tgn:1000001",
        "tgn:2001263",
        "tgn:7012149",
        "tgn:7007524",
        "tgn:7029392"
    ],
    "tgn:id":2299113,
    "tgn:name":"Duck Creek",
    "tgn:placetype":[
        "aat:300008706"
    ]
},
  "bbox": [],
  "geometry": {"coordinates":[-111.2667,46.5167],"type":"Point"}
}