{
  "id": 1019911,
  "type": "Feature",
  "properties": {
    "tgn:hierarchy":[
        "tgn:1019911",
        "tgn:1001182",
        "tgn:7006477",
        "tgn:1000002",
        "tgn:7029392"
    ],
    "tgn:id":1019911,
    "tgn:name":"Quir\u00f3s",
    "tgn:placetype":[
        "aat:300008347"
    ]
},
  "bbox": [],
  "geometry": {"coordinates":[-65.1167,-28.7833],"type":"Point"}
}