{
  "id": 2533173,
  "type": "Feature",
  "properties": {
    "tgn:hierarchy":[
        "tgn:2533173",
        "tgn:1000001",
        "tgn:7012149",
        "tgn:2001552",
        "tgn:7007709",
        "tgn:7029392"
    ],
    "tgn:id":2533173,
    "tgn:name":"Musgrave Crossroads",
    "tgn:placetype":[
        "aat:300008347"
    ]
},
  "bbox": [],
  "geometry": {"coordinates":[-77.8667,35.4833],"type":"Point"}
}