{
  "id": 7490471,
  "type": "Feature",
  "properties": {
    "tgn:hierarchy":[
        "tgn:7490471",
        "tgn:7001010",
        "tgn:1000004",
        "tgn:1000141",
        "tgn:7029392"
    ],
    "tgn:id":7490471,
    "tgn:name":"Shakadang Xi",
    "tgn:placetype":[
        "aat:300008699"
    ]
},
  "bbox": [],
  "geometry": {"coordinates":[121.613611,24.161024],"type":"Point"}
}