{
  "id": 2588265,
  "type": "Feature",
  "properties": {
    "tgn:hierarchy":[
        "tgn:2588265",
        "tgn:1000001",
        "tgn:7012149",
        "tgn:1002583",
        "tgn:7007251",
        "tgn:7029392"
    ],
    "tgn:id":2588265,
    "tgn:name":"Plum Creek",
    "tgn:placetype":[
        "aat:300008706"
    ]
},
  "bbox": [],
  "geometry": {"coordinates":[-89.5167,41.8833],"type":"Point"}
}