{
  "id": 2369114,
  "type": "Feature",
  "properties": {
    "tgn:hierarchy":[
        "tgn:2369114",
        "tgn:1000001",
        "tgn:7012149",
        "tgn:2002047",
        "tgn:7007826",
        "tgn:7029392"
    ],
    "tgn:id":2369114,
    "tgn:name":"Gum Lake",
    "tgn:placetype":[
        "aat:300008680"
    ]
},
  "bbox": [],
  "geometry": {"coordinates":[-93.5167,31.0167],"type":"Point"}
}