{
  "id": 2069749,
  "type": "Feature",
  "properties": {
    "tgn:hierarchy":[
        "tgn:2069749",
        "tgn:1000001",
        "tgn:7012149",
        "tgn:1002882",
        "tgn:7007568",
        "tgn:7029392"
    ],
    "tgn:id":2069749,
    "tgn:name":"Holton Beach",
    "tgn:placetype":[
        "aat:300008347"
    ]
},
  "bbox": [],
  "geometry": {"coordinates":[-76.6833,42.6167],"type":"Point"}
}