{
  "id": 1058015,
  "type": "Feature",
  "properties": {
    "tgn:hierarchy":[
        "tgn:1058015",
        "tgn:1000004",
        "tgn:7018213",
        "tgn:7002435",
        "tgn:7029392"
    ],
    "tgn:id":1058015,
    "tgn:name":"Ordzhonikidzevskaya",
    "tgn:placetype":[
        "aat:300008347"
    ]
},
  "bbox": [],
  "geometry": {"coordinates":[45.0333,43.3333],"type":"Point"}
}