{
  "id": 7438846,
  "type": "Feature",
  "properties": {
    "tgn:hierarchy":[
        "tgn:7438846",
        "tgn:7005581",
        "tgn:1000001",
        "tgn:7005560",
        "tgn:7029392"
    ],
    "tgn:id":7438846,
    "tgn:name":"Tehuarichic",
    "tgn:placetype":[
        "aat:300008347"
    ]
},
  "bbox": [],
  "geometry": {"coordinates":[-107.25,28.133333],"type":"Point"}
}