{
  "id": 2407360,
  "type": "Feature",
  "properties": {
    "tgn:hierarchy":[
        "tgn:2407360",
        "tgn:1000001",
        "tgn:2001746",
        "tgn:7012149",
        "tgn:7007712",
        "tgn:7029392"
    ],
    "tgn:id":2407360,
    "tgn:name":"Huntington Marsh",
    "tgn:placetype":[
        "aat:300008347"
    ]
},
  "bbox": [],
  "geometry": {"coordinates":[-79.05,33.5167],"type":"Point"}
}