<<<<<<< HEAD
{
  "id": 2407360,
  "type": "Feature",
  "properties": {
    "tgn:hierarchy":[
        "tgn:2407360",
        "tgn:1000001",
        "tgn:2001746",
        "tgn:7012149",
        "tgn:7007712",
        "tgn:7029392"
    ],
    "tgn:id":2407360,
    "tgn:name":"Huntington Marsh",
    "tgn:placetype":[
        "aat:300008347"
    ]
},
  "bbox": [],
  "geometry": {"coordinates":[-79.05,33.5167],"type":"Point"}
}
=======
{"geometry":{"type":"Point","coordinates":[-79.050000,33.516700]},"type":"Feature","properties":{"hierarchy":["tgn:2407360","tgn:1000001","tgn:2001746","tgn:7012149","tgn:7007712","tgn:7029392"],"placetype":["aat:300008347"],"id":2407360,"name:xx":"Huntington Marsh"}}
>>>>>>> 03f74aca74312dbeaf24d7e61306dd6a786dc3d0
