<<<<<<< HEAD
{
  "id": 2333692,
  "type": "Feature",
  "properties": {
    "tgn:hierarchy":[
        "tgn:2333692",
        "tgn:7006450",
        "tgn:1000001",
        "tgn:7012149",
        "tgn:2000082",
        "tgn:7029392"
    ],
    "tgn:id":2333692,
    "tgn:name":"Fools Point",
    "tgn:placetype":[
        "aat:300008850"
    ]
},
  "bbox": [],
  "geometry": {"coordinates":[-130.1333,55.1667],"type":"Point"}
}
=======
{"geometry":{"type":"Point","coordinates":[-130.133300,55.166700]},"type":"Feature","properties":{"hierarchy":["tgn:2333692","tgn:7006450","tgn:1000001","tgn:7012149","tgn:2000082","tgn:7029392"],"placetype":["aat:300008850"],"id":2333692,"name:xx":"Fools Point"}}
>>>>>>> 03f74aca74312dbeaf24d7e61306dd6a786dc3d0
