{
  "id": 1062810,
  "type": "Feature",
  "properties": {
    "tgn:hierarchy":[
        "tgn:1062810",
        "tgn:1000003",
        "tgn:7003777",
        "tgn:1000097",
        "tgn:7029392"
    ],
    "tgn:id":1062810,
    "tgn:name":"Bergshamra",
    "tgn:placetype":[
        "aat:300008347"
    ]
},
  "bbox": [],
  "geometry": {"coordinates":[18.6667,59.6333],"type":"Point"}
}