{
  "id": 2459096,
  "type": "Feature",
  "properties": {
    "tgn:hierarchy":[
        "tgn:2459096",
        "tgn:1000001",
        "tgn:7012149",
        "tgn:7014589",
        "tgn:7007515",
        "tgn:7029392"
    ],
    "tgn:id":2459096,
    "tgn:name":"Little Pine Island",
    "tgn:placetype":[
        "aat:300008791"
    ]
},
  "bbox": [],
  "geometry": {"coordinates":[-67.6833,45.1667],"type":"Point"}
}