{
  "id": 2204173,
  "type": "Feature",
  "properties": {
    "tgn:hierarchy":[
        "tgn:2204173",
        "tgn:1000001",
        "tgn:7012149",
        "tgn:1002545",
        "tgn:7007157",
        "tgn:7029392"
    ],
    "tgn:id":2204173,
    "tgn:name":"Buena Vista Canyon",
    "tgn:placetype":[
        "aat:300008761"
    ]
},
  "bbox": [],
  "geometry": {"coordinates":[-117.9667,35.6833],"type":"Point"}
}