{
  "id": 7130381,
  "type": "Feature",
  "properties": {
    "tgn:hierarchy":[
        "tgn:7130381",
        "tgn:1000003",
        "tgn:7003684",
        "tgn:7000084",
        "tgn:7029392"
    ],
    "tgn:id":7130381,
    "tgn:name":"Marpingen",
    "tgn:placetype":[
        "aat:300008347"
    ]
},
  "bbox": [],
  "geometry": {"coordinates":[7.05,49.45],"type":"Point"}
}