{
  "id": 7421015,
  "type": "Feature",
  "properties": {
    "tgn:hierarchy":[
        "tgn:7421015",
        "tgn:1000001",
        "tgn:7005589",
        "tgn:7005560",
        "tgn:7029392"
    ],
    "tgn:id":7421015,
    "tgn:name:es":"El Miguelito",
    "tgn:placetype":[
        "aat:300008347"
    ]
},
  "bbox": [],
  "geometry": {"coordinates":[-99.916389,25.514167],"type":"Point"}
}