{
  "id": 2513612,
  "type": "Feature",
  "properties": {
    "tgn:hierarchy":[
        "tgn:2513612",
        "tgn:1000001",
        "tgn:2001331",
        "tgn:7012149",
        "tgn:7007525",
        "tgn:7029392"
    ],
    "tgn:id":2513612,
    "tgn:name":"Mill Pond",
    "tgn:placetype":[
        "aat:300008680"
    ]
},
  "bbox": [],
  "geometry": {"coordinates":[-100.55,42.8833],"type":"Point"}
}