{
  "id": 2704734,
  "type": "Feature",
  "properties": {
    "tgn:hierarchy":[
        "tgn:2704734",
        "tgn:1000001",
        "tgn:7012149",
        "tgn:7007157",
        "tgn:2000188",
        "tgn:7029392"
    ],
    "tgn:id":2704734,
    "tgn:name":"Sunset Gulch",
    "tgn:placetype":[
        "aat:300008761"
    ]
},
  "bbox": [],
  "geometry": {"coordinates":[-121.7333,40.65],"type":"Point"}
}