{
  "id": 2195098,
  "type": "Feature",
  "properties": {
    "tgn:hierarchy":[
        "tgn:2195098",
        "tgn:1000001",
        "tgn:7012149",
        "tgn:1002797",
        "tgn:7007706",
        "tgn:7029392"
    ],
    "tgn:id":2195098,
    "tgn:name":"Brimfield Station",
    "tgn:placetype":[
        "aat:300008347"
    ]
},
  "bbox": [],
  "geometry": {"coordinates":[-81.3667,41.0833],"type":"Point"}
}