{
  "id": 2302084,
  "type": "Feature",
  "properties": {
    "tgn:hierarchy":[
        "tgn:2302084",
        "tgn:1000001",
        "tgn:1002219",
        "tgn:7012149",
        "tgn:7007157",
        "tgn:7029392"
    ],
    "tgn:id":2302084,
    "tgn:name":"Dutch Creek",
    "tgn:placetype":[
        "aat:300008706"
    ]
},
  "bbox": [],
  "geometry": {"coordinates":[-120.3667,38.3667],"type":"Point"}
}