<<<<<<< HEAD
{
  "id": 2401114,
  "type": "Feature",
  "properties": {
    "tgn:hierarchy":[
        "tgn:2401114",
        "tgn:1000001",
        "tgn:7012149",
        "tgn:7007157",
        "tgn:2000188",
        "tgn:7029392"
    ],
    "tgn:id":2401114,
    "tgn:name":"Horsebone Ridge",
    "tgn:placetype":[
        "aat:300266640"
    ]
},
  "bbox": [],
  "geometry": {"coordinates":[-122.5333,40.9],"type":"Point"}
}
=======
{"geometry":{"type":"Point","coordinates":[-122.533300,40.900000]},"type":"Feature","properties":{"hierarchy":["tgn:2401114","tgn:1000001","tgn:7012149","tgn:7007157","tgn:2000188","tgn:7029392"],"placetype":["aat:300266640"],"id":2401114,"name:xx":"Horsebone Ridge"}}
>>>>>>> 03f74aca74312dbeaf24d7e61306dd6a786dc3d0
