{
  "id": 2591339,
  "type": "Feature",
  "properties": {
    "tgn:hierarchy":[
        "tgn:2591339",
        "tgn:1000001",
        "tgn:2000779",
        "tgn:7012149",
        "tgn:7007255",
        "tgn:7029392"
    ],
    "tgn:id":2591339,
    "tgn:name":"Polly Ridge",
    "tgn:placetype":[
        "aat:300266640"
    ]
},
  "bbox": [],
  "geometry": {"coordinates":[-84.95,37.1667],"type":"Point"}
}