{
  "id": 7492461,
  "type": "Feature",
  "properties": {
    "tgn:hierarchy":[
        "tgn:7492461",
        "tgn:1000004",
        "tgn:7001014",
        "tgn:1000141",
        "tgn:7029392"
    ],
    "tgn:id":7492461,
    "tgn:name":"Siguliao",
    "tgn:placetype":[
        "aat:300008347"
    ]
},
  "bbox": [],
  "geometry": {"coordinates":[120.3521,23.627326],"type":"Point"}
}