<<<<<<< HEAD
{
  "id": 2766870,
  "type": "Feature",
  "properties": {
    "tgn:hierarchy":[
        "tgn:2766870",
        "tgn:1000001",
        "tgn:7012149",
        "tgn:2002125",
        "tgn:7007827",
        "tgn:7029392"
    ],
    "tgn:id":2766870,
    "tgn:name":"White Pine Hollow",
    "tgn:placetype":[
        "aat:300008761"
    ]
},
  "bbox": [],
  "geometry": {"coordinates":[-111.7,39.8333],"type":"Point"}
}
=======
{"geometry":{"type":"Point","coordinates":[-111.700000,39.833300]},"type":"Feature","properties":{"hierarchy":["tgn:2766870","tgn:1000001","tgn:7012149","tgn:2002125","tgn:7007827","tgn:7029392"],"placetype":["aat:300008761"],"id":2766870,"name:xx":"White Pine Hollow"}}
>>>>>>> 03f74aca74312dbeaf24d7e61306dd6a786dc3d0
