{
  "id": 7590585,
  "type": "Feature",
  "properties": {
    "tgn:hierarchy":[
        "tgn:7590585",
        "tgn:1000004",
        "tgn:7000198",
        "tgn:7000799",
        "tgn:7029392"
    ],
    "tgn:id":7590585,
    "tgn:name:en":"Sum\u0101n",
    "tgn:placetype":[
        "aat:300008347"
    ]
},
  "bbox": [],
  "geometry": {"coordinates":[74.347685,33.812975],"type":"Point"}
}