{
  "id": 7062134,
  "type": "Feature",
  "properties": {
    "tgn:hierarchy":[
        "tgn:7062134",
        "tgn:7003669",
        "tgn:1000003",
        "tgn:7000084",
        "tgn:7029392"
    ],
    "tgn:id":7062134,
    "tgn:name":"Bachham",
    "tgn:placetype":[
        "aat:300000206"
    ]
},
  "bbox": [],
  "geometry": {"coordinates":[12.366667,48.233333],"type":"Point"}
}