{
  "id": 2687939,
  "type": "Feature",
  "properties": {
    "tgn:hierarchy":[
        "tgn:2687939",
        "tgn:7013272",
        "tgn:1000001",
        "tgn:7012149",
        "tgn:7007710",
        "tgn:7029392"
    ],
    "tgn:id":2687939,
    "tgn:name":"Springdale Lake",
    "tgn:placetype":[
        "aat:300006191"
    ]
},
  "bbox": [],
  "geometry": {"coordinates":[-79.7833,40.55],"type":"Point"}
}