{
  "id": 2353133,
  "type": "Feature",
  "properties": {
    "tgn:hierarchy":[
        "tgn:2353133",
        "tgn:1000001",
        "tgn:7012149",
        "tgn:7013867",
        "tgn:7007710",
        "tgn:7029392"
    ],
    "tgn:id":2353133,
    "tgn:name":"Goff Run",
    "tgn:placetype":[
        "aat:300008699"
    ]
},
  "bbox": [],
  "geometry": {"coordinates":[-76.2167,39.8833],"type":"Point"}
}