{
  "id": 2254667,
  "type": "Feature",
  "properties": {
    "tgn:hierarchy":[
        "tgn:2254667",
        "tgn:1000001",
        "tgn:7012149",
        "tgn:2001027",
        "tgn:7007521",
        "tgn:7029392"
    ],
    "tgn:id":2254667,
    "tgn:name":"Coon Lake",
    "tgn:placetype":[
        "aat:300008680"
    ]
},
  "bbox": [],
  "geometry": {"coordinates":[-94.85,47.0167],"type":"Point"}
}