{
  "id": 2420812,
  "type": "Feature",
  "properties": {
    "tgn:hierarchy":[
        "tgn:2420812",
        "tgn:1000001",
        "tgn:7012149",
        "tgn:7014185",
        "tgn:7007710",
        "tgn:7029392"
    ],
    "tgn:id":2420812,
    "tgn:name":"Jennings Run",
    "tgn:placetype":[
        "aat:300008699"
    ]
},
  "bbox": [],
  "geometry": {"coordinates":[-79.7667,39.8833],"type":"Point"}
}