{
  "id": 7220236,
  "type": "Feature",
  "properties": {
    "tgn:hierarchy":[
        "tgn:7220236",
        "tgn:7011330",
        "tgn:7002674",
        "tgn:1000003",
        "tgn:1000074",
        "tgn:7029392"
    ],
    "tgn:id":7220236,
    "tgn:name":"Limen\u00e1ri, \u00d3rmos",
    "tgn:placetype":[
        "aat:300132316"
    ]
},
  "bbox": [],
  "geometry": {"coordinates":[27.3075,36.419444],"type":"Point"}
}