{
  "id": 2166926,
  "type": "Feature",
  "properties": {
    "tgn:hierarchy":[
        "tgn:2166926",
        "tgn:1000001",
        "tgn:7012149",
        "tgn:2001553",
        "tgn:7007709",
        "tgn:7029392"
    ],
    "tgn:id":2166926,
    "tgn:name":"Big Bugaboo Creek",
    "tgn:placetype":[
        "aat:300008706"
    ]
},
  "bbox": [],
  "geometry": {"coordinates":[-80.9667,36.3167],"type":"Point"}
}