<<<<<<< HEAD
{
  "id": 7052132,
  "type": "Feature",
  "properties": {
    "tgn:hierarchy":[
        "tgn:7052132",
        "tgn:7003163",
        "tgn:1000003",
        "tgn:7009760",
        "tgn:1000080",
        "tgn:7029392"
    ],
    "tgn:id":7052132,
    "tgn:name":"La Cava",
    "tgn:placetype":[
        "aat:300008347"
    ]
},
  "bbox": [],
  "geometry": {"coordinates":[10.866667,43.5],"type":"Point"}
}
=======
{"geometry":{"type":"Point","coordinates":[10.866667,43.500000]},"type":"Feature","properties":{"hierarchy":["tgn:7052132","tgn:7003163","tgn:1000003","tgn:7009760","tgn:1000080","tgn:7029392"],"placetype":["aat:300008347"],"id":7052132,"name:xx":"La Cava"}}
>>>>>>> 03f74aca74312dbeaf24d7e61306dd6a786dc3d0
