{
  "id": 1088686,
  "type": "Feature",
  "properties": {
    "tgn:hierarchy":[
        "tgn:1088686",
        "tgn:7001242",
        "tgn:1001023",
        "tgn:1000158",
        "tgn:7029392"
    ],
    "tgn:id":1088686,
    "tgn:name":"Masa",
    "tgn:placetype":[
        "aat:300008347"
    ]
},
  "bbox": [],
  "geometry": {"coordinates":[15.4833,-3.75],"type":"Point"}
}