{
  "id": 1084455,
  "type": "Feature",
  "properties": {
    "tgn:hierarchy":[
        "tgn:1084455",
        "tgn:1000004",
        "tgn:1001185",
        "tgn:1000135",
        "tgn:7029392"
    ],
    "tgn:id":1084455,
    "tgn:name":"Medellin",
    "tgn:placetype":[
        "aat:300008347"
    ]
},
  "bbox": [],
  "geometry": {"coordinates":[123.95,11.1333],"type":"Point"}
}