{
  "id": 7146590,
  "type": "Feature",
  "properties": {
    "tgn:hierarchy":[
        "tgn:7146590",
        "tgn:7000096",
        "tgn:1000003",
        "tgn:7000084",
        "tgn:7029392"
    ],
    "tgn:id":7146590,
    "tgn:name":"Kopplin",
    "tgn:placetype":[
        "aat:300008347"
    ]
},
  "bbox": [],
  "geometry": {"coordinates":[13.916667,52.116667],"type":"Point"}
}