{
  "id": 7292455,
  "type": "Feature",
  "properties": {
    "tgn:hierarchy":[
        "tgn:7292455",
        "tgn:1001702",
        "tgn:1000049",
        "tgn:1000002",
        "tgn:7029392"
    ],
    "tgn:id":7292455,
    "tgn:name":"Elena, Caleta",
    "tgn:placetype":[
        "aat:300132317"
    ]
},
  "bbox": [],
  "geometry": {"coordinates":[-74.483333,-49.75],"type":"Point"}
}