{
  "id": 2379932,
  "type": "Feature",
  "properties": {
    "tgn:hierarchy":[
        "tgn:2379932",
        "tgn:1000001",
        "tgn:7012149",
        "tgn:2002251",
        "tgn:7007920",
        "tgn:7029392"
    ],
    "tgn:id":2379932,
    "tgn:name":"Hatch",
    "tgn:placetype":[
        "aat:300008347"
    ]
},
  "bbox": [],
  "geometry": {"coordinates":[-118.6667,46.2667],"type":"Point"}
}