{
  "id": 7216351,
  "type": "Feature",
  "properties": {
    "tgn:hierarchy":[
        "tgn:7216351",
        "tgn:7003669",
        "tgn:1000003",
        "tgn:7000084",
        "tgn:7029392"
    ],
    "tgn:id":7216351,
    "tgn:name":"Aidenau",
    "tgn:placetype":[
        "aat:300008347"
    ]
},
  "bbox": [],
  "geometry": {"coordinates":[10.266667,49.366667],"type":"Point"}
}