{
  "id": 1110626,
  "type": "Feature",
  "properties": {
    "tgn:hierarchy":[
        "tgn:1110626",
        "tgn:7003025",
        "tgn:1000003",
        "tgn:1000062",
        "tgn:7029392"
    ],
    "tgn:id":1110626,
    "tgn:name":"Wiener Berg",
    "tgn:placetype":[
        "aat:300008777"
    ]
},
  "bbox": [],
  "geometry": {"coordinates":[16.3667,48.1667],"type":"Point"}
}