<<<<<<< HEAD
{
  "id": 2159530,
  "type": "Feature",
  "properties": {
    "tgn:hierarchy":[
        "tgn:2159530",
        "tgn:1000001",
        "tgn:7006451",
        "tgn:7012149",
        "tgn:2000097",
        "tgn:7029392"
    ],
    "tgn:id":2159530,
    "tgn:name":"Bee Mountain",
    "tgn:placetype":[
        "aat:300008798"
    ]
},
  "bbox": [],
  "geometry": {"coordinates":[-111.6167,33.7667],"type":"Point"}
}
=======
{"geometry":{"type":"Point","coordinates":[-111.616700,33.766700]},"type":"Feature","properties":{"hierarchy":["tgn:2159530","tgn:1000001","tgn:7006451","tgn:7012149","tgn:2000097","tgn:7029392"],"placetype":["aat:300008798"],"id":2159530,"name:xx":"Bee Mountain"}}
>>>>>>> 03f74aca74312dbeaf24d7e61306dd6a786dc3d0
