{
  "id": 7475405,
  "type": "Feature",
  "properties": {
    "tgn:hierarchy":[
        "tgn:7475405",
        "tgn:1000004",
        "tgn:7467799",
        "tgn:1000141",
        "tgn:7029392"
    ],
    "tgn:id":7475405,
    "tgn:name":"Weicuo Cun",
    "tgn:placetype":[
        "aat:300387173"
    ]
},
  "bbox": [],
  "geometry": {"coordinates":[120.4991,23.8554],"type":"Point"}
}