<<<<<<< HEAD
{
  "id": 7475405,
  "type": "Feature",
  "properties": {
    "tgn:hierarchy":[
        "tgn:7475405",
        "tgn:1000004",
        "tgn:7467799",
        "tgn:1000141",
        "tgn:7029392"
    ],
    "tgn:id":7475405,
    "tgn:name":"Weicuo Cun",
    "tgn:placetype":[
        "aat:300387173"
    ]
},
  "bbox": [],
  "geometry": {"coordinates":[120.4991,23.8554],"type":"Point"}
}
=======
{"geometry":{"type":"Point","coordinates":[120.499100,23.855400]},"type":"Feature","properties":{"hierarchy":["tgn:7475405","tgn:1000004","tgn:7467799","tgn:1000141","tgn:7029392"],"placetype":["aat:300387173"],"id":7475405,"name:xx":"Weicuo Cun"}}
>>>>>>> 03f74aca74312dbeaf24d7e61306dd6a786dc3d0
