{
  "id": 7218257,
  "type": "Feature",
  "properties": {
    "tgn:hierarchy":[
        "tgn:7218257",
        "tgn:7011163",
        "tgn:7002674",
        "tgn:1000003",
        "tgn:1000074",
        "tgn:7029392"
    ],
    "tgn:id":7218257,
    "tgn:name":"Avl\u00e1ki, \u00cdfaloi",
    "tgn:placetype":[
        "aat:300011692"
    ]
},
  "bbox": [],
  "geometry": {"coordinates":[25.027778,39.547222],"type":"Point"}
}