{
  "id": 7592957,
  "type": "Feature",
  "properties": {
    "tgn:hierarchy":[
        "tgn:7592957",
        "tgn:1000004",
        "tgn:7000198",
        "tgn:7000799",
        "tgn:7029392"
    ],
    "tgn:id":7592957,
    "tgn:name:en":"Thatthar",
    "tgn:placetype":[
        "aat:300008347"
    ]
},
  "bbox": [],
  "geometry": {"coordinates":[74.828407,32.793794],"type":"Point"}
}