{
  "id": 2597585,
  "type": "Feature",
  "properties": {
    "tgn:hierarchy":[
        "tgn:2597585",
        "tgn:1000001",
        "tgn:7016172",
        "tgn:7012149",
        "tgn:7029392"
    ],
    "tgn:id":2597585,
    "tgn:name":"Prairie, The",
    "tgn:placetype":[
        "aat:300055621"
    ]
},
  "bbox": [],
  "geometry": {"coordinates":[-91.9667,33.5667],"type":"Point"}
}