{
  "id": 2236294,
  "type": "Feature",
  "properties": {
    "tgn:hierarchy":[
        "tgn:2236294",
        "tgn:1000001",
        "tgn:7012149",
        "tgn:1002723",
        "tgn:7007252",
        "tgn:7029392"
    ],
    "tgn:id":2236294,
    "tgn:name":"Chicken Coop Island",
    "tgn:placetype":[
        "aat:300008791"
    ]
},
  "bbox": [],
  "geometry": {"coordinates":[-85.3333,41.4667],"type":"Point"}
}