{
  "id": 7272476,
  "type": "Feature",
  "properties": {
    "tgn:concordances":{
        "gn:id":"2745502"
    },
    "tgn:hierarchy":[
        "tgn:7272476",
        "tgn:1000003",
        "tgn:7003624",
        "tgn:7016845",
        "tgn:7029392"
    ],
    "tgn:id":7272476,
    "tgn:name:nl":"Vinkenberg",
    "tgn:placetype":[
        "aat:300008347"
    ]
},
  "bbox": [],
  "geometry": {"coordinates":[5.183333,51.533333],"type":"Point"}
}