{
  "id": 7491331,
  "type": "Feature",
  "properties": {
    "tgn:hierarchy":[
        "tgn:7491331",
        "tgn:1000004",
        "tgn:7492971",
        "tgn:1000141",
        "tgn:7029392"
    ],
    "tgn:id":7491331,
    "tgn:name":"Santai Shan",
    "tgn:placetype":[
        "aat:300008798"
    ]
},
  "bbox": [],
  "geometry": {"coordinates":[120.772222,22.024722],"type":"Point"}
}