{
  "id": 1010947,
  "type": "Feature",
  "properties": {
    "tgn:hierarchy":[
        "tgn:1010947",
        "tgn:7001242",
        "tgn:7016833",
        "tgn:7001336",
        "tgn:7029392"
    ],
    "tgn:id":1010947,
    "tgn:name":"Misallah, Ra's",
    "tgn:placetype":[
        "aat:300008850"
    ]
},
  "bbox": [],
  "geometry": {"coordinates":[32.612721,29.821585],"type":"Point"}
}