{
  "id": 2624796,
  "type": "Feature",
  "properties": {
    "tgn:hierarchy":[
        "tgn:2624796",
        "tgn:1000001",
        "tgn:7012149",
        "tgn:2002127",
        "tgn:7007827",
        "tgn:7029392"
    ],
    "tgn:id":2624796,
    "tgn:name":"Rock Spring",
    "tgn:placetype":[
        "aat:300008697"
    ]
},
  "bbox": [],
  "geometry": {"coordinates":[-113.1667,37.3333],"type":"Point"}
}