{
  "id": 1112453,
  "type": "Feature",
  "properties": {
    "tgn:hierarchy":[
        "tgn:1112453",
        "tgn:1000003",
        "tgn:7594273",
        "tgn:1000070",
        "tgn:7029392"
    ],
    "tgn:id":1112453,
    "tgn:name":"Porto-Vecchio, Golfe de",
    "tgn:placetype":[
        "aat:300132315"
    ]
},
  "bbox": [],
  "geometry": {"coordinates":[9.4833,41.4667],"type":"Point"}
}