{
  "id": 7553880,
  "type": "Feature",
  "properties": {
    "tgn:hierarchy":[
        "tgn:7553880",
        "tgn:1000004",
        "tgn:7000198",
        "tgn:1001895",
        "tgn:7029392"
    ],
    "tgn:id":7553880,
    "tgn:name:en":"M\u0101legaon",
    "tgn:placetype":[
        "aat:300008347"
    ]
},
  "bbox": [],
  "geometry": {"coordinates":[76.983333,20.25],"type":"Point"}
}