{
  "id": 7546470,
  "type": "Feature",
  "properties": {
    "tgn:hierarchy":[
        "tgn:7546470",
        "tgn:1000004",
        "tgn:1001832",
        "tgn:7000198",
        "tgn:7029392"
    ],
    "tgn:id":7546470,
    "tgn:name:en":"Balagaon",
    "tgn:placetype":[
        "aat:300008347"
    ]
},
  "bbox": [],
  "geometry": {"coordinates":[91.330922,26.132251],"type":"Point"}
}