<<<<<<< HEAD
{
  "id": 7026326,
  "type": "Feature",
  "properties": {
    "tgn:hierarchy":[
        "tgn:7026326",
        "tgn:7002445",
        "tgn:1000003",
        "tgn:7008131",
        "tgn:7008591",
        "tgn:7029392"
    ],
    "tgn:id":7026326,
    "tgn:name":"South Fambridge",
    "tgn:placetype":[
        "aat:300008347"
    ]
},
  "bbox": [],
  "geometry": {"coordinates":[0.6833,51.6333],"type":"Point"}
}
=======
{"geometry":{"type":"Point","coordinates":[0.683300,51.633300]},"type":"Feature","properties":{"hierarchy":["tgn:7026326","tgn:7002445","tgn:1000003","tgn:7008131","tgn:7008591","tgn:7029392"],"placetype":["aat:300008347"],"id":7026326,"name:xx":"South Fambridge"}}
>>>>>>> 03f74aca74312dbeaf24d7e61306dd6a786dc3d0
