{
  "id": 2171086,
  "type": "Feature",
  "properties": {
    "tgn:hierarchy":[
        "tgn:2171086",
        "tgn:1000001",
        "tgn:7012149",
        "tgn:2001285",
        "tgn:7007524",
        "tgn:7029392"
    ],
    "tgn:id":2171086,
    "tgn:name":"Big Spring",
    "tgn:placetype":[
        "aat:300008697"
    ]
},
  "bbox": [],
  "geometry": {"coordinates":[-111.1167,48.8333],"type":"Point"}
}