{
  "id": 7033241,
  "type": "Feature",
  "properties": {
    "tgn:hierarchy":[
        "tgn:7033241",
        "tgn:7003129",
        "tgn:1000003",
        "tgn:7008516",
        "tgn:1000080",
        "tgn:7029392"
    ],
    "tgn:id":7033241,
    "tgn:name":"Bona",
    "tgn:placetype":[
        "aat:300008347"
    ]
},
  "bbox": [],
  "geometry": {"coordinates":[12.188056,44.045278],"type":"Point"}
}