{
  "id": 7551712,
  "type": "Feature",
  "properties": {
    "tgn:hierarchy":[
        "tgn:7551712",
        "tgn:1000004",
        "tgn:7000198",
        "tgn:7016722",
        "tgn:7029392"
    ],
    "tgn:id":7551712,
    "tgn:name:en":"Deai Tikar",
    "tgn:placetype":[
        "aat:300008347"
    ]
},
  "bbox": [],
  "geometry": {"coordinates":[81.065787,26.70556],"type":"Point"}
}