<<<<<<< HEAD
{
  "id": 2761702,
  "type": "Feature",
  "properties": {
    "tgn:hierarchy":[
        "tgn:2761702",
        "tgn:1000001",
        "tgn:7012149",
        "tgn:1002505",
        "tgn:7007920",
        "tgn:7029392"
    ],
    "tgn:id":2761702,
    "tgn:name":"West Point",
    "tgn:placetype":[
        "aat:300008850"
    ]
},
  "bbox": [],
  "geometry": {"coordinates":[-122.65,48.4],"type":"Point"}
}
=======
{"geometry":{"type":"Point","coordinates":[-122.650000,48.400000]},"type":"Feature","properties":{"hierarchy":["tgn:2761702","tgn:1000001","tgn:7012149","tgn:1002505","tgn:7007920","tgn:7029392"],"placetype":["aat:300008850"],"id":2761702,"name:xx":"West Point"}}
>>>>>>> 03f74aca74312dbeaf24d7e61306dd6a786dc3d0
