{
  "id": 7322329,
  "type": "Feature",
  "properties": {
    "tgn:hierarchy":[
        "tgn:7322329",
        "tgn:1001623",
        "tgn:1000049",
        "tgn:1000002",
        "tgn:7029392"
    ],
    "tgn:id":7322329,
    "tgn:name":"Arutti",
    "tgn:placetype":[
        "aat:300004792"
    ]
},
  "bbox": [],
  "geometry": {"coordinates":[-72.483333,-47.45],"type":"Point"}
}