{
  "id": 1087554,
  "type": "Feature",
  "properties": {
    "tgn:hierarchy":[
        "tgn:1087554",
        "tgn:7001242",
        "tgn:7016752",
        "tgn:1000693",
        "tgn:7029392"
    ],
    "tgn:id":1087554,
    "tgn:name":"Sidi Ali",
    "tgn:placetype":[
        "aat:300008347"
    ]
},
  "bbox": [],
  "geometry": {"coordinates":[0.4167,36.1167],"type":"Point"}
}