{
  "id": 7565783,
  "type": "Feature",
  "properties": {
    "tgn:hierarchy":[
        "tgn:7565783",
        "tgn:1000004",
        "tgn:7000198",
        "tgn:7016722",
        "tgn:7029392"
    ],
    "tgn:id":7565783,
    "tgn:name:en":"Lah\u016bra",
    "tgn:placetype":[
        "aat:300008347"
    ]
},
  "bbox": [],
  "geometry": {"coordinates":[79.45962,26.066901],"type":"Point"}
}