{
  "id": 7592954,
  "type": "Feature",
  "properties": {
    "tgn:hierarchy":[
        "tgn:7592954",
        "tgn:1000004",
        "tgn:7000198",
        "tgn:7000799",
        "tgn:7029392"
    ],
    "tgn:id":7592954,
    "tgn:name:en":"Dam\u0101na",
    "tgn:placetype":[
        "aat:300008347"
    ]
},
  "bbox": [],
  "geometry": {"coordinates":[74.786623,32.791542],"type":"Point"}
}