{
  "id": 2505353,
  "type": "Feature",
  "properties": {
    "tgn:hierarchy":[
        "tgn:2505353",
        "tgn:1000001",
        "tgn:7016172",
        "tgn:7012149",
        "tgn:2000163",
        "tgn:7029392"
    ],
    "tgn:id":2505353,
    "tgn:name":"Mellon Branch",
    "tgn:placetype":[
        "aat:300008699"
    ]
},
  "bbox": [],
  "geometry": {"coordinates":[-91.6333,34.8333],"type":"Point"}
}