{
  "id": 1005977,
  "type": "Feature",
  "properties": {
    "tgn:hierarchy":[
        "tgn:1005977",
        "tgn:1000003",
        "tgn:7007809",
        "tgn:7024114",
        "tgn:7006366",
        "tgn:7029392"
    ],
    "tgn:id":1005977,
    "tgn:name":"Zdroje",
    "tgn:placetype":[
        "aat:300000745"
    ]
},
  "bbox": [],
  "geometry": {"coordinates":[14.6333,53.3833],"type":"Point"}
}