{
  "id": 7071481,
  "type": "Feature",
  "properties": {
    "tgn:hierarchy":[
        "tgn:7071481",
        "tgn:7003712",
        "tgn:7003670",
        "tgn:1000003",
        "tgn:7000084",
        "tgn:7029392"
    ],
    "tgn:id":7071481,
    "tgn:name":"F\u00f6rsterei Tegelsee",
    "tgn:placetype":[
        "aat:300387503",
        "aat:300004792"
    ]
},
  "bbox": [],
  "geometry": {"coordinates":[13.25,52.583333],"type":"Point"}
}