{
  "id": 2273718,
  "type": "Feature",
  "properties": {
    "tgn:hierarchy":[
        "tgn:2273718",
        "tgn:1000001",
        "tgn:7012149",
        "tgn:2001310",
        "tgn:7007524",
        "tgn:7029392"
    ],
    "tgn:id":2273718,
    "tgn:name":"D Ratzburg Reservoir",
    "tgn:placetype":[
        "aat:300006191"
    ]
},
  "bbox": [],
  "geometry": {"coordinates":[-111.5833,48.25],"type":"Point"}
}