{
  "id": 2699558,
  "type": "Feature",
  "properties": {
    "tgn:hierarchy":[
        "tgn:2699558",
        "tgn:1000001",
        "tgn:7012149",
        "tgn:1002484",
        "tgn:7007826",
        "tgn:7029392"
    ],
    "tgn:id":2699558,
    "tgn:name":"Strouds Creek",
    "tgn:placetype":[
        "aat:300008706"
    ]
},
  "bbox": [],
  "geometry": {"coordinates":[-97.95,32.4167],"type":"Point"}
}