{
  "id": 2712965,
  "type": "Feature",
  "properties": {
    "tgn:hierarchy":[
        "tgn:2712965",
        "tgn:1000001",
        "tgn:7012149",
        "tgn:7007157",
        "tgn:1002608",
        "tgn:7029392"
    ],
    "tgn:id":2712965,
    "tgn:name":"Taylor Junction",
    "tgn:placetype":[
        "aat:300008347"
    ]
},
  "bbox": [],
  "geometry": {"coordinates":[-118.2167,34.05],"type":"Point"}
}