{
  "id": 2566092,
  "type": "Feature",
  "properties": {
    "tgn:hierarchy":[
        "tgn:2566092",
        "tgn:1000001",
        "tgn:7012149",
        "tgn:2000975",
        "tgn:7007520",
        "tgn:7029392"
    ],
    "tgn:id":2566092,
    "tgn:name":"Palmer Lake",
    "tgn:placetype":[
        "aat:300008680"
    ]
},
  "bbox": [],
  "geometry": {"coordinates":[-87.6167,46.4333],"type":"Point"}
}