{
  "id": 7029903,
  "type": "Feature",
  "properties": {
    "tgn:hierarchy":[
        "tgn:7029903",
        "tgn:7002445",
        "tgn:1000003",
        "tgn:7008166",
        "tgn:7008591",
        "tgn:7029392"
    ],
    "tgn:id":7029903,
    "tgn:name":"Camblesforth",
    "tgn:placetype":[
        "aat:300008347",
        "aat:300008372"
    ]
},
  "bbox": [],
  "geometry": {"coordinates":[-1.016,53.718],"type":"Point"}
}