{
  "id": 2059969,
  "type": "Feature",
  "properties": {
    "tgn:hierarchy":[
        "tgn:2059969",
        "tgn:1000001",
        "tgn:7012149",
        "tgn:2001252",
        "tgn:7007523",
        "tgn:7029392"
    ],
    "tgn:id":2059969,
    "tgn:name":"Old Success",
    "tgn:placetype":[
        "aat:300008347",
        "aat:300387210"
    ]
},
  "bbox": [],
  "geometry": {"coordinates":[-92.0833,37.45],"type":"Point"}
}