{
  "id": 2727789,
  "type": "Feature",
  "properties": {
    "tgn:hierarchy":[
        "tgn:2727789",
        "tgn:1000001",
        "tgn:7012149",
        "tgn:2001306",
        "tgn:7007524",
        "tgn:7029392"
    ],
    "tgn:id":2727789,
    "tgn:name":"Trainer Gulch",
    "tgn:placetype":[
        "aat:300008761"
    ]
},
  "bbox": [],
  "geometry": {"coordinates":[-112.4167,45.8167],"type":"Point"}
}