{
  "id": 1085637,
  "type": "Feature",
  "properties": {
    "tgn:hierarchy":[
        "tgn:1085637",
        "tgn:7005194",
        "tgn:1000004",
        "tgn:7000947",
        "tgn:1000142",
        "tgn:7029392"
    ],
    "tgn:id":1085637,
    "tgn:name":"Phitsanulok",
    "tgn:placetype":[
        "aat:300008347",
        "aat:300387223",
        "aat:300008375",
        "aat:300387270"
    ]
},
  "bbox": [],
  "geometry": {"coordinates":[100.25,16.8333],"type":"Point"}
}