{
  "id": 7164139,
  "type": "Feature",
  "properties": {
    "tgn:hierarchy":[
        "tgn:7164139",
        "tgn:7003669",
        "tgn:1000003",
        "tgn:7000084",
        "tgn:7029392"
    ],
    "tgn:id":7164139,
    "tgn:name":"Hubbr\u00e4nde",
    "tgn:placetype":[
        "aat:300000206"
    ]
},
  "bbox": [],
  "geometry": {"coordinates":[10.166667,47.783333],"type":"Point"}
}