{
  "id": 1010615,
  "type": "Feature",
  "properties": {
    "tgn:hierarchy":[
        "tgn:1010615",
        "tgn:1000003",
        "tgn:1000070",
        "tgn:7002895",
        "tgn:7029392"
    ],
    "tgn:id":1010615,
    "tgn:name":"Croisette, Cap",
    "tgn:placetype":[
        "aat:300008850"
    ]
},
  "bbox": [],
  "geometry": {"coordinates":[5.3333,43.2167],"type":"Point"}
}