{
  "id": 2617893,
  "type": "Feature",
  "properties": {
    "tgn:hierarchy":[
        "tgn:2617893",
        "tgn:1000001",
        "tgn:2000327",
        "tgn:7012149",
        "tgn:7007248",
        "tgn:7029392"
    ],
    "tgn:id":2617893,
    "tgn:name":"Ridge Point",
    "tgn:placetype":[
        "aat:300008347"
    ]
},
  "bbox": [],
  "geometry": {"coordinates":[-82.1167,33.4667],"type":"Point"}
}