<<<<<<< HEAD
{
  "id": 2405175,
  "type": "Feature",
  "properties": {
    "tgn:hierarchy":[
        "tgn:2405175",
        "tgn:1000001",
        "tgn:7006451",
        "tgn:2000092",
        "tgn:7012149",
        "tgn:7029392"
    ],
    "tgn:id":2405175,
    "tgn:name":"Huethawali, Mount",
    "tgn:placetype":[
        "aat:300008798"
    ]
},
  "bbox": [],
  "geometry": {"coordinates":[-112.3667,36.2],"type":"Point"}
}
=======
{"geometry":{"type":"Point","coordinates":[-112.366700,36.200000]},"type":"Feature","properties":{"hierarchy":["tgn:2405175","tgn:1000001","tgn:7006451","tgn:2000092","tgn:7012149","tgn:7029392"],"placetype":["aat:300008798"],"id":2405175,"name:xx":"Huethawali, Mount"}}
>>>>>>> 03f74aca74312dbeaf24d7e61306dd6a786dc3d0
