{
  "id": 7432086,
  "type": "Feature",
  "properties": {
    "tgn:hierarchy":[
        "tgn:7432086",
        "tgn:1001853",
        "tgn:1000001",
        "tgn:7005560",
        "tgn:7029392"
    ],
    "tgn:id":7432086,
    "tgn:name":"Castillo",
    "tgn:placetype":[
        "aat:300008347"
    ]
},
  "bbox": [],
  "geometry": {"coordinates":[-100.883333,29.25],"type":"Point"}
}