{
  "id": 7099045,
  "type": "Feature",
  "properties": {
    "tgn:hierarchy":[
        "tgn:7099045",
        "tgn:1000003",
        "tgn:7003676",
        "tgn:7000084",
        "tgn:7029392"
    ],
    "tgn:id":7099045,
    "tgn:name":"Spintenkamp",
    "tgn:placetype":[
        "aat:300000206"
    ]
},
  "bbox": [],
  "geometry": {"coordinates":[8.883333,53.416667],"type":"Point"}
}