{
  "id": 7214394,
  "type": "Feature",
  "properties": {
    "tgn:hierarchy":[
        "tgn:7214394",
        "tgn:7000096",
        "tgn:1000003",
        "tgn:7000084",
        "tgn:7029392"
    ],
    "tgn:id":7214394,
    "tgn:name":"Birkenheim",
    "tgn:placetype":[
        "aat:300008347"
    ]
},
  "bbox": [],
  "geometry": {"coordinates":[13.716667,52.483333],"type":"Point"}
}