{
  "id": 2547976,
  "type": "Feature",
  "properties": {
    "tgn:hierarchy":[
        "tgn:2547976",
        "tgn:1000001",
        "tgn:2001775",
        "tgn:7012149",
        "tgn:7007713",
        "tgn:7029392"
    ],
    "tgn:id":2547976,
    "tgn:name":"North Grove Addition",
    "tgn:placetype":[
        "aat:300008347"
    ]
},
  "bbox": [],
  "geometry": {"coordinates":[-96.7833,44.4167],"type":"Point"}
}