<<<<<<< HEAD
{
  "id": 7477291,
  "type": "Feature",
  "properties": {
    "tgn:hierarchy":[
        "tgn:7477291",
        "tgn:1000004",
        "tgn:1000454",
        "tgn:1000141",
        "tgn:7029392"
    ],
    "tgn:id":7477291,
    "tgn:name":"Shuangxi Guoxiao",
    "tgn:placetype":[
        "aat:300006495"
    ]
},
  "bbox": [],
  "geometry": {"coordinates":[121.8672,25.032914],"type":"Point"}
}
=======
{"geometry":{"type":"Point","coordinates":[121.867200,25.032914]},"type":"Feature","properties":{"hierarchy":["tgn:7477291","tgn:1000004","tgn:1000454","tgn:1000141","tgn:7029392"],"placetype":["aat:300006495"],"id":7477291,"name:xx":"Shuangxi Guoxiao"}}
>>>>>>> 03f74aca74312dbeaf24d7e61306dd6a786dc3d0
