{
  "id": 7477291,
  "type": "Feature",
  "properties": {
    "tgn:hierarchy":[
        "tgn:7477291",
        "tgn:1000004",
        "tgn:1000454",
        "tgn:1000141",
        "tgn:7029392"
    ],
    "tgn:id":7477291,
    "tgn:name":"Shuangxi Guoxiao",
    "tgn:placetype":[
        "aat:300006495"
    ]
},
  "bbox": [],
  "geometry": {"coordinates":[121.8672,25.032914],"type":"Point"}
}