{
  "id": 1129637,
  "type": "Feature",
  "properties": {
    "tgn:hierarchy":[
        "tgn:1129637",
        "tgn:1000001",
        "tgn:7029392"
    ],
    "tgn:id":1129637,
    "tgn:name":"Santa Cruz, R\u00edo de",
    "tgn:placetype":[
        "aat:300008707"
    ]
},
  "bbox": [],
  "geometry": {"coordinates":[-112.2333,33.3167],"type":"Point"}
}