{
  "id": 7554616,
  "type": "Feature",
  "properties": {
    "tgn:hierarchy":[
        "tgn:7554616",
        "tgn:1000004",
        "tgn:7000198",
        "tgn:7016694",
        "tgn:7029392"
    ],
    "tgn:id":7554616,
    "tgn:name:en":"Mendah",
    "tgn:placetype":[
        "aat:300008347"
    ]
},
  "bbox": [],
  "geometry": {"coordinates":[83.616667,20.833333],"type":"Point"}
}