{
  "id": 1077130,
  "type": "Feature",
  "properties": {
    "tgn:hierarchy":[
        "tgn:1077130",
        "tgn:1000004",
        "tgn:7000198",
        "tgn:1001977",
        "tgn:7029392"
    ],
    "tgn:id":1077130,
    "tgn:name":"Tapasi",
    "tgn:placetype":[
        "aat:300008347"
    ]
},
  "bbox": [],
  "geometry": {"coordinates":[87.1333,23.6667],"type":"Point"}
}