{
  "id": 2687423,
  "type": "Feature",
  "properties": {
    "tgn:hierarchy":[
        "tgn:2687423",
        "tgn:1000001",
        "tgn:7012149",
        "tgn:2001871",
        "tgn:7007825",
        "tgn:7029392"
    ],
    "tgn:id":2687423,
    "tgn:name":"Spring Lake",
    "tgn:placetype":[
        "aat:300006191"
    ]
},
  "bbox": [],
  "geometry": {"coordinates":[-89.0167,35.0333],"type":"Point"}
}