{
  "id": 7502398,
  "type": "Feature",
  "properties": {
    "tgn:hierarchy":[
        "tgn:7502398",
        "tgn:7001010",
        "tgn:1000004",
        "tgn:1000141",
        "tgn:7029392"
    ],
    "tgn:id":7502398,
    "tgn:name":"Zengchan Qiao",
    "tgn:placetype":[
        "aat:300007836"
    ]
},
  "bbox": [],
  "geometry": {"coordinates":[121.511667,23.605278],"type":"Point"}
}