{
  "id": 2661765,
  "type": "Feature",
  "properties": {
    "tgn:hierarchy":[
        "tgn:2661765",
        "tgn:7006450",
        "tgn:1000001",
        "tgn:2124053",
        "tgn:7012149",
        "tgn:7029392"
    ],
    "tgn:id":2661765,
    "tgn:name":"Shulin Lake",
    "tgn:placetype":[
        "aat:300008680"
    ]
},
  "bbox": [],
  "geometry": {"coordinates":[-150.85,62.1333],"type":"Point"}
}