{
  "id": 2595256,
  "type": "Feature",
  "properties": {
    "tgn:hierarchy":[
        "tgn:2595256",
        "tgn:1002338",
        "tgn:1000001",
        "tgn:7012149",
        "tgn:7007516",
        "tgn:7029392"
    ],
    "tgn:id":2595256,
    "tgn:name":"Pot Island Creek",
    "tgn:placetype":[
        "aat:300008706"
    ]
},
  "bbox": [],
  "geometry": {"coordinates":[-76.2333,38.3667],"type":"Point"}
}