<<<<<<< HEAD
{
  "id": 2157651,
  "type": "Feature",
  "properties": {
    "tgn:hierarchy":[
        "tgn:2157651",
        "tgn:1002933",
        "tgn:1000001",
        "tgn:7012149",
        "tgn:7007239",
        "tgn:7029392"
    ],
    "tgn:id":2157651,
    "tgn:name":"Beaver Dam Ditch",
    "tgn:placetype":[
        "aat:300006075"
    ]
},
  "bbox": [],
  "geometry": {"coordinates":[-75.1333,38.5167],"type":"Point"}
}
=======
{"geometry":{"type":"Point","coordinates":[-75.133300,38.516700]},"type":"Feature","properties":{"hierarchy":["tgn:2157651","tgn:1002933","tgn:1000001","tgn:7012149","tgn:7007239","tgn:7029392"],"placetype":["aat:300006075"],"id":2157651,"name:xx":"Beaver Dam Ditch"}}
>>>>>>> 03f74aca74312dbeaf24d7e61306dd6a786dc3d0
