{
  "id": 7322995,
  "type": "Feature",
  "properties": {
    "tgn:hierarchy":[
        "tgn:7322995",
        "tgn:7010420",
        "tgn:1000003",
        "tgn:7002795",
        "tgn:1000095",
        "tgn:7029392"
    ],
    "tgn:id":7322995,
    "tgn:name":"Saced\u00f3n, Arroyo del",
    "tgn:placetype":[
        "aat:300008699"
    ]
},
  "bbox": [],
  "geometry": {"coordinates":[-3.516667,40.766667],"type":"Point"}
}