{
  "id": 2677061,
  "type": "Feature",
  "properties": {
    "tgn:hierarchy":[
        "tgn:2677061",
        "tgn:1000001",
        "tgn:7012149",
        "tgn:7007516",
        "tgn:7029392"
    ],
    "tgn:id":2677061,
    "tgn:name":"South Branch Patapsco River",
    "tgn:placetype":[
        "aat:300008707"
    ]
},
  "bbox": [],
  "geometry": {"coordinates":[-77.1667,39.35],"type":"Point"}
}