{
  "id": 7406740,
  "type": "Feature",
  "properties": {
    "tgn:hierarchy":[
        "tgn:7406740",
        "tgn:1000001",
        "tgn:1001906",
        "tgn:7005560",
        "tgn:7029392"
    ],
    "tgn:id":7406740,
    "tgn:name":"El Cangrejo",
    "tgn:placetype":[
        "aat:300008347"
    ]
},
  "bbox": [],
  "geometry": {"coordinates":[-105.016667,22.433333],"type":"Point"}
}