{
  "id": 2371136,
  "type": "Feature",
  "properties": {
    "tgn:hierarchy":[
        "tgn:2371136",
        "tgn:1000001",
        "tgn:7012149",
        "tgn:2000287",
        "tgn:7007240",
        "tgn:7029392"
    ],
    "tgn:id":2371136,
    "tgn:name":"Hagens Cove",
    "tgn:placetype":[
        "aat:300132316"
    ]
},
  "bbox": [],
  "geometry": {"coordinates":[-83.5667,29.7667],"type":"Point"}
}