{
  "id": 2261976,
  "type": "Feature",
  "properties": {
    "tgn:hierarchy":[
        "tgn:2261976",
        "tgn:1000001",
        "tgn:7012149",
        "tgn:2002251",
        "tgn:7007920",
        "tgn:7029392"
    ],
    "tgn:id":2261976,
    "tgn:name":"Cow Bar Canyon",
    "tgn:placetype":[
        "aat:300008761"
    ]
},
  "bbox": [],
  "geometry": {"coordinates":[-118.4167,46.55],"type":"Point"}
}