{
  "id": 2529851,
  "type": "Feature",
  "properties": {
    "tgn:hierarchy":[
        "tgn:2529851",
        "tgn:1000001",
        "tgn:2002104",
        "tgn:7012149",
        "tgn:7007827",
        "tgn:7029392"
    ],
    "tgn:id":2529851,
    "tgn:name":"Mud Ridge",
    "tgn:placetype":[
        "aat:300266640"
    ]
},
  "bbox": [],
  "geometry": {"coordinates":[-111.2167,39.75],"type":"Point"}
}