{
  "id": 7196389,
  "type": "Feature",
  "properties": {
    "tgn:hierarchy":[
        "tgn:7196389",
        "tgn:1000003",
        "tgn:7003682",
        "tgn:7000084",
        "tgn:7029392"
    ],
    "tgn:id":7196389,
    "tgn:name":"Daun, Forst",
    "tgn:placetype":[
        "aat:300008863"
    ]
},
  "bbox": [],
  "geometry": {"coordinates":[6.666667,50.166667],"type":"Point"}
}