{
  "id": 2176879,
  "type": "Feature",
  "properties": {
    "tgn:hierarchy":[
        "tgn:2176879",
        "tgn:1000001",
        "tgn:7012149",
        "tgn:2001532",
        "tgn:7007709",
        "tgn:7029392"
    ],
    "tgn:id":2176879,
    "tgn:name":"Black Mountain",
    "tgn:placetype":[
        "aat:300008798"
    ]
},
  "bbox": [],
  "geometry": {"coordinates":[-79.95,35.5333],"type":"Point"}
}