{
  "id": 7163420,
  "type": "Feature",
  "properties": {
    "tgn:hierarchy":[
        "tgn:7163420",
        "tgn:1000003",
        "tgn:7003677",
        "tgn:7000084",
        "tgn:7029392"
    ],
    "tgn:id":7163420,
    "tgn:name":"Hufschenhof",
    "tgn:placetype":[
        "aat:300000206"
    ]
},
  "bbox": [],
  "geometry": {"coordinates":[6.05,51.833333],"type":"Point"}
}