<<<<<<< HEAD
{
  "id": 2337709,
  "type": "Feature",
  "properties": {
    "tgn:hierarchy":[
        "tgn:2337709",
        "tgn:1000001",
        "tgn:7012149",
        "tgn:7007157",
        "tgn:1002608",
        "tgn:7029392"
    ],
    "tgn:id":2337709,
    "tgn:name":"Fox Creek",
    "tgn:placetype":[
        "aat:300008706"
    ]
},
  "bbox": [],
  "geometry": {"coordinates":[-118.1667,34.3667],"type":"Point"}
}
=======
{"geometry":{"type":"Point","coordinates":[-118.166700,34.366700]},"type":"Feature","properties":{"hierarchy":["tgn:2337709","tgn:1000001","tgn:7012149","tgn:7007157","tgn:1002608","tgn:7029392"],"placetype":["aat:300008706"],"id":2337709,"name:xx":"Fox Creek"}}
>>>>>>> 03f74aca74312dbeaf24d7e61306dd6a786dc3d0
