{
  "id": 7244434,
  "type": "Feature",
  "properties": {
    "tgn:hierarchy":[
        "tgn:7244434",
        "tgn:7003457",
        "tgn:1000003",
        "tgn:1000063",
        "tgn:7018236",
        "tgn:7029392"
    ],
    "tgn:id":7244434,
    "tgn:name":"Keutelhoek",
    "tgn:placetype":[
        "aat:300008347"
    ]
},
  "bbox": [],
  "geometry": {"coordinates":[3.783333,50.983333],"type":"Point"}
}