{
  "id": 1031370,
  "type": "Feature",
  "properties": {
    "tgn:hierarchy":[
        "tgn:1031370",
        "tgn:7594381",
        "tgn:1000003",
        "tgn:1000069",
        "tgn:7029392"
    ],
    "tgn:id":1031370,
    "tgn:name":"Kerim\u00e4ki",
    "tgn:placetype":[
        "aat:300008347"
    ]
},
  "bbox": [],
  "geometry": {"coordinates":[29.2833,61.9167],"type":"Point"}
}