{
  "id": 2448032,
  "type": "Feature",
  "properties": {
    "tgn:hierarchy":[
        "tgn:2448032",
        "tgn:1000001",
        "tgn:1002289",
        "tgn:7012149",
        "tgn:7007240",
        "tgn:7029392"
    ],
    "tgn:id":2448032,
    "tgn:name":"Lighter Bay",
    "tgn:placetype":[
        "aat:300132316"
    ]
},
  "bbox": [],
  "geometry": {"coordinates":[-81.6167,25.9333],"type":"Point"}
}