{
  "id": 7158330,
  "type": "Feature",
  "properties": {
    "tgn:hierarchy":[
        "tgn:7158330",
        "tgn:1000003",
        "tgn:7003676",
        "tgn:7000084",
        "tgn:7029392"
    ],
    "tgn:id":7158330,
    "tgn:name":"Hoh-Berg",
    "tgn:placetype":[
        "aat:300008777"
    ]
},
  "bbox": [],
  "geometry": {"coordinates":[9.216667,51.983333],"type":"Point"}
}