{
  "id": 7382069,
  "type": "Feature",
  "properties": {
    "tgn:hierarchy":[
        "tgn:7382069",
        "tgn:1001853",
        "tgn:1000001",
        "tgn:7005560",
        "tgn:7029392"
    ],
    "tgn:id":7382069,
    "tgn:name":"Rancho Los Borrachos",
    "tgn:placetype":[
        "aat:300000241"
    ]
},
  "bbox": [],
  "geometry": {"coordinates":[-102.416667,27.716667],"type":"Point"}
}