{
  "id": 2042475,
  "type": "Feature",
  "properties": {
    "tgn:hierarchy":[
        "tgn:2042475",
        "tgn:1000001",
        "tgn:2000862",
        "tgn:7012149",
        "tgn:7007256",
        "tgn:7029392"
    ],
    "tgn:id":2042475,
    "tgn:name":"Cecile",
    "tgn:placetype":[
        "aat:300008347",
        "aat:300387210"
    ]
},
  "bbox": [],
  "geometry": {"coordinates":[-93.5833,32.3167],"type":"Point"}
}