{
  "id": 7147535,
  "type": "Feature",
  "properties": {
    "tgn:hierarchy":[
        "tgn:7147535",
        "tgn:1000003",
        "tgn:7003677",
        "tgn:7000084",
        "tgn:7029392"
    ],
    "tgn:id":7147535,
    "tgn:name":"Krewerth",
    "tgn:placetype":[
        "aat:300000206"
    ]
},
  "bbox": [],
  "geometry": {"coordinates":[8.15,51.966667],"type":"Point"}
}