{
  "id": 7144176,
  "type": "Feature",
  "properties": {
    "tgn:hierarchy":[
        "tgn:7144176",
        "tgn:7003669",
        "tgn:1000003",
        "tgn:7000084",
        "tgn:7029392"
    ],
    "tgn:id":7144176,
    "tgn:name":"K\u00f6glitz",
    "tgn:placetype":[
        "aat:300008347"
    ]
},
  "bbox": [],
  "geometry": {"coordinates":[11.933333,49.85],"type":"Point"}
}