{
  "id": 2461992,
  "type": "Feature",
  "properties": {
    "tgn:hierarchy":[
        "tgn:2461992",
        "tgn:1000001",
        "tgn:7012149",
        "tgn:2000930",
        "tgn:7007515",
        "tgn:7029392"
    ],
    "tgn:id":2461992,
    "tgn:name":"Little Turner Pond",
    "tgn:placetype":[
        "aat:300008680"
    ]
},
  "bbox": [],
  "geometry": {"coordinates":[-70.45,45.6333],"type":"Point"}
}