{
  "id": 2732881,
  "type": "Feature",
  "properties": {
    "tgn:hierarchy":[
        "tgn:2732881",
        "tgn:1000001",
        "tgn:7012149",
        "tgn:2000806",
        "tgn:7007255",
        "tgn:7029392"
    ],
    "tgn:id":2732881,
    "tgn:name":"Turkey Fork",
    "tgn:placetype":[
        "aat:300008699"
    ]
},
  "bbox": [],
  "geometry": {"coordinates":[-83.6667,36.9333],"type":"Point"}
}