{
  "id": 7520674,
  "type": "Feature",
  "properties": {
    "tgn:hierarchy":[
        "tgn:7520674",
        "tgn:7001242",
        "tgn:7001311",
        "tgn:7016833",
        "tgn:7029392"
    ],
    "tgn:id":7520674,
    "tgn:name:en":"Abraq, Jabal",
    "tgn:placetype":[
        "aat:300008795"
    ]
},
  "bbox": [],
  "geometry": {"coordinates":[34.815025,23.384138],"type":"Point"}
}