{
  "id": 2214071,
  "type": "Feature",
  "properties": {
    "tgn:hierarchy":[
        "tgn:2214071",
        "tgn:1000001",
        "tgn:7016172",
        "tgn:7012149",
        "tgn:2000163",
        "tgn:7029392"
    ],
    "tgn:id":2214071,
    "tgn:name":"Cagles Eddy",
    "tgn:placetype":[
        "aat:300008680"
    ]
},
  "bbox": [],
  "geometry": {"coordinates":[-91.4667,34.9167],"type":"Point"}
}