{
  "id": 2649987,
  "type": "Feature",
  "properties": {
    "tgn:hierarchy":[
        "tgn:2649987",
        "tgn:1000001",
        "tgn:7012149",
        "tgn:1002251",
        "tgn:7007826",
        "tgn:7029392"
    ],
    "tgn:id":2649987,
    "tgn:name":"Sea Breeze",
    "tgn:placetype":[
        "aat:300008347"
    ]
},
  "bbox": [],
  "geometry": {"coordinates":[-94.3667,29.7167],"type":"Point"}
}