{
  "id": 7469727,
  "type": "Feature",
  "properties": {
    "tgn:hierarchy":[
        "tgn:7469727",
        "tgn:1000004",
        "tgn:7471332",
        "tgn:1000141",
        "tgn:7029392"
    ],
    "tgn:id":7469727,
    "tgn:name":"Xiabeishi",
    "tgn:placetype":[
        "aat:300008347"
    ]
},
  "bbox": [],
  "geometry": {"coordinates":[121.038611,24.891389],"type":"Point"}
}