<<<<<<< HEAD
{
  "id": 2406832,
  "type": "Feature",
  "properties": {
    "tgn:hierarchy":[
        "tgn:2406832",
        "tgn:1000001",
        "tgn:7012149",
        "tgn:2000227",
        "tgn:7007158",
        "tgn:7029392"
    ],
    "tgn:id":2406832,
    "tgn:name":"Hunter Canyon",
    "tgn:placetype":[
        "aat:300008761"
    ]
},
  "bbox": [],
  "geometry": {"coordinates":[-104.6833,37.25],"type":"Point"}
}
=======
{"geometry":{"type":"Point","coordinates":[-104.683300,37.250000]},"type":"Feature","properties":{"hierarchy":["tgn:2406832","tgn:1000001","tgn:7012149","tgn:2000227","tgn:7007158","tgn:7029392"],"placetype":["aat:300008761"],"id":2406832,"name:xx":"Hunter Canyon"}}
>>>>>>> 03f74aca74312dbeaf24d7e61306dd6a786dc3d0
