{
  "id": 1043858,
  "type": "Feature",
  "properties": {
    "tgn:hierarchy":[
        "tgn:1043858",
        "tgn:1003464",
        "tgn:1000003",
        "tgn:7003241",
        "tgn:1000080",
        "tgn:7029392"
    ],
    "tgn:id":1043858,
    "tgn:name":"Capracotta",
    "tgn:placetype":[
        "aat:300008347"
    ]
},
  "bbox": [],
  "geometry": {"coordinates":[14.266667,41.833333],"type":"Point"}
}