{
  "id": 7565775,
  "type": "Feature",
  "properties": {
    "tgn:hierarchy":[
        "tgn:7565775",
        "tgn:1000004",
        "tgn:7000198",
        "tgn:7016722",
        "tgn:7029392"
    ],
    "tgn:id":7565775,
    "tgn:name:en":"R\u016bra Mallu",
    "tgn:placetype":[
        "aat:300008347"
    ]
},
  "bbox": [],
  "geometry": {"coordinates":[79.363657,26.066822],"type":"Point"}
}