{
  "id": 2660535,
  "type": "Feature",
  "properties": {
    "tgn:hierarchy":[
        "tgn:2660535",
        "tgn:1000001",
        "tgn:7012149",
        "tgn:1003020",
        "tgn:7007920",
        "tgn:7029392"
    ],
    "tgn:id":2660535,
    "tgn:name":"Sholes Creek",
    "tgn:placetype":[
        "aat:300008706"
    ]
},
  "bbox": [],
  "geometry": {"coordinates":[-121.75,48.8167],"type":"Point"}
}