{
  "id": 2256902,
  "type": "Feature",
  "properties": {
    "tgn:hierarchy":[
        "tgn:2256902",
        "tgn:1000001",
        "tgn:7012149",
        "tgn:2001756",
        "tgn:7007712",
        "tgn:7029392"
    ],
    "tgn:id":2256902,
    "tgn:name":"Corley Millpond",
    "tgn:placetype":[
        "aat:300006191"
    ]
},
  "bbox": [],
  "geometry": {"coordinates":[-81.15,34.0333],"type":"Point"}
}