<<<<<<< HEAD
{
  "id": 2256902,
  "type": "Feature",
  "properties": {
    "tgn:hierarchy":[
        "tgn:2256902",
        "tgn:1000001",
        "tgn:7012149",
        "tgn:2001756",
        "tgn:7007712",
        "tgn:7029392"
    ],
    "tgn:id":2256902,
    "tgn:name":"Corley Millpond",
    "tgn:placetype":[
        "aat:300006191"
    ]
},
  "bbox": [],
  "geometry": {"coordinates":[-81.15,34.0333],"type":"Point"}
}
=======
{"geometry":{"type":"Point","coordinates":[-81.150000,34.033300]},"type":"Feature","properties":{"hierarchy":["tgn:2256902","tgn:1000001","tgn:7012149","tgn:2001756","tgn:7007712","tgn:7029392"],"placetype":["aat:300006191"],"id":2256902,"name:xx":"Corley Millpond"}}
>>>>>>> 03f74aca74312dbeaf24d7e61306dd6a786dc3d0
