{
  "id": 7154270,
  "type": "Feature",
  "properties": {
    "tgn:hierarchy":[
        "tgn:7154270",
        "tgn:7003669",
        "tgn:1000003",
        "tgn:7000084",
        "tgn:7029392"
    ],
    "tgn:id":7154270,
    "tgn:name":"Irs\u00f6d",
    "tgn:placetype":[
        "aat:300000206"
    ]
},
  "bbox": [],
  "geometry": {"coordinates":[13.333333,48.55],"type":"Point"}
}