{
  "id": 2300661,
  "type": "Feature",
  "properties": {
    "tgn:hierarchy":[
        "tgn:2300661",
        "tgn:1000001",
        "tgn:7012149",
        "tgn:2001713",
        "tgn:7007708",
        "tgn:7029392"
    ],
    "tgn:id":2300661,
    "tgn:name":"Dunbar Gulch",
    "tgn:placetype":[
        "aat:300008761"
    ]
},
  "bbox": [],
  "geometry": {"coordinates":[-123.3667,42.6667],"type":"Point"}
}