{
  "id": 2069986,
  "type": "Feature",
  "properties": {
    "tgn:hierarchy":[
        "tgn:2069986",
        "tgn:1000001",
        "tgn:7012149",
        "tgn:1002681",
        "tgn:7007568",
        "tgn:7029392"
    ],
    "tgn:id":2069986,
    "tgn:name":"Kendall Mills",
    "tgn:placetype":[
        "aat:300008347"
    ]
},
  "bbox": [],
  "geometry": {"coordinates":[-77.9833,43.2833],"type":"Point"}
}