{
  "id": 7287244,
  "type": "Feature",
  "properties": {
    "tgn:hierarchy":[
        "tgn:7287244",
        "tgn:1001630",
        "tgn:1000049",
        "tgn:1000002",
        "tgn:7029392"
    ],
    "tgn:id":7287244,
    "tgn:name":"Grande, Quebrada",
    "tgn:placetype":[
        "aat:300008699"
    ]
},
  "bbox": [],
  "geometry": {"coordinates":[-69.916667,-28.716667],"type":"Point"}
}