{
  "id": 2271532,
  "type": "Feature",
  "properties": {
    "tgn:hierarchy":[
        "tgn:2271532",
        "tgn:1000001",
        "tgn:7012149",
        "tgn:2000846",
        "tgn:7007255",
        "tgn:7029392"
    ],
    "tgn:id":2271532,
    "tgn:name":"Cumberland Shores",
    "tgn:placetype":[
        "aat:300008347"
    ]
},
  "bbox": [],
  "geometry": {"coordinates":[-87.9333,36.75],"type":"Point"}
}