{
  "id": 2628105,
  "type": "Feature",
  "properties": {
    "tgn:hierarchy":[
        "tgn:2628105",
        "tgn:1000001",
        "tgn:7012149",
        "tgn:2001509",
        "tgn:7007709",
        "tgn:7029392"
    ],
    "tgn:id":2628105,
    "tgn:name":"Rollingwood",
    "tgn:placetype":[
        "aat:300008347"
    ]
},
  "bbox": [],
  "geometry": {"coordinates":[-78.4333,35.65],"type":"Point"}
}