{
  "id": 7588914,
  "type": "Feature",
  "properties": {
    "tgn:hierarchy":[
        "tgn:7588914",
        "tgn:1000004",
        "tgn:7000198",
        "tgn:7000799",
        "tgn:7029392"
    ],
    "tgn:id":7588914,
    "tgn:name:en":"K\u0101l\u0101bar",
    "tgn:placetype":[
        "aat:300008347"
    ]
},
  "bbox": [],
  "geometry": {"coordinates":[74.178668,33.676684],"type":"Point"}
}