<<<<<<< HEAD
{
  "id": 2761267,
  "type": "Feature",
  "properties": {
    "tgn:hierarchy":[
        "tgn:2761267",
        "tgn:1000001",
        "tgn:2002102",
        "tgn:7012149",
        "tgn:7007827",
        "tgn:7029392"
    ],
    "tgn:id":2761267,
    "tgn:name":"West Marsh",
    "tgn:placetype":[
        "aat:300008905"
    ]
},
  "bbox": [],
  "geometry": {"coordinates":[-112.3167,41.55],"type":"Point"}
}
=======
{"geometry":{"type":"Point","coordinates":[-112.316700,41.550000]},"type":"Feature","properties":{"hierarchy":["tgn:2761267","tgn:1000001","tgn:2002102","tgn:7012149","tgn:7007827","tgn:7029392"],"placetype":["aat:300008905"],"id":2761267,"name:xx":"West Marsh"}}
>>>>>>> 03f74aca74312dbeaf24d7e61306dd6a786dc3d0
