{
  "id": 2694592,
  "type": "Feature",
  "properties": {
    "tgn:hierarchy":[
        "tgn:2694592",
        "tgn:1000001",
        "tgn:7012149",
        "tgn:2001872",
        "tgn:7007825",
        "tgn:7029392"
    ],
    "tgn:id":2694592,
    "tgn:name":"Stewart Hollow",
    "tgn:placetype":[
        "aat:300008761"
    ]
},
  "bbox": [],
  "geometry": {"coordinates":[-88.1167,35.05],"type":"Point"}
}