{
  "id": 2301915,
  "type": "Feature",
  "properties": {
    "tgn:hierarchy":[
        "tgn:2301915",
        "tgn:1000001",
        "tgn:7012149",
        "tgn:1002751",
        "tgn:7007568",
        "tgn:7029392"
    ],
    "tgn:id":2301915,
    "tgn:name":"Durlandville Ditch",
    "tgn:placetype":[
        "aat:300006075"
    ]
},
  "bbox": [],
  "geometry": {"coordinates":[-74.4167,41.3333],"type":"Point"}
}