<<<<<<< HEAD
{
  "id": 2406122,
  "type": "Feature",
  "properties": {
    "tgn:hierarchy":[
        "tgn:2406122",
        "tgn:1000001",
        "tgn:2001411",
        "tgn:7012149",
        "tgn:7007526",
        "tgn:7029392"
    ],
    "tgn:id":2406122,
    "tgn:name":"Humming Bird Spring",
    "tgn:placetype":[
        "aat:300008697"
    ]
},
  "bbox": [],
  "geometry": {"coordinates":[-115.25,41.8],"type":"Point"}
}
=======
{"geometry":{"type":"Point","coordinates":[-115.250000,41.800000]},"type":"Feature","properties":{"hierarchy":["tgn:2406122","tgn:1000001","tgn:2001411","tgn:7012149","tgn:7007526","tgn:7029392"],"placetype":["aat:300008697"],"id":2406122,"name:xx":"Humming Bird Spring"}}
>>>>>>> 03f74aca74312dbeaf24d7e61306dd6a786dc3d0
