{
  "id": 7468814,
  "type": "Feature",
  "properties": {
    "tgn:hierarchy":[
        "tgn:7468814",
        "tgn:7001001",
        "tgn:1000004",
        "tgn:1000141",
        "tgn:7029392"
    ],
    "tgn:id":7468814,
    "tgn:name":"Xialutou",
    "tgn:placetype":[
        "aat:300008347"
    ]
},
  "bbox": [],
  "geometry": {"coordinates":[120.441667,23.460556],"type":"Point"}
}