<<<<<<< HEAD
{
  "id": 2337141,
  "type": "Feature",
  "properties": {
    "tgn:hierarchy":[
        "tgn:2337141",
        "tgn:1000001",
        "tgn:2001266",
        "tgn:7012149",
        "tgn:7007524",
        "tgn:7029392"
    ],
    "tgn:id":2337141,
    "tgn:name":"Fourteen Creek",
    "tgn:placetype":[
        "aat:300008706"
    ]
},
  "bbox": [],
  "geometry": {"coordinates":[-111.5833,47.0333],"type":"Point"}
}
=======
{"geometry":{"type":"Point","coordinates":[-111.583300,47.033300]},"type":"Feature","properties":{"hierarchy":["tgn:2337141","tgn:1000001","tgn:2001266","tgn:7012149","tgn:7007524","tgn:7029392"],"placetype":["aat:300008706"],"id":2337141,"name:xx":"Fourteen Creek"}}
>>>>>>> 03f74aca74312dbeaf24d7e61306dd6a786dc3d0
