{
  "id": 7443911,
  "type": "Feature",
  "properties": {
    "tgn:hierarchy":[
        "tgn:7443911",
        "tgn:7002445",
        "tgn:1000003",
        "tgn:7008165",
        "tgn:7008591",
        "tgn:7029392"
    ],
    "tgn:id":7443911,
    "tgn:name:en":"West Ord",
    "tgn:placetype":[
        "aat:300008347"
    ]
},
  "bbox": [],
  "geometry": {"coordinates":[-2.066667,55.75],"type":"Point"}
}