{
  "id": 2726450,
  "type": "Feature",
  "properties": {
    "tgn:hierarchy":[
        "tgn:2726450",
        "tgn:1000001",
        "tgn:2002260",
        "tgn:7012149",
        "tgn:7013961",
        "tgn:7029392"
    ],
    "tgn:id":2726450,
    "tgn:name":"Town Camp Run",
    "tgn:placetype":[
        "aat:300008699"
    ]
},
  "bbox": [],
  "geometry": {"coordinates":[-80.7167,39.15],"type":"Point"}
}