{
  "id": 2544347,
  "type": "Feature",
  "properties": {
    "tgn:hierarchy":[
        "tgn:2544347",
        "tgn:1000001",
        "tgn:7012149",
        "tgn:7007515",
        "tgn:7029392"
    ],
    "tgn:id":2544347,
    "tgn:name":"North Branch Spruce Brook",
    "tgn:placetype":[
        "aat:300008699"
    ]
},
  "bbox": [],
  "geometry": {"coordinates":[-69.7167,46.1833],"type":"Point"}
}