{
  "id": 2163137,
  "type": "Feature",
  "properties": {
    "tgn:hierarchy":[
        "tgn:2163137",
        "tgn:1000001",
        "tgn:7012149",
        "tgn:2001144",
        "tgn:7007522",
        "tgn:7029392"
    ],
    "tgn:id":2163137,
    "tgn:name":"Bennett Lake",
    "tgn:placetype":[
        "aat:300006191"
    ]
},
  "bbox": [],
  "geometry": {"coordinates":[-88.55,34.5667],"type":"Point"}
}