{
  "id": 2036731,
  "type": "Feature",
  "properties": {
    "tgn:hierarchy":[
        "tgn:2036731",
        "tgn:1000001",
        "tgn:7012149",
        "tgn:2000743",
        "tgn:7007254",
        "tgn:7029392"
    ],
    "tgn:id":2036731,
    "tgn:name":"Lucas",
    "tgn:placetype":[
        "aat:300008347"
    ]
},
  "bbox": [],
  "geometry": {"coordinates":[-98.5333,39.05],"type":"Point"}
}