{
  "id": 2200936,
  "type": "Feature",
  "properties": {
    "tgn:hierarchy":[
        "tgn:2200936",
        "tgn:1000001",
        "tgn:7012149",
        "tgn:2001212",
        "tgn:7007523",
        "tgn:7029392"
    ],
    "tgn:id":2200936,
    "tgn:name":"Bryant Knob",
    "tgn:placetype":[
        "aat:300008798"
    ]
},
  "bbox": [],
  "geometry": {"coordinates":[-93.9833,39.0833],"type":"Point"}
}