{
  "id": 7535227,
  "type": "Feature",
  "properties": {
    "tgn:hierarchy":[
        "tgn:7535227",
        "tgn:7001242",
        "tgn:7001311",
        "tgn:7016833",
        "tgn:7029392"
    ],
    "tgn:id":7535227,
    "tgn:name:en":"Hutit, W\u00e2di",
    "tgn:placetype":[
        "aat:300379998"
    ]
},
  "bbox": [],
  "geometry": {"coordinates":[35.23629,23.372297],"type":"Point"}
}