<<<<<<< HEAD
{
  "id": 2339822,
  "type": "Feature",
  "properties": {
    "tgn:hierarchy":[
        "tgn:2339822",
        "tgn:1000001",
        "tgn:7012149",
        "tgn:2000214",
        "tgn:7007158",
        "tgn:7029392"
    ],
    "tgn:id":2339822,
    "tgn:name":"Freeman Creek",
    "tgn:placetype":[
        "aat:300008706"
    ]
},
  "bbox": [],
  "geometry": {"coordinates":[-107.3333,39.3667],"type":"Point"}
}
=======
{"geometry":{"type":"Point","coordinates":[-107.333300,39.366700]},"type":"Feature","properties":{"hierarchy":["tgn:2339822","tgn:1000001","tgn:7012149","tgn:2000214","tgn:7007158","tgn:7029392"],"placetype":["aat:300008706"],"id":2339822,"name:xx":"Freeman Creek"}}
>>>>>>> 03f74aca74312dbeaf24d7e61306dd6a786dc3d0
