{
  "id": 7064120,
  "type": "Feature",
  "properties": {
    "tgn:hierarchy":[
        "tgn:7064120",
        "tgn:7003692",
        "tgn:1000003",
        "tgn:7000084",
        "tgn:7029392"
    ],
    "tgn:id":7064120,
    "tgn:name":"Unterer Wald",
    "tgn:placetype":[
        "aat:300008863"
    ]
},
  "bbox": [],
  "geometry": {"coordinates":[10.033333,47.833333],"type":"Point"}
}