{
  "id": 7455648,
  "type": "Feature",
  "properties": {
    "tgn:hierarchy":[
        "tgn:7455648",
        "tgn:7019094",
        "tgn:7002444",
        "tgn:1000003",
        "tgn:7008591",
        "tgn:7029392"
    ],
    "tgn:id":7455648,
    "tgn:name:en":"Dubh Sgeir",
    "tgn:placetype":[
        "aat:300011692"
    ]
},
  "bbox": [],
  "geometry": {"coordinates":[-5.65,56.316667],"type":"Point"}
}