<<<<<<< HEAD
{
  "id": 7476828,
  "type": "Feature",
  "properties": {
    "tgn:hierarchy":[
        "tgn:7476828",
        "tgn:1000004",
        "tgn:7004300",
        "tgn:1000141",
        "tgn:7029392"
    ],
    "tgn:id":7476828,
    "tgn:name":"Chamu Yu Dengta",
    "tgn:placetype":[
        "aat:300007741"
    ]
},
  "bbox": [],
  "geometry": {"coordinates":[119.725894,23.535965],"type":"Point"}
}
=======
{"geometry":{"type":"Point","coordinates":[119.725894,23.535965]},"type":"Feature","properties":{"hierarchy":["tgn:7476828","tgn:1000004","tgn:7004300","tgn:1000141","tgn:7029392"],"placetype":["aat:300007741"],"id":7476828,"name:xx":"Chamu Yu Dengta"}}
>>>>>>> 03f74aca74312dbeaf24d7e61306dd6a786dc3d0
