{
  "id": 7430146,
  "type": "Feature",
  "properties": {
    "tgn:hierarchy":[
        "tgn:7430146",
        "tgn:1001835",
        "tgn:1000001",
        "tgn:7005560",
        "tgn:7029392"
    ],
    "tgn:id":7430146,
    "tgn:name":"San Antonio de las Minas",
    "tgn:placetype":[
        "aat:300008347"
    ]
},
  "bbox": [],
  "geometry": {"coordinates":[-116.65,31.933333],"type":"Point"}
}