{
  "id": 2532637,
  "type": "Feature",
  "properties": {
    "tgn:hierarchy":[
        "tgn:2532637",
        "tgn:1000001",
        "tgn:7012149",
        "tgn:7007523",
        "tgn:7029392"
    ],
    "tgn:id":2532637,
    "tgn:name":"Murphy Hollow",
    "tgn:placetype":[
        "aat:300008761"
    ]
},
  "bbox": [],
  "geometry": {"coordinates":[-91.05,38.1833],"type":"Point"}
}