<<<<<<< HEAD
{
  "id": 2767171,
  "type": "Feature",
  "properties": {
    "tgn:hierarchy":[
        "tgn:2767171",
        "tgn:1000001",
        "tgn:7012149",
        "tgn:7014185",
        "tgn:7007710",
        "tgn:7029392"
    ],
    "tgn:id":2767171,
    "tgn:name":"White Rock Hollow",
    "tgn:placetype":[
        "aat:300008761"
    ]
},
  "bbox": [],
  "geometry": {"coordinates":[-79.6833,39.8167],"type":"Point"}
}
=======
{"geometry":{"type":"Point","coordinates":[-79.683300,39.816700]},"type":"Feature","properties":{"hierarchy":["tgn:2767171","tgn:1000001","tgn:7012149","tgn:7014185","tgn:7007710","tgn:7029392"],"placetype":["aat:300008761"],"id":2767171,"name:xx":"White Rock Hollow"}}
>>>>>>> 03f74aca74312dbeaf24d7e61306dd6a786dc3d0
