{
  "id": 7103688,
  "type": "Feature",
  "properties": {
    "tgn:hierarchy":[
        "tgn:7103688",
        "tgn:1000003",
        "tgn:7003688",
        "tgn:7000084",
        "tgn:7029392"
    ],
    "tgn:id":7103688,
    "tgn:name":"Sandh\u00f6rn",
    "tgn:placetype":[
        "aat:300386970"
    ]
},
  "bbox": [],
  "geometry": {"coordinates":[8.816667,54.616667],"type":"Point"}
}