{
  "id": 7524298,
  "type": "Feature",
  "properties": {
    "tgn:hierarchy":[
        "tgn:7524298",
        "tgn:7001242",
        "tgn:1001059",
        "tgn:7016833",
        "tgn:7029392"
    ],
    "tgn:id":7524298,
    "tgn:name:en":"A\u0163 \u0162ayyibah",
    "tgn:placetype":[
        "aat:300008347"
    ]
},
  "bbox": [],
  "geometry": {"coordinates":[31.312168,31.132913],"type":"Point"}
}