{
  "id": 1126658,
  "type": "Feature",
  "properties": {
    "tgn:hierarchy":[
        "tgn:1126658",
        "tgn:1001622",
        "tgn:1000003",
        "tgn:7003122",
        "tgn:1000080",
        "tgn:7029392"
    ],
    "tgn:id":1126658,
    "tgn:name":"Magazzolo",
    "tgn:placetype":[
        "aat:300008707",
        "aat:300008699"
    ]
},
  "bbox": [],
  "geometry": {"coordinates":[13.25,37.416667],"type":"Point"}
}