<<<<<<< HEAD
{
  "id": 7472437,
  "type": "Feature",
  "properties": {
    "tgn:hierarchy":[
        "tgn:7472437",
        "tgn:1000004",
        "tgn:1000454",
        "tgn:1000141",
        "tgn:7029392"
    ],
    "tgn:id":7472437,
    "tgn:name":"Tucheng Shi",
    "tgn:placetype":[
        "aat:300387173"
    ]
},
  "bbox": [],
  "geometry": {"coordinates":[121.433333,24.966667],"type":"Point"}
}
=======
{"geometry":{"type":"Point","coordinates":[121.433333,24.966667]},"type":"Feature","properties":{"hierarchy":["tgn:7472437","tgn:1000004","tgn:1000454","tgn:1000141","tgn:7029392"],"placetype":["aat:300387173"],"id":7472437,"name:xx":"Tucheng Shi"}}
>>>>>>> 03f74aca74312dbeaf24d7e61306dd6a786dc3d0
