<<<<<<< HEAD
{
  "id": 7354834,
  "type": "Feature",
  "properties": {
    "tgn:hierarchy":[
        "tgn:7354834",
        "tgn:1000001",
        "tgn:7005589",
        "tgn:7005560",
        "tgn:7029392"
    ],
    "tgn:id":7354834,
    "tgn:name":"Cato, Arroyo del",
    "tgn:placetype":[
        "aat:300266554",
        "aat:300008699"
    ]
},
  "bbox": [],
  "geometry": {"coordinates":[-98.583333,25.883333],"type":"Point"}
}
=======
{"geometry":{"type":"Point","coordinates":[-98.583333,25.883333]},"type":"Feature","properties":{"hierarchy":["tgn:7354834","tgn:1000001","tgn:7005589","tgn:7005560","tgn:7029392"],"placetype":["aat:300266554","aat:300008699"],"id":7354834,"name:xx":"Cato, Arroyo del"}}
>>>>>>> 03f74aca74312dbeaf24d7e61306dd6a786dc3d0
