<<<<<<< HEAD
{
  "id": 7054306,
  "type": "Feature",
  "properties": {
    "tgn:hierarchy":[
        "tgn:7054306",
        "tgn:7003127",
        "tgn:1000003",
        "tgn:7008516",
        "tgn:1000080",
        "tgn:7029392"
    ],
    "tgn:id":7054306,
    "tgn:name":"Palazzo San Lazzaro",
    "tgn:placetype":[
        "aat:300008347"
    ]
},
  "bbox": [],
  "geometry": {"coordinates":[11.75,44.333333],"type":"Point"}
}
=======
{"geometry":{"type":"Point","coordinates":[11.750000,44.333333]},"type":"Feature","properties":{"hierarchy":["tgn:7054306","tgn:7003127","tgn:1000003","tgn:7008516","tgn:1000080","tgn:7029392"],"placetype":["aat:300008347"],"id":7054306,"name:xx":"Palazzo San Lazzaro"}}
>>>>>>> 03f74aca74312dbeaf24d7e61306dd6a786dc3d0
