{
  "id": 2460744,
  "type": "Feature",
  "properties": {
    "tgn:hierarchy":[
        "tgn:2460744",
        "tgn:1000001",
        "tgn:7012149",
        "tgn:2000476",
        "tgn:7007250",
        "tgn:7029392"
    ],
    "tgn:id":2460744,
    "tgn:name":"Little Sheepeater Point",
    "tgn:placetype":[
        "aat:300008798"
    ]
},
  "bbox": [],
  "geometry": {"coordinates":[-115.3833,45.3833],"type":"Point"}
}