{
  "id": 2084745,
  "type": "Feature",
  "properties": {
    "tgn:hierarchy":[
        "tgn:2084745",
        "tgn:1000001",
        "tgn:7012149",
        "tgn:2001716",
        "tgn:7007708",
        "tgn:7029392"
    ],
    "tgn:id":2084745,
    "tgn:name":"Finn Rock",
    "tgn:placetype":[
        "aat:300008347"
    ]
},
  "bbox": [],
  "geometry": {"coordinates":[-122.3667,44.1167],"type":"Point"}
}