{
  "id": 2456243,
  "type": "Feature",
  "properties": {
    "tgn:hierarchy":[
        "tgn:2456243",
        "tgn:1000001",
        "tgn:7012149",
        "tgn:2001286",
        "tgn:7007524",
        "tgn:7029392"
    ],
    "tgn:id":2456243,
    "tgn:name":"Little Hoodoo Mountain",
    "tgn:placetype":[
        "aat:300008798"
    ]
},
  "bbox": [],
  "geometry": {"coordinates":[-115.55,48.25],"type":"Point"}
}