{
  "id": 2066972,
  "type": "Feature",
  "properties": {
    "tgn:hierarchy":[
        "tgn:2066972",
        "tgn:1000001",
        "tgn:7012149",
        "tgn:2001452",
        "tgn:7007566",
        "tgn:7029392"
    ],
    "tgn:id":2066972,
    "tgn:name":"Fruitland",
    "tgn:placetype":[
        "aat:300008347"
    ]
},
  "bbox": [],
  "geometry": {"coordinates":[-108.3833,36.7333],"type":"Point"}
}