{
  "id": 7038786,
  "type": "Feature",
  "properties": {
    "tgn:hierarchy":[
        "tgn:7038786",
        "tgn:1003506",
        "tgn:1000003",
        "tgn:7002993",
        "tgn:1000080",
        "tgn:7029392"
    ],
    "tgn:id":7038786,
    "tgn:name":"Stella, Fiume",
    "tgn:placetype":[
        "aat:300008699"
    ]
},
  "bbox": [],
  "geometry": {"coordinates":[13.097778,45.735833],"type":"Point"}
}