{
  "id": 7569632,
  "type": "Feature",
  "properties": {
    "tgn:hierarchy":[
        "tgn:7569632",
        "tgn:1000004",
        "tgn:7000198",
        "tgn:7016788",
        "tgn:7029392"
    ],
    "tgn:id":7569632,
    "tgn:name:en":"Bhukhiya N\u0101la",
    "tgn:placetype":[
        "aat:300008699"
    ]
},
  "bbox": [],
  "geometry": {"coordinates":[75.660487,25.551048],"type":"Point"}
}