{
  "id": 2736701,
  "type": "Feature",
  "properties": {
    "tgn:hierarchy":[
        "tgn:2736701",
        "tgn:1000001",
        "tgn:7006451",
        "tgn:7012149",
        "tgn:2000098",
        "tgn:7029392"
    ],
    "tgn:id":2736701,
    "tgn:name":"Twin Tanks",
    "tgn:placetype":[
        "aat:300006191"
    ]
},
  "bbox": [],
  "geometry": {"coordinates":[-112.8667,36.5167],"type":"Point"}
}