{
  "id": 2370329,
  "type": "Feature",
  "properties": {
    "tgn:hierarchy":[
        "tgn:2370329",
        "tgn:1000001",
        "tgn:7012149",
        "tgn:2001766",
        "tgn:7007712",
        "tgn:7029392"
    ],
    "tgn:id":2370329,
    "tgn:name":"H B Davis Pond",
    "tgn:placetype":[
        "aat:300006191"
    ]
},
  "bbox": [],
  "geometry": {"coordinates":[-82.1333,35.0167],"type":"Point"}
}