{
  "id": 7297771,
  "type": "Feature",
  "properties": {
    "tgn:hierarchy":[
        "tgn:7297771",
        "tgn:7002824",
        "tgn:1000003",
        "tgn:7002786",
        "tgn:1000095",
        "tgn:7029392"
    ],
    "tgn:id":7297771,
    "tgn:name":"Soneira, Sierra de",
    "tgn:placetype":[
        "aat:300008795"
    ]
},
  "bbox": [],
  "geometry": {"coordinates":[-8.866667,43.083333],"type":"Point"}
}