{
  "id": 7221054,
  "type": "Feature",
  "properties": {
    "tgn:hierarchy":[
        "tgn:7221054",
        "tgn:7002715",
        "tgn:7002731",
        "tgn:1000003",
        "tgn:1000074",
        "tgn:7029392"
    ],
    "tgn:id":7221054,
    "tgn:name":"Vardarit, Lumi i",
    "tgn:placetype":[
        "aat:300008699"
    ]
},
  "bbox": [],
  "geometry": {"coordinates":[22.722269,40.500374],"type":"Point"}
}