{
  "id": 7166314,
  "type": "Feature",
  "properties": {
    "tgn:hierarchy":[
        "tgn:7166314",
        "tgn:7003669",
        "tgn:1000003",
        "tgn:7000084",
        "tgn:7029392"
    ],
    "tgn:id":7166314,
    "tgn:name":"Hailzing",
    "tgn:placetype":[
        "aat:300000206"
    ]
},
  "bbox": [],
  "geometry": {"coordinates":[12.516667,48.066667],"type":"Point"}
}