{
  "id": 2187638,
  "type": "Feature",
  "properties": {
    "tgn:hierarchy":[
        "tgn:2187638",
        "tgn:1000001",
        "tgn:7012149",
        "tgn:1002742",
        "tgn:7007920",
        "tgn:7029392"
    ],
    "tgn:id":2187638,
    "tgn:name":"Booth Canyon",
    "tgn:placetype":[
        "aat:300008761"
    ]
},
  "bbox": [],
  "geometry": {"coordinates":[-120.1333,48.3167],"type":"Point"}
}