{
  "id": 7395521,
  "type": "Feature",
  "properties": {
    "tgn:hierarchy":[
        "tgn:7395521",
        "tgn:7005584",
        "tgn:1000001",
        "tgn:7005560",
        "tgn:7029392"
    ],
    "tgn:id":7395521,
    "tgn:name":"San Antonio",
    "tgn:placetype":[
        "aat:300008347"
    ]
},
  "bbox": [],
  "geometry": {"coordinates":[-101.416667,21.25],"type":"Point"}
}