{
  "id": 7388441,
  "type": "Feature",
  "properties": {
    "tgn:hierarchy":[
        "tgn:7388441",
        "tgn:1000001",
        "tgn:7005592",
        "tgn:7005560",
        "tgn:7029392"
    ],
    "tgn:id":7388441,
    "tgn:name":"Paso Nacional",
    "tgn:placetype":[
        "aat:300008347"
    ]
},
  "bbox": [],
  "geometry": {"coordinates":[-97.366667,19.15],"type":"Point"}
}