{
  "id": 7470679,
  "type": "Feature",
  "properties": {
    "tgn:hierarchy":[
        "tgn:7470679",
        "tgn:1000004",
        "tgn:7471332",
        "tgn:1000141",
        "tgn:7029392"
    ],
    "tgn:id":7470679,
    "tgn:name":"Qingbuzi",
    "tgn:placetype":[
        "aat:300008347"
    ]
},
  "bbox": [],
  "geometry": {"coordinates":[121.005,24.922222],"type":"Point"}
}