{
  "id": 2736798,
  "type": "Feature",
  "properties": {
    "tgn:hierarchy":[
        "tgn:2736798",
        "tgn:1000001",
        "tgn:7012149",
        "tgn:7007827",
        "tgn:7029392"
    ],
    "tgn:id":2736798,
    "tgn:name":"Twist Trail",
    "tgn:placetype":[
        "aat:300008761"
    ]
},
  "bbox": [],
  "geometry": {"coordinates":[-110.5833,39.8167],"type":"Point"}
}