{
  "id": 2288531,
  "type": "Feature",
  "properties": {
    "tgn:hierarchy":[
        "tgn:2288531",
        "tgn:1000001",
        "tgn:7012149",
        "tgn:1002946",
        "tgn:7007252",
        "tgn:7029392"
    ],
    "tgn:id":2288531,
    "tgn:name":"Dismal Creek",
    "tgn:placetype":[
        "aat:300008706"
    ]
},
  "bbox": [],
  "geometry": {"coordinates":[-86.7667,40.3167],"type":"Point"}
}