{
  "id": 2346804,
  "type": "Feature",
  "properties": {
    "tgn:hierarchy":[
        "tgn:2346804",
        "tgn:1000001",
        "tgn:7006451",
        "tgn:7012149",
        "tgn:7029392"
    ],
    "tgn:id":2346804,
    "tgn:name":"Geesaman Wash",
    "tgn:placetype":[
        "aat:300008699"
    ]
},
  "bbox": [],
  "geometry": {"coordinates":[-110.7167,32.4667],"type":"Point"}
}