{
  "id": 2490731,
  "type": "Feature",
  "properties": {
    "tgn:hierarchy":[
        "tgn:2490731",
        "tgn:1000001",
        "tgn:7012149",
        "tgn:1002928",
        "tgn:7007706",
        "tgn:7029392"
    ],
    "tgn:id":2490731,
    "tgn:name":"Mannings Pond",
    "tgn:placetype":[
        "aat:300008680"
    ]
},
  "bbox": [],
  "geometry": {"coordinates":[-81.5333,41.05],"type":"Point"}
}