{
  "id": 7577954,
  "type": "Feature",
  "properties": {
    "tgn:hierarchy":[
        "tgn:7577954",
        "tgn:1000004",
        "tgn:7000198",
        "tgn:1001895",
        "tgn:7029392"
    ],
    "tgn:id":7577954,
    "tgn:name:en":"Kumbhoj",
    "tgn:placetype":[
        "aat:300008347"
    ]
},
  "bbox": [],
  "geometry": {"coordinates":[74.433333,16.833333],"type":"Point"}
}