{
  "id": 1114197,
  "type": "Feature",
  "properties": {
    "tgn:hierarchy":[
        "tgn:1114197",
        "tgn:7005685",
        "tgn:1000001",
        "tgn:1000296",
        "tgn:7029392"
    ],
    "tgn:id":1114197,
    "tgn:name":"Maury Channel",
    "tgn:placetype":[
        "aat:300008713"
    ]
},
  "bbox": [],
  "geometry": {"coordinates":[-94.6667,75.7333],"type":"Point"}
}