{
  "id": 7005657,
  "type": "Feature",
  "properties": {
    "tgn:hierarchy":[
        "tgn:7005657",
        "tgn:7024835",
        "tgn:1000003",
        "tgn:7003120",
        "tgn:1000080",
        "tgn:7029392"
    ],
    "tgn:id":7005657,
    "tgn:name":"Stresa",
    "tgn:placetype":[
        "aat:300008347"
    ]
},
  "bbox": [],
  "geometry": {"coordinates":[8.533333,45.883333],"type":"Point"}
}