{
  "id": 7407769,
  "type": "Feature",
  "properties": {
    "tgn:hierarchy":[
        "tgn:7407769",
        "tgn:7005580",
        "tgn:1000001",
        "tgn:7005560",
        "tgn:7029392"
    ],
    "tgn:id":7407769,
    "tgn:name":"Custepec, R\u00edo",
    "tgn:placetype":[
        "aat:300008699"
    ]
},
  "bbox": [],
  "geometry": {"coordinates":[-92.75,16.108333],"type":"Point"}
}