{
  "id": 2210984,
  "type": "Feature",
  "properties": {
    "tgn:hierarchy":[
        "tgn:2210984",
        "tgn:1000001",
        "tgn:7012149",
        "tgn:1002487",
        "tgn:7007252",
        "tgn:7029392"
    ],
    "tgn:id":2210984,
    "tgn:name":"Butler Ditch",
    "tgn:placetype":[
        "aat:300006075"
    ]
},
  "bbox": [],
  "geometry": {"coordinates":[-86.2167,40.4167],"type":"Point"}
}