{
  "id": 7328963,
  "type": "Feature",
  "properties": {
    "tgn:hierarchy":[
        "tgn:7328963",
        "tgn:7008911",
        "tgn:1000003",
        "tgn:7002763",
        "tgn:1000095",
        "tgn:7029392"
    ],
    "tgn:id":7328963,
    "tgn:name":"Reconcos",
    "tgn:placetype":[
        "aat:300008347"
    ]
},
  "bbox": [],
  "geometry": {"coordinates":[-5.833333,43.033333],"type":"Point"}
}