<<<<<<< HEAD
{
  "id": 7376270,
  "type": "Feature",
  "properties": {
    "tgn:hierarchy":[
        "tgn:7376270",
        "tgn:1000001",
        "tgn:7005589",
        "tgn:7005560",
        "tgn:7029392"
    ],
    "tgn:id":7376270,
    "tgn:name":"Las Jarillas",
    "tgn:placetype":[
        "aat:300008347"
    ]
},
  "bbox": [],
  "geometry": {"coordinates":[-100.283333,23.783333],"type":"Point"}
}
=======
{"geometry":{"type":"Point","coordinates":[-100.283333,23.783333]},"type":"Feature","properties":{"hierarchy":["tgn:7376270","tgn:1000001","tgn:7005589","tgn:7005560","tgn:7029392"],"placetype":["aat:300008347"],"id":7376270,"name:xx":"Las Jarillas"}}
>>>>>>> 03f74aca74312dbeaf24d7e61306dd6a786dc3d0
