{
  "id": 1054487,
  "type": "Feature",
  "properties": {
    "tgn:hierarchy":[
        "tgn:1054487",
        "tgn:1000004",
        "tgn:7011600",
        "tgn:7018214",
        "tgn:7002435",
        "tgn:7029392"
    ],
    "tgn:id":1054487,
    "tgn:name":"Izumrud",
    "tgn:placetype":[
        "aat:300008347"
    ]
},
  "bbox": [],
  "geometry": {"coordinates":[61.4167,57.1333],"type":"Point"}
}