<<<<<<< HEAD
{
  "id": 7020080,
  "type": "Feature",
  "properties": {
    "tgn:hierarchy":[
        "tgn:7020080",
        "tgn:1000001",
        "tgn:7012149",
        "tgn:1002564",
        "tgn:7007710",
        "tgn:7029392"
    ],
    "tgn:id":7020080,
    "tgn:name":"Waters Reservoir",
    "tgn:placetype":[
        "aat:300006191"
    ]
},
  "bbox": [],
  "geometry": {"coordinates":[-75.6167,41.2833],"type":"Point"}
}
=======
{"geometry":{"type":"Point","coordinates":[-75.616700,41.283300]},"type":"Feature","properties":{"hierarchy":["tgn:7020080","tgn:1000001","tgn:7012149","tgn:1002564","tgn:7007710","tgn:7029392"],"placetype":["aat:300006191"],"id":7020080,"name:xx":"Waters Reservoir"}}
>>>>>>> 03f74aca74312dbeaf24d7e61306dd6a786dc3d0
