{
  "id": 7020080,
  "type": "Feature",
  "properties": {
    "tgn:hierarchy":[
        "tgn:7020080",
        "tgn:1000001",
        "tgn:7012149",
        "tgn:1002564",
        "tgn:7007710",
        "tgn:7029392"
    ],
    "tgn:id":7020080,
    "tgn:name":"Waters Reservoir",
    "tgn:placetype":[
        "aat:300006191"
    ]
},
  "bbox": [],
  "geometry": {"coordinates":[-75.6167,41.2833],"type":"Point"}
}