{
  "id": 7231194,
  "type": "Feature",
  "properties": {
    "tgn:hierarchy":[
        "tgn:7231194",
        "tgn:7002681",
        "tgn:7001395",
        "tgn:1000003",
        "tgn:1000074",
        "tgn:7029392"
    ],
    "tgn:id":7231194,
    "tgn:name":"Kouvar\u00e1s",
    "tgn:placetype":[
        "aat:300008347"
    ]
},
  "bbox": [],
  "geometry": {"coordinates":[23.966667,37.833333],"type":"Point"}
}