<<<<<<< HEAD
{
  "id": 7353907,
  "type": "Feature",
  "properties": {
    "tgn:hierarchy":[
        "tgn:7353907",
        "tgn:1000001",
        "tgn:1001960",
        "tgn:7005560",
        "tgn:7029392"
    ],
    "tgn:id":7353907,
    "tgn:name":"Campo Sesenta Nueve",
    "tgn:placetype":[
        "aat:300008347"
    ]
},
  "bbox": [],
  "geometry": {"coordinates":[-110.083333,27.283333],"type":"Point"}
}
=======
{"geometry":{"type":"Point","coordinates":[-110.083333,27.283333]},"type":"Feature","properties":{"hierarchy":["tgn:7353907","tgn:1000001","tgn:1001960","tgn:7005560","tgn:7029392"],"placetype":["aat:300008347"],"id":7353907,"name:xx":"Campo Sesenta Nueve"}}
>>>>>>> 03f74aca74312dbeaf24d7e61306dd6a786dc3d0
