{
  "id": 2328535,
  "type": "Feature",
  "properties": {
    "tgn:hierarchy":[
        "tgn:2328535",
        "tgn:1000001",
        "tgn:7016172",
        "tgn:7012149",
        "tgn:2000155",
        "tgn:7029392"
    ],
    "tgn:id":2328535,
    "tgn:name":"Fisher Point",
    "tgn:placetype":[
        "aat:300008798"
    ]
},
  "bbox": [],
  "geometry": {"coordinates":[-93.3167,36.0333],"type":"Point"}
}