{
  "id": 7051459,
  "type": "Feature",
  "properties": {
    "tgn:hierarchy":[
        "tgn:7051459",
        "tgn:1003471",
        "tgn:1000003",
        "tgn:7003240",
        "tgn:1000080",
        "tgn:7029392"
    ],
    "tgn:id":7051459,
    "tgn:name":"Piaggia",
    "tgn:placetype":[
        "aat:300008347"
    ]
},
  "bbox": [],
  "geometry": {"coordinates":[12.966667,42.916667],"type":"Point"}
}