{
  "id": 7317004,
  "type": "Feature",
  "properties": {
    "tgn:hierarchy":[
        "tgn:7317004",
        "tgn:1001623",
        "tgn:1000049",
        "tgn:1000002",
        "tgn:7029392"
    ],
    "tgn:id":7317004,
    "tgn:name":"C\u00f3ndor, Lago",
    "tgn:placetype":[
        "aat:300008680"
    ]
},
  "bbox": [],
  "geometry": {"coordinates":[-72.966667,-45.566667],"type":"Point"}
}