{
  "id": 2510833,
  "type": "Feature",
  "properties": {
    "tgn:hierarchy":[
        "tgn:2510833",
        "tgn:1000001",
        "tgn:7012149",
        "tgn:2002129",
        "tgn:7007827",
        "tgn:7029392"
    ],
    "tgn:id":2510833,
    "tgn:name":"Midland Square",
    "tgn:placetype":[
        "aat:300008347"
    ]
},
  "bbox": [],
  "geometry": {"coordinates":[-112.0333,41.1833],"type":"Point"}
}