{
  "id": 2605354,
  "type": "Feature",
  "properties": {
    "tgn:hierarchy":[
        "tgn:2605354",
        "tgn:1000001",
        "tgn:2002109",
        "tgn:7012149",
        "tgn:7007827",
        "tgn:7029392"
    ],
    "tgn:id":2605354,
    "tgn:name":"Raggy Draws",
    "tgn:placetype":[
        "aat:300055621"
    ]
},
  "bbox": [],
  "geometry": {"coordinates":[-110.75,38.0333],"type":"Point"}
}