{
  "id": 7308637,
  "type": "Feature",
  "properties": {
    "tgn:hierarchy":[
        "tgn:7308637",
        "tgn:1001630",
        "tgn:1000049",
        "tgn:1000002",
        "tgn:7029392"
    ],
    "tgn:id":7308637,
    "tgn:name":"Manchado, Cerro",
    "tgn:placetype":[
        "aat:300008795"
    ]
},
  "bbox": [],
  "geometry": {"coordinates":[-68.766667,-25.733333],"type":"Point"}
}