{
  "id": 2765897,
  "type": "Feature",
  "properties": {
    "tgn:hierarchy":[
        "tgn:2765897",
        "tgn:1000001",
        "tgn:7012149",
        "tgn:7007710",
        "tgn:7029392"
    ],
    "tgn:id":2765897,
    "tgn:name":"White Hall Creek",
    "tgn:placetype":[
        "aat:300008706"
    ]
},
  "bbox": [],
  "geometry": {"coordinates":[-76.6167,41.1167],"type":"Point"}
}