{
  "id": 7504764,
  "type": "Feature",
  "properties": {
    "tgn:hierarchy":[
        "tgn:7504764",
        "tgn:7000508",
        "tgn:1008380",
        "tgn:1000226",
        "tgn:1000006",
        "tgn:7029392"
    ],
    "tgn:id":7504764,
    "tgn:name:en":"Motupotaka Rocks",
    "tgn:placetype":[
        "aat:300011692"
    ]
},
  "bbox": [],
  "geometry": {"coordinates":[175.360833,-36.641944],"type":"Point"}
}