{
  "id": 7011546,
  "type": "Feature",
  "properties": {
    "tgn:hierarchy":[
        "tgn:7011546",
        "tgn:4000818",
        "tgn:1000004",
        "tgn:7018214",
        "tgn:7002435",
        "tgn:7029392"
    ],
    "tgn:id":7011546,
    "tgn:name":"Arkhangelsk",
    "tgn:placetype":[
        "aat:300008347",
        "aat:300008389",
        "aat:300387308",
        "aat:300387220",
        "aat:300387302",
        "aat:300120599",
        "aat:300387286"
    ]
},
  "bbox": [],
  "geometry": {"coordinates":[40.6667,64.5333],"type":"Point"}
}