{
  "id": 1137361,
  "type": "Feature",
  "properties": {
    "tgn:hierarchy":[
        "tgn:1137361",
        "tgn:1000004",
        "tgn:1003408",
        "tgn:7018214",
        "tgn:7002435",
        "tgn:7029392"
    ],
    "tgn:id":1137361,
    "tgn:name":"Dergachi",
    "tgn:placetype":[
        "aat:300008347"
    ]
},
  "bbox": [],
  "geometry": {"coordinates":[48.7667,51.2333],"type":"Point"}
}