{
  "id": 2646075,
  "type": "Feature",
  "properties": {
    "tgn:hierarchy":[
        "tgn:2646075",
        "tgn:1000001",
        "tgn:7012149",
        "tgn:7013961",
        "tgn:7029392"
    ],
    "tgn:id":2646075,
    "tgn:name":"Sawmill Run",
    "tgn:placetype":[
        "aat:300008699"
    ]
},
  "bbox": [],
  "geometry": {"coordinates":[-78.8167,39.1667],"type":"Point"}
}