{
  "id": 2327930,
  "type": "Feature",
  "properties": {
    "tgn:hierarchy":[
        "tgn:2327930",
        "tgn:1000001",
        "tgn:7012149",
        "tgn:2000905",
        "tgn:7007256",
        "tgn:7029392"
    ],
    "tgn:id":2327930,
    "tgn:name":"Fish Lake",
    "tgn:placetype":[
        "aat:300008680"
    ]
},
  "bbox": [],
  "geometry": {"coordinates":[-89.85,30.6333],"type":"Point"}
}