{
  "id": 7388092,
  "type": "Feature",
  "properties": {
    "tgn:hierarchy":[
        "tgn:7388092",
        "tgn:7005581",
        "tgn:1000001",
        "tgn:7005560",
        "tgn:7029392"
    ],
    "tgn:id":7388092,
    "tgn:name":"Pie de la Cuesta",
    "tgn:placetype":[
        "aat:300387007"
    ]
},
  "bbox": [],
  "geometry": {"coordinates":[-108.966667,27.966667],"type":"Point"}
}