{
  "id": 2776564,
  "type": "Feature",
  "properties": {
    "tgn:hierarchy":[
        "tgn:2776564",
        "tgn:1000001",
        "tgn:2000307",
        "tgn:7012149",
        "tgn:7007248",
        "tgn:7029392"
    ],
    "tgn:id":2776564,
    "tgn:name":"Windfield",
    "tgn:placetype":[
        "aat:300008347"
    ]
},
  "bbox": [],
  "geometry": {"coordinates":[-81.7333,32.45],"type":"Point"}
}