{
  "id": 7577646,
  "type": "Feature",
  "properties": {
    "tgn:hierarchy":[
        "tgn:7577646",
        "tgn:1000004",
        "tgn:7000198",
        "tgn:7016722",
        "tgn:7029392"
    ],
    "tgn:id":7577646,
    "tgn:name:en":"Karwan Nad\u012b",
    "tgn:placetype":[
        "aat:300008699"
    ]
},
  "bbox": [],
  "geometry": {"coordinates":[78.079956,27.201629],"type":"Point"}
}