{
  "id": 7518906,
  "type": "Feature",
  "properties": {
    "tgn:hierarchy":[
        "tgn:7518906",
        "tgn:1009227",
        "tgn:1000226",
        "tgn:7520095",
        "tgn:1000006",
        "tgn:7029392"
    ],
    "tgn:id":7518906,
    "tgn:name:en":"Arnst Gully",
    "tgn:placetype":[
        "aat:300008767"
    ]
},
  "bbox": [],
  "geometry": {"coordinates":[172.816667,-41.933333],"type":"Point"}
}