{
  "id": 7569141,
  "type": "Feature",
  "properties": {
    "tgn:hierarchy":[
        "tgn:7569141",
        "tgn:1000004",
        "tgn:7000198",
        "tgn:7016788",
        "tgn:7029392"
    ],
    "tgn:id":7569141,
    "tgn:name:en":"Gad\u0101na",
    "tgn:placetype":[
        "aat:300008347"
    ]
},
  "bbox": [],
  "geometry": {"coordinates":[74.890462,28.678959],"type":"Point"}
}