{
  "id": 2086185,
  "type": "Feature",
  "properties": {
    "tgn:hierarchy":[
        "tgn:2086185",
        "tgn:1000001",
        "tgn:7012149",
        "tgn:1002900",
        "tgn:7007710",
        "tgn:7029392"
    ],
    "tgn:id":2086185,
    "tgn:name":"Bannerville",
    "tgn:placetype":[
        "aat:300008347"
    ]
},
  "bbox": [],
  "geometry": {"coordinates":[-77.3333,40.7167],"type":"Point"}
}