{
  "id": 2288855,
  "type": "Feature",
  "properties": {
    "tgn:hierarchy":[
        "tgn:2288855",
        "tgn:1000001",
        "tgn:7012149",
        "tgn:2000658",
        "tgn:7007253",
        "tgn:7029392"
    ],
    "tgn:id":2288855,
    "tgn:name":"Ditch Number 6",
    "tgn:placetype":[
        "aat:300006075"
    ]
},
  "bbox": [],
  "geometry": {"coordinates":[-93.4167,43.4333],"type":"Point"}
}