{
  "id": 2428074,
  "type": "Feature",
  "properties": {
    "tgn:hierarchy":[
        "tgn:2428074",
        "tgn:1000001",
        "tgn:7012149",
        "tgn:1003045",
        "tgn:7007568",
        "tgn:7029392"
    ],
    "tgn:id":2428074,
    "tgn:name":"Jubertown Swamp",
    "tgn:placetype":[
        "aat:300008905"
    ]
},
  "bbox": [],
  "geometry": {"coordinates":[-77.2167,42.5833],"type":"Point"}
}