{
  "id": 2130946,
  "type": "Feature",
  "properties": {
    "tgn:hierarchy":[
        "tgn:2130946",
        "tgn:1000001",
        "tgn:7012149",
        "tgn:1002967",
        "tgn:7007520",
        "tgn:7029392"
    ],
    "tgn:id":2130946,
    "tgn:name":"Almena",
    "tgn:placetype":[
        "aat:300008347"
    ]
},
  "bbox": [],
  "geometry": {"coordinates":[-85.8167,42.25],"type":"Point"}
}