{
  "id": 2300603,
  "type": "Feature",
  "properties": {
    "tgn:hierarchy":[
        "tgn:2300603",
        "tgn:1000001",
        "tgn:7012149",
        "tgn:7007157",
        "tgn:2000191",
        "tgn:7029392"
    ],
    "tgn:id":2300603,
    "tgn:name":"Dun Juan Point",
    "tgn:placetype":[
        "aat:300008850"
    ]
},
  "bbox": [],
  "geometry": {"coordinates":[-123.4167,40.7833],"type":"Point"}
}