{
  "id": 1094918,
  "type": "Feature",
  "properties": {
    "tgn:hierarchy":[
        "tgn:1094918",
        "tgn:7001242",
        "tgn:1002078",
        "tgn:1000205",
        "tgn:7029392"
    ],
    "tgn:id":1094918,
    "tgn:name":"Dahmani",
    "tgn:placetype":[
        "aat:300008347"
    ]
},
  "bbox": [],
  "geometry": {"coordinates":[8.7833,35.9667],"type":"Point"}
}