{
  "id": 1062620,
  "type": "Feature",
  "properties": {
    "tgn:hierarchy":[
        "tgn:1062620",
        "tgn:7002808",
        "tgn:7030216",
        "tgn:1000003",
        "tgn:1000095",
        "tgn:7029392"
    ],
    "tgn:id":1062620,
    "tgn:name":"Viladec\u00e1ns",
    "tgn:placetype":[
        "aat:300008347"
    ]
},
  "bbox": [],
  "geometry": {"coordinates":[2.016775,41.316881],"type":"Point"}
}