{
  "id": 7479104,
  "type": "Feature",
  "properties": {
    "tgn:hierarchy":[
        "tgn:7479104",
        "tgn:1000004",
        "tgn:7490934",
        "tgn:1000141",
        "tgn:7029392"
    ],
    "tgn:id":7479104,
    "tgn:name":"Beiji Dian",
    "tgn:placetype":[
        "aat:300007595"
    ]
},
  "bbox": [],
  "geometry": {"coordinates":[120.460858,23.122398],"type":"Point"}
}