{
  "id": 2396676,
  "type": "Feature",
  "properties": {
    "tgn:hierarchy":[
        "tgn:2396676",
        "tgn:1002366",
        "tgn:1000001",
        "tgn:7012149",
        "tgn:7007159",
        "tgn:7029392"
    ],
    "tgn:id":2396676,
    "tgn:name":"Holy Ghost Fathers Brook",
    "tgn:placetype":[
        "aat:300008699"
    ]
},
  "bbox": [],
  "geometry": {"coordinates":[-73.45,41.1167],"type":"Point"}
}