{
  "id": 7589590,
  "type": "Feature",
  "properties": {
    "tgn:hierarchy":[
        "tgn:7589590",
        "tgn:1000004",
        "tgn:7000198",
        "tgn:7000799",
        "tgn:7029392"
    ],
    "tgn:id":7589590,
    "tgn:name:en":"Lulo",
    "tgn:placetype":[
        "aat:300008347"
    ]
},
  "bbox": [],
  "geometry": {"coordinates":[76.0125,34.661111],"type":"Point"}
}