{
  "id": 1050779,
  "type": "Feature",
  "properties": {
    "tgn:hierarchy":[
        "tgn:1050779",
        "tgn:7002444",
        "tgn:1000003",
        "tgn:7019152",
        "tgn:7008591",
        "tgn:7029392"
    ],
    "tgn:id":1050779,
    "tgn:name:en":"Kenmore",
    "tgn:placetype":[
        "aat:300008347"
    ]
},
  "bbox": [],
  "geometry": {"coordinates":[-3.983333,56.566667],"type":"Point"}
}