{
  "id": 2226270,
  "type": "Feature",
  "properties": {
    "tgn:hierarchy":[
        "tgn:2226270",
        "tgn:1000001",
        "tgn:7012149",
        "tgn:1002773",
        "tgn:7007240",
        "tgn:7029392"
    ],
    "tgn:id":2226270,
    "tgn:name":"Catfish Lake",
    "tgn:placetype":[
        "aat:300008680"
    ]
},
  "bbox": [],
  "geometry": {"coordinates":[-82.4333,28.1833],"type":"Point"}
}