{
  "id": 2240021,
  "type": "Feature",
  "properties": {
    "tgn:hierarchy":[
        "tgn:2240021",
        "tgn:1000001",
        "tgn:2002148",
        "tgn:7012149",
        "tgn:7007919",
        "tgn:7029392"
    ],
    "tgn:id":2240021,
    "tgn:name":"Cindy Fork",
    "tgn:placetype":[
        "aat:300008699"
    ]
},
  "bbox": [],
  "geometry": {"coordinates":[-82.2167,37.25],"type":"Point"}
}