<<<<<<< HEAD
{
  "id": 7353860,
  "type": "Feature",
  "properties": {
    "tgn:hierarchy":[
        "tgn:7353860",
        "tgn:1000001",
        "tgn:1001960",
        "tgn:7005560",
        "tgn:7029392"
    ],
    "tgn:id":7353860,
    "tgn:name":"Babasac",
    "tgn:placetype":[
        "aat:300008347"
    ]
},
  "bbox": [],
  "geometry": {"coordinates":[-110.8,30.8],"type":"Point"}
}
=======
{"geometry":{"type":"Point","coordinates":[-110.800000,30.800000]},"type":"Feature","properties":{"hierarchy":["tgn:7353860","tgn:1000001","tgn:1001960","tgn:7005560","tgn:7029392"],"placetype":["aat:300008347"],"id":7353860,"name:xx":"Babasac"}}
>>>>>>> 03f74aca74312dbeaf24d7e61306dd6a786dc3d0
