{
  "id": 7585368,
  "type": "Feature",
  "properties": {
    "tgn:hierarchy":[
        "tgn:7585368",
        "tgn:1000004",
        "tgn:7000198",
        "tgn:1001894",
        "tgn:7029392"
    ],
    "tgn:id":7585368,
    "tgn:name:en":"D\u016bnra",
    "tgn:placetype":[
        "aat:300008347"
    ]
},
  "bbox": [],
  "geometry": {"coordinates":[78.970552,24.562013],"type":"Point"}
}