<<<<<<< HEAD
{
  "id": 7050264,
  "type": "Feature",
  "properties": {
    "tgn:hierarchy":[
        "tgn:7050264",
        "tgn:7003170",
        "tgn:1000003",
        "tgn:7003125",
        "tgn:1000080",
        "tgn:7029392"
    ],
    "tgn:id":7050264,
    "tgn:name":"Pietramelina",
    "tgn:placetype":[
        "aat:300008347"
    ]
},
  "bbox": [],
  "geometry": {"coordinates":[12.416667,43.266667],"type":"Point"}
}
=======
{"geometry":{"type":"Point","coordinates":[12.416667,43.266667]},"type":"Feature","properties":{"hierarchy":["tgn:7050264","tgn:7003170","tgn:1000003","tgn:7003125","tgn:1000080","tgn:7029392"],"placetype":["aat:300008347"],"id":7050264,"name:xx":"Pietramelina"}}
>>>>>>> 03f74aca74312dbeaf24d7e61306dd6a786dc3d0
