{
  "id": 7575795,
  "type": "Feature",
  "properties": {
    "tgn:hierarchy":[
        "tgn:7575795",
        "tgn:1000004",
        "tgn:7000198",
        "tgn:7016788",
        "tgn:7029392"
    ],
    "tgn:id":7575795,
    "tgn:name:en":"Khairtal",
    "tgn:placetype":[
        "aat:300007783"
    ]
},
  "bbox": [],
  "geometry": {"coordinates":[76.641673,27.797655],"type":"Point"}
}