{
  "id": 7524423,
  "type": "Feature",
  "properties": {
    "tgn:hierarchy":[
        "tgn:7524423",
        "tgn:7001242",
        "tgn:7016833",
        "tgn:7001335",
        "tgn:7029392"
    ],
    "tgn:id":7524423,
    "tgn:name:en":"B\u00eer el-'Eshsha",
    "tgn:placetype":[
        "aat:300006207"
    ]
},
  "bbox": [],
  "geometry": {"coordinates":[34.206944,31.311667],"type":"Point"}
}