{
  "id": 2786017,
  "type": "Feature",
  "properties": {
    "tgn:hierarchy":[
        "tgn:2786017",
        "tgn:1000001",
        "tgn:7012149",
        "tgn:2001420",
        "tgn:7007526",
        "tgn:7029392"
    ],
    "tgn:id":2786017,
    "tgn:name":"Young Canyon",
    "tgn:placetype":[
        "aat:300008761"
    ]
},
  "bbox": [],
  "geometry": {"coordinates":[-114.1833,38.9333],"type":"Point"}
}