{
  "id": 7380333,
  "type": "Feature",
  "properties": {
    "tgn:hierarchy":[
        "tgn:7380333",
        "tgn:1001835",
        "tgn:1000001",
        "tgn:7005560",
        "tgn:7029392"
    ],
    "tgn:id":7380333,
    "tgn:name":"Rancho Macias",
    "tgn:placetype":[
        "aat:300000241"
    ]
},
  "bbox": [],
  "geometry": {"coordinates":[-115.216667,31.066667],"type":"Point"}
}