{
  "id": 7276711,
  "type": "Feature",
  "properties": {
    "tgn:hierarchy":[
        "tgn:7276711",
        "tgn:1001630",
        "tgn:1000049",
        "tgn:1000002",
        "tgn:7029392"
    ],
    "tgn:id":7276711,
    "tgn:name":"Villanueva, Sierra",
    "tgn:placetype":[
        "aat:300008795"
    ]
},
  "bbox": [],
  "geometry": {"coordinates":[-69.683333,-26.566667],"type":"Point"}
}