{
  "id": 7495208,
  "type": "Feature",
  "properties": {
    "tgn:hierarchy":[
        "tgn:7495208",
        "tgn:1000004",
        "tgn:7001013",
        "tgn:1000141",
        "tgn:7029392"
    ],
    "tgn:id":7495208,
    "tgn:name":"Daxi Qiao",
    "tgn:placetype":[
        "aat:300007836"
    ]
},
  "bbox": [],
  "geometry": {"coordinates":[121.283263,24.884845],"type":"Point"}
}