{
  "id": 2059597,
  "type": "Feature",
  "properties": {
    "tgn:hierarchy":[
        "tgn:2059597",
        "tgn:1000001",
        "tgn:7012149",
        "tgn:1002517",
        "tgn:7007523",
        "tgn:7029392"
    ],
    "tgn:id":2059597,
    "tgn:name":"Ludwig",
    "tgn:placetype":[
        "aat:300387016"
    ]
},
  "bbox": [],
  "geometry": {"coordinates":[-90.4167,38.2333],"type":"Point"}
}