{
  "id": 1123288,
  "type": "Feature",
  "properties": {
    "tgn:hierarchy":[
        "tgn:1123288",
        "tgn:1000004",
        "tgn:1001390",
        "tgn:1000111",
        "tgn:7029392"
    ],
    "tgn:id":1123288,
    "tgn:name":"Daling",
    "tgn:placetype":[
        "aat:300008707"
    ]
},
  "bbox": [],
  "geometry": {"coordinates":[121.7333,40.9333],"type":"Point"}
}