{
  "id": 2785193,
  "type": "Feature",
  "properties": {
    "tgn:hierarchy":[
        "tgn:2785193",
        "tgn:1000001",
        "tgn:7012149",
        "tgn:1002999",
        "tgn:7007526",
        "tgn:7029392"
    ],
    "tgn:id":2785193,
    "tgn:name":"Yellow Rock Spring",
    "tgn:placetype":[
        "aat:300008697"
    ]
},
  "bbox": [],
  "geometry": {"coordinates":[-119.4333,41.35],"type":"Point"}
}