{
  "id": 2700580,
  "type": "Feature",
  "properties": {
    "tgn:hierarchy":[
        "tgn:2700580",
        "tgn:1000001",
        "tgn:7012149",
        "tgn:2000967",
        "tgn:7007520",
        "tgn:7029392"
    ],
    "tgn:id":2700580,
    "tgn:name":"Sucker Creek",
    "tgn:placetype":[
        "aat:300008706"
    ]
},
  "bbox": [],
  "geometry": {"coordinates":[-84.9667,43.7833],"type":"Point"}
}