{
  "id": 2369685,
  "type": "Feature",
  "properties": {
    "tgn:hierarchy":[
        "tgn:2369685",
        "tgn:1000001",
        "tgn:7006451",
        "tgn:7012149",
        "tgn:2000100",
        "tgn:7029392"
    ],
    "tgn:id":2369685,
    "tgn:name":"Gunsight Wash",
    "tgn:placetype":[
        "aat:300008699"
    ]
},
  "bbox": [],
  "geometry": {"coordinates":[-112.5833,32.15],"type":"Point"}
}