{
  "id": 2293075,
  "type": "Feature",
  "properties": {
    "tgn:hierarchy":[
        "tgn:2293075",
        "tgn:1000001",
        "tgn:7006451",
        "tgn:2000092",
        "tgn:7012149",
        "tgn:7029392"
    ],
    "tgn:id":2293075,
    "tgn:name":"Dotson Spring",
    "tgn:placetype":[
        "aat:300008697"
    ]
},
  "bbox": [],
  "geometry": {"coordinates":[-111.2333,36.1333],"type":"Point"}
}