{
  "id": 7586878,
  "type": "Feature",
  "properties": {
    "tgn:hierarchy":[
        "tgn:7586878",
        "tgn:1000004",
        "tgn:7000198",
        "tgn:7000799",
        "tgn:7029392"
    ],
    "tgn:id":7586878,
    "tgn:name:en":"Rakh Gand\u0101ka Sh\u0101h",
    "tgn:placetype":[
        "aat:300008903"
    ]
},
  "bbox": [],
  "geometry": {"coordinates":[74.758333,34.083333],"type":"Point"}
}