<<<<<<< HEAD
{
  "id": 2405385,
  "type": "Feature",
  "properties": {
    "tgn:hierarchy":[
        "tgn:2405385",
        "tgn:1000001",
        "tgn:7012149",
        "tgn:7007825",
        "tgn:7029392"
    ],
    "tgn:id":2405385,
    "tgn:name":"Huggins Creek",
    "tgn:placetype":[
        "aat:300008706"
    ]
},
  "bbox": [],
  "geometry": {"coordinates":[-88.6,35.2667],"type":"Point"}
}
=======
{"geometry":{"type":"Point","coordinates":[-88.600000,35.266700]},"type":"Feature","properties":{"hierarchy":["tgn:2405385","tgn:1000001","tgn:7012149","tgn:7007825","tgn:7029392"],"placetype":["aat:300008706"],"id":2405385,"name:xx":"Huggins Creek"}}
>>>>>>> 03f74aca74312dbeaf24d7e61306dd6a786dc3d0
