{
  "id": 7561692,
  "type": "Feature",
  "properties": {
    "tgn:hierarchy":[
        "tgn:7561692",
        "tgn:1000004",
        "tgn:7000198",
        "tgn:7016722",
        "tgn:7029392"
    ],
    "tgn:id":7561692,
    "tgn:name:en":"Hay\u0101tnagar",
    "tgn:placetype":[
        "aat:300008347"
    ]
},
  "bbox": [],
  "geometry": {"coordinates":[79.205097,27.952311],"type":"Point"}
}