{
  "id": 2589469,
  "type": "Feature",
  "properties": {
    "tgn:hierarchy":[
        "tgn:2589469",
        "tgn:7006450",
        "tgn:1000001",
        "tgn:7012149",
        "tgn:2124005",
        "tgn:7029392"
    ],
    "tgn:id":2589469,
    "tgn:name":"Point Gordon",
    "tgn:placetype":[
        "aat:300008850"
    ]
},
  "bbox": [],
  "geometry": {"coordinates":[-146.6167,70.1833],"type":"Point"}
}