{
  "id": 2140332,
  "type": "Feature",
  "properties": {
    "tgn:hierarchy":[
        "tgn:2140332",
        "tgn:1000001",
        "tgn:7012149",
        "tgn:1003007",
        "tgn:7007706",
        "tgn:7029392"
    ],
    "tgn:id":2140332,
    "tgn:name":"Aukerman",
    "tgn:placetype":[
        "aat:300008347"
    ]
},
  "bbox": [],
  "geometry": {"coordinates":[-82.0167,40.95],"type":"Point"}
}