{
  "id": 2599120,
  "type": "Feature",
  "properties": {
    "tgn:hierarchy":[
        "tgn:2599120",
        "tgn:1000001",
        "tgn:7012149",
        "tgn:2001298",
        "tgn:7007524",
        "tgn:7029392"
    ],
    "tgn:id":2599120,
    "tgn:name":"Prison Farm",
    "tgn:placetype":[
        "aat:300008347"
    ]
},
  "bbox": [],
  "geometry": {"coordinates":[-112.7167,46.3833],"type":"Point"}
}