{
  "id": 7297835,
  "type": "Feature",
  "properties": {
    "tgn:hierarchy":[
        "tgn:7297835",
        "tgn:7002820",
        "tgn:7030216",
        "tgn:1000003",
        "tgn:1000095",
        "tgn:7029392"
    ],
    "tgn:id":7297835,
    "tgn:name":"Sert, R\u00edo",
    "tgn:placetype":[
        "aat:300008699"
    ]
},
  "bbox": [],
  "geometry": {"coordinates":[2.759743,42.186188],"type":"Point"}
}