{
  "id": 1097936,
  "type": "Feature",
  "properties": {
    "tgn:hierarchy":[
        "tgn:1097936",
        "tgn:7000490",
        "tgn:1000006",
        "tgn:7001830",
        "tgn:7029392"
    ],
    "tgn:id":1097936,
    "tgn:name":"Pentland",
    "tgn:placetype":[
        "aat:300008347"
    ]
},
  "bbox": [],
  "geometry": {"coordinates":[145.4167,-20.5167],"type":"Point"}
}