<<<<<<< HEAD
{
  "id": 7113177,
  "type": "Feature",
  "properties": {
    "tgn:hierarchy":[
        "tgn:7113177",
        "tgn:1000003",
        "tgn:7003676",
        "tgn:7000084",
        "tgn:7029392"
    ],
    "tgn:id":7113177,
    "tgn:name":"Rodetal",
    "tgn:placetype":[
        "aat:300008761"
    ]
},
  "bbox": [],
  "geometry": {"coordinates":[9.95,51.616667],"type":"Point"}
}
=======
{"geometry":{"type":"Point","coordinates":[9.950000,51.616667]},"type":"Feature","properties":{"hierarchy":["tgn:7113177","tgn:1000003","tgn:7003676","tgn:7000084","tgn:7029392"],"placetype":["aat:300008761"],"id":7113177,"name:xx":"Rodetal"}}
>>>>>>> 03f74aca74312dbeaf24d7e61306dd6a786dc3d0
