{
  "id": 7344227,
  "type": "Feature",
  "properties": {
    "tgn:hierarchy":[
        "tgn:7344227",
        "tgn:7002759",
        "tgn:7002843",
        "tgn:1000003",
        "tgn:1000095",
        "tgn:7029392"
    ],
    "tgn:id":7344227,
    "tgn:name":"Barrio de las Minas",
    "tgn:placetype":[
        "aat:300008347"
    ]
},
  "bbox": [],
  "geometry": {"coordinates":[-1.183333,40.133333],"type":"Point"}
}