{
  "id": 2595260,
  "type": "Feature",
  "properties": {
    "tgn:hierarchy":[
        "tgn:2595260",
        "tgn:1000001",
        "tgn:2000955",
        "tgn:7012149",
        "tgn:7007520",
        "tgn:7029392"
    ],
    "tgn:id":2595260,
    "tgn:name":"Pot Lake",
    "tgn:placetype":[
        "aat:300008680"
    ]
},
  "bbox": [],
  "geometry": {"coordinates":[-86.4833,46.1333],"type":"Point"}
}