{
  "id": 2156280,
  "type": "Feature",
  "properties": {
    "tgn:hierarchy":[
        "tgn:2156280",
        "tgn:7006450",
        "tgn:1000001",
        "tgn:7012149",
        "tgn:2000089",
        "tgn:7029392"
    ],
    "tgn:id":2156280,
    "tgn:name":"Bearnose Hill",
    "tgn:placetype":[
        "aat:300008798"
    ]
},
  "bbox": [],
  "geometry": {"coordinates":[-143.4333,66.4667],"type":"Point"}
}