<<<<<<< HEAD
{
  "id": 2156280,
  "type": "Feature",
  "properties": {
    "tgn:hierarchy":[
        "tgn:2156280",
        "tgn:7006450",
        "tgn:1000001",
        "tgn:7012149",
        "tgn:2000089",
        "tgn:7029392"
    ],
    "tgn:id":2156280,
    "tgn:name":"Bearnose Hill",
    "tgn:placetype":[
        "aat:300008798"
    ]
},
  "bbox": [],
  "geometry": {"coordinates":[-143.4333,66.4667],"type":"Point"}
}
=======
{"geometry":{"type":"Point","coordinates":[-143.433300,66.466700]},"type":"Feature","properties":{"hierarchy":["tgn:2156280","tgn:7006450","tgn:1000001","tgn:7012149","tgn:2000089","tgn:7029392"],"placetype":["aat:300008798"],"id":2156280,"name:xx":"Bearnose Hill"}}
>>>>>>> 03f74aca74312dbeaf24d7e61306dd6a786dc3d0
