{
  "id": 7400403,
  "type": "Feature",
  "properties": {
    "tgn:hierarchy":[
        "tgn:7400403",
        "tgn:1000001",
        "tgn:7005599",
        "tgn:7005560",
        "tgn:7029392"
    ],
    "tgn:id":7400403,
    "tgn:name":"San Pedro, R\u00edo",
    "tgn:placetype":[
        "aat:300008699"
    ]
},
  "bbox": [],
  "geometry": {"coordinates":[-98.516667,21.383333],"type":"Point"}
}