{
  "id": 2554456,
  "type": "Feature",
  "properties": {
    "tgn:hierarchy":[
        "tgn:2554456",
        "tgn:1002169",
        "tgn:1000001",
        "tgn:7012149",
        "tgn:7007255",
        "tgn:7029392"
    ],
    "tgn:id":2554456,
    "tgn:name":"Oakla",
    "tgn:placetype":[
        "aat:300008347"
    ]
},
  "bbox": [],
  "geometry": {"coordinates":[-83.7167,38.2333],"type":"Point"}
}