{
  "id": 2169039,
  "type": "Feature",
  "properties": {
    "tgn:hierarchy":[
        "tgn:2169039",
        "tgn:1000001",
        "tgn:7012149",
        "tgn:1002411",
        "tgn:7007919",
        "tgn:7029392"
    ],
    "tgn:id":2169039,
    "tgn:name":"Big Island",
    "tgn:placetype":[
        "aat:300008791"
    ]
},
  "bbox": [],
  "geometry": {"coordinates":[-76.3667,37.2667],"type":"Point"}
}