{
  "id": 2740012,
  "type": "Feature",
  "properties": {
    "tgn:hierarchy":[
        "tgn:2740012",
        "tgn:1000001",
        "tgn:7012149",
        "tgn:2001718",
        "tgn:7007708",
        "tgn:7029392"
    ],
    "tgn:id":2740012,
    "tgn:name":"Upper Gregory Creek Reservoir",
    "tgn:placetype":[
        "aat:300006191"
    ]
},
  "bbox": [],
  "geometry": {"coordinates":[-117.9333,43.9667],"type":"Point"}
}