{
  "id": 1121383,
  "type": "Feature",
  "properties": {
    "tgn:hierarchy":[
        "tgn:1121383",
        "tgn:7016644",
        "tgn:1000001",
        "tgn:7005560",
        "tgn:7029392"
    ],
    "tgn:id":1121383,
    "tgn:name":"Armer\u00eda, R\u00edo",
    "tgn:placetype":[
        "aat:300008707",
        "aat:300008699"
    ]
},
  "bbox": [],
  "geometry": {"coordinates":[-103.983333,18.866667],"type":"Point"}
}