<<<<<<< HEAD
{
  "id": 2256505,
  "type": "Feature",
  "properties": {
    "tgn:hierarchy":[
        "tgn:2256505",
        "tgn:1000001",
        "tgn:7012149",
        "tgn:2000966",
        "tgn:7007520",
        "tgn:7029392"
    ],
    "tgn:id":2256505,
    "tgn:name":"Corbett Lake",
    "tgn:placetype":[
        "aat:300008680"
    ]
},
  "bbox": [],
  "geometry": {"coordinates":[-88.15,46.2],"type":"Point"}
}
=======
{"geometry":{"type":"Point","coordinates":[-88.150000,46.200000]},"type":"Feature","properties":{"hierarchy":["tgn:2256505","tgn:1000001","tgn:7012149","tgn:2000966","tgn:7007520","tgn:7029392"],"placetype":["aat:300008680"],"id":2256505,"name:xx":"Corbett Lake"}}
>>>>>>> 03f74aca74312dbeaf24d7e61306dd6a786dc3d0
