<<<<<<< HEAD
{
  "id": 7111476,
  "type": "Feature",
  "properties": {
    "tgn:hierarchy":[
        "tgn:7111476",
        "tgn:1000003",
        "tgn:7003688",
        "tgn:7000084",
        "tgn:7029392"
    ],
    "tgn:id":7111476,
    "tgn:name":"Rickelsb\u00fcll",
    "tgn:placetype":[
        "aat:300000206"
    ]
},
  "bbox": [],
  "geometry": {"coordinates":[8.666667,54.9],"type":"Point"}
}
=======
{"geometry":{"type":"Point","coordinates":[8.666667,54.900000]},"type":"Feature","properties":{"hierarchy":["tgn:7111476","tgn:1000003","tgn:7003688","tgn:7000084","tgn:7029392"],"placetype":["aat:300000206"],"id":7111476,"name:xx":"Rickelsb\u00fcll"}}
>>>>>>> 03f74aca74312dbeaf24d7e61306dd6a786dc3d0
