{
  "id": 7170184,
  "type": "Feature",
  "properties": {
    "tgn:hierarchy":[
        "tgn:7170184",
        "tgn:1000003",
        "tgn:7003676",
        "tgn:7000084",
        "tgn:7029392"
    ],
    "tgn:id":7170184,
    "tgn:name":"Hinterbruch",
    "tgn:placetype":[
        "aat:300055621"
    ]
},
  "bbox": [],
  "geometry": {"coordinates":[8.283333,52.383333],"type":"Point"}
}