{
  "id": 7249893,
  "type": "Feature",
  "properties": {
    "tgn:hierarchy":[
        "tgn:7249893",
        "tgn:7003466",
        "tgn:1000003",
        "tgn:1000063",
        "tgn:4012014",
        "tgn:7029392"
    ],
    "tgn:id":7249893,
    "tgn:name":"Noiseux",
    "tgn:placetype":[
        "aat:300008347"
    ]
},
  "bbox": [],
  "geometry": {"coordinates":[5.376478,50.300691],"type":"Point"}
}