{
  "id": 7060001,
  "type": "Feature",
  "properties": {
    "tgn:hierarchy":[
        "tgn:7060001",
        "tgn:7003669",
        "tgn:1000003",
        "tgn:7000084",
        "tgn:7029392"
    ],
    "tgn:id":7060001,
    "tgn:name":"Alladorf",
    "tgn:placetype":[
        "aat:300008347"
    ]
},
  "bbox": [],
  "geometry": {"coordinates":[11.383333,49.966667],"type":"Point"}
}