{
  "id": 2257090,
  "type": "Feature",
  "properties": {
    "tgn:hierarchy":[
        "tgn:2257090",
        "tgn:1000001",
        "tgn:1002213",
        "tgn:7012149",
        "tgn:7007710",
        "tgn:7029392"
    ],
    "tgn:id":2257090,
    "tgn:name":"Cornell",
    "tgn:placetype":[
        "aat:300008347"
    ]
},
  "bbox": [],
  "geometry": {"coordinates":[-75.0167,40.1833],"type":"Point"}
}