{
  "id": 2486162,
  "type": "Feature",
  "properties": {
    "tgn:hierarchy":[
        "tgn:2486162",
        "tgn:1000001",
        "tgn:2002242",
        "tgn:7012149",
        "tgn:7007920",
        "tgn:7029392"
    ],
    "tgn:id":2486162,
    "tgn:name":"Leahy",
    "tgn:placetype":[
        "aat:300008347"
    ]
},
  "bbox": [],
  "geometry": {"coordinates":[-119.3833,47.9167],"type":"Point"}
}