{
  "id": 7032652,
  "type": "Feature",
  "properties": {
    "tgn:hierarchy":[
        "tgn:7032652",
        "tgn:7002445",
        "tgn:1000003",
        "tgn:7019054",
        "tgn:7008591",
        "tgn:7029392"
    ],
    "tgn:id":7032652,
    "tgn:name":"Waterton",
    "tgn:placetype":[
        "aat:300020756",
        "aat:300008347",
        "aat:300000810",
        "aat:300167671",
        "aat:300008372"
    ]
},
  "bbox": [],
  "geometry": {"coordinates":[-0.711,53.6511],"type":"Point"}
}