{
  "id": 1008559,
  "type": "Feature",
  "properties": {
    "tgn:hierarchy":[
        "tgn:1008559",
        "tgn:7005151",
        "tgn:7005152",
        "tgn:1000002",
        "tgn:7029392"
    ],
    "tgn:id":1008559,
    "tgn:name":"Pebble Island",
    "tgn:placetype":[
        "aat:300008791"
    ]
},
  "bbox": [],
  "geometry": {"coordinates":[-59.5833,-51.3167],"type":"Point"}
}