{
  "id": 7188451,
  "type": "Feature",
  "properties": {
    "tgn:hierarchy":[
        "tgn:7188451",
        "tgn:1000003",
        "tgn:7003682",
        "tgn:7000084",
        "tgn:7029392"
    ],
    "tgn:id":7188451,
    "tgn:name":"Essingen",
    "tgn:placetype":[
        "aat:300000745"
    ]
},
  "bbox": [],
  "geometry": {"coordinates":[6.716667,50.266667],"type":"Point"}
}