{
  "id": 7585853,
  "type": "Feature",
  "properties": {
    "tgn:hierarchy":[
        "tgn:7585853",
        "tgn:1000004",
        "tgn:7000198",
        "tgn:7000799",
        "tgn:7029392"
    ],
    "tgn:id":7585853,
    "tgn:name:en":"L\u0101lbug",
    "tgn:placetype":[
        "aat:300008347"
    ]
},
  "bbox": [],
  "geometry": {"coordinates":[74.358333,34.368056],"type":"Point"}
}