{
  "id": 1022254,
  "type": "Feature",
  "properties": {
    "tgn:hierarchy":[
        "tgn:1022254",
        "tgn:7006247",
        "tgn:1000047",
        "tgn:7002456",
        "tgn:1000002",
        "tgn:7029392"
    ],
    "tgn:id":1022254,
    "tgn:name":"Oeiras do Par\u00e1",
    "tgn:placetype":[
        "aat:300008347"
    ]
},
  "bbox": [],
  "geometry": {"coordinates":[-49.85,-1.9667],"type":"Point"}
}