{
  "id": 7511260,
  "type": "Feature",
  "properties": {
    "tgn:hierarchy":[
        "tgn:7511260",
        "tgn:1009227",
        "tgn:1000226",
        "tgn:7016729",
        "tgn:1000006",
        "tgn:7029392"
    ],
    "tgn:id":7511260,
    "tgn:name:en":"Tuamarina",
    "tgn:placetype":[
        "aat:300008777"
    ]
},
  "bbox": [],
  "geometry": {"coordinates":[173.933333,-41.433333],"type":"Point"}
}