{
  "id": 2379621,
  "type": "Feature",
  "properties": {
    "tgn:hierarchy":[
        "tgn:2379621",
        "tgn:1000001",
        "tgn:7012149",
        "tgn:2001274",
        "tgn:7007524",
        "tgn:7029392"
    ],
    "tgn:id":2379621,
    "tgn:name":"Hash Mountain",
    "tgn:placetype":[
        "aat:300008798"
    ]
},
  "bbox": [],
  "geometry": {"coordinates":[-114.0167,48.2333],"type":"Point"}
}