{
  "id": 7254178,
  "type": "Feature",
  "properties": {
    "tgn:hierarchy":[
        "tgn:7254178",
        "tgn:7003461",
        "tgn:1000003",
        "tgn:1000063",
        "tgn:7018236",
        "tgn:7029392"
    ],
    "tgn:id":7254178,
    "tgn:name":"Schoorbroek",
    "tgn:placetype":[
        "aat:300008347"
    ]
},
  "bbox": [],
  "geometry": {"coordinates":[5.127069,50.785671],"type":"Point"}
}