{
  "id": 1010689,
  "type": "Feature",
  "properties": {
    "tgn:hierarchy":[
        "tgn:1010689",
        "tgn:7002878",
        "tgn:1000003",
        "tgn:1000070",
        "tgn:7029392"
    ],
    "tgn:id":1010689,
    "tgn:name":"Ferret, Cap",
    "tgn:placetype":[
        "aat:300008850"
    ]
},
  "bbox": [],
  "geometry": {"coordinates":[-1.2667,44.6333],"type":"Point"}
}