{
  "id": 7119788,
  "type": "Feature",
  "properties": {
    "tgn:hierarchy":[
        "tgn:7119788",
        "tgn:7003669",
        "tgn:1000003",
        "tgn:7000084",
        "tgn:7029392"
    ],
    "tgn:id":7119788,
    "tgn:name":"Pfistern",
    "tgn:placetype":[
        "aat:300008347"
    ]
},
  "bbox": [],
  "geometry": {"coordinates":[11.566667,47.733333],"type":"Point"}
}