{
  "id": 7103852,
  "type": "Feature",
  "properties": {
    "tgn:hierarchy":[
        "tgn:7103852",
        "tgn:1000003",
        "tgn:7003682",
        "tgn:7000084",
        "tgn:7029392"
    ],
    "tgn:id":7103852,
    "tgn:name":"Schmalenberg",
    "tgn:placetype":[
        "aat:300008347"
    ]
},
  "bbox": [],
  "geometry": {"coordinates":[7.733333,49.333333],"type":"Point"}
}