{
  "id": 2175801,
  "type": "Feature",
  "properties": {
    "tgn:hierarchy":[
        "tgn:2175801",
        "tgn:1000001",
        "tgn:7012149",
        "tgn:1002980",
        "tgn:7007826",
        "tgn:7029392"
    ],
    "tgn:id":2175801,
    "tgn:name":"Black Creek",
    "tgn:placetype":[
        "aat:300008706"
    ]
},
  "bbox": [],
  "geometry": {"coordinates":[-95.6167,30.85],"type":"Point"}
}