{
  "id": 2394799,
  "type": "Feature",
  "properties": {
    "tgn:hierarchy":[
        "tgn:2394799",
        "tgn:1000001",
        "tgn:2000920",
        "tgn:7012149",
        "tgn:7007515",
        "tgn:7029392"
    ],
    "tgn:id":2394799,
    "tgn:name":"Holbrook Ledge",
    "tgn:placetype":[
        "aat:300132348"
    ]
},
  "bbox": [],
  "geometry": {"coordinates":[-69.9333,43.7333],"type":"Point"}
}