{
  "id": 2417972,
  "type": "Feature",
  "properties": {
    "tgn:hierarchy":[
        "tgn:2417972",
        "tgn:1000001",
        "tgn:2000469",
        "tgn:7012149",
        "tgn:7007250",
        "tgn:7029392"
    ],
    "tgn:id":2417972,
    "tgn:name":"Jackson Mountain",
    "tgn:placetype":[
        "aat:300008798"
    ]
},
  "bbox": [],
  "geometry": {"coordinates":[-116.2667,46.8167],"type":"Point"}
}