<<<<<<< HEAD
{
  "id": 2156995,
  "type": "Feature",
  "properties": {
    "tgn:hierarchy":[
        "tgn:2156995",
        "tgn:1000001",
        "tgn:7012149",
        "tgn:7007157",
        "tgn:1002863",
        "tgn:7029392"
    ],
    "tgn:id":2156995,
    "tgn:name":"Beauty Spring",
    "tgn:placetype":[
        "aat:300008697"
    ]
},
  "bbox": [],
  "geometry": {"coordinates":[-120.7667,35.4667],"type":"Point"}
}
=======
{"geometry":{"type":"Point","coordinates":[-120.766700,35.466700]},"type":"Feature","properties":{"hierarchy":["tgn:2156995","tgn:1000001","tgn:7012149","tgn:7007157","tgn:1002863","tgn:7029392"],"placetype":["aat:300008697"],"id":2156995,"name:xx":"Beauty Spring"}}
>>>>>>> 03f74aca74312dbeaf24d7e61306dd6a786dc3d0
