{
  "id": 1034224,
  "type": "Feature",
  "properties": {
    "tgn:hierarchy":[
        "tgn:1034224",
        "tgn:1000003",
        "tgn:1000070",
        "tgn:7002895",
        "tgn:7029392"
    ],
    "tgn:id":1034224,
    "tgn:name:fr":"Mandelieu",
    "tgn:name:la":"Manduolocus",
    "tgn:placetype":[
        "aat:300008347",
        "aat:300000745"
    ]
},
  "bbox": [],
  "geometry": {"coordinates":[6.9333,43.55],"type":"Point"}
}