<<<<<<< HEAD
{
  "id": 7357582,
  "type": "Feature",
  "properties": {
    "tgn:hierarchy":[
        "tgn:7357582",
        "tgn:7005581",
        "tgn:1000001",
        "tgn:7005560",
        "tgn:7029392"
    ],
    "tgn:id":7357582,
    "tgn:name":"Corrales, Cerro",
    "tgn:placetype":[
        "aat:300008795"
    ]
},
  "bbox": [],
  "geometry": {"coordinates":[-105.066667,26.916667],"type":"Point"}
}
=======
{"geometry":{"type":"Point","coordinates":[-105.066667,26.916667]},"type":"Feature","properties":{"hierarchy":["tgn:7357582","tgn:7005581","tgn:1000001","tgn:7005560","tgn:7029392"],"placetype":["aat:300008795"],"id":7357582,"name:xx":"Corrales, Cerro"}}
>>>>>>> 03f74aca74312dbeaf24d7e61306dd6a786dc3d0
