{
  "id": 7392538,
  "type": "Feature",
  "properties": {
    "tgn:hierarchy":[
        "tgn:7392538",
        "tgn:1001835",
        "tgn:1000001",
        "tgn:7005560",
        "tgn:7029392"
    ],
    "tgn:id":7392538,
    "tgn:name":"Redondo, Morro",
    "tgn:placetype":[
        "aat:300386846"
    ]
},
  "bbox": [],
  "geometry": {"coordinates":[-115.183333,28.05],"type":"Point"}
}