<<<<<<< HEAD
{
  "id": 7029344,
  "type": "Feature",
  "properties": {
    "tgn:hierarchy":[
        "tgn:7029344",
        "tgn:7002445",
        "tgn:1000003",
        "tgn:7019057",
        "tgn:7008591",
        "tgn:7029392"
    ],
    "tgn:id":7029344,
    "tgn:name:en":"Seaton Ross",
    "tgn:placetype":[
        "aat:300008347",
        "aat:300008372"
    ]
},
  "bbox": [],
  "geometry": {"coordinates":[-0.816667,53.85],"type":"Point"}
}
=======
{"geometry":{"type":"Point","coordinates":[-0.816667,53.850000]},"type":"Feature","properties":{"hierarchy":["tgn:7029344","tgn:7002445","tgn:1000003","tgn:7019057","tgn:7008591","tgn:7029392"],"placetype":["aat:300008347","aat:300008372"],"name:en":"Seaton Ross","id":7029344}}
>>>>>>> 03f74aca74312dbeaf24d7e61306dd6a786dc3d0
