{
  "id": 2201737,
  "type": "Feature",
  "properties": {
    "tgn:hierarchy":[
        "tgn:2201737",
        "tgn:1000001",
        "tgn:7012149",
        "tgn:1003034",
        "tgn:7007826",
        "tgn:7029392"
    ],
    "tgn:id":2201737,
    "tgn:name":"Buck Creek",
    "tgn:placetype":[
        "aat:300008706"
    ]
},
  "bbox": [],
  "geometry": {"coordinates":[-95.35,32.8167],"type":"Point"}
}