{
  "id": 1099994,
  "type": "Feature",
  "properties": {
    "tgn:hierarchy":[
        "tgn:1099994",
        "tgn:1000003",
        "tgn:7003142",
        "tgn:7003236",
        "tgn:1000080",
        "tgn:7029392"
    ],
    "tgn:id":1099994,
    "tgn:name":"Madonna della Guardia",
    "tgn:placetype":[
        "aat:300007466"
    ]
},
  "bbox": [],
  "geometry": {"coordinates":[8.85,44.4833],"type":"Point"}
}