{
  "id": 2056096,
  "type": "Feature",
  "properties": {
    "tgn:hierarchy":[
        "tgn:2056096",
        "tgn:1000001",
        "tgn:7012149",
        "tgn:2001130",
        "tgn:7007522",
        "tgn:7029392"
    ],
    "tgn:id":2056096,
    "tgn:name":"Cameron",
    "tgn:placetype":[
        "aat:300008347",
        "aat:300387210"
    ]
},
  "bbox": [],
  "geometry": {"coordinates":[-89.8833,32.8333],"type":"Point"}
}