{
  "id": 2560497,
  "type": "Feature",
  "properties": {
    "tgn:hierarchy":[
        "tgn:2560497",
        "tgn:1000001",
        "tgn:7012149",
        "tgn:2000481",
        "tgn:7007250",
        "tgn:7029392"
    ],
    "tgn:id":2560497,
    "tgn:name":"Ore Cash Mine",
    "tgn:placetype":[
        "aat:300000390"
    ]
},
  "bbox": [],
  "geometry": {"coordinates":[-113.6833,45.2833],"type":"Point"}
}