{
  "id": 7310759,
  "type": "Feature",
  "properties": {
    "tgn:hierarchy":[
        "tgn:7310759",
        "tgn:1001702",
        "tgn:1000049",
        "tgn:1000002",
        "tgn:7029392"
    ],
    "tgn:id":7310759,
    "tgn:name":"Middleton, Banco",
    "tgn:placetype":[
        "aat:300387036"
    ]
},
  "bbox": [],
  "geometry": {"coordinates":[-70.266667,-52.916667],"type":"Point"}
}