{
  "id": 1018978,
  "type": "Feature",
  "properties": {
    "tgn:hierarchy":[
        "tgn:1018978",
        "tgn:7017441",
        "tgn:1000001",
        "tgn:7004643",
        "tgn:7029392"
    ],
    "tgn:id":1018978,
    "tgn:name":"Las Pi\u00f1as",
    "tgn:placetype":[
        "aat:300008347"
    ]
},
  "bbox": [],
  "geometry": {"coordinates":[-65.9167,18.25],"type":"Point"}
}