<<<<<<< HEAD
{
  "id": 2704121,
  "type": "Feature",
  "properties": {
    "tgn:hierarchy":[
        "tgn:2704121",
        "tgn:1000001",
        "tgn:7012149",
        "tgn:7007157",
        "tgn:1002857",
        "tgn:7029392"
    ],
    "tgn:id":2704121,
    "tgn:name":"Sunflower Spring",
    "tgn:placetype":[
        "aat:300008697"
    ]
},
  "bbox": [],
  "geometry": {"coordinates":[-115.1167,34.5333],"type":"Point"}
}
=======
{"geometry":{"type":"Point","coordinates":[-115.116700,34.533300]},"type":"Feature","properties":{"hierarchy":["tgn:2704121","tgn:1000001","tgn:7012149","tgn:7007157","tgn:1002857","tgn:7029392"],"placetype":["aat:300008697"],"id":2704121,"name:xx":"Sunflower Spring"}}
>>>>>>> 03f74aca74312dbeaf24d7e61306dd6a786dc3d0
