{
  "id": 7377062,
  "type": "Feature",
  "properties": {
    "tgn:hierarchy":[
        "tgn:7377062",
        "tgn:1000001",
        "tgn:7005594",
        "tgn:7005560",
        "tgn:7029392"
    ],
    "tgn:id":7377062,
    "tgn:name":"La Trinidad",
    "tgn:placetype":[
        "aat:300008347"
    ]
},
  "bbox": [],
  "geometry": {"coordinates":[-101.216667,23.116667],"type":"Point"}
}