{
  "id": 2249257,
  "type": "Feature",
  "properties": {
    "tgn:hierarchy":[
        "tgn:2249257",
        "tgn:1000001",
        "tgn:7012149",
        "tgn:7029392"
    ],
    "tgn:id":2249257,
    "tgn:name":"Cole River",
    "tgn:placetype":[
        "aat:300008707"
    ]
},
  "bbox": [],
  "geometry": {"coordinates":[-71.1667,41.8333],"type":"Point"}
}