{
  "id": 7274962,
  "type": "Feature",
  "properties": {
    "tgn:hierarchy":[
        "tgn:7274962",
        "tgn:1001702",
        "tgn:1000049",
        "tgn:1000002",
        "tgn:7029392"
    ],
    "tgn:id":7274962,
    "tgn:name":"Julepe, Punta",
    "tgn:placetype":[
        "aat:300386846"
    ]
},
  "bbox": [],
  "geometry": {"coordinates":[-70.783333,-54.75],"type":"Point"}
}