{
  "id": 2469193,
  "type": "Feature",
  "properties": {
    "tgn:hierarchy":[
        "tgn:2469193",
        "tgn:1000001",
        "tgn:2000859",
        "tgn:7012149",
        "tgn:7007256",
        "tgn:7029392"
    ],
    "tgn:id":2469193,
    "tgn:name":"Longacre",
    "tgn:placetype":[
        "aat:300008347"
    ]
},
  "bbox": [],
  "geometry": {"coordinates":[-93.15,30.8167],"type":"Point"}
}