{
  "id": 2776098,
  "type": "Feature",
  "properties": {
    "tgn:hierarchy":[
        "tgn:2776098",
        "tgn:1000001",
        "tgn:7012149",
        "tgn:2002186",
        "tgn:7007919",
        "tgn:7029392"
    ],
    "tgn:id":2776098,
    "tgn:name":"Wilson Springs",
    "tgn:placetype":[
        "aat:300008347"
    ]
},
  "bbox": [],
  "geometry": {"coordinates":[-79.4333,37.9167],"type":"Point"}
}