<<<<<<< HEAD
{
  "id": 7174732,
  "type": "Feature",
  "properties": {
    "tgn:hierarchy":[
        "tgn:7174732",
        "tgn:1000003",
        "tgn:7003677",
        "tgn:7000084",
        "tgn:7029392"
    ],
    "tgn:id":7174732,
    "tgn:name":"Gro\u00df H\u00f6vel",
    "tgn:placetype":[
        "aat:300000206"
    ]
},
  "bbox": [],
  "geometry": {"coordinates":[6.183333,51.75],"type":"Point"}
}
=======
{"geometry":{"type":"Point","coordinates":[6.183333,51.750000]},"type":"Feature","properties":{"hierarchy":["tgn:7174732","tgn:1000003","tgn:7003677","tgn:7000084","tgn:7029392"],"placetype":["aat:300000206"],"id":7174732,"name:xx":"Gro\u00df H\u00f6vel"}}
>>>>>>> 03f74aca74312dbeaf24d7e61306dd6a786dc3d0
