{
  "id": 7174732,
  "type": "Feature",
  "properties": {
    "tgn:hierarchy":[
        "tgn:7174732",
        "tgn:1000003",
        "tgn:7003677",
        "tgn:7000084",
        "tgn:7029392"
    ],
    "tgn:id":7174732,
    "tgn:name":"Gro\u00df H\u00f6vel",
    "tgn:placetype":[
        "aat:300000206"
    ]
},
  "bbox": [],
  "geometry": {"coordinates":[6.183333,51.75],"type":"Point"}
}