{
  "id": 2060427,
  "type": "Feature",
  "properties": {
    "tgn:hierarchy":[
        "tgn:2060427",
        "tgn:1000001",
        "tgn:2001175",
        "tgn:7012149",
        "tgn:7007523",
        "tgn:7029392"
    ],
    "tgn:id":2060427,
    "tgn:name":"Saxton",
    "tgn:placetype":[
        "aat:300008347"
    ]
},
  "bbox": [],
  "geometry": {"coordinates":[-94.75,39.7167],"type":"Point"}
}