{
  "id": 2559970,
  "type": "Feature",
  "properties": {
    "tgn:hierarchy":[
        "tgn:2559970",
        "tgn:1000001",
        "tgn:2001779",
        "tgn:7012149",
        "tgn:7007713",
        "tgn:7029392"
    ],
    "tgn:id":2559970,
    "tgn:name":"Opossum Hollow",
    "tgn:placetype":[
        "aat:300008761"
    ]
},
  "bbox": [],
  "geometry": {"coordinates":[-103.8833,44.95],"type":"Point"}
}