{
  "id": 7441579,
  "type": "Feature",
  "properties": {
    "tgn:hierarchy":[
        "tgn:7441579",
        "tgn:7002445",
        "tgn:1000003",
        "tgn:7008165",
        "tgn:7008591",
        "tgn:7029392"
    ],
    "tgn:id":7441579,
    "tgn:name:en":"Tree o' the House",
    "tgn:placetype":[
        "aat:300008808"
    ]
},
  "bbox": [],
  "geometry": {"coordinates":[-1.716667,55.65],"type":"Point"}
}