{
  "id": 7489365,
  "type": "Feature",
  "properties": {
    "tgn:hierarchy":[
        "tgn:7489365",
        "tgn:1000004",
        "tgn:7471332",
        "tgn:1000141",
        "tgn:7029392"
    ],
    "tgn:id":7489365,
    "tgn:name":"Yitong Si",
    "tgn:placetype":[
        "aat:300007595"
    ]
},
  "bbox": [],
  "geometry": {"coordinates":[120.970278,24.782778],"type":"Point"}
}