{
  "id": 2504712,
  "type": "Feature",
  "properties": {
    "tgn:hierarchy":[
        "tgn:2504712",
        "tgn:1000001",
        "tgn:7012149",
        "tgn:7007157",
        "tgn:1003046",
        "tgn:7029392"
    ],
    "tgn:id":2504712,
    "tgn:name":"Medical Spring",
    "tgn:placetype":[
        "aat:300008697"
    ]
},
  "bbox": [],
  "geometry": {"coordinates":[-122.1167,38.65],"type":"Point"}
}