{
  "id": 7594207,
  "type": "Feature",
  "properties": {
    "tgn:hierarchy":[
        "tgn:7594207",
        "tgn:1000003",
        "tgn:7005729",
        "tgn:7029392"
    ],
    "tgn:id":7594207,
    "tgn:name":"Kirkop",
    "tgn:placetype":[
        "aat:300387064",
        "aat:300387205"
    ]
},
  "bbox": [],
  "geometry": {"coordinates":[14.484167,35.844167],"type":"Point"}
}