{
  "id": 7581098,
  "type": "Feature",
  "properties": {
    "tgn:hierarchy":[
        "tgn:7581098",
        "tgn:1000004",
        "tgn:1001871",
        "tgn:7000198",
        "tgn:7029392"
    ],
    "tgn:id":7581098,
    "tgn:name:en":"Surajpur",
    "tgn:placetype":[
        "aat:300008347"
    ]
},
  "bbox": [],
  "geometry": {"coordinates":[76.899019,30.787764],"type":"Point"}
}