{
  "id": 1135371,
  "type": "Feature",
  "properties": {
    "tgn:hierarchy":[
        "tgn:1135371",
        "tgn:7003025",
        "tgn:1000003",
        "tgn:1000062",
        "tgn:7029392"
    ],
    "tgn:id":1135371,
    "tgn:name":"Russbach",
    "tgn:placetype":[
        "aat:300008703"
    ]
},
  "bbox": [],
  "geometry": {"coordinates":[16.9667,48.1833],"type":"Point"}
}