{
  "id": 4001283,
  "type": "Feature",
  "properties": {
    "tgn:hierarchy":[
        "tgn:4001283",
        "tgn:7003669",
        "tgn:1000003",
        "tgn:7000084",
        "tgn:7029392"
    ],
    "tgn:id":4001283,
    "tgn:name:de":"Baumburg",
    "tgn:placetype":[
        "aat:300008347",
        "aat:300000641",
        "aat:300008375"
    ]
},
  "bbox": [],
  "geometry": {"coordinates":[-6.8833,51.1333],"type":"Point"}
}