{
  "id": 7254343,
  "type": "Feature",
  "properties": {
    "tgn:hierarchy":[
        "tgn:7254343",
        "tgn:7003456",
        "tgn:1000003",
        "tgn:1000063",
        "tgn:7018236",
        "tgn:7029392"
    ],
    "tgn:id":7254343,
    "tgn:name":"Venitiaanseheide",
    "tgn:placetype":[
        "aat:300008347"
    ]
},
  "bbox": [],
  "geometry": {"coordinates":[4.51331,51.441944],"type":"Point"}
}