{
  "id": 7274148,
  "type": "Feature",
  "properties": {
    "tgn:hierarchy":[
        "tgn:7274148",
        "tgn:7003616",
        "tgn:1000003",
        "tgn:7016845",
        "tgn:7029392"
    ],
    "tgn:id":7274148,
    "tgn:name:nl":"Zoolpolder",
    "tgn:placetype":[
        "aat:300006163"
    ]
},
  "bbox": [],
  "geometry": {"coordinates":[5.45,52.883333],"type":"Point"}
}