{
  "id": 2776842,
  "type": "Feature",
  "properties": {
    "tgn:hierarchy":[
        "tgn:2776842",
        "tgn:1000001",
        "tgn:7012149",
        "tgn:2000224",
        "tgn:7007158",
        "tgn:7029392"
    ],
    "tgn:id":2776842,
    "tgn:name":"Windsor Lake",
    "tgn:placetype":[
        "aat:300008680"
    ]
},
  "bbox": [],
  "geometry": {"coordinates":[-106.4833,39.2333],"type":"Point"}
}