{
  "id": 2685093,
  "type": "Feature",
  "properties": {
    "tgn:hierarchy":[
        "tgn:2685093",
        "tgn:1000001",
        "tgn:7012149",
        "tgn:2002353",
        "tgn:7007922",
        "tgn:7029392"
    ],
    "tgn:id":2685093,
    "tgn:name":"Spooky Bay Creek",
    "tgn:placetype":[
        "aat:300132316"
    ]
},
  "bbox": [],
  "geometry": {"coordinates":[-91.15,45.8833],"type":"Point"}
}