{
  "id": 2741739,
  "type": "Feature",
  "properties": {
    "tgn:hierarchy":[
        "tgn:2741739",
        "tgn:1000001",
        "tgn:7012149",
        "tgn:7007710",
        "tgn:7029392"
    ],
    "tgn:id":2741739,
    "tgn:name":"Utley Brook",
    "tgn:placetype":[
        "aat:300008699"
    ]
},
  "bbox": [],
  "geometry": {"coordinates":[-75.7333,41.6833],"type":"Point"}
}