{
  "id": 2702594,
  "type": "Feature",
  "properties": {
    "tgn:hierarchy":[
        "tgn:2702594",
        "tgn:1000001",
        "tgn:7012149",
        "tgn:7007708",
        "tgn:7029392"
    ],
    "tgn:id":2702594,
    "tgn:name":"Sulphur Creek",
    "tgn:placetype":[
        "aat:300008706"
    ]
},
  "bbox": [],
  "geometry": {"coordinates":[-123.8167,45.05],"type":"Point"}
}