{
  "id": 2751355,
  "type": "Feature",
  "properties": {
    "tgn:hierarchy":[
        "tgn:2751355",
        "tgn:1000001",
        "tgn:7012149",
        "tgn:2001706",
        "tgn:7007708",
        "tgn:7029392"
    ],
    "tgn:id":2751355,
    "tgn:name":"Warm Spring Creek",
    "tgn:placetype":[
        "aat:300008706"
    ]
},
  "bbox": [],
  "geometry": {"coordinates":[-122.1667,43.3667],"type":"Point"}
}