{
  "id": 7558068,
  "type": "Feature",
  "properties": {
    "tgn:hierarchy":[
        "tgn:7558068",
        "tgn:1000004",
        "tgn:7000198",
        "tgn:1001895",
        "tgn:7029392"
    ],
    "tgn:id":7558068,
    "tgn:name:en":"Prongs Reef",
    "tgn:placetype":[
        "aat:300008808"
    ]
},
  "bbox": [],
  "geometry": {"coordinates":[72.801944,18.886389],"type":"Point"}
}