{
  "id": 2625093,
  "type": "Feature",
  "properties": {
    "tgn:hierarchy":[
        "tgn:2625093",
        "tgn:1000001",
        "tgn:7012149",
        "tgn:1002350",
        "tgn:7007157",
        "tgn:7029392"
    ],
    "tgn:id":2625093,
    "tgn:name":"Rockbound Valley",
    "tgn:placetype":[
        "aat:300008761"
    ]
},
  "bbox": [],
  "geometry": {"coordinates":[-120.1667,38.8667],"type":"Point"}
}