{
  "id": 1089592,
  "type": "Feature",
  "properties": {
    "tgn:hierarchy":[
        "tgn:1089592",
        "tgn:7001242",
        "tgn:7016654",
        "tgn:1000159",
        "tgn:7029392"
    ],
    "tgn:id":1089592,
    "tgn:name":"Yokolo",
    "tgn:placetype":[
        "aat:300008347"
    ]
},
  "bbox": [],
  "geometry": {"coordinates":[23.0667,-0.6667],"type":"Point"}
}