{
  "id": 2533337,
  "type": "Feature",
  "properties": {
    "tgn:hierarchy":[
        "tgn:2533337",
        "tgn:1000001",
        "tgn:7012149",
        "tgn:2001979",
        "tgn:7007826",
        "tgn:7029392"
    ],
    "tgn:id":2533337,
    "tgn:name":"Muskingum Draw",
    "tgn:placetype":[
        "aat:300008761"
    ]
},
  "bbox": [],
  "geometry": {"coordinates":[-102.35,31.8333],"type":"Point"}
}