{
  "id": 7483113,
  "type": "Feature",
  "properties": {
    "tgn:hierarchy":[
        "tgn:7483113",
        "tgn:1000004",
        "tgn:7001014",
        "tgn:1000141",
        "tgn:7029392"
    ],
    "tgn:id":7483113,
    "tgn:name":"Haifeng Qiao",
    "tgn:placetype":[
        "aat:300007836"
    ]
},
  "bbox": [],
  "geometry": {"coordinates":[120.259181,23.687007],"type":"Point"}
}