<<<<<<< HEAD
{
  "id": 7483113,
  "type": "Feature",
  "properties": {
    "tgn:hierarchy":[
        "tgn:7483113",
        "tgn:1000004",
        "tgn:7001014",
        "tgn:1000141",
        "tgn:7029392"
    ],
    "tgn:id":7483113,
    "tgn:name":"Haifeng Qiao",
    "tgn:placetype":[
        "aat:300007836"
    ]
},
  "bbox": [],
  "geometry": {"coordinates":[120.259181,23.687007],"type":"Point"}
}
=======
{"geometry":{"type":"Point","coordinates":[120.259181,23.687007]},"type":"Feature","properties":{"hierarchy":["tgn:7483113","tgn:1000004","tgn:7001014","tgn:1000141","tgn:7029392"],"placetype":["aat:300007836"],"id":7483113,"name:xx":"Haifeng Qiao"}}
>>>>>>> 03f74aca74312dbeaf24d7e61306dd6a786dc3d0
