{
  "id": 2268357,
  "type": "Feature",
  "properties": {
    "tgn:hierarchy":[
        "tgn:2268357",
        "tgn:1000001",
        "tgn:7006451",
        "tgn:2000092",
        "tgn:7012149",
        "tgn:7029392"
    ],
    "tgn:id":2268357,
    "tgn:name":"Crooked Ridge",
    "tgn:placetype":[
        "aat:300266640"
    ]
},
  "bbox": [],
  "geometry": {"coordinates":[-111.35,36.3667],"type":"Point"}
}