{
  "id": 7146267,
  "type": "Feature",
  "properties": {
    "tgn:hierarchy":[
        "tgn:7146267",
        "tgn:1000003",
        "tgn:7003676",
        "tgn:7000084",
        "tgn:7029392"
    ],
    "tgn:id":7146267,
    "tgn:name":"Klunderburg",
    "tgn:placetype":[
        "aat:300000206"
    ]
},
  "bbox": [],
  "geometry": {"coordinates":[7.166667,53.366667],"type":"Point"}
}