{
  "id": 7585513,
  "type": "Feature",
  "properties": {
    "tgn:hierarchy":[
        "tgn:7585513",
        "tgn:1000004",
        "tgn:7000198",
        "tgn:7000799",
        "tgn:7029392"
    ],
    "tgn:id":7585513,
    "tgn:name:en":"Parokhin",
    "tgn:placetype":[
        "aat:300008347"
    ]
},
  "bbox": [],
  "geometry": {"coordinates":[74.058238,33.253889],"type":"Point"}
}