{
  "id": 7183673,
  "type": "Feature",
  "properties": {
    "tgn:hierarchy":[
        "tgn:7183673",
        "tgn:1000003",
        "tgn:7003677",
        "tgn:7000084",
        "tgn:7029392"
    ],
    "tgn:id":7183673,
    "tgn:name":"Gillenberg",
    "tgn:placetype":[
        "aat:300008347"
    ]
},
  "bbox": [],
  "geometry": {"coordinates":[6.55,50.483333],"type":"Point"}
}