<<<<<<< HEAD
{
  "id": 7361225,
  "type": "Feature",
  "properties": {
    "tgn:hierarchy":[
        "tgn:7361225",
        "tgn:7005583",
        "tgn:1000001",
        "tgn:7005560",
        "tgn:7029392"
    ],
    "tgn:id":7361225,
    "tgn:name":"El Conejo",
    "tgn:placetype":[
        "aat:300008347"
    ]
},
  "bbox": [],
  "geometry": {"coordinates":[-104.7,23.983333],"type":"Point"}
}
=======
{"geometry":{"type":"Point","coordinates":[-104.700000,23.983333]},"type":"Feature","properties":{"hierarchy":["tgn:7361225","tgn:7005583","tgn:1000001","tgn:7005560","tgn:7029392"],"placetype":["aat:300008347"],"id":7361225,"name:xx":"El Conejo"}}
>>>>>>> 03f74aca74312dbeaf24d7e61306dd6a786dc3d0
