{
  "id": 2067627,
  "type": "Feature",
  "properties": {
    "tgn:hierarchy":[
        "tgn:2067627",
        "tgn:1000001",
        "tgn:7012149",
        "tgn:2001457",
        "tgn:7007566",
        "tgn:7029392"
    ],
    "tgn:id":2067627,
    "tgn:name":"Trampas",
    "tgn:placetype":[
        "aat:300008347"
    ]
},
  "bbox": [],
  "geometry": {"coordinates":[-105.75,36.1167],"type":"Point"}
}