{
  "id": 7487443,
  "type": "Feature",
  "properties": {
    "tgn:hierarchy":[
        "tgn:7487443",
        "tgn:1000004",
        "tgn:7490934",
        "tgn:1000141",
        "tgn:7029392"
    ],
    "tgn:id":7487443,
    "tgn:name":"Linziding",
    "tgn:placetype":[
        "aat:300008347"
    ]
},
  "bbox": [],
  "geometry": {"coordinates":[120.268333,22.970278],"type":"Point"}
}