{
  "id": 7279702,
  "type": "Feature",
  "properties": {
    "tgn:hierarchy":[
        "tgn:7279702",
        "tgn:1001630",
        "tgn:1000049",
        "tgn:1000002",
        "tgn:7029392"
    ],
    "tgn:id":7279702,
    "tgn:name":"Ranchos de Don Goyo",
    "tgn:placetype":[
        "aat:300008347"
    ]
},
  "bbox": [],
  "geometry": {"coordinates":[-69.85,-28.35],"type":"Point"}
}