{
  "id": 2756514,
  "type": "Feature",
  "properties": {
    "tgn:hierarchy":[
        "tgn:2756514",
        "tgn:1000001",
        "tgn:1002461",
        "tgn:7012149",
        "tgn:7007159",
        "tgn:7029392"
    ],
    "tgn:id":2756514,
    "tgn:name":"Welles Pond",
    "tgn:placetype":[
        "aat:300008680"
    ]
},
  "bbox": [],
  "geometry": {"coordinates":[-72.7833,41.7833],"type":"Point"}
}