{
  "id": 7133861,
  "type": "Feature",
  "properties": {
    "tgn:hierarchy":[
        "tgn:7133861",
        "tgn:1000003",
        "tgn:7003685",
        "tgn:7000084",
        "tgn:7029392"
    ],
    "tgn:id":7133861,
    "tgn:name":"M\u00fchl-Berg",
    "tgn:placetype":[
        "aat:300008777"
    ]
},
  "bbox": [],
  "geometry": {"coordinates":[13.066667,51.116667],"type":"Point"}
}