{
  "id": 2560641,
  "type": "Feature",
  "properties": {
    "tgn:hierarchy":[
        "tgn:2560641",
        "tgn:1000001",
        "tgn:7012149",
        "tgn:2002379",
        "tgn:7007923",
        "tgn:7029392"
    ],
    "tgn:id":2560641,
    "tgn:name":"Oregon Mine",
    "tgn:placetype":[
        "aat:300000390"
    ]
},
  "bbox": [],
  "geometry": {"coordinates":[-109.2833,43.8833],"type":"Point"}
}