{
  "id": 7368888,
  "type": "Feature",
  "properties": {
    "tgn:hierarchy":[
        "tgn:7368888",
        "tgn:1000001",
        "tgn:7005591",
        "tgn:7005560",
        "tgn:7029392"
    ],
    "tgn:id":7368888,
    "tgn:name:es":"Ixcatepec",
    "tgn:placetype":[
        "aat:300008347"
    ]
},
  "bbox": [],
  "geometry": {"coordinates":[-95.908333,16.296667],"type":"Point"}
}