{
  "id": 7549236,
  "type": "Feature",
  "properties": {
    "tgn:hierarchy":[
        "tgn:7549236",
        "tgn:1000004",
        "tgn:7000198",
        "tgn:7000799",
        "tgn:7029392"
    ],
    "tgn:id":7549236,
    "tgn:name:en":"East Liddar River",
    "tgn:placetype":[
        "aat:300008699"
    ]
},
  "bbox": [],
  "geometry": {"coordinates":[75.315515,34.015485],"type":"Point"}
}