{
  "id": 7472769,
  "type": "Feature",
  "properties": {
    "tgn:hierarchy":[
        "tgn:7472769",
        "tgn:7001004",
        "tgn:1000004",
        "tgn:1000141",
        "tgn:7029392"
    ],
    "tgn:id":7472769,
    "tgn:name":"Niaosong Xiang",
    "tgn:placetype":[
        "aat:300387173"
    ]
},
  "bbox": [],
  "geometry": {"coordinates":[120.368,22.6567],"type":"Point"}
}