{
  "id": 1077937,
  "type": "Feature",
  "properties": {
    "tgn:hierarchy":[
        "tgn:1077937",
        "tgn:1001321",
        "tgn:1000004",
        "tgn:1000116",
        "tgn:7029392"
    ],
    "tgn:id":1077937,
    "tgn:name":"Labuhan",
    "tgn:placetype":[
        "aat:300008347"
    ]
},
  "bbox": [],
  "geometry": {"coordinates":[105.8167,-6.4167],"type":"Point"}
}