<<<<<<< HEAD
{
  "id": 2156956,
  "type": "Feature",
  "properties": {
    "tgn:hierarchy":[
        "tgn:2156956",
        "tgn:1000001",
        "tgn:7016172",
        "tgn:7012149",
        "tgn:2000155",
        "tgn:7029392"
    ],
    "tgn:id":2156956,
    "tgn:name":"Beauty Cave",
    "tgn:placetype":[
        "aat:300008746"
    ]
},
  "bbox": [],
  "geometry": {"coordinates":[-93.25,36.0833],"type":"Point"}
}
=======
{"geometry":{"type":"Point","coordinates":[-93.250000,36.083300]},"type":"Feature","properties":{"hierarchy":["tgn:2156956","tgn:1000001","tgn:7016172","tgn:7012149","tgn:2000155","tgn:7029392"],"placetype":["aat:300008746"],"id":2156956,"name:xx":"Beauty Cave"}}
>>>>>>> 03f74aca74312dbeaf24d7e61306dd6a786dc3d0
