{
  "id": 7414848,
  "type": "Feature",
  "properties": {
    "tgn:hierarchy":[
        "tgn:7414848",
        "tgn:1000001",
        "tgn:7005591",
        "tgn:7005560",
        "tgn:7029392"
    ],
    "tgn:id":7414848,
    "tgn:name:es":"Santo Domingo",
    "tgn:placetype":[
        "aat:300008347"
    ]
},
  "bbox": [],
  "geometry": {"coordinates":[-97.344167,17.531111],"type":"Point"}
}