{
  "id": 2611661,
  "type": "Feature",
  "properties": {
    "tgn:hierarchy":[
        "tgn:2611661",
        "tgn:1000001",
        "tgn:2001704",
        "tgn:7012149",
        "tgn:7007708",
        "tgn:7029392"
    ],
    "tgn:id":2611661,
    "tgn:name":"Red Mountain Creek",
    "tgn:placetype":[
        "aat:300008706"
    ]
},
  "bbox": [],
  "geometry": {"coordinates":[-123.9833,42.1833],"type":"Point"}
}