{
  "id": 7296259,
  "type": "Feature",
  "properties": {
    "tgn:hierarchy":[
        "tgn:7296259",
        "tgn:7002813",
        "tgn:7002758",
        "tgn:1000003",
        "tgn:1000095",
        "tgn:7029392"
    ],
    "tgn:id":7296259,
    "tgn:name":"La Esparraguera",
    "tgn:placetype":[
        "aat:300387200"
    ]
},
  "bbox": [],
  "geometry": {"coordinates":[-6.258056,36.885556],"type":"Point"}
}