{
  "id": 7449860,
  "type": "Feature",
  "properties": {
    "tgn:hierarchy":[
        "tgn:7449860",
        "tgn:7019094",
        "tgn:7002444",
        "tgn:1000003",
        "tgn:7008591",
        "tgn:7029392"
    ],
    "tgn:id":7449860,
    "tgn:name:en":"Glenacardoch Point",
    "tgn:placetype":[
        "aat:300386846"
    ]
},
  "bbox": [],
  "geometry": {"coordinates":[-5.716667,55.583333],"type":"Point"}
}