{
  "id": 2216670,
  "type": "Feature",
  "properties": {
    "tgn:hierarchy":[
        "tgn:2216670",
        "tgn:1000001",
        "tgn:7012149",
        "tgn:2001712",
        "tgn:7007708",
        "tgn:7029392"
    ],
    "tgn:id":2216670,
    "tgn:name":"Camp Creek Butte",
    "tgn:placetype":[
        "aat:300008798"
    ]
},
  "bbox": [],
  "geometry": {"coordinates":[-121.6667,44.6833],"type":"Point"}
}