{
  "id": 1120598,
  "type": "Feature",
  "properties": {
    "tgn:hierarchy":[
        "tgn:1120598",
        "tgn:7000490",
        "tgn:1000006",
        "tgn:7001828",
        "tgn:7029392"
    ],
    "tgn:id":1120598,
    "tgn:name":"Tumut Pond Reservoir",
    "tgn:placetype":[
        "aat:300006191"
    ]
},
  "bbox": [],
  "geometry": {"coordinates":[148.4167,-35.9833],"type":"Point"}
}