<<<<<<< HEAD
{
  "id": 2405884,
  "type": "Feature",
  "properties": {
    "tgn:hierarchy":[
        "tgn:2405884",
        "tgn:1000001",
        "tgn:7012149",
        "tgn:7007157",
        "tgn:2000185",
        "tgn:7029392"
    ],
    "tgn:id":2405884,
    "tgn:name":"Hulls Valley",
    "tgn:placetype":[
        "aat:300008761"
    ]
},
  "bbox": [],
  "geometry": {"coordinates":[-123.2667,39.8833],"type":"Point"}
}
=======
{"geometry":{"type":"Point","coordinates":[-123.266700,39.883300]},"type":"Feature","properties":{"hierarchy":["tgn:2405884","tgn:1000001","tgn:7012149","tgn:7007157","tgn:2000185","tgn:7029392"],"placetype":["aat:300008761"],"id":2405884,"name:xx":"Hulls Valley"}}
>>>>>>> 03f74aca74312dbeaf24d7e61306dd6a786dc3d0
