{
  "id": 7486442,
  "type": "Feature",
  "properties": {
    "tgn:hierarchy":[
        "tgn:7486442",
        "tgn:1000004",
        "tgn:1000454",
        "tgn:1000141",
        "tgn:7029392"
    ],
    "tgn:id":7486442,
    "tgn:name":"Mao'ao Wan",
    "tgn:placetype":[
        "aat:300132317"
    ]
},
  "bbox": [],
  "geometry": {"coordinates":[121.983333,25.016667],"type":"Point"}
}