{
  "id": 7506284,
  "type": "Feature",
  "properties": {
    "tgn:hierarchy":[
        "tgn:7506284",
        "tgn:1009227",
        "tgn:1000226",
        "tgn:7016822",
        "tgn:1000006",
        "tgn:7029392"
    ],
    "tgn:id":7506284,
    "tgn:name:en":"Rurikaka Creek",
    "tgn:placetype":[
        "aat:300008699"
    ]
},
  "bbox": [],
  "geometry": {"coordinates":[167.733333,-46.333333],"type":"Point"}
}