{
  "id": 7192730,
  "type": "Feature",
  "properties": {
    "tgn:hierarchy":[
        "tgn:7192730",
        "tgn:1000003",
        "tgn:7003689",
        "tgn:7000084",
        "tgn:7029392"
    ],
    "tgn:id":7192730,
    "tgn:name":"Ferne-Bach",
    "tgn:placetype":[
        "aat:300008699"
    ]
},
  "bbox": [],
  "geometry": {"coordinates":[10.783333,51.183333],"type":"Point"}
}