<<<<<<< HEAD
{
  "id": 7354311,
  "type": "Feature",
  "properties": {
    "tgn:hierarchy":[
        "tgn:7354311",
        "tgn:7005583",
        "tgn:1000001",
        "tgn:7005560",
        "tgn:7029392"
    ],
    "tgn:id":7354311,
    "tgn:name":"Rancho Ca\u00f1ada Verde",
    "tgn:placetype":[
        "aat:300000241"
    ]
},
  "bbox": [],
  "geometry": {"coordinates":[-106.283333,26.183333],"type":"Point"}
}
=======
{"geometry":{"type":"Point","coordinates":[-106.283333,26.183333]},"type":"Feature","properties":{"hierarchy":["tgn:7354311","tgn:7005583","tgn:1000001","tgn:7005560","tgn:7029392"],"placetype":["aat:300000241"],"id":7354311,"name:xx":"Rancho Ca\u00f1ada Verde"}}
>>>>>>> 03f74aca74312dbeaf24d7e61306dd6a786dc3d0
