{
  "id": 7343660,
  "type": "Feature",
  "properties": {
    "tgn:hierarchy":[
        "tgn:7343660",
        "tgn:7002805",
        "tgn:7002758",
        "tgn:1000003",
        "tgn:1000095",
        "tgn:7029392"
    ],
    "tgn:id":7343660,
    "tgn:name":"Cabriles",
    "tgn:placetype":[
        "aat:300008347"
    ]
},
  "bbox": [],
  "geometry": {"coordinates":[-2.833333,36.766667],"type":"Point"}
}