{
  "id": 2748361,
  "type": "Feature",
  "properties": {
    "tgn:hierarchy":[
        "tgn:2748361",
        "tgn:1000001",
        "tgn:7012149",
        "tgn:2002057",
        "tgn:7007826",
        "tgn:7029392"
    ],
    "tgn:id":2748361,
    "tgn:name":"Walker Creek",
    "tgn:placetype":[
        "aat:300008706"
    ]
},
  "bbox": [],
  "geometry": {"coordinates":[-104.65,30.4333],"type":"Point"}
}