{
  "id": 2276830,
  "type": "Feature",
  "properties": {
    "tgn:hierarchy":[
        "tgn:2276830",
        "tgn:7002659",
        "tgn:1000001",
        "tgn:7012149",
        "tgn:2000041",
        "tgn:7029392"
    ],
    "tgn:id":2276830,
    "tgn:name":"Davis Branch",
    "tgn:placetype":[
        "aat:300008699"
    ]
},
  "bbox": [],
  "geometry": {"coordinates":[-86.9833,34.9167],"type":"Point"}
}