{
  "id": 2044974,
  "type": "Feature",
  "properties": {
    "tgn:hierarchy":[
        "tgn:2044974",
        "tgn:1000001",
        "tgn:7012149",
        "tgn:2000926",
        "tgn:7007515",
        "tgn:7029392"
    ],
    "tgn:id":2044974,
    "tgn:name":"Houghton",
    "tgn:placetype":[
        "aat:300008347",
        "aat:300387210"
    ]
},
  "bbox": [],
  "geometry": {"coordinates":[-70.65,44.75],"type":"Point"}
}