{
  "id": 2352390,
  "type": "Feature",
  "properties": {
    "tgn:hierarchy":[
        "tgn:2352390",
        "tgn:1002146",
        "tgn:1000001",
        "tgn:7012149",
        "tgn:7007157",
        "tgn:7029392"
    ],
    "tgn:id":2352390,
    "tgn:name":"Goat Hill",
    "tgn:placetype":[
        "aat:300008798"
    ]
},
  "bbox": [],
  "geometry": {"coordinates":[-120.7667,38.2833],"type":"Point"}
}