<<<<<<< HEAD
{
  "id": 2766752,
  "type": "Feature",
  "properties": {
    "tgn:hierarchy":[
        "tgn:2766752",
        "tgn:1000001",
        "tgn:7012149",
        "tgn:7013961",
        "tgn:7029392"
    ],
    "tgn:id":2766752,
    "tgn:name":"White Oak Run",
    "tgn:placetype":[
        "aat:300008699"
    ]
},
  "bbox": [],
  "geometry": {"coordinates":[-81.5333,38.6333],"type":"Point"}
}
=======
{"geometry":{"type":"Point","coordinates":[-81.533300,38.633300]},"type":"Feature","properties":{"hierarchy":["tgn:2766752","tgn:1000001","tgn:7012149","tgn:7013961","tgn:7029392"],"placetype":["aat:300008699"],"id":2766752,"name:xx":"White Oak Run"}}
>>>>>>> 03f74aca74312dbeaf24d7e61306dd6a786dc3d0
