{
  "id": 1063347,
  "type": "Feature",
  "properties": {
    "tgn:hierarchy":[
        "tgn:1063347",
        "tgn:1000003",
        "tgn:7024620",
        "tgn:1000097",
        "tgn:7029392"
    ],
    "tgn:id":1063347,
    "tgn:name":"Lysekil",
    "tgn:placetype":[
        "aat:300008347"
    ]
},
  "bbox": [],
  "geometry": {"coordinates":[11.4333,58.2667],"type":"Point"}
}