<<<<<<< HEAD
{
  "id": 2335257,
  "type": "Feature",
  "properties": {
    "tgn:hierarchy":[
        "tgn:2335257",
        "tgn:1000001",
        "tgn:7012149",
        "tgn:2000526",
        "tgn:7007251",
        "tgn:7029392"
    ],
    "tgn:id":2335257,
    "tgn:name":"Fort Gage",
    "tgn:placetype":[
        "aat:300008347"
    ]
},
  "bbox": [],
  "geometry": {"coordinates":[-89.9,37.95],"type":"Point"}
}
=======
{"geometry":{"type":"Point","coordinates":[-89.900000,37.950000]},"type":"Feature","properties":{"hierarchy":["tgn:2335257","tgn:1000001","tgn:7012149","tgn:2000526","tgn:7007251","tgn:7029392"],"placetype":["aat:300008347"],"id":2335257,"name:xx":"Fort Gage"}}
>>>>>>> 03f74aca74312dbeaf24d7e61306dd6a786dc3d0
