{
  "id": 2215973,
  "type": "Feature",
  "properties": {
    "tgn:hierarchy":[
        "tgn:2215973",
        "tgn:1000001",
        "tgn:7012149",
        "tgn:2000964",
        "tgn:7007520",
        "tgn:7029392"
    ],
    "tgn:id":2215973,
    "tgn:name":"Cameron Drain",
    "tgn:placetype":[
        "aat:300006075"
    ]
},
  "bbox": [],
  "geometry": {"coordinates":[-83.0333,43.75],"type":"Point"}
}