{
  "id": 1099519,
  "type": "Feature",
  "properties": {
    "tgn:hierarchy":[
        "tgn:1099519",
        "tgn:7006160",
        "tgn:1000946",
        "tgn:1000006",
        "tgn:7029392"
    ],
    "tgn:id":1099519,
    "tgn:name":"Lamogai",
    "tgn:placetype":[
        "aat:300008347"
    ]
},
  "bbox": [],
  "geometry": {"coordinates":[149.3667,-5.85],"type":"Point"}
}