{
  "id": 7108610,
  "type": "Feature",
  "properties": {
    "tgn:hierarchy":[
        "tgn:7108610",
        "tgn:7003712",
        "tgn:7003670",
        "tgn:1000003",
        "tgn:7000084",
        "tgn:7029392"
    ],
    "tgn:id":7108610,
    "tgn:name":"Reiswerder",
    "tgn:placetype":[
        "aat:300008791"
    ]
},
  "bbox": [],
  "geometry": {"coordinates":[13.25,52.566667],"type":"Point"}
}