<<<<<<< HEAD
{
  "id": 2401403,
  "type": "Feature",
  "properties": {
    "tgn:hierarchy":[
        "tgn:2401403",
        "tgn:1000001",
        "tgn:2000301",
        "tgn:7012149",
        "tgn:7007248",
        "tgn:7029392"
    ],
    "tgn:id":2401403,
    "tgn:name":"Horseshoe 4",
    "tgn:placetype":[
        "aat:300008680"
    ]
},
  "bbox": [],
  "geometry": {"coordinates":[-83.35,31.3833],"type":"Point"}
}
=======
{"geometry":{"type":"Point","coordinates":[-83.350000,31.383300]},"type":"Feature","properties":{"hierarchy":["tgn:2401403","tgn:1000001","tgn:2000301","tgn:7012149","tgn:7007248","tgn:7029392"],"placetype":["aat:300008680"],"id":2401403,"name:xx":"Horseshoe 4"}}
>>>>>>> 03f74aca74312dbeaf24d7e61306dd6a786dc3d0
