{
  "id": 2401403,
  "type": "Feature",
  "properties": {
    "tgn:hierarchy":[
        "tgn:2401403",
        "tgn:1000001",
        "tgn:2000301",
        "tgn:7012149",
        "tgn:7007248",
        "tgn:7029392"
    ],
    "tgn:id":2401403,
    "tgn:name":"Horseshoe 4",
    "tgn:placetype":[
        "aat:300008680"
    ]
},
  "bbox": [],
  "geometry": {"coordinates":[-83.35,31.3833],"type":"Point"}
}