{
  "id": 7463831,
  "type": "Feature",
  "properties": {
    "tgn:hierarchy":[
        "tgn:7463831",
        "tgn:7002445",
        "tgn:1000003",
        "tgn:7008160",
        "tgn:7008591",
        "tgn:7029392"
    ],
    "tgn:id":7463831,
    "tgn:name:en":"Houghton",
    "tgn:placetype":[
        "aat:300008347"
    ]
},
  "bbox": [],
  "geometry": {"coordinates":[0.65,52.816667],"type":"Point"}
}