{
  "id": 2044144,
  "type": "Feature",
  "properties": {
    "tgn:hierarchy":[
        "tgn:2044144",
        "tgn:1000001",
        "tgn:7012149",
        "tgn:2000882",
        "tgn:7007256",
        "tgn:7029392"
    ],
    "tgn:id":2044144,
    "tgn:name":"Thibodaux",
    "tgn:placetype":[
        "aat:300008347"
    ]
},
  "bbox": [],
  "geometry": {"coordinates":[-90.8167,29.7833],"type":"Point"}
}