{
  "id": 2618448,
  "type": "Feature",
  "properties": {
    "tgn:hierarchy":[
        "tgn:2618448",
        "tgn:1000001",
        "tgn:2002256",
        "tgn:7012149",
        "tgn:7013961",
        "tgn:7029392"
    ],
    "tgn:id":2618448,
    "tgn:name":"Right Fork Cedar Creek",
    "tgn:placetype":[
        "aat:300008706"
    ]
},
  "bbox": [],
  "geometry": {"coordinates":[-80.75,38.7333],"type":"Point"}
}