<<<<<<< HEAD
{
  "id": 2406476,
  "type": "Feature",
  "properties": {
    "tgn:hierarchy":[
        "tgn:2406476",
        "tgn:1000001",
        "tgn:1002245",
        "tgn:7012149",
        "tgn:7007568",
        "tgn:7029392"
    ],
    "tgn:id":2406476,
    "tgn:name":"Hungry Hollow",
    "tgn:placetype":[
        "aat:300008761"
    ]
},
  "bbox": [],
  "geometry": {"coordinates":[-78.6833,42.2333],"type":"Point"}
}
=======
{"geometry":{"type":"Point","coordinates":[-78.683300,42.233300]},"type":"Feature","properties":{"hierarchy":["tgn:2406476","tgn:1000001","tgn:1002245","tgn:7012149","tgn:7007568","tgn:7029392"],"placetype":["aat:300008761"],"id":2406476,"name:xx":"Hungry Hollow"}}
>>>>>>> 03f74aca74312dbeaf24d7e61306dd6a786dc3d0
