{
  "id": 2285447,
  "type": "Feature",
  "properties": {
    "tgn:hierarchy":[
        "tgn:2285447",
        "tgn:1000001",
        "tgn:7006451",
        "tgn:2000092",
        "tgn:7012149",
        "tgn:7029392"
    ],
    "tgn:id":2285447,
    "tgn:name":"Devils Dining Room",
    "tgn:placetype":[
        "aat:300055621"
    ]
},
  "bbox": [],
  "geometry": {"coordinates":[-111.75,34.8333],"type":"Point"}
}