{
  "id": 2617695,
  "type": "Feature",
  "properties": {
    "tgn:hierarchy":[
        "tgn:2617695",
        "tgn:1000001",
        "tgn:7012149",
        "tgn:1002474",
        "tgn:7007709",
        "tgn:7029392"
    ],
    "tgn:id":2617695,
    "tgn:name":"Riddicks Landing",
    "tgn:placetype":[
        "aat:300008347"
    ]
},
  "bbox": [],
  "geometry": {"coordinates":[-76.9167,36.5167],"type":"Point"}
}