{
  "id": 7219693,
  "type": "Feature",
  "properties": {
    "tgn:hierarchy":[
        "tgn:7219693",
        "tgn:7011330",
        "tgn:7002674",
        "tgn:1000003",
        "tgn:1000074",
        "tgn:7029392"
    ],
    "tgn:id":7219693,
    "tgn:name":"Krev\u00e1ti, Vrachonis\u00edda",
    "tgn:placetype":[
        "aat:300008791"
    ]
},
  "bbox": [],
  "geometry": {"coordinates":[27.62,36.214444],"type":"Point"}
}