{
  "id": 7038080,
  "type": "Feature",
  "properties": {
    "tgn:hierarchy":[
        "tgn:7038080",
        "tgn:1000003",
        "tgn:7003151",
        "tgn:7003237",
        "tgn:1000080",
        "tgn:7029392"
    ],
    "tgn:id":7038080,
    "tgn:name":"Trebbiano Nizza",
    "tgn:placetype":[
        "aat:300008347"
    ]
},
  "bbox": [],
  "geometry": {"coordinates":[9.116667,44.883333],"type":"Point"}
}