{
  "id": 7385978,
  "type": "Feature",
  "properties": {
    "tgn:hierarchy":[
        "tgn:7385978",
        "tgn:1000001",
        "tgn:7005600",
        "tgn:7005560",
        "tgn:7029392"
    ],
    "tgn:id":7385978,
    "tgn:name":"Quintana Roo",
    "tgn:placetype":[
        "aat:300008347"
    ]
},
  "bbox": [],
  "geometry": {"coordinates":[-88.633333,20.866667],"type":"Point"}
}