{
  "id": 2703893,
  "type": "Feature",
  "properties": {
    "tgn:hierarchy":[
        "tgn:2703893",
        "tgn:1000001",
        "tgn:2000460",
        "tgn:7012149",
        "tgn:7007250",
        "tgn:7029392"
    ],
    "tgn:id":2703893,
    "tgn:name":"Sundance Mountain",
    "tgn:placetype":[
        "aat:300008798"
    ]
},
  "bbox": [],
  "geometry": {"coordinates":[-116.75,48.4833],"type":"Point"}
}