{
  "id": 2299883,
  "type": "Feature",
  "properties": {
    "tgn:hierarchy":[
        "tgn:2299883",
        "tgn:1000001",
        "tgn:7012149",
        "tgn:2002301",
        "tgn:7013961",
        "tgn:7029392"
    ],
    "tgn:id":2299883,
    "tgn:name":"Duerrs Run",
    "tgn:placetype":[
        "aat:300008699"
    ]
},
  "bbox": [],
  "geometry": {"coordinates":[-80.7667,39.6333],"type":"Point"}
}