{
  "id": 7126303,
  "type": "Feature",
  "properties": {
    "tgn:hierarchy":[
        "tgn:7126303",
        "tgn:7003669",
        "tgn:1000003",
        "tgn:7000084",
        "tgn:7029392"
    ],
    "tgn:id":7126303,
    "tgn:name":"Oberholz",
    "tgn:placetype":[
        "aat:300008863"
    ]
},
  "bbox": [],
  "geometry": {"coordinates":[10.183333,48.366667],"type":"Point"}
}