<<<<<<< HEAD
{
  "id": 7026884,
  "type": "Feature",
  "properties": {
    "tgn:hierarchy":[
        "tgn:7026884",
        "tgn:7002445",
        "tgn:1000003",
        "tgn:7008139",
        "tgn:7008591",
        "tgn:7029392"
    ],
    "tgn:id":7026884,
    "tgn:name":"Little Ann",
    "tgn:placetype":[
        "aat:300008347",
        "aat:300008372"
    ]
},
  "bbox": [],
  "geometry": {"coordinates":[-1.5167,51.1833],"type":"Point"}
}
=======
{"geometry":{"type":"Point","coordinates":[-1.516700,51.183300]},"type":"Feature","properties":{"hierarchy":["tgn:7026884","tgn:7002445","tgn:1000003","tgn:7008139","tgn:7008591","tgn:7029392"],"placetype":["aat:300008347","aat:300008372"],"id":7026884,"name:xx":"Little Ann"}}
>>>>>>> 03f74aca74312dbeaf24d7e61306dd6a786dc3d0
