{
  "id": 7086580,
  "type": "Feature",
  "properties": {
    "tgn:hierarchy":[
        "tgn:7086580",
        "tgn:7003669",
        "tgn:1000003",
        "tgn:7000084",
        "tgn:7029392"
    ],
    "tgn:id":7086580,
    "tgn:name":"Weingarten",
    "tgn:placetype":[
        "aat:300008347"
    ]
},
  "bbox": [],
  "geometry": {"coordinates":[11.05,49.95],"type":"Point"}
}