<<<<<<< HEAD
{
  "id": 7358961,
  "type": "Feature",
  "properties": {
    "tgn:hierarchy":[
        "tgn:7358961",
        "tgn:1000001",
        "tgn:1001893",
        "tgn:7005560",
        "tgn:7029392"
    ],
    "tgn:id":7358961,
    "tgn:name":"Dieta",
    "tgn:placetype":[
        "aat:300008347"
    ]
},
  "bbox": [],
  "geometry": {"coordinates":[-100.216667,19.45],"type":"Point"}
}
=======
{"geometry":{"type":"Point","coordinates":[-100.216667,19.450000]},"type":"Feature","properties":{"hierarchy":["tgn:7358961","tgn:1000001","tgn:1001893","tgn:7005560","tgn:7029392"],"placetype":["aat:300008347"],"id":7358961,"name:xx":"Dieta"}}
>>>>>>> 03f74aca74312dbeaf24d7e61306dd6a786dc3d0
