{
  "id": 2150645,
  "type": "Feature",
  "properties": {
    "tgn:hierarchy":[
        "tgn:2150645",
        "tgn:1000001",
        "tgn:7012149",
        "tgn:2002377",
        "tgn:7007923",
        "tgn:7029392"
    ],
    "tgn:id":2150645,
    "tgn:name":"Baskett Reservoir",
    "tgn:placetype":[
        "aat:300006191"
    ]
},
  "bbox": [],
  "geometry": {"coordinates":[-106.8167,43.2667],"type":"Point"}
}