{
  "id": 1035208,
  "type": "Feature",
  "properties": {
    "tgn:hierarchy":[
        "tgn:1035208",
        "tgn:1000003",
        "tgn:7002877",
        "tgn:1000070",
        "tgn:7029392"
    ],
    "tgn:id":1035208,
    "tgn:name":"Sach\u00e9",
    "tgn:placetype":[
        "aat:300008347"
    ]
},
  "bbox": [],
  "geometry": {"coordinates":[0.55,47.2333],"type":"Point"}
}