{
  "id": 7418340,
  "type": "Feature",
  "properties": {
    "tgn:hierarchy":[
        "tgn:7418340",
        "tgn:7005579",
        "tgn:1000001",
        "tgn:7005560",
        "tgn:7029392"
    ],
    "tgn:id":7418340,
    "tgn:name":"Juan El Grande, Cerro",
    "tgn:placetype":[
        "aat:300008795"
    ]
},
  "bbox": [],
  "geometry": {"coordinates":[-101.916667,21.941667],"type":"Point"}
}