{
  "id": 1052116,
  "type": "Feature",
  "properties": {
    "tgn:hierarchy":[
        "tgn:1052116",
        "tgn:7011438",
        "tgn:1000004",
        "tgn:7006646",
        "tgn:7029392"
    ],
    "tgn:id":1052116,
    "tgn:name":"Alibeyli",
    "tgn:placetype":[
        "aat:300008347"
    ]
},
  "bbox": [],
  "geometry": {"coordinates":[46.8167,41.3667],"type":"Point"}
}