{
  "id": 7551405,
  "type": "Feature",
  "properties": {
    "tgn:hierarchy":[
        "tgn:7551405",
        "tgn:1000004",
        "tgn:7000198",
        "tgn:1001894",
        "tgn:7029392"
    ],
    "tgn:id":7551405,
    "tgn:name:en":"Bolkheri",
    "tgn:placetype":[
        "aat:300008347"
    ]
},
  "bbox": [],
  "geometry": {"coordinates":[75.803364,23.67216],"type":"Point"}
}