{
  "id": 2270586,
  "type": "Feature",
  "properties": {
    "tgn:hierarchy":[
        "tgn:2270586",
        "tgn:1000001",
        "tgn:2002136",
        "tgn:7012149",
        "tgn:7007828",
        "tgn:7029392"
    ],
    "tgn:id":2270586,
    "tgn:name":"Crystal Pond",
    "tgn:placetype":[
        "aat:300008680"
    ]
},
  "bbox": [],
  "geometry": {"coordinates":[-72.4667,43.5833],"type":"Point"}
}