{
  "id": 7214689,
  "type": "Feature",
  "properties": {
    "tgn:hierarchy":[
        "tgn:7214689",
        "tgn:1000003",
        "tgn:7000094",
        "tgn:7000084",
        "tgn:7029392"
    ],
    "tgn:id":7214689,
    "tgn:name":"Waldw\u00e4rter Beughorst",
    "tgn:placetype":[
        "aat:300004792"
    ]
},
  "bbox": [],
  "geometry": {"coordinates":[12.616667,54.333333],"type":"Point"}
}