{
  "id": 2579579,
  "type": "Feature",
  "properties": {
    "tgn:hierarchy":[
        "tgn:2579579",
        "tgn:1000001",
        "tgn:7012149",
        "tgn:1002737",
        "tgn:7007520",
        "tgn:7029392"
    ],
    "tgn:id":2579579,
    "tgn:name":"Pickett Lake",
    "tgn:placetype":[
        "aat:300008680"
    ]
},
  "bbox": [],
  "geometry": {"coordinates":[-83.65,42.5667],"type":"Point"}
}