{
  "id": 2462360,
  "type": "Feature",
  "properties": {
    "tgn:hierarchy":[
        "tgn:2462360",
        "tgn:1000001",
        "tgn:2001009",
        "tgn:7012149",
        "tgn:7007521",
        "tgn:7029392"
    ],
    "tgn:id":2462360,
    "tgn:name":"Little Webb Lake",
    "tgn:placetype":[
        "aat:300008680"
    ]
},
  "bbox": [],
  "geometry": {"coordinates":[-94.4167,46.9667],"type":"Point"}
}