{
  "id": 2495345,
  "type": "Feature",
  "properties": {
    "tgn:hierarchy":[
        "tgn:2495345",
        "tgn:1000001",
        "tgn:7012149",
        "tgn:7007923",
        "tgn:7029392"
    ],
    "tgn:id":2495345,
    "tgn:name":"Mary Mountain",
    "tgn:placetype":[
        "aat:300008798"
    ]
},
  "bbox": [],
  "geometry": {"coordinates":[-110.6333,44.6167],"type":"Point"}
}