{
  "id": 7311036,
  "type": "Feature",
  "properties": {
    "tgn:hierarchy":[
        "tgn:7311036",
        "tgn:7002464",
        "tgn:1000049",
        "tgn:1000002",
        "tgn:7029392"
    ],
    "tgn:id":7311036,
    "tgn:name":"Oficina Progreso",
    "tgn:placetype":[
        "aat:300008057"
    ]
},
  "bbox": [],
  "geometry": {"coordinates":[-69.833333,-19.883333],"type":"Point"}
}