{
  "id": 7396253,
  "type": "Feature",
  "properties": {
    "tgn:hierarchy":[
        "tgn:7396253",
        "tgn:7005580",
        "tgn:1000001",
        "tgn:7005560",
        "tgn:7029392"
    ],
    "tgn:id":7396253,
    "tgn:name":"Santa Rita",
    "tgn:placetype":[
        "aat:300008347"
    ]
},
  "bbox": [],
  "geometry": {"coordinates":[-91.45,16.916667],"type":"Point"}
}