{
  "id": 2407665,
  "type": "Feature",
  "properties": {
    "tgn:hierarchy":[
        "tgn:2407665",
        "tgn:1000001",
        "tgn:7012149",
        "tgn:2002371",
        "tgn:7007923",
        "tgn:7029392"
    ],
    "tgn:id":2407665,
    "tgn:name":"Hurley Draw",
    "tgn:placetype":[
        "aat:300008761"
    ]
},
  "bbox": [],
  "geometry": {"coordinates":[-108.8833,43.4833],"type":"Point"}
}