<<<<<<< HEAD
{
  "id": 2407665,
  "type": "Feature",
  "properties": {
    "tgn:hierarchy":[
        "tgn:2407665",
        "tgn:1000001",
        "tgn:7012149",
        "tgn:2002371",
        "tgn:7007923",
        "tgn:7029392"
    ],
    "tgn:id":2407665,
    "tgn:name":"Hurley Draw",
    "tgn:placetype":[
        "aat:300008761"
    ]
},
  "bbox": [],
  "geometry": {"coordinates":[-108.8833,43.4833],"type":"Point"}
}
=======
{"geometry":{"type":"Point","coordinates":[-108.883300,43.483300]},"type":"Feature","properties":{"hierarchy":["tgn:2407665","tgn:1000001","tgn:7012149","tgn:2002371","tgn:7007923","tgn:7029392"],"placetype":["aat:300008761"],"id":2407665,"name:xx":"Hurley Draw"}}
>>>>>>> 03f74aca74312dbeaf24d7e61306dd6a786dc3d0
