{
  "id": 2113481,
  "type": "Feature",
  "properties": {
    "tgn:hierarchy":[
        "tgn:2113481",
        "tgn:2002141",
        "tgn:1000001",
        "tgn:7012149",
        "tgn:7007919",
        "tgn:7029392"
    ],
    "tgn:id":2113481,
    "tgn:name":"Oakville",
    "tgn:placetype":[
        "aat:300008347"
    ]
},
  "bbox": [],
  "geometry": {"coordinates":[-78.85,37.4167],"type":"Point"}
}