{
  "id": 7467665,
  "type": "Feature",
  "properties": {
    "tgn:hierarchy":[
        "tgn:7467665",
        "tgn:7488858",
        "tgn:1000004",
        "tgn:1000141",
        "tgn:7029392"
    ],
    "tgn:id":7467665,
    "tgn:name":"Guoxizi",
    "tgn:placetype":[
        "aat:300008347"
    ]
},
  "bbox": [],
  "geometry": {"coordinates":[120.702336,23.866803],"type":"Point"}
}