{
  "id": 1123652,
  "type": "Feature",
  "properties": {
    "tgn:hierarchy":[
        "tgn:1123652",
        "tgn:1000001",
        "tgn:7012149",
        "tgn:7007712",
        "tgn:7029392"
    ],
    "tgn:id":1123652,
    "tgn:name":"Edisto",
    "tgn:placetype":[
        "aat:300008707"
    ]
},
  "bbox": [],
  "geometry": {"coordinates":[-80.8833,33.25],"type":"Point"}
}