{
  "id": 2022552,
  "type": "Feature",
  "properties": {
    "tgn:hierarchy":[
        "tgn:2022552",
        "tgn:1000001",
        "tgn:7012149",
        "tgn:2000331",
        "tgn:7007248",
        "tgn:7029392"
    ],
    "tgn:id":2022552,
    "tgn:name":"Coney",
    "tgn:placetype":[
        "aat:300008347"
    ]
},
  "bbox": [],
  "geometry": {"coordinates":[-83.8833,31.95],"type":"Point"}
}