{
  "id": 7589745,
  "type": "Feature",
  "properties": {
    "tgn:hierarchy":[
        "tgn:7589745",
        "tgn:1000004",
        "tgn:7000198",
        "tgn:7000799",
        "tgn:7029392"
    ],
    "tgn:id":7589745,
    "tgn:name:en":"Bat\u0101lik",
    "tgn:placetype":[
        "aat:300008347"
    ]
},
  "bbox": [],
  "geometry": {"coordinates":[76.341667,34.656944],"type":"Point"}
}