{
  "id": 2701320,
  "type": "Feature",
  "properties": {
    "tgn:hierarchy":[
        "tgn:2701320",
        "tgn:1000001",
        "tgn:7012149",
        "tgn:2001823",
        "tgn:7007713",
        "tgn:7029392"
    ],
    "tgn:id":2701320,
    "tgn:name":"Sugar Loaf Rock",
    "tgn:placetype":[
        "aat:300008798"
    ]
},
  "bbox": [],
  "geometry": {"coordinates":[-100.3667,44.95],"type":"Point"}
}