{
  "id": 7507025,
  "type": "Feature",
  "properties": {
    "tgn:hierarchy":[
        "tgn:7507025",
        "tgn:7520092",
        "tgn:1008380",
        "tgn:1000226",
        "tgn:1000006",
        "tgn:7029392"
    ],
    "tgn:id":7507025,
    "tgn:name:en":"Rakautakihi",
    "tgn:placetype":[
        "aat:300008795"
    ]
},
  "bbox": [],
  "geometry": {"coordinates":[177.55,-37.916667],"type":"Point"}
}