{
  "id": 7091293,
  "type": "Feature",
  "properties": {
    "tgn:hierarchy":[
        "tgn:7091293",
        "tgn:7003692",
        "tgn:1000003",
        "tgn:7000084",
        "tgn:7029392"
    ],
    "tgn:id":7091293,
    "tgn:name":"Vormberg",
    "tgn:placetype":[
        "aat:300008347"
    ]
},
  "bbox": [],
  "geometry": {"coordinates":[8.183333,48.75],"type":"Point"}
}