{
  "id": 2477735,
  "type": "Feature",
  "properties": {
    "tgn:hierarchy":[
        "tgn:2477735",
        "tgn:1000001",
        "tgn:7012149",
        "tgn:2001297",
        "tgn:7007524",
        "tgn:7029392"
    ],
    "tgn:id":2477735,
    "tgn:name":"Mac Alister Draw",
    "tgn:placetype":[
        "aat:300008761"
    ]
},
  "bbox": [],
  "geometry": {"coordinates":[-106.2333,45.05],"type":"Point"}
}