<<<<<<< HEAD
{
  "id": 2335637,
  "type": "Feature",
  "properties": {
    "tgn:hierarchy":[
        "tgn:2335637",
        "tgn:1000001",
        "tgn:7012149",
        "tgn:2002119",
        "tgn:7007827",
        "tgn:7029392"
    ],
    "tgn:id":2335637,
    "tgn:name":"Fortress Canyon",
    "tgn:placetype":[
        "aat:300008761"
    ]
},
  "bbox": [],
  "geometry": {"coordinates":[-109.9333,37.5167],"type":"Point"}
}
=======
{"geometry":{"type":"Point","coordinates":[-109.933300,37.516700]},"type":"Feature","properties":{"hierarchy":["tgn:2335637","tgn:1000001","tgn:7012149","tgn:2002119","tgn:7007827","tgn:7029392"],"placetype":["aat:300008761"],"id":2335637,"name:xx":"Fortress Canyon"}}
>>>>>>> 03f74aca74312dbeaf24d7e61306dd6a786dc3d0
