{
  "id": 2642687,
  "type": "Feature",
  "properties": {
    "tgn:hierarchy":[
        "tgn:2642687",
        "tgn:7006450",
        "tgn:1000001",
        "tgn:7012149",
        "tgn:2000082",
        "tgn:7029392"
    ],
    "tgn:id":2642687,
    "tgn:name":"Sandfly Bay",
    "tgn:placetype":[
        "aat:300132316"
    ]
},
  "bbox": [],
  "geometry": {"coordinates":[-130.15,55.15],"type":"Point"}
}