{
  "id": 7226804,
  "type": "Feature",
  "properties": {
    "tgn:hierarchy":[
        "tgn:7226804",
        "tgn:7002728",
        "tgn:7002715",
        "tgn:1000003",
        "tgn:1000074",
        "tgn:7029392"
    ],
    "tgn:id":7226804,
    "tgn:name":"Pyrokorf\u00ed",
    "tgn:placetype":[
        "aat:300008798"
    ]
},
  "bbox": [],
  "geometry": {"coordinates":[22.256944,41.041944],"type":"Point"}
}