{
  "id": 7079890,
  "type": "Feature",
  "properties": {
    "tgn:hierarchy":[
        "tgn:7079890",
        "tgn:7003669",
        "tgn:1000003",
        "tgn:7000084",
        "tgn:7029392"
    ],
    "tgn:id":7079890,
    "tgn:name":"Wolfhof",
    "tgn:placetype":[
        "aat:300000206"
    ]
},
  "bbox": [],
  "geometry": {"coordinates":[11.033333,47.85],"type":"Point"}
}