{
  "id": 2543229,
  "type": "Feature",
  "properties": {
    "tgn:hierarchy":[
        "tgn:2543229",
        "tgn:1000001",
        "tgn:7012149",
        "tgn:1002978",
        "tgn:7007252",
        "tgn:7029392"
    ],
    "tgn:id":2543229,
    "tgn:name":"Nordman Ditch",
    "tgn:placetype":[
        "aat:300006075"
    ]
},
  "bbox": [],
  "geometry": {"coordinates":[-85.8667,40.9833],"type":"Point"}
}