{
  "id": 2626654,
  "type": "Feature",
  "properties": {
    "tgn:hierarchy":[
        "tgn:2626654",
        "tgn:1000001",
        "tgn:7012149",
        "tgn:7014097",
        "tgn:7007158",
        "tgn:7029392"
    ],
    "tgn:id":2626654,
    "tgn:name":"Rocky Mountain",
    "tgn:placetype":[
        "aat:300008798"
    ]
},
  "bbox": [],
  "geometry": {"coordinates":[-104.95,38.85],"type":"Point"}
}