{
  "id": 2353382,
  "type": "Feature",
  "properties": {
    "tgn:hierarchy":[
        "tgn:2353382",
        "tgn:1000001",
        "tgn:7012149",
        "tgn:2001300",
        "tgn:7007524",
        "tgn:7029392"
    ],
    "tgn:id":2353382,
    "tgn:name":"Gold Creek",
    "tgn:placetype":[
        "aat:300008706"
    ]
},
  "bbox": [],
  "geometry": {"coordinates":[-114.2167,46.1667],"type":"Point"}
}