{
  "id": 2212985,
  "type": "Feature",
  "properties": {
    "tgn:hierarchy":[
        "tgn:2212985",
        "tgn:1000001",
        "tgn:2000324",
        "tgn:7012149",
        "tgn:7007248",
        "tgn:7029392"
    ],
    "tgn:id":2212985,
    "tgn:name":"Ca Reca, Lake",
    "tgn:placetype":[
        "aat:300006191"
    ]
},
  "bbox": [],
  "geometry": {"coordinates":[-84.5667,33.7667],"type":"Point"}
}