{
  "id": 1015652,
  "type": "Feature",
  "properties": {
    "tgn:hierarchy":[
        "tgn:1015652",
        "tgn:7005685",
        "tgn:1000001",
        "tgn:7005804",
        "tgn:7029392"
    ],
    "tgn:id":1015652,
    "tgn:name":"Saint-Fran\u00e7ois-du-Lac",
    "tgn:placetype":[
        "aat:300008347"
    ]
},
  "bbox": [],
  "geometry": {"coordinates":[-72.8333,46.0667],"type":"Point"}
}