{
  "id": 2068529,
  "type": "Feature",
  "properties": {
    "tgn:hierarchy":[
        "tgn:2068529",
        "tgn:1002139",
        "tgn:1000001",
        "tgn:7012149",
        "tgn:7007568",
        "tgn:7029392"
    ],
    "tgn:id":2068529,
    "tgn:name":"Clarksville",
    "tgn:placetype":[
        "aat:300008347"
    ]
},
  "bbox": [],
  "geometry": {"coordinates":[-73.95,42.5667],"type":"Point"}
}