{
  "id": 7416190,
  "type": "Feature",
  "properties": {
    "tgn:hierarchy":[
        "tgn:7416190",
        "tgn:1000001",
        "tgn:7005591",
        "tgn:7005560",
        "tgn:7029392"
    ],
    "tgn:id":7416190,
    "tgn:name:es":"Bobo, R\u00edo",
    "tgn:placetype":[
        "aat:300008699"
    ]
},
  "bbox": [],
  "geometry": {"coordinates":[-95.593611,17.093611],"type":"Point"}
}