<<<<<<< HEAD
{
  "id": 2157422,
  "type": "Feature",
  "properties": {
    "tgn:hierarchy":[
        "tgn:2157422",
        "tgn:1000001",
        "tgn:7012149",
        "tgn:1002794",
        "tgn:7007708",
        "tgn:7029392"
    ],
    "tgn:id":2157422,
    "tgn:name":"Beaver Creek",
    "tgn:placetype":[
        "aat:300008706"
    ]
},
  "bbox": [],
  "geometry": {"coordinates":[-123.6,44.8],"type":"Point"}
}
=======
{"geometry":{"type":"Point","coordinates":[-123.600000,44.800000]},"type":"Feature","properties":{"hierarchy":["tgn:2157422","tgn:1000001","tgn:7012149","tgn:1002794","tgn:7007708","tgn:7029392"],"placetype":["aat:300008706"],"id":2157422,"name:xx":"Beaver Creek"}}
>>>>>>> 03f74aca74312dbeaf24d7e61306dd6a786dc3d0
