<<<<<<< HEAD
{
  "id": 7240963,
  "type": "Feature",
  "properties": {
    "tgn:hierarchy":[
        "tgn:7240963",
        "tgn:7018239",
        "tgn:1000003",
        "tgn:1000063",
        "tgn:7018236",
        "tgn:7029392"
    ],
    "tgn:id":7240963,
    "tgn:name":"Goetsenhoven",
    "tgn:placetype":[
        "aat:300008347"
    ]
},
  "bbox": [],
  "geometry": {"coordinates":[4.95,50.766667],"type":"Point"}
}
=======
{"geometry":{"type":"Point","coordinates":[4.950000,50.766667]},"type":"Feature","properties":{"hierarchy":["tgn:7240963","tgn:7018239","tgn:1000003","tgn:1000063","tgn:7018236","tgn:7029392"],"placetype":["aat:300008347"],"id":7240963,"name:xx":"Goetsenhoven"}}
>>>>>>> 03f74aca74312dbeaf24d7e61306dd6a786dc3d0
