{
  "id": 2608792,
  "type": "Feature",
  "properties": {
    "tgn:hierarchy":[
        "tgn:2608792",
        "tgn:1000001",
        "tgn:7012149",
        "tgn:7007157",
        "tgn:1002706",
        "tgn:7029392"
    ],
    "tgn:id":2608792,
    "tgn:name":"Rattlesnake Spring",
    "tgn:placetype":[
        "aat:300008697"
    ]
},
  "bbox": [],
  "geometry": {"coordinates":[-122.5833,38.6667],"type":"Point"}
}