{
  "id": 2317223,
  "type": "Feature",
  "properties": {
    "tgn:hierarchy":[
        "tgn:2317223",
        "tgn:1000001",
        "tgn:7006451",
        "tgn:7012149",
        "tgn:2000098",
        "tgn:7029392"
    ],
    "tgn:id":2317223,
    "tgn:name":"Emma, Mount",
    "tgn:placetype":[
        "aat:300008798"
    ]
},
  "bbox": [],
  "geometry": {"coordinates":[-113.1667,36.25],"type":"Point"}
}