{
  "id": 7350178,
  "type": "Feature",
  "properties": {
    "tgn:hierarchy":[
        "tgn:7350178",
        "tgn:7005585",
        "tgn:1000001",
        "tgn:7005560",
        "tgn:7029392"
    ],
    "tgn:id":7350178,
    "tgn:name":"Ahuehuepan",
    "tgn:placetype":[
        "aat:300008347"
    ]
},
  "bbox": [],
  "geometry": {"coordinates":[-99.483333,18.083333],"type":"Point"}
}