{
  "id": 7132964,
  "type": "Feature",
  "properties": {
    "tgn:hierarchy":[
        "tgn:7132964",
        "tgn:1000003",
        "tgn:7000094",
        "tgn:7000084",
        "tgn:7029392"
    ],
    "tgn:id":7132964,
    "tgn:name":"M\u00fchlenbeck",
    "tgn:placetype":[
        "aat:300008347"
    ]
},
  "bbox": [],
  "geometry": {"coordinates":[11.25,53.533333],"type":"Point"}
}