{
  "id": 7228455,
  "type": "Feature",
  "properties": {
    "tgn:hierarchy":[
        "tgn:7228455",
        "tgn:7002741",
        "tgn:7017076",
        "tgn:1000003",
        "tgn:1000074",
        "tgn:7029392"
    ],
    "tgn:id":7228455,
    "tgn:name":"Kas\u00eddhis, Nis\u00eds",
    "tgn:placetype":[
        "aat:300008791"
    ]
},
  "bbox": [],
  "geometry": {"coordinates":[22.683333,38.316667],"type":"Point"}
}