{
  "id": 7168528,
  "type": "Feature",
  "properties": {
    "tgn:hierarchy":[
        "tgn:7168528",
        "tgn:1000003",
        "tgn:7003688",
        "tgn:7000084",
        "tgn:7029392"
    ],
    "tgn:id":7168528,
    "tgn:name":"Hasseldieksdamm",
    "tgn:placetype":[
        "aat:300008347"
    ]
},
  "bbox": [],
  "geometry": {"coordinates":[10.083333,54.316667],"type":"Point"}
}