<<<<<<< HEAD
{
  "id": 7245955,
  "type": "Feature",
  "properties": {
    "tgn:hierarchy":[
        "tgn:7245955",
        "tgn:7003456",
        "tgn:1000003",
        "tgn:1000063",
        "tgn:7018236",
        "tgn:7029392"
    ],
    "tgn:id":7245955,
    "tgn:name":"Bonten Os",
    "tgn:placetype":[
        "aat:300008347"
    ]
},
  "bbox": [],
  "geometry": {"coordinates":[4.743115,51.018825],"type":"Point"}
}
=======
{"geometry":{"type":"Point","coordinates":[4.743115,51.018825]},"type":"Feature","properties":{"hierarchy":["tgn:7245955","tgn:7003456","tgn:1000003","tgn:1000063","tgn:7018236","tgn:7029392"],"placetype":["aat:300008347"],"id":7245955,"name:xx":"Bonten Os"}}
>>>>>>> 03f74aca74312dbeaf24d7e61306dd6a786dc3d0
