{
  "id": 7142606,
  "type": "Feature",
  "properties": {
    "tgn:hierarchy":[
        "tgn:7142606",
        "tgn:7003669",
        "tgn:1000003",
        "tgn:7000084",
        "tgn:7029392"
    ],
    "tgn:id":7142606,
    "tgn:name":"Lindenhof",
    "tgn:placetype":[
        "aat:300008347"
    ]
},
  "bbox": [],
  "geometry": {"coordinates":[9.65,47.566667],"type":"Point"}
}