{
  "id": 1075626,
  "type": "Feature",
  "properties": {
    "tgn:hierarchy":[
        "tgn:1075626",
        "tgn:1000004",
        "tgn:1001871",
        "tgn:7000198",
        "tgn:7029392"
    ],
    "tgn:id":1075626,
    "tgn:name:en":"Jhajjar",
    "tgn:placetype":[
        "aat:300008347"
    ]
},
  "bbox": [],
  "geometry": {"coordinates":[76.657296,28.607211],"type":"Point"}
}