{
  "id": 2526870,
  "type": "Feature",
  "properties": {
    "tgn:hierarchy":[
        "tgn:2526870",
        "tgn:1000001",
        "tgn:7012149",
        "tgn:7007826",
        "tgn:7029392"
    ],
    "tgn:id":2526870,
    "tgn:name":"Mound Creek",
    "tgn:placetype":[
        "aat:300008706"
    ]
},
  "bbox": [],
  "geometry": {"coordinates":[-95.7833,29.3667],"type":"Point"}
}