{
  "id": 7388691,
  "type": "Feature",
  "properties": {
    "tgn:hierarchy":[
        "tgn:7388691",
        "tgn:7005585",
        "tgn:1000001",
        "tgn:7005560",
        "tgn:7029392"
    ],
    "tgn:id":7388691,
    "tgn:name":"Piedras Negras",
    "tgn:placetype":[
        "aat:300008347"
    ]
},
  "bbox": [],
  "geometry": {"coordinates":[-99.583333,18.733333],"type":"Point"}
}