{
  "id": 7535318,
  "type": "Feature",
  "properties": {
    "tgn:hierarchy":[
        "tgn:7535318",
        "tgn:7001242",
        "tgn:7016833",
        "tgn:1001092",
        "tgn:7029392"
    ],
    "tgn:id":7535318,
    "tgn:name":"Kafr al 'Arab",
    "tgn:placetype":[
        "aat:300008347"
    ]
},
  "bbox": [],
  "geometry": {"coordinates":[31.226774,30.408624],"type":"Point"}
}