{
  "id": 2769584,
  "type": "Feature",
  "properties": {
    "tgn:hierarchy":[
        "tgn:2769584",
        "tgn:1000001",
        "tgn:7012149",
        "tgn:2002057",
        "tgn:7007826",
        "tgn:7029392"
    ],
    "tgn:id":2769584,
    "tgn:name":"Widow Spring",
    "tgn:placetype":[
        "aat:300008697"
    ]
},
  "bbox": [],
  "geometry": {"coordinates":[-104.75,30.35],"type":"Point"}
}