{
  "id": 2716018,
  "type": "Feature",
  "properties": {
    "tgn:hierarchy":[
        "tgn:2716018",
        "tgn:7002659",
        "tgn:1000001",
        "tgn:7012149",
        "tgn:2000038",
        "tgn:7029392"
    ],
    "tgn:id":2716018,
    "tgn:name":"Texas Ridge",
    "tgn:placetype":[
        "aat:300266640"
    ]
},
  "bbox": [],
  "geometry": {"coordinates":[-87.95,34.9167],"type":"Point"}
}