{
  "id": 2266716,
  "type": "Feature",
  "properties": {
    "tgn:hierarchy":[
        "tgn:2266716",
        "tgn:7006450",
        "tgn:1000001",
        "tgn:7019698",
        "tgn:7012149",
        "tgn:7029392"
    ],
    "tgn:id":2266716,
    "tgn:name":"Crescent Creek",
    "tgn:placetype":[
        "aat:300008706"
    ]
},
  "bbox": [],
  "geometry": {"coordinates":[-149.5667,60.4667],"type":"Point"}
}