{
  "id": 2693442,
  "type": "Feature",
  "properties": {
    "tgn:hierarchy":[
        "tgn:2693442",
        "tgn:7006450",
        "tgn:1000001",
        "tgn:7012149",
        "tgn:2000087",
        "tgn:7029392"
    ],
    "tgn:id":2693442,
    "tgn:name":"Stella Creek",
    "tgn:placetype":[
        "aat:300008706"
    ]
},
  "bbox": [],
  "geometry": {"coordinates":[-161.7833,61.8833],"type":"Point"}
}