<<<<<<< HEAD
{
  "id": 2151493,
  "type": "Feature",
  "properties": {
    "tgn:hierarchy":[
        "tgn:2151493",
        "tgn:1000001",
        "tgn:2000870",
        "tgn:7012149",
        "tgn:7007256",
        "tgn:7029392"
    ],
    "tgn:id":2151493,
    "tgn:name":"Baton Rouge Harbor",
    "tgn:placetype":[
        "aat:300008678"
    ]
},
  "bbox": [],
  "geometry": {"coordinates":[-91.2,30.5333],"type":"Point"}
}
=======
{"geometry":{"type":"Point","coordinates":[-91.200000,30.533300]},"type":"Feature","properties":{"hierarchy":["tgn:2151493","tgn:1000001","tgn:2000870","tgn:7012149","tgn:7007256","tgn:7029392"],"placetype":["aat:300008678"],"id":2151493,"name:xx":"Baton Rouge Harbor"}}
>>>>>>> 03f74aca74312dbeaf24d7e61306dd6a786dc3d0
