{
  "id": 2659325,
  "type": "Feature",
  "properties": {
    "tgn:hierarchy":[
        "tgn:2659325",
        "tgn:1000001",
        "tgn:7012149",
        "tgn:2001447",
        "tgn:7007566",
        "tgn:7029392"
    ],
    "tgn:id":2659325,
    "tgn:name":"Shiloh Draw",
    "tgn:placetype":[
        "aat:300008761"
    ]
},
  "bbox": [],
  "geometry": {"coordinates":[-105.8333,32.2333],"type":"Point"}
}