{
  "id": 2176236,
  "type": "Feature",
  "properties": {
    "tgn:hierarchy":[
        "tgn:2176236",
        "tgn:1000001",
        "tgn:2001945",
        "tgn:7012149",
        "tgn:7007826",
        "tgn:7029392"
    ],
    "tgn:id":2176236,
    "tgn:name":"Black Hills",
    "tgn:placetype":[
        "aat:300008798"
    ]
},
  "bbox": [],
  "geometry": {"coordinates":[-102.9833,29.8167],"type":"Point"}
}