{
  "id": 2601700,
  "type": "Feature",
  "properties": {
    "tgn:hierarchy":[
        "tgn:2601700",
        "tgn:7006450",
        "tgn:1000001",
        "tgn:7012149",
        "tgn:2000088",
        "tgn:7029392"
    ],
    "tgn:id":2601700,
    "tgn:name":"Putnam Peak",
    "tgn:placetype":[
        "aat:300008798"
    ]
},
  "bbox": [],
  "geometry": {"coordinates":[-133.1667,56.95],"type":"Point"}
}