{
  "id": 2169593,
  "type": "Feature",
  "properties": {
    "tgn:hierarchy":[
        "tgn:2169593",
        "tgn:1000001",
        "tgn:7012149",
        "tgn:1003018",
        "tgn:7007919",
        "tgn:7029392"
    ],
    "tgn:id":2169593,
    "tgn:name":"Big Meadow Run",
    "tgn:placetype":[
        "aat:300008699"
    ]
},
  "bbox": [],
  "geometry": {"coordinates":[-76.85,38.1333],"type":"Point"}
}