{
  "id": 2423280,
  "type": "Feature",
  "properties": {
    "tgn:hierarchy":[
        "tgn:2423280",
        "tgn:1000001",
        "tgn:7006451",
        "tgn:7012149",
        "tgn:2000103",
        "tgn:7029392"
    ],
    "tgn:id":2423280,
    "tgn:name":"Joes Tank",
    "tgn:placetype":[
        "aat:300006191"
    ]
},
  "bbox": [],
  "geometry": {"coordinates":[-112.2667,34.1167],"type":"Point"}
}