{
  "id": 7335383,
  "type": "Feature",
  "properties": {
    "tgn:hierarchy":[
        "tgn:7335383",
        "tgn:7002826",
        "tgn:7001158",
        "tgn:1000003",
        "tgn:1000095",
        "tgn:7029392"
    ],
    "tgn:id":7335383,
    "tgn:name":"Fresno del Camino",
    "tgn:placetype":[
        "aat:300008347"
    ]
},
  "bbox": [],
  "geometry": {"coordinates":[-5.65,42.566667],"type":"Point"}
}