{
  "id": 2593808,
  "type": "Feature",
  "properties": {
    "tgn:hierarchy":[
        "tgn:2593808",
        "tgn:1000001",
        "tgn:7012149",
        "tgn:2002350",
        "tgn:7007922",
        "tgn:7029392"
    ],
    "tgn:id":2593808,
    "tgn:name":"Port Arthur",
    "tgn:placetype":[
        "aat:300008347"
    ]
},
  "bbox": [],
  "geometry": {"coordinates":[-91.15,45.4167],"type":"Point"}
}