{
  "id": 2117265,
  "type": "Feature",
  "properties": {
    "tgn:hierarchy":[
        "tgn:2117265",
        "tgn:1000001",
        "tgn:7012149",
        "tgn:2002273",
        "tgn:7013961",
        "tgn:7029392"
    ],
    "tgn:id":2117265,
    "tgn:name":"Aracoma",
    "tgn:placetype":[
        "aat:300008347"
    ]
},
  "bbox": [],
  "geometry": {"coordinates":[-81.9833,37.85],"type":"Point"}
}