<<<<<<< HEAD
{
  "id": 2151944,
  "type": "Feature",
  "properties": {
    "tgn:hierarchy":[
        "tgn:2151944",
        "tgn:1000001",
        "tgn:7012149",
        "tgn:2001234",
        "tgn:7007523",
        "tgn:7029392"
    ],
    "tgn:id":2151944,
    "tgn:name":"Baugh Branch",
    "tgn:placetype":[
        "aat:300008699"
    ]
},
  "bbox": [],
  "geometry": {"coordinates":[-92.75,40.4333],"type":"Point"}
}
=======
{"geometry":{"type":"Point","coordinates":[-92.750000,40.433300]},"type":"Feature","properties":{"hierarchy":["tgn:2151944","tgn:1000001","tgn:7012149","tgn:2001234","tgn:7007523","tgn:7029392"],"placetype":["aat:300008699"],"id":2151944,"name:xx":"Baugh Branch"}}
>>>>>>> 03f74aca74312dbeaf24d7e61306dd6a786dc3d0
