{
  "id": 7551456,
  "type": "Feature",
  "properties": {
    "tgn:hierarchy":[
        "tgn:7551456",
        "tgn:1000004",
        "tgn:1001871",
        "tgn:7000198",
        "tgn:7029392"
    ],
    "tgn:id":7551456,
    "tgn:name:en":"Chh\u0101ra",
    "tgn:placetype":[
        "aat:300008347"
    ]
},
  "bbox": [],
  "geometry": {"coordinates":[76.717003,28.696226],"type":"Point"}
}