{
  "id": 7206250,
  "type": "Feature",
  "properties": {
    "tgn:hierarchy":[
        "tgn:7206250",
        "tgn:7000096",
        "tgn:1000003",
        "tgn:7000084",
        "tgn:7029392"
    ],
    "tgn:id":7206250,
    "tgn:name":"B\u00fccknitzer Heide",
    "tgn:placetype":[
        "aat:300008863"
    ]
},
  "bbox": [],
  "geometry": {"coordinates":[12.333333,52.283333],"type":"Point"}
}