{
  "id": 2668115,
  "type": "Feature",
  "properties": {
    "tgn:hierarchy":[
        "tgn:2668115",
        "tgn:1000001",
        "tgn:7012149",
        "tgn:2001711",
        "tgn:7007708",
        "tgn:7029392"
    ],
    "tgn:id":2668115,
    "tgn:name":"Skyline Mine",
    "tgn:placetype":[
        "aat:300000390"
    ]
},
  "bbox": [],
  "geometry": {"coordinates":[-122.7333,42.15],"type":"Point"}
}