{
  "id": 7468832,
  "type": "Feature",
  "properties": {
    "tgn:hierarchy":[
        "tgn:7468832",
        "tgn:1000004",
        "tgn:7001014",
        "tgn:1000141",
        "tgn:7029392"
    ],
    "tgn:id":7468832,
    "tgn:name":"Xialiao Cun",
    "tgn:placetype":[
        "aat:300387173"
    ]
},
  "bbox": [],
  "geometry": {"coordinates":[120.3257,23.6159],"type":"Point"}
}