{
  "id": 7400735,
  "type": "Feature",
  "properties": {
    "tgn:hierarchy":[
        "tgn:7400735",
        "tgn:1000001",
        "tgn:7005599",
        "tgn:7005560",
        "tgn:7029392"
    ],
    "tgn:id":7400735,
    "tgn:name":"Seis de Enero",
    "tgn:placetype":[
        "aat:300008347"
    ]
},
  "bbox": [],
  "geometry": {"coordinates":[-95.25,18.608333],"type":"Point"}
}