{
  "id": 7494557,
  "type": "Feature",
  "properties": {
    "tgn:hierarchy":[
        "tgn:7494557",
        "tgn:1000004",
        "tgn:7001014",
        "tgn:1000141",
        "tgn:7029392"
    ],
    "tgn:id":7494557,
    "tgn:name":"Pinghe Qiao",
    "tgn:placetype":[
        "aat:300007836"
    ]
},
  "bbox": [],
  "geometry": {"coordinates":[120.459045,23.700802],"type":"Point"}
}