<<<<<<< HEAD
{
  "id": 7360446,
  "type": "Feature",
  "properties": {
    "tgn:hierarchy":[
        "tgn:7360446",
        "tgn:1000001",
        "tgn:1001937",
        "tgn:7005560",
        "tgn:7029392"
    ],
    "tgn:id":7360446,
    "tgn:name":"Coch\u00e1n",
    "tgn:placetype":[
        "aat:300387007"
    ]
},
  "bbox": [],
  "geometry": {"coordinates":[-88.133333,19.366667],"type":"Point"}
}
=======
{"geometry":{"type":"Point","coordinates":[-88.133333,19.366667]},"type":"Feature","properties":{"hierarchy":["tgn:7360446","tgn:1000001","tgn:1001937","tgn:7005560","tgn:7029392"],"placetype":["aat:300387007"],"id":7360446,"name:xx":"Coch\u00e1n"}}
>>>>>>> 03f74aca74312dbeaf24d7e61306dd6a786dc3d0
