{
  "id": 7519510,
  "type": "Feature",
  "properties": {
    "tgn:hierarchy":[
        "tgn:7519510",
        "tgn:1009841",
        "tgn:1000226",
        "tgn:1000006",
        "tgn:7029392"
    ],
    "tgn:id":7519510,
    "tgn:name:en":"Bollons Island",
    "tgn:placetype":[
        "aat:300008791"
    ]
},
  "bbox": [],
  "geometry": {"coordinates":[178.819167,-49.645],"type":"Point"}
}