{
  "id": 2693790,
  "type": "Feature",
  "properties": {
    "tgn:hierarchy":[
        "tgn:2693790",
        "tgn:1000001",
        "tgn:7016172",
        "tgn:2000113",
        "tgn:7012149",
        "tgn:7029392"
    ],
    "tgn:id":2693790,
    "tgn:name":"Sterling",
    "tgn:placetype":[
        "aat:300008347"
    ]
},
  "bbox": [],
  "geometry": {"coordinates":[-91.1833,33.0167],"type":"Point"}
}