{
  "id": 2694257,
  "type": "Feature",
  "properties": {
    "tgn:hierarchy":[
        "tgn:2694257",
        "tgn:1000001",
        "tgn:7012149",
        "tgn:2000209",
        "tgn:7007158",
        "tgn:7029392"
    ],
    "tgn:id":2694257,
    "tgn:name":"Stevens Reservoir Number 2 and 3",
    "tgn:placetype":[
        "aat:300006191"
    ]
},
  "bbox": [],
  "geometry": {"coordinates":[-104.9667,39.35],"type":"Point"}
}