{
  "id": 5002103,
  "type": "Feature",
  "properties": {
    "tgn:hierarchy":[
        "tgn:5002103",
        "tgn:7009084",
        "tgn:7003001",
        "tgn:1000003",
        "tgn:1000080",
        "tgn:7029392"
    ],
    "tgn:id":5002103,
    "tgn:name":"Notaresco",
    "tgn:placetype":[
        "aat:300008347"
    ]
},
  "bbox": [],
  "geometry": {"coordinates":[13.883333,42.65],"type":"Point"}
}