{
  "id": 7555407,
  "type": "Feature",
  "properties": {
    "tgn:hierarchy":[
        "tgn:7555407",
        "tgn:1000004",
        "tgn:7000198",
        "tgn:7016788",
        "tgn:7029392"
    ],
    "tgn:id":7555407,
    "tgn:name:en":"Mogra Khurd",
    "tgn:placetype":[
        "aat:300008347"
    ]
},
  "bbox": [],
  "geometry": {"coordinates":[73.05879,26.126455],"type":"Point"}
}