{
  "id": 7364189,
  "type": "Feature",
  "properties": {
    "tgn:hierarchy":[
        "tgn:7364189",
        "tgn:1000001",
        "tgn:1001906",
        "tgn:7005560",
        "tgn:7029392"
    ],
    "tgn:id":7364189,
    "tgn:name":"El Ciruelo",
    "tgn:placetype":[
        "aat:300008699"
    ]
},
  "bbox": [],
  "geometry": {"coordinates":[-105.083333,21.666667],"type":"Point"}
}