{
  "id": 7208932,
  "type": "Feature",
  "properties": {
    "tgn:hierarchy":[
        "tgn:7208932",
        "tgn:1000003",
        "tgn:7003676",
        "tgn:7000084",
        "tgn:7029392"
    ],
    "tgn:id":7208932,
    "tgn:name":"Beckmannsfeld",
    "tgn:placetype":[
        "aat:300000206"
    ]
},
  "bbox": [],
  "geometry": {"coordinates":[8.316667,53.516667],"type":"Point"}
}