<<<<<<< HEAD
{
  "id": 2400786,
  "type": "Feature",
  "properties": {
    "tgn:hierarchy":[
        "tgn:2400786",
        "tgn:1000001",
        "tgn:1002738",
        "tgn:7012149",
        "tgn:7007565",
        "tgn:7029392"
    ],
    "tgn:id":2400786,
    "tgn:name":"Horse Point",
    "tgn:placetype":[
        "aat:300008850"
    ]
},
  "bbox": [],
  "geometry": {"coordinates":[-74.25,39.6167],"type":"Point"}
}
=======
{"geometry":{"type":"Point","coordinates":[-74.250000,39.616700]},"type":"Feature","properties":{"hierarchy":["tgn:2400786","tgn:1000001","tgn:1002738","tgn:7012149","tgn:7007565","tgn:7029392"],"placetype":["aat:300008850"],"id":2400786,"name:xx":"Horse Point"}}
>>>>>>> 03f74aca74312dbeaf24d7e61306dd6a786dc3d0
