{
  "id": 2726519,
  "type": "Feature",
  "properties": {
    "tgn:hierarchy":[
        "tgn:2726519",
        "tgn:1000001",
        "tgn:7012149",
        "tgn:2001155",
        "tgn:7007522",
        "tgn:7029392"
    ],
    "tgn:id":2726519,
    "tgn:name":"Town Creek",
    "tgn:placetype":[
        "aat:300008706"
    ]
},
  "bbox": [],
  "geometry": {"coordinates":[-88.9333,34.7333],"type":"Point"}
}