{
  "id": 7215997,
  "type": "Feature",
  "properties": {
    "tgn:hierarchy":[
        "tgn:7215997",
        "tgn:7003669",
        "tgn:1000003",
        "tgn:7000084",
        "tgn:7029392"
    ],
    "tgn:id":7215997,
    "tgn:name":"Altkaslehen",
    "tgn:placetype":[
        "aat:300000206"
    ]
},
  "bbox": [],
  "geometry": {"coordinates":[11.583333,48.533333],"type":"Point"}
}