{
  "id": 2476455,
  "type": "Feature",
  "properties": {
    "tgn:hierarchy":[
        "tgn:2476455",
        "tgn:1000001",
        "tgn:7012149",
        "tgn:7007157",
        "tgn:1002858",
        "tgn:7029392"
    ],
    "tgn:id":2476455,
    "tgn:name":"Lupe Spring",
    "tgn:placetype":[
        "aat:300008697"
    ]
},
  "bbox": [],
  "geometry": {"coordinates":[-116.7667,32.5833],"type":"Point"}
}