{
  "id": 2332178,
  "type": "Feature",
  "properties": {
    "tgn:hierarchy":[
        "tgn:2332178",
        "tgn:1000001",
        "tgn:7012149",
        "tgn:2002293",
        "tgn:7013961",
        "tgn:7029392"
    ],
    "tgn:id":2332178,
    "tgn:name":"Flint Town",
    "tgn:placetype":[
        "aat:300008347"
    ]
},
  "bbox": [],
  "geometry": {"coordinates":[-81.4833,38.7333],"type":"Point"}
}