{
  "id": 7577653,
  "type": "Feature",
  "properties": {
    "tgn:hierarchy":[
        "tgn:7577653",
        "tgn:1000004",
        "tgn:7000198",
        "tgn:1001886",
        "tgn:7029392"
    ],
    "tgn:id":7577653,
    "tgn:name:en":"Karuv\u0101rakundu",
    "tgn:placetype":[
        "aat:300008347"
    ]
},
  "bbox": [],
  "geometry": {"coordinates":[76.333333,11.133333],"type":"Point"}
}