<<<<<<< HEAD
{
  "id": 7020204,
  "type": "Feature",
  "properties": {
    "tgn:hierarchy":[
        "tgn:7020204",
        "tgn:1000001",
        "tgn:7012149",
        "tgn:1002354",
        "tgn:7007255",
        "tgn:7029392"
    ],
    "tgn:id":7020204,
    "tgn:name":"Green Branch",
    "tgn:placetype":[
        "aat:300008699"
    ]
},
  "bbox": [],
  "geometry": {"coordinates":[-83.0167,38.1],"type":"Point"}
}
=======
{"geometry":{"type":"Point","coordinates":[-83.016700,38.100000]},"type":"Feature","properties":{"hierarchy":["tgn:7020204","tgn:1000001","tgn:7012149","tgn:1002354","tgn:7007255","tgn:7029392"],"placetype":["aat:300008699"],"id":7020204,"name:xx":"Green Branch"}}
>>>>>>> 03f74aca74312dbeaf24d7e61306dd6a786dc3d0
