{
  "id": 2604646,
  "type": "Feature",
  "properties": {
    "tgn:hierarchy":[
        "tgn:2604646",
        "tgn:1000001",
        "tgn:7016172",
        "tgn:7012149",
        "tgn:2000160",
        "tgn:7029392"
    ],
    "tgn:id":2604646,
    "tgn:name":"Raccoon Bayou",
    "tgn:placetype":[
        "aat:300008699"
    ]
},
  "bbox": [],
  "geometry": {"coordinates":[-90.8167,35.6333],"type":"Point"}
}