{
  "id": 2190804,
  "type": "Feature",
  "properties": {
    "tgn:hierarchy":[
        "tgn:2190804",
        "tgn:7013349",
        "tgn:1000001",
        "tgn:7012149",
        "tgn:7007708",
        "tgn:7029392"
    ],
    "tgn:id":2190804,
    "tgn:name":"Boyce spring",
    "tgn:placetype":[
        "aat:300008697"
    ]
},
  "bbox": [],
  "geometry": {"coordinates":[-117.3333,44.7667],"type":"Point"}
}