{
  "id": 7320606,
  "type": "Feature",
  "properties": {
    "tgn:hierarchy":[
        "tgn:7320606",
        "tgn:7002464",
        "tgn:1000049",
        "tgn:1000002",
        "tgn:7029392"
    ],
    "tgn:id":7320606,
    "tgn:name":"Blanco, R\u00edo",
    "tgn:placetype":[
        "aat:300266554",
        "aat:300008699"
    ]
},
  "bbox": [],
  "geometry": {"coordinates":[-69.283333,-18.933333],"type":"Point"}
}