{
  "id": 2657948,
  "type": "Feature",
  "properties": {
    "tgn:hierarchy":[
        "tgn:2657948",
        "tgn:1000001",
        "tgn:7012149",
        "tgn:2001723",
        "tgn:7007708",
        "tgn:7029392"
    ],
    "tgn:id":2657948,
    "tgn:name":"Shell Rock Mountain",
    "tgn:placetype":[
        "aat:300266640"
    ]
},
  "bbox": [],
  "geometry": {"coordinates":[-120.0167,44.75],"type":"Point"}
}