{
  "id": 7191027,
  "type": "Feature",
  "properties": {
    "tgn:hierarchy":[
        "tgn:7191027",
        "tgn:7003692",
        "tgn:1000003",
        "tgn:7000084",
        "tgn:7029392"
    ],
    "tgn:id":7191027,
    "tgn:name":"Freudenweiler",
    "tgn:placetype":[
        "aat:300008347"
    ]
},
  "bbox": [],
  "geometry": {"coordinates":[9.116667,48.233333],"type":"Point"}
}