{
  "id": 7101555,
  "type": "Feature",
  "properties": {
    "tgn:hierarchy":[
        "tgn:7101555",
        "tgn:1000003",
        "tgn:7003682",
        "tgn:7000084",
        "tgn:7029392"
    ],
    "tgn:id":7101555,
    "tgn:name":"Rotherhof",
    "tgn:placetype":[
        "aat:300000206"
    ]
},
  "bbox": [],
  "geometry": {"coordinates":[7.75,49.816667],"type":"Point"}
}