{
  "id": 2512661,
  "type": "Feature",
  "properties": {
    "tgn:hierarchy":[
        "tgn:2512661",
        "tgn:1000001",
        "tgn:7012149",
        "tgn:2000917",
        "tgn:7007256",
        "tgn:7029392"
    ],
    "tgn:id":2512661,
    "tgn:name":"Mill Creek",
    "tgn:placetype":[
        "aat:300008706"
    ]
},
  "bbox": [],
  "geometry": {"coordinates":[-92.8167,31.95],"type":"Point"}
}