{
  "id": 2295740,
  "type": "Feature",
  "properties": {
    "tgn:hierarchy":[
        "tgn:2295740",
        "tgn:1000001",
        "tgn:7012149",
        "tgn:2000358",
        "tgn:7007248",
        "tgn:7029392"
    ],
    "tgn:id":2295740,
    "tgn:name":"Drowning Creek",
    "tgn:placetype":[
        "aat:300008706"
    ]
},
  "bbox": [],
  "geometry": {"coordinates":[-83.8833,33.9667],"type":"Point"}
}