{
  "id": 7113526,
  "type": "Feature",
  "properties": {
    "tgn:hierarchy":[
        "tgn:7113526",
        "tgn:1000003",
        "tgn:7000094",
        "tgn:7000084",
        "tgn:7029392"
    ],
    "tgn:id":7113526,
    "tgn:name":"Retz-See",
    "tgn:placetype":[
        "aat:300008680"
    ]
},
  "bbox": [],
  "geometry": {"coordinates":[12.783333,53.333333],"type":"Point"}
}