<<<<<<< HEAD
{
  "id": 2259001,
  "type": "Feature",
  "properties": {
    "tgn:hierarchy":[
        "tgn:2259001",
        "tgn:1000001",
        "tgn:7012149",
        "tgn:7021746",
        "tgn:7007826",
        "tgn:7029392"
    ],
    "tgn:id":2259001,
    "tgn:name":"Cottonwood Creek",
    "tgn:placetype":[
        "aat:300008706"
    ]
},
  "bbox": [],
  "geometry": {"coordinates":[-97.4667,29.0333],"type":"Point"}
}
=======
{"geometry":{"type":"Point","coordinates":[-97.466700,29.033300]},"type":"Feature","properties":{"hierarchy":["tgn:2259001","tgn:1000001","tgn:7012149","tgn:7021746","tgn:7007826","tgn:7029392"],"placetype":["aat:300008706"],"id":2259001,"name:xx":"Cottonwood Creek"}}
>>>>>>> 03f74aca74312dbeaf24d7e61306dd6a786dc3d0
