<<<<<<< HEAD
{
  "id": 2406210,
  "type": "Feature",
  "properties": {
    "tgn:hierarchy":[
        "tgn:2406210",
        "tgn:1000001",
        "tgn:2001331",
        "tgn:7012149",
        "tgn:7007525",
        "tgn:7029392"
    ],
    "tgn:id":2406210,
    "tgn:name":"Humpert Lake",
    "tgn:placetype":[
        "aat:300008680"
    ]
},
  "bbox": [],
  "geometry": {"coordinates":[-100.9667,42.3],"type":"Point"}
}
=======
{"geometry":{"type":"Point","coordinates":[-100.966700,42.300000]},"type":"Feature","properties":{"hierarchy":["tgn:2406210","tgn:1000001","tgn:2001331","tgn:7012149","tgn:7007525","tgn:7029392"],"placetype":["aat:300008680"],"id":2406210,"name:xx":"Humpert Lake"}}
>>>>>>> 03f74aca74312dbeaf24d7e61306dd6a786dc3d0
