{
  "id": 1059889,
  "type": "Feature",
  "properties": {
    "tgn:hierarchy":[
        "tgn:1059889",
        "tgn:1000004",
        "tgn:1003418",
        "tgn:7018214",
        "tgn:7002435",
        "tgn:7029392"
    ],
    "tgn:id":1059889,
    "tgn:name":"Suchodolskiy",
    "tgn:placetype":[
        "aat:300008347"
    ]
},
  "bbox": [],
  "geometry": {"coordinates":[38.2667,53.7167],"type":"Point"}
}