{
  "id": 7316144,
  "type": "Feature",
  "properties": {
    "tgn:hierarchy":[
        "tgn:7316144",
        "tgn:1001657",
        "tgn:1000049",
        "tgn:1000002",
        "tgn:7029392"
    ],
    "tgn:id":7316144,
    "tgn:name":"Car\u00e9n, R\u00edo",
    "tgn:placetype":[
        "aat:300008699"
    ]
},
  "bbox": [],
  "geometry": {"coordinates":[-70.85,-31.55],"type":"Point"}
}