{
  "id": 7283811,
  "type": "Feature",
  "properties": {
    "tgn:hierarchy":[
        "tgn:7283811",
        "tgn:1001637",
        "tgn:1000049",
        "tgn:1000002",
        "tgn:7029392"
    ],
    "tgn:id":7283811,
    "tgn:name":"Panguilemo",
    "tgn:placetype":[
        "aat:300000206"
    ]
},
  "bbox": [],
  "geometry": {"coordinates":[-73.566667,-37.666667],"type":"Point"}
}