{
  "id": 7565217,
  "type": "Feature",
  "properties": {
    "tgn:hierarchy":[
        "tgn:7565217",
        "tgn:1000004",
        "tgn:7000198",
        "tgn:7016722",
        "tgn:7029392"
    ],
    "tgn:id":7565217,
    "tgn:name:en":"Garhiya Bakhs\u012br\u0101m",
    "tgn:placetype":[
        "aat:300008347"
    ]
},
  "bbox": [],
  "geometry": {"coordinates":[79.475861,26.497122],"type":"Point"}
}