{
  "id": 2559262,
  "type": "Feature",
  "properties": {
    "tgn:hierarchy":[
        "tgn:2559262",
        "tgn:1000001",
        "tgn:7012149",
        "tgn:7007923",
        "tgn:7029392"
    ],
    "tgn:id":2559262,
    "tgn:name":"Onemile Creek",
    "tgn:placetype":[
        "aat:300008706"
    ]
},
  "bbox": [],
  "geometry": {"coordinates":[-106.0833,41.4333],"type":"Point"}
}