{
  "id": 7103933,
  "type": "Feature",
  "properties": {
    "tgn:hierarchy":[
        "tgn:7103933",
        "tgn:1000003",
        "tgn:7003678",
        "tgn:7000084",
        "tgn:7029392"
    ],
    "tgn:id":7103933,
    "tgn:name":"Scheichenhof",
    "tgn:placetype":[
        "aat:300000206"
    ]
},
  "bbox": [],
  "geometry": {"coordinates":[9.45,50.483333],"type":"Point"}
}