<<<<<<< HEAD
{
  "id": 7478436,
  "type": "Feature",
  "properties": {
    "tgn:hierarchy":[
        "tgn:7478436",
        "tgn:7487020",
        "tgn:1000004",
        "tgn:1000141",
        "tgn:7029392"
    ],
    "tgn:id":7478436,
    "tgn:name":"Kanglangbu",
    "tgn:placetype":[
        "aat:300008777"
    ]
},
  "bbox": [],
  "geometry": {"coordinates":[120.759956,24.537226],"type":"Point"}
}
=======
{"geometry":{"type":"Point","coordinates":[120.759956,24.537226]},"type":"Feature","properties":{"hierarchy":["tgn:7478436","tgn:7487020","tgn:1000004","tgn:1000141","tgn:7029392"],"placetype":["aat:300008777"],"id":7478436,"name:xx":"Kanglangbu"}}
>>>>>>> 03f74aca74312dbeaf24d7e61306dd6a786dc3d0
