{
  "id": 2650265,
  "type": "Feature",
  "properties": {
    "tgn:hierarchy":[
        "tgn:2650265",
        "tgn:1000001",
        "tgn:7012149",
        "tgn:2000416",
        "tgn:7007248",
        "tgn:7029392"
    ],
    "tgn:id":2650265,
    "tgn:name":"Sealeys Island",
    "tgn:placetype":[
        "aat:300008791"
    ]
},
  "bbox": [],
  "geometry": {"coordinates":[-84.8333,30.7833],"type":"Point"}
}