{
  "id": 7223897,
  "type": "Feature",
  "properties": {
    "tgn:hierarchy":[
        "tgn:7223897",
        "tgn:7002715",
        "tgn:7002731",
        "tgn:1000003",
        "tgn:1000074",
        "tgn:7029392"
    ],
    "tgn:id":7223897,
    "tgn:name":"Thessalon\u00edkis, \u00d3rmos",
    "tgn:placetype":[
        "aat:300132316"
    ]
},
  "bbox": [],
  "geometry": {"coordinates":[22.906254,40.604193],"type":"Point"}
}