{
  "id": 7418341,
  "type": "Feature",
  "properties": {
    "tgn:hierarchy":[
        "tgn:7418341",
        "tgn:7005579",
        "tgn:1000001",
        "tgn:7005560",
        "tgn:7029392"
    ],
    "tgn:id":7418341,
    "tgn:name":"El Llavero, Cerro",
    "tgn:placetype":[
        "aat:300008795"
    ]
},
  "bbox": [],
  "geometry": {"coordinates":[-102.0875,22.066667],"type":"Point"}
}