{
  "id": 2352423,
  "type": "Feature",
  "properties": {
    "tgn:hierarchy":[
        "tgn:2352423",
        "tgn:1000001",
        "tgn:7016172",
        "tgn:2000116",
        "tgn:7012149",
        "tgn:7029392"
    ],
    "tgn:id":2352423,
    "tgn:name":"Goat Island",
    "tgn:placetype":[
        "aat:300008791"
    ]
},
  "bbox": [],
  "geometry": {"coordinates":[-92.0833,35.5167],"type":"Point"}
}