<<<<<<< HEAD
{
  "id": 2403241,
  "type": "Feature",
  "properties": {
    "tgn:hierarchy":[
        "tgn:2403241",
        "tgn:1000001",
        "tgn:7006451",
        "tgn:2000092",
        "tgn:7012149",
        "tgn:7029392"
    ],
    "tgn:id":2403241,
    "tgn:name":"House Rock Canyon",
    "tgn:placetype":[
        "aat:300008761"
    ]
},
  "bbox": [],
  "geometry": {"coordinates":[-112.1,36.7167],"type":"Point"}
}
=======
{"geometry":{"type":"Point","coordinates":[-112.100000,36.716700]},"type":"Feature","properties":{"hierarchy":["tgn:2403241","tgn:1000001","tgn:7006451","tgn:2000092","tgn:7012149","tgn:7029392"],"placetype":["aat:300008761"],"id":2403241,"name:xx":"House Rock Canyon"}}
>>>>>>> 03f74aca74312dbeaf24d7e61306dd6a786dc3d0
