{
  "id": 7085753,
  "type": "Feature",
  "properties": {
    "tgn:hierarchy":[
        "tgn:7085753",
        "tgn:1000003",
        "tgn:7003685",
        "tgn:7000084",
        "tgn:7029392"
    ],
    "tgn:id":7085753,
    "tgn:name":"Wassergrund",
    "tgn:placetype":[
        "aat:300008347"
    ]
},
  "bbox": [],
  "geometry": {"coordinates":[14.483333,51.066667],"type":"Point"}
}