{
  "id": 2359784,
  "type": "Feature",
  "properties": {
    "tgn:hierarchy":[
        "tgn:2359784",
        "tgn:1000001",
        "tgn:7012149",
        "tgn:2002264",
        "tgn:7013961",
        "tgn:7029392"
    ],
    "tgn:id":2359784,
    "tgn:name":"Grapevine Cave",
    "tgn:placetype":[
        "aat:300008746"
    ]
},
  "bbox": [],
  "geometry": {"coordinates":[-80.45,37.8167],"type":"Point"}
}