{
  "id": 2442030,
  "type": "Feature",
  "properties": {
    "tgn:hierarchy":[
        "tgn:2442030",
        "tgn:1000001",
        "tgn:2001701",
        "tgn:7012149",
        "tgn:7007708",
        "tgn:7029392"
    ],
    "tgn:id":2442030,
    "tgn:name":"Kopplein",
    "tgn:placetype":[
        "aat:300008347"
    ]
},
  "bbox": [],
  "geometry": {"coordinates":[-123.4833,44.7167],"type":"Point"}
}