{
  "id": 2447276,
  "type": "Feature",
  "properties": {
    "tgn:hierarchy":[
        "tgn:2447276",
        "tgn:1000001",
        "tgn:7012149",
        "tgn:1002290",
        "tgn:7007826",
        "tgn:7029392"
    ],
    "tgn:id":2447276,
    "tgn:name":"Lick Branch",
    "tgn:placetype":[
        "aat:300008699"
    ]
},
  "bbox": [],
  "geometry": {"coordinates":[-96.4333,33.2833],"type":"Point"}
}