{
  "id": 2759783,
  "type": "Feature",
  "properties": {
    "tgn:hierarchy":[
        "tgn:2759783",
        "tgn:1000001",
        "tgn:7012149",
        "tgn:7029392"
    ],
    "tgn:id":2759783,
    "tgn:name":"West Fork Keeler Creek",
    "tgn:placetype":[
        "aat:300008706"
    ]
},
  "bbox": [],
  "geometry": {"coordinates":[-116.0667,48.3333],"type":"Point"}
}