{
  "id": 2729804,
  "type": "Feature",
  "properties": {
    "tgn:hierarchy":[
        "tgn:2729804",
        "tgn:1000001",
        "tgn:7012149",
        "tgn:2000354",
        "tgn:7007248",
        "tgn:7029392"
    ],
    "tgn:id":2729804,
    "tgn:name":"Troup Creek",
    "tgn:placetype":[
        "aat:300008706"
    ]
},
  "bbox": [],
  "geometry": {"coordinates":[-81.4167,31.25],"type":"Point"}
}