{
  "id": 2232549,
  "type": "Feature",
  "properties": {
    "tgn:hierarchy":[
        "tgn:2232549",
        "tgn:1000001",
        "tgn:7012149",
        "tgn:1002474",
        "tgn:7007709",
        "tgn:7029392"
    ],
    "tgn:id":2232549,
    "tgn:name":"Chapel Branch",
    "tgn:placetype":[
        "aat:300008699"
    ]
},
  "bbox": [],
  "geometry": {"coordinates":[-77.05,36.3167],"type":"Point"}
}