{
  "id": 2346146,
  "type": "Feature",
  "properties": {
    "tgn:hierarchy":[
        "tgn:2346146",
        "tgn:1000001",
        "tgn:7012149",
        "tgn:2001710",
        "tgn:7007708",
        "tgn:7029392"
    ],
    "tgn:id":2346146,
    "tgn:name":"Gate Creek",
    "tgn:placetype":[
        "aat:300008706"
    ]
},
  "bbox": [],
  "geometry": {"coordinates":[-121.7333,45.6167],"type":"Point"}
}