{
  "id": 1023530,
  "type": "Feature",
  "properties": {
    "tgn:hierarchy":[
        "tgn:1023530",
        "tgn:1001708",
        "tgn:1000049",
        "tgn:1000002",
        "tgn:7029392"
    ],
    "tgn:id":1023530,
    "tgn:name":"Los Quillayes",
    "tgn:placetype":[
        "aat:300008347"
    ]
},
  "bbox": [],
  "geometry": {"coordinates":[-70.616667,-33.566667],"type":"Point"}
}