{
  "id": 2242781,
  "type": "Feature",
  "properties": {
    "tgn:hierarchy":[
        "tgn:2242781",
        "tgn:1000001",
        "tgn:7012149",
        "tgn:2001876",
        "tgn:7007825",
        "tgn:7029392"
    ],
    "tgn:id":2242781,
    "tgn:name":"Clear Creek",
    "tgn:placetype":[
        "aat:300008706"
    ]
},
  "bbox": [],
  "geometry": {"coordinates":[-88.3333,36.4667],"type":"Point"}
}