{
  "id": 2649916,
  "type": "Feature",
  "properties": {
    "tgn:hierarchy":[
        "tgn:2649916",
        "tgn:1000001",
        "tgn:7012149",
        "tgn:2000836",
        "tgn:7007255",
        "tgn:7029392"
    ],
    "tgn:id":2649916,
    "tgn:name":"Scuddy Branch",
    "tgn:placetype":[
        "aat:300008699"
    ]
},
  "bbox": [],
  "geometry": {"coordinates":[-83.0667,37.1833],"type":"Point"}
}