{
  "id": 7511439,
  "type": "Feature",
  "properties": {
    "tgn:hierarchy":[
        "tgn:7511439",
        "tgn:1009227",
        "tgn:1000226",
        "tgn:7520095",
        "tgn:1000006",
        "tgn:7029392"
    ],
    "tgn:id":7511439,
    "tgn:name:en":"Moutere",
    "tgn:placetype":[
        "aat:300132316"
    ]
},
  "bbox": [],
  "geometry": {"coordinates":[172.166667,-40.833333],"type":"Point"}
}