{
  "id": 7149918,
  "type": "Feature",
  "properties": {
    "tgn:hierarchy":[
        "tgn:7149918",
        "tgn:1000003",
        "tgn:7003678",
        "tgn:7000084",
        "tgn:7029392"
    ],
    "tgn:id":7149918,
    "tgn:name":"Laisbach",
    "tgn:placetype":[
        "aat:300008699"
    ]
},
  "bbox": [],
  "geometry": {"coordinates":[8.95,50.366667],"type":"Point"}
}