<<<<<<< HEAD
{
  "id": 7363194,
  "type": "Feature",
  "properties": {
    "tgn:hierarchy":[
        "tgn:7363194",
        "tgn:1000001",
        "tgn:7005589",
        "tgn:7005560",
        "tgn:7029392"
    ],
    "tgn:id":7363194,
    "tgn:name":"El Cerrito",
    "tgn:placetype":[
        "aat:300008795"
    ]
},
  "bbox": [],
  "geometry": {"coordinates":[-100.066667,26.016667],"type":"Point"}
}
=======
{"geometry":{"type":"Point","coordinates":[-100.066667,26.016667]},"type":"Feature","properties":{"hierarchy":["tgn:7363194","tgn:1000001","tgn:7005589","tgn:7005560","tgn:7029392"],"placetype":["aat:300008795"],"id":7363194,"name:xx":"El Cerrito"}}
>>>>>>> 03f74aca74312dbeaf24d7e61306dd6a786dc3d0
