<<<<<<< HEAD
{
  "id": 7113275,
  "type": "Feature",
  "properties": {
    "tgn:hierarchy":[
        "tgn:7113275",
        "tgn:7003669",
        "tgn:1000003",
        "tgn:7000084",
        "tgn:7029392"
    ],
    "tgn:id":7113275,
    "tgn:name":"Reut",
    "tgn:placetype":[
        "aat:300008347"
    ]
},
  "bbox": [],
  "geometry": {"coordinates":[13.6,48.766667],"type":"Point"}
}
=======
{"geometry":{"type":"Point","coordinates":[13.600000,48.766667]},"type":"Feature","properties":{"hierarchy":["tgn:7113275","tgn:7003669","tgn:1000003","tgn:7000084","tgn:7029392"],"placetype":["aat:300008347"],"id":7113275,"name:xx":"Reut"}}
>>>>>>> 03f74aca74312dbeaf24d7e61306dd6a786dc3d0
