{
  "id": 2024266,
  "type": "Feature",
  "properties": {
    "tgn:hierarchy":[
        "tgn:2024266",
        "tgn:1000001",
        "tgn:2000327",
        "tgn:7012149",
        "tgn:7007248",
        "tgn:7029392"
    ],
    "tgn:id":2024266,
    "tgn:name":"Sawdust",
    "tgn:placetype":[
        "aat:300008347"
    ]
},
  "bbox": [],
  "geometry": {"coordinates":[-82.3167,33.4167],"type":"Point"}
}