{
  "id": 2201029,
  "type": "Feature",
  "properties": {
    "tgn:hierarchy":[
        "tgn:2201029",
        "tgn:1000001",
        "tgn:7012149",
        "tgn:1002425",
        "tgn:7007919",
        "tgn:7029392"
    ],
    "tgn:id":2201029,
    "tgn:name":"Bryants Millpond",
    "tgn:placetype":[
        "aat:300006191"
    ]
},
  "bbox": [],
  "geometry": {"coordinates":[-77.4333,36.5667],"type":"Point"}
}