{
  "id": 2056814,
  "type": "Feature",
  "properties": {
    "tgn:hierarchy":[
        "tgn:2056814",
        "tgn:1000001",
        "tgn:7012149",
        "tgn:2001153",
        "tgn:7007522",
        "tgn:7029392"
    ],
    "tgn:id":2056814,
    "tgn:name":"Leverett",
    "tgn:placetype":[
        "aat:300008347",
        "aat:300387210"
    ]
},
  "bbox": [],
  "geometry": {"coordinates":[-90.0667,33.8667],"type":"Point"}
}