{
  "id": 7309988,
  "type": "Feature",
  "properties": {
    "tgn:hierarchy":[
        "tgn:7309988",
        "tgn:1001637",
        "tgn:1000049",
        "tgn:1000002",
        "tgn:7029392"
    ],
    "tgn:id":7309988,
    "tgn:name":"Mutup\u00edn",
    "tgn:placetype":[
        "aat:300008347"
    ]
},
  "bbox": [],
  "geometry": {"coordinates":[-71.866667,-36.433333],"type":"Point"}
}