{
  "id": 7432621,
  "type": "Feature",
  "properties": {
    "tgn:hierarchy":[
        "tgn:7432621",
        "tgn:1000001",
        "tgn:7005590",
        "tgn:7005560",
        "tgn:7029392"
    ],
    "tgn:id":7432621,
    "tgn:name":"Tomend\u00e1n",
    "tgn:placetype":[
        "aat:300007783"
    ]
},
  "bbox": [],
  "geometry": {"coordinates":[-101.85,19.233333],"type":"Point"}
}