{
  "id": 2271230,
  "type": "Feature",
  "properties": {
    "tgn:hierarchy":[
        "tgn:2271230",
        "tgn:1000001",
        "tgn:7012149",
        "tgn:2001556",
        "tgn:7007709",
        "tgn:7029392"
    ],
    "tgn:id":2271230,
    "tgn:name":"Culbert Ridge",
    "tgn:placetype":[
        "aat:300266640"
    ]
},
  "bbox": [],
  "geometry": {"coordinates":[-82.4333,35.9667],"type":"Point"}
}