{
  "id": 7560484,
  "type": "Feature",
  "properties": {
    "tgn:hierarchy":[
        "tgn:7560484",
        "tgn:1000004",
        "tgn:7000198",
        "tgn:7016722",
        "tgn:7029392"
    ],
    "tgn:id":7560484,
    "tgn:name:en":"Nagla Bhoj",
    "tgn:placetype":[
        "aat:300008347"
    ]
},
  "bbox": [],
  "geometry": {"coordinates":[79.220434,26.822557],"type":"Point"}
}