{
  "id": 7139381,
  "type": "Feature",
  "properties": {
    "tgn:hierarchy":[
        "tgn:7139381",
        "tgn:7003692",
        "tgn:1000003",
        "tgn:7000084",
        "tgn:7029392"
    ],
    "tgn:id":7139381,
    "tgn:name":"Leinenfirst",
    "tgn:placetype":[
        "aat:300008347"
    ]
},
  "bbox": [],
  "geometry": {"coordinates":[10.033333,48.95],"type":"Point"}
}