{
  "id": 2414647,
  "type": "Feature",
  "properties": {
    "tgn:hierarchy":[
        "tgn:2414647",
        "tgn:1000001",
        "tgn:7012149",
        "tgn:2001716",
        "tgn:7007708",
        "tgn:7029392"
    ],
    "tgn:id":2414647,
    "tgn:name":"Irving Glacier",
    "tgn:placetype":[
        "aat:300008835"
    ]
},
  "bbox": [],
  "geometry": {"coordinates":[-121.7667,44.1333],"type":"Point"}
}