{
  "id": 7291651,
  "type": "Feature",
  "properties": {
    "tgn:hierarchy":[
        "tgn:7291651",
        "tgn:1001702",
        "tgn:1000049",
        "tgn:1000002",
        "tgn:7029392"
    ],
    "tgn:id":7291651,
    "tgn:name":"Entrada, Islotes",
    "tgn:placetype":[
        "aat:300008791"
    ]
},
  "bbox": [],
  "geometry": {"coordinates":[-70.966667,-54.266667],"type":"Point"}
}