<<<<<<< HEAD
{
  "id": 7244534,
  "type": "Feature",
  "properties": {
    "tgn:hierarchy":[
        "tgn:7244534",
        "tgn:7003460",
        "tgn:1000003",
        "tgn:1000063",
        "tgn:4012014",
        "tgn:7029392"
    ],
    "tgn:id":7244534,
    "tgn:name":"Kuckeberg",
    "tgn:placetype":[
        "aat:300008777"
    ]
},
  "bbox": [],
  "geometry": {"coordinates":[6.0375,50.245833],"type":"Point"}
}
=======
{"geometry":{"type":"Point","coordinates":[6.037500,50.245833]},"type":"Feature","properties":{"hierarchy":["tgn:7244534","tgn:7003460","tgn:1000003","tgn:1000063","tgn:4012014","tgn:7029392"],"placetype":["aat:300008777"],"id":7244534,"name:xx":"Kuckeberg"}}
>>>>>>> 03f74aca74312dbeaf24d7e61306dd6a786dc3d0
