{
  "id": 2778525,
  "type": "Feature",
  "properties": {
    "tgn:hierarchy":[
        "tgn:2778525",
        "tgn:1000001",
        "tgn:7012149",
        "tgn:2001831",
        "tgn:7007713",
        "tgn:7029392"
    ],
    "tgn:id":2778525,
    "tgn:name":"Witten Dam Reservoir",
    "tgn:placetype":[
        "aat:300006191"
    ]
},
  "bbox": [],
  "geometry": {"coordinates":[-100.0667,43.4333],"type":"Point"}
}