{
  "id": 2781959,
  "type": "Feature",
  "properties": {
    "tgn:hierarchy":[
        "tgn:2781959",
        "tgn:1000001",
        "tgn:7012149",
        "tgn:1002917",
        "tgn:7007706",
        "tgn:7029392"
    ],
    "tgn:id":2781959,
    "tgn:name":"Woods Lake",
    "tgn:placetype":[
        "aat:300008680"
    ]
},
  "bbox": [],
  "geometry": {"coordinates":[-81.1833,40.9333],"type":"Point"}
}