{
  "id": 1122228,
  "type": "Feature",
  "properties": {
    "tgn:hierarchy":[
        "tgn:1122228",
        "tgn:7005735",
        "tgn:7005685",
        "tgn:1000001",
        "tgn:7029392"
    ],
    "tgn:id":1122228,
    "tgn:name":"Bridge River",
    "tgn:placetype":[
        "aat:300008707"
    ]
},
  "bbox": [],
  "geometry": {"coordinates":[-121.9167,50.75],"type":"Point"}
}