{
  "id": 7559933,
  "type": "Feature",
  "properties": {
    "tgn:hierarchy":[
        "tgn:7559933",
        "tgn:1000004",
        "tgn:7000198",
        "tgn:7016788",
        "tgn:7029392"
    ],
    "tgn:id":7559933,
    "tgn:name:en":"Kheri",
    "tgn:placetype":[
        "aat:300008347"
    ]
},
  "bbox": [],
  "geometry": {"coordinates":[75.505937,26.957269],"type":"Point"}
}