{
  "id": 2724189,
  "type": "Feature",
  "properties": {
    "tgn:hierarchy":[
        "tgn:2724189",
        "tgn:1000001",
        "tgn:2002144",
        "tgn:7012149",
        "tgn:7007919",
        "tgn:7029392"
    ],
    "tgn:id":2724189,
    "tgn:name":"Tom Branch",
    "tgn:placetype":[
        "aat:300008699"
    ]
},
  "bbox": [],
  "geometry": {"coordinates":[-79.5833,37.0833],"type":"Point"}
}