{
  "id": 2268396,
  "type": "Feature",
  "properties": {
    "tgn:hierarchy":[
        "tgn:2268396",
        "tgn:1000001",
        "tgn:7012149",
        "tgn:1002501",
        "tgn:7007710",
        "tgn:7029392"
    ],
    "tgn:id":2268396,
    "tgn:name":"Crooked Run",
    "tgn:placetype":[
        "aat:300008699"
    ]
},
  "bbox": [],
  "geometry": {"coordinates":[-78.9833,40.7667],"type":"Point"}
}