{
  "id": 7245996,
  "type": "Feature",
  "properties": {
    "tgn:hierarchy":[
        "tgn:7245996",
        "tgn:7003456",
        "tgn:1000003",
        "tgn:1000063",
        "tgn:7018236",
        "tgn:7029392"
    ],
    "tgn:id":7245996,
    "tgn:name":"De Schot",
    "tgn:placetype":[
        "aat:300000206"
    ]
},
  "bbox": [],
  "geometry": {"coordinates":[4.666667,50.966667],"type":"Point"}
}