{
  "id": 7218844,
  "type": "Feature",
  "properties": {
    "tgn:hierarchy":[
        "tgn:7218844",
        "tgn:7011161",
        "tgn:7002674",
        "tgn:1000003",
        "tgn:1000074",
        "tgn:7029392"
    ],
    "tgn:id":7218844,
    "tgn:name":"K\u00f3finas",
    "tgn:placetype":[
        "aat:300008798"
    ]
},
  "bbox": [],
  "geometry": {"coordinates":[26.040833,38.261389],"type":"Point"}
}