{
  "id": 2327774,
  "type": "Feature",
  "properties": {
    "tgn:hierarchy":[
        "tgn:2327774",
        "tgn:1000001",
        "tgn:7012149",
        "tgn:2001290",
        "tgn:7007524",
        "tgn:7029392"
    ],
    "tgn:id":2327774,
    "tgn:name":"Fish Creek Mine",
    "tgn:placetype":[
        "aat:300000390"
    ]
},
  "bbox": [],
  "geometry": {"coordinates":[-114.7333,46.9167],"type":"Point"}
}