{
  "id": 7040317,
  "type": "Feature",
  "properties": {
    "tgn:hierarchy":[
        "tgn:7040317",
        "tgn:7003162",
        "tgn:1000003",
        "tgn:7009760",
        "tgn:1000080",
        "tgn:7029392"
    ],
    "tgn:id":7040317,
    "tgn:name":"San Zio, Monte",
    "tgn:placetype":[
        "aat:300008795"
    ]
},
  "bbox": [],
  "geometry": {"coordinates":[11.75,43.466667],"type":"Point"}
}