{
  "id": 7297133,
  "type": "Feature",
  "properties": {
    "tgn:hierarchy":[
        "tgn:7297133",
        "tgn:7002760",
        "tgn:1000003",
        "tgn:1000095",
        "tgn:7029392"
    ],
    "tgn:id":7297133,
    "tgn:name":"Tarriba",
    "tgn:placetype":[
        "aat:300008347"
    ]
},
  "bbox": [],
  "geometry": {"coordinates":[-4.033333,43.266667],"type":"Point"}
}