{
  "id": 7324315,
  "type": "Feature",
  "properties": {
    "tgn:hierarchy":[
        "tgn:7324315",
        "tgn:7001158",
        "tgn:7002848",
        "tgn:1000003",
        "tgn:1000095",
        "tgn:7029392"
    ],
    "tgn:id":7324315,
    "tgn:name":"San Pedro de Latarce",
    "tgn:placetype":[
        "aat:300008347"
    ]
},
  "bbox": [],
  "geometry": {"coordinates":[-5.316667,41.733333],"type":"Point"}
}