{
  "id": 2537531,
  "type": "Feature",
  "properties": {
    "tgn:hierarchy":[
        "tgn:2537531",
        "tgn:1000001",
        "tgn:7012149",
        "tgn:2001843",
        "tgn:7007825",
        "tgn:7029392"
    ],
    "tgn:id":2537531,
    "tgn:name":"Negro Ridge",
    "tgn:placetype":[
        "aat:300266640"
    ]
},
  "bbox": [],
  "geometry": {"coordinates":[-84.05,36.35],"type":"Point"}
}