{
  "id": 7296082,
  "type": "Feature",
  "properties": {
    "tgn:hierarchy":[
        "tgn:7296082",
        "tgn:7008912",
        "tgn:7030216",
        "tgn:1000003",
        "tgn:1000095",
        "tgn:7029392"
    ],
    "tgn:id":7296082,
    "tgn:name":"Y\u00f1ola, R\u00edo",
    "tgn:placetype":[
        "aat:300008699"
    ]
},
  "bbox": [],
  "geometry": {"coordinates":[0.904298,42.709704],"type":"Point"}
}