{
  "id": 7556927,
  "type": "Feature",
  "properties": {
    "tgn:hierarchy":[
        "tgn:7556927",
        "tgn:1000004",
        "tgn:7000198",
        "tgn:7016788",
        "tgn:7029392"
    ],
    "tgn:id":7556927,
    "tgn:name:en":"R\u0101mganj Mandi",
    "tgn:placetype":[
        "aat:300008347"
    ]
},
  "bbox": [],
  "geometry": {"coordinates":[75.943251,24.646476],"type":"Point"}
}