{
  "id": 2186465,
  "type": "Feature",
  "properties": {
    "tgn:hierarchy":[
        "tgn:2186465",
        "tgn:1000001",
        "tgn:7012149",
        "tgn:2002264",
        "tgn:7013961",
        "tgn:7029392"
    ],
    "tgn:id":2186465,
    "tgn:name":"Bone Cave",
    "tgn:placetype":[
        "aat:300008746"
    ]
},
  "bbox": [],
  "geometry": {"coordinates":[-80.3333,37.9833],"type":"Point"}
}