{
  "id": 7325945,
  "type": "Feature",
  "properties": {
    "tgn:hierarchy":[
        "tgn:7325945",
        "tgn:7002847",
        "tgn:1001647",
        "tgn:1000003",
        "tgn:1000095",
        "tgn:7029392"
    ],
    "tgn:id":7325945,
    "tgn:name":"San Juli\u00e1n, Arroyo de",
    "tgn:placetype":[
        "aat:300008699"
    ]
},
  "bbox": [],
  "geometry": {"coordinates":[-5.333333,40.05],"type":"Point"}
}