{
  "id": 2575411,
  "type": "Feature",
  "properties": {
    "tgn:hierarchy":[
        "tgn:2575411",
        "tgn:1000001",
        "tgn:2001265",
        "tgn:7012149",
        "tgn:7007524",
        "tgn:7029392"
    ],
    "tgn:id":2575411,
    "tgn:name":"Pentecost Reservoir",
    "tgn:placetype":[
        "aat:300006191"
    ]
},
  "bbox": [],
  "geometry": {"coordinates":[-104.95,45.3833],"type":"Point"}
}