{
  "id": 7573319,
  "type": "Feature",
  "properties": {
    "tgn:hierarchy":[
        "tgn:7573319",
        "tgn:1000004",
        "tgn:7000198",
        "tgn:7016694",
        "tgn:7029392"
    ],
    "tgn:id":7573319,
    "tgn:name:en":"Gumsar",
    "tgn:placetype":[
        "aat:300008347"
    ]
},
  "bbox": [],
  "geometry": {"coordinates":[83.366667,20.366667],"type":"Point"}
}