{
  "id": 7345927,
  "type": "Feature",
  "properties": {
    "tgn:hierarchy":[
        "tgn:7345927",
        "tgn:7001155",
        "tgn:1000003",
        "tgn:7002790",
        "tgn:1000095",
        "tgn:7029392"
    ],
    "tgn:id":7345927,
    "tgn:name":"Ar\u00f3stegui",
    "tgn:placetype":[
        "aat:300008347"
    ]
},
  "bbox": [],
  "geometry": {"coordinates":[-1.683333,42.933333],"type":"Point"}
}