{
  "id": 7032757,
  "type": "Feature",
  "properties": {
    "tgn:hierarchy":[
        "tgn:7032757",
        "tgn:1000001",
        "tgn:1001893",
        "tgn:7005560",
        "tgn:7029392"
    ],
    "tgn:id":7032757,
    "tgn:name":"Huexotla",
    "tgn:placetype":[
        "aat:300008347",
        "aat:300000810",
        "aat:300167671",
        "aat:300016619",
        "aat:300008057"
    ]
},
  "bbox": [],
  "geometry": {"coordinates":[-98.872,19.475],"type":"Point"}
}