{
  "id": 7050180,
  "type": "Feature",
  "properties": {
    "tgn:hierarchy":[
        "tgn:7050180",
        "tgn:7003128",
        "tgn:1000003",
        "tgn:7008516",
        "tgn:1000080",
        "tgn:7029392"
    ],
    "tgn:id":7050180,
    "tgn:name":"La Terzana",
    "tgn:placetype":[
        "aat:300008347"
    ]
},
  "bbox": [],
  "geometry": {"coordinates":[11.316667,44.933333],"type":"Point"}
}