{
  "id": 7585097,
  "type": "Feature",
  "properties": {
    "tgn:hierarchy":[
        "tgn:7585097",
        "tgn:1000004",
        "tgn:7000198",
        "tgn:1001894",
        "tgn:7029392"
    ],
    "tgn:id":7585097,
    "tgn:name:en":"Jur\u0101w\u0101n",
    "tgn:placetype":[
        "aat:300008347"
    ]
},
  "bbox": [],
  "geometry": {"coordinates":[78.836713,24.65458],"type":"Point"}
}