{
  "id": 7258449,
  "type": "Feature",
  "properties": {
    "tgn:hierarchy":[
        "tgn:7258449",
        "tgn:7003456",
        "tgn:1000003",
        "tgn:1000063",
        "tgn:7018236",
        "tgn:7029392"
    ],
    "tgn:id":7258449,
    "tgn:name":"Zevenbunder",
    "tgn:placetype":[
        "aat:300000206"
    ]
},
  "bbox": [],
  "geometry": {"coordinates":[4.45,51.083333],"type":"Point"}
}