{
  "id": 2494488,
  "type": "Feature",
  "properties": {
    "tgn:hierarchy":[
        "tgn:2494488",
        "tgn:1000001",
        "tgn:7012149",
        "tgn:1002700",
        "tgn:7007520",
        "tgn:7029392"
    ],
    "tgn:id":2494488,
    "tgn:name":"Martin Drain",
    "tgn:placetype":[
        "aat:300006075"
    ]
},
  "bbox": [],
  "geometry": {"coordinates":[-86.0667,43.4167],"type":"Point"}
}