{
  "id": 7393942,
  "type": "Feature",
  "properties": {
    "tgn:hierarchy":[
        "tgn:7393942",
        "tgn:1000001",
        "tgn:7005591",
        "tgn:7005560",
        "tgn:7029392"
    ],
    "tgn:id":7393942,
    "tgn:name":"San Juan Yuta",
    "tgn:placetype":[
        "aat:300008347"
    ]
},
  "bbox": [],
  "geometry": {"coordinates":[-97.166667,17.016667],"type":"Point"}
}