{
  "id": 2054359,
  "type": "Feature",
  "properties": {
    "tgn:hierarchy":[
        "tgn:2054359",
        "tgn:1000001",
        "tgn:7012149",
        "tgn:2001029",
        "tgn:7007521",
        "tgn:7029392"
    ],
    "tgn:id":2054359,
    "tgn:name":"Effie",
    "tgn:placetype":[
        "aat:300008347"
    ]
},
  "bbox": [],
  "geometry": {"coordinates":[-93.6333,47.8333],"type":"Point"}
}