{
  "id": 2195668,
  "type": "Feature",
  "properties": {
    "tgn:hierarchy":[
        "tgn:2195668",
        "tgn:1000001",
        "tgn:7013368",
        "tgn:7012149",
        "tgn:7007709",
        "tgn:7029392"
    ],
    "tgn:id":2195668,
    "tgn:name":"Broad Creek Canal",
    "tgn:placetype":[
        "aat:300006075"
    ]
},
  "bbox": [],
  "geometry": {"coordinates":[-76.7167,35.5833],"type":"Point"}
}