{
  "id": 7280829,
  "type": "Feature",
  "properties": {
    "tgn:hierarchy":[
        "tgn:7280829",
        "tgn:1001692",
        "tgn:1000049",
        "tgn:1000002",
        "tgn:7029392"
    ],
    "tgn:id":7280829,
    "tgn:name":"Santa Mar\u00eda",
    "tgn:placetype":[
        "aat:300008347"
    ]
},
  "bbox": [],
  "geometry": {"coordinates":[-71.666667,-38.816667],"type":"Point"}
}