<<<<<<< HEAD
{
  "id": 7372475,
  "type": "Feature",
  "properties": {
    "tgn:hierarchy":[
        "tgn:7372475",
        "tgn:7005581",
        "tgn:1000001",
        "tgn:7005560",
        "tgn:7029392"
    ],
    "tgn:id":7372475,
    "tgn:name":"La Noria",
    "tgn:placetype":[
        "aat:300008347"
    ]
},
  "bbox": [],
  "geometry": {"coordinates":[-107.716667,30.716667],"type":"Point"}
}
=======
{"geometry":{"type":"Point","coordinates":[-107.716667,30.716667]},"type":"Feature","properties":{"hierarchy":["tgn:7372475","tgn:7005581","tgn:1000001","tgn:7005560","tgn:7029392"],"placetype":["aat:300008347"],"id":7372475,"name:xx":"La Noria"}}
>>>>>>> 03f74aca74312dbeaf24d7e61306dd6a786dc3d0
