{
  "id": 2423884,
  "type": "Feature",
  "properties": {
    "tgn:hierarchy":[
        "tgn:2423884",
        "tgn:1000001",
        "tgn:7012149",
        "tgn:2000181",
        "tgn:7007157",
        "tgn:7029392"
    ],
    "tgn:id":2423884,
    "tgn:name":"Johnny Jack Ridge",
    "tgn:placetype":[
        "aat:300266640"
    ]
},
  "bbox": [],
  "geometry": {"coordinates":[-124.2833,40.25],"type":"Point"}
}