{
  "id": 7559621,
  "type": "Feature",
  "properties": {
    "tgn:hierarchy":[
        "tgn:7559621",
        "tgn:1000004",
        "tgn:7000198",
        "tgn:7016722",
        "tgn:7029392"
    ],
    "tgn:id":7559621,
    "tgn:name:en":"Bul\u0101ki Purwa",
    "tgn:placetype":[
        "aat:300008347"
    ]
},
  "bbox": [],
  "geometry": {"coordinates":[79.9172,27.0206],"type":"Point"}
}