{
  "id": 2323063,
  "type": "Feature",
  "properties": {
    "tgn:hierarchy":[
        "tgn:2323063",
        "tgn:1000001",
        "tgn:2000465",
        "tgn:7012149",
        "tgn:7007250",
        "tgn:7029392"
    ],
    "tgn:id":2323063,
    "tgn:name":"Fargo Low Line Canal",
    "tgn:placetype":[
        "aat:300006075"
    ]
},
  "bbox": [],
  "geometry": {"coordinates":[-116.9167,43.65],"type":"Point"}
}