{
  "id": 2318775,
  "type": "Feature",
  "properties": {
    "tgn:hierarchy":[
        "tgn:2318775",
        "tgn:1000001",
        "tgn:7006451",
        "tgn:2000092",
        "tgn:7012149",
        "tgn:7029392"
    ],
    "tgn:id":2318775,
    "tgn:name":"Escalante Creek",
    "tgn:placetype":[
        "aat:300008706"
    ]
},
  "bbox": [],
  "geometry": {"coordinates":[-111.85,36.05],"type":"Point"}
}