{
  "id": 2600811,
  "type": "Feature",
  "properties": {
    "tgn:hierarchy":[
        "tgn:2600811",
        "tgn:1000001",
        "tgn:2001419",
        "tgn:7012149",
        "tgn:7007526",
        "tgn:7029392"
    ],
    "tgn:id":2600811,
    "tgn:name":"Pumpernickel Reservoir",
    "tgn:placetype":[
        "aat:300006191"
    ]
},
  "bbox": [],
  "geometry": {"coordinates":[-117.4833,40.6667],"type":"Point"}
}