{
  "id": 2387919,
  "type": "Feature",
  "properties": {
    "tgn:hierarchy":[
        "tgn:2387919",
        "tgn:1000001",
        "tgn:7012149",
        "tgn:7007710",
        "tgn:7029392"
    ],
    "tgn:id":2387919,
    "tgn:name":"Hickory Bottom Creek",
    "tgn:placetype":[
        "aat:300008706"
    ]
},
  "bbox": [],
  "geometry": {"coordinates":[-78.3167,40.25],"type":"Point"}
}