{
  "id": 2420008,
  "type": "Feature",
  "properties": {
    "tgn:hierarchy":[
        "tgn:2420008",
        "tgn:2001086",
        "tgn:1000001",
        "tgn:7012149",
        "tgn:7007522",
        "tgn:7029392"
    ],
    "tgn:id":2420008,
    "tgn:name":"Jeannette",
    "tgn:placetype":[
        "aat:300008347"
    ]
},
  "bbox": [],
  "geometry": {"coordinates":[-91.2333,31.4833],"type":"Point"}
}