{
  "id": 7536986,
  "type": "Feature",
  "properties": {
    "tgn:hierarchy":[
        "tgn:7536986",
        "tgn:7001242",
        "tgn:7016833",
        "tgn:1001087",
        "tgn:7029392"
    ],
    "tgn:id":7536986,
    "tgn:name:en":"Kafr ash Shaba'",
    "tgn:placetype":[
        "aat:300008347"
    ]
},
  "bbox": [],
  "geometry": {"coordinates":[30.842469,30.63825],"type":"Point"}
}