{
  "id": 7322651,
  "type": "Feature",
  "properties": {
    "tgn:hierarchy":[
        "tgn:7322651",
        "tgn:7002849",
        "tgn:1000003",
        "tgn:7009604",
        "tgn:1000095",
        "tgn:7029392"
    ],
    "tgn:id":7322651,
    "tgn:name":"Salvajes, Playa de los",
    "tgn:placetype":[
        "aat:300008816"
    ]
},
  "bbox": [],
  "geometry": {"coordinates":[-2.983333,43.383333],"type":"Point"}
}