{
  "id": 7411197,
  "type": "Feature",
  "properties": {
    "tgn:hierarchy":[
        "tgn:7411197",
        "tgn:1000001",
        "tgn:7005596",
        "tgn:7005560",
        "tgn:7029392"
    ],
    "tgn:id":7411197,
    "tgn:name:es":"Chiguihuite",
    "tgn:placetype":[
        "aat:300008347"
    ]
},
  "bbox": [],
  "geometry": {"coordinates":[-92.404167,17.816667],"type":"Point"}
}