{
  "id": 7407988,
  "type": "Feature",
  "properties": {
    "tgn:hierarchy":[
        "tgn:7407988",
        "tgn:7005580",
        "tgn:1000001",
        "tgn:7005560",
        "tgn:7029392"
    ],
    "tgn:id":7407988,
    "tgn:name":"Manuel Velazco Su\u00e1rez",
    "tgn:placetype":[
        "aat:300008347"
    ]
},
  "bbox": [],
  "geometry": {"coordinates":[-92.216667,16.116667],"type":"Point"}
}