{
  "id": 7245830,
  "type": "Feature",
  "properties": {
    "tgn:hierarchy":[
        "tgn:7245830",
        "tgn:7007877",
        "tgn:1000003",
        "tgn:1000063",
        "tgn:4012014",
        "tgn:7029392"
    ],
    "tgn:id":7245830,
    "tgn:name":"Coeurq",
    "tgn:placetype":[
        "aat:300008347"
    ]
},
  "bbox": [],
  "geometry": {"coordinates":[4.190159,50.664248],"type":"Point"}
}