<<<<<<< HEAD
{
  "id": 2257651,
  "type": "Feature",
  "properties": {
    "tgn:hierarchy":[
        "tgn:2257651",
        "tgn:1000001",
        "tgn:7012149",
        "tgn:2001715",
        "tgn:7007708",
        "tgn:7029392"
    ],
    "tgn:id":2257651,
    "tgn:name":"Corral Creek",
    "tgn:placetype":[
        "aat:300008706"
    ]
},
  "bbox": [],
  "geometry": {"coordinates":[-119.6667,42.4333],"type":"Point"}
}
=======
{"geometry":{"type":"Point","coordinates":[-119.666700,42.433300]},"type":"Feature","properties":{"hierarchy":["tgn:2257651","tgn:1000001","tgn:7012149","tgn:2001715","tgn:7007708","tgn:7029392"],"placetype":["aat:300008706"],"id":2257651,"name:xx":"Corral Creek"}}
>>>>>>> 03f74aca74312dbeaf24d7e61306dd6a786dc3d0
