{
  "id": 2387602,
  "type": "Feature",
  "properties": {
    "tgn:hierarchy":[
        "tgn:2387602",
        "tgn:1000001",
        "tgn:7012149",
        "tgn:7007157",
        "tgn:1002937",
        "tgn:7029392"
    ],
    "tgn:id":2387602,
    "tgn:name":"Hiatt Lake",
    "tgn:placetype":[
        "aat:300008680"
    ]
},
  "bbox": [],
  "geometry": {"coordinates":[-121.7833,38.8833],"type":"Point"}
}