{
  "id": 7577814,
  "type": "Feature",
  "properties": {
    "tgn:hierarchy":[
        "tgn:7577814",
        "tgn:1000004",
        "tgn:7000198",
        "tgn:1001998",
        "tgn:7029392"
    ],
    "tgn:id":7577814,
    "tgn:name:en":"Khuangleng",
    "tgn:placetype":[
        "aat:300008347"
    ]
},
  "bbox": [],
  "geometry": {"coordinates":[93.289155,23.306755],"type":"Point"}
}