{
  "id": 7562272,
  "type": "Feature",
  "properties": {
    "tgn:hierarchy":[
        "tgn:7562272",
        "tgn:1000004",
        "tgn:7000198",
        "tgn:7016722",
        "tgn:7029392"
    ],
    "tgn:id":7562272,
    "tgn:name:en":"Bh\u0101npur",
    "tgn:placetype":[
        "aat:300008347"
    ]
},
  "bbox": [],
  "geometry": {"coordinates":[79.8529,27.096],"type":"Point"}
}