<<<<<<< HEAD
{
  "id": 7115277,
  "type": "Feature",
  "properties": {
    "tgn:hierarchy":[
        "tgn:7115277",
        "tgn:1000003",
        "tgn:7003688",
        "tgn:7000084",
        "tgn:7029392"
    ],
    "tgn:id":7115277,
    "tgn:name":"Ostereck",
    "tgn:placetype":[
        "aat:300000206"
    ]
},
  "bbox": [],
  "geometry": {"coordinates":[8.65,54.333333],"type":"Point"}
}
=======
{"geometry":{"type":"Point","coordinates":[8.650000,54.333333]},"type":"Feature","properties":{"hierarchy":["tgn:7115277","tgn:1000003","tgn:7003688","tgn:7000084","tgn:7029392"],"placetype":["aat:300000206"],"id":7115277,"name:xx":"Ostereck"}}
>>>>>>> 03f74aca74312dbeaf24d7e61306dd6a786dc3d0
