{
  "id": 1086055,
  "type": "Feature",
  "properties": {
    "tgn:hierarchy":[
        "tgn:1086055",
        "tgn:1001569",
        "tgn:1000004",
        "tgn:7018450",
        "tgn:1000144",
        "tgn:7029392"
    ],
    "tgn:id":1086055,
    "tgn:name":"Ball\u0131",
    "tgn:placetype":[
        "aat:300008347"
    ]
},
  "bbox": [],
  "geometry": {"coordinates":[27.0833,40.85],"type":"Point"}
}