{
  "id": 7463237,
  "type": "Feature",
  "properties": {
    "tgn:hierarchy":[
        "tgn:7463237",
        "tgn:7002444",
        "tgn:1000003",
        "tgn:7008094",
        "tgn:7008591",
        "tgn:7029392"
    ],
    "tgn:id":7463237,
    "tgn:name:en":"Liana M\u00f2ire, Loch na",
    "tgn:placetype":[
        "aat:300008680"
    ]
},
  "bbox": [],
  "geometry": {"coordinates":[-7.433333,57.216667],"type":"Point"}
}