{
  "id": 7296370,
  "type": "Feature",
  "properties": {
    "tgn:hierarchy":[
        "tgn:7296370",
        "tgn:7002826",
        "tgn:7001158",
        "tgn:1000003",
        "tgn:1000095",
        "tgn:7029392"
    ],
    "tgn:id":7296370,
    "tgn:name":"Villari\u00f1os",
    "tgn:placetype":[
        "aat:300008347"
    ]
},
  "bbox": [],
  "geometry": {"coordinates":[-6.916667,42.733333],"type":"Point"}
}