{
  "id": 2338418,
  "type": "Feature",
  "properties": {
    "tgn:hierarchy":[
        "tgn:2338418",
        "tgn:1000001",
        "tgn:7012149",
        "tgn:2002300",
        "tgn:7013961",
        "tgn:7029392"
    ],
    "tgn:id":2338418,
    "tgn:name":"Foxtree Run",
    "tgn:placetype":[
        "aat:300008699"
    ]
},
  "bbox": [],
  "geometry": {"coordinates":[-80.45,38.2833],"type":"Point"}
}