{
  "id": 2509893,
  "type": "Feature",
  "properties": {
    "tgn:hierarchy":[
        "tgn:2509893",
        "tgn:1000001",
        "tgn:7012149",
        "tgn:2000232",
        "tgn:7007158",
        "tgn:7029392"
    ],
    "tgn:id":2509893,
    "tgn:name":"Middle Mountain",
    "tgn:placetype":[
        "aat:300008798"
    ]
},
  "bbox": [],
  "geometry": {"coordinates":[-108.9333,40.95],"type":"Point"}
}