{
  "id": 2235412,
  "type": "Feature",
  "properties": {
    "tgn:hierarchy":[
        "tgn:2235412",
        "tgn:1000001",
        "tgn:7012149",
        "tgn:2002386",
        "tgn:7007923",
        "tgn:7029392"
    ],
    "tgn:id":2235412,
    "tgn:name":"Chess Reservoir",
    "tgn:placetype":[
        "aat:300006191"
    ]
},
  "bbox": [],
  "geometry": {"coordinates":[-107.5833,43.9333],"type":"Point"}
}