{
  "id": 7232301,
  "type": "Feature",
  "properties": {
    "tgn:hierarchy":[
        "tgn:7232301",
        "tgn:7002707",
        "tgn:7002705",
        "tgn:1000003",
        "tgn:1000074",
        "tgn:7029392"
    ],
    "tgn:id":7232301,
    "tgn:name":"Koukko\u00falion",
    "tgn:placetype":[
        "aat:300008347"
    ]
},
  "bbox": [],
  "geometry": {"coordinates":[20.775833,39.869444],"type":"Point"}
}