{
  "id": 2344655,
  "type": "Feature",
  "properties": {
    "tgn:hierarchy":[
        "tgn:2344655",
        "tgn:1000001",
        "tgn:7012149",
        "tgn:2001449",
        "tgn:7007566",
        "tgn:7029392"
    ],
    "tgn:id":2344655,
    "tgn:name":"Garcia Tank",
    "tgn:placetype":[
        "aat:300006191"
    ]
},
  "bbox": [],
  "geometry": {"coordinates":[-106.5667,36.4167],"type":"Point"}
}