{
  "id": 2010766,
  "type": "Feature",
  "properties": {
    "tgn:hierarchy":[
        "tgn:2010766",
        "tgn:1000001",
        "tgn:7012149",
        "tgn:7007157",
        "tgn:2000187",
        "tgn:7029392"
    ],
    "tgn:id":2010766,
    "tgn:name":"Clio",
    "tgn:placetype":[
        "aat:300008347"
    ]
},
  "bbox": [],
  "geometry": {"coordinates":[-120.5667,39.7333],"type":"Point"}
}