<<<<<<< HEAD
{
  "id": 2761608,
  "type": "Feature",
  "properties": {
    "tgn:hierarchy":[
        "tgn:2761608",
        "tgn:1000001",
        "tgn:7012149",
        "tgn:7007515",
        "tgn:7029392"
    ],
    "tgn:id":2761608,
    "tgn:name":"West Penobscot Bay",
    "tgn:placetype":[
        "aat:300132316"
    ]
},
  "bbox": [],
  "geometry": {"coordinates":[-69.0,44.1833],"type":"Point"}
}
=======
{"geometry":{"type":"Point","coordinates":[-69.000000,44.183300]},"type":"Feature","properties":{"hierarchy":["tgn:2761608","tgn:1000001","tgn:7012149","tgn:7007515","tgn:7029392"],"placetype":["aat:300132316"],"id":2761608,"name:xx":"West Penobscot Bay"}}
>>>>>>> 03f74aca74312dbeaf24d7e61306dd6a786dc3d0
