{
  "id": 7041340,
  "type": "Feature",
  "properties": {
    "tgn:hierarchy":[
        "tgn:7041340",
        "tgn:7003134",
        "tgn:1000003",
        "tgn:7008516",
        "tgn:1000080",
        "tgn:7029392"
    ],
    "tgn:id":7041340,
    "tgn:name":"San Maurizio",
    "tgn:placetype":[
        "aat:300008347"
    ]
},
  "bbox": [],
  "geometry": {"coordinates":[10.683333,44.683333],"type":"Point"}
}