{
  "id": 2710036,
  "type": "Feature",
  "properties": {
    "tgn:hierarchy":[
        "tgn:2710036",
        "tgn:1000001",
        "tgn:7012149",
        "tgn:2002070",
        "tgn:7007826",
        "tgn:7029392"
    ],
    "tgn:id":2710036,
    "tgn:name":"Talbot Lake",
    "tgn:placetype":[
        "aat:300008680"
    ]
},
  "bbox": [],
  "geometry": {"coordinates":[-100.1167,30.8167],"type":"Point"}
}