{
  "id": 2348812,
  "type": "Feature",
  "properties": {
    "tgn:hierarchy":[
        "tgn:2348812",
        "tgn:1000001",
        "tgn:7012149",
        "tgn:2001539",
        "tgn:7007709",
        "tgn:7029392"
    ],
    "tgn:id":2348812,
    "tgn:name":"Gibson Mill",
    "tgn:placetype":[
        "aat:300008347"
    ]
},
  "bbox": [],
  "geometry": {"coordinates":[-79.4667,34.8333],"type":"Point"}
}