{
  "id": 7447732,
  "type": "Feature",
  "properties": {
    "tgn:hierarchy":[
        "tgn:7447732",
        "tgn:7002445",
        "tgn:1000003",
        "tgn:7012032",
        "tgn:7008591",
        "tgn:7029392"
    ],
    "tgn:id":7447732,
    "tgn:name:en":"Staple Fitzpaine",
    "tgn:placetype":[
        "aat:300008347"
    ]
},
  "bbox": [],
  "geometry": {"coordinates":[-3.05,50.95],"type":"Point"}
}