{
  "id": 7079130,
  "type": "Feature",
  "properties": {
    "tgn:hierarchy":[
        "tgn:7079130",
        "tgn:1000003",
        "tgn:7003677",
        "tgn:7000084",
        "tgn:7029392"
    ],
    "tgn:id":7079130,
    "tgn:name":"Bahnhof Wuppertal-Oberbarmen",
    "tgn:placetype":[
        "aat:300007783"
    ]
},
  "bbox": [],
  "geometry": {"coordinates":[7.221389,51.273611],"type":"Point"}
}