{
  "id": 2482422,
  "type": "Feature",
  "properties": {
    "tgn:hierarchy":[
        "tgn:2482422",
        "tgn:1000001",
        "tgn:1002218",
        "tgn:7012149",
        "tgn:7007157",
        "tgn:7029392"
    ],
    "tgn:id":2482422,
    "tgn:name":"Lanigan Gulch",
    "tgn:placetype":[
        "aat:300008761"
    ]
},
  "bbox": [],
  "geometry": {"coordinates":[-121.3667,39.5667],"type":"Point"}
}