{
  "id": 7243551,
  "type": "Feature",
  "properties": {
    "tgn:hierarchy":[
        "tgn:7243551",
        "tgn:7003461",
        "tgn:1000003",
        "tgn:1000063",
        "tgn:7018236",
        "tgn:7029392"
    ],
    "tgn:id":7243551,
    "tgn:name":"Mal",
    "tgn:placetype":[
        "aat:300008347"
    ]
},
  "bbox": [],
  "geometry": {"coordinates":[5.519697,50.768687],"type":"Point"}
}