{
  "id": 7004772,
  "type": "Feature",
  "properties": {
    "tgn:hierarchy":[
        "tgn:7004772",
        "tgn:1000001",
        "tgn:7029392"
    ],
    "tgn:id":7004772,
    "tgn:name:ar":"\u0633\u0627\u0647\u062a \u0648\u064b\u0633 \u0627\u064e",
    "tgn:name:en":"Saint Lucia",
    "tgn:name:es":"Sainte-Lucie",
    "tgn:name:fr":"Santa Luc\u00eda",
    "tgn:name:ru":"\u0421\u0435\u043d\u0442-\u041b\u044e\u0441\u0438\u044f",
    "tgn:name:zh":"\u5723\u5362\u897f\u4e9a",
    "tgn:placetype":[
        "aat:300387054",
        "aat:300235115",
        "aat:300387062",
        "aat:300128207",
        "aat:300387174"
    ]
},
  "bbox": [],
  "geometry": {"coordinates":[-60.9667,13.8833],"type":"Point"}
}