{
  "id": 2223459,
  "type": "Feature",
  "properties": {
    "tgn:hierarchy":[
        "tgn:2223459",
        "tgn:1000001",
        "tgn:7006451",
        "tgn:2000092",
        "tgn:7012149",
        "tgn:7029392"
    ],
    "tgn:id":2223459,
    "tgn:name":"Cart Ridge",
    "tgn:placetype":[
        "aat:300266640"
    ]
},
  "bbox": [],
  "geometry": {"coordinates":[-111.0833,34.5833],"type":"Point"}
}