{
  "id": 7228473,
  "type": "Feature",
  "properties": {
    "tgn:hierarchy":[
        "tgn:7228473",
        "tgn:7002690",
        "tgn:7012056",
        "tgn:1000003",
        "tgn:1000074",
        "tgn:7029392"
    ],
    "tgn:id":7228473,
    "tgn:name":"Gnafian\u00e1",
    "tgn:placetype":[
        "aat:300008347"
    ]
},
  "bbox": [],
  "geometry": {"coordinates":[23.783333,35.333333],"type":"Point"}
}