{
  "id": 2441351,
  "type": "Feature",
  "properties": {
    "tgn:hierarchy":[
        "tgn:2441351",
        "tgn:1000001",
        "tgn:1002260",
        "tgn:7012149",
        "tgn:7007920",
        "tgn:7029392"
    ],
    "tgn:id":2441351,
    "tgn:name":"Knox Lake",
    "tgn:placetype":[
        "aat:300008680"
    ]
},
  "bbox": [],
  "geometry": {"coordinates":[-120.8833,47.6833],"type":"Point"}
}