<<<<<<< HEAD
{
  "id": 7369622,
  "type": "Feature",
  "properties": {
    "tgn:hierarchy":[
        "tgn:7369622",
        "tgn:1001853",
        "tgn:1000001",
        "tgn:7005560",
        "tgn:7029392"
    ],
    "tgn:id":7369622,
    "tgn:name":"Guaje, Sierra del",
    "tgn:placetype":[
        "aat:300008777"
    ]
},
  "bbox": [],
  "geometry": {"coordinates":[-101.9,25.066667],"type":"Point"}
}
=======
{"geometry":{"type":"Point","coordinates":[-101.900000,25.066667]},"type":"Feature","properties":{"hierarchy":["tgn:7369622","tgn:1001853","tgn:1000001","tgn:7005560","tgn:7029392"],"placetype":["aat:300008777"],"id":7369622,"name:xx":"Guaje, Sierra del"}}
>>>>>>> 03f74aca74312dbeaf24d7e61306dd6a786dc3d0
