{
  "id": 7013797,
  "type": "Feature",
  "properties": {
    "tgn:hierarchy":[
        "tgn:7013797",
        "tgn:1000001",
        "tgn:7012149",
        "tgn:1002569",
        "tgn:7007252",
        "tgn:7029392"
    ],
    "tgn:id":7013797,
    "tgn:name":"Gary",
    "tgn:placetype":[
        "aat:300008347",
        "aat:300008389",
        "aat:300264742",
        "aat:300387302"
    ]
},
  "bbox": [],
  "geometry": {"coordinates":[-87.3333,41.5833],"type":"Point"}
}