<<<<<<< HEAD
{
  "id": 7021131,
  "type": "Feature",
  "properties": {
    "tgn:hierarchy":[
        "tgn:7021131",
        "tgn:1000001",
        "tgn:7012149",
        "tgn:2001027",
        "tgn:7007521",
        "tgn:7029392"
    ],
    "tgn:id":7021131,
    "tgn:name":"Emma, Lake",
    "tgn:placetype":[
        "aat:300008680"
    ]
},
  "bbox": [],
  "geometry": {"coordinates":[-95.0333,47.2833],"type":"Point"}
}
=======
{"geometry":{"type":"Point","coordinates":[-95.033300,47.283300]},"type":"Feature","properties":{"hierarchy":["tgn:7021131","tgn:1000001","tgn:7012149","tgn:2001027","tgn:7007521","tgn:7029392"],"placetype":["aat:300008680"],"id":7021131,"name:xx":"Emma, Lake"}}
>>>>>>> 03f74aca74312dbeaf24d7e61306dd6a786dc3d0
