<<<<<<< HEAD
{
  "id": 2152060,
  "type": "Feature",
  "properties": {
    "tgn:hierarchy":[
        "tgn:2152060",
        "tgn:7002659",
        "tgn:1000001",
        "tgn:7012149",
        "tgn:2000021",
        "tgn:7029392"
    ],
    "tgn:id":2152060,
    "tgn:name":"Bavar Creek",
    "tgn:placetype":[
        "aat:300008706"
    ]
},
  "bbox": [],
  "geometry": {"coordinates":[-86.8333,34.1],"type":"Point"}
}
=======
{"geometry":{"type":"Point","coordinates":[-86.833300,34.100000]},"type":"Feature","properties":{"hierarchy":["tgn:2152060","tgn:7002659","tgn:1000001","tgn:7012149","tgn:2000021","tgn:7029392"],"placetype":["aat:300008706"],"id":2152060,"name:xx":"Bavar Creek"}}
>>>>>>> 03f74aca74312dbeaf24d7e61306dd6a786dc3d0
