{
  "id": 1011609,
  "type": "Feature",
  "properties": {
    "tgn:hierarchy":[
        "tgn:1011609",
        "tgn:7001242",
        "tgn:7001311",
        "tgn:7016833",
        "tgn:7029392"
    ],
    "tgn:id":1011609,
    "tgn:name:en":"Ban\u0101s, Ra's",
    "tgn:placetype":[
        "aat:300386846"
    ]
},
  "bbox": [],
  "geometry": {"coordinates":[35.789269,23.905523],"type":"Point"}
}