{
  "id": 7209433,
  "type": "Feature",
  "properties": {
    "tgn:hierarchy":[
        "tgn:7209433",
        "tgn:1000003",
        "tgn:7003676",
        "tgn:7000084",
        "tgn:7029392"
    ],
    "tgn:id":7209433,
    "tgn:name":"Barg",
    "tgn:placetype":[
        "aat:300000206"
    ]
},
  "bbox": [],
  "geometry": {"coordinates":[7.833333,53.583333],"type":"Point"}
}