{
  "id": 2647874,
  "type": "Feature",
  "properties": {
    "tgn:hierarchy":[
        "tgn:2647874",
        "tgn:1000001",
        "tgn:7012149",
        "tgn:1002830",
        "tgn:7007826",
        "tgn:7029392"
    ],
    "tgn:id":2647874,
    "tgn:name":"Schoolhouse Branch",
    "tgn:placetype":[
        "aat:300008699"
    ]
},
  "bbox": [],
  "geometry": {"coordinates":[-96.4167,31.2333],"type":"Point"}
}