{
  "id": 7519774,
  "type": "Feature",
  "properties": {
    "tgn:hierarchy":[
        "tgn:7519774",
        "tgn:1009227",
        "tgn:7001866",
        "tgn:1000226",
        "tgn:1000006",
        "tgn:7029392"
    ],
    "tgn:id":7519774,
    "tgn:name:en":"Blackburn Stream",
    "tgn:placetype":[
        "aat:300008699"
    ]
},
  "bbox": [],
  "geometry": {"coordinates":[173.366667,-42.533333],"type":"Point"}
}