{
  "id": 2067114,
  "type": "Feature",
  "properties": {
    "tgn:hierarchy":[
        "tgn:2067114",
        "tgn:1000001",
        "tgn:7012149",
        "tgn:2001455",
        "tgn:7007566",
        "tgn:7029392"
    ],
    "tgn:id":2067114,
    "tgn:name":"Las Palomas",
    "tgn:placetype":[
        "aat:300008347",
        "aat:300387210"
    ]
},
  "bbox": [],
  "geometry": {"coordinates":[-107.2833,33.05],"type":"Point"}
}