{
  "id": 7479164,
  "type": "Feature",
  "properties": {
    "tgn:hierarchy":[
        "tgn:7479164",
        "tgn:1000004",
        "tgn:7490934",
        "tgn:1000141",
        "tgn:7029392"
    ],
    "tgn:id":7479164,
    "tgn:name":"Tainan N\u00fczi Jishuxueyuan",
    "tgn:placetype":[
        "aat:300006610"
    ]
},
  "bbox": [],
  "geometry": {"coordinates":[120.242778,23.036111],"type":"Point"}
}