<<<<<<< HEAD
{
  "id": 7479164,
  "type": "Feature",
  "properties": {
    "tgn:hierarchy":[
        "tgn:7479164",
        "tgn:1000004",
        "tgn:7490934",
        "tgn:1000141",
        "tgn:7029392"
    ],
    "tgn:id":7479164,
    "tgn:name":"Tainan N\u00fczi Jishuxueyuan",
    "tgn:placetype":[
        "aat:300006610"
    ]
},
  "bbox": [],
  "geometry": {"coordinates":[120.242778,23.036111],"type":"Point"}
}
=======
{"geometry":{"type":"Point","coordinates":[120.242778,23.036111]},"type":"Feature","properties":{"hierarchy":["tgn:7479164","tgn:1000004","tgn:7490934","tgn:1000141","tgn:7029392"],"placetype":["aat:300006610"],"id":7479164,"name:xx":"Tainan N\u00fczi Jishuxueyuan"}}
>>>>>>> 03f74aca74312dbeaf24d7e61306dd6a786dc3d0
