{
  "id": 1140896,
  "type": "Feature",
  "properties": {
    "tgn:hierarchy":[
        "tgn:1140896",
        "tgn:7001242",
        "tgn:7000556",
        "tgn:1000173",
        "tgn:7029392"
    ],
    "tgn:id":1140896,
    "tgn:name":"Fenoarivo",
    "tgn:placetype":[
        "aat:300008347"
    ]
},
  "bbox": [],
  "geometry": {"coordinates":[46.8667,-20.8667],"type":"Point"}
}