{
  "id": 7303415,
  "type": "Feature",
  "properties": {
    "tgn:hierarchy":[
        "tgn:7303415",
        "tgn:7002806",
        "tgn:7001158",
        "tgn:1000003",
        "tgn:1000095",
        "tgn:7029392"
    ],
    "tgn:id":7303415,
    "tgn:name":"Navarregadilla",
    "tgn:placetype":[
        "aat:300008347"
    ]
},
  "bbox": [],
  "geometry": {"coordinates":[-5.433333,40.383333],"type":"Point"}
}