{
  "id": 2530819,
  "type": "Feature",
  "properties": {
    "tgn:hierarchy":[
        "tgn:2530819",
        "tgn:1000001",
        "tgn:2002369",
        "tgn:7012149",
        "tgn:7007923",
        "tgn:7029392"
    ],
    "tgn:id":2530819,
    "tgn:name":"Muddy Wagon Hound Creek",
    "tgn:placetype":[
        "aat:300008706"
    ]
},
  "bbox": [],
  "geometry": {"coordinates":[-105.65,42.5667],"type":"Point"}
}