{
  "id": 7412123,
  "type": "Feature",
  "properties": {
    "tgn:hierarchy":[
        "tgn:7412123",
        "tgn:1000001",
        "tgn:7005596",
        "tgn:7005560",
        "tgn:7029392"
    ],
    "tgn:id":7412123,
    "tgn:name:es":"El Puente",
    "tgn:placetype":[
        "aat:300008347"
    ]
},
  "bbox": [],
  "geometry": {"coordinates":[-93.4375,17.8625],"type":"Point"}
}