{
  "id": 2180797,
  "type": "Feature",
  "properties": {
    "tgn:hierarchy":[
        "tgn:2180797",
        "tgn:1000001",
        "tgn:7012149",
        "tgn:2002030",
        "tgn:7007826",
        "tgn:7029392"
    ],
    "tgn:id":2180797,
    "tgn:name":"Blount Mountain",
    "tgn:placetype":[
        "aat:300008798"
    ]
},
  "bbox": [],
  "geometry": {"coordinates":[-98.7833,30.65],"type":"Point"}
}