{
  "id": 2351986,
  "type": "Feature",
  "properties": {
    "tgn:hierarchy":[
        "tgn:2351986",
        "tgn:1000001",
        "tgn:7012149",
        "tgn:7007158",
        "tgn:2000251",
        "tgn:7029392"
    ],
    "tgn:id":2351986,
    "tgn:name":"Globe Hill",
    "tgn:placetype":[
        "aat:300008798"
    ]
},
  "bbox": [],
  "geometry": {"coordinates":[-105.15,38.7333],"type":"Point"}
}