<<<<<<< HEAD
{
  "id": 7365616,
  "type": "Feature",
  "properties": {
    "tgn:hierarchy":[
        "tgn:7365616",
        "tgn:7005581",
        "tgn:1000001",
        "tgn:7005560",
        "tgn:7029392"
    ],
    "tgn:id":7365616,
    "tgn:name":"Fushes, Cerro de",
    "tgn:placetype":[
        "aat:300008777"
    ]
},
  "bbox": [],
  "geometry": {"coordinates":[-107.6,31.55],"type":"Point"}
}
=======
{"geometry":{"type":"Point","coordinates":[-107.600000,31.550000]},"type":"Feature","properties":{"hierarchy":["tgn:7365616","tgn:7005581","tgn:1000001","tgn:7005560","tgn:7029392"],"placetype":["aat:300008777"],"id":7365616,"name:xx":"Fushes, Cerro de"}}
>>>>>>> 03f74aca74312dbeaf24d7e61306dd6a786dc3d0
