{
  "id": 1065366,
  "type": "Feature",
  "properties": {
    "tgn:hierarchy":[
        "tgn:1065366",
        "tgn:7016612",
        "tgn:1000004",
        "tgn:1001362",
        "tgn:7029392"
    ],
    "tgn:id":1065366,
    "tgn:name":"Asmar",
    "tgn:placetype":[
        "aat:300008347"
    ]
},
  "bbox": [],
  "geometry": {"coordinates":[71.4833,35.05],"type":"Point"}
}