{
  "id": 7061847,
  "type": "Feature",
  "properties": {
    "tgn:hierarchy":[
        "tgn:7061847",
        "tgn:7003669",
        "tgn:1000003",
        "tgn:7000084",
        "tgn:7029392"
    ],
    "tgn:id":7061847,
    "tgn:name":"Arracher Bach",
    "tgn:placetype":[
        "aat:300008699"
    ]
},
  "bbox": [],
  "geometry": {"coordinates":[12.433333,49.083333],"type":"Point"}
}