<<<<<<< HEAD
{
  "id": 7053771,
  "type": "Feature",
  "properties": {
    "tgn:hierarchy":[
        "tgn:7053771",
        "tgn:7003132",
        "tgn:1000003",
        "tgn:7008516",
        "tgn:1000080",
        "tgn:7029392"
    ],
    "tgn:id":7053771,
    "tgn:name":"Lusurasco",
    "tgn:placetype":[
        "aat:300008347"
    ]
},
  "bbox": [],
  "geometry": {"coordinates":[9.9,44.883333],"type":"Point"}
}
=======
{"geometry":{"type":"Point","coordinates":[9.900000,44.883333]},"type":"Feature","properties":{"hierarchy":["tgn:7053771","tgn:7003132","tgn:1000003","tgn:7008516","tgn:1000080","tgn:7029392"],"placetype":["aat:300008347"],"id":7053771,"name:xx":"Lusurasco"}}
>>>>>>> 03f74aca74312dbeaf24d7e61306dd6a786dc3d0
