{
  "id": 7055463,
  "type": "Feature",
  "properties": {
    "tgn:hierarchy":[
        "tgn:7055463",
        "tgn:1003460",
        "tgn:1000003",
        "tgn:7009760",
        "tgn:1000080",
        "tgn:7029392"
    ],
    "tgn:id":7055463,
    "tgn:name":"Poggio",
    "tgn:placetype":[
        "aat:300008347"
    ]
},
  "bbox": [],
  "geometry": {"coordinates":[11.55,42.666667],"type":"Point"}
}