{
  "id": 7517358,
  "type": "Feature",
  "properties": {
    "tgn:hierarchy":[
        "tgn:7517358",
        "tgn:1009227",
        "tgn:1000226",
        "tgn:7016822",
        "tgn:1000006",
        "tgn:7029392"
    ],
    "tgn:id":7517358,
    "tgn:name:en":"North Branch Cleddau River",
    "tgn:placetype":[
        "aat:300008699"
    ]
},
  "bbox": [],
  "geometry": {"coordinates":[167.916667,-44.733333],"type":"Point"}
}