{
  "id": 7051045,
  "type": "Feature",
  "properties": {
    "tgn:hierarchy":[
        "tgn:7051045",
        "tgn:7003002",
        "tgn:7003005",
        "tgn:1000003",
        "tgn:1000080",
        "tgn:7029392"
    ],
    "tgn:id":7051045,
    "tgn:name":"Piano",
    "tgn:placetype":[
        "aat:300008347"
    ]
},
  "bbox": [],
  "geometry": {"coordinates":[14.75,40.816667],"type":"Point"}
}