{
  "id": 7546317,
  "type": "Feature",
  "properties": {
    "tgn:hierarchy":[
        "tgn:7546317",
        "tgn:1000004",
        "tgn:7031781",
        "tgn:7000198",
        "tgn:7029392"
    ],
    "tgn:id":7546317,
    "tgn:name:en":"Bajpar",
    "tgn:placetype":[
        "aat:300008347"
    ]
},
  "bbox": [],
  "geometry": {"coordinates":[83.256993,22.600295],"type":"Point"}
}