{
  "id": 2719520,
  "type": "Feature",
  "properties": {
    "tgn:hierarchy":[
        "tgn:2719520",
        "tgn:1000001",
        "tgn:7012149",
        "tgn:1002742",
        "tgn:7007920",
        "tgn:7029392"
    ],
    "tgn:id":2719520,
    "tgn:name":"Three Forks",
    "tgn:placetype":[
        "aat:300008699"
    ]
},
  "bbox": [],
  "geometry": {"coordinates":[-119.7333,48.7667],"type":"Point"}
}