<<<<<<< HEAD
{
  "id": 2335962,
  "type": "Feature",
  "properties": {
    "tgn:hierarchy":[
        "tgn:2335962",
        "tgn:1000001",
        "tgn:7012149",
        "tgn:7007923",
        "tgn:7029392"
    ],
    "tgn:id":2335962,
    "tgn:name":"Fossil Ridge",
    "tgn:placetype":[
        "aat:300266640"
    ]
},
  "bbox": [],
  "geometry": {"coordinates":[-110.7833,41.7667],"type":"Point"}
}
=======
{"geometry":{"type":"Point","coordinates":[-110.783300,41.766700]},"type":"Feature","properties":{"hierarchy":["tgn:2335962","tgn:1000001","tgn:7012149","tgn:7007923","tgn:7029392"],"placetype":["aat:300266640"],"id":2335962,"name:xx":"Fossil Ridge"}}
>>>>>>> 03f74aca74312dbeaf24d7e61306dd6a786dc3d0
