{
  "id": 2192044,
  "type": "Feature",
  "properties": {
    "tgn:hierarchy":[
        "tgn:2192044",
        "tgn:1000001",
        "tgn:7012149",
        "tgn:2002155",
        "tgn:7007919",
        "tgn:7029392"
    ],
    "tgn:id":2192044,
    "tgn:name":"Braggs Corner",
    "tgn:placetype":[
        "aat:300008347"
    ]
},
  "bbox": [],
  "geometry": {"coordinates":[-77.95,38.4667],"type":"Point"}
}