{
  "id": 2264592,
  "type": "Feature",
  "properties": {
    "tgn:hierarchy":[
        "tgn:2264592",
        "tgn:1000001",
        "tgn:7012149",
        "tgn:2000491",
        "tgn:7007250",
        "tgn:7029392"
    ],
    "tgn:id":2264592,
    "tgn:name":"Craddock Creek",
    "tgn:placetype":[
        "aat:300008706"
    ]
},
  "bbox": [],
  "geometry": {"coordinates":[-115.4833,47.2833],"type":"Point"}
}