<<<<<<< HEAD
{
  "id": 2404653,
  "type": "Feature",
  "properties": {
    "tgn:hierarchy":[
        "tgn:2404653",
        "tgn:1000001",
        "tgn:7012149",
        "tgn:2001976",
        "tgn:7007826",
        "tgn:7029392"
    ],
    "tgn:id":2404653,
    "tgn:name":"Huckberry Creek",
    "tgn:placetype":[
        "aat:300008706"
    ]
},
  "bbox": [],
  "geometry": {"coordinates":[-100.85,35.15],"type":"Point"}
}
=======
{"geometry":{"type":"Point","coordinates":[-100.850000,35.150000]},"type":"Feature","properties":{"hierarchy":["tgn:2404653","tgn:1000001","tgn:7012149","tgn:2001976","tgn:7007826","tgn:7029392"],"placetype":["aat:300008706"],"id":2404653,"name:xx":"Huckberry Creek"}}
>>>>>>> 03f74aca74312dbeaf24d7e61306dd6a786dc3d0
