{
  "id": 2404653,
  "type": "Feature",
  "properties": {
    "tgn:hierarchy":[
        "tgn:2404653",
        "tgn:1000001",
        "tgn:7012149",
        "tgn:2001976",
        "tgn:7007826",
        "tgn:7029392"
    ],
    "tgn:id":2404653,
    "tgn:name":"Huckberry Creek",
    "tgn:placetype":[
        "aat:300008706"
    ]
},
  "bbox": [],
  "geometry": {"coordinates":[-100.85,35.15],"type":"Point"}
}