{
  "id": 2300010,
  "type": "Feature",
  "properties": {
    "tgn:hierarchy":[
        "tgn:2300010",
        "tgn:1000001",
        "tgn:1002479",
        "tgn:7012149",
        "tgn:7007240",
        "tgn:7029392"
    ],
    "tgn:id":2300010,
    "tgn:name":"Dug Creek",
    "tgn:placetype":[
        "aat:300008706"
    ]
},
  "bbox": [],
  "geometry": {"coordinates":[-82.3167,27.7167],"type":"Point"}
}