{
  "id": 7118488,
  "type": "Feature",
  "properties": {
    "tgn:hierarchy":[
        "tgn:7118488",
        "tgn:7000096",
        "tgn:1000003",
        "tgn:7000084",
        "tgn:7029392"
    ],
    "tgn:id":7118488,
    "tgn:name":"Petersdorf",
    "tgn:placetype":[
        "aat:300008347"
    ]
},
  "bbox": [],
  "geometry": {"coordinates":[14.083333,52.316667],"type":"Point"}
}