{
  "id": 2165984,
  "type": "Feature",
  "properties": {
    "tgn:hierarchy":[
        "tgn:2165984",
        "tgn:2001610",
        "tgn:1000001",
        "tgn:7012149",
        "tgn:7007706",
        "tgn:7029392"
    ],
    "tgn:id":2165984,
    "tgn:name":"Big Bailey Run",
    "tgn:placetype":[
        "aat:300008699"
    ]
},
  "bbox": [],
  "geometry": {"coordinates":[-82.15,39.45],"type":"Point"}
}