{
  "id": 7381675,
  "type": "Feature",
  "properties": {
    "tgn:hierarchy":[
        "tgn:7381675",
        "tgn:7005586",
        "tgn:1000001",
        "tgn:7005560",
        "tgn:7029392"
    ],
    "tgn:id":7381675,
    "tgn:name":"Malpaso",
    "tgn:placetype":[
        "aat:300008347"
    ]
},
  "bbox": [],
  "geometry": {"coordinates":[-104.133333,20.566667],"type":"Point"}
}