{
  "id": 2540037,
  "type": "Feature",
  "properties": {
    "tgn:hierarchy":[
        "tgn:2540037",
        "tgn:1000001",
        "tgn:2000500",
        "tgn:7012149",
        "tgn:7007251",
        "tgn:7029392"
    ],
    "tgn:id":2540037,
    "tgn:name":"Newby",
    "tgn:placetype":[
        "aat:300008347"
    ]
},
  "bbox": [],
  "geometry": {"coordinates":[-88.3167,39.4333],"type":"Point"}
}