{
  "id": 7119394,
  "type": "Feature",
  "properties": {
    "tgn:hierarchy":[
        "tgn:7119394",
        "tgn:1000003",
        "tgn:7003677",
        "tgn:7000084",
        "tgn:7029392"
    ],
    "tgn:id":7119394,
    "tgn:name":"Peppenhoven",
    "tgn:placetype":[
        "aat:300008347"
    ]
},
  "bbox": [],
  "geometry": {"coordinates":[6.95,50.65],"type":"Point"}
}