{
  "id": 1105229,
  "type": "Feature",
  "properties": {
    "tgn:hierarchy":[
        "tgn:1105229",
        "tgn:1000001",
        "tgn:7012149",
        "tgn:2001660",
        "tgn:7007707",
        "tgn:7029392"
    ],
    "tgn:id":1105229,
    "tgn:name":"King Mountain",
    "tgn:placetype":[
        "aat:300008795"
    ]
},
  "bbox": [],
  "geometry": {"coordinates":[-99.2833,34.8667],"type":"Point"}
}