{
  "id": 2262904,
  "type": "Feature",
  "properties": {
    "tgn:hierarchy":[
        "tgn:2262904",
        "tgn:1000001",
        "tgn:7012149",
        "tgn:7029392"
    ],
    "tgn:id":2262904,
    "tgn:name":"Cowboy Wash",
    "tgn:placetype":[
        "aat:300008761"
    ]
},
  "bbox": [],
  "geometry": {"coordinates":[-108.8333,37.1667],"type":"Point"}
}