{
  "id": 2417724,
  "type": "Feature",
  "properties": {
    "tgn:hierarchy":[
        "tgn:2417724",
        "tgn:1000001",
        "tgn:7012149",
        "tgn:7016056",
        "tgn:7007520",
        "tgn:7029392"
    ],
    "tgn:id":2417724,
    "tgn:name":"Jackson Drain",
    "tgn:placetype":[
        "aat:300008699"
    ]
},
  "bbox": [],
  "geometry": {"coordinates":[-82.7167,43.0833],"type":"Point"}
}