{
  "id": 1092136,
  "type": "Feature",
  "properties": {
    "tgn:hierarchy":[
        "tgn:1092136",
        "tgn:7001242",
        "tgn:1001931",
        "tgn:1000182",
        "tgn:7029392"
    ],
    "tgn:id":1092136,
    "tgn:name":"Kwolla",
    "tgn:placetype":[
        "aat:300008347"
    ]
},
  "bbox": [],
  "geometry": {"coordinates":[9.2833,8.9333],"type":"Point"}
}