{
  "id": 2008969,
  "type": "Feature",
  "properties": {
    "tgn:hierarchy":[
        "tgn:2008969",
        "tgn:1000001",
        "tgn:7016172",
        "tgn:2000119",
        "tgn:7012149",
        "tgn:7029392"
    ],
    "tgn:id":2008969,
    "tgn:name":"Morrilton",
    "tgn:placetype":[
        "aat:300008347"
    ]
},
  "bbox": [],
  "geometry": {"coordinates":[-92.7333,35.15],"type":"Point"}
}