{
  "id": 7568004,
  "type": "Feature",
  "properties": {
    "tgn:hierarchy":[
        "tgn:7568004",
        "tgn:1001828",
        "tgn:1000004",
        "tgn:7000198",
        "tgn:7029392"
    ],
    "tgn:id":7568004,
    "tgn:name:en":"Tulj\u0101pur",
    "tgn:placetype":[
        "aat:300008347"
    ]
},
  "bbox": [],
  "geometry": {"coordinates":[78.284722,17.820278],"type":"Point"}
}