{
  "id": 7240405,
  "type": "Feature",
  "properties": {
    "tgn:hierarchy":[
        "tgn:7240405",
        "tgn:7007877",
        "tgn:1000003",
        "tgn:1000063",
        "tgn:4012014",
        "tgn:7029392"
    ],
    "tgn:id":7240405,
    "tgn:name":"Erquennes",
    "tgn:placetype":[
        "aat:300008347"
    ]
},
  "bbox": [],
  "geometry": {"coordinates":[3.783333,50.35],"type":"Point"}
}