{
  "id": 7517045,
  "type": "Feature",
  "properties": {
    "tgn:hierarchy":[
        "tgn:7517045",
        "tgn:1009227",
        "tgn:7001866",
        "tgn:1000226",
        "tgn:1000006",
        "tgn:7029392"
    ],
    "tgn:id":7517045,
    "tgn:name:en":"Middle Hill",
    "tgn:placetype":[
        "aat:300008795"
    ]
},
  "bbox": [],
  "geometry": {"coordinates":[171.433333,-43.416667],"type":"Point"}
}