<<<<<<< HEAD
{
  "id": 7241026,
  "type": "Feature",
  "properties": {
    "tgn:hierarchy":[
        "tgn:7241026",
        "tgn:7007877",
        "tgn:1000003",
        "tgn:1000063",
        "tgn:4012014",
        "tgn:7029392"
    ],
    "tgn:id":7241026,
    "tgn:name":"Haie-le-Comte, Bois de la",
    "tgn:placetype":[
        "aat:300008863"
    ]
},
  "bbox": [],
  "geometry": {"coordinates":[4.02555,50.53876],"type":"Point"}
}
=======
{"geometry":{"type":"Point","coordinates":[4.025550,50.538760]},"type":"Feature","properties":{"hierarchy":["tgn:7241026","tgn:7007877","tgn:1000003","tgn:1000063","tgn:4012014","tgn:7029392"],"placetype":["aat:300008863"],"id":7241026,"name:xx":"Haie-le-Comte, Bois de la"}}
>>>>>>> 03f74aca74312dbeaf24d7e61306dd6a786dc3d0
