<<<<<<< HEAD
{
  "id": 7376315,
  "type": "Feature",
  "properties": {
    "tgn:hierarchy":[
        "tgn:7376315",
        "tgn:1000001",
        "tgn:7005597",
        "tgn:7005560",
        "tgn:7029392"
    ],
    "tgn:id":7376315,
    "tgn:name":"Rancho La Roca",
    "tgn:placetype":[
        "aat:300000241"
    ]
},
  "bbox": [],
  "geometry": {"coordinates":[-98.633333,25.016667],"type":"Point"}
}
=======
{"geometry":{"type":"Point","coordinates":[-98.633333,25.016667]},"type":"Feature","properties":{"hierarchy":["tgn:7376315","tgn:1000001","tgn:7005597","tgn:7005560","tgn:7029392"],"placetype":["aat:300000241"],"id":7376315,"name:xx":"Rancho La Roca"}}
>>>>>>> 03f74aca74312dbeaf24d7e61306dd6a786dc3d0
