{
  "id": 2569553,
  "type": "Feature",
  "properties": {
    "tgn:hierarchy":[
        "tgn:2569553",
        "tgn:1000001",
        "tgn:2001178",
        "tgn:7012149",
        "tgn:7007523",
        "tgn:7029392"
    ],
    "tgn:id":2569553,
    "tgn:name":"Parrish Hollow",
    "tgn:placetype":[
        "aat:300008761"
    ]
},
  "bbox": [],
  "geometry": {"coordinates":[-92.7167,38.0333],"type":"Point"}
}