{
  "id": 7221085,
  "type": "Feature",
  "properties": {
    "tgn:hierarchy":[
        "tgn:7221085",
        "tgn:7002709",
        "tgn:7002705",
        "tgn:1000003",
        "tgn:1000074",
        "tgn:7029392"
    ],
    "tgn:id":7221085,
    "tgn:name":"V\u00e1ltou, Orm\u00edskos",
    "tgn:placetype":[
        "aat:300132316"
    ]
},
  "bbox": [],
  "geometry": {"coordinates":[20.17,39.526389],"type":"Point"}
}