{
  "id": 7587441,
  "type": "Feature",
  "properties": {
    "tgn:hierarchy":[
        "tgn:7587441",
        "tgn:1000004",
        "tgn:7000198",
        "tgn:7000799",
        "tgn:7029392"
    ],
    "tgn:id":7587441,
    "tgn:name:en":"Veth River",
    "tgn:placetype":[
        "aat:300008699"
    ]
},
  "bbox": [],
  "geometry": {"coordinates":[74.677778,34.183333],"type":"Point"}
}