{
  "id": 2501709,
  "type": "Feature",
  "properties": {
    "tgn:hierarchy":[
        "tgn:2501709",
        "tgn:1000001",
        "tgn:2001785",
        "tgn:7012149",
        "tgn:7007713",
        "tgn:7029392"
    ],
    "tgn:id":2501709,
    "tgn:name":"McIntosh Lake",
    "tgn:placetype":[
        "aat:300006191"
    ]
},
  "bbox": [],
  "geometry": {"coordinates":[-101.3333,45.9167],"type":"Point"}
}