{
  "id": 7442621,
  "type": "Feature",
  "properties": {
    "tgn:hierarchy":[
        "tgn:7442621",
        "tgn:7002444",
        "tgn:1000003",
        "tgn:7008082",
        "tgn:7008591",
        "tgn:7029392"
    ],
    "tgn:id":7442621,
    "tgn:name:en":"Beatrice Oil Field",
    "tgn:placetype":[
        "aat:300000401"
    ]
},
  "bbox": [],
  "geometry": {"coordinates":[-3.083333,58.116667],"type":"Point"}
}