{
  "id": 2155252,
  "type": "Feature",
  "properties": {
    "tgn:hierarchy":[
        "tgn:2155252",
        "tgn:1000001",
        "tgn:7012149",
        "tgn:2000930",
        "tgn:7007515",
        "tgn:7029392"
    ],
    "tgn:id":2155252,
    "tgn:name":"Bear Mountain",
    "tgn:placetype":[
        "aat:300008798"
    ]
},
  "bbox": [],
  "geometry": {"coordinates":[-70.3167,45.3667],"type":"Point"}
}