{
  "id": 7472971,
  "type": "Feature",
  "properties": {
    "tgn:hierarchy":[
        "tgn:7472971",
        "tgn:7488858",
        "tgn:1000004",
        "tgn:1000141",
        "tgn:7029392"
    ],
    "tgn:id":7472971,
    "tgn:name":"Donghu Cun",
    "tgn:placetype":[
        "aat:300387173"
    ]
},
  "bbox": [],
  "geometry": {"coordinates":[120.709537,23.864711],"type":"Point"}
}