<<<<<<< HEAD
{
  "id": 7472971,
  "type": "Feature",
  "properties": {
    "tgn:hierarchy":[
        "tgn:7472971",
        "tgn:7488858",
        "tgn:1000004",
        "tgn:1000141",
        "tgn:7029392"
    ],
    "tgn:id":7472971,
    "tgn:name":"Donghu Cun",
    "tgn:placetype":[
        "aat:300387173"
    ]
},
  "bbox": [],
  "geometry": {"coordinates":[120.709537,23.864711],"type":"Point"}
}
=======
{"geometry":{"type":"Point","coordinates":[120.709537,23.864711]},"type":"Feature","properties":{"hierarchy":["tgn:7472971","tgn:7488858","tgn:1000004","tgn:1000141","tgn:7029392"],"placetype":["aat:300387173"],"id":7472971,"name:xx":"Donghu Cun"}}
>>>>>>> 03f74aca74312dbeaf24d7e61306dd6a786dc3d0
