{
  "id": 7495834,
  "type": "Feature",
  "properties": {
    "tgn:hierarchy":[
        "tgn:7495834",
        "tgn:1000004",
        "tgn:7001013",
        "tgn:1000141",
        "tgn:7029392"
    ],
    "tgn:id":7495834,
    "tgn:name":"Yixing Xi",
    "tgn:placetype":[
        "aat:300008699"
    ]
},
  "bbox": [],
  "geometry": {"coordinates":[121.369725,24.791202],"type":"Point"}
}