{
  "id": 2428815,
  "type": "Feature",
  "properties": {
    "tgn:hierarchy":[
        "tgn:2428815",
        "tgn:1000001",
        "tgn:7012149",
        "tgn:7007158",
        "tgn:2000250",
        "tgn:7029392"
    ],
    "tgn:id":2428815,
    "tgn:name":"Jumbo Mine",
    "tgn:placetype":[
        "aat:300000390"
    ]
},
  "bbox": [],
  "geometry": {"coordinates":[-105.85,39.5833],"type":"Point"}
}