{
  "id": 2304811,
  "type": "Feature",
  "properties": {
    "tgn:hierarchy":[
        "tgn:2304811",
        "tgn:1000001",
        "tgn:7012149",
        "tgn:1002531",
        "tgn:7007251",
        "tgn:7029392"
    ],
    "tgn:id":2304811,
    "tgn:name":"East Branch Big Rock Creek",
    "tgn:placetype":[
        "aat:300008706"
    ]
},
  "bbox": [],
  "geometry": {"coordinates":[-88.5833,41.8667],"type":"Point"}
}