{
  "id": 2642308,
  "type": "Feature",
  "properties": {
    "tgn:hierarchy":[
        "tgn:2642308",
        "tgn:1000001",
        "tgn:7012149",
        "tgn:2001447",
        "tgn:7007566",
        "tgn:7029392"
    ],
    "tgn:id":2642308,
    "tgn:name":"Sand Spring",
    "tgn:placetype":[
        "aat:300008697"
    ]
},
  "bbox": [],
  "geometry": {"coordinates":[-106.0667,32.9833],"type":"Point"}
}