{
  "id": 7326127,
  "type": "Feature",
  "properties": {
    "tgn:hierarchy":[
        "tgn:7326127",
        "tgn:7002820",
        "tgn:7030216",
        "tgn:1000003",
        "tgn:1000095",
        "tgn:7029392"
    ],
    "tgn:id":7326127,
    "tgn:name":"Port-Bou",
    "tgn:placetype":[
        "aat:300008347"
    ]
},
  "bbox": [],
  "geometry": {"coordinates":[3.157673,42.426304],"type":"Point"}
}