<<<<<<< HEAD
{
  "id": 2336037,
  "type": "Feature",
  "properties": {
    "tgn:hierarchy":[
        "tgn:2336037",
        "tgn:1000001",
        "tgn:7012149",
        "tgn:7007256",
        "tgn:7029392"
    ],
    "tgn:id":2336037,
    "tgn:name":"Foster Creek",
    "tgn:placetype":[
        "aat:300008706"
    ]
},
  "bbox": [],
  "geometry": {"coordinates":[-91.2333,30.7],"type":"Point"}
}
=======
{"geometry":{"type":"Point","coordinates":[-91.233300,30.700000]},"type":"Feature","properties":{"hierarchy":["tgn:2336037","tgn:1000001","tgn:7012149","tgn:7007256","tgn:7029392"],"placetype":["aat:300008706"],"id":2336037,"name:xx":"Foster Creek"}}
>>>>>>> 03f74aca74312dbeaf24d7e61306dd6a786dc3d0
