{
  "id": 2679808,
  "type": "Feature",
  "properties": {
    "tgn:hierarchy":[
        "tgn:2679808",
        "tgn:1000001",
        "tgn:7012149",
        "tgn:2001298",
        "tgn:7007524",
        "tgn:7029392"
    ],
    "tgn:id":2679808,
    "tgn:name":"South Fork Rock Creek",
    "tgn:placetype":[
        "aat:300008706"
    ]
},
  "bbox": [],
  "geometry": {"coordinates":[-113.0167,46.35],"type":"Point"}
}