{
  "id": 7221189,
  "type": "Feature",
  "properties": {
    "tgn:hierarchy":[
        "tgn:7221189",
        "tgn:7002750",
        "tgn:7001399",
        "tgn:1000003",
        "tgn:1000074",
        "tgn:7029392"
    ],
    "tgn:id":7221189,
    "tgn:name":"Pig\u00ed",
    "tgn:placetype":[
        "aat:300055621"
    ]
},
  "bbox": [],
  "geometry": {"coordinates":[22.554167,39.772778],"type":"Point"}
}