{
  "id": 7034931,
  "type": "Feature",
  "properties": {
    "tgn:hierarchy":[
        "tgn:7034931",
        "tgn:7003138",
        "tgn:1000003",
        "tgn:7003080",
        "tgn:1000080",
        "tgn:7029392"
    ],
    "tgn:id":7034931,
    "tgn:name":"Casa Martinello",
    "tgn:placetype":[
        "aat:300005433"
    ]
},
  "bbox": [],
  "geometry": {"coordinates":[11.766667,42.15],"type":"Point"}
}