{
  "id": 7565484,
  "type": "Feature",
  "properties": {
    "tgn:hierarchy":[
        "tgn:7565484",
        "tgn:1000004",
        "tgn:7000198",
        "tgn:7016722",
        "tgn:7029392"
    ],
    "tgn:id":7565484,
    "tgn:name:en":"Mau",
    "tgn:placetype":[
        "aat:300008347"
    ]
},
  "bbox": [],
  "geometry": {"coordinates":[79.429588,26.242251],"type":"Point"}
}