{
  "id": 2458257,
  "type": "Feature",
  "properties": {
    "tgn:hierarchy":[
        "tgn:2458257",
        "tgn:1000001",
        "tgn:7012149",
        "tgn:2000927",
        "tgn:7007515",
        "tgn:7029392"
    ],
    "tgn:id":2458257,
    "tgn:name":"Little Mud Brook",
    "tgn:placetype":[
        "aat:300008699"
    ]
},
  "bbox": [],
  "geometry": {"coordinates":[-68.6833,45.7833],"type":"Point"}
}