{
  "id": 7482431,
  "type": "Feature",
  "properties": {
    "tgn:hierarchy":[
        "tgn:7482431",
        "tgn:1000004",
        "tgn:7490934",
        "tgn:1000141",
        "tgn:7029392"
    ],
    "tgn:id":7482431,
    "tgn:name":"Naba Guoxiao",
    "tgn:placetype":[
        "aat:300006495"
    ]
},
  "bbox": [],
  "geometry": {"coordinates":[120.34884,23.068256],"type":"Point"}
}