{
  "id": 7172524,
  "type": "Feature",
  "properties": {
    "tgn:hierarchy":[
        "tgn:7172524",
        "tgn:1000003",
        "tgn:7000094",
        "tgn:7000084",
        "tgn:7029392"
    ],
    "tgn:id":7172524,
    "tgn:name":"Hexen-Berg",
    "tgn:placetype":[
        "aat:300008777"
    ]
},
  "bbox": [],
  "geometry": {"coordinates":[12.783333,53.783333],"type":"Point"}
}