{
  "id": 2756843,
  "type": "Feature",
  "properties": {
    "tgn:hierarchy":[
        "tgn:2756843",
        "tgn:1000001",
        "tgn:7012149",
        "tgn:2000967",
        "tgn:7007520",
        "tgn:7029392"
    ],
    "tgn:id":2756843,
    "tgn:name":"Welnack Drain",
    "tgn:placetype":[
        "aat:300006075"
    ]
},
  "bbox": [],
  "geometry": {"coordinates":[-84.6667,43.65],"type":"Point"}
}