{
  "id": 2535744,
  "type": "Feature",
  "properties": {
    "tgn:hierarchy":[
        "tgn:2535744",
        "tgn:1000001",
        "tgn:7012149",
        "tgn:2001067",
        "tgn:7007521",
        "tgn:7029392"
    ],
    "tgn:id":2535744,
    "tgn:name":"Nashata Point",
    "tgn:placetype":[
        "aat:300008850"
    ]
},
  "bbox": [],
  "geometry": {"coordinates":[-92.9667,48.4667],"type":"Point"}
}