{
  "id": 7213709,
  "type": "Feature",
  "properties": {
    "tgn:hierarchy":[
        "tgn:7213709",
        "tgn:1000003",
        "tgn:7003676",
        "tgn:7000084",
        "tgn:7029392"
    ],
    "tgn:id":7213709,
    "tgn:name":"Blumenkamp",
    "tgn:placetype":[
        "aat:300000206"
    ]
},
  "bbox": [],
  "geometry": {"coordinates":[8.233333,52.283333],"type":"Point"}
}