{
  "id": 7159252,
  "type": "Feature",
  "properties": {
    "tgn:hierarchy":[
        "tgn:7159252",
        "tgn:7003669",
        "tgn:1000003",
        "tgn:7000084",
        "tgn:7029392"
    ],
    "tgn:id":7159252,
    "tgn:name":"H\u00f6fles Berg",
    "tgn:placetype":[
        "aat:300008777"
    ]
},
  "bbox": [],
  "geometry": {"coordinates":[12.333333,49.466667],"type":"Point"}
}