{
  "id": 7209534,
  "type": "Feature",
  "properties": {
    "tgn:hierarchy":[
        "tgn:7209534",
        "tgn:1000003",
        "tgn:7003676",
        "tgn:7000084",
        "tgn:7029392"
    ],
    "tgn:id":7209534,
    "tgn:name":"Benstreek",
    "tgn:placetype":[
        "aat:300000206"
    ]
},
  "bbox": [],
  "geometry": {"coordinates":[7.85,53.383333],"type":"Point"}
}