{
  "id": 7180226,
  "type": "Feature",
  "properties": {
    "tgn:hierarchy":[
        "tgn:7180226",
        "tgn:7003669",
        "tgn:1000003",
        "tgn:7000084",
        "tgn:7029392"
    ],
    "tgn:id":7180226,
    "tgn:name":"Fuchs-B\u00fchel",
    "tgn:placetype":[
        "aat:300008777"
    ]
},
  "bbox": [],
  "geometry": {"coordinates":[11.983333,47.916667],"type":"Point"}
}