{
  "id": 7384701,
  "type": "Feature",
  "properties": {
    "tgn:hierarchy":[
        "tgn:7384701",
        "tgn:1000001",
        "tgn:7005595",
        "tgn:7005560",
        "tgn:7029392"
    ],
    "tgn:id":7384701,
    "tgn:name":"Ojitos",
    "tgn:placetype":[
        "aat:300008347"
    ]
},
  "bbox": [],
  "geometry": {"coordinates":[-108.233333,25.95],"type":"Point"}
}