{
  "id": 2233691,
  "type": "Feature",
  "properties": {
    "tgn:hierarchy":[
        "tgn:2233691",
        "tgn:1000001",
        "tgn:7012149",
        "tgn:1002505",
        "tgn:7007920",
        "tgn:7029392"
    ],
    "tgn:id":2233691,
    "tgn:name":"Chase Lake",
    "tgn:placetype":[
        "aat:300008680"
    ]
},
  "bbox": [],
  "geometry": {"coordinates":[-122.55,48.0333],"type":"Point"}
}