{
  "id": 7565598,
  "type": "Feature",
  "properties": {
    "tgn:hierarchy":[
        "tgn:7565598",
        "tgn:1000004",
        "tgn:7000198",
        "tgn:7016788",
        "tgn:7029392"
    ],
    "tgn:id":7565598,
    "tgn:name:en":"Chhila N\u0101di",
    "tgn:placetype":[
        "aat:300008347"
    ]
},
  "bbox": [],
  "geometry": {"coordinates":[71.662022,27.308275],"type":"Point"}
}