<<<<<<< HEAD
{
  "id": 2252296,
  "type": "Feature",
  "properties": {
    "tgn:hierarchy":[
        "tgn:2252296",
        "tgn:1000001",
        "tgn:7012149",
        "tgn:1002945",
        "tgn:7007710",
        "tgn:7029392"
    ],
    "tgn:id":2252296,
    "tgn:name":"Confer Sag",
    "tgn:placetype":[
        "aat:300008761"
    ]
},
  "bbox": [],
  "geometry": {"coordinates":[-77.4167,41.7667],"type":"Point"}
}
=======
{"geometry":{"type":"Point","coordinates":[-77.416700,41.766700]},"type":"Feature","properties":{"hierarchy":["tgn:2252296","tgn:1000001","tgn:7012149","tgn:1002945","tgn:7007710","tgn:7029392"],"placetype":["aat:300008761"],"id":2252296,"name:xx":"Confer Sag"}}
>>>>>>> 03f74aca74312dbeaf24d7e61306dd6a786dc3d0
