{
  "id": 7377707,
  "type": "Feature",
  "properties": {
    "tgn:hierarchy":[
        "tgn:7377707",
        "tgn:7005581",
        "tgn:1000001",
        "tgn:7005560",
        "tgn:7029392"
    ],
    "tgn:id":7377707,
    "tgn:name":"La Soledad",
    "tgn:placetype":[
        "aat:300008347"
    ]
},
  "bbox": [],
  "geometry": {"coordinates":[-103.85,26.916667],"type":"Point"}
}