{
  "id": 2519985,
  "type": "Feature",
  "properties": {
    "tgn:hierarchy":[
        "tgn:2519985",
        "tgn:1000001",
        "tgn:7012149",
        "tgn:2001158",
        "tgn:7007522",
        "tgn:7029392"
    ],
    "tgn:id":2519985,
    "tgn:name":"Molino",
    "tgn:placetype":[
        "aat:300008347"
    ]
},
  "bbox": [],
  "geometry": {"coordinates":[-88.8833,34.5667],"type":"Point"}
}