{
  "id": 7364256,
  "type": "Feature",
  "properties": {
    "tgn:hierarchy":[
        "tgn:7364256",
        "tgn:1000001",
        "tgn:7005596",
        "tgn:7005560",
        "tgn:7029392"
    ],
    "tgn:id":7364256,
    "tgn:name":"El Hormiguero",
    "tgn:placetype":[
        "aat:300008347"
    ]
},
  "bbox": [],
  "geometry": {"coordinates":[-91.916667,17.883333],"type":"Point"}
}