{
  "id": 7528443,
  "type": "Feature",
  "properties": {
    "tgn:hierarchy":[
        "tgn:7528443",
        "tgn:7001242",
        "tgn:7016833",
        "tgn:7029392"
    ],
    "tgn:id":7528443,
    "tgn:name:en":"Sh\u016bshat al Kh\u0101dim",
    "tgn:placetype":[
        "aat:300008777"
    ]
},
  "bbox": [],
  "geometry": {"coordinates":[27.780422,28.599022],"type":"Point"}
}