{
  "id": 7044310,
  "type": "Feature",
  "properties": {
    "tgn:hierarchy":[
        "tgn:7044310",
        "tgn:1000003",
        "tgn:7003141",
        "tgn:7003236",
        "tgn:1000080",
        "tgn:7029392"
    ],
    "tgn:id":7044310,
    "tgn:name":"Costarainera",
    "tgn:placetype":[
        "aat:300008347"
    ]
},
  "bbox": [],
  "geometry": {"coordinates":[7.933333,43.85],"type":"Point"}
}