{
  "id": 2781707,
  "type": "Feature",
  "properties": {
    "tgn:hierarchy":[
        "tgn:2781707",
        "tgn:1000001",
        "tgn:2001417",
        "tgn:7012149",
        "tgn:7007526",
        "tgn:7029392"
    ],
    "tgn:id":2781707,
    "tgn:name":"Woodruffs",
    "tgn:placetype":[
        "aat:300008347"
    ]
},
  "bbox": [],
  "geometry": {"coordinates":[-118.1833,38.9167],"type":"Point"}
}