{
  "id": 2748799,
  "type": "Feature",
  "properties": {
    "tgn:hierarchy":[
        "tgn:2748799",
        "tgn:1000001",
        "tgn:7012149",
        "tgn:2001724",
        "tgn:7007710",
        "tgn:7029392"
    ],
    "tgn:id":2748799,
    "tgn:name":"Walkers Run",
    "tgn:placetype":[
        "aat:300008699"
    ]
},
  "bbox": [],
  "geometry": {"coordinates":[-80.2167,39.9833],"type":"Point"}
}