{
  "id": 2354606,
  "type": "Feature",
  "properties": {
    "tgn:hierarchy":[
        "tgn:2354606",
        "tgn:1000001",
        "tgn:7006451",
        "tgn:7012149",
        "tgn:2000101",
        "tgn:7029392"
    ],
    "tgn:id":2354606,
    "tgn:name":"Gonzales Pass Canyon",
    "tgn:placetype":[
        "aat:300008761"
    ]
},
  "bbox": [],
  "geometry": {"coordinates":[-111.2167,33.2667],"type":"Point"}
}