{
  "id": 1065945,
  "type": "Feature",
  "properties": {
    "tgn:hierarchy":[
        "tgn:1065945",
        "tgn:1000004",
        "tgn:7000191",
        "tgn:1000105",
        "tgn:7029392"
    ],
    "tgn:id":1065945,
    "tgn:name":"Sir\u0101jganj",
    "tgn:placetype":[
        "aat:300008347",
        "aat:300387316",
        "aat:300008375",
        "aat:300120599"
    ]
},
  "bbox": [],
  "geometry": {"coordinates":[89.7167,24.45],"type":"Point"}
}