<<<<<<< HEAD
{
  "id": 2150813,
  "type": "Feature",
  "properties": {
    "tgn:hierarchy":[
        "tgn:2150813",
        "tgn:1000001",
        "tgn:2000952",
        "tgn:7012149",
        "tgn:7007520",
        "tgn:7029392"
    ],
    "tgn:id":2150813,
    "tgn:name":"Bass Lake",
    "tgn:placetype":[
        "aat:300008680"
    ]
},
  "bbox": [],
  "geometry": {"coordinates":[-83.55,45.9167],"type":"Point"}
}
=======
{"geometry":{"type":"Point","coordinates":[-83.550000,45.916700]},"type":"Feature","properties":{"hierarchy":["tgn:2150813","tgn:1000001","tgn:2000952","tgn:7012149","tgn:7007520","tgn:7029392"],"placetype":["aat:300008680"],"id":2150813,"name:xx":"Bass Lake"}}
>>>>>>> 03f74aca74312dbeaf24d7e61306dd6a786dc3d0
