{
  "id": 2150813,
  "type": "Feature",
  "properties": {
    "tgn:hierarchy":[
        "tgn:2150813",
        "tgn:1000001",
        "tgn:2000952",
        "tgn:7012149",
        "tgn:7007520",
        "tgn:7029392"
    ],
    "tgn:id":2150813,
    "tgn:name":"Bass Lake",
    "tgn:placetype":[
        "aat:300008680"
    ]
},
  "bbox": [],
  "geometry": {"coordinates":[-83.55,45.9167],"type":"Point"}
}