{
  "id": 7542960,
  "type": "Feature",
  "properties": {
    "tgn:hierarchy":[
        "tgn:7542960",
        "tgn:7001242",
        "tgn:7016833",
        "tgn:1001113",
        "tgn:7029392"
    ],
    "tgn:id":7542960,
    "tgn:name:en":"Qaryat al Azh\u0101r",
    "tgn:placetype":[
        "aat:300008347"
    ]
},
  "bbox": [],
  "geometry": {"coordinates":[32.064806,30.989032],"type":"Point"}
}