<<<<<<< HEAD
{
  "id": 2338965,
  "type": "Feature",
  "properties": {
    "tgn:hierarchy":[
        "tgn:2338965",
        "tgn:1000001",
        "tgn:7012149",
        "tgn:2002040",
        "tgn:7007826",
        "tgn:7029392"
    ],
    "tgn:id":2338965,
    "tgn:name":"Franklin Draw",
    "tgn:placetype":[
        "aat:300008761"
    ]
},
  "bbox": [],
  "geometry": {"coordinates":[-99.6167,30.7833],"type":"Point"}
}
=======
{"geometry":{"type":"Point","coordinates":[-99.616700,30.783300]},"type":"Feature","properties":{"hierarchy":["tgn:2338965","tgn:1000001","tgn:7012149","tgn:2002040","tgn:7007826","tgn:7029392"],"placetype":["aat:300008761"],"id":2338965,"name:xx":"Franklin Draw"}}
>>>>>>> 03f74aca74312dbeaf24d7e61306dd6a786dc3d0
