{
  "id": 7415916,
  "type": "Feature",
  "properties": {
    "tgn:hierarchy":[
        "tgn:7415916",
        "tgn:1000001",
        "tgn:7005591",
        "tgn:7005560",
        "tgn:7029392"
    ],
    "tgn:id":7415916,
    "tgn:name:es":"Estaci\u00f3n Mocote",
    "tgn:placetype":[
        "aat:300007783"
    ]
},
  "bbox": [],
  "geometry": {"coordinates":[-96.796667,17.171667],"type":"Point"}
}