{
  "id": 1137578,
  "type": "Feature",
  "properties": {
    "tgn:hierarchy":[
        "tgn:1137578",
        "tgn:1000004",
        "tgn:1003408",
        "tgn:7018214",
        "tgn:7002435",
        "tgn:7029392"
    ],
    "tgn:id":1137578,
    "tgn:name":"Kalininsk",
    "tgn:placetype":[
        "aat:300008347"
    ]
},
  "bbox": [],
  "geometry": {"coordinates":[44.4833,51.5333],"type":"Point"}
}