{
  "id": 7009836,
  "type": "Feature",
  "properties": {
    "tgn:hierarchy":[
        "tgn:7009836",
        "tgn:1000003",
        "tgn:7003774",
        "tgn:1000097",
        "tgn:7029392"
    ],
    "tgn:id":7009836,
    "tgn:name":"Lule\u00e5",
    "tgn:placetype":[
        "aat:300008347",
        "aat:300008416",
        "aat:300008389",
        "aat:300264742",
        "aat:300387512",
        "aat:300387235",
        "aat:300120599"
    ]
},
  "bbox": [],
  "geometry": {"coordinates":[22.1667,65.5667],"type":"Point"}
}