{
  "id": 7572142,
  "type": "Feature",
  "properties": {
    "tgn:hierarchy":[
        "tgn:7572142",
        "tgn:1000004",
        "tgn:7000198",
        "tgn:1001977",
        "tgn:7029392"
    ],
    "tgn:id":7572142,
    "tgn:name:en":"H\u012br\u0101pur",
    "tgn:placetype":[
        "aat:300008347"
    ]
},
  "bbox": [],
  "geometry": {"coordinates":[86.935471,23.658521],"type":"Point"}
}