{
  "id": 7175700,
  "type": "Feature",
  "properties": {
    "tgn:hierarchy":[
        "tgn:7175700",
        "tgn:1000003",
        "tgn:7003676",
        "tgn:7000084",
        "tgn:7029392"
    ],
    "tgn:id":7175700,
    "tgn:name":"Gro\u00dfenv\u00f6rde",
    "tgn:placetype":[
        "aat:300008347"
    ]
},
  "bbox": [],
  "geometry": {"coordinates":[8.883333,52.433333],"type":"Point"}
}