{
  "id": 2322506,
  "type": "Feature",
  "properties": {
    "tgn:hierarchy":[
        "tgn:2322506",
        "tgn:7006450",
        "tgn:1000001",
        "tgn:2124053",
        "tgn:7012149",
        "tgn:7029392"
    ],
    "tgn:id":2322506,
    "tgn:name":"Falls Creek",
    "tgn:placetype":[
        "aat:300008706"
    ]
},
  "bbox": [],
  "geometry": {"coordinates":[-151.0167,62.55],"type":"Point"}
}