<<<<<<< HEAD
{
  "id": 2157014,
  "type": "Feature",
  "properties": {
    "tgn:hierarchy":[
        "tgn:2157014",
        "tgn:1000001",
        "tgn:7012149",
        "tgn:2000232",
        "tgn:7007158",
        "tgn:7029392"
    ],
    "tgn:id":2157014,
    "tgn:name":"Beaver Basin",
    "tgn:placetype":[
        "aat:300386845"
    ]
},
  "bbox": [],
  "geometry": {"coordinates":[-108.95,40.9333],"type":"Point"}
}
=======
{"geometry":{"type":"Point","coordinates":[-108.950000,40.933300]},"type":"Feature","properties":{"hierarchy":["tgn:2157014","tgn:1000001","tgn:7012149","tgn:2000232","tgn:7007158","tgn:7029392"],"placetype":["aat:300386845"],"id":2157014,"name:xx":"Beaver Basin"}}
>>>>>>> 03f74aca74312dbeaf24d7e61306dd6a786dc3d0
