{
  "id": 2011031,
  "type": "Feature",
  "properties": {
    "tgn:hierarchy":[
        "tgn:2011031",
        "tgn:1000001",
        "tgn:7012149",
        "tgn:7007157",
        "tgn:1002901",
        "tgn:7029392"
    ],
    "tgn:id":2011031,
    "tgn:name":"Denverton",
    "tgn:placetype":[
        "aat:300008347",
        "aat:300387210"
    ]
},
  "bbox": [],
  "geometry": {"coordinates":[-121.8833,38.2167],"type":"Point"}
}