{
  "id": 7496141,
  "type": "Feature",
  "properties": {
    "tgn:hierarchy":[
        "tgn:7496141",
        "tgn:7487020",
        "tgn:1000004",
        "tgn:1000141",
        "tgn:7029392"
    ],
    "tgn:id":7496141,
    "tgn:name":"Meizikeng",
    "tgn:placetype":[
        "aat:300008347"
    ]
},
  "bbox": [],
  "geometry": {"coordinates":[120.739209,24.516358],"type":"Point"}
}