{
  "id": 2588052,
  "type": "Feature",
  "properties": {
    "tgn:hierarchy":[
        "tgn:2588052",
        "tgn:1000001",
        "tgn:1002316",
        "tgn:7012149",
        "tgn:7007922",
        "tgn:7029392"
    ],
    "tgn:id":2588052,
    "tgn:name":"Pleasure Valley",
    "tgn:placetype":[
        "aat:300008761"
    ]
},
  "bbox": [],
  "geometry": {"coordinates":[-89.8167,43.0167],"type":"Point"}
}