<<<<<<< HEAD
{
  "id": 7022559,
  "type": "Feature",
  "properties": {
    "tgn:hierarchy":[
        "tgn:7022559",
        "tgn:1000001",
        "tgn:7012149",
        "tgn:7029392"
    ],
    "tgn:id":7022559,
    "tgn:name":"Yuma Main Canal",
    "tgn:placetype":[
        "aat:300006075"
    ]
},
  "bbox": [],
  "geometry": {"coordinates":[-114.6167,32.7167],"type":"Point"}
}
=======
{"geometry":{"type":"Point","coordinates":[-114.616700,32.716700]},"type":"Feature","properties":{"hierarchy":["tgn:7022559","tgn:1000001","tgn:7012149","tgn:7029392"],"placetype":["aat:300006075"],"id":7022559,"name:xx":"Yuma Main Canal"}}
>>>>>>> 03f74aca74312dbeaf24d7e61306dd6a786dc3d0
