{
  "id": 7022559,
  "type": "Feature",
  "properties": {
    "tgn:hierarchy":[
        "tgn:7022559",
        "tgn:1000001",
        "tgn:7012149",
        "tgn:7029392"
    ],
    "tgn:id":7022559,
    "tgn:name":"Yuma Main Canal",
    "tgn:placetype":[
        "aat:300006075"
    ]
},
  "bbox": [],
  "geometry": {"coordinates":[-114.6167,32.7167],"type":"Point"}
}