<<<<<<< HEAD
{
  "id": 2335271,
  "type": "Feature",
  "properties": {
    "tgn:hierarchy":[
        "tgn:2335271",
        "tgn:2000454",
        "tgn:1000001",
        "tgn:7012149",
        "tgn:7007250",
        "tgn:7029392"
    ],
    "tgn:id":2335271,
    "tgn:name":"Fort Hall Canyon",
    "tgn:placetype":[
        "aat:300008761"
    ]
},
  "bbox": [],
  "geometry": {"coordinates":[-112.35,42.75],"type":"Point"}
}
=======
{"geometry":{"type":"Point","coordinates":[-112.350000,42.750000]},"type":"Feature","properties":{"hierarchy":["tgn:2335271","tgn:2000454","tgn:1000001","tgn:7012149","tgn:7007250","tgn:7029392"],"placetype":["aat:300008761"],"id":2335271,"name:xx":"Fort Hall Canyon"}}
>>>>>>> 03f74aca74312dbeaf24d7e61306dd6a786dc3d0
