{
  "id": 2664807,
  "type": "Feature",
  "properties": {
    "tgn:hierarchy":[
        "tgn:2664807",
        "tgn:1000001",
        "tgn:7012149",
        "tgn:2002272",
        "tgn:7013961",
        "tgn:7029392"
    ],
    "tgn:id":2664807,
    "tgn:name":"Simon Creek",
    "tgn:placetype":[
        "aat:300008706"
    ]
},
  "bbox": [],
  "geometry": {"coordinates":[-82.05,38.2833],"type":"Point"}
}