{
  "id": 7386531,
  "type": "Feature",
  "properties": {
    "tgn:hierarchy":[
        "tgn:7386531",
        "tgn:1000001",
        "tgn:1001906",
        "tgn:7005560",
        "tgn:7029392"
    ],
    "tgn:id":7386531,
    "tgn:name":"Platanitos",
    "tgn:placetype":[
        "aat:300008347"
    ]
},
  "bbox": [],
  "geometry": {"coordinates":[-105.233333,21.35],"type":"Point"}
}