<<<<<<< HEAD
{
  "id": 2254877,
  "type": "Feature",
  "properties": {
    "tgn:hierarchy":[
        "tgn:2254877",
        "tgn:1000001",
        "tgn:7012149",
        "tgn:2002274",
        "tgn:7013961",
        "tgn:7029392"
    ],
    "tgn:id":2254877,
    "tgn:name":"Coontree Branch",
    "tgn:placetype":[
        "aat:300008699"
    ]
},
  "bbox": [],
  "geometry": {"coordinates":[-81.6667,37.4],"type":"Point"}
}
=======
{"geometry":{"type":"Point","coordinates":[-81.666700,37.400000]},"type":"Feature","properties":{"hierarchy":["tgn:2254877","tgn:1000001","tgn:7012149","tgn:2002274","tgn:7013961","tgn:7029392"],"placetype":["aat:300008699"],"id":2254877,"name:xx":"Coontree Branch"}}
>>>>>>> 03f74aca74312dbeaf24d7e61306dd6a786dc3d0
