{
  "id": 7454965,
  "type": "Feature",
  "properties": {
    "tgn:hierarchy":[
        "tgn:7454965",
        "tgn:7019094",
        "tgn:7002444",
        "tgn:1000003",
        "tgn:7008591",
        "tgn:7029392"
    ],
    "tgn:id":7454965,
    "tgn:name:en":"Bruichladdich",
    "tgn:placetype":[
        "aat:300008347"
    ]
},
  "bbox": [],
  "geometry": {"coordinates":[-6.366667,55.766667],"type":"Point"}
}