{
  "id": 2765653,
  "type": "Feature",
  "properties": {
    "tgn:hierarchy":[
        "tgn:2765653",
        "tgn:1000001",
        "tgn:7016172",
        "tgn:7012149",
        "tgn:2000163",
        "tgn:7029392"
    ],
    "tgn:id":2765653,
    "tgn:name":"White Creek",
    "tgn:placetype":[
        "aat:300008706"
    ]
},
  "bbox": [],
  "geometry": {"coordinates":[-91.6667,34.9667],"type":"Point"}
}