{
  "id": 7245194,
  "type": "Feature",
  "properties": {
    "tgn:hierarchy":[
        "tgn:7245194",
        "tgn:7003456",
        "tgn:1000003",
        "tgn:1000063",
        "tgn:7018236",
        "tgn:7029392"
    ],
    "tgn:id":7245194,
    "tgn:name":"Achterheide",
    "tgn:placetype":[
        "aat:300008347"
    ]
},
  "bbox": [],
  "geometry": {"coordinates":[4.698202,51.044677],"type":"Point"}
}