{
  "id": 2046988,
  "type": "Feature",
  "properties": {
    "tgn:hierarchy":[
        "tgn:2046988",
        "tgn:2000934",
        "tgn:1000001",
        "tgn:7012149",
        "tgn:7007516",
        "tgn:7029392"
    ],
    "tgn:id":2046988,
    "tgn:name":"Ellerslie",
    "tgn:placetype":[
        "aat:300008347"
    ]
},
  "bbox": [],
  "geometry": {"coordinates":[-78.7667,39.7167],"type":"Point"}
}