{
  "id": 2351029,
  "type": "Feature",
  "properties": {
    "tgn:hierarchy":[
        "tgn:2351029",
        "tgn:7013349",
        "tgn:1000001",
        "tgn:7012149",
        "tgn:7007708",
        "tgn:7029392"
    ],
    "tgn:id":2351029,
    "tgn:name":"Glasgow Gulch",
    "tgn:placetype":[
        "aat:300008761"
    ]
},
  "bbox": [],
  "geometry": {"coordinates":[-117.8167,44.5333],"type":"Point"}
}