{
  "id": 7421016,
  "type": "Feature",
  "properties": {
    "tgn:hierarchy":[
        "tgn:7421016",
        "tgn:1000001",
        "tgn:7005589",
        "tgn:7005560",
        "tgn:7029392"
    ],
    "tgn:id":7421016,
    "tgn:name:es":"El Sabarado",
    "tgn:placetype":[
        "aat:300008347"
    ]
},
  "bbox": [],
  "geometry": {"coordinates":[-99.884722,25.501944],"type":"Point"}
}