{
  "id": 2221209,
  "type": "Feature",
  "properties": {
    "tgn:hierarchy":[
        "tgn:2221209",
        "tgn:1000001",
        "tgn:2000108",
        "tgn:7016172",
        "tgn:7012149",
        "tgn:7029392"
    ],
    "tgn:id":2221209,
    "tgn:name":"Carden Branch",
    "tgn:placetype":[
        "aat:300008699"
    ]
},
  "bbox": [],
  "geometry": {"coordinates":[-94.0667,36.45],"type":"Point"}
}