{
  "id": 7394309,
  "type": "Feature",
  "properties": {
    "tgn:hierarchy":[
        "tgn:7394309",
        "tgn:7005583",
        "tgn:1000001",
        "tgn:7005560",
        "tgn:7029392"
    ],
    "tgn:id":7394309,
    "tgn:name":"Rancho San Jos\u00e9",
    "tgn:placetype":[
        "aat:300000241"
    ]
},
  "bbox": [],
  "geometry": {"coordinates":[-105.533333,26.433333],"type":"Point"}
}