{
  "id": 2352061,
  "type": "Feature",
  "properties": {
    "tgn:hierarchy":[
        "tgn:2352061",
        "tgn:1000001",
        "tgn:2002102",
        "tgn:7012149",
        "tgn:7007827",
        "tgn:7029392"
    ],
    "tgn:id":2352061,
    "tgn:name":"Glory Hole",
    "tgn:placetype":[
        "aat:300008680"
    ]
},
  "bbox": [],
  "geometry": {"coordinates":[-112.15,41.4833],"type":"Point"}
}