<<<<<<< HEAD
{
  "id": 2760556,
  "type": "Feature",
  "properties": {
    "tgn:hierarchy":[
        "tgn:2760556",
        "tgn:1000001",
        "tgn:7012149",
        "tgn:2002119",
        "tgn:7007827",
        "tgn:7029392"
    ],
    "tgn:id":2760556,
    "tgn:name":"West Fork Twin Canyon",
    "tgn:placetype":[
        "aat:300008761"
    ]
},
  "bbox": [],
  "geometry": {"coordinates":[-109.9167,38.1167],"type":"Point"}
}
=======
{"geometry":{"type":"Point","coordinates":[-109.916700,38.116700]},"type":"Feature","properties":{"hierarchy":["tgn:2760556","tgn:1000001","tgn:7012149","tgn:2002119","tgn:7007827","tgn:7029392"],"placetype":["aat:300008761"],"id":2760556,"name:xx":"West Fork Twin Canyon"}}
>>>>>>> 03f74aca74312dbeaf24d7e61306dd6a786dc3d0
