{
  "id": 7452592,
  "type": "Feature",
  "properties": {
    "tgn:hierarchy":[
        "tgn:7452592",
        "tgn:7002445",
        "tgn:1000003",
        "tgn:7008134",
        "tgn:7008591",
        "tgn:7029392"
    ],
    "tgn:id":7452592,
    "tgn:name:en":"Goodwood House",
    "tgn:placetype":[
        "aat:300387502"
    ]
},
  "bbox": [],
  "geometry": {"coordinates":[-0.733333,50.866667],"type":"Point"}
}