<<<<<<< HEAD
{
  "id": 2409290,
  "type": "Feature",
  "properties": {
    "tgn:hierarchy":[
        "tgn:2409290",
        "tgn:1000001",
        "tgn:7012149",
        "tgn:1002545",
        "tgn:7007157",
        "tgn:7029392"
    ],
    "tgn:id":2409290,
    "tgn:name":"Iconoclast Mine",
    "tgn:placetype":[
        "aat:300000390"
    ]
},
  "bbox": [],
  "geometry": {"coordinates":[-118.3667,35.5333],"type":"Point"}
}
=======
{"geometry":{"type":"Point","coordinates":[-118.366700,35.533300]},"type":"Feature","properties":{"hierarchy":["tgn:2409290","tgn:1000001","tgn:7012149","tgn:1002545","tgn:7007157","tgn:7029392"],"placetype":["aat:300000390"],"id":2409290,"name:xx":"Iconoclast Mine"}}
>>>>>>> 03f74aca74312dbeaf24d7e61306dd6a786dc3d0
