<<<<<<< HEAD
{
  "id": 7170233,
  "type": "Feature",
  "properties": {
    "tgn:hierarchy":[
        "tgn:7170233",
        "tgn:1000003",
        "tgn:7003688",
        "tgn:7000084",
        "tgn:7029392"
    ],
    "tgn:id":7170233,
    "tgn:name":"Hetlingerdeich",
    "tgn:placetype":[
        "aat:300000206"
    ]
},
  "bbox": [],
  "geometry": {"coordinates":[9.616667,53.633333],"type":"Point"}
}
=======
{"geometry":{"type":"Point","coordinates":[9.616667,53.633333]},"type":"Feature","properties":{"hierarchy":["tgn:7170233","tgn:1000003","tgn:7003688","tgn:7000084","tgn:7029392"],"placetype":["aat:300000206"],"id":7170233,"name:xx":"Hetlingerdeich"}}
>>>>>>> 03f74aca74312dbeaf24d7e61306dd6a786dc3d0
