{
  "id": 7573722,
  "type": "Feature",
  "properties": {
    "tgn:hierarchy":[
        "tgn:7573722",
        "tgn:1000004",
        "tgn:1001869",
        "tgn:7000198",
        "tgn:7029392"
    ],
    "tgn:id":7573722,
    "tgn:name:en":"Kadod",
    "tgn:placetype":[
        "aat:300008347"
    ]
},
  "bbox": [],
  "geometry": {"coordinates":[73.233333,21.216667],"type":"Point"}
}