{
  "id": 7568769,
  "type": "Feature",
  "properties": {
    "tgn:hierarchy":[
        "tgn:7568769",
        "tgn:1000004",
        "tgn:7000198",
        "tgn:7016722",
        "tgn:7029392"
    ],
    "tgn:id":7568769,
    "tgn:name:en":"Mah\u0101batpur",
    "tgn:placetype":[
        "aat:300008347"
    ]
},
  "bbox": [],
  "geometry": {"coordinates":[77.385982,29.514628],"type":"Point"}
}