{
  "id": 2014907,
  "type": "Feature",
  "properties": {
    "tgn:hierarchy":[
        "tgn:2014907",
        "tgn:1000001",
        "tgn:7012149",
        "tgn:1002392",
        "tgn:7007157",
        "tgn:7029392"
    ],
    "tgn:id":2014907,
    "tgn:name":"Westhaven",
    "tgn:placetype":[
        "aat:300008347",
        "aat:300387210"
    ]
},
  "bbox": [],
  "geometry": {"coordinates":[-119.9833,36.2167],"type":"Point"}
}