{
  "id": 2487016,
  "type": "Feature",
  "properties": {
    "tgn:hierarchy":[
        "tgn:2487016",
        "tgn:1000001",
        "tgn:2001411",
        "tgn:7012149",
        "tgn:7007526",
        "tgn:7029392"
    ],
    "tgn:id":2487016,
    "tgn:name":"Lee Peak",
    "tgn:placetype":[
        "aat:300008798"
    ]
},
  "bbox": [],
  "geometry": {"coordinates":[-115.4833,40.6167],"type":"Point"}
}