<<<<<<< HEAD
{
  "id": 2760611,
  "type": "Feature",
  "properties": {
    "tgn:hierarchy":[
        "tgn:2760611",
        "tgn:1000001",
        "tgn:7012149",
        "tgn:1002691",
        "tgn:7007826",
        "tgn:7029392"
    ],
    "tgn:id":2760611,
    "tgn:name":"West Fork White Oak Creek",
    "tgn:placetype":[
        "aat:300008706"
    ]
},
  "bbox": [],
  "geometry": {"coordinates":[-95.5,30.3833],"type":"Point"}
}
=======
{"geometry":{"type":"Point","coordinates":[-95.500000,30.383300]},"type":"Feature","properties":{"hierarchy":["tgn:2760611","tgn:1000001","tgn:7012149","tgn:1002691","tgn:7007826","tgn:7029392"],"placetype":["aat:300008706"],"id":2760611,"name:xx":"West Fork White Oak Creek"}}
>>>>>>> 03f74aca74312dbeaf24d7e61306dd6a786dc3d0
