{
  "id": 7396373,
  "type": "Feature",
  "properties": {
    "tgn:hierarchy":[
        "tgn:7396373",
        "tgn:7005585",
        "tgn:1000001",
        "tgn:7005560",
        "tgn:7029392"
    ],
    "tgn:id":7396373,
    "tgn:name":"Santa Rita",
    "tgn:placetype":[
        "aat:300008347"
    ]
},
  "bbox": [],
  "geometry": {"coordinates":[-99.783333,17.283333],"type":"Point"}
}