{
  "id": 2557928,
  "type": "Feature",
  "properties": {
    "tgn:hierarchy":[
        "tgn:2557928",
        "tgn:1000001",
        "tgn:7012149",
        "tgn:7007157",
        "tgn:1002828",
        "tgn:7029392"
    ],
    "tgn:id":2557928,
    "tgn:name":"Old Swede Mine",
    "tgn:placetype":[
        "aat:300000390"
    ]
},
  "bbox": [],
  "geometry": {"coordinates":[-115.7667,33.9667],"type":"Point"}
}