{
  "id": 7078546,
  "type": "Feature",
  "properties": {
    "tgn:hierarchy":[
        "tgn:7078546",
        "tgn:7003669",
        "tgn:1000003",
        "tgn:7000084",
        "tgn:7029392"
    ],
    "tgn:id":7078546,
    "tgn:name":"Wittenbach",
    "tgn:placetype":[
        "aat:300008347"
    ]
},
  "bbox": [],
  "geometry": {"coordinates":[10.383333,49.016667],"type":"Point"}
}