<<<<<<< HEAD
{
  "id": 7118432,
  "type": "Feature",
  "properties": {
    "tgn:hierarchy":[
        "tgn:7118432",
        "tgn:7003669",
        "tgn:1000003",
        "tgn:7000084",
        "tgn:7029392"
    ],
    "tgn:id":7118432,
    "tgn:name":"Pilsach",
    "tgn:placetype":[
        "aat:300008347"
    ]
},
  "bbox": [],
  "geometry": {"coordinates":[11.5,49.316667],"type":"Point"}
}
=======
{"geometry":{"type":"Point","coordinates":[11.500000,49.316667]},"type":"Feature","properties":{"hierarchy":["tgn:7118432","tgn:7003669","tgn:1000003","tgn:7000084","tgn:7029392"],"placetype":["aat:300008347"],"id":7118432,"name:xx":"Pilsach"}}
>>>>>>> 03f74aca74312dbeaf24d7e61306dd6a786dc3d0
