{
  "id": 2061991,
  "type": "Feature",
  "properties": {
    "tgn:hierarchy":[
        "tgn:2061991",
        "tgn:1000001",
        "tgn:7012149",
        "tgn:2001385",
        "tgn:7007525",
        "tgn:7029392"
    ],
    "tgn:id":2061991,
    "tgn:name":"Breslau",
    "tgn:placetype":[
        "aat:300008347",
        "aat:300387210"
    ]
},
  "bbox": [],
  "geometry": {"coordinates":[-97.6833,42.35],"type":"Point"}
}