{
  "id": 7233617,
  "type": "Feature",
  "properties": {
    "tgn:hierarchy":[
        "tgn:7233617",
        "tgn:7011369",
        "tgn:7017076",
        "tgn:1000003",
        "tgn:1000074",
        "tgn:7029392"
    ],
    "tgn:id":7233617,
    "tgn:name":"Dhi\u00f3dhia",
    "tgn:placetype":[
        "aat:300008347"
    ]
},
  "bbox": [],
  "geometry": {"coordinates":[21.866667,37.083333],"type":"Point"}
}