<<<<<<< HEAD
{
  "id": 2762884,
  "type": "Feature",
  "properties": {
    "tgn:hierarchy":[
        "tgn:2762884",
        "tgn:1000001",
        "tgn:2001748",
        "tgn:7012149",
        "tgn:7007712",
        "tgn:7029392"
    ],
    "tgn:id":2762884,
    "tgn:name":"Westgate",
    "tgn:placetype":[
        "aat:300008347"
    ]
},
  "bbox": [],
  "geometry": {"coordinates":[-82.2,34.1833],"type":"Point"}
}
=======
{"geometry":{"type":"Point","coordinates":[-82.200000,34.183300]},"type":"Feature","properties":{"hierarchy":["tgn:2762884","tgn:1000001","tgn:2001748","tgn:7012149","tgn:7007712","tgn:7029392"],"placetype":["aat:300008347"],"id":2762884,"name:xx":"Westgate"}}
>>>>>>> 03f74aca74312dbeaf24d7e61306dd6a786dc3d0
