{
  "id": 2649010,
  "type": "Feature",
  "properties": {
    "tgn:hierarchy":[
        "tgn:2649010",
        "tgn:1000001",
        "tgn:7012149",
        "tgn:2001716",
        "tgn:7007708",
        "tgn:7029392"
    ],
    "tgn:id":2649010,
    "tgn:name":"Scott Creek",
    "tgn:placetype":[
        "aat:300008706"
    ]
},
  "bbox": [],
  "geometry": {"coordinates":[-121.95,44.1833],"type":"Point"}
}