{
  "id": 1029750,
  "type": "Feature",
  "properties": {
    "tgn:hierarchy":[
        "tgn:1029750",
        "tgn:7019053",
        "tgn:7002445",
        "tgn:1000003",
        "tgn:7029505",
        "tgn:7008591",
        "tgn:7029392"
    ],
    "tgn:id":1029750,
    "tgn:name":"Kirk Sandall",
    "tgn:placetype":[
        "aat:300008347"
    ]
},
  "bbox": [],
  "geometry": {"coordinates":[-1.083333,53.55],"type":"Point"}
}