{
  "id": 7335754,
  "type": "Feature",
  "properties": {
    "tgn:hierarchy":[
        "tgn:7335754",
        "tgn:7002831",
        "tgn:1000003",
        "tgn:7002786",
        "tgn:1000095",
        "tgn:7029392"
    ],
    "tgn:id":7335754,
    "tgn:name":"Gobias, Arroyo",
    "tgn:placetype":[
        "aat:300008699"
    ]
},
  "bbox": [],
  "geometry": {"coordinates":[-7.566667,42.383333],"type":"Point"}
}