<<<<<<< HEAD
{
  "id": 2152916,
  "type": "Feature",
  "properties": {
    "tgn:hierarchy":[
        "tgn:2152916",
        "tgn:1002338",
        "tgn:1000001",
        "tgn:7012149",
        "tgn:7007516",
        "tgn:7029392"
    ],
    "tgn:id":2152916,
    "tgn:name":"Beach Creek",
    "tgn:placetype":[
        "aat:300008706"
    ]
},
  "bbox": [],
  "geometry": {"coordinates":[-75.7833,38.55],"type":"Point"}
}
=======
{"geometry":{"type":"Point","coordinates":[-75.783300,38.550000]},"type":"Feature","properties":{"hierarchy":["tgn:2152916","tgn:1002338","tgn:1000001","tgn:7012149","tgn:7007516","tgn:7029392"],"placetype":["aat:300008706"],"id":2152916,"name:xx":"Beach Creek"}}
>>>>>>> 03f74aca74312dbeaf24d7e61306dd6a786dc3d0
