{
  "id": 7158626,
  "type": "Feature",
  "properties": {
    "tgn:hierarchy":[
        "tgn:7158626",
        "tgn:7003669",
        "tgn:1000003",
        "tgn:7000084",
        "tgn:7029392"
    ],
    "tgn:id":7158626,
    "tgn:name":"H\u00f6llenstein",
    "tgn:placetype":[
        "aat:300008777"
    ]
},
  "bbox": [],
  "geometry": {"coordinates":[12.166667,49.483333],"type":"Point"}
}