{
  "id": 7176764,
  "type": "Feature",
  "properties": {
    "tgn:hierarchy":[
        "tgn:7176764",
        "tgn:1000003",
        "tgn:7003687",
        "tgn:7000084",
        "tgn:7029392"
    ],
    "tgn:id":7176764,
    "tgn:name":"G\u00fctschow Berg",
    "tgn:placetype":[
        "aat:300008777"
    ]
},
  "bbox": [],
  "geometry": {"coordinates":[12.183333,52.666667],"type":"Point"}
}