{
  "id": 7256519,
  "type": "Feature",
  "properties": {
    "tgn:hierarchy":[
        "tgn:7256519",
        "tgn:7003461",
        "tgn:1000003",
        "tgn:1000063",
        "tgn:7018236",
        "tgn:7029392"
    ],
    "tgn:id":7256519,
    "tgn:name":"Widooie",
    "tgn:placetype":[
        "aat:300008347"
    ]
},
  "bbox": [],
  "geometry": {"coordinates":[5.407765,50.771941],"type":"Point"}
}