{
  "id": 2471795,
  "type": "Feature",
  "properties": {
    "tgn:hierarchy":[
        "tgn:2471795",
        "tgn:1002172",
        "tgn:1000001",
        "tgn:7012149",
        "tgn:7007710",
        "tgn:7029392"
    ],
    "tgn:id":2471795,
    "tgn:name":"Lost Run",
    "tgn:placetype":[
        "aat:300008699"
    ]
},
  "bbox": [],
  "geometry": {"coordinates":[-78.6167,39.7667],"type":"Point"}
}