{
  "id": 7288408,
  "type": "Feature",
  "properties": {
    "tgn:hierarchy":[
        "tgn:7288408",
        "tgn:1001637",
        "tgn:1000049",
        "tgn:1000002",
        "tgn:7029392"
    ],
    "tgn:id":7288408,
    "tgn:name":"Huing\u00e1n",
    "tgn:placetype":[
        "aat:300000206"
    ]
},
  "bbox": [],
  "geometry": {"coordinates":[-72.183333,-37.633333],"type":"Point"}
}