<<<<<<< HEAD
{
  "id": 7471850,
  "type": "Feature",
  "properties": {
    "tgn:hierarchy":[
        "tgn:7471850",
        "tgn:1000004",
        "tgn:7492971",
        "tgn:1000141",
        "tgn:7029392"
    ],
    "tgn:id":7471850,
    "tgn:name":"Chufeng Shan",
    "tgn:placetype":[
        "aat:300008795"
    ]
},
  "bbox": [],
  "geometry": {"coordinates":[120.874167,22.046667],"type":"Point"}
}
=======
{"geometry":{"type":"Point","coordinates":[120.874167,22.046667]},"type":"Feature","properties":{"hierarchy":["tgn:7471850","tgn:1000004","tgn:7492971","tgn:1000141","tgn:7029392"],"placetype":["aat:300008795"],"id":7471850,"name:xx":"Chufeng Shan"}}
>>>>>>> 03f74aca74312dbeaf24d7e61306dd6a786dc3d0
