{
  "id": 6004623,
  "type": "Feature",
  "properties": {
    "tgn:hierarchy":[
        "tgn:6004623",
        "tgn:7002443",
        "tgn:1000003",
        "tgn:7018960",
        "tgn:7008591",
        "tgn:7029392"
    ],
    "tgn:id":6004623,
    "tgn:name":"Pen-y-darren",
    "tgn:placetype":[
        "aat:300008347"
    ]
},
  "bbox": [],
  "geometry": {"coordinates":[-3.3667,51.75],"type":"Point"}
}