{
  "id": 2632780,
  "type": "Feature",
  "properties": {
    "tgn:hierarchy":[
        "tgn:2632780",
        "tgn:1000001",
        "tgn:2001331",
        "tgn:7012149",
        "tgn:7007525",
        "tgn:7029392"
    ],
    "tgn:id":2632780,
    "tgn:name":"Ruby Lake",
    "tgn:placetype":[
        "aat:300008680"
    ]
},
  "bbox": [],
  "geometry": {"coordinates":[-101.8333,42.4333],"type":"Point"}
}