<<<<<<< HEAD
{
  "id": 7358882,
  "type": "Feature",
  "properties": {
    "tgn:hierarchy":[
        "tgn:7358882",
        "tgn:1000001",
        "tgn:7005597",
        "tgn:7005560",
        "tgn:7029392"
    ],
    "tgn:id":7358882,
    "tgn:name":"Cruillas, Sierra",
    "tgn:placetype":[
        "aat:300008795"
    ]
},
  "bbox": [],
  "geometry": {"coordinates":[-98.5,24.716667],"type":"Point"}
}
=======
{"geometry":{"type":"Point","coordinates":[-98.500000,24.716667]},"type":"Feature","properties":{"hierarchy":["tgn:7358882","tgn:1000001","tgn:7005597","tgn:7005560","tgn:7029392"],"placetype":["aat:300008795"],"id":7358882,"name:xx":"Cruillas, Sierra"}}
>>>>>>> 03f74aca74312dbeaf24d7e61306dd6a786dc3d0
