{
  "id": 2665304,
  "type": "Feature",
  "properties": {
    "tgn:hierarchy":[
        "tgn:2665304",
        "tgn:7006450",
        "tgn:1000001",
        "tgn:7012149",
        "tgn:2000082",
        "tgn:7029392"
    ],
    "tgn:id":2665304,
    "tgn:name":"Singa Island",
    "tgn:placetype":[
        "aat:300008791"
    ]
},
  "bbox": [],
  "geometry": {"coordinates":[-133.35,55.9333],"type":"Point"}
}