{
  "id": 1140048,
  "type": "Feature",
  "properties": {
    "tgn:hierarchy":[
        "tgn:1140048",
        "tgn:1000956",
        "tgn:1000004",
        "tgn:1000111",
        "tgn:7029392"
    ],
    "tgn:id":1140048,
    "tgn:name":"Zhanggezhuang",
    "tgn:placetype":[
        "aat:300008347"
    ]
},
  "bbox": [],
  "geometry": {"coordinates":[116.9333,40.1333],"type":"Point"}
}