{
  "id": 7432267,
  "type": "Feature",
  "properties": {
    "tgn:hierarchy":[
        "tgn:7432267",
        "tgn:1001853",
        "tgn:1000001",
        "tgn:7005560",
        "tgn:7029392"
    ],
    "tgn:id":7432267,
    "tgn:name":"El Sotol",
    "tgn:placetype":[
        "aat:300008347"
    ]
},
  "bbox": [],
  "geometry": {"coordinates":[-101.283333,29.266667],"type":"Point"}
}