{
  "id": 2008828,
  "type": "Feature",
  "properties": {
    "tgn:hierarchy":[
        "tgn:2008828",
        "tgn:1000001",
        "tgn:7016172",
        "tgn:7012149",
        "tgn:2000125",
        "tgn:7029392"
    ],
    "tgn:id":2008828,
    "tgn:name":"McArthur",
    "tgn:placetype":[
        "aat:300008347",
        "aat:300387210"
    ]
},
  "bbox": [],
  "geometry": {"coordinates":[-91.3333,33.6833],"type":"Point"}
}