<<<<<<< HEAD
{
  "id": 2768402,
  "type": "Feature",
  "properties": {
    "tgn:hierarchy":[
        "tgn:2768402",
        "tgn:1000001",
        "tgn:7012149",
        "tgn:7007566",
        "tgn:7029392"
    ],
    "tgn:id":2768402,
    "tgn:name":"Whitetail Canyon",
    "tgn:placetype":[
        "aat:300008761"
    ]
},
  "bbox": [],
  "geometry": {"coordinates":[-105.6167,33.2167],"type":"Point"}
}
=======
{"geometry":{"type":"Point","coordinates":[-105.616700,33.216700]},"type":"Feature","properties":{"hierarchy":["tgn:2768402","tgn:1000001","tgn:7012149","tgn:7007566","tgn:7029392"],"placetype":["aat:300008761"],"id":2768402,"name:xx":"Whitetail Canyon"}}
>>>>>>> 03f74aca74312dbeaf24d7e61306dd6a786dc3d0
