{
  "id": 7196546,
  "type": "Feature",
  "properties": {
    "tgn:hierarchy":[
        "tgn:7196546",
        "tgn:7003669",
        "tgn:1000003",
        "tgn:7000084",
        "tgn:7029392"
    ],
    "tgn:id":7196546,
    "tgn:name":"Deuringen",
    "tgn:placetype":[
        "aat:300008347"
    ]
},
  "bbox": [],
  "geometry": {"coordinates":[10.816667,48.366667],"type":"Point"}
}