<<<<<<< HEAD
{
  "id": 7359348,
  "type": "Feature",
  "properties": {
    "tgn:hierarchy":[
        "tgn:7359348",
        "tgn:1000001",
        "tgn:7005601",
        "tgn:7005560",
        "tgn:7029392"
    ],
    "tgn:id":7359348,
    "tgn:name":"Cruz Verde",
    "tgn:placetype":[
        "aat:300008347"
    ]
},
  "bbox": [],
  "geometry": {"coordinates":[-102.9,21.933333],"type":"Point"}
}
=======
{"geometry":{"type":"Point","coordinates":[-102.900000,21.933333]},"type":"Feature","properties":{"hierarchy":["tgn:7359348","tgn:1000001","tgn:7005601","tgn:7005560","tgn:7029392"],"placetype":["aat:300008347"],"id":7359348,"name:xx":"Cruz Verde"}}
>>>>>>> 03f74aca74312dbeaf24d7e61306dd6a786dc3d0
