<<<<<<< HEAD
{
  "id": 7241925,
  "type": "Feature",
  "properties": {
    "tgn:hierarchy":[
        "tgn:7241925",
        "tgn:7003456",
        "tgn:1000003",
        "tgn:1000063",
        "tgn:7018236",
        "tgn:7029392"
    ],
    "tgn:id":7241925,
    "tgn:name":"Lipseinde",
    "tgn:placetype":[
        "aat:300008347"
    ]
},
  "bbox": [],
  "geometry": {"coordinates":[4.9,51.383333],"type":"Point"}
}
=======
{"geometry":{"type":"Point","coordinates":[4.900000,51.383333]},"type":"Feature","properties":{"hierarchy":["tgn:7241925","tgn:7003456","tgn:1000003","tgn:1000063","tgn:7018236","tgn:7029392"],"placetype":["aat:300008347"],"id":7241925,"name:xx":"Lipseinde"}}
>>>>>>> 03f74aca74312dbeaf24d7e61306dd6a786dc3d0
