{
  "id": 2214619,
  "type": "Feature",
  "properties": {
    "tgn:hierarchy":[
        "tgn:2214619",
        "tgn:1002933",
        "tgn:1000001",
        "tgn:7012149",
        "tgn:7007239",
        "tgn:7029392"
    ],
    "tgn:id":2214619,
    "tgn:name":"Caleb Pond",
    "tgn:placetype":[
        "aat:300008680"
    ]
},
  "bbox": [],
  "geometry": {"coordinates":[-75.25,38.85],"type":"Point"}
}