{
  "id": 7483667,
  "type": "Feature",
  "properties": {
    "tgn:hierarchy":[
        "tgn:7483667",
        "tgn:1000004",
        "tgn:1000454",
        "tgn:1000141",
        "tgn:7029392"
    ],
    "tgn:id":7483667,
    "tgn:name":"Xiweiliao Shan",
    "tgn:placetype":[
        "aat:300008798"
    ]
},
  "bbox": [],
  "geometry": {"coordinates":[121.823333,24.975833],"type":"Point"}
}