<<<<<<< HEAD
{
  "id": 2150977,
  "type": "Feature",
  "properties": {
    "tgn:hierarchy":[
        "tgn:2150977",
        "tgn:1002201",
        "tgn:1000001",
        "tgn:7012149",
        "tgn:7007517",
        "tgn:7029392"
    ],
    "tgn:id":2150977,
    "tgn:name":"Bassett Brook",
    "tgn:placetype":[
        "aat:300008699"
    ]
},
  "bbox": [],
  "geometry": {"coordinates":[-70.9833,41.9167],"type":"Point"}
}
=======
{"geometry":{"type":"Point","coordinates":[-70.983300,41.916700]},"type":"Feature","properties":{"hierarchy":["tgn:2150977","tgn:1002201","tgn:1000001","tgn:7012149","tgn:7007517","tgn:7029392"],"placetype":["aat:300008699"],"id":2150977,"name:xx":"Bassett Brook"}}
>>>>>>> 03f74aca74312dbeaf24d7e61306dd6a786dc3d0
