{
  "id": 2150977,
  "type": "Feature",
  "properties": {
    "tgn:hierarchy":[
        "tgn:2150977",
        "tgn:1002201",
        "tgn:1000001",
        "tgn:7012149",
        "tgn:7007517",
        "tgn:7029392"
    ],
    "tgn:id":2150977,
    "tgn:name":"Bassett Brook",
    "tgn:placetype":[
        "aat:300008699"
    ]
},
  "bbox": [],
  "geometry": {"coordinates":[-70.9833,41.9167],"type":"Point"}
}