{
  "id": 7492564,
  "type": "Feature",
  "properties": {
    "tgn:hierarchy":[
        "tgn:7492564",
        "tgn:7001010",
        "tgn:1000004",
        "tgn:1000141",
        "tgn:7029392"
    ],
    "tgn:id":7492564,
    "tgn:name":"Danong",
    "tgn:placetype":[
        "aat:300008347"
    ]
},
  "bbox": [],
  "geometry": {"coordinates":[121.428608,23.615691],"type":"Point"}
}