{
  "id": 1058542,
  "type": "Feature",
  "properties": {
    "tgn:hierarchy":[
        "tgn:1058542",
        "tgn:7012187",
        "tgn:1000003",
        "tgn:7006657",
        "tgn:7029392"
    ],
    "tgn:id":1058542,
    "tgn:name":"Poles'ye",
    "tgn:placetype":[
        "aat:300008347"
    ]
},
  "bbox": [],
  "geometry": {"coordinates":[31.2833,53.0833],"type":"Point"}
}