<<<<<<< HEAD
{
  "id": 2339646,
  "type": "Feature",
  "properties": {
    "tgn:hierarchy":[
        "tgn:2339646",
        "tgn:1000001",
        "tgn:2001023",
        "tgn:7012149",
        "tgn:7007521",
        "tgn:7029392"
    ],
    "tgn:id":2339646,
    "tgn:name":"Fredrickson, Lake",
    "tgn:placetype":[
        "aat:300006191"
    ]
},
  "bbox": [],
  "geometry": {"coordinates":[-92.9,44.5],"type":"Point"}
}
=======
{"geometry":{"type":"Point","coordinates":[-92.900000,44.500000]},"type":"Feature","properties":{"hierarchy":["tgn:2339646","tgn:1000001","tgn:2001023","tgn:7012149","tgn:7007521","tgn:7029392"],"placetype":["aat:300006191"],"id":2339646,"name:xx":"Fredrickson, Lake"}}
>>>>>>> 03f74aca74312dbeaf24d7e61306dd6a786dc3d0
