{
  "id": 2235950,
  "type": "Feature",
  "properties": {
    "tgn:hierarchy":[
        "tgn:2235950",
        "tgn:1000001",
        "tgn:2001703",
        "tgn:7012149",
        "tgn:7007708",
        "tgn:7029392"
    ],
    "tgn:id":2235950,
    "tgn:name":"Chev Spring",
    "tgn:placetype":[
        "aat:300008697"
    ]
},
  "bbox": [],
  "geometry": {"coordinates":[-120.3333,44.2833],"type":"Point"}
}