{
  "id": 2182371,
  "type": "Feature",
  "properties": {
    "tgn:hierarchy":[
        "tgn:2182371",
        "tgn:1000001",
        "tgn:7006451",
        "tgn:7012149",
        "tgn:7029392"
    ],
    "tgn:id":2182371,
    "tgn:name":"Blue Ridge",
    "tgn:placetype":[
        "aat:300266640"
    ]
},
  "bbox": [],
  "geometry": {"coordinates":[-111.5167,33.45],"type":"Point"}
}