{
  "id": 1112023,
  "type": "Feature",
  "properties": {
    "tgn:hierarchy":[
        "tgn:1112023",
        "tgn:1000004",
        "tgn:1000121",
        "tgn:7029392"
    ],
    "tgn:id":1112023,
    "tgn:name":"Jabb\u0101n, Ar\u1e0d al-",
    "tgn:placetype":[
        "aat:300387346"
    ]
},
  "bbox": [],
  "geometry": {"coordinates":[36.5833,32.1333],"type":"Point"}
}