{
  "id": 2569059,
  "type": "Feature",
  "properties": {
    "tgn:hierarchy":[
        "tgn:2569059",
        "tgn:1000001",
        "tgn:7012149",
        "tgn:2001709",
        "tgn:7007708",
        "tgn:7029392"
    ],
    "tgn:id":2569059,
    "tgn:name":"Parker Springs",
    "tgn:placetype":[
        "aat:300008697"
    ]
},
  "bbox": [],
  "geometry": {"coordinates":[-119.1333,43.6667],"type":"Point"}
}