{
  "id": 2626832,
  "type": "Feature",
  "properties": {
    "tgn:hierarchy":[
        "tgn:2626832",
        "tgn:1000001",
        "tgn:7012149",
        "tgn:2002026",
        "tgn:7007826",
        "tgn:7029392"
    ],
    "tgn:id":2626832,
    "tgn:name":"Rocky Point",
    "tgn:placetype":[
        "aat:300008798"
    ]
},
  "bbox": [],
  "geometry": {"coordinates":[-98.2833,31.2667],"type":"Point"}
}