{
  "id": 2363330,
  "type": "Feature",
  "properties": {
    "tgn:hierarchy":[
        "tgn:2363330",
        "tgn:1000001",
        "tgn:7012149",
        "tgn:1002554",
        "tgn:7007920",
        "tgn:7029392"
    ],
    "tgn:id":2363330,
    "tgn:name":"Green Canyon",
    "tgn:placetype":[
        "aat:300008761"
    ]
},
  "bbox": [],
  "geometry": {"coordinates":[-121.1833,45.7333],"type":"Point"}
}