{
  "id": 2433189,
  "type": "Feature",
  "properties": {
    "tgn:hierarchy":[
        "tgn:2433189",
        "tgn:1000001",
        "tgn:7012149",
        "tgn:2000905",
        "tgn:7007256",
        "tgn:7029392"
    ],
    "tgn:id":2433189,
    "tgn:name":"Keller Bayou",
    "tgn:placetype":[
        "aat:300008699"
    ]
},
  "bbox": [],
  "geometry": {"coordinates":[-89.7833,30.5167],"type":"Point"}
}