{
  "id": 2257583,
  "type": "Feature",
  "properties": {
    "tgn:hierarchy":[
        "tgn:2257583",
        "tgn:7002659",
        "tgn:1000001",
        "tgn:7012149",
        "tgn:2000051",
        "tgn:7029392"
    ],
    "tgn:id":2257583,
    "tgn:name":"Corral Cave",
    "tgn:placetype":[
        "aat:300008746"
    ]
},
  "bbox": [],
  "geometry": {"coordinates":[-86.5833,33.4167],"type":"Point"}
}