{
  "id": 7510446,
  "type": "Feature",
  "properties": {
    "tgn:hierarchy":[
        "tgn:7510446",
        "tgn:1009227",
        "tgn:1000226",
        "tgn:7016729",
        "tgn:1000006",
        "tgn:7029392"
    ],
    "tgn:id":7510446,
    "tgn:name:en":"Spray",
    "tgn:placetype":[
        "aat:300008795"
    ]
},
  "bbox": [],
  "geometry": {"coordinates":[173.416667,-41.816667],"type":"Point"}
}