{
  "id": 7444192,
  "type": "Feature",
  "properties": {
    "tgn:hierarchy":[
        "tgn:7444192",
        "tgn:7002444",
        "tgn:1000003",
        "tgn:7008082",
        "tgn:7008591",
        "tgn:7029392"
    ],
    "tgn:id":7444192,
    "tgn:name:en":"Uisge, Loch",
    "tgn:placetype":[
        "aat:300008680"
    ]
},
  "bbox": [],
  "geometry": {"coordinates":[-5.583333,56.633333],"type":"Point"}
}