{
  "id": 7051392,
  "type": "Feature",
  "properties": {
    "tgn:hierarchy":[
        "tgn:7051392",
        "tgn:1000003",
        "tgn:7003152",
        "tgn:7003237",
        "tgn:1000080",
        "tgn:7029392"
    ],
    "tgn:id":7051392,
    "tgn:name":"La Costa",
    "tgn:placetype":[
        "aat:300008347"
    ]
},
  "bbox": [],
  "geometry": {"coordinates":[9.816667,46.083333],"type":"Point"}
}