{
  "id": 7519077,
  "type": "Feature",
  "properties": {
    "tgn:hierarchy":[
        "tgn:7519077",
        "tgn:1009227",
        "tgn:1000226",
        "tgn:1000006",
        "tgn:7016850",
        "tgn:7029392"
    ],
    "tgn:id":7519077,
    "tgn:name:en":"Arapito",
    "tgn:placetype":[
        "aat:300008347"
    ]
},
  "bbox": [],
  "geometry": {"coordinates":[172.166667,-41.266667],"type":"Point"}
}