{
  "id": 2656006,
  "type": "Feature",
  "properties": {
    "tgn:hierarchy":[
        "tgn:2656006",
        "tgn:1000001",
        "tgn:2000315",
        "tgn:7012149",
        "tgn:7007248",
        "tgn:7029392"
    ],
    "tgn:id":2656006,
    "tgn:name":"Shaw Lake",
    "tgn:placetype":[
        "aat:300008680"
    ]
},
  "bbox": [],
  "geometry": {"coordinates":[-82.0667,30.35],"type":"Point"}
}