{
  "id": 7198899,
  "type": "Feature",
  "properties": {
    "tgn:hierarchy":[
        "tgn:7198899",
        "tgn:7003669",
        "tgn:1000003",
        "tgn:7000084",
        "tgn:7029392"
    ],
    "tgn:id":7198899,
    "tgn:name":"Eberding",
    "tgn:placetype":[
        "aat:300008347"
    ]
},
  "bbox": [],
  "geometry": {"coordinates":[12.85,47.95],"type":"Point"}
}