{
  "id": 2018127,
  "type": "Feature",
  "properties": {
    "tgn:hierarchy":[
        "tgn:2018127",
        "tgn:7014201",
        "tgn:1000001",
        "tgn:7012149",
        "tgn:7007239",
        "tgn:7029392"
    ],
    "tgn:id":2018127,
    "tgn:name":"Rambleton Acres",
    "tgn:placetype":[
        "aat:300008347"
    ]
},
  "bbox": [],
  "geometry": {"coordinates":[-75.6167,39.6333],"type":"Point"}
}