{
  "id": 2606449,
  "type": "Feature",
  "properties": {
    "tgn:hierarchy":[
        "tgn:2606449",
        "tgn:1000001",
        "tgn:7012149",
        "tgn:2001906",
        "tgn:7007825",
        "tgn:7029392"
    ],
    "tgn:id":2606449,
    "tgn:name":"Ram Pump Spring",
    "tgn:placetype":[
        "aat:300008697"
    ]
},
  "bbox": [],
  "geometry": {"coordinates":[-84.6167,35.1333],"type":"Point"}
}