{
  "id": 7324465,
  "type": "Feature",
  "properties": {
    "tgn:hierarchy":[
        "tgn:7324465",
        "tgn:7002849",
        "tgn:1000003",
        "tgn:7009604",
        "tgn:1000095",
        "tgn:7029392"
    ],
    "tgn:id":7324465,
    "tgn:name":"Saturrar\u00e1n",
    "tgn:placetype":[
        "aat:300008347"
    ]
},
  "bbox": [],
  "geometry": {"coordinates":[-2.411918,43.319094],"type":"Point"}
}