{
  "id": 7527330,
  "type": "Feature",
  "properties": {
    "tgn:hierarchy":[
        "tgn:7527330",
        "tgn:7001242",
        "tgn:7016833",
        "tgn:1001091",
        "tgn:7029392"
    ],
    "tgn:id":7527330,
    "tgn:name":"Mas\u0101kin ad Darr\u0101sah",
    "tgn:placetype":[
        "aat:300000745"
    ]
},
  "bbox": [],
  "geometry": {"coordinates":[31.268841,30.048675],"type":"Point"}
}