{
  "id": 7510356,
  "type": "Feature",
  "properties": {
    "tgn:hierarchy":[
        "tgn:7510356",
        "tgn:1009227",
        "tgn:1000226",
        "tgn:7016729",
        "tgn:1000006",
        "tgn:7029392"
    ],
    "tgn:id":7510356,
    "tgn:name:en":"Te Ikaamaru Bay",
    "tgn:placetype":[
        "aat:300132316"
    ]
},
  "bbox": [],
  "geometry": {"coordinates":[174.666667,-41.25],"type":"Point"}
}