{
  "id": 7090155,
  "type": "Feature",
  "properties": {
    "tgn:hierarchy":[
        "tgn:7090155",
        "tgn:1000003",
        "tgn:7003688",
        "tgn:7000084",
        "tgn:7029392"
    ],
    "tgn:id":7090155,
    "tgn:name":"Waardingdeel",
    "tgn:placetype":[
        "aat:300386860"
    ]
},
  "bbox": [],
  "geometry": {"coordinates":[8.283333,54.816667],"type":"Point"}
}