<<<<<<< HEAD
{
  "id": 7370963,
  "type": "Feature",
  "properties": {
    "tgn:hierarchy":[
        "tgn:7370963",
        "tgn:1000001",
        "tgn:1001906",
        "tgn:7005560",
        "tgn:7029392"
    ],
    "tgn:id":7370963,
    "tgn:name":"Gorda, Punta",
    "tgn:placetype":[
        "aat:300386846"
    ]
},
  "bbox": [],
  "geometry": {"coordinates":[-105.25,21.383333],"type":"Point"}
}
=======
{"geometry":{"type":"Point","coordinates":[-105.250000,21.383333]},"type":"Feature","properties":{"hierarchy":["tgn:7370963","tgn:1000001","tgn:1001906","tgn:7005560","tgn:7029392"],"placetype":["aat:300386846"],"id":7370963,"name:xx":"Gorda, Punta"}}
>>>>>>> 03f74aca74312dbeaf24d7e61306dd6a786dc3d0
