{
  "id": 2100717,
  "type": "Feature",
  "properties": {
    "tgn:hierarchy":[
        "tgn:2100717",
        "tgn:1000001",
        "tgn:7012149",
        "tgn:2001930",
        "tgn:7007825",
        "tgn:7029392"
    ],
    "tgn:id":2100717,
    "tgn:name":"New Hope",
    "tgn:placetype":[
        "aat:300008347"
    ]
},
  "bbox": [],
  "geometry": {"coordinates":[-87.15,36.0167],"type":"Point"}
}