{
  "id": 7579069,
  "type": "Feature",
  "properties": {
    "tgn:hierarchy":[
        "tgn:7579069",
        "tgn:1000004",
        "tgn:7000198",
        "tgn:1001894",
        "tgn:7029392"
    ],
    "tgn:id":7579069,
    "tgn:name:en":"Ukme Nad\u012b",
    "tgn:placetype":[
        "aat:300008699"
    ]
},
  "bbox": [],
  "geometry": {"coordinates":[81.341113,24.902747],"type":"Point"}
}