{
  "id": 7071487,
  "type": "Feature",
  "properties": {
    "tgn:hierarchy":[
        "tgn:7071487",
        "tgn:1000003",
        "tgn:7003676",
        "tgn:7000084",
        "tgn:7029392"
    ],
    "tgn:id":7071487,
    "tgn:name":"Tegeler Plate",
    "tgn:placetype":[
        "aat:300386990"
    ]
},
  "bbox": [],
  "geometry": {"coordinates":[8.516667,53.466667],"type":"Point"}
}