{
  "id": 7264663,
  "type": "Feature",
  "properties": {
    "tgn:hierarchy":[
        "tgn:7264663",
        "tgn:1000003",
        "tgn:7006951",
        "tgn:7016845",
        "tgn:7029392"
    ],
    "tgn:id":7264663,
    "tgn:name:nl":"Hornmeerpolder",
    "tgn:placetype":[
        "aat:300006163"
    ]
},
  "bbox": [],
  "geometry": {"coordinates":[4.766667,52.266667],"type":"Point"}
}