{
  "id": 2731471,
  "type": "Feature",
  "properties": {
    "tgn:hierarchy":[
        "tgn:2731471",
        "tgn:1000001",
        "tgn:2001629",
        "tgn:7012149",
        "tgn:7007707",
        "tgn:7029392"
    ],
    "tgn:id":2731471,
    "tgn:name":"Tuklo Creek",
    "tgn:placetype":[
        "aat:300008706"
    ]
},
  "bbox": [],
  "geometry": {"coordinates":[-96.1833,33.9167],"type":"Point"}
}