{
  "id": 2513073,
  "type": "Feature",
  "properties": {
    "tgn:hierarchy":[
        "tgn:2513073",
        "tgn:1000001",
        "tgn:1002275",
        "tgn:7012149",
        "tgn:7007920",
        "tgn:7029392"
    ],
    "tgn:id":2513073,
    "tgn:name":"Mill Creek",
    "tgn:placetype":[
        "aat:300008706"
    ]
},
  "bbox": [],
  "geometry": {"coordinates":[-122.55,45.7833],"type":"Point"}
}