{
  "id": 7552765,
  "type": "Feature",
  "properties": {
    "tgn:hierarchy":[
        "tgn:7552765",
        "tgn:1001828",
        "tgn:1000004",
        "tgn:7000198",
        "tgn:7029392"
    ],
    "tgn:id":7552765,
    "tgn:name:en":"Mudivedu",
    "tgn:placetype":[
        "aat:300008347"
    ]
},
  "bbox": [],
  "geometry": {"coordinates":[78.516667,13.716667],"type":"Point"}
}