<<<<<<< HEAD
{
  "id": 2764984,
  "type": "Feature",
  "properties": {
    "tgn:hierarchy":[
        "tgn:2764984",
        "tgn:1000001",
        "tgn:7012149",
        "tgn:7007520",
        "tgn:7029392"
    ],
    "tgn:id":2764984,
    "tgn:name":"Whisky Creek",
    "tgn:placetype":[
        "aat:300008706"
    ]
},
  "bbox": [],
  "geometry": {"coordinates":[-85.0833,44.0833],"type":"Point"}
}
=======
{"geometry":{"type":"Point","coordinates":[-85.083300,44.083300]},"type":"Feature","properties":{"hierarchy":["tgn:2764984","tgn:1000001","tgn:7012149","tgn:7007520","tgn:7029392"],"placetype":["aat:300008706"],"id":2764984,"name:xx":"Whisky Creek"}}
>>>>>>> 03f74aca74312dbeaf24d7e61306dd6a786dc3d0
