{
  "id": 7424134,
  "type": "Feature",
  "properties": {
    "tgn:hierarchy":[
        "tgn:7424134",
        "tgn:1000001",
        "tgn:7005601",
        "tgn:7005560",
        "tgn:7029392"
    ],
    "tgn:id":7424134,
    "tgn:name":"Verde",
    "tgn:placetype":[
        "aat:300008347"
    ]
},
  "bbox": [],
  "geometry": {"coordinates":[-102.416667,22.466667],"type":"Point"}
}