{
  "id": 7478957,
  "type": "Feature",
  "properties": {
    "tgn:hierarchy":[
        "tgn:7478957",
        "tgn:1000004",
        "tgn:7489179",
        "tgn:1000141",
        "tgn:7029392"
    ],
    "tgn:id":7478957,
    "tgn:name":"Mamei Shan",
    "tgn:placetype":[
        "aat:300008798"
    ]
},
  "bbox": [],
  "geometry": {"coordinates":[121.485556,24.348333],"type":"Point"}
}