{
  "id": 2221521,
  "type": "Feature",
  "properties": {
    "tgn:hierarchy":[
        "tgn:2221521",
        "tgn:1000001",
        "tgn:7012149",
        "tgn:7007157",
        "tgn:2000189",
        "tgn:7029392"
    ],
    "tgn:id":2221521,
    "tgn:name":"Caribou Mountain",
    "tgn:placetype":[
        "aat:300008798"
    ]
},
  "bbox": [],
  "geometry": {"coordinates":[-122.95,41.0167],"type":"Point"}
}