<<<<<<< HEAD
{
  "id": 2159378,
  "type": "Feature",
  "properties": {
    "tgn:hierarchy":[
        "tgn:2159378",
        "tgn:1000001",
        "tgn:7012149",
        "tgn:2001882",
        "tgn:7007825",
        "tgn:7029392"
    ],
    "tgn:id":2159378,
    "tgn:name":"Bee Cove Branch",
    "tgn:placetype":[
        "aat:300008699"
    ]
},
  "bbox": [],
  "geometry": {"coordinates":[-81.8667,36.4667],"type":"Point"}
}
=======
{"geometry":{"type":"Point","coordinates":[-81.866700,36.466700]},"type":"Feature","properties":{"hierarchy":["tgn:2159378","tgn:1000001","tgn:7012149","tgn:2001882","tgn:7007825","tgn:7029392"],"placetype":["aat:300008699"],"id":2159378,"name:xx":"Bee Cove Branch"}}
>>>>>>> 03f74aca74312dbeaf24d7e61306dd6a786dc3d0
