{
  "id": 7335362,
  "type": "Feature",
  "properties": {
    "tgn:hierarchy":[
        "tgn:7335362",
        "tgn:7001165",
        "tgn:1000003",
        "tgn:7002793",
        "tgn:1000095",
        "tgn:7029392"
    ],
    "tgn:id":7335362,
    "tgn:name":"Gallego de Poyo, Barranco del",
    "tgn:placetype":[
        "aat:300266554",
        "aat:300008699"
    ]
},
  "bbox": [],
  "geometry": {"coordinates":[-0.516667,39.466667],"type":"Point"}
}