{
  "id": 7102616,
  "type": "Feature",
  "properties": {
    "tgn:hierarchy":[
        "tgn:7102616",
        "tgn:1000003",
        "tgn:7003676",
        "tgn:7000084",
        "tgn:7029392"
    ],
    "tgn:id":7102616,
    "tgn:name":"Ruhbrink",
    "tgn:placetype":[
        "aat:300266640"
    ]
},
  "bbox": [],
  "geometry": {"coordinates":[9.533333,52.133333],"type":"Point"}
}