{
  "id": 7410706,
  "type": "Feature",
  "properties": {
    "tgn:hierarchy":[
        "tgn:7410706",
        "tgn:7005580",
        "tgn:1000001",
        "tgn:7005560",
        "tgn:7029392"
    ],
    "tgn:id":7410706,
    "tgn:name":"Santa Isabel",
    "tgn:placetype":[
        "aat:300008347"
    ]
},
  "bbox": [],
  "geometry": {"coordinates":[-93.866667,16.366667],"type":"Point"}
}