{
  "id": 2644320,
  "type": "Feature",
  "properties": {
    "tgn:hierarchy":[
        "tgn:2644320",
        "tgn:1000001",
        "tgn:7012149",
        "tgn:2000386",
        "tgn:7007248",
        "tgn:7029392"
    ],
    "tgn:id":2644320,
    "tgn:name":"Sapelo Sound",
    "tgn:placetype":[
        "aat:300132316"
    ]
},
  "bbox": [],
  "geometry": {"coordinates":[-81.2167,31.5333],"type":"Point"}
}