{
  "id": 2249813,
  "type": "Feature",
  "properties": {
    "tgn:hierarchy":[
        "tgn:2249813",
        "tgn:1000001",
        "tgn:7012149",
        "tgn:1002755",
        "tgn:7007523",
        "tgn:7029392"
    ],
    "tgn:id":2249813,
    "tgn:name":"College Hill Lake",
    "tgn:placetype":[
        "aat:300006191"
    ]
},
  "bbox": [],
  "geometry": {"coordinates":[-91.6833,38.3833],"type":"Point"}
}