{
  "id": 7485707,
  "type": "Feature",
  "properties": {
    "tgn:hierarchy":[
        "tgn:7485707",
        "tgn:1000004",
        "tgn:7492971",
        "tgn:1000141",
        "tgn:7029392"
    ],
    "tgn:id":7485707,
    "tgn:name":"Fenggang Xikou",
    "tgn:placetype":[
        "aat:300387057"
    ]
},
  "bbox": [],
  "geometry": {"coordinates":[120.684722,22.195],"type":"Point"}
}