{
  "id": 2028756,
  "type": "Feature",
  "properties": {
    "tgn:hierarchy":[
        "tgn:2028756",
        "tgn:1000001",
        "tgn:7012149",
        "tgn:2000530",
        "tgn:7007251",
        "tgn:7029392"
    ],
    "tgn:id":2028756,
    "tgn:name":"Liberty",
    "tgn:placetype":[
        "aat:300008347"
    ]
},
  "bbox": [],
  "geometry": {"coordinates":[-88.5667,37.7167],"type":"Point"}
}