{
  "id": 7232548,
  "type": "Feature",
  "properties": {
    "tgn:hierarchy":[
        "tgn:7232548",
        "tgn:7002748",
        "tgn:7001399",
        "tgn:1000003",
        "tgn:1000074",
        "tgn:7029392"
    ],
    "tgn:id":7232548,
    "tgn:name":"Is\u00f3mata",
    "tgn:placetype":[
        "aat:300008347"
    ]
},
  "bbox": [],
  "geometry": {"coordinates":[21.533333,39.366667],"type":"Point"}
}