<<<<<<< HEAD
{
  "id": 7054447,
  "type": "Feature",
  "properties": {
    "tgn:hierarchy":[
        "tgn:7054447",
        "tgn:7003135",
        "tgn:1000003",
        "tgn:7003080",
        "tgn:1000080",
        "tgn:7029392"
    ],
    "tgn:id":7054447,
    "tgn:name":"Monna Casale",
    "tgn:placetype":[
        "aat:300008795"
    ]
},
  "bbox": [],
  "geometry": {"coordinates":[13.983333,41.566667],"type":"Point"}
}
=======
{"geometry":{"type":"Point","coordinates":[13.983333,41.566667]},"type":"Feature","properties":{"hierarchy":["tgn:7054447","tgn:7003135","tgn:1000003","tgn:7003080","tgn:1000080","tgn:7029392"],"placetype":["aat:300008795"],"id":7054447,"name:xx":"Monna Casale"}}
>>>>>>> 03f74aca74312dbeaf24d7e61306dd6a786dc3d0
