{
  "id": 7284710,
  "type": "Feature",
  "properties": {
    "tgn:hierarchy":[
        "tgn:7284710",
        "tgn:1001699",
        "tgn:1000049",
        "tgn:1000002",
        "tgn:7029392"
    ],
    "tgn:id":7284710,
    "tgn:name":"Pilcomayo, Punta",
    "tgn:placetype":[
        "aat:300386846"
    ]
},
  "bbox": [],
  "geometry": {"coordinates":[-72.833333,-43.016667],"type":"Point"}
}