{
  "id": 2148501,
  "type": "Feature",
  "properties": {
    "tgn:hierarchy":[
        "tgn:2148501",
        "tgn:7002659",
        "tgn:1000001",
        "tgn:7012149",
        "tgn:2000063",
        "tgn:7029392"
    ],
    "tgn:id":2148501,
    "tgn:name":"Barnes Branch",
    "tgn:placetype":[
        "aat:300008699"
    ]
},
  "bbox": [],
  "geometry": {"coordinates":[-87.0833,33.6667],"type":"Point"}
}