{
  "id": 7423591,
  "type": "Feature",
  "properties": {
    "tgn:hierarchy":[
        "tgn:7423591",
        "tgn:1000001",
        "tgn:1001960",
        "tgn:7005560",
        "tgn:7029392"
    ],
    "tgn:id":7423591,
    "tgn:name":"La Pintada",
    "tgn:placetype":[
        "aat:300008347"
    ]
},
  "bbox": [],
  "geometry": {"coordinates":[-111.016667,28.583333],"type":"Point"}
}