{
  "id": 7188361,
  "type": "Feature",
  "properties": {
    "tgn:hierarchy":[
        "tgn:7188361",
        "tgn:7003692",
        "tgn:1000003",
        "tgn:7000084",
        "tgn:7029392"
    ],
    "tgn:id":7188361,
    "tgn:name":"Emmingen",
    "tgn:placetype":[
        "aat:300008347"
    ]
},
  "bbox": [],
  "geometry": {"coordinates":[8.733333,48.583333],"type":"Point"}
}