{
  "id": 2757433,
  "type": "Feature",
  "properties": {
    "tgn:hierarchy":[
        "tgn:2757433",
        "tgn:1000001",
        "tgn:7012149",
        "tgn:7007158",
        "tgn:2000248",
        "tgn:7029392"
    ],
    "tgn:id":2757433,
    "tgn:name":"West Beaver Creek",
    "tgn:placetype":[
        "aat:300008706"
    ]
},
  "bbox": [],
  "geometry": {"coordinates":[-108.2167,37.8333],"type":"Point"}
}