{
  "id": 1132941,
  "type": "Feature",
  "properties": {
    "tgn:hierarchy":[
        "tgn:1132941",
        "tgn:1000001",
        "tgn:7012149",
        "tgn:1003017",
        "tgn:7007710",
        "tgn:7029392"
    ],
    "tgn:id":1132941,
    "tgn:name":"Crabtree Creek",
    "tgn:placetype":[
        "aat:300008706"
    ]
},
  "bbox": [],
  "geometry": {"coordinates":[-79.5167,40.3667],"type":"Point"}
}