{
  "id": 2541768,
  "type": "Feature",
  "properties": {
    "tgn:hierarchy":[
        "tgn:2541768",
        "tgn:1000001",
        "tgn:7012149",
        "tgn:7007923",
        "tgn:7029392"
    ],
    "tgn:id":2541768,
    "tgn:name":"Ninemile Creek",
    "tgn:placetype":[
        "aat:300008706"
    ]
},
  "bbox": [],
  "geometry": {"coordinates":[-105.9167,43.55],"type":"Point"}
}