{
  "id": 7490150,
  "type": "Feature",
  "properties": {
    "tgn:hierarchy":[
        "tgn:7490150",
        "tgn:7001004",
        "tgn:1000004",
        "tgn:1000141",
        "tgn:7029392"
    ],
    "tgn:id":7490150,
    "tgn:name":"Daqiuyuan",
    "tgn:placetype":[
        "aat:300008347"
    ]
},
  "bbox": [],
  "geometry": {"coordinates":[120.566111,23.06],"type":"Point"}
}