{
  "id": 2456345,
  "type": "Feature",
  "properties": {
    "tgn:hierarchy":[
        "tgn:2456345",
        "tgn:1000001",
        "tgn:7012149",
        "tgn:7007157",
        "tgn:1002857",
        "tgn:7029392"
    ],
    "tgn:id":2456345,
    "tgn:name":"Little Horsethief Canyon",
    "tgn:placetype":[
        "aat:300008761"
    ]
},
  "bbox": [],
  "geometry": {"coordinates":[-117.4167,34.2833],"type":"Point"}
}