{
  "id": 2402870,
  "type": "Feature",
  "properties": {
    "tgn:hierarchy":[
        "tgn:2402870",
        "tgn:1000001",
        "tgn:7012149",
        "tgn:2000206",
        "tgn:7007158",
        "tgn:7029392"
    ],
    "tgn:id":2402870,
    "tgn:name":"Hotel Twin Reservoir",
    "tgn:placetype":[
        "aat:300006191"
    ]
},
  "bbox": [],
  "geometry": {"coordinates":[-107.95,39.0333],"type":"Point"}
}