<<<<<<< HEAD
{
  "id": 2402870,
  "type": "Feature",
  "properties": {
    "tgn:hierarchy":[
        "tgn:2402870",
        "tgn:1000001",
        "tgn:7012149",
        "tgn:2000206",
        "tgn:7007158",
        "tgn:7029392"
    ],
    "tgn:id":2402870,
    "tgn:name":"Hotel Twin Reservoir",
    "tgn:placetype":[
        "aat:300006191"
    ]
},
  "bbox": [],
  "geometry": {"coordinates":[-107.95,39.0333],"type":"Point"}
}
=======
{"geometry":{"type":"Point","coordinates":[-107.950000,39.033300]},"type":"Feature","properties":{"hierarchy":["tgn:2402870","tgn:1000001","tgn:7012149","tgn:2000206","tgn:7007158","tgn:7029392"],"placetype":["aat:300006191"],"id":2402870,"name:xx":"Hotel Twin Reservoir"}}
>>>>>>> 03f74aca74312dbeaf24d7e61306dd6a786dc3d0
