{
  "id": 7269797,
  "type": "Feature",
  "properties": {
    "tgn:hierarchy":[
        "tgn:7269797",
        "tgn:1000003",
        "tgn:7003632",
        "tgn:7016845",
        "tgn:7029392"
    ],
    "tgn:id":7269797,
    "tgn:name:nl":"Middelburgsche Brug",
    "tgn:placetype":[
        "aat:300007836"
    ]
},
  "bbox": [],
  "geometry": {"coordinates":[4.683333,52.05],"type":"Point"}
}