{
  "id": 2631414,
  "type": "Feature",
  "properties": {
    "tgn:hierarchy":[
        "tgn:2631414",
        "tgn:1000001",
        "tgn:7012149",
        "tgn:2002374",
        "tgn:7007923",
        "tgn:7029392"
    ],
    "tgn:id":2631414,
    "tgn:name":"Round Rock Reservoir",
    "tgn:placetype":[
        "aat:300006191"
    ]
},
  "bbox": [],
  "geometry": {"coordinates":[-106.7333,43.7667],"type":"Point"}
}