{
  "id": 7320868,
  "type": "Feature",
  "properties": {
    "tgn:hierarchy":[
        "tgn:7320868",
        "tgn:1001699",
        "tgn:1000049",
        "tgn:1000002",
        "tgn:7029392"
    ],
    "tgn:id":7320868,
    "tgn:name":"Cayo Blanco, Islote",
    "tgn:placetype":[
        "aat:300008791"
    ]
},
  "bbox": [],
  "geometry": {"coordinates":[-73.533333,-44.783333],"type":"Point"}
}