{
  "id": 7553493,
  "type": "Feature",
  "properties": {
    "tgn:hierarchy":[
        "tgn:7553493",
        "tgn:1000004",
        "tgn:1001869",
        "tgn:7000198",
        "tgn:7029392"
    ],
    "tgn:id":7553493,
    "tgn:name:en":"M\u0101shuri Creek",
    "tgn:placetype":[
        "aat:300008699"
    ]
},
  "bbox": [],
  "geometry": {"coordinates":[69.95,22.533333],"type":"Point"}
}