<<<<<<< HEAD
{
  "id": 2150311,
  "type": "Feature",
  "properties": {
    "tgn:hierarchy":[
        "tgn:2150311",
        "tgn:1000001",
        "tgn:7012149",
        "tgn:2000365",
        "tgn:7007248",
        "tgn:7029392"
    ],
    "tgn:id":2150311,
    "tgn:name":"Basil Lake",
    "tgn:placetype":[
        "aat:300006191"
    ]
},
  "bbox": [],
  "geometry": {"coordinates":[-83.2,33.3],"type":"Point"}
}
=======
{"geometry":{"type":"Point","coordinates":[-83.200000,33.300000]},"type":"Feature","properties":{"hierarchy":["tgn:2150311","tgn:1000001","tgn:7012149","tgn:2000365","tgn:7007248","tgn:7029392"],"placetype":["aat:300006191"],"id":2150311,"name:xx":"Basil Lake"}}
>>>>>>> 03f74aca74312dbeaf24d7e61306dd6a786dc3d0
