{
  "id": 2367406,
  "type": "Feature",
  "properties": {
    "tgn:hierarchy":[
        "tgn:2367406",
        "tgn:1000001",
        "tgn:7012149",
        "tgn:7007158",
        "tgn:2000246",
        "tgn:7029392"
    ],
    "tgn:id":2367406,
    "tgn:name":"Groundhog Creek",
    "tgn:placetype":[
        "aat:300008706"
    ]
},
  "bbox": [],
  "geometry": {"coordinates":[-106.6167,37.8667],"type":"Point"}
}