{
  "id": 7157563,
  "type": "Feature",
  "properties": {
    "tgn:hierarchy":[
        "tgn:7157563",
        "tgn:1000003",
        "tgn:7003689",
        "tgn:7000084",
        "tgn:7029392"
    ],
    "tgn:id":7157563,
    "tgn:name":"Kien-Berg",
    "tgn:placetype":[
        "aat:300008777"
    ]
},
  "bbox": [],
  "geometry": {"coordinates":[10.533333,50.55],"type":"Point"}
}