{
  "id": 2113844,
  "type": "Feature",
  "properties": {
    "tgn:hierarchy":[
        "tgn:2113844",
        "tgn:1000001",
        "tgn:7012149",
        "tgn:2002186",
        "tgn:7007919",
        "tgn:7029392"
    ],
    "tgn:id":2113844,
    "tgn:name":"Raphine",
    "tgn:placetype":[
        "aat:300008347"
    ]
},
  "bbox": [],
  "geometry": {"coordinates":[-79.2167,37.9333],"type":"Point"}
}