{
  "id": 7453842,
  "type": "Feature",
  "properties": {
    "tgn:hierarchy":[
        "tgn:7453842",
        "tgn:7002448",
        "tgn:7019217",
        "tgn:1000003",
        "tgn:7008591",
        "tgn:7029392"
    ],
    "tgn:id":7453842,
    "tgn:name:en":"Desertmartin",
    "tgn:placetype":[
        "aat:300008347"
    ]
},
  "bbox": [],
  "geometry": {"coordinates":[-6.683333,54.766667],"type":"Point"}
}