{
  "id": 2523962,
  "type": "Feature",
  "properties": {
    "tgn:hierarchy":[
        "tgn:2523962",
        "tgn:1000001",
        "tgn:7012149",
        "tgn:7007157",
        "tgn:1002858",
        "tgn:7029392"
    ],
    "tgn:id":2523962,
    "tgn:name":"Morena Reservoir",
    "tgn:placetype":[
        "aat:300006191"
    ]
},
  "bbox": [],
  "geometry": {"coordinates":[-116.5333,32.6833],"type":"Point"}
}