{
  "id": 2468903,
  "type": "Feature",
  "properties": {
    "tgn:hierarchy":[
        "tgn:2468903",
        "tgn:1000001",
        "tgn:1002225",
        "tgn:7012149",
        "tgn:7007710",
        "tgn:7029392"
    ],
    "tgn:id":2468903,
    "tgn:name":"Long Run",
    "tgn:placetype":[
        "aat:300008347"
    ]
},
  "bbox": [],
  "geometry": {"coordinates":[-78.8167,40.65],"type":"Point"}
}