<<<<<<< HEAD
{
  "id": 2768944,
  "type": "Feature",
  "properties": {
    "tgn:hierarchy":[
        "tgn:2768944",
        "tgn:1000001",
        "tgn:7012149",
        "tgn:1002999",
        "tgn:7007526",
        "tgn:7029392"
    ],
    "tgn:id":2768944,
    "tgn:name":"Whitney Spring",
    "tgn:placetype":[
        "aat:300008697"
    ]
},
  "bbox": [],
  "geometry": {"coordinates":[-119.8833,39.8],"type":"Point"}
}
=======
{"geometry":{"type":"Point","coordinates":[-119.883300,39.800000]},"type":"Feature","properties":{"hierarchy":["tgn:2768944","tgn:1000001","tgn:7012149","tgn:1002999","tgn:7007526","tgn:7029392"],"placetype":["aat:300008697"],"id":2768944,"name:xx":"Whitney Spring"}}
>>>>>>> 03f74aca74312dbeaf24d7e61306dd6a786dc3d0
