{
  "id": 2771314,
  "type": "Feature",
  "properties": {
    "tgn:hierarchy":[
        "tgn:2771314",
        "tgn:1000001",
        "tgn:1002480",
        "tgn:7012149",
        "tgn:7007564",
        "tgn:7029392"
    ],
    "tgn:id":2771314,
    "tgn:name":"Wilder",
    "tgn:placetype":[
        "aat:300008347"
    ]
},
  "bbox": [],
  "geometry": {"coordinates":[-71.9167,42.7833],"type":"Point"}
}