{
  "id": 2734121,
  "type": "Feature",
  "properties": {
    "tgn:hierarchy":[
        "tgn:2734121",
        "tgn:1000001",
        "tgn:7012149",
        "tgn:2001503",
        "tgn:7007709",
        "tgn:7029392"
    ],
    "tgn:id":2734121,
    "tgn:name":"Turnpike Creek",
    "tgn:placetype":[
        "aat:300008706"
    ]
},
  "bbox": [],
  "geometry": {"coordinates":[-82.9167,35.3667],"type":"Point"}
}