{
  "id": 2172158,
  "type": "Feature",
  "properties": {
    "tgn:hierarchy":[
        "tgn:2172158",
        "tgn:1000001",
        "tgn:1002270",
        "tgn:7012149",
        "tgn:7007708",
        "tgn:7029392"
    ],
    "tgn:id":2172158,
    "tgn:name":"Bighorn Creek",
    "tgn:placetype":[
        "aat:300008706"
    ]
},
  "bbox": [],
  "geometry": {"coordinates":[-121.9167,45.2333],"type":"Point"}
}