<<<<<<< HEAD
{
  "id": 2763845,
  "type": "Feature",
  "properties": {
    "tgn:hierarchy":[
        "tgn:2763845",
        "tgn:1000001",
        "tgn:7012149",
        "tgn:2001304",
        "tgn:7007524",
        "tgn:7029392"
    ],
    "tgn:id":2763845,
    "tgn:name":"Wheatgrass Gulch",
    "tgn:placetype":[
        "aat:300008761"
    ]
},
  "bbox": [],
  "geometry": {"coordinates":[-115.5167,47.6167],"type":"Point"}
}
=======
{"geometry":{"type":"Point","coordinates":[-115.516700,47.616700]},"type":"Feature","properties":{"hierarchy":["tgn:2763845","tgn:1000001","tgn:7012149","tgn:2001304","tgn:7007524","tgn:7029392"],"placetype":["aat:300008761"],"id":2763845,"name:xx":"Wheatgrass Gulch"}}
>>>>>>> 03f74aca74312dbeaf24d7e61306dd6a786dc3d0
