{
  "id": 1061528,
  "type": "Feature",
  "properties": {
    "tgn:hierarchy":[
        "tgn:1061528",
        "tgn:1000004",
        "tgn:7011573",
        "tgn:7018214",
        "tgn:7002435",
        "tgn:7029392"
    ],
    "tgn:id":1061528,
    "tgn:name":"Zaoz'orje",
    "tgn:placetype":[
        "aat:300008347"
    ]
},
  "bbox": [],
  "geometry": {"coordinates":[38.0333,55.5667],"type":"Point"}
}