{
  "id": 7443086,
  "type": "Feature",
  "properties": {
    "tgn:hierarchy":[
        "tgn:7443086",
        "tgn:7002445",
        "tgn:1000003",
        "tgn:7011961",
        "tgn:7008591",
        "tgn:7029392"
    ],
    "tgn:id":7443086,
    "tgn:name:en":"Newton's Cove",
    "tgn:placetype":[
        "aat:300132317"
    ]
},
  "bbox": [],
  "geometry": {"coordinates":[-2.449444,50.604167],"type":"Point"}
}