{
  "id": 7576091,
  "type": "Feature",
  "properties": {
    "tgn:hierarchy":[
        "tgn:7576091",
        "tgn:1000004",
        "tgn:7000198",
        "tgn:1001894",
        "tgn:7029392"
    ],
    "tgn:id":7576091,
    "tgn:name:en":"L\u0101lburra",
    "tgn:placetype":[
        "aat:300008347"
    ]
},
  "bbox": [],
  "geometry": {"coordinates":[80.052526,21.943831],"type":"Point"}
}