{
  "id": 1050412,
  "type": "Feature",
  "properties": {
    "tgn:hierarchy":[
        "tgn:1050412",
        "tgn:7002444",
        "tgn:1000003",
        "tgn:7009907",
        "tgn:7008591",
        "tgn:1009121",
        "tgn:7029392"
    ],
    "tgn:id":1050412,
    "tgn:name":"Balfour",
    "tgn:placetype":[
        "aat:300008347"
    ]
},
  "bbox": [],
  "geometry": {"coordinates":[-2.9167,59.0333],"type":"Point"}
}