{
  "id": 7277914,
  "type": "Feature",
  "properties": {
    "tgn:hierarchy":[
        "tgn:7277914",
        "tgn:1001768",
        "tgn:1000049",
        "tgn:1000002",
        "tgn:7029392"
    ],
    "tgn:id":7277914,
    "tgn:name":"Vegas del Negro",
    "tgn:placetype":[
        "aat:300055621"
    ]
},
  "bbox": [],
  "geometry": {"coordinates":[-70.466667,-32.35],"type":"Point"}
}