{
  "id": 7511466,
  "type": "Feature",
  "properties": {
    "tgn:hierarchy":[
        "tgn:7511466",
        "tgn:1009227",
        "tgn:7001866",
        "tgn:1000226",
        "tgn:1000006",
        "tgn:7029392"
    ],
    "tgn:id":7511466,
    "tgn:name:en":"Maryburn",
    "tgn:placetype":[
        "aat:300000206"
    ]
},
  "bbox": [],
  "geometry": {"coordinates":[170.316667,-44.183333],"type":"Point"}
}