{
  "id": 2320766,
  "type": "Feature",
  "properties": {
    "tgn:hierarchy":[
        "tgn:2320766",
        "tgn:1000001",
        "tgn:7012149",
        "tgn:2000380",
        "tgn:7007248",
        "tgn:7029392"
    ],
    "tgn:id":2320766,
    "tgn:name":"Experiment Shoal",
    "tgn:placetype":[
        "aat:300132348"
    ]
},
  "bbox": [],
  "geometry": {"coordinates":[-81.15,31.5333],"type":"Point"}
}