{
  "id": 2483790,
  "type": "Feature",
  "properties": {
    "tgn:hierarchy":[
        "tgn:2483790",
        "tgn:1000001",
        "tgn:7016172",
        "tgn:7012149",
        "tgn:2000132",
        "tgn:7029392"
    ],
    "tgn:id":2483790,
    "tgn:name":"Lateral Number 5A",
    "tgn:placetype":[
        "aat:300006075"
    ]
},
  "bbox": [],
  "geometry": {"coordinates":[-90.7667,36.15],"type":"Point"}
}