{
  "id": 7303851,
  "type": "Feature",
  "properties": {
    "tgn:hierarchy":[
        "tgn:7303851",
        "tgn:7008911",
        "tgn:1000003",
        "tgn:7002763",
        "tgn:1000095",
        "tgn:7029392"
    ],
    "tgn:id":7303851,
    "tgn:name":"Oballo",
    "tgn:placetype":[
        "aat:300008347"
    ]
},
  "bbox": [],
  "geometry": {"coordinates":[-6.65,43.066667],"type":"Point"}
}