{
  "id": 7590650,
  "type": "Feature",
  "properties": {
    "tgn:hierarchy":[
        "tgn:7590650",
        "tgn:1000004",
        "tgn:7000198",
        "tgn:7000799",
        "tgn:7029392"
    ],
    "tgn:id":7590650,
    "tgn:name:en":"S\u0101rwa",
    "tgn:placetype":[
        "aat:300008347"
    ]
},
  "bbox": [],
  "geometry": {"coordinates":[74.966818,32.531464],"type":"Point"}
}