{
  "id": 1130566,
  "type": "Feature",
  "properties": {
    "tgn:hierarchy":[
        "tgn:1130566",
        "tgn:1000001",
        "tgn:7012149",
        "tgn:7007521",
        "tgn:7029392"
    ],
    "tgn:id":1130566,
    "tgn:name":"Tamarac",
    "tgn:placetype":[
        "aat:300008707"
    ]
},
  "bbox": [],
  "geometry": {"coordinates":[-94.2667,48.1333],"type":"Point"}
}