{
  "id": 2239853,
  "type": "Feature",
  "properties": {
    "tgn:hierarchy":[
        "tgn:2239853",
        "tgn:1000001",
        "tgn:7012149",
        "tgn:2001284",
        "tgn:7007524",
        "tgn:7029392"
    ],
    "tgn:id":2239853,
    "tgn:name":"Cigarette Creek",
    "tgn:placetype":[
        "aat:300008706"
    ]
},
  "bbox": [],
  "geometry": {"coordinates":[-112.8333,47.35],"type":"Point"}
}