{
  "id": 7199978,
  "type": "Feature",
  "properties": {
    "tgn:hierarchy":[
        "tgn:7199978",
        "tgn:7003669",
        "tgn:1000003",
        "tgn:7000084",
        "tgn:7029392"
    ],
    "tgn:id":7199978,
    "tgn:name":"Edenstrass",
    "tgn:placetype":[
        "aat:300000206"
    ]
},
  "bbox": [],
  "geometry": {"coordinates":[12.616667,48.083333],"type":"Point"}
}