{
  "id": 2742551,
  "type": "Feature",
  "properties": {
    "tgn:hierarchy":[
        "tgn:2742551",
        "tgn:1000001",
        "tgn:7006451",
        "tgn:7012149",
        "tgn:2000097",
        "tgn:7029392"
    ],
    "tgn:id":2742551,
    "tgn:name":"Valley View",
    "tgn:placetype":[
        "aat:300008347"
    ]
},
  "bbox": [],
  "geometry": {"coordinates":[-112.0667,33.65],"type":"Point"}
}