{
  "id": 2705005,
  "type": "Feature",
  "properties": {
    "tgn:hierarchy":[
        "tgn:2705005",
        "tgn:1000001",
        "tgn:7012149",
        "tgn:7022542",
        "tgn:7007825",
        "tgn:7029392"
    ],
    "tgn:id":2705005,
    "tgn:name":"Sunset View",
    "tgn:placetype":[
        "aat:300008347"
    ]
},
  "bbox": [],
  "geometry": {"coordinates":[-84.5667,35.4167],"type":"Point"}
}