{
  "id": 7442714,
  "type": "Feature",
  "properties": {
    "tgn:hierarchy":[
        "tgn:7442714",
        "tgn:7002445",
        "tgn:1000003",
        "tgn:7008185",
        "tgn:7008591",
        "tgn:7029392"
    ],
    "tgn:id":7442714,
    "tgn:name:en":"Walpole",
    "tgn:placetype":[
        "aat:300008347"
    ]
},
  "bbox": [],
  "geometry": {"coordinates":[1.483333,52.316667],"type":"Point"}
}