{
  "id": 2676889,
  "type": "Feature",
  "properties": {
    "tgn:hierarchy":[
        "tgn:2676889",
        "tgn:1000001",
        "tgn:7012149",
        "tgn:7029392"
    ],
    "tgn:id":2676889,
    "tgn:name":"South Branch Grummit Canyon Creek",
    "tgn:placetype":[
        "aat:300008706"
    ]
},
  "bbox": [],
  "geometry": {"coordinates":[-104.0833,44.6833],"type":"Point"}
}