{
  "id": 1028431,
  "type": "Feature",
  "properties": {
    "tgn:hierarchy":[
        "tgn:1028431",
        "tgn:7002445",
        "tgn:1000003",
        "tgn:7008154",
        "tgn:7008591",
        "tgn:7029392"
    ],
    "tgn:id":1028431,
    "tgn:name:en":"Baxenden",
    "tgn:placetype":[
        "aat:300008347"
    ]
},
  "bbox": [],
  "geometry": {"coordinates":[-2.35,53.733333],"type":"Point"}
}