{
  "id": 7077440,
  "type": "Feature",
  "properties": {
    "tgn:hierarchy":[
        "tgn:7077440",
        "tgn:1000003",
        "tgn:7000094",
        "tgn:7000084",
        "tgn:7029392"
    ],
    "tgn:id":7077440,
    "tgn:name":"Neu Gaarz",
    "tgn:placetype":[
        "aat:300008347"
    ]
},
  "bbox": [],
  "geometry": {"coordinates":[11.633333,54.116667],"type":"Point"}
}