{
  "id": 2032457,
  "type": "Feature",
  "properties": {
    "tgn:hierarchy":[
        "tgn:2032457",
        "tgn:1000001",
        "tgn:7012149",
        "tgn:1002962",
        "tgn:7007252",
        "tgn:7029392"
    ],
    "tgn:id":2032457,
    "tgn:name":"Kitchel",
    "tgn:placetype":[
        "aat:300008347"
    ]
},
  "bbox": [],
  "geometry": {"coordinates":[-84.85,39.6667],"type":"Point"}
}