{
  "id": 7292726,
  "type": "Feature",
  "properties": {
    "tgn:hierarchy":[
        "tgn:7292726",
        "tgn:1001623",
        "tgn:1000049",
        "tgn:1000002",
        "tgn:7029392"
    ],
    "tgn:id":7292726,
    "tgn:name":"Expedici\u00f3n, Fiordo",
    "tgn:placetype":[
        "aat:300008676"
    ]
},
  "bbox": [],
  "geometry": {"coordinates":[-74.316667,-46.783333],"type":"Point"}
}