{
  "id": 7163916,
  "type": "Feature",
  "properties": {
    "tgn:hierarchy":[
        "tgn:7163916",
        "tgn:1000003",
        "tgn:7003685",
        "tgn:7000084",
        "tgn:7029392"
    ],
    "tgn:id":7163916,
    "tgn:name":"Hubertusburg",
    "tgn:placetype":[
        "aat:300008347"
    ]
},
  "bbox": [],
  "geometry": {"coordinates":[12.933333,51.283333],"type":"Point"}
}