{
  "id": 7231631,
  "type": "Feature",
  "properties": {
    "tgn:hierarchy":[
        "tgn:7231631",
        "tgn:7002741",
        "tgn:7017076",
        "tgn:1000003",
        "tgn:1000074",
        "tgn:7029392"
    ],
    "tgn:id":7231631,
    "tgn:name":"Kern\u00edtsa",
    "tgn:placetype":[
        "aat:300008347"
    ]
},
  "bbox": [],
  "geometry": {"coordinates":[22.216667,38.133333],"type":"Point"}
}