<<<<<<< HEAD
{
  "id": 2766731,
  "type": "Feature",
  "properties": {
    "tgn:hierarchy":[
        "tgn:2766731",
        "tgn:1000001",
        "tgn:7012149",
        "tgn:2001543",
        "tgn:7007709",
        "tgn:7029392"
    ],
    "tgn:id":2766731,
    "tgn:name":"White Oak Ridge",
    "tgn:placetype":[
        "aat:300266640"
    ]
},
  "bbox": [],
  "geometry": {"coordinates":[-83.55,35.5],"type":"Point"}
}
=======
{"geometry":{"type":"Point","coordinates":[-83.550000,35.500000]},"type":"Feature","properties":{"hierarchy":["tgn:2766731","tgn:1000001","tgn:7012149","tgn:2001543","tgn:7007709","tgn:7029392"],"placetype":["aat:300266640"],"id":2766731,"name:xx":"White Oak Ridge"}}
>>>>>>> 03f74aca74312dbeaf24d7e61306dd6a786dc3d0
