{
  "id": 7302958,
  "type": "Feature",
  "properties": {
    "tgn:hierarchy":[
        "tgn:7302958",
        "tgn:7002805",
        "tgn:7002758",
        "tgn:1000003",
        "tgn:1000095",
        "tgn:7029392"
    ],
    "tgn:id":7302958,
    "tgn:name":"Negra, Punta",
    "tgn:placetype":[
        "aat:300386846"
    ]
},
  "bbox": [],
  "geometry": {"coordinates":[-2.166667,36.716667],"type":"Point"}
}