{
  "id": 2551164,
  "type": "Feature",
  "properties": {
    "tgn:hierarchy":[
        "tgn:2551164",
        "tgn:1000001",
        "tgn:7016172",
        "tgn:7012149",
        "tgn:2000178",
        "tgn:7029392"
    ],
    "tgn:id":2551164,
    "tgn:name":"Nubbin Ridge",
    "tgn:placetype":[
        "aat:300266640"
    ]
},
  "bbox": [],
  "geometry": {"coordinates":[-91.2333,35.0833],"type":"Point"}
}