{
  "id": 1020040,
  "type": "Feature",
  "properties": {
    "tgn:hierarchy":[
        "tgn:1020040",
        "tgn:7006477",
        "tgn:1001376",
        "tgn:1000002",
        "tgn:7029392"
    ],
    "tgn:id":1020040,
    "tgn:name":"Villa Santa Rita de Catuna",
    "tgn:placetype":[
        "aat:300008347"
    ]
},
  "bbox": [],
  "geometry": {"coordinates":[-66.2167,-30.95],"type":"Point"}
}