{
  "id": 2027880,
  "type": "Feature",
  "properties": {
    "tgn:hierarchy":[
        "tgn:2027880",
        "tgn:1000001",
        "tgn:7012149",
        "tgn:1002643",
        "tgn:7007251",
        "tgn:7029392"
    ],
    "tgn:id":2027880,
    "tgn:name":"Forest City",
    "tgn:placetype":[
        "aat:300008347"
    ]
},
  "bbox": [],
  "geometry": {"coordinates":[-89.8167,40.3667],"type":"Point"}
}