{
  "id": 7193703,
  "type": "Feature",
  "properties": {
    "tgn:hierarchy":[
        "tgn:7193703",
        "tgn:1000003",
        "tgn:7003688",
        "tgn:7000084",
        "tgn:7029392"
    ],
    "tgn:id":7193703,
    "tgn:name":"Eversdorf",
    "tgn:placetype":[
        "aat:300008347"
    ]
},
  "bbox": [],
  "geometry": {"coordinates":[9.483333,53.983333],"type":"Point"}
}