{
  "id": 7222693,
  "type": "Feature",
  "properties": {
    "tgn:hierarchy":[
        "tgn:7222693",
        "tgn:7011167",
        "tgn:7001338",
        "tgn:1000003",
        "tgn:1000074",
        "tgn:7029392"
    ],
    "tgn:id":7222693,
    "tgn:name":"Plemon\u00e1ri, \u00c1kra",
    "tgn:placetype":[
        "aat:300008850"
    ]
},
  "bbox": [],
  "geometry": {"coordinates":[20.616667,37.85],"type":"Point"}
}