{
  "id": 7475271,
  "type": "Feature",
  "properties": {
    "tgn:hierarchy":[
        "tgn:7475271",
        "tgn:1000004",
        "tgn:7001014",
        "tgn:1000141",
        "tgn:7029392"
    ],
    "tgn:id":7475271,
    "tgn:name":"Sanhe Qiao",
    "tgn:placetype":[
        "aat:300007836"
    ]
},
  "bbox": [],
  "geometry": {"coordinates":[120.438913,23.671759],"type":"Point"}
}