{
  "id": 2565594,
  "type": "Feature",
  "properties": {
    "tgn:hierarchy":[
        "tgn:2565594",
        "tgn:1000001",
        "tgn:7012149",
        "tgn:2001312",
        "tgn:7007524",
        "tgn:7029392"
    ],
    "tgn:id":2565594,
    "tgn:name":"Paisley",
    "tgn:placetype":[
        "aat:300008347"
    ]
},
  "bbox": [],
  "geometry": {"coordinates":[-106.7167,48.2167],"type":"Point"}
}