{
  "id": 2546314,
  "type": "Feature",
  "properties": {
    "tgn:hierarchy":[
        "tgn:2546314",
        "tgn:1000001",
        "tgn:1002293",
        "tgn:7012149",
        "tgn:7007708",
        "tgn:7029392"
    ],
    "tgn:id":2546314,
    "tgn:name":"North Fork Green Timber Creek",
    "tgn:placetype":[
        "aat:300008706"
    ]
},
  "bbox": [],
  "geometry": {"coordinates":[-123.3333,45.7833],"type":"Point"}
}