{
  "id": 2073472,
  "type": "Feature",
  "properties": {
    "tgn:hierarchy":[
        "tgn:2073472",
        "tgn:1000001",
        "tgn:7012149",
        "tgn:2001505",
        "tgn:7007709",
        "tgn:7029392"
    ],
    "tgn:id":2073472,
    "tgn:name":"Arabia",
    "tgn:placetype":[
        "aat:300008347"
    ]
},
  "bbox": [],
  "geometry": {"coordinates":[-79.1167,34.95],"type":"Point"}
}