<<<<<<< HEAD
{
  "id": 7178235,
  "type": "Feature",
  "properties": {
    "tgn:hierarchy":[
        "tgn:7178235",
        "tgn:7003669",
        "tgn:1000003",
        "tgn:7000084",
        "tgn:7029392"
    ],
    "tgn:id":7178235,
    "tgn:name":"Handstauden",
    "tgn:placetype":[
        "aat:300008863"
    ]
},
  "bbox": [],
  "geometry": {"coordinates":[12.483333,49.966667],"type":"Point"}
}
=======
{"geometry":{"type":"Point","coordinates":[12.483333,49.966667]},"type":"Feature","properties":{"hierarchy":["tgn:7178235","tgn:7003669","tgn:1000003","tgn:7000084","tgn:7029392"],"placetype":["aat:300008863"],"id":7178235,"name:xx":"Handstauden"}}
>>>>>>> 03f74aca74312dbeaf24d7e61306dd6a786dc3d0
