{
  "id": 7273843,
  "type": "Feature",
  "properties": {
    "tgn:hierarchy":[
        "tgn:7273843",
        "tgn:1000003",
        "tgn:7003613",
        "tgn:7016845",
        "tgn:7029392"
    ],
    "tgn:id":7273843,
    "tgn:name:nl":"Warffumerlaag",
    "tgn:placetype":[
        "aat:300132350"
    ]
},
  "bbox": [],
  "geometry": {"coordinates":[6.566667,53.45],"type":"Point"}
}