<<<<<<< HEAD
{
  "id": 7173330,
  "type": "Feature",
  "properties": {
    "tgn:hierarchy":[
        "tgn:7173330",
        "tgn:1000003",
        "tgn:7003673",
        "tgn:7000084",
        "tgn:7029392"
    ],
    "tgn:id":7173330,
    "tgn:name":"Gr\u00fcnerdeich",
    "tgn:placetype":[
        "aat:300008347"
    ]
},
  "bbox": [],
  "geometry": {"coordinates":[10.2,53.4],"type":"Point"}
}
=======
{"geometry":{"type":"Point","coordinates":[10.200000,53.400000]},"type":"Feature","properties":{"hierarchy":["tgn:7173330","tgn:1000003","tgn:7003673","tgn:7000084","tgn:7029392"],"placetype":["aat:300008347"],"id":7173330,"name:xx":"Gr\u00fcnerdeich"}}
>>>>>>> 03f74aca74312dbeaf24d7e61306dd6a786dc3d0
