{
  "id": 1134952,
  "type": "Feature",
  "properties": {
    "tgn:hierarchy":[
        "tgn:1134952",
        "tgn:1002138",
        "tgn:1000001",
        "tgn:7012149",
        "tgn:7007157",
        "tgn:7029392"
    ],
    "tgn:id":1134952,
    "tgn:name":"Vallecitos Creek",
    "tgn:placetype":[
        "aat:300008706"
    ]
},
  "bbox": [],
  "geometry": {"coordinates":[-121.8167,37.6167],"type":"Point"}
}