{
  "id": 2652342,
  "type": "Feature",
  "properties": {
    "tgn:hierarchy":[
        "tgn:2652342",
        "tgn:1000001",
        "tgn:2001264",
        "tgn:7012149",
        "tgn:7007524",
        "tgn:7029392"
    ],
    "tgn:id":2652342,
    "tgn:name":"Senal Lake",
    "tgn:placetype":[
        "aat:300008680"
    ]
},
  "bbox": [],
  "geometry": {"coordinates":[-109.5667,45.1333],"type":"Point"}
}