{
  "id": 7564167,
  "type": "Feature",
  "properties": {
    "tgn:hierarchy":[
        "tgn:7564167",
        "tgn:1000004",
        "tgn:7000198",
        "tgn:7016788",
        "tgn:7029392"
    ],
    "tgn:id":7564167,
    "tgn:name:en":"Shivji ka Mandir",
    "tgn:placetype":[
        "aat:300007595"
    ]
},
  "bbox": [],
  "geometry": {"coordinates":[74.644718,28.367982],"type":"Point"}
}