{
  "id": 1098665,
  "type": "Feature",
  "properties": {
    "tgn:hierarchy":[
        "tgn:1098665",
        "tgn:7000490",
        "tgn:1000006",
        "tgn:7001831",
        "tgn:7029392"
    ],
    "tgn:id":1098665,
    "tgn:name":"Yinkanie",
    "tgn:placetype":[
        "aat:300008347"
    ]
},
  "bbox": [],
  "geometry": {"coordinates":[140.3167,-34.3333],"type":"Point"}
}