{
  "id": 2063700,
  "type": "Feature",
  "properties": {
    "tgn:hierarchy":[
        "tgn:2063700",
        "tgn:1000001",
        "tgn:2001424",
        "tgn:7012149",
        "tgn:7007564",
        "tgn:7029392"
    ],
    "tgn:id":2063700,
    "tgn:name":"Parker Hill",
    "tgn:placetype":[
        "aat:300008347",
        "aat:300387210"
    ]
},
  "bbox": [],
  "geometry": {"coordinates":[-71.95,44.25],"type":"Point"}
}