{
  "id": 2610956,
  "type": "Feature",
  "properties": {
    "tgn:hierarchy":[
        "tgn:2610956",
        "tgn:1000001",
        "tgn:7012149",
        "tgn:2001279",
        "tgn:7007524",
        "tgn:7029392"
    ],
    "tgn:id":2610956,
    "tgn:name":"Red Hill",
    "tgn:placetype":[
        "aat:300008798"
    ]
},
  "bbox": [],
  "geometry": {"coordinates":[-113.2833,46.35],"type":"Point"}
}