{
  "id": 7411795,
  "type": "Feature",
  "properties": {
    "tgn:hierarchy":[
        "tgn:7411795",
        "tgn:7005587",
        "tgn:1000001",
        "tgn:7005560",
        "tgn:7029392"
    ],
    "tgn:id":7411795,
    "tgn:name:es":"San Lorenzo Sayula",
    "tgn:placetype":[
        "aat:300008347"
    ]
},
  "bbox": [],
  "geometry": {"coordinates":[-98.295833,19.991667],"type":"Point"}
}