{
  "id": 2479611,
  "type": "Feature",
  "properties": {
    "tgn:hierarchy":[
        "tgn:2479611",
        "tgn:1000001",
        "tgn:7012149",
        "tgn:1002830",
        "tgn:7007826",
        "tgn:7029392"
    ],
    "tgn:id":2479611,
    "tgn:name":"Lake Branch",
    "tgn:placetype":[
        "aat:300008699"
    ]
},
  "bbox": [],
  "geometry": {"coordinates":[-96.3333,31.15],"type":"Point"}
}