{
  "id": 7041267,
  "type": "Feature",
  "properties": {
    "tgn:hierarchy":[
        "tgn:7041267",
        "tgn:7004595",
        "tgn:7003005",
        "tgn:1000003",
        "tgn:1000080",
        "tgn:7029392"
    ],
    "tgn:id":7041267,
    "tgn:name":"San Nicola, Torrente",
    "tgn:placetype":[
        "aat:300008699"
    ]
},
  "bbox": [],
  "geometry": {"coordinates":[14.783333,41.133333],"type":"Point"}
}