{
  "id": 7491193,
  "type": "Feature",
  "properties": {
    "tgn:hierarchy":[
        "tgn:7491193",
        "tgn:1000004",
        "tgn:7467799",
        "tgn:1000141",
        "tgn:7029392"
    ],
    "tgn:id":7491193,
    "tgn:name":"Darao",
    "tgn:placetype":[
        "aat:300008347"
    ]
},
  "bbox": [],
  "geometry": {"coordinates":[120.577703,23.937557],"type":"Point"}
}