{
  "id": 1007311,
  "type": "Feature",
  "properties": {
    "tgn:hierarchy":[
        "tgn:1007311",
        "tgn:1009907",
        "tgn:1000004",
        "tgn:1001174",
        "tgn:1000135",
        "tgn:7029392"
    ],
    "tgn:id":1007311,
    "tgn:name":"Guintinua Island",
    "tgn:placetype":[
        "aat:300008791"
    ]
},
  "bbox": [],
  "geometry": {"coordinates":[122.85,14.4333],"type":"Point"}
}