<<<<<<< HEAD
{
  "id": 2159056,
  "type": "Feature",
  "properties": {
    "tgn:hierarchy":[
        "tgn:2159056",
        "tgn:1000001",
        "tgn:7012149",
        "tgn:7007568",
        "tgn:7029392"
    ],
    "tgn:id":2159056,
    "tgn:name":"Bed Hollow",
    "tgn:placetype":[
        "aat:300008761"
    ]
},
  "bbox": [],
  "geometry": {"coordinates":[-74.4667,42.25],"type":"Point"}
}
=======
{"geometry":{"type":"Point","coordinates":[-74.466700,42.250000]},"type":"Feature","properties":{"hierarchy":["tgn:2159056","tgn:1000001","tgn:7012149","tgn:7007568","tgn:7029392"],"placetype":["aat:300008761"],"id":2159056,"name:xx":"Bed Hollow"}}
>>>>>>> 03f74aca74312dbeaf24d7e61306dd6a786dc3d0
