{
  "id": 2159056,
  "type": "Feature",
  "properties": {
    "tgn:hierarchy":[
        "tgn:2159056",
        "tgn:1000001",
        "tgn:7012149",
        "tgn:7007568",
        "tgn:7029392"
    ],
    "tgn:id":2159056,
    "tgn:name":"Bed Hollow",
    "tgn:placetype":[
        "aat:300008761"
    ]
},
  "bbox": [],
  "geometry": {"coordinates":[-74.4667,42.25],"type":"Point"}
}