{
  "id": 7219511,
  "type": "Feature",
  "properties": {
    "tgn:hierarchy":[
        "tgn:7219511",
        "tgn:7002724",
        "tgn:7002715",
        "tgn:1000003",
        "tgn:1000074",
        "tgn:7029392"
    ],
    "tgn:id":7219511,
    "tgn:name":"Vl\u00e1sti",
    "tgn:placetype":[
        "aat:300008347"
    ]
},
  "bbox": [],
  "geometry": {"coordinates":[21.516667,40.45],"type":"Point"}
}