{
  "id": 7547439,
  "type": "Feature",
  "properties": {
    "tgn:hierarchy":[
        "tgn:7547439",
        "tgn:1000004",
        "tgn:7018318",
        "tgn:7000198",
        "tgn:7029392"
    ],
    "tgn:id":7547439,
    "tgn:name:en":"Aguada, Enseada da",
    "tgn:placetype":[
        "aat:300132316"
    ]
},
  "bbox": [],
  "geometry": {"coordinates":[73.766667,15.466667],"type":"Point"}
}