{
  "id": 7479524,
  "type": "Feature",
  "properties": {
    "tgn:hierarchy":[
        "tgn:7479524",
        "tgn:1000004",
        "tgn:7001013",
        "tgn:1000141",
        "tgn:7029392"
    ],
    "tgn:id":7479524,
    "tgn:name":"Zhongyang Daxue",
    "tgn:placetype":[
        "aat:300006610"
    ]
},
  "bbox": [],
  "geometry": {"coordinates":[121.1925,24.968056],"type":"Point"}
}