<<<<<<< HEAD
{
  "id": 7479524,
  "type": "Feature",
  "properties": {
    "tgn:hierarchy":[
        "tgn:7479524",
        "tgn:1000004",
        "tgn:7001013",
        "tgn:1000141",
        "tgn:7029392"
    ],
    "tgn:id":7479524,
    "tgn:name":"Zhongyang Daxue",
    "tgn:placetype":[
        "aat:300006610"
    ]
},
  "bbox": [],
  "geometry": {"coordinates":[121.1925,24.968056],"type":"Point"}
}
=======
{"geometry":{"type":"Point","coordinates":[121.192500,24.968056]},"type":"Feature","properties":{"hierarchy":["tgn:7479524","tgn:1000004","tgn:7001013","tgn:1000141","tgn:7029392"],"placetype":["aat:300006610"],"id":7479524,"name:xx":"Zhongyang Daxue"}}
>>>>>>> 03f74aca74312dbeaf24d7e61306dd6a786dc3d0
