{
  "id": 7341277,
  "type": "Feature",
  "properties": {
    "tgn:hierarchy":[
        "tgn:7341277",
        "tgn:7008911",
        "tgn:1000003",
        "tgn:7002763",
        "tgn:1000095",
        "tgn:7029392"
    ],
    "tgn:id":7341277,
    "tgn:name":"Bra\u00f1aseca",
    "tgn:placetype":[
        "aat:300008347"
    ]
},
  "bbox": [],
  "geometry": {"coordinates":[-6.25,43.516667],"type":"Point"}
}