{
  "id": 2705068,
  "type": "Feature",
  "properties": {
    "tgn:hierarchy":[
        "tgn:2705068",
        "tgn:1000001",
        "tgn:7012149",
        "tgn:2002092",
        "tgn:7007826",
        "tgn:7029392"
    ],
    "tgn:id":2705068,
    "tgn:name":"Sunshine Hill",
    "tgn:placetype":[
        "aat:300008798"
    ]
},
  "bbox": [],
  "geometry": {"coordinates":[-98.7833,34.05],"type":"Point"}
}