{
  "id": 2169172,
  "type": "Feature",
  "properties": {
    "tgn:hierarchy":[
        "tgn:2169172",
        "tgn:1000001",
        "tgn:2001746",
        "tgn:7012149",
        "tgn:7007712",
        "tgn:7029392"
    ],
    "tgn:id":2169172,
    "tgn:name":"Big Kilsock Bay",
    "tgn:placetype":[
        "aat:300008905"
    ]
},
  "bbox": [],
  "geometry": {"coordinates":[-79.3833,33.2833],"type":"Point"}
}