{
  "id": 7160136,
  "type": "Feature",
  "properties": {
    "tgn:hierarchy":[
        "tgn:7160136",
        "tgn:7003692",
        "tgn:1000003",
        "tgn:7000084",
        "tgn:7029392"
    ],
    "tgn:id":7160136,
    "tgn:name":"H\u00f6fen",
    "tgn:placetype":[
        "aat:300008347"
    ]
},
  "bbox": [],
  "geometry": {"coordinates":[7.95,48.25],"type":"Point"}
}