{
  "id": 2239906,
  "type": "Feature",
  "properties": {
    "tgn:hierarchy":[
        "tgn:2239906",
        "tgn:1000001",
        "tgn:2001432",
        "tgn:7012149",
        "tgn:7007566",
        "tgn:7029392"
    ],
    "tgn:id":2239906,
    "tgn:name":"Cimarroncito Reservoir",
    "tgn:placetype":[
        "aat:300006191"
    ]
},
  "bbox": [],
  "geometry": {"coordinates":[-105.05,36.4667],"type":"Point"}
}