{
  "id": 1041397,
  "type": "Feature",
  "properties": {
    "tgn:hierarchy":[
        "tgn:1041397",
        "tgn:7003692",
        "tgn:1000003",
        "tgn:7000084",
        "tgn:7029392"
    ],
    "tgn:id":1041397,
    "tgn:name":"Tengen",
    "tgn:placetype":[
        "aat:300008347"
    ]
},
  "bbox": [],
  "geometry": {"coordinates":[8.666667,47.816667],"type":"Point"}
}