{
  "id": 7560979,
  "type": "Feature",
  "properties": {
    "tgn:hierarchy":[
        "tgn:7560979",
        "tgn:1000004",
        "tgn:7000198",
        "tgn:7016722",
        "tgn:7029392"
    ],
    "tgn:id":7560979,
    "tgn:name:en":"All\u0101hpur",
    "tgn:placetype":[
        "aat:300008347"
    ]
},
  "bbox": [],
  "geometry": {"coordinates":[79.620117,27.550815],"type":"Point"}
}