{
  "id": 2511281,
  "type": "Feature",
  "properties": {
    "tgn:hierarchy":[
        "tgn:2511281",
        "tgn:2002142",
        "tgn:1000001",
        "tgn:7012149",
        "tgn:7007919",
        "tgn:7029392"
    ],
    "tgn:id":2511281,
    "tgn:name":"Mikes Knob",
    "tgn:placetype":[
        "aat:300008798"
    ]
},
  "bbox": [],
  "geometry": {"coordinates":[-78.8333,38.0833],"type":"Point"}
}