{
  "id": 2768755,
  "type": "Feature",
  "properties": {
    "tgn:hierarchy":[
        "tgn:2768755",
        "tgn:7006450",
        "tgn:1000001",
        "tgn:2124076",
        "tgn:7012149",
        "tgn:7029392"
    ],
    "tgn:id":2768755,
    "tgn:name":"Whitman Lake",
    "tgn:placetype":[
        "aat:300008680"
    ]
},
  "bbox": [],
  "geometry": {"coordinates":[-131.5333,55.3333],"type":"Point"}
}