<<<<<<< HEAD
{
  "id": 7484645,
  "type": "Feature",
  "properties": {
    "tgn:hierarchy":[
        "tgn:7484645",
        "tgn:1000004",
        "tgn:7492971",
        "tgn:1000141",
        "tgn:7029392"
    ],
    "tgn:id":7484645,
    "tgn:name":"Cidewucun",
    "tgn:placetype":[
        "aat:300008347"
    ]
},
  "bbox": [],
  "geometry": {"coordinates":[120.519167,22.449444],"type":"Point"}
}
=======
{"geometry":{"type":"Point","coordinates":[120.519167,22.449444]},"type":"Feature","properties":{"hierarchy":["tgn:7484645","tgn:1000004","tgn:7492971","tgn:1000141","tgn:7029392"],"placetype":["aat:300008347"],"id":7484645,"name:xx":"Cidewucun"}}
>>>>>>> 03f74aca74312dbeaf24d7e61306dd6a786dc3d0
