{
  "id": 2029027,
  "type": "Feature",
  "properties": {
    "tgn:hierarchy":[
        "tgn:2029027",
        "tgn:1000001",
        "tgn:7019013",
        "tgn:7012149",
        "tgn:7007251",
        "tgn:7029392"
    ],
    "tgn:id":2029027,
    "tgn:name":"Medinah",
    "tgn:placetype":[
        "aat:300008347"
    ]
},
  "bbox": [],
  "geometry": {"coordinates":[-88.05,41.9667],"type":"Point"}
}