{
  "id": 7421725,
  "type": "Feature",
  "properties": {
    "tgn:hierarchy":[
        "tgn:7421725",
        "tgn:1000001",
        "tgn:7005601",
        "tgn:7005560",
        "tgn:7029392"
    ],
    "tgn:id":7421725,
    "tgn:name":"Palos Altos",
    "tgn:placetype":[
        "aat:300008347"
    ]
},
  "bbox": [],
  "geometry": {"coordinates":[-103.366667,22.583333],"type":"Point"}
}