{
  "id": 2508287,
  "type": "Feature",
  "properties": {
    "tgn:hierarchy":[
        "tgn:2508287",
        "tgn:1000001",
        "tgn:7012149",
        "tgn:2001709",
        "tgn:7007708",
        "tgn:7029392"
    ],
    "tgn:id":2508287,
    "tgn:name":"Middle Butler Reservoir",
    "tgn:placetype":[
        "aat:300006191"
    ]
},
  "bbox": [],
  "geometry": {"coordinates":[-119.1167,43.0167],"type":"Point"}
}