{
  "id": 7249944,
  "type": "Feature",
  "properties": {
    "tgn:hierarchy":[
        "tgn:7249944",
        "tgn:7003460",
        "tgn:1000003",
        "tgn:1000063",
        "tgn:4012014",
        "tgn:7029392"
    ],
    "tgn:id":7249944,
    "tgn:name":"Pair",
    "tgn:placetype":[
        "aat:300008347"
    ]
},
  "bbox": [],
  "geometry": {"coordinates":[5.401662,50.44121],"type":"Point"}
}