{
  "id": 2035002,
  "type": "Feature",
  "properties": {
    "tgn:hierarchy":[
        "tgn:2035002",
        "tgn:1000001",
        "tgn:7019178",
        "tgn:7012149",
        "tgn:7007253",
        "tgn:7029392"
    ],
    "tgn:id":2035002,
    "tgn:name":"Jamison",
    "tgn:placetype":[
        "aat:300008347"
    ]
},
  "bbox": [],
  "geometry": {"coordinates":[-93.7167,41.1167],"type":"Point"}
}