{
  "id": 2523712,
  "type": "Feature",
  "properties": {
    "tgn:hierarchy":[
        "tgn:2523712",
        "tgn:1000001",
        "tgn:2001431",
        "tgn:7012149",
        "tgn:7007566",
        "tgn:7029392"
    ],
    "tgn:id":2523712,
    "tgn:name":"Moquino",
    "tgn:placetype":[
        "aat:300008347"
    ]
},
  "bbox": [],
  "geometry": {"coordinates":[-107.3667,35.1667],"type":"Point"}
}