{
  "id": 7412688,
  "type": "Feature",
  "properties": {
    "tgn:hierarchy":[
        "tgn:7412688",
        "tgn:7005587",
        "tgn:1000001",
        "tgn:7005560",
        "tgn:7029392"
    ],
    "tgn:id":7412688,
    "tgn:name:es":"Estaci\u00f3n Tolteca",
    "tgn:placetype":[
        "aat:300007783"
    ]
},
  "bbox": [],
  "geometry": {"coordinates":[-99.3375,20.023611],"type":"Point"}
}