{
  "id": 7582319,
  "type": "Feature",
  "properties": {
    "tgn:hierarchy":[
        "tgn:7582319",
        "tgn:1000004",
        "tgn:7000198",
        "tgn:7016722",
        "tgn:7029392"
    ],
    "tgn:id":7582319,
    "tgn:name:en":"Barora",
    "tgn:placetype":[
        "aat:300008347"
    ]
},
  "bbox": [],
  "geometry": {"coordinates":[78.416872,24.82515],"type":"Point"}
}