{
  "id": 2717445,
  "type": "Feature",
  "properties": {
    "tgn:hierarchy":[
        "tgn:2717445",
        "tgn:1000001",
        "tgn:7012149",
        "tgn:7007157",
        "tgn:2000185",
        "tgn:7029392"
    ],
    "tgn:id":2717445,
    "tgn:name":"Thistle Spring",
    "tgn:placetype":[
        "aat:300008697"
    ]
},
  "bbox": [],
  "geometry": {"coordinates":[-123.0833,39.8833],"type":"Point"}
}