{
  "id": 7139395,
  "type": "Feature",
  "properties": {
    "tgn:hierarchy":[
        "tgn:7139395",
        "tgn:1000003",
        "tgn:7003688",
        "tgn:7000084",
        "tgn:7029392"
    ],
    "tgn:id":7139395,
    "tgn:name":"Lein-Berg",
    "tgn:placetype":[
        "aat:300008777"
    ]
},
  "bbox": [],
  "geometry": {"coordinates":[9.633333,54.033333],"type":"Point"}
}