{
  "id": 7515070,
  "type": "Feature",
  "properties": {
    "tgn:hierarchy":[
        "tgn:7515070",
        "tgn:1009227",
        "tgn:1000226",
        "tgn:7016822",
        "tgn:1000006",
        "tgn:7029392"
    ],
    "tgn:id":7515070,
    "tgn:name:en":"Camp Creek",
    "tgn:placetype":[
        "aat:300008699"
    ]
},
  "bbox": [],
  "geometry": {"coordinates":[167.666667,-46.166667],"type":"Point"}
}