{
  "id": 2511310,
  "type": "Feature",
  "properties": {
    "tgn:hierarchy":[
        "tgn:2511310",
        "tgn:1000001",
        "tgn:7012149",
        "tgn:2001437",
        "tgn:7007566",
        "tgn:7029392"
    ],
    "tgn:id":2511310,
    "tgn:name":"Mikes Tank",
    "tgn:placetype":[
        "aat:300006191"
    ]
},
  "bbox": [],
  "geometry": {"coordinates":[-108.4833,32.95],"type":"Point"}
}