<<<<<<< HEAD
{
  "id": 2336140,
  "type": "Feature",
  "properties": {
    "tgn:hierarchy":[
        "tgn:2336140",
        "tgn:1000001",
        "tgn:7012149",
        "tgn:7007157",
        "tgn:2000191",
        "tgn:7029392"
    ],
    "tgn:id":2336140,
    "tgn:name":"Foster Lake",
    "tgn:placetype":[
        "aat:300008680"
    ]
},
  "bbox": [],
  "geometry": {"coordinates":[-122.85,41.0333],"type":"Point"}
}
=======
{"geometry":{"type":"Point","coordinates":[-122.850000,41.033300]},"type":"Feature","properties":{"hierarchy":["tgn:2336140","tgn:1000001","tgn:7012149","tgn:7007157","tgn:2000191","tgn:7029392"],"placetype":["aat:300008680"],"id":2336140,"name:xx":"Foster Lake"}}
>>>>>>> 03f74aca74312dbeaf24d7e61306dd6a786dc3d0
