{
  "id": 7524533,
  "type": "Feature",
  "properties": {
    "tgn:hierarchy":[
        "tgn:7524533",
        "tgn:7001242",
        "tgn:7016833",
        "tgn:1001079",
        "tgn:7029392"
    ],
    "tgn:id":7524533,
    "tgn:name:en":"B\u016bgh\u0101z, Mamarr al",
    "tgn:placetype":[
        "aat:300008713"
    ]
},
  "bbox": [],
  "geometry": {"coordinates":[29.821944,31.178611],"type":"Point"}
}