{
  "id": 7389093,
  "type": "Feature",
  "properties": {
    "tgn:hierarchy":[
        "tgn:7389093",
        "tgn:7005583",
        "tgn:1000001",
        "tgn:7005560",
        "tgn:7029392"
    ],
    "tgn:id":7389093,
    "tgn:name":"Quelites, Sierra de",
    "tgn:placetype":[
        "aat:300008795"
    ]
},
  "bbox": [],
  "geometry": {"coordinates":[-103.15,24.616667],"type":"Point"}
}