{
  "id": 1095211,
  "type": "Feature",
  "properties": {
    "tgn:hierarchy":[
        "tgn:1095211",
        "tgn:7001242",
        "tgn:7016833",
        "tgn:1001114",
        "tgn:7029392"
    ],
    "tgn:id":1095211,
    "tgn:name":"Al \u02bbIzz\u012byah",
    "tgn:placetype":[
        "aat:300008347"
    ]
},
  "bbox": [],
  "geometry": {"coordinates":[30.989949,27.221163],"type":"Point"}
}