<<<<<<< HEAD
{
  "id": 2407485,
  "type": "Feature",
  "properties": {
    "tgn:hierarchy":[
        "tgn:2407485",
        "tgn:1000001",
        "tgn:2001740",
        "tgn:7012149",
        "tgn:7007712",
        "tgn:7029392"
    ],
    "tgn:id":2407485,
    "tgn:name":"Hunts Crossroads",
    "tgn:placetype":[
        "aat:300008347"
    ]
},
  "bbox": [],
  "geometry": {"coordinates":[-80.0333,34.4167],"type":"Point"}
}
=======
{"geometry":{"type":"Point","coordinates":[-80.033300,34.416700]},"type":"Feature","properties":{"hierarchy":["tgn:2407485","tgn:1000001","tgn:2001740","tgn:7012149","tgn:7007712","tgn:7029392"],"placetype":["aat:300008347"],"id":2407485,"name:xx":"Hunts Crossroads"}}
>>>>>>> 03f74aca74312dbeaf24d7e61306dd6a786dc3d0
