{
  "id": 2114349,
  "type": "Feature",
  "properties": {
    "tgn:hierarchy":[
        "tgn:2114349",
        "tgn:1000001",
        "tgn:7012149",
        "tgn:2002159",
        "tgn:7007919",
        "tgn:7029392"
    ],
    "tgn:id":2114349,
    "tgn:name":"Stage Junction",
    "tgn:placetype":[
        "aat:300008347",
        "aat:300387210"
    ]
},
  "bbox": [],
  "geometry": {"coordinates":[-78.15,37.7833],"type":"Point"}
}