<<<<<<< HEAD
{
  "id": 7489536,
  "type": "Feature",
  "properties": {
    "tgn:hierarchy":[
        "tgn:7489536",
        "tgn:7001004",
        "tgn:1000004",
        "tgn:1000141",
        "tgn:7029392"
    ],
    "tgn:id":7489536,
    "tgn:name":"Renwu",
    "tgn:placetype":[
        "aat:300008347"
    ]
},
  "bbox": [],
  "geometry": {"coordinates":[120.3434,22.701346],"type":"Point"}
}
=======
{"geometry":{"type":"Point","coordinates":[120.343400,22.701346]},"type":"Feature","properties":{"hierarchy":["tgn:7489536","tgn:7001004","tgn:1000004","tgn:1000141","tgn:7029392"],"placetype":["aat:300008347"],"id":7489536,"name:xx":"Renwu"}}
>>>>>>> 03f74aca74312dbeaf24d7e61306dd6a786dc3d0
