<<<<<<< HEAD
{
  "id": 2256326,
  "type": "Feature",
  "properties": {
    "tgn:hierarchy":[
        "tgn:2256326",
        "tgn:7002659",
        "tgn:1000001",
        "tgn:2000004",
        "tgn:7012149",
        "tgn:7029392"
    ],
    "tgn:id":2256326,
    "tgn:name":"Coppers Branch",
    "tgn:placetype":[
        "aat:300008699"
    ]
},
  "bbox": [],
  "geometry": {"coordinates":[-86.6167,34.0833],"type":"Point"}
}
=======
{"geometry":{"type":"Point","coordinates":[-86.616700,34.083300]},"type":"Feature","properties":{"hierarchy":["tgn:2256326","tgn:7002659","tgn:1000001","tgn:2000004","tgn:7012149","tgn:7029392"],"placetype":["aat:300008699"],"id":2256326,"name:xx":"Coppers Branch"}}
>>>>>>> 03f74aca74312dbeaf24d7e61306dd6a786dc3d0
