{
  "id": 2371193,
  "type": "Feature",
  "properties": {
    "tgn:hierarchy":[
        "tgn:2371193",
        "tgn:1000001",
        "tgn:7012149",
        "tgn:1002994",
        "tgn:7007708",
        "tgn:7029392"
    ],
    "tgn:id":2371193,
    "tgn:name":"Hagerty Ridge",
    "tgn:placetype":[
        "aat:300266640"
    ]
},
  "bbox": [],
  "geometry": {"coordinates":[-123.2833,45.4333],"type":"Point"}
}