{
  "id": 2187530,
  "type": "Feature",
  "properties": {
    "tgn:hierarchy":[
        "tgn:2187530",
        "tgn:1000001",
        "tgn:7012149",
        "tgn:7013941",
        "tgn:7007568",
        "tgn:7029392"
    ],
    "tgn:id":2187530,
    "tgn:name":"Boot Bay",
    "tgn:placetype":[
        "aat:300132316"
    ]
},
  "bbox": [],
  "geometry": {"coordinates":[-74.2167,44.2833],"type":"Point"}
}