{
  "id": 7306965,
  "type": "Feature",
  "properties": {
    "tgn:hierarchy":[
        "tgn:7306965",
        "tgn:7002805",
        "tgn:7002758",
        "tgn:1000003",
        "tgn:1000095",
        "tgn:7029392"
    ],
    "tgn:id":7306965,
    "tgn:name":"Los Nietos de Campo Hermoso",
    "tgn:placetype":[
        "aat:300008347"
    ]
},
  "bbox": [],
  "geometry": {"coordinates":[-2.166667,36.883333],"type":"Point"}
}