{
  "id": 7590068,
  "type": "Feature",
  "properties": {
    "tgn:hierarchy":[
        "tgn:7590068",
        "tgn:1000004",
        "tgn:7000198",
        "tgn:7016722",
        "tgn:7029392"
    ],
    "tgn:id":7590068,
    "tgn:name:en":"Bisangarh",
    "tgn:placetype":[
        "aat:300008347"
    ]
},
  "bbox": [],
  "geometry": {"coordinates":[77.16765,29.783936],"type":"Point"}
}