{
  "id": 7438011,
  "type": "Feature",
  "properties": {
    "tgn:hierarchy":[
        "tgn:7438011",
        "tgn:7005581",
        "tgn:1000001",
        "tgn:7005560",
        "tgn:7029392"
    ],
    "tgn:id":7438011,
    "tgn:name":"Tambor, Sierra del",
    "tgn:placetype":[
        "aat:300008795"
    ]
},
  "bbox": [],
  "geometry": {"coordinates":[-106.366667,28.483333],"type":"Point"}
}