{
  "id": 2540615,
  "type": "Feature",
  "properties": {
    "tgn:hierarchy":[
        "tgn:2540615",
        "tgn:1000001",
        "tgn:7012149",
        "tgn:1002564",
        "tgn:7007710",
        "tgn:7029392"
    ],
    "tgn:id":2540615,
    "tgn:name":"Newton Lake",
    "tgn:placetype":[
        "aat:300008680"
    ]
},
  "bbox": [],
  "geometry": {"coordinates":[-75.5333,41.6167],"type":"Point"}
}