{
  "id": 2158765,
  "type": "Feature",
  "properties": {
    "tgn:hierarchy":[
        "tgn:2158765",
        "tgn:1000001",
        "tgn:7012149",
        "tgn:1002496",
        "tgn:7007252",
        "tgn:7029392"
    ],
    "tgn:id":2158765,
    "tgn:name":"Beck Ditch",
    "tgn:placetype":[
        "aat:300006075"
    ]
},
  "bbox": [],
  "geometry": {"coordinates":[-85.45,40.9333],"type":"Point"}
}