<<<<<<< HEAD
{
  "id": 2158765,
  "type": "Feature",
  "properties": {
    "tgn:hierarchy":[
        "tgn:2158765",
        "tgn:1000001",
        "tgn:7012149",
        "tgn:1002496",
        "tgn:7007252",
        "tgn:7029392"
    ],
    "tgn:id":2158765,
    "tgn:name":"Beck Ditch",
    "tgn:placetype":[
        "aat:300006075"
    ]
},
  "bbox": [],
  "geometry": {"coordinates":[-85.45,40.9333],"type":"Point"}
}
=======
{"geometry":{"type":"Point","coordinates":[-85.450000,40.933300]},"type":"Feature","properties":{"hierarchy":["tgn:2158765","tgn:1000001","tgn:7012149","tgn:1002496","tgn:7007252","tgn:7029392"],"placetype":["aat:300006075"],"id":2158765,"name:xx":"Beck Ditch"}}
>>>>>>> 03f74aca74312dbeaf24d7e61306dd6a786dc3d0
