{
  "id": 1073675,
  "type": "Feature",
  "properties": {
    "tgn:hierarchy":[
        "tgn:1073675",
        "tgn:1000004",
        "tgn:7002086",
        "tgn:1000111",
        "tgn:7029392"
    ],
    "tgn:id":1073675,
    "tgn:name":"Youyu",
    "tgn:placetype":[
        "aat:300008347"
    ]
},
  "bbox": [],
  "geometry": {"coordinates":[112.5333,40.15],"type":"Point"}
}