{
  "id": 7414707,
  "type": "Feature",
  "properties": {
    "tgn:hierarchy":[
        "tgn:7414707",
        "tgn:7005584",
        "tgn:1000001",
        "tgn:7005560",
        "tgn:7029392"
    ],
    "tgn:id":7414707,
    "tgn:name":"Salitrillo",
    "tgn:placetype":[
        "aat:300008347"
    ]
},
  "bbox": [],
  "geometry": {"coordinates":[-101.91,20.413333],"type":"Point"}
}