{
  "id": 2774790,
  "type": "Feature",
  "properties": {
    "tgn:hierarchy":[
        "tgn:2774790",
        "tgn:1000001",
        "tgn:7006451",
        "tgn:7012149",
        "tgn:2000097",
        "tgn:7029392"
    ],
    "tgn:id":2774790,
    "tgn:name":"Willow Spring Mountain",
    "tgn:placetype":[
        "aat:300008798"
    ]
},
  "bbox": [],
  "geometry": {"coordinates":[-111.7833,33.9667],"type":"Point"}
}