{
  "id": 7339343,
  "type": "Feature",
  "properties": {
    "tgn:hierarchy":[
        "tgn:7339343",
        "tgn:7002759",
        "tgn:7002843",
        "tgn:1000003",
        "tgn:1000095",
        "tgn:7029392"
    ],
    "tgn:id":7339343,
    "tgn:name":"Cretas",
    "tgn:placetype":[
        "aat:300008347"
    ]
},
  "bbox": [],
  "geometry": {"coordinates":[0.216667,40.933333],"type":"Point"}
}