{
  "id": 7115103,
  "type": "Feature",
  "properties": {
    "tgn:hierarchy":[
        "tgn:7115103",
        "tgn:1000003",
        "tgn:7003688",
        "tgn:7000084",
        "tgn:7029392"
    ],
    "tgn:id":7115103,
    "tgn:name":"Oldendorf",
    "tgn:placetype":[
        "aat:300008347"
    ]
},
  "bbox": [],
  "geometry": {"coordinates":[9.45,53.95],"type":"Point"}
}