{
  "id": 2498513,
  "type": "Feature",
  "properties": {
    "tgn:hierarchy":[
        "tgn:2498513",
        "tgn:1000001",
        "tgn:2001703",
        "tgn:7012149",
        "tgn:7007708",
        "tgn:7029392"
    ],
    "tgn:id":2498513,
    "tgn:name":"McAllister Creek",
    "tgn:placetype":[
        "aat:300008706"
    ]
},
  "bbox": [],
  "geometry": {"coordinates":[-120.3667,44.4333],"type":"Point"}
}