{
  "id": 7120047,
  "type": "Feature",
  "properties": {
    "tgn:hierarchy":[
        "tgn:7120047",
        "tgn:1000003",
        "tgn:7000094",
        "tgn:7000084",
        "tgn:7029392"
    ],
    "tgn:id":7120047,
    "tgn:name":"Pfenningshorst",
    "tgn:placetype":[
        "aat:300008347"
    ]
},
  "bbox": [],
  "geometry": {"coordinates":[14.05,53.683333],"type":"Point"}
}