{
  "id": 2396109,
  "type": "Feature",
  "properties": {
    "tgn:hierarchy":[
        "tgn:2396109",
        "tgn:1000001",
        "tgn:7012149",
        "tgn:1002511",
        "tgn:7007919",
        "tgn:7029392"
    ],
    "tgn:id":2396109,
    "tgn:name":"Hollybrook",
    "tgn:placetype":[
        "aat:300008347"
    ]
},
  "bbox": [],
  "geometry": {"coordinates":[-76.7333,37.2333],"type":"Point"}
}