{
  "id": 7426784,
  "type": "Feature",
  "properties": {
    "tgn:hierarchy":[
        "tgn:7426784",
        "tgn:1000001",
        "tgn:7005594",
        "tgn:7005560",
        "tgn:7029392"
    ],
    "tgn:id":7426784,
    "tgn:name":"Don Benjam\u00edn",
    "tgn:placetype":[
        "aat:300008347"
    ]
},
  "bbox": [],
  "geometry": {"coordinates":[-101.35,22.966667],"type":"Point"}
}