{
  "id": 1089828,
  "type": "Feature",
  "properties": {
    "tgn:hierarchy":[
        "tgn:1089828",
        "tgn:7001242",
        "tgn:1001308",
        "tgn:7000489",
        "tgn:7029392"
    ],
    "tgn:id":1089828,
    "tgn:name":"Gor\u0113",
    "tgn:placetype":[
        "aat:300008347",
        "aat:300387220"
    ]
},
  "bbox": [],
  "geometry": {"coordinates":[35.4833,8.1667],"type":"Point"}
}