{
  "id": 2657755,
  "type": "Feature",
  "properties": {
    "tgn:hierarchy":[
        "tgn:2657755",
        "tgn:1000001",
        "tgn:7012149",
        "tgn:2001272",
        "tgn:7007524",
        "tgn:7029392"
    ],
    "tgn:id":2657755,
    "tgn:name":"Shell Butte",
    "tgn:placetype":[
        "aat:300008798"
    ]
},
  "bbox": [],
  "geometry": {"coordinates":[-104.2333,46.6167],"type":"Point"}
}