{
  "id": 7251947,
  "type": "Feature",
  "properties": {
    "tgn:hierarchy":[
        "tgn:7251947",
        "tgn:7018239",
        "tgn:1000003",
        "tgn:1000063",
        "tgn:7018236",
        "tgn:7029392"
    ],
    "tgn:id":7251947,
    "tgn:name":"Meer",
    "tgn:placetype":[
        "aat:300008347"
    ]
},
  "bbox": [],
  "geometry": {"coordinates":[4.819979,50.786971],"type":"Point"}
}