{
  "id": 7563579,
  "type": "Feature",
  "properties": {
    "tgn:hierarchy":[
        "tgn:7563579",
        "tgn:1000004",
        "tgn:7000198",
        "tgn:7016722",
        "tgn:7029392"
    ],
    "tgn:id":7563579,
    "tgn:name:en":"Bhiw\u0101n Minor",
    "tgn:placetype":[
        "aat:300006075"
    ]
},
  "bbox": [],
  "geometry": {"coordinates":[79.994254,26.585462],"type":"Point"}
}