{
  "id": 7290215,
  "type": "Feature",
  "properties": {
    "tgn:hierarchy":[
        "tgn:7290215",
        "tgn:1001702",
        "tgn:1000049",
        "tgn:1000002",
        "tgn:7029392"
    ],
    "tgn:id":7290215,
    "tgn:name":"Drummond Hay, Isla",
    "tgn:placetype":[
        "aat:300008791"
    ]
},
  "bbox": [],
  "geometry": {"coordinates":[-74.866667,-50.266667],"type":"Point"}
}