{
  "id": 1045018,
  "type": "Feature",
  "properties": {
    "tgn:hierarchy":[
        "tgn:1045018",
        "tgn:7003158",
        "tgn:1000003",
        "tgn:7003124",
        "tgn:1000080",
        "tgn:7029392"
    ],
    "tgn:id":1045018,
    "tgn:name":"Lardaro",
    "tgn:placetype":[
        "aat:300008347"
    ]
},
  "bbox": [],
  "geometry": {"coordinates":[10.65,45.966667],"type":"Point"}
}