{
  "id": 1072059,
  "type": "Feature",
  "properties": {
    "tgn:hierarchy":[
        "tgn:1072059",
        "tgn:1000004",
        "tgn:7002087",
        "tgn:1000111",
        "tgn:7029392"
    ],
    "tgn:id":1072059,
    "tgn:name":"Taihe",
    "tgn:placetype":[
        "aat:300008347"
    ]
},
  "bbox": [],
  "geometry": {"coordinates":[106.0667,30.1333],"type":"Point"}
}