{
  "id": 2584929,
  "type": "Feature",
  "properties": {
    "tgn:hierarchy":[
        "tgn:2584929",
        "tgn:1000001",
        "tgn:7012149",
        "tgn:2001251",
        "tgn:7007523",
        "tgn:7029392"
    ],
    "tgn:id":2584929,
    "tgn:name":"Pinnacle",
    "tgn:placetype":[
        "aat:300008798"
    ]
},
  "bbox": [],
  "geometry": {"coordinates":[-92.7667,36.7167],"type":"Point"}
}