{
  "id": 2291305,
  "type": "Feature",
  "properties": {
    "tgn:hierarchy":[
        "tgn:2291305",
        "tgn:1000001",
        "tgn:7012149",
        "tgn:7022542",
        "tgn:7007825",
        "tgn:7029392"
    ],
    "tgn:id":2291305,
    "tgn:name":"Dogwood Hollow",
    "tgn:placetype":[
        "aat:300008761"
    ]
},
  "bbox": [],
  "geometry": {"coordinates":[-84.6833,35.35],"type":"Point"}
}