{
  "id": 7583565,
  "type": "Feature",
  "properties": {
    "tgn:hierarchy":[
        "tgn:7583565",
        "tgn:1000004",
        "tgn:7000198",
        "tgn:1001894",
        "tgn:7029392"
    ],
    "tgn:id":7583565,
    "tgn:name:en":"L\u0101iganj",
    "tgn:placetype":[
        "aat:300008347"
    ]
},
  "bbox": [],
  "geometry": {"coordinates":[75.660843,24.544998],"type":"Point"}
}