<<<<<<< HEAD
{
  "id": 2258796,
  "type": "Feature",
  "properties": {
    "tgn:hierarchy":[
        "tgn:2258796",
        "tgn:1000001",
        "tgn:7012149",
        "tgn:7007157",
        "tgn:1002621",
        "tgn:7029392"
    ],
    "tgn:id":2258796,
    "tgn:name":"Cottonwood Creek",
    "tgn:placetype":[
        "aat:300008706"
    ]
},
  "bbox": [],
  "geometry": {"coordinates":[-119.9,37.05],"type":"Point"}
}
=======
{"geometry":{"type":"Point","coordinates":[-119.900000,37.050000]},"type":"Feature","properties":{"hierarchy":["tgn:2258796","tgn:1000001","tgn:7012149","tgn:7007157","tgn:1002621","tgn:7029392"],"placetype":["aat:300008706"],"id":2258796,"name:xx":"Cottonwood Creek"}}
>>>>>>> 03f74aca74312dbeaf24d7e61306dd6a786dc3d0
