{
  "id": 2136637,
  "type": "Feature",
  "properties": {
    "tgn:hierarchy":[
        "tgn:2136637",
        "tgn:1000001",
        "tgn:7012149",
        "tgn:7007157",
        "tgn:1002828",
        "tgn:7029392"
    ],
    "tgn:id":2136637,
    "tgn:name":"Arcilla",
    "tgn:placetype":[
        "aat:300008347"
    ]
},
  "bbox": [],
  "geometry": {"coordinates":[-117.4667,33.7833],"type":"Point"}
}