{
  "id": 2709683,
  "type": "Feature",
  "properties": {
    "tgn:hierarchy":[
        "tgn:2709683",
        "tgn:1000001",
        "tgn:7012149",
        "tgn:2000964",
        "tgn:7007520",
        "tgn:7029392"
    ],
    "tgn:id":2709683,
    "tgn:name":"Taft Drain",
    "tgn:placetype":[
        "aat:300006075"
    ]
},
  "bbox": [],
  "geometry": {"coordinates":[-83.0833,43.9667],"type":"Point"}
}