{
  "id": 7039129,
  "type": "Feature",
  "properties": {
    "tgn:hierarchy":[
        "tgn:7039129",
        "tgn:7009084",
        "tgn:7004154",
        "tgn:1000003",
        "tgn:1000080",
        "tgn:7029392"
    ],
    "tgn:id":7039129,
    "tgn:name":"Simbrivio, Fiume",
    "tgn:placetype":[
        "aat:300008699"
    ]
},
  "bbox": [],
  "geometry": {"coordinates":[13.183333,41.866667],"type":"Point"}
}