{
  "id": 2357538,
  "type": "Feature",
  "properties": {
    "tgn:hierarchy":[
        "tgn:2357538",
        "tgn:1000001",
        "tgn:2000261",
        "tgn:7012149",
        "tgn:7007240",
        "tgn:7029392"
    ],
    "tgn:id":2357538,
    "tgn:name":"Governors Creek",
    "tgn:placetype":[
        "aat:300008706"
    ]
},
  "bbox": [],
  "geometry": {"coordinates":[-81.7167,29.9167],"type":"Point"}
}