{
  "id": 7278050,
  "type": "Feature",
  "properties": {
    "tgn:hierarchy":[
        "tgn:7278050",
        "tgn:1001623",
        "tgn:1000049",
        "tgn:1000002",
        "tgn:7029392"
    ],
    "tgn:id":7278050,
    "tgn:name":"Waller, Isla",
    "tgn:placetype":[
        "aat:300008791"
    ]
},
  "bbox": [],
  "geometry": {"coordinates":[-75.266667,-46.766667],"type":"Point"}
}