{
  "id": 2373601,
  "type": "Feature",
  "properties": {
    "tgn:hierarchy":[
        "tgn:2373601",
        "tgn:1000001",
        "tgn:7012149",
        "tgn:2001254",
        "tgn:7007523",
        "tgn:7029392"
    ],
    "tgn:id":2373601,
    "tgn:name":"Hamilton Cave",
    "tgn:placetype":[
        "aat:300008746"
    ]
},
  "bbox": [],
  "geometry": {"coordinates":[-91.0667,38.1667],"type":"Point"}
}