{
  "id": 1094798,
  "type": "Feature",
  "properties": {
    "tgn:hierarchy":[
        "tgn:1094798",
        "tgn:7001242",
        "tgn:1001685",
        "tgn:1000203",
        "tgn:7029392"
    ],
    "tgn:id":1094798,
    "tgn:name":"Njombe",
    "tgn:placetype":[
        "aat:300008347"
    ]
},
  "bbox": [],
  "geometry": {"coordinates":[34.7833,-9.3333],"type":"Point"}
}