{
  "id": 7207927,
  "type": "Feature",
  "properties": {
    "tgn:hierarchy":[
        "tgn:7207927",
        "tgn:7003692",
        "tgn:1000003",
        "tgn:7000084",
        "tgn:7029392"
    ],
    "tgn:id":7207927,
    "tgn:name":"Conweiler",
    "tgn:placetype":[
        "aat:300008347"
    ]
},
  "bbox": [],
  "geometry": {"coordinates":[8.533333,48.85],"type":"Point"}
}