<<<<<<< HEAD
{
  "id": 2339771,
  "type": "Feature",
  "properties": {
    "tgn:hierarchy":[
        "tgn:2339771",
        "tgn:1000001",
        "tgn:2001777",
        "tgn:7012149",
        "tgn:7007713",
        "tgn:7029392"
    ],
    "tgn:id":2339771,
    "tgn:name":"Freeland Lake",
    "tgn:placetype":[
        "aat:300008905"
    ]
},
  "bbox": [],
  "geometry": {"coordinates":[-98.8667,43.6],"type":"Point"}
}
=======
{"geometry":{"type":"Point","coordinates":[-98.866700,43.600000]},"type":"Feature","properties":{"hierarchy":["tgn:2339771","tgn:1000001","tgn:2001777","tgn:7012149","tgn:7007713","tgn:7029392"],"placetype":["aat:300008905"],"id":2339771,"name:xx":"Freeland Lake"}}
>>>>>>> 03f74aca74312dbeaf24d7e61306dd6a786dc3d0
