{
  "id": 2148267,
  "type": "Feature",
  "properties": {
    "tgn:hierarchy":[
        "tgn:2148267",
        "tgn:1000001",
        "tgn:2001264",
        "tgn:7012149",
        "tgn:7007524",
        "tgn:7029392"
    ],
    "tgn:id":2148267,
    "tgn:name":"Barlow Creek",
    "tgn:placetype":[
        "aat:300008706"
    ]
},
  "bbox": [],
  "geometry": {"coordinates":[-109.4167,45.2333],"type":"Point"}
}