{
  "id": 7502924,
  "type": "Feature",
  "properties": {
    "tgn:hierarchy":[
        "tgn:7502924",
        "tgn:1000004",
        "tgn:7491221",
        "tgn:1000141",
        "tgn:7029392"
    ],
    "tgn:id":7502924,
    "tgn:name":"Dapo Guoxiao",
    "tgn:placetype":[
        "aat:300006495"
    ]
},
  "bbox": [],
  "geometry": {"coordinates":[121.231111,23.124722],"type":"Point"}
}