{
  "id": 2374213,
  "type": "Feature",
  "properties": {
    "tgn:hierarchy":[
        "tgn:2374213",
        "tgn:1000001",
        "tgn:7012149",
        "tgn:7007157",
        "tgn:1002863",
        "tgn:7029392"
    ],
    "tgn:id":2374213,
    "tgn:name":"Hammond Spring",
    "tgn:placetype":[
        "aat:300008697"
    ]
},
  "bbox": [],
  "geometry": {"coordinates":[-120.3333,35.7333],"type":"Point"}
}