{
  "id": 2443256,
  "type": "Feature",
  "properties": {
    "tgn:hierarchy":[
        "tgn:2443256",
        "tgn:7002659",
        "tgn:1000001",
        "tgn:7012149",
        "tgn:2000060",
        "tgn:7029392"
    ],
    "tgn:id":2443256,
    "tgn:name":"Kyser Leonard Lakefront Estates",
    "tgn:placetype":[
        "aat:300008347"
    ]
},
  "bbox": [],
  "geometry": {"coordinates":[-86.2333,33.4833],"type":"Point"}
}