<<<<<<< HEAD
{
  "id": 7110976,
  "type": "Feature",
  "properties": {
    "tgn:hierarchy":[
        "tgn:7110976",
        "tgn:7003692",
        "tgn:1000003",
        "tgn:7000084",
        "tgn:7029392"
    ],
    "tgn:id":7110976,
    "tgn:name":"Riedbach",
    "tgn:placetype":[
        "aat:300008699"
    ]
},
  "bbox": [],
  "geometry": {"coordinates":[9.033333,48.2],"type":"Point"}
}
=======
{"geometry":{"type":"Point","coordinates":[9.033333,48.200000]},"type":"Feature","properties":{"hierarchy":["tgn:7110976","tgn:7003692","tgn:1000003","tgn:7000084","tgn:7029392"],"placetype":["aat:300008699"],"id":7110976,"name:xx":"Riedbach"}}
>>>>>>> 03f74aca74312dbeaf24d7e61306dd6a786dc3d0
