{
  "id": 2583282,
  "type": "Feature",
  "properties": {
    "tgn:hierarchy":[
        "tgn:2583282",
        "tgn:2001422",
        "tgn:1000001",
        "tgn:7012149",
        "tgn:7007564",
        "tgn:7029392"
    ],
    "tgn:id":2583282,
    "tgn:name":"Pine Mountain",
    "tgn:placetype":[
        "aat:300008798"
    ]
},
  "bbox": [],
  "geometry": {"coordinates":[-71.2667,43.4667],"type":"Point"}
}