{
  "id": 7332524,
  "type": "Feature",
  "properties": {
    "tgn:hierarchy":[
        "tgn:7332524",
        "tgn:7008911",
        "tgn:1000003",
        "tgn:7002763",
        "tgn:1000095",
        "tgn:7029392"
    ],
    "tgn:id":7332524,
    "tgn:name":"La Arena",
    "tgn:placetype":[
        "aat:300008347"
    ]
},
  "bbox": [],
  "geometry": {"coordinates":[-6.071667,43.558611],"type":"Point"}
}