{
  "id": 2215280,
  "type": "Feature",
  "properties": {
    "tgn:hierarchy":[
        "tgn:2215280",
        "tgn:1000001",
        "tgn:7012149",
        "tgn:7014097",
        "tgn:7007158",
        "tgn:7029392"
    ],
    "tgn:id":2215280,
    "tgn:name":"Callahan Reservoir",
    "tgn:placetype":[
        "aat:300006191"
    ]
},
  "bbox": [],
  "geometry": {"coordinates":[-104.65,38.6333],"type":"Point"}
}