<<<<<<< HEAD
{
  "id": 2333219,
  "type": "Feature",
  "properties": {
    "tgn:hierarchy":[
        "tgn:2333219",
        "tgn:1000001",
        "tgn:7012149",
        "tgn:2002355",
        "tgn:7007922",
        "tgn:7029392"
    ],
    "tgn:id":2333219,
    "tgn:name":"Flynns Spring",
    "tgn:placetype":[
        "aat:300008697"
    ]
},
  "bbox": [],
  "geometry": {"coordinates":[-88.1167,43.65],"type":"Point"}
}
=======
{"geometry":{"type":"Point","coordinates":[-88.116700,43.650000]},"type":"Feature","properties":{"hierarchy":["tgn:2333219","tgn:1000001","tgn:7012149","tgn:2002355","tgn:7007922","tgn:7029392"],"placetype":["aat:300008697"],"id":2333219,"name:xx":"Flynns Spring"}}
>>>>>>> 03f74aca74312dbeaf24d7e61306dd6a786dc3d0
