{
  "id": 2787307,
  "type": "Feature",
  "properties": {
    "tgn:hierarchy":[
        "tgn:2787307",
        "tgn:1000001",
        "tgn:7006451",
        "tgn:2000095",
        "tgn:7012149",
        "tgn:7029392"
    ],
    "tgn:id":2787307,
    "tgn:name":"Zuni Basin",
    "tgn:placetype":[
        "aat:300386845"
    ]
},
  "bbox": [],
  "geometry": {"coordinates":[-109.1167,33.3833],"type":"Point"}
}