<<<<<<< HEAD
{
  "id": 7367054,
  "type": "Feature",
  "properties": {
    "tgn:hierarchy":[
        "tgn:7367054",
        "tgn:7005580",
        "tgn:1000001",
        "tgn:7005560",
        "tgn:7029392"
    ],
    "tgn:id":7367054,
    "tgn:name":"El Pictutal",
    "tgn:placetype":[
        "aat:300008347"
    ]
},
  "bbox": [],
  "geometry": {"coordinates":[-93.316667,16.716667],"type":"Point"}
}
=======
{"geometry":{"type":"Point","coordinates":[-93.316667,16.716667]},"type":"Feature","properties":{"hierarchy":["tgn:7367054","tgn:7005580","tgn:1000001","tgn:7005560","tgn:7029392"],"placetype":["aat:300008347"],"id":7367054,"name:xx":"El Pictutal"}}
>>>>>>> 03f74aca74312dbeaf24d7e61306dd6a786dc3d0
