{
  "id": 1076251,
  "type": "Feature",
  "properties": {
    "tgn:hierarchy":[
        "tgn:1076251",
        "tgn:1000004",
        "tgn:7000198",
        "tgn:1001905",
        "tgn:7029392"
    ],
    "tgn:id":1076251,
    "tgn:name:en":"Mokokch\u016bng",
    "tgn:placetype":[
        "aat:300008347"
    ]
},
  "bbox": [],
  "geometry": {"coordinates":[94.51834,26.324799],"type":"Point"}
}