{
  "id": 2583159,
  "type": "Feature",
  "properties": {
    "tgn:hierarchy":[
        "tgn:2583159",
        "tgn:1000001",
        "tgn:7012149",
        "tgn:2001442",
        "tgn:7007566",
        "tgn:7029392"
    ],
    "tgn:id":2583159,
    "tgn:name":"Pine Lodge",
    "tgn:placetype":[
        "aat:300000390"
    ]
},
  "bbox": [],
  "geometry": {"coordinates":[-105.6667,33.8333],"type":"Point"}
}