{
  "id": 7302574,
  "type": "Feature",
  "properties": {
    "tgn:hierarchy":[
        "tgn:7302574",
        "tgn:7002829",
        "tgn:1000003",
        "tgn:7002786",
        "tgn:1000095",
        "tgn:7029392"
    ],
    "tgn:id":7302574,
    "tgn:name":"Murias",
    "tgn:placetype":[
        "aat:300008347"
    ]
},
  "bbox": [],
  "geometry": {"coordinates":[-6.883333,42.933333],"type":"Point"}
}