{
  "id": 7011556,
  "type": "Feature",
  "properties": {
    "tgn:hierarchy":[
        "tgn:7011556",
        "tgn:7002445",
        "tgn:1000003",
        "tgn:7008153",
        "tgn:7008591",
        "tgn:7029392"
    ],
    "tgn:id":7011556,
    "tgn:name:en":"Folkestone",
    "tgn:placetype":[
        "aat:300008347",
        "aat:300387007",
        "aat:300008375",
        "aat:300387251",
        "aat:300120599",
        "aat:300387292"
    ]
},
  "bbox": [],
  "geometry": {"coordinates":[1.183333,51.083333],"type":"Point"}
}