{
  "id": 2428366,
  "type": "Feature",
  "properties": {
    "tgn:hierarchy":[
        "tgn:2428366",
        "tgn:1000001",
        "tgn:2001022",
        "tgn:7012149",
        "tgn:7007521",
        "tgn:7029392"
    ],
    "tgn:id":2428366,
    "tgn:name":"Judicial Ditch Number Twelve",
    "tgn:placetype":[
        "aat:300006075"
    ]
},
  "bbox": [],
  "geometry": {"coordinates":[-93.2333,43.75],"type":"Point"}
}