{
  "id": 2763599,
  "type": "Feature",
  "properties": {
    "tgn:hierarchy":[
        "tgn:2763599",
        "tgn:1000001",
        "tgn:2000924",
        "tgn:7012149",
        "tgn:7007515",
        "tgn:7029392"
    ],
    "tgn:id":2763599,
    "tgn:name":"Whaleback",
    "tgn:placetype":[
        "aat:300132348"
    ]
},
  "bbox": [],
  "geometry": {"coordinates":[-68.8667,43.8667],"type":"Point"}
}