<<<<<<< HEAD
{
  "id": 2763599,
  "type": "Feature",
  "properties": {
    "tgn:hierarchy":[
        "tgn:2763599",
        "tgn:1000001",
        "tgn:2000924",
        "tgn:7012149",
        "tgn:7007515",
        "tgn:7029392"
    ],
    "tgn:id":2763599,
    "tgn:name":"Whaleback",
    "tgn:placetype":[
        "aat:300132348"
    ]
},
  "bbox": [],
  "geometry": {"coordinates":[-68.8667,43.8667],"type":"Point"}
}
=======
{"geometry":{"type":"Point","coordinates":[-68.866700,43.866700]},"type":"Feature","properties":{"hierarchy":["tgn:2763599","tgn:1000001","tgn:2000924","tgn:7012149","tgn:7007515","tgn:7029392"],"placetype":["aat:300132348"],"id":2763599,"name:xx":"Whaleback"}}
>>>>>>> 03f74aca74312dbeaf24d7e61306dd6a786dc3d0
