{
  "id": 7027429,
  "type": "Feature",
  "properties": {
    "tgn:hierarchy":[
        "tgn:7027429",
        "tgn:7002758",
        "tgn:7002823",
        "tgn:1000003",
        "tgn:1000095",
        "tgn:7029392"
    ],
    "tgn:id":7027429,
    "tgn:name":"Almonaster la Real",
    "tgn:placetype":[
        "aat:300008347",
        "aat:300008372"
    ]
},
  "bbox": [],
  "geometry": {"coordinates":[-6.783333,37.866667],"type":"Point"}
}