<<<<<<< HEAD
{
  "id": 7027429,
  "type": "Feature",
  "properties": {
    "tgn:hierarchy":[
        "tgn:7027429",
        "tgn:7002758",
        "tgn:7002823",
        "tgn:1000003",
        "tgn:1000095",
        "tgn:7029392"
    ],
    "tgn:id":7027429,
    "tgn:name":"Almonaster la Real",
    "tgn:placetype":[
        "aat:300008347",
        "aat:300008372"
    ]
},
  "bbox": [],
  "geometry": {"coordinates":[-6.783333,37.866667],"type":"Point"}
}
=======
{"geometry":{"type":"Point","coordinates":[-6.783333,37.866667]},"type":"Feature","properties":{"hierarchy":["tgn:7027429","tgn:7002758","tgn:7002823","tgn:1000003","tgn:1000095","tgn:7029392"],"placetype":["aat:300008347","aat:300008372"],"id":7027429,"name:xx":"Almonaster la Real"}}
>>>>>>> 03f74aca74312dbeaf24d7e61306dd6a786dc3d0
