{
  "id": 7330691,
  "type": "Feature",
  "properties": {
    "tgn:hierarchy":[
        "tgn:7330691",
        "tgn:7002844",
        "tgn:7030216",
        "tgn:1000003",
        "tgn:1000095",
        "tgn:7029392"
    ],
    "tgn:id":7330691,
    "tgn:name":"Grosa, Punta",
    "tgn:placetype":[
        "aat:300386846"
    ]
},
  "bbox": [],
  "geometry": {"coordinates":[1.166667,41.05],"type":"Point"}
}