{
  "id": 7282196,
  "type": "Feature",
  "properties": {
    "tgn:hierarchy":[
        "tgn:7282196",
        "tgn:1001702",
        "tgn:1000049",
        "tgn:1000002",
        "tgn:7029392"
    ],
    "tgn:id":7282196,
    "tgn:name":"Sara",
    "tgn:placetype":[
        "aat:300000241"
    ]
},
  "bbox": [],
  "geometry": {"coordinates":[-69.333333,-52.733333],"type":"Point"}
}