{
  "id": 7125963,
  "type": "Feature",
  "properties": {
    "tgn:hierarchy":[
        "tgn:7125963",
        "tgn:1000003",
        "tgn:7003676",
        "tgn:7000084",
        "tgn:7029392"
    ],
    "tgn:id":7125963,
    "tgn:name":"Norder Nauens",
    "tgn:placetype":[
        "aat:300000206"
    ]
},
  "bbox": [],
  "geometry": {"coordinates":[7.983333,53.65],"type":"Point"}
}