{
  "id": 7269182,
  "type": "Feature",
  "properties": {
    "tgn:hierarchy":[
        "tgn:7269182",
        "tgn:1000003",
        "tgn:7003632",
        "tgn:7016845",
        "tgn:7029392"
    ],
    "tgn:id":7269182,
    "tgn:name:nl":"Oude Haven",
    "tgn:placetype":[
        "aat:300008699"
    ]
},
  "bbox": [],
  "geometry": {"coordinates":[4.116667,51.783333],"type":"Point"}
}