{
  "id": 2004285,
  "type": "Feature",
  "properties": {
    "tgn:hierarchy":[
        "tgn:2004285",
        "tgn:7002659",
        "tgn:1000001",
        "tgn:7012149",
        "tgn:2000038",
        "tgn:7029392"
    ],
    "tgn:id":2004285,
    "tgn:name":"Lovelace Crossroads",
    "tgn:placetype":[
        "aat:300008347"
    ]
},
  "bbox": [],
  "geometry": {"coordinates":[-87.75,34.85],"type":"Point"}
}