{
  "id": 7018050,
  "type": "Feature",
  "properties": {
    "tgn:hierarchy":[
        "tgn:7018050",
        "tgn:1000641",
        "tgn:1000002",
        "tgn:1000056",
        "tgn:7029392"
    ],
    "tgn:id":7018050,
    "tgn:name":"Nazca",
    "tgn:placetype":[
        "aat:300008347",
        "aat:300008375"
    ]
},
  "bbox": [],
  "geometry": {"coordinates":[-74.936625,-14.828651],"type":"Point"}
}