{
  "id": 7523277,
  "type": "Feature",
  "properties": {
    "tgn:hierarchy":[
        "tgn:7523277",
        "tgn:7001242",
        "tgn:7001311",
        "tgn:7016833",
        "tgn:7029392"
    ],
    "tgn:id":7523277,
    "tgn:name:en":"Durunk\u0101t, Jabal",
    "tgn:placetype":[
        "aat:300008795"
    ]
},
  "bbox": [],
  "geometry": {"coordinates":[34.764594,24.395242],"type":"Point"}
}