{
  "id": 7308000,
  "type": "Feature",
  "properties": {
    "tgn:hierarchy":[
        "tgn:7308000",
        "tgn:1001705",
        "tgn:1000049",
        "tgn:1000002",
        "tgn:7029392"
    ],
    "tgn:id":7308000,
    "tgn:name":"Molinos, Cerro",
    "tgn:placetype":[
        "aat:300008795"
    ]
},
  "bbox": [],
  "geometry": {"coordinates":[-72.583333,-35.95],"type":"Point"}
}