<<<<<<< HEAD
{
  "id": 2256867,
  "type": "Feature",
  "properties": {
    "tgn:hierarchy":[
        "tgn:2256867",
        "tgn:1000001",
        "tgn:7012149",
        "tgn:2002250",
        "tgn:7007920",
        "tgn:7029392"
    ],
    "tgn:id":2256867,
    "tgn:name":"Corkscrew Canyon",
    "tgn:placetype":[
        "aat:300008761"
    ]
},
  "bbox": [],
  "geometry": {"coordinates":[-118.3333,48.0167],"type":"Point"}
}
=======
{"geometry":{"type":"Point","coordinates":[-118.333300,48.016700]},"type":"Feature","properties":{"hierarchy":["tgn:2256867","tgn:1000001","tgn:7012149","tgn:2002250","tgn:7007920","tgn:7029392"],"placetype":["aat:300008761"],"id":2256867,"name:xx":"Corkscrew Canyon"}}
>>>>>>> 03f74aca74312dbeaf24d7e61306dd6a786dc3d0
