{
  "id": 2161473,
  "type": "Feature",
  "properties": {
    "tgn:hierarchy":[
        "tgn:2161473",
        "tgn:1000001",
        "tgn:7012149",
        "tgn:2001898",
        "tgn:7007825",
        "tgn:7029392"
    ],
    "tgn:id":2161473,
    "tgn:name":"Bell Spring",
    "tgn:placetype":[
        "aat:300008697"
    ]
},
  "bbox": [],
  "geometry": {"coordinates":[-84.4833,35.5333],"type":"Point"}
}