{
  "id": 2611624,
  "type": "Feature",
  "properties": {
    "tgn:hierarchy":[
        "tgn:2611624",
        "tgn:1000001",
        "tgn:7012149",
        "tgn:2001883",
        "tgn:7007825",
        "tgn:7029392"
    ],
    "tgn:id":2611624,
    "tgn:name":"Red Mountain",
    "tgn:placetype":[
        "aat:300008798"
    ]
},
  "bbox": [],
  "geometry": {"coordinates":[-83.8667,35.85],"type":"Point"}
}