{
  "id": 2725703,
  "type": "Feature",
  "properties": {
    "tgn:hierarchy":[
        "tgn:2725703",
        "tgn:7013349",
        "tgn:1000001",
        "tgn:7012149",
        "tgn:7007708",
        "tgn:7029392"
    ],
    "tgn:id":2725703,
    "tgn:name":"Torchlight Spring",
    "tgn:placetype":[
        "aat:300008697"
    ]
},
  "bbox": [],
  "geometry": {"coordinates":[-117.35,44.95],"type":"Point"}
}