{
  "id": 1110610,
  "type": "Feature",
  "properties": {
    "tgn:hierarchy":[
        "tgn:1110610",
        "tgn:1001945",
        "tgn:1000047",
        "tgn:7002457",
        "tgn:1000002",
        "tgn:7029392"
    ],
    "tgn:id":1110610,
    "tgn:name":"Taquaxiara, Serra da",
    "tgn:placetype":[
        "aat:300008777"
    ]
},
  "bbox": [],
  "geometry": {"coordinates":[-46.8667,-23.7667],"type":"Point"}
}