<<<<<<< HEAD
{
  "id": 7116894,
  "type": "Feature",
  "properties": {
    "tgn:hierarchy":[
        "tgn:7116894",
        "tgn:1000003",
        "tgn:7003676",
        "tgn:7000084",
        "tgn:7029392"
    ],
    "tgn:id":7116894,
    "tgn:name":"Ort-Berg",
    "tgn:placetype":[
        "aat:300008777"
    ]
},
  "bbox": [],
  "geometry": {"coordinates":[9.75,51.516667],"type":"Point"}
}
=======
{"geometry":{"type":"Point","coordinates":[9.750000,51.516667]},"type":"Feature","properties":{"hierarchy":["tgn:7116894","tgn:1000003","tgn:7003676","tgn:7000084","tgn:7029392"],"placetype":["aat:300008777"],"id":7116894,"name:xx":"Ort-Berg"}}
>>>>>>> 03f74aca74312dbeaf24d7e61306dd6a786dc3d0
