{
  "id": 1014101,
  "type": "Feature",
  "properties": {
    "tgn:hierarchy":[
        "tgn:1014101",
        "tgn:7005685",
        "tgn:1000001",
        "tgn:7005799",
        "tgn:7029392"
    ],
    "tgn:id":1014101,
    "tgn:name":"Petitcodiac",
    "tgn:placetype":[
        "aat:300008347"
    ]
},
  "bbox": [],
  "geometry": {"coordinates":[-65.1833,45.9167],"type":"Point"}
}