{
  "id": 1114267,
  "type": "Feature",
  "properties": {
    "tgn:hierarchy":[
        "tgn:1114267",
        "tgn:1000004",
        "tgn:1000105",
        "tgn:7029392"
    ],
    "tgn:id":1114267,
    "tgn:name":"Sh\u0101hb\u0101zpur",
    "tgn:placetype":[
        "aat:300008713"
    ]
},
  "bbox": [],
  "geometry": {"coordinates":[90.8333,22.0833],"type":"Point"}
}