{
  "id": 2127035,
  "type": "Feature",
  "properties": {
    "tgn:hierarchy":[
        "tgn:2127035",
        "tgn:1000001",
        "tgn:7012149",
        "tgn:1002798",
        "tgn:7007252",
        "tgn:7029392"
    ],
    "tgn:id":2127035,
    "tgn:name":"Ahlgrim Ditch",
    "tgn:placetype":[
        "aat:300006075"
    ]
},
  "bbox": [],
  "geometry": {"coordinates":[-87.0167,41.3667],"type":"Point"}
}