{
  "id": 2246586,
  "type": "Feature",
  "properties": {
    "tgn:hierarchy":[
        "tgn:2246586",
        "tgn:1000001",
        "tgn:7012149",
        "tgn:1003040",
        "tgn:7007568",
        "tgn:7029392"
    ],
    "tgn:id":2246586,
    "tgn:name":"Cobble Hill",
    "tgn:placetype":[
        "aat:300008798"
    ]
},
  "bbox": [],
  "geometry": {"coordinates":[-78.2833,42.7667],"type":"Point"}
}