{
  "id": 7517682,
  "type": "Feature",
  "properties": {
    "tgn:hierarchy":[
        "tgn:7517682",
        "tgn:1009227",
        "tgn:1000226",
        "tgn:7016822",
        "tgn:1000006",
        "tgn:7029392"
    ],
    "tgn:id":7517682,
    "tgn:name:en":"Knob, The",
    "tgn:placetype":[
        "aat:300008795"
    ]
},
  "bbox": [],
  "geometry": {"coordinates":[167.75,-45.783333],"type":"Point"}
}