{
  "id": 1026224,
  "type": "Feature",
  "properties": {
    "tgn:hierarchy":[
        "tgn:1026224",
        "tgn:7003023",
        "tgn:1000003",
        "tgn:1000062",
        "tgn:7029392"
    ],
    "tgn:id":1026224,
    "tgn:name":"Weppersdorf",
    "tgn:placetype":[
        "aat:300008347"
    ]
},
  "bbox": [],
  "geometry": {"coordinates":[16.4333,47.5833],"type":"Point"}
}