{
  "id": 2280827,
  "type": "Feature",
  "properties": {
    "tgn:hierarchy":[
        "tgn:2280827",
        "tgn:1000001",
        "tgn:7012149",
        "tgn:7007705",
        "tgn:7029392"
    ],
    "tgn:id":2280827,
    "tgn:name":"Deep Creek",
    "tgn:placetype":[
        "aat:300008706"
    ]
},
  "bbox": [],
  "geometry": {"coordinates":[-102.8333,47.6667],"type":"Point"}
}