{
  "id": 7098699,
  "type": "Feature",
  "properties": {
    "tgn:hierarchy":[
        "tgn:7098699",
        "tgn:7000096",
        "tgn:1000003",
        "tgn:7000084",
        "tgn:7029392"
    ],
    "tgn:id":7098699,
    "tgn:name":"Silberberg",
    "tgn:placetype":[
        "aat:300008347"
    ]
},
  "bbox": [],
  "geometry": {"coordinates":[14.033333,52.25],"type":"Point"}
}