{
  "id": 7408555,
  "type": "Feature",
  "properties": {
    "tgn:hierarchy":[
        "tgn:7408555",
        "tgn:1000001",
        "tgn:1001893",
        "tgn:7005560",
        "tgn:7029392"
    ],
    "tgn:id":7408555,
    "tgn:name":"Potrerillos",
    "tgn:placetype":[
        "aat:300008347"
    ]
},
  "bbox": [],
  "geometry": {"coordinates":[-100.4375,18.658333],"type":"Point"}
}