<<<<<<< HEAD
{
  "id": 2760292,
  "type": "Feature",
  "properties": {
    "tgn:hierarchy":[
        "tgn:2760292",
        "tgn:1000001",
        "tgn:7012149",
        "tgn:7007157",
        "tgn:1002608",
        "tgn:7029392"
    ],
    "tgn:id":2760292,
    "tgn:name":"West Fork San Dimas Canyon",
    "tgn:placetype":[
        "aat:300008761"
    ]
},
  "bbox": [],
  "geometry": {"coordinates":[-117.7667,34.2],"type":"Point"}
}
=======
{"geometry":{"type":"Point","coordinates":[-117.766700,34.200000]},"type":"Feature","properties":{"hierarchy":["tgn:2760292","tgn:1000001","tgn:7012149","tgn:7007157","tgn:1002608","tgn:7029392"],"placetype":["aat:300008761"],"id":2760292,"name:xx":"West Fork San Dimas Canyon"}}
>>>>>>> 03f74aca74312dbeaf24d7e61306dd6a786dc3d0
