{
  "id": 7474852,
  "type": "Feature",
  "properties": {
    "tgn:hierarchy":[
        "tgn:7474852",
        "tgn:1000004",
        "tgn:1000959",
        "tgn:1000141",
        "tgn:7029392"
    ],
    "tgn:id":7474852,
    "tgn:name":"Yongtai Li",
    "tgn:placetype":[
        "aat:300387173"
    ]
},
  "bbox": [],
  "geometry": {"coordinates":[121.5835,25.0715],"type":"Point"}
}