{
  "id": 2489822,
  "type": "Feature",
  "properties": {
    "tgn:hierarchy":[
        "tgn:2489822",
        "tgn:1000001",
        "tgn:7006451",
        "tgn:7012149",
        "tgn:2000097",
        "tgn:7029392"
    ],
    "tgn:id":2489822,
    "tgn:name":"Malpais Canyon",
    "tgn:placetype":[
        "aat:300008761"
    ]
},
  "bbox": [],
  "geometry": {"coordinates":[-111.5667,33.7167],"type":"Point"}
}