{
  "id": 2104630,
  "type": "Feature",
  "properties": {
    "tgn:hierarchy":[
        "tgn:2104630",
        "tgn:1000001",
        "tgn:7012149",
        "tgn:2002076",
        "tgn:7007826",
        "tgn:7029392"
    ],
    "tgn:id":2104630,
    "tgn:name":"Gunsight",
    "tgn:placetype":[
        "aat:300008347",
        "aat:300387210"
    ]
},
  "bbox": [],
  "geometry": {"coordinates":[-98.8667,32.5333],"type":"Point"}
}