{
  "id": 7574838,
  "type": "Feature",
  "properties": {
    "tgn:hierarchy":[
        "tgn:7574838",
        "tgn:1000004",
        "tgn:7000198",
        "tgn:7016722",
        "tgn:7029392"
    ],
    "tgn:id":7574838,
    "tgn:name:en":"Kaur\u0101ra",
    "tgn:placetype":[
        "aat:300007783"
    ]
},
  "bbox": [],
  "geometry": {"coordinates":[78.662085,27.02953],"type":"Point"}
}