{
  "id": 7577077,
  "type": "Feature",
  "properties": {
    "tgn:hierarchy":[
        "tgn:7577077",
        "tgn:1000004",
        "tgn:7000198",
        "tgn:7000799",
        "tgn:7029392"
    ],
    "tgn:id":7577077,
    "tgn:name:en":"Krar",
    "tgn:placetype":[
        "aat:300008347"
    ]
},
  "bbox": [],
  "geometry": {"coordinates":[74.471371,34.169921],"type":"Point"}
}