<<<<<<< HEAD
{
  "id": 7376083,
  "type": "Feature",
  "properties": {
    "tgn:hierarchy":[
        "tgn:7376083",
        "tgn:7005583",
        "tgn:1000001",
        "tgn:7005560",
        "tgn:7029392"
    ],
    "tgn:id":7376083,
    "tgn:name":"La Sierrita Del Negro",
    "tgn:placetype":[
        "aat:300008795"
    ]
},
  "bbox": [],
  "geometry": {"coordinates":[-102.9,24.65],"type":"Point"}
}
=======
{"geometry":{"type":"Point","coordinates":[-102.900000,24.650000]},"type":"Feature","properties":{"hierarchy":["tgn:7376083","tgn:7005583","tgn:1000001","tgn:7005560","tgn:7029392"],"placetype":["aat:300008795"],"id":7376083,"name:xx":"La Sierrita Del Negro"}}
>>>>>>> 03f74aca74312dbeaf24d7e61306dd6a786dc3d0
