{
  "id": 7474313,
  "type": "Feature",
  "properties": {
    "tgn:hierarchy":[
        "tgn:7474313",
        "tgn:1000004",
        "tgn:7467799",
        "tgn:1000141",
        "tgn:7029392"
    ],
    "tgn:id":7474313,
    "tgn:name":"Waisankuaicuo",
    "tgn:placetype":[
        "aat:300008347"
    ]
},
  "bbox": [],
  "geometry": {"coordinates":[120.56391,23.869009],"type":"Point"}
}