<<<<<<< HEAD
{
  "id": 7172619,
  "type": "Feature",
  "properties": {
    "tgn:hierarchy":[
        "tgn:7172619",
        "tgn:1000003",
        "tgn:7003677",
        "tgn:7000084",
        "tgn:7029392"
    ],
    "tgn:id":7172619,
    "tgn:name":"Heller-Berg",
    "tgn:placetype":[
        "aat:300008777"
    ]
},
  "bbox": [],
  "geometry": {"coordinates":[8.0,50.783333],"type":"Point"}
}
=======
{"geometry":{"type":"Point","coordinates":[8.000000,50.783333]},"type":"Feature","properties":{"hierarchy":["tgn:7172619","tgn:1000003","tgn:7003677","tgn:7000084","tgn:7029392"],"placetype":["aat:300008777"],"id":7172619,"name:xx":"Heller-Berg"}}
>>>>>>> 03f74aca74312dbeaf24d7e61306dd6a786dc3d0
