{
  "id": 2662635,
  "type": "Feature",
  "properties": {
    "tgn:hierarchy":[
        "tgn:2662635",
        "tgn:1000001",
        "tgn:7012149",
        "tgn:2001455",
        "tgn:7007566",
        "tgn:7029392"
    ],
    "tgn:id":2662635,
    "tgn:name":"Signal Peak",
    "tgn:placetype":[
        "aat:300008798"
    ]
},
  "bbox": [],
  "geometry": {"coordinates":[-107.65,32.7667],"type":"Point"}
}