{
  "id": 7586344,
  "type": "Feature",
  "properties": {
    "tgn:hierarchy":[
        "tgn:7586344",
        "tgn:1000004",
        "tgn:7000198",
        "tgn:7000799",
        "tgn:7029392"
    ],
    "tgn:id":7586344,
    "tgn:name:en":"Lundi",
    "tgn:placetype":[
        "aat:300008699"
    ]
},
  "bbox": [],
  "geometry": {"coordinates":[74.791667,34.380556],"type":"Point"}
}