{
  "id": 7505254,
  "type": "Feature",
  "properties": {
    "tgn:hierarchy":[
        "tgn:7505254",
        "tgn:1008380",
        "tgn:1000226",
        "tgn:7018426",
        "tgn:1000006",
        "tgn:7029392"
    ],
    "tgn:id":7505254,
    "tgn:name:en":"Woodleigh",
    "tgn:placetype":[
        "aat:300008347"
    ]
},
  "bbox": [],
  "geometry": {"coordinates":[174.916667,-37.533333],"type":"Point"}
}