{
  "id": 7460854,
  "type": "Feature",
  "properties": {
    "tgn:hierarchy":[
        "tgn:7460854",
        "tgn:7002445",
        "tgn:1000003",
        "tgn:7008175",
        "tgn:7008591",
        "tgn:7029392"
    ],
    "tgn:id":7460854,
    "tgn:name:en":"Holmbury Saint Mary",
    "tgn:placetype":[
        "aat:300008347"
    ]
},
  "bbox": [],
  "geometry": {"coordinates":[-0.416667,51.183333],"type":"Point"}
}