{
  "id": 7210465,
  "type": "Feature",
  "properties": {
    "tgn:hierarchy":[
        "tgn:7210465",
        "tgn:1000003",
        "tgn:7003687",
        "tgn:7000084",
        "tgn:7029392"
    ],
    "tgn:id":7210465,
    "tgn:name":"Vorwerk B\u00e4umchen",
    "tgn:placetype":[
        "aat:300000206"
    ]
},
  "bbox": [],
  "geometry": {"coordinates":[11.983333,51.266667],"type":"Point"}
}