{
  "id": 2075990,
  "type": "Feature",
  "properties": {
    "tgn:hierarchy":[
        "tgn:2075990",
        "tgn:1000001",
        "tgn:7012149",
        "tgn:2001511",
        "tgn:7007709",
        "tgn:7029392"
    ],
    "tgn:id":2075990,
    "tgn:name":"Osgood",
    "tgn:placetype":[
        "aat:300008347",
        "aat:300387210"
    ]
},
  "bbox": [],
  "geometry": {"coordinates":[-79.1167,35.55],"type":"Point"}
}