{
  "id": 2761722,
  "type": "Feature",
  "properties": {
    "tgn:hierarchy":[
        "tgn:2761722",
        "tgn:1002933",
        "tgn:1000001",
        "tgn:7012149",
        "tgn:7007239",
        "tgn:7029392"
    ],
    "tgn:id":2761722,
    "tgn:name":"West Pond",
    "tgn:placetype":[
        "aat:300008905"
    ]
},
  "bbox": [],
  "geometry": {"coordinates":[-75.45,38.55],"type":"Point"}
}