<<<<<<< HEAD
{
  "id": 7375674,
  "type": "Feature",
  "properties": {
    "tgn:hierarchy":[
        "tgn:7375674",
        "tgn:1000001",
        "tgn:1001960",
        "tgn:7005560",
        "tgn:7029392"
    ],
    "tgn:id":7375674,
    "tgn:name":"Rancho La Rastrita",
    "tgn:placetype":[
        "aat:300000241"
    ]
},
  "bbox": [],
  "geometry": {"coordinates":[-109.116667,30.3],"type":"Point"}
}
=======
{"geometry":{"type":"Point","coordinates":[-109.116667,30.300000]},"type":"Feature","properties":{"hierarchy":["tgn:7375674","tgn:1000001","tgn:1001960","tgn:7005560","tgn:7029392"],"placetype":["aat:300000241"],"id":7375674,"name:xx":"Rancho La Rastrita"}}
>>>>>>> 03f74aca74312dbeaf24d7e61306dd6a786dc3d0
