{
  "id": 1078225,
  "type": "Feature",
  "properties": {
    "tgn:hierarchy":[
        "tgn:1078225",
        "tgn:7016479",
        "tgn:1000004",
        "tgn:1000116",
        "tgn:7029392"
    ],
    "tgn:id":1078225,
    "tgn:name":"Neuheum",
    "tgn:placetype":[
        "aat:300008347"
    ]
},
  "bbox": [],
  "geometry": {"coordinates":[95.4167,5.6333],"type":"Point"}
}