{
  "id": 7584813,
  "type": "Feature",
  "properties": {
    "tgn:hierarchy":[
        "tgn:7584813",
        "tgn:1000004",
        "tgn:7000198",
        "tgn:1001894",
        "tgn:7029392"
    ],
    "tgn:id":7584813,
    "tgn:name:en":"S\u0101wantnagar",
    "tgn:placetype":[
        "aat:300008057"
    ]
},
  "bbox": [],
  "geometry": {"coordinates":[78.945319,24.689792],"type":"Point"}
}