{
  "id": 7300707,
  "type": "Feature",
  "properties": {
    "tgn:hierarchy":[
        "tgn:7300707",
        "tgn:7002824",
        "tgn:1000003",
        "tgn:7002786",
        "tgn:1000095",
        "tgn:7029392"
    ],
    "tgn:id":7300707,
    "tgn:name":"Nant\u00f3n",
    "tgn:placetype":[
        "aat:300008347"
    ]
},
  "bbox": [],
  "geometry": {"coordinates":[-8.866667,43.166667],"type":"Point"}
}