{
  "id": 2057998,
  "type": "Feature",
  "properties": {
    "tgn:hierarchy":[
        "tgn:2057998",
        "tgn:1000001",
        "tgn:7012149",
        "tgn:2001224",
        "tgn:7007523",
        "tgn:7029392"
    ],
    "tgn:id":2057998,
    "tgn:name":"Bedison",
    "tgn:placetype":[
        "aat:300008347",
        "aat:300387210"
    ]
},
  "bbox": [],
  "geometry": {"coordinates":[-94.7667,40.2833],"type":"Point"}
}