{
  "id": 7340561,
  "type": "Feature",
  "properties": {
    "tgn:hierarchy":[
        "tgn:7340561",
        "tgn:7002836",
        "tgn:7016622",
        "tgn:1000003",
        "tgn:1000095",
        "tgn:7029392"
    ],
    "tgn:id":7340561,
    "tgn:name":"Cantadal, Playa del",
    "tgn:placetype":[
        "aat:300008816"
    ]
},
  "bbox": [],
  "geometry": {"coordinates":[-17.966667,27.65],"type":"Point"}
}