{
  "id": 1085727,
  "type": "Feature",
  "properties": {
    "tgn:hierarchy":[
        "tgn:1085727",
        "tgn:7005193",
        "tgn:1000004",
        "tgn:7000974",
        "tgn:1000142",
        "tgn:7029392"
    ],
    "tgn:id":1085727,
    "tgn:name":"Ubon Ratchathani",
    "tgn:placetype":[
        "aat:300008347",
        "aat:300387223",
        "aat:300008375",
        "aat:300387270",
        "aat:300387286"
    ]
},
  "bbox": [],
  "geometry": {"coordinates":[104.8333,15.25],"type":"Point"}
}