{
  "id": 7588167,
  "type": "Feature",
  "properties": {
    "tgn:hierarchy":[
        "tgn:7588167",
        "tgn:1000004",
        "tgn:7000198",
        "tgn:1001977",
        "tgn:7029392"
    ],
    "tgn:id":7588167,
    "tgn:name:en":"M\u0101jerp\u0101ra",
    "tgn:placetype":[
        "aat:300008347"
    ]
},
  "bbox": [],
  "geometry": {"coordinates":[88.722778,22.529722],"type":"Point"}
}