<<<<<<< HEAD
{
  "id": 7487858,
  "type": "Feature",
  "properties": {
    "tgn:hierarchy":[
        "tgn:7487858",
        "tgn:1000004",
        "tgn:7467799",
        "tgn:1000141",
        "tgn:7029392"
    ],
    "tgn:id":7487858,
    "tgn:name":"Youshuikeng",
    "tgn:placetype":[
        "aat:300008347"
    ]
},
  "bbox": [],
  "geometry": {"coordinates":[120.63128,23.80802],"type":"Point"}
}
=======
{"geometry":{"type":"Point","coordinates":[120.631280,23.808020]},"type":"Feature","properties":{"hierarchy":["tgn:7487858","tgn:1000004","tgn:7467799","tgn:1000141","tgn:7029392"],"placetype":["aat:300008347"],"id":7487858,"name:xx":"Youshuikeng"}}
>>>>>>> 03f74aca74312dbeaf24d7e61306dd6a786dc3d0
