{
  "id": 7487858,
  "type": "Feature",
  "properties": {
    "tgn:hierarchy":[
        "tgn:7487858",
        "tgn:1000004",
        "tgn:7467799",
        "tgn:1000141",
        "tgn:7029392"
    ],
    "tgn:id":7487858,
    "tgn:name":"Youshuikeng",
    "tgn:placetype":[
        "aat:300008347"
    ]
},
  "bbox": [],
  "geometry": {"coordinates":[120.63128,23.80802],"type":"Point"}
}