{
  "id": 7213980,
  "type": "Feature",
  "properties": {
    "tgn:hierarchy":[
        "tgn:7213980",
        "tgn:7003669",
        "tgn:1000003",
        "tgn:7000084",
        "tgn:7029392"
    ],
    "tgn:id":7213980,
    "tgn:name":"Birket",
    "tgn:placetype":[
        "aat:300008347"
    ]
},
  "bbox": [],
  "geometry": {"coordinates":[13.35,48.716667],"type":"Point"}
}