{
  "id": 7082560,
  "type": "Feature",
  "properties": {
    "tgn:hierarchy":[
        "tgn:7082560",
        "tgn:7003692",
        "tgn:1000003",
        "tgn:7000084",
        "tgn:7029392"
    ],
    "tgn:id":7082560,
    "tgn:name":"Westernbach",
    "tgn:placetype":[
        "aat:300008347"
    ]
},
  "bbox": [],
  "geometry": {"coordinates":[9.499167,49.228056],"type":"Point"}
}