{
  "id": 2126997,
  "type": "Feature",
  "properties": {
    "tgn:hierarchy":[
        "tgn:2126997",
        "tgn:1000001",
        "tgn:1002206",
        "tgn:7012149",
        "tgn:7007568",
        "tgn:7029392"
    ],
    "tgn:id":2126997,
    "tgn:name":"Agwaterra Pond",
    "tgn:placetype":[
        "aat:300006191"
    ]
},
  "bbox": [],
  "geometry": {"coordinates":[-75.9333,42.0167],"type":"Point"}
}