{
  "id": 2480556,
  "type": "Feature",
  "properties": {
    "tgn:hierarchy":[
        "tgn:2480556",
        "tgn:1000001",
        "tgn:7012149",
        "tgn:1002862",
        "tgn:7007920",
        "tgn:7029392"
    ],
    "tgn:id":2480556,
    "tgn:name":"Lakedale",
    "tgn:placetype":[
        "aat:300008347"
    ]
},
  "bbox": [],
  "geometry": {"coordinates":[-123.0667,48.5667],"type":"Point"}
}