{
  "id": 7157649,
  "type": "Feature",
  "properties": {
    "tgn:hierarchy":[
        "tgn:7157649",
        "tgn:1000003",
        "tgn:7003687",
        "tgn:7000084",
        "tgn:7029392"
    ],
    "tgn:id":7157649,
    "tgn:name":"Kleiner Klingen-Berg",
    "tgn:placetype":[
        "aat:300266640"
    ]
},
  "bbox": [],
  "geometry": {"coordinates":[10.933333,51.683333],"type":"Point"}
}