{
  "id": 7582003,
  "type": "Feature",
  "properties": {
    "tgn:hierarchy":[
        "tgn:7582003",
        "tgn:1000004",
        "tgn:7000198",
        "tgn:7016883",
        "tgn:7029392"
    ],
    "tgn:id":7582003,
    "tgn:name:en":"Karo M\u0101jra",
    "tgn:placetype":[
        "aat:300008347"
    ]
},
  "bbox": [],
  "geometry": {"coordinates":[76.75682,30.674177],"type":"Point"}
}