{
  "id": 2260759,
  "type": "Feature",
  "properties": {
    "tgn:hierarchy":[
        "tgn:2260759",
        "tgn:1000001",
        "tgn:7012149",
        "tgn:2001082",
        "tgn:7007521",
        "tgn:7029392"
    ],
    "tgn:id":2260759,
    "tgn:name":"County Ditch Number One-a",
    "tgn:placetype":[
        "aat:300006075"
    ]
},
  "bbox": [],
  "geometry": {"coordinates":[-96.5667,46.3833],"type":"Point"}
}