{
  "id": 2017350,
  "type": "Feature",
  "properties": {
    "tgn:hierarchy":[
        "tgn:2017350",
        "tgn:1000001",
        "tgn:1002601",
        "tgn:7012149",
        "tgn:7007159",
        "tgn:7029392"
    ],
    "tgn:id":2017350,
    "tgn:name":"Robertsville",
    "tgn:placetype":[
        "aat:300008347"
    ]
},
  "bbox": [],
  "geometry": {"coordinates":[-73.0333,41.9667],"type":"Point"}
}