{
  "id": 2195515,
  "type": "Feature",
  "properties": {
    "tgn:hierarchy":[
        "tgn:2195515",
        "tgn:1000001",
        "tgn:7012149",
        "tgn:2002178",
        "tgn:7007919",
        "tgn:7029392"
    ],
    "tgn:id":2195515,
    "tgn:name":"Britton Hollow",
    "tgn:placetype":[
        "aat:300008761"
    ]
},
  "bbox": [],
  "geometry": {"coordinates":[-78.3667,38.6833],"type":"Point"}
}