{
  "id": 7129890,
  "type": "Feature",
  "properties": {
    "tgn:hierarchy":[
        "tgn:7129890",
        "tgn:1000003",
        "tgn:7003678",
        "tgn:7000084",
        "tgn:7029392"
    ],
    "tgn:id":7129890,
    "tgn:name":"Marxheim",
    "tgn:placetype":[
        "aat:300008347"
    ]
},
  "bbox": [],
  "geometry": {"coordinates":[8.433333,50.066667],"type":"Point"}
}