{
  "id": 7563442,
  "type": "Feature",
  "properties": {
    "tgn:hierarchy":[
        "tgn:7563442",
        "tgn:1000004",
        "tgn:7000198",
        "tgn:7016788",
        "tgn:7029392"
    ],
    "tgn:id":7563442,
    "tgn:name":"Sinyo Dhora",
    "tgn:placetype":[
        "aat:300008750"
    ]
},
  "bbox": [],
  "geometry": {"coordinates":[74.369468,28.806595],"type":"Point"}
}