{
  "id": 2311808,
  "type": "Feature",
  "properties": {
    "tgn:hierarchy":[
        "tgn:2311808",
        "tgn:1000001",
        "tgn:7012149",
        "tgn:2001766",
        "tgn:7007712",
        "tgn:7029392"
    ],
    "tgn:id":2311808,
    "tgn:name":"Edwin Johnson, Lake",
    "tgn:placetype":[
        "aat:300006191"
    ]
},
  "bbox": [],
  "geometry": {"coordinates":[-81.8333,34.8667],"type":"Point"}
}