{
  "id": 7450052,
  "type": "Feature",
  "properties": {
    "tgn:hierarchy":[
        "tgn:7450052",
        "tgn:7002444",
        "tgn:1000003",
        "tgn:7009907",
        "tgn:7008591",
        "tgn:7029392"
    ],
    "tgn:id":7450052,
    "tgn:name:en":"Hacksness",
    "tgn:placetype":[
        "aat:300008850"
    ]
},
  "bbox": [],
  "geometry": {"coordinates":[-2.833333,59.016667],"type":"Point"}
}