{
  "id": 7267459,
  "type": "Feature",
  "properties": {
    "tgn:hierarchy":[
        "tgn:7267459",
        "tgn:1000003",
        "tgn:7003635",
        "tgn:7016845",
        "tgn:7029392"
    ],
    "tgn:id":7267459,
    "tgn:name:nl":"Ouwerkerk, Hoek van",
    "tgn:placetype":[
        "aat:300386846"
    ]
},
  "bbox": [],
  "geometry": {"coordinates":[3.966667,51.616667],"type":"Point"}
}