{
  "id": 1011855,
  "type": "Feature",
  "properties": {
    "tgn:hierarchy":[
        "tgn:1011855",
        "tgn:1000985",
        "tgn:7016529",
        "tgn:7016531",
        "tgn:1000004",
        "tgn:1000120",
        "tgn:7029392"
    ],
    "tgn:id":1011855,
    "tgn:name":"Esan-misaki",
    "tgn:placetype":[
        "aat:300386846"
    ]
},
  "bbox": [],
  "geometry": {"coordinates":[141.1833,41.8167],"type":"Point"}
}