{
  "id": 2753989,
  "type": "Feature",
  "properties": {
    "tgn:hierarchy":[
        "tgn:2753989",
        "tgn:1000001",
        "tgn:7012149",
        "tgn:2000928",
        "tgn:7007515",
        "tgn:7029392"
    ],
    "tgn:id":2753989,
    "tgn:name":"Watson Hill",
    "tgn:placetype":[
        "aat:300008798"
    ]
},
  "bbox": [],
  "geometry": {"coordinates":[-69.3333,45.15],"type":"Point"}
}