{
  "id": 2231217,
  "type": "Feature",
  "properties": {
    "tgn:hierarchy":[
        "tgn:2231217",
        "tgn:1000001",
        "tgn:7012149",
        "tgn:2002280",
        "tgn:7013961",
        "tgn:7029392"
    ],
    "tgn:id":2231217,
    "tgn:name":"Chafin Branch",
    "tgn:placetype":[
        "aat:300008699"
    ]
},
  "bbox": [],
  "geometry": {"coordinates":[-82.0833,37.6333],"type":"Point"}
}