{
  "id": 7479460,
  "type": "Feature",
  "properties": {
    "tgn:hierarchy":[
        "tgn:7479460",
        "tgn:1000004",
        "tgn:7490934",
        "tgn:1000141",
        "tgn:7029392"
    ],
    "tgn:id":7479460,
    "tgn:name":"Wenchang Ci",
    "tgn:placetype":[
        "aat:300007595"
    ]
},
  "bbox": [],
  "geometry": {"coordinates":[120.255,23.187222],"type":"Point"}
}