{
  "id": 2102770,
  "type": "Feature",
  "properties": {
    "tgn:hierarchy":[
        "tgn:2102770",
        "tgn:1000001",
        "tgn:7012149",
        "tgn:2001962",
        "tgn:7007826",
        "tgn:7029392"
    ],
    "tgn:id":2102770,
    "tgn:name":"Blanket",
    "tgn:placetype":[
        "aat:300008347"
    ]
},
  "bbox": [],
  "geometry": {"coordinates":[-98.7833,31.8167],"type":"Point"}
}