{
  "id": 2538135,
  "type": "Feature",
  "properties": {
    "tgn:hierarchy":[
        "tgn:2538135",
        "tgn:1000001",
        "tgn:7012149",
        "tgn:2000363",
        "tgn:7007248",
        "tgn:7029392"
    ],
    "tgn:id":2538135,
    "tgn:name":"Nelson Lake",
    "tgn:placetype":[
        "aat:300006191"
    ]
},
  "bbox": [],
  "geometry": {"coordinates":[-84.95,32.7167],"type":"Point"}
}