{
  "id": 2167904,
  "type": "Feature",
  "properties": {
    "tgn:hierarchy":[
        "tgn:2167904",
        "tgn:1000001",
        "tgn:7012149",
        "tgn:2002374",
        "tgn:7007923",
        "tgn:7029392"
    ],
    "tgn:id":2167904,
    "tgn:name":"Big Donaldson Reservoir",
    "tgn:placetype":[
        "aat:300006191"
    ]
},
  "bbox": [],
  "geometry": {"coordinates":[-106.4333,44.55],"type":"Point"}
}