{
  "id": 2122277,
  "type": "Feature",
  "properties": {
    "tgn:hierarchy":[
        "tgn:2122277",
        "tgn:1000001",
        "tgn:2002320",
        "tgn:7012149",
        "tgn:7007922",
        "tgn:7029392"
    ],
    "tgn:id":2122277,
    "tgn:name":"Rodell",
    "tgn:placetype":[
        "aat:300008347",
        "aat:300387210"
    ]
},
  "bbox": [],
  "geometry": {"coordinates":[-91.1833,44.7167],"type":"Point"}
}