{
  "id": 7406294,
  "type": "Feature",
  "properties": {
    "tgn:hierarchy":[
        "tgn:7406294",
        "tgn:1000001",
        "tgn:1001906",
        "tgn:7005560",
        "tgn:7029392"
    ],
    "tgn:id":7406294,
    "tgn:name":"Ortega",
    "tgn:placetype":[
        "aat:300008347"
    ]
},
  "bbox": [],
  "geometry": {"coordinates":[-104.425,22.35],"type":"Point"}
}