{
  "id": 1087738,
  "type": "Feature",
  "properties": {
    "tgn:hierarchy":[
        "tgn:1087738",
        "tgn:7001242",
        "tgn:1000149",
        "tgn:1000867",
        "tgn:7029392"
    ],
    "tgn:id":1087738,
    "tgn:name":"Chibemba",
    "tgn:placetype":[
        "aat:300008347"
    ]
},
  "bbox": [],
  "geometry": {"coordinates":[14.1167,-15.7167],"type":"Point"}
}