<<<<<<< HEAD
{
  "id": 7370653,
  "type": "Feature",
  "properties": {
    "tgn:hierarchy":[
        "tgn:7370653",
        "tgn:1000001",
        "tgn:7005590",
        "tgn:7005560",
        "tgn:7029392"
    ],
    "tgn:id":7370653,
    "tgn:name":"Jauja",
    "tgn:placetype":[
        "aat:300000241"
    ]
},
  "bbox": [],
  "geometry": {"coordinates":[-102.033333,20.25],"type":"Point"}
}
=======
{"geometry":{"type":"Point","coordinates":[-102.033333,20.250000]},"type":"Feature","properties":{"hierarchy":["tgn:7370653","tgn:1000001","tgn:7005590","tgn:7005560","tgn:7029392"],"placetype":["aat:300000241"],"id":7370653,"name:xx":"Jauja"}}
>>>>>>> 03f74aca74312dbeaf24d7e61306dd6a786dc3d0
