{
  "id": 7370653,
  "type": "Feature",
  "properties": {
    "tgn:hierarchy":[
        "tgn:7370653",
        "tgn:1000001",
        "tgn:7005590",
        "tgn:7005560",
        "tgn:7029392"
    ],
    "tgn:id":7370653,
    "tgn:name":"Jauja",
    "tgn:placetype":[
        "aat:300000241"
    ]
},
  "bbox": [],
  "geometry": {"coordinates":[-102.033333,20.25],"type":"Point"}
}