{
  "id": 2769624,
  "type": "Feature",
  "properties": {
    "tgn:hierarchy":[
        "tgn:2769624",
        "tgn:1000001",
        "tgn:7012149",
        "tgn:2001108",
        "tgn:7007522",
        "tgn:7029392"
    ],
    "tgn:id":2769624,
    "tgn:name":"Wiehe",
    "tgn:placetype":[
        "aat:300008347"
    ]
},
  "bbox": [],
  "geometry": {"coordinates":[-89.4833,30.4667],"type":"Point"}
}