{
  "id": 2671654,
  "type": "Feature",
  "properties": {
    "tgn:hierarchy":[
        "tgn:2671654",
        "tgn:1000001",
        "tgn:7012149",
        "tgn:2002303",
        "tgn:7013961",
        "tgn:7029392"
    ],
    "tgn:id":2671654,
    "tgn:name":"Smith Lakes",
    "tgn:placetype":[
        "aat:300006191"
    ]
},
  "bbox": [],
  "geometry": {"coordinates":[-81.5667,39.2333],"type":"Point"}
}