{
  "id": 2132610,
  "type": "Feature",
  "properties": {
    "tgn:hierarchy":[
        "tgn:2132610",
        "tgn:7023902",
        "tgn:1000001",
        "tgn:7012149",
        "tgn:7007249",
        "tgn:7029392"
    ],
    "tgn:id":2132610,
    "tgn:name":"Anahulu",
    "tgn:placetype":[
        "aat:300055621"
    ]
},
  "bbox": [],
  "geometry": {"coordinates":[-155.8333,19.85],"type":"Point"}
}