{
  "id": 2431688,
  "type": "Feature",
  "properties": {
    "tgn:hierarchy":[
        "tgn:2431688",
        "tgn:1000001",
        "tgn:7012149",
        "tgn:7014021",
        "tgn:7007709",
        "tgn:7029392"
    ],
    "tgn:id":2431688,
    "tgn:name":"Kathleen, Lake",
    "tgn:placetype":[
        "aat:300006191"
    ]
},
  "bbox": [],
  "geometry": {"coordinates":[-80.9833,35.25],"type":"Point"}
}