{
  "id": 7457299,
  "type": "Feature",
  "properties": {
    "tgn:hierarchy":[
        "tgn:7457299",
        "tgn:7002445",
        "tgn:1000003",
        "tgn:7008174",
        "tgn:7008591",
        "tgn:7029392"
    ],
    "tgn:id":7457299,
    "tgn:name:en":"Marchington Woodlands",
    "tgn:placetype":[
        "aat:300008347"
    ]
},
  "bbox": [],
  "geometry": {"coordinates":[-1.833333,52.85],"type":"Point"}
}