{
  "id": 2464395,
  "type": "Feature",
  "properties": {
    "tgn:hierarchy":[
        "tgn:2464395",
        "tgn:1000001",
        "tgn:7012149",
        "tgn:1002505",
        "tgn:7007920",
        "tgn:7029392"
    ],
    "tgn:id":2464395,
    "tgn:name":"Loers Pond",
    "tgn:placetype":[
        "aat:300006191"
    ]
},
  "bbox": [],
  "geometry": {"coordinates":[-122.6833,48.2833],"type":"Point"}
}