<<<<<<< HEAD
{
  "id": 2408018,
  "type": "Feature",
  "properties": {
    "tgn:hierarchy":[
        "tgn:2408018",
        "tgn:1000001",
        "tgn:7012149",
        "tgn:7007825",
        "tgn:7029392"
    ],
    "tgn:id":2408018,
    "tgn:name":"Hurricane Creek Canal",
    "tgn:placetype":[
        "aat:300006075"
    ]
},
  "bbox": [],
  "geometry": {"coordinates":[-88.3,35.3833],"type":"Point"}
}
=======
{"geometry":{"type":"Point","coordinates":[-88.300000,35.383300]},"type":"Feature","properties":{"hierarchy":["tgn:2408018","tgn:1000001","tgn:7012149","tgn:7007825","tgn:7029392"],"placetype":["aat:300006075"],"id":2408018,"name:xx":"Hurricane Creek Canal"}}
>>>>>>> 03f74aca74312dbeaf24d7e61306dd6a786dc3d0
