<<<<<<< HEAD
{
  "id": 7481822,
  "type": "Feature",
  "properties": {
    "tgn:hierarchy":[
        "tgn:7481822",
        "tgn:1000004",
        "tgn:7490934",
        "tgn:1000141",
        "tgn:7029392"
    ],
    "tgn:id":7481822,
    "tgn:name":"Yanliaoxian",
    "tgn:placetype":[
        "aat:300006075"
    ]
},
  "bbox": [],
  "geometry": {"coordinates":[120.121853,23.250343],"type":"Point"}
}
=======
{"geometry":{"type":"Point","coordinates":[120.121853,23.250343]},"type":"Feature","properties":{"hierarchy":["tgn:7481822","tgn:1000004","tgn:7490934","tgn:1000141","tgn:7029392"],"placetype":["aat:300006075"],"id":7481822,"name:xx":"Yanliaoxian"}}
>>>>>>> 03f74aca74312dbeaf24d7e61306dd6a786dc3d0
