{
  "id": 7310922,
  "type": "Feature",
  "properties": {
    "tgn:hierarchy":[
        "tgn:7310922",
        "tgn:1001702",
        "tgn:1000049",
        "tgn:1000002",
        "tgn:7029392"
    ],
    "tgn:id":7310922,
    "tgn:name":"Moraine, Cerro",
    "tgn:placetype":[
        "aat:300008795"
    ]
},
  "bbox": [],
  "geometry": {"coordinates":[-72.95,-53.533333],"type":"Point"}
}