{
  "id": 1030798,
  "type": "Feature",
  "properties": {
    "tgn:hierarchy":[
        "tgn:1030798",
        "tgn:7002445",
        "tgn:1000003",
        "tgn:7008153",
        "tgn:7008591",
        "tgn:7029392"
    ],
    "tgn:id":1030798,
    "tgn:name:en":"Sundridge",
    "tgn:placetype":[
        "aat:300008347"
    ]
},
  "bbox": [],
  "geometry": {"coordinates":[0.133333,51.266667],"type":"Point"}
}