{
  "id": 2153174,
  "type": "Feature",
  "properties": {
    "tgn:hierarchy":[
        "tgn:2153174",
        "tgn:1000001",
        "tgn:7012149",
        "tgn:2001714",
        "tgn:7007708",
        "tgn:7029392"
    ],
    "tgn:id":2153174,
    "tgn:name":"Beal Lake",
    "tgn:placetype":[
        "aat:300008680"
    ]
},
  "bbox": [],
  "geometry": {"coordinates":[-122.2667,42.5167],"type":"Point"}
}