{
  "id": 2696776,
  "type": "Feature",
  "properties": {
    "tgn:hierarchy":[
        "tgn:2696776",
        "tgn:1000001",
        "tgn:2001424",
        "tgn:7012149",
        "tgn:7007564",
        "tgn:7029392"
    ],
    "tgn:id":2696776,
    "tgn:name":"Stonehouse Mountain",
    "tgn:placetype":[
        "aat:300008798"
    ]
},
  "bbox": [],
  "geometry": {"coordinates":[-72.0667,43.85],"type":"Point"}
}