{
  "id": 2261766,
  "type": "Feature",
  "properties": {
    "tgn:hierarchy":[
        "tgn:2261766",
        "tgn:1000001",
        "tgn:7012149",
        "tgn:2002191",
        "tgn:7007919",
        "tgn:7029392"
    ],
    "tgn:id":2261766,
    "tgn:name":"Cove Ridge",
    "tgn:placetype":[
        "aat:300266640"
    ]
},
  "bbox": [],
  "geometry": {"coordinates":[-81.55,36.95],"type":"Point"}
}