{
  "id": 2443865,
  "type": "Feature",
  "properties": {
    "tgn:hierarchy":[
        "tgn:2443865",
        "tgn:7006450",
        "tgn:1000001",
        "tgn:7012149",
        "tgn:7019760",
        "tgn:7029392"
    ],
    "tgn:id":2443865,
    "tgn:name":"La Perouse Glacier",
    "tgn:placetype":[
        "aat:300008835"
    ]
},
  "bbox": [],
  "geometry": {"coordinates":[-137.2167,58.5333],"type":"Point"}
}