{
  "id": 2524592,
  "type": "Feature",
  "properties": {
    "tgn:hierarchy":[
        "tgn:2524592",
        "tgn:1000001",
        "tgn:7012149",
        "tgn:7007157",
        "tgn:1002858",
        "tgn:7029392"
    ],
    "tgn:id":2524592,
    "tgn:name":"Morley Field",
    "tgn:placetype":[
        "aat:300055621"
    ]
},
  "bbox": [],
  "geometry": {"coordinates":[-117.1333,32.7333],"type":"Point"}
}