{
  "id": 2499228,
  "type": "Feature",
  "properties": {
    "tgn:hierarchy":[
        "tgn:2499228",
        "tgn:1000001",
        "tgn:7012149",
        "tgn:7018871",
        "tgn:7007920",
        "tgn:7029392"
    ],
    "tgn:id":2499228,
    "tgn:name":"McClain Peaks",
    "tgn:placetype":[
        "aat:300008798"
    ]
},
  "bbox": [],
  "geometry": {"coordinates":[-121.55,47.6833],"type":"Point"}
}