{
  "id": 7009231,
  "type": "Feature",
  "properties": {
    "tgn:hierarchy":[
        "tgn:7009231",
        "tgn:1000003",
        "tgn:7002880",
        "tgn:1000070",
        "tgn:7029392"
    ],
    "tgn:id":7009231,
    "tgn:name":"Hautvillers",
    "tgn:placetype":[
        "aat:300008347"
    ]
},
  "bbox": [],
  "geometry": {"coordinates":[3.95,49.0833],"type":"Point"}
}