{
  "id": 2205010,
  "type": "Feature",
  "properties": {
    "tgn:hierarchy":[
        "tgn:2205010",
        "tgn:1000001",
        "tgn:1002276",
        "tgn:7012149",
        "tgn:7007708",
        "tgn:7029392"
    ],
    "tgn:id":2205010,
    "tgn:name":"Bugby Hole",
    "tgn:placetype":[
        "aat:300386845"
    ]
},
  "bbox": [],
  "geometry": {"coordinates":[-123.4167,46.1667],"type":"Point"}
}