{
  "id": 7458689,
  "type": "Feature",
  "properties": {
    "tgn:hierarchy":[
        "tgn:7458689",
        "tgn:7002448",
        "tgn:7019157",
        "tgn:1000003",
        "tgn:7008591",
        "tgn:7029392"
    ],
    "tgn:id":7458689,
    "tgn:name:en":"Lurigethan",
    "tgn:placetype":[
        "aat:300008795"
    ]
},
  "bbox": [],
  "geometry": {"coordinates":[-6.083333,55.05],"type":"Point"}
}