{
  "id": 7303679,
  "type": "Feature",
  "properties": {
    "tgn:hierarchy":[
        "tgn:7303679",
        "tgn:7002816",
        "tgn:1001647",
        "tgn:1000003",
        "tgn:1000095",
        "tgn:7029392"
    ],
    "tgn:id":7303679,
    "tgn:name":"Navalagrulla, Laguna de",
    "tgn:placetype":[
        "aat:300008680"
    ]
},
  "bbox": [],
  "geometry": {"coordinates":[-3.633333,38.733333],"type":"Point"}
}