{
  "id": 7345156,
  "type": "Feature",
  "properties": {
    "tgn:hierarchy":[
        "tgn:7345156",
        "tgn:7002758",
        "tgn:7002823",
        "tgn:1000003",
        "tgn:1000095",
        "tgn:7029392"
    ],
    "tgn:id":7345156,
    "tgn:name":"Algarrobo, Arroyo del",
    "tgn:placetype":[
        "aat:300008699"
    ]
},
  "bbox": [],
  "geometry": {"coordinates":[-6.433333,37.216667],"type":"Point"}
}