{
  "id": 1059126,
  "type": "Feature",
  "properties": {
    "tgn:hierarchy":[
        "tgn:1059126",
        "tgn:1000003",
        "tgn:7011999",
        "tgn:7006660",
        "tgn:7029392"
    ],
    "tgn:id":1059126,
    "tgn:name":"Sal'nytsya",
    "tgn:placetype":[
        "aat:300008347"
    ]
},
  "bbox": [],
  "geometry": {"coordinates":[28.0333,49.7333],"type":"Point"}
}