{
  "id": 2786198,
  "type": "Feature",
  "properties": {
    "tgn:hierarchy":[
        "tgn:2786198",
        "tgn:1000001",
        "tgn:7012149",
        "tgn:2001723",
        "tgn:7007708",
        "tgn:7029392"
    ],
    "tgn:id":2786198,
    "tgn:name":"Younger Spring",
    "tgn:placetype":[
        "aat:300008697"
    ]
},
  "bbox": [],
  "geometry": {"coordinates":[-119.9833,44.4333],"type":"Point"}
}