{
  "id": 2293522,
  "type": "Feature",
  "properties": {
    "tgn:hierarchy":[
        "tgn:2293522",
        "tgn:1000001",
        "tgn:7012149",
        "tgn:2001911",
        "tgn:7007825",
        "tgn:7029392"
    ],
    "tgn:id":2293522,
    "tgn:name":"Double Spring",
    "tgn:placetype":[
        "aat:300008697"
    ]
},
  "bbox": [],
  "geometry": {"coordinates":[-86.3333,35.8167],"type":"Point"}
}