<<<<<<< HEAD
{
  "id": 2403497,
  "type": "Feature",
  "properties": {
    "tgn:hierarchy":[
        "tgn:2403497",
        "tgn:1000001",
        "tgn:7013368",
        "tgn:7012149",
        "tgn:7007709",
        "tgn:7029392"
    ],
    "tgn:id":2403497,
    "tgn:name":"How Point",
    "tgn:placetype":[
        "aat:300008850"
    ]
},
  "bbox": [],
  "geometry": {"coordinates":[-76.65,35.35],"type":"Point"}
}
=======
{"geometry":{"type":"Point","coordinates":[-76.650000,35.350000]},"type":"Feature","properties":{"hierarchy":["tgn:2403497","tgn:1000001","tgn:7013368","tgn:7012149","tgn:7007709","tgn:7029392"],"placetype":["aat:300008850"],"id":2403497,"name:xx":"How Point"}}
>>>>>>> 03f74aca74312dbeaf24d7e61306dd6a786dc3d0
