{
  "id": 2403497,
  "type": "Feature",
  "properties": {
    "tgn:hierarchy":[
        "tgn:2403497",
        "tgn:1000001",
        "tgn:7013368",
        "tgn:7012149",
        "tgn:7007709",
        "tgn:7029392"
    ],
    "tgn:id":2403497,
    "tgn:name":"How Point",
    "tgn:placetype":[
        "aat:300008850"
    ]
},
  "bbox": [],
  "geometry": {"coordinates":[-76.65,35.35],"type":"Point"}
}