{
  "id": 7173547,
  "type": "Feature",
  "properties": {
    "tgn:hierarchy":[
        "tgn:7173547",
        "tgn:1000003",
        "tgn:7003676",
        "tgn:7000084",
        "tgn:7029392"
    ],
    "tgn:id":7173547,
    "tgn:name":"Gr\u00fcnegras",
    "tgn:placetype":[
        "aat:300008347"
    ]
},
  "bbox": [],
  "geometry": {"coordinates":[7.916667,52.416667],"type":"Point"}
}