{
  "id": 7546540,
  "type": "Feature",
  "properties": {
    "tgn:hierarchy":[
        "tgn:7546540",
        "tgn:1000004",
        "tgn:7000198",
        "tgn:1001895",
        "tgn:7029392"
    ],
    "tgn:id":7546540,
    "tgn:name:en":"B\u0101z\u0101rgaon",
    "tgn:placetype":[
        "aat:300008347"
    ]
},
  "bbox": [],
  "geometry": {"coordinates":[78.771345,21.139447],"type":"Point"}
}