{
  "id": 2483102,
  "type": "Feature",
  "properties": {
    "tgn:hierarchy":[
        "tgn:2483102",
        "tgn:1000001",
        "tgn:2002317",
        "tgn:7012149",
        "tgn:7007922",
        "tgn:7029392"
    ],
    "tgn:id":2483102,
    "tgn:name":"Larson Swamp",
    "tgn:placetype":[
        "aat:300008905"
    ]
},
  "bbox": [],
  "geometry": {"coordinates":[-87.4667,44.85],"type":"Point"}
}