{
  "id": 2573137,
  "type": "Feature",
  "properties": {
    "tgn:hierarchy":[
        "tgn:2573137",
        "tgn:1000001",
        "tgn:2002241",
        "tgn:7012149",
        "tgn:7007920",
        "tgn:7029392"
    ],
    "tgn:id":2573137,
    "tgn:name":"Pearson Spring",
    "tgn:placetype":[
        "aat:300008697"
    ]
},
  "bbox": [],
  "geometry": {"coordinates":[-117.6333,46.05],"type":"Point"}
}