{
  "id": 2193895,
  "type": "Feature",
  "properties": {
    "tgn:hierarchy":[
        "tgn:2193895",
        "tgn:1000001",
        "tgn:7012149",
        "tgn:2002346",
        "tgn:7007922",
        "tgn:7029392"
    ],
    "tgn:id":2193895,
    "tgn:name":"Briar Lake",
    "tgn:placetype":[
        "aat:300008680"
    ]
},
  "bbox": [],
  "geometry": {"coordinates":[-92.2833,45.7167],"type":"Point"}
}