{
  "id": 1095692,
  "type": "Feature",
  "properties": {
    "tgn:hierarchy":[
        "tgn:1095692",
        "tgn:7001242",
        "tgn:7016833",
        "tgn:1001418",
        "tgn:7029392"
    ],
    "tgn:id":1095692,
    "tgn:name:en":"S\u012blah",
    "tgn:placetype":[
        "aat:300008347"
    ]
},
  "bbox": [],
  "geometry": {"coordinates":[30.969799,29.353309],"type":"Point"}
}