{
  "id": 7029549,
  "type": "Feature",
  "properties": {
    "tgn:hierarchy":[
        "tgn:7029549",
        "tgn:1001109",
        "tgn:1000004",
        "tgn:1000118",
        "tgn:7001784",
        "tgn:7029392"
    ],
    "tgn:id":7029549,
    "tgn:name":"Anab",
    "tgn:placetype":[
        "aat:300008347"
    ]
},
  "bbox": [],
  "geometry": {"coordinates":[46.016,35.206],"type":"Point"}
}