<<<<<<< HEAD
{
  "id": 7482306,
  "type": "Feature",
  "properties": {
    "tgn:hierarchy":[
        "tgn:7482306",
        "tgn:1000004",
        "tgn:7489179",
        "tgn:1000141",
        "tgn:7029392"
    ],
    "tgn:id":7482306,
    "tgn:name":"Tayafu Shan",
    "tgn:placetype":[
        "aat:300008798"
    ]
},
  "bbox": [],
  "geometry": {"coordinates":[121.335,24.44],"type":"Point"}
}
=======
{"geometry":{"type":"Point","coordinates":[121.335000,24.440000]},"type":"Feature","properties":{"hierarchy":["tgn:7482306","tgn:1000004","tgn:7489179","tgn:1000141","tgn:7029392"],"placetype":["aat:300008798"],"id":7482306,"name:xx":"Tayafu Shan"}}
>>>>>>> 03f74aca74312dbeaf24d7e61306dd6a786dc3d0
