{
  "id": 2579627,
  "type": "Feature",
  "properties": {
    "tgn:hierarchy":[
        "tgn:2579627",
        "tgn:1000001",
        "tgn:7006451",
        "tgn:2000091",
        "tgn:7012149",
        "tgn:7029392"
    ],
    "tgn:id":2579627,
    "tgn:name":"Pickhandle Hills",
    "tgn:placetype":[
        "aat:300386831"
    ]
},
  "bbox": [],
  "geometry": {"coordinates":[-109.1167,31.3833],"type":"Point"}
}