<<<<<<< HEAD
{
  "id": 7370876,
  "type": "Feature",
  "properties": {
    "tgn:hierarchy":[
        "tgn:7370876",
        "tgn:7005580",
        "tgn:1000001",
        "tgn:7005560",
        "tgn:7029392"
    ],
    "tgn:id":7370876,
    "tgn:name":"G\u00f3mez",
    "tgn:placetype":[
        "aat:300008347"
    ]
},
  "bbox": [],
  "geometry": {"coordinates":[-93.45,17.1],"type":"Point"}
}
=======
{"geometry":{"type":"Point","coordinates":[-93.450000,17.100000]},"type":"Feature","properties":{"hierarchy":["tgn:7370876","tgn:7005580","tgn:1000001","tgn:7005560","tgn:7029392"],"placetype":["aat:300008347"],"id":7370876,"name:xx":"G\u00f3mez"}}
>>>>>>> 03f74aca74312dbeaf24d7e61306dd6a786dc3d0
