{
  "id": 2155127,
  "type": "Feature",
  "properties": {
    "tgn:hierarchy":[
        "tgn:2155127",
        "tgn:1002148",
        "tgn:1000001",
        "tgn:7012149",
        "tgn:7007826",
        "tgn:7029392"
    ],
    "tgn:id":2155127,
    "tgn:name":"Bear Lake",
    "tgn:placetype":[
        "aat:300008680"
    ]
},
  "bbox": [],
  "geometry": {"coordinates":[-95.8833,31.7667],"type":"Point"}
}