{
  "id": 7589177,
  "type": "Feature",
  "properties": {
    "tgn:hierarchy":[
        "tgn:7589177",
        "tgn:1000004",
        "tgn:7000198",
        "tgn:7000799",
        "tgn:7029392"
    ],
    "tgn:id":7589177,
    "tgn:name:en":"Lorihom",
    "tgn:placetype":[
        "aat:300008347"
    ]
},
  "bbox": [],
  "geometry": {"coordinates":[74.405223,34.285729],"type":"Point"}
}