{
  "id": 2041328,
  "type": "Feature",
  "properties": {
    "tgn:hierarchy":[
        "tgn:2041328",
        "tgn:1002169",
        "tgn:1000001",
        "tgn:7012149",
        "tgn:7007255",
        "tgn:7029392"
    ],
    "tgn:id":2041328,
    "tgn:name":"Slate Valley",
    "tgn:placetype":[
        "aat:300008347"
    ]
},
  "bbox": [],
  "geometry": {"coordinates":[-83.7167,38.1667],"type":"Point"}
}