{
  "id": 7335550,
  "type": "Feature",
  "properties": {
    "tgn:hierarchy":[
        "tgn:7335550",
        "tgn:7002849",
        "tgn:1000003",
        "tgn:7009604",
        "tgn:1000095",
        "tgn:7029392"
    ],
    "tgn:id":7335550,
    "tgn:name":"Gallarta",
    "tgn:placetype":[
        "aat:300008347"
    ]
},
  "bbox": [],
  "geometry": {"coordinates":[-3.069712,43.310768],"type":"Point"}
}