{
  "id": 7192444,
  "type": "Feature",
  "properties": {
    "tgn:hierarchy":[
        "tgn:7192444",
        "tgn:7003692",
        "tgn:1000003",
        "tgn:7000084",
        "tgn:7029392"
    ],
    "tgn:id":7192444,
    "tgn:name":"Fl\u00f6hberg",
    "tgn:placetype":[
        "aat:300008777"
    ]
},
  "bbox": [],
  "geometry": {"coordinates":[9.516667,49.75],"type":"Point"}
}