{
  "id": 2359736,
  "type": "Feature",
  "properties": {
    "tgn:hierarchy":[
        "tgn:2359736",
        "tgn:1000001",
        "tgn:1002601",
        "tgn:7012149",
        "tgn:7007159",
        "tgn:7029392"
    ],
    "tgn:id":2359736,
    "tgn:name":"Grapeville",
    "tgn:placetype":[
        "aat:300008347"
    ]
},
  "bbox": [],
  "geometry": {"coordinates":[-73.2167,41.7167],"type":"Point"}
}