<<<<<<< HEAD
{
  "id": 2765908,
  "type": "Feature",
  "properties": {
    "tgn:hierarchy":[
        "tgn:2765908",
        "tgn:1000001",
        "tgn:7012149",
        "tgn:1002612",
        "tgn:7007710",
        "tgn:7029392"
    ],
    "tgn:id":2765908,
    "tgn:name":"White Haven Center",
    "tgn:placetype":[
        "aat:300008347"
    ]
},
  "bbox": [],
  "geometry": {"coordinates":[-75.7833,41.05],"type":"Point"}
}
=======
{"geometry":{"type":"Point","coordinates":[-75.783300,41.050000]},"type":"Feature","properties":{"hierarchy":["tgn:2765908","tgn:1000001","tgn:7012149","tgn:1002612","tgn:7007710","tgn:7029392"],"placetype":["aat:300008347"],"id":2765908,"name:xx":"White Haven Center"}}
>>>>>>> 03f74aca74312dbeaf24d7e61306dd6a786dc3d0
