{
  "id": 2325027,
  "type": "Feature",
  "properties": {
    "tgn:hierarchy":[
        "tgn:2325027",
        "tgn:1000001",
        "tgn:7012149",
        "tgn:7018871",
        "tgn:7007920",
        "tgn:7029392"
    ],
    "tgn:id":2325027,
    "tgn:name":"Fern Cove",
    "tgn:placetype":[
        "aat:300132316"
    ]
},
  "bbox": [],
  "geometry": {"coordinates":[-122.4667,47.4667],"type":"Point"}
}