{
  "id": 1099222,
  "type": "Feature",
  "properties": {
    "tgn:hierarchy":[
        "tgn:1099222",
        "tgn:7000508",
        "tgn:1008380",
        "tgn:1000226",
        "tgn:1000006",
        "tgn:7029392"
    ],
    "tgn:id":1099222,
    "tgn:name:en":"Silverdale",
    "tgn:placetype":[
        "aat:300008347"
    ]
},
  "bbox": [],
  "geometry": {"coordinates":[174.666667,-36.616667],"type":"Point"}
}