{
  "id": 2730630,
  "type": "Feature",
  "properties": {
    "tgn:hierarchy":[
        "tgn:2730630",
        "tgn:1000001",
        "tgn:7012149",
        "tgn:2000907",
        "tgn:7007256",
        "tgn:7029392"
    ],
    "tgn:id":2730630,
    "tgn:name":"Trusler Lake",
    "tgn:placetype":[
        "aat:300008680"
    ]
},
  "bbox": [],
  "geometry": {"coordinates":[-91.4667,32.1167],"type":"Point"}
}