{
  "id": 1107814,
  "type": "Feature",
  "properties": {
    "tgn:hierarchy":[
        "tgn:1107814",
        "tgn:7001242",
        "tgn:7016833",
        "tgn:1001418",
        "tgn:7029392"
    ],
    "tgn:id":1107814,
    "tgn:name":"\u02bbAbd al \u1e24af\u012bz, Q\u0101rat",
    "tgn:placetype":[
        "aat:300008777"
    ]
},
  "bbox": [],
  "geometry": {"coordinates":[30.133333,28.883333],"type":"Point"}
}