{
  "id": 2356359,
  "type": "Feature",
  "properties": {
    "tgn:hierarchy":[
        "tgn:2356359",
        "tgn:1002146",
        "tgn:1000001",
        "tgn:7012149",
        "tgn:7007157",
        "tgn:7029392"
    ],
    "tgn:id":2356359,
    "tgn:name":"Gopher Mine",
    "tgn:placetype":[
        "aat:300000390"
    ]
},
  "bbox": [],
  "geometry": {"coordinates":[-120.8167,38.4333],"type":"Point"}
}