<<<<<<< HEAD
{
  "id": 7484862,
  "type": "Feature",
  "properties": {
    "tgn:hierarchy":[
        "tgn:7484862",
        "tgn:1000004",
        "tgn:7490934",
        "tgn:1000141",
        "tgn:7029392"
    ],
    "tgn:id":7484862,
    "tgn:name":"Houcengkeng",
    "tgn:placetype":[
        "aat:300008699"
    ]
},
  "bbox": [],
  "geometry": {"coordinates":[120.5825,23.140833],"type":"Point"}
}
=======
{"geometry":{"type":"Point","coordinates":[120.582500,23.140833]},"type":"Feature","properties":{"hierarchy":["tgn:7484862","tgn:1000004","tgn:7490934","tgn:1000141","tgn:7029392"],"placetype":["aat:300008699"],"id":7484862,"name:xx":"Houcengkeng"}}
>>>>>>> 03f74aca74312dbeaf24d7e61306dd6a786dc3d0
