{
  "id": 2132606,
  "type": "Feature",
  "properties": {
    "tgn:hierarchy":[
        "tgn:2132606",
        "tgn:1007657",
        "tgn:1002534",
        "tgn:1000001",
        "tgn:7012149",
        "tgn:7007249",
        "tgn:7029392"
    ],
    "tgn:id":2132606,
    "tgn:name":"Anahola",
    "tgn:placetype":[
        "aat:300008798"
    ]
},
  "bbox": [],
  "geometry": {"coordinates":[-159.3833,22.1333],"type":"Point"}
}