{
  "id": 2438462,
  "type": "Feature",
  "properties": {
    "tgn:hierarchy":[
        "tgn:2438462",
        "tgn:1002201",
        "tgn:1000001",
        "tgn:7012149",
        "tgn:7007517",
        "tgn:7029392"
    ],
    "tgn:id":2438462,
    "tgn:name":"Kings Pond",
    "tgn:placetype":[
        "aat:300008680"
    ]
},
  "bbox": [],
  "geometry": {"coordinates":[-71.05,41.9333],"type":"Point"}
}