<<<<<<< HEAD
{
  "id": 7024878,
  "type": "Feature",
  "properties": {
    "tgn:hierarchy":[
        "tgn:7024878",
        "tgn:1006323",
        "tgn:7002444",
        "tgn:1000003",
        "tgn:7019091",
        "tgn:7008591",
        "tgn:7029392"
    ],
    "tgn:id":7024878,
    "tgn:name:en":"Machrie Water",
    "tgn:placetype":[
        "aat:300008699"
    ]
},
  "bbox": [],
  "geometry": {"coordinates":[-5.333333,55.55],"type":"Point"}
}
=======
{"geometry":{"type":"Point","coordinates":[-5.333333,55.550000]},"type":"Feature","properties":{"hierarchy":["tgn:7024878","tgn:1006323","tgn:7002444","tgn:1000003","tgn:7019091","tgn:7008591","tgn:7029392"],"placetype":["aat:300008699"],"name:en":"Machrie Water","id":7024878}}
>>>>>>> 03f74aca74312dbeaf24d7e61306dd6a786dc3d0
