{
  "id": 2700256,
  "type": "Feature",
  "properties": {
    "tgn:hierarchy":[
        "tgn:2700256",
        "tgn:1000001",
        "tgn:1002275",
        "tgn:7012149",
        "tgn:7007920",
        "tgn:7029392"
    ],
    "tgn:id":2700256,
    "tgn:name":"Sturgeon Rock",
    "tgn:placetype":[
        "aat:300008798"
    ]
},
  "bbox": [],
  "geometry": {"coordinates":[-122.2667,45.7333],"type":"Point"}
}