{
  "id": 7218968,
  "type": "Feature",
  "properties": {
    "tgn:hierarchy":[
        "tgn:7218968",
        "tgn:7002750",
        "tgn:7001399",
        "tgn:1000003",
        "tgn:1000074",
        "tgn:7029392"
    ],
    "tgn:id":7218968,
    "tgn:name":"\u00c1zoros",
    "tgn:placetype":[
        "aat:300008347"
    ]
},
  "bbox": [],
  "geometry": {"coordinates":[22.071944,39.999444],"type":"Point"}
}