{
  "id": 7474394,
  "type": "Feature",
  "properties": {
    "tgn:hierarchy":[
        "tgn:7474394",
        "tgn:1000004",
        "tgn:7490934",
        "tgn:1000141",
        "tgn:7029392"
    ],
    "tgn:id":7474394,
    "tgn:name":"Dongkou",
    "tgn:placetype":[
        "aat:300008347"
    ]
},
  "bbox": [],
  "geometry": {"coordinates":[120.491199,23.220654],"type":"Point"}
}