{
  "id": 6001564,
  "type": "Feature",
  "properties": {
    "tgn:hierarchy":[
        "tgn:6001564",
        "tgn:7002739",
        "tgn:7017076",
        "tgn:1000003",
        "tgn:1000074",
        "tgn:7029392"
    ],
    "tgn:id":6001564,
    "tgn:name":"Korone",
    "tgn:placetype":[
        "aat:300008347",
        "aat:300000810",
        "aat:300167671"
    ]
},
  "bbox": [],
  "geometry": {"coordinates":[22.862071,37.545403],"type":"Point"}
}