<<<<<<< HEAD
{
  "id": 7352035,
  "type": "Feature",
  "properties": {
    "tgn:hierarchy":[
        "tgn:7352035",
        "tgn:7005581",
        "tgn:1000001",
        "tgn:7005560",
        "tgn:7029392"
    ],
    "tgn:id":7352035,
    "tgn:name":"Rancho Arroyo Seco",
    "tgn:placetype":[
        "aat:300000241"
    ]
},
  "bbox": [],
  "geometry": {"coordinates":[-107.883333,30.2],"type":"Point"}
}
=======
{"geometry":{"type":"Point","coordinates":[-107.883333,30.200000]},"type":"Feature","properties":{"hierarchy":["tgn:7352035","tgn:7005581","tgn:1000001","tgn:7005560","tgn:7029392"],"placetype":["aat:300000241"],"id":7352035,"name:xx":"Rancho Arroyo Seco"}}
>>>>>>> 03f74aca74312dbeaf24d7e61306dd6a786dc3d0
