{
  "id": 2513949,
  "type": "Feature",
  "properties": {
    "tgn:hierarchy":[
        "tgn:2513949",
        "tgn:1000001",
        "tgn:7012149",
        "tgn:7007523",
        "tgn:7029392"
    ],
    "tgn:id":2513949,
    "tgn:name":"Millam Creek",
    "tgn:placetype":[
        "aat:300008706"
    ]
},
  "bbox": [],
  "geometry": {"coordinates":[-91.3167,38.85],"type":"Point"}
}