<<<<<<< HEAD
{
  "id": 7358779,
  "type": "Feature",
  "properties": {
    "tgn:hierarchy":[
        "tgn:7358779",
        "tgn:7005587",
        "tgn:1000001",
        "tgn:7005560",
        "tgn:7029392"
    ],
    "tgn:id":7358779,
    "tgn:name":"El Aguacate",
    "tgn:placetype":[
        "aat:300008347"
    ]
},
  "bbox": [],
  "geometry": {"coordinates":[-98.166667,20.383333],"type":"Point"}
}
=======
{"geometry":{"type":"Point","coordinates":[-98.166667,20.383333]},"type":"Feature","properties":{"hierarchy":["tgn:7358779","tgn:7005587","tgn:1000001","tgn:7005560","tgn:7029392"],"placetype":["aat:300008347"],"id":7358779,"name:xx":"El Aguacate"}}
>>>>>>> 03f74aca74312dbeaf24d7e61306dd6a786dc3d0
