{
  "id": 2490972,
  "type": "Feature",
  "properties": {
    "tgn:hierarchy":[
        "tgn:2490972",
        "tgn:1000001",
        "tgn:7012149",
        "tgn:2002120",
        "tgn:7007827",
        "tgn:7029392"
    ],
    "tgn:id":2490972,
    "tgn:name":"Manti Mountain",
    "tgn:placetype":[
        "aat:300008798"
    ]
},
  "bbox": [],
  "geometry": {"coordinates":[-111.5333,39.2667],"type":"Point"}
}