<<<<<<< HEAD
{
  "id": 7369790,
  "type": "Feature",
  "properties": {
    "tgn:hierarchy":[
        "tgn:7369790",
        "tgn:7005580",
        "tgn:1000001",
        "tgn:7005560",
        "tgn:7029392"
    ],
    "tgn:id":7369790,
    "tgn:name":"Jachinul\u00e1",
    "tgn:placetype":[
        "aat:300008699"
    ]
},
  "bbox": [],
  "geometry": {"coordinates":[-92.3,15.7],"type":"Point"}
}
=======
{"geometry":{"type":"Point","coordinates":[-92.300000,15.700000]},"type":"Feature","properties":{"hierarchy":["tgn:7369790","tgn:7005580","tgn:1000001","tgn:7005560","tgn:7029392"],"placetype":["aat:300008699"],"id":7369790,"name:xx":"Jachinul\u00e1"}}
>>>>>>> 03f74aca74312dbeaf24d7e61306dd6a786dc3d0
