{
  "id": 2744416,
  "type": "Feature",
  "properties": {
    "tgn:hierarchy":[
        "tgn:2744416",
        "tgn:1000001",
        "tgn:7012149",
        "tgn:2001925",
        "tgn:7007825",
        "tgn:7029392"
    ],
    "tgn:id":2744416,
    "tgn:name":"Vervilla",
    "tgn:placetype":[
        "aat:300008347"
    ]
},
  "bbox": [],
  "geometry": {"coordinates":[-85.8667,35.5833],"type":"Point"}
}