{
  "id": 2042022,
  "type": "Feature",
  "properties": {
    "tgn:hierarchy":[
        "tgn:2042022",
        "tgn:1000001",
        "tgn:7012149",
        "tgn:2000837",
        "tgn:7007255",
        "tgn:7029392"
    ],
    "tgn:id":2042022,
    "tgn:name":"Wolfpit",
    "tgn:placetype":[
        "aat:300008347"
    ]
},
  "bbox": [],
  "geometry": {"coordinates":[-82.4167,37.35],"type":"Point"}
}