{
  "id": 2220504,
  "type": "Feature",
  "properties": {
    "tgn:hierarchy":[
        "tgn:2220504",
        "tgn:7006450",
        "tgn:1000001",
        "tgn:7012149",
        "tgn:2000082",
        "tgn:7029392"
    ],
    "tgn:id":2220504,
    "tgn:name":"Cape Lynch",
    "tgn:placetype":[
        "aat:300008850"
    ]
},
  "bbox": [],
  "geometry": {"coordinates":[-133.6833,55.7667],"type":"Point"}
}