{
  "id": 7337421,
  "type": "Feature",
  "properties": {
    "tgn:hierarchy":[
        "tgn:7337421",
        "tgn:7002804",
        "tgn:1000003",
        "tgn:7002793",
        "tgn:1000095",
        "tgn:7029392"
    ],
    "tgn:id":7337421,
    "tgn:name":"Cid, Sierra del",
    "tgn:placetype":[
        "aat:300008795"
    ]
},
  "bbox": [],
  "geometry": {"coordinates":[-0.716667,38.466667],"type":"Point"}
}