<<<<<<< HEAD
{
  "id": 2331747,
  "type": "Feature",
  "properties": {
    "tgn:hierarchy":[
        "tgn:2331747",
        "tgn:1000001",
        "tgn:7012149",
        "tgn:2002382",
        "tgn:7007923",
        "tgn:7029392"
    ],
    "tgn:id":2331747,
    "tgn:name":"Fleming Slough",
    "tgn:placetype":[
        "aat:300008699"
    ]
},
  "bbox": [],
  "geometry": {"coordinates":[-110.25,42.65],"type":"Point"}
}
=======
{"geometry":{"type":"Point","coordinates":[-110.250000,42.650000]},"type":"Feature","properties":{"hierarchy":["tgn:2331747","tgn:1000001","tgn:7012149","tgn:2002382","tgn:7007923","tgn:7029392"],"placetype":["aat:300008699"],"id":2331747,"name:xx":"Fleming Slough"}}
>>>>>>> 03f74aca74312dbeaf24d7e61306dd6a786dc3d0
