{
  "id": 2355733,
  "type": "Feature",
  "properties": {
    "tgn:hierarchy":[
        "tgn:2355733",
        "tgn:1000001",
        "tgn:1002337",
        "tgn:7012149",
        "tgn:7007922",
        "tgn:7029392"
    ],
    "tgn:id":2355733,
    "tgn:name":"Goose Island",
    "tgn:placetype":[
        "aat:300008791"
    ]
},
  "bbox": [],
  "geometry": {"coordinates":[-88.65,43.5333],"type":"Point"}
}