{
  "id": 2046352,
  "type": "Feature",
  "properties": {
    "tgn:hierarchy":[
        "tgn:2046352",
        "tgn:1000001",
        "tgn:7016106",
        "tgn:7012149",
        "tgn:7007516",
        "tgn:7029392"
    ],
    "tgn:id":2046352,
    "tgn:name":"Breathedsville",
    "tgn:placetype":[
        "aat:300008347"
    ]
},
  "bbox": [],
  "geometry": {"coordinates":[-77.7167,39.5333],"type":"Point"}
}