{
  "id": 7110696,
  "type": "Feature",
  "properties": {
    "tgn:hierarchy":[
        "tgn:7110696",
        "tgn:7003669",
        "tgn:1000003",
        "tgn:7000084",
        "tgn:7029392"
    ],
    "tgn:id":7110696,
    "tgn:name":"Reichersdorf",
    "tgn:placetype":[
        "aat:300008347"
    ]
},
  "bbox": [],
  "geometry": {"coordinates":[13.083333,48.75],"type":"Point"}
}