{
  "id": 7245561,
  "type": "Feature",
  "properties": {
    "tgn:hierarchy":[
        "tgn:7245561",
        "tgn:7007877",
        "tgn:1000003",
        "tgn:1000063",
        "tgn:4012014",
        "tgn:7029392"
    ],
    "tgn:id":7245561,
    "tgn:name":"Ferme Beaudribu",
    "tgn:placetype":[
        "aat:300000206"
    ]
},
  "bbox": [],
  "geometry": {"coordinates":[4.333333,50.333333],"type":"Point"}
}