{
  "id": 1110436,
  "type": "Feature",
  "properties": {
    "tgn:hierarchy":[
        "tgn:1110436",
        "tgn:1000767",
        "tgn:1000002",
        "tgn:1000058",
        "tgn:7029392"
    ],
    "tgn:id":1110436,
    "tgn:name":"Corralito, Cuchilla del",
    "tgn:placetype":[
        "aat:300008777"
    ]
},
  "bbox": [],
  "geometry": {"coordinates":[-57.7333,-33.6667],"type":"Point"}
}