{
  "id": 7385173,
  "type": "Feature",
  "properties": {
    "tgn:hierarchy":[
        "tgn:7385173",
        "tgn:7005580",
        "tgn:1000001",
        "tgn:7005560",
        "tgn:7029392"
    ],
    "tgn:id":7385173,
    "tgn:name":"Nicol\u00e1s Bravo N\u00famero Dos",
    "tgn:placetype":[
        "aat:300008347"
    ]
},
  "bbox": [],
  "geometry": {"coordinates":[-92.833333,15.35],"type":"Point"}
}