{
  "id": 7213162,
  "type": "Feature",
  "properties": {
    "tgn:hierarchy":[
        "tgn:7213162",
        "tgn:1000003",
        "tgn:7003687",
        "tgn:7000084",
        "tgn:7029392"
    ],
    "tgn:id":7213162,
    "tgn:name":"Bone",
    "tgn:placetype":[
        "aat:300008347"
    ]
},
  "bbox": [],
  "geometry": {"coordinates":[12.133333,51.966667],"type":"Point"}
}