{
  "id": 7104187,
  "type": "Feature",
  "properties": {
    "tgn:hierarchy":[
        "tgn:7104187",
        "tgn:1000003",
        "tgn:7003688",
        "tgn:7000084",
        "tgn:7029392"
    ],
    "tgn:id":7104187,
    "tgn:name":"Scheelenkuhlen",
    "tgn:placetype":[
        "aat:300000206"
    ]
},
  "bbox": [],
  "geometry": {"coordinates":[9.266667,53.883333],"type":"Point"}
}