{
  "id": 7032596,
  "type": "Feature",
  "properties": {
    "tgn:hierarchy":[
        "tgn:7032596",
        "tgn:7001242",
        "tgn:1000905",
        "tgn:1000150",
        "tgn:7029392"
    ],
    "tgn:id":7032596,
    "tgn:name":"Tsodilo Hills",
    "tgn:placetype":[
        "aat:300387241",
        "aat:300000810",
        "aat:300266152",
        "aat:300387006",
        "aat:300263063",
        "aat:300008777"
    ]
},
  "bbox": [],
  "geometry": {"coordinates":[21.779,-18.75],"type":"Point"}
}