{
  "id": 2396853,
  "type": "Feature",
  "properties": {
    "tgn:hierarchy":[
        "tgn:2396853",
        "tgn:1000001",
        "tgn:7012149",
        "tgn:2001769",
        "tgn:7007712",
        "tgn:7029392"
    ],
    "tgn:id":2396853,
    "tgn:name":"Home Swamp",
    "tgn:placetype":[
        "aat:300008699"
    ]
},
  "bbox": [],
  "geometry": {"coordinates":[-79.7167,33.65],"type":"Point"}
}