{
  "id": 2649155,
  "type": "Feature",
  "properties": {
    "tgn:hierarchy":[
        "tgn:2649155",
        "tgn:1000001",
        "tgn:7012149",
        "tgn:1002737",
        "tgn:7007520",
        "tgn:7029392"
    ],
    "tgn:id":2649155,
    "tgn:name":"Scott Lake",
    "tgn:placetype":[
        "aat:300008680"
    ]
},
  "bbox": [],
  "geometry": {"coordinates":[-83.35,42.6667],"type":"Point"}
}