{
  "id": 7564865,
  "type": "Feature",
  "properties": {
    "tgn:hierarchy":[
        "tgn:7564865",
        "tgn:1000004",
        "tgn:7000198",
        "tgn:7016722",
        "tgn:7029392"
    ],
    "tgn:id":7564865,
    "tgn:name:en":"Ekm\u0101n",
    "tgn:placetype":[
        "aat:300008347"
    ]
},
  "bbox": [],
  "geometry": {"coordinates":[79.627468,26.902102],"type":"Point"}
}