<<<<<<< HEAD
{
  "id": 2155841,
  "type": "Feature",
  "properties": {
    "tgn:hierarchy":[
        "tgn:2155841",
        "tgn:1000001",
        "tgn:2000458",
        "tgn:7012149",
        "tgn:7007250",
        "tgn:7029392"
    ],
    "tgn:id":2155841,
    "tgn:name":"Bear Trap Cave",
    "tgn:placetype":[
        "aat:300008746"
    ]
},
  "bbox": [],
  "geometry": {"coordinates":[-113.35,42.9833],"type":"Point"}
}
=======
{"geometry":{"type":"Point","coordinates":[-113.350000,42.983300]},"type":"Feature","properties":{"hierarchy":["tgn:2155841","tgn:1000001","tgn:2000458","tgn:7012149","tgn:7007250","tgn:7029392"],"placetype":["aat:300008746"],"id":2155841,"name:xx":"Bear Trap Cave"}}
>>>>>>> 03f74aca74312dbeaf24d7e61306dd6a786dc3d0
