{
  "id": 2602746,
  "type": "Feature",
  "properties": {
    "tgn:hierarchy":[
        "tgn:2602746",
        "tgn:1000001",
        "tgn:7012149",
        "tgn:2002118",
        "tgn:7007827",
        "tgn:7029392"
    ],
    "tgn:id":2602746,
    "tgn:name":"Quail Valley",
    "tgn:placetype":[
        "aat:300008347"
    ]
},
  "bbox": [],
  "geometry": {"coordinates":[-111.8167,40.5833],"type":"Point"}
}