{
  "id": 7208153,
  "type": "Feature",
  "properties": {
    "tgn:hierarchy":[
        "tgn:7208153",
        "tgn:1000003",
        "tgn:7003682",
        "tgn:7000084",
        "tgn:7029392"
    ],
    "tgn:id":7208153,
    "tgn:name":"Colgenstein-Heidesheim",
    "tgn:placetype":[
        "aat:300008347"
    ]
},
  "bbox": [],
  "geometry": {"coordinates":[8.202222,49.583333],"type":"Point"}
}