{
  "id": 2680622,
  "type": "Feature",
  "properties": {
    "tgn:hierarchy":[
        "tgn:2680622",
        "tgn:1000001",
        "tgn:1002738",
        "tgn:7012149",
        "tgn:7007565",
        "tgn:7029392"
    ],
    "tgn:id":2680622,
    "tgn:name":"South Harbor",
    "tgn:placetype":[
        "aat:300132316"
    ]
},
  "bbox": [],
  "geometry": {"coordinates":[-74.1833,39.7833],"type":"Point"}
}