{
  "id": 2630335,
  "type": "Feature",
  "properties": {
    "tgn:hierarchy":[
        "tgn:2630335",
        "tgn:1000001",
        "tgn:7012149",
        "tgn:2001515",
        "tgn:7007709",
        "tgn:7029392"
    ],
    "tgn:id":2630335,
    "tgn:name":"Rough Knob",
    "tgn:placetype":[
        "aat:300008798"
    ]
},
  "bbox": [],
  "geometry": {"coordinates":[-83.2667,35.1667],"type":"Point"}
}