{
  "id": 2655292,
  "type": "Feature",
  "properties": {
    "tgn:hierarchy":[
        "tgn:2655292",
        "tgn:1000001",
        "tgn:7012149",
        "tgn:1002800",
        "tgn:7007710",
        "tgn:7029392"
    ],
    "tgn:id":2655292,
    "tgn:name":"Shanty Hollow",
    "tgn:placetype":[
        "aat:300008761"
    ]
},
  "bbox": [],
  "geometry": {"coordinates":[-77.7833,41.9667],"type":"Point"}
}