{
  "id": 7361022,
  "type": "Feature",
  "properties": {
    "tgn:hierarchy":[
        "tgn:7361022",
        "tgn:1001835",
        "tgn:1000001",
        "tgn:7005560",
        "tgn:7029392"
    ],
    "tgn:id":7361022,
    "tgn:name":"El Compadre",
    "tgn:placetype":[
        "aat:300008347"
    ]
},
  "bbox": [],
  "geometry": {"coordinates":[-116.216667,32.333333],"type":"Point"}
}