{
  "id": 7574354,
  "type": "Feature",
  "properties": {
    "tgn:hierarchy":[
        "tgn:7574354",
        "tgn:1000004",
        "tgn:7000198",
        "tgn:7016788",
        "tgn:7029392"
    ],
    "tgn:id":7574354,
    "tgn:name:en":"Jaipura",
    "tgn:placetype":[
        "aat:300008347"
    ]
},
  "bbox": [],
  "geometry": {"coordinates":[74.142993,23.912091],"type":"Point"}
}