{
  "id": 7462482,
  "type": "Feature",
  "properties": {
    "tgn:hierarchy":[
        "tgn:7462482",
        "tgn:7002445",
        "tgn:1000003",
        "tgn:7008154",
        "tgn:7008591",
        "tgn:7029392"
    ],
    "tgn:id":7462482,
    "tgn:name:en":"Higher Thrushgill",
    "tgn:placetype":[
        "aat:300008347"
    ]
},
  "bbox": [],
  "geometry": {"coordinates":[-2.533333,54.05],"type":"Point"}
}