{
  "id": 7387986,
  "type": "Feature",
  "properties": {
    "tgn:hierarchy":[
        "tgn:7387986",
        "tgn:7005586",
        "tgn:1000001",
        "tgn:7005560",
        "tgn:7029392"
    ],
    "tgn:id":7387986,
    "tgn:name":"Paso del Lobo",
    "tgn:placetype":[
        "aat:300008699"
    ]
},
  "bbox": [],
  "geometry": {"coordinates":[-103.133333,20.616667],"type":"Point"}
}