{
  "id": 7589558,
  "type": "Feature",
  "properties": {
    "tgn:hierarchy":[
        "tgn:7589558",
        "tgn:1000004",
        "tgn:7000198",
        "tgn:7000799",
        "tgn:7029392"
    ],
    "tgn:id":7589558,
    "tgn:name:en":"Hamboting La",
    "tgn:placetype":[
        "aat:300259572"
    ]
},
  "bbox": [],
  "geometry": {"coordinates":[76.275381,34.584613],"type":"Point"}
}