<<<<<<< HEAD
{
  "id": 2401510,
  "type": "Feature",
  "properties": {
    "tgn:hierarchy":[
        "tgn:2401510",
        "tgn:2000090",
        "tgn:1000001",
        "tgn:7006451",
        "tgn:7012149",
        "tgn:7029392"
    ],
    "tgn:id":2401510,
    "tgn:name":"Horseshoe Cienega Lake",
    "tgn:placetype":[
        "aat:300006191"
    ]
},
  "bbox": [],
  "geometry": {"coordinates":[-109.6833,34.0333],"type":"Point"}
}
=======
{"geometry":{"type":"Point","coordinates":[-109.683300,34.033300]},"type":"Feature","properties":{"hierarchy":["tgn:2401510","tgn:2000090","tgn:1000001","tgn:7006451","tgn:7012149","tgn:7029392"],"placetype":["aat:300006191"],"id":2401510,"name:xx":"Horseshoe Cienega Lake"}}
>>>>>>> 03f74aca74312dbeaf24d7e61306dd6a786dc3d0
