{
  "id": 1016671,
  "type": "Feature",
  "properties": {
    "tgn:hierarchy":[
        "tgn:1016671",
        "tgn:1000602",
        "tgn:1000001",
        "tgn:7005493",
        "tgn:7029392"
    ],
    "tgn:id":1016671,
    "tgn:name":"La Gomera",
    "tgn:placetype":[
        "aat:300008347"
    ]
},
  "bbox": [],
  "geometry": {"coordinates":[-91.05,14.0833],"type":"Point"}
}