{
  "id": 7590324,
  "type": "Feature",
  "properties": {
    "tgn:hierarchy":[
        "tgn:7590324",
        "tgn:1000004",
        "tgn:7000198",
        "tgn:7000799",
        "tgn:7029392"
    ],
    "tgn:id":7590324,
    "tgn:name:en":"Kalas Forest",
    "tgn:placetype":[
        "aat:300008863"
    ]
},
  "bbox": [],
  "geometry": {"coordinates":[74.330556,33.825],"type":"Point"}
}