{
  "id": 7104031,
  "type": "Feature",
  "properties": {
    "tgn:hierarchy":[
        "tgn:7104031",
        "tgn:7003692",
        "tgn:1000003",
        "tgn:7000084",
        "tgn:7029392"
    ],
    "tgn:id":7104031,
    "tgn:name":"Schachen",
    "tgn:placetype":[
        "aat:300008863"
    ]
},
  "bbox": [],
  "geometry": {"coordinates":[9.716667,48.133333],"type":"Point"}
}