<<<<<<< HEAD
{
  "id": 2331609,
  "type": "Feature",
  "properties": {
    "tgn:hierarchy":[
        "tgn:2331609",
        "tgn:1000001",
        "tgn:7012149",
        "tgn:2001457",
        "tgn:7007566",
        "tgn:7029392"
    ],
    "tgn:id":2331609,
    "tgn:name":"Flechado Canyon",
    "tgn:placetype":[
        "aat:300008761"
    ]
},
  "bbox": [],
  "geometry": {"coordinates":[-105.5333,36.1667],"type":"Point"}
}
=======
{"geometry":{"type":"Point","coordinates":[-105.533300,36.166700]},"type":"Feature","properties":{"hierarchy":["tgn:2331609","tgn:1000001","tgn:7012149","tgn:2001457","tgn:7007566","tgn:7029392"],"placetype":["aat:300008761"],"id":2331609,"name:xx":"Flechado Canyon"}}
>>>>>>> 03f74aca74312dbeaf24d7e61306dd6a786dc3d0
