{
  "id": 2570954,
  "type": "Feature",
  "properties": {
    "tgn:hierarchy":[
        "tgn:2570954",
        "tgn:1000001",
        "tgn:2001185",
        "tgn:7012149",
        "tgn:7007523",
        "tgn:7029392"
    ],
    "tgn:id":2570954,
    "tgn:name":"Patterson Hollow",
    "tgn:placetype":[
        "aat:300008761"
    ]
},
  "bbox": [],
  "geometry": {"coordinates":[-92.9333,36.85],"type":"Point"}
}