{
  "id": 7003534,
  "type": "Feature",
  "properties": {
    "tgn:hierarchy":[
        "tgn:7003534",
        "tgn:1000003",
        "tgn:7003514",
        "tgn:7029392"
    ],
    "tgn:id":7003534,
    "tgn:name":"Luxembourg",
    "tgn:placetype":[
        "aat:300387064",
        "aat:300387081"
    ]
},
  "bbox": [],
  "geometry": {"coordinates":[6.09,49.627],"type":"Point"}
}