{
  "id": 2307960,
  "type": "Feature",
  "properties": {
    "tgn:hierarchy":[
        "tgn:2307960",
        "tgn:1000001",
        "tgn:7012149",
        "tgn:1002550",
        "tgn:7007157",
        "tgn:7029392"
    ],
    "tgn:id":2307960,
    "tgn:name":"East Hansen Fisk Ditch",
    "tgn:placetype":[
        "aat:300006075"
    ]
},
  "bbox": [],
  "geometry": {"coordinates":[-119.55,36.0167],"type":"Point"}
}