{
  "id": 7237242,
  "type": "Feature",
  "properties": {
    "tgn:hierarchy":[
        "tgn:7237242",
        "tgn:7002706",
        "tgn:7002705",
        "tgn:1000003",
        "tgn:1000074",
        "tgn:7029392"
    ],
    "tgn:id":7237242,
    "tgn:name":"Vourgar\u00e9li",
    "tgn:placetype":[
        "aat:300008347"
    ]
},
  "bbox": [],
  "geometry": {"coordinates":[21.183333,39.371944],"type":"Point"}
}