{
  "id": 7436097,
  "type": "Feature",
  "properties": {
    "tgn:hierarchy":[
        "tgn:7436097",
        "tgn:1001835",
        "tgn:1000001",
        "tgn:7005560",
        "tgn:7029392"
    ],
    "tgn:id":7436097,
    "tgn:name":"Santo Tom\u00e1s, R\u00edo",
    "tgn:placetype":[
        "aat:300008699"
    ]
},
  "bbox": [],
  "geometry": {"coordinates":[-116.666667,31.533333],"type":"Point"}
}