{
  "id": 2598100,
  "type": "Feature",
  "properties": {
    "tgn:hierarchy":[
        "tgn:2598100",
        "tgn:1000001",
        "tgn:7012149",
        "tgn:2000982",
        "tgn:7007520",
        "tgn:7029392"
    ],
    "tgn:id":2598100,
    "tgn:name":"Presque Isle State Forest",
    "tgn:placetype":[
        "aat:300008863"
    ]
},
  "bbox": [],
  "geometry": {"coordinates":[-84.3167,44.9333],"type":"Point"}
}