{
  "id": 7217743,
  "type": "Feature",
  "properties": {
    "tgn:hierarchy":[
        "tgn:7217743",
        "tgn:7002751",
        "tgn:7001399",
        "tgn:1000003",
        "tgn:1000074",
        "tgn:7029392"
    ],
    "tgn:id":7217743,
    "tgn:name":"Yerakio\u00fa",
    "tgn:placetype":[
        "aat:300008347"
    ]
},
  "bbox": [],
  "geometry": {"coordinates":[23.233333,38.983333],"type":"Point"}
}