{
  "id": 7500357,
  "type": "Feature",
  "properties": {
    "tgn:hierarchy":[
        "tgn:7500357",
        "tgn:1000004",
        "tgn:7001009",
        "tgn:1000141",
        "tgn:7029392"
    ],
    "tgn:id":7500357,
    "tgn:name":"Maozilun",
    "tgn:placetype":[
        "aat:300008347"
    ]
},
  "bbox": [],
  "geometry": {"coordinates":[120.590569,24.153919],"type":"Point"}
}