{
  "id": 7387231,
  "type": "Feature",
  "properties": {
    "tgn:hierarchy":[
        "tgn:7387231",
        "tgn:7005583",
        "tgn:1000001",
        "tgn:7005560",
        "tgn:7029392"
    ],
    "tgn:id":7387231,
    "tgn:name":"Pueblo Viejo",
    "tgn:placetype":[
        "aat:300008347"
    ]
},
  "bbox": [],
  "geometry": {"coordinates":[-106.608611,24.570833],"type":"Point"}
}