{
  "id": 7545245,
  "type": "Feature",
  "properties": {
    "tgn:hierarchy":[
        "tgn:7545245",
        "tgn:1000004",
        "tgn:7000198",
        "tgn:1001894",
        "tgn:7029392"
    ],
    "tgn:id":7545245,
    "tgn:name:en":"Bher\u0101gh\u0101t",
    "tgn:placetype":[
        "aat:300008347"
    ]
},
  "bbox": [],
  "geometry": {"coordinates":[79.800989,23.131468],"type":"Point"}
}