<<<<<<< HEAD
{
  "id": 7488077,
  "type": "Feature",
  "properties": {
    "tgn:hierarchy":[
        "tgn:7488077",
        "tgn:1000004",
        "tgn:7001009",
        "tgn:1000141",
        "tgn:7029392"
    ],
    "tgn:id":7488077,
    "tgn:name":"Huangxi Cun",
    "tgn:placetype":[
        "aat:300387173"
    ]
},
  "bbox": [],
  "geometry": {"coordinates":[120.53867,24.140952],"type":"Point"}
}
=======
{"geometry":{"type":"Point","coordinates":[120.538670,24.140952]},"type":"Feature","properties":{"hierarchy":["tgn:7488077","tgn:1000004","tgn:7001009","tgn:1000141","tgn:7029392"],"placetype":["aat:300387173"],"id":7488077,"name:xx":"Huangxi Cun"}}
>>>>>>> 03f74aca74312dbeaf24d7e61306dd6a786dc3d0
