{
  "id": 2539401,
  "type": "Feature",
  "properties": {
    "tgn:hierarchy":[
        "tgn:2539401",
        "tgn:1000001",
        "tgn:1002273",
        "tgn:7012149",
        "tgn:7007252",
        "tgn:7029392"
    ],
    "tgn:id":2539401,
    "tgn:name":"New Liberty",
    "tgn:placetype":[
        "aat:300008347"
    ]
},
  "bbox": [],
  "geometry": {"coordinates":[-85.8667,38.5667],"type":"Point"}
}