<<<<<<< HEAD
{
  "id": 2255811,
  "type": "Feature",
  "properties": {
    "tgn:hierarchy":[
        "tgn:2255811",
        "tgn:2000453",
        "tgn:1000001",
        "tgn:7012149",
        "tgn:7007250",
        "tgn:7029392"
    ],
    "tgn:id":2255811,
    "tgn:name":"Copper Cliff Mine",
    "tgn:placetype":[
        "aat:300000390"
    ]
},
  "bbox": [],
  "geometry": {"coordinates":[-116.6667,45.1],"type":"Point"}
}
=======
{"geometry":{"type":"Point","coordinates":[-116.666700,45.100000]},"type":"Feature","properties":{"hierarchy":["tgn:2255811","tgn:2000453","tgn:1000001","tgn:7012149","tgn:7007250","tgn:7029392"],"placetype":["aat:300000390"],"id":2255811,"name:xx":"Copper Cliff Mine"}}
>>>>>>> 03f74aca74312dbeaf24d7e61306dd6a786dc3d0
