{
  "id": 2223364,
  "type": "Feature",
  "properties": {
    "tgn:hierarchy":[
        "tgn:2223364",
        "tgn:1000001",
        "tgn:7012149",
        "tgn:2000230",
        "tgn:7007158",
        "tgn:7029392"
    ],
    "tgn:id":2223364,
    "tgn:name":"Carson Hole",
    "tgn:placetype":[
        "aat:300008761"
    ]
},
  "bbox": [],
  "geometry": {"coordinates":[-108.6167,38.7167],"type":"Point"}
}