{
  "id": 2403504,
  "type": "Feature",
  "properties": {
    "tgn:hierarchy":[
        "tgn:2403504",
        "tgn:1000001",
        "tgn:2002242",
        "tgn:7012149",
        "tgn:7007920",
        "tgn:7029392"
    ],
    "tgn:id":2403504,
    "tgn:name":"Howard",
    "tgn:placetype":[
        "aat:300008347"
    ]
},
  "bbox": [],
  "geometry": {"coordinates":[-119.8167,47.8833],"type":"Point"}
}