<<<<<<< HEAD
{
  "id": 2708872,
  "type": "Feature",
  "properties": {
    "tgn:hierarchy":[
        "tgn:2708872",
        "tgn:1000001",
        "tgn:7012149",
        "tgn:2000833",
        "tgn:7007255",
        "tgn:7029392"
    ],
    "tgn:id":2708872,
    "tgn:name":"Sympson Lake",
    "tgn:placetype":[
        "aat:300006191"
    ]
},
  "bbox": [],
  "geometry": {"coordinates":[-85.5,37.8],"type":"Point"}
}
=======
{"geometry":{"type":"Point","coordinates":[-85.500000,37.800000]},"type":"Feature","properties":{"hierarchy":["tgn:2708872","tgn:1000001","tgn:7012149","tgn:2000833","tgn:7007255","tgn:7029392"],"placetype":["aat:300006191"],"id":2708872,"name:xx":"Sympson Lake"}}
>>>>>>> 03f74aca74312dbeaf24d7e61306dd6a786dc3d0
