{
  "id": 7565797,
  "type": "Feature",
  "properties": {
    "tgn:hierarchy":[
        "tgn:7565797",
        "tgn:1000004",
        "tgn:7000198",
        "tgn:1001894",
        "tgn:7029392"
    ],
    "tgn:id":7565797,
    "tgn:name:en":"Sukkanpura",
    "tgn:placetype":[
        "aat:300008347"
    ]
},
  "bbox": [],
  "geometry": {"coordinates":[79.23354,24.673475],"type":"Point"}
}