{
  "id": 2195406,
  "type": "Feature",
  "properties": {
    "tgn:hierarchy":[
        "tgn:2195406",
        "tgn:1000001",
        "tgn:7006451",
        "tgn:2000092",
        "tgn:7012149",
        "tgn:7029392"
    ],
    "tgn:id":2195406,
    "tgn:name":"Bristow Tank",
    "tgn:placetype":[
        "aat:300006191"
    ]
},
  "bbox": [],
  "geometry": {"coordinates":[-111.3667,34.6833],"type":"Point"}
}