{
  "id": 7171135,
  "type": "Feature",
  "properties": {
    "tgn:hierarchy":[
        "tgn:7171135",
        "tgn:1000003",
        "tgn:7003678",
        "tgn:7000084",
        "tgn:7029392"
    ],
    "tgn:id":7171135,
    "tgn:name":"Himbeer-Kopf",
    "tgn:placetype":[
        "aat:300008777"
    ]
},
  "bbox": [],
  "geometry": {"coordinates":[8.95,51.133333],"type":"Point"}
}