{
  "id": 2077474,
  "type": "Feature",
  "properties": {
    "tgn:hierarchy":[
        "tgn:2077474",
        "tgn:2001566",
        "tgn:1000001",
        "tgn:7012149",
        "tgn:7007705",
        "tgn:7029392"
    ],
    "tgn:id":2077474,
    "tgn:name":"Calvin",
    "tgn:placetype":[
        "aat:300008347"
    ]
},
  "bbox": [],
  "geometry": {"coordinates":[-98.9333,48.85],"type":"Point"}
}