{
  "id": 2689207,
  "type": "Feature",
  "properties": {
    "tgn:hierarchy":[
        "tgn:2689207",
        "tgn:1000001",
        "tgn:7012149",
        "tgn:2001277",
        "tgn:7007524",
        "tgn:7029392"
    ],
    "tgn:id":2689207,
    "tgn:name":"Squaw Buttes",
    "tgn:placetype":[
        "aat:300008697"
    ]
},
  "bbox": [],
  "geometry": {"coordinates":[-112.4833,48.5333],"type":"Point"}
}