{
  "id": 7207998,
  "type": "Feature",
  "properties": {
    "tgn:hierarchy":[
        "tgn:7207998",
        "tgn:1000003",
        "tgn:7003688",
        "tgn:7000084",
        "tgn:7029392"
    ],
    "tgn:id":7207998,
    "tgn:name":"B\u00fcnsdorf",
    "tgn:placetype":[
        "aat:300008347"
    ]
},
  "bbox": [],
  "geometry": {"coordinates":[9.75,54.366667],"type":"Point"}
}