{
  "id": 2294851,
  "type": "Feature",
  "properties": {
    "tgn:hierarchy":[
        "tgn:2294851",
        "tgn:1000001",
        "tgn:7012149",
        "tgn:2000615",
        "tgn:7007253",
        "tgn:7029392"
    ],
    "tgn:id":2294851,
    "tgn:name":"Drainage Ditch Number 84",
    "tgn:placetype":[
        "aat:300006075"
    ]
},
  "bbox": [],
  "geometry": {"coordinates":[-94.0833,43.1167],"type":"Point"}
}