{
  "id": 7571688,
  "type": "Feature",
  "properties": {
    "tgn:hierarchy":[
        "tgn:7571688",
        "tgn:1000004",
        "tgn:7000198",
        "tgn:7016788",
        "tgn:7029392"
    ],
    "tgn:id":7571688,
    "tgn:name:en":"Jaswantpura",
    "tgn:placetype":[
        "aat:300008347"
    ]
},
  "bbox": [],
  "geometry": {"coordinates":[72.460877,24.801776],"type":"Point"}
}