{
  "id": 7213930,
  "type": "Feature",
  "properties": {
    "tgn:hierarchy":[
        "tgn:7213930",
        "tgn:7003692",
        "tgn:1000003",
        "tgn:7000084",
        "tgn:7029392"
    ],
    "tgn:id":7213930,
    "tgn:name":"Bluium",
    "tgn:placetype":[
        "aat:300008863"
    ]
},
  "bbox": [],
  "geometry": {"coordinates":[9.75,48.216667],"type":"Point"}
}