{
  "id": 2601295,
  "type": "Feature",
  "properties": {
    "tgn:hierarchy":[
        "tgn:2601295",
        "tgn:1000001",
        "tgn:7012149",
        "tgn:7007157",
        "tgn:1002957",
        "tgn:7029392"
    ],
    "tgn:id":2601295,
    "tgn:name":"Puppy Dome",
    "tgn:placetype":[
        "aat:300008798"
    ]
},
  "bbox": [],
  "geometry": {"coordinates":[-119.3333,37.8667],"type":"Point"}
}