{
  "id": 2193772,
  "type": "Feature",
  "properties": {
    "tgn:hierarchy":[
        "tgn:2193772",
        "tgn:7002659",
        "tgn:1000001",
        "tgn:7012149",
        "tgn:2000035",
        "tgn:7029392"
    ],
    "tgn:id":2193772,
    "tgn:name":"Brewsters Pit",
    "tgn:placetype":[
        "aat:300008746"
    ]
},
  "bbox": [],
  "geometry": {"coordinates":[-85.9667,34.75],"type":"Point"}
}