<<<<<<< HEAD
{
  "id": 2151897,
  "type": "Feature",
  "properties": {
    "tgn:hierarchy":[
        "tgn:2151897",
        "tgn:2002238",
        "tgn:1000001",
        "tgn:7012149",
        "tgn:7007920",
        "tgn:7029392"
    ],
    "tgn:id":2151897,
    "tgn:name":"Batum",
    "tgn:placetype":[
        "aat:300008347"
    ]
},
  "bbox": [],
  "geometry": {"coordinates":[-118.8,47.2333],"type":"Point"}
}
=======
{"geometry":{"type":"Point","coordinates":[-118.800000,47.233300]},"type":"Feature","properties":{"hierarchy":["tgn:2151897","tgn:2002238","tgn:1000001","tgn:7012149","tgn:7007920","tgn:7029392"],"placetype":["aat:300008347"],"id":2151897,"name:xx":"Batum"}}
>>>>>>> 03f74aca74312dbeaf24d7e61306dd6a786dc3d0
