{
  "id": 2586422,
  "type": "Feature",
  "properties": {
    "tgn:hierarchy":[
        "tgn:2586422",
        "tgn:1000001",
        "tgn:7012149",
        "tgn:2001534",
        "tgn:7007709",
        "tgn:7029392"
    ],
    "tgn:id":2586422,
    "tgn:name":"Pitman Mill Branch",
    "tgn:placetype":[
        "aat:300008699"
    ]
},
  "bbox": [],
  "geometry": {"coordinates":[-79.1333,34.4833],"type":"Point"}
}