{
  "id": 2265694,
  "type": "Feature",
  "properties": {
    "tgn:hierarchy":[
        "tgn:2265694",
        "tgn:1000001",
        "tgn:7006451",
        "tgn:7012149",
        "tgn:2000098",
        "tgn:7029392"
    ],
    "tgn:id":2265694,
    "tgn:name":"Crappie Cove",
    "tgn:placetype":[
        "aat:300132316"
    ]
},
  "bbox": [],
  "geometry": {"coordinates":[-114.0833,36.1167],"type":"Point"}
}