{
  "id": 2526016,
  "type": "Feature",
  "properties": {
    "tgn:hierarchy":[
        "tgn:2526016",
        "tgn:1000001",
        "tgn:7012149",
        "tgn:7007157",
        "tgn:1002710",
        "tgn:7029392"
    ],
    "tgn:id":2526016,
    "tgn:name":"Mosquito Creek",
    "tgn:placetype":[
        "aat:300008706"
    ]
},
  "bbox": [],
  "geometry": {"coordinates":[-120.9667,39.2667],"type":"Point"}
}