{
  "id": 7586314,
  "type": "Feature",
  "properties": {
    "tgn:hierarchy":[
        "tgn:7586314",
        "tgn:1000004",
        "tgn:7000198",
        "tgn:7000799",
        "tgn:7029392"
    ],
    "tgn:id":7586314,
    "tgn:name:en":"Shiu",
    "tgn:placetype":[
        "aat:300008347"
    ]
},
  "bbox": [],
  "geometry": {"coordinates":[74.452841,34.368588],"type":"Point"}
}