<<<<<<< HEAD
{
  "id": 7174436,
  "type": "Feature",
  "properties": {
    "tgn:hierarchy":[
        "tgn:7174436",
        "tgn:1000003",
        "tgn:7003677",
        "tgn:7000084",
        "tgn:7029392"
    ],
    "tgn:id":7174436,
    "tgn:name":"Grolis-Bach",
    "tgn:placetype":[
        "aat:300008699"
    ]
},
  "bbox": [],
  "geometry": {"coordinates":[6.2,50.65],"type":"Point"}
}
=======
{"geometry":{"type":"Point","coordinates":[6.200000,50.650000]},"type":"Feature","properties":{"hierarchy":["tgn:7174436","tgn:1000003","tgn:7003677","tgn:7000084","tgn:7029392"],"placetype":["aat:300008699"],"id":7174436,"name:xx":"Grolis-Bach"}}
>>>>>>> 03f74aca74312dbeaf24d7e61306dd6a786dc3d0
