{
  "id": 2073726,
  "type": "Feature",
  "properties": {
    "tgn:hierarchy":[
        "tgn:2073726",
        "tgn:1000001",
        "tgn:2001471",
        "tgn:7012149",
        "tgn:7007709",
        "tgn:7029392"
    ],
    "tgn:id":2073726,
    "tgn:name":"Bladenboro",
    "tgn:placetype":[
        "aat:300008347"
    ]
},
  "bbox": [],
  "geometry": {"coordinates":[-78.7833,34.5333],"type":"Point"}
}