{
  "id": 7514993,
  "type": "Feature",
  "properties": {
    "tgn:hierarchy":[
        "tgn:7514993",
        "tgn:1008380",
        "tgn:1000226",
        "tgn:7000512",
        "tgn:1000006",
        "tgn:7029392"
    ],
    "tgn:id":7514993,
    "tgn:name:en":"Carswells",
    "tgn:placetype":[
        "aat:300008347"
    ]
},
  "bbox": [],
  "geometry": {"coordinates":[175.916667,-40.933333],"type":"Point"}
}