<<<<<<< HEAD
{
  "id": 7179562,
  "type": "Feature",
  "properties": {
    "tgn:hierarchy":[
        "tgn:7179562",
        "tgn:1000003",
        "tgn:7003676",
        "tgn:7000084",
        "tgn:7029392"
    ],
    "tgn:id":7179562,
    "tgn:name":"H\u00e4melhausen",
    "tgn:placetype":[
        "aat:300008347"
    ]
},
  "bbox": [],
  "geometry": {"coordinates":[9.283333,52.783333],"type":"Point"}
}
=======
{"geometry":{"type":"Point","coordinates":[9.283333,52.783333]},"type":"Feature","properties":{"hierarchy":["tgn:7179562","tgn:1000003","tgn:7003676","tgn:7000084","tgn:7029392"],"placetype":["aat:300008347"],"id":7179562,"name:xx":"H\u00e4melhausen"}}
>>>>>>> 03f74aca74312dbeaf24d7e61306dd6a786dc3d0
