<<<<<<< HEAD
{
  "id": 7177947,
  "type": "Feature",
  "properties": {
    "tgn:hierarchy":[
        "tgn:7177947",
        "tgn:1000003",
        "tgn:7003678",
        "tgn:7000084",
        "tgn:7029392"
    ],
    "tgn:id":7177947,
    "tgn:name":"Gundwald",
    "tgn:placetype":[
        "aat:300008863"
    ]
},
  "bbox": [],
  "geometry": {"coordinates":[8.566667,50.016667],"type":"Point"}
}
=======
{"geometry":{"type":"Point","coordinates":[8.566667,50.016667]},"type":"Feature","properties":{"hierarchy":["tgn:7177947","tgn:1000003","tgn:7003678","tgn:7000084","tgn:7029392"],"placetype":["aat:300008863"],"id":7177947,"name:xx":"Gundwald"}}
>>>>>>> 03f74aca74312dbeaf24d7e61306dd6a786dc3d0
