{
  "id": 7177947,
  "type": "Feature",
  "properties": {
    "tgn:hierarchy":[
        "tgn:7177947",
        "tgn:1000003",
        "tgn:7003678",
        "tgn:7000084",
        "tgn:7029392"
    ],
    "tgn:id":7177947,
    "tgn:name":"Gundwald",
    "tgn:placetype":[
        "aat:300008863"
    ]
},
  "bbox": [],
  "geometry": {"coordinates":[8.566667,50.016667],"type":"Point"}
}