<<<<<<< HEAD
{
  "id": 7247880,
  "type": "Feature",
  "properties": {
    "tgn:hierarchy":[
        "tgn:7247880",
        "tgn:7003458",
        "tgn:1000003",
        "tgn:1000063",
        "tgn:7018236",
        "tgn:7029392"
    ],
    "tgn:id":7247880,
    "tgn:name":"De Meiboom",
    "tgn:placetype":[
        "aat:300008347"
    ]
},
  "bbox": [],
  "geometry": {"coordinates":[3.156088,51.292535],"type":"Point"}
}
=======
{"geometry":{"type":"Point","coordinates":[3.156088,51.292535]},"type":"Feature","properties":{"hierarchy":["tgn:7247880","tgn:7003458","tgn:1000003","tgn:1000063","tgn:7018236","tgn:7029392"],"placetype":["aat:300008347"],"id":7247880,"name:xx":"De Meiboom"}}
>>>>>>> 03f74aca74312dbeaf24d7e61306dd6a786dc3d0
