{
  "id": 1058641,
  "type": "Feature",
  "properties": {
    "tgn:hierarchy":[
        "tgn:1058641",
        "tgn:1000004",
        "tgn:1003314",
        "tgn:7018214",
        "tgn:7002435",
        "tgn:7029392"
    ],
    "tgn:id":1058641,
    "tgn:name":"Predivinsk",
    "tgn:placetype":[
        "aat:300008347"
    ]
},
  "bbox": [],
  "geometry": {"coordinates":[93.4833,57.0667],"type":"Point"}
}