{
  "id": 2033822,
  "type": "Feature",
  "properties": {
    "tgn:hierarchy":[
        "tgn:2033822",
        "tgn:1000001",
        "tgn:7012149",
        "tgn:1002827",
        "tgn:7007252",
        "tgn:7029392"
    ],
    "tgn:id":2033822,
    "tgn:name":"Sunman",
    "tgn:placetype":[
        "aat:300008347"
    ]
},
  "bbox": [],
  "geometry": {"coordinates":[-85.0833,39.2333],"type":"Point"}
}