{
  "id": 7592930,
  "type": "Feature",
  "properties": {
    "tgn:hierarchy":[
        "tgn:7592930",
        "tgn:1000004",
        "tgn:7000198",
        "tgn:7000799",
        "tgn:7029392"
    ],
    "tgn:id":7592930,
    "tgn:name:en":"Siddraiy\u0101nw\u0101li Khad",
    "tgn:placetype":[
        "aat:300266554",
        "aat:300008699"
    ]
},
  "bbox": [],
  "geometry": {"coordinates":[74.897222,32.754167],"type":"Point"}
}