{
  "id": 1078147,
  "type": "Feature",
  "properties": {
    "tgn:hierarchy":[
        "tgn:1078147",
        "tgn:1000004",
        "tgn:7003970",
        "tgn:1007722",
        "tgn:1000116",
        "tgn:7029392"
    ],
    "tgn:id":1078147,
    "tgn:name":"Mombum",
    "tgn:placetype":[
        "aat:300008347"
    ]
},
  "bbox": [],
  "geometry": {"coordinates":[138.85,-8.3833],"type":"Point"}
}