{
  "id": 1089957,
  "type": "Feature",
  "properties": {
    "tgn:hierarchy":[
        "tgn:1089957",
        "tgn:7001242",
        "tgn:1001136",
        "tgn:7000489",
        "tgn:7029392"
    ],
    "tgn:id":1089957,
    "tgn:name":"Suca",
    "tgn:placetype":[
        "aat:300008347"
    ]
},
  "bbox": [],
  "geometry": {"coordinates":[39.2333,6.5167],"type":"Point"}
}