{
  "id": 7424629,
  "type": "Feature",
  "properties": {
    "tgn:hierarchy":[
        "tgn:7424629",
        "tgn:1000001",
        "tgn:7005601",
        "tgn:7005560",
        "tgn:7029392"
    ],
    "tgn:id":7424629,
    "tgn:name":"Santa Mar\u00eda La Paz",
    "tgn:placetype":[
        "aat:300008347"
    ]
},
  "bbox": [],
  "geometry": {"coordinates":[-102.15,22.55],"type":"Point"}
}