{
  "id": 1122154,
  "type": "Feature",
  "properties": {
    "tgn:hierarchy":[
        "tgn:1122154",
        "tgn:1000003",
        "tgn:1000070",
        "tgn:7029392"
    ],
    "tgn:id":1122154,
    "tgn:name":"Boulogne",
    "tgn:placetype":[
        "aat:300008707"
    ]
},
  "bbox": [],
  "geometry": {"coordinates":[-1.6833,47.0833],"type":"Point"}
}