{
  "id": 7429346,
  "type": "Feature",
  "properties": {
    "tgn:hierarchy":[
        "tgn:7429346",
        "tgn:1001853",
        "tgn:1000001",
        "tgn:7005560",
        "tgn:7029392"
    ],
    "tgn:id":7429346,
    "tgn:name":"Estaci\u00f3 Guillermo",
    "tgn:placetype":[
        "aat:300007783"
    ]
},
  "bbox": [],
  "geometry": {"coordinates":[-101.05,25.05],"type":"Point"}
}