{
  "id": 2237455,
  "type": "Feature",
  "properties": {
    "tgn:hierarchy":[
        "tgn:2237455",
        "tgn:1000001",
        "tgn:7012149",
        "tgn:2001707",
        "tgn:7007708",
        "tgn:7029392"
    ],
    "tgn:id":2237455,
    "tgn:name":"China Ditch",
    "tgn:placetype":[
        "aat:300006075"
    ]
},
  "bbox": [],
  "geometry": {"coordinates":[-120.1667,45.6333],"type":"Point"}
}