{
  "id": 2709651,
  "type": "Feature",
  "properties": {
    "tgn:hierarchy":[
        "tgn:2709651",
        "tgn:7006450",
        "tgn:1000001",
        "tgn:7012149",
        "tgn:2124005",
        "tgn:7029392"
    ],
    "tgn:id":2709651,
    "tgn:name":"Taffy Creek",
    "tgn:placetype":[
        "aat:300008706"
    ]
},
  "bbox": [],
  "geometry": {"coordinates":[-156.9667,68.5333],"type":"Point"}
}