{
  "id": 7382516,
  "type": "Feature",
  "properties": {
    "tgn:hierarchy":[
        "tgn:7382516",
        "tgn:1000001",
        "tgn:7005593",
        "tgn:7005560",
        "tgn:7029392"
    ],
    "tgn:id":7382516,
    "tgn:name":"Noria",
    "tgn:placetype":[
        "aat:300007783"
    ]
},
  "bbox": [],
  "geometry": {"coordinates":[-100.15,20.583333],"type":"Point"}
}