{
  "id": 7575086,
  "type": "Feature",
  "properties": {
    "tgn:hierarchy":[
        "tgn:7575086",
        "tgn:1000004",
        "tgn:7000198",
        "tgn:1001894",
        "tgn:7029392"
    ],
    "tgn:id":7575086,
    "tgn:name:en":"Kelhari",
    "tgn:placetype":[
        "aat:300008347"
    ]
},
  "bbox": [],
  "geometry": {"coordinates":[82.04424,23.413433],"type":"Point"}
}