{
  "id": 1088854,
  "type": "Feature",
  "properties": {
    "tgn:hierarchy":[
        "tgn:1088854",
        "tgn:7001242",
        "tgn:7016654",
        "tgn:1000159",
        "tgn:7029392"
    ],
    "tgn:id":1088854,
    "tgn:name":"Bolondo",
    "tgn:placetype":[
        "aat:300008347"
    ]
},
  "bbox": [],
  "geometry": {"coordinates":[20.0167,0.45],"type":"Point"}
}