{
  "id": 7544968,
  "type": "Feature",
  "properties": {
    "tgn:hierarchy":[
        "tgn:7544968",
        "tgn:1000004",
        "tgn:7000198",
        "tgn:1001894",
        "tgn:7029392"
    ],
    "tgn:id":7544968,
    "tgn:name:en":"B\u0101bulda",
    "tgn:placetype":[
        "aat:300008347"
    ]
},
  "bbox": [],
  "geometry": {"coordinates":[75.687682,24.471478],"type":"Point"}
}