<<<<<<< HEAD
{
  "id": 7020064,
  "type": "Feature",
  "properties": {
    "tgn:hierarchy":[
        "tgn:7020064",
        "tgn:1000001",
        "tgn:2002242",
        "tgn:7012149",
        "tgn:7007920",
        "tgn:7029392"
    ],
    "tgn:id":7020064,
    "tgn:name":"Jollys Pond",
    "tgn:placetype":[
        "aat:300008680"
    ]
},
  "bbox": [],
  "geometry": {"coordinates":[-119.3667,47.6833],"type":"Point"}
}
=======
{"geometry":{"type":"Point","coordinates":[-119.366700,47.683300]},"type":"Feature","properties":{"hierarchy":["tgn:7020064","tgn:1000001","tgn:2002242","tgn:7012149","tgn:7007920","tgn:7029392"],"placetype":["aat:300008680"],"id":7020064,"name:xx":"Jollys Pond"}}
>>>>>>> 03f74aca74312dbeaf24d7e61306dd6a786dc3d0
