{
  "id": 7539904,
  "type": "Feature",
  "properties": {
    "tgn:hierarchy":[
        "tgn:7539904",
        "tgn:7001242",
        "tgn:7016833",
        "tgn:1001418",
        "tgn:7029392"
    ],
    "tgn:id":7539904,
    "tgn:name:en":"Samkat J\u0101b All\u0101h",
    "tgn:placetype":[
        "aat:300008777"
    ]
},
  "bbox": [],
  "geometry": {"coordinates":[29.089772,30.465281],"type":"Point"}
}