{
  "id": 1076005,
  "type": "Feature",
  "properties": {
    "tgn:hierarchy":[
        "tgn:1076005",
        "tgn:1000004",
        "tgn:7000198",
        "tgn:7016788",
        "tgn:7029392"
    ],
    "tgn:id":1076005,
    "tgn:name:en":"L\u016bni",
    "tgn:placetype":[
        "aat:300008347"
    ]
},
  "bbox": [],
  "geometry": {"coordinates":[73.005,-26.003],"type":"Point"}
}