{
  "id": 7135800,
  "type": "Feature",
  "properties": {
    "tgn:hierarchy":[
        "tgn:7135800",
        "tgn:1000003",
        "tgn:7003678",
        "tgn:7000084",
        "tgn:7029392"
    ],
    "tgn:id":7135800,
    "tgn:name":"Molken-Kopf",
    "tgn:placetype":[
        "aat:300008777"
    ]
},
  "bbox": [],
  "geometry": {"coordinates":[9.483333,51.516667],"type":"Point"}
}