{
  "id": 7417603,
  "type": "Feature",
  "properties": {
    "tgn:hierarchy":[
        "tgn:7417603",
        "tgn:1000001",
        "tgn:7005591",
        "tgn:7005560",
        "tgn:7029392"
    ],
    "tgn:id":7417603,
    "tgn:name:es":"Guivicia",
    "tgn:placetype":[
        "aat:300008347"
    ]
},
  "bbox": [],
  "geometry": {"coordinates":[-94.976389,16.959722],"type":"Point"}
}