{
  "id": 2303910,
  "type": "Feature",
  "properties": {
    "tgn:hierarchy":[
        "tgn:2303910",
        "tgn:1000001",
        "tgn:7012149",
        "tgn:2000927",
        "tgn:7007515",
        "tgn:7029392"
    ],
    "tgn:id":2303910,
    "tgn:name":"Eagle Pond",
    "tgn:placetype":[
        "aat:300008680"
    ]
},
  "bbox": [],
  "geometry": {"coordinates":[-68.1167,45.5667],"type":"Point"}
}