{
  "id": 1128130,
  "type": "Feature",
  "properties": {
    "tgn:hierarchy":[
        "tgn:1128130",
        "tgn:7001242",
        "tgn:7029392"
    ],
    "tgn:id":1128130,
    "tgn:name":"Orange",
    "tgn:placetype":[
        "aat:300008707"
    ]
},
  "bbox": [],
  "geometry": {"coordinates":[16.4667,-28.6833],"type":"Point"}
}