{
  "id": 2382471,
  "type": "Feature",
  "properties": {
    "tgn:hierarchy":[
        "tgn:2382471",
        "tgn:1000001",
        "tgn:7012149",
        "tgn:2000476",
        "tgn:7007250",
        "tgn:7029392"
    ],
    "tgn:id":2382471,
    "tgn:name":"Haystack Mine",
    "tgn:placetype":[
        "aat:300000390"
    ]
},
  "bbox": [],
  "geometry": {"coordinates":[-115.5833,45.7667],"type":"Point"}
}