{
  "id": 1013246,
  "type": "Feature",
  "properties": {
    "tgn:hierarchy":[
        "tgn:1013246",
        "tgn:7005694",
        "tgn:7005685",
        "tgn:1000001",
        "tgn:7029392"
    ],
    "tgn:id":1013246,
    "tgn:name":"Morrin",
    "tgn:placetype":[
        "aat:300008347"
    ]
},
  "bbox": [],
  "geometry": {"coordinates":[-112.7333,51.6667],"type":"Point"}
}