{
  "id": 7022582,
  "type": "Feature",
  "properties": {
    "tgn:hierarchy":[
        "tgn:7022582",
        "tgn:1000001",
        "tgn:7012149",
        "tgn:2001492",
        "tgn:7007709",
        "tgn:7029392"
    ],
    "tgn:id":7022582,
    "tgn:name":"Colony Park",
    "tgn:placetype":[
        "aat:300008347"
    ]
},
  "bbox": [],
  "geometry": {"coordinates":[-78.95,35.9833],"type":"Point"}
}