{
  "id": 7303265,
  "type": "Feature",
  "properties": {
    "tgn:hierarchy":[
        "tgn:7303265",
        "tgn:7002759",
        "tgn:7002845",
        "tgn:1000003",
        "tgn:1000095",
        "tgn:7029392"
    ],
    "tgn:id":7303265,
    "tgn:name":"Moyuela, R\u00edo",
    "tgn:placetype":[
        "aat:300008699"
    ]
},
  "bbox": [],
  "geometry": {"coordinates":[-0.833333,41.15],"type":"Point"}
}