<<<<<<< HEAD
{
  "id": 7174119,
  "type": "Feature",
  "properties": {
    "tgn:hierarchy":[
        "tgn:7174119",
        "tgn:1000003",
        "tgn:7000094",
        "tgn:7000084",
        "tgn:7029392"
    ],
    "tgn:id":7174119,
    "tgn:name":"Gro\u00dfer Moorholz",
    "tgn:placetype":[
        "aat:300008863"
    ]
},
  "bbox": [],
  "geometry": {"coordinates":[13.9,53.916667],"type":"Point"}
}
=======
{"geometry":{"type":"Point","coordinates":[13.900000,53.916667]},"type":"Feature","properties":{"hierarchy":["tgn:7174119","tgn:1000003","tgn:7000094","tgn:7000084","tgn:7029392"],"placetype":["aat:300008863"],"id":7174119,"name:xx":"Gro\u00dfer Moorholz"}}
>>>>>>> 03f74aca74312dbeaf24d7e61306dd6a786dc3d0
