{
  "id": 7379687,
  "type": "Feature",
  "properties": {
    "tgn:hierarchy":[
        "tgn:7379687",
        "tgn:1000001",
        "tgn:7005597",
        "tgn:7005560",
        "tgn:7029392"
    ],
    "tgn:id":7379687,
    "tgn:name":"Martine\u00f1o de Arriba",
    "tgn:placetype":[
        "aat:300008347"
    ]
},
  "bbox": [],
  "geometry": {"coordinates":[-99.433333,27.016667],"type":"Point"}
}