{
  "id": 7235453,
  "type": "Feature",
  "properties": {
    "tgn:hierarchy":[
        "tgn:7235453",
        "tgn:7002735",
        "tgn:7017076",
        "tgn:1000003",
        "tgn:1000074",
        "tgn:7029392"
    ],
    "tgn:id":7235453,
    "tgn:name":"Arkas\u00e1dhes",
    "tgn:placetype":[
        "aat:300008347"
    ]
},
  "bbox": [],
  "geometry": {"coordinates":[22.466667,36.966667],"type":"Point"}
}