{
  "id": 7399224,
  "type": "Feature",
  "properties": {
    "tgn:hierarchy":[
        "tgn:7399224",
        "tgn:1001835",
        "tgn:1000001",
        "tgn:7005560",
        "tgn:7029392"
    ],
    "tgn:id":7399224,
    "tgn:name":"El Oasis",
    "tgn:placetype":[
        "aat:300008347"
    ]
},
  "bbox": [],
  "geometry": {"coordinates":[-115.743056,32.578056],"type":"Point"}
}