{
  "id": 2638341,
  "type": "Feature",
  "properties": {
    "tgn:hierarchy":[
        "tgn:2638341",
        "tgn:1000001",
        "tgn:7012149",
        "tgn:1002459",
        "tgn:7007706",
        "tgn:7029392"
    ],
    "tgn:id":2638341,
    "tgn:name":"Sally Buffalo Creek",
    "tgn:placetype":[
        "aat:300008706"
    ]
},
  "bbox": [],
  "geometry": {"coordinates":[-81.0167,40.2667],"type":"Point"}
}