<<<<<<< HEAD
{
  "id": 2408697,
  "type": "Feature",
  "properties": {
    "tgn:hierarchy":[
        "tgn:2408697",
        "tgn:1000001",
        "tgn:7012149",
        "tgn:2001752",
        "tgn:7007712",
        "tgn:7029392"
    ],
    "tgn:id":2408697,
    "tgn:name":"Hyatts Millpond",
    "tgn:placetype":[
        "aat:300008680"
    ]
},
  "bbox": [],
  "geometry": {"coordinates":[-80.4833,34.35],"type":"Point"}
}
=======
{"geometry":{"type":"Point","coordinates":[-80.483300,34.350000]},"type":"Feature","properties":{"hierarchy":["tgn:2408697","tgn:1000001","tgn:7012149","tgn:2001752","tgn:7007712","tgn:7029392"],"placetype":["aat:300008680"],"id":2408697,"name:xx":"Hyatts Millpond"}}
>>>>>>> 03f74aca74312dbeaf24d7e61306dd6a786dc3d0
