{
  "id": 7294621,
  "type": "Feature",
  "properties": {
    "tgn:hierarchy":[
        "tgn:7294621",
        "tgn:7002810",
        "tgn:7001158",
        "tgn:1000003",
        "tgn:1000095",
        "tgn:7029392"
    ],
    "tgn:id":7294621,
    "tgn:name":"Valles de Palenzuela",
    "tgn:placetype":[
        "aat:300008347"
    ]
},
  "bbox": [],
  "geometry": {"coordinates":[-4.066667,42.116667],"type":"Point"}
}