<<<<<<< HEAD
{
  "id": 2152922,
  "type": "Feature",
  "properties": {
    "tgn:hierarchy":[
        "tgn:2152922",
        "tgn:1000001",
        "tgn:2001746",
        "tgn:7012149",
        "tgn:7007712",
        "tgn:7029392"
    ],
    "tgn:id":2152922,
    "tgn:name":"Beach Creek",
    "tgn:placetype":[
        "aat:300008706"
    ]
},
  "bbox": [],
  "geometry": {"coordinates":[-79.2,33.1667],"type":"Point"}
}
=======
{"geometry":{"type":"Point","coordinates":[-79.200000,33.166700]},"type":"Feature","properties":{"hierarchy":["tgn:2152922","tgn:1000001","tgn:2001746","tgn:7012149","tgn:7007712","tgn:7029392"],"placetype":["aat:300008706"],"id":2152922,"name:xx":"Beach Creek"}}
>>>>>>> 03f74aca74312dbeaf24d7e61306dd6a786dc3d0
