{
  "id": 2779891,
  "type": "Feature",
  "properties": {
    "tgn:hierarchy":[
        "tgn:2779891",
        "tgn:1000001",
        "tgn:7012149",
        "tgn:1002877",
        "tgn:7007706",
        "tgn:7029392"
    ],
    "tgn:id":2779891,
    "tgn:name":"Wolfden Lake",
    "tgn:placetype":[
        "aat:300006191"
    ]
},
  "bbox": [],
  "geometry": {"coordinates":[-83.2167,38.75],"type":"Point"}
}