{
  "id": 1101579,
  "type": "Feature",
  "properties": {
    "tgn:hierarchy":[
        "tgn:1101579",
        "tgn:7000490",
        "tgn:1000006",
        "tgn:7001830",
        "tgn:7029392"
    ],
    "tgn:id":1101579,
    "tgn:name":"Hinchinbrook Island National Park",
    "tgn:placetype":[
        "aat:300008189"
    ]
},
  "bbox": [],
  "geometry": {"coordinates":[146.3333,-18.3333],"type":"Point"}
}