{
  "id": 7593422,
  "type": "Feature",
  "properties": {
    "tgn:hierarchy":[
        "tgn:7593422",
        "tgn:7005402",
        "tgn:1000001",
        "tgn:7005388",
        "tgn:7029392"
    ],
    "tgn:id":7593422,
    "tgn:name":"Cabo Enga\u00f1o",
    "tgn:placetype":[
        "aat:300008347"
    ]
},
  "bbox": [],
  "geometry": {"coordinates":[-68.333,19.616],"type":"Point"}
}