{
  "id": 1000756,
  "type": "Feature",
  "properties": {
    "tgn:hierarchy":[
        "tgn:1000756",
        "tgn:7001242",
        "tgn:1000168",
        "tgn:7029392"
    ],
    "tgn:id":1000756,
    "tgn:name":"Sassandra, D\u00e9partement de",
    "tgn:placetype":[
        "aat:300387064",
        "aat:300000772"
    ]
},
  "bbox": [],
  "geometry": {"coordinates":[-6.1667,5.3333],"type":"Point"}
}