{
  "id": 1078326,
  "type": "Feature",
  "properties": {
    "tgn:hierarchy":[
        "tgn:1078326",
        "tgn:1000004",
        "tgn:1001502",
        "tgn:1000116",
        "tgn:7029392"
    ],
    "tgn:id":1078326,
    "tgn:name":"Pasirpengarayan",
    "tgn:placetype":[
        "aat:300008347"
    ]
},
  "bbox": [],
  "geometry": {"coordinates":[100.2667,0.85],"type":"Point"}
}