{
  "id": 7592053,
  "type": "Feature",
  "properties": {
    "tgn:hierarchy":[
        "tgn:7592053",
        "tgn:1000004",
        "tgn:7000198",
        "tgn:7000799",
        "tgn:7029392"
    ],
    "tgn:id":7592053,
    "tgn:name:en":"Charn\u0101h",
    "tgn:placetype":[
        "aat:300008347"
    ]
},
  "bbox": [],
  "geometry": {"coordinates":[74.992136,32.688768],"type":"Point"}
}