{
  "id": 1015678,
  "type": "Feature",
  "properties": {
    "tgn:hierarchy":[
        "tgn:1015678",
        "tgn:7005685",
        "tgn:1000001",
        "tgn:7005804",
        "tgn:7029392"
    ],
    "tgn:id":1015678,
    "tgn:name":"Saint-Joseph-de-Sorel",
    "tgn:placetype":[
        "aat:300008347"
    ]
},
  "bbox": [],
  "geometry": {"coordinates":[-73.1167,46.0333],"type":"Point"}
}