{
  "id": 7083459,
  "type": "Feature",
  "properties": {
    "tgn:hierarchy":[
        "tgn:7083459",
        "tgn:1000003",
        "tgn:7003676",
        "tgn:7000084",
        "tgn:7029392"
    ],
    "tgn:id":7083459,
    "tgn:name":"Wester-Berg",
    "tgn:placetype":[
        "aat:300008777"
    ]
},
  "bbox": [],
  "geometry": {"coordinates":[9.333333,52.183333],"type":"Point"}
}