{
  "id": 7268939,
  "type": "Feature",
  "properties": {
    "tgn:hierarchy":[
        "tgn:7268939",
        "tgn:7003614",
        "tgn:1000003",
        "tgn:7016845",
        "tgn:7029392"
    ],
    "tgn:id":7268939,
    "tgn:name:nl":"Ruimsloot",
    "tgn:placetype":[
        "aat:300006075"
    ]
},
  "bbox": [],
  "geometry": {"coordinates":[6.583333,52.95],"type":"Point"}
}