{
  "id": 2234886,
  "type": "Feature",
  "properties": {
    "tgn:hierarchy":[
        "tgn:2234886",
        "tgn:1000001",
        "tgn:2002262",
        "tgn:7012149",
        "tgn:7013961",
        "tgn:7029392"
    ],
    "tgn:id":2234886,
    "tgn:name":"Cherry Fork",
    "tgn:placetype":[
        "aat:300008699"
    ]
},
  "bbox": [],
  "geometry": {"coordinates":[-80.8667,39.0333],"type":"Point"}
}