{
  "id": 2742063,
  "type": "Feature",
  "properties": {
    "tgn:hierarchy":[
        "tgn:2742063",
        "tgn:7006450",
        "tgn:1000001",
        "tgn:7012149",
        "tgn:2000086",
        "tgn:7029392"
    ],
    "tgn:id":2742063,
    "tgn:name":"Valdez Glacier Stream",
    "tgn:placetype":[
        "aat:300008699"
    ]
},
  "bbox": [],
  "geometry": {"coordinates":[-146.1667,61.1333],"type":"Point"}
}