{
  "id": 7504593,
  "type": "Feature",
  "properties": {
    "tgn:hierarchy":[
        "tgn:7504593",
        "tgn:1008380",
        "tgn:7000507",
        "tgn:1000226",
        "tgn:1000006",
        "tgn:7029392"
    ],
    "tgn:id":7504593,
    "tgn:name:en":"Elizabeth Reef",
    "tgn:placetype":[
        "aat:300008808"
    ]
},
  "bbox": [],
  "geometry": {"coordinates":[174.499167,-35.508611],"type":"Point"}
}