{
  "id": 7330246,
  "type": "Feature",
  "properties": {
    "tgn:hierarchy":[
        "tgn:7330246",
        "tgn:7010420",
        "tgn:1000003",
        "tgn:7002795",
        "tgn:1000095",
        "tgn:7029392"
    ],
    "tgn:id":7330246,
    "tgn:name":"Horcajo de la Sierra",
    "tgn:placetype":[
        "aat:300008347"
    ]
},
  "bbox": [],
  "geometry": {"coordinates":[-3.583333,41.066667],"type":"Point"}
}