{
  "id": 2089830,
  "type": "Feature",
  "properties": {
    "tgn:hierarchy":[
        "tgn:2089830",
        "tgn:1000001",
        "tgn:7012149",
        "tgn:1002387",
        "tgn:7007710",
        "tgn:7029392"
    ],
    "tgn:id":2089830,
    "tgn:name":"Knepper",
    "tgn:placetype":[
        "aat:300008347",
        "aat:300387210"
    ]
},
  "bbox": [],
  "geometry": {"coordinates":[-77.5667,39.8167],"type":"Point"}
}