{
  "id": 2237252,
  "type": "Feature",
  "properties": {
    "tgn:hierarchy":[
        "tgn:2237252",
        "tgn:2002142",
        "tgn:1000001",
        "tgn:7012149",
        "tgn:7007919",
        "tgn:7029392"
    ],
    "tgn:id":2237252,
    "tgn:name":"Chimney Rock",
    "tgn:placetype":[
        "aat:300008798"
    ]
},
  "bbox": [],
  "geometry": {"coordinates":[-78.7667,38.1833],"type":"Point"}
}