{
  "id": 7282813,
  "type": "Feature",
  "properties": {
    "tgn:hierarchy":[
        "tgn:7282813",
        "tgn:1001637",
        "tgn:1000049",
        "tgn:1000002",
        "tgn:7029392"
    ],
    "tgn:id":7282813,
    "tgn:name":"Peluca",
    "tgn:placetype":[
        "aat:300008347"
    ]
},
  "bbox": [],
  "geometry": {"coordinates":[-71.616667,-37.333333],"type":"Point"}
}