{
  "id": 1011495,
  "type": "Feature",
  "properties": {
    "tgn:hierarchy":[
        "tgn:1011495",
        "tgn:5000432",
        "tgn:7002444",
        "tgn:1000003",
        "tgn:7008591",
        "tgn:7029392"
    ],
    "tgn:id":1011495,
    "tgn:name:en":"Rattray Head",
    "tgn:placetype":[
        "aat:300008850",
        "aat:300387499"
    ]
},
  "bbox": [],
  "geometry": {"coordinates":[-1.816667,57.616667],"type":"Point"}
}