{
  "id": 7169835,
  "type": "Feature",
  "properties": {
    "tgn:hierarchy":[
        "tgn:7169835",
        "tgn:7003669",
        "tgn:1000003",
        "tgn:7000084",
        "tgn:7029392"
    ],
    "tgn:id":7169835,
    "tgn:name":"Herfurth",
    "tgn:placetype":[
        "aat:300000206"
    ]
},
  "bbox": [],
  "geometry": {"coordinates":[12.433333,48.95],"type":"Point"}
}