{
  "id": 7310163,
  "type": "Feature",
  "properties": {
    "tgn:hierarchy":[
        "tgn:7310163",
        "tgn:1001637",
        "tgn:1000049",
        "tgn:1000002",
        "tgn:7029392"
    ],
    "tgn:id":7310163,
    "tgn:name":"Nitrao",
    "tgn:placetype":[
        "aat:300000206"
    ]
},
  "bbox": [],
  "geometry": {"coordinates":[-72.95,-37.216667],"type":"Point"}
}