{
  "id": 7199249,
  "type": "Feature",
  "properties": {
    "tgn:hierarchy":[
        "tgn:7199249",
        "tgn:7003669",
        "tgn:1000003",
        "tgn:7000084",
        "tgn:7029392"
    ],
    "tgn:id":7199249,
    "tgn:name":"Eichenbrunn",
    "tgn:placetype":[
        "aat:300008347"
    ]
},
  "bbox": [],
  "geometry": {"coordinates":[11.983333,49.066667],"type":"Point"}
}