{
  "id": 7468891,
  "type": "Feature",
  "properties": {
    "tgn:hierarchy":[
        "tgn:7468891",
        "tgn:1000004",
        "tgn:7492971",
        "tgn:1000141",
        "tgn:7029392"
    ],
    "tgn:id":7468891,
    "tgn:name":"Xindaluguan Nongchang",
    "tgn:placetype":[
        "aat:300000206"
    ]
},
  "bbox": [],
  "geometry": {"coordinates":[120.616667,22.733333],"type":"Point"}
}