<<<<<<< HEAD
{
  "id": 2259524,
  "type": "Feature",
  "properties": {
    "tgn:hierarchy":[
        "tgn:2259524",
        "tgn:1000001",
        "tgn:7012149",
        "tgn:2001276",
        "tgn:7007524",
        "tgn:7029392"
    ],
    "tgn:id":2259524,
    "tgn:name":"Cottonwood Tree Lakes",
    "tgn:placetype":[
        "aat:300006191"
    ]
},
  "bbox": [],
  "geometry": {"coordinates":[-106.9,46.8833],"type":"Point"}
}
=======
{"geometry":{"type":"Point","coordinates":[-106.900000,46.883300]},"type":"Feature","properties":{"hierarchy":["tgn:2259524","tgn:1000001","tgn:7012149","tgn:2001276","tgn:7007524","tgn:7029392"],"placetype":["aat:300006191"],"id":2259524,"name:xx":"Cottonwood Tree Lakes"}}
>>>>>>> 03f74aca74312dbeaf24d7e61306dd6a786dc3d0
