{
  "id": 2475802,
  "type": "Feature",
  "properties": {
    "tgn:hierarchy":[
        "tgn:2475802",
        "tgn:1000001",
        "tgn:7012149",
        "tgn:7007157",
        "tgn:2000191",
        "tgn:7029392"
    ],
    "tgn:id":2475802,
    "tgn:name":"Lucky Sunday Mine",
    "tgn:placetype":[
        "aat:300000390"
    ]
},
  "bbox": [],
  "geometry": {"coordinates":[-123.2333,40.15],"type":"Point"}
}