{
  "id": 7096047,
  "type": "Feature",
  "properties": {
    "tgn:hierarchy":[
        "tgn:7096047",
        "tgn:7003669",
        "tgn:1000003",
        "tgn:7000084",
        "tgn:7029392"
    ],
    "tgn:id":7096047,
    "tgn:name":"Schressendorf",
    "tgn:placetype":[
        "aat:300008347"
    ]
},
  "bbox": [],
  "geometry": {"coordinates":[11.333333,49.883333],"type":"Point"}
}