{
  "id": 7332678,
  "type": "Feature",
  "properties": {
    "tgn:hierarchy":[
        "tgn:7332678",
        "tgn:7002805",
        "tgn:7002758",
        "tgn:1000003",
        "tgn:1000095",
        "tgn:7029392"
    ],
    "tgn:id":7332678,
    "tgn:name":"La Fuensanta",
    "tgn:placetype":[
        "aat:300008347"
    ]
},
  "bbox": [],
  "geometry": {"coordinates":[-1.95,37.516667],"type":"Point"}
}