{
  "id": 2458732,
  "type": "Feature",
  "properties": {
    "tgn:hierarchy":[
        "tgn:2458732",
        "tgn:1000001",
        "tgn:7012149",
        "tgn:1002593",
        "tgn:7007568",
        "tgn:7029392"
    ],
    "tgn:id":2458732,
    "tgn:name":"Little Otter Lake",
    "tgn:placetype":[
        "aat:300008680"
    ]
},
  "bbox": [],
  "geometry": {"coordinates":[-75.25,43.7333],"type":"Point"}
}