{
  "id": 2656742,
  "type": "Feature",
  "properties": {
    "tgn:hierarchy":[
        "tgn:2656742",
        "tgn:1000001",
        "tgn:2002144",
        "tgn:7012149",
        "tgn:7007919",
        "tgn:7029392"
    ],
    "tgn:id":2656742,
    "tgn:name":"Sheep Creek",
    "tgn:placetype":[
        "aat:300008706"
    ]
},
  "bbox": [],
  "geometry": {"coordinates":[-79.6167,37.45],"type":"Point"}
}