<<<<<<< HEAD
{
  "id": 2155980,
  "type": "Feature",
  "properties": {
    "tgn:hierarchy":[
        "tgn:2155980",
        "tgn:1000001",
        "tgn:7012149",
        "tgn:2001457",
        "tgn:7007566",
        "tgn:7029392"
    ],
    "tgn:id":2155980,
    "tgn:name":"Bear Wallow Canyon",
    "tgn:placetype":[
        "aat:300008761"
    ]
},
  "bbox": [],
  "geometry": {"coordinates":[-105.5167,36.2833],"type":"Point"}
}
=======
{"geometry":{"type":"Point","coordinates":[-105.516700,36.283300]},"type":"Feature","properties":{"hierarchy":["tgn:2155980","tgn:1000001","tgn:7012149","tgn:2001457","tgn:7007566","tgn:7029392"],"placetype":["aat:300008761"],"id":2155980,"name:xx":"Bear Wallow Canyon"}}
>>>>>>> 03f74aca74312dbeaf24d7e61306dd6a786dc3d0
