{
  "id": 7220343,
  "type": "Feature",
  "properties": {
    "tgn:hierarchy":[
        "tgn:7220343",
        "tgn:7002706",
        "tgn:7002705",
        "tgn:1000003",
        "tgn:1000074",
        "tgn:7029392"
    ],
    "tgn:id":7220343,
    "tgn:name":"T\u00e1vla",
    "tgn:placetype":[
        "aat:300008347"
    ]
},
  "bbox": [],
  "geometry": {"coordinates":[21.113056,39.300556],"type":"Point"}
}