<<<<<<< HEAD
{
  "id": 2401194,
  "type": "Feature",
  "properties": {
    "tgn:hierarchy":[
        "tgn:2401194",
        "tgn:1000001",
        "tgn:7012149",
        "tgn:2001248",
        "tgn:7007523",
        "tgn:7029392"
    ],
    "tgn:id":2401194,
    "tgn:name":"Horsehead Knoll",
    "tgn:placetype":[
        "aat:300008798"
    ]
},
  "bbox": [],
  "geometry": {"coordinates":[-90.1333,37.0167],"type":"Point"}
}
=======
{"geometry":{"type":"Point","coordinates":[-90.133300,37.016700]},"type":"Feature","properties":{"hierarchy":["tgn:2401194","tgn:1000001","tgn:7012149","tgn:2001248","tgn:7007523","tgn:7029392"],"placetype":["aat:300008798"],"id":2401194,"name:xx":"Horsehead Knoll"}}
>>>>>>> 03f74aca74312dbeaf24d7e61306dd6a786dc3d0
