{
  "id": 2137518,
  "type": "Feature",
  "properties": {
    "tgn:hierarchy":[
        "tgn:2137518",
        "tgn:1000001",
        "tgn:7012149",
        "tgn:7007157",
        "tgn:2000189",
        "tgn:7029392"
    ],
    "tgn:id":2137518,
    "tgn:name":"Arnica Sink",
    "tgn:placetype":[
        "aat:300386845"
    ]
},
  "bbox": [],
  "geometry": {"coordinates":[-121.5667,41.5833],"type":"Point"}
}