{
  "id": 7163078,
  "type": "Feature",
  "properties": {
    "tgn:hierarchy":[
        "tgn:7163078",
        "tgn:1000003",
        "tgn:7003676",
        "tgn:7000084",
        "tgn:7029392"
    ],
    "tgn:id":7163078,
    "tgn:name":"In den Fuhren",
    "tgn:placetype":[
        "aat:300000206"
    ]
},
  "bbox": [],
  "geometry": {"coordinates":[9.116667,53.116667],"type":"Point"}
}