{
  "id": 1086450,
  "type": "Feature",
  "properties": {
    "tgn:hierarchy":[
        "tgn:1086450",
        "tgn:1001052",
        "tgn:1000004",
        "tgn:7018450",
        "tgn:1000144",
        "tgn:7029392"
    ],
    "tgn:id":1086450,
    "tgn:name":"K\u00f6m\u00fcrc\u00fcp\u0131nar",
    "tgn:placetype":[
        "aat:300008347"
    ]
},
  "bbox": [],
  "geometry": {"coordinates":[28.85,41.25],"type":"Point"}
}