<<<<<<< HEAD
{
  "id": 7361043,
  "type": "Feature",
  "properties": {
    "tgn:hierarchy":[
        "tgn:7361043",
        "tgn:1000001",
        "tgn:1001960",
        "tgn:7005560",
        "tgn:7029392"
    ],
    "tgn:id":7361043,
    "tgn:name":"Rancho El Colorado",
    "tgn:placetype":[
        "aat:300000241"
    ]
},
  "bbox": [],
  "geometry": {"coordinates":[-108.616667,29.733333],"type":"Point"}
}
=======
{"geometry":{"type":"Point","coordinates":[-108.616667,29.733333]},"type":"Feature","properties":{"hierarchy":["tgn:7361043","tgn:1000001","tgn:1001960","tgn:7005560","tgn:7029392"],"placetype":["aat:300000241"],"id":7361043,"name:xx":"Rancho El Colorado"}}
>>>>>>> 03f74aca74312dbeaf24d7e61306dd6a786dc3d0
