{
  "id": 1050500,
  "type": "Feature",
  "properties": {
    "tgn:hierarchy":[
        "tgn:1050500",
        "tgn:7002444",
        "tgn:7008074",
        "tgn:1000003",
        "tgn:7008591",
        "tgn:7029392"
    ],
    "tgn:id":1050500,
    "tgn:name:en":"Canonbie",
    "tgn:placetype":[
        "aat:300008347"
    ]
},
  "bbox": [],
  "geometry": {"coordinates":[-2.95,55.066667],"type":"Point"}
}