{
  "id": 7494819,
  "type": "Feature",
  "properties": {
    "tgn:hierarchy":[
        "tgn:7494819",
        "tgn:7468018",
        "tgn:1000004",
        "tgn:1000141",
        "tgn:7029392"
    ],
    "tgn:id":7494819,
    "tgn:name":"Taoziliaowei",
    "tgn:placetype":[
        "aat:300008347"
    ]
},
  "bbox": [],
  "geometry": {"coordinates":[120.580261,23.411096],"type":"Point"}
}