{
  "id": 2146630,
  "type": "Feature",
  "properties": {
    "tgn:hierarchy":[
        "tgn:2146630",
        "tgn:1000001",
        "tgn:7012149",
        "tgn:2002164",
        "tgn:7007919",
        "tgn:7029392"
    ],
    "tgn:id":2146630,
    "tgn:name":"Band Branch",
    "tgn:placetype":[
        "aat:300008699"
    ]
},
  "bbox": [],
  "geometry": {"coordinates":[-81.1833,36.5833],"type":"Point"}
}