{
  "id": 7347092,
  "type": "Feature",
  "properties": {
    "tgn:hierarchy":[
        "tgn:7347092",
        "tgn:7002836",
        "tgn:7016622",
        "tgn:1000003",
        "tgn:1000095",
        "tgn:7029392"
    ],
    "tgn:id":7347092,
    "tgn:name":"Arenal, Playa del",
    "tgn:placetype":[
        "aat:300008816"
    ]
},
  "bbox": [],
  "geometry": {"coordinates":[-16.333333,28.55],"type":"Point"}
}