{
  "id": 2657511,
  "type": "Feature",
  "properties": {
    "tgn:hierarchy":[
        "tgn:2657511",
        "tgn:1000001",
        "tgn:2002146",
        "tgn:7012149",
        "tgn:7007919",
        "tgn:7029392"
    ],
    "tgn:id":2657511,
    "tgn:name":"Sheets Mountain",
    "tgn:placetype":[
        "aat:300008798"
    ]
},
  "bbox": [],
  "geometry": {"coordinates":[-79.75,37.65],"type":"Point"}
}