{
  "id": 1064921,
  "type": "Feature",
  "properties": {
    "tgn:hierarchy":[
        "tgn:1064921",
        "tgn:7017294",
        "tgn:1000003",
        "tgn:7006663",
        "tgn:7029392"
    ],
    "tgn:id":1064921,
    "tgn:name":"Benkovac",
    "tgn:placetype":[
        "aat:300008347"
    ]
},
  "bbox": [],
  "geometry": {"coordinates":[15.65,44.0333],"type":"Point"}
}