{
  "id": 1065098,
  "type": "Feature",
  "properties": {
    "tgn:hierarchy":[
        "tgn:1065098",
        "tgn:7015108",
        "tgn:1000003",
        "tgn:7006670",
        "tgn:7029392"
    ],
    "tgn:id":1065098,
    "tgn:name":"Lendava",
    "tgn:placetype":[
        "aat:300008347",
        "aat:300387222",
        "aat:300008375"
    ]
},
  "bbox": [],
  "geometry": {"coordinates":[16.45,46.5667],"type":"Point"}
}