{
  "id": 2459263,
  "type": "Feature",
  "properties": {
    "tgn:hierarchy":[
        "tgn:2459263",
        "tgn:1000001",
        "tgn:7012149",
        "tgn:7014589",
        "tgn:7007515",
        "tgn:7029392"
    ],
    "tgn:id":2459263,
    "tgn:name":"Little Point",
    "tgn:placetype":[
        "aat:300008850"
    ]
},
  "bbox": [],
  "geometry": {"coordinates":[-67.3833,44.6667],"type":"Point"}
}