{
  "id": 2341962,
  "type": "Feature",
  "properties": {
    "tgn:hierarchy":[
        "tgn:2341962",
        "tgn:7006450",
        "tgn:1000001",
        "tgn:7012149",
        "tgn:2000089",
        "tgn:7029392"
    ],
    "tgn:id":2341962,
    "tgn:name":"Fry Island",
    "tgn:placetype":[
        "aat:300008791"
    ]
},
  "bbox": [],
  "geometry": {"coordinates":[-154.9333,65.7833],"type":"Point"}
}