{
  "id": 2532526,
  "type": "Feature",
  "properties": {
    "tgn:hierarchy":[
        "tgn:2532526",
        "tgn:1000001",
        "tgn:7012149",
        "tgn:7007157",
        "tgn:2000185",
        "tgn:7029392"
    ],
    "tgn:id":2532526,
    "tgn:name":"Murphy Creek",
    "tgn:placetype":[
        "aat:300008706"
    ]
},
  "bbox": [],
  "geometry": {"coordinates":[-123.15,39.9167],"type":"Point"}
}