{
  "id": 7528091,
  "type": "Feature",
  "properties": {
    "tgn:hierarchy":[
        "tgn:7528091",
        "tgn:7001242",
        "tgn:7016833",
        "tgn:1001087",
        "tgn:7029392"
    ],
    "tgn:id":7528091,
    "tgn:name:en":"Sinjirj",
    "tgn:placetype":[
        "aat:300008347"
    ]
},
  "bbox": [],
  "geometry": {"coordinates":[30.946658,30.511607],"type":"Point"}
}