{
  "id": 2209015,
  "type": "Feature",
  "properties": {
    "tgn:hierarchy":[
        "tgn:2209015",
        "tgn:1000001",
        "tgn:7012149",
        "tgn:2002113",
        "tgn:7007827",
        "tgn:7029392"
    ],
    "tgn:id":2209015,
    "tgn:name":"Burnt Flat Gulch",
    "tgn:placetype":[
        "aat:300008761"
    ]
},
  "bbox": [],
  "geometry": {"coordinates":[-112.7333,37.3167],"type":"Point"}
}