{
  "id": 7525916,
  "type": "Feature",
  "properties": {
    "tgn:hierarchy":[
        "tgn:7525916",
        "tgn:7001242",
        "tgn:7016833",
        "tgn:1001114",
        "tgn:7029392"
    ],
    "tgn:id":7525916,
    "tgn:name:en":"Ash Shan\u0101bilah",
    "tgn:placetype":[
        "aat:300008347"
    ]
},
  "bbox": [],
  "geometry": {"coordinates":[31.030435,27.314549],"type":"Point"}
}