{
  "id": 2652290,
  "type": "Feature",
  "properties": {
    "tgn:hierarchy":[
        "tgn:2652290",
        "tgn:1000001",
        "tgn:2002368",
        "tgn:7012149",
        "tgn:7007923",
        "tgn:7029392"
    ],
    "tgn:id":2652290,
    "tgn:name":"Seminoe Mine",
    "tgn:placetype":[
        "aat:300000390"
    ]
},
  "bbox": [],
  "geometry": {"coordinates":[-106.75,41.8667],"type":"Point"}
}