{
  "id": 7362351,
  "type": "Feature",
  "properties": {
    "tgn:hierarchy":[
        "tgn:7362351",
        "tgn:7005585",
        "tgn:1000001",
        "tgn:7005560",
        "tgn:7029392"
    ],
    "tgn:id":7362351,
    "tgn:name":"El Papayo",
    "tgn:placetype":[
        "aat:300008347"
    ]
},
  "bbox": [],
  "geometry": {"coordinates":[-100.533333,17.916667],"type":"Point"}
}