{
  "id": 7432644,
  "type": "Feature",
  "properties": {
    "tgn:hierarchy":[
        "tgn:7432644",
        "tgn:1000001",
        "tgn:1001937",
        "tgn:7005560",
        "tgn:7029392"
    ],
    "tgn:id":7432644,
    "tgn:name":"Tomas Aznar",
    "tgn:placetype":[
        "aat:300008347"
    ]
},
  "bbox": [],
  "geometry": {"coordinates":[-89.183333,18.483333],"type":"Point"}
}