{
  "id": 2273461,
  "type": "Feature",
  "properties": {
    "tgn:hierarchy":[
        "tgn:2273461",
        "tgn:1000001",
        "tgn:7012149",
        "tgn:2001160",
        "tgn:7007522",
        "tgn:7029392"
    ],
    "tgn:id":2273461,
    "tgn:name":"Cypress Lake",
    "tgn:placetype":[
        "aat:300008680"
    ]
},
  "bbox": [],
  "geometry": {"coordinates":[-91.0833,32.1667],"type":"Point"}
}