{
  "id": 2223825,
  "type": "Feature",
  "properties": {
    "tgn:hierarchy":[
        "tgn:2223825",
        "tgn:1000001",
        "tgn:2001265",
        "tgn:7012149",
        "tgn:7007524",
        "tgn:7029392"
    ],
    "tgn:id":2223825,
    "tgn:name":"Carter Spring",
    "tgn:placetype":[
        "aat:300008697"
    ]
},
  "bbox": [],
  "geometry": {"coordinates":[-104.4833,45.85],"type":"Point"}
}