{
  "id": 7557456,
  "type": "Feature",
  "properties": {
    "tgn:hierarchy":[
        "tgn:7557456",
        "tgn:1000004",
        "tgn:7031781",
        "tgn:7000198",
        "tgn:7029392"
    ],
    "tgn:id":7557456,
    "tgn:name:en":"R\u0101mtek",
    "tgn:placetype":[
        "aat:300008347"
    ]
},
  "bbox": [],
  "geometry": {"coordinates":[83.112441,21.493249],"type":"Point"}
}