{
  "id": 2689348,
  "type": "Feature",
  "properties": {
    "tgn:hierarchy":[
        "tgn:2689348",
        "tgn:1000001",
        "tgn:1002270",
        "tgn:7012149",
        "tgn:7007708",
        "tgn:7029392"
    ],
    "tgn:id":2689348,
    "tgn:name":"Squaw Creek",
    "tgn:placetype":[
        "aat:300008706"
    ]
},
  "bbox": [],
  "geometry": {"coordinates":[-122.0167,45.2167],"type":"Point"}
}