{
  "id": 2522181,
  "type": "Feature",
  "properties": {
    "tgn:hierarchy":[
        "tgn:2522181",
        "tgn:1000001",
        "tgn:7012149",
        "tgn:2002248",
        "tgn:7007920",
        "tgn:7029392"
    ],
    "tgn:id":2522181,
    "tgn:name":"Moon Creek",
    "tgn:placetype":[
        "aat:300008706"
    ]
},
  "bbox": [],
  "geometry": {"coordinates":[-117.2833,48.0833],"type":"Point"}
}