{
  "id": 2524924,
  "type": "Feature",
  "properties": {
    "tgn:hierarchy":[
        "tgn:2524924",
        "tgn:1000001",
        "tgn:7012149",
        "tgn:2001118",
        "tgn:7007522",
        "tgn:7029392"
    ],
    "tgn:id":2524924,
    "tgn:name":"Morris",
    "tgn:placetype":[
        "aat:300008347"
    ]
},
  "bbox": [],
  "geometry": {"coordinates":[-89.65,31.45],"type":"Point"}
}