{
  "id": 7516923,
  "type": "Feature",
  "properties": {
    "tgn:hierarchy":[
        "tgn:7516923",
        "tgn:1009227",
        "tgn:1000226",
        "tgn:7016822",
        "tgn:1000006",
        "tgn:7029392"
    ],
    "tgn:id":7516923,
    "tgn:name:en":"North West Reef",
    "tgn:placetype":[
        "aat:300008808"
    ]
},
  "bbox": [],
  "geometry": {"coordinates":[-176.916667,-43.516667],"type":"Point"}
}