<<<<<<< HEAD
{
  "id": 7021178,
  "type": "Feature",
  "properties": {
    "tgn:hierarchy":[
        "tgn:7021178",
        "tgn:1000001",
        "tgn:7012149",
        "tgn:2002271",
        "tgn:7013961",
        "tgn:7029392"
    ],
    "tgn:id":7021178,
    "tgn:name":"Wolf Run",
    "tgn:placetype":[
        "aat:300008699"
    ]
},
  "bbox": [],
  "geometry": {"coordinates":[-80.3667,38.9167],"type":"Point"}
}
=======
{"geometry":{"type":"Point","coordinates":[-80.366700,38.916700]},"type":"Feature","properties":{"hierarchy":["tgn:7021178","tgn:1000001","tgn:7012149","tgn:2002271","tgn:7013961","tgn:7029392"],"placetype":["aat:300008699"],"id":7021178,"name:xx":"Wolf Run"}}
>>>>>>> 03f74aca74312dbeaf24d7e61306dd6a786dc3d0
