{
  "id": 7021178,
  "type": "Feature",
  "properties": {
    "tgn:hierarchy":[
        "tgn:7021178",
        "tgn:1000001",
        "tgn:7012149",
        "tgn:2002271",
        "tgn:7013961",
        "tgn:7029392"
    ],
    "tgn:id":7021178,
    "tgn:name":"Wolf Run",
    "tgn:placetype":[
        "aat:300008699"
    ]
},
  "bbox": [],
  "geometry": {"coordinates":[-80.3667,38.9167],"type":"Point"}
}