{
  "id": 2725886,
  "type": "Feature",
  "properties": {
    "tgn:hierarchy":[
        "tgn:2725886",
        "tgn:1000001",
        "tgn:7012149",
        "tgn:2002051",
        "tgn:7007826",
        "tgn:7029392"
    ],
    "tgn:id":2725886,
    "tgn:name":"Torrey Tank",
    "tgn:placetype":[
        "aat:300006191"
    ]
},
  "bbox": [],
  "geometry": {"coordinates":[-102.4167,35.4833],"type":"Point"}
}