{
  "id": 2698980,
  "type": "Feature",
  "properties": {
    "tgn:hierarchy":[
        "tgn:2698980",
        "tgn:1000001",
        "tgn:7012149",
        "tgn:2001714",
        "tgn:7007708",
        "tgn:7029392"
    ],
    "tgn:id":2698980,
    "tgn:name":"Strawberry Spring",
    "tgn:placetype":[
        "aat:300008697"
    ]
},
  "bbox": [],
  "geometry": {"coordinates":[-120.6667,42.6333],"type":"Point"}
}