{
  "id": 7477443,
  "type": "Feature",
  "properties": {
    "tgn:hierarchy":[
        "tgn:7477443",
        "tgn:7488858",
        "tgn:1000004",
        "tgn:1000141",
        "tgn:7029392"
    ],
    "tgn:id":7477443,
    "tgn:name":"Dishuikeng",
    "tgn:placetype":[
        "aat:300008347"
    ]
},
  "bbox": [],
  "geometry": {"coordinates":[120.960866,23.917087],"type":"Point"}
}