{
  "id": 2633685,
  "type": "Feature",
  "properties": {
    "tgn:hierarchy":[
        "tgn:2633685",
        "tgn:1000001",
        "tgn:2000470",
        "tgn:7012149",
        "tgn:7007250",
        "tgn:7029392"
    ],
    "tgn:id":2633685,
    "tgn:name":"Rush Creek",
    "tgn:placetype":[
        "aat:300008706"
    ]
},
  "bbox": [],
  "geometry": {"coordinates":[-114.65,44.5333],"type":"Point"}
}