<<<<<<< HEAD
{
  "id": 2766987,
  "type": "Feature",
  "properties": {
    "tgn:hierarchy":[
        "tgn:2766987",
        "tgn:1000001",
        "tgn:2000460",
        "tgn:7012149",
        "tgn:7007250",
        "tgn:7029392"
    ],
    "tgn:id":2766987,
    "tgn:name":"White Quartz Ridge",
    "tgn:placetype":[
        "aat:300266640"
    ]
},
  "bbox": [],
  "geometry": {"coordinates":[-116.3667,48.0833],"type":"Point"}
}
=======
{"geometry":{"type":"Point","coordinates":[-116.366700,48.083300]},"type":"Feature","properties":{"hierarchy":["tgn:2766987","tgn:1000001","tgn:2000460","tgn:7012149","tgn:7007250","tgn:7029392"],"placetype":["aat:300266640"],"id":2766987,"name:xx":"White Quartz Ridge"}}
>>>>>>> 03f74aca74312dbeaf24d7e61306dd6a786dc3d0
