{
  "id": 7231604,
  "type": "Feature",
  "properties": {
    "tgn:hierarchy":[
        "tgn:7231604",
        "tgn:7002709",
        "tgn:7002705",
        "tgn:1000003",
        "tgn:1000074",
        "tgn:7029392"
    ],
    "tgn:id":7231604,
    "tgn:name":"Kourem\u00e1dion",
    "tgn:placetype":[
        "aat:300008347"
    ]
},
  "bbox": [],
  "geometry": {"coordinates":[20.466111,39.752778],"type":"Point"}
}