{
  "id": 2657057,
  "type": "Feature",
  "properties": {
    "tgn:hierarchy":[
        "tgn:2657057",
        "tgn:1000001",
        "tgn:7012149",
        "tgn:2001708",
        "tgn:7007708",
        "tgn:7029392"
    ],
    "tgn:id":2657057,
    "tgn:name":"Sheep Mountain",
    "tgn:placetype":[
        "aat:300008798"
    ]
},
  "bbox": [],
  "geometry": {"coordinates":[-118.4667,44.25],"type":"Point"}
}