<<<<<<< HEAD
{
  "id": 2337465,
  "type": "Feature",
  "properties": {
    "tgn:hierarchy":[
        "tgn:2337465",
        "tgn:1000001",
        "tgn:7016172",
        "tgn:7012149",
        "tgn:2000155",
        "tgn:7029392"
    ],
    "tgn:id":2337465,
    "tgn:name":"Fowler Lake",
    "tgn:placetype":[
        "aat:300006191"
    ]
},
  "bbox": [],
  "geometry": {"coordinates":[-93.4,35.95],"type":"Point"}
}
=======
{"geometry":{"type":"Point","coordinates":[-93.400000,35.950000]},"type":"Feature","properties":{"hierarchy":["tgn:2337465","tgn:1000001","tgn:7016172","tgn:7012149","tgn:2000155","tgn:7029392"],"placetype":["aat:300006191"],"id":2337465,"name:xx":"Fowler Lake"}}
>>>>>>> 03f74aca74312dbeaf24d7e61306dd6a786dc3d0
