{
  "id": 7484558,
  "type": "Feature",
  "properties": {
    "tgn:hierarchy":[
        "tgn:7484558",
        "tgn:1000004",
        "tgn:7492971",
        "tgn:1000141",
        "tgn:7029392"
    ],
    "tgn:id":7484558,
    "tgn:name":"Jiadong Gaonong",
    "tgn:placetype":[
        "aat:300006495"
    ]
},
  "bbox": [],
  "geometry": {"coordinates":[120.564444,22.412222],"type":"Point"}
}