{
  "id": 7365157,
  "type": "Feature",
  "properties": {
    "tgn:hierarchy":[
        "tgn:7365157",
        "tgn:7005580",
        "tgn:1000001",
        "tgn:7005560",
        "tgn:7029392"
    ],
    "tgn:id":7365157,
    "tgn:name":"El Sina\u00ed",
    "tgn:placetype":[
        "aat:300008347"
    ]
},
  "bbox": [],
  "geometry": {"coordinates":[-93.316667,16.933333],"type":"Point"}
}