{
  "id": 2163304,
  "type": "Feature",
  "properties": {
    "tgn:hierarchy":[
        "tgn:2163304",
        "tgn:1000001",
        "tgn:2001477",
        "tgn:7012149",
        "tgn:7007709",
        "tgn:7029392"
    ],
    "tgn:id":2163304,
    "tgn:name":"Benneys Creek",
    "tgn:placetype":[
        "aat:300008706"
    ]
},
  "bbox": [],
  "geometry": {"coordinates":[-76.45,34.9167],"type":"Point"}
}