{
  "id": 2017346,
  "type": "Feature",
  "properties": {
    "tgn:hierarchy":[
        "tgn:2017346",
        "tgn:1000001",
        "tgn:1002712",
        "tgn:7012149",
        "tgn:7007159",
        "tgn:7029392"
    ],
    "tgn:id":2017346,
    "tgn:name":"Riverside",
    "tgn:placetype":[
        "aat:300008347",
        "aat:300387210"
    ]
},
  "bbox": [],
  "geometry": {"coordinates":[-73.1667,41.3833],"type":"Point"}
}