{
  "id": 1043321,
  "type": "Feature",
  "properties": {
    "tgn:hierarchy":[
        "tgn:1043321",
        "tgn:7005852",
        "tgn:1000003",
        "tgn:7003237",
        "tgn:1000080",
        "tgn:7029392"
    ],
    "tgn:id":1043321,
    "tgn:name":"Asso",
    "tgn:placetype":[
        "aat:300008347"
    ]
},
  "bbox": [],
  "geometry": {"coordinates":[9.266667,45.866667],"type":"Point"}
}