{
  "id": 7550448,
  "type": "Feature",
  "properties": {
    "tgn:hierarchy":[
        "tgn:7550448",
        "tgn:1000004",
        "tgn:7000198",
        "tgn:7000799",
        "tgn:7029392"
    ],
    "tgn:id":7550448,
    "tgn:name:en":"Bhut Nad\u012b",
    "tgn:placetype":[
        "aat:300008699"
    ]
},
  "bbox": [],
  "geometry": {"coordinates":[76.164811,33.271404],"type":"Point"}
}