<<<<<<< HEAD
{
  "id": 2251210,
  "type": "Feature",
  "properties": {
    "tgn:hierarchy":[
        "tgn:2251210",
        "tgn:1000001",
        "tgn:7012149",
        "tgn:2001446",
        "tgn:7007566",
        "tgn:7029392"
    ],
    "tgn:id":2251210,
    "tgn:name":"Comanche Peak",
    "tgn:placetype":[
        "aat:300008798"
    ]
},
  "bbox": [],
  "geometry": {"coordinates":[-105.3,36.0167],"type":"Point"}
}
=======
{"geometry":{"type":"Point","coordinates":[-105.300000,36.016700]},"type":"Feature","properties":{"hierarchy":["tgn:2251210","tgn:1000001","tgn:7012149","tgn:2001446","tgn:7007566","tgn:7029392"],"placetype":["aat:300008798"],"id":2251210,"name:xx":"Comanche Peak"}}
>>>>>>> 03f74aca74312dbeaf24d7e61306dd6a786dc3d0
