{
  "id": 2462966,
  "type": "Feature",
  "properties": {
    "tgn:hierarchy":[
        "tgn:2462966",
        "tgn:1000001",
        "tgn:7012149",
        "tgn:2001962",
        "tgn:7007826",
        "tgn:7029392"
    ],
    "tgn:id":2462966,
    "tgn:name":"Live Oak Creek",
    "tgn:placetype":[
        "aat:300008706"
    ]
},
  "bbox": [],
  "geometry": {"coordinates":[-98.3833,31.7333],"type":"Point"}
}