{
  "id": 7259710,
  "type": "Feature",
  "properties": {
    "tgn:hierarchy":[
        "tgn:7259710",
        "tgn:7007877",
        "tgn:1000003",
        "tgn:1000063",
        "tgn:4012014",
        "tgn:7029392"
    ],
    "tgn:id":7259710,
    "tgn:name":"Waudrez",
    "tgn:placetype":[
        "aat:300008347"
    ]
},
  "bbox": [],
  "geometry": {"coordinates":[4.133333,50.416667],"type":"Point"}
}