{
  "id": 7348866,
  "type": "Feature",
  "properties": {
    "tgn:hierarchy":[
        "tgn:7348866",
        "tgn:1000001",
        "tgn:1001960",
        "tgn:7005560",
        "tgn:7029392"
    ],
    "tgn:id":7348866,
    "tgn:name":"Alamo, Arroyo el",
    "tgn:placetype":[
        "aat:300266554",
        "aat:300008699"
    ]
},
  "bbox": [],
  "geometry": {"coordinates":[-111.233333,30.316667],"type":"Point"}
}