{
  "id": 2375274,
  "type": "Feature",
  "properties": {
    "tgn:hierarchy":[
        "tgn:2375274",
        "tgn:1000001",
        "tgn:7012149",
        "tgn:1003020",
        "tgn:7007920",
        "tgn:7029392"
    ],
    "tgn:id":2375274,
    "tgn:name":"Hannegan Peak",
    "tgn:placetype":[
        "aat:300008798"
    ]
},
  "bbox": [],
  "geometry": {"coordinates":[-121.5167,48.8833],"type":"Point"}
}