{
  "id": 2553838,
  "type": "Feature",
  "properties": {
    "tgn:hierarchy":[
        "tgn:2553838",
        "tgn:1002996",
        "tgn:1000001",
        "tgn:7012149",
        "tgn:7007711",
        "tgn:7029392"
    ],
    "tgn:id":2553838,
    "tgn:name":"Oak Hill Pond",
    "tgn:placetype":[
        "aat:300008680"
    ]
},
  "bbox": [],
  "geometry": {"coordinates":[-71.4833,41.55],"type":"Point"}
}