{
  "id": 7518575,
  "type": "Feature",
  "properties": {
    "tgn:hierarchy":[
        "tgn:7518575",
        "tgn:7000508",
        "tgn:1008380",
        "tgn:1000226",
        "tgn:1000006",
        "tgn:7029392"
    ],
    "tgn:id":7518575,
    "tgn:name:en":"Lucas Creek",
    "tgn:placetype":[
        "aat:300008777"
    ]
},
  "bbox": [],
  "geometry": {"coordinates":[174.666667,-36.75],"type":"Point"}
}