{
  "id": 2200160,
  "type": "Feature",
  "properties": {
    "tgn:hierarchy":[
        "tgn:2200160",
        "tgn:1000001",
        "tgn:7012149",
        "tgn:2002043",
        "tgn:7007826",
        "tgn:7029392"
    ],
    "tgn:id":2200160,
    "tgn:name":"Brushy Creek",
    "tgn:placetype":[
        "aat:300008706"
    ]
},
  "bbox": [],
  "geometry": {"coordinates":[-100.6667,32.1333],"type":"Point"}
}