{
  "id": 7152457,
  "type": "Feature",
  "properties": {
    "tgn:hierarchy":[
        "tgn:7152457",
        "tgn:7000096",
        "tgn:1000003",
        "tgn:7000084",
        "tgn:7029392"
    ],
    "tgn:id":7152457,
    "tgn:name":"K\u00e4se H\u00fcgel",
    "tgn:placetype":[
        "aat:300008777"
    ]
},
  "bbox": [],
  "geometry": {"coordinates":[14.633333,51.916667],"type":"Point"}
}