{
  "id": 2400807,
  "type": "Feature",
  "properties": {
    "tgn:hierarchy":[
        "tgn:2400807",
        "tgn:1000001",
        "tgn:7012149",
        "tgn:2001756",
        "tgn:7007712",
        "tgn:7029392"
    ],
    "tgn:id":2400807,
    "tgn:name":"Horse Pond",
    "tgn:placetype":[
        "aat:300008680"
    ]
},
  "bbox": [],
  "geometry": {"coordinates":[-81.0667,33.9833],"type":"Point"}
}