{
  "id": 7034645,
  "type": "Feature",
  "properties": {
    "tgn:hierarchy":[
        "tgn:7034645",
        "tgn:7003006",
        "tgn:1000003",
        "tgn:7002997",
        "tgn:1000080",
        "tgn:7029392"
    ],
    "tgn:id":7034645,
    "tgn:name":"Orfanello, Canale",
    "tgn:placetype":[
        "aat:300008713"
    ]
},
  "bbox": [],
  "geometry": {"coordinates":[12.35,45.429167],"type":"Point"}
}