<<<<<<< HEAD
{
  "id": 7374799,
  "type": "Feature",
  "properties": {
    "tgn:hierarchy":[
        "tgn:7374799",
        "tgn:7005581",
        "tgn:1000001",
        "tgn:7005560",
        "tgn:7029392"
    ],
    "tgn:id":7374799,
    "tgn:name":"Rancho Lagunitas",
    "tgn:placetype":[
        "aat:300000241"
    ]
},
  "bbox": [],
  "geometry": {"coordinates":[-107.05,26.9],"type":"Point"}
}
=======
{"geometry":{"type":"Point","coordinates":[-107.050000,26.900000]},"type":"Feature","properties":{"hierarchy":["tgn:7374799","tgn:7005581","tgn:1000001","tgn:7005560","tgn:7029392"],"placetype":["aat:300000241"],"id":7374799,"name:xx":"Rancho Lagunitas"}}
>>>>>>> 03f74aca74312dbeaf24d7e61306dd6a786dc3d0
