<<<<<<< HEAD
{
  "id": 7247173,
  "type": "Feature",
  "properties": {
    "tgn:hierarchy":[
        "tgn:7247173",
        "tgn:7003466",
        "tgn:1000003",
        "tgn:1000063",
        "tgn:4012014",
        "tgn:7029392"
    ],
    "tgn:id":7247173,
    "tgn:name":"Dame, Bois de la",
    "tgn:placetype":[
        "aat:300008863"
    ]
},
  "bbox": [],
  "geometry": {"coordinates":[4.883333,49.9],"type":"Point"}
}
=======
{"geometry":{"type":"Point","coordinates":[4.883333,49.900000]},"type":"Feature","properties":{"hierarchy":["tgn:7247173","tgn:7003466","tgn:1000003","tgn:1000063","tgn:4012014","tgn:7029392"],"placetype":["aat:300008863"],"id":7247173,"name:xx":"Dame, Bois de la"}}
>>>>>>> 03f74aca74312dbeaf24d7e61306dd6a786dc3d0
