{
  "id": 7338247,
  "type": "Feature",
  "properties": {
    "tgn:hierarchy":[
        "tgn:7338247",
        "tgn:7002831",
        "tgn:1000003",
        "tgn:7002786",
        "tgn:1000095",
        "tgn:7029392"
    ],
    "tgn:id":7338247,
    "tgn:name":"Cea",
    "tgn:placetype":[
        "aat:300008347"
    ]
},
  "bbox": [],
  "geometry": {"coordinates":[-7.983333,42.466667],"type":"Point"}
}