{
  "id": 2669437,
  "type": "Feature",
  "properties": {
    "tgn:hierarchy":[
        "tgn:2669437",
        "tgn:1000001",
        "tgn:7006451",
        "tgn:2000092",
        "tgn:7012149",
        "tgn:7029392"
    ],
    "tgn:id":2669437,
    "tgn:name":"Slide Canyon",
    "tgn:placetype":[
        "aat:300008761"
    ]
},
  "bbox": [],
  "geometry": {"coordinates":[-112.35,36.5833],"type":"Point"}
}