<<<<<<< HEAD
{
  "id": 2338573,
  "type": "Feature",
  "properties": {
    "tgn:hierarchy":[
        "tgn:2338573",
        "tgn:1000001",
        "tgn:7012149",
        "tgn:2000383",
        "tgn:7007248",
        "tgn:7029392"
    ],
    "tgn:id":2338573,
    "tgn:name":"Frances Lake",
    "tgn:placetype":[
        "aat:300008680"
    ]
},
  "bbox": [],
  "geometry": {"coordinates":[-83.2,30.6667],"type":"Point"}
}
=======
{"geometry":{"type":"Point","coordinates":[-83.200000,30.666700]},"type":"Feature","properties":{"hierarchy":["tgn:2338573","tgn:1000001","tgn:7012149","tgn:2000383","tgn:7007248","tgn:7029392"],"placetype":["aat:300008680"],"id":2338573,"name:xx":"Frances Lake"}}
>>>>>>> 03f74aca74312dbeaf24d7e61306dd6a786dc3d0
