{
  "id": 2443428,
  "type": "Feature",
  "properties": {
    "tgn:hierarchy":[
        "tgn:2443428",
        "tgn:1000001",
        "tgn:7012149",
        "tgn:1002997",
        "tgn:7007826",
        "tgn:7029392"
    ],
    "tgn:id":2443428,
    "tgn:name":"La Bahia",
    "tgn:placetype":[
        "aat:300008347"
    ]
},
  "bbox": [],
  "geometry": {"coordinates":[-96.6333,30.1333],"type":"Point"}
}