{
  "id": 1011500,
  "type": "Feature",
  "properties": {
    "tgn:hierarchy":[
        "tgn:1011500",
        "tgn:7002443",
        "tgn:1000003",
        "tgn:7018993",
        "tgn:7008591",
        "tgn:7029392"
    ],
    "tgn:id":1011500,
    "tgn:name:en":"Saint Ann's Head",
    "tgn:placetype":[
        "aat:300387499",
        "aat:300386846"
    ]
},
  "bbox": [],
  "geometry": {"coordinates":[-5.173889,51.682778],"type":"Point"}
}