{
  "id": 7450544,
  "type": "Feature",
  "properties": {
    "tgn:hierarchy":[
        "tgn:7450544",
        "tgn:7002444",
        "tgn:1000003",
        "tgn:7008082",
        "tgn:7008591",
        "tgn:7029392"
    ],
    "tgn:id":7450544,
    "tgn:name:en":"Gheodha Dhuibh, Sr\u00f2n a'",
    "tgn:placetype":[
        "aat:300386846"
    ]
},
  "bbox": [],
  "geometry": {"coordinates":[-5.766667,57.866667],"type":"Point"}
}