{
  "id": 2783853,
  "type": "Feature",
  "properties": {
    "tgn:hierarchy":[
        "tgn:2783853",
        "tgn:1000001",
        "tgn:7012149",
        "tgn:2000806",
        "tgn:7007255",
        "tgn:7029392"
    ],
    "tgn:id":2783853,
    "tgn:name":"Wyrick Branch",
    "tgn:placetype":[
        "aat:300008699"
    ]
},
  "bbox": [],
  "geometry": {"coordinates":[-83.85,36.95],"type":"Point"}
}