{
  "id": 1087668,
  "type": "Feature",
  "properties": {
    "tgn:hierarchy":[
        "tgn:1087668",
        "tgn:7001242",
        "tgn:1000149",
        "tgn:7000392",
        "tgn:7029392"
    ],
    "tgn:id":1087668,
    "tgn:name":"Caitou",
    "tgn:placetype":[
        "aat:300008347"
    ]
},
  "bbox": [],
  "geometry": {"coordinates":[13.1167,-14.4667],"type":"Point"}
}