{
  "id": 2235954,
  "type": "Feature",
  "properties": {
    "tgn:hierarchy":[
        "tgn:2235954",
        "tgn:1000001",
        "tgn:7013649",
        "tgn:7012149",
        "tgn:7007251",
        "tgn:7029392"
    ],
    "tgn:id":2235954,
    "tgn:name":"Chevalier Woods",
    "tgn:placetype":[
        "aat:300132451"
    ]
},
  "bbox": [],
  "geometry": {"coordinates":[-87.8333,41.9667],"type":"Point"}
}