{
  "id": 2518272,
  "type": "Feature",
  "properties": {
    "tgn:hierarchy":[
        "tgn:2518272",
        "tgn:1000001",
        "tgn:7012149",
        "tgn:2000216",
        "tgn:7007158",
        "tgn:7029392"
    ],
    "tgn:id":2518272,
    "tgn:name":"Missouri Ditch",
    "tgn:placetype":[
        "aat:300006075"
    ]
},
  "bbox": [],
  "geometry": {"coordinates":[-106.3167,40.1833],"type":"Point"}
}