{
  "id": 2695527,
  "type": "Feature",
  "properties": {
    "tgn:hierarchy":[
        "tgn:2695527",
        "tgn:1000001",
        "tgn:7012149",
        "tgn:7007705",
        "tgn:7029392"
    ],
    "tgn:id":2695527,
    "tgn:name":"Stink Lake",
    "tgn:placetype":[
        "aat:300008680"
    ]
},
  "bbox": [],
  "geometry": {"coordinates":[-104.0167,48.6167],"type":"Point"}
}