{
  "id": 7533392,
  "type": "Feature",
  "properties": {
    "tgn:hierarchy":[
        "tgn:7533392",
        "tgn:7001242",
        "tgn:7001311",
        "tgn:7016833",
        "tgn:7029392"
    ],
    "tgn:id":7533392,
    "tgn:name:en":"Jabr\u0101w\u012b, W\u0101d\u012b al",
    "tgn:placetype":[
        "aat:300379998"
    ]
},
  "bbox": [],
  "geometry": {"coordinates":[31.077771,27.344026],"type":"Point"}
}