{
  "id": 2303601,
  "type": "Feature",
  "properties": {
    "tgn:hierarchy":[
        "tgn:2303601",
        "tgn:1000001",
        "tgn:7012149",
        "tgn:2000886",
        "tgn:7007256",
        "tgn:7029392"
    ],
    "tgn:id":2303601,
    "tgn:name":"Eagle Lake",
    "tgn:placetype":[
        "aat:300008680"
    ]
},
  "bbox": [],
  "geometry": {"coordinates":[-91.2333,32.4333],"type":"Point"}
}