{
  "id": 2104608,
  "type": "Feature",
  "properties": {
    "tgn:hierarchy":[
        "tgn:2104608",
        "tgn:1000001",
        "tgn:2001948",
        "tgn:7012149",
        "tgn:7007826",
        "tgn:7029392"
    ],
    "tgn:id":2104608,
    "tgn:name":"Grosvenor",
    "tgn:placetype":[
        "aat:300008347",
        "aat:300387210"
    ]
},
  "bbox": [],
  "geometry": {"coordinates":[-99.1333,31.8667],"type":"Point"}
}