{
  "id": 2422843,
  "type": "Feature",
  "properties": {
    "tgn:hierarchy":[
        "tgn:2422843",
        "tgn:1000001",
        "tgn:7012149",
        "tgn:1002943",
        "tgn:7007708",
        "tgn:7029392"
    ],
    "tgn:id":2422843,
    "tgn:name":"Joe Creek",
    "tgn:placetype":[
        "aat:300008706"
    ]
},
  "bbox": [],
  "geometry": {"coordinates":[-123.8333,45.3667],"type":"Point"}
}