{
  "id": 2166142,
  "type": "Feature",
  "properties": {
    "tgn:hierarchy":[
        "tgn:2166142",
        "tgn:1000001",
        "tgn:7012149",
        "tgn:2000512",
        "tgn:7007251",
        "tgn:7029392"
    ],
    "tgn:id":2166142,
    "tgn:name":"Big Bayou",
    "tgn:placetype":[
        "aat:300008699"
    ]
},
  "bbox": [],
  "geometry": {"coordinates":[-89.4333,37.6333],"type":"Point"}
}