{
  "id": 7486175,
  "type": "Feature",
  "properties": {
    "tgn:hierarchy":[
        "tgn:7486175",
        "tgn:7001010",
        "tgn:1000004",
        "tgn:1000141",
        "tgn:7029392"
    ],
    "tgn:id":7486175,
    "tgn:name":"Maxisang",
    "tgn:placetype":[
        "aat:300132356"
    ]
},
  "bbox": [],
  "geometry": {"coordinates":[121.144722,23.406944],"type":"Point"}
}