<<<<<<< HEAD
{
  "id": 7486175,
  "type": "Feature",
  "properties": {
    "tgn:hierarchy":[
        "tgn:7486175",
        "tgn:7001010",
        "tgn:1000004",
        "tgn:1000141",
        "tgn:7029392"
    ],
    "tgn:id":7486175,
    "tgn:name":"Maxisang",
    "tgn:placetype":[
        "aat:300132356"
    ]
},
  "bbox": [],
  "geometry": {"coordinates":[121.144722,23.406944],"type":"Point"}
}
=======
{"geometry":{"type":"Point","coordinates":[121.144722,23.406944]},"type":"Feature","properties":{"hierarchy":["tgn:7486175","tgn:7001010","tgn:1000004","tgn:1000141","tgn:7029392"],"placetype":["aat:300132356"],"id":7486175,"name:xx":"Maxisang"}}
>>>>>>> 03f74aca74312dbeaf24d7e61306dd6a786dc3d0
