<<<<<<< HEAD
{
  "id": 2761365,
  "type": "Feature",
  "properties": {
    "tgn:hierarchy":[
        "tgn:2761365",
        "tgn:1000001",
        "tgn:7012149",
        "tgn:2002342",
        "tgn:7007922",
        "tgn:7029392"
    ],
    "tgn:id":2761365,
    "tgn:name":"West Mitchell Lake",
    "tgn:placetype":[
        "aat:300008680"
    ]
},
  "bbox": [],
  "geometry": {"coordinates":[-89.7,45.65],"type":"Point"}
}
=======
{"geometry":{"type":"Point","coordinates":[-89.700000,45.650000]},"type":"Feature","properties":{"hierarchy":["tgn:2761365","tgn:1000001","tgn:7012149","tgn:2002342","tgn:7007922","tgn:7029392"],"placetype":["aat:300008680"],"id":2761365,"name:xx":"West Mitchell Lake"}}
>>>>>>> 03f74aca74312dbeaf24d7e61306dd6a786dc3d0
