{
  "id": 7373485,
  "type": "Feature",
  "properties": {
    "tgn:hierarchy":[
        "tgn:7373485",
        "tgn:1000001",
        "tgn:7005600",
        "tgn:7005560",
        "tgn:7029392"
    ],
    "tgn:id":7373485,
    "tgn:name":"Lagartos, R\u00edo",
    "tgn:placetype":[
        "aat:300008713"
    ]
},
  "bbox": [],
  "geometry": {"coordinates":[-88.233333,21.583333],"type":"Point"}
}