{
  "id": 2387774,
  "type": "Feature",
  "properties": {
    "tgn:hierarchy":[
        "tgn:2387774",
        "tgn:1000001",
        "tgn:7014352",
        "tgn:7012149",
        "tgn:7007564",
        "tgn:7029392"
    ],
    "tgn:id":2387774,
    "tgn:name":"Hickey Hill",
    "tgn:placetype":[
        "aat:300008798"
    ]
},
  "bbox": [],
  "geometry": {"coordinates":[-70.95,43.0333],"type":"Point"}
}