{
  "id": 7265842,
  "type": "Feature",
  "properties": {
    "tgn:hierarchy":[
        "tgn:7265842",
        "tgn:7003619",
        "tgn:1000003",
        "tgn:7016845",
        "tgn:7029392"
    ],
    "tgn:id":7265842,
    "tgn:name:nl":"Indoornikse Brug",
    "tgn:placetype":[
        "aat:300007836"
    ]
},
  "bbox": [],
  "geometry": {"coordinates":[5.716667,51.933333],"type":"Point"}
}