{
  "id": 7540312,
  "type": "Feature",
  "properties": {
    "tgn:hierarchy":[
        "tgn:7540312",
        "tgn:7001242",
        "tgn:7001105",
        "tgn:7016833",
        "tgn:7029392"
    ],
    "tgn:id":7540312,
    "tgn:name:en":"Naj' al \u1e28ajar, \u1e28amr\u0101yat",
    "tgn:placetype":[
        "aat:300008916"
    ]
},
  "bbox": [],
  "geometry": {"coordinates":[30.65,29.133333],"type":"Point"}
}