{
  "id": 7506897,
  "type": "Feature",
  "properties": {
    "tgn:hierarchy":[
        "tgn:7506897",
        "tgn:7000508",
        "tgn:1008380",
        "tgn:1000226",
        "tgn:1000006",
        "tgn:7029392"
    ],
    "tgn:id":7506897,
    "tgn:name:en":"Rangiwhakaea Bay",
    "tgn:placetype":[
        "aat:300132316"
    ]
},
  "bbox": [],
  "geometry": {"coordinates":[175.416667,-36.083333],"type":"Point"}
}