<<<<<<< HEAD
{
  "id": 2158244,
  "type": "Feature",
  "properties": {
    "tgn:hierarchy":[
        "tgn:2158244",
        "tgn:1000001",
        "tgn:7012149",
        "tgn:1002520",
        "tgn:7007710",
        "tgn:7029392"
    ],
    "tgn:id":2158244,
    "tgn:name":"Beaver Run",
    "tgn:placetype":[
        "aat:300008699"
    ]
},
  "bbox": [],
  "geometry": {"coordinates":[-78.9333,41.2],"type":"Point"}
}
=======
{"geometry":{"type":"Point","coordinates":[-78.933300,41.200000]},"type":"Feature","properties":{"hierarchy":["tgn:2158244","tgn:1000001","tgn:7012149","tgn:1002520","tgn:7007710","tgn:7029392"],"placetype":["aat:300008699"],"id":2158244,"name:xx":"Beaver Run"}}
>>>>>>> 03f74aca74312dbeaf24d7e61306dd6a786dc3d0
