{
  "id": 2273348,
  "type": "Feature",
  "properties": {
    "tgn:hierarchy":[
        "tgn:2273348",
        "tgn:1000001",
        "tgn:2001471",
        "tgn:7012149",
        "tgn:7007709",
        "tgn:7029392"
    ],
    "tgn:id":2273348,
    "tgn:name":"Cypress Creek",
    "tgn:placetype":[
        "aat:300008706"
    ]
},
  "bbox": [],
  "geometry": {"coordinates":[-78.5167,34.7833],"type":"Point"}
}