{
  "id": 7220904,
  "type": "Feature",
  "properties": {
    "tgn:hierarchy":[
        "tgn:7220904",
        "tgn:7002715",
        "tgn:7002729",
        "tgn:1000003",
        "tgn:1000074",
        "tgn:7029392"
    ],
    "tgn:id":7220904,
    "tgn:name":"T\u00f3xon",
    "tgn:placetype":[
        "aat:300008347"
    ]
},
  "bbox": [],
  "geometry": {"coordinates":[22.392222,40.34],"type":"Point"}
}