{
  "id": 2633590,
  "type": "Feature",
  "properties": {
    "tgn:hierarchy":[
        "tgn:2633590",
        "tgn:1000001",
        "tgn:7012149",
        "tgn:2001420",
        "tgn:7007526",
        "tgn:7029392"
    ],
    "tgn:id":2633590,
    "tgn:name":"Ruppes Place",
    "tgn:placetype":[
        "aat:300008347"
    ]
},
  "bbox": [],
  "geometry": {"coordinates":[-115.05,38.75],"type":"Point"}
}