<<<<<<< HEAD
{
  "id": 2257944,
  "type": "Feature",
  "properties": {
    "tgn:hierarchy":[
        "tgn:2257944",
        "tgn:1000001",
        "tgn:1002340",
        "tgn:7012149",
        "tgn:7007526",
        "tgn:7029392"
    ],
    "tgn:id":2257944,
    "tgn:name":"Corsser Creek",
    "tgn:placetype":[
        "aat:300008706"
    ]
},
  "bbox": [],
  "geometry": {"coordinates":[-119.8667,38.95],"type":"Point"}
}
=======
{"geometry":{"type":"Point","coordinates":[-119.866700,38.950000]},"type":"Feature","properties":{"hierarchy":["tgn:2257944","tgn:1000001","tgn:1002340","tgn:7012149","tgn:7007526","tgn:7029392"],"placetype":["aat:300008706"],"id":2257944,"name:xx":"Corsser Creek"}}
>>>>>>> 03f74aca74312dbeaf24d7e61306dd6a786dc3d0
