{
  "id": 2752878,
  "type": "Feature",
  "properties": {
    "tgn:hierarchy":[
        "tgn:2752878",
        "tgn:1000001",
        "tgn:1002340",
        "tgn:7012149",
        "tgn:7007526",
        "tgn:7029392"
    ],
    "tgn:id":2752878,
    "tgn:name":"Water Canyon",
    "tgn:placetype":[
        "aat:300008761"
    ]
},
  "bbox": [],
  "geometry": {"coordinates":[-119.8667,39.0667],"type":"Point"}
}