{
  "id": 2518388,
  "type": "Feature",
  "properties": {
    "tgn:hierarchy":[
        "tgn:2518388",
        "tgn:1000001",
        "tgn:7012149",
        "tgn:7007826",
        "tgn:7029392"
    ],
    "tgn:id":2518388,
    "tgn:name":"Mitcham Branch",
    "tgn:placetype":[
        "aat:300008699"
    ]
},
  "bbox": [],
  "geometry": {"coordinates":[-95.8667,33.0333],"type":"Point"}
}