{
  "id": 2583497,
  "type": "Feature",
  "properties": {
    "tgn:hierarchy":[
        "tgn:2583497",
        "tgn:1000001",
        "tgn:7012149",
        "tgn:1002986",
        "tgn:7007568",
        "tgn:7029392"
    ],
    "tgn:id":2583497,
    "tgn:name":"Pine Ridge",
    "tgn:placetype":[
        "aat:300266640"
    ]
},
  "bbox": [],
  "geometry": {"coordinates":[-73.9667,43.5333],"type":"Point"}
}