{
  "id": 7352521,
  "type": "Feature",
  "properties": {
    "tgn:hierarchy":[
        "tgn:7352521",
        "tgn:7005581",
        "tgn:1000001",
        "tgn:7005560",
        "tgn:7029392"
    ],
    "tgn:id":7352521,
    "tgn:name":"Basaseachic",
    "tgn:placetype":[
        "aat:300008347"
    ]
},
  "bbox": [],
  "geometry": {"coordinates":[-108.233333,28.216667],"type":"Point"}
}