{
  "id": 2180787,
  "type": "Feature",
  "properties": {
    "tgn:hierarchy":[
        "tgn:2180787",
        "tgn:1000001",
        "tgn:7012149",
        "tgn:2000393",
        "tgn:7007248",
        "tgn:7029392"
    ],
    "tgn:id":2180787,
    "tgn:name":"Blount",
    "tgn:placetype":[
        "aat:300008347"
    ]
},
  "bbox": [],
  "geometry": {"coordinates":[-83.95,33.1667],"type":"Point"}
}