{
  "id": 7589056,
  "type": "Feature",
  "properties": {
    "tgn:hierarchy":[
        "tgn:7589056",
        "tgn:1000004",
        "tgn:1001869",
        "tgn:7000198",
        "tgn:7029392"
    ],
    "tgn:id":7589056,
    "tgn:name:en":"Damr\u0101la",
    "tgn:placetype":[
        "aat:300008347"
    ]
},
  "bbox": [],
  "geometry": {"coordinates":[70.913567,21.550796],"type":"Point"}
}