{
  "id": 2175365,
  "type": "Feature",
  "properties": {
    "tgn:hierarchy":[
        "tgn:2175365",
        "tgn:1000001",
        "tgn:2001417",
        "tgn:7012149",
        "tgn:7007526",
        "tgn:7029392"
    ],
    "tgn:id":2175365,
    "tgn:name":"Black Butte Mine",
    "tgn:placetype":[
        "aat:300000390"
    ]
},
  "bbox": [],
  "geometry": {"coordinates":[-118.15,38.4333],"type":"Point"}
}