{
  "id": 2372593,
  "type": "Feature",
  "properties": {
    "tgn:hierarchy":[
        "tgn:2372593",
        "tgn:1000001",
        "tgn:7016172",
        "tgn:7012149",
        "tgn:2000124",
        "tgn:7029392"
    ],
    "tgn:id":2372593,
    "tgn:name":"Hall Creek",
    "tgn:placetype":[
        "aat:300008706"
    ]
},
  "bbox": [],
  "geometry": {"coordinates":[-92.6667,34.0333],"type":"Point"}
}