{
  "id": 2591641,
  "type": "Feature",
  "properties": {
    "tgn:hierarchy":[
        "tgn:2591641",
        "tgn:1000001",
        "tgn:7012149",
        "tgn:7007568",
        "tgn:7029392"
    ],
    "tgn:id":2591641,
    "tgn:name":"Pond Brook",
    "tgn:placetype":[
        "aat:300008699"
    ]
},
  "bbox": [],
  "geometry": {"coordinates":[-75.8667,42.45],"type":"Point"}
}