{
  "id": 2241730,
  "type": "Feature",
  "properties": {
    "tgn:hierarchy":[
        "tgn:2241730",
        "tgn:1002716",
        "tgn:1000001",
        "tgn:7012149",
        "tgn:7007711",
        "tgn:7029392"
    ],
    "tgn:id":2241730,
    "tgn:name":"Clarks Village",
    "tgn:placetype":[
        "aat:300008347"
    ]
},
  "bbox": [],
  "geometry": {"coordinates":[-71.3833,41.45],"type":"Point"}
}