{
  "id": 2119842,
  "type": "Feature",
  "properties": {
    "tgn:hierarchy":[
        "tgn:2119842",
        "tgn:1000001",
        "tgn:7012149",
        "tgn:2002301",
        "tgn:7013961",
        "tgn:7029392"
    ],
    "tgn:id":2119842,
    "tgn:name":"Round Bottom",
    "tgn:placetype":[
        "aat:300008347",
        "aat:300387210"
    ]
},
  "bbox": [],
  "geometry": {"coordinates":[-80.4333,39.6833],"type":"Point"}
}