{
  "id": 2513533,
  "type": "Feature",
  "properties": {
    "tgn:hierarchy":[
        "tgn:2513533",
        "tgn:1002716",
        "tgn:1000001",
        "tgn:7012149",
        "tgn:7007711",
        "tgn:7029392"
    ],
    "tgn:id":2513533,
    "tgn:name":"Mill Point",
    "tgn:placetype":[
        "aat:300008850"
    ]
},
  "bbox": [],
  "geometry": {"coordinates":[-71.1667,41.45],"type":"Point"}
}