{
  "id": 2220036,
  "type": "Feature",
  "properties": {
    "tgn:hierarchy":[
        "tgn:2220036",
        "tgn:1000001",
        "tgn:7012149",
        "tgn:2001990",
        "tgn:7007826",
        "tgn:7029392"
    ],
    "tgn:id":2220036,
    "tgn:name":"Canyon Creek",
    "tgn:placetype":[
        "aat:300008706"
    ]
},
  "bbox": [],
  "geometry": {"coordinates":[-99.0167,30.3333],"type":"Point"}
}