{
  "id": 2215224,
  "type": "Feature",
  "properties": {
    "tgn:hierarchy":[
        "tgn:2215224",
        "tgn:1000001",
        "tgn:7012149",
        "tgn:2001288",
        "tgn:7007524",
        "tgn:7029392"
    ],
    "tgn:id":2215224,
    "tgn:name":"Call Road Reservoir",
    "tgn:placetype":[
        "aat:300006191"
    ]
},
  "bbox": [],
  "geometry": {"coordinates":[-111.85,45.1333],"type":"Point"}
}