{
  "id": 2158351,
  "type": "Feature",
  "properties": {
    "tgn:hierarchy":[
        "tgn:2158351",
        "tgn:1000001",
        "tgn:7012149",
        "tgn:7029392"
    ],
    "tgn:id":2158351,
    "tgn:name":"Beaverdam Branch",
    "tgn:placetype":[
        "aat:300008699"
    ]
},
  "bbox": [],
  "geometry": {"coordinates":[-85.0667,31.5333],"type":"Point"}
}