<<<<<<< HEAD
{
  "id": 2158351,
  "type": "Feature",
  "properties": {
    "tgn:hierarchy":[
        "tgn:2158351",
        "tgn:1000001",
        "tgn:7012149",
        "tgn:7029392"
    ],
    "tgn:id":2158351,
    "tgn:name":"Beaverdam Branch",
    "tgn:placetype":[
        "aat:300008699"
    ]
},
  "bbox": [],
  "geometry": {"coordinates":[-85.0667,31.5333],"type":"Point"}
}
=======
{"geometry":{"type":"Point","coordinates":[-85.066700,31.533300]},"type":"Feature","properties":{"hierarchy":["tgn:2158351","tgn:1000001","tgn:7012149","tgn:7029392"],"placetype":["aat:300008699"],"id":2158351,"name:xx":"Beaverdam Branch"}}
>>>>>>> 03f74aca74312dbeaf24d7e61306dd6a786dc3d0
