{
  "id": 1140743,
  "type": "Feature",
  "properties": {
    "tgn:hierarchy":[
        "tgn:1140743",
        "tgn:1000004",
        "tgn:1001178",
        "tgn:1000135",
        "tgn:7029392"
    ],
    "tgn:id":1140743,
    "tgn:name":"Pilar",
    "tgn:placetype":[
        "aat:300008347"
    ]
},
  "bbox": [],
  "geometry": {"coordinates":[126.1167,9.85],"type":"Point"}
}