{
  "id": 7301900,
  "type": "Feature",
  "properties": {
    "tgn:hierarchy":[
        "tgn:7301900",
        "tgn:7002811",
        "tgn:1000003",
        "tgn:7003837",
        "tgn:1000095",
        "tgn:7029392"
    ],
    "tgn:id":7301900,
    "tgn:name":"Mej\u00edas, Puerto",
    "tgn:placetype":[
        "aat:300259572"
    ]
},
  "bbox": [],
  "geometry": {"coordinates":[-6.566667,39.333333],"type":"Point"}
}