{
  "id": 7495030,
  "type": "Feature",
  "properties": {
    "tgn:hierarchy":[
        "tgn:7495030",
        "tgn:1000004",
        "tgn:7467799",
        "tgn:1000141",
        "tgn:7029392"
    ],
    "tgn:id":7495030,
    "tgn:name":"Nanping",
    "tgn:placetype":[
        "aat:300000745"
    ]
},
  "bbox": [],
  "geometry": {"coordinates":[120.567551,23.965949],"type":"Point"}
}