<<<<<<< HEAD
{
  "id": 2256761,
  "type": "Feature",
  "properties": {
    "tgn:hierarchy":[
        "tgn:2256761",
        "tgn:1000001",
        "tgn:7012149",
        "tgn:2000911",
        "tgn:7007256",
        "tgn:7029392"
    ],
    "tgn:id":2256761,
    "tgn:name":"Corey Branch",
    "tgn:placetype":[
        "aat:300008699"
    ]
},
  "bbox": [],
  "geometry": {"coordinates":[-93.5167,31.1167],"type":"Point"}
}
=======
{"geometry":{"type":"Point","coordinates":[-93.516700,31.116700]},"type":"Feature","properties":{"hierarchy":["tgn:2256761","tgn:1000001","tgn:7012149","tgn:2000911","tgn:7007256","tgn:7029392"],"placetype":["aat:300008699"],"id":2256761,"name:xx":"Corey Branch"}}
>>>>>>> 03f74aca74312dbeaf24d7e61306dd6a786dc3d0
