{
  "id": 1095597,
  "type": "Feature",
  "properties": {
    "tgn:hierarchy":[
        "tgn:1095597",
        "tgn:7001242",
        "tgn:7016833",
        "tgn:1001113",
        "tgn:7029392"
    ],
    "tgn:id":1095597,
    "tgn:name:en":"Masht\u016bl as S\u016bq",
    "tgn:placetype":[
        "aat:300008347"
    ]
},
  "bbox": [],
  "geometry": {"coordinates":[31.377604,30.360563],"type":"Point"}
}