{
  "id": 7382166,
  "type": "Feature",
  "properties": {
    "tgn:hierarchy":[
        "tgn:7382166",
        "tgn:1000001",
        "tgn:7005589",
        "tgn:7005560",
        "tgn:7029392"
    ],
    "tgn:id":7382166,
    "tgn:name":"Monterrey, R\u00edo de",
    "tgn:placetype":[
        "aat:300008699"
    ]
},
  "bbox": [],
  "geometry": {"coordinates":[-99.533333,25.483333],"type":"Point"}
}