{
  "id": 7424024,
  "type": "Feature",
  "properties": {
    "tgn:hierarchy":[
        "tgn:7424024",
        "tgn:1000001",
        "tgn:1001960",
        "tgn:7005560",
        "tgn:7029392"
    ],
    "tgn:id":7424024,
    "tgn:name":"Los Pesados",
    "tgn:placetype":[
        "aat:300008347"
    ]
},
  "bbox": [],
  "geometry": {"coordinates":[-108.983333,29.483333],"type":"Point"}
}