{
  "id": 2453184,
  "type": "Feature",
  "properties": {
    "tgn:hierarchy":[
        "tgn:2453184",
        "tgn:1000001",
        "tgn:7012149",
        "tgn:7007157",
        "tgn:1002863",
        "tgn:7029392"
    ],
    "tgn:id":2453184,
    "tgn:name":"Little Cayucos Creek",
    "tgn:placetype":[
        "aat:300008706"
    ]
},
  "bbox": [],
  "geometry": {"coordinates":[-120.8833,35.4833],"type":"Point"}
}