{
  "id": 7239776,
  "type": "Feature",
  "properties": {
    "tgn:hierarchy":[
        "tgn:7239776",
        "tgn:7003456",
        "tgn:1000003",
        "tgn:1000063",
        "tgn:7018236",
        "tgn:7029392"
    ],
    "tgn:id":7239776,
    "tgn:name":"Heikant",
    "tgn:placetype":[
        "aat:300008347"
    ]
},
  "bbox": [],
  "geometry": {"coordinates":[4.207337,51.063934],"type":"Point"}
}