{
  "id": 2182355,
  "type": "Feature",
  "properties": {
    "tgn:hierarchy":[
        "tgn:2182355",
        "tgn:1000001",
        "tgn:7012149",
        "tgn:2001715",
        "tgn:7007708",
        "tgn:7029392"
    ],
    "tgn:id":2182355,
    "tgn:name":"Blue Reservoir",
    "tgn:placetype":[
        "aat:300006191"
    ]
},
  "bbox": [],
  "geometry": {"coordinates":[-120.6667,43.1333],"type":"Point"}
}