<<<<<<< HEAD
{
  "id": 2331840,
  "type": "Feature",
  "properties": {
    "tgn:hierarchy":[
        "tgn:2331840",
        "tgn:7002659",
        "tgn:1000001",
        "tgn:7012149",
        "tgn:7029392"
    ],
    "tgn:id":2331840,
    "tgn:name":"Fletcher Creek",
    "tgn:placetype":[
        "aat:300008706"
    ]
},
  "bbox": [],
  "geometry": {"coordinates":[-87.6167,31.1167],"type":"Point"}
}
=======
{"geometry":{"type":"Point","coordinates":[-87.616700,31.116700]},"type":"Feature","properties":{"hierarchy":["tgn:2331840","tgn:7002659","tgn:1000001","tgn:7012149","tgn:7029392"],"placetype":["aat:300008706"],"id":2331840,"name:xx":"Fletcher Creek"}}
>>>>>>> 03f74aca74312dbeaf24d7e61306dd6a786dc3d0
