{
  "id": 2186991,
  "type": "Feature",
  "properties": {
    "tgn:hierarchy":[
        "tgn:2186991",
        "tgn:1000001",
        "tgn:7012149",
        "tgn:2002118",
        "tgn:7007827",
        "tgn:7029392"
    ],
    "tgn:id":2186991,
    "tgn:name":"Bonneville Acres",
    "tgn:placetype":[
        "aat:300008347"
    ]
},
  "bbox": [],
  "geometry": {"coordinates":[-112.0667,40.6833],"type":"Point"}
}