{
  "id": 1118914,
  "type": "Feature",
  "properties": {
    "tgn:hierarchy":[
        "tgn:1118914",
        "tgn:7001242",
        "tgn:7016752",
        "tgn:1000769",
        "tgn:7029392"
    ],
    "tgn:id":1118914,
    "tgn:name":"Be\u00efda, Chott",
    "tgn:placetype":[
        "aat:300266556"
    ]
},
  "bbox": [],
  "geometry": {"coordinates":[5.807,35.926],"type":"Point"}
}