{
  "id": 2525939,
  "type": "Feature",
  "properties": {
    "tgn:hierarchy":[
        "tgn:2525939",
        "tgn:1000001",
        "tgn:7012149",
        "tgn:2002336",
        "tgn:7007922",
        "tgn:7029392"
    ],
    "tgn:id":2525939,
    "tgn:name":"Mosinee Flowage",
    "tgn:placetype":[
        "aat:300006191"
    ]
},
  "bbox": [],
  "geometry": {"coordinates":[-89.6833,44.7833],"type":"Point"}
}