{
  "id": 1132637,
  "type": "Feature",
  "properties": {
    "tgn:hierarchy":[
        "tgn:1132637",
        "tgn:7005685",
        "tgn:1000001",
        "tgn:7013154",
        "tgn:7029392"
    ],
    "tgn:id":1132637,
    "tgn:name":"Burnley Creek",
    "tgn:placetype":[
        "aat:300008706"
    ]
},
  "bbox": [],
  "geometry": {"coordinates":[-77.85,44.2167],"type":"Point"}
}