{
  "id": 2684021,
  "type": "Feature",
  "properties": {
    "tgn:hierarchy":[
        "tgn:2684021",
        "tgn:1000001",
        "tgn:7012149",
        "tgn:2000836",
        "tgn:7007255",
        "tgn:7029392"
    ],
    "tgn:id":2684021,
    "tgn:name":"Spencer Creek",
    "tgn:placetype":[
        "aat:300008706"
    ]
},
  "bbox": [],
  "geometry": {"coordinates":[-83.3167,37.3333],"type":"Point"}
}