{
  "id": 7415081,
  "type": "Feature",
  "properties": {
    "tgn:hierarchy":[
        "tgn:7415081",
        "tgn:1000001",
        "tgn:7005591",
        "tgn:7005560",
        "tgn:7029392"
    ],
    "tgn:id":7415081,
    "tgn:name:es":"Santa Luc\u00eda Sosola",
    "tgn:placetype":[
        "aat:300008347"
    ]
},
  "bbox": [],
  "geometry": {"coordinates":[-97.068611,17.430556],"type":"Point"}
}