{
  "id": 7230032,
  "type": "Feature",
  "properties": {
    "tgn:hierarchy":[
        "tgn:7230032",
        "tgn:1042193",
        "tgn:7002705",
        "tgn:1000003",
        "tgn:1000074",
        "tgn:7029392"
    ],
    "tgn:id":7230032,
    "tgn:name":"L\u00e1kkaza",
    "tgn:placetype":[
        "aat:300008777"
    ]
},
  "bbox": [],
  "geometry": {"coordinates":[20.633333,39.216667],"type":"Point"}
}