{
  "id": 2568979,
  "type": "Feature",
  "properties": {
    "tgn:hierarchy":[
        "tgn:2568979",
        "tgn:1000001",
        "tgn:7012149",
        "tgn:1002935",
        "tgn:7007919",
        "tgn:7029392"
    ],
    "tgn:id":2568979,
    "tgn:name":"Parker Number Two Pond",
    "tgn:placetype":[
        "aat:300006191"
    ]
},
  "bbox": [],
  "geometry": {"coordinates":[-76.9833,36.95],"type":"Point"}
}