{
  "id": 2356320,
  "type": "Feature",
  "properties": {
    "tgn:hierarchy":[
        "tgn:2356320",
        "tgn:1000001",
        "tgn:7012149",
        "tgn:1002631",
        "tgn:7007240",
        "tgn:7029392"
    ],
    "tgn:id":2356320,
    "tgn:name":"Gooski Prairie",
    "tgn:placetype":[
        "aat:300008905"
    ]
},
  "bbox": [],
  "geometry": {"coordinates":[-82.05,29.3333],"type":"Point"}
}