{
  "id": 7292847,
  "type": "Feature",
  "properties": {
    "tgn:hierarchy":[
        "tgn:7292847",
        "tgn:1001768",
        "tgn:1000049",
        "tgn:1000002",
        "tgn:7029392"
    ],
    "tgn:id":7292847,
    "tgn:name":"El Morado, Cerro",
    "tgn:placetype":[
        "aat:300008795"
    ]
},
  "bbox": [],
  "geometry": {"coordinates":[-71.016667,-32.55],"type":"Point"}
}