{
  "id": 7112651,
  "type": "Feature",
  "properties": {
    "tgn:hierarchy":[
        "tgn:7112651",
        "tgn:7003669",
        "tgn:1000003",
        "tgn:7000084",
        "tgn:7029392"
    ],
    "tgn:id":7112651,
    "tgn:name":"Rosen-Weiher",
    "tgn:placetype":[
        "aat:300008680"
    ]
},
  "bbox": [],
  "geometry": {"coordinates":[10.85,49.533333],"type":"Point"}
}