{
  "id": 2605854,
  "type": "Feature",
  "properties": {
    "tgn:hierarchy":[
        "tgn:2605854",
        "tgn:1000001",
        "tgn:7012149",
        "tgn:2000226",
        "tgn:7007158",
        "tgn:7029392"
    ],
    "tgn:id":2605854,
    "tgn:name":"Rainbow Lake",
    "tgn:placetype":[
        "aat:300006191"
    ]
},
  "bbox": [],
  "geometry": {"coordinates":[-105.4167,40.25],"type":"Point"}
}