{
  "id": 7509944,
  "type": "Feature",
  "properties": {
    "tgn:hierarchy":[
        "tgn:7509944",
        "tgn:7000509",
        "tgn:1008380",
        "tgn:1000226",
        "tgn:1000006",
        "tgn:7029392"
    ],
    "tgn:id":7509944,
    "tgn:name:en":"Te Puhikoko",
    "tgn:placetype":[
        "aat:300008795"
    ]
},
  "bbox": [],
  "geometry": {"coordinates":[177.016667,-38.016667],"type":"Point"}
}