{
  "id": 2625831,
  "type": "Feature",
  "properties": {
    "tgn:hierarchy":[
        "tgn:2625831",
        "tgn:1000001",
        "tgn:7012149",
        "tgn:7007564",
        "tgn:7029392"
    ],
    "tgn:id":2625831,
    "tgn:name":"Rocky Branch",
    "tgn:placetype":[
        "aat:300008699"
    ]
},
  "bbox": [],
  "geometry": {"coordinates":[-71.2833,44.2333],"type":"Point"}
}