{
  "id": 1097928,
  "type": "Feature",
  "properties": {
    "tgn:hierarchy":[
        "tgn:1097928",
        "tgn:7000490",
        "tgn:1000006",
        "tgn:7001834",
        "tgn:7029392"
    ],
    "tgn:id":1097928,
    "tgn:name":"Pemberton",
    "tgn:placetype":[
        "aat:300008347"
    ]
},
  "bbox": [],
  "geometry": {"coordinates":[155.9833,-34.45],"type":"Point"}
}