{
  "id": 7461337,
  "type": "Feature",
  "properties": {
    "tgn:hierarchy":[
        "tgn:7461337",
        "tgn:7019030",
        "tgn:7002445",
        "tgn:1000003",
        "tgn:7029506",
        "tgn:7008591",
        "tgn:7029392"
    ],
    "tgn:id":7461337,
    "tgn:name:en":"Himley",
    "tgn:placetype":[
        "aat:300008347"
    ]
},
  "bbox": [],
  "geometry": {"coordinates":[-2.15,52.516667],"type":"Point"}
}