{
  "id": 2602135,
  "type": "Feature",
  "properties": {
    "tgn:hierarchy":[
        "tgn:2602135",
        "tgn:7023902",
        "tgn:1000001",
        "tgn:7012149",
        "tgn:7007249",
        "tgn:7029392"
    ],
    "tgn:id":2602135,
    "tgn:name":"Puu Ulaulua",
    "tgn:placetype":[
        "aat:300008798"
    ]
},
  "bbox": [],
  "geometry": {"coordinates":[-155.3667,19.8167],"type":"Point"}
}