{
  "id": 2458777,
  "type": "Feature",
  "properties": {
    "tgn:hierarchy":[
        "tgn:2458777",
        "tgn:1000001",
        "tgn:7012149",
        "tgn:7007710",
        "tgn:7029392"
    ],
    "tgn:id":2458777,
    "tgn:name":"Little Paint Creek",
    "tgn:placetype":[
        "aat:300008706"
    ]
},
  "bbox": [],
  "geometry": {"coordinates":[-78.75,40.25],"type":"Point"}
}