{
  "id": 7534515,
  "type": "Feature",
  "properties": {
    "tgn:hierarchy":[
        "tgn:7534515",
        "tgn:7001242",
        "tgn:7001311",
        "tgn:7016833",
        "tgn:7029392"
    ],
    "tgn:id":7534515,
    "tgn:name:en":"Jund\u012b, Jabal al",
    "tgn:placetype":[
        "aat:300008795"
    ]
},
  "bbox": [],
  "geometry": {"coordinates":[33.947824,25.477551],"type":"Point"}
}