{
  "id": 4008048,
  "type": "Feature",
  "properties": {
    "tgn:hierarchy":[
        "tgn:4008048",
        "tgn:7010420",
        "tgn:1000003",
        "tgn:7002795",
        "tgn:1000095",
        "tgn:7029392"
    ],
    "tgn:id":4008048,
    "tgn:name":"Nuevo Bazt\u00e1n",
    "tgn:placetype":[
        "aat:300008347"
    ]
},
  "bbox": [],
  "geometry": {"coordinates":[-3.25,40.366667],"type":"Point"}
}