<<<<<<< HEAD
{
  "id": 7050530,
  "type": "Feature",
  "properties": {
    "tgn:hierarchy":[
        "tgn:7050530",
        "tgn:7003006",
        "tgn:1000003",
        "tgn:7002997",
        "tgn:1000080",
        "tgn:7029392"
    ],
    "tgn:id":7050530,
    "tgn:name":"Canale Largon",
    "tgn:placetype":[
        "aat:300006075"
    ]
},
  "bbox": [],
  "geometry": {"coordinates":[12.816667,45.6],"type":"Point"}
}
=======
{"geometry":{"type":"Point","coordinates":[12.816667,45.600000]},"type":"Feature","properties":{"hierarchy":["tgn:7050530","tgn:7003006","tgn:1000003","tgn:7002997","tgn:1000080","tgn:7029392"],"placetype":["aat:300006075"],"id":7050530,"name:xx":"Canale Largon"}}
>>>>>>> 03f74aca74312dbeaf24d7e61306dd6a786dc3d0
