{
  "id": 2289261,
  "type": "Feature",
  "properties": {
    "tgn:hierarchy":[
        "tgn:2289261",
        "tgn:1000001",
        "tgn:2002102",
        "tgn:7012149",
        "tgn:7007827",
        "tgn:7029392"
    ],
    "tgn:id":2289261,
    "tgn:name":"Division Lake",
    "tgn:placetype":[
        "aat:300006191"
    ]
},
  "bbox": [],
  "geometry": {"coordinates":[-112.2833,41.6167],"type":"Point"}
}