<<<<<<< HEAD
{
  "id": 7371900,
  "type": "Feature",
  "properties": {
    "tgn:hierarchy":[
        "tgn:7371900",
        "tgn:7005583",
        "tgn:1000001",
        "tgn:7005560",
        "tgn:7029392"
    ],
    "tgn:id":7371900,
    "tgn:name":"La Campana",
    "tgn:placetype":[
        "aat:300008347"
    ]
},
  "bbox": [],
  "geometry": {"coordinates":[-106.216667,24.533333],"type":"Point"}
}
=======
{"geometry":{"type":"Point","coordinates":[-106.216667,24.533333]},"type":"Feature","properties":{"hierarchy":["tgn:7371900","tgn:7005583","tgn:1000001","tgn:7005560","tgn:7029392"],"placetype":["aat:300008347"],"id":7371900,"name:xx":"La Campana"}}
>>>>>>> 03f74aca74312dbeaf24d7e61306dd6a786dc3d0
