{
  "id": 7496826,
  "type": "Feature",
  "properties": {
    "tgn:hierarchy":[
        "tgn:7496826",
        "tgn:1000004",
        "tgn:1000959",
        "tgn:1000141",
        "tgn:7029392"
    ],
    "tgn:id":7496826,
    "tgn:name":"Maishuai Yi Qiao",
    "tgn:placetype":[
        "aat:300007836"
    ]
},
  "bbox": [],
  "geometry": {"coordinates":[121.571837,25.051778],"type":"Point"}
}