{
  "id": 2160767,
  "type": "Feature",
  "properties": {
    "tgn:hierarchy":[
        "tgn:2160767",
        "tgn:1000001",
        "tgn:1002461",
        "tgn:7012149",
        "tgn:7007159",
        "tgn:7029392"
    ],
    "tgn:id":2160767,
    "tgn:name":"Belden Brook",
    "tgn:placetype":[
        "aat:300008699"
    ]
},
  "bbox": [],
  "geometry": {"coordinates":[-72.8833,42.0167],"type":"Point"}
}