{
  "id": 7393641,
  "type": "Feature",
  "properties": {
    "tgn:hierarchy":[
        "tgn:7393641",
        "tgn:1000001",
        "tgn:7005600",
        "tgn:7005560",
        "tgn:7029392"
    ],
    "tgn:id":7393641,
    "tgn:name":"San Jos\u00e9",
    "tgn:placetype":[
        "aat:300008347"
    ]
},
  "bbox": [],
  "geometry": {"coordinates":[-87.966667,21.35],"type":"Point"}
}