{
  "id": 7531268,
  "type": "Feature",
  "properties": {
    "tgn:hierarchy":[
        "tgn:7531268",
        "tgn:7001242",
        "tgn:7016833",
        "tgn:7029392"
    ],
    "tgn:id":7531268,
    "tgn:name:en":"Government Department Collective",
    "tgn:placetype":[
        "aat:300000202"
    ]
},
  "bbox": [],
  "geometry": {"coordinates":[31.744477,30.282882],"type":"Point"}
}