{
  "id": 2107154,
  "type": "Feature",
  "properties": {
    "tgn:hierarchy":[
        "tgn:2107154",
        "tgn:1000001",
        "tgn:7012149",
        "tgn:2002075",
        "tgn:7007826",
        "tgn:7029392"
    ],
    "tgn:id":2107154,
    "tgn:name":"Rio Grande City",
    "tgn:placetype":[
        "aat:300008347"
    ]
},
  "bbox": [],
  "geometry": {"coordinates":[-98.8167,26.3667],"type":"Point"}
}