{
  "id": 7530796,
  "type": "Feature",
  "properties": {
    "tgn:hierarchy":[
        "tgn:7530796",
        "tgn:7001242",
        "tgn:7016833",
        "tgn:1001083",
        "tgn:7029392"
    ],
    "tgn:id":7530796,
    "tgn:name":"An Nas\u0101j\u016bn ash Sharq\u012by\u016bn",
    "tgn:placetype":[
        "aat:300006676"
    ]
},
  "bbox": [],
  "geometry": {"coordinates":[31.203977,30.009122],"type":"Point"}
}