{
  "id": 2190965,
  "type": "Feature",
  "properties": {
    "tgn:hierarchy":[
        "tgn:2190965",
        "tgn:1000001",
        "tgn:7012149",
        "tgn:2001210",
        "tgn:7007523",
        "tgn:7029392"
    ],
    "tgn:id":2190965,
    "tgn:name":"Boyd Pond",
    "tgn:placetype":[
        "aat:300008680"
    ]
},
  "bbox": [],
  "geometry": {"coordinates":[-93.5667,38.75],"type":"Point"}
}