{
  "id": 7407643,
  "type": "Feature",
  "properties": {
    "tgn:hierarchy":[
        "tgn:7407643",
        "tgn:1000001",
        "tgn:1001893",
        "tgn:7005560",
        "tgn:7029392"
    ],
    "tgn:id":7407643,
    "tgn:name":"San Jos\u00e9 Chalmita",
    "tgn:placetype":[
        "aat:300008347"
    ]
},
  "bbox": [],
  "geometry": {"coordinates":[-99.55,18.85],"type":"Point"}
}