{
  "id": 7219403,
  "type": "Feature",
  "properties": {
    "tgn:hierarchy":[
        "tgn:7219403",
        "tgn:7011164",
        "tgn:7002674",
        "tgn:1000003",
        "tgn:1000074",
        "tgn:7029392"
    ],
    "tgn:id":7219403,
    "tgn:name":"Plat\u00fd, Vrachonis\u00edda",
    "tgn:placetype":[
        "aat:300008791"
    ]
},
  "bbox": [],
  "geometry": {"coordinates":[26.488333,37.516111],"type":"Point"}
}