{
  "id": 2501025,
  "type": "Feature",
  "properties": {
    "tgn:hierarchy":[
        "tgn:2501025",
        "tgn:1000001",
        "tgn:2001842",
        "tgn:7012149",
        "tgn:7007825",
        "tgn:7029392"
    ],
    "tgn:id":2501025,
    "tgn:name":"McGaha Hollow",
    "tgn:placetype":[
        "aat:300008761"
    ]
},
  "bbox": [],
  "geometry": {"coordinates":[-84.95,35.2667],"type":"Point"}
}