{
  "id": 7342168,
  "type": "Feature",
  "properties": {
    "tgn:hierarchy":[
        "tgn:7342168",
        "tgn:7002758",
        "tgn:7002830",
        "tgn:1000003",
        "tgn:1000095",
        "tgn:7029392"
    ],
    "tgn:id":7342168,
    "tgn:name":"Carratraca",
    "tgn:placetype":[
        "aat:300008347"
    ]
},
  "bbox": [],
  "geometry": {"coordinates":[-4.816667,36.85],"type":"Point"}
}