{
  "id": 2355026,
  "type": "Feature",
  "properties": {
    "tgn:hierarchy":[
        "tgn:2355026",
        "tgn:1000001",
        "tgn:7012149",
        "tgn:2001867",
        "tgn:7007825",
        "tgn:7029392"
    ],
    "tgn:id":2355026,
    "tgn:name":"Goodman Point",
    "tgn:placetype":[
        "aat:300008850"
    ]
},
  "bbox": [],
  "geometry": {"coordinates":[-85.8333,35.2833],"type":"Point"}
}