{
  "id": 7074222,
  "type": "Feature",
  "properties": {
    "tgn:hierarchy":[
        "tgn:7074222",
        "tgn:7003669",
        "tgn:1000003",
        "tgn:7000084",
        "tgn:7029392"
    ],
    "tgn:id":7074222,
    "tgn:name":"Tenn-See",
    "tgn:placetype":[
        "aat:300008680"
    ]
},
  "bbox": [],
  "geometry": {"coordinates":[11.266667,47.466667],"type":"Point"}
}