<<<<<<< HEAD
{
  "id": 7055939,
  "type": "Feature",
  "properties": {
    "tgn:hierarchy":[
        "tgn:7055939",
        "tgn:7003137",
        "tgn:1000003",
        "tgn:7003080",
        "tgn:1000080",
        "tgn:7029392"
    ],
    "tgn:id":7055939,
    "tgn:name":"Opagna",
    "tgn:placetype":[
        "aat:300008347"
    ]
},
  "bbox": [],
  "geometry": {"coordinates":[13.1,42.65],"type":"Point"}
}
=======
{"geometry":{"type":"Point","coordinates":[13.100000,42.650000]},"type":"Feature","properties":{"hierarchy":["tgn:7055939","tgn:7003137","tgn:1000003","tgn:7003080","tgn:1000080","tgn:7029392"],"placetype":["aat:300008347"],"id":7055939,"name:xx":"Opagna"}}
>>>>>>> 03f74aca74312dbeaf24d7e61306dd6a786dc3d0
