{
  "id": 7315605,
  "type": "Feature",
  "properties": {
    "tgn:hierarchy":[
        "tgn:7315605",
        "tgn:1001699",
        "tgn:1000049",
        "tgn:1000002",
        "tgn:7029392"
    ],
    "tgn:id":7315605,
    "tgn:name":"Chacayal",
    "tgn:placetype":[
        "aat:300000206"
    ]
},
  "bbox": [],
  "geometry": {"coordinates":[-73.133333,-40.516667],"type":"Point"}
}