<<<<<<< HEAD
{
  "id": 2154507,
  "type": "Feature",
  "properties": {
    "tgn:hierarchy":[
        "tgn:2154507",
        "tgn:1000001",
        "tgn:2002369",
        "tgn:7012149",
        "tgn:7007923",
        "tgn:7029392"
    ],
    "tgn:id":2154507,
    "tgn:name":"Bear Creek Mine",
    "tgn:placetype":[
        "aat:300000390"
    ]
},
  "bbox": [],
  "geometry": {"coordinates":[-105.6,43.2667],"type":"Point"}
}
=======
{"geometry":{"type":"Point","coordinates":[-105.600000,43.266700]},"type":"Feature","properties":{"hierarchy":["tgn:2154507","tgn:1000001","tgn:2002369","tgn:7012149","tgn:7007923","tgn:7029392"],"placetype":["aat:300000390"],"id":2154507,"name:xx":"Bear Creek Mine"}}
>>>>>>> 03f74aca74312dbeaf24d7e61306dd6a786dc3d0
