{
  "id": 7250386,
  "type": "Feature",
  "properties": {
    "tgn:hierarchy":[
        "tgn:7250386",
        "tgn:7003465",
        "tgn:1000003",
        "tgn:1000063",
        "tgn:4012014",
        "tgn:7029392"
    ],
    "tgn:id":7250386,
    "tgn:name":"Prov\u00e8droux, H\u00e9 de",
    "tgn:placetype":[
        "aat:300008863"
    ]
},
  "bbox": [],
  "geometry": {"coordinates":[5.887222,50.242778],"type":"Point"}
}