{
  "id": 1105192,
  "type": "Feature",
  "properties": {
    "tgn:hierarchy":[
        "tgn:1105192",
        "tgn:7003029",
        "tgn:1000003",
        "tgn:1000062",
        "tgn:7029392"
    ],
    "tgn:id":1105192,
    "tgn:name":"Kellerjoch",
    "tgn:placetype":[
        "aat:300008795"
    ]
},
  "bbox": [],
  "geometry": {"coordinates":[11.7667,47.3167],"type":"Point"}
}