{
  "id": 2186046,
  "type": "Feature",
  "properties": {
    "tgn:hierarchy":[
        "tgn:2186046",
        "tgn:1002201",
        "tgn:1000001",
        "tgn:7012149",
        "tgn:7007517",
        "tgn:7029392"
    ],
    "tgn:id":2186046,
    "tgn:name":"Bolton Cedar Swamp",
    "tgn:placetype":[
        "aat:300008905"
    ]
},
  "bbox": [],
  "geometry": {"coordinates":[-70.95,41.75],"type":"Point"}
}