{
  "id": 2716983,
  "type": "Feature",
  "properties": {
    "tgn:hierarchy":[
        "tgn:2716983",
        "tgn:1000001",
        "tgn:7012149",
        "tgn:2001152",
        "tgn:7007522",
        "tgn:7029392"
    ],
    "tgn:id":2716983,
    "tgn:name":"Thigpen Lake",
    "tgn:placetype":[
        "aat:300008680",
        "aat:300387018"
    ]
},
  "bbox": [],
  "geometry": {"coordinates":[-90.6833,33.3833],"type":"Point"}
}