<<<<<<< HEAD
{
  "id": 2768338,
  "type": "Feature",
  "properties": {
    "tgn:hierarchy":[
        "tgn:2768338",
        "tgn:1000001",
        "tgn:7012149",
        "tgn:2000851",
        "tgn:7007255",
        "tgn:7029392"
    ],
    "tgn:id":2768338,
    "tgn:name":"Whiteside Creek",
    "tgn:placetype":[
        "aat:300008706"
    ]
},
  "bbox": [],
  "geometry": {"coordinates":[-87.6333,37.4667],"type":"Point"}
}
=======
{"geometry":{"type":"Point","coordinates":[-87.633300,37.466700]},"type":"Feature","properties":{"hierarchy":["tgn:2768338","tgn:1000001","tgn:7012149","tgn:2000851","tgn:7007255","tgn:7029392"],"placetype":["aat:300008706"],"id":2768338,"name:xx":"Whiteside Creek"}}
>>>>>>> 03f74aca74312dbeaf24d7e61306dd6a786dc3d0
