{
  "id": 7206502,
  "type": "Feature",
  "properties": {
    "tgn:hierarchy":[
        "tgn:7206502",
        "tgn:7003669",
        "tgn:1000003",
        "tgn:7000084",
        "tgn:7029392"
    ],
    "tgn:id":7206502,
    "tgn:name":"Buchwald",
    "tgn:placetype":[
        "aat:300000206"
    ]
},
  "bbox": [],
  "geometry": {"coordinates":[10.516667,47.683333],"type":"Point"}
}