{
  "id": 2394162,
  "type": "Feature",
  "properties": {
    "tgn:hierarchy":[
        "tgn:2394162",
        "tgn:1000001",
        "tgn:7019982",
        "tgn:7012149",
        "tgn:7007517",
        "tgn:7029392"
    ],
    "tgn:id":2394162,
    "tgn:name":"Hogan Ponds",
    "tgn:placetype":[
        "aat:300008680"
    ]
},
  "bbox": [],
  "geometry": {"coordinates":[-72.5667,42.1333],"type":"Point"}
}