{
  "id": 2757793,
  "type": "Feature",
  "properties": {
    "tgn:hierarchy":[
        "tgn:2757793",
        "tgn:1000001",
        "tgn:7012149",
        "tgn:7007710",
        "tgn:7029392"
    ],
    "tgn:id":2757793,
    "tgn:name":"West Branch Hicks Run",
    "tgn:placetype":[
        "aat:300008699"
    ]
},
  "bbox": [],
  "geometry": {"coordinates":[-78.4167,41.4333],"type":"Point"}
}