{
  "id": 2787219,
  "type": "Feature",
  "properties": {
    "tgn:hierarchy":[
        "tgn:2787219",
        "tgn:1000001",
        "tgn:7012149",
        "tgn:2000358",
        "tgn:7007248",
        "tgn:7029392"
    ],
    "tgn:id":2787219,
    "tgn:name":"Zola, Lake",
    "tgn:placetype":[
        "aat:300006191"
    ]
},
  "bbox": [],
  "geometry": {"coordinates":[-84.0167,33.8833],"type":"Point"}
}