{
  "id": 7234093,
  "type": "Feature",
  "properties": {
    "tgn:hierarchy":[
        "tgn:7234093",
        "tgn:7002750",
        "tgn:7001399",
        "tgn:1000003",
        "tgn:1000074",
        "tgn:7029392"
    ],
    "tgn:id":7234093,
    "tgn:name":"Akh\u00edllion",
    "tgn:placetype":[
        "aat:300008347"
    ]
},
  "bbox": [],
  "geometry": {"coordinates":[22.666667,39.533333],"type":"Point"}
}