{
  "id": 2354451,
  "type": "Feature",
  "properties": {
    "tgn:hierarchy":[
        "tgn:2354451",
        "tgn:1000001",
        "tgn:7006451",
        "tgn:2000092",
        "tgn:7012149",
        "tgn:7029392"
    ],
    "tgn:id":2354451,
    "tgn:name":"Goldtrap Tank",
    "tgn:placetype":[
        "aat:300006191"
    ]
},
  "bbox": [],
  "geometry": {"coordinates":[-112.5333,35.3833],"type":"Point"}
}