<<<<<<< HEAD
{
  "id": 7170840,
  "type": "Feature",
  "properties": {
    "tgn:hierarchy":[
        "tgn:7170840",
        "tgn:1000003",
        "tgn:7003685",
        "tgn:7000084",
        "tgn:7029392"
    ],
    "tgn:id":7170840,
    "tgn:name":"Hirschsprung",
    "tgn:placetype":[
        "aat:300008795"
    ]
},
  "bbox": [],
  "geometry": {"coordinates":[12.8,50.466667],"type":"Point"}
}
=======
{"geometry":{"type":"Point","coordinates":[12.800000,50.466667]},"type":"Feature","properties":{"hierarchy":["tgn:7170840","tgn:1000003","tgn:7003685","tgn:7000084","tgn:7029392"],"placetype":["aat:300008795"],"id":7170840,"name:xx":"Hirschsprung"}}
>>>>>>> 03f74aca74312dbeaf24d7e61306dd6a786dc3d0
