{
  "id": 2009844,
  "type": "Feature",
  "properties": {
    "tgn:hierarchy":[
        "tgn:2009844",
        "tgn:1000001",
        "tgn:7016172",
        "tgn:7012149",
        "tgn:2000178",
        "tgn:7029392"
    ],
    "tgn:id":2009844,
    "tgn:name":"Wiville",
    "tgn:placetype":[
        "aat:300008347",
        "aat:300387210"
    ]
},
  "bbox": [],
  "geometry": {"coordinates":[-91.2333,35.1333],"type":"Point"}
}