{
  "id": 2037740,
  "type": "Feature",
  "properties": {
    "tgn:hierarchy":[
        "tgn:2037740",
        "tgn:1000001",
        "tgn:7012149",
        "tgn:2000832",
        "tgn:7007255",
        "tgn:7029392"
    ],
    "tgn:id":2037740,
    "tgn:name":"Bevier",
    "tgn:placetype":[
        "aat:300008347",
        "aat:300387210"
    ]
},
  "bbox": [],
  "geometry": {"coordinates":[-87.0667,37.2333],"type":"Point"}
}