{
  "id": 2193787,
  "type": "Feature",
  "properties": {
    "tgn:hierarchy":[
        "tgn:2193787",
        "tgn:1000001",
        "tgn:7012149",
        "tgn:7007710",
        "tgn:7029392"
    ],
    "tgn:id":2193787,
    "tgn:name":"Brian Branch",
    "tgn:placetype":[
        "aat:300008699"
    ]
},
  "bbox": [],
  "geometry": {"coordinates":[-76.75,41.4667],"type":"Point"}
}