{
  "id": 2205997,
  "type": "Feature",
  "properties": {
    "tgn:hierarchy":[
        "tgn:2205997",
        "tgn:1000001",
        "tgn:7012149",
        "tgn:7007157",
        "tgn:1002956",
        "tgn:7029392"
    ],
    "tgn:id":2205997,
    "tgn:name":"Bull Run Basin",
    "tgn:placetype":[
        "aat:300386845"
    ]
},
  "bbox": [],
  "geometry": {"coordinates":[-118.5167,35.7833],"type":"Point"}
}