{
  "id": 7237196,
  "type": "Feature",
  "properties": {
    "tgn:hierarchy":[
        "tgn:7237196",
        "tgn:7002680",
        "tgn:7001395",
        "tgn:1000003",
        "tgn:1000074",
        "tgn:7029392"
    ],
    "tgn:id":7237196,
    "tgn:name":"Eglik\u00e1dha",
    "tgn:placetype":[
        "aat:300008347"
    ]
},
  "bbox": [],
  "geometry": {"coordinates":[21.766667,38.233333],"type":"Point"}
}