{
  "id": 2467640,
  "type": "Feature",
  "properties": {
    "tgn:hierarchy":[
        "tgn:2467640",
        "tgn:1000001",
        "tgn:2001943",
        "tgn:7012149",
        "tgn:7007826",
        "tgn:7029392"
    ],
    "tgn:id":2467640,
    "tgn:name":"Long Hollow Tank",
    "tgn:placetype":[
        "aat:300006191"
    ]
},
  "bbox": [],
  "geometry": {"coordinates":[-101.5667,32.5667],"type":"Point"}
}