{
  "id": 2368273,
  "type": "Feature",
  "properties": {
    "tgn:hierarchy":[
        "tgn:2368273",
        "tgn:1000001",
        "tgn:7012149",
        "tgn:2001708",
        "tgn:7007708",
        "tgn:7029392"
    ],
    "tgn:id":2368273,
    "tgn:name":"Guernsey Pond",
    "tgn:placetype":[
        "aat:300006191"
    ]
},
  "bbox": [],
  "geometry": {"coordinates":[-118.95,44.2833],"type":"Point"}
}