{
  "id": 7408213,
  "type": "Feature",
  "properties": {
    "tgn:hierarchy":[
        "tgn:7408213",
        "tgn:7005580",
        "tgn:1000001",
        "tgn:7005560",
        "tgn:7029392"
    ],
    "tgn:id":7408213,
    "tgn:name":"El Cedro",
    "tgn:placetype":[
        "aat:300008347"
    ]
},
  "bbox": [],
  "geometry": {"coordinates":[-90.433333,16.416667],"type":"Point"}
}