{
  "id": 2704992,
  "type": "Feature",
  "properties": {
    "tgn:hierarchy":[
        "tgn:2704992",
        "tgn:1000001",
        "tgn:2001485",
        "tgn:7012149",
        "tgn:7007709",
        "tgn:7029392"
    ],
    "tgn:id":2704992,
    "tgn:name":"Sunset Terrace",
    "tgn:placetype":[
        "aat:300008347"
    ]
},
  "bbox": [],
  "geometry": {"coordinates":[-78.7167,34.3333],"type":"Point"}
}