<<<<<<< HEAD
{
  "id": 7052066,
  "type": "Feature",
  "properties": {
    "tgn:hierarchy":[
        "tgn:7052066",
        "tgn:7003138",
        "tgn:1000003",
        "tgn:7003080",
        "tgn:1000080",
        "tgn:7029392"
    ],
    "tgn:id":7052066,
    "tgn:name":"Marano",
    "tgn:placetype":[
        "aat:300008347"
    ]
},
  "bbox": [],
  "geometry": {"coordinates":[13.016667,42.0],"type":"Point"}
}
=======
{"geometry":{"type":"Point","coordinates":[13.016667,42.000000]},"type":"Feature","properties":{"hierarchy":["tgn:7052066","tgn:7003138","tgn:1000003","tgn:7003080","tgn:1000080","tgn:7029392"],"placetype":["aat:300008347"],"id":7052066,"name:xx":"Marano"}}
>>>>>>> 03f74aca74312dbeaf24d7e61306dd6a786dc3d0
