{
  "id": 2065150,
  "type": "Feature",
  "properties": {
    "tgn:hierarchy":[
        "tgn:2065150",
        "tgn:1000001",
        "tgn:1002695",
        "tgn:7012149",
        "tgn:7007565",
        "tgn:7029392"
    ],
    "tgn:id":2065150,
    "tgn:name":"Lake Telemark",
    "tgn:placetype":[
        "aat:300008347"
    ]
},
  "bbox": [],
  "geometry": {"coordinates":[-74.4833,40.95],"type":"Point"}
}