{
  "id": 7554088,
  "type": "Feature",
  "properties": {
    "tgn:hierarchy":[
        "tgn:7554088",
        "tgn:1000004",
        "tgn:7000198",
        "tgn:7016722",
        "tgn:7029392"
    ],
    "tgn:id":7554088,
    "tgn:name:en":"Maw\u0101na",
    "tgn:placetype":[
        "aat:300008347"
    ]
},
  "bbox": [],
  "geometry": {"coordinates":[77.921342,29.104363],"type":"Point"}
}