{
  "id": 2078288,
  "type": "Feature",
  "properties": {
    "tgn:hierarchy":[
        "tgn:2078288",
        "tgn:1000001",
        "tgn:7012149",
        "tgn:1002883",
        "tgn:7007706",
        "tgn:7029392"
    ],
    "tgn:id":2078288,
    "tgn:name":"Attica Junction",
    "tgn:placetype":[
        "aat:300008347"
    ]
},
  "bbox": [],
  "geometry": {"coordinates":[-82.8667,41.0833],"type":"Point"}
}