{
  "id": 7414784,
  "type": "Feature",
  "properties": {
    "tgn:hierarchy":[
        "tgn:7414784",
        "tgn:1000001",
        "tgn:7005591",
        "tgn:7005560",
        "tgn:7029392"
    ],
    "tgn:id":7414784,
    "tgn:name:es":"Cerro Iguana",
    "tgn:placetype":[
        "aat:300008347"
    ]
},
  "bbox": [],
  "geometry": {"coordinates":[-94.726389,16.493056],"type":"Point"}
}