{
  "id": 7232691,
  "type": "Feature",
  "properties": {
    "tgn:hierarchy":[
        "tgn:7232691",
        "tgn:7002735",
        "tgn:7017076",
        "tgn:1000003",
        "tgn:1000074",
        "tgn:7029392"
    ],
    "tgn:id":7232691,
    "tgn:name":"Kosk\u00f3raka, R\u00e9mma",
    "tgn:placetype":[
        "aat:300008699"
    ]
},
  "bbox": [],
  "geometry": {"coordinates":[22.183333,36.95],"type":"Point"}
}