{
  "id": 1017042,
  "type": "Feature",
  "properties": {
    "tgn:hierarchy":[
        "tgn:1017042",
        "tgn:7005586",
        "tgn:1000001",
        "tgn:7005560",
        "tgn:7029392"
    ],
    "tgn:id":1017042,
    "tgn:name":"Atotonilco el Alto",
    "tgn:placetype":[
        "aat:300008347"
    ]
},
  "bbox": [],
  "geometry": {"coordinates":[-102.516667,20.55],"type":"Point"}
}