{
  "id": 7082949,
  "type": "Feature",
  "properties": {
    "tgn:hierarchy":[
        "tgn:7082949",
        "tgn:1000003",
        "tgn:7003676",
        "tgn:7000084",
        "tgn:7029392"
    ],
    "tgn:id":7082949,
    "tgn:name":"Wierener Berge",
    "tgn:placetype":[
        "aat:300266640"
    ]
},
  "bbox": [],
  "geometry": {"coordinates":[10.633333,52.866667],"type":"Point"}
}