{
  "id": 7433835,
  "type": "Feature",
  "properties": {
    "tgn:hierarchy":[
        "tgn:7433835",
        "tgn:1001835",
        "tgn:1000001",
        "tgn:7005560",
        "tgn:7029392"
    ],
    "tgn:id":7433835,
    "tgn:name":"Verde, Ca\u00f1ada",
    "tgn:placetype":[
        "aat:300008773"
    ]
},
  "bbox": [],
  "geometry": {"coordinates":[-116.333333,31.583333],"type":"Point"}
}