{
  "id": 2541047,
  "type": "Feature",
  "properties": {
    "tgn:hierarchy":[
        "tgn:2541047",
        "tgn:1000001",
        "tgn:7012149",
        "tgn:1002603",
        "tgn:7007520",
        "tgn:7029392"
    ],
    "tgn:id":2541047,
    "tgn:name":"Nicholson",
    "tgn:placetype":[
        "aat:300008347"
    ]
},
  "bbox": [],
  "geometry": {"coordinates":[-84.1167,42.7667],"type":"Point"}
}