{
  "id": 7296931,
  "type": "Feature",
  "properties": {
    "tgn:hierarchy":[
        "tgn:7296931",
        "tgn:7002844",
        "tgn:7030216",
        "tgn:1000003",
        "tgn:1000095",
        "tgn:7029392"
    ],
    "tgn:id":7296931,
    "tgn:name":"Trinidad, Salinas de la",
    "tgn:placetype":[
        "aat:300386883"
    ]
},
  "bbox": [],
  "geometry": {"coordinates":[0.666667,40.583333],"type":"Point"}
}