{
  "id": 7564452,
  "type": "Feature",
  "properties": {
    "tgn:hierarchy":[
        "tgn:7564452",
        "tgn:1000004",
        "tgn:7000198",
        "tgn:1001894",
        "tgn:7029392"
    ],
    "tgn:id":7564452,
    "tgn:name:en":"Machora",
    "tgn:placetype":[
        "aat:300008347"
    ]
},
  "bbox": [],
  "geometry": {"coordinates":[79.060603,24.984356],"type":"Point"}
}