{
  "id": 7129489,
  "type": "Feature",
  "properties": {
    "tgn:hierarchy":[
        "tgn:7129489",
        "tgn:7003692",
        "tgn:1000003",
        "tgn:7000084",
        "tgn:7029392"
    ],
    "tgn:id":7129489,
    "tgn:name":"Bahnhof Mannheim-Luzenberg",
    "tgn:placetype":[
        "aat:300007783"
    ]
},
  "bbox": [],
  "geometry": {"coordinates":[8.466667,49.516667],"type":"Point"}
}