{
  "id": 1025171,
  "type": "Feature",
  "properties": {
    "tgn:hierarchy":[
        "tgn:1025171",
        "tgn:1001837",
        "tgn:1000002",
        "tgn:1000059",
        "tgn:7029392"
    ],
    "tgn:id":1025171,
    "tgn:name":"La Uni\u00f3n",
    "tgn:placetype":[
        "aat:300008347"
    ]
},
  "bbox": [],
  "geometry": {"coordinates":[-67.7667,8.25],"type":"Point"}
}