{
  "id": 7198479,
  "type": "Feature",
  "properties": {
    "tgn:hierarchy":[
        "tgn:7198479",
        "tgn:1000003",
        "tgn:7003685",
        "tgn:7000084",
        "tgn:7029392"
    ],
    "tgn:id":7198479,
    "tgn:name":"Ebersbrunn",
    "tgn:placetype":[
        "aat:300008347"
    ]
},
  "bbox": [],
  "geometry": {"coordinates":[12.433333,50.65],"type":"Point"}
}