{
  "id": 2314912,
  "type": "Feature",
  "properties": {
    "tgn:hierarchy":[
        "tgn:2314912",
        "tgn:1000001",
        "tgn:7012149",
        "tgn:7007157",
        "tgn:1002863",
        "tgn:7029392"
    ],
    "tgn:id":2314912,
    "tgn:name":"Elkhorn Plain",
    "tgn:placetype":[
        "aat:300008805"
    ]
},
  "bbox": [],
  "geometry": {"coordinates":[-119.55,35.0667],"type":"Point"}
}