{
  "id": 7584374,
  "type": "Feature",
  "properties": {
    "tgn:hierarchy":[
        "tgn:7584374",
        "tgn:1000004",
        "tgn:7000198",
        "tgn:1001894",
        "tgn:7029392"
    ],
    "tgn:id":7584374,
    "tgn:name:en":"Mau",
    "tgn:placetype":[
        "aat:300008347"
    ]
},
  "bbox": [],
  "geometry": {"coordinates":[78.785198,24.790057],"type":"Point"}
}