{
  "id": 7215898,
  "type": "Feature",
  "properties": {
    "tgn:hierarchy":[
        "tgn:7215898",
        "tgn:7003692",
        "tgn:1000003",
        "tgn:7000084",
        "tgn:7029392"
    ],
    "tgn:id":7215898,
    "tgn:name":"Aitrach",
    "tgn:placetype":[
        "aat:300008699"
    ]
},
  "bbox": [],
  "geometry": {"coordinates":[10.083333,47.95],"type":"Point"}
}