<<<<<<< HEAD
{
  "id": 7481914,
  "type": "Feature",
  "properties": {
    "tgn:hierarchy":[
        "tgn:7481914",
        "tgn:1000004",
        "tgn:7001013",
        "tgn:1000141",
        "tgn:7029392"
    ],
    "tgn:id":7481914,
    "tgn:name":"Gaorong Gongyequ",
    "tgn:placetype":[
        "aat:300387302"
    ]
},
  "bbox": [],
  "geometry": {"coordinates":[121.159167,24.955556],"type":"Point"}
}
=======
{"geometry":{"type":"Point","coordinates":[121.159167,24.955556]},"type":"Feature","properties":{"hierarchy":["tgn:7481914","tgn:1000004","tgn:7001013","tgn:1000141","tgn:7029392"],"placetype":["aat:300387302"],"id":7481914,"name:xx":"Gaorong Gongyequ"}}
>>>>>>> 03f74aca74312dbeaf24d7e61306dd6a786dc3d0
