{
  "id": 7481914,
  "type": "Feature",
  "properties": {
    "tgn:hierarchy":[
        "tgn:7481914",
        "tgn:1000004",
        "tgn:7001013",
        "tgn:1000141",
        "tgn:7029392"
    ],
    "tgn:id":7481914,
    "tgn:name":"Gaorong Gongyequ",
    "tgn:placetype":[
        "aat:300387302"
    ]
},
  "bbox": [],
  "geometry": {"coordinates":[121.159167,24.955556],"type":"Point"}
}