{
  "id": 7481581,
  "type": "Feature",
  "properties": {
    "tgn:hierarchy":[
        "tgn:7481581",
        "tgn:7487020",
        "tgn:1000004",
        "tgn:1000141",
        "tgn:7029392"
    ],
    "tgn:id":7481581,
    "tgn:name":"Qijun Shan",
    "tgn:placetype":[
        "aat:300008798"
    ]
},
  "bbox": [],
  "geometry": {"coordinates":[121.1375,24.354722],"type":"Point"}
}