{
  "id": 2331365,
  "type": "Feature",
  "properties": {
    "tgn:hierarchy":[
        "tgn:2331365",
        "tgn:1000001",
        "tgn:7006451",
        "tgn:7012149",
        "tgn:2000101",
        "tgn:7029392"
    ],
    "tgn:id":2331365,
    "tgn:name":"Flatiron, The",
    "tgn:placetype":[
        "aat:300008798"
    ]
},
  "bbox": [],
  "geometry": {"coordinates":[-111.4333,33.4167],"type":"Point"}
}