{
  "id": 7436728,
  "type": "Feature",
  "properties": {
    "tgn:hierarchy":[
        "tgn:7436728",
        "tgn:1000001",
        "tgn:7005599",
        "tgn:7005560",
        "tgn:7029392"
    ],
    "tgn:id":7436728,
    "tgn:name":"Sochiapa",
    "tgn:placetype":[
        "aat:300008347"
    ]
},
  "bbox": [],
  "geometry": {"coordinates":[-96.916667,19.183333],"type":"Point"}
}