{
  "id": 2672783,
  "type": "Feature",
  "properties": {
    "tgn:hierarchy":[
        "tgn:2672783",
        "tgn:1000001",
        "tgn:7012149",
        "tgn:2001902",
        "tgn:7007825",
        "tgn:7029392"
    ],
    "tgn:id":2672783,
    "tgn:name":"Snaggy Bar",
    "tgn:placetype":[
        "aat:300132348"
    ]
},
  "bbox": [],
  "geometry": {"coordinates":[-89.3333,36.4167],"type":"Point"}
}