{
  "id": 7043729,
  "type": "Feature",
  "properties": {
    "tgn:hierarchy":[
        "tgn:7043729",
        "tgn:1001724",
        "tgn:1000003",
        "tgn:7003121",
        "tgn:1000080",
        "tgn:7029392"
    ],
    "tgn:id":7043729,
    "tgn:name":"Gairo Scalo",
    "tgn:placetype":[
        "aat:300008347"
    ]
},
  "bbox": [],
  "geometry": {"coordinates":[9.461667,39.856667],"type":"Point"}
}