{
  "id": 7104925,
  "type": "Feature",
  "properties": {
    "tgn:hierarchy":[
        "tgn:7104925",
        "tgn:1000003",
        "tgn:7003678",
        "tgn:7000084",
        "tgn:7029392"
    ],
    "tgn:id":7104925,
    "tgn:name":"Schnegelshof",
    "tgn:placetype":[
        "aat:300000206"
    ]
},
  "bbox": [],
  "geometry": {"coordinates":[9.516667,51.066667],"type":"Point"}
}