{
  "id": 2037513,
  "type": "Feature",
  "properties": {
    "tgn:hierarchy":[
        "tgn:2037513",
        "tgn:1000001",
        "tgn:7012149",
        "tgn:2000837",
        "tgn:7007255",
        "tgn:7029392"
    ],
    "tgn:id":2037513,
    "tgn:name":"Argo",
    "tgn:placetype":[
        "aat:300008347"
    ]
},
  "bbox": [],
  "geometry": {"coordinates":[-82.05,37.4667],"type":"Point"}
}