<<<<<<< HEAD
{
  "id": 2250430,
  "type": "Feature",
  "properties": {
    "tgn:hierarchy":[
        "tgn:2250430",
        "tgn:1000001",
        "tgn:2000313",
        "tgn:7012149",
        "tgn:7007248",
        "tgn:7029392"
    ],
    "tgn:id":2250430,
    "tgn:name":"Colonial Estates",
    "tgn:placetype":[
        "aat:300008347"
    ]
},
  "bbox": [],
  "geometry": {"coordinates":[-85.1167,33.55],"type":"Point"}
}
=======
{"geometry":{"type":"Point","coordinates":[-85.116700,33.550000]},"type":"Feature","properties":{"hierarchy":["tgn:2250430","tgn:1000001","tgn:2000313","tgn:7012149","tgn:7007248","tgn:7029392"],"placetype":["aat:300008347"],"id":2250430,"name:xx":"Colonial Estates"}}
>>>>>>> 03f74aca74312dbeaf24d7e61306dd6a786dc3d0
