{
  "id": 7098230,
  "type": "Feature",
  "properties": {
    "tgn:hierarchy":[
        "tgn:7098230",
        "tgn:7003669",
        "tgn:1000003",
        "tgn:7000084",
        "tgn:7029392"
    ],
    "tgn:id":7098230,
    "tgn:name":"Simets Berg",
    "tgn:placetype":[
        "aat:300008795"
    ]
},
  "bbox": [],
  "geometry": {"coordinates":[11.25,47.566667],"type":"Point"}
}