<<<<<<< HEAD
{
  "id": 2336741,
  "type": "Feature",
  "properties": {
    "tgn:hierarchy":[
        "tgn:2336741",
        "tgn:1000001",
        "tgn:7012149",
        "tgn:7007256",
        "tgn:7029392"
    ],
    "tgn:id":2336741,
    "tgn:name":"Fourche, Bayou",
    "tgn:placetype":[
        "aat:300008699"
    ]
},
  "bbox": [],
  "geometry": {"coordinates":[-91.2667,29.9833],"type":"Point"}
}
=======
{"geometry":{"type":"Point","coordinates":[-91.266700,29.983300]},"type":"Feature","properties":{"hierarchy":["tgn:2336741","tgn:1000001","tgn:7012149","tgn:7007256","tgn:7029392"],"placetype":["aat:300008699"],"id":2336741,"name:xx":"Fourche, Bayou"}}
>>>>>>> 03f74aca74312dbeaf24d7e61306dd6a786dc3d0
