{
  "id": 2302551,
  "type": "Feature",
  "properties": {
    "tgn:hierarchy":[
        "tgn:2302551",
        "tgn:1000001",
        "tgn:2001411",
        "tgn:7012149",
        "tgn:7007526",
        "tgn:7029392"
    ],
    "tgn:id":2302551,
    "tgn:name":"Dutton",
    "tgn:placetype":[
        "aat:300008347",
        "aat:300167671"
    ]
},
  "bbox": [],
  "geometry": {"coordinates":[-116.7333,41.1833],"type":"Point"}
}