<<<<<<< HEAD
{
  "id": 7379881,
  "type": "Feature",
  "properties": {
    "tgn:hierarchy":[
        "tgn:7379881",
        "tgn:7005586",
        "tgn:1000001",
        "tgn:7005560",
        "tgn:7029392"
    ],
    "tgn:id":7379881,
    "tgn:name":"Loya, Estero",
    "tgn:placetype":[
        "aat:300132317"
    ]
},
  "bbox": [],
  "geometry": {"coordinates":[-105.383333,19.866667],"type":"Point"}
}
=======
{"geometry":{"type":"Point","coordinates":[-105.383333,19.866667]},"type":"Feature","properties":{"hierarchy":["tgn:7379881","tgn:7005586","tgn:1000001","tgn:7005560","tgn:7029392"],"placetype":["aat:300132317"],"id":7379881,"name:xx":"Loya, Estero"}}
>>>>>>> 03f74aca74312dbeaf24d7e61306dd6a786dc3d0
