{
  "id": 7588237,
  "type": "Feature",
  "properties": {
    "tgn:hierarchy":[
        "tgn:7588237",
        "tgn:1000004",
        "tgn:7000198",
        "tgn:7000799",
        "tgn:7029392"
    ],
    "tgn:id":7588237,
    "tgn:name:en":"M\u0101hadeo N\u0101r",
    "tgn:placetype":[
        "aat:300008699"
    ]
},
  "bbox": [],
  "geometry": {"coordinates":[74.920833,34.154167],"type":"Point"}
}