{
  "id": 2607994,
  "type": "Feature",
  "properties": {
    "tgn:hierarchy":[
        "tgn:2607994",
        "tgn:1000001",
        "tgn:7012149",
        "tgn:2001146",
        "tgn:7007522",
        "tgn:7029392"
    ],
    "tgn:id":2607994,
    "tgn:name":"Ratliff",
    "tgn:placetype":[
        "aat:300008347"
    ]
},
  "bbox": [],
  "geometry": {"coordinates":[-89.7833,32.5667],"type":"Point"}
}