{
  "id": 2642179,
  "type": "Feature",
  "properties": {
    "tgn:hierarchy":[
        "tgn:2642179",
        "tgn:1000001",
        "tgn:7012149",
        "tgn:1002494",
        "tgn:7007710",
        "tgn:7029392"
    ],
    "tgn:id":2642179,
    "tgn:name":"Sand Ridge",
    "tgn:placetype":[
        "aat:300266640"
    ]
},
  "bbox": [],
  "geometry": {"coordinates":[-77.95,40.3667],"type":"Point"}
}