{
  "id": 2465544,
  "type": "Feature",
  "properties": {
    "tgn:hierarchy":[
        "tgn:2465544",
        "tgn:1000001",
        "tgn:7012149",
        "tgn:1002303",
        "tgn:7007826",
        "tgn:7029392"
    ],
    "tgn:id":2465544,
    "tgn:name":"Lone Mountain",
    "tgn:placetype":[
        "aat:300008798"
    ]
},
  "bbox": [],
  "geometry": {"coordinates":[-97.75,31.1667],"type":"Point"}
}