{
  "id": 1118634,
  "type": "Feature",
  "properties": {
    "tgn:hierarchy":[
        "tgn:1118634",
        "tgn:1000001",
        "tgn:7012149",
        "tgn:7007710",
        "tgn:7029392"
    ],
    "tgn:id":1118634,
    "tgn:name":"Wallenpaupack, Lake",
    "tgn:placetype":[
        "aat:300008680",
        "aat:300006191"
    ]
},
  "bbox": [],
  "geometry": {"coordinates":[-75.1833,41.45],"type":"Point"}
}