{
  "id": 2474354,
  "type": "Feature",
  "properties": {
    "tgn:hierarchy":[
        "tgn:2474354",
        "tgn:1000001",
        "tgn:2001937",
        "tgn:7012149",
        "tgn:7007826",
        "tgn:7029392"
    ],
    "tgn:id":2474354,
    "tgn:name":"Lower Pauls Lake",
    "tgn:placetype":[
        "aat:300008680"
    ]
},
  "bbox": [],
  "geometry": {"coordinates":[-102.7167,33.9667],"type":"Point"}
}