{
  "id": 2140149,
  "type": "Feature",
  "properties": {
    "tgn:hierarchy":[
        "tgn:2140149",
        "tgn:1000001",
        "tgn:7014423",
        "tgn:7012149",
        "tgn:7007517",
        "tgn:7029392"
    ],
    "tgn:id":2140149,
    "tgn:name":"Aucoot Creek",
    "tgn:placetype":[
        "aat:300008706"
    ]
},
  "bbox": [],
  "geometry": {"coordinates":[-70.7833,41.6833],"type":"Point"}
}