{
  "id": 2205303,
  "type": "Feature",
  "properties": {
    "tgn:hierarchy":[
        "tgn:2205303",
        "tgn:1000001",
        "tgn:7006451",
        "tgn:2000093",
        "tgn:7012149",
        "tgn:7029392"
    ],
    "tgn:id":2205303,
    "tgn:name":"Bull Canyon",
    "tgn:placetype":[
        "aat:300008761"
    ]
},
  "bbox": [],
  "geometry": {"coordinates":[-110.7667,33.2833],"type":"Point"}
}