{
  "id": 7293700,
  "type": "Feature",
  "properties": {
    "tgn:hierarchy":[
        "tgn:7293700",
        "tgn:7002810",
        "tgn:7001158",
        "tgn:1000003",
        "tgn:1000095",
        "tgn:7029392"
    ],
    "tgn:id":7293700,
    "tgn:name":"Villab\u00e1scones de Bezana",
    "tgn:placetype":[
        "aat:300008347"
    ]
},
  "bbox": [],
  "geometry": {"coordinates":[-3.733333,42.966667],"type":"Point"}
}