{
  "id": 7424019,
  "type": "Feature",
  "properties": {
    "tgn:hierarchy":[
        "tgn:7424019",
        "tgn:1000001",
        "tgn:1001960",
        "tgn:7005560",
        "tgn:7029392"
    ],
    "tgn:id":7424019,
    "tgn:name":"Los Baj\u00edos",
    "tgn:placetype":[
        "aat:300008347"
    ]
},
  "bbox": [],
  "geometry": {"coordinates":[-108.816667,29.416667],"type":"Point"}
}