{
  "id": 2349753,
  "type": "Feature",
  "properties": {
    "tgn:hierarchy":[
        "tgn:2349753",
        "tgn:1000001",
        "tgn:7012149",
        "tgn:2001851",
        "tgn:7007825",
        "tgn:7029392"
    ],
    "tgn:id":2349753,
    "tgn:name":"Gilliland Fork",
    "tgn:placetype":[
        "aat:300008699"
    ]
},
  "bbox": [],
  "geometry": {"coordinates":[-83.1667,35.75],"type":"Point"}
}