{
  "id": 7430238,
  "type": "Feature",
  "properties": {
    "tgn:hierarchy":[
        "tgn:7430238",
        "tgn:1000001",
        "tgn:7005595",
        "tgn:7005560",
        "tgn:7029392"
    ],
    "tgn:id":7430238,
    "tgn:name":"Herculano de la Rocha",
    "tgn:placetype":[
        "aat:300008347"
    ]
},
  "bbox": [],
  "geometry": {"coordinates":[-108.316667,25.616667],"type":"Point"}
}