{
  "id": 2201586,
  "type": "Feature",
  "properties": {
    "tgn:hierarchy":[
        "tgn:2201586",
        "tgn:1000001",
        "tgn:7012149",
        "tgn:2000481",
        "tgn:7007250",
        "tgn:7029392"
    ],
    "tgn:id":2201586,
    "tgn:name":"Buck Creek",
    "tgn:placetype":[
        "aat:300008706"
    ]
},
  "bbox": [],
  "geometry": {"coordinates":[-113.8333,44.75],"type":"Point"}
}