{
  "id": 7543839,
  "type": "Feature",
  "properties": {
    "tgn:hierarchy":[
        "tgn:7543839",
        "tgn:7001242",
        "tgn:1001059",
        "tgn:7016833",
        "tgn:7029392"
    ],
    "tgn:id":7543839,
    "tgn:name":"An Naj\u0101yrah",
    "tgn:placetype":[
        "aat:300008347"
    ]
},
  "bbox": [],
  "geometry": {"coordinates":[31.511064,31.330434],"type":"Point"}
}