<<<<<<< HEAD
{
  "id": 7371361,
  "type": "Feature",
  "properties": {
    "tgn:hierarchy":[
        "tgn:7371361",
        "tgn:1000001",
        "tgn:1001893",
        "tgn:7005560",
        "tgn:7029392"
    ],
    "tgn:id":7371361,
    "tgn:name":"San Marcos Jilotzingo",
    "tgn:placetype":[
        "aat:300008347"
    ]
},
  "bbox": [],
  "geometry": {"coordinates":[-99.057778,19.87],"type":"Point"}
}
=======
{"geometry":{"type":"Point","coordinates":[-99.057778,19.870000]},"type":"Feature","properties":{"hierarchy":["tgn:7371361","tgn:1000001","tgn:1001893","tgn:7005560","tgn:7029392"],"placetype":["aat:300008347"],"id":7371361,"name:xx":"San Marcos Jilotzingo"}}
>>>>>>> 03f74aca74312dbeaf24d7e61306dd6a786dc3d0
