{
  "id": 2492014,
  "type": "Feature",
  "properties": {
    "tgn:hierarchy":[
        "tgn:2492014",
        "tgn:1000001",
        "tgn:2001483",
        "tgn:7012149",
        "tgn:7007709",
        "tgn:7029392"
    ],
    "tgn:id":2492014,
    "tgn:name":"Marbleyard Ridge",
    "tgn:placetype":[
        "aat:300266640"
    ]
},
  "bbox": [],
  "geometry": {"coordinates":[-83.5667,35.05],"type":"Point"}
}