<<<<<<< HEAD
{
  "id": 2150499,
  "type": "Feature",
  "properties": {
    "tgn:hierarchy":[
        "tgn:2150499",
        "tgn:1000001",
        "tgn:1002270",
        "tgn:7012149",
        "tgn:7007708",
        "tgn:7029392"
    ],
    "tgn:id":2150499,
    "tgn:name":"Basin Point",
    "tgn:placetype":[
        "aat:300008798"
    ]
},
  "bbox": [],
  "geometry": {"coordinates":[-121.75,45.1667],"type":"Point"}
}
=======
{"geometry":{"type":"Point","coordinates":[-121.750000,45.166700]},"type":"Feature","properties":{"hierarchy":["tgn:2150499","tgn:1000001","tgn:1002270","tgn:7012149","tgn:7007708","tgn:7029392"],"placetype":["aat:300008798"],"id":2150499,"name:xx":"Basin Point"}}
>>>>>>> 03f74aca74312dbeaf24d7e61306dd6a786dc3d0
