{
  "id": 7299672,
  "type": "Feature",
  "properties": {
    "tgn:hierarchy":[
        "tgn:7299672",
        "tgn:1001439",
        "tgn:1000003",
        "tgn:7002797",
        "tgn:1000095",
        "tgn:7029392"
    ],
    "tgn:id":7299672,
    "tgn:name":"Estaci\u00f3n de Ulea",
    "tgn:placetype":[
        "aat:300007783"
    ]
},
  "bbox": [],
  "geometry": {"coordinates":[-1.266667,38.183333],"type":"Point"}
}