{
  "id": 7251920,
  "type": "Feature",
  "properties": {
    "tgn:hierarchy":[
        "tgn:7251920",
        "tgn:7003458",
        "tgn:1000003",
        "tgn:1000063",
        "tgn:7018236",
        "tgn:7029392"
    ],
    "tgn:id":7251920,
    "tgn:name":"Meerlaan",
    "tgn:placetype":[
        "aat:300008347"
    ]
},
  "bbox": [],
  "geometry": {"coordinates":[3.433333,50.85],"type":"Point"}
}