{
  "id": 2198466,
  "type": "Feature",
  "properties": {
    "tgn:hierarchy":[
        "tgn:2198466",
        "tgn:1000001",
        "tgn:7012149",
        "tgn:2001026",
        "tgn:7007521",
        "tgn:7029392"
    ],
    "tgn:id":2198466,
    "tgn:name":"Browns Island",
    "tgn:placetype":[
        "aat:300008791"
    ]
},
  "bbox": [],
  "geometry": {"coordinates":[-91.2667,43.6333],"type":"Point"}
}