{
  "id": 7232489,
  "type": "Feature",
  "properties": {
    "tgn:hierarchy":[
        "tgn:7232489",
        "tgn:7002709",
        "tgn:7002705",
        "tgn:1000003",
        "tgn:1000074",
        "tgn:7029392"
    ],
    "tgn:id":7232489,
    "tgn:name":"Ka\u1e2ftsa",
    "tgn:placetype":[
        "aat:300008347"
    ]
},
  "bbox": [],
  "geometry": {"coordinates":[20.440833,39.448611],"type":"Point"}
}