{
  "id": 2167951,
  "type": "Feature",
  "properties": {
    "tgn:hierarchy":[
        "tgn:2167951",
        "tgn:1000001",
        "tgn:7012149",
        "tgn:2001270",
        "tgn:7007524",
        "tgn:7029392"
    ],
    "tgn:id":2167951,
    "tgn:name":"Big Drop Reservoir",
    "tgn:placetype":[
        "aat:300006191"
    ]
},
  "bbox": [],
  "geometry": {"coordinates":[-104.6333,46.8833],"type":"Point"}
}