<<<<<<< HEAD
{
  "id": 2400474,
  "type": "Feature",
  "properties": {
    "tgn:hierarchy":[
        "tgn:2400474",
        "tgn:1000001",
        "tgn:7012149",
        "tgn:2000642",
        "tgn:7007253",
        "tgn:7029392"
    ],
    "tgn:id":2400474,
    "tgn:name":"Horse Island",
    "tgn:placetype":[
        "aat:300008791"
    ]
},
  "bbox": [],
  "geometry": {"coordinates":[-90.65,41.4667],"type":"Point"}
}
=======
{"geometry":{"type":"Point","coordinates":[-90.650000,41.466700]},"type":"Feature","properties":{"hierarchy":["tgn:2400474","tgn:1000001","tgn:7012149","tgn:2000642","tgn:7007253","tgn:7029392"],"placetype":["aat:300008791"],"id":2400474,"name:xx":"Horse Island"}}
>>>>>>> 03f74aca74312dbeaf24d7e61306dd6a786dc3d0
