{
  "id": 2400474,
  "type": "Feature",
  "properties": {
    "tgn:hierarchy":[
        "tgn:2400474",
        "tgn:1000001",
        "tgn:7012149",
        "tgn:2000642",
        "tgn:7007253",
        "tgn:7029392"
    ],
    "tgn:id":2400474,
    "tgn:name":"Horse Island",
    "tgn:placetype":[
        "aat:300008791"
    ]
},
  "bbox": [],
  "geometry": {"coordinates":[-90.65,41.4667],"type":"Point"}
}