{
  "id": 2786568,
  "type": "Feature",
  "properties": {
    "tgn:hierarchy":[
        "tgn:2786568",
        "tgn:1000001",
        "tgn:7012149",
        "tgn:2000234",
        "tgn:7007158",
        "tgn:7029392"
    ],
    "tgn:id":2786568,
    "tgn:name":"Z K Reservoir",
    "tgn:placetype":[
        "aat:300006191"
    ]
},
  "bbox": [],
  "geometry": {"coordinates":[-108.0667,38.1833],"type":"Point"}
}