{
  "id": 2505652,
  "type": "Feature",
  "properties": {
    "tgn:hierarchy":[
        "tgn:2505652",
        "tgn:1000001",
        "tgn:2001432",
        "tgn:7012149",
        "tgn:7007566",
        "tgn:7029392"
    ],
    "tgn:id":2505652,
    "tgn:name":"Mendelsohn",
    "tgn:placetype":[
        "aat:300000390"
    ]
},
  "bbox": [],
  "geometry": {"coordinates":[-104.35,36.95],"type":"Point"}
}