{
  "id": 2060214,
  "type": "Feature",
  "properties": {
    "tgn:hierarchy":[
        "tgn:2060214",
        "tgn:1000001",
        "tgn:7012149",
        "tgn:1002402",
        "tgn:7007523",
        "tgn:7029392"
    ],
    "tgn:id":2060214,
    "tgn:name":"Redbird",
    "tgn:placetype":[
        "aat:300008347"
    ]
},
  "bbox": [],
  "geometry": {"coordinates":[-91.5667,38.1667],"type":"Point"}
}