{
  "id": 7462964,
  "type": "Feature",
  "properties": {
    "tgn:hierarchy":[
        "tgn:7462964",
        "tgn:7002445",
        "tgn:1000003",
        "tgn:7008154",
        "tgn:7008591",
        "tgn:7029392"
    ],
    "tgn:id":7462964,
    "tgn:name:en":"Loud, River",
    "tgn:placetype":[
        "aat:300008699"
    ]
},
  "bbox": [],
  "geometry": {"coordinates":[-2.533333,53.883333],"type":"Point"}
}