{
  "id": 2578638,
  "type": "Feature",
  "properties": {
    "tgn:hierarchy":[
        "tgn:2578638",
        "tgn:1000001",
        "tgn:7012149",
        "tgn:2001872",
        "tgn:7007825",
        "tgn:7029392"
    ],
    "tgn:id":2578638,
    "tgn:name":"Phillips",
    "tgn:placetype":[
        "aat:300008347"
    ]
},
  "bbox": [],
  "geometry": {"coordinates":[-88.2167,35.2333],"type":"Point"}
}