<<<<<<< HEAD
{
  "id": 2252872,
  "type": "Feature",
  "properties": {
    "tgn:hierarchy":[
        "tgn:2252872",
        "tgn:1000001",
        "tgn:7012149",
        "tgn:7029392"
    ],
    "tgn:id":2252872,
    "tgn:name":"Conowingo Creek",
    "tgn:placetype":[
        "aat:300008706"
    ]
},
  "bbox": [],
  "geometry": {"coordinates":[-76.2333,39.8833],"type":"Point"}
}
=======
{"geometry":{"type":"Point","coordinates":[-76.233300,39.883300]},"type":"Feature","properties":{"hierarchy":["tgn:2252872","tgn:1000001","tgn:7012149","tgn:7029392"],"placetype":["aat:300008706"],"id":2252872,"name:xx":"Conowingo Creek"}}
>>>>>>> 03f74aca74312dbeaf24d7e61306dd6a786dc3d0
