{
  "id": 1090072,
  "type": "Feature",
  "properties": {
    "tgn:hierarchy":[
        "tgn:1090072",
        "tgn:7001242",
        "tgn:7017738",
        "tgn:1000165",
        "tgn:7029392"
    ],
    "tgn:id":1090072,
    "tgn:name":"Kerewan",
    "tgn:placetype":[
        "aat:300008347",
        "aat:300387220",
        "aat:300008375"
    ]
},
  "bbox": [],
  "geometry": {"coordinates":[-16.1667,13.4833],"type":"Point"}
}