{
  "id": 2611824,
  "type": "Feature",
  "properties": {
    "tgn:hierarchy":[
        "tgn:2611824",
        "tgn:1000001",
        "tgn:7012149",
        "tgn:2002124",
        "tgn:7007827",
        "tgn:7029392"
    ],
    "tgn:id":2611824,
    "tgn:name":"Red Pine Creek",
    "tgn:placetype":[
        "aat:300008706"
    ]
},
  "bbox": [],
  "geometry": {"coordinates":[-109.6333,40.6833],"type":"Point"}
}