{
  "id": 7276002,
  "type": "Feature",
  "properties": {
    "tgn:hierarchy":[
        "tgn:7276002",
        "tgn:7016598",
        "tgn:1000049",
        "tgn:1000002",
        "tgn:7029392"
    ],
    "tgn:id":7276002,
    "tgn:name":"Toro Blanco",
    "tgn:placetype":[
        "aat:300008697"
    ]
},
  "bbox": [],
  "geometry": {"coordinates":[-67.616667,-23.45],"type":"Point"}
}