{
  "id": 2484030,
  "type": "Feature",
  "properties": {
    "tgn:hierarchy":[
        "tgn:2484030",
        "tgn:1000001",
        "tgn:2000466",
        "tgn:7012149",
        "tgn:7007250",
        "tgn:7029392"
    ],
    "tgn:id":2484030,
    "tgn:name":"Lau Creek",
    "tgn:placetype":[
        "aat:300008706"
    ]
},
  "bbox": [],
  "geometry": {"coordinates":[-111.1833,42.9333],"type":"Point"}
}