{
  "id": 7301284,
  "type": "Feature",
  "properties": {
    "tgn:hierarchy":[
        "tgn:7301284",
        "tgn:7002759",
        "tgn:7002845",
        "tgn:1000003",
        "tgn:1000095",
        "tgn:7029392"
    ],
    "tgn:id":7301284,
    "tgn:name":"Monegrillo, R\u00edo",
    "tgn:placetype":[
        "aat:300008699"
    ]
},
  "bbox": [],
  "geometry": {"coordinates":[-1.866667,41.316667],"type":"Point"}
}