{
  "id": 2446123,
  "type": "Feature",
  "properties": {
    "tgn:hierarchy":[
        "tgn:2446123",
        "tgn:1000001",
        "tgn:7012149",
        "tgn:1002396",
        "tgn:7007252",
        "tgn:7029392"
    ],
    "tgn:id":2446123,
    "tgn:name":"Levi Rouch Ditch",
    "tgn:placetype":[
        "aat:300006075"
    ]
},
  "bbox": [],
  "geometry": {"coordinates":[-86.2667,40.95],"type":"Point"}
}