{
  "id": 2002612,
  "type": "Feature",
  "properties": {
    "tgn:hierarchy":[
        "tgn:2002612",
        "tgn:7002659",
        "tgn:1000001",
        "tgn:7012149",
        "tgn:2000029",
        "tgn:7029392"
    ],
    "tgn:id":2002612,
    "tgn:name":"Belgreen",
    "tgn:placetype":[
        "aat:300008347"
    ]
},
  "bbox": [],
  "geometry": {"coordinates":[-87.85,34.4667],"type":"Point"}
}