{
  "id": 2345099,
  "type": "Feature",
  "properties": {
    "tgn:hierarchy":[
        "tgn:2345099",
        "tgn:1000001",
        "tgn:7012149",
        "tgn:7007158",
        "tgn:2000245",
        "tgn:7029392"
    ],
    "tgn:id":2345099,
    "tgn:name":"Gardner Park Reservoir",
    "tgn:placetype":[
        "aat:300006191"
    ]
},
  "bbox": [],
  "geometry": {"coordinates":[-107.0167,40.0333],"type":"Point"}
}