{
  "id": 2269813,
  "type": "Feature",
  "properties": {
    "tgn:hierarchy":[
        "tgn:2269813",
        "tgn:1000001",
        "tgn:7012149",
        "tgn:2001718",
        "tgn:7007708",
        "tgn:7029392"
    ],
    "tgn:id":2269813,
    "tgn:name":"Crows Nest Reservoir",
    "tgn:placetype":[
        "aat:300006191"
    ]
},
  "bbox": [],
  "geometry": {"coordinates":[-117.3833,42.6167],"type":"Point"}
}