{
  "id": 2263088,
  "type": "Feature",
  "properties": {
    "tgn:hierarchy":[
        "tgn:2263088",
        "tgn:1000001",
        "tgn:7012149",
        "tgn:2000883",
        "tgn:7007256",
        "tgn:7029392"
    ],
    "tgn:id":2263088,
    "tgn:name":"Cowpen Bayou",
    "tgn:placetype":[
        "aat:300008699"
    ]
},
  "bbox": [],
  "geometry": {"coordinates":[-92.0167,31.5333],"type":"Point"}
}