{
  "id": 2620457,
  "type": "Feature",
  "properties": {
    "tgn:hierarchy":[
        "tgn:2620457",
        "tgn:1000001",
        "tgn:7012149",
        "tgn:2000799",
        "tgn:7007255",
        "tgn:7029392"
    ],
    "tgn:id":2620457,
    "tgn:name":"River Slough",
    "tgn:placetype":[
        "aat:300008699"
    ]
},
  "bbox": [],
  "geometry": {"coordinates":[-87.5667,37.9167],"type":"Point"}
}