{
  "id": 1122997,
  "type": "Feature",
  "properties": {
    "tgn:hierarchy":[
        "tgn:1122997",
        "tgn:1001944",
        "tgn:1000047",
        "tgn:7002456",
        "tgn:1000002",
        "tgn:7029392"
    ],
    "tgn:id":1122997,
    "tgn:name":"Colorado",
    "tgn:placetype":[
        "aat:300008707"
    ]
},
  "bbox": [],
  "geometry": {"coordinates":[-62.3333,-13.05],"type":"Point"}
}