{
  "id": 2785463,
  "type": "Feature",
  "properties": {
    "tgn:hierarchy":[
        "tgn:2785463",
        "tgn:1000001",
        "tgn:7012149",
        "tgn:1002552",
        "tgn:7007920",
        "tgn:7029392"
    ],
    "tgn:id":2785463,
    "tgn:name":"Yeomalt Point",
    "tgn:placetype":[
        "aat:300008850"
    ]
},
  "bbox": [],
  "geometry": {"coordinates":[-122.4833,47.6333],"type":"Point"}
}