{
  "id": 2015655,
  "type": "Feature",
  "properties": {
    "tgn:hierarchy":[
        "tgn:2015655",
        "tgn:1000001",
        "tgn:7012149",
        "tgn:2000226",
        "tgn:7007158",
        "tgn:7029392"
    ],
    "tgn:id":2015655,
    "tgn:name":"Glen Comfort",
    "tgn:placetype":[
        "aat:300008347"
    ]
},
  "bbox": [],
  "geometry": {"coordinates":[-105.4333,40.3833],"type":"Point"}
}