{
  "id": 2001559,
  "type": "Feature",
  "properties": {
    "tgn:hierarchy":[
        "tgn:2001559",
        "tgn:1000001",
        "tgn:7012149",
        "tgn:7007705",
        "tgn:7029392"
    ],
    "tgn:id":2001559,
    "tgn:name":"Benson",
    "tgn:placetype":[
        "aat:300387145",
        "aat:300000771"
    ]
},
  "bbox": [],
  "geometry": {"coordinates":[-99.45,48.0333],"type":"Point"}
}