{
  "id": 7040908,
  "type": "Feature",
  "properties": {
    "tgn:hierarchy":[
        "tgn:7040908",
        "tgn:7003139",
        "tgn:1000003",
        "tgn:7003080",
        "tgn:1000080",
        "tgn:7029392"
    ],
    "tgn:id":7040908,
    "tgn:name":"Santi, Monte",
    "tgn:placetype":[
        "aat:300008777"
    ]
},
  "bbox": [],
  "geometry": {"coordinates":[11.95,42.216667],"type":"Point"}
}