{
  "id": 2175603,
  "type": "Feature",
  "properties": {
    "tgn:hierarchy":[
        "tgn:2175603",
        "tgn:1000001",
        "tgn:7012149",
        "tgn:2001457",
        "tgn:7007566",
        "tgn:7029392"
    ],
    "tgn:id":2175603,
    "tgn:name":"Black Copper Canyon",
    "tgn:placetype":[
        "aat:300008761"
    ]
},
  "bbox": [],
  "geometry": {"coordinates":[-105.35,36.6167],"type":"Point"}
}