{
  "id": 2111731,
  "type": "Feature",
  "properties": {
    "tgn:hierarchy":[
        "tgn:2111731",
        "tgn:1000001",
        "tgn:7012149",
        "tgn:1002913",
        "tgn:7007919",
        "tgn:7029392"
    ],
    "tgn:id":2111731,
    "tgn:name":"Falmouth",
    "tgn:placetype":[
        "aat:300008347"
    ]
},
  "bbox": [],
  "geometry": {"coordinates":[-77.4667,38.3167],"type":"Point"}
}