{
  "id": 2285293,
  "type": "Feature",
  "properties": {
    "tgn:hierarchy":[
        "tgn:2285293",
        "tgn:1000001",
        "tgn:2001265",
        "tgn:7012149",
        "tgn:7007524",
        "tgn:7029392"
    ],
    "tgn:id":2285293,
    "tgn:name":"Devils Canyon Reservoir",
    "tgn:placetype":[
        "aat:300006191"
    ]
},
  "bbox": [],
  "geometry": {"coordinates":[-104.25,45.6833],"type":"Point"}
}