<<<<<<< HEAD
{
  "id": 7110947,
  "type": "Feature",
  "properties": {
    "tgn:hierarchy":[
        "tgn:7110947",
        "tgn:7003669",
        "tgn:1000003",
        "tgn:7000084",
        "tgn:7029392"
    ],
    "tgn:id":7110947,
    "tgn:name":"Reichenbach bei Oberstdorf",
    "tgn:placetype":[
        "aat:300008347"
    ]
},
  "bbox": [],
  "geometry": {"coordinates":[10.3,47.45],"type":"Point"}
}
=======
{"geometry":{"type":"Point","coordinates":[10.300000,47.450000]},"type":"Feature","properties":{"hierarchy":["tgn:7110947","tgn:7003669","tgn:1000003","tgn:7000084","tgn:7029392"],"placetype":["aat:300008347"],"id":7110947,"name:xx":"Reichenbach bei Oberstdorf"}}
>>>>>>> 03f74aca74312dbeaf24d7e61306dd6a786dc3d0
