<<<<<<< HEAD
{
  "id": 2760283,
  "type": "Feature",
  "properties": {
    "tgn:hierarchy":[
        "tgn:2760283",
        "tgn:1000001",
        "tgn:7012149",
        "tgn:7007157",
        "tgn:2000188",
        "tgn:7029392"
    ],
    "tgn:id":2760283,
    "tgn:name":"West Fork Salt Creek",
    "tgn:placetype":[
        "aat:300008706"
    ]
},
  "bbox": [],
  "geometry": {"coordinates":[-122.2833,40.9333],"type":"Point"}
}
=======
{"geometry":{"type":"Point","coordinates":[-122.283300,40.933300]},"type":"Feature","properties":{"hierarchy":["tgn:2760283","tgn:1000001","tgn:7012149","tgn:7007157","tgn:2000188","tgn:7029392"],"placetype":["aat:300008706"],"id":2760283,"name:xx":"West Fork Salt Creek"}}
>>>>>>> 03f74aca74312dbeaf24d7e61306dd6a786dc3d0
