<<<<<<< HEAD
{
  "id": 7362614,
  "type": "Feature",
  "properties": {
    "tgn:hierarchy":[
        "tgn:7362614",
        "tgn:1000001",
        "tgn:7005599",
        "tgn:7005560",
        "tgn:7029392"
    ],
    "tgn:id":7362614,
    "tgn:name":"El Majagual",
    "tgn:placetype":[
        "aat:300008347"
    ]
},
  "bbox": [],
  "geometry": {"coordinates":[-97.4,21.15],"type":"Point"}
}
=======
{"geometry":{"type":"Point","coordinates":[-97.400000,21.150000]},"type":"Feature","properties":{"hierarchy":["tgn:7362614","tgn:1000001","tgn:7005599","tgn:7005560","tgn:7029392"],"placetype":["aat:300008347"],"id":7362614,"name:xx":"El Majagual"}}
>>>>>>> 03f74aca74312dbeaf24d7e61306dd6a786dc3d0
