{
  "id": 2700751,
  "type": "Feature",
  "properties": {
    "tgn:hierarchy":[
        "tgn:2700751",
        "tgn:1000001",
        "tgn:7012149",
        "tgn:2001153",
        "tgn:7007522",
        "tgn:7029392"
    ],
    "tgn:id":2700751,
    "tgn:name":"Suffer Brake",
    "tgn:placetype":[
        "aat:300008905"
    ]
},
  "bbox": [],
  "geometry": {"coordinates":[-90.2833,34.0333],"type":"Point"}
}