{
  "id": 7590895,
  "type": "Feature",
  "properties": {
    "tgn:hierarchy":[
        "tgn:7590895",
        "tgn:1000004",
        "tgn:7000198",
        "tgn:7000799",
        "tgn:7029392"
    ],
    "tgn:id":7590895,
    "tgn:name:en":"Zarla N\u0101r",
    "tgn:placetype":[
        "aat:300008699"
    ]
},
  "bbox": [],
  "geometry": {"coordinates":[73.911312,34.404126],"type":"Point"}
}