{
  "id": 2630663,
  "type": "Feature",
  "properties": {
    "tgn:hierarchy":[
        "tgn:2630663",
        "tgn:1000001",
        "tgn:7012149",
        "tgn:1003005",
        "tgn:7007520",
        "tgn:7029392"
    ],
    "tgn:id":2630663,
    "tgn:name":"Round Island",
    "tgn:placetype":[
        "aat:300008791"
    ]
},
  "bbox": [],
  "geometry": {"coordinates":[-83.1667,42.0833],"type":"Point"}
}