{
  "id": 2105894,
  "type": "Feature",
  "properties": {
    "tgn:hierarchy":[
        "tgn:2105894",
        "tgn:1000001",
        "tgn:7012149",
        "tgn:1002484",
        "tgn:7007826",
        "tgn:7029392"
    ],
    "tgn:id":2105894,
    "tgn:name":"Mambrino",
    "tgn:placetype":[
        "aat:300008347",
        "aat:300387210"
    ]
},
  "bbox": [],
  "geometry": {"coordinates":[-97.7333,32.3667],"type":"Point"}
}