{
  "id": 2764650,
  "type": "Feature",
  "properties": {
    "tgn:hierarchy":[
        "tgn:2764650",
        "tgn:1000001",
        "tgn:7012149",
        "tgn:1002718",
        "tgn:7007568",
        "tgn:7029392"
    ],
    "tgn:id":2764650,
    "tgn:name":"Whirlpool Point",
    "tgn:placetype":[
        "aat:300008850"
    ]
},
  "bbox": [],
  "geometry": {"coordinates":[-79.05,43.1167],"type":"Point"}
}