<<<<<<< HEAD
{
  "id": 2764650,
  "type": "Feature",
  "properties": {
    "tgn:hierarchy":[
        "tgn:2764650",
        "tgn:1000001",
        "tgn:7012149",
        "tgn:1002718",
        "tgn:7007568",
        "tgn:7029392"
    ],
    "tgn:id":2764650,
    "tgn:name":"Whirlpool Point",
    "tgn:placetype":[
        "aat:300008850"
    ]
},
  "bbox": [],
  "geometry": {"coordinates":[-79.05,43.1167],"type":"Point"}
}
=======
{"geometry":{"type":"Point","coordinates":[-79.050000,43.116700]},"type":"Feature","properties":{"hierarchy":["tgn:2764650","tgn:1000001","tgn:7012149","tgn:1002718","tgn:7007568","tgn:7029392"],"placetype":["aat:300008850"],"id":2764650,"name:xx":"Whirlpool Point"}}
>>>>>>> 03f74aca74312dbeaf24d7e61306dd6a786dc3d0
