{
  "id": 7480180,
  "type": "Feature",
  "properties": {
    "tgn:hierarchy":[
        "tgn:7480180",
        "tgn:1000004",
        "tgn:7490934",
        "tgn:1000141",
        "tgn:7029392"
    ],
    "tgn:id":7480180,
    "tgn:name":"Dagong Shan",
    "tgn:placetype":[
        "aat:300008777"
    ]
},
  "bbox": [],
  "geometry": {"coordinates":[120.441817,23.079494],"type":"Point"}
}