<<<<<<< HEAD
{
  "id": 7480180,
  "type": "Feature",
  "properties": {
    "tgn:hierarchy":[
        "tgn:7480180",
        "tgn:1000004",
        "tgn:7490934",
        "tgn:1000141",
        "tgn:7029392"
    ],
    "tgn:id":7480180,
    "tgn:name":"Dagong Shan",
    "tgn:placetype":[
        "aat:300008777"
    ]
},
  "bbox": [],
  "geometry": {"coordinates":[120.441817,23.079494],"type":"Point"}
}
=======
{"geometry":{"type":"Point","coordinates":[120.441817,23.079494]},"type":"Feature","properties":{"hierarchy":["tgn:7480180","tgn:1000004","tgn:7490934","tgn:1000141","tgn:7029392"],"placetype":["aat:300008777"],"id":7480180,"name:xx":"Dagong Shan"}}
>>>>>>> 03f74aca74312dbeaf24d7e61306dd6a786dc3d0
