{
  "id": 2002441,
  "type": "Feature",
  "properties": {
    "tgn:hierarchy":[
        "tgn:2002441",
        "tgn:7002659",
        "tgn:1000001",
        "tgn:7012149",
        "tgn:2000053",
        "tgn:7029392"
    ],
    "tgn:id":2002441,
    "tgn:name":"Aliceville",
    "tgn:placetype":[
        "aat:300008347"
    ]
},
  "bbox": [],
  "geometry": {"coordinates":[-88.15,33.1167],"type":"Point"}
}