<<<<<<< HEAD
{
  "id": 2155559,
  "type": "Feature",
  "properties": {
    "tgn:hierarchy":[
        "tgn:2155559",
        "tgn:1000001",
        "tgn:7012149",
        "tgn:7016020",
        "tgn:7007710",
        "tgn:7029392"
    ],
    "tgn:id":2155559,
    "tgn:name":"Bear Run",
    "tgn:placetype":[
        "aat:300008699"
    ]
},
  "bbox": [],
  "geometry": {"coordinates":[-78.6667,41.8167],"type":"Point"}
}
=======
{"geometry":{"type":"Point","coordinates":[-78.666700,41.816700]},"type":"Feature","properties":{"hierarchy":["tgn:2155559","tgn:1000001","tgn:7012149","tgn:7016020","tgn:7007710","tgn:7029392"],"placetype":["aat:300008699"],"id":2155559,"name:xx":"Bear Run"}}
>>>>>>> 03f74aca74312dbeaf24d7e61306dd6a786dc3d0
