{
  "id": 2646159,
  "type": "Feature",
  "properties": {
    "tgn:hierarchy":[
        "tgn:2646159",
        "tgn:1000001",
        "tgn:7012149",
        "tgn:2000481",
        "tgn:7007250",
        "tgn:7029392"
    ],
    "tgn:id":2646159,
    "tgn:name":"Sawpit Creek",
    "tgn:placetype":[
        "aat:300008706"
    ]
},
  "bbox": [],
  "geometry": {"coordinates":[-114.0333,45.2167],"type":"Point"}
}