{
  "id": 2348181,
  "type": "Feature",
  "properties": {
    "tgn:hierarchy":[
        "tgn:2348181",
        "tgn:1000001",
        "tgn:7012149",
        "tgn:2001716",
        "tgn:7007708",
        "tgn:7029392"
    ],
    "tgn:id":2348181,
    "tgn:name":"Gertrude Lake",
    "tgn:placetype":[
        "aat:300008680"
    ]
},
  "bbox": [],
  "geometry": {"coordinates":[-122.5333,43.5833],"type":"Point"}
}