{
  "id": 7055758,
  "type": "Feature",
  "properties": {
    "tgn:hierarchy":[
        "tgn:7055758",
        "tgn:7003131",
        "tgn:1000003",
        "tgn:7008516",
        "tgn:1000080",
        "tgn:7029392"
    ],
    "tgn:id":7055758,
    "tgn:name":"Lesignano di Palmia",
    "tgn:placetype":[
        "aat:300008347"
    ]
},
  "bbox": [],
  "geometry": {"coordinates":[10.116667,44.616667],"type":"Point"}
}