<<<<<<< HEAD
{
  "id": 2402543,
  "type": "Feature",
  "properties": {
    "tgn:hierarchy":[
        "tgn:2402543",
        "tgn:1000001",
        "tgn:2000922",
        "tgn:7012149",
        "tgn:7007515",
        "tgn:7029392"
    ],
    "tgn:id":2402543,
    "tgn:name":"Hospital Island",
    "tgn:placetype":[
        "aat:300008791"
    ]
},
  "bbox": [],
  "geometry": {"coordinates":[-68.7833,44.3667],"type":"Point"}
}
=======
{"geometry":{"type":"Point","coordinates":[-68.783300,44.366700]},"type":"Feature","properties":{"hierarchy":["tgn:2402543","tgn:1000001","tgn:2000922","tgn:7012149","tgn:7007515","tgn:7029392"],"placetype":["aat:300008791"],"id":2402543,"name:xx":"Hospital Island"}}
>>>>>>> 03f74aca74312dbeaf24d7e61306dd6a786dc3d0
