<<<<<<< HEAD
{
  "id": 7242478,
  "type": "Feature",
  "properties": {
    "tgn:hierarchy":[
        "tgn:7242478",
        "tgn:7007877",
        "tgn:1000003",
        "tgn:1000063",
        "tgn:4012014",
        "tgn:7029392"
    ],
    "tgn:id":7242478,
    "tgn:name":"Ferme de Long Pont",
    "tgn:placetype":[
        "aat:300000206"
    ]
},
  "bbox": [],
  "geometry": {"coordinates":[4.033333,50.583333],"type":"Point"}
}
=======
{"geometry":{"type":"Point","coordinates":[4.033333,50.583333]},"type":"Feature","properties":{"hierarchy":["tgn:7242478","tgn:7007877","tgn:1000003","tgn:1000063","tgn:4012014","tgn:7029392"],"placetype":["aat:300000206"],"id":7242478,"name:xx":"Ferme de Long Pont"}}
>>>>>>> 03f74aca74312dbeaf24d7e61306dd6a786dc3d0
