{
  "id": 7257974,
  "type": "Feature",
  "properties": {
    "tgn:concordances":{
        "gn:id":"2758697"
    },
    "tgn:hierarchy":[
        "tgn:7257974",
        "tgn:1000003",
        "tgn:7003624",
        "tgn:7016845",
        "tgn:7029392"
    ],
    "tgn:id":7257974,
    "tgn:name:nl":"Bolberg",
    "tgn:placetype":[
        "aat:300008347"
    ]
},
  "bbox": [],
  "geometry": {"coordinates":[4.933333,51.533333],"type":"Point"}
}