{
  "id": 7495362,
  "type": "Feature",
  "properties": {
    "tgn:hierarchy":[
        "tgn:7495362",
        "tgn:1000004",
        "tgn:7001013",
        "tgn:1000141",
        "tgn:7029392"
    ],
    "tgn:id":7495362,
    "tgn:name":"Quezikeng",
    "tgn:placetype":[
        "aat:300008777"
    ]
},
  "bbox": [],
  "geometry": {"coordinates":[121.307567,24.930296],"type":"Point"}
}