{
  "id": 7236167,
  "type": "Feature",
  "properties": {
    "tgn:hierarchy":[
        "tgn:7236167",
        "tgn:7002739",
        "tgn:7017076",
        "tgn:1000003",
        "tgn:1000074",
        "tgn:7029392"
    ],
    "tgn:id":7236167,
    "tgn:name":"\u00c1yios Vas\u00edlios",
    "tgn:placetype":[
        "aat:300008347"
    ]
},
  "bbox": [],
  "geometry": {"coordinates":[22.416667,37.516667],"type":"Point"}
}