{
  "id": 7325199,
  "type": "Feature",
  "properties": {
    "tgn:hierarchy":[
        "tgn:7325199",
        "tgn:7002826",
        "tgn:7001158",
        "tgn:1000003",
        "tgn:1000095",
        "tgn:7029392"
    ],
    "tgn:id":7325199,
    "tgn:name":"Santa Elena de Jamuz",
    "tgn:placetype":[
        "aat:300008347"
    ]
},
  "bbox": [],
  "geometry": {"coordinates":[-5.883333,42.266667],"type":"Point"}
}