<<<<<<< HEAD
{
  "id": 2409238,
  "type": "Feature",
  "properties": {
    "tgn:hierarchy":[
        "tgn:2409238",
        "tgn:1000001",
        "tgn:7012149",
        "tgn:2001283",
        "tgn:7007524",
        "tgn:7029392"
    ],
    "tgn:id":2409238,
    "tgn:name":"Icefloe Lake",
    "tgn:placetype":[
        "aat:300008680"
    ]
},
  "bbox": [],
  "geometry": {"coordinates":[-113.9,47.3667],"type":"Point"}
}
=======
{"geometry":{"type":"Point","coordinates":[-113.900000,47.366700]},"type":"Feature","properties":{"hierarchy":["tgn:2409238","tgn:1000001","tgn:7012149","tgn:2001283","tgn:7007524","tgn:7029392"],"placetype":["aat:300008680"],"id":2409238,"name:xx":"Icefloe Lake"}}
>>>>>>> 03f74aca74312dbeaf24d7e61306dd6a786dc3d0
