<<<<<<< HEAD
{
  "id": 2159857,
  "type": "Feature",
  "properties": {
    "tgn:hierarchy":[
        "tgn:2159857",
        "tgn:1000001",
        "tgn:7012149",
        "tgn:2002273",
        "tgn:7013961",
        "tgn:7029392"
    ],
    "tgn:id":2159857,
    "tgn:name":"Beech Creek",
    "tgn:placetype":[
        "aat:300008706"
    ]
},
  "bbox": [],
  "geometry": {"coordinates":[-81.8667,37.8833],"type":"Point"}
}
=======
{"geometry":{"type":"Point","coordinates":[-81.866700,37.883300]},"type":"Feature","properties":{"hierarchy":["tgn:2159857","tgn:1000001","tgn:7012149","tgn:2002273","tgn:7013961","tgn:7029392"],"placetype":["aat:300008706"],"id":2159857,"name:xx":"Beech Creek"}}
>>>>>>> 03f74aca74312dbeaf24d7e61306dd6a786dc3d0
