<<<<<<< HEAD
{
  "id": 2155106,
  "type": "Feature",
  "properties": {
    "tgn:hierarchy":[
        "tgn:2155106",
        "tgn:1000001",
        "tgn:7012149",
        "tgn:2001298",
        "tgn:7007524",
        "tgn:7029392"
    ],
    "tgn:id":2155106,
    "tgn:name":"Bear Lake",
    "tgn:placetype":[
        "aat:300008680"
    ]
},
  "bbox": [],
  "geometry": {"coordinates":[-112.9333,47.1],"type":"Point"}
}
=======
{"geometry":{"type":"Point","coordinates":[-112.933300,47.100000]},"type":"Feature","properties":{"hierarchy":["tgn:2155106","tgn:1000001","tgn:7012149","tgn:2001298","tgn:7007524","tgn:7029392"],"placetype":["aat:300008680"],"id":2155106,"name:xx":"Bear Lake"}}
>>>>>>> 03f74aca74312dbeaf24d7e61306dd6a786dc3d0
