{
  "id": 2427223,
  "type": "Feature",
  "properties": {
    "tgn:hierarchy":[
        "tgn:2427223",
        "tgn:1000001",
        "tgn:2156155",
        "tgn:7012149",
        "tgn:7007248",
        "tgn:7029392"
    ],
    "tgn:id":2427223,
    "tgn:name":"Jordan Company Lake",
    "tgn:placetype":[
        "aat:300006191"
    ]
},
  "bbox": [],
  "geometry": {"coordinates":[-85.0167,32.5667],"type":"Point"}
}