<<<<<<< HEAD
{
  "id": 2765340,
  "type": "Feature",
  "properties": {
    "tgn:hierarchy":[
        "tgn:2765340",
        "tgn:1000001",
        "tgn:7012149",
        "tgn:2000930",
        "tgn:7007515",
        "tgn:7029392"
    ],
    "tgn:id":2765340,
    "tgn:name":"Whitcombe Brook",
    "tgn:placetype":[
        "aat:300008699"
    ]
},
  "bbox": [],
  "geometry": {"coordinates":[-69.4833,44.8333],"type":"Point"}
}
=======
{"geometry":{"type":"Point","coordinates":[-69.483300,44.833300]},"type":"Feature","properties":{"hierarchy":["tgn:2765340","tgn:1000001","tgn:7012149","tgn:2000930","tgn:7007515","tgn:7029392"],"placetype":["aat:300008699"],"id":2765340,"name:xx":"Whitcombe Brook"}}
>>>>>>> 03f74aca74312dbeaf24d7e61306dd6a786dc3d0
