{
  "id": 2192883,
  "type": "Feature",
  "properties": {
    "tgn:hierarchy":[
        "tgn:2192883",
        "tgn:1000001",
        "tgn:7012149",
        "tgn:1002481",
        "tgn:7007520",
        "tgn:7029392"
    ],
    "tgn:id":2192883,
    "tgn:name":"Braxee Lake",
    "tgn:placetype":[
        "aat:300008680"
    ]
},
  "bbox": [],
  "geometry": {"coordinates":[-84.45,42.05],"type":"Point"}
}