{
  "id": 2691702,
  "type": "Feature",
  "properties": {
    "tgn:hierarchy":[
        "tgn:2691702",
        "tgn:1000001",
        "tgn:2000870",
        "tgn:7012149",
        "tgn:7007256",
        "tgn:7029392"
    ],
    "tgn:id":2691702,
    "tgn:name":"Starling",
    "tgn:placetype":[
        "aat:300008347"
    ]
},
  "bbox": [],
  "geometry": {"coordinates":[-91.1167,30.3167],"type":"Point"}
}