{
  "id": 1136675,
  "type": "Feature",
  "properties": {
    "tgn:hierarchy":[
        "tgn:1136675",
        "tgn:7002445",
        "tgn:1000003",
        "tgn:7008154",
        "tgn:7008591",
        "tgn:7029392"
    ],
    "tgn:id":1136675,
    "tgn:name:en":"Broughton",
    "tgn:placetype":[
        "aat:300008347",
        "aat:300008372"
    ]
},
  "bbox": [],
  "geometry": {"coordinates":[-2.733333,53.816667],"type":"Point"}
}