{
  "id": 7475160,
  "type": "Feature",
  "properties": {
    "tgn:hierarchy":[
        "tgn:7475160",
        "tgn:1000004",
        "tgn:7489179",
        "tgn:1000141",
        "tgn:7029392"
    ],
    "tgn:id":7475160,
    "tgn:name":"Tuchang Xi",
    "tgn:placetype":[
        "aat:300008699"
    ]
},
  "bbox": [],
  "geometry": {"coordinates":[121.4975,24.576944],"type":"Point"}
}