<<<<<<< HEAD
{
  "id": 2407379,
  "type": "Feature",
  "properties": {
    "tgn:hierarchy":[
        "tgn:2407379",
        "tgn:1002300",
        "tgn:1000001",
        "tgn:7012149",
        "tgn:7007564",
        "tgn:7029392"
    ],
    "tgn:id":2407379,
    "tgn:name":"Huntington Ravine",
    "tgn:placetype":[
        "aat:300008761"
    ]
},
  "bbox": [],
  "geometry": {"coordinates":[-71.2833,44.2667],"type":"Point"}
}
=======
{"geometry":{"type":"Point","coordinates":[-71.283300,44.266700]},"type":"Feature","properties":{"hierarchy":["tgn:2407379","tgn:1002300","tgn:1000001","tgn:7012149","tgn:7007564","tgn:7029392"],"placetype":["aat:300008761"],"id":2407379,"name:xx":"Huntington Ravine"}}
>>>>>>> 03f74aca74312dbeaf24d7e61306dd6a786dc3d0
