{
  "id": 2518752,
  "type": "Feature",
  "properties": {
    "tgn:hierarchy":[
        "tgn:2518752",
        "tgn:1000001",
        "tgn:7012149",
        "tgn:1002552",
        "tgn:7007920",
        "tgn:7029392"
    ],
    "tgn:id":2518752,
    "tgn:name":"Mitchell Point",
    "tgn:placetype":[
        "aat:300008850"
    ]
},
  "bbox": [],
  "geometry": {"coordinates":[-122.6167,47.5333],"type":"Point"}
}