{
  "id": 2421409,
  "type": "Feature",
  "properties": {
    "tgn:hierarchy":[
        "tgn:2421409",
        "tgn:7002659",
        "tgn:1000001",
        "tgn:7012149",
        "tgn:2000063",
        "tgn:7029392"
    ],
    "tgn:id":2421409,
    "tgn:name":"Jess Creek",
    "tgn:placetype":[
        "aat:300008706"
    ]
},
  "bbox": [],
  "geometry": {"coordinates":[-87.5167,33.8333],"type":"Point"}
}