{
  "id": 2202402,
  "type": "Feature",
  "properties": {
    "tgn:hierarchy":[
        "tgn:2202402",
        "tgn:1000001",
        "tgn:7012149",
        "tgn:2001723",
        "tgn:7007708",
        "tgn:7029392"
    ],
    "tgn:id":2202402,
    "tgn:name":"Buck Point Troughs",
    "tgn:placetype":[
        "aat:300008697"
    ]
},
  "bbox": [],
  "geometry": {"coordinates":[-119.9167,44.4667],"type":"Point"}
}