{
  "id": 2041565,
  "type": "Feature",
  "properties": {
    "tgn:hierarchy":[
        "tgn:2041565",
        "tgn:1000001",
        "tgn:7012149",
        "tgn:2000834",
        "tgn:7007255",
        "tgn:7029392"
    ],
    "tgn:id":2041565,
    "tgn:name":"Taffy",
    "tgn:placetype":[
        "aat:300008347",
        "aat:300387210"
    ]
},
  "bbox": [],
  "geometry": {"coordinates":[-86.8833,37.55],"type":"Point"}
}