{
  "id": 2364552,
  "type": "Feature",
  "properties": {
    "tgn:hierarchy":[
        "tgn:2364552",
        "tgn:1000001",
        "tgn:7012149",
        "tgn:2002276",
        "tgn:7013961",
        "tgn:7029392"
    ],
    "tgn:id":2364552,
    "tgn:name":"Green Valley Lakes",
    "tgn:placetype":[
        "aat:300006191"
    ]
},
  "bbox": [],
  "geometry": {"coordinates":[-80.5667,40.0167],"type":"Point"}
}