{
  "id": 7248248,
  "type": "Feature",
  "properties": {
    "tgn:hierarchy":[
        "tgn:7248248",
        "tgn:7003460",
        "tgn:1000003",
        "tgn:1000063",
        "tgn:4012014",
        "tgn:7029392"
    ],
    "tgn:id":7248248,
    "tgn:name":"Befve",
    "tgn:placetype":[
        "aat:300008347"
    ]
},
  "bbox": [],
  "geometry": {"coordinates":[5.85,50.666667],"type":"Point"}
}