{
  "id": 2573658,
  "type": "Feature",
  "properties": {
    "tgn:hierarchy":[
        "tgn:2573658",
        "tgn:1000001",
        "tgn:7006451",
        "tgn:7012149",
        "tgn:2000100",
        "tgn:7029392"
    ],
    "tgn:id":2573658,
    "tgn:name":"Peck Spring",
    "tgn:placetype":[
        "aat:300008697"
    ]
},
  "bbox": [],
  "geometry": {"coordinates":[-110.55,32.4667],"type":"Point"}
}