{
  "id": 2642946,
  "type": "Feature",
  "properties": {
    "tgn:hierarchy":[
        "tgn:2642946",
        "tgn:1000001",
        "tgn:7012149",
        "tgn:7007157",
        "tgn:1002684",
        "tgn:7029392"
    ],
    "tgn:id":2642946,
    "tgn:name":"Sandstone Ridge",
    "tgn:placetype":[
        "aat:300266640"
    ]
},
  "bbox": [],
  "geometry": {"coordinates":[-121.7167,36.6167],"type":"Point"}
}