{
  "id": 7035568,
  "type": "Feature",
  "properties": {
    "tgn:hierarchy":[
        "tgn:7035568",
        "tgn:7002991",
        "tgn:1000003",
        "tgn:7002997",
        "tgn:1000080",
        "tgn:7029392"
    ],
    "tgn:id":7035568,
    "tgn:name":"Pizzocco, Monte",
    "tgn:placetype":[
        "aat:300008795"
    ]
},
  "bbox": [],
  "geometry": {"coordinates":[12.008333,46.141389],"type":"Point"}
}