{
  "id": 2512846,
  "type": "Feature",
  "properties": {
    "tgn:hierarchy":[
        "tgn:2512846",
        "tgn:1000001",
        "tgn:7012149",
        "tgn:2001531",
        "tgn:7007709",
        "tgn:7029392"
    ],
    "tgn:id":2512846,
    "tgn:name":"Mill Creek",
    "tgn:placetype":[
        "aat:300008706"
    ]
},
  "bbox": [],
  "geometry": {"coordinates":[-82.0833,35.2333],"type":"Point"}
}