<<<<<<< HEAD
{
  "id": 7359986,
  "type": "Feature",
  "properties": {
    "tgn:hierarchy":[
        "tgn:7359986",
        "tgn:1000001",
        "tgn:1001960",
        "tgn:7005560",
        "tgn:7029392"
    ],
    "tgn:id":7359986,
    "tgn:name":"Concordia",
    "tgn:placetype":[
        "aat:300008347"
    ]
},
  "bbox": [],
  "geometry": {"coordinates":[-110.633333,31.0],"type":"Point"}
}
=======
{"geometry":{"type":"Point","coordinates":[-110.633333,31.000000]},"type":"Feature","properties":{"hierarchy":["tgn:7359986","tgn:1000001","tgn:1001960","tgn:7005560","tgn:7029392"],"placetype":["aat:300008347"],"id":7359986,"name:xx":"Concordia"}}
>>>>>>> 03f74aca74312dbeaf24d7e61306dd6a786dc3d0
