{
  "id": 1011312,
  "type": "Feature",
  "properties": {
    "tgn:hierarchy":[
        "tgn:1011312",
        "tgn:7015163",
        "tgn:1000003",
        "tgn:7003121",
        "tgn:1000080",
        "tgn:7029392"
    ],
    "tgn:id":1011312,
    "tgn:name":"Testa, Capo",
    "tgn:placetype":[
        "aat:300008850"
    ]
},
  "bbox": [],
  "geometry": {"coordinates":[9.133333,41.233333],"type":"Point"}
}