<<<<<<< HEAD
{
  "id": 2402329,
  "type": "Feature",
  "properties": {
    "tgn:hierarchy":[
        "tgn:2402329",
        "tgn:1000001",
        "tgn:7012149",
        "tgn:2000183",
        "tgn:7007157",
        "tgn:7029392"
    ],
    "tgn:id":2402329,
    "tgn:name":"Horton Creek",
    "tgn:placetype":[
        "aat:300008706"
    ]
},
  "bbox": [],
  "geometry": {"coordinates":[-118.6833,37.3],"type":"Point"}
}
=======
{"geometry":{"type":"Point","coordinates":[-118.683300,37.300000]},"type":"Feature","properties":{"hierarchy":["tgn:2402329","tgn:1000001","tgn:7012149","tgn:2000183","tgn:7007157","tgn:7029392"],"placetype":["aat:300008706"],"id":2402329,"name:xx":"Horton Creek"}}
>>>>>>> 03f74aca74312dbeaf24d7e61306dd6a786dc3d0
