{
  "id": 2377494,
  "type": "Feature",
  "properties": {
    "tgn:hierarchy":[
        "tgn:2377494",
        "tgn:1000001",
        "tgn:7012149",
        "tgn:7007157",
        "tgn:1002684",
        "tgn:7029392"
    ],
    "tgn:id":2377494,
    "tgn:name":"Harper Creek",
    "tgn:placetype":[
        "aat:300008706"
    ]
},
  "bbox": [],
  "geometry": {"coordinates":[-121.6333,36.55],"type":"Point"}
}