<<<<<<< HEAD
{
  "id": 2331147,
  "type": "Feature",
  "properties": {
    "tgn:hierarchy":[
        "tgn:2331147",
        "tgn:1000001",
        "tgn:7012149",
        "tgn:7007826",
        "tgn:7029392"
    ],
    "tgn:id":2331147,
    "tgn:name":"Flat Top",
    "tgn:placetype":[
        "aat:300008798"
    ]
},
  "bbox": [],
  "geometry": {"coordinates":[-99.0833,32.85],"type":"Point"}
}
=======
{"geometry":{"type":"Point","coordinates":[-99.083300,32.850000]},"type":"Feature","properties":{"hierarchy":["tgn:2331147","tgn:1000001","tgn:7012149","tgn:7007826","tgn:7029392"],"placetype":["aat:300008798"],"id":2331147,"name:xx":"Flat Top"}}
>>>>>>> 03f74aca74312dbeaf24d7e61306dd6a786dc3d0
