{
  "id": 2331147,
  "type": "Feature",
  "properties": {
    "tgn:hierarchy":[
        "tgn:2331147",
        "tgn:1000001",
        "tgn:7012149",
        "tgn:7007826",
        "tgn:7029392"
    ],
    "tgn:id":2331147,
    "tgn:name":"Flat Top",
    "tgn:placetype":[
        "aat:300008798"
    ]
},
  "bbox": [],
  "geometry": {"coordinates":[-99.0833,32.85],"type":"Point"}
}