<<<<<<< HEAD
{
  "id": 7110483,
  "type": "Feature",
  "properties": {
    "tgn:hierarchy":[
        "tgn:7110483",
        "tgn:7003669",
        "tgn:1000003",
        "tgn:7000084",
        "tgn:7029392"
    ],
    "tgn:id":7110483,
    "tgn:name":"Reichlingsried",
    "tgn:placetype":[
        "aat:300008347"
    ]
},
  "bbox": [],
  "geometry": {"coordinates":[10.933333,47.933333],"type":"Point"}
}
=======
{"geometry":{"type":"Point","coordinates":[10.933333,47.933333]},"type":"Feature","properties":{"hierarchy":["tgn:7110483","tgn:7003669","tgn:1000003","tgn:7000084","tgn:7029392"],"placetype":["aat:300008347"],"id":7110483,"name:xx":"Reichlingsried"}}
>>>>>>> 03f74aca74312dbeaf24d7e61306dd6a786dc3d0
