<<<<<<< HEAD
{
  "id": 2251198,
  "type": "Feature",
  "properties": {
    "tgn:hierarchy":[
        "tgn:2251198",
        "tgn:1000001",
        "tgn:7012149",
        "tgn:2000205",
        "tgn:7007158",
        "tgn:7029392"
    ],
    "tgn:id":2251198,
    "tgn:name":"Comanche Lake",
    "tgn:placetype":[
        "aat:300008680"
    ]
},
  "bbox": [],
  "geometry": {"coordinates":[-105.6,38.05],"type":"Point"}
}
=======
{"geometry":{"type":"Point","coordinates":[-105.600000,38.050000]},"type":"Feature","properties":{"hierarchy":["tgn:2251198","tgn:1000001","tgn:7012149","tgn:2000205","tgn:7007158","tgn:7029392"],"placetype":["aat:300008680"],"id":2251198,"name:xx":"Comanche Lake"}}
>>>>>>> 03f74aca74312dbeaf24d7e61306dd6a786dc3d0
