{
  "id": 7506499,
  "type": "Feature",
  "properties": {
    "tgn:hierarchy":[
        "tgn:7506499",
        "tgn:1009227",
        "tgn:7001866",
        "tgn:1000226",
        "tgn:1000006",
        "tgn:7029392"
    ],
    "tgn:id":7506499,
    "tgn:name:en":"Rosa, Mount",
    "tgn:placetype":[
        "aat:300008795"
    ]
},
  "bbox": [],
  "geometry": {"coordinates":[171.933333,-43.133333],"type":"Point"}
}