{
  "id": 2000310,
  "type": "Feature",
  "properties": {
    "tgn:hierarchy":[
        "tgn:2000310",
        "tgn:1000001",
        "tgn:7012149",
        "tgn:7007248",
        "tgn:7029392"
    ],
    "tgn:id":2000310,
    "tgn:name":"Calhoun",
    "tgn:placetype":[
        "aat:300387145",
        "aat:300000771"
    ]
},
  "bbox": [],
  "geometry": {"coordinates":[-84.6167,31.5333],"type":"Point"}
}