{
  "id": 7265493,
  "type": "Feature",
  "properties": {
    "tgn:hierarchy":[
        "tgn:7265493",
        "tgn:7003619",
        "tgn:1000003",
        "tgn:7016845",
        "tgn:7029392"
    ],
    "tgn:id":7265493,
    "tgn:name:nl":"Maalberg",
    "tgn:placetype":[
        "aat:300008777"
    ]
},
  "bbox": [],
  "geometry": {"coordinates":[5.816667,52.183333],"type":"Point"}
}