<<<<<<< HEAD
{
  "id": 7476078,
  "type": "Feature",
  "properties": {
    "tgn:hierarchy":[
        "tgn:7476078",
        "tgn:7488858",
        "tgn:1000004",
        "tgn:1000141",
        "tgn:7029392"
    ],
    "tgn:id":7476078,
    "tgn:name":"Fangzijiao",
    "tgn:placetype":[
        "aat:300008347"
    ]
},
  "bbox": [],
  "geometry": {"coordinates":[120.6968,23.8537],"type":"Point"}
}
=======
{"geometry":{"type":"Point","coordinates":[120.696800,23.853700]},"type":"Feature","properties":{"hierarchy":["tgn:7476078","tgn:7488858","tgn:1000004","tgn:1000141","tgn:7029392"],"placetype":["aat:300008347"],"id":7476078,"name:xx":"Fangzijiao"}}
>>>>>>> 03f74aca74312dbeaf24d7e61306dd6a786dc3d0
