{
  "id": 7201185,
  "type": "Feature",
  "properties": {
    "tgn:hierarchy":[
        "tgn:7201185",
        "tgn:1000003",
        "tgn:7003676",
        "tgn:7000084",
        "tgn:7029392"
    ],
    "tgn:id":7201185,
    "tgn:name":"Dumstorf",
    "tgn:placetype":[
        "aat:300008347"
    ]
},
  "bbox": [],
  "geometry": {"coordinates":[10.683333,53.183333],"type":"Point"}
}