{
  "id": 2672086,
  "type": "Feature",
  "properties": {
    "tgn:hierarchy":[
        "tgn:2672086",
        "tgn:1000001",
        "tgn:7012149",
        "tgn:1002486",
        "tgn:7007826",
        "tgn:7029392"
    ],
    "tgn:id":2672086,
    "tgn:name":"Smitherman Branch",
    "tgn:placetype":[
        "aat:300008699"
    ]
},
  "bbox": [],
  "geometry": {"coordinates":[-95.1833,31.3333],"type":"Point"}
}