<<<<<<< HEAD
{
  "id": 7472678,
  "type": "Feature",
  "properties": {
    "tgn:hierarchy":[
        "tgn:7472678",
        "tgn:1000004",
        "tgn:1000959",
        "tgn:1000141",
        "tgn:7029392"
    ],
    "tgn:id":7472678,
    "tgn:name":"Bao Qiao",
    "tgn:placetype":[
        "aat:300007836"
    ]
},
  "bbox": [],
  "geometry": {"coordinates":[121.553,24.9797],"type":"Point"}
}
=======
{"geometry":{"type":"Point","coordinates":[121.553000,24.979700]},"type":"Feature","properties":{"hierarchy":["tgn:7472678","tgn:1000004","tgn:1000959","tgn:1000141","tgn:7029392"],"placetype":["aat:300007836"],"id":7472678,"name:xx":"Bao Qiao"}}
>>>>>>> 03f74aca74312dbeaf24d7e61306dd6a786dc3d0
