{
  "id": 2321315,
  "type": "Feature",
  "properties": {
    "tgn:hierarchy":[
        "tgn:2321315",
        "tgn:1000001",
        "tgn:7012149",
        "tgn:2001117",
        "tgn:7007522",
        "tgn:7029392"
    ],
    "tgn:id":2321315,
    "tgn:name":"Fairchilds Creek",
    "tgn:placetype":[
        "aat:300008706"
    ]
},
  "bbox": [],
  "geometry": {"coordinates":[-91.05,31.7167],"type":"Point"}
}