{
  "id": 2202594,
  "type": "Feature",
  "properties": {
    "tgn:hierarchy":[
        "tgn:2202594",
        "tgn:1000001",
        "tgn:7012149",
        "tgn:2000484",
        "tgn:7007250",
        "tgn:7029392"
    ],
    "tgn:id":2202594,
    "tgn:name":"Buck Spring",
    "tgn:placetype":[
        "aat:300008697"
    ]
},
  "bbox": [],
  "geometry": {"coordinates":[-111.35,43.65],"type":"Point"}
}