{
  "id": 1032197,
  "type": "Feature",
  "properties": {
    "tgn:hierarchy":[
        "tgn:1032197",
        "tgn:1000003",
        "tgn:7002883",
        "tgn:1000070",
        "tgn:7029392"
    ],
    "tgn:id":1032197,
    "tgn:name":"Boissettes",
    "tgn:placetype":[
        "aat:300008347"
    ]
},
  "bbox": [],
  "geometry": {"coordinates":[2.6167,48.5167],"type":"Point"}
}