{
  "id": 7286533,
  "type": "Feature",
  "properties": {
    "tgn:hierarchy":[
        "tgn:7286533",
        "tgn:1001702",
        "tgn:1000049",
        "tgn:1000002",
        "tgn:7029392"
    ],
    "tgn:id":7286533,
    "tgn:name":"Hansen, Punta",
    "tgn:placetype":[
        "aat:300386846"
    ]
},
  "bbox": [],
  "geometry": {"coordinates":[-72.583333,-51.683333],"type":"Point"}
}