{
  "id": 2483634,
  "type": "Feature",
  "properties": {
    "tgn:hierarchy":[
        "tgn:2483634",
        "tgn:1000001",
        "tgn:7016172",
        "tgn:7012149",
        "tgn:2000139",
        "tgn:7029392"
    ],
    "tgn:id":2483634,
    "tgn:name":"Lateral A-2",
    "tgn:placetype":[
        "aat:300006075"
    ]
},
  "bbox": [],
  "geometry": {"coordinates":[-91.7667,34.25],"type":"Point"}
}