{
  "id": 2560624,
  "type": "Feature",
  "properties": {
    "tgn:hierarchy":[
        "tgn:2560624",
        "tgn:1000001",
        "tgn:7012149",
        "tgn:2001711",
        "tgn:7007708",
        "tgn:7029392"
    ],
    "tgn:id":2560624,
    "tgn:name":"Oregon Gulch Reservoir Number One",
    "tgn:placetype":[
        "aat:300006191"
    ]
},
  "bbox": [],
  "geometry": {"coordinates":[-122.3667,42.05],"type":"Point"}
}