{
  "id": 2522356,
  "type": "Feature",
  "properties": {
    "tgn:hierarchy":[
        "tgn:2522356",
        "tgn:1000001",
        "tgn:7006451",
        "tgn:7012149",
        "tgn:2000097",
        "tgn:7029392"
    ],
    "tgn:id":2522356,
    "tgn:name":"Moon Valley",
    "tgn:placetype":[
        "aat:300008761"
    ]
},
  "bbox": [],
  "geometry": {"coordinates":[-112.05,33.5833],"type":"Point"}
}