{
  "id": 7519972,
  "type": "Feature",
  "properties": {
    "tgn:hierarchy":[
        "tgn:7519972",
        "tgn:1009227",
        "tgn:1000226",
        "tgn:7016822",
        "tgn:1000006",
        "tgn:7029392"
    ],
    "tgn:id":7519972,
    "tgn:name:en":"Beaumont",
    "tgn:placetype":[
        "aat:300008795"
    ]
},
  "bbox": [],
  "geometry": {"coordinates":[168.016667,-45.866667],"type":"Point"}
}