{
  "id": 7109736,
  "type": "Feature",
  "properties": {
    "tgn:hierarchy":[
        "tgn:7109736",
        "tgn:7000096",
        "tgn:1000003",
        "tgn:7000084",
        "tgn:7029392"
    ],
    "tgn:id":7109736,
    "tgn:name":"Quappen-Berg",
    "tgn:placetype":[
        "aat:300008777"
    ]
},
  "bbox": [],
  "geometry": {"coordinates":[12.45,52.583333],"type":"Point"}
}