{
  "id": 7294729,
  "type": "Feature",
  "properties": {
    "tgn:hierarchy":[
        "tgn:7294729",
        "tgn:7002758",
        "tgn:7002823",
        "tgn:1000003",
        "tgn:1000095",
        "tgn:7029392"
    ],
    "tgn:id":7294729,
    "tgn:name":"Vega, Arroyo de la",
    "tgn:placetype":[
        "aat:300008699"
    ]
},
  "bbox": [],
  "geometry": {"coordinates":[-7.216667,37.316667],"type":"Point"}
}