{
  "id": 7280825,
  "type": "Feature",
  "properties": {
    "tgn:hierarchy":[
        "tgn:7280825",
        "tgn:1001702",
        "tgn:1000049",
        "tgn:1000002",
        "tgn:7029392"
    ],
    "tgn:id":7280825,
    "tgn:name":"Estancia Santa Mar\u00eda",
    "tgn:placetype":[
        "aat:300000241"
    ]
},
  "bbox": [],
  "geometry": {"coordinates":[-70.283333,-53.383333],"type":"Point"}
}