{
  "id": 1095152,
  "type": "Feature",
  "properties": {
    "tgn:hierarchy":[
        "tgn:1095152",
        "tgn:7001242",
        "tgn:7016833",
        "tgn:7001335",
        "tgn:7029392"
    ],
    "tgn:id":1095152,
    "tgn:name":"A\u1e0d-\u1e0cuhayr",
    "tgn:placetype":[
        "aat:300008347"
    ]
},
  "bbox": [],
  "geometry": {"coordinates":[32.008333,31.171389],"type":"Point"}
}