{
  "id": 2473947,
  "type": "Feature",
  "properties": {
    "tgn:hierarchy":[
        "tgn:2473947",
        "tgn:1000001",
        "tgn:7012149",
        "tgn:2000928",
        "tgn:7007515",
        "tgn:7029392"
    ],
    "tgn:id":2473947,
    "tgn:name":"Lower Hudson Pond",
    "tgn:placetype":[
        "aat:300008680"
    ]
},
  "bbox": [],
  "geometry": {"coordinates":[-69.0333,46.55],"type":"Point"}
}