<<<<<<< HEAD
{
  "id": 2767954,
  "type": "Feature",
  "properties": {
    "tgn:hierarchy":[
        "tgn:2767954",
        "tgn:1000001",
        "tgn:7012149",
        "tgn:7007523",
        "tgn:7029392"
    ],
    "tgn:id":2767954,
    "tgn:name":"Whitener Creek",
    "tgn:placetype":[
        "aat:300008706"
    ]
},
  "bbox": [],
  "geometry": {"coordinates":[-90.1333,37.45],"type":"Point"}
}
=======
{"geometry":{"type":"Point","coordinates":[-90.133300,37.450000]},"type":"Feature","properties":{"hierarchy":["tgn:2767954","tgn:1000001","tgn:7012149","tgn:7007523","tgn:7029392"],"placetype":["aat:300008706"],"id":2767954,"name:xx":"Whitener Creek"}}
>>>>>>> 03f74aca74312dbeaf24d7e61306dd6a786dc3d0
