{
  "id": 2767954,
  "type": "Feature",
  "properties": {
    "tgn:hierarchy":[
        "tgn:2767954",
        "tgn:1000001",
        "tgn:7012149",
        "tgn:7007523",
        "tgn:7029392"
    ],
    "tgn:id":2767954,
    "tgn:name":"Whitener Creek",
    "tgn:placetype":[
        "aat:300008706"
    ]
},
  "bbox": [],
  "geometry": {"coordinates":[-90.1333,37.45],"type":"Point"}
}