{
  "id": 7239212,
  "type": "Feature",
  "properties": {
    "tgn:hierarchy":[
        "tgn:7239212",
        "tgn:7003456",
        "tgn:1000003",
        "tgn:1000063",
        "tgn:7018236",
        "tgn:7029392"
    ],
    "tgn:id":7239212,
    "tgn:name":"Hofstede",
    "tgn:placetype":[
        "aat:300008347"
    ]
},
  "bbox": [],
  "geometry": {"coordinates":[5.083333,51.183333],"type":"Point"}
}