{
  "id": 2579011,
  "type": "Feature",
  "properties": {
    "tgn:hierarchy":[
        "tgn:2579011",
        "tgn:1000001",
        "tgn:7012149",
        "tgn:1002350",
        "tgn:7007157",
        "tgn:7029392"
    ],
    "tgn:id":2579011,
    "tgn:name":"Phipps Lake",
    "tgn:placetype":[
        "aat:300008680"
    ]
},
  "bbox": [],
  "geometry": {"coordinates":[-120.1333,38.95],"type":"Point"}
}