{
  "id": 1083164,
  "type": "Feature",
  "properties": {
    "tgn:hierarchy":[
        "tgn:1083164",
        "tgn:1000004",
        "tgn:1001227",
        "tgn:7029379",
        "tgn:7029392"
    ],
    "tgn:id":1083164,
    "tgn:name":"Ider",
    "tgn:placetype":[
        "aat:300008347"
    ]
},
  "bbox": [],
  "geometry": {"coordinates":[97.3833,48.2167],"type":"Point"}
}