{
  "id": 7257288,
  "type": "Feature",
  "properties": {
    "tgn:hierarchy":[
        "tgn:7257288",
        "tgn:7003616",
        "tgn:1000003",
        "tgn:7016845",
        "tgn:7029392"
    ],
    "tgn:id":7257288,
    "tgn:name:nl":"Blesdijkerheide",
    "tgn:placetype":[
        "aat:300386887"
    ]
},
  "bbox": [],
  "geometry": {"coordinates":[6.05,52.833333],"type":"Point"}
}