{
  "id": 7145862,
  "type": "Feature",
  "properties": {
    "tgn:hierarchy":[
        "tgn:7145862",
        "tgn:1000003",
        "tgn:7003688",
        "tgn:7000084",
        "tgn:7029392"
    ],
    "tgn:id":7145862,
    "tgn:name":"Klein Tastrup",
    "tgn:placetype":[
        "aat:300000206"
    ]
},
  "bbox": [],
  "geometry": {"coordinates":[9.466667,54.766667],"type":"Point"}
}