{
  "id": 7398999,
  "type": "Feature",
  "properties": {
    "tgn:hierarchy":[
        "tgn:7398999",
        "tgn:1000001",
        "tgn:1001893",
        "tgn:7005560",
        "tgn:7029392"
    ],
    "tgn:id":7398999,
    "tgn:name":"Tixmadej\u00e9 Chiquito",
    "tgn:placetype":[
        "aat:300008347"
    ]
},
  "bbox": [],
  "geometry": {"coordinates":[-99.9175,19.9675],"type":"Point"}
}