{
  "id": 2361048,
  "type": "Feature",
  "properties": {
    "tgn:hierarchy":[
        "tgn:2361048",
        "tgn:1000001",
        "tgn:7012149",
        "tgn:2001708",
        "tgn:7007708",
        "tgn:7029392"
    ],
    "tgn:id":2361048,
    "tgn:name":"Grassy Spring",
    "tgn:placetype":[
        "aat:300008697"
    ]
},
  "bbox": [],
  "geometry": {"coordinates":[-118.7333,44.6167],"type":"Point"}
}