{
  "id": 2189493,
  "type": "Feature",
  "properties": {
    "tgn:hierarchy":[
        "tgn:2189493",
        "tgn:7006450",
        "tgn:1000001",
        "tgn:7012149",
        "tgn:2000085",
        "tgn:7029392"
    ],
    "tgn:id":2189493,
    "tgn:name":"Bow Creek",
    "tgn:placetype":[
        "aat:300008706"
    ]
},
  "bbox": [],
  "geometry": {"coordinates":[-141.3833,64.2333],"type":"Point"}
}