{
  "id": 7098724,
  "type": "Feature",
  "properties": {
    "tgn:hierarchy":[
        "tgn:7098724",
        "tgn:1000003",
        "tgn:7003678",
        "tgn:7000084",
        "tgn:7029392"
    ],
    "tgn:id":7098724,
    "tgn:name":"Silber-Berg",
    "tgn:placetype":[
        "aat:300008777"
    ]
},
  "bbox": [],
  "geometry": {"coordinates":[9.416667,50.95],"type":"Point"}
}