{
  "id": 2408205,
  "type": "Feature",
  "properties": {
    "tgn:hierarchy":[
        "tgn:2408205",
        "tgn:1000001",
        "tgn:2000772",
        "tgn:7012149",
        "tgn:7007255",
        "tgn:7029392"
    ],
    "tgn:id":2408205,
    "tgn:name":"Hurst Fork",
    "tgn:placetype":[
        "aat:300008699"
    ]
},
  "bbox": [],
  "geometry": {"coordinates":[-83.4167,37.6833],"type":"Point"}
}