<<<<<<< HEAD
{
  "id": 2408205,
  "type": "Feature",
  "properties": {
    "tgn:hierarchy":[
        "tgn:2408205",
        "tgn:1000001",
        "tgn:2000772",
        "tgn:7012149",
        "tgn:7007255",
        "tgn:7029392"
    ],
    "tgn:id":2408205,
    "tgn:name":"Hurst Fork",
    "tgn:placetype":[
        "aat:300008699"
    ]
},
  "bbox": [],
  "geometry": {"coordinates":[-83.4167,37.6833],"type":"Point"}
}
=======
{"geometry":{"type":"Point","coordinates":[-83.416700,37.683300]},"type":"Feature","properties":{"hierarchy":["tgn:2408205","tgn:1000001","tgn:2000772","tgn:7012149","tgn:7007255","tgn:7029392"],"placetype":["aat:300008699"],"id":2408205,"name:xx":"Hurst Fork"}}
>>>>>>> 03f74aca74312dbeaf24d7e61306dd6a786dc3d0
