{
  "id": 2719944,
  "type": "Feature",
  "properties": {
    "tgn:hierarchy":[
        "tgn:2719944",
        "tgn:1000001",
        "tgn:2001600",
        "tgn:7012149",
        "tgn:7007705",
        "tgn:7029392"
    ],
    "tgn:id":2719944,
    "tgn:name":"Three V Crossing",
    "tgn:placetype":[
        "aat:300008347"
    ]
},
  "bbox": [],
  "geometry": {"coordinates":[-103.7833,46.55],"type":"Point"}
}