{
  "id": 2569151,
  "type": "Feature",
  "properties": {
    "tgn:hierarchy":[
        "tgn:2569151",
        "tgn:1000001",
        "tgn:1002665",
        "tgn:7012149",
        "tgn:7007517",
        "tgn:7029392"
    ],
    "tgn:id":2569151,
    "tgn:name":"Parkerville",
    "tgn:placetype":[
        "aat:300008347"
    ]
},
  "bbox": [],
  "geometry": {"coordinates":[-71.4333,42.55],"type":"Point"}
}