<<<<<<< HEAD
{
  "id": 2337819,
  "type": "Feature",
  "properties": {
    "tgn:hierarchy":[
        "tgn:2337819",
        "tgn:1000001",
        "tgn:7012149",
        "tgn:2002194",
        "tgn:7007919",
        "tgn:7029392"
    ],
    "tgn:id":2337819,
    "tgn:name":"Fox Den",
    "tgn:placetype":[
        "aat:300008746"
    ]
},
  "bbox": [],
  "geometry": {"coordinates":[-81.8667,36.7167],"type":"Point"}
}
=======
{"geometry":{"type":"Point","coordinates":[-81.866700,36.716700]},"type":"Feature","properties":{"hierarchy":["tgn:2337819","tgn:1000001","tgn:7012149","tgn:2002194","tgn:7007919","tgn:7029392"],"placetype":["aat:300008746"],"id":2337819,"name:xx":"Fox Den"}}
>>>>>>> 03f74aca74312dbeaf24d7e61306dd6a786dc3d0
