<<<<<<< HEAD
{
  "id": 2337052,
  "type": "Feature",
  "properties": {
    "tgn:hierarchy":[
        "tgn:2337052",
        "tgn:1000001",
        "tgn:7012149",
        "tgn:2000290",
        "tgn:7007240",
        "tgn:7029392"
    ],
    "tgn:id":2337052,
    "tgn:name":"Fourmile Point",
    "tgn:placetype":[
        "aat:300008850"
    ]
},
  "bbox": [],
  "geometry": {"coordinates":[-86.3,30.4167],"type":"Point"}
}
=======
{"geometry":{"type":"Point","coordinates":[-86.300000,30.416700]},"type":"Feature","properties":{"hierarchy":["tgn:2337052","tgn:1000001","tgn:7012149","tgn:2000290","tgn:7007240","tgn:7029392"],"placetype":["aat:300008850"],"id":2337052,"name:xx":"Fourmile Point"}}
>>>>>>> 03f74aca74312dbeaf24d7e61306dd6a786dc3d0
