<<<<<<< HEAD
{
  "id": 2409853,
  "type": "Feature",
  "properties": {
    "tgn:hierarchy":[
        "tgn:2409853",
        "tgn:1000001",
        "tgn:7012149",
        "tgn:2001246",
        "tgn:7007523",
        "tgn:7029392"
    ],
    "tgn:id":2409853,
    "tgn:name":"Illmo Branch",
    "tgn:placetype":[
        "aat:300008699"
    ]
},
  "bbox": [],
  "geometry": {"coordinates":[-89.5,37.2167],"type":"Point"}
}
=======
{"geometry":{"type":"Point","coordinates":[-89.500000,37.216700]},"type":"Feature","properties":{"hierarchy":["tgn:2409853","tgn:1000001","tgn:7012149","tgn:2001246","tgn:7007523","tgn:7029392"],"placetype":["aat:300008699"],"id":2409853,"name:xx":"Illmo Branch"}}
>>>>>>> 03f74aca74312dbeaf24d7e61306dd6a786dc3d0
