{
  "id": 7420454,
  "type": "Feature",
  "properties": {
    "tgn:hierarchy":[
        "tgn:7420454",
        "tgn:7005584",
        "tgn:1000001",
        "tgn:7005560",
        "tgn:7029392"
    ],
    "tgn:id":7420454,
    "tgn:name":"Ermita Las Cuchillas",
    "tgn:placetype":[
        "aat:300008347"
    ]
},
  "bbox": [],
  "geometry": {"coordinates":[-100.296667,21.337778],"type":"Point"}
}