{
  "id": 7424426,
  "type": "Feature",
  "properties": {
    "tgn:hierarchy":[
        "tgn:7424426",
        "tgn:1000001",
        "tgn:1001906",
        "tgn:7005560",
        "tgn:7029392"
    ],
    "tgn:id":7424426,
    "tgn:name":"Puerta del Macho",
    "tgn:placetype":[
        "aat:300008347"
    ]
},
  "bbox": [],
  "geometry": {"coordinates":[-105.49,22.290833],"type":"Point"}
}