{
  "id": 7498439,
  "type": "Feature",
  "properties": {
    "tgn:hierarchy":[
        "tgn:7498439",
        "tgn:1000957",
        "tgn:1000004",
        "tgn:1000141",
        "tgn:7029392"
    ],
    "tgn:id":7498439,
    "tgn:name":"Guanyinhu Shan",
    "tgn:placetype":[
        "aat:300008798"
    ]
},
  "bbox": [],
  "geometry": {"coordinates":[121.740736,25.082249],"type":"Point"}
}