{
  "id": 1049369,
  "type": "Feature",
  "properties": {
    "tgn:hierarchy":[
        "tgn:1049369",
        "tgn:1000003",
        "tgn:7024114",
        "tgn:7006366",
        "tgn:7029392"
    ],
    "tgn:id":1049369,
    "tgn:name":"Polan\u00f3w",
    "tgn:placetype":[
        "aat:300008347"
    ]
},
  "bbox": [],
  "geometry": {"coordinates":[16.6667,54.1167],"type":"Point"}
}