{
  "id": 1100621,
  "type": "Feature",
  "properties": {
    "tgn:hierarchy":[
        "tgn:1100621",
        "tgn:7016696",
        "tgn:1000004",
        "tgn:7000894",
        "tgn:1000120",
        "tgn:7029392"
    ],
    "tgn:id":1100621,
    "tgn:name":"Perry's Landing Monument",
    "tgn:placetype":[
        "aat:300000833"
    ]
},
  "bbox": [],
  "geometry": {"coordinates":[139.7167,35.2167],"type":"Point"}
}