<<<<<<< HEAD
{
  "id": 2763118,
  "type": "Feature",
  "properties": {
    "tgn:hierarchy":[
        "tgn:2763118",
        "tgn:1000001",
        "tgn:7012149",
        "tgn:2001864",
        "tgn:7007825",
        "tgn:7029392"
    ],
    "tgn:id":2763118,
    "tgn:name":"Westside",
    "tgn:placetype":[
        "aat:300008347"
    ]
},
  "bbox": [],
  "geometry": {"coordinates":[-87.2,35.1833],"type":"Point"}
}
=======
{"geometry":{"type":"Point","coordinates":[-87.200000,35.183300]},"type":"Feature","properties":{"hierarchy":["tgn:2763118","tgn:1000001","tgn:7012149","tgn:2001864","tgn:7007825","tgn:7029392"],"placetype":["aat:300008347"],"id":2763118,"name:xx":"Westside"}}
>>>>>>> 03f74aca74312dbeaf24d7e61306dd6a786dc3d0
