{
  "id": 2164531,
  "type": "Feature",
  "properties": {
    "tgn:hierarchy":[
        "tgn:2164531",
        "tgn:1000001",
        "tgn:2001425",
        "tgn:7012149",
        "tgn:7007564",
        "tgn:7029392"
    ],
    "tgn:id":2164531,
    "tgn:name":"Berry Pond Brook",
    "tgn:placetype":[
        "aat:300008699"
    ]
},
  "bbox": [],
  "geometry": {"coordinates":[-71.2833,43.2667],"type":"Point"}
}