<<<<<<< HEAD
{
  "id": 2155039,
  "type": "Feature",
  "properties": {
    "tgn:hierarchy":[
        "tgn:2155039",
        "tgn:1000001",
        "tgn:2000199",
        "tgn:7012149",
        "tgn:7007158",
        "tgn:7029392"
    ],
    "tgn:id":2155039,
    "tgn:name":"Bear Lake",
    "tgn:placetype":[
        "aat:300008680"
    ]
},
  "bbox": [],
  "geometry": {"coordinates":[-106.3167,38.9],"type":"Point"}
}
=======
{"geometry":{"type":"Point","coordinates":[-106.316700,38.900000]},"type":"Feature","properties":{"hierarchy":["tgn:2155039","tgn:1000001","tgn:2000199","tgn:7012149","tgn:7007158","tgn:7029392"],"placetype":["aat:300008680"],"id":2155039,"name:xx":"Bear Lake"}}
>>>>>>> 03f74aca74312dbeaf24d7e61306dd6a786dc3d0
