{
  "id": 2142503,
  "type": "Feature",
  "properties": {
    "tgn:hierarchy":[
        "tgn:2142503",
        "tgn:1000001",
        "tgn:7012149",
        "tgn:1002633",
        "tgn:7007252",
        "tgn:7029392"
    ],
    "tgn:id":2142503,
    "tgn:name":"Bacon Swamp",
    "tgn:placetype":[
        "aat:300008905"
    ]
},
  "bbox": [],
  "geometry": {"coordinates":[-86.1167,39.85],"type":"Point"}
}