{
  "id": 7066784,
  "type": "Feature",
  "properties": {
    "tgn:hierarchy":[
        "tgn:7066784",
        "tgn:7003669",
        "tgn:1000003",
        "tgn:7000084",
        "tgn:7029392"
    ],
    "tgn:id":7066784,
    "tgn:name":"Stocka",
    "tgn:placetype":[
        "aat:300000206"
    ]
},
  "bbox": [],
  "geometry": {"coordinates":[11.95,48.816667],"type":"Point"}
}