{
  "id": 2652058,
  "type": "Feature",
  "properties": {
    "tgn:hierarchy":[
        "tgn:2652058",
        "tgn:1000001",
        "tgn:7012149",
        "tgn:1002409",
        "tgn:7007157",
        "tgn:7029392"
    ],
    "tgn:id":2652058,
    "tgn:name":"Self Ridge",
    "tgn:placetype":[
        "aat:300266640"
    ]
},
  "bbox": [],
  "geometry": {"coordinates":[-122.6333,39.5833],"type":"Point"}
}