<<<<<<< HEAD
{
  "id": 2337289,
  "type": "Feature",
  "properties": {
    "tgn:hierarchy":[
        "tgn:2337289",
        "tgn:1000001",
        "tgn:7006451",
        "tgn:7012149",
        "tgn:2000097",
        "tgn:7029392"
    ],
    "tgn:id":2337289,
    "tgn:name":"Fourth of July Butte",
    "tgn:placetype":[
        "aat:300008798"
    ]
},
  "bbox": [],
  "geometry": {"coordinates":[-113.1,33.2667],"type":"Point"}
}
=======
{"geometry":{"type":"Point","coordinates":[-113.100000,33.266700]},"type":"Feature","properties":{"hierarchy":["tgn:2337289","tgn:1000001","tgn:7006451","tgn:7012149","tgn:2000097","tgn:7029392"],"placetype":["aat:300008798"],"id":2337289,"name:xx":"Fourth of July Butte"}}
>>>>>>> 03f74aca74312dbeaf24d7e61306dd6a786dc3d0
