{
  "id": 2184592,
  "type": "Feature",
  "properties": {
    "tgn:hierarchy":[
        "tgn:2184592",
        "tgn:1000001",
        "tgn:7012149",
        "tgn:2001882",
        "tgn:7007825",
        "tgn:7029392"
    ],
    "tgn:id":2184592,
    "tgn:name":"Bodane Ridge",
    "tgn:placetype":[
        "aat:300266640"
    ]
},
  "bbox": [],
  "geometry": {"coordinates":[-81.85,36.4833],"type":"Point"}
}