{
  "id": 2002459,
  "type": "Feature",
  "properties": {
    "tgn:hierarchy":[
        "tgn:2002459",
        "tgn:7002659",
        "tgn:1000001",
        "tgn:7012149",
        "tgn:2000027",
        "tgn:7029392"
    ],
    "tgn:id":2002459,
    "tgn:name":"Altoona",
    "tgn:placetype":[
        "aat:300008347"
    ]
},
  "bbox": [],
  "geometry": {"coordinates":[-86.3167,34.0167],"type":"Point"}
}