{
  "id": 1039521,
  "type": "Feature",
  "properties": {
    "tgn:hierarchy":[
        "tgn:1039521",
        "tgn:7003669",
        "tgn:1000003",
        "tgn:7000084",
        "tgn:7029392"
    ],
    "tgn:id":1039521,
    "tgn:name":"Heimbuchenthal",
    "tgn:placetype":[
        "aat:300008347"
    ]
},
  "bbox": [],
  "geometry": {"coordinates":[9.295556,49.889167],"type":"Point"}
}