{
  "id": 2099347,
  "type": "Feature",
  "properties": {
    "tgn:hierarchy":[
        "tgn:2099347",
        "tgn:1000001",
        "tgn:7012149",
        "tgn:2001902",
        "tgn:7007825",
        "tgn:7029392"
    ],
    "tgn:id":2099347,
    "tgn:name":"Gratio",
    "tgn:placetype":[
        "aat:300008347",
        "aat:300387210"
    ]
},
  "bbox": [],
  "geometry": {"coordinates":[-89.4167,36.25],"type":"Point"}
}