{
  "id": 2441860,
  "type": "Feature",
  "properties": {
    "tgn:hierarchy":[
        "tgn:2441860",
        "tgn:7006450",
        "tgn:1000001",
        "tgn:7012149",
        "tgn:2000089",
        "tgn:7029392"
    ],
    "tgn:id":2441860,
    "tgn:name":"Konedsin Minnkohwin Lake",
    "tgn:placetype":[
        "aat:300008680"
    ]
},
  "bbox": [],
  "geometry": {"coordinates":[-151.95,66.3667],"type":"Point"}
}