{
  "id": 2714505,
  "type": "Feature",
  "properties": {
    "tgn:hierarchy":[
        "tgn:2714505",
        "tgn:1000001",
        "tgn:1002260",
        "tgn:7012149",
        "tgn:7007920",
        "tgn:7029392"
    ],
    "tgn:id":2714505,
    "tgn:name":"Temple, The",
    "tgn:placetype":[
        "aat:300008798"
    ]
},
  "bbox": [],
  "geometry": {"coordinates":[-120.7667,47.4833],"type":"Point"}
}