{
  "id": 2723097,
  "type": "Feature",
  "properties": {
    "tgn:hierarchy":[
        "tgn:2723097",
        "tgn:1000001",
        "tgn:2000272",
        "tgn:7012149",
        "tgn:7007240",
        "tgn:7029392"
    ],
    "tgn:id":2723097,
    "tgn:name":"Titi Branch",
    "tgn:placetype":[
        "aat:300008699"
    ]
},
  "bbox": [],
  "geometry": {"coordinates":[-85.75,30.9167],"type":"Point"}
}