{
  "id": 2750017,
  "type": "Feature",
  "properties": {
    "tgn:hierarchy":[
        "tgn:2750017",
        "tgn:1000001",
        "tgn:7012149",
        "tgn:2000793",
        "tgn:7007255",
        "tgn:7029392"
    ],
    "tgn:id":2750017,
    "tgn:name":"Walter Creek",
    "tgn:placetype":[
        "aat:300008706"
    ]
},
  "bbox": [],
  "geometry": {"coordinates":[-86.45,37.5167],"type":"Point"}
}