{
  "id": 7084708,
  "type": "Feature",
  "properties": {
    "tgn:hierarchy":[
        "tgn:7084708",
        "tgn:1000003",
        "tgn:7003687",
        "tgn:7000084",
        "tgn:7029392"
    ],
    "tgn:id":7084708,
    "tgn:name":"Wei\u00dfes Moor",
    "tgn:placetype":[
        "aat:300386886"
    ]
},
  "bbox": [],
  "geometry": {"coordinates":[11.55,52.933333],"type":"Point"}
}