{
  "id": 2183449,
  "type": "Feature",
  "properties": {
    "tgn:hierarchy":[
        "tgn:2183449",
        "tgn:1000001",
        "tgn:7012149",
        "tgn:2001137",
        "tgn:7007522",
        "tgn:7029392"
    ],
    "tgn:id":2183449,
    "tgn:name":"Bluff Lake",
    "tgn:placetype":[
        "aat:300006191"
    ]
},
  "bbox": [],
  "geometry": {"coordinates":[-88.7667,33.2667],"type":"Point"}
}