{
  "id": 2728248,
  "type": "Feature",
  "properties": {
    "tgn:hierarchy":[
        "tgn:2728248",
        "tgn:1000001",
        "tgn:7012149",
        "tgn:2000963",
        "tgn:7007520",
        "tgn:7029392"
    ],
    "tgn:id":2728248,
    "tgn:name":"Traverse Point",
    "tgn:placetype":[
        "aat:300008850"
    ]
},
  "bbox": [],
  "geometry": {"coordinates":[-88.2167,47.1333],"type":"Point"}
}