{
  "id": 2317043,
  "type": "Feature",
  "properties": {
    "tgn:hierarchy":[
        "tgn:2317043",
        "tgn:1000001",
        "tgn:7012149",
        "tgn:1002545",
        "tgn:7007157",
        "tgn:7029392"
    ],
    "tgn:id":2317043,
    "tgn:name":"Emigrant Hill",
    "tgn:placetype":[
        "aat:300008798"
    ]
},
  "bbox": [],
  "geometry": {"coordinates":[-119.9667,35.7333],"type":"Point"}
}