<<<<<<< HEAD
{
  "id": 2766098,
  "type": "Feature",
  "properties": {
    "tgn:hierarchy":[
        "tgn:2766098",
        "tgn:1000001",
        "tgn:7012149",
        "tgn:7007526",
        "tgn:7029392"
    ],
    "tgn:id":2766098,
    "tgn:name":"White House Ditch",
    "tgn:placetype":[
        "aat:300006075"
    ]
},
  "bbox": [],
  "geometry": {"coordinates":[-116.6667,40.7],"type":"Point"}
}
=======
{"geometry":{"type":"Point","coordinates":[-116.666700,40.700000]},"type":"Feature","properties":{"hierarchy":["tgn:2766098","tgn:1000001","tgn:7012149","tgn:7007526","tgn:7029392"],"placetype":["aat:300006075"],"id":2766098,"name:xx":"White House Ditch"}}
>>>>>>> 03f74aca74312dbeaf24d7e61306dd6a786dc3d0
