{
  "id": 7520567,
  "type": "Feature",
  "properties": {
    "tgn:hierarchy":[
        "tgn:7520567",
        "tgn:7001242",
        "tgn:7016833",
        "tgn:1001418",
        "tgn:7029392"
    ],
    "tgn:id":7520567,
    "tgn:name:en":"Abid Rabbo, 'Alam",
    "tgn:placetype":[
        "aat:300008777"
    ]
},
  "bbox": [],
  "geometry": {"coordinates":[25.74375,30.382578],"type":"Point"}
}