<<<<<<< HEAD
{
  "id": 2407997,
  "type": "Feature",
  "properties": {
    "tgn:hierarchy":[
        "tgn:2407997",
        "tgn:1000001",
        "tgn:7012149",
        "tgn:2001901",
        "tgn:7007825",
        "tgn:7029392"
    ],
    "tgn:id":2407997,
    "tgn:name":"Hurricane Creek",
    "tgn:placetype":[
        "aat:300008706"
    ]
},
  "bbox": [],
  "geometry": {"coordinates":[-84.85,36.2333],"type":"Point"}
}
=======
{"geometry":{"type":"Point","coordinates":[-84.850000,36.233300]},"type":"Feature","properties":{"hierarchy":["tgn:2407997","tgn:1000001","tgn:7012149","tgn:2001901","tgn:7007825","tgn:7029392"],"placetype":["aat:300008706"],"id":2407997,"name:xx":"Hurricane Creek"}}
>>>>>>> 03f74aca74312dbeaf24d7e61306dd6a786dc3d0
