<<<<<<< HEAD
{
  "id": 7478138,
  "type": "Feature",
  "properties": {
    "tgn:hierarchy":[
        "tgn:7478138",
        "tgn:7487020",
        "tgn:1000004",
        "tgn:1000141",
        "tgn:7029392"
    ],
    "tgn:id":7478138,
    "tgn:name":"Laoqiping Ding",
    "tgn:placetype":[
        "aat:300008777"
    ]
},
  "bbox": [],
  "geometry": {"coordinates":[120.951473,24.693081],"type":"Point"}
}
=======
{"geometry":{"type":"Point","coordinates":[120.951473,24.693081]},"type":"Feature","properties":{"hierarchy":["tgn:7478138","tgn:7487020","tgn:1000004","tgn:1000141","tgn:7029392"],"placetype":["aat:300008777"],"id":7478138,"name:xx":"Laoqiping Ding"}}
>>>>>>> 03f74aca74312dbeaf24d7e61306dd6a786dc3d0
