{
  "id": 2269121,
  "type": "Feature",
  "properties": {
    "tgn:hierarchy":[
        "tgn:2269121",
        "tgn:1000001",
        "tgn:7012149",
        "tgn:2002125",
        "tgn:7007827",
        "tgn:7029392"
    ],
    "tgn:id":2269121,
    "tgn:name":"Crotons Mine",
    "tgn:placetype":[
        "aat:300000390"
    ]
},
  "bbox": [],
  "geometry": {"coordinates":[-111.4833,39.85],"type":"Point"}
}