{
  "id": 1020797,
  "type": "Feature",
  "properties": {
    "tgn:hierarchy":[
        "tgn:1020797",
        "tgn:7006246",
        "tgn:1000047",
        "tgn:7002455",
        "tgn:1000002",
        "tgn:7029392"
    ],
    "tgn:id":1020797,
    "tgn:name":"Barreirinhas",
    "tgn:placetype":[
        "aat:300008347"
    ]
},
  "bbox": [],
  "geometry": {"coordinates":[-42.85,-2.7667],"type":"Point"}
}