{
  "id": 1083750,
  "type": "Feature",
  "properties": {
    "tgn:hierarchy":[
        "tgn:1083750",
        "tgn:7000360",
        "tgn:1000004",
        "tgn:1000133",
        "tgn:7029392"
    ],
    "tgn:id":1083750,
    "tgn:name":"Rung\u0101ni",
    "tgn:placetype":[
        "aat:300008347"
    ]
},
  "bbox": [],
  "geometry": {"coordinates":[65.7167,26.6333],"type":"Point"}
}