{
  "id": 7259452,
  "type": "Feature",
  "properties": {
    "tgn:hierarchy":[
        "tgn:7259452",
        "tgn:7003460",
        "tgn:1000003",
        "tgn:1000063",
        "tgn:4012014",
        "tgn:7029392"
    ],
    "tgn:id":7259452,
    "tgn:name":"Bacsay, Ruisseau de",
    "tgn:placetype":[
        "aat:300008699"
    ]
},
  "bbox": [],
  "geometry": {"coordinates":[5.716667,50.683333],"type":"Point"}
}