<<<<<<< HEAD
{
  "id": 2401215,
  "type": "Feature",
  "properties": {
    "tgn:hierarchy":[
        "tgn:2401215",
        "tgn:1000001",
        "tgn:7012149",
        "tgn:2001291",
        "tgn:7007524",
        "tgn:7029392"
    ],
    "tgn:id":2401215,
    "tgn:name":"Horsehead Peak",
    "tgn:placetype":[
        "aat:300008798"
    ]
},
  "bbox": [],
  "geometry": {"coordinates":[-114.6333,47.1667],"type":"Point"}
}
=======
{"geometry":{"type":"Point","coordinates":[-114.633300,47.166700]},"type":"Feature","properties":{"hierarchy":["tgn:2401215","tgn:1000001","tgn:7012149","tgn:2001291","tgn:7007524","tgn:7029392"],"placetype":["aat:300008798"],"id":2401215,"name:xx":"Horsehead Peak"}}
>>>>>>> 03f74aca74312dbeaf24d7e61306dd6a786dc3d0
