{
  "id": 1124526,
  "type": "Feature",
  "properties": {
    "tgn:hierarchy":[
        "tgn:1124526",
        "tgn:1000004",
        "tgn:7001838",
        "tgn:1000111",
        "tgn:7029392"
    ],
    "tgn:id":1124526,
    "tgn:name":"Hailar He",
    "tgn:placetype":[
        "aat:300008707"
    ]
},
  "bbox": [],
  "geometry": {"coordinates":[118.3333,49.1667],"type":"Point"}
}