{
  "id": 1137868,
  "type": "Feature",
  "properties": {
    "tgn:hierarchy":[
        "tgn:1137868",
        "tgn:1000004",
        "tgn:7011584",
        "tgn:7018214",
        "tgn:7002435",
        "tgn:7029392"
    ],
    "tgn:id":1137868,
    "tgn:name":"Lovozero",
    "tgn:placetype":[
        "aat:300008347"
    ]
},
  "bbox": [],
  "geometry": {"coordinates":[35.1333,68.0167],"type":"Point"}
}