{
  "id": 7006007,
  "type": "Feature",
  "properties": {
    "tgn:hierarchy":[
        "tgn:7006007",
        "tgn:7003150",
        "tgn:1000003",
        "tgn:7003237",
        "tgn:1000080",
        "tgn:7029392"
    ],
    "tgn:id":7006007,
    "tgn:name":"Vimercate",
    "tgn:placetype":[
        "aat:300008347"
    ]
},
  "bbox": [],
  "geometry": {"coordinates":[9.366667,45.616667],"type":"Point"}
}