{
  "id": 7504247,
  "type": "Feature",
  "properties": {
    "tgn:hierarchy":[
        "tgn:7504247",
        "tgn:1009227",
        "tgn:1000226",
        "tgn:7016729",
        "tgn:1000006",
        "tgn:7029392"
    ],
    "tgn:id":7504247,
    "tgn:name:en":"Wakamarina River",
    "tgn:placetype":[
        "aat:300008699"
    ]
},
  "bbox": [],
  "geometry": {"coordinates":[173.666667,-41.283333],"type":"Point"}
}