{
  "id": 2214975,
  "type": "Feature",
  "properties": {
    "tgn:hierarchy":[
        "tgn:2214975",
        "tgn:1000001",
        "tgn:7012149",
        "tgn:2001714",
        "tgn:7007708",
        "tgn:7029392"
    ],
    "tgn:id":2214975,
    "tgn:name":"Calico Spring",
    "tgn:placetype":[
        "aat:300008697"
    ]
},
  "bbox": [],
  "geometry": {"coordinates":[-121.5667,42.3833],"type":"Point"}
}