<<<<<<< HEAD
{
  "id": 7058168,
  "type": "Feature",
  "properties": {
    "tgn:hierarchy":[
        "tgn:7058168",
        "tgn:7003006",
        "tgn:1000003",
        "tgn:7002997",
        "tgn:1000080",
        "tgn:7029392"
    ],
    "tgn:id":7058168,
    "tgn:name":"Bovo Moche",
    "tgn:placetype":[
        "aat:300006075"
    ]
},
  "bbox": [],
  "geometry": {"coordinates":[12.7,45.516667],"type":"Point"}
}
=======
{"geometry":{"type":"Point","coordinates":[12.700000,45.516667]},"type":"Feature","properties":{"hierarchy":["tgn:7058168","tgn:7003006","tgn:1000003","tgn:7002997","tgn:1000080","tgn:7029392"],"placetype":["aat:300006075"],"id":7058168,"name:xx":"Bovo Moche"}}
>>>>>>> 03f74aca74312dbeaf24d7e61306dd6a786dc3d0
