{
  "id": 7019559,
  "type": "Feature",
  "properties": {
    "tgn:hierarchy":[
        "tgn:7019559",
        "tgn:1000001",
        "tgn:7012149",
        "tgn:2001456",
        "tgn:7007566",
        "tgn:7029392"
    ],
    "tgn:id":7019559,
    "tgn:name":"Carthage",
    "tgn:placetype":[
        "aat:300008347"
    ]
},
  "bbox": [],
  "geometry": {"coordinates":[-106.65,33.8833],"type":"Point"}
}