{
  "id": 2228685,
  "type": "Feature",
  "properties": {
    "tgn:hierarchy":[
        "tgn:2228685",
        "tgn:1000001",
        "tgn:7012149",
        "tgn:2002071",
        "tgn:7007826",
        "tgn:7029392"
    ],
    "tgn:id":2228685,
    "tgn:name":"Cedar Draw",
    "tgn:placetype":[
        "aat:300008761"
    ]
},
  "bbox": [],
  "geometry": {"coordinates":[-100.7667,32.8833],"type":"Point"}
}