{
  "id": 2663106,
  "type": "Feature",
  "properties": {
    "tgn:hierarchy":[
        "tgn:2663106",
        "tgn:1000001",
        "tgn:7012149",
        "tgn:2001983",
        "tgn:7007826",
        "tgn:7029392"
    ],
    "tgn:id":2663106,
    "tgn:name":"Silver City",
    "tgn:placetype":[
        "aat:300008347"
    ]
},
  "bbox": [],
  "geometry": {"coordinates":[-95.9833,33.4833],"type":"Point"}
}