{
  "id": 2518821,
  "type": "Feature",
  "properties": {
    "tgn:hierarchy":[
        "tgn:2518821",
        "tgn:1000001",
        "tgn:2002243",
        "tgn:7012149",
        "tgn:7007920",
        "tgn:7029392"
    ],
    "tgn:id":2518821,
    "tgn:name":"Mitchell Spring",
    "tgn:placetype":[
        "aat:300008697"
    ]
},
  "bbox": [],
  "geometry": {"coordinates":[-118.3667,48.05],"type":"Point"}
}