{
  "id": 1067402,
  "type": "Feature",
  "properties": {
    "tgn:hierarchy":[
        "tgn:1067402",
        "tgn:1000004",
        "tgn:7002087",
        "tgn:1000111",
        "tgn:7029392"
    ],
    "tgn:id":1067402,
    "tgn:name":"Daisi",
    "tgn:placetype":[
        "aat:300008347"
    ]
},
  "bbox": [],
  "geometry": {"coordinates":[105.1333,29.2333],"type":"Point"}
}