{
  "id": 7476460,
  "type": "Feature",
  "properties": {
    "tgn:hierarchy":[
        "tgn:7476460",
        "tgn:7488858",
        "tgn:1000004",
        "tgn:1000141",
        "tgn:7029392"
    ],
    "tgn:id":7476460,
    "tgn:name":"Guangfu Qiao",
    "tgn:placetype":[
        "aat:300007836"
    ]
},
  "bbox": [],
  "geometry": {"coordinates":[120.807277,23.989868],"type":"Point"}
}