<<<<<<< HEAD
{
  "id": 7022819,
  "type": "Feature",
  "properties": {
    "tgn:hierarchy":[
        "tgn:7022819",
        "tgn:1000001",
        "tgn:7012149",
        "tgn:7007256",
        "tgn:7029392"
    ],
    "tgn:id":7022819,
    "tgn:name":"Dizzy Brake",
    "tgn:placetype":[
        "aat:300008905"
    ]
},
  "bbox": [],
  "geometry": {"coordinates":[-92.0167,32.1],"type":"Point"}
}
=======
{"geometry":{"type":"Point","coordinates":[-92.016700,32.100000]},"type":"Feature","properties":{"hierarchy":["tgn:7022819","tgn:1000001","tgn:7012149","tgn:7007256","tgn:7029392"],"placetype":["aat:300008905"],"id":7022819,"name:xx":"Dizzy Brake"}}
>>>>>>> 03f74aca74312dbeaf24d7e61306dd6a786dc3d0
