{
  "id": 2455195,
  "type": "Feature",
  "properties": {
    "tgn:hierarchy":[
        "tgn:2455195",
        "tgn:1000001",
        "tgn:7012149",
        "tgn:2000471",
        "tgn:7007250",
        "tgn:7029392"
    ],
    "tgn:id":2455195,
    "tgn:name":"Little Fiddler",
    "tgn:placetype":[
        "aat:300008798"
    ]
},
  "bbox": [],
  "geometry": {"coordinates":[-115.7167,43.4833],"type":"Point"}
}