{
  "id": 2468081,
  "type": "Feature",
  "properties": {
    "tgn:hierarchy":[
        "tgn:2468081",
        "tgn:1000001",
        "tgn:7012149",
        "tgn:2002021",
        "tgn:7007826",
        "tgn:7029392"
    ],
    "tgn:id":2468081,
    "tgn:name":"Long Lake",
    "tgn:placetype":[
        "aat:300008680"
    ]
},
  "bbox": [],
  "geometry": {"coordinates":[-100.25,29.5333],"type":"Point"}
}