{
  "id": 2013312,
  "type": "Feature",
  "properties": {
    "tgn:hierarchy":[
        "tgn:2013312",
        "tgn:1000001",
        "tgn:7012149",
        "tgn:2000181",
        "tgn:7007157",
        "tgn:7029392"
    ],
    "tgn:id":2013312,
    "tgn:name":"Pepperwood",
    "tgn:placetype":[
        "aat:300008347"
    ]
},
  "bbox": [],
  "geometry": {"coordinates":[-123.9833,40.4333],"type":"Point"}
}