{
  "id": 2312601,
  "type": "Feature",
  "properties": {
    "tgn:hierarchy":[
        "tgn:2312601",
        "tgn:1000001",
        "tgn:2001573",
        "tgn:7012149",
        "tgn:7007705",
        "tgn:7029392"
    ],
    "tgn:id":2312601,
    "tgn:name":"Ekre",
    "tgn:placetype":[
        "aat:300008347"
    ]
},
  "bbox": [],
  "geometry": {"coordinates":[-103.9667,46.7833],"type":"Point"}
}