<<<<<<< HEAD
{
  "id": 7115884,
  "type": "Feature",
  "properties": {
    "tgn:hierarchy":[
        "tgn:7115884",
        "tgn:1000003",
        "tgn:7003677",
        "tgn:7000084",
        "tgn:7029392"
    ],
    "tgn:id":7115884,
    "tgn:name":"Overschlag",
    "tgn:placetype":[
        "aat:300387200"
    ]
},
  "bbox": [],
  "geometry": {"coordinates":[6.116667,51.183333],"type":"Point"}
}
=======
{"geometry":{"type":"Point","coordinates":[6.116667,51.183333]},"type":"Feature","properties":{"hierarchy":["tgn:7115884","tgn:1000003","tgn:7003677","tgn:7000084","tgn:7029392"],"placetype":["aat:300387200"],"id":7115884,"name:xx":"Overschlag"}}
>>>>>>> 03f74aca74312dbeaf24d7e61306dd6a786dc3d0
