{
  "id": 7199653,
  "type": "Feature",
  "properties": {
    "tgn:hierarchy":[
        "tgn:7199653",
        "tgn:1000003",
        "tgn:7003689",
        "tgn:7000084",
        "tgn:7029392"
    ],
    "tgn:id":7199653,
    "tgn:name":"Drei Herrenstein",
    "tgn:placetype":[
        "aat:300008777"
    ]
},
  "bbox": [],
  "geometry": {"coordinates":[10.416667,51.066667],"type":"Point"}
}