{
  "id": 7580200,
  "type": "Feature",
  "properties": {
    "tgn:hierarchy":[
        "tgn:7580200",
        "tgn:1000004",
        "tgn:7000198",
        "tgn:7016788",
        "tgn:7029392"
    ],
    "tgn:id":7580200,
    "tgn:name:en":"Jh\u0101roli",
    "tgn:placetype":[
        "aat:300008347"
    ]
},
  "bbox": [],
  "geometry": {"coordinates":[73.028579,24.81961],"type":"Point"}
}