{
  "id": 7052436,
  "type": "Feature",
  "properties": {
    "tgn:hierarchy":[
        "tgn:7052436",
        "tgn:1003430",
        "tgn:1000003",
        "tgn:7003126",
        "tgn:1000080",
        "tgn:7029392"
    ],
    "tgn:id":7052436,
    "tgn:name":"Montita",
    "tgn:placetype":[
        "aat:300008347"
    ]
},
  "bbox": [],
  "geometry": {"coordinates":[6.983333,45.833333],"type":"Point"}
}