{
  "id": 7585516,
  "type": "Feature",
  "properties": {
    "tgn:hierarchy":[
        "tgn:7585516",
        "tgn:1000004",
        "tgn:7000198",
        "tgn:7000799",
        "tgn:7029392"
    ],
    "tgn:id":7585516,
    "tgn:name:en":"Nekpur",
    "tgn:placetype":[
        "aat:300008347"
    ]
},
  "bbox": [],
  "geometry": {"coordinates":[74.062141,33.266492],"type":"Point"}
}