{
  "id": 2100989,
  "type": "Feature",
  "properties": {
    "tgn:hierarchy":[
        "tgn:2100989",
        "tgn:1000001",
        "tgn:7012149",
        "tgn:2001901",
        "tgn:7007825",
        "tgn:7029392"
    ],
    "tgn:id":2100989,
    "tgn:name":"Pilot Mountain",
    "tgn:placetype":[
        "aat:300008347"
    ]
},
  "bbox": [],
  "geometry": {"coordinates":[-84.65,36.1833],"type":"Point"}
}