<<<<<<< HEAD
{
  "id": 2768742,
  "type": "Feature",
  "properties": {
    "tgn:hierarchy":[
        "tgn:2768742",
        "tgn:1000001",
        "tgn:7012149",
        "tgn:7007708",
        "tgn:7029392"
    ],
    "tgn:id":2768742,
    "tgn:name":"Whitman Creek",
    "tgn:placetype":[
        "aat:300008706"
    ]
},
  "bbox": [],
  "geometry": {"coordinates":[-122.2667,42.6667],"type":"Point"}
}
=======
{"geometry":{"type":"Point","coordinates":[-122.266700,42.666700]},"type":"Feature","properties":{"hierarchy":["tgn:2768742","tgn:1000001","tgn:7012149","tgn:7007708","tgn:7029392"],"placetype":["aat:300008706"],"id":2768742,"name:xx":"Whitman Creek"}}
>>>>>>> 03f74aca74312dbeaf24d7e61306dd6a786dc3d0
