<<<<<<< HEAD
{
  "id": 7353795,
  "type": "Feature",
  "properties": {
    "tgn:hierarchy":[
        "tgn:7353795",
        "tgn:1000001",
        "tgn:7005589",
        "tgn:7005560",
        "tgn:7029392"
    ],
    "tgn:id":7353795,
    "tgn:name":"Anteojitos",
    "tgn:placetype":[
        "aat:300008347"
    ]
},
  "bbox": [],
  "geometry": {"coordinates":[-99.881944,24.22],"type":"Point"}
}
=======
{"geometry":{"type":"Point","coordinates":[-99.881944,24.220000]},"type":"Feature","properties":{"hierarchy":["tgn:7353795","tgn:1000001","tgn:7005589","tgn:7005560","tgn:7029392"],"placetype":["aat:300008347"],"id":7353795,"name:xx":"Anteojitos"}}
>>>>>>> 03f74aca74312dbeaf24d7e61306dd6a786dc3d0
