<<<<<<< HEAD
{
  "id": 2405247,
  "type": "Feature",
  "properties": {
    "tgn:hierarchy":[
        "tgn:2405247",
        "tgn:1000001",
        "tgn:7012149",
        "tgn:2002248",
        "tgn:7007920",
        "tgn:7029392"
    ],
    "tgn:id":2405247,
    "tgn:name":"Huff Lake",
    "tgn:placetype":[
        "aat:300008680"
    ]
},
  "bbox": [],
  "geometry": {"coordinates":[-117.05,48.7333],"type":"Point"}
}
=======
{"geometry":{"type":"Point","coordinates":[-117.050000,48.733300]},"type":"Feature","properties":{"hierarchy":["tgn:2405247","tgn:1000001","tgn:7012149","tgn:2002248","tgn:7007920","tgn:7029392"],"placetype":["aat:300008680"],"id":2405247,"name:xx":"Huff Lake"}}
>>>>>>> 03f74aca74312dbeaf24d7e61306dd6a786dc3d0
