{
  "id": 7519623,
  "type": "Feature",
  "properties": {
    "tgn:hierarchy":[
        "tgn:7519623",
        "tgn:1009227",
        "tgn:1000226",
        "tgn:7016822",
        "tgn:1000006",
        "tgn:7029392"
    ],
    "tgn:id":7519623,
    "tgn:name:en":"Aan River",
    "tgn:placetype":[
        "aat:300008699"
    ]
},
  "bbox": [],
  "geometry": {"coordinates":[166.983333,-46.233333],"type":"Point"}
}