{
  "id": 2343578,
  "type": "Feature",
  "properties": {
    "tgn:hierarchy":[
        "tgn:2343578",
        "tgn:1000001",
        "tgn:7012149",
        "tgn:7007157",
        "tgn:1003050",
        "tgn:7029392"
    ],
    "tgn:id":2343578,
    "tgn:name":"Galena Hill",
    "tgn:placetype":[
        "aat:300008798"
    ]
},
  "bbox": [],
  "geometry": {"coordinates":[-121.05,39.4667],"type":"Point"}
}