{
  "id": 2297971,
  "type": "Feature",
  "properties": {
    "tgn:hierarchy":[
        "tgn:2297971",
        "tgn:1000001",
        "tgn:7019982",
        "tgn:7012149",
        "tgn:7007517",
        "tgn:7029392"
    ],
    "tgn:id":2297971,
    "tgn:name":"Dry Knoll",
    "tgn:placetype":[
        "aat:300008798"
    ]
},
  "bbox": [],
  "geometry": {"coordinates":[-72.6167,42.2667],"type":"Point"}
}