<<<<<<< HEAD
{
  "id": 7357597,
  "type": "Feature",
  "properties": {
    "tgn:hierarchy":[
        "tgn:7357597",
        "tgn:1000001",
        "tgn:7005590",
        "tgn:7005560",
        "tgn:7029392"
    ],
    "tgn:id":7357597,
    "tgn:name":"Corrales",
    "tgn:placetype":[
        "aat:300008347"
    ]
},
  "bbox": [],
  "geometry": {"coordinates":[-101.566667,20.3],"type":"Point"}
}
=======
{"geometry":{"type":"Point","coordinates":[-101.566667,20.300000]},"type":"Feature","properties":{"hierarchy":["tgn:7357597","tgn:1000001","tgn:7005590","tgn:7005560","tgn:7029392"],"placetype":["aat:300008347"],"id":7357597,"name:xx":"Corrales"}}
>>>>>>> 03f74aca74312dbeaf24d7e61306dd6a786dc3d0
