{
  "id": 2709004,
  "type": "Feature",
  "properties": {
    "tgn:hierarchy":[
        "tgn:2709004",
        "tgn:1000001",
        "tgn:2002244",
        "tgn:7012149",
        "tgn:7007920",
        "tgn:7029392"
    ],
    "tgn:id":2709004,
    "tgn:name":"T Lake",
    "tgn:placetype":[
        "aat:300008680"
    ]
},
  "bbox": [],
  "geometry": {"coordinates":[-118.9333,46.6333],"type":"Point"}
}