{
  "id": 7097729,
  "type": "Feature",
  "properties": {
    "tgn:hierarchy":[
        "tgn:7097729",
        "tgn:1000003",
        "tgn:7003688",
        "tgn:7000084",
        "tgn:7029392"
    ],
    "tgn:id":7097729,
    "tgn:name":"Soramsh\u00f6rn",
    "tgn:placetype":[
        "aat:300000206"
    ]
},
  "bbox": [],
  "geometry": {"coordinates":[8.883333,54.366667],"type":"Point"}
}