{
  "id": 2385370,
  "type": "Feature",
  "properties": {
    "tgn:hierarchy":[
        "tgn:2385370",
        "tgn:1002716",
        "tgn:1000001",
        "tgn:7012149",
        "tgn:7007711",
        "tgn:7029392"
    ],
    "tgn:id":2385370,
    "tgn:name":"Hen Island",
    "tgn:placetype":[
        "aat:300008791"
    ]
},
  "bbox": [],
  "geometry": {"coordinates":[-71.2167,41.6167],"type":"Point"}
}