<<<<<<< HEAD
{
  "id": 2336181,
  "type": "Feature",
  "properties": {
    "tgn:hierarchy":[
        "tgn:2336181",
        "tgn:1000001",
        "tgn:7012149",
        "tgn:2002379",
        "tgn:7007923",
        "tgn:7029392"
    ],
    "tgn:id":2336181,
    "tgn:name":"Foster Number 3 Reservoir",
    "tgn:placetype":[
        "aat:300006191"
    ]
},
  "bbox": [],
  "geometry": {"coordinates":[-109.1833,44.2667],"type":"Point"}
}
=======
{"geometry":{"type":"Point","coordinates":[-109.183300,44.266700]},"type":"Feature","properties":{"hierarchy":["tgn:2336181","tgn:1000001","tgn:7012149","tgn:2002379","tgn:7007923","tgn:7029392"],"placetype":["aat:300006191"],"id":2336181,"name:xx":"Foster Number 3 Reservoir"}}
>>>>>>> 03f74aca74312dbeaf24d7e61306dd6a786dc3d0
