{
  "id": 2336181,
  "type": "Feature",
  "properties": {
    "tgn:hierarchy":[
        "tgn:2336181",
        "tgn:1000001",
        "tgn:7012149",
        "tgn:2002379",
        "tgn:7007923",
        "tgn:7029392"
    ],
    "tgn:id":2336181,
    "tgn:name":"Foster Number 3 Reservoir",
    "tgn:placetype":[
        "aat:300006191"
    ]
},
  "bbox": [],
  "geometry": {"coordinates":[-109.1833,44.2667],"type":"Point"}
}