{
  "id": 2027967,
  "type": "Feature",
  "properties": {
    "tgn:hierarchy":[
        "tgn:2027967",
        "tgn:1000001",
        "tgn:7012149",
        "tgn:2000515",
        "tgn:7007251",
        "tgn:7029392"
    ],
    "tgn:id":2027967,
    "tgn:name":"Ganntown",
    "tgn:placetype":[
        "aat:300008347"
    ]
},
  "bbox": [],
  "geometry": {"coordinates":[-88.7833,37.35],"type":"Point"}
}