{
  "id": 7076028,
  "type": "Feature",
  "properties": {
    "tgn:hierarchy":[
        "tgn:7076028",
        "tgn:1000003",
        "tgn:7003676",
        "tgn:7000084",
        "tgn:7029392"
    ],
    "tgn:id":7076028,
    "tgn:name":"Lucie",
    "tgn:placetype":[
        "aat:300055621"
    ]
},
  "bbox": [],
  "geometry": {"coordinates":[11.15,53.033333],"type":"Point"}
}