{
  "id": 2651058,
  "type": "Feature",
  "properties": {
    "tgn:hierarchy":[
        "tgn:2651058",
        "tgn:1000001",
        "tgn:7012149",
        "tgn:1002440",
        "tgn:7007568",
        "tgn:7029392"
    ],
    "tgn:id":2651058,
    "tgn:name":"Second Stillwater",
    "tgn:placetype":[
        "aat:300008680"
    ]
},
  "bbox": [],
  "geometry": {"coordinates":[-74.7667,43.5833],"type":"Point"}
}