{
  "id": 2437541,
  "type": "Feature",
  "properties": {
    "tgn:hierarchy":[
        "tgn:2437541",
        "tgn:1000001",
        "tgn:7012149",
        "tgn:1002784",
        "tgn:7007706",
        "tgn:7029392"
    ],
    "tgn:id":2437541,
    "tgn:name":"Kinderhook",
    "tgn:placetype":[
        "aat:300008347"
    ]
},
  "bbox": [],
  "geometry": {"coordinates":[-83.0667,39.5667],"type":"Point"}
}