<<<<<<< HEAD
{
  "id": 7172971,
  "type": "Feature",
  "properties": {
    "tgn:hierarchy":[
        "tgn:7172971",
        "tgn:7003669",
        "tgn:1000003",
        "tgn:7000084",
        "tgn:7029392"
    ],
    "tgn:id":7172971,
    "tgn:name":"Gro\u00dfsch\u00f6nbrunn",
    "tgn:placetype":[
        "aat:300008347"
    ]
},
  "bbox": [],
  "geometry": {"coordinates":[11.883333,49.566667],"type":"Point"}
}
=======
{"geometry":{"type":"Point","coordinates":[11.883333,49.566667]},"type":"Feature","properties":{"hierarchy":["tgn:7172971","tgn:7003669","tgn:1000003","tgn:7000084","tgn:7029392"],"placetype":["aat:300008347"],"id":7172971,"name:xx":"Gro\u00dfsch\u00f6nbrunn"}}
>>>>>>> 03f74aca74312dbeaf24d7e61306dd6a786dc3d0
