{
  "id": 2293194,
  "type": "Feature",
  "properties": {
    "tgn:hierarchy":[
        "tgn:2293194",
        "tgn:1000001",
        "tgn:2001471",
        "tgn:7012149",
        "tgn:7007709",
        "tgn:7029392"
    ],
    "tgn:id":2293194,
    "tgn:name":"Double Branch",
    "tgn:placetype":[
        "aat:300008699"
    ]
},
  "bbox": [],
  "geometry": {"coordinates":[-78.4167,34.6167],"type":"Point"}
}