{
  "id": 2768039,
  "type": "Feature",
  "properties": {
    "tgn:hierarchy":[
        "tgn:2768039",
        "tgn:1000001",
        "tgn:7012149",
        "tgn:2001888",
        "tgn:7007825",
        "tgn:7029392"
    ],
    "tgn:id":2768039,
    "tgn:name":"Whiteoak Swamp",
    "tgn:placetype":[
        "aat:300008905"
    ]
},
  "bbox": [],
  "geometry": {"coordinates":[-86.6333,35.0167],"type":"Point"}
}