{
  "id": 7162532,
  "type": "Feature",
  "properties": {
    "tgn:hierarchy":[
        "tgn:7162532",
        "tgn:1000003",
        "tgn:7003677",
        "tgn:7000084",
        "tgn:7029392"
    ],
    "tgn:id":7162532,
    "tgn:name":"H\u00fcls-Berg",
    "tgn:placetype":[
        "aat:300008777"
    ]
},
  "bbox": [],
  "geometry": {"coordinates":[8.166667,51.15],"type":"Point"}
}