{
  "id": 2448301,
  "type": "Feature",
  "properties": {
    "tgn:hierarchy":[
        "tgn:2448301",
        "tgn:7002659",
        "tgn:1000001",
        "tgn:7012149",
        "tgn:2000055",
        "tgn:7029392"
    ],
    "tgn:id":2448301,
    "tgn:name":"Liles Branch",
    "tgn:placetype":[
        "aat:300008699"
    ]
},
  "bbox": [],
  "geometry": {"coordinates":[-85.4167,33.1667],"type":"Point"}
}