<<<<<<< HEAD
{
  "id": 2153171,
  "type": "Feature",
  "properties": {
    "tgn:hierarchy":[
        "tgn:2153171",
        "tgn:1000001",
        "tgn:7012149",
        "tgn:7007157",
        "tgn:2000189",
        "tgn:7029392"
    ],
    "tgn:id":2153171,
    "tgn:name":"Beal Lake",
    "tgn:placetype":[
        "aat:300008680"
    ]
},
  "bbox": [],
  "geometry": {"coordinates":[-121.8667,41.95],"type":"Point"}
}
=======
{"geometry":{"type":"Point","coordinates":[-121.866700,41.950000]},"type":"Feature","properties":{"hierarchy":["tgn:2153171","tgn:1000001","tgn:7012149","tgn:7007157","tgn:2000189","tgn:7029392"],"placetype":["aat:300008680"],"id":2153171,"name:xx":"Beal Lake"}}
>>>>>>> 03f74aca74312dbeaf24d7e61306dd6a786dc3d0
