<<<<<<< HEAD
{
  "id": 7484113,
  "type": "Feature",
  "properties": {
    "tgn:hierarchy":[
        "tgn:7484113",
        "tgn:1000004",
        "tgn:7492971",
        "tgn:1000141",
        "tgn:7029392"
    ],
    "tgn:id":7484113,
    "tgn:name":"Xinle",
    "tgn:placetype":[
        "aat:300008347"
    ]
},
  "bbox": [],
  "geometry": {"coordinates":[120.624444,22.491944],"type":"Point"}
}
=======
{"geometry":{"type":"Point","coordinates":[120.624444,22.491944]},"type":"Feature","properties":{"hierarchy":["tgn:7484113","tgn:1000004","tgn:7492971","tgn:1000141","tgn:7029392"],"placetype":["aat:300008347"],"id":7484113,"name:xx":"Xinle"}}
>>>>>>> 03f74aca74312dbeaf24d7e61306dd6a786dc3d0
