<<<<<<< HEAD
{
  "id": 2337075,
  "type": "Feature",
  "properties": {
    "tgn:hierarchy":[
        "tgn:2337075",
        "tgn:1000001",
        "tgn:7012149",
        "tgn:1002453",
        "tgn:7007706",
        "tgn:7029392"
    ],
    "tgn:id":2337075,
    "tgn:name":"Fourmile Run",
    "tgn:placetype":[
        "aat:300008699"
    ]
},
  "bbox": [],
  "geometry": {"coordinates":[-83.6833,40.7],"type":"Point"}
}
=======
{"geometry":{"type":"Point","coordinates":[-83.683300,40.700000]},"type":"Feature","properties":{"hierarchy":["tgn:2337075","tgn:1000001","tgn:7012149","tgn:1002453","tgn:7007706","tgn:7029392"],"placetype":["aat:300008699"],"id":2337075,"name:xx":"Fourmile Run"}}
>>>>>>> 03f74aca74312dbeaf24d7e61306dd6a786dc3d0
