{
  "id": 2350795,
  "type": "Feature",
  "properties": {
    "tgn:hierarchy":[
        "tgn:2350795",
        "tgn:1000001",
        "tgn:7012149",
        "tgn:2000208",
        "tgn:7007158",
        "tgn:7029392"
    ],
    "tgn:id":2350795,
    "tgn:name":"Glade Mountain",
    "tgn:placetype":[
        "aat:300008798"
    ]
},
  "bbox": [],
  "geometry": {"coordinates":[-108.5833,37.7667],"type":"Point"}
}