{
  "id": 2690938,
  "type": "Feature",
  "properties": {
    "tgn:hierarchy":[
        "tgn:2690938",
        "tgn:1000001",
        "tgn:1002305",
        "tgn:7012149",
        "tgn:7007920",
        "tgn:7029392"
    ],
    "tgn:id":2690938,
    "tgn:name":"Stankey Creek",
    "tgn:placetype":[
        "aat:300008706"
    ]
},
  "bbox": [],
  "geometry": {"coordinates":[-122.8333,46.2833],"type":"Point"}
}