{
  "id": 1024951,
  "type": "Feature",
  "properties": {
    "tgn:hierarchy":[
        "tgn:1024951",
        "tgn:7002649",
        "tgn:1000002",
        "tgn:1000058",
        "tgn:7029392"
    ],
    "tgn:id":1024951,
    "tgn:name":"Pir\u00ed\u00e1polis",
    "tgn:placetype":[
        "aat:300008347"
    ]
},
  "bbox": [],
  "geometry": {"coordinates":[-55.25,-34.85],"type":"Point"}
}