{
  "id": 2199200,
  "type": "Feature",
  "properties": {
    "tgn:hierarchy":[
        "tgn:2199200",
        "tgn:1000001",
        "tgn:7012149",
        "tgn:2000291",
        "tgn:7007240",
        "tgn:7029392"
    ],
    "tgn:id":2199200,
    "tgn:name":"Brunner Pond",
    "tgn:placetype":[
        "aat:300008680"
    ]
},
  "bbox": [],
  "geometry": {"coordinates":[-85.7333,30.6167],"type":"Point"}
}