{
  "id": 2302677,
  "type": "Feature",
  "properties": {
    "tgn:hierarchy":[
        "tgn:2302677",
        "tgn:1000001",
        "tgn:7012149",
        "tgn:1002961",
        "tgn:7007568",
        "tgn:7029392"
    ],
    "tgn:id":2302677,
    "tgn:name":"Dwaarkill",
    "tgn:placetype":[
        "aat:300008347"
    ]
},
  "bbox": [],
  "geometry": {"coordinates":[-74.25,41.6333],"type":"Point"}
}