{
  "id": 2166849,
  "type": "Feature",
  "properties": {
    "tgn:hierarchy":[
        "tgn:2166849",
        "tgn:2002130",
        "tgn:1000001",
        "tgn:7012149",
        "tgn:7007828",
        "tgn:7029392"
    ],
    "tgn:id":2166849,
    "tgn:name":"Big Brook",
    "tgn:placetype":[
        "aat:300008699"
    ]
},
  "bbox": [],
  "geometry": {"coordinates":[-73.3167,43.7667],"type":"Point"}
}