{
  "id": 2713049,
  "type": "Feature",
  "properties": {
    "tgn:hierarchy":[
        "tgn:2713049",
        "tgn:1000001",
        "tgn:7012149",
        "tgn:2001510",
        "tgn:7007709",
        "tgn:7029392"
    ],
    "tgn:id":2713049,
    "tgn:name":"Taylor Landing",
    "tgn:placetype":[
        "aat:300055621"
    ]
},
  "bbox": [],
  "geometry": {"coordinates":[-77.1667,35.0333],"type":"Point"}
}