{
  "id": 2089607,
  "type": "Feature",
  "properties": {
    "tgn:hierarchy":[
        "tgn:2089607",
        "tgn:1000001",
        "tgn:7012149",
        "tgn:1002876",
        "tgn:7007710",
        "tgn:7029392"
    ],
    "tgn:id":2089607,
    "tgn:name":"Jefferson",
    "tgn:placetype":[
        "aat:300008347"
    ]
},
  "bbox": [],
  "geometry": {"coordinates":[-76.1167,40.5833],"type":"Point"}
}