{
  "id": 2487668,
  "type": "Feature",
  "properties": {
    "tgn:hierarchy":[
        "tgn:2487668",
        "tgn:1000001",
        "tgn:2002148",
        "tgn:7012149",
        "tgn:7007919",
        "tgn:7029392"
    ],
    "tgn:id":2487668,
    "tgn:name":"Left Fork Linn Camp Branch",
    "tgn:placetype":[
        "aat:300008699"
    ]
},
  "bbox": [],
  "geometry": {"coordinates":[-81.85,37.2667],"type":"Point"}
}