{
  "id": 2184937,
  "type": "Feature",
  "properties": {
    "tgn:hierarchy":[
        "tgn:2184937",
        "tgn:1000001",
        "tgn:7012149",
        "tgn:2002286",
        "tgn:7013961",
        "tgn:7029392"
    ],
    "tgn:id":2184937,
    "tgn:name":"Bogart Run",
    "tgn:placetype":[
        "aat:300008699"
    ]
},
  "bbox": [],
  "geometry": {"coordinates":[-81.1167,39.4167],"type":"Point"}
}