<<<<<<< HEAD
{
  "id": 7352708,
  "type": "Feature",
  "properties": {
    "tgn:hierarchy":[
        "tgn:7352708",
        "tgn:7005581",
        "tgn:1000001",
        "tgn:7005560",
        "tgn:7029392"
    ],
    "tgn:id":7352708,
    "tgn:name":"Rancho Basiguare",
    "tgn:placetype":[
        "aat:300000241"
    ]
},
  "bbox": [],
  "geometry": {"coordinates":[-107.483333,27.466667],"type":"Point"}
}
=======
{"geometry":{"type":"Point","coordinates":[-107.483333,27.466667]},"type":"Feature","properties":{"hierarchy":["tgn:7352708","tgn:7005581","tgn:1000001","tgn:7005560","tgn:7029392"],"placetype":["aat:300000241"],"id":7352708,"name:xx":"Rancho Basiguare"}}
>>>>>>> 03f74aca74312dbeaf24d7e61306dd6a786dc3d0
