<<<<<<< HEAD
{
  "id": 7111507,
  "type": "Feature",
  "properties": {
    "tgn:hierarchy":[
        "tgn:7111507",
        "tgn:7003669",
        "tgn:1000003",
        "tgn:7000084",
        "tgn:7029392"
    ],
    "tgn:id":7111507,
    "tgn:name":"Ro\u00dfstall",
    "tgn:placetype":[
        "aat:300055621"
    ]
},
  "bbox": [],
  "geometry": {"coordinates":[10.9,47.583333],"type":"Point"}
}
=======
{"geometry":{"type":"Point","coordinates":[10.900000,47.583333]},"type":"Feature","properties":{"hierarchy":["tgn:7111507","tgn:7003669","tgn:1000003","tgn:7000084","tgn:7029392"],"placetype":["aat:300055621"],"id":7111507,"name:xx":"Ro\u00dfstall"}}
>>>>>>> 03f74aca74312dbeaf24d7e61306dd6a786dc3d0
