{
  "id": 2123053,
  "type": "Feature",
  "properties": {
    "tgn:hierarchy":[
        "tgn:2123053",
        "tgn:1000001",
        "tgn:7012149",
        "tgn:2002376",
        "tgn:7007923",
        "tgn:7029392"
    ],
    "tgn:id":2123053,
    "tgn:name":"Marse",
    "tgn:placetype":[
        "aat:300387016"
    ]
},
  "bbox": [],
  "geometry": {"coordinates":[-110.9833,42.15],"type":"Point"}
}