{
  "id": 2668132,
  "type": "Feature",
  "properties": {
    "tgn:hierarchy":[
        "tgn:2668132",
        "tgn:1000001",
        "tgn:7012149",
        "tgn:2002165",
        "tgn:7007919",
        "tgn:7029392"
    ],
    "tgn:id":2668132,
    "tgn:name":"Skyline, Lake",
    "tgn:placetype":[
        "aat:300006191"
    ]
},
  "bbox": [],
  "geometry": {"coordinates":[-78.4333,38.25],"type":"Point"}
}