<<<<<<< HEAD
{
  "id": 7176363,
  "type": "Feature",
  "properties": {
    "tgn:hierarchy":[
        "tgn:7176363",
        "tgn:7000096",
        "tgn:1000003",
        "tgn:7000084",
        "tgn:7029392"
    ],
    "tgn:id":7176363,
    "tgn:name":"Grunow",
    "tgn:placetype":[
        "aat:300008347"
    ]
},
  "bbox": [],
  "geometry": {"coordinates":[14.033333,52.6],"type":"Point"}
}
=======
{"geometry":{"type":"Point","coordinates":[14.033333,52.600000]},"type":"Feature","properties":{"hierarchy":["tgn:7176363","tgn:7000096","tgn:1000003","tgn:7000084","tgn:7029392"],"placetype":["aat:300008347"],"id":7176363,"name:xx":"Grunow"}}
>>>>>>> 03f74aca74312dbeaf24d7e61306dd6a786dc3d0
