<<<<<<< HEAD
{
  "id": 2761218,
  "type": "Feature",
  "properties": {
    "tgn:hierarchy":[
        "tgn:2761218",
        "tgn:1000001",
        "tgn:7012149",
        "tgn:7007523",
        "tgn:7029392"
    ],
    "tgn:id":2761218,
    "tgn:name":"West Locust Creek",
    "tgn:placetype":[
        "aat:300008706"
    ]
},
  "bbox": [],
  "geometry": {"coordinates":[-93.2667,40.3833],"type":"Point"}
}
=======
{"geometry":{"type":"Point","coordinates":[-93.266700,40.383300]},"type":"Feature","properties":{"hierarchy":["tgn:2761218","tgn:1000001","tgn:7012149","tgn:7007523","tgn:7029392"],"placetype":["aat:300008706"],"id":2761218,"name:xx":"West Locust Creek"}}
>>>>>>> 03f74aca74312dbeaf24d7e61306dd6a786dc3d0
