{
  "id": 1021071,
  "type": "Feature",
  "properties": {
    "tgn:hierarchy":[
        "tgn:1021071",
        "tgn:1001941",
        "tgn:1000047",
        "tgn:7002458",
        "tgn:1000002",
        "tgn:7029392"
    ],
    "tgn:id":1021071,
    "tgn:name":"Carazinho",
    "tgn:placetype":[
        "aat:300008347",
        "aat:300008389"
    ]
},
  "bbox": [],
  "geometry": {"coordinates":[-52.7667,-28.2667],"type":"Point"}
}