{
  "id": 2664224,
  "type": "Feature",
  "properties": {
    "tgn:hierarchy":[
        "tgn:2664224",
        "tgn:1000001",
        "tgn:7012149",
        "tgn:1002785",
        "tgn:7007920",
        "tgn:7029392"
    ],
    "tgn:id":2664224,
    "tgn:name":"Silver Springs",
    "tgn:placetype":[
        "aat:300008697"
    ]
},
  "bbox": [],
  "geometry": {"coordinates":[-121.5167,46.9833],"type":"Point"}
}