{
  "id": 2483988,
  "type": "Feature",
  "properties": {
    "tgn:hierarchy":[
        "tgn:2483988",
        "tgn:1000001",
        "tgn:7012149",
        "tgn:2000479",
        "tgn:7007250",
        "tgn:7029392"
    ],
    "tgn:id":2483988,
    "tgn:name":"Latour Baldy",
    "tgn:placetype":[
        "aat:300008798"
    ]
},
  "bbox": [],
  "geometry": {"coordinates":[-116.3333,47.4667],"type":"Point"}
}