{
  "id": 1090012,
  "type": "Feature",
  "properties": {
    "tgn:hierarchy":[
        "tgn:1090012",
        "tgn:1001668",
        "tgn:7001242",
        "tgn:1000164",
        "tgn:7029392"
    ],
    "tgn:id":1090012,
    "tgn:name":"Kango",
    "tgn:placetype":[
        "aat:300008347"
    ]
},
  "bbox": [],
  "geometry": {"coordinates":[10.1833,0.25],"type":"Point"}
}