{
  "id": 2206604,
  "type": "Feature",
  "properties": {
    "tgn:hierarchy":[
        "tgn:2206604",
        "tgn:1000001",
        "tgn:2001945",
        "tgn:7012149",
        "tgn:7007826",
        "tgn:7029392"
    ],
    "tgn:id":2206604,
    "tgn:name":"Bullis Gap Tank",
    "tgn:placetype":[
        "aat:300006191"
    ]
},
  "bbox": [],
  "geometry": {"coordinates":[-102.5833,29.8167],"type":"Point"}
}