{
  "id": 7201863,
  "type": "Feature",
  "properties": {
    "tgn:hierarchy":[
        "tgn:7201863",
        "tgn:1000003",
        "tgn:7000094",
        "tgn:7000084",
        "tgn:7029392"
    ],
    "tgn:id":7201863,
    "tgn:name":"Breitenstein",
    "tgn:placetype":[
        "aat:300000206"
    ]
},
  "bbox": [],
  "geometry": {"coordinates":[14.15,53.516667],"type":"Point"}
}