{
  "id": 7531480,
  "type": "Feature",
  "properties": {
    "tgn:hierarchy":[
        "tgn:7531480",
        "tgn:7001242",
        "tgn:7016833",
        "tgn:1001091",
        "tgn:7029392"
    ],
    "tgn:id":7531480,
    "tgn:name":"Masjid al Malik Fay\u015fal Bin 'Abd al 'Az\u012bz",
    "tgn:placetype":[
        "aat:300007544"
    ]
},
  "bbox": [],
  "geometry": {"coordinates":[31.398611,30.124861],"type":"Point"}
}