{
  "id": 7591517,
  "type": "Feature",
  "properties": {
    "tgn:hierarchy":[
        "tgn:7591517",
        "tgn:1000004",
        "tgn:7000198",
        "tgn:7000799",
        "tgn:7029392"
    ],
    "tgn:id":7591517,
    "tgn:name:en":"Gh\u0101zia",
    "tgn:placetype":[
        "aat:300008347"
    ]
},
  "bbox": [],
  "geometry": {"coordinates":[74.818056,32.629167],"type":"Point"}
}