{
  "id": 7290893,
  "type": "Feature",
  "properties": {
    "tgn:hierarchy":[
        "tgn:7290893",
        "tgn:1001699",
        "tgn:1000049",
        "tgn:1000002",
        "tgn:7029392"
    ],
    "tgn:id":7290893,
    "tgn:name":"Canal Desertores",
    "tgn:placetype":[
        "aat:300387026"
    ]
},
  "bbox": [],
  "geometry": {"coordinates":[-72.928889,-42.6425],"type":"Point"}
}