{
  "id": 1091691,
  "type": "Feature",
  "properties": {
    "tgn:hierarchy":[
        "tgn:1091691",
        "tgn:7001242",
        "tgn:1000893",
        "tgn:1000180",
        "tgn:7029392"
    ],
    "tgn:id":1091691,
    "tgn:name":"Uampochane",
    "tgn:placetype":[
        "aat:300008347"
    ]
},
  "bbox": [],
  "geometry": {"coordinates":[32.6833,-26.3833],"type":"Point"}
}