<<<<<<< HEAD
{
  "id": 7247055,
  "type": "Feature",
  "properties": {
    "tgn:hierarchy":[
        "tgn:7247055",
        "tgn:7003456",
        "tgn:1000003",
        "tgn:1000063",
        "tgn:7018236",
        "tgn:7029392"
    ],
    "tgn:id":7247055,
    "tgn:name":"Schans van Dorpveld",
    "tgn:placetype":[
        "aat:300006909"
    ]
},
  "bbox": [],
  "geometry": {"coordinates":[4.527794,51.066811],"type":"Point"}
}
=======
{"geometry":{"type":"Point","coordinates":[4.527794,51.066811]},"type":"Feature","properties":{"hierarchy":["tgn:7247055","tgn:7003456","tgn:1000003","tgn:1000063","tgn:7018236","tgn:7029392"],"placetype":["aat:300006909"],"id":7247055,"name:xx":"Schans van Dorpveld"}}
>>>>>>> 03f74aca74312dbeaf24d7e61306dd6a786dc3d0
