{
  "id": 7033586,
  "type": "Feature",
  "properties": {
    "tgn:hierarchy":[
        "tgn:7033586",
        "tgn:7003133",
        "tgn:1000003",
        "tgn:7008516",
        "tgn:1000080",
        "tgn:7029392"
    ],
    "tgn:id":7033586,
    "tgn:name":"Villanova",
    "tgn:placetype":[
        "aat:300008347"
    ]
},
  "bbox": [],
  "geometry": {"coordinates":[12.047778,44.447222],"type":"Point"}
}