{
  "id": 2166860,
  "type": "Feature",
  "properties": {
    "tgn:hierarchy":[
        "tgn:2166860",
        "tgn:1000001",
        "tgn:7012149",
        "tgn:2001758",
        "tgn:7007712",
        "tgn:7029392"
    ],
    "tgn:id":2166860,
    "tgn:name":"Big Brown Lake",
    "tgn:placetype":[
        "aat:300008680"
    ]
},
  "bbox": [],
  "geometry": {"coordinates":[-79.3167,33.9167],"type":"Point"}
}