<<<<<<< HEAD
{
  "id": 2761202,
  "type": "Feature",
  "properties": {
    "tgn:hierarchy":[
        "tgn:2761202",
        "tgn:1000001",
        "tgn:2000197",
        "tgn:7012149",
        "tgn:7007158",
        "tgn:7029392"
    ],
    "tgn:id":2761202,
    "tgn:name":"West Limestone Creek",
    "tgn:placetype":[
        "aat:300008706"
    ]
},
  "bbox": [],
  "geometry": {"coordinates":[-102.9167,38.2167],"type":"Point"}
}
=======
{"geometry":{"type":"Point","coordinates":[-102.916700,38.216700]},"type":"Feature","properties":{"hierarchy":["tgn:2761202","tgn:1000001","tgn:2000197","tgn:7012149","tgn:7007158","tgn:7029392"],"placetype":["aat:300008706"],"id":2761202,"name:xx":"West Limestone Creek"}}
>>>>>>> 03f74aca74312dbeaf24d7e61306dd6a786dc3d0
