{
  "id": 2734736,
  "type": "Feature",
  "properties": {
    "tgn:hierarchy":[
        "tgn:2734736",
        "tgn:1000001",
        "tgn:1002286",
        "tgn:7012149",
        "tgn:7007710",
        "tgn:7029392"
    ],
    "tgn:id":2734736,
    "tgn:name":"Tuttle Run",
    "tgn:placetype":[
        "aat:300008699"
    ]
},
  "bbox": [],
  "geometry": {"coordinates":[-77.85,41.4667],"type":"Point"}
}