{
  "id": 1007617,
  "type": "Feature",
  "properties": {
    "tgn:hierarchy":[
        "tgn:1007617",
        "tgn:1000139",
        "tgn:7004345",
        "tgn:1000004",
        "tgn:7000261",
        "tgn:7029392"
    ],
    "tgn:id":1007617,
    "tgn:name":"Kamar\u0101n",
    "tgn:placetype":[
        "aat:300008791"
    ]
},
  "bbox": [],
  "geometry": {"coordinates":[42.5667,15.35],"type":"Point"}
}