{
  "id": 1104228,
  "type": "Feature",
  "properties": {
    "tgn:hierarchy":[
        "tgn:1104228",
        "tgn:1000004",
        "tgn:7029392"
    ],
    "tgn:id":1104228,
    "tgn:name":"Cho-mo-la-li Shan",
    "tgn:placetype":[
        "aat:300008795"
    ]
},
  "bbox": [],
  "geometry": {"coordinates":[89.2667,27.8333],"type":"Point"}
}