{
  "id": 7537215,
  "type": "Feature",
  "properties": {
    "tgn:hierarchy":[
        "tgn:7537215",
        "tgn:7001242",
        "tgn:7016833",
        "tgn:1001418",
        "tgn:7029392"
    ],
    "tgn:id":7537215,
    "tgn:name:en":"Misharrik, T\u00fbq el",
    "tgn:placetype":[
        "aat:300008777"
    ]
},
  "bbox": [],
  "geometry": {"coordinates":[27.383333,30.35],"type":"Point"}
}