{
  "id": 2713017,
  "type": "Feature",
  "properties": {
    "tgn:hierarchy":[
        "tgn:2713017",
        "tgn:1000001",
        "tgn:1002360",
        "tgn:7012149",
        "tgn:7007565",
        "tgn:7029392"
    ],
    "tgn:id":2713017,
    "tgn:name":"Taylor Lake",
    "tgn:placetype":[
        "aat:300006191"
    ]
},
  "bbox": [],
  "geometry": {"coordinates":[-74.3333,40.75],"type":"Point"}
}