{
  "id": 7521864,
  "type": "Feature",
  "properties": {
    "tgn:hierarchy":[
        "tgn:7521864",
        "tgn:7001242",
        "tgn:7016833",
        "tgn:7000123",
        "tgn:7029392"
    ],
    "tgn:id":7521864,
    "tgn:name:en":"Ab\u016b Misallah, W\u0101d\u012b",
    "tgn:placetype":[
        "aat:300379998"
    ]
},
  "bbox": [],
  "geometry": {"coordinates":[32.65,25.15],"type":"Point"}
}