{
  "id": 7223435,
  "type": "Feature",
  "properties": {
    "tgn:hierarchy":[
        "tgn:7223435",
        "tgn:7002724",
        "tgn:7002715",
        "tgn:1000003",
        "tgn:1000074",
        "tgn:7029392"
    ],
    "tgn:id":7223435,
    "tgn:name":"Oxi\u00e1",
    "tgn:placetype":[
        "aat:300008347"
    ]
},
  "bbox": [],
  "geometry": {"coordinates":[21.133333,40.733333],"type":"Point"}
}