<<<<<<< HEAD
{
  "id": 2769917,
  "type": "Feature",
  "properties": {
    "tgn:hierarchy":[
        "tgn:2769917",
        "tgn:1000001",
        "tgn:1002347",
        "tgn:7012149",
        "tgn:7007568",
        "tgn:7029392"
    ],
    "tgn:id":2769917,
    "tgn:name":"Wilbur Pond",
    "tgn:placetype":[
        "aat:300008680"
    ]
},
  "bbox": [],
  "geometry": {"coordinates":[-73.7333,41.9667],"type":"Point"}
}
=======
{"geometry":{"type":"Point","coordinates":[-73.733300,41.966700]},"type":"Feature","properties":{"hierarchy":["tgn:2769917","tgn:1000001","tgn:1002347","tgn:7012149","tgn:7007568","tgn:7029392"],"placetype":["aat:300008680"],"id":2769917,"name:xx":"Wilbur Pond"}}
>>>>>>> 03f74aca74312dbeaf24d7e61306dd6a786dc3d0
