{
  "id": 2309941,
  "type": "Feature",
  "properties": {
    "tgn:hierarchy":[
        "tgn:2309941",
        "tgn:1000001",
        "tgn:7012149",
        "tgn:1002993",
        "tgn:7007568",
        "tgn:7029392"
    ],
    "tgn:id":2309941,
    "tgn:name":"Easton",
    "tgn:placetype":[
        "aat:300008347"
    ]
},
  "bbox": [],
  "geometry": {"coordinates":[-73.55,42.9833],"type":"Point"}
}