<<<<<<< HEAD
{
  "id": 2255081,
  "type": "Feature",
  "properties": {
    "tgn:hierarchy":[
        "tgn:2255081",
        "tgn:1000001",
        "tgn:7016172",
        "tgn:7012149",
        "tgn:2000142",
        "tgn:7029392"
    ],
    "tgn:id":2255081,
    "tgn:name":"Cooper Creek Site Five Reservoir",
    "tgn:placetype":[
        "aat:300006191"
    ]
},
  "bbox": [],
  "geometry": {"coordinates":[-91.2833,36.05],"type":"Point"}
}
=======
{"geometry":{"type":"Point","coordinates":[-91.283300,36.050000]},"type":"Feature","properties":{"hierarchy":["tgn:2255081","tgn:1000001","tgn:7016172","tgn:7012149","tgn:2000142","tgn:7029392"],"placetype":["aat:300006191"],"id":2255081,"name:xx":"Cooper Creek Site Five Reservoir"}}
>>>>>>> 03f74aca74312dbeaf24d7e61306dd6a786dc3d0
