{
  "id": 2255081,
  "type": "Feature",
  "properties": {
    "tgn:hierarchy":[
        "tgn:2255081",
        "tgn:1000001",
        "tgn:7016172",
        "tgn:7012149",
        "tgn:2000142",
        "tgn:7029392"
    ],
    "tgn:id":2255081,
    "tgn:name":"Cooper Creek Site Five Reservoir",
    "tgn:placetype":[
        "aat:300006191"
    ]
},
  "bbox": [],
  "geometry": {"coordinates":[-91.2833,36.05],"type":"Point"}
}