{
  "id": 7216864,
  "type": "Feature",
  "properties": {
    "tgn:hierarchy":[
        "tgn:7216864",
        "tgn:7000096",
        "tgn:1000003",
        "tgn:7000084",
        "tgn:7029392"
    ],
    "tgn:id":7216864,
    "tgn:name":"Altes Dorf",
    "tgn:placetype":[
        "aat:300008347"
    ]
},
  "bbox": [],
  "geometry": {"coordinates":[12.283333,52.666667],"type":"Point"}
}