{
  "id": 2627005,
  "type": "Feature",
  "properties": {
    "tgn:hierarchy":[
        "tgn:2627005",
        "tgn:1000001",
        "tgn:7012149",
        "tgn:2001612",
        "tgn:7007706",
        "tgn:7029392"
    ],
    "tgn:id":2627005,
    "tgn:name":"Rocky Run",
    "tgn:placetype":[
        "aat:300008699"
    ]
},
  "bbox": [],
  "geometry": {"coordinates":[-82.2167,38.7333],"type":"Point"}
}