{
  "id": 2540343,
  "type": "Feature",
  "properties": {
    "tgn:hierarchy":[
        "tgn:2540343",
        "tgn:1000001",
        "tgn:2002318",
        "tgn:7012149",
        "tgn:7007922",
        "tgn:7029392"
    ],
    "tgn:id":2540343,
    "tgn:name":"Newman, Lake",
    "tgn:placetype":[
        "aat:300008680"
    ]
},
  "bbox": [],
  "geometry": {"coordinates":[-92.0167,46.4667],"type":"Point"}
}