{
  "id": 2446372,
  "type": "Feature",
  "properties": {
    "tgn:hierarchy":[
        "tgn:2446372",
        "tgn:1000001",
        "tgn:7012149",
        "tgn:1002594",
        "tgn:7007920",
        "tgn:7029392"
    ],
    "tgn:id":2446372,
    "tgn:name":"Lewis Creek",
    "tgn:placetype":[
        "aat:300008706"
    ]
},
  "bbox": [],
  "geometry": {"coordinates":[-122.3333,46.7167],"type":"Point"}
}