{
  "id": 2193967,
  "type": "Feature",
  "properties": {
    "tgn:hierarchy":[
        "tgn:2193967",
        "tgn:1000001",
        "tgn:7012149",
        "tgn:2001126",
        "tgn:7007522",
        "tgn:7029392"
    ],
    "tgn:id":2193967,
    "tgn:name":"Briarwood",
    "tgn:placetype":[
        "aat:300008347"
    ]
},
  "bbox": [],
  "geometry": {"coordinates":[-88.7167,34.2667],"type":"Point"}
}