{
  "id": 7532211,
  "type": "Feature",
  "properties": {
    "tgn:hierarchy":[
        "tgn:7532211",
        "tgn:7001242",
        "tgn:7016833",
        "tgn:7001334",
        "tgn:7029392"
    ],
    "tgn:id":7532211,
    "tgn:name:en":"Darb el-Bit\u00e2n",
    "tgn:placetype":[
        "aat:300008217"
    ]
},
  "bbox": [],
  "geometry": {"coordinates":[32.308056,24.000833],"type":"Point"}
}