{
  "id": 2261066,
  "type": "Feature",
  "properties": {
    "tgn:hierarchy":[
        "tgn:2261066",
        "tgn:1000001",
        "tgn:7012149",
        "tgn:2001084",
        "tgn:7007521",
        "tgn:7029392"
    ],
    "tgn:id":2261066,
    "tgn:name":"County Ditch Number Twenty",
    "tgn:placetype":[
        "aat:300006075"
    ]
},
  "bbox": [],
  "geometry": {"coordinates":[-94.0167,45.25],"type":"Point"}
}