<<<<<<< HEAD
{
  "id": 7484995,
  "type": "Feature",
  "properties": {
    "tgn:hierarchy":[
        "tgn:7484995",
        "tgn:7488858",
        "tgn:1000004",
        "tgn:1000141",
        "tgn:7029392"
    ],
    "tgn:id":7484995,
    "tgn:name":"Guandao Xi Qiao",
    "tgn:placetype":[
        "aat:300007836"
    ]
},
  "bbox": [],
  "geometry": {"coordinates":[121.036111,24.081389],"type":"Point"}
}
=======
{"geometry":{"type":"Point","coordinates":[121.036111,24.081389]},"type":"Feature","properties":{"hierarchy":["tgn:7484995","tgn:7488858","tgn:1000004","tgn:1000141","tgn:7029392"],"placetype":["aat:300007836"],"id":7484995,"name:xx":"Guandao Xi Qiao"}}
>>>>>>> 03f74aca74312dbeaf24d7e61306dd6a786dc3d0
