{
  "id": 7566174,
  "type": "Feature",
  "properties": {
    "tgn:hierarchy":[
        "tgn:7566174",
        "tgn:1000004",
        "tgn:7000198",
        "tgn:7016722",
        "tgn:7029392"
    ],
    "tgn:id":7566174,
    "tgn:name:en":"Naw\u0101da Sh\u0101ham",
    "tgn:placetype":[
        "aat:300008347"
    ]
},
  "bbox": [],
  "geometry": {"coordinates":[79.84048,26.736823],"type":"Point"}
}