{
  "id": 7276032,
  "type": "Feature",
  "properties": {
    "tgn:hierarchy":[
        "tgn:7276032",
        "tgn:1001702",
        "tgn:1000049",
        "tgn:1000002",
        "tgn:7029392"
    ],
    "tgn:id":7276032,
    "tgn:name":"Titus, Islotes",
    "tgn:placetype":[
        "aat:300008791"
    ]
},
  "bbox": [],
  "geometry": {"coordinates":[-73.966667,-51.716667],"type":"Point"}
}