{
  "id": 7300941,
  "type": "Feature",
  "properties": {
    "tgn:hierarchy":[
        "tgn:7300941",
        "tgn:7008911",
        "tgn:1000003",
        "tgn:7002763",
        "tgn:1000095",
        "tgn:7029392"
    ],
    "tgn:id":7300941,
    "tgn:name":"Montouto",
    "tgn:placetype":[
        "aat:300008347"
    ]
},
  "bbox": [],
  "geometry": {"coordinates":[-7.016667,43.433333],"type":"Point"}
}