{
  "id": 2335848,
  "type": "Feature",
  "properties": {
    "tgn:hierarchy":[
        "tgn:2335848",
        "tgn:1000001",
        "tgn:7012149",
        "tgn:2001047",
        "tgn:7007521",
        "tgn:7029392"
    ],
    "tgn:id":2335848,
    "tgn:name":"Fosdick Lake",
    "tgn:placetype":[
        "aat:300008680"
    ]
},
  "bbox": [],
  "geometry": {"coordinates":[-94.4333,46.2333],"type":"Point"}
}