{
  "id": 1076869,
  "type": "Feature",
  "properties": {
    "tgn:hierarchy":[
        "tgn:1076869",
        "tgn:1000004",
        "tgn:7000198",
        "tgn:7001797",
        "tgn:7029392"
    ],
    "tgn:id":1076869,
    "tgn:name:en":"Sankarankovil",
    "tgn:placetype":[
        "aat:300008347"
    ]
},
  "bbox": [],
  "geometry": {"coordinates":[77.55,9.166667],"type":"Point"}
}