{
  "id": 2411608,
  "type": "Feature",
  "properties": {
    "tgn:hierarchy":[
        "tgn:2411608",
        "tgn:7002659",
        "tgn:1000001",
        "tgn:7012149",
        "tgn:2000062",
        "tgn:7029392"
    ],
    "tgn:id":2411608,
    "tgn:name":"Indian Lake",
    "tgn:placetype":[
        "aat:300006191"
    ]
},
  "bbox": [],
  "geometry": {"coordinates":[-87.55,33.2333],"type":"Point"}
}