{
  "id": 2108583,
  "type": "Feature",
  "properties": {
    "tgn:hierarchy":[
        "tgn:2108583",
        "tgn:1000001",
        "tgn:7012149",
        "tgn:1002898",
        "tgn:7007826",
        "tgn:7029392"
    ],
    "tgn:id":2108583,
    "tgn:name":"Winona",
    "tgn:placetype":[
        "aat:300008347"
    ]
},
  "bbox": [],
  "geometry": {"coordinates":[-95.1667,32.4833],"type":"Point"}
}