{
  "id": 2450657,
  "type": "Feature",
  "properties": {
    "tgn:hierarchy":[
        "tgn:2450657",
        "tgn:1000001",
        "tgn:1002219",
        "tgn:7012149",
        "tgn:7007157",
        "tgn:7029392"
    ],
    "tgn:id":2450657,
    "tgn:name":"Lion Lake",
    "tgn:placetype":[
        "aat:300008680"
    ]
},
  "bbox": [],
  "geometry": {"coordinates":[-120.0333,38.4333],"type":"Point"}
}