{
  "id": 2616855,
  "type": "Feature",
  "properties": {
    "tgn:hierarchy":[
        "tgn:2616855",
        "tgn:1000001",
        "tgn:7012149",
        "tgn:7013961",
        "tgn:7029392"
    ],
    "tgn:id":2616855,
    "tgn:name":"Rich Knob",
    "tgn:placetype":[
        "aat:300008798"
    ]
},
  "bbox": [],
  "geometry": {"coordinates":[-81.1833,37.5667],"type":"Point"}
}