{
  "id": 7474832,
  "type": "Feature",
  "properties": {
    "tgn:hierarchy":[
        "tgn:7474832",
        "tgn:1000004",
        "tgn:7492971",
        "tgn:1000141",
        "tgn:7029392"
    ],
    "tgn:id":7474832,
    "tgn:name":"Guanbu",
    "tgn:placetype":[
        "aat:300008347"
    ]
},
  "bbox": [],
  "geometry": {"coordinates":[120.522778,22.446389],"type":"Point"}
}