{
  "id": 7001754,
  "type": "Feature",
  "properties": {
    "tgn:hierarchy":[
        "tgn:7001754",
        "tgn:7001242",
        "tgn:1002089",
        "tgn:1000205",
        "tgn:7029392"
    ],
    "tgn:id":7001754,
    "tgn:name":"Sbeitla",
    "tgn:placetype":[
        "aat:300008347",
        "aat:300008375"
    ]
},
  "bbox": [],
  "geometry": {"coordinates":[9.118,35.229],"type":"Point"}
}