{
  "id": 7585803,
  "type": "Feature",
  "properties": {
    "tgn:hierarchy":[
        "tgn:7585803",
        "tgn:1000004",
        "tgn:7000198",
        "tgn:7000799",
        "tgn:7029392"
    ],
    "tgn:id":7585803,
    "tgn:name:en":"Bisiw\u0101li Dh\u0101r",
    "tgn:placetype":[
        "aat:300008795"
    ]
},
  "bbox": [],
  "geometry": {"coordinates":[74.016667,34.263889],"type":"Point"}
}