{
  "id": 7104692,
  "type": "Feature",
  "properties": {
    "tgn:hierarchy":[
        "tgn:7104692",
        "tgn:7003669",
        "tgn:1000003",
        "tgn:7000084",
        "tgn:7029392"
    ],
    "tgn:id":7104692,
    "tgn:name":"Schneitweg",
    "tgn:placetype":[
        "aat:300008347"
    ]
},
  "bbox": [],
  "geometry": {"coordinates":[12.183333,49.133333],"type":"Point"}
}