{
  "id": 2680915,
  "type": "Feature",
  "properties": {
    "tgn:hierarchy":[
        "tgn:2680915",
        "tgn:1000001",
        "tgn:7012149",
        "tgn:7007157",
        "tgn:1002675",
        "tgn:7029392"
    ],
    "tgn:id":2680915,
    "tgn:name":"South Landing",
    "tgn:placetype":[
        "aat:300008347"
    ]
},
  "bbox": [],
  "geometry": {"coordinates":[-118.7167,37.5667],"type":"Point"}
}