{
  "id": 7412886,
  "type": "Feature",
  "properties": {
    "tgn:hierarchy":[
        "tgn:7412886",
        "tgn:7005587",
        "tgn:1000001",
        "tgn:7005560",
        "tgn:7029392"
    ],
    "tgn:id":7412886,
    "tgn:name:es":"Presa Da\u00f1\u00fa",
    "tgn:placetype":[
        "aat:300006191"
    ]
},
  "bbox": [],
  "geometry": {"coordinates":[-99.683333,20.195833],"type":"Point"}
}