{
  "id": 7179883,
  "type": "Feature",
  "properties": {
    "tgn:hierarchy":[
        "tgn:7179883",
        "tgn:7003669",
        "tgn:1000003",
        "tgn:7000084",
        "tgn:7029392"
    ],
    "tgn:id":7179883,
    "tgn:name":"Hahnenberg",
    "tgn:placetype":[
        "aat:300008777"
    ]
},
  "bbox": [],
  "geometry": {"coordinates":[10.583333,48.816667],"type":"Point"}
}