<<<<<<< HEAD
{
  "id": 2156181,
  "type": "Feature",
  "properties": {
    "tgn:hierarchy":[
        "tgn:2156181",
        "tgn:1000001",
        "tgn:2002261",
        "tgn:7012149",
        "tgn:7013961",
        "tgn:7029392"
    ],
    "tgn:id":2156181,
    "tgn:name":"Beards Fork",
    "tgn:placetype":[
        "aat:300008699"
    ]
},
  "bbox": [],
  "geometry": {"coordinates":[-81.1833,38.05],"type":"Point"}
}
=======
{"geometry":{"type":"Point","coordinates":[-81.183300,38.050000]},"type":"Feature","properties":{"hierarchy":["tgn:2156181","tgn:1000001","tgn:2002261","tgn:7012149","tgn:7013961","tgn:7029392"],"placetype":["aat:300008699"],"id":2156181,"name:xx":"Beards Fork"}}
>>>>>>> 03f74aca74312dbeaf24d7e61306dd6a786dc3d0
