<<<<<<< HEAD
{
  "id": 7475331,
  "type": "Feature",
  "properties": {
    "tgn:hierarchy":[
        "tgn:7475331",
        "tgn:1000004",
        "tgn:7467799",
        "tgn:1000141",
        "tgn:7029392"
    ],
    "tgn:id":7475331,
    "tgn:name":"Lushankeng",
    "tgn:placetype":[
        "aat:300008347"
    ]
},
  "bbox": [],
  "geometry": {"coordinates":[120.577,24.0711],"type":"Point"}
}
=======
{"geometry":{"type":"Point","coordinates":[120.577000,24.071100]},"type":"Feature","properties":{"hierarchy":["tgn:7475331","tgn:1000004","tgn:7467799","tgn:1000141","tgn:7029392"],"placetype":["aat:300008347"],"id":7475331,"name:xx":"Lushankeng"}}
>>>>>>> 03f74aca74312dbeaf24d7e61306dd6a786dc3d0
