{
  "id": 7475331,
  "type": "Feature",
  "properties": {
    "tgn:hierarchy":[
        "tgn:7475331",
        "tgn:1000004",
        "tgn:7467799",
        "tgn:1000141",
        "tgn:7029392"
    ],
    "tgn:id":7475331,
    "tgn:name":"Lushankeng",
    "tgn:placetype":[
        "aat:300008347"
    ]
},
  "bbox": [],
  "geometry": {"coordinates":[120.577,24.0711],"type":"Point"}
}