{
  "id": 2431474,
  "type": "Feature",
  "properties": {
    "tgn:hierarchy":[
        "tgn:2431474",
        "tgn:1000001",
        "tgn:7012149",
        "tgn:2001060",
        "tgn:7007521",
        "tgn:7029392"
    ],
    "tgn:id":2431474,
    "tgn:name":"Karth Lake",
    "tgn:placetype":[
        "aat:300008680"
    ]
},
  "bbox": [],
  "geometry": {"coordinates":[-93.15,45.0667],"type":"Point"}
}