{
  "id": 7552038,
  "type": "Feature",
  "properties": {
    "tgn:hierarchy":[
        "tgn:7552038",
        "tgn:1000004",
        "tgn:7000198",
        "tgn:7016788",
        "tgn:7029392"
    ],
    "tgn:id":7552038,
    "tgn:name:en":"N\u0101r\u0101yanpur",
    "tgn:placetype":[
        "aat:300008347"
    ]
},
  "bbox": [],
  "geometry": {"coordinates":[76.299306,27.514829],"type":"Point"}
}