{
  "id": 7221016,
  "type": "Feature",
  "properties": {
    "tgn:hierarchy":[
        "tgn:7221016",
        "tgn:7002739",
        "tgn:7017076",
        "tgn:1000003",
        "tgn:1000074",
        "tgn:7029392"
    ],
    "tgn:id":7221016,
    "tgn:name":"Cha\u00efd\u00e1ri, \u00c1kra",
    "tgn:placetype":[
        "aat:300008850"
    ]
},
  "bbox": [],
  "geometry": {"coordinates":[22.927524,37.524696],"type":"Point"}
}