{
  "id": 7500371,
  "type": "Feature",
  "properties": {
    "tgn:hierarchy":[
        "tgn:7500371",
        "tgn:1000004",
        "tgn:7001009",
        "tgn:1000141",
        "tgn:7029392"
    ],
    "tgn:id":7500371,
    "tgn:name":"Zhongcuo",
    "tgn:placetype":[
        "aat:300008347"
    ]
},
  "bbox": [],
  "geometry": {"coordinates":[120.527067,24.206999],"type":"Point"}
}