{
  "id": 2449341,
  "type": "Feature",
  "properties": {
    "tgn:hierarchy":[
        "tgn:2449341",
        "tgn:2000919",
        "tgn:1000001",
        "tgn:7012149",
        "tgn:7007515",
        "tgn:7029392"
    ],
    "tgn:id":2449341,
    "tgn:name":"Limestone Point",
    "tgn:placetype":[
        "aat:300008850"
    ]
},
  "bbox": [],
  "geometry": {"coordinates":[-68.3667,47.05],"type":"Point"}
}