{
  "id": 2584808,
  "type": "Feature",
  "properties": {
    "tgn:hierarchy":[
        "tgn:2584808",
        "tgn:1000001",
        "tgn:7012149",
        "tgn:2001286",
        "tgn:7007524",
        "tgn:7029392"
    ],
    "tgn:id":2584808,
    "tgn:name":"Pink Creek",
    "tgn:placetype":[
        "aat:300008706"
    ]
},
  "bbox": [],
  "geometry": {"coordinates":[-115.1333,48.7167],"type":"Point"}
}