{
  "id": 2770569,
  "type": "Feature",
  "properties": {
    "tgn:hierarchy":[
        "tgn:2770569",
        "tgn:1000001",
        "tgn:7012149",
        "tgn:2000893",
        "tgn:7007256",
        "tgn:7029392"
    ],
    "tgn:id":2770569,
    "tgn:name":"Wilda",
    "tgn:placetype":[
        "aat:300008347"
    ]
},
  "bbox": [],
  "geometry": {"coordinates":[-92.7333,31.2833],"type":"Point"}
}