{
  "id": 7496983,
  "type": "Feature",
  "properties": {
    "tgn:hierarchy":[
        "tgn:7496983",
        "tgn:1000004",
        "tgn:1000454",
        "tgn:1000141",
        "tgn:7029392"
    ],
    "tgn:id":7496983,
    "tgn:name":"Xinghua Guoxiao",
    "tgn:placetype":[
        "aat:300006495"
    ]
},
  "bbox": [],
  "geometry": {"coordinates":[121.501491,25.203786],"type":"Point"}
}