{
  "id": 2614456,
  "type": "Feature",
  "properties": {
    "tgn:hierarchy":[
        "tgn:2614456",
        "tgn:1000001",
        "tgn:7012149",
        "tgn:2001761",
        "tgn:7007712",
        "tgn:7029392"
    ],
    "tgn:id":2614456,
    "tgn:name":"Reids Pond",
    "tgn:placetype":[
        "aat:300006191"
    ]
},
  "bbox": [],
  "geometry": {"coordinates":[-83.1167,34.7167],"type":"Point"}
}