{
  "id": 2753138,
  "type": "Feature",
  "properties": {
    "tgn:hierarchy":[
        "tgn:2753138",
        "tgn:1000001",
        "tgn:7012149",
        "tgn:2000233",
        "tgn:7007158",
        "tgn:7029392"
    ],
    "tgn:id":2753138,
    "tgn:name":"Water Tank Gulch",
    "tgn:placetype":[
        "aat:300008761"
    ]
},
  "bbox": [],
  "geometry": {"coordinates":[-108.15,37.5667],"type":"Point"}
}