{
  "id": 2710297,
  "type": "Feature",
  "properties": {
    "tgn:hierarchy":[
        "tgn:2710297",
        "tgn:1000001",
        "tgn:7012149",
        "tgn:7007248",
        "tgn:7029392"
    ],
    "tgn:id":2710297,
    "tgn:name":"Tallulah Mountain",
    "tgn:placetype":[
        "aat:300008798"
    ]
},
  "bbox": [],
  "geometry": {"coordinates":[-83.4167,34.7333],"type":"Point"}
}