{
  "id": 2419799,
  "type": "Feature",
  "properties": {
    "tgn:hierarchy":[
        "tgn:2419799",
        "tgn:1000001",
        "tgn:7012149",
        "tgn:2001711",
        "tgn:7007708",
        "tgn:7029392"
    ],
    "tgn:id":2419799,
    "tgn:name":"Jay Bird Mine",
    "tgn:placetype":[
        "aat:300000390"
    ]
},
  "bbox": [],
  "geometry": {"coordinates":[-123.1333,42.0833],"type":"Point"}
}