{
  "id": 7433106,
  "type": "Feature",
  "properties": {
    "tgn:hierarchy":[
        "tgn:7433106",
        "tgn:7005580",
        "tgn:1000001",
        "tgn:7005560",
        "tgn:7029392"
    ],
    "tgn:id":7433106,
    "tgn:name":"Yocnajab",
    "tgn:placetype":[
        "aat:300008347"
    ]
},
  "bbox": [],
  "geometry": {"coordinates":[-92.083333,16.233333],"type":"Point"}
}