{
  "id": 2339106,
  "type": "Feature",
  "properties": {
    "tgn:hierarchy":[
        "tgn:2339106",
        "tgn:1000001",
        "tgn:7012149",
        "tgn:2001981",
        "tgn:7007826",
        "tgn:7029392"
    ],
    "tgn:id":2339106,
    "tgn:name":"Franklin, Mount",
    "tgn:placetype":[
        "aat:300008798"
    ]
},
  "bbox": [],
  "geometry": {"coordinates":[-106.4833,31.8167],"type":"Point"}
}