{
  "id": 2353300,
  "type": "Feature",
  "properties": {
    "tgn:hierarchy":[
        "tgn:2353300",
        "tgn:1000001",
        "tgn:2000469",
        "tgn:7012149",
        "tgn:7007250",
        "tgn:7029392"
    ],
    "tgn:id":2353300,
    "tgn:name":"Gold Butte",
    "tgn:placetype":[
        "aat:300008798"
    ]
},
  "bbox": [],
  "geometry": {"coordinates":[-116.0333,46.7667],"type":"Point"}
}