{
  "id": 7034598,
  "type": "Feature",
  "properties": {
    "tgn:hierarchy":[
        "tgn:7034598",
        "tgn:1003500",
        "tgn:1000003",
        "tgn:7010380",
        "tgn:1000080",
        "tgn:7029392"
    ],
    "tgn:id":7034598,
    "tgn:name":"Masseria Patemisco",
    "tgn:placetype":[
        "aat:300000206"
    ]
},
  "bbox": [],
  "geometry": {"coordinates":[17.100833,40.540556],"type":"Point"}
}