{
  "id": 7424225,
  "type": "Feature",
  "properties": {
    "tgn:hierarchy":[
        "tgn:7424225",
        "tgn:1000001",
        "tgn:1001906",
        "tgn:7005560",
        "tgn:7029392"
    ],
    "tgn:id":7424225,
    "tgn:name":"Las Tueras, Picacho",
    "tgn:placetype":[
        "aat:300008795"
    ]
},
  "bbox": [],
  "geometry": {"coordinates":[-105.416944,22.922222],"type":"Point"}
}