{
  "id": 2495927,
  "type": "Feature",
  "properties": {
    "tgn:hierarchy":[
        "tgn:2495927",
        "tgn:1000001",
        "tgn:7012149",
        "tgn:1002494",
        "tgn:7007710",
        "tgn:7029392"
    ],
    "tgn:id":2495927,
    "tgn:name":"Mason Spring",
    "tgn:placetype":[
        "aat:300008697"
    ]
},
  "bbox": [],
  "geometry": {"coordinates":[-78.0333,40.4833],"type":"Point"}
}