<<<<<<< HEAD
{
  "id": 2767158,
  "type": "Feature",
  "properties": {
    "tgn:hierarchy":[
        "tgn:2767158",
        "tgn:1000001",
        "tgn:2001431",
        "tgn:7012149",
        "tgn:7007566",
        "tgn:7029392"
    ],
    "tgn:id":2767158,
    "tgn:name":"White Rock Draw",
    "tgn:placetype":[
        "aat:300008761"
    ]
},
  "bbox": [],
  "geometry": {"coordinates":[-108.3,34.9333],"type":"Point"}
}
=======
{"geometry":{"type":"Point","coordinates":[-108.300000,34.933300]},"type":"Feature","properties":{"hierarchy":["tgn:2767158","tgn:1000001","tgn:2001431","tgn:7012149","tgn:7007566","tgn:7029392"],"placetype":["aat:300008761"],"id":2767158,"name:xx":"White Rock Draw"}}
>>>>>>> 03f74aca74312dbeaf24d7e61306dd6a786dc3d0
