<<<<<<< HEAD
{
  "id": 7114114,
  "type": "Feature",
  "properties": {
    "tgn:hierarchy":[
        "tgn:7114114",
        "tgn:1000003",
        "tgn:7003689",
        "tgn:7000084",
        "tgn:7029392"
    ],
    "tgn:id":7114114,
    "tgn:name":"Rockhausen",
    "tgn:placetype":[
        "aat:300008347"
    ]
},
  "bbox": [],
  "geometry": {"coordinates":[11.05,50.9],"type":"Point"}
}
=======
{"geometry":{"type":"Point","coordinates":[11.050000,50.900000]},"type":"Feature","properties":{"hierarchy":["tgn:7114114","tgn:1000003","tgn:7003689","tgn:7000084","tgn:7029392"],"placetype":["aat:300008347"],"id":7114114,"name:xx":"Rockhausen"}}
>>>>>>> 03f74aca74312dbeaf24d7e61306dd6a786dc3d0
