{
  "id": 7588405,
  "type": "Feature",
  "properties": {
    "tgn:hierarchy":[
        "tgn:7588405",
        "tgn:1000004",
        "tgn:7000198",
        "tgn:1001977",
        "tgn:7029392"
    ],
    "tgn:id":7588405,
    "tgn:name:en":"Mith\u0101kh\u0101li",
    "tgn:placetype":[
        "aat:300008347"
    ]
},
  "bbox": [],
  "geometry": {"coordinates":[88.798889,22.319167],"type":"Point"}
}