{
  "id": 2564787,
  "type": "Feature",
  "properties": {
    "tgn:hierarchy":[
        "tgn:2564787",
        "tgn:2000090",
        "tgn:1000001",
        "tgn:7006451",
        "tgn:7012149",
        "tgn:7029392"
    ],
    "tgn:id":2564787,
    "tgn:name":"Paddy Fork Tank",
    "tgn:placetype":[
        "aat:300006191"
    ]
},
  "bbox": [],
  "geometry": {"coordinates":[-109.1167,33.9167],"type":"Point"}
}