{
  "id": 2424390,
  "type": "Feature",
  "properties": {
    "tgn:hierarchy":[
        "tgn:2424390",
        "tgn:1000001",
        "tgn:7012149",
        "tgn:7007828",
        "tgn:7029392"
    ],
    "tgn:id":2424390,
    "tgn:name":"Johnson Brook",
    "tgn:placetype":[
        "aat:300008699"
    ]
},
  "bbox": [],
  "geometry": {"coordinates":[-72.7333,43.6833],"type":"Point"}
}