{
  "id": 2137663,
  "type": "Feature",
  "properties": {
    "tgn:hierarchy":[
        "tgn:2137663",
        "tgn:1000001",
        "tgn:7012149",
        "tgn:2001461",
        "tgn:7007568",
        "tgn:7029392"
    ],
    "tgn:id":2137663,
    "tgn:name":"Arnold Pond",
    "tgn:placetype":[
        "aat:300008680"
    ]
},
  "bbox": [],
  "geometry": {"coordinates":[-73.6167,43.8667],"type":"Point"}
}