<<<<<<< HEAD
{
  "id": 7118002,
  "type": "Feature",
  "properties": {
    "tgn:hierarchy":[
        "tgn:7118002",
        "tgn:1000003",
        "tgn:7003676",
        "tgn:7000084",
        "tgn:7029392"
    ],
    "tgn:id":7118002,
    "tgn:name":"Olthuis",
    "tgn:placetype":[
        "aat:300000206"
    ]
},
  "bbox": [],
  "geometry": {"coordinates":[6.8,52.55],"type":"Point"}
}
=======
{"geometry":{"type":"Point","coordinates":[6.800000,52.550000]},"type":"Feature","properties":{"hierarchy":["tgn:7118002","tgn:1000003","tgn:7003676","tgn:7000084","tgn:7029392"],"placetype":["aat:300000206"],"id":7118002,"name:xx":"Olthuis"}}
>>>>>>> 03f74aca74312dbeaf24d7e61306dd6a786dc3d0
