{
  "id": 7132937,
  "type": "Feature",
  "properties": {
    "tgn:hierarchy":[
        "tgn:7132937",
        "tgn:1000003",
        "tgn:7003689",
        "tgn:7000084",
        "tgn:7029392"
    ],
    "tgn:id":7132937,
    "tgn:name":"M\u00fchlen-Berg",
    "tgn:placetype":[
        "aat:300008777"
    ]
},
  "bbox": [],
  "geometry": {"coordinates":[11.766667,50.75],"type":"Point"}
}