{
  "id": 2050216,
  "type": "Feature",
  "properties": {
    "tgn:hierarchy":[
        "tgn:2050216",
        "tgn:1000001",
        "tgn:1002665",
        "tgn:7012149",
        "tgn:2050214",
        "tgn:7007517",
        "tgn:7029392"
    ],
    "tgn:id":2050216,
    "tgn:name":"Auburndale",
    "tgn:placetype":[
        "aat:300387331"
    ]
},
  "bbox": [],
  "geometry": {"coordinates":[-71.25,42.3333],"type":"Point"}
}