{
  "id": 2729741,
  "type": "Feature",
  "properties": {
    "tgn:hierarchy":[
        "tgn:2729741",
        "tgn:1000001",
        "tgn:7012149",
        "tgn:2002115",
        "tgn:7007827",
        "tgn:7029392"
    ],
    "tgn:id":2729741,
    "tgn:name":"Trough Hollow",
    "tgn:placetype":[
        "aat:300008761"
    ]
},
  "bbox": [],
  "geometry": {"coordinates":[-111.6333,40.8833],"type":"Point"}
}