{
  "id": 2703052,
  "type": "Feature",
  "properties": {
    "tgn:hierarchy":[
        "tgn:2703052",
        "tgn:1000001",
        "tgn:7012149",
        "tgn:2002125",
        "tgn:7007827",
        "tgn:7029392"
    ],
    "tgn:id":2703052,
    "tgn:name":"Sumac Hollow",
    "tgn:placetype":[
        "aat:300008761"
    ]
},
  "bbox": [],
  "geometry": {"coordinates":[-111.6667,40.35],"type":"Point"}
}