{
  "id": 2610383,
  "type": "Feature",
  "properties": {
    "tgn:hierarchy":[
        "tgn:2610383",
        "tgn:1000001",
        "tgn:7012149",
        "tgn:2001284",
        "tgn:7007524",
        "tgn:7029392"
    ],
    "tgn:id":2610383,
    "tgn:name":"Red Butte Creek",
    "tgn:placetype":[
        "aat:300008706"
    ]
},
  "bbox": [],
  "geometry": {"coordinates":[-113.1167,47.5833],"type":"Point"}
}