{
  "id": 2614666,
  "type": "Feature",
  "properties": {
    "tgn:hierarchy":[
        "tgn:2614666",
        "tgn:7002659",
        "tgn:1000001",
        "tgn:7012149",
        "tgn:2000045",
        "tgn:7029392"
    ],
    "tgn:id":2614666,
    "tgn:name":"Remberts Bar",
    "tgn:placetype":[
        "aat:300132348"
    ]
},
  "bbox": [],
  "geometry": {"coordinates":[-87.95,32.2833],"type":"Point"}
}