<<<<<<< HEAD
{
  "id": 2330341,
  "type": "Feature",
  "properties": {
    "tgn:hierarchy":[
        "tgn:2330341",
        "tgn:7002659",
        "tgn:1000001",
        "tgn:7012149",
        "tgn:2000058",
        "tgn:7029392"
    ],
    "tgn:id":2330341,
    "tgn:name":"Flat Branch",
    "tgn:placetype":[
        "aat:300008699"
    ]
},
  "bbox": [],
  "geometry": {"coordinates":[-86.5,33.1333],"type":"Point"}
}
=======
{"geometry":{"type":"Point","coordinates":[-86.500000,33.133300]},"type":"Feature","properties":{"hierarchy":["tgn:2330341","tgn:7002659","tgn:1000001","tgn:7012149","tgn:2000058","tgn:7029392"],"placetype":["aat:300008699"],"id":2330341,"name:xx":"Flat Branch"}}
>>>>>>> 03f74aca74312dbeaf24d7e61306dd6a786dc3d0
