{
  "id": 1087571,
  "type": "Feature",
  "properties": {
    "tgn:hierarchy":[
        "tgn:1087571",
        "tgn:7001242",
        "tgn:7016752",
        "tgn:7000350",
        "tgn:7029392"
    ],
    "tgn:id":1087571,
    "tgn:name":"Tadjenanet",
    "tgn:placetype":[
        "aat:300008347"
    ]
},
  "bbox": [],
  "geometry": {"coordinates":[5.9833,36.1167],"type":"Point"}
}