{
  "id": 2480589,
  "type": "Feature",
  "properties": {
    "tgn:hierarchy":[
        "tgn:2480589",
        "tgn:1000001",
        "tgn:7012149",
        "tgn:1002793",
        "tgn:7007240",
        "tgn:7029392"
    ],
    "tgn:id":2480589,
    "tgn:name":"Lakeland Highlands",
    "tgn:placetype":[
        "aat:300266640"
    ]
},
  "bbox": [],
  "geometry": {"coordinates":[-81.9167,27.95],"type":"Point"}
}