{
  "id": 7165829,
  "type": "Feature",
  "properties": {
    "tgn:hierarchy":[
        "tgn:7165829",
        "tgn:1000003",
        "tgn:7003682",
        "tgn:7000084",
        "tgn:7029392"
    ],
    "tgn:id":7165829,
    "tgn:name":"Hasen-Kopf",
    "tgn:placetype":[
        "aat:300008777"
    ]
},
  "bbox": [],
  "geometry": {"coordinates":[7.866667,49.05],"type":"Point"}
}