{
  "id": 7173361,
  "type": "Feature",
  "properties": {
    "tgn:hierarchy":[
        "tgn:7173361",
        "tgn:1000003",
        "tgn:7003677",
        "tgn:7000084",
        "tgn:7029392"
    ],
    "tgn:id":7173361,
    "tgn:name":"Haltepunkt Gr\u00fcnenbaum",
    "tgn:placetype":[
        "aat:300007783"
    ]
},
  "bbox": [],
  "geometry": {"coordinates":[7.616667,51.15],"type":"Point"}
}