{
  "id": 2658934,
  "type": "Feature",
  "properties": {
    "tgn:hierarchy":[
        "tgn:2658934",
        "tgn:1000001",
        "tgn:7012149",
        "tgn:1002690",
        "tgn:7007710",
        "tgn:7029392"
    ],
    "tgn:id":2658934,
    "tgn:name":"Sherry Lake",
    "tgn:placetype":[
        "aat:300008680"
    ]
},
  "bbox": [],
  "geometry": {"coordinates":[-75.2833,40.0833],"type":"Point"}
}