{
  "id": 2782651,
  "type": "Feature",
  "properties": {
    "tgn:hierarchy":[
        "tgn:2782651",
        "tgn:1000001",
        "tgn:7012149",
        "tgn:2000963",
        "tgn:7007520",
        "tgn:7029392"
    ],
    "tgn:id":2782651,
    "tgn:name":"Worham Creek",
    "tgn:placetype":[
        "aat:300008706"
    ]
},
  "bbox": [],
  "geometry": {"coordinates":[-88.5833,46.9833],"type":"Point"}
}