<<<<<<< HEAD
{
  "id": 7110812,
  "type": "Feature",
  "properties": {
    "tgn:hierarchy":[
        "tgn:7110812",
        "tgn:1000003",
        "tgn:7003687",
        "tgn:7000084",
        "tgn:7029392"
    ],
    "tgn:id":7110812,
    "tgn:name":"Rahnsee",
    "tgn:placetype":[
        "aat:300008680"
    ]
},
  "bbox": [],
  "geometry": {"coordinates":[12.1,52.766667],"type":"Point"}
}
=======
{"geometry":{"type":"Point","coordinates":[12.100000,52.766667]},"type":"Feature","properties":{"hierarchy":["tgn:7110812","tgn:1000003","tgn:7003687","tgn:7000084","tgn:7029392"],"placetype":["aat:300008680"],"id":7110812,"name:xx":"Rahnsee"}}
>>>>>>> 03f74aca74312dbeaf24d7e61306dd6a786dc3d0
