{
  "id": 7235083,
  "type": "Feature",
  "properties": {
    "tgn:hierarchy":[
        "tgn:7235083",
        "tgn:7002735",
        "tgn:7017076",
        "tgn:1000003",
        "tgn:1000074",
        "tgn:7029392"
    ],
    "tgn:id":7235083,
    "tgn:name":"Bolana\u00edika",
    "tgn:placetype":[
        "aat:300008347"
    ]
},
  "bbox": [],
  "geometry": {"coordinates":[22.316667,37.183333],"type":"Point"}
}