{
  "id": 7242795,
  "type": "Feature",
  "properties": {
    "tgn:hierarchy":[
        "tgn:7242795",
        "tgn:7003457",
        "tgn:1000003",
        "tgn:1000063",
        "tgn:7018236",
        "tgn:7029392"
    ],
    "tgn:id":7242795,
    "tgn:name":"Langedonk",
    "tgn:placetype":[
        "aat:300008347"
    ]
},
  "bbox": [],
  "geometry": {"coordinates":[3.405094,51.127166],"type":"Point"}
}