{
  "id": 7200149,
  "type": "Feature",
  "properties": {
    "tgn:hierarchy":[
        "tgn:7200149",
        "tgn:7003692",
        "tgn:1000003",
        "tgn:7000084",
        "tgn:7029392"
    ],
    "tgn:id":7200149,
    "tgn:name":"Eichb\u00fchl",
    "tgn:placetype":[
        "aat:300008347"
    ]
},
  "bbox": [],
  "geometry": {"coordinates":[9.983333,48.05],"type":"Point"}
}