{
  "id": 7146212,
  "type": "Feature",
  "properties": {
    "tgn:hierarchy":[
        "tgn:7146212",
        "tgn:1000003",
        "tgn:7000094",
        "tgn:7000084",
        "tgn:7029392"
    ],
    "tgn:id":7146212,
    "tgn:name":"Knaakr\u00fccken",
    "tgn:placetype":[
        "aat:300008713"
    ]
},
  "bbox": [],
  "geometry": {"coordinates":[13.733333,54.166667],"type":"Point"}
}