{
  "id": 7383445,
  "type": "Feature",
  "properties": {
    "tgn:hierarchy":[
        "tgn:7383445",
        "tgn:1000001",
        "tgn:7005595",
        "tgn:7005560",
        "tgn:7029392"
    ],
    "tgn:id":7383445,
    "tgn:name":"Otate, Islas",
    "tgn:placetype":[
        "aat:300008791"
    ]
},
  "bbox": [],
  "geometry": {"coordinates":[-108.233333,25.133333],"type":"Point"}
}