{
  "id": 2304422,
  "type": "Feature",
  "properties": {
    "tgn:hierarchy":[
        "tgn:2304422",
        "tgn:1000001",
        "tgn:2001429",
        "tgn:7012149",
        "tgn:7007566",
        "tgn:7029392"
    ],
    "tgn:id":2304422,
    "tgn:name":"Earth Tank",
    "tgn:placetype":[
        "aat:300006191"
    ]
},
  "bbox": [],
  "geometry": {"coordinates":[-107.9333,34.0833],"type":"Point"}
}