{
  "id": 7545989,
  "type": "Feature",
  "properties": {
    "tgn:hierarchy":[
        "tgn:7545989",
        "tgn:1000004",
        "tgn:7000198",
        "tgn:7016722",
        "tgn:7029392"
    ],
    "tgn:id":7545989,
    "tgn:name:en":"Bhola",
    "tgn:placetype":[
        "aat:300008347"
    ]
},
  "bbox": [],
  "geometry": {"coordinates":[77.57178,29.009105],"type":"Point"}
}