<<<<<<< HEAD
{
  "id": 2257268,
  "type": "Feature",
  "properties": {
    "tgn:hierarchy":[
        "tgn:2257268",
        "tgn:1000001",
        "tgn:7012149",
        "tgn:2001221",
        "tgn:7007523",
        "tgn:7029392"
    ],
    "tgn:id":2257268,
    "tgn:name":"Cornet Creek",
    "tgn:placetype":[
        "aat:300008706"
    ]
},
  "bbox": [],
  "geometry": {"coordinates":[-92.7333,38.4],"type":"Point"}
}
=======
{"geometry":{"type":"Point","coordinates":[-92.733300,38.400000]},"type":"Feature","properties":{"hierarchy":["tgn:2257268","tgn:1000001","tgn:7012149","tgn:2001221","tgn:7007523","tgn:7029392"],"placetype":["aat:300008706"],"id":2257268,"name:xx":"Cornet Creek"}}
>>>>>>> 03f74aca74312dbeaf24d7e61306dd6a786dc3d0
