{
  "id": 2339796,
  "type": "Feature",
  "properties": {
    "tgn:hierarchy":[
        "tgn:2339796",
        "tgn:1000001",
        "tgn:7012149",
        "tgn:2000276",
        "tgn:7007240",
        "tgn:7029392"
    ],
    "tgn:id":2339796,
    "tgn:name":"Freeman Bay",
    "tgn:placetype":[
        "aat:300008905"
    ]
},
  "bbox": [],
  "geometry": {"coordinates":[-84.5833,30.3667],"type":"Point"}
}