{
  "id": 2019457,
  "type": "Feature",
  "properties": {
    "tgn:hierarchy":[
        "tgn:2019457",
        "tgn:1000001",
        "tgn:7012149",
        "tgn:1002314",
        "tgn:7007240",
        "tgn:7029392"
    ],
    "tgn:id":2019457,
    "tgn:name":"Golden Glades Shopping Center",
    "tgn:placetype":[
        "aat:300247594"
    ]
},
  "bbox": [],
  "geometry": {"coordinates":[-80.2167,25.8833],"type":"Point"}
}