{
  "id": 2492401,
  "type": "Feature",
  "properties": {
    "tgn:hierarchy":[
        "tgn:2492401",
        "tgn:1000001",
        "tgn:7012149",
        "tgn:1003017",
        "tgn:7007710",
        "tgn:7029392"
    ],
    "tgn:id":2492401,
    "tgn:name":"Marguerite Reservoir",
    "tgn:placetype":[
        "aat:300006191"
    ]
},
  "bbox": [],
  "geometry": {"coordinates":[-79.4667,40.25],"type":"Point"}
}