{
  "id": 1107247,
  "type": "Feature",
  "properties": {
    "tgn:hierarchy":[
        "tgn:1107247",
        "tgn:1000001",
        "tgn:7012149",
        "tgn:2001716",
        "tgn:7007708",
        "tgn:7029392"
    ],
    "tgn:id":1107247,
    "tgn:name":"Fairview Peak",
    "tgn:placetype":[
        "aat:300008798"
    ]
},
  "bbox": [],
  "geometry": {"coordinates":[-122.65,43.5833],"type":"Point"}
}