<<<<<<< HEAD
{
  "id": 7482285,
  "type": "Feature",
  "properties": {
    "tgn:hierarchy":[
        "tgn:7482285",
        "tgn:1000004",
        "tgn:7001009",
        "tgn:1000141",
        "tgn:7029392"
    ],
    "tgn:id":7482285,
    "tgn:name":"Ganshu Nanfeng",
    "tgn:placetype":[
        "aat:300008798"
    ]
},
  "bbox": [],
  "geometry": {"coordinates":[121.38,24.280278],"type":"Point"}
}
=======
{"geometry":{"type":"Point","coordinates":[121.380000,24.280278]},"type":"Feature","properties":{"hierarchy":["tgn:7482285","tgn:1000004","tgn:7001009","tgn:1000141","tgn:7029392"],"placetype":["aat:300008798"],"id":7482285,"name:xx":"Ganshu Nanfeng"}}
>>>>>>> 03f74aca74312dbeaf24d7e61306dd6a786dc3d0
