{
  "id": 7492807,
  "type": "Feature",
  "properties": {
    "tgn:hierarchy":[
        "tgn:7492807",
        "tgn:7001010",
        "tgn:1000004",
        "tgn:1000141",
        "tgn:7029392"
    ],
    "tgn:id":7492807,
    "tgn:name":"Pinghe",
    "tgn:placetype":[
        "aat:300008347"
    ]
},
  "bbox": [],
  "geometry": {"coordinates":[121.521111,23.886667],"type":"Point"}
}