<<<<<<< HEAD
{
  "id": 2763154,
  "type": "Feature",
  "properties": {
    "tgn:hierarchy":[
        "tgn:2763154",
        "tgn:2001728",
        "tgn:1000001",
        "tgn:7012149",
        "tgn:7007712",
        "tgn:7029392"
    ],
    "tgn:id":2763154,
    "tgn:name":"Westview Heights",
    "tgn:placetype":[
        "aat:300008347"
    ]
},
  "bbox": [],
  "geometry": {"coordinates":[-82.6667,34.4833],"type":"Point"}
}
=======
{"geometry":{"type":"Point","coordinates":[-82.666700,34.483300]},"type":"Feature","properties":{"hierarchy":["tgn:2763154","tgn:2001728","tgn:1000001","tgn:7012149","tgn:7007712","tgn:7029392"],"placetype":["aat:300008347"],"id":2763154,"name:xx":"Westview Heights"}}
>>>>>>> 03f74aca74312dbeaf24d7e61306dd6a786dc3d0
