{
  "id": 2243575,
  "type": "Feature",
  "properties": {
    "tgn:hierarchy":[
        "tgn:2243575",
        "tgn:1000001",
        "tgn:7012149",
        "tgn:2001309",
        "tgn:7007524",
        "tgn:7029392"
    ],
    "tgn:id":2243575,
    "tgn:name":"Cleiv Spring",
    "tgn:placetype":[
        "aat:300008697"
    ]
},
  "bbox": [],
  "geometry": {"coordinates":[-111.8833,47.6833],"type":"Point"}
}