{
  "id": 1064904,
  "type": "Feature",
  "properties": {
    "tgn:hierarchy":[
        "tgn:1064904",
        "tgn:1000003",
        "tgn:4011927",
        "tgn:7006669",
        "tgn:7029392"
    ],
    "tgn:id":1064904,
    "tgn:name":"Ba\u010dka Topola",
    "tgn:placetype":[
        "aat:300008347"
    ]
},
  "bbox": [],
  "geometry": {"coordinates":[19.65,45.8167],"type":"Point"}
}