{
  "id": 7515489,
  "type": "Feature",
  "properties": {
    "tgn:hierarchy":[
        "tgn:7515489",
        "tgn:7000508",
        "tgn:1008380",
        "tgn:1000226",
        "tgn:1000006",
        "tgn:7029392"
    ],
    "tgn:id":7515489,
    "tgn:name:en":"Oneroa Bay",
    "tgn:placetype":[
        "aat:300132316"
    ]
},
  "bbox": [],
  "geometry": {"coordinates":[175.016667,-36.766667],"type":"Point"}
}