{
  "id": 1032937,
  "type": "Feature",
  "properties": {
    "tgn:hierarchy":[
        "tgn:1032937",
        "tgn:1000003",
        "tgn:7002888",
        "tgn:1000070",
        "tgn:7029392"
    ],
    "tgn:id":1032937,
    "tgn:name":"Distroff",
    "tgn:placetype":[
        "aat:300008347"
    ]
},
  "bbox": [],
  "geometry": {"coordinates":[6.2667,49.3333],"type":"Point"}
}