{
  "id": 7093046,
  "type": "Feature",
  "properties": {
    "tgn:hierarchy":[
        "tgn:7093046",
        "tgn:1000003",
        "tgn:7003677",
        "tgn:7000084",
        "tgn:7029392"
    ],
    "tgn:id":7093046,
    "tgn:name":"Schwalmtal",
    "tgn:placetype":[
        "aat:300387173"
    ]
},
  "bbox": [],
  "geometry": {"coordinates":[6.266667,51.216667],"type":"Point"}
}