<<<<<<< HEAD
{
  "id": 2764998,
  "type": "Feature",
  "properties": {
    "tgn:hierarchy":[
        "tgn:2764998",
        "tgn:1000001",
        "tgn:2001632",
        "tgn:7012149",
        "tgn:7007707",
        "tgn:7029392"
    ],
    "tgn:id":2764998,
    "tgn:name":"Whisky Creek",
    "tgn:placetype":[
        "aat:300008706"
    ]
},
  "bbox": [],
  "geometry": {"coordinates":[-97.5333,34.3],"type":"Point"}
}
=======
{"geometry":{"type":"Point","coordinates":[-97.533300,34.300000]},"type":"Feature","properties":{"hierarchy":["tgn:2764998","tgn:1000001","tgn:2001632","tgn:7012149","tgn:7007707","tgn:7029392"],"placetype":["aat:300008706"],"id":2764998,"name:xx":"Whisky Creek"}}
>>>>>>> 03f74aca74312dbeaf24d7e61306dd6a786dc3d0
