{
  "id": 7485692,
  "type": "Feature",
  "properties": {
    "tgn:hierarchy":[
        "tgn:7485692",
        "tgn:1000004",
        "tgn:7492971",
        "tgn:1000141",
        "tgn:7029392"
    ],
    "tgn:id":7485692,
    "tgn:name":"Fude Gong",
    "tgn:placetype":[
        "aat:300007595"
    ]
},
  "bbox": [],
  "geometry": {"coordinates":[120.725833,22.061111],"type":"Point"}
}