{
  "id": 2317419,
  "type": "Feature",
  "properties": {
    "tgn:hierarchy":[
        "tgn:2317419",
        "tgn:1000001",
        "tgn:7012149",
        "tgn:2001455",
        "tgn:7007566",
        "tgn:7029392"
    ],
    "tgn:id":2317419,
    "tgn:name":"Empire Mine",
    "tgn:placetype":[
        "aat:300000390"
    ]
},
  "bbox": [],
  "geometry": {"coordinates":[-107.55,32.95],"type":"Point"}
}