{
  "id": 7294310,
  "type": "Feature",
  "properties": {
    "tgn:hierarchy":[
        "tgn:7294310",
        "tgn:7002759",
        "tgn:7002845",
        "tgn:1000003",
        "tgn:1000095",
        "tgn:7029392"
    ],
    "tgn:id":7294310,
    "tgn:name":"Vera de Moncayo",
    "tgn:placetype":[
        "aat:300008347"
    ]
},
  "bbox": [],
  "geometry": {"coordinates":[-1.683333,41.816667],"type":"Point"}
}