{
  "id": 7205704,
  "type": "Feature",
  "properties": {
    "tgn:hierarchy":[
        "tgn:7205704",
        "tgn:7000096",
        "tgn:1000003",
        "tgn:7000084",
        "tgn:7029392"
    ],
    "tgn:id":7205704,
    "tgn:name":"Charlottenhof",
    "tgn:placetype":[
        "aat:300000206"
    ]
},
  "bbox": [],
  "geometry": {"coordinates":[12.683333,52.966667],"type":"Point"}
}