{
  "id": 2198288,
  "type": "Feature",
  "properties": {
    "tgn:hierarchy":[
        "tgn:2198288",
        "tgn:1000001",
        "tgn:2000924",
        "tgn:7012149",
        "tgn:7007515",
        "tgn:7029392"
    ],
    "tgn:id":2198288,
    "tgn:name":"Browns Cove",
    "tgn:placetype":[
        "aat:300132316"
    ]
},
  "bbox": [],
  "geometry": {"coordinates":[-68.8833,44.1167],"type":"Point"}
}