{
  "id": 7218186,
  "type": "Feature",
  "properties": {
    "tgn:hierarchy":[
        "tgn:7218186",
        "tgn:7011161",
        "tgn:7002674",
        "tgn:1000003",
        "tgn:1000074",
        "tgn:7029392"
    ],
    "tgn:id":7218186,
    "tgn:name":"Mon\u00ed Panag\u00edas",
    "tgn:placetype":[
        "aat:300000641"
    ]
},
  "bbox": [],
  "geometry": {"coordinates":[25.969167,38.283889],"type":"Point"}
}