{
  "id": 7556852,
  "type": "Feature",
  "properties": {
    "tgn:hierarchy":[
        "tgn:7556852",
        "tgn:1000004",
        "tgn:7000198",
        "tgn:1001894",
        "tgn:7029392"
    ],
    "tgn:id":7556852,
    "tgn:name:en":"Pindk\u0101p\u0101r",
    "tgn:placetype":[
        "aat:300008347"
    ]
},
  "bbox": [],
  "geometry": {"coordinates":[79.501119,21.803273],"type":"Point"}
}