{
  "id": 2187411,
  "type": "Feature",
  "properties": {
    "tgn:hierarchy":[
        "tgn:2187411",
        "tgn:1000001",
        "tgn:7012149",
        "tgn:1002418",
        "tgn:7007920",
        "tgn:7029392"
    ],
    "tgn:id":2187411,
    "tgn:name":"Boone Creek",
    "tgn:placetype":[
        "aat:300008706"
    ]
},
  "bbox": [],
  "geometry": {"coordinates":[-124.0833,47.1667],"type":"Point"}
}