{
  "id": 7387062,
  "type": "Feature",
  "properties": {
    "tgn:hierarchy":[
        "tgn:7387062",
        "tgn:1000001",
        "tgn:7005595",
        "tgn:7005560",
        "tgn:7029392"
    ],
    "tgn:id":7387062,
    "tgn:name":"Pueblo de Alaya",
    "tgn:placetype":[
        "aat:300008347"
    ]
},
  "bbox": [],
  "geometry": {"coordinates":[-106.878889,24.52],"type":"Point"}
}