{
  "id": 2610418,
  "type": "Feature",
  "properties": {
    "tgn:hierarchy":[
        "tgn:2610418",
        "tgn:1000001",
        "tgn:7012149",
        "tgn:2000220",
        "tgn:7007158",
        "tgn:7029392"
    ],
    "tgn:id":2610418,
    "tgn:name":"Red Canyon",
    "tgn:placetype":[
        "aat:300008761"
    ]
},
  "bbox": [],
  "geometry": {"coordinates":[-106.65,40.6667],"type":"Point"}
}