{
  "id": 1102932,
  "type": "Feature",
  "properties": {
    "tgn:hierarchy":[
        "tgn:1102932",
        "tgn:7000490",
        "tgn:1000006",
        "tgn:7006238",
        "tgn:7029392"
    ],
    "tgn:id":1102932,
    "tgn:name":"Lower Eltham Park",
    "tgn:placetype":[
        "aat:300008187"
    ]
},
  "bbox": [],
  "geometry": {"coordinates":[145.15,-37.75],"type":"Point"}
}