<<<<<<< HEAD
{
  "id": 2338743,
  "type": "Feature",
  "properties": {
    "tgn:hierarchy":[
        "tgn:2338743",
        "tgn:1000001",
        "tgn:7012149",
        "tgn:2001034",
        "tgn:7007521",
        "tgn:7029392"
    ],
    "tgn:id":2338743,
    "tgn:name":"Frank Bay",
    "tgn:placetype":[
        "aat:300132316"
    ]
},
  "bbox": [],
  "geometry": {"coordinates":[-93.2,48.6],"type":"Point"}
}
=======
{"geometry":{"type":"Point","coordinates":[-93.200000,48.600000]},"type":"Feature","properties":{"hierarchy":["tgn:2338743","tgn:1000001","tgn:7012149","tgn:2001034","tgn:7007521","tgn:7029392"],"placetype":["aat:300132316"],"id":2338743,"name:xx":"Frank Bay"}}
>>>>>>> 03f74aca74312dbeaf24d7e61306dd6a786dc3d0
