{
  "id": 7142031,
  "type": "Feature",
  "properties": {
    "tgn:hierarchy":[
        "tgn:7142031",
        "tgn:7003669",
        "tgn:1000003",
        "tgn:7000084",
        "tgn:7029392"
    ],
    "tgn:id":7142031,
    "tgn:name":"Luhe",
    "tgn:placetype":[
        "aat:300008699"
    ]
},
  "bbox": [],
  "geometry": {"coordinates":[12.15,49.583333],"type":"Point"}
}