{
  "id": 1076178,
  "type": "Feature",
  "properties": {
    "tgn:hierarchy":[
        "tgn:1076178",
        "tgn:1000004",
        "tgn:1001832",
        "tgn:7000198",
        "tgn:7029392"
    ],
    "tgn:id":1076178,
    "tgn:name:en":"Mangaldai",
    "tgn:placetype":[
        "aat:300008347"
    ]
},
  "bbox": [],
  "geometry": {"coordinates":[92.030469,26.442124],"type":"Point"}
}