{
  "id": 2295572,
  "type": "Feature",
  "properties": {
    "tgn:hierarchy":[
        "tgn:2295572",
        "tgn:1000001",
        "tgn:7012149",
        "tgn:2002046",
        "tgn:7007826",
        "tgn:7029392"
    ],
    "tgn:id":2295572,
    "tgn:name":"Dripping Springs",
    "tgn:placetype":[
        "aat:300008699"
    ]
},
  "bbox": [],
  "geometry": {"coordinates":[-100.9167,33.9833],"type":"Point"}
}