{
  "id": 2648004,
  "type": "Feature",
  "properties": {
    "tgn:hierarchy":[
        "tgn:2648004",
        "tgn:1000001",
        "tgn:7012149",
        "tgn:7007157",
        "tgn:2000189",
        "tgn:7029392"
    ],
    "tgn:id":2648004,
    "tgn:name":"Schoolhouse Hill",
    "tgn:placetype":[
        "aat:300008798"
    ]
},
  "bbox": [],
  "geometry": {"coordinates":[-122.7333,41.3667],"type":"Point"}
}