{
  "id": 1079509,
  "type": "Feature",
  "properties": {
    "tgn:hierarchy":[
        "tgn:1079509",
        "tgn:1000862",
        "tgn:1000004",
        "tgn:1000119",
        "tgn:7029392"
    ],
    "tgn:id":1079509,
    "tgn:name":"E\u1e6d \u1e6caiyiba",
    "tgn:placetype":[
        "aat:300008347"
    ]
},
  "bbox": [],
  "geometry": {"coordinates":[34.95,32.2333],"type":"Point"}
}