{
  "id": 2264843,
  "type": "Feature",
  "properties": {
    "tgn:hierarchy":[
        "tgn:2264843",
        "tgn:1000001",
        "tgn:7012149",
        "tgn:2000232",
        "tgn:7007158",
        "tgn:7029392"
    ],
    "tgn:id":2264843,
    "tgn:name":"Craig Raw Water Reservoir",
    "tgn:placetype":[
        "aat:300006191"
    ]
},
  "bbox": [],
  "geometry": {"coordinates":[-107.5833,40.4833],"type":"Point"}
}