{
  "id": 2679129,
  "type": "Feature",
  "properties": {
    "tgn:hierarchy":[
        "tgn:2679129",
        "tgn:1000001",
        "tgn:7012149",
        "tgn:2001711",
        "tgn:7007708",
        "tgn:7029392"
    ],
    "tgn:id":2679129,
    "tgn:name":"South Fork Keene Creek",
    "tgn:placetype":[
        "aat:300008706"
    ]
},
  "bbox": [],
  "geometry": {"coordinates":[-122.4667,42.0833],"type":"Point"}
}