{
  "id": 2057249,
  "type": "Feature",
  "properties": {
    "tgn:hierarchy":[
        "tgn:2057249",
        "tgn:1000001",
        "tgn:7012149",
        "tgn:2001144",
        "tgn:7007522",
        "tgn:7029392"
    ],
    "tgn:id":2057249,
    "tgn:name":"Pisgah",
    "tgn:placetype":[
        "aat:300008347"
    ]
},
  "bbox": [],
  "geometry": {"coordinates":[-88.6167,34.7333],"type":"Point"}
}