<<<<<<< HEAD
{
  "id": 2404964,
  "type": "Feature",
  "properties": {
    "tgn:hierarchy":[
        "tgn:2404964",
        "tgn:7006450",
        "tgn:1000001",
        "tgn:7012149",
        "tgn:2000089",
        "tgn:7029392"
    ],
    "tgn:id":2404964,
    "tgn:name":"Hudson Bay Creek",
    "tgn:placetype":[
        "aat:300008706"
    ]
},
  "bbox": [],
  "geometry": {"coordinates":[-150.6667,66.9333],"type":"Point"}
}
=======
{"geometry":{"type":"Point","coordinates":[-150.666700,66.933300]},"type":"Feature","properties":{"hierarchy":["tgn:2404964","tgn:7006450","tgn:1000001","tgn:7012149","tgn:2000089","tgn:7029392"],"placetype":["aat:300008706"],"id":2404964,"name:xx":"Hudson Bay Creek"}}
>>>>>>> 03f74aca74312dbeaf24d7e61306dd6a786dc3d0
