{
  "id": 2730004,
  "type": "Feature",
  "properties": {
    "tgn:hierarchy":[
        "tgn:2730004",
        "tgn:1000001",
        "tgn:7012149",
        "tgn:1002594",
        "tgn:7007920",
        "tgn:7029392"
    ],
    "tgn:id":2730004,
    "tgn:name":"Trout Creek",
    "tgn:placetype":[
        "aat:300008706"
    ]
},
  "bbox": [],
  "geometry": {"coordinates":[-122.2667,46.6667],"type":"Point"}
}