{
  "id": 7445326,
  "type": "Feature",
  "properties": {
    "tgn:hierarchy":[
        "tgn:7445326",
        "tgn:7002445",
        "tgn:1000003",
        "tgn:7008160",
        "tgn:7008591",
        "tgn:7029392"
    ],
    "tgn:id":7445326,
    "tgn:name:en":"Wayland Wood",
    "tgn:placetype":[
        "aat:300008863"
    ]
},
  "bbox": [],
  "geometry": {"coordinates":[0.833333,52.55],"type":"Point"}
}