<<<<<<< HEAD
{
  "id": 2253274,
  "type": "Feature",
  "properties": {
    "tgn:hierarchy":[
        "tgn:2253274",
        "tgn:1000001",
        "tgn:7012149",
        "tgn:7007158",
        "tgn:2000240",
        "tgn:7029392"
    ],
    "tgn:id":2253274,
    "tgn:name":"Conundrum Peak",
    "tgn:placetype":[
        "aat:300008798"
    ]
},
  "bbox": [],
  "geometry": {"coordinates":[-106.85,39.0],"type":"Point"}
}
=======
{"geometry":{"type":"Point","coordinates":[-106.850000,39.000000]},"type":"Feature","properties":{"hierarchy":["tgn:2253274","tgn:1000001","tgn:7012149","tgn:7007158","tgn:2000240","tgn:7029392"],"placetype":["aat:300008798"],"id":2253274,"name:xx":"Conundrum Peak"}}
>>>>>>> 03f74aca74312dbeaf24d7e61306dd6a786dc3d0
