{
  "id": 7321063,
  "type": "Feature",
  "properties": {
    "tgn:hierarchy":[
        "tgn:7321063",
        "tgn:1001708",
        "tgn:1000049",
        "tgn:1000002",
        "tgn:7029392"
    ],
    "tgn:id":7321063,
    "tgn:name":"Buitre, Morro del",
    "tgn:placetype":[
        "aat:300008795"
    ]
},
  "bbox": [],
  "geometry": {"coordinates":[-71.166667,-34.15],"type":"Point"}
}