{
  "id": 7524008,
  "type": "Feature",
  "properties": {
    "tgn:hierarchy":[
        "tgn:7524008",
        "tgn:7001242",
        "tgn:7016833",
        "tgn:1001110",
        "tgn:7029392"
    ],
    "tgn:id":7524008,
    "tgn:name:en":"El-Mahamdiyin",
    "tgn:placetype":[
        "aat:300005926"
    ]
},
  "bbox": [],
  "geometry": {"coordinates":[32.25372,29.339294],"type":"Point"}
}