{
  "id": 7275758,
  "type": "Feature",
  "properties": {
    "tgn:hierarchy":[
        "tgn:7275758",
        "tgn:1001692",
        "tgn:1000049",
        "tgn:1000002",
        "tgn:7029392"
    ],
    "tgn:id":7275758,
    "tgn:name":"Tranam\u00e1n",
    "tgn:placetype":[
        "aat:300008347"
    ]
},
  "bbox": [],
  "geometry": {"coordinates":[-72.983333,-38.266667],"type":"Point"}
}