{
  "id": 7365348,
  "type": "Feature",
  "properties": {
    "tgn:hierarchy":[
        "tgn:7365348",
        "tgn:7005581",
        "tgn:1000001",
        "tgn:7005560",
        "tgn:7029392"
    ],
    "tgn:id":7365348,
    "tgn:name":"Rancho El Socorro",
    "tgn:placetype":[
        "aat:300000241"
    ]
},
  "bbox": [],
  "geometry": {"coordinates":[-104.55,28.766667],"type":"Point"}
}