{
  "id": 7551235,
  "type": "Feature",
  "properties": {
    "tgn:hierarchy":[
        "tgn:7551235",
        "tgn:1000004",
        "tgn:7000198",
        "tgn:7016788",
        "tgn:7029392"
    ],
    "tgn:id":7551235,
    "tgn:name:en":"Ch\u0101vand",
    "tgn:placetype":[
        "aat:300008347"
    ]
},
  "bbox": [],
  "geometry": {"coordinates":[73.810294,24.187461],"type":"Point"}
}