{
  "id": 2494581,
  "type": "Feature",
  "properties": {
    "tgn:hierarchy":[
        "tgn:2494581",
        "tgn:1000001",
        "tgn:2000458",
        "tgn:7012149",
        "tgn:7007250",
        "tgn:7029392"
    ],
    "tgn:id":2494581,
    "tgn:name":"Martin Lake",
    "tgn:placetype":[
        "aat:300008680"
    ]
},
  "bbox": [],
  "geometry": {"coordinates":[-113.1333,43.2167],"type":"Point"}
}