{
  "id": 7567836,
  "type": "Feature",
  "properties": {
    "tgn:hierarchy":[
        "tgn:7567836",
        "tgn:1000004",
        "tgn:7000198",
        "tgn:7031786",
        "tgn:7029392"
    ],
    "tgn:id":7567836,
    "tgn:name:en":"N\u0101th\u016bpur",
    "tgn:placetype":[
        "aat:300008347"
    ]
},
  "bbox": [],
  "geometry": {"coordinates":[78.634857,29.791063],"type":"Point"}
}