{
  "id": 7431225,
  "type": "Feature",
  "properties": {
    "tgn:hierarchy":[
        "tgn:7431225",
        "tgn:7005583",
        "tgn:1000001",
        "tgn:7005560",
        "tgn:7029392"
    ],
    "tgn:id":7431225,
    "tgn:name":"La Posta, R\u00edo",
    "tgn:placetype":[
        "aat:300266554",
        "aat:300008699"
    ]
},
  "bbox": [],
  "geometry": {"coordinates":[-105.75,25.733333],"type":"Point"}
}