{
  "id": 1002425,
  "type": "Feature",
  "properties": {
    "tgn:hierarchy":[
        "tgn:1002425",
        "tgn:1000001",
        "tgn:7012149",
        "tgn:7007919",
        "tgn:7029392"
    ],
    "tgn:id":1002425,
    "tgn:name":"Greensville",
    "tgn:placetype":[
        "aat:300387145",
        "aat:300000771"
    ]
},
  "bbox": [],
  "geometry": {"coordinates":[-77.5667,36.6833],"type":"Point"}
}