{
  "id": 2235887,
  "type": "Feature",
  "properties": {
    "tgn:hierarchy":[
        "tgn:2235887",
        "tgn:1000001",
        "tgn:7012149",
        "tgn:2001494",
        "tgn:7007709",
        "tgn:7029392"
    ],
    "tgn:id":2235887,
    "tgn:name":"Chestnut Trails",
    "tgn:placetype":[
        "aat:300008347"
    ]
},
  "bbox": [],
  "geometry": {"coordinates":[-80.2333,36.2333],"type":"Point"}
}