{
  "id": 7582294,
  "type": "Feature",
  "properties": {
    "tgn:hierarchy":[
        "tgn:7582294",
        "tgn:1000004",
        "tgn:7000198",
        "tgn:7016883",
        "tgn:7029392"
    ],
    "tgn:id":7582294,
    "tgn:name:en":"Dadr\u0101la",
    "tgn:placetype":[
        "aat:300008347"
    ]
},
  "bbox": [],
  "geometry": {"coordinates":[76.850516,30.561973],"type":"Point"}
}