{
  "id": 2106483,
  "type": "Feature",
  "properties": {
    "tgn:hierarchy":[
        "tgn:2106483",
        "tgn:1000001",
        "tgn:7012149",
        "tgn:2001978",
        "tgn:7007826",
        "tgn:7029392"
    ],
    "tgn:id":2106483,
    "tgn:name":"Olden",
    "tgn:placetype":[
        "aat:300008347"
    ]
},
  "bbox": [],
  "geometry": {"coordinates":[-98.75,32.4167],"type":"Point"}
}