{
  "id": 2533296,
  "type": "Feature",
  "properties": {
    "tgn:hierarchy":[
        "tgn:2533296",
        "tgn:7006450",
        "tgn:1000001",
        "tgn:7012149",
        "tgn:2000079",
        "tgn:7029392"
    ],
    "tgn:id":2533296,
    "tgn:name":"Muskellunge Creek",
    "tgn:placetype":[
        "aat:300008706"
    ]
},
  "bbox": [],
  "geometry": {"coordinates":[-163.5667,65.5833],"type":"Point"}
}