<<<<<<< HEAD
{
  "id": 2255316,
  "type": "Feature",
  "properties": {
    "tgn:hierarchy":[
        "tgn:2255316",
        "tgn:7002659",
        "tgn:1000001",
        "tgn:2000015",
        "tgn:7012149",
        "tgn:7029392"
    ],
    "tgn:id":2255316,
    "tgn:name":"Coopers Creek",
    "tgn:placetype":[
        "aat:300008706"
    ]
},
  "bbox": [],
  "geometry": {"coordinates":[-85.95,31.4],"type":"Point"}
}
=======
{"geometry":{"type":"Point","coordinates":[-85.950000,31.400000]},"type":"Feature","properties":{"hierarchy":["tgn:2255316","tgn:7002659","tgn:1000001","tgn:2000015","tgn:7012149","tgn:7029392"],"placetype":["aat:300008706"],"id":2255316,"name:xx":"Coopers Creek"}}
>>>>>>> 03f74aca74312dbeaf24d7e61306dd6a786dc3d0
