{
  "id": 1096521,
  "type": "Feature",
  "properties": {
    "tgn:hierarchy":[
        "tgn:1096521",
        "tgn:7000490",
        "tgn:1000006",
        "tgn:7006238",
        "tgn:7029392"
    ],
    "tgn:id":1096521,
    "tgn:name":"Castlemaine",
    "tgn:placetype":[
        "aat:300008347"
    ]
},
  "bbox": [],
  "geometry": {"coordinates":[144.3167,-37.0833],"type":"Point"}
}