<<<<<<< HEAD
{
  "id": 2766571,
  "type": "Feature",
  "properties": {
    "tgn:hierarchy":[
        "tgn:2766571",
        "tgn:1000001",
        "tgn:7012149",
        "tgn:2001208",
        "tgn:7007523",
        "tgn:7029392"
    ],
    "tgn:id":2766571,
    "tgn:name":"White Oak Creek",
    "tgn:placetype":[
        "aat:300008706"
    ]
},
  "bbox": [],
  "geometry": {"coordinates":[-94.4667,38.9833],"type":"Point"}
}
=======
{"geometry":{"type":"Point","coordinates":[-94.466700,38.983300]},"type":"Feature","properties":{"hierarchy":["tgn:2766571","tgn:1000001","tgn:7012149","tgn:2001208","tgn:7007523","tgn:7029392"],"placetype":["aat:300008706"],"id":2766571,"name:xx":"White Oak Creek"}}
>>>>>>> 03f74aca74312dbeaf24d7e61306dd6a786dc3d0
