{
  "id": 7082946,
  "type": "Feature",
  "properties": {
    "tgn:hierarchy":[
        "tgn:7082946",
        "tgn:1000003",
        "tgn:7003688",
        "tgn:7000084",
        "tgn:7029392"
    ],
    "tgn:id":7082946,
    "tgn:name":"Wierenkamp",
    "tgn:placetype":[
        "aat:300008347"
    ]
},
  "bbox": [],
  "geometry": {"coordinates":[9.966667,53.883333],"type":"Point"}
}