<<<<<<< HEAD
{
  "id": 7358205,
  "type": "Feature",
  "properties": {
    "tgn:hierarchy":[
        "tgn:7358205",
        "tgn:7005583",
        "tgn:1000001",
        "tgn:7005560",
        "tgn:7029392"
    ],
    "tgn:id":7358205,
    "tgn:name":"Coto",
    "tgn:placetype":[
        "aat:300008347"
    ]
},
  "bbox": [],
  "geometry": {"coordinates":[-105.816667,23.783333],"type":"Point"}
}
=======
{"geometry":{"type":"Point","coordinates":[-105.816667,23.783333]},"type":"Feature","properties":{"hierarchy":["tgn:7358205","tgn:7005583","tgn:1000001","tgn:7005560","tgn:7029392"],"placetype":["aat:300008347"],"id":7358205,"name:xx":"Coto"}}
>>>>>>> 03f74aca74312dbeaf24d7e61306dd6a786dc3d0
