<<<<<<< HEAD
{
  "id": 7052013,
  "type": "Feature",
  "properties": {
    "tgn:hierarchy":[
        "tgn:7052013",
        "tgn:7005765",
        "tgn:1000003",
        "tgn:7003237",
        "tgn:1000080",
        "tgn:7029392"
    ],
    "tgn:id":7052013,
    "tgn:name":"Mosina",
    "tgn:placetype":[
        "aat:300008347"
    ]
},
  "bbox": [],
  "geometry": {"coordinates":[10.416667,45.533333],"type":"Point"}
}
=======
{"geometry":{"type":"Point","coordinates":[10.416667,45.533333]},"type":"Feature","properties":{"hierarchy":["tgn:7052013","tgn:7005765","tgn:1000003","tgn:7003237","tgn:1000080","tgn:7029392"],"placetype":["aat:300008347"],"id":7052013,"name:xx":"Mosina"}}
>>>>>>> 03f74aca74312dbeaf24d7e61306dd6a786dc3d0
