<<<<<<< HEAD
{
  "id": 7351976,
  "type": "Feature",
  "properties": {
    "tgn:hierarchy":[
        "tgn:7351976",
        "tgn:1000001",
        "tgn:7005594",
        "tgn:7005560",
        "tgn:7029392"
    ],
    "tgn:id":7351976,
    "tgn:name":"Calabazas",
    "tgn:placetype":[
        "aat:300008347"
    ]
},
  "bbox": [],
  "geometry": {"coordinates":[-99.45,21.516667],"type":"Point"}
}
=======
{"geometry":{"type":"Point","coordinates":[-99.450000,21.516667]},"type":"Feature","properties":{"hierarchy":["tgn:7351976","tgn:1000001","tgn:7005594","tgn:7005560","tgn:7029392"],"placetype":["aat:300008347"],"id":7351976,"name:xx":"Calabazas"}}
>>>>>>> 03f74aca74312dbeaf24d7e61306dd6a786dc3d0
