{
  "id": 1016310,
  "type": "Feature",
  "properties": {
    "tgn:hierarchy":[
        "tgn:1016310",
        "tgn:1001374",
        "tgn:1000001",
        "tgn:7004624",
        "tgn:7029392"
    ],
    "tgn:id":1016310,
    "tgn:name":"Bataban\u00f3",
    "tgn:placetype":[
        "aat:300008347"
    ]
},
  "bbox": [],
  "geometry": {"coordinates":[-82.2833,22.7167],"type":"Point"}
}