{
  "id": 7270816,
  "type": "Feature",
  "properties": {
    "tgn:hierarchy":[
        "tgn:7270816",
        "tgn:7003614",
        "tgn:1000003",
        "tgn:7016845",
        "tgn:7029392"
    ],
    "tgn:id":7270816,
    "tgn:name:nl":"Boswachterij Sleenerzand",
    "tgn:placetype":[
        "aat:300008187"
    ]
},
  "bbox": [],
  "geometry": {"coordinates":[6.733333,52.833333],"type":"Point"}
}