<<<<<<< HEAD
{
  "id": 2336314,
  "type": "Feature",
  "properties": {
    "tgn:hierarchy":[
        "tgn:2336314",
        "tgn:1000001",
        "tgn:7012149",
        "tgn:7014510",
        "tgn:7007920",
        "tgn:7029392"
    ],
    "tgn:id":2336314,
    "tgn:name":"Found Lakes",
    "tgn:placetype":[
        "aat:300008680"
    ]
},
  "bbox": [],
  "geometry": {"coordinates":[-121.25,48.4167],"type":"Point"}
}
=======
{"geometry":{"type":"Point","coordinates":[-121.250000,48.416700]},"type":"Feature","properties":{"hierarchy":["tgn:2336314","tgn:1000001","tgn:7012149","tgn:7014510","tgn:7007920","tgn:7029392"],"placetype":["aat:300008680"],"id":2336314,"name:xx":"Found Lakes"}}
>>>>>>> 03f74aca74312dbeaf24d7e61306dd6a786dc3d0
