<<<<<<< HEAD
{
  "id": 2709867,
  "type": "Feature",
  "properties": {
    "tgn:hierarchy":[
        "tgn:2709867",
        "tgn:1000001",
        "tgn:7012149",
        "tgn:2001896",
        "tgn:7007825",
        "tgn:7029392"
    ],
    "tgn:id":2709867,
    "tgn:name":"Tailings Pond Number Two",
    "tgn:placetype":[
        "aat:300006191"
    ]
},
  "bbox": [],
  "geometry": {"coordinates":[-87.1167,35.6667],"type":"Point"}
}
=======
{"geometry":{"type":"Point","coordinates":[-87.116700,35.666700]},"type":"Feature","properties":{"hierarchy":["tgn:2709867","tgn:1000001","tgn:7012149","tgn:2001896","tgn:7007825","tgn:7029392"],"placetype":["aat:300006191"],"id":2709867,"name:xx":"Tailings Pond Number Two"}}
>>>>>>> 03f74aca74312dbeaf24d7e61306dd6a786dc3d0
