{
  "id": 2623299,
  "type": "Feature",
  "properties": {
    "tgn:hierarchy":[
        "tgn:2623299",
        "tgn:1000001",
        "tgn:7012149",
        "tgn:2002383",
        "tgn:7007923",
        "tgn:7029392"
    ],
    "tgn:id":2623299,
    "tgn:name":"Rock Cabin Spring",
    "tgn:placetype":[
        "aat:300008697"
    ]
},
  "bbox": [],
  "geometry": {"coordinates":[-108.9667,42.1333],"type":"Point"}
}