{
  "id": 2028172,
  "type": "Feature",
  "properties": {
    "tgn:hierarchy":[
        "tgn:2028172",
        "tgn:1000001",
        "tgn:7012149",
        "tgn:1002446",
        "tgn:7007251",
        "tgn:7029392"
    ],
    "tgn:id":2028172,
    "tgn:name":"Hamilton",
    "tgn:placetype":[
        "aat:300008347"
    ]
},
  "bbox": [],
  "geometry": {"coordinates":[-91.3333,40.3833],"type":"Point"}
}