{
  "id": 7091204,
  "type": "Feature",
  "properties": {
    "tgn:hierarchy":[
        "tgn:7091204",
        "tgn:1000003",
        "tgn:7003676",
        "tgn:7000084",
        "tgn:7029392"
    ],
    "tgn:id":7091204,
    "tgn:name":"Vallen Moor",
    "tgn:placetype":[
        "aat:300386886"
    ]
},
  "bbox": [],
  "geometry": {"coordinates":[8.05,52.433333],"type":"Point"}
}