{
  "id": 7421615,
  "type": "Feature",
  "properties": {
    "tgn:hierarchy":[
        "tgn:7421615",
        "tgn:7005584",
        "tgn:1000001",
        "tgn:7005560",
        "tgn:7029392"
    ],
    "tgn:id":7421615,
    "tgn:name":"Derramadero",
    "tgn:placetype":[
        "aat:300008347"
    ]
},
  "bbox": [],
  "geometry": {"coordinates":[-101.413889,21.17],"type":"Point"}
}