{
  "id": 7170870,
  "type": "Feature",
  "properties": {
    "tgn:hierarchy":[
        "tgn:7170870",
        "tgn:1000003",
        "tgn:7003676",
        "tgn:7000084",
        "tgn:7029392"
    ],
    "tgn:id":7170870,
    "tgn:name":"Himmerheide",
    "tgn:placetype":[
        "aat:300387200"
    ]
},
  "bbox": [],
  "geometry": {"coordinates":[8.25,52.183333],"type":"Point"}
}