{
  "id": 2352309,
  "type": "Feature",
  "properties": {
    "tgn:hierarchy":[
        "tgn:2352309",
        "tgn:1000001",
        "tgn:7012149",
        "tgn:2002005",
        "tgn:7007826",
        "tgn:7029392"
    ],
    "tgn:id":2352309,
    "tgn:name":"Goat Canyon",
    "tgn:placetype":[
        "aat:300008761"
    ]
},
  "bbox": [],
  "geometry": {"coordinates":[-105.25,30.8333],"type":"Point"}
}