{
  "id": 7066649,
  "type": "Feature",
  "properties": {
    "tgn:hierarchy":[
        "tgn:7066649",
        "tgn:1000003",
        "tgn:7003678",
        "tgn:7000084",
        "tgn:7029392"
    ],
    "tgn:id":7066649,
    "tgn:name":"St\u00f6ckeshof",
    "tgn:placetype":[
        "aat:300000206"
    ]
},
  "bbox": [],
  "geometry": {"coordinates":[9.833333,50.55],"type":"Point"}
}