{
  "id": 1097764,
  "type": "Feature",
  "properties": {
    "tgn:hierarchy":[
        "tgn:1097764",
        "tgn:7000490",
        "tgn:1000006",
        "tgn:7001834",
        "tgn:7029392"
    ],
    "tgn:id":1097764,
    "tgn:name":"New Norcia",
    "tgn:placetype":[
        "aat:300008347"
    ]
},
  "bbox": [],
  "geometry": {"coordinates":[116.25,-30.9667],"type":"Point"}
}