{
  "id": 7155076,
  "type": "Feature",
  "properties": {
    "tgn:hierarchy":[
        "tgn:7155076",
        "tgn:7000096",
        "tgn:1000003",
        "tgn:7000084",
        "tgn:7029392"
    ],
    "tgn:id":7155076,
    "tgn:name":"Kessel-Berg",
    "tgn:placetype":[
        "aat:300008777"
    ]
},
  "bbox": [],
  "geometry": {"coordinates":[13.083333,52.266667],"type":"Point"}
}