{
  "id": 2543003,
  "type": "Feature",
  "properties": {
    "tgn:hierarchy":[
        "tgn:2543003",
        "tgn:1000001",
        "tgn:7012149",
        "tgn:2001544",
        "tgn:7007709",
        "tgn:7029392"
    ],
    "tgn:id":2543003,
    "tgn:name":"Noname",
    "tgn:placetype":[
        "aat:300006191"
    ]
},
  "bbox": [],
  "geometry": {"coordinates":[-82.8667,35.0833],"type":"Point"}
}