{
  "id": 7334693,
  "type": "Feature",
  "properties": {
    "tgn:hierarchy":[
        "tgn:7334693",
        "tgn:7002803",
        "tgn:1001647",
        "tgn:1000003",
        "tgn:1000095",
        "tgn:7029392"
    ],
    "tgn:id":7334693,
    "tgn:name":"El Estrecho",
    "tgn:placetype":[
        "aat:300008347"
    ]
},
  "bbox": [],
  "geometry": {"coordinates":[-2.25,38.433333],"type":"Point"}
}