{
  "id": 1049282,
  "type": "Feature",
  "properties": {
    "tgn:hierarchy":[
        "tgn:1049282",
        "tgn:1000003",
        "tgn:7024126",
        "tgn:7006366",
        "tgn:7029392"
    ],
    "tgn:id":1049282,
    "tgn:name":"Narol",
    "tgn:placetype":[
        "aat:300008347"
    ]
},
  "bbox": [],
  "geometry": {"coordinates":[23.3167,50.35],"type":"Point"}
}