<<<<<<< HEAD
{
  "id": 2339620,
  "type": "Feature",
  "properties": {
    "tgn:hierarchy":[
        "tgn:2339620",
        "tgn:1000001",
        "tgn:7012149",
        "tgn:2001874",
        "tgn:7007825",
        "tgn:7029392"
    ],
    "tgn:id":2339620,
    "tgn:name":"Fredonia",
    "tgn:placetype":[
        "aat:300008347"
    ]
},
  "bbox": [],
  "geometry": {"coordinates":[-89.4333,35.4],"type":"Point"}
}
=======
{"geometry":{"type":"Point","coordinates":[-89.433300,35.400000]},"type":"Feature","properties":{"hierarchy":["tgn:2339620","tgn:1000001","tgn:7012149","tgn:2001874","tgn:7007825","tgn:7029392"],"placetype":["aat:300008347"],"id":2339620,"name:xx":"Fredonia"}}
>>>>>>> 03f74aca74312dbeaf24d7e61306dd6a786dc3d0
