{
  "id": 2614159,
  "type": "Feature",
  "properties": {
    "tgn:hierarchy":[
        "tgn:2614159",
        "tgn:1000001",
        "tgn:7012149",
        "tgn:7007157",
        "tgn:1002656",
        "tgn:7029392"
    ],
    "tgn:id":2614159,
    "tgn:name":"Reeves Spring",
    "tgn:placetype":[
        "aat:300008697"
    ]
},
  "bbox": [],
  "geometry": {"coordinates":[-121.1667,37.15],"type":"Point"}
}