{
  "id": 7336758,
  "type": "Feature",
  "properties": {
    "tgn:hierarchy":[
        "tgn:7336758",
        "tgn:7002816",
        "tgn:1001647",
        "tgn:1000003",
        "tgn:1000095",
        "tgn:7029392"
    ],
    "tgn:id":7336758,
    "tgn:name":"Fontarr\u00f3n, Arroyo del",
    "tgn:placetype":[
        "aat:300266554",
        "aat:300008699"
    ]
},
  "bbox": [],
  "geometry": {"coordinates":[-4.333333,38.566667],"type":"Point"}
}