{
  "id": 7030985,
  "type": "Feature",
  "properties": {
    "tgn:hierarchy":[
        "tgn:7030985",
        "tgn:7002445",
        "tgn:1000003",
        "tgn:7012031",
        "tgn:7008591",
        "tgn:7029392"
    ],
    "tgn:id":7030985,
    "tgn:name:en":"Yelvertoft",
    "tgn:placetype":[
        "aat:300008347",
        "aat:300008372"
    ]
},
  "bbox": [],
  "geometry": {"coordinates":[-1.116667,52.366667],"type":"Point"}
}