{
  "id": 2215131,
  "type": "Feature",
  "properties": {
    "tgn:hierarchy":[
        "tgn:2215131",
        "tgn:1000001",
        "tgn:2001416",
        "tgn:7012149",
        "tgn:7007526",
        "tgn:7029392"
    ],
    "tgn:id":2215131,
    "tgn:name":"California Pioche Mine",
    "tgn:placetype":[
        "aat:300000390"
    ]
},
  "bbox": [],
  "geometry": {"coordinates":[-114.45,37.9167],"type":"Point"}
}