{
  "id": 7586840,
  "type": "Feature",
  "properties": {
    "tgn:hierarchy":[
        "tgn:7586840",
        "tgn:1000004",
        "tgn:7000198",
        "tgn:7000799",
        "tgn:7029392"
    ],
    "tgn:id":7586840,
    "tgn:name:en":"Keri",
    "tgn:placetype":[
        "aat:300008347"
    ]
},
  "bbox": [],
  "geometry": {"coordinates":[74.549585,32.94017],"type":"Point"}
}