{
  "id": 2569469,
  "type": "Feature",
  "properties": {
    "tgn:hierarchy":[
        "tgn:2569469",
        "tgn:1000001",
        "tgn:7012149",
        "tgn:1002387",
        "tgn:7007710",
        "tgn:7029392"
    ],
    "tgn:id":2569469,
    "tgn:name":"Parnell Knob",
    "tgn:placetype":[
        "aat:300008798"
    ]
},
  "bbox": [],
  "geometry": {"coordinates":[-77.85,39.9167],"type":"Point"}
}