{
  "id": 2389499,
  "type": "Feature",
  "properties": {
    "tgn:hierarchy":[
        "tgn:2389499",
        "tgn:1000001",
        "tgn:2000457",
        "tgn:7012149",
        "tgn:7007250",
        "tgn:7029392"
    ],
    "tgn:id":2389499,
    "tgn:name":"High Basin",
    "tgn:placetype":[
        "aat:300386845"
    ]
},
  "bbox": [],
  "geometry": {"coordinates":[-111.8667,43.1667],"type":"Point"}
}