{
  "id": 7337119,
  "type": "Feature",
  "properties": {
    "tgn:hierarchy":[
        "tgn:7337119",
        "tgn:7002820",
        "tgn:7030216",
        "tgn:1000003",
        "tgn:1000095",
        "tgn:7029392"
    ],
    "tgn:id":7337119,
    "tgn:name":"Cogolls",
    "tgn:placetype":[
        "aat:300008347"
    ]
},
  "bbox": [],
  "geometry": {"coordinates":[2.541148,42.085831],"type":"Point"}
}