{
  "id": 7578396,
  "type": "Feature",
  "properties": {
    "tgn:hierarchy":[
        "tgn:7578396",
        "tgn:1000004",
        "tgn:7000198",
        "tgn:1001895",
        "tgn:7029392"
    ],
    "tgn:id":7578396,
    "tgn:name:en":"Sirli",
    "tgn:placetype":[
        "aat:300008347"
    ]
},
  "bbox": [],
  "geometry": {"coordinates":[77.233333,19.516667],"type":"Point"}
}