<<<<<<< HEAD
{
  "id": 2409483,
  "type": "Feature",
  "properties": {
    "tgn:hierarchy":[
        "tgn:2409483",
        "tgn:1000001",
        "tgn:7012149",
        "tgn:2001909",
        "tgn:7007825",
        "tgn:7029392"
    ],
    "tgn:id":2409483,
    "tgn:name":"Idle Oaks",
    "tgn:placetype":[
        "aat:300008347"
    ]
},
  "bbox": [],
  "geometry": {"coordinates":[-84.5833,35.8],"type":"Point"}
}
=======
{"geometry":{"type":"Point","coordinates":[-84.583300,35.800000]},"type":"Feature","properties":{"hierarchy":["tgn:2409483","tgn:1000001","tgn:7012149","tgn:2001909","tgn:7007825","tgn:7029392"],"placetype":["aat:300008347"],"id":2409483,"name:xx":"Idle Oaks"}}
>>>>>>> 03f74aca74312dbeaf24d7e61306dd6a786dc3d0
