{
  "id": 2386900,
  "type": "Feature",
  "properties": {
    "tgn:hierarchy":[
        "tgn:2386900",
        "tgn:1000001",
        "tgn:7012149",
        "tgn:2000928",
        "tgn:7007515",
        "tgn:7029392"
    ],
    "tgn:id":2386900,
    "tgn:name":"Heron Lake",
    "tgn:placetype":[
        "aat:300132316"
    ]
},
  "bbox": [],
  "geometry": {"coordinates":[-69.2833,46.4833],"type":"Point"}
}