{
  "id": 7316020,
  "type": "Feature",
  "properties": {
    "tgn:hierarchy":[
        "tgn:7316020",
        "tgn:1001637",
        "tgn:1000049",
        "tgn:1000002",
        "tgn:7029392"
    ],
    "tgn:id":7316020,
    "tgn:name":"Caupolic\u00e1n",
    "tgn:placetype":[
        "aat:300387200"
    ]
},
  "bbox": [],
  "geometry": {"coordinates":[-73.016667,-36.85],"type":"Point"}
}