{
  "id": 7423002,
  "type": "Feature",
  "properties": {
    "tgn:hierarchy":[
        "tgn:7423002",
        "tgn:1000001",
        "tgn:7005601",
        "tgn:7005560",
        "tgn:7029392"
    ],
    "tgn:id":7423002,
    "tgn:name":"El Rodeo",
    "tgn:placetype":[
        "aat:300008347"
    ]
},
  "bbox": [],
  "geometry": {"coordinates":[-102.966667,21.85],"type":"Point"}
}