{
  "id": 7565540,
  "type": "Feature",
  "properties": {
    "tgn:hierarchy":[
        "tgn:7565540",
        "tgn:1000004",
        "tgn:7000198",
        "tgn:1001894",
        "tgn:7029392"
    ],
    "tgn:id":7565540,
    "tgn:name:en":"Monem\u0101to ka Khero",
    "tgn:placetype":[
        "aat:300008347"
    ]
},
  "bbox": [],
  "geometry": {"coordinates":[79.204157,24.740176],"type":"Point"}
}