{
  "id": 2121406,
  "type": "Feature",
  "properties": {
    "tgn:hierarchy":[
        "tgn:2121406",
        "tgn:1000001",
        "tgn:7012149",
        "tgn:2002326",
        "tgn:7007922",
        "tgn:7029392"
    ],
    "tgn:id":2121406,
    "tgn:name":"Hollandale",
    "tgn:placetype":[
        "aat:300008347"
    ]
},
  "bbox": [],
  "geometry": {"coordinates":[-89.9333,42.8667],"type":"Point"}
}