{
  "id": 7187122,
  "type": "Feature",
  "properties": {
    "tgn:hierarchy":[
        "tgn:7187122",
        "tgn:1000003",
        "tgn:7003677",
        "tgn:7000084",
        "tgn:7029392"
    ],
    "tgn:id":7187122,
    "tgn:name":"Eidinghauser-Berg",
    "tgn:placetype":[
        "aat:300008777"
    ]
},
  "bbox": [],
  "geometry": {"coordinates":[8.833333,52.25],"type":"Point"}
}