<<<<<<< HEAD
{
  "id": 7058565,
  "type": "Feature",
  "properties": {
    "tgn:hierarchy":[
        "tgn:7058565",
        "tgn:7003127",
        "tgn:1000003",
        "tgn:7008516",
        "tgn:1000080",
        "tgn:7029392"
    ],
    "tgn:id":7058565,
    "tgn:name":"Borgo di Bisano",
    "tgn:placetype":[
        "aat:300008347"
    ]
},
  "bbox": [],
  "geometry": {"coordinates":[11.383333,44.266667],"type":"Point"}
}
=======
{"geometry":{"type":"Point","coordinates":[11.383333,44.266667]},"type":"Feature","properties":{"hierarchy":["tgn:7058565","tgn:7003127","tgn:1000003","tgn:7008516","tgn:1000080","tgn:7029392"],"placetype":["aat:300008347"],"id":7058565,"name:xx":"Borgo di Bisano"}}
>>>>>>> 03f74aca74312dbeaf24d7e61306dd6a786dc3d0
