{
  "id": 7226032,
  "type": "Feature",
  "properties": {
    "tgn:hierarchy":[
        "tgn:7226032",
        "tgn:7002689",
        "tgn:7012056",
        "tgn:1000003",
        "tgn:1000074",
        "tgn:7029392"
    ],
    "tgn:id":7226032,
    "tgn:name":"Mournia\u00ed",
    "tgn:placetype":[
        "aat:300008347"
    ]
},
  "bbox": [],
  "geometry": {"coordinates":[24.009167,35.476389],"type":"Point"}
}