{
  "id": 2774176,
  "type": "Feature",
  "properties": {
    "tgn:hierarchy":[
        "tgn:2774176",
        "tgn:1000001",
        "tgn:7012149",
        "tgn:2001712",
        "tgn:7007708",
        "tgn:7029392"
    ],
    "tgn:id":2774176,
    "tgn:name":"Willow Creek Canyon",
    "tgn:placetype":[
        "aat:300008761"
    ]
},
  "bbox": [],
  "geometry": {"coordinates":[-121.1333,44.6333],"type":"Point"}
}