{
  "id": 2288004,
  "type": "Feature",
  "properties": {
    "tgn:hierarchy":[
        "tgn:2288004",
        "tgn:1000001",
        "tgn:7012149",
        "tgn:7007157",
        "tgn:2000185",
        "tgn:7029392"
    ],
    "tgn:id":2288004,
    "tgn:name":"Dingman Creek",
    "tgn:placetype":[
        "aat:300008706"
    ]
},
  "bbox": [],
  "geometry": {"coordinates":[-122.9667,39.6833],"type":"Point"}
}