{
  "id": 7228719,
  "type": "Feature",
  "properties": {
    "tgn:hierarchy":[
        "tgn:7228719",
        "tgn:7002741",
        "tgn:7017076",
        "tgn:1000003",
        "tgn:1000074",
        "tgn:7029392"
    ],
    "tgn:id":7228719,
    "tgn:name":"Kl\u00edtsikas",
    "tgn:placetype":[
        "aat:300008777"
    ]
},
  "bbox": [],
  "geometry": {"coordinates":[22.883333,38.033333],"type":"Point"}
}