<<<<<<< HEAD
{
  "id": 2765219,
  "type": "Feature",
  "properties": {
    "tgn:hierarchy":[
        "tgn:2765219",
        "tgn:1000001",
        "tgn:7016172",
        "tgn:7012149",
        "tgn:2000143",
        "tgn:7029392"
    ],
    "tgn:id":2765219,
    "tgn:name":"Whistling Lake",
    "tgn:placetype":[
        "aat:300008680"
    ]
},
  "bbox": [],
  "geometry": {"coordinates":[-91.05,34.7833],"type":"Point"}
}
=======
{"geometry":{"type":"Point","coordinates":[-91.050000,34.783300]},"type":"Feature","properties":{"hierarchy":["tgn:2765219","tgn:1000001","tgn:7016172","tgn:7012149","tgn:2000143","tgn:7029392"],"placetype":["aat:300008680"],"id":2765219,"name:xx":"Whistling Lake"}}
>>>>>>> 03f74aca74312dbeaf24d7e61306dd6a786dc3d0
