{
  "id": 2765219,
  "type": "Feature",
  "properties": {
    "tgn:hierarchy":[
        "tgn:2765219",
        "tgn:1000001",
        "tgn:7016172",
        "tgn:7012149",
        "tgn:2000143",
        "tgn:7029392"
    ],
    "tgn:id":2765219,
    "tgn:name":"Whistling Lake",
    "tgn:placetype":[
        "aat:300008680"
    ]
},
  "bbox": [],
  "geometry": {"coordinates":[-91.05,34.7833],"type":"Point"}
}