{
  "id": 7517077,
  "type": "Feature",
  "properties": {
    "tgn:hierarchy":[
        "tgn:7517077",
        "tgn:7016670",
        "tgn:1008380",
        "tgn:1000226",
        "tgn:1000006",
        "tgn:7029392"
    ],
    "tgn:id":7517077,
    "tgn:name:en":"Mangamingi",
    "tgn:placetype":[
        "aat:300008347"
    ]
},
  "bbox": [],
  "geometry": {"coordinates":[176.15,-39.133333],"type":"Point"}
}