<<<<<<< HEAD
{
  "id": 7051904,
  "type": "Feature",
  "properties": {
    "tgn:hierarchy":[
        "tgn:7051904",
        "tgn:1003506",
        "tgn:1000003",
        "tgn:7002993",
        "tgn:1000080",
        "tgn:7029392"
    ],
    "tgn:id":7051904,
    "tgn:name":"Pesarina, Torrente",
    "tgn:placetype":[
        "aat:300008699"
    ]
},
  "bbox": [],
  "geometry": {"coordinates":[12.859167,46.506389],"type":"Point"}
}
=======
{"geometry":{"type":"Point","coordinates":[12.859167,46.506389]},"type":"Feature","properties":{"hierarchy":["tgn:7051904","tgn:1003506","tgn:1000003","tgn:7002993","tgn:1000080","tgn:7029392"],"placetype":["aat:300008699"],"id":7051904,"name:xx":"Pesarina, Torrente"}}
>>>>>>> 03f74aca74312dbeaf24d7e61306dd6a786dc3d0
