{
  "id": 2248129,
  "type": "Feature",
  "properties": {
    "tgn:hierarchy":[
        "tgn:2248129",
        "tgn:1000001",
        "tgn:7012149",
        "tgn:7007157",
        "tgn:2000187",
        "tgn:7029392"
    ],
    "tgn:id":2248129,
    "tgn:name":"Cold Brook Creek",
    "tgn:placetype":[
        "aat:300008706"
    ]
},
  "bbox": [],
  "geometry": {"coordinates":[-121.1167,40.0667],"type":"Point"}
}