{
  "id": 7398810,
  "type": "Feature",
  "properties": {
    "tgn:hierarchy":[
        "tgn:7398810",
        "tgn:1000001",
        "tgn:1001893",
        "tgn:7005560",
        "tgn:7029392"
    ],
    "tgn:id":7398810,
    "tgn:name":"San Jos\u00e9 Path\u00e9",
    "tgn:placetype":[
        "aat:300008347"
    ]
},
  "bbox": [],
  "geometry": {"coordinates":[-99.566667,19.45],"type":"Point"}
}