{
  "id": 2430712,
  "type": "Feature",
  "properties": {
    "tgn:hierarchy":[
        "tgn:2430712",
        "tgn:1002483",
        "tgn:7019080",
        "tgn:1000001",
        "tgn:7012149",
        "tgn:7007249",
        "tgn:7029392"
    ],
    "tgn:id":2430712,
    "tgn:name":"Kaluakauila Stream",
    "tgn:placetype":[
        "aat:300008699"
    ]
},
  "bbox": [],
  "geometry": {"coordinates":[-158.2167,21.55],"type":"Point"}
}