{
  "id": 2380744,
  "type": "Feature",
  "properties": {
    "tgn:hierarchy":[
        "tgn:2380744",
        "tgn:1000001",
        "tgn:7012149",
        "tgn:2002160",
        "tgn:7007919",
        "tgn:7029392"
    ],
    "tgn:id":2380744,
    "tgn:name":"Haw Patch Hill",
    "tgn:placetype":[
        "aat:300008798"
    ]
},
  "bbox": [],
  "geometry": {"coordinates":[-79.9833,36.8833],"type":"Point"}
}