{
  "id": 2732222,
  "type": "Feature",
  "properties": {
    "tgn:hierarchy":[
        "tgn:2732222",
        "tgn:7006450",
        "tgn:1000001",
        "tgn:7012149",
        "tgn:2124005",
        "tgn:7029392"
    ],
    "tgn:id":2732222,
    "tgn:name":"Tunusiktok Lake",
    "tgn:placetype":[
        "aat:300008680"
    ]
},
  "bbox": [],
  "geometry": {"coordinates":[-162.2333,69.55],"type":"Point"}
}