{
  "id": 7376336,
  "type": "Feature",
  "properties": {
    "tgn:hierarchy":[
        "tgn:7376336",
        "tgn:7005586",
        "tgn:1000001",
        "tgn:7005560",
        "tgn:7029392"
    ],
    "tgn:id":7376336,
    "tgn:name":"La Tapona",
    "tgn:placetype":[
        "aat:300008347"
    ]
},
  "bbox": [],
  "geometry": {"coordinates":[-101.916667,21.216667],"type":"Point"}
}