{
  "id": 2437390,
  "type": "Feature",
  "properties": {
    "tgn:hierarchy":[
        "tgn:2437390",
        "tgn:7006450",
        "tgn:1000001",
        "tgn:7012149",
        "tgn:2124005",
        "tgn:7029392"
    ],
    "tgn:id":2437390,
    "tgn:name":"Kimikpaurauk River",
    "tgn:placetype":[
        "aat:300008707"
    ]
},
  "bbox": [],
  "geometry": {"coordinates":[-142.7667,69.9167],"type":"Point"}
}