{
  "id": 2776023,
  "type": "Feature",
  "properties": {
    "tgn:hierarchy":[
        "tgn:2776023",
        "tgn:1000001",
        "tgn:7006451",
        "tgn:7012149",
        "tgn:2000098",
        "tgn:7029392"
    ],
    "tgn:id":2776023,
    "tgn:name":"Wilson Ridge",
    "tgn:placetype":[
        "aat:300266640"
    ]
},
  "bbox": [],
  "geometry": {"coordinates":[-114.5833,35.9667],"type":"Point"}
}