<<<<<<< HEAD
{
  "id": 2157891,
  "type": "Feature",
  "properties": {
    "tgn:hierarchy":[
        "tgn:2157891",
        "tgn:1000001",
        "tgn:7012149",
        "tgn:1002789",
        "tgn:7007710",
        "tgn:7029392"
    ],
    "tgn:id":2157891,
    "tgn:name":"Beaver Lake",
    "tgn:placetype":[
        "aat:300006191"
    ]
},
  "bbox": [],
  "geometry": {"coordinates":[-74.85,41.3],"type":"Point"}
}
=======
{"geometry":{"type":"Point","coordinates":[-74.850000,41.300000]},"type":"Feature","properties":{"hierarchy":["tgn:2157891","tgn:1000001","tgn:7012149","tgn:1002789","tgn:7007710","tgn:7029392"],"placetype":["aat:300006191"],"id":2157891,"name:xx":"Beaver Lake"}}
>>>>>>> 03f74aca74312dbeaf24d7e61306dd6a786dc3d0
