{
  "id": 7334782,
  "type": "Feature",
  "properties": {
    "tgn:hierarchy":[
        "tgn:7334782",
        "tgn:7002758",
        "tgn:7002823",
        "tgn:1000003",
        "tgn:1000095",
        "tgn:7029392"
    ],
    "tgn:id":7334782,
    "tgn:name":"El Puente",
    "tgn:placetype":[
        "aat:300008347"
    ]
},
  "bbox": [],
  "geometry": {"coordinates":[-6.966667,37.383333],"type":"Point"}
}