{
  "id": 7564930,
  "type": "Feature",
  "properties": {
    "tgn:hierarchy":[
        "tgn:7564930",
        "tgn:1000004",
        "tgn:7000198",
        "tgn:1001894",
        "tgn:7029392"
    ],
    "tgn:id":7564930,
    "tgn:name:en":"Hing\u0101i Pah\u0101r",
    "tgn:placetype":[
        "aat:300008777"
    ]
},
  "bbox": [],
  "geometry": {"coordinates":[79.125389,24.900946],"type":"Point"}
}