{
  "id": 7566223,
  "type": "Feature",
  "properties": {
    "tgn:hierarchy":[
        "tgn:7566223",
        "tgn:1000004",
        "tgn:7000198",
        "tgn:7016722",
        "tgn:7029392"
    ],
    "tgn:id":7566223,
    "tgn:name:en":"D\u016bri Reserved Forest",
    "tgn:placetype":[
        "aat:300008865"
    ]
},
  "bbox": [],
  "geometry": {"coordinates":[79.227846,25.747741],"type":"Point"}
}