{
  "id": 7494703,
  "type": "Feature",
  "properties": {
    "tgn:hierarchy":[
        "tgn:7494703",
        "tgn:1000004",
        "tgn:7001014",
        "tgn:1000141",
        "tgn:7029392"
    ],
    "tgn:id":7494703,
    "tgn:name":"Guoxizi Qiao",
    "tgn:placetype":[
        "aat:300007836"
    ]
},
  "bbox": [],
  "geometry": {"coordinates":[120.458411,23.733089],"type":"Point"}
}