{
  "id": 7261551,
  "type": "Feature",
  "properties": {
    "tgn:concordances":{
        "gn:id":"2757085"
    },
    "tgn:hierarchy":[
        "tgn:7261551",
        "tgn:1000003",
        "tgn:7003632",
        "tgn:7016845",
        "tgn:7029392"
    ],
    "tgn:id":7261551,
    "tgn:name:nl":"De Rotte",
    "tgn:placetype":[
        "aat:300008347"
    ]
},
  "bbox": [],
  "geometry": {"coordinates":[4.533333,51.966667],"type":"Point"}
}