{
  "id": 7137733,
  "type": "Feature",
  "properties": {
    "tgn:hierarchy":[
        "tgn:7137733",
        "tgn:1000003",
        "tgn:7003677",
        "tgn:7000084",
        "tgn:7029392"
    ],
    "tgn:id":7137733,
    "tgn:name":"Lentfort",
    "tgn:placetype":[
        "aat:300000206"
    ]
},
  "bbox": [],
  "geometry": {"coordinates":[6.766667,52.083333],"type":"Point"}
}