{
  "id": 2204206,
  "type": "Feature",
  "properties": {
    "tgn:hierarchy":[
        "tgn:2204206",
        "tgn:1000001",
        "tgn:7012149",
        "tgn:7007157",
        "tgn:1002621",
        "tgn:7029392"
    ],
    "tgn:id":2204206,
    "tgn:name":"Buena Vista Peak",
    "tgn:placetype":[
        "aat:300008798"
    ]
},
  "bbox": [],
  "geometry": {"coordinates":[-119.5167,37.5833],"type":"Point"}
}