{
  "id": 2273987,
  "type": "Feature",
  "properties": {
    "tgn:hierarchy":[
        "tgn:2273987",
        "tgn:1000001",
        "tgn:7012149",
        "tgn:1002755",
        "tgn:7007523",
        "tgn:7029392"
    ],
    "tgn:id":2273987,
    "tgn:name":"Daggetts Ford",
    "tgn:placetype":[
        "aat:300008347"
    ]
},
  "bbox": [],
  "geometry": {"coordinates":[-91.8333,38.3167],"type":"Point"}
}