{
  "id": 7149796,
  "type": "Feature",
  "properties": {
    "tgn:hierarchy":[
        "tgn:7149796",
        "tgn:7003669",
        "tgn:1000003",
        "tgn:7000084",
        "tgn:7029392"
    ],
    "tgn:id":7149796,
    "tgn:name":"Kronwit H\u00f6he",
    "tgn:placetype":[
        "aat:300008795"
    ]
},
  "bbox": [],
  "geometry": {"coordinates":[13.016667,49.233333],"type":"Point"}
}