{
  "id": 1088908,
  "type": "Feature",
  "properties": {
    "tgn:hierarchy":[
        "tgn:1088908",
        "tgn:7001242",
        "tgn:7016755",
        "tgn:1000159",
        "tgn:7029392"
    ],
    "tgn:id":1088908,
    "tgn:name":"Butsha",
    "tgn:placetype":[
        "aat:300008347"
    ]
},
  "bbox": [],
  "geometry": {"coordinates":[29.2167,0.95],"type":"Point"}
}