{
  "id": 7517221,
  "type": "Feature",
  "properties": {
    "tgn:hierarchy":[
        "tgn:7517221",
        "tgn:1008380",
        "tgn:7000507",
        "tgn:1000226",
        "tgn:1000006",
        "tgn:7029392"
    ],
    "tgn:id":7517221,
    "tgn:name:en":"Kopuatete",
    "tgn:placetype":[
        "aat:300008777"
    ]
},
  "bbox": [],
  "geometry": {"coordinates":[174.05,-36.183333],"type":"Point"}
}