{
  "id": 2583164,
  "type": "Feature",
  "properties": {
    "tgn:hierarchy":[
        "tgn:2583164",
        "tgn:1000001",
        "tgn:2001485",
        "tgn:7012149",
        "tgn:7007709",
        "tgn:7029392"
    ],
    "tgn:id":2583164,
    "tgn:name":"Pine Log Bay",
    "tgn:placetype":[
        "aat:300008905"
    ]
},
  "bbox": [],
  "geometry": {"coordinates":[-78.7833,34.35],"type":"Point"}
}