{
  "id": 2298394,
  "type": "Feature",
  "properties": {
    "tgn:hierarchy":[
        "tgn:2298394",
        "tgn:1000001",
        "tgn:7012149",
        "tgn:2002276",
        "tgn:7013961",
        "tgn:7029392"
    ],
    "tgn:id":2298394,
    "tgn:name":"Dry Ridge",
    "tgn:placetype":[
        "aat:300266640"
    ]
},
  "bbox": [],
  "geometry": {"coordinates":[-80.5167,39.9167],"type":"Point"}
}