{
  "id": 2735759,
  "type": "Feature",
  "properties": {
    "tgn:hierarchy":[
        "tgn:2735759",
        "tgn:1000001",
        "tgn:7012149",
        "tgn:2000980",
        "tgn:7007520",
        "tgn:7029392"
    ],
    "tgn:id":2735759,
    "tgn:name":"Twin Lake",
    "tgn:placetype":[
        "aat:300008680"
    ]
},
  "bbox": [],
  "geometry": {"coordinates":[-85.2667,44.35],"type":"Point"}
}