<<<<<<< HEAD
{
  "id": 2155456,
  "type": "Feature",
  "properties": {
    "tgn:hierarchy":[
        "tgn:2155456",
        "tgn:1000001",
        "tgn:1002218",
        "tgn:7012149",
        "tgn:7007157",
        "tgn:7029392"
    ],
    "tgn:id":2155456,
    "tgn:name":"Bear Ranch Creek",
    "tgn:placetype":[
        "aat:300008706"
    ]
},
  "bbox": [],
  "geometry": {"coordinates":[-121.35,39.8167],"type":"Point"}
}
=======
{"geometry":{"type":"Point","coordinates":[-121.350000,39.816700]},"type":"Feature","properties":{"hierarchy":["tgn:2155456","tgn:1000001","tgn:1002218","tgn:7012149","tgn:7007157","tgn:7029392"],"placetype":["aat:300008706"],"id":2155456,"name:xx":"Bear Ranch Creek"}}
>>>>>>> 03f74aca74312dbeaf24d7e61306dd6a786dc3d0
