{
  "id": 1112887,
  "type": "Feature",
  "properties": {
    "tgn:hierarchy":[
        "tgn:1112887",
        "tgn:7005685",
        "tgn:1000001",
        "tgn:1000296",
        "tgn:7024239",
        "tgn:7029392"
    ],
    "tgn:id":1112887,
    "tgn:name":"Deans Dundas Bay",
    "tgn:placetype":[
        "aat:300132316"
    ]
},
  "bbox": [],
  "geometry": {"coordinates":[-118.4167,72.25],"type":"Point"}
}