<<<<<<< HEAD
{
  "id": 2159059,
  "type": "Feature",
  "properties": {
    "tgn:hierarchy":[
        "tgn:2159059",
        "tgn:1000001",
        "tgn:2000467",
        "tgn:7012149",
        "tgn:7007250",
        "tgn:7029392"
    ],
    "tgn:id":2159059,
    "tgn:name":"Bed Spring",
    "tgn:placetype":[
        "aat:300008697"
    ]
},
  "bbox": [],
  "geometry": {"coordinates":[-114.2,42.2333],"type":"Point"}
}
=======
{"geometry":{"type":"Point","coordinates":[-114.200000,42.233300]},"type":"Feature","properties":{"hierarchy":["tgn:2159059","tgn:1000001","tgn:2000467","tgn:7012149","tgn:7007250","tgn:7029392"],"placetype":["aat:300008697"],"id":2159059,"name:xx":"Bed Spring"}}
>>>>>>> 03f74aca74312dbeaf24d7e61306dd6a786dc3d0
