{
  "id": 2371938,
  "type": "Feature",
  "properties": {
    "tgn:hierarchy":[
        "tgn:2371938",
        "tgn:1000001",
        "tgn:2000264",
        "tgn:7012149",
        "tgn:7007240",
        "tgn:7029392"
    ],
    "tgn:id":2371938,
    "tgn:name":"Half Creek",
    "tgn:placetype":[
        "aat:300008706"
    ]
},
  "bbox": [],
  "geometry": {"coordinates":[-81.7167,30.45],"type":"Point"}
}