{
  "id": 1017579,
  "type": "Feature",
  "properties": {
    "tgn:hierarchy":[
        "tgn:1017579",
        "tgn:1000001",
        "tgn:7005596",
        "tgn:7005560",
        "tgn:7029392"
    ],
    "tgn:id":1017579,
    "tgn:name":"Huimanguillo",
    "tgn:placetype":[
        "aat:300008347"
    ]
},
  "bbox": [],
  "geometry": {"coordinates":[-93.383333,17.85],"type":"Point"}
}