<<<<<<< HEAD
{
  "id": 2156719,
  "type": "Feature",
  "properties": {
    "tgn:hierarchy":[
        "tgn:2156719",
        "tgn:1000001",
        "tgn:7012149",
        "tgn:7007157",
        "tgn:1002621",
        "tgn:7029392"
    ],
    "tgn:id":2156719,
    "tgn:name":"Beasore Creek",
    "tgn:placetype":[
        "aat:300008706"
    ]
},
  "bbox": [],
  "geometry": {"coordinates":[-119.4667,37.4333],"type":"Point"}
}
=======
{"geometry":{"type":"Point","coordinates":[-119.466700,37.433300]},"type":"Feature","properties":{"hierarchy":["tgn:2156719","tgn:1000001","tgn:7012149","tgn:7007157","tgn:1002621","tgn:7029392"],"placetype":["aat:300008706"],"id":2156719,"name:xx":"Beasore Creek"}}
>>>>>>> 03f74aca74312dbeaf24d7e61306dd6a786dc3d0
