{
  "id": 2118077,
  "type": "Feature",
  "properties": {
    "tgn:hierarchy":[
        "tgn:2118077",
        "tgn:1000001",
        "tgn:7012149",
        "tgn:2002270",
        "tgn:7013961",
        "tgn:7029392"
    ],
    "tgn:id":2118077,
    "tgn:name":"East Bank",
    "tgn:placetype":[
        "aat:300008347"
    ]
},
  "bbox": [],
  "geometry": {"coordinates":[-81.4333,38.2167],"type":"Point"}
}