{
  "id": 2763369,
  "type": "Feature",
  "properties": {
    "tgn:hierarchy":[
        "tgn:2763369",
        "tgn:1000001",
        "tgn:7012149",
        "tgn:2000473",
        "tgn:7007250",
        "tgn:7029392"
    ],
    "tgn:id":2763369,
    "tgn:name":"Wet Weather Reservoir",
    "tgn:placetype":[
        "aat:300006191"
    ]
},
  "bbox": [],
  "geometry": {"coordinates":[-111.5667,44.2667],"type":"Point"}
}