{
  "id": 1136064,
  "type": "Feature",
  "properties": {
    "tgn:hierarchy":[
        "tgn:1136064",
        "tgn:7001242",
        "tgn:1000175",
        "tgn:7029392"
    ],
    "tgn:id":1136064,
    "tgn:name":"Sahel, Canal du",
    "tgn:placetype":[
        "aat:300006075"
    ]
},
  "bbox": [],
  "geometry": {"coordinates":[-6.0833,13.7333],"type":"Point"}
}