{
  "id": 1098785,
  "type": "Feature",
  "properties": {
    "tgn:hierarchy":[
        "tgn:1098785",
        "tgn:7000665",
        "tgn:1000223",
        "tgn:1000006",
        "tgn:7029392"
    ],
    "tgn:id":1098785,
    "tgn:name":"Bourail",
    "tgn:placetype":[
        "aat:300008347"
    ]
},
  "bbox": [],
  "geometry": {"coordinates":[165.4833,-21.5667],"type":"Point"}
}