{
  "id": 2227881,
  "type": "Feature",
  "properties": {
    "tgn:hierarchy":[
        "tgn:2227881",
        "tgn:1000001",
        "tgn:7012149",
        "tgn:2001754",
        "tgn:7007712",
        "tgn:7029392"
    ],
    "tgn:id":2227881,
    "tgn:name":"Cecils Inc Pond",
    "tgn:placetype":[
        "aat:300006191"
    ]
},
  "bbox": [],
  "geometry": {"coordinates":[-81.8167,34.5333],"type":"Point"}
}