{
  "id": 7052831,
  "type": "Feature",
  "properties": {
    "tgn:hierarchy":[
        "tgn:7052831",
        "tgn:1003483",
        "tgn:1000003",
        "tgn:7003240",
        "tgn:1000080",
        "tgn:7029392"
    ],
    "tgn:id":7052831,
    "tgn:name":"Malinello, Rio",
    "tgn:placetype":[
        "aat:300008699"
    ]
},
  "bbox": [],
  "geometry": {"coordinates":[12.716667,43.783333],"type":"Point"}
}