{
  "id": 7197125,
  "type": "Feature",
  "properties": {
    "tgn:hierarchy":[
        "tgn:7197125",
        "tgn:1000003",
        "tgn:7003687",
        "tgn:7000084",
        "tgn:7029392"
    ],
    "tgn:id":7197125,
    "tgn:name":"Domburg",
    "tgn:placetype":[
        "aat:300008777"
    ]
},
  "bbox": [],
  "geometry": {"coordinates":[11.316667,51.866667],"type":"Point"}
}