<<<<<<< HEAD
{
  "id": 2760883,
  "type": "Feature",
  "properties": {
    "tgn:hierarchy":[
        "tgn:2760883",
        "tgn:1000001",
        "tgn:1002753",
        "tgn:7012149",
        "tgn:7007828",
        "tgn:7029392"
    ],
    "tgn:id":2760883,
    "tgn:name":"West Hill",
    "tgn:placetype":[
        "aat:300008798"
    ]
},
  "bbox": [],
  "geometry": {"coordinates":[-72.4,44.6],"type":"Point"}
}
=======
{"geometry":{"type":"Point","coordinates":[-72.400000,44.600000]},"type":"Feature","properties":{"hierarchy":["tgn:2760883","tgn:1000001","tgn:1002753","tgn:7012149","tgn:7007828","tgn:7029392"],"placetype":["aat:300008798"],"id":2760883,"name:xx":"West Hill"}}
>>>>>>> 03f74aca74312dbeaf24d7e61306dd6a786dc3d0
