{
  "id": 2716770,
  "type": "Feature",
  "properties": {
    "tgn:hierarchy":[
        "tgn:2716770",
        "tgn:1000001",
        "tgn:7012149",
        "tgn:1002690",
        "tgn:7007710",
        "tgn:7029392"
    ],
    "tgn:id":2716770,
    "tgn:name":"The Woodlands",
    "tgn:placetype":[
        "aat:300008347"
    ]
},
  "bbox": [],
  "geometry": {"coordinates":[-75.15,40.1667],"type":"Point"}
}