{
  "id": 7545810,
  "type": "Feature",
  "properties": {
    "tgn:hierarchy":[
        "tgn:7545810",
        "tgn:1000004",
        "tgn:1001869",
        "tgn:7000198",
        "tgn:7029392"
    ],
    "tgn:id":7545810,
    "tgn:name:en":"Bhog\u0101t",
    "tgn:placetype":[
        "aat:300008347"
    ]
},
  "bbox": [],
  "geometry": {"coordinates":[69.239444,21.990278],"type":"Point"}
}