{
  "id": 2412018,
  "type": "Feature",
  "properties": {
    "tgn:hierarchy":[
        "tgn:2412018",
        "tgn:1000001",
        "tgn:7012149",
        "tgn:2001720",
        "tgn:7007708",
        "tgn:7029392"
    ],
    "tgn:id":2412018,
    "tgn:name":"Indian Ridge",
    "tgn:placetype":[
        "aat:300266640"
    ]
},
  "bbox": [],
  "geometry": {"coordinates":[-118.0167,45.9667],"type":"Point"}
}