{
  "id": 2657053,
  "type": "Feature",
  "properties": {
    "tgn:hierarchy":[
        "tgn:2657053",
        "tgn:1000001",
        "tgn:7012149",
        "tgn:2001723",
        "tgn:7007708",
        "tgn:7029392"
    ],
    "tgn:id":2657053,
    "tgn:name":"Sheep Mountain",
    "tgn:placetype":[
        "aat:300266640"
    ]
},
  "bbox": [],
  "geometry": {"coordinates":[-120.3333,44.5833],"type":"Point"}
}