{
  "id": 7341647,
  "type": "Feature",
  "properties": {
    "tgn:hierarchy":[
        "tgn:7341647",
        "tgn:7002834",
        "tgn:1000003",
        "tgn:7002786",
        "tgn:1000095",
        "tgn:7029392"
    ],
    "tgn:id":7341647,
    "tgn:name":"Berm\u00fan",
    "tgn:placetype":[
        "aat:300008347"
    ]
},
  "bbox": [],
  "geometry": {"coordinates":[-7.883333,42.583333],"type":"Point"}
}