{
  "id": 7071078,
  "type": "Feature",
  "properties": {
    "tgn:hierarchy":[
        "tgn:7071078",
        "tgn:1000003",
        "tgn:7000094",
        "tgn:7000084",
        "tgn:7029392"
    ],
    "tgn:id":7071078,
    "tgn:name":"Sylvin",
    "tgn:placetype":[
        "aat:300008347"
    ]
},
  "bbox": [],
  "geometry": {"coordinates":[13.35,54.55],"type":"Point"}
}