{
  "id": 2697796,
  "type": "Feature",
  "properties": {
    "tgn:hierarchy":[
        "tgn:2697796",
        "tgn:1000001",
        "tgn:7012149",
        "tgn:7020792",
        "tgn:7007524",
        "tgn:7029392"
    ],
    "tgn:id":2697796,
    "tgn:name":"Storm Lake Creek",
    "tgn:placetype":[
        "aat:300008706"
    ]
},
  "bbox": [],
  "geometry": {"coordinates":[-113.2333,46.0667],"type":"Point"}
}