{
  "id": 7031595,
  "type": "Feature",
  "properties": {
    "tgn:hierarchy":[
        "tgn:7031595",
        "tgn:7012158",
        "tgn:1000003",
        "tgn:7006657",
        "tgn:7029392"
    ],
    "tgn:id":7031595,
    "tgn:name:en":"Hrodna",
    "tgn:placetype":[
        "aat:300387256",
        "aat:300008347",
        "aat:300008389",
        "aat:300387222",
        "aat:300387220",
        "aat:300387302"
    ]
},
  "bbox": [],
  "geometry": {"coordinates":[23.813,53.681],"type":"Point"}
}