<<<<<<< HEAD
{
  "id": 2766769,
  "type": "Feature",
  "properties": {
    "tgn:hierarchy":[
        "tgn:2766769",
        "tgn:1000001",
        "tgn:7012149",
        "tgn:2002018",
        "tgn:7007826",
        "tgn:7029392"
    ],
    "tgn:id":2766769,
    "tgn:name":"White Oak Spring",
    "tgn:placetype":[
        "aat:300008697"
    ]
},
  "bbox": [],
  "geometry": {"coordinates":[-99.4167,30.0],"type":"Point"}
}
=======
{"geometry":{"type":"Point","coordinates":[-99.416700,30.000000]},"type":"Feature","properties":{"hierarchy":["tgn:2766769","tgn:1000001","tgn:7012149","tgn:2002018","tgn:7007826","tgn:7029392"],"placetype":["aat:300008697"],"id":2766769,"name:xx":"White Oak Spring"}}
>>>>>>> 03f74aca74312dbeaf24d7e61306dd6a786dc3d0
