{
  "id": 2523568,
  "type": "Feature",
  "properties": {
    "tgn:hierarchy":[
        "tgn:2523568",
        "tgn:1000001",
        "tgn:7012149",
        "tgn:2001067",
        "tgn:7007521",
        "tgn:7029392"
    ],
    "tgn:id":2523568,
    "tgn:name":"Moose Point",
    "tgn:placetype":[
        "aat:300008850"
    ]
},
  "bbox": [],
  "geometry": {"coordinates":[-91.8833,47.7167],"type":"Point"}
}