<<<<<<< HEAD
{
  "id": 7350771,
  "type": "Feature",
  "properties": {
    "tgn:hierarchy":[
        "tgn:7350771",
        "tgn:1000001",
        "tgn:7005593",
        "tgn:7005560",
        "tgn:7029392"
    ],
    "tgn:id":7350771,
    "tgn:name":"Blanco, Cerro",
    "tgn:placetype":[
        "aat:300008795"
    ]
},
  "bbox": [],
  "geometry": {"coordinates":[-100.05,20.133333],"type":"Point"}
}
=======
{"geometry":{"type":"Point","coordinates":[-100.050000,20.133333]},"type":"Feature","properties":{"hierarchy":["tgn:7350771","tgn:1000001","tgn:7005593","tgn:7005560","tgn:7029392"],"placetype":["aat:300008795"],"id":7350771,"name:xx":"Blanco, Cerro"}}
>>>>>>> 03f74aca74312dbeaf24d7e61306dd6a786dc3d0
