{
  "id": 2572289,
  "type": "Feature",
  "properties": {
    "tgn:hierarchy":[
        "tgn:2572289",
        "tgn:1000001",
        "tgn:7012149",
        "tgn:1002398",
        "tgn:7007706",
        "tgn:7029392"
    ],
    "tgn:id":2572289,
    "tgn:name":"Peaceful Valley",
    "tgn:placetype":[
        "aat:300008347"
    ]
},
  "bbox": [],
  "geometry": {"coordinates":[-83.9667,41.5333],"type":"Point"}
}