{
  "id": 2355094,
  "type": "Feature",
  "properties": {
    "tgn:hierarchy":[
        "tgn:2355094",
        "tgn:1000001",
        "tgn:2000921",
        "tgn:7012149",
        "tgn:7007515",
        "tgn:7029392"
    ],
    "tgn:id":2355094,
    "tgn:name":"Goodrich Corner",
    "tgn:placetype":[
        "aat:300008347"
    ]
},
  "bbox": [],
  "geometry": {"coordinates":[-70.05,44.7167],"type":"Point"}
}