{
  "id": 2364557,
  "type": "Feature",
  "properties": {
    "tgn:hierarchy":[
        "tgn:2364557",
        "tgn:1000001",
        "tgn:7012149",
        "tgn:1002779",
        "tgn:7007710",
        "tgn:7029392"
    ],
    "tgn:id":2364557,
    "tgn:name":"Green Valley Run",
    "tgn:placetype":[
        "aat:300008699"
    ]
},
  "bbox": [],
  "geometry": {"coordinates":[-77.3167,40.2833],"type":"Point"}
}