<<<<<<< HEAD
{
  "id": 2253450,
  "type": "Feature",
  "properties": {
    "tgn:hierarchy":[
        "tgn:2253450",
        "tgn:1000001",
        "tgn:7012149",
        "tgn:7007157",
        "tgn:1002857",
        "tgn:7029392"
    ],
    "tgn:id":2253450,
    "tgn:name":"Cook Canyon",
    "tgn:placetype":[
        "aat:300008761"
    ]
},
  "bbox": [],
  "geometry": {"coordinates":[-117.15,34.15],"type":"Point"}
}
=======
{"geometry":{"type":"Point","coordinates":[-117.150000,34.150000]},"type":"Feature","properties":{"hierarchy":["tgn:2253450","tgn:1000001","tgn:7012149","tgn:7007157","tgn:1002857","tgn:7029392"],"placetype":["aat:300008761"],"id":2253450,"name:xx":"Cook Canyon"}}
>>>>>>> 03f74aca74312dbeaf24d7e61306dd6a786dc3d0
