{
  "id": 2400796,
  "type": "Feature",
  "properties": {
    "tgn:hierarchy":[
        "tgn:2400796",
        "tgn:1000001",
        "tgn:1002714",
        "tgn:7012149",
        "tgn:7007159",
        "tgn:7029392"
    ],
    "tgn:id":2400796,
    "tgn:name":"Horse Pond",
    "tgn:placetype":[
        "aat:300008680"
    ]
},
  "bbox": [],
  "geometry": {"coordinates":[-72.25,41.45],"type":"Point"}
}