{
  "id": 7249963,
  "type": "Feature",
  "properties": {
    "tgn:hierarchy":[
        "tgn:7249963",
        "tgn:7007877",
        "tgn:1000003",
        "tgn:1000063",
        "tgn:4012014",
        "tgn:7029392"
    ],
    "tgn:id":7249963,
    "tgn:name":"Pachy Aubraine",
    "tgn:placetype":[
        "aat:300008347"
    ]
},
  "bbox": [],
  "geometry": {"coordinates":[3.883333,50.316667],"type":"Point"}
}