<<<<<<< HEAD
{
  "id": 7054133,
  "type": "Feature",
  "properties": {
    "tgn:hierarchy":[
        "tgn:7054133",
        "tgn:1001724",
        "tgn:1000003",
        "tgn:7003121",
        "tgn:1000080",
        "tgn:7029392"
    ],
    "tgn:id":7054133,
    "tgn:name":"Luna, Cala di",
    "tgn:placetype":[
        "aat:300132317"
    ]
},
  "bbox": [],
  "geometry": {"coordinates":[9.633333,40.233333],"type":"Point"}
}
=======
{"geometry":{"type":"Point","coordinates":[9.633333,40.233333]},"type":"Feature","properties":{"hierarchy":["tgn:7054133","tgn:1001724","tgn:1000003","tgn:7003121","tgn:1000080","tgn:7029392"],"placetype":["aat:300132317"],"id":7054133,"name:xx":"Luna, Cala di"}}
>>>>>>> 03f74aca74312dbeaf24d7e61306dd6a786dc3d0
