{
  "id": 2493468,
  "type": "Feature",
  "properties": {
    "tgn:hierarchy":[
        "tgn:2493468",
        "tgn:1000001",
        "tgn:1002949",
        "tgn:7012149",
        "tgn:7007159",
        "tgn:7029392"
    ],
    "tgn:id":2493468,
    "tgn:name":"Marsh Brook",
    "tgn:placetype":[
        "aat:300008699"
    ]
},
  "bbox": [],
  "geometry": {"coordinates":[-72.4333,41.8833],"type":"Point"}
}