{
  "id": 7221148,
  "type": "Feature",
  "properties": {
    "tgn:hierarchy":[
        "tgn:7221148",
        "tgn:7002715",
        "tgn:7002731",
        "tgn:1000003",
        "tgn:1000074",
        "tgn:7029392"
    ],
    "tgn:id":7221148,
    "tgn:name":"Synoikism\u00f3s Metrin\u00f3n",
    "tgn:placetype":[
        "aat:300008347"
    ]
},
  "bbox": [],
  "geometry": {"coordinates":[22.694167,40.735],"type":"Point"}
}