{
  "id": 7002324,
  "type": "Feature",
  "properties": {
    "tgn:hierarchy":[
        "tgn:7002324",
        "tgn:1001045",
        "tgn:1000004",
        "tgn:7018454",
        "tgn:1000144",
        "tgn:7029392"
    ],
    "tgn:id":7002324,
    "tgn:name":"Alaca",
    "tgn:placetype":[
        "aat:300008347",
        "aat:300000810",
        "aat:300167671",
        "aat:300008375"
    ]
},
  "bbox": [],
  "geometry": {"coordinates":[34.8667,40.1667],"type":"Point"}
}