{
  "id": 7281043,
  "type": "Feature",
  "properties": {
    "tgn:hierarchy":[
        "tgn:7281043",
        "tgn:1001702",
        "tgn:1000049",
        "tgn:1000002",
        "tgn:7029392"
    ],
    "tgn:id":7281043,
    "tgn:name":"Sheep, Isla",
    "tgn:placetype":[
        "aat:300008791"
    ]
},
  "bbox": [],
  "geometry": {"coordinates":[-68.066667,-55.533333],"type":"Point"}
}