{
  "id": 7307850,
  "type": "Feature",
  "properties": {
    "tgn:hierarchy":[
        "tgn:7307850",
        "tgn:1001623",
        "tgn:1000049",
        "tgn:1000002",
        "tgn:7029392"
    ],
    "tgn:id":7307850,
    "tgn:name":"Oeste, Morro",
    "tgn:placetype":[
        "aat:300008777"
    ]
},
  "bbox": [],
  "geometry": {"coordinates":[-75.133333,-44.816667],"type":"Point"}
}