{
  "id": 2316780,
  "type": "Feature",
  "properties": {
    "tgn:hierarchy":[
        "tgn:2316780",
        "tgn:1000001",
        "tgn:7012149",
        "tgn:2001306",
        "tgn:7007524",
        "tgn:7029392"
    ],
    "tgn:id":2316780,
    "tgn:name":"Emerald Lake",
    "tgn:placetype":[
        "aat:300008680"
    ]
},
  "bbox": [],
  "geometry": {"coordinates":[-112.4667,45.75],"type":"Point"}
}