{
  "id": 2514869,
  "type": "Feature",
  "properties": {
    "tgn:hierarchy":[
        "tgn:2514869",
        "tgn:7002659",
        "tgn:1000001",
        "tgn:2000016",
        "tgn:7012149",
        "tgn:7029392"
    ],
    "tgn:id":2514869,
    "tgn:name":"Miller Ridge",
    "tgn:placetype":[
        "aat:300266640"
    ]
},
  "bbox": [],
  "geometry": {"coordinates":[-87.9167,34.6667],"type":"Point"}
}