{
  "id": 7504699,
  "type": "Feature",
  "properties": {
    "tgn:hierarchy":[
        "tgn:7504699",
        "tgn:7000508",
        "tgn:1008380",
        "tgn:1000226",
        "tgn:1000006",
        "tgn:7029392"
    ],
    "tgn:id":7504699,
    "tgn:name:en":"Bean Rocks",
    "tgn:placetype":[
        "aat:300011692"
    ]
},
  "bbox": [],
  "geometry": {"coordinates":[174.832222,-36.834444],"type":"Point"}
}