{
  "id": 2163167,
  "type": "Feature",
  "properties": {
    "tgn:hierarchy":[
        "tgn:2163167",
        "tgn:1000001",
        "tgn:7012149",
        "tgn:2002264",
        "tgn:7013961",
        "tgn:7029392"
    ],
    "tgn:id":2163167,
    "tgn:name":"Bennett Mountain",
    "tgn:placetype":[
        "aat:300008798"
    ]
},
  "bbox": [],
  "geometry": {"coordinates":[-80.6833,37.8167],"type":"Point"}
}