{
  "id": 2451176,
  "type": "Feature",
  "properties": {
    "tgn:hierarchy":[
        "tgn:2451176",
        "tgn:1000001",
        "tgn:7012149",
        "tgn:2000811",
        "tgn:7007255",
        "tgn:7029392"
    ],
    "tgn:id":2451176,
    "tgn:name":"Little Asher Branch",
    "tgn:placetype":[
        "aat:300008699"
    ]
},
  "bbox": [],
  "geometry": {"coordinates":[-83.3833,37.1833],"type":"Point"}
}