{
  "id": 2132311,
  "type": "Feature",
  "properties": {
    "tgn:hierarchy":[
        "tgn:2132311",
        "tgn:1000001",
        "tgn:7012149",
        "tgn:7007256",
        "tgn:7029392"
    ],
    "tgn:id":2132311,
    "tgn:name":"Amite River Diversion Canal",
    "tgn:placetype":[
        "aat:300006075"
    ]
},
  "bbox": [],
  "geometry": {"coordinates":[-90.75,30.2333],"type":"Point"}
}