{
  "id": 2640784,
  "type": "Feature",
  "properties": {
    "tgn:hierarchy":[
        "tgn:2640784",
        "tgn:1000001",
        "tgn:7012149",
        "tgn:7007827",
        "tgn:7029392"
    ],
    "tgn:id":2640784,
    "tgn:name":"San Rafael Desert",
    "tgn:placetype":[
        "aat:300008805"
    ]
},
  "bbox": [],
  "geometry": {"coordinates":[-110.4333,38.6667],"type":"Point"}
}