{
  "id": 2264045,
  "type": "Feature",
  "properties": {
    "tgn:hierarchy":[
        "tgn:2264045",
        "tgn:1000001",
        "tgn:7012149",
        "tgn:7007157",
        "tgn:7014005",
        "tgn:7029392"
    ],
    "tgn:id":2264045,
    "tgn:name":"Coyote Ridge",
    "tgn:placetype":[
        "aat:300266640"
    ]
},
  "bbox": [],
  "geometry": {"coordinates":[-122.55,37.85],"type":"Point"}
}