{
  "id": 7443333,
  "type": "Feature",
  "properties": {
    "tgn:hierarchy":[
        "tgn:7443333",
        "tgn:7002445",
        "tgn:1000003",
        "tgn:7011961",
        "tgn:7008591",
        "tgn:7029392"
    ],
    "tgn:id":7443333,
    "tgn:name:en":"King Rock",
    "tgn:placetype":[
        "aat:300011692"
    ]
},
  "bbox": [],
  "geometry": {"coordinates":[-2.326667,50.627778],"type":"Point"}
}