{
  "id": 2672110,
  "type": "Feature",
  "properties": {
    "tgn:hierarchy":[
        "tgn:2672110",
        "tgn:1000001",
        "tgn:7012149",
        "tgn:1002506",
        "tgn:7007919",
        "tgn:7029392"
    ],
    "tgn:id":2672110,
    "tgn:name":"Smithfield Lake",
    "tgn:placetype":[
        "aat:300006191"
    ]
},
  "bbox": [],
  "geometry": {"coordinates":[-76.65,36.9667],"type":"Point"}
}