{
  "id": 2370691,
  "type": "Feature",
  "properties": {
    "tgn:hierarchy":[
        "tgn:2370691",
        "tgn:1000001",
        "tgn:7006451",
        "tgn:7012149",
        "tgn:2000103",
        "tgn:7029392"
    ],
    "tgn:id":2370691,
    "tgn:name":"Hackberry Tank",
    "tgn:placetype":[
        "aat:300006191"
    ]
},
  "bbox": [],
  "geometry": {"coordinates":[-113.1667,35.0167],"type":"Point"}
}