{
  "id": 7470368,
  "type": "Feature",
  "properties": {
    "tgn:hierarchy":[
        "tgn:7470368",
        "tgn:1000004",
        "tgn:7467799",
        "tgn:1000141",
        "tgn:7029392"
    ],
    "tgn:id":7470368,
    "tgn:name":"Buwei",
    "tgn:placetype":[
        "aat:300008347"
    ]
},
  "bbox": [],
  "geometry": {"coordinates":[120.48531,23.889637],"type":"Point"}
}