<<<<<<< HEAD
{
  "id": 2150306,
  "type": "Feature",
  "properties": {
    "tgn:hierarchy":[
        "tgn:2150306",
        "tgn:7006450",
        "tgn:1000001",
        "tgn:2124053",
        "tgn:7012149",
        "tgn:7029392"
    ],
    "tgn:id":2150306,
    "tgn:name":"Basic Creek",
    "tgn:placetype":[
        "aat:300008706"
    ]
},
  "bbox": [],
  "geometry": {"coordinates":[-151.0333,62.55],"type":"Point"}
}
=======
{"geometry":{"type":"Point","coordinates":[-151.033300,62.550000]},"type":"Feature","properties":{"hierarchy":["tgn:2150306","tgn:7006450","tgn:1000001","tgn:2124053","tgn:7012149","tgn:7029392"],"placetype":["aat:300008706"],"id":2150306,"name:xx":"Basic Creek"}}
>>>>>>> 03f74aca74312dbeaf24d7e61306dd6a786dc3d0
