{
  "id": 2466134,
  "type": "Feature",
  "properties": {
    "tgn:hierarchy":[
        "tgn:2466134",
        "tgn:1000001",
        "tgn:7012149",
        "tgn:1002871",
        "tgn:7007568",
        "tgn:7029392"
    ],
    "tgn:id":2466134,
    "tgn:name":"Lonely, Lake",
    "tgn:placetype":[
        "aat:300008680"
    ]
},
  "bbox": [],
  "geometry": {"coordinates":[-73.7333,43.05],"type":"Point"}
}