{
  "id": 2566962,
  "type": "Feature",
  "properties": {
    "tgn:hierarchy":[
        "tgn:2566962",
        "tgn:1000001",
        "tgn:7012149",
        "tgn:1002786",
        "tgn:7007251",
        "tgn:7029392"
    ],
    "tgn:id":2566962,
    "tgn:name":"Panther Creek",
    "tgn:placetype":[
        "aat:300008706"
    ]
},
  "bbox": [],
  "geometry": {"coordinates":[-90.8667,39.65],"type":"Point"}
}