{
  "id": 7548058,
  "type": "Feature",
  "properties": {
    "tgn:hierarchy":[
        "tgn:7548058",
        "tgn:1000004",
        "tgn:7000198",
        "tgn:7031783",
        "tgn:7029392"
    ],
    "tgn:id":7548058,
    "tgn:name:en":"Bhandra",
    "tgn:placetype":[
        "aat:300008347"
    ]
},
  "bbox": [],
  "geometry": {"coordinates":[84.79952,23.362084],"type":"Point"}
}