{
  "id": 2480837,
  "type": "Feature",
  "properties": {
    "tgn:hierarchy":[
        "tgn:2480837",
        "tgn:1000001",
        "tgn:1002305",
        "tgn:7012149",
        "tgn:7007920",
        "tgn:7029392"
    ],
    "tgn:id":2480837,
    "tgn:name":"Lakeview Peak Lake",
    "tgn:placetype":[
        "aat:300008680"
    ]
},
  "bbox": [],
  "geometry": {"coordinates":[-122.3833,46.05],"type":"Point"}
}