{
  "id": 2653386,
  "type": "Feature",
  "properties": {
    "tgn:hierarchy":[
        "tgn:2653386",
        "tgn:1000001",
        "tgn:7012149",
        "tgn:2001967",
        "tgn:7007826",
        "tgn:7029392"
    ],
    "tgn:id":2653386,
    "tgn:name":"Sevenmile Draw",
    "tgn:placetype":[
        "aat:300008761"
    ]
},
  "bbox": [],
  "geometry": {"coordinates":[-101.35,30.45],"type":"Point"}
}