{
  "id": 7041750,
  "type": "Feature",
  "properties": {
    "tgn:hierarchy":[
        "tgn:7041750",
        "tgn:1003468",
        "tgn:1000003",
        "tgn:7010380",
        "tgn:1000080",
        "tgn:7029392"
    ],
    "tgn:id":7041750,
    "tgn:name":"Torre San Gennaro",
    "tgn:placetype":[
        "aat:300004847"
    ]
},
  "bbox": [],
  "geometry": {"coordinates":[18.075833,40.538333],"type":"Point"}
}