<<<<<<< HEAD
{
  "id": 7178815,
  "type": "Feature",
  "properties": {
    "tgn:hierarchy":[
        "tgn:7178815",
        "tgn:7003669",
        "tgn:1000003",
        "tgn:7000084",
        "tgn:7029392"
    ],
    "tgn:id":7178815,
    "tgn:name":"Guglh\u00f6r",
    "tgn:placetype":[
        "aat:300000206"
    ]
},
  "bbox": [],
  "geometry": {"coordinates":[11.266667,47.683333],"type":"Point"}
}
=======
{"geometry":{"type":"Point","coordinates":[11.266667,47.683333]},"type":"Feature","properties":{"hierarchy":["tgn:7178815","tgn:7003669","tgn:1000003","tgn:7000084","tgn:7029392"],"placetype":["aat:300000206"],"id":7178815,"name:xx":"Guglh\u00f6r"}}
>>>>>>> 03f74aca74312dbeaf24d7e61306dd6a786dc3d0
