<<<<<<< HEAD
{
  "id": 2406667,
  "type": "Feature",
  "properties": {
    "tgn:hierarchy":[
        "tgn:2406667",
        "tgn:1000001",
        "tgn:7012149",
        "tgn:1003042",
        "tgn:7007920",
        "tgn:7029392"
    ],
    "tgn:id":2406667,
    "tgn:name":"Hunt Creek",
    "tgn:placetype":[
        "aat:300008706"
    ]
},
  "bbox": [],
  "geometry": {"coordinates":[-120.9833,46.3333],"type":"Point"}
}
=======
{"geometry":{"type":"Point","coordinates":[-120.983300,46.333300]},"type":"Feature","properties":{"hierarchy":["tgn:2406667","tgn:1000001","tgn:7012149","tgn:1003042","tgn:7007920","tgn:7029392"],"placetype":["aat:300008706"],"id":2406667,"name:xx":"Hunt Creek"}}
>>>>>>> 03f74aca74312dbeaf24d7e61306dd6a786dc3d0
