{
  "id": 2416565,
  "type": "Feature",
  "properties": {
    "tgn:hierarchy":[
        "tgn:2416565",
        "tgn:1000001",
        "tgn:2001411",
        "tgn:7012149",
        "tgn:7007526",
        "tgn:7029392"
    ],
    "tgn:id":2416565,
    "tgn:name":"Jack Creek Tank",
    "tgn:placetype":[
        "aat:300006191"
    ]
},
  "bbox": [],
  "geometry": {"coordinates":[-115.35,41.8667],"type":"Point"}
}