{
  "id": 7429391,
  "type": "Feature",
  "properties": {
    "tgn:hierarchy":[
        "tgn:7429391",
        "tgn:1001853",
        "tgn:1000001",
        "tgn:7005560",
        "tgn:7029392"
    ],
    "tgn:id":7429391,
    "tgn:name":"Estaci\u00f3n Bilbao",
    "tgn:placetype":[
        "aat:300007783"
    ]
},
  "bbox": [],
  "geometry": {"coordinates":[-102.733333,25.383333],"type":"Point"}
}