{
  "id": 7395554,
  "type": "Feature",
  "properties": {
    "tgn:hierarchy":[
        "tgn:7395554",
        "tgn:1000001",
        "tgn:7005595",
        "tgn:7005560",
        "tgn:7029392"
    ],
    "tgn:id":7395554,
    "tgn:name":"San Jos\u00e9 Nuevo",
    "tgn:placetype":[
        "aat:300008347"
    ]
},
  "bbox": [],
  "geometry": {"coordinates":[-108.366667,25.966667],"type":"Point"}
}