{
  "id": 1136232,
  "type": "Feature",
  "properties": {
    "tgn:hierarchy":[
        "tgn:1136232",
        "tgn:1000004",
        "tgn:7000894",
        "tgn:1000120",
        "tgn:7029392"
    ],
    "tgn:id":1136232,
    "tgn:name":"Nobidome-y\u014dsui",
    "tgn:placetype":[
        "aat:300006165"
    ]
},
  "bbox": [],
  "geometry": {"coordinates":[139.45,35.7333],"type":"Point"}
}