{
  "id": 7493342,
  "type": "Feature",
  "properties": {
    "tgn:hierarchy":[
        "tgn:7493342",
        "tgn:7001004",
        "tgn:1000004",
        "tgn:1000141",
        "tgn:7029392"
    ],
    "tgn:id":7493342,
    "tgn:name":"Dongshikeng Xi",
    "tgn:placetype":[
        "aat:300008699"
    ]
},
  "bbox": [],
  "geometry": {"coordinates":[120.594858,22.932687],"type":"Point"}
}