<<<<<<< HEAD
{
  "id": 2259330,
  "type": "Feature",
  "properties": {
    "tgn:hierarchy":[
        "tgn:2259330",
        "tgn:1000001",
        "tgn:7012149",
        "tgn:2000230",
        "tgn:7007158",
        "tgn:7029392"
    ],
    "tgn:id":2259330,
    "tgn:name":"Cottonwood Reservoir Number 5",
    "tgn:placetype":[
        "aat:300006191"
    ]
},
  "bbox": [],
  "geometry": {"coordinates":[-107.95,39.0833],"type":"Point"}
}
=======
{"geometry":{"type":"Point","coordinates":[-107.950000,39.083300]},"type":"Feature","properties":{"hierarchy":["tgn:2259330","tgn:1000001","tgn:7012149","tgn:2000230","tgn:7007158","tgn:7029392"],"placetype":["aat:300006191"],"id":2259330,"name:xx":"Cottonwood Reservoir Number 5"}}
>>>>>>> 03f74aca74312dbeaf24d7e61306dd6a786dc3d0
