{
  "id": 2417433,
  "type": "Feature",
  "properties": {
    "tgn:hierarchy":[
        "tgn:2417433",
        "tgn:7006450",
        "tgn:2000069",
        "tgn:1000001",
        "tgn:7012149",
        "tgn:7029392"
    ],
    "tgn:id":2417433,
    "tgn:name":"Jacksmith Bay",
    "tgn:placetype":[
        "aat:300132316"
    ]
},
  "bbox": [],
  "geometry": {"coordinates":[-161.7333,59.4833],"type":"Point"}
}