<<<<<<< HEAD
{
  "id": 2157548,
  "type": "Feature",
  "properties": {
    "tgn:hierarchy":[
        "tgn:2157548",
        "tgn:1000001",
        "tgn:7012149",
        "tgn:2002376",
        "tgn:7007923",
        "tgn:7029392"
    ],
    "tgn:id":2157548,
    "tgn:name":"Beaver Creek",
    "tgn:placetype":[
        "aat:300008706"
    ]
},
  "bbox": [],
  "geometry": {"coordinates":[-110.6,42.1333],"type":"Point"}
}
=======
{"geometry":{"type":"Point","coordinates":[-110.600000,42.133300]},"type":"Feature","properties":{"hierarchy":["tgn:2157548","tgn:1000001","tgn:7012149","tgn:2002376","tgn:7007923","tgn:7029392"],"placetype":["aat:300008706"],"id":2157548,"name:xx":"Beaver Creek"}}
>>>>>>> 03f74aca74312dbeaf24d7e61306dd6a786dc3d0
