<<<<<<< HEAD
{
  "id": 2250588,
  "type": "Feature",
  "properties": {
    "tgn:hierarchy":[
        "tgn:2250588",
        "tgn:1000001",
        "tgn:7012149",
        "tgn:2002381",
        "tgn:7007923",
        "tgn:7029392"
    ],
    "tgn:id":2250588,
    "tgn:name":"Colorado Colony Ditch",
    "tgn:placetype":[
        "aat:300006075"
    ]
},
  "bbox": [],
  "geometry": {"coordinates":[-107.0,44.7333],"type":"Point"}
}
=======
{"geometry":{"type":"Point","coordinates":[-107.000000,44.733300]},"type":"Feature","properties":{"hierarchy":["tgn:2250588","tgn:1000001","tgn:7012149","tgn:2002381","tgn:7007923","tgn:7029392"],"placetype":["aat:300006075"],"id":2250588,"name:xx":"Colorado Colony Ditch"}}
>>>>>>> 03f74aca74312dbeaf24d7e61306dd6a786dc3d0
