{
  "id": 7356331,
  "type": "Feature",
  "properties": {
    "tgn:hierarchy":[
        "tgn:7356331",
        "tgn:7005587",
        "tgn:1000001",
        "tgn:7005560",
        "tgn:7029392"
    ],
    "tgn:id":7356331,
    "tgn:name":"Chilcuautla",
    "tgn:placetype":[
        "aat:300008347"
    ]
},
  "bbox": [],
  "geometry": {"coordinates":[-99.233333,20.333333],"type":"Point"}
}