<<<<<<< HEAD
{
  "id": 7356331,
  "type": "Feature",
  "properties": {
    "tgn:hierarchy":[
        "tgn:7356331",
        "tgn:7005587",
        "tgn:1000001",
        "tgn:7005560",
        "tgn:7029392"
    ],
    "tgn:id":7356331,
    "tgn:name":"Chilcuautla",
    "tgn:placetype":[
        "aat:300008347"
    ]
},
  "bbox": [],
  "geometry": {"coordinates":[-99.233333,20.333333],"type":"Point"}
}
=======
{"geometry":{"type":"Point","coordinates":[-99.233333,20.333333]},"type":"Feature","properties":{"hierarchy":["tgn:7356331","tgn:7005587","tgn:1000001","tgn:7005560","tgn:7029392"],"placetype":["aat:300008347"],"id":7356331,"name:xx":"Chilcuautla"}}
>>>>>>> 03f74aca74312dbeaf24d7e61306dd6a786dc3d0
