{
  "id": 7447479,
  "type": "Feature",
  "properties": {
    "tgn:hierarchy":[
        "tgn:7447479",
        "tgn:7002445",
        "tgn:7011781",
        "tgn:7018931",
        "tgn:1000003",
        "tgn:7008136",
        "tgn:7008591",
        "tgn:7029392"
    ],
    "tgn:id":7447479,
    "tgn:name:en":"Stepney",
    "tgn:placetype":[
        "aat:300008347"
    ]
},
  "bbox": [],
  "geometry": {"coordinates":[-0.033333,51.516667],"type":"Point"}
}