{
  "id": 7192965,
  "type": "Feature",
  "properties": {
    "tgn:hierarchy":[
        "tgn:7192965",
        "tgn:1000003",
        "tgn:7003684",
        "tgn:7000084",
        "tgn:7029392"
    ],
    "tgn:id":7192965,
    "tgn:name":"Fenne",
    "tgn:placetype":[
        "aat:300008347"
    ]
},
  "bbox": [],
  "geometry": {"coordinates":[6.883333,49.25],"type":"Point"}
}