{
  "id": 2416341,
  "type": "Feature",
  "properties": {
    "tgn:hierarchy":[
        "tgn:2416341",
        "tgn:1000001",
        "tgn:7012149",
        "tgn:1002986",
        "tgn:7007568",
        "tgn:7029392"
    ],
    "tgn:id":2416341,
    "tgn:name":"Jabe Pond Brook",
    "tgn:placetype":[
        "aat:300008699"
    ]
},
  "bbox": [],
  "geometry": {"coordinates":[-73.5333,43.6833],"type":"Point"}
}