{
  "id": 7282152,
  "type": "Feature",
  "properties": {
    "tgn:hierarchy":[
        "tgn:7282152",
        "tgn:1001699",
        "tgn:1000049",
        "tgn:1000002",
        "tgn:7029392"
    ],
    "tgn:id":7282152,
    "tgn:name":"Saturno, Islote",
    "tgn:placetype":[
        "aat:300008791"
    ]
},
  "bbox": [],
  "geometry": {"coordinates":[-74.004722,-43.778889],"type":"Point"}
}