{
  "id": 1025552,
  "type": "Feature",
  "properties": {
    "tgn:hierarchy":[
        "tgn:1025552",
        "tgn:7003028",
        "tgn:1000003",
        "tgn:1000062",
        "tgn:7029392"
    ],
    "tgn:id":1025552,
    "tgn:name":"Frohnleiten",
    "tgn:placetype":[
        "aat:300008347"
    ]
},
  "bbox": [],
  "geometry": {"coordinates":[15.3333,47.2833],"type":"Point"}
}