{
  "id": 7231893,
  "type": "Feature",
  "properties": {
    "tgn:hierarchy":[
        "tgn:7231893",
        "tgn:7002680",
        "tgn:7001395",
        "tgn:1000003",
        "tgn:1000074",
        "tgn:7029392"
    ],
    "tgn:id":7231893,
    "tgn:name":"Malata\u00edikon",
    "tgn:placetype":[
        "aat:300008347"
    ]
},
  "bbox": [],
  "geometry": {"coordinates":[21.366667,38.816667],"type":"Point"}
}