{
  "id": 7545057,
  "type": "Feature",
  "properties": {
    "tgn:hierarchy":[
        "tgn:7545057",
        "tgn:1000004",
        "tgn:7000198",
        "tgn:7000799",
        "tgn:7029392"
    ],
    "tgn:id":7545057,
    "tgn:name:en":"\u0100l Pathri",
    "tgn:placetype":[
        "aat:300008688"
    ]
},
  "bbox": [],
  "geometry": {"coordinates":[74.330083,34.021205],"type":"Point"}
}