{
  "id": 1050421,
  "type": "Feature",
  "properties": {
    "tgn:hierarchy":[
        "tgn:1050421",
        "tgn:7002444",
        "tgn:1000003",
        "tgn:7008082",
        "tgn:7008591",
        "tgn:7029392"
    ],
    "tgn:id":1050421,
    "tgn:name":"Balnacra",
    "tgn:placetype":[
        "aat:300008347"
    ]
},
  "bbox": [],
  "geometry": {"coordinates":[-5.3833,57.4667],"type":"Point"}
}