{
  "id": 2577574,
  "type": "Feature",
  "properties": {
    "tgn:hierarchy":[
        "tgn:2577574",
        "tgn:7006450",
        "tgn:1000001",
        "tgn:2124089",
        "tgn:7012149",
        "tgn:7029392"
    ],
    "tgn:id":2577574,
    "tgn:name":"Peterson Lake",
    "tgn:placetype":[
        "aat:300008680"
    ]
},
  "bbox": [],
  "geometry": {"coordinates":[-134.7167,58.4333],"type":"Point"}
}