{
  "id": 7575645,
  "type": "Feature",
  "properties": {
    "tgn:hierarchy":[
        "tgn:7575645",
        "tgn:1000004",
        "tgn:7000198",
        "tgn:1001895",
        "tgn:7029392"
    ],
    "tgn:id":7575645,
    "tgn:name:en":"Lakda",
    "tgn:placetype":[
        "aat:300008347"
    ]
},
  "bbox": [],
  "geometry": {"coordinates":[75.416667,17.183333],"type":"Point"}
}