{
  "id": 2054156,
  "type": "Feature",
  "properties": {
    "tgn:hierarchy":[
        "tgn:2054156",
        "tgn:1000001",
        "tgn:7012149",
        "tgn:2001056",
        "tgn:7007521",
        "tgn:7029392"
    ],
    "tgn:id":2054156,
    "tgn:name":"Cloverton",
    "tgn:placetype":[
        "aat:300008347"
    ]
},
  "bbox": [],
  "geometry": {"coordinates":[-92.3167,46.1667],"type":"Point"}
}