<<<<<<< HEAD
{
  "id": 7117529,
  "type": "Feature",
  "properties": {
    "tgn:hierarchy":[
        "tgn:7117529",
        "tgn:1000003",
        "tgn:7003677",
        "tgn:7000084",
        "tgn:7029392"
    ],
    "tgn:id":7117529,
    "tgn:name":"Ostholt",
    "tgn:placetype":[
        "aat:300000206"
    ]
},
  "bbox": [],
  "geometry": {"coordinates":[8.15,52.016667],"type":"Point"}
}
=======
{"geometry":{"type":"Point","coordinates":[8.150000,52.016667]},"type":"Feature","properties":{"hierarchy":["tgn:7117529","tgn:1000003","tgn:7003677","tgn:7000084","tgn:7029392"],"placetype":["aat:300000206"],"id":7117529,"name:xx":"Ostholt"}}
>>>>>>> 03f74aca74312dbeaf24d7e61306dd6a786dc3d0
