{
  "id": 2238828,
  "type": "Feature",
  "properties": {
    "tgn:hierarchy":[
        "tgn:2238828",
        "tgn:1000001",
        "tgn:7012149",
        "tgn:2001287",
        "tgn:7007524",
        "tgn:7029392"
    ],
    "tgn:id":2238828,
    "tgn:name":"Christianson Reservoir",
    "tgn:placetype":[
        "aat:300006191"
    ]
},
  "bbox": [],
  "geometry": {"coordinates":[-105.9833,47.7667],"type":"Point"}
}