{
  "id": 2571194,
  "type": "Feature",
  "properties": {
    "tgn:hierarchy":[
        "tgn:2571194",
        "tgn:1000001",
        "tgn:2000868",
        "tgn:7012149",
        "tgn:7007256",
        "tgn:7029392"
    ],
    "tgn:id":2571194,
    "tgn:name":"Patton Lake",
    "tgn:placetype":[
        "aat:300008680"
    ]
},
  "bbox": [],
  "geometry": {"coordinates":[-91.7667,31.2667],"type":"Point"}
}