{
  "id": 7392555,
  "type": "Feature",
  "properties": {
    "tgn:hierarchy":[
        "tgn:7392555",
        "tgn:1000001",
        "tgn:1001906",
        "tgn:7005560",
        "tgn:7029392"
    ],
    "tgn:id":7392555,
    "tgn:name":"Redenci\u00f3n",
    "tgn:placetype":[
        "aat:300008347"
    ]
},
  "bbox": [],
  "geometry": {"coordinates":[-105.033333,21.85],"type":"Point"}
}