{
  "id": 7415207,
  "type": "Feature",
  "properties": {
    "tgn:hierarchy":[
        "tgn:7415207",
        "tgn:7005584",
        "tgn:1000001",
        "tgn:7005560",
        "tgn:7029392"
    ],
    "tgn:id":7415207,
    "tgn:name":"La Minita",
    "tgn:placetype":[
        "aat:300008347"
    ]
},
  "bbox": [],
  "geometry": {"coordinates":[-101.157778,20.151111],"type":"Point"}
}