{
  "id": 1063550,
  "type": "Feature",
  "properties": {
    "tgn:hierarchy":[
        "tgn:1063550",
        "tgn:1000003",
        "tgn:1000466",
        "tgn:1000097",
        "tgn:7029392"
    ],
    "tgn:id":1063550,
    "tgn:name":"S\u00f6r\u00e5ker",
    "tgn:placetype":[
        "aat:300008347"
    ]
},
  "bbox": [],
  "geometry": {"coordinates":[17.5333,62.5333],"type":"Point"}
}