{
  "id": 7149043,
  "type": "Feature",
  "properties": {
    "tgn:hierarchy":[
        "tgn:7149043",
        "tgn:7003669",
        "tgn:1000003",
        "tgn:7000084",
        "tgn:7029392"
    ],
    "tgn:id":7149043,
    "tgn:name":"Kumpfm\u00fchl",
    "tgn:placetype":[
        "aat:300000206"
    ]
},
  "bbox": [],
  "geometry": {"coordinates":[12.45,48.35],"type":"Point"}
}