<<<<<<< HEAD
{
  "id": 2259508,
  "type": "Feature",
  "properties": {
    "tgn:hierarchy":[
        "tgn:2259508",
        "tgn:1000001",
        "tgn:7012149",
        "tgn:2001455",
        "tgn:7007566",
        "tgn:7029392"
    ],
    "tgn:id":2259508,
    "tgn:name":"Cottonwood Tank",
    "tgn:placetype":[
        "aat:300006191"
    ]
},
  "bbox": [],
  "geometry": {"coordinates":[-107.65,33.1167],"type":"Point"}
}
=======
{"geometry":{"type":"Point","coordinates":[-107.650000,33.116700]},"type":"Feature","properties":{"hierarchy":["tgn:2259508","tgn:1000001","tgn:7012149","tgn:2001455","tgn:7007566","tgn:7029392"],"placetype":["aat:300006191"],"id":2259508,"name:xx":"Cottonwood Tank"}}
>>>>>>> 03f74aca74312dbeaf24d7e61306dd6a786dc3d0
