{
  "id": 7544280,
  "type": "Feature",
  "properties": {
    "tgn:hierarchy":[
        "tgn:7544280",
        "tgn:7001242",
        "tgn:7016833",
        "tgn:1001335",
        "tgn:7029392"
    ],
    "tgn:id":7544280,
    "tgn:name":"Tur'at ash Shar\u0101qwah",
    "tgn:placetype":[
        "aat:300006075"
    ]
},
  "bbox": [],
  "geometry": {"coordinates":[31.219719,31.365042],"type":"Point"}
}