<<<<<<< HEAD
{
  "id": 2335865,
  "type": "Feature",
  "properties": {
    "tgn:hierarchy":[
        "tgn:2335865",
        "tgn:1000001",
        "tgn:7012149",
        "tgn:2001312",
        "tgn:7007524",
        "tgn:7029392"
    ],
    "tgn:id":2335865,
    "tgn:name":"Foss Coulee",
    "tgn:placetype":[
        "aat:300008761"
    ]
},
  "bbox": [],
  "geometry": {"coordinates":[-106.55,48.4],"type":"Point"}
}
=======
{"geometry":{"type":"Point","coordinates":[-106.550000,48.400000]},"type":"Feature","properties":{"hierarchy":["tgn:2335865","tgn:1000001","tgn:7012149","tgn:2001312","tgn:7007524","tgn:7029392"],"placetype":["aat:300008761"],"id":2335865,"name:xx":"Foss Coulee"}}
>>>>>>> 03f74aca74312dbeaf24d7e61306dd6a786dc3d0
