<<<<<<< HEAD
{
  "id": 2158829,
  "type": "Feature",
  "properties": {
    "tgn:hierarchy":[
        "tgn:2158829",
        "tgn:1000001",
        "tgn:1002305",
        "tgn:7012149",
        "tgn:7007920",
        "tgn:7029392"
    ],
    "tgn:id":2158829,
    "tgn:name":"Becker Creek",
    "tgn:placetype":[
        "aat:300008706"
    ]
},
  "bbox": [],
  "geometry": {"coordinates":[-123.0833,46.35],"type":"Point"}
}
=======
{"geometry":{"type":"Point","coordinates":[-123.083300,46.350000]},"type":"Feature","properties":{"hierarchy":["tgn:2158829","tgn:1000001","tgn:1002305","tgn:7012149","tgn:7007920","tgn:7029392"],"placetype":["aat:300008706"],"id":2158829,"name:xx":"Becker Creek"}}
>>>>>>> 03f74aca74312dbeaf24d7e61306dd6a786dc3d0
