{
  "id": 7228726,
  "type": "Feature",
  "properties": {
    "tgn:hierarchy":[
        "tgn:7228726",
        "tgn:7002680",
        "tgn:7001395",
        "tgn:1000003",
        "tgn:1000074",
        "tgn:7029392"
    ],
    "tgn:id":7228726,
    "tgn:name":"Kl\u00edsovis, Limnoth\u00e1lassa",
    "tgn:placetype":[
        "aat:300008679"
    ]
},
  "bbox": [],
  "geometry": {"coordinates":[21.466667,38.35],"type":"Point"}
}