{
  "id": 7560005,
  "type": "Feature",
  "properties": {
    "tgn:hierarchy":[
        "tgn:7560005",
        "tgn:1000004",
        "tgn:7000198",
        "tgn:7016722",
        "tgn:7029392"
    ],
    "tgn:id":7560005,
    "tgn:name:en":"Dhobia Khurd",
    "tgn:placetype":[
        "aat:300008347"
    ]
},
  "bbox": [],
  "geometry": {"coordinates":[79.259863,27.203411],"type":"Point"}
}