<<<<<<< HEAD
{
  "id": 2254207,
  "type": "Feature",
  "properties": {
    "tgn:hierarchy":[
        "tgn:2254207",
        "tgn:1000001",
        "tgn:7012149",
        "tgn:2000839",
        "tgn:7007255",
        "tgn:7029392"
    ],
    "tgn:id":2254207,
    "tgn:name":"Coomer Hollow",
    "tgn:placetype":[
        "aat:300008761"
    ]
},
  "bbox": [],
  "geometry": {"coordinates":[-84.65,36.95],"type":"Point"}
}
=======
{"geometry":{"type":"Point","coordinates":[-84.650000,36.950000]},"type":"Feature","properties":{"hierarchy":["tgn:2254207","tgn:1000001","tgn:7012149","tgn:2000839","tgn:7007255","tgn:7029392"],"placetype":["aat:300008761"],"id":2254207,"name:xx":"Coomer Hollow"}}
>>>>>>> 03f74aca74312dbeaf24d7e61306dd6a786dc3d0
