{
  "id": 7334379,
  "type": "Feature",
  "properties": {
    "tgn:hierarchy":[
        "tgn:7334379",
        "tgn:7002803",
        "tgn:1001647",
        "tgn:1000003",
        "tgn:1000095",
        "tgn:7029392"
    ],
    "tgn:id":7334379,
    "tgn:name":"El Horcajo",
    "tgn:placetype":[
        "aat:300008347"
    ]
},
  "bbox": [],
  "geometry": {"coordinates":[-2.466667,38.716667],"type":"Point"}
}