{
  "id": 2174704,
  "type": "Feature",
  "properties": {
    "tgn:hierarchy":[
        "tgn:2174704",
        "tgn:1000001",
        "tgn:7012149",
        "tgn:7029392"
    ],
    "tgn:id":2174704,
    "tgn:name":"Bitter Creek",
    "tgn:placetype":[
        "aat:300008706"
    ]
},
  "bbox": [],
  "geometry": {"coordinates":[-108.95,32.8833],"type":"Point"}
}