<<<<<<< HEAD
{
  "id": 2338196,
  "type": "Feature",
  "properties": {
    "tgn:hierarchy":[
        "tgn:2338196",
        "tgn:1000001",
        "tgn:7012149",
        "tgn:1002368",
        "tgn:7007919",
        "tgn:7029392"
    ],
    "tgn:id":2338196,
    "tgn:name":"Fox Pond",
    "tgn:placetype":[
        "aat:300006191"
    ]
},
  "bbox": [],
  "geometry": {"coordinates":[-77.7833,38.7667],"type":"Point"}
}
=======
{"geometry":{"type":"Point","coordinates":[-77.783300,38.766700]},"type":"Feature","properties":{"hierarchy":["tgn:2338196","tgn:1000001","tgn:7012149","tgn:1002368","tgn:7007919","tgn:7029392"],"placetype":["aat:300006191"],"id":2338196,"name:xx":"Fox Pond"}}
>>>>>>> 03f74aca74312dbeaf24d7e61306dd6a786dc3d0
