{
  "id": 2338196,
  "type": "Feature",
  "properties": {
    "tgn:hierarchy":[
        "tgn:2338196",
        "tgn:1000001",
        "tgn:7012149",
        "tgn:1002368",
        "tgn:7007919",
        "tgn:7029392"
    ],
    "tgn:id":2338196,
    "tgn:name":"Fox Pond",
    "tgn:placetype":[
        "aat:300006191"
    ]
},
  "bbox": [],
  "geometry": {"coordinates":[-77.7833,38.7667],"type":"Point"}
}