<<<<<<< HEAD
{
  "id": 7118144,
  "type": "Feature",
  "properties": {
    "tgn:hierarchy":[
        "tgn:7118144",
        "tgn:7003669",
        "tgn:1000003",
        "tgn:7000084",
        "tgn:7029392"
    ],
    "tgn:id":7118144,
    "tgn:name":"Oberschroffen",
    "tgn:placetype":[
        "aat:300000206"
    ]
},
  "bbox": [],
  "geometry": {"coordinates":[12.65,48.15],"type":"Point"}
}
=======
{"geometry":{"type":"Point","coordinates":[12.650000,48.150000]},"type":"Feature","properties":{"hierarchy":["tgn:7118144","tgn:7003669","tgn:1000003","tgn:7000084","tgn:7029392"],"placetype":["aat:300000206"],"id":7118144,"name:xx":"Oberschroffen"}}
>>>>>>> 03f74aca74312dbeaf24d7e61306dd6a786dc3d0
