{
  "id": 7118144,
  "type": "Feature",
  "properties": {
    "tgn:hierarchy":[
        "tgn:7118144",
        "tgn:7003669",
        "tgn:1000003",
        "tgn:7000084",
        "tgn:7029392"
    ],
    "tgn:id":7118144,
    "tgn:name":"Oberschroffen",
    "tgn:placetype":[
        "aat:300000206"
    ]
},
  "bbox": [],
  "geometry": {"coordinates":[12.65,48.15],"type":"Point"}
}