{
  "id": 2022607,
  "type": "Feature",
  "properties": {
    "tgn:hierarchy":[
        "tgn:2022607",
        "tgn:1000001",
        "tgn:7012149",
        "tgn:2000355",
        "tgn:7007248",
        "tgn:7029392"
    ],
    "tgn:id":2022607,
    "tgn:name":"Curryville",
    "tgn:placetype":[
        "aat:300008347",
        "aat:300387210"
    ]
},
  "bbox": [],
  "geometry": {"coordinates":[-85.0667,34.4333],"type":"Point"}
}