{
  "id": 7549210,
  "type": "Feature",
  "properties": {
    "tgn:hierarchy":[
        "tgn:7549210",
        "tgn:1000004",
        "tgn:7000198",
        "tgn:1001894",
        "tgn:7029392"
    ],
    "tgn:id":7549210,
    "tgn:name:en":"Eklaira",
    "tgn:placetype":[
        "aat:300008347"
    ]
},
  "bbox": [],
  "geometry": {"coordinates":[78.689232,22.203578],"type":"Point"}
}