<<<<<<< HEAD
{
  "id": 7171667,
  "type": "Feature",
  "properties": {
    "tgn:hierarchy":[
        "tgn:7171667",
        "tgn:1000003",
        "tgn:7003688",
        "tgn:7000084",
        "tgn:7029392"
    ],
    "tgn:id":7171667,
    "tgn:name":"Hemmelsdorf",
    "tgn:placetype":[
        "aat:300008347"
    ]
},
  "bbox": [],
  "geometry": {"coordinates":[10.766667,53.966667],"type":"Point"}
}
=======
{"geometry":{"type":"Point","coordinates":[10.766667,53.966667]},"type":"Feature","properties":{"hierarchy":["tgn:7171667","tgn:1000003","tgn:7003688","tgn:7000084","tgn:7029392"],"placetype":["aat:300008347"],"id":7171667,"name:xx":"Hemmelsdorf"}}
>>>>>>> 03f74aca74312dbeaf24d7e61306dd6a786dc3d0
