{
  "id": 7545808,
  "type": "Feature",
  "properties": {
    "tgn:hierarchy":[
        "tgn:7545808",
        "tgn:1000004",
        "tgn:1001869",
        "tgn:7000198",
        "tgn:7029392"
    ],
    "tgn:id":7545808,
    "tgn:name:en":"Bhog\u0101va River",
    "tgn:placetype":[
        "aat:300008699"
    ]
},
  "bbox": [],
  "geometry": {"coordinates":[72.333333,22.433333],"type":"Point"}
}