{
  "id": 2747250,
  "type": "Feature",
  "properties": {
    "tgn:hierarchy":[
        "tgn:2747250",
        "tgn:1000001",
        "tgn:7012149",
        "tgn:7007157",
        "tgn:2000184",
        "tgn:7029392"
    ],
    "tgn:id":2747250,
    "tgn:name":"Wagontire Reservoir",
    "tgn:placetype":[
        "aat:300006191"
    ]
},
  "bbox": [],
  "geometry": {"coordinates":[-121.0667,40.95],"type":"Point"}
}