{
  "id": 7568451,
  "type": "Feature",
  "properties": {
    "tgn:hierarchy":[
        "tgn:7568451",
        "tgn:1000004",
        "tgn:7000198",
        "tgn:7016788",
        "tgn:7029392"
    ],
    "tgn:id":7568451,
    "tgn:name:en":"Kh\u0101ria",
    "tgn:placetype":[
        "aat:300008347"
    ]
},
  "bbox": [],
  "geometry": {"coordinates":[73.91127,28.971059],"type":"Point"}
}