{
  "id": 7345175,
  "type": "Feature",
  "properties": {
    "tgn:hierarchy":[
        "tgn:7345175",
        "tgn:7002804",
        "tgn:1000003",
        "tgn:7002793",
        "tgn:1000095",
        "tgn:7029392"
    ],
    "tgn:id":7345175,
    "tgn:name":"Alcoyes",
    "tgn:placetype":[
        "aat:300008347"
    ]
},
  "bbox": [],
  "geometry": {"coordinates":[-0.383333,38.633333],"type":"Point"}
}