{
  "id": 2713736,
  "type": "Feature",
  "properties": {
    "tgn:hierarchy":[
        "tgn:2713736",
        "tgn:1000001",
        "tgn:7012149",
        "tgn:7007157",
        "tgn:1002858",
        "tgn:7029392"
    ],
    "tgn:id":2713736,
    "tgn:name":"Tecate Divide",
    "tgn:placetype":[
        "aat:300266640"
    ]
},
  "bbox": [],
  "geometry": {"coordinates":[-116.3167,32.6833],"type":"Point"}
}