{
  "id": 2369174,
  "type": "Feature",
  "properties": {
    "tgn:hierarchy":[
        "tgn:2369174",
        "tgn:1000001",
        "tgn:7016172",
        "tgn:7012149",
        "tgn:2000174",
        "tgn:7029392"
    ],
    "tgn:id":2369174,
    "tgn:name":"Gum Ridge",
    "tgn:placetype":[
        "aat:300266640"
    ]
},
  "bbox": [],
  "geometry": {"coordinates":[-92.1333,33.0667],"type":"Point"}
}