{
  "id": 2531055,
  "type": "Feature",
  "properties": {
    "tgn:hierarchy":[
        "tgn:2531055",
        "tgn:1000001",
        "tgn:7012149",
        "tgn:2001706",
        "tgn:7007708",
        "tgn:7029392"
    ],
    "tgn:id":2531055,
    "tgn:name":"Muir Creek",
    "tgn:placetype":[
        "aat:300008706"
    ]
},
  "bbox": [],
  "geometry": {"coordinates":[-122.3333,43.0833],"type":"Point"}
}