{
  "id": 7361970,
  "type": "Feature",
  "properties": {
    "tgn:hierarchy":[
        "tgn:7361970",
        "tgn:1000001",
        "tgn:7005601",
        "tgn:7005560",
        "tgn:7029392"
    ],
    "tgn:id":7361970,
    "tgn:name":"El Capul\u00edn",
    "tgn:placetype":[
        "aat:300008347"
    ]
},
  "bbox": [],
  "geometry": {"coordinates":[-103.183333,22.75],"type":"Point"}
}