{
  "id": 2586321,
  "type": "Feature",
  "properties": {
    "tgn:hierarchy":[
        "tgn:2586321",
        "tgn:1000001",
        "tgn:7012149",
        "tgn:2001275",
        "tgn:7007524",
        "tgn:7029392"
    ],
    "tgn:id":2586321,
    "tgn:name":"Pitcher Creek",
    "tgn:placetype":[
        "aat:300008706"
    ]
},
  "bbox": [],
  "geometry": {"coordinates":[-110.8833,45.6667],"type":"Point"}
}