{
  "id": 7579583,
  "type": "Feature",
  "properties": {
    "tgn:hierarchy":[
        "tgn:7579583",
        "tgn:1000004",
        "tgn:7000198",
        "tgn:1003539",
        "tgn:7029392"
    ],
    "tgn:id":7579583,
    "tgn:name:en":"Shangpung",
    "tgn:placetype":[
        "aat:300008347"
    ]
},
  "bbox": [],
  "geometry": {"coordinates":[92.351321,25.476795],"type":"Point"}
}