{
  "id": 7305203,
  "type": "Feature",
  "properties": {
    "tgn:hierarchy":[
        "tgn:7305203",
        "tgn:7002832",
        "tgn:7001158",
        "tgn:1000003",
        "tgn:1000095",
        "tgn:7029392"
    ],
    "tgn:id":7305203,
    "tgn:name":"La Serna",
    "tgn:placetype":[
        "aat:300008347"
    ]
},
  "bbox": [],
  "geometry": {"coordinates":[-4.666667,42.416667],"type":"Point"}
}