{
  "id": 2484032,
  "type": "Feature",
  "properties": {
    "tgn:hierarchy":[
        "tgn:2484032",
        "tgn:1000001",
        "tgn:2000457",
        "tgn:7012149",
        "tgn:7007250",
        "tgn:7029392"
    ],
    "tgn:id":2484032,
    "tgn:name":"Lau Lakes",
    "tgn:placetype":[
        "aat:300008680"
    ]
},
  "bbox": [],
  "geometry": {"coordinates":[-112.95,43.1833],"type":"Point"}
}