{
  "id": 2290343,
  "type": "Feature",
  "properties": {
    "tgn:hierarchy":[
        "tgn:2290343",
        "tgn:1000001",
        "tgn:7012149",
        "tgn:2001130",
        "tgn:7007522",
        "tgn:7029392"
    ],
    "tgn:id":2290343,
    "tgn:name":"Dodson Branch",
    "tgn:placetype":[
        "aat:300008699"
    ]
},
  "bbox": [],
  "geometry": {"coordinates":[-90.3333,32.5667],"type":"Point"}
}