{
  "id": 2711404,
  "type": "Feature",
  "properties": {
    "tgn:hierarchy":[
        "tgn:2711404",
        "tgn:1000001",
        "tgn:7012149",
        "tgn:1002429",
        "tgn:7007826",
        "tgn:7029392"
    ],
    "tgn:id":2711404,
    "tgn:name":"Tanyard Branch",
    "tgn:placetype":[
        "aat:300008699"
    ]
},
  "bbox": [],
  "geometry": {"coordinates":[-96.0333,30.55],"type":"Point"}
}