{
  "id": 2652986,
  "type": "Feature",
  "properties": {
    "tgn:hierarchy":[
        "tgn:2652986",
        "tgn:1000001",
        "tgn:1002270",
        "tgn:7012149",
        "tgn:7007708",
        "tgn:7029392"
    ],
    "tgn:id":2652986,
    "tgn:name":"Sevcik Pond",
    "tgn:placetype":[
        "aat:300006191"
    ]
},
  "bbox": [],
  "geometry": {"coordinates":[-122.65,45.2833],"type":"Point"}
}