{
  "id": 2430269,
  "type": "Feature",
  "properties": {
    "tgn:hierarchy":[
        "tgn:2430269",
        "tgn:1000001",
        "tgn:7006451",
        "tgn:2000092",
        "tgn:7012149",
        "tgn:7029392"
    ],
    "tgn:id":2430269,
    "tgn:name":"Kaibab Lake",
    "tgn:placetype":[
        "aat:300006191"
    ]
},
  "bbox": [],
  "geometry": {"coordinates":[-112.15,35.2833],"type":"Point"}
}