<<<<<<< HEAD
{
  "id": 7351719,
  "type": "Feature",
  "properties": {
    "tgn:hierarchy":[
        "tgn:7351719",
        "tgn:7005583",
        "tgn:1000001",
        "tgn:7005560",
        "tgn:7029392"
    ],
    "tgn:id":7351719,
    "tgn:name":"Boquilla de Lobo, Cerro",
    "tgn:placetype":[
        "aat:300008795"
    ]
},
  "bbox": [],
  "geometry": {"coordinates":[-104.283333,25.95],"type":"Point"}
}
=======
{"geometry":{"type":"Point","coordinates":[-104.283333,25.950000]},"type":"Feature","properties":{"hierarchy":["tgn:7351719","tgn:7005583","tgn:1000001","tgn:7005560","tgn:7029392"],"placetype":["aat:300008795"],"id":7351719,"name:xx":"Boquilla de Lobo, Cerro"}}
>>>>>>> 03f74aca74312dbeaf24d7e61306dd6a786dc3d0
