{
  "id": 7341550,
  "type": "Feature",
  "properties": {
    "tgn:hierarchy":[
        "tgn:7341550",
        "tgn:7002759",
        "tgn:7002843",
        "tgn:1000003",
        "tgn:1000095",
        "tgn:7029392"
    ],
    "tgn:id":7341550,
    "tgn:name":"Blanquilla, Fuente",
    "tgn:placetype":[
        "aat:300008697"
    ]
},
  "bbox": [],
  "geometry": {"coordinates":[-1.033333,40.116667],"type":"Point"}
}