{
  "id": 2080265,
  "type": "Feature",
  "properties": {
    "tgn:hierarchy":[
        "tgn:2080265",
        "tgn:1000001",
        "tgn:7012149",
        "tgn:1002607",
        "tgn:7007706",
        "tgn:7029392"
    ],
    "tgn:id":2080265,
    "tgn:name":"Lagrange",
    "tgn:placetype":[
        "aat:300008347"
    ]
},
  "bbox": [],
  "geometry": {"coordinates":[-82.1167,41.2333],"type":"Point"}
}