{
  "id": 2115255,
  "type": "Feature",
  "properties": {
    "tgn:hierarchy":[
        "tgn:2115255",
        "tgn:2002239",
        "tgn:1000001",
        "tgn:7012149",
        "tgn:7007920",
        "tgn:7029392"
    ],
    "tgn:id":2115255,
    "tgn:name":"Asotin",
    "tgn:placetype":[
        "aat:300008347",
        "aat:300008416"
    ]
},
  "bbox": [],
  "geometry": {"coordinates":[-117.0333,46.3333],"type":"Point"}
}