{
  "id": 2012223,
  "type": "Feature",
  "properties": {
    "tgn:hierarchy":[
        "tgn:2012223",
        "tgn:1000001",
        "tgn:7012149",
        "tgn:7007157",
        "tgn:1002656",
        "tgn:7029392"
    ],
    "tgn:id":2012223,
    "tgn:name":"Lingard",
    "tgn:placetype":[
        "aat:300008347",
        "aat:300387210"
    ]
},
  "bbox": [],
  "geometry": {"coordinates":[-120.3833,37.2333],"type":"Point"}
}