{
  "id": 7256232,
  "type": "Feature",
  "properties": {
    "tgn:hierarchy":[
        "tgn:7256232",
        "tgn:1000003",
        "tgn:1000063",
        "tgn:7029392"
    ],
    "tgn:id":7256232,
    "tgn:name":"Westpit",
    "tgn:placetype":[
        "aat:300008713"
    ]
},
  "bbox": [],
  "geometry": {"coordinates":[3.083333,51.566667],"type":"Point"}
}