{
  "id": 2608686,
  "type": "Feature",
  "properties": {
    "tgn:hierarchy":[
        "tgn:2608686",
        "tgn:1000001",
        "tgn:7012149",
        "tgn:2001455",
        "tgn:7007566",
        "tgn:7029392"
    ],
    "tgn:id":2608686,
    "tgn:name":"Rattlesnake Placers",
    "tgn:placetype":[
        "aat:300000390"
    ]
},
  "bbox": [],
  "geometry": {"coordinates":[-107.55,32.9333],"type":"Point"}
}