<<<<<<< HEAD
{
  "id": 2769952,
  "type": "Feature",
  "properties": {
    "tgn:hierarchy":[
        "tgn:2769952",
        "tgn:1000001",
        "tgn:7012149",
        "tgn:2001392",
        "tgn:7007525",
        "tgn:7029392"
    ],
    "tgn:id":2769952,
    "tgn:name":"Wilburn Island",
    "tgn:placetype":[
        "aat:300008791"
    ]
},
  "bbox": [],
  "geometry": {"coordinates":[-96.3333,41.0833],"type":"Point"}
}
=======
{"geometry":{"type":"Point","coordinates":[-96.333300,41.083300]},"type":"Feature","properties":{"hierarchy":["tgn:2769952","tgn:1000001","tgn:7012149","tgn:2001392","tgn:7007525","tgn:7029392"],"placetype":["aat:300008791"],"id":2769952,"name:xx":"Wilburn Island"}}
>>>>>>> 03f74aca74312dbeaf24d7e61306dd6a786dc3d0
