<<<<<<< HEAD
{
  "id": 2404706,
  "type": "Feature",
  "properties": {
    "tgn:hierarchy":[
        "tgn:2404706",
        "tgn:1000001",
        "tgn:2000267",
        "tgn:7012149",
        "tgn:7007240",
        "tgn:7029392"
    ],
    "tgn:id":2404706,
    "tgn:name":"Huckleberry Creek",
    "tgn:placetype":[
        "aat:300008706"
    ]
},
  "bbox": [],
  "geometry": {"coordinates":[-85.0667,29.7167],"type":"Point"}
}
=======
{"geometry":{"type":"Point","coordinates":[-85.066700,29.716700]},"type":"Feature","properties":{"hierarchy":["tgn:2404706","tgn:1000001","tgn:2000267","tgn:7012149","tgn:7007240","tgn:7029392"],"placetype":["aat:300008706"],"id":2404706,"name:xx":"Huckleberry Creek"}}
>>>>>>> 03f74aca74312dbeaf24d7e61306dd6a786dc3d0
