{
  "id": 2404706,
  "type": "Feature",
  "properties": {
    "tgn:hierarchy":[
        "tgn:2404706",
        "tgn:1000001",
        "tgn:2000267",
        "tgn:7012149",
        "tgn:7007240",
        "tgn:7029392"
    ],
    "tgn:id":2404706,
    "tgn:name":"Huckleberry Creek",
    "tgn:placetype":[
        "aat:300008706"
    ]
},
  "bbox": [],
  "geometry": {"coordinates":[-85.0667,29.7167],"type":"Point"}
}