<<<<<<< HEAD
{
  "id": 7353258,
  "type": "Feature",
  "properties": {
    "tgn:hierarchy":[
        "tgn:7353258",
        "tgn:1000001",
        "tgn:7005597",
        "tgn:7005560",
        "tgn:7029392"
    ],
    "tgn:id":7353258,
    "tgn:name":"Anacuas Caja Pinta",
    "tgn:placetype":[
        "aat:300008347"
    ]
},
  "bbox": [],
  "geometry": {"coordinates":[-97.5,25.816667],"type":"Point"}
}
=======
{"geometry":{"type":"Point","coordinates":[-97.500000,25.816667]},"type":"Feature","properties":{"hierarchy":["tgn:7353258","tgn:1000001","tgn:7005597","tgn:7005560","tgn:7029392"],"placetype":["aat:300008347"],"id":7353258,"name:xx":"Anacuas Caja Pinta"}}
>>>>>>> 03f74aca74312dbeaf24d7e61306dd6a786dc3d0
