{
  "id": 7416558,
  "type": "Feature",
  "properties": {
    "tgn:hierarchy":[
        "tgn:7416558",
        "tgn:1000001",
        "tgn:7005596",
        "tgn:7005560",
        "tgn:7029392"
    ],
    "tgn:id":7416558,
    "tgn:name:es":"Emiliano Zapata",
    "tgn:placetype":[
        "aat:300008347"
    ]
},
  "bbox": [],
  "geometry": {"coordinates":[-93.25,18.129167],"type":"Point"}
}