{
  "id": 2281108,
  "type": "Feature",
  "properties": {
    "tgn:hierarchy":[
        "tgn:2281108",
        "tgn:1000001",
        "tgn:7012149",
        "tgn:7007157",
        "tgn:2000191",
        "tgn:7029392"
    ],
    "tgn:id":2281108,
    "tgn:name":"Deep Hollow Creek",
    "tgn:placetype":[
        "aat:300008706"
    ]
},
  "bbox": [],
  "geometry": {"coordinates":[-123.3333,40.2167],"type":"Point"}
}