{
  "id": 7592254,
  "type": "Feature",
  "properties": {
    "tgn:hierarchy":[
        "tgn:7592254",
        "tgn:1000004",
        "tgn:7000198",
        "tgn:7000799",
        "tgn:7029392"
    ],
    "tgn:id":7592254,
    "tgn:name:en":"Pati\u0101r",
    "tgn:placetype":[
        "aat:300008347"
    ]
},
  "bbox": [],
  "geometry": {"coordinates":[74.982883,32.948416],"type":"Point"}
}