{
  "id": 2287821,
  "type": "Feature",
  "properties": {
    "tgn:hierarchy":[
        "tgn:2287821",
        "tgn:1000001",
        "tgn:7012149",
        "tgn:2000430",
        "tgn:7007248",
        "tgn:7029392"
    ],
    "tgn:id":2287821,
    "tgn:name":"Dills Branch",
    "tgn:placetype":[
        "aat:300008699"
    ]
},
  "bbox": [],
  "geometry": {"coordinates":[-83.75,34.8333],"type":"Point"}
}