{
  "id": 2669173,
  "type": "Feature",
  "properties": {
    "tgn:hierarchy":[
        "tgn:2669173",
        "tgn:1000001",
        "tgn:7012149",
        "tgn:2002117",
        "tgn:7007827",
        "tgn:7029392"
    ],
    "tgn:id":2669173,
    "tgn:name":"Sleepy Gulch",
    "tgn:placetype":[
        "aat:300008761"
    ]
},
  "bbox": [],
  "geometry": {"coordinates":[-111.4333,41.3667],"type":"Point"}
}