{
  "id": 2412128,
  "type": "Feature",
  "properties": {
    "tgn:hierarchy":[
        "tgn:2412128",
        "tgn:1000001",
        "tgn:7012149",
        "tgn:7007710",
        "tgn:7029392"
    ],
    "tgn:id":2412128,
    "tgn:name":"Indian Run",
    "tgn:placetype":[
        "aat:300008699"
    ]
},
  "bbox": [],
  "geometry": {"coordinates":[-78.1833,41.7333],"type":"Point"}
}