<<<<<<< HEAD
{
  "id": 2402561,
  "type": "Feature",
  "properties": {
    "tgn:hierarchy":[
        "tgn:2402561",
        "tgn:1000001",
        "tgn:7012149",
        "tgn:2000181",
        "tgn:7007157",
        "tgn:7029392"
    ],
    "tgn:id":2402561,
    "tgn:name":"Hospital Ridge",
    "tgn:placetype":[
        "aat:300266640"
    ]
},
  "bbox": [],
  "geometry": {"coordinates":[-123.6833,41.0333],"type":"Point"}
}
=======
{"geometry":{"type":"Point","coordinates":[-123.683300,41.033300]},"type":"Feature","properties":{"hierarchy":["tgn:2402561","tgn:1000001","tgn:7012149","tgn:2000181","tgn:7007157","tgn:7029392"],"placetype":["aat:300266640"],"id":2402561,"name:xx":"Hospital Ridge"}}
>>>>>>> 03f74aca74312dbeaf24d7e61306dd6a786dc3d0
