{
  "id": 2026938,
  "type": "Feature",
  "properties": {
    "tgn:hierarchy":[
        "tgn:2026938",
        "tgn:1000001",
        "tgn:7012149",
        "tgn:1002786",
        "tgn:7007251",
        "tgn:7029392"
    ],
    "tgn:id":2026938,
    "tgn:name":"Chambersburg",
    "tgn:placetype":[
        "aat:300008347"
    ]
},
  "bbox": [],
  "geometry": {"coordinates":[-90.65,39.8167],"type":"Point"}
}