<<<<<<< HEAD
{
  "id": 7173136,
  "type": "Feature",
  "properties": {
    "tgn:hierarchy":[
        "tgn:7173136",
        "tgn:1000003",
        "tgn:7003688",
        "tgn:7000084",
        "tgn:7029392"
    ],
    "tgn:id":7173136,
    "tgn:name":"Grellsb\u00fcll",
    "tgn:placetype":[
        "aat:300008347"
    ]
},
  "bbox": [],
  "geometry": {"coordinates":[8.866667,54.866667],"type":"Point"}
}
=======
{"geometry":{"type":"Point","coordinates":[8.866667,54.866667]},"type":"Feature","properties":{"hierarchy":["tgn:7173136","tgn:1000003","tgn:7003688","tgn:7000084","tgn:7029392"],"placetype":["aat:300008347"],"id":7173136,"name:xx":"Grellsb\u00fcll"}}
>>>>>>> 03f74aca74312dbeaf24d7e61306dd6a786dc3d0
