{
  "id": 7407342,
  "type": "Feature",
  "properties": {
    "tgn:hierarchy":[
        "tgn:7407342",
        "tgn:7005580",
        "tgn:1000001",
        "tgn:7005560",
        "tgn:7029392"
    ],
    "tgn:id":7407342,
    "tgn:name":"San Lucas, R\u00edo",
    "tgn:placetype":[
        "aat:300008699"
    ]
},
  "bbox": [],
  "geometry": {"coordinates":[-93.45,16.266667],"type":"Point"}
}