<<<<<<< HEAD
{
  "id": 2333651,
  "type": "Feature",
  "properties": {
    "tgn:hierarchy":[
        "tgn:2333651",
        "tgn:1000001",
        "tgn:2001016",
        "tgn:7012149",
        "tgn:7007521",
        "tgn:7029392"
    ],
    "tgn:id":2333651,
    "tgn:name":"Fool Lake",
    "tgn:placetype":[
        "aat:300008680"
    ]
},
  "bbox": [],
  "geometry": {"coordinates":[-94.0,46.5667],"type":"Point"}
}
=======
{"geometry":{"type":"Point","coordinates":[-94.000000,46.566700]},"type":"Feature","properties":{"hierarchy":["tgn:2333651","tgn:1000001","tgn:2001016","tgn:7012149","tgn:7007521","tgn:7029392"],"placetype":["aat:300008680"],"id":2333651,"name:xx":"Fool Lake"}}
>>>>>>> 03f74aca74312dbeaf24d7e61306dd6a786dc3d0
