{
  "id": 7543781,
  "type": "Feature",
  "properties": {
    "tgn:hierarchy":[
        "tgn:7543781",
        "tgn:7001242",
        "tgn:7016833",
        "tgn:1001110",
        "tgn:7029392"
    ],
    "tgn:id":7543781,
    "tgn:name:en":"Umm \u1e28amdah, Jabal",
    "tgn:placetype":[
        "aat:300008777"
    ]
},
  "bbox": [],
  "geometry": {"coordinates":[32.730556,30.018056],"type":"Point"}
}