<<<<<<< HEAD
{
  "id": 7365783,
  "type": "Feature",
  "properties": {
    "tgn:hierarchy":[
        "tgn:7365783",
        "tgn:7005583",
        "tgn:1000001",
        "tgn:7005560",
        "tgn:7029392"
    ],
    "tgn:id":7365783,
    "tgn:name":"El Tanque Kil\u00f3metro 987",
    "tgn:placetype":[
        "aat:300006191"
    ]
},
  "bbox": [],
  "geometry": {"coordinates":[-102.616667,24.7],"type":"Point"}
}
=======
{"geometry":{"type":"Point","coordinates":[-102.616667,24.700000]},"type":"Feature","properties":{"hierarchy":["tgn:7365783","tgn:7005583","tgn:1000001","tgn:7005560","tgn:7029392"],"placetype":["aat:300006191"],"id":7365783,"name:xx":"El Tanque Kil\u00f3metro 987"}}
>>>>>>> 03f74aca74312dbeaf24d7e61306dd6a786dc3d0
