{
  "id": 1106367,
  "type": "Feature",
  "properties": {
    "tgn:hierarchy":[
        "tgn:1106367",
        "tgn:7003669",
        "tgn:1000003",
        "tgn:7000084",
        "tgn:7029392"
    ],
    "tgn:id":1106367,
    "tgn:name":"Schneeberg",
    "tgn:placetype":[
        "aat:300008795"
    ]
},
  "bbox": [],
  "geometry": {"coordinates":[11.85,50.05],"type":"Point"}
}