{
  "id": 7516245,
  "type": "Feature",
  "properties": {
    "tgn:hierarchy":[
        "tgn:7516245",
        "tgn:7016670",
        "tgn:1008380",
        "tgn:1000226",
        "tgn:1000006",
        "tgn:7029392"
    ],
    "tgn:id":7516245,
    "tgn:name:en":"Mangareia",
    "tgn:placetype":[
        "aat:300008699"
    ]
},
  "bbox": [],
  "geometry": {"coordinates":[176.633333,-40.316667],"type":"Point"}
}