{
  "id": 7562407,
  "type": "Feature",
  "properties": {
    "tgn:hierarchy":[
        "tgn:7562407",
        "tgn:1000004",
        "tgn:7000198",
        "tgn:7016722",
        "tgn:7029392"
    ],
    "tgn:id":7562407,
    "tgn:name:en":"Santpur",
    "tgn:placetype":[
        "aat:300008347"
    ]
},
  "bbox": [],
  "geometry": {"coordinates":[79.347768,27.056121],"type":"Point"}
}