{
  "id": 7352539,
  "type": "Feature",
  "properties": {
    "tgn:hierarchy":[
        "tgn:7352539",
        "tgn:1000001",
        "tgn:7005595",
        "tgn:7005560",
        "tgn:7029392"
    ],
    "tgn:id":7352539,
    "tgn:name":"Barr\u00f3n",
    "tgn:placetype":[
        "aat:300008347"
    ]
},
  "bbox": [],
  "geometry": {"coordinates":[-106.283333,23.116667],"type":"Point"}
}