{
  "id": 7556434,
  "type": "Feature",
  "properties": {
    "tgn:hierarchy":[
        "tgn:7556434",
        "tgn:1000004",
        "tgn:7000198",
        "tgn:7000799",
        "tgn:7029392"
    ],
    "tgn:id":7556434,
    "tgn:name:en":"Ph\u014dti La",
    "tgn:placetype":[
        "aat:300259572"
    ]
},
  "bbox": [],
  "geometry": {"coordinates":[79.098528,32.759406],"type":"Point"}
}