{
  "id": 7533733,
  "type": "Feature",
  "properties": {
    "tgn:hierarchy":[
        "tgn:7533733",
        "tgn:7001242",
        "tgn:7016833",
        "tgn:7001312",
        "tgn:7029392"
    ],
    "tgn:id":7533733,
    "tgn:name:en":"Kafr 'I\u015f\u0101m",
    "tgn:placetype":[
        "aat:300008347"
    ]
},
  "bbox": [],
  "geometry": {"coordinates":[30.98389,30.806776],"type":"Point"}
}