{
  "id": 1096558,
  "type": "Feature",
  "properties": {
    "tgn:hierarchy":[
        "tgn:1096558",
        "tgn:7000490",
        "tgn:1000006",
        "tgn:7001828",
        "tgn:7029392"
    ],
    "tgn:id":1096558,
    "tgn:name":"Clarence Town",
    "tgn:placetype":[
        "aat:300008347"
    ]
},
  "bbox": [],
  "geometry": {"coordinates":[151.7833,-32.5833],"type":"Point"}
}