{
  "id": 7283605,
  "type": "Feature",
  "properties": {
    "tgn:hierarchy":[
        "tgn:7283605",
        "tgn:1001623",
        "tgn:1000049",
        "tgn:1000002",
        "tgn:7029392"
    ],
    "tgn:id":7283605,
    "tgn:name":"Papal",
    "tgn:placetype":[
        "aat:300004792"
    ]
},
  "bbox": [],
  "geometry": {"coordinates":[-73.15,-47.683333],"type":"Point"}
}