{
  "id": 7592026,
  "type": "Feature",
  "properties": {
    "tgn:hierarchy":[
        "tgn:7592026",
        "tgn:1000004",
        "tgn:7000198",
        "tgn:7000799",
        "tgn:7029392"
    ],
    "tgn:id":7592026,
    "tgn:name:en":"Nuni\u0101l",
    "tgn:placetype":[
        "aat:300008347"
    ]
},
  "bbox": [],
  "geometry": {"coordinates":[74.20943,33.15135],"type":"Point"}
}