{
  "id": 2639034,
  "type": "Feature",
  "properties": {
    "tgn:hierarchy":[
        "tgn:2639034",
        "tgn:2002101",
        "tgn:1000001",
        "tgn:7012149",
        "tgn:7007827",
        "tgn:7029392"
    ],
    "tgn:id":2639034,
    "tgn:name":"Salt Hollow",
    "tgn:placetype":[
        "aat:300008761"
    ]
},
  "bbox": [],
  "geometry": {"coordinates":[-112.55,38.4667],"type":"Point"}
}