{
  "id": 1071028,
  "type": "Feature",
  "properties": {
    "tgn:hierarchy":[
        "tgn:1071028",
        "tgn:1000004",
        "tgn:7002087",
        "tgn:1000111",
        "tgn:7029392"
    ],
    "tgn:id":1071028,
    "tgn:name":"Qijian",
    "tgn:placetype":[
        "aat:300008347"
    ]
},
  "bbox": [],
  "geometry": {"coordinates":[106.15,30.2333],"type":"Point"}
}