{
  "id": 7298123,
  "type": "Feature",
  "properties": {
    "tgn:hierarchy":[
        "tgn:7298123",
        "tgn:7010420",
        "tgn:1000003",
        "tgn:7002795",
        "tgn:1000095",
        "tgn:7029392"
    ],
    "tgn:id":7298123,
    "tgn:name":"Sietearroyos, Arroyo",
    "tgn:placetype":[
        "aat:300008699"
    ]
},
  "bbox": [],
  "geometry": {"coordinates":[-3.966667,40.95],"type":"Point"}
}