{
  "id": 2757299,
  "type": "Feature",
  "properties": {
    "tgn:hierarchy":[
        "tgn:2757299",
        "tgn:1000001",
        "tgn:7012149",
        "tgn:2000961",
        "tgn:7007520",
        "tgn:7029392"
    ],
    "tgn:id":2757299,
    "tgn:name":"West Arm Acme Creek",
    "tgn:placetype":[
        "aat:300008706"
    ]
},
  "bbox": [],
  "geometry": {"coordinates":[-85.4667,44.75],"type":"Point"}
}