{
  "id": 2279857,
  "type": "Feature",
  "properties": {
    "tgn:hierarchy":[
        "tgn:2279857",
        "tgn:1000001",
        "tgn:7012149",
        "tgn:2001129",
        "tgn:7007522",
        "tgn:7029392"
    ],
    "tgn:id":2279857,
    "tgn:name":"Dean Acres",
    "tgn:placetype":[
        "aat:300008347"
    ]
},
  "bbox": [],
  "geometry": {"coordinates":[-88.3833,33.4667],"type":"Point"}
}