{
  "id": 2539991,
  "type": "Feature",
  "properties": {
    "tgn:hierarchy":[
        "tgn:2539991",
        "tgn:1000001",
        "tgn:7012149",
        "tgn:2000432",
        "tgn:7007248",
        "tgn:7029392"
    ],
    "tgn:id":2539991,
    "tgn:name":"Newberry Lake",
    "tgn:placetype":[
        "aat:300006191"
    ]
},
  "bbox": [],
  "geometry": {"coordinates":[-84.9667,33.0833],"type":"Point"}
}