{
  "id": 2560447,
  "type": "Feature",
  "properties": {
    "tgn:hierarchy":[
        "tgn:2560447",
        "tgn:1000001",
        "tgn:7012149",
        "tgn:2000621",
        "tgn:7007253",
        "tgn:7029392"
    ],
    "tgn:id":2560447,
    "tgn:name":"Ord",
    "tgn:placetype":[
        "aat:300008347"
    ]
},
  "bbox": [],
  "geometry": {"coordinates":[-94.0667,41.25],"type":"Point"}
}