{
  "id": 2431203,
  "type": "Feature",
  "properties": {
    "tgn:hierarchy":[
        "tgn:2431203",
        "tgn:1000001",
        "tgn:2001410",
        "tgn:7012149",
        "tgn:7007526",
        "tgn:7029392"
    ],
    "tgn:id":2431203,
    "tgn:name":"Kaolin Wash",
    "tgn:placetype":[
        "aat:300008699"
    ]
},
  "bbox": [],
  "geometry": {"coordinates":[-114.55,36.45],"type":"Point"}
}