{
  "id": 7075539,
  "type": "Feature",
  "properties": {
    "tgn:hierarchy":[
        "tgn:7075539",
        "tgn:7003669",
        "tgn:1000003",
        "tgn:7000084",
        "tgn:7029392"
    ],
    "tgn:id":7075539,
    "tgn:name":"Stauden",
    "tgn:placetype":[
        "aat:300055621"
    ]
},
  "bbox": [],
  "geometry": {"coordinates":[10.666667,48.216667],"type":"Point"}
}