{
  "id": 1135574,
  "type": "Feature",
  "properties": {
    "tgn:hierarchy":[
        "tgn:1135574",
        "tgn:1000001",
        "tgn:7005595",
        "tgn:7005560",
        "tgn:7029392"
    ],
    "tgn:id":1135574,
    "tgn:name":"Baluarte, Boca del",
    "tgn:placetype":[
        "aat:300387057"
    ]
},
  "bbox": [],
  "geometry": {"coordinates":[-106.033333,22.833333],"type":"Point"}
}