{
  "id": 2484921,
  "type": "Feature",
  "properties": {
    "tgn:hierarchy":[
        "tgn:2484921",
        "tgn:1000001",
        "tgn:2001410",
        "tgn:7012149",
        "tgn:7007526",
        "tgn:7029392"
    ],
    "tgn:id":2484921,
    "tgn:name":"Lava Butte Wash",
    "tgn:placetype":[
        "aat:300008699"
    ]
},
  "bbox": [],
  "geometry": {"coordinates":[-114.9167,36.1333],"type":"Point"}
}