{
  "id": 2605741,
  "type": "Feature",
  "properties": {
    "tgn:hierarchy":[
        "tgn:2605741",
        "tgn:1000001",
        "tgn:2000953",
        "tgn:7012149",
        "tgn:7007520",
        "tgn:7029392"
    ],
    "tgn:id":2605741,
    "tgn:name":"Rainbow Bend",
    "tgn:placetype":[
        "aat:300008347"
    ]
},
  "bbox": [],
  "geometry": {"coordinates":[-84.9167,44.1167],"type":"Point"}
}