{
  "id": 2110890,
  "type": "Feature",
  "properties": {
    "tgn:hierarchy":[
        "tgn:2110890",
        "tgn:1000001",
        "tgn:7012149",
        "tgn:2002167",
        "tgn:7007919",
        "tgn:7029392"
    ],
    "tgn:id":2110890,
    "tgn:name":"Burnt Chimneys",
    "tgn:placetype":[
        "aat:300387016"
    ]
},
  "bbox": [],
  "geometry": {"coordinates":[-79.7167,36.6667],"type":"Point"}
}