<<<<<<< HEAD
{
  "id": 7378473,
  "type": "Feature",
  "properties": {
    "tgn:hierarchy":[
        "tgn:7378473",
        "tgn:7005584",
        "tgn:1000001",
        "tgn:7005560",
        "tgn:7029392"
    ],
    "tgn:id":7378473,
    "tgn:name":"La Presita",
    "tgn:placetype":[
        "aat:300008347"
    ]
},
  "bbox": [],
  "geometry": {"coordinates":[-100.783333,21.433333],"type":"Point"}
}
=======
{"geometry":{"type":"Point","coordinates":[-100.783333,21.433333]},"type":"Feature","properties":{"hierarchy":["tgn:7378473","tgn:7005584","tgn:1000001","tgn:7005560","tgn:7029392"],"placetype":["aat:300008347"],"id":7378473,"name:xx":"La Presita"}}
>>>>>>> 03f74aca74312dbeaf24d7e61306dd6a786dc3d0
