{
  "id": 2382459,
  "type": "Feature",
  "properties": {
    "tgn:hierarchy":[
        "tgn:2382459",
        "tgn:1000001",
        "tgn:2002102",
        "tgn:7012149",
        "tgn:7007827",
        "tgn:7029392"
    ],
    "tgn:id":2382459,
    "tgn:name":"Haystack Hill",
    "tgn:placetype":[
        "aat:300008798"
    ]
},
  "bbox": [],
  "geometry": {"coordinates":[-113.8667,41.6667],"type":"Point"}
}