{
  "id": 2363266,
  "type": "Feature",
  "properties": {
    "tgn:hierarchy":[
        "tgn:2363266",
        "tgn:1000001",
        "tgn:7012149",
        "tgn:7007568",
        "tgn:7029392"
    ],
    "tgn:id":2363266,
    "tgn:name":"Green Briar Brook",
    "tgn:placetype":[
        "aat:300008699"
    ]
},
  "bbox": [],
  "geometry": {"coordinates":[-73.6833,41.3333],"type":"Point"}
}