{
  "id": 7186796,
  "type": "Feature",
  "properties": {
    "tgn:hierarchy":[
        "tgn:7186796",
        "tgn:1000003",
        "tgn:7003689",
        "tgn:7000084",
        "tgn:7029392"
    ],
    "tgn:id":7186796,
    "tgn:name":"Gispersleben-Kiliani",
    "tgn:placetype":[
        "aat:300000745"
    ]
},
  "bbox": [],
  "geometry": {"coordinates":[10.983333,51.016667],"type":"Point"}
}