{
  "id": 2276245,
  "type": "Feature",
  "properties": {
    "tgn:hierarchy":[
        "tgn:2276245",
        "tgn:1000001",
        "tgn:7012149",
        "tgn:1002833",
        "tgn:7007568",
        "tgn:7029392"
    ],
    "tgn:id":2276245,
    "tgn:name":"Daters Mountain",
    "tgn:placetype":[
        "aat:300008798"
    ]
},
  "bbox": [],
  "geometry": {"coordinates":[-74.1667,41.1833],"type":"Point"}
}