{
  "id": 2442390,
  "type": "Feature",
  "properties": {
    "tgn:hierarchy":[
        "tgn:2442390",
        "tgn:1000001",
        "tgn:7012149",
        "tgn:7007158",
        "tgn:7029392"
    ],
    "tgn:id":2442390,
    "tgn:name":"Kreutzer, Mount",
    "tgn:placetype":[
        "aat:300008798"
    ]
},
  "bbox": [],
  "geometry": {"coordinates":[-106.4167,38.75],"type":"Point"}
}