{
  "id": 2296869,
  "type": "Feature",
  "properties": {
    "tgn:hierarchy":[
        "tgn:2296869",
        "tgn:1000001",
        "tgn:7012149",
        "tgn:1002517",
        "tgn:7007523",
        "tgn:7029392"
    ],
    "tgn:id":2296869,
    "tgn:name":"Dry Creek",
    "tgn:placetype":[
        "aat:300008706"
    ]
},
  "bbox": [],
  "geometry": {"coordinates":[-90.55,38.2333],"type":"Point"}
}