{
  "id": 7549321,
  "type": "Feature",
  "properties": {
    "tgn:hierarchy":[
        "tgn:7549321",
        "tgn:1000004",
        "tgn:7000198",
        "tgn:7016788",
        "tgn:7029392"
    ],
    "tgn:id":7549321,
    "tgn:name:en":"Chadi",
    "tgn:placetype":[
        "aat:300008347"
    ]
},
  "bbox": [],
  "geometry": {"coordinates":[73.055021,27.141263],"type":"Point"}
}