{
  "id": 2786094,
  "type": "Feature",
  "properties": {
    "tgn:hierarchy":[
        "tgn:2786094",
        "tgn:1000001",
        "tgn:7012149",
        "tgn:2000346",
        "tgn:7007248",
        "tgn:7029392"
    ],
    "tgn:id":2786094,
    "tgn:name":"Young Lake",
    "tgn:placetype":[
        "aat:300006191"
    ]
},
  "bbox": [],
  "geometry": {"coordinates":[-84.3833,34.85],"type":"Point"}
}