{
  "id": 7553253,
  "type": "Feature",
  "properties": {
    "tgn:hierarchy":[
        "tgn:7553253",
        "tgn:1000004",
        "tgn:7000198",
        "tgn:1001886",
        "tgn:7029392"
    ],
    "tgn:id":7553253,
    "tgn:name:en":"Neriyamangalam",
    "tgn:placetype":[
        "aat:300008347"
    ]
},
  "bbox": [],
  "geometry": {"coordinates":[76.783333,10.05],"type":"Point"}
}