{
  "id": 7310332,
  "type": "Feature",
  "properties": {
    "tgn:hierarchy":[
        "tgn:7310332",
        "tgn:7016598",
        "tgn:1000049",
        "tgn:1000002",
        "tgn:7029392"
    ],
    "tgn:id":7310332,
    "tgn:name":"Ordonez, Quebrada",
    "tgn:placetype":[
        "aat:300266554",
        "aat:300008699"
    ]
},
  "bbox": [],
  "geometry": {"coordinates":[-69.716667,-21.833333],"type":"Point"}
}