{
  "id": 2109186,
  "type": "Feature",
  "properties": {
    "tgn:hierarchy":[
        "tgn:2109186",
        "tgn:1000001",
        "tgn:7012149",
        "tgn:2002110",
        "tgn:7007827",
        "tgn:7029392"
    ],
    "tgn:id":2109186,
    "tgn:name":"Potash",
    "tgn:placetype":[
        "aat:300387016"
    ]
},
  "bbox": [],
  "geometry": {"coordinates":[-109.65,38.5167],"type":"Point"}
}