{
  "id": 2480222,
  "type": "Feature",
  "properties": {
    "tgn:hierarchy":[
        "tgn:2480222",
        "tgn:1000001",
        "tgn:7012149",
        "tgn:2001854",
        "tgn:7007825",
        "tgn:7029392"
    ],
    "tgn:id":2480222,
    "tgn:name":"Lake Park",
    "tgn:placetype":[
        "aat:300008347"
    ]
},
  "bbox": [],
  "geometry": {"coordinates":[-85.1667,35.8167],"type":"Point"}
}