{
  "id": 7348905,
  "type": "Feature",
  "properties": {
    "tgn:hierarchy":[
        "tgn:7348905",
        "tgn:1000001",
        "tgn:7005594",
        "tgn:7005560",
        "tgn:7029392"
    ],
    "tgn:id":7348905,
    "tgn:name":"\u00c1lamos",
    "tgn:placetype":[
        "aat:300008347"
    ]
},
  "bbox": [],
  "geometry": {"coordinates":[-100.016667,21.533333],"type":"Point"}
}