{
  "id": 2221202,
  "type": "Feature",
  "properties": {
    "tgn:hierarchy":[
        "tgn:2221202",
        "tgn:1000001",
        "tgn:7012149",
        "tgn:1002818",
        "tgn:7007252",
        "tgn:7029392"
    ],
    "tgn:id":2221202,
    "tgn:name":"Card Run",
    "tgn:placetype":[
        "aat:300008699"
    ]
},
  "bbox": [],
  "geometry": {"coordinates":[-84.8833,40.0333],"type":"Point"}
}