{
  "id": 7500421,
  "type": "Feature",
  "properties": {
    "tgn:hierarchy":[
        "tgn:7500421",
        "tgn:1000004",
        "tgn:7004300",
        "tgn:1000141",
        "tgn:7029392"
    ],
    "tgn:id":7500421,
    "tgn:name":"Dachijiao Wan",
    "tgn:placetype":[
        "aat:300132316"
    ]
},
  "bbox": [],
  "geometry": {"coordinates":[119.5075,23.611944],"type":"Point"}
}