{
  "id": 2756412,
  "type": "Feature",
  "properties": {
    "tgn:hierarchy":[
        "tgn:2756412",
        "tgn:1000001",
        "tgn:7012149",
        "tgn:1002999",
        "tgn:7007526",
        "tgn:7029392"
    ],
    "tgn:id":2756412,
    "tgn:name":"Well Canyon",
    "tgn:placetype":[
        "aat:300008761"
    ]
},
  "bbox": [],
  "geometry": {"coordinates":[-119.7167,41.15],"type":"Point"}
}