<<<<<<< HEAD
{
  "id": 2151641,
  "type": "Feature",
  "properties": {
    "tgn:hierarchy":[
        "tgn:2151641",
        "tgn:1000001",
        "tgn:7012149",
        "tgn:2000488",
        "tgn:7007250",
        "tgn:7029392"
    ],
    "tgn:id":2151641,
    "tgn:name":"Battle Creek",
    "tgn:placetype":[
        "aat:300008706"
    ]
},
  "bbox": [],
  "geometry": {"coordinates":[-116.4,42.7333],"type":"Point"}
}
=======
{"geometry":{"type":"Point","coordinates":[-116.400000,42.733300]},"type":"Feature","properties":{"hierarchy":["tgn:2151641","tgn:1000001","tgn:7012149","tgn:2000488","tgn:7007250","tgn:7029392"],"placetype":["aat:300008706"],"id":2151641,"name:xx":"Battle Creek"}}
>>>>>>> 03f74aca74312dbeaf24d7e61306dd6a786dc3d0
