{
  "id": 2182109,
  "type": "Feature",
  "properties": {
    "tgn:hierarchy":[
        "tgn:2182109",
        "tgn:1000001",
        "tgn:7012149",
        "tgn:2001232",
        "tgn:7007523",
        "tgn:7029392"
    ],
    "tgn:id":2182109,
    "tgn:name":"Blue Mound",
    "tgn:placetype":[
        "aat:300008798"
    ]
},
  "bbox": [],
  "geometry": {"coordinates":[-93.1833,37.5833],"type":"Point"}
}