{
  "id": 2389980,
  "type": "Feature",
  "properties": {
    "tgn:hierarchy":[
        "tgn:2389980",
        "tgn:1000001",
        "tgn:7012149",
        "tgn:2001843",
        "tgn:7007825",
        "tgn:7029392"
    ],
    "tgn:id":2389980,
    "tgn:name":"High Point Hollow",
    "tgn:placetype":[
        "aat:300008761"
    ]
},
  "bbox": [],
  "geometry": {"coordinates":[-84.2333,36.2833],"type":"Point"}
}