{
  "id": 7394543,
  "type": "Feature",
  "properties": {
    "tgn:hierarchy":[
        "tgn:7394543",
        "tgn:7005581",
        "tgn:1000001",
        "tgn:7005560",
        "tgn:7029392"
    ],
    "tgn:id":7394543,
    "tgn:name":"Sanguijuela, Sierra",
    "tgn:placetype":[
        "aat:300008795"
    ]
},
  "bbox": [],
  "geometry": {"coordinates":[-107.116667,30.833333],"type":"Point"}
}