<<<<<<< HEAD
{
  "id": 2336826,
  "type": "Feature",
  "properties": {
    "tgn:hierarchy":[
        "tgn:2336826",
        "tgn:1000001",
        "tgn:7012149",
        "tgn:1002384",
        "tgn:7007523",
        "tgn:7029392"
    ],
    "tgn:id":2336826,
    "tgn:name":"Fourmile Corner",
    "tgn:placetype":[
        "aat:300008347"
    ]
},
  "bbox": [],
  "geometry": {"coordinates":[-91.0333,38.5],"type":"Point"}
}
=======
{"geometry":{"type":"Point","coordinates":[-91.033300,38.500000]},"type":"Feature","properties":{"hierarchy":["tgn:2336826","tgn:1000001","tgn:7012149","tgn:1002384","tgn:7007523","tgn:7029392"],"placetype":["aat:300008347"],"id":2336826,"name:xx":"Fourmile Corner"}}
>>>>>>> 03f74aca74312dbeaf24d7e61306dd6a786dc3d0
