{
  "id": 2544758,
  "type": "Feature",
  "properties": {
    "tgn:hierarchy":[
        "tgn:2544758",
        "tgn:1000001",
        "tgn:2001842",
        "tgn:7012149",
        "tgn:7007825",
        "tgn:7029392"
    ],
    "tgn:id":2544758,
    "tgn:name":"North Club Estates",
    "tgn:placetype":[
        "aat:300008347"
    ]
},
  "bbox": [],
  "geometry": {"coordinates":[-84.8167,35.2167],"type":"Point"}
}