{
  "id": 7439768,
  "type": "Feature",
  "properties": {
    "tgn:hierarchy":[
        "tgn:7439768",
        "tgn:1000001",
        "tgn:7005591",
        "tgn:7005560",
        "tgn:7029392"
    ],
    "tgn:id":7439768,
    "tgn:name":"Santa Mar\u00eda Totolapilla",
    "tgn:placetype":[
        "aat:300008347"
    ]
},
  "bbox": [],
  "geometry": {"coordinates":[-95.633333,16.616667],"type":"Point"}
}