{
  "id": 7425091,
  "type": "Feature",
  "properties": {
    "tgn:hierarchy":[
        "tgn:7425091",
        "tgn:7005581",
        "tgn:1000001",
        "tgn:7005560",
        "tgn:7029392"
    ],
    "tgn:id":7425091,
    "tgn:name":"La Boquilla, Arroyo",
    "tgn:placetype":[
        "aat:300008699"
    ]
},
  "bbox": [],
  "geometry": {"coordinates":[-105.666667,27.533333],"type":"Point"}
}