{
  "id": 2616453,
  "type": "Feature",
  "properties": {
    "tgn:hierarchy":[
        "tgn:2616453",
        "tgn:1000001",
        "tgn:2001746",
        "tgn:7012149",
        "tgn:7007712",
        "tgn:7029392"
    ],
    "tgn:id":2616453,
    "tgn:name":"Rice Crossroads",
    "tgn:placetype":[
        "aat:300008347"
    ]
},
  "bbox": [],
  "geometry": {"coordinates":[-79.2333,33.65],"type":"Point"}
}