{
  "id": 1030551,
  "type": "Feature",
  "properties": {
    "tgn:hierarchy":[
        "tgn:1030551",
        "tgn:7002445",
        "tgn:1000003",
        "tgn:7008165",
        "tgn:7008591",
        "tgn:7029392"
    ],
    "tgn:id":1030551,
    "tgn:name":"Scremerston Station",
    "tgn:placetype":[
        "aat:300008347"
    ]
},
  "bbox": [],
  "geometry": {"coordinates":[-1.9667,55.7333],"type":"Point"}
}