{
  "id": 2658780,
  "type": "Feature",
  "properties": {
    "tgn:hierarchy":[
        "tgn:2658780",
        "tgn:1000001",
        "tgn:7012149",
        "tgn:2001147",
        "tgn:7007522",
        "tgn:7029392"
    ],
    "tgn:id":2658780,
    "tgn:name":"Sherman Hill",
    "tgn:placetype":[
        "aat:300008798"
    ]
},
  "bbox": [],
  "geometry": {"coordinates":[-89.3833,32.2667],"type":"Point"}
}