{
  "id": 7008992,
  "type": "Feature",
  "properties": {
    "tgn:hierarchy":[
        "tgn:7008992",
        "tgn:1000003",
        "tgn:1000070",
        "tgn:7002895",
        "tgn:7029392"
    ],
    "tgn:id":7008992,
    "tgn:name":"Brian\u00e7on",
    "tgn:placetype":[
        "aat:300008347",
        "aat:300387238",
        "aat:300387330",
        "aat:300008375"
    ]
},
  "bbox": [],
  "geometry": {"coordinates":[6.65,44.8833],"type":"Point"}
}