{
  "id": 2297805,
  "type": "Feature",
  "properties": {
    "tgn:hierarchy":[
        "tgn:2297805",
        "tgn:1000001",
        "tgn:2001260",
        "tgn:7012149",
        "tgn:7007524",
        "tgn:7029392"
    ],
    "tgn:id":2297805,
    "tgn:name":"Dry Hill",
    "tgn:placetype":[
        "aat:300008798"
    ]
},
  "bbox": [],
  "geometry": {"coordinates":[-112.65,45.05],"type":"Point"}
}