{
  "id": 2519938,
  "type": "Feature",
  "properties": {
    "tgn:hierarchy":[
        "tgn:2519938",
        "tgn:7006450",
        "tgn:1000001",
        "tgn:7012149",
        "tgn:2000085",
        "tgn:7029392"
    ],
    "tgn:id":2519938,
    "tgn:name":"Molbdenum Ridge",
    "tgn:placetype":[
        "aat:300266640"
    ]
},
  "bbox": [],
  "geometry": {"coordinates":[-146.65,63.8167],"type":"Point"}
}