<<<<<<< HEAD
{
  "id": 7175762,
  "type": "Feature",
  "properties": {
    "tgn:hierarchy":[
        "tgn:7175762",
        "tgn:1000003",
        "tgn:7003676",
        "tgn:7000084",
        "tgn:7029392"
    ],
    "tgn:id":7175762,
    "tgn:name":"Grienenbergsmoor",
    "tgn:placetype":[
        "aat:300386886"
    ]
},
  "bbox": [],
  "geometry": {"coordinates":[8.6,53.35],"type":"Point"}
}
=======
{"geometry":{"type":"Point","coordinates":[8.600000,53.350000]},"type":"Feature","properties":{"hierarchy":["tgn:7175762","tgn:1000003","tgn:7003676","tgn:7000084","tgn:7029392"],"placetype":["aat:300386886"],"id":7175762,"name:xx":"Grienenbergsmoor"}}
>>>>>>> 03f74aca74312dbeaf24d7e61306dd6a786dc3d0
