{
  "id": 7559150,
  "type": "Feature",
  "properties": {
    "tgn:hierarchy":[
        "tgn:7559150",
        "tgn:1000004",
        "tgn:1001842",
        "tgn:7000198",
        "tgn:7029392"
    ],
    "tgn:id":7559150,
    "tgn:name:en":"Sarmera",
    "tgn:placetype":[
        "aat:300008347"
    ]
},
  "bbox": [],
  "geometry": {"coordinates":[85.798799,25.254552],"type":"Point"}
}