{
  "id": 2221585,
  "type": "Feature",
  "properties": {
    "tgn:hierarchy":[
        "tgn:2221585",
        "tgn:1000001",
        "tgn:2001635",
        "tgn:7012149",
        "tgn:7007707",
        "tgn:7029392"
    ],
    "tgn:id":2221585,
    "tgn:name":"Carl Etling, Lake",
    "tgn:placetype":[
        "aat:300006191"
    ]
},
  "bbox": [],
  "geometry": {"coordinates":[-102.8667,36.8333],"type":"Point"}
}