{
  "id": 2367957,
  "type": "Feature",
  "properties": {
    "tgn:hierarchy":[
        "tgn:2367957",
        "tgn:1000001",
        "tgn:7012149",
        "tgn:1002372",
        "tgn:7007706",
        "tgn:7029392"
    ],
    "tgn:id":2367957,
    "tgn:name":"Grub Run",
    "tgn:placetype":[
        "aat:300008699"
    ]
},
  "bbox": [],
  "geometry": {"coordinates":[-83.3167,39.5833],"type":"Point"}
}