<<<<<<< HEAD
{
  "id": 2404600,
  "type": "Feature",
  "properties": {
    "tgn:hierarchy":[
        "tgn:2404600",
        "tgn:1000001",
        "tgn:7012149",
        "tgn:1002685",
        "tgn:7007251",
        "tgn:7029392"
    ],
    "tgn:id":2404600,
    "tgn:name":"Huber Hill",
    "tgn:placetype":[
        "aat:300008798"
    ]
},
  "bbox": [],
  "geometry": {"coordinates":[-89.5167,39.1667],"type":"Point"}
}
=======
{"geometry":{"type":"Point","coordinates":[-89.516700,39.166700]},"type":"Feature","properties":{"hierarchy":["tgn:2404600","tgn:1000001","tgn:7012149","tgn:1002685","tgn:7007251","tgn:7029392"],"placetype":["aat:300008798"],"id":2404600,"name:xx":"Huber Hill"}}
>>>>>>> 03f74aca74312dbeaf24d7e61306dd6a786dc3d0
