{
  "id": 7351253,
  "type": "Feature",
  "properties": {
    "tgn:hierarchy":[
        "tgn:7351253",
        "tgn:7005580",
        "tgn:1000001",
        "tgn:7005560",
        "tgn:7029392"
    ],
    "tgn:id":7351253,
    "tgn:name":"Cacaluta",
    "tgn:placetype":[
        "aat:300008699"
    ]
},
  "bbox": [],
  "geometry": {"coordinates":[-92.883333,15.233333],"type":"Point"}
}