<<<<<<< HEAD
{
  "id": 7351253,
  "type": "Feature",
  "properties": {
    "tgn:hierarchy":[
        "tgn:7351253",
        "tgn:7005580",
        "tgn:1000001",
        "tgn:7005560",
        "tgn:7029392"
    ],
    "tgn:id":7351253,
    "tgn:name":"Cacaluta",
    "tgn:placetype":[
        "aat:300008699"
    ]
},
  "bbox": [],
  "geometry": {"coordinates":[-92.883333,15.233333],"type":"Point"}
}
=======
{"geometry":{"type":"Point","coordinates":[-92.883333,15.233333]},"type":"Feature","properties":{"hierarchy":["tgn:7351253","tgn:7005580","tgn:1000001","tgn:7005560","tgn:7029392"],"placetype":["aat:300008699"],"id":7351253,"name:xx":"Cacaluta"}}
>>>>>>> 03f74aca74312dbeaf24d7e61306dd6a786dc3d0
