{
  "id": 7243356,
  "type": "Feature",
  "properties": {
    "tgn:hierarchy":[
        "tgn:7243356",
        "tgn:7003456",
        "tgn:1000003",
        "tgn:1000063",
        "tgn:7018236",
        "tgn:7029392"
    ],
    "tgn:id":7243356,
    "tgn:name":"Kruikeven",
    "tgn:placetype":[
        "aat:300008347"
    ]
},
  "bbox": [],
  "geometry": {"coordinates":[5.116667,51.35],"type":"Point"}
}