<<<<<<< HEAD
{
  "id": 7243356,
  "type": "Feature",
  "properties": {
    "tgn:hierarchy":[
        "tgn:7243356",
        "tgn:7003456",
        "tgn:1000003",
        "tgn:1000063",
        "tgn:7018236",
        "tgn:7029392"
    ],
    "tgn:id":7243356,
    "tgn:name":"Kruikeven",
    "tgn:placetype":[
        "aat:300008347"
    ]
},
  "bbox": [],
  "geometry": {"coordinates":[5.116667,51.35],"type":"Point"}
}
=======
{"geometry":{"type":"Point","coordinates":[5.116667,51.350000]},"type":"Feature","properties":{"hierarchy":["tgn:7243356","tgn:7003456","tgn:1000003","tgn:1000063","tgn:7018236","tgn:7029392"],"placetype":["aat:300008347"],"id":7243356,"name:xx":"Kruikeven"}}
>>>>>>> 03f74aca74312dbeaf24d7e61306dd6a786dc3d0
