{
  "id": 2220108,
  "type": "Feature",
  "properties": {
    "tgn:hierarchy":[
        "tgn:2220108",
        "tgn:7006450",
        "tgn:2000069",
        "tgn:1000001",
        "tgn:7012149",
        "tgn:7029392"
    ],
    "tgn:id":2220108,
    "tgn:name":"Canyon Lake",
    "tgn:placetype":[
        "aat:300008680"
    ]
},
  "bbox": [],
  "geometry": {"coordinates":[-161.1667,59.4167],"type":"Point"}
}