{
  "id": 2545317,
  "type": "Feature",
  "properties": {
    "tgn:hierarchy":[
        "tgn:2545317",
        "tgn:1000001",
        "tgn:7012149",
        "tgn:7007157",
        "tgn:1002857",
        "tgn:7029392"
    ],
    "tgn:id":2545317,
    "tgn:name":"North Fork Barrett Canyon",
    "tgn:placetype":[
        "aat:300008761"
    ]
},
  "bbox": [],
  "geometry": {"coordinates":[-117.6333,34.2167],"type":"Point"}
}