{
  "id": 2325243,
  "type": "Feature",
  "properties": {
    "tgn:hierarchy":[
        "tgn:2325243",
        "tgn:1000001",
        "tgn:7012149",
        "tgn:7016167",
        "tgn:7007523",
        "tgn:7029392"
    ],
    "tgn:id":2325243,
    "tgn:name":"Fernridge",
    "tgn:placetype":[
        "aat:300008347"
    ]
},
  "bbox": [],
  "geometry": {"coordinates":[-90.4667,38.6667],"type":"Point"}
}