{
  "id": 2233045,
  "type": "Feature",
  "properties": {
    "tgn:hierarchy":[
        "tgn:2233045",
        "tgn:1000001",
        "tgn:7012149",
        "tgn:7007825",
        "tgn:7029392"
    ],
    "tgn:id":2233045,
    "tgn:name":"Charit Creek",
    "tgn:placetype":[
        "aat:300008706"
    ]
},
  "bbox": [],
  "geometry": {"coordinates":[-84.75,36.55],"type":"Point"}
}