{
  "id": 1072867,
  "type": "Feature",
  "properties": {
    "tgn:hierarchy":[
        "tgn:1072867",
        "tgn:1000004",
        "tgn:7002087",
        "tgn:1000111",
        "tgn:7029392"
    ],
    "tgn:id":1072867,
    "tgn:name":"Xiaonanhai",
    "tgn:placetype":[
        "aat:300008347"
    ]
},
  "bbox": [],
  "geometry": {"coordinates":[106.4333,29.3833],"type":"Point"}
}