{
  "id": 2316222,
  "type": "Feature",
  "properties": {
    "tgn:hierarchy":[
        "tgn:2316222",
        "tgn:1000001",
        "tgn:7012149",
        "tgn:2000553",
        "tgn:7007252",
        "tgn:7029392"
    ],
    "tgn:id":2316222,
    "tgn:name":"Elmer Martens Lake",
    "tgn:placetype":[
        "aat:300006191"
    ]
},
  "bbox": [],
  "geometry": {"coordinates":[-86.6833,39.7333],"type":"Point"}
}