<<<<<<< HEAD
{
  "id": 7110743,
  "type": "Feature",
  "properties": {
    "tgn:hierarchy":[
        "tgn:7110743",
        "tgn:1000003",
        "tgn:7003688",
        "tgn:7000084",
        "tgn:7029392"
    ],
    "tgn:id":7110743,
    "tgn:name":"Rauher Berg",
    "tgn:placetype":[
        "aat:300008777"
    ]
},
  "bbox": [],
  "geometry": {"coordinates":[11.05,54.266667],"type":"Point"}
}
=======
{"geometry":{"type":"Point","coordinates":[11.050000,54.266667]},"type":"Feature","properties":{"hierarchy":["tgn:7110743","tgn:1000003","tgn:7003688","tgn:7000084","tgn:7029392"],"placetype":["aat:300008777"],"id":7110743,"name:xx":"Rauher Berg"}}
>>>>>>> 03f74aca74312dbeaf24d7e61306dd6a786dc3d0
