<<<<<<< HEAD
{
  "id": 2339671,
  "type": "Feature",
  "properties": {
    "tgn:hierarchy":[
        "tgn:2339671",
        "tgn:7002659",
        "tgn:1000001",
        "tgn:7012149",
        "tgn:7029392"
    ],
    "tgn:id":2339671,
    "tgn:name":"Free Branch",
    "tgn:placetype":[
        "aat:300008699"
    ]
},
  "bbox": [],
  "geometry": {"coordinates":[-86.45,31.7],"type":"Point"}
}
=======
{"geometry":{"type":"Point","coordinates":[-86.450000,31.700000]},"type":"Feature","properties":{"hierarchy":["tgn:2339671","tgn:7002659","tgn:1000001","tgn:7012149","tgn:7029392"],"placetype":["aat:300008699"],"id":2339671,"name:xx":"Free Branch"}}
>>>>>>> 03f74aca74312dbeaf24d7e61306dd6a786dc3d0
