{
  "id": 2184779,
  "type": "Feature",
  "properties": {
    "tgn:hierarchy":[
        "tgn:2184779",
        "tgn:1000001",
        "tgn:7012149",
        "tgn:2000978",
        "tgn:7007520",
        "tgn:7029392"
    ],
    "tgn:id":2184779,
    "tgn:name":"Bog Brook",
    "tgn:placetype":[
        "aat:300008699"
    ]
},
  "bbox": [],
  "geometry": {"coordinates":[-87.6333,45.5833],"type":"Point"}
}