<<<<<<< HEAD
{
  "id": 7172142,
  "type": "Feature",
  "properties": {
    "tgn:hierarchy":[
        "tgn:7172142",
        "tgn:1000003",
        "tgn:7003676",
        "tgn:7000084",
        "tgn:7029392"
    ],
    "tgn:id":7172142,
    "tgn:name":"Helmscherode",
    "tgn:placetype":[
        "aat:300008347"
    ]
},
  "bbox": [],
  "geometry": {"coordinates":[10.05,51.916667],"type":"Point"}
}
=======
{"geometry":{"type":"Point","coordinates":[10.050000,51.916667]},"type":"Feature","properties":{"hierarchy":["tgn:7172142","tgn:1000003","tgn:7003676","tgn:7000084","tgn:7029392"],"placetype":["aat:300008347"],"id":7172142,"name:xx":"Helmscherode"}}
>>>>>>> 03f74aca74312dbeaf24d7e61306dd6a786dc3d0
