<<<<<<< HEAD
{
  "id": 7369096,
  "type": "Feature",
  "properties": {
    "tgn:hierarchy":[
        "tgn:7369096",
        "tgn:1001836",
        "tgn:1000001",
        "tgn:7005560",
        "tgn:7029392"
    ],
    "tgn:id":7369096,
    "tgn:name":"Ixcatla",
    "tgn:placetype":[
        "aat:300008347"
    ]
},
  "bbox": [],
  "geometry": {"coordinates":[-96.922222,19.073611],"type":"Point"}
}
=======
{"geometry":{"type":"Point","coordinates":[-96.922222,19.073611]},"type":"Feature","properties":{"hierarchy":["tgn:7369096","tgn:1001836","tgn:1000001","tgn:7005560","tgn:7029392"],"placetype":["aat:300008347"],"id":7369096,"name:xx":"Ixcatla"}}
>>>>>>> 03f74aca74312dbeaf24d7e61306dd6a786dc3d0
