{
  "id": 7369096,
  "type": "Feature",
  "properties": {
    "tgn:hierarchy":[
        "tgn:7369096",
        "tgn:1001836",
        "tgn:1000001",
        "tgn:7005560",
        "tgn:7029392"
    ],
    "tgn:id":7369096,
    "tgn:name":"Ixcatla",
    "tgn:placetype":[
        "aat:300008347"
    ]
},
  "bbox": [],
  "geometry": {"coordinates":[-96.922222,19.073611],"type":"Point"}
}