{
  "id": 2772403,
  "type": "Feature",
  "properties": {
    "tgn:hierarchy":[
        "tgn:2772403",
        "tgn:1000001",
        "tgn:7012149",
        "tgn:2000851",
        "tgn:7007255",
        "tgn:7029392"
    ],
    "tgn:id":2772403,
    "tgn:name":"Williams",
    "tgn:placetype":[
        "aat:300008347"
    ]
},
  "bbox": [],
  "geometry": {"coordinates":[-87.85,37.5167],"type":"Point"}
}