<<<<<<< HEAD
{
  "id": 2253759,
  "type": "Feature",
  "properties": {
    "tgn:hierarchy":[
        "tgn:2253759",
        "tgn:1000001",
        "tgn:7012149",
        "tgn:2001491",
        "tgn:7007709",
        "tgn:7029392"
    ],
    "tgn:id":2253759,
    "tgn:name":"Cooks Branch",
    "tgn:placetype":[
        "aat:300008699"
    ]
},
  "bbox": [],
  "geometry": {"coordinates":[-77.9333,34.8333],"type":"Point"}
}
=======
{"geometry":{"type":"Point","coordinates":[-77.933300,34.833300]},"type":"Feature","properties":{"hierarchy":["tgn:2253759","tgn:1000001","tgn:7012149","tgn:2001491","tgn:7007709","tgn:7029392"],"placetype":["aat:300008699"],"id":2253759,"name:xx":"Cooks Branch"}}
>>>>>>> 03f74aca74312dbeaf24d7e61306dd6a786dc3d0
