{
  "id": 7304312,
  "type": "Feature",
  "properties": {
    "tgn:hierarchy":[
        "tgn:7304312",
        "tgn:7008911",
        "tgn:1000003",
        "tgn:7002763",
        "tgn:1000095",
        "tgn:7029392"
    ],
    "tgn:id":7304312,
    "tgn:name":"Los Carreros, Bajo",
    "tgn:placetype":[
        "aat:300387036"
    ]
},
  "bbox": [],
  "geometry": {"coordinates":[-5.116667,43.483333],"type":"Point"}
}