{
  "id": 2770205,
  "type": "Feature",
  "properties": {
    "tgn:hierarchy":[
        "tgn:2770205",
        "tgn:1000001",
        "tgn:1002233",
        "tgn:7012149",
        "tgn:7007710",
        "tgn:7029392"
    ],
    "tgn:id":2770205,
    "tgn:name":"Wild Creek",
    "tgn:placetype":[
        "aat:300008706"
    ]
},
  "bbox": [],
  "geometry": {"coordinates":[-75.6333,40.9333],"type":"Point"}
}