{
  "id": 7331611,
  "type": "Feature",
  "properties": {
    "tgn:hierarchy":[
        "tgn:7331611",
        "tgn:7002807",
        "tgn:1000003",
        "tgn:7003837",
        "tgn:1000095",
        "tgn:7029392"
    ],
    "tgn:id":7331611,
    "tgn:name":"Lacar\u00f3n, R\u00edo",
    "tgn:placetype":[
        "aat:300008699"
    ]
},
  "bbox": [],
  "geometry": {"coordinates":[-6.55,38.883333],"type":"Point"}
}