{
  "id": 2311149,
  "type": "Feature",
  "properties": {
    "tgn:hierarchy":[
        "tgn:2311149",
        "tgn:7014201",
        "tgn:1000001",
        "tgn:7012149",
        "tgn:7007239",
        "tgn:7029392"
    ],
    "tgn:id":2311149,
    "tgn:name":"Edgebrooke",
    "tgn:placetype":[
        "aat:300008347"
    ]
},
  "bbox": [],
  "geometry": {"coordinates":[-75.65,39.6667],"type":"Point"}
}