{
  "id": 1012526,
  "type": "Feature",
  "properties": {
    "tgn:hierarchy":[
        "tgn:1012526",
        "tgn:1000001",
        "tgn:7012149",
        "tgn:1002356",
        "tgn:7007568",
        "tgn:7029392"
    ],
    "tgn:id":1012526,
    "tgn:name":"Sturgeon Point",
    "tgn:placetype":[
        "aat:300386846"
    ]
},
  "bbox": [],
  "geometry": {"coordinates":[-79.0333,42.6833],"type":"Point"}
}