{
  "id": 7232560,
  "type": "Feature",
  "properties": {
    "tgn:hierarchy":[
        "tgn:7232560",
        "tgn:7002741",
        "tgn:7017076",
        "tgn:1000003",
        "tgn:1000074",
        "tgn:7029392"
    ],
    "tgn:id":7232560,
    "tgn:name":"Isidh\u00f3rou, \u00d3rmos",
    "tgn:placetype":[
        "aat:300132316"
    ]
},
  "bbox": [],
  "geometry": {"coordinates":[22.616667,38.35],"type":"Point"}
}