{
  "id": 7555914,
  "type": "Feature",
  "properties": {
    "tgn:hierarchy":[
        "tgn:7555914",
        "tgn:1000004",
        "tgn:7000198",
        "tgn:1001977",
        "tgn:7029392"
    ],
    "tgn:id":7555914,
    "tgn:name:en":"N\u0101r\u0101ngi",
    "tgn:placetype":[
        "aat:300008347"
    ]
},
  "bbox": [],
  "geometry": {"coordinates":[87.516667,23.083333],"type":"Point"}
}