{
  "id": 2626366,
  "type": "Feature",
  "properties": {
    "tgn:hierarchy":[
        "tgn:2626366",
        "tgn:1000001",
        "tgn:7012149",
        "tgn:1002476",
        "tgn:7007706",
        "tgn:7029392"
    ],
    "tgn:id":2626366,
    "tgn:name":"Rocky Fork",
    "tgn:placetype":[
        "aat:300008699"
    ]
},
  "bbox": [],
  "geometry": {"coordinates":[-83.65,39.1333],"type":"Point"}
}