{
  "id": 2226473,
  "type": "Feature",
  "properties": {
    "tgn:hierarchy":[
        "tgn:2226473",
        "tgn:1000001",
        "tgn:7012149",
        "tgn:2001217",
        "tgn:7007523",
        "tgn:7029392"
    ],
    "tgn:id":2226473,
    "tgn:name":"Catherine Mines",
    "tgn:placetype":[
        "aat:300000390"
    ]
},
  "bbox": [],
  "geometry": {"coordinates":[-90.3333,37.5833],"type":"Point"}
}