{
  "id": 7054962,
  "type": "Feature",
  "properties": {
    "tgn:hierarchy":[
        "tgn:7054962",
        "tgn:7005023",
        "tgn:1000003",
        "tgn:7003237",
        "tgn:1000080",
        "tgn:7029392"
    ],
    "tgn:id":7054962,
    "tgn:name":"Lizzola Alta",
    "tgn:placetype":[
        "aat:300008347"
    ]
},
  "bbox": [],
  "geometry": {"coordinates":[10.016667,46.033333],"type":"Point"}
}