<<<<<<< HEAD
{
  "id": 7372006,
  "type": "Feature",
  "properties": {
    "tgn:hierarchy":[
        "tgn:7372006",
        "tgn:1000001",
        "tgn:7005589",
        "tgn:7005560",
        "tgn:7029392"
    ],
    "tgn:id":7372006,
    "tgn:name":"La Negra, Arroyo",
    "tgn:placetype":[
        "aat:300266554",
        "aat:300008699"
    ]
},
  "bbox": [],
  "geometry": {"coordinates":[-100.233333,25.966667],"type":"Point"}
}
=======
{"geometry":{"type":"Point","coordinates":[-100.233333,25.966667]},"type":"Feature","properties":{"hierarchy":["tgn:7372006","tgn:1000001","tgn:7005589","tgn:7005560","tgn:7029392"],"placetype":["aat:300266554","aat:300008699"],"id":7372006,"name:xx":"La Negra, Arroyo"}}
>>>>>>> 03f74aca74312dbeaf24d7e61306dd6a786dc3d0
