{
  "id": 2699593,
  "type": "Feature",
  "properties": {
    "tgn:hierarchy":[
        "tgn:2699593",
        "tgn:1000001",
        "tgn:7012149",
        "tgn:1002943",
        "tgn:7007708",
        "tgn:7029392"
    ],
    "tgn:id":2699593,
    "tgn:name":"Struby Creek Reservoir",
    "tgn:placetype":[
        "aat:300006191"
    ]
},
  "bbox": [],
  "geometry": {"coordinates":[-123.8833,45.5667],"type":"Point"}
}