{
  "id": 2343505,
  "type": "Feature",
  "properties": {
    "tgn:hierarchy":[
        "tgn:2343505",
        "tgn:1000001",
        "tgn:7012149",
        "tgn:7007157",
        "tgn:1002894",
        "tgn:7029392"
    ],
    "tgn:id":2343505,
    "tgn:name":"Gale Creek",
    "tgn:placetype":[
        "aat:300008706"
    ]
},
  "bbox": [],
  "geometry": {"coordinates":[-120.9333,39.4833],"type":"Point"}
}