{
  "id": 7532233,
  "type": "Feature",
  "properties": {
    "tgn:hierarchy":[
        "tgn:7532233",
        "tgn:7001242",
        "tgn:7016833",
        "tgn:1001335",
        "tgn:7029392"
    ],
    "tgn:id":7532233,
    "tgn:name:en":"K\u00fbdya, R\u00e2s el-",
    "tgn:placetype":[
        "aat:300386846"
    ]
},
  "bbox": [],
  "geometry": {"coordinates":[30.902778,31.541667],"type":"Point"}
}