{
  "id": 7382839,
  "type": "Feature",
  "properties": {
    "tgn:hierarchy":[
        "tgn:7382839",
        "tgn:7005586",
        "tgn:1000001",
        "tgn:7005560",
        "tgn:7029392"
    ],
    "tgn:id":7382839,
    "tgn:name":"Palos Altos",
    "tgn:placetype":[
        "aat:300008347"
    ]
},
  "bbox": [],
  "geometry": {"coordinates":[-103.15,20.866667],"type":"Point"}
}