{
  "id": 7222701,
  "type": "Feature",
  "properties": {
    "tgn:hierarchy":[
        "tgn:7222701",
        "tgn:7002718",
        "tgn:7002715",
        "tgn:1000003",
        "tgn:1000074",
        "tgn:7029392"
    ],
    "tgn:id":7222701,
    "tgn:name":"Palai\u00f3n Zervoch\u00f3rion",
    "tgn:placetype":[
        "aat:300008347"
    ]
},
  "bbox": [],
  "geometry": {"coordinates":[22.233056,40.651111],"type":"Point"}
}