{
  "id": 2621596,
  "type": "Feature",
  "properties": {
    "tgn:hierarchy":[
        "tgn:2621596",
        "tgn:2000106",
        "tgn:1000001",
        "tgn:7016172",
        "tgn:7012149",
        "tgn:7029392"
    ],
    "tgn:id":2621596,
    "tgn:name":"Roark",
    "tgn:placetype":[
        "aat:300008347"
    ]
},
  "bbox": [],
  "geometry": {"coordinates":[-91.8167,33.35],"type":"Point"}
}