{
  "id": 7195600,
  "type": "Feature",
  "properties": {
    "tgn:hierarchy":[
        "tgn:7195600",
        "tgn:1000003",
        "tgn:7000094",
        "tgn:7000084",
        "tgn:7029392"
    ],
    "tgn:id":7195600,
    "tgn:name":"Dischley",
    "tgn:placetype":[
        "aat:300008347"
    ]
},
  "bbox": [],
  "geometry": {"coordinates":[13.466667,53.733333],"type":"Point"}
}