{
  "id": 2484344,
  "type": "Feature",
  "properties": {
    "tgn:hierarchy":[
        "tgn:2484344",
        "tgn:1000001",
        "tgn:7012149",
        "tgn:7007157",
        "tgn:7014004",
        "tgn:7029392"
    ],
    "tgn:id":2484344,
    "tgn:name":"Laurel Creek",
    "tgn:placetype":[
        "aat:300008706"
    ]
},
  "bbox": [],
  "geometry": {"coordinates":[-119.6833,37.4667],"type":"Point"}
}