<<<<<<< HEAD
{
  "id": 7479602,
  "type": "Feature",
  "properties": {
    "tgn:hierarchy":[
        "tgn:7479602",
        "tgn:1000004",
        "tgn:7490934",
        "tgn:1000141",
        "tgn:7029392"
    ],
    "tgn:id":7479602,
    "tgn:name":"Meizhou Gong",
    "tgn:placetype":[
        "aat:300007595"
    ]
},
  "bbox": [],
  "geometry": {"coordinates":[120.205,23.111944],"type":"Point"}
}
=======
{"geometry":{"type":"Point","coordinates":[120.205000,23.111944]},"type":"Feature","properties":{"hierarchy":["tgn:7479602","tgn:1000004","tgn:7490934","tgn:1000141","tgn:7029392"],"placetype":["aat:300007595"],"id":7479602,"name:xx":"Meizhou Gong"}}
>>>>>>> 03f74aca74312dbeaf24d7e61306dd6a786dc3d0
