{
  "id": 2266648,
  "type": "Feature",
  "properties": {
    "tgn:hierarchy":[
        "tgn:2266648",
        "tgn:1000001",
        "tgn:7012149",
        "tgn:2000539",
        "tgn:7007251",
        "tgn:7029392"
    ],
    "tgn:id":2266648,
    "tgn:name":"Crenshaw Crossing",
    "tgn:placetype":[
        "aat:300008347"
    ]
},
  "bbox": [],
  "geometry": {"coordinates":[-88.9667,37.7667],"type":"Point"}
}