<<<<<<< HEAD
{
  "id": 2336545,
  "type": "Feature",
  "properties": {
    "tgn:hierarchy":[
        "tgn:2336545",
        "tgn:1000001",
        "tgn:7012149",
        "tgn:2002374",
        "tgn:7007923",
        "tgn:7029392"
    ],
    "tgn:id":2336545,
    "tgn:name":"Four H Reservoir",
    "tgn:placetype":[
        "aat:300006191"
    ]
},
  "bbox": [],
  "geometry": {"coordinates":[-106.5333,44.4667],"type":"Point"}
}
=======
{"geometry":{"type":"Point","coordinates":[-106.533300,44.466700]},"type":"Feature","properties":{"hierarchy":["tgn:2336545","tgn:1000001","tgn:7012149","tgn:2002374","tgn:7007923","tgn:7029392"],"placetype":["aat:300006191"],"id":2336545,"name:xx":"Four H Reservoir"}}
>>>>>>> 03f74aca74312dbeaf24d7e61306dd6a786dc3d0
