<<<<<<< HEAD
{
  "id": 7486133,
  "type": "Feature",
  "properties": {
    "tgn:hierarchy":[
        "tgn:7486133",
        "tgn:7487020",
        "tgn:1000004",
        "tgn:1000141",
        "tgn:7029392"
    ],
    "tgn:id":7486133,
    "tgn:name":"Malinshe",
    "tgn:placetype":[
        "aat:300008347"
    ]
},
  "bbox": [],
  "geometry": {"coordinates":[120.965809,24.591339],"type":"Point"}
}
=======
{"geometry":{"type":"Point","coordinates":[120.965809,24.591339]},"type":"Feature","properties":{"hierarchy":["tgn:7486133","tgn:7487020","tgn:1000004","tgn:1000141","tgn:7029392"],"placetype":["aat:300008347"],"id":7486133,"name:xx":"Malinshe"}}
>>>>>>> 03f74aca74312dbeaf24d7e61306dd6a786dc3d0
