{
  "id": 2392652,
  "type": "Feature",
  "properties": {
    "tgn:hierarchy":[
        "tgn:2392652",
        "tgn:1000001",
        "tgn:7012149",
        "tgn:2001706",
        "tgn:7007708",
        "tgn:7029392"
    ],
    "tgn:id":2392652,
    "tgn:name":"Hob Knob",
    "tgn:placetype":[
        "aat:300008798"
    ]
},
  "bbox": [],
  "geometry": {"coordinates":[-122.8333,43.0333],"type":"Point"}
}