{
  "id": 2349680,
  "type": "Feature",
  "properties": {
    "tgn:hierarchy":[
        "tgn:2349680",
        "tgn:1000001",
        "tgn:2001775",
        "tgn:7012149",
        "tgn:7007713",
        "tgn:7029392"
    ],
    "tgn:id":2349680,
    "tgn:name":"Gilleys Grove",
    "tgn:placetype":[
        "aat:300132451"
    ]
},
  "bbox": [],
  "geometry": {"coordinates":[-96.5333,44.45],"type":"Point"}
}