{
  "id": 7149658,
  "type": "Feature",
  "properties": {
    "tgn:hierarchy":[
        "tgn:7149658",
        "tgn:7003669",
        "tgn:1000003",
        "tgn:7000084",
        "tgn:7029392"
    ],
    "tgn:id":7149658,
    "tgn:name":"Krebs",
    "tgn:placetype":[
        "aat:300008347"
    ]
},
  "bbox": [],
  "geometry": {"coordinates":[9.983333,47.533333],"type":"Point"}
}