{
  "id": 2272906,
  "type": "Feature",
  "properties": {
    "tgn:hierarchy":[
        "tgn:2272906",
        "tgn:1000001",
        "tgn:2000323",
        "tgn:7012149",
        "tgn:7007248",
        "tgn:7029392"
    ],
    "tgn:id":2272906,
    "tgn:name":"Cutoff Branch",
    "tgn:placetype":[
        "aat:300008699"
    ]
},
  "bbox": [],
  "geometry": {"coordinates":[-82.6333,30.7167],"type":"Point"}
}