{
  "id": 7293915,
  "type": "Feature",
  "properties": {
    "tgn:hierarchy":[
        "tgn:7293915",
        "tgn:7002844",
        "tgn:7030216",
        "tgn:1000003",
        "tgn:1000095",
        "tgn:7029392"
    ],
    "tgn:id":7293915,
    "tgn:name":"Vila, Barranco de",
    "tgn:placetype":[
        "aat:300008699"
    ]
},
  "bbox": [],
  "geometry": {"coordinates":[0.733333,41.15],"type":"Point"}
}