{
  "id": 2777951,
  "type": "Feature",
  "properties": {
    "tgn:hierarchy":[
        "tgn:2777951",
        "tgn:1000001",
        "tgn:1002340",
        "tgn:7012149",
        "tgn:7007526",
        "tgn:7029392"
    ],
    "tgn:id":2777951,
    "tgn:name":"Winters Mine",
    "tgn:placetype":[
        "aat:300000390"
    ]
},
  "bbox": [],
  "geometry": {"coordinates":[-119.4667,38.8667],"type":"Point"}
}