<<<<<<< HEAD
{
  "id": 2256702,
  "type": "Feature",
  "properties": {
    "tgn:hierarchy":[
        "tgn:2256702",
        "tgn:1000001",
        "tgn:2001432",
        "tgn:7012149",
        "tgn:7007566",
        "tgn:7029392"
    ],
    "tgn:id":2256702,
    "tgn:name":"Corduroy Canyon",
    "tgn:placetype":[
        "aat:300008761"
    ]
},
  "bbox": [],
  "geometry": {"coordinates":[-104.7167,36.9333],"type":"Point"}
}
=======
{"geometry":{"type":"Point","coordinates":[-104.716700,36.933300]},"type":"Feature","properties":{"hierarchy":["tgn:2256702","tgn:1000001","tgn:2001432","tgn:7012149","tgn:7007566","tgn:7029392"],"placetype":["aat:300008761"],"id":2256702,"name:xx":"Corduroy Canyon"}}
>>>>>>> 03f74aca74312dbeaf24d7e61306dd6a786dc3d0
