{
  "id": 2585897,
  "type": "Feature",
  "properties": {
    "tgn:hierarchy":[
        "tgn:2585897",
        "tgn:1000001",
        "tgn:7006451",
        "tgn:7012149",
        "tgn:2000101",
        "tgn:7029392"
    ],
    "tgn:id":2585897,
    "tgn:name":"Piper Springs",
    "tgn:placetype":[
        "aat:300008697"
    ]
},
  "bbox": [],
  "geometry": {"coordinates":[-110.7167,32.9833],"type":"Point"}
}