{
  "id": 7139534,
  "type": "Feature",
  "properties": {
    "tgn:hierarchy":[
        "tgn:7139534",
        "tgn:1000003",
        "tgn:7003689",
        "tgn:7000084",
        "tgn:7029392"
    ],
    "tgn:id":7139534,
    "tgn:name":"Leutenthal",
    "tgn:placetype":[
        "aat:300008347"
    ]
},
  "bbox": [],
  "geometry": {"coordinates":[11.366667,51.05],"type":"Point"}
}