{
  "id": 1139698,
  "type": "Feature",
  "properties": {
    "tgn:hierarchy":[
        "tgn:1139698",
        "tgn:1000004",
        "tgn:7002079",
        "tgn:1000111",
        "tgn:7029392"
    ],
    "tgn:id":1139698,
    "tgn:name":"Taoyuan",
    "tgn:placetype":[
        "aat:300008347"
    ]
},
  "bbox": [],
  "geometry": {"coordinates":[111.3333,28.7667],"type":"Point"}
}