{
  "id": 2713095,
  "type": "Feature",
  "properties": {
    "tgn:hierarchy":[
        "tgn:2713095",
        "tgn:1000001",
        "tgn:2001938",
        "tgn:7012149",
        "tgn:7007826",
        "tgn:7029392"
    ],
    "tgn:id":2713095,
    "tgn:name":"Taylor Mountain",
    "tgn:placetype":[
        "aat:300008798"
    ]
},
  "bbox": [],
  "geometry": {"coordinates":[-99.5167,29.7167],"type":"Point"}
}