{
  "id": 2075839,
  "type": "Feature",
  "properties": {
    "tgn:hierarchy":[
        "tgn:2075839",
        "tgn:1000001",
        "tgn:7012149",
        "tgn:2001555",
        "tgn:7007709",
        "tgn:7029392"
    ],
    "tgn:id":2075839,
    "tgn:name":"Nebo",
    "tgn:placetype":[
        "aat:300008347",
        "aat:300387210"
    ]
},
  "bbox": [],
  "geometry": {"coordinates":[-80.65,36.2167],"type":"Point"}
}