{
  "id": 7311152,
  "type": "Feature",
  "properties": {
    "tgn:hierarchy":[
        "tgn:7311152",
        "tgn:1001702",
        "tgn:1000049",
        "tgn:1000002",
        "tgn:7029392"
    ],
    "tgn:id":7311152,
    "tgn:name":"Tenedero Montes",
    "tgn:placetype":[
        "aat:300386968"
    ]
},
  "bbox": [],
  "geometry": {"coordinates":[-72.866667,-51.966667],"type":"Point"}
}