{
  "id": 2471999,
  "type": "Feature",
  "properties": {
    "tgn:hierarchy":[
        "tgn:2471999",
        "tgn:1000001",
        "tgn:7012149",
        "tgn:1002676",
        "tgn:7007240",
        "tgn:7029392"
    ],
    "tgn:id":2471999,
    "tgn:name":"Lostmans Creek",
    "tgn:placetype":[
        "aat:300008706"
    ]
},
  "bbox": [],
  "geometry": {"coordinates":[-80.9667,25.5833],"type":"Point"}
}