{
  "id": 7089056,
  "type": "Feature",
  "properties": {
    "tgn:hierarchy":[
        "tgn:7089056",
        "tgn:7000096",
        "tgn:1000003",
        "tgn:7000084",
        "tgn:7029392"
    ],
    "tgn:id":7089056,
    "tgn:name":"Wagenitzer Wiesen",
    "tgn:placetype":[
        "aat:300386990"
    ]
},
  "bbox": [],
  "geometry": {"coordinates":[12.716667,52.716667],"type":"Point"}
}