{
  "id": 2117329,
  "type": "Feature",
  "properties": {
    "tgn:hierarchy":[
        "tgn:2117329",
        "tgn:1000001",
        "tgn:7012149",
        "tgn:2002269",
        "tgn:7013961",
        "tgn:7029392"
    ],
    "tgn:id":2117329,
    "tgn:name":"Bakerton",
    "tgn:placetype":[
        "aat:300008347"
    ]
},
  "bbox": [],
  "geometry": {"coordinates":[-77.75,39.35],"type":"Point"}
}