<<<<<<< HEAD
{
  "id": 7175221,
  "type": "Feature",
  "properties": {
    "tgn:hierarchy":[
        "tgn:7175221",
        "tgn:1000003",
        "tgn:7003685",
        "tgn:7000084",
        "tgn:7029392"
    ],
    "tgn:id":7175221,
    "tgn:name":"Gro\u00dffriesen",
    "tgn:placetype":[
        "aat:300008347"
    ]
},
  "bbox": [],
  "geometry": {"coordinates":[12.2,50.483333],"type":"Point"}
}
=======
{"geometry":{"type":"Point","coordinates":[12.200000,50.483333]},"type":"Feature","properties":{"hierarchy":["tgn:7175221","tgn:1000003","tgn:7003685","tgn:7000084","tgn:7029392"],"placetype":["aat:300008347"],"id":7175221,"name:xx":"Gro\u00dffriesen"}}
>>>>>>> 03f74aca74312dbeaf24d7e61306dd6a786dc3d0
