{
  "id": 2147374,
  "type": "Feature",
  "properties": {
    "tgn:hierarchy":[
        "tgn:2147374",
        "tgn:1000001",
        "tgn:7012149",
        "tgn:2001502",
        "tgn:7007709",
        "tgn:7029392"
    ],
    "tgn:id":2147374,
    "tgn:name":"Barbecue Creek",
    "tgn:placetype":[
        "aat:300008706"
    ]
},
  "bbox": [],
  "geometry": {"coordinates":[-79.0667,35.2667],"type":"Point"}
}