{
  "id": 1047299,
  "type": "Feature",
  "properties": {
    "tgn:hierarchy":[
        "tgn:1047299",
        "tgn:1001641",
        "tgn:1000003",
        "tgn:7003121",
        "tgn:1000080",
        "tgn:7029392"
    ],
    "tgn:id":1047299,
    "tgn:name":"Vallermosa",
    "tgn:placetype":[
        "aat:300008347"
    ]
},
  "bbox": [],
  "geometry": {"coordinates":[8.795556,39.363889],"type":"Point"}
}