<<<<<<< HEAD
{
  "id": 2406295,
  "type": "Feature",
  "properties": {
    "tgn:hierarchy":[
        "tgn:2406295",
        "tgn:1000001",
        "tgn:7012149",
        "tgn:2002299",
        "tgn:7013961",
        "tgn:7029392"
    ],
    "tgn:id":2406295,
    "tgn:name":"Humpy Branch",
    "tgn:placetype":[
        "aat:300008699"
    ]
},
  "bbox": [],
  "geometry": {"coordinates":[-82.3833,38.0167],"type":"Point"}
}
=======
{"geometry":{"type":"Point","coordinates":[-82.383300,38.016700]},"type":"Feature","properties":{"hierarchy":["tgn:2406295","tgn:1000001","tgn:7012149","tgn:2002299","tgn:7013961","tgn:7029392"],"placetype":["aat:300008699"],"id":2406295,"name:xx":"Humpy Branch"}}
>>>>>>> 03f74aca74312dbeaf24d7e61306dd6a786dc3d0
