<<<<<<< HEAD
{
  "id": 7059583,
  "type": "Feature",
  "properties": {
    "tgn:hierarchy":[
        "tgn:7059583",
        "tgn:1000003",
        "tgn:7003676",
        "tgn:7000084",
        "tgn:7029392"
    ],
    "tgn:id":7059583,
    "tgn:name":"Ahlshausen",
    "tgn:placetype":[
        "aat:300008347"
    ]
},
  "bbox": [],
  "geometry": {"coordinates":[9.966667,51.8],"type":"Point"}
}
=======
{"geometry":{"type":"Point","coordinates":[9.966667,51.800000]},"type":"Feature","properties":{"hierarchy":["tgn:7059583","tgn:1000003","tgn:7003676","tgn:7000084","tgn:7029392"],"placetype":["aat:300008347"],"id":7059583,"name:xx":"Ahlshausen"}}
>>>>>>> 03f74aca74312dbeaf24d7e61306dd6a786dc3d0
