{
  "id": 2760345,
  "type": "Feature",
  "properties": {
    "tgn:hierarchy":[
        "tgn:2760345",
        "tgn:1000001",
        "tgn:7012149",
        "tgn:7007923",
        "tgn:7029392"
    ],
    "tgn:id":2760345,
    "tgn:name":"West Fork Sheep Creek",
    "tgn:placetype":[
        "aat:300008706"
    ]
},
  "bbox": [],
  "geometry": {"coordinates":[-108.6833,43.5833],"type":"Point"}
}