<<<<<<< HEAD
{
  "id": 2760345,
  "type": "Feature",
  "properties": {
    "tgn:hierarchy":[
        "tgn:2760345",
        "tgn:1000001",
        "tgn:7012149",
        "tgn:7007923",
        "tgn:7029392"
    ],
    "tgn:id":2760345,
    "tgn:name":"West Fork Sheep Creek",
    "tgn:placetype":[
        "aat:300008706"
    ]
},
  "bbox": [],
  "geometry": {"coordinates":[-108.6833,43.5833],"type":"Point"}
}
=======
{"geometry":{"type":"Point","coordinates":[-108.683300,43.583300]},"type":"Feature","properties":{"hierarchy":["tgn:2760345","tgn:1000001","tgn:7012149","tgn:7007923","tgn:7029392"],"placetype":["aat:300008706"],"id":2760345,"name:xx":"West Fork Sheep Creek"}}
>>>>>>> 03f74aca74312dbeaf24d7e61306dd6a786dc3d0
