{
  "id": 2735700,
  "type": "Feature",
  "properties": {
    "tgn:hierarchy":[
        "tgn:2735700",
        "tgn:1000001",
        "tgn:7012149",
        "tgn:1002793",
        "tgn:7007240",
        "tgn:7029392"
    ],
    "tgn:id":2735700,
    "tgn:name":"Twin Islands",
    "tgn:placetype":[
        "aat:300386853"
    ]
},
  "bbox": [],
  "geometry": {"coordinates":[-81.5333,28.0833],"type":"Point"}
}