{
  "id": 7585971,
  "type": "Feature",
  "properties": {
    "tgn:hierarchy":[
        "tgn:7585971",
        "tgn:1000004",
        "tgn:7000198",
        "tgn:7000799",
        "tgn:7029392"
    ],
    "tgn:id":7585971,
    "tgn:name:en":"Chak Giripur",
    "tgn:placetype":[
        "aat:300008347"
    ]
},
  "bbox": [],
  "geometry": {"coordinates":[74.213889,34.461111],"type":"Point"}
}