{
  "id": 2559483,
  "type": "Feature",
  "properties": {
    "tgn:hierarchy":[
        "tgn:2559483",
        "tgn:1000001",
        "tgn:7012149",
        "tgn:2001190",
        "tgn:7007523",
        "tgn:7029392"
    ],
    "tgn:id":2559483,
    "tgn:name":"Onondaga Cave",
    "tgn:placetype":[
        "aat:300008746"
    ]
},
  "bbox": [],
  "geometry": {"coordinates":[-91.2167,38.05],"type":"Point"}
}