{
  "id": 7365434,
  "type": "Feature",
  "properties": {
    "tgn:hierarchy":[
        "tgn:7365434",
        "tgn:7005581",
        "tgn:1000001",
        "tgn:7005560",
        "tgn:7029392"
    ],
    "tgn:id":7365434,
    "tgn:name":"El Rayo",
    "tgn:placetype":[
        "aat:300008347"
    ]
},
  "bbox": [],
  "geometry": {"coordinates":[-107.15,28.716667],"type":"Point"}
}