{
  "id": 2783164,
  "type": "Feature",
  "properties": {
    "tgn:hierarchy":[
        "tgn:2783164",
        "tgn:1000001",
        "tgn:7012149",
        "tgn:1002564",
        "tgn:7007710",
        "tgn:7029392"
    ],
    "tgn:id":2783164,
    "tgn:name":"Wright Hill",
    "tgn:placetype":[
        "aat:300008798"
    ]
},
  "bbox": [],
  "geometry": {"coordinates":[-75.75,41.5667],"type":"Point"}
}