{
  "id": 2012798,
  "type": "Feature",
  "properties": {
    "tgn:hierarchy":[
        "tgn:2012798",
        "tgn:1000001",
        "tgn:7012149",
        "tgn:7007157",
        "tgn:1002608",
        "tgn:7029392"
    ],
    "tgn:id":2012798,
    "tgn:name":"Monterey Park",
    "tgn:placetype":[
        "aat:300008347",
        "aat:300008389"
    ]
},
  "bbox": [],
  "geometry": {"coordinates":[-118.1167,34.05],"type":"Point"}
}