{
  "id": 7508547,
  "type": "Feature",
  "properties": {
    "tgn:hierarchy":[
        "tgn:7508547",
        "tgn:1009227",
        "tgn:1000226",
        "tgn:7016822",
        "tgn:1000006",
        "tgn:7029392"
    ],
    "tgn:id":7508547,
    "tgn:name:en":"Otara",
    "tgn:placetype":[
        "aat:300008347"
    ]
},
  "bbox": [],
  "geometry": {"coordinates":[168.883333,-46.633333],"type":"Point"}
}