{
  "id": 7304348,
  "type": "Feature",
  "properties": {
    "tgn:hierarchy":[
        "tgn:7304348",
        "tgn:7002824",
        "tgn:1000003",
        "tgn:7002786",
        "tgn:1000095",
        "tgn:7029392"
    ],
    "tgn:id":7304348,
    "tgn:name":"Llagosteira, Playa de",
    "tgn:placetype":[
        "aat:300008816"
    ]
},
  "bbox": [],
  "geometry": {"coordinates":[-9.25,42.916667],"type":"Point"}
}