{
  "id": 2442750,
  "type": "Feature",
  "properties": {
    "tgn:hierarchy":[
        "tgn:2442750",
        "tgn:7006450",
        "tgn:2000069",
        "tgn:1000001",
        "tgn:7012149",
        "tgn:7029392"
    ],
    "tgn:id":2442750,
    "tgn:name":"Kukaktlim Lake",
    "tgn:placetype":[
        "aat:300008680"
    ]
},
  "bbox": [],
  "geometry": {"coordinates":[-160.4667,59.3333],"type":"Point"}
}