{
  "id": 2077022,
  "type": "Feature",
  "properties": {
    "tgn:hierarchy":[
        "tgn:2077022",
        "tgn:1000001",
        "tgn:2001479",
        "tgn:7012149",
        "tgn:7007709",
        "tgn:7029392"
    ],
    "tgn:id":2077022,
    "tgn:name":"Valley Hills Mall",
    "tgn:placetype":[
        "aat:300247594"
    ]
},
  "bbox": [],
  "geometry": {"coordinates":[-81.3333,35.7167],"type":"Point"}
}