{
  "id": 1061826,
  "type": "Feature",
  "properties": {
    "tgn:hierarchy":[
        "tgn:1061826",
        "tgn:7002829",
        "tgn:1000003",
        "tgn:7002786",
        "tgn:1000095",
        "tgn:7029392"
    ],
    "tgn:id":1061826,
    "tgn:name":"Becerre\u00e1",
    "tgn:placetype":[
        "aat:300008347"
    ]
},
  "bbox": [],
  "geometry": {"coordinates":[-7.166667,42.85],"type":"Point"}
}