{
  "id": 7423898,
  "type": "Feature",
  "properties": {
    "tgn:hierarchy":[
        "tgn:7423898",
        "tgn:1000001",
        "tgn:7005601",
        "tgn:7005560",
        "tgn:7029392"
    ],
    "tgn:id":7423898,
    "tgn:name":"San Agust\u00edn",
    "tgn:placetype":[
        "aat:300008347"
    ]
},
  "bbox": [],
  "geometry": {"coordinates":[-101.783333,22.45],"type":"Point"}
}