{
  "id": 1102517,
  "type": "Feature",
  "properties": {
    "tgn:hierarchy":[
        "tgn:1102517",
        "tgn:1007657",
        "tgn:1002534",
        "tgn:1000001",
        "tgn:7012149",
        "tgn:7007249",
        "tgn:7029392"
    ],
    "tgn:id":1102517,
    "tgn:name":"Waimea Canyon State Park",
    "tgn:placetype":[
        "aat:300008192"
    ]
},
  "bbox": [],
  "geometry": {"coordinates":[-159.65,22.05],"type":"Point"}
}