{
  "id": 7505095,
  "type": "Feature",
  "properties": {
    "tgn:hierarchy":[
        "tgn:7505095",
        "tgn:7016670",
        "tgn:1008380",
        "tgn:1000226",
        "tgn:1000006",
        "tgn:7029392"
    ],
    "tgn:id":7505095,
    "tgn:name:en":"Hut Cove",
    "tgn:placetype":[
        "aat:300132317"
    ]
},
  "bbox": [],
  "geometry": {"coordinates":[178.808333,-49.667222],"type":"Point"}
}