{
  "id": 2112333,
  "type": "Feature",
  "properties": {
    "tgn:hierarchy":[
        "tgn:2112333",
        "tgn:1000001",
        "tgn:7012149",
        "tgn:2002193",
        "tgn:7007919",
        "tgn:7029392"
    ],
    "tgn:id":2112333,
    "tgn:name":"Howellsville",
    "tgn:placetype":[
        "aat:300008347",
        "aat:300387210"
    ]
},
  "bbox": [],
  "geometry": {"coordinates":[-78.0667,38.9667],"type":"Point"}
}