{
  "id": 2249876,
  "type": "Feature",
  "properties": {
    "tgn:hierarchy":[
        "tgn:2249876",
        "tgn:1000001",
        "tgn:2000668",
        "tgn:7012149",
        "tgn:7007254",
        "tgn:7029392"
    ],
    "tgn:id":2249876,
    "tgn:name":"Collett Creek",
    "tgn:placetype":[
        "aat:300008706"
    ]
},
  "bbox": [],
  "geometry": {"coordinates":[-96.7333,38.4667],"type":"Point"}
}