{
  "id": 2748416,
  "type": "Feature",
  "properties": {
    "tgn:hierarchy":[
        "tgn:2748416",
        "tgn:1000001",
        "tgn:2002256",
        "tgn:7012149",
        "tgn:7013961",
        "tgn:7029392"
    ],
    "tgn:id":2748416,
    "tgn:name":"Walker Fork",
    "tgn:placetype":[
        "aat:300008699"
    ]
},
  "bbox": [],
  "geometry": {"coordinates":[-80.7333,38.8167],"type":"Point"}
}