{
  "id": 7517558,
  "type": "Feature",
  "properties": {
    "tgn:hierarchy":[
        "tgn:7517558",
        "tgn:1009227",
        "tgn:7001866",
        "tgn:1000226",
        "tgn:1000006",
        "tgn:7029392"
    ],
    "tgn:id":7517558,
    "tgn:name:en":"Malthus",
    "tgn:placetype":[
        "aat:300008798"
    ]
},
  "bbox": [],
  "geometry": {"coordinates":[170.583333,-43.433333],"type":"Point"}
}