{
  "id": 1007531,
  "type": "Feature",
  "properties": {
    "tgn:hierarchy":[
        "tgn:1007531",
        "tgn:1002338",
        "tgn:1000001",
        "tgn:7012149",
        "tgn:7007516",
        "tgn:7029392"
    ],
    "tgn:id":1007531,
    "tgn:name":"James Island",
    "tgn:placetype":[
        "aat:300008791"
    ]
},
  "bbox": [],
  "geometry": {"coordinates":[-76.3333,38.5167],"type":"Point"}
}