<<<<<<< HEAD
{
  "id": 7024918,
  "type": "Feature",
  "properties": {
    "tgn:hierarchy":[
        "tgn:7024918",
        "tgn:7002445",
        "tgn:7008103",
        "tgn:1000003",
        "tgn:7008591",
        "tgn:7029392"
    ],
    "tgn:id":7024918,
    "tgn:name":"Ivel",
    "tgn:placetype":[
        "aat:300008707"
    ]
},
  "bbox": [],
  "geometry": {"coordinates":[-0.3,52.1667],"type":"Point"}
}
=======
{"geometry":{"type":"Point","coordinates":[-0.300000,52.166700]},"type":"Feature","properties":{"hierarchy":["tgn:7024918","tgn:7002445","tgn:7008103","tgn:1000003","tgn:7008591","tgn:7029392"],"placetype":["aat:300008707"],"id":7024918,"name:xx":"Ivel"}}
>>>>>>> 03f74aca74312dbeaf24d7e61306dd6a786dc3d0
