{
  "id": 7512155,
  "type": "Feature",
  "properties": {
    "tgn:hierarchy":[
        "tgn:7512155",
        "tgn:1009227",
        "tgn:1000226",
        "tgn:1000006",
        "tgn:7016850",
        "tgn:7029392"
    ],
    "tgn:id":7512155,
    "tgn:name:en":"Jellicoe Ridge",
    "tgn:placetype":[
        "aat:300266640"
    ]
},
  "bbox": [],
  "geometry": {"coordinates":[171.483333,-42.95],"type":"Point"}
}