<<<<<<< HEAD
{
  "id": 2259106,
  "type": "Feature",
  "properties": {
    "tgn:hierarchy":[
        "tgn:2259106",
        "tgn:1000001",
        "tgn:7012149",
        "tgn:2001999",
        "tgn:7007826",
        "tgn:7029392"
    ],
    "tgn:id":2259106,
    "tgn:name":"Cottonwood Draw",
    "tgn:placetype":[
        "aat:300008761"
    ]
},
  "bbox": [],
  "geometry": {"coordinates":[-102.6333,35.9333],"type":"Point"}
}
=======
{"geometry":{"type":"Point","coordinates":[-102.633300,35.933300]},"type":"Feature","properties":{"hierarchy":["tgn:2259106","tgn:1000001","tgn:7012149","tgn:2001999","tgn:7007826","tgn:7029392"],"placetype":["aat:300008761"],"id":2259106,"name:xx":"Cottonwood Draw"}}
>>>>>>> 03f74aca74312dbeaf24d7e61306dd6a786dc3d0
