<<<<<<< HEAD
{
  "id": 2769065,
  "type": "Feature",
  "properties": {
    "tgn:hierarchy":[
        "tgn:2769065",
        "tgn:1000001",
        "tgn:7012149",
        "tgn:1003017",
        "tgn:7007710",
        "tgn:7029392"
    ],
    "tgn:id":2769065,
    "tgn:name":"Whitten Hollow",
    "tgn:placetype":[
        "aat:300008761"
    ]
},
  "bbox": [],
  "geometry": {"coordinates":[-79.6333,40.5167],"type":"Point"}
}
=======
{"geometry":{"type":"Point","coordinates":[-79.633300,40.516700]},"type":"Feature","properties":{"hierarchy":["tgn:2769065","tgn:1000001","tgn:7012149","tgn:1003017","tgn:7007710","tgn:7029392"],"placetype":["aat:300008761"],"id":2769065,"name:xx":"Whitten Hollow"}}
>>>>>>> 03f74aca74312dbeaf24d7e61306dd6a786dc3d0
