{
  "id": 2336001,
  "type": "Feature",
  "properties": {
    "tgn:hierarchy":[
        "tgn:2336001",
        "tgn:1000001",
        "tgn:7012149",
        "tgn:2002299",
        "tgn:7013961",
        "tgn:7029392"
    ],
    "tgn:id":2336001,
    "tgn:name":"Foster Branch",
    "tgn:placetype":[
        "aat:300008699"
    ]
},
  "bbox": [],
  "geometry": {"coordinates":[-82.5333,38.15],"type":"Point"}
}