{
  "id": 2678488,
  "type": "Feature",
  "properties": {
    "tgn:hierarchy":[
        "tgn:2678488",
        "tgn:1000001",
        "tgn:7012149",
        "tgn:2000476",
        "tgn:7007250",
        "tgn:7029392"
    ],
    "tgn:id":2678488,
    "tgn:name":"South Fork Cottonwood Creek",
    "tgn:placetype":[
        "aat:300008706"
    ]
},
  "bbox": [],
  "geometry": {"coordinates":[-114.95,45.2333],"type":"Point"}
}