{
  "id": 7506594,
  "type": "Feature",
  "properties": {
    "tgn:hierarchy":[
        "tgn:7506594",
        "tgn:1008380",
        "tgn:1000226",
        "tgn:7000512",
        "tgn:1000006",
        "tgn:7029392"
    ],
    "tgn:id":7506594,
    "tgn:name:en":"Roberts",
    "tgn:placetype":[
        "aat:300008777"
    ]
},
  "bbox": [],
  "geometry": {"coordinates":[174.85,-41.166667],"type":"Point"}
}