<<<<<<< HEAD
{
  "id": 7058027,
  "type": "Feature",
  "properties": {
    "tgn:hierarchy":[
        "tgn:7058027",
        "tgn:7003137",
        "tgn:1000003",
        "tgn:7003080",
        "tgn:1000080",
        "tgn:7029392"
    ],
    "tgn:id":7058027,
    "tgn:name":"Arafranca",
    "tgn:placetype":[
        "aat:300008347"
    ]
},
  "bbox": [],
  "geometry": {"coordinates":[13.3,42.616667],"type":"Point"}
}
=======
{"geometry":{"type":"Point","coordinates":[13.300000,42.616667]},"type":"Feature","properties":{"hierarchy":["tgn:7058027","tgn:7003137","tgn:1000003","tgn:7003080","tgn:1000080","tgn:7029392"],"placetype":["aat:300008347"],"id":7058027,"name:xx":"Arafranca"}}
>>>>>>> 03f74aca74312dbeaf24d7e61306dd6a786dc3d0
