{
  "id": 7363133,
  "type": "Feature",
  "properties": {
    "tgn:hierarchy":[
        "tgn:7363133",
        "tgn:1000001",
        "tgn:7005597",
        "tgn:7005560",
        "tgn:7029392"
    ],
    "tgn:id":7363133,
    "tgn:name":"El Aquichal",
    "tgn:placetype":[
        "aat:300008347"
    ]
},
  "bbox": [],
  "geometry": {"coordinates":[-99.066667,23.183333],"type":"Point"}
}