{
  "id": 7170953,
  "type": "Feature",
  "properties": {
    "tgn:hierarchy":[
        "tgn:7170953",
        "tgn:1000003",
        "tgn:7003676",
        "tgn:7000084",
        "tgn:7029392"
    ],
    "tgn:id":7170953,
    "tgn:name":"Herzog Juliush\u00fctte",
    "tgn:placetype":[
        "aat:300008347"
    ]
},
  "bbox": [],
  "geometry": {"coordinates":[10.383333,51.933333],"type":"Point"}
}