{
  "id": 1025505,
  "type": "Feature",
  "properties": {
    "tgn:hierarchy":[
        "tgn:1025505",
        "tgn:7003028",
        "tgn:1000003",
        "tgn:1000062",
        "tgn:7029392"
    ],
    "tgn:id":1025505,
    "tgn:name":"Eisenerz",
    "tgn:placetype":[
        "aat:300008347"
    ]
},
  "bbox": [],
  "geometry": {"coordinates":[14.8833,47.55],"type":"Point"}
}