<<<<<<< HEAD
{
  "id": 2335956,
  "type": "Feature",
  "properties": {
    "tgn:hierarchy":[
        "tgn:2335956",
        "tgn:1000001",
        "tgn:7012149",
        "tgn:1002298",
        "tgn:7007157",
        "tgn:7029392"
    ],
    "tgn:id":2335956,
    "tgn:name":"Fossil Ridge",
    "tgn:placetype":[
        "aat:300266640"
    ]
},
  "bbox": [],
  "geometry": {"coordinates":[-121.9167,37.8333],"type":"Point"}
}
=======
{"geometry":{"type":"Point","coordinates":[-121.916700,37.833300]},"type":"Feature","properties":{"hierarchy":["tgn:2335956","tgn:1000001","tgn:7012149","tgn:1002298","tgn:7007157","tgn:7029392"],"placetype":["aat:300266640"],"id":2335956,"name:xx":"Fossil Ridge"}}
>>>>>>> 03f74aca74312dbeaf24d7e61306dd6a786dc3d0
