{
  "id": 2335956,
  "type": "Feature",
  "properties": {
    "tgn:hierarchy":[
        "tgn:2335956",
        "tgn:1000001",
        "tgn:7012149",
        "tgn:1002298",
        "tgn:7007157",
        "tgn:7029392"
    ],
    "tgn:id":2335956,
    "tgn:name":"Fossil Ridge",
    "tgn:placetype":[
        "aat:300266640"
    ]
},
  "bbox": [],
  "geometry": {"coordinates":[-121.9167,37.8333],"type":"Point"}
}