{
  "id": 7035577,
  "type": "Feature",
  "properties": {
    "tgn:hierarchy":[
        "tgn:7035577",
        "tgn:7002991",
        "tgn:1000003",
        "tgn:7002997",
        "tgn:1000080",
        "tgn:7029392"
    ],
    "tgn:id":7035577,
    "tgn:name":"L\u00e8vego",
    "tgn:placetype":[
        "aat:300008347"
    ]
},
  "bbox": [],
  "geometry": {"coordinates":[12.252778,46.153333],"type":"Point"}
}