{
  "id": 7347649,
  "type": "Feature",
  "properties": {
    "tgn:hierarchy":[
        "tgn:7347649",
        "tgn:7002759",
        "tgn:7008909",
        "tgn:1000003",
        "tgn:1000095",
        "tgn:7029392"
    ],
    "tgn:id":7347649,
    "tgn:name":"Ballobar",
    "tgn:placetype":[
        "aat:300008347"
    ]
},
  "bbox": [],
  "geometry": {"coordinates":[0.191287,41.620443],"type":"Point"}
}