{
  "id": 2457038,
  "type": "Feature",
  "properties": {
    "tgn:hierarchy":[
        "tgn:2457038",
        "tgn:1000001",
        "tgn:7012149",
        "tgn:2002340",
        "tgn:7007922",
        "tgn:7029392"
    ],
    "tgn:id":2457038,
    "tgn:name":"Little LaCrosse River",
    "tgn:placetype":[
        "aat:300008707"
    ]
},
  "bbox": [],
  "geometry": {"coordinates":[-90.7833,43.7333],"type":"Point"}
}