{
  "id": 7436658,
  "type": "Feature",
  "properties": {
    "tgn:hierarchy":[
        "tgn:7436658",
        "tgn:7005581",
        "tgn:1000001",
        "tgn:7005560",
        "tgn:7029392"
    ],
    "tgn:id":7436658,
    "tgn:name":"Tarjea, Pico",
    "tgn:placetype":[
        "aat:300008795"
    ]
},
  "bbox": [],
  "geometry": {"coordinates":[-106.083333,28.433333],"type":"Point"}
}