<<<<<<< HEAD
{
  "id": 2336335,
  "type": "Feature",
  "properties": {
    "tgn:hierarchy":[
        "tgn:2336335",
        "tgn:1000001",
        "tgn:7013942",
        "tgn:7012149",
        "tgn:7007517",
        "tgn:7029392"
    ],
    "tgn:id":2336335,
    "tgn:name":"Foundry Brook",
    "tgn:placetype":[
        "aat:300008699"
    ]
},
  "bbox": [],
  "geometry": {"coordinates":[-72.7167,42.6667],"type":"Point"}
}
=======
{"geometry":{"type":"Point","coordinates":[-72.716700,42.666700]},"type":"Feature","properties":{"hierarchy":["tgn:2336335","tgn:1000001","tgn:7013942","tgn:7012149","tgn:7007517","tgn:7029392"],"placetype":["aat:300008699"],"id":2336335,"name:xx":"Foundry Brook"}}
>>>>>>> 03f74aca74312dbeaf24d7e61306dd6a786dc3d0
