{
  "id": 2591108,
  "type": "Feature",
  "properties": {
    "tgn:hierarchy":[
        "tgn:2591108",
        "tgn:1000001",
        "tgn:1002174",
        "tgn:7012149",
        "tgn:7007826",
        "tgn:7029392"
    ],
    "tgn:id":2591108,
    "tgn:name":"Polk, Lake",
    "tgn:placetype":[
        "aat:300006191"
    ]
},
  "bbox": [],
  "geometry": {"coordinates":[-97.3667,31.0833],"type":"Point"}
}