{
  "id": 7302906,
  "type": "Feature",
  "properties": {
    "tgn:hierarchy":[
        "tgn:7302906",
        "tgn:7002810",
        "tgn:7001158",
        "tgn:1000003",
        "tgn:1000095",
        "tgn:7029392"
    ],
    "tgn:id":7302906,
    "tgn:name":"Olmos de la Picaza",
    "tgn:placetype":[
        "aat:300008347"
    ]
},
  "bbox": [],
  "geometry": {"coordinates":[-4.033333,42.483333],"type":"Point"}
}