{
  "id": 7527814,
  "type": "Feature",
  "properties": {
    "tgn:hierarchy":[
        "tgn:7527814",
        "tgn:7001242",
        "tgn:7016833",
        "tgn:1001418",
        "tgn:7029392"
    ],
    "tgn:id":7527814,
    "tgn:name:en":"S\u012bd\u012b Zuraybah",
    "tgn:placetype":[
        "aat:300005926"
    ]
},
  "bbox": [],
  "geometry": {"coordinates":[29.414764,30.721483],"type":"Point"}
}