{
  "id": 7125744,
  "type": "Feature",
  "properties": {
    "tgn:hierarchy":[
        "tgn:7125744",
        "tgn:1000003",
        "tgn:7003688",
        "tgn:7000084",
        "tgn:7029392"
    ],
    "tgn:id":7125744,
    "tgn:name":"Nordhackstedt",
    "tgn:placetype":[
        "aat:300008347"
    ]
},
  "bbox": [],
  "geometry": {"coordinates":[9.166667,54.733333],"type":"Point"}
}