{
  "id": 2450499,
  "type": "Feature",
  "properties": {
    "tgn:hierarchy":[
        "tgn:2450499",
        "tgn:1000001",
        "tgn:7012149",
        "tgn:7014371",
        "tgn:7007248",
        "tgn:7029392"
    ],
    "tgn:id":2450499,
    "tgn:name":"Linton Lake",
    "tgn:placetype":[
        "aat:300008905"
    ]
},
  "bbox": [],
  "geometry": {"coordinates":[-83.75,30.6667],"type":"Point"}
}