{
  "id": 7110851,
  "type": "Feature",
  "properties": {
    "tgn:hierarchy":[
        "tgn:7110851",
        "tgn:1000003",
        "tgn:7003676",
        "tgn:7000084",
        "tgn:7029392"
    ],
    "tgn:id":7110851,
    "tgn:name":"P\u00fcggen",
    "tgn:placetype":[
        "aat:300008347"
    ]
},
  "bbox": [],
  "geometry": {"coordinates":[11.016667,52.95],"type":"Point"}
}