{
  "id": 7178822,
  "type": "Feature",
  "properties": {
    "tgn:hierarchy":[
        "tgn:7178822",
        "tgn:7003669",
        "tgn:1000003",
        "tgn:7000084",
        "tgn:7029392"
    ],
    "tgn:id":7178822,
    "tgn:name":"Guggenhierl",
    "tgn:placetype":[
        "aat:300000206"
    ]
},
  "bbox": [],
  "geometry": {"coordinates":[10.366667,47.933333],"type":"Point"}
}