{
  "id": 7416934,
  "type": "Feature",
  "properties": {
    "tgn:hierarchy":[
        "tgn:7416934",
        "tgn:7005584",
        "tgn:1000001",
        "tgn:7005560",
        "tgn:7029392"
    ],
    "tgn:id":7416934,
    "tgn:name":"Hermosillo",
    "tgn:placetype":[
        "aat:300008347"
    ]
},
  "bbox": [],
  "geometry": {"coordinates":[-101.529722,20.575556],"type":"Point"}
}