{
  "id": 1025880,
  "type": "Feature",
  "properties": {
    "tgn:hierarchy":[
        "tgn:1025880",
        "tgn:7003027",
        "tgn:1000003",
        "tgn:1000062",
        "tgn:7029392"
    ],
    "tgn:id":1025880,
    "tgn:name":"Neukirchen",
    "tgn:placetype":[
        "aat:300008347"
    ]
},
  "bbox": [],
  "geometry": {"coordinates":[12.2833,47.2667],"type":"Point"}
}