{
  "id": 2394948,
  "type": "Feature",
  "properties": {
    "tgn:hierarchy":[
        "tgn:2394948",
        "tgn:1000001",
        "tgn:7012149",
        "tgn:7007256",
        "tgn:7029392"
    ],
    "tgn:id":2394948,
    "tgn:name":"Holdens Creek",
    "tgn:placetype":[
        "aat:300008706"
    ]
},
  "bbox": [],
  "geometry": {"coordinates":[-89.9333,30.6667],"type":"Point"}
}