{
  "id": 2657646,
  "type": "Feature",
  "properties": {
    "tgn:hierarchy":[
        "tgn:2657646",
        "tgn:1000001",
        "tgn:7016172",
        "tgn:7012149",
        "tgn:2000155",
        "tgn:7029392"
    ],
    "tgn:id":2657646,
    "tgn:name":"Sheldon Branch",
    "tgn:placetype":[
        "aat:300008699"
    ]
},
  "bbox": [],
  "geometry": {"coordinates":[-93.0833,35.9667],"type":"Point"}
}