{
  "id": 7223371,
  "type": "Feature",
  "properties": {
    "tgn:hierarchy":[
        "tgn:7223371",
        "tgn:7002735",
        "tgn:7017076",
        "tgn:1000003",
        "tgn:1000074",
        "tgn:7029392"
    ],
    "tgn:id":7223371,
    "tgn:name":"Platan\u00e1kion",
    "tgn:placetype":[
        "aat:300008347"
    ]
},
  "bbox": [],
  "geometry": {"coordinates":[22.666667,37.166667],"type":"Point"}
}