{
  "id": 7018877,
  "type": "Feature",
  "properties": {
    "tgn:hierarchy":[
        "tgn:7018877",
        "tgn:1000004",
        "tgn:7002088",
        "tgn:1000111",
        "tgn:7029392"
    ],
    "tgn:id":7018877,
    "tgn:name":"Nan Hulsan Hu",
    "tgn:placetype":[
        "aat:300008680"
    ]
},
  "bbox": [],
  "geometry": {"coordinates":[96.3333,36.6667],"type":"Point"}
}