{
  "id": 2110001,
  "type": "Feature",
  "properties": {
    "tgn:hierarchy":[
        "tgn:2110001",
        "tgn:1000001",
        "tgn:1002389",
        "tgn:7012149",
        "tgn:7007828",
        "tgn:7029392"
    ],
    "tgn:id":2110001,
    "tgn:name":"Shawville",
    "tgn:placetype":[
        "aat:300008347",
        "aat:300387210"
    ]
},
  "bbox": [],
  "geometry": {"coordinates":[-72.95,44.9167],"type":"Point"}
}