{
  "id": 2291422,
  "type": "Feature",
  "properties": {
    "tgn:hierarchy":[
        "tgn:2291422",
        "tgn:1000001",
        "tgn:7012149",
        "tgn:2002088",
        "tgn:7007826",
        "tgn:7029392"
    ],
    "tgn:id":2291422,
    "tgn:name":"Dolan Springs",
    "tgn:placetype":[
        "aat:300008697"
    ]
},
  "bbox": [],
  "geometry": {"coordinates":[-100.9833,29.8833],"type":"Point"}
}