{
  "id": 7030486,
  "type": "Feature",
  "properties": {
    "tgn:hierarchy":[
        "tgn:7030486",
        "tgn:7003818",
        "tgn:1000003",
        "tgn:1000090",
        "tgn:7029392"
    ],
    "tgn:id":7030486,
    "tgn:name:pt":"Grij\u00f3",
    "tgn:placetype":[
        "aat:300007783"
    ]
},
  "bbox": [],
  "geometry": {"coordinates":[-6.987,41.511],"type":"Point"}
}