{
  "id": 1031064,
  "type": "Feature",
  "properties": {
    "tgn:hierarchy":[
        "tgn:1031064",
        "tgn:7002445",
        "tgn:1000003",
        "tgn:7011961",
        "tgn:7008591",
        "tgn:7029392"
    ],
    "tgn:id":1031064,
    "tgn:name":"West Moors",
    "tgn:placetype":[
        "aat:300008347"
    ]
},
  "bbox": [],
  "geometry": {"coordinates":[-1.9167,50.8167],"type":"Point"}
}