{
  "id": 7406280,
  "type": "Feature",
  "properties": {
    "tgn:hierarchy":[
        "tgn:7406280",
        "tgn:1000001",
        "tgn:1001906",
        "tgn:7005560",
        "tgn:7029392"
    ],
    "tgn:id":7406280,
    "tgn:name":"El Verde",
    "tgn:placetype":[
        "aat:300008347"
    ]
},
  "bbox": [],
  "geometry": {"coordinates":[-104.458333,22.291667],"type":"Point"}
}