{
  "id": 2733248,
  "type": "Feature",
  "properties": {
    "tgn:hierarchy":[
        "tgn:2733248",
        "tgn:1000001",
        "tgn:7012149",
        "tgn:2001556",
        "tgn:7007709",
        "tgn:7029392"
    ],
    "tgn:id":2733248,
    "tgn:name":"Turkey Ridge",
    "tgn:placetype":[
        "aat:300266640"
    ]
},
  "bbox": [],
  "geometry": {"coordinates":[-82.3167,35.85],"type":"Point"}
}