{
  "id": 2158092,
  "type": "Feature",
  "properties": {
    "tgn:hierarchy":[
        "tgn:2158092",
        "tgn:1000001",
        "tgn:7012149",
        "tgn:2001125",
        "tgn:7007522",
        "tgn:7029392"
    ],
    "tgn:id":2158092,
    "tgn:name":"Beaver Pond",
    "tgn:placetype":[
        "aat:300008680"
    ]
},
  "bbox": [],
  "geometry": {"coordinates":[-89.5833,32.65],"type":"Point"}
}