<<<<<<< HEAD
{
  "id": 2158092,
  "type": "Feature",
  "properties": {
    "tgn:hierarchy":[
        "tgn:2158092",
        "tgn:1000001",
        "tgn:7012149",
        "tgn:2001125",
        "tgn:7007522",
        "tgn:7029392"
    ],
    "tgn:id":2158092,
    "tgn:name":"Beaver Pond",
    "tgn:placetype":[
        "aat:300008680"
    ]
},
  "bbox": [],
  "geometry": {"coordinates":[-89.5833,32.65],"type":"Point"}
}
=======
{"geometry":{"type":"Point","coordinates":[-89.583300,32.650000]},"type":"Feature","properties":{"hierarchy":["tgn:2158092","tgn:1000001","tgn:7012149","tgn:2001125","tgn:7007522","tgn:7029392"],"placetype":["aat:300008680"],"id":2158092,"name:xx":"Beaver Pond"}}
>>>>>>> 03f74aca74312dbeaf24d7e61306dd6a786dc3d0
