{
  "id": 7099815,
  "type": "Feature",
  "properties": {
    "tgn:hierarchy":[
        "tgn:7099815",
        "tgn:7003669",
        "tgn:1000003",
        "tgn:7000084",
        "tgn:7029392"
    ],
    "tgn:id":7099815,
    "tgn:name":"Sollern",
    "tgn:placetype":[
        "aat:300008347"
    ]
},
  "bbox": [],
  "geometry": {"coordinates":[11.85,48.466667],"type":"Point"}
}