{
  "id": 7577669,
  "type": "Feature",
  "properties": {
    "tgn:hierarchy":[
        "tgn:7577669",
        "tgn:1000004",
        "tgn:7000198",
        "tgn:7001797",
        "tgn:7029392"
    ],
    "tgn:id":7577669,
    "tgn:name:en":"Karumattampatti",
    "tgn:placetype":[
        "aat:300008347"
    ]
},
  "bbox": [],
  "geometry": {"coordinates":[77.183333,11.116667],"type":"Point"}
}