{
  "id": 7391411,
  "type": "Feature",
  "properties": {
    "tgn:hierarchy":[
        "tgn:7391411",
        "tgn:7005583",
        "tgn:1000001",
        "tgn:7005560",
        "tgn:7029392"
    ],
    "tgn:id":7391411,
    "tgn:name":"Rancho La Sabina",
    "tgn:placetype":[
        "aat:300008347"
    ]
},
  "bbox": [],
  "geometry": {"coordinates":[-104.85,25.916667],"type":"Point"}
}