{
  "id": 7013721,
  "type": "Feature",
  "properties": {
    "tgn:hierarchy":[
        "tgn:7013721",
        "tgn:7002659",
        "tgn:1000001",
        "tgn:7012149",
        "tgn:2000061",
        "tgn:7029392"
    ],
    "tgn:id":7013721,
    "tgn:name":"Horseshoe Bend National Military Park",
    "tgn:placetype":[
        "aat:300000835",
        "aat:300386978"
    ]
},
  "bbox": [],
  "geometry": {"coordinates":[-85.7333,32.9667],"type":"Point"}
}