<<<<<<< HEAD
{
  "id": 7353898,
  "type": "Feature",
  "properties": {
    "tgn:hierarchy":[
        "tgn:7353898",
        "tgn:1000001",
        "tgn:1001960",
        "tgn:7005560",
        "tgn:7029392"
    ],
    "tgn:id":7353898,
    "tgn:name":"Campo Uno Ciento Tres",
    "tgn:placetype":[
        "aat:300008347"
    ]
},
  "bbox": [],
  "geometry": {"coordinates":[-110.15,27.35],"type":"Point"}
}
=======
{"geometry":{"type":"Point","coordinates":[-110.150000,27.350000]},"type":"Feature","properties":{"hierarchy":["tgn:7353898","tgn:1000001","tgn:1001960","tgn:7005560","tgn:7029392"],"placetype":["aat:300008347"],"id":7353898,"name:xx":"Campo Uno Ciento Tres"}}
>>>>>>> 03f74aca74312dbeaf24d7e61306dd6a786dc3d0
