{
  "id": 2754186,
  "type": "Feature",
  "properties": {
    "tgn:hierarchy":[
        "tgn:2754186",
        "tgn:1000001",
        "tgn:7012149",
        "tgn:7007157",
        "tgn:1002675",
        "tgn:7029392"
    ],
    "tgn:id":2754186,
    "tgn:name":"Watterson Troughs",
    "tgn:placetype":[
        "aat:300008697"
    ]
},
  "bbox": [],
  "geometry": {"coordinates":[-118.65,37.6667],"type":"Point"}
}