<<<<<<< HEAD
{
  "id": 2330291,
  "type": "Feature",
  "properties": {
    "tgn:hierarchy":[
        "tgn:2330291",
        "tgn:1000001",
        "tgn:7012149",
        "tgn:7007525",
        "tgn:7029392"
    ],
    "tgn:id":2330291,
    "tgn:name":"Flash Creek",
    "tgn:placetype":[
        "aat:300008706"
    ]
},
  "bbox": [],
  "geometry": {"coordinates":[-98.7333,40.9167],"type":"Point"}
}
=======
{"geometry":{"type":"Point","coordinates":[-98.733300,40.916700]},"type":"Feature","properties":{"hierarchy":["tgn:2330291","tgn:1000001","tgn:7012149","tgn:7007525","tgn:7029392"],"placetype":["aat:300008706"],"id":2330291,"name:xx":"Flash Creek"}}
>>>>>>> 03f74aca74312dbeaf24d7e61306dd6a786dc3d0
