{
  "id": 2330291,
  "type": "Feature",
  "properties": {
    "tgn:hierarchy":[
        "tgn:2330291",
        "tgn:1000001",
        "tgn:7012149",
        "tgn:7007525",
        "tgn:7029392"
    ],
    "tgn:id":2330291,
    "tgn:name":"Flash Creek",
    "tgn:placetype":[
        "aat:300008706"
    ]
},
  "bbox": [],
  "geometry": {"coordinates":[-98.7333,40.9167],"type":"Point"}
}