{
  "id": 2374078,
  "type": "Feature",
  "properties": {
    "tgn:hierarchy":[
        "tgn:2374078",
        "tgn:1000001",
        "tgn:1002452",
        "tgn:7012149",
        "tgn:7007240",
        "tgn:7029392"
    ],
    "tgn:id":2374078,
    "tgn:name":"Hammock Pond",
    "tgn:placetype":[
        "aat:300008905"
    ]
},
  "bbox": [],
  "geometry": {"coordinates":[-81.8667,27.5667],"type":"Point"}
}