{
  "id": 7259169,
  "type": "Feature",
  "properties": {
    "tgn:hierarchy":[
        "tgn:7259169",
        "tgn:7003457",
        "tgn:1000003",
        "tgn:1000063",
        "tgn:7018236",
        "tgn:7029392"
    ],
    "tgn:id":7259169,
    "tgn:name":"Vurste",
    "tgn:placetype":[
        "aat:300008347"
    ]
},
  "bbox": [],
  "geometry": {"coordinates":[3.683065,50.943208],"type":"Point"}
}