{
  "id": 2193336,
  "type": "Feature",
  "properties": {
    "tgn:hierarchy":[
        "tgn:2193336",
        "tgn:1000001",
        "tgn:7006451",
        "tgn:7012149",
        "tgn:2000103",
        "tgn:7029392"
    ],
    "tgn:id":2193336,
    "tgn:name":"Breezy Pines",
    "tgn:placetype":[
        "aat:300008347"
    ]
},
  "bbox": [],
  "geometry": {"coordinates":[-112.35,34.4333],"type":"Point"}
}