{
  "id": 2271731,
  "type": "Feature",
  "properties": {
    "tgn:hierarchy":[
        "tgn:2271731",
        "tgn:1000001",
        "tgn:7012149",
        "tgn:2000348",
        "tgn:7007248",
        "tgn:7029392"
    ],
    "tgn:id":2271731,
    "tgn:name":"Cunningham",
    "tgn:placetype":[
        "aat:300008347"
    ]
},
  "bbox": [],
  "geometry": {"coordinates":[-85.25,34.15],"type":"Point"}
}