{
  "id": 2144804,
  "type": "Feature",
  "properties": {
    "tgn:hierarchy":[
        "tgn:2144804",
        "tgn:1000001",
        "tgn:7012149",
        "tgn:2002009",
        "tgn:7007826",
        "tgn:7029392"
    ],
    "tgn:id":2144804,
    "tgn:name":"Bald Hill",
    "tgn:placetype":[
        "aat:300008798"
    ]
},
  "bbox": [],
  "geometry": {"coordinates":[-93.9833,30.8333],"type":"Point"}
}