{
  "id": 2781077,
  "type": "Feature",
  "properties": {
    "tgn:hierarchy":[
        "tgn:2781077",
        "tgn:1000001",
        "tgn:7012149",
        "tgn:7014185",
        "tgn:7007710",
        "tgn:7029392"
    ],
    "tgn:id":2781077,
    "tgn:name":"Woodcock Hill",
    "tgn:placetype":[
        "aat:300008798"
    ]
},
  "bbox": [],
  "geometry": {"coordinates":[-79.4667,39.7667],"type":"Point"}
}