{
  "id": 2467482,
  "type": "Feature",
  "properties": {
    "tgn:hierarchy":[
        "tgn:2467482",
        "tgn:1000001",
        "tgn:2000265",
        "tgn:7012149",
        "tgn:7007240",
        "tgn:7029392"
    ],
    "tgn:id":2467482,
    "tgn:name":"Long Hollow",
    "tgn:placetype":[
        "aat:300008761"
    ]
},
  "bbox": [],
  "geometry": {"coordinates":[-87.55,30.9667],"type":"Point"}
}