{
  "id": 7565400,
  "type": "Feature",
  "properties": {
    "tgn:hierarchy":[
        "tgn:7565400",
        "tgn:1000004",
        "tgn:7000198",
        "tgn:7016722",
        "tgn:7029392"
    ],
    "tgn:id":7565400,
    "tgn:name:en":"T\u0101jpur Bidh\u016bna",
    "tgn:placetype":[
        "aat:300008347"
    ]
},
  "bbox": [],
  "geometry": {"coordinates":[79.538408,26.816323],"type":"Point"}
}