{
  "id": 7545943,
  "type": "Feature",
  "properties": {
    "tgn:hierarchy":[
        "tgn:7545943",
        "tgn:1000004",
        "tgn:7000198",
        "tgn:7000799",
        "tgn:7029392"
    ],
    "tgn:id":7545943,
    "tgn:name:en":"Bhud",
    "tgn:placetype":[
        "aat:300008347"
    ]
},
  "bbox": [],
  "geometry": {"coordinates":[75.815629,32.607044],"type":"Point"}
}