{
  "id": 2726669,
  "type": "Feature",
  "properties": {
    "tgn:hierarchy":[
        "tgn:2726669",
        "tgn:1000001",
        "tgn:2000920",
        "tgn:7012149",
        "tgn:7007515",
        "tgn:7029392"
    ],
    "tgn:id":2726669,
    "tgn:name":"Town Landing",
    "tgn:placetype":[
        "aat:300008347"
    ]
},
  "bbox": [],
  "geometry": {"coordinates":[-70.3333,43.5333],"type":"Point"}
}