{
  "id": 2674927,
  "type": "Feature",
  "properties": {
    "tgn:hierarchy":[
        "tgn:2674927",
        "tgn:1000001",
        "tgn:2001705",
        "tgn:7012149",
        "tgn:7007708",
        "tgn:7029392"
    ],
    "tgn:id":2674927,
    "tgn:name":"Soda Creek",
    "tgn:placetype":[
        "aat:300008706"
    ]
},
  "bbox": [],
  "geometry": {"coordinates":[-121.6667,44.05],"type":"Point"}
}