{
  "id": 2243309,
  "type": "Feature",
  "properties": {
    "tgn:hierarchy":[
        "tgn:2243309",
        "tgn:1000001",
        "tgn:7012149",
        "tgn:2000841",
        "tgn:7007255",
        "tgn:7029392"
    ],
    "tgn:id":2243309,
    "tgn:name":"Clear Spring Ridge",
    "tgn:placetype":[
        "aat:300266640"
    ]
},
  "bbox": [],
  "geometry": {"coordinates":[-85.05,37.05],"type":"Point"}
}