<<<<<<< HEAD
{
  "id": 2154589,
  "type": "Feature",
  "properties": {
    "tgn:hierarchy":[
        "tgn:2154589",
        "tgn:2002137",
        "tgn:1000001",
        "tgn:7012149",
        "tgn:7007919",
        "tgn:7029392"
    ],
    "tgn:id":2154589,
    "tgn:name":"Bear Den Mountain",
    "tgn:placetype":[
        "aat:300008798"
    ]
},
  "bbox": [],
  "geometry": {"coordinates":[-78.5833,38.0167],"type":"Point"}
}
=======
{"geometry":{"type":"Point","coordinates":[-78.583300,38.016700]},"type":"Feature","properties":{"hierarchy":["tgn:2154589","tgn:2002137","tgn:1000001","tgn:7012149","tgn:7007919","tgn:7029392"],"placetype":["aat:300008798"],"id":2154589,"name:xx":"Bear Den Mountain"}}
>>>>>>> 03f74aca74312dbeaf24d7e61306dd6a786dc3d0
