{
  "id": 1036159,
  "type": "Feature",
  "properties": {
    "tgn:hierarchy":[
        "tgn:1036159",
        "tgn:1000003",
        "tgn:7002883",
        "tgn:1000070",
        "tgn:7029392"
    ],
    "tgn:id":1036159,
    "tgn:name":"Villeneuve-la-Garonne",
    "tgn:placetype":[
        "aat:300008347"
    ]
},
  "bbox": [],
  "geometry": {"coordinates":[2.3167,48.9333],"type":"Point"}
}