{
  "id": 2325568,
  "type": "Feature",
  "properties": {
    "tgn:hierarchy":[
        "tgn:2325568",
        "tgn:1000001",
        "tgn:7012149",
        "tgn:2001707",
        "tgn:7007708",
        "tgn:7029392"
    ],
    "tgn:id":2325568,
    "tgn:name":"Fichter Canyon",
    "tgn:placetype":[
        "aat:300008761"
    ]
},
  "bbox": [],
  "geometry": {"coordinates":[-119.85,45.1167],"type":"Point"}
}