{
  "id": 7114937,
  "type": "Feature",
  "properties": {
    "tgn:hierarchy":[
        "tgn:7114937",
        "tgn:1000003",
        "tgn:7003687",
        "tgn:7000084",
        "tgn:7029392"
    ],
    "tgn:id":7114937,
    "tgn:name":"Ochsenkopf",
    "tgn:placetype":[
        "aat:300008777"
    ]
},
  "bbox": [],
  "geometry": {"coordinates":[10.766667,51.666667],"type":"Point"}
}