{
  "id": 2182712,
  "type": "Feature",
  "properties": {
    "tgn:hierarchy":[
        "tgn:2182712",
        "tgn:1000001",
        "tgn:7012149",
        "tgn:7007255",
        "tgn:7029392"
    ],
    "tgn:id":2182712,
    "tgn:name":"Blue Spring Creek",
    "tgn:placetype":[
        "aat:300008706"
    ]
},
  "bbox": [],
  "geometry": {"coordinates":[-85.7167,37.0167],"type":"Point"}
}