{
  "id": 7104137,
  "type": "Feature",
  "properties": {
    "tgn:hierarchy":[
        "tgn:7104137",
        "tgn:1000003",
        "tgn:7003677",
        "tgn:7000084",
        "tgn:7029392"
    ],
    "tgn:id":7104137,
    "tgn:name":"Schiren-Berg",
    "tgn:placetype":[
        "aat:300008777"
    ]
},
  "bbox": [],
  "geometry": {"coordinates":[8.916667,51.75],"type":"Point"}
}