{
  "id": 7564006,
  "type": "Feature",
  "properties": {
    "tgn:hierarchy":[
        "tgn:7564006",
        "tgn:1000004",
        "tgn:7000198",
        "tgn:1001894",
        "tgn:7029392"
    ],
    "tgn:id":7564006,
    "tgn:name:en":"Pacher",
    "tgn:placetype":[
        "aat:300008347"
    ]
},
  "bbox": [],
  "geometry": {"coordinates":[79.328999,24.909662],"type":"Point"}
}