{
  "id": 2749345,
  "type": "Feature",
  "properties": {
    "tgn:hierarchy":[
        "tgn:2749345",
        "tgn:2001422",
        "tgn:1000001",
        "tgn:7012149",
        "tgn:7007564",
        "tgn:7029392"
    ],
    "tgn:id":2749345,
    "tgn:name":"Wallis Brook",
    "tgn:placetype":[
        "aat:300008699"
    ]
},
  "bbox": [],
  "geometry": {"coordinates":[-71.5333,43.5167],"type":"Point"}
}