{
  "id": 2135791,
  "type": "Feature",
  "properties": {
    "tgn:hierarchy":[
        "tgn:2135791",
        "tgn:1000001",
        "tgn:7006451",
        "tgn:7012149",
        "tgn:2000097",
        "tgn:7029392"
    ],
    "tgn:id":2135791,
    "tgn:name":"Apollo Mobile Home Park",
    "tgn:placetype":[
        "aat:300008347"
    ]
},
  "bbox": [],
  "geometry": {"coordinates":[-112.2667,33.5667],"type":"Point"}
}