<<<<<<< HEAD
{
  "id": 7351778,
  "type": "Feature",
  "properties": {
    "tgn:hierarchy":[
        "tgn:7351778",
        "tgn:1000001",
        "tgn:7005589",
        "tgn:7005560",
        "tgn:7029392"
    ],
    "tgn:id":7351778,
    "tgn:name":"Arroyo Colorado",
    "tgn:placetype":[
        "aat:300008347"
    ]
},
  "bbox": [],
  "geometry": {"coordinates":[-100.133333,24.7],"type":"Point"}
}
=======
{"geometry":{"type":"Point","coordinates":[-100.133333,24.700000]},"type":"Feature","properties":{"hierarchy":["tgn:7351778","tgn:1000001","tgn:7005589","tgn:7005560","tgn:7029392"],"placetype":["aat:300008347"],"id":7351778,"name:xx":"Arroyo Colorado"}}
>>>>>>> 03f74aca74312dbeaf24d7e61306dd6a786dc3d0
