{
  "id": 7352518,
  "type": "Feature",
  "properties": {
    "tgn:hierarchy":[
        "tgn:7352518",
        "tgn:1000001",
        "tgn:1001960",
        "tgn:7005560",
        "tgn:7029392"
    ],
    "tgn:id":7352518,
    "tgn:name":"Bascobampo",
    "tgn:placetype":[
        "aat:300008347"
    ]
},
  "bbox": [],
  "geometry": {"coordinates":[-109.65,26.983333],"type":"Point"}
}