{
  "id": 2589378,
  "type": "Feature",
  "properties": {
    "tgn:hierarchy":[
        "tgn:2589378",
        "tgn:1000001",
        "tgn:7012149",
        "tgn:2001108",
        "tgn:7007522",
        "tgn:7029392"
    ],
    "tgn:id":2589378,
    "tgn:name":"Point Clear Island",
    "tgn:placetype":[
        "aat:300008791"
    ]
},
  "bbox": [],
  "geometry": {"coordinates":[-89.4333,30.2167],"type":"Point"}
}