<<<<<<< HEAD
{
  "id": 7244978,
  "type": "Feature",
  "properties": {
    "tgn:hierarchy":[
        "tgn:7244978",
        "tgn:7003466",
        "tgn:1000003",
        "tgn:1000063",
        "tgn:4012014",
        "tgn:7029392"
    ],
    "tgn:id":7244978,
    "tgn:name":"Ave",
    "tgn:placetype":[
        "aat:300008699"
    ]
},
  "bbox": [],
  "geometry": {"coordinates":[5.183333,50.133333],"type":"Point"}
}
=======
{"geometry":{"type":"Point","coordinates":[5.183333,50.133333]},"type":"Feature","properties":{"hierarchy":["tgn:7244978","tgn:7003466","tgn:1000003","tgn:1000063","tgn:4012014","tgn:7029392"],"placetype":["aat:300008699"],"id":7244978,"name:xx":"Ave"}}
>>>>>>> 03f74aca74312dbeaf24d7e61306dd6a786dc3d0
