{
  "id": 2266119,
  "type": "Feature",
  "properties": {
    "tgn:hierarchy":[
        "tgn:2266119",
        "tgn:1000001",
        "tgn:7012149",
        "tgn:7007825",
        "tgn:7029392"
    ],
    "tgn:id":2266119,
    "tgn:name":"Crawford Hollow",
    "tgn:placetype":[
        "aat:300008761"
    ]
},
  "bbox": [],
  "geometry": {"coordinates":[-87.4833,35.9833],"type":"Point"}
}