{
  "id": 7511288,
  "type": "Feature",
  "properties": {
    "tgn:hierarchy":[
        "tgn:7511288",
        "tgn:1009227",
        "tgn:7001866",
        "tgn:1000226",
        "tgn:1000006",
        "tgn:7029392"
    ],
    "tgn:id":7511288,
    "tgn:name:en":"Trinity Hill",
    "tgn:placetype":[
        "aat:300008795"
    ]
},
  "bbox": [],
  "geometry": {"coordinates":[171.183333,-43.633333],"type":"Point"}
}