{
  "id": 2096597,
  "type": "Feature",
  "properties": {
    "tgn:hierarchy":[
        "tgn:2096597",
        "tgn:1000001",
        "tgn:2001744",
        "tgn:7012149",
        "tgn:7007712",
        "tgn:7029392"
    ],
    "tgn:id":2096597,
    "tgn:name":"Rockton",
    "tgn:placetype":[
        "aat:300008347",
        "aat:300387210"
    ]
},
  "bbox": [],
  "geometry": {"coordinates":[-81.0833,34.3333],"type":"Point"}
}