<<<<<<< HEAD
{
  "id": 2153682,
  "type": "Feature",
  "properties": {
    "tgn:hierarchy":[
        "tgn:2153682",
        "tgn:1000001",
        "tgn:7012149",
        "tgn:2001856",
        "tgn:7007825",
        "tgn:7029392"
    ],
    "tgn:id":2153682,
    "tgn:name":"Bear Branch",
    "tgn:placetype":[
        "aat:300008699"
    ]
},
  "bbox": [],
  "geometry": {"coordinates":[-88.1833,35.4],"type":"Point"}
}
=======
{"geometry":{"type":"Point","coordinates":[-88.183300,35.400000]},"type":"Feature","properties":{"hierarchy":["tgn:2153682","tgn:1000001","tgn:7012149","tgn:2001856","tgn:7007825","tgn:7029392"],"placetype":["aat:300008699"],"id":2153682,"name:xx":"Bear Branch"}}
>>>>>>> 03f74aca74312dbeaf24d7e61306dd6a786dc3d0
