{
  "id": 1071587,
  "type": "Feature",
  "properties": {
    "tgn:hierarchy":[
        "tgn:1071587",
        "tgn:1000004",
        "tgn:7002082",
        "tgn:1000111",
        "tgn:7029392"
    ],
    "tgn:id":1071587,
    "tgn:name":"Shengang",
    "tgn:placetype":[
        "aat:300008347"
    ]
},
  "bbox": [],
  "geometry": {"coordinates":[116.3333,27.3333],"type":"Point"}
}