{
  "id": 7370663,
  "type": "Feature",
  "properties": {
    "tgn:hierarchy":[
        "tgn:7370663",
        "tgn:1000001",
        "tgn:7005592",
        "tgn:7005560",
        "tgn:7029392"
    ],
    "tgn:id":7370663,
    "tgn:name":"Huipiltepec",
    "tgn:placetype":[
        "aat:300008347"
    ]
},
  "bbox": [],
  "geometry": {"coordinates":[-97.116667,20.15],"type":"Point"}
}