{
  "id": 7514908,
  "type": "Feature",
  "properties": {
    "tgn:hierarchy":[
        "tgn:7514908",
        "tgn:1009227",
        "tgn:7001866",
        "tgn:1000226",
        "tgn:1000006",
        "tgn:7029392"
    ],
    "tgn:id":7514908,
    "tgn:name:en":"Constance, Lake",
    "tgn:placetype":[
        "aat:300008680"
    ]
},
  "bbox": [],
  "geometry": {"coordinates":[172.666667,-42.083333],"type":"Point"}
}