<<<<<<< HEAD
{
  "id": 7024210,
  "type": "Feature",
  "properties": {
    "tgn:hierarchy":[
        "tgn:7024210",
        "tgn:7000490",
        "tgn:1001991",
        "tgn:1000006",
        "tgn:7029392"
    ],
    "tgn:id":7024210,
    "tgn:name":"Cato Reef",
    "tgn:placetype":[
        "aat:300008808"
    ]
},
  "bbox": [],
  "geometry": {"coordinates":[155.5333,-23.25],"type":"Point"}
}
=======
{"geometry":{"type":"Point","coordinates":[155.533300,-23.250000]},"type":"Feature","properties":{"hierarchy":["tgn:7024210","tgn:7000490","tgn:1001991","tgn:1000006","tgn:7029392"],"placetype":["aat:300008808"],"id":7024210,"name:xx":"Cato Reef"}}
>>>>>>> 03f74aca74312dbeaf24d7e61306dd6a786dc3d0
