{
  "id": 2463955,
  "type": "Feature",
  "properties": {
    "tgn:hierarchy":[
        "tgn:2463955",
        "tgn:1000001",
        "tgn:7012149",
        "tgn:2001300",
        "tgn:7007524",
        "tgn:7029392"
    ],
    "tgn:id":2463955,
    "tgn:name":"Lockwood Lake",
    "tgn:placetype":[
        "aat:300008680"
    ]
},
  "bbox": [],
  "geometry": {"coordinates":[-114.4167,46.3167],"type":"Point"}
}