<<<<<<< HEAD
{
  "id": 2763485,
  "type": "Feature",
  "properties": {
    "tgn:hierarchy":[
        "tgn:2763485",
        "tgn:1000001",
        "tgn:7012149",
        "tgn:2002350",
        "tgn:7007922",
        "tgn:7029392"
    ],
    "tgn:id":2763485,
    "tgn:name":"Weyerhauser",
    "tgn:placetype":[
        "aat:300008347"
    ]
},
  "bbox": [],
  "geometry": {"coordinates":[-91.4,45.4167],"type":"Point"}
}
=======
{"geometry":{"type":"Point","coordinates":[-91.400000,45.416700]},"type":"Feature","properties":{"hierarchy":["tgn:2763485","tgn:1000001","tgn:7012149","tgn:2002350","tgn:7007922","tgn:7029392"],"placetype":["aat:300008347"],"id":2763485,"name:xx":"Weyerhauser"}}
>>>>>>> 03f74aca74312dbeaf24d7e61306dd6a786dc3d0
