{
  "id": 1043279,
  "type": "Feature",
  "properties": {
    "tgn:hierarchy":[
        "tgn:1043279",
        "tgn:7015163",
        "tgn:1000003",
        "tgn:7003121",
        "tgn:1000080",
        "tgn:7029392"
    ],
    "tgn:id":1043279,
    "tgn:name":"Miniera dell'Argentiera",
    "tgn:placetype":[
        "aat:300008347"
    ]
},
  "bbox": [],
  "geometry": {"coordinates":[8.149,40.74],"type":"Point"}
}