<<<<<<< HEAD
{
  "id": 2335295,
  "type": "Feature",
  "properties": {
    "tgn:hierarchy":[
        "tgn:2335295",
        "tgn:2000934",
        "tgn:1000001",
        "tgn:7012149",
        "tgn:7007516",
        "tgn:7029392"
    ],
    "tgn:id":2335295,
    "tgn:name":"Fort Hill",
    "tgn:placetype":[
        "aat:300008798"
    ]
},
  "bbox": [],
  "geometry": {"coordinates":[-78.9,39.5167],"type":"Point"}
}
=======
{"geometry":{"type":"Point","coordinates":[-78.900000,39.516700]},"type":"Feature","properties":{"hierarchy":["tgn:2335295","tgn:2000934","tgn:1000001","tgn:7012149","tgn:7007516","tgn:7029392"],"placetype":["aat:300008798"],"id":2335295,"name:xx":"Fort Hill"}}
>>>>>>> 03f74aca74312dbeaf24d7e61306dd6a786dc3d0
