{
  "id": 7059368,
  "type": "Feature",
  "properties": {
    "tgn:hierarchy":[
        "tgn:7059368",
        "tgn:7003692",
        "tgn:1000003",
        "tgn:7000084",
        "tgn:7029392"
    ],
    "tgn:id":7059368,
    "tgn:name":"Allmersbach am Weinberg",
    "tgn:placetype":[
        "aat:300008347"
    ]
},
  "bbox": [],
  "geometry": {"coordinates":[9.383333,48.983333],"type":"Point"}
}