{
  "id": 7399965,
  "type": "Feature",
  "properties": {
    "tgn:hierarchy":[
        "tgn:7399965",
        "tgn:1000001",
        "tgn:7005593",
        "tgn:7005560",
        "tgn:7029392"
    ],
    "tgn:id":7399965,
    "tgn:name":"El Madro\u00f1o, Cerro",
    "tgn:placetype":[
        "aat:300008795"
    ]
},
  "bbox": [],
  "geometry": {"coordinates":[-99.775,21.333333],"type":"Point"}
}