{
  "id": 7070412,
  "type": "Feature",
  "properties": {
    "tgn:hierarchy":[
        "tgn:7070412",
        "tgn:7003669",
        "tgn:1000003",
        "tgn:7000084",
        "tgn:7029392"
    ],
    "tgn:id":7070412,
    "tgn:name":"Steinbach",
    "tgn:placetype":[
        "aat:300008347"
    ]
},
  "bbox": [],
  "geometry": {"coordinates":[11.75,48.616667],"type":"Point"}
}