{
  "id": 2280467,
  "type": "Feature",
  "properties": {
    "tgn:hierarchy":[
        "tgn:2280467",
        "tgn:1000001",
        "tgn:7012149",
        "tgn:2002363",
        "tgn:7007922",
        "tgn:7029392"
    ],
    "tgn:id":2280467,
    "tgn:name":"Decorah Beach",
    "tgn:placetype":[
        "aat:300008347"
    ]
},
  "bbox": [],
  "geometry": {"coordinates":[-88.4667,43.9167],"type":"Point"}
}