{
  "id": 7507016,
  "type": "Feature",
  "properties": {
    "tgn:hierarchy":[
        "tgn:7507016",
        "tgn:1008380",
        "tgn:7520093",
        "tgn:1000226",
        "tgn:1000006",
        "tgn:7029392"
    ],
    "tgn:id":7507016,
    "tgn:name:en":"Raketapauma",
    "tgn:placetype":[
        "aat:300008347"
    ]
},
  "bbox": [],
  "geometry": {"coordinates":[175.583333,-39.55],"type":"Point"}
}