{
  "id": 2783027,
  "type": "Feature",
  "properties": {
    "tgn:hierarchy":[
        "tgn:2783027",
        "tgn:1000001",
        "tgn:2001009",
        "tgn:7012149",
        "tgn:7007521",
        "tgn:7029392"
    ],
    "tgn:id":2783027,
    "tgn:name":"Wren Lake",
    "tgn:placetype":[
        "aat:300008680"
    ]
},
  "bbox": [],
  "geometry": {"coordinates":[-93.8833,46.8667],"type":"Point"}
}