{
  "id": 2208928,
  "type": "Feature",
  "properties": {
    "tgn:hierarchy":[
        "tgn:2208928",
        "tgn:1000001",
        "tgn:2000922",
        "tgn:7012149",
        "tgn:7007515",
        "tgn:7029392"
    ],
    "tgn:id":2208928,
    "tgn:name":"Burnt Coat Harbor",
    "tgn:placetype":[
        "aat:300132316"
    ]
},
  "bbox": [],
  "geometry": {"coordinates":[-68.4333,44.1333],"type":"Point"}
}