<<<<<<< HEAD
{
  "id": 7174150,
  "type": "Feature",
  "properties": {
    "tgn:hierarchy":[
        "tgn:7174150",
        "tgn:7000096",
        "tgn:1000003",
        "tgn:7000084",
        "tgn:7029392"
    ],
    "tgn:id":7174150,
    "tgn:name":"Gro\u00dfer L\u00fcbbenower See",
    "tgn:placetype":[
        "aat:300008680"
    ]
},
  "bbox": [],
  "geometry": {"coordinates":[13.8,53.45],"type":"Point"}
}
=======
{"geometry":{"type":"Point","coordinates":[13.800000,53.450000]},"type":"Feature","properties":{"hierarchy":["tgn:7174150","tgn:7000096","tgn:1000003","tgn:7000084","tgn:7029392"],"placetype":["aat:300008680"],"id":7174150,"name:xx":"Gro\u00dfer L\u00fcbbenower See"}}
>>>>>>> 03f74aca74312dbeaf24d7e61306dd6a786dc3d0
