{
  "id": 7556448,
  "type": "Feature",
  "properties": {
    "tgn:hierarchy":[
        "tgn:7556448",
        "tgn:1000004",
        "tgn:7000198",
        "tgn:7000799",
        "tgn:7029392"
    ],
    "tgn:id":7556448,
    "tgn:name:en":"Saf\u0101pur",
    "tgn:placetype":[
        "aat:300008347"
    ]
},
  "bbox": [],
  "geometry": {"coordinates":[74.664695,34.259435],"type":"Point"}
}