{
  "id": 7181375,
  "type": "Feature",
  "properties": {
    "tgn:hierarchy":[
        "tgn:7181375",
        "tgn:1000003",
        "tgn:7003677",
        "tgn:7000084",
        "tgn:7029392"
    ],
    "tgn:id":7181375,
    "tgn:name":"Gei\u00dfel",
    "tgn:placetype":[
        "aat:300000206"
    ]
},
  "bbox": [],
  "geometry": {"coordinates":[8.35,51.783333],"type":"Point"}
}