{
  "id": 2131552,
  "type": "Feature",
  "properties": {
    "tgn:hierarchy":[
        "tgn:2131552",
        "tgn:1000001",
        "tgn:7012149",
        "tgn:2002299",
        "tgn:7013961",
        "tgn:7029392"
    ],
    "tgn:id":2131552,
    "tgn:name":"Alum Fork",
    "tgn:placetype":[
        "aat:300008699"
    ]
},
  "bbox": [],
  "geometry": {"coordinates":[-82.2833,38.0667],"type":"Point"}
}