{
  "id": 2439304,
  "type": "Feature",
  "properties": {
    "tgn:hierarchy":[
        "tgn:2439304",
        "tgn:7030516",
        "tgn:7006450",
        "tgn:1000001",
        "tgn:7012149",
        "tgn:7029392"
    ],
    "tgn:id":2439304,
    "tgn:name":"Kirilof Bay",
    "tgn:placetype":[
        "aat:300132316"
    ]
},
  "bbox": [],
  "geometry": {"coordinates":[179.25,51.4167],"type":"Point"}
}