<<<<<<< HEAD
{
  "id": 7247643,
  "type": "Feature",
  "properties": {
    "tgn:hierarchy":[
        "tgn:7247643",
        "tgn:7007877",
        "tgn:1000003",
        "tgn:1000063",
        "tgn:4012014",
        "tgn:7029392"
    ],
    "tgn:id":7247643,
    "tgn:name":"Chauss\u00e9e-Notre-Dame-Louvignies",
    "tgn:placetype":[
        "aat:300008347"
    ]
},
  "bbox": [],
  "geometry": {"coordinates":[3.998771,50.592729],"type":"Point"}
}
=======
{"geometry":{"type":"Point","coordinates":[3.998771,50.592729]},"type":"Feature","properties":{"hierarchy":["tgn:7247643","tgn:7007877","tgn:1000003","tgn:1000063","tgn:4012014","tgn:7029392"],"placetype":["aat:300008347"],"id":7247643,"name:xx":"Chauss\u00e9e-Notre-Dame-Louvignies"}}
>>>>>>> 03f74aca74312dbeaf24d7e61306dd6a786dc3d0
