<<<<<<< HEAD
{
  "id": 2334002,
  "type": "Feature",
  "properties": {
    "tgn:hierarchy":[
        "tgn:2334002",
        "tgn:1000001",
        "tgn:2001794",
        "tgn:7012149",
        "tgn:7007713",
        "tgn:7029392"
    ],
    "tgn:id":2334002,
    "tgn:name":"Ford Lake",
    "tgn:placetype":[
        "aat:300008680"
    ]
},
  "bbox": [],
  "geometry": {"coordinates":[-99.45,45.0333],"type":"Point"}
}
=======
{"geometry":{"type":"Point","coordinates":[-99.450000,45.033300]},"type":"Feature","properties":{"hierarchy":["tgn:2334002","tgn:1000001","tgn:2001794","tgn:7012149","tgn:7007713","tgn:7029392"],"placetype":["aat:300008680"],"id":2334002,"name:xx":"Ford Lake"}}
>>>>>>> 03f74aca74312dbeaf24d7e61306dd6a786dc3d0
