{
  "id": 7431537,
  "type": "Feature",
  "properties": {
    "tgn:hierarchy":[
        "tgn:7431537",
        "tgn:7005586",
        "tgn:1000001",
        "tgn:7005560",
        "tgn:7029392"
    ],
    "tgn:id":7431537,
    "tgn:name":"Amolco,R\u00edo",
    "tgn:placetype":[
        "aat:300008699"
    ]
},
  "bbox": [],
  "geometry": {"coordinates":[-104.25,20.833333],"type":"Point"}
}