{
  "id": 2524487,
  "type": "Feature",
  "properties": {
    "tgn:hierarchy":[
        "tgn:2524487",
        "tgn:7002659",
        "tgn:1000001",
        "tgn:7012149",
        "tgn:2000054",
        "tgn:7029392"
    ],
    "tgn:id":2524487,
    "tgn:name":"Morgans Branch",
    "tgn:placetype":[
        "aat:300008699"
    ]
},
  "bbox": [],
  "geometry": {"coordinates":[-85.9167,31.8333],"type":"Point"}
}