{
  "id": 7051180,
  "type": "Feature",
  "properties": {
    "tgn:hierarchy":[
        "tgn:7051180",
        "tgn:7009084",
        "tgn:7004154",
        "tgn:1000003",
        "tgn:1000080",
        "tgn:7029392"
    ],
    "tgn:id":7051180,
    "tgn:name":"Navelli",
    "tgn:placetype":[
        "aat:300008347"
    ]
},
  "bbox": [],
  "geometry": {"coordinates":[13.733333,42.233333],"type":"Point"}
}