{
  "id": 2371736,
  "type": "Feature",
  "properties": {
    "tgn:hierarchy":[
        "tgn:2371736",
        "tgn:1000001",
        "tgn:7012149",
        "tgn:7007158",
        "tgn:2000254",
        "tgn:7029392"
    ],
    "tgn:id":2371736,
    "tgn:name":"Hale Ponds",
    "tgn:placetype":[
        "aat:300006191"
    ]
},
  "bbox": [],
  "geometry": {"coordinates":[-102.05,39.6333],"type":"Point"}
}