{
  "id": 2663317,
  "type": "Feature",
  "properties": {
    "tgn:hierarchy":[
        "tgn:2663317",
        "tgn:1000001",
        "tgn:7012149",
        "tgn:1002729",
        "tgn:7007710",
        "tgn:7029392"
    ],
    "tgn:id":2663317,
    "tgn:name":"Silver Creek",
    "tgn:placetype":[
        "aat:300008706"
    ]
},
  "bbox": [],
  "geometry": {"coordinates":[-75.2833,40.5667],"type":"Point"}
}