{
  "id": 2710995,
  "type": "Feature",
  "properties": {
    "tgn:hierarchy":[
        "tgn:2710995",
        "tgn:1000001",
        "tgn:7012149",
        "tgn:2001453",
        "tgn:7007566",
        "tgn:7029392"
    ],
    "tgn:id":2710995,
    "tgn:name":"Tank Number 2",
    "tgn:placetype":[
        "aat:300006191"
    ]
},
  "bbox": [],
  "geometry": {"coordinates":[-105.6333,35.15],"type":"Point"}
}