<<<<<<< HEAD
{
  "id": 2769755,
  "type": "Feature",
  "properties": {
    "tgn:hierarchy":[
        "tgn:2769755",
        "tgn:1000001",
        "tgn:7012149",
        "tgn:2000356",
        "tgn:7007248",
        "tgn:7029392"
    ],
    "tgn:id":2769755,
    "tgn:name":"Wight North, Lake",
    "tgn:placetype":[
        "aat:300006191"
    ]
},
  "bbox": [],
  "geometry": {"coordinates":[-84.2167,30.85],"type":"Point"}
}
=======
{"geometry":{"type":"Point","coordinates":[-84.216700,30.850000]},"type":"Feature","properties":{"hierarchy":["tgn:2769755","tgn:1000001","tgn:7012149","tgn:2000356","tgn:7007248","tgn:7029392"],"placetype":["aat:300006191"],"id":2769755,"name:xx":"Wight North, Lake"}}
>>>>>>> 03f74aca74312dbeaf24d7e61306dd6a786dc3d0
