{
  "id": 2602185,
  "type": "Feature",
  "properties": {
    "tgn:hierarchy":[
        "tgn:2602185",
        "tgn:7023902",
        "tgn:1000001",
        "tgn:7012149",
        "tgn:7007249",
        "tgn:7029392"
    ],
    "tgn:id":2602185,
    "tgn:name":"Puu o Mahana",
    "tgn:placetype":[
        "aat:300008798"
    ]
},
  "bbox": [],
  "geometry": {"coordinates":[-155.6333,18.9333],"type":"Point"}
}