{
  "id": 2399955,
  "type": "Feature",
  "properties": {
    "tgn:hierarchy":[
        "tgn:2399955",
        "tgn:1000001",
        "tgn:2001414",
        "tgn:7012149",
        "tgn:7007526",
        "tgn:7029392"
    ],
    "tgn:id":2399955,
    "tgn:name":"Horse Canyon Spring",
    "tgn:placetype":[
        "aat:300008697"
    ]
},
  "bbox": [],
  "geometry": {"coordinates":[-119.3167,41.8167],"type":"Point"}
}