{
  "id": 2262338,
  "type": "Feature",
  "properties": {
    "tgn:hierarchy":[
        "tgn:2262338",
        "tgn:1000001",
        "tgn:2001411",
        "tgn:7012149",
        "tgn:7007526",
        "tgn:7029392"
    ],
    "tgn:id":2262338,
    "tgn:name":"Cow Creek Canyon",
    "tgn:placetype":[
        "aat:300008761"
    ]
},
  "bbox": [],
  "geometry": {"coordinates":[-115.4667,41.8833],"type":"Point"}
}