{
  "id": 7039185,
  "type": "Feature",
  "properties": {
    "tgn:hierarchy":[
        "tgn:7039185",
        "tgn:1001641",
        "tgn:1000003",
        "tgn:7003121",
        "tgn:1000080",
        "tgn:7029392"
    ],
    "tgn:id":7039185,
    "tgn:name":"Spigulu, Riu",
    "tgn:placetype":[
        "aat:300008699"
    ]
},
  "bbox": [],
  "geometry": {"coordinates":[9.383333,39.533333],"type":"Point"}
}