{
  "id": 2136179,
  "type": "Feature",
  "properties": {
    "tgn:hierarchy":[
        "tgn:2136179",
        "tgn:1000001",
        "tgn:7012149",
        "tgn:2001439",
        "tgn:7007566",
        "tgn:7029392"
    ],
    "tgn:id":2136179,
    "tgn:name":"Aragon Hill",
    "tgn:placetype":[
        "aat:300008798"
    ]
},
  "bbox": [],
  "geometry": {"coordinates":[-103.8333,36.1333],"type":"Point"}
}