{
  "id": 2310146,
  "type": "Feature",
  "properties": {
    "tgn:hierarchy":[
        "tgn:2310146",
        "tgn:1000001",
        "tgn:7012149",
        "tgn:2000930",
        "tgn:7007515",
        "tgn:7029392"
    ],
    "tgn:id":2310146,
    "tgn:name":"Eaton Hill",
    "tgn:placetype":[
        "aat:300008798"
    ]
},
  "bbox": [],
  "geometry": {"coordinates":[-69.7667,44.95],"type":"Point"}
}