<<<<<<< HEAD
{
  "id": 2153299,
  "type": "Feature",
  "properties": {
    "tgn:hierarchy":[
        "tgn:2153299",
        "tgn:1000001",
        "tgn:2000921",
        "tgn:7012149",
        "tgn:7007515",
        "tgn:7029392"
    ],
    "tgn:id":2153299,
    "tgn:name":"Bean Brook",
    "tgn:placetype":[
        "aat:300008699"
    ]
},
  "bbox": [],
  "geometry": {"coordinates":[-70.3167,44.85],"type":"Point"}
}
=======
{"geometry":{"type":"Point","coordinates":[-70.316700,44.850000]},"type":"Feature","properties":{"hierarchy":["tgn:2153299","tgn:1000001","tgn:2000921","tgn:7012149","tgn:7007515","tgn:7029392"],"placetype":["aat:300008699"],"id":2153299,"name:xx":"Bean Brook"}}
>>>>>>> 03f74aca74312dbeaf24d7e61306dd6a786dc3d0
