{
  "id": 1025949,
  "type": "Feature",
  "properties": {
    "tgn:hierarchy":[
        "tgn:1025949",
        "tgn:7003028",
        "tgn:1000003",
        "tgn:1000062",
        "tgn:7029392"
    ],
    "tgn:id":1025949,
    "tgn:name":"Piberegg",
    "tgn:placetype":[
        "aat:300008347"
    ]
},
  "bbox": [],
  "geometry": {"coordinates":[15.0833,47.0833],"type":"Point"}
}