{
  "id": 2323649,
  "type": "Feature",
  "properties": {
    "tgn:hierarchy":[
        "tgn:2323649",
        "tgn:1000001",
        "tgn:7012149",
        "tgn:2002054",
        "tgn:7007826",
        "tgn:7029392"
    ],
    "tgn:id":2323649,
    "tgn:name":"Farwell",
    "tgn:placetype":[
        "aat:300008347"
    ]
},
  "bbox": [],
  "geometry": {"coordinates":[-103.25,30.25],"type":"Point"}
}