{
  "id": 1020526,
  "type": "Feature",
  "properties": {
    "tgn:hierarchy":[
        "tgn:1020526",
        "tgn:1001941",
        "tgn:1000047",
        "tgn:7002458",
        "tgn:1000002",
        "tgn:7029392"
    ],
    "tgn:id":1020526,
    "tgn:name":"Agudo",
    "tgn:placetype":[
        "aat:300008347"
    ]
},
  "bbox": [],
  "geometry": {"coordinates":[-53.25,-29.6333],"type":"Point"}
}