{
  "id": 7536710,
  "type": "Feature",
  "properties": {
    "tgn:hierarchy":[
        "tgn:7536710",
        "tgn:7001242",
        "tgn:7016833",
        "tgn:1001113",
        "tgn:7029392"
    ],
    "tgn:id":7536710,
    "tgn:name:en":"Kafr az Zand",
    "tgn:placetype":[
        "aat:300008347"
    ]
},
  "bbox": [],
  "geometry": {"coordinates":[31.483333,30.583333],"type":"Point"}
}