<<<<<<< HEAD
{
  "id": 2408630,
  "type": "Feature",
  "properties": {
    "tgn:hierarchy":[
        "tgn:2408630",
        "tgn:1000001",
        "tgn:2000870",
        "tgn:7012149",
        "tgn:7007256",
        "tgn:7029392"
    ],
    "tgn:id":2408630,
    "tgn:name":"Hyacinth Terrace",
    "tgn:placetype":[
        "aat:300008347"
    ]
},
  "bbox": [],
  "geometry": {"coordinates":[-91.1333,30.4],"type":"Point"}
}
=======
{"geometry":{"type":"Point","coordinates":[-91.133300,30.400000]},"type":"Feature","properties":{"hierarchy":["tgn:2408630","tgn:1000001","tgn:2000870","tgn:7012149","tgn:7007256","tgn:7029392"],"placetype":["aat:300008347"],"id":2408630,"name:xx":"Hyacinth Terrace"}}
>>>>>>> 03f74aca74312dbeaf24d7e61306dd6a786dc3d0
