{
  "id": 2545741,
  "type": "Feature",
  "properties": {
    "tgn:hierarchy":[
        "tgn:2545741",
        "tgn:1000001",
        "tgn:7012149",
        "tgn:2001722",
        "tgn:7007708",
        "tgn:7029392"
    ],
    "tgn:id":2545741,
    "tgn:name":"North Fork Cliff Creek",
    "tgn:placetype":[
        "aat:300008706"
    ]
},
  "bbox": [],
  "geometry": {"coordinates":[-117.15,45.8167],"type":"Point"}
}