{
  "id": 7291778,
  "type": "Feature",
  "properties": {
    "tgn:hierarchy":[
        "tgn:7291778",
        "tgn:1001708",
        "tgn:1000049",
        "tgn:1000002",
        "tgn:7029392"
    ],
    "tgn:id":7291778,
    "tgn:name":"El Hornillo",
    "tgn:placetype":[
        "aat:300008795"
    ]
},
  "bbox": [],
  "geometry": {"coordinates":[-70.633333,-33.05],"type":"Point"}
}