{
  "id": 7019086,
  "type": "Feature",
  "properties": {
    "tgn:hierarchy":[
        "tgn:7019086",
        "tgn:1000001",
        "tgn:7012149",
        "tgn:7007157",
        "tgn:1002608",
        "tgn:7029392"
    ],
    "tgn:id":7019086,
    "tgn:name":"La Ca\u00f1ada Flintridge",
    "tgn:placetype":[
        "aat:300008347"
    ]
},
  "bbox": [],
  "geometry": {"coordinates":[-118.1833,34.1833],"type":"Point"}
}