{
  "id": 7345819,
  "type": "Feature",
  "properties": {
    "tgn:hierarchy":[
        "tgn:7345819",
        "tgn:7002831",
        "tgn:1000003",
        "tgn:7002786",
        "tgn:1000095",
        "tgn:7029392"
    ],
    "tgn:id":7345819,
    "tgn:name":"Barrio",
    "tgn:placetype":[
        "aat:300008347"
    ]
},
  "bbox": [],
  "geometry": {"coordinates":[-6.866667,42.45],"type":"Point"}
}