{
  "id": 2532512,
  "type": "Feature",
  "properties": {
    "tgn:hierarchy":[
        "tgn:2532512",
        "tgn:2000918",
        "tgn:1000001",
        "tgn:7012149",
        "tgn:7007515",
        "tgn:7029392"
    ],
    "tgn:id":2532512,
    "tgn:name":"Murphy Corner",
    "tgn:placetype":[
        "aat:300008347"
    ]
},
  "bbox": [],
  "geometry": {"coordinates":[-70.2333,44.0333],"type":"Point"}
}