<<<<<<< HEAD
{
  "id": 7379686,
  "type": "Feature",
  "properties": {
    "tgn:hierarchy":[
        "tgn:7379686",
        "tgn:1000001",
        "tgn:7005591",
        "tgn:7005560",
        "tgn:7029392"
    ],
    "tgn:id":7379686,
    "tgn:name":"Mart\u00edn Enr\u00edquez",
    "tgn:placetype":[
        "aat:300008347"
    ]
},
  "bbox": [],
  "geometry": {"coordinates":[-96.583333,15.833333],"type":"Point"}
}
=======
{"geometry":{"type":"Point","coordinates":[-96.583333,15.833333]},"type":"Feature","properties":{"hierarchy":["tgn:7379686","tgn:1000001","tgn:7005591","tgn:7005560","tgn:7029392"],"placetype":["aat:300008347"],"id":7379686,"name:xx":"Mart\u00edn Enr\u00edquez"}}
>>>>>>> 03f74aca74312dbeaf24d7e61306dd6a786dc3d0
