{
  "id": 1101204,
  "type": "Feature",
  "properties": {
    "tgn:hierarchy":[
        "tgn:1101204",
        "tgn:1000004",
        "tgn:7000894",
        "tgn:1001032",
        "tgn:1000120",
        "tgn:7029392"
    ],
    "tgn:id":1101204,
    "tgn:name":"Og\u014dchi-dam",
    "tgn:placetype":[
        "aat:300006084"
    ]
},
  "bbox": [],
  "geometry": {"coordinates":[139.0667,35.7833],"type":"Point"}
}