{
  "id": 2145015,
  "type": "Feature",
  "properties": {
    "tgn:hierarchy":[
        "tgn:2145015",
        "tgn:1000001",
        "tgn:7012149",
        "tgn:2002125",
        "tgn:7007827",
        "tgn:7029392"
    ],
    "tgn:id":2145015,
    "tgn:name":"Bald Knoll",
    "tgn:placetype":[
        "aat:300008798"
    ]
},
  "bbox": [],
  "geometry": {"coordinates":[-111.5167,40.25],"type":"Point"}
}