{
  "id": 7330121,
  "type": "Feature",
  "properties": {
    "tgn:hierarchy":[
        "tgn:7330121",
        "tgn:7002803",
        "tgn:1001647",
        "tgn:1000003",
        "tgn:1000095",
        "tgn:7029392"
    ],
    "tgn:id":7330121,
    "tgn:name":"Hoya-Gonzalo",
    "tgn:placetype":[
        "aat:300008347"
    ]
},
  "bbox": [],
  "geometry": {"coordinates":[-1.55,38.95],"type":"Point"}
}