{
  "id": 2164232,
  "type": "Feature",
  "properties": {
    "tgn:hierarchy":[
        "tgn:2164232",
        "tgn:1000001",
        "tgn:1002182",
        "tgn:7012149",
        "tgn:7007520",
        "tgn:7029392"
    ],
    "tgn:id":2164232,
    "tgn:name":"Bernhart Lake",
    "tgn:placetype":[
        "aat:300008905"
    ]
},
  "bbox": [],
  "geometry": {"coordinates":[-86.2333,41.9667],"type":"Point"}
}