{
  "id": 2359569,
  "type": "Feature",
  "properties": {
    "tgn:hierarchy":[
        "tgn:2359569",
        "tgn:1000001",
        "tgn:7012149",
        "tgn:2000217",
        "tgn:7007158",
        "tgn:7029392"
    ],
    "tgn:id":2359569,
    "tgn:name":"Grant, Lake",
    "tgn:placetype":[
        "aat:300006191"
    ]
},
  "bbox": [],
  "geometry": {"coordinates":[-106.9333,38.8667],"type":"Point"}
}