<<<<<<< HEAD
{
  "id": 7370281,
  "type": "Feature",
  "properties": {
    "tgn:hierarchy":[
        "tgn:7370281",
        "tgn:7005583",
        "tgn:1000001",
        "tgn:7005560",
        "tgn:7029392"
    ],
    "tgn:id":7370281,
    "tgn:name":"Los Sauces",
    "tgn:placetype":[
        "aat:300008347"
    ]
},
  "bbox": [],
  "geometry": {"coordinates":[-104.875278,24.723056],"type":"Point"}
}
=======
{"geometry":{"type":"Point","coordinates":[-104.875278,24.723056]},"type":"Feature","properties":{"hierarchy":["tgn:7370281","tgn:7005583","tgn:1000001","tgn:7005560","tgn:7029392"],"placetype":["aat:300008347"],"id":7370281,"name:xx":"Los Sauces"}}
>>>>>>> 03f74aca74312dbeaf24d7e61306dd6a786dc3d0
