{
  "id": 1092333,
  "type": "Feature",
  "properties": {
    "tgn:hierarchy":[
        "tgn:1092333",
        "tgn:7001242",
        "tgn:7014990",
        "tgn:1000183",
        "tgn:7029392"
    ],
    "tgn:id":1092333,
    "tgn:name":"Nova Lamego",
    "tgn:placetype":[
        "aat:300008347"
    ]
},
  "bbox": [],
  "geometry": {"coordinates":[-14.1833,12.3167],"type":"Point"}
}