{
  "id": 7005748,
  "type": "Feature",
  "properties": {
    "tgn:hierarchy":[
        "tgn:7005748",
        "tgn:1000003",
        "tgn:7594223",
        "tgn:7005729",
        "tgn:7029392"
    ],
    "tgn:id":7005748,
    "tgn:name":"Qormi",
    "tgn:placetype":[
        "aat:300008347"
    ]
},
  "bbox": [],
  "geometry": {"coordinates":[14.4667,35.8833],"type":"Point"}
}