<<<<<<< HEAD
{
  "id": 2404409,
  "type": "Feature",
  "properties": {
    "tgn:hierarchy":[
        "tgn:2404409",
        "tgn:1000001",
        "tgn:2002102",
        "tgn:7012149",
        "tgn:7007827",
        "tgn:7029392"
    ],
    "tgn:id":2404409,
    "tgn:name":"Hubbard Canyon",
    "tgn:placetype":[
        "aat:300008761"
    ]
},
  "bbox": [],
  "geometry": {"coordinates":[-113.7333,41.7167],"type":"Point"}
}
=======
{"geometry":{"type":"Point","coordinates":[-113.733300,41.716700]},"type":"Feature","properties":{"hierarchy":["tgn:2404409","tgn:1000001","tgn:2002102","tgn:7012149","tgn:7007827","tgn:7029392"],"placetype":["aat:300008761"],"id":2404409,"name:xx":"Hubbard Canyon"}}
>>>>>>> 03f74aca74312dbeaf24d7e61306dd6a786dc3d0
