{
  "id": 7590659,
  "type": "Feature",
  "properties": {
    "tgn:hierarchy":[
        "tgn:7590659",
        "tgn:1000004",
        "tgn:7000198",
        "tgn:7000799",
        "tgn:7029392"
    ],
    "tgn:id":7590659,
    "tgn:name:en":"Ramblu Rasoriy\u0101n",
    "tgn:placetype":[
        "aat:300008347"
    ]
},
  "bbox": [],
  "geometry": {"coordinates":[74.952778,32.511111],"type":"Point"}
}