{
  "id": 7513473,
  "type": "Feature",
  "properties": {
    "tgn:hierarchy":[
        "tgn:7513473",
        "tgn:1009227",
        "tgn:1000226",
        "tgn:7016822",
        "tgn:1000006",
        "tgn:7029392"
    ],
    "tgn:id":7513473,
    "tgn:name:en":"Glenfalloch",
    "tgn:placetype":[
        "aat:300000206"
    ]
},
  "bbox": [],
  "geometry": {"coordinates":[168.666667,-45.55],"type":"Point"}
}