{
  "id": 7334154,
  "type": "Feature",
  "properties": {
    "tgn:hierarchy":[
        "tgn:7334154",
        "tgn:7002820",
        "tgn:7030216",
        "tgn:1000003",
        "tgn:1000095",
        "tgn:7029392"
    ],
    "tgn:id":7334154,
    "tgn:name":"Els Molins",
    "tgn:placetype":[
        "aat:300008347"
    ]
},
  "bbox": [],
  "geometry": {"coordinates":[2.916667,42.316667],"type":"Point"}
}