{
  "id": 7577511,
  "type": "Feature",
  "properties": {
    "tgn:hierarchy":[
        "tgn:7577511",
        "tgn:1000004",
        "tgn:7000198",
        "tgn:1001894",
        "tgn:7029392"
    ],
    "tgn:id":7577511,
    "tgn:name:en":"Kukdeshwar",
    "tgn:placetype":[
        "aat:300008347"
    ]
},
  "bbox": [],
  "geometry": {"coordinates":[75.267548,24.48285],"type":"Point"}
}