{
  "id": 2414951,
  "type": "Feature",
  "properties": {
    "tgn:hierarchy":[
        "tgn:2414951",
        "tgn:7006450",
        "tgn:1000001",
        "tgn:7012149",
        "tgn:2124005",
        "tgn:7029392"
    ],
    "tgn:id":2414951,
    "tgn:name":"Ishuktak Creek",
    "tgn:placetype":[
        "aat:300008706"
    ]
},
  "bbox": [],
  "geometry": {"coordinates":[-156.3667,69.6333],"type":"Point"}
}