{
  "id": 2000331,
  "type": "Feature",
  "properties": {
    "tgn:hierarchy":[
        "tgn:2000331",
        "tgn:1000001",
        "tgn:7012149",
        "tgn:7007248",
        "tgn:7029392"
    ],
    "tgn:id":2000331,
    "tgn:name":"Crisp",
    "tgn:placetype":[
        "aat:300387145",
        "aat:300000771"
    ]
},
  "bbox": [],
  "geometry": {"coordinates":[-83.7667,31.9333],"type":"Point"}
}