{
  "id": 2179100,
  "type": "Feature",
  "properties": {
    "tgn:hierarchy":[
        "tgn:2179100",
        "tgn:1000001",
        "tgn:7012149",
        "tgn:2001916",
        "tgn:7007825",
        "tgn:7029392"
    ],
    "tgn:id":2179100,
    "tgn:name":"Blair Hollow",
    "tgn:placetype":[
        "aat:300008761"
    ]
},
  "bbox": [],
  "geometry": {"coordinates":[-85.8333,36.2167],"type":"Point"}
}