{
  "id": 7142682,
  "type": "Feature",
  "properties": {
    "tgn:hierarchy":[
        "tgn:7142682",
        "tgn:7003692",
        "tgn:1000003",
        "tgn:7000084",
        "tgn:7029392"
    ],
    "tgn:id":7142682,
    "tgn:name":"Mahd",
    "tgn:placetype":[
        "aat:300008863"
    ]
},
  "bbox": [],
  "geometry": {"coordinates":[10.316667,48.733333],"type":"Point"}
}