{
  "id": 2779537,
  "type": "Feature",
  "properties": {
    "tgn:hierarchy":[
        "tgn:2779537",
        "tgn:1000001",
        "tgn:7016172",
        "tgn:7012149",
        "tgn:2000150",
        "tgn:7029392"
    ],
    "tgn:id":2779537,
    "tgn:name":"Wolf Mountain",
    "tgn:placetype":[
        "aat:300008798"
    ]
},
  "bbox": [],
  "geometry": {"coordinates":[-93.85,33.3833],"type":"Point"}
}