{
  "id": 7297749,
  "type": "Feature",
  "properties": {
    "tgn:hierarchy":[
        "tgn:7297749",
        "tgn:7002760",
        "tgn:1000003",
        "tgn:1000095",
        "tgn:7029392"
    ],
    "tgn:id":7297749,
    "tgn:name":"Sope\u00f1a",
    "tgn:placetype":[
        "aat:300008347"
    ]
},
  "bbox": [],
  "geometry": {"coordinates":[-4.133333,42.95],"type":"Point"}
}