{
  "id": 2093614,
  "type": "Feature",
  "properties": {
    "tgn:hierarchy":[
        "tgn:2093614",
        "tgn:1000001",
        "tgn:1002286",
        "tgn:7012149",
        "tgn:7007710",
        "tgn:7029392"
    ],
    "tgn:id":2093614,
    "tgn:name":"Swissdale",
    "tgn:placetype":[
        "aat:300008347"
    ]
},
  "bbox": [],
  "geometry": {"coordinates":[-77.4333,41.1667],"type":"Point"}
}