{
  "id": 2291214,
  "type": "Feature",
  "properties": {
    "tgn:hierarchy":[
        "tgn:2291214",
        "tgn:1000001",
        "tgn:7006451",
        "tgn:2000092",
        "tgn:7012149",
        "tgn:7029392"
    ],
    "tgn:id":2291214,
    "tgn:name":"Dogtown Wash",
    "tgn:placetype":[
        "aat:300008699"
    ]
},
  "bbox": [],
  "geometry": {"coordinates":[-112.1833,35.1833],"type":"Point"}
}