{
  "id": 2176605,
  "type": "Feature",
  "properties": {
    "tgn:hierarchy":[
        "tgn:2176605",
        "tgn:1000001",
        "tgn:7012149",
        "tgn:2002327",
        "tgn:7007922",
        "tgn:7029392"
    ],
    "tgn:id":2176605,
    "tgn:name":"Black Lake",
    "tgn:placetype":[
        "aat:300008680"
    ]
},
  "bbox": [],
  "geometry": {"coordinates":[-89.9333,46.0167],"type":"Point"}
}