<<<<<<< HEAD
{
  "id": 7023931,
  "type": "Feature",
  "properties": {
    "tgn:hierarchy":[
        "tgn:7023931",
        "tgn:7023928",
        "tgn:1000001",
        "tgn:7004786",
        "tgn:7029392"
    ],
    "tgn:id":7023931,
    "tgn:name":"Bethel",
    "tgn:placetype":[
        "aat:300008347",
        "aat:300008375"
    ]
},
  "bbox": [],
  "geometry": {"coordinates":[-62.15,16.733],"type":"Point"}
}
=======
{"geometry":{"type":"Point","coordinates":[-62.150000,16.733000]},"type":"Feature","properties":{"hierarchy":["tgn:7023931","tgn:7023928","tgn:1000001","tgn:7004786","tgn:7029392"],"placetype":["aat:300008347","aat:300008375"],"id":7023931,"name:xx":"Bethel"}}
>>>>>>> 03f74aca74312dbeaf24d7e61306dd6a786dc3d0
