{
  "id": 1097980,
  "type": "Feature",
  "properties": {
    "tgn:hierarchy":[
        "tgn:1097980",
        "tgn:7000490",
        "tgn:1000006",
        "tgn:7001831",
        "tgn:7029392"
    ],
    "tgn:id":1097980,
    "tgn:name":"Port Clinton",
    "tgn:placetype":[
        "aat:300008347"
    ]
},
  "bbox": [],
  "geometry": {"coordinates":[138.0333,-34.2333],"type":"Point"}
}