{
  "id": 2406191,
  "type": "Feature",
  "properties": {
    "tgn:hierarchy":[
        "tgn:2406191",
        "tgn:7006450",
        "tgn:1000001",
        "tgn:7030517",
        "tgn:7012149",
        "tgn:7029392"
    ],
    "tgn:id":2406191,
    "tgn:name":"Humpback Bay",
    "tgn:placetype":[
        "aat:300132316"
    ]
},
  "bbox": [],
  "geometry": {"coordinates":[-159.3667,55.85],"type":"Point"}
}