{
  "id": 2499995,
  "type": "Feature",
  "properties": {
    "tgn:hierarchy":[
        "tgn:2499995",
        "tgn:1000001",
        "tgn:7012149",
        "tgn:1002862",
        "tgn:7007920",
        "tgn:7029392"
    ],
    "tgn:id":2499995,
    "tgn:name":"McCracken Point",
    "tgn:placetype":[
        "aat:300008850"
    ]
},
  "bbox": [],
  "geometry": {"coordinates":[-123.1667,48.6167],"type":"Point"}
}