<<<<<<< HEAD
{
  "id": 2153092,
  "type": "Feature",
  "properties": {
    "tgn:hierarchy":[
        "tgn:2153092",
        "tgn:1000001",
        "tgn:2001938",
        "tgn:7012149",
        "tgn:7007826",
        "tgn:7029392"
    ],
    "tgn:id":2153092,
    "tgn:name":"Beacon Point",
    "tgn:placetype":[
        "aat:300008850"
    ]
},
  "bbox": [],
  "geometry": {"coordinates":[-98.9333,29.55],"type":"Point"}
}
=======
{"geometry":{"type":"Point","coordinates":[-98.933300,29.550000]},"type":"Feature","properties":{"hierarchy":["tgn:2153092","tgn:1000001","tgn:2001938","tgn:7012149","tgn:7007826","tgn:7029392"],"placetype":["aat:300008850"],"id":2153092,"name:xx":"Beacon Point"}}
>>>>>>> 03f74aca74312dbeaf24d7e61306dd6a786dc3d0
