{
  "id": 2521012,
  "type": "Feature",
  "properties": {
    "tgn:hierarchy":[
        "tgn:2521012",
        "tgn:1000001",
        "tgn:7012149",
        "tgn:2001295",
        "tgn:7007524",
        "tgn:7029392"
    ],
    "tgn:id":2521012,
    "tgn:name":"Montana Gulch",
    "tgn:placetype":[
        "aat:300008761"
    ]
},
  "bbox": [],
  "geometry": {"coordinates":[-108.6167,47.9167],"type":"Point"}
}