{
  "id": 7523622,
  "type": "Feature",
  "properties": {
    "tgn:hierarchy":[
        "tgn:7523622",
        "tgn:7001242",
        "tgn:7016833",
        "tgn:1001418",
        "tgn:7029392"
    ],
    "tgn:id":7523622,
    "tgn:name:en":"Faras, Ghurd al",
    "tgn:placetype":[
        "aat:300008750"
    ]
},
  "bbox": [],
  "geometry": {"coordinates":[28.054073,29.714581],"type":"Point"}
}