{
  "id": 7334647,
  "type": "Feature",
  "properties": {
    "tgn:hierarchy":[
        "tgn:7334647",
        "tgn:7002818",
        "tgn:1001647",
        "tgn:1000003",
        "tgn:1000095",
        "tgn:7029392"
    ],
    "tgn:id":7334647,
    "tgn:name":"El Molino",
    "tgn:placetype":[
        "aat:300008347"
    ]
},
  "bbox": [],
  "geometry": {"coordinates":[-1.95,40.433333],"type":"Point"}
}