{
  "id": 7030811,
  "type": "Feature",
  "properties": {
    "tgn:hierarchy":[
        "tgn:7030811",
        "tgn:7002445",
        "tgn:1000003",
        "tgn:7012031",
        "tgn:7008591",
        "tgn:7029392"
    ],
    "tgn:id":7030811,
    "tgn:name":"Little Creaton",
    "tgn:placetype":[
        "aat:300008347",
        "aat:300008369"
    ]
},
  "bbox": [],
  "geometry": {"coordinates":[-0.982,52.333],"type":"Point"}
}