<<<<<<< HEAD
{
  "id": 2762609,
  "type": "Feature",
  "properties": {
    "tgn:hierarchy":[
        "tgn:2762609",
        "tgn:1000001",
        "tgn:7012149",
        "tgn:2002118",
        "tgn:7007827",
        "tgn:7029392"
    ],
    "tgn:id":2762609,
    "tgn:name":"Westbrook Park",
    "tgn:placetype":[
        "aat:300008347"
    ]
},
  "bbox": [],
  "geometry": {"coordinates":[-111.9667,40.7],"type":"Point"}
}
=======
{"geometry":{"type":"Point","coordinates":[-111.966700,40.700000]},"type":"Feature","properties":{"hierarchy":["tgn:2762609","tgn:1000001","tgn:7012149","tgn:2002118","tgn:7007827","tgn:7029392"],"placetype":["aat:300008347"],"id":2762609,"name:xx":"Westbrook Park"}}
>>>>>>> 03f74aca74312dbeaf24d7e61306dd6a786dc3d0
