{
  "id": 7562515,
  "type": "Feature",
  "properties": {
    "tgn:hierarchy":[
        "tgn:7562515",
        "tgn:1000004",
        "tgn:7000198",
        "tgn:7016722",
        "tgn:7029392"
    ],
    "tgn:id":7562515,
    "tgn:name:en":"Ratbh\u0101npur",
    "tgn:placetype":[
        "aat:300008347"
    ]
},
  "bbox": [],
  "geometry": {"coordinates":[79.342412,27.011007],"type":"Point"}
}