{
  "id": 7318078,
  "type": "Feature",
  "properties": {
    "tgn:hierarchy":[
        "tgn:7318078",
        "tgn:1001630",
        "tgn:1000049",
        "tgn:1000002",
        "tgn:7029392"
    ],
    "tgn:id":7318078,
    "tgn:name":"Corrales",
    "tgn:placetype":[
        "aat:300008697"
    ]
},
  "bbox": [],
  "geometry": {"coordinates":[-69.733333,-26.983333],"type":"Point"}
}