<<<<<<< HEAD
{
  "id": 7023915,
  "type": "Feature",
  "properties": {
    "tgn:hierarchy":[
        "tgn:7023915",
        "tgn:1000003",
        "tgn:7024125",
        "tgn:7006366",
        "tgn:7029392"
    ],
    "tgn:id":7023915,
    "tgn:name":"Czaniec",
    "tgn:placetype":[
        "aat:300008347"
    ]
},
  "bbox": [],
  "geometry": {"coordinates":[19.25,49.85],"type":"Point"}
}
=======
{"geometry":{"type":"Point","coordinates":[19.250000,49.850000]},"type":"Feature","properties":{"hierarchy":["tgn:7023915","tgn:1000003","tgn:7024125","tgn:7006366","tgn:7029392"],"placetype":["aat:300008347"],"id":7023915,"name:xx":"Czaniec"}}
>>>>>>> 03f74aca74312dbeaf24d7e61306dd6a786dc3d0
