{
  "id": 2041161,
  "type": "Feature",
  "properties": {
    "tgn:hierarchy":[
        "tgn:2041161",
        "tgn:1000001",
        "tgn:7012149",
        "tgn:2000793",
        "tgn:7007255",
        "tgn:7029392"
    ],
    "tgn:id":2041161,
    "tgn:name":"Saint Paul",
    "tgn:placetype":[
        "aat:300008347"
    ]
},
  "bbox": [],
  "geometry": {"coordinates":[-86.1833,37.55],"type":"Point"}
}