{
  "id": 2682789,
  "type": "Feature",
  "properties": {
    "tgn:hierarchy":[
        "tgn:2682789",
        "tgn:1000001",
        "tgn:7012149",
        "tgn:1002768",
        "tgn:7007240",
        "tgn:7029392"
    ],
    "tgn:id":2682789,
    "tgn:name":"Southwest Fork Loxahatchee River",
    "tgn:placetype":[
        "aat:300008707"
    ]
},
  "bbox": [],
  "geometry": {"coordinates":[-80.1167,26.9167],"type":"Point"}
}