{
  "id": 7226191,
  "type": "Feature",
  "properties": {
    "tgn:hierarchy":[
        "tgn:7226191",
        "tgn:7011167",
        "tgn:7001338",
        "tgn:1000003",
        "tgn:1000074",
        "tgn:7029392"
    ],
    "tgn:id":7226191,
    "tgn:name":"Sarakin\u00e1to, \u00c1kra",
    "tgn:placetype":[
        "aat:300008850"
    ]
},
  "bbox": [],
  "geometry": {"coordinates":[20.783333,38.15],"type":"Point"}
}