{
  "id": 2785398,
  "type": "Feature",
  "properties": {
    "tgn:hierarchy":[
        "tgn:2785398",
        "tgn:7006450",
        "tgn:1000001",
        "tgn:7012149",
        "tgn:2000079",
        "tgn:7029392"
    ],
    "tgn:id":2785398,
    "tgn:name":"Yellowstone Creek",
    "tgn:placetype":[
        "aat:300008706"
    ]
},
  "bbox": [],
  "geometry": {"coordinates":[-166.3167,65.1667],"type":"Point"}
}