{
  "id": 2144478,
  "type": "Feature",
  "properties": {
    "tgn:hierarchy":[
        "tgn:2144478",
        "tgn:1000001",
        "tgn:2000318",
        "tgn:7012149",
        "tgn:7007248",
        "tgn:7029392"
    ],
    "tgn:id":2144478,
    "tgn:name":"Bakers Pond",
    "tgn:placetype":[
        "aat:300008680"
    ]
},
  "bbox": [],
  "geometry": {"coordinates":[-85.45,34.2833],"type":"Point"}
}