{
  "id": 7382800,
  "type": "Feature",
  "properties": {
    "tgn:hierarchy":[
        "tgn:7382800",
        "tgn:1000001",
        "tgn:7005599",
        "tgn:7005560",
        "tgn:7029392"
    ],
    "tgn:id":7382800,
    "tgn:name":"Palo Solo",
    "tgn:placetype":[
        "aat:300008347"
    ]
},
  "bbox": [],
  "geometry": {"coordinates":[-98.283333,21.516667],"type":"Point"}
}