{
  "id": 2288500,
  "type": "Feature",
  "properties": {
    "tgn:hierarchy":[
        "tgn:2288500",
        "tgn:1000001",
        "tgn:7012149",
        "tgn:1002440",
        "tgn:7007568",
        "tgn:7029392"
    ],
    "tgn:id":2288500,
    "tgn:name":"Dishrag Pond",
    "tgn:placetype":[
        "aat:300008680"
    ]
},
  "bbox": [],
  "geometry": {"coordinates":[-74.4833,43.7667],"type":"Point"}
}