{
  "id": 7513609,
  "type": "Feature",
  "properties": {
    "tgn:hierarchy":[
        "tgn:7513609",
        "tgn:1008380",
        "tgn:7000507",
        "tgn:1000226",
        "tgn:1000006",
        "tgn:7029392"
    ],
    "tgn:id":7513609,
    "tgn:name:en":"Galakek Island",
    "tgn:placetype":[
        "aat:300008791"
    ]
},
  "bbox": [],
  "geometry": {"coordinates":[174.133333,-35.15],"type":"Point"}
}