<<<<<<< HEAD
{
  "id": 7026897,
  "type": "Feature",
  "properties": {
    "tgn:hierarchy":[
        "tgn:7026897",
        "tgn:7002445",
        "tgn:1000003",
        "tgn:7008139",
        "tgn:7008591",
        "tgn:7029392"
    ],
    "tgn:id":7026897,
    "tgn:name":"Old Milton",
    "tgn:placetype":[
        "aat:300008347",
        "aat:300008375"
    ]
},
  "bbox": [],
  "geometry": {"coordinates":[-1.6667,50.75],"type":"Point"}
}
=======
{"geometry":{"type":"Point","coordinates":[-1.666700,50.750000]},"type":"Feature","properties":{"hierarchy":["tgn:7026897","tgn:7002445","tgn:1000003","tgn:7008139","tgn:7008591","tgn:7029392"],"placetype":["aat:300008347","aat:300008375"],"id":7026897,"name:xx":"Old Milton"}}
>>>>>>> 03f74aca74312dbeaf24d7e61306dd6a786dc3d0
