{
  "id": 2430784,
  "type": "Feature",
  "properties": {
    "tgn:hierarchy":[
        "tgn:2430784",
        "tgn:1002648",
        "tgn:1000001",
        "tgn:7019158",
        "tgn:7012149",
        "tgn:7007249",
        "tgn:7029392"
    ],
    "tgn:id":2430784,
    "tgn:name":"Kamanawai Gulch",
    "tgn:placetype":[
        "aat:300008761"
    ]
},
  "bbox": [],
  "geometry": {"coordinates":[-156.5333,20.7833],"type":"Point"}
}