{
  "id": 7511770,
  "type": "Feature",
  "properties": {
    "tgn:hierarchy":[
        "tgn:7511770",
        "tgn:1009227",
        "tgn:1000226",
        "tgn:1000006",
        "tgn:7016850",
        "tgn:7029392"
    ],
    "tgn:id":7511770,
    "tgn:name:en":"Karangarua",
    "tgn:placetype":[
        "aat:300008347"
    ]
},
  "bbox": [],
  "geometry": {"coordinates":[169.816667,-43.533333],"type":"Point"}
}