<<<<<<< HEAD
{
  "id": 2335228,
  "type": "Feature",
  "properties": {
    "tgn:hierarchy":[
        "tgn:2335228",
        "tgn:1000001",
        "tgn:7012149",
        "tgn:1002999",
        "tgn:7007526",
        "tgn:7029392"
    ],
    "tgn:id":2335228,
    "tgn:name":"Fort Defiance Canyon",
    "tgn:placetype":[
        "aat:300008761"
    ]
},
  "bbox": [],
  "geometry": {"coordinates":[-119.4167,39.7],"type":"Point"}
}
=======
{"geometry":{"type":"Point","coordinates":[-119.416700,39.700000]},"type":"Feature","properties":{"hierarchy":["tgn:2335228","tgn:1000001","tgn:7012149","tgn:1002999","tgn:7007526","tgn:7029392"],"placetype":["aat:300008761"],"id":2335228,"name:xx":"Fort Defiance Canyon"}}
>>>>>>> 03f74aca74312dbeaf24d7e61306dd6a786dc3d0
