{
  "id": 2328417,
  "type": "Feature",
  "properties": {
    "tgn:hierarchy":[
        "tgn:2328417",
        "tgn:1000001",
        "tgn:7012149",
        "tgn:2001827",
        "tgn:7007713",
        "tgn:7029392"
    ],
    "tgn:id":2328417,
    "tgn:name":"Fisher Grove",
    "tgn:placetype":[
        "aat:300055621"
    ]
},
  "bbox": [],
  "geometry": {"coordinates":[-98.35,44.8833],"type":"Point"}
}