{
  "id": 7579482,
  "type": "Feature",
  "properties": {
    "tgn:hierarchy":[
        "tgn:7579482",
        "tgn:1001828",
        "tgn:1000004",
        "tgn:7000198",
        "tgn:7029392"
    ],
    "tgn:id":7579482,
    "tgn:name:en":"Somala",
    "tgn:placetype":[
        "aat:300008347"
    ]
},
  "bbox": [],
  "geometry": {"coordinates":[78.816667,13.466667],"type":"Point"}
}