<<<<<<< HEAD
{
  "id": 2159932,
  "type": "Feature",
  "properties": {
    "tgn:hierarchy":[
        "tgn:2159932",
        "tgn:1000001",
        "tgn:2001424",
        "tgn:7012149",
        "tgn:7007564",
        "tgn:7029392"
    ],
    "tgn:id":2159932,
    "tgn:name":"Beech Hill",
    "tgn:placetype":[
        "aat:300266640"
    ]
},
  "bbox": [],
  "geometry": {"coordinates":[-71.7167,43.8],"type":"Point"}
}
=======
{"geometry":{"type":"Point","coordinates":[-71.716700,43.800000]},"type":"Feature","properties":{"hierarchy":["tgn:2159932","tgn:1000001","tgn:2001424","tgn:7012149","tgn:7007564","tgn:7029392"],"placetype":["aat:300266640"],"id":2159932,"name:xx":"Beech Hill"}}
>>>>>>> 03f74aca74312dbeaf24d7e61306dd6a786dc3d0
