{
  "id": 1107961,
  "type": "Feature",
  "properties": {
    "tgn:hierarchy":[
        "tgn:1107961",
        "tgn:1003391",
        "tgn:1000003",
        "tgn:7006657",
        "tgn:7029392"
    ],
    "tgn:id":1107961,
    "tgn:name":"Dzer\u017einskaja, gora",
    "tgn:placetype":[
        "aat:300008777"
    ]
},
  "bbox": [],
  "geometry": {"coordinates":[27.05,53.85],"type":"Point"}
}