{
  "id": 7492510,
  "type": "Feature",
  "properties": {
    "tgn:hierarchy":[
        "tgn:7492510",
        "tgn:1000004",
        "tgn:7004300",
        "tgn:1000141",
        "tgn:7029392"
    ],
    "tgn:id":7492510,
    "tgn:name":"Sijiao Yu",
    "tgn:placetype":[
        "aat:300008791"
    ]
},
  "bbox": [],
  "geometry": {"coordinates":[119.542299,23.553982],"type":"Point"}
}