<<<<<<< HEAD
{
  "id": 7470452,
  "type": "Feature",
  "properties": {
    "tgn:hierarchy":[
        "tgn:7470452",
        "tgn:1000004",
        "tgn:1000454",
        "tgn:1000141",
        "tgn:7029392"
    ],
    "tgn:id":7470452,
    "tgn:name":"Zhuzihu",
    "tgn:placetype":[
        "aat:300008347"
    ]
},
  "bbox": [],
  "geometry": {"coordinates":[121.540059,25.170141],"type":"Point"}
}
=======
{"geometry":{"type":"Point","coordinates":[121.540059,25.170141]},"type":"Feature","properties":{"hierarchy":["tgn:7470452","tgn:1000004","tgn:1000454","tgn:1000141","tgn:7029392"],"placetype":["aat:300008347"],"id":7470452,"name:xx":"Zhuzihu"}}
>>>>>>> 03f74aca74312dbeaf24d7e61306dd6a786dc3d0
