<<<<<<< HEAD
{
  "id": 2761669,
  "type": "Feature",
  "properties": {
    "tgn:hierarchy":[
        "tgn:2761669",
        "tgn:7006450",
        "tgn:1000001",
        "tgn:7012149",
        "tgn:2000088",
        "tgn:7029392"
    ],
    "tgn:id":2761669,
    "tgn:name":"West Point",
    "tgn:placetype":[
        "aat:300008850"
    ]
},
  "bbox": [],
  "geometry": {"coordinates":[-133.3333,57.0],"type":"Point"}
}
=======
{"geometry":{"type":"Point","coordinates":[-133.333300,57.000000]},"type":"Feature","properties":{"hierarchy":["tgn:2761669","tgn:7006450","tgn:1000001","tgn:7012149","tgn:2000088","tgn:7029392"],"placetype":["aat:300008850"],"id":2761669,"name:xx":"West Point"}}
>>>>>>> 03f74aca74312dbeaf24d7e61306dd6a786dc3d0
