{
  "id": 7592442,
  "type": "Feature",
  "properties": {
    "tgn:hierarchy":[
        "tgn:7592442",
        "tgn:1000004",
        "tgn:7000198",
        "tgn:7000799",
        "tgn:7029392"
    ],
    "tgn:id":7592442,
    "tgn:name:en":"Dhariala",
    "tgn:placetype":[
        "aat:300008347"
    ]
},
  "bbox": [],
  "geometry": {"coordinates":[74.239083,33.102512],"type":"Point"}
}