{
  "id": 2178383,
  "type": "Feature",
  "properties": {
    "tgn:hierarchy":[
        "tgn:2178383",
        "tgn:1000001",
        "tgn:7012149",
        "tgn:7007710",
        "tgn:7029392"
    ],
    "tgn:id":2178383,
    "tgn:name":"Blacklog Mountain",
    "tgn:placetype":[
        "aat:300386831"
    ]
},
  "bbox": [],
  "geometry": {"coordinates":[-77.8667,40.2333],"type":"Point"}
}