{
  "id": 7519478,
  "type": "Feature",
  "properties": {
    "tgn:hierarchy":[
        "tgn:7519478",
        "tgn:1009227",
        "tgn:1000226",
        "tgn:7016729",
        "tgn:1000006",
        "tgn:7029392"
    ],
    "tgn:id":7519478,
    "tgn:name:en":"Boulder Stream",
    "tgn:placetype":[
        "aat:300008699"
    ]
},
  "bbox": [],
  "geometry": {"coordinates":[173.166667,-41.683333],"type":"Point"}
}