<<<<<<< HEAD
{
  "id": 2769630,
  "type": "Feature",
  "properties": {
    "tgn:hierarchy":[
        "tgn:2769630",
        "tgn:1000001",
        "tgn:7012149",
        "tgn:1002671",
        "tgn:7007523",
        "tgn:7029392"
    ],
    "tgn:id":2769630,
    "tgn:name":"Wiemer Creek",
    "tgn:placetype":[
        "aat:300008706"
    ]
},
  "bbox": [],
  "geometry": {"coordinates":[-92.2167,38.15],"type":"Point"}
}
=======
{"geometry":{"type":"Point","coordinates":[-92.216700,38.150000]},"type":"Feature","properties":{"hierarchy":["tgn:2769630","tgn:1000001","tgn:7012149","tgn:1002671","tgn:7007523","tgn:7029392"],"placetype":["aat:300008706"],"id":2769630,"name:xx":"Wiemer Creek"}}
>>>>>>> 03f74aca74312dbeaf24d7e61306dd6a786dc3d0
