{
  "id": 2769630,
  "type": "Feature",
  "properties": {
    "tgn:hierarchy":[
        "tgn:2769630",
        "tgn:1000001",
        "tgn:7012149",
        "tgn:1002671",
        "tgn:7007523",
        "tgn:7029392"
    ],
    "tgn:id":2769630,
    "tgn:name":"Wiemer Creek",
    "tgn:placetype":[
        "aat:300008706"
    ]
},
  "bbox": [],
  "geometry": {"coordinates":[-92.2167,38.15],"type":"Point"}
}