{
  "id": 1029544,
  "type": "Feature",
  "properties": {
    "tgn:hierarchy":[
        "tgn:1029544",
        "tgn:7002445",
        "tgn:1000003",
        "tgn:7008153",
        "tgn:7008591",
        "tgn:7029392"
    ],
    "tgn:id":1029544,
    "tgn:name":"Hextable",
    "tgn:placetype":[
        "aat:300008347"
    ]
},
  "bbox": [],
  "geometry": {"coordinates":[0.1833,51.4167],"type":"Point"}
}