{
  "id": 1014772,
  "type": "Feature",
  "properties": {
    "tgn:hierarchy":[
        "tgn:1014772",
        "tgn:7005685",
        "tgn:1000001",
        "tgn:7013154",
        "tgn:7029392"
    ],
    "tgn:id":1014772,
    "tgn:name":"Foleyet",
    "tgn:placetype":[
        "aat:300008347"
    ]
},
  "bbox": [],
  "geometry": {"coordinates":[-82.4333,48.25],"type":"Point"}
}