{
  "id": 7152216,
  "type": "Feature",
  "properties": {
    "tgn:hierarchy":[
        "tgn:7152216",
        "tgn:1000003",
        "tgn:7003687",
        "tgn:7000084",
        "tgn:7029392"
    ],
    "tgn:id":7152216,
    "tgn:name":"Kassieck",
    "tgn:placetype":[
        "aat:300008347"
    ]
},
  "bbox": [],
  "geometry": {"coordinates":[11.483333,52.583333],"type":"Point"}
}