<<<<<<< HEAD
{
  "id": 2156903,
  "type": "Feature",
  "properties": {
    "tgn:hierarchy":[
        "tgn:2156903",
        "tgn:1000001",
        "tgn:7012149",
        "tgn:7014612",
        "tgn:7007568",
        "tgn:7029392"
    ],
    "tgn:id":2156903,
    "tgn:name":"Beaufort Point",
    "tgn:placetype":[
        "aat:300008850"
    ]
},
  "bbox": [],
  "geometry": {"coordinates":[-73.7667,40.9],"type":"Point"}
}
=======
{"geometry":{"type":"Point","coordinates":[-73.766700,40.900000]},"type":"Feature","properties":{"hierarchy":["tgn:2156903","tgn:1000001","tgn:7012149","tgn:7014612","tgn:7007568","tgn:7029392"],"placetype":["aat:300008850"],"id":2156903,"name:xx":"Beaufort Point"}}
>>>>>>> 03f74aca74312dbeaf24d7e61306dd6a786dc3d0
