{
  "id": 7527056,
  "type": "Feature",
  "properties": {
    "tgn:hierarchy":[
        "tgn:7527056",
        "tgn:7001242",
        "tgn:7016833",
        "tgn:1001091",
        "tgn:7029392"
    ],
    "tgn:id":7527056,
    "tgn:name":"K\u016bbr\u012b as Sayyidah '\u0100'ishah",
    "tgn:placetype":[
        "aat:300007836"
    ]
},
  "bbox": [],
  "geometry": {"coordinates":[31.257107,30.024374],"type":"Point"}
}