{
  "id": 7587147,
  "type": "Feature",
  "properties": {
    "tgn:hierarchy":[
        "tgn:7587147",
        "tgn:1000004",
        "tgn:7000198",
        "tgn:7000799",
        "tgn:7029392"
    ],
    "tgn:id":7587147,
    "tgn:name:en":"Gund Rahm\u0101n",
    "tgn:placetype":[
        "aat:300008347"
    ]
},
  "bbox": [],
  "geometry": {"coordinates":[74.765315,34.182117],"type":"Point"}
}