<<<<<<< HEAD
{
  "id": 2765810,
  "type": "Feature",
  "properties": {
    "tgn:hierarchy":[
        "tgn:2765810",
        "tgn:1000001",
        "tgn:7012149",
        "tgn:2001283",
        "tgn:7007524",
        "tgn:7029392"
    ],
    "tgn:id":2765810,
    "tgn:name":"White Earth Creek",
    "tgn:placetype":[
        "aat:300008706"
    ]
},
  "bbox": [],
  "geometry": {"coordinates":[-114.4167,47.7833],"type":"Point"}
}
=======
{"geometry":{"type":"Point","coordinates":[-114.416700,47.783300]},"type":"Feature","properties":{"hierarchy":["tgn:2765810","tgn:1000001","tgn:7012149","tgn:2001283","tgn:7007524","tgn:7029392"],"placetype":["aat:300008706"],"id":2765810,"name:xx":"White Earth Creek"}}
>>>>>>> 03f74aca74312dbeaf24d7e61306dd6a786dc3d0
