{
  "id": 7233786,
  "type": "Feature",
  "properties": {
    "tgn:hierarchy":[
        "tgn:7233786",
        "tgn:7011270",
        "tgn:7002674",
        "tgn:1000003",
        "tgn:1000074",
        "tgn:7029392"
    ],
    "tgn:id":7233786,
    "tgn:name":"\u00c1latos, \u00c1kra",
    "tgn:placetype":[
        "aat:300008850"
    ]
},
  "bbox": [],
  "geometry": {"coordinates":[25.85,36.85],"type":"Point"}
}