{
  "id": 7418767,
  "type": "Feature",
  "properties": {
    "tgn:hierarchy":[
        "tgn:7418767",
        "tgn:7005579",
        "tgn:1000001",
        "tgn:7005560",
        "tgn:7029392"
    ],
    "tgn:id":7418767,
    "tgn:name":"El Tepoz\u00e1n, Arroyo",
    "tgn:placetype":[
        "aat:300266554",
        "aat:300008699"
    ]
},
  "bbox": [],
  "geometry": {"coordinates":[-102.166667,22.175],"type":"Point"}
}