{
  "id": 7492299,
  "type": "Feature",
  "properties": {
    "tgn:hierarchy":[
        "tgn:7492299",
        "tgn:1000004",
        "tgn:7467799",
        "tgn:1000141",
        "tgn:7029392"
    ],
    "tgn:id":7492299,
    "tgn:name":"Sijiaoting",
    "tgn:placetype":[
        "aat:300008347"
    ]
},
  "bbox": [],
  "geometry": {"coordinates":[120.575125,23.852687],"type":"Point"}
}