{
  "id": 7414729,
  "type": "Feature",
  "properties": {
    "tgn:hierarchy":[
        "tgn:7414729",
        "tgn:7005584",
        "tgn:1000001",
        "tgn:7005560",
        "tgn:7029392"
    ],
    "tgn:id":7414729,
    "tgn:name":"Puerto de \u00c1guila",
    "tgn:placetype":[
        "aat:300008347"
    ]
},
  "bbox": [],
  "geometry": {"coordinates":[-101.325833,20.281111],"type":"Point"}
}