{
  "id": 7372307,
  "type": "Feature",
  "properties": {
    "tgn:hierarchy":[
        "tgn:7372307",
        "tgn:7005586",
        "tgn:1000001",
        "tgn:7005560",
        "tgn:7029392"
    ],
    "tgn:id":7372307,
    "tgn:name":"La Noria",
    "tgn:placetype":[
        "aat:300008347"
    ]
},
  "bbox": [],
  "geometry": {"coordinates":[-102.316667,20.366667],"type":"Point"}
}