{
  "id": 2750975,
  "type": "Feature",
  "properties": {
    "tgn:hierarchy":[
        "tgn:2750975",
        "tgn:1000001",
        "tgn:7012149",
        "tgn:1002314",
        "tgn:7007240",
        "tgn:7029392"
    ],
    "tgn:id":2750975,
    "tgn:name":"Ward, Lake",
    "tgn:placetype":[
        "aat:300008680"
    ]
},
  "bbox": [],
  "geometry": {"coordinates":[-80.1667,25.85],"type":"Point"}
}