{
  "id": 7355099,
  "type": "Feature",
  "properties": {
    "tgn:hierarchy":[
        "tgn:7355099",
        "tgn:1000001",
        "tgn:1001960",
        "tgn:7005560",
        "tgn:7029392"
    ],
    "tgn:id":7355099,
    "tgn:name":"Cebampo",
    "tgn:placetype":[
        "aat:300008347"
    ]
},
  "bbox": [],
  "geometry": {"coordinates":[-109.416667,26.85],"type":"Point"}
}