{
  "id": 7312211,
  "type": "Feature",
  "properties": {
    "tgn:hierarchy":[
        "tgn:7312211",
        "tgn:1001695",
        "tgn:1000049",
        "tgn:1000002",
        "tgn:7029392"
    ],
    "tgn:id":7312211,
    "tgn:name":"Las Cabras",
    "tgn:placetype":[
        "aat:300000206"
    ]
},
  "bbox": [],
  "geometry": {"coordinates":[-70.816667,-34.266667],"type":"Point"}
}