{
  "id": 2020824,
  "type": "Feature",
  "properties": {
    "tgn:hierarchy":[
        "tgn:2020824",
        "tgn:1000001",
        "tgn:1002207",
        "tgn:7012149",
        "tgn:7007240",
        "tgn:7029392"
    ],
    "tgn:id":2020824,
    "tgn:name":"Pembroke Park",
    "tgn:placetype":[
        "aat:300008347"
    ]
},
  "bbox": [],
  "geometry": {"coordinates":[-80.1667,25.9833],"type":"Point"}
}