{
  "id": 2347304,
  "type": "Feature",
  "properties": {
    "tgn:hierarchy":[
        "tgn:2347304",
        "tgn:1000001",
        "tgn:7012149",
        "tgn:2000227",
        "tgn:7007158",
        "tgn:7029392"
    ],
    "tgn:id":2347304,
    "tgn:name":"George Canyon",
    "tgn:placetype":[
        "aat:300008761"
    ]
},
  "bbox": [],
  "geometry": {"coordinates":[-103.5667,37.15],"type":"Point"}
}