{
  "id": 2126428,
  "type": "Feature",
  "properties": {
    "tgn:hierarchy":[
        "tgn:2126428",
        "tgn:1000001",
        "tgn:2002367",
        "tgn:7012149",
        "tgn:7007923",
        "tgn:7029392"
    ],
    "tgn:id":2126428,
    "tgn:name":"Adon",
    "tgn:placetype":[
        "aat:300008347"
    ]
},
  "bbox": [],
  "geometry": {"coordinates":[-105.2167,44.5167],"type":"Point"}
}