{
  "id": 7174587,
  "type": "Feature",
  "properties": {
    "tgn:hierarchy":[
        "tgn:7174587",
        "tgn:1000003",
        "tgn:7003689",
        "tgn:7000084",
        "tgn:7029392"
    ],
    "tgn:id":7174587,
    "tgn:name":"Gro\u00df Insels Berg",
    "tgn:placetype":[
        "aat:300008795"
    ]
},
  "bbox": [],
  "geometry": {"coordinates":[10.466667,50.866667],"type":"Point"}
}