{
  "id": 7483626,
  "type": "Feature",
  "properties": {
    "tgn:hierarchy":[
        "tgn:7483626",
        "tgn:1000004",
        "tgn:7490934",
        "tgn:1000141",
        "tgn:7029392"
    ],
    "tgn:id":7483626,
    "tgn:name":"Beishi",
    "tgn:placetype":[
        "aat:300008347"
    ]
},
  "bbox": [],
  "geometry": {"coordinates":[120.543611,23.183611],"type":"Point"}
}