{
  "id": 2528711,
  "type": "Feature",
  "properties": {
    "tgn:hierarchy":[
        "tgn:2528711",
        "tgn:1000001",
        "tgn:2001801",
        "tgn:7012149",
        "tgn:7007713",
        "tgn:7029392"
    ],
    "tgn:id":2528711,
    "tgn:name":"Mud Butte",
    "tgn:placetype":[
        "aat:300008798"
    ]
},
  "bbox": [],
  "geometry": {"coordinates":[-103.6333,45.7167],"type":"Point"}
}