{
  "id": 2478620,
  "type": "Feature",
  "properties": {
    "tgn:hierarchy":[
        "tgn:2478620",
        "tgn:1000001",
        "tgn:7012149",
        "tgn:2001453",
        "tgn:7007566",
        "tgn:7029392"
    ],
    "tgn:id":2478620,
    "tgn:name":"Madera, Ca\u00f1on de la",
    "tgn:placetype":[
        "aat:300008761"
    ]
},
  "bbox": [],
  "geometry": {"coordinates":[-105.6333,35.6333],"type":"Point"}
}