{
  "id": 7190558,
  "type": "Feature",
  "properties": {
    "tgn:hierarchy":[
        "tgn:7190558",
        "tgn:7003669",
        "tgn:1000003",
        "tgn:7000084",
        "tgn:7029392"
    ],
    "tgn:id":7190558,
    "tgn:name":"Feichel Berg",
    "tgn:placetype":[
        "aat:300008777"
    ]
},
  "bbox": [],
  "geometry": {"coordinates":[11.283333,48.383333],"type":"Point"}
}