<<<<<<< HEAD
{
  "id": 7470129,
  "type": "Feature",
  "properties": {
    "tgn:hierarchy":[
        "tgn:7470129",
        "tgn:7001004",
        "tgn:1000004",
        "tgn:1000141",
        "tgn:7029392"
    ],
    "tgn:id":7470129,
    "tgn:name":"Qinhecun",
    "tgn:placetype":[
        "aat:300008347"
    ]
},
  "bbox": [],
  "geometry": {"coordinates":[120.775278,23.171389],"type":"Point"}
}
=======
{"geometry":{"type":"Point","coordinates":[120.775278,23.171389]},"type":"Feature","properties":{"hierarchy":["tgn:7470129","tgn:7001004","tgn:1000004","tgn:1000141","tgn:7029392"],"placetype":["aat:300008347"],"id":7470129,"name:xx":"Qinhecun"}}
>>>>>>> 03f74aca74312dbeaf24d7e61306dd6a786dc3d0
