{
  "id": 1140141,
  "type": "Feature",
  "properties": {
    "tgn:hierarchy":[
        "tgn:1140141",
        "tgn:1000004",
        "tgn:7000198",
        "tgn:7016788",
        "tgn:7029392"
    ],
    "tgn:id":1140141,
    "tgn:name:en":"Gang\u0101pur",
    "tgn:placetype":[
        "aat:300008347"
    ]
},
  "bbox": [],
  "geometry": {"coordinates":[74.262004,25.218386],"type":"Point"}
}