{
  "id": 2490587,
  "type": "Feature",
  "properties": {
    "tgn:hierarchy":[
        "tgn:2490587",
        "tgn:1000001",
        "tgn:7012149",
        "tgn:2002189",
        "tgn:7007919",
        "tgn:7029392"
    ],
    "tgn:id":2490587,
    "tgn:name":"Mann Cave",
    "tgn:placetype":[
        "aat:300008746"
    ]
},
  "bbox": [],
  "geometry": {"coordinates":[-82.5667,36.8167],"type":"Point"}
}