{
  "id": 2422361,
  "type": "Feature",
  "properties": {
    "tgn:hierarchy":[
        "tgn:2422361",
        "tgn:7006450",
        "tgn:1000001",
        "tgn:7012149",
        "tgn:2000089",
        "tgn:7029392"
    ],
    "tgn:id":2422361,
    "tgn:name":"Jimmy Island",
    "tgn:placetype":[
        "aat:300008791"
    ]
},
  "bbox": [],
  "geometry": {"coordinates":[-157.0333,64.7833],"type":"Point"}
}