{
  "id": 7108354,
  "type": "Feature",
  "properties": {
    "tgn:hierarchy":[
        "tgn:7108354",
        "tgn:1000003",
        "tgn:7003689",
        "tgn:7000084",
        "tgn:7029392"
    ],
    "tgn:id":7108354,
    "tgn:name":"Ruine Rabiswald",
    "tgn:placetype":[
        "aat:300008057"
    ]
},
  "bbox": [],
  "geometry": {"coordinates":[11.366667,51.25],"type":"Point"}
}