{
  "id": 2670231,
  "type": "Feature",
  "properties": {
    "tgn:hierarchy":[
        "tgn:2670231",
        "tgn:1000001",
        "tgn:7012149",
        "tgn:2002248",
        "tgn:7007920",
        "tgn:7029392"
    ],
    "tgn:id":2670231,
    "tgn:name":"Slumber Peak",
    "tgn:placetype":[
        "aat:300008798"
    ]
},
  "bbox": [],
  "geometry": {"coordinates":[-117.2833,48.95],"type":"Point"}
}