{
  "id": 2060024,
  "type": "Feature",
  "properties": {
    "tgn:hierarchy":[
        "tgn:2060024",
        "tgn:1000001",
        "tgn:7012149",
        "tgn:1002384",
        "tgn:7007523",
        "tgn:7029392"
    ],
    "tgn:id":2060024,
    "tgn:name":"Pacific",
    "tgn:placetype":[
        "aat:300008347"
    ]
},
  "bbox": [],
  "geometry": {"coordinates":[-90.7333,38.4667],"type":"Point"}
}