{
  "id": 7229049,
  "type": "Feature",
  "properties": {
    "tgn:hierarchy":[
        "tgn:7229049",
        "tgn:4003773",
        "tgn:7001395",
        "tgn:1000003",
        "tgn:1000074",
        "tgn:7029392"
    ],
    "tgn:id":7229049,
    "tgn:name":"Kl\u00e1vsion",
    "tgn:placetype":[
        "aat:300008347"
    ]
},
  "bbox": [],
  "geometry": {"coordinates":[21.766667,38.866667],"type":"Point"}
}