<<<<<<< HEAD
{
  "id": 7479916,
  "type": "Feature",
  "properties": {
    "tgn:hierarchy":[
        "tgn:7479916",
        "tgn:7468018",
        "tgn:1000004",
        "tgn:1000141",
        "tgn:7029392"
    ],
    "tgn:id":7479916,
    "tgn:name":"Renhe Qiao",
    "tgn:placetype":[
        "aat:300007836"
    ]
},
  "bbox": [],
  "geometry": {"coordinates":[120.285,23.472222],"type":"Point"}
}
=======
{"geometry":{"type":"Point","coordinates":[120.285000,23.472222]},"type":"Feature","properties":{"hierarchy":["tgn:7479916","tgn:7468018","tgn:1000004","tgn:1000141","tgn:7029392"],"placetype":["aat:300007836"],"id":7479916,"name:xx":"Renhe Qiao"}}
>>>>>>> 03f74aca74312dbeaf24d7e61306dd6a786dc3d0
