{
  "id": 7329911,
  "type": "Feature",
  "properties": {
    "tgn:hierarchy":[
        "tgn:7329911",
        "tgn:7002758",
        "tgn:1001316",
        "tgn:1000003",
        "tgn:1000095",
        "tgn:7029392"
    ],
    "tgn:id":7329911,
    "tgn:name":"Humilladero",
    "tgn:placetype":[
        "aat:300008777"
    ]
},
  "bbox": [],
  "geometry": {"coordinates":[-4.05,38.233333],"type":"Point"}
}