{
  "id": 1090932,
  "type": "Feature",
  "properties": {
    "tgn:hierarchy":[
        "tgn:1090932",
        "tgn:7001242",
        "tgn:1001405",
        "tgn:1000173",
        "tgn:7029392"
    ],
    "tgn:id":1090932,
    "tgn:name":"Mahabe",
    "tgn:placetype":[
        "aat:300008347"
    ]
},
  "bbox": [],
  "geometry": {"coordinates":[45.3333,-17.0333],"type":"Point"}
}