{
  "id": 2436379,
  "type": "Feature",
  "properties": {
    "tgn:hierarchy":[
        "tgn:2436379",
        "tgn:1000001",
        "tgn:7012149",
        "tgn:7007515",
        "tgn:7029392"
    ],
    "tgn:id":2436379,
    "tgn:name":"Kibby Stream",
    "tgn:placetype":[
        "aat:300008699"
    ]
},
  "bbox": [],
  "geometry": {"coordinates":[-70.6167,45.3833],"type":"Point"}
}