{
  "id": 2010431,
  "type": "Feature",
  "properties": {
    "tgn:hierarchy":[
        "tgn:2010431",
        "tgn:1000001",
        "tgn:1002219",
        "tgn:7012149",
        "tgn:7007157",
        "tgn:7029392"
    ],
    "tgn:id":2010431,
    "tgn:name":"Burson",
    "tgn:placetype":[
        "aat:300008347"
    ]
},
  "bbox": [],
  "geometry": {"coordinates":[-120.8833,38.1833],"type":"Point"}
}