{
  "id": 2529758,
  "type": "Feature",
  "properties": {
    "tgn:hierarchy":[
        "tgn:2529758",
        "tgn:1000001",
        "tgn:7012149",
        "tgn:2000930",
        "tgn:7007515",
        "tgn:7029392"
    ],
    "tgn:id":2529758,
    "tgn:name":"Mud Pond",
    "tgn:placetype":[
        "aat:300008680"
    ]
},
  "bbox": [],
  "geometry": {"coordinates":[-69.5333,44.75],"type":"Point"}
}