{
  "id": 2676265,
  "type": "Feature",
  "properties": {
    "tgn:hierarchy":[
        "tgn:2676265",
        "tgn:1000001",
        "tgn:7012149",
        "tgn:2001614",
        "tgn:7007706",
        "tgn:7029392"
    ],
    "tgn:id":2676265,
    "tgn:name":"Sour Run",
    "tgn:placetype":[
        "aat:300008699"
    ]
},
  "bbox": [],
  "geometry": {"coordinates":[-82.65,39.15],"type":"Point"}
}