{
  "id": 7593937,
  "type": "Feature",
  "properties": {
    "tgn:hierarchy":[
        "tgn:7593937",
        "tgn:7005361",
        "tgn:7005346",
        "tgn:1000001",
        "tgn:7029392"
    ],
    "tgn:id":7593937,
    "tgn:name":"Chan Chen",
    "tgn:placetype":[
        "aat:300008347",
        "aat:300008372"
    ]
},
  "bbox": [],
  "geometry": {"coordinates":[-88.416667,18.433333],"type":"Point"}
}