{
  "id": 2309122,
  "type": "Feature",
  "properties": {
    "tgn:hierarchy":[
        "tgn:2309122",
        "tgn:1000001",
        "tgn:7012149",
        "tgn:2001029",
        "tgn:7007521",
        "tgn:7029392"
    ],
    "tgn:id":2309122,
    "tgn:name":"East Seelye Bay",
    "tgn:placetype":[
        "aat:300132316"
    ]
},
  "bbox": [],
  "geometry": {"coordinates":[-94.0833,47.5167],"type":"Point"}
}