{
  "id": 2673017,
  "type": "Feature",
  "properties": {
    "tgn:hierarchy":[
        "tgn:2673017",
        "tgn:1000001",
        "tgn:7012149",
        "tgn:1002810",
        "tgn:7007568",
        "tgn:7029392"
    ],
    "tgn:id":2673017,
    "tgn:name":"Snake Hill",
    "tgn:placetype":[
        "aat:300008798"
    ]
},
  "bbox": [],
  "geometry": {"coordinates":[-73.5667,41.4167],"type":"Point"}
}