<<<<<<< HEAD
{
  "id": 2337026,
  "type": "Feature",
  "properties": {
    "tgn:hierarchy":[
        "tgn:2337026",
        "tgn:7006450",
        "tgn:1000001",
        "tgn:7012149",
        "tgn:2000089",
        "tgn:7029392"
    ],
    "tgn:id":2337026,
    "tgn:name":"Fourmile Lake",
    "tgn:placetype":[
        "aat:300008680"
    ]
},
  "bbox": [],
  "geometry": {"coordinates":[-154.45,63.0167],"type":"Point"}
}
=======
{"geometry":{"type":"Point","coordinates":[-154.450000,63.016700]},"type":"Feature","properties":{"hierarchy":["tgn:2337026","tgn:7006450","tgn:1000001","tgn:7012149","tgn:2000089","tgn:7029392"],"placetype":["aat:300008680"],"id":2337026,"name:xx":"Fourmile Lake"}}
>>>>>>> 03f74aca74312dbeaf24d7e61306dd6a786dc3d0
