{
  "id": 1138345,
  "type": "Feature",
  "properties": {
    "tgn:hierarchy":[
        "tgn:1138345",
        "tgn:4000818",
        "tgn:1000004",
        "tgn:7018214",
        "tgn:7002435",
        "tgn:7029392"
    ],
    "tgn:id":1138345,
    "tgn:name":"Safonovo",
    "tgn:placetype":[
        "aat:300008347"
    ]
},
  "bbox": [],
  "geometry": {"coordinates":[47.7333,65.7167],"type":"Point"}
}