{
  "id": 2400156,
  "type": "Feature",
  "properties": {
    "tgn:hierarchy":[
        "tgn:2400156",
        "tgn:1000001",
        "tgn:7012149",
        "tgn:2001706",
        "tgn:7007708",
        "tgn:7029392"
    ],
    "tgn:id":2400156,
    "tgn:name":"Horse Creek",
    "tgn:placetype":[
        "aat:300008706"
    ]
},
  "bbox": [],
  "geometry": {"coordinates":[-122.4333,43.1167],"type":"Point"}
}