<<<<<<< HEAD
{
  "id": 2400156,
  "type": "Feature",
  "properties": {
    "tgn:hierarchy":[
        "tgn:2400156",
        "tgn:1000001",
        "tgn:7012149",
        "tgn:2001706",
        "tgn:7007708",
        "tgn:7029392"
    ],
    "tgn:id":2400156,
    "tgn:name":"Horse Creek",
    "tgn:placetype":[
        "aat:300008706"
    ]
},
  "bbox": [],
  "geometry": {"coordinates":[-122.4333,43.1167],"type":"Point"}
}
=======
{"geometry":{"type":"Point","coordinates":[-122.433300,43.116700]},"type":"Feature","properties":{"hierarchy":["tgn:2400156","tgn:1000001","tgn:7012149","tgn:2001706","tgn:7007708","tgn:7029392"],"placetype":["aat:300008706"],"id":2400156,"name:xx":"Horse Creek"}}
>>>>>>> 03f74aca74312dbeaf24d7e61306dd6a786dc3d0
