<<<<<<< HEAD
{
  "id": 7488900,
  "type": "Feature",
  "properties": {
    "tgn:hierarchy":[
        "tgn:7488900",
        "tgn:1000004",
        "tgn:7004300",
        "tgn:1000141",
        "tgn:7029392"
    ],
    "tgn:id":7488900,
    "tgn:name":"Hudong",
    "tgn:placetype":[
        "aat:300008347"
    ]
},
  "bbox": [],
  "geometry": {"coordinates":[119.662464,23.581917],"type":"Point"}
}
=======
{"geometry":{"type":"Point","coordinates":[119.662464,23.581917]},"type":"Feature","properties":{"hierarchy":["tgn:7488900","tgn:1000004","tgn:7004300","tgn:1000141","tgn:7029392"],"placetype":["aat:300008347"],"id":7488900,"name:xx":"Hudong"}}
>>>>>>> 03f74aca74312dbeaf24d7e61306dd6a786dc3d0
