{
  "id": 7409992,
  "type": "Feature",
  "properties": {
    "tgn:hierarchy":[
        "tgn:7409992",
        "tgn:7005580",
        "tgn:1000001",
        "tgn:7005560",
        "tgn:7029392"
    ],
    "tgn:id":7409992,
    "tgn:name":"Buenavista, Estero",
    "tgn:placetype":[
        "aat:300185707"
    ]
},
  "bbox": [],
  "geometry": {"coordinates":[-93.083333,15.466667],"type":"Point"}
}