{
  "id": 2298059,
  "type": "Feature",
  "properties": {
    "tgn:hierarchy":[
        "tgn:2298059",
        "tgn:1000001",
        "tgn:2001419",
        "tgn:7012149",
        "tgn:7007526",
        "tgn:7029392"
    ],
    "tgn:id":2298059,
    "tgn:name":"Dry Lake",
    "tgn:placetype":[
        "aat:300055621"
    ]
},
  "bbox": [],
  "geometry": {"coordinates":[-119.0667,40.3833],"type":"Point"}
}