{
  "id": 1010944,
  "type": "Feature",
  "properties": {
    "tgn:hierarchy":[
        "tgn:1010944",
        "tgn:1000007",
        "tgn:7029392"
    ],
    "tgn:id":1010944,
    "tgn:name":"Mikhaylov, Cape",
    "tgn:placetype":[
        "aat:300008850"
    ]
},
  "bbox": [],
  "geometry": {"coordinates":[118.55,-66.85],"type":"Point"}
}