<<<<<<< HEAD
{
  "id": 2259849,
  "type": "Feature",
  "properties": {
    "tgn:hierarchy":[
        "tgn:2259849",
        "tgn:1000001",
        "tgn:7012149",
        "tgn:2000891",
        "tgn:7007256",
        "tgn:7029392"
    ],
    "tgn:id":2259849,
    "tgn:name":"Coule Pond",
    "tgn:placetype":[
        "aat:300132316"
    ]
},
  "bbox": [],
  "geometry": {"coordinates":[-89.2167,29.1833],"type":"Point"}
}
=======
{"geometry":{"type":"Point","coordinates":[-89.216700,29.183300]},"type":"Feature","properties":{"hierarchy":["tgn:2259849","tgn:1000001","tgn:7012149","tgn:2000891","tgn:7007256","tgn:7029392"],"placetype":["aat:300132316"],"id":2259849,"name:xx":"Coule Pond"}}
>>>>>>> 03f74aca74312dbeaf24d7e61306dd6a786dc3d0
