{
  "id": 2549745,
  "type": "Feature",
  "properties": {
    "tgn:hierarchy":[
        "tgn:2549745",
        "tgn:1000001",
        "tgn:7012149",
        "tgn:2002055",
        "tgn:7007826",
        "tgn:7029392"
    ],
    "tgn:id":2549745,
    "tgn:name":"North Tank",
    "tgn:placetype":[
        "aat:300006191"
    ]
},
  "bbox": [],
  "geometry": {"coordinates":[-103.2167,30.5167],"type":"Point"}
}