<<<<<<< HEAD
{
  "id": 2251530,
  "type": "Feature",
  "properties": {
    "tgn:hierarchy":[
        "tgn:2251530",
        "tgn:1000001",
        "tgn:1002923",
        "tgn:7012149",
        "tgn:7007517",
        "tgn:7029392"
    ],
    "tgn:id":2251530,
    "tgn:name":"Commissioners Ledge",
    "tgn:placetype":[
        "aat:300011692"
    ]
},
  "bbox": [],
  "geometry": {"coordinates":[-70.9,42.35],"type":"Point"}
}
=======
{"geometry":{"type":"Point","coordinates":[-70.900000,42.350000]},"type":"Feature","properties":{"hierarchy":["tgn:2251530","tgn:1000001","tgn:1002923","tgn:7012149","tgn:7007517","tgn:7029392"],"placetype":["aat:300011692"],"id":2251530,"name:xx":"Commissioners Ledge"}}
>>>>>>> 03f74aca74312dbeaf24d7e61306dd6a786dc3d0
