<<<<<<< HEAD
{
  "id": 7055205,
  "type": "Feature",
  "properties": {
    "tgn:hierarchy":[
        "tgn:7055205",
        "tgn:7003131",
        "tgn:1000003",
        "tgn:7008516",
        "tgn:1000080",
        "tgn:7029392"
    ],
    "tgn:id":7055205,
    "tgn:name":"Osacca",
    "tgn:placetype":[
        "aat:300008347"
    ]
},
  "bbox": [],
  "geometry": {"coordinates":[9.75,44.55],"type":"Point"}
}
=======
{"geometry":{"type":"Point","coordinates":[9.750000,44.550000]},"type":"Feature","properties":{"hierarchy":["tgn:7055205","tgn:7003131","tgn:1000003","tgn:7008516","tgn:1000080","tgn:7029392"],"placetype":["aat:300008347"],"id":7055205,"name:xx":"Osacca"}}
>>>>>>> 03f74aca74312dbeaf24d7e61306dd6a786dc3d0
