{
  "id": 7537606,
  "type": "Feature",
  "properties": {
    "tgn:hierarchy":[
        "tgn:7537606",
        "tgn:7001242",
        "tgn:7016833",
        "tgn:1001225",
        "tgn:7029392"
    ],
    "tgn:id":7537606,
    "tgn:name:en":"Raml, Barr ar",
    "tgn:placetype":[
        "aat:300008791"
    ]
},
  "bbox": [],
  "geometry": {"coordinates":[31.905905,31.400386],"type":"Point"}
}