{
  "id": 2415137,
  "type": "Feature",
  "properties": {
    "tgn:hierarchy":[
        "tgn:2415137",
        "tgn:1000001",
        "tgn:7012149",
        "tgn:2001508",
        "tgn:7007709",
        "tgn:7029392"
    ],
    "tgn:id":2415137,
    "tgn:name":"Island Ford",
    "tgn:placetype":[
        "aat:300008347"
    ]
},
  "bbox": [],
  "geometry": {"coordinates":[-83.0333,35.2167],"type":"Point"}
}