<<<<<<< HEAD
{
  "id": 7361233,
  "type": "Feature",
  "properties": {
    "tgn:hierarchy":[
        "tgn:7361233",
        "tgn:1000001",
        "tgn:7005595",
        "tgn:7005560",
        "tgn:7029392"
    ],
    "tgn:id":7361233,
    "tgn:name":"El Caim\u00e1n del Otro Lado",
    "tgn:placetype":[
        "aat:300008347"
    ]
},
  "bbox": [],
  "geometry": {"coordinates":[-108.316667,25.866667],"type":"Point"}
}
=======
{"geometry":{"type":"Point","coordinates":[-108.316667,25.866667]},"type":"Feature","properties":{"hierarchy":["tgn:7361233","tgn:1000001","tgn:7005595","tgn:7005560","tgn:7029392"],"placetype":["aat:300008347"],"id":7361233,"name:xx":"El Caim\u00e1n del Otro Lado"}}
>>>>>>> 03f74aca74312dbeaf24d7e61306dd6a786dc3d0
