{
  "id": 7389294,
  "type": "Feature",
  "properties": {
    "tgn:hierarchy":[
        "tgn:7389294",
        "tgn:1001853",
        "tgn:1000001",
        "tgn:7005560",
        "tgn:7029392"
    ],
    "tgn:id":7389294,
    "tgn:name":"Rancho El Porvenir",
    "tgn:placetype":[
        "aat:300008347"
    ]
},
  "bbox": [],
  "geometry": {"coordinates":[-101.516667,24.816667],"type":"Point"}
}