{
  "id": 2449159,
  "type": "Feature",
  "properties": {
    "tgn:hierarchy":[
        "tgn:2449159",
        "tgn:1000001",
        "tgn:7012149",
        "tgn:2002043",
        "tgn:7007826",
        "tgn:7029392"
    ],
    "tgn:id":2449159,
    "tgn:name":"Limekin Tank",
    "tgn:placetype":[
        "aat:300006191"
    ]
},
  "bbox": [],
  "geometry": {"coordinates":[-100.95,32.0833],"type":"Point"}
}