{
  "id": 2520383,
  "type": "Feature",
  "properties": {
    "tgn:hierarchy":[
        "tgn:2520383",
        "tgn:1000001",
        "tgn:7012149",
        "tgn:2002371",
        "tgn:7007923",
        "tgn:7029392"
    ],
    "tgn:id":2520383,
    "tgn:name":"Moneta Divide",
    "tgn:placetype":[
        "aat:300266640"
    ]
},
  "bbox": [],
  "geometry": {"coordinates":[-107.7167,43.0333],"type":"Point"}
}