{
  "id": 2190264,
  "type": "Feature",
  "properties": {
    "tgn:hierarchy":[
        "tgn:2190264",
        "tgn:1000001",
        "tgn:2001338",
        "tgn:7012149",
        "tgn:7007525",
        "tgn:7029392"
    ],
    "tgn:id":2190264,
    "tgn:name":"Box Butte Reservoir",
    "tgn:placetype":[
        "aat:300006191"
    ]
},
  "bbox": [],
  "geometry": {"coordinates":[-103.0667,42.45],"type":"Point"}
}