{
  "id": 2535133,
  "type": "Feature",
  "properties": {
    "tgn:hierarchy":[
        "tgn:2535133",
        "tgn:1000001",
        "tgn:7012149",
        "tgn:2002304",
        "tgn:7013961",
        "tgn:7029392"
    ],
    "tgn:id":2535133,
    "tgn:name":"Nancy Fork",
    "tgn:placetype":[
        "aat:300008699"
    ]
},
  "bbox": [],
  "geometry": {"coordinates":[-81.55,37.5167],"type":"Point"}
}