{
  "id": 2309001,
  "type": "Feature",
  "properties": {
    "tgn:hierarchy":[
        "tgn:2309001",
        "tgn:1000001",
        "tgn:7012149",
        "tgn:2002373",
        "tgn:7007923",
        "tgn:7029392"
    ],
    "tgn:id":2309001,
    "tgn:name":"East Ridge",
    "tgn:placetype":[
        "aat:300266640"
    ]
},
  "bbox": [],
  "geometry": {"coordinates":[-108.4667,44.0667],"type":"Point"}
}