{
  "id": 1011800,
  "type": "Feature",
  "properties": {
    "tgn:hierarchy":[
        "tgn:1011800",
        "tgn:7005332",
        "tgn:1008328",
        "tgn:1000001",
        "tgn:7029392"
    ],
    "tgn:id":1011800,
    "tgn:name":"Delaport Point",
    "tgn:placetype":[
        "aat:300386846"
    ]
},
  "bbox": [],
  "geometry": {"coordinates":[-77.45,25.0833],"type":"Point"}
}