{
  "id": 2750176,
  "type": "Feature",
  "properties": {
    "tgn:hierarchy":[
        "tgn:2750176",
        "tgn:1000001",
        "tgn:7012149",
        "tgn:1002454",
        "tgn:7007826",
        "tgn:7029392"
    ],
    "tgn:id":2750176,
    "tgn:name":"Walton Creek",
    "tgn:placetype":[
        "aat:300008706"
    ]
},
  "bbox": [],
  "geometry": {"coordinates":[-94.2167,30.2833],"type":"Point"}
}