{
  "id": 7105206,
  "type": "Feature",
  "properties": {
    "tgn:hierarchy":[
        "tgn:7105206",
        "tgn:7003669",
        "tgn:1000003",
        "tgn:7000084",
        "tgn:7029392"
    ],
    "tgn:id":7105206,
    "tgn:name":"Schlo\u00dfbauer",
    "tgn:placetype":[
        "aat:300000206"
    ]
},
  "bbox": [],
  "geometry": {"coordinates":[10.333333,47.933333],"type":"Point"}
}