{
  "id": 2517986,
  "type": "Feature",
  "properties": {
    "tgn:hierarchy":[
        "tgn:2517986",
        "tgn:1000001",
        "tgn:7012149",
        "tgn:2000471",
        "tgn:7007250",
        "tgn:7029392"
    ],
    "tgn:id":2517986,
    "tgn:name":"Misfire Creek",
    "tgn:placetype":[
        "aat:300008706"
    ]
},
  "bbox": [],
  "geometry": {"coordinates":[-115.0667,43.8667],"type":"Point"}
}