{
  "id": 7564028,
  "type": "Feature",
  "properties": {
    "tgn:hierarchy":[
        "tgn:7564028",
        "tgn:1000004",
        "tgn:7000198",
        "tgn:7016722",
        "tgn:7029392"
    ],
    "tgn:id":7564028,
    "tgn:name:en":"Kandri",
    "tgn:placetype":[
        "aat:300008347"
    ]
},
  "bbox": [],
  "geometry": {"coordinates":[79.983609,26.561576],"type":"Point"}
}