{
  "id": 2597380,
  "type": "Feature",
  "properties": {
    "tgn:hierarchy":[
        "tgn:2597380",
        "tgn:1000001",
        "tgn:2002367",
        "tgn:7012149",
        "tgn:7007923",
        "tgn:7029392"
    ],
    "tgn:id":2597380,
    "tgn:name":"Prairie Creek",
    "tgn:placetype":[
        "aat:300008706"
    ]
},
  "bbox": [],
  "geometry": {"coordinates":[-105.3833,44.3333],"type":"Point"}
}