<<<<<<< HEAD
{
  "id": 2152431,
  "type": "Feature",
  "properties": {
    "tgn:hierarchy":[
        "tgn:2152431",
        "tgn:1000001",
        "tgn:7012149",
        "tgn:1002761",
        "tgn:7007706",
        "tgn:7029392"
    ],
    "tgn:id":2152431,
    "tgn:name":"Bay Point Shoal",
    "tgn:placetype":[
        "aat:300132348"
    ]
},
  "bbox": [],
  "geometry": {"coordinates":[-82.6833,41.5],"type":"Point"}
}
=======
{"geometry":{"type":"Point","coordinates":[-82.683300,41.500000]},"type":"Feature","properties":{"hierarchy":["tgn:2152431","tgn:1000001","tgn:7012149","tgn:1002761","tgn:7007706","tgn:7029392"],"placetype":["aat:300132348"],"id":2152431,"name:xx":"Bay Point Shoal"}}
>>>>>>> 03f74aca74312dbeaf24d7e61306dd6a786dc3d0
