{
  "id": 7132750,
  "type": "Feature",
  "properties": {
    "tgn:hierarchy":[
        "tgn:7132750",
        "tgn:7000096",
        "tgn:1000003",
        "tgn:7000084",
        "tgn:7029392"
    ],
    "tgn:id":7132750,
    "tgn:name":"Mildenberg",
    "tgn:placetype":[
        "aat:300008347"
    ]
},
  "bbox": [],
  "geometry": {"coordinates":[13.283333,53.016667],"type":"Point"}
}