{
  "id": 2620986,
  "type": "Feature",
  "properties": {
    "tgn:hierarchy":[
        "tgn:2620986",
        "tgn:1000001",
        "tgn:2001429",
        "tgn:7012149",
        "tgn:7007566",
        "tgn:7029392"
    ],
    "tgn:id":2620986,
    "tgn:name":"Road Canyon Tank",
    "tgn:placetype":[
        "aat:300006191"
    ]
},
  "bbox": [],
  "geometry": {"coordinates":[-108.05,33.2667],"type":"Point"}
}