{
  "id": 7504521,
  "type": "Feature",
  "properties": {
    "tgn:hierarchy":[
        "tgn:7504521",
        "tgn:1009227",
        "tgn:1000226",
        "tgn:1000006",
        "tgn:7016850",
        "tgn:7029392"
    ],
    "tgn:id":7504521,
    "tgn:name:en":"Cook Bluff",
    "tgn:placetype":[
        "aat:300008749"
    ]
},
  "bbox": [],
  "geometry": {"coordinates":[169.766111,-43.448889],"type":"Point"}
}