{
  "id": 2417781,
  "type": "Feature",
  "properties": {
    "tgn:hierarchy":[
        "tgn:2417781",
        "tgn:1000001",
        "tgn:7012149",
        "tgn:2000931",
        "tgn:7007515",
        "tgn:7029392"
    ],
    "tgn:id":2417781,
    "tgn:name":"Jackson Hill",
    "tgn:placetype":[
        "aat:300008798"
    ]
},
  "bbox": [],
  "geometry": {"coordinates":[-68.9667,44.3167],"type":"Point"}
}