{
  "id": 7220071,
  "type": "Feature",
  "properties": {
    "tgn:hierarchy":[
        "tgn:7220071",
        "tgn:7002690",
        "tgn:7012056",
        "tgn:1000003",
        "tgn:1000074",
        "tgn:7029392"
    ],
    "tgn:id":7220071,
    "tgn:name":"Velo\u00falion",
    "tgn:placetype":[
        "aat:300008347"
    ]
},
  "bbox": [],
  "geometry": {"coordinates":[25.133333,35.066667],"type":"Point"}
}