{
  "id": 2326218,
  "type": "Feature",
  "properties": {
    "tgn:hierarchy":[
        "tgn:2326218",
        "tgn:1002140",
        "tgn:1000001",
        "tgn:7012149",
        "tgn:7007520",
        "tgn:7029392"
    ],
    "tgn:id":2326218,
    "tgn:name":"Fillmore",
    "tgn:placetype":[
        "aat:300008347"
    ]
},
  "bbox": [],
  "geometry": {"coordinates":[-86.0333,42.7167],"type":"Point"}
}