{
  "id": 1095259,
  "type": "Feature",
  "properties": {
    "tgn:hierarchy":[
        "tgn:1095259",
        "tgn:7001242",
        "tgn:7001105",
        "tgn:7016833",
        "tgn:7029392"
    ],
    "tgn:id":1095259,
    "tgn:name:en":"Al Gharaq",
    "tgn:placetype":[
        "aat:300008347"
    ]
},
  "bbox": [],
  "geometry": {"coordinates":[30.700728,29.137886],"type":"Point"}
}