{
  "id": 2273353,
  "type": "Feature",
  "properties": {
    "tgn:hierarchy":[
        "tgn:2273353",
        "tgn:1000001",
        "tgn:7012149",
        "tgn:2001510",
        "tgn:7007709",
        "tgn:7029392"
    ],
    "tgn:id":2273353,
    "tgn:name":"Cypress Creek",
    "tgn:placetype":[
        "aat:300055621"
    ]
},
  "bbox": [],
  "geometry": {"coordinates":[-77.4667,35.0167],"type":"Point"}
}