<<<<<<< HEAD
{
  "id": 2766772,
  "type": "Feature",
  "properties": {
    "tgn:hierarchy":[
        "tgn:2766772",
        "tgn:1000001",
        "tgn:7012149",
        "tgn:7007157",
        "tgn:1002858",
        "tgn:7029392"
    ],
    "tgn:id":2766772,
    "tgn:name":"White Oak Springs",
    "tgn:placetype":[
        "aat:300008697"
    ]
},
  "bbox": [],
  "geometry": {"coordinates":[-117.4667,33.4833],"type":"Point"}
}
=======
{"geometry":{"type":"Point","coordinates":[-117.466700,33.483300]},"type":"Feature","properties":{"hierarchy":["tgn:2766772","tgn:1000001","tgn:7012149","tgn:7007157","tgn:1002858","tgn:7029392"],"placetype":["aat:300008697"],"id":2766772,"name:xx":"White Oak Springs"}}
>>>>>>> 03f74aca74312dbeaf24d7e61306dd6a786dc3d0
