{
  "id": 7311095,
  "type": "Feature",
  "properties": {
    "tgn:hierarchy":[
        "tgn:7311095",
        "tgn:1001695",
        "tgn:1000049",
        "tgn:1000002",
        "tgn:7029392"
    ],
    "tgn:id":7311095,
    "tgn:name":"Negro, Cerro",
    "tgn:placetype":[
        "aat:300008795"
    ]
},
  "bbox": [],
  "geometry": {"coordinates":[-70.883333,-34.266667],"type":"Point"}
}