{
  "id": 1075173,
  "type": "Feature",
  "properties": {
    "tgn:hierarchy":[
        "tgn:1075173",
        "tgn:1000004",
        "tgn:7000198",
        "tgn:1001996",
        "tgn:7029392"
    ],
    "tgn:id":1075173,
    "tgn:name":"Dharmsala",
    "tgn:placetype":[
        "aat:300008347"
    ]
},
  "bbox": [],
  "geometry": {"coordinates":[76.322687,32.208256],"type":"Point"}
}