{
  "id": 1050783,
  "type": "Feature",
  "properties": {
    "tgn:hierarchy":[
        "tgn:1050783",
        "tgn:7002444",
        "tgn:1000003",
        "tgn:7008094",
        "tgn:1009238",
        "tgn:7008591",
        "tgn:7029392"
    ],
    "tgn:id":1050783,
    "tgn:name":"Kilbride",
    "tgn:placetype":[
        "aat:300008347"
    ]
},
  "bbox": [],
  "geometry": {"coordinates":[-7.45,57.0833],"type":"Point"}
}