{
  "id": 7275030,
  "type": "Feature",
  "properties": {
    "tgn:hierarchy":[
        "tgn:7275030",
        "tgn:1001630",
        "tgn:1000049",
        "tgn:1000002",
        "tgn:7029392"
    ],
    "tgn:id":7275030,
    "tgn:name":"Zenteno, Caleta",
    "tgn:placetype":[
        "aat:300132317"
    ]
},
  "bbox": [],
  "geometry": {"coordinates":[-70.816667,-26.85],"type":"Point"}
}