<<<<<<< HEAD
{
  "id": 2251062,
  "type": "Feature",
  "properties": {
    "tgn:hierarchy":[
        "tgn:2251062",
        "tgn:1000001",
        "tgn:1002473",
        "tgn:7012149",
        "tgn:7007240",
        "tgn:7029392"
    ],
    "tgn:id":2251062,
    "tgn:name":"Colvalia Key",
    "tgn:placetype":[
        "aat:300008791"
    ]
},
  "bbox": [],
  "geometry": {"coordinates":[-82.65,28.6833],"type":"Point"}
}
=======
{"geometry":{"type":"Point","coordinates":[-82.650000,28.683300]},"type":"Feature","properties":{"hierarchy":["tgn:2251062","tgn:1000001","tgn:1002473","tgn:7012149","tgn:7007240","tgn:7029392"],"placetype":["aat:300008791"],"id":2251062,"name:xx":"Colvalia Key"}}
>>>>>>> 03f74aca74312dbeaf24d7e61306dd6a786dc3d0
