{
  "id": 2108084,
  "type": "Feature",
  "properties": {
    "tgn:hierarchy":[
        "tgn:2108084",
        "tgn:1000001",
        "tgn:7012149",
        "tgn:2002030",
        "tgn:7007826",
        "tgn:7029392"
    ],
    "tgn:id":2108084,
    "tgn:name":"Tow",
    "tgn:placetype":[
        "aat:300008347"
    ]
},
  "bbox": [],
  "geometry": {"coordinates":[-98.4667,30.8833],"type":"Point"}
}