{
  "id": 7509234,
  "type": "Feature",
  "properties": {
    "tgn:hierarchy":[
        "tgn:7509234",
        "tgn:7000509",
        "tgn:1008380",
        "tgn:1000226",
        "tgn:1000006",
        "tgn:7029392"
    ],
    "tgn:id":7509234,
    "tgn:name:en":"Tikorangi",
    "tgn:placetype":[
        "aat:300008795"
    ]
},
  "bbox": [],
  "geometry": {"coordinates":[176.733333,-38.583333],"type":"Point"}
}