{
  "id": 7288280,
  "type": "Feature",
  "properties": {
    "tgn:hierarchy":[
        "tgn:7288280",
        "tgn:1001708",
        "tgn:1000049",
        "tgn:1000002",
        "tgn:7029392"
    ],
    "tgn:id":7288280,
    "tgn:name":"La Chupalla",
    "tgn:placetype":[
        "aat:300008795"
    ]
},
  "bbox": [],
  "geometry": {"coordinates":[-70.283333,-33.733333],"type":"Point"}
}