<<<<<<< HEAD
{
  "id": 7353913,
  "type": "Feature",
  "properties": {
    "tgn:hierarchy":[
        "tgn:7353913",
        "tgn:1000001",
        "tgn:7005595",
        "tgn:7005560",
        "tgn:7029392"
    ],
    "tgn:id":7353913,
    "tgn:name":"Campo Santa Mar\u00eda",
    "tgn:placetype":[
        "aat:300008347"
    ]
},
  "bbox": [],
  "geometry": {"coordinates":[-107.633333,25.033333],"type":"Point"}
}
=======
{"geometry":{"type":"Point","coordinates":[-107.633333,25.033333]},"type":"Feature","properties":{"hierarchy":["tgn:7353913","tgn:1000001","tgn:7005595","tgn:7005560","tgn:7029392"],"placetype":["aat:300008347"],"id":7353913,"name:xx":"Campo Santa Mar\u00eda"}}
>>>>>>> 03f74aca74312dbeaf24d7e61306dd6a786dc3d0
