{
  "id": 2240163,
  "type": "Feature",
  "properties": {
    "tgn:hierarchy":[
        "tgn:2240163",
        "tgn:1000001",
        "tgn:7012149",
        "tgn:2001246",
        "tgn:7007523",
        "tgn:7029392"
    ],
    "tgn:id":2240163,
    "tgn:name":"Circle Ditch",
    "tgn:placetype":[
        "aat:300006075"
    ]
},
  "bbox": [],
  "geometry": {"coordinates":[-89.4167,37.0333],"type":"Point"}
}