{
  "id": 2384721,
  "type": "Feature",
  "properties": {
    "tgn:hierarchy":[
        "tgn:2384721",
        "tgn:1000001",
        "tgn:2001264",
        "tgn:7012149",
        "tgn:7007524",
        "tgn:7029392"
    ],
    "tgn:id":2384721,
    "tgn:name":"Hellroaring Creek",
    "tgn:placetype":[
        "aat:300008706"
    ]
},
  "bbox": [],
  "geometry": {"coordinates":[-109.5667,45.1667],"type":"Point"}
}