{
  "id": 7416696,
  "type": "Feature",
  "properties": {
    "tgn:hierarchy":[
        "tgn:7416696",
        "tgn:1000001",
        "tgn:7005591",
        "tgn:7005560",
        "tgn:7029392"
    ],
    "tgn:id":7416696,
    "tgn:name:es":"Santiago Cuixla",
    "tgn:placetype":[
        "aat:300008347"
    ]
},
  "bbox": [],
  "geometry": {"coordinates":[-97.189167,16.073611],"type":"Point"}
}