{
  "id": 7477953,
  "type": "Feature",
  "properties": {
    "tgn:hierarchy":[
        "tgn:7477953",
        "tgn:1000004",
        "tgn:7001013",
        "tgn:1000141",
        "tgn:7029392"
    ],
    "tgn:id":7477953,
    "tgn:name":"Xuexiao Pi",
    "tgn:placetype":[
        "aat:300008688"
    ]
},
  "bbox": [],
  "geometry": {"coordinates":[121.139778,25.014862],"type":"Point"}
}