{
  "id": 7106484,
  "type": "Feature",
  "properties": {
    "tgn:hierarchy":[
        "tgn:7106484",
        "tgn:1000003",
        "tgn:7003689",
        "tgn:7000084",
        "tgn:7029392"
    ],
    "tgn:id":7106484,
    "tgn:name":"Schafpreskeln",
    "tgn:placetype":[
        "aat:300008347"
    ]
},
  "bbox": [],
  "geometry": {"coordinates":[12.033333,50.833333],"type":"Point"}
}