<<<<<<< HEAD
{
  "id": 2153902,
  "type": "Feature",
  "properties": {
    "tgn:hierarchy":[
        "tgn:2153902",
        "tgn:1000001",
        "tgn:7012149",
        "tgn:2001455",
        "tgn:7007566",
        "tgn:7029392"
    ],
    "tgn:id":2153902,
    "tgn:name":"Bear Canyon Tank",
    "tgn:placetype":[
        "aat:300006191"
    ]
},
  "bbox": [],
  "geometry": {"coordinates":[-107.6833,33.1333],"type":"Point"}
}
=======
{"geometry":{"type":"Point","coordinates":[-107.683300,33.133300]},"type":"Feature","properties":{"hierarchy":["tgn:2153902","tgn:1000001","tgn:7012149","tgn:2001455","tgn:7007566","tgn:7029392"],"placetype":["aat:300006191"],"id":2153902,"name:xx":"Bear Canyon Tank"}}
>>>>>>> 03f74aca74312dbeaf24d7e61306dd6a786dc3d0
