{
  "id": 2153902,
  "type": "Feature",
  "properties": {
    "tgn:hierarchy":[
        "tgn:2153902",
        "tgn:1000001",
        "tgn:7012149",
        "tgn:2001455",
        "tgn:7007566",
        "tgn:7029392"
    ],
    "tgn:id":2153902,
    "tgn:name":"Bear Canyon Tank",
    "tgn:placetype":[
        "aat:300006191"
    ]
},
  "bbox": [],
  "geometry": {"coordinates":[-107.6833,33.1333],"type":"Point"}
}