{
  "id": 1054248,
  "type": "Feature",
  "properties": {
    "tgn:hierarchy":[
        "tgn:1054248",
        "tgn:1003361",
        "tgn:1000003",
        "tgn:7006660",
        "tgn:7029392"
    ],
    "tgn:id":1054248,
    "tgn:name":"Guty",
    "tgn:placetype":[
        "aat:300008347"
    ]
},
  "bbox": [],
  "geometry": {"coordinates":[35.35,50.1167],"type":"Point"}
}