{
  "id": 2619119,
  "type": "Feature",
  "properties": {
    "tgn:hierarchy":[
        "tgn:2619119",
        "tgn:7002659",
        "tgn:1000001",
        "tgn:7012149",
        "tgn:7029392"
    ],
    "tgn:id":2619119,
    "tgn:name":"Riley Creek",
    "tgn:placetype":[
        "aat:300008706"
    ]
},
  "bbox": [],
  "geometry": {"coordinates":[-85.4167,31.5333],"type":"Point"}
}