{
  "id": 2301254,
  "type": "Feature",
  "properties": {
    "tgn:hierarchy":[
        "tgn:2301254",
        "tgn:1000001",
        "tgn:7012149",
        "tgn:1002636",
        "tgn:7007708",
        "tgn:7029392"
    ],
    "tgn:id":2301254,
    "tgn:name":"Dunlap Lake",
    "tgn:placetype":[
        "aat:300008680"
    ]
},
  "bbox": [],
  "geometry": {"coordinates":[-122.0833,44.8167],"type":"Point"}
}