{
  "id": 7589062,
  "type": "Feature",
  "properties": {
    "tgn:hierarchy":[
        "tgn:7589062",
        "tgn:1000004",
        "tgn:1001869",
        "tgn:7000198",
        "tgn:7029392"
    ],
    "tgn:id":7589062,
    "tgn:name:en":"B\u0101kuri",
    "tgn:placetype":[
        "aat:300008347"
    ]
},
  "bbox": [],
  "geometry": {"coordinates":[69.343335,22.031727],"type":"Point"}
}