<<<<<<< HEAD
{
  "id": 7177352,
  "type": "Feature",
  "properties": {
    "tgn:hierarchy":[
        "tgn:7177352",
        "tgn:7003669",
        "tgn:1000003",
        "tgn:7000084",
        "tgn:7029392"
    ],
    "tgn:id":7177352,
    "tgn:name":"H\u00e4ldele",
    "tgn:placetype":[
        "aat:300000206"
    ]
},
  "bbox": [],
  "geometry": {"coordinates":[10.166667,47.8],"type":"Point"}
}
=======
{"geometry":{"type":"Point","coordinates":[10.166667,47.800000]},"type":"Feature","properties":{"hierarchy":["tgn:7177352","tgn:7003669","tgn:1000003","tgn:7000084","tgn:7029392"],"placetype":["aat:300000206"],"id":7177352,"name:xx":"H\u00e4ldele"}}
>>>>>>> 03f74aca74312dbeaf24d7e61306dd6a786dc3d0
