<<<<<<< HEAD
{
  "id": 2254938,
  "type": "Feature",
  "properties": {
    "tgn:hierarchy":[
        "tgn:2254938",
        "tgn:1000001",
        "tgn:7012149",
        "tgn:2000550",
        "tgn:7007252",
        "tgn:7029392"
    ],
    "tgn:id":2254938,
    "tgn:name":"Cooper Branch",
    "tgn:placetype":[
        "aat:300008699"
    ]
},
  "bbox": [],
  "geometry": {"coordinates":[-86.7167,38.0167],"type":"Point"}
}
=======
{"geometry":{"type":"Point","coordinates":[-86.716700,38.016700]},"type":"Feature","properties":{"hierarchy":["tgn:2254938","tgn:1000001","tgn:7012149","tgn:2000550","tgn:7007252","tgn:7029392"],"placetype":["aat:300008699"],"id":2254938,"name:xx":"Cooper Branch"}}
>>>>>>> 03f74aca74312dbeaf24d7e61306dd6a786dc3d0
