{
  "id": 2254938,
  "type": "Feature",
  "properties": {
    "tgn:hierarchy":[
        "tgn:2254938",
        "tgn:1000001",
        "tgn:7012149",
        "tgn:2000550",
        "tgn:7007252",
        "tgn:7029392"
    ],
    "tgn:id":2254938,
    "tgn:name":"Cooper Branch",
    "tgn:placetype":[
        "aat:300008699"
    ]
},
  "bbox": [],
  "geometry": {"coordinates":[-86.7167,38.0167],"type":"Point"}
}