{
  "id": 7469812,
  "type": "Feature",
  "properties": {
    "tgn:hierarchy":[
        "tgn:7469812",
        "tgn:1000004",
        "tgn:7001014",
        "tgn:1000141",
        "tgn:7029392"
    ],
    "tgn:id":7469812,
    "tgn:name":"Haibei Cun",
    "tgn:placetype":[
        "aat:300387173"
    ]
},
  "bbox": [],
  "geometry": {"coordinates":[120.195278,23.707778],"type":"Point"}
}