{
  "id": 7536811,
  "type": "Feature",
  "properties": {
    "tgn:hierarchy":[
        "tgn:7536811",
        "tgn:7001242",
        "tgn:7016833",
        "tgn:1001079",
        "tgn:7029392"
    ],
    "tgn:id":7536811,
    "tgn:name:en":"Victoria Station",
    "tgn:placetype":[
        "aat:300007783"
    ]
},
  "bbox": [],
  "geometry": {"coordinates":[29.978979,31.248543],"type":"Point"}
}