<<<<<<< HEAD
{
  "id": 2257175,
  "type": "Feature",
  "properties": {
    "tgn:hierarchy":[
        "tgn:2257175",
        "tgn:1000001",
        "tgn:7012149",
        "tgn:2001461",
        "tgn:7007568",
        "tgn:7029392"
    ],
    "tgn:id":2257175,
    "tgn:name":"Corner Pond",
    "tgn:placetype":[
        "aat:300008680"
    ]
},
  "bbox": [],
  "geometry": {"coordinates":[-74.2333,43.8167],"type":"Point"}
}
=======
{"geometry":{"type":"Point","coordinates":[-74.233300,43.816700]},"type":"Feature","properties":{"hierarchy":["tgn:2257175","tgn:1000001","tgn:7012149","tgn:2001461","tgn:7007568","tgn:7029392"],"placetype":["aat:300008680"],"id":2257175,"name:xx":"Corner Pond"}}
>>>>>>> 03f74aca74312dbeaf24d7e61306dd6a786dc3d0
