{
  "id": 2521926,
  "type": "Feature",
  "properties": {
    "tgn:hierarchy":[
        "tgn:2521926",
        "tgn:1000001",
        "tgn:7012149",
        "tgn:7007157",
        "tgn:1002791",
        "tgn:7029392"
    ],
    "tgn:id":2521926,
    "tgn:name":"Monumental Ridge",
    "tgn:placetype":[
        "aat:300266640"
    ]
},
  "bbox": [],
  "geometry": {"coordinates":[-120.5667,39.2667],"type":"Point"}
}