{
  "id": 2379763,
  "type": "Feature",
  "properties": {
    "tgn:hierarchy":[
        "tgn:2379763",
        "tgn:1000001",
        "tgn:7012149",
        "tgn:1002924",
        "tgn:7007568",
        "tgn:7029392"
    ],
    "tgn:id":2379763,
    "tgn:name":"Hassock, The",
    "tgn:placetype":[
        "aat:300008791"
    ]
},
  "bbox": [],
  "geometry": {"coordinates":[-73.1833,40.65],"type":"Point"}
}