{
  "id": 1032743,
  "type": "Feature",
  "properties": {
    "tgn:hierarchy":[
        "tgn:1032743",
        "tgn:1000003",
        "tgn:7002889",
        "tgn:1000070",
        "tgn:7029392"
    ],
    "tgn:id":1032743,
    "tgn:name":"Condom",
    "tgn:placetype":[
        "aat:300008347"
    ]
},
  "bbox": [],
  "geometry": {"coordinates":[0.3833,43.9667],"type":"Point"}
}