{
  "id": 2383160,
  "type": "Feature",
  "properties": {
    "tgn:hierarchy":[
        "tgn:2383160",
        "tgn:1000001",
        "tgn:2001266",
        "tgn:7012149",
        "tgn:7007524",
        "tgn:7029392"
    ],
    "tgn:id":2383160,
    "tgn:name":"Headstone Gulch",
    "tgn:placetype":[
        "aat:300008761"
    ]
},
  "bbox": [],
  "geometry": {"coordinates":[-110.7167,46.9667],"type":"Point"}
}