{
  "id": 2312821,
  "type": "Feature",
  "properties": {
    "tgn:hierarchy":[
        "tgn:2312821",
        "tgn:1000001",
        "tgn:7012149",
        "tgn:2002090",
        "tgn:7007826",
        "tgn:7029392"
    ],
    "tgn:id":2312821,
    "tgn:name":"El Pico",
    "tgn:placetype":[
        "aat:300008798"
    ]
},
  "bbox": [],
  "geometry": {"coordinates":[-99.55,27.6167],"type":"Point"}
}