{
  "id": 1049501,
  "type": "Feature",
  "properties": {
    "tgn:hierarchy":[
        "tgn:1049501",
        "tgn:1000003",
        "tgn:7024127",
        "tgn:7006366",
        "tgn:7029392"
    ],
    "tgn:id":1049501,
    "tgn:name":"Sucha",
    "tgn:placetype":[
        "aat:300008347"
    ]
},
  "bbox": [],
  "geometry": {"coordinates":[19.5833,49.7333],"type":"Point"}
}