{
  "id": 1088828,
  "type": "Feature",
  "properties": {
    "tgn:hierarchy":[
        "tgn:1088828",
        "tgn:7001242",
        "tgn:7016654",
        "tgn:1000159",
        "tgn:7029392"
    ],
    "tgn:id":1088828,
    "tgn:name":"Bodjoki",
    "tgn:placetype":[
        "aat:300008347"
    ]
},
  "bbox": [],
  "geometry": {"coordinates":[22.3833,2.9167],"type":"Point"}
}