{
  "id": 7120828,
  "type": "Feature",
  "properties": {
    "tgn:hierarchy":[
        "tgn:7120828",
        "tgn:7003712",
        "tgn:7003670",
        "tgn:1000003",
        "tgn:7000084",
        "tgn:7029392"
    ],
    "tgn:id":7120828,
    "tgn:name":"Bahnhof Potsdamer Platz",
    "tgn:placetype":[
        "aat:300007783"
    ]
},
  "bbox": [],
  "geometry": {"coordinates":[13.376111,52.51],"type":"Point"}
}