<<<<<<< HEAD
{
  "id": 7360034,
  "type": "Feature",
  "properties": {
    "tgn:hierarchy":[
        "tgn:7360034",
        "tgn:1000001",
        "tgn:1001960",
        "tgn:7005560",
        "tgn:7029392"
    ],
    "tgn:id":7360034,
    "tgn:name":"Cub\u00fan",
    "tgn:placetype":[
        "aat:300008347"
    ]
},
  "bbox": [],
  "geometry": {"coordinates":[-110.116667,27.516667],"type":"Point"}
}
=======
{"geometry":{"type":"Point","coordinates":[-110.116667,27.516667]},"type":"Feature","properties":{"hierarchy":["tgn:7360034","tgn:1000001","tgn:1001960","tgn:7005560","tgn:7029392"],"placetype":["aat:300008347"],"id":7360034,"name:xx":"Cub\u00fan"}}
>>>>>>> 03f74aca74312dbeaf24d7e61306dd6a786dc3d0
