{
  "id": 7092355,
  "type": "Feature",
  "properties": {
    "tgn:hierarchy":[
        "tgn:7092355",
        "tgn:1000003",
        "tgn:7003677",
        "tgn:7000084",
        "tgn:7029392"
    ],
    "tgn:id":7092355,
    "tgn:name":"Urlaubs-Bach",
    "tgn:placetype":[
        "aat:300008699"
    ]
},
  "bbox": [],
  "geometry": {"coordinates":[7.716667,51.833333],"type":"Point"}
}