{
  "id": 7234311,
  "type": "Feature",
  "properties": {
    "tgn:hierarchy":[
        "tgn:7234311",
        "tgn:4003773",
        "tgn:7001395",
        "tgn:1000003",
        "tgn:1000074",
        "tgn:7029392"
    ],
    "tgn:id":7234311,
    "tgn:name":"Asv\u00e9stion",
    "tgn:placetype":[
        "aat:300008347"
    ]
},
  "bbox": [],
  "geometry": {"coordinates":[22.133333,39.016667],"type":"Point"}
}