{
  "id": 1077150,
  "type": "Feature",
  "properties": {
    "tgn:hierarchy":[
        "tgn:1077150",
        "tgn:1000004",
        "tgn:7000198",
        "tgn:7016722",
        "tgn:7029392"
    ],
    "tgn:id":1077150,
    "tgn:name:en":"Th\u0101kurdw\u0101ra",
    "tgn:placetype":[
        "aat:300008347"
    ]
},
  "bbox": [],
  "geometry": {"coordinates":[78.861452,29.192029],"type":"Point"}
}