<<<<<<< HEAD
{
  "id": 7117439,
  "type": "Feature",
  "properties": {
    "tgn:hierarchy":[
        "tgn:7117439",
        "tgn:1000003",
        "tgn:7003678",
        "tgn:7000084",
        "tgn:7029392"
    ],
    "tgn:id":7117439,
    "tgn:name":"Obersteinige Berg",
    "tgn:placetype":[
        "aat:300008777"
    ]
},
  "bbox": [],
  "geometry": {"coordinates":[9.35,50.166667],"type":"Point"}
}
=======
{"geometry":{"type":"Point","coordinates":[9.350000,50.166667]},"type":"Feature","properties":{"hierarchy":["tgn:7117439","tgn:1000003","tgn:7003678","tgn:7000084","tgn:7029392"],"placetype":["aat:300008777"],"id":7117439,"name:xx":"Obersteinige Berg"}}
>>>>>>> 03f74aca74312dbeaf24d7e61306dd6a786dc3d0
