{
  "id": 7275299,
  "type": "Feature",
  "properties": {
    "tgn:hierarchy":[
        "tgn:7275299",
        "tgn:1001637",
        "tgn:1000049",
        "tgn:1000002",
        "tgn:7029392"
    ],
    "tgn:id":7275299,
    "tgn:name":"Turqu\u00eda",
    "tgn:placetype":[
        "aat:300008347"
    ]
},
  "bbox": [],
  "geometry": {"coordinates":[-72.666667,-37.216667],"type":"Point"}
}