{
  "id": 2425573,
  "type": "Feature",
  "properties": {
    "tgn:hierarchy":[
        "tgn:2425573",
        "tgn:1000001",
        "tgn:7012149",
        "tgn:2001248",
        "tgn:7007523",
        "tgn:7029392"
    ],
    "tgn:id":2425573,
    "tgn:name":"Johnsons Lake",
    "tgn:placetype":[
        "aat:300006191"
    ]
},
  "bbox": [],
  "geometry": {"coordinates":[-89.95,37.0167],"type":"Point"}
}