{
  "id": 2614290,
  "type": "Feature",
  "properties": {
    "tgn:hierarchy":[
        "tgn:2614290",
        "tgn:1000001",
        "tgn:7012149",
        "tgn:1002517",
        "tgn:7007523",
        "tgn:7029392"
    ],
    "tgn:id":2614290,
    "tgn:name":"Regina",
    "tgn:placetype":[
        "aat:300008347"
    ]
},
  "bbox": [],
  "geometry": {"coordinates":[-90.5833,38.3167],"type":"Point"}
}