<<<<<<< HEAD
{
  "id": 2400914,
  "type": "Feature",
  "properties": {
    "tgn:hierarchy":[
        "tgn:2400914",
        "tgn:7006450",
        "tgn:1000001",
        "tgn:7012149",
        "tgn:7019760",
        "tgn:7029392"
    ],
    "tgn:id":2400914,
    "tgn:name":"Horse Shoal",
    "tgn:placetype":[
        "aat:300132348"
    ]
},
  "bbox": [],
  "geometry": {"coordinates":[-134.7,58.25],"type":"Point"}
}
=======
{"geometry":{"type":"Point","coordinates":[-134.700000,58.250000]},"type":"Feature","properties":{"hierarchy":["tgn:2400914","tgn:7006450","tgn:1000001","tgn:7012149","tgn:7019760","tgn:7029392"],"placetype":["aat:300132348"],"id":2400914,"name:xx":"Horse Shoal"}}
>>>>>>> 03f74aca74312dbeaf24d7e61306dd6a786dc3d0
