{
  "id": 2658208,
  "type": "Feature",
  "properties": {
    "tgn:hierarchy":[
        "tgn:2658208",
        "tgn:7002659",
        "tgn:1000001",
        "tgn:2000018",
        "tgn:7012149",
        "tgn:7029392"
    ],
    "tgn:id":2658208,
    "tgn:name":"Shelton Lake",
    "tgn:placetype":[
        "aat:300006191"
    ]
},
  "bbox": [],
  "geometry": {"coordinates":[-86.2833,32.75],"type":"Point"}
}