{
  "id": 7266494,
  "type": "Feature",
  "properties": {
    "tgn:concordances":{
        "gn:id":"2754390"
    },
    "tgn:hierarchy":[
        "tgn:7266494",
        "tgn:1000003",
        "tgn:7003626",
        "tgn:7016845",
        "tgn:7029392"
    ],
    "tgn:id":7266494,
    "tgn:name:nl":"Hengeveld",
    "tgn:placetype":[
        "aat:300008347"
    ]
},
  "bbox": [],
  "geometry": {"coordinates":[6.166667,52.366667],"type":"Point"}
}