{
  "id": 7380416,
  "type": "Feature",
  "properties": {
    "tgn:hierarchy":[
        "tgn:7380416",
        "tgn:1000001",
        "tgn:7005589",
        "tgn:7005560",
        "tgn:7029392"
    ],
    "tgn:id":7380416,
    "tgn:name":"Matatenas",
    "tgn:placetype":[
        "aat:300008347"
    ]
},
  "bbox": [],
  "geometry": {"coordinates":[-99.983333,26.516667],"type":"Point"}
}