<<<<<<< HEAD
{
  "id": 2331625,
  "type": "Feature",
  "properties": {
    "tgn:hierarchy":[
        "tgn:2331625",
        "tgn:1000001",
        "tgn:7012149",
        "tgn:2000181",
        "tgn:7007157",
        "tgn:7029392"
    ],
    "tgn:id":2331625,
    "tgn:name":"Fleener Creek",
    "tgn:placetype":[
        "aat:300008706"
    ]
},
  "bbox": [],
  "geometry": {"coordinates":[-124.3,40.5333],"type":"Point"}
}
=======
{"geometry":{"type":"Point","coordinates":[-124.300000,40.533300]},"type":"Feature","properties":{"hierarchy":["tgn:2331625","tgn:1000001","tgn:7012149","tgn:2000181","tgn:7007157","tgn:7029392"],"placetype":["aat:300008706"],"id":2331625,"name:xx":"Fleener Creek"}}
>>>>>>> 03f74aca74312dbeaf24d7e61306dd6a786dc3d0
