{
  "id": 1090212,
  "type": "Feature",
  "properties": {
    "tgn:hierarchy":[
        "tgn:1090212",
        "tgn:7001242",
        "tgn:7018307",
        "tgn:1000166",
        "tgn:7029392"
    ],
    "tgn:id":1090212,
    "tgn:name":"Zebila",
    "tgn:placetype":[
        "aat:300008347"
    ]
},
  "bbox": [],
  "geometry": {"coordinates":[-0.4833,10.9333],"type":"Point"}
}