{
  "id": 2205793,
  "type": "Feature",
  "properties": {
    "tgn:hierarchy":[
        "tgn:2205793",
        "tgn:1000001",
        "tgn:7016172",
        "tgn:7012149",
        "tgn:2000177",
        "tgn:7029392"
    ],
    "tgn:id":2205793,
    "tgn:name":"Bull Mountain",
    "tgn:placetype":[
        "aat:300266640"
    ]
},
  "bbox": [],
  "geometry": {"coordinates":[-92.0333,35.1333],"type":"Point"}
}