{
  "id": 2609365,
  "type": "Feature",
  "properties": {
    "tgn:hierarchy":[
        "tgn:2609365",
        "tgn:1000001",
        "tgn:7012149",
        "tgn:7007826",
        "tgn:7029392"
    ],
    "tgn:id":2609365,
    "tgn:name":"Ray Hubbard, Lake",
    "tgn:placetype":[
        "aat:300006191"
    ]
},
  "bbox": [],
  "geometry": {"coordinates":[-96.4833,32.7833],"type":"Point"}
}