{
  "id": 1048885,
  "type": "Feature",
  "properties": {
    "tgn:hierarchy":[
        "tgn:1048885",
        "tgn:1000003",
        "tgn:7024119",
        "tgn:7006366",
        "tgn:7029392"
    ],
    "tgn:id":1048885,
    "tgn:name":"\u0141ob\u017cenica",
    "tgn:placetype":[
        "aat:300008347"
    ]
},
  "bbox": [],
  "geometry": {"coordinates":[17.2333,53.2833],"type":"Point"}
}