{
  "id": 7412289,
  "type": "Feature",
  "properties": {
    "tgn:hierarchy":[
        "tgn:7412289",
        "tgn:7005587",
        "tgn:1000001",
        "tgn:7005560",
        "tgn:7029392"
    ],
    "tgn:id":7412289,
    "tgn:name:es":"Tala Cuatro",
    "tgn:placetype":[
        "aat:300008347"
    ]
},
  "bbox": [],
  "geometry": {"coordinates":[-98.5625,21.169444],"type":"Point"}
}