{
  "id": 2161068,
  "type": "Feature",
  "properties": {
    "tgn:hierarchy":[
        "tgn:2161068",
        "tgn:1000001",
        "tgn:7012149",
        "tgn:2002186",
        "tgn:7007919",
        "tgn:7029392"
    ],
    "tgn:id":2161068,
    "tgn:name":"Bell Cave",
    "tgn:placetype":[
        "aat:300008746"
    ]
},
  "bbox": [],
  "geometry": {"coordinates":[-79.3667,37.7833],"type":"Point"}
}