{
  "id": 1134106,
  "type": "Feature",
  "properties": {
    "tgn:hierarchy":[
        "tgn:1134106",
        "tgn:7003028",
        "tgn:1000003",
        "tgn:1000062",
        "tgn:7029392"
    ],
    "tgn:id":1134106,
    "tgn:name":"Paltenbach",
    "tgn:placetype":[
        "aat:300008706"
    ]
},
  "bbox": [],
  "geometry": {"coordinates":[14.3333,47.5667],"type":"Point"}
}