{
  "id": 7407530,
  "type": "Feature",
  "properties": {
    "tgn:hierarchy":[
        "tgn:7407530",
        "tgn:7005580",
        "tgn:1000001",
        "tgn:7005560",
        "tgn:7029392"
    ],
    "tgn:id":7407530,
    "tgn:name":"Jos\u00e9 Mar\u00eda Garza",
    "tgn:placetype":[
        "aat:300008347"
    ]
},
  "bbox": [],
  "geometry": {"coordinates":[-93.291667,16.395833],"type":"Point"}
}