{
  "id": 2569578,
  "type": "Feature",
  "properties": {
    "tgn:hierarchy":[
        "tgn:2569578",
        "tgn:7006450",
        "tgn:1000001",
        "tgn:2124012",
        "tgn:7012149",
        "tgn:7029392"
    ],
    "tgn:id":2569578,
    "tgn:name":"Parrot Island",
    "tgn:placetype":[
        "aat:300008791"
    ]
},
  "bbox": [],
  "geometry": {"coordinates":[-152.5667,58.0833],"type":"Point"}
}