{
  "id": 7124206,
  "type": "Feature",
  "properties": {
    "tgn:hierarchy":[
        "tgn:7124206",
        "tgn:7003692",
        "tgn:1000003",
        "tgn:7000084",
        "tgn:7029392"
    ],
    "tgn:id":7124206,
    "tgn:name":"Neuhaus",
    "tgn:placetype":[
        "aat:300000206"
    ]
},
  "bbox": [],
  "geometry": {"coordinates":[9.366667,49.116667],"type":"Point"}
}