{
  "id": 7348274,
  "type": "Feature",
  "properties": {
    "tgn:hierarchy":[
        "tgn:7348274",
        "tgn:7002825",
        "tgn:7016622",
        "tgn:1000003",
        "tgn:1000095",
        "tgn:7029392"
    ],
    "tgn:id":7348274,
    "tgn:name":"\u00c1guila, Barranco del",
    "tgn:placetype":[
        "aat:300266554",
        "aat:300008699"
    ]
},
  "bbox": [],
  "geometry": {"coordinates":[-15.516667,27.766667],"type":"Point"}
}