{
  "id": 2573469,
  "type": "Feature",
  "properties": {
    "tgn:hierarchy":[
        "tgn:2573469",
        "tgn:1000001",
        "tgn:7012149",
        "tgn:2001996",
        "tgn:7007826",
        "tgn:7029392"
    ],
    "tgn:id":2573469,
    "tgn:name":"Pecan Creek",
    "tgn:placetype":[
        "aat:300008706"
    ]
},
  "bbox": [],
  "geometry": {"coordinates":[-98.15,31.8667],"type":"Point"}
}