{
  "id": 7472425,
  "type": "Feature",
  "properties": {
    "tgn:hierarchy":[
        "tgn:7472425",
        "tgn:7001010",
        "tgn:1000004",
        "tgn:1000141",
        "tgn:7029392"
    ],
    "tgn:id":7472425,
    "tgn:name":"Fushi Qiao",
    "tgn:placetype":[
        "aat:300007836"
    ]
},
  "bbox": [],
  "geometry": {"coordinates":[121.6304,24.1457],"type":"Point"}
}