<<<<<<< HEAD
{
  "id": 7472425,
  "type": "Feature",
  "properties": {
    "tgn:hierarchy":[
        "tgn:7472425",
        "tgn:7001010",
        "tgn:1000004",
        "tgn:1000141",
        "tgn:7029392"
    ],
    "tgn:id":7472425,
    "tgn:name":"Fushi Qiao",
    "tgn:placetype":[
        "aat:300007836"
    ]
},
  "bbox": [],
  "geometry": {"coordinates":[121.6304,24.1457],"type":"Point"}
}
=======
{"geometry":{"type":"Point","coordinates":[121.630400,24.145700]},"type":"Feature","properties":{"hierarchy":["tgn:7472425","tgn:7001010","tgn:1000004","tgn:1000141","tgn:7029392"],"placetype":["aat:300007836"],"id":7472425,"name:xx":"Fushi Qiao"}}
>>>>>>> 03f74aca74312dbeaf24d7e61306dd6a786dc3d0
