{
  "id": 2484079,
  "type": "Feature",
  "properties": {
    "tgn:hierarchy":[
        "tgn:2484079",
        "tgn:1000001",
        "tgn:7012149",
        "tgn:1002827",
        "tgn:7007252",
        "tgn:7029392"
    ],
    "tgn:id":2484079,
    "tgn:name":"Laugheryville",
    "tgn:placetype":[
        "aat:300008347"
    ]
},
  "bbox": [],
  "geometry": {"coordinates":[-85.2833,39.2167],"type":"Point"}
}