{
  "id": 2715364,
  "type": "Feature",
  "properties": {
    "tgn:hierarchy":[
        "tgn:2715364",
        "tgn:1000001",
        "tgn:7012149",
        "tgn:7007157",
        "tgn:1002863",
        "tgn:7029392"
    ],
    "tgn:id":2715364,
    "tgn:name":"Terrace Hill",
    "tgn:placetype":[
        "aat:300008798"
    ]
},
  "bbox": [],
  "geometry": {"coordinates":[-120.6333,35.2667],"type":"Point"}
}