{
  "id": 7381538,
  "type": "Feature",
  "properties": {
    "tgn:hierarchy":[
        "tgn:7381538",
        "tgn:7005581",
        "tgn:1000001",
        "tgn:7005560",
        "tgn:7029392"
    ],
    "tgn:id":7381538,
    "tgn:name":"Rancho Mesa Colorada",
    "tgn:placetype":[
        "aat:300000241"
    ]
},
  "bbox": [],
  "geometry": {"coordinates":[-108.483333,29.833333],"type":"Point"}
}