{
  "id": 7592001,
  "type": "Feature",
  "properties": {
    "tgn:hierarchy":[
        "tgn:7592001",
        "tgn:1000004",
        "tgn:7000198",
        "tgn:7000799",
        "tgn:7029392"
    ],
    "tgn:id":7592001,
    "tgn:name:en":"Dororen B\u0101n",
    "tgn:placetype":[
        "aat:300008347"
    ]
},
  "bbox": [],
  "geometry": {"coordinates":[74.896304,32.922176],"type":"Point"}
}