{
  "id": 7368685,
  "type": "Feature",
  "properties": {
    "tgn:hierarchy":[
        "tgn:7368685",
        "tgn:1000001",
        "tgn:7005594",
        "tgn:7005560",
        "tgn:7029392"
    ],
    "tgn:id":7368685,
    "tgn:name":"Juan Gordo",
    "tgn:placetype":[
        "aat:300008347"
    ]
},
  "bbox": [],
  "geometry": {"coordinates":[-99.033333,22.25],"type":"Point"}
}