{
  "id": 2670407,
  "type": "Feature",
  "properties": {
    "tgn:hierarchy":[
        "tgn:2670407",
        "tgn:1000001",
        "tgn:7012149",
        "tgn:2000230",
        "tgn:7007158",
        "tgn:7029392"
    ],
    "tgn:id":2670407,
    "tgn:name":"Smalley Gulch",
    "tgn:placetype":[
        "aat:300008761"
    ]
},
  "bbox": [],
  "geometry": {"coordinates":[-107.9167,39.3333],"type":"Point"}
}