{
  "id": 2667482,
  "type": "Feature",
  "properties": {
    "tgn:hierarchy":[
        "tgn:2667482",
        "tgn:1000001",
        "tgn:2000920",
        "tgn:7012149",
        "tgn:7007515",
        "tgn:7029392"
    ],
    "tgn:id":2667482,
    "tgn:name":"Skolfield Cove",
    "tgn:placetype":[
        "aat:300132316"
    ]
},
  "bbox": [],
  "geometry": {"coordinates":[-69.9333,43.85],"type":"Point"}
}