{
  "id": 7441534,
  "type": "Feature",
  "properties": {
    "tgn:hierarchy":[
        "tgn:7441534",
        "tgn:1000727",
        "tgn:1000001",
        "tgn:7005493",
        "tgn:7029392"
    ],
    "tgn:id":7441534,
    "tgn:name":"Sacul",
    "tgn:placetype":[
        "aat:300008347",
        "aat:300387007",
        "aat:300000810",
        "aat:300008389"
    ]
},
  "bbox": [],
  "geometry": {"coordinates":[-89.288,16.546],"type":"Point"}
}