{
  "id": 7368063,
  "type": "Feature",
  "properties": {
    "tgn:hierarchy":[
        "tgn:7368063",
        "tgn:1000001",
        "tgn:7005591",
        "tgn:7005560",
        "tgn:7029392"
    ],
    "tgn:id":7368063,
    "tgn:name":"Grande, R\u00edo",
    "tgn:placetype":[
        "aat:300008699"
    ]
},
  "bbox": [],
  "geometry": {"coordinates":[-97.483333,15.966667],"type":"Point"}
}