{
  "id": 7242627,
  "type": "Feature",
  "properties": {
    "tgn:hierarchy":[
        "tgn:7242627",
        "tgn:7018239",
        "tgn:1000003",
        "tgn:1000063",
        "tgn:7018236",
        "tgn:7029392"
    ],
    "tgn:id":7242627,
    "tgn:name":"Kooige",
    "tgn:placetype":[
        "aat:300008347"
    ]
},
  "bbox": [],
  "geometry": {"coordinates":[4.55,50.85],"type":"Point"}
}