{
  "id": 7201598,
  "type": "Feature",
  "properties": {
    "tgn:hierarchy":[
        "tgn:7201598",
        "tgn:7003692",
        "tgn:1000003",
        "tgn:7000084",
        "tgn:7029392"
    ],
    "tgn:id":7201598,
    "tgn:name":"Breitnau",
    "tgn:placetype":[
        "aat:300008347"
    ]
},
  "bbox": [],
  "geometry": {"coordinates":[8.083333,47.933333],"type":"Point"}
}