{
  "id": 7490656,
  "type": "Feature",
  "properties": {
    "tgn:hierarchy":[
        "tgn:7490656",
        "tgn:1000004",
        "tgn:7492971",
        "tgn:1000141",
        "tgn:7029392"
    ],
    "tgn:id":7490656,
    "tgn:name":"Dewenshe",
    "tgn:placetype":[
        "aat:300008347"
    ]
},
  "bbox": [],
  "geometry": {"coordinates":[120.696168,22.606541],"type":"Point"}
}