{
  "id": 7384774,
  "type": "Feature",
  "properties": {
    "tgn:hierarchy":[
        "tgn:7384774",
        "tgn:1000001",
        "tgn:7005589",
        "tgn:7005560",
        "tgn:7029392"
    ],
    "tgn:id":7384774,
    "tgn:name":"Rancho Palma de Afuera",
    "tgn:placetype":[
        "aat:300000241"
    ]
},
  "bbox": [],
  "geometry": {"coordinates":[-100.75,26.533333],"type":"Point"}
}