{
  "id": 7551416,
  "type": "Feature",
  "properties": {
    "tgn:hierarchy":[
        "tgn:7551416",
        "tgn:1000004",
        "tgn:7000198",
        "tgn:1001894",
        "tgn:7029392"
    ],
    "tgn:id":7551416,
    "tgn:name:en":"Bokhr\u0101ta",
    "tgn:placetype":[
        "aat:300008347"
    ]
},
  "bbox": [],
  "geometry": {"coordinates":[74.61466,21.855959],"type":"Point"}
}