{
  "id": 2723800,
  "type": "Feature",
  "properties": {
    "tgn:hierarchy":[
        "tgn:2723800",
        "tgn:1000001",
        "tgn:7012149",
        "tgn:2001067",
        "tgn:7007521",
        "tgn:7029392"
    ],
    "tgn:id":2723800,
    "tgn:name":"Toimi Creek",
    "tgn:placetype":[
        "aat:300008706"
    ]
},
  "bbox": [],
  "geometry": {"coordinates":[-91.7833,47.4167],"type":"Point"}
}