{
  "id": 2566382,
  "type": "Feature",
  "properties": {
    "tgn:hierarchy":[
        "tgn:2566382",
        "tgn:1000001",
        "tgn:7006451",
        "tgn:7012149",
        "tgn:2000100",
        "tgn:7029392"
    ],
    "tgn:id":2566382,
    "tgn:name":"Palo Verde Stand",
    "tgn:placetype":[
        "aat:300008347"
    ]
},
  "bbox": [],
  "geometry": {"coordinates":[-112.0167,32.3333],"type":"Point"}
}