{
  "id": 2738918,
  "type": "Feature",
  "properties": {
    "tgn:hierarchy":[
        "tgn:2738918",
        "tgn:1000001",
        "tgn:7012149",
        "tgn:1002552",
        "tgn:7007920",
        "tgn:7029392"
    ],
    "tgn:id":2738918,
    "tgn:name":"Union River Reservoir",
    "tgn:placetype":[
        "aat:300006191"
    ]
},
  "bbox": [],
  "geometry": {"coordinates":[-122.7667,47.5333],"type":"Point"}
}