{
  "id": 2780401,
  "type": "Feature",
  "properties": {
    "tgn:hierarchy":[
        "tgn:2780401",
        "tgn:1000001",
        "tgn:7012149",
        "tgn:2001722",
        "tgn:7007708",
        "tgn:7029392"
    ],
    "tgn:id":2780401,
    "tgn:name":"Wood Butte",
    "tgn:placetype":[
        "aat:300008798"
    ]
},
  "bbox": [],
  "geometry": {"coordinates":[-117.4333,45.7667],"type":"Point"}
}