{
  "id": 7015930,
  "type": "Feature",
  "properties": {
    "tgn:hierarchy":[
        "tgn:7015930",
        "tgn:1000003",
        "tgn:7029392"
    ],
    "tgn:id":7015930,
    "tgn:name:fi":"Norra Kvarken",
    "tgn:name:sv":"Merenkurkku",
    "tgn:placetype":[
        "aat:300266559"
    ]
},
  "bbox": [],
  "geometry": {"coordinates":[20.75,63.5833],"type":"Point"}
}