{
  "id": 2141237,
  "type": "Feature",
  "properties": {
    "tgn:hierarchy":[
        "tgn:2141237",
        "tgn:1002933",
        "tgn:1000001",
        "tgn:7012149",
        "tgn:7007239",
        "tgn:7029392"
    ],
    "tgn:id":2141237,
    "tgn:name":"Aydelotte Point",
    "tgn:placetype":[
        "aat:300008850"
    ]
},
  "bbox": [],
  "geometry": {"coordinates":[-75.1667,38.5667],"type":"Point"}
}