{
  "id": 2498377,
  "type": "Feature",
  "properties": {
    "tgn:hierarchy":[
        "tgn:2498377",
        "tgn:1000001",
        "tgn:7012149",
        "tgn:2001312",
        "tgn:7007524",
        "tgn:7029392"
    ],
    "tgn:id":2498377,
    "tgn:name":"Mc Kee Reservoir",
    "tgn:placetype":[
        "aat:300006191"
    ]
},
  "bbox": [],
  "geometry": {"coordinates":[-107.3333,47.8833],"type":"Point"}
}