{
  "id": 2357104,
  "type": "Feature",
  "properties": {
    "tgn:hierarchy":[
        "tgn:2357104",
        "tgn:1000001",
        "tgn:7012149",
        "tgn:2001846",
        "tgn:7007825",
        "tgn:7029392"
    ],
    "tgn:id":2357104,
    "tgn:name":"Gouge Branch",
    "tgn:placetype":[
        "aat:300008699"
    ]
},
  "bbox": [],
  "geometry": {"coordinates":[-82.15,36.2167],"type":"Point"}
}