{
  "id": 7174371,
  "type": "Feature",
  "properties": {
    "tgn:hierarchy":[
        "tgn:7174371",
        "tgn:1000003",
        "tgn:7000094",
        "tgn:7000084",
        "tgn:7029392"
    ],
    "tgn:id":7174371,
    "tgn:name":"Gro\u00dfer Kotzower See",
    "tgn:placetype":[
        "aat:300008680"
    ]
},
  "bbox": [],
  "geometry": {"coordinates":[12.816667,53.316667],"type":"Point"}
}