{
  "id": 2659140,
  "type": "Feature",
  "properties": {
    "tgn:hierarchy":[
        "tgn:2659140",
        "tgn:1000001",
        "tgn:7006451",
        "tgn:7012149",
        "tgn:2000099",
        "tgn:7029392"
    ],
    "tgn:id":2659140,
    "tgn:name":"Sheza Butte",
    "tgn:placetype":[
        "aat:300008798"
    ]
},
  "bbox": [],
  "geometry": {"coordinates":[-110.1167,34.6833],"type":"Point"}
}