{
  "id": 1074570,
  "type": "Feature",
  "properties": {
    "tgn:hierarchy":[
        "tgn:1074570",
        "tgn:1000004",
        "tgn:7000198",
        "tgn:1001894",
        "tgn:7029392"
    ],
    "tgn:id":1074570,
    "tgn:name":"B\u012bna-Et\u0101wa",
    "tgn:placetype":[
        "aat:300008347"
    ]
},
  "bbox": [],
  "geometry": {"coordinates":[78.201276,24.183856],"type":"Point"}
}