{
  "id": 1085980,
  "type": "Feature",
  "properties": {
    "tgn:hierarchy":[
        "tgn:1085980",
        "tgn:1000004",
        "tgn:1001576",
        "tgn:7018454",
        "tgn:1000144",
        "tgn:7029392"
    ],
    "tgn:id":1085980,
    "tgn:name":"Arakl\u0131",
    "tgn:placetype":[
        "aat:300008347"
    ]
},
  "bbox": [],
  "geometry": {"coordinates":[39.9333,40.95],"type":"Point"}
}