{
  "id": 7043611,
  "type": "Feature",
  "properties": {
    "tgn:hierarchy":[
        "tgn:7043611",
        "tgn:1003471",
        "tgn:1000003",
        "tgn:7003240",
        "tgn:1000080",
        "tgn:7029392"
    ],
    "tgn:id":7043611,
    "tgn:name":"Carbonara, Monte",
    "tgn:placetype":[
        "aat:300008777"
    ]
},
  "bbox": [],
  "geometry": {"coordinates":[13.333333,43.316667],"type":"Point"}
}