{
  "id": 2703132,
  "type": "Feature",
  "properties": {
    "tgn:hierarchy":[
        "tgn:2703132",
        "tgn:1000001",
        "tgn:7012149",
        "tgn:7007520",
        "tgn:7029392"
    ],
    "tgn:id":2703132,
    "tgn:name":"Summer Meadow Creek",
    "tgn:placetype":[
        "aat:300008706"
    ]
},
  "bbox": [],
  "geometry": {"coordinates":[-87.2667,46.0833],"type":"Point"}
}