{
  "id": 7468789,
  "type": "Feature",
  "properties": {
    "tgn:hierarchy":[
        "tgn:7468789",
        "tgn:1000004",
        "tgn:7489179",
        "tgn:1000141",
        "tgn:7029392"
    ],
    "tgn:id":7468789,
    "tgn:name":"Xinshe Cun",
    "tgn:placetype":[
        "aat:300387173"
    ]
},
  "bbox": [],
  "geometry": {"coordinates":[121.809722,24.786667],"type":"Point"}
}