{
  "id": 2163964,
  "type": "Feature",
  "properties": {
    "tgn:hierarchy":[
        "tgn:2163964",
        "tgn:1000001",
        "tgn:7012149",
        "tgn:2000472",
        "tgn:7007250",
        "tgn:7029392"
    ],
    "tgn:id":2163964,
    "tgn:name":"Bergguist Spring",
    "tgn:placetype":[
        "aat:300008697"
    ]
},
  "bbox": [],
  "geometry": {"coordinates":[-111.6333,42.1333],"type":"Point"}
}