{
  "id": 2768849,
  "type": "Feature",
  "properties": {
    "tgn:hierarchy":[
        "tgn:2768849",
        "tgn:1000001",
        "tgn:7012149",
        "tgn:2002246",
        "tgn:7007920",
        "tgn:7029392"
    ],
    "tgn:id":2768849,
    "tgn:name":"Whitney Canyon",
    "tgn:placetype":[
        "aat:300008761"
    ]
},
  "bbox": [],
  "geometry": {"coordinates":[-119.0833,47.8333],"type":"Point"}
}