{
  "id": 7105758,
  "type": "Feature",
  "properties": {
    "tgn:hierarchy":[
        "tgn:7105758",
        "tgn:1000003",
        "tgn:7003689",
        "tgn:7000084",
        "tgn:7029392"
    ],
    "tgn:id":7105758,
    "tgn:name":"Schiebelau",
    "tgn:placetype":[
        "aat:300008347"
    ]
},
  "bbox": [],
  "geometry": {"coordinates":[11.633333,50.866667],"type":"Point"}
}