{
  "id": 2613035,
  "type": "Feature",
  "properties": {
    "tgn:hierarchy":[
        "tgn:2613035",
        "tgn:1000001",
        "tgn:7006451",
        "tgn:7012149",
        "tgn:2000101",
        "tgn:7029392"
    ],
    "tgn:id":2613035,
    "tgn:name":"Reds Tank",
    "tgn:placetype":[
        "aat:300006191"
    ]
},
  "bbox": [],
  "geometry": {"coordinates":[-111.3333,32.8833],"type":"Point"}
}