{
  "id": 7115027,
  "type": "Feature",
  "properties": {
    "tgn:hierarchy":[
        "tgn:7115027",
        "tgn:1000003",
        "tgn:7003688",
        "tgn:7000084",
        "tgn:7029392"
    ],
    "tgn:id":7115027,
    "tgn:name":"Osterhof",
    "tgn:placetype":[
        "aat:300000206"
    ]
},
  "bbox": [],
  "geometry": {"coordinates":[8.783333,54.766667],"type":"Point"}
}