{
  "id": 7510563,
  "type": "Feature",
  "properties": {
    "tgn:hierarchy":[
        "tgn:7510563",
        "tgn:1009227",
        "tgn:1000226",
        "tgn:7016729",
        "tgn:1000006",
        "tgn:7029392"
    ],
    "tgn:id":7510563,
    "tgn:name:en":"United Creek",
    "tgn:placetype":[
        "aat:300008699"
    ]
},
  "bbox": [],
  "geometry": {"coordinates":[173.283333,-41.383333],"type":"Point"}
}