{
  "id": 2371059,
  "type": "Feature",
  "properties": {
    "tgn:hierarchy":[
        "tgn:2371059",
        "tgn:1000001",
        "tgn:7012149",
        "tgn:7007157",
        "tgn:2000188",
        "tgn:7029392"
    ],
    "tgn:id":2371059,
    "tgn:name":"Hagaman Gulch",
    "tgn:placetype":[
        "aat:300008761"
    ]
},
  "bbox": [],
  "geometry": {"coordinates":[-121.8333,40.5833],"type":"Point"}
}