<<<<<<< HEAD
{
  "id": 7248723,
  "type": "Feature",
  "properties": {
    "tgn:hierarchy":[
        "tgn:7248723",
        "tgn:7003466",
        "tgn:1000003",
        "tgn:1000063",
        "tgn:4012014",
        "tgn:7029392"
    ],
    "tgn:id":7248723,
    "tgn:name":"Cense du Bocq",
    "tgn:placetype":[
        "aat:300000206"
    ]
},
  "bbox": [],
  "geometry": {"coordinates":[5.0,50.366667],"type":"Point"}
}
=======
{"geometry":{"type":"Point","coordinates":[5.000000,50.366667]},"type":"Feature","properties":{"hierarchy":["tgn:7248723","tgn:7003466","tgn:1000003","tgn:1000063","tgn:4012014","tgn:7029392"],"placetype":["aat:300000206"],"id":7248723,"name:xx":"Cense du Bocq"}}
>>>>>>> 03f74aca74312dbeaf24d7e61306dd6a786dc3d0
