{
  "id": 7297007,
  "type": "Feature",
  "properties": {
    "tgn:hierarchy":[
        "tgn:7297007",
        "tgn:7002810",
        "tgn:7001158",
        "tgn:1000003",
        "tgn:1000095",
        "tgn:7029392"
    ],
    "tgn:id":7297007,
    "tgn:name":"Torralba, R\u00edo",
    "tgn:placetype":[
        "aat:300008699"
    ]
},
  "bbox": [],
  "geometry": {"coordinates":[-3.016667,41.95],"type":"Point"}
}