{
  "id": 7226000,
  "type": "Feature",
  "properties": {
    "tgn:hierarchy":[
        "tgn:7226000",
        "tgn:7002681",
        "tgn:7001395",
        "tgn:1000003",
        "tgn:1000074",
        "tgn:7029392"
    ],
    "tgn:id":7226000,
    "tgn:name":"Mouz\u00e1ki, \u00c1kra",
    "tgn:placetype":[
        "aat:300008850"
    ]
},
  "bbox": [],
  "geometry": {"coordinates":[23.27739,37.348097],"type":"Point"}
}