{
  "id": 7563239,
  "type": "Feature",
  "properties": {
    "tgn:hierarchy":[
        "tgn:7563239",
        "tgn:1000004",
        "tgn:7000198",
        "tgn:7016722",
        "tgn:7029392"
    ],
    "tgn:id":7563239,
    "tgn:name:en":"Kania",
    "tgn:placetype":[
        "aat:300008347"
    ]
},
  "bbox": [],
  "geometry": {"coordinates":[79.497111,25.401654],"type":"Point"}
}