{
  "id": 7572732,
  "type": "Feature",
  "properties": {
    "tgn:hierarchy":[
        "tgn:7572732",
        "tgn:1000004",
        "tgn:7000198",
        "tgn:7016883",
        "tgn:7029392"
    ],
    "tgn:id":7572732,
    "tgn:name:en":"J\u012bwa Ar\u0101\u012bn",
    "tgn:placetype":[
        "aat:300007783"
    ]
},
  "bbox": [],
  "geometry": {"coordinates":[74.340222,30.657264],"type":"Point"}
}