{
  "id": 2252183,
  "type": "Feature",
  "properties": {
    "tgn:hierarchy":[
        "tgn:2252183",
        "tgn:1000001",
        "tgn:7012149",
        "tgn:2000180",
        "tgn:7007157",
        "tgn:7029392"
    ],
    "tgn:id":2252183,
    "tgn:name":"Cone Rock",
    "tgn:placetype":[
        "aat:300008791"
    ]
},
  "bbox": [],
  "geometry": {"coordinates":[-124.2167,41.9667],"type":"Point"}
}