<<<<<<< HEAD
{
  "id": 2252183,
  "type": "Feature",
  "properties": {
    "tgn:hierarchy":[
        "tgn:2252183",
        "tgn:1000001",
        "tgn:7012149",
        "tgn:2000180",
        "tgn:7007157",
        "tgn:7029392"
    ],
    "tgn:id":2252183,
    "tgn:name":"Cone Rock",
    "tgn:placetype":[
        "aat:300008791"
    ]
},
  "bbox": [],
  "geometry": {"coordinates":[-124.2167,41.9667],"type":"Point"}
}
=======
{"geometry":{"type":"Point","coordinates":[-124.216700,41.966700]},"type":"Feature","properties":{"hierarchy":["tgn:2252183","tgn:1000001","tgn:7012149","tgn:2000180","tgn:7007157","tgn:7029392"],"placetype":["aat:300008791"],"id":2252183,"name:xx":"Cone Rock"}}
>>>>>>> 03f74aca74312dbeaf24d7e61306dd6a786dc3d0
