{
  "id": 7242027,
  "type": "Feature",
  "properties": {
    "tgn:hierarchy":[
        "tgn:7242027",
        "tgn:7003458",
        "tgn:1000003",
        "tgn:1000063",
        "tgn:7018236",
        "tgn:7029392"
    ],
    "tgn:id":7242027,
    "tgn:name":"Klein Walegeleed",
    "tgn:placetype":[
        "aat:300008699"
    ]
},
  "bbox": [],
  "geometry": {"coordinates":[2.858101,51.106961],"type":"Point"}
}