{
  "id": 2314086,
  "type": "Feature",
  "properties": {
    "tgn:hierarchy":[
        "tgn:2314086",
        "tgn:1000001",
        "tgn:7012149",
        "tgn:2001619",
        "tgn:7007706",
        "tgn:7029392"
    ],
    "tgn:id":2314086,
    "tgn:name":"Elk",
    "tgn:placetype":[
        "aat:300008347"
    ]
},
  "bbox": [],
  "geometry": {"coordinates":[-81.3333,39.6667],"type":"Point"}
}