{
  "id": 2552338,
  "type": "Feature",
  "properties": {
    "tgn:hierarchy":[
        "tgn:2552338",
        "tgn:1000001",
        "tgn:7012149",
        "tgn:1002709",
        "tgn:7007826",
        "tgn:7029392"
    ],
    "tgn:id":2552338,
    "tgn:name":"Number Three, Reservoir",
    "tgn:placetype":[
        "aat:300006191"
    ]
},
  "bbox": [],
  "geometry": {"coordinates":[-96.4333,32.2667],"type":"Point"}
}