{
  "id": 7496558,
  "type": "Feature",
  "properties": {
    "tgn:hierarchy":[
        "tgn:7496558",
        "tgn:7487020",
        "tgn:1000004",
        "tgn:1000141",
        "tgn:7029392"
    ],
    "tgn:id":7496558,
    "tgn:name":"Paozhudong Shan",
    "tgn:placetype":[
        "aat:300008795"
    ]
},
  "bbox": [],
  "geometry": {"coordinates":[120.876732,24.410851],"type":"Point"}
}