{
  "id": 1086960,
  "type": "Feature",
  "properties": {
    "tgn:hierarchy":[
        "tgn:1086960",
        "tgn:1001584",
        "tgn:1000004",
        "tgn:7018451",
        "tgn:1000144",
        "tgn:7029392"
    ],
    "tgn:id":1086960,
    "tgn:name:en":"Ushak",
    "tgn:placetype":[
        "aat:300008347",
        "aat:300008389",
        "aat:300387223"
    ]
},
  "bbox": [],
  "geometry": {"coordinates":[29.4167,38.6833],"type":"Point"}
}