{
  "id": 2667317,
  "type": "Feature",
  "properties": {
    "tgn:hierarchy":[
        "tgn:2667317",
        "tgn:1000001",
        "tgn:7012149",
        "tgn:1003038",
        "tgn:7007517",
        "tgn:7029392"
    ],
    "tgn:id":2667317,
    "tgn:name":"Skinner Hill",
    "tgn:placetype":[
        "aat:300008798"
    ]
},
  "bbox": [],
  "geometry": {"coordinates":[-72.2333,42.4167],"type":"Point"}
}