{
  "id": 2590470,
  "type": "Feature",
  "properties": {
    "tgn:hierarchy":[
        "tgn:2590470",
        "tgn:1000001",
        "tgn:7012149",
        "tgn:2000493",
        "tgn:7007250",
        "tgn:7029392"
    ],
    "tgn:id":2590470,
    "tgn:name":"Pole Camp Spring",
    "tgn:placetype":[
        "aat:300008697"
    ]
},
  "bbox": [],
  "geometry": {"coordinates":[-114.35,42.25],"type":"Point"}
}