{
  "id": 7505010,
  "type": "Feature",
  "properties": {
    "tgn:hierarchy":[
        "tgn:7505010",
        "tgn:7520092",
        "tgn:1008380",
        "tgn:1000226",
        "tgn:1000006",
        "tgn:7029392"
    ],
    "tgn:id":7505010,
    "tgn:name:en":"Town Hill",
    "tgn:placetype":[
        "aat:300008777"
    ]
},
  "bbox": [],
  "geometry": {"coordinates":[178.0325,-38.629722],"type":"Point"}
}