{
  "id": 7123221,
  "type": "Feature",
  "properties": {
    "tgn:hierarchy":[
        "tgn:7123221",
        "tgn:1000003",
        "tgn:7003689",
        "tgn:7000084",
        "tgn:7029392"
    ],
    "tgn:id":7123221,
    "tgn:name":"Neustadt",
    "tgn:placetype":[
        "aat:300008347"
    ]
},
  "bbox": [],
  "geometry": {"coordinates":[10.466667,51.466667],"type":"Point"}
}