{
  "id": 1027945,
  "type": "Feature",
  "properties": {
    "tgn:hierarchy":[
        "tgn:1027945",
        "tgn:7594006",
        "tgn:1000003",
        "tgn:1000066",
        "tgn:7029392"
    ],
    "tgn:id":1027945,
    "tgn:name":"Juelsminde",
    "tgn:placetype":[
        "aat:300008347"
    ]
},
  "bbox": [],
  "geometry": {"coordinates":[10.0333,55.7167],"type":"Point"}
}