{
  "id": 7385948,
  "type": "Feature",
  "properties": {
    "tgn:hierarchy":[
        "tgn:7385948",
        "tgn:7005586",
        "tgn:1000001",
        "tgn:7005560",
        "tgn:7029392"
    ],
    "tgn:id":7385948,
    "tgn:name":"Pi\u00f1uela",
    "tgn:placetype":[
        "aat:300008347"
    ]
},
  "bbox": [],
  "geometry": {"coordinates":[-104.283333,20.033333],"type":"Point"}
}