{
  "id": 1041635,
  "type": "Feature",
  "properties": {
    "tgn:hierarchy":[
        "tgn:1041635",
        "tgn:1000003",
        "tgn:7003682",
        "tgn:7000084",
        "tgn:7029392"
    ],
    "tgn:id":1041635,
    "tgn:name":"Waldmohr",
    "tgn:placetype":[
        "aat:300008347"
    ]
},
  "bbox": [],
  "geometry": {"coordinates":[7.333333,49.383333],"type":"Point"}
}