{
  "id": 2578176,
  "type": "Feature",
  "properties": {
    "tgn:hierarchy":[
        "tgn:2578176",
        "tgn:1000001",
        "tgn:7016172",
        "tgn:7012149",
        "tgn:7029392"
    ],
    "tgn:id":2578176,
    "tgn:name":"Peyton Creek",
    "tgn:placetype":[
        "aat:300008706"
    ]
},
  "bbox": [],
  "geometry": {"coordinates":[-92.6333,35.7667],"type":"Point"}
}