{
  "id": 2483944,
  "type": "Feature",
  "properties": {
    "tgn:hierarchy":[
        "tgn:2483944",
        "tgn:1000001",
        "tgn:7012149",
        "tgn:2001717",
        "tgn:7007708",
        "tgn:7029392"
    ],
    "tgn:id":2483944,
    "tgn:name":"Latigo Lake",
    "tgn:placetype":[
        "aat:300008680"
    ]
},
  "bbox": [],
  "geometry": {"coordinates":[-121.9167,44.4833],"type":"Point"}
}