{
  "id": 7545088,
  "type": "Feature",
  "properties": {
    "tgn:hierarchy":[
        "tgn:7545088",
        "tgn:1000004",
        "tgn:7000198",
        "tgn:7016722",
        "tgn:7029392"
    ],
    "tgn:id":7545088,
    "tgn:name:en":"Bhauv\u0101p\u0101r",
    "tgn:placetype":[
        "aat:300008347"
    ]
},
  "bbox": [],
  "geometry": {"coordinates":[83.372418,26.66846],"type":"Point"}
}