{
  "id": 2336005,
  "type": "Feature",
  "properties": {
    "tgn:hierarchy":[
        "tgn:2336005",
        "tgn:1002141",
        "tgn:1000001",
        "tgn:7012149",
        "tgn:7007568",
        "tgn:7029392"
    ],
    "tgn:id":2336005,
    "tgn:name":"Foster Brook",
    "tgn:placetype":[
        "aat:300008699"
    ]
},
  "bbox": [],
  "geometry": {"coordinates":[-78.2333,42.0333],"type":"Point"}
}