{
  "id": 7448036,
  "type": "Feature",
  "properties": {
    "tgn:hierarchy":[
        "tgn:7448036",
        "tgn:7002445",
        "tgn:1000003",
        "tgn:7012034",
        "tgn:7008591",
        "tgn:7029392"
    ],
    "tgn:id":7448036,
    "tgn:name:en":"Ryton",
    "tgn:placetype":[
        "aat:300008347"
    ]
},
  "bbox": [],
  "geometry": {"coordinates":[-2.35,52.616667],"type":"Point"}
}