{
  "id": 2188854,
  "type": "Feature",
  "properties": {
    "tgn:hierarchy":[
        "tgn:2188854",
        "tgn:1000001",
        "tgn:7012149",
        "tgn:1002943",
        "tgn:7007708",
        "tgn:7029392"
    ],
    "tgn:id":2188854,
    "tgn:name":"Boulder Creek",
    "tgn:placetype":[
        "aat:300008706"
    ]
},
  "bbox": [],
  "geometry": {"coordinates":[-123.75,45.2167],"type":"Point"}
}