<<<<<<< HEAD
{
  "id": 7488799,
  "type": "Feature",
  "properties": {
    "tgn:hierarchy":[
        "tgn:7488799",
        "tgn:7001004",
        "tgn:1000004",
        "tgn:1000141",
        "tgn:7029392"
    ],
    "tgn:id":7488799,
    "tgn:name":"Kuhanuoxin Shan",
    "tgn:placetype":[
        "aat:300008798"
    ]
},
  "bbox": [],
  "geometry": {"coordinates":[120.900072,23.262888],"type":"Point"}
}
=======
{"geometry":{"type":"Point","coordinates":[120.900072,23.262888]},"type":"Feature","properties":{"hierarchy":["tgn:7488799","tgn:7001004","tgn:1000004","tgn:1000141","tgn:7029392"],"placetype":["aat:300008798"],"id":7488799,"name:xx":"Kuhanuoxin Shan"}}
>>>>>>> 03f74aca74312dbeaf24d7e61306dd6a786dc3d0
