{
  "id": 7145278,
  "type": "Feature",
  "properties": {
    "tgn:hierarchy":[
        "tgn:7145278",
        "tgn:1000003",
        "tgn:7003677",
        "tgn:7000084",
        "tgn:7029392"
    ],
    "tgn:id":7145278,
    "tgn:name":"Bahnhof K\u00f6ln West",
    "tgn:placetype":[
        "aat:300007783"
    ]
},
  "bbox": [],
  "geometry": {"coordinates":[6.934167,50.944167],"type":"Point"}
}