{
  "id": 1043812,
  "type": "Feature",
  "properties": {
    "tgn:hierarchy":[
        "tgn:1043812",
        "tgn:1003489",
        "tgn:7004610",
        "tgn:1000003",
        "tgn:1000080",
        "tgn:7029392"
    ],
    "tgn:id":1043812,
    "tgn:name":"Cancellara",
    "tgn:placetype":[
        "aat:300008347"
    ]
},
  "bbox": [],
  "geometry": {"coordinates":[15.933333,40.733333],"type":"Point"}
}