{
  "id": 7347346,
  "type": "Feature",
  "properties": {
    "tgn:hierarchy":[
        "tgn:7347346",
        "tgn:7002849",
        "tgn:1000003",
        "tgn:7009604",
        "tgn:1000095",
        "tgn:7029392"
    ],
    "tgn:id":7347346,
    "tgn:name":"Arcocha",
    "tgn:placetype":[
        "aat:300008347"
    ]
},
  "bbox": [],
  "geometry": {"coordinates":[-3.029227,43.303354],"type":"Point"}
}