{
  "id": 2446763,
  "type": "Feature",
  "properties": {
    "tgn:hierarchy":[
        "tgn:2446763",
        "tgn:1000001",
        "tgn:1002665",
        "tgn:7012149",
        "tgn:7007517",
        "tgn:7029392"
    ],
    "tgn:id":2446763,
    "tgn:name":"Lexington Reservoir",
    "tgn:placetype":[
        "aat:300006191"
    ]
},
  "bbox": [],
  "geometry": {"coordinates":[-71.2333,42.4333],"type":"Point"}
}