{
  "id": 7480098,
  "type": "Feature",
  "properties": {
    "tgn:hierarchy":[
        "tgn:7480098",
        "tgn:1000004",
        "tgn:7490934",
        "tgn:1000141",
        "tgn:7029392"
    ],
    "tgn:id":7480098,
    "tgn:name":"Shiziqi",
    "tgn:placetype":[
        "aat:300008777"
    ]
},
  "bbox": [],
  "geometry": {"coordinates":[120.377645,23.082209],"type":"Point"}
}