{
  "id": 1073985,
  "type": "Feature",
  "properties": {
    "tgn:hierarchy":[
        "tgn:1073985",
        "tgn:1000004",
        "tgn:7002087",
        "tgn:1000111",
        "tgn:7029392"
    ],
    "tgn:id":1073985,
    "tgn:name":"Zhenjiangguan",
    "tgn:placetype":[
        "aat:300008347"
    ]
},
  "bbox": [],
  "geometry": {"coordinates":[103.7167,32.3167],"type":"Point"}
}