{
  "id": 7361464,
  "type": "Feature",
  "properties": {
    "tgn:hierarchy":[
        "tgn:7361464",
        "tgn:7005583",
        "tgn:1000001",
        "tgn:7005560",
        "tgn:7029392"
    ],
    "tgn:id":7361464,
    "tgn:name":"Rancho El Ojo de Agua",
    "tgn:placetype":[
        "aat:300000241"
    ]
},
  "bbox": [],
  "geometry": {"coordinates":[-105.616667,26.283333],"type":"Point"}
}