{
  "id": 7075474,
  "type": "Feature",
  "properties": {
    "tgn:hierarchy":[
        "tgn:7075474",
        "tgn:1000003",
        "tgn:7003685",
        "tgn:7000084",
        "tgn:7029392"
    ],
    "tgn:id":7075474,
    "tgn:name":"Z\u00f6blitz-Bach",
    "tgn:placetype":[
        "aat:300008699"
    ]
},
  "bbox": [],
  "geometry": {"coordinates":[13.266667,50.683333],"type":"Point"}
}