{
  "id": 7404091,
  "type": "Feature",
  "properties": {
    "tgn:hierarchy":[
        "tgn:7404091",
        "tgn:7016644",
        "tgn:1000001",
        "tgn:7005560",
        "tgn:7029392"
    ],
    "tgn:id":7404091,
    "tgn:name":"La Ver\u00f3nica",
    "tgn:placetype":[
        "aat:300008347"
    ]
},
  "bbox": [],
  "geometry": {"coordinates":[-103.868056,18.858333],"type":"Point"}
}