{
  "id": 2092433,
  "type": "Feature",
  "properties": {
    "tgn:hierarchy":[
        "tgn:2092433",
        "tgn:1000001",
        "tgn:7012149",
        "tgn:1002520",
        "tgn:7007710",
        "tgn:7029392"
    ],
    "tgn:id":2092433,
    "tgn:name":"Reynoldsville",
    "tgn:placetype":[
        "aat:300008347"
    ]
},
  "bbox": [],
  "geometry": {"coordinates":[-78.8833,41.0833],"type":"Point"}
}