{
  "id": 2279952,
  "type": "Feature",
  "properties": {
    "tgn:hierarchy":[
        "tgn:2279952",
        "tgn:1000001",
        "tgn:7012149",
        "tgn:2001253",
        "tgn:7007523",
        "tgn:7029392"
    ],
    "tgn:id":2279952,
    "tgn:name":"Dean Lake",
    "tgn:placetype":[
        "aat:300008680"
    ]
},
  "bbox": [],
  "geometry": {"coordinates":[-94.3833,37.8833],"type":"Point"}
}