{
  "id": 2132447,
  "type": "Feature",
  "properties": {
    "tgn:hierarchy":[
        "tgn:2132447",
        "tgn:1002165",
        "tgn:1000001",
        "tgn:7012149",
        "tgn:7007517",
        "tgn:7029392"
    ],
    "tgn:id":2132447,
    "tgn:name":"Amos Pond",
    "tgn:placetype":[
        "aat:300008680"
    ]
},
  "bbox": [],
  "geometry": {"coordinates":[-70.45,41.6333],"type":"Point"}
}