{
  "id": 7390736,
  "type": "Feature",
  "properties": {
    "tgn:hierarchy":[
        "tgn:7390736",
        "tgn:7005580",
        "tgn:1000001",
        "tgn:7005560",
        "tgn:7029392"
    ],
    "tgn:id":7390736,
    "tgn:name":"Rio Arriba",
    "tgn:placetype":[
        "aat:300008347"
    ]
},
  "bbox": [],
  "geometry": {"coordinates":[-92.716667,15.158333],"type":"Point"}
}