{
  "id": 2329900,
  "type": "Feature",
  "properties": {
    "tgn:hierarchy":[
        "tgn:2329900",
        "tgn:1000001",
        "tgn:7012149",
        "tgn:2002272",
        "tgn:7013961",
        "tgn:7029392"
    ],
    "tgn:id":2329900,
    "tgn:name":"Flag Knob",
    "tgn:placetype":[
        "aat:300008798"
    ]
},
  "bbox": [],
  "geometry": {"coordinates":[-82.2167,38.2333],"type":"Point"}
}