{
  "id": 7326854,
  "type": "Feature",
  "properties": {
    "tgn:hierarchy":[
        "tgn:7326854",
        "tgn:7001158",
        "tgn:7002850",
        "tgn:1000003",
        "tgn:1000095",
        "tgn:7029392"
    ],
    "tgn:id":7326854,
    "tgn:name":"Peleagonzalo",
    "tgn:placetype":[
        "aat:300008347"
    ]
},
  "bbox": [],
  "geometry": {"coordinates":[-5.483333,41.483333],"type":"Point"}
}