<<<<<<< HEAD
{
  "id": 7176412,
  "type": "Feature",
  "properties": {
    "tgn:hierarchy":[
        "tgn:7176412",
        "tgn:1000003",
        "tgn:7003678",
        "tgn:7000084",
        "tgn:7029392"
    ],
    "tgn:id":7176412,
    "tgn:name":"Gr\u00fcnhof",
    "tgn:placetype":[
        "aat:300000206"
    ]
},
  "bbox": [],
  "geometry": {"coordinates":[9.416667,51.05],"type":"Point"}
}
=======
{"geometry":{"type":"Point","coordinates":[9.416667,51.050000]},"type":"Feature","properties":{"hierarchy":["tgn:7176412","tgn:1000003","tgn:7003678","tgn:7000084","tgn:7029392"],"placetype":["aat:300000206"],"id":7176412,"name:xx":"Gr\u00fcnhof"}}
>>>>>>> 03f74aca74312dbeaf24d7e61306dd6a786dc3d0
