{
  "id": 7586607,
  "type": "Feature",
  "properties": {
    "tgn:hierarchy":[
        "tgn:7586607",
        "tgn:1000004",
        "tgn:7000198",
        "tgn:7000799",
        "tgn:7029392"
    ],
    "tgn:id":7586607,
    "tgn:name:en":"Ganga Gali",
    "tgn:placetype":[
        "aat:300259572"
    ]
},
  "bbox": [],
  "geometry": {"coordinates":[74.901389,34.45],"type":"Point"}
}