{
  "id": 7462081,
  "type": "Feature",
  "properties": {
    "tgn:hierarchy":[
        "tgn:7462081",
        "tgn:7002445",
        "tgn:7008103",
        "tgn:1000003",
        "tgn:7008591",
        "tgn:7029392"
    ],
    "tgn:id":7462081,
    "tgn:name:en":"Little Staughton",
    "tgn:placetype":[
        "aat:300008347"
    ]
},
  "bbox": [],
  "geometry": {"coordinates":[-0.383333,52.25],"type":"Point"}
}