{
  "id": 7496527,
  "type": "Feature",
  "properties": {
    "tgn:hierarchy":[
        "tgn:7496527",
        "tgn:7468018",
        "tgn:1000004",
        "tgn:1000141",
        "tgn:7029392"
    ],
    "tgn:id":7496527,
    "tgn:name":"Yantan Dapaishui",
    "tgn:placetype":[
        "aat:300006075"
    ]
},
  "bbox": [],
  "geometry": {"coordinates":[120.372548,23.610958],"type":"Point"}
}