<<<<<<< HEAD
{
  "id": 7113222,
  "type": "Feature",
  "properties": {
    "tgn:hierarchy":[
        "tgn:7113222",
        "tgn:7003692",
        "tgn:1000003",
        "tgn:7000084",
        "tgn:7029392"
    ],
    "tgn:id":7113222,
    "tgn:name":"Riesenk\u00f6pfle",
    "tgn:placetype":[
        "aat:300008795"
    ]
},
  "bbox": [],
  "geometry": {"coordinates":[8.25,48.55],"type":"Point"}
}
=======
{"geometry":{"type":"Point","coordinates":[8.250000,48.550000]},"type":"Feature","properties":{"hierarchy":["tgn:7113222","tgn:7003692","tgn:1000003","tgn:7000084","tgn:7029392"],"placetype":["aat:300008795"],"id":7113222,"name:xx":"Riesenk\u00f6pfle"}}
>>>>>>> 03f74aca74312dbeaf24d7e61306dd6a786dc3d0
