{
  "id": 7498855,
  "type": "Feature",
  "properties": {
    "tgn:hierarchy":[
        "tgn:7498855",
        "tgn:1000004",
        "tgn:7491221",
        "tgn:1000141",
        "tgn:7029392"
    ],
    "tgn:id":7498855,
    "tgn:name":"Kangle Daqiao",
    "tgn:placetype":[
        "aat:300007836"
    ]
},
  "bbox": [],
  "geometry": {"coordinates":[121.136257,22.754361],"type":"Point"}
}