{
  "id": 2532340,
  "type": "Feature",
  "properties": {
    "tgn:hierarchy":[
        "tgn:2532340",
        "tgn:7030516",
        "tgn:7006450",
        "tgn:1000001",
        "tgn:7012149",
        "tgn:7029392"
    ],
    "tgn:id":2532340,
    "tgn:name":"Murder Point",
    "tgn:placetype":[
        "aat:300008850"
    ]
},
  "bbox": [],
  "geometry": {"coordinates":[173.1667,52.7833],"type":"Point"}
}