{
  "id": 7133751,
  "type": "Feature",
  "properties": {
    "tgn:hierarchy":[
        "tgn:7133751",
        "tgn:1000003",
        "tgn:7003676",
        "tgn:7000084",
        "tgn:7029392"
    ],
    "tgn:id":7133751,
    "tgn:name":"F\u00f6rsterei Neerensett",
    "tgn:placetype":[
        "aat:300004792"
    ]
},
  "bbox": [],
  "geometry": {"coordinates":[8.433333,52.483333],"type":"Point"}
}