<<<<<<< HEAD
{
  "id": 2252042,
  "type": "Feature",
  "properties": {
    "tgn:hierarchy":[
        "tgn:2252042",
        "tgn:1000001",
        "tgn:2000868",
        "tgn:7012149",
        "tgn:7007256",
        "tgn:7029392"
    ],
    "tgn:id":2252042,
    "tgn:name":"Concordia, Lake",
    "tgn:placetype":[
        "aat:300008680"
    ]
},
  "bbox": [],
  "geometry": {"coordinates":[-91.5167,31.6333],"type":"Point"}
}
=======
{"geometry":{"type":"Point","coordinates":[-91.516700,31.633300]},"type":"Feature","properties":{"hierarchy":["tgn:2252042","tgn:1000001","tgn:2000868","tgn:7012149","tgn:7007256","tgn:7029392"],"placetype":["aat:300008680"],"id":2252042,"name:xx":"Concordia, Lake"}}
>>>>>>> 03f74aca74312dbeaf24d7e61306dd6a786dc3d0
