{
  "id": 2252042,
  "type": "Feature",
  "properties": {
    "tgn:hierarchy":[
        "tgn:2252042",
        "tgn:1000001",
        "tgn:2000868",
        "tgn:7012149",
        "tgn:7007256",
        "tgn:7029392"
    ],
    "tgn:id":2252042,
    "tgn:name":"Concordia, Lake",
    "tgn:placetype":[
        "aat:300008680"
    ]
},
  "bbox": [],
  "geometry": {"coordinates":[-91.5167,31.6333],"type":"Point"}
}