{
  "id": 2180756,
  "type": "Feature",
  "properties": {
    "tgn:hierarchy":[
        "tgn:2180756",
        "tgn:1000001",
        "tgn:1002340",
        "tgn:7012149",
        "tgn:7007526",
        "tgn:7029392"
    ],
    "tgn:id":2180756,
    "tgn:name":"Blossom Canyon",
    "tgn:placetype":[
        "aat:300008761"
    ]
},
  "bbox": [],
  "geometry": {"coordinates":[-119.55,38.8167],"type":"Point"}
}