<<<<<<< HEAD
{
  "id": 2151138,
  "type": "Feature",
  "properties": {
    "tgn:hierarchy":[
        "tgn:2151138",
        "tgn:1000001",
        "tgn:7012149",
        "tgn:7007825",
        "tgn:7029392"
    ],
    "tgn:id":2151138,
    "tgn:name":"Bat Creek",
    "tgn:placetype":[
        "aat:300008706"
    ]
},
  "bbox": [],
  "geometry": {"coordinates":[-84.4,35.5167],"type":"Point"}
}
=======
{"geometry":{"type":"Point","coordinates":[-84.400000,35.516700]},"type":"Feature","properties":{"hierarchy":["tgn:2151138","tgn:1000001","tgn:7012149","tgn:7007825","tgn:7029392"],"placetype":["aat:300008706"],"id":2151138,"name:xx":"Bat Creek"}}
>>>>>>> 03f74aca74312dbeaf24d7e61306dd6a786dc3d0
