{
  "id": 7324054,
  "type": "Feature",
  "properties": {
    "tgn:hierarchy":[
        "tgn:7324054",
        "tgn:7002810",
        "tgn:7001158",
        "tgn:1000003",
        "tgn:1000095",
        "tgn:7029392"
    ],
    "tgn:id":7324054,
    "tgn:name":"Santa Olalla de Valdivielso",
    "tgn:placetype":[
        "aat:300008347"
    ]
},
  "bbox": [],
  "geometry": {"coordinates":[-3.566667,42.833333],"type":"Point"}
}