{
  "id": 7003082,
  "type": "Feature",
  "properties": {
    "tgn:hierarchy":[
        "tgn:7003082",
        "tgn:7002994",
        "tgn:1000003",
        "tgn:7002997",
        "tgn:1000080",
        "tgn:7029392"
    ],
    "tgn:id":7003082,
    "tgn:name":"Piove di Sacco",
    "tgn:placetype":[
        "aat:300008347"
    ]
},
  "bbox": [],
  "geometry": {"coordinates":[12.042778,45.2975],"type":"Point"}
}