{
  "id": 7285623,
  "type": "Feature",
  "properties": {
    "tgn:hierarchy":[
        "tgn:7285623",
        "tgn:7002464",
        "tgn:1000049",
        "tgn:1000002",
        "tgn:7029392"
    ],
    "tgn:id":7285623,
    "tgn:name":"Pichincho, Cerro",
    "tgn:placetype":[
        "aat:300008777"
    ]
},
  "bbox": [],
  "geometry": {"coordinates":[-69.35,-18.033333],"type":"Point"}
}