<<<<<<< HEAD
{
  "id": 7179771,
  "type": "Feature",
  "properties": {
    "tgn:hierarchy":[
        "tgn:7179771",
        "tgn:1000003",
        "tgn:7003685",
        "tgn:7000084",
        "tgn:7029392"
    ],
    "tgn:id":7179771,
    "tgn:name":"Gr\u00fcnp\u00f6hl",
    "tgn:placetype":[
        "aat:300008347"
    ]
},
  "bbox": [],
  "geometry": {"coordinates":[12.083333,50.35],"type":"Point"}
}
=======
{"geometry":{"type":"Point","coordinates":[12.083333,50.350000]},"type":"Feature","properties":{"hierarchy":["tgn:7179771","tgn:1000003","tgn:7003685","tgn:7000084","tgn:7029392"],"placetype":["aat:300008347"],"id":7179771,"name:xx":"Gr\u00fcnp\u00f6hl"}}
>>>>>>> 03f74aca74312dbeaf24d7e61306dd6a786dc3d0
