<<<<<<< HEAD
{
  "id": 2331201,
  "type": "Feature",
  "properties": {
    "tgn:hierarchy":[
        "tgn:2331201",
        "tgn:1000001",
        "tgn:7006451",
        "tgn:7012149",
        "tgn:2000102",
        "tgn:7029392"
    ],
    "tgn:id":2331201,
    "tgn:name":"Flat Top Mountain",
    "tgn:placetype":[
        "aat:300008798"
    ]
},
  "bbox": [],
  "geometry": {"coordinates":[-111.2167,31.3833],"type":"Point"}
}
=======
{"geometry":{"type":"Point","coordinates":[-111.216700,31.383300]},"type":"Feature","properties":{"hierarchy":["tgn:2331201","tgn:1000001","tgn:7006451","tgn:7012149","tgn:2000102","tgn:7029392"],"placetype":["aat:300008798"],"id":2331201,"name:xx":"Flat Top Mountain"}}
>>>>>>> 03f74aca74312dbeaf24d7e61306dd6a786dc3d0
