{
  "id": 2331201,
  "type": "Feature",
  "properties": {
    "tgn:hierarchy":[
        "tgn:2331201",
        "tgn:1000001",
        "tgn:7006451",
        "tgn:7012149",
        "tgn:2000102",
        "tgn:7029392"
    ],
    "tgn:id":2331201,
    "tgn:name":"Flat Top Mountain",
    "tgn:placetype":[
        "aat:300008798"
    ]
},
  "bbox": [],
  "geometry": {"coordinates":[-111.2167,31.3833],"type":"Point"}
}