{
  "id": 2456349,
  "type": "Feature",
  "properties": {
    "tgn:hierarchy":[
        "tgn:2456349",
        "tgn:1000001",
        "tgn:1002753",
        "tgn:7012149",
        "tgn:7007828",
        "tgn:7029392"
    ],
    "tgn:id":2456349,
    "tgn:name":"Little Hosmer Pond",
    "tgn:placetype":[
        "aat:300008680"
    ]
},
  "bbox": [],
  "geometry": {"coordinates":[-72.3667,44.6667],"type":"Point"}
}