{
  "id": 7042291,
  "type": "Feature",
  "properties": {
    "tgn:hierarchy":[
        "tgn:7042291",
        "tgn:7003137",
        "tgn:1000003",
        "tgn:7003080",
        "tgn:1000080",
        "tgn:7029392"
    ],
    "tgn:id":7042291,
    "tgn:name":"Rocca di Botte",
    "tgn:placetype":[
        "aat:300008347"
    ]
},
  "bbox": [],
  "geometry": {"coordinates":[13.066667,42.016667],"type":"Point"}
}