{
  "id": 2269941,
  "type": "Feature",
  "properties": {
    "tgn:hierarchy":[
        "tgn:2269941",
        "tgn:1000001",
        "tgn:7012149",
        "tgn:1002944",
        "tgn:7007568",
        "tgn:7029392"
    ],
    "tgn:id":2269941,
    "tgn:name":"Crum Town",
    "tgn:placetype":[
        "aat:300008347"
    ]
},
  "bbox": [],
  "geometry": {"coordinates":[-76.4333,42.25],"type":"Point"}
}