{
  "id": 2481807,
  "type": "Feature",
  "properties": {
    "tgn:hierarchy":[
        "tgn:2481807",
        "tgn:7006450",
        "tgn:1000001",
        "tgn:7012149",
        "tgn:2000086",
        "tgn:7029392"
    ],
    "tgn:id":2481807,
    "tgn:name":"Landmark Gap Lake",
    "tgn:placetype":[
        "aat:300008680"
    ]
},
  "bbox": [],
  "geometry": {"coordinates":[-146.0833,63.1167],"type":"Point"}
}