{
  "id": 2241553,
  "type": "Feature",
  "properties": {
    "tgn:hierarchy":[
        "tgn:2241553",
        "tgn:1000001",
        "tgn:7012149",
        "tgn:1002809",
        "tgn:7007252",
        "tgn:7029392"
    ],
    "tgn:id":2241553,
    "tgn:name":"Clarks",
    "tgn:placetype":[
        "aat:300008347"
    ]
},
  "bbox": [],
  "geometry": {"coordinates":[-86.8833,41.1333],"type":"Point"}
}