{
  "id": 1064572,
  "type": "Feature",
  "properties": {
    "tgn:hierarchy":[
        "tgn:1064572",
        "tgn:7002443",
        "tgn:5000552",
        "tgn:1000003",
        "tgn:7008591",
        "tgn:7029392"
    ],
    "tgn:id":1064572,
    "tgn:name:en":"Ammanford",
    "tgn:placetype":[
        "aat:300008347",
        "aat:300008375"
    ]
},
  "bbox": [],
  "geometry": {"coordinates":[-3.989167,51.791944],"type":"Point"}
}