{
  "id": 2051872,
  "type": "Feature",
  "properties": {
    "tgn:hierarchy":[
        "tgn:2051872",
        "tgn:1000001",
        "tgn:1002182",
        "tgn:7012149",
        "tgn:7007520",
        "tgn:7029392"
    ],
    "tgn:id":2051872,
    "tgn:name":"Fair Plain",
    "tgn:placetype":[
        "aat:300008347"
    ]
},
  "bbox": [],
  "geometry": {"coordinates":[-86.45,42.0833],"type":"Point"}
}