{
  "id": 7424652,
  "type": "Feature",
  "properties": {
    "tgn:hierarchy":[
        "tgn:7424652",
        "tgn:1000001",
        "tgn:7005601",
        "tgn:7005560",
        "tgn:7029392"
    ],
    "tgn:id":7424652,
    "tgn:name":"Campo Nueve",
    "tgn:placetype":[
        "aat:300008347"
    ]
},
  "bbox": [],
  "geometry": {"coordinates":[-103.486111,24.073611],"type":"Point"}
}