{
  "id": 2651234,
  "type": "Feature",
  "properties": {
    "tgn:hierarchy":[
        "tgn:2651234",
        "tgn:1000001",
        "tgn:7012149",
        "tgn:2000490",
        "tgn:7007250",
        "tgn:7029392"
    ],
    "tgn:id":2651234,
    "tgn:name":"Section Corner Canyon",
    "tgn:placetype":[
        "aat:300008761"
    ]
},
  "bbox": [],
  "geometry": {"coordinates":[-112.9833,42.3833],"type":"Point"}
}