<<<<<<< HEAD
{
  "id": 7377568,
  "type": "Feature",
  "properties": {
    "tgn:hierarchy":[
        "tgn:7377568",
        "tgn:1000001",
        "tgn:1001906",
        "tgn:7005560",
        "tgn:7029392"
    ],
    "tgn:id":7377568,
    "tgn:name":"La Paz",
    "tgn:placetype":[
        "aat:300008347"
    ]
},
  "bbox": [],
  "geometry": {"coordinates":[-104.966667,21.2],"type":"Point"}
}
=======
{"geometry":{"type":"Point","coordinates":[-104.966667,21.200000]},"type":"Feature","properties":{"hierarchy":["tgn:7377568","tgn:1000001","tgn:1001906","tgn:7005560","tgn:7029392"],"placetype":["aat:300008347"],"id":7377568,"name:xx":"La Paz"}}
>>>>>>> 03f74aca74312dbeaf24d7e61306dd6a786dc3d0
