{
  "id": 7151983,
  "type": "Feature",
  "properties": {
    "tgn:hierarchy":[
        "tgn:7151983",
        "tgn:1000003",
        "tgn:7003688",
        "tgn:7000084",
        "tgn:7029392"
    ],
    "tgn:id":7151983,
    "tgn:name":"Jardelunder Wiesen",
    "tgn:placetype":[
        "aat:300386990"
    ]
},
  "bbox": [],
  "geometry": {"coordinates":[9.216667,54.85],"type":"Point"}
}