{
  "id": 2280363,
  "type": "Feature",
  "properties": {
    "tgn:hierarchy":[
        "tgn:2280363",
        "tgn:1000001",
        "tgn:1002209",
        "tgn:7012149",
        "tgn:7007252",
        "tgn:7029392"
    ],
    "tgn:id":2280363,
    "tgn:name":"Deckard Ridge",
    "tgn:placetype":[
        "aat:300266640"
    ]
},
  "bbox": [],
  "geometry": {"coordinates":[-86.35,39.0833],"type":"Point"}
}