{
  "id": 2060251,
  "type": "Feature",
  "properties": {
    "tgn:hierarchy":[
        "tgn:2060251",
        "tgn:2001170",
        "tgn:1000001",
        "tgn:7012149",
        "tgn:7007523",
        "tgn:7029392"
    ],
    "tgn:id":2060251,
    "tgn:name":"Ridgley",
    "tgn:placetype":[
        "aat:300008347",
        "aat:300387210"
    ]
},
  "bbox": [],
  "geometry": {"coordinates":[-94.0167,36.6833],"type":"Point"}
}