{
  "id": 1057132,
  "type": "Feature",
  "properties": {
    "tgn:hierarchy":[
        "tgn:1057132",
        "tgn:1000004",
        "tgn:7011523",
        "tgn:7002435",
        "tgn:7029392"
    ],
    "tgn:id":1057132,
    "tgn:name":"Morga",
    "tgn:placetype":[
        "aat:300008347"
    ]
},
  "bbox": [],
  "geometry": {"coordinates":[46.4833,54.4333],"type":"Point"}
}