{
  "id": 7054465,
  "type": "Feature",
  "properties": {
    "tgn:hierarchy":[
        "tgn:7054465",
        "tgn:7003154",
        "tgn:1000003",
        "tgn:7003120",
        "tgn:1000080",
        "tgn:7029392"
    ],
    "tgn:id":7054465,
    "tgn:name":"Monfret, Cime",
    "tgn:placetype":[
        "aat:300008798"
    ]
},
  "bbox": [],
  "geometry": {"coordinates":[7.166667,45.366667],"type":"Point"}
}