{
  "id": 7559198,
  "type": "Feature",
  "properties": {
    "tgn:hierarchy":[
        "tgn:7559198",
        "tgn:1000004",
        "tgn:7000198",
        "tgn:7016788",
        "tgn:7029392"
    ],
    "tgn:id":7559198,
    "tgn:name:en":"R\u0101haw\u0101s",
    "tgn:placetype":[
        "aat:300008347"
    ]
},
  "bbox": [],
  "geometry": {"coordinates":[76.335787,26.70003],"type":"Point"}
}