{
  "id": 7509820,
  "type": "Feature",
  "properties": {
    "tgn:hierarchy":[
        "tgn:7509820",
        "tgn:1009227",
        "tgn:1000226",
        "tgn:7016729",
        "tgn:1000006",
        "tgn:7029392"
    ],
    "tgn:id":7509820,
    "tgn:name:en":"Waikaihu Stream",
    "tgn:placetype":[
        "aat:300008699"
    ]
},
  "bbox": [],
  "geometry": {"coordinates":[173.766667,-41.316667],"type":"Point"}
}