<<<<<<< HEAD
{
  "id": 7249934,
  "type": "Feature",
  "properties": {
    "tgn:hierarchy":[
        "tgn:7249934",
        "tgn:7003460",
        "tgn:1000003",
        "tgn:1000063",
        "tgn:4012014",
        "tgn:7029392"
    ],
    "tgn:id":7249934,
    "tgn:name":"Pouhon, Bois",
    "tgn:placetype":[
        "aat:300008863"
    ]
},
  "bbox": [],
  "geometry": {"coordinates":[5.666667,50.416667],"type":"Point"}
}
=======
{"geometry":{"type":"Point","coordinates":[5.666667,50.416667]},"type":"Feature","properties":{"hierarchy":["tgn:7249934","tgn:7003460","tgn:1000003","tgn:1000063","tgn:4012014","tgn:7029392"],"placetype":["aat:300008863"],"id":7249934,"name:xx":"Pouhon, Bois"}}
>>>>>>> 03f74aca74312dbeaf24d7e61306dd6a786dc3d0
