{
  "id": 7005520,
  "type": "Feature",
  "properties": {
    "tgn:hierarchy":[
        "tgn:7005520",
        "tgn:1003440",
        "tgn:1000003",
        "tgn:7003124",
        "tgn:1000080",
        "tgn:7029392"
    ],
    "tgn:id":7005520,
    "tgn:name":"Terlano",
    "tgn:placetype":[
        "aat:300008347"
    ]
},
  "bbox": [],
  "geometry": {"coordinates":[11.25,46.533333],"type":"Point"}
}