{
  "id": 2595401,
  "type": "Feature",
  "properties": {
    "tgn:hierarchy":[
        "tgn:2595401",
        "tgn:1000001",
        "tgn:7012149",
        "tgn:2000376",
        "tgn:7007248",
        "tgn:7029392"
    ],
    "tgn:id":2595401,
    "tgn:name":"Potato Creek Structure Number 103 Lak",
    "tgn:placetype":[
        "aat:300006191"
    ]
},
  "bbox": [],
  "geometry": {"coordinates":[-84.1833,33.0333],"type":"Point"}
}