{
  "id": 7133680,
  "type": "Feature",
  "properties": {
    "tgn:hierarchy":[
        "tgn:7133680",
        "tgn:1000003",
        "tgn:7003682",
        "tgn:7000084",
        "tgn:7029392"
    ],
    "tgn:id":7133680,
    "tgn:name":"Moosalbe",
    "tgn:placetype":[
        "aat:300008699"
    ]
},
  "bbox": [],
  "geometry": {"coordinates":[7.65,49.283333],"type":"Point"}
}