<<<<<<< HEAD
{
  "id": 2330240,
  "type": "Feature",
  "properties": {
    "tgn:hierarchy":[
        "tgn:2330240",
        "tgn:1000001",
        "tgn:7012149",
        "tgn:1002839",
        "tgn:7007826",
        "tgn:7029392"
    ],
    "tgn:id":2330240,
    "tgn:name":"Flanigan Branch",
    "tgn:placetype":[
        "aat:300008699"
    ]
},
  "bbox": [],
  "geometry": {"coordinates":[-94.8167,32.1667],"type":"Point"}
}
=======
{"geometry":{"type":"Point","coordinates":[-94.816700,32.166700]},"type":"Feature","properties":{"hierarchy":["tgn:2330240","tgn:1000001","tgn:7012149","tgn:1002839","tgn:7007826","tgn:7029392"],"placetype":["aat:300008699"],"id":2330240,"name:xx":"Flanigan Branch"}}
>>>>>>> 03f74aca74312dbeaf24d7e61306dd6a786dc3d0
