<<<<<<< HEAD
{
  "id": 7488929,
  "type": "Feature",
  "properties": {
    "tgn:hierarchy":[
        "tgn:7488929",
        "tgn:1000004",
        "tgn:7467799",
        "tgn:1000141",
        "tgn:7029392"
    ],
    "tgn:id":7488929,
    "tgn:name":"Hushanyan",
    "tgn:placetype":[
        "aat:300008347"
    ]
},
  "bbox": [],
  "geometry": {"coordinates":[120.560057,24.044104],"type":"Point"}
}
=======
{"geometry":{"type":"Point","coordinates":[120.560057,24.044104]},"type":"Feature","properties":{"hierarchy":["tgn:7488929","tgn:1000004","tgn:7467799","tgn:1000141","tgn:7029392"],"placetype":["aat:300008347"],"id":7488929,"name:xx":"Hushanyan"}}
>>>>>>> 03f74aca74312dbeaf24d7e61306dd6a786dc3d0
