{
  "id": 7449666,
  "type": "Feature",
  "properties": {
    "tgn:hierarchy":[
        "tgn:7449666",
        "tgn:7002444",
        "tgn:1000003",
        "tgn:5000460",
        "tgn:7008591",
        "tgn:7029392"
    ],
    "tgn:id":7449666,
    "tgn:name:en":"Flanders Moss",
    "tgn:placetype":[
        "aat:300008903"
    ]
},
  "bbox": [],
  "geometry": {"coordinates":[-4.316667,56.133333],"type":"Point"}
}