{
  "id": 2176623,
  "type": "Feature",
  "properties": {
    "tgn:hierarchy":[
        "tgn:2176623",
        "tgn:1000001",
        "tgn:7012149",
        "tgn:7007520",
        "tgn:7029392"
    ],
    "tgn:id":2176623,
    "tgn:name":"Black Lake State Forest",
    "tgn:placetype":[
        "aat:300008863"
    ]
},
  "bbox": [],
  "geometry": {"coordinates":[-84.3167,45.4167],"type":"Point"}
}