{
  "id": 2295402,
  "type": "Feature",
  "properties": {
    "tgn:hierarchy":[
        "tgn:2295402",
        "tgn:1000001",
        "tgn:7012149",
        "tgn:1002990",
        "tgn:7007708",
        "tgn:7029392"
    ],
    "tgn:id":2295402,
    "tgn:name":"Drill Box Canyon",
    "tgn:placetype":[
        "aat:300008761"
    ]
},
  "bbox": [],
  "geometry": {"coordinates":[-120.95,45.5333],"type":"Point"}
}