{
  "id": 7312966,
  "type": "Feature",
  "properties": {
    "tgn:hierarchy":[
        "tgn:7312966",
        "tgn:1001695",
        "tgn:1000049",
        "tgn:1000002",
        "tgn:7029392"
    ],
    "tgn:id":7312966,
    "tgn:name":"La Poblaci\u00f3n, Estero de",
    "tgn:placetype":[
        "aat:300008699"
    ]
},
  "bbox": [],
  "geometry": {"coordinates":[-71.916667,-34.65],"type":"Point"}
}