{
  "id": 7519386,
  "type": "Feature",
  "properties": {
    "tgn:hierarchy":[
        "tgn:7519386",
        "tgn:7000508",
        "tgn:1008380",
        "tgn:1000226",
        "tgn:1000006",
        "tgn:7029392"
    ],
    "tgn:id":7519386,
    "tgn:name:en":"Albert, Mount",
    "tgn:placetype":[
        "aat:300008795"
    ]
},
  "bbox": [],
  "geometry": {"coordinates":[174.716667,-36.883333],"type":"Point"}
}