{
  "id": 7297525,
  "type": "Feature",
  "properties": {
    "tgn:hierarchy":[
        "tgn:7297525",
        "tgn:7002759",
        "tgn:7008909",
        "tgn:1000003",
        "tgn:1000095",
        "tgn:7029392"
    ],
    "tgn:id":7297525,
    "tgn:name":"Suelves",
    "tgn:placetype":[
        "aat:300008347"
    ]
},
  "bbox": [],
  "geometry": {"coordinates":[0.107909,42.214936],"type":"Point"}
}