{
  "id": 1115025,
  "type": "Feature",
  "properties": {
    "tgn:hierarchy":[
        "tgn:1115025",
        "tgn:1000001",
        "tgn:7012149",
        "tgn:7029392"
    ],
    "tgn:id":1115025,
    "tgn:name":"Pocomoke Sound",
    "tgn:placetype":[
        "aat:300266558"
    ]
},
  "bbox": [],
  "geometry": {"coordinates":[-75.7833,37.9167],"type":"Point"}
}