{
  "id": 2622650,
  "type": "Feature",
  "properties": {
    "tgn:hierarchy":[
        "tgn:2622650",
        "tgn:2001088",
        "tgn:1000001",
        "tgn:7012149",
        "tgn:7007522",
        "tgn:7029392"
    ],
    "tgn:id":2622650,
    "tgn:name":"Robinson Creek",
    "tgn:placetype":[
        "aat:300008706"
    ]
},
  "bbox": [],
  "geometry": {"coordinates":[-90.7333,31.2833],"type":"Point"}
}