{
  "id": 2004566,
  "type": "Feature",
  "properties": {
    "tgn:hierarchy":[
        "tgn:2004566",
        "tgn:7002659",
        "tgn:1000001",
        "tgn:7012149",
        "tgn:2000062",
        "tgn:7029392"
    ],
    "tgn:id":2004566,
    "tgn:name":"Moores Bridge",
    "tgn:placetype":[
        "aat:300008347",
        "aat:300387210"
    ]
},
  "bbox": [],
  "geometry": {"coordinates":[-87.7833,33.4333],"type":"Point"}
}