{
  "id": 2559602,
  "type": "Feature",
  "properties": {
    "tgn:hierarchy":[
        "tgn:2559602",
        "tgn:1000001",
        "tgn:7012149",
        "tgn:7007825",
        "tgn:7029392"
    ],
    "tgn:id":2559602,
    "tgn:name":"Oostanaula Creek",
    "tgn:placetype":[
        "aat:300008706"
    ]
},
  "bbox": [],
  "geometry": {"coordinates":[-84.4333,35.5167],"type":"Point"}
}