{
  "id": 7180762,
  "type": "Feature",
  "properties": {
    "tgn:hierarchy":[
        "tgn:7180762",
        "tgn:1000003",
        "tgn:7003678",
        "tgn:7000084",
        "tgn:7029392"
    ],
    "tgn:id":7180762,
    "tgn:name":"Gasterfelder Holz",
    "tgn:placetype":[
        "aat:300008863"
    ]
},
  "bbox": [],
  "geometry": {"coordinates":[9.116667,51.333333],"type":"Point"}
}