{
  "id": 7395982,
  "type": "Feature",
  "properties": {
    "tgn:hierarchy":[
        "tgn:7395982",
        "tgn:1000001",
        "tgn:7005589",
        "tgn:7005560",
        "tgn:7029392"
    ],
    "tgn:id":7395982,
    "tgn:name":"San Juan",
    "tgn:placetype":[
        "aat:300008347"
    ]
},
  "bbox": [],
  "geometry": {"coordinates":[-100.05,24.966667],"type":"Point"}
}