{
  "id": 1054681,
  "type": "Feature",
  "properties": {
    "tgn:hierarchy":[
        "tgn:1054681",
        "tgn:1000004",
        "tgn:6003227",
        "tgn:7018214",
        "tgn:7002435",
        "tgn:7029392"
    ],
    "tgn:id":1054681,
    "tgn:name":"Yeloshnoye",
    "tgn:placetype":[
        "aat:300008347"
    ]
},
  "bbox": [],
  "geometry": {"coordinates":[66.7833,55.4667],"type":"Point"}
}