{
  "id": 2566510,
  "type": "Feature",
  "properties": {
    "tgn:hierarchy":[
        "tgn:2566510",
        "tgn:1000001",
        "tgn:1002270",
        "tgn:7012149",
        "tgn:7007708",
        "tgn:7029392"
    ],
    "tgn:id":2566510,
    "tgn:name":"Pan Creek",
    "tgn:placetype":[
        "aat:300008706"
    ]
},
  "bbox": [],
  "geometry": {"coordinates":[-121.8667,45.0167],"type":"Point"}
}