{
  "id": 7564463,
  "type": "Feature",
  "properties": {
    "tgn:hierarchy":[
        "tgn:7564463",
        "tgn:1000004",
        "tgn:7000198",
        "tgn:7016722",
        "tgn:7029392"
    ],
    "tgn:id":7564463,
    "tgn:name:en":"Mohanganj",
    "tgn:placetype":[
        "aat:300008347"
    ]
},
  "bbox": [],
  "geometry": {"coordinates":[79.998103,26.669694],"type":"Point"}
}