<<<<<<< HEAD
{
  "id": 7023237,
  "type": "Feature",
  "properties": {
    "tgn:hierarchy":[
        "tgn:7023237",
        "tgn:1000001",
        "tgn:7012149",
        "tgn:7022240",
        "tgn:7007523",
        "tgn:7029392"
    ],
    "tgn:id":7023237,
    "tgn:name":"Lemay",
    "tgn:placetype":[
        "aat:300008347"
    ]
},
  "bbox": [],
  "geometry": {"coordinates":[-90.3,38.4833],"type":"Point"}
}
=======
{"geometry":{"type":"Point","coordinates":[-90.300000,38.483300]},"type":"Feature","properties":{"hierarchy":["tgn:7023237","tgn:1000001","tgn:7012149","tgn:7022240","tgn:7007523","tgn:7029392"],"placetype":["aat:300008347"],"id":7023237,"name:xx":"Lemay"}}
>>>>>>> 03f74aca74312dbeaf24d7e61306dd6a786dc3d0
