{
  "id": 7301158,
  "type": "Feature",
  "properties": {
    "tgn:hierarchy":[
        "tgn:7301158",
        "tgn:7008912",
        "tgn:7030216",
        "tgn:1000003",
        "tgn:1000095",
        "tgn:7029392"
    ],
    "tgn:id":7301158,
    "tgn:name":"Montclar",
    "tgn:placetype":[
        "aat:300008347"
    ]
},
  "bbox": [],
  "geometry": {"coordinates":[1.041892,41.846688],"type":"Point"}
}