{
  "id": 2056250,
  "type": "Feature",
  "properties": {
    "tgn:hierarchy":[
        "tgn:2056250",
        "tgn:1000001",
        "tgn:7012149",
        "tgn:2001167",
        "tgn:7007522",
        "tgn:7029392"
    ],
    "tgn:id":2056250,
    "tgn:name":"Crupp",
    "tgn:placetype":[
        "aat:300008347",
        "aat:300387210"
    ]
},
  "bbox": [],
  "geometry": {"coordinates":[-90.45,32.7833],"type":"Point"}
}