{
  "id": 2727883,
  "type": "Feature",
  "properties": {
    "tgn:hierarchy":[
        "tgn:2727883",
        "tgn:1000001",
        "tgn:7012149",
        "tgn:1002482",
        "tgn:7007706",
        "tgn:7029392"
    ],
    "tgn:id":2727883,
    "tgn:name":"Tranquil Valley Lake",
    "tgn:placetype":[
        "aat:300006191"
    ]
},
  "bbox": [],
  "geometry": {"coordinates":[-81.8667,40.5333],"type":"Point"}
}