{
  "id": 2283403,
  "type": "Feature",
  "properties": {
    "tgn:hierarchy":[
        "tgn:2283403",
        "tgn:1000001",
        "tgn:2001410",
        "tgn:7012149",
        "tgn:7007526",
        "tgn:7029392"
    ],
    "tgn:id":2283403,
    "tgn:name":"Delmar Bay",
    "tgn:placetype":[
        "aat:300132316"
    ]
},
  "bbox": [],
  "geometry": {"coordinates":[-114.2833,36.0667],"type":"Point"}
}