{
  "id": 7170833,
  "type": "Feature",
  "properties": {
    "tgn:hierarchy":[
        "tgn:7170833",
        "tgn:7003669",
        "tgn:1000003",
        "tgn:7000084",
        "tgn:7029392"
    ],
    "tgn:id":7170833,
    "tgn:name":"Hirschstein",
    "tgn:placetype":[
        "aat:300008749"
    ]
},
  "bbox": [],
  "geometry": {"coordinates":[11.866667,50.366667],"type":"Point"}
}