{
  "id": 7512218,
  "type": "Feature",
  "properties": {
    "tgn:hierarchy":[
        "tgn:7512218",
        "tgn:1009227",
        "tgn:1000226",
        "tgn:7018437",
        "tgn:1000006",
        "tgn:7029392"
    ],
    "tgn:id":7512218,
    "tgn:name:en":"Island Stream",
    "tgn:placetype":[
        "aat:300008699"
    ]
},
  "bbox": [],
  "geometry": {"coordinates":[170.833333,-45.166667],"type":"Point"}
}