{
  "id": 2497161,
  "type": "Feature",
  "properties": {
    "tgn:hierarchy":[
        "tgn:2497161",
        "tgn:1000001",
        "tgn:2001436",
        "tgn:7012149",
        "tgn:7007566",
        "tgn:7029392"
    ],
    "tgn:id":2497161,
    "tgn:name":"Maverick Canyon",
    "tgn:placetype":[
        "aat:300008761"
    ]
},
  "bbox": [],
  "geometry": {"coordinates":[-102.35,32.2333],"type":"Point"}
}