{
  "id": 7498277,
  "type": "Feature",
  "properties": {
    "tgn:hierarchy":[
        "tgn:7498277",
        "tgn:1000004",
        "tgn:1000454",
        "tgn:1000141",
        "tgn:7029392"
    ],
    "tgn:id":7498277,
    "tgn:name":"Mazhujiao",
    "tgn:placetype":[
        "aat:300008347"
    ]
},
  "bbox": [],
  "geometry": {"coordinates":[121.641395,25.186929],"type":"Point"}
}