{
  "id": 2464418,
  "type": "Feature",
  "properties": {
    "tgn:hierarchy":[
        "tgn:2464418",
        "tgn:1000001",
        "tgn:7012149",
        "tgn:2000874",
        "tgn:7007256",
        "tgn:7029392"
    ],
    "tgn:id":2464418,
    "tgn:name":"Loften Bayou",
    "tgn:placetype":[
        "aat:300008699"
    ]
},
  "bbox": [],
  "geometry": {"coordinates":[-91.6833,31.9333],"type":"Point"}
}