{
  "id": 7220808,
  "type": "Feature",
  "properties": {
    "tgn:hierarchy":[
        "tgn:7220808",
        "tgn:7011330",
        "tgn:7002674",
        "tgn:1000003",
        "tgn:1000074",
        "tgn:7029392"
    ],
    "tgn:id":7220808,
    "tgn:name":"Vas\u00e1li, \u00d3rmos",
    "tgn:placetype":[
        "aat:300132316"
    ]
},
  "bbox": [],
  "geometry": {"coordinates":[27.833333,36.583333],"type":"Point"}
}