{
  "id": 2355566,
  "type": "Feature",
  "properties": {
    "tgn:hierarchy":[
        "tgn:2355566",
        "tgn:1000001",
        "tgn:7012149",
        "tgn:1002482",
        "tgn:7007706",
        "tgn:7029392"
    ],
    "tgn:id":2355566,
    "tgn:name":"Goose Creek",
    "tgn:placetype":[
        "aat:300008706"
    ]
},
  "bbox": [],
  "geometry": {"coordinates":[-81.7667,40.55],"type":"Point"}
}