{
  "id": 2200064,
  "type": "Feature",
  "properties": {
    "tgn:hierarchy":[
        "tgn:2200064",
        "tgn:1000001",
        "tgn:2000328",
        "tgn:7012149",
        "tgn:7007248",
        "tgn:7029392"
    ],
    "tgn:id":2200064,
    "tgn:name":"Brushy Creek",
    "tgn:placetype":[
        "aat:300008706"
    ]
},
  "bbox": [],
  "geometry": {"coordinates":[-83.4667,31.3167],"type":"Point"}
}