{
  "id": 7267271,
  "type": "Feature",
  "properties": {
    "tgn:hierarchy":[
        "tgn:7267271",
        "tgn:1000003",
        "tgn:7003624",
        "tgn:7016845",
        "tgn:7029392"
    ],
    "tgn:id":7267271,
    "tgn:name:nl":"Refelingsche Heide",
    "tgn:placetype":[
        "aat:300386887"
    ]
},
  "bbox": [],
  "geometry": {"coordinates":[5.55,51.466667],"type":"Point"}
}