{
  "id": 2610771,
  "type": "Feature",
  "properties": {
    "tgn:hierarchy":[
        "tgn:2610771",
        "tgn:1000001",
        "tgn:2000201",
        "tgn:7012149",
        "tgn:7007158",
        "tgn:7029392"
    ],
    "tgn:id":2610771,
    "tgn:name":"Red Elephant Hill",
    "tgn:placetype":[
        "aat:300008798"
    ]
},
  "bbox": [],
  "geometry": {"coordinates":[-105.6333,39.7667],"type":"Point"}
}