{
  "id": 2458458,
  "type": "Feature",
  "properties": {
    "tgn:hierarchy":[
        "tgn:2458458",
        "tgn:2000195",
        "tgn:1000001",
        "tgn:7012149",
        "tgn:7007158",
        "tgn:7029392"
    ],
    "tgn:id":2458458,
    "tgn:name":"Little Navajo River",
    "tgn:placetype":[
        "aat:300008707"
    ]
},
  "bbox": [],
  "geometry": {"coordinates":[-106.7667,37.1333],"type":"Point"}
}