{
  "id": 7419315,
  "type": "Feature",
  "properties": {
    "tgn:hierarchy":[
        "tgn:7419315",
        "tgn:1000001",
        "tgn:1001937",
        "tgn:7005560",
        "tgn:7029392"
    ],
    "tgn:id":7419315,
    "tgn:name":"Palancar, Arrecife",
    "tgn:placetype":[
        "aat:300008808"
    ]
},
  "bbox": [],
  "geometry": {"coordinates":[-87.025,20.183333],"type":"Point"}
}