{
  "id": 2322897,
  "type": "Feature",
  "properties": {
    "tgn:hierarchy":[
        "tgn:2322897",
        "tgn:1000001",
        "tgn:7012149",
        "tgn:1002793",
        "tgn:7007240",
        "tgn:7029392"
    ],
    "tgn:id":2322897,
    "tgn:name":"Fannie, Lake",
    "tgn:placetype":[
        "aat:300008680"
    ]
},
  "bbox": [],
  "geometry": {"coordinates":[-81.6833,28.05],"type":"Point"}
}