{
  "id": 7277565,
  "type": "Feature",
  "properties": {
    "tgn:hierarchy":[
        "tgn:7277565",
        "tgn:1001637",
        "tgn:1000049",
        "tgn:1000002",
        "tgn:7029392"
    ],
    "tgn:id":7277565,
    "tgn:name":"Manzano, Ras",
    "tgn:placetype":[
        "aat:300011692"
    ]
},
  "bbox": [],
  "geometry": {"coordinates":[-73.097222,-36.683333],"type":"Point"}
}