{
  "id": 2315984,
  "type": "Feature",
  "properties": {
    "tgn:hierarchy":[
        "tgn:2315984",
        "tgn:1000001",
        "tgn:2001948",
        "tgn:7012149",
        "tgn:7007826",
        "tgn:7029392"
    ],
    "tgn:id":2315984,
    "tgn:name":"Elm Creek",
    "tgn:placetype":[
        "aat:300008706"
    ]
},
  "bbox": [],
  "geometry": {"coordinates":[-98.8833,31.9167],"type":"Point"}
}