{
  "id": 1096656,
  "type": "Feature",
  "properties": {
    "tgn:hierarchy":[
        "tgn:1096656",
        "tgn:7000490",
        "tgn:1000006",
        "tgn:7001831",
        "tgn:7029392"
    ],
    "tgn:id":1096656,
    "tgn:name":"Coulta",
    "tgn:placetype":[
        "aat:300008347"
    ]
},
  "bbox": [],
  "geometry": {"coordinates":[135.4667,-34.3833],"type":"Point"}
}