{
  "id": 2302223,
  "type": "Feature",
  "properties": {
    "tgn:hierarchy":[
        "tgn:2302223",
        "tgn:1000001",
        "tgn:1002840",
        "tgn:7012149",
        "tgn:7007828",
        "tgn:7029392"
    ],
    "tgn:id":2302223,
    "tgn:name":"Dutch Hill",
    "tgn:placetype":[
        "aat:300008798"
    ]
},
  "bbox": [],
  "geometry": {"coordinates":[-73.0667,43.3667],"type":"Point"}
}