<<<<<<< HEAD
{
  "id": 2401518,
  "type": "Feature",
  "properties": {
    "tgn:hierarchy":[
        "tgn:2401518",
        "tgn:1000001",
        "tgn:2000263",
        "tgn:7012149",
        "tgn:7007240",
        "tgn:7029392"
    ],
    "tgn:id":2401518,
    "tgn:name":"Horseshoe Cove",
    "tgn:placetype":[
        "aat:300132316"
    ]
},
  "bbox": [],
  "geometry": {"coordinates":[-83.2167,29.4167],"type":"Point"}
}
=======
{"geometry":{"type":"Point","coordinates":[-83.216700,29.416700]},"type":"Feature","properties":{"hierarchy":["tgn:2401518","tgn:1000001","tgn:2000263","tgn:7012149","tgn:7007240","tgn:7029392"],"placetype":["aat:300132316"],"id":2401518,"name:xx":"Horseshoe Cove"}}
>>>>>>> 03f74aca74312dbeaf24d7e61306dd6a786dc3d0
