<<<<<<< HEAD
{
  "id": 7351575,
  "type": "Feature",
  "properties": {
    "tgn:hierarchy":[
        "tgn:7351575",
        "tgn:1000001",
        "tgn:7005600",
        "tgn:7005560",
        "tgn:7029392"
    ],
    "tgn:id":7351575,
    "tgn:name":"Arroyo Claro",
    "tgn:placetype":[
        "aat:300007783"
    ]
},
  "bbox": [],
  "geometry": {"coordinates":[-95.8,18.15],"type":"Point"}
}
=======
{"geometry":{"type":"Point","coordinates":[-95.800000,18.150000]},"type":"Feature","properties":{"hierarchy":["tgn:7351575","tgn:1000001","tgn:7005600","tgn:7005560","tgn:7029392"],"placetype":["aat:300007783"],"id":7351575,"name:xx":"Arroyo Claro"}}
>>>>>>> 03f74aca74312dbeaf24d7e61306dd6a786dc3d0
