<<<<<<< HEAD
{
  "id": 2153102,
  "type": "Feature",
  "properties": {
    "tgn:hierarchy":[
        "tgn:2153102",
        "tgn:1000001",
        "tgn:2001435",
        "tgn:7012149",
        "tgn:7007566",
        "tgn:7029392"
    ],
    "tgn:id":2153102,
    "tgn:name":"Beacon Tank",
    "tgn:placetype":[
        "aat:300006191"
    ]
},
  "bbox": [],
  "geometry": {"coordinates":[-106.75,32.6333],"type":"Point"}
}
=======
{"geometry":{"type":"Point","coordinates":[-106.750000,32.633300]},"type":"Feature","properties":{"hierarchy":["tgn:2153102","tgn:1000001","tgn:2001435","tgn:7012149","tgn:7007566","tgn:7029392"],"placetype":["aat:300006191"],"id":2153102,"name:xx":"Beacon Tank"}}
>>>>>>> 03f74aca74312dbeaf24d7e61306dd6a786dc3d0
