{
  "id": 2218856,
  "type": "Feature",
  "properties": {
    "tgn:hierarchy":[
        "tgn:2218856",
        "tgn:1000001",
        "tgn:7012149",
        "tgn:2001449",
        "tgn:7007566",
        "tgn:7029392"
    ],
    "tgn:id":2218856,
    "tgn:name":"Canelejas, Ca\u00f1ada de las",
    "tgn:placetype":[
        "aat:300008699"
    ]
},
  "bbox": [],
  "geometry": {"coordinates":[-106.0333,36.1833],"type":"Point"}
}