{
  "id": 2526148,
  "type": "Feature",
  "properties": {
    "tgn:hierarchy":[
        "tgn:2526148",
        "tgn:1000001",
        "tgn:7012149",
        "tgn:1002999",
        "tgn:7007526",
        "tgn:7029392"
    ],
    "tgn:id":2526148,
    "tgn:name":"Mosquito Lake",
    "tgn:placetype":[
        "aat:300008680"
    ]
},
  "bbox": [],
  "geometry": {"coordinates":[-119.8333,41.8333],"type":"Point"}
}