<<<<<<< HEAD
{
  "id": 2405343,
  "type": "Feature",
  "properties": {
    "tgn:hierarchy":[
        "tgn:2405343",
        "tgn:7002659",
        "tgn:1000001",
        "tgn:7012149",
        "tgn:2000042",
        "tgn:7029392"
    ],
    "tgn:id":2405343,
    "tgn:name":"Huffmans Pond",
    "tgn:placetype":[
        "aat:300006191"
    ]
},
  "bbox": [],
  "geometry": {"coordinates":[-86.45,32.1667],"type":"Point"}
}
=======
{"geometry":{"type":"Point","coordinates":[-86.450000,32.166700]},"type":"Feature","properties":{"hierarchy":["tgn:2405343","tgn:7002659","tgn:1000001","tgn:7012149","tgn:2000042","tgn:7029392"],"placetype":["aat:300006191"],"id":2405343,"name:xx":"Huffmans Pond"}}
>>>>>>> 03f74aca74312dbeaf24d7e61306dd6a786dc3d0
