{
  "id": 2649656,
  "type": "Feature",
  "properties": {
    "tgn:hierarchy":[
        "tgn:2649656",
        "tgn:7006450",
        "tgn:1000001",
        "tgn:2124089",
        "tgn:7012149",
        "tgn:7029392"
    ],
    "tgn:id":2649656,
    "tgn:name":"Scow Cove",
    "tgn:placetype":[
        "aat:300132316"
    ]
},
  "bbox": [],
  "geometry": {"coordinates":[-134.05,58.35],"type":"Point"}
}