{
  "id": 7327454,
  "type": "Feature",
  "properties": {
    "tgn:hierarchy":[
        "tgn:7327454",
        "tgn:7002758",
        "tgn:7002830",
        "tgn:1000003",
        "tgn:1000095",
        "tgn:7029392"
    ],
    "tgn:id":7327454,
    "tgn:name":"Palomeras, Arroyo de las",
    "tgn:placetype":[
        "aat:300008699"
    ]
},
  "bbox": [],
  "geometry": {"coordinates":[-4.983333,36.866667],"type":"Point"}
}