{
  "id": 7205447,
  "type": "Feature",
  "properties": {
    "tgn:hierarchy":[
        "tgn:7205447",
        "tgn:1000003",
        "tgn:7003677",
        "tgn:7000084",
        "tgn:7029392"
    ],
    "tgn:id":7205447,
    "tgn:name":"Dambroich",
    "tgn:placetype":[
        "aat:300008347"
    ]
},
  "bbox": [],
  "geometry": {"coordinates":[7.233333,50.75],"type":"Point"}
}