{
  "id": 2135474,
  "type": "Feature",
  "properties": {
    "tgn:hierarchy":[
        "tgn:2135474",
        "tgn:1000001",
        "tgn:7012149",
        "tgn:2001300",
        "tgn:7007524",
        "tgn:7029392"
    ],
    "tgn:id":2135474,
    "tgn:name":"Antrim Point",
    "tgn:placetype":[
        "aat:300008850"
    ]
},
  "bbox": [],
  "geometry": {"coordinates":[-114.0167,46.6167],"type":"Point"}
}