{
  "id": 2410189,
  "type": "Feature",
  "properties": {
    "tgn:hierarchy":[
        "tgn:2410189",
        "tgn:1000001",
        "tgn:2000469",
        "tgn:7012149",
        "tgn:7007250",
        "tgn:7029392"
    ],
    "tgn:id":2410189,
    "tgn:name":"Independence Ridge",
    "tgn:placetype":[
        "aat:300266640"
    ]
},
  "bbox": [],
  "geometry": {"coordinates":[-115.0833,46.7667],"type":"Point"}
}