{
  "id": 6003779,
  "type": "Feature",
  "properties": {
    "tgn:hierarchy":[
        "tgn:6003779",
        "tgn:7003692",
        "tgn:1000003",
        "tgn:7000084",
        "tgn:7029392"
    ],
    "tgn:id":6003779,
    "tgn:name":"Mauer",
    "tgn:placetype":[
        "aat:300008347"
    ]
},
  "bbox": [],
  "geometry": {"coordinates":[8.800278,49.340833],"type":"Point"}
}