<<<<<<< HEAD
{
  "id": 2158640,
  "type": "Feature",
  "properties": {
    "tgn:hierarchy":[
        "tgn:2158640",
        "tgn:1000001",
        "tgn:7012149",
        "tgn:1002742",
        "tgn:7007920",
        "tgn:7029392"
    ],
    "tgn:id":2158640,
    "tgn:name":"Beaverhouse Creek",
    "tgn:placetype":[
        "aat:300008706"
    ]
},
  "bbox": [],
  "geometry": {"coordinates":[-119.3833,48.3333],"type":"Point"}
}
=======
{"geometry":{"type":"Point","coordinates":[-119.383300,48.333300]},"type":"Feature","properties":{"hierarchy":["tgn:2158640","tgn:1000001","tgn:7012149","tgn:1002742","tgn:7007920","tgn:7029392"],"placetype":["aat:300008706"],"id":2158640,"name:xx":"Beaverhouse Creek"}}
>>>>>>> 03f74aca74312dbeaf24d7e61306dd6a786dc3d0
