{
  "id": 2158640,
  "type": "Feature",
  "properties": {
    "tgn:hierarchy":[
        "tgn:2158640",
        "tgn:1000001",
        "tgn:7012149",
        "tgn:1002742",
        "tgn:7007920",
        "tgn:7029392"
    ],
    "tgn:id":2158640,
    "tgn:name":"Beaverhouse Creek",
    "tgn:placetype":[
        "aat:300008706"
    ]
},
  "bbox": [],
  "geometry": {"coordinates":[-119.3833,48.3333],"type":"Point"}
}