{
  "id": 7189740,
  "type": "Feature",
  "properties": {
    "tgn:hierarchy":[
        "tgn:7189740",
        "tgn:7003669",
        "tgn:1000003",
        "tgn:7000084",
        "tgn:7029392"
    ],
    "tgn:id":7189740,
    "tgn:name":"Einsassen",
    "tgn:placetype":[
        "aat:300008347"
    ]
},
  "bbox": [],
  "geometry": {"coordinates":[11.383333,48.45],"type":"Point"}
}