{
  "id": 7193426,
  "type": "Feature",
  "properties": {
    "tgn:hierarchy":[
        "tgn:7193426",
        "tgn:7000096",
        "tgn:1000003",
        "tgn:7000084",
        "tgn:7029392"
    ],
    "tgn:id":7193426,
    "tgn:name":"Feldsch\u00e4nke",
    "tgn:placetype":[
        "aat:300008347"
    ]
},
  "bbox": [],
  "geometry": {"coordinates":[14.066667,51.666667],"type":"Point"}
}