{
  "id": 7257238,
  "type": "Feature",
  "properties": {
    "tgn:hierarchy":[
        "tgn:7257238",
        "tgn:7003458",
        "tgn:1000003",
        "tgn:1000063",
        "tgn:7018236",
        "tgn:7029392"
    ],
    "tgn:id":7257238,
    "tgn:name":"Wippenhoek",
    "tgn:placetype":[
        "aat:300008347"
    ]
},
  "bbox": [],
  "geometry": {"coordinates":[2.683333,50.816667],"type":"Point"}
}