{
  "id": 7509127,
  "type": "Feature",
  "properties": {
    "tgn:hierarchy":[
        "tgn:7509127",
        "tgn:1008380",
        "tgn:1000226",
        "tgn:7000512",
        "tgn:1000006",
        "tgn:7029392"
    ],
    "tgn:id":7509127,
    "tgn:name:en":"Wainuiomata River",
    "tgn:placetype":[
        "aat:300008699"
    ]
},
  "bbox": [],
  "geometry": {"coordinates":[174.883333,-41.416667],"type":"Point"}
}