{
  "id": 1133133,
  "type": "Feature",
  "properties": {
    "tgn:hierarchy":[
        "tgn:1133133",
        "tgn:7593341",
        "tgn:1000002",
        "tgn:1000059",
        "tgn:7029392"
    ],
    "tgn:id":1133133,
    "tgn:name":"El Cojo, Quebrada",
    "tgn:placetype":[
        "aat:300008706"
    ]
},
  "bbox": [],
  "geometry": {"coordinates":[-66.8833,10.6167],"type":"Point"}
}