{
  "id": 2755809,
  "type": "Feature",
  "properties": {
    "tgn:hierarchy":[
        "tgn:2755809",
        "tgn:1000001",
        "tgn:7012149",
        "tgn:2000930",
        "tgn:7007515",
        "tgn:7029392"
    ],
    "tgn:id":2755809,
    "tgn:name":"Weeks Basin",
    "tgn:placetype":[
        "aat:300386845"
    ]
},
  "bbox": [],
  "geometry": {"coordinates":[-69.7333,45.1167],"type":"Point"}
}