{
  "id": 2294224,
  "type": "Feature",
  "properties": {
    "tgn:hierarchy":[
        "tgn:2294224",
        "tgn:1000001",
        "tgn:2000922",
        "tgn:7012149",
        "tgn:7007515",
        "tgn:7029392"
    ],
    "tgn:id":2294224,
    "tgn:name":"Dow Ledge",
    "tgn:placetype":[
        "aat:300132348"
    ]
},
  "bbox": [],
  "geometry": {"coordinates":[-68.6333,44.15],"type":"Point"}
}