{
  "id": 2662995,
  "type": "Feature",
  "properties": {
    "tgn:hierarchy":[
        "tgn:2662995",
        "tgn:1000001",
        "tgn:1002738",
        "tgn:7012149",
        "tgn:7007565",
        "tgn:7029392"
    ],
    "tgn:id":2662995,
    "tgn:name":"Silver Beach",
    "tgn:placetype":[
        "aat:300008347"
    ]
},
  "bbox": [],
  "geometry": {"coordinates":[-74.05,39.9833],"type":"Point"}
}