{
  "id": 7396616,
  "type": "Feature",
  "properties": {
    "tgn:hierarchy":[
        "tgn:7396616",
        "tgn:7005586",
        "tgn:1000001",
        "tgn:7005560",
        "tgn:7029392"
    ],
    "tgn:id":7396616,
    "tgn:name":"Santa Rita",
    "tgn:placetype":[
        "aat:300006191"
    ]
},
  "bbox": [],
  "geometry": {"coordinates":[-102.383333,20.45],"type":"Point"}
}