{
  "id": 7409034,
  "type": "Feature",
  "properties": {
    "tgn:hierarchy":[
        "tgn:7409034",
        "tgn:1000001",
        "tgn:7005590",
        "tgn:7005560",
        "tgn:7029392"
    ],
    "tgn:id":7409034,
    "tgn:name":"Infiernillo",
    "tgn:placetype":[
        "aat:300008347"
    ]
},
  "bbox": [],
  "geometry": {"coordinates":[-101.908333,18.283333],"type":"Point"}
}