{
  "id": 7392502,
  "type": "Feature",
  "properties": {
    "tgn:hierarchy":[
        "tgn:7392502",
        "tgn:1000001",
        "tgn:7005597",
        "tgn:7005560",
        "tgn:7029392"
    ],
    "tgn:id":7392502,
    "tgn:name":"Rancho Los Mimbres",
    "tgn:placetype":[
        "aat:300008347"
    ]
},
  "bbox": [],
  "geometry": {"coordinates":[-99.431944,24.075556],"type":"Point"}
}