{
  "id": 2705843,
  "type": "Feature",
  "properties": {
    "tgn:hierarchy":[
        "tgn:2705843",
        "tgn:1000001",
        "tgn:2000463",
        "tgn:7012149",
        "tgn:7007250",
        "tgn:7029392"
    ],
    "tgn:id":2705843,
    "tgn:name":"Sutton Canyon",
    "tgn:placetype":[
        "aat:300008761"
    ]
},
  "bbox": [],
  "geometry": {"coordinates":[-113.1333,43.6833],"type":"Point"}
}