{
  "id": 2682324,
  "type": "Feature",
  "properties": {
    "tgn:hierarchy":[
        "tgn:2682324",
        "tgn:1000001",
        "tgn:7012149",
        "tgn:2000720",
        "tgn:7007254",
        "tgn:7029392"
    ],
    "tgn:id":2682324,
    "tgn:name":"South Wea Creek",
    "tgn:placetype":[
        "aat:300008706"
    ]
},
  "bbox": [],
  "geometry": {"coordinates":[-94.6667,38.5833],"type":"Point"}
}