<<<<<<< HEAD
{
  "id": 7369944,
  "type": "Feature",
  "properties": {
    "tgn:hierarchy":[
        "tgn:7369944",
        "tgn:7005587",
        "tgn:1000001",
        "tgn:7005560",
        "tgn:7029392"
    ],
    "tgn:id":7369944,
    "tgn:name":"Jalamelco",
    "tgn:placetype":[
        "aat:300008347"
    ]
},
  "bbox": [],
  "geometry": {"coordinates":[-98.7,20.816667],"type":"Point"}
}
=======
{"geometry":{"type":"Point","coordinates":[-98.700000,20.816667]},"type":"Feature","properties":{"hierarchy":["tgn:7369944","tgn:7005587","tgn:1000001","tgn:7005560","tgn:7029392"],"placetype":["aat:300008347"],"id":7369944,"name:xx":"Jalamelco"}}
>>>>>>> 03f74aca74312dbeaf24d7e61306dd6a786dc3d0
