<<<<<<< HEAD
{
  "id": 7470897,
  "type": "Feature",
  "properties": {
    "tgn:hierarchy":[
        "tgn:7470897",
        "tgn:1000004",
        "tgn:1000454",
        "tgn:1000141",
        "tgn:7029392"
    ],
    "tgn:id":7470897,
    "tgn:name":"Erkonggui",
    "tgn:placetype":[
        "aat:300008347"
    ]
},
  "bbox": [],
  "geometry": {"coordinates":[121.6964,25.0342],"type":"Point"}
}
=======
{"geometry":{"type":"Point","coordinates":[121.696400,25.034200]},"type":"Feature","properties":{"hierarchy":["tgn:7470897","tgn:1000004","tgn:1000454","tgn:1000141","tgn:7029392"],"placetype":["aat:300008347"],"id":7470897,"name:xx":"Erkonggui"}}
>>>>>>> 03f74aca74312dbeaf24d7e61306dd6a786dc3d0
