{
  "id": 2244272,
  "type": "Feature",
  "properties": {
    "tgn:hierarchy":[
        "tgn:2244272",
        "tgn:7002659",
        "tgn:1000001",
        "tgn:2000003",
        "tgn:7012149",
        "tgn:7029392"
    ],
    "tgn:id":2244272,
    "tgn:name":"Clifton Branch",
    "tgn:placetype":[
        "aat:300008699"
    ]
},
  "bbox": [],
  "geometry": {"coordinates":[-87.15,33.1333],"type":"Point"}
}