{
  "id": 2486453,
  "type": "Feature",
  "properties": {
    "tgn:hierarchy":[
        "tgn:2486453",
        "tgn:1000001",
        "tgn:7012149",
        "tgn:2000477",
        "tgn:7007250",
        "tgn:7029392"
    ],
    "tgn:id":2486453,
    "tgn:name":"Leavitz Pond",
    "tgn:placetype":[
        "aat:300008680"
    ]
},
  "bbox": [],
  "geometry": {"coordinates":[-112.2333,43.9167],"type":"Point"}
}