{
  "id": 7473660,
  "type": "Feature",
  "properties": {
    "tgn:hierarchy":[
        "tgn:7473660",
        "tgn:1000004",
        "tgn:7467799",
        "tgn:1000141",
        "tgn:7029392"
    ],
    "tgn:id":7473660,
    "tgn:name":"Yingbu",
    "tgn:placetype":[
        "aat:300000745"
    ]
},
  "bbox": [],
  "geometry": {"coordinates":[120.501944,24.117778],"type":"Point"}
}