{
  "id": 2692681,
  "type": "Feature",
  "properties": {
    "tgn:hierarchy":[
        "tgn:2692681",
        "tgn:1000001",
        "tgn:7012149",
        "tgn:2002376",
        "tgn:7007923",
        "tgn:7029392"
    ],
    "tgn:id":2692681,
    "tgn:name":"Steed Ditch",
    "tgn:placetype":[
        "aat:300006075"
    ]
},
  "bbox": [],
  "geometry": {"coordinates":[-110.1833,42.2167],"type":"Point"}
}