{
  "id": 7190398,
  "type": "Feature",
  "properties": {
    "tgn:hierarchy":[
        "tgn:7190398",
        "tgn:1000003",
        "tgn:7003688",
        "tgn:7000084",
        "tgn:7029392"
    ],
    "tgn:id":7190398,
    "tgn:name":"Ellerhoop",
    "tgn:placetype":[
        "aat:300008347"
    ]
},
  "bbox": [],
  "geometry": {"coordinates":[9.766667,53.733333],"type":"Point"}
}