{
  "id": 2479208,
  "type": "Feature",
  "properties": {
    "tgn:hierarchy":[
        "tgn:2479208",
        "tgn:1000001",
        "tgn:7016172",
        "tgn:7012149",
        "tgn:2000137",
        "tgn:7029392"
    ],
    "tgn:id":2479208,
    "tgn:name":"Lafferty Hollow",
    "tgn:placetype":[
        "aat:300008761"
    ]
},
  "bbox": [],
  "geometry": {"coordinates":[-91.85,35.9333],"type":"Point"}
}