{
  "id": 2583416,
  "type": "Feature",
  "properties": {
    "tgn:hierarchy":[
        "tgn:2583416",
        "tgn:1000001",
        "tgn:2001704",
        "tgn:7012149",
        "tgn:7007708",
        "tgn:7029392"
    ],
    "tgn:id":2583416,
    "tgn:name":"Pine Point",
    "tgn:placetype":[
        "aat:300008798"
    ]
},
  "bbox": [],
  "geometry": {"coordinates":[-124.2833,42.2833],"type":"Point"}
}