{
  "id": 2745716,
  "type": "Feature",
  "properties": {
    "tgn:hierarchy":[
        "tgn:2745716",
        "tgn:1000001",
        "tgn:7012149",
        "tgn:7007157",
        "tgn:1002675",
        "tgn:7029392"
    ],
    "tgn:id":2745716,
    "tgn:name":"Virginia Lakes",
    "tgn:placetype":[
        "aat:300008680"
    ]
},
  "bbox": [],
  "geometry": {"coordinates":[-119.25,38.0333],"type":"Point"}
}