{
  "id": 2150747,
  "type": "Feature",
  "properties": {
    "tgn:hierarchy":[
        "tgn:2150747",
        "tgn:1000001",
        "tgn:7012149",
        "tgn:7007157",
        "tgn:2000184",
        "tgn:7029392"
    ],
    "tgn:id":2150747,
    "tgn:name":"Bass Hill",
    "tgn:placetype":[
        "aat:300008798"
    ]
},
  "bbox": [],
  "geometry": {"coordinates":[-120.5167,40.3333],"type":"Point"}
}