{
  "id": 7468591,
  "type": "Feature",
  "properties": {
    "tgn:hierarchy":[
        "tgn:7468591",
        "tgn:1000004",
        "tgn:1000454",
        "tgn:1000141",
        "tgn:7029392"
    ],
    "tgn:id":7468591,
    "tgn:name":"Xinbuzi",
    "tgn:placetype":[
        "aat:300008347"
    ]
},
  "bbox": [],
  "geometry": {"coordinates":[121.449767,25.227515],"type":"Point"}
}