{
  "id": 2628720,
  "type": "Feature",
  "properties": {
    "tgn:hierarchy":[
        "tgn:2628720",
        "tgn:1000001",
        "tgn:7016172",
        "tgn:7012149",
        "tgn:2000173",
        "tgn:7029392"
    ],
    "tgn:id":2628720,
    "tgn:name":"Roper Hollow",
    "tgn:placetype":[
        "aat:300008761"
    ]
},
  "bbox": [],
  "geometry": {"coordinates":[-92.1167,35.95],"type":"Point"}
}