{
  "id": 2760384,
  "type": "Feature",
  "properties": {
    "tgn:hierarchy":[
        "tgn:2760384",
        "tgn:1000001",
        "tgn:7012149",
        "tgn:2000826",
        "tgn:7007255",
        "tgn:7029392"
    ],
    "tgn:id":2760384,
    "tgn:name":"West Fork Slate Creek",
    "tgn:placetype":[
        "aat:300008706"
    ]
},
  "bbox": [],
  "geometry": {"coordinates":[-83.75,37.9833],"type":"Point"}
}