<<<<<<< HEAD
{
  "id": 2760384,
  "type": "Feature",
  "properties": {
    "tgn:hierarchy":[
        "tgn:2760384",
        "tgn:1000001",
        "tgn:7012149",
        "tgn:2000826",
        "tgn:7007255",
        "tgn:7029392"
    ],
    "tgn:id":2760384,
    "tgn:name":"West Fork Slate Creek",
    "tgn:placetype":[
        "aat:300008706"
    ]
},
  "bbox": [],
  "geometry": {"coordinates":[-83.75,37.9833],"type":"Point"}
}
=======
{"geometry":{"type":"Point","coordinates":[-83.750000,37.983300]},"type":"Feature","properties":{"hierarchy":["tgn:2760384","tgn:1000001","tgn:7012149","tgn:2000826","tgn:7007255","tgn:7029392"],"placetype":["aat:300008706"],"id":2760384,"name:xx":"West Fork Slate Creek"}}
>>>>>>> 03f74aca74312dbeaf24d7e61306dd6a786dc3d0
