{
  "id": 2377387,
  "type": "Feature",
  "properties": {
    "tgn:hierarchy":[
        "tgn:2377387",
        "tgn:1000001",
        "tgn:7012149",
        "tgn:1002582",
        "tgn:7007240",
        "tgn:7029392"
    ],
    "tgn:id":2377387,
    "tgn:name":"Harney Point",
    "tgn:placetype":[
        "aat:300008850"
    ]
},
  "bbox": [],
  "geometry": {"coordinates":[-81.9333,26.55],"type":"Point"}
}