{
  "id": 2033511,
  "type": "Feature",
  "properties": {
    "tgn:hierarchy":[
        "tgn:2033511",
        "tgn:1000001",
        "tgn:1002188",
        "tgn:7012149",
        "tgn:7007252",
        "tgn:7029392"
    ],
    "tgn:id":2033511,
    "tgn:name":"Rosston",
    "tgn:placetype":[
        "aat:300008347"
    ]
},
  "bbox": [],
  "geometry": {"coordinates":[-86.2833,40.0333],"type":"Point"}
}