{
  "id": 1128034,
  "type": "Feature",
  "properties": {
    "tgn:hierarchy":[
        "tgn:1128034",
        "tgn:1000001",
        "tgn:7012149",
        "tgn:7007248",
        "tgn:7029392"
    ],
    "tgn:id":1128034,
    "tgn:name":"Ohoopee",
    "tgn:placetype":[
        "aat:300008707"
    ]
},
  "bbox": [],
  "geometry": {"coordinates":[-82.7833,32.9333],"type":"Point"}
}