{
  "id": 7235567,
  "type": "Feature",
  "properties": {
    "tgn:hierarchy":[
        "tgn:7235567",
        "tgn:7002745",
        "tgn:7017076",
        "tgn:1000003",
        "tgn:1000074",
        "tgn:7029392"
    ],
    "tgn:id":7235567,
    "tgn:name":"Fidhon\u00edsi",
    "tgn:placetype":[
        "aat:300008791"
    ]
},
  "bbox": [],
  "geometry": {"coordinates":[23.083333,36.266667],"type":"Point"}
}