{
  "id": 2096706,
  "type": "Feature",
  "properties": {
    "tgn:hierarchy":[
        "tgn:2096706",
        "tgn:1000001",
        "tgn:2001747",
        "tgn:7012149",
        "tgn:7007712",
        "tgn:7029392"
    ],
    "tgn:id":2096706,
    "tgn:name":"Simpsonville",
    "tgn:placetype":[
        "aat:300008347"
    ]
},
  "bbox": [],
  "geometry": {"coordinates":[-82.25,34.7333],"type":"Point"}
}