{
  "id": 2488165,
  "type": "Feature",
  "properties": {
    "tgn:hierarchy":[
        "tgn:2488165",
        "tgn:1000001",
        "tgn:1002200",
        "tgn:7012149",
        "tgn:7007240",
        "tgn:7029392"
    ],
    "tgn:id":2488165,
    "tgn:name":"Magnolia Point",
    "tgn:placetype":[
        "aat:300008850"
    ]
},
  "bbox": [],
  "geometry": {"coordinates":[-80.7333,28.3667],"type":"Point"}
}