{
  "id": 2778721,
  "type": "Feature",
  "properties": {
    "tgn:hierarchy":[
        "tgn:2778721",
        "tgn:1000001",
        "tgn:7012149",
        "tgn:2000823",
        "tgn:7007255",
        "tgn:7029392"
    ],
    "tgn:id":2778721,
    "tgn:name":"Wolf Branch",
    "tgn:placetype":[
        "aat:300008699"
    ]
},
  "bbox": [],
  "geometry": {"coordinates":[-88.1667,36.7667],"type":"Point"}
}