{
  "id": 2719349,
  "type": "Feature",
  "properties": {
    "tgn:hierarchy":[
        "tgn:2719349",
        "tgn:1000001",
        "tgn:7012149",
        "tgn:2001281",
        "tgn:7007524",
        "tgn:7029392"
    ],
    "tgn:id":2719349,
    "tgn:name":"Three Brothers",
    "tgn:placetype":[
        "aat:300008697"
    ]
},
  "bbox": [],
  "geometry": {"coordinates":[-112.25,46.3833],"type":"Point"}
}