{
  "id": 2424733,
  "type": "Feature",
  "properties": {
    "tgn:hierarchy":[
        "tgn:2424733",
        "tgn:1000001",
        "tgn:2000199",
        "tgn:7012149",
        "tgn:7007158",
        "tgn:7029392"
    ],
    "tgn:id":2424733,
    "tgn:name":"Johnson Ditch",
    "tgn:placetype":[
        "aat:300006075"
    ]
},
  "bbox": [],
  "geometry": {"coordinates":[-106.1333,38.8167],"type":"Point"}
}