{
  "id": 2675481,
  "type": "Feature",
  "properties": {
    "tgn:hierarchy":[
        "tgn:2675481",
        "tgn:1000001",
        "tgn:7012149",
        "tgn:2002383",
        "tgn:7007923",
        "tgn:7029392"
    ],
    "tgn:id":2675481,
    "tgn:name":"Solid Waste Disposal Cell H Reservoir",
    "tgn:placetype":[
        "aat:300006191"
    ]
},
  "bbox": [],
  "geometry": {"coordinates":[-109.75,41.5833],"type":"Point"}
}