{
  "id": 2707897,
  "type": "Feature",
  "properties": {
    "tgn:hierarchy":[
        "tgn:2707897",
        "tgn:1000001",
        "tgn:7012149",
        "tgn:2001903",
        "tgn:7007825",
        "tgn:7029392"
    ],
    "tgn:id":2707897,
    "tgn:name":"Swift Cave",
    "tgn:placetype":[
        "aat:300008746"
    ]
},
  "bbox": [],
  "geometry": {"coordinates":[-85.3833,36.25],"type":"Point"}
}