{
  "id": 2342702,
  "type": "Feature",
  "properties": {
    "tgn:hierarchy":[
        "tgn:2342702",
        "tgn:1000001",
        "tgn:7012149",
        "tgn:7007825",
        "tgn:7029392"
    ],
    "tgn:id":2342702,
    "tgn:name":"Funns Branch",
    "tgn:placetype":[
        "aat:300008699"
    ]
},
  "bbox": [],
  "geometry": {"coordinates":[-85.8333,36.3333],"type":"Point"}
}