{
  "id": 7495478,
  "type": "Feature",
  "properties": {
    "tgn:hierarchy":[
        "tgn:7495478",
        "tgn:7487020",
        "tgn:1000004",
        "tgn:1000141",
        "tgn:7029392"
    ],
    "tgn:id":7495478,
    "tgn:name":"Cuicheng Qiao",
    "tgn:placetype":[
        "aat:300007836"
    ]
},
  "bbox": [],
  "geometry": {"coordinates":[120.7958,24.3871],"type":"Point"}
}