{
  "id": 1080398,
  "type": "Feature",
  "properties": {
    "tgn:hierarchy":[
        "tgn:1080398",
        "tgn:1000004",
        "tgn:7000274",
        "tgn:7000893",
        "tgn:1000120",
        "tgn:7029392"
    ],
    "tgn:id":1080398,
    "tgn:name":"Kaminoyama",
    "tgn:placetype":[
        "aat:300008347"
    ]
},
  "bbox": [],
  "geometry": {"coordinates":[140.2667,38.1667],"type":"Point"}
}