{
  "id": 2733651,
  "type": "Feature",
  "properties": {
    "tgn:hierarchy":[
        "tgn:2733651",
        "tgn:1000001",
        "tgn:7012149",
        "tgn:7016021",
        "tgn:7007568",
        "tgn:7029392"
    ],
    "tgn:id":2733651,
    "tgn:name":"Turnbull Corner",
    "tgn:placetype":[
        "aat:300008347"
    ]
},
  "bbox": [],
  "geometry": {"coordinates":[-75.1333,44.7667],"type":"Point"}
}