{
  "id": 2327896,
  "type": "Feature",
  "properties": {
    "tgn:hierarchy":[
        "tgn:2327896",
        "tgn:1000001",
        "tgn:7016172",
        "tgn:7012149",
        "tgn:2000152",
        "tgn:7029392"
    ],
    "tgn:id":2327896,
    "tgn:name":"Fish Lake",
    "tgn:placetype":[
        "aat:300008680"
    ]
},
  "bbox": [],
  "geometry": {"coordinates":[-91.3167,34.7667],"type":"Point"}
}