{
  "id": 7178795,
  "type": "Feature",
  "properties": {
    "tgn:hierarchy":[
        "tgn:7178795",
        "tgn:1000003",
        "tgn:7003676",
        "tgn:7000084",
        "tgn:7029392"
    ],
    "tgn:id":7178795,
    "tgn:name":"Hachenhausen",
    "tgn:placetype":[
        "aat:300008347"
    ]
},
  "bbox": [],
  "geometry": {"coordinates":[10.083333,51.866667],"type":"Point"}
}