{
  "id": 2230789,
  "type": "Feature",
  "properties": {
    "tgn:hierarchy":[
        "tgn:2230789",
        "tgn:1000001",
        "tgn:7012149",
        "tgn:2000182",
        "tgn:7007157",
        "tgn:7029392"
    ],
    "tgn:id":2230789,
    "tgn:name":"Central Drain Nine",
    "tgn:placetype":[
        "aat:300006075"
    ]
},
  "bbox": [],
  "geometry": {"coordinates":[-115.6167,32.7833],"type":"Point"}
}