{
  "id": 7463322,
  "type": "Feature",
  "properties": {
    "tgn:hierarchy":[
        "tgn:7463322",
        "tgn:7002445",
        "tgn:1000003",
        "tgn:7008134",
        "tgn:7008591",
        "tgn:7029392"
    ],
    "tgn:id":7463322,
    "tgn:name:en":"Kingmere Rocks",
    "tgn:placetype":[
        "aat:300008808"
    ]
},
  "bbox": [],
  "geometry": {"coordinates":[-0.466667,50.716667],"type":"Point"}
}