{
  "id": 7448694,
  "type": "Feature",
  "properties": {
    "tgn:hierarchy":[
        "tgn:7448694",
        "tgn:7002444",
        "tgn:1000003",
        "tgn:7008094",
        "tgn:7008591",
        "tgn:7029392"
    ],
    "tgn:id":7448694,
    "tgn:name:en":"Sgriobh Bhan",
    "tgn:placetype":[
        "aat:300386970"
    ]
},
  "bbox": [],
  "geometry": {"coordinates":[-7.733333,56.65],"type":"Point"}
}