<<<<<<< HEAD
{
  "id": 7113869,
  "type": "Feature",
  "properties": {
    "tgn:hierarchy":[
        "tgn:7113869",
        "tgn:7000096",
        "tgn:1000003",
        "tgn:7000084",
        "tgn:7029392"
    ],
    "tgn:id":7113869,
    "tgn:name":"R\u00f6ddelinsee",
    "tgn:placetype":[
        "aat:300008680"
    ]
},
  "bbox": [],
  "geometry": {"coordinates":[13.45,53.1],"type":"Point"}
}
=======
{"geometry":{"type":"Point","coordinates":[13.450000,53.100000]},"type":"Feature","properties":{"hierarchy":["tgn:7113869","tgn:7000096","tgn:1000003","tgn:7000084","tgn:7029392"],"placetype":["aat:300008680"],"id":7113869,"name:xx":"R\u00f6ddelinsee"}}
>>>>>>> 03f74aca74312dbeaf24d7e61306dd6a786dc3d0
