{
  "id": 7172297,
  "type": "Feature",
  "properties": {
    "tgn:hierarchy":[
        "tgn:7172297",
        "tgn:1000003",
        "tgn:7003682",
        "tgn:7000084",
        "tgn:7029392"
    ],
    "tgn:id":7172297,
    "tgn:name":"Herren-Sulzbach",
    "tgn:placetype":[
        "aat:300008347"
    ]
},
  "bbox": [],
  "geometry": {"coordinates":[7.533333,49.65],"type":"Point"}
}