{
  "id": 2634520,
  "type": "Feature",
  "properties": {
    "tgn:hierarchy":[
        "tgn:2634520",
        "tgn:1000001",
        "tgn:7012149",
        "tgn:7007157",
        "tgn:1002857",
        "tgn:7029392"
    ],
    "tgn:id":2634520,
    "tgn:name":"Rustler Canyon",
    "tgn:placetype":[
        "aat:300008761"
    ]
},
  "bbox": [],
  "geometry": {"coordinates":[-115.35,35.05],"type":"Point"}
}