{
  "id": 2112597,
  "type": "Feature",
  "properties": {
    "tgn:hierarchy":[
        "tgn:2112597",
        "tgn:1000001",
        "tgn:7012149",
        "tgn:1002362",
        "tgn:7007919",
        "tgn:7029392"
    ],
    "tgn:id":2112597,
    "tgn:name":"Laneview",
    "tgn:placetype":[
        "aat:300008347"
    ]
},
  "bbox": [],
  "geometry": {"coordinates":[-76.7167,37.75],"type":"Point"}
}