{
  "id": 7363180,
  "type": "Feature",
  "properties": {
    "tgn:hierarchy":[
        "tgn:7363180",
        "tgn:1000001",
        "tgn:7005597",
        "tgn:7005560",
        "tgn:7029392"
    ],
    "tgn:id":7363180,
    "tgn:name":"El Mezquital",
    "tgn:placetype":[
        "aat:300008347"
    ]
},
  "bbox": [],
  "geometry": {"coordinates":[-99.183333,26.633333],"type":"Point"}
}