<<<<<<< HEAD
{
  "id": 7470710,
  "type": "Feature",
  "properties": {
    "tgn:hierarchy":[
        "tgn:7470710",
        "tgn:1000004",
        "tgn:1000454",
        "tgn:1000141",
        "tgn:7029392"
    ],
    "tgn:id":7470710,
    "tgn:name":"Houzhouzi",
    "tgn:placetype":[
        "aat:300008347"
    ]
},
  "bbox": [],
  "geometry": {"coordinates":[121.447729,25.2253],"type":"Point"}
}
=======
{"geometry":{"type":"Point","coordinates":[121.447729,25.225300]},"type":"Feature","properties":{"hierarchy":["tgn:7470710","tgn:1000004","tgn:1000454","tgn:1000141","tgn:7029392"],"placetype":["aat:300008347"],"id":7470710,"name:xx":"Houzhouzi"}}
>>>>>>> 03f74aca74312dbeaf24d7e61306dd6a786dc3d0
