{
  "id": 2653548,
  "type": "Feature",
  "properties": {
    "tgn:hierarchy":[
        "tgn:2653548",
        "tgn:1000001",
        "tgn:7012149",
        "tgn:7007158",
        "tgn:2000253",
        "tgn:7029392"
    ],
    "tgn:id":2653548,
    "tgn:name":"Seventy Holes Lake",
    "tgn:placetype":[
        "aat:300008680"
    ]
},
  "bbox": [],
  "geometry": {"coordinates":[-104.3167,40.3333],"type":"Point"}
}