{
  "id": 7258515,
  "type": "Feature",
  "properties": {
    "tgn:hierarchy":[
        "tgn:7258515",
        "tgn:1000003",
        "tgn:7003624",
        "tgn:7016845",
        "tgn:7029392"
    ],
    "tgn:id":7258515,
    "tgn:name:nl":"Allardspolder",
    "tgn:placetype":[
        "aat:300006163"
    ]
},
  "bbox": [],
  "geometry": {"coordinates":[4.85,51.716667],"type":"Point"}
}