{
  "id": 2718361,
  "type": "Feature",
  "properties": {
    "tgn:hierarchy":[
        "tgn:2718361",
        "tgn:1000001",
        "tgn:7012149",
        "tgn:1003018",
        "tgn:7007919",
        "tgn:7029392"
    ],
    "tgn:id":2718361,
    "tgn:name":"Thompson Hill",
    "tgn:placetype":[
        "aat:300008798"
    ]
},
  "bbox": [],
  "geometry": {"coordinates":[-76.7333,38.0833],"type":"Point"}
}