{
  "id": 7460743,
  "type": "Feature",
  "properties": {
    "tgn:hierarchy":[
        "tgn:7460743",
        "tgn:7002444",
        "tgn:1000003",
        "tgn:7008082",
        "tgn:7008591",
        "tgn:7029392"
    ],
    "tgn:id":7460743,
    "tgn:name:en":"Latheronwheel House",
    "tgn:placetype":[
        "aat:300004792"
    ]
},
  "bbox": [],
  "geometry": {"coordinates":[-3.383333,58.266667],"type":"Point"}
}