{
  "id": 7523522,
  "type": "Feature",
  "properties": {
    "tgn:hierarchy":[
        "tgn:7523522",
        "tgn:7001242",
        "tgn:7001311",
        "tgn:7016833",
        "tgn:7029392"
    ],
    "tgn:id":7523522,
    "tgn:name:en":"Falq al Hun\u016bd, W\u0101d\u012b",
    "tgn:placetype":[
        "aat:300379998"
    ]
},
  "bbox": [],
  "geometry": {"coordinates":[32.59834,25.336665],"type":"Point"}
}