{
  "id": 2343512,
  "type": "Feature",
  "properties": {
    "tgn:hierarchy":[
        "tgn:2343512",
        "tgn:1000001",
        "tgn:7012149",
        "tgn:1002553",
        "tgn:7007920",
        "tgn:7029392"
    ],
    "tgn:id":2343512,
    "tgn:name":"Gale Creek",
    "tgn:placetype":[
        "aat:300008706"
    ]
},
  "bbox": [],
  "geometry": {"coordinates":[-121.3167,47.3667],"type":"Point"}
}