{
  "id": 2100298,
  "type": "Feature",
  "properties": {
    "tgn:hierarchy":[
        "tgn:2100298",
        "tgn:1000001",
        "tgn:7012149",
        "tgn:2001889",
        "tgn:7007825",
        "tgn:7029392"
    ],
    "tgn:id":2100298,
    "tgn:name":"Meadow",
    "tgn:placetype":[
        "aat:300008347",
        "aat:300387210"
    ]
},
  "bbox": [],
  "geometry": {"coordinates":[-84.15,35.6833],"type":"Point"}
}