{
  "id": 7153318,
  "type": "Feature",
  "properties": {
    "tgn:hierarchy":[
        "tgn:7153318",
        "tgn:1000003",
        "tgn:7003676",
        "tgn:7000084",
        "tgn:7029392"
    ],
    "tgn:id":7153318,
    "tgn:name":"Jader Marsch",
    "tgn:placetype":[
        "aat:300055621"
    ]
},
  "bbox": [],
  "geometry": {"coordinates":[8.216667,53.35],"type":"Point"}
}