{
  "id": 2685495,
  "type": "Feature",
  "properties": {
    "tgn:hierarchy":[
        "tgn:2685495",
        "tgn:1000001",
        "tgn:7012149",
        "tgn:1002701",
        "tgn:7007706",
        "tgn:7029392"
    ],
    "tgn:id":2685495,
    "tgn:name":"Spratt",
    "tgn:placetype":[
        "aat:300008347"
    ]
},
  "bbox": [],
  "geometry": {"coordinates":[-81.7167,39.8667],"type":"Point"}
}