{
  "id": 7435459,
  "type": "Feature",
  "properties": {
    "tgn:hierarchy":[
        "tgn:7435459",
        "tgn:1000001",
        "tgn:1001960",
        "tgn:7005560",
        "tgn:7029392"
    ],
    "tgn:id":7435459,
    "tgn:name":"Rancho Vado Seco",
    "tgn:placetype":[
        "aat:300000241"
    ]
},
  "bbox": [],
  "geometry": {"coordinates":[-110.616667,30.883333],"type":"Point"}
}