{
  "id": 7021349,
  "type": "Feature",
  "properties": {
    "tgn:hierarchy":[
        "tgn:7021349",
        "tgn:1000001",
        "tgn:7012149",
        "tgn:2001059",
        "tgn:7007521",
        "tgn:7029392"
    ],
    "tgn:id":7021349,
    "tgn:name":"Nilson Lake",
    "tgn:placetype":[
        "aat:300008680"
    ]
},
  "bbox": [],
  "geometry": {"coordinates":[-95.2833,45.4667],"type":"Point"}
}