<<<<<<< HEAD
{
  "id": 7021349,
  "type": "Feature",
  "properties": {
    "tgn:hierarchy":[
        "tgn:7021349",
        "tgn:1000001",
        "tgn:7012149",
        "tgn:2001059",
        "tgn:7007521",
        "tgn:7029392"
    ],
    "tgn:id":7021349,
    "tgn:name":"Nilson Lake",
    "tgn:placetype":[
        "aat:300008680"
    ]
},
  "bbox": [],
  "geometry": {"coordinates":[-95.2833,45.4667],"type":"Point"}
}
=======
{"geometry":{"type":"Point","coordinates":[-95.283300,45.466700]},"type":"Feature","properties":{"hierarchy":["tgn:7021349","tgn:1000001","tgn:7012149","tgn:2001059","tgn:7007521","tgn:7029392"],"placetype":["aat:300008680"],"id":7021349,"name:xx":"Nilson Lake"}}
>>>>>>> 03f74aca74312dbeaf24d7e61306dd6a786dc3d0
