{
  "id": 2079159,
  "type": "Feature",
  "properties": {
    "tgn:hierarchy":[
        "tgn:2079159",
        "tgn:1000001",
        "tgn:7012149",
        "tgn:1002761",
        "tgn:7007706",
        "tgn:7029392"
    ],
    "tgn:id":2079159,
    "tgn:name":"Curtice",
    "tgn:placetype":[
        "aat:300008347"
    ]
},
  "bbox": [],
  "geometry": {"coordinates":[-83.3667,41.6167],"type":"Point"}
}