{
  "id": 1107041,
  "type": "Feature",
  "properties": {
    "tgn:hierarchy":[
        "tgn:1107041",
        "tgn:7000895",
        "tgn:1000004",
        "tgn:1001037",
        "tgn:1000120",
        "tgn:7029392"
    ],
    "tgn:id":1107041,
    "tgn:name":"Yakushi-dake",
    "tgn:placetype":[
        "aat:300008795"
    ]
},
  "bbox": [],
  "geometry": {"coordinates":[137.55,36.4667],"type":"Point"}
}