{
  "id": 7471511,
  "type": "Feature",
  "properties": {
    "tgn:hierarchy":[
        "tgn:7471511",
        "tgn:7001004",
        "tgn:1000004",
        "tgn:1000141",
        "tgn:7029392"
    ],
    "tgn:id":7471511,
    "tgn:name":"Xinghualiao",
    "tgn:placetype":[
        "aat:300008347"
    ]
},
  "bbox": [],
  "geometry": {"coordinates":[120.4261,22.6967],"type":"Point"}
}