{
  "id": 7550614,
  "type": "Feature",
  "properties": {
    "tgn:hierarchy":[
        "tgn:7550614",
        "tgn:7016678",
        "tgn:7000204",
        "tgn:1000004",
        "tgn:1007275",
        "tgn:7000198",
        "tgn:7029392"
    ],
    "tgn:id":7550614,
    "tgn:name:en":"Dak-omkeh",
    "tgn:placetype":[
        "aat:300008347"
    ]
},
  "bbox": [],
  "geometry": {"coordinates":[93.65,7.083333],"type":"Point"}
}