{
  "id": 2501752,
  "type": "Feature",
  "properties": {
    "tgn:hierarchy":[
        "tgn:2501752",
        "tgn:1000001",
        "tgn:7012149",
        "tgn:7007157",
        "tgn:1002956",
        "tgn:7029392"
    ],
    "tgn:id":2501752,
    "tgn:name":"McIntyre Grove",
    "tgn:placetype":[
        "aat:300132451"
    ]
},
  "bbox": [],
  "geometry": {"coordinates":[-118.5833,36.1333],"type":"Point"}
}