{
  "id": 7299418,
  "type": "Feature",
  "properties": {
    "tgn:hierarchy":[
        "tgn:7299418",
        "tgn:7002849",
        "tgn:1000003",
        "tgn:7009604",
        "tgn:1000095",
        "tgn:7029392"
    ],
    "tgn:id":7299418,
    "tgn:name":"Urbi",
    "tgn:placetype":[
        "aat:300008347"
    ]
},
  "bbox": [],
  "geometry": {"coordinates":[-2.870568,43.239708],"type":"Point"}
}