{
  "id": 2214288,
  "type": "Feature",
  "properties": {
    "tgn:hierarchy":[
        "tgn:2214288",
        "tgn:1000001",
        "tgn:7012149",
        "tgn:2002378",
        "tgn:7007923",
        "tgn:7029392"
    ],
    "tgn:id":2214288,
    "tgn:name":"Cake Hill",
    "tgn:placetype":[
        "aat:300008798"
    ]
},
  "bbox": [],
  "geometry": {"coordinates":[-104.8667,43.1333],"type":"Point"}
}