<<<<<<< HEAD
{
  "id": 7370708,
  "type": "Feature",
  "properties": {
    "tgn:hierarchy":[
        "tgn:7370708",
        "tgn:1001853",
        "tgn:1000001",
        "tgn:7005560",
        "tgn:7029392"
    ],
    "tgn:id":7370708,
    "tgn:name":"Gloria, Laguna de la",
    "tgn:placetype":[
        "aat:300387087"
    ]
},
  "bbox": [],
  "geometry": {"coordinates":[-100.4,27.616667],"type":"Point"}
}
=======
{"geometry":{"type":"Point","coordinates":[-100.400000,27.616667]},"type":"Feature","properties":{"hierarchy":["tgn:7370708","tgn:1001853","tgn:1000001","tgn:7005560","tgn:7029392"],"placetype":["aat:300387087"],"id":7370708,"name:xx":"Gloria, Laguna de la"}}
>>>>>>> 03f74aca74312dbeaf24d7e61306dd6a786dc3d0
