{
  "id": 2435125,
  "type": "Feature",
  "properties": {
    "tgn:hierarchy":[
        "tgn:2435125",
        "tgn:1000001",
        "tgn:7012149",
        "tgn:2000963",
        "tgn:7007520",
        "tgn:7029392"
    ],
    "tgn:id":2435125,
    "tgn:name":"Kentucky Lake",
    "tgn:placetype":[
        "aat:300008680"
    ]
},
  "bbox": [],
  "geometry": {"coordinates":[-88.7833,46.5667],"type":"Point"}
}