{
  "id": 7501808,
  "type": "Feature",
  "properties": {
    "tgn:hierarchy":[
        "tgn:7501808",
        "tgn:7488858",
        "tgn:1000004",
        "tgn:1000141",
        "tgn:7029392"
    ],
    "tgn:id":7501808,
    "tgn:name":"Shangping",
    "tgn:placetype":[
        "aat:300008347"
    ]
},
  "bbox": [],
  "geometry": {"coordinates":[120.894237,24.113163],"type":"Point"}
}