{
  "id": 7383921,
  "type": "Feature",
  "properties": {
    "tgn:hierarchy":[
        "tgn:7383921",
        "tgn:1000001",
        "tgn:7005600",
        "tgn:7005560",
        "tgn:7029392"
    ],
    "tgn:id":7383921,
    "tgn:name":"Oxcum",
    "tgn:placetype":[
        "aat:300008347"
    ]
},
  "bbox": [],
  "geometry": {"coordinates":[-89.766667,20.933333],"type":"Point"}
}