{
  "id": 2086972,
  "type": "Feature",
  "properties": {
    "tgn:hierarchy":[
        "tgn:2086972",
        "tgn:1000001",
        "tgn:1002225",
        "tgn:7012149",
        "tgn:7007710",
        "tgn:7029392"
    ],
    "tgn:id":2086972,
    "tgn:name":"Cardiff",
    "tgn:placetype":[
        "aat:300008347",
        "aat:300387210"
    ]
},
  "bbox": [],
  "geometry": {"coordinates":[-78.8333,40.4833],"type":"Point"}
}