{
  "id": 2763265,
  "type": "Feature",
  "properties": {
    "tgn:hierarchy":[
        "tgn:2763265",
        "tgn:1000001",
        "tgn:7012149",
        "tgn:2002167",
        "tgn:7007919",
        "tgn:7029392"
    ],
    "tgn:id":2763265,
    "tgn:name":"Wet Branch",
    "tgn:placetype":[
        "aat:300008699"
    ]
},
  "bbox": [],
  "geometry": {"coordinates":[-79.7333,36.75],"type":"Point"}
}