<<<<<<< HEAD
{
  "id": 2153969,
  "type": "Feature",
  "properties": {
    "tgn:hierarchy":[
        "tgn:2153969",
        "tgn:7006450",
        "tgn:2000069",
        "tgn:1000001",
        "tgn:7012149",
        "tgn:7029392"
    ],
    "tgn:id":2153969,
    "tgn:name":"Bear Creek",
    "tgn:placetype":[
        "aat:300008706"
    ]
},
  "bbox": [],
  "geometry": {"coordinates":[-161.1833,59.3833],"type":"Point"}
}
=======
{"geometry":{"type":"Point","coordinates":[-161.183300,59.383300]},"type":"Feature","properties":{"hierarchy":["tgn:2153969","tgn:7006450","tgn:2000069","tgn:1000001","tgn:7012149","tgn:7029392"],"placetype":["aat:300008706"],"id":2153969,"name:xx":"Bear Creek"}}
>>>>>>> 03f74aca74312dbeaf24d7e61306dd6a786dc3d0
