{
  "id": 2153969,
  "type": "Feature",
  "properties": {
    "tgn:hierarchy":[
        "tgn:2153969",
        "tgn:7006450",
        "tgn:2000069",
        "tgn:1000001",
        "tgn:7012149",
        "tgn:7029392"
    ],
    "tgn:id":2153969,
    "tgn:name":"Bear Creek",
    "tgn:placetype":[
        "aat:300008706"
    ]
},
  "bbox": [],
  "geometry": {"coordinates":[-161.1833,59.3833],"type":"Point"}
}