{
  "id": 7325982,
  "type": "Feature",
  "properties": {
    "tgn:hierarchy":[
        "tgn:7325982",
        "tgn:7001158",
        "tgn:7002848",
        "tgn:1000003",
        "tgn:1000095",
        "tgn:7029392"
    ],
    "tgn:id":7325982,
    "tgn:name":"Ramiro",
    "tgn:placetype":[
        "aat:300008347"
    ]
},
  "bbox": [],
  "geometry": {"coordinates":[-4.783333,41.233333],"type":"Point"}
}