{
  "id": 1091279,
  "type": "Feature",
  "properties": {
    "tgn:hierarchy":[
        "tgn:1091279",
        "tgn:7001242",
        "tgn:1001758",
        "tgn:1000176",
        "tgn:7029392"
    ],
    "tgn:id":1091279,
    "tgn:name":"A\u00efn Ben Tili",
    "tgn:placetype":[
        "aat:300008347"
    ]
},
  "bbox": [],
  "geometry": {"coordinates":[-9.5833,25.4333],"type":"Point"}
}