{
  "id": 2429930,
  "type": "Feature",
  "properties": {
    "tgn:hierarchy":[
        "tgn:2429930",
        "tgn:7023902",
        "tgn:1000001",
        "tgn:7012149",
        "tgn:7007249",
        "tgn:7029392"
    ],
    "tgn:id":2429930,
    "tgn:name":"Kaalaala Gulch",
    "tgn:placetype":[
        "aat:300008761"
    ]
},
  "bbox": [],
  "geometry": {"coordinates":[-155.5167,19.2667],"type":"Point"}
}