{
  "id": 2692025,
  "type": "Feature",
  "properties": {
    "tgn:hierarchy":[
        "tgn:2692025",
        "tgn:1000001",
        "tgn:2001410",
        "tgn:7012149",
        "tgn:7007526",
        "tgn:7029392"
    ],
    "tgn:id":2692025,
    "tgn:name":"State Line Hills",
    "tgn:placetype":[
        "aat:300386831"
    ]
},
  "bbox": [],
  "geometry": {"coordinates":[-115.4333,35.6667],"type":"Point"}
}