{
  "id": 7303874,
  "type": "Feature",
  "properties": {
    "tgn:hierarchy":[
        "tgn:7303874",
        "tgn:7002847",
        "tgn:1001647",
        "tgn:1000003",
        "tgn:1000095",
        "tgn:7029392"
    ],
    "tgn:id":7303874,
    "tgn:name":"Navahermosa",
    "tgn:placetype":[
        "aat:300008347"
    ]
},
  "bbox": [],
  "geometry": {"coordinates":[-4.466667,39.633333],"type":"Point"}
}