{
  "id": 7405503,
  "type": "Feature",
  "properties": {
    "tgn:hierarchy":[
        "tgn:7405503",
        "tgn:7005585",
        "tgn:1000001",
        "tgn:7005560",
        "tgn:7029392"
    ],
    "tgn:id":7405503,
    "tgn:name":"Zoyacalco",
    "tgn:placetype":[
        "aat:300008347"
    ]
},
  "bbox": [],
  "geometry": {"coordinates":[-99.958333,17.75],"type":"Point"}
}