{
  "id": 1011194,
  "type": "Feature",
  "properties": {
    "tgn:hierarchy":[
        "tgn:1011194",
        "tgn:7001242",
        "tgn:1000893",
        "tgn:1000180",
        "tgn:7029392"
    ],
    "tgn:id":1011194,
    "tgn:name":"Santa Marta, Cabo de",
    "tgn:placetype":[
        "aat:300008850"
    ]
},
  "bbox": [],
  "geometry": {"coordinates":[32.9667,-26.0833],"type":"Point"}
}