{
  "id": 2552818,
  "type": "Feature",
  "properties": {
    "tgn:hierarchy":[
        "tgn:2552818",
        "tgn:1000001",
        "tgn:7012149",
        "tgn:2001068",
        "tgn:7007521",
        "tgn:7029392"
    ],
    "tgn:id":2552818,
    "tgn:name":"Nyssens Lake",
    "tgn:placetype":[
        "aat:300008680"
    ]
},
  "bbox": [],
  "geometry": {"coordinates":[-93.55,44.7833],"type":"Point"}
}