{
  "id": 2407472,
  "type": "Feature",
  "properties": {
    "tgn:hierarchy":[
        "tgn:2407472",
        "tgn:1000001",
        "tgn:7012149",
        "tgn:1002575",
        "tgn:7007919",
        "tgn:7029392"
    ],
    "tgn:id":2407472,
    "tgn:name":"Hunts Cove",
    "tgn:placetype":[
        "aat:300132316"
    ]
},
  "bbox": [],
  "geometry": {"coordinates":[-76.3333,37.6667],"type":"Point"}
}