{
  "id": 2515776,
  "type": "Feature",
  "properties": {
    "tgn:hierarchy":[
        "tgn:2515776",
        "tgn:1000001",
        "tgn:7012149",
        "tgn:2000393",
        "tgn:7007248",
        "tgn:7029392"
    ],
    "tgn:id":2515776,
    "tgn:name":"Millwood Lake",
    "tgn:placetype":[
        "aat:300006191"
    ]
},
  "bbox": [],
  "geometry": {"coordinates":[-83.8833,33.0167],"type":"Point"}
}