{
  "id": 2744681,
  "type": "Feature",
  "properties": {
    "tgn:hierarchy":[
        "tgn:2744681",
        "tgn:7006450",
        "tgn:1000001",
        "tgn:7012149",
        "tgn:2000089",
        "tgn:7029392"
    ],
    "tgn:id":2744681,
    "tgn:name":"Victor Lake",
    "tgn:placetype":[
        "aat:300008680"
    ]
},
  "bbox": [],
  "geometry": {"coordinates":[-146.8333,66.1833],"type":"Point"}
}