{
  "id": 7422544,
  "type": "Feature",
  "properties": {
    "tgn:hierarchy":[
        "tgn:7422544",
        "tgn:1000001",
        "tgn:1001960",
        "tgn:7005560",
        "tgn:7029392"
    ],
    "tgn:id":7422544,
    "tgn:name":"El Rinc\u00f3n",
    "tgn:placetype":[
        "aat:300008347"
    ]
},
  "bbox": [],
  "geometry": {"coordinates":[-111.064167,30.9275],"type":"Point"}
}