{
  "id": 7033698,
  "type": "Feature",
  "properties": {
    "tgn:hierarchy":[
        "tgn:7033698",
        "tgn:7003129",
        "tgn:1000003",
        "tgn:7008516",
        "tgn:1000080",
        "tgn:7029392"
    ],
    "tgn:id":7033698,
    "tgn:name":"Coriano",
    "tgn:placetype":[
        "aat:300008347"
    ]
},
  "bbox": [],
  "geometry": {"coordinates":[12.073611,44.230833],"type":"Point"}
}