{
  "id": 2325769,
  "type": "Feature",
  "properties": {
    "tgn:hierarchy":[
        "tgn:2325769",
        "tgn:1000001",
        "tgn:7012149",
        "tgn:2001714",
        "tgn:7007708",
        "tgn:7029392"
    ],
    "tgn:id":2325769,
    "tgn:name":"Field Spring",
    "tgn:placetype":[
        "aat:300008697"
    ]
},
  "bbox": [],
  "geometry": {"coordinates":[-121.2833,42.2667],"type":"Point"}
}