{
  "id": 7130607,
  "type": "Feature",
  "properties": {
    "tgn:hierarchy":[
        "tgn:7130607",
        "tgn:7003669",
        "tgn:1000003",
        "tgn:7000084",
        "tgn:7029392"
    ],
    "tgn:id":7130607,
    "tgn:name":"Marktzeuln",
    "tgn:placetype":[
        "aat:300008347"
    ]
},
  "bbox": [],
  "geometry": {"coordinates":[11.183333,50.166667],"type":"Point"}
}