{
  "id": 2223522,
  "type": "Feature",
  "properties": {
    "tgn:hierarchy":[
        "tgn:2223522",
        "tgn:1000001",
        "tgn:7012149",
        "tgn:2001846",
        "tgn:7007825",
        "tgn:7029392"
    ],
    "tgn:id":2223522,
    "tgn:name":"Carter Branch",
    "tgn:placetype":[
        "aat:300008699"
    ]
},
  "bbox": [],
  "geometry": {"coordinates":[-82.0333,36.4667],"type":"Point"}
}