{
  "id": 2026160,
  "type": "Feature",
  "properties": {
    "tgn:hierarchy":[
        "tgn:2026160",
        "tgn:1000001",
        "tgn:2000460",
        "tgn:7012149",
        "tgn:7007250",
        "tgn:7029392"
    ],
    "tgn:id":2026160,
    "tgn:name":"Sunnyside",
    "tgn:placetype":[
        "aat:300008347",
        "aat:300387210"
    ]
},
  "bbox": [],
  "geometry": {"coordinates":[-116.3833,48.2667],"type":"Point"}
}