{
  "id": 2688439,
  "type": "Feature",
  "properties": {
    "tgn:hierarchy":[
        "tgn:2688439",
        "tgn:1000001",
        "tgn:2000923",
        "tgn:7012149",
        "tgn:7007515",
        "tgn:7029392"
    ],
    "tgn:id":2688439,
    "tgn:name":"Spruce Island",
    "tgn:placetype":[
        "aat:300008791"
    ]
},
  "bbox": [],
  "geometry": {"coordinates":[-70.0333,44.4833],"type":"Point"}
}