{
  "id": 2566892,
  "type": "Feature",
  "properties": {
    "tgn:hierarchy":[
        "tgn:2566892",
        "tgn:1000001",
        "tgn:7012149",
        "tgn:2001237",
        "tgn:7007523",
        "tgn:7029392"
    ],
    "tgn:id":2566892,
    "tgn:name":"Panther Cave",
    "tgn:placetype":[
        "aat:300008746"
    ]
},
  "bbox": [],
  "geometry": {"coordinates":[-91.0667,36.7333],"type":"Point"}
}