{
  "id": 7229810,
  "type": "Feature",
  "properties": {
    "tgn:hierarchy":[
        "tgn:7229810",
        "tgn:7002739",
        "tgn:7017076",
        "tgn:1000003",
        "tgn:1000074",
        "tgn:7029392"
    ],
    "tgn:id":7229810,
    "tgn:name":"Khrisov\u00edtsion",
    "tgn:placetype":[
        "aat:300008347"
    ]
},
  "bbox": [],
  "geometry": {"coordinates":[22.216667,37.55],"type":"Point"}
}