{
  "id": 2016623,
  "type": "Feature",
  "properties": {
    "tgn:hierarchy":[
        "tgn:2016623",
        "tgn:1000001",
        "tgn:1002949",
        "tgn:7012149",
        "tgn:7007159",
        "tgn:7029392"
    ],
    "tgn:id":2016623,
    "tgn:name":"Bolton",
    "tgn:placetype":[
        "aat:300008347"
    ]
},
  "bbox": [],
  "geometry": {"coordinates":[-72.4333,41.7667],"type":"Point"}
}