{
  "id": 7506840,
  "type": "Feature",
  "properties": {
    "tgn:hierarchy":[
        "tgn:7506840",
        "tgn:1008380",
        "tgn:1000226",
        "tgn:7018426",
        "tgn:1000006",
        "tgn:7029392"
    ],
    "tgn:id":7506840,
    "tgn:name:en":"Rauaruhe",
    "tgn:placetype":[
        "aat:300008795"
    ]
},
  "bbox": [],
  "geometry": {"coordinates":[175.233333,-38.45],"type":"Point"}
}