{
  "id": 2108593,
  "type": "Feature",
  "properties": {
    "tgn:hierarchy":[
        "tgn:2108593",
        "tgn:1000001",
        "tgn:7012149",
        "tgn:1002492",
        "tgn:7007826",
        "tgn:7029392"
    ],
    "tgn:id":2108593,
    "tgn:name":"Wolfe City",
    "tgn:placetype":[
        "aat:300008347"
    ]
},
  "bbox": [],
  "geometry": {"coordinates":[-96.0667,33.3667],"type":"Point"}
}