{
  "id": 1105414,
  "type": "Feature",
  "properties": {
    "tgn:hierarchy":[
        "tgn:1105414",
        "tgn:1000001",
        "tgn:7012149",
        "tgn:2002010",
        "tgn:7007826",
        "tgn:7029392"
    ],
    "tgn:id":1105414,
    "tgn:name":"Livermore, Mount",
    "tgn:placetype":[
        "aat:300008795"
    ]
},
  "bbox": [],
  "geometry": {"coordinates":[-104.1667,30.6167],"type":"Point"}
}