{
  "id": 1050638,
  "type": "Feature",
  "properties": {
    "tgn:hierarchy":[
        "tgn:1050638",
        "tgn:7002444",
        "tgn:1000003",
        "tgn:7008082",
        "tgn:7008591",
        "tgn:7008959",
        "tgn:7029392"
    ],
    "tgn:id":1050638,
    "tgn:name:en":"Earlish",
    "tgn:placetype":[
        "aat:300008347"
    ]
},
  "bbox": [],
  "geometry": {"coordinates":[-6.383333,57.566667],"type":"Point"}
}