{
  "id": 7225623,
  "type": "Feature",
  "properties": {
    "tgn:hierarchy":[
        "tgn:7225623",
        "tgn:7011170",
        "tgn:7002715",
        "tgn:1000003",
        "tgn:1000074",
        "tgn:7029392"
    ],
    "tgn:id":7225623,
    "tgn:name":"N\u00e9a Mors\u00edni",
    "tgn:placetype":[
        "aat:300008347"
    ]
},
  "bbox": [],
  "geometry": {"coordinates":[24.85,41.116667],"type":"Point"}
}