{
  "id": 7227604,
  "type": "Feature",
  "properties": {
    "tgn:hierarchy":[
        "tgn:7227604",
        "tgn:7002745",
        "tgn:7017076",
        "tgn:1000003",
        "tgn:1000074",
        "tgn:7029392"
    ],
    "tgn:id":7227604,
    "tgn:name":"Kondrafouri\u00e1nika",
    "tgn:placetype":[
        "aat:300008347"
    ]
},
  "bbox": [],
  "geometry": {"coordinates":[23.033333,36.566667],"type":"Point"}
}