{
  "id": 2396609,
  "type": "Feature",
  "properties": {
    "tgn:hierarchy":[
        "tgn:2396609",
        "tgn:1000001",
        "tgn:7012149",
        "tgn:2001862",
        "tgn:7007825",
        "tgn:7029392"
    ],
    "tgn:id":2396609,
    "tgn:name":"Holts Hollow",
    "tgn:placetype":[
        "aat:300008761"
    ]
},
  "bbox": [],
  "geometry": {"coordinates":[-86.1667,35.2167],"type":"Point"}
}