{
  "id": 7463376,
  "type": "Feature",
  "properties": {
    "tgn:hierarchy":[
        "tgn:7463376",
        "tgn:7002444",
        "tgn:1000003",
        "tgn:7009907",
        "tgn:7008591",
        "tgn:7029392"
    ],
    "tgn:id":7463376,
    "tgn:name:en":"Hunda",
    "tgn:placetype":[
        "aat:300008791"
    ]
},
  "bbox": [],
  "geometry": {"coordinates":[-2.983333,58.85],"type":"Point"}
}