{
  "id": 2000533,
  "type": "Feature",
  "properties": {
    "tgn:hierarchy":[
        "tgn:2000533",
        "tgn:1000001",
        "tgn:7012149",
        "tgn:7007251",
        "tgn:7029392"
    ],
    "tgn:id":2000533,
    "tgn:name":"Tazewell",
    "tgn:placetype":[
        "aat:300387145",
        "aat:300000771"
    ]
},
  "bbox": [],
  "geometry": {"coordinates":[-89.55,40.5333],"type":"Point"}
}