<<<<<<< HEAD
{
  "id": 2338441,
  "type": "Feature",
  "properties": {
    "tgn:hierarchy":[
        "tgn:2338441",
        "tgn:1002247",
        "tgn:1000001",
        "tgn:7012149",
        "tgn:7007516",
        "tgn:7029392"
    ],
    "tgn:id":2338441,
    "tgn:name":"Foys Hill",
    "tgn:placetype":[
        "aat:300008798"
    ]
},
  "bbox": [],
  "geometry": {"coordinates":[-76.0,39.5833],"type":"Point"}
}
=======
{"geometry":{"type":"Point","coordinates":[-76.000000,39.583300]},"type":"Feature","properties":{"hierarchy":["tgn:2338441","tgn:1002247","tgn:1000001","tgn:7012149","tgn:7007516","tgn:7029392"],"placetype":["aat:300008798"],"id":2338441,"name:xx":"Foys Hill"}}
>>>>>>> 03f74aca74312dbeaf24d7e61306dd6a786dc3d0
