{
  "id": 2132141,
  "type": "Feature",
  "properties": {
    "tgn:hierarchy":[
        "tgn:2132141",
        "tgn:1000001",
        "tgn:7012149",
        "tgn:2001286",
        "tgn:7007524",
        "tgn:7029392"
    ],
    "tgn:id":2132141,
    "tgn:name":"American Mountain",
    "tgn:placetype":[
        "aat:300008798"
    ]
},
  "bbox": [],
  "geometry": {"coordinates":[-116.0167,48.95],"type":"Point"}
}