{
  "id": 2531746,
  "type": "Feature",
  "properties": {
    "tgn:hierarchy":[
        "tgn:2531746",
        "tgn:1000001",
        "tgn:7012149",
        "tgn:1002525",
        "tgn:7007252",
        "tgn:7029392"
    ],
    "tgn:id":2531746,
    "tgn:name":"Mullendore Pond",
    "tgn:placetype":[
        "aat:300008680"
    ]
},
  "bbox": [],
  "geometry": {"coordinates":[-86.0667,39.4167],"type":"Point"}
}