{
  "id": 2680892,
  "type": "Feature",
  "properties": {
    "tgn:hierarchy":[
        "tgn:2680892",
        "tgn:1000001",
        "tgn:7012149",
        "tgn:2001714",
        "tgn:7007708",
        "tgn:7029392"
    ],
    "tgn:id":2680892,
    "tgn:name":"South Lake",
    "tgn:placetype":[
        "aat:300008680"
    ]
},
  "bbox": [],
  "geometry": {"coordinates":[-122.2167,42.65],"type":"Point"}
}