<<<<<<< HEAD
{
  "id": 7176427,
  "type": "Feature",
  "properties": {
    "tgn:hierarchy":[
        "tgn:7176427",
        "tgn:7003692",
        "tgn:1000003",
        "tgn:7000084",
        "tgn:7029392"
    ],
    "tgn:id":7176427,
    "tgn:name":"Haltnau",
    "tgn:placetype":[
        "aat:300000206"
    ]
},
  "bbox": [],
  "geometry": {"coordinates":[9.283333,47.683333],"type":"Point"}
}
=======
{"geometry":{"type":"Point","coordinates":[9.283333,47.683333]},"type":"Feature","properties":{"hierarchy":["tgn:7176427","tgn:7003692","tgn:1000003","tgn:7000084","tgn:7029392"],"placetype":["aat:300000206"],"id":7176427,"name:xx":"Haltnau"}}
>>>>>>> 03f74aca74312dbeaf24d7e61306dd6a786dc3d0
