{
  "id": 2428708,
  "type": "Feature",
  "properties": {
    "tgn:hierarchy":[
        "tgn:2428708",
        "tgn:1002149",
        "tgn:1000001",
        "tgn:7012149",
        "tgn:7007826",
        "tgn:7029392"
    ],
    "tgn:id":2428708,
    "tgn:name":"Julie Creek",
    "tgn:placetype":[
        "aat:300008706"
    ]
},
  "bbox": [],
  "geometry": {"coordinates":[-94.3333,31.15],"type":"Point"}
}