{
  "id": 2728049,
  "type": "Feature",
  "properties": {
    "tgn:hierarchy":[
        "tgn:2728049",
        "tgn:1000001",
        "tgn:1002174",
        "tgn:7012149",
        "tgn:7007826",
        "tgn:7029392"
    ],
    "tgn:id":2728049,
    "tgn:name":"Trapnell Point",
    "tgn:placetype":[
        "aat:300008798"
    ]
},
  "bbox": [],
  "geometry": {"coordinates":[-97.6667,31.1667],"type":"Point"}
}