{
  "id": 2249048,
  "type": "Feature",
  "properties": {
    "tgn:hierarchy":[
        "tgn:2249048",
        "tgn:1000001",
        "tgn:7012149",
        "tgn:2002112",
        "tgn:7007827",
        "tgn:7029392"
    ],
    "tgn:id":2249048,
    "tgn:name":"Cole Canyon",
    "tgn:placetype":[
        "aat:300008761"
    ]
},
  "bbox": [],
  "geometry": {"coordinates":[-112.1167,39.9667],"type":"Point"}
}