{
  "id": 2394656,
  "type": "Feature",
  "properties": {
    "tgn:hierarchy":[
        "tgn:2394656",
        "tgn:1000001",
        "tgn:7012149",
        "tgn:2001969",
        "tgn:7007826",
        "tgn:7029392"
    ],
    "tgn:id":2394656,
    "tgn:name":"Hogue Tank",
    "tgn:placetype":[
        "aat:300006191"
    ]
},
  "bbox": [],
  "geometry": {"coordinates":[-104.75,31.6333],"type":"Point"}
}