{
  "id": 2462949,
  "type": "Feature",
  "properties": {
    "tgn:hierarchy":[
        "tgn:2462949",
        "tgn:1000001",
        "tgn:7012149",
        "tgn:7007157",
        "tgn:1002828",
        "tgn:7029392"
    ],
    "tgn:id":2462949,
    "tgn:name":"Live Oak Canyon",
    "tgn:placetype":[
        "aat:300008761"
    ]
},
  "bbox": [],
  "geometry": {"coordinates":[-116.55,33.6167],"type":"Point"}
}