{
  "id": 7489703,
  "type": "Feature",
  "properties": {
    "tgn:hierarchy":[
        "tgn:7489703",
        "tgn:1000004",
        "tgn:1000454",
        "tgn:1000141",
        "tgn:7029392"
    ],
    "tgn:id":7489703,
    "tgn:name":"Gupoliao Jianshan",
    "tgn:placetype":[
        "aat:300008798"
    ]
},
  "bbox": [],
  "geometry": {"coordinates":[121.697525,24.858656],"type":"Point"}
}