{
  "id": 7578251,
  "type": "Feature",
  "properties": {
    "tgn:hierarchy":[
        "tgn:7578251",
        "tgn:1000004",
        "tgn:7000198",
        "tgn:7000799",
        "tgn:7029392"
    ],
    "tgn:id":7578251,
    "tgn:name:en":"Singran",
    "tgn:placetype":[
        "aat:300008347"
    ]
},
  "bbox": [],
  "geometry": {"coordinates":[76.039525,34.261166],"type":"Point"}
}