{
  "id": 7250348,
  "type": "Feature",
  "properties": {
    "tgn:hierarchy":[
        "tgn:7250348",
        "tgn:7003465",
        "tgn:1000003",
        "tgn:1000063",
        "tgn:4012014",
        "tgn:7029392"
    ],
    "tgn:id":7250348,
    "tgn:name":"Odeigne, Bois d'",
    "tgn:placetype":[
        "aat:300008863"
    ]
},
  "bbox": [],
  "geometry": {"coordinates":[5.683333,50.233333],"type":"Point"}
}