{
  "id": 2728471,
  "type": "Feature",
  "properties": {
    "tgn:hierarchy":[
        "tgn:2728471",
        "tgn:1000001",
        "tgn:2000921",
        "tgn:7012149",
        "tgn:7007515",
        "tgn:7029392"
    ],
    "tgn:id":2728471,
    "tgn:name":"Treat Hill",
    "tgn:placetype":[
        "aat:300008798"
    ]
},
  "bbox": [],
  "geometry": {"coordinates":[-70.1833,44.4833],"type":"Point"}
}