{
  "id": 2584182,
  "type": "Feature",
  "properties": {
    "tgn:hierarchy":[
        "tgn:2584182",
        "tgn:1000001",
        "tgn:7012149",
        "tgn:2000232",
        "tgn:7007158",
        "tgn:7029392"
    ],
    "tgn:id":2584182,
    "tgn:name":"Pines, The",
    "tgn:placetype":[
        "aat:300055621"
    ]
},
  "bbox": [],
  "geometry": {"coordinates":[-108.8833,40.9167],"type":"Point"}
}