<<<<<<< HEAD
{
  "id": 7244938,
  "type": "Feature",
  "properties": {
    "tgn:hierarchy":[
        "tgn:7244938",
        "tgn:7003460",
        "tgn:1000003",
        "tgn:1000063",
        "tgn:4012014",
        "tgn:7029392"
    ],
    "tgn:id":7244938,
    "tgn:name":"Aywaille, Bois d'",
    "tgn:placetype":[
        "aat:300008863"
    ]
},
  "bbox": [],
  "geometry": {"coordinates":[5.733333,50.433333],"type":"Point"}
}
=======
{"geometry":{"type":"Point","coordinates":[5.733333,50.433333]},"type":"Feature","properties":{"hierarchy":["tgn:7244938","tgn:7003460","tgn:1000003","tgn:1000063","tgn:4012014","tgn:7029392"],"placetype":["aat:300008863"],"id":7244938,"name:xx":"Aywaille, Bois d'"}}
>>>>>>> 03f74aca74312dbeaf24d7e61306dd6a786dc3d0
