{
  "id": 7382914,
  "type": "Feature",
  "properties": {
    "tgn:hierarchy":[
        "tgn:7382914",
        "tgn:1000001",
        "tgn:7005599",
        "tgn:7005560",
        "tgn:7029392"
    ],
    "tgn:id":7382914,
    "tgn:name":"Palotal",
    "tgn:placetype":[
        "aat:300008347"
    ]
},
  "bbox": [],
  "geometry": {"coordinates":[-94.916667,17.783333],"type":"Point"}
}