{
  "id": 7321325,
  "type": "Feature",
  "properties": {
    "tgn:hierarchy":[
        "tgn:7321325",
        "tgn:1001702",
        "tgn:1000049",
        "tgn:1000002",
        "tgn:7029392"
    ],
    "tgn:id":7321325,
    "tgn:name":"Bethel, Bah\u00eda",
    "tgn:placetype":[
        "aat:300008676"
    ]
},
  "bbox": [],
  "geometry": {"coordinates":[-75.216667,-49.683333],"type":"Point"}
}