<<<<<<< HEAD
{
  "id": 7025830,
  "type": "Feature",
  "properties": {
    "tgn:hierarchy":[
        "tgn:7025830",
        "tgn:7001242",
        "tgn:7017584",
        "tgn:1000193",
        "tgn:7029392"
    ],
    "tgn:id":7025830,
    "tgn:name":"Simonstad",
    "tgn:placetype":[
        "aat:300008347"
    ]
},
  "bbox": [],
  "geometry": {"coordinates":[18.4333,-34.2],"type":"Point"}
}
=======
{"geometry":{"type":"Point","coordinates":[18.433300,-34.200000]},"type":"Feature","properties":{"hierarchy":["tgn:7025830","tgn:7001242","tgn:7017584","tgn:1000193","tgn:7029392"],"placetype":["aat:300008347"],"id":7025830,"name:xx":"Simonstad"}}
>>>>>>> 03f74aca74312dbeaf24d7e61306dd6a786dc3d0
