{
  "id": 2458565,
  "type": "Feature",
  "properties": {
    "tgn:hierarchy":[
        "tgn:2458565",
        "tgn:1000001",
        "tgn:7012149",
        "tgn:7007157",
        "tgn:2000185",
        "tgn:7029392"
    ],
    "tgn:id":2458565,
    "tgn:name":"Little North Fork Navarro River",
    "tgn:placetype":[
        "aat:300008707"
    ]
},
  "bbox": [],
  "geometry": {"coordinates":[-123.4333,39.1833],"type":"Point"}
}