{
  "id": 2454350,
  "type": "Feature",
  "properties": {
    "tgn:hierarchy":[
        "tgn:2454350",
        "tgn:1000001",
        "tgn:7014352",
        "tgn:7012149",
        "tgn:7007564",
        "tgn:7029392"
    ],
    "tgn:id":2454350,
    "tgn:name":"Little Cub Pond",
    "tgn:placetype":[
        "aat:300008680"
    ]
},
  "bbox": [],
  "geometry": {"coordinates":[-71.1333,42.9167],"type":"Point"}
}