<<<<<<< HEAD
{
  "id": 2259732,
  "type": "Feature",
  "properties": {
    "tgn:hierarchy":[
        "tgn:2259732",
        "tgn:1000001",
        "tgn:7012149",
        "tgn:1002979",
        "tgn:7007920",
        "tgn:7029392"
    ],
    "tgn:id":2259732,
    "tgn:name":"Cougar Creek Reservoir",
    "tgn:placetype":[
        "aat:300006191"
    ]
},
  "bbox": [],
  "geometry": {"coordinates":[-123.35,46.1833],"type":"Point"}
}
=======
{"geometry":{"type":"Point","coordinates":[-123.350000,46.183300]},"type":"Feature","properties":{"hierarchy":["tgn:2259732","tgn:1000001","tgn:7012149","tgn:1002979","tgn:7007920","tgn:7029392"],"placetype":["aat:300006191"],"id":2259732,"name:xx":"Cougar Creek Reservoir"}}
>>>>>>> 03f74aca74312dbeaf24d7e61306dd6a786dc3d0
