{
  "id": 2642058,
  "type": "Feature",
  "properties": {
    "tgn:hierarchy":[
        "tgn:2642058",
        "tgn:1000001",
        "tgn:2000922",
        "tgn:7012149",
        "tgn:7007515",
        "tgn:7029392"
    ],
    "tgn:id":2642058,
    "tgn:name":"Sand Point",
    "tgn:placetype":[
        "aat:300008850"
    ]
},
  "bbox": [],
  "geometry": {"coordinates":[-68.5333,44.35],"type":"Point"}
}