{
  "id": 7422626,
  "type": "Feature",
  "properties": {
    "tgn:hierarchy":[
        "tgn:7422626",
        "tgn:1000001",
        "tgn:7005601",
        "tgn:7005560",
        "tgn:7029392"
    ],
    "tgn:id":7422626,
    "tgn:name":"Monte Longo",
    "tgn:placetype":[
        "aat:300008347"
    ]
},
  "bbox": [],
  "geometry": {"coordinates":[-102.466667,23.416667],"type":"Point"}
}