{
  "id": 2068162,
  "type": "Feature",
  "properties": {
    "tgn:hierarchy":[
        "tgn:2068162",
        "tgn:1002139",
        "tgn:1000001",
        "tgn:7012149",
        "tgn:7007568",
        "tgn:7029392"
    ],
    "tgn:id":2068162,
    "tgn:name":"Bramans Corners",
    "tgn:placetype":[
        "aat:300008347",
        "aat:300387210"
    ]
},
  "bbox": [],
  "geometry": {"coordinates":[-74.0167,42.55],"type":"Point"}
}