{
  "id": 2529179,
  "type": "Feature",
  "properties": {
    "tgn:hierarchy":[
        "tgn:2529179",
        "tgn:1000001",
        "tgn:7012149",
        "tgn:1002758",
        "tgn:7007568",
        "tgn:7029392"
    ],
    "tgn:id":2529179,
    "tgn:name":"Mud Hill",
    "tgn:placetype":[
        "aat:300008798"
    ]
},
  "bbox": [],
  "geometry": {"coordinates":[-75.9167,43.3833],"type":"Point"}
}