{
  "id": 1118280,
  "type": "Feature",
  "properties": {
    "tgn:hierarchy":[
        "tgn:1118280",
        "tgn:1000001",
        "tgn:7012149",
        "tgn:7007564",
        "tgn:7029392"
    ],
    "tgn:id":1118280,
    "tgn:name":"Sunapee Lake",
    "tgn:placetype":[
        "aat:300008680"
    ]
},
  "bbox": [],
  "geometry": {"coordinates":[-72.05,43.3833],"type":"Point"}
}