{
  "id": 1119545,
  "type": "Feature",
  "properties": {
    "tgn:hierarchy":[
        "tgn:1119545",
        "tgn:1000001",
        "tgn:7012149",
        "tgn:7007157",
        "tgn:7029392"
    ],
    "tgn:id":1119545,
    "tgn:name":"Camanche Reservoir",
    "tgn:placetype":[
        "aat:300006191"
    ]
},
  "bbox": [],
  "geometry": {"coordinates":[-121.0167,38.2167],"type":"Point"}
}