{
  "id": 7554200,
  "type": "Feature",
  "properties": {
    "tgn:hierarchy":[
        "tgn:7554200",
        "tgn:1009838",
        "tgn:7000204",
        "tgn:1000004",
        "tgn:7000198",
        "tgn:1009218",
        "tgn:7029392"
    ],
    "tgn:id":7554200,
    "tgn:name:en":"M\u0101y\u0101bandar",
    "tgn:placetype":[
        "aat:300008347"
    ]
},
  "bbox": [],
  "geometry": {"coordinates":[92.933333,12.933333],"type":"Point"}
}