{
  "id": 7192442,
  "type": "Feature",
  "properties": {
    "tgn:hierarchy":[
        "tgn:7192442",
        "tgn:1000003",
        "tgn:7003676",
        "tgn:7000084",
        "tgn:7029392"
    ],
    "tgn:id":7192442,
    "tgn:name":"Flohburg",
    "tgn:placetype":[
        "aat:300008347"
    ]
},
  "bbox": [],
  "geometry": {"coordinates":[8.516667,53.683333],"type":"Point"}
}