<<<<<<< HEAD
{
  "id": 7377400,
  "type": "Feature",
  "properties": {
    "tgn:hierarchy":[
        "tgn:7377400",
        "tgn:7005580",
        "tgn:1000001",
        "tgn:7005560",
        "tgn:7029392"
    ],
    "tgn:id":7377400,
    "tgn:name":"La Piedad",
    "tgn:placetype":[
        "aat:300008347"
    ]
},
  "bbox": [],
  "geometry": {"coordinates":[-92.383333,15.9],"type":"Point"}
}
=======
{"geometry":{"type":"Point","coordinates":[-92.383333,15.900000]},"type":"Feature","properties":{"hierarchy":["tgn:7377400","tgn:7005580","tgn:1000001","tgn:7005560","tgn:7029392"],"placetype":["aat:300008347"],"id":7377400,"name:xx":"La Piedad"}}
>>>>>>> 03f74aca74312dbeaf24d7e61306dd6a786dc3d0
