{
  "id": 2198858,
  "type": "Feature",
  "properties": {
    "tgn:hierarchy":[
        "tgn:2198858",
        "tgn:1000001",
        "tgn:7012149",
        "tgn:7007157",
        "tgn:7029392"
    ],
    "tgn:id":2198858,
    "tgn:name":"Brubaker Canyon",
    "tgn:placetype":[
        "aat:300008761"
    ]
},
  "bbox": [],
  "geometry": {"coordinates":[-119.45,34.75],"type":"Point"}
}