{
  "id": 2199933,
  "type": "Feature",
  "properties": {
    "tgn:hierarchy":[
        "tgn:2199933",
        "tgn:1000001",
        "tgn:7012149",
        "tgn:7007248",
        "tgn:7029392"
    ],
    "tgn:id":2199933,
    "tgn:name":"Brushy Branch",
    "tgn:placetype":[
        "aat:300008699"
    ]
},
  "bbox": [],
  "geometry": {"coordinates":[-83.9333,31.3333],"type":"Point"}
}