{
  "id": 7035813,
  "type": "Feature",
  "properties": {
    "tgn:hierarchy":[
        "tgn:7035813",
        "tgn:7002991",
        "tgn:1000003",
        "tgn:7002997",
        "tgn:1000080",
        "tgn:7029392"
    ],
    "tgn:id":7035813,
    "tgn:name":"Ponte della Lasta",
    "tgn:placetype":[
        "aat:300007836"
    ]
},
  "bbox": [],
  "geometry": {"coordinates":[12.521944,46.541111],"type":"Point"}
}