{
  "id": 2361116,
  "type": "Feature",
  "properties": {
    "tgn:hierarchy":[
        "tgn:2361116",
        "tgn:1000001",
        "tgn:7012149",
        "tgn:2001286",
        "tgn:7007524",
        "tgn:7029392"
    ],
    "tgn:id":2361116,
    "tgn:name":"Grave Creek",
    "tgn:placetype":[
        "aat:300008706"
    ]
},
  "bbox": [],
  "geometry": {"coordinates":[-114.75,48.95],"type":"Point"}
}