{
  "id": 7171004,
  "type": "Feature",
  "properties": {
    "tgn:hierarchy":[
        "tgn:7171004",
        "tgn:1000003",
        "tgn:7003676",
        "tgn:7000084",
        "tgn:7029392"
    ],
    "tgn:id":7171004,
    "tgn:name":"Hengstenberg",
    "tgn:placetype":[
        "aat:300387200"
    ]
},
  "bbox": [],
  "geometry": {"coordinates":[8.416667,52.133333],"type":"Point"}
}