{
  "id": 7531332,
  "type": "Feature",
  "properties": {
    "tgn:hierarchy":[
        "tgn:7531332",
        "tgn:7001242",
        "tgn:7016833",
        "tgn:7001312",
        "tgn:7029392"
    ],
    "tgn:id":7531332,
    "tgn:name:en":"Tur'at al Basy\u016bn\u012b",
    "tgn:placetype":[
        "aat:300006075"
    ]
},
  "bbox": [],
  "geometry": {"coordinates":[30.814722,30.958056],"type":"Point"}
}