{
  "id": 1023390,
  "type": "Feature",
  "properties": {
    "tgn:hierarchy":[
        "tgn:1023390",
        "tgn:1001630",
        "tgn:1000049",
        "tgn:1000002",
        "tgn:7029392"
    ],
    "tgn:id":1023390,
    "tgn:name":"Caldera",
    "tgn:placetype":[
        "aat:300008347"
    ]
},
  "bbox": [],
  "geometry": {"coordinates":[-70.833333,-27.066667],"type":"Point"}
}