{
  "id": 2780790,
  "type": "Feature",
  "properties": {
    "tgn:hierarchy":[
        "tgn:2780790",
        "tgn:1000001",
        "tgn:7006451",
        "tgn:2000093",
        "tgn:7012149",
        "tgn:7029392"
    ],
    "tgn:id":2780790,
    "tgn:name":"Wood Springs Wash",
    "tgn:placetype":[
        "aat:300008699"
    ]
},
  "bbox": [],
  "geometry": {"coordinates":[-110.75,33.55],"type":"Point"}
}