{
  "id": 2589684,
  "type": "Feature",
  "properties": {
    "tgn:hierarchy":[
        "tgn:2589684",
        "tgn:1000001",
        "tgn:7012149",
        "tgn:2000887",
        "tgn:7007256",
        "tgn:7029392"
    ],
    "tgn:id":2589684,
    "tgn:name":"Point Pleasant",
    "tgn:placetype":[
        "aat:300008347"
    ]
},
  "bbox": [],
  "geometry": {"coordinates":[-91.95,32.7667],"type":"Point"}
}