{
  "id": 7228109,
  "type": "Feature",
  "properties": {
    "tgn:hierarchy":[
        "tgn:7228109",
        "tgn:7002750",
        "tgn:7001399",
        "tgn:1000003",
        "tgn:1000074",
        "tgn:7029392"
    ],
    "tgn:id":7228109,
    "tgn:name":"Go\u00faras, Voun\u00e1",
    "tgn:placetype":[
        "aat:300008795"
    ]
},
  "bbox": [],
  "geometry": {"coordinates":[22.566667,39.133333],"type":"Point"}
}