<<<<<<< HEAD
{
  "id": 2406999,
  "type": "Feature",
  "properties": {
    "tgn:hierarchy":[
        "tgn:2406999",
        "tgn:1000001",
        "tgn:2001178",
        "tgn:7012149",
        "tgn:7007523",
        "tgn:7029392"
    ],
    "tgn:id":2406999,
    "tgn:name":"Hunter Mine",
    "tgn:placetype":[
        "aat:300000390"
    ]
},
  "bbox": [],
  "geometry": {"coordinates":[-92.6833,38.1],"type":"Point"}
}
=======
{"geometry":{"type":"Point","coordinates":[-92.683300,38.100000]},"type":"Feature","properties":{"hierarchy":["tgn:2406999","tgn:1000001","tgn:2001178","tgn:7012149","tgn:7007523","tgn:7029392"],"placetype":["aat:300000390"],"id":2406999,"name:xx":"Hunter Mine"}}
>>>>>>> 03f74aca74312dbeaf24d7e61306dd6a786dc3d0
