{
  "id": 7483660,
  "type": "Feature",
  "properties": {
    "tgn:hierarchy":[
        "tgn:7483660",
        "tgn:1000004",
        "tgn:7489179",
        "tgn:1000141",
        "tgn:7029392"
    ],
    "tgn:id":7483660,
    "tgn:name":"Daxi Suidao",
    "tgn:placetype":[
        "aat:300007899"
    ]
},
  "bbox": [],
  "geometry": {"coordinates":[121.899167,24.945],"type":"Point"}
}