<<<<<<< HEAD
{
  "id": 7483660,
  "type": "Feature",
  "properties": {
    "tgn:hierarchy":[
        "tgn:7483660",
        "tgn:1000004",
        "tgn:7489179",
        "tgn:1000141",
        "tgn:7029392"
    ],
    "tgn:id":7483660,
    "tgn:name":"Daxi Suidao",
    "tgn:placetype":[
        "aat:300007899"
    ]
},
  "bbox": [],
  "geometry": {"coordinates":[121.899167,24.945],"type":"Point"}
}
=======
{"geometry":{"type":"Point","coordinates":[121.899167,24.945000]},"type":"Feature","properties":{"hierarchy":["tgn:7483660","tgn:1000004","tgn:7489179","tgn:1000141","tgn:7029392"],"placetype":["aat:300007899"],"id":7483660,"name:xx":"Daxi Suidao"}}
>>>>>>> 03f74aca74312dbeaf24d7e61306dd6a786dc3d0
