<<<<<<< HEAD
{
  "id": 7112292,
  "type": "Feature",
  "properties": {
    "tgn:hierarchy":[
        "tgn:7112292",
        "tgn:1000003",
        "tgn:7003689",
        "tgn:7000084",
        "tgn:7029392"
    ],
    "tgn:id":7112292,
    "tgn:name":"Rohnstedt",
    "tgn:placetype":[
        "aat:300008347"
    ]
},
  "bbox": [],
  "geometry": {"coordinates":[10.833333,51.216667],"type":"Point"}
}
=======
{"geometry":{"type":"Point","coordinates":[10.833333,51.216667]},"type":"Feature","properties":{"hierarchy":["tgn:7112292","tgn:1000003","tgn:7003689","tgn:7000084","tgn:7029392"],"placetype":["aat:300008347"],"id":7112292,"name:xx":"Rohnstedt"}}
>>>>>>> 03f74aca74312dbeaf24d7e61306dd6a786dc3d0
