{
  "id": 2132934,
  "type": "Feature",
  "properties": {
    "tgn:hierarchy":[
        "tgn:2132934",
        "tgn:1000001",
        "tgn:7012149",
        "tgn:1002350",
        "tgn:7007157",
        "tgn:7029392"
    ],
    "tgn:id":2132934,
    "tgn:name":"Anderson Creek",
    "tgn:placetype":[
        "aat:300008706"
    ]
},
  "bbox": [],
  "geometry": {"coordinates":[-121.0667,38.7667],"type":"Point"}
}