{
  "id": 7545250,
  "type": "Feature",
  "properties": {
    "tgn:hierarchy":[
        "tgn:7545250",
        "tgn:1000004",
        "tgn:7000198",
        "tgn:7016788",
        "tgn:7029392"
    ],
    "tgn:id":7545250,
    "tgn:name:en":"Bhelu",
    "tgn:placetype":[
        "aat:300008347"
    ]
},
  "bbox": [],
  "geometry": {"coordinates":[72.942319,27.461535],"type":"Point"}
}