{
  "id": 7019302,
  "type": "Feature",
  "properties": {
    "tgn:hierarchy":[
        "tgn:7019302",
        "tgn:1000001",
        "tgn:7012149",
        "tgn:2000232",
        "tgn:7007158",
        "tgn:7029392"
    ],
    "tgn:id":7019302,
    "tgn:name":"Chokecherry Draw",
    "tgn:placetype":[
        "aat:300008761"
    ]
},
  "bbox": [],
  "geometry": {"coordinates":[-109.0167,40.7667],"type":"Point"}
}