{
  "id": 1136646,
  "type": "Feature",
  "properties": {
    "tgn:hierarchy":[
        "tgn:1136646",
        "tgn:7003457",
        "tgn:1000003",
        "tgn:1000063",
        "tgn:7018236",
        "tgn:7029392"
    ],
    "tgn:id":1136646,
    "tgn:name":"Moerbeke",
    "tgn:placetype":[
        "aat:300008347"
    ]
},
  "bbox": [],
  "geometry": {"coordinates":[3.930006,51.174094],"type":"Point"}
}