{
  "id": 7017982,
  "type": "Feature",
  "properties": {
    "tgn:hierarchy":[
        "tgn:7017982",
        "tgn:1000004",
        "tgn:7011531",
        "tgn:7018214",
        "tgn:7002435",
        "tgn:7029392"
    ],
    "tgn:id":7017982,
    "tgn:name":"Anapa",
    "tgn:placetype":[
        "aat:300008347"
    ]
},
  "bbox": [],
  "geometry": {"coordinates":[37.3167,44.8833],"type":"Point"}
}