{
  "id": 7202101,
  "type": "Feature",
  "properties": {
    "tgn:hierarchy":[
        "tgn:7202101",
        "tgn:1000003",
        "tgn:7003676",
        "tgn:7000084",
        "tgn:7029392"
    ],
    "tgn:id":7202101,
    "tgn:name":"Bramscher Berg",
    "tgn:placetype":[
        "aat:300008777"
    ]
},
  "bbox": [],
  "geometry": {"coordinates":[7.966667,52.416667],"type":"Point"}
}