{
  "id": 2348106,
  "type": "Feature",
  "properties": {
    "tgn:hierarchy":[
        "tgn:2348106",
        "tgn:1000001",
        "tgn:7006451",
        "tgn:2000092",
        "tgn:7012149",
        "tgn:7029392"
    ],
    "tgn:id":2348106,
    "tgn:name":"Geronimo Number Two Tank",
    "tgn:placetype":[
        "aat:300006191"
    ]
},
  "bbox": [],
  "geometry": {"coordinates":[-111.6667,34.9333],"type":"Point"}
}