{
  "id": 2658152,
  "type": "Feature",
  "properties": {
    "tgn:hierarchy":[
        "tgn:2658152",
        "tgn:1000001",
        "tgn:2002368",
        "tgn:7012149",
        "tgn:7007923",
        "tgn:7029392"
    ],
    "tgn:id":2658152,
    "tgn:name":"Shelton Allen Ditch",
    "tgn:placetype":[
        "aat:300006075"
    ]
},
  "bbox": [],
  "geometry": {"coordinates":[-106.65,41.5833],"type":"Point"}
}