{
  "id": 2484235,
  "type": "Feature",
  "properties": {
    "tgn:hierarchy":[
        "tgn:2484235",
        "tgn:1000001",
        "tgn:2000772",
        "tgn:7012149",
        "tgn:7007255",
        "tgn:7029392"
    ],
    "tgn:id":2484235,
    "tgn:name":"Laurel Branch",
    "tgn:placetype":[
        "aat:300008699"
    ]
},
  "bbox": [],
  "geometry": {"coordinates":[-83.1667,37.5167],"type":"Point"}
}