{
  "id": 7498177,
  "type": "Feature",
  "properties": {
    "tgn:hierarchy":[
        "tgn:7498177",
        "tgn:1000004",
        "tgn:1000454",
        "tgn:1000141",
        "tgn:7029392"
    ],
    "tgn:id":7498177,
    "tgn:name":"Yuanyuan Qiao",
    "tgn:placetype":[
        "aat:300007836"
    ]
},
  "bbox": [],
  "geometry": {"coordinates":[121.74637,25.100927],"type":"Point"}
}