<<<<<<< HEAD
{
  "id": 2252266,
  "type": "Feature",
  "properties": {
    "tgn:hierarchy":[
        "tgn:2252266",
        "tgn:1000001",
        "tgn:7012149",
        "tgn:7007568",
        "tgn:7029392"
    ],
    "tgn:id":2252266,
    "tgn:name":"Coney Island Channel",
    "tgn:placetype":[
        "aat:300008699"
    ]
},
  "bbox": [],
  "geometry": {"coordinates":[-74.0,40.5833],"type":"Point"}
}
=======
{"geometry":{"type":"Point","coordinates":[-74.000000,40.583300]},"type":"Feature","properties":{"hierarchy":["tgn:2252266","tgn:1000001","tgn:7012149","tgn:7007568","tgn:7029392"],"placetype":["aat:300008699"],"id":2252266,"name:xx":"Coney Island Channel"}}
>>>>>>> 03f74aca74312dbeaf24d7e61306dd6a786dc3d0
