<<<<<<< HEAD
{
  "id": 2330346,
  "type": "Feature",
  "properties": {
    "tgn:hierarchy":[
        "tgn:2330346",
        "tgn:1000001",
        "tgn:7012149",
        "tgn:2000352",
        "tgn:7007248",
        "tgn:7029392"
    ],
    "tgn:id":2330346,
    "tgn:name":"Flat Branch",
    "tgn:placetype":[
        "aat:300008347"
    ]
},
  "bbox": [],
  "geometry": {"coordinates":[-84.4833,34.7667],"type":"Point"}
}
=======
{"geometry":{"type":"Point","coordinates":[-84.483300,34.766700]},"type":"Feature","properties":{"hierarchy":["tgn:2330346","tgn:1000001","tgn:7012149","tgn:2000352","tgn:7007248","tgn:7029392"],"placetype":["aat:300008347"],"id":2330346,"name:xx":"Flat Branch"}}
>>>>>>> 03f74aca74312dbeaf24d7e61306dd6a786dc3d0
