{
  "id": 2438204,
  "type": "Feature",
  "properties": {
    "tgn:hierarchy":[
        "tgn:2438204",
        "tgn:1000001",
        "tgn:7012149",
        "tgn:2000707",
        "tgn:7007254",
        "tgn:7029392"
    ],
    "tgn:id":2438204,
    "tgn:name":"Kingman County State Lake",
    "tgn:placetype":[
        "aat:300006191"
    ]
},
  "bbox": [],
  "geometry": {"coordinates":[-98.25,37.6333],"type":"Point"}
}