{
  "id": 2145676,
  "type": "Feature",
  "properties": {
    "tgn:hierarchy":[
        "tgn:2145676",
        "tgn:1000001",
        "tgn:7006451",
        "tgn:2000092",
        "tgn:7012149",
        "tgn:7029392"
    ],
    "tgn:id":2145676,
    "tgn:name":"Baldy Basin",
    "tgn:placetype":[
        "aat:300386845"
    ]
},
  "bbox": [],
  "geometry": {"coordinates":[-112.5333,35.9333],"type":"Point"}
}