{
  "id": 2499935,
  "type": "Feature",
  "properties": {
    "tgn:hierarchy":[
        "tgn:2499935",
        "tgn:1000001",
        "tgn:7012149",
        "tgn:7007157",
        "tgn:2000185",
        "tgn:7029392"
    ],
    "tgn:id":2499935,
    "tgn:name":"McCoy Ridge",
    "tgn:placetype":[
        "aat:300266640"
    ]
},
  "bbox": [],
  "geometry": {"coordinates":[-122.95,39.6667],"type":"Point"}
}