{
  "id": 2339623,
  "type": "Feature",
  "properties": {
    "tgn:hierarchy":[
        "tgn:2339623",
        "tgn:1000001",
        "tgn:7016172",
        "tgn:7012149",
        "tgn:2000173",
        "tgn:7029392"
    ],
    "tgn:id":2339623,
    "tgn:name":"Fredonia Hill",
    "tgn:placetype":[
        "aat:300008798"
    ]
},
  "bbox": [],
  "geometry": {"coordinates":[-92.15,35.8167],"type":"Point"}
}