{
  "id": 7225665,
  "type": "Feature",
  "properties": {
    "tgn:hierarchy":[
        "tgn:7225665",
        "tgn:7002750",
        "tgn:7001399",
        "tgn:1000003",
        "tgn:1000074",
        "tgn:7029392"
    ],
    "tgn:id":7225665,
    "tgn:name":"N\u00e9ai Karia\u00ed",
    "tgn:placetype":[
        "aat:300008347"
    ]
},
  "bbox": [],
  "geometry": {"coordinates":[22.466667,39.516667],"type":"Point"}
}