{
  "id": 2648955,
  "type": "Feature",
  "properties": {
    "tgn:hierarchy":[
        "tgn:2648955",
        "tgn:7002659",
        "tgn:1000001",
        "tgn:7012149",
        "tgn:2000044",
        "tgn:7029392"
    ],
    "tgn:id":2648955,
    "tgn:name":"Scott Cave",
    "tgn:placetype":[
        "aat:300008746"
    ]
},
  "bbox": [],
  "geometry": {"coordinates":[-86.3667,34.8167],"type":"Point"}
}