{
  "id": 2580786,
  "type": "Feature",
  "properties": {
    "tgn:hierarchy":[
        "tgn:2580786",
        "tgn:1002172",
        "tgn:1000001",
        "tgn:7012149",
        "tgn:7007710",
        "tgn:7029392"
    ],
    "tgn:id":2580786,
    "tgn:name":"Pigeonroost Run",
    "tgn:placetype":[
        "aat:300008699"
    ]
},
  "bbox": [],
  "geometry": {"coordinates":[-78.5667,39.85],"type":"Point"}
}