{
  "id": 7538239,
  "type": "Feature",
  "properties": {
    "tgn:hierarchy":[
        "tgn:7538239",
        "tgn:7001242",
        "tgn:7001105",
        "tgn:7016833",
        "tgn:7029392"
    ],
    "tgn:id":7538239,
    "tgn:name:en":"Rayy\u0101n al Qibl\u012byah, 'Ayn ar",
    "tgn:placetype":[
        "aat:300008697"
    ]
},
  "bbox": [],
  "geometry": {"coordinates":[30.303907,29.050464],"type":"Point"}
}