{
  "id": 2183708,
  "type": "Feature",
  "properties": {
    "tgn:hierarchy":[
        "tgn:2183708",
        "tgn:1000001",
        "tgn:7012149",
        "tgn:2001708",
        "tgn:7007708",
        "tgn:7029392"
    ],
    "tgn:id":2183708,
    "tgn:name":"Boag Creek",
    "tgn:placetype":[
        "aat:300008706"
    ]
},
  "bbox": [],
  "geometry": {"coordinates":[-119.3333,44.6333],"type":"Point"}
}