{
  "id": 7229493,
  "type": "Feature",
  "properties": {
    "tgn:hierarchy":[
        "tgn:7229493",
        "tgn:7002748",
        "tgn:7001399",
        "tgn:1000003",
        "tgn:1000074",
        "tgn:7029392"
    ],
    "tgn:id":7229493,
    "tgn:name":"Kar\u00e1vas, Ner\u00f3",
    "tgn:placetype":[
        "aat:300008699"
    ]
},
  "bbox": [],
  "geometry": {"coordinates":[21.64,39.403056],"type":"Point"}
}