{
  "id": 2235093,
  "type": "Feature",
  "properties": {
    "tgn:hierarchy":[
        "tgn:2235093",
        "tgn:1000001",
        "tgn:7012149",
        "tgn:7013961",
        "tgn:7029392"
    ],
    "tgn:id":2235093,
    "tgn:name":"Cherry Pond Mountain",
    "tgn:placetype":[
        "aat:300008798"
    ]
},
  "bbox": [],
  "geometry": {"coordinates":[-81.55,37.8333],"type":"Point"}
}