{
  "id": 2160172,
  "type": "Feature",
  "properties": {
    "tgn:hierarchy":[
        "tgn:2160172",
        "tgn:1000001",
        "tgn:7012149",
        "tgn:2002180",
        "tgn:7007919",
        "tgn:7029392"
    ],
    "tgn:id":2160172,
    "tgn:name":"Beechtree Creek",
    "tgn:placetype":[
        "aat:300008706"
    ]
},
  "bbox": [],
  "geometry": {"coordinates":[-79.25,37.0167],"type":"Point"}
}