{
  "id": 7428325,
  "type": "Feature",
  "properties": {
    "tgn:hierarchy":[
        "tgn:7428325",
        "tgn:1000001",
        "tgn:7005594",
        "tgn:7005560",
        "tgn:7029392"
    ],
    "tgn:id":7428325,
    "tgn:name":"Las Gavias",
    "tgn:placetype":[
        "aat:300008347"
    ]
},
  "bbox": [],
  "geometry": {"coordinates":[-99.516667,22.216667],"type":"Point"}
}