{
  "id": 7201512,
  "type": "Feature",
  "properties": {
    "tgn:hierarchy":[
        "tgn:7201512",
        "tgn:1000003",
        "tgn:7003677",
        "tgn:7000084",
        "tgn:7029392"
    ],
    "tgn:id":7201512,
    "tgn:name":"Borke",
    "tgn:placetype":[
        "aat:300008699"
    ]
},
  "bbox": [],
  "geometry": {"coordinates":[7.866667,51.333333],"type":"Point"}
}