{
  "id": 2442635,
  "type": "Feature",
  "properties": {
    "tgn:hierarchy":[
        "tgn:2442635",
        "tgn:1000001",
        "tgn:7012149",
        "tgn:1002578",
        "tgn:7007826",
        "tgn:7029392"
    ],
    "tgn:id":2442635,
    "tgn:name":"Kuehns Creek",
    "tgn:placetype":[
        "aat:300008706"
    ]
},
  "bbox": [],
  "geometry": {"coordinates":[-97.1833,29.5333],"type":"Point"}
}