{
  "id": 7277281,
  "type": "Feature",
  "properties": {
    "tgn:hierarchy":[
        "tgn:7277281",
        "tgn:7002464",
        "tgn:1000049",
        "tgn:1000002",
        "tgn:7029392"
    ],
    "tgn:id":7277281,
    "tgn:name":"Calapampa, Pampa",
    "tgn:placetype":[
        "aat:300008805"
    ]
},
  "bbox": [],
  "geometry": {"coordinates":[-69.593611,-17.902222],"type":"Point"}
}