{
  "id": 7080077,
  "type": "Feature",
  "properties": {
    "tgn:hierarchy":[
        "tgn:7080077",
        "tgn:1000003",
        "tgn:7003676",
        "tgn:7000084",
        "tgn:7029392"
    ],
    "tgn:id":7080077,
    "tgn:name":"Wrisser Hammrich",
    "tgn:placetype":[
        "aat:300000206"
    ]
},
  "bbox": [],
  "geometry": {"coordinates":[7.633333,53.45],"type":"Point"}
}