{
  "id": 2359082,
  "type": "Feature",
  "properties": {
    "tgn:hierarchy":[
        "tgn:2359082",
        "tgn:1000001",
        "tgn:7012149",
        "tgn:2001456",
        "tgn:7007566",
        "tgn:7029392"
    ],
    "tgn:id":2359082,
    "tgn:name":"Granite Mountain",
    "tgn:placetype":[
        "aat:300008798"
    ]
},
  "bbox": [],
  "geometry": {"coordinates":[-107.2167,34.1333],"type":"Point"}
}