{
  "id": 7018060,
  "type": "Feature",
  "properties": {
    "tgn:hierarchy":[
        "tgn:7018060",
        "tgn:1000004",
        "tgn:7002076",
        "tgn:1000111",
        "tgn:7029392"
    ],
    "tgn:id":7018060,
    "tgn:name":"Taozhu",
    "tgn:placetype":[
        "aat:300008347"
    ]
},
  "bbox": [],
  "geometry": {"coordinates":[121.5333,28.8333],"type":"Point"}
}