{
  "id": 7310457,
  "type": "Feature",
  "properties": {
    "tgn:hierarchy":[
        "tgn:7310457",
        "tgn:1001692",
        "tgn:1000049",
        "tgn:1000002",
        "tgn:7029392"
    ],
    "tgn:id":7310457,
    "tgn:name":"Motrenco, Alto",
    "tgn:placetype":[
        "aat:300008777"
    ]
},
  "bbox": [],
  "geometry": {"coordinates":[-72.85,-38.016667],"type":"Point"}
}