{
  "id": 2775411,
  "type": "Feature",
  "properties": {
    "tgn:hierarchy":[
        "tgn:2775411",
        "tgn:1000001",
        "tgn:2001705",
        "tgn:7012149",
        "tgn:7007708",
        "tgn:7029392"
    ],
    "tgn:id":2775411,
    "tgn:name":"Wilson Cave",
    "tgn:placetype":[
        "aat:300008746"
    ]
},
  "bbox": [],
  "geometry": {"coordinates":[-121.2167,44.0833],"type":"Point"}
}