{
  "id": 1011180,
  "type": "Feature",
  "properties": {
    "tgn:hierarchy":[
        "tgn:1011180",
        "tgn:1001861",
        "tgn:1000002",
        "tgn:1000059",
        "tgn:7029392"
    ],
    "tgn:id":1011180,
    "tgn:name":"San Rom\u00e1n, Cabo",
    "tgn:placetype":[
        "aat:300008850"
    ]
},
  "bbox": [],
  "geometry": {"coordinates":[-70.0167,12.1667],"type":"Point"}
}