{
  "id": 2146116,
  "type": "Feature",
  "properties": {
    "tgn:hierarchy":[
        "tgn:2146116",
        "tgn:1000001",
        "tgn:7012149",
        "tgn:2002046",
        "tgn:7007826",
        "tgn:7029392"
    ],
    "tgn:id":2146116,
    "tgn:name":"Ballard Creek",
    "tgn:placetype":[
        "aat:300008706"
    ]
},
  "bbox": [],
  "geometry": {"coordinates":[-100.8333,33.9833],"type":"Point"}
}