{
  "id": 7415273,
  "type": "Feature",
  "properties": {
    "tgn:hierarchy":[
        "tgn:7415273",
        "tgn:1000001",
        "tgn:7005591",
        "tgn:7005560",
        "tgn:7029392"
    ],
    "tgn:id":7415273,
    "tgn:name:es":"Morro Ayutla, Ensenada",
    "tgn:placetype":[
        "aat:300132317"
    ]
},
  "bbox": [],
  "geometry": {"coordinates":[-95.764167,15.8975],"type":"Point"}
}