{
  "id": 2714331,
  "type": "Feature",
  "properties": {
    "tgn:hierarchy":[
        "tgn:2714331",
        "tgn:1000001",
        "tgn:7020680",
        "tgn:7012149",
        "tgn:7007256",
        "tgn:7029392"
    ],
    "tgn:id":2714331,
    "tgn:name":"Teloque Lake",
    "tgn:placetype":[
        "aat:300008680"
    ]
},
  "bbox": [],
  "geometry": {"coordinates":[-93.4167,31.9333],"type":"Point"}
}