{
  "id": 7329329,
  "type": "Feature",
  "properties": {
    "tgn:hierarchy":[
        "tgn:7329329",
        "tgn:7002822",
        "tgn:1001647",
        "tgn:1000003",
        "tgn:1000095",
        "tgn:7029392"
    ],
    "tgn:id":7329329,
    "tgn:name":"Pinilla de Molina",
    "tgn:placetype":[
        "aat:300008347"
    ]
},
  "bbox": [],
  "geometry": {"coordinates":[-1.883333,40.683333],"type":"Point"}
}