{
  "id": 2170373,
  "type": "Feature",
  "properties": {
    "tgn:hierarchy":[
        "tgn:2170373",
        "tgn:7006450",
        "tgn:1000001",
        "tgn:2124012",
        "tgn:7012149",
        "tgn:7029392"
    ],
    "tgn:id":2170373,
    "tgn:name":"Big Rock",
    "tgn:placetype":[
        "aat:300132348"
    ]
},
  "bbox": [],
  "geometry": {"coordinates":[-152.65,58.0167],"type":"Point"}
}