{
  "id": 7468997,
  "type": "Feature",
  "properties": {
    "tgn:hierarchy":[
        "tgn:7468997",
        "tgn:1000004",
        "tgn:7491221",
        "tgn:1000141",
        "tgn:7029392"
    ],
    "tgn:id":7468997,
    "tgn:name":"Xinxianglan",
    "tgn:placetype":[
        "aat:300008347"
    ]
},
  "bbox": [],
  "geometry": {"coordinates":[120.989167,22.575833],"type":"Point"}
}