{
  "id": 7575336,
  "type": "Feature",
  "properties": {
    "tgn:hierarchy":[
        "tgn:7575336",
        "tgn:1000004",
        "tgn:7000198",
        "tgn:7001797",
        "tgn:7029392"
    ],
    "tgn:id":7575336,
    "tgn:name:en":"Kokkul\u0101ncheri",
    "tgn:placetype":[
        "aat:300007783"
    ]
},
  "bbox": [],
  "geometry": {"coordinates":[77.966667,9.65],"type":"Point"}
}