{
  "id": 2487436,
  "type": "Feature",
  "properties": {
    "tgn:hierarchy":[
        "tgn:2487436",
        "tgn:1000001",
        "tgn:7012149",
        "tgn:2000821",
        "tgn:7007255",
        "tgn:7029392"
    ],
    "tgn:id":2487436,
    "tgn:name":"Left Fork Beetree Branch",
    "tgn:placetype":[
        "aat:300008699"
    ]
},
  "bbox": [],
  "geometry": {"coordinates":[-82.9333,37.55],"type":"Point"}
}