{
  "id": 2018932,
  "type": "Feature",
  "properties": {
    "tgn:hierarchy":[
        "tgn:2018932",
        "tgn:1000001",
        "tgn:7012149",
        "tgn:1002768",
        "tgn:7007240",
        "tgn:7029392"
    ],
    "tgn:id":2018932,
    "tgn:name":"Cloud Lake",
    "tgn:placetype":[
        "aat:300008347"
    ]
},
  "bbox": [],
  "geometry": {"coordinates":[-80.0667,26.6667],"type":"Point"}
}