<<<<<<< HEAD
{
  "id": 7370405,
  "type": "Feature",
  "properties": {
    "tgn:hierarchy":[
        "tgn:7370405",
        "tgn:7005585",
        "tgn:1000001",
        "tgn:7005560",
        "tgn:7029392"
    ],
    "tgn:id":7370405,
    "tgn:name":"Huerta Vieja",
    "tgn:placetype":[
        "aat:300008347"
    ]
},
  "bbox": [],
  "geometry": {"coordinates":[-100.516667,17.916667],"type":"Point"}
}
=======
{"geometry":{"type":"Point","coordinates":[-100.516667,17.916667]},"type":"Feature","properties":{"hierarchy":["tgn:7370405","tgn:7005585","tgn:1000001","tgn:7005560","tgn:7029392"],"placetype":["aat:300008347"],"id":7370405,"name:xx":"Huerta Vieja"}}
>>>>>>> 03f74aca74312dbeaf24d7e61306dd6a786dc3d0
