{
  "id": 2116264,
  "type": "Feature",
  "properties": {
    "tgn:hierarchy":[
        "tgn:2116264",
        "tgn:1000001",
        "tgn:7012149",
        "tgn:1002942",
        "tgn:7007920",
        "tgn:7029392"
    ],
    "tgn:id":2116264,
    "tgn:name":"Maytown",
    "tgn:placetype":[
        "aat:300008347",
        "aat:300387210"
    ]
},
  "bbox": [],
  "geometry": {"coordinates":[-122.9333,46.8833],"type":"Point"}
}