{
  "id": 2157678,
  "type": "Feature",
  "properties": {
    "tgn:hierarchy":[
        "tgn:2157678",
        "tgn:1000001",
        "tgn:1002337",
        "tgn:7012149",
        "tgn:7007922",
        "tgn:7029392"
    ],
    "tgn:id":2157678,
    "tgn:name":"Beaver Dam Lake",
    "tgn:placetype":[
        "aat:300006191"
    ]
},
  "bbox": [],
  "geometry": {"coordinates":[-88.8333,43.45],"type":"Point"}
}