<<<<<<< HEAD
{
  "id": 2157678,
  "type": "Feature",
  "properties": {
    "tgn:hierarchy":[
        "tgn:2157678",
        "tgn:1000001",
        "tgn:1002337",
        "tgn:7012149",
        "tgn:7007922",
        "tgn:7029392"
    ],
    "tgn:id":2157678,
    "tgn:name":"Beaver Dam Lake",
    "tgn:placetype":[
        "aat:300006191"
    ]
},
  "bbox": [],
  "geometry": {"coordinates":[-88.8333,43.45],"type":"Point"}
}
=======
{"geometry":{"type":"Point","coordinates":[-88.833300,43.450000]},"type":"Feature","properties":{"hierarchy":["tgn:2157678","tgn:1000001","tgn:1002337","tgn:7012149","tgn:7007922","tgn:7029392"],"placetype":["aat:300006191"],"id":2157678,"name:xx":"Beaver Dam Lake"}}
>>>>>>> 03f74aca74312dbeaf24d7e61306dd6a786dc3d0
