{
  "id": 1107099,
  "type": "Feature",
  "properties": {
    "tgn:hierarchy":[
        "tgn:1107099",
        "tgn:1000004",
        "tgn:1001481",
        "tgn:1000135",
        "tgn:7029392"
    ],
    "tgn:id":1107099,
    "tgn:name":"Anepahan Peak",
    "tgn:placetype":[
        "aat:300008798"
    ]
},
  "bbox": [],
  "geometry": {"coordinates":[118.4167,9.6667],"type":"Point"}
}