{
  "id": 2310913,
  "type": "Feature",
  "properties": {
    "tgn:hierarchy":[
        "tgn:2310913",
        "tgn:1000001",
        "tgn:7012149",
        "tgn:2001304",
        "tgn:7007524",
        "tgn:7029392"
    ],
    "tgn:id":2310913,
    "tgn:name":"Eddy Creek",
    "tgn:placetype":[
        "aat:300008706"
    ]
},
  "bbox": [],
  "geometry": {"coordinates":[-115.15,47.4667],"type":"Point"}
}