{
  "id": 2692749,
  "type": "Feature",
  "properties": {
    "tgn:hierarchy":[
        "tgn:2692749",
        "tgn:1000001",
        "tgn:7012149",
        "tgn:2000238",
        "tgn:7007158",
        "tgn:7029392"
    ],
    "tgn:id":2692749,
    "tgn:name":"Steel Gulch",
    "tgn:placetype":[
        "aat:300008761"
    ]
},
  "bbox": [],
  "geometry": {"coordinates":[-105.6667,39.1167],"type":"Point"}
}