<<<<<<< HEAD
{
  "id": 7055730,
  "type": "Feature",
  "properties": {
    "tgn:hierarchy":[
        "tgn:7055730",
        "tgn:7003135",
        "tgn:1000003",
        "tgn:7003080",
        "tgn:1000080",
        "tgn:7029392"
    ],
    "tgn:id":7055730,
    "tgn:name":"Leucio, Monte",
    "tgn:placetype":[
        "aat:300008795"
    ]
},
  "bbox": [],
  "geometry": {"coordinates":[13.6,41.466667],"type":"Point"}
}
=======
{"geometry":{"type":"Point","coordinates":[13.600000,41.466667]},"type":"Feature","properties":{"hierarchy":["tgn:7055730","tgn:7003135","tgn:1000003","tgn:7003080","tgn:1000080","tgn:7029392"],"placetype":["aat:300008795"],"id":7055730,"name:xx":"Leucio, Monte"}}
>>>>>>> 03f74aca74312dbeaf24d7e61306dd6a786dc3d0
