{
  "id": 2745859,
  "type": "Feature",
  "properties": {
    "tgn:hierarchy":[
        "tgn:2745859",
        "tgn:1000001",
        "tgn:7012149",
        "tgn:2002382",
        "tgn:7007923",
        "tgn:7029392"
    ],
    "tgn:id":2745859,
    "tgn:name":"Vital Reservoir",
    "tgn:placetype":[
        "aat:300006191"
    ]
},
  "bbox": [],
  "geometry": {"coordinates":[-109.95,42.4333],"type":"Point"}
}