{
  "id": 2508321,
  "type": "Feature",
  "properties": {
    "tgn:hierarchy":[
        "tgn:2508321",
        "tgn:1000001",
        "tgn:7012149",
        "tgn:7007157",
        "tgn:1002608",
        "tgn:1008999",
        "tgn:7029392"
    ],
    "tgn:id":2508321,
    "tgn:name":"Middle Canyon",
    "tgn:placetype":[
        "aat:300008761"
    ]
},
  "bbox": [],
  "geometry": {"coordinates":[-118.3667,33.3667],"type":"Point"}
}