{
  "id": 7475660,
  "type": "Feature",
  "properties": {
    "tgn:hierarchy":[
        "tgn:7475660",
        "tgn:7488858",
        "tgn:1000004",
        "tgn:1000141",
        "tgn:7029392"
    ],
    "tgn:id":7475660,
    "tgn:name":"Neibu",
    "tgn:placetype":[
        "aat:300008347"
    ]
},
  "bbox": [],
  "geometry": {"coordinates":[121.000814,23.985391],"type":"Point"}
}