{
  "id": 1081638,
  "type": "Feature",
  "properties": {
    "tgn:hierarchy":[
        "tgn:1081638",
        "tgn:1000975",
        "tgn:1000004",
        "tgn:7000901",
        "tgn:1000120",
        "tgn:7029392"
    ],
    "tgn:id":1081638,
    "tgn:name":"Tsuyazaki",
    "tgn:placetype":[
        "aat:300008347"
    ]
},
  "bbox": [],
  "geometry": {"coordinates":[130.45,33.8167],"type":"Point"}
}