{
  "id": 2710573,
  "type": "Feature",
  "properties": {
    "tgn:hierarchy":[
        "tgn:2710573",
        "tgn:1000001",
        "tgn:7012149",
        "tgn:7007157",
        "tgn:2000188",
        "tgn:7029392"
    ],
    "tgn:id":2710573,
    "tgn:name":"Tamarack Swale",
    "tgn:placetype":[
        "aat:300008761"
    ]
},
  "bbox": [],
  "geometry": {"coordinates":[-121.5167,40.7167],"type":"Point"}
}