<<<<<<< HEAD
{
  "id": 7360428,
  "type": "Feature",
  "properties": {
    "tgn:hierarchy":[
        "tgn:7360428",
        "tgn:7005583",
        "tgn:1000001",
        "tgn:7005560",
        "tgn:7029392"
    ],
    "tgn:id":7360428,
    "tgn:name":"Cocina",
    "tgn:placetype":[
        "aat:300007783"
    ]
},
  "bbox": [],
  "geometry": {"coordinates":[-106.033333,26.8],"type":"Point"}
}
=======
{"geometry":{"type":"Point","coordinates":[-106.033333,26.800000]},"type":"Feature","properties":{"hierarchy":["tgn:7360428","tgn:7005583","tgn:1000001","tgn:7005560","tgn:7029392"],"placetype":["aat:300007783"],"id":7360428,"name:xx":"Cocina"}}
>>>>>>> 03f74aca74312dbeaf24d7e61306dd6a786dc3d0
