{
  "id": 2279728,
  "type": "Feature",
  "properties": {
    "tgn:hierarchy":[
        "tgn:2279728",
        "tgn:1000001",
        "tgn:1002218",
        "tgn:7012149",
        "tgn:7007157",
        "tgn:7029392"
    ],
    "tgn:id":2279728,
    "tgn:name":"Deadwood",
    "tgn:placetype":[
        "aat:300008347"
    ]
},
  "bbox": [],
  "geometry": {"coordinates":[-121.5167,39.7333],"type":"Point"}
}