<<<<<<< HEAD
{
  "id": 2407550,
  "type": "Feature",
  "properties": {
    "tgn:hierarchy":[
        "tgn:2407550",
        "tgn:1000001",
        "tgn:7012149",
        "tgn:1002612",
        "tgn:7007710",
        "tgn:7029392"
    ],
    "tgn:id":2407550,
    "tgn:name":"Huntsville Creek",
    "tgn:placetype":[
        "aat:300008706"
    ]
},
  "bbox": [],
  "geometry": {"coordinates":[-75.9667,41.3],"type":"Point"}
}
=======
{"geometry":{"type":"Point","coordinates":[-75.966700,41.300000]},"type":"Feature","properties":{"hierarchy":["tgn:2407550","tgn:1000001","tgn:7012149","tgn:1002612","tgn:7007710","tgn:7029392"],"placetype":["aat:300008706"],"id":2407550,"name:xx":"Huntsville Creek"}}
>>>>>>> 03f74aca74312dbeaf24d7e61306dd6a786dc3d0
