{
  "id": 2586150,
  "type": "Feature",
  "properties": {
    "tgn:hierarchy":[
        "tgn:2586150",
        "tgn:1000001",
        "tgn:2002259",
        "tgn:7012149",
        "tgn:7013961",
        "tgn:7029392"
    ],
    "tgn:id":2586150,
    "tgn:name":"Pisgah, Mount",
    "tgn:placetype":[
        "aat:300008798"
    ]
},
  "bbox": [],
  "geometry": {"coordinates":[-81.0667,38.4333],"type":"Point"}
}