{
  "id": 2075553,
  "type": "Feature",
  "properties": {
    "tgn:hierarchy":[
        "tgn:2075553",
        "tgn:1000001",
        "tgn:7012149",
        "tgn:2001493",
        "tgn:7007709",
        "tgn:7029392"
    ],
    "tgn:id":2075553,
    "tgn:name":"Macclesfield",
    "tgn:placetype":[
        "aat:300008347"
    ]
},
  "bbox": [],
  "geometry": {"coordinates":[-77.6667,35.75],"type":"Point"}
}