{
  "id": 1080389,
  "type": "Feature",
  "properties": {
    "tgn:hierarchy":[
        "tgn:1080389",
        "tgn:1000004",
        "tgn:7000894",
        "tgn:7016797",
        "tgn:1000120",
        "tgn:7029392"
    ],
    "tgn:id":1080389,
    "tgn:name":"Kamikawa",
    "tgn:placetype":[
        "aat:300008347"
    ]
},
  "bbox": [],
  "geometry": {"coordinates":[139.1167,36.2167],"type":"Point"}
}