{
  "id": 2181287,
  "type": "Feature",
  "properties": {
    "tgn:hierarchy":[
        "tgn:2181287",
        "tgn:1000001",
        "tgn:7012149",
        "tgn:7007251",
        "tgn:7029392"
    ],
    "tgn:id":2181287,
    "tgn:name":"Blue Creek",
    "tgn:placetype":[
        "aat:300008706"
    ]
},
  "bbox": [],
  "geometry": {"coordinates":[-89.4333,40.7667],"type":"Point"}
}