{
  "id": 7525690,
  "type": "Feature",
  "properties": {
    "tgn:hierarchy":[
        "tgn:7525690",
        "tgn:7001242",
        "tgn:7016833",
        "tgn:1001091",
        "tgn:7029392"
    ],
    "tgn:id":7525690,
    "tgn:name:en":"Bandayrah, W\u0101d\u012b al",
    "tgn:placetype":[
        "aat:300379998"
    ]
},
  "bbox": [],
  "geometry": {"coordinates":[31.424836,30.133941],"type":"Point"}
}