{
  "id": 2689703,
  "type": "Feature",
  "properties": {
    "tgn:hierarchy":[
        "tgn:2689703",
        "tgn:1000001",
        "tgn:7006451",
        "tgn:7012149",
        "tgn:2000099",
        "tgn:7029392"
    ],
    "tgn:id":2689703,
    "tgn:name":"Squaw Tank",
    "tgn:placetype":[
        "aat:300006191"
    ]
},
  "bbox": [],
  "geometry": {"coordinates":[-110.5833,34.5833],"type":"Point"}
}