{
  "id": 2088898,
  "type": "Feature",
  "properties": {
    "tgn:hierarchy":[
        "tgn:2088898",
        "tgn:1000001",
        "tgn:7012149",
        "tgn:2001724",
        "tgn:7007710",
        "tgn:7029392"
    ],
    "tgn:id":2088898,
    "tgn:name":"Graysville",
    "tgn:placetype":[
        "aat:300008347"
    ]
},
  "bbox": [],
  "geometry": {"coordinates":[-80.3833,39.9167],"type":"Point"}
}