{
  "id": 2322786,
  "type": "Feature",
  "properties": {
    "tgn:hierarchy":[
        "tgn:2322786",
        "tgn:1000001",
        "tgn:7012149",
        "tgn:7007157",
        "tgn:1002857",
        "tgn:7029392"
    ],
    "tgn:id":2322786,
    "tgn:name":"Fan Canyon",
    "tgn:placetype":[
        "aat:300008761"
    ]
},
  "bbox": [],
  "geometry": {"coordinates":[-117.5667,34.1833],"type":"Point"}
}