{
  "id": 7440860,
  "type": "Feature",
  "properties": {
    "tgn:hierarchy":[
        "tgn:7440860",
        "tgn:1000001",
        "tgn:1001960",
        "tgn:7005560",
        "tgn:7029392"
    ],
    "tgn:id":7440860,
    "tgn:name":"San Luis",
    "tgn:placetype":[
        "aat:300008347"
    ]
},
  "bbox": [],
  "geometry": {"coordinates":[-111.083333,29.55],"type":"Point"}
}