{
  "id": 2608944,
  "type": "Feature",
  "properties": {
    "tgn:hierarchy":[
        "tgn:2608944",
        "tgn:1000001",
        "tgn:7012149",
        "tgn:2001894",
        "tgn:7007825",
        "tgn:7029392"
    ],
    "tgn:id":2608944,
    "tgn:name":"Raulston Branch",
    "tgn:placetype":[
        "aat:300008699"
    ]
},
  "bbox": [],
  "geometry": {"coordinates":[-85.6833,35.0667],"type":"Point"}
}