{
  "id": 2218651,
  "type": "Feature",
  "properties": {
    "tgn:hierarchy":[
        "tgn:2218651",
        "tgn:2001837",
        "tgn:1000001",
        "tgn:7012149",
        "tgn:7007825",
        "tgn:7029392"
    ],
    "tgn:id":2218651,
    "tgn:name":"Cane Creek",
    "tgn:placetype":[
        "aat:300008347"
    ]
},
  "bbox": [],
  "geometry": {"coordinates":[-84.1167,36.1667],"type":"Point"}
}