{
  "id": 7284408,
  "type": "Feature",
  "properties": {
    "tgn:hierarchy":[
        "tgn:7284408",
        "tgn:7016598",
        "tgn:1000049",
        "tgn:1000002",
        "tgn:7029392"
    ],
    "tgn:id":7284408,
    "tgn:name":"Posta La Cruz",
    "tgn:placetype":[
        "aat:300004792"
    ]
},
  "bbox": [],
  "geometry": {"coordinates":[-69.566667,-22.233333],"type":"Point"}
}