{
  "id": 7148425,
  "type": "Feature",
  "properties": {
    "tgn:hierarchy":[
        "tgn:7148425",
        "tgn:1000003",
        "tgn:7000094",
        "tgn:7000084",
        "tgn:7029392"
    ],
    "tgn:id":7148425,
    "tgn:name":"Krummer Woklowsee",
    "tgn:placetype":[
        "aat:300008680"
    ]
},
  "bbox": [],
  "geometry": {"coordinates":[12.933333,53.25],"type":"Point"}
}