{
  "id": 1066530,
  "type": "Feature",
  "properties": {
    "tgn:hierarchy":[
        "tgn:1066530",
        "tgn:1000004",
        "tgn:7002087",
        "tgn:1000111",
        "tgn:7029392"
    ],
    "tgn:id":1066530,
    "tgn:name":"Anfuzhen",
    "tgn:placetype":[
        "aat:300008347"
    ]
},
  "bbox": [],
  "geometry": {"coordinates":[104.6833,28.7833],"type":"Point"}
}