<<<<<<< HEAD
{
  "id": 7477969,
  "type": "Feature",
  "properties": {
    "tgn:hierarchy":[
        "tgn:7477969",
        "tgn:7487020",
        "tgn:1000004",
        "tgn:1000141",
        "tgn:7029392"
    ],
    "tgn:id":7477969,
    "tgn:name":"Ximen Qiao",
    "tgn:placetype":[
        "aat:300007836"
    ]
},
  "bbox": [],
  "geometry": {"coordinates":[120.861191,24.682475],"type":"Point"}
}
=======
{"geometry":{"type":"Point","coordinates":[120.861191,24.682475]},"type":"Feature","properties":{"hierarchy":["tgn:7477969","tgn:7487020","tgn:1000004","tgn:1000141","tgn:7029392"],"placetype":["aat:300007836"],"id":7477969,"name:xx":"Ximen Qiao"}}
>>>>>>> 03f74aca74312dbeaf24d7e61306dd6a786dc3d0
