{
  "id": 1044115,
  "type": "Feature",
  "properties": {
    "tgn:hierarchy":[
        "tgn:1044115",
        "tgn:7002996",
        "tgn:1000003",
        "tgn:7002997",
        "tgn:1000080",
        "tgn:7029392"
    ],
    "tgn:id":1044115,
    "tgn:name":"Cavaso del Tomba",
    "tgn:placetype":[
        "aat:300008347"
    ]
},
  "bbox": [],
  "geometry": {"coordinates":[11.8667,45.85],"type":"Point"}
}