{
  "id": 7069663,
  "type": "Feature",
  "properties": {
    "tgn:hierarchy":[
        "tgn:7069663",
        "tgn:1000003",
        "tgn:7000094",
        "tgn:7000084",
        "tgn:7029392"
    ],
    "tgn:id":7069663,
    "tgn:name":"Thomsholz",
    "tgn:placetype":[
        "aat:300008863"
    ]
},
  "bbox": [],
  "geometry": {"coordinates":[11.883333,53.866667],"type":"Point"}
}