{
  "id": 7303132,
  "type": "Feature",
  "properties": {
    "tgn:hierarchy":[
        "tgn:7303132",
        "tgn:7002818",
        "tgn:1001647",
        "tgn:1000003",
        "tgn:1000095",
        "tgn:7029392"
    ],
    "tgn:id":7303132,
    "tgn:name":"Olivilla, Cerro",
    "tgn:placetype":[
        "aat:300008777"
    ]
},
  "bbox": [],
  "geometry": {"coordinates":[-2.383333,39.666667],"type":"Point"}
}