{
  "id": 2266178,
  "type": "Feature",
  "properties": {
    "tgn:hierarchy":[
        "tgn:2266178",
        "tgn:1000001",
        "tgn:1002500",
        "tgn:7012149",
        "tgn:7007240",
        "tgn:7029392"
    ],
    "tgn:id":2266178,
    "tgn:name":"Crawford Point",
    "tgn:placetype":[
        "aat:300008850"
    ]
},
  "bbox": [],
  "geometry": {"coordinates":[-80.35,27.5833],"type":"Point"}
}