{
  "id": 7206626,
  "type": "Feature",
  "properties": {
    "tgn:hierarchy":[
        "tgn:7206626",
        "tgn:7000096",
        "tgn:1000003",
        "tgn:7000084",
        "tgn:7029392"
    ],
    "tgn:id":7206626,
    "tgn:name":"Calauer Vorstadt",
    "tgn:placetype":[
        "aat:300000745"
    ]
},
  "bbox": [],
  "geometry": {"coordinates":[13.733333,51.85],"type":"Point"}
}