{
  "id": 2684686,
  "type": "Feature",
  "properties": {
    "tgn:hierarchy":[
        "tgn:2684686",
        "tgn:1000001",
        "tgn:7012149",
        "tgn:7014510",
        "tgn:7007920",
        "tgn:7029392"
    ],
    "tgn:id":2684686,
    "tgn:name":"Spire Lake",
    "tgn:placetype":[
        "aat:300008680"
    ]
},
  "bbox": [],
  "geometry": {"coordinates":[-121.0833,48.3167],"type":"Point"}
}