<<<<<<< HEAD
{
  "id": 2333181,
  "type": "Feature",
  "properties": {
    "tgn:hierarchy":[
        "tgn:2333181",
        "tgn:1000001",
        "tgn:7012149",
        "tgn:2001854",
        "tgn:7007825",
        "tgn:7029392"
    ],
    "tgn:id":2333181,
    "tgn:name":"Flynn Creek",
    "tgn:placetype":[
        "aat:300008706"
    ]
},
  "bbox": [],
  "geometry": {"coordinates":[-85.1333,35.8667],"type":"Point"}
}
=======
{"geometry":{"type":"Point","coordinates":[-85.133300,35.866700]},"type":"Feature","properties":{"hierarchy":["tgn:2333181","tgn:1000001","tgn:7012149","tgn:2001854","tgn:7007825","tgn:7029392"],"placetype":["aat:300008706"],"id":2333181,"name:xx":"Flynn Creek"}}
>>>>>>> 03f74aca74312dbeaf24d7e61306dd6a786dc3d0
