{
  "id": 1059378,
  "type": "Feature",
  "properties": {
    "tgn:hierarchy":[
        "tgn:1059378",
        "tgn:1000004",
        "tgn:7024035",
        "tgn:7006651",
        "tgn:7029392"
    ],
    "tgn:id":1059378,
    "tgn:name:en":"Sevan",
    "tgn:placetype":[
        "aat:300008347",
        "aat:300387220",
        "aat:300008375"
    ]
},
  "bbox": [],
  "geometry": {"coordinates":[44.965,40.555],"type":"Point"}
}