{
  "id": 2279588,
  "type": "Feature",
  "properties": {
    "tgn:hierarchy":[
        "tgn:2279588",
        "tgn:7016099",
        "tgn:1000001",
        "tgn:7012149",
        "tgn:7007516",
        "tgn:7029392"
    ],
    "tgn:id":2279588,
    "tgn:name":"Deadman Run",
    "tgn:placetype":[
        "aat:300008699"
    ]
},
  "bbox": [],
  "geometry": {"coordinates":[-76.7333,39.4833],"type":"Point"}
}