{
  "id": 2214766,
  "type": "Feature",
  "properties": {
    "tgn:hierarchy":[
        "tgn:2214766",
        "tgn:1000001",
        "tgn:7012149",
        "tgn:2000805",
        "tgn:7007255",
        "tgn:7029392"
    ],
    "tgn:id":2214766,
    "tgn:name":"Calf Hollow",
    "tgn:placetype":[
        "aat:300008761"
    ]
},
  "bbox": [],
  "geometry": {"coordinates":[-83.0333,37.2833],"type":"Point"}
}