{
  "id": 2477927,
  "type": "Feature",
  "properties": {
    "tgn:hierarchy":[
        "tgn:2477927",
        "tgn:1000001",
        "tgn:7012149",
        "tgn:1002230",
        "tgn:7007826",
        "tgn:7029392"
    ],
    "tgn:id":2477927,
    "tgn:name":"Macedonia",
    "tgn:placetype":[
        "aat:300008347"
    ]
},
  "bbox": [],
  "geometry": {"coordinates":[-94.9667,33.0333],"type":"Point"}
}