{
  "id": 1075129,
  "type": "Feature",
  "properties": {
    "tgn:hierarchy":[
        "tgn:1075129",
        "tgn:1000004",
        "tgn:7000198",
        "tgn:7016722",
        "tgn:7029392"
    ],
    "tgn:id":1075129,
    "tgn:name:en":"Deoria",
    "tgn:placetype":[
        "aat:300008347"
    ]
},
  "bbox": [],
  "geometry": {"coordinates":[83.779364,26.50167],"type":"Point"}
}