{
  "id": 2362265,
  "type": "Feature",
  "properties": {
    "tgn:hierarchy":[
        "tgn:2362265",
        "tgn:1000001",
        "tgn:7012149",
        "tgn:2001499",
        "tgn:7007709",
        "tgn:7029392"
    ],
    "tgn:id":2362265,
    "tgn:name":"Grays Millpond",
    "tgn:placetype":[
        "aat:300006191"
    ]
},
  "bbox": [],
  "geometry": {"coordinates":[-77.65,35.35],"type":"Point"}
}