<<<<<<< HEAD
{
  "id": 2767218,
  "type": "Feature",
  "properties": {
    "tgn:hierarchy":[
        "tgn:2767218",
        "tgn:1000001",
        "tgn:7012149",
        "tgn:2000488",
        "tgn:7007250",
        "tgn:7029392"
    ],
    "tgn:id":2767218,
    "tgn:name":"White Rock Reservoir",
    "tgn:placetype":[
        "aat:300006191"
    ]
},
  "bbox": [],
  "geometry": {"coordinates":[-116.5833,42.2667],"type":"Point"}
}
=======
{"geometry":{"type":"Point","coordinates":[-116.583300,42.266700]},"type":"Feature","properties":{"hierarchy":["tgn:2767218","tgn:1000001","tgn:7012149","tgn:2000488","tgn:7007250","tgn:7029392"],"placetype":["aat:300006191"],"id":2767218,"name:xx":"White Rock Reservoir"}}
>>>>>>> 03f74aca74312dbeaf24d7e61306dd6a786dc3d0
