{
  "id": 7088633,
  "type": "Feature",
  "properties": {
    "tgn:hierarchy":[
        "tgn:7088633",
        "tgn:1000003",
        "tgn:7003678",
        "tgn:7000084",
        "tgn:7029392"
    ],
    "tgn:id":7088633,
    "tgn:name":"Wahlert",
    "tgn:placetype":[
        "aat:300008347"
    ]
},
  "bbox": [],
  "geometry": {"coordinates":[9.366667,50.316667],"type":"Point"}
}