{
  "id": 7321541,
  "type": "Feature",
  "properties": {
    "tgn:hierarchy":[
        "tgn:7321541",
        "tgn:1001623",
        "tgn:1000049",
        "tgn:1000002",
        "tgn:7029392"
    ],
    "tgn:id":7321541,
    "tgn:name":"Benjam\u00edn, Cerro",
    "tgn:placetype":[
        "aat:300008777"
    ]
},
  "bbox": [],
  "geometry": {"coordinates":[-74.666667,-46.866667],"type":"Point"}
}