<<<<<<< HEAD
{
  "id": 7176387,
  "type": "Feature",
  "properties": {
    "tgn:hierarchy":[
        "tgn:7176387",
        "tgn:7003692",
        "tgn:1000003",
        "tgn:7000084",
        "tgn:7029392"
    ],
    "tgn:id":7176387,
    "tgn:name":"Gr\u00fcningen",
    "tgn:placetype":[
        "aat:300008347"
    ]
},
  "bbox": [],
  "geometry": {"coordinates":[8.466667,47.983333],"type":"Point"}
}
=======
{"geometry":{"type":"Point","coordinates":[8.466667,47.983333]},"type":"Feature","properties":{"hierarchy":["tgn:7176387","tgn:7003692","tgn:1000003","tgn:7000084","tgn:7029392"],"placetype":["aat:300008347"],"id":7176387,"name:xx":"Gr\u00fcningen"}}
>>>>>>> 03f74aca74312dbeaf24d7e61306dd6a786dc3d0
