{
  "id": 7584398,
  "type": "Feature",
  "properties": {
    "tgn:hierarchy":[
        "tgn:7584398",
        "tgn:1000004",
        "tgn:7000198",
        "tgn:1001894",
        "tgn:7029392"
    ],
    "tgn:id":7584398,
    "tgn:name:en":"Pathariya",
    "tgn:placetype":[
        "aat:300008347"
    ]
},
  "bbox": [],
  "geometry": {"coordinates":[78.85627,24.867324],"type":"Point"}
}