{
  "id": 7561293,
  "type": "Feature",
  "properties": {
    "tgn:hierarchy":[
        "tgn:7561293",
        "tgn:1000004",
        "tgn:7000198",
        "tgn:7016722",
        "tgn:7029392"
    ],
    "tgn:id":7561293,
    "tgn:name:en":"Chinjri",
    "tgn:placetype":[
        "aat:300008347"
    ]
},
  "bbox": [],
  "geometry": {"coordinates":[79.288409,27.974771],"type":"Point"}
}