<<<<<<< HEAD
{
  "id": 7020868,
  "type": "Feature",
  "properties": {
    "tgn:hierarchy":[
        "tgn:7020868",
        "tgn:1000001",
        "tgn:7012149",
        "tgn:7029392"
    ],
    "tgn:id":7020868,
    "tgn:name":"Locust Creek",
    "tgn:placetype":[
        "aat:300008706"
    ]
},
  "bbox": [],
  "geometry": {"coordinates":[-93.2167,40.6667],"type":"Point"}
}
=======
{"geometry":{"type":"Point","coordinates":[-93.216700,40.666700]},"type":"Feature","properties":{"hierarchy":["tgn:7020868","tgn:1000001","tgn:7012149","tgn:7029392"],"placetype":["aat:300008706"],"id":7020868,"name:xx":"Locust Creek"}}
>>>>>>> 03f74aca74312dbeaf24d7e61306dd6a786dc3d0
