{
  "id": 7555913,
  "type": "Feature",
  "properties": {
    "tgn:hierarchy":[
        "tgn:7555913",
        "tgn:1000004",
        "tgn:7031781",
        "tgn:7000198",
        "tgn:7029392"
    ],
    "tgn:id":7555913,
    "tgn:name:en":"Narangi River",
    "tgn:placetype":[
        "aat:300008699"
    ]
},
  "bbox": [],
  "geometry": {"coordinates":[81.733333,19.183333],"type":"Point"}
}