{
  "id": 7077353,
  "type": "Feature",
  "properties": {
    "tgn:hierarchy":[
        "tgn:7077353",
        "tgn:1000003",
        "tgn:7003678",
        "tgn:7000084",
        "tgn:7029392"
    ],
    "tgn:id":7077353,
    "tgn:name":"Ziegenhagen",
    "tgn:placetype":[
        "aat:300008347"
    ]
},
  "bbox": [],
  "geometry": {"coordinates":[9.75,51.366667],"type":"Point"}
}