{
  "id": 1009119,
  "type": "Feature",
  "properties": {
    "tgn:hierarchy":[
        "tgn:1009119",
        "tgn:1000004",
        "tgn:7002077",
        "tgn:1000111",
        "tgn:7029392"
    ],
    "tgn:id":1009119,
    "tgn:name":"Shaleitian Dao",
    "tgn:placetype":[
        "aat:300008791"
    ]
},
  "bbox": [],
  "geometry": {"coordinates":[118.7333,39.05],"type":"Point"}
}