{
  "id": 7260307,
  "type": "Feature",
  "properties": {
    "tgn:concordances":{
        "gn:id":"2755364"
    },
    "tgn:hierarchy":[
        "tgn:7260307",
        "tgn:1000003",
        "tgn:7003635",
        "tgn:7016845",
        "tgn:7029392"
    ],
    "tgn:id":7260307,
    "tgn:name:nl":"Graszode",
    "tgn:placetype":[
        "aat:300008347"
    ]
},
  "bbox": [],
  "geometry": {"coordinates":[3.783333,51.483333],"type":"Point"}
}