{
  "id": 7463403,
  "type": "Feature",
  "properties": {
    "tgn:hierarchy":[
        "tgn:7463403",
        "tgn:7002445",
        "tgn:1000003",
        "tgn:7008178",
        "tgn:7008591",
        "tgn:7029392"
    ],
    "tgn:id":7463403,
    "tgn:name:en":"Long Marston",
    "tgn:placetype":[
        "aat:300008347"
    ]
},
  "bbox": [],
  "geometry": {"coordinates":[-1.783333,52.133333],"type":"Point"}
}