{
  "id": 2624310,
  "type": "Feature",
  "properties": {
    "tgn:hierarchy":[
        "tgn:2624310",
        "tgn:1000001",
        "tgn:2001096",
        "tgn:7012149",
        "tgn:7007522",
        "tgn:7029392"
    ],
    "tgn:id":2624310,
    "tgn:name":"Rock Lake",
    "tgn:placetype":[
        "aat:300008680"
    ]
},
  "bbox": [],
  "geometry": {"coordinates":[-91.0333,32.0333],"type":"Point"}
}