{
  "id": 2640166,
  "type": "Feature",
  "properties": {
    "tgn:hierarchy":[
        "tgn:2640166",
        "tgn:1000001",
        "tgn:7012149",
        "tgn:1002798",
        "tgn:7007252",
        "tgn:7029392"
    ],
    "tgn:id":2640166,
    "tgn:name":"Samuelson Ditch",
    "tgn:placetype":[
        "aat:300008699"
    ]
},
  "bbox": [],
  "geometry": {"coordinates":[-87.1167,41.6167],"type":"Point"}
}