<<<<<<< HEAD
{
  "id": 2335912,
  "type": "Feature",
  "properties": {
    "tgn:hierarchy":[
        "tgn:2335912",
        "tgn:1000001",
        "tgn:7012149",
        "tgn:7007157",
        "tgn:2000185",
        "tgn:7029392"
    ],
    "tgn:id":2335912,
    "tgn:name":"Fossil Creek",
    "tgn:placetype":[
        "aat:300008706"
    ]
},
  "bbox": [],
  "geometry": {"coordinates":[-123.0667,39.9167],"type":"Point"}
}
=======
{"geometry":{"type":"Point","coordinates":[-123.066700,39.916700]},"type":"Feature","properties":{"hierarchy":["tgn:2335912","tgn:1000001","tgn:7012149","tgn:7007157","tgn:2000185","tgn:7029392"],"placetype":["aat:300008706"],"id":2335912,"name:xx":"Fossil Creek"}}
>>>>>>> 03f74aca74312dbeaf24d7e61306dd6a786dc3d0
