{
  "id": 2213932,
  "type": "Feature",
  "properties": {
    "tgn:hierarchy":[
        "tgn:2213932",
        "tgn:1000001",
        "tgn:7012149",
        "tgn:2000973",
        "tgn:7007520",
        "tgn:7029392"
    ],
    "tgn:id":2213932,
    "tgn:name":"Cadogan Point",
    "tgn:placetype":[
        "aat:300008850"
    ]
},
  "bbox": [],
  "geometry": {"coordinates":[-84.1333,45.9667],"type":"Point"}
}