{
  "id": 7495086,
  "type": "Feature",
  "properties": {
    "tgn:hierarchy":[
        "tgn:7495086",
        "tgn:1000004",
        "tgn:7001013",
        "tgn:1000141",
        "tgn:7029392"
    ],
    "tgn:id":7495086,
    "tgn:name":"Qiao'ai Guoxiao",
    "tgn:placetype":[
        "aat:300006495"
    ]
},
  "bbox": [],
  "geometry": {"coordinates":[121.292268,24.921643],"type":"Point"}
}