{
  "id": 1013770,
  "type": "Feature",
  "properties": {
    "tgn:hierarchy":[
        "tgn:1013770",
        "tgn:7005735",
        "tgn:7005685",
        "tgn:1000001",
        "tgn:7029392"
    ],
    "tgn:id":1013770,
    "tgn:name":"Spences Bridge",
    "tgn:placetype":[
        "aat:300008347"
    ]
},
  "bbox": [],
  "geometry": {"coordinates":[-121.35,50.3833],"type":"Point"}
}