{
  "id": 7561800,
  "type": "Feature",
  "properties": {
    "tgn:hierarchy":[
        "tgn:7561800",
        "tgn:1000004",
        "tgn:7000198",
        "tgn:7016722",
        "tgn:7029392"
    ],
    "tgn:id":7561800,
    "tgn:name:en":"Devganj",
    "tgn:placetype":[
        "aat:300008347"
    ]
},
  "bbox": [],
  "geometry": {"coordinates":[79.267663,27.094008],"type":"Point"}
}