{
  "id": 2520154,
  "type": "Feature",
  "properties": {
    "tgn:hierarchy":[
        "tgn:2520154",
        "tgn:1007657",
        "tgn:1002534",
        "tgn:1000001",
        "tgn:7012149",
        "tgn:7007249",
        "tgn:7029392"
    ],
    "tgn:id":2520154,
    "tgn:name":"Moloaa Bay",
    "tgn:placetype":[
        "aat:300132316"
    ]
},
  "bbox": [],
  "geometry": {"coordinates":[-159.3333,22.1833],"type":"Point"}
}