{
  "id": 2487711,
  "type": "Feature",
  "properties": {
    "tgn:hierarchy":[
        "tgn:2487711",
        "tgn:1000001",
        "tgn:7012149",
        "tgn:1003017",
        "tgn:7007710",
        "tgn:7029392"
    ],
    "tgn:id":2487711,
    "tgn:name":"Left Fork Mill Creek",
    "tgn:placetype":[
        "aat:300008706"
    ]
},
  "bbox": [],
  "geometry": {"coordinates":[-79.0833,40.2333],"type":"Point"}
}