{
  "id": 7099946,
  "type": "Feature",
  "properties": {
    "tgn:hierarchy":[
        "tgn:7099946",
        "tgn:7003669",
        "tgn:1000003",
        "tgn:7000084",
        "tgn:7029392"
    ],
    "tgn:id":7099946,
    "tgn:name":"Sperklgrub",
    "tgn:placetype":[
        "aat:300000206"
    ]
},
  "bbox": [],
  "geometry": {"coordinates":[13.15,48.566667],"type":"Point"}
}