{
  "id": 7020155,
  "type": "Feature",
  "properties": {
    "tgn:hierarchy":[
        "tgn:7020155",
        "tgn:2000767",
        "tgn:1000001",
        "tgn:7012149",
        "tgn:7007255",
        "tgn:7029392"
    ],
    "tgn:id":7020155,
    "tgn:name":"Clear Lake",
    "tgn:placetype":[
        "aat:300008680"
    ]
},
  "bbox": [],
  "geometry": {"coordinates":[-89.0833,37.05],"type":"Point"}
}