{
  "id": 2249268,
  "type": "Feature",
  "properties": {
    "tgn:hierarchy":[
        "tgn:2249268",
        "tgn:1000001",
        "tgn:7012149",
        "tgn:7007157",
        "tgn:7029392"
    ],
    "tgn:id":2249268,
    "tgn:name":"Cole Slough",
    "tgn:placetype":[
        "aat:300008699"
    ]
},
  "bbox": [],
  "geometry": {"coordinates":[-119.5333,36.4833],"type":"Point"}
}