{
  "id": 7359403,
  "type": "Feature",
  "properties": {
    "tgn:hierarchy":[
        "tgn:7359403",
        "tgn:1000001",
        "tgn:7005601",
        "tgn:7005560",
        "tgn:7029392"
    ],
    "tgn:id":7359403,
    "tgn:name":"Dolores",
    "tgn:placetype":[
        "aat:300008347"
    ]
},
  "bbox": [],
  "geometry": {"coordinates":[-101.833333,23.616667],"type":"Point"}
}