{
  "id": 2390408,
  "type": "Feature",
  "properties": {
    "tgn:hierarchy":[
        "tgn:2390408",
        "tgn:1000001",
        "tgn:7012149",
        "tgn:1002751",
        "tgn:7007568",
        "tgn:7029392"
    ],
    "tgn:id":2390408,
    "tgn:name":"Highland Lake",
    "tgn:placetype":[
        "aat:300006191"
    ]
},
  "bbox": [],
  "geometry": {"coordinates":[-74.4833,41.45],"type":"Point"}
}