{
  "id": 7496494,
  "type": "Feature",
  "properties": {
    "tgn:hierarchy":[
        "tgn:7496494",
        "tgn:1000004",
        "tgn:7001014",
        "tgn:1000141",
        "tgn:7029392"
    ],
    "tgn:id":7496494,
    "tgn:name":"Zhengmin Guoxiao",
    "tgn:placetype":[
        "aat:300006495"
    ]
},
  "bbox": [],
  "geometry": {"coordinates":[120.408825,23.708677],"type":"Point"}
}