{
  "id": 2621903,
  "type": "Feature",
  "properties": {
    "tgn:hierarchy":[
        "tgn:2621903",
        "tgn:1000001",
        "tgn:7012149",
        "tgn:2000471",
        "tgn:7007250",
        "tgn:7029392"
    ],
    "tgn:id":2621903,
    "tgn:name":"Robert E Lee Creek",
    "tgn:placetype":[
        "aat:300008706"
    ]
},
  "bbox": [],
  "geometry": {"coordinates":[-115.4167,43.8667],"type":"Point"}
}