{
  "id": 7125285,
  "type": "Feature",
  "properties": {
    "tgn:hierarchy":[
        "tgn:7125285",
        "tgn:7003669",
        "tgn:1000003",
        "tgn:7000084",
        "tgn:7029392"
    ],
    "tgn:id":7125285,
    "tgn:name":"Neulohe",
    "tgn:placetype":[
        "aat:300008347"
    ]
},
  "bbox": [],
  "geometry": {"coordinates":[11.816667,48.983333],"type":"Point"}
}