{
  "id": 2324397,
  "type": "Feature",
  "properties": {
    "tgn:hierarchy":[
        "tgn:2324397",
        "tgn:1000001",
        "tgn:7012149",
        "tgn:2000885",
        "tgn:7007256",
        "tgn:7029392"
    ],
    "tgn:id":2324397,
    "tgn:name":"Felbert Creek",
    "tgn:placetype":[
        "aat:300008706"
    ]
},
  "bbox": [],
  "geometry": {"coordinates":[-90.75,30.6333],"type":"Point"}
}