{
  "id": 2748759,
  "type": "Feature",
  "properties": {
    "tgn:hierarchy":[
        "tgn:2748759",
        "tgn:1000001",
        "tgn:7012149",
        "tgn:1002624",
        "tgn:7007568",
        "tgn:7029392"
    ],
    "tgn:id":2748759,
    "tgn:name":"Walkers Corners",
    "tgn:placetype":[
        "aat:300008347"
    ]
},
  "bbox": [],
  "geometry": {"coordinates":[-75.7667,43.1167],"type":"Point"}
}