{
  "id": 2108690,
  "type": "Feature",
  "properties": {
    "tgn:hierarchy":[
        "tgn:2108690",
        "tgn:1000001",
        "tgn:7012149",
        "tgn:2002121",
        "tgn:7007827",
        "tgn:7029392"
    ],
    "tgn:id":2108690,
    "tgn:name":"Austin",
    "tgn:placetype":[
        "aat:300008347"
    ]
},
  "bbox": [],
  "geometry": {"coordinates":[-112.1167,38.6667],"type":"Point"}
}