{
  "id": 7534430,
  "type": "Feature",
  "properties": {
    "tgn:hierarchy":[
        "tgn:7534430",
        "tgn:7001242",
        "tgn:7016833",
        "tgn:1001113",
        "tgn:7029392"
    ],
    "tgn:id":7534430,
    "tgn:name":"Kafr S\u016br at Tall",
    "tgn:placetype":[
        "aat:300008347"
    ]
},
  "bbox": [],
  "geometry": {"coordinates":[31.666667,30.483333],"type":"Point"}
}