{
  "id": 7589669,
  "type": "Feature",
  "properties": {
    "tgn:hierarchy":[
        "tgn:7589669",
        "tgn:1000004",
        "tgn:7000198",
        "tgn:7000799",
        "tgn:7029392"
    ],
    "tgn:id":7589669,
    "tgn:name:en":"Gal\u0101li",
    "tgn:placetype":[
        "aat:300008347"
    ]
},
  "bbox": [],
  "geometry": {"coordinates":[74.785909,32.937582],"type":"Point"}
}