{
  "id": 7525776,
  "type": "Feature",
  "properties": {
    "tgn:hierarchy":[
        "tgn:7525776",
        "tgn:7001242",
        "tgn:7016833",
        "tgn:1001225",
        "tgn:7029392"
    ],
    "tgn:id":7525776,
    "tgn:name:en":"Darf\u012bl, \u1e28alq ad",
    "tgn:placetype":[
        "aat:300132317"
    ]
},
  "bbox": [],
  "geometry": {"coordinates":[31.919049,31.390747],"type":"Point"}
}