{
  "id": 2582605,
  "type": "Feature",
  "properties": {
    "tgn:hierarchy":[
        "tgn:2582605",
        "tgn:1000001",
        "tgn:7012149",
        "tgn:7013941",
        "tgn:7007568",
        "tgn:7029392"
    ],
    "tgn:id":2582605,
    "tgn:name":"Pine Hill",
    "tgn:placetype":[
        "aat:300008798"
    ]
},
  "bbox": [],
  "geometry": {"coordinates":[-74.0167,44.45],"type":"Point"}
}