{
  "id": 2447633,
  "type": "Feature",
  "properties": {
    "tgn:hierarchy":[
        "tgn:2447633",
        "tgn:1000001",
        "tgn:2001181",
        "tgn:7012149",
        "tgn:7007523",
        "tgn:7029392"
    ],
    "tgn:id":2447633,
    "tgn:name":"Lick Log Hollow",
    "tgn:placetype":[
        "aat:300008761"
    ]
},
  "bbox": [],
  "geometry": {"coordinates":[-91.0167,36.8833],"type":"Point"}
}