{
  "id": 7373178,
  "type": "Feature",
  "properties": {
    "tgn:hierarchy":[
        "tgn:7373178",
        "tgn:1000001",
        "tgn:7005595",
        "tgn:7005560",
        "tgn:7029392"
    ],
    "tgn:id":7373178,
    "tgn:name":"Rancho La Palma",
    "tgn:placetype":[
        "aat:300000241"
    ]
},
  "bbox": [],
  "geometry": {"coordinates":[-108.163611,26.564722],"type":"Point"}
}