<<<<<<< HEAD
{
  "id": 2254369,
  "type": "Feature",
  "properties": {
    "tgn:hierarchy":[
        "tgn:2254369",
        "tgn:1000001",
        "tgn:7012149",
        "tgn:1002892",
        "tgn:7007520",
        "tgn:7029392"
    ],
    "tgn:id":2254369,
    "tgn:name":"Coon Creek",
    "tgn:placetype":[
        "aat:300008706"
    ]
},
  "bbox": [],
  "geometry": {"coordinates":[-84.3333,42.8833],"type":"Point"}
}
=======
{"geometry":{"type":"Point","coordinates":[-84.333300,42.883300]},"type":"Feature","properties":{"hierarchy":["tgn:2254369","tgn:1000001","tgn:7012149","tgn:1002892","tgn:7007520","tgn:7029392"],"placetype":["aat:300008706"],"id":2254369,"name:xx":"Coon Creek"}}
>>>>>>> 03f74aca74312dbeaf24d7e61306dd6a786dc3d0
