{
  "id": 2254369,
  "type": "Feature",
  "properties": {
    "tgn:hierarchy":[
        "tgn:2254369",
        "tgn:1000001",
        "tgn:7012149",
        "tgn:1002892",
        "tgn:7007520",
        "tgn:7029392"
    ],
    "tgn:id":2254369,
    "tgn:name":"Coon Creek",
    "tgn:placetype":[
        "aat:300008706"
    ]
},
  "bbox": [],
  "geometry": {"coordinates":[-84.3333,42.8833],"type":"Point"}
}