<<<<<<< HEAD
{
  "id": 2332535,
  "type": "Feature",
  "properties": {
    "tgn:hierarchy":[
        "tgn:2332535",
        "tgn:1000001",
        "tgn:7012149",
        "tgn:2001449",
        "tgn:7007566",
        "tgn:7029392"
    ],
    "tgn:id":2332535,
    "tgn:name":"Florentino, Ca\u00f1on",
    "tgn:placetype":[
        "aat:300008761"
    ]
},
  "bbox": [],
  "geometry": {"coordinates":[-106.1833,36.9833],"type":"Point"}
}
=======
{"geometry":{"type":"Point","coordinates":[-106.183300,36.983300]},"type":"Feature","properties":{"hierarchy":["tgn:2332535","tgn:1000001","tgn:7012149","tgn:2001449","tgn:7007566","tgn:7029392"],"placetype":["aat:300008761"],"id":2332535,"name:xx":"Florentino, Ca\u00f1on"}}
>>>>>>> 03f74aca74312dbeaf24d7e61306dd6a786dc3d0
