<<<<<<< HEAD
{
  "id": 7482504,
  "type": "Feature",
  "properties": {
    "tgn:hierarchy":[
        "tgn:7482504",
        "tgn:7469009",
        "tgn:1000004",
        "tgn:1000141",
        "tgn:7029392"
    ],
    "tgn:id":7482504,
    "tgn:name":"Rong Hu",
    "tgn:placetype":[
        "aat:300008680"
    ]
},
  "bbox": [],
  "geometry": {"coordinates":[118.410139,24.487547],"type":"Point"}
}
=======
{"geometry":{"type":"Point","coordinates":[118.410139,24.487547]},"type":"Feature","properties":{"hierarchy":["tgn:7482504","tgn:7469009","tgn:1000004","tgn:1000141","tgn:7029392"],"placetype":["aat:300008680"],"id":7482504,"name:xx":"Rong Hu"}}
>>>>>>> 03f74aca74312dbeaf24d7e61306dd6a786dc3d0
