{
  "id": 7065042,
  "type": "Feature",
  "properties": {
    "tgn:hierarchy":[
        "tgn:7065042",
        "tgn:1000003",
        "tgn:7003678",
        "tgn:7000084",
        "tgn:7029392"
    ],
    "tgn:id":7065042,
    "tgn:name":"Steink\u00fcppel",
    "tgn:placetype":[
        "aat:300008777"
    ]
},
  "bbox": [],
  "geometry": {"coordinates":[8.05,50.216667],"type":"Point"}
}