{
  "id": 2742745,
  "type": "Feature",
  "properties": {
    "tgn:hierarchy":[
        "tgn:2742745",
        "tgn:1000001",
        "tgn:2001260",
        "tgn:7012149",
        "tgn:7007524",
        "tgn:7029392"
    ],
    "tgn:id":2742745,
    "tgn:name":"Van Camp Canyon",
    "tgn:placetype":[
        "aat:300008761"
    ]
},
  "bbox": [],
  "geometry": {"coordinates":[-112.4667,45.1167],"type":"Point"}
}