{
  "id": 7182727,
  "type": "Feature",
  "properties": {
    "tgn:hierarchy":[
        "tgn:7182727",
        "tgn:1000003",
        "tgn:7003684",
        "tgn:7000084",
        "tgn:7029392"
    ],
    "tgn:id":7182727,
    "tgn:name":"Gehweiler",
    "tgn:placetype":[
        "aat:300008347"
    ]
},
  "bbox": [],
  "geometry": {"coordinates":[7.183333,49.533333],"type":"Point"}
}