{
  "id": 2677378,
  "type": "Feature",
  "properties": {
    "tgn:hierarchy":[
        "tgn:2677378",
        "tgn:1000001",
        "tgn:1002340",
        "tgn:7012149",
        "tgn:7007526",
        "tgn:7029392"
    ],
    "tgn:id":2677378,
    "tgn:name":"South Camp Peak",
    "tgn:placetype":[
        "aat:300008798"
    ]
},
  "bbox": [],
  "geometry": {"coordinates":[-119.8833,39.05],"type":"Point"}
}