{
  "id": 7391199,
  "type": "Feature",
  "properties": {
    "tgn:hierarchy":[
        "tgn:7391199",
        "tgn:1000001",
        "tgn:7005597",
        "tgn:7005560",
        "tgn:7029392"
    ],
    "tgn:id":7391199,
    "tgn:name":"Rancho Santa Elena",
    "tgn:placetype":[
        "aat:300008347"
    ]
},
  "bbox": [],
  "geometry": {"coordinates":[-98.15,25.116667],"type":"Point"}
}