{
  "id": 7343014,
  "type": "Feature",
  "properties": {
    "tgn:hierarchy":[
        "tgn:7343014",
        "tgn:7002804",
        "tgn:1000003",
        "tgn:7002793",
        "tgn:1000095",
        "tgn:7029392"
    ],
    "tgn:id":7343014,
    "tgn:name":"Caser\u00edo El Campello",
    "tgn:placetype":[
        "aat:300008347"
    ]
},
  "bbox": [],
  "geometry": {"coordinates":[-0.616667,38.566667],"type":"Point"}
}