{
  "id": 7421416,
  "type": "Feature",
  "properties": {
    "tgn:hierarchy":[
        "tgn:7421416",
        "tgn:7005584",
        "tgn:1000001",
        "tgn:7005560",
        "tgn:7029392"
    ],
    "tgn:id":7421416,
    "tgn:name":"Alfaro",
    "tgn:placetype":[
        "aat:300008347"
    ]
},
  "bbox": [],
  "geometry": {"coordinates":[-101.607222,21.147778],"type":"Point"}
}