<<<<<<< HEAD
{
  "id": 7057547,
  "type": "Feature",
  "properties": {
    "tgn:hierarchy":[
        "tgn:7057547",
        "tgn:1001730",
        "tgn:1000003",
        "tgn:7003121",
        "tgn:1000080",
        "tgn:7029392"
    ],
    "tgn:id":7057547,
    "tgn:name":"Buttoni, Riude",
    "tgn:placetype":[
        "aat:300008699"
    ]
},
  "bbox": [],
  "geometry": {"coordinates":[8.516667,40.2],"type":"Point"}
}
=======
{"geometry":{"type":"Point","coordinates":[8.516667,40.200000]},"type":"Feature","properties":{"hierarchy":["tgn:7057547","tgn:1001730","tgn:1000003","tgn:7003121","tgn:1000080","tgn:7029392"],"placetype":["aat:300008699"],"id":7057547,"name:xx":"Buttoni, Riude"}}
>>>>>>> 03f74aca74312dbeaf24d7e61306dd6a786dc3d0
