{
  "id": 2613347,
  "type": "Feature",
  "properties": {
    "tgn:hierarchy":[
        "tgn:2613347",
        "tgn:1000001",
        "tgn:7012149",
        "tgn:2000928",
        "tgn:7007515",
        "tgn:7029392"
    ],
    "tgn:id":2613347,
    "tgn:name":"Reed Deadwater",
    "tgn:placetype":[
        "aat:300008680"
    ]
},
  "bbox": [],
  "geometry": {"coordinates":[-69.05,46.3333],"type":"Point"}
}