<<<<<<< HEAD
{
  "id": 2400829,
  "type": "Feature",
  "properties": {
    "tgn:hierarchy":[
        "tgn:2400829",
        "tgn:1000001",
        "tgn:7012149",
        "tgn:7007157",
        "tgn:1002710",
        "tgn:7029392"
    ],
    "tgn:id":2400829,
    "tgn:name":"Horse Range",
    "tgn:placetype":[
        "aat:300386831"
    ]
},
  "bbox": [],
  "geometry": {"coordinates":[-120.3,39.3333],"type":"Point"}
}
=======
{"geometry":{"type":"Point","coordinates":[-120.300000,39.333300]},"type":"Feature","properties":{"hierarchy":["tgn:2400829","tgn:1000001","tgn:7012149","tgn:7007157","tgn:1002710","tgn:7029392"],"placetype":["aat:300386831"],"id":2400829,"name:xx":"Horse Range"}}
>>>>>>> 03f74aca74312dbeaf24d7e61306dd6a786dc3d0
