{
  "id": 2197243,
  "type": "Feature",
  "properties": {
    "tgn:hierarchy":[
        "tgn:2197243",
        "tgn:1000001",
        "tgn:7006451",
        "tgn:7012149",
        "tgn:2000103",
        "tgn:7029392"
    ],
    "tgn:id":2197243,
    "tgn:name":"Brown Basin Tank",
    "tgn:placetype":[
        "aat:300006191"
    ]
},
  "bbox": [],
  "geometry": {"coordinates":[-113.0167,35.1833],"type":"Point"}
}