{
  "id": 7577807,
  "type": "Feature",
  "properties": {
    "tgn:hierarchy":[
        "tgn:7577807",
        "tgn:1000004",
        "tgn:7000198",
        "tgn:1001894",
        "tgn:7029392"
    ],
    "tgn:id":7577807,
    "tgn:name:en":"Kulh\u0101r",
    "tgn:placetype":[
        "aat:300008347"
    ]
},
  "bbox": [],
  "geometry": {"coordinates":[78.060198,23.969139],"type":"Point"}
}