{
  "id": 2719633,
  "type": "Feature",
  "properties": {
    "tgn:hierarchy":[
        "tgn:2719633",
        "tgn:1000001",
        "tgn:7012149",
        "tgn:2002113",
        "tgn:7007827",
        "tgn:7029392"
    ],
    "tgn:id":2719633,
    "tgn:name":"Three Lakes",
    "tgn:placetype":[
        "aat:300008680"
    ]
},
  "bbox": [],
  "geometry": {"coordinates":[-112.55,37.1333],"type":"Point"}
}