<<<<<<< HEAD
{
  "id": 2402880,
  "type": "Feature",
  "properties": {
    "tgn:hierarchy":[
        "tgn:2402880",
        "tgn:1000001",
        "tgn:2000922",
        "tgn:7012149",
        "tgn:7007515",
        "tgn:7029392"
    ],
    "tgn:id":2402880,
    "tgn:name":"Hothole Pond",
    "tgn:placetype":[
        "aat:300008680"
    ]
},
  "bbox": [],
  "geometry": {"coordinates":[-68.6667,44.6],"type":"Point"}
}
=======
{"geometry":{"type":"Point","coordinates":[-68.666700,44.600000]},"type":"Feature","properties":{"hierarchy":["tgn:2402880","tgn:1000001","tgn:2000922","tgn:7012149","tgn:7007515","tgn:7029392"],"placetype":["aat:300008680"],"id":2402880,"name:xx":"Hothole Pond"}}
>>>>>>> 03f74aca74312dbeaf24d7e61306dd6a786dc3d0
