{
  "id": 2315305,
  "type": "Feature",
  "properties": {
    "tgn:hierarchy":[
        "tgn:2315305",
        "tgn:1000001",
        "tgn:7012149",
        "tgn:2000892",
        "tgn:7007256",
        "tgn:7029392"
    ],
    "tgn:id":2315305,
    "tgn:name":"Elliot City",
    "tgn:placetype":[
        "aat:300008347"
    ]
},
  "bbox": [],
  "geometry": {"coordinates":[-91.6833,30.55],"type":"Point"}
}