{
  "id": 7358137,
  "type": "Feature",
  "properties": {
    "tgn:hierarchy":[
        "tgn:7358137",
        "tgn:1001835",
        "tgn:1000001",
        "tgn:7005560",
        "tgn:7029392"
    ],
    "tgn:id":7358137,
    "tgn:name":"La Puerta",
    "tgn:placetype":[
        "aat:300008347"
    ]
},
  "bbox": [],
  "geometry": {"coordinates":[-115.329444,32.325278],"type":"Point"}
}