{
  "id": 2134996,
  "type": "Feature",
  "properties": {
    "tgn:hierarchy":[
        "tgn:2134996",
        "tgn:1000001",
        "tgn:7012149",
        "tgn:2002383",
        "tgn:7007923",
        "tgn:7029392"
    ],
    "tgn:id":2134996,
    "tgn:name":"Antelope Spring",
    "tgn:placetype":[
        "aat:300008697"
    ]
},
  "bbox": [],
  "geometry": {"coordinates":[-107.5167,41.85],"type":"Point"}
}