{
  "id": 2662839,
  "type": "Feature",
  "properties": {
    "tgn:hierarchy":[
        "tgn:2662839",
        "tgn:2000496",
        "tgn:1000001",
        "tgn:7012149",
        "tgn:7007251",
        "tgn:7029392"
    ],
    "tgn:id":2662839,
    "tgn:name":"Silica Mine",
    "tgn:placetype":[
        "aat:300000390"
    ]
},
  "bbox": [],
  "geometry": {"coordinates":[-89.3333,37.1667],"type":"Point"}
}