{
  "id": 7586436,
  "type": "Feature",
  "properties": {
    "tgn:hierarchy":[
        "tgn:7586436",
        "tgn:1000004",
        "tgn:7000198",
        "tgn:7000799",
        "tgn:7029392"
    ],
    "tgn:id":7586436,
    "tgn:name:en":"Sh\u012bra Sar",
    "tgn:placetype":[
        "aat:300008688"
    ]
},
  "bbox": [],
  "geometry": {"coordinates":[74.886111,34.394444],"type":"Point"}
}