{
  "id": 2476922,
  "type": "Feature",
  "properties": {
    "tgn:hierarchy":[
        "tgn:2476922",
        "tgn:1000001",
        "tgn:7012149",
        "tgn:2001711",
        "tgn:7007708",
        "tgn:7029392"
    ],
    "tgn:id":2476922,
    "tgn:name":"Lyman Mine",
    "tgn:placetype":[
        "aat:300000390"
    ]
},
  "bbox": [],
  "geometry": {"coordinates":[-123.0167,42.4667],"type":"Point"}
}