<<<<<<< HEAD
{
  "id": 2152927,
  "type": "Feature",
  "properties": {
    "tgn:hierarchy":[
        "tgn:2152927",
        "tgn:1002232",
        "tgn:1000001",
        "tgn:7012149",
        "tgn:7007565",
        "tgn:7029392"
    ],
    "tgn:id":2152927,
    "tgn:name":"Beach Creek Meadow",
    "tgn:placetype":[
        "aat:300008905"
    ]
},
  "bbox": [],
  "geometry": {"coordinates":[-74.7833,39.0167],"type":"Point"}
}
=======
{"geometry":{"type":"Point","coordinates":[-74.783300,39.016700]},"type":"Feature","properties":{"hierarchy":["tgn:2152927","tgn:1002232","tgn:1000001","tgn:7012149","tgn:7007565","tgn:7029392"],"placetype":["aat:300008905"],"id":2152927,"name:xx":"Beach Creek Meadow"}}
>>>>>>> 03f74aca74312dbeaf24d7e61306dd6a786dc3d0
