{
  "id": 7030596,
  "type": "Feature",
  "properties": {
    "tgn:hierarchy":[
        "tgn:7030596",
        "tgn:7001242",
        "tgn:7030592",
        "tgn:1000198",
        "tgn:7029392"
    ],
    "tgn:id":7030596,
    "tgn:name":"Oponono",
    "tgn:placetype":[
        "aat:300387200"
    ]
},
  "bbox": [],
  "geometry": {"coordinates":[15.796,-19.149],"type":"Point"}
}