{
  "id": 7001468,
  "type": "Feature",
  "properties": {
    "tgn:hierarchy":[
        "tgn:7001468",
        "tgn:1000004",
        "tgn:7002077",
        "tgn:1000111",
        "tgn:7029392"
    ],
    "tgn:id":7001468,
    "tgn:name":"Anping",
    "tgn:placetype":[
        "aat:300008347",
        "aat:300008375",
        "aat:300235099"
    ]
},
  "bbox": [],
  "geometry": {"coordinates":[115.5333,38.2167],"type":"Point"}
}