{
  "id": 2298381,
  "type": "Feature",
  "properties": {
    "tgn:hierarchy":[
        "tgn:2298381",
        "tgn:1000001",
        "tgn:2001266",
        "tgn:7012149",
        "tgn:7007524",
        "tgn:7029392"
    ],
    "tgn:id":2298381,
    "tgn:name":"Dry Ridge",
    "tgn:placetype":[
        "aat:300266640"
    ]
},
  "bbox": [],
  "geometry": {"coordinates":[-110.7833,47.0667],"type":"Point"}
}