{
  "id": 2323620,
  "type": "Feature",
  "properties": {
    "tgn:hierarchy":[
        "tgn:2323620",
        "tgn:1000001",
        "tgn:7016172",
        "tgn:7012149",
        "tgn:2000140",
        "tgn:7029392"
    ],
    "tgn:id":2323620,
    "tgn:name":"Farris Springs",
    "tgn:placetype":[
        "aat:300008697"
    ]
},
  "bbox": [],
  "geometry": {"coordinates":[-93.45,35.6333],"type":"Point"}
}