{
  "id": 7443596,
  "type": "Feature",
  "properties": {
    "tgn:hierarchy":[
        "tgn:7443596",
        "tgn:7002448",
        "tgn:7019157",
        "tgn:1000003",
        "tgn:7008591",
        "tgn:7029392"
    ],
    "tgn:id":7443596,
    "tgn:name:en":"Laconia Bank",
    "tgn:placetype":[
        "aat:300386970"
    ]
},
  "bbox": [],
  "geometry": {"coordinates":[-6.416667,55.383333],"type":"Point"}
}