{
  "id": 2038970,
  "type": "Feature",
  "properties": {
    "tgn:hierarchy":[
        "tgn:2038970",
        "tgn:1000001",
        "tgn:7012149",
        "tgn:1002469",
        "tgn:7007255",
        "tgn:7029392"
    ],
    "tgn:id":2038970,
    "tgn:name":"Franklinton",
    "tgn:placetype":[
        "aat:300008347"
    ]
},
  "bbox": [],
  "geometry": {"coordinates":[-85.05,38.45],"type":"Point"}
}