{
  "id": 7186904,
  "type": "Feature",
  "properties": {
    "tgn:hierarchy":[
        "tgn:7186904",
        "tgn:1000003",
        "tgn:7003685",
        "tgn:7000084",
        "tgn:7029392"
    ],
    "tgn:id":7186904,
    "tgn:name":"G\u00f6tzh\u00f6he",
    "tgn:placetype":[
        "aat:300008777"
    ]
},
  "bbox": [],
  "geometry": {"coordinates":[13.033333,50.766667],"type":"Point"}
}