{
  "id": 2146941,
  "type": "Feature",
  "properties": {
    "tgn:hierarchy":[
        "tgn:2146941",
        "tgn:1000001",
        "tgn:1002218",
        "tgn:7012149",
        "tgn:7007157",
        "tgn:7029392"
    ],
    "tgn:id":2146941,
    "tgn:name":"Banner Mine",
    "tgn:placetype":[
        "aat:300000390"
    ]
},
  "bbox": [],
  "geometry": {"coordinates":[-121.5167,39.55],"type":"Point"}
}