{
  "id": 2325730,
  "type": "Feature",
  "properties": {
    "tgn:hierarchy":[
        "tgn:2325730",
        "tgn:1000001",
        "tgn:7012149",
        "tgn:2001706",
        "tgn:7007708",
        "tgn:7029392"
    ],
    "tgn:id":2325730,
    "tgn:name":"Field Creek",
    "tgn:placetype":[
        "aat:300008706"
    ]
},
  "bbox": [],
  "geometry": {"coordinates":[-123.0667,43.3833],"type":"Point"}
}