{
  "id": 2413104,
  "type": "Feature",
  "properties": {
    "tgn:hierarchy":[
        "tgn:2413104",
        "tgn:1000001",
        "tgn:7006451",
        "tgn:2000092",
        "tgn:7012149",
        "tgn:7029392"
    ],
    "tgn:id":2413104,
    "tgn:name":"Inner Basin",
    "tgn:placetype":[
        "aat:300386845"
    ]
},
  "bbox": [],
  "geometry": {"coordinates":[-111.65,35.3333],"type":"Point"}
}