{
  "id": 2359048,
  "type": "Feature",
  "properties": {
    "tgn:hierarchy":[
        "tgn:2359048",
        "tgn:1000001",
        "tgn:7012149",
        "tgn:7007157",
        "tgn:1002675",
        "tgn:7029392"
    ],
    "tgn:id":2359048,
    "tgn:name":"Granite Mine",
    "tgn:placetype":[
        "aat:300000390"
    ]
},
  "bbox": [],
  "geometry": {"coordinates":[-118.5167,37.65],"type":"Point"}
}