{
  "id": 7223884,
  "type": "Feature",
  "properties": {
    "tgn:hierarchy":[
        "tgn:7223884",
        "tgn:7011161",
        "tgn:7002674",
        "tgn:1000003",
        "tgn:1000074",
        "tgn:7029392"
    ],
    "tgn:id":7223884,
    "tgn:name":"Thymian\u00e1",
    "tgn:placetype":[
        "aat:300008347"
    ]
},
  "bbox": [],
  "geometry": {"coordinates":[26.133611,38.315],"type":"Point"}
}