{
  "id": 7583923,
  "type": "Feature",
  "properties": {
    "tgn:hierarchy":[
        "tgn:7583923",
        "tgn:1000004",
        "tgn:7000198",
        "tgn:1001894",
        "tgn:7029392"
    ],
    "tgn:id":7583923,
    "tgn:name:en":"Kunwarpura Protected Forest",
    "tgn:placetype":[
        "aat:300008865"
    ]
},
  "bbox": [],
  "geometry": {"coordinates":[78.9488,24.9453],"type":"Point"}
}