{
  "id": 2018801,
  "type": "Feature",
  "properties": {
    "tgn:hierarchy":[
        "tgn:2018801",
        "tgn:1000001",
        "tgn:1002200",
        "tgn:7012149",
        "tgn:7007240",
        "tgn:7029392"
    ],
    "tgn:id":2018801,
    "tgn:name":"Canova Beach",
    "tgn:placetype":[
        "aat:300008347"
    ]
},
  "bbox": [],
  "geometry": {"coordinates":[-80.5667,28.1333],"type":"Point"}
}