{
  "id": 7485174,
  "type": "Feature",
  "properties": {
    "tgn:hierarchy":[
        "tgn:7485174",
        "tgn:1000004",
        "tgn:7491221",
        "tgn:1000141",
        "tgn:7029392"
    ],
    "tgn:id":7485174,
    "tgn:name":"Zhongxing Qiao",
    "tgn:placetype":[
        "aat:300007836"
    ]
},
  "bbox": [],
  "geometry": {"coordinates":[121.283333,22.991389],"type":"Point"}
}