{
  "id": 7493896,
  "type": "Feature",
  "properties": {
    "tgn:hierarchy":[
        "tgn:7493896",
        "tgn:7468018",
        "tgn:1000004",
        "tgn:1000141",
        "tgn:7029392"
    ],
    "tgn:id":7493896,
    "tgn:name":"Dahu Guoxiao",
    "tgn:placetype":[
        "aat:300006495"
    ]
},
  "bbox": [],
  "geometry": {"coordinates":[120.620207,23.474208],"type":"Point"}
}