{
  "id": 2786015,
  "type": "Feature",
  "properties": {
    "tgn:hierarchy":[
        "tgn:2786015",
        "tgn:1000001",
        "tgn:2001419",
        "tgn:7012149",
        "tgn:7007526",
        "tgn:7029392"
    ],
    "tgn:id":2786015,
    "tgn:name":"Young Canal",
    "tgn:placetype":[
        "aat:300006075"
    ]
},
  "bbox": [],
  "geometry": {"coordinates":[-118.4167,40.2333],"type":"Point"}
}