{
  "id": 7226146,
  "type": "Feature",
  "properties": {
    "tgn:hierarchy":[
        "tgn:7226146",
        "tgn:7002741",
        "tgn:7017076",
        "tgn:1000003",
        "tgn:1000074",
        "tgn:7029392"
    ],
    "tgn:id":7226146,
    "tgn:name":"Soumali\u00e9s",
    "tgn:placetype":[
        "aat:300008777"
    ]
},
  "bbox": [],
  "geometry": {"coordinates":[22.583333,38.433333],"type":"Point"}
}