{
  "id": 2720977,
  "type": "Feature",
  "properties": {
    "tgn:hierarchy":[
        "tgn:2720977",
        "tgn:7002659",
        "tgn:1000001",
        "tgn:2000004",
        "tgn:7012149",
        "tgn:7029392"
    ],
    "tgn:id":2720977,
    "tgn:name":"Tidwell Hollow",
    "tgn:placetype":[
        "aat:300008761"
    ]
},
  "bbox": [],
  "geometry": {"coordinates":[-86.5333,33.8833],"type":"Point"}
}