{
  "id": 2231015,
  "type": "Feature",
  "properties": {
    "tgn:hierarchy":[
        "tgn:2231015",
        "tgn:1000001",
        "tgn:7012149",
        "tgn:2000203",
        "tgn:7007158",
        "tgn:7029392"
    ],
    "tgn:id":2231015,
    "tgn:name":"Cerro Ditch Number 1",
    "tgn:placetype":[
        "aat:300006075"
    ]
},
  "bbox": [],
  "geometry": {"coordinates":[-105.3667,37.1667],"type":"Point"}
}