{
  "id": 1083316,
  "type": "Feature",
  "properties": {
    "tgn:hierarchy":[
        "tgn:1083316",
        "tgn:7001433",
        "tgn:7001420",
        "tgn:1000004",
        "tgn:1000132",
        "tgn:7029392"
    ],
    "tgn:id":1083316,
    "tgn:name":"Silgarhi-Dot\u012b",
    "tgn:placetype":[
        "aat:300008347"
    ]
},
  "bbox": [],
  "geometry": {"coordinates":[80.9833,29.2667],"type":"Point"}
}