{
  "id": 2468961,
  "type": "Feature",
  "properties": {
    "tgn:hierarchy":[
        "tgn:2468961",
        "tgn:1000001",
        "tgn:1002479",
        "tgn:7012149",
        "tgn:7007240",
        "tgn:7029392"
    ],
    "tgn:id":2468961,
    "tgn:name":"Long Shoal",
    "tgn:placetype":[
        "aat:300132348"
    ]
},
  "bbox": [],
  "geometry": {"coordinates":[-82.45,27.8667],"type":"Point"}
}