{
  "id": 7254044,
  "type": "Feature",
  "properties": {
    "tgn:hierarchy":[
        "tgn:7254044",
        "tgn:7003460",
        "tgn:1000003",
        "tgn:1000063",
        "tgn:4012014",
        "tgn:7029392"
    ],
    "tgn:id":7254044,
    "tgn:name":"Spa, Eau de",
    "tgn:placetype":[
        "aat:300008699"
    ]
},
  "bbox": [],
  "geometry": {"coordinates":[5.816667,50.516667],"type":"Point"}
}