{
  "id": 7221328,
  "type": "Feature",
  "properties": {
    "tgn:hierarchy":[
        "tgn:7221328",
        "tgn:7002725",
        "tgn:7002715",
        "tgn:1000003",
        "tgn:1000074",
        "tgn:7029392"
    ],
    "tgn:id":7221328,
    "tgn:name":"Vafioch\u00f3rion",
    "tgn:placetype":[
        "aat:300008347"
    ]
},
  "bbox": [],
  "geometry": {"coordinates":[22.664167,41.010833],"type":"Point"}
}