{
  "id": 2399234,
  "type": "Feature",
  "properties": {
    "tgn:hierarchy":[
        "tgn:2399234",
        "tgn:1000001",
        "tgn:2001748",
        "tgn:7012149",
        "tgn:7007712",
        "tgn:7029392"
    ],
    "tgn:id":2399234,
    "tgn:name":"Horeb Branch",
    "tgn:placetype":[
        "aat:300008699"
    ]
},
  "bbox": [],
  "geometry": {"coordinates":[-82.2667,34.0167],"type":"Point"}
}