{
  "id": 7590118,
  "type": "Feature",
  "properties": {
    "tgn:hierarchy":[
        "tgn:7590118",
        "tgn:1000004",
        "tgn:7000198",
        "tgn:7000799",
        "tgn:7029392"
    ],
    "tgn:id":7590118,
    "tgn:name:en":"Bed\u0101r Baln\u0101l",
    "tgn:placetype":[
        "aat:300008347"
    ]
},
  "bbox": [],
  "geometry": {"coordinates":[74.270837,33.827961],"type":"Point"}
}