<<<<<<< HEAD
{
  "id": 7350287,
  "type": "Feature",
  "properties": {
    "tgn:hierarchy":[
        "tgn:7350287",
        "tgn:7005583",
        "tgn:1000001",
        "tgn:7005560",
        "tgn:7029392"
    ],
    "tgn:id":7350287,
    "tgn:name":"Biogame, Arroyo de",
    "tgn:placetype":[
        "aat:300008699"
    ]
},
  "bbox": [],
  "geometry": {"coordinates":[-105.8,25.8],"type":"Point"}
}
=======
{"geometry":{"type":"Point","coordinates":[-105.800000,25.800000]},"type":"Feature","properties":{"hierarchy":["tgn:7350287","tgn:7005583","tgn:1000001","tgn:7005560","tgn:7029392"],"placetype":["aat:300008699"],"id":7350287,"name:xx":"Biogame, Arroyo de"}}
>>>>>>> 03f74aca74312dbeaf24d7e61306dd6a786dc3d0
