<<<<<<< HEAD
{
  "id": 2333400,
  "type": "Feature",
  "properties": {
    "tgn:hierarchy":[
        "tgn:2333400",
        "tgn:1000001",
        "tgn:7012149",
        "tgn:2000960",
        "tgn:7007520",
        "tgn:7029392"
    ],
    "tgn:id":2333400,
    "tgn:name":"Foley Creek",
    "tgn:placetype":[
        "aat:300008706"
    ]
},
  "bbox": [],
  "geometry": {"coordinates":[-90.1333,46.6167],"type":"Point"}
}
=======
{"geometry":{"type":"Point","coordinates":[-90.133300,46.616700]},"type":"Feature","properties":{"hierarchy":["tgn:2333400","tgn:1000001","tgn:7012149","tgn:2000960","tgn:7007520","tgn:7029392"],"placetype":["aat:300008706"],"id":2333400,"name:xx":"Foley Creek"}}
>>>>>>> 03f74aca74312dbeaf24d7e61306dd6a786dc3d0
