{
  "id": 1083640,
  "type": "Feature",
  "properties": {
    "tgn:hierarchy":[
        "tgn:1083640",
        "tgn:6000543",
        "tgn:1000004",
        "tgn:1000133",
        "tgn:7029392"
    ],
    "tgn:id":1083640,
    "tgn:name":"Mangla",
    "tgn:placetype":[
        "aat:300008347"
    ]
},
  "bbox": [],
  "geometry": {"coordinates":[73.7333,33.15],"type":"Point"}
}