{
  "id": 2355611,
  "type": "Feature",
  "properties": {
    "tgn:hierarchy":[
        "tgn:2355611",
        "tgn:1000001",
        "tgn:7012149",
        "tgn:2002375",
        "tgn:7007923",
        "tgn:7029392"
    ],
    "tgn:id":2355611,
    "tgn:name":"Goose Creek",
    "tgn:placetype":[
        "aat:300008706"
    ]
},
  "bbox": [],
  "geometry": {"coordinates":[-105.2333,41.0667],"type":"Point"}
}