{
  "id": 2617429,
  "type": "Feature",
  "properties": {
    "tgn:hierarchy":[
        "tgn:2617429",
        "tgn:1000001",
        "tgn:7012149",
        "tgn:1002463",
        "tgn:7007826",
        "tgn:7029392"
    ],
    "tgn:id":2617429,
    "tgn:name":"Richmond Branch",
    "tgn:placetype":[
        "aat:300008699"
    ]
},
  "bbox": [],
  "geometry": {"coordinates":[-97.8333,30.05],"type":"Point"}
}