<<<<<<< HEAD
{
  "id": 2151545,
  "type": "Feature",
  "properties": {
    "tgn:hierarchy":[
        "tgn:2151545",
        "tgn:1000001",
        "tgn:2002260",
        "tgn:7012149",
        "tgn:7013961",
        "tgn:7029392"
    ],
    "tgn:id":2151545,
    "tgn:name":"Batten Run",
    "tgn:placetype":[
        "aat:300008699"
    ]
},
  "bbox": [],
  "geometry": {"coordinates":[-80.6833,39.1667],"type":"Point"}
}
=======
{"geometry":{"type":"Point","coordinates":[-80.683300,39.166700]},"type":"Feature","properties":{"hierarchy":["tgn:2151545","tgn:1000001","tgn:2002260","tgn:7012149","tgn:7013961","tgn:7029392"],"placetype":["aat:300008699"],"id":2151545,"name:xx":"Batten Run"}}
>>>>>>> 03f74aca74312dbeaf24d7e61306dd6a786dc3d0
