<<<<<<< HEAD
{
  "id": 2259207,
  "type": "Feature",
  "properties": {
    "tgn:hierarchy":[
        "tgn:2259207",
        "tgn:1000001",
        "tgn:7012149",
        "tgn:2001040",
        "tgn:7007521",
        "tgn:7029392"
    ],
    "tgn:id":2259207,
    "tgn:name":"Cottonwood Lake",
    "tgn:placetype":[
        "aat:300008680"
    ]
},
  "bbox": [],
  "geometry": {"coordinates":[-95.6667,44.6167],"type":"Point"}
}
=======
{"geometry":{"type":"Point","coordinates":[-95.666700,44.616700]},"type":"Feature","properties":{"hierarchy":["tgn:2259207","tgn:1000001","tgn:7012149","tgn:2001040","tgn:7007521","tgn:7029392"],"placetype":["aat:300008680"],"id":2259207,"name:xx":"Cottonwood Lake"}}
>>>>>>> 03f74aca74312dbeaf24d7e61306dd6a786dc3d0
