{
  "id": 2462901,
  "type": "Feature",
  "properties": {
    "tgn:hierarchy":[
        "tgn:2462901",
        "tgn:1000001",
        "tgn:7012149",
        "tgn:2000818",
        "tgn:7007255",
        "tgn:7029392"
    ],
    "tgn:id":2462901,
    "tgn:name":"Litton Branch",
    "tgn:placetype":[
        "aat:300008699"
    ]
},
  "bbox": [],
  "geometry": {"coordinates":[-84.2833,36.6167],"type":"Point"}
}