{
  "id": 7278430,
  "type": "Feature",
  "properties": {
    "tgn:hierarchy":[
        "tgn:7278430",
        "tgn:1001702",
        "tgn:1000049",
        "tgn:1000002",
        "tgn:7029392"
    ],
    "tgn:id":7278430,
    "tgn:name":"Fondeadero Sutlej",
    "tgn:placetype":[
        "aat:300386968"
    ]
},
  "bbox": [],
  "geometry": {"coordinates":[-68.666667,-52.583333],"type":"Point"}
}