{
  "id": 2741616,
  "type": "Feature",
  "properties": {
    "tgn:hierarchy":[
        "tgn:2741616",
        "tgn:1000001",
        "tgn:7012149",
        "tgn:2002268",
        "tgn:7013961",
        "tgn:7029392"
    ],
    "tgn:id":2741616,
    "tgn:name":"Utah Hill",
    "tgn:placetype":[
        "aat:300008798"
    ]
},
  "bbox": [],
  "geometry": {"coordinates":[-81.7167,38.9667],"type":"Point"}
}