{
  "id": 2369514,
  "type": "Feature",
  "properties": {
    "tgn:hierarchy":[
        "tgn:2369514",
        "tgn:1000001",
        "tgn:7012149",
        "tgn:2001543",
        "tgn:7007709",
        "tgn:7029392"
    ],
    "tgn:id":2369514,
    "tgn:name":"Gunlock Ridge",
    "tgn:placetype":[
        "aat:300266640"
    ]
},
  "bbox": [],
  "geometry": {"coordinates":[-83.6667,35.4833],"type":"Point"}
}