{
  "id": 2166070,
  "type": "Feature",
  "properties": {
    "tgn:hierarchy":[
        "tgn:2166070",
        "tgn:1000001",
        "tgn:7012149",
        "tgn:1002564",
        "tgn:7007710",
        "tgn:7029392"
    ],
    "tgn:id":2166070,
    "tgn:name":"Big Bass Lake",
    "tgn:placetype":[
        "aat:300006191"
    ]
},
  "bbox": [],
  "geometry": {"coordinates":[-75.4833,41.25],"type":"Point"}
}