{
  "id": 2536548,
  "type": "Feature",
  "properties": {
    "tgn:hierarchy":[
        "tgn:2536548",
        "tgn:7002659",
        "tgn:1000001",
        "tgn:7012149",
        "tgn:2000035",
        "tgn:7029392"
    ],
    "tgn:id":2536548,
    "tgn:name":"Near Halfshot Cave",
    "tgn:placetype":[
        "aat:300008746"
    ]
},
  "bbox": [],
  "geometry": {"coordinates":[-86.3333,34.6667],"type":"Point"}
}