{
  "id": 7324125,
  "type": "Feature",
  "properties": {
    "tgn:hierarchy":[
        "tgn:7324125",
        "tgn:7002808",
        "tgn:7030216",
        "tgn:1000003",
        "tgn:1000095",
        "tgn:7029392"
    ],
    "tgn:id":7324125,
    "tgn:name":"San Pedro de Ribas",
    "tgn:placetype":[
        "aat:300008347"
    ]
},
  "bbox": [],
  "geometry": {"coordinates":[1.772075,41.26126],"type":"Point"}
}