{
  "id": 2315643,
  "type": "Feature",
  "properties": {
    "tgn:hierarchy":[
        "tgn:2315643",
        "tgn:1000001",
        "tgn:1002724",
        "tgn:7012149",
        "tgn:7007517",
        "tgn:7029392"
    ],
    "tgn:id":2315643,
    "tgn:name":"Ellis Pond",
    "tgn:placetype":[
        "aat:300006191"
    ]
},
  "bbox": [],
  "geometry": {"coordinates":[-71.2167,42.1667],"type":"Point"}
}