{
  "id": 7046918,
  "type": "Feature",
  "properties": {
    "tgn:hierarchy":[
        "tgn:7046918",
        "tgn:7002991",
        "tgn:1000003",
        "tgn:7002997",
        "tgn:1000080",
        "tgn:7029392"
    ],
    "tgn:id":7046918,
    "tgn:name":"Cascina Rin de Mera",
    "tgn:placetype":[
        "aat:300008347"
    ]
},
  "bbox": [],
  "geometry": {"coordinates":[12.516667,46.483333],"type":"Point"}
}