{
  "id": 1088577,
  "type": "Feature",
  "properties": {
    "tgn:hierarchy":[
        "tgn:1088577",
        "tgn:7001242",
        "tgn:7016848",
        "tgn:1000156",
        "tgn:7029392"
    ],
    "tgn:id":1088577,
    "tgn:name":"T\u00e9dji",
    "tgn:placetype":[
        "aat:300008347"
    ]
},
  "bbox": [],
  "geometry": {"coordinates":[21.45,11.7833],"type":"Point"}
}