{
  "id": 2404166,
  "type": "Feature",
  "properties": {
    "tgn:hierarchy":[
        "tgn:2404166",
        "tgn:7006450",
        "tgn:1000001",
        "tgn:7012149",
        "tgn:2000089",
        "tgn:7029392"
    ],
    "tgn:id":2404166,
    "tgn:name":"Howling Dog Canyon",
    "tgn:placetype":[
        "aat:300008761"
    ]
},
  "bbox": [],
  "geometry": {"coordinates":[-141.6667,67.15],"type":"Point"}
}