{
  "id": 2359983,
  "type": "Feature",
  "properties": {
    "tgn:hierarchy":[
        "tgn:2359983",
        "tgn:1000001",
        "tgn:7012149",
        "tgn:2001706",
        "tgn:7007708",
        "tgn:7029392"
    ],
    "tgn:id":2359983,
    "tgn:name":"Grass Creek",
    "tgn:placetype":[
        "aat:300008706"
    ]
},
  "bbox": [],
  "geometry": {"coordinates":[-122.7167,43.3667],"type":"Point"}
}