{
  "id": 2001481,
  "type": "Feature",
  "properties": {
    "tgn:hierarchy":[
        "tgn:2001481",
        "tgn:1000001",
        "tgn:7012149",
        "tgn:7007709",
        "tgn:7029392"
    ],
    "tgn:id":2001481,
    "tgn:name":"Cherokee",
    "tgn:placetype":[
        "aat:300387145",
        "aat:300000771"
    ]
},
  "bbox": [],
  "geometry": {"coordinates":[-84.0333,35.15],"type":"Point"}
}