{
  "id": 2655822,
  "type": "Feature",
  "properties": {
    "tgn:hierarchy":[
        "tgn:2655822",
        "tgn:1000001",
        "tgn:7012149",
        "tgn:2002194",
        "tgn:7007919",
        "tgn:7029392"
    ],
    "tgn:id":2655822,
    "tgn:name":"Shavers Cave",
    "tgn:placetype":[
        "aat:300008746"
    ]
},
  "bbox": [],
  "geometry": {"coordinates":[-82.2333,36.6333],"type":"Point"}
}