{
  "id": 7411284,
  "type": "Feature",
  "properties": {
    "tgn:hierarchy":[
        "tgn:7411284",
        "tgn:7005580",
        "tgn:1000001",
        "tgn:7005560",
        "tgn:7029392"
    ],
    "tgn:id":7411284,
    "tgn:name":"Tiemopa",
    "tgn:placetype":[
        "aat:300008347"
    ]
},
  "bbox": [],
  "geometry": {"coordinates":[-92.183333,17.416667],"type":"Point"}
}