{
  "id": 7175558,
  "type": "Feature",
  "properties": {
    "tgn:hierarchy":[
        "tgn:7175558",
        "tgn:1000003",
        "tgn:7003676",
        "tgn:7000084",
        "tgn:7029392"
    ],
    "tgn:id":7175558,
    "tgn:name":"Gries-Berg",
    "tgn:placetype":[
        "aat:300008777"
    ]
},
  "bbox": [],
  "geometry": {"coordinates":[9.966667,52.066667],"type":"Point"}
}