{
  "id": 7538710,
  "type": "Feature",
  "properties": {
    "tgn:hierarchy":[
        "tgn:7538710",
        "tgn:7001242",
        "tgn:7016833",
        "tgn:1001418",
        "tgn:7029392"
    ],
    "tgn:id":7538710,
    "tgn:name:en":"Niqd, 'Alam el",
    "tgn:placetype":[
        "aat:300008777"
    ]
},
  "bbox": [],
  "geometry": {"coordinates":[26.335315,30.959403],"type":"Point"}
}