{
  "id": 2478940,
  "type": "Feature",
  "properties": {
    "tgn:hierarchy":[
        "tgn:2478940",
        "tgn:1000001",
        "tgn:7012149",
        "tgn:2000491",
        "tgn:7007250",
        "tgn:7029392"
    ],
    "tgn:id":2478940,
    "tgn:name":"Magee Peak",
    "tgn:placetype":[
        "aat:300008798"
    ]
},
  "bbox": [],
  "geometry": {"coordinates":[-116.2833,47.8667],"type":"Point"}
}