{
  "id": 2761027,
  "type": "Feature",
  "properties": {
    "tgn:hierarchy":[
        "tgn:2761027",
        "tgn:1000001",
        "tgn:7016172",
        "tgn:2000115",
        "tgn:7012149",
        "tgn:7029392"
    ],
    "tgn:id":2761027,
    "tgn:name":"West Kennett",
    "tgn:placetype":[
        "aat:300008347"
    ]
},
  "bbox": [],
  "geometry": {"coordinates":[-90.1167,36.25],"type":"Point"}
}