{
  "id": 2378801,
  "type": "Feature",
  "properties": {
    "tgn:hierarchy":[
        "tgn:2378801",
        "tgn:1000001",
        "tgn:7012149",
        "tgn:2000435",
        "tgn:7007248",
        "tgn:7029392"
    ],
    "tgn:id":2378801,
    "tgn:name":"Hart Cove",
    "tgn:placetype":[
        "aat:300132316"
    ]
},
  "bbox": [],
  "geometry": {"coordinates":[-84.1167,34.8167],"type":"Point"}
}