{
  "id": 2538865,
  "type": "Feature",
  "properties": {
    "tgn:hierarchy":[
        "tgn:2538865",
        "tgn:1000001",
        "tgn:2001945",
        "tgn:7012149",
        "tgn:7007826",
        "tgn:7029392"
    ],
    "tgn:id":2538865,
    "tgn:name":"Neville Spring",
    "tgn:placetype":[
        "aat:300008697"
    ]
},
  "bbox": [],
  "geometry": {"coordinates":[-103.1833,29.3667],"type":"Point"}
}