{
  "id": 2755911,
  "type": "Feature",
  "properties": {
    "tgn:hierarchy":[
        "tgn:2755911",
        "tgn:1000001",
        "tgn:7012149",
        "tgn:7007525",
        "tgn:7029392"
    ],
    "tgn:id":2755911,
    "tgn:name":"Weeping Water Creek",
    "tgn:placetype":[
        "aat:300008706"
    ]
},
  "bbox": [],
  "geometry": {"coordinates":[-96.3833,40.85],"type":"Point"}
}