<<<<<<< HEAD
{
  "id": 2153702,
  "type": "Feature",
  "properties": {
    "tgn:hierarchy":[
        "tgn:2153702",
        "tgn:1000001",
        "tgn:7012149",
        "tgn:1002578",
        "tgn:7007826",
        "tgn:7029392"
    ],
    "tgn:id":2153702,
    "tgn:name":"Bear Branch",
    "tgn:placetype":[
        "aat:300008699"
    ]
},
  "bbox": [],
  "geometry": {"coordinates":[-96.9167,29.1833],"type":"Point"}
}
=======
{"geometry":{"type":"Point","coordinates":[-96.916700,29.183300]},"type":"Feature","properties":{"hierarchy":["tgn:2153702","tgn:1000001","tgn:7012149","tgn:1002578","tgn:7007826","tgn:7029392"],"placetype":["aat:300008699"],"id":2153702,"name:xx":"Bear Branch"}}
>>>>>>> 03f74aca74312dbeaf24d7e61306dd6a786dc3d0
