{
  "id": 2153702,
  "type": "Feature",
  "properties": {
    "tgn:hierarchy":[
        "tgn:2153702",
        "tgn:1000001",
        "tgn:7012149",
        "tgn:1002578",
        "tgn:7007826",
        "tgn:7029392"
    ],
    "tgn:id":2153702,
    "tgn:name":"Bear Branch",
    "tgn:placetype":[
        "aat:300008699"
    ]
},
  "bbox": [],
  "geometry": {"coordinates":[-96.9167,29.1833],"type":"Point"}
}