<<<<<<< HEAD
{
  "id": 7357766,
  "type": "Feature",
  "properties": {
    "tgn:hierarchy":[
        "tgn:7357766",
        "tgn:7005581",
        "tgn:1000001",
        "tgn:7005560",
        "tgn:7029392"
    ],
    "tgn:id":7357766,
    "tgn:name":"Colonia Cuauht\u00e9moc",
    "tgn:placetype":[
        "aat:300008347"
    ]
},
  "bbox": [],
  "geometry": {"coordinates":[-108.05,30.283333],"type":"Point"}
}
=======
{"geometry":{"type":"Point","coordinates":[-108.050000,30.283333]},"type":"Feature","properties":{"hierarchy":["tgn:7357766","tgn:7005581","tgn:1000001","tgn:7005560","tgn:7029392"],"placetype":["aat:300008347"],"id":7357766,"name:xx":"Colonia Cuauht\u00e9moc"}}
>>>>>>> 03f74aca74312dbeaf24d7e61306dd6a786dc3d0
