{
  "id": 7167156,
  "type": "Feature",
  "properties": {
    "tgn:hierarchy":[
        "tgn:7167156",
        "tgn:7003669",
        "tgn:1000003",
        "tgn:7000084",
        "tgn:7029392"
    ],
    "tgn:id":7167156,
    "tgn:name":"Haunst\u00e4dter Bach",
    "tgn:placetype":[
        "aat:300008699"
    ]
},
  "bbox": [],
  "geometry": {"coordinates":[11.45,48.783333],"type":"Point"}
}