{
  "id": 1011887,
  "type": "Feature",
  "properties": {
    "tgn:hierarchy":[
        "tgn:1011887",
        "tgn:7002445",
        "tgn:1000003",
        "tgn:7012077",
        "tgn:7008591",
        "tgn:7029392"
    ],
    "tgn:id":1011887,
    "tgn:name":"Foreland Point",
    "tgn:placetype":[
        "aat:300386846"
    ]
},
  "bbox": [],
  "geometry": {"coordinates":[-3.7833,51.2667],"type":"Point"}
}