{
  "id": 7318352,
  "type": "Feature",
  "properties": {
    "tgn:hierarchy":[
        "tgn:7318352",
        "tgn:1001623",
        "tgn:1000049",
        "tgn:1000002",
        "tgn:7029392"
    ],
    "tgn:id":7318352,
    "tgn:name":"Colorada, Isla",
    "tgn:placetype":[
        "aat:300008791"
    ]
},
  "bbox": [],
  "geometry": {"coordinates":[-73.366667,-45.35],"type":"Point"}
}