{
  "id": 7592359,
  "type": "Feature",
  "properties": {
    "tgn:hierarchy":[
        "tgn:7592359",
        "tgn:1000004",
        "tgn:7000198",
        "tgn:7016722",
        "tgn:7029392"
    ],
    "tgn:id":7592359,
    "tgn:name:en":"Ism\u0101ilpur",
    "tgn:placetype":[
        "aat:300008347"
    ]
},
  "bbox": [],
  "geometry": {"coordinates":[77.811054,30.108722],"type":"Point"}
}