{
  "id": 7260152,
  "type": "Feature",
  "properties": {
    "tgn:hierarchy":[
        "tgn:7260152",
        "tgn:7003619",
        "tgn:1000003",
        "tgn:7016845",
        "tgn:7029392"
    ],
    "tgn:id":7260152,
    "tgn:name:nl":"Boswachterij Gortel",
    "tgn:placetype":[
        "aat:300008187"
    ]
},
  "bbox": [],
  "geometry": {"coordinates":[5.883333,52.316667],"type":"Point"}
}