{
  "id": 1080109,
  "type": "Feature",
  "properties": {
    "tgn:hierarchy":[
        "tgn:1080109",
        "tgn:1000971",
        "tgn:1000004",
        "tgn:7000894",
        "tgn:1000120",
        "tgn:7029392"
    ],
    "tgn:id":1080109,
    "tgn:name":"Hikarigaoka",
    "tgn:placetype":[
        "aat:300008347"
    ]
},
  "bbox": [],
  "geometry": {"coordinates":[139.9667,35.8333],"type":"Point"}
}