{
  "id": 2442506,
  "type": "Feature",
  "properties": {
    "tgn:hierarchy":[
        "tgn:2442506",
        "tgn:1000001",
        "tgn:7012149",
        "tgn:1002742",
        "tgn:7007920",
        "tgn:7029392"
    ],
    "tgn:id":2442506,
    "tgn:name":"Kruger Mountian",
    "tgn:placetype":[
        "aat:300008798"
    ]
},
  "bbox": [],
  "geometry": {"coordinates":[-119.4833,48.9833],"type":"Point"}
}