{
  "id": 1051415,
  "type": "Feature",
  "properties": {
    "tgn:hierarchy":[
        "tgn:1051415",
        "tgn:1000004",
        "tgn:1003377",
        "tgn:7018214",
        "tgn:7002435",
        "tgn:7029392"
    ],
    "tgn:id":1051415,
    "tgn:name":"\u010cornaja Gr'az'",
    "tgn:placetype":[
        "aat:300008347"
    ]
},
  "bbox": [],
  "geometry": {"coordinates":[35.8667,54.5167],"type":"Point"}
}