{
  "id": 7490483,
  "type": "Feature",
  "properties": {
    "tgn:hierarchy":[
        "tgn:7490483",
        "tgn:1000004",
        "tgn:1000454",
        "tgn:1000141",
        "tgn:7029392"
    ],
    "tgn:id":7490483,
    "tgn:name":"Daxiqian Xi",
    "tgn:placetype":[
        "aat:300008699"
    ]
},
  "bbox": [],
  "geometry": {"coordinates":[121.65,25.016667],"type":"Point"}
}