{
  "id": 2043346,
  "type": "Feature",
  "properties": {
    "tgn:hierarchy":[
        "tgn:2043346",
        "tgn:1000001",
        "tgn:2000863",
        "tgn:7012149",
        "tgn:7007256",
        "tgn:7029392"
    ],
    "tgn:id":2043346,
    "tgn:name":"Lucas",
    "tgn:placetype":[
        "aat:300387016"
    ]
},
  "bbox": [],
  "geometry": {"coordinates":[-93.55,30.3667],"type":"Point"}
}