{
  "id": 7577801,
  "type": "Feature",
  "properties": {
    "tgn:hierarchy":[
        "tgn:7577801",
        "tgn:1000004",
        "tgn:7000198",
        "tgn:7001797",
        "tgn:7029392"
    ],
    "tgn:id":7577801,
    "tgn:name:en":"K\u016blip\u0101laiyam",
    "tgn:placetype":[
        "aat:300007783"
    ]
},
  "bbox": [],
  "geometry": {"coordinates":[77.416667,11.15],"type":"Point"}
}