{
  "id": 7325911,
  "type": "Feature",
  "properties": {
    "tgn:hierarchy":[
        "tgn:7325911",
        "tgn:7002811",
        "tgn:1000003",
        "tgn:7003837",
        "tgn:1000095",
        "tgn:7029392"
    ],
    "tgn:id":7325911,
    "tgn:name":"San L\u00e1zaro, Estanque de",
    "tgn:placetype":[
        "aat:300008688"
    ]
},
  "bbox": [],
  "geometry": {"coordinates":[-5.866667,39.45],"type":"Point"}
}