{
  "id": 7013296,
  "type": "Feature",
  "properties": {
    "tgn:hierarchy":[
        "tgn:7013296",
        "tgn:1000001",
        "tgn:7013686",
        "tgn:7012149",
        "tgn:7007517",
        "tgn:7029392"
    ],
    "tgn:id":7013296,
    "tgn:name":"Amherst",
    "tgn:placetype":[
        "aat:300008347",
        "aat:300387308",
        "aat:300264742",
        "aat:300008375"
    ]
},
  "bbox": [],
  "geometry": {"coordinates":[-72.5167,42.3667],"type":"Point"}
}