{
  "id": 2139394,
  "type": "Feature",
  "properties": {
    "tgn:hierarchy":[
        "tgn:2139394",
        "tgn:1000001",
        "tgn:7012149",
        "tgn:2000208",
        "tgn:7007158",
        "tgn:7029392"
    ],
    "tgn:id":2139394,
    "tgn:name":"Aspen Reservoir",
    "tgn:placetype":[
        "aat:300006191"
    ]
},
  "bbox": [],
  "geometry": {"coordinates":[-108.2667,37.7167],"type":"Point"}
}