{
  "id": 2347399,
  "type": "Feature",
  "properties": {
    "tgn:hierarchy":[
        "tgn:2347399",
        "tgn:1000001",
        "tgn:7012149",
        "tgn:2001503",
        "tgn:7007709",
        "tgn:7029392"
    ],
    "tgn:id":2347399,
    "tgn:name":"George Ira Creek",
    "tgn:placetype":[
        "aat:300008706"
    ]
},
  "bbox": [],
  "geometry": {"coordinates":[-83.15,35.5667],"type":"Point"}
}