{
  "id": 7016028,
  "type": "Feature",
  "properties": {
    "tgn:hierarchy":[
        "tgn:7016028",
        "tgn:7006450",
        "tgn:1000001",
        "tgn:7012149",
        "tgn:2000082",
        "tgn:7019648",
        "tgn:7029392"
    ],
    "tgn:id":7016028,
    "tgn:name":"Craig",
    "tgn:placetype":[
        "aat:300008347",
        "aat:300008375"
    ]
},
  "bbox": [],
  "geometry": {"coordinates":[-133.1333,55.4667],"type":"Point"}
}