{
  "id": 2452091,
  "type": "Feature",
  "properties": {
    "tgn:hierarchy":[
        "tgn:2452091",
        "tgn:1000001",
        "tgn:7012149",
        "tgn:1002612",
        "tgn:7007710",
        "tgn:7029392"
    ],
    "tgn:id":2452091,
    "tgn:name":"Little Black Creek",
    "tgn:placetype":[
        "aat:300008706"
    ]
},
  "bbox": [],
  "geometry": {"coordinates":[-75.9333,40.9833],"type":"Point"}
}