{
  "id": 7076506,
  "type": "Feature",
  "properties": {
    "tgn:hierarchy":[
        "tgn:7076506",
        "tgn:7003692",
        "tgn:1000003",
        "tgn:7000084",
        "tgn:7029392"
    ],
    "tgn:id":7076506,
    "tgn:name":"Wittighausen",
    "tgn:placetype":[
        "aat:300387173"
    ]
},
  "bbox": [],
  "geometry": {"coordinates":[9.842222,49.619167],"type":"Point"}
}