{
  "id": 2767544,
  "type": "Feature",
  "properties": {
    "tgn:hierarchy":[
        "tgn:2767544",
        "tgn:1000001",
        "tgn:7012149",
        "tgn:2000892",
        "tgn:7007256",
        "tgn:7029392"
    ],
    "tgn:id":2767544,
    "tgn:name":"White Vine, Bayou",
    "tgn:placetype":[
        "aat:300008699"
    ]
},
  "bbox": [],
  "geometry": {"coordinates":[-91.6167,30.8167],"type":"Point"}
}