{
  "id": 2609660,
  "type": "Feature",
  "properties": {
    "tgn:hierarchy":[
        "tgn:2609660",
        "tgn:1000001",
        "tgn:2001418",
        "tgn:7012149",
        "tgn:7007526",
        "tgn:7029392"
    ],
    "tgn:id":2609660,
    "tgn:name":"Razorback Ridge",
    "tgn:placetype":[
        "aat:300266640"
    ]
},
  "bbox": [],
  "geometry": {"coordinates":[-116.6833,36.8667],"type":"Point"}
}