{
  "id": 7168850,
  "type": "Feature",
  "properties": {
    "tgn:hierarchy":[
        "tgn:7168850",
        "tgn:1000003",
        "tgn:7003682",
        "tgn:7000084",
        "tgn:7029392"
    ],
    "tgn:id":7168850,
    "tgn:name":"Heilbach",
    "tgn:placetype":[
        "aat:300008347"
    ]
},
  "bbox": [],
  "geometry": {"coordinates":[6.283333,50.05],"type":"Point"}
}