<<<<<<< HEAD
{
  "id": 7021587,
  "type": "Feature",
  "properties": {
    "tgn:hierarchy":[
        "tgn:7021587",
        "tgn:1000001",
        "tgn:7012149",
        "tgn:2001612",
        "tgn:7007706",
        "tgn:7029392"
    ],
    "tgn:id":7021587,
    "tgn:name":"Big Creek",
    "tgn:placetype":[
        "aat:300008706"
    ]
},
  "bbox": [],
  "geometry": {"coordinates":[-82.2667,38.6167],"type":"Point"}
}
=======
{"geometry":{"type":"Point","coordinates":[-82.266700,38.616700]},"type":"Feature","properties":{"hierarchy":["tgn:7021587","tgn:1000001","tgn:7012149","tgn:2001612","tgn:7007706","tgn:7029392"],"placetype":["aat:300008706"],"id":7021587,"name:xx":"Big Creek"}}
>>>>>>> 03f74aca74312dbeaf24d7e61306dd6a786dc3d0
