{
  "id": 2455462,
  "type": "Feature",
  "properties": {
    "tgn:hierarchy":[
        "tgn:2455462",
        "tgn:1000001",
        "tgn:2000772",
        "tgn:7012149",
        "tgn:7007255",
        "tgn:7029392"
    ],
    "tgn:id":2455462,
    "tgn:name":"Little Frozen Creek",
    "tgn:placetype":[
        "aat:300008706"
    ]
},
  "bbox": [],
  "geometry": {"coordinates":[-83.4333,37.6333],"type":"Point"}
}