{
  "id": 7160801,
  "type": "Feature",
  "properties": {
    "tgn:hierarchy":[
        "tgn:7160801",
        "tgn:7003669",
        "tgn:1000003",
        "tgn:7000084",
        "tgn:7029392"
    ],
    "tgn:id":7160801,
    "tgn:name":"H\u00f6hen-Berg",
    "tgn:placetype":[
        "aat:300008777"
    ]
},
  "bbox": [],
  "geometry": {"coordinates":[11.283333,47.716667],"type":"Point"}
}