{
  "id": 2285571,
  "type": "Feature",
  "properties": {
    "tgn:hierarchy":[
        "tgn:2285571",
        "tgn:1000001",
        "tgn:7012149",
        "tgn:7007157",
        "tgn:1002706",
        "tgn:7029392"
    ],
    "tgn:id":2285571,
    "tgn:name":"Devils Head Peak",
    "tgn:placetype":[
        "aat:300008798"
    ]
},
  "bbox": [],
  "geometry": {"coordinates":[-122.3833,38.7333],"type":"Point"}
}