<<<<<<< HEAD
{
  "id": 7372564,
  "type": "Feature",
  "properties": {
    "tgn:hierarchy":[
        "tgn:7372564",
        "tgn:1000001",
        "tgn:1001960",
        "tgn:7005560",
        "tgn:7029392"
    ],
    "tgn:id":7372564,
    "tgn:name":"La Norte",
    "tgn:placetype":[
        "aat:300008347"
    ]
},
  "bbox": [],
  "geometry": {"coordinates":[-111.65,28.633333],"type":"Point"}
}
=======
{"geometry":{"type":"Point","coordinates":[-111.650000,28.633333]},"type":"Feature","properties":{"hierarchy":["tgn:7372564","tgn:1000001","tgn:1001960","tgn:7005560","tgn:7029392"],"placetype":["aat:300008347"],"id":7372564,"name:xx":"La Norte"}}
>>>>>>> 03f74aca74312dbeaf24d7e61306dd6a786dc3d0
