{
  "id": 2777862,
  "type": "Feature",
  "properties": {
    "tgn:hierarchy":[
        "tgn:2777862",
        "tgn:1000001",
        "tgn:7012149",
        "tgn:7021313",
        "tgn:7007521",
        "tgn:7029392"
    ],
    "tgn:id":2777862,
    "tgn:name":"Winter Road Lake",
    "tgn:placetype":[
        "aat:300008680"
    ]
},
  "bbox": [],
  "geometry": {"coordinates":[-95.0333,48.6833],"type":"Point"}
}