{
  "id": 2648772,
  "type": "Feature",
  "properties": {
    "tgn:hierarchy":[
        "tgn:2648772",
        "tgn:1000001",
        "tgn:7012149",
        "tgn:1002440",
        "tgn:7007568",
        "tgn:7029392"
    ],
    "tgn:id":2648772,
    "tgn:name":"Scotch Lake",
    "tgn:placetype":[
        "aat:300008680"
    ]
},
  "bbox": [],
  "geometry": {"coordinates":[-74.55,43.45],"type":"Point"}
}