<<<<<<< HEAD
{
  "id": 2407352,
  "type": "Feature",
  "properties": {
    "tgn:hierarchy":[
        "tgn:2407352",
        "tgn:1000001",
        "tgn:1002712",
        "tgn:7012149",
        "tgn:7007159",
        "tgn:7029392"
    ],
    "tgn:id":2407352,
    "tgn:name":"Huntington Hill",
    "tgn:placetype":[
        "aat:300008798"
    ]
},
  "bbox": [],
  "geometry": {"coordinates":[-73.0667,41.4667],"type":"Point"}
}
=======
{"geometry":{"type":"Point","coordinates":[-73.066700,41.466700]},"type":"Feature","properties":{"hierarchy":["tgn:2407352","tgn:1000001","tgn:1002712","tgn:7012149","tgn:7007159","tgn:7029392"],"placetype":["aat:300008798"],"id":2407352,"name:xx":"Huntington Hill"}}
>>>>>>> 03f74aca74312dbeaf24d7e61306dd6a786dc3d0
