{
  "id": 1065014,
  "type": "Feature",
  "properties": {
    "tgn:hierarchy":[
        "tgn:1065014",
        "tgn:1000003",
        "tgn:7006669",
        "tgn:7029392"
    ],
    "tgn:id":1065014,
    "tgn:name":"Grdelica",
    "tgn:placetype":[
        "aat:300008347"
    ]
},
  "bbox": [],
  "geometry": {"coordinates":[22.05,42.9167],"type":"Point"}
}