{
  "id": 2432581,
  "type": "Feature",
  "properties": {
    "tgn:hierarchy":[
        "tgn:2432581",
        "tgn:1000001",
        "tgn:7012149",
        "tgn:2002359",
        "tgn:7007922",
        "tgn:7029392"
    ],
    "tgn:id":2432581,
    "tgn:name":"Keego Lake",
    "tgn:placetype":[
        "aat:300008680"
    ]
},
  "bbox": [],
  "geometry": {"coordinates":[-89.7333,46.15],"type":"Point"}
}