{
  "id": 7036190,
  "type": "Feature",
  "properties": {
    "tgn:hierarchy":[
        "tgn:7036190",
        "tgn:7002996",
        "tgn:1000003",
        "tgn:7002997",
        "tgn:1000080",
        "tgn:7029392"
    ],
    "tgn:id":7036190,
    "tgn:name":"Padernello",
    "tgn:placetype":[
        "aat:300008347"
    ]
},
  "bbox": [],
  "geometry": {"coordinates":[12.121667,45.684722],"type":"Point"}
}