{
  "id": 1027040,
  "type": "Feature",
  "properties": {
    "tgn:hierarchy":[
        "tgn:1027040",
        "tgn:1003523",
        "tgn:1000003",
        "tgn:1001780",
        "tgn:7029392"
    ],
    "tgn:id":1027040,
    "tgn:name":"\u0160titary",
    "tgn:placetype":[
        "aat:300008347"
    ]
},
  "bbox": [],
  "geometry": {"coordinates":[15.85,48.9333],"type":"Point"}
}