<<<<<<< HEAD
{
  "id": 7470583,
  "type": "Feature",
  "properties": {
    "tgn:hierarchy":[
        "tgn:7470583",
        "tgn:1000004",
        "tgn:7490934",
        "tgn:1000141",
        "tgn:7029392"
    ],
    "tgn:id":7470583,
    "tgn:name":"Xigang",
    "tgn:placetype":[
        "aat:300008347"
    ]
},
  "bbox": [],
  "geometry": {"coordinates":[120.204167,23.1225],"type":"Point"}
}
=======
{"geometry":{"type":"Point","coordinates":[120.204167,23.122500]},"type":"Feature","properties":{"hierarchy":["tgn:7470583","tgn:1000004","tgn:7490934","tgn:1000141","tgn:7029392"],"placetype":["aat:300008347"],"id":7470583,"name:xx":"Xigang"}}
>>>>>>> 03f74aca74312dbeaf24d7e61306dd6a786dc3d0
