{
  "id": 2428701,
  "type": "Feature",
  "properties": {
    "tgn:hierarchy":[
        "tgn:2428701",
        "tgn:1000001",
        "tgn:7012149",
        "tgn:7007157",
        "tgn:2000185",
        "tgn:7029392"
    ],
    "tgn:id":2428701,
    "tgn:name":"Julias Creek",
    "tgn:placetype":[
        "aat:300008706"
    ]
},
  "bbox": [],
  "geometry": {"coordinates":[-123.7833,39.85],"type":"Point"}
}