{
  "id": 2471832,
  "type": "Feature",
  "properties": {
    "tgn:hierarchy":[
        "tgn:2471832",
        "tgn:1000001",
        "tgn:7006451",
        "tgn:2000094",
        "tgn:7012149",
        "tgn:7029392"
    ],
    "tgn:id":2471832,
    "tgn:name":"Lost Spring",
    "tgn:placetype":[
        "aat:300008697"
    ]
},
  "bbox": [],
  "geometry": {"coordinates":[-109.8667,33.3833],"type":"Point"}
}