{
  "id": 7327097,
  "type": "Feature",
  "properties": {
    "tgn:hierarchy":[
        "tgn:7327097",
        "tgn:7001158",
        "tgn:7002850",
        "tgn:1000003",
        "tgn:1000095",
        "tgn:7029392"
    ],
    "tgn:id":7327097,
    "tgn:name":"Parada, Arroyo",
    "tgn:placetype":[
        "aat:300008699"
    ]
},
  "bbox": [],
  "geometry": {"coordinates":[-6.716667,42.033333],"type":"Point"}
}