{
  "id": 7589900,
  "type": "Feature",
  "properties": {
    "tgn:hierarchy":[
        "tgn:7589900",
        "tgn:1000004",
        "tgn:1001871",
        "tgn:7000198",
        "tgn:7029392"
    ],
    "tgn:id":7589900,
    "tgn:name:en":"Samaura Jh\u012bl",
    "tgn:placetype":[
        "aat:300008905"
    ]
},
  "bbox": [],
  "geometry": {"coordinates":[77.013566,29.817994],"type":"Point"}
}