{
  "id": 1077765,
  "type": "Feature",
  "properties": {
    "tgn:hierarchy":[
        "tgn:1077765",
        "tgn:1000004",
        "tgn:1001555",
        "tgn:1000116",
        "tgn:7029392"
    ],
    "tgn:id":1077765,
    "tgn:name":"Kabanjahe",
    "tgn:placetype":[
        "aat:300008347"
    ]
},
  "bbox": [],
  "geometry": {"coordinates":[98.4333,3.0333],"type":"Point"}
}