{
  "id": 2096093,
  "type": "Feature",
  "properties": {
    "tgn:hierarchy":[
        "tgn:2096093",
        "tgn:2001732",
        "tgn:1000001",
        "tgn:7012149",
        "tgn:7007712",
        "tgn:7029392"
    ],
    "tgn:id":2096093,
    "tgn:name":"Kittredge",
    "tgn:placetype":[
        "aat:300008347",
        "aat:300387210"
    ]
},
  "bbox": [],
  "geometry": {"coordinates":[-79.9667,33.0667],"type":"Point"}
}