{
  "id": 7340508,
  "type": "Feature",
  "properties": {
    "tgn:hierarchy":[
        "tgn:7340508",
        "tgn:7002805",
        "tgn:7002758",
        "tgn:1000003",
        "tgn:1000095",
        "tgn:7029392"
    ],
    "tgn:id":7340508,
    "tgn:name":"Casablanca",
    "tgn:placetype":[
        "aat:300008347"
    ]
},
  "bbox": [],
  "geometry": {"coordinates":[-2.683333,36.816667],"type":"Point"}
}