{
  "id": 2397647,
  "type": "Feature",
  "properties": {
    "tgn:hierarchy":[
        "tgn:2397647",
        "tgn:1000001",
        "tgn:7012149",
        "tgn:1002742",
        "tgn:7007920",
        "tgn:7029392"
    ],
    "tgn:id":2397647,
    "tgn:name":"Honeymoon Creek",
    "tgn:placetype":[
        "aat:300008706"
    ]
},
  "bbox": [],
  "geometry": {"coordinates":[-120.05,48.7333],"type":"Point"}
}