{
  "id": 7003367,
  "type": "Feature",
  "properties": {
    "tgn:hierarchy":[
        "tgn:7003367",
        "tgn:7032088",
        "tgn:1000003",
        "tgn:7003515",
        "tgn:7029392"
    ],
    "tgn:id":7003367,
    "tgn:name":"Vaduz",
    "tgn:placetype":[
        "aat:300008347",
        "aat:300387219",
        "aat:300008375"
    ]
},
  "bbox": [],
  "geometry": {"coordinates":[9.5333,47.1333],"type":"Point"}
}