<<<<<<< HEAD
{
  "id": 2255875,
  "type": "Feature",
  "properties": {
    "tgn:hierarchy":[
        "tgn:2255875",
        "tgn:1000001",
        "tgn:7012149",
        "tgn:2001706",
        "tgn:7007708",
        "tgn:7029392"
    ],
    "tgn:id":2255875,
    "tgn:name":"Copper Creek",
    "tgn:placetype":[
        "aat:300008706"
    ]
},
  "bbox": [],
  "geometry": {"coordinates":[-123.0,42.8333],"type":"Point"}
}
=======
{"geometry":{"type":"Point","coordinates":[-123.000000,42.833300]},"type":"Feature","properties":{"hierarchy":["tgn:2255875","tgn:1000001","tgn:7012149","tgn:2001706","tgn:7007708","tgn:7029392"],"placetype":["aat:300008706"],"id":2255875,"name:xx":"Copper Creek"}}
>>>>>>> 03f74aca74312dbeaf24d7e61306dd6a786dc3d0
