{
  "id": 7310426,
  "type": "Feature",
  "properties": {
    "tgn:hierarchy":[
        "tgn:7310426",
        "tgn:1001630",
        "tgn:1000049",
        "tgn:1000002",
        "tgn:7029392"
    ],
    "tgn:id":7310426,
    "tgn:name":"Nicolasa",
    "tgn:placetype":[
        "aat:300007783"
    ]
},
  "bbox": [],
  "geometry": {"coordinates":[-71.016667,-28.516667],"type":"Point"}
}