{
  "id": 1088926,
  "type": "Feature",
  "properties": {
    "tgn:hierarchy":[
        "tgn:1088926",
        "tgn:7001242",
        "tgn:7016755",
        "tgn:1000159",
        "tgn:7029392"
    ],
    "tgn:id":1088926,
    "tgn:name":"Djabir",
    "tgn:placetype":[
        "aat:300008347"
    ]
},
  "bbox": [],
  "geometry": {"coordinates":[24.0833,0.5333],"type":"Point"}
}