{
  "id": 2604630,
  "type": "Feature",
  "properties": {
    "tgn:hierarchy":[
        "tgn:2604630",
        "tgn:1000001",
        "tgn:7012149",
        "tgn:2001754",
        "tgn:7007712",
        "tgn:7029392"
    ],
    "tgn:id":2604630,
    "tgn:name":"Rabon Creek",
    "tgn:placetype":[
        "aat:300008706"
    ]
},
  "bbox": [],
  "geometry": {"coordinates":[-82.1333,34.4667],"type":"Point"}
}