<<<<<<< HEAD
{
  "id": 7247830,
  "type": "Feature",
  "properties": {
    "tgn:hierarchy":[
        "tgn:7247830",
        "tgn:7007877",
        "tgn:1000003",
        "tgn:1000063",
        "tgn:4012014",
        "tgn:7029392"
    ],
    "tgn:id":7247830,
    "tgn:name":"Ch\u00eane Houdiez, Bois du",
    "tgn:placetype":[
        "aat:300008863"
    ]
},
  "bbox": [],
  "geometry": {"coordinates":[4.116667,50.333333],"type":"Point"}
}
=======
{"geometry":{"type":"Point","coordinates":[4.116667,50.333333]},"type":"Feature","properties":{"hierarchy":["tgn:7247830","tgn:7007877","tgn:1000003","tgn:1000063","tgn:4012014","tgn:7029392"],"placetype":["aat:300008863"],"id":7247830,"name:xx":"Ch\u00eane Houdiez, Bois du"}}
>>>>>>> 03f74aca74312dbeaf24d7e61306dd6a786dc3d0
