{
  "id": 2427334,
  "type": "Feature",
  "properties": {
    "tgn:hierarchy":[
        "tgn:2427334",
        "tgn:1000001",
        "tgn:7012149",
        "tgn:1002512",
        "tgn:7007252",
        "tgn:7029392"
    ],
    "tgn:id":2427334,
    "tgn:name":"Jordan Ditch",
    "tgn:placetype":[
        "aat:300006075"
    ]
},
  "bbox": [],
  "geometry": {"coordinates":[-86.9833,40.9167],"type":"Point"}
}