{
  "id": 2116294,
  "type": "Feature",
  "properties": {
    "tgn:hierarchy":[
        "tgn:2116294",
        "tgn:1000001",
        "tgn:7012149",
        "tgn:2002249",
        "tgn:7007920",
        "tgn:7029392"
    ],
    "tgn:id":2116294,
    "tgn:name":"Milan",
    "tgn:placetype":[
        "aat:300008347"
    ]
},
  "bbox": [],
  "geometry": {"coordinates":[-117.3167,47.9667],"type":"Point"}
}