{
  "id": 7213457,
  "type": "Feature",
  "properties": {
    "tgn:hierarchy":[
        "tgn:7213457",
        "tgn:1000003",
        "tgn:7003673",
        "tgn:7000084",
        "tgn:7029392"
    ],
    "tgn:id":7213457,
    "tgn:name":"Boberg",
    "tgn:placetype":[
        "aat:300008347"
    ]
},
  "bbox": [],
  "geometry": {"coordinates":[10.15,53.516667],"type":"Point"}
}