<<<<<<< HEAD
{
  "id": 2333185,
  "type": "Feature",
  "properties": {
    "tgn:hierarchy":[
        "tgn:2333185",
        "tgn:1000001",
        "tgn:7012149",
        "tgn:7007922",
        "tgn:7029392"
    ],
    "tgn:id":2333185,
    "tgn:name":"Flynn Creek",
    "tgn:placetype":[
        "aat:300008706"
    ]
},
  "bbox": [],
  "geometry": {"coordinates":[-88.3,43.25],"type":"Point"}
}
=======
{"geometry":{"type":"Point","coordinates":[-88.300000,43.250000]},"type":"Feature","properties":{"hierarchy":["tgn:2333185","tgn:1000001","tgn:7012149","tgn:7007922","tgn:7029392"],"placetype":["aat:300008706"],"id":2333185,"name:xx":"Flynn Creek"}}
>>>>>>> 03f74aca74312dbeaf24d7e61306dd6a786dc3d0
