{
  "id": 2356906,
  "type": "Feature",
  "properties": {
    "tgn:hierarchy":[
        "tgn:2356906",
        "tgn:1000001",
        "tgn:7012149",
        "tgn:2001420",
        "tgn:7007526",
        "tgn:7029392"
    ],
    "tgn:id":2356906,
    "tgn:name":"Goshute Basin",
    "tgn:placetype":[
        "aat:300386845"
    ]
},
  "bbox": [],
  "geometry": {"coordinates":[-114.85,40.0667],"type":"Point"}
}