{
  "id": 2608219,
  "type": "Feature",
  "properties": {
    "tgn:hierarchy":[
        "tgn:2608219",
        "tgn:1000001",
        "tgn:7012149",
        "tgn:2000219",
        "tgn:7007158",
        "tgn:7029392"
    ],
    "tgn:id":2608219,
    "tgn:name":"Rattlesnake Canyon",
    "tgn:placetype":[
        "aat:300008761"
    ]
},
  "bbox": [],
  "geometry": {"coordinates":[-104.45,37.7333],"type":"Point"}
}