{
  "id": 7317620,
  "type": "Feature",
  "properties": {
    "tgn:hierarchy":[
        "tgn:7317620",
        "tgn:7016598",
        "tgn:1000049",
        "tgn:1000002",
        "tgn:7029392"
    ],
    "tgn:id":7317620,
    "tgn:name":"Costino",
    "tgn:placetype":[
        "aat:300387033"
    ]
},
  "bbox": [],
  "geometry": {"coordinates":[-70.433333,-23.733333],"type":"Point"}
}