<<<<<<< HEAD
{
  "id": 2159634,
  "type": "Feature",
  "properties": {
    "tgn:hierarchy":[
        "tgn:2159634",
        "tgn:1000001",
        "tgn:7012149",
        "tgn:2001140",
        "tgn:7007522",
        "tgn:7029392"
    ],
    "tgn:id":2159634,
    "tgn:name":"Bee Tree Brake",
    "tgn:placetype":[
        "aat:300008699"
    ]
},
  "bbox": [],
  "geometry": {"coordinates":[-89.4167,30.9],"type":"Point"}
}
=======
{"geometry":{"type":"Point","coordinates":[-89.416700,30.900000]},"type":"Feature","properties":{"hierarchy":["tgn:2159634","tgn:1000001","tgn:7012149","tgn:2001140","tgn:7007522","tgn:7029392"],"placetype":["aat:300008699"],"id":2159634,"name:xx":"Bee Tree Brake"}}
>>>>>>> 03f74aca74312dbeaf24d7e61306dd6a786dc3d0
