{
  "id": 7439235,
  "type": "Feature",
  "properties": {
    "tgn:hierarchy":[
        "tgn:7439235",
        "tgn:1000001",
        "tgn:7005594",
        "tgn:7005560",
        "tgn:7029392"
    ],
    "tgn:id":7439235,
    "tgn:name":"San Vicente",
    "tgn:placetype":[
        "aat:300008347"
    ]
},
  "bbox": [],
  "geometry": {"coordinates":[-100.883333,24.166667],"type":"Point"}
}