{
  "id": 1097137,
  "type": "Feature",
  "properties": {
    "tgn:hierarchy":[
        "tgn:1097137",
        "tgn:7000490",
        "tgn:1000006",
        "tgn:7001828",
        "tgn:7029392"
    ],
    "tgn:id":1097137,
    "tgn:name":"Howes Valley",
    "tgn:placetype":[
        "aat:300008347"
    ]
},
  "bbox": [],
  "geometry": {"coordinates":[150.8667,-32.8333],"type":"Point"}
}