{
  "id": 7199543,
  "type": "Feature",
  "properties": {
    "tgn:hierarchy":[
        "tgn:7199543",
        "tgn:7000096",
        "tgn:1000003",
        "tgn:7000084",
        "tgn:7029392"
    ],
    "tgn:id":7199543,
    "tgn:name":"F\u00f6rsterei Eduardspring",
    "tgn:placetype":[
        "aat:300004792"
    ]
},
  "bbox": [],
  "geometry": {"coordinates":[14.433333,52.35],"type":"Point"}
}