{
  "id": 2711485,
  "type": "Feature",
  "properties": {
    "tgn:hierarchy":[
        "tgn:2711485",
        "tgn:1000001",
        "tgn:7012149",
        "tgn:2001457",
        "tgn:7007566",
        "tgn:7029392"
    ],
    "tgn:id":2711485,
    "tgn:name":"Taos Mountains",
    "tgn:placetype":[
        "aat:300386831"
    ]
},
  "bbox": [],
  "geometry": {"coordinates":[-105.4833,36.85],"type":"Point"}
}