<<<<<<< HEAD
{
  "id": 7172901,
  "type": "Feature",
  "properties": {
    "tgn:hierarchy":[
        "tgn:7172901",
        "tgn:1000003",
        "tgn:7003676",
        "tgn:7000084",
        "tgn:7029392"
    ],
    "tgn:id":7172901,
    "tgn:name":"Grenz-Graben",
    "tgn:placetype":[
        "aat:300008699"
    ]
},
  "bbox": [],
  "geometry": {"coordinates":[7.5,52.8],"type":"Point"}
}
=======
{"geometry":{"type":"Point","coordinates":[7.500000,52.800000]},"type":"Feature","properties":{"hierarchy":["tgn:7172901","tgn:1000003","tgn:7003676","tgn:7000084","tgn:7029392"],"placetype":["aat:300008699"],"id":7172901,"name:xx":"Grenz-Graben"}}
>>>>>>> 03f74aca74312dbeaf24d7e61306dd6a786dc3d0
