{
  "id": 7203063,
  "type": "Feature",
  "properties": {
    "tgn:hierarchy":[
        "tgn:7203063",
        "tgn:7003669",
        "tgn:1000003",
        "tgn:7000084",
        "tgn:7029392"
    ],
    "tgn:id":7203063,
    "tgn:name":"Brunnhof",
    "tgn:placetype":[
        "aat:300000206"
    ]
},
  "bbox": [],
  "geometry": {"coordinates":[11.883333,49.283333],"type":"Point"}
}