<<<<<<< HEAD
{
  "id": 7114591,
  "type": "Feature",
  "properties": {
    "tgn:hierarchy":[
        "tgn:7114591",
        "tgn:7003669",
        "tgn:1000003",
        "tgn:7000084",
        "tgn:7029392"
    ],
    "tgn:id":7114591,
    "tgn:name":"Ritzenried",
    "tgn:placetype":[
        "aat:300008347"
    ]
},
  "bbox": [],
  "geometry": {"coordinates":[12.9,49.283333],"type":"Point"}
}
=======
{"geometry":{"type":"Point","coordinates":[12.900000,49.283333]},"type":"Feature","properties":{"hierarchy":["tgn:7114591","tgn:7003669","tgn:1000003","tgn:7000084","tgn:7029392"],"placetype":["aat:300008347"],"id":7114591,"name:xx":"Ritzenried"}}
>>>>>>> 03f74aca74312dbeaf24d7e61306dd6a786dc3d0
