{
  "id": 7356676,
  "type": "Feature",
  "properties": {
    "tgn:hierarchy":[
        "tgn:7356676",
        "tgn:1000001",
        "tgn:7005599",
        "tgn:7005560",
        "tgn:7029392"
    ],
    "tgn:id":7356676,
    "tgn:name":"Chacalapa",
    "tgn:placetype":[
        "aat:300008347"
    ]
},
  "bbox": [],
  "geometry": {"coordinates":[-95.35,18.216667],"type":"Point"}
}