{
  "id": 7547346,
  "type": "Feature",
  "properties": {
    "tgn:hierarchy":[
        "tgn:7547346",
        "tgn:1000004",
        "tgn:1001832",
        "tgn:7000198",
        "tgn:7029392"
    ],
    "tgn:id":7547346,
    "tgn:name:en":"Bamungaon",
    "tgn:placetype":[
        "aat:300008347"
    ]
},
  "bbox": [],
  "geometry": {"coordinates":[94.163578,26.922245],"type":"Point"}
}