{
  "id": 7431359,
  "type": "Feature",
  "properties": {
    "tgn:hierarchy":[
        "tgn:7431359",
        "tgn:7005586",
        "tgn:1000001",
        "tgn:7005560",
        "tgn:7029392"
    ],
    "tgn:id":7431359,
    "tgn:name":"La Puerta",
    "tgn:placetype":[
        "aat:300008347"
    ]
},
  "bbox": [],
  "geometry": {"coordinates":[-103.483333,20.733333],"type":"Point"}
}