<<<<<<< HEAD
{
  "id": 7486989,
  "type": "Feature",
  "properties": {
    "tgn:hierarchy":[
        "tgn:7486989",
        "tgn:1000004",
        "tgn:7489179",
        "tgn:1000141",
        "tgn:7029392"
    ],
    "tgn:id":7486989,
    "tgn:name":"Baihuxincheng",
    "tgn:placetype":[
        "aat:300008347"
    ]
},
  "bbox": [],
  "geometry": {"coordinates":[121.796851,24.641208],"type":"Point"}
}
=======
{"geometry":{"type":"Point","coordinates":[121.796851,24.641208]},"type":"Feature","properties":{"hierarchy":["tgn:7486989","tgn:1000004","tgn:7489179","tgn:1000141","tgn:7029392"],"placetype":["aat:300008347"],"id":7486989,"name:xx":"Baihuxincheng"}}
>>>>>>> 03f74aca74312dbeaf24d7e61306dd6a786dc3d0
