{
  "id": 2132002,
  "type": "Feature",
  "properties": {
    "tgn:hierarchy":[
        "tgn:2132002",
        "tgn:1000001",
        "tgn:7012149",
        "tgn:7007157",
        "tgn:1002863",
        "tgn:7029392"
    ],
    "tgn:id":2132002,
    "tgn:name":"American Canyon Spring",
    "tgn:placetype":[
        "aat:300008697"
    ]
},
  "bbox": [],
  "geometry": {"coordinates":[-120.25,35.2833],"type":"Point"}
}