{
  "id": 7484794,
  "type": "Feature",
  "properties": {
    "tgn:hierarchy":[
        "tgn:7484794",
        "tgn:7468018",
        "tgn:1000004",
        "tgn:1000141",
        "tgn:7029392"
    ],
    "tgn:id":7484794,
    "tgn:name":"Madoudian Qiao",
    "tgn:placetype":[
        "aat:300007836"
    ]
},
  "bbox": [],
  "geometry": {"coordinates":[120.348889,23.410278],"type":"Point"}
}