{
  "id": 1112721,
  "type": "Feature",
  "properties": {
    "tgn:hierarchy":[
        "tgn:1112721",
        "tgn:7002445",
        "tgn:1000003",
        "tgn:7012032",
        "tgn:7008591",
        "tgn:7029392"
    ],
    "tgn:id":1112721,
    "tgn:name:en":"Bridgwater Bay",
    "tgn:placetype":[
        "aat:300132316"
    ]
},
  "bbox": [],
  "geometry": {"coordinates":[-3.283333,51.216667],"type":"Point"}
}