<<<<<<< HEAD
{
  "id": 2254488,
  "type": "Feature",
  "properties": {
    "tgn:hierarchy":[
        "tgn:2254488",
        "tgn:1000001",
        "tgn:7012149",
        "tgn:2001249",
        "tgn:7007523",
        "tgn:7029392"
    ],
    "tgn:id":2254488,
    "tgn:name":"Coon Creek Hollow",
    "tgn:placetype":[
        "aat:300008761"
    ]
},
  "bbox": [],
  "geometry": {"coordinates":[-93.4167,36.65],"type":"Point"}
}
=======
{"geometry":{"type":"Point","coordinates":[-93.416700,36.650000]},"type":"Feature","properties":{"hierarchy":["tgn:2254488","tgn:1000001","tgn:7012149","tgn:2001249","tgn:7007523","tgn:7029392"],"placetype":["aat:300008761"],"id":2254488,"name:xx":"Coon Creek Hollow"}}
>>>>>>> 03f74aca74312dbeaf24d7e61306dd6a786dc3d0
