{
  "id": 2085991,
  "type": "Feature",
  "properties": {
    "tgn:hierarchy":[
        "tgn:2085991",
        "tgn:1000001",
        "tgn:7012149",
        "tgn:1003017",
        "tgn:7007710",
        "tgn:7029392"
    ],
    "tgn:id":2085991,
    "tgn:name":"Alverton",
    "tgn:placetype":[
        "aat:300008347"
    ]
},
  "bbox": [],
  "geometry": {"coordinates":[-79.5833,40.1333],"type":"Point"}
}