{
  "id": 7381788,
  "type": "Feature",
  "properties": {
    "tgn:hierarchy":[
        "tgn:7381788",
        "tgn:1000001",
        "tgn:7005589",
        "tgn:7005560",
        "tgn:7029392"
    ],
    "tgn:id":7381788,
    "tgn:name":"Los Atascaderos",
    "tgn:placetype":[
        "aat:300008347"
    ]
},
  "bbox": [],
  "geometry": {"coordinates":[-100.266667,26.033333],"type":"Point"}
}