{
  "id": 1027495,
  "type": "Feature",
  "properties": {
    "tgn:hierarchy":[
        "tgn:1027495",
        "tgn:7593919",
        "tgn:1000003",
        "tgn:1001780",
        "tgn:7029392"
    ],
    "tgn:id":1027495,
    "tgn:name":"Rej\u0161tejn",
    "tgn:placetype":[
        "aat:300008347"
    ]
},
  "bbox": [],
  "geometry": {"coordinates":[13.5333,49.15],"type":"Point"}
}