{
  "id": 7394909,
  "type": "Feature",
  "properties": {
    "tgn:hierarchy":[
        "tgn:7394909",
        "tgn:7005584",
        "tgn:1000001",
        "tgn:7005560",
        "tgn:7029392"
    ],
    "tgn:id":7394909,
    "tgn:name":"San Cosme",
    "tgn:placetype":[
        "aat:300008347"
    ]
},
  "bbox": [],
  "geometry": {"coordinates":[-100.583333,24.35],"type":"Point"}
}