{
  "id": 7391902,
  "type": "Feature",
  "properties": {
    "tgn:hierarchy":[
        "tgn:7391902",
        "tgn:1001836",
        "tgn:1000001",
        "tgn:7005560",
        "tgn:7029392"
    ],
    "tgn:id":7391902,
    "tgn:name":"Rosario",
    "tgn:placetype":[
        "aat:300008347"
    ]
},
  "bbox": [],
  "geometry": {"coordinates":[-111.25,25.183333],"type":"Point"}
}