{
  "id": 2708160,
  "type": "Feature",
  "properties": {
    "tgn:hierarchy":[
        "tgn:2708160",
        "tgn:2001726",
        "tgn:1000001",
        "tgn:7012149",
        "tgn:7007712",
        "tgn:7029392"
    ],
    "tgn:id":2708160,
    "tgn:name":"Swints Lake",
    "tgn:placetype":[
        "aat:300006191"
    ]
},
  "bbox": [],
  "geometry": {"coordinates":[-81.9167,33.5833],"type":"Point"}
}