<<<<<<< HEAD
{
  "id": 2763859,
  "type": "Feature",
  "properties": {
    "tgn:hierarchy":[
        "tgn:2763859",
        "tgn:1000001",
        "tgn:7012149",
        "tgn:2001998",
        "tgn:7007826",
        "tgn:7029392"
    ],
    "tgn:id":2763859,
    "tgn:name":"Wheatland",
    "tgn:placetype":[
        "aat:300008347"
    ]
},
  "bbox": [],
  "geometry": {"coordinates":[-99.8833,34.3],"type":"Point"}
}
=======
{"geometry":{"type":"Point","coordinates":[-99.883300,34.300000]},"type":"Feature","properties":{"hierarchy":["tgn:2763859","tgn:1000001","tgn:7012149","tgn:2001998","tgn:7007826","tgn:7029392"],"placetype":["aat:300008347"],"id":2763859,"name:xx":"Wheatland"}}
>>>>>>> 03f74aca74312dbeaf24d7e61306dd6a786dc3d0
