<<<<<<< HEAD
{
  "id": 7174612,
  "type": "Feature",
  "properties": {
    "tgn:hierarchy":[
        "tgn:7174612",
        "tgn:7003692",
        "tgn:1000003",
        "tgn:7000084",
        "tgn:7029392"
    ],
    "tgn:id":7174612,
    "tgn:name":"Gro\u00dfer Hof",
    "tgn:placetype":[
        "aat:300000206"
    ]
},
  "bbox": [],
  "geometry": {"coordinates":[8.366667,48.1],"type":"Point"}
}
=======
{"geometry":{"type":"Point","coordinates":[8.366667,48.100000]},"type":"Feature","properties":{"hierarchy":["tgn:7174612","tgn:7003692","tgn:1000003","tgn:7000084","tgn:7029392"],"placetype":["aat:300000206"],"id":7174612,"name:xx":"Gro\u00dfer Hof"}}
>>>>>>> 03f74aca74312dbeaf24d7e61306dd6a786dc3d0
