{
  "id": 7191947,
  "type": "Feature",
  "properties": {
    "tgn:hierarchy":[
        "tgn:7191947",
        "tgn:1000003",
        "tgn:7003685",
        "tgn:7000084",
        "tgn:7029392"
    ],
    "tgn:id":7191947,
    "tgn:name":"Freigut",
    "tgn:placetype":[
        "aat:300000206"
    ]
},
  "bbox": [],
  "geometry": {"coordinates":[12.633333,50.533333],"type":"Point"}
}