<<<<<<< HEAD
{
  "id": 2333738,
  "type": "Feature",
  "properties": {
    "tgn:hierarchy":[
        "tgn:2333738",
        "tgn:2002365",
        "tgn:1000001",
        "tgn:7012149",
        "tgn:7007923",
        "tgn:7029392"
    ],
    "tgn:id":2333738,
    "tgn:name":"Foote Creek Lake",
    "tgn:placetype":[
        "aat:300008680"
    ]
},
  "bbox": [],
  "geometry": {"coordinates":[-106.05,41.8167],"type":"Point"}
}
=======
{"geometry":{"type":"Point","coordinates":[-106.050000,41.816700]},"type":"Feature","properties":{"hierarchy":["tgn:2333738","tgn:2002365","tgn:1000001","tgn:7012149","tgn:7007923","tgn:7029392"],"placetype":["aat:300008680"],"id":2333738,"name:xx":"Foote Creek Lake"}}
>>>>>>> 03f74aca74312dbeaf24d7e61306dd6a786dc3d0
