{
  "id": 7033765,
  "type": "Feature",
  "properties": {
    "tgn:hierarchy":[
        "tgn:7033765",
        "tgn:1003459",
        "tgn:1000003",
        "tgn:7002993",
        "tgn:1000080",
        "tgn:7029392"
    ],
    "tgn:id":7033765,
    "tgn:name":"Plessiva",
    "tgn:placetype":[
        "aat:300008347"
    ]
},
  "bbox": [],
  "geometry": {"coordinates":[13.499167,45.981389],"type":"Point"}
}