{
  "id": 7421624,
  "type": "Feature",
  "properties": {
    "tgn:hierarchy":[
        "tgn:7421624",
        "tgn:7005584",
        "tgn:1000001",
        "tgn:7005560",
        "tgn:7029392"
    ],
    "tgn:id":7421624,
    "tgn:name":"Salitrillo",
    "tgn:placetype":[
        "aat:300008347"
    ]
},
  "bbox": [],
  "geometry": {"coordinates":[-101.453056,21.031944],"type":"Point"}
}