{
  "id": 2025274,
  "type": "Feature",
  "properties": {
    "tgn:hierarchy":[
        "tgn:2025274",
        "tgn:1002483",
        "tgn:7019080",
        "tgn:1000001",
        "tgn:7012149",
        "tgn:7007249",
        "tgn:7029392"
    ],
    "tgn:id":2025274,
    "tgn:name":"Waianae",
    "tgn:placetype":[
        "aat:300008347"
    ]
},
  "bbox": [],
  "geometry": {"coordinates":[-158.1833,21.4333],"type":"Point"}
}