{
  "id": 7434541,
  "type": "Feature",
  "properties": {
    "tgn:hierarchy":[
        "tgn:7434541",
        "tgn:7005583",
        "tgn:1000001",
        "tgn:7005560",
        "tgn:7029392"
    ],
    "tgn:id":7434541,
    "tgn:name":"Veinticino de Diciembre",
    "tgn:placetype":[
        "aat:300008347"
    ]
},
  "bbox": [],
  "geometry": {"coordinates":[-104.05,25.25],"type":"Point"}
}