{
  "id": 7156525,
  "type": "Feature",
  "properties": {
    "tgn:hierarchy":[
        "tgn:7156525",
        "tgn:1000003",
        "tgn:7003682",
        "tgn:7000084",
        "tgn:7029392"
    ],
    "tgn:id":7156525,
    "tgn:name":"Kleine Schie\u00df",
    "tgn:placetype":[
        "aat:300008777"
    ]
},
  "bbox": [],
  "geometry": {"coordinates":[7.733333,49.216667],"type":"Point"}
}