<<<<<<< HEAD
{
  "id": 7371270,
  "type": "Feature",
  "properties": {
    "tgn:hierarchy":[
        "tgn:7371270",
        "tgn:7005580",
        "tgn:1000001",
        "tgn:7005560",
        "tgn:7029392"
    ],
    "tgn:id":7371270,
    "tgn:name":"Ibarra, Sierra",
    "tgn:placetype":[
        "aat:300266640"
    ]
},
  "bbox": [],
  "geometry": {"coordinates":[-91.4,16.683333],"type":"Point"}
}
=======
{"geometry":{"type":"Point","coordinates":[-91.400000,16.683333]},"type":"Feature","properties":{"hierarchy":["tgn:7371270","tgn:7005580","tgn:1000001","tgn:7005560","tgn:7029392"],"placetype":["aat:300266640"],"id":7371270,"name:xx":"Ibarra, Sierra"}}
>>>>>>> 03f74aca74312dbeaf24d7e61306dd6a786dc3d0
