<<<<<<< HEAD
{
  "id": 2769896,
  "type": "Feature",
  "properties": {
    "tgn:hierarchy":[
        "tgn:2769896",
        "tgn:1000001",
        "tgn:7012149",
        "tgn:1003005",
        "tgn:7007520",
        "tgn:7029392"
    ],
    "tgn:id":2769896,
    "tgn:name":"Wilbur Drain",
    "tgn:placetype":[
        "aat:300008699"
    ]
},
  "bbox": [],
  "geometry": {"coordinates":[-83.4167,42.25],"type":"Point"}
}
=======
{"geometry":{"type":"Point","coordinates":[-83.416700,42.250000]},"type":"Feature","properties":{"hierarchy":["tgn:2769896","tgn:1000001","tgn:7012149","tgn:1003005","tgn:7007520","tgn:7029392"],"placetype":["aat:300008699"],"id":2769896,"name:xx":"Wilbur Drain"}}
>>>>>>> 03f74aca74312dbeaf24d7e61306dd6a786dc3d0
