<<<<<<< HEAD
{
  "id": 2251526,
  "type": "Feature",
  "properties": {
    "tgn:hierarchy":[
        "tgn:2251526",
        "tgn:1000001",
        "tgn:7012149",
        "tgn:2000225",
        "tgn:7007158",
        "tgn:7029392"
    ],
    "tgn:id":2251526,
    "tgn:name":"Commissioner Ditch",
    "tgn:placetype":[
        "aat:300006075"
    ]
},
  "bbox": [],
  "geometry": {"coordinates":[-107.6167,37.1167],"type":"Point"}
}
=======
{"geometry":{"type":"Point","coordinates":[-107.616700,37.116700]},"type":"Feature","properties":{"hierarchy":["tgn:2251526","tgn:1000001","tgn:7012149","tgn:2000225","tgn:7007158","tgn:7029392"],"placetype":["aat:300006075"],"id":2251526,"name:xx":"Commissioner Ditch"}}
>>>>>>> 03f74aca74312dbeaf24d7e61306dd6a786dc3d0
