{
  "id": 2251526,
  "type": "Feature",
  "properties": {
    "tgn:hierarchy":[
        "tgn:2251526",
        "tgn:1000001",
        "tgn:7012149",
        "tgn:2000225",
        "tgn:7007158",
        "tgn:7029392"
    ],
    "tgn:id":2251526,
    "tgn:name":"Commissioner Ditch",
    "tgn:placetype":[
        "aat:300006075"
    ]
},
  "bbox": [],
  "geometry": {"coordinates":[-107.6167,37.1167],"type":"Point"}
}