{
  "id": 1050738,
  "type": "Feature",
  "properties": {
    "tgn:hierarchy":[
        "tgn:1050738",
        "tgn:7002444",
        "tgn:1000003",
        "tgn:7009907",
        "tgn:1008385",
        "tgn:7008591",
        "tgn:7029392"
    ],
    "tgn:id":1050738,
    "tgn:name":"Hollandstoun",
    "tgn:placetype":[
        "aat:300008347"
    ]
},
  "bbox": [],
  "geometry": {"coordinates":[-2.4333,59.35],"type":"Point"}
}