{
  "id": 7510005,
  "type": "Feature",
  "properties": {
    "tgn:hierarchy":[
        "tgn:7510005",
        "tgn:1008380",
        "tgn:7000507",
        "tgn:1000226",
        "tgn:1000006",
        "tgn:7029392"
    ],
    "tgn:id":7510005,
    "tgn:name:en":"Te Moho",
    "tgn:placetype":[
        "aat:300008777"
    ]
},
  "bbox": [],
  "geometry": {"coordinates":[173.483333,-35.566667],"type":"Point"}
}