{
  "id": 2004683,
  "type": "Feature",
  "properties": {
    "tgn:hierarchy":[
        "tgn:2004683",
        "tgn:7002659",
        "tgn:1000001",
        "tgn:7012149",
        "tgn:2000044",
        "tgn:7029392"
    ],
    "tgn:id":2004683,
    "tgn:name":"New Haven",
    "tgn:placetype":[
        "aat:300008347",
        "aat:300387210"
    ]
},
  "bbox": [],
  "geometry": {"coordinates":[-86.75,34.6333],"type":"Point"}
}