{
  "id": 7338223,
  "type": "Feature",
  "properties": {
    "tgn:hierarchy":[
        "tgn:7338223",
        "tgn:7002824",
        "tgn:1000003",
        "tgn:7002786",
        "tgn:1000095",
        "tgn:7029392"
    ],
    "tgn:id":7338223,
    "tgn:name":"Cebr\u00e1ns",
    "tgn:placetype":[
        "aat:300008347"
    ]
},
  "bbox": [],
  "geometry": {"coordinates":[-9.166667,43.083333],"type":"Point"}
}