<<<<<<< HEAD
{
  "id": 2403937,
  "type": "Feature",
  "properties": {
    "tgn:hierarchy":[
        "tgn:2403937",
        "tgn:1000001",
        "tgn:7012149",
        "tgn:2001146",
        "tgn:7007522",
        "tgn:7029392"
    ],
    "tgn:id":2403937,
    "tgn:name":"Howell",
    "tgn:placetype":[
        "aat:300008347"
    ]
},
  "bbox": [],
  "geometry": {"coordinates":[-90.1,32.2333],"type":"Point"}
}
=======
{"geometry":{"type":"Point","coordinates":[-90.100000,32.233300]},"type":"Feature","properties":{"hierarchy":["tgn:2403937","tgn:1000001","tgn:7012149","tgn:2001146","tgn:7007522","tgn:7029392"],"placetype":["aat:300008347"],"id":2403937,"name:xx":"Howell"}}
>>>>>>> 03f74aca74312dbeaf24d7e61306dd6a786dc3d0
