{
  "id": 7057287,
  "type": "Feature",
  "properties": {
    "tgn:hierarchy":[
        "tgn:7057287",
        "tgn:7007850",
        "tgn:1003491",
        "tgn:1000003",
        "tgn:1000080",
        "tgn:7029392"
    ],
    "tgn:id":7057287,
    "tgn:name":"Bagaladi",
    "tgn:placetype":[
        "aat:300008347"
    ]
},
  "bbox": [],
  "geometry": {"coordinates":[15.816667,38.016667],"type":"Point"}
}