{
  "id": 2121528,
  "type": "Feature",
  "properties": {
    "tgn:hierarchy":[
        "tgn:2121528",
        "tgn:1000001",
        "tgn:1002316",
        "tgn:7012149",
        "tgn:7007922",
        "tgn:7029392"
    ],
    "tgn:id":2121528,
    "tgn:name":"Klevenville",
    "tgn:placetype":[
        "aat:300008347"
    ]
},
  "bbox": [],
  "geometry": {"coordinates":[-89.6667,43.0167],"type":"Point"}
}