<<<<<<< HEAD
{
  "id": 7379513,
  "type": "Feature",
  "properties": {
    "tgn:hierarchy":[
        "tgn:7379513",
        "tgn:1000001",
        "tgn:7005599",
        "tgn:7005560",
        "tgn:7029392"
    ],
    "tgn:id":7379513,
    "tgn:name":"Marqu\u00e9s, Laguna del",
    "tgn:placetype":[
        "aat:300008680"
    ]
},
  "bbox": [],
  "geometry": {"coordinates":[-95.466667,18.65],"type":"Point"}
}
=======
{"geometry":{"type":"Point","coordinates":[-95.466667,18.650000]},"type":"Feature","properties":{"hierarchy":["tgn:7379513","tgn:1000001","tgn:7005599","tgn:7005560","tgn:7029392"],"placetype":["aat:300008680"],"id":7379513,"name:xx":"Marqu\u00e9s, Laguna del"}}
>>>>>>> 03f74aca74312dbeaf24d7e61306dd6a786dc3d0
