{
  "id": 7467332,
  "type": "Feature",
  "properties": {
    "tgn:hierarchy":[
        "tgn:7467332",
        "tgn:7487020",
        "tgn:1000004",
        "tgn:1000141",
        "tgn:7029392"
    ],
    "tgn:id":7467332,
    "tgn:name":"Aikouliao",
    "tgn:placetype":[
        "aat:300008347"
    ]
},
  "bbox": [],
  "geometry": {"coordinates":[120.678333,24.457778],"type":"Point"}
}