<<<<<<< HEAD
{
  "id": 7376185,
  "type": "Feature",
  "properties": {
    "tgn:hierarchy":[
        "tgn:7376185",
        "tgn:7005581",
        "tgn:1000001",
        "tgn:7005560",
        "tgn:7029392"
    ],
    "tgn:id":7376185,
    "tgn:name":"Las Varas, Sierra",
    "tgn:placetype":[
        "aat:300008795"
    ]
},
  "bbox": [],
  "geometry": {"coordinates":[-108.166667,30.616667],"type":"Point"}
}
=======
{"geometry":{"type":"Point","coordinates":[-108.166667,30.616667]},"type":"Feature","properties":{"hierarchy":["tgn:7376185","tgn:7005581","tgn:1000001","tgn:7005560","tgn:7029392"],"placetype":["aat:300008795"],"id":7376185,"name:xx":"Las Varas, Sierra"}}
>>>>>>> 03f74aca74312dbeaf24d7e61306dd6a786dc3d0
