{
  "id": 2585851,
  "type": "Feature",
  "properties": {
    "tgn:hierarchy":[
        "tgn:2585851",
        "tgn:1000001",
        "tgn:7012149",
        "tgn:2000931",
        "tgn:7007515",
        "tgn:7029392"
    ],
    "tgn:id":2585851,
    "tgn:name":"Piper Brook",
    "tgn:placetype":[
        "aat:300008699"
    ]
},
  "bbox": [],
  "geometry": {"coordinates":[-68.9333,44.4833],"type":"Point"}
}