<<<<<<< HEAD
{
  "id": 7021539,
  "type": "Feature",
  "properties": {
    "tgn:hierarchy":[
        "tgn:7021539",
        "tgn:1000001",
        "tgn:7012149",
        "tgn:7029392"
    ],
    "tgn:id":7021539,
    "tgn:name":"West Fork Copper Canyon",
    "tgn:placetype":[
        "aat:300008761"
    ]
},
  "bbox": [],
  "geometry": {"coordinates":[-110.4333,36.9167],"type":"Point"}
}
=======
{"geometry":{"type":"Point","coordinates":[-110.433300,36.916700]},"type":"Feature","properties":{"hierarchy":["tgn:7021539","tgn:1000001","tgn:7012149","tgn:7029392"],"placetype":["aat:300008761"],"id":7021539,"name:xx":"West Fork Copper Canyon"}}
>>>>>>> 03f74aca74312dbeaf24d7e61306dd6a786dc3d0
