{
  "id": 7021539,
  "type": "Feature",
  "properties": {
    "tgn:hierarchy":[
        "tgn:7021539",
        "tgn:1000001",
        "tgn:7012149",
        "tgn:7029392"
    ],
    "tgn:id":7021539,
    "tgn:name":"West Fork Copper Canyon",
    "tgn:placetype":[
        "aat:300008761"
    ]
},
  "bbox": [],
  "geometry": {"coordinates":[-110.4333,36.9167],"type":"Point"}
}