<<<<<<< HEAD
{
  "id": 2252373,
  "type": "Feature",
  "properties": {
    "tgn:hierarchy":[
        "tgn:2252373",
        "tgn:1000001",
        "tgn:7012149",
        "tgn:2000838",
        "tgn:7007255",
        "tgn:7029392"
    ],
    "tgn:id":2252373,
    "tgn:name":"Congleton Mountain",
    "tgn:placetype":[
        "aat:300008798"
    ]
},
  "bbox": [],
  "geometry": {"coordinates":[-83.8,37.8667],"type":"Point"}
}
=======
{"geometry":{"type":"Point","coordinates":[-83.800000,37.866700]},"type":"Feature","properties":{"hierarchy":["tgn:2252373","tgn:1000001","tgn:7012149","tgn:2000838","tgn:7007255","tgn:7029392"],"placetype":["aat:300008798"],"id":2252373,"name:xx":"Congleton Mountain"}}
>>>>>>> 03f74aca74312dbeaf24d7e61306dd6a786dc3d0
