{
  "id": 1126762,
  "type": "Feature",
  "properties": {
    "tgn:hierarchy":[
        "tgn:1126762",
        "tgn:1001826",
        "tgn:1000047",
        "tgn:7002456",
        "tgn:1000002",
        "tgn:7029392"
    ],
    "tgn:id":1126762,
    "tgn:name":"Manac\u00e1",
    "tgn:placetype":[
        "aat:300008707"
    ]
},
  "bbox": [],
  "geometry": {"coordinates":[-61.8333,-2.8667],"type":"Point"}
}