{
  "id": 1048684,
  "type": "Feature",
  "properties": {
    "tgn:hierarchy":[
        "tgn:1048684",
        "tgn:7003646",
        "tgn:1000003",
        "tgn:1000088",
        "tgn:7029392"
    ],
    "tgn:id":1048684,
    "tgn:name":"Norheimsund",
    "tgn:placetype":[
        "aat:300008347"
    ]
},
  "bbox": [],
  "geometry": {"coordinates":[6.15,60.3667],"type":"Point"}
}