{
  "id": 1041076,
  "type": "Feature",
  "properties": {
    "tgn:hierarchy":[
        "tgn:1041076",
        "tgn:1000003",
        "tgn:7003688",
        "tgn:7000084",
        "tgn:7029392"
    ],
    "tgn:id":1041076,
    "tgn:name":"Scharbeutz",
    "tgn:placetype":[
        "aat:300008347"
    ]
},
  "bbox": [],
  "geometry": {"coordinates":[10.75,54.033333],"type":"Point"}
}