<<<<<<< HEAD
{
  "id": 7476229,
  "type": "Feature",
  "properties": {
    "tgn:hierarchy":[
        "tgn:7476229",
        "tgn:1000004",
        "tgn:7489179",
        "tgn:1000141",
        "tgn:7029392"
    ],
    "tgn:id":7476229,
    "tgn:name":"Hanxi Guoxiao Fenban",
    "tgn:placetype":[
        "aat:300006495"
    ]
},
  "bbox": [],
  "geometry": {"coordinates":[121.7045,24.617043],"type":"Point"}
}
=======
{"geometry":{"type":"Point","coordinates":[121.704500,24.617043]},"type":"Feature","properties":{"hierarchy":["tgn:7476229","tgn:1000004","tgn:7489179","tgn:1000141","tgn:7029392"],"placetype":["aat:300006495"],"id":7476229,"name:xx":"Hanxi Guoxiao Fenban"}}
>>>>>>> 03f74aca74312dbeaf24d7e61306dd6a786dc3d0
