{
  "id": 1054479,
  "type": "Feature",
  "properties": {
    "tgn:hierarchy":[
        "tgn:1054479",
        "tgn:1000004",
        "tgn:7011494",
        "tgn:7002435",
        "tgn:7029392"
    ],
    "tgn:id":1054479,
    "tgn:name":"Izberbash",
    "tgn:placetype":[
        "aat:300008347"
    ]
},
  "bbox": [],
  "geometry": {"coordinates":[47.8667,42.5167],"type":"Point"}
}