{
  "id": 1028729,
  "type": "Feature",
  "properties": {
    "tgn:hierarchy":[
        "tgn:1028729",
        "tgn:7002445",
        "tgn:1000003",
        "tgn:7008160",
        "tgn:7008591",
        "tgn:7029392"
    ],
    "tgn:id":1028729,
    "tgn:name":"Caister-on-Sea",
    "tgn:placetype":[
        "aat:300008347",
        "aat:300387314",
        "aat:300008375",
        "aat:300120599"
    ]
},
  "bbox": [],
  "geometry": {"coordinates":[1.75,52.65],"type":"Point"}
}