{
  "id": 7228387,
  "type": "Feature",
  "properties": {
    "tgn:hierarchy":[
        "tgn:7228387",
        "tgn:7002735",
        "tgn:7017076",
        "tgn:1000003",
        "tgn:1000074",
        "tgn:7029392"
    ],
    "tgn:id":7228387,
    "tgn:name":"Kast\u00e9llia",
    "tgn:placetype":[
        "aat:300008777"
    ]
},
  "bbox": [],
  "geometry": {"coordinates":[22.833333,37.016667],"type":"Point"}
}