{
  "id": 7419968,
  "type": "Feature",
  "properties": {
    "tgn:hierarchy":[
        "tgn:7419968",
        "tgn:7005579",
        "tgn:1000001",
        "tgn:7005560",
        "tgn:7029392"
    ],
    "tgn:id":7419968,
    "tgn:name":"Baj\u00edo Los V\u00e1zquez",
    "tgn:placetype":[
        "aat:300008347"
    ]
},
  "bbox": [],
  "geometry": {"coordinates":[-102.116667,21.75],"type":"Point"}
}