{
  "id": 2158415,
  "type": "Feature",
  "properties": {
    "tgn:hierarchy":[
        "tgn:2158415",
        "tgn:1000001",
        "tgn:2000301",
        "tgn:7012149",
        "tgn:7007248",
        "tgn:7029392"
    ],
    "tgn:id":2158415,
    "tgn:name":"Beaverdam Creek",
    "tgn:placetype":[
        "aat:300008706"
    ]
},
  "bbox": [],
  "geometry": {"coordinates":[-83.1667,31.0667],"type":"Point"}
}