{
  "id": 7357625,
  "type": "Feature",
  "properties": {
    "tgn:hierarchy":[
        "tgn:7357625",
        "tgn:7005586",
        "tgn:1000001",
        "tgn:7005560",
        "tgn:7029392"
    ],
    "tgn:id":7357625,
    "tgn:name":"Cumbres del Obispo",
    "tgn:placetype":[
        "aat:300008347"
    ]
},
  "bbox": [],
  "geometry": {"coordinates":[-104.466667,19.766667],"type":"Point"}
}