<<<<<<< HEAD
{
  "id": 7026278,
  "type": "Feature",
  "properties": {
    "tgn:hierarchy":[
        "tgn:7026278",
        "tgn:7002443",
        "tgn:1000003",
        "tgn:7008591",
        "tgn:7029392"
    ],
    "tgn:id":7026278,
    "tgn:name:en":"Flintshire",
    "tgn:placetype":[
        "aat:300008347",
        "aat:300387064",
        "aat:300387145",
        "aat:300387346",
        "aat:300000771",
        "aat:300387071"
    ]
},
  "bbox": [],
  "geometry": {"coordinates":[-3.0833,53.25],"type":"Point"}
}
=======
{"geometry":{"type":"Point","coordinates":[-3.083300,53.250000]},"type":"Feature","properties":{"hierarchy":["tgn:7026278","tgn:7002443","tgn:1000003","tgn:7008591","tgn:7029392"],"placetype":["aat:300008347","aat:300387064","aat:300387145","aat:300387346","aat:300000771","aat:300387071"],"name:en":"Flintshire","id":7026278}}
>>>>>>> 03f74aca74312dbeaf24d7e61306dd6a786dc3d0
