{
  "id": 7040495,
  "type": "Feature",
  "properties": {
    "tgn:hierarchy":[
        "tgn:7040495",
        "tgn:7003137",
        "tgn:1000003",
        "tgn:7003080",
        "tgn:1000080",
        "tgn:7029392"
    ],
    "tgn:id":7040495,
    "tgn:name":"Santa Giusta",
    "tgn:placetype":[
        "aat:300008347"
    ]
},
  "bbox": [],
  "geometry": {"coordinates":[13.25,42.633333],"type":"Point"}
}