{
  "id": 7265572,
  "type": "Feature",
  "properties": {
    "tgn:concordances":{
        "gn:id":"2753393"
    },
    "tgn:hierarchy":[
        "tgn:7265572",
        "tgn:7003616",
        "tgn:1000003",
        "tgn:7016845",
        "tgn:7029392"
    ],
    "tgn:id":7265572,
    "tgn:name:nl":"Idsegahuizum",
    "tgn:placetype":[
        "aat:300008347"
    ]
},
  "bbox": [],
  "geometry": {"coordinates":[5.416667,53.05],"type":"Point"}
}