{
  "id": 2105688,
  "type": "Feature",
  "properties": {
    "tgn:hierarchy":[
        "tgn:2105688",
        "tgn:1000001",
        "tgn:7012149",
        "tgn:2001993",
        "tgn:7007826",
        "tgn:7029392"
    ],
    "tgn:id":2105688,
    "tgn:name":"Locust",
    "tgn:placetype":[
        "aat:300008347",
        "aat:300387210"
    ]
},
  "bbox": [],
  "geometry": {"coordinates":[-96.7667,33.7833],"type":"Point"}
}