{
  "id": 2097353,
  "type": "Feature",
  "properties": {
    "tgn:hierarchy":[
        "tgn:2097353",
        "tgn:1000001",
        "tgn:7012149",
        "tgn:2001832",
        "tgn:7007713",
        "tgn:7029392"
    ],
    "tgn:id":2097353,
    "tgn:name":"Marion",
    "tgn:placetype":[
        "aat:300008347"
    ]
},
  "bbox": [],
  "geometry": {"coordinates":[-97.25,43.4167],"type":"Point"}
}