{
  "id": 7076274,
  "type": "Feature",
  "properties": {
    "tgn:hierarchy":[
        "tgn:7076274",
        "tgn:1000003",
        "tgn:7003688",
        "tgn:7000084",
        "tgn:7029392"
    ],
    "tgn:id":7076274,
    "tgn:name":"Buckhagener Geh\u00f6lz",
    "tgn:placetype":[
        "aat:300008863"
    ]
},
  "bbox": [],
  "geometry": {"coordinates":[9.95,54.683333],"type":"Point"}
}