{
  "id": 2300675,
  "type": "Feature",
  "properties": {
    "tgn:hierarchy":[
        "tgn:2300675",
        "tgn:1000001",
        "tgn:2001746",
        "tgn:7012149",
        "tgn:7007712",
        "tgn:7029392"
    ],
    "tgn:id":2300675,
    "tgn:name":"Dunbar Landing",
    "tgn:placetype":[
        "aat:300008347"
    ]
},
  "bbox": [],
  "geometry": {"coordinates":[-79.35,33.5333],"type":"Point"}
}