{
  "id": 2552518,
  "type": "Feature",
  "properties": {
    "tgn:hierarchy":[
        "tgn:2552518",
        "tgn:1000001",
        "tgn:7012149",
        "tgn:1002353",
        "tgn:7007252",
        "tgn:7029392"
    ],
    "tgn:id":2552518,
    "tgn:name":"Nunemaker Ditch",
    "tgn:placetype":[
        "aat:300006075"
    ]
},
  "bbox": [],
  "geometry": {"coordinates":[-86.0667,42.3167],"type":"Point"}
}