{
  "id": 7469316,
  "type": "Feature",
  "properties": {
    "tgn:hierarchy":[
        "tgn:7469316",
        "tgn:1000004",
        "tgn:7492971",
        "tgn:1000141",
        "tgn:7029392"
    ],
    "tgn:id":7469316,
    "tgn:name":"Xishi",
    "tgn:placetype":[
        "aat:300008347"
    ]
},
  "bbox": [],
  "geometry": {"coordinates":[120.524844,22.622989],"type":"Point"}
}