{
  "id": 2474446,
  "type": "Feature",
  "properties": {
    "tgn:hierarchy":[
        "tgn:2474446",
        "tgn:1000001",
        "tgn:7012149",
        "tgn:1002833",
        "tgn:7007568",
        "tgn:7029392"
    ],
    "tgn:id":2474446,
    "tgn:name":"Lower Pound Swamp",
    "tgn:placetype":[
        "aat:300008905"
    ]
},
  "bbox": [],
  "geometry": {"coordinates":[-74.0333,41.2333],"type":"Point"}
}