<<<<<<< HEAD
{
  "id": 2153390,
  "type": "Feature",
  "properties": {
    "tgn:hierarchy":[
        "tgn:2153390",
        "tgn:1000001",
        "tgn:7012149",
        "tgn:2002358",
        "tgn:7007922",
        "tgn:7029392"
    ],
    "tgn:id":2153390,
    "tgn:name":"Bean Hollow",
    "tgn:placetype":[
        "aat:300008761"
    ]
},
  "bbox": [],
  "geometry": {"coordinates":[-91.1167,43.45],"type":"Point"}
}
=======
{"geometry":{"type":"Point","coordinates":[-91.116700,43.450000]},"type":"Feature","properties":{"hierarchy":["tgn:2153390","tgn:1000001","tgn:7012149","tgn:2002358","tgn:7007922","tgn:7029392"],"placetype":["aat:300008761"],"id":2153390,"name:xx":"Bean Hollow"}}
>>>>>>> 03f74aca74312dbeaf24d7e61306dd6a786dc3d0
