{
  "id": 2452229,
  "type": "Feature",
  "properties": {
    "tgn:hierarchy":[
        "tgn:2452229",
        "tgn:1000001",
        "tgn:7012149",
        "tgn:1002700",
        "tgn:7007520",
        "tgn:7029392"
    ],
    "tgn:id":2452229,
    "tgn:name":"Little Blue Lake",
    "tgn:placetype":[
        "aat:300008680"
    ]
},
  "bbox": [],
  "geometry": {"coordinates":[-86.2167,43.3833],"type":"Point"}
}