{
  "id": 2516705,
  "type": "Feature",
  "properties": {
    "tgn:hierarchy":[
        "tgn:2516705",
        "tgn:1000001",
        "tgn:2000582",
        "tgn:7012149",
        "tgn:7007253",
        "tgn:7029392"
    ],
    "tgn:id":2516705,
    "tgn:name":"Miners Creek",
    "tgn:placetype":[
        "aat:300008706"
    ]
},
  "bbox": [],
  "geometry": {"coordinates":[-91.1833,42.8167],"type":"Point"}
}