<<<<<<< HEAD
{
  "id": 2258117,
  "type": "Feature",
  "properties": {
    "tgn:hierarchy":[
        "tgn:2258117",
        "tgn:1000001",
        "tgn:1002714",
        "tgn:7012149",
        "tgn:7007159",
        "tgn:7029392"
    ],
    "tgn:id":2258117,
    "tgn:name":"Cossaduck Hill",
    "tgn:placetype":[
        "aat:300008798"
    ]
},
  "bbox": [],
  "geometry": {"coordinates":[-71.9,41.4667],"type":"Point"}
}
=======
{"geometry":{"type":"Point","coordinates":[-71.900000,41.466700]},"type":"Feature","properties":{"hierarchy":["tgn:2258117","tgn:1000001","tgn:1002714","tgn:7012149","tgn:7007159","tgn:7029392"],"placetype":["aat:300008798"],"id":2258117,"name:xx":"Cossaduck Hill"}}
>>>>>>> 03f74aca74312dbeaf24d7e61306dd6a786dc3d0
