{
  "id": 2345496,
  "type": "Feature",
  "properties": {
    "tgn:hierarchy":[
        "tgn:2345496",
        "tgn:1000001",
        "tgn:2001424",
        "tgn:7012149",
        "tgn:7007564",
        "tgn:7029392"
    ],
    "tgn:id":2345496,
    "tgn:name":"Garnet Hill",
    "tgn:placetype":[
        "aat:300008798"
    ]
},
  "bbox": [],
  "geometry": {"coordinates":[-71.7833,44.2167],"type":"Point"}
}