{
  "id": 2065603,
  "type": "Feature",
  "properties": {
    "tgn:hierarchy":[
        "tgn:2065603",
        "tgn:1000001",
        "tgn:1002775",
        "tgn:7012149",
        "tgn:7007565",
        "tgn:7029392"
    ],
    "tgn:id":2065603,
    "tgn:name":"Newfoundland",
    "tgn:placetype":[
        "aat:300008347"
    ]
},
  "bbox": [],
  "geometry": {"coordinates":[-74.4333,41.0333],"type":"Point"}
}