{
  "id": 2476882,
  "type": "Feature",
  "properties": {
    "tgn:hierarchy":[
        "tgn:2476882",
        "tgn:1000001",
        "tgn:2001426",
        "tgn:7012149",
        "tgn:7007564",
        "tgn:7029392"
    ],
    "tgn:id":2476882,
    "tgn:name":"Lyman Brook",
    "tgn:placetype":[
        "aat:300008699"
    ]
},
  "bbox": [],
  "geometry": {"coordinates":[-71.0167,43.4167],"type":"Point"}
}