{
  "id": 7254641,
  "type": "Feature",
  "properties": {
    "tgn:hierarchy":[
        "tgn:7254641",
        "tgn:7003458",
        "tgn:1000003",
        "tgn:1000063",
        "tgn:7018236",
        "tgn:7029392"
    ],
    "tgn:id":7254641,
    "tgn:name":"Verlorenhoek",
    "tgn:placetype":[
        "aat:300008347"
    ]
},
  "bbox": [],
  "geometry": {"coordinates":[2.933333,50.85],"type":"Point"}
}