{
  "id": 7560402,
  "type": "Feature",
  "properties": {
    "tgn:hierarchy":[
        "tgn:7560402",
        "tgn:1000004",
        "tgn:7000198",
        "tgn:7016788",
        "tgn:7029392"
    ],
    "tgn:id":7560402,
    "tgn:name:en":"S\u0101njriya",
    "tgn:placetype":[
        "aat:300008347"
    ]
},
  "bbox": [],
  "geometry": {"coordinates":[75.591669,26.859124],"type":"Point"}
}