{
  "id": 7307925,
  "type": "Feature",
  "properties": {
    "tgn:hierarchy":[
        "tgn:7307925",
        "tgn:1001699",
        "tgn:1000049",
        "tgn:1000002",
        "tgn:7029392"
    ],
    "tgn:id":7307925,
    "tgn:name":"Nayahua, Bah\u00eda",
    "tgn:placetype":[
        "aat:300132316"
    ]
},
  "bbox": [],
  "geometry": {"coordinates":[-74.156389,-43.3525],"type":"Point"}
}