{
  "id": 2228586,
  "type": "Feature",
  "properties": {
    "tgn:hierarchy":[
        "tgn:2228586",
        "tgn:1000001",
        "tgn:7012149",
        "tgn:2002194",
        "tgn:7007919",
        "tgn:7029392"
    ],
    "tgn:id":2228586,
    "tgn:name":"Cedar Creek",
    "tgn:placetype":[
        "aat:300008706"
    ]
},
  "bbox": [],
  "geometry": {"coordinates":[-81.85,36.7667],"type":"Point"}
}