<<<<<<< HEAD
{
  "id": 2703474,
  "type": "Feature",
  "properties": {
    "tgn:hierarchy":[
        "tgn:2703474",
        "tgn:1000001",
        "tgn:7012149",
        "tgn:1002564",
        "tgn:7007710",
        "tgn:7029392"
    ],
    "tgn:id":2703474,
    "tgn:name":"Summit Lake",
    "tgn:placetype":[
        "aat:300006191"
    ]
},
  "bbox": [],
  "geometry": {"coordinates":[-75.7,41.4667],"type":"Point"}
}
=======
{"geometry":{"type":"Point","coordinates":[-75.700000,41.466700]},"type":"Feature","properties":{"hierarchy":["tgn:2703474","tgn:1000001","tgn:7012149","tgn:1002564","tgn:7007710","tgn:7029392"],"placetype":["aat:300006191"],"id":2703474,"name:xx":"Summit Lake"}}
>>>>>>> 03f74aca74312dbeaf24d7e61306dd6a786dc3d0
