{
  "id": 7534085,
  "type": "Feature",
  "properties": {
    "tgn:hierarchy":[
        "tgn:7534085",
        "tgn:7001242",
        "tgn:7016833",
        "tgn:7001335",
        "tgn:7029392"
    ],
    "tgn:id":7534085,
    "tgn:name":"Jidd\u012b, Jabal al",
    "tgn:placetype":[
        "aat:300008795"
    ]
},
  "bbox": [],
  "geometry": {"coordinates":[33.147481,30.165521],"type":"Point"}
}