{
  "id": 2422994,
  "type": "Feature",
  "properties": {
    "tgn:hierarchy":[
        "tgn:2422994",
        "tgn:1000001",
        "tgn:2002109",
        "tgn:7012149",
        "tgn:7007827",
        "tgn:7029392"
    ],
    "tgn:id":2422994,
    "tgn:name":"Joe Lay Reservoir",
    "tgn:placetype":[
        "aat:300006191"
    ]
},
  "bbox": [],
  "geometry": {"coordinates":[-111.8167,37.9167],"type":"Point"}
}