{
  "id": 1093285,
  "type": "Feature",
  "properties": {
    "tgn:hierarchy":[
        "tgn:1093285",
        "tgn:7001242",
        "tgn:7017584",
        "tgn:1000193",
        "tgn:7029392"
    ],
    "tgn:id":1093285,
    "tgn:name":"Kruisrivier",
    "tgn:placetype":[
        "aat:300008347"
    ]
},
  "bbox": [],
  "geometry": {"coordinates":[21.8833,-33.4333],"type":"Point"}
}