{
  "id": 2359956,
  "type": "Feature",
  "properties": {
    "tgn:hierarchy":[
        "tgn:2359956",
        "tgn:1000001",
        "tgn:7012149",
        "tgn:1002518",
        "tgn:7007568",
        "tgn:7029392"
    ],
    "tgn:id":2359956,
    "tgn:name":"Grass Bay",
    "tgn:placetype":[
        "aat:300132316"
    ]
},
  "bbox": [],
  "geometry": {"coordinates":[-76.2667,44.15],"type":"Point"}
}