{
  "id": 2030992,
  "type": "Feature",
  "properties": {
    "tgn:hierarchy":[
        "tgn:2030992",
        "tgn:1000001",
        "tgn:7012149",
        "tgn:1002827",
        "tgn:7007252",
        "tgn:7029392"
    ],
    "tgn:id":2030992,
    "tgn:name":"Ballstown",
    "tgn:placetype":[
        "aat:300008347",
        "aat:300387210"
    ]
},
  "bbox": [],
  "geometry": {"coordinates":[-85.2333,39.25],"type":"Point"}
}