{
  "id": 7077856,
  "type": "Feature",
  "properties": {
    "tgn:hierarchy":[
        "tgn:7077856",
        "tgn:1000003",
        "tgn:7003678",
        "tgn:7000084",
        "tgn:7029392"
    ],
    "tgn:id":7077856,
    "tgn:name":"Ziegelhof",
    "tgn:placetype":[
        "aat:300000206"
    ]
},
  "bbox": [],
  "geometry": {"coordinates":[9.966667,50.566667],"type":"Point"}
}