{
  "id": 2288196,
  "type": "Feature",
  "properties": {
    "tgn:hierarchy":[
        "tgn:2288196",
        "tgn:1000001",
        "tgn:7012149",
        "tgn:2002376",
        "tgn:7007923",
        "tgn:7029392"
    ],
    "tgn:id":2288196,
    "tgn:name":"Dipper Creek",
    "tgn:placetype":[
        "aat:300008706"
    ]
},
  "bbox": [],
  "geometry": {"coordinates":[-110.9167,42.45],"type":"Point"}
}