{
  "id": 2729634,
  "type": "Feature",
  "properties": {
    "tgn:hierarchy":[
        "tgn:2729634",
        "tgn:1000001",
        "tgn:7012149",
        "tgn:2001157",
        "tgn:7007522",
        "tgn:7029392"
    ],
    "tgn:id":2729634,
    "tgn:name":"Trotters Point",
    "tgn:placetype":[
        "aat:300008850"
    ]
},
  "bbox": [],
  "geometry": {"coordinates":[-90.5333,34.5333],"type":"Point"}
}