{
  "id": 1017627,
  "type": "Feature",
  "properties": {
    "tgn:hierarchy":[
        "tgn:1017627",
        "tgn:1000001",
        "tgn:7005593",
        "tgn:7005560",
        "tgn:7029392"
    ],
    "tgn:id":1017627,
    "tgn:name":"Jalpan",
    "tgn:placetype":[
        "aat:300008347"
    ]
},
  "bbox": [],
  "geometry": {"coordinates":[-99.483333,21.233333],"type":"Point"}
}