{
  "id": 2088883,
  "type": "Feature",
  "properties": {
    "tgn:hierarchy":[
        "tgn:2088883",
        "tgn:1000001",
        "tgn:1002194",
        "tgn:7012149",
        "tgn:7007710",
        "tgn:7029392"
    ],
    "tgn:id":2088883,
    "tgn:name":"Granville Summit",
    "tgn:placetype":[
        "aat:300008347"
    ]
},
  "bbox": [],
  "geometry": {"coordinates":[-76.7667,41.7167],"type":"Point"}
}