<<<<<<< HEAD
{
  "id": 2336613,
  "type": "Feature",
  "properties": {
    "tgn:hierarchy":[
        "tgn:2336613",
        "tgn:1000001",
        "tgn:7006451",
        "tgn:7012149",
        "tgn:2000097",
        "tgn:7029392"
    ],
    "tgn:id":2336613,
    "tgn:name":"Four Peaks Spring Number One",
    "tgn:placetype":[
        "aat:300008697"
    ]
},
  "bbox": [],
  "geometry": {"coordinates":[-111.3333,33.6833],"type":"Point"}
}
=======
{"geometry":{"type":"Point","coordinates":[-111.333300,33.683300]},"type":"Feature","properties":{"hierarchy":["tgn:2336613","tgn:1000001","tgn:7006451","tgn:7012149","tgn:2000097","tgn:7029392"],"placetype":["aat:300008697"],"id":2336613,"name:xx":"Four Peaks Spring Number One"}}
>>>>>>> 03f74aca74312dbeaf24d7e61306dd6a786dc3d0
