{
  "id": 2255612,
  "type": "Feature",
  "properties": {
    "tgn:hierarchy":[
        "tgn:2255612",
        "tgn:1000001",
        "tgn:7012149",
        "tgn:1002749",
        "tgn:7007240",
        "tgn:7029392"
    ],
    "tgn:id":2255612,
    "tgn:name":"Copeland, Lake",
    "tgn:placetype":[
        "aat:300008680"
    ]
},
  "bbox": [],
  "geometry": {"coordinates":[-81.3667,28.5167],"type":"Point"}
}