{
  "id": 7392431,
  "type": "Feature",
  "properties": {
    "tgn:hierarchy":[
        "tgn:7392431",
        "tgn:1000001",
        "tgn:7005589",
        "tgn:7005560",
        "tgn:7029392"
    ],
    "tgn:id":7392431,
    "tgn:name":"Rancho El Jardin",
    "tgn:placetype":[
        "aat:300008347"
    ]
},
  "bbox": [],
  "geometry": {"coordinates":[-100.35,26.166667],"type":"Point"}
}