<<<<<<< HEAD
{
  "id": 2150785,
  "type": "Feature",
  "properties": {
    "tgn:hierarchy":[
        "tgn:2150785",
        "tgn:1000001",
        "tgn:7012149",
        "tgn:1002723",
        "tgn:7007252",
        "tgn:7029392"
    ],
    "tgn:id":2150785,
    "tgn:name":"Bass Lake",
    "tgn:placetype":[
        "aat:300008680"
    ]
},
  "bbox": [],
  "geometry": {"coordinates":[-85.4333,41.3333],"type":"Point"}
}
=======
{"geometry":{"type":"Point","coordinates":[-85.433300,41.333300]},"type":"Feature","properties":{"hierarchy":["tgn:2150785","tgn:1000001","tgn:7012149","tgn:1002723","tgn:7007252","tgn:7029392"],"placetype":["aat:300008680"],"id":2150785,"name:xx":"Bass Lake"}}
>>>>>>> 03f74aca74312dbeaf24d7e61306dd6a786dc3d0
