{
  "id": 7201151,
  "type": "Feature",
  "properties": {
    "tgn:hierarchy":[
        "tgn:7201151",
        "tgn:1000003",
        "tgn:7003687",
        "tgn:7000084",
        "tgn:7029392"
    ],
    "tgn:id":7201151,
    "tgn:name":"Dunkelforth",
    "tgn:placetype":[
        "aat:300008347"
    ]
},
  "bbox": [],
  "geometry": {"coordinates":[12.233333,52.416667],"type":"Point"}
}