{
  "id": 1075278,
  "type": "Feature",
  "properties": {
    "tgn:hierarchy":[
        "tgn:1075278",
        "tgn:1000004",
        "tgn:7000198",
        "tgn:7031783",
        "tgn:7029392"
    ],
    "tgn:id":1075278,
    "tgn:name:en":"G\u0101nde",
    "tgn:placetype":[
        "aat:300008347"
    ]
},
  "bbox": [],
  "geometry": {"coordinates":[86.433333,24.166667],"type":"Point"}
}