{
  "id": 7278208,
  "type": "Feature",
  "properties": {
    "tgn:hierarchy":[
        "tgn:7278208",
        "tgn:1001702",
        "tgn:1000049",
        "tgn:1000002",
        "tgn:7029392"
    ],
    "tgn:id":7278208,
    "tgn:name":"El Gorro, Cerro",
    "tgn:placetype":[
        "aat:300008777"
    ]
},
  "bbox": [],
  "geometry": {"coordinates":[-69.816667,-55.033333],"type":"Point"}
}