{
  "id": 2600636,
  "type": "Feature",
  "properties": {
    "tgn:hierarchy":[
        "tgn:2600636",
        "tgn:1000001",
        "tgn:7012149",
        "tgn:2001288",
        "tgn:7007524",
        "tgn:7029392"
    ],
    "tgn:id":2600636,
    "tgn:name":"Puller Hot Springs",
    "tgn:placetype":[
        "aat:300008697"
    ]
},
  "bbox": [],
  "geometry": {"coordinates":[-112.15,45.1667],"type":"Point"}
}