{
  "id": 2564930,
  "type": "Feature",
  "properties": {
    "tgn:hierarchy":[
        "tgn:2564930",
        "tgn:1002648",
        "tgn:1000001",
        "tgn:1008191",
        "tgn:7012149",
        "tgn:7007249",
        "tgn:7029392"
    ],
    "tgn:id":2564930,
    "tgn:name":"Paenapalaua Gulch",
    "tgn:placetype":[
        "aat:300008761"
    ]
},
  "bbox": [],
  "geometry": {"coordinates":[-156.7333,21.1167],"type":"Point"}
}