{
  "id": 7478814,
  "type": "Feature",
  "properties": {
    "tgn:hierarchy":[
        "tgn:7478814",
        "tgn:1000004",
        "tgn:7467799",
        "tgn:1000141",
        "tgn:7029392"
    ],
    "tgn:id":7478814,
    "tgn:name":"Xingluo Qiao",
    "tgn:placetype":[
        "aat:300007836"
    ]
},
  "bbox": [],
  "geometry": {"coordinates":[120.590263,23.823707],"type":"Point"}
}