<<<<<<< HEAD
{
  "id": 7478814,
  "type": "Feature",
  "properties": {
    "tgn:hierarchy":[
        "tgn:7478814",
        "tgn:1000004",
        "tgn:7467799",
        "tgn:1000141",
        "tgn:7029392"
    ],
    "tgn:id":7478814,
    "tgn:name":"Xingluo Qiao",
    "tgn:placetype":[
        "aat:300007836"
    ]
},
  "bbox": [],
  "geometry": {"coordinates":[120.590263,23.823707],"type":"Point"}
}
=======
{"geometry":{"type":"Point","coordinates":[120.590263,23.823707]},"type":"Feature","properties":{"hierarchy":["tgn:7478814","tgn:1000004","tgn:7467799","tgn:1000141","tgn:7029392"],"placetype":["aat:300007836"],"id":7478814,"name:xx":"Xingluo Qiao"}}
>>>>>>> 03f74aca74312dbeaf24d7e61306dd6a786dc3d0
