{
  "id": 1024357,
  "type": "Feature",
  "properties": {
    "tgn:hierarchy":[
        "tgn:1024357",
        "tgn:1000670",
        "tgn:1000002",
        "tgn:1000056",
        "tgn:7029392"
    ],
    "tgn:id":1024357,
    "tgn:name":"Anc\u00f3n",
    "tgn:placetype":[
        "aat:300008347"
    ]
},
  "bbox": [],
  "geometry": {"coordinates":[-77.1333,-11.75],"type":"Point"}
}