{
  "id": 1009459,
  "type": "Feature",
  "properties": {
    "tgn:hierarchy":[
        "tgn:1009459",
        "tgn:1009907",
        "tgn:1000004",
        "tgn:1001174",
        "tgn:1000135",
        "tgn:7029392"
    ],
    "tgn:id":1009459,
    "tgn:name":"Tinaga Island",
    "tgn:placetype":[
        "aat:300008791"
    ]
},
  "bbox": [],
  "geometry": {"coordinates":[122.9167,14.4833],"type":"Point"}
}