{
  "id": 7214527,
  "type": "Feature",
  "properties": {
    "tgn:hierarchy":[
        "tgn:7214527",
        "tgn:1000003",
        "tgn:7003677",
        "tgn:7000084",
        "tgn:7029392"
    ],
    "tgn:id":7214527,
    "tgn:name":"Boisheim",
    "tgn:placetype":[
        "aat:300008347"
    ]
},
  "bbox": [],
  "geometry": {"coordinates":[6.266667,51.266667],"type":"Point"}
}