{
  "id": 7320478,
  "type": "Feature",
  "properties": {
    "tgn:hierarchy":[
        "tgn:7320478",
        "tgn:1001623",
        "tgn:1000049",
        "tgn:1000002",
        "tgn:7029392"
    ],
    "tgn:id":7320478,
    "tgn:name":"Barba, Grupo",
    "tgn:placetype":[
        "aat:300008791"
    ]
},
  "bbox": [],
  "geometry": {"coordinates":[-73.733333,-45.366667],"type":"Point"}
}