{
  "id": 2383649,
  "type": "Feature",
  "properties": {
    "tgn:hierarchy":[
        "tgn:2383649",
        "tgn:1000001",
        "tgn:7012149",
        "tgn:7019676",
        "tgn:7007566",
        "tgn:7029392"
    ],
    "tgn:id":2383649,
    "tgn:name":"Heaton Mine",
    "tgn:placetype":[
        "aat:300000390"
    ]
},
  "bbox": [],
  "geometry": {"coordinates":[-108.7167,35.5667],"type":"Point"}
}