{
  "id": 7442249,
  "type": "Feature",
  "properties": {
    "tgn:hierarchy":[
        "tgn:7442249",
        "tgn:7002445",
        "tgn:1000003",
        "tgn:7012032",
        "tgn:7008591",
        "tgn:7029392"
    ],
    "tgn:id":7442249,
    "tgn:name:en":"Tone, River",
    "tgn:placetype":[
        "aat:300008699"
    ]
},
  "bbox": [],
  "geometry": {"coordinates":[-2.915278,51.068889],"type":"Point"}
}