{
  "id": 2238573,
  "type": "Feature",
  "properties": {
    "tgn:hierarchy":[
        "tgn:2238573",
        "tgn:1000001",
        "tgn:7012149",
        "tgn:2001067",
        "tgn:7007521",
        "tgn:7029392"
    ],
    "tgn:id":2238573,
    "tgn:name":"Chorus Lake",
    "tgn:placetype":[
        "aat:300008680"
    ]
},
  "bbox": [],
  "geometry": {"coordinates":[-91.95,48.0667],"type":"Point"}
}