{
  "id": 2098876,
  "type": "Feature",
  "properties": {
    "tgn:hierarchy":[
        "tgn:2098876",
        "tgn:1000001",
        "tgn:7012149",
        "tgn:2001885",
        "tgn:7007825",
        "tgn:7029392"
    ],
    "tgn:id":2098876,
    "tgn:name":"Dry Hill",
    "tgn:placetype":[
        "aat:300008347",
        "aat:300387210"
    ]
},
  "bbox": [],
  "geometry": {"coordinates":[-89.4667,35.8333],"type":"Point"}
}