{
  "id": 2719229,
  "type": "Feature",
  "properties": {
    "tgn:hierarchy":[
        "tgn:2719229",
        "tgn:1000001",
        "tgn:2001471",
        "tgn:7012149",
        "tgn:7007709",
        "tgn:7029392"
    ],
    "tgn:id":2719229,
    "tgn:name":"Thousand Acres Bay",
    "tgn:placetype":[
        "aat:300008905"
    ]
},
  "bbox": [],
  "geometry": {"coordinates":[-78.3667,34.55],"type":"Point"}
}