{
  "id": 2351903,
  "type": "Feature",
  "properties": {
    "tgn:hierarchy":[
        "tgn:2351903",
        "tgn:1000001",
        "tgn:7012149",
        "tgn:2001281",
        "tgn:7007524",
        "tgn:7029392"
    ],
    "tgn:id":2351903,
    "tgn:name":"Glenwood Lake",
    "tgn:placetype":[
        "aat:300008680"
    ]
},
  "bbox": [],
  "geometry": {"coordinates":[-111.8833,46.2833],"type":"Point"}
}