{
  "id": 7270580,
  "type": "Feature",
  "properties": {
    "tgn:hierarchy":[
        "tgn:7270580",
        "tgn:7003619",
        "tgn:1000003",
        "tgn:7016845",
        "tgn:7029392"
    ],
    "tgn:id":7270580,
    "tgn:name:nl":"Ravenhorst",
    "tgn:placetype":[
        "aat:300387502"
    ]
},
  "bbox": [],
  "geometry": {"coordinates":[6.716667,51.983333],"type":"Point"}
}