{
  "id": 7051008,
  "type": "Feature",
  "properties": {
    "tgn:hierarchy":[
        "tgn:7051008",
        "tgn:1000003",
        "tgn:7003152",
        "tgn:7003237",
        "tgn:1000080",
        "tgn:7029392"
    ],
    "tgn:id":7051008,
    "tgn:name":"Piantedo",
    "tgn:placetype":[
        "aat:300008347"
    ]
},
  "bbox": [],
  "geometry": {"coordinates":[9.433333,46.133333],"type":"Point"}
}