{
  "id": 2417504,
  "type": "Feature",
  "properties": {
    "tgn:hierarchy":[
        "tgn:2417504",
        "tgn:2001726",
        "tgn:1000001",
        "tgn:7012149",
        "tgn:7007712",
        "tgn:7029392"
    ],
    "tgn:id":2417504,
    "tgn:name":"Jackson Branch",
    "tgn:placetype":[
        "aat:300008699"
    ]
},
  "bbox": [],
  "geometry": {"coordinates":[-81.6167,33.5167],"type":"Point"}
}