{
  "id": 7268635,
  "type": "Feature",
  "properties": {
    "tgn:hierarchy":[
        "tgn:7268635",
        "tgn:1000003",
        "tgn:7003635",
        "tgn:7016845",
        "tgn:7029392"
    ],
    "tgn:id":7268635,
    "tgn:name:nl":"Oranjepolder",
    "tgn:placetype":[
        "aat:300006163"
    ]
},
  "bbox": [],
  "geometry": {"coordinates":[3.683333,51.516667],"type":"Point"}
}