{
  "id": 2619084,
  "type": "Feature",
  "properties": {
    "tgn:hierarchy":[
        "tgn:2619084",
        "tgn:1000001",
        "tgn:7012149",
        "tgn:2000792",
        "tgn:7007255",
        "tgn:7029392"
    ],
    "tgn:id":2619084,
    "tgn:name":"Riley Branch",
    "tgn:placetype":[
        "aat:300008699"
    ]
},
  "bbox": [],
  "geometry": {"coordinates":[-88.5333,36.7167],"type":"Point"}
}