{
  "id": 2138737,
  "type": "Feature",
  "properties": {
    "tgn:hierarchy":[
        "tgn:2138737",
        "tgn:1000001",
        "tgn:7012149",
        "tgn:1002472",
        "tgn:7007568",
        "tgn:7029392"
    ],
    "tgn:id":2138737,
    "tgn:name":"Ash Ridge",
    "tgn:placetype":[
        "aat:300266640"
    ]
},
  "bbox": [],
  "geometry": {"coordinates":[-75.0333,43.4167],"type":"Point"}
}