{
  "id": 2196545,
  "type": "Feature",
  "properties": {
    "tgn:hierarchy":[
        "tgn:2196545",
        "tgn:1000001",
        "tgn:7012149",
        "tgn:1003017",
        "tgn:7007710",
        "tgn:7029392"
    ],
    "tgn:id":2196545,
    "tgn:name":"Brook Shore Lakes",
    "tgn:placetype":[
        "aat:300006191"
    ]
},
  "bbox": [],
  "geometry": {"coordinates":[-79.5333,40.4667],"type":"Point"}
}