{
  "id": 2509363,
  "type": "Feature",
  "properties": {
    "tgn:hierarchy":[
        "tgn:2509363",
        "tgn:1000001",
        "tgn:7012149",
        "tgn:2001273",
        "tgn:7007524",
        "tgn:7029392"
    ],
    "tgn:id":2509363,
    "tgn:name":"Middle Fork Salt Creek",
    "tgn:placetype":[
        "aat:300008706"
    ]
},
  "bbox": [],
  "geometry": {"coordinates":[-109.4333,47.35],"type":"Point"}
}