<<<<<<< HEAD
{
  "id": 2406529,
  "type": "Feature",
  "properties": {
    "tgn:hierarchy":[
        "tgn:2406529",
        "tgn:1000001",
        "tgn:7012149",
        "tgn:1003030",
        "tgn:7007251",
        "tgn:7029392"
    ],
    "tgn:id":2406529,
    "tgn:name":"Hungry Run",
    "tgn:placetype":[
        "aat:300008699"
    ]
},
  "bbox": [],
  "geometry": {"coordinates":[-89.2833,42.4],"type":"Point"}
}
=======
{"geometry":{"type":"Point","coordinates":[-89.283300,42.400000]},"type":"Feature","properties":{"hierarchy":["tgn:2406529","tgn:1000001","tgn:7012149","tgn:1003030","tgn:7007251","tgn:7029392"],"placetype":["aat:300008699"],"id":2406529,"name:xx":"Hungry Run"}}
>>>>>>> 03f74aca74312dbeaf24d7e61306dd6a786dc3d0
