{
  "id": 2375167,
  "type": "Feature",
  "properties": {
    "tgn:hierarchy":[
        "tgn:2375167",
        "tgn:1000001",
        "tgn:7016172",
        "tgn:7012149",
        "tgn:2000139",
        "tgn:7029392"
    ],
    "tgn:id":2375167,
    "tgn:name":"Hannaberry",
    "tgn:placetype":[
        "aat:300008347"
    ]
},
  "bbox": [],
  "geometry": {"coordinates":[-91.55,34.1167],"type":"Point"}
}