{
  "id": 2322232,
  "type": "Feature",
  "properties": {
    "tgn:hierarchy":[
        "tgn:2322232",
        "tgn:1000001",
        "tgn:7012149",
        "tgn:7029392"
    ],
    "tgn:id":2322232,
    "tgn:name":"Fall Run",
    "tgn:placetype":[
        "aat:300008699"
    ]
},
  "bbox": [],
  "geometry": {"coordinates":[-80.5167,39.75],"type":"Point"}
}