<<<<<<< HEAD
{
  "id": 2337854,
  "type": "Feature",
  "properties": {
    "tgn:hierarchy":[
        "tgn:2337854",
        "tgn:7006450",
        "tgn:1000001",
        "tgn:7012149",
        "tgn:2000089",
        "tgn:7029392"
    ],
    "tgn:id":2337854,
    "tgn:name":"Fox Gulch",
    "tgn:placetype":[
        "aat:300008761"
    ]
},
  "bbox": [],
  "geometry": {"coordinates":[-155.4833,64.5333],"type":"Point"}
}
=======
{"geometry":{"type":"Point","coordinates":[-155.483300,64.533300]},"type":"Feature","properties":{"hierarchy":["tgn:2337854","tgn:7006450","tgn:1000001","tgn:7012149","tgn:2000089","tgn:7029392"],"placetype":["aat:300008761"],"id":2337854,"name:xx":"Fox Gulch"}}
>>>>>>> 03f74aca74312dbeaf24d7e61306dd6a786dc3d0
