{
  "id": 2497002,
  "type": "Feature",
  "properties": {
    "tgn:hierarchy":[
        "tgn:2497002",
        "tgn:1000001",
        "tgn:7012149",
        "tgn:2001486",
        "tgn:7007709",
        "tgn:7029392"
    ],
    "tgn:id":2497002,
    "tgn:name":"Mauls Swamp",
    "tgn:placetype":[
        "aat:300008699"
    ]
},
  "bbox": [],
  "geometry": {"coordinates":[-77.0667,35.3333],"type":"Point"}
}