{
  "id": 1019421,
  "type": "Feature",
  "properties": {
    "tgn:hierarchy":[
        "tgn:1019421",
        "tgn:1001160",
        "tgn:7006477",
        "tgn:1000002",
        "tgn:7029392"
    ],
    "tgn:id":1019421,
    "tgn:name":"El Talar",
    "tgn:placetype":[
        "aat:300008347"
    ]
},
  "bbox": [],
  "geometry": {"coordinates":[-58.65,-34.45],"type":"Point"}
}