{
  "id": 7308017,
  "type": "Feature",
  "properties": {
    "tgn:hierarchy":[
        "tgn:7308017",
        "tgn:1001768",
        "tgn:1000049",
        "tgn:1000002",
        "tgn:7029392"
    ],
    "tgn:id":7308017,
    "tgn:name":"Melosillas",
    "tgn:placetype":[
        "aat:300000206"
    ]
},
  "bbox": [],
  "geometry": {"coordinates":[-71.516667,-33.216667],"type":"Point"}
}