<<<<<<< HEAD
{
  "id": 2333442,
  "type": "Feature",
  "properties": {
    "tgn:hierarchy":[
        "tgn:2333442",
        "tgn:1000001",
        "tgn:7012149",
        "tgn:1002794",
        "tgn:7007708",
        "tgn:7029392"
    ],
    "tgn:id":2333442,
    "tgn:name":"Folk Creek",
    "tgn:placetype":[
        "aat:300008706"
    ]
},
  "bbox": [],
  "geometry": {"coordinates":[-123.5,45.0167],"type":"Point"}
}
=======
{"geometry":{"type":"Point","coordinates":[-123.500000,45.016700]},"type":"Feature","properties":{"hierarchy":["tgn:2333442","tgn:1000001","tgn:7012149","tgn:1002794","tgn:7007708","tgn:7029392"],"placetype":["aat:300008706"],"id":2333442,"name:xx":"Folk Creek"}}
>>>>>>> 03f74aca74312dbeaf24d7e61306dd6a786dc3d0
