{
  "id": 7260267,
  "type": "Feature",
  "properties": {
    "tgn:concordances":{
        "gn:id":"2756081"
    },
    "tgn:hierarchy":[
        "tgn:7260267",
        "tgn:7003616",
        "tgn:1000003",
        "tgn:7016845",
        "tgn:7029392"
    ],
    "tgn:id":7260267,
    "tgn:name:nl":"Engwierum",
    "tgn:placetype":[
        "aat:300008347"
    ]
},
  "bbox": [],
  "geometry": {"coordinates":[6.133333,53.316667],"type":"Point"}
}