{
  "id": 1136475,
  "type": "Feature",
  "properties": {
    "tgn:hierarchy":[
        "tgn:1136475",
        "tgn:7006477",
        "tgn:1001524",
        "tgn:1000002",
        "tgn:7029392"
    ],
    "tgn:id":1136475,
    "tgn:name":"Santo Tom\u00e9",
    "tgn:placetype":[
        "aat:300008347"
    ]
},
  "bbox": [],
  "geometry": {"coordinates":[-60.7667,-31.6667],"type":"Point"}
}