{
  "id": 2278426,
  "type": "Feature",
  "properties": {
    "tgn:hierarchy":[
        "tgn:2278426",
        "tgn:1000001",
        "tgn:7020939",
        "tgn:7012149",
        "tgn:7007922",
        "tgn:7029392"
    ],
    "tgn:id":2278426,
    "tgn:name":"De Neveu Lake",
    "tgn:placetype":[
        "aat:300008680"
    ]
},
  "bbox": [],
  "geometry": {"coordinates":[-88.3833,43.7167],"type":"Point"}
}