{
  "id": 2149052,
  "type": "Feature",
  "properties": {
    "tgn:hierarchy":[
        "tgn:2149052",
        "tgn:1000001",
        "tgn:7012149",
        "tgn:2000207",
        "tgn:7007158",
        "tgn:7029392"
    ],
    "tgn:id":2149052,
    "tgn:name":"Barnum Park Lake Reservoir",
    "tgn:placetype":[
        "aat:300006191"
    ]
},
  "bbox": [],
  "geometry": {"coordinates":[-105.0167,39.7167],"type":"Point"}
}