{
  "id": 1006269,
  "type": "Feature",
  "properties": {
    "tgn:hierarchy":[
        "tgn:1006269",
        "tgn:7000677",
        "tgn:1000004",
        "tgn:7003877",
        "tgn:1000137",
        "tgn:7029392"
    ],
    "tgn:id":1006269,
    "tgn:name":"An-Nabq\u012byah",
    "tgn:placetype":[
        "aat:300008791"
    ]
},
  "bbox": [],
  "geometry": {"coordinates":[36.05,26.75],"type":"Point"}
}