{
  "id": 2700471,
  "type": "Feature",
  "properties": {
    "tgn:hierarchy":[
        "tgn:2700471",
        "tgn:1002165",
        "tgn:1000001",
        "tgn:7012149",
        "tgn:7007517",
        "tgn:7029392"
    ],
    "tgn:id":2700471,
    "tgn:name":"Succonnesset Shoal",
    "tgn:placetype":[
        "aat:300132348"
    ]
},
  "bbox": [],
  "geometry": {"coordinates":[-70.45,41.5333],"type":"Point"}
}