{
  "id": 1042118,
  "type": "Feature",
  "properties": {
    "tgn:hierarchy":[
        "tgn:1042118",
        "tgn:7011270",
        "tgn:7002674",
        "tgn:1000003",
        "tgn:1000074",
        "tgn:1007946",
        "tgn:7029392"
    ],
    "tgn:id":1042118,
    "tgn:name:en":"M\u00fdkonos",
    "tgn:placetype":[
        "aat:300008347"
    ]
},
  "bbox": [],
  "geometry": {"coordinates":[25.333333,37.45],"type":"Point"}
}