{
  "id": 1067001,
  "type": "Feature",
  "properties": {
    "tgn:hierarchy":[
        "tgn:1067001",
        "tgn:7002075",
        "tgn:1000004",
        "tgn:1000111",
        "tgn:7029392"
    ],
    "tgn:id":1067001,
    "tgn:name":"Caolaoji",
    "tgn:placetype":[
        "aat:300008347"
    ]
},
  "bbox": [],
  "geometry": {"coordinates":[117.35,33.0833],"type":"Point"}
}