{
  "id": 2535882,
  "type": "Feature",
  "properties": {
    "tgn:hierarchy":[
        "tgn:2535882",
        "tgn:2000858",
        "tgn:1000001",
        "tgn:7012149",
        "tgn:7007256",
        "tgn:7029392"
    ],
    "tgn:id":2535882,
    "tgn:name":"Natchitoches, \u00cele",
    "tgn:placetype":[
        "aat:300008791"
    ]
},
  "bbox": [],
  "geometry": {"coordinates":[-91.85,31.1333],"type":"Point"}
}