{
  "id": 2742479,
  "type": "Feature",
  "properties": {
    "tgn:hierarchy":[
        "tgn:2742479",
        "tgn:1000001",
        "tgn:7012149",
        "tgn:2002265",
        "tgn:7013961",
        "tgn:7029392"
    ],
    "tgn:id":2742479,
    "tgn:name":"Valley Mountain",
    "tgn:placetype":[
        "aat:300008798"
    ]
},
  "bbox": [],
  "geometry": {"coordinates":[-78.65,39.4667],"type":"Point"}
}