{
  "id": 7313378,
  "type": "Feature",
  "properties": {
    "tgn:hierarchy":[
        "tgn:7313378",
        "tgn:1001699",
        "tgn:1000049",
        "tgn:1000002",
        "tgn:7029392"
    ],
    "tgn:id":7313378,
    "tgn:name":"Lliguim\u00e1n, Ensenada",
    "tgn:placetype":[
        "aat:300132316"
    ]
},
  "bbox": [],
  "geometry": {"coordinates":[-72.787778,-41.99],"type":"Point"}
}