{
  "id": 2125176,
  "type": "Feature",
  "properties": {
    "tgn:hierarchy":[
        "tgn:2125176",
        "tgn:1000001",
        "tgn:7012149",
        "tgn:7014160",
        "tgn:7007919",
        "tgn:7029392"
    ],
    "tgn:id":2125176,
    "tgn:name":"Accotink Bay",
    "tgn:placetype":[
        "aat:300132316"
    ]
},
  "bbox": [],
  "geometry": {"coordinates":[-77.15,38.6833],"type":"Point"}
}