{
  "id": 2519212,
  "type": "Feature",
  "properties": {
    "tgn:hierarchy":[
        "tgn:2519212",
        "tgn:1000001",
        "tgn:2001481",
        "tgn:7012149",
        "tgn:7007709",
        "tgn:7029392"
    ],
    "tgn:id":2519212,
    "tgn:name":"Moccasin Creek",
    "tgn:placetype":[
        "aat:300008706"
    ]
},
  "bbox": [],
  "geometry": {"coordinates":[-84.1833,35.1833],"type":"Point"}
}