{
  "id": 7033266,
  "type": "Feature",
  "properties": {
    "tgn:hierarchy":[
        "tgn:7033266",
        "tgn:1003459",
        "tgn:1000003",
        "tgn:7002993",
        "tgn:1000080",
        "tgn:7029392"
    ],
    "tgn:id":7033266,
    "tgn:name":"Alberone",
    "tgn:placetype":[
        "aat:300008347"
    ]
},
  "bbox": [],
  "geometry": {"coordinates":[13.508889,45.756667],"type":"Point"}
}