{
  "id": 2644970,
  "type": "Feature",
  "properties": {
    "tgn:hierarchy":[
        "tgn:2644970",
        "tgn:1000001",
        "tgn:7012149",
        "tgn:2002339",
        "tgn:7007922",
        "tgn:7029392"
    ],
    "tgn:id":2644970,
    "tgn:name":"Saturday Islands",
    "tgn:placetype":[
        "aat:300386853"
    ]
},
  "bbox": [],
  "geometry": {"coordinates":[-88.65,45.0167],"type":"Point"}
}