{
  "id": 2458369,
  "type": "Feature",
  "properties": {
    "tgn:hierarchy":[
        "tgn:2458369",
        "tgn:1000001",
        "tgn:7012149",
        "tgn:2000230",
        "tgn:7007158",
        "tgn:7029392"
    ],
    "tgn:id":2458369,
    "tgn:name":"Little Muddy Gulch",
    "tgn:placetype":[
        "aat:300008761"
    ]
},
  "bbox": [],
  "geometry": {"coordinates":[-107.5833,39.25],"type":"Point"}
}