{
  "id": 2203857,
  "type": "Feature",
  "properties": {
    "tgn:hierarchy":[
        "tgn:2203857",
        "tgn:1000001",
        "tgn:7012149",
        "tgn:2000213",
        "tgn:7007158",
        "tgn:7029392"
    ],
    "tgn:id":2203857,
    "tgn:name":"Buckskin Joe",
    "tgn:placetype":[
        "aat:300008347"
    ]
},
  "bbox": [],
  "geometry": {"coordinates":[-105.3167,38.4667],"type":"Point"}
}