{
  "id": 7400677,
  "type": "Feature",
  "properties": {
    "tgn:hierarchy":[
        "tgn:7400677",
        "tgn:1000001",
        "tgn:7005599",
        "tgn:7005560",
        "tgn:7029392"
    ],
    "tgn:id":7400677,
    "tgn:name":"La Mata del Padre",
    "tgn:placetype":[
        "aat:300008347"
    ]
},
  "bbox": [],
  "geometry": {"coordinates":[-96.308333,18.575],"type":"Point"}
}