{
  "id": 7510552,
  "type": "Feature",
  "properties": {
    "tgn:hierarchy":[
        "tgn:7510552",
        "tgn:1008380",
        "tgn:7520093",
        "tgn:1000226",
        "tgn:1000006",
        "tgn:7029392"
    ],
    "tgn:id":7510552,
    "tgn:name:en":"Upokonui",
    "tgn:placetype":[
        "aat:300008347"
    ]
},
  "bbox": [],
  "geometry": {"coordinates":[175.216667,-39.783333],"type":"Point"}
}