{
  "id": 2141910,
  "type": "Feature",
  "properties": {
    "tgn:hierarchy":[
        "tgn:2141910",
        "tgn:1000001",
        "tgn:7012149",
        "tgn:2000913",
        "tgn:7007256",
        "tgn:7029392"
    ],
    "tgn:id":2141910,
    "tgn:name":"Baccus",
    "tgn:placetype":[
        "aat:300008347"
    ]
},
  "bbox": [],
  "geometry": {"coordinates":[-93.45,32.9333],"type":"Point"}
}