{
  "id": 7414983,
  "type": "Feature",
  "properties": {
    "tgn:hierarchy":[
        "tgn:7414983",
        "tgn:7005584",
        "tgn:1000001",
        "tgn:7005560",
        "tgn:7029392"
    ],
    "tgn:id":7414983,
    "tgn:name":"Veredas",
    "tgn:placetype":[
        "aat:300008347"
    ]
},
  "bbox": [],
  "geometry": {"coordinates":[-101.845,20.255556],"type":"Point"}
}