{
  "id": 7347577,
  "type": "Feature",
  "properties": {
    "tgn:hierarchy":[
        "tgn:7347577",
        "tgn:7002820",
        "tgn:7030216",
        "tgn:1000003",
        "tgn:1000095",
        "tgn:7029392"
    ],
    "tgn:id":7347577,
    "tgn:name":"Arbucias, Riera de",
    "tgn:placetype":[
        "aat:300008699"
    ]
},
  "bbox": [],
  "geometry": {"coordinates":[2.625855,41.731673],"type":"Point"}
}