{
  "id": 1020263,
  "type": "Feature",
  "properties": {
    "tgn:hierarchy":[
        "tgn:1020263",
        "tgn:1000571",
        "tgn:1000046",
        "tgn:1000002",
        "tgn:7029392"
    ],
    "tgn:id":1020263,
    "tgn:name":"Camargo",
    "tgn:placetype":[
        "aat:300008347"
    ]
},
  "bbox": [],
  "geometry": {"coordinates":[-65.25,-20.6333],"type":"Point"}
}