{
  "id": 7219895,
  "type": "Feature",
  "properties": {
    "tgn:hierarchy":[
        "tgn:7219895",
        "tgn:7011330",
        "tgn:7002674",
        "tgn:1000003",
        "tgn:1000074",
        "tgn:7029392"
    ],
    "tgn:id":7219895,
    "tgn:name":"Panag\u00eda",
    "tgn:placetype":[
        "aat:300007466"
    ]
},
  "bbox": [],
  "geometry": {"coordinates":[27.273333,36.838611],"type":"Point"}
}