<<<<<<< HEAD
{
  "id": 7353093,
  "type": "Feature",
  "properties": {
    "tgn:hierarchy":[
        "tgn:7353093",
        "tgn:7005585",
        "tgn:1000001",
        "tgn:7005560",
        "tgn:7029392"
    ],
    "tgn:id":7353093,
    "tgn:name":"Ameyaltepec",
    "tgn:placetype":[
        "aat:300008347"
    ]
},
  "bbox": [],
  "geometry": {"coordinates":[-99.5,17.966667],"type":"Point"}
}
=======
{"geometry":{"type":"Point","coordinates":[-99.500000,17.966667]},"type":"Feature","properties":{"hierarchy":["tgn:7353093","tgn:7005585","tgn:1000001","tgn:7005560","tgn:7029392"],"placetype":["aat:300008347"],"id":7353093,"name:xx":"Ameyaltepec"}}
>>>>>>> 03f74aca74312dbeaf24d7e61306dd6a786dc3d0
