{
  "id": 7040605,
  "type": "Feature",
  "properties": {
    "tgn:hierarchy":[
        "tgn:7040605",
        "tgn:7003002",
        "tgn:7003005",
        "tgn:1000003",
        "tgn:1000080",
        "tgn:7029392"
    ],
    "tgn:id":7040605,
    "tgn:name":"San Simeone",
    "tgn:placetype":[
        "aat:300008347"
    ]
},
  "bbox": [],
  "geometry": {"coordinates":[15.016667,40.85],"type":"Point"}
}