{
  "id": 1095993,
  "type": "Feature",
  "properties": {
    "tgn:hierarchy":[
        "tgn:1095993",
        "tgn:7001242",
        "tgn:1001458",
        "tgn:1000209",
        "tgn:7029392"
    ],
    "tgn:id":1095993,
    "tgn:name":"Mushima",
    "tgn:placetype":[
        "aat:300008347"
    ]
},
  "bbox": [],
  "geometry": {"coordinates":[24.9333,-14.1667],"type":"Point"}
}