{
  "id": 2297964,
  "type": "Feature",
  "properties": {
    "tgn:hierarchy":[
        "tgn:2297964",
        "tgn:1000001",
        "tgn:7012149",
        "tgn:2002246",
        "tgn:7007920",
        "tgn:7029392"
    ],
    "tgn:id":2297964,
    "tgn:name":"Dry Island",
    "tgn:placetype":[
        "aat:300055621"
    ]
},
  "bbox": [],
  "geometry": {"coordinates":[-119.7333,46.85],"type":"Point"}
}