<<<<<<< HEAD
{
  "id": 7350930,
  "type": "Feature",
  "properties": {
    "tgn:hierarchy":[
        "tgn:7350930",
        "tgn:1000001",
        "tgn:7005595",
        "tgn:7005560",
        "tgn:7029392"
    ],
    "tgn:id":7350930,
    "tgn:name":"Bledal",
    "tgn:placetype":[
        "aat:300008347"
    ]
},
  "bbox": [],
  "geometry": {"coordinates":[-107.812222,24.823056],"type":"Point"}
}
=======
{"geometry":{"type":"Point","coordinates":[-107.812222,24.823056]},"type":"Feature","properties":{"hierarchy":["tgn:7350930","tgn:1000001","tgn:7005595","tgn:7005560","tgn:7029392"],"placetype":["aat:300008347"],"id":7350930,"name:xx":"Bledal"}}
>>>>>>> 03f74aca74312dbeaf24d7e61306dd6a786dc3d0
