{
  "id": 2266886,
  "type": "Feature",
  "properties": {
    "tgn:hierarchy":[
        "tgn:2266886",
        "tgn:1000001",
        "tgn:2001701",
        "tgn:7012149",
        "tgn:7007708",
        "tgn:7029392"
    ],
    "tgn:id":2266886,
    "tgn:name":"Crescent Valley",
    "tgn:placetype":[
        "aat:300055621"
    ]
},
  "bbox": [],
  "geometry": {"coordinates":[-123.25,44.6167],"type":"Point"}
}