{
  "id": 7419477,
  "type": "Feature",
  "properties": {
    "tgn:hierarchy":[
        "tgn:7419477",
        "tgn:7005579",
        "tgn:1000001",
        "tgn:7005560",
        "tgn:7029392"
    ],
    "tgn:id":7419477,
    "tgn:name":"Presa El Muerto",
    "tgn:placetype":[
        "aat:300006191"
    ]
},
  "bbox": [],
  "geometry": {"coordinates":[-102.216667,21.733333],"type":"Point"}
}