{
  "id": 2687604,
  "type": "Feature",
  "properties": {
    "tgn:hierarchy":[
        "tgn:2687604",
        "tgn:1000001",
        "tgn:2000502",
        "tgn:7012149",
        "tgn:7007251",
        "tgn:7029392"
    ],
    "tgn:id":2687604,
    "tgn:name":"Spring Point Creek",
    "tgn:placetype":[
        "aat:300008706"
    ]
},
  "bbox": [],
  "geometry": {"coordinates":[-88.4167,39.2667],"type":"Point"}
}