{
  "id": 2060132,
  "type": "Feature",
  "properties": {
    "tgn:hierarchy":[
        "tgn:2060132",
        "tgn:1000001",
        "tgn:7012149",
        "tgn:2001222",
        "tgn:7007523",
        "tgn:7029392"
    ],
    "tgn:id":2060132,
    "tgn:name":"Point Pleasant",
    "tgn:placetype":[
        "aat:300008347"
    ]
},
  "bbox": [],
  "geometry": {"coordinates":[-89.5667,36.45],"type":"Point"}
}