{
  "id": 7484449,
  "type": "Feature",
  "properties": {
    "tgn:hierarchy":[
        "tgn:7484449",
        "tgn:7468018",
        "tgn:1000004",
        "tgn:1000141",
        "tgn:7029392"
    ],
    "tgn:id":7484449,
    "tgn:name":"Keng Shan",
    "tgn:placetype":[
        "aat:300008777"
    ]
},
  "bbox": [],
  "geometry": {"coordinates":[120.524444,23.512778],"type":"Point"}
}