{
  "id": 2713952,
  "type": "Feature",
  "properties": {
    "tgn:hierarchy":[
        "tgn:2713952",
        "tgn:1000001",
        "tgn:7012149",
        "tgn:2000219",
        "tgn:7007158",
        "tgn:7029392"
    ],
    "tgn:id":2713952,
    "tgn:name":"Teeple Reservoir",
    "tgn:placetype":[
        "aat:300006191"
    ]
},
  "bbox": [],
  "geometry": {"coordinates":[-104.4833,37.8167],"type":"Point"}
}