{
  "id": 2291629,
  "type": "Feature",
  "properties": {
    "tgn:hierarchy":[
        "tgn:2291629",
        "tgn:1000001",
        "tgn:7012149",
        "tgn:2001455",
        "tgn:7007566",
        "tgn:7029392"
    ],
    "tgn:id":2291629,
    "tgn:name":"Dollar Tank",
    "tgn:placetype":[
        "aat:300006191"
    ]
},
  "bbox": [],
  "geometry": {"coordinates":[-107.5833,33.0333],"type":"Point"}
}