{
  "id": 2043830,
  "type": "Feature",
  "properties": {
    "tgn:hierarchy":[
        "tgn:2043830",
        "tgn:1000001",
        "tgn:7012149",
        "tgn:2000893",
        "tgn:7007256",
        "tgn:7029392"
    ],
    "tgn:id":2043830,
    "tgn:name":"Rapides",
    "tgn:placetype":[
        "aat:300008347",
        "aat:300387210"
    ]
},
  "bbox": [],
  "geometry": {"coordinates":[-92.5833,31.35],"type":"Point"}
}