{
  "id": 7561183,
  "type": "Feature",
  "properties": {
    "tgn:hierarchy":[
        "tgn:7561183",
        "tgn:1000004",
        "tgn:7000198",
        "tgn:7016722",
        "tgn:7029392"
    ],
    "tgn:id":7561183,
    "tgn:name:en":"Repura",
    "tgn:placetype":[
        "aat:300008347"
    ]
},
  "bbox": [],
  "geometry": {"coordinates":[79.138752,26.901881],"type":"Point"}
}