{
  "id": 2441316,
  "type": "Feature",
  "properties": {
    "tgn:hierarchy":[
        "tgn:2441316",
        "tgn:1000001",
        "tgn:7012149",
        "tgn:2000490",
        "tgn:7007250",
        "tgn:7029392"
    ],
    "tgn:id":2441316,
    "tgn:name":"Knox Canyon",
    "tgn:placetype":[
        "aat:300008761"
    ]
},
  "bbox": [],
  "geometry": {"coordinates":[-112.6833,42.5333],"type":"Point"}
}