<<<<<<< HEAD
{
  "id": 2409672,
  "type": "Feature",
  "properties": {
    "tgn:hierarchy":[
        "tgn:2409672",
        "tgn:1000001",
        "tgn:7012149",
        "tgn:1002375",
        "tgn:7007255",
        "tgn:7029392"
    ],
    "tgn:id":2409672,
    "tgn:name":"Ike Stacy Branch",
    "tgn:placetype":[
        "aat:300008699"
    ]
},
  "bbox": [],
  "geometry": {"coordinates":[-83.4833,38.3833],"type":"Point"}
}
=======
{"geometry":{"type":"Point","coordinates":[-83.483300,38.383300]},"type":"Feature","properties":{"hierarchy":["tgn:2409672","tgn:1000001","tgn:7012149","tgn:1002375","tgn:7007255","tgn:7029392"],"placetype":["aat:300008699"],"id":2409672,"name:xx":"Ike Stacy Branch"}}
>>>>>>> 03f74aca74312dbeaf24d7e61306dd6a786dc3d0
