{
  "id": 1037201,
  "type": "Feature",
  "properties": {
    "tgn:hierarchy":[
        "tgn:1037201",
        "tgn:1000003",
        "tgn:7003685",
        "tgn:7000084",
        "tgn:7029392"
    ],
    "tgn:id":1037201,
    "tgn:name":"Lichtenstein",
    "tgn:placetype":[
        "aat:300008347"
    ]
},
  "bbox": [],
  "geometry": {"coordinates":[12.65,50.75],"type":"Point"}
}