{
  "id": 7383757,
  "type": "Feature",
  "properties": {
    "tgn:hierarchy":[
        "tgn:7383757",
        "tgn:1000001",
        "tgn:1001960",
        "tgn:7005560",
        "tgn:7029392"
    ],
    "tgn:id":7383757,
    "tgn:name":"N\u00e1cori, R\u00edo",
    "tgn:placetype":[
        "aat:300008699"
    ]
},
  "bbox": [],
  "geometry": {"coordinates":[-108.95,29.35],"type":"Point"}
}