{
  "id": 7006309,
  "type": "Feature",
  "properties": {
    "tgn:hierarchy":[
        "tgn:7006309",
        "tgn:7003162",
        "tgn:1000003",
        "tgn:7009760",
        "tgn:1000080",
        "tgn:7029392"
    ],
    "tgn:id":7006309,
    "tgn:name":"Badia Prataglia",
    "tgn:placetype":[
        "aat:300008347"
    ]
},
  "bbox": [],
  "geometry": {"coordinates":[11.866667,43.783333],"type":"Point"}
}