{
  "id": 7447084,
  "type": "Feature",
  "properties": {
    "tgn:hierarchy":[
        "tgn:7447084",
        "tgn:7002444",
        "tgn:1000003",
        "tgn:7008082",
        "tgn:7008591",
        "tgn:7029392"
    ],
    "tgn:id":7447084,
    "tgn:name:en":"Skeabost",
    "tgn:placetype":[
        "aat:300008347"
    ]
},
  "bbox": [],
  "geometry": {"coordinates":[-6.316667,57.45],"type":"Point"}
}