{
  "id": 2451612,
  "type": "Feature",
  "properties": {
    "tgn:hierarchy":[
        "tgn:2451612",
        "tgn:1000001",
        "tgn:7012149",
        "tgn:2001056",
        "tgn:7007521",
        "tgn:7029392"
    ],
    "tgn:id":2451612,
    "tgn:name":"Little Bear Creek",
    "tgn:placetype":[
        "aat:300008706"
    ]
},
  "bbox": [],
  "geometry": {"coordinates":[-92.7333,46.0833],"type":"Point"}
}