{
  "id": 1128703,
  "type": "Feature",
  "properties": {
    "tgn:hierarchy":[
        "tgn:1128703",
        "tgn:1000001",
        "tgn:7012149",
        "tgn:7029392"
    ],
    "tgn:id":1128703,
    "tgn:name":"Platte",
    "tgn:placetype":[
        "aat:300008707"
    ]
},
  "bbox": [],
  "geometry": {"coordinates":[-94.8333,39.25],"type":"Point"}
}