{
  "id": 7358065,
  "type": "Feature",
  "properties": {
    "tgn:hierarchy":[
        "tgn:7358065",
        "tgn:1001853",
        "tgn:1000001",
        "tgn:7005560",
        "tgn:7029392"
    ],
    "tgn:id":7358065,
    "tgn:name":"Ejido Minerva",
    "tgn:placetype":[
        "aat:300008347"
    ]
},
  "bbox": [],
  "geometry": {"coordinates":[-100.95,28.533333],"type":"Point"}
}