{
  "id": 2283043,
  "type": "Feature",
  "properties": {
    "tgn:hierarchy":[
        "tgn:2283043",
        "tgn:1000001",
        "tgn:7006451",
        "tgn:2000093",
        "tgn:7012149",
        "tgn:7029392"
    ],
    "tgn:id":2283043,
    "tgn:name":"Del Shay Spring",
    "tgn:placetype":[
        "aat:300008697"
    ]
},
  "bbox": [],
  "geometry": {"coordinates":[-111.2333,33.9667],"type":"Point"}
}