{
  "id": 2004937,
  "type": "Feature",
  "properties": {
    "tgn:hierarchy":[
        "tgn:2004937",
        "tgn:7002659",
        "tgn:1000001",
        "tgn:7012149",
        "tgn:2000060",
        "tgn:7029392"
    ],
    "tgn:id":2004937,
    "tgn:name":"Plantersville",
    "tgn:placetype":[
        "aat:300008347"
    ]
},
  "bbox": [],
  "geometry": {"coordinates":[-86.2333,33.3667],"type":"Point"}
}