<<<<<<< HEAD
{
  "id": 2701999,
  "type": "Feature",
  "properties": {
    "tgn:hierarchy":[
        "tgn:2701999",
        "tgn:1000001",
        "tgn:7012149",
        "tgn:2001708",
        "tgn:7007708",
        "tgn:7029392"
    ],
    "tgn:id":2701999,
    "tgn:name":"Sugarloaf Spring",
    "tgn:placetype":[
        "aat:300008697"
    ]
},
  "bbox": [],
  "geometry": {"coordinates":[-118.9167,44.2167],"type":"Point"}
}
=======
{"geometry":{"type":"Point","coordinates":[-118.916700,44.216700]},"type":"Feature","properties":{"hierarchy":["tgn:2701999","tgn:1000001","tgn:7012149","tgn:2001708","tgn:7007708","tgn:7029392"],"placetype":["aat:300008697"],"id":2701999,"name:xx":"Sugarloaf Spring"}}
>>>>>>> 03f74aca74312dbeaf24d7e61306dd6a786dc3d0
