{
  "id": 7232983,
  "type": "Feature",
  "properties": {
    "tgn:hierarchy":[
        "tgn:7232983",
        "tgn:7002690",
        "tgn:7012056",
        "tgn:1000003",
        "tgn:1000074",
        "tgn:7029392"
    ],
    "tgn:id":7232983,
    "tgn:name":"Lo\u00farai",
    "tgn:placetype":[
        "aat:300008347"
    ]
},
  "bbox": [],
  "geometry": {"coordinates":[25.066667,35.05],"type":"Point"}
}