<<<<<<< HEAD
{
  "id": 2405839,
  "type": "Feature",
  "properties": {
    "tgn:hierarchy":[
        "tgn:2405839",
        "tgn:1000001",
        "tgn:7012149",
        "tgn:7007157",
        "tgn:7029392"
    ],
    "tgn:id":2405839,
    "tgn:name":"Hull Mountain",
    "tgn:placetype":[
        "aat:300008798"
    ]
},
  "bbox": [],
  "geometry": {"coordinates":[-122.9333,39.5167],"type":"Point"}
}
=======
{"geometry":{"type":"Point","coordinates":[-122.933300,39.516700]},"type":"Feature","properties":{"hierarchy":["tgn:2405839","tgn:1000001","tgn:7012149","tgn:7007157","tgn:7029392"],"placetype":["aat:300008798"],"id":2405839,"name:xx":"Hull Mountain"}}
>>>>>>> 03f74aca74312dbeaf24d7e61306dd6a786dc3d0
