{
  "id": 2406962,
  "type": "Feature",
  "properties": {
    "tgn:hierarchy":[
        "tgn:2406962",
        "tgn:1000001",
        "tgn:2002316",
        "tgn:7012149",
        "tgn:7007922",
        "tgn:7029392"
    ],
    "tgn:id":2406962,
    "tgn:name":"Hunter Island",
    "tgn:placetype":[
        "aat:300008791"
    ]
},
  "bbox": [],
  "geometry": {"coordinates":[-91.15,43.0167],"type":"Point"}
}