<<<<<<< HEAD
{
  "id": 2760615,
  "type": "Feature",
  "properties": {
    "tgn:hierarchy":[
        "tgn:2760615",
        "tgn:2002308",
        "tgn:1000001",
        "tgn:7012149",
        "tgn:7007922",
        "tgn:7029392"
    ],
    "tgn:id":2760615,
    "tgn:name":"West Fork White River",
    "tgn:placetype":[
        "aat:300008707"
    ]
},
  "bbox": [],
  "geometry": {"coordinates":[-91.3,46.4667],"type":"Point"}
}
=======
{"geometry":{"type":"Point","coordinates":[-91.300000,46.466700]},"type":"Feature","properties":{"hierarchy":["tgn:2760615","tgn:2002308","tgn:1000001","tgn:7012149","tgn:7007922","tgn:7029392"],"placetype":["aat:300008707"],"id":2760615,"name:xx":"West Fork White River"}}
>>>>>>> 03f74aca74312dbeaf24d7e61306dd6a786dc3d0
