<<<<<<< HEAD
{
  "id": 2408198,
  "type": "Feature",
  "properties": {
    "tgn:hierarchy":[
        "tgn:2408198",
        "tgn:1002338",
        "tgn:1000001",
        "tgn:7012149",
        "tgn:7007516",
        "tgn:7029392"
    ],
    "tgn:id":2408198,
    "tgn:name":"Hurst Creek",
    "tgn:placetype":[
        "aat:300008706"
    ]
},
  "bbox": [],
  "geometry": {"coordinates":[-76.0,38.5333],"type":"Point"}
}
=======
{"geometry":{"type":"Point","coordinates":[-76.000000,38.533300]},"type":"Feature","properties":{"hierarchy":["tgn:2408198","tgn:1002338","tgn:1000001","tgn:7012149","tgn:7007516","tgn:7029392"],"placetype":["aat:300008706"],"id":2408198,"name:xx":"Hurst Creek"}}
>>>>>>> 03f74aca74312dbeaf24d7e61306dd6a786dc3d0
