{
  "id": 2240221,
  "type": "Feature",
  "properties": {
    "tgn:hierarchy":[
        "tgn:2240221",
        "tgn:1000001",
        "tgn:7012149",
        "tgn:2002383",
        "tgn:7007923",
        "tgn:7029392"
    ],
    "tgn:id":2240221,
    "tgn:name":"Circle Springs Draw",
    "tgn:placetype":[
        "aat:300008761"
    ]
},
  "bbox": [],
  "geometry": {"coordinates":[-109.1167,41.3333],"type":"Point"}
}