{
  "id": 2646999,
  "type": "Feature",
  "properties": {
    "tgn:hierarchy":[
        "tgn:2646999",
        "tgn:1000001",
        "tgn:2001009",
        "tgn:7012149",
        "tgn:7007521",
        "tgn:7029392"
    ],
    "tgn:id":2646999,
    "tgn:name":"Schafer Lake",
    "tgn:placetype":[
        "aat:300008680"
    ]
},
  "bbox": [],
  "geometry": {"coordinates":[-93.85,46.8333],"type":"Point"}
}