{
  "id": 1094760,
  "type": "Feature",
  "properties": {
    "tgn:hierarchy":[
        "tgn:1094760",
        "tgn:7001242",
        "tgn:1001739",
        "tgn:1000203",
        "tgn:7029392"
    ],
    "tgn:id":1094760,
    "tgn:name":"Mtakuja",
    "tgn:placetype":[
        "aat:300008347"
    ]
},
  "bbox": [],
  "geometry": {"coordinates":[30.6167,-7.35],"type":"Point"}
}