{
  "id": 2720151,
  "type": "Feature",
  "properties": {
    "tgn:hierarchy":[
        "tgn:2720151",
        "tgn:1000001",
        "tgn:7012149",
        "tgn:1002990",
        "tgn:7007708",
        "tgn:7029392"
    ],
    "tgn:id":2720151,
    "tgn:name":"Threemile Ditch",
    "tgn:placetype":[
        "aat:300006075"
    ]
},
  "bbox": [],
  "geometry": {"coordinates":[-121.3167,45.2333],"type":"Point"}
}