{
  "id": 2487044,
  "type": "Feature",
  "properties": {
    "tgn:hierarchy":[
        "tgn:2487044",
        "tgn:1000001",
        "tgn:7012149",
        "tgn:2002293",
        "tgn:7013961",
        "tgn:7029392"
    ],
    "tgn:id":2487044,
    "tgn:name":"Lee Run",
    "tgn:placetype":[
        "aat:300008699"
    ]
},
  "bbox": [],
  "geometry": {"coordinates":[-81.2667,38.8667],"type":"Point"}
}