<<<<<<< HEAD
{
  "id": 7475185,
  "type": "Feature",
  "properties": {
    "tgn:hierarchy":[
        "tgn:7475185",
        "tgn:1000004",
        "tgn:1000454",
        "tgn:1000141",
        "tgn:7029392"
    ],
    "tgn:id":7475185,
    "tgn:name":"Xishihu",
    "tgn:placetype":[
        "aat:300008795"
    ]
},
  "bbox": [],
  "geometry": {"coordinates":[121.603913,25.252963],"type":"Point"}
}
=======
{"geometry":{"type":"Point","coordinates":[121.603913,25.252963]},"type":"Feature","properties":{"hierarchy":["tgn:7475185","tgn:1000004","tgn:1000454","tgn:1000141","tgn:7029392"],"placetype":["aat:300008795"],"id":7475185,"name:xx":"Xishihu"}}
>>>>>>> 03f74aca74312dbeaf24d7e61306dd6a786dc3d0
