{
  "id": 2676763,
  "type": "Feature",
  "properties": {
    "tgn:hierarchy":[
        "tgn:2676763",
        "tgn:1000001",
        "tgn:7012149",
        "tgn:2000226",
        "tgn:7007158",
        "tgn:7029392"
    ],
    "tgn:id":2676763,
    "tgn:name":"South Branch Boxelder Creek",
    "tgn:placetype":[
        "aat:300008706"
    ]
},
  "bbox": [],
  "geometry": {"coordinates":[-105.2667,40.9667],"type":"Point"}
}