{
  "id": 2608548,
  "type": "Feature",
  "properties": {
    "tgn:hierarchy":[
        "tgn:2608548",
        "tgn:1000001",
        "tgn:7012149",
        "tgn:1002977",
        "tgn:7007240",
        "tgn:7029392"
    ],
    "tgn:id":2608548,
    "tgn:name":"Rattlesnake Island",
    "tgn:placetype":[
        "aat:300008791"
    ]
},
  "bbox": [],
  "geometry": {"coordinates":[-81.0167,28.8833],"type":"Point"}
}