{
  "id": 1113459,
  "type": "Feature",
  "properties": {
    "tgn:hierarchy":[
        "tgn:1113459",
        "tgn:1000001",
        "tgn:1002902",
        "tgn:7012149",
        "tgn:7007516",
        "tgn:7029392"
    ],
    "tgn:id":1113459,
    "tgn:name":"Monie Bay",
    "tgn:placetype":[
        "aat:300132316"
    ]
},
  "bbox": [],
  "geometry": {"coordinates":[-75.8333,38.2167],"type":"Point"}
}