{
  "id": 2609990,
  "type": "Feature",
  "properties": {
    "tgn:hierarchy":[
        "tgn:2609990",
        "tgn:1000001",
        "tgn:7012149",
        "tgn:1002512",
        "tgn:7007252",
        "tgn:7029392"
    ],
    "tgn:id":2609990,
    "tgn:name":"Record Lateral",
    "tgn:placetype":[
        "aat:300006075"
    ]
},
  "bbox": [],
  "geometry": {"coordinates":[-86.9667,41.05],"type":"Point"}
}