{
  "id": 7094349,
  "type": "Feature",
  "properties": {
    "tgn:hierarchy":[
        "tgn:7094349",
        "tgn:1000003",
        "tgn:7003676",
        "tgn:7000084",
        "tgn:7029392"
    ],
    "tgn:id":7094349,
    "tgn:name":"Schwarzes Meer",
    "tgn:placetype":[
        "aat:300008688"
    ]
},
  "bbox": [],
  "geometry": {"coordinates":[8.633333,52.733333],"type":"Point"}
}