<<<<<<< HEAD
{
  "id": 7479012,
  "type": "Feature",
  "properties": {
    "tgn:hierarchy":[
        "tgn:7479012",
        "tgn:1000004",
        "tgn:7490934",
        "tgn:1000141",
        "tgn:7029392"
    ],
    "tgn:id":7479012,
    "tgn:name":"Sanbaierwan",
    "tgn:placetype":[
        "aat:300008347"
    ]
},
  "bbox": [],
  "geometry": {"coordinates":[120.128611,23.100833],"type":"Point"}
}
=======
{"geometry":{"type":"Point","coordinates":[120.128611,23.100833]},"type":"Feature","properties":{"hierarchy":["tgn:7479012","tgn:1000004","tgn:7490934","tgn:1000141","tgn:7029392"],"placetype":["aat:300008347"],"id":7479012,"name:xx":"Sanbaierwan"}}
>>>>>>> 03f74aca74312dbeaf24d7e61306dd6a786dc3d0
