<<<<<<< HEAD
{
  "id": 7118313,
  "type": "Feature",
  "properties": {
    "tgn:hierarchy":[
        "tgn:7118313",
        "tgn:1000003",
        "tgn:7003676",
        "tgn:7000084",
        "tgn:7029392"
    ],
    "tgn:id":7118313,
    "tgn:name":"Papageien-Berg",
    "tgn:placetype":[
        "aat:300008777"
    ]
},
  "bbox": [],
  "geometry": {"coordinates":[10.433333,53.3],"type":"Point"}
}
=======
{"geometry":{"type":"Point","coordinates":[10.433333,53.300000]},"type":"Feature","properties":{"hierarchy":["tgn:7118313","tgn:1000003","tgn:7003676","tgn:7000084","tgn:7029392"],"placetype":["aat:300008777"],"id":7118313,"name:xx":"Papageien-Berg"}}
>>>>>>> 03f74aca74312dbeaf24d7e61306dd6a786dc3d0
