{
  "id": 7413860,
  "type": "Feature",
  "properties": {
    "tgn:hierarchy":[
        "tgn:7413860",
        "tgn:1000001",
        "tgn:7005596",
        "tgn:7005560",
        "tgn:7029392"
    ],
    "tgn:id":7413860,
    "tgn:name:es":"Manuel Vuelta y Ray\u00f3n",
    "tgn:placetype":[
        "aat:300008347"
    ]
},
  "bbox": [],
  "geometry": {"coordinates":[-92.95,17.704167],"type":"Point"}
}