{
  "id": 2697137,
  "type": "Feature",
  "properties": {
    "tgn:hierarchy":[
        "tgn:2697137",
        "tgn:1000001",
        "tgn:2002312",
        "tgn:7012149",
        "tgn:7007922",
        "tgn:7029392"
    ],
    "tgn:id":2697137,
    "tgn:name":"Stony Brook",
    "tgn:placetype":[
        "aat:300008699"
    ]
},
  "bbox": [],
  "geometry": {"coordinates":[-88.25,44.05],"type":"Point"}
}