{
  "id": 2033960,
  "type": "Feature",
  "properties": {
    "tgn:hierarchy":[
        "tgn:2033960",
        "tgn:1000001",
        "tgn:7012149",
        "tgn:2000552",
        "tgn:7007252",
        "tgn:7029392"
    ],
    "tgn:id":2033960,
    "tgn:name":"Upton",
    "tgn:placetype":[
        "aat:300008347",
        "aat:300387210"
    ]
},
  "bbox": [],
  "geometry": {"coordinates":[-87.95,37.95],"type":"Point"}
}