{
  "id": 7589067,
  "type": "Feature",
  "properties": {
    "tgn:hierarchy":[
        "tgn:7589067",
        "tgn:1000004",
        "tgn:1001869",
        "tgn:7000198",
        "tgn:7029392"
    ],
    "tgn:id":7589067,
    "tgn:name:en":"Panch\u0101sara N\u0101na",
    "tgn:placetype":[
        "aat:300008347"
    ]
},
  "bbox": [],
  "geometry": {"coordinates":[70.120055,22.234831],"type":"Point"}
}