{
  "id": 2116899,
  "type": "Feature",
  "properties": {
    "tgn:hierarchy":[
        "tgn:2116899",
        "tgn:1000001",
        "tgn:7012149",
        "tgn:1002785",
        "tgn:7007920",
        "tgn:7029392"
    ],
    "tgn:id":2116899,
    "tgn:name":"Sunrise Beach",
    "tgn:placetype":[
        "aat:300008347",
        "aat:300387210"
    ]
},
  "bbox": [],
  "geometry": {"coordinates":[-122.55,47.3333],"type":"Point"}
}