{
  "id": 7529069,
  "type": "Feature",
  "properties": {
    "tgn:hierarchy":[
        "tgn:7529069",
        "tgn:7001242",
        "tgn:7016833",
        "tgn:1001083",
        "tgn:7029392"
    ],
    "tgn:id":7529069,
    "tgn:name:en":"Tafla, W\u00e2d\u00ee",
    "tgn:placetype":[
        "aat:300379998"
    ]
},
  "bbox": [],
  "geometry": {"coordinates":[31.216667,29.833333],"type":"Point"}
}