<<<<<<< HEAD
{
  "id": 7117869,
  "type": "Feature",
  "properties": {
    "tgn:hierarchy":[
        "tgn:7117869",
        "tgn:1000003",
        "tgn:7003677",
        "tgn:7000084",
        "tgn:7029392"
    ],
    "tgn:id":7117869,
    "tgn:name":"Odenheimer-Bach",
    "tgn:placetype":[
        "aat:300008699"
    ]
},
  "bbox": [],
  "geometry": {"coordinates":[8.9,51.616667],"type":"Point"}
}
=======
{"geometry":{"type":"Point","coordinates":[8.900000,51.616667]},"type":"Feature","properties":{"hierarchy":["tgn:7117869","tgn:1000003","tgn:7003677","tgn:7000084","tgn:7029392"],"placetype":["aat:300008699"],"id":7117869,"name:xx":"Odenheimer-Bach"}}
>>>>>>> 03f74aca74312dbeaf24d7e61306dd6a786dc3d0
