{
  "id": 2616038,
  "type": "Feature",
  "properties": {
    "tgn:hierarchy":[
        "tgn:2616038",
        "tgn:1000001",
        "tgn:7006451",
        "tgn:7012149",
        "tgn:2000099",
        "tgn:7029392"
    ],
    "tgn:id":2616038,
    "tgn:name":"Rhine Ridge",
    "tgn:placetype":[
        "aat:300266640"
    ]
},
  "bbox": [],
  "geometry": {"coordinates":[-110.4167,34.2667],"type":"Point"}
}