{
  "id": 2187796,
  "type": "Feature",
  "properties": {
    "tgn:hierarchy":[
        "tgn:2187796",
        "tgn:1000001",
        "tgn:7012149",
        "tgn:2001452",
        "tgn:7007566",
        "tgn:7029392"
    ],
    "tgn:id":2187796,
    "tgn:name":"Bootlegger Spring",
    "tgn:placetype":[
        "aat:300008697"
    ]
},
  "bbox": [],
  "geometry": {"coordinates":[-107.85,36.85],"type":"Point"}
}