{
  "id": 7035756,
  "type": "Feature",
  "properties": {
    "tgn:hierarchy":[
        "tgn:7035756",
        "tgn:7002991",
        "tgn:1000003",
        "tgn:7002997",
        "tgn:1000080",
        "tgn:7029392"
    ],
    "tgn:id":7035756,
    "tgn:name":"Medone, Valle",
    "tgn:placetype":[
        "aat:300008761"
    ]
},
  "bbox": [],
  "geometry": {"coordinates":[12.183611,46.184444],"type":"Point"}
}