{
  "id": 2712579,
  "type": "Feature",
  "properties": {
    "tgn:hierarchy":[
        "tgn:2712579",
        "tgn:1000001",
        "tgn:7012149",
        "tgn:2002304",
        "tgn:7013961",
        "tgn:7029392"
    ],
    "tgn:id":2712579,
    "tgn:name":"Taylor Branch",
    "tgn:placetype":[
        "aat:300008699"
    ]
},
  "bbox": [],
  "geometry": {"coordinates":[-81.6833,37.5333],"type":"Point"}
}