{
  "id": 2282909,
  "type": "Feature",
  "properties": {
    "tgn:hierarchy":[
        "tgn:2282909",
        "tgn:1000001",
        "tgn:7012149",
        "tgn:2001420",
        "tgn:7007526",
        "tgn:7029392"
    ],
    "tgn:id":2282909,
    "tgn:name":"Defue Spring",
    "tgn:placetype":[
        "aat:300008697"
    ]
},
  "bbox": [],
  "geometry": {"coordinates":[-115.7333,40.0167],"type":"Point"}
}