{
  "id": 7406128,
  "type": "Feature",
  "properties": {
    "tgn:hierarchy":[
        "tgn:7406128",
        "tgn:7005585",
        "tgn:1000001",
        "tgn:7005560",
        "tgn:7029392"
    ],
    "tgn:id":7406128,
    "tgn:name":"Ceniza",
    "tgn:placetype":[
        "aat:300008347"
    ]
},
  "bbox": [],
  "geometry": {"coordinates":[-98.683333,16.516667],"type":"Point"}
}