{
  "id": 7098653,
  "type": "Feature",
  "properties": {
    "tgn:hierarchy":[
        "tgn:7098653",
        "tgn:7003669",
        "tgn:1000003",
        "tgn:7000084",
        "tgn:7029392"
    ],
    "tgn:id":7098653,
    "tgn:name":"Sonnen",
    "tgn:placetype":[
        "aat:300008347"
    ]
},
  "bbox": [],
  "geometry": {"coordinates":[11.033333,47.65],"type":"Point"}
}