{
  "id": 2570323,
  "type": "Feature",
  "properties": {
    "tgn:hierarchy":[
        "tgn:2570323",
        "tgn:1000001",
        "tgn:7016172",
        "tgn:7012149",
        "tgn:2000136",
        "tgn:7029392"
    ],
    "tgn:id":2570323,
    "tgn:name":"Pat Hollow",
    "tgn:placetype":[
        "aat:300008761"
    ]
},
  "bbox": [],
  "geometry": {"coordinates":[-91.8167,35.7167],"type":"Point"}
}