{
  "id": 7183844,
  "type": "Feature",
  "properties": {
    "tgn:hierarchy":[
        "tgn:7183844",
        "tgn:1000003",
        "tgn:7003677",
        "tgn:7000084",
        "tgn:7029392"
    ],
    "tgn:id":7183844,
    "tgn:name":"Gohfeld",
    "tgn:placetype":[
        "aat:300008347"
    ]
},
  "bbox": [],
  "geometry": {"coordinates":[7.933333,52.266667],"type":"Point"}
}