{
  "id": 2744336,
  "type": "Feature",
  "properties": {
    "tgn:hierarchy":[
        "tgn:2744336",
        "tgn:1000001",
        "tgn:7012149",
        "tgn:2001504",
        "tgn:7007709",
        "tgn:7029392"
    ],
    "tgn:id":2744336,
    "tgn:name":"Vernon Creek",
    "tgn:placetype":[
        "aat:300008706"
    ]
},
  "bbox": [],
  "geometry": {"coordinates":[-82.45,35.2333],"type":"Point"}
}