{
  "id": 7372905,
  "type": "Feature",
  "properties": {
    "tgn:hierarchy":[
        "tgn:7372905",
        "tgn:1000001",
        "tgn:7005596",
        "tgn:7005560",
        "tgn:7029392"
    ],
    "tgn:id":7372905,
    "tgn:name":"La Palma",
    "tgn:placetype":[
        "aat:300008347"
    ]
},
  "bbox": [],
  "geometry": {"coordinates":[-92.116667,18.216667],"type":"Point"}
}