{
  "id": 2723615,
  "type": "Feature",
  "properties": {
    "tgn:hierarchy":[
        "tgn:2723615",
        "tgn:1000001",
        "tgn:7012149",
        "tgn:2001912",
        "tgn:7007825",
        "tgn:7029392"
    ],
    "tgn:id":2723615,
    "tgn:name":"Todd Mine",
    "tgn:placetype":[
        "aat:300000390"
    ]
},
  "bbox": [],
  "geometry": {"coordinates":[-84.4667,36.2833],"type":"Point"}
}