{
  "id": 7557599,
  "type": "Feature",
  "properties": {
    "tgn:hierarchy":[
        "tgn:7557599",
        "tgn:1000004",
        "tgn:7000198",
        "tgn:7016788",
        "tgn:7029392"
    ],
    "tgn:id":7557599,
    "tgn:name:en":"Rangmahal",
    "tgn:placetype":[
        "aat:300007783"
    ]
},
  "bbox": [],
  "geometry": {"coordinates":[73.95932,29.389667],"type":"Point"}
}