{
  "id": 7210784,
  "type": "Feature",
  "properties": {
    "tgn:hierarchy":[
        "tgn:7210784",
        "tgn:1000003",
        "tgn:7003687",
        "tgn:7000084",
        "tgn:7029392"
    ],
    "tgn:id":7210784,
    "tgn:name":"Balsam-Graben",
    "tgn:placetype":[
        "aat:300008699"
    ]
},
  "bbox": [],
  "geometry": {"coordinates":[11.883333,52.766667],"type":"Point"}
}