{
  "id": 7458461,
  "type": "Feature",
  "properties": {
    "tgn:hierarchy":[
        "tgn:7458461",
        "tgn:7002444",
        "tgn:7019099",
        "tgn:1000003",
        "tgn:7008591",
        "tgn:7029392"
    ],
    "tgn:id":7458461,
    "tgn:name:en":"Luggie Water",
    "tgn:placetype":[
        "aat:300008699"
    ]
},
  "bbox": [],
  "geometry": {"coordinates":[-4.15,55.933333],"type":"Point"}
}