{
  "id": 2209302,
  "type": "Feature",
  "properties": {
    "tgn:hierarchy":[
        "tgn:2209302",
        "tgn:1000001",
        "tgn:7012149",
        "tgn:1002897",
        "tgn:7007920",
        "tgn:7029392"
    ],
    "tgn:id":2209302,
    "tgn:name":"Burnt Peak",
    "tgn:placetype":[
        "aat:300008798"
    ]
},
  "bbox": [],
  "geometry": {"coordinates":[-121.8667,46.0667],"type":"Point"}
}