{
  "id": 2313122,
  "type": "Feature",
  "properties": {
    "tgn:hierarchy":[
        "tgn:2313122",
        "tgn:1000001",
        "tgn:1002243",
        "tgn:7012149",
        "tgn:7007520",
        "tgn:7029392"
    ],
    "tgn:id":2313122,
    "tgn:name":"Elbow Lake",
    "tgn:placetype":[
        "aat:300008680"
    ]
},
  "bbox": [],
  "geometry": {"coordinates":[-85.8333,41.8667],"type":"Point"}
}