{
  "id": 2779371,
  "type": "Feature",
  "properties": {
    "tgn:hierarchy":[
        "tgn:2779371",
        "tgn:1000001",
        "tgn:7012149",
        "tgn:2001667",
        "tgn:7007707",
        "tgn:7029392"
    ],
    "tgn:id":2779371,
    "tgn:name":"Wolf Hollow",
    "tgn:placetype":[
        "aat:300008761"
    ]
},
  "bbox": [],
  "geometry": {"coordinates":[-94.9667,34.1667],"type":"Point"}
}