<<<<<<< HEAD
{
  "id": 7352109,
  "type": "Feature",
  "properties": {
    "tgn:hierarchy":[
        "tgn:7352109",
        "tgn:7005586",
        "tgn:1000001",
        "tgn:7005560",
        "tgn:7029392"
    ],
    "tgn:id":7352109,
    "tgn:name":"Barranca de los Otates",
    "tgn:placetype":[
        "aat:300008347"
    ]
},
  "bbox": [],
  "geometry": {"coordinates":[-103.666667,20.266667],"type":"Point"}
}
=======
{"geometry":{"type":"Point","coordinates":[-103.666667,20.266667]},"type":"Feature","properties":{"hierarchy":["tgn:7352109","tgn:7005586","tgn:1000001","tgn:7005560","tgn:7029392"],"placetype":["aat:300008347"],"id":7352109,"name:xx":"Barranca de los Otates"}}
>>>>>>> 03f74aca74312dbeaf24d7e61306dd6a786dc3d0
