{
  "id": 7477854,
  "type": "Feature",
  "properties": {
    "tgn:hierarchy":[
        "tgn:7477854",
        "tgn:1000004",
        "tgn:1000454",
        "tgn:1000141",
        "tgn:7029392"
    ],
    "tgn:id":7477854,
    "tgn:name":"Fanzi'ao Shan",
    "tgn:placetype":[
        "aat:300008777"
    ]
},
  "bbox": [],
  "geometry": {"coordinates":[121.822955,25.135378],"type":"Point"}
}