{
  "id": 2238208,
  "type": "Feature",
  "properties": {
    "tgn:hierarchy":[
        "tgn:2238208",
        "tgn:1000001",
        "tgn:1002260",
        "tgn:7012149",
        "tgn:7007920",
        "tgn:7029392"
    ],
    "tgn:id":2238208,
    "tgn:name":"Chiwawa Ridge",
    "tgn:placetype":[
        "aat:300266640"
    ]
},
  "bbox": [],
  "geometry": {"coordinates":[-120.8667,47.9833],"type":"Point"}
}