<<<<<<< HEAD
{
  "id": 7116687,
  "type": "Feature",
  "properties": {
    "tgn:hierarchy":[
        "tgn:7116687",
        "tgn:1000003",
        "tgn:7003682",
        "tgn:7000084",
        "tgn:7029392"
    ],
    "tgn:id":7116687,
    "tgn:name":"Offenbach",
    "tgn:placetype":[
        "aat:300000745"
    ]
},
  "bbox": [],
  "geometry": {"coordinates":[7.55,49.616667],"type":"Point"}
}
=======
{"geometry":{"type":"Point","coordinates":[7.550000,49.616667]},"type":"Feature","properties":{"hierarchy":["tgn:7116687","tgn:1000003","tgn:7003682","tgn:7000084","tgn:7029392"],"placetype":["aat:300000745"],"id":7116687,"name:xx":"Offenbach"}}
>>>>>>> 03f74aca74312dbeaf24d7e61306dd6a786dc3d0
