{
  "id": 2754507,
  "type": "Feature",
  "properties": {
    "tgn:hierarchy":[
        "tgn:2754507",
        "tgn:1000001",
        "tgn:7012149",
        "tgn:2001904",
        "tgn:7007825",
        "tgn:7029392"
    ],
    "tgn:id":2754507,
    "tgn:name":"Waxtree Hollow",
    "tgn:placetype":[
        "aat:300008761"
    ]
},
  "bbox": [],
  "geometry": {"coordinates":[-87.7333,35.5333],"type":"Point"}
}