{
  "id": 7056693,
  "type": "Feature",
  "properties": {
    "tgn:hierarchy":[
        "tgn:7056693",
        "tgn:7005765",
        "tgn:1000003",
        "tgn:7003237",
        "tgn:1000080",
        "tgn:7029392"
    ],
    "tgn:id":7056693,
    "tgn:name":"Acqualunga",
    "tgn:placetype":[
        "aat:300008347"
    ]
},
  "bbox": [],
  "geometry": {"coordinates":[9.95,45.316667],"type":"Point"}
}