{
  "id": 2502907,
  "type": "Feature",
  "properties": {
    "tgn:hierarchy":[
        "tgn:2502907",
        "tgn:1000001",
        "tgn:7012149",
        "tgn:2000965",
        "tgn:7007520",
        "tgn:7029392"
    ],
    "tgn:id":2502907,
    "tgn:name":"McMullen Drain",
    "tgn:placetype":[
        "aat:300008699"
    ]
},
  "bbox": [],
  "geometry": {"coordinates":[-83.65,44.2167],"type":"Point"}
}