{
  "id": 2757038,
  "type": "Feature",
  "properties": {
    "tgn:hierarchy":[
        "tgn:2757038",
        "tgn:1000001",
        "tgn:7012149",
        "tgn:2000812",
        "tgn:7007255",
        "tgn:7029392"
    ],
    "tgn:id":2757038,
    "tgn:name":"Wentz",
    "tgn:placetype":[
        "aat:300008347"
    ]
},
  "bbox": [],
  "geometry": {"coordinates":[-83.05,37.0667],"type":"Point"}
}