{
  "id": 2127596,
  "type": "Feature",
  "properties": {
    "tgn:hierarchy":[
        "tgn:2127596",
        "tgn:1000001",
        "tgn:7012149",
        "tgn:2001289",
        "tgn:7007524",
        "tgn:7029392"
    ],
    "tgn:id":2127596,
    "tgn:name":"Alabaugh Creek",
    "tgn:placetype":[
        "aat:300008706"
    ]
},
  "bbox": [],
  "geometry": {"coordinates":[-110.7333,46.4333],"type":"Point"}
}