{
  "id": 2642567,
  "type": "Feature",
  "properties": {
    "tgn:hierarchy":[
        "tgn:2642567",
        "tgn:1000001",
        "tgn:2000263",
        "tgn:7012149",
        "tgn:7007240",
        "tgn:7029392"
    ],
    "tgn:id":2642567,
    "tgn:name":"Sanders Creek",
    "tgn:placetype":[
        "aat:300008706"
    ]
},
  "bbox": [],
  "geometry": {"coordinates":[-83.1333,29.45],"type":"Point"}
}