{
  "id": 7279583,
  "type": "Feature",
  "properties": {
    "tgn:hierarchy":[
        "tgn:7279583",
        "tgn:1001708",
        "tgn:1000049",
        "tgn:1000002",
        "tgn:7029392"
    ],
    "tgn:id":7279583,
    "tgn:name":"Rinc\u00f3n del Peralillo",
    "tgn:placetype":[
        "aat:300387200"
    ]
},
  "bbox": [],
  "geometry": {"coordinates":[-71.033333,-34.05],"type":"Point"}
}