{
  "id": 2344004,
  "type": "Feature",
  "properties": {
    "tgn:hierarchy":[
        "tgn:2344004",
        "tgn:1000001",
        "tgn:2001025",
        "tgn:7012149",
        "tgn:7007521",
        "tgn:7029392"
    ],
    "tgn:id":2344004,
    "tgn:name":"Galpin Lake",
    "tgn:placetype":[
        "aat:300008680"
    ]
},
  "bbox": [],
  "geometry": {"coordinates":[-93.55,44.8833],"type":"Point"}
}