{
  "id": 2766498,
  "type": "Feature",
  "properties": {
    "tgn:hierarchy":[
        "tgn:2766498",
        "tgn:1000001",
        "tgn:7012149",
        "tgn:2002294",
        "tgn:7013961",
        "tgn:7029392"
    ],
    "tgn:id":2766498,
    "tgn:name":"White Oak Branch",
    "tgn:placetype":[
        "aat:300008699"
    ]
},
  "bbox": [],
  "geometry": {"coordinates":[-81.0167,37.65],"type":"Point"}
}