{
  "id": 2206098,
  "type": "Feature",
  "properties": {
    "tgn:hierarchy":[
        "tgn:2206098",
        "tgn:1000001",
        "tgn:2001416",
        "tgn:7012149",
        "tgn:7007526",
        "tgn:7029392"
    ],
    "tgn:id":2206098,
    "tgn:name":"Bull Spring",
    "tgn:placetype":[
        "aat:300008697"
    ]
},
  "bbox": [],
  "geometry": {"coordinates":[-114.6667,37.4667],"type":"Point"}
}