{
  "id": 2077955,
  "type": "Feature",
  "properties": {
    "tgn:hierarchy":[
        "tgn:2077955",
        "tgn:1000001",
        "tgn:2001584",
        "tgn:7012149",
        "tgn:7007705",
        "tgn:7029392"
    ],
    "tgn:id":2077955,
    "tgn:name":"Raub",
    "tgn:placetype":[
        "aat:300008347"
    ]
},
  "bbox": [],
  "geometry": {"coordinates":[-102.0333,47.7333],"type":"Point"}
}