{
  "id": 7030502,
  "type": "Feature",
  "properties": {
    "tgn:hierarchy":[
        "tgn:7030502",
        "tgn:7002445",
        "tgn:1000003",
        "tgn:7008166",
        "tgn:7008591",
        "tgn:7029392"
    ],
    "tgn:id":7030502,
    "tgn:name":"Ryther",
    "tgn:placetype":[
        "aat:300008347"
    ]
},
  "bbox": [],
  "geometry": {"coordinates":[-1.152,53.835],"type":"Point"}
}