{
  "id": 2482169,
  "type": "Feature",
  "properties": {
    "tgn:hierarchy":[
        "tgn:2482169",
        "tgn:1000001",
        "tgn:7012149",
        "tgn:1002564",
        "tgn:7007710",
        "tgn:7029392"
    ],
    "tgn:id":2482169,
    "tgn:name":"Langan Swamp",
    "tgn:placetype":[
        "aat:300008905"
    ]
},
  "bbox": [],
  "geometry": {"coordinates":[-75.5167,41.3167],"type":"Point"}
}