{
  "id": 7442789,
  "type": "Feature",
  "properties": {
    "tgn:hierarchy":[
        "tgn:7442789",
        "tgn:7002445",
        "tgn:1000003",
        "tgn:7012032",
        "tgn:7008591",
        "tgn:7029392"
    ],
    "tgn:id":7442789,
    "tgn:name:en":"Timberscombe",
    "tgn:placetype":[
        "aat:300008347"
    ]
},
  "bbox": [],
  "geometry": {"coordinates":[-3.496389,51.167778],"type":"Point"}
}