{
  "id": 2229553,
  "type": "Feature",
  "properties": {
    "tgn:hierarchy":[
        "tgn:2229553",
        "tgn:1000001",
        "tgn:7014423",
        "tgn:7012149",
        "tgn:7007517",
        "tgn:7029392"
    ],
    "tgn:id":2229553,
    "tgn:name":"Cedar Ponds",
    "tgn:placetype":[
        "aat:300008680"
    ]
},
  "bbox": [],
  "geometry": {"coordinates":[-70.65,41.75],"type":"Point"}
}