{
  "id": 2176503,
  "type": "Feature",
  "properties": {
    "tgn:hierarchy":[
        "tgn:2176503",
        "tgn:1000001",
        "tgn:7012149",
        "tgn:2000479",
        "tgn:7007250",
        "tgn:7029392"
    ],
    "tgn:id":2176503,
    "tgn:name":"Black Lake",
    "tgn:placetype":[
        "aat:300006191"
    ]
},
  "bbox": [],
  "geometry": {"coordinates":[-116.65,47.45],"type":"Point"}
}