{
  "id": 2280987,
  "type": "Feature",
  "properties": {
    "tgn:hierarchy":[
        "tgn:2280987",
        "tgn:1000001",
        "tgn:7012149",
        "tgn:2002053",
        "tgn:7007826",
        "tgn:7029392"
    ],
    "tgn:id":2280987,
    "tgn:name":"Deep Elm Creek",
    "tgn:placetype":[
        "aat:300008706"
    ]
},
  "bbox": [],
  "geometry": {"coordinates":[-98.3667,32.95],"type":"Point"}
}