{
  "id": 7021649,
  "type": "Feature",
  "properties": {
    "tgn:hierarchy":[
        "tgn:7021649",
        "tgn:2001730",
        "tgn:1000001",
        "tgn:7012149",
        "tgn:7007712",
        "tgn:7029392"
    ],
    "tgn:id":7021649,
    "tgn:name":"Nicks Lake",
    "tgn:placetype":[
        "aat:300008680",
        "aat:300387018"
    ]
},
  "bbox": [],
  "geometry": {"coordinates":[-81.2333,33.4333],"type":"Point"}
}