{
  "id": 7473641,
  "type": "Feature",
  "properties": {
    "tgn:hierarchy":[
        "tgn:7473641",
        "tgn:1000004",
        "tgn:7492971",
        "tgn:1000141",
        "tgn:7029392"
    ],
    "tgn:id":7473641,
    "tgn:name":"Dingliuzilin",
    "tgn:placetype":[
        "aat:300008347"
    ]
},
  "bbox": [],
  "geometry": {"coordinates":[120.498555,22.644918],"type":"Point"}
}