{
  "id": 7314398,
  "type": "Feature",
  "properties": {
    "tgn:hierarchy":[
        "tgn:7314398",
        "tgn:1001692",
        "tgn:1000049",
        "tgn:1000002",
        "tgn:7029392"
    ],
    "tgn:id":7314398,
    "tgn:name":"Los Lleuques, Estero",
    "tgn:placetype":[
        "aat:300008699"
    ]
},
  "bbox": [],
  "geometry": {"coordinates":[-71.883333,-38.75],"type":"Point"}
}