{
  "id": 7574813,
  "type": "Feature",
  "properties": {
    "tgn:hierarchy":[
        "tgn:7574813",
        "tgn:1000004",
        "tgn:7000198",
        "tgn:1001895",
        "tgn:7029392"
    ],
    "tgn:id":7574813,
    "tgn:name:en":"Kavlapur",
    "tgn:placetype":[
        "aat:300008347"
    ]
},
  "bbox": [],
  "geometry": {"coordinates":[74.633333,16.933333],"type":"Point"}
}