{
  "id": 2746265,
  "type": "Feature",
  "properties": {
    "tgn:hierarchy":[
        "tgn:2746265",
        "tgn:1000001",
        "tgn:7012149",
        "tgn:7007158",
        "tgn:2000246",
        "tgn:7029392"
    ],
    "tgn:id":2746265,
    "tgn:name":"Vulcan Creek",
    "tgn:placetype":[
        "aat:300008706"
    ]
},
  "bbox": [],
  "geometry": {"coordinates":[-106.3833,38.25],"type":"Point"}
}