{
  "id": 6000442,
  "type": "Feature",
  "properties": {
    "tgn:hierarchy":[
        "tgn:6000442",
        "tgn:1000004",
        "tgn:1000118",
        "tgn:1001441",
        "tgn:7029392"
    ],
    "tgn:id":6000442,
    "tgn:name":"Ashur",
    "tgn:placetype":[
        "aat:300008347",
        "aat:300000810",
        "aat:300167671",
        "aat:300387218",
        "aat:300387286",
        "aat:300379515"
    ]
},
  "bbox": [],
  "geometry": {"coordinates":[43.2333,35.4833],"type":"Point"}
}