<<<<<<< HEAD
{
  "id": 2765471,
  "type": "Feature",
  "properties": {
    "tgn:hierarchy":[
        "tgn:2765471",
        "tgn:1000001",
        "tgn:7012149",
        "tgn:2001916",
        "tgn:7007825",
        "tgn:7029392"
    ],
    "tgn:id":2765471,
    "tgn:name":"White Branch",
    "tgn:placetype":[
        "aat:300008699"
    ]
},
  "bbox": [],
  "geometry": {"coordinates":[-86.1167,36.2667],"type":"Point"}
}
=======
{"geometry":{"type":"Point","coordinates":[-86.116700,36.266700]},"type":"Feature","properties":{"hierarchy":["tgn:2765471","tgn:1000001","tgn:7012149","tgn:2001916","tgn:7007825","tgn:7029392"],"placetype":["aat:300008699"],"id":2765471,"name:xx":"White Branch"}}
>>>>>>> 03f74aca74312dbeaf24d7e61306dd6a786dc3d0
