{
  "id": 2765471,
  "type": "Feature",
  "properties": {
    "tgn:hierarchy":[
        "tgn:2765471",
        "tgn:1000001",
        "tgn:7012149",
        "tgn:2001916",
        "tgn:7007825",
        "tgn:7029392"
    ],
    "tgn:id":2765471,
    "tgn:name":"White Branch",
    "tgn:placetype":[
        "aat:300008699"
    ]
},
  "bbox": [],
  "geometry": {"coordinates":[-86.1167,36.2667],"type":"Point"}
}