{
  "id": 2653957,
  "type": "Feature",
  "properties": {
    "tgn:hierarchy":[
        "tgn:2653957",
        "tgn:1000001",
        "tgn:7012149",
        "tgn:1002746",
        "tgn:7007568",
        "tgn:7029392"
    ],
    "tgn:id":2653957,
    "tgn:name":"Shackelton Point",
    "tgn:placetype":[
        "aat:300008850"
    ]
},
  "bbox": [],
  "geometry": {"coordinates":[-75.9333,43.1667],"type":"Point"}
}