<<<<<<< HEAD
{
  "id": 2331783,
  "type": "Feature",
  "properties": {
    "tgn:hierarchy":[
        "tgn:2331783",
        "tgn:7002659",
        "tgn:1000001",
        "tgn:7012149",
        "tgn:2000062",
        "tgn:7029392"
    ],
    "tgn:id":2331783,
    "tgn:name":"Flemons Shoal",
    "tgn:placetype":[
        "aat:300387099",
        "aat:300132348"
    ]
},
  "bbox": [],
  "geometry": {"coordinates":[-87.4167,33.2667],"type":"Point"}
}
=======
{"geometry":{"type":"Point","coordinates":[-87.416700,33.266700]},"type":"Feature","properties":{"hierarchy":["tgn:2331783","tgn:7002659","tgn:1000001","tgn:7012149","tgn:2000062","tgn:7029392"],"placetype":["aat:300387099","aat:300132348"],"id":2331783,"name:xx":"Flemons Shoal"}}
>>>>>>> 03f74aca74312dbeaf24d7e61306dd6a786dc3d0
