{
  "id": 2022360,
  "type": "Feature",
  "properties": {
    "tgn:hierarchy":[
        "tgn:2022360",
        "tgn:1000001",
        "tgn:7012149",
        "tgn:2000422",
        "tgn:7007248",
        "tgn:7029392"
    ],
    "tgn:id":2022360,
    "tgn:name":"Carters Grove",
    "tgn:placetype":[
        "aat:300008347",
        "aat:300387210"
    ]
},
  "bbox": [],
  "geometry": {"coordinates":[-82.9333,33.6833],"type":"Point"}
}