{
  "id": 7005614,
  "type": "Feature",
  "properties": {
    "tgn:hierarchy":[
        "tgn:7005614",
        "tgn:7005611",
        "tgn:1000003",
        "tgn:7003120",
        "tgn:1000080",
        "tgn:7029392"
    ],
    "tgn:id":7005614,
    "tgn:name":"Nizza Monferrato",
    "tgn:placetype":[
        "aat:300008347"
    ]
},
  "bbox": [],
  "geometry": {"coordinates":[8.35,44.766667],"type":"Point"}
}