{
  "id": 2714038,
  "type": "Feature",
  "properties": {
    "tgn:hierarchy":[
        "tgn:2714038",
        "tgn:1000001",
        "tgn:7012149",
        "tgn:7019676",
        "tgn:7007566",
        "tgn:7029392"
    ],
    "tgn:id":2714038,
    "tgn:name":"Tekapo Reservoir",
    "tgn:placetype":[
        "aat:300006191"
    ]
},
  "bbox": [],
  "geometry": {"coordinates":[-108.9333,35.0167],"type":"Point"}
}