{
  "id": 2583578,
  "type": "Feature",
  "properties": {
    "tgn:hierarchy":[
        "tgn:2583578",
        "tgn:1000001",
        "tgn:7012149",
        "tgn:2000559",
        "tgn:7007252",
        "tgn:7029392"
    ],
    "tgn:id":2583578,
    "tgn:name":"Pine Ridge Mine Pond",
    "tgn:placetype":[
        "aat:300006191"
    ]
},
  "bbox": [],
  "geometry": {"coordinates":[-87.4833,39.5667],"type":"Point"}
}