{
  "id": 7271447,
  "type": "Feature",
  "properties": {
    "tgn:hierarchy":[
        "tgn:7271447",
        "tgn:7003619",
        "tgn:1000003",
        "tgn:7016845",
        "tgn:7029392"
    ],
    "tgn:id":7271447,
    "tgn:name:nl":"Talmahoeve",
    "tgn:placetype":[
        "aat:300000206"
    ]
},
  "bbox": [],
  "geometry": {"coordinates":[5.716667,52.216667],"type":"Point"}
}