{
  "id": 7049739,
  "type": "Feature",
  "properties": {
    "tgn:hierarchy":[
        "tgn:7049739",
        "tgn:7003165",
        "tgn:1000003",
        "tgn:7009760",
        "tgn:1000080",
        "tgn:7029392"
    ],
    "tgn:id":7049739,
    "tgn:name":"Cerageto",
    "tgn:placetype":[
        "aat:300008347"
    ]
},
  "bbox": [],
  "geometry": {"coordinates":[10.416667,44.166667],"type":"Point"}
}