{
  "id": 7307195,
  "type": "Feature",
  "properties": {
    "tgn:hierarchy":[
        "tgn:7307195",
        "tgn:7002805",
        "tgn:7002758",
        "tgn:1000003",
        "tgn:1000095",
        "tgn:7029392"
    ],
    "tgn:id":7307195,
    "tgn:name":"Los Matreros",
    "tgn:placetype":[
        "aat:300008347"
    ]
},
  "bbox": [],
  "geometry": {"coordinates":[-1.983333,37.216667],"type":"Point"}
}