<<<<<<< HEAD
{
  "id": 7027369,
  "type": "Feature",
  "properties": {
    "tgn:hierarchy":[
        "tgn:7027369",
        "tgn:7002445",
        "tgn:7018924",
        "tgn:7011781",
        "tgn:1000003",
        "tgn:7008136",
        "tgn:7008591",
        "tgn:7029392"
    ],
    "tgn:id":7027369,
    "tgn:name":"Lee",
    "tgn:placetype":[
        "aat:300008347",
        "aat:300000745",
        "aat:300000874"
    ]
},
  "bbox": [],
  "geometry": {"coordinates":[0.0,51.45],"type":"Point"}
}
=======
{"geometry":{"type":"Point","coordinates":[0.000000,51.450000]},"type":"Feature","properties":{"hierarchy":["tgn:7027369","tgn:7002445","tgn:7018924","tgn:7011781","tgn:1000003","tgn:7008136","tgn:7008591","tgn:7029392"],"placetype":["aat:300008347","aat:300000745","aat:300000874"],"id":7027369,"name:xx":"Lee"}}
>>>>>>> 03f74aca74312dbeaf24d7e61306dd6a786dc3d0
