{
  "id": 2199312,
  "type": "Feature",
  "properties": {
    "tgn:hierarchy":[
        "tgn:2199312",
        "tgn:1000001",
        "tgn:7012149",
        "tgn:1002794",
        "tgn:7007708",
        "tgn:7029392"
    ],
    "tgn:id":2199312,
    "tgn:name":"Brush College",
    "tgn:placetype":[
        "aat:300008347"
    ]
},
  "bbox": [],
  "geometry": {"coordinates":[-123.0667,44.9667],"type":"Point"}
}