{
  "id": 7496924,
  "type": "Feature",
  "properties": {
    "tgn:hierarchy":[
        "tgn:7496924",
        "tgn:1000004",
        "tgn:1000959",
        "tgn:1000141",
        "tgn:7029392"
    ],
    "tgn:id":7496924,
    "tgn:name":"Jiabo Guoxiao",
    "tgn:placetype":[
        "aat:300006495"
    ]
},
  "bbox": [],
  "geometry": {"coordinates":[121.575825,25.00269],"type":"Point"}
}