{
  "id": 2344404,
  "type": "Feature",
  "properties": {
    "tgn:hierarchy":[
        "tgn:2344404",
        "tgn:1000001",
        "tgn:7012149",
        "tgn:1003026",
        "tgn:7007826",
        "tgn:7029392"
    ],
    "tgn:id":2344404,
    "tgn:name":"Ganzert Lake",
    "tgn:placetype":[
        "aat:300006191"
    ]
},
  "bbox": [],
  "geometry": {"coordinates":[-97.7333,30.4667],"type":"Point"}
}