{
  "id": 2691571,
  "type": "Feature",
  "properties": {
    "tgn:hierarchy":[
        "tgn:2691571",
        "tgn:1000001",
        "tgn:2001006",
        "tgn:7012149",
        "tgn:7007521",
        "tgn:7029392"
    ],
    "tgn:id":2691571,
    "tgn:name":"Stark",
    "tgn:placetype":[
        "aat:300008347"
    ]
},
  "bbox": [],
  "geometry": {"coordinates":[-94.6333,44.2333],"type":"Point"}
}