{
  "id": 7108665,
  "type": "Feature",
  "properties": {
    "tgn:hierarchy":[
        "tgn:7108665",
        "tgn:1000003",
        "tgn:7003688",
        "tgn:7000084",
        "tgn:7029392"
    ],
    "tgn:id":7108665,
    "tgn:name":"Rehberg",
    "tgn:placetype":[
        "aat:300008347"
    ]
},
  "bbox": [],
  "geometry": {"coordinates":[9.616667,54.683333],"type":"Point"}
}