<<<<<<< HEAD
{
  "id": 2152793,
  "type": "Feature",
  "properties": {
    "tgn:hierarchy":[
        "tgn:2152793",
        "tgn:7002659",
        "tgn:1000001",
        "tgn:7012149",
        "tgn:2000044",
        "tgn:7029392"
    ],
    "tgn:id":2152793,
    "tgn:name":"Bayou, The",
    "tgn:placetype":[
        "aat:300008699"
    ]
},
  "bbox": [],
  "geometry": {"coordinates":[-86.4167,34.5167],"type":"Point"}
}
=======
{"geometry":{"type":"Point","coordinates":[-86.416700,34.516700]},"type":"Feature","properties":{"hierarchy":["tgn:2152793","tgn:7002659","tgn:1000001","tgn:7012149","tgn:2000044","tgn:7029392"],"placetype":["aat:300008699"],"id":2152793,"name:xx":"Bayou, The"}}
>>>>>>> 03f74aca74312dbeaf24d7e61306dd6a786dc3d0
