{
  "id": 2611258,
  "type": "Feature",
  "properties": {
    "tgn:hierarchy":[
        "tgn:2611258",
        "tgn:1000001",
        "tgn:7012149",
        "tgn:1002423",
        "tgn:7007568",
        "tgn:7029392"
    ],
    "tgn:id":2611258,
    "tgn:name":"Red Kill",
    "tgn:placetype":[
        "aat:300008699"
    ]
},
  "bbox": [],
  "geometry": {"coordinates":[-74.1833,42.2167],"type":"Point"}
}