{
  "id": 7507244,
  "type": "Feature",
  "properties": {
    "tgn:hierarchy":[
        "tgn:7507244",
        "tgn:1008380",
        "tgn:1000226",
        "tgn:7018426",
        "tgn:1000006",
        "tgn:7029392"
    ],
    "tgn:id":7507244,
    "tgn:name:en":"Puketutu",
    "tgn:placetype":[
        "aat:300008795"
    ]
},
  "bbox": [],
  "geometry": {"coordinates":[175.783333,-38.283333],"type":"Point"}
}