<<<<<<< HEAD
{
  "id": 2254408,
  "type": "Feature",
  "properties": {
    "tgn:hierarchy":[
        "tgn:2254408",
        "tgn:1000001",
        "tgn:2001324",
        "tgn:7012149",
        "tgn:7007525",
        "tgn:7029392"
    ],
    "tgn:id":2254408,
    "tgn:name":"Coon Creek",
    "tgn:placetype":[
        "aat:300008706"
    ]
},
  "bbox": [],
  "geometry": {"coordinates":[-100.0167,42.5667],"type":"Point"}
}
=======
{"geometry":{"type":"Point","coordinates":[-100.016700,42.566700]},"type":"Feature","properties":{"hierarchy":["tgn:2254408","tgn:1000001","tgn:2001324","tgn:7012149","tgn:7007525","tgn:7029392"],"placetype":["aat:300008706"],"id":2254408,"name:xx":"Coon Creek"}}
>>>>>>> 03f74aca74312dbeaf24d7e61306dd6a786dc3d0
