{
  "id": 2393564,
  "type": "Feature",
  "properties": {
    "tgn:hierarchy":[
        "tgn:2393564",
        "tgn:1000001",
        "tgn:7012149",
        "tgn:2001139",
        "tgn:7007522",
        "tgn:7029392"
    ],
    "tgn:id":2393564,
    "tgn:name":"Hog Creek",
    "tgn:placetype":[
        "aat:300008706"
    ]
},
  "bbox": [],
  "geometry": {"coordinates":[-90.1167,34.4333],"type":"Point"}
}