<<<<<<< HEAD
{
  "id": 2408587,
  "type": "Feature",
  "properties": {
    "tgn:hierarchy":[
        "tgn:2408587",
        "tgn:1000001",
        "tgn:7012149",
        "tgn:2002266",
        "tgn:7013961",
        "tgn:7029392"
    ],
    "tgn:id":2408587,
    "tgn:name":"Hutton Run",
    "tgn:placetype":[
        "aat:300008699"
    ]
},
  "bbox": [],
  "geometry": {"coordinates":[-79.0667,39.0167],"type":"Point"}
}
=======
{"geometry":{"type":"Point","coordinates":[-79.066700,39.016700]},"type":"Feature","properties":{"hierarchy":["tgn:2408587","tgn:1000001","tgn:7012149","tgn:2002266","tgn:7013961","tgn:7029392"],"placetype":["aat:300008699"],"id":2408587,"name:xx":"Hutton Run"}}
>>>>>>> 03f74aca74312dbeaf24d7e61306dd6a786dc3d0
