{
  "id": 2726221,
  "type": "Feature",
  "properties": {
    "tgn:hierarchy":[
        "tgn:2726221",
        "tgn:1000001",
        "tgn:1002724",
        "tgn:7012149",
        "tgn:7007517",
        "tgn:7029392"
    ],
    "tgn:id":2726221,
    "tgn:name":"Tower Hill",
    "tgn:placetype":[
        "aat:300008798"
    ]
},
  "bbox": [],
  "geometry": {"coordinates":[-71.0667,42.1667],"type":"Point"}
}