<<<<<<< HEAD
{
  "id": 7173659,
  "type": "Feature",
  "properties": {
    "tgn:hierarchy":[
        "tgn:7173659",
        "tgn:1000003",
        "tgn:7003676",
        "tgn:7000084",
        "tgn:7029392"
    ],
    "tgn:id":7173659,
    "tgn:name":"Gro\u00dfer Schleifstein-Berg",
    "tgn:placetype":[
        "aat:300008795"
    ]
},
  "bbox": [],
  "geometry": {"coordinates":[10.4,51.866667],"type":"Point"}
}
=======
{"geometry":{"type":"Point","coordinates":[10.400000,51.866667]},"type":"Feature","properties":{"hierarchy":["tgn:7173659","tgn:1000003","tgn:7003676","tgn:7000084","tgn:7029392"],"placetype":["aat:300008795"],"id":7173659,"name:xx":"Gro\u00dfer Schleifstein-Berg"}}
>>>>>>> 03f74aca74312dbeaf24d7e61306dd6a786dc3d0
