{
  "id": 2284390,
  "type": "Feature",
  "properties": {
    "tgn:hierarchy":[
        "tgn:2284390",
        "tgn:7030516",
        "tgn:7006450",
        "tgn:1000001",
        "tgn:7012149",
        "tgn:7029392"
    ],
    "tgn:id":2284390,
    "tgn:name":"Derby Point",
    "tgn:placetype":[
        "aat:300008850"
    ]
},
  "bbox": [],
  "geometry": {"coordinates":[-168.7833,53.15],"type":"Point"}
}