{
  "id": 7443069,
  "type": "Feature",
  "properties": {
    "tgn:hierarchy":[
        "tgn:7443069",
        "tgn:7002445",
        "tgn:7008116",
        "tgn:1000003",
        "tgn:7008591",
        "tgn:7029392"
    ],
    "tgn:id":7443069,
    "tgn:name:en":"Stones, The",
    "tgn:placetype":[
        "aat:300011692"
    ]
},
  "bbox": [],
  "geometry": {"coordinates":[-5.425,50.25],"type":"Point"}
}