{
  "id": 1090868,
  "type": "Feature",
  "properties": {
    "tgn:hierarchy":[
        "tgn:1090868",
        "tgn:7001242",
        "tgn:1001405",
        "tgn:1000173",
        "tgn:7029392"
    ],
    "tgn:id":1090868,
    "tgn:name":"Besalampy",
    "tgn:placetype":[
        "aat:300008347"
    ]
},
  "bbox": [],
  "geometry": {"coordinates":[44.4833,-16.7167],"type":"Point"}
}