{
  "id": 2453146,
  "type": "Feature",
  "properties": {
    "tgn:hierarchy":[
        "tgn:2453146",
        "tgn:1000001",
        "tgn:7012149",
        "tgn:2002360",
        "tgn:7007922",
        "tgn:7029392"
    ],
    "tgn:id":2453146,
    "tgn:name":"Little Casey Lake",
    "tgn:placetype":[
        "aat:300008680"
    ]
},
  "bbox": [],
  "geometry": {"coordinates":[-91.9167,45.9167],"type":"Point"}
}