{
  "id": 7009322,
  "type": "Feature",
  "properties": {
    "tgn:hierarchy":[
        "tgn:7009322",
        "tgn:1000003",
        "tgn:7002877",
        "tgn:1000070",
        "tgn:7029392"
    ],
    "tgn:id":7009322,
    "tgn:name":"Malesherbes",
    "tgn:placetype":[
        "aat:300008347"
    ]
},
  "bbox": [],
  "geometry": {"coordinates":[2.4167,48.2833],"type":"Point"}
}