{
  "id": 2401384,
  "type": "Feature",
  "properties": {
    "tgn:hierarchy":[
        "tgn:2401384",
        "tgn:1000001",
        "tgn:7012149",
        "tgn:7007709",
        "tgn:7029392"
    ],
    "tgn:id":2401384,
    "tgn:name":"Horsepen Swamp",
    "tgn:placetype":[
        "aat:300008699"
    ]
},
  "bbox": [],
  "geometry": {"coordinates":[-77.1167,35.7167],"type":"Point"}
}