<<<<<<< HEAD
{
  "id": 2401384,
  "type": "Feature",
  "properties": {
    "tgn:hierarchy":[
        "tgn:2401384",
        "tgn:1000001",
        "tgn:7012149",
        "tgn:7007709",
        "tgn:7029392"
    ],
    "tgn:id":2401384,
    "tgn:name":"Horsepen Swamp",
    "tgn:placetype":[
        "aat:300008699"
    ]
},
  "bbox": [],
  "geometry": {"coordinates":[-77.1167,35.7167],"type":"Point"}
}
=======
{"geometry":{"type":"Point","coordinates":[-77.116700,35.716700]},"type":"Feature","properties":{"hierarchy":["tgn:2401384","tgn:1000001","tgn:7012149","tgn:7007709","tgn:7029392"],"placetype":["aat:300008699"],"id":2401384,"name:xx":"Horsepen Swamp"}}
>>>>>>> 03f74aca74312dbeaf24d7e61306dd6a786dc3d0
