{
  "id": 7141144,
  "type": "Feature",
  "properties": {
    "tgn:hierarchy":[
        "tgn:7141144",
        "tgn:1000003",
        "tgn:7003688",
        "tgn:7000084",
        "tgn:7029392"
    ],
    "tgn:id":7141144,
    "tgn:name":"L\u00f6ptiner See",
    "tgn:placetype":[
        "aat:300008680"
    ]
},
  "bbox": [],
  "geometry": {"coordinates":[10.216667,54.183333],"type":"Point"}
}