<<<<<<< HEAD
{
  "id": 2254407,
  "type": "Feature",
  "properties": {
    "tgn:hierarchy":[
        "tgn:2254407",
        "tgn:1000001",
        "tgn:2001346",
        "tgn:7012149",
        "tgn:7007525",
        "tgn:7029392"
    ],
    "tgn:id":2254407,
    "tgn:name":"Coon Creek",
    "tgn:placetype":[
        "aat:300008706"
    ]
},
  "bbox": [],
  "geometry": {"coordinates":[-98.9333,40.1333],"type":"Point"}
}
=======
{"geometry":{"type":"Point","coordinates":[-98.933300,40.133300]},"type":"Feature","properties":{"hierarchy":["tgn:2254407","tgn:1000001","tgn:2001346","tgn:7012149","tgn:7007525","tgn:7029392"],"placetype":["aat:300008706"],"id":2254407,"name:xx":"Coon Creek"}}
>>>>>>> 03f74aca74312dbeaf24d7e61306dd6a786dc3d0
