{
  "id": 2211781,
  "type": "Feature",
  "properties": {
    "tgn:hierarchy":[
        "tgn:2211781",
        "tgn:1000001",
        "tgn:7012149",
        "tgn:2002371",
        "tgn:7007923",
        "tgn:7029392"
    ],
    "tgn:id":2211781,
    "tgn:name":"Button Draw",
    "tgn:placetype":[
        "aat:300008761"
    ]
},
  "bbox": [],
  "geometry": {"coordinates":[-109.4667,43.6667],"type":"Point"}
}