{
  "id": 7430693,
  "type": "Feature",
  "properties": {
    "tgn:hierarchy":[
        "tgn:7430693",
        "tgn:1001853",
        "tgn:1000001",
        "tgn:7005560",
        "tgn:7029392"
    ],
    "tgn:id":7430693,
    "tgn:name":"El Porvenir",
    "tgn:placetype":[
        "aat:300008347"
    ]
},
  "bbox": [],
  "geometry": {"coordinates":[-102.233333,27.266667],"type":"Point"}
}