{
  "id": 2266565,
  "type": "Feature",
  "properties": {
    "tgn:hierarchy":[
        "tgn:2266565",
        "tgn:1000001",
        "tgn:2001747",
        "tgn:7012149",
        "tgn:7007712",
        "tgn:7029392"
    ],
    "tgn:id":2266565,
    "tgn:name":"Creekside Villas",
    "tgn:placetype":[
        "aat:300008347"
    ]
},
  "bbox": [],
  "geometry": {"coordinates":[-82.3333,34.9167],"type":"Point"}
}