{
  "id": 7472280,
  "type": "Feature",
  "properties": {
    "tgn:hierarchy":[
        "tgn:7472280",
        "tgn:1000004",
        "tgn:7471332",
        "tgn:1000141",
        "tgn:7029392"
    ],
    "tgn:id":7472280,
    "tgn:name":"Zuoteng Shan",
    "tgn:placetype":[
        "aat:300008798"
    ]
},
  "bbox": [],
  "geometry": {"coordinates":[121.197778,24.537222],"type":"Point"}
}