{
  "id": 2731329,
  "type": "Feature",
  "properties": {
    "tgn:hierarchy":[
        "tgn:2731329",
        "tgn:1000001",
        "tgn:7006451",
        "tgn:7012149",
        "tgn:2000098",
        "tgn:7029392"
    ],
    "tgn:id":2731329,
    "tgn:name":"Tuckup Canyon",
    "tgn:placetype":[
        "aat:300008761"
    ]
},
  "bbox": [],
  "geometry": {"coordinates":[-112.9167,36.3833],"type":"Point"}
}