{
  "id": 2780573,
  "type": "Feature",
  "properties": {
    "tgn:hierarchy":[
        "tgn:2780573",
        "tgn:7013349",
        "tgn:1000001",
        "tgn:7012149",
        "tgn:7007708",
        "tgn:7029392"
    ],
    "tgn:id":2780573,
    "tgn:name":"Wood Gulch",
    "tgn:placetype":[
        "aat:300008761"
    ]
},
  "bbox": [],
  "geometry": {"coordinates":[-118.05,44.5333],"type":"Point"}
}