{
  "id": 2525738,
  "type": "Feature",
  "properties": {
    "tgn:hierarchy":[
        "tgn:2525738",
        "tgn:1000001",
        "tgn:2000315",
        "tgn:7012149",
        "tgn:7007248",
        "tgn:7029392"
    ],
    "tgn:id":2525738,
    "tgn:name":"Mose Lake",
    "tgn:placetype":[
        "aat:300008680"
    ]
},
  "bbox": [],
  "geometry": {"coordinates":[-82.15,30.9333],"type":"Point"}
}