{
  "id": 7441926,
  "type": "Feature",
  "properties": {
    "tgn:hierarchy":[
        "tgn:7441926",
        "tgn:7002444",
        "tgn:1000003",
        "tgn:7008082",
        "tgn:7008591",
        "tgn:7029392"
    ],
    "tgn:id":7441926,
    "tgn:name:en":"Torrish Burn",
    "tgn:placetype":[
        "aat:300008699"
    ]
},
  "bbox": [],
  "geometry": {"coordinates":[-3.75,58.133333],"type":"Point"}
}