{
  "id": 7381945,
  "type": "Feature",
  "properties": {
    "tgn:hierarchy":[
        "tgn:7381945",
        "tgn:1001835",
        "tgn:1000001",
        "tgn:7005560",
        "tgn:7029392"
    ],
    "tgn:id":7381945,
    "tgn:name":"Manch\u00f3n Blanco",
    "tgn:placetype":[
        "aat:300008347"
    ]
},
  "bbox": [],
  "geometry": {"coordinates":[-116.133333,32.483333],"type":"Point"}
}