{
  "id": 2599961,
  "type": "Feature",
  "properties": {
    "tgn:hierarchy":[
        "tgn:2599961",
        "tgn:1000001",
        "tgn:7012149",
        "tgn:2002165",
        "tgn:7007919",
        "tgn:7029392"
    ],
    "tgn:id":2599961,
    "tgn:name":"Pruess Farm Pond",
    "tgn:placetype":[
        "aat:300006191"
    ]
},
  "bbox": [],
  "geometry": {"coordinates":[-78.4333,38.3333],"type":"Point"}
}