{
  "id": 2582079,
  "type": "Feature",
  "properties": {
    "tgn:hierarchy":[
        "tgn:2582079",
        "tgn:7002659",
        "tgn:1000001",
        "tgn:7012149",
        "tgn:7029392"
    ],
    "tgn:id":2582079,
    "tgn:name":"Pine Creek",
    "tgn:placetype":[
        "aat:300008706"
    ]
},
  "bbox": [],
  "geometry": {"coordinates":[-86.45,32.5167],"type":"Point"}
}