{
  "id": 2732790,
  "type": "Feature",
  "properties": {
    "tgn:hierarchy":[
        "tgn:2732790",
        "tgn:1002148",
        "tgn:1000001",
        "tgn:7012149",
        "tgn:7007826",
        "tgn:7029392"
    ],
    "tgn:id":2732790,
    "tgn:name":"Turkey Creek",
    "tgn:placetype":[
        "aat:300008706"
    ]
},
  "bbox": [],
  "geometry": {"coordinates":[-95.4333,31.7167],"type":"Point"}
}