{
  "id": 1095904,
  "type": "Feature",
  "properties": {
    "tgn:hierarchy":[
        "tgn:1095904",
        "tgn:7001242",
        "tgn:1001461",
        "tgn:1000209",
        "tgn:7029392"
    ],
    "tgn:id":1095904,
    "tgn:name":"Chilubula Mission",
    "tgn:placetype":[
        "aat:300008347"
    ]
},
  "bbox": [],
  "geometry": {"coordinates":[30.95,-10.15],"type":"Point"}
}