{
  "id": 1049301,
  "type": "Feature",
  "properties": {
    "tgn:hierarchy":[
        "tgn:1049301",
        "tgn:1000003",
        "tgn:7024115",
        "tgn:7006366",
        "tgn:7029392"
    ],
    "tgn:id":1049301,
    "tgn:name":"Nowy Staw",
    "tgn:placetype":[
        "aat:300008347"
    ]
},
  "bbox": [],
  "geometry": {"coordinates":[19.0167,54.1333],"type":"Point"}
}