{
  "id": 2755714,
  "type": "Feature",
  "properties": {
    "tgn:hierarchy":[
        "tgn:2755714",
        "tgn:1000001",
        "tgn:7012149",
        "tgn:2000358",
        "tgn:7007248",
        "tgn:7029392"
    ],
    "tgn:id":2755714,
    "tgn:name":"Weed Branch",
    "tgn:placetype":[
        "aat:300008699"
    ]
},
  "bbox": [],
  "geometry": {"coordinates":[-84.05,33.85],"type":"Point"}
}