{
  "id": 7371324,
  "type": "Feature",
  "properties": {
    "tgn:hierarchy":[
        "tgn:7371324",
        "tgn:7005583",
        "tgn:1000001",
        "tgn:7005560",
        "tgn:7029392"
    ],
    "tgn:id":7371324,
    "tgn:name":"Isabel Robles",
    "tgn:placetype":[
        "aat:300008347"
    ]
},
  "bbox": [],
  "geometry": {"coordinates":[-103.293056,24.6425],"type":"Point"}
}