{
  "id": 2523836,
  "type": "Feature",
  "properties": {
    "tgn:hierarchy":[
        "tgn:2523836",
        "tgn:1000001",
        "tgn:7006451",
        "tgn:2000094",
        "tgn:7012149",
        "tgn:7029392"
    ],
    "tgn:id":2523836,
    "tgn:name":"Morano Spring",
    "tgn:placetype":[
        "aat:300008697"
    ]
},
  "bbox": [],
  "geometry": {"coordinates":[-110.2333,32.8167],"type":"Point"}
}