{
  "id": 7083048,
  "type": "Feature",
  "properties": {
    "tgn:hierarchy":[
        "tgn:7083048",
        "tgn:7003692",
        "tgn:1000003",
        "tgn:7000084",
        "tgn:7029392"
    ],
    "tgn:id":7083048,
    "tgn:name":"Wendelbach",
    "tgn:placetype":[
        "aat:300000206"
    ]
},
  "bbox": [],
  "geometry": {"coordinates":[8.116667,48.65],"type":"Point"}
}