{
  "id": 7026407,
  "type": "Feature",
  "properties": {
    "tgn:hierarchy":[
        "tgn:7026407",
        "tgn:7002445",
        "tgn:1000003",
        "tgn:7008168",
        "tgn:7008591",
        "tgn:7029392"
    ],
    "tgn:id":7026407,
    "tgn:name:en":"Childrey",
    "tgn:placetype":[
        "aat:300008347",
        "aat:300008372"
    ]
},
  "bbox": [],
  "geometry": {"coordinates":[-1.483333,51.583333],"type":"Point"}
}