{
  "id": 2034570,
  "type": "Feature",
  "properties": {
    "tgn:hierarchy":[
        "tgn:2034570",
        "tgn:1000001",
        "tgn:7012149",
        "tgn:2000612",
        "tgn:7007253",
        "tgn:7029392"
    ],
    "tgn:id":2034570,
    "tgn:name":"Cosgrove",
    "tgn:placetype":[
        "aat:300008347"
    ]
},
  "bbox": [],
  "geometry": {"coordinates":[-91.7333,41.6333],"type":"Point"}
}