{
  "id": 7431748,
  "type": "Feature",
  "properties": {
    "tgn:hierarchy":[
        "tgn:7431748",
        "tgn:1000001",
        "tgn:7005595",
        "tgn:7005560",
        "tgn:7029392"
    ],
    "tgn:id":7431748,
    "tgn:name":"Ponce",
    "tgn:placetype":[
        "aat:300008347"
    ]
},
  "bbox": [],
  "geometry": {"coordinates":[-105.833333,22.933333],"type":"Point"}
}