{
  "id": 2009943,
  "type": "Feature",
  "properties": {
    "tgn:hierarchy":[
        "tgn:2009943",
        "tgn:1000001",
        "tgn:7012149",
        "tgn:7007157",
        "tgn:1002858",
        "tgn:7029392"
    ],
    "tgn:id":2009943,
    "tgn:name":"Alpine",
    "tgn:placetype":[
        "aat:300008347"
    ]
},
  "bbox": [],
  "geometry": {"coordinates":[-116.75,32.8333],"type":"Point"}
}