{
  "id": 2352313,
  "type": "Feature",
  "properties": {
    "tgn:hierarchy":[
        "tgn:2352313",
        "tgn:1000001",
        "tgn:7012149",
        "tgn:2000225",
        "tgn:7007158",
        "tgn:7029392"
    ],
    "tgn:id":2352313,
    "tgn:name":"Goat Canyon Reservoir",
    "tgn:placetype":[
        "aat:300006191"
    ]
},
  "bbox": [],
  "geometry": {"coordinates":[-107.9167,37.1333],"type":"Point"}
}