{
  "id": 2316256,
  "type": "Feature",
  "properties": {
    "tgn:hierarchy":[
        "tgn:2316256",
        "tgn:1000001",
        "tgn:2001268",
        "tgn:7012149",
        "tgn:7007524",
        "tgn:7029392"
    ],
    "tgn:id":2316256,
    "tgn:name":"Elmhurst Creek",
    "tgn:placetype":[
        "aat:300008706"
    ]
},
  "bbox": [],
  "geometry": {"coordinates":[-105.1833,45.8833],"type":"Point"}
}