{
  "id": 2545316,
  "type": "Feature",
  "properties": {
    "tgn:hierarchy":[
        "tgn:2545316",
        "tgn:1000001",
        "tgn:2000459",
        "tgn:7012149",
        "tgn:7007250",
        "tgn:7029392"
    ],
    "tgn:id":2545316,
    "tgn:name":"North Fork Baron Creek",
    "tgn:placetype":[
        "aat:300008706"
    ]
},
  "bbox": [],
  "geometry": {"coordinates":[-115.0167,44.15],"type":"Point"}
}