{
  "id": 2662672,
  "type": "Feature",
  "properties": {
    "tgn:hierarchy":[
        "tgn:2662672",
        "tgn:1000001",
        "tgn:7016172",
        "tgn:7012149",
        "tgn:2000173",
        "tgn:7029392"
    ],
    "tgn:id":2662672,
    "tgn:name":"Signboard Hollow",
    "tgn:placetype":[
        "aat:300008761"
    ]
},
  "bbox": [],
  "geometry": {"coordinates":[-92.2333,35.85],"type":"Point"}
}