{
  "id": 7279983,
  "type": "Feature",
  "properties": {
    "tgn:hierarchy":[
        "tgn:7279983",
        "tgn:1001702",
        "tgn:1000049",
        "tgn:1000002",
        "tgn:7029392"
    ],
    "tgn:id":7279983,
    "tgn:name":"Rees, Isla",
    "tgn:placetype":[
        "aat:300008791"
    ]
},
  "bbox": [],
  "geometry": {"coordinates":[-70.983333,-54.15],"type":"Point"}
}