{
  "id": 7410283,
  "type": "Feature",
  "properties": {
    "tgn:hierarchy":[
        "tgn:7410283",
        "tgn:1000001",
        "tgn:7005592",
        "tgn:7005560",
        "tgn:7029392"
    ],
    "tgn:id":7410283,
    "tgn:name":"Estaci\u00f3n Acuaco",
    "tgn:placetype":[
        "aat:300007783"
    ]
},
  "bbox": [],
  "geometry": {"coordinates":[-97.590278,19.708333],"type":"Point"}
}