{
  "id": 1136279,
  "type": "Feature",
  "properties": {
    "tgn:hierarchy":[
        "tgn:1136279",
        "tgn:7005586",
        "tgn:1000001",
        "tgn:7005560",
        "tgn:7029392"
    ],
    "tgn:id":1136279,
    "tgn:name":"Cocula",
    "tgn:placetype":[
        "aat:300008347"
    ]
},
  "bbox": [],
  "geometry": {"coordinates":[-103.833333,20.383333],"type":"Point"}
}