{
  "id": 2550915,
  "type": "Feature",
  "properties": {
    "tgn:hierarchy":[
        "tgn:2550915",
        "tgn:1000001",
        "tgn:7012149",
        "tgn:2001249",
        "tgn:7007523",
        "tgn:7029392"
    ],
    "tgn:id":2550915,
    "tgn:name":"Notch",
    "tgn:placetype":[
        "aat:300008347"
    ]
},
  "bbox": [],
  "geometry": {"coordinates":[-93.3333,36.6667],"type":"Point"}
}