{
  "id": 2028245,
  "type": "Feature",
  "properties": {
    "tgn:hierarchy":[
        "tgn:2028245",
        "tgn:1000001",
        "tgn:2000501",
        "tgn:7012149",
        "tgn:7007251",
        "tgn:7029392"
    ],
    "tgn:id":2028245,
    "tgn:name":"Heathsville",
    "tgn:placetype":[
        "aat:300008347",
        "aat:300387210"
    ]
},
  "bbox": [],
  "geometry": {"coordinates":[-87.5667,38.8833],"type":"Point"}
}