{
  "id": 7377829,
  "type": "Feature",
  "properties": {
    "tgn:hierarchy":[
        "tgn:7377829",
        "tgn:1000001",
        "tgn:1001960",
        "tgn:7005560",
        "tgn:7029392"
    ],
    "tgn:id":7377829,
    "tgn:name":"La Placita",
    "tgn:placetype":[
        "aat:300008347"
    ]
},
  "bbox": [],
  "geometry": {"coordinates":[-110.616667,28.75],"type":"Point"}
}