{
  "id": 1084115,
  "type": "Feature",
  "properties": {
    "tgn:hierarchy":[
        "tgn:1084115",
        "tgn:1000004",
        "tgn:1001481",
        "tgn:1000135",
        "tgn:7029392"
    ],
    "tgn:id":1084115,
    "tgn:name":"Canipaan",
    "tgn:placetype":[
        "aat:300008347"
    ]
},
  "bbox": [],
  "geometry": {"coordinates":[117.2667,8.5833],"type":"Point"}
}