{
  "id": 2572640,
  "type": "Feature",
  "properties": {
    "tgn:hierarchy":[
        "tgn:2572640",
        "tgn:1000001",
        "tgn:2000462",
        "tgn:7012149",
        "tgn:7007250",
        "tgn:7029392"
    ],
    "tgn:id":2572640,
    "tgn:name":"Peak Creek",
    "tgn:placetype":[
        "aat:300008706"
    ]
},
  "bbox": [],
  "geometry": {"coordinates":[-116.6333,48.7333],"type":"Point"}
}