<<<<<<< HEAD
{
  "id": 7477636,
  "type": "Feature",
  "properties": {
    "tgn:hierarchy":[
        "tgn:7477636",
        "tgn:7488858",
        "tgn:1000004",
        "tgn:1000141",
        "tgn:7029392"
    ],
    "tgn:id":7477636,
    "tgn:name":"Yongjundong",
    "tgn:placetype":[
        "aat:300008347"
    ]
},
  "bbox": [],
  "geometry": {"coordinates":[120.84967,23.828136],"type":"Point"}
}
=======
{"geometry":{"type":"Point","coordinates":[120.849670,23.828136]},"type":"Feature","properties":{"hierarchy":["tgn:7477636","tgn:7488858","tgn:1000004","tgn:1000141","tgn:7029392"],"placetype":["aat:300008347"],"id":7477636,"name:xx":"Yongjundong"}}
>>>>>>> 03f74aca74312dbeaf24d7e61306dd6a786dc3d0
