{
  "id": 7221133,
  "type": "Feature",
  "properties": {
    "tgn:hierarchy":[
        "tgn:7221133",
        "tgn:7002725",
        "tgn:7002715",
        "tgn:1000003",
        "tgn:1000074",
        "tgn:7029392"
    ],
    "tgn:id":7221133,
    "tgn:name":"Vako\u00fafion",
    "tgn:placetype":[
        "aat:300008347"
    ]
},
  "bbox": [],
  "geometry": {"coordinates":[22.722222,40.888333],"type":"Point"}
}