{
  "id": 2702991,
  "type": "Feature",
  "properties": {
    "tgn:hierarchy":[
        "tgn:2702991",
        "tgn:1000001",
        "tgn:7016172",
        "tgn:2000116",
        "tgn:7012149",
        "tgn:7029392"
    ],
    "tgn:id":2702991,
    "tgn:name":"Sulphur Springs Hollow",
    "tgn:placetype":[
        "aat:300008761"
    ]
},
  "bbox": [],
  "geometry": {"coordinates":[-92.1667,35.4667],"type":"Point"}
}