{
  "id": 2570697,
  "type": "Feature",
  "properties": {
    "tgn:hierarchy":[
        "tgn:2570697",
        "tgn:1000001",
        "tgn:7012149",
        "tgn:2001298",
        "tgn:7007524",
        "tgn:7029392"
    ],
    "tgn:id":2570697,
    "tgn:name":"Pats Gulch",
    "tgn:placetype":[
        "aat:300008761"
    ]
},
  "bbox": [],
  "geometry": {"coordinates":[-112.4667,46.6667],"type":"Point"}
}