{
  "id": 1030970,
  "type": "Feature",
  "properties": {
    "tgn:hierarchy":[
        "tgn:1030970",
        "tgn:1003573",
        "tgn:7002445",
        "tgn:1000003",
        "tgn:7029507",
        "tgn:7008591",
        "tgn:7029392"
    ],
    "tgn:id":1030970,
    "tgn:name":"Wainstalls",
    "tgn:placetype":[
        "aat:300008347"
    ]
},
  "bbox": [],
  "geometry": {"coordinates":[-1.9333,53.75],"type":"Point"}
}