{
  "id": 7021643,
  "type": "Feature",
  "properties": {
    "tgn:hierarchy":[
        "tgn:7021643",
        "tgn:2001726",
        "tgn:1000001",
        "tgn:7012149",
        "tgn:7007712",
        "tgn:7029392"
    ],
    "tgn:id":7021643,
    "tgn:name":"Tarrants Millpond",
    "tgn:placetype":[
        "aat:300006191"
    ]
},
  "bbox": [],
  "geometry": {"coordinates":[-81.5667,33.4833],"type":"Point"}
}