<<<<<<< HEAD
{
  "id": 7021643,
  "type": "Feature",
  "properties": {
    "tgn:hierarchy":[
        "tgn:7021643",
        "tgn:2001726",
        "tgn:1000001",
        "tgn:7012149",
        "tgn:7007712",
        "tgn:7029392"
    ],
    "tgn:id":7021643,
    "tgn:name":"Tarrants Millpond",
    "tgn:placetype":[
        "aat:300006191"
    ]
},
  "bbox": [],
  "geometry": {"coordinates":[-81.5667,33.4833],"type":"Point"}
}
=======
{"geometry":{"type":"Point","coordinates":[-81.566700,33.483300]},"type":"Feature","properties":{"hierarchy":["tgn:7021643","tgn:2001726","tgn:1000001","tgn:7012149","tgn:7007712","tgn:7029392"],"placetype":["aat:300006191"],"id":7021643,"name:xx":"Tarrants Millpond"}}
>>>>>>> 03f74aca74312dbeaf24d7e61306dd6a786dc3d0
