{
  "id": 7496927,
  "type": "Feature",
  "properties": {
    "tgn:hierarchy":[
        "tgn:7496927",
        "tgn:1000004",
        "tgn:1000959",
        "tgn:1000141",
        "tgn:7029392"
    ],
    "tgn:id":7496927,
    "tgn:name":"Taibei Suidao Yi",
    "tgn:placetype":[
        "aat:300007899"
    ]
},
  "bbox": [],
  "geometry": {"coordinates":[121.571787,25.007269],"type":"Point"}
}