{
  "id": 7278115,
  "type": "Feature",
  "properties": {
    "tgn:hierarchy":[
        "tgn:7278115",
        "tgn:1001702",
        "tgn:1000049",
        "tgn:1000002",
        "tgn:7029392"
    ],
    "tgn:id":7278115,
    "tgn:name":"V\u00e1squez, Isla",
    "tgn:placetype":[
        "aat:300008791"
    ]
},
  "bbox": [],
  "geometry": {"coordinates":[-68.233333,-54.916667],"type":"Point"}
}