{
  "id": 7390991,
  "type": "Feature",
  "properties": {
    "tgn:hierarchy":[
        "tgn:7390991",
        "tgn:7005581",
        "tgn:1000001",
        "tgn:7005560",
        "tgn:7029392"
    ],
    "tgn:id":7390991,
    "tgn:name":"R\u00edo Verde",
    "tgn:placetype":[
        "aat:300008347"
    ]
},
  "bbox": [],
  "geometry": {"coordinates":[-106.45,26.266667],"type":"Point"}
}