{
  "id": 2561117,
  "type": "Feature",
  "properties": {
    "tgn:hierarchy":[
        "tgn:2561117",
        "tgn:1000001",
        "tgn:7012149",
        "tgn:1003047",
        "tgn:7007710",
        "tgn:7029392"
    ],
    "tgn:id":2561117,
    "tgn:name":"Orson Run",
    "tgn:placetype":[
        "aat:300008699"
    ]
},
  "bbox": [],
  "geometry": {"coordinates":[-76.4167,39.8333],"type":"Point"}
}