{
  "id": 7281982,
  "type": "Feature",
  "properties": {
    "tgn:hierarchy":[
        "tgn:7281982",
        "tgn:1001699",
        "tgn:1000049",
        "tgn:1000002",
        "tgn:7029392"
    ],
    "tgn:id":7281982,
    "tgn:name":"San Pedro, R\u00edo",
    "tgn:placetype":[
        "aat:300008699"
    ]
},
  "bbox": [],
  "geometry": {"coordinates":[-72.766667,-39.833333],"type":"Point"}
}