{
  "id": 7241971,
  "type": "Feature",
  "properties": {
    "tgn:hierarchy":[
        "tgn:7241971",
        "tgn:7003456",
        "tgn:1000003",
        "tgn:1000063",
        "tgn:7018236",
        "tgn:7029392"
    ],
    "tgn:id":7241971,
    "tgn:name":"Leibeek",
    "tgn:placetype":[
        "aat:300008699"
    ]
},
  "bbox": [],
  "geometry": {"coordinates":[4.734618,51.116168],"type":"Point"}
}