<<<<<<< HEAD
{
  "id": 2406705,
  "type": "Feature",
  "properties": {
    "tgn:hierarchy":[
        "tgn:2406705",
        "tgn:1000001",
        "tgn:7016172",
        "tgn:7012149",
        "tgn:2000136",
        "tgn:7029392"
    ],
    "tgn:id":2406705,
    "tgn:name":"Hunt Hollow Mine",
    "tgn:placetype":[
        "aat:300000390"
    ]
},
  "bbox": [],
  "geometry": {"coordinates":[-91.6167,35.8667],"type":"Point"}
}
=======
{"geometry":{"type":"Point","coordinates":[-91.616700,35.866700]},"type":"Feature","properties":{"hierarchy":["tgn:2406705","tgn:1000001","tgn:7016172","tgn:7012149","tgn:2000136","tgn:7029392"],"placetype":["aat:300000390"],"id":2406705,"name:xx":"Hunt Hollow Mine"}}
>>>>>>> 03f74aca74312dbeaf24d7e61306dd6a786dc3d0
