{
  "id": 2719796,
  "type": "Feature",
  "properties": {
    "tgn:hierarchy":[
        "tgn:2719796",
        "tgn:1000001",
        "tgn:1002840",
        "tgn:7012149",
        "tgn:7007828",
        "tgn:7029392"
    ],
    "tgn:id":2719796,
    "tgn:name":"Three Shanties Brook",
    "tgn:placetype":[
        "aat:300008699"
    ]
},
  "bbox": [],
  "geometry": {"coordinates":[-72.9167,43.3167],"type":"Point"}
}