{
  "id": 2582431,
  "type": "Feature",
  "properties": {
    "tgn:hierarchy":[
        "tgn:2582431",
        "tgn:7002659",
        "tgn:1000001",
        "tgn:7012149",
        "tgn:2000053",
        "tgn:7029392"
    ],
    "tgn:id":2582431,
    "tgn:name":"Pine Grove",
    "tgn:placetype":[
        "aat:300008347"
    ]
},
  "bbox": [],
  "geometry": {"coordinates":[-88.2167,33.3333],"type":"Point"}
}