<<<<<<< HEAD
{
  "id": 7487242,
  "type": "Feature",
  "properties": {
    "tgn:hierarchy":[
        "tgn:7487242",
        "tgn:7488858",
        "tgn:1000004",
        "tgn:1000141",
        "tgn:7029392"
    ],
    "tgn:id":7487242,
    "tgn:name":"Lincuo Li",
    "tgn:placetype":[
        "aat:300387173"
    ]
},
  "bbox": [],
  "geometry": {"coordinates":[120.621313,23.935698],"type":"Point"}
}
=======
{"geometry":{"type":"Point","coordinates":[120.621313,23.935698]},"type":"Feature","properties":{"hierarchy":["tgn:7487242","tgn:7488858","tgn:1000004","tgn:1000141","tgn:7029392"],"placetype":["aat:300387173"],"id":7487242,"name:xx":"Lincuo Li"}}
>>>>>>> 03f74aca74312dbeaf24d7e61306dd6a786dc3d0
