{
  "id": 2447161,
  "type": "Feature",
  "properties": {
    "tgn:hierarchy":[
        "tgn:2447161",
        "tgn:1000001",
        "tgn:7012149",
        "tgn:2000818",
        "tgn:7007255",
        "tgn:7029392"
    ],
    "tgn:id":2447161,
    "tgn:name":"Lick Branch",
    "tgn:placetype":[
        "aat:300008699"
    ]
},
  "bbox": [],
  "geometry": {"coordinates":[-84.5333,36.8333],"type":"Point"}
}