{
  "id": 1006010,
  "type": "Feature",
  "properties": {
    "tgn:hierarchy":[
        "tgn:1006010",
        "tgn:7002036",
        "tgn:1000217",
        "tgn:1000006",
        "tgn:7029392"
    ],
    "tgn:id":1006010,
    "tgn:name":"Abemama",
    "tgn:placetype":[
        "aat:300008793"
    ]
},
  "bbox": [],
  "geometry": {"coordinates":[173.8333,0.3333],"type":"Point"}
}