{
  "id": 2391548,
  "type": "Feature",
  "properties": {
    "tgn:hierarchy":[
        "tgn:2391548",
        "tgn:1002136",
        "tgn:1000001",
        "tgn:7012149",
        "tgn:7007706",
        "tgn:7029392"
    ],
    "tgn:id":2391548,
    "tgn:name":"Hills Fork",
    "tgn:placetype":[
        "aat:300008699"
    ]
},
  "bbox": [],
  "geometry": {"coordinates":[-83.6167,38.85],"type":"Point"}
}