<<<<<<< HEAD
{
  "id": 7362826,
  "type": "Feature",
  "properties": {
    "tgn:hierarchy":[
        "tgn:7362826",
        "tgn:1001835",
        "tgn:1000001",
        "tgn:7005560",
        "tgn:7029392"
    ],
    "tgn:id":7362826,
    "tgn:name":"Rancho El Encinal",
    "tgn:placetype":[
        "aat:300000241"
    ]
},
  "bbox": [],
  "geometry": {"coordinates":[-116.633333,32.316667],"type":"Point"}
}
=======
{"geometry":{"type":"Point","coordinates":[-116.633333,32.316667]},"type":"Feature","properties":{"hierarchy":["tgn:7362826","tgn:1001835","tgn:1000001","tgn:7005560","tgn:7029392"],"placetype":["aat:300000241"],"id":7362826,"name:xx":"Rancho El Encinal"}}
>>>>>>> 03f74aca74312dbeaf24d7e61306dd6a786dc3d0
