{
  "id": 7568418,
  "type": "Feature",
  "properties": {
    "tgn:hierarchy":[
        "tgn:7568418",
        "tgn:1000004",
        "tgn:7000198",
        "tgn:7016788",
        "tgn:7029392"
    ],
    "tgn:id":7568418,
    "tgn:name:en":"Mang\u0101sar",
    "tgn:placetype":[
        "aat:300008347"
    ]
},
  "bbox": [],
  "geometry": {"coordinates":[74.518406,28.279562],"type":"Point"}
}