{
  "id": 2120616,
  "type": "Feature",
  "properties": {
    "tgn:hierarchy":[
        "tgn:2120616",
        "tgn:1000001",
        "tgn:7012149",
        "tgn:2002333",
        "tgn:7007922",
        "tgn:7029392"
    ],
    "tgn:id":2120616,
    "tgn:name":"Antigo",
    "tgn:placetype":[
        "aat:300008347"
    ]
},
  "bbox": [],
  "geometry": {"coordinates":[-89.15,45.1333],"type":"Point"}
}