{
  "id": 7571792,
  "type": "Feature",
  "properties": {
    "tgn:hierarchy":[
        "tgn:7571792",
        "tgn:1000004",
        "tgn:7000198",
        "tgn:7000799",
        "tgn:7029392"
    ],
    "tgn:id":7571792,
    "tgn:name:en":"Jaura",
    "tgn:placetype":[
        "aat:300008347"
    ]
},
  "bbox": [],
  "geometry": {"coordinates":[75.797642,33.087622],"type":"Point"}
}