{
  "id": 2628814,
  "type": "Feature",
  "properties": {
    "tgn:hierarchy":[
        "tgn:2628814",
        "tgn:1000001",
        "tgn:7012149",
        "tgn:1002881",
        "tgn:7007240",
        "tgn:7029392"
    ],
    "tgn:id":2628814,
    "tgn:name":"Rosalind Heights",
    "tgn:placetype":[
        "aat:300008347"
    ]
},
  "bbox": [],
  "geometry": {"coordinates":[-81.25,28.7667],"type":"Point"}
}