{
  "id": 2542031,
  "type": "Feature",
  "properties": {
    "tgn:hierarchy":[
        "tgn:2542031",
        "tgn:7030515",
        "tgn:7006450",
        "tgn:1000001",
        "tgn:7012149",
        "tgn:7029392"
    ],
    "tgn:id":2542031,
    "tgn:name":"Nipper Creek",
    "tgn:placetype":[
        "aat:300008706"
    ]
},
  "bbox": [],
  "geometry": {"coordinates":[-164.4667,54.85],"type":"Point"}
}