{
  "id": 7483143,
  "type": "Feature",
  "properties": {
    "tgn:hierarchy":[
        "tgn:7483143",
        "tgn:7487020",
        "tgn:1000004",
        "tgn:1000141",
        "tgn:7029392"
    ],
    "tgn:id":7483143,
    "tgn:name":"Tai'an Guoxiao",
    "tgn:placetype":[
        "aat:300006495"
    ]
},
  "bbox": [],
  "geometry": {"coordinates":[120.750278,24.325],"type":"Point"}
}