<<<<<<< HEAD
{
  "id": 7483143,
  "type": "Feature",
  "properties": {
    "tgn:hierarchy":[
        "tgn:7483143",
        "tgn:7487020",
        "tgn:1000004",
        "tgn:1000141",
        "tgn:7029392"
    ],
    "tgn:id":7483143,
    "tgn:name":"Tai'an Guoxiao",
    "tgn:placetype":[
        "aat:300006495"
    ]
},
  "bbox": [],
  "geometry": {"coordinates":[120.750278,24.325],"type":"Point"}
}
=======
{"geometry":{"type":"Point","coordinates":[120.750278,24.325000]},"type":"Feature","properties":{"hierarchy":["tgn:7483143","tgn:7487020","tgn:1000004","tgn:1000141","tgn:7029392"],"placetype":["aat:300006495"],"id":7483143,"name:xx":"Tai'an Guoxiao"}}
>>>>>>> 03f74aca74312dbeaf24d7e61306dd6a786dc3d0
