<<<<<<< HEAD
{
  "id": 7484273,
  "type": "Feature",
  "properties": {
    "tgn:hierarchy":[
        "tgn:7484273",
        "tgn:1000004",
        "tgn:7492971",
        "tgn:1000141",
        "tgn:7029392"
    ],
    "tgn:id":7484273,
    "tgn:name":"Qiedongjiao",
    "tgn:placetype":[
        "aat:300387033"
    ]
},
  "bbox": [],
  "geometry": {"coordinates":[120.551944,22.425556],"type":"Point"}
}
=======
{"geometry":{"type":"Point","coordinates":[120.551944,22.425556]},"type":"Feature","properties":{"hierarchy":["tgn:7484273","tgn:1000004","tgn:7492971","tgn:1000141","tgn:7029392"],"placetype":["aat:300387033"],"id":7484273,"name:xx":"Qiedongjiao"}}
>>>>>>> 03f74aca74312dbeaf24d7e61306dd6a786dc3d0
