{
  "id": 7319069,
  "type": "Feature",
  "properties": {
    "tgn:hierarchy":[
        "tgn:7319069",
        "tgn:1001692",
        "tgn:1000049",
        "tgn:1000002",
        "tgn:7029392"
    ],
    "tgn:id":7319069,
    "tgn:name":"Api\u00f1ilco",
    "tgn:placetype":[
        "aat:300008699"
    ]
},
  "bbox": [],
  "geometry": {"coordinates":[-72.716667,-38.033333],"type":"Point"}
}