<<<<<<< HEAD
{
  "id": 7055415,
  "type": "Feature",
  "properties": {
    "tgn:hierarchy":[
        "tgn:7055415",
        "tgn:7003162",
        "tgn:1000003",
        "tgn:7009760",
        "tgn:1000080",
        "tgn:7029392"
    ],
    "tgn:id":7055415,
    "tgn:name":"Poggioni",
    "tgn:placetype":[
        "aat:300008347"
    ]
},
  "bbox": [],
  "geometry": {"coordinates":[12.083333,43.35],"type":"Point"}
}
=======
{"geometry":{"type":"Point","coordinates":[12.083333,43.350000]},"type":"Feature","properties":{"hierarchy":["tgn:7055415","tgn:7003162","tgn:1000003","tgn:7009760","tgn:1000080","tgn:7029392"],"placetype":["aat:300008347"],"id":7055415,"name:xx":"Poggioni"}}
>>>>>>> 03f74aca74312dbeaf24d7e61306dd6a786dc3d0
