{
  "id": 2751207,
  "type": "Feature",
  "properties": {
    "tgn:hierarchy":[
        "tgn:2751207",
        "tgn:1002238",
        "tgn:1000001",
        "tgn:7012149",
        "tgn:7007516",
        "tgn:7029392"
    ],
    "tgn:id":2751207,
    "tgn:name":"Warfieldsburg",
    "tgn:placetype":[
        "aat:300008347"
    ]
},
  "bbox": [],
  "geometry": {"coordinates":[-77.0167,39.5167],"type":"Point"}
}