<<<<<<< HEAD
{
  "id": 2764288,
  "type": "Feature",
  "properties": {
    "tgn:hierarchy":[
        "tgn:2764288",
        "tgn:1000001",
        "tgn:2001426",
        "tgn:7012149",
        "tgn:7007564",
        "tgn:7029392"
    ],
    "tgn:id":2764288,
    "tgn:name":"Wheelwright Pond",
    "tgn:placetype":[
        "aat:300008680"
    ]
},
  "bbox": [],
  "geometry": {"coordinates":[-71.0,43.1333],"type":"Point"}
}
=======
{"geometry":{"type":"Point","coordinates":[-71.000000,43.133300]},"type":"Feature","properties":{"hierarchy":["tgn:2764288","tgn:1000001","tgn:2001426","tgn:7012149","tgn:7007564","tgn:7029392"],"placetype":["aat:300008680"],"id":2764288,"name:xx":"Wheelwright Pond"}}
>>>>>>> 03f74aca74312dbeaf24d7e61306dd6a786dc3d0
