{
  "id": 2695206,
  "type": "Feature",
  "properties": {
    "tgn:hierarchy":[
        "tgn:2695206",
        "tgn:1000001",
        "tgn:1002249",
        "tgn:7012149",
        "tgn:7007710",
        "tgn:7029392"
    ],
    "tgn:id":2695206,
    "tgn:name":"Stillhouse Hollow",
    "tgn:placetype":[
        "aat:300008761"
    ]
},
  "bbox": [],
  "geometry": {"coordinates":[-77.4833,40.8333],"type":"Point"}
}