{
  "id": 2454738,
  "type": "Feature",
  "properties": {
    "tgn:hierarchy":[
        "tgn:2454738",
        "tgn:1000001",
        "tgn:7006451",
        "tgn:2000091",
        "tgn:7012149",
        "tgn:7029392"
    ],
    "tgn:id":2454738,
    "tgn:name":"Little Dragon Mountains",
    "tgn:placetype":[
        "aat:300008798"
    ]
},
  "bbox": [],
  "geometry": {"coordinates":[-110.1167,32.0833],"type":"Point"}
}