<<<<<<< HEAD
{
  "id": 2704592,
  "type": "Feature",
  "properties": {
    "tgn:hierarchy":[
        "tgn:2704592",
        "tgn:7006450",
        "tgn:1000001",
        "tgn:7012149",
        "tgn:2000088",
        "tgn:7029392"
    ],
    "tgn:id":2704592,
    "tgn:name":"Sunrise Peak",
    "tgn:placetype":[
        "aat:300008798"
    ]
},
  "bbox": [],
  "geometry": {"coordinates":[-132.4667,56.4],"type":"Point"}
}
=======
{"geometry":{"type":"Point","coordinates":[-132.466700,56.400000]},"type":"Feature","properties":{"hierarchy":["tgn:2704592","tgn:7006450","tgn:1000001","tgn:7012149","tgn:2000088","tgn:7029392"],"placetype":["aat:300008798"],"id":2704592,"name:xx":"Sunrise Peak"}}
>>>>>>> 03f74aca74312dbeaf24d7e61306dd6a786dc3d0
