{
  "id": 2754972,
  "type": "Feature",
  "properties": {
    "tgn:hierarchy":[
        "tgn:2754972",
        "tgn:1000001",
        "tgn:7012149",
        "tgn:7007157",
        "tgn:1002858",
        "tgn:7029392"
    ],
    "tgn:id":2754972,
    "tgn:name":"Weaver Mountain",
    "tgn:placetype":[
        "aat:300008798"
    ]
},
  "bbox": [],
  "geometry": {"coordinates":[-117.0667,33.2833],"type":"Point"}
}