{
  "id": 7276231,
  "type": "Feature",
  "properties": {
    "tgn:hierarchy":[
        "tgn:7276231",
        "tgn:7002464",
        "tgn:1000049",
        "tgn:1000002",
        "tgn:7029392"
    ],
    "tgn:id":7276231,
    "tgn:name":"Tillujaya",
    "tgn:placetype":[
        "aat:300008347"
    ]
},
  "bbox": [],
  "geometry": {"coordinates":[-68.55,-19.616667],"type":"Point"}
}