{
  "id": 7022483,
  "type": "Feature",
  "properties": {
    "tgn:hierarchy":[
        "tgn:7022483",
        "tgn:1000001",
        "tgn:7012149",
        "tgn:7007158",
        "tgn:7029392"
    ],
    "tgn:id":7022483,
    "tgn:name":"Carbonate Hill",
    "tgn:placetype":[
        "aat:300008798"
    ]
},
  "bbox": [],
  "geometry": {"coordinates":[-106.2667,39.2333],"type":"Point"}
}