<<<<<<< HEAD
{
  "id": 7022483,
  "type": "Feature",
  "properties": {
    "tgn:hierarchy":[
        "tgn:7022483",
        "tgn:1000001",
        "tgn:7012149",
        "tgn:7007158",
        "tgn:7029392"
    ],
    "tgn:id":7022483,
    "tgn:name":"Carbonate Hill",
    "tgn:placetype":[
        "aat:300008798"
    ]
},
  "bbox": [],
  "geometry": {"coordinates":[-106.2667,39.2333],"type":"Point"}
}
=======
{"geometry":{"type":"Point","coordinates":[-106.266700,39.233300]},"type":"Feature","properties":{"hierarchy":["tgn:7022483","tgn:1000001","tgn:7012149","tgn:7007158","tgn:7029392"],"placetype":["aat:300008798"],"id":7022483,"name:xx":"Carbonate Hill"}}
>>>>>>> 03f74aca74312dbeaf24d7e61306dd6a786dc3d0
