{
  "id": 7405377,
  "type": "Feature",
  "properties": {
    "tgn:hierarchy":[
        "tgn:7405377",
        "tgn:1000001",
        "tgn:7005592",
        "tgn:7005560",
        "tgn:7029392"
    ],
    "tgn:id":7405377,
    "tgn:name":"Mezquital",
    "tgn:placetype":[
        "aat:300008347"
    ]
},
  "bbox": [],
  "geometry": {"coordinates":[-97.866667,18.083333],"type":"Point"}
}