<<<<<<< HEAD
{
  "id": 2251823,
  "type": "Feature",
  "properties": {
    "tgn:hierarchy":[
        "tgn:2251823",
        "tgn:1000001",
        "tgn:1002840",
        "tgn:7012149",
        "tgn:7007828",
        "tgn:7029392"
    ],
    "tgn:id":2251823,
    "tgn:name":"Comtois Hill",
    "tgn:placetype":[
        "aat:300008798"
    ]
},
  "bbox": [],
  "geometry": {"coordinates":[-72.8333,43.5],"type":"Point"}
}
=======
{"geometry":{"type":"Point","coordinates":[-72.833300,43.500000]},"type":"Feature","properties":{"hierarchy":["tgn:2251823","tgn:1000001","tgn:1002840","tgn:7012149","tgn:7007828","tgn:7029392"],"placetype":["aat:300008798"],"id":2251823,"name:xx":"Comtois Hill"}}
>>>>>>> 03f74aca74312dbeaf24d7e61306dd6a786dc3d0
