{
  "id": 7063459,
  "type": "Feature",
  "properties": {
    "tgn:hierarchy":[
        "tgn:7063459",
        "tgn:1000003",
        "tgn:7000094",
        "tgn:7000084",
        "tgn:7029392"
    ],
    "tgn:id":7063459,
    "tgn:name":"Alt Zarrendorf",
    "tgn:placetype":[
        "aat:300008347"
    ]
},
  "bbox": [],
  "geometry": {"coordinates":[13.066667,54.233333],"type":"Point"}
}