{
  "id": 7437850,
  "type": "Feature",
  "properties": {
    "tgn:hierarchy":[
        "tgn:7437850",
        "tgn:1000001",
        "tgn:7005596",
        "tgn:7005560",
        "tgn:7029392"
    ],
    "tgn:id":7437850,
    "tgn:name":"Seco, R\u00edo",
    "tgn:placetype":[
        "aat:300008699"
    ]
},
  "bbox": [],
  "geometry": {"coordinates":[-93.133333,18.433333],"type":"Point"}
}