{
  "id": 7520881,
  "type": "Feature",
  "properties": {
    "tgn:hierarchy":[
        "tgn:7520881",
        "tgn:7001242",
        "tgn:7016833",
        "tgn:1001087",
        "tgn:7029392"
    ],
    "tgn:id":7520881,
    "tgn:name":"Al Kut\u0101m\u012byah",
    "tgn:placetype":[
        "aat:300008347"
    ]
},
  "bbox": [],
  "geometry": {"coordinates":[31.051894,30.364701],"type":"Point"}
}