{
  "id": 1092548,
  "type": "Feature",
  "properties": {
    "tgn:hierarchy":[
        "tgn:1092548",
        "tgn:7001242",
        "tgn:1001757",
        "tgn:1000189",
        "tgn:7029392"
    ],
    "tgn:id":1092548,
    "tgn:name":"Thi\u00e8s",
    "tgn:placetype":[
        "aat:300008347",
        "aat:300387220",
        "aat:300008375",
        "aat:300387270"
    ]
},
  "bbox": [],
  "geometry": {"coordinates":[-16.8667,14.8167],"type":"Point"}
}