{
  "id": 2140944,
  "type": "Feature",
  "properties": {
    "tgn:hierarchy":[
        "tgn:2140944",
        "tgn:2001422",
        "tgn:1000001",
        "tgn:7012149",
        "tgn:7007564",
        "tgn:7029392"
    ],
    "tgn:id":2140944,
    "tgn:name":"Avery Hill",
    "tgn:placetype":[
        "aat:300008798"
    ]
},
  "bbox": [],
  "geometry": {"coordinates":[-71.2833,43.4667],"type":"Point"}
}