{
  "id": 1099407,
  "type": "Feature",
  "properties": {
    "tgn:hierarchy":[
        "tgn:1099407",
        "tgn:1009462",
        "tgn:7000552",
        "tgn:1000006",
        "tgn:7029392"
    ],
    "tgn:id":1099407,
    "tgn:name":"Tinian",
    "tgn:placetype":[
        "aat:300008347"
    ]
},
  "bbox": [],
  "geometry": {"coordinates":[145.6333,-14.9667],"type":"Point"}
}