{
  "id": 7565492,
  "type": "Feature",
  "properties": {
    "tgn:hierarchy":[
        "tgn:7565492",
        "tgn:1000004",
        "tgn:7000198",
        "tgn:7016722",
        "tgn:7029392"
    ],
    "tgn:id":7565492,
    "tgn:name:en":"Barsesi",
    "tgn:placetype":[
        "aat:300008347"
    ]
},
  "bbox": [],
  "geometry": {"coordinates":[79.295559,26.007952],"type":"Point"}
}