{
  "id": 2508799,
  "type": "Feature",
  "properties": {
    "tgn:hierarchy":[
        "tgn:2508799",
        "tgn:1000001",
        "tgn:7012149",
        "tgn:1002457",
        "tgn:7007252",
        "tgn:7029392"
    ],
    "tgn:id":2508799,
    "tgn:name":"Middle Fork Buck Creek",
    "tgn:placetype":[
        "aat:300008706"
    ]
},
  "bbox": [],
  "geometry": {"coordinates":[-85.9167,38.1667],"type":"Point"}
}