{
  "id": 2395377,
  "type": "Feature",
  "properties": {
    "tgn:hierarchy":[
        "tgn:2395377",
        "tgn:1000001",
        "tgn:2001436",
        "tgn:7012149",
        "tgn:7007566",
        "tgn:7029392"
    ],
    "tgn:id":2395377,
    "tgn:name":"Hollan Tank",
    "tgn:placetype":[
        "aat:300006191"
    ]
},
  "bbox": [],
  "geometry": {"coordinates":[-104.8333,32.0333],"type":"Point"}
}