<<<<<<< HEAD
{
  "id": 2253173,
  "type": "Feature",
  "properties": {
    "tgn:hierarchy":[
        "tgn:2253173",
        "tgn:1000001",
        "tgn:7012149",
        "tgn:7007158",
        "tgn:7029392"
    ],
    "tgn:id":2253173,
    "tgn:name":"Continental Divide",
    "tgn:placetype":[
        "aat:300266640"
    ]
},
  "bbox": [],
  "geometry": {"coordinates":[-106.5833,39.0],"type":"Point"}
}
=======
{"geometry":{"type":"Point","coordinates":[-106.583300,39.000000]},"type":"Feature","properties":{"hierarchy":["tgn:2253173","tgn:1000001","tgn:7012149","tgn:7007158","tgn:7029392"],"placetype":["aat:300266640"],"id":2253173,"name:xx":"Continental Divide"}}
>>>>>>> 03f74aca74312dbeaf24d7e61306dd6a786dc3d0
