{
  "id": 7513951,
  "type": "Feature",
  "properties": {
    "tgn:hierarchy":[
        "tgn:7513951",
        "tgn:1009227",
        "tgn:1000226",
        "tgn:7016822",
        "tgn:1000006",
        "tgn:7029392"
    ],
    "tgn:id":7513951,
    "tgn:name:en":"Fancy Group",
    "tgn:placetype":[
        "aat:300008791"
    ]
},
  "bbox": [],
  "geometry": {"coordinates":[168.266667,-46.866667],"type":"Point"}
}