{
  "id": 7218380,
  "type": "Feature",
  "properties": {
    "tgn:hierarchy":[
        "tgn:7218380",
        "tgn:7002735",
        "tgn:7017076",
        "tgn:1000003",
        "tgn:1000074",
        "tgn:7029392"
    ],
    "tgn:id":7218380,
    "tgn:name":"Xeri\u00e1s R\u00e9ma",
    "tgn:placetype":[
        "aat:300008699"
    ]
},
  "bbox": [],
  "geometry": {"coordinates":[22.616667,36.85],"type":"Point"}
}