{
  "id": 2358496,
  "type": "Feature",
  "properties": {
    "tgn:hierarchy":[
        "tgn:2358496",
        "tgn:1000001",
        "tgn:2001476",
        "tgn:7012149",
        "tgn:7007709",
        "tgn:7029392"
    ],
    "tgn:id":2358496,
    "tgn:name":"Grand View Park",
    "tgn:placetype":[
        "aat:300008347"
    ]
},
  "bbox": [],
  "geometry": {"coordinates":[-81.5667,35.8833],"type":"Point"}
}