{
  "id": 2307583,
  "type": "Feature",
  "properties": {
    "tgn:hierarchy":[
        "tgn:2307583",
        "tgn:7006450",
        "tgn:1000001",
        "tgn:7012149",
        "tgn:2000087",
        "tgn:7029392"
    ],
    "tgn:id":2307583,
    "tgn:name":"East Fork Spruce Creek",
    "tgn:placetype":[
        "aat:300008706"
    ]
},
  "bbox": [],
  "geometry": {"coordinates":[-161.8667,61.8167],"type":"Point"}
}