{
  "id": 2633980,
  "type": "Feature",
  "properties": {
    "tgn:hierarchy":[
        "tgn:2633980",
        "tgn:1000001",
        "tgn:7012149",
        "tgn:2001881",
        "tgn:7007825",
        "tgn:7029392"
    ],
    "tgn:id":2633980,
    "tgn:name":"Rushy Springs",
    "tgn:placetype":[
        "aat:300008347"
    ]
},
  "bbox": [],
  "geometry": {"coordinates":[-83.35,36.1167],"type":"Point"}
}