{
  "id": 7590425,
  "type": "Feature",
  "properties": {
    "tgn:hierarchy":[
        "tgn:7590425",
        "tgn:1000004",
        "tgn:7000198",
        "tgn:7000799",
        "tgn:7029392"
    ],
    "tgn:id":7590425,
    "tgn:name:en":"Gagar Forest",
    "tgn:placetype":[
        "aat:300008863"
    ]
},
  "bbox": [],
  "geometry": {"coordinates":[74.305556,33.772222],"type":"Point"}
}