{
  "id": 2282116,
  "type": "Feature",
  "properties": {
    "tgn:hierarchy":[
        "tgn:2282116",
        "tgn:1000001",
        "tgn:1002195",
        "tgn:7012149",
        "tgn:7007520",
        "tgn:7029392"
    ],
    "tgn:id":2282116,
    "tgn:name":"Deer Lake",
    "tgn:placetype":[
        "aat:300008680"
    ]
},
  "bbox": [],
  "geometry": {"coordinates":[-84.5333,41.8667],"type":"Point"}
}