{
  "id": 7230390,
  "type": "Feature",
  "properties": {
    "tgn:hierarchy":[
        "tgn:7230390",
        "tgn:7011270",
        "tgn:7002674",
        "tgn:1000003",
        "tgn:1000074",
        "tgn:7029392"
    ],
    "tgn:id":7230390,
    "tgn:name":"Kt\u00e9nia, Vr\u00e1khoi",
    "tgn:placetype":[
        "aat:300011692"
    ]
},
  "bbox": [],
  "geometry": {"coordinates":[24.566667,36.633333],"type":"Point"}
}