{
  "id": 7330227,
  "type": "Feature",
  "properties": {
    "tgn:hierarchy":[
        "tgn:7330227",
        "tgn:1001439",
        "tgn:1000003",
        "tgn:7002797",
        "tgn:1000095",
        "tgn:7029392"
    ],
    "tgn:id":7330227,
    "tgn:name":"Hormigas, Islas",
    "tgn:placetype":[
        "aat:300008791"
    ]
},
  "bbox": [],
  "geometry": {"coordinates":[-0.65,37.666667],"type":"Point"}
}