<<<<<<< HEAD
{
  "id": 7478987,
  "type": "Feature",
  "properties": {
    "tgn:hierarchy":[
        "tgn:7478987",
        "tgn:1000004",
        "tgn:7001009",
        "tgn:1000141",
        "tgn:7029392"
    ],
    "tgn:id":7478987,
    "tgn:name":"Wuling Youke Zhongxin",
    "tgn:placetype":[
        "aat:300004792"
    ]
},
  "bbox": [],
  "geometry": {"coordinates":[121.310556,24.354444],"type":"Point"}
}
=======
{"geometry":{"type":"Point","coordinates":[121.310556,24.354444]},"type":"Feature","properties":{"hierarchy":["tgn:7478987","tgn:1000004","tgn:7001009","tgn:1000141","tgn:7029392"],"placetype":["aat:300004792"],"id":7478987,"name:xx":"Wuling Youke Zhongxin"}}
>>>>>>> 03f74aca74312dbeaf24d7e61306dd6a786dc3d0
