{
  "id": 7478987,
  "type": "Feature",
  "properties": {
    "tgn:hierarchy":[
        "tgn:7478987",
        "tgn:1000004",
        "tgn:7001009",
        "tgn:1000141",
        "tgn:7029392"
    ],
    "tgn:id":7478987,
    "tgn:name":"Wuling Youke Zhongxin",
    "tgn:placetype":[
        "aat:300004792"
    ]
},
  "bbox": [],
  "geometry": {"coordinates":[121.310556,24.354444],"type":"Point"}
}