{
  "id": 2698700,
  "type": "Feature",
  "properties": {
    "tgn:hierarchy":[
        "tgn:2698700",
        "tgn:2000919",
        "tgn:1000001",
        "tgn:7012149",
        "tgn:7007515",
        "tgn:7029392"
    ],
    "tgn:id":2698700,
    "tgn:name":"Stratton Island",
    "tgn:placetype":[
        "aat:300008791"
    ]
},
  "bbox": [],
  "geometry": {"coordinates":[-68.15,46.7667],"type":"Point"}
}