{
  "id": 7284220,
  "type": "Feature",
  "properties": {
    "tgn:hierarchy":[
        "tgn:7284220",
        "tgn:1001657",
        "tgn:1000049",
        "tgn:1000002",
        "tgn:7029392"
    ],
    "tgn:id":7284220,
    "tgn:name":"Potrerillos",
    "tgn:placetype":[
        "aat:300000206"
    ]
},
  "bbox": [],
  "geometry": {"coordinates":[-70.916667,-30.716667],"type":"Point"}
}