<<<<<<< HEAD
{
  "id": 2153515,
  "type": "Feature",
  "properties": {
    "tgn:hierarchy":[
        "tgn:2153515",
        "tgn:2000195",
        "tgn:1000001",
        "tgn:7012149",
        "tgn:7007158",
        "tgn:7029392"
    ],
    "tgn:id":2153515,
    "tgn:name":"Bear Basin",
    "tgn:placetype":[
        "aat:300386845"
    ]
},
  "bbox": [],
  "geometry": {"coordinates":[-106.8667,37.1667],"type":"Point"}
}
=======
{"geometry":{"type":"Point","coordinates":[-106.866700,37.166700]},"type":"Feature","properties":{"hierarchy":["tgn:2153515","tgn:2000195","tgn:1000001","tgn:7012149","tgn:7007158","tgn:7029392"],"placetype":["aat:300386845"],"id":2153515,"name:xx":"Bear Basin"}}
>>>>>>> 03f74aca74312dbeaf24d7e61306dd6a786dc3d0
