{
  "id": 7418140,
  "type": "Feature",
  "properties": {
    "tgn:hierarchy":[
        "tgn:7418140",
        "tgn:1001836",
        "tgn:1000001",
        "tgn:7005560",
        "tgn:7029392"
    ],
    "tgn:id":7418140,
    "tgn:name":"Blanca, Punta",
    "tgn:placetype":[
        "aat:300386846"
    ]
},
  "bbox": [],
  "geometry": {"coordinates":[-110.881667,25.128611],"type":"Point"}
}