{
  "id": 2582686,
  "type": "Feature",
  "properties": {
    "tgn:hierarchy":[
        "tgn:2582686",
        "tgn:1000001",
        "tgn:7012149",
        "tgn:2000329",
        "tgn:7007248",
        "tgn:7029392"
    ],
    "tgn:id":2582686,
    "tgn:name":"Pine Hills",
    "tgn:placetype":[
        "aat:300008347"
    ]
},
  "bbox": [],
  "geometry": {"coordinates":[-84.8333,33.35],"type":"Point"}
}