{
  "id": 2582196,
  "type": "Feature",
  "properties": {
    "tgn:hierarchy":[
        "tgn:2582196",
        "tgn:1000001",
        "tgn:7012149",
        "tgn:2001396",
        "tgn:7007525",
        "tgn:7029392"
    ],
    "tgn:id":2582196,
    "tgn:name":"Pine Creek",
    "tgn:placetype":[
        "aat:300008706"
    ]
},
  "bbox": [],
  "geometry": {"coordinates":[-102.4167,42.35],"type":"Point"}
}