{
  "id": 2106907,
  "type": "Feature",
  "properties": {
    "tgn:hierarchy":[
        "tgn:2106907",
        "tgn:1000001",
        "tgn:7012149",
        "tgn:1002485",
        "tgn:7007826",
        "tgn:7029392"
    ],
    "tgn:id":2106907,
    "tgn:name":"Posey",
    "tgn:placetype":[
        "aat:300008347",
        "aat:300387210"
    ]
},
  "bbox": [],
  "geometry": {"coordinates":[-95.65,33.2667],"type":"Point"}
}