{
  "id": 7228116,
  "type": "Feature",
  "properties": {
    "tgn:hierarchy":[
        "tgn:7228116",
        "tgn:7002741",
        "tgn:7017076",
        "tgn:1000003",
        "tgn:1000074",
        "tgn:7029392"
    ],
    "tgn:id":7228116,
    "tgn:name":"Gounari\u00e1nnika",
    "tgn:placetype":[
        "aat:300008347"
    ]
},
  "bbox": [],
  "geometry": {"coordinates":[22.233333,38.016667],"type":"Point"}
}