{
  "id": 7591110,
  "type": "Feature",
  "properties": {
    "tgn:hierarchy":[
        "tgn:7591110",
        "tgn:1000004",
        "tgn:7000198",
        "tgn:7000799",
        "tgn:7029392"
    ],
    "tgn:id":7591110,
    "tgn:name:en":"Nanian",
    "tgn:placetype":[
        "aat:300008347"
    ]
},
  "bbox": [],
  "geometry": {"coordinates":[74.45,32.995833],"type":"Point"}
}