{
  "id": 1007041,
  "type": "Feature",
  "properties": {
    "tgn:hierarchy":[
        "tgn:1007041",
        "tgn:7002444",
        "tgn:1000003",
        "tgn:7008094",
        "tgn:7008591",
        "tgn:7029392"
    ],
    "tgn:id":1007041,
    "tgn:name:en":"Ensay",
    "tgn:placetype":[
        "aat:300008791"
    ]
},
  "bbox": [],
  "geometry": {"coordinates":[-7.083333,57.766667],"type":"Point"}
}