{
  "id": 2547244,
  "type": "Feature",
  "properties": {
    "tgn:hierarchy":[
        "tgn:2547244",
        "tgn:1000001",
        "tgn:7012149",
        "tgn:2001276",
        "tgn:7007524",
        "tgn:7029392"
    ],
    "tgn:id":2547244,
    "tgn:name":"North Fork Sage Hen Creek",
    "tgn:placetype":[
        "aat:300008706"
    ]
},
  "bbox": [],
  "geometry": {"coordinates":[-107.8333,47.05],"type":"Point"}
}