{
  "id": 7369532,
  "type": "Feature",
  "properties": {
    "tgn:hierarchy":[
        "tgn:7369532",
        "tgn:1000001",
        "tgn:7005592",
        "tgn:7005560",
        "tgn:7029392"
    ],
    "tgn:id":7369532,
    "tgn:name":"Huajoyuca",
    "tgn:placetype":[
        "aat:300008347"
    ]
},
  "bbox": [],
  "geometry": {"coordinates":[-97.916667,18.516667],"type":"Point"}
}