<<<<<<< HEAD
{
  "id": 2156681,
  "type": "Feature",
  "properties": {
    "tgn:hierarchy":[
        "tgn:2156681",
        "tgn:1000001",
        "tgn:7012149",
        "tgn:2001864",
        "tgn:7007825",
        "tgn:7029392"
    ],
    "tgn:id":2156681,
    "tgn:name":"Beasley Island",
    "tgn:placetype":[
        "aat:300008791"
    ]
},
  "bbox": [],
  "geometry": {"coordinates":[-86.9,35.0167],"type":"Point"}
}
=======
{"geometry":{"type":"Point","coordinates":[-86.900000,35.016700]},"type":"Feature","properties":{"hierarchy":["tgn:2156681","tgn:1000001","tgn:7012149","tgn:2001864","tgn:7007825","tgn:7029392"],"placetype":["aat:300008791"],"id":2156681,"name:xx":"Beasley Island"}}
>>>>>>> 03f74aca74312dbeaf24d7e61306dd6a786dc3d0
