{
  "id": 7025363,
  "type": "Feature",
  "properties": {
    "tgn:hierarchy":[
        "tgn:7025363",
        "tgn:7002445",
        "tgn:1000003",
        "tgn:7012077",
        "tgn:7008591",
        "tgn:7029392"
    ],
    "tgn:id":7025363,
    "tgn:name":"North Aller",
    "tgn:placetype":[
        "aat:300008347"
    ]
},
  "bbox": [],
  "geometry": {"coordinates":[-3.85,51.0333],"type":"Point"}
}