{
  "id": 1023666,
  "type": "Feature",
  "properties": {
    "tgn:hierarchy":[
        "tgn:1023666",
        "tgn:7016598",
        "tgn:1000049",
        "tgn:1000002",
        "tgn:7029392"
    ],
    "tgn:id":1023666,
    "tgn:name":"Toconao",
    "tgn:placetype":[
        "aat:300008347"
    ]
},
  "bbox": [],
  "geometry": {"coordinates":[-68.016667,-23.183333],"type":"Point"}
}