{
  "id": 1129146,
  "type": "Feature",
  "properties": {
    "tgn:hierarchy":[
        "tgn:1129146",
        "tgn:7005694",
        "tgn:7005685",
        "tgn:1000001",
        "tgn:7029392"
    ],
    "tgn:id":1129146,
    "tgn:name":"Rocky",
    "tgn:placetype":[
        "aat:300008707"
    ]
},
  "bbox": [],
  "geometry": {"coordinates":[-117.9833,53.1333],"type":"Point"}
}