{
  "id": 7385276,
  "type": "Feature",
  "properties": {
    "tgn:hierarchy":[
        "tgn:7385276",
        "tgn:1000001",
        "tgn:1001906",
        "tgn:7005560",
        "tgn:7029392"
    ],
    "tgn:id":7385276,
    "tgn:name":"Palmito del Verde, Isla",
    "tgn:placetype":[
        "aat:300008791"
    ]
},
  "bbox": [],
  "geometry": {"coordinates":[-105.833333,22.666667],"type":"Point"}
}