{
  "id": 7236069,
  "type": "Feature",
  "properties": {
    "tgn:hierarchy":[
        "tgn:7236069",
        "tgn:7002719",
        "tgn:7002715",
        "tgn:1000003",
        "tgn:1000074",
        "tgn:7029392"
    ],
    "tgn:id":7236069,
    "tgn:name":"Exoch\u00ed",
    "tgn:placetype":[
        "aat:300008347"
    ]
},
  "bbox": [],
  "geometry": {"coordinates":[23.833333,41.416667],"type":"Point"}
}