{
  "id": 7496034,
  "type": "Feature",
  "properties": {
    "tgn:hierarchy":[
        "tgn:7496034",
        "tgn:7487020",
        "tgn:1000004",
        "tgn:1000141",
        "tgn:7029392"
    ],
    "tgn:id":7496034,
    "tgn:name":"Qiedonghen",
    "tgn:placetype":[
        "aat:300387033"
    ]
},
  "bbox": [],
  "geometry": {"coordinates":[120.767854,24.452963],"type":"Point"}
}