{
  "id": 2364472,
  "type": "Feature",
  "properties": {
    "tgn:hierarchy":[
        "tgn:2364472",
        "tgn:1000001",
        "tgn:7012149",
        "tgn:7007157",
        "tgn:1002675",
        "tgn:7029392"
    ],
    "tgn:id":2364472,
    "tgn:name":"Green Treble Lake",
    "tgn:placetype":[
        "aat:300008680"
    ]
},
  "bbox": [],
  "geometry": {"coordinates":[-119.2833,37.95],"type":"Point"}
}