{
  "id": 1005362,
  "type": "Feature",
  "properties": {
    "tgn:hierarchy":[
        "tgn:1005362",
        "tgn:1000882",
        "tgn:1000003",
        "tgn:1000090",
        "tgn:7029392"
    ],
    "tgn:id":1005362,
    "tgn:name":"Pontinha",
    "tgn:placetype":[
        "aat:300008347",
        "aat:300000745"
    ]
},
  "bbox": [],
  "geometry": {"coordinates":[-9.199,38.767],"type":"Point"}
}