{
  "id": 2713956,
  "type": "Feature",
  "properties": {
    "tgn:hierarchy":[
        "tgn:2713956",
        "tgn:1000001",
        "tgn:2001264",
        "tgn:7012149",
        "tgn:7007524",
        "tgn:7029392"
    ],
    "tgn:id":2713956,
    "tgn:name":"Teeples Spring",
    "tgn:placetype":[
        "aat:300008697"
    ]
},
  "bbox": [],
  "geometry": {"coordinates":[-108.4167,45.1833],"type":"Point"}
}