{
  "id": 2493269,
  "type": "Feature",
  "properties": {
    "tgn:hierarchy":[
        "tgn:2493269",
        "tgn:1000001",
        "tgn:7006451",
        "tgn:7012149",
        "tgn:2000103",
        "tgn:7029392"
    ],
    "tgn:id":2493269,
    "tgn:name":"Maroney Gulch",
    "tgn:placetype":[
        "aat:300008761"
    ]
},
  "bbox": [],
  "geometry": {"coordinates":[-113.1833,34.5667],"type":"Point"}
}