{
  "id": 7286989,
  "type": "Feature",
  "properties": {
    "tgn:hierarchy":[
        "tgn:7286989",
        "tgn:7016598",
        "tgn:1000049",
        "tgn:1000002",
        "tgn:7029392"
    ],
    "tgn:id":7286989,
    "tgn:name":"Gentilar",
    "tgn:placetype":[
        "aat:300008697"
    ]
},
  "bbox": [],
  "geometry": {"coordinates":[-68.65,-22.283333],"type":"Point"}
}