{
  "id": 2781236,
  "type": "Feature",
  "properties": {
    "tgn:hierarchy":[
        "tgn:2781236",
        "tgn:1000001",
        "tgn:7012149",
        "tgn:2001764",
        "tgn:7007712",
        "tgn:7029392"
    ],
    "tgn:id":2781236,
    "tgn:name":"Woodhill Estates",
    "tgn:placetype":[
        "aat:300008347"
    ]
},
  "bbox": [],
  "geometry": {"coordinates":[-80.9667,33.9667],"type":"Point"}
}