{
  "id": 7155429,
  "type": "Feature",
  "properties": {
    "tgn:hierarchy":[
        "tgn:7155429",
        "tgn:1000003",
        "tgn:7003676",
        "tgn:7000084",
        "tgn:7029392"
    ],
    "tgn:id":7155429,
    "tgn:name":"Klein Charlottengrode",
    "tgn:placetype":[
        "aat:300000206"
    ]
},
  "bbox": [],
  "geometry": {"coordinates":[7.766667,53.683333],"type":"Point"}
}