{
  "id": 7193517,
  "type": "Feature",
  "properties": {
    "tgn:hierarchy":[
        "tgn:7193517",
        "tgn:1000003",
        "tgn:7003678",
        "tgn:7000084",
        "tgn:7029392"
    ],
    "tgn:id":7193517,
    "tgn:name":"Bahnhof Frankfurt-Sportfeld",
    "tgn:placetype":[
        "aat:300007783"
    ]
},
  "bbox": [],
  "geometry": {"coordinates":[8.6325,50.067778],"type":"Point"}
}