{
  "id": 1129006,
  "type": "Feature",
  "properties": {
    "tgn:hierarchy":[
        "tgn:1129006",
        "tgn:1000001",
        "tgn:7012149",
        "tgn:2000968",
        "tgn:7007520",
        "tgn:7029392"
    ],
    "tgn:id":1129006,
    "tgn:name":"Rapid",
    "tgn:placetype":[
        "aat:300008707"
    ]
},
  "bbox": [],
  "geometry": {"coordinates":[-85.0667,44.8333],"type":"Point"}
}