{
  "id": 7384020,
  "type": "Feature",
  "properties": {
    "tgn:hierarchy":[
        "tgn:7384020",
        "tgn:1001836",
        "tgn:1000001",
        "tgn:7005560",
        "tgn:7029392"
    ],
    "tgn:id":7384020,
    "tgn:name":"Nopol\u00f3, Punta",
    "tgn:placetype":[
        "aat:300386846"
    ]
},
  "bbox": [],
  "geometry": {"coordinates":[-110.759167,25.016667],"type":"Point"}
}