{
  "id": 2482036,
  "type": "Feature",
  "properties": {
    "tgn:hierarchy":[
        "tgn:2482036",
        "tgn:1000001",
        "tgn:7012149",
        "tgn:2001226",
        "tgn:7007523",
        "tgn:7029392"
    ],
    "tgn:id":2482036,
    "tgn:name":"Lane Spring",
    "tgn:placetype":[
        "aat:300008697"
    ]
},
  "bbox": [],
  "geometry": {"coordinates":[-92.1667,36.65],"type":"Point"}
}