{
  "id": 2244378,
  "type": "Feature",
  "properties": {
    "tgn:hierarchy":[
        "tgn:2244378",
        "tgn:1000001",
        "tgn:7012149",
        "tgn:2001876",
        "tgn:7007825",
        "tgn:7029392"
    ],
    "tgn:id":2244378,
    "tgn:name":"Clifty Creek",
    "tgn:placetype":[
        "aat:300008706"
    ]
},
  "bbox": [],
  "geometry": {"coordinates":[-88.3167,36.2667],"type":"Point"}
}