{
  "id": 1035135,
  "type": "Feature",
  "properties": {
    "tgn:hierarchy":[
        "tgn:1035135",
        "tgn:1000003",
        "tgn:7001097",
        "tgn:1000070",
        "tgn:7029392"
    ],
    "tgn:id":1035135,
    "tgn:name":"Roncq",
    "tgn:placetype":[
        "aat:300008347"
    ]
},
  "bbox": [],
  "geometry": {"coordinates":[3.1167,50.75],"type":"Point"}
}