{
  "id": 2552871,
  "type": "Feature",
  "properties": {
    "tgn:hierarchy":[
        "tgn:2552871",
        "tgn:1000001",
        "tgn:7012149",
        "tgn:2001720",
        "tgn:7007708",
        "tgn:7029392"
    ],
    "tgn:id":2552871,
    "tgn:name":"O Pipe",
    "tgn:placetype":[
        "aat:300006075"
    ]
},
  "bbox": [],
  "geometry": {"coordinates":[-119.25,45.8833],"type":"Point"}
}