{
  "id": 7090230,
  "type": "Feature",
  "properties": {
    "tgn:hierarchy":[
        "tgn:7090230",
        "tgn:7003669",
        "tgn:1000003",
        "tgn:7000084",
        "tgn:7029392"
    ],
    "tgn:id":7090230,
    "tgn:name":"Voigendorf",
    "tgn:placetype":[
        "aat:300008347"
    ]
},
  "bbox": [],
  "geometry": {"coordinates":[11.266667,49.833333],"type":"Point"}
}