{
  "id": 7382082,
  "type": "Feature",
  "properties": {
    "tgn:hierarchy":[
        "tgn:7382082",
        "tgn:1000001",
        "tgn:1001893",
        "tgn:7005560",
        "tgn:7029392"
    ],
    "tgn:id":7382082,
    "tgn:name":"Los Bejucos",
    "tgn:placetype":[
        "aat:300008347"
    ]
},
  "bbox": [],
  "geometry": {"coordinates":[-100.433333,18.75],"type":"Point"}
}