{
  "id": 7383687,
  "type": "Feature",
  "properties": {
    "tgn:hierarchy":[
        "tgn:7383687",
        "tgn:7005581",
        "tgn:1000001",
        "tgn:7005560",
        "tgn:7029392"
    ],
    "tgn:id":7383687,
    "tgn:name":"Rancho Paradero",
    "tgn:placetype":[
        "aat:300000241"
    ]
},
  "bbox": [],
  "geometry": {"coordinates":[-105.033333,29.716667],"type":"Point"}
}