{
  "id": 2274348,
  "type": "Feature",
  "properties": {
    "tgn:hierarchy":[
        "tgn:2274348",
        "tgn:2000563",
        "tgn:1000001",
        "tgn:7012149",
        "tgn:7007253",
        "tgn:7029392"
    ],
    "tgn:id":2274348,
    "tgn:name":"Dalby",
    "tgn:placetype":[
        "aat:300008347"
    ]
},
  "bbox": [],
  "geometry": {"coordinates":[-91.2667,43.25],"type":"Point"}
}