{
  "id": 2474008,
  "type": "Feature",
  "properties": {
    "tgn:hierarchy":[
        "tgn:2474008",
        "tgn:1000001",
        "tgn:7006451",
        "tgn:2000095",
        "tgn:7012149",
        "tgn:7029392"
    ],
    "tgn:id":2474008,
    "tgn:name":"Lower Juan Miller Springs Number One",
    "tgn:placetype":[
        "aat:300008697"
    ]
},
  "bbox": [],
  "geometry": {"coordinates":[-109.3167,33.2667],"type":"Point"}
}