{
  "id": 2163026,
  "type": "Feature",
  "properties": {
    "tgn:hierarchy":[
        "tgn:2163026",
        "tgn:1000001",
        "tgn:2001424",
        "tgn:7012149",
        "tgn:7007564",
        "tgn:7029392"
    ],
    "tgn:id":2163026,
    "tgn:name":"Bennett Brook",
    "tgn:placetype":[
        "aat:300008699"
    ]
},
  "bbox": [],
  "geometry": {"coordinates":[-71.55,43.7833],"type":"Point"}
}