{
  "id": 2466146,
  "type": "Feature",
  "properties": {
    "tgn:hierarchy":[
        "tgn:2466146",
        "tgn:1000001",
        "tgn:7012149",
        "tgn:2001300",
        "tgn:7007524",
        "tgn:7029392"
    ],
    "tgn:id":2466146,
    "tgn:name":"Lonesome Bachelor, The",
    "tgn:placetype":[
        "aat:300008798"
    ]
},
  "bbox": [],
  "geometry": {"coordinates":[-114.3667,45.9833],"type":"Point"}
}