{
  "id": 2742089,
  "type": "Feature",
  "properties": {
    "tgn:hierarchy":[
        "tgn:2742089",
        "tgn:2000934",
        "tgn:1000001",
        "tgn:7012149",
        "tgn:7007516",
        "tgn:7029392"
    ],
    "tgn:id":2742089,
    "tgn:name":"Vale Run",
    "tgn:placetype":[
        "aat:300008699"
    ]
},
  "bbox": [],
  "geometry": {"coordinates":[-78.9167,39.6167],"type":"Point"}
}