<<<<<<< HEAD
{
  "id": 7372945,
  "type": "Feature",
  "properties": {
    "tgn:hierarchy":[
        "tgn:7372945",
        "tgn:7005583",
        "tgn:1000001",
        "tgn:7005560",
        "tgn:7029392"
    ],
    "tgn:id":7372945,
    "tgn:name":"La Laguna",
    "tgn:placetype":[
        "aat:300008347"
    ]
},
  "bbox": [],
  "geometry": {"coordinates":[-106.4,24.616667],"type":"Point"}
}
=======
{"geometry":{"type":"Point","coordinates":[-106.400000,24.616667]},"type":"Feature","properties":{"hierarchy":["tgn:7372945","tgn:7005583","tgn:1000001","tgn:7005560","tgn:7029392"],"placetype":["aat:300008347"],"id":7372945,"name:xx":"La Laguna"}}
>>>>>>> 03f74aca74312dbeaf24d7e61306dd6a786dc3d0
