{
  "id": 1018965,
  "type": "Feature",
  "properties": {
    "tgn:hierarchy":[
        "tgn:1018965",
        "tgn:7017440",
        "tgn:1000001",
        "tgn:7004643",
        "tgn:7029392"
    ],
    "tgn:id":1018965,
    "tgn:name":"Jobos",
    "tgn:placetype":[
        "aat:300008347"
    ]
},
  "bbox": [],
  "geometry": {"coordinates":[-66.1667,17.9667],"type":"Point"}
}