{
  "id": 2507342,
  "type": "Feature",
  "properties": {
    "tgn:hierarchy":[
        "tgn:2507342",
        "tgn:1000001",
        "tgn:2002109",
        "tgn:7012149",
        "tgn:7007827",
        "tgn:7029392"
    ],
    "tgn:id":2507342,
    "tgn:name":"Mexican Hollow",
    "tgn:placetype":[
        "aat:300008761"
    ]
},
  "bbox": [],
  "geometry": {"coordinates":[-112.5333,37.65],"type":"Point"}
}