{
  "id": 7031599,
  "type": "Feature",
  "properties": {
    "tgn:hierarchy":[
        "tgn:7031599",
        "tgn:7594005",
        "tgn:1000003",
        "tgn:1000066",
        "tgn:7029392"
    ],
    "tgn:id":7031599,
    "tgn:name":"Humleb\u00e6k",
    "tgn:placetype":[
        "aat:300008347"
    ]
},
  "bbox": [],
  "geometry": {"coordinates":[12.5667,55.9667],"type":"Point"}
}