<<<<<<< HEAD
{
  "id": 2154810,
  "type": "Feature",
  "properties": {
    "tgn:hierarchy":[
        "tgn:2154810",
        "tgn:2001318",
        "tgn:1000001",
        "tgn:7012149",
        "tgn:7007525",
        "tgn:7029392"
    ],
    "tgn:id":2154810,
    "tgn:name":"Bear Hill",
    "tgn:placetype":[
        "aat:300008798"
    ]
},
  "bbox": [],
  "geometry": {"coordinates":[-101.8,41.4167],"type":"Point"}
}
=======
{"geometry":{"type":"Point","coordinates":[-101.800000,41.416700]},"type":"Feature","properties":{"hierarchy":["tgn:2154810","tgn:2001318","tgn:1000001","tgn:7012149","tgn:7007525","tgn:7029392"],"placetype":["aat:300008798"],"id":2154810,"name:xx":"Bear Hill"}}
>>>>>>> 03f74aca74312dbeaf24d7e61306dd6a786dc3d0
