{
  "id": 7420813,
  "type": "Feature",
  "properties": {
    "tgn:hierarchy":[
        "tgn:7420813",
        "tgn:1001836",
        "tgn:1000001",
        "tgn:7005560",
        "tgn:7029392"
    ],
    "tgn:id":7420813,
    "tgn:name":"Palo Fierral",
    "tgn:placetype":[
        "aat:300008347"
    ]
},
  "bbox": [],
  "geometry": {"coordinates":[-111.688889,24.796667],"type":"Point"}
}