{
  "id": 7151694,
  "type": "Feature",
  "properties": {
    "tgn:hierarchy":[
        "tgn:7151694",
        "tgn:1000003",
        "tgn:7003677",
        "tgn:7000084",
        "tgn:7029392"
    ],
    "tgn:id":7151694,
    "tgn:name":"Kahlen-Berg",
    "tgn:placetype":[
        "aat:300008795"
    ]
},
  "bbox": [],
  "geometry": {"coordinates":[8.75,51.383333],"type":"Point"}
}