{
  "id": 1076036,
  "type": "Feature",
  "properties": {
    "tgn:hierarchy":[
        "tgn:1076036",
        "tgn:1000004",
        "tgn:7000198",
        "tgn:7016722",
        "tgn:7029392"
    ],
    "tgn:id":1076036,
    "tgn:name:en":"Loni",
    "tgn:placetype":[
        "aat:300008347"
    ]
},
  "bbox": [],
  "geometry": {"coordinates":[77.288,28.751527],"type":"Point"}
}