{
  "id": 2004263,
  "type": "Feature",
  "properties": {
    "tgn:hierarchy":[
        "tgn:2004263",
        "tgn:7002659",
        "tgn:1000001",
        "tgn:7012149",
        "tgn:2000041",
        "tgn:7029392"
    ],
    "tgn:id":2004263,
    "tgn:name":"Locke Crossroads",
    "tgn:placetype":[
        "aat:300008347",
        "aat:300387210"
    ]
},
  "bbox": [],
  "geometry": {"coordinates":[-86.95,34.9333],"type":"Point"}
}