{
  "id": 7475892,
  "type": "Feature",
  "properties": {
    "tgn:hierarchy":[
        "tgn:7475892",
        "tgn:7488858",
        "tgn:1000004",
        "tgn:1000141",
        "tgn:7029392"
    ],
    "tgn:id":7475892,
    "tgn:name":"Shi'anwei",
    "tgn:placetype":[
        "aat:300008347"
    ]
},
  "bbox": [],
  "geometry": {"coordinates":[120.6985,23.8139],"type":"Point"}
}