{
  "id": 7011052,
  "type": "Feature",
  "properties": {
    "tgn:hierarchy":[
        "tgn:7011052",
        "tgn:7002681",
        "tgn:7001395",
        "tgn:1000003",
        "tgn:1000074",
        "tgn:7029392"
    ],
    "tgn:id":7011052,
    "tgn:name":"Salam\u00eds",
    "tgn:placetype":[
        "aat:300008791"
    ]
},
  "bbox": [],
  "geometry": {"coordinates":[23.506771,37.921886],"type":"Point"}
}