{
  "id": 2349450,
  "type": "Feature",
  "properties": {
    "tgn:hierarchy":[
        "tgn:2349450",
        "tgn:1000001",
        "tgn:2000921",
        "tgn:7012149",
        "tgn:7007515",
        "tgn:7029392"
    ],
    "tgn:id":2349450,
    "tgn:name":"Gilkey Brook",
    "tgn:placetype":[
        "aat:300008699"
    ]
},
  "bbox": [],
  "geometry": {"coordinates":[-70.1833,44.8833],"type":"Point"}
}