{
  "id": 7439324,
  "type": "Feature",
  "properties": {
    "tgn:hierarchy":[
        "tgn:7439324",
        "tgn:1001853",
        "tgn:1000001",
        "tgn:7005560",
        "tgn:7029392"
    ],
    "tgn:id":7439324,
    "tgn:name":"Tecolote, Cerro",
    "tgn:placetype":[
        "aat:300008777"
    ]
},
  "bbox": [],
  "geometry": {"coordinates":[-102.983333,26.016667],"type":"Point"}
}