{
  "id": 2324877,
  "type": "Feature",
  "properties": {
    "tgn:hierarchy":[
        "tgn:2324877",
        "tgn:1000001",
        "tgn:7012149",
        "tgn:2002383",
        "tgn:7007923",
        "tgn:7029392"
    ],
    "tgn:id":2324877,
    "tgn:name":"Ferguson Corner",
    "tgn:placetype":[
        "aat:300008347"
    ]
},
  "bbox": [],
  "geometry": {"coordinates":[-105.1167,41.95],"type":"Point"}
}