{
  "id": 1015747,
  "type": "Feature",
  "properties": {
    "tgn:hierarchy":[
        "tgn:1015747",
        "tgn:7005685",
        "tgn:1000001",
        "tgn:7005804",
        "tgn:7029392"
    ],
    "tgn:id":1015747,
    "tgn:name":"Sainte-H\u00e9l\u00e8ne-de-Bagot",
    "tgn:placetype":[
        "aat:300008347"
    ]
},
  "bbox": [],
  "geometry": {"coordinates":[-72.7333,45.7333],"type":"Point"}
}