{
  "id": 2063322,
  "type": "Feature",
  "properties": {
    "tgn:hierarchy":[
        "tgn:2063322",
        "tgn:1000001",
        "tgn:1002480",
        "tgn:7012149",
        "tgn:7007564",
        "tgn:7029392"
    ],
    "tgn:id":2063322,
    "tgn:name":"Clinton Grove",
    "tgn:placetype":[
        "aat:300008347",
        "aat:300387210"
    ]
},
  "bbox": [],
  "geometry": {"coordinates":[-71.75,43.0667],"type":"Point"}
}