{
  "id": 2651950,
  "type": "Feature",
  "properties": {
    "tgn:hierarchy":[
        "tgn:2651950",
        "tgn:1000001",
        "tgn:7012149",
        "tgn:1002679",
        "tgn:7007520",
        "tgn:7029392"
    ],
    "tgn:id":2651950,
    "tgn:name":"Seitz Drain",
    "tgn:placetype":[
        "aat:300008699"
    ]
},
  "bbox": [],
  "geometry": {"coordinates":[-83.55,41.9667],"type":"Point"}
}