{
  "id": 7039936,
  "type": "Feature",
  "properties": {
    "tgn:hierarchy":[
        "tgn:7039936",
        "tgn:7003137",
        "tgn:1000003",
        "tgn:7003080",
        "tgn:1000080",
        "tgn:7029392"
    ],
    "tgn:id":7039936,
    "tgn:name":"Secco, Fosso",
    "tgn:placetype":[
        "aat:300008699"
    ]
},
  "bbox": [],
  "geometry": {"coordinates":[13.05,42.05],"type":"Point"}
}