{
  "id": 1123036,
  "type": "Feature",
  "properties": {
    "tgn:hierarchy":[
        "tgn:1123036",
        "tgn:7000490",
        "tgn:1000006",
        "tgn:7001828",
        "tgn:7029392"
    ],
    "tgn:id":1123036,
    "tgn:name":"Cooks River",
    "tgn:placetype":[
        "aat:300008707"
    ]
},
  "bbox": [],
  "geometry": {"coordinates":[151.1833,-33.95],"type":"Point"}
}