{
  "id": 7469136,
  "type": "Feature",
  "properties": {
    "tgn:hierarchy":[
        "tgn:7469136",
        "tgn:1000004",
        "tgn:7467799",
        "tgn:1000141",
        "tgn:7029392"
    ],
    "tgn:id":7469136,
    "tgn:name":"Zhong Xi",
    "tgn:placetype":[
        "aat:300008699"
    ]
},
  "bbox": [],
  "geometry": {"coordinates":[120.366667,24.033333],"type":"Point"}
}