{
  "id": 7550507,
  "type": "Feature",
  "properties": {
    "tgn:hierarchy":[
        "tgn:7550507",
        "tgn:1000004",
        "tgn:1001869",
        "tgn:7000198",
        "tgn:7029392"
    ],
    "tgn:id":7550507,
    "tgn:name:en":"Chh\u0101ra",
    "tgn:placetype":[
        "aat:300008347"
    ]
},
  "bbox": [],
  "geometry": {"coordinates":[70.714722,20.739722],"type":"Point"}
}