{
  "id": 1038172,
  "type": "Feature",
  "properties": {
    "tgn:hierarchy":[
        "tgn:1038172",
        "tgn:1000003",
        "tgn:7003677",
        "tgn:7000084",
        "tgn:7029392"
    ],
    "tgn:id":1038172,
    "tgn:name":"Altenbeken",
    "tgn:placetype":[
        "aat:300008347"
    ]
},
  "bbox": [],
  "geometry": {"coordinates":[8.933333,51.766667],"type":"Point"}
}