{
  "id": 2420530,
  "type": "Feature",
  "properties": {
    "tgn:hierarchy":[
        "tgn:2420530",
        "tgn:1000001",
        "tgn:7012149",
        "tgn:2001508",
        "tgn:7007709",
        "tgn:7029392"
    ],
    "tgn:id":2420530,
    "tgn:name":"Jenkins Lake",
    "tgn:placetype":[
        "aat:300006191"
    ]
},
  "bbox": [],
  "geometry": {"coordinates":[-83.1167,35.15],"type":"Point"}
}