{
  "id": 2391949,
  "type": "Feature",
  "properties": {
    "tgn:hierarchy":[
        "tgn:2391949",
        "tgn:1000001",
        "tgn:2001801",
        "tgn:7012149",
        "tgn:7007713",
        "tgn:7029392"
    ],
    "tgn:id":2391949,
    "tgn:name":"Hilton Mine",
    "tgn:placetype":[
        "aat:300000390"
    ]
},
  "bbox": [],
  "geometry": {"coordinates":[-103.55,45.7167],"type":"Point"}
}