{
  "id": 7336303,
  "type": "Feature",
  "properties": {
    "tgn:hierarchy":[
        "tgn:7336303",
        "tgn:7002808",
        "tgn:7030216",
        "tgn:1000003",
        "tgn:1000095",
        "tgn:7029392"
    ],
    "tgn:id":7336303,
    "tgn:name":"Fornes, R\u00edo",
    "tgn:placetype":[
        "aat:300008699"
    ]
},
  "bbox": [],
  "geometry": {"coordinates":[2.266667,42.05],"type":"Point"}
}