<<<<<<< HEAD
{
  "id": 7114571,
  "type": "Feature",
  "properties": {
    "tgn:hierarchy":[
        "tgn:7114571",
        "tgn:1000003",
        "tgn:7003688",
        "tgn:7000084",
        "tgn:7029392"
    ],
    "tgn:id":7114571,
    "tgn:name":"Ritzkrog",
    "tgn:placetype":[
        "aat:300000206"
    ]
},
  "bbox": [],
  "geometry": {"coordinates":[10.7,54.05],"type":"Point"}
}
=======
{"geometry":{"type":"Point","coordinates":[10.700000,54.050000]},"type":"Feature","properties":{"hierarchy":["tgn:7114571","tgn:1000003","tgn:7003688","tgn:7000084","tgn:7029392"],"placetype":["aat:300000206"],"id":7114571,"name:xx":"Ritzkrog"}}
>>>>>>> 03f74aca74312dbeaf24d7e61306dd6a786dc3d0
