{
  "id": 2169465,
  "type": "Feature",
  "properties": {
    "tgn:hierarchy":[
        "tgn:2169465",
        "tgn:1000001",
        "tgn:2001416",
        "tgn:7012149",
        "tgn:7007526",
        "tgn:7029392"
    ],
    "tgn:id":2169465,
    "tgn:name":"Big Lime Mountain",
    "tgn:placetype":[
        "aat:300008798"
    ]
},
  "bbox": [],
  "geometry": {"coordinates":[-114.7667,37.3833],"type":"Point"}
}