{
  "id": 2611702,
  "type": "Feature",
  "properties": {
    "tgn:hierarchy":[
        "tgn:2611702",
        "tgn:1000001",
        "tgn:7012149",
        "tgn:2000809",
        "tgn:7007255",
        "tgn:7029392"
    ],
    "tgn:id":2611702,
    "tgn:name":"Red Mud Ridge",
    "tgn:placetype":[
        "aat:300266640"
    ]
},
  "bbox": [],
  "geometry": {"coordinates":[-82.7667,38.1333],"type":"Point"}
}