{
  "id": 2263387,
  "type": "Feature",
  "properties": {
    "tgn:hierarchy":[
        "tgn:2263387",
        "tgn:1000001",
        "tgn:7012149",
        "tgn:2001896",
        "tgn:7007825",
        "tgn:7029392"
    ],
    "tgn:id":2263387,
    "tgn:name":"Cox Hollow",
    "tgn:placetype":[
        "aat:300008761"
    ]
},
  "bbox": [],
  "geometry": {"coordinates":[-87.2833,35.55],"type":"Point"}
}