{
  "id": 2246993,
  "type": "Feature",
  "properties": {
    "tgn:hierarchy":[
        "tgn:2246993",
        "tgn:1000001",
        "tgn:2001745",
        "tgn:7012149",
        "tgn:7007712",
        "tgn:7029392"
    ],
    "tgn:id":2246993,
    "tgn:name":"Cockfield Bay",
    "tgn:placetype":[
        "aat:300386845"
    ]
},
  "bbox": [],
  "geometry": {"coordinates":[-79.6167,33.95],"type":"Point"}
}