{
  "id": 2306078,
  "type": "Feature",
  "properties": {
    "tgn:hierarchy":[
        "tgn:2306078",
        "tgn:1000001",
        "tgn:7012149",
        "tgn:7007157",
        "tgn:1002857",
        "tgn:7029392"
    ],
    "tgn:id":2306078,
    "tgn:name":"East Fork Barton Creek",
    "tgn:placetype":[
        "aat:300008706"
    ]
},
  "bbox": [],
  "geometry": {"coordinates":[-116.8833,34.1167],"type":"Point"}
}