{
  "id": 2405154,
  "type": "Feature",
  "properties": {
    "tgn:hierarchy":[
        "tgn:2405154",
        "tgn:1000001",
        "tgn:7012149",
        "tgn:2001452",
        "tgn:7007566",
        "tgn:7029392"
    ],
    "tgn:id":2405154,
    "tgn:name":"Huerfanito Canyon",
    "tgn:placetype":[
        "aat:300008761"
    ]
},
  "bbox": [],
  "geometry": {"coordinates":[-107.7667,36.5333],"type":"Point"}
}