{
  "id": 2463090,
  "type": "Feature",
  "properties": {
    "tgn:hierarchy":[
        "tgn:2463090",
        "tgn:1000001",
        "tgn:7012149",
        "tgn:7016056",
        "tgn:7007520",
        "tgn:7029392"
    ],
    "tgn:id":2463090,
    "tgn:name":"Livergood Drain",
    "tgn:placetype":[
        "aat:300006075"
    ]
},
  "bbox": [],
  "geometry": {"coordinates":[-82.7333,43.1167],"type":"Point"}
}