{
  "id": 2213801,
  "type": "Feature",
  "properties": {
    "tgn:hierarchy":[
        "tgn:2213801",
        "tgn:1000001",
        "tgn:7012149",
        "tgn:2002110",
        "tgn:7007827",
        "tgn:7029392"
    ],
    "tgn:id":2213801,
    "tgn:name":"Cactus Rat Mine",
    "tgn:placetype":[
        "aat:300000390"
    ]
},
  "bbox": [],
  "geometry": {"coordinates":[-109.4833,38.85],"type":"Point"}
}