{
  "id": 7313360,
  "type": "Feature",
  "properties": {
    "tgn:hierarchy":[
        "tgn:7313360",
        "tgn:1001695",
        "tgn:1000049",
        "tgn:1000002",
        "tgn:7029392"
    ],
    "tgn:id":7313360,
    "tgn:name":"Llivillivi, Alto",
    "tgn:placetype":[
        "aat:300008795"
    ]
},
  "bbox": [],
  "geometry": {"coordinates":[-70.916667,-34.15],"type":"Point"}
}