{
  "id": 2733313,
  "type": "Feature",
  "properties": {
    "tgn:hierarchy":[
        "tgn:2733313",
        "tgn:1000001",
        "tgn:7012149",
        "tgn:2001679",
        "tgn:7007707",
        "tgn:7029392"
    ],
    "tgn:id":2733313,
    "tgn:name":"Turkey Run",
    "tgn:placetype":[
        "aat:300008699"
    ]
},
  "bbox": [],
  "geometry": {"coordinates":[-96.45,36.55],"type":"Point"}
}