{
  "id": 2205189,
  "type": "Feature",
  "properties": {
    "tgn:hierarchy":[
        "tgn:2205189",
        "tgn:1000001",
        "tgn:7012149",
        "tgn:2000488",
        "tgn:7007250",
        "tgn:7029392"
    ],
    "tgn:id":2205189,
    "tgn:name":"Bull Basin",
    "tgn:placetype":[
        "aat:300386845"
    ]
},
  "bbox": [],
  "geometry": {"coordinates":[-116.2667,42.45],"type":"Point"}
}