{
  "id": 2231543,
  "type": "Feature",
  "properties": {
    "tgn:hierarchy":[
        "tgn:2231543",
        "tgn:1000001",
        "tgn:7006451",
        "tgn:2000093",
        "tgn:7012149",
        "tgn:7029392"
    ],
    "tgn:id":2231543,
    "tgn:name":"Chalk Mountain",
    "tgn:placetype":[
        "aat:300008798"
    ]
},
  "bbox": [],
  "geometry": {"coordinates":[-111.15,33.9833],"type":"Point"}
}