{
  "id": 2068907,
  "type": "Feature",
  "properties": {
    "tgn:hierarchy":[
        "tgn:2068907",
        "tgn:1000001",
        "tgn:7012149",
        "tgn:1002821",
        "tgn:7007568",
        "tgn:7029392"
    ],
    "tgn:id":2068907,
    "tgn:name":"East Buskirk",
    "tgn:placetype":[
        "aat:300008347",
        "aat:300387210"
    ]
},
  "bbox": [],
  "geometry": {"coordinates":[-73.4333,42.9333],"type":"Point"}
}