<<<<<<< HEAD
{
  "id": 7171014,
  "type": "Feature",
  "properties": {
    "tgn:hierarchy":[
        "tgn:7171014",
        "tgn:1000003",
        "tgn:7003685",
        "tgn:7000084",
        "tgn:7029392"
    ],
    "tgn:id":7171014,
    "tgn:name":"Hengst-Berg",
    "tgn:placetype":[
        "aat:300008777"
    ]
},
  "bbox": [],
  "geometry": {"coordinates":[12.733333,51.266667],"type":"Point"}
}
=======
{"geometry":{"type":"Point","coordinates":[12.733333,51.266667]},"type":"Feature","properties":{"hierarchy":["tgn:7171014","tgn:1000003","tgn:7003685","tgn:7000084","tgn:7029392"],"placetype":["aat:300008777"],"id":7171014,"name:xx":"Hengst-Berg"}}
>>>>>>> 03f74aca74312dbeaf24d7e61306dd6a786dc3d0
