{
  "id": 2690935,
  "type": "Feature",
  "properties": {
    "tgn:hierarchy":[
        "tgn:2690935",
        "tgn:7030515",
        "tgn:7006450",
        "tgn:1000001",
        "tgn:7012149",
        "tgn:7029392"
    ],
    "tgn:id":2690935,
    "tgn:name":"Staniukovich Mountain",
    "tgn:placetype":[
        "aat:300008798"
    ]
},
  "bbox": [],
  "geometry": {"coordinates":[-160.6167,55.8167],"type":"Point"}
}