{
  "id": 2406877,
  "type": "Feature",
  "properties": {
    "tgn:hierarchy":[
        "tgn:2406877",
        "tgn:1000001",
        "tgn:7012149",
        "tgn:2001286",
        "tgn:7007524",
        "tgn:7029392"
    ],
    "tgn:id":2406877,
    "tgn:name":"Hunter Creek",
    "tgn:placetype":[
        "aat:300008706"
    ]
},
  "bbox": [],
  "geometry": {"coordinates":[-115.3333,48.0667],"type":"Point"}
}