{
  "id": 1056968,
  "type": "Feature",
  "properties": {
    "tgn:hierarchy":[
        "tgn:1056968",
        "tgn:7011648",
        "tgn:1000003",
        "tgn:7006660",
        "tgn:7029392"
    ],
    "tgn:id":1056968,
    "tgn:name":"Myshuryn Rih",
    "tgn:placetype":[
        "aat:300008347"
    ]
},
  "bbox": [],
  "geometry": {"coordinates":[33.9667,48.8333],"type":"Point"}
}