{
  "id": 1137564,
  "type": "Feature",
  "properties": {
    "tgn:hierarchy":[
        "tgn:1137564",
        "tgn:1000004",
        "tgn:7011608",
        "tgn:7018214",
        "tgn:7002435",
        "tgn:7029392"
    ],
    "tgn:id":1137564,
    "tgn:name":"Yudino",
    "tgn:placetype":[
        "aat:300008347"
    ]
},
  "bbox": [],
  "geometry": {"coordinates":[39.2833,58.7167],"type":"Point"}
}