{
  "id": 2166075,
  "type": "Feature",
  "properties": {
    "tgn:hierarchy":[
        "tgn:2166075",
        "tgn:1000001",
        "tgn:7012149",
        "tgn:7029392"
    ],
    "tgn:id":2166075,
    "tgn:name":"Big Bateau Lake",
    "tgn:placetype":[
        "aat:300008680"
    ]
},
  "bbox": [],
  "geometry": {"coordinates":[-89.2833,46.1667],"type":"Point"}
}