{
  "id": 2575096,
  "type": "Feature",
  "properties": {
    "tgn:hierarchy":[
        "tgn:2575096",
        "tgn:1000001",
        "tgn:7012149",
        "tgn:2000420",
        "tgn:7007248",
        "tgn:7029392"
    ],
    "tgn:id":2575096,
    "tgn:name":"Pennington",
    "tgn:placetype":[
        "aat:300008347"
    ]
},
  "bbox": [],
  "geometry": {"coordinates":[-84.0833,32.15],"type":"Point"}
}