{
  "id": 2288646,
  "type": "Feature",
  "properties": {
    "tgn:hierarchy":[
        "tgn:2288646",
        "tgn:1000001",
        "tgn:7012149",
        "tgn:2001167",
        "tgn:7007522",
        "tgn:7029392"
    ],
    "tgn:id":2288646,
    "tgn:name":"Ditch Branch",
    "tgn:placetype":[
        "aat:300008699"
    ]
},
  "bbox": [],
  "geometry": {"coordinates":[-90.4833,32.6833],"type":"Point"}
}