{
  "id": 7116790,
  "type": "Feature",
  "properties": {
    "tgn:hierarchy":[
        "tgn:7116790",
        "tgn:1000003",
        "tgn:7003682",
        "tgn:7000084",
        "tgn:7029392"
    ],
    "tgn:id":7116790,
    "tgn:name":"Otter Bach",
    "tgn:placetype":[
        "aat:300008699"
    ]
},
  "bbox": [],
  "geometry": {"coordinates":[7.733333,49.483333],"type":"Point"}
}