<<<<<<< HEAD
{
  "id": 7172337,
  "type": "Feature",
  "properties": {
    "tgn:hierarchy":[
        "tgn:7172337",
        "tgn:7003669",
        "tgn:1000003",
        "tgn:7000084",
        "tgn:7029392"
    ],
    "tgn:id":7172337,
    "tgn:name":"Herrenholz",
    "tgn:placetype":[
        "aat:300008863"
    ]
},
  "bbox": [],
  "geometry": {"coordinates":[11.216667,48.866667],"type":"Point"}
}
=======
{"geometry":{"type":"Point","coordinates":[11.216667,48.866667]},"type":"Feature","properties":{"hierarchy":["tgn:7172337","tgn:7003669","tgn:1000003","tgn:7000084","tgn:7029392"],"placetype":["aat:300008863"],"id":7172337,"name:xx":"Herrenholz"}}
>>>>>>> 03f74aca74312dbeaf24d7e61306dd6a786dc3d0
