{
  "id": 2704814,
  "type": "Feature",
  "properties": {
    "tgn:hierarchy":[
        "tgn:2704814",
        "tgn:1000001",
        "tgn:7012149",
        "tgn:1002529",
        "tgn:7007520",
        "tgn:7029392"
    ],
    "tgn:id":2704814,
    "tgn:name":"Sunset Lake",
    "tgn:placetype":[
        "aat:300008680"
    ]
},
  "bbox": [],
  "geometry": {"coordinates":[-85.5333,42.1167],"type":"Point"}
}