{
  "id": 7226965,
  "type": "Feature",
  "properties": {
    "tgn:hierarchy":[
        "tgn:7226965",
        "tgn:7002680",
        "tgn:7001395",
        "tgn:1000003",
        "tgn:1000074",
        "tgn:7029392"
    ],
    "tgn:id":7226965,
    "tgn:name":"Po\u00fanda, \u00c1kra",
    "tgn:placetype":[
        "aat:300386846"
    ]
},
  "bbox": [],
  "geometry": {"coordinates":[22.083333,38.35],"type":"Point"}
}