{
  "id": 2586143,
  "type": "Feature",
  "properties": {
    "tgn:hierarchy":[
        "tgn:2586143",
        "tgn:1000001",
        "tgn:7012149",
        "tgn:1002612",
        "tgn:7007710",
        "tgn:7029392"
    ],
    "tgn:id":2586143,
    "tgn:name":"Pisgah, Mount",
    "tgn:placetype":[
        "aat:300008798"
    ]
},
  "bbox": [],
  "geometry": {"coordinates":[-75.6833,41.2667],"type":"Point"}
}