{
  "id": 2251613,
  "type": "Feature",
  "properties": {
    "tgn:hierarchy":[
        "tgn:2251613",
        "tgn:1000001",
        "tgn:7012149",
        "tgn:7007923",
        "tgn:7029392"
    ],
    "tgn:id":2251613,
    "tgn:name":"Como Ridge",
    "tgn:placetype":[
        "aat:300266640"
    ]
},
  "bbox": [],
  "geometry": {"coordinates":[-106.05,41.8833],"type":"Point"}
}