{
  "id": 7273641,
  "type": "Feature",
  "properties": {
    "tgn:concordances":{
        "gn:id":"2744349"
    },
    "tgn:hierarchy":[
        "tgn:7273641",
        "tgn:1000003",
        "tgn:7003624",
        "tgn:7016845",
        "tgn:7029392"
    ],
    "tgn:id":7273641,
    "tgn:name:nl":"Winkelsche Hoek",
    "tgn:placetype":[
        "aat:300008347"
    ]
},
  "bbox": [],
  "geometry": {"coordinates":[5.166667,51.616667],"type":"Point"}
}