{
  "id": 7233186,
  "type": "Feature",
  "properties": {
    "tgn:hierarchy":[
        "tgn:7233186",
        "tgn:7002728",
        "tgn:7002715",
        "tgn:1000003",
        "tgn:1000074",
        "tgn:7029392"
    ],
    "tgn:id":7233186,
    "tgn:name":"K\u00e1to Loutr\u00e1kion",
    "tgn:placetype":[
        "aat:300008347"
    ]
},
  "bbox": [],
  "geometry": {"coordinates":[21.95,40.966667],"type":"Point"}
}