{
  "id": 2740192,
  "type": "Feature",
  "properties": {
    "tgn:hierarchy":[
        "tgn:2740192",
        "tgn:1000001",
        "tgn:7012149",
        "tgn:7007157",
        "tgn:1002710",
        "tgn:7029392"
    ],
    "tgn:id":2740192,
    "tgn:name":"Upper Jones Valley",
    "tgn:placetype":[
        "aat:300008761"
    ]
},
  "bbox": [],
  "geometry": {"coordinates":[-120.4333,39.35],"type":"Point"}
}