{
  "id": 1065037,
  "type": "Feature",
  "properties": {
    "tgn:hierarchy":[
        "tgn:1065037",
        "tgn:7015100",
        "tgn:1000003",
        "tgn:7006670",
        "tgn:7029392"
    ],
    "tgn:id":1065037,
    "tgn:name":"Jesenice",
    "tgn:placetype":[
        "aat:300008347",
        "aat:300387222",
        "aat:300008375"
    ]
},
  "bbox": [],
  "geometry": {"coordinates":[14.0333,46.4333],"type":"Point"}
}