{
  "id": 1141181,
  "type": "Feature",
  "properties": {
    "tgn:hierarchy":[
        "tgn:1141181",
        "tgn:1000003",
        "tgn:7003677",
        "tgn:7000084",
        "tgn:7004982",
        "tgn:7029392"
    ],
    "tgn:id":1141181,
    "tgn:name":"Rahm",
    "tgn:placetype":[
        "aat:300000745",
        "aat:300387332"
    ]
},
  "bbox": [],
  "geometry": {"coordinates":[7.3833,51.5333],"type":"Point"}
}