{
  "id": 2536799,
  "type": "Feature",
  "properties": {
    "tgn:hierarchy":[
        "tgn:2536799",
        "tgn:1000001",
        "tgn:7012149",
        "tgn:7014398",
        "tgn:7013961",
        "tgn:7029392"
    ],
    "tgn:id":2536799,
    "tgn:name":"Neds Mountain",
    "tgn:placetype":[
        "aat:300008798"
    ]
},
  "bbox": [],
  "geometry": {"coordinates":[-79.3333,38.5833],"type":"Point"}
}