{
  "id": 7126935,
  "type": "Feature",
  "properties": {
    "tgn:hierarchy":[
        "tgn:7126935",
        "tgn:1000003",
        "tgn:7003678",
        "tgn:7000084",
        "tgn:7029392"
    ],
    "tgn:id":7126935,
    "tgn:name":"Oberorke",
    "tgn:placetype":[
        "aat:300008347"
    ]
},
  "bbox": [],
  "geometry": {"coordinates":[8.833333,51.133333],"type":"Point"}
}