{
  "id": 2616728,
  "type": "Feature",
  "properties": {
    "tgn:hierarchy":[
        "tgn:2616728",
        "tgn:1000001",
        "tgn:7012149",
        "tgn:7007825",
        "tgn:7029392"
    ],
    "tgn:id":2616728,
    "tgn:name":"Rich Branch",
    "tgn:placetype":[
        "aat:300008699"
    ]
},
  "bbox": [],
  "geometry": {"coordinates":[-85.45,36.4333],"type":"Point"}
}