{
  "id": 2185101,
  "type": "Feature",
  "properties": {
    "tgn:hierarchy":[
        "tgn:2185101",
        "tgn:1000001",
        "tgn:7012149",
        "tgn:2000378",
        "tgn:7007248",
        "tgn:7029392"
    ],
    "tgn:id":2185101,
    "tgn:name":"Boggy Branch",
    "tgn:placetype":[
        "aat:300008699"
    ]
},
  "bbox": [],
  "geometry": {"coordinates":[-83.1167,32.4167],"type":"Point"}
}