{
  "id": 1015179,
  "type": "Feature",
  "properties": {
    "tgn:hierarchy":[
        "tgn:1015179",
        "tgn:7005685",
        "tgn:1000001",
        "tgn:7013154",
        "tgn:7029392"
    ],
    "tgn:id":1015179,
    "tgn:name":"Uxbridge",
    "tgn:placetype":[
        "aat:300008347"
    ]
},
  "bbox": [],
  "geometry": {"coordinates":[-79.15,44.1167],"type":"Point"}
}