<<<<<<< HEAD
{
  "id": 2333591,
  "type": "Feature",
  "properties": {
    "tgn:hierarchy":[
        "tgn:2333591",
        "tgn:1000001",
        "tgn:7012149",
        "tgn:7007157",
        "tgn:2000189",
        "tgn:7029392"
    ],
    "tgn:id":2333591,
    "tgn:name":"Fons Butte",
    "tgn:placetype":[
        "aat:300008798"
    ]
},
  "bbox": [],
  "geometry": {"coordinates":[-121.9833,41.4],"type":"Point"}
}
=======
{"geometry":{"type":"Point","coordinates":[-121.983300,41.400000]},"type":"Feature","properties":{"hierarchy":["tgn:2333591","tgn:1000001","tgn:7012149","tgn:7007157","tgn:2000189","tgn:7029392"],"placetype":["aat:300008798"],"id":2333591,"name:xx":"Fons Butte"}}
>>>>>>> 03f74aca74312dbeaf24d7e61306dd6a786dc3d0
