{
  "id": 7238066,
  "type": "Feature",
  "properties": {
    "tgn:hierarchy":[
        "tgn:7238066",
        "tgn:7007877",
        "tgn:1000003",
        "tgn:1000063",
        "tgn:4012014",
        "tgn:7029392"
    ],
    "tgn:id":7238066,
    "tgn:name":"Herseau",
    "tgn:placetype":[
        "aat:300008699"
    ]
},
  "bbox": [],
  "geometry": {"coordinates":[3.631196,50.606636],"type":"Point"}
}