{
  "id": 7485655,
  "type": "Feature",
  "properties": {
    "tgn:hierarchy":[
        "tgn:7485655",
        "tgn:1000004",
        "tgn:7490934",
        "tgn:1000141",
        "tgn:7029392"
    ],
    "tgn:id":7485655,
    "tgn:name":"Chaoguang Miao",
    "tgn:placetype":[
        "aat:300007595"
    ]
},
  "bbox": [],
  "geometry": {"coordinates":[120.185278,22.9275],"type":"Point"}
}