{
  "id": 7296006,
  "type": "Feature",
  "properties": {
    "tgn:hierarchy":[
        "tgn:7296006",
        "tgn:7002760",
        "tgn:1000003",
        "tgn:1000095",
        "tgn:7029392"
    ],
    "tgn:id":7296006,
    "tgn:name":"Vaca, Bajos de la",
    "tgn:placetype":[
        "aat:300387036"
    ]
},
  "bbox": [],
  "geometry": {"coordinates":[-3.51,43.494722],"type":"Point"}
}