{
  "id": 7378702,
  "type": "Feature",
  "properties": {
    "tgn:hierarchy":[
        "tgn:7378702",
        "tgn:7005580",
        "tgn:1000001",
        "tgn:7005560",
        "tgn:7029392"
    ],
    "tgn:id":7378702,
    "tgn:name":"Los Cacaos",
    "tgn:placetype":[
        "aat:300008347"
    ]
},
  "bbox": [],
  "geometry": {"coordinates":[-92.65,15.383333],"type":"Point"}
}