{
  "id": 7527958,
  "type": "Feature",
  "properties": {
    "tgn:hierarchy":[
        "tgn:7527958",
        "tgn:7001242",
        "tgn:7001311",
        "tgn:7016833",
        "tgn:7029392"
    ],
    "tgn:id":7527958,
    "tgn:name:en":"Zunayqah, W\u0101d\u012b az",
    "tgn:placetype":[
        "aat:300379998"
    ]
},
  "bbox": [],
  "geometry": {"coordinates":[32.55,26.216667],"type":"Point"}
}