{
  "id": 7558600,
  "type": "Feature",
  "properties": {
    "tgn:hierarchy":[
        "tgn:7558600",
        "tgn:1000004",
        "tgn:7000198",
        "tgn:1001895",
        "tgn:7029392"
    ],
    "tgn:id":7558600,
    "tgn:name:en":"P\u016brna River",
    "tgn:placetype":[
        "aat:300008699"
    ]
},
  "bbox": [],
  "geometry": {"coordinates":[76.008291,21.093515],"type":"Point"}
}