{
  "id": 7247515,
  "type": "Feature",
  "properties": {
    "tgn:hierarchy":[
        "tgn:7247515",
        "tgn:7003457",
        "tgn:1000003",
        "tgn:1000063",
        "tgn:7018236",
        "tgn:7029392"
    ],
    "tgn:id":7247515,
    "tgn:name":"Drie Schouwen",
    "tgn:placetype":[
        "aat:300008347"
    ]
},
  "bbox": [],
  "geometry": {"coordinates":[4.065739,51.221154],"type":"Point"}
}