{
  "id": 7533502,
  "type": "Feature",
  "properties": {
    "tgn:hierarchy":[
        "tgn:7533502",
        "tgn:7001242",
        "tgn:7001311",
        "tgn:7016833",
        "tgn:7029392"
    ],
    "tgn:id":7533502,
    "tgn:name:en":"Little Jemsa",
    "tgn:placetype":[
        "aat:300008795"
    ]
},
  "bbox": [],
  "geometry": {"coordinates":[33.566667,27.666667],"type":"Point"}
}