{
  "id": 7256813,
  "type": "Feature",
  "properties": {
    "tgn:hierarchy":[
        "tgn:7256813",
        "tgn:7593113",
        "tgn:7016620",
        "tgn:7593112",
        "tgn:1000001",
        "tgn:7029392"
    ],
    "tgn:id":7256813,
    "tgn:name:nl":"Dorp Rinc\u00f3n",
    "tgn:placetype":[
        "aat:300008347"
    ]
},
  "bbox": [],
  "geometry": {"coordinates":[-68.333333,12.233333],"type":"Point"}
}