{
  "id": 2086495,
  "type": "Feature",
  "properties": {
    "tgn:hierarchy":[
        "tgn:2086495",
        "tgn:1002153",
        "tgn:1000001",
        "tgn:7012149",
        "tgn:7007710",
        "tgn:7029392"
    ],
    "tgn:id":2086495,
    "tgn:name":"Blanco",
    "tgn:placetype":[
        "aat:300008347",
        "aat:300387210"
    ]
},
  "bbox": [],
  "geometry": {"coordinates":[-79.35,40.7667],"type":"Point"}
}