{
  "id": 7215276,
  "type": "Feature",
  "properties": {
    "tgn:hierarchy":[
        "tgn:7215276",
        "tgn:1000003",
        "tgn:7003687",
        "tgn:7000084",
        "tgn:7029392"
    ],
    "tgn:id":7215276,
    "tgn:name":"Blauer Berg",
    "tgn:placetype":[
        "aat:300008777"
    ]
},
  "bbox": [],
  "geometry": {"coordinates":[12.133333,52.266667],"type":"Point"}
}