{
  "id": 7407637,
  "type": "Feature",
  "properties": {
    "tgn:hierarchy":[
        "tgn:7407637",
        "tgn:1000001",
        "tgn:1001893",
        "tgn:7005560",
        "tgn:7029392"
    ],
    "tgn:id":7407637,
    "tgn:name":"San Joaqu\u00edn del Monte",
    "tgn:placetype":[
        "aat:300008347"
    ]
},
  "bbox": [],
  "geometry": {"coordinates":[-100.158333,19.633333],"type":"Point"}
}