{
  "id": 7593803,
  "type": "Feature",
  "properties": {
    "tgn:hierarchy":[
        "tgn:7593803",
        "tgn:7001242",
        "tgn:1000169",
        "tgn:7029392"
    ],
    "tgn:id":7593803,
    "tgn:name":"West Pokot",
    "tgn:placetype":[
        "aat:300387064",
        "aat:300000771"
    ]
},
  "bbox": [],
  "geometry": {"coordinates":[35.25,1.75],"type":"Point"}
}