<<<<<<< HEAD
{
  "id": 2158044,
  "type": "Feature",
  "properties": {
    "tgn:hierarchy":[
        "tgn:2158044",
        "tgn:1000001",
        "tgn:7012149",
        "tgn:2000233",
        "tgn:7007158",
        "tgn:7029392"
    ],
    "tgn:id":2158044,
    "tgn:name":"Beaver Point Number Four Reservoir",
    "tgn:placetype":[
        "aat:300006191"
    ]
},
  "bbox": [],
  "geometry": {"coordinates":[-108.4667,37.5167],"type":"Point"}
}
=======
{"geometry":{"type":"Point","coordinates":[-108.466700,37.516700]},"type":"Feature","properties":{"hierarchy":["tgn:2158044","tgn:1000001","tgn:7012149","tgn:2000233","tgn:7007158","tgn:7029392"],"placetype":["aat:300006191"],"id":2158044,"name:xx":"Beaver Point Number Four Reservoir"}}
>>>>>>> 03f74aca74312dbeaf24d7e61306dd6a786dc3d0
