{
  "id": 2158044,
  "type": "Feature",
  "properties": {
    "tgn:hierarchy":[
        "tgn:2158044",
        "tgn:1000001",
        "tgn:7012149",
        "tgn:2000233",
        "tgn:7007158",
        "tgn:7029392"
    ],
    "tgn:id":2158044,
    "tgn:name":"Beaver Point Number Four Reservoir",
    "tgn:placetype":[
        "aat:300006191"
    ]
},
  "bbox": [],
  "geometry": {"coordinates":[-108.4667,37.5167],"type":"Point"}
}