{
  "id": 7456588,
  "type": "Feature",
  "properties": {
    "tgn:hierarchy":[
        "tgn:7456588",
        "tgn:5000432",
        "tgn:7002444",
        "tgn:1000003",
        "tgn:7008591",
        "tgn:7029392"
    ],
    "tgn:id":7456588,
    "tgn:name:en":"May Craig",
    "tgn:placetype":[
        "aat:300011692"
    ]
},
  "bbox": [],
  "geometry": {"coordinates":[-2.15,57.033333],"type":"Point"}
}