{
  "id": 7192119,
  "type": "Feature",
  "properties": {
    "tgn:hierarchy":[
        "tgn:7192119",
        "tgn:7003692",
        "tgn:1000003",
        "tgn:7000084",
        "tgn:7029392"
    ],
    "tgn:id":7192119,
    "tgn:name":"Falkenstein",
    "tgn:placetype":[
        "aat:300000206"
    ]
},
  "bbox": [],
  "geometry": {"coordinates":[8.383333,48.216667],"type":"Point"}
}