{
  "id": 7370580,
  "type": "Feature",
  "properties": {
    "tgn:hierarchy":[
        "tgn:7370580",
        "tgn:1001836",
        "tgn:1000001",
        "tgn:7005560",
        "tgn:7029392"
    ],
    "tgn:id":7370580,
    "tgn:name":"Hughes, Punta",
    "tgn:placetype":[
        "aat:300386846"
    ]
},
  "bbox": [],
  "geometry": {"coordinates":[-112.283333,24.766667],"type":"Point"}
}