{
  "id": 2602613,
  "type": "Feature",
  "properties": {
    "tgn:hierarchy":[
        "tgn:2602613",
        "tgn:1000001",
        "tgn:1002219",
        "tgn:7012149",
        "tgn:7007157",
        "tgn:7029392"
    ],
    "tgn:id":2602613,
    "tgn:name":"Quail Hill Mine",
    "tgn:placetype":[
        "aat:300000390"
    ]
},
  "bbox": [],
  "geometry": {"coordinates":[-120.7333,37.95],"type":"Point"}
}