<<<<<<< HEAD
{
  "id": 7021206,
  "type": "Feature",
  "properties": {
    "tgn:hierarchy":[
        "tgn:7021206",
        "tgn:1000001",
        "tgn:7012149",
        "tgn:2002274",
        "tgn:7013961",
        "tgn:7029392"
    ],
    "tgn:id":7021206,
    "tgn:name":"Meathouse Branch",
    "tgn:placetype":[
        "aat:300008699"
    ]
},
  "bbox": [],
  "geometry": {"coordinates":[-81.6833,37.4],"type":"Point"}
}
=======
{"geometry":{"type":"Point","coordinates":[-81.683300,37.400000]},"type":"Feature","properties":{"hierarchy":["tgn:7021206","tgn:1000001","tgn:7012149","tgn:2002274","tgn:7013961","tgn:7029392"],"placetype":["aat:300008699"],"id":7021206,"name:xx":"Meathouse Branch"}}
>>>>>>> 03f74aca74312dbeaf24d7e61306dd6a786dc3d0
