{
  "id": 7313176,
  "type": "Feature",
  "properties": {
    "tgn:hierarchy":[
        "tgn:7313176",
        "tgn:1001699",
        "tgn:1000049",
        "tgn:1000002",
        "tgn:7029392"
    ],
    "tgn:id":7313176,
    "tgn:name":"Lenqui, Punta",
    "tgn:placetype":[
        "aat:300386846"
    ]
},
  "bbox": [],
  "geometry": {"coordinates":[-73.666667,-41.75],"type":"Point"}
}