{
  "id": 7209716,
  "type": "Feature",
  "properties": {
    "tgn:hierarchy":[
        "tgn:7209716",
        "tgn:1000003",
        "tgn:7003689",
        "tgn:7000084",
        "tgn:7029392"
    ],
    "tgn:id":7209716,
    "tgn:name":"Berlingerode",
    "tgn:placetype":[
        "aat:300008347"
    ]
},
  "bbox": [],
  "geometry": {"coordinates":[10.233333,51.466667],"type":"Point"}
}