{
  "id": 7464704,
  "type": "Feature",
  "properties": {
    "tgn:hierarchy":[
        "tgn:7464704",
        "tgn:7002448",
        "tgn:7008700",
        "tgn:1000003",
        "tgn:7008591",
        "tgn:7029392"
    ],
    "tgn:id":7464704,
    "tgn:name:en":"Benaughlin",
    "tgn:placetype":[
        "aat:300008795"
    ]
},
  "bbox": [],
  "geometry": {"coordinates":[-7.716667,54.233333],"type":"Point"}
}