{
  "id": 7058830,
  "type": "Feature",
  "properties": {
    "tgn:hierarchy":[
        "tgn:7058830",
        "tgn:7005023",
        "tgn:1000003",
        "tgn:7003237",
        "tgn:1000080",
        "tgn:7029392"
    ],
    "tgn:id":7058830,
    "tgn:name":"Alino",
    "tgn:placetype":[
        "aat:300008347"
    ]
},
  "bbox": [],
  "geometry": {"coordinates":[9.633333,45.85],"type":"Point"}
}