{
  "id": 7265576,
  "type": "Feature",
  "properties": {
    "tgn:hierarchy":[
        "tgn:7265576",
        "tgn:1000003",
        "tgn:7003626",
        "tgn:7016845",
        "tgn:7029392"
    ],
    "tgn:id":7265576,
    "tgn:name:nl":"Huurnerveld",
    "tgn:placetype":[
        "aat:300386887"
    ]
},
  "bbox": [],
  "geometry": {"coordinates":[6.533333,52.383333],"type":"Point"}
}