{
  "id": 2204170,
  "type": "Feature",
  "properties": {
    "tgn:hierarchy":[
        "tgn:2204170",
        "tgn:1000001",
        "tgn:7012149",
        "tgn:1003018",
        "tgn:7007919",
        "tgn:7029392"
    ],
    "tgn:id":2204170,
    "tgn:name":"Buena Vista Branch",
    "tgn:placetype":[
        "aat:300008699"
    ]
},
  "bbox": [],
  "geometry": {"coordinates":[-76.65,38.05],"type":"Point"}
}