{
  "id": 2529543,
  "type": "Feature",
  "properties": {
    "tgn:hierarchy":[
        "tgn:2529543",
        "tgn:1000001",
        "tgn:7012149",
        "tgn:1002427",
        "tgn:7007826",
        "tgn:7029392"
    ],
    "tgn:id":2529543,
    "tgn:name":"Mud Lake",
    "tgn:placetype":[
        "aat:300008680"
    ]
},
  "bbox": [],
  "geometry": {"coordinates":[-94.8167,32.4667],"type":"Point"}
}