{
  "id": 7577309,
  "type": "Feature",
  "properties": {
    "tgn:hierarchy":[
        "tgn:7577309",
        "tgn:1000004",
        "tgn:7000198",
        "tgn:7031783",
        "tgn:7029392"
    ],
    "tgn:id":7577309,
    "tgn:name:en":"Loh\u0101jimi",
    "tgn:placetype":[
        "aat:300008347"
    ]
},
  "bbox": [],
  "geometry": {"coordinates":[85.132642,22.826741],"type":"Point"}
}