{
  "id": 2733615,
  "type": "Feature",
  "properties": {
    "tgn:hierarchy":[
        "tgn:2733615",
        "tgn:1000001",
        "tgn:7012149",
        "tgn:2000182",
        "tgn:7007157",
        "tgn:7029392"
    ],
    "tgn:id":2733615,
    "tgn:name":"Turnaround Wash",
    "tgn:placetype":[
        "aat:300008699"
    ]
},
  "bbox": [],
  "geometry": {"coordinates":[-114.75,33.15],"type":"Point"}
}