<<<<<<< HEAD
{
  "id": 2156896,
  "type": "Feature",
  "properties": {
    "tgn:hierarchy":[
        "tgn:2156896",
        "tgn:7006450",
        "tgn:1000001",
        "tgn:7012149",
        "tgn:2124005",
        "tgn:7029392"
    ],
    "tgn:id":2156896,
    "tgn:name":"Beaufort Basin",
    "tgn:placetype":[
        "aat:300386845"
    ]
},
  "bbox": [],
  "geometry": {"coordinates":[-162.9667,69.0167],"type":"Point"}
}
=======
{"geometry":{"type":"Point","coordinates":[-162.966700,69.016700]},"type":"Feature","properties":{"hierarchy":["tgn:2156896","tgn:7006450","tgn:1000001","tgn:7012149","tgn:2124005","tgn:7029392"],"placetype":["aat:300386845"],"id":2156896,"name:xx":"Beaufort Basin"}}
>>>>>>> 03f74aca74312dbeaf24d7e61306dd6a786dc3d0
