{
  "id": 1028691,
  "type": "Feature",
  "properties": {
    "tgn:hierarchy":[
        "tgn:1028691",
        "tgn:7002445",
        "tgn:1000003",
        "tgn:7008180",
        "tgn:7008591",
        "tgn:7029392"
    ],
    "tgn:id":1028691,
    "tgn:name:en":"Burbage",
    "tgn:placetype":[
        "aat:300008347"
    ]
},
  "bbox": [],
  "geometry": {"coordinates":[-1.666667,51.333333],"type":"Point"}
}