{
  "id": 2152975,
  "type": "Feature",
  "properties": {
    "tgn:hierarchy":[
        "tgn:2152975",
        "tgn:1000001",
        "tgn:7012149",
        "tgn:1002647",
        "tgn:7007919",
        "tgn:7029392"
    ],
    "tgn:id":2152975,
    "tgn:name":"Beach Point",
    "tgn:placetype":[
        "aat:300008850"
    ]
},
  "bbox": [],
  "geometry": {"coordinates":[-76.25,37.35],"type":"Point"}
}