{
  "id": 7308792,
  "type": "Feature",
  "properties": {
    "tgn:hierarchy":[
        "tgn:7308792",
        "tgn:1001708",
        "tgn:1000049",
        "tgn:1000002",
        "tgn:7029392"
    ],
    "tgn:id":7308792,
    "tgn:name":"Mahuida, Cerro",
    "tgn:placetype":[
        "aat:300008795"
    ]
},
  "bbox": [],
  "geometry": {"coordinates":[-70.666667,-33.05],"type":"Point"}
}