{
  "id": 2618318,
  "type": "Feature",
  "properties": {
    "tgn:hierarchy":[
        "tgn:2618318",
        "tgn:1000001",
        "tgn:7012149",
        "tgn:2002113",
        "tgn:7007827",
        "tgn:7029392"
    ],
    "tgn:id":2618318,
    "tgn:name":"Riggs Spring",
    "tgn:placetype":[
        "aat:300008697"
    ]
},
  "bbox": [],
  "geometry": {"coordinates":[-112.2333,37.45],"type":"Point"}
}