{
  "id": 2464064,
  "type": "Feature",
  "properties": {
    "tgn:hierarchy":[
        "tgn:2464064",
        "tgn:1000001",
        "tgn:7012149",
        "tgn:7007252",
        "tgn:7029392"
    ],
    "tgn:id":2464064,
    "tgn:name":"Locust Creek",
    "tgn:placetype":[
        "aat:300008706"
    ]
},
  "bbox": [],
  "geometry": {"coordinates":[-87.5833,38.0833],"type":"Point"}
}