{
  "id": 2367263,
  "type": "Feature",
  "properties": {
    "tgn:hierarchy":[
        "tgn:2367263",
        "tgn:1000001",
        "tgn:7012149",
        "tgn:2002182",
        "tgn:7007919",
        "tgn:7029392"
    ],
    "tgn:id":2367263,
    "tgn:name":"Gross Creek",
    "tgn:placetype":[
        "aat:300008706"
    ]
},
  "bbox": [],
  "geometry": {"coordinates":[-78.3833,37.2833],"type":"Point"}
}