{
  "id": 7559348,
  "type": "Feature",
  "properties": {
    "tgn:hierarchy":[
        "tgn:7559348",
        "tgn:1000004",
        "tgn:7000198",
        "tgn:7016788",
        "tgn:7029392"
    ],
    "tgn:id":7559348,
    "tgn:name:en":"S\u0101rola Khurd",
    "tgn:placetype":[
        "aat:300008347"
    ]
},
  "bbox": [],
  "geometry": {"coordinates":[76.417873,24.642529],"type":"Point"}
}