{
  "id": 7502030,
  "type": "Feature",
  "properties": {
    "tgn:hierarchy":[
        "tgn:7502030",
        "tgn:7001004",
        "tgn:1000004",
        "tgn:1000141",
        "tgn:7029392"
    ],
    "tgn:id":7502030,
    "tgn:name":"Guanghua Qiao",
    "tgn:placetype":[
        "aat:300007836"
    ]
},
  "bbox": [],
  "geometry": {"coordinates":[120.501111,22.995556],"type":"Point"}
}