{
  "id": 2367029,
  "type": "Feature",
  "properties": {
    "tgn:hierarchy":[
        "tgn:2367029",
        "tgn:1000001",
        "tgn:7012149",
        "tgn:7007157",
        "tgn:2000187",
        "tgn:7029392"
    ],
    "tgn:id":2367029,
    "tgn:name":"Grizzly Ice Pond",
    "tgn:placetype":[
        "aat:300006191"
    ]
},
  "bbox": [],
  "geometry": {"coordinates":[-120.4167,39.8333],"type":"Point"}
}