{
  "id": 7186951,
  "type": "Feature",
  "properties": {
    "tgn:hierarchy":[
        "tgn:7186951",
        "tgn:1000003",
        "tgn:7003678",
        "tgn:7000084",
        "tgn:7029392"
    ],
    "tgn:id":7186951,
    "tgn:name":"Goldbeck",
    "tgn:placetype":[
        "aat:300000206"
    ]
},
  "bbox": [],
  "geometry": {"coordinates":[8.65,51.333333],"type":"Point"}
}