{
  "id": 7044057,
  "type": "Feature",
  "properties": {
    "tgn:hierarchy":[
        "tgn:7044057",
        "tgn:7009084",
        "tgn:7004154",
        "tgn:1000003",
        "tgn:1000080",
        "tgn:7029392"
    ],
    "tgn:id":7044057,
    "tgn:name":"Capo d'Acero, Monte",
    "tgn:placetype":[
        "aat:300008795"
    ]
},
  "bbox": [],
  "geometry": {"coordinates":[13.866667,42.133333],"type":"Point"}
}