<<<<<<< HEAD
{
  "id": 2254653,
  "type": "Feature",
  "properties": {
    "tgn:hierarchy":[
        "tgn:2254653",
        "tgn:1000001",
        "tgn:2002256",
        "tgn:7012149",
        "tgn:7013961",
        "tgn:7029392"
    ],
    "tgn:id":2254653,
    "tgn:name":"Coon Knob",
    "tgn:placetype":[
        "aat:300008798"
    ]
},
  "bbox": [],
  "geometry": {"coordinates":[-80.7667,38.6],"type":"Point"}
}
=======
{"geometry":{"type":"Point","coordinates":[-80.766700,38.600000]},"type":"Feature","properties":{"hierarchy":["tgn:2254653","tgn:1000001","tgn:2002256","tgn:7012149","tgn:7013961","tgn:7029392"],"placetype":["aat:300008798"],"id":2254653,"name:xx":"Coon Knob"}}
>>>>>>> 03f74aca74312dbeaf24d7e61306dd6a786dc3d0
