{
  "id": 2540619,
  "type": "Feature",
  "properties": {
    "tgn:hierarchy":[
        "tgn:2540619",
        "tgn:1000001",
        "tgn:7012149",
        "tgn:1002670",
        "tgn:7007826",
        "tgn:7029392"
    ],
    "tgn:id":2540619,
    "tgn:name":"Newton Lakes",
    "tgn:placetype":[
        "aat:300006191"
    ]
},
  "bbox": [],
  "geometry": {"coordinates":[-96.7833,30.65],"type":"Point"}
}