{
  "id": 7571971,
  "type": "Feature",
  "properties": {
    "tgn:hierarchy":[
        "tgn:7571971",
        "tgn:1000004",
        "tgn:7000198",
        "tgn:1001894",
        "tgn:7029392"
    ],
    "tgn:id":7571971,
    "tgn:name:en":"J\u0101walkhed\u0101",
    "tgn:placetype":[
        "aat:300008347"
    ]
},
  "bbox": [],
  "geometry": {"coordinates":[78.222258,21.840519],"type":"Point"}
}