{
  "id": 7050374,
  "type": "Feature",
  "properties": {
    "tgn:hierarchy":[
        "tgn:7050374",
        "tgn:7015163",
        "tgn:1000003",
        "tgn:7003121",
        "tgn:1000080",
        "tgn:7029392"
    ],
    "tgn:id":7050374,
    "tgn:name":"Nostra Signora de Cabu Abbas",
    "tgn:placetype":[
        "aat:300007558"
    ]
},
  "bbox": [],
  "geometry": {"coordinates":[8.75,40.483333],"type":"Point"}
}