<<<<<<< HEAD
{
  "id": 7050374,
  "type": "Feature",
  "properties": {
    "tgn:hierarchy":[
        "tgn:7050374",
        "tgn:7015163",
        "tgn:1000003",
        "tgn:7003121",
        "tgn:1000080",
        "tgn:7029392"
    ],
    "tgn:id":7050374,
    "tgn:name":"Nostra Signora de Cabu Abbas",
    "tgn:placetype":[
        "aat:300007558"
    ]
},
  "bbox": [],
  "geometry": {"coordinates":[8.75,40.483333],"type":"Point"}
}
=======
{"geometry":{"type":"Point","coordinates":[8.750000,40.483333]},"type":"Feature","properties":{"hierarchy":["tgn:7050374","tgn:7015163","tgn:1000003","tgn:7003121","tgn:1000080","tgn:7029392"],"placetype":["aat:300007558"],"id":7050374,"name:xx":"Nostra Signora de Cabu Abbas"}}
>>>>>>> 03f74aca74312dbeaf24d7e61306dd6a786dc3d0
