{
  "id": 2211417,
  "type": "Feature",
  "properties": {
    "tgn:hierarchy":[
        "tgn:2211417",
        "tgn:2000453",
        "tgn:1000001",
        "tgn:7012149",
        "tgn:7007250",
        "tgn:7029392"
    ],
    "tgn:id":2211417,
    "tgn:name":"Butter Gulch",
    "tgn:placetype":[
        "aat:300008761"
    ]
},
  "bbox": [],
  "geometry": {"coordinates":[-116.4833,45.0333],"type":"Point"}
}