{
  "id": 1022355,
  "type": "Feature",
  "properties": {
    "tgn:hierarchy":[
        "tgn:1022355",
        "tgn:1001834",
        "tgn:1000047",
        "tgn:7002455",
        "tgn:1000002",
        "tgn:7029392"
    ],
    "tgn:id":1022355,
    "tgn:name":"Paratinga",
    "tgn:placetype":[
        "aat:300008347"
    ]
},
  "bbox": [],
  "geometry": {"coordinates":[-43.1833,-12.75],"type":"Point"}
}