{
  "id": 2758722,
  "type": "Feature",
  "properties": {
    "tgn:hierarchy":[
        "tgn:2758722",
        "tgn:1000001",
        "tgn:7012149",
        "tgn:7029392"
    ],
    "tgn:id":2758722,
    "tgn:name":"West Deep Creek",
    "tgn:placetype":[
        "aat:300008706"
    ]
},
  "bbox": [],
  "geometry": {"coordinates":[-113.9833,40.0167],"type":"Point"}
}