{
  "id": 2494389,
  "type": "Feature",
  "properties": {
    "tgn:hierarchy":[
        "tgn:2494389",
        "tgn:1000001",
        "tgn:7012149",
        "tgn:2000786",
        "tgn:7007255",
        "tgn:7029392"
    ],
    "tgn:id":2494389,
    "tgn:name":"Martin Creek",
    "tgn:placetype":[
        "aat:300008706"
    ]
},
  "bbox": [],
  "geometry": {"coordinates":[-87.2833,37.8167],"type":"Point"}
}