{
  "id": 2042425,
  "type": "Feature",
  "properties": {
    "tgn:hierarchy":[
        "tgn:2042425",
        "tgn:1000001",
        "tgn:2000870",
        "tgn:7012149",
        "tgn:7007256",
        "tgn:7029392"
    ],
    "tgn:id":2042425,
    "tgn:name":"Burtville",
    "tgn:placetype":[
        "aat:300387016"
    ]
},
  "bbox": [],
  "geometry": {"coordinates":[-91.1333,30.3167],"type":"Point"}
}