{
  "id": 2119730,
  "type": "Feature",
  "properties": {
    "tgn:hierarchy":[
        "tgn:2119730",
        "tgn:1000001",
        "tgn:7012149",
        "tgn:2002270",
        "tgn:7013961",
        "tgn:7029392"
    ],
    "tgn:id":2119730,
    "tgn:name":"Red Warrior",
    "tgn:placetype":[
        "aat:300008347"
    ]
},
  "bbox": [],
  "geometry": {"coordinates":[-81.45,38.05],"type":"Point"}
}