{
  "id": 2730980,
  "type": "Feature",
  "properties": {
    "tgn:hierarchy":[
        "tgn:2730980",
        "tgn:7006450",
        "tgn:2000069",
        "tgn:1000001",
        "tgn:7012149",
        "tgn:7029392"
    ],
    "tgn:id":2730980,
    "tgn:name":"Tubungaluk Creek",
    "tgn:placetype":[
        "aat:300008706"
    ]
},
  "bbox": [],
  "geometry": {"coordinates":[-161.8167,60.9333],"type":"Point"}
}