{
  "id": 7389870,
  "type": "Feature",
  "properties": {
    "tgn:hierarchy":[
        "tgn:7389870",
        "tgn:1000001",
        "tgn:1001893",
        "tgn:7005560",
        "tgn:7029392"
    ],
    "tgn:id":7389870,
    "tgn:name":"Repastito, Laguna el",
    "tgn:placetype":[
        "aat:300008680"
    ]
},
  "bbox": [],
  "geometry": {"coordinates":[-91.116667,17.25],"type":"Point"}
}