{
  "id": 7525333,
  "type": "Feature",
  "properties": {
    "tgn:hierarchy":[
        "tgn:7525333",
        "tgn:7001242",
        "tgn:7016833",
        "tgn:1001083",
        "tgn:7029392"
    ],
    "tgn:id":7525333,
    "tgn:name:en":"Dahsh\u016br",
    "tgn:placetype":[
        "aat:300008347"
    ]
},
  "bbox": [],
  "geometry": {"coordinates":[31.233333,29.75],"type":"Point"}
}