{
  "id": 2602902,
  "type": "Feature",
  "properties": {
    "tgn:hierarchy":[
        "tgn:2602902",
        "tgn:1000001",
        "tgn:7006451",
        "tgn:2000092",
        "tgn:7012149",
        "tgn:7029392"
    ],
    "tgn:id":2602902,
    "tgn:name":"Quaking Aspen Spring",
    "tgn:placetype":[
        "aat:300008697"
    ]
},
  "bbox": [],
  "geometry": {"coordinates":[-112.2667,36.3667],"type":"Point"}
}