{
  "id": 7377082,
  "type": "Feature",
  "properties": {
    "tgn:hierarchy":[
        "tgn:7377082",
        "tgn:7005583",
        "tgn:1000001",
        "tgn:7005560",
        "tgn:7029392"
    ],
    "tgn:id":7377082,
    "tgn:name":"Las An\u00edmas",
    "tgn:placetype":[
        "aat:300008347"
    ]
},
  "bbox": [],
  "geometry": {"coordinates":[-104.433333,25.133333],"type":"Point"}
}