{
  "id": 1068356,
  "type": "Feature",
  "properties": {
    "tgn:hierarchy":[
        "tgn:1068356",
        "tgn:1000004",
        "tgn:7002081",
        "tgn:1000111",
        "tgn:7029392"
    ],
    "tgn:id":1068356,
    "tgn:name":"Guabu",
    "tgn:placetype":[
        "aat:300008347"
    ]
},
  "bbox": [],
  "geometry": {"coordinates":[118.8833,32.25],"type":"Point"}
}