{
  "id": 2493636,
  "type": "Feature",
  "properties": {
    "tgn:hierarchy":[
        "tgn:2493636",
        "tgn:1000001",
        "tgn:7012149",
        "tgn:7007521",
        "tgn:7029392"
    ],
    "tgn:id":2493636,
    "tgn:name":"Marsh Lake",
    "tgn:placetype":[
        "aat:300006191"
    ]
},
  "bbox": [],
  "geometry": {"coordinates":[-96.0833,45.1667],"type":"Point"}
}