<<<<<<< HEAD
{
  "id": 2338044,
  "type": "Feature",
  "properties": {
    "tgn:hierarchy":[
        "tgn:2338044",
        "tgn:1000001",
        "tgn:1002200",
        "tgn:7012149",
        "tgn:7007240",
        "tgn:7029392"
    ],
    "tgn:id":2338044,
    "tgn:name":"Fox Lake",
    "tgn:placetype":[
        "aat:300008680"
    ]
},
  "bbox": [],
  "geometry": {"coordinates":[-80.8667,28.5833],"type":"Point"}
}
=======
{"geometry":{"type":"Point","coordinates":[-80.866700,28.583300]},"type":"Feature","properties":{"hierarchy":["tgn:2338044","tgn:1000001","tgn:1002200","tgn:7012149","tgn:7007240","tgn:7029392"],"placetype":["aat:300008680"],"id":2338044,"name:xx":"Fox Lake"}}
>>>>>>> 03f74aca74312dbeaf24d7e61306dd6a786dc3d0
