<<<<<<< HEAD
{
  "id": 7378680,
  "type": "Feature",
  "properties": {
    "tgn:hierarchy":[
        "tgn:7378680",
        "tgn:1000001",
        "tgn:7005595",
        "tgn:7005560",
        "tgn:7029392"
    ],
    "tgn:id":7378680,
    "tgn:name":"Los Capomos",
    "tgn:placetype":[
        "aat:300008347"
    ]
},
  "bbox": [],
  "geometry": {"coordinates":[-108.2,25.6],"type":"Point"}
}
=======
{"geometry":{"type":"Point","coordinates":[-108.200000,25.600000]},"type":"Feature","properties":{"hierarchy":["tgn:7378680","tgn:1000001","tgn:7005595","tgn:7005560","tgn:7029392"],"placetype":["aat:300008347"],"id":7378680,"name:xx":"Los Capomos"}}
>>>>>>> 03f74aca74312dbeaf24d7e61306dd6a786dc3d0
