{
  "id": 7034247,
  "type": "Feature",
  "properties": {
    "tgn:hierarchy":[
        "tgn:7034247",
        "tgn:1001641",
        "tgn:1000003",
        "tgn:7003121",
        "tgn:1000080",
        "tgn:7029392"
    ],
    "tgn:id":7034247,
    "tgn:name":"Berni, Secca dei",
    "tgn:placetype":[
        "aat:300387036"
    ]
},
  "bbox": [],
  "geometry": {"coordinates":[9.549167,39.112778],"type":"Point"}
}