{
  "id": 2412149,
  "type": "Feature",
  "properties": {
    "tgn:hierarchy":[
        "tgn:2412149",
        "tgn:1000001",
        "tgn:7012149",
        "tgn:1002876",
        "tgn:7007710",
        "tgn:7029392"
    ],
    "tgn:id":2412149,
    "tgn:name":"Indian Run Reservoir",
    "tgn:placetype":[
        "aat:300006191"
    ]
},
  "bbox": [],
  "geometry": {"coordinates":[-76.2333,40.65],"type":"Point"}
}