{
  "id": 2762742,
  "type": "Feature",
  "properties": {
    "tgn:hierarchy":[
        "tgn:2762742",
        "tgn:1000001",
        "tgn:2000924",
        "tgn:7012149",
        "tgn:7007515",
        "tgn:7029392"
    ],
    "tgn:id":2762742,
    "tgn:name":"Western Head",
    "tgn:placetype":[
        "aat:300008798"
    ]
},
  "bbox": [],
  "geometry": {"coordinates":[-68.75,43.8833],"type":"Point"}
}