{
  "id": 7525784,
  "type": "Feature",
  "properties": {
    "tgn:hierarchy":[
        "tgn:7525784",
        "tgn:7001242",
        "tgn:1001059",
        "tgn:7016833",
        "tgn:7029392"
    ],
    "tgn:id":7525784,
    "tgn:name:en":"Darawah",
    "tgn:placetype":[
        "aat:300008347"
    ]
},
  "bbox": [],
  "geometry": {"coordinates":[31.36559,30.866732],"type":"Point"}
}