{
  "id": 2609266,
  "type": "Feature",
  "properties": {
    "tgn:hierarchy":[
        "tgn:2609266",
        "tgn:1000001",
        "tgn:2000497",
        "tgn:7012149",
        "tgn:7007251",
        "tgn:7029392"
    ],
    "tgn:id":2609266,
    "tgn:name":"Rawson, Lake",
    "tgn:placetype":[
        "aat:300008680"
    ]
},
  "bbox": [],
  "geometry": {"coordinates":[-89.3667,41.2833],"type":"Point"}
}