<<<<<<< HEAD
{
  "id": 2259047,
  "type": "Feature",
  "properties": {
    "tgn:hierarchy":[
        "tgn:2259047",
        "tgn:1000001",
        "tgn:2002243",
        "tgn:7012149",
        "tgn:7007920",
        "tgn:7029392"
    ],
    "tgn:id":2259047,
    "tgn:name":"Cottonwood Creek",
    "tgn:placetype":[
        "aat:300008706"
    ]
},
  "bbox": [],
  "geometry": {"coordinates":[-118.6667,48.9333],"type":"Point"}
}
=======
{"geometry":{"type":"Point","coordinates":[-118.666700,48.933300]},"type":"Feature","properties":{"hierarchy":["tgn:2259047","tgn:1000001","tgn:2002243","tgn:7012149","tgn:7007920","tgn:7029392"],"placetype":["aat:300008706"],"id":2259047,"name:xx":"Cottonwood Creek"}}
>>>>>>> 03f74aca74312dbeaf24d7e61306dd6a786dc3d0
