{
  "id": 7427372,
  "type": "Feature",
  "properties": {
    "tgn:hierarchy":[
        "tgn:7427372",
        "tgn:1000001",
        "tgn:7005601",
        "tgn:7005560",
        "tgn:7029392"
    ],
    "tgn:id":7427372,
    "tgn:name":"El Tenelo",
    "tgn:placetype":[
        "aat:300008347"
    ]
},
  "bbox": [],
  "geometry": {"coordinates":[-101.766667,23.65],"type":"Point"}
}