<<<<<<< HEAD
{
  "id": 2256296,
  "type": "Feature",
  "properties": {
    "tgn:hierarchy":[
        "tgn:2256296",
        "tgn:1000001",
        "tgn:2000782",
        "tgn:7012149",
        "tgn:7007255",
        "tgn:7029392"
    ],
    "tgn:id":2256296,
    "tgn:name":"Copperhead Hollow",
    "tgn:placetype":[
        "aat:300008761"
    ]
},
  "bbox": [],
  "geometry": {"coordinates":[-83.7,37.05],"type":"Point"}
}
=======
{"geometry":{"type":"Point","coordinates":[-83.700000,37.050000]},"type":"Feature","properties":{"hierarchy":["tgn:2256296","tgn:1000001","tgn:2000782","tgn:7012149","tgn:7007255","tgn:7029392"],"placetype":["aat:300008761"],"id":2256296,"name:xx":"Copperhead Hollow"}}
>>>>>>> 03f74aca74312dbeaf24d7e61306dd6a786dc3d0
