{
  "id": 2575011,
  "type": "Feature",
  "properties": {
    "tgn:hierarchy":[
        "tgn:2575011",
        "tgn:1000001",
        "tgn:2002368",
        "tgn:7012149",
        "tgn:7007923",
        "tgn:7029392"
    ],
    "tgn:id":2575011,
    "tgn:name":"Penn Mine",
    "tgn:placetype":[
        "aat:300000390"
    ]
},
  "bbox": [],
  "geometry": {"coordinates":[-107.0333,42.1667],"type":"Point"}
}