{
  "id": 2114700,
  "type": "Feature",
  "properties": {
    "tgn:hierarchy":[
        "tgn:2114700",
        "tgn:1000001",
        "tgn:7012149",
        "tgn:2002172",
        "tgn:7007919",
        "tgn:7029392"
    ],
    "tgn:id":2114700,
    "tgn:name":"Uno",
    "tgn:placetype":[
        "aat:300008347",
        "aat:300387210"
    ]
},
  "bbox": [],
  "geometry": {"coordinates":[-78.2167,38.25],"type":"Point"}
}