{
  "id": 7315741,
  "type": "Feature",
  "properties": {
    "tgn:hierarchy":[
        "tgn:7315741",
        "tgn:1001623",
        "tgn:1000049",
        "tgn:1000002",
        "tgn:7029392"
    ],
    "tgn:id":7315741,
    "tgn:name":"Chaculay, Isla",
    "tgn:placetype":[
        "aat:300008791"
    ]
},
  "bbox": [],
  "geometry": {"coordinates":[-73.533333,-45.266667],"type":"Point"}
}