{
  "id": 2393449,
  "type": "Feature",
  "properties": {
    "tgn:hierarchy":[
        "tgn:2393449",
        "tgn:1000001",
        "tgn:7012149",
        "tgn:7007826",
        "tgn:7029392"
    ],
    "tgn:id":2393449,
    "tgn:name":"Hog Branch",
    "tgn:placetype":[
        "aat:300008699"
    ]
},
  "bbox": [],
  "geometry": {"coordinates":[-99.2167,29.8833],"type":"Point"}
}