{
  "id": 7470402,
  "type": "Feature",
  "properties": {
    "tgn:hierarchy":[
        "tgn:7470402",
        "tgn:1000004",
        "tgn:7004300",
        "tgn:1000141",
        "tgn:7029392"
    ],
    "tgn:id":7470402,
    "tgn:name":"Qitou",
    "tgn:placetype":[
        "aat:300008347"
    ]
},
  "bbox": [],
  "geometry": {"coordinates":[119.610736,23.650057],"type":"Point"}
}