{
  "id": 2276813,
  "type": "Feature",
  "properties": {
    "tgn:hierarchy":[
        "tgn:2276813",
        "tgn:1000001",
        "tgn:7012149",
        "tgn:2000234",
        "tgn:7007158",
        "tgn:7029392"
    ],
    "tgn:id":2276813,
    "tgn:name":"Davis Basin",
    "tgn:placetype":[
        "aat:300386845"
    ]
},
  "bbox": [],
  "geometry": {"coordinates":[-108.1833,38.4167],"type":"Point"}
}