<<<<<<< HEAD
{
  "id": 2152458,
  "type": "Feature",
  "properties": {
    "tgn:hierarchy":[
        "tgn:2152458",
        "tgn:1000001",
        "tgn:7012149",
        "tgn:2000882",
        "tgn:7007256",
        "tgn:7029392"
    ],
    "tgn:id":2152458,
    "tgn:name":"Bay Sevin",
    "tgn:placetype":[
        "aat:300008680"
    ]
},
  "bbox": [],
  "geometry": {"coordinates":[-90.2833,29.3333],"type":"Point"}
}
=======
{"geometry":{"type":"Point","coordinates":[-90.283300,29.333300]},"type":"Feature","properties":{"hierarchy":["tgn:2152458","tgn:1000001","tgn:7012149","tgn:2000882","tgn:7007256","tgn:7029392"],"placetype":["aat:300008680"],"id":2152458,"name:xx":"Bay Sevin"}}
>>>>>>> 03f74aca74312dbeaf24d7e61306dd6a786dc3d0
