{
  "id": 7227752,
  "type": "Feature",
  "properties": {
    "tgn:hierarchy":[
        "tgn:7227752",
        "tgn:7011170",
        "tgn:7002715",
        "tgn:1000003",
        "tgn:1000074",
        "tgn:7029392"
    ],
    "tgn:id":7227752,
    "tgn:name":"Gratin\u00ed",
    "tgn:placetype":[
        "aat:300008347"
    ]
},
  "bbox": [],
  "geometry": {"coordinates":[25.533333,41.15],"type":"Point"}
}