{
  "id": 7583226,
  "type": "Feature",
  "properties": {
    "tgn:hierarchy":[
        "tgn:7583226",
        "tgn:1000004",
        "tgn:7000198",
        "tgn:1001894",
        "tgn:7029392"
    ],
    "tgn:id":7583226,
    "tgn:name:en":"B\u0101ngchi",
    "tgn:placetype":[
        "aat:300008347"
    ]
},
  "bbox": [],
  "geometry": {"coordinates":[78.358045,24.014923],"type":"Point"}
}