<<<<<<< HEAD
{
  "id": 7485108,
  "type": "Feature",
  "properties": {
    "tgn:hierarchy":[
        "tgn:7485108",
        "tgn:1000004",
        "tgn:7467799",
        "tgn:1000141",
        "tgn:7029392"
    ],
    "tgn:id":7485108,
    "tgn:name":"Yuanding",
    "tgn:placetype":[
        "aat:300008347"
    ]
},
  "bbox": [],
  "geometry": {"coordinates":[120.4925,24.144722],"type":"Point"}
}
=======
{"geometry":{"type":"Point","coordinates":[120.492500,24.144722]},"type":"Feature","properties":{"hierarchy":["tgn:7485108","tgn:1000004","tgn:7467799","tgn:1000141","tgn:7029392"],"placetype":["aat:300008347"],"id":7485108,"name:xx":"Yuanding"}}
>>>>>>> 03f74aca74312dbeaf24d7e61306dd6a786dc3d0
