{
  "id": 7485108,
  "type": "Feature",
  "properties": {
    "tgn:hierarchy":[
        "tgn:7485108",
        "tgn:1000004",
        "tgn:7467799",
        "tgn:1000141",
        "tgn:7029392"
    ],
    "tgn:id":7485108,
    "tgn:name":"Yuanding",
    "tgn:placetype":[
        "aat:300008347"
    ]
},
  "bbox": [],
  "geometry": {"coordinates":[120.4925,24.144722],"type":"Point"}
}