{
  "id": 2241393,
  "type": "Feature",
  "properties": {
    "tgn:hierarchy":[
        "tgn:2241393",
        "tgn:7013388",
        "tgn:1000001",
        "tgn:7012149",
        "tgn:7007517",
        "tgn:7029392"
    ],
    "tgn:id":2241393,
    "tgn:name":"Clark Pond",
    "tgn:placetype":[
        "aat:300008680"
    ]
},
  "bbox": [],
  "geometry": {"coordinates":[-73.3167,42.2667],"type":"Point"}
}