{
  "id": 1004004,
  "type": "Feature",
  "properties": {
    "tgn:hierarchy":[
        "tgn:1004004",
        "tgn:7001242",
        "tgn:7016833",
        "tgn:1001110",
        "tgn:7029392"
    ],
    "tgn:id":1004004,
    "tgn:name:en":"Az Zayt\u012byah",
    "tgn:placetype":[
        "aat:300008347",
        "aat:300000745"
    ]
},
  "bbox": [],
  "geometry": {"coordinates":[32.5167,29.9667],"type":"Point"}
}