{
  "id": 1106783,
  "type": "Feature",
  "properties": {
    "tgn:hierarchy":[
        "tgn:1106783",
        "tgn:7018452",
        "tgn:1001051",
        "tgn:1000004",
        "tgn:1000144",
        "tgn:7029392"
    ],
    "tgn:id":1106783,
    "tgn:name":"Toros Dagi",
    "tgn:placetype":[
        "aat:300008795"
    ]
},
  "bbox": [],
  "geometry": {"coordinates":[34.5667,37.3833],"type":"Point"}
}