{
  "id": 7549673,
  "type": "Feature",
  "properties": {
    "tgn:hierarchy":[
        "tgn:7549673",
        "tgn:1000004",
        "tgn:7000198",
        "tgn:1001894",
        "tgn:7029392"
    ],
    "tgn:id":7549673,
    "tgn:name:en":"Bichrod",
    "tgn:placetype":[
        "aat:300008347"
    ]
},
  "bbox": [],
  "geometry": {"coordinates":[75.966667,23.366667],"type":"Point"}
}