{
  "id": 2243102,
  "type": "Feature",
  "properties": {
    "tgn:hierarchy":[
        "tgn:2243102",
        "tgn:1000001",
        "tgn:7012149",
        "tgn:2001305",
        "tgn:7007524",
        "tgn:7029392"
    ],
    "tgn:id":2243102,
    "tgn:name":"Clear Lake",
    "tgn:placetype":[
        "aat:300008680"
    ]
},
  "bbox": [],
  "geometry": {"coordinates":[-104.1333,48.65],"type":"Point"}
}