{
  "id": 7086796,
  "type": "Feature",
  "properties": {
    "tgn:hierarchy":[
        "tgn:7086796",
        "tgn:7000096",
        "tgn:1000003",
        "tgn:7000084",
        "tgn:7029392"
    ],
    "tgn:id":7086796,
    "tgn:name":"Weinberge",
    "tgn:placetype":[
        "aat:300008347"
    ]
},
  "bbox": [],
  "geometry": {"coordinates":[14.066667,52.383333],"type":"Point"}
}