{
  "id": 2358216,
  "type": "Feature",
  "properties": {
    "tgn:hierarchy":[
        "tgn:2358216",
        "tgn:1000001",
        "tgn:7012149",
        "tgn:2001108",
        "tgn:7007522",
        "tgn:7029392"
    ],
    "tgn:id":2358216,
    "tgn:name":"Grand Bayou",
    "tgn:placetype":[
        "aat:300008699"
    ]
},
  "bbox": [],
  "geometry": {"coordinates":[-89.3833,30.2667],"type":"Point"}
}