{
  "id": 1127564,
  "type": "Feature",
  "properties": {
    "tgn:hierarchy":[
        "tgn:1127564",
        "tgn:7016674",
        "tgn:1000004",
        "tgn:1000120",
        "tgn:7029392"
    ],
    "tgn:id":1127564,
    "tgn:name":"Nakatsu-gawa",
    "tgn:placetype":[
        "aat:300008707"
    ]
},
  "bbox": [],
  "geometry": {"coordinates":[138.6333,37.0167],"type":"Point"}
}