<<<<<<< HEAD
{
  "id": 2769625,
  "type": "Feature",
  "properties": {
    "tgn:hierarchy":[
        "tgn:2769625",
        "tgn:7006450",
        "tgn:1000001",
        "tgn:7012149",
        "tgn:2000089",
        "tgn:7029392"
    ],
    "tgn:id":2769625,
    "tgn:name":"Wiehl Mountain",
    "tgn:placetype":[
        "aat:300008798"
    ]
},
  "bbox": [],
  "geometry": {"coordinates":[-149.5833,67.6],"type":"Point"}
}
=======
{"geometry":{"type":"Point","coordinates":[-149.583300,67.600000]},"type":"Feature","properties":{"hierarchy":["tgn:2769625","tgn:7006450","tgn:1000001","tgn:7012149","tgn:2000089","tgn:7029392"],"placetype":["aat:300008798"],"id":2769625,"name:xx":"Wiehl Mountain"}}
>>>>>>> 03f74aca74312dbeaf24d7e61306dd6a786dc3d0
