{
  "id": 7052647,
  "type": "Feature",
  "properties": {
    "tgn:hierarchy":[
        "tgn:7052647",
        "tgn:7005023",
        "tgn:1000003",
        "tgn:7003237",
        "tgn:1000080",
        "tgn:7029392"
    ],
    "tgn:id":7052647,
    "tgn:name":"Peghera",
    "tgn:placetype":[
        "aat:300008347"
    ]
},
  "bbox": [],
  "geometry": {"coordinates":[9.55,45.866667],"type":"Point"}
}