{
  "id": 2238997,
  "type": "Feature",
  "properties": {
    "tgn:hierarchy":[
        "tgn:2238997",
        "tgn:1000001",
        "tgn:2000506",
        "tgn:7012149",
        "tgn:7007251",
        "tgn:7029392"
    ],
    "tgn:id":2238997,
    "tgn:name":"Christopher Reservoir",
    "tgn:placetype":[
        "aat:300006191"
    ]
},
  "bbox": [],
  "geometry": {"coordinates":[-89.0667,37.9833],"type":"Point"}
}