{
  "id": 7033991,
  "type": "Feature",
  "properties": {
    "tgn:hierarchy":[
        "tgn:7033991",
        "tgn:1001641",
        "tgn:1000003",
        "tgn:7003121",
        "tgn:1000080",
        "tgn:7029392"
    ],
    "tgn:id":7033991,
    "tgn:name":"Torre Sant'Elia",
    "tgn:placetype":[
        "aat:300004847"
    ]
},
  "bbox": [],
  "geometry": {"coordinates":[9.164167,39.1875],"type":"Point"}
}