<<<<<<< HEAD
{
  "id": 7371660,
  "type": "Feature",
  "properties": {
    "tgn:hierarchy":[
        "tgn:7371660",
        "tgn:1000001",
        "tgn:7005589",
        "tgn:7005560",
        "tgn:7029392"
    ],
    "tgn:id":7371660,
    "tgn:name":"La Brisa",
    "tgn:placetype":[
        "aat:300008347"
    ]
},
  "bbox": [],
  "geometry": {"coordinates":[-98.783333,25.533333],"type":"Point"}
}
=======
{"geometry":{"type":"Point","coordinates":[-98.783333,25.533333]},"type":"Feature","properties":{"hierarchy":["tgn:7371660","tgn:1000001","tgn:7005589","tgn:7005560","tgn:7029392"],"placetype":["aat:300008347"],"id":7371660,"name:xx":"La Brisa"}}
>>>>>>> 03f74aca74312dbeaf24d7e61306dd6a786dc3d0
