{
  "id": 2201982,
  "type": "Feature",
  "properties": {
    "tgn:hierarchy":[
        "tgn:2201982",
        "tgn:1000001",
        "tgn:7012149",
        "tgn:7007708",
        "tgn:7029392"
    ],
    "tgn:id":2201982,
    "tgn:name":"Buck Hollow Creek",
    "tgn:placetype":[
        "aat:300008706"
    ]
},
  "bbox": [],
  "geometry": {"coordinates":[-121.0167,45.25],"type":"Point"}
}