{
  "id": 7180524,
  "type": "Feature",
  "properties": {
    "tgn:hierarchy":[
        "tgn:7180524",
        "tgn:1000003",
        "tgn:7003682",
        "tgn:7000084",
        "tgn:7029392"
    ],
    "tgn:id":7180524,
    "tgn:name":"Gauersheim",
    "tgn:placetype":[
        "aat:300008347"
    ]
},
  "bbox": [],
  "geometry": {"coordinates":[8.071944,49.659722],"type":"Point"}
}