{
  "id": 2702618,
  "type": "Feature",
  "properties": {
    "tgn:hierarchy":[
        "tgn:2702618",
        "tgn:1000001",
        "tgn:2002102",
        "tgn:7012149",
        "tgn:7007827",
        "tgn:7029392"
    ],
    "tgn:id":2702618,
    "tgn:name":"Sulphur Creek",
    "tgn:placetype":[
        "aat:300008706"
    ]
},
  "bbox": [],
  "geometry": {"coordinates":[-112.1833,41.6333],"type":"Point"}
}