{
  "id": 2592149,
  "type": "Feature",
  "properties": {
    "tgn:hierarchy":[
        "tgn:2592149",
        "tgn:1000001",
        "tgn:7012149",
        "tgn:2002379",
        "tgn:7007923",
        "tgn:7029392"
    ],
    "tgn:id":2592149,
    "tgn:name":"Ponuntpa Springs",
    "tgn:placetype":[
        "aat:300008697"
    ]
},
  "bbox": [],
  "geometry": {"coordinates":[-110.2833,44.6667],"type":"Point"}
}