{
  "id": 2578952,
  "type": "Feature",
  "properties": {
    "tgn:hierarchy":[
        "tgn:2578952",
        "tgn:1000001",
        "tgn:7012149",
        "tgn:2002193",
        "tgn:7007919",
        "tgn:7029392"
    ],
    "tgn:id":2578952,
    "tgn:name":"Phils Arm Run",
    "tgn:placetype":[
        "aat:300008699"
    ]
},
  "bbox": [],
  "geometry": {"coordinates":[-78.2167,38.7667],"type":"Point"}
}