{
  "id": 7504858,
  "type": "Feature",
  "properties": {
    "tgn:hierarchy":[
        "tgn:7504858",
        "tgn:1009227",
        "tgn:7001866",
        "tgn:1000226",
        "tgn:1000006",
        "tgn:7029392"
    ],
    "tgn:id":7504858,
    "tgn:name:en":"Whitewash Head",
    "tgn:placetype":[
        "aat:300386846"
    ]
},
  "bbox": [],
  "geometry": {"coordinates":[172.776389,-43.573611],"type":"Point"}
}