<<<<<<< HEAD
{
  "id": 7053728,
  "type": "Feature",
  "properties": {
    "tgn:hierarchy":[
        "tgn:7053728",
        "tgn:1003505",
        "tgn:1000003",
        "tgn:7002993",
        "tgn:1000080",
        "tgn:7029392"
    ],
    "tgn:id":7053728,
    "tgn:name":"Macello",
    "tgn:placetype":[
        "aat:300008347"
    ]
},
  "bbox": [],
  "geometry": {"coordinates":[13.8,45.633333],"type":"Point"}
}
=======
{"geometry":{"type":"Point","coordinates":[13.800000,45.633333]},"type":"Feature","properties":{"hierarchy":["tgn:7053728","tgn:1003505","tgn:1000003","tgn:7002993","tgn:1000080","tgn:7029392"],"placetype":["aat:300008347"],"id":7053728,"name:xx":"Macello"}}
>>>>>>> 03f74aca74312dbeaf24d7e61306dd6a786dc3d0
