{
  "id": 2219760,
  "type": "Feature",
  "properties": {
    "tgn:hierarchy":[
        "tgn:2219760",
        "tgn:7002659",
        "tgn:1000001",
        "tgn:7012149",
        "tgn:2000050",
        "tgn:7029392"
    ],
    "tgn:id":2219760,
    "tgn:name":"Cantelous Hill",
    "tgn:placetype":[
        "aat:300008798"
    ]
},
  "bbox": [],
  "geometry": {"coordinates":[-86.45,32.3333],"type":"Point"}
}