{
  "id": 2569249,
  "type": "Feature",
  "properties": {
    "tgn:hierarchy":[
        "tgn:2569249",
        "tgn:1000001",
        "tgn:7012149",
        "tgn:7007520",
        "tgn:7029392"
    ],
    "tgn:id":2569249,
    "tgn:name":"Parks Drain",
    "tgn:placetype":[
        "aat:300008699"
    ]
},
  "bbox": [],
  "geometry": {"coordinates":[-83.5833,42.3167],"type":"Point"}
}