{
  "id": 7229858,
  "type": "Feature",
  "properties": {
    "tgn:hierarchy":[
        "tgn:7229858",
        "tgn:4003773",
        "tgn:7001395",
        "tgn:1000003",
        "tgn:1000074",
        "tgn:7029392"
    ],
    "tgn:id":7229858,
    "tgn:name":"Kapnokh\u00f3rion",
    "tgn:placetype":[
        "aat:300008347"
    ]
},
  "bbox": [],
  "geometry": {"coordinates":[22.233333,38.866667],"type":"Point"}
}