{
  "id": 2353564,
  "type": "Feature",
  "properties": {
    "tgn:hierarchy":[
        "tgn:2353564",
        "tgn:1000001",
        "tgn:7012149",
        "tgn:2002010",
        "tgn:7007826",
        "tgn:7029392"
    ],
    "tgn:id":2353564,
    "tgn:name":"Gold Hill",
    "tgn:placetype":[
        "aat:300008798"
    ]
},
  "bbox": [],
  "geometry": {"coordinates":[-104.05,31.0333],"type":"Point"}
}