{
  "id": 2170497,
  "type": "Feature",
  "properties": {
    "tgn:hierarchy":[
        "tgn:2170497",
        "tgn:1000001",
        "tgn:7012149",
        "tgn:2000803",
        "tgn:7007255",
        "tgn:7029392"
    ],
    "tgn:id":2170497,
    "tgn:name":"Big Round Mountain",
    "tgn:placetype":[
        "aat:300008798"
    ]
},
  "bbox": [],
  "geometry": {"coordinates":[-83.85,37.9333],"type":"Point"}
}