{
  "id": 2189151,
  "type": "Feature",
  "properties": {
    "tgn:hierarchy":[
        "tgn:2189151",
        "tgn:1000001",
        "tgn:7012149",
        "tgn:2002119",
        "tgn:7007827",
        "tgn:7029392"
    ],
    "tgn:id":2189151,
    "tgn:name":"Boundary Butte Mesa",
    "tgn:placetype":[
        "aat:300008798"
    ]
},
  "bbox": [],
  "geometry": {"coordinates":[-109.4667,37.0333],"type":"Point"}
}