{
  "id": 7508076,
  "type": "Feature",
  "properties": {
    "tgn:hierarchy":[
        "tgn:7508076",
        "tgn:7000508",
        "tgn:1008380",
        "tgn:1000226",
        "tgn:1000006",
        "tgn:7029392"
    ],
    "tgn:id":7508076,
    "tgn:name:en":"Parnell",
    "tgn:placetype":[
        "aat:300000745"
    ]
},
  "bbox": [],
  "geometry": {"coordinates":[174.783333,-36.866667],"type":"Point"}
}