{
  "id": 2334699,
  "type": "Feature",
  "properties": {
    "tgn:hierarchy":[
        "tgn:2334699",
        "tgn:1000001",
        "tgn:7012149",
        "tgn:7007523",
        "tgn:7029392"
    ],
    "tgn:id":2334699,
    "tgn:name":"Fork Creek",
    "tgn:placetype":[
        "aat:300008706"
    ]
},
  "bbox": [],
  "geometry": {"coordinates":[-91.45,38.5833],"type":"Point"}
}