<<<<<<< HEAD
{
  "id": 2334699,
  "type": "Feature",
  "properties": {
    "tgn:hierarchy":[
        "tgn:2334699",
        "tgn:1000001",
        "tgn:7012149",
        "tgn:7007523",
        "tgn:7029392"
    ],
    "tgn:id":2334699,
    "tgn:name":"Fork Creek",
    "tgn:placetype":[
        "aat:300008706"
    ]
},
  "bbox": [],
  "geometry": {"coordinates":[-91.45,38.5833],"type":"Point"}
}
=======
{"geometry":{"type":"Point","coordinates":[-91.450000,38.583300]},"type":"Feature","properties":{"hierarchy":["tgn:2334699","tgn:1000001","tgn:7012149","tgn:7007523","tgn:7029392"],"placetype":["aat:300008706"],"id":2334699,"name:xx":"Fork Creek"}}
>>>>>>> 03f74aca74312dbeaf24d7e61306dd6a786dc3d0
