{
  "id": 7290133,
  "type": "Feature",
  "properties": {
    "tgn:hierarchy":[
        "tgn:7290133",
        "tgn:1001623",
        "tgn:1000049",
        "tgn:1000002",
        "tgn:7029392"
    ],
    "tgn:id":7290133,
    "tgn:name":"Dyer, Cabo",
    "tgn:placetype":[
        "aat:300386846"
    ]
},
  "bbox": [],
  "geometry": {"coordinates":[-75.583333,-48.083333],"type":"Point"}
}