<<<<<<< HEAD
{
  "id": 2152587,
  "type": "Feature",
  "properties": {
    "tgn:hierarchy":[
        "tgn:2152587",
        "tgn:1000001",
        "tgn:7012149",
        "tgn:2000488",
        "tgn:7007250",
        "tgn:7029392"
    ],
    "tgn:id":2152587,
    "tgn:name":"Bayha Island",
    "tgn:placetype":[
        "aat:300008791"
    ]
},
  "bbox": [],
  "geometry": {"coordinates":[-116.6167,43.3667],"type":"Point"}
}
=======
{"geometry":{"type":"Point","coordinates":[-116.616700,43.366700]},"type":"Feature","properties":{"hierarchy":["tgn:2152587","tgn:1000001","tgn:7012149","tgn:2000488","tgn:7007250","tgn:7029392"],"placetype":["aat:300008791"],"id":2152587,"name:xx":"Bayha Island"}}
>>>>>>> 03f74aca74312dbeaf24d7e61306dd6a786dc3d0
