{
  "id": 7209981,
  "type": "Feature",
  "properties": {
    "tgn:hierarchy":[
        "tgn:7209981",
        "tgn:7003692",
        "tgn:1000003",
        "tgn:7000084",
        "tgn:7029392"
    ],
    "tgn:id":7209981,
    "tgn:name":"Benitzenhof",
    "tgn:placetype":[
        "aat:300000206"
    ]
},
  "bbox": [],
  "geometry": {"coordinates":[8.15,47.933333],"type":"Point"}
}