{
  "id": 1017586,
  "type": "Feature",
  "properties": {
    "tgn:hierarchy":[
        "tgn:1017586",
        "tgn:1000001",
        "tgn:7005594",
        "tgn:7005560",
        "tgn:7029392"
    ],
    "tgn:id":1017586,
    "tgn:name":"Huizache",
    "tgn:placetype":[
        "aat:300008347"
    ]
},
  "bbox": [],
  "geometry": {"coordinates":[-100.416667,22.916667],"type":"Point"}
}