{
  "id": 2452646,
  "type": "Feature",
  "properties": {
    "tgn:hierarchy":[
        "tgn:2452646",
        "tgn:1000001",
        "tgn:7012149",
        "tgn:2000476",
        "tgn:7007250",
        "tgn:7029392"
    ],
    "tgn:id":2452646,
    "tgn:name":"Little Buck Creek",
    "tgn:placetype":[
        "aat:300008706"
    ]
},
  "bbox": [],
  "geometry": {"coordinates":[-115.5833,45.2333],"type":"Point"}
}