<<<<<<< HEAD
{
  "id": 7478225,
  "type": "Feature",
  "properties": {
    "tgn:hierarchy":[
        "tgn:7478225",
        "tgn:1000004",
        "tgn:7001013",
        "tgn:1000141",
        "tgn:7029392"
    ],
    "tgn:id":7478225,
    "tgn:name":"Daniuchou",
    "tgn:placetype":[
        "aat:300008347"
    ]
},
  "bbox": [],
  "geometry": {"coordinates":[121.224679,25.057203],"type":"Point"}
}
=======
{"geometry":{"type":"Point","coordinates":[121.224679,25.057203]},"type":"Feature","properties":{"hierarchy":["tgn:7478225","tgn:1000004","tgn:7001013","tgn:1000141","tgn:7029392"],"placetype":["aat:300008347"],"id":7478225,"name:xx":"Daniuchou"}}
>>>>>>> 03f74aca74312dbeaf24d7e61306dd6a786dc3d0
