<<<<<<< HEAD
{
  "id": 2252284,
  "type": "Feature",
  "properties": {
    "tgn:hierarchy":[
        "tgn:2252284",
        "tgn:1000001",
        "tgn:7012149",
        "tgn:2001911",
        "tgn:7007825",
        "tgn:7029392"
    ],
    "tgn:id":2252284,
    "tgn:name":"Confederate Glen Estates",
    "tgn:placetype":[
        "aat:300008347"
    ]
},
  "bbox": [],
  "geometry": {"coordinates":[-86.45,35.8667],"type":"Point"}
}
=======
{"geometry":{"type":"Point","coordinates":[-86.450000,35.866700]},"type":"Feature","properties":{"hierarchy":["tgn:2252284","tgn:1000001","tgn:7012149","tgn:2001911","tgn:7007825","tgn:7029392"],"placetype":["aat:300008347"],"id":2252284,"name:xx":"Confederate Glen Estates"}}
>>>>>>> 03f74aca74312dbeaf24d7e61306dd6a786dc3d0
