<<<<<<< HEAD
{
  "id": 2760205,
  "type": "Feature",
  "properties": {
    "tgn:hierarchy":[
        "tgn:2760205",
        "tgn:1000001",
        "tgn:7012149",
        "tgn:2001457",
        "tgn:7007566",
        "tgn:7029392"
    ],
    "tgn:id":2760205,
    "tgn:name":"West Fork Red River",
    "tgn:placetype":[
        "aat:300008707"
    ]
},
  "bbox": [],
  "geometry": {"coordinates":[-105.4333,36.6167],"type":"Point"}
}
=======
{"geometry":{"type":"Point","coordinates":[-105.433300,36.616700]},"type":"Feature","properties":{"hierarchy":["tgn:2760205","tgn:1000001","tgn:7012149","tgn:2001457","tgn:7007566","tgn:7029392"],"placetype":["aat:300008707"],"id":2760205,"name:xx":"West Fork Red River"}}
>>>>>>> 03f74aca74312dbeaf24d7e61306dd6a786dc3d0
