{
  "id": 7480192,
  "type": "Feature",
  "properties": {
    "tgn:hierarchy":[
        "tgn:7480192",
        "tgn:1000004",
        "tgn:7001013",
        "tgn:1000141",
        "tgn:7029392"
    ],
    "tgn:id":7480192,
    "tgn:name":"Tudigongkeng Shan",
    "tgn:placetype":[
        "aat:300008777"
    ]
},
  "bbox": [],
  "geometry": {"coordinates":[121.311519,25.070995],"type":"Point"}
}