{
  "id": 7154216,
  "type": "Feature",
  "properties": {
    "tgn:hierarchy":[
        "tgn:7154216",
        "tgn:1000003",
        "tgn:7000094",
        "tgn:7000084",
        "tgn:7029392"
    ],
    "tgn:id":7154216,
    "tgn:name":"Johannisberg",
    "tgn:placetype":[
        "aat:300000206"
    ]
},
  "bbox": [],
  "geometry": {"coordinates":[14.233333,53.45],"type":"Point"}
}