{
  "id": 7566455,
  "type": "Feature",
  "properties": {
    "tgn:hierarchy":[
        "tgn:7566455",
        "tgn:1000004",
        "tgn:7000198",
        "tgn:7016722",
        "tgn:7029392"
    ],
    "tgn:id":7566455,
    "tgn:name:en":"Birhan Minor",
    "tgn:placetype":[
        "aat:300006075"
    ]
},
  "bbox": [],
  "geometry": {"coordinates":[79.908132,26.708455],"type":"Point"}
}