{
  "id": 7542168,
  "type": "Feature",
  "properties": {
    "tgn:hierarchy":[
        "tgn:7542168",
        "tgn:7001242",
        "tgn:7016833",
        "tgn:7029392"
    ],
    "tgn:id":7542168,
    "tgn:name":"Thum\u0101\u012bl, W\u0101d\u012b ath",
    "tgn:placetype":[
        "aat:300379998"
    ]
},
  "bbox": [],
  "geometry": {"coordinates":[34.586944,27.950556],"type":"Point"}
}