<<<<<<< HEAD
{
  "id": 2255781,
  "type": "Feature",
  "properties": {
    "tgn:hierarchy":[
        "tgn:2255781",
        "tgn:1000001",
        "tgn:7012149",
        "tgn:7007526",
        "tgn:7029392"
    ],
    "tgn:id":2255781,
    "tgn:name":"Copper Canyon",
    "tgn:placetype":[
        "aat:300008761"
    ]
},
  "bbox": [],
  "geometry": {"coordinates":[-115.9833,40.3],"type":"Point"}
}
=======
{"geometry":{"type":"Point","coordinates":[-115.983300,40.300000]},"type":"Feature","properties":{"hierarchy":["tgn:2255781","tgn:1000001","tgn:7012149","tgn:7007526","tgn:7029392"],"placetype":["aat:300008761"],"id":2255781,"name:xx":"Copper Canyon"}}
>>>>>>> 03f74aca74312dbeaf24d7e61306dd6a786dc3d0
