{
  "id": 2463155,
  "type": "Feature",
  "properties": {
    "tgn:hierarchy":[
        "tgn:2463155",
        "tgn:1000001",
        "tgn:7012149",
        "tgn:7007157",
        "tgn:1002656",
        "tgn:7029392"
    ],
    "tgn:id":2463155,
    "tgn:name":"Livingston Drain",
    "tgn:placetype":[
        "aat:300006075"
    ]
},
  "bbox": [],
  "geometry": {"coordinates":[-120.7333,37.3167],"type":"Point"}
}