<<<<<<< HEAD
{
  "id": 7177205,
  "type": "Feature",
  "properties": {
    "tgn:hierarchy":[
        "tgn:7177205",
        "tgn:7003692",
        "tgn:1000003",
        "tgn:7000084",
        "tgn:7029392"
    ],
    "tgn:id":7177205,
    "tgn:name":"Hagendorn",
    "tgn:placetype":[
        "aat:300000206"
    ]
},
  "bbox": [],
  "geometry": {"coordinates":[9.1,47.883333],"type":"Point"}
}
=======
{"geometry":{"type":"Point","coordinates":[9.100000,47.883333]},"type":"Feature","properties":{"hierarchy":["tgn:7177205","tgn:7003692","tgn:1000003","tgn:7000084","tgn:7029392"],"placetype":["aat:300000206"],"id":7177205,"name:xx":"Hagendorn"}}
>>>>>>> 03f74aca74312dbeaf24d7e61306dd6a786dc3d0
