{
  "id": 2407756,
  "type": "Feature",
  "properties": {
    "tgn:hierarchy":[
        "tgn:2407756",
        "tgn:1000001",
        "tgn:7012149",
        "tgn:2002070",
        "tgn:7007826",
        "tgn:7029392"
    ],
    "tgn:id":2407756,
    "tgn:name":"Hurricane Bluff Waterhole",
    "tgn:placetype":[
        "aat:300008680"
    ]
},
  "bbox": [],
  "geometry": {"coordinates":[-100.3167,30.85],"type":"Point"}
}