{
  "id": 2255617,
  "type": "Feature",
  "properties": {
    "tgn:hierarchy":[
        "tgn:2255617",
        "tgn:2002142",
        "tgn:1000001",
        "tgn:7012149",
        "tgn:7007919",
        "tgn:7029392"
    ],
    "tgn:id":2255617,
    "tgn:name":"Copelands Tetons",
    "tgn:placetype":[
        "aat:300008798"
    ]
},
  "bbox": [],
  "geometry": {"coordinates":[-78.8833,38.0167],"type":"Point"}
}