<<<<<<< HEAD
{
  "id": 2255617,
  "type": "Feature",
  "properties": {
    "tgn:hierarchy":[
        "tgn:2255617",
        "tgn:2002142",
        "tgn:1000001",
        "tgn:7012149",
        "tgn:7007919",
        "tgn:7029392"
    ],
    "tgn:id":2255617,
    "tgn:name":"Copelands Tetons",
    "tgn:placetype":[
        "aat:300008798"
    ]
},
  "bbox": [],
  "geometry": {"coordinates":[-78.8833,38.0167],"type":"Point"}
}
=======
{"geometry":{"type":"Point","coordinates":[-78.883300,38.016700]},"type":"Feature","properties":{"hierarchy":["tgn:2255617","tgn:2002142","tgn:1000001","tgn:7012149","tgn:7007919","tgn:7029392"],"placetype":["aat:300008798"],"id":2255617,"name:xx":"Copelands Tetons"}}
>>>>>>> 03f74aca74312dbeaf24d7e61306dd6a786dc3d0
