{
  "id": 7012244,
  "type": "Feature",
  "properties": {
    "tgn:hierarchy":[
        "tgn:7012244",
        "tgn:7011642",
        "tgn:1000004",
        "tgn:7006659",
        "tgn:7029392"
    ],
    "tgn:id":7012244,
    "tgn:name":"Merv",
    "tgn:placetype":[
        "aat:300008347",
        "aat:300000810",
        "aat:300167671",
        "aat:300387272",
        "aat:300263063"
    ]
},
  "bbox": [],
  "geometry": {"coordinates":[62.192,37.662],"type":"Point"}
}