{
  "id": 2146705,
  "type": "Feature",
  "properties": {
    "tgn:hierarchy":[
        "tgn:2146705",
        "tgn:1000001",
        "tgn:7012149",
        "tgn:2001274",
        "tgn:7007524",
        "tgn:7029392"
    ],
    "tgn:id":2146705,
    "tgn:name":"Baney Lake",
    "tgn:placetype":[
        "aat:300008680"
    ]
},
  "bbox": [],
  "geometry": {"coordinates":[-114.4333,48.3167],"type":"Point"}
}