{
  "id": 7564373,
  "type": "Feature",
  "properties": {
    "tgn:hierarchy":[
        "tgn:7564373",
        "tgn:1000004",
        "tgn:7000198",
        "tgn:1001894",
        "tgn:7029392"
    ],
    "tgn:id":7564373,
    "tgn:name:en":"Pipariya",
    "tgn:placetype":[
        "aat:300008347"
    ]
},
  "bbox": [],
  "geometry": {"coordinates":[79.332859,24.76303],"type":"Point"}
}