{
  "id": 7401000,
  "type": "Feature",
  "properties": {
    "tgn:hierarchy":[
        "tgn:7401000",
        "tgn:1000001",
        "tgn:7005599",
        "tgn:7005560",
        "tgn:7029392"
    ],
    "tgn:id":7401000,
    "tgn:name":"Emiliano Zapata",
    "tgn:placetype":[
        "aat:300008347"
    ]
},
  "bbox": [],
  "geometry": {"coordinates":[-97.223611,20.825],"type":"Point"}
}