{
  "id": 7330687,
  "type": "Feature",
  "properties": {
    "tgn:hierarchy":[
        "tgn:7330687",
        "tgn:7008912",
        "tgn:7030216",
        "tgn:1000003",
        "tgn:1000095",
        "tgn:7029392"
    ],
    "tgn:id":7330687,
    "tgn:name":"Grosa, Sierra",
    "tgn:placetype":[
        "aat:300266640"
    ]
},
  "bbox": [],
  "geometry": {"coordinates":[0.55,41.433333],"type":"Point"}
}