{
  "id": 7194654,
  "type": "Feature",
  "properties": {
    "tgn:hierarchy":[
        "tgn:7194654",
        "tgn:1000003",
        "tgn:7003678",
        "tgn:7000084",
        "tgn:7029392"
    ],
    "tgn:id":7194654,
    "tgn:name":"Dornholzhausen",
    "tgn:placetype":[
        "aat:300008347"
    ]
},
  "bbox": [],
  "geometry": {"coordinates":[8.583333,50.25],"type":"Point"}
}