{
  "id": 7415237,
  "type": "Feature",
  "properties": {
    "tgn:hierarchy":[
        "tgn:7415237",
        "tgn:1000001",
        "tgn:7005591",
        "tgn:7005560",
        "tgn:7029392"
    ],
    "tgn:id":7415237,
    "tgn:name:es":"Arroyo S\u00fachil",
    "tgn:placetype":[
        "aat:300008347"
    ]
},
  "bbox": [],
  "geometry": {"coordinates":[-96.231667,15.859167],"type":"Point"}
}