{
  "id": 2447006,
  "type": "Feature",
  "properties": {
    "tgn:hierarchy":[
        "tgn:2447006",
        "tgn:1000001",
        "tgn:7012149",
        "tgn:2001507",
        "tgn:7007709",
        "tgn:7029392"
    ],
    "tgn:id":2447006,
    "tgn:name":"Liberty Hill",
    "tgn:placetype":[
        "aat:300008347"
    ]
},
  "bbox": [],
  "geometry": {"coordinates":[-80.9667,35.85],"type":"Point"}
}