{
  "id": 2133856,
  "type": "Feature",
  "properties": {
    "tgn:hierarchy":[
        "tgn:2133856",
        "tgn:1000001",
        "tgn:7012149",
        "tgn:2001274",
        "tgn:7007524",
        "tgn:7029392"
    ],
    "tgn:id":2133856,
    "tgn:name":"Angel Point",
    "tgn:placetype":[
        "aat:300008850"
    ]
},
  "bbox": [],
  "geometry": {"coordinates":[-114.1667,47.9833],"type":"Point"}
}