{
  "id": 2767096,
  "type": "Feature",
  "properties": {
    "tgn:hierarchy":[
        "tgn:2767096",
        "tgn:1000001",
        "tgn:7012149",
        "tgn:2002175",
        "tgn:7007919",
        "tgn:7029392"
    ],
    "tgn:id":2767096,
    "tgn:name":"White Rock",
    "tgn:placetype":[
        "aat:300008347"
    ]
},
  "bbox": [],
  "geometry": {"coordinates":[-79.05,37.8833],"type":"Point"}
}