<<<<<<< HEAD
{
  "id": 2767096,
  "type": "Feature",
  "properties": {
    "tgn:hierarchy":[
        "tgn:2767096",
        "tgn:1000001",
        "tgn:7012149",
        "tgn:2002175",
        "tgn:7007919",
        "tgn:7029392"
    ],
    "tgn:id":2767096,
    "tgn:name":"White Rock",
    "tgn:placetype":[
        "aat:300008347"
    ]
},
  "bbox": [],
  "geometry": {"coordinates":[-79.05,37.8833],"type":"Point"}
}
=======
{"geometry":{"type":"Point","coordinates":[-79.050000,37.883300]},"type":"Feature","properties":{"hierarchy":["tgn:2767096","tgn:1000001","tgn:7012149","tgn:2002175","tgn:7007919","tgn:7029392"],"placetype":["aat:300008347"],"id":2767096,"name:xx":"White Rock"}}
>>>>>>> 03f74aca74312dbeaf24d7e61306dd6a786dc3d0
