{
  "id": 7268706,
  "type": "Feature",
  "properties": {
    "tgn:concordances":{
        "gn:id":"2748574"
    },
    "tgn:hierarchy":[
        "tgn:7268706",
        "tgn:1000003",
        "tgn:7003635",
        "tgn:7016845",
        "tgn:7029392"
    ],
    "tgn:id":7268706,
    "tgn:name:nl":"Pitteperk",
    "tgn:placetype":[
        "aat:300008347"
    ]
},
  "bbox": [],
  "geometry": {"coordinates":[3.616667,51.566667],"type":"Point"}
}