{
  "id": 2349261,
  "type": "Feature",
  "properties": {
    "tgn:hierarchy":[
        "tgn:2349261",
        "tgn:1000001",
        "tgn:7012149",
        "tgn:2001140",
        "tgn:7007522",
        "tgn:7029392"
    ],
    "tgn:id":2349261,
    "tgn:name":"Gilberts Lake",
    "tgn:placetype":[
        "aat:300006191"
    ]
},
  "bbox": [],
  "geometry": {"coordinates":[-89.45,30.6667],"type":"Point"}
}