{
  "id": 2195397,
  "type": "Feature",
  "properties": {
    "tgn:hierarchy":[
        "tgn:2195397",
        "tgn:7002659",
        "tgn:1000001",
        "tgn:7012149",
        "tgn:2000027",
        "tgn:7029392"
    ],
    "tgn:id":2195397,
    "tgn:name":"Bristow Creek",
    "tgn:placetype":[
        "aat:300008706"
    ]
},
  "bbox": [],
  "geometry": {"coordinates":[-86.2167,34.0667],"type":"Point"}
}