{
  "id": 2563560,
  "type": "Feature",
  "properties": {
    "tgn:hierarchy":[
        "tgn:2563560",
        "tgn:1000001",
        "tgn:7012149",
        "tgn:2001447",
        "tgn:7007566",
        "tgn:7029392"
    ],
    "tgn:id":2563560,
    "tgn:name":"Owl Tank",
    "tgn:placetype":[
        "aat:300006191"
    ]
},
  "bbox": [],
  "geometry": {"coordinates":[-105.8833,32.15],"type":"Point"}
}