{
  "id": 7390409,
  "type": "Feature",
  "properties": {
    "tgn:hierarchy":[
        "tgn:7390409",
        "tgn:7005583",
        "tgn:1000001",
        "tgn:7005560",
        "tgn:7029392"
    ],
    "tgn:id":7390409,
    "tgn:name":"Rancho La Colonia",
    "tgn:placetype":[
        "aat:300008347"
    ]
},
  "bbox": [],
  "geometry": {"coordinates":[-103.566667,25.683333],"type":"Point"}
}