{
  "id": 2343400,
  "type": "Feature",
  "properties": {
    "tgn:hierarchy":[
        "tgn:2343400",
        "tgn:7002659",
        "tgn:1000001",
        "tgn:7012149",
        "tgn:2000063",
        "tgn:7029392"
    ],
    "tgn:id":2343400,
    "tgn:name":"Gaines Hill",
    "tgn:placetype":[
        "aat:300008798"
    ]
},
  "bbox": [],
  "geometry": {"coordinates":[-87.45,33.7167],"type":"Point"}
}