{
  "id": 7380483,
  "type": "Feature",
  "properties": {
    "tgn:hierarchy":[
        "tgn:7380483",
        "tgn:1000001",
        "tgn:7005599",
        "tgn:7005560",
        "tgn:7029392"
    ],
    "tgn:id":7380483,
    "tgn:name":"Loma Buenavista",
    "tgn:placetype":[
        "aat:300008347"
    ]
},
  "bbox": [],
  "geometry": {"coordinates":[-95.666667,18.733333],"type":"Point"}
}