<<<<<<< HEAD
{
  "id": 7366467,
  "type": "Feature",
  "properties": {
    "tgn:hierarchy":[
        "tgn:7366467",
        "tgn:7005586",
        "tgn:1000001",
        "tgn:7005560",
        "tgn:7029392"
    ],
    "tgn:id":7366467,
    "tgn:name":"El Tigre",
    "tgn:placetype":[
        "aat:300007783"
    ]
},
  "bbox": [],
  "geometry": {"coordinates":[-102.25,21.6],"type":"Point"}
}
=======
{"geometry":{"type":"Point","coordinates":[-102.250000,21.600000]},"type":"Feature","properties":{"hierarchy":["tgn:7366467","tgn:7005586","tgn:1000001","tgn:7005560","tgn:7029392"],"placetype":["aat:300007783"],"id":7366467,"name:xx":"El Tigre"}}
>>>>>>> 03f74aca74312dbeaf24d7e61306dd6a786dc3d0
