<<<<<<< HEAD
{
  "id": 2336072,
  "type": "Feature",
  "properties": {
    "tgn:hierarchy":[
        "tgn:2336072",
        "tgn:1000001",
        "tgn:7012149",
        "tgn:7020792",
        "tgn:7007524",
        "tgn:7029392"
    ],
    "tgn:id":2336072,
    "tgn:name":"Foster Creek Mine",
    "tgn:placetype":[
        "aat:300000390"
    ]
},
  "bbox": [],
  "geometry": {"coordinates":[-113.1333,46.1833],"type":"Point"}
}
=======
{"geometry":{"type":"Point","coordinates":[-113.133300,46.183300]},"type":"Feature","properties":{"hierarchy":["tgn:2336072","tgn:1000001","tgn:7012149","tgn:7020792","tgn:7007524","tgn:7029392"],"placetype":["aat:300000390"],"id":2336072,"name:xx":"Foster Creek Mine"}}
>>>>>>> 03f74aca74312dbeaf24d7e61306dd6a786dc3d0
