<<<<<<< HEAD
{
  "id": 2760291,
  "type": "Feature",
  "properties": {
    "tgn:hierarchy":[
        "tgn:2760291",
        "tgn:2000192",
        "tgn:1000001",
        "tgn:7012149",
        "tgn:7007158",
        "tgn:7029392"
    ],
    "tgn:id":2760291,
    "tgn:name":"West Fork San Arroyo Creek",
    "tgn:placetype":[
        "aat:300008706"
    ]
},
  "bbox": [],
  "geometry": {"coordinates":[-103.8833,39.8833],"type":"Point"}
}
=======
{"geometry":{"type":"Point","coordinates":[-103.883300,39.883300]},"type":"Feature","properties":{"hierarchy":["tgn:2760291","tgn:2000192","tgn:1000001","tgn:7012149","tgn:7007158","tgn:7029392"],"placetype":["aat:300008706"],"id":2760291,"name:xx":"West Fork San Arroyo Creek"}}
>>>>>>> 03f74aca74312dbeaf24d7e61306dd6a786dc3d0
