<<<<<<< HEAD
{
  "id": 2333639,
  "type": "Feature",
  "properties": {
    "tgn:hierarchy":[
        "tgn:2333639",
        "tgn:1000001",
        "tgn:7012149",
        "tgn:2001284",
        "tgn:7007524",
        "tgn:7029392"
    ],
    "tgn:id":2333639,
    "tgn:name":"Fool Hen Creek",
    "tgn:placetype":[
        "aat:300008706"
    ]
},
  "bbox": [],
  "geometry": {"coordinates":[-112.45,46.8667],"type":"Point"}
}
=======
{"geometry":{"type":"Point","coordinates":[-112.450000,46.866700]},"type":"Feature","properties":{"hierarchy":["tgn:2333639","tgn:1000001","tgn:7012149","tgn:2001284","tgn:7007524","tgn:7029392"],"placetype":["aat:300008706"],"id":2333639,"name:xx":"Fool Hen Creek"}}
>>>>>>> 03f74aca74312dbeaf24d7e61306dd6a786dc3d0
