{
  "id": 2674095,
  "type": "Feature",
  "properties": {
    "tgn:hierarchy":[
        "tgn:2674095",
        "tgn:1000001",
        "tgn:7012149",
        "tgn:2000848",
        "tgn:7007255",
        "tgn:7029392"
    ],
    "tgn:id":2674095,
    "tgn:name":"Snowbirds Point",
    "tgn:placetype":[
        "aat:300008798"
    ]
},
  "bbox": [],
  "geometry": {"coordinates":[-86.5333,37.0833],"type":"Point"}
}