{
  "id": 7069546,
  "type": "Feature",
  "properties": {
    "tgn:hierarchy":[
        "tgn:7069546",
        "tgn:1000003",
        "tgn:7003689",
        "tgn:7000084",
        "tgn:7029392"
    ],
    "tgn:id":7069546,
    "tgn:name":"Thr\u00e4nitz",
    "tgn:placetype":[
        "aat:300008347"
    ]
},
  "bbox": [],
  "geometry": {"coordinates":[12.133333,50.866667],"type":"Point"}
}