{
  "id": 7312034,
  "type": "Feature",
  "properties": {
    "tgn:hierarchy":[
        "tgn:7312034",
        "tgn:1001695",
        "tgn:1000049",
        "tgn:1000002",
        "tgn:7029392"
    ],
    "tgn:id":7312034,
    "tgn:name":"Las Damas",
    "tgn:placetype":[
        "aat:300008777"
    ]
},
  "bbox": [],
  "geometry": {"coordinates":[-71.733333,-34.216667],"type":"Point"}
}