{
  "id": 2164549,
  "type": "Feature",
  "properties": {
    "tgn:hierarchy":[
        "tgn:2164549",
        "tgn:1000001",
        "tgn:7012149",
        "tgn:2001300",
        "tgn:7007524",
        "tgn:7029392"
    ],
    "tgn:id":2164549,
    "tgn:name":"Berry Rush Mine",
    "tgn:placetype":[
        "aat:300000390"
    ]
},
  "bbox": [],
  "geometry": {"coordinates":[-113.9333,46.7167],"type":"Point"}
}