<<<<<<< HEAD
{
  "id": 7248920,
  "type": "Feature",
  "properties": {
    "tgn:hierarchy":[
        "tgn:7248920",
        "tgn:7003456",
        "tgn:1000003",
        "tgn:1000063",
        "tgn:7018236",
        "tgn:7029392"
    ],
    "tgn:id":7248920,
    "tgn:name":"Broek Beek",
    "tgn:placetype":[
        "aat:300008699"
    ]
},
  "bbox": [],
  "geometry": {"coordinates":[4.85,51.266667],"type":"Point"}
}
=======
{"geometry":{"type":"Point","coordinates":[4.850000,51.266667]},"type":"Feature","properties":{"hierarchy":["tgn:7248920","tgn:7003456","tgn:1000003","tgn:1000063","tgn:7018236","tgn:7029392"],"placetype":["aat:300008699"],"id":7248920,"name:xx":"Broek Beek"}}
>>>>>>> 03f74aca74312dbeaf24d7e61306dd6a786dc3d0
