{
  "id": 7248920,
  "type": "Feature",
  "properties": {
    "tgn:hierarchy":[
        "tgn:7248920",
        "tgn:7003456",
        "tgn:1000003",
        "tgn:1000063",
        "tgn:7018236",
        "tgn:7029392"
    ],
    "tgn:id":7248920,
    "tgn:name":"Broek Beek",
    "tgn:placetype":[
        "aat:300008699"
    ]
},
  "bbox": [],
  "geometry": {"coordinates":[4.85,51.266667],"type":"Point"}
}