{
  "id": 7306557,
  "type": "Feature",
  "properties": {
    "tgn:hierarchy":[
        "tgn:7306557",
        "tgn:1001439",
        "tgn:1000003",
        "tgn:7002797",
        "tgn:1000095",
        "tgn:7029392"
    ],
    "tgn:id":7306557,
    "tgn:name":"Los Pinos",
    "tgn:placetype":[
        "aat:300008347"
    ]
},
  "bbox": [],
  "geometry": {"coordinates":[-0.833333,37.85],"type":"Point"}
}