{
  "id": 1115249,
  "type": "Feature",
  "properties": {
    "tgn:hierarchy":[
        "tgn:1115249",
        "tgn:1000004",
        "tgn:7016744",
        "tgn:1000135",
        "tgn:7029392"
    ],
    "tgn:id":1115249,
    "tgn:name":"Sarangani Strait",
    "tgn:placetype":[
        "aat:300266559"
    ]
},
  "bbox": [],
  "geometry": {"coordinates":[125.3833,5.5167],"type":"Point"}
}