{
  "id": 7567317,
  "type": "Feature",
  "properties": {
    "tgn:hierarchy":[
        "tgn:7567317",
        "tgn:1001828",
        "tgn:1000004",
        "tgn:7000198",
        "tgn:7029392"
    ],
    "tgn:id":7567317,
    "tgn:name:en":"Lingainpalli",
    "tgn:placetype":[
        "aat:300008347"
    ]
},
  "bbox": [],
  "geometry": {"coordinates":[78.257222,17.918056],"type":"Point"}
}