<<<<<<< HEAD
{
  "id": 2157044,
  "type": "Feature",
  "properties": {
    "tgn:hierarchy":[
        "tgn:2157044",
        "tgn:1000001",
        "tgn:7012149",
        "tgn:2000281",
        "tgn:7007240",
        "tgn:7029392"
    ],
    "tgn:id":2157044,
    "tgn:name":"Beaver Branch",
    "tgn:placetype":[
        "aat:300008699"
    ]
},
  "bbox": [],
  "geometry": {"coordinates":[-86.6333,30.8],"type":"Point"}
}
=======
{"geometry":{"type":"Point","coordinates":[-86.633300,30.800000]},"type":"Feature","properties":{"hierarchy":["tgn:2157044","tgn:1000001","tgn:7012149","tgn:2000281","tgn:7007240","tgn:7029392"],"placetype":["aat:300008699"],"id":2157044,"name:xx":"Beaver Branch"}}
>>>>>>> 03f74aca74312dbeaf24d7e61306dd6a786dc3d0
