<<<<<<< HEAD
{
  "id": 2769634,
  "type": "Feature",
  "properties": {
    "tgn:hierarchy":[
        "tgn:2769634",
        "tgn:7006450",
        "tgn:1000001",
        "tgn:7012149",
        "tgn:2000089",
        "tgn:7029392"
    ],
    "tgn:id":2769634,
    "tgn:name":"Wien Lake",
    "tgn:placetype":[
        "aat:300008680"
    ]
},
  "bbox": [],
  "geometry": {"coordinates":[-151.2833,64.35],"type":"Point"}
}
=======
{"geometry":{"type":"Point","coordinates":[-151.283300,64.350000]},"type":"Feature","properties":{"hierarchy":["tgn:2769634","tgn:7006450","tgn:1000001","tgn:7012149","tgn:2000089","tgn:7029392"],"placetype":["aat:300008680"],"id":2769634,"name:xx":"Wien Lake"}}
>>>>>>> 03f74aca74312dbeaf24d7e61306dd6a786dc3d0
