{
  "id": 2359526,
  "type": "Feature",
  "properties": {
    "tgn:hierarchy":[
        "tgn:2359526",
        "tgn:1000001",
        "tgn:7012149",
        "tgn:2000559",
        "tgn:7007252",
        "tgn:7029392"
    ],
    "tgn:id":2359526,
    "tgn:name":"Grant Mine Pond",
    "tgn:placetype":[
        "aat:300008680"
    ]
},
  "bbox": [],
  "geometry": {"coordinates":[-87.4667,39.5667],"type":"Point"}
}