{
  "id": 2606492,
  "type": "Feature",
  "properties": {
    "tgn:hierarchy":[
        "tgn:2606492",
        "tgn:1000001",
        "tgn:7012149",
        "tgn:2001274",
        "tgn:7007524",
        "tgn:7029392"
    ],
    "tgn:id":2606492,
    "tgn:name":"Rambler Creek",
    "tgn:placetype":[
        "aat:300008706"
    ]
},
  "bbox": [],
  "geometry": {"coordinates":[-113.25,47.7667],"type":"Point"}
}