{
  "id": 2370494,
  "type": "Feature",
  "properties": {
    "tgn:hierarchy":[
        "tgn:2370494",
        "tgn:1000001",
        "tgn:7012149",
        "tgn:2001514",
        "tgn:7007709",
        "tgn:7029392"
    ],
    "tgn:id":2370494,
    "tgn:name":"Habersham Mountains",
    "tgn:placetype":[
        "aat:300386831"
    ]
},
  "bbox": [],
  "geometry": {"coordinates":[-82.0167,35.6333],"type":"Point"}
}