{
  "id": 2126143,
  "type": "Feature",
  "properties": {
    "tgn:hierarchy":[
        "tgn:2126143",
        "tgn:1000001",
        "tgn:1002665",
        "tgn:7012149",
        "tgn:7007517",
        "tgn:7029392"
    ],
    "tgn:id":2126143,
    "tgn:name":"Addition Hill",
    "tgn:placetype":[
        "aat:300008798"
    ]
},
  "bbox": [],
  "geometry": {"coordinates":[-71.55,42.35],"type":"Point"}
}