{
  "id": 2781380,
  "type": "Feature",
  "properties": {
    "tgn:hierarchy":[
        "tgn:2781380",
        "tgn:1000001",
        "tgn:2000198",
        "tgn:7012149",
        "tgn:7007158",
        "tgn:7029392"
    ],
    "tgn:id":2781380,
    "tgn:name":"Woodland Mountain",
    "tgn:placetype":[
        "aat:300266640"
    ]
},
  "bbox": [],
  "geometry": {"coordinates":[-105.65,39.95],"type":"Point"}
}