{
  "id": 2499667,
  "type": "Feature",
  "properties": {
    "tgn:hierarchy":[
        "tgn:2499667",
        "tgn:1000001",
        "tgn:7012149",
        "tgn:1002880",
        "tgn:7007255",
        "tgn:7029392"
    ],
    "tgn:id":2499667,
    "tgn:name":"McConnell Run",
    "tgn:placetype":[
        "aat:300008699"
    ]
},
  "bbox": [],
  "geometry": {"coordinates":[-84.6333,38.3167],"type":"Point"}
}