{
  "id": 1133788,
  "type": "Feature",
  "properties": {
    "tgn:hierarchy":[
        "tgn:1133788",
        "tgn:1000001",
        "tgn:7012149",
        "tgn:7007922",
        "tgn:7029392"
    ],
    "tgn:id":1133788,
    "tgn:name":"Marsh Creek",
    "tgn:placetype":[
        "aat:300008706"
    ]
},
  "bbox": [],
  "geometry": {"coordinates":[-89.7833,43.1833],"type":"Point"}
}