{
  "id": 7341671,
  "type": "Feature",
  "properties": {
    "tgn:hierarchy":[
        "tgn:7341671",
        "tgn:7002805",
        "tgn:7002758",
        "tgn:1000003",
        "tgn:1000095",
        "tgn:7029392"
    ],
    "tgn:id":7341671,
    "tgn:name":"Bolonor, Barranco de",
    "tgn:placetype":[
        "aat:300266554",
        "aat:300008699"
    ]
},
  "bbox": [],
  "geometry": {"coordinates":[-2.516667,37.35],"type":"Point"}
}