{
  "id": 7248827,
  "type": "Feature",
  "properties": {
    "tgn:hierarchy":[
        "tgn:7248827",
        "tgn:7003457",
        "tgn:1000003",
        "tgn:1000063",
        "tgn:7018236",
        "tgn:7029392"
    ],
    "tgn:id":7248827,
    "tgn:name":"Boekmolen",
    "tgn:placetype":[
        "aat:300008347"
    ]
},
  "bbox": [],
  "geometry": {"coordinates":[4.133333,51.133333],"type":"Point"}
}