{
  "id": 2754500,
  "type": "Feature",
  "properties": {
    "tgn:hierarchy":[
        "tgn:2754500",
        "tgn:7002659",
        "tgn:1000001",
        "tgn:7012149",
        "tgn:7029392"
    ],
    "tgn:id":2754500,
    "tgn:name":"Waxahatchee Creek",
    "tgn:placetype":[
        "aat:300008706"
    ]
},
  "bbox": [],
  "geometry": {"coordinates":[-86.65,33.1833],"type":"Point"}
}