{
  "id": 1092193,
  "type": "Feature",
  "properties": {
    "tgn:hierarchy":[
        "tgn:1092193",
        "tgn:7001242",
        "tgn:7015579",
        "tgn:1000182",
        "tgn:7029392"
    ],
    "tgn:id":1092193,
    "tgn:name":"Nsukka",
    "tgn:placetype":[
        "aat:300387277",
        "aat:300008347",
        "aat:300008375",
        "aat:300387286",
        "aat:300387296"
    ]
},
  "bbox": [],
  "geometry": {"coordinates":[7.4833,6.85],"type":"Point"}
}