{
  "id": 2193592,
  "type": "Feature",
  "properties": {
    "tgn:hierarchy":[
        "tgn:2193592",
        "tgn:1000001",
        "tgn:7012149",
        "tgn:2001255",
        "tgn:7007523",
        "tgn:7029392"
    ],
    "tgn:id":2193592,
    "tgn:name":"Brewer Bay",
    "tgn:placetype":[
        "aat:300008699"
    ]
},
  "bbox": [],
  "geometry": {"coordinates":[-90.75,37.1167],"type":"Point"}
}