{
  "id": 7558251,
  "type": "Feature",
  "properties": {
    "tgn:hierarchy":[
        "tgn:7558251",
        "tgn:1000004",
        "tgn:7000198",
        "tgn:7001797",
        "tgn:7029392"
    ],
    "tgn:id":7558251,
    "tgn:name:en":"Pugal\u016br",
    "tgn:placetype":[
        "aat:300008347"
    ]
},
  "bbox": [],
  "geometry": {"coordinates":[78.016667,11.083333],"type":"Point"}
}