{
  "id": 2583078,
  "type": "Feature",
  "properties": {
    "tgn:hierarchy":[
        "tgn:2583078",
        "tgn:1000001",
        "tgn:7012149",
        "tgn:2001611",
        "tgn:7007706",
        "tgn:7029392"
    ],
    "tgn:id":2583078,
    "tgn:name":"Pine Lake",
    "tgn:placetype":[
        "aat:300006191"
    ]
},
  "bbox": [],
  "geometry": {"coordinates":[-82.5833,39.65],"type":"Point"}
}