{
  "id": 7567145,
  "type": "Feature",
  "properties": {
    "tgn:hierarchy":[
        "tgn:7567145",
        "tgn:1000004",
        "tgn:1001871",
        "tgn:7000198",
        "tgn:7029392"
    ],
    "tgn:id":7567145,
    "tgn:name:en":"Mukandpura",
    "tgn:placetype":[
        "aat:300008347"
    ]
},
  "bbox": [],
  "geometry": {"coordinates":[76.003736,28.046587],"type":"Point"}
}