{
  "id": 2216914,
  "type": "Feature",
  "properties": {
    "tgn:hierarchy":[
        "tgn:2216914",
        "tgn:1000001",
        "tgn:1002479",
        "tgn:7012149",
        "tgn:7007240",
        "tgn:7029392"
    ],
    "tgn:id":2216914,
    "tgn:name":"Camp Key",
    "tgn:placetype":[
        "aat:300008791"
    ]
},
  "bbox": [],
  "geometry": {"coordinates":[-82.5167,27.6833],"type":"Point"}
}