<<<<<<< HEAD
{
  "id": 7475359,
  "type": "Feature",
  "properties": {
    "tgn:hierarchy":[
        "tgn:7475359",
        "tgn:1000004",
        "tgn:7467799",
        "tgn:1000141",
        "tgn:7029392"
    ],
    "tgn:id":7475359,
    "tgn:name":"Wanxing Qiao",
    "tgn:placetype":[
        "aat:300007836"
    ]
},
  "bbox": [],
  "geometry": {"coordinates":[120.418059,23.955111],"type":"Point"}
}
=======
{"geometry":{"type":"Point","coordinates":[120.418059,23.955111]},"type":"Feature","properties":{"hierarchy":["tgn:7475359","tgn:1000004","tgn:7467799","tgn:1000141","tgn:7029392"],"placetype":["aat:300007836"],"id":7475359,"name:xx":"Wanxing Qiao"}}
>>>>>>> 03f74aca74312dbeaf24d7e61306dd6a786dc3d0
