{
  "id": 7475359,
  "type": "Feature",
  "properties": {
    "tgn:hierarchy":[
        "tgn:7475359",
        "tgn:1000004",
        "tgn:7467799",
        "tgn:1000141",
        "tgn:7029392"
    ],
    "tgn:id":7475359,
    "tgn:name":"Wanxing Qiao",
    "tgn:placetype":[
        "aat:300007836"
    ]
},
  "bbox": [],
  "geometry": {"coordinates":[120.418059,23.955111],"type":"Point"}
}