{
  "id": 2241409,
  "type": "Feature",
  "properties": {
    "tgn:hierarchy":[
        "tgn:2241409",
        "tgn:1000001",
        "tgn:2001424",
        "tgn:7012149",
        "tgn:7007564",
        "tgn:7029392"
    ],
    "tgn:id":2241409,
    "tgn:name":"Clark Pond Brook",
    "tgn:placetype":[
        "aat:300008699"
    ]
},
  "bbox": [],
  "geometry": {"coordinates":[-72.0667,43.7333],"type":"Point"}
}