{
  "id": 7271594,
  "type": "Feature",
  "properties": {
    "tgn:hierarchy":[
        "tgn:7271594",
        "tgn:1000003",
        "tgn:7006951",
        "tgn:7016845",
        "tgn:7029392"
    ],
    "tgn:id":7271594,
    "tgn:name:nl":"Terp",
    "tgn:placetype":[
        "aat:300008187"
    ]
},
  "bbox": [],
  "geometry": {"coordinates":[5.016667,52.85],"type":"Point"}
}