<<<<<<< HEAD
{
  "id": 2332613,
  "type": "Feature",
  "properties": {
    "tgn:hierarchy":[
        "tgn:2332613",
        "tgn:1000001",
        "tgn:2001415",
        "tgn:7012149",
        "tgn:7007526",
        "tgn:7029392"
    ],
    "tgn:id":2332613,
    "tgn:name":"Florida West Mine",
    "tgn:placetype":[
        "aat:300000390"
    ]
},
  "bbox": [],
  "geometry": {"coordinates":[-117.0,39.5],"type":"Point"}
}
=======
{"geometry":{"type":"Point","coordinates":[-117.000000,39.500000]},"type":"Feature","properties":{"hierarchy":["tgn:2332613","tgn:1000001","tgn:2001415","tgn:7012149","tgn:7007526","tgn:7029392"],"placetype":["aat:300000390"],"id":2332613,"name:xx":"Florida West Mine"}}
>>>>>>> 03f74aca74312dbeaf24d7e61306dd6a786dc3d0
