{
  "id": 2707275,
  "type": "Feature",
  "properties": {
    "tgn:hierarchy":[
        "tgn:2707275",
        "tgn:1000001",
        "tgn:2002245",
        "tgn:7012149",
        "tgn:7007920",
        "tgn:7029392"
    ],
    "tgn:id":2707275,
    "tgn:name":"Sweeney Gulch",
    "tgn:placetype":[
        "aat:300008761"
    ]
},
  "bbox": [],
  "geometry": {"coordinates":[-117.4833,46.3833],"type":"Point"}
}