{
  "id": 7539996,
  "type": "Feature",
  "properties": {
    "tgn:hierarchy":[
        "tgn:7539996",
        "tgn:7001242",
        "tgn:7016833",
        "tgn:7001312",
        "tgn:7029392"
    ],
    "tgn:id":7539996,
    "tgn:name":"Sandabas\u0163",
    "tgn:placetype":[
        "aat:300008347"
    ]
},
  "bbox": [],
  "geometry": {"coordinates":[31.25775,30.698619],"type":"Point"}
}