{
  "id": 7023772,
  "type": "Feature",
  "properties": {
    "tgn:hierarchy":[
        "tgn:7023772",
        "tgn:1000001",
        "tgn:2001414",
        "tgn:7012149",
        "tgn:7007526",
        "tgn:7029392"
    ],
    "tgn:id":7023772,
    "tgn:name":"Adelaide",
    "tgn:placetype":[
        "aat:300008347"
    ]
},
  "bbox": [],
  "geometry": {"coordinates":[-117.5167,40.8167],"type":"Point"}
}