<<<<<<< HEAD
{
  "id": 7172195,
  "type": "Feature",
  "properties": {
    "tgn:hierarchy":[
        "tgn:7172195",
        "tgn:7003669",
        "tgn:1000003",
        "tgn:7000084",
        "tgn:7029392"
    ],
    "tgn:id":7172195,
    "tgn:name":"Hinterwelln",
    "tgn:placetype":[
        "aat:300000206"
    ]
},
  "bbox": [],
  "geometry": {"coordinates":[12.666667,47.833333],"type":"Point"}
}
=======
{"geometry":{"type":"Point","coordinates":[12.666667,47.833333]},"type":"Feature","properties":{"hierarchy":["tgn:7172195","tgn:7003669","tgn:1000003","tgn:7000084","tgn:7029392"],"placetype":["aat:300000206"],"id":7172195,"name:xx":"Hinterwelln"}}
>>>>>>> 03f74aca74312dbeaf24d7e61306dd6a786dc3d0
