{
  "id": 7046875,
  "type": "Feature",
  "properties": {
    "tgn:hierarchy":[
        "tgn:7046875",
        "tgn:1000003",
        "tgn:7003151",
        "tgn:7003237",
        "tgn:1000080",
        "tgn:7029392"
    ],
    "tgn:id":7046875,
    "tgn:name":"Case del Molino",
    "tgn:placetype":[
        "aat:300008347"
    ]
},
  "bbox": [],
  "geometry": {"coordinates":[9.133333,44.916667],"type":"Point"}
}