{
  "id": 7583772,
  "type": "Feature",
  "properties": {
    "tgn:hierarchy":[
        "tgn:7583772",
        "tgn:1000004",
        "tgn:7000198",
        "tgn:1001894",
        "tgn:7029392"
    ],
    "tgn:id":7583772,
    "tgn:name:en":"Kharon",
    "tgn:placetype":[
        "aat:300008347"
    ]
},
  "bbox": [],
  "geometry": {"coordinates":[78.928825,25.150207],"type":"Point"}
}