{
  "id": 7496868,
  "type": "Feature",
  "properties": {
    "tgn:hierarchy":[
        "tgn:7496868",
        "tgn:7001004",
        "tgn:1000004",
        "tgn:1000141",
        "tgn:7029392"
    ],
    "tgn:id":7496868,
    "tgn:name":"Gaoxiong Gangwuju",
    "tgn:placetype":[
        "aat:300386996"
    ]
},
  "bbox": [],
  "geometry": {"coordinates":[120.2712,22.6229],"type":"Point"}
}