{
  "id": 2748733,
  "type": "Feature",
  "properties": {
    "tgn:hierarchy":[
        "tgn:2748733",
        "tgn:1000001",
        "tgn:2001410",
        "tgn:7012149",
        "tgn:7007526",
        "tgn:7029392"
    ],
    "tgn:id":2748733,
    "tgn:name":"Walker Wash",
    "tgn:placetype":[
        "aat:300008699"
    ]
},
  "bbox": [],
  "geometry": {"coordinates":[-114.2667,36.15],"type":"Point"}
}