{
  "id": 7592998,
  "type": "Feature",
  "properties": {
    "tgn:hierarchy":[
        "tgn:7592998",
        "tgn:1000004",
        "tgn:7000198",
        "tgn:7000799",
        "tgn:7029392"
    ],
    "tgn:id":7592998,
    "tgn:name:en":"Y\u016brb\u0101th\u0101k",
    "tgn:placetype":[
        "aat:300008347"
    ]
},
  "bbox": [],
  "geometry": {"coordinates":[76.198611,34.576389],"type":"Point"}
}