{
  "id": 7039496,
  "type": "Feature",
  "properties": {
    "tgn:hierarchy":[
        "tgn:7039496",
        "tgn:7003164",
        "tgn:1000003",
        "tgn:7009760",
        "tgn:1000080",
        "tgn:7029392"
    ],
    "tgn:id":7039496,
    "tgn:name":"Stella, Golfo",
    "tgn:placetype":[
        "aat:300132315"
    ]
},
  "bbox": [],
  "geometry": {"coordinates":[10.333333,42.75],"type":"Point"}
}