{
  "id": 7324222,
  "type": "Feature",
  "properties": {
    "tgn:hierarchy":[
        "tgn:7324222",
        "tgn:7002820",
        "tgn:7030216",
        "tgn:1000003",
        "tgn:1000095",
        "tgn:7029392"
    ],
    "tgn:id":7324222,
    "tgn:name":"Se-Calm, Puig",
    "tgn:placetype":[
        "aat:300008795"
    ]
},
  "bbox": [],
  "geometry": {"coordinates":[2.387847,42.125287],"type":"Point"}
}