{
  "id": 7550550,
  "type": "Feature",
  "properties": {
    "tgn:hierarchy":[
        "tgn:7550550",
        "tgn:7001819",
        "tgn:1000004",
        "tgn:7000198",
        "tgn:7029392"
    ],
    "tgn:id":7550550,
    "tgn:name:en":"Bichom River",
    "tgn:placetype":[
        "aat:300008699"
    ]
},
  "bbox": [],
  "geometry": {"coordinates":[92.722154,27.280594],"type":"Point"}
}