{
  "id": 7493937,
  "type": "Feature",
  "properties": {
    "tgn:hierarchy":[
        "tgn:7493937",
        "tgn:1000004",
        "tgn:7491221",
        "tgn:1000141",
        "tgn:7029392"
    ],
    "tgn:id":7493937,
    "tgn:name":"Decheng",
    "tgn:placetype":[
        "aat:300008347"
    ]
},
  "bbox": [],
  "geometry": {"coordinates":[121.301544,23.05981],"type":"Point"}
}