{
  "id": 7057265,
  "type": "Feature",
  "properties": {
    "tgn:hierarchy":[
        "tgn:7057265",
        "tgn:7003168",
        "tgn:1000003",
        "tgn:7009760",
        "tgn:1000080",
        "tgn:7029392"
    ],
    "tgn:id":7057265,
    "tgn:name":"Bagnaia",
    "tgn:placetype":[
        "aat:300008347"
    ]
},
  "bbox": [],
  "geometry": {"coordinates":[11.283333,43.216667],"type":"Point"}
}