{
  "id": 7445859,
  "type": "Feature",
  "properties": {
    "tgn:hierarchy":[
        "tgn:7445859",
        "tgn:7002444",
        "tgn:1000003",
        "tgn:7008082",
        "tgn:7008591",
        "tgn:7029392"
    ],
    "tgn:id":7445859,
    "tgn:name:en":"Suileag, Gleann",
    "tgn:placetype":[
        "aat:300008761"
    ]
},
  "bbox": [],
  "geometry": {"coordinates":[-5.266667,56.883333],"type":"Point"}
}