{
  "id": 7488749,
  "type": "Feature",
  "properties": {
    "tgn:hierarchy":[
        "tgn:7488749",
        "tgn:1000004",
        "tgn:7491221",
        "tgn:1000141",
        "tgn:7029392"
    ],
    "tgn:id":7488749,
    "tgn:name":"Long Shan",
    "tgn:placetype":[
        "aat:300008798"
    ]
},
  "bbox": [],
  "geometry": {"coordinates":[120.944167,22.513333],"type":"Point"}
}