{
  "id": 2534365,
  "type": "Feature",
  "properties": {
    "tgn:hierarchy":[
        "tgn:2534365",
        "tgn:1000001",
        "tgn:7012149",
        "tgn:2001281",
        "tgn:7007524",
        "tgn:7029392"
    ],
    "tgn:id":2534365,
    "tgn:name":"NE NE Section 29 Mine",
    "tgn:placetype":[
        "aat:300000390"
    ]
},
  "bbox": [],
  "geometry": {"coordinates":[-112.1167,46.3333],"type":"Point"}
}