{
  "id": 7506627,
  "type": "Feature",
  "properties": {
    "tgn:hierarchy":[
        "tgn:7506627",
        "tgn:1009227",
        "tgn:1000226",
        "tgn:7016729",
        "tgn:1000006",
        "tgn:7029392"
    ],
    "tgn:id":7506627,
    "tgn:name:en":"Rintoul, Mount",
    "tgn:placetype":[
        "aat:300008795"
    ]
},
  "bbox": [],
  "geometry": {"coordinates":[173.233333,-41.516667],"type":"Point"}
}