{
  "id": 2594387,
  "type": "Feature",
  "properties": {
    "tgn:hierarchy":[
        "tgn:2594387",
        "tgn:1000001",
        "tgn:7013686",
        "tgn:7012149",
        "tgn:7007517",
        "tgn:7029392"
    ],
    "tgn:id":2594387,
    "tgn:name":"Porter Swamp",
    "tgn:placetype":[
        "aat:300008905"
    ]
},
  "bbox": [],
  "geometry": {"coordinates":[-72.5167,42.2667],"type":"Point"}
}