{
  "id": 2206119,
  "type": "Feature",
  "properties": {
    "tgn:hierarchy":[
        "tgn:2206119",
        "tgn:1000001",
        "tgn:7012149",
        "tgn:2002375",
        "tgn:7007923",
        "tgn:7029392"
    ],
    "tgn:id":2206119,
    "tgn:name":"Bull Spring",
    "tgn:placetype":[
        "aat:300008697"
    ]
},
  "bbox": [],
  "geometry": {"coordinates":[-104.3667,41.45],"type":"Point"}
}