{
  "id": 7036740,
  "type": "Feature",
  "properties": {
    "tgn:hierarchy":[
        "tgn:7036740",
        "tgn:1003478",
        "tgn:1000003",
        "tgn:7003120",
        "tgn:1000080",
        "tgn:7029392"
    ],
    "tgn:id":7036740,
    "tgn:name":"Vinzaglio",
    "tgn:placetype":[
        "aat:300008347"
    ]
},
  "bbox": [],
  "geometry": {"coordinates":[8.516667,45.316667],"type":"Point"}
}