{
  "id": 7070825,
  "type": "Feature",
  "properties": {
    "tgn:hierarchy":[
        "tgn:7070825",
        "tgn:1000003",
        "tgn:7003682",
        "tgn:7000084",
        "tgn:7029392"
    ],
    "tgn:id":7070825,
    "tgn:name":"Stein-Bockenheim",
    "tgn:placetype":[
        "aat:300008347"
    ]
},
  "bbox": [],
  "geometry": {"coordinates":[7.966667,49.766667],"type":"Point"}
}