{
  "id": 7540511,
  "type": "Feature",
  "properties": {
    "tgn:hierarchy":[
        "tgn:7540511",
        "tgn:7001242",
        "tgn:7016833",
        "tgn:7001312",
        "tgn:7029392"
    ],
    "tgn:id":7540511,
    "tgn:name:en":"Minsh\u0101t al K\u016bd\u012b",
    "tgn:placetype":[
        "aat:300008347"
    ]
},
  "bbox": [],
  "geometry": {"coordinates":[30.828833,30.777418],"type":"Point"}
}