{
  "id": 7064716,
  "type": "Feature",
  "properties": {
    "tgn:hierarchy":[
        "tgn:7064716",
        "tgn:7003669",
        "tgn:1000003",
        "tgn:7000084",
        "tgn:7029392"
    ],
    "tgn:id":7064716,
    "tgn:name":"Untergrub",
    "tgn:placetype":[
        "aat:300000206"
    ]
},
  "bbox": [],
  "geometry": {"coordinates":[12.016667,48.616667],"type":"Point"}
}