{
  "id": 7492175,
  "type": "Feature",
  "properties": {
    "tgn:hierarchy":[
        "tgn:7492175",
        "tgn:1000004",
        "tgn:7490934",
        "tgn:1000141",
        "tgn:7029392"
    ],
    "tgn:id":7492175,
    "tgn:name":"Beizidian",
    "tgn:placetype":[
        "aat:300008347"
    ]
},
  "bbox": [],
  "geometry": {"coordinates":[120.312009,23.136684],"type":"Point"}
}