{
  "id": 7552721,
  "type": "Feature",
  "properties": {
    "tgn:hierarchy":[
        "tgn:7552721",
        "tgn:1000004",
        "tgn:7000198",
        "tgn:1001895",
        "tgn:7029392"
    ],
    "tgn:id":7552721,
    "tgn:name:en":"Manori Creek",
    "tgn:placetype":[
        "aat:300266571"
    ]
},
  "bbox": [],
  "geometry": {"coordinates":[72.783333,19.183333],"type":"Point"}
}