{
  "id": 7087711,
  "type": "Feature",
  "properties": {
    "tgn:hierarchy":[
        "tgn:7087711",
        "tgn:7000096",
        "tgn:1000003",
        "tgn:7000084",
        "tgn:7029392"
    ],
    "tgn:id":7087711,
    "tgn:name":"Weinberg",
    "tgn:placetype":[
        "aat:300000206"
    ]
},
  "bbox": [],
  "geometry": {"coordinates":[14.266667,51.733333],"type":"Point"}
}