{
  "id": 2089442,
  "type": "Feature",
  "properties": {
    "tgn:hierarchy":[
        "tgn:2089442",
        "tgn:1000001",
        "tgn:7012149",
        "tgn:1002612",
        "tgn:7007710",
        "tgn:7029392"
    ],
    "tgn:id":2089442,
    "tgn:name":"Hughestown",
    "tgn:placetype":[
        "aat:300008347"
    ]
},
  "bbox": [],
  "geometry": {"coordinates":[-75.7667,41.3167],"type":"Point"}
}