{
  "id": 2101096,
  "type": "Feature",
  "properties": {
    "tgn:hierarchy":[
        "tgn:2101096",
        "tgn:1000001",
        "tgn:7012149",
        "tgn:2001889",
        "tgn:7007825",
        "tgn:7029392"
    ],
    "tgn:id":2101096,
    "tgn:name":"Poplar Springs",
    "tgn:placetype":[
        "aat:300008347",
        "aat:300387210"
    ]
},
  "bbox": [],
  "geometry": {"coordinates":[-84.2833,35.7333],"type":"Point"}
}