{
  "id": 2371433,
  "type": "Feature",
  "properties": {
    "tgn:hierarchy":[
        "tgn:2371433",
        "tgn:1000001",
        "tgn:7012149",
        "tgn:1002623",
        "tgn:7007252",
        "tgn:7029392"
    ],
    "tgn:id":2371433,
    "tgn:name":"Haines Ditch",
    "tgn:placetype":[
        "aat:300006075"
    ]
},
  "bbox": [],
  "geometry": {"coordinates":[-85.85,40.3667],"type":"Point"}
}