{
  "id": 2436362,
  "type": "Feature",
  "properties": {
    "tgn:hierarchy":[
        "tgn:2436362",
        "tgn:1000001",
        "tgn:7012149",
        "tgn:7007157",
        "tgn:1002957",
        "tgn:7029392"
    ],
    "tgn:id":2436362,
    "tgn:name":"Kibbie Lake",
    "tgn:placetype":[
        "aat:300008680"
    ]
},
  "bbox": [],
  "geometry": {"coordinates":[-119.8333,38.05],"type":"Point"}
}