<<<<<<< HEAD
{
  "id": 7021612,
  "type": "Feature",
  "properties": {
    "tgn:hierarchy":[
        "tgn:7021612",
        "tgn:1000001",
        "tgn:7012149",
        "tgn:1002315",
        "tgn:7007826",
        "tgn:7029392"
    ],
    "tgn:id":7021612,
    "tgn:name":"De Soto",
    "tgn:placetype":[
        "aat:300008347"
    ]
},
  "bbox": [],
  "geometry": {"coordinates":[-96.85,32.5833],"type":"Point"}
}
=======
{"geometry":{"type":"Point","coordinates":[-96.850000,32.583300]},"type":"Feature","properties":{"hierarchy":["tgn:7021612","tgn:1000001","tgn:7012149","tgn:1002315","tgn:7007826","tgn:7029392"],"placetype":["aat:300008347"],"id":7021612,"name:xx":"De Soto"}}
>>>>>>> 03f74aca74312dbeaf24d7e61306dd6a786dc3d0
