{
  "id": 7289212,
  "type": "Feature",
  "properties": {
    "tgn:hierarchy":[
        "tgn:7289212",
        "tgn:1001657",
        "tgn:1000049",
        "tgn:1000002",
        "tgn:7029392"
    ],
    "tgn:id":7289212,
    "tgn:name":"La Bandera, Cerros",
    "tgn:placetype":[
        "aat:300008795"
    ]
},
  "bbox": [],
  "geometry": {"coordinates":[-71.933333,-30.383333],"type":"Point"}
}