{
  "id": 2267904,
  "type": "Feature",
  "properties": {
    "tgn:hierarchy":[
        "tgn:2267904",
        "tgn:7002659",
        "tgn:1000001",
        "tgn:7012149",
        "tgn:2000057",
        "tgn:7029392"
    ],
    "tgn:id":2267904,
    "tgn:name":"Crooked Creek",
    "tgn:placetype":[
        "aat:300008706"
    ]
},
  "bbox": [],
  "geometry": {"coordinates":[-86.4167,33.6833],"type":"Point"}
}