{
  "id": 7256973,
  "type": "Feature",
  "properties": {
    "tgn:hierarchy":[
        "tgn:7256973",
        "tgn:7593113",
        "tgn:7016620",
        "tgn:7593112",
        "tgn:1000001",
        "tgn:7029392"
    ],
    "tgn:id":7256973,
    "tgn:name:nl":"Jan Doran",
    "tgn:placetype":[
        "aat:300008347"
    ]
},
  "bbox": [],
  "geometry": {"coordinates":[-68.35,12.216667],"type":"Point"}
}