{
  "id": 7581931,
  "type": "Feature",
  "properties": {
    "tgn:hierarchy":[
        "tgn:7581931",
        "tgn:1000004",
        "tgn:1001871",
        "tgn:7000198",
        "tgn:7029392"
    ],
    "tgn:id":7581931,
    "tgn:name:en":"Lakhi Tibba",
    "tgn:placetype":[
        "aat:300008777"
    ]
},
  "bbox": [],
  "geometry": {"coordinates":[75.591772,28.898099],"type":"Point"}
}