<<<<<<< HEAD
{
  "id": 2409509,
  "type": "Feature",
  "properties": {
    "tgn:hierarchy":[
        "tgn:2409509",
        "tgn:2000000",
        "tgn:7002659",
        "tgn:1000001",
        "tgn:7012149",
        "tgn:7029392"
    ],
    "tgn:id":2409509,
    "tgn:name":"Idlewild Lake",
    "tgn:placetype":[
        "aat:300006191"
    ]
},
  "bbox": [],
  "geometry": {"coordinates":[-86.5667,32.45],"type":"Point"}
}
=======
{"geometry":{"type":"Point","coordinates":[-86.566700,32.450000]},"type":"Feature","properties":{"hierarchy":["tgn:2409509","tgn:2000000","tgn:7002659","tgn:1000001","tgn:7012149","tgn:7029392"],"placetype":["aat:300006191"],"id":2409509,"name:xx":"Idlewild Lake"}}
>>>>>>> 03f74aca74312dbeaf24d7e61306dd6a786dc3d0
