{
  "id": 2465305,
  "type": "Feature",
  "properties": {
    "tgn:hierarchy":[
        "tgn:2465305",
        "tgn:1000001",
        "tgn:7012149",
        "tgn:2001288",
        "tgn:7007524",
        "tgn:7029392"
    ],
    "tgn:id":2465305,
    "tgn:name":"Lone Acre Lake",
    "tgn:placetype":[
        "aat:300008680"
    ]
},
  "bbox": [],
  "geometry": {"coordinates":[-111.55,45.45],"type":"Point"}
}