<<<<<<< HEAD
{
  "id": 7480127,
  "type": "Feature",
  "properties": {
    "tgn:hierarchy":[
        "tgn:7480127",
        "tgn:1000004",
        "tgn:7001013",
        "tgn:1000141",
        "tgn:7029392"
    ],
    "tgn:id":7480127,
    "tgn:name":"Pingzhen Yihao Qiao",
    "tgn:placetype":[
        "aat:300007836"
    ]
},
  "bbox": [],
  "geometry": {"coordinates":[121.196111,24.921111],"type":"Point"}
}
=======
{"geometry":{"type":"Point","coordinates":[121.196111,24.921111]},"type":"Feature","properties":{"hierarchy":["tgn:7480127","tgn:1000004","tgn:7001013","tgn:1000141","tgn:7029392"],"placetype":["aat:300007836"],"id":7480127,"name:xx":"Pingzhen Yihao Qiao"}}
>>>>>>> 03f74aca74312dbeaf24d7e61306dd6a786dc3d0
