<<<<<<< HEAD
{
  "id": 2254399,
  "type": "Feature",
  "properties": {
    "tgn:hierarchy":[
        "tgn:2254399",
        "tgn:1000001",
        "tgn:7012149",
        "tgn:2001277",
        "tgn:7007524",
        "tgn:7029392"
    ],
    "tgn:id":2254399,
    "tgn:name":"Coon Creek",
    "tgn:placetype":[
        "aat:300008706"
    ]
},
  "bbox": [],
  "geometry": {"coordinates":[-113.0833,48.3],"type":"Point"}
}
=======
{"geometry":{"type":"Point","coordinates":[-113.083300,48.300000]},"type":"Feature","properties":{"hierarchy":["tgn:2254399","tgn:1000001","tgn:7012149","tgn:2001277","tgn:7007524","tgn:7029392"],"placetype":["aat:300008706"],"id":2254399,"name:xx":"Coon Creek"}}
>>>>>>> 03f74aca74312dbeaf24d7e61306dd6a786dc3d0
