{
  "id": 2340202,
  "type": "Feature",
  "properties": {
    "tgn:hierarchy":[
        "tgn:2340202",
        "tgn:1000001",
        "tgn:7012149",
        "tgn:7007157",
        "tgn:1002861",
        "tgn:7029392"
    ],
    "tgn:id":2340202,
    "tgn:name":"French Camp Slough",
    "tgn:placetype":[
        "aat:300008699"
    ]
},
  "bbox": [],
  "geometry": {"coordinates":[-121.2333,37.8667],"type":"Point"}
}