{
  "id": 2493451,
  "type": "Feature",
  "properties": {
    "tgn:hierarchy":[
        "tgn:2493451",
        "tgn:1000001",
        "tgn:1002200",
        "tgn:7012149",
        "tgn:7007240",
        "tgn:7029392"
    ],
    "tgn:id":2493451,
    "tgn:name":"Marsh Bay",
    "tgn:placetype":[
        "aat:300132316"
    ]
},
  "bbox": [],
  "geometry": {"coordinates":[-80.75,28.6833],"type":"Point"}
}