{
  "id": 2372997,
  "type": "Feature",
  "properties": {
    "tgn:hierarchy":[
        "tgn:2372997",
        "tgn:1000001",
        "tgn:1002664",
        "tgn:7012149",
        "tgn:7007159",
        "tgn:7029392"
    ],
    "tgn:id":2372997,
    "tgn:name":"Hallocks Pond",
    "tgn:placetype":[
        "aat:300008680"
    ]
},
  "bbox": [],
  "geometry": {"coordinates":[-72.5833,41.55],"type":"Point"}
}