<<<<<<< HEAD
{
  "id": 7366689,
  "type": "Feature",
  "properties": {
    "tgn:hierarchy":[
        "tgn:7366689",
        "tgn:1000001",
        "tgn:1001960",
        "tgn:7005560",
        "tgn:7029392"
    ],
    "tgn:id":7366689,
    "tgn:name":"Rancho El Pinto",
    "tgn:placetype":[
        "aat:300000241"
    ]
},
  "bbox": [],
  "geometry": {"coordinates":[-111.116667,30.483333],"type":"Point"}
}
=======
{"geometry":{"type":"Point","coordinates":[-111.116667,30.483333]},"type":"Feature","properties":{"hierarchy":["tgn:7366689","tgn:1000001","tgn:1001960","tgn:7005560","tgn:7029392"],"placetype":["aat:300000241"],"id":7366689,"name:xx":"Rancho El Pinto"}}
>>>>>>> 03f74aca74312dbeaf24d7e61306dd6a786dc3d0
