{
  "id": 7122343,
  "type": "Feature",
  "properties": {
    "tgn:hierarchy":[
        "tgn:7122343",
        "tgn:1000003",
        "tgn:7000094",
        "tgn:7000084",
        "tgn:7029392"
    ],
    "tgn:id":7122343,
    "tgn:name":"Neu Klokow",
    "tgn:placetype":[
        "aat:300008347"
    ]
},
  "bbox": [],
  "geometry": {"coordinates":[11.783333,53.416667],"type":"Point"}
}