{
  "id": 2526975,
  "type": "Feature",
  "properties": {
    "tgn:hierarchy":[
        "tgn:2526975",
        "tgn:1000001",
        "tgn:7012149",
        "tgn:7014334",
        "tgn:7007919",
        "tgn:7029392"
    ],
    "tgn:id":2526975,
    "tgn:name":"Mount Airy Millpond",
    "tgn:placetype":[
        "aat:300006191"
    ]
},
  "bbox": [],
  "geometry": {"coordinates":[-76.7833,37.9667],"type":"Point"}
}