<<<<<<< HEAD
{
  "id": 7020539,
  "type": "Feature",
  "properties": {
    "tgn:hierarchy":[
        "tgn:7020539",
        "tgn:1000001",
        "tgn:7012149",
        "tgn:1002407",
        "tgn:7007568",
        "tgn:7029392"
    ],
    "tgn:id":7020539,
    "tgn:name":"Bethany",
    "tgn:placetype":[
        "aat:300008347"
    ]
},
  "bbox": [],
  "geometry": {"coordinates":[-78.1333,42.9167],"type":"Point"}
}
=======
{"geometry":{"type":"Point","coordinates":[-78.133300,42.916700]},"type":"Feature","properties":{"hierarchy":["tgn:7020539","tgn:1000001","tgn:7012149","tgn:1002407","tgn:7007568","tgn:7029392"],"placetype":["aat:300008347"],"id":7020539,"name:xx":"Bethany"}}
>>>>>>> 03f74aca74312dbeaf24d7e61306dd6a786dc3d0
