{
  "id": 7252805,
  "type": "Feature",
  "properties": {
    "tgn:hierarchy":[
        "tgn:7252805",
        "tgn:7007877",
        "tgn:1000003",
        "tgn:1000063",
        "tgn:4012014",
        "tgn:7029392"
    ],
    "tgn:id":7252805,
    "tgn:name":"Salles",
    "tgn:placetype":[
        "aat:300008347"
    ]
},
  "bbox": [],
  "geometry": {"coordinates":[4.25,50.05],"type":"Point"}
}