{
  "id": 2411982,
  "type": "Feature",
  "properties": {
    "tgn:hierarchy":[
        "tgn:2411982",
        "tgn:7002659",
        "tgn:1000001",
        "tgn:7012149",
        "tgn:2000045",
        "tgn:7029392"
    ],
    "tgn:id":2411982,
    "tgn:name":"Indian Queen Bar",
    "tgn:placetype":[
        "aat:300132348"
    ]
},
  "bbox": [],
  "geometry": {"coordinates":[-88.0167,32.4333],"type":"Point"}
}