<<<<<<< HEAD
{
  "id": 7110659,
  "type": "Feature",
  "properties": {
    "tgn:hierarchy":[
        "tgn:7110659",
        "tgn:7003669",
        "tgn:1000003",
        "tgn:7000084",
        "tgn:7029392"
    ],
    "tgn:id":7110659,
    "tgn:name":"Pullach",
    "tgn:placetype":[
        "aat:300008347"
    ]
},
  "bbox": [],
  "geometry": {"coordinates":[11.533333,48.05],"type":"Point"}
}
=======
{"geometry":{"type":"Point","coordinates":[11.533333,48.050000]},"type":"Feature","properties":{"hierarchy":["tgn:7110659","tgn:7003669","tgn:1000003","tgn:7000084","tgn:7029392"],"placetype":["aat:300008347"],"id":7110659,"name:xx":"Pullach"}}
>>>>>>> 03f74aca74312dbeaf24d7e61306dd6a786dc3d0
