{
  "id": 7281959,
  "type": "Feature",
  "properties": {
    "tgn:hierarchy":[
        "tgn:7281959",
        "tgn:1001708",
        "tgn:1000049",
        "tgn:1000002",
        "tgn:7029392"
    ],
    "tgn:id":7281959,
    "tgn:name":"Sauce, Quebrada del",
    "tgn:placetype":[
        "aat:300008699"
    ]
},
  "bbox": [],
  "geometry": {"coordinates":[-70.933333,-34.033333],"type":"Point"}
}