{
  "id": 7497876,
  "type": "Feature",
  "properties": {
    "tgn:hierarchy":[
        "tgn:7497876",
        "tgn:1000004",
        "tgn:7491221",
        "tgn:1000141",
        "tgn:7029392"
    ],
    "tgn:id":7497876,
    "tgn:name":"Jiamuzi",
    "tgn:placetype":[
        "aat:300008347"
    ]
},
  "bbox": [],
  "geometry": {"coordinates":[121.210613,22.864632],"type":"Point"}
}