{
  "id": 7189042,
  "type": "Feature",
  "properties": {
    "tgn:hierarchy":[
        "tgn:7189042",
        "tgn:1000003",
        "tgn:7003677",
        "tgn:7000084",
        "tgn:7029392"
    ],
    "tgn:id":7189042,
    "tgn:name":"Eltingm\u00fchlen-Bach",
    "tgn:placetype":[
        "aat:300008699"
    ]
},
  "bbox": [],
  "geometry": {"coordinates":[7.666667,52.133333],"type":"Point"}
}