<<<<<<< HEAD
{
  "id": 2338922,
  "type": "Feature",
  "properties": {
    "tgn:hierarchy":[
        "tgn:2338922",
        "tgn:1000001",
        "tgn:7012149",
        "tgn:7007157",
        "tgn:2000187",
        "tgn:7029392"
    ],
    "tgn:id":2338922,
    "tgn:name":"Franklin Canyon",
    "tgn:placetype":[
        "aat:300008761"
    ]
},
  "bbox": [],
  "geometry": {"coordinates":[-121.05,39.8],"type":"Point"}
}
=======
{"geometry":{"type":"Point","coordinates":[-121.050000,39.800000]},"type":"Feature","properties":{"hierarchy":["tgn:2338922","tgn:1000001","tgn:7012149","tgn:7007157","tgn:2000187","tgn:7029392"],"placetype":["aat:300008761"],"id":2338922,"name:xx":"Franklin Canyon"}}
>>>>>>> 03f74aca74312dbeaf24d7e61306dd6a786dc3d0
