<<<<<<< HEAD
{
  "id": 2258152,
  "type": "Feature",
  "properties": {
    "tgn:hierarchy":[
        "tgn:2258152",
        "tgn:1002224",
        "tgn:1000001",
        "tgn:7012149",
        "tgn:7007516",
        "tgn:7029392"
    ],
    "tgn:id":2258152,
    "tgn:name":"Coster",
    "tgn:placetype":[
        "aat:300008347"
    ]
},
  "bbox": [],
  "geometry": {"coordinates":[-76.4667,38.35],"type":"Point"}
}
=======
{"geometry":{"type":"Point","coordinates":[-76.466700,38.350000]},"type":"Feature","properties":{"hierarchy":["tgn:2258152","tgn:1002224","tgn:1000001","tgn:7012149","tgn:7007516","tgn:7029392"],"placetype":["aat:300008347"],"id":2258152,"name:xx":"Coster"}}
>>>>>>> 03f74aca74312dbeaf24d7e61306dd6a786dc3d0
