{
  "id": 7307820,
  "type": "Feature",
  "properties": {
    "tgn:hierarchy":[
        "tgn:7307820",
        "tgn:7002811",
        "tgn:1000003",
        "tgn:7003837",
        "tgn:1000095",
        "tgn:7029392"
    ],
    "tgn:id":7307820,
    "tgn:name":"Marchagaz",
    "tgn:placetype":[
        "aat:300008347"
    ]
},
  "bbox": [],
  "geometry": {"coordinates":[-6.266667,40.266667],"type":"Point"}
}