<<<<<<< HEAD
{
  "id": 7359122,
  "type": "Feature",
  "properties": {
    "tgn:hierarchy":[
        "tgn:7359122",
        "tgn:1001836",
        "tgn:1000001",
        "tgn:7005560",
        "tgn:7029392"
    ],
    "tgn:id":7359122,
    "tgn:name":"Colorado, Punta",
    "tgn:placetype":[
        "aat:300386846"
    ]
},
  "bbox": [],
  "geometry": {"coordinates":[-111.65,26.733333],"type":"Point"}
}
=======
{"geometry":{"type":"Point","coordinates":[-111.650000,26.733333]},"type":"Feature","properties":{"hierarchy":["tgn:7359122","tgn:1001836","tgn:1000001","tgn:7005560","tgn:7029392"],"placetype":["aat:300386846"],"id":7359122,"name:xx":"Colorado, Punta"}}
>>>>>>> 03f74aca74312dbeaf24d7e61306dd6a786dc3d0
