{
  "id": 2205022,
  "type": "Feature",
  "properties": {
    "tgn:hierarchy":[
        "tgn:2205022",
        "tgn:1000001",
        "tgn:7006451",
        "tgn:2000092",
        "tgn:7012149",
        "tgn:7029392"
    ],
    "tgn:id":2205022,
    "tgn:name":"Buggeln Tank",
    "tgn:placetype":[
        "aat:300006191"
    ]
},
  "bbox": [],
  "geometry": {"coordinates":[-111.95,35.9667],"type":"Point"}
}