{
  "id": 7217916,
  "type": "Feature",
  "properties": {
    "tgn:hierarchy":[
        "tgn:7217916",
        "tgn:7011164",
        "tgn:7002674",
        "tgn:1000003",
        "tgn:1000074",
        "tgn:7029392"
    ],
    "tgn:id":7217916,
    "tgn:name":"Mourti\u00e1s, \u00d3rmos",
    "tgn:placetype":[
        "aat:300185707"
    ]
},
  "bbox": [],
  "geometry": {"coordinates":[27.034167,37.753611],"type":"Point"}
}