{
  "id": 2663870,
  "type": "Feature",
  "properties": {
    "tgn:hierarchy":[
        "tgn:2663870",
        "tgn:1000001",
        "tgn:7012149",
        "tgn:1003020",
        "tgn:7007920",
        "tgn:7029392"
    ],
    "tgn:id":2663870,
    "tgn:name":"Silver Lake",
    "tgn:placetype":[
        "aat:300008680"
    ]
},
  "bbox": [],
  "geometry": {"coordinates":[-122.0667,48.9667],"type":"Point"}
}