<<<<<<< HEAD
{
  "id": 2150509,
  "type": "Feature",
  "properties": {
    "tgn:hierarchy":[
        "tgn:2150509",
        "tgn:1000001",
        "tgn:7012149",
        "tgn:7007158",
        "tgn:2000243",
        "tgn:7029392"
    ],
    "tgn:id":2150509,
    "tgn:name":"Basin Reservoir",
    "tgn:placetype":[
        "aat:300006191"
    ]
},
  "bbox": [],
  "geometry": {"coordinates":[-108.6667,40.0],"type":"Point"}
}
=======
{"geometry":{"type":"Point","coordinates":[-108.666700,40.000000]},"type":"Feature","properties":{"hierarchy":["tgn:2150509","tgn:1000001","tgn:7012149","tgn:7007158","tgn:2000243","tgn:7029392"],"placetype":["aat:300006191"],"id":2150509,"name:xx":"Basin Reservoir"}}
>>>>>>> 03f74aca74312dbeaf24d7e61306dd6a786dc3d0
