{
  "id": 2155041,
  "type": "Feature",
  "properties": {
    "tgn:hierarchy":[
        "tgn:2155041",
        "tgn:1000001",
        "tgn:7012149",
        "tgn:2000219",
        "tgn:7007158",
        "tgn:7029392"
    ],
    "tgn:id":2155041,
    "tgn:name":"Bear Lake",
    "tgn:placetype":[
        "aat:300008680"
    ]
},
  "bbox": [],
  "geometry": {"coordinates":[-105.1333,37.3167],"type":"Point"}
}