{
  "id": 7498798,
  "type": "Feature",
  "properties": {
    "tgn:hierarchy":[
        "tgn:7498798",
        "tgn:7488858",
        "tgn:1000004",
        "tgn:1000141",
        "tgn:7029392"
    ],
    "tgn:id":7498798,
    "tgn:name":"Zhici Gong",
    "tgn:placetype":[
        "aat:300007595"
    ]
},
  "bbox": [],
  "geometry": {"coordinates":[120.878433,24.059187],"type":"Point"}
}