{
  "id": 7547760,
  "type": "Feature",
  "properties": {
    "tgn:hierarchy":[
        "tgn:7547760",
        "tgn:1000004",
        "tgn:1001832",
        "tgn:7000198",
        "tgn:7029392"
    ],
    "tgn:id":7547760,
    "tgn:name:en":"B\u0101nguk",
    "tgn:placetype":[
        "aat:300008347"
    ]
},
  "bbox": [],
  "geometry": {"coordinates":[95.540245,28.027903],"type":"Point"}
}