{
  "id": 2377788,
  "type": "Feature",
  "properties": {
    "tgn:hierarchy":[
        "tgn:2377788",
        "tgn:7006450",
        "tgn:1000001",
        "tgn:2124076",
        "tgn:7012149",
        "tgn:7029392"
    ],
    "tgn:id":2377788,
    "tgn:name":"Harriet, Lake Hunt",
    "tgn:placetype":[
        "aat:300008680"
    ]
},
  "bbox": [],
  "geometry": {"coordinates":[-131.5833,55.4833],"type":"Point"}
}