{
  "id": 7048738,
  "type": "Feature",
  "properties": {
    "tgn:hierarchy":[
        "tgn:7048738",
        "tgn:7003150",
        "tgn:1000003",
        "tgn:7003237",
        "tgn:1000080",
        "tgn:7029392"
    ],
    "tgn:id":7048738,
    "tgn:name":"Dovera",
    "tgn:placetype":[
        "aat:300008347"
    ]
},
  "bbox": [],
  "geometry": {"coordinates":[9.533333,45.366667],"type":"Point"}
}