<<<<<<< HEAD
{
  "id": 7058772,
  "type": "Feature",
  "properties": {
    "tgn:hierarchy":[
        "tgn:7058772",
        "tgn:7003127",
        "tgn:1000003",
        "tgn:7008516",
        "tgn:1000080",
        "tgn:7029392"
    ],
    "tgn:id":7058772,
    "tgn:name":"Bonconvento",
    "tgn:placetype":[
        "aat:300008347"
    ]
},
  "bbox": [],
  "geometry": {"coordinates":[11.3,44.616667],"type":"Point"}
}
=======
{"geometry":{"type":"Point","coordinates":[11.300000,44.616667]},"type":"Feature","properties":{"hierarchy":["tgn:7058772","tgn:7003127","tgn:1000003","tgn:7008516","tgn:1000080","tgn:7029392"],"placetype":["aat:300008347"],"id":7058772,"name:xx":"Bonconvento"}}
>>>>>>> 03f74aca74312dbeaf24d7e61306dd6a786dc3d0
