{
  "id": 2510508,
  "type": "Feature",
  "properties": {
    "tgn:hierarchy":[
        "tgn:2510508",
        "tgn:1000001",
        "tgn:7012149",
        "tgn:2001437",
        "tgn:7007566",
        "tgn:7029392"
    ],
    "tgn:id":2510508,
    "tgn:name":"Middle Tank",
    "tgn:placetype":[
        "aat:300006191"
    ]
},
  "bbox": [],
  "geometry": {"coordinates":[-108.6667,32.6167],"type":"Point"}
}