{
  "id": 2382783,
  "type": "Feature",
  "properties": {
    "tgn:hierarchy":[
        "tgn:2382783",
        "tgn:1000001",
        "tgn:7006451",
        "tgn:7012149",
        "tgn:2000098",
        "tgn:7029392"
    ],
    "tgn:id":2382783,
    "tgn:name":"Hazel K Mine",
    "tgn:placetype":[
        "aat:300000390"
    ]
},
  "bbox": [],
  "geometry": {"coordinates":[-114.1333,35.3833],"type":"Point"}
}