<<<<<<< HEAD
{
  "id": 2769851,
  "type": "Feature",
  "properties": {
    "tgn:hierarchy":[
        "tgn:2769851",
        "tgn:1000001",
        "tgn:7012149",
        "tgn:2002069",
        "tgn:7007826",
        "tgn:7029392"
    ],
    "tgn:id":2769851,
    "tgn:name":"Wilbarger Creek",
    "tgn:placetype":[
        "aat:300008706"
    ]
},
  "bbox": [],
  "geometry": {"coordinates":[-99.0667,31.3167],"type":"Point"}
}
=======
{"geometry":{"type":"Point","coordinates":[-99.066700,31.316700]},"type":"Feature","properties":{"hierarchy":["tgn:2769851","tgn:1000001","tgn:7012149","tgn:2002069","tgn:7007826","tgn:7029392"],"placetype":["aat:300008706"],"id":2769851,"name:xx":"Wilbarger Creek"}}
>>>>>>> 03f74aca74312dbeaf24d7e61306dd6a786dc3d0
