<<<<<<< HEAD
{
  "id": 2150850,
  "type": "Feature",
  "properties": {
    "tgn:hierarchy":[
        "tgn:2150850",
        "tgn:1000001",
        "tgn:7012149",
        "tgn:7019676",
        "tgn:7007566",
        "tgn:7029392"
    ],
    "tgn:id":2150850,
    "tgn:name":"Bass Lake",
    "tgn:placetype":[
        "aat:300008680"
    ]
},
  "bbox": [],
  "geometry": {"coordinates":[-108.6833,35.7167],"type":"Point"}
}
=======
{"geometry":{"type":"Point","coordinates":[-108.683300,35.716700]},"type":"Feature","properties":{"hierarchy":["tgn:2150850","tgn:1000001","tgn:7012149","tgn:7019676","tgn:7007566","tgn:7029392"],"placetype":["aat:300008680"],"id":2150850,"name:xx":"Bass Lake"}}
>>>>>>> 03f74aca74312dbeaf24d7e61306dd6a786dc3d0
