{
  "id": 2103000,
  "type": "Feature",
  "properties": {
    "tgn:hierarchy":[
        "tgn:2103000",
        "tgn:1000001",
        "tgn:7012149",
        "tgn:1002526",
        "tgn:7007826",
        "tgn:7029392"
    ],
    "tgn:id":2103000,
    "tgn:name":"Burleson",
    "tgn:placetype":[
        "aat:300008347"
    ]
},
  "bbox": [],
  "geometry": {"coordinates":[-97.3167,32.5333],"type":"Point"}
}