<<<<<<< HEAD
{
  "id": 2258898,
  "type": "Feature",
  "properties": {
    "tgn:hierarchy":[
        "tgn:2258898",
        "tgn:1000001",
        "tgn:7012149",
        "tgn:2001308",
        "tgn:7007524",
        "tgn:7029392"
    ],
    "tgn:id":2258898,
    "tgn:name":"Cottonwood Creek",
    "tgn:placetype":[
        "aat:300008706"
    ]
},
  "bbox": [],
  "geometry": {"coordinates":[-109.6667,46.0],"type":"Point"}
}
=======
{"geometry":{"type":"Point","coordinates":[-109.666700,46.000000]},"type":"Feature","properties":{"hierarchy":["tgn:2258898","tgn:1000001","tgn:7012149","tgn:2001308","tgn:7007524","tgn:7029392"],"placetype":["aat:300008706"],"id":2258898,"name:xx":"Cottonwood Creek"}}
>>>>>>> 03f74aca74312dbeaf24d7e61306dd6a786dc3d0
