<<<<<<< HEAD
{
  "id": 7372600,
  "type": "Feature",
  "properties": {
    "tgn:hierarchy":[
        "tgn:7372600",
        "tgn:7005584",
        "tgn:1000001",
        "tgn:7005560",
        "tgn:7029392"
    ],
    "tgn:id":7372600,
    "tgn:name":"La Estancita",
    "tgn:placetype":[
        "aat:300008347"
    ]
},
  "bbox": [],
  "geometry": {"coordinates":[-101.066667,21.533333],"type":"Point"}
}
=======
{"geometry":{"type":"Point","coordinates":[-101.066667,21.533333]},"type":"Feature","properties":{"hierarchy":["tgn:7372600","tgn:7005584","tgn:1000001","tgn:7005560","tgn:7029392"],"placetype":["aat:300008347"],"id":7372600,"name:xx":"La Estancita"}}
>>>>>>> 03f74aca74312dbeaf24d7e61306dd6a786dc3d0
