{
  "id": 2211515,
  "type": "Feature",
  "properties": {
    "tgn:hierarchy":[
        "tgn:2211515",
        "tgn:1000001",
        "tgn:1002260",
        "tgn:7012149",
        "tgn:7007920",
        "tgn:7029392"
    ],
    "tgn:id":2211515,
    "tgn:name":"Butterfly Butte",
    "tgn:placetype":[
        "aat:300008798"
    ]
},
  "bbox": [],
  "geometry": {"coordinates":[-120.95,48.0667],"type":"Point"}
}