{
  "id": 2601062,
  "type": "Feature",
  "properties": {
    "tgn:hierarchy":[
        "tgn:2601062",
        "tgn:2000919",
        "tgn:1000001",
        "tgn:7012149",
        "tgn:7007515",
        "tgn:7029392"
    ],
    "tgn:id":2601062,
    "tgn:name":"Punchard Brook",
    "tgn:placetype":[
        "aat:300008699"
    ]
},
  "bbox": [],
  "geometry": {"coordinates":[-68.55,46.5667],"type":"Point"}
}