{
  "id": 7577260,
  "type": "Feature",
  "properties": {
    "tgn:hierarchy":[
        "tgn:7577260",
        "tgn:1001828",
        "tgn:1000004",
        "tgn:7000198",
        "tgn:7029392"
    ],
    "tgn:id":7577260,
    "tgn:name:en":"Kros\u016bru",
    "tgn:placetype":[
        "aat:300008347"
    ]
},
  "bbox": [],
  "geometry": {"coordinates":[80.133333,16.55],"type":"Point"}
}