<<<<<<< HEAD
{
  "id": 7056291,
  "type": "Feature",
  "properties": {
    "tgn:hierarchy":[
        "tgn:7056291",
        "tgn:1001641",
        "tgn:1000003",
        "tgn:7003121",
        "tgn:1000080",
        "tgn:7029392"
    ],
    "tgn:id":7056291,
    "tgn:name":"Pimentel",
    "tgn:placetype":[
        "aat:300008347"
    ]
},
  "bbox": [],
  "geometry": {"coordinates":[9.065278,39.489167],"type":"Point"}
}
=======
{"geometry":{"type":"Point","coordinates":[9.065278,39.489167]},"type":"Feature","properties":{"hierarchy":["tgn:7056291","tgn:1001641","tgn:1000003","tgn:7003121","tgn:1000080","tgn:7029392"],"placetype":["aat:300008347"],"id":7056291,"name:xx":"Pimentel"}}
>>>>>>> 03f74aca74312dbeaf24d7e61306dd6a786dc3d0
