{
  "id": 7485189,
  "type": "Feature",
  "properties": {
    "tgn:hierarchy":[
        "tgn:7485189",
        "tgn:1000004",
        "tgn:7491221",
        "tgn:1000141",
        "tgn:7029392"
    ],
    "tgn:id":7485189,
    "tgn:name":"Daniao Xikou",
    "tgn:placetype":[
        "aat:300387057"
    ]
},
  "bbox": [],
  "geometry": {"coordinates":[120.913611,22.380556],"type":"Point"}
}