{
  "id": 2604154,
  "type": "Feature",
  "properties": {
    "tgn:hierarchy":[
        "tgn:2604154",
        "tgn:1000001",
        "tgn:7006451",
        "tgn:7012149",
        "tgn:2000100",
        "tgn:7029392"
    ],
    "tgn:id":2604154,
    "tgn:name":"Quitobaquito Springs",
    "tgn:placetype":[
        "aat:300008697"
    ]
},
  "bbox": [],
  "geometry": {"coordinates":[-113.0167,31.9333],"type":"Point"}
}