{
  "id": 1060679,
  "type": "Feature",
  "properties": {
    "tgn:hierarchy":[
        "tgn:1060679",
        "tgn:1000004",
        "tgn:7011500",
        "tgn:7002435",
        "tgn:7029392"
    ],
    "tgn:id":1060679,
    "tgn:name":"Uoyan",
    "tgn:placetype":[
        "aat:300008347"
    ]
},
  "bbox": [],
  "geometry": {"coordinates":[111.6667,56.1333],"type":"Point"}
}