{
  "id": 2735520,
  "type": "Feature",
  "properties": {
    "tgn:hierarchy":[
        "tgn:2735520",
        "tgn:1000001",
        "tgn:7012149",
        "tgn:2000987",
        "tgn:7007520",
        "tgn:7029392"
    ],
    "tgn:id":2735520,
    "tgn:name":"Twin Creek",
    "tgn:placetype":[
        "aat:300008706"
    ]
},
  "bbox": [],
  "geometry": {"coordinates":[-85.3167,43.95],"type":"Point"}
}