<<<<<<< HEAD
{
  "id": 2407797,
  "type": "Feature",
  "properties": {
    "tgn:hierarchy":[
        "tgn:2407797",
        "tgn:1000001",
        "tgn:1002240",
        "tgn:7012149",
        "tgn:7007255",
        "tgn:7029392"
    ],
    "tgn:id":2407797,
    "tgn:name":"Hurricane Branch",
    "tgn:placetype":[
        "aat:300008699"
    ]
},
  "bbox": [],
  "geometry": {"coordinates":[-83.05,38.4333],"type":"Point"}
}
=======
{"geometry":{"type":"Point","coordinates":[-83.050000,38.433300]},"type":"Feature","properties":{"hierarchy":["tgn:2407797","tgn:1000001","tgn:1002240","tgn:7012149","tgn:7007255","tgn:7029392"],"placetype":["aat:300008699"],"id":2407797,"name:xx":"Hurricane Branch"}}
>>>>>>> 03f74aca74312dbeaf24d7e61306dd6a786dc3d0
