{
  "id": 7444918,
  "type": "Feature",
  "properties": {
    "tgn:hierarchy":[
        "tgn:7444918",
        "tgn:7002445",
        "tgn:7019018",
        "tgn:1000003",
        "tgn:7008591",
        "tgn:7029392"
    ],
    "tgn:id":7444918,
    "tgn:name:en":"Trym, River",
    "tgn:placetype":[
        "aat:300008699"
    ]
},
  "bbox": [],
  "geometry": {"coordinates":[-2.633333,51.483333],"type":"Point"}
}