<<<<<<< HEAD
{
  "id": 2153860,
  "type": "Feature",
  "properties": {
    "tgn:hierarchy":[
        "tgn:2153860",
        "tgn:2002101",
        "tgn:1000001",
        "tgn:7012149",
        "tgn:7007827",
        "tgn:7029392"
    ],
    "tgn:id":2153860,
    "tgn:name":"Bear Canyon",
    "tgn:placetype":[
        "aat:300008761"
    ]
},
  "bbox": [],
  "geometry": {"coordinates":[-112.5,38.35],"type":"Point"}
}
=======
{"geometry":{"type":"Point","coordinates":[-112.500000,38.350000]},"type":"Feature","properties":{"hierarchy":["tgn:2153860","tgn:2002101","tgn:1000001","tgn:7012149","tgn:7007827","tgn:7029392"],"placetype":["aat:300008761"],"id":2153860,"name:xx":"Bear Canyon"}}
>>>>>>> 03f74aca74312dbeaf24d7e61306dd6a786dc3d0
