<<<<<<< HEAD
{
  "id": 7478516,
  "type": "Feature",
  "properties": {
    "tgn:hierarchy":[
        "tgn:7478516",
        "tgn:1000004",
        "tgn:7467799",
        "tgn:1000141",
        "tgn:7029392"
    ],
    "tgn:id":7478516,
    "tgn:name":"Fenghe Qiao",
    "tgn:placetype":[
        "aat:300007836"
    ]
},
  "bbox": [],
  "geometry": {"coordinates":[120.591862,23.89834],"type":"Point"}
}
=======
{"geometry":{"type":"Point","coordinates":[120.591862,23.898340]},"type":"Feature","properties":{"hierarchy":["tgn:7478516","tgn:1000004","tgn:7467799","tgn:1000141","tgn:7029392"],"placetype":["aat:300007836"],"id":7478516,"name:xx":"Fenghe Qiao"}}
>>>>>>> 03f74aca74312dbeaf24d7e61306dd6a786dc3d0
