{
  "id": 7259577,
  "type": "Feature",
  "properties": {
    "tgn:hierarchy":[
        "tgn:7259577",
        "tgn:7007877",
        "tgn:1000003",
        "tgn:1000063",
        "tgn:4012014",
        "tgn:7029392"
    ],
    "tgn:id":7259577,
    "tgn:name":"Warcoing",
    "tgn:placetype":[
        "aat:300008347"
    ]
},
  "bbox": [],
  "geometry": {"coordinates":[3.346203,50.704469],"type":"Point"}
}