{
  "id": 7044174,
  "type": "Feature",
  "properties": {
    "tgn:hierarchy":[
        "tgn:7044174",
        "tgn:1003468",
        "tgn:1000003",
        "tgn:7010380",
        "tgn:1000080",
        "tgn:7029392"
    ],
    "tgn:id":7044174,
    "tgn:name":"Frigole",
    "tgn:placetype":[
        "aat:300008347"
    ]
},
  "bbox": [],
  "geometry": {"coordinates":[18.240278,40.425833],"type":"Point"}
}