{
  "id": 2486740,
  "type": "Feature",
  "properties": {
    "tgn:hierarchy":[
        "tgn:2486740",
        "tgn:7002659",
        "tgn:1000001",
        "tgn:7012149",
        "tgn:2000057",
        "tgn:7029392"
    ],
    "tgn:id":2486740,
    "tgn:name":"Lee Branch",
    "tgn:placetype":[
        "aat:300008699"
    ]
},
  "bbox": [],
  "geometry": {"coordinates":[-86.45,33.55],"type":"Point"}
}