{
  "id": 7500017,
  "type": "Feature",
  "properties": {
    "tgn:hierarchy":[
        "tgn:7500017",
        "tgn:1000004",
        "tgn:1000959",
        "tgn:1000141",
        "tgn:7029392"
    ],
    "tgn:id":7500017,
    "tgn:name":"Beitou Guoxiao",
    "tgn:placetype":[
        "aat:300006495"
    ]
},
  "bbox": [],
  "geometry": {"coordinates":[121.499226,25.133498],"type":"Point"}
}