{
  "id": 2167885,
  "type": "Feature",
  "properties": {
    "tgn:hierarchy":[
        "tgn:2167885",
        "tgn:1000001",
        "tgn:7012149",
        "tgn:2000904",
        "tgn:7007256",
        "tgn:7029392"
    ],
    "tgn:id":2167885,
    "tgn:name":"Big Doctors Bayou",
    "tgn:placetype":[
        "aat:300008699"
    ]
},
  "bbox": [],
  "geometry": {"coordinates":[-91.3167,29.5167],"type":"Point"}
}