{
  "id": 7566495,
  "type": "Feature",
  "properties": {
    "tgn:hierarchy":[
        "tgn:7566495",
        "tgn:1000004",
        "tgn:7000198",
        "tgn:1001894",
        "tgn:7029392"
    ],
    "tgn:id":7566495,
    "tgn:name:en":"Ganjpura",
    "tgn:placetype":[
        "aat:300008347"
    ]
},
  "bbox": [],
  "geometry": {"coordinates":[79.076001,24.508273],"type":"Point"}
}