{
  "id": 7342276,
  "type": "Feature",
  "properties": {
    "tgn:hierarchy":[
        "tgn:7342276",
        "tgn:7001158",
        "tgn:7002850",
        "tgn:1000003",
        "tgn:1000095",
        "tgn:7029392"
    ],
    "tgn:id":7342276,
    "tgn:name":"Calzadilla de Tera",
    "tgn:placetype":[
        "aat:300008347"
    ]
},
  "bbox": [],
  "geometry": {"coordinates":[-6.083333,41.983333],"type":"Point"}
}