{
  "id": 7223467,
  "type": "Feature",
  "properties": {
    "tgn:hierarchy":[
        "tgn:7223467",
        "tgn:7002745",
        "tgn:7017076",
        "tgn:1000003",
        "tgn:1000074",
        "tgn:7029392"
    ],
    "tgn:id":7223467,
    "tgn:name":"Oryi\u00e1s, \u00c1kra",
    "tgn:placetype":[
        "aat:300386846"
    ]
},
  "bbox": [],
  "geometry": {"coordinates":[21.883333,36.716667],"type":"Point"}
}