{
  "id": 7491753,
  "type": "Feature",
  "properties": {
    "tgn:hierarchy":[
        "tgn:7491753",
        "tgn:7001010",
        "tgn:1000004",
        "tgn:1000141",
        "tgn:7029392"
    ],
    "tgn:id":7491753,
    "tgn:name":"Beisanzhan",
    "tgn:placetype":[
        "aat:300008347"
    ]
},
  "bbox": [],
  "geometry": {"coordinates":[121.62041,24.10531],"type":"Point"}
}