{
  "id": 2698949,
  "type": "Feature",
  "properties": {
    "tgn:hierarchy":[
        "tgn:2698949",
        "tgn:1000001",
        "tgn:7012149",
        "tgn:1002521",
        "tgn:7007920",
        "tgn:7029392"
    ],
    "tgn:id":2698949,
    "tgn:name":"Strawberry Point",
    "tgn:placetype":[
        "aat:300008850"
    ]
},
  "bbox": [],
  "geometry": {"coordinates":[-124.55,47.8333],"type":"Point"}
}