{
  "id": 2396299,
  "type": "Feature",
  "properties": {
    "tgn:hierarchy":[
        "tgn:2396299",
        "tgn:1000001",
        "tgn:7012149",
        "tgn:2001860",
        "tgn:7007825",
        "tgn:7029392"
    ],
    "tgn:id":2396299,
    "tgn:name":"Holmes Creek",
    "tgn:placetype":[
        "aat:300008706"
    ]
},
  "bbox": [],
  "geometry": {"coordinates":[-89.3333,35.1167],"type":"Point"}
}