{
  "id": 2200563,
  "type": "Feature",
  "properties": {
    "tgn:hierarchy":[
        "tgn:2200563",
        "tgn:1000001",
        "tgn:7012149",
        "tgn:2000839",
        "tgn:7007255",
        "tgn:7029392"
    ],
    "tgn:id":2200563,
    "tgn:name":"Brushy Point",
    "tgn:placetype":[
        "aat:300008798"
    ]
},
  "bbox": [],
  "geometry": {"coordinates":[-84.45,37.1333],"type":"Point"}
}