{
  "id": 2117246,
  "type": "Feature",
  "properties": {
    "tgn:hierarchy":[
        "tgn:2117246",
        "tgn:1000001",
        "tgn:7012149",
        "tgn:2002274",
        "tgn:7013961",
        "tgn:7029392"
    ],
    "tgn:id":2117246,
    "tgn:name":"Anawalt",
    "tgn:placetype":[
        "aat:300008347"
    ]
},
  "bbox": [],
  "geometry": {"coordinates":[-81.4333,37.3333],"type":"Point"}
}