{
  "id": 1067970,
  "type": "Feature",
  "properties": {
    "tgn:hierarchy":[
        "tgn:1067970",
        "tgn:1000004",
        "tgn:1000958",
        "tgn:1000111",
        "tgn:7029392"
    ],
    "tgn:id":1067970,
    "tgn:name":"Fahuaqiao",
    "tgn:placetype":[
        "aat:300008347"
    ]
},
  "bbox": [],
  "geometry": {"coordinates":[121.4333,30.8667],"type":"Point"}
}