{
  "id": 2578462,
  "type": "Feature",
  "properties": {
    "tgn:hierarchy":[
        "tgn:2578462",
        "tgn:2000090",
        "tgn:1000001",
        "tgn:7006451",
        "tgn:7012149",
        "tgn:7029392"
    ],
    "tgn:id":2578462,
    "tgn:name":"Phelps Spring",
    "tgn:placetype":[
        "aat:300008697"
    ]
},
  "bbox": [],
  "geometry": {"coordinates":[-109.4833,33.9167],"type":"Point"}
}