{
  "id": 2376580,
  "type": "Feature",
  "properties": {
    "tgn:hierarchy":[
        "tgn:2376580",
        "tgn:1000001",
        "tgn:7012149",
        "tgn:7007251",
        "tgn:7029392"
    ],
    "tgn:id":2376580,
    "tgn:name":"Hardscrabble Hollow",
    "tgn:placetype":[
        "aat:300008761"
    ]
},
  "bbox": [],
  "geometry": {"coordinates":[-89.4667,40.9833],"type":"Point"}
}