{
  "id": 2658555,
  "type": "Feature",
  "properties": {
    "tgn:hierarchy":[
        "tgn:2658555",
        "tgn:1000001",
        "tgn:7012149",
        "tgn:7014589",
        "tgn:7007515",
        "tgn:7029392"
    ],
    "tgn:id":2658555,
    "tgn:name":"Sherb Brook",
    "tgn:placetype":[
        "aat:300008699"
    ]
},
  "bbox": [],
  "geometry": {"coordinates":[-67.7167,44.7167],"type":"Point"}
}