{
  "id": 7417902,
  "type": "Feature",
  "properties": {
    "tgn:hierarchy":[
        "tgn:7417902",
        "tgn:1000001",
        "tgn:7005596",
        "tgn:7005560",
        "tgn:7029392"
    ],
    "tgn:id":7417902,
    "tgn:name:es":"La Union Primera Secci\u00f3n",
    "tgn:placetype":[
        "aat:300008347"
    ]
},
  "bbox": [],
  "geometry": {"coordinates":[-93.483333,18.441667],"type":"Point"}
}