{
  "id": 1117911,
  "type": "Feature",
  "properties": {
    "tgn:hierarchy":[
        "tgn:1117911",
        "tgn:1000001",
        "tgn:7012149",
        "tgn:1002797",
        "tgn:7007706",
        "tgn:7029392"
    ],
    "tgn:id":1117911,
    "tgn:name":"Rockwell, Lake",
    "tgn:placetype":[
        "aat:300008680"
    ]
},
  "bbox": [],
  "geometry": {"coordinates":[-81.3167,41.1833],"type":"Point"}
}