{
  "id": 2549747,
  "type": "Feature",
  "properties": {
    "tgn:hierarchy":[
        "tgn:2549747",
        "tgn:1000001",
        "tgn:7012149",
        "tgn:2002005",
        "tgn:7007826",
        "tgn:7029392"
    ],
    "tgn:id":2549747,
    "tgn:name":"North Tank",
    "tgn:placetype":[
        "aat:300006191"
    ]
},
  "bbox": [],
  "geometry": {"coordinates":[-105.4333,31.5333],"type":"Point"}
}