{
  "id": 2203356,
  "type": "Feature",
  "properties": {
    "tgn:hierarchy":[
        "tgn:2203356",
        "tgn:1000001",
        "tgn:2001414",
        "tgn:7012149",
        "tgn:7007526",
        "tgn:7029392"
    ],
    "tgn:id":2203356,
    "tgn:name":"Buckhorn Reservoir",
    "tgn:placetype":[
        "aat:300006191"
    ]
},
  "bbox": [],
  "geometry": {"coordinates":[-117.3167,41.5333],"type":"Point"}
}