{
  "id": 2645053,
  "type": "Feature",
  "properties": {
    "tgn:hierarchy":[
        "tgn:2645053",
        "tgn:1000001",
        "tgn:7012149",
        "tgn:2002266",
        "tgn:7013961",
        "tgn:7029392"
    ],
    "tgn:id":2645053,
    "tgn:name":"Sauerkraut Run",
    "tgn:placetype":[
        "aat:300008699"
    ]
},
  "bbox": [],
  "geometry": {"coordinates":[-78.6167,39.1167],"type":"Point"}
}