{
  "id": 7247094,
  "type": "Feature",
  "properties": {
    "tgn:hierarchy":[
        "tgn:7247094",
        "tgn:7003457",
        "tgn:1000003",
        "tgn:1000063",
        "tgn:7018236",
        "tgn:7029392"
    ],
    "tgn:id":7247094,
    "tgn:name":"Doorn",
    "tgn:placetype":[
        "aat:300008347"
    ]
},
  "bbox": [],
  "geometry": {"coordinates":[4.137356,51.211329],"type":"Point"}
}