<<<<<<< HEAD
{
  "id": 7487340,
  "type": "Feature",
  "properties": {
    "tgn:hierarchy":[
        "tgn:7487340",
        "tgn:1000004",
        "tgn:7471332",
        "tgn:1000141",
        "tgn:7029392"
    ],
    "tgn:id":7487340,
    "tgn:name":"Ganliaoping",
    "tgn:placetype":[
        "aat:300008347"
    ]
},
  "bbox": [],
  "geometry": {"coordinates":[121.063889,24.641389],"type":"Point"}
}
=======
{"geometry":{"type":"Point","coordinates":[121.063889,24.641389]},"type":"Feature","properties":{"hierarchy":["tgn:7487340","tgn:1000004","tgn:7471332","tgn:1000141","tgn:7029392"],"placetype":["aat:300008347"],"id":7487340,"name:xx":"Ganliaoping"}}
>>>>>>> 03f74aca74312dbeaf24d7e61306dd6a786dc3d0
