{
  "id": 7279477,
  "type": "Feature",
  "properties": {
    "tgn:hierarchy":[
        "tgn:7279477",
        "tgn:1001708",
        "tgn:1000049",
        "tgn:1000002",
        "tgn:7029392"
    ],
    "tgn:id":7279477,
    "tgn:name":"R\u00edo Blanco, Cerro del",
    "tgn:placetype":[
        "aat:300008795"
    ]
},
  "bbox": [],
  "geometry": {"coordinates":[-70.083333,-34.183333],"type":"Point"}
}