{
  "id": 1043519,
  "type": "Feature",
  "properties": {
    "tgn:hierarchy":[
        "tgn:1043519",
        "tgn:7007850",
        "tgn:1003491",
        "tgn:1000003",
        "tgn:1000080",
        "tgn:7029392"
    ],
    "tgn:id":1043519,
    "tgn:name":"Bivongi",
    "tgn:placetype":[
        "aat:300008347"
    ]
},
  "bbox": [],
  "geometry": {"coordinates":[16.45,38.466667],"type":"Point"}
}