{
  "id": 7519320,
  "type": "Feature",
  "properties": {
    "tgn:hierarchy":[
        "tgn:7519320",
        "tgn:1008380",
        "tgn:1000226",
        "tgn:7000512",
        "tgn:1000006",
        "tgn:7029392"
    ],
    "tgn:id":7519320,
    "tgn:name:en":"Alpha",
    "tgn:placetype":[
        "aat:300008795"
    ]
},
  "bbox": [],
  "geometry": {"coordinates":[175.266667,-40.983333],"type":"Point"}
}