{
  "id": 7545371,
  "type": "Feature",
  "properties": {
    "tgn:hierarchy":[
        "tgn:7545371",
        "tgn:1000004",
        "tgn:7000198",
        "tgn:7016694",
        "tgn:7029392"
    ],
    "tgn:id":7545371,
    "tgn:name:en":"Bari",
    "tgn:placetype":[
        "aat:300008347"
    ]
},
  "bbox": [],
  "geometry": {"coordinates":[86.347174,20.689686],"type":"Point"}
}