{
  "id": 7577099,
  "type": "Feature",
  "properties": {
    "tgn:hierarchy":[
        "tgn:7577099",
        "tgn:1000004",
        "tgn:7000198",
        "tgn:7001797",
        "tgn:7029392"
    ],
    "tgn:id":7577099,
    "tgn:name:en":"Kovilnattam",
    "tgn:placetype":[
        "aat:300008347"
    ]
},
  "bbox": [],
  "geometry": {"coordinates":[77.466667,11.716667],"type":"Point"}
}