{
  "id": 7456890,
  "type": "Feature",
  "properties": {
    "tgn:hierarchy":[
        "tgn:7456890",
        "tgn:7002445",
        "tgn:1000003",
        "tgn:7008174",
        "tgn:7008591",
        "tgn:7029392"
    ],
    "tgn:id":7456890,
    "tgn:name:en":"Pipe Ridware",
    "tgn:placetype":[
        "aat:300008347"
    ]
},
  "bbox": [],
  "geometry": {"coordinates":[-1.833333,52.75],"type":"Point"}
}