<<<<<<< HEAD
{
  "id": 7376353,
  "type": "Feature",
  "properties": {
    "tgn:hierarchy":[
        "tgn:7376353",
        "tgn:7005586",
        "tgn:1000001",
        "tgn:7005560",
        "tgn:7029392"
    ],
    "tgn:id":7376353,
    "tgn:name":"Las Juntas",
    "tgn:placetype":[
        "aat:300266554",
        "aat:300008699"
    ]
},
  "bbox": [],
  "geometry": {"coordinates":[-104.75,21.0],"type":"Point"}
}
=======
{"geometry":{"type":"Point","coordinates":[-104.750000,21.000000]},"type":"Feature","properties":{"hierarchy":["tgn:7376353","tgn:7005586","tgn:1000001","tgn:7005560","tgn:7029392"],"placetype":["aat:300266554","aat:300008699"],"id":7376353,"name:xx":"Las Juntas"}}
>>>>>>> 03f74aca74312dbeaf24d7e61306dd6a786dc3d0
