{
  "id": 7330560,
  "type": "Feature",
  "properties": {
    "tgn:hierarchy":[
        "tgn:7330560",
        "tgn:7002810",
        "tgn:7001158",
        "tgn:1000003",
        "tgn:1000095",
        "tgn:7029392"
    ],
    "tgn:id":7330560,
    "tgn:name":"Herr\u00e1n",
    "tgn:placetype":[
        "aat:300008347"
    ]
},
  "bbox": [],
  "geometry": {"coordinates":[-3.216667,42.816667],"type":"Point"}
}