{
  "id": 2358175,
  "type": "Feature",
  "properties": {
    "tgn:hierarchy":[
        "tgn:2358175",
        "tgn:1000001",
        "tgn:7012149",
        "tgn:2000216",
        "tgn:7007158",
        "tgn:7029392"
    ],
    "tgn:id":2358175,
    "tgn:name":"Granby Mesa",
    "tgn:placetype":[
        "aat:300008798"
    ]
},
  "bbox": [],
  "geometry": {"coordinates":[-105.8833,40.0667],"type":"Point"}
}