<<<<<<< HEAD
{
  "id": 2335815,
  "type": "Feature",
  "properties": {
    "tgn:hierarchy":[
        "tgn:2335815",
        "tgn:1000001",
        "tgn:7006451",
        "tgn:7012149",
        "tgn:2000100",
        "tgn:7029392"
    ],
    "tgn:id":2335815,
    "tgn:name":"Fortynine Wash",
    "tgn:placetype":[
        "aat:300008699"
    ]
},
  "bbox": [],
  "geometry": {"coordinates":[-110.6333,31.8333],"type":"Point"}
}
=======
{"geometry":{"type":"Point","coordinates":[-110.633300,31.833300]},"type":"Feature","properties":{"hierarchy":["tgn:2335815","tgn:1000001","tgn:7006451","tgn:7012149","tgn:2000100","tgn:7029392"],"placetype":["aat:300008699"],"id":2335815,"name:xx":"Fortynine Wash"}}
>>>>>>> 03f74aca74312dbeaf24d7e61306dd6a786dc3d0
