{
  "id": 7476715,
  "type": "Feature",
  "properties": {
    "tgn:hierarchy":[
        "tgn:7476715",
        "tgn:7488858",
        "tgn:1000004",
        "tgn:1000141",
        "tgn:7029392"
    ],
    "tgn:id":7476715,
    "tgn:name":"Yuantong Si",
    "tgn:placetype":[
        "aat:300007595"
    ]
},
  "bbox": [],
  "geometry": {"coordinates":[120.913409,23.987976],"type":"Point"}
}