{
  "id": 2434750,
  "type": "Feature",
  "properties": {
    "tgn:hierarchy":[
        "tgn:2434750",
        "tgn:1000001",
        "tgn:2001176",
        "tgn:7012149",
        "tgn:7007523",
        "tgn:7029392"
    ],
    "tgn:id":2434750,
    "tgn:name":"Kenner Spring Branch",
    "tgn:placetype":[
        "aat:300008699"
    ]
},
  "bbox": [],
  "geometry": {"coordinates":[-90.4667,36.7667],"type":"Point"}
}