<<<<<<< HEAD
{
  "id": 7177238,
  "type": "Feature",
  "properties": {
    "tgn:hierarchy":[
        "tgn:7177238",
        "tgn:1000003",
        "tgn:7003678",
        "tgn:7000084",
        "tgn:7029392"
    ],
    "tgn:id":7177238,
    "tgn:name":"Gustavsburg",
    "tgn:placetype":[
        "aat:300000745"
    ]
},
  "bbox": [],
  "geometry": {"coordinates":[8.336389,50.000278],"type":"Point"}
}
=======
{"geometry":{"type":"Point","coordinates":[8.336389,50.000278]},"type":"Feature","properties":{"hierarchy":["tgn:7177238","tgn:1000003","tgn:7003678","tgn:7000084","tgn:7029392"],"placetype":["aat:300000745"],"id":7177238,"name:xx":"Gustavsburg"}}
>>>>>>> 03f74aca74312dbeaf24d7e61306dd6a786dc3d0
