<<<<<<< HEAD
{
  "id": 2333592,
  "type": "Feature",
  "properties": {
    "tgn:hierarchy":[
        "tgn:2333592",
        "tgn:1000001",
        "tgn:7012149",
        "tgn:7007523",
        "tgn:7029392"
    ],
    "tgn:id":2333592,
    "tgn:name":"Fonso Branch",
    "tgn:placetype":[
        "aat:300008699"
    ]
},
  "bbox": [],
  "geometry": {"coordinates":[-91.7,38.9],"type":"Point"}
}
=======
{"geometry":{"type":"Point","coordinates":[-91.700000,38.900000]},"type":"Feature","properties":{"hierarchy":["tgn:2333592","tgn:1000001","tgn:7012149","tgn:7007523","tgn:7029392"],"placetype":["aat:300008699"],"id":2333592,"name:xx":"Fonso Branch"}}
>>>>>>> 03f74aca74312dbeaf24d7e61306dd6a786dc3d0
