{
  "id": 2442939,
  "type": "Feature",
  "properties": {
    "tgn:hierarchy":[
        "tgn:2442939",
        "tgn:1000001",
        "tgn:2002107",
        "tgn:7012149",
        "tgn:7007827",
        "tgn:7029392"
    ],
    "tgn:id":2442939,
    "tgn:name":"Kuntz Hollow",
    "tgn:placetype":[
        "aat:300008761"
    ]
},
  "bbox": [],
  "geometry": {"coordinates":[-110.45,40.3167],"type":"Point"}
}