{
  "id": 2347205,
  "type": "Feature",
  "properties": {
    "tgn:hierarchy":[
        "tgn:2347205",
        "tgn:1000001",
        "tgn:7006451",
        "tgn:2000093",
        "tgn:7012149",
        "tgn:7029392"
    ],
    "tgn:id":2347205,
    "tgn:name":"Gentry Canyon Spring",
    "tgn:placetype":[
        "aat:300008697"
    ]
},
  "bbox": [],
  "geometry": {"coordinates":[-110.7833,34.0333],"type":"Point"}
}