{
  "id": 2462748,
  "type": "Feature",
  "properties": {
    "tgn:hierarchy":[
        "tgn:2462748",
        "tgn:1000001",
        "tgn:7012149",
        "tgn:2001714",
        "tgn:7007708",
        "tgn:7029392"
    ],
    "tgn:id":2462748,
    "tgn:name":"Little Yamsay Mountain",
    "tgn:placetype":[
        "aat:300008798"
    ]
},
  "bbox": [],
  "geometry": {"coordinates":[-121.4167,42.9833],"type":"Point"}
}