{
  "id": 7516852,
  "type": "Feature",
  "properties": {
    "tgn:hierarchy":[
        "tgn:7516852",
        "tgn:1008380",
        "tgn:7000507",
        "tgn:1000226",
        "tgn:1000006",
        "tgn:7029392"
    ],
    "tgn:id":7516852,
    "tgn:name:en":"Ohaeawai",
    "tgn:placetype":[
        "aat:300008347"
    ]
},
  "bbox": [],
  "geometry": {"coordinates":[173.883333,-35.35],"type":"Point"}
}