{
  "id": 2566615,
  "type": "Feature",
  "properties": {
    "tgn:hierarchy":[
        "tgn:2566615",
        "tgn:1000001",
        "tgn:7012149",
        "tgn:1002564",
        "tgn:7007710",
        "tgn:7029392"
    ],
    "tgn:id":2566615,
    "tgn:name":"Pancoast Creek",
    "tgn:placetype":[
        "aat:300008706"
    ]
},
  "bbox": [],
  "geometry": {"coordinates":[-75.6167,41.45],"type":"Point"}
}