{
  "id": 2382175,
  "type": "Feature",
  "properties": {
    "tgn:hierarchy":[
        "tgn:2382175",
        "tgn:1000001",
        "tgn:7012149",
        "tgn:2001156",
        "tgn:7007522",
        "tgn:7029392"
    ],
    "tgn:id":2382175,
    "tgn:name":"Haynes Branch",
    "tgn:placetype":[
        "aat:300008699"
    ]
},
  "bbox": [],
  "geometry": {"coordinates":[-88.35,34.9333],"type":"Point"}
}