{
  "id": 2573217,
  "type": "Feature",
  "properties": {
    "tgn:hierarchy":[
        "tgn:2573217",
        "tgn:1000001",
        "tgn:2000921",
        "tgn:7012149",
        "tgn:7007515",
        "tgn:7029392"
    ],
    "tgn:id":2573217,
    "tgn:name":"Pease Pond",
    "tgn:placetype":[
        "aat:300008680"
    ]
},
  "bbox": [],
  "geometry": {"coordinates":[-70.1667,44.5833],"type":"Point"}
}