{
  "id": 7546425,
  "type": "Feature",
  "properties": {
    "tgn:hierarchy":[
        "tgn:7546425",
        "tgn:1000004",
        "tgn:7000198",
        "tgn:7016788",
        "tgn:7029392"
    ],
    "tgn:id":7546425,
    "tgn:name:en":"Adamw\u0101la Kera",
    "tgn:placetype":[
        "aat:300008347"
    ]
},
  "bbox": [],
  "geometry": {"coordinates":[72.990525,29.040092],"type":"Point"}
}