{
  "id": 2402867,
  "type": "Feature",
  "properties": {
    "tgn:hierarchy":[
        "tgn:2402867",
        "tgn:1000001",
        "tgn:7012149",
        "tgn:1002758",
        "tgn:7007568",
        "tgn:7029392"
    ],
    "tgn:id":2402867,
    "tgn:name":"Hotel Pond",
    "tgn:placetype":[
        "aat:300008680"
    ]
},
  "bbox": [],
  "geometry": {"coordinates":[-75.9333,43.3667],"type":"Point"}
}