{
  "id": 7567522,
  "type": "Feature",
  "properties": {
    "tgn:hierarchy":[
        "tgn:7567522",
        "tgn:1000004",
        "tgn:7000198",
        "tgn:7001797",
        "tgn:7029392"
    ],
    "tgn:id":7567522,
    "tgn:name:en":"S\u016brappattu",
    "tgn:placetype":[
        "aat:300008347"
    ]
},
  "bbox": [],
  "geometry": {"coordinates":[80.185278,13.141944],"type":"Point"}
}