{
  "id": 7199973,
  "type": "Feature",
  "properties": {
    "tgn:hierarchy":[
        "tgn:7199973",
        "tgn:7003669",
        "tgn:1000003",
        "tgn:7000084",
        "tgn:7029392"
    ],
    "tgn:id":7199973,
    "tgn:name":"Eder",
    "tgn:placetype":[
        "aat:300000206"
    ]
},
  "bbox": [],
  "geometry": {"coordinates":[12.45,48.15],"type":"Point"}
}