{
  "id": 2457086,
  "type": "Feature",
  "properties": {
    "tgn:hierarchy":[
        "tgn:2457086",
        "tgn:1000001",
        "tgn:7012149",
        "tgn:2000883",
        "tgn:7007256",
        "tgn:7029392"
    ],
    "tgn:id":2457086,
    "tgn:name":"Little Lake",
    "tgn:placetype":[
        "aat:300008680"
    ]
},
  "bbox": [],
  "geometry": {"coordinates":[-92.0167,31.5333],"type":"Point"}
}