{
  "id": 2108688,
  "type": "Feature",
  "properties": {
    "tgn:hierarchy":[
        "tgn:2108688",
        "tgn:1000001",
        "tgn:7012149",
        "tgn:2002122",
        "tgn:7007827",
        "tgn:7029392"
    ],
    "tgn:id":2108688,
    "tgn:name":"Atkinson",
    "tgn:placetype":[
        "aat:300387016"
    ]
},
  "bbox": [],
  "geometry": {"coordinates":[-111.4667,40.7333],"type":"Point"}
}