{
  "id": 7553922,
  "type": "Feature",
  "properties": {
    "tgn:hierarchy":[
        "tgn:7553922",
        "tgn:1000004",
        "tgn:7000198",
        "tgn:1001894",
        "tgn:7029392"
    ],
    "tgn:id":7553922,
    "tgn:name:en":"Mau",
    "tgn:placetype":[
        "aat:300008347"
    ]
},
  "bbox": [],
  "geometry": {"coordinates":[78.671083,26.265837],"type":"Point"}
}