{
  "id": 1044755,
  "type": "Feature",
  "properties": {
    "tgn:hierarchy":[
        "tgn:1044755",
        "tgn:1003474",
        "tgn:7004610",
        "tgn:1000003",
        "tgn:1000080",
        "tgn:7029392"
    ],
    "tgn:id":1044755,
    "tgn:name":"Garaguso",
    "tgn:placetype":[
        "aat:300008347"
    ]
},
  "bbox": [],
  "geometry": {"coordinates":[16.233333,40.55],"type":"Point"}
}