{
  "id": 2025820,
  "type": "Feature",
  "properties": {
    "tgn:hierarchy":[
        "tgn:2025820",
        "tgn:1000001",
        "tgn:7012149",
        "tgn:2000474",
        "tgn:7007250",
        "tgn:7029392"
    ],
    "tgn:id":2025820,
    "tgn:name":"Letha",
    "tgn:placetype":[
        "aat:300008347"
    ]
},
  "bbox": [],
  "geometry": {"coordinates":[-116.6333,43.8833],"type":"Point"}
}