{
  "id": 2161722,
  "type": "Feature",
  "properties": {
    "tgn:hierarchy":[
        "tgn:2161722",
        "tgn:7013349",
        "tgn:1000001",
        "tgn:7012149",
        "tgn:7007708",
        "tgn:7029392"
    ],
    "tgn:id":2161722,
    "tgn:name":"Belle of Baker Mine",
    "tgn:placetype":[
        "aat:300000390"
    ]
},
  "bbox": [],
  "geometry": {"coordinates":[-118.25,44.8167],"type":"Point"}
}