<<<<<<< HEAD
{
  "id": 7377629,
  "type": "Feature",
  "properties": {
    "tgn:hierarchy":[
        "tgn:7377629",
        "tgn:1001835",
        "tgn:1000001",
        "tgn:7005560",
        "tgn:7029392"
    ],
    "tgn:id":7377629,
    "tgn:name":"Las Cabras",
    "tgn:placetype":[
        "aat:300008347"
    ]
},
  "bbox": [],
  "geometry": {"coordinates":[-115.85,31.016667],"type":"Point"}
}
=======
{"geometry":{"type":"Point","coordinates":[-115.850000,31.016667]},"type":"Feature","properties":{"hierarchy":["tgn:7377629","tgn:1001835","tgn:1000001","tgn:7005560","tgn:7029392"],"placetype":["aat:300008347"],"id":7377629,"name:xx":"Las Cabras"}}
>>>>>>> 03f74aca74312dbeaf24d7e61306dd6a786dc3d0
