{
  "id": 2041223,
  "type": "Feature",
  "properties": {
    "tgn:hierarchy":[
        "tgn:2041223",
        "tgn:1000001",
        "tgn:7012149",
        "tgn:2000826",
        "tgn:7007255",
        "tgn:7029392"
    ],
    "tgn:id":2041223,
    "tgn:name":"Scranton",
    "tgn:placetype":[
        "aat:300008347"
    ]
},
  "bbox": [],
  "geometry": {"coordinates":[-83.5167,37.9833],"type":"Point"}
}