{
  "id": 2443085,
  "type": "Feature",
  "properties": {
    "tgn:hierarchy":[
        "tgn:2443085",
        "tgn:7023902",
        "tgn:1000001",
        "tgn:7012149",
        "tgn:7007249",
        "tgn:7029392"
    ],
    "tgn:id":2443085,
    "tgn:name":"Kuualii Fishpond",
    "tgn:placetype":[
        "aat:300008680"
    ]
},
  "bbox": [],
  "geometry": {"coordinates":[-155.8833,19.9167],"type":"Point"}
}