{
  "id": 2072398,
  "type": "Feature",
  "properties": {
    "tgn:hierarchy":[
        "tgn:2072398",
        "tgn:1000001",
        "tgn:7012149",
        "tgn:7014318",
        "tgn:7007568",
        "tgn:7029392"
    ],
    "tgn:id":2072398,
    "tgn:name":"South Edmeston",
    "tgn:placetype":[
        "aat:300008347"
    ]
},
  "bbox": [],
  "geometry": {"coordinates":[-75.3167,42.6833],"type":"Point"}
}