{
  "id": 7287072,
  "type": "Feature",
  "properties": {
    "tgn:hierarchy":[
        "tgn:7287072",
        "tgn:1001702",
        "tgn:1000049",
        "tgn:1000002",
        "tgn:7029392"
    ],
    "tgn:id":7287072,
    "tgn:name":"Grau, Caleta",
    "tgn:placetype":[
        "aat:300132317"
    ]
},
  "bbox": [],
  "geometry": {"coordinates":[-74.433333,-49.35],"type":"Point"}
}