{
  "id": 7216429,
  "type": "Feature",
  "properties": {
    "tgn:hierarchy":[
        "tgn:7216429",
        "tgn:1000003",
        "tgn:7000094",
        "tgn:7000084",
        "tgn:7029392"
    ],
    "tgn:id":7216429,
    "tgn:name":"Alt G\u00fcstelitz",
    "tgn:placetype":[
        "aat:300008347"
    ]
},
  "bbox": [],
  "geometry": {"coordinates":[13.433333,54.35],"type":"Point"}
}