{
  "id": 7465941,
  "type": "Feature",
  "properties": {
    "tgn:hierarchy":[
        "tgn:7465941",
        "tgn:7002444",
        "tgn:1000003",
        "tgn:5000451",
        "tgn:7008591",
        "tgn:7029392"
    ],
    "tgn:id":7465941,
    "tgn:name:en":"Ardwell",
    "tgn:placetype":[
        "aat:300008347"
    ]
},
  "bbox": [],
  "geometry": {"coordinates":[-3.05,57.35],"type":"Point"}
}