{
  "id": 7520308,
  "type": "Feature",
  "properties": {
    "tgn:hierarchy":[
        "tgn:7520308",
        "tgn:7001242",
        "tgn:7016833",
        "tgn:1001418",
        "tgn:7029392"
    ],
    "tgn:id":7520308,
    "tgn:name:en":"Ab\u016b \u0162\u0101qah, 'Alam",
    "tgn:placetype":[
        "aat:300008777"
    ]
},
  "bbox": [],
  "geometry": {"coordinates":[28.656745,30.97021],"type":"Point"}
}