{
  "id": 7064903,
  "type": "Feature",
  "properties": {
    "tgn:hierarchy":[
        "tgn:7064903",
        "tgn:1000003",
        "tgn:7000094",
        "tgn:7000084",
        "tgn:7029392"
    ],
    "tgn:id":7064903,
    "tgn:name":"Steinsoll",
    "tgn:placetype":[
        "aat:300008688"
    ]
},
  "bbox": [],
  "geometry": {"coordinates":[12.35,53.366667],"type":"Point"}
}