{
  "id": 7360774,
  "type": "Feature",
  "properties": {
    "tgn:hierarchy":[
        "tgn:7360774",
        "tgn:7016644",
        "tgn:1000001",
        "tgn:7005560",
        "tgn:7029392"
    ],
    "tgn:id":7360774,
    "tgn:name":"Cofrad\u00eda",
    "tgn:placetype":[
        "aat:300008347"
    ]
},
  "bbox": [],
  "geometry": {"coordinates":[-103.55,19.433333],"type":"Point"}
}