{
  "id": 2722832,
  "type": "Feature",
  "properties": {
    "tgn:hierarchy":[
        "tgn:2722832",
        "tgn:1000001",
        "tgn:7012149",
        "tgn:2002123",
        "tgn:7007827",
        "tgn:7029392"
    ],
    "tgn:id":2722832,
    "tgn:name":"Tip Top Mine",
    "tgn:placetype":[
        "aat:300000390"
    ]
},
  "bbox": [],
  "geometry": {"coordinates":[-112.3167,40.45],"type":"Point"}
}