{
  "id": 2051371,
  "type": "Feature",
  "properties": {
    "tgn:hierarchy":[
        "tgn:2051371",
        "tgn:1000001",
        "tgn:7012149",
        "tgn:2000973",
        "tgn:7007520",
        "tgn:7029392"
    ],
    "tgn:id":2051371,
    "tgn:name":"Brevort",
    "tgn:placetype":[
        "aat:300008347"
    ]
},
  "bbox": [],
  "geometry": {"coordinates":[-85.0333,46.0167],"type":"Point"}
}