{
  "id": 2345855,
  "type": "Feature",
  "properties": {
    "tgn:hierarchy":[
        "tgn:2345855",
        "tgn:1000001",
        "tgn:7012149",
        "tgn:7016022",
        "tgn:7007251",
        "tgn:7029392"
    ],
    "tgn:id":2345855,
    "tgn:name":"Gartside",
    "tgn:placetype":[
        "aat:300008347"
    ]
},
  "bbox": [],
  "geometry": {"coordinates":[-90.0333,38.5333],"type":"Point"}
}