{
  "id": 2787076,
  "type": "Feature",
  "properties": {
    "tgn:hierarchy":[
        "tgn:2787076",
        "tgn:1000001",
        "tgn:7012149",
        "tgn:1002581",
        "tgn:7007710",
        "tgn:7029392"
    ],
    "tgn:id":2787076,
    "tgn:name":"Zinns Mill",
    "tgn:placetype":[
        "aat:300008347"
    ]
},
  "bbox": [],
  "geometry": {"coordinates":[-76.4167,40.2833],"type":"Point"}
}