{
  "id": 2411885,
  "type": "Feature",
  "properties": {
    "tgn:hierarchy":[
        "tgn:2411885",
        "tgn:7002659",
        "tgn:1000001",
        "tgn:7012149",
        "tgn:2000035",
        "tgn:7029392"
    ],
    "tgn:id":2411885,
    "tgn:name":"Indian Point",
    "tgn:placetype":[
        "aat:300008850"
    ]
},
  "bbox": [],
  "geometry": {"coordinates":[-85.9333,34.8333],"type":"Point"}
}