{
  "id": 2382695,
  "type": "Feature",
  "properties": {
    "tgn:hierarchy":[
        "tgn:2382695",
        "tgn:1000001",
        "tgn:7012149",
        "tgn:2002375",
        "tgn:7007923",
        "tgn:7029392"
    ],
    "tgn:id":2382695,
    "tgn:name":"Hazard Creek",
    "tgn:placetype":[
        "aat:300008706"
    ]
},
  "bbox": [],
  "geometry": {"coordinates":[-104.9167,41.0833],"type":"Point"}
}