{
  "id": 7501225,
  "type": "Feature",
  "properties": {
    "tgn:hierarchy":[
        "tgn:7501225",
        "tgn:7488858",
        "tgn:1000004",
        "tgn:1000141",
        "tgn:7029392"
    ],
    "tgn:id":7501225,
    "tgn:name":"Shihao Suidao",
    "tgn:placetype":[
        "aat:300007899"
    ]
},
  "bbox": [],
  "geometry": {"coordinates":[120.803889,23.543611],"type":"Point"}
}