{
  "id": 7236333,
  "type": "Feature",
  "properties": {
    "tgn:hierarchy":[
        "tgn:7236333",
        "tgn:7011171",
        "tgn:7001395",
        "tgn:1000003",
        "tgn:1000074",
        "tgn:7029392"
    ],
    "tgn:id":7236333,
    "tgn:name":"\u00c1no Kouro\u00fanion",
    "tgn:placetype":[
        "aat:300008347"
    ]
},
  "bbox": [],
  "geometry": {"coordinates":[24.083333,38.583333],"type":"Point"}
}