{
  "id": 2117049,
  "type": "Feature",
  "properties": {
    "tgn:hierarchy":[
        "tgn:2117049",
        "tgn:1000001",
        "tgn:7012149",
        "tgn:1002899",
        "tgn:7007920",
        "tgn:7029392"
    ],
    "tgn:id":2117049,
    "tgn:name":"Verlot",
    "tgn:placetype":[
        "aat:300008347"
    ]
},
  "bbox": [],
  "geometry": {"coordinates":[-121.7667,48.0833],"type":"Point"}
}