{
  "id": 2161418,
  "type": "Feature",
  "properties": {
    "tgn:hierarchy":[
        "tgn:2161418",
        "tgn:1000001",
        "tgn:7012149",
        "tgn:2001295",
        "tgn:7007524",
        "tgn:7029392"
    ],
    "tgn:id":2161418,
    "tgn:name":"Bell Reservoir",
    "tgn:placetype":[
        "aat:300006191"
    ]
},
  "bbox": [],
  "geometry": {"coordinates":[-108.6333,47.6833],"type":"Point"}
}