{
  "id": 1139074,
  "type": "Feature",
  "properties": {
    "tgn:hierarchy":[
        "tgn:1139074",
        "tgn:1000004",
        "tgn:7002082",
        "tgn:1000111",
        "tgn:7029392"
    ],
    "tgn:id":1139074,
    "tgn:name":"Hengshi",
    "tgn:placetype":[
        "aat:300008347"
    ]
},
  "bbox": [],
  "geometry": {"coordinates":[114.6833,26.05],"type":"Point"}
}