{
  "id": 2098335,
  "type": "Feature",
  "properties": {
    "tgn:hierarchy":[
        "tgn:2098335",
        "tgn:1000001",
        "tgn:7012149",
        "tgn:2001925",
        "tgn:7007825",
        "tgn:7029392"
    ],
    "tgn:id":2098335,
    "tgn:name":"Centertown",
    "tgn:placetype":[
        "aat:300008347"
    ]
},
  "bbox": [],
  "geometry": {"coordinates":[-85.9167,35.7167],"type":"Point"}
}