{
  "id": 7452135,
  "type": "Feature",
  "properties": {
    "tgn:hierarchy":[
        "tgn:7452135",
        "tgn:7019198",
        "tgn:7002448",
        "tgn:1000003",
        "tgn:7008591",
        "tgn:7029392"
    ],
    "tgn:id":7452135,
    "tgn:name:en":"Gransha",
    "tgn:placetype":[
        "aat:300008347"
    ]
},
  "bbox": [],
  "geometry": {"coordinates":[-6.066667,54.316667],"type":"Point"}
}