{
  "id": 2075264,
  "type": "Feature",
  "properties": {
    "tgn:hierarchy":[
        "tgn:2075264",
        "tgn:1000001",
        "tgn:7012149",
        "tgn:2001533",
        "tgn:7007709",
        "tgn:7029392"
    ],
    "tgn:id":2075264,
    "tgn:name":"Jefferson Park",
    "tgn:placetype":[
        "aat:300008347"
    ]
},
  "bbox": [],
  "geometry": {"coordinates":[-79.7833,34.9167],"type":"Point"}
}