<<<<<<< HEAD
{
  "id": 7372780,
  "type": "Feature",
  "properties": {
    "tgn:hierarchy":[
        "tgn:7372780",
        "tgn:1000001",
        "tgn:7005594",
        "tgn:7005560",
        "tgn:7029392"
    ],
    "tgn:id":7372780,
    "tgn:name":"La Cazuela",
    "tgn:placetype":[
        "aat:300008347"
    ]
},
  "bbox": [],
  "geometry": {"coordinates":[-100.35,22.7],"type":"Point"}
}
=======
{"geometry":{"type":"Point","coordinates":[-100.350000,22.700000]},"type":"Feature","properties":{"hierarchy":["tgn:7372780","tgn:1000001","tgn:7005594","tgn:7005560","tgn:7029392"],"placetype":["aat:300008347"],"id":7372780,"name:xx":"La Cazuela"}}
>>>>>>> 03f74aca74312dbeaf24d7e61306dd6a786dc3d0
