{
  "id": 7255994,
  "type": "Feature",
  "properties": {
    "tgn:hierarchy":[
        "tgn:7255994",
        "tgn:7003460",
        "tgn:1000003",
        "tgn:1000063",
        "tgn:4012014",
        "tgn:7029392"
    ],
    "tgn:id":7255994,
    "tgn:name":"Saint-Paul, Bois de",
    "tgn:placetype":[
        "aat:300008863"
    ]
},
  "bbox": [],
  "geometry": {"coordinates":[5.449229,50.573956],"type":"Point"}
}