<<<<<<< HEAD
{
  "id": 2763121,
  "type": "Feature",
  "properties": {
    "tgn:hierarchy":[
        "tgn:2763121",
        "tgn:1000001",
        "tgn:2001413",
        "tgn:7012149",
        "tgn:7007526",
        "tgn:7029392"
    ],
    "tgn:id":2763121,
    "tgn:name":"Westside Ditch",
    "tgn:placetype":[
        "aat:300006075"
    ]
},
  "bbox": [],
  "geometry": {"coordinates":[-116.5,40.6167],"type":"Point"}
}
=======
{"geometry":{"type":"Point","coordinates":[-116.500000,40.616700]},"type":"Feature","properties":{"hierarchy":["tgn:2763121","tgn:1000001","tgn:2001413","tgn:7012149","tgn:7007526","tgn:7029392"],"placetype":["aat:300006075"],"id":2763121,"name:xx":"Westside Ditch"}}
>>>>>>> 03f74aca74312dbeaf24d7e61306dd6a786dc3d0
