{
  "id": 2342224,
  "type": "Feature",
  "properties": {
    "tgn:hierarchy":[
        "tgn:2342224",
        "tgn:1000001",
        "tgn:2001939",
        "tgn:7012149",
        "tgn:7007826",
        "tgn:7029392"
    ],
    "tgn:id":2342224,
    "tgn:name":"Fulda",
    "tgn:placetype":[
        "aat:300008347"
    ]
},
  "bbox": [],
  "geometry": {"coordinates":[-99.0167,33.6833],"type":"Point"}
}