{
  "id": 2359640,
  "type": "Feature",
  "properties": {
    "tgn:hierarchy":[
        "tgn:2359640",
        "tgn:1000001",
        "tgn:2001418",
        "tgn:7012149",
        "tgn:7007526",
        "tgn:7029392"
    ],
    "tgn:id":2359640,
    "tgn:name":"Grantsville Ridge",
    "tgn:placetype":[
        "aat:300266640"
    ]
},
  "bbox": [],
  "geometry": {"coordinates":[-117.5667,38.8167],"type":"Point"}
}