{
  "id": 2550766,
  "type": "Feature",
  "properties": {
    "tgn:hierarchy":[
        "tgn:2550766",
        "tgn:1000001",
        "tgn:7012149",
        "tgn:2000991",
        "tgn:7007520",
        "tgn:7029392"
    ],
    "tgn:id":2550766,
    "tgn:name":"Norway Point",
    "tgn:placetype":[
        "aat:300008850"
    ]
},
  "bbox": [],
  "geometry": {"coordinates":[-84.45,44.35],"type":"Point"}
}