{
  "id": 2682504,
  "type": "Feature",
  "properties": {
    "tgn:hierarchy":[
        "tgn:2682504",
        "tgn:1002996",
        "tgn:1000001",
        "tgn:7012149",
        "tgn:7007711",
        "tgn:7029392"
    ],
    "tgn:id":2682504,
    "tgn:name":"Southeast Point",
    "tgn:placetype":[
        "aat:300008850"
    ]
},
  "bbox": [],
  "geometry": {"coordinates":[-71.5333,41.15],"type":"Point"}
}