<<<<<<< HEAD
{
  "id": 7247383,
  "type": "Feature",
  "properties": {
    "tgn:hierarchy":[
        "tgn:7247383",
        "tgn:7018239",
        "tgn:1000003",
        "tgn:1000063",
        "tgn:7018236",
        "tgn:7029392"
    ],
    "tgn:id":7247383,
    "tgn:name":"Chapelle, Bois de la",
    "tgn:placetype":[
        "aat:300008863"
    ]
},
  "bbox": [],
  "geometry": {"coordinates":[4.931678,50.743212],"type":"Point"}
}
=======
{"geometry":{"type":"Point","coordinates":[4.931678,50.743212]},"type":"Feature","properties":{"hierarchy":["tgn:7247383","tgn:7018239","tgn:1000003","tgn:1000063","tgn:7018236","tgn:7029392"],"placetype":["aat:300008863"],"id":7247383,"name:xx":"Chapelle, Bois de la"}}
>>>>>>> 03f74aca74312dbeaf24d7e61306dd6a786dc3d0
