{
  "id": 7536602,
  "type": "Feature",
  "properties": {
    "tgn:hierarchy":[
        "tgn:7536602",
        "tgn:7001242",
        "tgn:7016833",
        "tgn:1001418",
        "tgn:7029392"
    ],
    "tgn:id":7536602,
    "tgn:name:en":"Giwiy, W\u00e2d\u00ee el-",
    "tgn:placetype":[
        "aat:300379998"
    ]
},
  "bbox": [],
  "geometry": {"coordinates":[29.217088,30.726131],"type":"Point"}
}