{
  "id": 7543432,
  "type": "Feature",
  "properties": {
    "tgn:hierarchy":[
        "tgn:7543432",
        "tgn:7001242",
        "tgn:7016833",
        "tgn:7000123",
        "tgn:7029392"
    ],
    "tgn:id":7543432,
    "tgn:name:en":"Naj' ad Dayr al Qad\u012bm",
    "tgn:placetype":[
        "aat:300008347"
    ]
},
  "bbox": [],
  "geometry": {"coordinates":[32.57163,25.331607],"type":"Point"}
}