{
  "id": 2468251,
  "type": "Feature",
  "properties": {
    "tgn:hierarchy":[
        "tgn:2468251",
        "tgn:1000001",
        "tgn:7006451",
        "tgn:7012149",
        "tgn:2000103",
        "tgn:7029392"
    ],
    "tgn:id":2468251,
    "tgn:name":"Long Mesa Tank",
    "tgn:placetype":[
        "aat:300006191"
    ]
},
  "bbox": [],
  "geometry": {"coordinates":[-111.7333,34.25],"type":"Point"}
}