{
  "id": 2211615,
  "type": "Feature",
  "properties": {
    "tgn:hierarchy":[
        "tgn:2211615",
        "tgn:1000001",
        "tgn:2000201",
        "tgn:7012149",
        "tgn:7007158",
        "tgn:7029392"
    ],
    "tgn:id":2211615,
    "tgn:name":"Buttermilk Gulch",
    "tgn:placetype":[
        "aat:300008761"
    ]
},
  "bbox": [],
  "geometry": {"coordinates":[-105.75,39.75],"type":"Point"}
}