{
  "id": 2749833,
  "type": "Feature",
  "properties": {
    "tgn:hierarchy":[
        "tgn:2749833",
        "tgn:7016099",
        "tgn:1000001",
        "tgn:7012149",
        "tgn:7007516",
        "tgn:7029392"
    ],
    "tgn:id":2749833,
    "tgn:name":"Walnut Point",
    "tgn:placetype":[
        "aat:300008850"
    ]
},
  "bbox": [],
  "geometry": {"coordinates":[-76.45,39.2833],"type":"Point"}
}