{
  "id": 7231023,
  "type": "Feature",
  "properties": {
    "tgn:hierarchy":[
        "tgn:7231023",
        "tgn:7002706",
        "tgn:7002705",
        "tgn:1000003",
        "tgn:1000074",
        "tgn:7029392"
    ],
    "tgn:id":7231023,
    "tgn:name":"Kallon\u00ed",
    "tgn:placetype":[
        "aat:300008347"
    ]
},
  "bbox": [],
  "geometry": {"coordinates":[21.092222,39.353611],"type":"Point"}
}