{
  "id": 7405334,
  "type": "Feature",
  "properties": {
    "tgn:hierarchy":[
        "tgn:7405334",
        "tgn:7005585",
        "tgn:1000001",
        "tgn:7005560",
        "tgn:7029392"
    ],
    "tgn:id":7405334,
    "tgn:name":"El Cajoncito",
    "tgn:placetype":[
        "aat:300008347"
    ]
},
  "bbox": [],
  "geometry": {"coordinates":[-101.433333,17.733333],"type":"Point"}
}