{
  "id": 2216228,
  "type": "Feature",
  "properties": {
    "tgn:hierarchy":[
        "tgn:2216228",
        "tgn:1000001",
        "tgn:2001485",
        "tgn:7012149",
        "tgn:7007709",
        "tgn:7029392"
    ],
    "tgn:id":2216228,
    "tgn:name":"Camp Branch",
    "tgn:placetype":[
        "aat:300008699"
    ]
},
  "bbox": [],
  "geometry": {"coordinates":[-78.7167,34.2667],"type":"Point"}
}