{
  "id": 2613066,
  "type": "Feature",
  "properties": {
    "tgn:hierarchy":[
        "tgn:2613066",
        "tgn:1000001",
        "tgn:7012149",
        "tgn:1002785",
        "tgn:7007920",
        "tgn:7029392"
    ],
    "tgn:id":2613066,
    "tgn:name":"Redstone Peak",
    "tgn:placetype":[
        "aat:300008798"
    ]
},
  "bbox": [],
  "geometry": {"coordinates":[-121.7167,46.95],"type":"Point"}
}