<<<<<<< HEAD
{
  "id": 2409707,
  "type": "Feature",
  "properties": {
    "tgn:hierarchy":[
        "tgn:2409707",
        "tgn:2002101",
        "tgn:1000001",
        "tgn:7012149",
        "tgn:7007827",
        "tgn:7029392"
    ],
    "tgn:id":2409707,
    "tgn:name":"Ikies Spring",
    "tgn:placetype":[
        "aat:300008697"
    ]
},
  "bbox": [],
  "geometry": {"coordinates":[-113.55,38.2833],"type":"Point"}
}
=======
{"geometry":{"type":"Point","coordinates":[-113.550000,38.283300]},"type":"Feature","properties":{"hierarchy":["tgn:2409707","tgn:2002101","tgn:1000001","tgn:7012149","tgn:7007827","tgn:7029392"],"placetype":["aat:300008697"],"id":2409707,"name:xx":"Ikies Spring"}}
>>>>>>> 03f74aca74312dbeaf24d7e61306dd6a786dc3d0
