<<<<<<< HEAD
{
  "id": 2333360,
  "type": "Feature",
  "properties": {
    "tgn:hierarchy":[
        "tgn:2333360",
        "tgn:1000001",
        "tgn:7012149",
        "tgn:1002899",
        "tgn:7007920",
        "tgn:7029392"
    ],
    "tgn:id":2333360,
    "tgn:name":"Foggy Lake",
    "tgn:placetype":[
        "aat:300008680"
    ]
},
  "bbox": [],
  "geometry": {"coordinates":[-121.45,47.9833],"type":"Point"}
}
=======
{"geometry":{"type":"Point","coordinates":[-121.450000,47.983300]},"type":"Feature","properties":{"hierarchy":["tgn:2333360","tgn:1000001","tgn:7012149","tgn:1002899","tgn:7007920","tgn:7029392"],"placetype":["aat:300008680"],"id":2333360,"name:xx":"Foggy Lake"}}
>>>>>>> 03f74aca74312dbeaf24d7e61306dd6a786dc3d0
