{
  "id": 2124728,
  "type": "Feature",
  "properties": {
    "tgn:hierarchy":[
        "tgn:2124728",
        "tgn:1000001",
        "tgn:7012149",
        "tgn:1002688",
        "tgn:7007568",
        "tgn:7029392"
    ],
    "tgn:id":2124728,
    "tgn:name":"Abeel Island",
    "tgn:placetype":[
        "aat:300008791"
    ]
},
  "bbox": [],
  "geometry": {"coordinates":[-74.6167,42.95],"type":"Point"}
}