{
  "id": 2549095,
  "type": "Feature",
  "properties": {
    "tgn:hierarchy":[
        "tgn:2549095",
        "tgn:1000001",
        "tgn:7012149",
        "tgn:2001503",
        "tgn:7007709",
        "tgn:7029392"
    ],
    "tgn:id":2549095,
    "tgn:name":"North Prong Shining Creek",
    "tgn:placetype":[
        "aat:300008706"
    ]
},
  "bbox": [],
  "geometry": {"coordinates":[-82.85,35.35],"type":"Point"}
}