{
  "id": 7233973,
  "type": "Feature",
  "properties": {
    "tgn:hierarchy":[
        "tgn:7233973",
        "tgn:7002680",
        "tgn:7001395",
        "tgn:1000003",
        "tgn:1000074",
        "tgn:7029392"
    ],
    "tgn:id":7233973,
    "tgn:name":"Ay\u00eda, \u00c1kra",
    "tgn:placetype":[
        "aat:300008850"
    ]
},
  "bbox": [],
  "geometry": {"coordinates":[21.75,38.283333],"type":"Point"}
}