<<<<<<< HEAD
{
  "id": 2407973,
  "type": "Feature",
  "properties": {
    "tgn:hierarchy":[
        "tgn:2407973",
        "tgn:1000001",
        "tgn:7012149",
        "tgn:2001503",
        "tgn:7007709",
        "tgn:7029392"
    ],
    "tgn:id":2407973,
    "tgn:name":"Hurricane Creek",
    "tgn:placetype":[
        "aat:300008706"
    ]
},
  "bbox": [],
  "geometry": {"coordinates":[-83.1333,35.5833],"type":"Point"}
}
=======
{"geometry":{"type":"Point","coordinates":[-83.133300,35.583300]},"type":"Feature","properties":{"hierarchy":["tgn:2407973","tgn:1000001","tgn:7012149","tgn:2001503","tgn:7007709","tgn:7029392"],"placetype":["aat:300008706"],"id":2407973,"name:xx":"Hurricane Creek"}}
>>>>>>> 03f74aca74312dbeaf24d7e61306dd6a786dc3d0
