{
  "id": 2229935,
  "type": "Feature",
  "properties": {
    "tgn:hierarchy":[
        "tgn:2229935",
        "tgn:1000001",
        "tgn:2001416",
        "tgn:7012149",
        "tgn:7007526",
        "tgn:7029392"
    ],
    "tgn:id":2229935,
    "tgn:name":"Cedar Wash",
    "tgn:placetype":[
        "aat:300008699"
    ]
},
  "bbox": [],
  "geometry": {"coordinates":[-114.7667,37.4333],"type":"Point"}
}