{
  "id": 2164190,
  "type": "Feature",
  "properties": {
    "tgn:hierarchy":[
        "tgn:2164190",
        "tgn:1000001",
        "tgn:7012149",
        "tgn:2001514",
        "tgn:7007709",
        "tgn:7029392"
    ],
    "tgn:id":2164190,
    "tgn:name":"Bernard Mountain",
    "tgn:placetype":[
        "aat:300008798"
    ]
},
  "bbox": [],
  "geometry": {"coordinates":[-82.2333,35.6333],"type":"Point"}
}