{
  "id": 2760601,
  "type": "Feature",
  "properties": {
    "tgn:hierarchy":[
        "tgn:2760601",
        "tgn:1000001",
        "tgn:7012149",
        "tgn:2001298",
        "tgn:7007524",
        "tgn:7029392"
    ],
    "tgn:id":2760601,
    "tgn:name":"West Fork Wet Cottonwood Creek",
    "tgn:placetype":[
        "aat:300008706"
    ]
},
  "bbox": [],
  "geometry": {"coordinates":[-112.85,46.7167],"type":"Point"}
}