{
  "id": 7069688,
  "type": "Feature",
  "properties": {
    "tgn:hierarchy":[
        "tgn:7069688",
        "tgn:1000003",
        "tgn:7003688",
        "tgn:7000084",
        "tgn:7029392"
    ],
    "tgn:id":7069688,
    "tgn:name":"Tonnenberg",
    "tgn:placetype":[
        "aat:300000206"
    ]
},
  "bbox": [],
  "geometry": {"coordinates":[10.033333,54.416667],"type":"Point"}
}