{
  "id": 7188312,
  "type": "Feature",
  "properties": {
    "tgn:hierarchy":[
        "tgn:7188312",
        "tgn:1000003",
        "tgn:7003676",
        "tgn:7000084",
        "tgn:7029392"
    ],
    "tgn:id":7188312,
    "tgn:name":"Erichshof",
    "tgn:placetype":[
        "aat:300000206"
    ]
},
  "bbox": [],
  "geometry": {"coordinates":[9.633333,52.333333],"type":"Point"}
}