{
  "id": 7427749,
  "type": "Feature",
  "properties": {
    "tgn:hierarchy":[
        "tgn:7427749",
        "tgn:7005581",
        "tgn:1000001",
        "tgn:7005560",
        "tgn:7029392"
    ],
    "tgn:id":7427749,
    "tgn:name":"La Laguna Chiquita",
    "tgn:placetype":[
        "aat:300008347"
    ]
},
  "bbox": [],
  "geometry": {"coordinates":[-107.316667,30.433333],"type":"Point"}
}