<<<<<<< HEAD
{
  "id": 2405838,
  "type": "Feature",
  "properties": {
    "tgn:hierarchy":[
        "tgn:2405838",
        "tgn:1000001",
        "tgn:7006451",
        "tgn:7012149",
        "tgn:2000104",
        "tgn:7029392"
    ],
    "tgn:id":2405838,
    "tgn:name":"Hull Mine",
    "tgn:placetype":[
        "aat:300000390"
    ]
},
  "bbox": [],
  "geometry": {"coordinates":[-114.1667,33.05],"type":"Point"}
}
=======
{"geometry":{"type":"Point","coordinates":[-114.166700,33.050000]},"type":"Feature","properties":{"hierarchy":["tgn:2405838","tgn:1000001","tgn:7006451","tgn:7012149","tgn:2000104","tgn:7029392"],"placetype":["aat:300000390"],"id":2405838,"name:xx":"Hull Mine"}}
>>>>>>> 03f74aca74312dbeaf24d7e61306dd6a786dc3d0
