{
  "id": 2205382,
  "type": "Feature",
  "properties": {
    "tgn:hierarchy":[
        "tgn:2205382",
        "tgn:1000001",
        "tgn:7012149",
        "tgn:7007157",
        "tgn:1002675",
        "tgn:7029392"
    ],
    "tgn:id":2205382,
    "tgn:name":"Bull Creek",
    "tgn:placetype":[
        "aat:300008706"
    ]
},
  "bbox": [],
  "geometry": {"coordinates":[-119.3667,38.2833],"type":"Point"}
}