{
  "id": 7178951,
  "type": "Feature",
  "properties": {
    "tgn:hierarchy":[
        "tgn:7178951",
        "tgn:7003669",
        "tgn:1000003",
        "tgn:7000084",
        "tgn:7029392"
    ],
    "tgn:id":7178951,
    "tgn:name":"Haidenberg",
    "tgn:placetype":[
        "aat:300008347"
    ]
},
  "bbox": [],
  "geometry": {"coordinates":[12.95,48.983333],"type":"Point"}
}