{
  "id": 2598686,
  "type": "Feature",
  "properties": {
    "tgn:hierarchy":[
        "tgn:2598686",
        "tgn:1000001",
        "tgn:7006451",
        "tgn:7012149",
        "tgn:2000104",
        "tgn:7029392"
    ],
    "tgn:id":2598686,
    "tgn:name":"Pride Mine",
    "tgn:placetype":[
        "aat:300000390"
    ]
},
  "bbox": [],
  "geometry": {"coordinates":[-114.0333,34.15],"type":"Point"}
}