<<<<<<< HEAD
{
  "id": 7360239,
  "type": "Feature",
  "properties": {
    "tgn:hierarchy":[
        "tgn:7360239",
        "tgn:1000001",
        "tgn:7005601",
        "tgn:7005560",
        "tgn:7029392"
    ],
    "tgn:id":7360239,
    "tgn:name":"Conos Ojuelos",
    "tgn:placetype":[
        "aat:300008347"
    ]
},
  "bbox": [],
  "geometry": {"coordinates":[-102.733333,23.066667],"type":"Point"}
}
=======
{"geometry":{"type":"Point","coordinates":[-102.733333,23.066667]},"type":"Feature","properties":{"hierarchy":["tgn:7360239","tgn:1000001","tgn:7005601","tgn:7005560","tgn:7029392"],"placetype":["aat:300008347"],"id":7360239,"name:xx":"Conos Ojuelos"}}
>>>>>>> 03f74aca74312dbeaf24d7e61306dd6a786dc3d0
