{
  "id": 1019075,
  "type": "Feature",
  "properties": {
    "tgn:hierarchy":[
        "tgn:1019075",
        "tgn:7017471",
        "tgn:1000001",
        "tgn:7004773",
        "tgn:7029392"
    ],
    "tgn:id":1019075,
    "tgn:name":"Wallibou",
    "tgn:placetype":[
        "aat:300008347"
    ]
},
  "bbox": [],
  "geometry": {"coordinates":[-61.2167,13.3167],"type":"Point"}
}