{
  "id": 7476116,
  "type": "Feature",
  "properties": {
    "tgn:hierarchy":[
        "tgn:7476116",
        "tgn:7488858",
        "tgn:1000004",
        "tgn:1000141",
        "tgn:7029392"
    ],
    "tgn:id":7476116,
    "tgn:name":"Wucheng Qiao",
    "tgn:placetype":[
        "aat:300007836"
    ]
},
  "bbox": [],
  "geometry": {"coordinates":[120.888531,23.887784],"type":"Point"}
}