<<<<<<< HEAD
{
  "id": 7476116,
  "type": "Feature",
  "properties": {
    "tgn:hierarchy":[
        "tgn:7476116",
        "tgn:7488858",
        "tgn:1000004",
        "tgn:1000141",
        "tgn:7029392"
    ],
    "tgn:id":7476116,
    "tgn:name":"Wucheng Qiao",
    "tgn:placetype":[
        "aat:300007836"
    ]
},
  "bbox": [],
  "geometry": {"coordinates":[120.888531,23.887784],"type":"Point"}
}
=======
{"geometry":{"type":"Point","coordinates":[120.888531,23.887784]},"type":"Feature","properties":{"hierarchy":["tgn:7476116","tgn:7488858","tgn:1000004","tgn:1000141","tgn:7029392"],"placetype":["aat:300007836"],"id":7476116,"name:xx":"Wucheng Qiao"}}
>>>>>>> 03f74aca74312dbeaf24d7e61306dd6a786dc3d0
