{
  "id": 7398627,
  "type": "Feature",
  "properties": {
    "tgn:hierarchy":[
        "tgn:7398627",
        "tgn:1000001",
        "tgn:7005593",
        "tgn:7005560",
        "tgn:7029392"
    ],
    "tgn:id":7398627,
    "tgn:name":"San Juan, R\u00edo",
    "tgn:placetype":[
        "aat:300008699"
    ]
},
  "bbox": [],
  "geometry": {"coordinates":[-99.855556,20.540278],"type":"Point"}
}