{
  "id": 7448999,
  "type": "Feature",
  "properties": {
    "tgn:hierarchy":[
        "tgn:7448999",
        "tgn:7002444",
        "tgn:1000003",
        "tgn:7009907",
        "tgn:7008591",
        "tgn:7029392"
    ],
    "tgn:id":7448999,
    "tgn:name:en":"Roost, The",
    "tgn:placetype":[
        "aat:300386114"
    ]
},
  "bbox": [],
  "geometry": {"coordinates":[-2.916667,59.366667],"type":"Point"}
}