{
  "id": 2237844,
  "type": "Feature",
  "properties": {
    "tgn:hierarchy":[
        "tgn:2237844",
        "tgn:7002659",
        "tgn:1000001",
        "tgn:2000018",
        "tgn:7012149",
        "tgn:7029392"
    ],
    "tgn:id":2237844,
    "tgn:name":"Chipco Creek",
    "tgn:placetype":[
        "aat:300008706"
    ]
},
  "bbox": [],
  "geometry": {"coordinates":[-86.2333,33.0167],"type":"Point"}
}