{
  "id": 7503265,
  "type": "Feature",
  "properties": {
    "tgn:hierarchy":[
        "tgn:7503265",
        "tgn:1000004",
        "tgn:7471332",
        "tgn:1000141",
        "tgn:7029392"
    ],
    "tgn:id":7503265,
    "tgn:name":"Xinle Daqiao",
    "tgn:placetype":[
        "aat:300007836"
    ]
},
  "bbox": [],
  "geometry": {"coordinates":[121.249444,24.731389],"type":"Point"}
}