{
  "id": 2394109,
  "type": "Feature",
  "properties": {
    "tgn:hierarchy":[
        "tgn:2394109",
        "tgn:1000001",
        "tgn:2001268",
        "tgn:7012149",
        "tgn:7007524",
        "tgn:7029392"
    ],
    "tgn:id":2394109,
    "tgn:name":"Hogan Creek",
    "tgn:placetype":[
        "aat:300008706"
    ]
},
  "bbox": [],
  "geometry": {"coordinates":[-105.1333,46.3667],"type":"Point"}
}