{
  "id": 2415355,
  "type": "Feature",
  "properties": {
    "tgn:hierarchy":[
        "tgn:2415355",
        "tgn:1000001",
        "tgn:7012149",
        "tgn:2001083",
        "tgn:7007521",
        "tgn:7029392"
    ],
    "tgn:id":2415355,
    "tgn:name":"Island Number Sixtysix",
    "tgn:placetype":[
        "aat:300008791"
    ]
},
  "bbox": [],
  "geometry": {"coordinates":[-91.6833,44.0833],"type":"Point"}
}