{
  "id": 1023457,
  "type": "Feature",
  "properties": {
    "tgn:hierarchy":[
        "tgn:1023457",
        "tgn:1001630",
        "tgn:1000049",
        "tgn:1000002",
        "tgn:7029392"
    ],
    "tgn:id":1023457,
    "tgn:name":"El Tr\u00e1nsito",
    "tgn:placetype":[
        "aat:300008347"
    ]
},
  "bbox": [],
  "geometry": {"coordinates":[-70.2825,-28.880833],"type":"Point"}
}