{
  "id": 7054664,
  "type": "Feature",
  "properties": {
    "tgn:hierarchy":[
        "tgn:7054664",
        "tgn:7003166",
        "tgn:1000003",
        "tgn:7009760",
        "tgn:1000080",
        "tgn:7029392"
    ],
    "tgn:id":7054664,
    "tgn:name":"Ponte Arpiglio",
    "tgn:placetype":[
        "aat:300008347"
    ]
},
  "bbox": [],
  "geometry": {"coordinates":[10.433333,43.666667],"type":"Point"}
}