{
  "id": 7308852,
  "type": "Feature",
  "properties": {
    "tgn:hierarchy":[
        "tgn:7308852",
        "tgn:1001705",
        "tgn:1000049",
        "tgn:1000002",
        "tgn:7029392"
    ],
    "tgn:id":7308852,
    "tgn:name":"Los Treiles",
    "tgn:placetype":[
        "aat:300008347"
    ]
},
  "bbox": [],
  "geometry": {"coordinates":[-72.133333,-34.883333],"type":"Point"}
}