{
  "id": 2503307,
  "type": "Feature",
  "properties": {
    "tgn:hierarchy":[
        "tgn:2503307",
        "tgn:1000001",
        "tgn:7012149",
        "tgn:2002373",
        "tgn:7007923",
        "tgn:7029392"
    ],
    "tgn:id":2503307,
    "tgn:name":"McQueen Spring",
    "tgn:placetype":[
        "aat:300008697"
    ]
},
  "bbox": [],
  "geometry": {"coordinates":[-108.4333,43.5667],"type":"Point"}
}