{
  "id": 1006028,
  "type": "Feature",
  "properties": {
    "tgn:hierarchy":[
        "tgn:1006028",
        "tgn:7000490",
        "tgn:1000006",
        "tgn:7001828",
        "tgn:7029392"
    ],
    "tgn:id":1006028,
    "tgn:name":"Elizabeth Reef",
    "tgn:placetype":[
        "aat:300008793"
    ]
},
  "bbox": [],
  "geometry": {"coordinates":[159.0667,-29.9333],"type":"Point"}
}