{
  "id": 2356744,
  "type": "Feature",
  "properties": {
    "tgn:hierarchy":[
        "tgn:2356744",
        "tgn:1000001",
        "tgn:7012149",
        "tgn:2001823",
        "tgn:7007713",
        "tgn:7029392"
    ],
    "tgn:id":2356744,
    "tgn:name":"Gorman",
    "tgn:placetype":[
        "aat:300008347"
    ]
},
  "bbox": [],
  "geometry": {"coordinates":[-100.0667,44.9167],"type":"Point"}
}