{
  "id": 2432772,
  "type": "Feature",
  "properties": {
    "tgn:hierarchy":[
        "tgn:2432772",
        "tgn:1002338",
        "tgn:1000001",
        "tgn:7012149",
        "tgn:7007516",
        "tgn:7029392"
    ],
    "tgn:id":2432772,
    "tgn:name":"Keenes Ditch",
    "tgn:placetype":[
        "aat:300006075"
    ]
},
  "bbox": [],
  "geometry": {"coordinates":[-76.05,38.4167],"type":"Point"}
}