{
  "id": 2606298,
  "type": "Feature",
  "properties": {
    "tgn:hierarchy":[
        "tgn:2606298",
        "tgn:1000001",
        "tgn:7016172",
        "tgn:2000109",
        "tgn:7012149",
        "tgn:7029392"
    ],
    "tgn:id":2606298,
    "tgn:name":"Rally Hill",
    "tgn:placetype":[
        "aat:300008347"
    ]
},
  "bbox": [],
  "geometry": {"coordinates":[-92.95,36.15],"type":"Point"}
}