{
  "id": 7236016,
  "type": "Feature",
  "properties": {
    "tgn:hierarchy":[
        "tgn:7236016",
        "tgn:7011170",
        "tgn:7002715",
        "tgn:1000003",
        "tgn:1000074",
        "tgn:7029392"
    ],
    "tgn:id":7236016,
    "tgn:name":"\u00c1nthia",
    "tgn:placetype":[
        "aat:300008347"
    ]
},
  "bbox": [],
  "geometry": {"coordinates":[25.983333,40.866667],"type":"Point"}
}