<<<<<<< HEAD
{
  "id": 7470497,
  "type": "Feature",
  "properties": {
    "tgn:hierarchy":[
        "tgn:7470497",
        "tgn:1000004",
        "tgn:7001014",
        "tgn:1000141",
        "tgn:7029392"
    ],
    "tgn:id":7470497,
    "tgn:name":"Jiuzhuang",
    "tgn:placetype":[
        "aat:300008347"
    ]
},
  "bbox": [],
  "geometry": {"coordinates":[120.329345,23.786904],"type":"Point"}
}
=======
{"geometry":{"type":"Point","coordinates":[120.329345,23.786904]},"type":"Feature","properties":{"hierarchy":["tgn:7470497","tgn:1000004","tgn:7001014","tgn:1000141","tgn:7029392"],"placetype":["aat:300008347"],"id":7470497,"name:xx":"Jiuzhuang"}}
>>>>>>> 03f74aca74312dbeaf24d7e61306dd6a786dc3d0
