{
  "id": 2481211,
  "type": "Feature",
  "properties": {
    "tgn:hierarchy":[
        "tgn:2481211",
        "tgn:1000001",
        "tgn:7012149",
        "tgn:1002296",
        "tgn:7007157",
        "tgn:7029392"
    ],
    "tgn:id":2481211,
    "tgn:name":"Lambert Hill",
    "tgn:placetype":[
        "aat:300008798"
    ]
},
  "bbox": [],
  "geometry": {"coordinates":[-122.4333,39.2167],"type":"Point"}
}