{
  "id": 2427268,
  "type": "Feature",
  "properties": {
    "tgn:hierarchy":[
        "tgn:2427268",
        "tgn:1000001",
        "tgn:7012149",
        "tgn:2000653",
        "tgn:7007253",
        "tgn:7029392"
    ],
    "tgn:id":2427268,
    "tgn:name":"Jordan Creek",
    "tgn:placetype":[
        "aat:300008706"
    ]
},
  "bbox": [],
  "geometry": {"coordinates":[-93.2833,40.8167],"type":"Point"}
}