{
  "id": 2473175,
  "type": "Feature",
  "properties": {
    "tgn:hierarchy":[
        "tgn:2473175",
        "tgn:1000001",
        "tgn:7012149",
        "tgn:2002300",
        "tgn:7013961",
        "tgn:7029392"
    ],
    "tgn:id":2473175,
    "tgn:name":"Lower Aaron Run",
    "tgn:placetype":[
        "aat:300008699"
    ]
},
  "bbox": [],
  "geometry": {"coordinates":[-80.3333,38.5167],"type":"Point"}
}