{
  "id": 2557835,
  "type": "Feature",
  "properties": {
    "tgn:hierarchy":[
        "tgn:2557835",
        "tgn:7013349",
        "tgn:1000001",
        "tgn:7012149",
        "tgn:7007708",
        "tgn:7029392"
    ],
    "tgn:id":2557835,
    "tgn:name":"Old Settlers Slough",
    "tgn:placetype":[
        "aat:300008699"
    ]
},
  "bbox": [],
  "geometry": {"coordinates":[-117.8167,44.75],"type":"Point"}
}