{
  "id": 7319432,
  "type": "Feature",
  "properties": {
    "tgn:hierarchy":[
        "tgn:7319432",
        "tgn:7002464",
        "tgn:1000049",
        "tgn:1000002",
        "tgn:7029392"
    ],
    "tgn:id":7319432,
    "tgn:name":"Altos del Huasco, Cord\u00f3n",
    "tgn:placetype":[
        "aat:300008777"
    ]
},
  "bbox": [],
  "geometry": {"coordinates":[-68.866667,-20.233333],"type":"Point"}
}