{
  "id": 1083477,
  "type": "Feature",
  "properties": {
    "tgn:hierarchy":[
        "tgn:1083477",
        "tgn:1000004",
        "tgn:7002462",
        "tgn:1000133",
        "tgn:7029392"
    ],
    "tgn:id":1083477,
    "tgn:name":"Hala",
    "tgn:placetype":[
        "aat:300008347"
    ]
},
  "bbox": [],
  "geometry": {"coordinates":[68.4667,25.7833],"type":"Point"}
}