{
  "id": 1071941,
  "type": "Feature",
  "properties": {
    "tgn:hierarchy":[
        "tgn:1071941",
        "tgn:1000004",
        "tgn:7001745",
        "tgn:1000111",
        "tgn:7029392"
    ],
    "tgn:id":1071941,
    "tgn:name":"Sitai",
    "tgn:placetype":[
        "aat:300008347"
    ]
},
  "bbox": [],
  "geometry": {"coordinates":[77.9333,39.3833],"type":"Point"}
}