{
  "id": 7586676,
  "type": "Feature",
  "properties": {
    "tgn:hierarchy":[
        "tgn:7586676",
        "tgn:1000004",
        "tgn:7000198",
        "tgn:7000799",
        "tgn:7029392"
    ],
    "tgn:id":7586676,
    "tgn:name:en":"Haddan N\u0101r",
    "tgn:placetype":[
        "aat:300008699"
    ]
},
  "bbox": [],
  "geometry": {"coordinates":[74.088766,34.316519],"type":"Point"}
}