<<<<<<< HEAD
{
  "id": 2158915,
  "type": "Feature",
  "properties": {
    "tgn:hierarchy":[
        "tgn:2158915",
        "tgn:1000001",
        "tgn:2000461",
        "tgn:7012149",
        "tgn:7007250",
        "tgn:7029392"
    ],
    "tgn:id":2158915,
    "tgn:name":"Beckman Ditch",
    "tgn:placetype":[
        "aat:300006075"
    ]
},
  "bbox": [],
  "geometry": {"coordinates":[-112.1167,43.5],"type":"Point"}
}
=======
{"geometry":{"type":"Point","coordinates":[-112.116700,43.500000]},"type":"Feature","properties":{"hierarchy":["tgn:2158915","tgn:1000001","tgn:2000461","tgn:7012149","tgn:7007250","tgn:7029392"],"placetype":["aat:300006075"],"id":2158915,"name:xx":"Beckman Ditch"}}
>>>>>>> 03f74aca74312dbeaf24d7e61306dd6a786dc3d0
