{
  "id": 1064639,
  "type": "Feature",
  "properties": {
    "tgn:hierarchy":[
        "tgn:1064639",
        "tgn:7002443",
        "tgn:7017242",
        "tgn:1000003",
        "tgn:7008591",
        "tgn:7029392"
    ],
    "tgn:id":1064639,
    "tgn:name":"Devil's Bridge",
    "tgn:placetype":[
        "aat:300008347"
    ]
},
  "bbox": [],
  "geometry": {"coordinates":[-3.85,52.35],"type":"Point"}
}