{
  "id": 7282903,
  "type": "Feature",
  "properties": {
    "tgn:hierarchy":[
        "tgn:7282903",
        "tgn:1001695",
        "tgn:1000049",
        "tgn:1000002",
        "tgn:7029392"
    ],
    "tgn:id":7282903,
    "tgn:name":"Peladero, Cerro",
    "tgn:placetype":[
        "aat:300008795"
    ]
},
  "bbox": [],
  "geometry": {"coordinates":[-71.233333,-34.483333],"type":"Point"}
}