{
  "id": 2377288,
  "type": "Feature",
  "properties": {
    "tgn:hierarchy":[
        "tgn:2377288",
        "tgn:7002659",
        "tgn:1000001",
        "tgn:7012149",
        "tgn:2000035",
        "tgn:7029392"
    ],
    "tgn:id":2377288,
    "tgn:name":"Harmony Branch",
    "tgn:placetype":[
        "aat:300008699"
    ]
},
  "bbox": [],
  "geometry": {"coordinates":[-86.05,34.5167],"type":"Point"}
}