{
  "id": 2153041,
  "type": "Feature",
  "properties": {
    "tgn:hierarchy":[
        "tgn:2153041",
        "tgn:1000001",
        "tgn:1002712",
        "tgn:7012149",
        "tgn:7007159",
        "tgn:7029392"
    ],
    "tgn:id":2153041,
    "tgn:name":"Beacon Hill",
    "tgn:placetype":[
        "aat:300008798"
    ]
},
  "bbox": [],
  "geometry": {"coordinates":[-72.85,41.2667],"type":"Point"}
}