<<<<<<< HEAD
{
  "id": 2153041,
  "type": "Feature",
  "properties": {
    "tgn:hierarchy":[
        "tgn:2153041",
        "tgn:1000001",
        "tgn:1002712",
        "tgn:7012149",
        "tgn:7007159",
        "tgn:7029392"
    ],
    "tgn:id":2153041,
    "tgn:name":"Beacon Hill",
    "tgn:placetype":[
        "aat:300008798"
    ]
},
  "bbox": [],
  "geometry": {"coordinates":[-72.85,41.2667],"type":"Point"}
}
=======
{"geometry":{"type":"Point","coordinates":[-72.850000,41.266700]},"type":"Feature","properties":{"hierarchy":["tgn:2153041","tgn:1000001","tgn:1002712","tgn:7012149","tgn:7007159","tgn:7029392"],"placetype":["aat:300008798"],"id":2153041,"name:xx":"Beacon Hill"}}
>>>>>>> 03f74aca74312dbeaf24d7e61306dd6a786dc3d0
