{
  "id": 7158588,
  "type": "Feature",
  "properties": {
    "tgn:hierarchy":[
        "tgn:7158588",
        "tgn:7003669",
        "tgn:1000003",
        "tgn:7000084",
        "tgn:7029392"
    ],
    "tgn:id":7158588,
    "tgn:name":"Hochgschirr",
    "tgn:placetype":[
        "aat:300259572"
    ]
},
  "bbox": [],
  "geometry": {"coordinates":[13.033333,47.533333],"type":"Point"}
}