<<<<<<< HEAD
{
  "id": 2250747,
  "type": "Feature",
  "properties": {
    "tgn:hierarchy":[
        "tgn:2250747",
        "tgn:1000001",
        "tgn:7012149",
        "tgn:2000476",
        "tgn:7007250",
        "tgn:7029392"
    ],
    "tgn:id":2250747,
    "tgn:name":"Colt Killed Creek",
    "tgn:placetype":[
        "aat:300008706"
    ]
},
  "bbox": [],
  "geometry": {"coordinates":[-114.4167,46.4333],"type":"Point"}
}
=======
{"geometry":{"type":"Point","coordinates":[-114.416700,46.433300]},"type":"Feature","properties":{"hierarchy":["tgn:2250747","tgn:1000001","tgn:7012149","tgn:2000476","tgn:7007250","tgn:7029392"],"placetype":["aat:300008706"],"id":2250747,"name:xx":"Colt Killed Creek"}}
>>>>>>> 03f74aca74312dbeaf24d7e61306dd6a786dc3d0
