{
  "id": 2328889,
  "type": "Feature",
  "properties": {
    "tgn:hierarchy":[
        "tgn:2328889",
        "tgn:1000001",
        "tgn:7012149",
        "tgn:2001190",
        "tgn:7007523",
        "tgn:7029392"
    ],
    "tgn:id":2328889,
    "tgn:name":"Fishing Spring",
    "tgn:placetype":[
        "aat:300008697"
    ]
},
  "bbox": [],
  "geometry": {"coordinates":[-91.3833,37.9833],"type":"Point"}
}