{
  "id": 2579991,
  "type": "Feature",
  "properties": {
    "tgn:hierarchy":[
        "tgn:2579991",
        "tgn:7006450",
        "tgn:1000001",
        "tgn:7012149",
        "tgn:2000082",
        "tgn:7029392"
    ],
    "tgn:id":2579991,
    "tgn:name":"Piedras Island",
    "tgn:placetype":[
        "aat:300008791"
    ]
},
  "bbox": [],
  "geometry": {"coordinates":[-133.2833,55.55],"type":"Point"}
}