{
  "id": 7572857,
  "type": "Feature",
  "properties": {
    "tgn:hierarchy":[
        "tgn:7572857",
        "tgn:1000004",
        "tgn:1001869",
        "tgn:7000198",
        "tgn:7029392"
    ],
    "tgn:id":7572857,
    "tgn:name:en":"Humani Point",
    "tgn:placetype":[
        "aat:300386846"
    ]
},
  "bbox": [],
  "geometry": {"coordinates":[69.053333,22.471667],"type":"Point"}
}