{
  "id": 7445433,
  "type": "Feature",
  "properties": {
    "tgn:hierarchy":[
        "tgn:7445433",
        "tgn:7002443",
        "tgn:1000003",
        "tgn:7018993",
        "tgn:7008591",
        "tgn:7029392"
    ],
    "tgn:id":7445433,
    "tgn:name:en":"Star",
    "tgn:placetype":[
        "aat:300008347"
    ]
},
  "bbox": [],
  "geometry": {"coordinates":[-4.557778,51.986389],"type":"Point"}
}