<<<<<<< HEAD
{
  "id": 2256037,
  "type": "Feature",
  "properties": {
    "tgn:hierarchy":[
        "tgn:2256037",
        "tgn:1000001",
        "tgn:7012149",
        "tgn:2002125",
        "tgn:7007827",
        "tgn:7029392"
    ],
    "tgn:id":2256037,
    "tgn:name":"Copper Leaf",
    "tgn:placetype":[
        "aat:300000390"
    ]
},
  "bbox": [],
  "geometry": {"coordinates":[-112.05,39.9667],"type":"Point"}
}
=======
{"geometry":{"type":"Point","coordinates":[-112.050000,39.966700]},"type":"Feature","properties":{"hierarchy":["tgn:2256037","tgn:1000001","tgn:7012149","tgn:2002125","tgn:7007827","tgn:7029392"],"placetype":["aat:300000390"],"id":2256037,"name:xx":"Copper Leaf"}}
>>>>>>> 03f74aca74312dbeaf24d7e61306dd6a786dc3d0
