<<<<<<< HEAD
{
  "id": 7055003,
  "type": "Feature",
  "properties": {
    "tgn:hierarchy":[
        "tgn:7055003",
        "tgn:7015163",
        "tgn:1000003",
        "tgn:7003121",
        "tgn:1000080",
        "tgn:7029392"
    ],
    "tgn:id":7055003,
    "tgn:name":"Liscia, Porto",
    "tgn:placetype":[
        "aat:300132316"
    ]
},
  "bbox": [],
  "geometry": {"coordinates":[9.3,41.2],"type":"Point"}
}
=======
{"geometry":{"type":"Point","coordinates":[9.300000,41.200000]},"type":"Feature","properties":{"hierarchy":["tgn:7055003","tgn:7015163","tgn:1000003","tgn:7003121","tgn:1000080","tgn:7029392"],"placetype":["aat:300132316"],"id":7055003,"name:xx":"Liscia, Porto"}}
>>>>>>> 03f74aca74312dbeaf24d7e61306dd6a786dc3d0
