{
  "id": 7424234,
  "type": "Feature",
  "properties": {
    "tgn:hierarchy":[
        "tgn:7424234",
        "tgn:1000001",
        "tgn:1001906",
        "tgn:7005560",
        "tgn:7029392"
    ],
    "tgn:id":7424234,
    "tgn:name":"La Pesca",
    "tgn:placetype":[
        "aat:300008680"
    ]
},
  "bbox": [],
  "geometry": {"coordinates":[-105.282778,22.068333],"type":"Point"}
}