{
  "id": 7296280,
  "type": "Feature",
  "properties": {
    "tgn:hierarchy":[
        "tgn:7296280",
        "tgn:7002824",
        "tgn:1000003",
        "tgn:7002786",
        "tgn:1000095",
        "tgn:7029392"
    ],
    "tgn:id":7296280,
    "tgn:name":"Los Curbeiros de Mi\u00f1o, Punta de",
    "tgn:placetype":[
        "aat:300386846"
    ]
},
  "bbox": [],
  "geometry": {"coordinates":[-8.218056,43.354167],"type":"Point"}
}