{
  "id": 2511046,
  "type": "Feature",
  "properties": {
    "tgn:hierarchy":[
        "tgn:2511046",
        "tgn:1002933",
        "tgn:1000001",
        "tgn:7012149",
        "tgn:7007239",
        "tgn:7029392"
    ],
    "tgn:id":2511046,
    "tgn:name":"Midway Estates",
    "tgn:placetype":[
        "aat:300008347"
    ]
},
  "bbox": [],
  "geometry": {"coordinates":[-75.15,38.7333],"type":"Point"}
}