{
  "id": 2244636,
  "type": "Feature",
  "properties": {
    "tgn:hierarchy":[
        "tgn:2244636",
        "tgn:1000001",
        "tgn:2001174",
        "tgn:7012149",
        "tgn:7007523",
        "tgn:7029392"
    ],
    "tgn:id":2244636,
    "tgn:name":"Clippard",
    "tgn:placetype":[
        "aat:300008347"
    ]
},
  "bbox": [],
  "geometry": {"coordinates":[-89.8667,37.2667],"type":"Point"}
}