{
  "id": 7149060,
  "type": "Feature",
  "properties": {
    "tgn:hierarchy":[
        "tgn:7149060",
        "tgn:7000096",
        "tgn:1000003",
        "tgn:7000084",
        "tgn:7029392"
    ],
    "tgn:id":7149060,
    "tgn:name":"Kummersdorf",
    "tgn:placetype":[
        "aat:300008347"
    ]
},
  "bbox": [],
  "geometry": {"coordinates":[13.866667,52.266667],"type":"Point"}
}