{
  "id": 7260356,
  "type": "Feature",
  "properties": {
    "tgn:hierarchy":[
        "tgn:7260356",
        "tgn:1000003",
        "tgn:7003622",
        "tgn:7016845",
        "tgn:7029392"
    ],
    "tgn:id":7260356,
    "tgn:name:nl":"Hoeve Erklo",
    "tgn:placetype":[
        "aat:300000206"
    ]
},
  "bbox": [],
  "geometry": {"coordinates":[5.95,51.383333],"type":"Point"}
}