{
  "id": 2421292,
  "type": "Feature",
  "properties": {
    "tgn:hierarchy":[
        "tgn:2421292",
        "tgn:1000001",
        "tgn:7012149",
        "tgn:2002069",
        "tgn:7007826",
        "tgn:7029392"
    ],
    "tgn:id":2421292,
    "tgn:name":"Jerrys Branch",
    "tgn:placetype":[
        "aat:300008699"
    ]
},
  "bbox": [],
  "geometry": {"coordinates":[-98.75,31.3167],"type":"Point"}
}