{
  "id": 2512486,
  "type": "Feature",
  "properties": {
    "tgn:hierarchy":[
        "tgn:2512486",
        "tgn:1000001",
        "tgn:7012149",
        "tgn:7007157",
        "tgn:1002684",
        "tgn:7029392"
    ],
    "tgn:id":2512486,
    "tgn:name":"Mill Creek",
    "tgn:placetype":[
        "aat:300008706"
    ]
},
  "bbox": [],
  "geometry": {"coordinates":[-121.4167,35.9667],"type":"Point"}
}