{
  "id": 7398017,
  "type": "Feature",
  "properties": {
    "tgn:hierarchy":[
        "tgn:7398017",
        "tgn:1000001",
        "tgn:1001960",
        "tgn:7005560",
        "tgn:7029392"
    ],
    "tgn:id":7398017,
    "tgn:name":"Ancha, Ca\u00f1ada",
    "tgn:placetype":[
        "aat:300008773"
    ]
},
  "bbox": [],
  "geometry": {"coordinates":[-111.488333,30.965],"type":"Point"}
}