<<<<<<< HEAD
{
  "id": 2706536,
  "type": "Feature",
  "properties": {
    "tgn:hierarchy":[
        "tgn:2706536",
        "tgn:1000001",
        "tgn:7012149",
        "tgn:7016022",
        "tgn:7007251",
        "tgn:7029392"
    ],
    "tgn:id":2706536,
    "tgn:name":"Swan Lake",
    "tgn:placetype":[
        "aat:300008680"
    ]
},
  "bbox": [],
  "geometry": {"coordinates":[-89.7167,38.4],"type":"Point"}
}
=======
{"geometry":{"type":"Point","coordinates":[-89.716700,38.400000]},"type":"Feature","properties":{"hierarchy":["tgn:2706536","tgn:1000001","tgn:7012149","tgn:7016022","tgn:7007251","tgn:7029392"],"placetype":["aat:300008680"],"id":2706536,"name:xx":"Swan Lake"}}
>>>>>>> 03f74aca74312dbeaf24d7e61306dd6a786dc3d0
