<<<<<<< HEAD
{
  "id": 7020510,
  "type": "Feature",
  "properties": {
    "tgn:hierarchy":[
        "tgn:7020510",
        "tgn:1000001",
        "tgn:7012149",
        "tgn:2001548",
        "tgn:7007709",
        "tgn:7029392"
    ],
    "tgn:id":7020510,
    "tgn:name":"Johnson, Lake",
    "tgn:placetype":[
        "aat:300006191"
    ]
},
  "bbox": [],
  "geometry": {"coordinates":[-78.3333,35.7833],"type":"Point"}
}
=======
{"geometry":{"type":"Point","coordinates":[-78.333300,35.783300]},"type":"Feature","properties":{"hierarchy":["tgn:7020510","tgn:1000001","tgn:7012149","tgn:2001548","tgn:7007709","tgn:7029392"],"placetype":["aat:300006191"],"id":7020510,"name:xx":"Johnson, Lake"}}
>>>>>>> 03f74aca74312dbeaf24d7e61306dd6a786dc3d0
