{
  "id": 7243093,
  "type": "Feature",
  "properties": {
    "tgn:hierarchy":[
        "tgn:7243093",
        "tgn:7003457",
        "tgn:1000003",
        "tgn:1000063",
        "tgn:7018236",
        "tgn:7029392"
    ],
    "tgn:id":7243093,
    "tgn:name":"Maalbroek",
    "tgn:placetype":[
        "aat:300008347"
    ]
},
  "bbox": [],
  "geometry": {"coordinates":[3.883333,50.983333],"type":"Point"}
}