<<<<<<< HEAD
{
  "id": 7378006,
  "type": "Feature",
  "properties": {
    "tgn:hierarchy":[
        "tgn:7378006",
        "tgn:7005580",
        "tgn:1000001",
        "tgn:7005560",
        "tgn:7029392"
    ],
    "tgn:id":7378006,
    "tgn:name":"La Ponzo\u00f1a",
    "tgn:placetype":[
        "aat:300008347"
    ]
},
  "bbox": [],
  "geometry": {"coordinates":[-92.8,15.35],"type":"Point"}
}
=======
{"geometry":{"type":"Point","coordinates":[-92.800000,15.350000]},"type":"Feature","properties":{"hierarchy":["tgn:7378006","tgn:7005580","tgn:1000001","tgn:7005560","tgn:7029392"],"placetype":["aat:300008347"],"id":7378006,"name:xx":"La Ponzo\u00f1a"}}
>>>>>>> 03f74aca74312dbeaf24d7e61306dd6a786dc3d0
