<<<<<<< HEAD
{
  "id": 7173798,
  "type": "Feature",
  "properties": {
    "tgn:hierarchy":[
        "tgn:7173798",
        "tgn:7003692",
        "tgn:1000003",
        "tgn:7000084",
        "tgn:7029392"
    ],
    "tgn:id":7173798,
    "tgn:name":"Gr\u00fcndel",
    "tgn:placetype":[
        "aat:300386970"
    ]
},
  "bbox": [],
  "geometry": {"coordinates":[9.4,47.666667],"type":"Point"}
}
=======
{"geometry":{"type":"Point","coordinates":[9.400000,47.666667]},"type":"Feature","properties":{"hierarchy":["tgn:7173798","tgn:7003692","tgn:1000003","tgn:7000084","tgn:7029392"],"placetype":["aat:300386970"],"id":7173798,"name:xx":"Gr\u00fcndel"}}
>>>>>>> 03f74aca74312dbeaf24d7e61306dd6a786dc3d0
