{
  "id": 7283533,
  "type": "Feature",
  "properties": {
    "tgn:hierarchy":[
        "tgn:7283533",
        "tgn:7016598",
        "tgn:1000049",
        "tgn:1000002",
        "tgn:7029392"
    ],
    "tgn:id":7283533,
    "tgn:name":"Pampa Blanca, Salar de",
    "tgn:placetype":[
        "aat:300386871"
    ]
},
  "bbox": [],
  "geometry": {"coordinates":[-69.433333,-23.066667],"type":"Point"}
}