{
  "id": 2686171,
  "type": "Feature",
  "properties": {
    "tgn:hierarchy":[
        "tgn:2686171",
        "tgn:1000001",
        "tgn:2001266",
        "tgn:7012149",
        "tgn:7007524",
        "tgn:7029392"
    ],
    "tgn:id":2686171,
    "tgn:name":"Spring Coulee",
    "tgn:placetype":[
        "aat:300008761"
    ]
},
  "bbox": [],
  "geometry": {"coordinates":[-111.35,47.0667],"type":"Point"}
}