{
  "id": 2227152,
  "type": "Feature",
  "properties": {
    "tgn:hierarchy":[
        "tgn:2227152",
        "tgn:1000001",
        "tgn:7012149",
        "tgn:2000486",
        "tgn:7007250",
        "tgn:7029392"
    ],
    "tgn:id":2227152,
    "tgn:name":"Cave Gulch",
    "tgn:placetype":[
        "aat:300008761"
    ]
},
  "bbox": [],
  "geometry": {"coordinates":[-116.8333,46.0167],"type":"Point"}
}