{
  "id": 7582946,
  "type": "Feature",
  "properties": {
    "tgn:hierarchy":[
        "tgn:7582946",
        "tgn:1000004",
        "tgn:7000198",
        "tgn:1001894",
        "tgn:7029392"
    ],
    "tgn:id":7582946,
    "tgn:name:en":"Garhaul\u012bdh\u012braj Khurd",
    "tgn:placetype":[
        "aat:300008347"
    ]
},
  "bbox": [],
  "geometry": {"coordinates":[78.453886,24.108487],"type":"Point"}
}