<<<<<<< HEAD
{
  "id": 7243998,
  "type": "Feature",
  "properties": {
    "tgn:hierarchy":[
        "tgn:7243998",
        "tgn:7007877",
        "tgn:1000003",
        "tgn:1000063",
        "tgn:4012014",
        "tgn:7029392"
    ],
    "tgn:id":7243998,
    "tgn:name":"Ferme Jean Meuse",
    "tgn:placetype":[
        "aat:300000206"
    ]
},
  "bbox": [],
  "geometry": {"coordinates":[4.233333,50.616667],"type":"Point"}
}
=======
{"geometry":{"type":"Point","coordinates":[4.233333,50.616667]},"type":"Feature","properties":{"hierarchy":["tgn:7243998","tgn:7007877","tgn:1000003","tgn:1000063","tgn:4012014","tgn:7029392"],"placetype":["aat:300000206"],"id":7243998,"name:xx":"Ferme Jean Meuse"}}
>>>>>>> 03f74aca74312dbeaf24d7e61306dd6a786dc3d0
