{
  "id": 2461671,
  "type": "Feature",
  "properties": {
    "tgn:hierarchy":[
        "tgn:2461671",
        "tgn:1000001",
        "tgn:7016172",
        "tgn:7012149",
        "tgn:7029392"
    ],
    "tgn:id":2461671,
    "tgn:name":"Little Terre Rouge Creek",
    "tgn:placetype":[
        "aat:300008706"
    ]
},
  "bbox": [],
  "geometry": {"coordinates":[-93.4833,33.75],"type":"Point"}
}