{
  "id": 2696462,
  "type": "Feature",
  "properties": {
    "tgn:hierarchy":[
        "tgn:2696462",
        "tgn:1000001",
        "tgn:7012149",
        "tgn:2001609",
        "tgn:7007705",
        "tgn:7029392"
    ],
    "tgn:id":2696462,
    "tgn:name":"Stone Johnny Coulee",
    "tgn:placetype":[
        "aat:300008761"
    ]
},
  "bbox": [],
  "geometry": {"coordinates":[-103.1667,48.2167],"type":"Point"}
}