{
  "id": 2308708,
  "type": "Feature",
  "properties": {
    "tgn:hierarchy":[
        "tgn:2308708",
        "tgn:1000001",
        "tgn:7012149",
        "tgn:7007515",
        "tgn:7029392"
    ],
    "tgn:id":2308708,
    "tgn:name":"East Penobscot Bay",
    "tgn:placetype":[
        "aat:300132316"
    ]
},
  "bbox": [],
  "geometry": {"coordinates":[-68.7333,44.1333],"type":"Point"}
}