{
  "id": 7129879,
  "type": "Feature",
  "properties": {
    "tgn:hierarchy":[
        "tgn:7129879",
        "tgn:7003692",
        "tgn:1000003",
        "tgn:7000084",
        "tgn:7029392"
    ],
    "tgn:id":7129879,
    "tgn:name":"Marzell",
    "tgn:placetype":[
        "aat:300008347"
    ]
},
  "bbox": [],
  "geometry": {"coordinates":[7.716667,47.766667],"type":"Point"}
}