{
  "id": 7099726,
  "type": "Feature",
  "properties": {
    "tgn:hierarchy":[
        "tgn:7099726",
        "tgn:1000003",
        "tgn:7003687",
        "tgn:7000084",
        "tgn:7029392"
    ],
    "tgn:id":7099726,
    "tgn:name":"Spickendorf",
    "tgn:placetype":[
        "aat:300008347"
    ]
},
  "bbox": [],
  "geometry": {"coordinates":[12.133333,51.55],"type":"Point"}
}