<<<<<<< HEAD
{
  "id": 7365537,
  "type": "Feature",
  "properties": {
    "tgn:hierarchy":[
        "tgn:7365537",
        "tgn:1000001",
        "tgn:7005597",
        "tgn:7005560",
        "tgn:7029392"
    ],
    "tgn:id":7365537,
    "tgn:name":"El Realito",
    "tgn:placetype":[
        "aat:300008347"
    ]
},
  "bbox": [],
  "geometry": {"coordinates":[-97.65,25.95],"type":"Point"}
}
=======
{"geometry":{"type":"Point","coordinates":[-97.650000,25.950000]},"type":"Feature","properties":{"hierarchy":["tgn:7365537","tgn:1000001","tgn:7005597","tgn:7005560","tgn:7029392"],"placetype":["aat:300008347"],"id":7365537,"name:xx":"El Realito"}}
>>>>>>> 03f74aca74312dbeaf24d7e61306dd6a786dc3d0
