{
  "id": 2438458,
  "type": "Feature",
  "properties": {
    "tgn:hierarchy":[
        "tgn:2438458",
        "tgn:1000001",
        "tgn:7012149",
        "tgn:1002862",
        "tgn:7007920",
        "tgn:7029392"
    ],
    "tgn:id":2438458,
    "tgn:name":"Kings Point",
    "tgn:placetype":[
        "aat:300008850"
    ]
},
  "bbox": [],
  "geometry": {"coordinates":[-122.9333,48.45],"type":"Point"}
}