{
  "id": 1054877,
  "type": "Feature",
  "properties": {
    "tgn:hierarchy":[
        "tgn:1054877",
        "tgn:1000004",
        "tgn:7011628",
        "tgn:7014835",
        "tgn:7029392"
    ],
    "tgn:id":1054877,
    "tgn:name":"Kayrakkum",
    "tgn:placetype":[
        "aat:300008347"
    ]
},
  "bbox": [],
  "geometry": {"coordinates":[69.8833,40.2167],"type":"Point"}
}