{
  "id": 2292260,
  "type": "Feature",
  "properties": {
    "tgn:hierarchy":[
        "tgn:2292260",
        "tgn:1000001",
        "tgn:7012149",
        "tgn:1002418",
        "tgn:7007920",
        "tgn:7029392"
    ],
    "tgn:id":2292260,
    "tgn:name":"Donkey Creek",
    "tgn:placetype":[
        "aat:300008706"
    ]
},
  "bbox": [],
  "geometry": {"coordinates":[-123.75,47.35],"type":"Point"}
}