{
  "id": 7203501,
  "type": "Feature",
  "properties": {
    "tgn:hierarchy":[
        "tgn:7203501",
        "tgn:1000003",
        "tgn:7003689",
        "tgn:7000084",
        "tgn:7029392"
    ],
    "tgn:id":7203501,
    "tgn:name":"Br\u00fcnn",
    "tgn:placetype":[
        "aat:300008347"
    ]
},
  "bbox": [],
  "geometry": {"coordinates":[10.85,50.45],"type":"Point"}
}