{
  "id": 2185883,
  "type": "Feature",
  "properties": {
    "tgn:hierarchy":[
        "tgn:2185883",
        "tgn:1000001",
        "tgn:7012149",
        "tgn:2000831",
        "tgn:7007255",
        "tgn:7029392"
    ],
    "tgn:id":2185883,
    "tgn:name":"Bolin Ridge",
    "tgn:placetype":[
        "aat:300266640"
    ]
},
  "bbox": [],
  "geometry": {"coordinates":[-83.1667,37.9167],"type":"Point"}
}