{
  "id": 1107812,
  "type": "Feature",
  "properties": {
    "tgn:hierarchy":[
        "tgn:1107812",
        "tgn:7016696",
        "tgn:1000004",
        "tgn:7000894",
        "tgn:1000120",
        "tgn:7029392"
    ],
    "tgn:id":1107812,
    "tgn:name":"\u014ckusu-yama",
    "tgn:placetype":[
        "aat:300008777"
    ]
},
  "bbox": [],
  "geometry": {"coordinates":[139.6333,35.25],"type":"Point"}
}