{
  "id": 2712710,
  "type": "Feature",
  "properties": {
    "tgn:hierarchy":[
        "tgn:2712710",
        "tgn:1000001",
        "tgn:2000459",
        "tgn:7012149",
        "tgn:7007250",
        "tgn:7029392"
    ],
    "tgn:id":2712710,
    "tgn:name":"Taylor Creek",
    "tgn:placetype":[
        "aat:300008706"
    ]
},
  "bbox": [],
  "geometry": {"coordinates":[-115.3333,43.9667],"type":"Point"}
}