<<<<<<< HEAD
{
  "id": 2339348,
  "type": "Feature",
  "properties": {
    "tgn:hierarchy":[
        "tgn:2339348",
        "tgn:1000001",
        "tgn:2001430",
        "tgn:7012149",
        "tgn:7007566",
        "tgn:7029392"
    ],
    "tgn:id":2339348,
    "tgn:name":"Frazier",
    "tgn:placetype":[
        "aat:300008347"
    ]
},
  "bbox": [],
  "geometry": {"coordinates":[-104.3167,33.5833],"type":"Point"}
}
=======
{"geometry":{"type":"Point","coordinates":[-104.316700,33.583300]},"type":"Feature","properties":{"hierarchy":["tgn:2339348","tgn:1000001","tgn:2001430","tgn:7012149","tgn:7007566","tgn:7029392"],"placetype":["aat:300008347"],"id":2339348,"name:xx":"Frazier"}}
>>>>>>> 03f74aca74312dbeaf24d7e61306dd6a786dc3d0
