{
  "id": 2145803,
  "type": "Feature",
  "properties": {
    "tgn:hierarchy":[
        "tgn:2145803",
        "tgn:1000001",
        "tgn:7012149",
        "tgn:1002554",
        "tgn:7007920",
        "tgn:7029392"
    ],
    "tgn:id":2145803,
    "tgn:name":"Baldy Peak",
    "tgn:placetype":[
        "aat:300008798"
    ]
},
  "bbox": [],
  "geometry": {"coordinates":[-121.5167,45.8167],"type":"Point"}
}