{
  "id": 7317954,
  "type": "Feature",
  "properties": {
    "tgn:hierarchy":[
        "tgn:7317954",
        "tgn:1001630",
        "tgn:1000049",
        "tgn:1000002",
        "tgn:7029392"
    ],
    "tgn:id":7317954,
    "tgn:name":"Cinchado, Morro",
    "tgn:placetype":[
        "aat:300008795"
    ]
},
  "bbox": [],
  "geometry": {"coordinates":[-70.133333,-27.833333],"type":"Point"}
}