{
  "id": 7040056,
  "type": "Feature",
  "properties": {
    "tgn:hierarchy":[
        "tgn:7040056",
        "tgn:7003168",
        "tgn:1000003",
        "tgn:7009760",
        "tgn:1000080",
        "tgn:7029392"
    ],
    "tgn:id":7040056,
    "tgn:name":"Schiantone, Fosso",
    "tgn:placetype":[
        "aat:300008699"
    ]
},
  "bbox": [],
  "geometry": {"coordinates":[11.783333,42.933333],"type":"Point"}
}