{
  "id": 2502367,
  "type": "Feature",
  "properties": {
    "tgn:hierarchy":[
        "tgn:2502367",
        "tgn:1000001",
        "tgn:2000469",
        "tgn:7012149",
        "tgn:7007250",
        "tgn:7029392"
    ],
    "tgn:id":2502367,
    "tgn:name":"McKinnon Creek",
    "tgn:placetype":[
        "aat:300008706"
    ]
},
  "bbox": [],
  "geometry": {"coordinates":[-116.05,46.5667],"type":"Point"}
}