<<<<<<< HEAD
{
  "id": 2159351,
  "type": "Feature",
  "properties": {
    "tgn:hierarchy":[
        "tgn:2159351",
        "tgn:1000001",
        "tgn:7006451",
        "tgn:2000093",
        "tgn:7012149",
        "tgn:7029392"
    ],
    "tgn:id":2159351,
    "tgn:name":"Bee Canyon",
    "tgn:placetype":[
        "aat:300008761"
    ]
},
  "bbox": [],
  "geometry": {"coordinates":[-110.7667,33.7167],"type":"Point"}
}
=======
{"geometry":{"type":"Point","coordinates":[-110.766700,33.716700]},"type":"Feature","properties":{"hierarchy":["tgn:2159351","tgn:1000001","tgn:7006451","tgn:2000093","tgn:7012149","tgn:7029392"],"placetype":["aat:300008761"],"id":2159351,"name:xx":"Bee Canyon"}}
>>>>>>> 03f74aca74312dbeaf24d7e61306dd6a786dc3d0
