{
  "id": 2275905,
  "type": "Feature",
  "properties": {
    "tgn:hierarchy":[
        "tgn:2275905",
        "tgn:7006450",
        "tgn:1000001",
        "tgn:2124012",
        "tgn:7012149",
        "tgn:7029392"
    ],
    "tgn:id":2275905,
    "tgn:name":"Dark Island",
    "tgn:placetype":[
        "aat:300008791"
    ]
},
  "bbox": [],
  "geometry": {"coordinates":[-152.5333,58.6333],"type":"Point"}
}