{
  "id": 2778234,
  "type": "Feature",
  "properties": {
    "tgn:hierarchy":[
        "tgn:2778234",
        "tgn:1000001",
        "tgn:7012149",
        "tgn:2001900",
        "tgn:7007825",
        "tgn:7029392"
    ],
    "tgn:id":2778234,
    "tgn:name":"Wiseman Spring",
    "tgn:placetype":[
        "aat:300008697"
    ]
},
  "bbox": [],
  "geometry": {"coordinates":[-86.35,35.2167],"type":"Point"}
}