{
  "id": 2609615,
  "type": "Feature",
  "properties": {
    "tgn:hierarchy":[
        "tgn:2609615",
        "tgn:1000001",
        "tgn:7012149",
        "tgn:2001437",
        "tgn:7007566",
        "tgn:7029392"
    ],
    "tgn:id":2609615,
    "tgn:name":"Rays Tank",
    "tgn:placetype":[
        "aat:300006191"
    ]
},
  "bbox": [],
  "geometry": {"coordinates":[-107.95,32.9667],"type":"Point"}
}