{
  "id": 7235037,
  "type": "Feature",
  "properties": {
    "tgn:hierarchy":[
        "tgn:7235037",
        "tgn:7002681",
        "tgn:7001395",
        "tgn:1000003",
        "tgn:1000074",
        "tgn:7029392"
    ],
    "tgn:id":7235037,
    "tgn:name":"Foni\u00e1s, Nis\u00eds",
    "tgn:placetype":[
        "aat:300008791"
    ]
},
  "bbox": [],
  "geometry": {"coordinates":[24.15,38.183333],"type":"Point"}
}