{
  "id": 2367649,
  "type": "Feature",
  "properties": {
    "tgn:hierarchy":[
        "tgn:2367649",
        "tgn:1000001",
        "tgn:1002270",
        "tgn:7012149",
        "tgn:7007708",
        "tgn:7029392"
    ],
    "tgn:id":2367649,
    "tgn:name":"Grouse Point",
    "tgn:placetype":[
        "aat:300008798"
    ]
},
  "bbox": [],
  "geometry": {"coordinates":[-122.0167,45.15],"type":"Point"}
}