{
  "id": 2480207,
  "type": "Feature",
  "properties": {
    "tgn:hierarchy":[
        "tgn:2480207",
        "tgn:1000001",
        "tgn:1002714",
        "tgn:7012149",
        "tgn:7007159",
        "tgn:7029392"
    ],
    "tgn:id":2480207,
    "tgn:name":"Lake Of Isles Brook",
    "tgn:placetype":[
        "aat:300008699"
    ]
},
  "bbox": [],
  "geometry": {"coordinates":[-71.95,41.4833],"type":"Point"}
}