<<<<<<< HEAD
{
  "id": 7486985,
  "type": "Feature",
  "properties": {
    "tgn:hierarchy":[
        "tgn:7486985",
        "tgn:1000004",
        "tgn:7490934",
        "tgn:1000141",
        "tgn:7029392"
    ],
    "tgn:id":7486985,
    "tgn:name":"Linfengying",
    "tgn:placetype":[
        "aat:300008347"
    ]
},
  "bbox": [],
  "geometry": {"coordinates":[120.319625,23.24237],"type":"Point"}
}
=======
{"geometry":{"type":"Point","coordinates":[120.319625,23.242370]},"type":"Feature","properties":{"hierarchy":["tgn:7486985","tgn:1000004","tgn:7490934","tgn:1000141","tgn:7029392"],"placetype":["aat:300008347"],"id":7486985,"name:xx":"Linfengying"}}
>>>>>>> 03f74aca74312dbeaf24d7e61306dd6a786dc3d0
