{
  "id": 7468910,
  "type": "Feature",
  "properties": {
    "tgn:hierarchy":[
        "tgn:7468910",
        "tgn:1000004",
        "tgn:7467799",
        "tgn:1000141",
        "tgn:7029392"
    ],
    "tgn:id":7468910,
    "tgn:name":"Xiushuicuo",
    "tgn:placetype":[
        "aat:300008347"
    ]
},
  "bbox": [],
  "geometry": {"coordinates":[120.426944,24.033333],"type":"Point"}
}