{
  "id": 7163082,
  "type": "Feature",
  "properties": {
    "tgn:hierarchy":[
        "tgn:7163082",
        "tgn:1000003",
        "tgn:7003676",
        "tgn:7000084",
        "tgn:7029392"
    ],
    "tgn:id":7163082,
    "tgn:name":"In den Dieven",
    "tgn:placetype":[
        "aat:300008901"
    ]
},
  "bbox": [],
  "geometry": {"coordinates":[8.133333,52.466667],"type":"Point"}
}