{
  "id": 2668059,
  "type": "Feature",
  "properties": {
    "tgn:hierarchy":[
        "tgn:2668059",
        "tgn:1000001",
        "tgn:7012149",
        "tgn:7007920",
        "tgn:7029392"
    ],
    "tgn:id":2668059,
    "tgn:name":"Skykomish Ranger District",
    "tgn:placetype":[
        "aat:300008863"
    ]
},
  "bbox": [],
  "geometry": {"coordinates":[-121.25,47.8333],"type":"Point"}
}