{
  "id": 2250281,
  "type": "Feature",
  "properties": {
    "tgn:hierarchy":[
        "tgn:2250281",
        "tgn:1000001",
        "tgn:7012149",
        "tgn:7007157",
        "tgn:2000189",
        "tgn:7029392"
    ],
    "tgn:id":2250281,
    "tgn:name":"Collins Spring",
    "tgn:placetype":[
        "aat:300008697"
    ]
},
  "bbox": [],
  "geometry": {"coordinates":[-122.5667,41.9833],"type":"Point"}
}