{
  "id": 2439549,
  "type": "Feature",
  "properties": {
    "tgn:hierarchy":[
        "tgn:2439549",
        "tgn:1000001",
        "tgn:7012149",
        "tgn:7007256",
        "tgn:7029392"
    ],
    "tgn:id":2439549,
    "tgn:name":"Kisatchie Bayou",
    "tgn:placetype":[
        "aat:300008699"
    ]
},
  "bbox": [],
  "geometry": {"coordinates":[-93.3167,31.4333],"type":"Point"}
}