{
  "id": 1128782,
  "type": "Feature",
  "properties": {
    "tgn:hierarchy":[
        "tgn:1128782",
        "tgn:1001724",
        "tgn:1000003",
        "tgn:7003121",
        "tgn:1000080",
        "tgn:7029392"
    ],
    "tgn:id":1128782,
    "tgn:name":"Posada",
    "tgn:placetype":[
        "aat:300008707",
        "aat:300008699"
    ]
},
  "bbox": [],
  "geometry": {"coordinates":[9.75,40.65],"type":"Point"}
}