{
  "id": 2738060,
  "type": "Feature",
  "properties": {
    "tgn:hierarchy":[
        "tgn:2738060",
        "tgn:1000001",
        "tgn:2002107",
        "tgn:7012149",
        "tgn:7007827",
        "tgn:7029392"
    ],
    "tgn:id":2738060,
    "tgn:name":"Uintah Canal",
    "tgn:placetype":[
        "aat:300006075"
    ]
},
  "bbox": [],
  "geometry": {"coordinates":[-110.0167,40.4667],"type":"Point"}
}