{
  "id": 1068195,
  "type": "Feature",
  "properties": {
    "tgn:hierarchy":[
        "tgn:1068195",
        "tgn:1000004",
        "tgn:7002081",
        "tgn:1000111",
        "tgn:7029392"
    ],
    "tgn:id":1068195,
    "tgn:name":"Ganyu",
    "tgn:placetype":[
        "aat:300008347"
    ]
},
  "bbox": [],
  "geometry": {"coordinates":[119.1833,34.8667],"type":"Point"}
}