{
  "id": 7376135,
  "type": "Feature",
  "properties": {
    "tgn:hierarchy":[
        "tgn:7376135",
        "tgn:7005581",
        "tgn:1000001",
        "tgn:7005560",
        "tgn:7029392"
    ],
    "tgn:id":7376135,
    "tgn:name":"La Tableta",
    "tgn:placetype":[
        "aat:300008347"
    ]
},
  "bbox": [],
  "geometry": {"coordinates":[-108.216667,27.916667],"type":"Point"}
}