{
  "id": 7265589,
  "type": "Feature",
  "properties": {
    "tgn:hierarchy":[
        "tgn:7265589",
        "tgn:7003614",
        "tgn:1000003",
        "tgn:7016845",
        "tgn:7029392"
    ],
    "tgn:id":7265589,
    "tgn:name:nl":"Hunzebos",
    "tgn:placetype":[
        "aat:300008863"
    ]
},
  "bbox": [],
  "geometry": {"coordinates":[6.866667,52.866667],"type":"Point"}
}