{
  "id": 7489725,
  "type": "Feature",
  "properties": {
    "tgn:hierarchy":[
        "tgn:7489725",
        "tgn:1000004",
        "tgn:7492971",
        "tgn:1000141",
        "tgn:7029392"
    ],
    "tgn:id":7489725,
    "tgn:name":"Pozhugu Shan",
    "tgn:placetype":[
        "aat:300008798"
    ]
},
  "bbox": [],
  "geometry": {"coordinates":[120.816944,22.208056],"type":"Point"}
}