{
  "id": 7008206,
  "type": "Feature",
  "properties": {
    "tgn:hierarchy":[
        "tgn:7008206",
        "tgn:7002871",
        "tgn:1000003",
        "tgn:1000070",
        "tgn:7029392"
    ],
    "tgn:id":7008206,
    "tgn:name":"Saint-Flour",
    "tgn:placetype":[
        "aat:300008347"
    ]
},
  "bbox": [],
  "geometry": {"coordinates":[3.0833,45.0333],"type":"Point"}
}