{
  "id": 7401439,
  "type": "Feature",
  "properties": {
    "tgn:hierarchy":[
        "tgn:7401439",
        "tgn:1000001",
        "tgn:7005599",
        "tgn:7005560",
        "tgn:7029392"
    ],
    "tgn:id":7401439,
    "tgn:name":"Santa F\u00e9",
    "tgn:placetype":[
        "aat:300008347"
    ]
},
  "bbox": [],
  "geometry": {"coordinates":[-94.886111,17.925],"type":"Point"}
}