{
  "id": 1140093,
  "type": "Feature",
  "properties": {
    "tgn:hierarchy":[
        "tgn:1140093",
        "tgn:1000004",
        "tgn:7002076",
        "tgn:1000111",
        "tgn:7029392"
    ],
    "tgn:id":1140093,
    "tgn:name":"Zhukou",
    "tgn:placetype":[
        "aat:300008347"
    ]
},
  "bbox": [],
  "geometry": {"coordinates":[118.8833,27.6833],"type":"Point"}
}