{
  "id": 2077927,
  "type": "Feature",
  "properties": {
    "tgn:hierarchy":[
        "tgn:2077927",
        "tgn:1000001",
        "tgn:2001578",
        "tgn:7012149",
        "tgn:7007705",
        "tgn:7029392"
    ],
    "tgn:id":2077927,
    "tgn:name":"Pettibone",
    "tgn:placetype":[
        "aat:300008347"
    ]
},
  "bbox": [],
  "geometry": {"coordinates":[-99.5167,47.1167],"type":"Point"}
}