{
  "id": 7567187,
  "type": "Feature",
  "properties": {
    "tgn:hierarchy":[
        "tgn:7567187",
        "tgn:1000004",
        "tgn:1001871",
        "tgn:7000198",
        "tgn:7029392"
    ],
    "tgn:id":7567187,
    "tgn:name:en":"Naurang\u0101w\u0101s",
    "tgn:placetype":[
        "aat:300008347"
    ]
},
  "bbox": [],
  "geometry": {"coordinates":[76.09577,28.440283],"type":"Point"}
}