{
  "id": 7580675,
  "type": "Feature",
  "properties": {
    "tgn:hierarchy":[
        "tgn:7580675",
        "tgn:1000004",
        "tgn:7031781",
        "tgn:7000198",
        "tgn:7029392"
    ],
    "tgn:id":7580675,
    "tgn:name:en":"Sulsuli",
    "tgn:placetype":[
        "aat:300008347"
    ]
},
  "bbox": [],
  "geometry": {"coordinates":[83.320603,23.83565],"type":"Point"}
}