{
  "id": 1129422,
  "type": "Feature",
  "properties": {
    "tgn:hierarchy":[
        "tgn:1129422",
        "tgn:7016696",
        "tgn:1000004",
        "tgn:7000894",
        "tgn:1000120",
        "tgn:7029392"
    ],
    "tgn:id":1129422,
    "tgn:name":"Sakawa-gawa",
    "tgn:placetype":[
        "aat:300008707"
    ]
},
  "bbox": [],
  "geometry": {"coordinates":[139.1833,35.25],"type":"Point"}
}