{
  "id": 2220626,
  "type": "Feature",
  "properties": {
    "tgn:hierarchy":[
        "tgn:2220626",
        "tgn:1000001",
        "tgn:7012149",
        "tgn:7014589",
        "tgn:7007515",
        "tgn:7029392"
    ],
    "tgn:id":2220626,
    "tgn:name":"Cape Wash Island",
    "tgn:placetype":[
        "aat:300008791"
    ]
},
  "bbox": [],
  "geometry": {"coordinates":[-67.25,44.6167],"type":"Point"}
}