{
  "id": 7151924,
  "type": "Feature",
  "properties": {
    "tgn:hierarchy":[
        "tgn:7151924",
        "tgn:7003669",
        "tgn:1000003",
        "tgn:7000084",
        "tgn:7029392"
    ],
    "tgn:id":7151924,
    "tgn:name":"Kahl-Berg",
    "tgn:placetype":[
        "aat:300008777"
    ]
},
  "bbox": [],
  "geometry": {"coordinates":[9.783333,49.866667],"type":"Point"}
}