{
  "id": 7314973,
  "type": "Feature",
  "properties": {
    "tgn:hierarchy":[
        "tgn:7314973",
        "tgn:1001702",
        "tgn:1000049",
        "tgn:1000002",
        "tgn:7029392"
    ],
    "tgn:id":7314973,
    "tgn:name":"L\u00edbano, Monte",
    "tgn:placetype":[
        "aat:300008795"
    ]
},
  "bbox": [],
  "geometry": {"coordinates":[-72.45,-53.183333],"type":"Point"}
}