{
  "id": 2186998,
  "type": "Feature",
  "properties": {
    "tgn:hierarchy":[
        "tgn:2186998",
        "tgn:1000001",
        "tgn:7012149",
        "tgn:2002382",
        "tgn:7007923",
        "tgn:7029392"
    ],
    "tgn:id":2186998,
    "tgn:name":"Bonneville Lakes",
    "tgn:placetype":[
        "aat:300008680"
    ]
},
  "bbox": [],
  "geometry": {"coordinates":[-109.3333,42.8667],"type":"Point"}
}