{
  "id": 2732716,
  "type": "Feature",
  "properties": {
    "tgn:hierarchy":[
        "tgn:2732716",
        "tgn:1000001",
        "tgn:7012149",
        "tgn:1002627",
        "tgn:7007706",
        "tgn:7029392"
    ],
    "tgn:id":2732716,
    "tgn:name":"Turkey Creek",
    "tgn:placetype":[
        "aat:300008706"
    ]
},
  "bbox": [],
  "geometry": {"coordinates":[-80.7333,40.9667],"type":"Point"}
}