{
  "id": 2712279,
  "type": "Feature",
  "properties": {
    "tgn:hierarchy":[
        "tgn:2712279",
        "tgn:1000001",
        "tgn:7012149",
        "tgn:1003038",
        "tgn:7007517",
        "tgn:7029392"
    ],
    "tgn:id":2712279,
    "tgn:name":"Tatnuck Brook",
    "tgn:placetype":[
        "aat:300008699"
    ]
},
  "bbox": [],
  "geometry": {"coordinates":[-71.8667,42.3167],"type":"Point"}
}