{
  "id": 2281796,
  "type": "Feature",
  "properties": {
    "tgn:hierarchy":[
        "tgn:2281796",
        "tgn:1000001",
        "tgn:7012149",
        "tgn:2001821",
        "tgn:7007713",
        "tgn:7029392"
    ],
    "tgn:id":2281796,
    "tgn:name":"Deer Creek",
    "tgn:placetype":[
        "aat:300008706"
    ]
},
  "bbox": [],
  "geometry": {"coordinates":[-103.55,44.1167],"type":"Point"}
}