{
  "id": 1068546,
  "type": "Feature",
  "properties": {
    "tgn:hierarchy":[
        "tgn:1068546",
        "tgn:1000004",
        "tgn:7002076",
        "tgn:1000111",
        "tgn:7029392"
    ],
    "tgn:id":1068546,
    "tgn:name":"Haining",
    "tgn:placetype":[
        "aat:300008347"
    ]
},
  "bbox": [],
  "geometry": {"coordinates":[120.5833,30.5167],"type":"Point"}
}