{
  "id": 7523039,
  "type": "Feature",
  "properties": {
    "tgn:hierarchy":[
        "tgn:7523039",
        "tgn:7001242",
        "tgn:7016833",
        "tgn:1001418",
        "tgn:7029392"
    ],
    "tgn:id":7523039,
    "tgn:name:en":"Diqn\u0101sh, Buwayb",
    "tgn:placetype":[
        "aat:300259572"
    ]
},
  "bbox": [],
  "geometry": {"coordinates":[25.35,30.466667],"type":"Point"}
}