{
  "id": 7315564,
  "type": "Feature",
  "properties": {
    "tgn:hierarchy":[
        "tgn:7315564",
        "tgn:1001695",
        "tgn:1000049",
        "tgn:1000002",
        "tgn:7029392"
    ],
    "tgn:id":7315564,
    "tgn:name":"Chada Chico, Cerro",
    "tgn:placetype":[
        "aat:300008795"
    ]
},
  "bbox": [],
  "geometry": {"coordinates":[-70.65,-33.933333],"type":"Point"}
}