{
  "id": 7063845,
  "type": "Feature",
  "properties": {
    "tgn:hierarchy":[
        "tgn:7063845",
        "tgn:1000003",
        "tgn:7003677",
        "tgn:7000084",
        "tgn:7029392"
    ],
    "tgn:id":7063845,
    "tgn:name":"Antfeld",
    "tgn:placetype":[
        "aat:300008347"
    ]
},
  "bbox": [],
  "geometry": {"coordinates":[8.466667,51.366667],"type":"Point"}
}