<<<<<<< HEAD
{
  "id": 2402026,
  "type": "Feature",
  "properties": {
    "tgn:hierarchy":[
        "tgn:2402026",
        "tgn:1000001",
        "tgn:7012149",
        "tgn:2001461",
        "tgn:7007568",
        "tgn:7029392"
    ],
    "tgn:id":2402026,
    "tgn:name":"Horseshoe Pond",
    "tgn:placetype":[
        "aat:300008680"
    ]
},
  "bbox": [],
  "geometry": {"coordinates":[-73.8,43.8167],"type":"Point"}
}
=======
{"geometry":{"type":"Point","coordinates":[-73.800000,43.816700]},"type":"Feature","properties":{"hierarchy":["tgn:2402026","tgn:1000001","tgn:7012149","tgn:2001461","tgn:7007568","tgn:7029392"],"placetype":["aat:300008680"],"id":2402026,"name:xx":"Horseshoe Pond"}}
>>>>>>> 03f74aca74312dbeaf24d7e61306dd6a786dc3d0
