{
  "id": 2431136,
  "type": "Feature",
  "properties": {
    "tgn:hierarchy":[
        "tgn:2431136",
        "tgn:1000001",
        "tgn:7012149",
        "tgn:7007523",
        "tgn:7029392"
    ],
    "tgn:id":2431136,
    "tgn:name":"Kansas City Urban Region",
    "tgn:placetype":[
        "aat:300055621"
    ]
},
  "bbox": [],
  "geometry": {"coordinates":[-94.6167,38.8667],"type":"Point"}
}