{
  "id": 7493450,
  "type": "Feature",
  "properties": {
    "tgn:hierarchy":[
        "tgn:7493450",
        "tgn:7468018",
        "tgn:1000004",
        "tgn:1000141",
        "tgn:7029392"
    ],
    "tgn:id":7493450,
    "tgn:name":"Minhe Guozhong",
    "tgn:placetype":[
        "aat:300006495"
    ]
},
  "bbox": [],
  "geometry": {"coordinates":[120.555587,23.465275],"type":"Point"}
}