<<<<<<< HEAD
{
  "id": 2156382,
  "type": "Feature",
  "properties": {
    "tgn:hierarchy":[
        "tgn:2156382",
        "tgn:1000001",
        "tgn:2002320",
        "tgn:7012149",
        "tgn:7007922",
        "tgn:7029392"
    ],
    "tgn:id":2156382,
    "tgn:name":"Bears Grass Creek",
    "tgn:placetype":[
        "aat:300008706"
    ]
},
  "bbox": [],
  "geometry": {"coordinates":[-91.2167,44.6],"type":"Point"}
}
=======
{"geometry":{"type":"Point","coordinates":[-91.216700,44.600000]},"type":"Feature","properties":{"hierarchy":["tgn:2156382","tgn:1000001","tgn:2002320","tgn:7012149","tgn:7007922","tgn:7029392"],"placetype":["aat:300008706"],"id":2156382,"name:xx":"Bears Grass Creek"}}
>>>>>>> 03f74aca74312dbeaf24d7e61306dd6a786dc3d0
