{
  "id": 2205116,
  "type": "Feature",
  "properties": {
    "tgn:hierarchy":[
        "tgn:2205116",
        "tgn:1000001",
        "tgn:7012149",
        "tgn:2000928",
        "tgn:7007515",
        "tgn:7029392"
    ],
    "tgn:id":2205116,
    "tgn:name":"Buker Mountain",
    "tgn:placetype":[
        "aat:300008798"
    ]
},
  "bbox": [],
  "geometry": {"coordinates":[-69.3167,45.2167],"type":"Point"}
}