{
  "id": 2552032,
  "type": "Feature",
  "properties": {
    "tgn:hierarchy":[
        "tgn:2552032",
        "tgn:1000001",
        "tgn:7006451",
        "tgn:2000092",
        "tgn:7012149",
        "tgn:7029392"
    ],
    "tgn:id":2552032,
    "tgn:name":"Number Fourteen, Tank",
    "tgn:placetype":[
        "aat:300006191"
    ]
},
  "bbox": [],
  "geometry": {"coordinates":[-112.8167,35.9333],"type":"Point"}
}