{
  "id": 7096838,
  "type": "Feature",
  "properties": {
    "tgn:hierarchy":[
        "tgn:7096838",
        "tgn:7003692",
        "tgn:1000003",
        "tgn:7000084",
        "tgn:7029392"
    ],
    "tgn:id":7096838,
    "tgn:name":"S\u00f6hlbach",
    "tgn:placetype":[
        "aat:300008347"
    ]
},
  "bbox": [],
  "geometry": {"coordinates":[9.316667,49.05],"type":"Point"}
}