{
  "id": 2053204,
  "type": "Feature",
  "properties": {
    "tgn:hierarchy":[
        "tgn:2053204",
        "tgn:1000001",
        "tgn:2000951",
        "tgn:7012149",
        "tgn:7007520",
        "tgn:7029392"
    ],
    "tgn:id":2053204,
    "tgn:name":"Royal Oak Beach",
    "tgn:placetype":[
        "aat:300008347",
        "aat:300387210"
    ]
},
  "bbox": [],
  "geometry": {"coordinates":[-84.5667,45.4833],"type":"Point"}
}