{
  "id": 2423331,
  "type": "Feature",
  "properties": {
    "tgn:hierarchy":[
        "tgn:2423331",
        "tgn:1000001",
        "tgn:7012149",
        "tgn:2001869",
        "tgn:7007825",
        "tgn:7029392"
    ],
    "tgn:id":2423331,
    "tgn:name":"John A Patten Island",
    "tgn:placetype":[
        "aat:300008791"
    ]
},
  "bbox": [],
  "geometry": {"coordinates":[-85.1167,35.15],"type":"Point"}
}