<<<<<<< HEAD
{
  "id": 7170093,
  "type": "Feature",
  "properties": {
    "tgn:hierarchy":[
        "tgn:7170093",
        "tgn:7003669",
        "tgn:1000003",
        "tgn:7000084",
        "tgn:7029392"
    ],
    "tgn:id":7170093,
    "tgn:name":"Herbolzheim",
    "tgn:placetype":[
        "aat:300008347"
    ]
},
  "bbox": [],
  "geometry": {"coordinates":[10.35,49.566667],"type":"Point"}
}
=======
{"geometry":{"type":"Point","coordinates":[10.350000,49.566667]},"type":"Feature","properties":{"hierarchy":["tgn:7170093","tgn:7003669","tgn:1000003","tgn:7000084","tgn:7029392"],"placetype":["aat:300008347"],"id":7170093,"name:xx":"Herbolzheim"}}
>>>>>>> 03f74aca74312dbeaf24d7e61306dd6a786dc3d0
