{
  "id": 2662490,
  "type": "Feature",
  "properties": {
    "tgn:hierarchy":[
        "tgn:2662490",
        "tgn:1000001",
        "tgn:7012149",
        "tgn:2002295",
        "tgn:7013961",
        "tgn:7029392"
    ],
    "tgn:id":2662490,
    "tgn:name":"Siggens Hollow",
    "tgn:placetype":[
        "aat:300008761"
    ]
},
  "bbox": [],
  "geometry": {"coordinates":[-79.95,39.35],"type":"Point"}
}