<<<<<<< HEAD
{
  "id": 7054281,
  "type": "Feature",
  "properties": {
    "tgn:hierarchy":[
        "tgn:7054281",
        "tgn:7003170",
        "tgn:1000003",
        "tgn:7003125",
        "tgn:1000080",
        "tgn:7029392"
    ],
    "tgn:id":7054281,
    "tgn:name":"Ponte Rio",
    "tgn:placetype":[
        "aat:300008347"
    ]
},
  "bbox": [],
  "geometry": {"coordinates":[12.4,42.8],"type":"Point"}
}
=======
{"geometry":{"type":"Point","coordinates":[12.400000,42.800000]},"type":"Feature","properties":{"hierarchy":["tgn:7054281","tgn:7003170","tgn:1000003","tgn:7003125","tgn:1000080","tgn:7029392"],"placetype":["aat:300008347"],"id":7054281,"name:xx":"Ponte Rio"}}
>>>>>>> 03f74aca74312dbeaf24d7e61306dd6a786dc3d0
