{
  "id": 2203481,
  "type": "Feature",
  "properties": {
    "tgn:hierarchy":[
        "tgn:2203481",
        "tgn:1000001",
        "tgn:7012149",
        "tgn:7007157",
        "tgn:7014004",
        "tgn:7029392"
    ],
    "tgn:id":2203481,
    "tgn:name":"Buckingham Mountain",
    "tgn:placetype":[
        "aat:300008798"
    ]
},
  "bbox": [],
  "geometry": {"coordinates":[-119.85,37.5167],"type":"Point"}
}