{
  "id": 2230159,
  "type": "Feature",
  "properties": {
    "tgn:hierarchy":[
        "tgn:2230159",
        "tgn:1000001",
        "tgn:7012149",
        "tgn:2001958",
        "tgn:7007826",
        "tgn:7029392"
    ],
    "tgn:id":2230159,
    "tgn:name":"Cement Mountain",
    "tgn:placetype":[
        "aat:300008798"
    ]
},
  "bbox": [],
  "geometry": {"coordinates":[-100.4833,31.75],"type":"Point"}
}