{
  "id": 7552943,
  "type": "Feature",
  "properties": {
    "tgn:hierarchy":[
        "tgn:7552943",
        "tgn:1000004",
        "tgn:7000198",
        "tgn:7016722",
        "tgn:7029392"
    ],
    "tgn:id":7552943,
    "tgn:name:en":"Muhammad\u0101b\u0101d",
    "tgn:placetype":[
        "aat:300008347"
    ]
},
  "bbox": [],
  "geometry": {"coordinates":[83.754988,25.618731],"type":"Point"}
}