{
  "id": 2046712,
  "type": "Feature",
  "properties": {
    "tgn:hierarchy":[
        "tgn:2046712",
        "tgn:1000001",
        "tgn:2124001",
        "tgn:7012149",
        "tgn:7007516",
        "tgn:7029392"
    ],
    "tgn:id":2046712,
    "tgn:name":"Colmar Manor",
    "tgn:placetype":[
        "aat:300008347"
    ]
},
  "bbox": [],
  "geometry": {"coordinates":[-76.9333,38.9167],"type":"Point"}
}