{
  "id": 7048790,
  "type": "Feature",
  "properties": {
    "tgn:hierarchy":[
        "tgn:7048790",
        "tgn:1001730",
        "tgn:1000003",
        "tgn:7003121",
        "tgn:1000080",
        "tgn:7029392"
    ],
    "tgn:id":7048790,
    "tgn:name":"Domusnovas Canales",
    "tgn:placetype":[
        "aat:300008347"
    ]
},
  "bbox": [],
  "geometry": {"coordinates":[8.833333,40.15],"type":"Point"}
}