<<<<<<< HEAD
{
  "id": 7245869,
  "type": "Feature",
  "properties": {
    "tgn:hierarchy":[
        "tgn:7245869",
        "tgn:7003466",
        "tgn:1000003",
        "tgn:1000063",
        "tgn:4012014",
        "tgn:7029392"
    ],
    "tgn:id":7245869,
    "tgn:name":"Br\u00fbly, Ruisseau du",
    "tgn:placetype":[
        "aat:300008699"
    ]
},
  "bbox": [],
  "geometry": {"coordinates":[4.433333,50.016667],"type":"Point"}
}
=======
{"geometry":{"type":"Point","coordinates":[4.433333,50.016667]},"type":"Feature","properties":{"hierarchy":["tgn:7245869","tgn:7003466","tgn:1000003","tgn:1000063","tgn:4012014","tgn:7029392"],"placetype":["aat:300008699"],"id":7245869,"name:xx":"Br\u00fbly, Ruisseau du"}}
>>>>>>> 03f74aca74312dbeaf24d7e61306dd6a786dc3d0
