{
  "id": 7016799,
  "type": "Feature",
  "properties": {
    "tgn:hierarchy":[
        "tgn:7016799",
        "tgn:1000004",
        "tgn:7000198",
        "tgn:7001797",
        "tgn:7029392"
    ],
    "tgn:id":7016799,
    "tgn:name:en":"Salem",
    "tgn:placetype":[
        "aat:300008347"
    ]
},
  "bbox": [],
  "geometry": {"coordinates":[78.166667,11.65],"type":"Point"}
}