{
  "id": 2465689,
  "type": "Feature",
  "properties": {
    "tgn:hierarchy":[
        "tgn:2465689",
        "tgn:1000001",
        "tgn:7012149",
        "tgn:2000183",
        "tgn:7007157",
        "tgn:7029392"
    ],
    "tgn:id":2465689,
    "tgn:name":"Lone Pine Peak",
    "tgn:placetype":[
        "aat:300008798"
    ]
},
  "bbox": [],
  "geometry": {"coordinates":[-118.2167,36.55],"type":"Point"}
}