{
  "id": 7490815,
  "type": "Feature",
  "properties": {
    "tgn:hierarchy":[
        "tgn:7490815",
        "tgn:7001010",
        "tgn:1000004",
        "tgn:1000141",
        "tgn:7029392"
    ],
    "tgn:id":7490815,
    "tgn:name":"Bazi Shan",
    "tgn:placetype":[
        "aat:300008798"
    ]
},
  "bbox": [],
  "geometry": {"coordinates":[121.329329,23.611594],"type":"Point"}
}