{
  "id": 7498274,
  "type": "Feature",
  "properties": {
    "tgn:hierarchy":[
        "tgn:7498274",
        "tgn:1000004",
        "tgn:1000454",
        "tgn:1000141",
        "tgn:7029392"
    ],
    "tgn:id":7498274,
    "tgn:name":"Erpingwei",
    "tgn:placetype":[
        "aat:300008347"
    ]
},
  "bbox": [],
  "geometry": {"coordinates":[121.643078,25.175612],"type":"Point"}
}