{
  "id": 2689849,
  "type": "Feature",
  "properties": {
    "tgn:hierarchy":[
        "tgn:2689849",
        "tgn:1000001",
        "tgn:7012149",
        "tgn:2002157",
        "tgn:7007919",
        "tgn:7029392"
    ],
    "tgn:id":2689849,
    "tgn:name":"Squirrel Camp Branch",
    "tgn:placetype":[
        "aat:300008699"
    ]
},
  "bbox": [],
  "geometry": {"coordinates":[-82.3333,37.1167],"type":"Point"}
}