{
  "id": 7320144,
  "type": "Feature",
  "properties": {
    "tgn:hierarchy":[
        "tgn:7320144",
        "tgn:1001699",
        "tgn:1000049",
        "tgn:1000002",
        "tgn:7029392"
    ],
    "tgn:id":7320144,
    "tgn:name":"Acui, Isla",
    "tgn:placetype":[
        "aat:300008791"
    ]
},
  "bbox": [],
  "geometry": {"coordinates":[-73.428333,-42.914444],"type":"Point"}
}