{
  "id": 7256864,
  "type": "Feature",
  "properties": {
    "tgn:hierarchy":[
        "tgn:7256864",
        "tgn:7003619",
        "tgn:1000003",
        "tgn:7016845",
        "tgn:7029392"
    ],
    "tgn:id":7256864,
    "tgn:name:nl":"Astbeek",
    "tgn:placetype":[
        "aat:300008699"
    ]
},
  "bbox": [],
  "geometry": {"coordinates":[5.666667,52.133333],"type":"Point"}
}