{
  "id": 7506382,
  "type": "Feature",
  "properties": {
    "tgn:hierarchy":[
        "tgn:7506382",
        "tgn:1008380",
        "tgn:1000226",
        "tgn:7018426",
        "tgn:1000006",
        "tgn:7029392"
    ],
    "tgn:id":7506382,
    "tgn:name:en":"Round Lake",
    "tgn:placetype":[
        "aat:300008680"
    ]
},
  "bbox": [],
  "geometry": {"coordinates":[175.333333,-37.95],"type":"Point"}
}