{
  "id": 7220119,
  "type": "Feature",
  "properties": {
    "tgn:hierarchy":[
        "tgn:7220119",
        "tgn:7002707",
        "tgn:7002705",
        "tgn:1000003",
        "tgn:1000074",
        "tgn:7029392"
    ],
    "tgn:id":7220119,
    "tgn:name":"Valtsini\u00e1",
    "tgn:placetype":[
        "aat:300008347"
    ]
},
  "bbox": [],
  "geometry": {"coordinates":[21.040556,39.707222],"type":"Point"}
}