{
  "id": 2340488,
  "type": "Feature",
  "properties": {
    "tgn:hierarchy":[
        "tgn:2340488",
        "tgn:1000001",
        "tgn:7012149",
        "tgn:1002545",
        "tgn:7007157",
        "tgn:7029392"
    ],
    "tgn:id":2340488,
    "tgn:name":"French Ranch Gulch",
    "tgn:placetype":[
        "aat:300008761"
    ]
},
  "bbox": [],
  "geometry": {"coordinates":[-118.65,35.5667],"type":"Point"}
}