{
  "id": 2515399,
  "type": "Feature",
  "properties": {
    "tgn:hierarchy":[
        "tgn:2515399",
        "tgn:1000001",
        "tgn:1002235",
        "tgn:7012149",
        "tgn:7007919",
        "tgn:7029392"
    ],
    "tgn:id":2515399,
    "tgn:name":"Millpond Creek",
    "tgn:placetype":[
        "aat:300008706"
    ]
},
  "bbox": [],
  "geometry": {"coordinates":[-77.3167,37.85],"type":"Point"}
}