{
  "id": 7345169,
  "type": "Feature",
  "properties": {
    "tgn:hierarchy":[
        "tgn:7345169",
        "tgn:7002842",
        "tgn:7001158",
        "tgn:1000003",
        "tgn:1000095",
        "tgn:7029392"
    ],
    "tgn:id":7345169,
    "tgn:name":"Alcubilla de las Pe\u00f1as",
    "tgn:placetype":[
        "aat:300008347"
    ]
},
  "bbox": [],
  "geometry": {"coordinates":[-2.516667,41.25],"type":"Point"}
}