{
  "id": 7037008,
  "type": "Feature",
  "properties": {
    "tgn:hierarchy":[
        "tgn:7037008",
        "tgn:7003129",
        "tgn:1000003",
        "tgn:7008516",
        "tgn:1000080",
        "tgn:7029392"
    ],
    "tgn:id":7037008,
    "tgn:name":"Villa Calabra",
    "tgn:placetype":[
        "aat:300008347"
    ]
},
  "bbox": [],
  "geometry": {"coordinates":[12.300556,44.179444],"type":"Point"}
}