{
  "id": 2726167,
  "type": "Feature",
  "properties": {
    "tgn:hierarchy":[
        "tgn:2726167",
        "tgn:1000001",
        "tgn:7012149",
        "tgn:2002124",
        "tgn:7007827",
        "tgn:7029392"
    ],
    "tgn:id":2726167,
    "tgn:name":"Towave Reservoir",
    "tgn:placetype":[
        "aat:300006191"
    ]
},
  "bbox": [],
  "geometry": {"coordinates":[-109.7333,39.5667],"type":"Point"}
}