{
  "id": 1057686,
  "type": "Feature",
  "properties": {
    "tgn:hierarchy":[
        "tgn:1057686",
        "tgn:7012076",
        "tgn:1000003",
        "tgn:7006660",
        "tgn:7029392"
    ],
    "tgn:id":1057686,
    "tgn:name":"Novojekaterinovka",
    "tgn:placetype":[
        "aat:300008347"
    ]
},
  "bbox": [],
  "geometry": {"coordinates":[38.1167,47.7167],"type":"Point"}
}