{
  "id": 2678569,
  "type": "Feature",
  "properties": {
    "tgn:hierarchy":[
        "tgn:2678569",
        "tgn:1000001",
        "tgn:7012149",
        "tgn:2001277",
        "tgn:7007524",
        "tgn:7029392"
    ],
    "tgn:id":2678569,
    "tgn:name":"South Fork Cut Bank Creek",
    "tgn:placetype":[
        "aat:300008706"
    ]
},
  "bbox": [],
  "geometry": {"coordinates":[-113.3667,48.5833],"type":"Point"}
}