{
  "id": 7381917,
  "type": "Feature",
  "properties": {
    "tgn:hierarchy":[
        "tgn:7381917",
        "tgn:1001853",
        "tgn:1000001",
        "tgn:7005560",
        "tgn:7029392"
    ],
    "tgn:id":7381917,
    "tgn:name":"Manga de la Rosita",
    "tgn:placetype":[
        "aat:300008347"
    ]
},
  "bbox": [],
  "geometry": {"coordinates":[-101.533333,29.116667],"type":"Point"}
}