<<<<<<< HEAD
{
  "id": 7374350,
  "type": "Feature",
  "properties": {
    "tgn:hierarchy":[
        "tgn:7374350",
        "tgn:7005581",
        "tgn:1000001",
        "tgn:7005560",
        "tgn:7029392"
    ],
    "tgn:id":7374350,
    "tgn:name":"Lagunas",
    "tgn:placetype":[
        "aat:300007783"
    ]
},
  "bbox": [],
  "geometry": {"coordinates":[-106.316667,29.466667],"type":"Point"}
}
=======
{"geometry":{"type":"Point","coordinates":[-106.316667,29.466667]},"type":"Feature","properties":{"hierarchy":["tgn:7374350","tgn:7005581","tgn:1000001","tgn:7005560","tgn:7029392"],"placetype":["aat:300007783"],"id":7374350,"name:xx":"Lagunas"}}
>>>>>>> 03f74aca74312dbeaf24d7e61306dd6a786dc3d0
