<<<<<<< HEAD
{
  "id": 2250510,
  "type": "Feature",
  "properties": {
    "tgn:hierarchy":[
        "tgn:2250510",
        "tgn:1000001",
        "tgn:7012149",
        "tgn:7014021",
        "tgn:7007709",
        "tgn:7029392"
    ],
    "tgn:id":2250510,
    "tgn:name":"Colony Acres",
    "tgn:placetype":[
        "aat:300008347"
    ]
},
  "bbox": [],
  "geometry": {"coordinates":[-80.8833,35.1333],"type":"Point"}
}
=======
{"geometry":{"type":"Point","coordinates":[-80.883300,35.133300]},"type":"Feature","properties":{"hierarchy":["tgn:2250510","tgn:1000001","tgn:7012149","tgn:7014021","tgn:7007709","tgn:7029392"],"placetype":["aat:300008347"],"id":2250510,"name:xx":"Colony Acres"}}
>>>>>>> 03f74aca74312dbeaf24d7e61306dd6a786dc3d0
