<<<<<<< HEAD
{
  "id": 7369428,
  "type": "Feature",
  "properties": {
    "tgn:hierarchy":[
        "tgn:7369428",
        "tgn:7005581",
        "tgn:1000001",
        "tgn:7005560",
        "tgn:7029392"
    ],
    "tgn:id":7369428,
    "tgn:name":"Huachajuri",
    "tgn:placetype":[
        "aat:300008347"
    ]
},
  "bbox": [],
  "geometry": {"coordinates":[-108.3,27.5],"type":"Point"}
}
=======
{"geometry":{"type":"Point","coordinates":[-108.300000,27.500000]},"type":"Feature","properties":{"hierarchy":["tgn:7369428","tgn:7005581","tgn:1000001","tgn:7005560","tgn:7029392"],"placetype":["aat:300008347"],"id":7369428,"name:xx":"Huachajuri"}}
>>>>>>> 03f74aca74312dbeaf24d7e61306dd6a786dc3d0
