{
  "id": 2546934,
  "type": "Feature",
  "properties": {
    "tgn:hierarchy":[
        "tgn:2546934",
        "tgn:1000001",
        "tgn:7012149",
        "tgn:7007157",
        "tgn:2000185",
        "tgn:7029392"
    ],
    "tgn:id":2546934,
    "tgn:name":"North Fork Noyo River",
    "tgn:placetype":[
        "aat:300008707"
    ]
},
  "bbox": [],
  "geometry": {"coordinates":[-123.55,39.4667],"type":"Point"}
}