{
  "id": 2474635,
  "type": "Feature",
  "properties": {
    "tgn:hierarchy":[
        "tgn:2474635",
        "tgn:1000001",
        "tgn:7012149",
        "tgn:1002877",
        "tgn:7007706",
        "tgn:7029392"
    ],
    "tgn:id":2474635,
    "tgn:name":"Lower Shaw Hollow",
    "tgn:placetype":[
        "aat:300008761"
    ]
},
  "bbox": [],
  "geometry": {"coordinates":[-83.1667,38.7333],"type":"Point"}
}