{
  "id": 7565887,
  "type": "Feature",
  "properties": {
    "tgn:hierarchy":[
        "tgn:7565887",
        "tgn:1000004",
        "tgn:1001832",
        "tgn:7000198",
        "tgn:7029392"
    ],
    "tgn:id":7565887,
    "tgn:name:en":"J\u0101r\u0101guri",
    "tgn:placetype":[
        "aat:300008347"
    ]
},
  "bbox": [],
  "geometry": {"coordinates":[89.882148,26.496054],"type":"Point"}
}