{
  "id": 2546190,
  "type": "Feature",
  "properties": {
    "tgn:hierarchy":[
        "tgn:2546190",
        "tgn:1000001",
        "tgn:7012149",
        "tgn:2001286",
        "tgn:7007524",
        "tgn:7029392"
    ],
    "tgn:id":2546190,
    "tgn:name":"North Fork Fitzsimmons Creek",
    "tgn:placetype":[
        "aat:300008706"
    ]
},
  "bbox": [],
  "geometry": {"coordinates":[-114.65,48.7667],"type":"Point"}
}