{
  "id": 1086472,
  "type": "Feature",
  "properties": {
    "tgn:hierarchy":[
        "tgn:1086472",
        "tgn:1001282",
        "tgn:1000004",
        "tgn:7018455",
        "tgn:1000144",
        "tgn:7029392"
    ],
    "tgn:id":1086472,
    "tgn:name":"Uludere",
    "tgn:placetype":[
        "aat:300008347"
    ]
},
  "bbox": [],
  "geometry": {"coordinates":[42.85,37.4167],"type":"Point"}
}