{
  "id": 2218557,
  "type": "Feature",
  "properties": {
    "tgn:hierarchy":[
        "tgn:2218557",
        "tgn:7002659",
        "tgn:1000001",
        "tgn:7012149",
        "tgn:2000055",
        "tgn:7029392"
    ],
    "tgn:id":2218557,
    "tgn:name":"Cane Creek",
    "tgn:placetype":[
        "aat:300008706"
    ]
},
  "bbox": [],
  "geometry": {"coordinates":[-85.3333,33.35],"type":"Point"}
}