{
  "id": 1099012,
  "type": "Feature",
  "properties": {
    "tgn:hierarchy":[
        "tgn:1099012",
        "tgn:1008380",
        "tgn:7000507",
        "tgn:1000226",
        "tgn:1000006",
        "tgn:7029392"
    ],
    "tgn:id":1099012,
    "tgn:name:en":"Kohukohu",
    "tgn:placetype":[
        "aat:300008347"
    ]
},
  "bbox": [],
  "geometry": {"coordinates":[173.533333,-35.35],"type":"Point"}
}