{
  "id": 2396924,
  "type": "Feature",
  "properties": {
    "tgn:hierarchy":[
        "tgn:2396924",
        "tgn:1000001",
        "tgn:7012149",
        "tgn:7007250",
        "tgn:7029392"
    ],
    "tgn:id":2396924,
    "tgn:name":"Homer Valley",
    "tgn:placetype":[
        "aat:300008761"
    ]
},
  "bbox": [],
  "geometry": {"coordinates":[-111.5667,43.15],"type":"Point"}
}