{
  "id": 2219953,
  "type": "Feature",
  "properties": {
    "tgn:hierarchy":[
        "tgn:2219953",
        "tgn:7006450",
        "tgn:1000001",
        "tgn:7019698",
        "tgn:7012149",
        "tgn:7029392"
    ],
    "tgn:id":2219953,
    "tgn:name":"Canyon Creek",
    "tgn:placetype":[
        "aat:300008706"
    ]
},
  "bbox": [],
  "geometry": {"coordinates":[-149.4333,60.5667],"type":"Point"}
}