{
  "id": 7530996,
  "type": "Feature",
  "properties": {
    "tgn:hierarchy":[
        "tgn:7530996",
        "tgn:7001242",
        "tgn:7016833",
        "tgn:1001113",
        "tgn:7029392"
    ],
    "tgn:id":7530996,
    "tgn:name":"Kafr al 'Awa\u1e11\u012b",
    "tgn:placetype":[
        "aat:300008347"
    ]
},
  "bbox": [],
  "geometry": {"coordinates":[31.513063,30.458593],"type":"Point"}
}