{
  "id": 2453290,
  "type": "Feature",
  "properties": {
    "tgn:hierarchy":[
        "tgn:2453290",
        "tgn:1000001",
        "tgn:7012149",
        "tgn:2000537",
        "tgn:7007251",
        "tgn:7029392"
    ],
    "tgn:id":2453290,
    "tgn:name":"Little Chain Hills",
    "tgn:placetype":[
        "aat:300008798"
    ]
},
  "bbox": [],
  "geometry": {"coordinates":[-88.0333,37.95],"type":"Point"}
}