{
  "id": 2734815,
  "type": "Feature",
  "properties": {
    "tgn:hierarchy":[
        "tgn:2734815",
        "tgn:1000001",
        "tgn:7012149",
        "tgn:1002288",
        "tgn:7007523",
        "tgn:7029392"
    ],
    "tgn:id":2734815,
    "tgn:name":"Twehaus Lake",
    "tgn:placetype":[
        "aat:300006191"
    ]
},
  "bbox": [],
  "geometry": {"coordinates":[-92.0667,38.4833],"type":"Point"}
}