{
  "id": 2710762,
  "type": "Feature",
  "properties": {
    "tgn:hierarchy":[
        "tgn:2710762",
        "tgn:1000001",
        "tgn:2001704",
        "tgn:7012149",
        "tgn:7007708",
        "tgn:7029392"
    ],
    "tgn:id":2710762,
    "tgn:name":"Tanbark Point",
    "tgn:placetype":[
        "aat:300008850"
    ]
},
  "bbox": [],
  "geometry": {"coordinates":[-124.2667,42.0333],"type":"Point"}
}