<<<<<<< HEAD
{
  "id": 2150739,
  "type": "Feature",
  "properties": {
    "tgn:hierarchy":[
        "tgn:2150739",
        "tgn:1000001",
        "tgn:7012149",
        "tgn:2001709",
        "tgn:7007708",
        "tgn:7029392"
    ],
    "tgn:id":2150739,
    "tgn:name":"Bass Haines Place",
    "tgn:placetype":[
        "aat:300008347"
    ]
},
  "bbox": [],
  "geometry": {"coordinates":[-118.9667,42.35],"type":"Point"}
}
=======
{"geometry":{"type":"Point","coordinates":[-118.966700,42.350000]},"type":"Feature","properties":{"hierarchy":["tgn:2150739","tgn:1000001","tgn:7012149","tgn:2001709","tgn:7007708","tgn:7029392"],"placetype":["aat:300008347"],"id":2150739,"name:xx":"Bass Haines Place"}}
>>>>>>> 03f74aca74312dbeaf24d7e61306dd6a786dc3d0
