{
  "id": 7449915,
  "type": "Feature",
  "properties": {
    "tgn:hierarchy":[
        "tgn:7449915",
        "tgn:7002444",
        "tgn:1000003",
        "tgn:7019085",
        "tgn:7008591",
        "tgn:7029392"
    ],
    "tgn:id":7449915,
    "tgn:name:en":"Finnarts House",
    "tgn:placetype":[
        "aat:300387502"
    ]
},
  "bbox": [],
  "geometry": {"coordinates":[-5.033333,55.016667],"type":"Point"}
}