{
  "id": 7468650,
  "type": "Feature",
  "properties": {
    "tgn:hierarchy":[
        "tgn:7468650",
        "tgn:1000004",
        "tgn:7001013",
        "tgn:1000141",
        "tgn:7029392"
    ],
    "tgn:id":7468650,
    "tgn:name":"Xiadaku",
    "tgn:placetype":[
        "aat:300008347"
    ]
},
  "bbox": [],
  "geometry": {"coordinates":[121.12764,25.003074],"type":"Point"}
}