{
  "id": 7569030,
  "type": "Feature",
  "properties": {
    "tgn:hierarchy":[
        "tgn:7569030",
        "tgn:1000004",
        "tgn:7000198",
        "tgn:1001996",
        "tgn:7029392"
    ],
    "tgn:id":7569030,
    "tgn:name:en":"J\u0101khari",
    "tgn:placetype":[
        "aat:300008347"
    ]
},
  "bbox": [],
  "geometry": {"coordinates":[77.047222,31.143056],"type":"Point"}
}