{
  "id": 2544083,
  "type": "Feature",
  "properties": {
    "tgn:hierarchy":[
        "tgn:2544083",
        "tgn:1000001",
        "tgn:7012149",
        "tgn:2002348",
        "tgn:7007922",
        "tgn:7029392"
    ],
    "tgn:id":2544083,
    "tgn:name":"North Branch Holmes Creek",
    "tgn:placetype":[
        "aat:300008706"
    ]
},
  "bbox": [],
  "geometry": {"coordinates":[-90.2167,45.45],"type":"Point"}
}