{
  "id": 2176288,
  "type": "Feature",
  "properties": {
    "tgn:hierarchy":[
        "tgn:2176288",
        "tgn:1000001",
        "tgn:7012149",
        "tgn:7007707",
        "tgn:7029392"
    ],
    "tgn:id":2176288,
    "tgn:name":"Black Hollow",
    "tgn:placetype":[
        "aat:300008761"
    ]
},
  "bbox": [],
  "geometry": {"coordinates":[-94.9667,36.3333],"type":"Point"}
}