{
  "id": 2360713,
  "type": "Feature",
  "properties": {
    "tgn:hierarchy":[
        "tgn:2360713",
        "tgn:1000001",
        "tgn:7012149",
        "tgn:2001515",
        "tgn:7007709",
        "tgn:7029392"
    ],
    "tgn:id":2360713,
    "tgn:name":"Grassy Knob",
    "tgn:placetype":[
        "aat:300008798"
    ]
},
  "bbox": [],
  "geometry": {"coordinates":[-83.4167,35.1833],"type":"Point"}
}