{
  "id": 7403822,
  "type": "Feature",
  "properties": {
    "tgn:hierarchy":[
        "tgn:7403822",
        "tgn:1000001",
        "tgn:1001906",
        "tgn:7005560",
        "tgn:7029392"
    ],
    "tgn:id":7403822,
    "tgn:name":"Valle de la Urraca",
    "tgn:placetype":[
        "aat:300008347"
    ]
},
  "bbox": [],
  "geometry": {"coordinates":[-105.641667,22.579167],"type":"Point"}
}