{
  "id": 7476719,
  "type": "Feature",
  "properties": {
    "tgn:hierarchy":[
        "tgn:7476719",
        "tgn:7488858",
        "tgn:1000004",
        "tgn:1000141",
        "tgn:7029392"
    ],
    "tgn:id":7476719,
    "tgn:name":"Jingtu Chansi",
    "tgn:placetype":[
        "aat:300007595"
    ]
},
  "bbox": [],
  "geometry": {"coordinates":[120.804279,23.898127],"type":"Point"}
}