<<<<<<< HEAD
{
  "id": 2336405,
  "type": "Feature",
  "properties": {
    "tgn:hierarchy":[
        "tgn:2336405",
        "tgn:1000001",
        "tgn:1002359",
        "tgn:7012149",
        "tgn:7007517",
        "tgn:7029392"
    ],
    "tgn:id":2336405,
    "tgn:name":"Fountain Pond",
    "tgn:placetype":[
        "aat:300006191"
    ]
},
  "bbox": [],
  "geometry": {"coordinates":[-70.9333,42.5],"type":"Point"}
}
=======
{"geometry":{"type":"Point","coordinates":[-70.933300,42.500000]},"type":"Feature","properties":{"hierarchy":["tgn:2336405","tgn:1000001","tgn:1002359","tgn:7012149","tgn:7007517","tgn:7029392"],"placetype":["aat:300006191"],"id":2336405,"name:xx":"Fountain Pond"}}
>>>>>>> 03f74aca74312dbeaf24d7e61306dd6a786dc3d0
