{
  "id": 7395846,
  "type": "Feature",
  "properties": {
    "tgn:hierarchy":[
        "tgn:7395846",
        "tgn:7005580",
        "tgn:1000001",
        "tgn:7005560",
        "tgn:7029392"
    ],
    "tgn:id":7395846,
    "tgn:name":"San Felipe",
    "tgn:placetype":[
        "aat:300008347"
    ]
},
  "bbox": [],
  "geometry": {"coordinates":[-92.416667,15.95],"type":"Point"}
}