{
  "id": 2658621,
  "type": "Feature",
  "properties": {
    "tgn:hierarchy":[
        "tgn:2658621",
        "tgn:1000001",
        "tgn:7012149",
        "tgn:2002129",
        "tgn:7007827",
        "tgn:7029392"
    ],
    "tgn:id":2658621,
    "tgn:name":"Sheridan Heights",
    "tgn:placetype":[
        "aat:300008347"
    ]
},
  "bbox": [],
  "geometry": {"coordinates":[-111.9333,41.25],"type":"Point"}
}