{
  "id": 1022122,
  "type": "Feature",
  "properties": {
    "tgn:hierarchy":[
        "tgn:1022122",
        "tgn:7006247",
        "tgn:1000047",
        "tgn:7002456",
        "tgn:1000002",
        "tgn:7029392"
    ],
    "tgn:id":1022122,
    "tgn:name":"Moju",
    "tgn:placetype":[
        "aat:300008347"
    ]
},
  "bbox": [],
  "geometry": {"coordinates":[-48.75,-1.8667],"type":"Point"}
}