{
  "id": 2009224,
  "type": "Feature",
  "properties": {
    "tgn:hierarchy":[
        "tgn:2009224",
        "tgn:1000001",
        "tgn:7016172",
        "tgn:7012149",
        "tgn:2000155",
        "tgn:7029392"
    ],
    "tgn:id":2009224,
    "tgn:name":"Piercetown",
    "tgn:placetype":[
        "aat:300008347",
        "aat:300387210"
    ]
},
  "bbox": [],
  "geometry": {"coordinates":[-93.0667,35.95],"type":"Point"}
}