<<<<<<< HEAD
{
  "id": 2153438,
  "type": "Feature",
  "properties": {
    "tgn:hierarchy":[
        "tgn:2153438",
        "tgn:1000001",
        "tgn:7012149",
        "tgn:7007825",
        "tgn:7029392"
    ],
    "tgn:id":2153438,
    "tgn:name":"Bean Ridge",
    "tgn:placetype":[
        "aat:300266640"
    ]
},
  "bbox": [],
  "geometry": {"coordinates":[-85.05,35.4333],"type":"Point"}
}
=======
{"geometry":{"type":"Point","coordinates":[-85.050000,35.433300]},"type":"Feature","properties":{"hierarchy":["tgn:2153438","tgn:1000001","tgn:7012149","tgn:7007825","tgn:7029392"],"placetype":["aat:300266640"],"id":2153438,"name:xx":"Bean Ridge"}}
>>>>>>> 03f74aca74312dbeaf24d7e61306dd6a786dc3d0
