<<<<<<< HEAD
{
  "id": 2334418,
  "type": "Feature",
  "properties": {
    "tgn:hierarchy":[
        "tgn:2334418",
        "tgn:1000001",
        "tgn:7012149",
        "tgn:7014021",
        "tgn:7007709",
        "tgn:7029392"
    ],
    "tgn:id":2334418,
    "tgn:name":"Forest Lake",
    "tgn:placetype":[
        "aat:300006191"
    ]
},
  "bbox": [],
  "geometry": {"coordinates":[-80.7167,35.2],"type":"Point"}
}
=======
{"geometry":{"type":"Point","coordinates":[-80.716700,35.200000]},"type":"Feature","properties":{"hierarchy":["tgn:2334418","tgn:1000001","tgn:7012149","tgn:7014021","tgn:7007709","tgn:7029392"],"placetype":["aat:300006191"],"id":2334418,"name:xx":"Forest Lake"}}
>>>>>>> 03f74aca74312dbeaf24d7e61306dd6a786dc3d0
