{
  "id": 1030765,
  "type": "Feature",
  "properties": {
    "tgn:hierarchy":[
        "tgn:1030765",
        "tgn:7002445",
        "tgn:1003666",
        "tgn:1000003",
        "tgn:7029504",
        "tgn:7008591",
        "tgn:7029392"
    ],
    "tgn:id":1030765,
    "tgn:name":"Storeton",
    "tgn:placetype":[
        "aat:300008347"
    ]
},
  "bbox": [],
  "geometry": {"coordinates":[-3.05,53.35],"type":"Point"}
}