{
  "id": 2132019,
  "type": "Feature",
  "properties": {
    "tgn:hierarchy":[
        "tgn:2132019",
        "tgn:7006450",
        "tgn:1000001",
        "tgn:7012149",
        "tgn:2000085",
        "tgn:7029392"
    ],
    "tgn:id":2132019,
    "tgn:name":"American Creek",
    "tgn:placetype":[
        "aat:300008706"
    ]
},
  "bbox": [],
  "geometry": {"coordinates":[-141.3167,64.6667],"type":"Point"}
}