{
  "id": 7302463,
  "type": "Feature",
  "properties": {
    "tgn:hierarchy":[
        "tgn:7302463",
        "tgn:7002758",
        "tgn:7002817",
        "tgn:1000003",
        "tgn:1000095",
        "tgn:7029392"
    ],
    "tgn:id":7302463,
    "tgn:name":"Onza, R\u00edo",
    "tgn:placetype":[
        "aat:300008699"
    ]
},
  "bbox": [],
  "geometry": {"coordinates":[-5.483333,38.083333],"type":"Point"}
}