{
  "id": 7585132,
  "type": "Feature",
  "properties": {
    "tgn:hierarchy":[
        "tgn:7585132",
        "tgn:1000004",
        "tgn:7000200",
        "tgn:7000198",
        "tgn:7029392"
    ],
    "tgn:id":7585132,
    "tgn:name:en":"R\u0101j Bhavan Hary\u0101na",
    "tgn:placetype":[
        "aat:300008347"
    ]
},
  "bbox": [],
  "geometry": {"coordinates":[76.808033,30.744172],"type":"Point"}
}