{
  "id": 7557522,
  "type": "Feature",
  "properties": {
    "tgn:hierarchy":[
        "tgn:7557522",
        "tgn:1000004",
        "tgn:7000198",
        "tgn:7031783",
        "tgn:7029392"
    ],
    "tgn:id":7557522,
    "tgn:name:en":"S\u0101lukd\u012bh",
    "tgn:placetype":[
        "aat:300008347"
    ]
},
  "bbox": [],
  "geometry": {"coordinates":[85.831554,23.116908],"type":"Point"}
}