{
  "id": 2023896,
  "type": "Feature",
  "properties": {
    "tgn:hierarchy":[
        "tgn:2023896",
        "tgn:1000001",
        "tgn:7012149",
        "tgn:2000393",
        "tgn:7007248",
        "tgn:7029392"
    ],
    "tgn:id":2023896,
    "tgn:name":"Percale",
    "tgn:placetype":[
        "aat:300387016"
    ]
},
  "bbox": [],
  "geometry": {"coordinates":[-83.7833,33.0833],"type":"Point"}
}