{
  "id": 2542083,
  "type": "Feature",
  "properties": {
    "tgn:hierarchy":[
        "tgn:2542083",
        "tgn:1000001",
        "tgn:7012149",
        "tgn:7014589",
        "tgn:7007515",
        "tgn:7029392"
    ],
    "tgn:id":2542083,
    "tgn:name":"Nipps Island",
    "tgn:placetype":[
        "aat:300008791"
    ]
},
  "bbox": [],
  "geometry": {"coordinates":[-67.05,44.9167],"type":"Point"}
}