{
  "id": 7549333,
  "type": "Feature",
  "properties": {
    "tgn:hierarchy":[
        "tgn:7549333",
        "tgn:1000004",
        "tgn:7000198",
        "tgn:1001895",
        "tgn:7029392"
    ],
    "tgn:id":7549333,
    "tgn:name:en":"Ekr\u016bk Lake",
    "tgn:placetype":[
        "aat:300008680"
    ]
},
  "bbox": [],
  "geometry": {"coordinates":[75.914736,17.74548],"type":"Point"}
}