{
  "id": 2729696,
  "type": "Feature",
  "properties": {
    "tgn:hierarchy":[
        "tgn:2729696",
        "tgn:1000001",
        "tgn:2002149",
        "tgn:7012149",
        "tgn:7007919",
        "tgn:7029392"
    ],
    "tgn:id":2729696,
    "tgn:name":"Troublesome Creek",
    "tgn:placetype":[
        "aat:300008706"
    ]
},
  "bbox": [],
  "geometry": {"coordinates":[-78.4667,37.5333],"type":"Point"}
}