{
  "id": 7498956,
  "type": "Feature",
  "properties": {
    "tgn:hierarchy":[
        "tgn:7498956",
        "tgn:1000004",
        "tgn:7001009",
        "tgn:1000141",
        "tgn:7029392"
    ],
    "tgn:id":7498956,
    "tgn:name":"Xinping",
    "tgn:placetype":[
        "aat:300008347"
    ]
},
  "bbox": [],
  "geometry": {"coordinates":[120.73257,24.118321],"type":"Point"}
}