{
  "id": 2282880,
  "type": "Feature",
  "properties": {
    "tgn:hierarchy":[
        "tgn:2282880",
        "tgn:1000001",
        "tgn:2001414",
        "tgn:7012149",
        "tgn:7007526",
        "tgn:7029392"
    ],
    "tgn:id":2282880,
    "tgn:name":"Defense Mine",
    "tgn:placetype":[
        "aat:300000390"
    ]
},
  "bbox": [],
  "geometry": {"coordinates":[-118.6833,41.85],"type":"Point"}
}