<<<<<<< HEAD
{
  "id": 7479491,
  "type": "Feature",
  "properties": {
    "tgn:hierarchy":[
        "tgn:7479491",
        "tgn:1000004",
        "tgn:7490934",
        "tgn:1000141",
        "tgn:7029392"
    ],
    "tgn:id":7479491,
    "tgn:name":"Bantianliao Shan",
    "tgn:placetype":[
        "aat:300008777"
    ]
},
  "bbox": [],
  "geometry": {"coordinates":[120.483333,23.373333],"type":"Point"}
}
=======
{"geometry":{"type":"Point","coordinates":[120.483333,23.373333]},"type":"Feature","properties":{"hierarchy":["tgn:7479491","tgn:1000004","tgn:7490934","tgn:1000141","tgn:7029392"],"placetype":["aat:300008777"],"id":7479491,"name:xx":"Bantianliao Shan"}}
>>>>>>> 03f74aca74312dbeaf24d7e61306dd6a786dc3d0
