{
  "id": 2659127,
  "type": "Feature",
  "properties": {
    "tgn:hierarchy":[
        "tgn:2659127",
        "tgn:1000001",
        "tgn:2001483",
        "tgn:7012149",
        "tgn:7007709",
        "tgn:7029392"
    ],
    "tgn:id":2659127,
    "tgn:name":"Shewbird Mountain",
    "tgn:placetype":[
        "aat:300008798"
    ]
},
  "bbox": [],
  "geometry": {"coordinates":[-83.8333,34.9833],"type":"Point"}
}