<<<<<<< HEAD
{
  "id": 2401986,
  "type": "Feature",
  "properties": {
    "tgn:hierarchy":[
        "tgn:2401986",
        "tgn:1000001",
        "tgn:7012149",
        "tgn:7007157",
        "tgn:7014516",
        "tgn:7029392"
    ],
    "tgn:id":2401986,
    "tgn:name":"Horseshoe Point",
    "tgn:placetype":[
        "aat:300008850"
    ]
},
  "bbox": [],
  "geometry": {"coordinates":[-123.3667,38.6],"type":"Point"}
}
=======
{"geometry":{"type":"Point","coordinates":[-123.366700,38.600000]},"type":"Feature","properties":{"hierarchy":["tgn:2401986","tgn:1000001","tgn:7012149","tgn:7007157","tgn:7014516","tgn:7029392"],"placetype":["aat:300008850"],"id":2401986,"name:xx":"Horseshoe Point"}}
>>>>>>> 03f74aca74312dbeaf24d7e61306dd6a786dc3d0
