{
  "id": 7476383,
  "type": "Feature",
  "properties": {
    "tgn:hierarchy":[
        "tgn:7476383",
        "tgn:7488858",
        "tgn:1000004",
        "tgn:1000141",
        "tgn:7029392"
    ],
    "tgn:id":7476383,
    "tgn:name":"Jiahe Guoxiao",
    "tgn:placetype":[
        "aat:300006495"
    ]
},
  "bbox": [],
  "geometry": {"coordinates":[120.6844,23.8971],"type":"Point"}
}