<<<<<<< HEAD
{
  "id": 2158711,
  "type": "Feature",
  "properties": {
    "tgn:hierarchy":[
        "tgn:2158711",
        "tgn:1000001",
        "tgn:7012149",
        "tgn:2000203",
        "tgn:7007158",
        "tgn:7029392"
    ],
    "tgn:id":2158711,
    "tgn:name":"Beccerro Basin",
    "tgn:placetype":[
        "aat:300386845"
    ]
},
  "bbox": [],
  "geometry": {"coordinates":[-105.1667,37.2833],"type":"Point"}
}
=======
{"geometry":{"type":"Point","coordinates":[-105.166700,37.283300]},"type":"Feature","properties":{"hierarchy":["tgn:2158711","tgn:1000001","tgn:7012149","tgn:2000203","tgn:7007158","tgn:7029392"],"placetype":["aat:300386845"],"id":2158711,"name:xx":"Beccerro Basin"}}
>>>>>>> 03f74aca74312dbeaf24d7e61306dd6a786dc3d0
