{
  "id": 1119408,
  "type": "Feature",
  "properties": {
    "tgn:hierarchy":[
        "tgn:1119408",
        "tgn:1000001",
        "tgn:7012149",
        "tgn:1002961",
        "tgn:7007568",
        "tgn:7029392"
    ],
    "tgn:id":1119408,
    "tgn:name":"Ashokan Reservoir",
    "tgn:placetype":[
        "aat:300006191"
    ]
},
  "bbox": [],
  "geometry": {"coordinates":[-74.2167,41.9333],"type":"Point"}
}