{
  "id": 7223056,
  "type": "Feature",
  "properties": {
    "tgn:hierarchy":[
        "tgn:7223056",
        "tgn:7002726",
        "tgn:7002715",
        "tgn:1000003",
        "tgn:1000074",
        "tgn:7029392"
    ],
    "tgn:id":7223056,
    "tgn:name":"Platan\u00f3rrevma",
    "tgn:placetype":[
        "aat:300008347"
    ]
},
  "bbox": [],
  "geometry": {"coordinates":[22.020556,40.196667],"type":"Point"}
}