{
  "id": 2237459,
  "type": "Feature",
  "properties": {
    "tgn:hierarchy":[
        "tgn:2237459",
        "tgn:1000001",
        "tgn:7006451",
        "tgn:7012149",
        "tgn:2000100",
        "tgn:7029392"
    ],
    "tgn:id":2237459,
    "tgn:name":"China Draw",
    "tgn:placetype":[
        "aat:300008761"
    ]
},
  "bbox": [],
  "geometry": {"coordinates":[-111.25,32.3167],"type":"Point"}
}