{
  "id": 7554499,
  "type": "Feature",
  "properties": {
    "tgn:hierarchy":[
        "tgn:7554499",
        "tgn:1000004",
        "tgn:7000198",
        "tgn:1003539",
        "tgn:7029392"
    ],
    "tgn:id":7554499,
    "tgn:name:en":"Nongjrong",
    "tgn:placetype":[
        "aat:300008347"
    ]
},
  "bbox": [],
  "geometry": {"coordinates":[92.492962,25.705493],"type":"Point"}
}