{
  "id": 7142729,
  "type": "Feature",
  "properties": {
    "tgn:hierarchy":[
        "tgn:7142729",
        "tgn:1000003",
        "tgn:7003677",
        "tgn:7000084",
        "tgn:7029392"
    ],
    "tgn:id":7142729,
    "tgn:name":"L\u00fcdershof",
    "tgn:placetype":[
        "aat:300000206"
    ]
},
  "bbox": [],
  "geometry": {"coordinates":[8.966667,51.983333],"type":"Point"}
}