{
  "id": 2610413,
  "type": "Feature",
  "properties": {
    "tgn:hierarchy":[
        "tgn:2610413",
        "tgn:1000001",
        "tgn:7006451",
        "tgn:7012149",
        "tgn:2000103",
        "tgn:7029392"
    ],
    "tgn:id":2610413,
    "tgn:name":"Red Canyon",
    "tgn:placetype":[
        "aat:300008761"
    ]
},
  "bbox": [],
  "geometry": {"coordinates":[-111.8833,34.9167],"type":"Point"}
}