{
  "id": 2515760,
  "type": "Feature",
  "properties": {
    "tgn:hierarchy":[
        "tgn:2515760",
        "tgn:1000001",
        "tgn:2000466",
        "tgn:7012149",
        "tgn:7007250",
        "tgn:7029392"
    ],
    "tgn:id":2515760,
    "tgn:name":"Millward Spring",
    "tgn:placetype":[
        "aat:300008697"
    ]
},
  "bbox": [],
  "geometry": {"coordinates":[-111.85,42.8667],"type":"Point"}
}