<<<<<<< HEAD
{
  "id": 7028076,
  "type": "Feature",
  "properties": {
    "tgn:hierarchy":[
        "tgn:7028076",
        "tgn:7002445",
        "tgn:1000003",
        "tgn:7008157",
        "tgn:7008591",
        "tgn:7029392"
    ],
    "tgn:id":7028076,
    "tgn:name:en":"Scrivelsby",
    "tgn:placetype":[
        "aat:300008347",
        "aat:300008372"
    ]
},
  "bbox": [],
  "geometry": {"coordinates":[-0.1,53.183333],"type":"Point"}
}
=======
{"geometry":{"type":"Point","coordinates":[-0.100000,53.183333]},"type":"Feature","properties":{"hierarchy":["tgn:7028076","tgn:7002445","tgn:1000003","tgn:7008157","tgn:7008591","tgn:7029392"],"placetype":["aat:300008347","aat:300008372"],"name:en":"Scrivelsby","id":7028076}}
>>>>>>> 03f74aca74312dbeaf24d7e61306dd6a786dc3d0
