{
  "id": 7493725,
  "type": "Feature",
  "properties": {
    "tgn:hierarchy":[
        "tgn:7493725",
        "tgn:7468018",
        "tgn:1000004",
        "tgn:1000141",
        "tgn:7029392"
    ],
    "tgn:id":7493725,
    "tgn:name":"Zhongzheng Guoxiao",
    "tgn:placetype":[
        "aat:300006495"
    ]
},
  "bbox": [],
  "geometry": {"coordinates":[120.572726,23.436996],"type":"Point"}
}