{
  "id": 2513592,
  "type": "Feature",
  "properties": {
    "tgn:hierarchy":[
        "tgn:2513592",
        "tgn:1000001",
        "tgn:7012149",
        "tgn:2000981",
        "tgn:7007520",
        "tgn:7029392"
    ],
    "tgn:id":2513592,
    "tgn:name":"Mill Pond",
    "tgn:placetype":[
        "aat:300008680"
    ]
},
  "bbox": [],
  "geometry": {"coordinates":[-85.5167,43.3667],"type":"Point"}
}