{
  "id": 2263659,
  "type": "Feature",
  "properties": {
    "tgn:hierarchy":[
        "tgn:2263659",
        "tgn:2000452",
        "tgn:1000001",
        "tgn:7012149",
        "tgn:7007250",
        "tgn:7029392"
    ],
    "tgn:id":2263659,
    "tgn:name":"Coyote Butte",
    "tgn:placetype":[
        "aat:300008798"
    ]
},
  "bbox": [],
  "geometry": {"coordinates":[-116.3667,43.3167],"type":"Point"}
}