{
  "id": 2495486,
  "type": "Feature",
  "properties": {
    "tgn:hierarchy":[
        "tgn:2495486",
        "tgn:1000001",
        "tgn:7012149",
        "tgn:2001915",
        "tgn:7007825",
        "tgn:7029392"
    ],
    "tgn:id":2495486,
    "tgn:name":"Marys Creek Lake Number Nine",
    "tgn:placetype":[
        "aat:300006191"
    ]
},
  "bbox": [],
  "geometry": {"coordinates":[-89.65,35.1333],"type":"Point"}
}