{
  "id": 7572166,
  "type": "Feature",
  "properties": {
    "tgn:hierarchy":[
        "tgn:7572166",
        "tgn:1000004",
        "tgn:7000198",
        "tgn:7016788",
        "tgn:7029392"
    ],
    "tgn:id":7572166,
    "tgn:name:en":"Hingoli",
    "tgn:placetype":[
        "aat:300008347"
    ]
},
  "bbox": [],
  "geometry": {"coordinates":[73.475673,26.720313],"type":"Point"}
}