{
  "id": 7475829,
  "type": "Feature",
  "properties": {
    "tgn:hierarchy":[
        "tgn:7475829",
        "tgn:7488858",
        "tgn:1000004",
        "tgn:1000141",
        "tgn:7029392"
    ],
    "tgn:id":7475829,
    "tgn:name":"Gugushan",
    "tgn:placetype":[
        "aat:300008347"
    ]
},
  "bbox": [],
  "geometry": {"coordinates":[120.966434,23.793616],"type":"Point"}
}