<<<<<<< HEAD
{
  "id": 7475829,
  "type": "Feature",
  "properties": {
    "tgn:hierarchy":[
        "tgn:7475829",
        "tgn:7488858",
        "tgn:1000004",
        "tgn:1000141",
        "tgn:7029392"
    ],
    "tgn:id":7475829,
    "tgn:name":"Gugushan",
    "tgn:placetype":[
        "aat:300008347"
    ]
},
  "bbox": [],
  "geometry": {"coordinates":[120.966434,23.793616],"type":"Point"}
}
=======
{"geometry":{"type":"Point","coordinates":[120.966434,23.793616]},"type":"Feature","properties":{"hierarchy":["tgn:7475829","tgn:7488858","tgn:1000004","tgn:1000141","tgn:7029392"],"placetype":["aat:300008347"],"id":7475829,"name:xx":"Gugushan"}}
>>>>>>> 03f74aca74312dbeaf24d7e61306dd6a786dc3d0
