{
  "id": 7050329,
  "type": "Feature",
  "properties": {
    "tgn:hierarchy":[
        "tgn:7050329",
        "tgn:7015163",
        "tgn:1000003",
        "tgn:7003121",
        "tgn:1000080",
        "tgn:7029392"
    ],
    "tgn:id":7050329,
    "tgn:name":"Nuchis",
    "tgn:placetype":[
        "aat:300008347"
    ]
},
  "bbox": [],
  "geometry": {"coordinates":[9.15,40.916667],"type":"Point"}
}