{
  "id": 7316193,
  "type": "Feature",
  "properties": {
    "tgn:hierarchy":[
        "tgn:7316193",
        "tgn:1001623",
        "tgn:1000049",
        "tgn:1000002",
        "tgn:7029392"
    ],
    "tgn:id":7316193,
    "tgn:name":"Catarata, Arroyo",
    "tgn:placetype":[
        "aat:300008699"
    ]
},
  "bbox": [],
  "geometry": {"coordinates":[-72.833333,-47.683333],"type":"Point"}
}