<<<<<<< HEAD
{
  "id": 2256458,
  "type": "Feature",
  "properties": {
    "tgn:hierarchy":[
        "tgn:2256458",
        "tgn:1000001",
        "tgn:7012149",
        "tgn:2001446",
        "tgn:7007566",
        "tgn:7029392"
    ],
    "tgn:id":2256458,
    "tgn:name":"Coral Spring",
    "tgn:placetype":[
        "aat:300008697"
    ]
},
  "bbox": [],
  "geometry": {"coordinates":[-104.7,36.0333],"type":"Point"}
}
=======
{"geometry":{"type":"Point","coordinates":[-104.700000,36.033300]},"type":"Feature","properties":{"hierarchy":["tgn:2256458","tgn:1000001","tgn:7012149","tgn:2001446","tgn:7007566","tgn:7029392"],"placetype":["aat:300008697"],"id":2256458,"name:xx":"Coral Spring"}}
>>>>>>> 03f74aca74312dbeaf24d7e61306dd6a786dc3d0
