{
  "id": 7080236,
  "type": "Feature",
  "properties": {
    "tgn:hierarchy":[
        "tgn:7080236",
        "tgn:7000096",
        "tgn:1000003",
        "tgn:7000084",
        "tgn:7029392"
    ],
    "tgn:id":7080236,
    "tgn:name":"Zechow",
    "tgn:placetype":[
        "aat:300008347"
    ]
},
  "bbox": [],
  "geometry": {"coordinates":[12.916667,53.05],"type":"Point"}
}