{
  "id": 2330173,
  "type": "Feature",
  "properties": {
    "tgn:hierarchy":[
        "tgn:2330173",
        "tgn:1000001",
        "tgn:2002105",
        "tgn:7012149",
        "tgn:7007827",
        "tgn:7029392"
    ],
    "tgn:id":2330173,
    "tgn:name":"Flaming Gorge Summer Home Area",
    "tgn:placetype":[
        "aat:300008347"
    ]
},
  "bbox": [],
  "geometry": {"coordinates":[-109.4667,40.8833],"type":"Point"}
}