{
  "id": 1107454,
  "type": "Feature",
  "properties": {
    "tgn:hierarchy":[
        "tgn:1107454",
        "tgn:1000001",
        "tgn:2001793",
        "tgn:7012149",
        "tgn:7007713",
        "tgn:7029392"
    ],
    "tgn:id":1107454,
    "tgn:name":"Parker Peak",
    "tgn:placetype":[
        "aat:300008798"
    ]
},
  "bbox": [],
  "geometry": {"coordinates":[-103.6833,43.3833],"type":"Point"}
}