{
  "id": 2280626,
  "type": "Feature",
  "properties": {
    "tgn:hierarchy":[
        "tgn:2280626",
        "tgn:1000001",
        "tgn:7012149",
        "tgn:7007157",
        "tgn:1002828",
        "tgn:7029392"
    ],
    "tgn:id":2280626,
    "tgn:name":"Deep Canyon",
    "tgn:placetype":[
        "aat:300008761"
    ]
},
  "bbox": [],
  "geometry": {"coordinates":[-116.7667,33.9667],"type":"Point"}
}