{
  "id": 1006079,
  "type": "Feature",
  "properties": {
    "tgn:hierarchy":[
        "tgn:1006079",
        "tgn:1010215",
        "tgn:1000217",
        "tgn:1000006",
        "tgn:7029392"
    ],
    "tgn:id":1006079,
    "tgn:name":"Nikumaroro",
    "tgn:placetype":[
        "aat:300008793"
    ]
},
  "bbox": [],
  "geometry": {"coordinates":[-174.5333,-4.6667],"type":"Point"}
}