{
  "id": 2331815,
  "type": "Feature",
  "properties": {
    "tgn:hierarchy":[
        "tgn:2331815",
        "tgn:1000001",
        "tgn:7016172",
        "tgn:7012149",
        "tgn:2000144",
        "tgn:7029392"
    ],
    "tgn:id":2331815,
    "tgn:name":"Fletcher Brake",
    "tgn:placetype":[
        "aat:300008905"
    ]
},
  "bbox": [],
  "geometry": {"coordinates":[-91.5667,33.85],"type":"Point"}
}