<<<<<<< HEAD
{
  "id": 2405720,
  "type": "Feature",
  "properties": {
    "tgn:hierarchy":[
        "tgn:2405720",
        "tgn:1000001",
        "tgn:7012149",
        "tgn:2002118",
        "tgn:7007827",
        "tgn:7029392"
    ],
    "tgn:id":2405720,
    "tgn:name":"Huish",
    "tgn:placetype":[
        "aat:300008347"
    ]
},
  "bbox": [],
  "geometry": {"coordinates":[-111.85,40.6],"type":"Point"}
}
=======
{"geometry":{"type":"Point","coordinates":[-111.850000,40.600000]},"type":"Feature","properties":{"hierarchy":["tgn:2405720","tgn:1000001","tgn:7012149","tgn:2002118","tgn:7007827","tgn:7029392"],"placetype":["aat:300008347"],"id":2405720,"name:xx":"Huish"}}
>>>>>>> 03f74aca74312dbeaf24d7e61306dd6a786dc3d0
