{
  "id": 7467528,
  "type": "Feature",
  "properties": {
    "tgn:hierarchy":[
        "tgn:7467528",
        "tgn:7001010",
        "tgn:1000004",
        "tgn:1000141",
        "tgn:7029392"
    ],
    "tgn:id":7467528,
    "tgn:name":"Chinancun",
    "tgn:placetype":[
        "aat:300008347"
    ]
},
  "bbox": [],
  "geometry": {"coordinates":[121.506204,23.91952],"type":"Point"}
}