<<<<<<< HEAD
{
  "id": 2333188,
  "type": "Feature",
  "properties": {
    "tgn:hierarchy":[
        "tgn:2333188",
        "tgn:1000001",
        "tgn:7012149",
        "tgn:2002374",
        "tgn:7007923",
        "tgn:7029392"
    ],
    "tgn:id":2333188,
    "tgn:name":"Flynn Draw",
    "tgn:placetype":[
        "aat:300008761"
    ]
},
  "bbox": [],
  "geometry": {"coordinates":[-106.6,43.6833],"type":"Point"}
}
=======
{"geometry":{"type":"Point","coordinates":[-106.600000,43.683300]},"type":"Feature","properties":{"hierarchy":["tgn:2333188","tgn:1000001","tgn:7012149","tgn:2002374","tgn:7007923","tgn:7029392"],"placetype":["aat:300008761"],"id":2333188,"name:xx":"Flynn Draw"}}
>>>>>>> 03f74aca74312dbeaf24d7e61306dd6a786dc3d0
