{
  "id": 2213452,
  "type": "Feature",
  "properties": {
    "tgn:hierarchy":[
        "tgn:2213452",
        "tgn:1000001",
        "tgn:1002294",
        "tgn:7012149",
        "tgn:7007710",
        "tgn:7029392"
    ],
    "tgn:id":2213452,
    "tgn:name":"Cabin Run",
    "tgn:placetype":[
        "aat:300008699"
    ]
},
  "bbox": [],
  "geometry": {"coordinates":[-76.3667,41.05],"type":"Point"}
}