{
  "id": 1098932,
  "type": "Feature",
  "properties": {
    "tgn:hierarchy":[
        "tgn:1098932",
        "tgn:1009227",
        "tgn:1000226",
        "tgn:7016729",
        "tgn:1000006",
        "tgn:7029392"
    ],
    "tgn:id":1098932,
    "tgn:name:en":"French Pass",
    "tgn:placetype":[
        "aat:300259572"
    ]
},
  "bbox": [],
  "geometry": {"coordinates":[173.85,-40.9167],"type":"Point"}
}