{
  "id": 2340837,
  "type": "Feature",
  "properties": {
    "tgn:hierarchy":[
        "tgn:2340837",
        "tgn:1000001",
        "tgn:2000324",
        "tgn:7012149",
        "tgn:7007248",
        "tgn:7029392"
    ],
    "tgn:id":2340837,
    "tgn:name":"Frey Lake",
    "tgn:placetype":[
        "aat:300008680"
    ]
},
  "bbox": [],
  "geometry": {"coordinates":[-84.5833,34.0333],"type":"Point"}
}