{
  "id": 2239077,
  "type": "Feature",
  "properties": {
    "tgn:hierarchy":[
        "tgn:2239077",
        "tgn:2000946",
        "tgn:1000001",
        "tgn:7012149",
        "tgn:7007520",
        "tgn:7029392"
    ],
    "tgn:id":2239077,
    "tgn:name":"Chub Creek",
    "tgn:placetype":[
        "aat:300008706"
    ]
},
  "bbox": [],
  "geometry": {"coordinates":[-83.8667,44.1167],"type":"Point"}
}