{
  "id": 7526073,
  "type": "Feature",
  "properties": {
    "tgn:hierarchy":[
        "tgn:7526073",
        "tgn:7001242",
        "tgn:7016833",
        "tgn:1001091",
        "tgn:7029392"
    ],
    "tgn:id":7526073,
    "tgn:name":"Shirkat ash Sharq al Awsa\u0163 li \u015ein\u0101'at az Zuj\u0101j",
    "tgn:placetype":[
        "aat:300004792"
    ]
},
  "bbox": [],
  "geometry": {"coordinates":[31.314895,30.045795],"type":"Point"}
}