{
  "id": 7263292,
  "type": "Feature",
  "properties": {
    "tgn:concordances":{
        "gn:id":"2757548"
    },
    "tgn:hierarchy":[
        "tgn:7263292",
        "tgn:1000003",
        "tgn:7006951",
        "tgn:7016845",
        "tgn:7029392"
    ],
    "tgn:id":7263292,
    "tgn:name:nl":"De Heul",
    "tgn:placetype":[
        "aat:300008347"
    ]
},
  "bbox": [],
  "geometry": {"coordinates":[4.866667,52.45],"type":"Point"}
}