{
  "id": 2272028,
  "type": "Feature",
  "properties": {
    "tgn:hierarchy":[
        "tgn:2272028",
        "tgn:1000001",
        "tgn:7012149",
        "tgn:7007705",
        "tgn:7029392"
    ],
    "tgn:id":2272028,
    "tgn:name":"Curlew Valley",
    "tgn:placetype":[
        "aat:300008761"
    ]
},
  "bbox": [],
  "geometry": {"coordinates":[-101.7333,46.8167],"type":"Point"}
}