<<<<<<< HEAD
{
  "id": 7171156,
  "type": "Feature",
  "properties": {
    "tgn:hierarchy":[
        "tgn:7171156",
        "tgn:1000003",
        "tgn:7003687",
        "tgn:7000084",
        "tgn:7029392"
    ],
    "tgn:id":7171156,
    "tgn:name":"Herzfelder Haken",
    "tgn:placetype":[
        "aat:300008680"
    ]
},
  "bbox": [],
  "geometry": {"coordinates":[11.816667,52.916667],"type":"Point"}
}
=======
{"geometry":{"type":"Point","coordinates":[11.816667,52.916667]},"type":"Feature","properties":{"hierarchy":["tgn:7171156","tgn:1000003","tgn:7003687","tgn:7000084","tgn:7029392"],"placetype":["aat:300008680"],"id":7171156,"name:xx":"Herzfelder Haken"}}
>>>>>>> 03f74aca74312dbeaf24d7e61306dd6a786dc3d0
