{
  "id": 7171156,
  "type": "Feature",
  "properties": {
    "tgn:hierarchy":[
        "tgn:7171156",
        "tgn:1000003",
        "tgn:7003687",
        "tgn:7000084",
        "tgn:7029392"
    ],
    "tgn:id":7171156,
    "tgn:name":"Herzfelder Haken",
    "tgn:placetype":[
        "aat:300008680"
    ]
},
  "bbox": [],
  "geometry": {"coordinates":[11.816667,52.916667],"type":"Point"}
}