{
  "id": 2666232,
  "type": "Feature",
  "properties": {
    "tgn:hierarchy":[
        "tgn:2666232",
        "tgn:7002659",
        "tgn:1000001",
        "tgn:2000003",
        "tgn:7012149",
        "tgn:7029392"
    ],
    "tgn:id":2666232,
    "tgn:name":"Six Mile Creek Cave",
    "tgn:placetype":[
        "aat:300008746"
    ]
},
  "bbox": [],
  "geometry": {"coordinates":[-87.0167,33.0167],"type":"Point"}
}