{
  "id": 7260351,
  "type": "Feature",
  "properties": {
    "tgn:hierarchy":[
        "tgn:7260351",
        "tgn:7003619",
        "tgn:1000003",
        "tgn:7016845",
        "tgn:7029392"
    ],
    "tgn:id":7260351,
    "tgn:name:nl":"Ermelose Heide",
    "tgn:placetype":[
        "aat:300386887"
    ]
},
  "bbox": [],
  "geometry": {"coordinates":[5.683333,52.283333],"type":"Point"}
}