<<<<<<< HEAD
{
  "id": 7054751,
  "type": "Feature",
  "properties": {
    "tgn:hierarchy":[
        "tgn:7054751",
        "tgn:7003170",
        "tgn:1000003",
        "tgn:7003125",
        "tgn:1000080",
        "tgn:7029392"
    ],
    "tgn:id":7054751,
    "tgn:name":"Padonchia",
    "tgn:placetype":[
        "aat:300008347"
    ]
},
  "bbox": [],
  "geometry": {"coordinates":[12.1,43.466667],"type":"Point"}
}
=======
{"geometry":{"type":"Point","coordinates":[12.100000,43.466667]},"type":"Feature","properties":{"hierarchy":["tgn:7054751","tgn:7003170","tgn:1000003","tgn:7003125","tgn:1000080","tgn:7029392"],"placetype":["aat:300008347"],"id":7054751,"name:xx":"Padonchia"}}
>>>>>>> 03f74aca74312dbeaf24d7e61306dd6a786dc3d0
