{
  "id": 2642496,
  "type": "Feature",
  "properties": {
    "tgn:hierarchy":[
        "tgn:2642496",
        "tgn:1000001",
        "tgn:7012149",
        "tgn:7014589",
        "tgn:7007515",
        "tgn:7029392"
    ],
    "tgn:id":2642496,
    "tgn:name":"Sandbar, The",
    "tgn:placetype":[
        "aat:300132348"
    ]
},
  "bbox": [],
  "geometry": {"coordinates":[-67.9333,45.6167],"type":"Point"}
}