{
  "id": 7579253,
  "type": "Feature",
  "properties": {
    "tgn:hierarchy":[
        "tgn:7579253",
        "tgn:1000004",
        "tgn:7000198",
        "tgn:7001797",
        "tgn:7029392"
    ],
    "tgn:id":7579253,
    "tgn:name:en":"Taruvaikkulam",
    "tgn:placetype":[
        "aat:300008347"
    ]
},
  "bbox": [],
  "geometry": {"coordinates":[78.166667,8.883333],"type":"Point"}
}