{
  "id": 2463426,
  "type": "Feature",
  "properties": {
    "tgn:hierarchy":[
        "tgn:2463426",
        "tgn:1000001",
        "tgn:7012149",
        "tgn:2001864",
        "tgn:7007825",
        "tgn:7029392"
    ],
    "tgn:id":2463426,
    "tgn:name":"Lloyd Hollow",
    "tgn:placetype":[
        "aat:300008761"
    ]
},
  "bbox": [],
  "geometry": {"coordinates":[-86.8333,35.1167],"type":"Point"}
}