{
  "id": 2067516,
  "type": "Feature",
  "properties": {
    "tgn:hierarchy":[
        "tgn:2067516",
        "tgn:1000001",
        "tgn:7012149",
        "tgn:2001438",
        "tgn:7007566",
        "tgn:7029392"
    ],
    "tgn:id":2067516,
    "tgn:name":"Santa Rosa",
    "tgn:placetype":[
        "aat:300008347",
        "aat:300008416"
    ]
},
  "bbox": [],
  "geometry": {"coordinates":[-104.6667,34.9333],"type":"Point"}
}