{
  "id": 2308303,
  "type": "Feature",
  "properties": {
    "tgn:hierarchy":[
        "tgn:2308303",
        "tgn:1000001",
        "tgn:7012149",
        "tgn:1003020",
        "tgn:7007920",
        "tgn:7029392"
    ],
    "tgn:id":2308303,
    "tgn:name":"East Lakes",
    "tgn:placetype":[
        "aat:300008680"
    ]
},
  "bbox": [],
  "geometry": {"coordinates":[-121.3333,48.8833],"type":"Point"}
}