{
  "id": 2490710,
  "type": "Feature",
  "properties": {
    "tgn:hierarchy":[
        "tgn:2490710",
        "tgn:1000001",
        "tgn:7012149",
        "tgn:2001486",
        "tgn:7007709",
        "tgn:7029392"
    ],
    "tgn:id":2490710,
    "tgn:name":"Manning Park",
    "tgn:placetype":[
        "aat:300008347"
    ]
},
  "bbox": [],
  "geometry": {"coordinates":[-77.1167,35.0667],"type":"Point"}
}