{
  "id": 1013215,
  "type": "Feature",
  "properties": {
    "tgn:hierarchy":[
        "tgn:1013215",
        "tgn:7005694",
        "tgn:7005685",
        "tgn:1000001",
        "tgn:7029392"
    ],
    "tgn:id":1013215,
    "tgn:name":"Kitscoty",
    "tgn:placetype":[
        "aat:300008347"
    ]
},
  "bbox": [],
  "geometry": {"coordinates":[-110.3667,53.3667],"type":"Point"}
}