{
  "id": 2661114,
  "type": "Feature",
  "properties": {
    "tgn:hierarchy":[
        "tgn:2661114",
        "tgn:1000001",
        "tgn:7012149",
        "tgn:1002636",
        "tgn:7007708",
        "tgn:7029392"
    ],
    "tgn:id":2661114,
    "tgn:name":"Short Lake",
    "tgn:placetype":[
        "aat:300008680"
    ]
},
  "bbox": [],
  "geometry": {"coordinates":[-121.9833,44.7833],"type":"Point"}
}