{
  "id": 2141754,
  "type": "Feature",
  "properties": {
    "tgn:hierarchy":[
        "tgn:2141754",
        "tgn:1000001",
        "tgn:7012149",
        "tgn:2001711",
        "tgn:7007708",
        "tgn:7029392"
    ],
    "tgn:id":2141754,
    "tgn:name":"Babe Creek",
    "tgn:placetype":[
        "aat:300008706"
    ]
},
  "bbox": [],
  "geometry": {"coordinates":[-122.5333,42.25],"type":"Point"}
}