{
  "id": 7454241,
  "type": "Feature",
  "properties": {
    "tgn:hierarchy":[
        "tgn:7454241",
        "tgn:7002445",
        "tgn:1000003",
        "tgn:7008165",
        "tgn:7008591",
        "tgn:7029392"
    ],
    "tgn:id":7454241,
    "tgn:name:en":"Budle Bay",
    "tgn:placetype":[
        "aat:300132316"
    ]
},
  "bbox": [],
  "geometry": {"coordinates":[-1.75,55.616667],"type":"Point"}
}