{
  "id": 2537051,
  "type": "Feature",
  "properties": {
    "tgn:hierarchy":[
        "tgn:2537051",
        "tgn:1000001",
        "tgn:7012149",
        "tgn:2000789",
        "tgn:7007255",
        "tgn:7029392"
    ],
    "tgn:id":2537051,
    "tgn:name":"Neely Branch",
    "tgn:placetype":[
        "aat:300008699"
    ]
},
  "bbox": [],
  "geometry": {"coordinates":[-82.85,37.65],"type":"Point"}
}