{
  "id": 7508146,
  "type": "Feature",
  "properties": {
    "tgn:hierarchy":[
        "tgn:7508146",
        "tgn:1008380",
        "tgn:1000226",
        "tgn:7016827",
        "tgn:1000006",
        "tgn:7029392"
    ],
    "tgn:id":7508146,
    "tgn:name:en":"Paraoa Stream",
    "tgn:placetype":[
        "aat:300008699"
    ]
},
  "bbox": [],
  "geometry": {"coordinates":[174.833333,-39.616667],"type":"Point"}
}