{
  "id": 7006271,
  "type": "Feature",
  "properties": {
    "tgn:hierarchy":[
        "tgn:7006271",
        "tgn:1000003",
        "tgn:1000077",
        "tgn:7029392"
    ],
    "tgn:id":7006271,
    "tgn:name":"Su\u00f0ur-M\u00falas\u00fdsla",
    "tgn:placetype":[
        "aat:300387064",
        "aat:300387173"
    ]
},
  "bbox": [],
  "geometry": {"coordinates":[-18.1333,65.7333],"type":"Point"}
}