{
  "id": 7250672,
  "type": "Feature",
  "properties": {
    "tgn:hierarchy":[
        "tgn:7250672",
        "tgn:7003458",
        "tgn:1000003",
        "tgn:1000063",
        "tgn:7018236",
        "tgn:7029392"
    ],
    "tgn:id":7250672,
    "tgn:name":"Puwitte",
    "tgn:placetype":[
        "aat:300000206"
    ]
},
  "bbox": [],
  "geometry": {"coordinates":[3.283333,51.083333],"type":"Point"}
}