<<<<<<< HEAD
{
  "id": 7176813,
  "type": "Feature",
  "properties": {
    "tgn:hierarchy":[
        "tgn:7176813",
        "tgn:7000096",
        "tgn:1000003",
        "tgn:7000084",
        "tgn:7029392"
    ],
    "tgn:id":7176813,
    "tgn:name":"G\u00fcterbank",
    "tgn:placetype":[
        "aat:300266640"
    ]
},
  "bbox": [],
  "geometry": {"coordinates":[13.5,51.483333],"type":"Point"}
}
=======
{"geometry":{"type":"Point","coordinates":[13.500000,51.483333]},"type":"Feature","properties":{"hierarchy":["tgn:7176813","tgn:7000096","tgn:1000003","tgn:7000084","tgn:7029392"],"placetype":["aat:300266640"],"id":7176813,"name:xx":"G\u00fcterbank"}}
>>>>>>> 03f74aca74312dbeaf24d7e61306dd6a786dc3d0
