{
  "id": 2042114,
  "type": "Feature",
  "properties": {
    "tgn:hierarchy":[
        "tgn:2042114",
        "tgn:1000001",
        "tgn:2000866",
        "tgn:7012149",
        "tgn:7007256",
        "tgn:7029392"
    ],
    "tgn:id":2042114,
    "tgn:name":"Aimwell",
    "tgn:placetype":[
        "aat:300008347"
    ]
},
  "bbox": [],
  "geometry": {"coordinates":[-91.9833,31.7833],"type":"Point"}
}