{
  "id": 1025136,
  "type": "Feature",
  "properties": {
    "tgn:hierarchy":[
        "tgn:1025136",
        "tgn:1001963",
        "tgn:1000002",
        "tgn:1000059",
        "tgn:7029392"
    ],
    "tgn:id":1025136,
    "tgn:name":"G\u00fciria",
    "tgn:placetype":[
        "aat:300008347"
    ]
},
  "bbox": [],
  "geometry": {"coordinates":[-62.35,10.6167],"type":"Point"}
}