{
  "id": 2452515,
  "type": "Feature",
  "properties": {
    "tgn:hierarchy":[
        "tgn:2452515",
        "tgn:1000001",
        "tgn:7012149",
        "tgn:2002277",
        "tgn:7013961",
        "tgn:7029392"
    ],
    "tgn:id":2452515,
    "tgn:name":"Little Broad Run",
    "tgn:placetype":[
        "aat:300008699"
    ]
},
  "bbox": [],
  "geometry": {"coordinates":[-81.95,38.9333],"type":"Point"}
}