{
  "id": 7361509,
  "type": "Feature",
  "properties": {
    "tgn:hierarchy":[
        "tgn:7361509",
        "tgn:7016644",
        "tgn:1000001",
        "tgn:7005560",
        "tgn:7029392"
    ],
    "tgn:id":7361509,
    "tgn:name":"El Corralillo",
    "tgn:placetype":[
        "aat:300008347"
    ]
},
  "bbox": [],
  "geometry": {"coordinates":[-102.983333,23.183333],"type":"Point"}
}