{
  "id": 7413473,
  "type": "Feature",
  "properties": {
    "tgn:hierarchy":[
        "tgn:7413473",
        "tgn:7005580",
        "tgn:1000001",
        "tgn:7005560",
        "tgn:7029392"
    ],
    "tgn:id":7413473,
    "tgn:name":"Oigelito",
    "tgn:placetype":[
        "aat:300008347"
    ]
},
  "bbox": [],
  "geometry": {"coordinates":[-92.829167,16.733333],"type":"Point"}
}