{
  "id": 7484000,
  "type": "Feature",
  "properties": {
    "tgn:hierarchy":[
        "tgn:7484000",
        "tgn:7468018",
        "tgn:1000004",
        "tgn:1000141",
        "tgn:7029392"
    ],
    "tgn:id":7484000,
    "tgn:name":"Jiaolong Qiao",
    "tgn:placetype":[
        "aat:300007836"
    ]
},
  "bbox": [],
  "geometry": {"coordinates":[120.749167,23.568611],"type":"Point"}
}