{
  "id": 2299267,
  "type": "Feature",
  "properties": {
    "tgn:hierarchy":[
        "tgn:2299267",
        "tgn:7006450",
        "tgn:1000001",
        "tgn:7012149",
        "tgn:2000086",
        "tgn:7029392"
    ],
    "tgn:id":2299267,
    "tgn:name":"Duck Lake",
    "tgn:placetype":[
        "aat:300008680"
    ]
},
  "bbox": [],
  "geometry": {"coordinates":[-144.0167,62.6167],"type":"Point"}
}