{
  "id": 7105390,
  "type": "Feature",
  "properties": {
    "tgn:hierarchy":[
        "tgn:7105390",
        "tgn:1000003",
        "tgn:7003688",
        "tgn:7000084",
        "tgn:7029392"
    ],
    "tgn:id":7105390,
    "tgn:name":"Schnappen",
    "tgn:placetype":[
        "aat:300000206"
    ]
},
  "bbox": [],
  "geometry": {"coordinates":[8.866667,54.15],"type":"Point"}
}