{
  "id": 2326579,
  "type": "Feature",
  "properties": {
    "tgn:hierarchy":[
        "tgn:2326579",
        "tgn:1000001",
        "tgn:7012149",
        "tgn:7007920",
        "tgn:7029392"
    ],
    "tgn:id":2326579,
    "tgn:name":"Finley Creek",
    "tgn:placetype":[
        "aat:300008706"
    ]
},
  "bbox": [],
  "geometry": {"coordinates":[-123.7667,47.5833],"type":"Point"}
}