{
  "id": 2665976,
  "type": "Feature",
  "properties": {
    "tgn:hierarchy":[
        "tgn:2665976",
        "tgn:1000001",
        "tgn:7016172",
        "tgn:2000112",
        "tgn:7012149",
        "tgn:7029392"
    ],
    "tgn:id":2665976,
    "tgn:name":"Sister Knob",
    "tgn:placetype":[
        "aat:300008798"
    ]
},
  "bbox": [],
  "geometry": {"coordinates":[-93.55,36.3833],"type":"Point"}
}