{
  "id": 1065688,
  "type": "Feature",
  "properties": {
    "tgn:hierarchy":[
        "tgn:1065688",
        "tgn:1000004",
        "tgn:7000190",
        "tgn:1000105",
        "tgn:7029392"
    ],
    "tgn:id":1065688,
    "tgn:name":"Dumria",
    "tgn:placetype":[
        "aat:300008347"
    ]
},
  "bbox": [],
  "geometry": {"coordinates":[89.4333,22.7833],"type":"Point"}
}