{
  "id": 2273669,
  "type": "Feature",
  "properties": {
    "tgn:hierarchy":[
        "tgn:2273669",
        "tgn:1000001",
        "tgn:7012149",
        "tgn:7007157",
        "tgn:1002828",
        "tgn:7029392"
    ],
    "tgn:id":2273669,
    "tgn:name":"D Canal",
    "tgn:placetype":[
        "aat:300006075"
    ]
},
  "bbox": [],
  "geometry": {"coordinates":[-114.5833,33.5833],"type":"Point"}
}