{
  "id": 7580159,
  "type": "Feature",
  "properties": {
    "tgn:hierarchy":[
        "tgn:7580159",
        "tgn:1000004",
        "tgn:7000198",
        "tgn:1001894",
        "tgn:7029392"
    ],
    "tgn:id":7580159,
    "tgn:name:en":"Sri Chhatarpur",
    "tgn:placetype":[
        "aat:300008347"
    ]
},
  "bbox": [],
  "geometry": {"coordinates":[75.935264,24.542772],"type":"Point"}
}