{
  "id": 2731010,
  "type": "Feature",
  "properties": {
    "tgn:hierarchy":[
        "tgn:2731010",
        "tgn:1000001",
        "tgn:7012149",
        "tgn:7029392"
    ],
    "tgn:id":2731010,
    "tgn:name":"Tuckabum Creek",
    "tgn:placetype":[
        "aat:300008706"
    ]
},
  "bbox": [],
  "geometry": {"coordinates":[-88.45,32.25],"type":"Point"}
}