{
  "id": 2535598,
  "type": "Feature",
  "properties": {
    "tgn:hierarchy":[
        "tgn:2535598",
        "tgn:7006450",
        "tgn:1000001",
        "tgn:7012149",
        "tgn:2000088",
        "tgn:7029392"
    ],
    "tgn:id":2535598,
    "tgn:name":"Narrows Peak",
    "tgn:placetype":[
        "aat:300008798"
    ]
},
  "bbox": [],
  "geometry": {"coordinates":[-132.9667,56.8333],"type":"Point"}
}