<<<<<<< HEAD
{
  "id": 2155479,
  "type": "Feature",
  "properties": {
    "tgn:hierarchy":[
        "tgn:2155479",
        "tgn:1000001",
        "tgn:7012149",
        "tgn:2001722",
        "tgn:7007708",
        "tgn:7029392"
    ],
    "tgn:id":2155479,
    "tgn:name":"Bear Ridge",
    "tgn:placetype":[
        "aat:300266640"
    ]
},
  "bbox": [],
  "geometry": {"coordinates":[-116.9833,45.8667],"type":"Point"}
}
=======
{"geometry":{"type":"Point","coordinates":[-116.983300,45.866700]},"type":"Feature","properties":{"hierarchy":["tgn:2155479","tgn:1000001","tgn:7012149","tgn:2001722","tgn:7007708","tgn:7029392"],"placetype":["aat:300266640"],"id":2155479,"name:xx":"Bear Ridge"}}
>>>>>>> 03f74aca74312dbeaf24d7e61306dd6a786dc3d0
