<<<<<<< HEAD
{
  "id": 2256192,
  "type": "Feature",
  "properties": {
    "tgn:hierarchy":[
        "tgn:2256192",
        "tgn:1000001",
        "tgn:7012149",
        "tgn:2001885",
        "tgn:7007825",
        "tgn:7029392"
    ],
    "tgn:id":2256192,
    "tgn:name":"Copper Springs Creek",
    "tgn:placetype":[
        "aat:300008706"
    ]
},
  "bbox": [],
  "geometry": {"coordinates":[-89.6167,35.7],"type":"Point"}
}
=======
{"geometry":{"type":"Point","coordinates":[-89.616700,35.700000]},"type":"Feature","properties":{"hierarchy":["tgn:2256192","tgn:1000001","tgn:7012149","tgn:2001885","tgn:7007825","tgn:7029392"],"placetype":["aat:300008706"],"id":2256192,"name:xx":"Copper Springs Creek"}}
>>>>>>> 03f74aca74312dbeaf24d7e61306dd6a786dc3d0
