{
  "id": 7102819,
  "type": "Feature",
  "properties": {
    "tgn:hierarchy":[
        "tgn:7102819",
        "tgn:7003692",
        "tgn:1000003",
        "tgn:7000084",
        "tgn:7029392"
    ],
    "tgn:id":7102819,
    "tgn:name":"Sachsenweiler",
    "tgn:placetype":[
        "aat:300008347"
    ]
},
  "bbox": [],
  "geometry": {"coordinates":[9.45,48.95],"type":"Point"}
}