{
  "id": 1112763,
  "type": "Feature",
  "properties": {
    "tgn:hierarchy":[
        "tgn:1112763",
        "tgn:1000001",
        "tgn:7012149",
        "tgn:7007517",
        "tgn:7029392"
    ],
    "tgn:id":1112763,
    "tgn:name":"Cape Cod Bay",
    "tgn:placetype":[
        "aat:300132316"
    ]
},
  "bbox": [],
  "geometry": {"coordinates":[-70.4167,42.0333],"type":"Point"}
}