{
  "id": 2710986,
  "type": "Feature",
  "properties": {
    "tgn:hierarchy":[
        "tgn:2710986",
        "tgn:1000001",
        "tgn:7012149",
        "tgn:2001452",
        "tgn:7007566",
        "tgn:7029392"
    ],
    "tgn:id":2710986,
    "tgn:name":"Tank Mountain Spring",
    "tgn:placetype":[
        "aat:300008697"
    ]
},
  "bbox": [],
  "geometry": {"coordinates":[-107.8333,36.9167],"type":"Point"}
}