<<<<<<< HEAD
{
  "id": 2706369,
  "type": "Feature",
  "properties": {
    "tgn:hierarchy":[
        "tgn:2706369",
        "tgn:1000001",
        "tgn:7012149",
        "tgn:1002599",
        "tgn:7007708",
        "tgn:7029392"
    ],
    "tgn:id":2706369,
    "tgn:name":"Swampy Creek",
    "tgn:placetype":[
        "aat:300008706"
    ]
},
  "bbox": [],
  "geometry": {"coordinates":[-123.8167,45.0167],"type":"Point"}
}
=======
{"geometry":{"type":"Point","coordinates":[-123.816700,45.016700]},"type":"Feature","properties":{"hierarchy":["tgn:2706369","tgn:1000001","tgn:7012149","tgn:1002599","tgn:7007708","tgn:7029392"],"placetype":["aat:300008706"],"id":2706369,"name:xx":"Swampy Creek"}}
>>>>>>> 03f74aca74312dbeaf24d7e61306dd6a786dc3d0
