{
  "id": 2690313,
  "type": "Feature",
  "properties": {
    "tgn:hierarchy":[
        "tgn:2690313",
        "tgn:1000001",
        "tgn:7012149",
        "tgn:1002406",
        "tgn:7007520",
        "tgn:7029392"
    ],
    "tgn:id":2690313,
    "tgn:name":"Stage Island",
    "tgn:placetype":[
        "aat:300008791"
    ]
},
  "bbox": [],
  "geometry": {"coordinates":[-83.8167,42.7833],"type":"Point"}
}