<<<<<<< HEAD
{
  "id": 7170142,
  "type": "Feature",
  "properties": {
    "tgn:hierarchy":[
        "tgn:7170142",
        "tgn:7000096",
        "tgn:1000003",
        "tgn:7000084",
        "tgn:7029392"
    ],
    "tgn:id":7170142,
    "tgn:name":"Hobrich-Teich",
    "tgn:placetype":[
        "aat:300008903"
    ]
},
  "bbox": [],
  "geometry": {"coordinates":[14.433333,51.633333],"type":"Point"}
}
=======
{"geometry":{"type":"Point","coordinates":[14.433333,51.633333]},"type":"Feature","properties":{"hierarchy":["tgn:7170142","tgn:7000096","tgn:1000003","tgn:7000084","tgn:7029392"],"placetype":["aat:300008903"],"id":7170142,"name:xx":"Hobrich-Teich"}}
>>>>>>> 03f74aca74312dbeaf24d7e61306dd6a786dc3d0
