{
  "id": 7359508,
  "type": "Feature",
  "properties": {
    "tgn:hierarchy":[
        "tgn:7359508",
        "tgn:7005581",
        "tgn:1000001",
        "tgn:7005560",
        "tgn:7029392"
    ],
    "tgn:id":7359508,
    "tgn:name":"Dolores",
    "tgn:placetype":[
        "aat:300008347"
    ]
},
  "bbox": [],
  "geometry": {"coordinates":[-104.533333,27.766667],"type":"Point"}
}