{
  "id": 1092832,
  "type": "Feature",
  "properties": {
    "tgn:hierarchy":[
        "tgn:1092832",
        "tgn:7001242",
        "tgn:7017582",
        "tgn:1000193",
        "tgn:7029392"
    ],
    "tgn:id":1092832,
    "tgn:name":"Askham",
    "tgn:placetype":[
        "aat:300008347"
    ]
},
  "bbox": [],
  "geometry": {"coordinates":[20.7833,-26.9833],"type":"Point"}
}