{
  "id": 2633069,
  "type": "Feature",
  "properties": {
    "tgn:hierarchy":[
        "tgn:2633069",
        "tgn:1000001",
        "tgn:7006451",
        "tgn:7012149",
        "tgn:2000100",
        "tgn:7029392"
    ],
    "tgn:id":2633069,
    "tgn:name":"Ruelas Spring Number Two and Three",
    "tgn:placetype":[
        "aat:300008697"
    ]
},
  "bbox": [],
  "geometry": {"coordinates":[-110.7667,31.8333],"type":"Point"}
}