{
  "id": 7005025,
  "type": "Feature",
  "properties": {
    "tgn:hierarchy":[
        "tgn:7005025",
        "tgn:7005023",
        "tgn:1000003",
        "tgn:7003237",
        "tgn:1000080",
        "tgn:7029392"
    ],
    "tgn:id":7005025,
    "tgn:name":"Bergamo",
    "tgn:placetype":[
        "aat:300008347",
        "aat:300008389",
        "aat:300387308",
        "aat:300387223",
        "aat:300387302"
    ]
},
  "bbox": [],
  "geometry": {"coordinates":[9.716667,45.683333],"type":"Point"}
}