{
  "id": 7252510,
  "type": "Feature",
  "properties": {
    "tgn:hierarchy":[
        "tgn:7252510",
        "tgn:7003456",
        "tgn:1000003",
        "tgn:1000063",
        "tgn:7018236",
        "tgn:7029392"
    ],
    "tgn:id":7252510,
    "tgn:name":"Netekant",
    "tgn:placetype":[
        "aat:300008347"
    ]
},
  "bbox": [],
  "geometry": {"coordinates":[4.627161,51.122235],"type":"Point"}
}