{
  "id": 1054719,
  "type": "Feature",
  "properties": {
    "tgn:hierarchy":[
        "tgn:1054719",
        "tgn:1000004",
        "tgn:1003407",
        "tgn:7018214",
        "tgn:7002435",
        "tgn:7029392"
    ],
    "tgn:id":1054719,
    "tgn:name":"Jermakovo",
    "tgn:placetype":[
        "aat:300008347"
    ]
},
  "bbox": [],
  "geometry": {"coordinates":[49.6333,53.1833],"type":"Point"}
}