{
  "id": 2681754,
  "type": "Feature",
  "properties": {
    "tgn:hierarchy":[
        "tgn:2681754",
        "tgn:2001004",
        "tgn:1000001",
        "tgn:7012149",
        "tgn:7007521",
        "tgn:7029392"
    ],
    "tgn:id":2681754,
    "tgn:name":"South Rothwell Lake",
    "tgn:placetype":[
        "aat:300008680"
    ]
},
  "bbox": [],
  "geometry": {"coordinates":[-96.45,45.4833],"type":"Point"}
}