{
  "id": 1064588,
  "type": "Feature",
  "properties": {
    "tgn:hierarchy":[
        "tgn:1064588",
        "tgn:7018958",
        "tgn:7002443",
        "tgn:1000003",
        "tgn:7008591",
        "tgn:7029392"
    ],
    "tgn:id":1064588,
    "tgn:name:en":"Blaina",
    "tgn:placetype":[
        "aat:300008347"
    ]
},
  "bbox": [],
  "geometry": {"coordinates":[-3.166667,51.766667],"type":"Point"}
}