{
  "id": 2181460,
  "type": "Feature",
  "properties": {
    "tgn:hierarchy":[
        "tgn:2181460",
        "tgn:1000001",
        "tgn:7012149",
        "tgn:2001105",
        "tgn:7007522",
        "tgn:7029392"
    ],
    "tgn:id":2181460,
    "tgn:name":"Blue Gill Lake",
    "tgn:placetype":[
        "aat:300008680"
    ]
},
  "bbox": [],
  "geometry": {"coordinates":[-88.6833,30.7833],"type":"Point"}
}