{
  "id": 2477359,
  "type": "Feature",
  "properties": {
    "tgn:hierarchy":[
        "tgn:2477359",
        "tgn:1000001",
        "tgn:7012149",
        "tgn:1002961",
        "tgn:7007568",
        "tgn:7029392"
    ],
    "tgn:id":2477359,
    "tgn:name":"Lyon Creek",
    "tgn:placetype":[
        "aat:300008706"
    ]
},
  "bbox": [],
  "geometry": {"coordinates":[-74.3333,41.7833],"type":"Point"}
}