{
  "id": 7244888,
  "type": "Feature",
  "properties": {
    "tgn:hierarchy":[
        "tgn:7244888",
        "tgn:7003456",
        "tgn:1000003",
        "tgn:1000063",
        "tgn:7018236",
        "tgn:7029392"
    ],
    "tgn:id":7244888,
    "tgn:name":"Austruweelsen Dijk",
    "tgn:placetype":[
        "aat:300170882"
    ]
},
  "bbox": [],
  "geometry": {"coordinates":[4.266667,51.316667],"type":"Point"}
}