{
  "id": 1015929,
  "type": "Feature",
  "properties": {
    "tgn:hierarchy":[
        "tgn:1015929",
        "tgn:7005685",
        "tgn:1000001",
        "tgn:7005805",
        "tgn:7029392"
    ],
    "tgn:id":1015929,
    "tgn:name":"Fusilier",
    "tgn:placetype":[
        "aat:300008347"
    ]
},
  "bbox": [],
  "geometry": {"coordinates":[-109.7333,51.8333],"type":"Point"}
}