{
  "id": 7198700,
  "type": "Feature",
  "properties": {
    "tgn:hierarchy":[
        "tgn:7198700",
        "tgn:7003669",
        "tgn:1000003",
        "tgn:7000084",
        "tgn:7029392"
    ],
    "tgn:id":7198700,
    "tgn:name":"Ebermergen",
    "tgn:placetype":[
        "aat:300008347"
    ]
},
  "bbox": [],
  "geometry": {"coordinates":[10.716667,48.75],"type":"Point"}
}