{
  "id": 7081591,
  "type": "Feature",
  "properties": {
    "tgn:hierarchy":[
        "tgn:7081591",
        "tgn:7003669",
        "tgn:1000003",
        "tgn:7000084",
        "tgn:7029392"
    ],
    "tgn:id":7081591,
    "tgn:name":"Wustviel",
    "tgn:placetype":[
        "aat:300008347"
    ]
},
  "bbox": [],
  "geometry": {"coordinates":[10.533333,49.883333],"type":"Point"}
}