{
  "id": 2627466,
  "type": "Feature",
  "properties": {
    "tgn:hierarchy":[
        "tgn:2627466",
        "tgn:1000001",
        "tgn:7012149",
        "tgn:7007515",
        "tgn:7029392"
    ],
    "tgn:id":2627466,
    "tgn:name":"Rogan Brook",
    "tgn:placetype":[
        "aat:300008699"
    ]
},
  "bbox": [],
  "geometry": {"coordinates":[-68.4167,45.8333],"type":"Point"}
}