{
  "id": 7507869,
  "type": "Feature",
  "properties": {
    "tgn:hierarchy":[
        "tgn:7507869",
        "tgn:1009227",
        "tgn:1000226",
        "tgn:7520095",
        "tgn:1000006",
        "tgn:7029392"
    ],
    "tgn:id":7507869,
    "tgn:name:en":"Phyllis, Lake",
    "tgn:placetype":[
        "aat:300008680"
    ]
},
  "bbox": [],
  "geometry": {"coordinates":[172.233333,-41.466667],"type":"Point"}
}