{
  "id": 2635482,
  "type": "Feature",
  "properties": {
    "tgn:hierarchy":[
        "tgn:2635482",
        "tgn:1000001",
        "tgn:7012149",
        "tgn:2002092",
        "tgn:7007826",
        "tgn:7029392"
    ],
    "tgn:id":2635482,
    "tgn:name":"SL Lateral",
    "tgn:placetype":[
        "aat:300006075"
    ]
},
  "bbox": [],
  "geometry": {"coordinates":[-98.7833,33.85],"type":"Point"}
}