{
  "id": 7385769,
  "type": "Feature",
  "properties": {
    "tgn:hierarchy":[
        "tgn:7385769",
        "tgn:1000001",
        "tgn:7005599",
        "tgn:7005560",
        "tgn:7029392"
    ],
    "tgn:id":7385769,
    "tgn:name:es":"Pedregal, R\u00edo",
    "tgn:placetype":[
        "aat:300008699"
    ]
},
  "bbox": [],
  "geometry": {"coordinates":[-93.958333,17.7625],"type":"Point"}
}