{
  "id": 2331755,
  "type": "Feature",
  "properties": {
    "tgn:hierarchy":[
        "tgn:2331755",
        "tgn:1000001",
        "tgn:7012149",
        "tgn:1002494",
        "tgn:7007710",
        "tgn:7029392"
    ],
    "tgn:id":2331755,
    "tgn:name":"Flemings Cave Number 2",
    "tgn:placetype":[
        "aat:300008746"
    ]
},
  "bbox": [],
  "geometry": {"coordinates":[-77.7833,40.2667],"type":"Point"}
}