<<<<<<< HEAD
{
  "id": 2331755,
  "type": "Feature",
  "properties": {
    "tgn:hierarchy":[
        "tgn:2331755",
        "tgn:1000001",
        "tgn:7012149",
        "tgn:1002494",
        "tgn:7007710",
        "tgn:7029392"
    ],
    "tgn:id":2331755,
    "tgn:name":"Flemings Cave Number 2",
    "tgn:placetype":[
        "aat:300008746"
    ]
},
  "bbox": [],
  "geometry": {"coordinates":[-77.7833,40.2667],"type":"Point"}
}
=======
{"geometry":{"type":"Point","coordinates":[-77.783300,40.266700]},"type":"Feature","properties":{"hierarchy":["tgn:2331755","tgn:1000001","tgn:7012149","tgn:1002494","tgn:7007710","tgn:7029392"],"placetype":["aat:300008746"],"id":2331755,"name:xx":"Flemings Cave Number 2"}}
>>>>>>> 03f74aca74312dbeaf24d7e61306dd6a786dc3d0
