{
  "id": 1020100,
  "type": "Feature",
  "properties": {
    "tgn:hierarchy":[
        "tgn:1020100",
        "tgn:7006477",
        "tgn:1001526",
        "tgn:1000002",
        "tgn:7029392"
    ],
    "tgn:id":1020100,
    "tgn:name":"Tobas",
    "tgn:placetype":[
        "aat:300008347"
    ]
},
  "bbox": [],
  "geometry": {"coordinates":[-62.7333,-28.1333],"type":"Point"}
}