{
  "id": 2268434,
  "type": "Feature",
  "properties": {
    "tgn:hierarchy":[
        "tgn:2268434",
        "tgn:1000001",
        "tgn:7012149",
        "tgn:2001541",
        "tgn:7007709",
        "tgn:7029392"
    ],
    "tgn:id":2268434,
    "tgn:name":"Crooked Run Creek",
    "tgn:placetype":[
        "aat:300008706"
    ]
},
  "bbox": [],
  "geometry": {"coordinates":[-80.35,36.2667],"type":"Point"}
}