{
  "id": 2122704,
  "type": "Feature",
  "properties": {
    "tgn:hierarchy":[
        "tgn:2122704",
        "tgn:1000001",
        "tgn:7012149",
        "tgn:2002356",
        "tgn:7007922",
        "tgn:7029392"
    ],
    "tgn:id":2122704,
    "tgn:name":"Whittlesey",
    "tgn:placetype":[
        "aat:300008347"
    ]
},
  "bbox": [],
  "geometry": {"coordinates":[-90.3167,45.2167],"type":"Point"}
}