{
  "id": 7398898,
  "type": "Feature",
  "properties": {
    "tgn:hierarchy":[
        "tgn:7398898",
        "tgn:1000001",
        "tgn:1001893",
        "tgn:7005560",
        "tgn:7029392"
    ],
    "tgn:id":7398898,
    "tgn:name":"Huemetla",
    "tgn:placetype":[
        "aat:300008347"
    ]
},
  "bbox": [],
  "geometry": {"coordinates":[-99.742778,19.715],"type":"Point"}
}