{
  "id": 2326171,
  "type": "Feature",
  "properties": {
    "tgn:hierarchy":[
        "tgn:2326171",
        "tgn:1000001",
        "tgn:7012149",
        "tgn:7014318",
        "tgn:7007568",
        "tgn:7029392"
    ],
    "tgn:id":2326171,
    "tgn:name":"Filer Hill",
    "tgn:placetype":[
        "aat:300008798"
    ]
},
  "bbox": [],
  "geometry": {"coordinates":[-75.25,42.45],"type":"Point"}
}