{
  "id": 7318496,
  "type": "Feature",
  "properties": {
    "tgn:hierarchy":[
        "tgn:7318496",
        "tgn:1001702",
        "tgn:1000049",
        "tgn:1000002",
        "tgn:7029392"
    ],
    "tgn:id":7318496,
    "tgn:name":"Charlton, Cabo",
    "tgn:placetype":[
        "aat:300008850"
    ]
},
  "bbox": [],
  "geometry": {"coordinates":[-74.883333,-51.633333],"type":"Point"}
}