{
  "id": 7489812,
  "type": "Feature",
  "properties": {
    "tgn:hierarchy":[
        "tgn:7489812",
        "tgn:7001004",
        "tgn:1000004",
        "tgn:1000141",
        "tgn:7029392"
    ],
    "tgn:id":7489812,
    "tgn:name":"Shedong",
    "tgn:placetype":[
        "aat:300008347"
    ]
},
  "bbox": [],
  "geometry": {"coordinates":[120.268056,22.866389],"type":"Point"}
}