{
  "id": 1136307,
  "type": "Feature",
  "properties": {
    "tgn:hierarchy":[
        "tgn:1136307",
        "tgn:1001853",
        "tgn:1000001",
        "tgn:7005560",
        "tgn:7029392"
    ],
    "tgn:id":1136307,
    "tgn:name":"Guadalupe Victoria",
    "tgn:placetype":[
        "aat:300008347"
    ]
},
  "bbox": [],
  "geometry": {"coordinates":[-101.033333,27.766667],"type":"Point"}
}