{
  "id": 1110467,
  "type": "Feature",
  "properties": {
    "tgn:hierarchy":[
        "tgn:1110467",
        "tgn:1000004",
        "tgn:7000198",
        "tgn:1001895",
        "tgn:7029392"
    ],
    "tgn:id":1110467,
    "tgn:name:en":"Gaw\u012blgarh Hills",
    "tgn:placetype":[
        "aat:300008777"
    ]
},
  "bbox": [],
  "geometry": {"coordinates":[76.999,21.347],"type":"Point"}
}