{
  "id": 2045633,
  "type": "Feature",
  "properties": {
    "tgn:hierarchy":[
        "tgn:2045633",
        "tgn:1000001",
        "tgn:7012149",
        "tgn:2000933",
        "tgn:7007515",
        "tgn:7029392"
    ],
    "tgn:id":2045633,
    "tgn:name":"South Lebanon",
    "tgn:placetype":[
        "aat:300008347"
    ]
},
  "bbox": [],
  "geometry": {"coordinates":[-70.9333,43.3333],"type":"Point"}
}