{
  "id": 7497035,
  "type": "Feature",
  "properties": {
    "tgn:hierarchy":[
        "tgn:7497035",
        "tgn:7001004",
        "tgn:1000004",
        "tgn:1000141",
        "tgn:7029392"
    ],
    "tgn:id":7497035,
    "tgn:name":"Qianjin Guoxiao",
    "tgn:placetype":[
        "aat:300006495"
    ]
},
  "bbox": [],
  "geometry": {"coordinates":[120.294123,22.625835],"type":"Point"}
}