{
  "id": 2751688,
  "type": "Feature",
  "properties": {
    "tgn:hierarchy":[
        "tgn:2751688",
        "tgn:1000001",
        "tgn:7012149",
        "tgn:7007158",
        "tgn:2000244",
        "tgn:7029392"
    ],
    "tgn:id":2751688,
    "tgn:name":"Warr Canyon",
    "tgn:placetype":[
        "aat:300008761"
    ]
},
  "bbox": [],
  "geometry": {"coordinates":[-106.4667,37.5833],"type":"Point"}
}