<<<<<<< HEAD
{
  "id": 2151870,
  "type": "Feature",
  "properties": {
    "tgn:hierarchy":[
        "tgn:2151870",
        "tgn:1000001",
        "tgn:7012149",
        "tgn:2002384",
        "tgn:7007923",
        "tgn:7029392"
    ],
    "tgn:id":2151870,
    "tgn:name":"Battleship Mountain",
    "tgn:placetype":[
        "aat:300008798"
    ]
},
  "bbox": [],
  "geometry": {"coordinates":[-110.8667,43.7167],"type":"Point"}
}
=======
{"geometry":{"type":"Point","coordinates":[-110.866700,43.716700]},"type":"Feature","properties":{"hierarchy":["tgn:2151870","tgn:1000001","tgn:7012149","tgn:2002384","tgn:7007923","tgn:7029392"],"placetype":["aat:300008798"],"id":2151870,"name:xx":"Battleship Mountain"}}
>>>>>>> 03f74aca74312dbeaf24d7e61306dd6a786dc3d0
