{
  "id": 2156323,
  "type": "Feature",
  "properties": {
    "tgn:hierarchy":[
        "tgn:2156323",
        "tgn:1000001",
        "tgn:7012149",
        "tgn:7007919",
        "tgn:7029392"
    ],
    "tgn:id":2156323,
    "tgn:name":"Bearpen Creek",
    "tgn:placetype":[
        "aat:300008706"
    ]
},
  "bbox": [],
  "geometry": {"coordinates":[-82.5667,37.15],"type":"Point"}
}