{
  "id": 2068848,
  "type": "Feature",
  "properties": {
    "tgn:hierarchy":[
        "tgn:2068848",
        "tgn:1000001",
        "tgn:1002347",
        "tgn:7012149",
        "tgn:7007568",
        "tgn:7029392"
    ],
    "tgn:id":2068848,
    "tgn:name":"Dover Plains",
    "tgn:placetype":[
        "aat:300008347"
    ]
},
  "bbox": [],
  "geometry": {"coordinates":[-73.5667,41.7333],"type":"Point"}
}