{
  "id": 2620033,
  "type": "Feature",
  "properties": {
    "tgn:hierarchy":[
        "tgn:2620033",
        "tgn:1000001",
        "tgn:2000461",
        "tgn:7012149",
        "tgn:7007250",
        "tgn:7029392"
    ],
    "tgn:id":2620033,
    "tgn:name":"Ririe Reservoir",
    "tgn:placetype":[
        "aat:300006191"
    ]
},
  "bbox": [],
  "geometry": {"coordinates":[-111.7333,43.5667],"type":"Point"}
}