{
  "id": 2762501,
  "type": "Feature",
  "properties": {
    "tgn:hierarchy":[
        "tgn:2762501",
        "tgn:1000001",
        "tgn:2001436",
        "tgn:7012149",
        "tgn:7007566",
        "tgn:7029392"
    ],
    "tgn:id":2762501,
    "tgn:name":"West Water Storage Tank",
    "tgn:placetype":[
        "aat:300006191"
    ]
},
  "bbox": [],
  "geometry": {"coordinates":[-104.7833,32.1333],"type":"Point"}
}