{
  "id": 2178528,
  "type": "Feature",
  "properties": {
    "tgn:hierarchy":[
        "tgn:2178528",
        "tgn:1000001",
        "tgn:7012149",
        "tgn:2002180",
        "tgn:7007919",
        "tgn:7029392"
    ],
    "tgn:id":2178528,
    "tgn:name":"Blacks Creek",
    "tgn:placetype":[
        "aat:300008706"
    ]
},
  "bbox": [],
  "geometry": {"coordinates":[-79.1667,36.9667],"type":"Point"}
}