{
  "id": 2555345,
  "type": "Feature",
  "properties": {
    "tgn:hierarchy":[
        "tgn:2555345",
        "tgn:1002149",
        "tgn:1000001",
        "tgn:7012149",
        "tgn:7007826",
        "tgn:7029392"
    ],
    "tgn:id":2555345,
    "tgn:name":"Odell Creek",
    "tgn:placetype":[
        "aat:300008706"
    ]
},
  "bbox": [],
  "geometry": {"coordinates":[-94.5833,31.2833],"type":"Point"}
}