{
  "id": 7270415,
  "type": "Feature",
  "properties": {
    "tgn:hierarchy":[
        "tgn:7270415",
        "tgn:1000003",
        "tgn:7003624",
        "tgn:7016845",
        "tgn:7029392"
    ],
    "tgn:id":7270415,
    "tgn:name:nl":"Oude Polder",
    "tgn:placetype":[
        "aat:300006163"
    ]
},
  "bbox": [],
  "geometry": {"coordinates":[4.233333,51.583333],"type":"Point"}
}