{
  "id": 7510681,
  "type": "Feature",
  "properties": {
    "tgn:hierarchy":[
        "tgn:7510681",
        "tgn:1009227",
        "tgn:7001866",
        "tgn:1000226",
        "tgn:1000006",
        "tgn:7029392"
    ],
    "tgn:id":7510681,
    "tgn:name:en":"Te Aitarakiki Creek",
    "tgn:placetype":[
        "aat:300008699"
    ]
},
  "bbox": [],
  "geometry": {"coordinates":[171.25,-44.383333],"type":"Point"}
}