{
  "id": 7545347,
  "type": "Feature",
  "properties": {
    "tgn:hierarchy":[
        "tgn:7545347",
        "tgn:1000004",
        "tgn:7000198",
        "tgn:7001797",
        "tgn:7029392"
    ],
    "tgn:id":7545347,
    "tgn:name:en":"Amar\u0101vati River",
    "tgn:placetype":[
        "aat:300008699"
    ]
},
  "bbox": [],
  "geometry": {"coordinates":[78.183333,10.85],"type":"Point"}
}