{
  "id": 7568190,
  "type": "Feature",
  "properties": {
    "tgn:hierarchy":[
        "tgn:7568190",
        "tgn:1001828",
        "tgn:1000004",
        "tgn:7000198",
        "tgn:7029392"
    ],
    "tgn:id":7568190,
    "tgn:name:en":"W\u016bdemari",
    "tgn:placetype":[
        "aat:300008347"
    ]
},
  "bbox": [],
  "geometry": {"coordinates":[78.681111,17.618333],"type":"Point"}
}