{
  "id": 7532494,
  "type": "Feature",
  "properties": {
    "tgn:hierarchy":[
        "tgn:7532494",
        "tgn:7001242",
        "tgn:7016833",
        "tgn:7001336",
        "tgn:7029392"
    ],
    "tgn:id":7532494,
    "tgn:name:en":"Sahya, W\u00e2di",
    "tgn:placetype":[
        "aat:300379998"
    ]
},
  "bbox": [],
  "geometry": {"coordinates":[34.154307,27.877791],"type":"Point"}
}