<<<<<<< HEAD
{
  "id": 7354235,
  "type": "Feature",
  "properties": {
    "tgn:hierarchy":[
        "tgn:7354235",
        "tgn:1000001",
        "tgn:1001960",
        "tgn:7005560",
        "tgn:7029392"
    ],
    "tgn:id":7354235,
    "tgn:name":"Rancho Casas",
    "tgn:placetype":[
        "aat:300000241"
    ]
},
  "bbox": [],
  "geometry": {"coordinates":[-109.783333,28.033333],"type":"Point"}
}
=======
{"geometry":{"type":"Point","coordinates":[-109.783333,28.033333]},"type":"Feature","properties":{"hierarchy":["tgn:7354235","tgn:1000001","tgn:1001960","tgn:7005560","tgn:7029392"],"placetype":["aat:300000241"],"id":7354235,"name:xx":"Rancho Casas"}}
>>>>>>> 03f74aca74312dbeaf24d7e61306dd6a786dc3d0
