<<<<<<< HEAD
{
  "id": 2767444,
  "type": "Feature",
  "properties": {
    "tgn:hierarchy":[
        "tgn:2767444",
        "tgn:1000001",
        "tgn:7012149",
        "tgn:7007157",
        "tgn:2000190",
        "tgn:7029392"
    ],
    "tgn:id":2767444,
    "tgn:name":"White Sulphur Spring",
    "tgn:placetype":[
        "aat:300008697"
    ]
},
  "bbox": [],
  "geometry": {"coordinates":[-121.55,40.35],"type":"Point"}
}
=======
{"geometry":{"type":"Point","coordinates":[-121.550000,40.350000]},"type":"Feature","properties":{"hierarchy":["tgn:2767444","tgn:1000001","tgn:7012149","tgn:7007157","tgn:2000190","tgn:7029392"],"placetype":["aat:300008697"],"id":2767444,"name:xx":"White Sulphur Spring"}}
>>>>>>> 03f74aca74312dbeaf24d7e61306dd6a786dc3d0
