{
  "id": 2502331,
  "type": "Feature",
  "properties": {
    "tgn:hierarchy":[
        "tgn:2502331",
        "tgn:1000001",
        "tgn:1002347",
        "tgn:7012149",
        "tgn:7007568",
        "tgn:7029392"
    ],
    "tgn:id":2502331,
    "tgn:name":"McKinney Pond",
    "tgn:placetype":[
        "aat:300006191"
    ]
},
  "bbox": [],
  "geometry": {"coordinates":[-73.6833,41.65],"type":"Point"}
}