{
  "id": 7343507,
  "type": "Feature",
  "properties": {
    "tgn:hierarchy":[
        "tgn:7343507",
        "tgn:7002826",
        "tgn:7001158",
        "tgn:1000003",
        "tgn:1000095",
        "tgn:7029392"
    ],
    "tgn:id":7343507,
    "tgn:name":"Carbajal de Fuentes",
    "tgn:placetype":[
        "aat:300008347"
    ]
},
  "bbox": [],
  "geometry": {"coordinates":[-5.45,42.183333],"type":"Point"}
}