{
  "id": 7275816,
  "type": "Feature",
  "properties": {
    "tgn:hierarchy":[
        "tgn:7275816",
        "tgn:1001702",
        "tgn:1000049",
        "tgn:1000002",
        "tgn:7029392"
    ],
    "tgn:id":7275816,
    "tgn:name":"Toyita, Caleta",
    "tgn:placetype":[
        "aat:300132317"
    ]
},
  "bbox": [],
  "geometry": {"coordinates":[-73.816667,-52.216667],"type":"Point"}
}