<<<<<<< HEAD
{
  "id": 2406417,
  "type": "Feature",
  "properties": {
    "tgn:hierarchy":[
        "tgn:2406417",
        "tgn:7006450",
        "tgn:2000069",
        "tgn:1000001",
        "tgn:7012149",
        "tgn:7029392"
    ],
    "tgn:id":2406417,
    "tgn:name":"Hungry Creek",
    "tgn:placetype":[
        "aat:300008706"
    ]
},
  "bbox": [],
  "geometry": {"coordinates":[-155.4833,61.2833],"type":"Point"}
}
=======
{"geometry":{"type":"Point","coordinates":[-155.483300,61.283300]},"type":"Feature","properties":{"hierarchy":["tgn:2406417","tgn:7006450","tgn:2000069","tgn:1000001","tgn:7012149","tgn:7029392"],"placetype":["aat:300008706"],"id":2406417,"name:xx":"Hungry Creek"}}
>>>>>>> 03f74aca74312dbeaf24d7e61306dd6a786dc3d0
