{
  "id": 7080596,
  "type": "Feature",
  "properties": {
    "tgn:hierarchy":[
        "tgn:7080596",
        "tgn:7003669",
        "tgn:1000003",
        "tgn:7000084",
        "tgn:7029392"
    ],
    "tgn:id":7080596,
    "tgn:name":"W\u00f6lbattendorf",
    "tgn:placetype":[
        "aat:300008347"
    ]
},
  "bbox": [],
  "geometry": {"coordinates":[11.85,50.316667],"type":"Point"}
}