{
  "id": 7467503,
  "type": "Feature",
  "properties": {
    "tgn:hierarchy":[
        "tgn:7467503",
        "tgn:1000004",
        "tgn:7490934",
        "tgn:1000141",
        "tgn:7029392"
    ],
    "tgn:id":7467503,
    "tgn:name":"Anding Xiang",
    "tgn:placetype":[
        "aat:300387173"
    ]
},
  "bbox": [],
  "geometry": {"coordinates":[120.233333,23.033333],"type":"Point"}
}