{
  "id": 2492761,
  "type": "Feature",
  "properties": {
    "tgn:hierarchy":[
        "tgn:2492761",
        "tgn:1000001",
        "tgn:7012149",
        "tgn:2000717",
        "tgn:7007254",
        "tgn:7029392"
    ],
    "tgn:id":2492761,
    "tgn:name":"Marion Reservoir",
    "tgn:placetype":[
        "aat:300006191"
    ]
},
  "bbox": [],
  "geometry": {"coordinates":[-97.0833,38.3667],"type":"Point"}
}