{
  "id": 2695526,
  "type": "Feature",
  "properties": {
    "tgn:hierarchy":[
        "tgn:2695526",
        "tgn:1000001",
        "tgn:2001571",
        "tgn:7012149",
        "tgn:7007705",
        "tgn:7029392"
    ],
    "tgn:id":2695526,
    "tgn:name":"Stink Lake",
    "tgn:placetype":[
        "aat:300008680"
    ]
},
  "bbox": [],
  "geometry": {"coordinates":[-99.9333,46.6167],"type":"Point"}
}