{
  "id": 7565426,
  "type": "Feature",
  "properties": {
    "tgn:hierarchy":[
        "tgn:7565426",
        "tgn:1000004",
        "tgn:7000198",
        "tgn:7016788",
        "tgn:7029392"
    ],
    "tgn:id":7565426,
    "tgn:name:en":"Sukri Nadi",
    "tgn:placetype":[
        "aat:300008347"
    ]
},
  "bbox": [],
  "geometry": {"coordinates":[71.451832,27.058791],"type":"Point"}
}