{
  "id": 2719318,
  "type": "Feature",
  "properties": {
    "tgn:hierarchy":[
        "tgn:2719318",
        "tgn:1000001",
        "tgn:7012149",
        "tgn:1002742",
        "tgn:7007920",
        "tgn:7029392"
    ],
    "tgn:id":2719318,
    "tgn:name":"Three A M Mountain",
    "tgn:placetype":[
        "aat:300008798"
    ]
},
  "bbox": [],
  "geometry": {"coordinates":[-120.4167,48.4167],"type":"Point"}
}