{
  "id": 2726940,
  "type": "Feature",
  "properties": {
    "tgn:hierarchy":[
        "tgn:2726940",
        "tgn:1000001",
        "tgn:7012149",
        "tgn:2000435",
        "tgn:7007248",
        "tgn:7029392"
    ],
    "tgn:id":2726940,
    "tgn:name":"Townsend Mill",
    "tgn:placetype":[
        "aat:300008347"
    ]
},
  "bbox": [],
  "geometry": {"coordinates":[-83.8667,34.9167],"type":"Point"}
}