{
  "id": 2463024,
  "type": "Feature",
  "properties": {
    "tgn:hierarchy":[
        "tgn:2463024",
        "tgn:1000001",
        "tgn:7012149",
        "tgn:7007157",
        "tgn:7029392"
    ],
    "tgn:id":2463024,
    "tgn:name":"Live Oak Slough",
    "tgn:placetype":[
        "aat:300008699"
    ]
},
  "bbox": [],
  "geometry": {"coordinates":[-121.6667,39.35],"type":"Point"}
}