{
  "id": 7543433,
  "type": "Feature",
  "properties": {
    "tgn:hierarchy":[
        "tgn:7543433",
        "tgn:7001242",
        "tgn:7016833",
        "tgn:7000123",
        "tgn:7029392"
    ],
    "tgn:id":7543433,
    "tgn:name:en":"Ban\u012b \u1e28umayd",
    "tgn:placetype":[
        "aat:300008347"
    ]
},
  "bbox": [],
  "geometry": {"coordinates":[32.548478,25.328046],"type":"Point"}
}