{
  "id": 7396963,
  "type": "Feature",
  "properties": {
    "tgn:hierarchy":[
        "tgn:7396963",
        "tgn:1000001",
        "tgn:7005600",
        "tgn:7005560",
        "tgn:7029392"
    ],
    "tgn:id":7396963,
    "tgn:name":"Santa Rosa",
    "tgn:placetype":[
        "aat:300008347"
    ]
},
  "bbox": [],
  "geometry": {"coordinates":[-89.75,20.533333],"type":"Point"}
}