{
  "id": 1059008,
  "type": "Feature",
  "properties": {
    "tgn:hierarchy":[
        "tgn:1059008",
        "tgn:7011626",
        "tgn:1000004",
        "tgn:7014835",
        "tgn:7029392"
    ],
    "tgn:id":1059008,
    "tgn:name":"Rushan",
    "tgn:placetype":[
        "aat:300008347"
    ]
},
  "bbox": [],
  "geometry": {"coordinates":[71.5333,37.9833],"type":"Point"}
}