{
  "id": 2160363,
  "type": "Feature",
  "properties": {
    "tgn:hierarchy":[
        "tgn:2160363",
        "tgn:1000001",
        "tgn:7006451",
        "tgn:2000092",
        "tgn:7012149",
        "tgn:7029392"
    ],
    "tgn:id":2160363,
    "tgn:name":"Beekid Halani Tank",
    "tgn:placetype":[
        "aat:300006191"
    ]
},
  "bbox": [],
  "geometry": {"coordinates":[-111.1333,35.6833],"type":"Point"}
}