{
  "id": 2157157,
  "type": "Feature",
  "properties": {
    "tgn:hierarchy":[
        "tgn:2157157",
        "tgn:1000001",
        "tgn:7012149",
        "tgn:2001718",
        "tgn:7007708",
        "tgn:7029392"
    ],
    "tgn:id":2157157,
    "tgn:name":"Beaver Charlie Breaks",
    "tgn:placetype":[
        "aat:300055621"
    ]
},
  "bbox": [],
  "geometry": {"coordinates":[-117.0333,42.35],"type":"Point"}
}