<<<<<<< HEAD
{
  "id": 2157157,
  "type": "Feature",
  "properties": {
    "tgn:hierarchy":[
        "tgn:2157157",
        "tgn:1000001",
        "tgn:7012149",
        "tgn:2001718",
        "tgn:7007708",
        "tgn:7029392"
    ],
    "tgn:id":2157157,
    "tgn:name":"Beaver Charlie Breaks",
    "tgn:placetype":[
        "aat:300055621"
    ]
},
  "bbox": [],
  "geometry": {"coordinates":[-117.0333,42.35],"type":"Point"}
}
=======
{"geometry":{"type":"Point","coordinates":[-117.033300,42.350000]},"type":"Feature","properties":{"hierarchy":["tgn:2157157","tgn:1000001","tgn:7012149","tgn:2001718","tgn:7007708","tgn:7029392"],"placetype":["aat:300055621"],"id":2157157,"name:xx":"Beaver Charlie Breaks"}}
>>>>>>> 03f74aca74312dbeaf24d7e61306dd6a786dc3d0
