{
  "id": 7593426,
  "type": "Feature",
  "properties": {
    "tgn:hierarchy":[
        "tgn:7593426",
        "tgn:7005402",
        "tgn:1000001",
        "tgn:7005388",
        "tgn:7029392"
    ],
    "tgn:id":7593426,
    "tgn:name":"San Rafael del Yuma",
    "tgn:placetype":[
        "aat:300008347"
    ]
},
  "bbox": [],
  "geometry": {"coordinates":[-68.673,18.43],"type":"Point"}
}