{
  "id": 2090443,
  "type": "Feature",
  "properties": {
    "tgn:hierarchy":[
        "tgn:2090443",
        "tgn:1000001",
        "tgn:7012149",
        "tgn:1002494",
        "tgn:7007710",
        "tgn:7029392"
    ],
    "tgn:id":2090443,
    "tgn:name":"McConnellstown",
    "tgn:placetype":[
        "aat:300008347"
    ]
},
  "bbox": [],
  "geometry": {"coordinates":[-78.0667,40.45],"type":"Point"}
}