{
  "id": 2399877,
  "type": "Feature",
  "properties": {
    "tgn:hierarchy":[
        "tgn:2399877",
        "tgn:1000001",
        "tgn:7012149",
        "tgn:7029392"
    ],
    "tgn:id":2399877,
    "tgn:name":"Horse Canyon",
    "tgn:placetype":[
        "aat:300008761"
    ]
},
  "bbox": [],
  "geometry": {"coordinates":[-110.8667,37.0333],"type":"Point"}
}