{
  "id": 7132354,
  "type": "Feature",
  "properties": {
    "tgn:hierarchy":[
        "tgn:7132354",
        "tgn:1000003",
        "tgn:7003678",
        "tgn:7000084",
        "tgn:7029392"
    ],
    "tgn:id":7132354,
    "tgn:name":"Maulhof",
    "tgn:placetype":[
        "aat:300000206"
    ]
},
  "bbox": [],
  "geometry": {"coordinates":[9.883333,50.516667],"type":"Point"}
}