{
  "id": 2212304,
  "type": "Feature",
  "properties": {
    "tgn:hierarchy":[
        "tgn:2212304",
        "tgn:1000001",
        "tgn:7012149",
        "tgn:2001237",
        "tgn:7007523",
        "tgn:7029392"
    ],
    "tgn:id":2212304,
    "tgn:name":"Buzzard Run",
    "tgn:placetype":[
        "aat:300008699"
    ]
},
  "bbox": [],
  "geometry": {"coordinates":[-90.6333,36.6667],"type":"Point"}
}