{
  "id": 1086133,
  "type": "Feature",
  "properties": {
    "tgn:hierarchy":[
        "tgn:1086133",
        "tgn:1001442",
        "tgn:1000004",
        "tgn:7018453",
        "tgn:1000144",
        "tgn:7029392"
    ],
    "tgn:id":1086133,
    "tgn:name":"Ciftehan",
    "tgn:placetype":[
        "aat:300008347"
    ]
},
  "bbox": [],
  "geometry": {"coordinates":[34.7667,37.5167],"type":"Point"}
}