{
  "id": 7389128,
  "type": "Feature",
  "properties": {
    "tgn:hierarchy":[
        "tgn:7389128",
        "tgn:1000001",
        "tgn:1001906",
        "tgn:7005560",
        "tgn:7029392"
    ],
    "tgn:id":7389128,
    "tgn:name":"Puyeque, Laguna",
    "tgn:placetype":[
        "aat:300008679"
    ]
},
  "bbox": [],
  "geometry": {"coordinates":[-105.383333,22.133333],"type":"Point"}
}