{
  "id": 7163212,
  "type": "Feature",
  "properties": {
    "tgn:hierarchy":[
        "tgn:7163212",
        "tgn:1000003",
        "tgn:7000094",
        "tgn:7000084",
        "tgn:7029392"
    ],
    "tgn:id":7163212,
    "tgn:name":"Hugoldsdorf",
    "tgn:placetype":[
        "aat:300008347"
    ]
},
  "bbox": [],
  "geometry": {"coordinates":[12.75,54.15],"type":"Point"}
}