{
  "id": 2329469,
  "type": "Feature",
  "properties": {
    "tgn:hierarchy":[
        "tgn:2329469",
        "tgn:1000001",
        "tgn:7012149",
        "tgn:1003007",
        "tgn:7007706",
        "tgn:7029392"
    ],
    "tgn:id":2329469,
    "tgn:name":"Five Points",
    "tgn:placetype":[
        "aat:300008347"
    ]
},
  "bbox": [],
  "geometry": {"coordinates":[-81.8333,40.8667],"type":"Point"}
}