{
  "id": 2211166,
  "type": "Feature",
  "properties": {
    "tgn:hierarchy":[
        "tgn:2211166",
        "tgn:1002366",
        "tgn:1000001",
        "tgn:7012149",
        "tgn:7007159",
        "tgn:7029392"
    ],
    "tgn:id":2211166,
    "tgn:name":"Butlers Island",
    "tgn:placetype":[
        "aat:300008791"
    ]
},
  "bbox": [],
  "geometry": {"coordinates":[-73.4333,41.05],"type":"Point"}
}