<<<<<<< HEAD
{
  "id": 2766983,
  "type": "Feature",
  "properties": {
    "tgn:hierarchy":[
        "tgn:2766983",
        "tgn:1000001",
        "tgn:7012149",
        "tgn:2001846",
        "tgn:7007825",
        "tgn:7029392"
    ],
    "tgn:id":2766983,
    "tgn:name":"White Prospect",
    "tgn:placetype":[
        "aat:300000390"
    ]
},
  "bbox": [],
  "geometry": {"coordinates":[-82.1667,36.3833],"type":"Point"}
}
=======
{"geometry":{"type":"Point","coordinates":[-82.166700,36.383300]},"type":"Feature","properties":{"hierarchy":["tgn:2766983","tgn:1000001","tgn:7012149","tgn:2001846","tgn:7007825","tgn:7029392"],"placetype":["aat:300000390"],"id":2766983,"name:xx":"White Prospect"}}
>>>>>>> 03f74aca74312dbeaf24d7e61306dd6a786dc3d0
