<<<<<<< HEAD
{
  "id": 7371999,
  "type": "Feature",
  "properties": {
    "tgn:hierarchy":[
        "tgn:7371999",
        "tgn:1001853",
        "tgn:1000001",
        "tgn:7005560",
        "tgn:7029392"
    ],
    "tgn:id":7371999,
    "tgn:name":"La Escondida",
    "tgn:placetype":[
        "aat:300008347"
    ]
},
  "bbox": [],
  "geometry": {"coordinates":[-103.15,25.5],"type":"Point"}
}
=======
{"geometry":{"type":"Point","coordinates":[-103.150000,25.500000]},"type":"Feature","properties":{"hierarchy":["tgn:7371999","tgn:1001853","tgn:1000001","tgn:7005560","tgn:7029392"],"placetype":["aat:300008347"],"id":7371999,"name:xx":"La Escondida"}}
>>>>>>> 03f74aca74312dbeaf24d7e61306dd6a786dc3d0
