{
  "id": 7413697,
  "type": "Feature",
  "properties": {
    "tgn:hierarchy":[
        "tgn:7413697",
        "tgn:7005580",
        "tgn:1000001",
        "tgn:7005560",
        "tgn:7029392"
    ],
    "tgn:id":7413697,
    "tgn:name":"Juan Crispin",
    "tgn:placetype":[
        "aat:300008347"
    ]
},
  "bbox": [],
  "geometry": {"coordinates":[-93.173611,16.930556],"type":"Point"}
}