{
  "id": 2206286,
  "type": "Feature",
  "properties": {
    "tgn:hierarchy":[
        "tgn:2206286",
        "tgn:1000001",
        "tgn:7012149",
        "tgn:7007158",
        "tgn:2000240",
        "tgn:7029392"
    ],
    "tgn:id":2206286,
    "tgn:name":"Bulldog Creek",
    "tgn:placetype":[
        "aat:300008706"
    ]
},
  "bbox": [],
  "geometry": {"coordinates":[-107.1333,39.2333],"type":"Point"}
}