{
  "id": 1080481,
  "type": "Feature",
  "properties": {
    "tgn:hierarchy":[
        "tgn:1080481",
        "tgn:1000004",
        "tgn:7000894",
        "tgn:7016797",
        "tgn:1000120",
        "tgn:7029392"
    ],
    "tgn:id":1080481,
    "tgn:name":"Katayama",
    "tgn:placetype":[
        "aat:300008347"
    ]
},
  "bbox": [],
  "geometry": {"coordinates":[139.5667,35.7667],"type":"Point"}
}