<<<<<<< HEAD
{
  "id": 2155670,
  "type": "Feature",
  "properties": {
    "tgn:hierarchy":[
        "tgn:2155670",
        "tgn:1000001",
        "tgn:7012149",
        "tgn:2002381",
        "tgn:7007923",
        "tgn:7029392"
    ],
    "tgn:id":2155670,
    "tgn:name":"Bear Spring",
    "tgn:placetype":[
        "aat:300008697"
    ]
},
  "bbox": [],
  "geometry": {"coordinates":[-107.7333,44.9167],"type":"Point"}
}
=======
{"geometry":{"type":"Point","coordinates":[-107.733300,44.916700]},"type":"Feature","properties":{"hierarchy":["tgn:2155670","tgn:1000001","tgn:7012149","tgn:2002381","tgn:7007923","tgn:7029392"],"placetype":["aat:300008697"],"id":2155670,"name:xx":"Bear Spring"}}
>>>>>>> 03f74aca74312dbeaf24d7e61306dd6a786dc3d0
