{
  "id": 2155670,
  "type": "Feature",
  "properties": {
    "tgn:hierarchy":[
        "tgn:2155670",
        "tgn:1000001",
        "tgn:7012149",
        "tgn:2002381",
        "tgn:7007923",
        "tgn:7029392"
    ],
    "tgn:id":2155670,
    "tgn:name":"Bear Spring",
    "tgn:placetype":[
        "aat:300008697"
    ]
},
  "bbox": [],
  "geometry": {"coordinates":[-107.7333,44.9167],"type":"Point"}
}