{
  "id": 1088819,
  "type": "Feature",
  "properties": {
    "tgn:hierarchy":[
        "tgn:1088819",
        "tgn:7001242",
        "tgn:7016654",
        "tgn:1000159",
        "tgn:7029392"
    ],
    "tgn:id":1088819,
    "tgn:name":"Binga",
    "tgn:placetype":[
        "aat:300008347"
    ]
},
  "bbox": [],
  "geometry": {"coordinates":[20.55,2.2833],"type":"Point"}
}