{
  "id": 2283037,
  "type": "Feature",
  "properties": {
    "tgn:hierarchy":[
        "tgn:2283037",
        "tgn:1000001",
        "tgn:7012149",
        "tgn:2000476",
        "tgn:7007250",
        "tgn:7029392"
    ],
    "tgn:id":2283037,
    "tgn:name":"Del Rio Mine",
    "tgn:placetype":[
        "aat:300000390"
    ]
},
  "bbox": [],
  "geometry": {"coordinates":[-115.6667,45.55],"type":"Point"}
}