{
  "id": 2542902,
  "type": "Feature",
  "properties": {
    "tgn:hierarchy":[
        "tgn:2542902",
        "tgn:1000001",
        "tgn:7012149",
        "tgn:7007158",
        "tgn:2000246",
        "tgn:7029392"
    ],
    "tgn:id":2542902,
    "tgn:name":"Noland Gulch",
    "tgn:placetype":[
        "aat:300008761"
    ]
},
  "bbox": [],
  "geometry": {"coordinates":[-106.0167,38.1833],"type":"Point"}
}