{
  "id": 2504301,
  "type": "Feature",
  "properties": {
    "tgn:hierarchy":[
        "tgn:2504301",
        "tgn:1000001",
        "tgn:7012149",
        "tgn:2001548",
        "tgn:7007709",
        "tgn:7029392"
    ],
    "tgn:id":2504301,
    "tgn:name":"Meadowbrook",
    "tgn:placetype":[
        "aat:300008347"
    ]
},
  "bbox": [],
  "geometry": {"coordinates":[-78.3667,35.7667],"type":"Point"}
}