{
  "id": 2305103,
  "type": "Feature",
  "properties": {
    "tgn:hierarchy":[
        "tgn:2305103",
        "tgn:1000001",
        "tgn:7012149",
        "tgn:1002729",
        "tgn:7007710",
        "tgn:7029392"
    ],
    "tgn:id":2305103,
    "tgn:name":"East Branch Monocacy Creek",
    "tgn:placetype":[
        "aat:300008706"
    ]
},
  "bbox": [],
  "geometry": {"coordinates":[-75.3667,40.7667],"type":"Point"}
}