{
  "id": 7311049,
  "type": "Feature",
  "properties": {
    "tgn:hierarchy":[
        "tgn:7311049",
        "tgn:7002464",
        "tgn:1000049",
        "tgn:1000002",
        "tgn:7029392"
    ],
    "tgn:id":7311049,
    "tgn:name":"Oficina Paposo",
    "tgn:placetype":[
        "aat:300387200"
    ]
},
  "bbox": [],
  "geometry": {"coordinates":[-69.866667,-20.35],"type":"Point"}
}