{
  "id": 2130832,
  "type": "Feature",
  "properties": {
    "tgn:hierarchy":[
        "tgn:2130832",
        "tgn:1000001",
        "tgn:2002106",
        "tgn:7012149",
        "tgn:7007827",
        "tgn:7029392"
    ],
    "tgn:id":2130832,
    "tgn:name":"Allred",
    "tgn:placetype":[
        "aat:300008347"
    ]
},
  "bbox": [],
  "geometry": {"coordinates":[-112.0333,41.15],"type":"Point"}
}