{
  "id": 7422388,
  "type": "Feature",
  "properties": {
    "tgn:hierarchy":[
        "tgn:7422388",
        "tgn:1000001",
        "tgn:7005601",
        "tgn:7005560",
        "tgn:7029392"
    ],
    "tgn:id":7422388,
    "tgn:name":"Nuevo D\u00eda",
    "tgn:placetype":[
        "aat:300008347"
    ]
},
  "bbox": [],
  "geometry": {"coordinates":[-102.95,22.883333],"type":"Point"}
}