{
  "id": 2451539,
  "type": "Feature",
  "properties": {
    "tgn:hierarchy":[
        "tgn:2451539",
        "tgn:1000001",
        "tgn:7012149",
        "tgn:2001115",
        "tgn:7007522",
        "tgn:7029392"
    ],
    "tgn:id":2451539,
    "tgn:name":"Little Bear Bayou",
    "tgn:placetype":[
        "aat:300008699"
    ]
},
  "bbox": [],
  "geometry": {"coordinates":[-88.5833,30.5333],"type":"Point"}
}