{
  "id": 1094048,
  "type": "Feature",
  "properties": {
    "tgn:hierarchy":[
        "tgn:1094048",
        "tgn:7001242",
        "tgn:1000179",
        "tgn:1000200",
        "tgn:7029392"
    ],
    "tgn:id":1094048,
    "tgn:name":"Al Mahbas",
    "tgn:placetype":[
        "aat:300008347"
    ]
},
  "bbox": [],
  "geometry": {"coordinates":[-9.1667,27.4667],"type":"Point"}
}