{
  "id": 2294798,
  "type": "Feature",
  "properties": {
    "tgn:hierarchy":[
        "tgn:2294798",
        "tgn:1000001",
        "tgn:7019180",
        "tgn:7012149",
        "tgn:7007253",
        "tgn:7029392"
    ],
    "tgn:id":2294798,
    "tgn:name":"Drainage Ditch Number 117",
    "tgn:placetype":[
        "aat:300006075"
    ]
},
  "bbox": [],
  "geometry": {"coordinates":[-94.55,41.9167],"type":"Point"}
}