{
  "id": 7119756,
  "type": "Feature",
  "properties": {
    "tgn:hierarchy":[
        "tgn:7119756",
        "tgn:7000096",
        "tgn:1000003",
        "tgn:7000084",
        "tgn:7029392"
    ],
    "tgn:id":7119756,
    "tgn:name":"Pl\u00f6tzin",
    "tgn:placetype":[
        "aat:300008347"
    ]
},
  "bbox": [],
  "geometry": {"coordinates":[12.833333,52.366667],"type":"Point"}
}