{
  "id": 1023831,
  "type": "Feature",
  "properties": {
    "tgn:hierarchy":[
        "tgn:1023831",
        "tgn:1000050",
        "tgn:1000694",
        "tgn:1000002",
        "tgn:7029392"
    ],
    "tgn:id":1023831,
    "tgn:name":"Guamal",
    "tgn:placetype":[
        "aat:300008347"
    ]
},
  "bbox": [],
  "geometry": {"coordinates":[-73.7333,3.8667],"type":"Point"}
}