{
  "id": 7416080,
  "type": "Feature",
  "properties": {
    "tgn:hierarchy":[
        "tgn:7416080",
        "tgn:7005584",
        "tgn:1000001",
        "tgn:7005560",
        "tgn:7029392"
    ],
    "tgn:id":7416080,
    "tgn:name":"Presa El Caballero",
    "tgn:placetype":[
        "aat:300006191"
    ]
},
  "bbox": [],
  "geometry": {"coordinates":[-101.244444,21.741944],"type":"Point"}
}