{
  "id": 2573368,
  "type": "Feature",
  "properties": {
    "tgn:hierarchy":[
        "tgn:2573368",
        "tgn:1000001",
        "tgn:1002293",
        "tgn:7012149",
        "tgn:7007708",
        "tgn:7029392"
    ],
    "tgn:id":2573368,
    "tgn:name":"Pebble",
    "tgn:placetype":[
        "aat:300008347"
    ]
},
  "bbox": [],
  "geometry": {"coordinates":[-123.1833,45.8167],"type":"Point"}
}