{
  "id": 7007766,
  "type": "Feature",
  "properties": {
    "tgn:hierarchy":[
        "tgn:7007766",
        "tgn:7009084",
        "tgn:7004154",
        "tgn:1000003",
        "tgn:1000080",
        "tgn:7029392"
    ],
    "tgn:id":7007766,
    "tgn:name":"Roccaraso",
    "tgn:placetype":[
        "aat:300008347"
    ]
},
  "bbox": [],
  "geometry": {"coordinates":[14.083333,41.85],"type":"Point"}
}