{
  "id": 2670649,
  "type": "Feature",
  "properties": {
    "tgn:hierarchy":[
        "tgn:2670649",
        "tgn:1000001",
        "tgn:7012149",
        "tgn:2001535",
        "tgn:7007709",
        "tgn:7029392"
    ],
    "tgn:id":2670649,
    "tgn:name":"Smith Acres",
    "tgn:placetype":[
        "aat:300008347"
    ]
},
  "bbox": [],
  "geometry": {"coordinates":[-79.7833,36.4833],"type":"Point"}
}