{
  "id": 7228876,
  "type": "Feature",
  "properties": {
    "tgn:hierarchy":[
        "tgn:7228876",
        "tgn:7002715",
        "tgn:7002729",
        "tgn:1000003",
        "tgn:1000074",
        "tgn:7029392"
    ],
    "tgn:id":7228876,
    "tgn:name":"Gan\u00f3chora",
    "tgn:placetype":[
        "aat:300008347"
    ]
},
  "bbox": [],
  "geometry": {"coordinates":[22.493333,40.306389],"type":"Point"}
}