<<<<<<< HEAD
{
  "id": 2408004,
  "type": "Feature",
  "properties": {
    "tgn:hierarchy":[
        "tgn:2408004",
        "tgn:1002148",
        "tgn:1000001",
        "tgn:7012149",
        "tgn:7007826",
        "tgn:7029392"
    ],
    "tgn:id":2408004,
    "tgn:name":"Hurricane Creek",
    "tgn:placetype":[
        "aat:300008706"
    ]
},
  "bbox": [],
  "geometry": {"coordinates":[-95.5833,31.8833],"type":"Point"}
}
=======
{"geometry":{"type":"Point","coordinates":[-95.583300,31.883300]},"type":"Feature","properties":{"hierarchy":["tgn:2408004","tgn:1002148","tgn:1000001","tgn:7012149","tgn:7007826","tgn:7029392"],"placetype":["aat:300008706"],"id":2408004,"name:xx":"Hurricane Creek"}}
>>>>>>> 03f74aca74312dbeaf24d7e61306dd6a786dc3d0
