{
  "id": 2674854,
  "type": "Feature",
  "properties": {
    "tgn:hierarchy":[
        "tgn:2674854",
        "tgn:1000001",
        "tgn:7012149",
        "tgn:2001456",
        "tgn:7007566",
        "tgn:7029392"
    ],
    "tgn:id":2674854,
    "tgn:name":"Socorro Ditch",
    "tgn:placetype":[
        "aat:300006075"
    ]
},
  "bbox": [],
  "geometry": {"coordinates":[-106.8667,34.0333],"type":"Point"}
}