{
  "id": 2150598,
  "type": "Feature",
  "properties": {
    "tgn:hierarchy":[
        "tgn:2150598",
        "tgn:1000001",
        "tgn:7012149",
        "tgn:2001898",
        "tgn:7007825",
        "tgn:7029392"
    ],
    "tgn:id":2150598,
    "tgn:name":"Basin, The",
    "tgn:placetype":[
        "aat:300386845"
    ]
},
  "bbox": [],
  "geometry": {"coordinates":[-84.4667,35.2833],"type":"Point"}
}