{
  "id": 7551851,
  "type": "Feature",
  "properties": {
    "tgn:hierarchy":[
        "tgn:7551851",
        "tgn:1000004",
        "tgn:1001869",
        "tgn:7000198",
        "tgn:7029392"
    ],
    "tgn:id":7551851,
    "tgn:name:en":"Boria Reef",
    "tgn:placetype":[
        "aat:300008808"
    ]
},
  "bbox": [],
  "geometry": {"coordinates":[69.216667,22.416667],"type":"Point"}
}