{
  "id": 2673333,
  "type": "Feature",
  "properties": {
    "tgn:hierarchy":[
        "tgn:2673333",
        "tgn:1000001",
        "tgn:7012149",
        "tgn:2000998",
        "tgn:7007520",
        "tgn:7029392"
    ],
    "tgn:id":2673333,
    "tgn:name":"Sneaky Valley",
    "tgn:placetype":[
        "aat:300008761"
    ]
},
  "bbox": [],
  "geometry": {"coordinates":[-85.7333,44.4667],"type":"Point"}
}