{
  "id": 7093273,
  "type": "Feature",
  "properties": {
    "tgn:hierarchy":[
        "tgn:7093273",
        "tgn:7003669",
        "tgn:1000003",
        "tgn:7000084",
        "tgn:7029392"
    ],
    "tgn:id":7093273,
    "tgn:name":"Schwaighof",
    "tgn:placetype":[
        "aat:300000206"
    ]
},
  "bbox": [],
  "geometry": {"coordinates":[13.066667,48.85],"type":"Point"}
}