{
  "id": 2665903,
  "type": "Feature",
  "properties": {
    "tgn:hierarchy":[
        "tgn:2665903",
        "tgn:1000001",
        "tgn:7012149",
        "tgn:2000180",
        "tgn:7007157",
        "tgn:7029392"
    ],
    "tgn:id":2665903,
    "tgn:name":"Siskiyou Fork",
    "tgn:placetype":[
        "aat:300008699"
    ]
},
  "bbox": [],
  "geometry": {"coordinates":[-123.6833,41.8667],"type":"Point"}
}