{
  "id": 1010381,
  "type": "Feature",
  "properties": {
    "tgn:hierarchy":[
        "tgn:1010381",
        "tgn:7005685",
        "tgn:1000001",
        "tgn:7005801",
        "tgn:7029392"
    ],
    "tgn:id":1010381,
    "tgn:name":"Wadham Islands",
    "tgn:placetype":[
        "aat:300386853"
    ]
},
  "bbox": [],
  "geometry": {"coordinates":[-53.8333,49.55],"type":"Point"}
}