{
  "id": 2391116,
  "type": "Feature",
  "properties": {
    "tgn:hierarchy":[
        "tgn:2391116",
        "tgn:1000001",
        "tgn:1002318",
        "tgn:7012149",
        "tgn:7007710",
        "tgn:7029392"
    ],
    "tgn:id":2391116,
    "tgn:name":"Hill Island",
    "tgn:placetype":[
        "aat:300008791"
    ]
},
  "bbox": [],
  "geometry": {"coordinates":[-76.7333,40.1667],"type":"Point"}
}