{
  "id": 7457710,
  "type": "Feature",
  "properties": {
    "tgn:hierarchy":[
        "tgn:7457710",
        "tgn:7002448",
        "tgn:7019216",
        "tgn:1000003",
        "tgn:7008591",
        "tgn:7029392"
    ],
    "tgn:id":7457710,
    "tgn:name:en":"Macosquin River",
    "tgn:placetype":[
        "aat:300008699"
    ]
},
  "bbox": [],
  "geometry": {"coordinates":[-6.583333,55.05],"type":"Point"}
}