{
  "id": 2248626,
  "type": "Feature",
  "properties": {
    "tgn:hierarchy":[
        "tgn:2248626",
        "tgn:1000001",
        "tgn:7012149",
        "tgn:2002266",
        "tgn:7013961",
        "tgn:7029392"
    ],
    "tgn:id":2248626,
    "tgn:name":"Cold Spring Hollow",
    "tgn:placetype":[
        "aat:300008761"
    ]
},
  "bbox": [],
  "geometry": {"coordinates":[-78.9667,39.0167],"type":"Point"}
}