{
  "id": 2755237,
  "type": "Feature",
  "properties": {
    "tgn:hierarchy":[
        "tgn:2755237",
        "tgn:1000001",
        "tgn:7012149",
        "tgn:7007919",
        "tgn:7029392"
    ],
    "tgn:id":2755237,
    "tgn:name":"Webb Run",
    "tgn:placetype":[
        "aat:300008699"
    ]
},
  "bbox": [],
  "geometry": {"coordinates":[-76.7333,37.9667],"type":"Point"}
}