{
  "id": 7474375,
  "type": "Feature",
  "properties": {
    "tgn:hierarchy":[
        "tgn:7474375",
        "tgn:1000004",
        "tgn:1000454",
        "tgn:1000141",
        "tgn:7029392"
    ],
    "tgn:id":7474375,
    "tgn:name":"Yuanchuang",
    "tgn:placetype":[
        "aat:300008347"
    ]
},
  "bbox": [],
  "geometry": {"coordinates":[121.508028,25.274483],"type":"Point"}
}