<<<<<<< HEAD
{
  "id": 2400021,
  "type": "Feature",
  "properties": {
    "tgn:hierarchy":[
        "tgn:2400021",
        "tgn:1002146",
        "tgn:1000001",
        "tgn:7012149",
        "tgn:7007157",
        "tgn:7029392"
    ],
    "tgn:id":2400021,
    "tgn:name":"Horse Creek",
    "tgn:placetype":[
        "aat:300008706"
    ]
},
  "bbox": [],
  "geometry": {"coordinates":[-120.8167,38.4],"type":"Point"}
}
=======
{"geometry":{"type":"Point","coordinates":[-120.816700,38.400000]},"type":"Feature","properties":{"hierarchy":["tgn:2400021","tgn:1002146","tgn:1000001","tgn:7012149","tgn:7007157","tgn:7029392"],"placetype":["aat:300008706"],"id":2400021,"name:xx":"Horse Creek"}}
>>>>>>> 03f74aca74312dbeaf24d7e61306dd6a786dc3d0
