{
  "id": 2731751,
  "type": "Feature",
  "properties": {
    "tgn:hierarchy":[
        "tgn:2731751",
        "tgn:1000001",
        "tgn:7012149",
        "tgn:2001453",
        "tgn:7007566",
        "tgn:7029392"
    ],
    "tgn:id":2731751,
    "tgn:name":"Tulosa Creek",
    "tgn:placetype":[
        "aat:300008706"
    ]
},
  "bbox": [],
  "geometry": {"coordinates":[-104.1333,35.5167],"type":"Point"}
}