<<<<<<< HEAD
{
  "id": 7377790,
  "type": "Feature",
  "properties": {
    "tgn:hierarchy":[
        "tgn:7377790",
        "tgn:7005584",
        "tgn:1000001",
        "tgn:7005560",
        "tgn:7029392"
    ],
    "tgn:id":7377790,
    "tgn:name":"Las Carretas",
    "tgn:placetype":[
        "aat:300008347"
    ]
},
  "bbox": [],
  "geometry": {"coordinates":[-101.566667,20.5],"type":"Point"}
}
=======
{"geometry":{"type":"Point","coordinates":[-101.566667,20.500000]},"type":"Feature","properties":{"hierarchy":["tgn:7377790","tgn:7005584","tgn:1000001","tgn:7005560","tgn:7029392"],"placetype":["aat:300008347"],"id":7377790,"name:xx":"Las Carretas"}}
>>>>>>> 03f74aca74312dbeaf24d7e61306dd6a786dc3d0
