{
  "id": 7586088,
  "type": "Feature",
  "properties": {
    "tgn:hierarchy":[
        "tgn:7586088",
        "tgn:1000004",
        "tgn:7000198",
        "tgn:1001977",
        "tgn:7029392"
    ],
    "tgn:id":7586088,
    "tgn:name:en":"H\u0101td\u0101nga",
    "tgn:placetype":[
        "aat:300008347"
    ]
},
  "bbox": [],
  "geometry": {"coordinates":[88.498889,22.791111],"type":"Point"}
}