{
  "id": 7198119,
  "type": "Feature",
  "properties": {
    "tgn:hierarchy":[
        "tgn:7198119",
        "tgn:1000003",
        "tgn:7003677",
        "tgn:7000084",
        "tgn:7029392"
    ],
    "tgn:id":7198119,
    "tgn:name":"Eichwald",
    "tgn:placetype":[
        "aat:300008863"
    ]
},
  "bbox": [],
  "geometry": {"coordinates":[8.166667,51.466667],"type":"Point"}
}