{
  "id": 7081063,
  "type": "Feature",
  "properties": {
    "tgn:hierarchy":[
        "tgn:7081063",
        "tgn:7003669",
        "tgn:1000003",
        "tgn:7000084",
        "tgn:7029392"
    ],
    "tgn:id":7081063,
    "tgn:name":"Woffendorf",
    "tgn:placetype":[
        "aat:300008347"
    ]
},
  "bbox": [],
  "geometry": {"coordinates":[11.233333,50.116667],"type":"Point"}
}