{
  "id": 2449219,
  "type": "Feature",
  "properties": {
    "tgn:hierarchy":[
        "tgn:2449219",
        "tgn:1000001",
        "tgn:7012149",
        "tgn:2001298",
        "tgn:7007524",
        "tgn:7029392"
    ],
    "tgn:id":2449219,
    "tgn:name":"Limestone Canyon",
    "tgn:placetype":[
        "aat:300008761"
    ]
},
  "bbox": [],
  "geometry": {"coordinates":[-112.8667,46.7167],"type":"Point"}
}