{
  "id": 2430706,
  "type": "Feature",
  "properties": {
    "tgn:hierarchy":[
        "tgn:2430706",
        "tgn:7023902",
        "tgn:1000001",
        "tgn:7012149",
        "tgn:7007249",
        "tgn:7029392"
    ],
    "tgn:id":2430706,
    "tgn:name":"Kaluahee Rock",
    "tgn:placetype":[
        "aat:300008791"
    ]
},
  "bbox": [],
  "geometry": {"coordinates":[-155.8833,19.2833],"type":"Point"}
}