{
  "id": 2307490,
  "type": "Feature",
  "properties": {
    "tgn:hierarchy":[
        "tgn:2307490",
        "tgn:7006450",
        "tgn:1000001",
        "tgn:7012149",
        "tgn:2000082",
        "tgn:7029392"
    ],
    "tgn:id":2307490,
    "tgn:name":"East Fork Short Creek",
    "tgn:placetype":[
        "aat:300008706"
    ]
},
  "bbox": [],
  "geometry": {"coordinates":[-131.5333,56.05],"type":"Point"}
}