{
  "id": 2332381,
  "type": "Feature",
  "properties": {
    "tgn:hierarchy":[
        "tgn:2332381",
        "tgn:1000001",
        "tgn:7012149",
        "tgn:2002379",
        "tgn:7007923",
        "tgn:7029392"
    ],
    "tgn:id":2332381,
    "tgn:name":"Flora Lake",
    "tgn:placetype":[
        "aat:300008680"
    ]
},
  "bbox": [],
  "geometry": {"coordinates":[-109.9333,44.35],"type":"Point"}
}