<<<<<<< HEAD
{
  "id": 2332381,
  "type": "Feature",
  "properties": {
    "tgn:hierarchy":[
        "tgn:2332381",
        "tgn:1000001",
        "tgn:7012149",
        "tgn:2002379",
        "tgn:7007923",
        "tgn:7029392"
    ],
    "tgn:id":2332381,
    "tgn:name":"Flora Lake",
    "tgn:placetype":[
        "aat:300008680"
    ]
},
  "bbox": [],
  "geometry": {"coordinates":[-109.9333,44.35],"type":"Point"}
}
=======
{"geometry":{"type":"Point","coordinates":[-109.933300,44.350000]},"type":"Feature","properties":{"hierarchy":["tgn:2332381","tgn:1000001","tgn:7012149","tgn:2002379","tgn:7007923","tgn:7029392"],"placetype":["aat:300008680"],"id":2332381,"name:xx":"Flora Lake"}}
>>>>>>> 03f74aca74312dbeaf24d7e61306dd6a786dc3d0
