{
  "id": 2583407,
  "type": "Feature",
  "properties": {
    "tgn:hierarchy":[
        "tgn:2583407",
        "tgn:1000001",
        "tgn:1002714",
        "tgn:7012149",
        "tgn:7007159",
        "tgn:7029392"
    ],
    "tgn:id":2583407,
    "tgn:name":"Pine Point",
    "tgn:placetype":[
        "aat:300008850"
    ]
},
  "bbox": [],
  "geometry": {"coordinates":[-71.9667,41.3333],"type":"Point"}
}