{
  "id": 7485738,
  "type": "Feature",
  "properties": {
    "tgn:hierarchy":[
        "tgn:7485738",
        "tgn:1000004",
        "tgn:7490934",
        "tgn:1000141",
        "tgn:7029392"
    ],
    "tgn:id":7485738,
    "tgn:name":"Houjia Guozhong",
    "tgn:placetype":[
        "aat:300006495"
    ]
},
  "bbox": [],
  "geometry": {"coordinates":[120.226111,22.995833],"type":"Point"}
}