{
  "id": 7259284,
  "type": "Feature",
  "properties": {
    "tgn:hierarchy":[
        "tgn:7259284",
        "tgn:7018239",
        "tgn:1000003",
        "tgn:1000063",
        "tgn:7018236",
        "tgn:7029392"
    ],
    "tgn:id":7259284,
    "tgn:name":"Vroenenbos",
    "tgn:placetype":[
        "aat:300008863"
    ]
},
  "bbox": [],
  "geometry": {"coordinates":[4.283333,50.716667],"type":"Point"}
}