{
  "id": 7203861,
  "type": "Feature",
  "properties": {
    "tgn:hierarchy":[
        "tgn:7203861",
        "tgn:1000003",
        "tgn:7003685",
        "tgn:7000084",
        "tgn:7029392"
    ],
    "tgn:id":7203861,
    "tgn:name":"Brauns Berg",
    "tgn:placetype":[
        "aat:300008777"
    ]
},
  "bbox": [],
  "geometry": {"coordinates":[13.783333,50.933333],"type":"Point"}
}