{
  "id": 2096024,
  "type": "Feature",
  "properties": {
    "tgn:hierarchy":[
        "tgn:2096024",
        "tgn:1000001",
        "tgn:7012149",
        "tgn:2001766",
        "tgn:7007712",
        "tgn:7029392"
    ],
    "tgn:id":2096024,
    "tgn:name":"Inman",
    "tgn:placetype":[
        "aat:300008347"
    ]
},
  "bbox": [],
  "geometry": {"coordinates":[-82.0833,35.0333],"type":"Point"}
}