{
  "id": 2221449,
  "type": "Feature",
  "properties": {
    "tgn:hierarchy":[
        "tgn:2221449",
        "tgn:1000001",
        "tgn:7006451",
        "tgn:7012149",
        "tgn:2000100",
        "tgn:7029392"
    ],
    "tgn:id":2221449,
    "tgn:name":"Cargodera Spring",
    "tgn:placetype":[
        "aat:300008697"
    ]
},
  "bbox": [],
  "geometry": {"coordinates":[-110.85,32.4333],"type":"Point"}
}