{
  "id": 2673718,
  "type": "Feature",
  "properties": {
    "tgn:hierarchy":[
        "tgn:2673718",
        "tgn:7006450",
        "tgn:1000001",
        "tgn:7012149",
        "tgn:2000079",
        "tgn:7029392"
    ],
    "tgn:id":2673718,
    "tgn:name":"Snow Creek",
    "tgn:placetype":[
        "aat:300008706"
    ]
},
  "bbox": [],
  "geometry": {"coordinates":[-163.8167,64.6833],"type":"Point"}
}