{
  "id": 2594960,
  "type": "Feature",
  "properties": {
    "tgn:hierarchy":[
        "tgn:2594960",
        "tgn:1000001",
        "tgn:1002664",
        "tgn:7012149",
        "tgn:7007159",
        "tgn:7029392"
    ],
    "tgn:id":2594960,
    "tgn:name":"Post Cove",
    "tgn:placetype":[
        "aat:300132316"
    ]
},
  "bbox": [],
  "geometry": {"coordinates":[-72.4167,41.3833],"type":"Point"}
}