{
  "id": 2762744,
  "type": "Feature",
  "properties": {
    "tgn:hierarchy":[
        "tgn:2762744",
        "tgn:1000001",
        "tgn:7012149",
        "tgn:7007825",
        "tgn:7029392"
    ],
    "tgn:id":2762744,
    "tgn:name":"Western Highland Rim",
    "tgn:placetype":[
        "aat:300055621"
    ]
},
  "bbox": [],
  "geometry": {"coordinates":[-87.4167,35.9167],"type":"Point"}
}