<<<<<<< HEAD
{
  "id": 2762744,
  "type": "Feature",
  "properties": {
    "tgn:hierarchy":[
        "tgn:2762744",
        "tgn:1000001",
        "tgn:7012149",
        "tgn:7007825",
        "tgn:7029392"
    ],
    "tgn:id":2762744,
    "tgn:name":"Western Highland Rim",
    "tgn:placetype":[
        "aat:300055621"
    ]
},
  "bbox": [],
  "geometry": {"coordinates":[-87.4167,35.9167],"type":"Point"}
}
=======
{"geometry":{"type":"Point","coordinates":[-87.416700,35.916700]},"type":"Feature","properties":{"hierarchy":["tgn:2762744","tgn:1000001","tgn:7012149","tgn:7007825","tgn:7029392"],"placetype":["aat:300055621"],"id":2762744,"name:xx":"Western Highland Rim"}}
>>>>>>> 03f74aca74312dbeaf24d7e61306dd6a786dc3d0
