{
  "id": 1032935,
  "type": "Feature",
  "properties": {
    "tgn:hierarchy":[
        "tgn:1032935",
        "tgn:1000003",
        "tgn:7012216",
        "tgn:1000070",
        "tgn:7029392"
    ],
    "tgn:id":1032935,
    "tgn:name":"Dinard-Saint-Enogat",
    "tgn:placetype":[
        "aat:300008347"
    ]
},
  "bbox": [],
  "geometry": {"coordinates":[-2.05,48.6333],"type":"Point"}
}