{
  "id": 1019952,
  "type": "Feature",
  "properties": {
    "tgn:hierarchy":[
        "tgn:1019952",
        "tgn:7006477",
        "tgn:1001514",
        "tgn:1000002",
        "tgn:7029392"
    ],
    "tgn:id":1019952,
    "tgn:name":"Rosario de Lerma",
    "tgn:placetype":[
        "aat:300008347"
    ]
},
  "bbox": [],
  "geometry": {"coordinates":[-65.5833,-24.9833],"type":"Point"}
}