{
  "id": 2102604,
  "type": "Feature",
  "properties": {
    "tgn:hierarchy":[
        "tgn:2102604",
        "tgn:1000001",
        "tgn:7012149",
        "tgn:1002456",
        "tgn:7007826",
        "tgn:7029392"
    ],
    "tgn:id":2102604,
    "tgn:name":"Bay Oaks",
    "tgn:placetype":[
        "aat:300008347"
    ]
},
  "bbox": [],
  "geometry": {"coordinates":[-95.0167,29.6333],"type":"Point"}
}