{
  "id": 1111064,
  "type": "Feature",
  "properties": {
    "tgn:hierarchy":[
        "tgn:1111064",
        "tgn:7001242",
        "tgn:7001311",
        "tgn:7016833",
        "tgn:7029392"
    ],
    "tgn:id":1111064,
    "tgn:name:en":"Hawash\u012bya, W\u0101di",
    "tgn:placetype":[
        "aat:300379998",
        "aat:300387091"
    ]
},
  "bbox": [],
  "geometry": {"coordinates":[32.941885,28.537078],"type":"Point"}
}