{
  "id": 1071584,
  "type": "Feature",
  "properties": {
    "tgn:hierarchy":[
        "tgn:1071584",
        "tgn:7002075",
        "tgn:1000004",
        "tgn:1000111",
        "tgn:7029392"
    ],
    "tgn:id":1071584,
    "tgn:name":"Shencun",
    "tgn:placetype":[
        "aat:300008347"
    ]
},
  "bbox": [],
  "geometry": {"coordinates":[118.85,31.05],"type":"Point"}
}