<<<<<<< HEAD
{
  "id": 2403650,
  "type": "Feature",
  "properties": {
    "tgn:hierarchy":[
        "tgn:2403650",
        "tgn:1000001",
        "tgn:7012149",
        "tgn:2001895",
        "tgn:7007825",
        "tgn:7029392"
    ],
    "tgn:id":2403650,
    "tgn:name":"Howard Hill",
    "tgn:placetype":[
        "aat:300008798"
    ]
},
  "bbox": [],
  "geometry": {"coordinates":[-86.7667,35.6833],"type":"Point"}
}
=======
{"geometry":{"type":"Point","coordinates":[-86.766700,35.683300]},"type":"Feature","properties":{"hierarchy":["tgn:2403650","tgn:1000001","tgn:7012149","tgn:2001895","tgn:7007825","tgn:7029392"],"placetype":["aat:300008798"],"id":2403650,"name:xx":"Howard Hill"}}
>>>>>>> 03f74aca74312dbeaf24d7e61306dd6a786dc3d0
