{
  "id": 1019979,
  "type": "Feature",
  "properties": {
    "tgn:hierarchy":[
        "tgn:1019979",
        "tgn:7006477",
        "tgn:7006348",
        "tgn:1000002",
        "tgn:7029392"
    ],
    "tgn:id":1019979,
    "tgn:name":"San Antonio Oeste",
    "tgn:placetype":[
        "aat:300008347"
    ]
},
  "bbox": [],
  "geometry": {"coordinates":[-64.9667,-40.75],"type":"Point"}
}