{
  "id": 2116765,
  "type": "Feature",
  "properties": {
    "tgn:hierarchy":[
        "tgn:2116765",
        "tgn:1000001",
        "tgn:7012149",
        "tgn:1002767",
        "tgn:7007920",
        "tgn:7029392"
    ],
    "tgn:id":2116765,
    "tgn:name":"Seaview",
    "tgn:placetype":[
        "aat:300008347"
    ]
},
  "bbox": [],
  "geometry": {"coordinates":[-124.05,46.3333],"type":"Point"}
}