{
  "id": 2092703,
  "type": "Feature",
  "properties": {
    "tgn:hierarchy":[
        "tgn:2092703",
        "tgn:1000001",
        "tgn:7012149",
        "tgn:1002945",
        "tgn:7007710",
        "tgn:7029392"
    ],
    "tgn:id":2092703,
    "tgn:name":"Sabinsville",
    "tgn:placetype":[
        "aat:300008347"
    ]
},
  "bbox": [],
  "geometry": {"coordinates":[-77.5167,41.8667],"type":"Point"}
}