{
  "id": 2675610,
  "type": "Feature",
  "properties": {
    "tgn:hierarchy":[
        "tgn:2675610",
        "tgn:7002659",
        "tgn:1000001",
        "tgn:7012149",
        "tgn:2000031",
        "tgn:7029392"
    ],
    "tgn:id":2675610,
    "tgn:name":"Solomon Hill",
    "tgn:placetype":[
        "aat:300008798"
    ]
},
  "bbox": [],
  "geometry": {"coordinates":[-88.0167,32.85],"type":"Point"}
}