{
  "id": 7080408,
  "type": "Feature",
  "properties": {
    "tgn:hierarchy":[
        "tgn:7080408",
        "tgn:1000003",
        "tgn:7003688",
        "tgn:7000084",
        "tgn:7029392"
    ],
    "tgn:id":7080408,
    "tgn:name":"Winser Berg",
    "tgn:placetype":[
        "aat:300008777"
    ]
},
  "bbox": [],
  "geometry": {"coordinates":[10.033333,53.833333],"type":"Point"}
}