{
  "id": 7539617,
  "type": "Feature",
  "properties": {
    "tgn:hierarchy":[
        "tgn:7539617",
        "tgn:7001242",
        "tgn:7016833",
        "tgn:7000124",
        "tgn:7029392"
    ],
    "tgn:id":7539617,
    "tgn:name:en":"Naj' Ab\u016b Laylah",
    "tgn:placetype":[
        "aat:300008347"
    ]
},
  "bbox": [],
  "geometry": {"coordinates":[31.430265,26.734358],"type":"Point"}
}