{
  "id": 2194273,
  "type": "Feature",
  "properties": {
    "tgn:hierarchy":[
        "tgn:2194273",
        "tgn:7006450",
        "tgn:1000001",
        "tgn:7012149",
        "tgn:2000086",
        "tgn:7029392"
    ],
    "tgn:id":2194273,
    "tgn:name":"Bridge Creek",
    "tgn:placetype":[
        "aat:300008706"
    ]
},
  "bbox": [],
  "geometry": {"coordinates":[-144.1833,61.3333],"type":"Point"}
}