{
  "id": 7581009,
  "type": "Feature",
  "properties": {
    "tgn:hierarchy":[
        "tgn:7581009",
        "tgn:1000004",
        "tgn:7000198",
        "tgn:7016722",
        "tgn:7029392"
    ],
    "tgn:id":7581009,
    "tgn:name:en":"Tindauli",
    "tgn:placetype":[
        "aat:300008347"
    ]
},
  "bbox": [],
  "geometry": {"coordinates":[78.921524,27.183732],"type":"Point"}
}