<<<<<<< HEAD
{
  "id": 7485024,
  "type": "Feature",
  "properties": {
    "tgn:hierarchy":[
        "tgn:7485024",
        "tgn:1000004",
        "tgn:7491221",
        "tgn:1000141",
        "tgn:7029392"
    ],
    "tgn:id":7485024,
    "tgn:name":"Gongzuodi",
    "tgn:placetype":[
        "aat:300008347"
    ]
},
  "bbox": [],
  "geometry": {"coordinates":[120.922222,22.456667],"type":"Point"}
}
=======
{"geometry":{"type":"Point","coordinates":[120.922222,22.456667]},"type":"Feature","properties":{"hierarchy":["tgn:7485024","tgn:1000004","tgn:7491221","tgn:1000141","tgn:7029392"],"placetype":["aat:300008347"],"id":7485024,"name:xx":"Gongzuodi"}}
>>>>>>> 03f74aca74312dbeaf24d7e61306dd6a786dc3d0
