{
  "id": 7415047,
  "type": "Feature",
  "properties": {
    "tgn:hierarchy":[
        "tgn:7415047",
        "tgn:1000001",
        "tgn:7005591",
        "tgn:7005560",
        "tgn:7029392"
    ],
    "tgn:id":7415047,
    "tgn:name:es":"R\u00edo Ejutla",
    "tgn:placetype":[
        "aat:300008347"
    ]
},
  "bbox": [],
  "geometry": {"coordinates":[-96.811111,16.546944],"type":"Point"}
}