{
  "id": 7177111,
  "type": "Feature",
  "properties": {
    "tgn:hierarchy":[
        "tgn:7177111",
        "tgn:1000003",
        "tgn:7003676",
        "tgn:7000084",
        "tgn:7029392"
    ],
    "tgn:id":7177111,
    "tgn:name":"Halenhorst",
    "tgn:placetype":[
        "aat:300008347"
    ]
},
  "bbox": [],
  "geometry": {"coordinates":[8.15,52.983333],"type":"Point"}
}