<<<<<<< HEAD
{
  "id": 7177111,
  "type": "Feature",
  "properties": {
    "tgn:hierarchy":[
        "tgn:7177111",
        "tgn:1000003",
        "tgn:7003676",
        "tgn:7000084",
        "tgn:7029392"
    ],
    "tgn:id":7177111,
    "tgn:name":"Halenhorst",
    "tgn:placetype":[
        "aat:300008347"
    ]
},
  "bbox": [],
  "geometry": {"coordinates":[8.15,52.983333],"type":"Point"}
}
=======
{"geometry":{"type":"Point","coordinates":[8.150000,52.983333]},"type":"Feature","properties":{"hierarchy":["tgn:7177111","tgn:1000003","tgn:7003676","tgn:7000084","tgn:7029392"],"placetype":["aat:300008347"],"id":7177111,"name:xx":"Halenhorst"}}
>>>>>>> 03f74aca74312dbeaf24d7e61306dd6a786dc3d0
