{
  "id": 7309119,
  "type": "Feature",
  "properties": {
    "tgn:hierarchy":[
        "tgn:7309119",
        "tgn:7002464",
        "tgn:1000049",
        "tgn:1000002",
        "tgn:7029392"
    ],
    "tgn:id":7309119,
    "tgn:name":"Macaya, Quebrada",
    "tgn:placetype":[
        "aat:300266554",
        "aat:300008699"
    ]
},
  "bbox": [],
  "geometry": {"coordinates":[-69.25,-20.15],"type":"Point"}
}