<<<<<<< HEAD
{
  "id": 2337476,
  "type": "Feature",
  "properties": {
    "tgn:hierarchy":[
        "tgn:2337476",
        "tgn:1000001",
        "tgn:7012149",
        "tgn:2000927",
        "tgn:7007515",
        "tgn:7029392"
    ],
    "tgn:id":2337476,
    "tgn:name":"Fowler Landing",
    "tgn:placetype":[
        "aat:300008347"
    ]
},
  "bbox": [],
  "geometry": {"coordinates":[-68.9333,44.7667],"type":"Point"}
}
=======
{"geometry":{"type":"Point","coordinates":[-68.933300,44.766700]},"type":"Feature","properties":{"hierarchy":["tgn:2337476","tgn:1000001","tgn:7012149","tgn:2000927","tgn:7007515","tgn:7029392"],"placetype":["aat:300008347"],"id":2337476,"name:xx":"Fowler Landing"}}
>>>>>>> 03f74aca74312dbeaf24d7e61306dd6a786dc3d0
