{
  "id": 2337476,
  "type": "Feature",
  "properties": {
    "tgn:hierarchy":[
        "tgn:2337476",
        "tgn:1000001",
        "tgn:7012149",
        "tgn:2000927",
        "tgn:7007515",
        "tgn:7029392"
    ],
    "tgn:id":2337476,
    "tgn:name":"Fowler Landing",
    "tgn:placetype":[
        "aat:300008347"
    ]
},
  "bbox": [],
  "geometry": {"coordinates":[-68.9333,44.7667],"type":"Point"}
}