{
  "id": 2204221,
  "type": "Feature",
  "properties": {
    "tgn:hierarchy":[
        "tgn:2204221",
        "tgn:1000001",
        "tgn:7012149",
        "tgn:1002678",
        "tgn:7007252",
        "tgn:7029392"
    ],
    "tgn:id":2204221,
    "tgn:name":"Buenavista",
    "tgn:placetype":[
        "aat:300008347"
    ]
},
  "bbox": [],
  "geometry": {"coordinates":[-87.65,39.0167],"type":"Point"}
}