{
  "id": 2132234,
  "type": "Feature",
  "properties": {
    "tgn:hierarchy":[
        "tgn:2132234",
        "tgn:1000001",
        "tgn:7012149",
        "tgn:7018871",
        "tgn:7007920",
        "tgn:7029392"
    ],
    "tgn:id":2132234,
    "tgn:name":"Ames Lake Pothole",
    "tgn:placetype":[
        "aat:300008680"
    ]
},
  "bbox": [],
  "geometry": {"coordinates":[-121.9667,47.6333],"type":"Point"}
}