{
  "id": 2595612,
  "type": "Feature",
  "properties": {
    "tgn:hierarchy":[
        "tgn:2595612",
        "tgn:1000001",
        "tgn:7012149",
        "tgn:1002995",
        "tgn:7007710",
        "tgn:7029392"
    ],
    "tgn:id":2595612,
    "tgn:name":"Potato Run",
    "tgn:placetype":[
        "aat:300008699"
    ]
},
  "bbox": [],
  "geometry": {"coordinates":[-80.1667,40.1167],"type":"Point"}
}