{
  "id": 2651480,
  "type": "Feature",
  "properties": {
    "tgn:hierarchy":[
        "tgn:2651480",
        "tgn:1000001",
        "tgn:7012149",
        "tgn:7022218",
        "tgn:7007919",
        "tgn:7029392"
    ],
    "tgn:id":2651480,
    "tgn:name":"Sedge Island Point",
    "tgn:placetype":[
        "aat:300008850"
    ]
},
  "bbox": [],
  "geometry": {"coordinates":[-75.9333,36.5667],"type":"Point"}
}