{
  "id": 2699643,
  "type": "Feature",
  "properties": {
    "tgn:hierarchy":[
        "tgn:2699643",
        "tgn:1000001",
        "tgn:7012149",
        "tgn:7007157",
        "tgn:7014516",
        "tgn:7029392"
    ],
    "tgn:id":2699643,
    "tgn:name":"Stuart Canyon",
    "tgn:placetype":[
        "aat:300008761"
    ]
},
  "bbox": [],
  "geometry": {"coordinates":[-122.4667,38.3833],"type":"Point"}
}