{
  "id": 7530194,
  "type": "Feature",
  "properties": {
    "tgn:hierarchy":[
        "tgn:7530194",
        "tgn:7001242",
        "tgn:7016833",
        "tgn:7001335",
        "tgn:7029392"
    ],
    "tgn:id":7530194,
    "tgn:name":"Umm Jayr, Jabal",
    "tgn:placetype":[
        "aat:300008795"
    ]
},
  "bbox": [],
  "geometry": {"coordinates":[34.33168,30.739637],"type":"Point"}
}