{
  "id": 7149695,
  "type": "Feature",
  "properties": {
    "tgn:hierarchy":[
        "tgn:7149695",
        "tgn:1000003",
        "tgn:7003677",
        "tgn:7000084",
        "tgn:7029392"
    ],
    "tgn:id":7149695,
    "tgn:name":"L\u00e4mershagen-Gr\u00e4finghagen",
    "tgn:placetype":[
        "aat:300387173"
    ]
},
  "bbox": [],
  "geometry": {"coordinates":[8.616667,51.966667],"type":"Point"}
}