{
  "id": 2511187,
  "type": "Feature",
  "properties": {
    "tgn:hierarchy":[
        "tgn:2511187",
        "tgn:7006450",
        "tgn:1000001",
        "tgn:2000071",
        "tgn:7012149",
        "tgn:7029392"
    ],
    "tgn:id":2511187,
    "tgn:name":"Mikchalk Lake",
    "tgn:placetype":[
        "aat:300008680"
    ]
},
  "bbox": [],
  "geometry": {"coordinates":[-158.8667,59.7333],"type":"Point"}
}