{
  "id": 7452063,
  "type": "Feature",
  "properties": {
    "tgn:hierarchy":[
        "tgn:7452063",
        "tgn:7002444",
        "tgn:1000003",
        "tgn:7019123",
        "tgn:7008591",
        "tgn:7029392"
    ],
    "tgn:id":7452063,
    "tgn:name:en":"Hawthornden",
    "tgn:placetype":[
        "aat:300008347"
    ]
},
  "bbox": [],
  "geometry": {"coordinates":[-3.133333,55.85],"type":"Point"}
}