{
  "id": 1086723,
  "type": "Feature",
  "properties": {
    "tgn:hierarchy":[
        "tgn:1086723",
        "tgn:7016655",
        "tgn:1000004",
        "tgn:7018455",
        "tgn:1000144",
        "tgn:7029392"
    ],
    "tgn:id":1086723,
    "tgn:name":"Narman",
    "tgn:placetype":[
        "aat:300008347"
    ]
},
  "bbox": [],
  "geometry": {"coordinates":[41.8333,40.3667],"type":"Point"}
}