{
  "id": 7197854,
  "type": "Feature",
  "properties": {
    "tgn:hierarchy":[
        "tgn:7197854",
        "tgn:1000003",
        "tgn:7003677",
        "tgn:7000084",
        "tgn:7029392"
    ],
    "tgn:id":7197854,
    "tgn:name":"D\u00fcferoth",
    "tgn:placetype":[
        "aat:300387200"
    ]
},
  "bbox": [],
  "geometry": {"coordinates":[7.25,50.733333],"type":"Point"}
}