{
  "id": 7395197,
  "type": "Feature",
  "properties": {
    "tgn:hierarchy":[
        "tgn:7395197",
        "tgn:7005581",
        "tgn:1000001",
        "tgn:7005560",
        "tgn:7029392"
    ],
    "tgn:id":7395197,
    "tgn:name":"Rancho San Jos\u00e9 del Milagro",
    "tgn:placetype":[
        "aat:300000241"
    ]
},
  "bbox": [],
  "geometry": {"coordinates":[-105.133333,27.516667],"type":"Point"}
}