{
  "id": 2690810,
  "type": "Feature",
  "properties": {
    "tgn:hierarchy":[
        "tgn:2690810",
        "tgn:1000001",
        "tgn:2002369",
        "tgn:7012149",
        "tgn:7007923",
        "tgn:7029392"
    ],
    "tgn:id":2690810,
    "tgn:name":"Standing Rock Creek",
    "tgn:placetype":[
        "aat:300008706"
    ]
},
  "bbox": [],
  "geometry": {"coordinates":[-105.8167,42.5333],"type":"Point"}
}