{
  "id": 7567485,
  "type": "Feature",
  "properties": {
    "tgn:hierarchy":[
        "tgn:7567485",
        "tgn:1000004",
        "tgn:7000198",
        "tgn:7031786",
        "tgn:7029392"
    ],
    "tgn:id":7567485,
    "tgn:name:en":"S\u012bla Reserved Forest",
    "tgn:placetype":[
        "aat:300008865"
    ]
},
  "bbox": [],
  "geometry": {"coordinates":[78.66,29.815556],"type":"Point"}
}