{
  "id": 1075005,
  "type": "Feature",
  "properties": {
    "tgn:hierarchy":[
        "tgn:1075005",
        "tgn:1000004",
        "tgn:7000198",
        "tgn:1001895",
        "tgn:7029392"
    ],
    "tgn:id":1075005,
    "tgn:name:en":"Chipl\u016bn",
    "tgn:placetype":[
        "aat:300008347"
    ]
},
  "bbox": [],
  "geometry": {"coordinates":[73.509,17.533],"type":"Point"}
}