{
  "id": 1010922,
  "type": "Feature",
  "properties": {
    "tgn:hierarchy":[
        "tgn:1010922",
        "tgn:1001724",
        "tgn:1000003",
        "tgn:7003121",
        "tgn:1000080",
        "tgn:7029392"
    ],
    "tgn:id":1010922,
    "tgn:name":"Marargiu, Capo",
    "tgn:placetype":[
        "aat:300008850"
    ]
},
  "bbox": [],
  "geometry": {"coordinates":[8.3833,40.3333],"type":"Point"}
}