{
  "id": 7297981,
  "type": "Feature",
  "properties": {
    "tgn:hierarchy":[
        "tgn:7297981",
        "tgn:7002815",
        "tgn:1000003",
        "tgn:7002793",
        "tgn:1000095",
        "tgn:7029392"
    ],
    "tgn:id":7297981,
    "tgn:name":"Serrallo, Playa del",
    "tgn:placetype":[
        "aat:300008816"
    ]
},
  "bbox": [],
  "geometry": {"coordinates":[0.016667,39.966667],"type":"Point"}
}