{
  "id": 1112946,
  "type": "Feature",
  "properties": {
    "tgn:hierarchy":[
        "tgn:1112946",
        "tgn:1000003",
        "tgn:7003688",
        "tgn:7000084",
        "tgn:7029392"
    ],
    "tgn:id":1112946,
    "tgn:name":"Eckernf\u00f6rder Bucht",
    "tgn:placetype":[
        "aat:300132316"
    ]
},
  "bbox": [],
  "geometry": {"coordinates":[9.8333,54.4667],"type":"Point"}
}