{
  "id": 2508397,
  "type": "Feature",
  "properties": {
    "tgn:hierarchy":[
        "tgn:2508397",
        "tgn:1000001",
        "tgn:2001416",
        "tgn:7012149",
        "tgn:7007526",
        "tgn:7029392"
    ],
    "tgn:id":2508397,
    "tgn:name":"Middle Cole Spring",
    "tgn:placetype":[
        "aat:300008697"
    ]
},
  "bbox": [],
  "geometry": {"coordinates":[-114.3167,38.1667],"type":"Point"}
}