{
  "id": 7253646,
  "type": "Feature",
  "properties": {
    "tgn:hierarchy":[
        "tgn:7253646",
        "tgn:7003457",
        "tgn:1000003",
        "tgn:1000063",
        "tgn:7018236",
        "tgn:7029392"
    ],
    "tgn:id":7253646,
    "tgn:name":"Uitbergen",
    "tgn:placetype":[
        "aat:300008347"
    ]
},
  "bbox": [],
  "geometry": {"coordinates":[3.955054,51.021515],"type":"Point"}
}