{
  "id": 1053598,
  "type": "Feature",
  "properties": {
    "tgn:hierarchy":[
        "tgn:1053598",
        "tgn:7011648",
        "tgn:1000003",
        "tgn:7006660",
        "tgn:7029392"
    ],
    "tgn:id":1053598,
    "tgn:name":"Devladovo",
    "tgn:placetype":[
        "aat:300008347"
    ]
},
  "bbox": [],
  "geometry": {"coordinates":[33.85,48.1167],"type":"Point"}
}