{
  "id": 2439732,
  "type": "Feature",
  "properties": {
    "tgn:hierarchy":[
        "tgn:2439732",
        "tgn:1000001",
        "tgn:7012149",
        "tgn:2000883",
        "tgn:7007256",
        "tgn:7029392"
    ],
    "tgn:id":2439732,
    "tgn:name":"Kitchen Creek",
    "tgn:placetype":[
        "aat:300008706"
    ]
},
  "bbox": [],
  "geometry": {"coordinates":[-92.25,31.7167],"type":"Point"}
}