{
  "id": 1072520,
  "type": "Feature",
  "properties": {
    "tgn:hierarchy":[
        "tgn:1072520",
        "tgn:1000004",
        "tgn:7002077",
        "tgn:1000111",
        "tgn:7029392"
    ],
    "tgn:id":1072520,
    "tgn:name":"Wanzhuang",
    "tgn:placetype":[
        "aat:300008347"
    ]
},
  "bbox": [],
  "geometry": {"coordinates":[116.5833,39.5667],"type":"Point"}
}