{
  "id": 7167346,
  "type": "Feature",
  "properties": {
    "tgn:hierarchy":[
        "tgn:7167346",
        "tgn:7003669",
        "tgn:1000003",
        "tgn:7000084",
        "tgn:7029392"
    ],
    "tgn:id":7167346,
    "tgn:name":"Haunkenzell",
    "tgn:placetype":[
        "aat:300008347"
    ]
},
  "bbox": [],
  "geometry": {"coordinates":[12.633333,49.033333],"type":"Point"}
}