{
  "id": 7269869,
  "type": "Feature",
  "properties": {
    "tgn:concordances":{
        "gn:id":"2750837"
    },
    "tgn:hierarchy":[
        "tgn:7269869",
        "tgn:7003616",
        "tgn:1000003",
        "tgn:7016845",
        "tgn:7029392"
    ],
    "tgn:id":7269869,
    "tgn:name:nl":"Midlum",
    "tgn:placetype":[
        "aat:300008347"
    ]
},
  "bbox": [],
  "geometry": {"coordinates":[5.45,53.183333],"type":"Point"}
}