{
  "id": 7033176,
  "type": "Feature",
  "properties": {
    "tgn:hierarchy":[
        "tgn:7033176",
        "tgn:1003506",
        "tgn:1000003",
        "tgn:7002993",
        "tgn:1000080",
        "tgn:7029392"
    ],
    "tgn:id":7033176,
    "tgn:name":"San Martino di Terzo",
    "tgn:placetype":[
        "aat:300008347"
    ]
},
  "bbox": [],
  "geometry": {"coordinates":[13.330833,45.798333],"type":"Point"}
}