{
  "id": 2514851,
  "type": "Feature",
  "properties": {
    "tgn:hierarchy":[
        "tgn:2514851",
        "tgn:1000001",
        "tgn:7012149",
        "tgn:1002513",
        "tgn:7007252",
        "tgn:7029392"
    ],
    "tgn:id":2514851,
    "tgn:name":"Miller Pugh Ditch",
    "tgn:placetype":[
        "aat:300006075"
    ]
},
  "bbox": [],
  "geometry": {"coordinates":[-85.1833,40.5333],"type":"Point"}
}