{
  "id": 7279888,
  "type": "Feature",
  "properties": {
    "tgn:hierarchy":[
        "tgn:7279888",
        "tgn:1001695",
        "tgn:1000049",
        "tgn:1000002",
        "tgn:7029392"
    ],
    "tgn:id":7279888,
    "tgn:name":"Rama, Estero",
    "tgn:placetype":[
        "aat:300008699"
    ]
},
  "bbox": [],
  "geometry": {"coordinates":[-70.933333,-34.55],"type":"Point"}
}