{
  "id": 2540838,
  "type": "Feature",
  "properties": {
    "tgn:hierarchy":[
        "tgn:2540838",
        "tgn:1000001",
        "tgn:7012149",
        "tgn:1002520",
        "tgn:7007710",
        "tgn:7029392"
    ],
    "tgn:id":2540838,
    "tgn:name":"Nicely Run",
    "tgn:placetype":[
        "aat:300008699"
    ]
},
  "bbox": [],
  "geometry": {"coordinates":[-79.0667,40.9333],"type":"Point"}
}