{
  "id": 1016396,
  "type": "Feature",
  "properties": {
    "tgn:hierarchy":[
        "tgn:1016396",
        "tgn:1001204",
        "tgn:1000001",
        "tgn:7004624",
        "tgn:7029392"
    ],
    "tgn:id":1016396,
    "tgn:name":"Mor\u00f3n",
    "tgn:placetype":[
        "aat:300008347"
    ]
},
  "bbox": [],
  "geometry": {"coordinates":[-78.65,22.1333],"type":"Point"}
}