{
  "id": 7357618,
  "type": "Feature",
  "properties": {
    "tgn:hierarchy":[
        "tgn:7357618",
        "tgn:1001835",
        "tgn:1000001",
        "tgn:7005560",
        "tgn:7029392"
    ],
    "tgn:id":7357618,
    "tgn:name":"Guanajuato",
    "tgn:placetype":[
        "aat:300008347"
    ]
},
  "bbox": [],
  "geometry": {"coordinates":[-115.337778,32.515833],"type":"Point"}
}