{
  "id": 7437998,
  "type": "Feature",
  "properties": {
    "tgn:hierarchy":[
        "tgn:7437998",
        "tgn:1000001",
        "tgn:7005592",
        "tgn:7005560",
        "tgn:7029392"
    ],
    "tgn:id":7437998,
    "tgn:name":"Tenampulco",
    "tgn:placetype":[
        "aat:300008347"
    ]
},
  "bbox": [],
  "geometry": {"coordinates":[-97.683333,19.733333],"type":"Point"}
}