{
  "id": 7092620,
  "type": "Feature",
  "properties": {
    "tgn:hierarchy":[
        "tgn:7092620",
        "tgn:1000003",
        "tgn:7003682",
        "tgn:7000084",
        "tgn:7029392"
    ],
    "tgn:id":7092620,
    "tgn:name":"Unterkr\u00e4lingen",
    "tgn:placetype":[
        "aat:300008347"
    ]
},
  "bbox": [],
  "geometry": {"coordinates":[6.95,50.533333],"type":"Point"}
}