{
  "id": 2335482,
  "type": "Feature",
  "properties": {
    "tgn:hierarchy":[
        "tgn:2335482",
        "tgn:1000001",
        "tgn:1002665",
        "tgn:7012149",
        "tgn:7007517",
        "tgn:7029392"
    ],
    "tgn:id":2335482,
    "tgn:name":"Fort Pond Brook Reservoir",
    "tgn:placetype":[
        "aat:300006191"
    ]
},
  "bbox": [],
  "geometry": {"coordinates":[-71.45,42.45],"type":"Point"}
}