{
  "id": 1062090,
  "type": "Feature",
  "properties": {
    "tgn:hierarchy":[
        "tgn:1062090",
        "tgn:7001155",
        "tgn:1000003",
        "tgn:7002790",
        "tgn:1000095",
        "tgn:7029392"
    ],
    "tgn:id":1062090,
    "tgn:name":"Irurzun",
    "tgn:placetype":[
        "aat:300008347"
    ]
},
  "bbox": [],
  "geometry": {"coordinates":[-1.833333,42.916667],"type":"Point"}
}