{
  "id": 7192518,
  "type": "Feature",
  "properties": {
    "tgn:hierarchy":[
        "tgn:7192518",
        "tgn:7003669",
        "tgn:1000003",
        "tgn:7000084",
        "tgn:7029392"
    ],
    "tgn:id":7192518,
    "tgn:name":"Fe\u00dfmannsdorf",
    "tgn:placetype":[
        "aat:300008347"
    ]
},
  "bbox": [],
  "geometry": {"coordinates":[12.866667,49.183333],"type":"Point"}
}