{
  "id": 7535413,
  "type": "Feature",
  "properties": {
    "tgn:hierarchy":[
        "tgn:7535413",
        "tgn:7001242",
        "tgn:7016833",
        "tgn:1001079",
        "tgn:7029392"
    ],
    "tgn:id":7535413,
    "tgn:name:en":"Ibn 'As\u012bl, Jaz\u012brat",
    "tgn:placetype":[
        "aat:300008791"
    ]
},
  "bbox": [],
  "geometry": {"coordinates":[30.016667,31.316667],"type":"Point"}
}