{
  "id": 2528266,
  "type": "Feature",
  "properties": {
    "tgn:hierarchy":[
        "tgn:2528266",
        "tgn:1000001",
        "tgn:7012149",
        "tgn:2000352",
        "tgn:7007248",
        "tgn:7029392"
    ],
    "tgn:id":2528266,
    "tgn:name":"Mountaintown",
    "tgn:placetype":[
        "aat:300008347"
    ]
},
  "bbox": [],
  "geometry": {"coordinates":[-84.55,34.75],"type":"Point"}
}