{
  "id": 2573981,
  "type": "Feature",
  "properties": {
    "tgn:hierarchy":[
        "tgn:2573981",
        "tgn:1000001",
        "tgn:7012149",
        "tgn:1002961",
        "tgn:7007568",
        "tgn:7029392"
    ],
    "tgn:id":2573981,
    "tgn:name":"Peekamoose Lake",
    "tgn:placetype":[
        "aat:300008680"
    ]
},
  "bbox": [],
  "geometry": {"coordinates":[-74.3667,41.9167],"type":"Point"}
}