{
  "id": 2417345,
  "type": "Feature",
  "properties": {
    "tgn:hierarchy":[
        "tgn:2417345",
        "tgn:1000001",
        "tgn:7012149",
        "tgn:2000289",
        "tgn:7007240",
        "tgn:7029392"
    ],
    "tgn:id":2417345,
    "tgn:name":"Jacks Island",
    "tgn:placetype":[
        "aat:300008791"
    ]
},
  "bbox": [],
  "geometry": {"coordinates":[-84.3167,30.0333],"type":"Point"}
}