{
  "id": 2644141,
  "type": "Feature",
  "properties": {
    "tgn:hierarchy":[
        "tgn:2644141",
        "tgn:1000001",
        "tgn:7006451",
        "tgn:2000095",
        "tgn:7012149",
        "tgn:7029392"
    ],
    "tgn:id":2644141,
    "tgn:name":"Santa Rosa Mountain",
    "tgn:placetype":[
        "aat:300008798"
    ]
},
  "bbox": [],
  "geometry": {"coordinates":[-109.3833,33.1333],"type":"Point"}
}