{
  "id": 7115281,
  "type": "Feature",
  "properties": {
    "tgn:hierarchy":[
        "tgn:7115281",
        "tgn:1000003",
        "tgn:7003688",
        "tgn:7000084",
        "tgn:7029392"
    ],
    "tgn:id":7115281,
    "tgn:name":"\u00d6sterdeichstrich",
    "tgn:placetype":[
        "aat:300008347"
    ]
},
  "bbox": [],
  "geometry": {"coordinates":[8.883333,54.15],"type":"Point"}
}