{
  "id": 7022786,
  "type": "Feature",
  "properties": {
    "tgn:hierarchy":[
        "tgn:7022786",
        "tgn:1000001",
        "tgn:2000307",
        "tgn:7012149",
        "tgn:7007248",
        "tgn:7029392"
    ],
    "tgn:id":7022786,
    "tgn:name":"De Loach Lower Pond",
    "tgn:placetype":[
        "aat:300006191"
    ]
},
  "bbox": [],
  "geometry": {"coordinates":[-81.7667,32.15],"type":"Point"}
}