{
  "id": 7312480,
  "type": "Feature",
  "properties": {
    "tgn:hierarchy":[
        "tgn:7312480",
        "tgn:1001695",
        "tgn:1000049",
        "tgn:1000002",
        "tgn:7029392"
    ],
    "tgn:id":7312480,
    "tgn:name":"La Placilla",
    "tgn:placetype":[
        "aat:300008347"
    ]
},
  "bbox": [],
  "geometry": {"coordinates":[-70.133333,-34.416667],"type":"Point"}
}