{
  "id": 5000227,
  "type": "Feature",
  "properties": {
    "tgn:hierarchy":[
        "tgn:5000227",
        "tgn:7002445",
        "tgn:1000003",
        "tgn:7008591",
        "tgn:7029392"
    ],
    "tgn:id":5000227,
    "tgn:name:en":"Worcestershire",
    "tgn:placetype":[
        "aat:300387064",
        "aat:300000771"
    ]
},
  "bbox": [],
  "geometry": {"coordinates":[-2.166667,52.166667],"type":"Point"}
}