{
  "id": 2165133,
  "type": "Feature",
  "properties": {
    "tgn:hierarchy":[
        "tgn:2165133",
        "tgn:1000001",
        "tgn:1002410",
        "tgn:7012149",
        "tgn:7007565",
        "tgn:7029392"
    ],
    "tgn:id":2165133,
    "tgn:name":"Bethel Run",
    "tgn:placetype":[
        "aat:300008699"
    ]
},
  "bbox": [],
  "geometry": {"coordinates":[-75.0667,39.75],"type":"Point"}
}