{
  "id": 1083766,
  "type": "Feature",
  "properties": {
    "tgn:hierarchy":[
        "tgn:1083766",
        "tgn:7000360",
        "tgn:1000004",
        "tgn:1000133",
        "tgn:7029392"
    ],
    "tgn:id":1083766,
    "tgn:name":"Samaw\u0101ri",
    "tgn:placetype":[
        "aat:300008347"
    ]
},
  "bbox": [],
  "geometry": {"coordinates":[66.7667,28.5667],"type":"Point"}
}