{
  "id": 2325723,
  "type": "Feature",
  "properties": {
    "tgn:hierarchy":[
        "tgn:2325723",
        "tgn:1000001",
        "tgn:7012149",
        "tgn:2001527",
        "tgn:7007709",
        "tgn:7029392"
    ],
    "tgn:id":2325723,
    "tgn:name":"Field Cove",
    "tgn:placetype":[
        "aat:300132316"
    ]
},
  "bbox": [],
  "geometry": {"coordinates":[-78.0833,34.3667],"type":"Point"}
}