{
  "id": 7410493,
  "type": "Feature",
  "properties": {
    "tgn:hierarchy":[
        "tgn:7410493",
        "tgn:1000001",
        "tgn:7005592",
        "tgn:7005560",
        "tgn:7029392"
    ],
    "tgn:id":7410493,
    "tgn:name":"Tenexate",
    "tgn:placetype":[
        "aat:300008347"
    ]
},
  "bbox": [],
  "geometry": {"coordinates":[-97.373611,20.141667],"type":"Point"}
}