{
  "id": 2512668,
  "type": "Feature",
  "properties": {
    "tgn:hierarchy":[
        "tgn:2512668",
        "tgn:1000001",
        "tgn:7012149",
        "tgn:2000896",
        "tgn:7007256",
        "tgn:7029392"
    ],
    "tgn:id":2512668,
    "tgn:name":"Mill Creek",
    "tgn:placetype":[
        "aat:300008706"
    ]
},
  "bbox": [],
  "geometry": {"coordinates":[-93.35,31.4167],"type":"Point"}
}