{
  "id": 2548312,
  "type": "Feature",
  "properties": {
    "tgn:hierarchy":[
        "tgn:2548312",
        "tgn:1000001",
        "tgn:7012149",
        "tgn:7007520",
        "tgn:7029392"
    ],
    "tgn:id":2548312,
    "tgn:name":"North Lake",
    "tgn:placetype":[
        "aat:300008680"
    ]
},
  "bbox": [],
  "geometry": {"coordinates":[-85.8667,46.5333],"type":"Point"}
}