<<<<<<< HEAD
{
  "id": 7479930,
  "type": "Feature",
  "properties": {
    "tgn:hierarchy":[
        "tgn:7479930",
        "tgn:7468018",
        "tgn:1000004",
        "tgn:1000141",
        "tgn:7029392"
    ],
    "tgn:id":7479930,
    "tgn:name":"Andong Guoxiao",
    "tgn:placetype":[
        "aat:300006495"
    ]
},
  "bbox": [],
  "geometry": {"coordinates":[120.3075,23.458611],"type":"Point"}
}
=======
{"geometry":{"type":"Point","coordinates":[120.307500,23.458611]},"type":"Feature","properties":{"hierarchy":["tgn:7479930","tgn:7468018","tgn:1000004","tgn:1000141","tgn:7029392"],"placetype":["aat:300006495"],"id":7479930,"name:xx":"Andong Guoxiao"}}
>>>>>>> 03f74aca74312dbeaf24d7e61306dd6a786dc3d0
