{
  "id": 7181414,
  "type": "Feature",
  "properties": {
    "tgn:hierarchy":[
        "tgn:7181414",
        "tgn:7003692",
        "tgn:1000003",
        "tgn:7000084",
        "tgn:7029392"
    ],
    "tgn:id":7181414,
    "tgn:name":"Garrweiler",
    "tgn:placetype":[
        "aat:300008347"
    ]
},
  "bbox": [],
  "geometry": {"coordinates":[8.55,48.583333],"type":"Point"}
}