{
  "id": 1042461,
  "type": "Feature",
  "properties": {
    "tgn:hierarchy":[
        "tgn:1042461",
        "tgn:7006350",
        "tgn:1000003",
        "tgn:7006278",
        "tgn:7029392"
    ],
    "tgn:id":1042461,
    "tgn:name":"Sopronk\u00f6vesd",
    "tgn:placetype":[
        "aat:300008347"
    ]
},
  "bbox": [],
  "geometry": {"coordinates":[16.75,47.55],"type":"Point"}
}