{
  "id": 2162729,
  "type": "Feature",
  "properties": {
    "tgn:hierarchy":[
        "tgn:2162729",
        "tgn:1000001",
        "tgn:7012149",
        "tgn:1002899",
        "tgn:7007920",
        "tgn:7029392"
    ],
    "tgn:id":2162729,
    "tgn:name":"Bender Creek",
    "tgn:placetype":[
        "aat:300008706"
    ]
},
  "bbox": [],
  "geometry": {"coordinates":[-121.5667,48.0333],"type":"Point"}
}