<<<<<<< HEAD
{
  "id": 7479922,
  "type": "Feature",
  "properties": {
    "tgn:hierarchy":[
        "tgn:7479922",
        "tgn:1000004",
        "tgn:7490934",
        "tgn:1000141",
        "tgn:7029392"
    ],
    "tgn:id":7479922,
    "tgn:name":"Dongxiu Qiao",
    "tgn:placetype":[
        "aat:300007836"
    ]
},
  "bbox": [],
  "geometry": {"coordinates":[120.331944,23.336111],"type":"Point"}
}
=======
{"geometry":{"type":"Point","coordinates":[120.331944,23.336111]},"type":"Feature","properties":{"hierarchy":["tgn:7479922","tgn:1000004","tgn:7490934","tgn:1000141","tgn:7029392"],"placetype":["aat:300007836"],"id":7479922,"name:xx":"Dongxiu Qiao"}}
>>>>>>> 03f74aca74312dbeaf24d7e61306dd6a786dc3d0
