{
  "id": 7479922,
  "type": "Feature",
  "properties": {
    "tgn:hierarchy":[
        "tgn:7479922",
        "tgn:1000004",
        "tgn:7490934",
        "tgn:1000141",
        "tgn:7029392"
    ],
    "tgn:id":7479922,
    "tgn:name":"Dongxiu Qiao",
    "tgn:placetype":[
        "aat:300007836"
    ]
},
  "bbox": [],
  "geometry": {"coordinates":[120.331944,23.336111],"type":"Point"}
}