{
  "id": 7567470,
  "type": "Feature",
  "properties": {
    "tgn:hierarchy":[
        "tgn:7567470",
        "tgn:1001828",
        "tgn:1000004",
        "tgn:7000198",
        "tgn:7029392"
    ],
    "tgn:id":7567470,
    "tgn:name:en":"Muppireddipalli",
    "tgn:placetype":[
        "aat:300008347"
    ]
},
  "bbox": [],
  "geometry": {"coordinates":[78.491389,17.733056],"type":"Point"}
}