<<<<<<< HEAD
{
  "id": 2258929,
  "type": "Feature",
  "properties": {
    "tgn:hierarchy":[
        "tgn:2258929",
        "tgn:1000001",
        "tgn:7012149",
        "tgn:2001440",
        "tgn:7007566",
        "tgn:7029392"
    ],
    "tgn:id":2258929,
    "tgn:name":"Cottonwood Creek",
    "tgn:placetype":[
        "aat:300008706"
    ]
},
  "bbox": [],
  "geometry": {"coordinates":[-108.7,31.6333],"type":"Point"}
}
=======
{"geometry":{"type":"Point","coordinates":[-108.700000,31.633300]},"type":"Feature","properties":{"hierarchy":["tgn:2258929","tgn:1000001","tgn:7012149","tgn:2001440","tgn:7007566","tgn:7029392"],"placetype":["aat:300008706"],"id":2258929,"name:xx":"Cottonwood Creek"}}
>>>>>>> 03f74aca74312dbeaf24d7e61306dd6a786dc3d0
