{
  "id": 7462933,
  "type": "Feature",
  "properties": {
    "tgn:hierarchy":[
        "tgn:7462933",
        "tgn:7002445",
        "tgn:1000003",
        "tgn:7008168",
        "tgn:7008591",
        "tgn:7029392"
    ],
    "tgn:id":7462933,
    "tgn:name:en":"Lower Assendon",
    "tgn:placetype":[
        "aat:300008347"
    ]
},
  "bbox": [],
  "geometry": {"coordinates":[-0.916667,51.55],"type":"Point"}
}