{
  "id": 2116250,
  "type": "Feature",
  "properties": {
    "tgn:hierarchy":[
        "tgn:2116250",
        "tgn:1000001",
        "tgn:7012149",
        "tgn:2002249",
        "tgn:7007920",
        "tgn:7029392"
    ],
    "tgn:id":2116250,
    "tgn:name":"Marshall",
    "tgn:placetype":[
        "aat:300008347"
    ]
},
  "bbox": [],
  "geometry": {"coordinates":[-117.4833,47.55],"type":"Point"}
}