{
  "id": 7548424,
  "type": "Feature",
  "properties": {
    "tgn:hierarchy":[
        "tgn:7548424",
        "tgn:1001828",
        "tgn:1000004",
        "tgn:7000198",
        "tgn:7029392"
    ],
    "tgn:id":7548424,
    "tgn:name:en":"Chillak\u016br",
    "tgn:placetype":[
        "aat:300008347"
    ]
},
  "bbox": [],
  "geometry": {"coordinates":[79.866667,14.133333],"type":"Point"}
}