{
  "id": 1112973,
  "type": "Feature",
  "properties": {
    "tgn:hierarchy":[
        "tgn:1112973",
        "tgn:1000001",
        "tgn:7012149",
        "tgn:7007157",
        "tgn:1002863",
        "tgn:7029392"
    ],
    "tgn:id":1112973,
    "tgn:name":"Estero Bay",
    "tgn:placetype":[
        "aat:300132316"
    ]
},
  "bbox": [],
  "geometry": {"coordinates":[-120.9167,35.4167],"type":"Point"}
}