{
  "id": 2367664,
  "type": "Feature",
  "properties": {
    "tgn:hierarchy":[
        "tgn:2367664",
        "tgn:1000001",
        "tgn:7012149",
        "tgn:7007920",
        "tgn:7029392"
    ],
    "tgn:id":2367664,
    "tgn:name":"Grouse Ridge",
    "tgn:placetype":[
        "aat:300266640"
    ]
},
  "bbox": [],
  "geometry": {"coordinates":[-117.7667,48.9833],"type":"Point"}
}