<<<<<<< HEAD
{
  "id": 2259266,
  "type": "Feature",
  "properties": {
    "tgn:hierarchy":[
        "tgn:2259266",
        "tgn:1000001",
        "tgn:7006451",
        "tgn:2000094",
        "tgn:7012149",
        "tgn:7029392"
    ],
    "tgn:id":2259266,
    "tgn:name":"Cottonwood Mountain",
    "tgn:placetype":[
        "aat:300008798"
    ]
},
  "bbox": [],
  "geometry": {"coordinates":[-110.1833,32.8667],"type":"Point"}
}
=======
{"geometry":{"type":"Point","coordinates":[-110.183300,32.866700]},"type":"Feature","properties":{"hierarchy":["tgn:2259266","tgn:1000001","tgn:7006451","tgn:2000094","tgn:7012149","tgn:7029392"],"placetype":["aat:300008798"],"id":2259266,"name:xx":"Cottonwood Mountain"}}
>>>>>>> 03f74aca74312dbeaf24d7e61306dd6a786dc3d0
