{
  "id": 2426102,
  "type": "Feature",
  "properties": {
    "tgn:hierarchy":[
        "tgn:2426102",
        "tgn:1000001",
        "tgn:7012149",
        "tgn:1002590",
        "tgn:7007826",
        "tgn:7029392"
    ],
    "tgn:id":2426102,
    "tgn:name":"Jones Branch",
    "tgn:placetype":[
        "aat:300008699"
    ]
},
  "bbox": [],
  "geometry": {"coordinates":[-95.8333,31.15],"type":"Point"}
}