{
  "id": 7510626,
  "type": "Feature",
  "properties": {
    "tgn:hierarchy":[
        "tgn:7510626",
        "tgn:1008380",
        "tgn:7000507",
        "tgn:1000226",
        "tgn:1000006",
        "tgn:7029392"
    ],
    "tgn:id":7510626,
    "tgn:name:en":"Tutukaka Harbour",
    "tgn:placetype":[
        "aat:300008678"
    ]
},
  "bbox": [],
  "geometry": {"coordinates":[174.55,-35.616667],"type":"Point"}
}