{
  "id": 1013539,
  "type": "Feature",
  "properties": {
    "tgn:hierarchy":[
        "tgn:1013539",
        "tgn:7005735",
        "tgn:7005685",
        "tgn:1000001",
        "tgn:7029392"
    ],
    "tgn:id":1013539,
    "tgn:name":"Halfmoon Bay",
    "tgn:placetype":[
        "aat:300008347"
    ]
},
  "bbox": [],
  "geometry": {"coordinates":[-123.9167,49.5167],"type":"Point"}
}