{
  "id": 7432087,
  "type": "Feature",
  "properties": {
    "tgn:hierarchy":[
        "tgn:7432087",
        "tgn:1001853",
        "tgn:1000001",
        "tgn:7005560",
        "tgn:7029392"
    ],
    "tgn:id":7432087,
    "tgn:name":"El Pilar",
    "tgn:placetype":[
        "aat:300008347"
    ]
},
  "bbox": [],
  "geometry": {"coordinates":[-100.916667,29.233333],"type":"Point"}
}