{
  "id": 7457187,
  "type": "Feature",
  "properties": {
    "tgn:hierarchy":[
        "tgn:7457187",
        "tgn:7002445",
        "tgn:1000003",
        "tgn:7008185",
        "tgn:7008591",
        "tgn:7029392"
    ],
    "tgn:id":7457187,
    "tgn:name:en":"North Ship Head",
    "tgn:placetype":[
        "aat:300387036"
    ]
},
  "bbox": [],
  "geometry": {"coordinates":[1.633333,52.016667],"type":"Point"}
}