<<<<<<< HEAD
{
  "id": 7357038,
  "type": "Feature",
  "properties": {
    "tgn:hierarchy":[
        "tgn:7357038",
        "tgn:1000001",
        "tgn:7005589",
        "tgn:7005560",
        "tgn:7029392"
    ],
    "tgn:id":7357038,
    "tgn:name":"Carrizalillo, Sierrita de",
    "tgn:placetype":[
        "aat:300008795"
    ]
},
  "bbox": [],
  "geometry": {"coordinates":[-99.791111,24.2175],"type":"Point"}
}
=======
{"geometry":{"type":"Point","coordinates":[-99.791111,24.217500]},"type":"Feature","properties":{"hierarchy":["tgn:7357038","tgn:1000001","tgn:7005589","tgn:7005560","tgn:7029392"],"placetype":["aat:300008795"],"id":7357038,"name:xx":"Carrizalillo, Sierrita de"}}
>>>>>>> 03f74aca74312dbeaf24d7e61306dd6a786dc3d0
