{
  "id": 7357038,
  "type": "Feature",
  "properties": {
    "tgn:hierarchy":[
        "tgn:7357038",
        "tgn:1000001",
        "tgn:7005589",
        "tgn:7005560",
        "tgn:7029392"
    ],
    "tgn:id":7357038,
    "tgn:name":"Carrizalillo, Sierrita de",
    "tgn:placetype":[
        "aat:300008795"
    ]
},
  "bbox": [],
  "geometry": {"coordinates":[-99.791111,24.2175],"type":"Point"}
}