{
  "id": 7484326,
  "type": "Feature",
  "properties": {
    "tgn:hierarchy":[
        "tgn:7484326",
        "tgn:7487020",
        "tgn:1000004",
        "tgn:1000141",
        "tgn:7029392"
    ],
    "tgn:id":7484326,
    "tgn:name":"Dajia Zhen Diba Gongmu",
    "tgn:placetype":[
        "aat:300266755"
    ]
},
  "bbox": [],
  "geometry": {"coordinates":[120.6375,24.392222],"type":"Point"}
}