{
  "id": 7502696,
  "type": "Feature",
  "properties": {
    "tgn:hierarchy":[
        "tgn:7502696",
        "tgn:7488858",
        "tgn:1000004",
        "tgn:1000141",
        "tgn:7029392"
    ],
    "tgn:id":7502696,
    "tgn:name":"Magu Xi",
    "tgn:placetype":[
        "aat:300008699"
    ]
},
  "bbox": [],
  "geometry": {"coordinates":[121.182778,23.951389],"type":"Point"}
}