{
  "id": 2640433,
  "type": "Feature",
  "properties": {
    "tgn:hierarchy":[
        "tgn:2640433",
        "tgn:1000001",
        "tgn:7012149",
        "tgn:7007158",
        "tgn:2000246",
        "tgn:7029392"
    ],
    "tgn:id":2640433,
    "tgn:name":"San Isabel Lake",
    "tgn:placetype":[
        "aat:300008680"
    ]
},
  "bbox": [],
  "geometry": {"coordinates":[-105.65,38.0667],"type":"Point"}
}