{
  "id": 2560854,
  "type": "Feature",
  "properties": {
    "tgn:hierarchy":[
        "tgn:2560854",
        "tgn:1000001",
        "tgn:2124001",
        "tgn:7012149",
        "tgn:7007516",
        "tgn:7029392"
    ],
    "tgn:id":2560854,
    "tgn:name":"Orme",
    "tgn:placetype":[
        "aat:300008347"
    ]
},
  "bbox": [],
  "geometry": {"coordinates":[-76.75,38.6333],"type":"Point"}
}