{
  "id": 7315060,
  "type": "Feature",
  "properties": {
    "tgn:hierarchy":[
        "tgn:7315060",
        "tgn:1001657",
        "tgn:1000049",
        "tgn:1000002",
        "tgn:7029392"
    ],
    "tgn:id":7315060,
    "tgn:name":"Los Farallones, Islotes",
    "tgn:placetype":[
        "aat:300008791"
    ]
},
  "bbox": [],
  "geometry": {"coordinates":[-71.333333,-29.483333],"type":"Point"}
}