{
  "id": 2005542,
  "type": "Feature",
  "properties": {
    "tgn:hierarchy":[
        "tgn:2005542",
        "tgn:7002659",
        "tgn:1000001",
        "tgn:7012149",
        "tgn:2000049",
        "tgn:7029392"
    ],
    "tgn:id":2005542,
    "tgn:name":"Turkestan",
    "tgn:placetype":[
        "aat:300008347",
        "aat:300387210"
    ]
},
  "bbox": [],
  "geometry": {"coordinates":[-87.15,31.7667],"type":"Point"}
}