{
  "id": 2101906,
  "type": "Feature",
  "properties": {
    "tgn:hierarchy":[
        "tgn:2101906",
        "tgn:1000001",
        "tgn:7012149",
        "tgn:2001922",
        "tgn:7007825",
        "tgn:7029392"
    ],
    "tgn:id":2101906,
    "tgn:name":"Unicoi",
    "tgn:placetype":[
        "aat:300008347"
    ]
},
  "bbox": [],
  "geometry": {"coordinates":[-82.3333,36.1833],"type":"Point"}
}