{
  "id": 7571388,
  "type": "Feature",
  "properties": {
    "tgn:hierarchy":[
        "tgn:7571388",
        "tgn:1000004",
        "tgn:7000198",
        "tgn:7016722",
        "tgn:7029392"
    ],
    "tgn:id":7571388,
    "tgn:name:en":"Girar",
    "tgn:placetype":[
        "aat:300008347"
    ]
},
  "bbox": [],
  "geometry": {"coordinates":[78.922755,24.317714],"type":"Point"}
}