{
  "id": 7505346,
  "type": "Feature",
  "properties": {
    "tgn:hierarchy":[
        "tgn:7505346",
        "tgn:1009227",
        "tgn:7001866",
        "tgn:1000226",
        "tgn:1000006",
        "tgn:7029392"
    ],
    "tgn:id":7505346,
    "tgn:name:en":"Wilmers Stream",
    "tgn:placetype":[
        "aat:300008699"
    ]
},
  "bbox": [],
  "geometry": {"coordinates":[172.683333,-42.416667],"type":"Point"}
}