{
  "id": 2439807,
  "type": "Feature",
  "properties": {
    "tgn:hierarchy":[
        "tgn:2439807",
        "tgn:1000001",
        "tgn:7012149",
        "tgn:7014510",
        "tgn:7007920",
        "tgn:7029392"
    ],
    "tgn:id":2439807,
    "tgn:name":"Kitling Peak",
    "tgn:placetype":[
        "aat:300008798"
    ]
},
  "bbox": [],
  "geometry": {"coordinates":[-120.85,48.5667],"type":"Point"}
}