{
  "id": 2405672,
  "type": "Feature",
  "properties": {
    "tgn:hierarchy":[
        "tgn:2405672",
        "tgn:1000001",
        "tgn:7012149",
        "tgn:2001215",
        "tgn:7007523",
        "tgn:7029392"
    ],
    "tgn:id":2405672,
    "tgn:name":"Hughs Lake",
    "tgn:placetype":[
        "aat:300006191"
    ]
},
  "bbox": [],
  "geometry": {"coordinates":[-93.3333,39.65],"type":"Point"}
}