{
  "id": 7273581,
  "type": "Feature",
  "properties": {
    "tgn:hierarchy":[
        "tgn:7273581",
        "tgn:7003614",
        "tgn:1000003",
        "tgn:7016845",
        "tgn:7029392"
    ],
    "tgn:id":7273581,
    "tgn:name:nl":"Wilhelminahoeve",
    "tgn:placetype":[
        "aat:300000206"
    ]
},
  "bbox": [],
  "geometry": {"coordinates":[6.216667,52.75],"type":"Point"}
}