{
  "id": 2389486,
  "type": "Feature",
  "properties": {
    "tgn:hierarchy":[
        "tgn:2389486",
        "tgn:1000001",
        "tgn:2001411",
        "tgn:7012149",
        "tgn:7007526",
        "tgn:7029392"
    ],
    "tgn:id":2389486,
    "tgn:name":"High Bald Peaks",
    "tgn:placetype":[
        "aat:300008798"
    ]
},
  "bbox": [],
  "geometry": {"coordinates":[-115.1333,40.2333],"type":"Point"}
}