{
  "id": 1011735,
  "type": "Feature",
  "properties": {
    "tgn:hierarchy":[
        "tgn:1011735",
        "tgn:7593485",
        "tgn:7005332",
        "tgn:1000001",
        "tgn:7029392"
    ],
    "tgn:id":1011735,
    "tgn:name":"Cherokee Point",
    "tgn:placetype":[
        "aat:300386846"
    ]
},
  "bbox": [],
  "geometry": {"coordinates":[-77.05,26.45],"type":"Point"}
}