{
  "id": 2363813,
  "type": "Feature",
  "properties": {
    "tgn:hierarchy":[
        "tgn:2363813",
        "tgn:1000001",
        "tgn:7012149",
        "tgn:2001106",
        "tgn:7007522",
        "tgn:7029392"
    ],
    "tgn:id":2363813,
    "tgn:name":"Green Lake",
    "tgn:placetype":[
        "aat:300008680"
    ]
},
  "bbox": [],
  "geometry": {"coordinates":[-88.7833,31.0833],"type":"Point"}
}