{
  "id": 2536824,
  "type": "Feature",
  "properties": {
    "tgn:hierarchy":[
        "tgn:2536824",
        "tgn:1000001",
        "tgn:7012149",
        "tgn:2001722",
        "tgn:7007708",
        "tgn:7029392"
    ],
    "tgn:id":2536824,
    "tgn:name":"Needham Creek",
    "tgn:placetype":[
        "aat:300008706"
    ]
},
  "bbox": [],
  "geometry": {"coordinates":[-116.8833,45.3167],"type":"Point"}
}