{
  "id": 7226262,
  "type": "Feature",
  "properties": {
    "tgn:hierarchy":[
        "tgn:7226262",
        "tgn:7002728",
        "tgn:7002715",
        "tgn:1000003",
        "tgn:1000074",
        "tgn:7029392"
    ],
    "tgn:id":7226262,
    "tgn:name":"Pentapl\u00e1tanon",
    "tgn:placetype":[
        "aat:300008347"
    ]
},
  "bbox": [],
  "geometry": {"coordinates":[22.408611,40.816667],"type":"Point"}
}