{
  "id": 7426684,
  "type": "Feature",
  "properties": {
    "tgn:hierarchy":[
        "tgn:7426684",
        "tgn:7005581",
        "tgn:1000001",
        "tgn:7005560",
        "tgn:7029392"
    ],
    "tgn:id":7426684,
    "tgn:name":"El Colegio",
    "tgn:placetype":[
        "aat:300008347"
    ]
},
  "bbox": [],
  "geometry": {"coordinates":[-108.066667,27.233333],"type":"Point"}
}