{
  "id": 2323730,
  "type": "Feature",
  "properties": {
    "tgn:hierarchy":[
        "tgn:2323730",
        "tgn:1000001",
        "tgn:7012149",
        "tgn:7007255",
        "tgn:7029392"
    ],
    "tgn:id":2323730,
    "tgn:name":"Faubush Creek",
    "tgn:placetype":[
        "aat:300008706"
    ]
},
  "bbox": [],
  "geometry": {"coordinates":[-84.8167,37.05],"type":"Point"}
}