<<<<<<< HEAD
{
  "id": 7178641,
  "type": "Feature",
  "properties": {
    "tgn:hierarchy":[
        "tgn:7178641",
        "tgn:7003669",
        "tgn:1000003",
        "tgn:7000084",
        "tgn:7029392"
    ],
    "tgn:id":7178641,
    "tgn:name":"Hampelhof",
    "tgn:placetype":[
        "aat:300000206"
    ]
},
  "bbox": [],
  "geometry": {"coordinates":[11.716667,50.216667],"type":"Point"}
}
=======
{"geometry":{"type":"Point","coordinates":[11.716667,50.216667]},"type":"Feature","properties":{"hierarchy":["tgn:7178641","tgn:7003669","tgn:1000003","tgn:7000084","tgn:7029392"],"placetype":["aat:300000206"],"id":7178641,"name:xx":"Hampelhof"}}
>>>>>>> 03f74aca74312dbeaf24d7e61306dd6a786dc3d0
