{
  "id": 1107556,
  "type": "Feature",
  "properties": {
    "tgn:hierarchy":[
        "tgn:1107556",
        "tgn:1000001",
        "tgn:7012149",
        "tgn:7007250",
        "tgn:7029392"
    ],
    "tgn:id":1107556,
    "tgn:name":"Snowyside Peak",
    "tgn:placetype":[
        "aat:300008798"
    ]
},
  "bbox": [],
  "geometry": {"coordinates":[-114.9667,43.9333],"type":"Point"}
}