{
  "id": 7417371,
  "type": "Feature",
  "properties": {
    "tgn:hierarchy":[
        "tgn:7417371",
        "tgn:1000001",
        "tgn:7005591",
        "tgn:7005560",
        "tgn:7029392"
    ],
    "tgn:id":7417371,
    "tgn:name:es":"Salado, R\u00edo",
    "tgn:placetype":[
        "aat:300008699"
    ]
},
  "bbox": [],
  "geometry": {"coordinates":[-97.781111,16.483889],"type":"Point"}
}