{
  "id": 2581032,
  "type": "Feature",
  "properties": {
    "tgn:hierarchy":[
        "tgn:2581032",
        "tgn:1000001",
        "tgn:7012149",
        "tgn:7022217",
        "tgn:7007919",
        "tgn:7029392"
    ],
    "tgn:id":2581032,
    "tgn:name":"Pike Point",
    "tgn:placetype":[
        "aat:300008850"
    ]
},
  "bbox": [],
  "geometry": {"coordinates":[-76.4833,36.9167],"type":"Point"}
}