{
  "id": 2296404,
  "type": "Feature",
  "properties": {
    "tgn:hierarchy":[
        "tgn:2296404",
        "tgn:1000001",
        "tgn:2000459",
        "tgn:7012149",
        "tgn:7007250",
        "tgn:7029392"
    ],
    "tgn:id":2296404,
    "tgn:name":"Dry Buck Valley",
    "tgn:placetype":[
        "aat:300008761"
    ]
},
  "bbox": [],
  "geometry": {"coordinates":[-116.15,44.0833],"type":"Point"}
}