<<<<<<< HEAD
{
  "id": 2155903,
  "type": "Feature",
  "properties": {
    "tgn:hierarchy":[
        "tgn:2155903",
        "tgn:1000001",
        "tgn:7012149",
        "tgn:2001437",
        "tgn:7007566",
        "tgn:7029392"
    ],
    "tgn:id":2155903,
    "tgn:name":"Bear Valley",
    "tgn:placetype":[
        "aat:300008761"
    ]
},
  "bbox": [],
  "geometry": {"coordinates":[-108.9,32.95],"type":"Point"}
}
=======
{"geometry":{"type":"Point","coordinates":[-108.900000,32.950000]},"type":"Feature","properties":{"hierarchy":["tgn:2155903","tgn:1000001","tgn:7012149","tgn:2001437","tgn:7007566","tgn:7029392"],"placetype":["aat:300008761"],"id":2155903,"name:xx":"Bear Valley"}}
>>>>>>> 03f74aca74312dbeaf24d7e61306dd6a786dc3d0
