{
  "id": 2319430,
  "type": "Feature",
  "properties": {
    "tgn:hierarchy":[
        "tgn:2319430",
        "tgn:1000001",
        "tgn:7012149",
        "tgn:2002005",
        "tgn:7007826",
        "tgn:7029392"
    ],
    "tgn:id":2319430,
    "tgn:name":"Etholen Tank",
    "tgn:placetype":[
        "aat:300006191"
    ]
},
  "bbox": [],
  "geometry": {"coordinates":[-105.3833,31.1833],"type":"Point"}
}