{
  "id": 1091704,
  "type": "Feature",
  "properties": {
    "tgn:hierarchy":[
        "tgn:1091704",
        "tgn:7001242",
        "tgn:1000940",
        "tgn:1000180",
        "tgn:7029392"
    ],
    "tgn:id":1091704,
    "tgn:name":"Vila Vasco da Gama",
    "tgn:placetype":[
        "aat:300008347"
    ]
},
  "bbox": [],
  "geometry": {"coordinates":[32.2833,-14.9167],"type":"Point"}
}