{
  "id": 2056901,
  "type": "Feature",
  "properties": {
    "tgn:hierarchy":[
        "tgn:2056901",
        "tgn:1000001",
        "tgn:7012149",
        "tgn:2001103",
        "tgn:7007522",
        "tgn:7029392"
    ],
    "tgn:id":2056901,
    "tgn:name":"McLaurin",
    "tgn:placetype":[
        "aat:300008347"
    ]
},
  "bbox": [],
  "geometry": {"coordinates":[-89.2167,31.1667],"type":"Point"}
}