{
  "id": 2171542,
  "type": "Feature",
  "properties": {
    "tgn:hierarchy":[
        "tgn:2171542",
        "tgn:1000001",
        "tgn:7012149",
        "tgn:7007919",
        "tgn:7029392"
    ],
    "tgn:id":2171542,
    "tgn:name":"Big Swamp",
    "tgn:placetype":[
        "aat:300008905"
    ]
},
  "bbox": [],
  "geometry": {"coordinates":[-77.65,37.6333],"type":"Point"}
}