<<<<<<< HEAD
{
  "id": 2761470,
  "type": "Feature",
  "properties": {
    "tgn:hierarchy":[
        "tgn:2761470",
        "tgn:1000001",
        "tgn:7012149",
        "tgn:2002114",
        "tgn:7007827",
        "tgn:7029392"
    ],
    "tgn:id":2761470,
    "tgn:name":"West Neels Reservoir",
    "tgn:placetype":[
        "aat:300006191"
    ]
},
  "bbox": [],
  "geometry": {"coordinates":[-112.8,39.05],"type":"Point"}
}
=======
{"geometry":{"type":"Point","coordinates":[-112.800000,39.050000]},"type":"Feature","properties":{"hierarchy":["tgn:2761470","tgn:1000001","tgn:7012149","tgn:2002114","tgn:7007827","tgn:7029392"],"placetype":["aat:300006191"],"id":2761470,"name:xx":"West Neels Reservoir"}}
>>>>>>> 03f74aca74312dbeaf24d7e61306dd6a786dc3d0
