{
  "id": 2283078,
  "type": "Feature",
  "properties": {
    "tgn:hierarchy":[
        "tgn:2283078",
        "tgn:1000001",
        "tgn:2001416",
        "tgn:7012149",
        "tgn:7007526",
        "tgn:7029392"
    ],
    "tgn:id":2283078,
    "tgn:name":"Delamar Valley",
    "tgn:placetype":[
        "aat:300008761"
    ]
},
  "bbox": [],
  "geometry": {"coordinates":[-114.8667,37.5833],"type":"Point"}
}