<<<<<<< HEAD
{
  "id": 2339723,
  "type": "Feature",
  "properties": {
    "tgn:hierarchy":[
        "tgn:2339723",
        "tgn:1000001",
        "tgn:7012149",
        "tgn:2000227",
        "tgn:7007158",
        "tgn:7029392"
    ],
    "tgn:id":2339723,
    "tgn:name":"Freeburrow Lake",
    "tgn:placetype":[
        "aat:300008680"
    ]
},
  "bbox": [],
  "geometry": {"coordinates":[-104.55,37.4],"type":"Point"}
}
=======
{"geometry":{"type":"Point","coordinates":[-104.550000,37.400000]},"type":"Feature","properties":{"hierarchy":["tgn:2339723","tgn:1000001","tgn:7012149","tgn:2000227","tgn:7007158","tgn:7029392"],"placetype":["aat:300008680"],"id":2339723,"name:xx":"Freeburrow Lake"}}
>>>>>>> 03f74aca74312dbeaf24d7e61306dd6a786dc3d0
