{
  "id": 2585951,
  "type": "Feature",
  "properties": {
    "tgn:hierarchy":[
        "tgn:2585951",
        "tgn:1000001",
        "tgn:2001431",
        "tgn:7012149",
        "tgn:7007566",
        "tgn:7029392"
    ],
    "tgn:id":2585951,
    "tgn:name":"Pipkin Canyon",
    "tgn:placetype":[
        "aat:300008761"
    ]
},
  "bbox": [],
  "geometry": {"coordinates":[-108.35,35.1833],"type":"Point"}
}