{
  "id": 2195169,
  "type": "Feature",
  "properties": {
    "tgn:hierarchy":[
        "tgn:2195169",
        "tgn:7002659",
        "tgn:1000001",
        "tgn:7012149",
        "tgn:2000066",
        "tgn:7029392"
    ],
    "tgn:id":2195169,
    "tgn:name":"Brindley Branch",
    "tgn:placetype":[
        "aat:300008699"
    ]
},
  "bbox": [],
  "geometry": {"coordinates":[-87.25,34.15],"type":"Point"}
}