{
  "id": 7060115,
  "type": "Feature",
  "properties": {
    "tgn:hierarchy":[
        "tgn:7060115",
        "tgn:7003669",
        "tgn:1000003",
        "tgn:7000084",
        "tgn:7029392"
    ],
    "tgn:id":7060115,
    "tgn:name":"Forsthaus Altenhimmel",
    "tgn:placetype":[
        "aat:300004792"
    ]
},
  "bbox": [],
  "geometry": {"coordinates":[11.466667,49.866667],"type":"Point"}
}