{
  "id": 2289187,
  "type": "Feature",
  "properties": {
    "tgn:hierarchy":[
        "tgn:2289187",
        "tgn:1000001",
        "tgn:1002317",
        "tgn:7012149",
        "tgn:7007706",
        "tgn:7029392"
    ],
    "tgn:id":2289187,
    "tgn:name":"Dividing Branch",
    "tgn:placetype":[
        "aat:300008699"
    ]
},
  "bbox": [],
  "geometry": {"coordinates":[-84.6167,39.9833],"type":"Point"}
}