{
  "id": 2641674,
  "type": "Feature",
  "properties": {
    "tgn:hierarchy":[
        "tgn:2641674",
        "tgn:1000001",
        "tgn:7012149",
        "tgn:2000373",
        "tgn:7007248",
        "tgn:7029392"
    ],
    "tgn:id":2641674,
    "tgn:name":"Sand Hill Branch",
    "tgn:placetype":[
        "aat:300008699"
    ]
},
  "bbox": [],
  "geometry": {"coordinates":[-82.0333,32.65],"type":"Point"}
}