{
  "id": 2396271,
  "type": "Feature",
  "properties": {
    "tgn:hierarchy":[
        "tgn:2396271",
        "tgn:7002659",
        "tgn:1000001",
        "tgn:7012149",
        "tgn:2000036",
        "tgn:7029392"
    ],
    "tgn:id":2396271,
    "tgn:name":"Holmes Cave",
    "tgn:placetype":[
        "aat:300008746"
    ]
},
  "bbox": [],
  "geometry": {"coordinates":[-86.55,33.6833],"type":"Point"}
}