{
  "id": 2703385,
  "type": "Feature",
  "properties": {
    "tgn:hierarchy":[
        "tgn:2703385",
        "tgn:1000001",
        "tgn:2002104",
        "tgn:7012149",
        "tgn:7007827",
        "tgn:7029392"
    ],
    "tgn:id":2703385,
    "tgn:name":"Summit Creek",
    "tgn:placetype":[
        "aat:300008706"
    ]
},
  "bbox": [],
  "geometry": {"coordinates":[-110.7167,39.75],"type":"Point"}
}