{
  "id": 7135015,
  "type": "Feature",
  "properties": {
    "tgn:hierarchy":[
        "tgn:7135015",
        "tgn:1000003",
        "tgn:7003682",
        "tgn:7000084",
        "tgn:7029392"
    ],
    "tgn:id":7135015,
    "tgn:name":"M\u00fcden",
    "tgn:placetype":[
        "aat:300008347"
    ]
},
  "bbox": [],
  "geometry": {"coordinates":[7.35,50.183333],"type":"Point"}
}