<<<<<<< HEAD
{
  "id": 7022979,
  "type": "Feature",
  "properties": {
    "tgn:hierarchy":[
        "tgn:7022979",
        "tgn:1000001",
        "tgn:7012149",
        "tgn:7007157",
        "tgn:7029392"
    ],
    "tgn:id":7022979,
    "tgn:name":"French Ravine",
    "tgn:placetype":[
        "aat:300008761"
    ]
},
  "bbox": [],
  "geometry": {"coordinates":[-121.2,39.3333],"type":"Point"}
}
=======
{"geometry":{"type":"Point","coordinates":[-121.200000,39.333300]},"type":"Feature","properties":{"hierarchy":["tgn:7022979","tgn:1000001","tgn:7012149","tgn:7007157","tgn:7029392"],"placetype":["aat:300008761"],"id":7022979,"name:xx":"French Ravine"}}
>>>>>>> 03f74aca74312dbeaf24d7e61306dd6a786dc3d0
