{
  "id": 7586414,
  "type": "Feature",
  "properties": {
    "tgn:hierarchy":[
        "tgn:7586414",
        "tgn:1000004",
        "tgn:7000198",
        "tgn:7000799",
        "tgn:7029392"
    ],
    "tgn:id":7586414,
    "tgn:name:en":"Padargund",
    "tgn:placetype":[
        "aat:300008347"
    ]
},
  "bbox": [],
  "geometry": {"coordinates":[74.152653,34.494121],"type":"Point"}
}