{
  "id": 7413934,
  "type": "Feature",
  "properties": {
    "tgn:hierarchy":[
        "tgn:7413934",
        "tgn:7005580",
        "tgn:1000001",
        "tgn:7005560",
        "tgn:7029392"
    ],
    "tgn:id":7413934,
    "tgn:name":"Albania",
    "tgn:placetype":[
        "aat:300008347"
    ]
},
  "bbox": [],
  "geometry": {"coordinates":[-93.433333,16.605556],"type":"Point"}
}