{
  "id": 7336239,
  "type": "Feature",
  "properties": {
    "tgn:hierarchy":[
        "tgn:7336239",
        "tgn:7002813",
        "tgn:7002758",
        "tgn:1000003",
        "tgn:1000095",
        "tgn:7029392"
    ],
    "tgn:id":7336239,
    "tgn:name":"Fuerticidad, Punta",
    "tgn:placetype":[
        "aat:300386846"
    ]
},
  "bbox": [],
  "geometry": {"coordinates":[-6.266667,36.583333],"type":"Point"}
}