{
  "id": 2615898,
  "type": "Feature",
  "properties": {
    "tgn:hierarchy":[
        "tgn:2615898",
        "tgn:1000001",
        "tgn:7012149",
        "tgn:2001210",
        "tgn:7007523",
        "tgn:7029392"
    ],
    "tgn:id":2615898,
    "tgn:name":"Reynolds Lake",
    "tgn:placetype":[
        "aat:300006191"
    ]
},
  "bbox": [],
  "geometry": {"coordinates":[-93.6667,38.8667],"type":"Point"}
}