{
  "id": 1092941,
  "type": "Feature",
  "properties": {
    "tgn:hierarchy":[
        "tgn:1092941",
        "tgn:7001242",
        "tgn:7017584",
        "tgn:1000193",
        "tgn:7029392"
    ],
    "tgn:id":1092941,
    "tgn:name":"Caledon",
    "tgn:placetype":[
        "aat:300008347"
    ]
},
  "bbox": [],
  "geometry": {"coordinates":[19.4167,-34.2333],"type":"Point"}
}