{
  "id": 2609703,
  "type": "Feature",
  "properties": {
    "tgn:hierarchy":[
        "tgn:2609703",
        "tgn:1000001",
        "tgn:7012149",
        "tgn:2000285",
        "tgn:7007240",
        "tgn:7029392"
    ],
    "tgn:id":2609703,
    "tgn:name":"Reader Creek",
    "tgn:placetype":[
        "aat:300008706"
    ]
},
  "bbox": [],
  "geometry": {"coordinates":[-87.0833,30.6833],"type":"Point"}
}