{
  "id": 7113587,
  "type": "Feature",
  "properties": {
    "tgn:hierarchy":[
        "tgn:7113587",
        "tgn:7003692",
        "tgn:1000003",
        "tgn:7000084",
        "tgn:7029392"
    ],
    "tgn:id":7113587,
    "tgn:name":"R\u00f6schbauer",
    "tgn:placetype":[
        "aat:300000206"
    ]
},
  "bbox": [],
  "geometry": {"coordinates":[7.983333,48.133333],"type":"Point"}
}