<<<<<<< HEAD
{
  "id": 7113587,
  "type": "Feature",
  "properties": {
    "tgn:hierarchy":[
        "tgn:7113587",
        "tgn:7003692",
        "tgn:1000003",
        "tgn:7000084",
        "tgn:7029392"
    ],
    "tgn:id":7113587,
    "tgn:name":"R\u00f6schbauer",
    "tgn:placetype":[
        "aat:300000206"
    ]
},
  "bbox": [],
  "geometry": {"coordinates":[7.983333,48.133333],"type":"Point"}
}
=======
{"geometry":{"type":"Point","coordinates":[7.983333,48.133333]},"type":"Feature","properties":{"hierarchy":["tgn:7113587","tgn:7003692","tgn:1000003","tgn:7000084","tgn:7029392"],"placetype":["aat:300000206"],"id":7113587,"name:xx":"R\u00f6schbauer"}}
>>>>>>> 03f74aca74312dbeaf24d7e61306dd6a786dc3d0
