{
  "id": 2177787,
  "type": "Feature",
  "properties": {
    "tgn:hierarchy":[
        "tgn:2177787",
        "tgn:1000001",
        "tgn:2001424",
        "tgn:7012149",
        "tgn:7007564",
        "tgn:7029392"
    ],
    "tgn:id":2177787,
    "tgn:name":"Black Valley",
    "tgn:placetype":[
        "aat:300008761"
    ]
},
  "bbox": [],
  "geometry": {"coordinates":[-71.9333,44.2667],"type":"Point"}
}