{
  "id": 2287401,
  "type": "Feature",
  "properties": {
    "tgn:hierarchy":[
        "tgn:2287401",
        "tgn:1000001",
        "tgn:2000300",
        "tgn:7012149",
        "tgn:7007248",
        "tgn:7029392"
    ],
    "tgn:id":2287401,
    "tgn:name":"Dicksons Millpond",
    "tgn:placetype":[
        "aat:300006191"
    ]
},
  "bbox": [],
  "geometry": {"coordinates":[-83.1167,31.7333],"type":"Point"}
}