{
  "id": 7252859,
  "type": "Feature",
  "properties": {
    "tgn:hierarchy":[
        "tgn:7252859",
        "tgn:7003458",
        "tgn:1000003",
        "tgn:1000063",
        "tgn:7018236",
        "tgn:7029392"
    ],
    "tgn:id":7252859,
    "tgn:name":"Trapegeer",
    "tgn:placetype":[
        "aat:300387036"
    ]
},
  "bbox": [],
  "geometry": {"coordinates":[2.549577,51.131515],"type":"Point"}
}