{
  "id": 2303838,
  "type": "Feature",
  "properties": {
    "tgn:hierarchy":[
        "tgn:2303838",
        "tgn:1000001",
        "tgn:7012149",
        "tgn:2001277",
        "tgn:7007524",
        "tgn:7029392"
    ],
    "tgn:id":2303838,
    "tgn:name":"Eagle Plume Mountain",
    "tgn:placetype":[
        "aat:300008798"
    ]
},
  "bbox": [],
  "geometry": {"coordinates":[-113.4167,48.55],"type":"Point"}
}