<<<<<<< HEAD
{
  "id": 2769894,
  "type": "Feature",
  "properties": {
    "tgn:hierarchy":[
        "tgn:2769894",
        "tgn:1000001",
        "tgn:7012149",
        "tgn:1002679",
        "tgn:7007520",
        "tgn:7029392"
    ],
    "tgn:id":2769894,
    "tgn:name":"Wilbur Drain",
    "tgn:placetype":[
        "aat:300006075"
    ]
},
  "bbox": [],
  "geometry": {"coordinates":[-83.65,41.8167],"type":"Point"}
}
=======
{"geometry":{"type":"Point","coordinates":[-83.650000,41.816700]},"type":"Feature","properties":{"hierarchy":["tgn:2769894","tgn:1000001","tgn:7012149","tgn:1002679","tgn:7007520","tgn:7029392"],"placetype":["aat:300006075"],"id":2769894,"name:xx":"Wilbur Drain"}}
>>>>>>> 03f74aca74312dbeaf24d7e61306dd6a786dc3d0
