{
  "id": 2476761,
  "type": "Feature",
  "properties": {
    "tgn:hierarchy":[
        "tgn:2476761",
        "tgn:1000001",
        "tgn:7012149",
        "tgn:2002113",
        "tgn:7007827",
        "tgn:7029392"
    ],
    "tgn:id":2476761,
    "tgn:name":"Lydias Canyon",
    "tgn:placetype":[
        "aat:300008761"
    ]
},
  "bbox": [],
  "geometry": {"coordinates":[-112.6333,37.35],"type":"Point"}
}