{
  "id": 2228219,
  "type": "Feature",
  "properties": {
    "tgn:hierarchy":[
        "tgn:2228219",
        "tgn:1000001",
        "tgn:7016172",
        "tgn:2000119",
        "tgn:7012149",
        "tgn:7029392"
    ],
    "tgn:id":2228219,
    "tgn:name":"Cedar Creek",
    "tgn:placetype":[
        "aat:300008347"
    ]
},
  "bbox": [],
  "geometry": {"coordinates":[-92.5333,35.3167],"type":"Point"}
}