{
  "id": 1062701,
  "type": "Feature",
  "properties": {
    "tgn:hierarchy":[
        "tgn:1062701",
        "tgn:1000003",
        "tgn:7003777",
        "tgn:1000097",
        "tgn:7029392"
    ],
    "tgn:id":1062701,
    "tgn:name":"\u00d6stan\u00e5",
    "tgn:placetype":[
        "aat:300008347"
    ]
},
  "bbox": [],
  "geometry": {"coordinates":[18.5833,59.55],"type":"Point"}
}