{
  "id": 7030053,
  "type": "Feature",
  "properties": {
    "tgn:hierarchy":[
        "tgn:7030053",
        "tgn:7019038",
        "tgn:7002445",
        "tgn:1000003",
        "tgn:7029507",
        "tgn:7008591",
        "tgn:7029392"
    ],
    "tgn:id":7030053,
    "tgn:name":"Kiddal Lane End",
    "tgn:placetype":[
        "aat:300008347",
        "aat:300008372"
    ]
},
  "bbox": [],
  "geometry": {"coordinates":[-1.389,53.85],"type":"Point"}
}