{
  "id": 7306348,
  "type": "Feature",
  "properties": {
    "tgn:hierarchy":[
        "tgn:7306348",
        "tgn:7002836",
        "tgn:7016622",
        "tgn:1000003",
        "tgn:1000095",
        "tgn:7029392"
    ],
    "tgn:id":7306348,
    "tgn:name":"Los Abades",
    "tgn:placetype":[
        "aat:300008795"
    ]
},
  "bbox": [],
  "geometry": {"coordinates":[-16.166667,28.533333],"type":"Point"}
}