{
  "id": 7126877,
  "type": "Feature",
  "properties": {
    "tgn:hierarchy":[
        "tgn:7126877",
        "tgn:1000003",
        "tgn:7003682",
        "tgn:7000084",
        "tgn:7029392"
    ],
    "tgn:id":7126877,
    "tgn:name":"Nollen-Bach",
    "tgn:placetype":[
        "aat:300008699"
    ]
},
  "bbox": [],
  "geometry": {"coordinates":[6.75,50.316667],"type":"Point"}
}