{
  "id": 2614421,
  "type": "Feature",
  "properties": {
    "tgn:hierarchy":[
        "tgn:2614421",
        "tgn:1000001",
        "tgn:7012149",
        "tgn:2000410",
        "tgn:7007248",
        "tgn:7029392"
    ],
    "tgn:id":2614421,
    "tgn:name":"Reid Mine",
    "tgn:placetype":[
        "aat:300000390"
    ]
},
  "bbox": [],
  "geometry": {"coordinates":[-83.1667,34.95],"type":"Point"}
}