{
  "id": 7268274,
  "type": "Feature",
  "properties": {
    "tgn:hierarchy":[
        "tgn:7268274",
        "tgn:1000003",
        "tgn:7003632",
        "tgn:7016845",
        "tgn:7029392"
    ],
    "tgn:id":7268274,
    "tgn:name:nl":"Oostvoornse Meer",
    "tgn:placetype":[
        "aat:300006191"
    ]
},
  "bbox": [],
  "geometry": {"coordinates":[4.066667,51.933333],"type":"Point"}
}