{
  "id": 7516533,
  "type": "Feature",
  "properties": {
    "tgn:hierarchy":[
        "tgn:7516533",
        "tgn:7016670",
        "tgn:1008380",
        "tgn:1000226",
        "tgn:1000006",
        "tgn:7029392"
    ],
    "tgn:id":7516533,
    "tgn:name:en":"Mohaka",
    "tgn:placetype":[
        "aat:300007783"
    ]
},
  "bbox": [],
  "geometry": {"coordinates":[177.15,-39.066667],"type":"Point"}
}