<<<<<<< HEAD
{
  "id": 2404762,
  "type": "Feature",
  "properties": {
    "tgn:hierarchy":[
        "tgn:2404762",
        "tgn:1000001",
        "tgn:7012149",
        "tgn:1002758",
        "tgn:7007568",
        "tgn:7029392"
    ],
    "tgn:id":2404762,
    "tgn:name":"Huckleberry Island",
    "tgn:placetype":[
        "aat:300008791"
    ]
},
  "bbox": [],
  "geometry": {"coordinates":[-75.8667,43.5333],"type":"Point"}
}
=======
{"geometry":{"type":"Point","coordinates":[-75.866700,43.533300]},"type":"Feature","properties":{"hierarchy":["tgn:2404762","tgn:1000001","tgn:7012149","tgn:1002758","tgn:7007568","tgn:7029392"],"placetype":["aat:300008791"],"id":2404762,"name:xx":"Huckleberry Island"}}
>>>>>>> 03f74aca74312dbeaf24d7e61306dd6a786dc3d0
