{
  "id": 2744757,
  "type": "Feature",
  "properties": {
    "tgn:hierarchy":[
        "tgn:2744757",
        "tgn:1000001",
        "tgn:2000198",
        "tgn:7012149",
        "tgn:7007158",
        "tgn:7029392"
    ],
    "tgn:id":2744757,
    "tgn:name":"Victoria Mine",
    "tgn:placetype":[
        "aat:300000390"
    ]
},
  "bbox": [],
  "geometry": {"coordinates":[-105.3833,40.05],"type":"Point"}
}