<<<<<<< HEAD
{
  "id": 7379185,
  "type": "Feature",
  "properties": {
    "tgn:hierarchy":[
        "tgn:7379185",
        "tgn:1000001",
        "tgn:7005589",
        "tgn:7005560",
        "tgn:7029392"
    ],
    "tgn:id":7379185,
    "tgn:name":"Los Sabinos",
    "tgn:placetype":[
        "aat:300008347"
    ]
},
  "bbox": [],
  "geometry": {"coordinates":[-99.766667,25.5],"type":"Point"}
}
=======
{"geometry":{"type":"Point","coordinates":[-99.766667,25.500000]},"type":"Feature","properties":{"hierarchy":["tgn:7379185","tgn:1000001","tgn:7005589","tgn:7005560","tgn:7029392"],"placetype":["aat:300008347"],"id":7379185,"name:xx":"Los Sabinos"}}
>>>>>>> 03f74aca74312dbeaf24d7e61306dd6a786dc3d0
