{
  "id": 2515316,
  "type": "Feature",
  "properties": {
    "tgn:hierarchy":[
        "tgn:2515316",
        "tgn:1000001",
        "tgn:7016172",
        "tgn:7012149",
        "tgn:2000177",
        "tgn:7029392"
    ],
    "tgn:id":2515316,
    "tgn:name":"Milliken Lake",
    "tgn:placetype":[
        "aat:300008680"
    ]
},
  "bbox": [],
  "geometry": {"coordinates":[-91.5667,35.1667],"type":"Point"}
}