{
  "id": 2653157,
  "type": "Feature",
  "properties": {
    "tgn:hierarchy":[
        "tgn:2653157",
        "tgn:1000001",
        "tgn:2000864",
        "tgn:7012149",
        "tgn:7007256",
        "tgn:7029392"
    ],
    "tgn:id":2653157,
    "tgn:name":"Seven Runs Crossing",
    "tgn:placetype":[
        "aat:300008347"
    ]
},
  "bbox": [],
  "geometry": {"coordinates":[-92.2667,32.1833],"type":"Point"}
}