{
  "id": 7287395,
  "type": "Feature",
  "properties": {
    "tgn:hierarchy":[
        "tgn:7287395",
        "tgn:1001699",
        "tgn:1000049",
        "tgn:1000002",
        "tgn:7029392"
    ],
    "tgn:id":7287395,
    "tgn:name":"Isla Guacanec",
    "tgn:placetype":[
        "aat:300008791"
    ]
},
  "bbox": [],
  "geometry": {"coordinates":[-73.983333,-43.785],"type":"Point"}
}