{
  "id": 2407892,
  "type": "Feature",
  "properties": {
    "tgn:hierarchy":[
        "tgn:2407892",
        "tgn:1000001",
        "tgn:7016172",
        "tgn:2000121",
        "tgn:7012149",
        "tgn:7029392"
    ],
    "tgn:id":2407892,
    "tgn:name":"Hurricane Creek",
    "tgn:placetype":[
        "aat:300008706"
    ]
},
  "bbox": [],
  "geometry": {"coordinates":[-94.2167,35.65],"type":"Point"}
}