{
  "id": 2607981,
  "type": "Feature",
  "properties": {
    "tgn:hierarchy":[
        "tgn:2607981",
        "tgn:1000001",
        "tgn:7012149",
        "tgn:2000479",
        "tgn:7007250",
        "tgn:7029392"
    ],
    "tgn:id":2607981,
    "tgn:name":"Rathdrum Creek",
    "tgn:placetype":[
        "aat:300008706"
    ]
},
  "bbox": [],
  "geometry": {"coordinates":[-116.85,47.85],"type":"Point"}
}