<<<<<<< HEAD
{
  "id": 2330844,
  "type": "Feature",
  "properties": {
    "tgn:hierarchy":[
        "tgn:2330844",
        "tgn:1000001",
        "tgn:7012149",
        "tgn:2000537",
        "tgn:7007251",
        "tgn:7029392"
    ],
    "tgn:id":2330844,
    "tgn:name":"Flat Pond",
    "tgn:placetype":[
        "aat:300008680"
    ]
},
  "bbox": [],
  "geometry": {"coordinates":[-88.0,38.1],"type":"Point"}
}
=======
{"geometry":{"type":"Point","coordinates":[-88.000000,38.100000]},"type":"Feature","properties":{"hierarchy":["tgn:2330844","tgn:1000001","tgn:7012149","tgn:2000537","tgn:7007251","tgn:7029392"],"placetype":["aat:300008680"],"id":2330844,"name:xx":"Flat Pond"}}
>>>>>>> 03f74aca74312dbeaf24d7e61306dd6a786dc3d0
