{
  "id": 2461231,
  "type": "Feature",
  "properties": {
    "tgn:hierarchy":[
        "tgn:2461231",
        "tgn:1000001",
        "tgn:2001786",
        "tgn:7012149",
        "tgn:7007713",
        "tgn:7029392"
    ],
    "tgn:id":2461231,
    "tgn:name":"Little Squaw Creek",
    "tgn:placetype":[
        "aat:300008706"
    ]
},
  "bbox": [],
  "geometry": {"coordinates":[-103.4667,43.7667],"type":"Point"}
}