{
  "id": 7396923,
  "type": "Feature",
  "properties": {
    "tgn:hierarchy":[
        "tgn:7396923",
        "tgn:7005583",
        "tgn:1000001",
        "tgn:7005560",
        "tgn:7029392"
    ],
    "tgn:id":7396923,
    "tgn:name":"San Rafael de Tejam\u00e9n",
    "tgn:placetype":[
        "aat:300008347"
    ]
},
  "bbox": [],
  "geometry": {"coordinates":[-105.110833,24.806944],"type":"Point"}
}