{
  "id": 7421286,
  "type": "Feature",
  "properties": {
    "tgn:hierarchy":[
        "tgn:7421286",
        "tgn:1001836",
        "tgn:1000001",
        "tgn:7005560",
        "tgn:7029392"
    ],
    "tgn:id":7421286,
    "tgn:name":"El Saucito",
    "tgn:placetype":[
        "aat:300008347"
    ]
},
  "bbox": [],
  "geometry": {"coordinates":[-113.001944,27.532778],"type":"Point"}
}