{
  "id": 2306004,
  "type": "Feature",
  "properties": {
    "tgn:hierarchy":[
        "tgn:2306004",
        "tgn:1000001",
        "tgn:7012149",
        "tgn:1002565",
        "tgn:7007252",
        "tgn:7029392"
    ],
    "tgn:id":2306004,
    "tgn:name":"East Fly Creek",
    "tgn:placetype":[
        "aat:300008706"
    ]
},
  "bbox": [],
  "geometry": {"coordinates":[-85.3167,41.6167],"type":"Point"}
}