<<<<<<< HEAD
{
  "id": 7352382,
  "type": "Feature",
  "properties": {
    "tgn:hierarchy":[
        "tgn:7352382",
        "tgn:1000001",
        "tgn:7005595",
        "tgn:7005560",
        "tgn:7029392"
    ],
    "tgn:id":7352382,
    "tgn:name":"Amapal",
    "tgn:placetype":[
        "aat:300008347"
    ]
},
  "bbox": [],
  "geometry": {"coordinates":[-108.25,25.983333],"type":"Point"}
}
=======
{"geometry":{"type":"Point","coordinates":[-108.250000,25.983333]},"type":"Feature","properties":{"hierarchy":["tgn:7352382","tgn:1000001","tgn:7005595","tgn:7005560","tgn:7029392"],"placetype":["aat:300008347"],"id":7352382,"name:xx":"Amapal"}}
>>>>>>> 03f74aca74312dbeaf24d7e61306dd6a786dc3d0
