{
  "id": 7509507,
  "type": "Feature",
  "properties": {
    "tgn:hierarchy":[
        "tgn:7509507",
        "tgn:1008380",
        "tgn:7000507",
        "tgn:1000226",
        "tgn:1000006",
        "tgn:7029392"
    ],
    "tgn:id":7509507,
    "tgn:name:en":"Waikiekie Station",
    "tgn:placetype":[
        "aat:300007783"
    ]
},
  "bbox": [],
  "geometry": {"coordinates":[174.25,-35.966667],"type":"Point"}
}