{
  "id": 7403056,
  "type": "Feature",
  "properties": {
    "tgn:hierarchy":[
        "tgn:7403056",
        "tgn:1000001",
        "tgn:7005600",
        "tgn:7005560",
        "tgn:7029392"
    ],
    "tgn:id":7403056,
    "tgn:name":"Ximab",
    "tgn:placetype":[
        "aat:300008347"
    ]
},
  "bbox": [],
  "geometry": {"coordinates":[-87.866667,20.758333],"type":"Point"}
}