{
  "id": 2473040,
  "type": "Feature",
  "properties": {
    "tgn:hierarchy":[
        "tgn:2473040",
        "tgn:1000001",
        "tgn:7006451",
        "tgn:2000092",
        "tgn:7012149",
        "tgn:7029392"
    ],
    "tgn:id":2473040,
    "tgn:name":"Low Valley",
    "tgn:placetype":[
        "aat:300386845"
    ]
},
  "bbox": [],
  "geometry": {"coordinates":[-111.2667,36.6333],"type":"Point"}
}