{
  "id": 1092491,
  "type": "Feature",
  "properties": {
    "tgn:hierarchy":[
        "tgn:1092491",
        "tgn:7001242",
        "tgn:1001670",
        "tgn:1000189",
        "tgn:7029392"
    ],
    "tgn:id":1092491,
    "tgn:name":"Dagana",
    "tgn:placetype":[
        "aat:300008347"
    ]
},
  "bbox": [],
  "geometry": {"coordinates":[-15.5833,16.4667],"type":"Point"}
}