{
  "id": 7531358,
  "type": "Feature",
  "properties": {
    "tgn:hierarchy":[
        "tgn:7531358",
        "tgn:7001242",
        "tgn:1001075",
        "tgn:7016833",
        "tgn:7029392"
    ],
    "tgn:id":7531358,
    "tgn:name:en":"A\u1e29mad R\u0101m\u012b",
    "tgn:placetype":[
        "aat:300008347"
    ]
},
  "bbox": [],
  "geometry": {"coordinates":[30.39205,30.732293],"type":"Point"}
}