{
  "id": 2287939,
  "type": "Feature",
  "properties": {
    "tgn:hierarchy":[
        "tgn:2287939",
        "tgn:1000001",
        "tgn:7013368",
        "tgn:7012149",
        "tgn:7007709",
        "tgn:7029392"
    ],
    "tgn:id":2287939,
    "tgn:name":"Dinah Landing",
    "tgn:placetype":[
        "aat:300008347"
    ]
},
  "bbox": [],
  "geometry": {"coordinates":[-76.9167,35.4667],"type":"Point"}
}