{
  "id": 7250916,
  "type": "Feature",
  "properties": {
    "tgn:hierarchy":[
        "tgn:7250916",
        "tgn:7003465",
        "tgn:1000003",
        "tgn:1000063",
        "tgn:4012014",
        "tgn:7029392"
    ],
    "tgn:id":7250916,
    "tgn:name":"Rahet",
    "tgn:placetype":[
        "aat:300008347"
    ]
},
  "bbox": [],
  "geometry": {"coordinates":[5.416667,50.316667],"type":"Point"}
}