{
  "id": 2766082,
  "type": "Feature",
  "properties": {
    "tgn:hierarchy":[
        "tgn:2766082",
        "tgn:1000001",
        "tgn:7006451",
        "tgn:2000092",
        "tgn:7012149",
        "tgn:7029392"
    ],
    "tgn:id":2766082,
    "tgn:name":"White Horse Tank",
    "tgn:placetype":[
        "aat:300006191"
    ]
},
  "bbox": [],
  "geometry": {"coordinates":[-112.3667,35.4667],"type":"Point"}
}