<<<<<<< HEAD
{
  "id": 2766082,
  "type": "Feature",
  "properties": {
    "tgn:hierarchy":[
        "tgn:2766082",
        "tgn:1000001",
        "tgn:7006451",
        "tgn:2000092",
        "tgn:7012149",
        "tgn:7029392"
    ],
    "tgn:id":2766082,
    "tgn:name":"White Horse Tank",
    "tgn:placetype":[
        "aat:300006191"
    ]
},
  "bbox": [],
  "geometry": {"coordinates":[-112.3667,35.4667],"type":"Point"}
}
=======
{"geometry":{"type":"Point","coordinates":[-112.366700,35.466700]},"type":"Feature","properties":{"hierarchy":["tgn:2766082","tgn:1000001","tgn:7006451","tgn:2000092","tgn:7012149","tgn:7029392"],"placetype":["aat:300006191"],"id":2766082,"name:xx":"White Horse Tank"}}
>>>>>>> 03f74aca74312dbeaf24d7e61306dd6a786dc3d0
