{
  "id": 7155468,
  "type": "Feature",
  "properties": {
    "tgn:hierarchy":[
        "tgn:7155468",
        "tgn:7003669",
        "tgn:1000003",
        "tgn:7000084",
        "tgn:7029392"
    ],
    "tgn:id":7155468,
    "tgn:name":"Bahnhof Kirchenlamitz",
    "tgn:placetype":[
        "aat:300007783"
    ]
},
  "bbox": [],
  "geometry": {"coordinates":[11.984167,50.168611],"type":"Point"}
}