{
  "id": 2304935,
  "type": "Feature",
  "properties": {
    "tgn:hierarchy":[
        "tgn:2304935",
        "tgn:1000001",
        "tgn:2001573",
        "tgn:7012149",
        "tgn:7007705",
        "tgn:7029392"
    ],
    "tgn:id":2304935,
    "tgn:name":"East Branch Elk Creek",
    "tgn:placetype":[
        "aat:300008706"
    ]
},
  "bbox": [],
  "geometry": {"coordinates":[-103.8333,47.0167],"type":"Point"}
}