{
  "id": 2437817,
  "type": "Feature",
  "properties": {
    "tgn:hierarchy":[
        "tgn:2437817",
        "tgn:1000001",
        "tgn:7012149",
        "tgn:7007157",
        "tgn:1002956",
        "tgn:7029392"
    ],
    "tgn:id":2437817,
    "tgn:name":"King George Peak",
    "tgn:placetype":[
        "aat:300008798"
    ]
},
  "bbox": [],
  "geometry": {"coordinates":[-118.7333,35.8667],"type":"Point"}
}