<<<<<<< HEAD
{
  "id": 2152483,
  "type": "Feature",
  "properties": {
    "tgn:hierarchy":[
        "tgn:2152483",
        "tgn:1000001",
        "tgn:7012149",
        "tgn:2001420",
        "tgn:7007526",
        "tgn:7029392"
    ],
    "tgn:id":2152483,
    "tgn:name":"Bay State Mine",
    "tgn:placetype":[
        "aat:300000390"
    ]
},
  "bbox": [],
  "geometry": {"coordinates":[-115.7833,39.5333],"type":"Point"}
}
=======
{"geometry":{"type":"Point","coordinates":[-115.783300,39.533300]},"type":"Feature","properties":{"hierarchy":["tgn:2152483","tgn:1000001","tgn:7012149","tgn:2001420","tgn:7007526","tgn:7029392"],"placetype":["aat:300000390"],"id":2152483,"name:xx":"Bay State Mine"}}
>>>>>>> 03f74aca74312dbeaf24d7e61306dd6a786dc3d0
