{
  "id": 2541825,
  "type": "Feature",
  "properties": {
    "tgn:hierarchy":[
        "tgn:2541825",
        "tgn:1000001",
        "tgn:7012149",
        "tgn:2000282",
        "tgn:7007240",
        "tgn:7029392"
    ],
    "tgn:id":2541825,
    "tgn:name":"Ninemile Point",
    "tgn:placetype":[
        "aat:300008850"
    ]
},
  "bbox": [],
  "geometry": {"coordinates":[-81.55,29.7667],"type":"Point"}
}