{
  "id": 7507189,
  "type": "Feature",
  "properties": {
    "tgn:hierarchy":[
        "tgn:7507189",
        "tgn:7000509",
        "tgn:1008380",
        "tgn:1000226",
        "tgn:1000006",
        "tgn:7029392"
    ],
    "tgn:id":7507189,
    "tgn:name:en":"Pupuwharau",
    "tgn:placetype":[
        "aat:300008680"
    ]
},
  "bbox": [],
  "geometry": {"coordinates":[176.766667,-38.083333],"type":"Point"}
}