{
  "id": 7546283,
  "type": "Feature",
  "properties": {
    "tgn:hierarchy":[
        "tgn:7546283",
        "tgn:1000004",
        "tgn:7000198",
        "tgn:7031783",
        "tgn:7029392"
    ],
    "tgn:id":7546283,
    "tgn:name:en":"B\u0101kra",
    "tgn:placetype":[
        "aat:300008347"
    ]
},
  "bbox": [],
  "geometry": {"coordinates":[86.486928,22.481959],"type":"Point"}
}