{
  "id": 1050050,
  "type": "Feature",
  "properties": {
    "tgn:hierarchy":[
        "tgn:1050050",
        "tgn:1000342",
        "tgn:1000003",
        "tgn:1000091",
        "tgn:7029392"
    ],
    "tgn:id":1050050,
    "tgn:name":"Buhu\u0219i",
    "tgn:placetype":[
        "aat:300008347"
    ]
},
  "bbox": [],
  "geometry": {"coordinates":[26.75,46.6833],"type":"Point"}
}