{
  "id": 2656508,
  "type": "Feature",
  "properties": {
    "tgn:hierarchy":[
        "tgn:2656508",
        "tgn:1000001",
        "tgn:7012149",
        "tgn:2001305",
        "tgn:7007524",
        "tgn:7029392"
    ],
    "tgn:id":2656508,
    "tgn:name":"Sheep Camp Coulee",
    "tgn:placetype":[
        "aat:300008761"
    ]
},
  "bbox": [],
  "geometry": {"coordinates":[-104.5667,48.5167],"type":"Point"}
}