{
  "id": 1089562,
  "type": "Feature",
  "properties": {
    "tgn:hierarchy":[
        "tgn:1089562",
        "tgn:7001242",
        "tgn:7016654",
        "tgn:1000159",
        "tgn:7029392"
    ],
    "tgn:id":1089562,
    "tgn:name":"Wendji",
    "tgn:placetype":[
        "aat:300008347"
    ]
},
  "bbox": [],
  "geometry": {"coordinates":[18.1667,-0.0667],"type":"Point"}
}