{
  "id": 2260658,
  "type": "Feature",
  "properties": {
    "tgn:hierarchy":[
        "tgn:2260658",
        "tgn:1000001",
        "tgn:7012149",
        "tgn:2001079",
        "tgn:7007521",
        "tgn:7029392"
    ],
    "tgn:id":2260658,
    "tgn:name":"County Ditch Number Ninteen",
    "tgn:placetype":[
        "aat:300006075"
    ]
},
  "bbox": [],
  "geometry": {"coordinates":[-93.6333,44.0667],"type":"Point"}
}