{
  "id": 7518852,
  "type": "Feature",
  "properties": {
    "tgn:hierarchy":[
        "tgn:7518852",
        "tgn:7000508",
        "tgn:1008380",
        "tgn:1000226",
        "tgn:1000006",
        "tgn:7029392"
    ],
    "tgn:id":7518852,
    "tgn:name:en":"Atiu Island",
    "tgn:placetype":[
        "aat:300008791"
    ]
},
  "bbox": [],
  "geometry": {"coordinates":[175.883333,-36.666667],"type":"Point"}
}