{
  "id": 2385429,
  "type": "Feature",
  "properties": {
    "tgn:hierarchy":[
        "tgn:2385429",
        "tgn:1000001",
        "tgn:1002190",
        "tgn:7012149",
        "tgn:7007523",
        "tgn:7029392"
    ],
    "tgn:id":2385429,
    "tgn:name":"Henderson Branch",
    "tgn:placetype":[
        "aat:300008699"
    ]
},
  "bbox": [],
  "geometry": {"coordinates":[-92.4333,38.9833],"type":"Point"}
}