{
  "id": 2412078,
  "type": "Feature",
  "properties": {
    "tgn:hierarchy":[
        "tgn:2412078",
        "tgn:7002659",
        "tgn:1000001",
        "tgn:7012149",
        "tgn:2000035",
        "tgn:7029392"
    ],
    "tgn:id":2412078,
    "tgn:name":"Indian Rock Cave",
    "tgn:placetype":[
        "aat:300008746"
    ]
},
  "bbox": [],
  "geometry": {"coordinates":[-86.1167,34.7667],"type":"Point"}
}