{
  "id": 2396711,
  "type": "Feature",
  "properties": {
    "tgn:hierarchy":[
        "tgn:2396711",
        "tgn:1000001",
        "tgn:7012149",
        "tgn:2001542",
        "tgn:7007709",
        "tgn:7029392"
    ],
    "tgn:id":2396711,
    "tgn:name":"Holyfield Lake",
    "tgn:placetype":[
        "aat:300006191"
    ]
},
  "bbox": [],
  "geometry": {"coordinates":[-80.7833,36.3667],"type":"Point"}
}