{
  "id": 2651641,
  "type": "Feature",
  "properties": {
    "tgn:hierarchy":[
        "tgn:2651641",
        "tgn:1000001",
        "tgn:1002347",
        "tgn:7012149",
        "tgn:7007568",
        "tgn:7029392"
    ],
    "tgn:id":2651641,
    "tgn:name":"Seeley Hill",
    "tgn:placetype":[
        "aat:300008798"
    ]
},
  "bbox": [],
  "geometry": {"coordinates":[-73.5333,41.5833],"type":"Point"}
}