{
  "id": 7586464,
  "type": "Feature",
  "properties": {
    "tgn:hierarchy":[
        "tgn:7586464",
        "tgn:1000004",
        "tgn:7000198",
        "tgn:7000799",
        "tgn:7029392"
    ],
    "tgn:id":7586464,
    "tgn:name:en":"Sh\u0101labut",
    "tgn:placetype":[
        "aat:300008795"
    ]
},
  "bbox": [],
  "geometry": {"coordinates":[74.3125,34.483333],"type":"Point"}
}