{
  "id": 7576231,
  "type": "Feature",
  "properties": {
    "tgn:hierarchy":[
        "tgn:7576231",
        "tgn:1000004",
        "tgn:7000198",
        "tgn:1001882",
        "tgn:7029392"
    ],
    "tgn:id":7576231,
    "tgn:name:en":"Kh\u0101n\u0101pur",
    "tgn:placetype":[
        "aat:300008347"
    ]
},
  "bbox": [],
  "geometry": {"coordinates":[77.383333,17.933333],"type":"Point"}
}