<<<<<<< HEAD
{
  "id": 7356792,
  "type": "Feature",
  "properties": {
    "tgn:hierarchy":[
        "tgn:7356792",
        "tgn:1000001",
        "tgn:7005591",
        "tgn:7005560",
        "tgn:7029392"
    ],
    "tgn:id":7356792,
    "tgn:name":"Carrillo",
    "tgn:placetype":[
        "aat:300008347"
    ]
},
  "bbox": [],
  "geometry": {"coordinates":[-96.15,17.666667],"type":"Point"}
}
=======
{"geometry":{"type":"Point","coordinates":[-96.150000,17.666667]},"type":"Feature","properties":{"hierarchy":["tgn:7356792","tgn:1000001","tgn:7005591","tgn:7005560","tgn:7029392"],"placetype":["aat:300008347"],"id":7356792,"name:xx":"Carrillo"}}
>>>>>>> 03f74aca74312dbeaf24d7e61306dd6a786dc3d0
