<<<<<<< HEAD
{
  "id": 7111704,
  "type": "Feature",
  "properties": {
    "tgn:hierarchy":[
        "tgn:7111704",
        "tgn:1000003",
        "tgn:7003677",
        "tgn:7000084",
        "tgn:7029392"
    ],
    "tgn:id":7111704,
    "tgn:name":"Richstein",
    "tgn:placetype":[
        "aat:300008347"
    ]
},
  "bbox": [],
  "geometry": {"coordinates":[8.45,50.983333],"type":"Point"}
}
=======
{"geometry":{"type":"Point","coordinates":[8.450000,50.983333]},"type":"Feature","properties":{"hierarchy":["tgn:7111704","tgn:1000003","tgn:7003677","tgn:7000084","tgn:7029392"],"placetype":["aat:300008347"],"id":7111704,"name:xx":"Richstein"}}
>>>>>>> 03f74aca74312dbeaf24d7e61306dd6a786dc3d0
