{
  "id": 7111704,
  "type": "Feature",
  "properties": {
    "tgn:hierarchy":[
        "tgn:7111704",
        "tgn:1000003",
        "tgn:7003677",
        "tgn:7000084",
        "tgn:7029392"
    ],
    "tgn:id":7111704,
    "tgn:name":"Richstein",
    "tgn:placetype":[
        "aat:300008347"
    ]
},
  "bbox": [],
  "geometry": {"coordinates":[8.45,50.983333],"type":"Point"}
}