{
  "id": 1113933,
  "type": "Feature",
  "properties": {
    "tgn:hierarchy":[
        "tgn:1113933",
        "tgn:1000004",
        "tgn:1001449",
        "tgn:1000135",
        "tgn:7029392"
    ],
    "tgn:id":1113933,
    "tgn:name":"Tolong Bay",
    "tgn:placetype":[
        "aat:300132316"
    ]
},
  "bbox": [],
  "geometry": {"coordinates":[122.8167,9.3333],"type":"Point"}
}