{
  "id": 7571767,
  "type": "Feature",
  "properties": {
    "tgn:hierarchy":[
        "tgn:7571767",
        "tgn:1000004",
        "tgn:7000198",
        "tgn:1001895",
        "tgn:7029392"
    ],
    "tgn:id":7571767,
    "tgn:name:en":"K\u0101mtha",
    "tgn:placetype":[
        "aat:300008347"
    ]
},
  "bbox": [],
  "geometry": {"coordinates":[80.307867,21.515617],"type":"Point"}
}