{
  "id": 7163700,
  "type": "Feature",
  "properties": {
    "tgn:hierarchy":[
        "tgn:7163700",
        "tgn:1000003",
        "tgn:7003677",
        "tgn:7000084",
        "tgn:7029392"
    ],
    "tgn:id":7163700,
    "tgn:name":"H\u00fcchelhoven",
    "tgn:placetype":[
        "aat:300008347"
    ]
},
  "bbox": [],
  "geometry": {"coordinates":[6.683333,51.016667],"type":"Point"}
}