{
  "id": 7072462,
  "type": "Feature",
  "properties": {
    "tgn:hierarchy":[
        "tgn:7072462",
        "tgn:7003692",
        "tgn:1000003",
        "tgn:7000084",
        "tgn:7029392"
    ],
    "tgn:id":7072462,
    "tgn:name":"Sulzbacherhof",
    "tgn:placetype":[
        "aat:300000206"
    ]
},
  "bbox": [],
  "geometry": {"coordinates":[8.666667,49.583333],"type":"Point"}
}