{
  "id": 2503964,
  "type": "Feature",
  "properties": {
    "tgn:hierarchy":[
        "tgn:2503964",
        "tgn:1000001",
        "tgn:1002235",
        "tgn:7012149",
        "tgn:7007919",
        "tgn:7029392"
    ],
    "tgn:id":2503964,
    "tgn:name":"Meadow Creek Pond",
    "tgn:placetype":[
        "aat:300008680"
    ]
},
  "bbox": [],
  "geometry": {"coordinates":[-77.3833,38.1333],"type":"Point"}
}