{
  "id": 7521084,
  "type": "Feature",
  "properties": {
    "tgn:hierarchy":[
        "tgn:7521084",
        "tgn:7001242",
        "tgn:7016833",
        "tgn:7000122",
        "tgn:7029392"
    ],
    "tgn:id":7521084,
    "tgn:name:en":"Al M\u0101lik\u012b",
    "tgn:placetype":[
        "aat:300008347"
    ]
},
  "bbox": [],
  "geometry": {"coordinates":[32.383333,22.65],"type":"Point"}
}