{
  "id": 2235034,
  "type": "Feature",
  "properties": {
    "tgn:hierarchy":[
        "tgn:2235034",
        "tgn:1000001",
        "tgn:7012149",
        "tgn:7007248",
        "tgn:7029392"
    ],
    "tgn:id":2235034,
    "tgn:name":"Cherry Log Creek",
    "tgn:placetype":[
        "aat:300008706"
    ]
},
  "bbox": [],
  "geometry": {"coordinates":[-84.3167,34.85],"type":"Point"}
}