{
  "id": 2501432,
  "type": "Feature",
  "properties": {
    "tgn:hierarchy":[
        "tgn:2501432",
        "tgn:1000001",
        "tgn:7012149",
        "tgn:2000436",
        "tgn:7007248",
        "tgn:7029392"
    ],
    "tgn:id":2501432,
    "tgn:name":"McGraw Mountain",
    "tgn:placetype":[
        "aat:300008798"
    ]
},
  "bbox": [],
  "geometry": {"coordinates":[-84.4333,32.9333],"type":"Point"}
}