{
  "id": 7372563,
  "type": "Feature",
  "properties": {
    "tgn:hierarchy":[
        "tgn:7372563",
        "tgn:1001853",
        "tgn:1000001",
        "tgn:7005560",
        "tgn:7029392"
    ],
    "tgn:id":7372563,
    "tgn:name":"Rancho Lantrisco",
    "tgn:placetype":[
        "aat:300000241"
    ]
},
  "bbox": [],
  "geometry": {"coordinates":[-100.85,25.816667],"type":"Point"}
}