{
  "id": 2248114,
  "type": "Feature",
  "properties": {
    "tgn:hierarchy":[
        "tgn:2248114",
        "tgn:1000001",
        "tgn:7012149",
        "tgn:1002920",
        "tgn:7007568",
        "tgn:7029392"
    ],
    "tgn:id":2248114,
    "tgn:name":"Cold Brook",
    "tgn:placetype":[
        "aat:300008699"
    ]
},
  "bbox": [],
  "geometry": {"coordinates":[-77.3167,42.3667],"type":"Point"}
}