{
  "id": 2203249,
  "type": "Feature",
  "properties": {
    "tgn:hierarchy":[
        "tgn:2203249",
        "tgn:1000001",
        "tgn:2002369",
        "tgn:7012149",
        "tgn:7007923",
        "tgn:7029392"
    ],
    "tgn:id":2203249,
    "tgn:name":"Buckhorn Creek",
    "tgn:placetype":[
        "aat:300008706"
    ]
},
  "bbox": [],
  "geometry": {"coordinates":[-105.75,42.4833],"type":"Point"}
}