{
  "id": 7229502,
  "type": "Feature",
  "properties": {
    "tgn:hierarchy":[
        "tgn:7229502",
        "tgn:7002735",
        "tgn:7017076",
        "tgn:1000003",
        "tgn:1000074",
        "tgn:7029392"
    ],
    "tgn:id":7229502,
    "tgn:name":"Karatz\u00e1s",
    "tgn:placetype":[
        "aat:300008795"
    ]
},
  "bbox": [],
  "geometry": {"coordinates":[22.933333,37.083333],"type":"Point"}
}