{
  "id": 2738047,
  "type": "Feature",
  "properties": {
    "tgn:hierarchy":[
        "tgn:2738047",
        "tgn:1000001",
        "tgn:7006451",
        "tgn:7012149",
        "tgn:2000100",
        "tgn:7029392"
    ],
    "tgn:id":2738047,
    "tgn:name":"Uhs Kug",
    "tgn:placetype":[
        "aat:300008347"
    ]
},
  "bbox": [],
  "geometry": {"coordinates":[-111.55,31.95],"type":"Point"}
}