{
  "id": 2522385,
  "type": "Feature",
  "properties": {
    "tgn:hierarchy":[
        "tgn:2522385",
        "tgn:1000001",
        "tgn:7012149",
        "tgn:2001312",
        "tgn:7007524",
        "tgn:7029392"
    ],
    "tgn:id":2522385,
    "tgn:name":"Mooney Coulee",
    "tgn:placetype":[
        "aat:300008761"
    ]
},
  "bbox": [],
  "geometry": {"coordinates":[-106.6667,48.4167],"type":"Point"}
}