{
  "id": 2662853,
  "type": "Feature",
  "properties": {
    "tgn:hierarchy":[
        "tgn:2662853",
        "tgn:1000001",
        "tgn:7012149",
        "tgn:1003008",
        "tgn:7007710",
        "tgn:7029392"
    ],
    "tgn:id":2662853,
    "tgn:name":"Silkmans Swamp",
    "tgn:placetype":[
        "aat:300008905"
    ]
},
  "bbox": [],
  "geometry": {"coordinates":[-75.4167,41.4333],"type":"Point"}
}