{
  "id": 1071486,
  "type": "Feature",
  "properties": {
    "tgn:hierarchy":[
        "tgn:1071486",
        "tgn:1000004",
        "tgn:7016672",
        "tgn:1000111",
        "tgn:7029392"
    ],
    "tgn:id":1071486,
    "tgn:name":"Shangqiu",
    "tgn:placetype":[
        "aat:300008347"
    ]
},
  "bbox": [],
  "geometry": {"coordinates":[115.6167,34.3833],"type":"Point"}
}