{
  "id": 4002912,
  "type": "Feature",
  "properties": {
    "tgn:hierarchy":[
        "tgn:4002912",
        "tgn:1000003",
        "tgn:7003751",
        "tgn:7011731",
        "tgn:7029392"
    ],
    "tgn:id":4002912,
    "tgn:name":"Cortaillod",
    "tgn:placetype":[
        "aat:300008347"
    ]
},
  "bbox": [],
  "geometry": {"coordinates":[6.8667,46.95],"type":"Point"}
}