{
  "id": 7262742,
  "type": "Feature",
  "properties": {
    "tgn:hierarchy":[
        "tgn:7262742",
        "tgn:7003619",
        "tgn:1000003",
        "tgn:7016845",
        "tgn:7029392"
    ],
    "tgn:id":7262742,
    "tgn:name:nl":"Cabenterbrug",
    "tgn:placetype":[
        "aat:300007836"
    ]
},
  "bbox": [],
  "geometry": {"coordinates":[6.116667,52.033333],"type":"Point"}
}