<<<<<<< HEAD
{
  "id": 2255052,
  "type": "Feature",
  "properties": {
    "tgn:hierarchy":[
        "tgn:2255052",
        "tgn:1000001",
        "tgn:7012149",
        "tgn:1002794",
        "tgn:7007708",
        "tgn:7029392"
    ],
    "tgn:id":2255052,
    "tgn:name":"Cooper Creek",
    "tgn:placetype":[
        "aat:300008706"
    ]
},
  "bbox": [],
  "geometry": {"coordinates":[-123.3,44.8667],"type":"Point"}
}
=======
{"geometry":{"type":"Point","coordinates":[-123.300000,44.866700]},"type":"Feature","properties":{"hierarchy":["tgn:2255052","tgn:1000001","tgn:7012149","tgn:1002794","tgn:7007708","tgn:7029392"],"placetype":["aat:300008706"],"id":2255052,"name:xx":"Cooper Creek"}}
>>>>>>> 03f74aca74312dbeaf24d7e61306dd6a786dc3d0
