{
  "id": 7475779,
  "type": "Feature",
  "properties": {
    "tgn:hierarchy":[
        "tgn:7475779",
        "tgn:1000004",
        "tgn:7489179",
        "tgn:1000141",
        "tgn:7029392"
    ],
    "tgn:id":7475779,
    "tgn:name":"Fenniaolin Yugang",
    "tgn:placetype":[
        "aat:300008678"
    ]
},
  "bbox": [],
  "geometry": {"coordinates":[121.843206,24.497719],"type":"Point"}
}