{
  "id": 2501702,
  "type": "Feature",
  "properties": {
    "tgn:hierarchy":[
        "tgn:2501702",
        "tgn:1000001",
        "tgn:2000772",
        "tgn:7012149",
        "tgn:7007255",
        "tgn:7029392"
    ],
    "tgn:id":2501702,
    "tgn:name":"McIntosh Fork",
    "tgn:placetype":[
        "aat:300008699"
    ]
},
  "bbox": [],
  "geometry": {"coordinates":[-83.5667,37.4667],"type":"Point"}
}