{
  "id": 1053149,
  "type": "Feature",
  "properties": {
    "tgn:hierarchy":[
        "tgn:1053149",
        "tgn:1000004",
        "tgn:7014474",
        "tgn:7018214",
        "tgn:7002435",
        "tgn:7029392"
    ],
    "tgn:id":1053149,
    "tgn:name":"Bulava",
    "tgn:placetype":[
        "aat:300008347"
    ]
},
  "bbox": [],
  "geometry": {"coordinates":[140.4167,51.9167],"type":"Point"}
}