{
  "id": 2486747,
  "type": "Feature",
  "properties": {
    "tgn:hierarchy":[
        "tgn:2486747",
        "tgn:1000001",
        "tgn:7012149",
        "tgn:2000340",
        "tgn:7007248",
        "tgn:7029392"
    ],
    "tgn:id":2486747,
    "tgn:name":"Lee Branch",
    "tgn:placetype":[
        "aat:300008699"
    ]
},
  "bbox": [],
  "geometry": {"coordinates":[-84.8333,31.4833],"type":"Point"}
}