{
  "id": 7529916,
  "type": "Feature",
  "properties": {
    "tgn:hierarchy":[
        "tgn:7529916",
        "tgn:7001242",
        "tgn:7016833",
        "tgn:7001335",
        "tgn:7029392"
    ],
    "tgn:id":7529916,
    "tgn:name":"Ham\u00eera, W\u00e2di",
    "tgn:placetype":[
        "aat:300379998"
    ]
},
  "bbox": [],
  "geometry": {"coordinates":[34.302778,30.351111],"type":"Point"}
}