{
  "id": 7498408,
  "type": "Feature",
  "properties": {
    "tgn:hierarchy":[
        "tgn:7498408",
        "tgn:1000004",
        "tgn:7492971",
        "tgn:1000141",
        "tgn:7029392"
    ],
    "tgn:id":7498408,
    "tgn:name":"Wanzishou Qiao",
    "tgn:placetype":[
        "aat:300007836"
    ]
},
  "bbox": [],
  "geometry": {"coordinates":[120.626595,22.846472],"type":"Point"}
}