<<<<<<< HEAD
{
  "id": 7021924,
  "type": "Feature",
  "properties": {
    "tgn:hierarchy":[
        "tgn:7021924",
        "tgn:2002142",
        "tgn:1000001",
        "tgn:7012149",
        "tgn:7007919",
        "tgn:7029392"
    ],
    "tgn:id":7021924,
    "tgn:name":"Miller Knob",
    "tgn:placetype":[
        "aat:300008798"
    ]
},
  "bbox": [],
  "geometry": {"coordinates":[-78.9,38.0333],"type":"Point"}
}
=======
{"geometry":{"type":"Point","coordinates":[-78.900000,38.033300]},"type":"Feature","properties":{"hierarchy":["tgn:7021924","tgn:2002142","tgn:1000001","tgn:7012149","tgn:7007919","tgn:7029392"],"placetype":["aat:300008798"],"id":7021924,"name:xx":"Miller Knob"}}
>>>>>>> 03f74aca74312dbeaf24d7e61306dd6a786dc3d0
