{
  "id": 2628267,
  "type": "Feature",
  "properties": {
    "tgn:hierarchy":[
        "tgn:2628267",
        "tgn:1000001",
        "tgn:7012149",
        "tgn:2001916",
        "tgn:7007825",
        "tgn:7029392"
    ],
    "tgn:id":2628267,
    "tgn:name":"Rome Island",
    "tgn:placetype":[
        "aat:300008791"
    ]
},
  "bbox": [],
  "geometry": {"coordinates":[-86.0833,36.2667],"type":"Point"}
}