{
  "id": 2421980,
  "type": "Feature",
  "properties": {
    "tgn:hierarchy":[
        "tgn:2421980",
        "tgn:1000001",
        "tgn:7012149",
        "tgn:7007253",
        "tgn:7029392"
    ],
    "tgn:id":2421980,
    "tgn:name":"Jim Creek",
    "tgn:placetype":[
        "aat:300008706"
    ]
},
  "bbox": [],
  "geometry": {"coordinates":[-94.1667,41.9667],"type":"Point"}
}