{
  "id": 2572776,
  "type": "Feature",
  "properties": {
    "tgn:hierarchy":[
        "tgn:2572776",
        "tgn:1000001",
        "tgn:7012149",
        "tgn:2000972",
        "tgn:7007520",
        "tgn:7029392"
    ],
    "tgn:id":2572776,
    "tgn:name":"Peanut Lake",
    "tgn:placetype":[
        "aat:300008680"
    ]
},
  "bbox": [],
  "geometry": {"coordinates":[-85.7167,46.4333],"type":"Point"}
}