{
  "id": 7469596,
  "type": "Feature",
  "properties": {
    "tgn:hierarchy":[
        "tgn:7469596",
        "tgn:7001004",
        "tgn:1000004",
        "tgn:1000141",
        "tgn:7029392"
    ],
    "tgn:id":7469596,
    "tgn:name":"Zhongliao",
    "tgn:placetype":[
        "aat:300008347"
    ]
},
  "bbox": [],
  "geometry": {"coordinates":[120.224167,22.858056],"type":"Point"}
}