{
  "id": 7280477,
  "type": "Feature",
  "properties": {
    "tgn:hierarchy":[
        "tgn:7280477",
        "tgn:7016598",
        "tgn:1000049",
        "tgn:1000002",
        "tgn:7029392"
    ],
    "tgn:id":7280477,
    "tgn:name":"San Juan",
    "tgn:placetype":[
        "aat:300008347"
    ]
},
  "bbox": [],
  "geometry": {"coordinates":[-69.816667,-25.466667],"type":"Point"}
}