{
  "id": 7343872,
  "type": "Feature",
  "properties": {
    "tgn:hierarchy":[
        "tgn:7343872",
        "tgn:7001155",
        "tgn:1000003",
        "tgn:7002790",
        "tgn:1000095",
        "tgn:7029392"
    ],
    "tgn:id":7343872,
    "tgn:name":"Cabredo",
    "tgn:placetype":[
        "aat:300008347"
    ]
},
  "bbox": [],
  "geometry": {"coordinates":[-2.412575,42.629348],"type":"Point"}
}