{
  "id": 7257678,
  "type": "Feature",
  "properties": {
    "tgn:concordances":{
        "gn:id":"2758742"
    },
    "tgn:hierarchy":[
        "tgn:7257678",
        "tgn:1000003",
        "tgn:7003624",
        "tgn:7016845",
        "tgn:7029392"
    ],
    "tgn:id":7257678,
    "tgn:name:nl":"Boerdonk",
    "tgn:placetype":[
        "aat:300008347"
    ]
},
  "bbox": [],
  "geometry": {"coordinates":[5.633333,51.566667],"type":"Point"}
}