{
  "id": 7341150,
  "type": "Feature",
  "properties": {
    "tgn:hierarchy":[
        "tgn:7341150",
        "tgn:7002810",
        "tgn:7001158",
        "tgn:1000003",
        "tgn:1000095",
        "tgn:7029392"
    ],
    "tgn:id":7341150,
    "tgn:name":"Brull\u00e9s",
    "tgn:placetype":[
        "aat:300008347"
    ]
},
  "bbox": [],
  "geometry": {"coordinates":[-3.916667,42.566667],"type":"Point"}
}