{
  "id": 2504806,
  "type": "Feature",
  "properties": {
    "tgn:hierarchy":[
        "tgn:2504806",
        "tgn:1000001",
        "tgn:7012149",
        "tgn:2001686",
        "tgn:7007707",
        "tgn:7029392"
    ],
    "tgn:id":2504806,
    "tgn:name":"Medicine Springs",
    "tgn:placetype":[
        "aat:300008697"
    ]
},
  "bbox": [],
  "geometry": {"coordinates":[-95.3833,34.3167],"type":"Point"}
}