<<<<<<< HEAD
{
  "id": 2762974,
  "type": "Feature",
  "properties": {
    "tgn:hierarchy":[
        "tgn:2762974",
        "tgn:1000001",
        "tgn:7012149",
        "tgn:2001272",
        "tgn:7007524",
        "tgn:7029392"
    ],
    "tgn:id":2762974,
    "tgn:name":"Westmore",
    "tgn:placetype":[
        "aat:300008347"
    ]
},
  "bbox": [],
  "geometry": {"coordinates":[-104.6333,46.4667],"type":"Point"}
}
=======
{"geometry":{"type":"Point","coordinates":[-104.633300,46.466700]},"type":"Feature","properties":{"hierarchy":["tgn:2762974","tgn:1000001","tgn:7012149","tgn:2001272","tgn:7007524","tgn:7029392"],"placetype":["aat:300008347"],"id":2762974,"name:xx":"Westmore"}}
>>>>>>> 03f74aca74312dbeaf24d7e61306dd6a786dc3d0
