{
  "id": 2071865,
  "type": "Feature",
  "properties": {
    "tgn:hierarchy":[
        "tgn:2071865",
        "tgn:1000001",
        "tgn:1002347",
        "tgn:7012149",
        "tgn:7007568",
        "tgn:7029392"
    ],
    "tgn:id":2071865,
    "tgn:name":"Red Hook",
    "tgn:placetype":[
        "aat:300008347"
    ]
},
  "bbox": [],
  "geometry": {"coordinates":[-73.8667,41.9833],"type":"Point"}
}