{
  "id": 7226846,
  "type": "Feature",
  "properties": {
    "tgn:hierarchy":[
        "tgn:7226846",
        "tgn:7002739",
        "tgn:7017076",
        "tgn:1000003",
        "tgn:1000074",
        "tgn:7029392"
    ],
    "tgn:id":7226846,
    "tgn:name":"Sko\u00fafia",
    "tgn:placetype":[
        "aat:300008795"
    ]
},
  "bbox": [],
  "geometry": {"coordinates":[22.816667,37.266667],"type":"Point"}
}