{
  "id": 2343887,
  "type": "Feature",
  "properties": {
    "tgn:hierarchy":[
        "tgn:2343887",
        "tgn:1000001",
        "tgn:7012149",
        "tgn:1003020",
        "tgn:7007920",
        "tgn:7029392"
    ],
    "tgn:id":2343887,
    "tgn:name":"Gallop Creek",
    "tgn:placetype":[
        "aat:300008706"
    ]
},
  "bbox": [],
  "geometry": {"coordinates":[-121.95,48.8333],"type":"Point"}
}