{
  "id": 7562236,
  "type": "Feature",
  "properties": {
    "tgn:hierarchy":[
        "tgn:7562236",
        "tgn:1000004",
        "tgn:7000198",
        "tgn:7016722",
        "tgn:7029392"
    ],
    "tgn:id":7562236,
    "tgn:name:en":"Harn\u0101garpur",
    "tgn:placetype":[
        "aat:300008347"
    ]
},
  "bbox": [],
  "geometry": {"coordinates":[79.250104,27.040873],"type":"Point"}
}