{
  "id": 1089846,
  "type": "Feature",
  "properties": {
    "tgn:hierarchy":[
        "tgn:1089846",
        "tgn:7001242",
        "tgn:1001570",
        "tgn:7000489",
        "tgn:7029392"
    ],
    "tgn:id":1089846,
    "tgn:name":"Hawz\u0113n",
    "tgn:placetype":[
        "aat:300008347"
    ]
},
  "bbox": [],
  "geometry": {"coordinates":[39.4333,13.9667],"type":"Point"}
}