{
  "id": 2327024,
  "type": "Feature",
  "properties": {
    "tgn:hierarchy":[
        "tgn:2327024",
        "tgn:1000001",
        "tgn:7012149",
        "tgn:2001556",
        "tgn:7007709",
        "tgn:7029392"
    ],
    "tgn:id":2327024,
    "tgn:name":"Firescald Mountain",
    "tgn:placetype":[
        "aat:300008798"
    ]
},
  "bbox": [],
  "geometry": {"coordinates":[-82.45,35.95],"type":"Point"}
}