{
  "id": 1135784,
  "type": "Feature",
  "properties": {
    "tgn:hierarchy":[
        "tgn:1135784",
        "tgn:1000004",
        "tgn:7000190",
        "tgn:1000105",
        "tgn:7029392"
    ],
    "tgn:id":1135784,
    "tgn:name":"M\u0101lancha",
    "tgn:placetype":[
        "aat:300387055"
    ]
},
  "bbox": [],
  "geometry": {"coordinates":[89.3333,21.6667],"type":"Point"}
}