{
  "id": 7391587,
  "type": "Feature",
  "properties": {
    "tgn:hierarchy":[
        "tgn:7391587",
        "tgn:7005583",
        "tgn:1000001",
        "tgn:7005560",
        "tgn:7029392"
    ],
    "tgn:id":7391587,
    "tgn:name":"Rancho Las Esperanzas",
    "tgn:placetype":[
        "aat:300008347"
    ]
},
  "bbox": [],
  "geometry": {"coordinates":[-103.983333,26.45],"type":"Point"}
}