{
  "id": 2625503,
  "type": "Feature",
  "properties": {
    "tgn:hierarchy":[
        "tgn:2625503",
        "tgn:1000001",
        "tgn:7012149",
        "tgn:2002162",
        "tgn:7007919",
        "tgn:7029392"
    ],
    "tgn:id":2625503,
    "tgn:name":"Rocks Sink School Cave",
    "tgn:placetype":[
        "aat:300008746"
    ]
},
  "bbox": [],
  "geometry": {"coordinates":[-80.5167,37.3167],"type":"Point"}
}