{
  "id": 1104801,
  "type": "Feature",
  "properties": {
    "tgn:hierarchy":[
        "tgn:1104801",
        "tgn:7002075",
        "tgn:1000004",
        "tgn:1000111",
        "tgn:7029392"
    ],
    "tgn:id":1104801,
    "tgn:name":"Guangming Ding",
    "tgn:placetype":[
        "aat:300008795"
    ]
},
  "bbox": [],
  "geometry": {"coordinates":[118.0667,30.0833],"type":"Point"}
}