{
  "id": 1087131,
  "type": "Feature",
  "properties": {
    "tgn:hierarchy":[
        "tgn:1087131",
        "tgn:1000004",
        "tgn:7001056",
        "tgn:1000145",
        "tgn:7029392"
    ],
    "tgn:id":1087131,
    "tgn:name":"H\u1eadu \u0110\u00fac",
    "tgn:placetype":[
        "aat:300008347"
    ]
},
  "bbox": [],
  "geometry": {"coordinates":[108.2167,15.3333],"type":"Point"}
}