{
  "id": 2176540,
  "type": "Feature",
  "properties": {
    "tgn:hierarchy":[
        "tgn:2176540",
        "tgn:1000001",
        "tgn:7012149",
        "tgn:2001060",
        "tgn:7007521",
        "tgn:7029392"
    ],
    "tgn:id":2176540,
    "tgn:name":"Black Lake",
    "tgn:placetype":[
        "aat:300008680"
    ]
},
  "bbox": [],
  "geometry": {"coordinates":[-93.0667,45.0833],"type":"Point"}
}