{
  "id": 7417595,
  "type": "Feature",
  "properties": {
    "tgn:hierarchy":[
        "tgn:7417595",
        "tgn:1000001",
        "tgn:7005591",
        "tgn:7005560",
        "tgn:7029392"
    ],
    "tgn:id":7417595,
    "tgn:name:es":"Banderillas, Cerro",
    "tgn:placetype":[
        "aat:300008795"
    ]
},
  "bbox": [],
  "geometry": {"coordinates":[-95.294444,16.938056],"type":"Point"}
}