{
  "id": 2316472,
  "type": "Feature",
  "properties": {
    "tgn:hierarchy":[
        "tgn:2316472",
        "tgn:1000001",
        "tgn:7012149",
        "tgn:1002612",
        "tgn:7007710",
        "tgn:7029392"
    ],
    "tgn:id":2316472,
    "tgn:name":"Elstons Pond",
    "tgn:placetype":[
        "aat:300006191"
    ]
},
  "bbox": [],
  "geometry": {"coordinates":[-75.9667,41.3667],"type":"Point"}
}