{
  "id": 2384909,
  "type": "Feature",
  "properties": {
    "tgn:hierarchy":[
        "tgn:2384909",
        "tgn:1000001",
        "tgn:7012149",
        "tgn:2001879",
        "tgn:7007825",
        "tgn:7029392"
    ],
    "tgn:id":2384909,
    "tgn:name":"Hellsneck Hollow",
    "tgn:placetype":[
        "aat:300008761"
    ]
},
  "bbox": [],
  "geometry": {"coordinates":[-87.8333,35.85],"type":"Point"}
}