{
  "id": 2630598,
  "type": "Feature",
  "properties": {
    "tgn:hierarchy":[
        "tgn:2630598",
        "tgn:1000001",
        "tgn:7012149",
        "tgn:2002187",
        "tgn:7007919",
        "tgn:7029392"
    ],
    "tgn:id":2630598,
    "tgn:name":"Round Hill",
    "tgn:placetype":[
        "aat:300008798"
    ]
},
  "bbox": [],
  "geometry": {"coordinates":[-78.9833,38.3833],"type":"Point"}
}