{
  "id": 7262187,
  "type": "Feature",
  "properties": {
    "tgn:hierarchy":[
        "tgn:7262187",
        "tgn:7003616",
        "tgn:1000003",
        "tgn:7016845",
        "tgn:7029392"
    ],
    "tgn:id":7262187,
    "tgn:name:nl":"De Wiel",
    "tgn:placetype":[
        "aat:300006075"
    ]
},
  "bbox": [],
  "geometry": {"coordinates":[5.933333,53.233333],"type":"Point"}
}