{
  "id": 2776979,
  "type": "Feature",
  "properties": {
    "tgn:hierarchy":[
        "tgn:2776979",
        "tgn:1000001",
        "tgn:2002369",
        "tgn:7012149",
        "tgn:7007923",
        "tgn:7029392"
    ],
    "tgn:id":2776979,
    "tgn:name":"Windy Draw",
    "tgn:placetype":[
        "aat:300008761"
    ]
},
  "bbox": [],
  "geometry": {"coordinates":[-105.0333,43.2667],"type":"Point"}
}