{
  "id": 7181662,
  "type": "Feature",
  "properties": {
    "tgn:hierarchy":[
        "tgn:7181662",
        "tgn:1000003",
        "tgn:7003689",
        "tgn:7000084",
        "tgn:7029392"
    ],
    "tgn:id":7181662,
    "tgn:name":"Garbus",
    "tgn:placetype":[
        "aat:300008347"
    ]
},
  "bbox": [],
  "geometry": {"coordinates":[12.516667,50.95],"type":"Point"}
}