{
  "id": 7048392,
  "type": "Feature",
  "properties": {
    "tgn:hierarchy":[
        "tgn:7048392",
        "tgn:7003134",
        "tgn:1000003",
        "tgn:7008516",
        "tgn:1000080",
        "tgn:7029392"
    ],
    "tgn:id":7048392,
    "tgn:name":"Due Maest\u00e0",
    "tgn:placetype":[
        "aat:300008347"
    ]
},
  "bbox": [],
  "geometry": {"coordinates":[10.65,44.666667],"type":"Point"}
}