{
  "id": 7306938,
  "type": "Feature",
  "properties": {
    "tgn:hierarchy":[
        "tgn:7306938",
        "tgn:7002810",
        "tgn:7001158",
        "tgn:1000003",
        "tgn:1000095",
        "tgn:7029392"
    ],
    "tgn:id":7306938,
    "tgn:name":"Magdalena, Sierra de la",
    "tgn:placetype":[
        "aat:300008795"
    ]
},
  "bbox": [],
  "geometry": {"coordinates":[-3.333333,43.066667],"type":"Point"}
}