{
  "id": 2445841,
  "type": "Feature",
  "properties": {
    "tgn:hierarchy":[
        "tgn:2445841",
        "tgn:1000001",
        "tgn:7012149",
        "tgn:7007706",
        "tgn:7029392"
    ],
    "tgn:id":2445841,
    "tgn:name":"Lesley Run",
    "tgn:placetype":[
        "aat:300008699"
    ]
},
  "bbox": [],
  "geometry": {"coordinates":[-84.4667,39.8167],"type":"Point"}
}