<<<<<<< HEAD
{
  "id": 7171466,
  "type": "Feature",
  "properties": {
    "tgn:hierarchy":[
        "tgn:7171466",
        "tgn:1000003",
        "tgn:7003677",
        "tgn:7000084",
        "tgn:7029392"
    ],
    "tgn:id":7171466,
    "tgn:name":"Burg Hemmersbach",
    "tgn:placetype":[
        "aat:300006891"
    ]
},
  "bbox": [],
  "geometry": {"coordinates":[6.7,50.916667],"type":"Point"}
}
=======
{"geometry":{"type":"Point","coordinates":[6.700000,50.916667]},"type":"Feature","properties":{"hierarchy":["tgn:7171466","tgn:1000003","tgn:7003677","tgn:7000084","tgn:7029392"],"placetype":["aat:300006891"],"id":7171466,"name:xx":"Burg Hemmersbach"}}
>>>>>>> 03f74aca74312dbeaf24d7e61306dd6a786dc3d0
