{
  "id": 2687698,
  "type": "Feature",
  "properties": {
    "tgn:hierarchy":[
        "tgn:2687698",
        "tgn:1000001",
        "tgn:1002308",
        "tgn:7012149",
        "tgn:7007710",
        "tgn:7029392"
    ],
    "tgn:id":2687698,
    "tgn:name":"Spring Run",
    "tgn:placetype":[
        "aat:300008699"
    ]
},
  "bbox": [],
  "geometry": {"coordinates":[-80.1667,41.65],"type":"Point"}
}