{
  "id": 7231849,
  "type": "Feature",
  "properties": {
    "tgn:hierarchy":[
        "tgn:7231849",
        "tgn:7002728",
        "tgn:7002715",
        "tgn:1000003",
        "tgn:1000074",
        "tgn:7029392"
    ],
    "tgn:id":7231849,
    "tgn:name":"M\u00e1ltska R\u00e9ma",
    "tgn:placetype":[
        "aat:300008699"
    ]
},
  "bbox": [],
  "geometry": {"coordinates":[21.433333,40.766667],"type":"Point"}
}