{
  "id": 1123335,
  "type": "Feature",
  "properties": {
    "tgn:hierarchy":[
        "tgn:1123335",
        "tgn:7005735",
        "tgn:7005685",
        "tgn:1000001",
        "tgn:7029392"
    ],
    "tgn:id":1123335,
    "tgn:name":"Deadman",
    "tgn:placetype":[
        "aat:300008707"
    ]
},
  "bbox": [],
  "geometry": {"coordinates":[-120.9167,50.75],"type":"Point"}
}