{
  "id": 2418815,
  "type": "Feature",
  "properties": {
    "tgn:hierarchy":[
        "tgn:2418815",
        "tgn:1000001",
        "tgn:7012149",
        "tgn:1002376",
        "tgn:7007252",
        "tgn:7029392"
    ],
    "tgn:id":2418815,
    "tgn:name":"James Branch",
    "tgn:placetype":[
        "aat:300008699"
    ]
},
  "bbox": [],
  "geometry": {"coordinates":[-85.8333,38.3833],"type":"Point"}
}