{
  "id": 2305261,
  "type": "Feature",
  "properties": {
    "tgn:hierarchy":[
        "tgn:2305261",
        "tgn:1002300",
        "tgn:1000001",
        "tgn:7012149",
        "tgn:7007564",
        "tgn:7029392"
    ],
    "tgn:id":2305261,
    "tgn:name":"East Branch Simms Stream",
    "tgn:placetype":[
        "aat:300008699"
    ]
},
  "bbox": [],
  "geometry": {"coordinates":[-71.3333,44.8167],"type":"Point"}
}