{
  "id": 2035703,
  "type": "Feature",
  "properties": {
    "tgn:hierarchy":[
        "tgn:2035703",
        "tgn:1000001",
        "tgn:7012149",
        "tgn:2000624",
        "tgn:7007253",
        "tgn:7029392"
    ],
    "tgn:id":2035703,
    "tgn:name":"State Center",
    "tgn:placetype":[
        "aat:300008347"
    ]
},
  "bbox": [],
  "geometry": {"coordinates":[-93.15,42.0167],"type":"Point"}
}