{
  "id": 7154437,
  "type": "Feature",
  "properties": {
    "tgn:hierarchy":[
        "tgn:7154437",
        "tgn:7003669",
        "tgn:1000003",
        "tgn:7000084",
        "tgn:7029392"
    ],
    "tgn:id":7154437,
    "tgn:name":"Joditz",
    "tgn:placetype":[
        "aat:300008347"
    ]
},
  "bbox": [],
  "geometry": {"coordinates":[11.833333,50.366667],"type":"Point"}
}