{
  "id": 2077556,
  "type": "Feature",
  "properties": {
    "tgn:hierarchy":[
        "tgn:2077556",
        "tgn:1000001",
        "tgn:2001586",
        "tgn:7012149",
        "tgn:7007705",
        "tgn:7029392"
    ],
    "tgn:id":2077556,
    "tgn:name":"Eagle Nest",
    "tgn:placetype":[
        "aat:300387016"
    ]
},
  "bbox": [],
  "geometry": {"coordinates":[-101.9167,46.85],"type":"Point"}
}