{
  "id": 2055716,
  "type": "Feature",
  "properties": {
    "tgn:hierarchy":[
        "tgn:2055716",
        "tgn:1000001",
        "tgn:7012149",
        "tgn:2001042",
        "tgn:7007521",
        "tgn:7029392"
    ],
    "tgn:id":2055716,
    "tgn:name":"Waubun",
    "tgn:placetype":[
        "aat:300008347"
    ]
},
  "bbox": [],
  "geometry": {"coordinates":[-95.9333,47.1667],"type":"Point"}
}