{
  "id": 7570897,
  "type": "Feature",
  "properties": {
    "tgn:hierarchy":[
        "tgn:7570897",
        "tgn:1000004",
        "tgn:7000198",
        "tgn:7016788",
        "tgn:7029392"
    ],
    "tgn:id":7570897,
    "tgn:name:en":"K\u0101liy\u0101s",
    "tgn:placetype":[
        "aat:300008347"
    ]
},
  "bbox": [],
  "geometry": {"coordinates":[74.504999,25.677303],"type":"Point"}
}