{
  "id": 7309228,
  "type": "Feature",
  "properties": {
    "tgn:hierarchy":[
        "tgn:7309228",
        "tgn:1001708",
        "tgn:1000049",
        "tgn:1000002",
        "tgn:7029392"
    ],
    "tgn:id":7309228,
    "tgn:name":"Maitenes",
    "tgn:placetype":[
        "aat:300008777"
    ]
},
  "bbox": [],
  "geometry": {"coordinates":[-71.833333,-33.966667],"type":"Point"}
}