{
  "id": 2191303,
  "type": "Feature",
  "properties": {
    "tgn:hierarchy":[
        "tgn:2191303",
        "tgn:7006450",
        "tgn:1000001",
        "tgn:7012149",
        "tgn:2000089",
        "tgn:7029392"
    ],
    "tgn:id":2191303,
    "tgn:name":"Brachipod Gulch",
    "tgn:placetype":[
        "aat:300008761"
    ]
},
  "bbox": [],
  "geometry": {"coordinates":[-147.3167,65.5333],"type":"Point"}
}