{
  "id": 2021935,
  "type": "Feature",
  "properties": {
    "tgn:hierarchy":[
        "tgn:2021935",
        "tgn:1000001",
        "tgn:7012149",
        "tgn:2000332",
        "tgn:7007248",
        "tgn:7029392"
    ],
    "tgn:id":2021935,
    "tgn:name":"Amos Mill",
    "tgn:placetype":[
        "aat:300008347",
        "aat:300387210"
    ]
},
  "bbox": [],
  "geometry": {"coordinates":[-85.5167,34.7167],"type":"Point"}
}