{
  "id": 7218966,
  "type": "Feature",
  "properties": {
    "tgn:hierarchy":[
        "tgn:7218966",
        "tgn:7002690",
        "tgn:7012056",
        "tgn:1000003",
        "tgn:1000074",
        "tgn:7029392"
    ],
    "tgn:id":7218966,
    "tgn:name":"Vouv\u00e1s",
    "tgn:placetype":[
        "aat:300008347"
    ]
},
  "bbox": [],
  "geometry": {"coordinates":[24.183333,35.216667],"type":"Point"}
}