{
  "id": 2056424,
  "type": "Feature",
  "properties": {
    "tgn:hierarchy":[
        "tgn:2056424",
        "tgn:1000001",
        "tgn:7012149",
        "tgn:2001142",
        "tgn:7007522",
        "tgn:7029392"
    ],
    "tgn:id":2056424,
    "tgn:name":"Fernwood",
    "tgn:placetype":[
        "aat:300008347"
    ]
},
  "bbox": [],
  "geometry": {"coordinates":[-90.4333,31.1833],"type":"Point"}
}