{
  "id": 2068940,
  "type": "Feature",
  "properties": {
    "tgn:hierarchy":[
        "tgn:2068940",
        "tgn:1000001",
        "tgn:7012149",
        "tgn:1002993",
        "tgn:7007568",
        "tgn:7029392"
    ],
    "tgn:id":2068940,
    "tgn:name":"East Hebron",
    "tgn:placetype":[
        "aat:300008347"
    ]
},
  "bbox": [],
  "geometry": {"coordinates":[-73.2833,43.25],"type":"Point"}
}