{
  "id": 7561444,
  "type": "Feature",
  "properties": {
    "tgn:hierarchy":[
        "tgn:7561444",
        "tgn:1000004",
        "tgn:7000198",
        "tgn:7016722",
        "tgn:7029392"
    ],
    "tgn:id":7561444,
    "tgn:name:en":"Balli Nagla",
    "tgn:placetype":[
        "aat:300008347"
    ]
},
  "bbox": [],
  "geometry": {"coordinates":[79.120355,27.822406],"type":"Point"}
}