{
  "id": 2557886,
  "type": "Feature",
  "properties": {
    "tgn:hierarchy":[
        "tgn:2557886",
        "tgn:1000001",
        "tgn:1002344",
        "tgn:7012149",
        "tgn:7007517",
        "tgn:7029392"
    ],
    "tgn:id":2557886,
    "tgn:name":"Old Spirit Rock",
    "tgn:placetype":[
        "aat:300011692"
    ]
},
  "bbox": [],
  "geometry": {"coordinates":[-70.7333,42.5667],"type":"Point"}
}