{
  "id": 2616094,
  "type": "Feature",
  "properties": {
    "tgn:hierarchy":[
        "tgn:2616094",
        "tgn:7014010",
        "tgn:1000001",
        "tgn:1002344",
        "tgn:7012149",
        "tgn:7007517",
        "tgn:7029392"
    ],
    "tgn:id":2616094,
    "tgn:name":"Rhoda Pond",
    "tgn:placetype":[
        "aat:300008680"
    ]
},
  "bbox": [],
  "geometry": {"coordinates":[-70.6333,41.45],"type":"Point"}
}