{
  "id": 7277545,
  "type": "Feature",
  "properties": {
    "tgn:hierarchy":[
        "tgn:7277545",
        "tgn:1001637",
        "tgn:1000049",
        "tgn:1000002",
        "tgn:7029392"
    ],
    "tgn:id":7277545,
    "tgn:name":"Puerto Pesquero de Talcahuano",
    "tgn:placetype":[
        "aat:300120599"
    ]
},
  "bbox": [],
  "geometry": {"coordinates":[-73.111111,-36.706944],"type":"Point"}
}