{
  "id": 7591725,
  "type": "Feature",
  "properties": {
    "tgn:hierarchy":[
        "tgn:7591725",
        "tgn:1000004",
        "tgn:7000198",
        "tgn:7000799",
        "tgn:7029392"
    ],
    "tgn:id":7591725,
    "tgn:name:en":"Angaikor",
    "tgn:placetype":[
        "aat:300008347"
    ]
},
  "bbox": [],
  "geometry": {"coordinates":[75.185897,34.518511],"type":"Point"}
}