{
  "id": 2138470,
  "type": "Feature",
  "properties": {
    "tgn:hierarchy":[
        "tgn:2138470",
        "tgn:1000001",
        "tgn:7012149",
        "tgn:2000888",
        "tgn:7007256",
        "tgn:7029392"
    ],
    "tgn:id":2138470,
    "tgn:name":"Ash Bayou",
    "tgn:placetype":[
        "aat:300008699"
    ]
},
  "bbox": [],
  "geometry": {"coordinates":[-93.1333,31.7333],"type":"Point"}
}