{
  "id": 2740219,
  "type": "Feature",
  "properties": {
    "tgn:hierarchy":[
        "tgn:2740219",
        "tgn:7006450",
        "tgn:1000001",
        "tgn:7019698",
        "tgn:7012149",
        "tgn:7029392"
    ],
    "tgn:id":2740219,
    "tgn:name":"Upper Killey Lake",
    "tgn:placetype":[
        "aat:300008680"
    ]
},
  "bbox": [],
  "geometry": {"coordinates":[-150.3167,60.2167],"type":"Point"}
}