{
  "id": 7211834,
  "type": "Feature",
  "properties": {
    "tgn:hierarchy":[
        "tgn:7211834",
        "tgn:1000003",
        "tgn:7000094",
        "tgn:7000084",
        "tgn:7029392"
    ],
    "tgn:id":7211834,
    "tgn:name":"Hahnentief-Schaar",
    "tgn:placetype":[
        "aat:300387036"
    ]
},
  "bbox": [],
  "geometry": {"coordinates":[13.15,54.566667],"type":"Point"}
}