{
  "id": 2635070,
  "type": "Feature",
  "properties": {
    "tgn:hierarchy":[
        "tgn:2635070",
        "tgn:1000001",
        "tgn:7012149",
        "tgn:2002194",
        "tgn:7007919",
        "tgn:7029392"
    ],
    "tgn:id":2635070,
    "tgn:name":"Rye Hollow",
    "tgn:placetype":[
        "aat:300008761"
    ]
},
  "bbox": [],
  "geometry": {"coordinates":[-82.0167,36.65],"type":"Point"}
}