{
  "id": 1132841,
  "type": "Feature",
  "properties": {
    "tgn:hierarchy":[
        "tgn:1132841",
        "tgn:1000001",
        "tgn:7012149",
        "tgn:1002897",
        "tgn:7007920",
        "tgn:7029392"
    ],
    "tgn:id":1132841,
    "tgn:name":"Clear Creek",
    "tgn:placetype":[
        "aat:300008706"
    ]
},
  "bbox": [],
  "geometry": {"coordinates":[-121.85,46.2667],"type":"Point"}
}