{
  "id": 2080355,
  "type": "Feature",
  "properties": {
    "tgn:hierarchy":[
        "tgn:2080355",
        "tgn:1000001",
        "tgn:7012149",
        "tgn:1002802",
        "tgn:7007706",
        "tgn:7029392"
    ],
    "tgn:id":2080355,
    "tgn:name":"Lewisburg",
    "tgn:placetype":[
        "aat:300008347"
    ]
},
  "bbox": [],
  "geometry": {"coordinates":[-84.5333,39.8333],"type":"Point"}
}