{
  "id": 2631957,
  "type": "Feature",
  "properties": {
    "tgn:hierarchy":[
        "tgn:2631957",
        "tgn:1000001",
        "tgn:7012149",
        "tgn:2000491",
        "tgn:7007250",
        "tgn:7029392"
    ],
    "tgn:id":2631957,
    "tgn:name":"Rover Creek",
    "tgn:placetype":[
        "aat:300008706"
    ]
},
  "bbox": [],
  "geometry": {"coordinates":[-115.9167,47.35],"type":"Point"}
}