<<<<<<< HEAD
{
  "id": 7170513,
  "type": "Feature",
  "properties": {
    "tgn:hierarchy":[
        "tgn:7170513",
        "tgn:7003692",
        "tgn:1000003",
        "tgn:7000084",
        "tgn:7029392"
    ],
    "tgn:id":7170513,
    "tgn:name":"Hepp",
    "tgn:placetype":[
        "aat:300000206"
    ]
},
  "bbox": [],
  "geometry": {"coordinates":[10.0,47.8],"type":"Point"}
}
=======
{"geometry":{"type":"Point","coordinates":[10.000000,47.800000]},"type":"Feature","properties":{"hierarchy":["tgn:7170513","tgn:7003692","tgn:1000003","tgn:7000084","tgn:7029392"],"placetype":["aat:300000206"],"id":7170513,"name:xx":"Hepp"}}
>>>>>>> 03f74aca74312dbeaf24d7e61306dd6a786dc3d0
