{
  "id": 2762489,
  "type": "Feature",
  "properties": {
    "tgn:hierarchy":[
        "tgn:2762489",
        "tgn:1000001",
        "tgn:7012149",
        "tgn:2000471",
        "tgn:7007250",
        "tgn:7029392"
    ],
    "tgn:id":2762489,
    "tgn:name":"West Warrior Creek",
    "tgn:placetype":[
        "aat:300008706"
    ]
},
  "bbox": [],
  "geometry": {"coordinates":[-115.2667,43.8833],"type":"Point"}
}