{
  "id": 7207953,
  "type": "Feature",
  "properties": {
    "tgn:hierarchy":[
        "tgn:7207953",
        "tgn:7003692",
        "tgn:1000003",
        "tgn:7000084",
        "tgn:7029392"
    ],
    "tgn:id":7207953,
    "tgn:name":"Busenbach",
    "tgn:placetype":[
        "aat:300008347"
    ]
},
  "bbox": [],
  "geometry": {"coordinates":[8.466667,48.933333],"type":"Point"}
}