<<<<<<< HEAD
{
  "id": 2333258,
  "type": "Feature",
  "properties": {
    "tgn:hierarchy":[
        "tgn:2333258",
        "tgn:1000001",
        "tgn:2001841",
        "tgn:7012149",
        "tgn:7007825",
        "tgn:7029392"
    ],
    "tgn:id":2333258,
    "tgn:name":"Fodderstack Branch",
    "tgn:placetype":[
        "aat:300008699"
    ]
},
  "bbox": [],
  "geometry": {"coordinates":[-83.6833,35.6333],"type":"Point"}
}
=======
{"geometry":{"type":"Point","coordinates":[-83.683300,35.633300]},"type":"Feature","properties":{"hierarchy":["tgn:2333258","tgn:1000001","tgn:2001841","tgn:7012149","tgn:7007825","tgn:7029392"],"placetype":["aat:300008699"],"id":2333258,"name:xx":"Fodderstack Branch"}}
>>>>>>> 03f74aca74312dbeaf24d7e61306dd6a786dc3d0
