{
  "id": 2407936,
  "type": "Feature",
  "properties": {
    "tgn:hierarchy":[
        "tgn:2407936",
        "tgn:1000001",
        "tgn:2000859",
        "tgn:7012149",
        "tgn:7007256",
        "tgn:7029392"
    ],
    "tgn:id":2407936,
    "tgn:name":"Hurricane Creek",
    "tgn:placetype":[
        "aat:300008706"
    ]
},
  "bbox": [],
  "geometry": {"coordinates":[-93.6333,30.4833],"type":"Point"}
}