<<<<<<< HEAD
{
  "id": 7354244,
  "type": "Feature",
  "properties": {
    "tgn:hierarchy":[
        "tgn:7354244",
        "tgn:7005581",
        "tgn:1000001",
        "tgn:7005560",
        "tgn:7029392"
    ],
    "tgn:id":7354244,
    "tgn:name":"Casa Madera",
    "tgn:placetype":[
        "aat:300008347"
    ]
},
  "bbox": [],
  "geometry": {"coordinates":[-108.1,31.45],"type":"Point"}
}
=======
{"geometry":{"type":"Point","coordinates":[-108.100000,31.450000]},"type":"Feature","properties":{"hierarchy":["tgn:7354244","tgn:7005581","tgn:1000001","tgn:7005560","tgn:7029392"],"placetype":["aat:300008347"],"id":7354244,"name:xx":"Casa Madera"}}
>>>>>>> 03f74aca74312dbeaf24d7e61306dd6a786dc3d0
