{
  "id": 7229012,
  "type": "Feature",
  "properties": {
    "tgn:hierarchy":[
        "tgn:7229012",
        "tgn:7011163",
        "tgn:7002674",
        "tgn:1000003",
        "tgn:1000074",
        "tgn:7029392"
    ],
    "tgn:id":7229012,
    "tgn:name":"Klei\u00f3",
    "tgn:placetype":[
        "aat:300008347"
    ]
},
  "bbox": [],
  "geometry": {"coordinates":[26.321667,39.348056],"type":"Point"}
}