<<<<<<< HEAD
{
  "id": 7368625,
  "type": "Feature",
  "properties": {
    "tgn:hierarchy":[
        "tgn:7368625",
        "tgn:1001836",
        "tgn:1000001",
        "tgn:7005560",
        "tgn:7029392"
    ],
    "tgn:id":7368625,
    "tgn:name":"Irad",
    "tgn:placetype":[
        "aat:300008347"
    ]
},
  "bbox": [],
  "geometry": {"coordinates":[-111.183333,24.833333],"type":"Point"}
}
=======
{"geometry":{"type":"Point","coordinates":[-111.183333,24.833333]},"type":"Feature","properties":{"hierarchy":["tgn:7368625","tgn:1001836","tgn:1000001","tgn:7005560","tgn:7029392"],"placetype":["aat:300008347"],"id":7368625,"name:xx":"Irad"}}
>>>>>>> 03f74aca74312dbeaf24d7e61306dd6a786dc3d0
