<<<<<<< HEAD
{
  "id": 7054138,
  "type": "Feature",
  "properties": {
    "tgn:hierarchy":[
        "tgn:7054138",
        "tgn:7005765",
        "tgn:1000003",
        "tgn:7003237",
        "tgn:1000080",
        "tgn:7029392"
    ],
    "tgn:id":7054138,
    "tgn:name":"Lumezzane San Sebastiano",
    "tgn:placetype":[
        "aat:300008347",
        "aat:300008375"
    ]
},
  "bbox": [],
  "geometry": {"coordinates":[10.25,45.65],"type":"Point"}
}
=======
{"geometry":{"type":"Point","coordinates":[10.250000,45.650000]},"type":"Feature","properties":{"hierarchy":["tgn:7054138","tgn:7005765","tgn:1000003","tgn:7003237","tgn:1000080","tgn:7029392"],"placetype":["aat:300008347","aat:300008375"],"id":7054138,"name:xx":"Lumezzane San Sebastiano"}}
>>>>>>> 03f74aca74312dbeaf24d7e61306dd6a786dc3d0
