{
  "id": 2001842,
  "type": "Feature",
  "properties": {
    "tgn:hierarchy":[
        "tgn:2001842",
        "tgn:1000001",
        "tgn:7012149",
        "tgn:7007825",
        "tgn:7029392"
    ],
    "tgn:id":2001842,
    "tgn:name":"Bradley",
    "tgn:placetype":[
        "aat:300387145",
        "aat:300000771"
    ]
},
  "bbox": [],
  "geometry": {"coordinates":[-84.8667,35.15],"type":"Point"}
}