{
  "id": 7501596,
  "type": "Feature",
  "properties": {
    "tgn:hierarchy":[
        "tgn:7501596",
        "tgn:7001004",
        "tgn:1000004",
        "tgn:1000141",
        "tgn:7029392"
    ],
    "tgn:id":7501596,
    "tgn:name":"Dongyue Gong",
    "tgn:placetype":[
        "aat:300007595"
    ]
},
  "bbox": [],
  "geometry": {"coordinates":[120.258611,22.859167],"type":"Point"}
}