{
  "id": 7396705,
  "type": "Feature",
  "properties": {
    "tgn:hierarchy":[
        "tgn:7396705",
        "tgn:1000001",
        "tgn:7005591",
        "tgn:7005560",
        "tgn:7029392"
    ],
    "tgn:id":7396705,
    "tgn:name":"Santa Cruz Yagavila",
    "tgn:placetype":[
        "aat:300008347"
    ]
},
  "bbox": [],
  "geometry": {"coordinates":[-96.35,17.516667],"type":"Point"}
}