{
  "id": 2509587,
  "type": "Feature",
  "properties": {
    "tgn:hierarchy":[
        "tgn:2509587",
        "tgn:1000001",
        "tgn:7012149",
        "tgn:1002676",
        "tgn:7007240",
        "tgn:7029392"
    ],
    "tgn:id":2509587,
    "tgn:name":"Middle Ground",
    "tgn:placetype":[
        "aat:300132348"
    ]
},
  "bbox": [],
  "geometry": {"coordinates":[-81.8167,24.5667],"type":"Point"}
}