{
  "id": 2749342,
  "type": "Feature",
  "properties": {
    "tgn:hierarchy":[
        "tgn:2749342",
        "tgn:1000001",
        "tgn:7012149",
        "tgn:2001103",
        "tgn:7007522",
        "tgn:7029392"
    ],
    "tgn:id":2749342,
    "tgn:name":"Wallis",
    "tgn:placetype":[
        "aat:300008347"
    ]
},
  "bbox": [],
  "geometry": {"coordinates":[-89.2333,31.15],"type":"Point"}
}