{
  "id": 2669190,
  "type": "Feature",
  "properties": {
    "tgn:hierarchy":[
        "tgn:2669190",
        "tgn:1000001",
        "tgn:7012149",
        "tgn:2001129",
        "tgn:7007522",
        "tgn:7029392"
    ],
    "tgn:id":2669190,
    "tgn:name":"Sleepy Hollow",
    "tgn:placetype":[
        "aat:300008347"
    ]
},
  "bbox": [],
  "geometry": {"coordinates":[-88.4333,33.5333],"type":"Point"}
}