{
  "id": 1120038,
  "type": "Feature",
  "properties": {
    "tgn:hierarchy":[
        "tgn:1120038",
        "tgn:7005685",
        "tgn:1000001",
        "tgn:7005804",
        "tgn:7029392"
    ],
    "tgn:id":1120038,
    "tgn:name":"La Mothe, Lac",
    "tgn:placetype":[
        "aat:300006191"
    ]
},
  "bbox": [],
  "geometry": {"coordinates":[-71.15,48.7667],"type":"Point"}
}