{
  "id": 7078976,
  "type": "Feature",
  "properties": {
    "tgn:hierarchy":[
        "tgn:7078976",
        "tgn:1000003",
        "tgn:7003678",
        "tgn:7000084",
        "tgn:7029392"
    ],
    "tgn:id":7078976,
    "tgn:name":"Wolfs-Kopf",
    "tgn:placetype":[
        "aat:300008777"
    ]
},
  "bbox": [],
  "geometry": {"coordinates":[8.35,50.183333],"type":"Point"}
}