{
  "id": 2462117,
  "type": "Feature",
  "properties": {
    "tgn:hierarchy":[
        "tgn:2462117",
        "tgn:1000001",
        "tgn:7012149",
        "tgn:2002110",
        "tgn:7007827",
        "tgn:7029392"
    ],
    "tgn:id":2462117,
    "tgn:name":"Little Valley",
    "tgn:placetype":[
        "aat:300008761"
    ]
},
  "bbox": [],
  "geometry": {"coordinates":[-109.6667,38.7667],"type":"Point"}
}