{
  "id": 2237814,
  "type": "Feature",
  "properties": {
    "tgn:hierarchy":[
        "tgn:2237814",
        "tgn:1000001",
        "tgn:7012149",
        "tgn:7029392"
    ],
    "tgn:id":2237814,
    "tgn:name":"Chinquapin Ridge",
    "tgn:placetype":[
        "aat:300266640"
    ]
},
  "bbox": [],
  "geometry": {"coordinates":[-88.15,34.5167],"type":"Point"}
}