{
  "id": 2248591,
  "type": "Feature",
  "properties": {
    "tgn:hierarchy":[
        "tgn:2248591",
        "tgn:1000001",
        "tgn:7012149",
        "tgn:2001709",
        "tgn:7007708",
        "tgn:7029392"
    ],
    "tgn:id":2248591,
    "tgn:name":"Cold Spring Creek",
    "tgn:placetype":[
        "aat:300008706"
    ]
},
  "bbox": [],
  "geometry": {"coordinates":[-118.65,42.7667],"type":"Point"}
}