<<<<<<< HEAD
{
  "id": 2257580,
  "type": "Feature",
  "properties": {
    "tgn:hierarchy":[
        "tgn:2257580",
        "tgn:1000001",
        "tgn:7012149",
        "tgn:2001437",
        "tgn:7007566",
        "tgn:7029392"
    ],
    "tgn:id":2257580,
    "tgn:name":"Corral Canyon Tank",
    "tgn:placetype":[
        "aat:300006191"
    ]
},
  "bbox": [],
  "geometry": {"coordinates":[-108.1333,33.1667],"type":"Point"}
}
=======
{"geometry":{"type":"Point","coordinates":[-108.133300,33.166700]},"type":"Feature","properties":{"hierarchy":["tgn:2257580","tgn:1000001","tgn:7012149","tgn:2001437","tgn:7007566","tgn:7029392"],"placetype":["aat:300006191"],"id":2257580,"name:xx":"Corral Canyon Tank"}}
>>>>>>> 03f74aca74312dbeaf24d7e61306dd6a786dc3d0
