{
  "id": 2769893,
  "type": "Feature",
  "properties": {
    "tgn:hierarchy":[
        "tgn:2769893",
        "tgn:1002143",
        "tgn:1000001",
        "tgn:7012149",
        "tgn:7007252",
        "tgn:7029392"
    ],
    "tgn:id":2769893,
    "tgn:name":"Wilbur Ditch",
    "tgn:placetype":[
        "aat:300006075"
    ]
},
  "bbox": [],
  "geometry": {"coordinates":[-84.9167,41.1667],"type":"Point"}
}