{
  "id": 7498435,
  "type": "Feature",
  "properties": {
    "tgn:hierarchy":[
        "tgn:7498435",
        "tgn:1000004",
        "tgn:1000454",
        "tgn:1000141",
        "tgn:7029392"
    ],
    "tgn:id":7498435,
    "tgn:name":"Zhongfu Shan",
    "tgn:placetype":[
        "aat:300008777"
    ]
},
  "bbox": [],
  "geometry": {"coordinates":[121.677721,25.167827],"type":"Point"}
}