{
  "id": 2293443,
  "type": "Feature",
  "properties": {
    "tgn:hierarchy":[
        "tgn:2293443",
        "tgn:7002659",
        "tgn:1000001",
        "tgn:7012149",
        "tgn:2000065",
        "tgn:7029392"
    ],
    "tgn:id":2293443,
    "tgn:name":"Double Natural Bridges",
    "tgn:placetype":[
        "aat:300386837"
    ]
},
  "bbox": [],
  "geometry": {"coordinates":[-87.65,31.8667],"type":"Point"}
}