{
  "id": 2654244,
  "type": "Feature",
  "properties": {
    "tgn:hierarchy":[
        "tgn:2654244",
        "tgn:1000001",
        "tgn:1002949",
        "tgn:7012149",
        "tgn:7007159",
        "tgn:7029392"
    ],
    "tgn:id":2654244,
    "tgn:name":"Shady Brook",
    "tgn:placetype":[
        "aat:300008699"
    ]
},
  "bbox": [],
  "geometry": {"coordinates":[-72.4167,41.9667],"type":"Point"}
}