{
  "id": 7209149,
  "type": "Feature",
  "properties": {
    "tgn:hierarchy":[
        "tgn:7209149",
        "tgn:1000003",
        "tgn:7003676",
        "tgn:7000084",
        "tgn:7029392"
    ],
    "tgn:id":7209149,
    "tgn:name":"Beckel-Berg",
    "tgn:placetype":[
        "aat:300008777"
    ]
},
  "bbox": [],
  "geometry": {"coordinates":[10.483333,53.083333],"type":"Point"}
}