{
  "id": 2334434,
  "type": "Feature",
  "properties": {
    "tgn:hierarchy":[
        "tgn:2334434",
        "tgn:1000001",
        "tgn:1002361",
        "tgn:7012149",
        "tgn:7007828",
        "tgn:7029392"
    ],
    "tgn:id":2334434,
    "tgn:name":"Forest Lake",
    "tgn:placetype":[
        "aat:300008680"
    ]
},
  "bbox": [],
  "geometry": {"coordinates":[-71.6667,44.9833],"type":"Point"}
}