{
  "id": 2665971,
  "type": "Feature",
  "properties": {
    "tgn:hierarchy":[
        "tgn:2665971",
        "tgn:1000001",
        "tgn:1002415",
        "tgn:7012149",
        "tgn:7007828",
        "tgn:7029392"
    ],
    "tgn:id":2665971,
    "tgn:name":"Sister Islands",
    "tgn:placetype":[
        "aat:300386853"
    ]
},
  "bbox": [],
  "geometry": {"coordinates":[-73.3333,44.7333],"type":"Point"}
}