{
  "id": 1001460,
  "type": "Feature",
  "properties": {
    "tgn:hierarchy":[
        "tgn:1001460",
        "tgn:7001242",
        "tgn:1000191",
        "tgn:7029392"
    ],
    "tgn:id":1001460,
    "tgn:name":"Northern Province",
    "tgn:placetype":[
        "aat:300387064",
        "aat:300000774"
    ]
},
  "bbox": [],
  "geometry": {"coordinates":[-11.7333,9.2333],"type":"Point"}
}