{
  "id": 7259508,
  "type": "Feature",
  "properties": {
    "tgn:hierarchy":[
        "tgn:7259508",
        "tgn:1000003",
        "tgn:1000063",
        "tgn:7029392"
    ],
    "tgn:id":7259508,
    "tgn:name":"Walvisstaart",
    "tgn:placetype":[
        "aat:300387036"
    ]
},
  "bbox": [],
  "geometry": {"coordinates":[3.266667,51.45],"type":"Point"}
}