{
  "id": 7484849,
  "type": "Feature",
  "properties": {
    "tgn:hierarchy":[
        "tgn:7484849",
        "tgn:7001004",
        "tgn:1000004",
        "tgn:1000141",
        "tgn:7029392"
    ],
    "tgn:id":7484849,
    "tgn:name":"Yansangkeng",
    "tgn:placetype":[
        "aat:300008699"
    ]
},
  "bbox": [],
  "geometry": {"coordinates":[120.607222,23.088333],"type":"Point"}
}