{
  "id": 7537066,
  "type": "Feature",
  "properties": {
    "tgn:hierarchy":[
        "tgn:7537066",
        "tgn:7001242",
        "tgn:7016833",
        "tgn:1001123",
        "tgn:7029392"
    ],
    "tgn:id":7537066,
    "tgn:name":"Laj\u0101n, Ba\u1e29r",
    "tgn:placetype":[
        "aat:300008680"
    ]
},
  "bbox": [],
  "geometry": {"coordinates":[32.085556,31.211944],"type":"Point"}
}