{
  "id": 2580272,
  "type": "Feature",
  "properties": {
    "tgn:hierarchy":[
        "tgn:2580272",
        "tgn:1000001",
        "tgn:7012149",
        "tgn:1002263",
        "tgn:7007826",
        "tgn:7029392"
    ],
    "tgn:id":2580272,
    "tgn:name":"Pierson Branch",
    "tgn:placetype":[
        "aat:300008699"
    ]
},
  "bbox": [],
  "geometry": {"coordinates":[-95.2667,32.0333],"type":"Point"}
}