{
  "id": 2492801,
  "type": "Feature",
  "properties": {
    "tgn:hierarchy":[
        "tgn:2492801",
        "tgn:1000001",
        "tgn:7012149",
        "tgn:7007157",
        "tgn:7014004",
        "tgn:7029392"
    ],
    "tgn:id":2492801,
    "tgn:name":"Mariposa Mine",
    "tgn:placetype":[
        "aat:300000390"
    ]
},
  "bbox": [],
  "geometry": {"coordinates":[-119.95,37.4833],"type":"Point"}
}