{
  "id": 1064655,
  "type": "Feature",
  "properties": {
    "tgn:hierarchy":[
        "tgn:1064655",
        "tgn:7002443",
        "tgn:1000003",
        "tgn:7018974",
        "tgn:7008591",
        "tgn:7029392"
    ],
    "tgn:id":1064655,
    "tgn:name":"Glyn-Neath",
    "tgn:placetype":[
        "aat:300008347"
    ]
},
  "bbox": [],
  "geometry": {"coordinates":[-3.618333,51.7475],"type":"Point"}
}