{
  "id": 2368750,
  "type": "Feature",
  "properties": {
    "tgn:hierarchy":[
        "tgn:2368750",
        "tgn:7006450",
        "tgn:1000001",
        "tgn:2124053",
        "tgn:7012149",
        "tgn:7029392"
    ],
    "tgn:id":2368750,
    "tgn:name":"Gull Lake",
    "tgn:placetype":[
        "aat:300008680"
    ]
},
  "bbox": [],
  "geometry": {"coordinates":[-148.9333,61.5333],"type":"Point"}
}