<<<<<<< HEAD
{
  "id": 7485417,
  "type": "Feature",
  "properties": {
    "tgn:hierarchy":[
        "tgn:7485417",
        "tgn:1000004",
        "tgn:7467799",
        "tgn:1000141",
        "tgn:7029392"
    ],
    "tgn:id":7485417,
    "tgn:name":"Yufeng Gong",
    "tgn:placetype":[
        "aat:300007595"
    ]
},
  "bbox": [],
  "geometry": {"coordinates":[120.484722,24.087222],"type":"Point"}
}
=======
{"geometry":{"type":"Point","coordinates":[120.484722,24.087222]},"type":"Feature","properties":{"hierarchy":["tgn:7485417","tgn:1000004","tgn:7467799","tgn:1000141","tgn:7029392"],"placetype":["aat:300007595"],"id":7485417,"name:xx":"Yufeng Gong"}}
>>>>>>> 03f74aca74312dbeaf24d7e61306dd6a786dc3d0
