{
  "id": 2135853,
  "type": "Feature",
  "properties": {
    "tgn:hierarchy":[
        "tgn:2135853",
        "tgn:1000001",
        "tgn:7012149",
        "tgn:2001706",
        "tgn:7007708",
        "tgn:7029392"
    ],
    "tgn:id":2135853,
    "tgn:name":"Apple Creek",
    "tgn:placetype":[
        "aat:300008706"
    ]
},
  "bbox": [],
  "geometry": {"coordinates":[-122.65,43.3167],"type":"Point"}
}