{
  "id": 1050418,
  "type": "Feature",
  "properties": {
    "tgn:hierarchy":[
        "tgn:1050418",
        "tgn:7002444",
        "tgn:1000003",
        "tgn:7019152",
        "tgn:7008591",
        "tgn:7029392"
    ],
    "tgn:id":1050418,
    "tgn:name:en":"Ballinluig",
    "tgn:placetype":[
        "aat:300008347"
    ]
},
  "bbox": [],
  "geometry": {"coordinates":[-3.65,56.633333],"type":"Point"}
}