{
  "id": 7593968,
  "type": "Feature",
  "properties": {
    "tgn:hierarchy":[
        "tgn:7593968",
        "tgn:1000003",
        "tgn:7015657",
        "tgn:7029392"
    ],
    "tgn:id":7593968,
    "tgn:name":"Danilovgrad",
    "tgn:placetype":[
        "aat:300387064",
        "aat:300265612"
    ]
},
  "bbox": [],
  "geometry": {"coordinates":[19.091111,42.558611],"type":"Point"}
}