{
  "id": 2255565,
  "type": "Feature",
  "properties": {
    "tgn:hierarchy":[
        "tgn:2255565",
        "tgn:1000001",
        "tgn:7012149",
        "tgn:2001883",
        "tgn:7007825",
        "tgn:7029392"
    ],
    "tgn:id":2255565,
    "tgn:name":"Copeland Hollow",
    "tgn:placetype":[
        "aat:300008761"
    ]
},
  "bbox": [],
  "geometry": {"coordinates":[-83.9833,36.0667],"type":"Point"}
}