<<<<<<< HEAD
{
  "id": 2336358,
  "type": "Feature",
  "properties": {
    "tgn:hierarchy":[
        "tgn:2336358",
        "tgn:1000001",
        "tgn:7012149",
        "tgn:1003004",
        "tgn:7007252",
        "tgn:7029392"
    ],
    "tgn:id":2336358,
    "tgn:name":"Fountain Creek",
    "tgn:placetype":[
        "aat:300008706"
    ]
},
  "bbox": [],
  "geometry": {"coordinates":[-84.85,40.0],"type":"Point"}
}
=======
{"geometry":{"type":"Point","coordinates":[-84.850000,40.000000]},"type":"Feature","properties":{"hierarchy":["tgn:2336358","tgn:1000001","tgn:7012149","tgn:1003004","tgn:7007252","tgn:7029392"],"placetype":["aat:300008706"],"id":2336358,"name:xx":"Fountain Creek"}}
>>>>>>> 03f74aca74312dbeaf24d7e61306dd6a786dc3d0
