<<<<<<< HEAD
{
  "id": 7025721,
  "type": "Feature",
  "properties": {
    "tgn:hierarchy":[
        "tgn:7025721",
        "tgn:7002445",
        "tgn:1000003",
        "tgn:7012077",
        "tgn:7008591",
        "tgn:7029392"
    ],
    "tgn:id":7025721,
    "tgn:name:en":"Shirwell",
    "tgn:placetype":[
        "aat:300008347"
    ]
},
  "bbox": [],
  "geometry": {"coordinates":[-4.0,51.116667],"type":"Point"}
}
=======
{"geometry":{"type":"Point","coordinates":[-4.000000,51.116667]},"type":"Feature","properties":{"hierarchy":["tgn:7025721","tgn:7002445","tgn:1000003","tgn:7012077","tgn:7008591","tgn:7029392"],"placetype":["aat:300008347"],"name:en":"Shirwell","id":7025721}}
>>>>>>> 03f74aca74312dbeaf24d7e61306dd6a786dc3d0
