{
  "id": 7522963,
  "type": "Feature",
  "properties": {
    "tgn:hierarchy":[
        "tgn:7522963",
        "tgn:7001242",
        "tgn:7016833",
        "tgn:1001110",
        "tgn:7029392"
    ],
    "tgn:id":7522963,
    "tgn:name:en":"Bar\u0101shah, W\u0101d\u012b",
    "tgn:placetype":[
        "aat:300379998"
    ]
},
  "bbox": [],
  "geometry": {"coordinates":[31.995044,30.218763],"type":"Point"}
}