{
  "id": 2279129,
  "type": "Feature",
  "properties": {
    "tgn:hierarchy":[
        "tgn:2279129",
        "tgn:1000001",
        "tgn:7012149",
        "tgn:2002270",
        "tgn:7013961",
        "tgn:7029392"
    ],
    "tgn:id":2279129,
    "tgn:name":"Deadening Hollow",
    "tgn:placetype":[
        "aat:300008761"
    ]
},
  "bbox": [],
  "geometry": {"coordinates":[-81.3167,38.2833],"type":"Point"}
}