<<<<<<< HEAD
{
  "id": 7054862,
  "type": "Feature",
  "properties": {
    "tgn:hierarchy":[
        "tgn:7054862",
        "tgn:1001730",
        "tgn:1000003",
        "tgn:7003121",
        "tgn:1000080",
        "tgn:7029392"
    ],
    "tgn:id":7054862,
    "tgn:name":"Molinos, Riu sos",
    "tgn:placetype":[
        "aat:300008699"
    ]
},
  "bbox": [],
  "geometry": {"coordinates":[8.666667,40.1],"type":"Point"}
}
=======
{"geometry":{"type":"Point","coordinates":[8.666667,40.100000]},"type":"Feature","properties":{"hierarchy":["tgn:7054862","tgn:1001730","tgn:1000003","tgn:7003121","tgn:1000080","tgn:7029392"],"placetype":["aat:300008699"],"id":7054862,"name:xx":"Molinos, Riu sos"}}
>>>>>>> 03f74aca74312dbeaf24d7e61306dd6a786dc3d0
