{
  "id": 7406537,
  "type": "Feature",
  "properties": {
    "tgn:hierarchy":[
        "tgn:7406537",
        "tgn:1000001",
        "tgn:1001906",
        "tgn:7005560",
        "tgn:7029392"
    ],
    "tgn:id":7406537,
    "tgn:name":"Los Pitorreales",
    "tgn:placetype":[
        "aat:300008347"
    ]
},
  "bbox": [],
  "geometry": {"coordinates":[-104.775,22.379167],"type":"Point"}
}