{
  "id": 2457471,
  "type": "Feature",
  "properties": {
    "tgn:hierarchy":[
        "tgn:2457471",
        "tgn:1000001",
        "tgn:7012149",
        "tgn:2001761",
        "tgn:7007712",
        "tgn:7029392"
    ],
    "tgn:id":2457471,
    "tgn:name":"Little Longnose Creek",
    "tgn:placetype":[
        "aat:300008706"
    ]
},
  "bbox": [],
  "geometry": {"coordinates":[-83.25,34.7167],"type":"Point"}
}