{
  "id": 2724007,
  "type": "Feature",
  "properties": {
    "tgn:hierarchy":[
        "tgn:2724007",
        "tgn:1000001",
        "tgn:7019982",
        "tgn:7012149",
        "tgn:7007517",
        "tgn:7029392"
    ],
    "tgn:id":2724007,
    "tgn:name":"Tolland State Forest",
    "tgn:placetype":[
        "aat:300008863"
    ]
},
  "bbox": [],
  "geometry": {"coordinates":[-73.0167,42.1333],"type":"Point"}
}