{
  "id": 7425160,
  "type": "Feature",
  "properties": {
    "tgn:hierarchy":[
        "tgn:7425160",
        "tgn:1000001",
        "tgn:1001960",
        "tgn:7005560",
        "tgn:7029392"
    ],
    "tgn:id":7425160,
    "tgn:name":"San Jes\u00fas",
    "tgn:placetype":[
        "aat:300008347"
    ]
},
  "bbox": [],
  "geometry": {"coordinates":[-112.166667,29.883333],"type":"Point"}
}