{
  "id": 7547031,
  "type": "Feature",
  "properties": {
    "tgn:hierarchy":[
        "tgn:7547031",
        "tgn:1000004",
        "tgn:7000198",
        "tgn:7001797",
        "tgn:7029392"
    ],
    "tgn:id":7547031,
    "tgn:name:en":"Belukkurichchi",
    "tgn:placetype":[
        "aat:300008347"
    ]
},
  "bbox": [],
  "geometry": {"coordinates":[78.25,11.383333],"type":"Point"}
}