{
  "id": 2627586,
  "type": "Feature",
  "properties": {
    "tgn:hierarchy":[
        "tgn:2627586",
        "tgn:7002659",
        "tgn:1000001",
        "tgn:7012149",
        "tgn:2000031",
        "tgn:7029392"
    ],
    "tgn:id":2627586,
    "tgn:name":"Rogers Creek",
    "tgn:placetype":[
        "aat:300008706"
    ]
},
  "bbox": [],
  "geometry": {"coordinates":[-88.0167,32.9333],"type":"Point"}
}