<<<<<<< HEAD
{
  "id": 2253301,
  "type": "Feature",
  "properties": {
    "tgn:hierarchy":[
        "tgn:2253301",
        "tgn:1000001",
        "tgn:7012149",
        "tgn:2001901",
        "tgn:7007825",
        "tgn:7029392"
    ],
    "tgn:id":2253301,
    "tgn:name":"Convict Branch",
    "tgn:placetype":[
        "aat:300008699"
    ]
},
  "bbox": [],
  "geometry": {"coordinates":[-84.6667,36.2],"type":"Point"}
}
=======
{"geometry":{"type":"Point","coordinates":[-84.666700,36.200000]},"type":"Feature","properties":{"hierarchy":["tgn:2253301","tgn:1000001","tgn:7012149","tgn:2001901","tgn:7007825","tgn:7029392"],"placetype":["aat:300008699"],"id":2253301,"name:xx":"Convict Branch"}}
>>>>>>> 03f74aca74312dbeaf24d7e61306dd6a786dc3d0
