{
  "id": 7398914,
  "type": "Feature",
  "properties": {
    "tgn:hierarchy":[
        "tgn:7398914",
        "tgn:1000001",
        "tgn:1001893",
        "tgn:7005560",
        "tgn:7029392"
    ],
    "tgn:id":7398914,
    "tgn:name":"Las \u00c1nimas",
    "tgn:placetype":[
        "aat:300008347"
    ]
},
  "bbox": [],
  "geometry": {"coordinates":[-99.502778,19.754167],"type":"Point"}
}