{
  "id": 1033396,
  "type": "Feature",
  "properties": {
    "tgn:hierarchy":[
        "tgn:1033396",
        "tgn:7002878",
        "tgn:1000003",
        "tgn:1000070",
        "tgn:7029392"
    ],
    "tgn:id":1033396,
    "tgn:name":"Hagetmau",
    "tgn:placetype":[
        "aat:300008347"
    ]
},
  "bbox": [],
  "geometry": {"coordinates":[-0.5833,43.65],"type":"Point"}
}