{
  "id": 2727975,
  "type": "Feature",
  "properties": {
    "tgn:hierarchy":[
        "tgn:2727975",
        "tgn:1000001",
        "tgn:7012149",
        "tgn:1002767",
        "tgn:7007920",
        "tgn:7029392"
    ],
    "tgn:id":2727975,
    "tgn:name":"Trap Creek",
    "tgn:placetype":[
        "aat:300008706"
    ]
},
  "bbox": [],
  "geometry": {"coordinates":[-123.7167,46.5333],"type":"Point"}
}