{
  "id": 2710306,
  "type": "Feature",
  "properties": {
    "tgn:hierarchy":[
        "tgn:2710306",
        "tgn:1000001",
        "tgn:7012149",
        "tgn:2001927",
        "tgn:7007825",
        "tgn:7029392"
    ],
    "tgn:id":2710306,
    "tgn:name":"Tally Branch",
    "tgn:placetype":[
        "aat:300008699"
    ]
},
  "bbox": [],
  "geometry": {"coordinates":[-87.8667,35.0167],"type":"Point"}
}