{
  "id": 2500865,
  "type": "Feature",
  "properties": {
    "tgn:hierarchy":[
        "tgn:2500865",
        "tgn:1000001",
        "tgn:1002198",
        "tgn:7012149",
        "tgn:7007826",
        "tgn:7029392"
    ],
    "tgn:id":2500865,
    "tgn:name":"McFadden Bayou",
    "tgn:placetype":[
        "aat:300008699"
    ]
},
  "bbox": [],
  "geometry": {"coordinates":[-95.5167,29.0667],"type":"Point"}
}