{
  "id": 7113104,
  "type": "Feature",
  "properties": {
    "tgn:hierarchy":[
        "tgn:7113104",
        "tgn:7000096",
        "tgn:1000003",
        "tgn:7000084",
        "tgn:7029392"
    ],
    "tgn:id":7113104,
    "tgn:name":"Rosengarten",
    "tgn:placetype":[
        "aat:300008347"
    ]
},
  "bbox": [],
  "geometry": {"coordinates":[14.466667,52.35],"type":"Point"}
}