{
  "id": 1094031,
  "type": "Feature",
  "properties": {
    "tgn:hierarchy":[
        "tgn:1094031",
        "tgn:7001242",
        "tgn:7030594",
        "tgn:1000198",
        "tgn:7029392"
    ],
    "tgn:id":1094031,
    "tgn:name":"Uchab",
    "tgn:placetype":[
        "aat:300008347"
    ]
},
  "bbox": [],
  "geometry": {"coordinates":[17.8333,-19.7333],"type":"Point"}
}