{
  "id": 2191992,
  "type": "Feature",
  "properties": {
    "tgn:hierarchy":[
        "tgn:2191992",
        "tgn:1000001",
        "tgn:7012149",
        "tgn:1002737",
        "tgn:7007520",
        "tgn:7029392"
    ],
    "tgn:id":2191992,
    "tgn:name":"Braemar, Lake",
    "tgn:placetype":[
        "aat:300006191"
    ]
},
  "bbox": [],
  "geometry": {"coordinates":[-83.5833,42.75],"type":"Point"}
}