{
  "id": 2508140,
  "type": "Feature",
  "properties": {
    "tgn:hierarchy":[
        "tgn:2508140",
        "tgn:1000001",
        "tgn:7012149",
        "tgn:2000972",
        "tgn:7007520",
        "tgn:7029392"
    ],
    "tgn:id":2508140,
    "tgn:name":"Middle Branch Linton Creek",
    "tgn:placetype":[
        "aat:300008706"
    ]
},
  "bbox": [],
  "geometry": {"coordinates":[-85.3333,46.5667],"type":"Point"}
}