{
  "id": 7426702,
  "type": "Feature",
  "properties": {
    "tgn:hierarchy":[
        "tgn:7426702",
        "tgn:7005581",
        "tgn:1000001",
        "tgn:7005560",
        "tgn:7029392"
    ],
    "tgn:id":7426702,
    "tgn:name":"El Chamizal",
    "tgn:placetype":[
        "aat:300008347"
    ]
},
  "bbox": [],
  "geometry": {"coordinates":[-106.183333,28.033333],"type":"Point"}
}