{
  "id": 7548950,
  "type": "Feature",
  "properties": {
    "tgn:hierarchy":[
        "tgn:7548950",
        "tgn:1001828",
        "tgn:1000004",
        "tgn:7000198",
        "tgn:7029392"
    ],
    "tgn:id":7548950,
    "tgn:name:en":"Chitigidda",
    "tgn:placetype":[
        "aat:300007783"
    ]
},
  "bbox": [],
  "geometry": {"coordinates":[77.966667,17.433333],"type":"Point"}
}