{
  "id": 7186254,
  "type": "Feature",
  "properties": {
    "tgn:hierarchy":[
        "tgn:7186254",
        "tgn:7000096",
        "tgn:1000003",
        "tgn:7000084",
        "tgn:7029392"
    ],
    "tgn:id":7186254,
    "tgn:name":"Gut Gollin",
    "tgn:placetype":[
        "aat:300000206"
    ]
},
  "bbox": [],
  "geometry": {"coordinates":[13.566667,53.05],"type":"Point"}
}