{
  "id": 7167812,
  "type": "Feature",
  "properties": {
    "tgn:hierarchy":[
        "tgn:7167812",
        "tgn:1000003",
        "tgn:7003678",
        "tgn:7000084",
        "tgn:7029392"
    ],
    "tgn:id":7167812,
    "tgn:name":"Hatzfeld, Forst",
    "tgn:placetype":[
        "aat:300008863"
    ]
},
  "bbox": [],
  "geometry": {"coordinates":[8.533333,50.966667],"type":"Point"}
}