{
  "id": 7536472,
  "type": "Feature",
  "properties": {
    "tgn:hierarchy":[
        "tgn:7536472",
        "tgn:7001242",
        "tgn:7016833",
        "tgn:1001225",
        "tgn:7029392"
    ],
    "tgn:id":7536472,
    "tgn:name":"Kafr ash Shinn\u0101w\u012b",
    "tgn:placetype":[
        "aat:300008347"
    ]
},
  "bbox": [],
  "geometry": {"coordinates":[31.696926,31.28875],"type":"Point"}
}