{
  "id": 2644851,
  "type": "Feature",
  "properties": {
    "tgn:hierarchy":[
        "tgn:2644851",
        "tgn:1000001",
        "tgn:7012149",
        "tgn:1002967",
        "tgn:7007520",
        "tgn:7029392"
    ],
    "tgn:id":2644851,
    "tgn:name":"Sassafras Lake",
    "tgn:placetype":[
        "aat:300008680"
    ]
},
  "bbox": [],
  "geometry": {"coordinates":[-86.1667,42.2333],"type":"Point"}
}