{
  "id": 2659848,
  "type": "Feature",
  "properties": {
    "tgn:hierarchy":[
        "tgn:2659848",
        "tgn:1000001",
        "tgn:2001427",
        "tgn:7012149",
        "tgn:7007564",
        "tgn:7029392"
    ],
    "tgn:id":2659848,
    "tgn:name":"Shipman Brook",
    "tgn:placetype":[
        "aat:300008699"
    ]
},
  "bbox": [],
  "geometry": {"coordinates":[-72.3167,43.55],"type":"Point"}
}