{
  "id": 7391098,
  "type": "Feature",
  "properties": {
    "tgn:hierarchy":[
        "tgn:7391098",
        "tgn:1000001",
        "tgn:7005589",
        "tgn:7005560",
        "tgn:7029392"
    ],
    "tgn:id":7391098,
    "tgn:name":"Rancho Chico",
    "tgn:placetype":[
        "aat:300008347"
    ]
},
  "bbox": [],
  "geometry": {"coordinates":[-99.916667,25.583333],"type":"Point"}
}