{
  "id": 7351764,
  "type": "Feature",
  "properties": {
    "tgn:hierarchy":[
        "tgn:7351764",
        "tgn:1000001",
        "tgn:7005599",
        "tgn:7005560",
        "tgn:7029392"
    ],
    "tgn:id":7351764,
    "tgn:name":"Arroyo del Diablo",
    "tgn:placetype":[
        "aat:300008347"
    ]
},
  "bbox": [],
  "geometry": {"coordinates":[-95.933333,18.866667],"type":"Point"}
}