{
  "id": 7571197,
  "type": "Feature",
  "properties": {
    "tgn:hierarchy":[
        "tgn:7571197",
        "tgn:1000004",
        "tgn:7000198",
        "tgn:7016788",
        "tgn:7029392"
    ],
    "tgn:id":7571197,
    "tgn:name:en":"Harn\u0101oda",
    "tgn:placetype":[
        "aat:300008347"
    ]
},
  "bbox": [],
  "geometry": {"coordinates":[76.708176,24.433406],"type":"Point"}
}