<<<<<<< HEAD
{
  "id": 7359238,
  "type": "Feature",
  "properties": {
    "tgn:hierarchy":[
        "tgn:7359238",
        "tgn:1000001",
        "tgn:7005601",
        "tgn:7005560",
        "tgn:7029392"
    ],
    "tgn:id":7359238,
    "tgn:name":"Divisadora, Cerro",
    "tgn:placetype":[
        "aat:300008795"
    ]
},
  "bbox": [],
  "geometry": {"coordinates":[-101.9,22.533333],"type":"Point"}
}
=======
{"geometry":{"type":"Point","coordinates":[-101.900000,22.533333]},"type":"Feature","properties":{"hierarchy":["tgn:7359238","tgn:1000001","tgn:7005601","tgn:7005560","tgn:7029392"],"placetype":["aat:300008795"],"id":7359238,"name:xx":"Divisadora, Cerro"}}
>>>>>>> 03f74aca74312dbeaf24d7e61306dd6a786dc3d0
