{
  "id": 7081457,
  "type": "Feature",
  "properties": {
    "tgn:hierarchy":[
        "tgn:7081457",
        "tgn:7000096",
        "tgn:1000003",
        "tgn:7000084",
        "tgn:7029392"
    ],
    "tgn:id":7081457,
    "tgn:name":"W\u00f6lmsdorf",
    "tgn:placetype":[
        "aat:300008347"
    ]
},
  "bbox": [],
  "geometry": {"coordinates":[12.966667,51.966667],"type":"Point"}
}