{
  "id": 7112730,
  "type": "Feature",
  "properties": {
    "tgn:hierarchy":[
        "tgn:7112730",
        "tgn:1000003",
        "tgn:7003677",
        "tgn:7000084",
        "tgn:7029392"
    ],
    "tgn:id":7112730,
    "tgn:name":"F\u00f6rsterei Roggenlager",
    "tgn:placetype":[
        "aat:300004792"
    ]
},
  "bbox": [],
  "geometry": {"coordinates":[6.233333,50.716667],"type":"Point"}
}