{
  "id": 2595663,
  "type": "Feature",
  "properties": {
    "tgn:hierarchy":[
        "tgn:2595663",
        "tgn:1000001",
        "tgn:7016172",
        "tgn:7012149",
        "tgn:2000168",
        "tgn:7029392"
    ],
    "tgn:id":2595663,
    "tgn:name":"Poteau River Site Nine Lake",
    "tgn:placetype":[
        "aat:300006191"
    ]
},
  "bbox": [],
  "geometry": {"coordinates":[-94.3167,34.9167],"type":"Point"}
}