{
  "id": 2552251,
  "type": "Feature",
  "properties": {
    "tgn:hierarchy":[
        "tgn:2552251",
        "tgn:1000001",
        "tgn:7012149",
        "tgn:1002961",
        "tgn:7007568",
        "tgn:7029392"
    ],
    "tgn:id":2552251,
    "tgn:name":"Number Ten Hollow",
    "tgn:placetype":[
        "aat:300008761"
    ]
},
  "bbox": [],
  "geometry": {"coordinates":[-74.5667,41.9833],"type":"Point"}
}