{
  "id": 2541210,
  "type": "Feature",
  "properties": {
    "tgn:hierarchy":[
        "tgn:2541210",
        "tgn:1000001",
        "tgn:1002209",
        "tgn:7012149",
        "tgn:7007252",
        "tgn:7029392"
    ],
    "tgn:id":2541210,
    "tgn:name":"Nickerson Hill",
    "tgn:placetype":[
        "aat:300008798"
    ]
},
  "bbox": [],
  "geometry": {"coordinates":[-86.1333,39.1167],"type":"Point"}
}