{
  "id": 7445983,
  "type": "Feature",
  "properties": {
    "tgn:hierarchy":[
        "tgn:7445983",
        "tgn:7002445",
        "tgn:1000003",
        "tgn:7008166",
        "tgn:7008591",
        "tgn:7029392"
    ],
    "tgn:id":7445983,
    "tgn:name:en":"Scarborough Rock",
    "tgn:placetype":[
        "aat:300386846"
    ]
},
  "bbox": [],
  "geometry": {"coordinates":[-0.384722,54.287222],"type":"Point"}
}