{
  "id": 2747545,
  "type": "Feature",
  "properties": {
    "tgn:hierarchy":[
        "tgn:2747545",
        "tgn:1002648",
        "tgn:1000001",
        "tgn:1008191",
        "tgn:7012149",
        "tgn:7007249",
        "tgn:7029392"
    ],
    "tgn:id":2747545,
    "tgn:name":"Waihuna",
    "tgn:placetype":[
        "aat:300008798"
    ]
},
  "bbox": [],
  "geometry": {"coordinates":[-157.1167,21.15],"type":"Point"}
}