<<<<<<< HEAD
{
  "id": 7247101,
  "type": "Feature",
  "properties": {
    "tgn:hierarchy":[
        "tgn:7247101",
        "tgn:7003457",
        "tgn:1000003",
        "tgn:1000063",
        "tgn:7018236",
        "tgn:7029392"
    ],
    "tgn:id":7247101,
    "tgn:name":"Daasdonk",
    "tgn:placetype":[
        "aat:300008347"
    ]
},
  "bbox": [],
  "geometry": {"coordinates":[3.649359,51.142544],"type":"Point"}
}
=======
{"geometry":{"type":"Point","coordinates":[3.649359,51.142544]},"type":"Feature","properties":{"hierarchy":["tgn:7247101","tgn:7003457","tgn:1000003","tgn:1000063","tgn:7018236","tgn:7029392"],"placetype":["aat:300008347"],"id":7247101,"name:xx":"Daasdonk"}}
>>>>>>> 03f74aca74312dbeaf24d7e61306dd6a786dc3d0
