{
  "id": 2213972,
  "type": "Feature",
  "properties": {
    "tgn:hierarchy":[
        "tgn:2213972",
        "tgn:1000001",
        "tgn:1002260",
        "tgn:7012149",
        "tgn:7007920",
        "tgn:7029392"
    ],
    "tgn:id":2213972,
    "tgn:name":"Cady Creek",
    "tgn:placetype":[
        "aat:300008706"
    ]
},
  "bbox": [],
  "geometry": {"coordinates":[-121.1333,47.95],"type":"Point"}
}