{
  "id": 2630420,
  "type": "Feature",
  "properties": {
    "tgn:hierarchy":[
        "tgn:2630420",
        "tgn:1000001",
        "tgn:7012149",
        "tgn:7007157",
        "tgn:1002861",
        "tgn:7029392"
    ],
    "tgn:id":2630420,
    "tgn:name":"Rough and Ready Island",
    "tgn:placetype":[
        "aat:300008791"
    ]
},
  "bbox": [],
  "geometry": {"coordinates":[-121.35,37.95],"type":"Point"}
}