{
  "id": 7225140,
  "type": "Feature",
  "properties": {
    "tgn:hierarchy":[
        "tgn:7225140",
        "tgn:4003773",
        "tgn:7001395",
        "tgn:1000003",
        "tgn:1000074",
        "tgn:7029392"
    ],
    "tgn:id":7225140,
    "tgn:name":"Rapt\u00f3poulon",
    "tgn:placetype":[
        "aat:300008347"
    ]
},
  "bbox": [],
  "geometry": {"coordinates":[21.480278,39.148611],"type":"Point"}
}