<<<<<<< HEAD
{
  "id": 2765090,
  "type": "Feature",
  "properties": {
    "tgn:hierarchy":[
        "tgn:2765090",
        "tgn:1000001",
        "tgn:2002105",
        "tgn:7012149",
        "tgn:7007827",
        "tgn:7029392"
    ],
    "tgn:id":2765090,
    "tgn:name":"Whisky Springs Draw",
    "tgn:placetype":[
        "aat:300008761"
    ]
},
  "bbox": [],
  "geometry": {"coordinates":[-109.1,40.9],"type":"Point"}
}
=======
{"geometry":{"type":"Point","coordinates":[-109.100000,40.900000]},"type":"Feature","properties":{"hierarchy":["tgn:2765090","tgn:1000001","tgn:2002105","tgn:7012149","tgn:7007827","tgn:7029392"],"placetype":["aat:300008761"],"id":2765090,"name:xx":"Whisky Springs Draw"}}
>>>>>>> 03f74aca74312dbeaf24d7e61306dd6a786dc3d0
