{
  "id": 2337842,
  "type": "Feature",
  "properties": {
    "tgn:hierarchy":[
        "tgn:2337842",
        "tgn:1000001",
        "tgn:7012149",
        "tgn:7007520",
        "tgn:7029392"
    ],
    "tgn:id":2337842,
    "tgn:name":"Fox Farm Creek",
    "tgn:placetype":[
        "aat:300008706"
    ]
},
  "bbox": [],
  "geometry": {"coordinates":[-88.4667,46.4167],"type":"Point"}
}