{
  "id": 7200970,
  "type": "Feature",
  "properties": {
    "tgn:hierarchy":[
        "tgn:7200970",
        "tgn:1000003",
        "tgn:7003676",
        "tgn:7000084",
        "tgn:7029392"
    ],
    "tgn:id":7200970,
    "tgn:name":"D\u00f6sehof",
    "tgn:placetype":[
        "aat:300000206"
    ]
},
  "bbox": [],
  "geometry": {"coordinates":[9.483333,53.633333],"type":"Point"}
}