{
  "id": 7037249,
  "type": "Feature",
  "properties": {
    "tgn:hierarchy":[
        "tgn:7037249",
        "tgn:7003139",
        "tgn:1000003",
        "tgn:7003080",
        "tgn:1000080",
        "tgn:7029392"
    ],
    "tgn:id":7037249,
    "tgn:name":"Valle Monda, Fosso",
    "tgn:placetype":[
        "aat:300008699"
    ]
},
  "bbox": [],
  "geometry": {"coordinates":[12.116667,42.533333],"type":"Point"}
}