{
  "id": 2305925,
  "type": "Feature",
  "properties": {
    "tgn:hierarchy":[
        "tgn:2305925",
        "tgn:2002308",
        "tgn:1000001",
        "tgn:7012149",
        "tgn:7007922",
        "tgn:7029392"
    ],
    "tgn:id":2305925,
    "tgn:name":"East Eightmile Lake",
    "tgn:placetype":[
        "aat:300008680"
    ]
},
  "bbox": [],
  "geometry": {"coordinates":[-91.45,46.4167],"type":"Point"}
}