{
  "id": 7171557,
  "type": "Feature",
  "properties": {
    "tgn:hierarchy":[
        "tgn:7171557",
        "tgn:7003669",
        "tgn:1000003",
        "tgn:7000084",
        "tgn:7029392"
    ],
    "tgn:id":7171557,
    "tgn:name":"Hilm",
    "tgn:placetype":[
        "aat:300008347"
    ]
},
  "bbox": [],
  "geometry": {"coordinates":[12.833333,48.983333],"type":"Point"}
}