{
  "id": 7577096,
  "type": "Feature",
  "properties": {
    "tgn:hierarchy":[
        "tgn:7577096",
        "tgn:1000004",
        "tgn:7000198",
        "tgn:7001797",
        "tgn:7029392"
    ],
    "tgn:id":7577096,
    "tgn:name:en":"Kovil\u016br",
    "tgn:placetype":[
        "aat:300008347"
    ]
},
  "bbox": [],
  "geometry": {"coordinates":[78.75,10.083333],"type":"Point"}
}