{
  "id": 1011395,
  "type": "Feature",
  "properties": {
    "tgn:hierarchy":[
        "tgn:1011395",
        "tgn:1008047",
        "tgn:1001407",
        "tgn:1000233",
        "tgn:1000006",
        "tgn:7029392"
    ],
    "tgn:id":1011395,
    "tgn:name":"Zelee, Cape",
    "tgn:placetype":[
        "aat:300008850"
    ]
},
  "bbox": [],
  "geometry": {"coordinates":[161.5667,-9.75],"type":"Point"}
}