{
  "id": 2293199,
  "type": "Feature",
  "properties": {
    "tgn:hierarchy":[
        "tgn:2293199",
        "tgn:1000001",
        "tgn:7012149",
        "tgn:2001762",
        "tgn:7007712",
        "tgn:7029392"
    ],
    "tgn:id":2293199,
    "tgn:name":"Double Branch",
    "tgn:placetype":[
        "aat:300008699"
    ]
},
  "bbox": [],
  "geometry": {"coordinates":[-81.0333,33.5167],"type":"Point"}
}