{
  "id": 7551024,
  "type": "Feature",
  "properties": {
    "tgn:hierarchy":[
        "tgn:7551024",
        "tgn:1000004",
        "tgn:7000198",
        "tgn:7016722",
        "tgn:7029392"
    ],
    "tgn:id":7551024,
    "tgn:name:en":"Dankaur",
    "tgn:placetype":[
        "aat:300008347"
    ]
},
  "bbox": [],
  "geometry": {"coordinates":[77.553446,28.350473],"type":"Point"}
}