<<<<<<< HEAD
{
  "id": 2157679,
  "type": "Feature",
  "properties": {
    "tgn:hierarchy":[
        "tgn:2157679",
        "tgn:1000001",
        "tgn:7012149",
        "tgn:1002590",
        "tgn:7007826",
        "tgn:7029392"
    ],
    "tgn:id":2157679,
    "tgn:name":"Beaver Dam Marsh",
    "tgn:placetype":[
        "aat:300008905"
    ]
},
  "bbox": [],
  "geometry": {"coordinates":[-95.7833,31.2833],"type":"Point"}
}
=======
{"geometry":{"type":"Point","coordinates":[-95.783300,31.283300]},"type":"Feature","properties":{"hierarchy":["tgn:2157679","tgn:1000001","tgn:7012149","tgn:1002590","tgn:7007826","tgn:7029392"],"placetype":["aat:300008905"],"id":2157679,"name:xx":"Beaver Dam Marsh"}}
>>>>>>> 03f74aca74312dbeaf24d7e61306dd6a786dc3d0
