{
  "id": 2757742,
  "type": "Feature",
  "properties": {
    "tgn:hierarchy":[
        "tgn:2757742",
        "tgn:1000001",
        "tgn:2001264",
        "tgn:7012149",
        "tgn:7007524",
        "tgn:7029392"
    ],
    "tgn:id":2757742,
    "tgn:name":"West Branch Finn Ditch",
    "tgn:placetype":[
        "aat:300006075"
    ]
},
  "bbox": [],
  "geometry": {"coordinates":[-109.2167,45.3667],"type":"Point"}
}