{
  "id": 2176111,
  "type": "Feature",
  "properties": {
    "tgn:hierarchy":[
        "tgn:2176111",
        "tgn:1000001",
        "tgn:7012149",
        "tgn:7007919",
        "tgn:7029392"
    ],
    "tgn:id":2176111,
    "tgn:name":"Black Haw Branch",
    "tgn:placetype":[
        "aat:300008699"
    ]
},
  "bbox": [],
  "geometry": {"coordinates":[-77.5833,37.7167],"type":"Point"}
}