{
  "id": 7275373,
  "type": "Feature",
  "properties": {
    "tgn:hierarchy":[
        "tgn:7275373",
        "tgn:1001692",
        "tgn:1000049",
        "tgn:1000002",
        "tgn:7029392"
    ],
    "tgn:id":7275373,
    "tgn:name":"Tumarcuicui, Estero",
    "tgn:placetype":[
        "aat:300008699"
    ]
},
  "bbox": [],
  "geometry": {"coordinates":[-72.433333,-38.083333],"type":"Point"}
}