{
  "id": 2250101,
  "type": "Feature",
  "properties": {
    "tgn:hierarchy":[
        "tgn:2250101",
        "tgn:1000001",
        "tgn:7012149",
        "tgn:7007709",
        "tgn:7029392"
    ],
    "tgn:id":2250101,
    "tgn:name":"Collins Creek",
    "tgn:placetype":[
        "aat:300008706"
    ]
},
  "bbox": [],
  "geometry": {"coordinates":[-79.1667,35.9667],"type":"Point"}
}