{
  "id": 7497955,
  "type": "Feature",
  "properties": {
    "tgn:hierarchy":[
        "tgn:7497955",
        "tgn:7001004",
        "tgn:1000004",
        "tgn:1000141",
        "tgn:7029392"
    ],
    "tgn:id":7497955,
    "tgn:name":"Zhongdao Zhan",
    "tgn:placetype":[
        "aat:300007783"
    ]
},
  "bbox": [],
  "geometry": {"coordinates":[120.299737,22.589998],"type":"Point"}
}