{
  "id": 2618163,
  "type": "Feature",
  "properties": {
    "tgn:hierarchy":[
        "tgn:2618163",
        "tgn:1000001",
        "tgn:7012149",
        "tgn:2002294",
        "tgn:7013961",
        "tgn:7029392"
    ],
    "tgn:id":2618163,
    "tgn:name":"Riffe",
    "tgn:placetype":[
        "aat:300008347"
    ]
},
  "bbox": [],
  "geometry": {"coordinates":[-80.6833,37.6667],"type":"Point"}
}