{
  "id": 7590837,
  "type": "Feature",
  "properties": {
    "tgn:hierarchy":[
        "tgn:7590837",
        "tgn:1000004",
        "tgn:7000198",
        "tgn:7000799",
        "tgn:7029392"
    ],
    "tgn:id":7590837,
    "tgn:name:en":"N\u016brpur",
    "tgn:placetype":[
        "aat:300008699"
    ]
},
  "bbox": [],
  "geometry": {"coordinates":[74.427778,33.793056],"type":"Point"}
}