{
  "id": 7493406,
  "type": "Feature",
  "properties": {
    "tgn:hierarchy":[
        "tgn:7493406",
        "tgn:1000004",
        "tgn:1000454",
        "tgn:1000141",
        "tgn:7029392"
    ],
    "tgn:id":7493406,
    "tgn:name":"Sanchenghu",
    "tgn:placetype":[
        "aat:300008347"
    ]
},
  "bbox": [],
  "geometry": {"coordinates":[121.482406,24.945968],"type":"Point"}
}