{
  "id": 2227456,
  "type": "Feature",
  "properties": {
    "tgn:hierarchy":[
        "tgn:2227456",
        "tgn:7002659",
        "tgn:1000001",
        "tgn:7012149",
        "tgn:2000051",
        "tgn:7029392"
    ],
    "tgn:id":2227456,
    "tgn:name":"Cave Spring Cave",
    "tgn:placetype":[
        "aat:300008746"
    ]
},
  "bbox": [],
  "geometry": {"coordinates":[-86.85,34.5333],"type":"Point"}
}