{
  "id": 1069191,
  "type": "Feature",
  "properties": {
    "tgn:hierarchy":[
        "tgn:1069191",
        "tgn:1000004",
        "tgn:7002076",
        "tgn:1000111",
        "tgn:7029392"
    ],
    "tgn:id":1069191,
    "tgn:name":"Jianqiao",
    "tgn:placetype":[
        "aat:300008347"
    ]
},
  "bbox": [],
  "geometry": {"coordinates":[120.2167,30.2833],"type":"Point"}
}