{
  "id": 2423732,
  "type": "Feature",
  "properties": {
    "tgn:hierarchy":[
        "tgn:2423732",
        "tgn:1000001",
        "tgn:7012149",
        "tgn:2001714",
        "tgn:7007708",
        "tgn:7029392"
    ],
    "tgn:id":2423732,
    "tgn:name":"John Spring",
    "tgn:placetype":[
        "aat:300008697"
    ]
},
  "bbox": [],
  "geometry": {"coordinates":[-121.2667,42.35],"type":"Point"}
}