<<<<<<< HEAD
{
  "id": 7056294,
  "type": "Feature",
  "properties": {
    "tgn:hierarchy":[
        "tgn:7056294",
        "tgn:7003171",
        "tgn:1000003",
        "tgn:7003125",
        "tgn:1000080",
        "tgn:7029392"
    ],
    "tgn:id":7056294,
    "tgn:name":"Piloni",
    "tgn:placetype":[
        "aat:300008347"
    ]
},
  "bbox": [],
  "geometry": {"coordinates":[12.533333,42.416667],"type":"Point"}
}
=======
{"geometry":{"type":"Point","coordinates":[12.533333,42.416667]},"type":"Feature","properties":{"hierarchy":["tgn:7056294","tgn:7003171","tgn:1000003","tgn:7003125","tgn:1000080","tgn:7029392"],"placetype":["aat:300008347"],"id":7056294,"name:xx":"Piloni"}}
>>>>>>> 03f74aca74312dbeaf24d7e61306dd6a786dc3d0
