{
  "id": 2466766,
  "type": "Feature",
  "properties": {
    "tgn:hierarchy":[
        "tgn:2466766",
        "tgn:1000001",
        "tgn:7012149",
        "tgn:7021748",
        "tgn:7007826",
        "tgn:7029392"
    ],
    "tgn:id":2466766,
    "tgn:name":"Long Branch",
    "tgn:placetype":[
        "aat:300008699"
    ]
},
  "bbox": [],
  "geometry": {"coordinates":[-97.4167,31.6167],"type":"Point"}
}