{
  "id": 7396804,
  "type": "Feature",
  "properties": {
    "tgn:hierarchy":[
        "tgn:7396804",
        "tgn:1001853",
        "tgn:1000001",
        "tgn:7005560",
        "tgn:7029392"
    ],
    "tgn:id":7396804,
    "tgn:name":"Hacienda Santa Rita de Agua Verde",
    "tgn:placetype":[
        "aat:300000241"
    ]
},
  "bbox": [],
  "geometry": {"coordinates":[-101.45,25.15],"type":"Point"}
}