{
  "id": 7393730,
  "type": "Feature",
  "properties": {
    "tgn:hierarchy":[
        "tgn:7393730",
        "tgn:7005583",
        "tgn:1000001",
        "tgn:7005560",
        "tgn:7029392"
    ],
    "tgn:id":7393730,
    "tgn:name":"San Jos\u00e9",
    "tgn:placetype":[
        "aat:300008347"
    ]
},
  "bbox": [],
  "geometry": {"coordinates":[-102.783333,24.716667],"type":"Point"}
}