{
  "id": 7116943,
  "type": "Feature",
  "properties": {
    "tgn:hierarchy":[
        "tgn:7116943",
        "tgn:7003669",
        "tgn:1000003",
        "tgn:7000084",
        "tgn:7029392"
    ],
    "tgn:id":7116943,
    "tgn:name":"Oeschle",
    "tgn:placetype":[
        "aat:300000206"
    ]
},
  "bbox": [],
  "geometry": {"coordinates":[10.333333,47.816667],"type":"Point"}
}