{
  "id": 2190292,
  "type": "Feature",
  "properties": {
    "tgn:hierarchy":[
        "tgn:2190292",
        "tgn:1000001",
        "tgn:7012149",
        "tgn:7007158",
        "tgn:2000248",
        "tgn:7029392"
    ],
    "tgn:id":2190292,
    "tgn:name":"Box Canyon",
    "tgn:placetype":[
        "aat:300008761"
    ]
},
  "bbox": [],
  "geometry": {"coordinates":[-108.7333,37.9333],"type":"Point"}
}