{
  "id": 7320530,
  "type": "Feature",
  "properties": {
    "tgn:hierarchy":[
        "tgn:7320530",
        "tgn:1001657",
        "tgn:1000049",
        "tgn:1000002",
        "tgn:7029392"
    ],
    "tgn:id":7320530,
    "tgn:name":"Canela",
    "tgn:placetype":[
        "aat:300008347"
    ]
},
  "bbox": [],
  "geometry": {"coordinates":[-70.85,-31.583333],"type":"Point"}
}