{
  "id": 1050019,
  "type": "Feature",
  "properties": {
    "tgn:hierarchy":[
        "tgn:1050019",
        "tgn:1000003",
        "tgn:1000461",
        "tgn:1000091",
        "tgn:7029392"
    ],
    "tgn:id":1050019,
    "tgn:name":"Babadag",
    "tgn:placetype":[
        "aat:300008347"
    ]
},
  "bbox": [],
  "geometry": {"coordinates":[28.7833,44.8833],"type":"Point"}
}