{
  "id": 2133207,
  "type": "Feature",
  "properties": {
    "tgn:hierarchy":[
        "tgn:2133207",
        "tgn:1000001",
        "tgn:2002318",
        "tgn:7012149",
        "tgn:7007922",
        "tgn:7029392"
    ],
    "tgn:id":2133207,
    "tgn:name":"Anderson Lake",
    "tgn:placetype":[
        "aat:300008680"
    ]
},
  "bbox": [],
  "geometry": {"coordinates":[-91.6833,46.45],"type":"Point"}
}