<<<<<<< HEAD
{
  "id": 7364133,
  "type": "Feature",
  "properties": {
    "tgn:hierarchy":[
        "tgn:7364133",
        "tgn:1000001",
        "tgn:7005589",
        "tgn:7005560",
        "tgn:7029392"
    ],
    "tgn:id":7364133,
    "tgn:name":"Rancho El Barro",
    "tgn:placetype":[
        "aat:300000241"
    ]
},
  "bbox": [],
  "geometry": {"coordinates":[-99.836667,24.018333],"type":"Point"}
}
=======
{"geometry":{"type":"Point","coordinates":[-99.836667,24.018333]},"type":"Feature","properties":{"hierarchy":["tgn:7364133","tgn:1000001","tgn:7005589","tgn:7005560","tgn:7029392"],"placetype":["aat:300000241"],"id":7364133,"name:xx":"Rancho El Barro"}}
>>>>>>> 03f74aca74312dbeaf24d7e61306dd6a786dc3d0
