{
  "id": 7534789,
  "type": "Feature",
  "properties": {
    "tgn:hierarchy":[
        "tgn:7534789",
        "tgn:7001242",
        "tgn:7001311",
        "tgn:7016833",
        "tgn:7029392"
    ],
    "tgn:id":7534789,
    "tgn:name:en":"Kadab\u016brah al \u1e28amr\u0101', Jabal",
    "tgn:placetype":[
        "aat:300008795"
    ]
},
  "bbox": [],
  "geometry": {"coordinates":[34.446118,25.444261],"type":"Point"}
}