{
  "id": 2513870,
  "type": "Feature",
  "properties": {
    "tgn:hierarchy":[
        "tgn:2513870",
        "tgn:1000001",
        "tgn:7012149",
        "tgn:2001881",
        "tgn:7007825",
        "tgn:7029392"
    ],
    "tgn:id":2513870,
    "tgn:name":"Mill Spring",
    "tgn:placetype":[
        "aat:300008697"
    ]
},
  "bbox": [],
  "geometry": {"coordinates":[-83.5167,36.15],"type":"Point"}
}