{
  "id": 2470626,
  "type": "Feature",
  "properties": {
    "tgn:hierarchy":[
        "tgn:2470626",
        "tgn:1000001",
        "tgn:7012149",
        "tgn:7007157",
        "tgn:1002858",
        "tgn:7029392"
    ],
    "tgn:id":2470626,
    "tgn:name":"Los Terrentos",
    "tgn:placetype":[
        "aat:300008347"
    ]
},
  "bbox": [],
  "geometry": {"coordinates":[-116.6167,32.8333],"type":"Point"}
}