{
  "id": 2266256,
  "type": "Feature",
  "properties": {
    "tgn:hierarchy":[
        "tgn:2266256",
        "tgn:1000001",
        "tgn:7012149",
        "tgn:2000784",
        "tgn:7007255",
        "tgn:7029392"
    ],
    "tgn:id":2266256,
    "tgn:name":"Crayne Knob",
    "tgn:placetype":[
        "aat:300008798"
    ]
},
  "bbox": [],
  "geometry": {"coordinates":[-88.0667,37.25],"type":"Point"}
}