{
  "id": 2168220,
  "type": "Feature",
  "properties": {
    "tgn:hierarchy":[
        "tgn:2168220",
        "tgn:1000001",
        "tgn:7012149",
        "tgn:2002250",
        "tgn:7007920",
        "tgn:7029392"
    ],
    "tgn:id":2168220,
    "tgn:name":"Big Foot Valley",
    "tgn:placetype":[
        "aat:300008761"
    ]
},
  "bbox": [],
  "geometry": {"coordinates":[-117.6333,47.9667],"type":"Point"}
}