{
  "id": 2635970,
  "type": "Feature",
  "properties": {
    "tgn:hierarchy":[
        "tgn:2635970",
        "tgn:1000001",
        "tgn:7012149",
        "tgn:2000383",
        "tgn:7007248",
        "tgn:7029392"
    ],
    "tgn:id":2635970,
    "tgn:name":"Saddle Bags Pond",
    "tgn:placetype":[
        "aat:300008680"
    ]
},
  "bbox": [],
  "geometry": {"coordinates":[-83.2167,30.6667],"type":"Point"}
}