{
  "id": 2565716,
  "type": "Feature",
  "properties": {
    "tgn:hierarchy":[
        "tgn:2565716",
        "tgn:1000001",
        "tgn:2001705",
        "tgn:7012149",
        "tgn:7007708",
        "tgn:7029392"
    ],
    "tgn:id":2565716,
    "tgn:name":"Palanush Butte",
    "tgn:placetype":[
        "aat:300008798"
    ]
},
  "bbox": [],
  "geometry": {"coordinates":[-121.7333,43.7667],"type":"Point"}
}