{
  "id": 2265052,
  "type": "Feature",
  "properties": {
    "tgn:hierarchy":[
        "tgn:2265052",
        "tgn:1000001",
        "tgn:7012149",
        "tgn:7007710",
        "tgn:7029392"
    ],
    "tgn:id":2265052,
    "tgn:name":"Cranberry Glade Run",
    "tgn:placetype":[
        "aat:300008699"
    ]
},
  "bbox": [],
  "geometry": {"coordinates":[-79.3833,39.9167],"type":"Point"}
}