{
  "id": 2129384,
  "type": "Feature",
  "properties": {
    "tgn:hierarchy":[
        "tgn:2129384",
        "tgn:1000001",
        "tgn:7012149",
        "tgn:7007157",
        "tgn:1002621",
        "tgn:7029392"
    ],
    "tgn:id":2129384,
    "tgn:name":"Aliso Canal",
    "tgn:placetype":[
        "aat:300006075"
    ]
},
  "bbox": [],
  "geometry": {"coordinates":[-120.25,36.85],"type":"Point"}
}