{
  "id": 7592326,
  "type": "Feature",
  "properties": {
    "tgn:hierarchy":[
        "tgn:7592326",
        "tgn:1000004",
        "tgn:7000198",
        "tgn:7000799",
        "tgn:7029392"
    ],
    "tgn:id":7592326,
    "tgn:name:en":"Gujr\u0101l",
    "tgn:placetype":[
        "aat:300008347"
    ]
},
  "bbox": [],
  "geometry": {"coordinates":[74.811111,32.729941],"type":"Point"}
}