<<<<<<< HEAD
{
  "id": 7350091,
  "type": "Feature",
  "properties": {
    "tgn:hierarchy":[
        "tgn:7350091",
        "tgn:1000001",
        "tgn:7005599",
        "tgn:7005560",
        "tgn:7029392"
    ],
    "tgn:id":7350091,
    "tgn:name":"Agayata",
    "tgn:placetype":[
        "aat:300008347"
    ]
},
  "bbox": [],
  "geometry": {"coordinates":[-95.0,18.4],"type":"Point"}
}
=======
{"geometry":{"type":"Point","coordinates":[-95.000000,18.400000]},"type":"Feature","properties":{"hierarchy":["tgn:7350091","tgn:1000001","tgn:7005599","tgn:7005560","tgn:7029392"],"placetype":["aat:300008347"],"id":7350091,"name:xx":"Agayata"}}
>>>>>>> 03f74aca74312dbeaf24d7e61306dd6a786dc3d0
