{
  "id": 1134050,
  "type": "Feature",
  "properties": {
    "tgn:hierarchy":[
        "tgn:1134050",
        "tgn:1000001",
        "tgn:7012149",
        "tgn:7007568",
        "tgn:7029392"
    ],
    "tgn:id":1134050,
    "tgn:name":"Oneida Creek",
    "tgn:placetype":[
        "aat:300008706"
    ]
},
  "bbox": [],
  "geometry": {"coordinates":[-75.6667,42.9833],"type":"Point"}
}