{
  "id": 7031374,
  "type": "Feature",
  "properties": {
    "tgn:hierarchy":[
        "tgn:7031374",
        "tgn:7002445",
        "tgn:1000003",
        "tgn:7008168",
        "tgn:7008591",
        "tgn:7029392"
    ],
    "tgn:id":7031374,
    "tgn:name":"Westcott Barton",
    "tgn:placetype":[
        "aat:300008347",
        "aat:300008372"
    ]
},
  "bbox": [],
  "geometry": {"coordinates":[-1.389,51.918],"type":"Point"}
}