{
  "id": 7517380,
  "type": "Feature",
  "properties": {
    "tgn:hierarchy":[
        "tgn:7517380",
        "tgn:1009227",
        "tgn:7001866",
        "tgn:1000226",
        "tgn:1000006",
        "tgn:7029392"
    ],
    "tgn:id":7517380,
    "tgn:name:en":"Nonoti",
    "tgn:placetype":[
        "aat:300007783"
    ]
},
  "bbox": [],
  "geometry": {"coordinates":[173.216667,-42.833333],"type":"Point"}
}