{
  "id": 1129238,
  "type": "Feature",
  "properties": {
    "tgn:hierarchy":[
        "tgn:1129238",
        "tgn:1000003",
        "tgn:1000063",
        "tgn:7029392"
    ],
    "tgn:id":1129238,
    "tgn:name":"Rupel",
    "tgn:placetype":[
        "aat:300008707"
    ]
},
  "bbox": [],
  "geometry": {"coordinates":[4.3167,51.1167],"type":"Point"}
}