<<<<<<< HEAD
{
  "id": 7056719,
  "type": "Feature",
  "properties": {
    "tgn:hierarchy":[
        "tgn:7056719",
        "tgn:7003154",
        "tgn:1000003",
        "tgn:7003120",
        "tgn:1000080",
        "tgn:7029392"
    ],
    "tgn:id":7056719,
    "tgn:name":"Berzano San Pietro",
    "tgn:placetype":[
        "aat:300008347"
    ]
},
  "bbox": [],
  "geometry": {"coordinates":[7.95,45.1],"type":"Point"}
}
=======
{"geometry":{"type":"Point","coordinates":[7.950000,45.100000]},"type":"Feature","properties":{"hierarchy":["tgn:7056719","tgn:7003154","tgn:1000003","tgn:7003120","tgn:1000080","tgn:7029392"],"placetype":["aat:300008347"],"id":7056719,"name:xx":"Berzano San Pietro"}}
>>>>>>> 03f74aca74312dbeaf24d7e61306dd6a786dc3d0
