{
  "id": 2588818,
  "type": "Feature",
  "properties": {
    "tgn:hierarchy":[
        "tgn:2588818",
        "tgn:1000001",
        "tgn:7012149",
        "tgn:7007157",
        "tgn:7014004",
        "tgn:7029392"
    ],
    "tgn:id":2588818,
    "tgn:name":"Pocahontas Mine",
    "tgn:placetype":[
        "aat:300000390"
    ]
},
  "bbox": [],
  "geometry": {"coordinates":[-120.05,37.3333],"type":"Point"}
}