{
  "id": 7288772,
  "type": "Feature",
  "properties": {
    "tgn:hierarchy":[
        "tgn:7288772",
        "tgn:1001695",
        "tgn:1000049",
        "tgn:1000002",
        "tgn:7029392"
    ],
    "tgn:id":7288772,
    "tgn:name":"La Calera",
    "tgn:placetype":[
        "aat:300000206"
    ]
},
  "bbox": [],
  "geometry": {"coordinates":[-71.333333,-34.733333],"type":"Point"}
}