{
  "id": 7234972,
  "type": "Feature",
  "properties": {
    "tgn:hierarchy":[
        "tgn:7234972",
        "tgn:7002743",
        "tgn:7017076",
        "tgn:1000003",
        "tgn:1000074",
        "tgn:7029392"
    ],
    "tgn:id":7234972,
    "tgn:name":"Fr\u00e1nga",
    "tgn:placetype":[
        "aat:300008347"
    ]
},
  "bbox": [],
  "geometry": {"coordinates":[21.483333,38.083333],"type":"Point"}
}