{
  "id": 2101888,
  "type": "Feature",
  "properties": {
    "tgn:hierarchy":[
        "tgn:2101888",
        "tgn:1000001",
        "tgn:7012149",
        "tgn:2001843",
        "tgn:7007825",
        "tgn:7029392"
    ],
    "tgn:id":2101888,
    "tgn:name":"Turley",
    "tgn:placetype":[
        "aat:300008347",
        "aat:300387210"
    ]
},
  "bbox": [],
  "geometry": {"coordinates":[-84.2667,36.3667],"type":"Point"}
}