{
  "id": 2426622,
  "type": "Feature",
  "properties": {
    "tgn:hierarchy":[
        "tgn:2426622",
        "tgn:1000001",
        "tgn:7012149",
        "tgn:2001508",
        "tgn:7007709",
        "tgn:7029392"
    ],
    "tgn:id":2426622,
    "tgn:name":"Jones Knob",
    "tgn:placetype":[
        "aat:300008798"
    ]
},
  "bbox": [],
  "geometry": {"coordinates":[-83.2667,35.2667],"type":"Point"}
}