{
  "id": 7581613,
  "type": "Feature",
  "properties": {
    "tgn:hierarchy":[
        "tgn:7581613",
        "tgn:1000004",
        "tgn:7000198",
        "tgn:1001894",
        "tgn:7029392"
    ],
    "tgn:id":7581613,
    "tgn:name:en":"T\u0101jpur",
    "tgn:placetype":[
        "aat:300008347"
    ]
},
  "bbox": [],
  "geometry": {"coordinates":[75.903167,23.225603],"type":"Point"}
}