{
  "id": 1049847,
  "type": "Feature",
  "properties": {
    "tgn:hierarchy":[
        "tgn:1049847",
        "tgn:1000882",
        "tgn:1000003",
        "tgn:1000090",
        "tgn:7029392"
    ],
    "tgn:id":1049847,
    "tgn:name":"Mortal",
    "tgn:placetype":[
        "aat:300008347"
    ]
},
  "bbox": [],
  "geometry": {"coordinates":[-9.36,38.705],"type":"Point"}
}