{
  "id": 2496231,
  "type": "Feature",
  "properties": {
    "tgn:hierarchy":[
        "tgn:2496231",
        "tgn:7006450",
        "tgn:1000001",
        "tgn:7012149",
        "tgn:2000089",
        "tgn:7029392"
    ],
    "tgn:id":2496231,
    "tgn:name":"Mastodon Dome",
    "tgn:placetype":[
        "aat:300008798"
    ]
},
  "bbox": [],
  "geometry": {"coordinates":[-145.3333,65.4167],"type":"Point"}
}