{
  "id": 7568999,
  "type": "Feature",
  "properties": {
    "tgn:hierarchy":[
        "tgn:7568999",
        "tgn:1000004",
        "tgn:7000198",
        "tgn:1001996",
        "tgn:7029392"
    ],
    "tgn:id":7568999,
    "tgn:name:en":"Sharog Protected Forest",
    "tgn:placetype":[
        "aat:300008863"
    ]
},
  "bbox": [],
  "geometry": {"coordinates":[77.098889,31.152222],"type":"Point"}
}