{
  "id": 7492377,
  "type": "Feature",
  "properties": {
    "tgn:hierarchy":[
        "tgn:7492377",
        "tgn:7001004",
        "tgn:1000004",
        "tgn:1000141",
        "tgn:7029392"
    ],
    "tgn:id":7492377,
    "tgn:name":"Tanshuiyan Shan",
    "tgn:placetype":[
        "aat:300008777"
    ]
},
  "bbox": [],
  "geometry": {"coordinates":[120.580746,22.933063],"type":"Point"}
}