{
  "id": 7147605,
  "type": "Feature",
  "properties": {
    "tgn:hierarchy":[
        "tgn:7147605",
        "tgn:1000003",
        "tgn:7003687",
        "tgn:7000084",
        "tgn:7029392"
    ],
    "tgn:id":7147605,
    "tgn:name":"Kr\u00e4hen-Berg",
    "tgn:placetype":[
        "aat:300008777"
    ]
},
  "bbox": [],
  "geometry": {"coordinates":[10.85,51.783333],"type":"Point"}
}