{
  "id": 2138798,
  "type": "Feature",
  "properties": {
    "tgn:hierarchy":[
        "tgn:2138798",
        "tgn:1000001",
        "tgn:7012149",
        "tgn:2000182",
        "tgn:7007157",
        "tgn:7029392"
    ],
    "tgn:id":2138798,
    "tgn:name":"Ash Thirtyfour Drain",
    "tgn:placetype":[
        "aat:300006075"
    ]
},
  "bbox": [],
  "geometry": {"coordinates":[-115.4167,32.7667],"type":"Point"}
}