{
  "id": 2610321,
  "type": "Feature",
  "properties": {
    "tgn:hierarchy":[
        "tgn:2610321",
        "tgn:1000001",
        "tgn:2001472",
        "tgn:7012149",
        "tgn:7007709",
        "tgn:7029392"
    ],
    "tgn:id":2610321,
    "tgn:name":"Red Bug",
    "tgn:placetype":[
        "aat:300008347"
    ]
},
  "bbox": [],
  "geometry": {"coordinates":[-78.3667,33.9667],"type":"Point"}
}