{
  "id": 2323427,
  "type": "Feature",
  "properties": {
    "tgn:hierarchy":[
        "tgn:2323427",
        "tgn:1000001",
        "tgn:7012149",
        "tgn:7007158",
        "tgn:2000250",
        "tgn:7029392"
    ],
    "tgn:id":2323427,
    "tgn:name":"Farncomb Hill",
    "tgn:placetype":[
        "aat:300008798"
    ]
},
  "bbox": [],
  "geometry": {"coordinates":[-105.95,39.4667],"type":"Point"}
}