{
  "id": 7206287,
  "type": "Feature",
  "properties": {
    "tgn:hierarchy":[
        "tgn:7206287",
        "tgn:7000096",
        "tgn:1000003",
        "tgn:7000084",
        "tgn:7029392"
    ],
    "tgn:id":7206287,
    "tgn:name":"Buckau",
    "tgn:placetype":[
        "aat:300008347"
    ]
},
  "bbox": [],
  "geometry": {"coordinates":[13.166667,51.666667],"type":"Point"}
}