{
  "id": 7206731,
  "type": "Feature",
  "properties": {
    "tgn:hierarchy":[
        "tgn:7206731",
        "tgn:7003692",
        "tgn:1000003",
        "tgn:7000084",
        "tgn:7029392"
    ],
    "tgn:id":7206731,
    "tgn:name":"Buchmannshof",
    "tgn:placetype":[
        "aat:300000206"
    ]
},
  "bbox": [],
  "geometry": {"coordinates":[9.85,47.816667],"type":"Point"}
}