{
  "id": 1132500,
  "type": "Feature",
  "properties": {
    "tgn:hierarchy":[
        "tgn:1132500",
        "tgn:1000001",
        "tgn:7012149",
        "tgn:7007520",
        "tgn:7029392"
    ],
    "tgn:id":1132500,
    "tgn:name":"Black Creek",
    "tgn:placetype":[
        "aat:300008706"
    ]
},
  "bbox": [],
  "geometry": {"coordinates":[-86.0167,44.05],"type":"Point"}
}