<<<<<<< HEAD
{
  "id": 2339933,
  "type": "Feature",
  "properties": {
    "tgn:hierarchy":[
        "tgn:2339933",
        "tgn:1000001",
        "tgn:7012149",
        "tgn:7007157",
        "tgn:2000189",
        "tgn:7029392"
    ],
    "tgn:id":2339933,
    "tgn:name":"Freeman Springs",
    "tgn:placetype":[
        "aat:300008697"
    ]
},
  "bbox": [],
  "geometry": {"coordinates":[-122.3167,41.9333],"type":"Point"}
}
=======
{"geometry":{"type":"Point","coordinates":[-122.316700,41.933300]},"type":"Feature","properties":{"hierarchy":["tgn:2339933","tgn:1000001","tgn:7012149","tgn:7007157","tgn:2000189","tgn:7029392"],"placetype":["aat:300008697"],"id":2339933,"name:xx":"Freeman Springs"}}
>>>>>>> 03f74aca74312dbeaf24d7e61306dd6a786dc3d0
