{
  "id": 2486237,
  "type": "Feature",
  "properties": {
    "tgn:hierarchy":[
        "tgn:2486237",
        "tgn:1000001",
        "tgn:2001429",
        "tgn:7012149",
        "tgn:7007566",
        "tgn:7029392"
    ],
    "tgn:id":2486237,
    "tgn:name":"Leap Year Lode",
    "tgn:placetype":[
        "aat:300000390"
    ]
},
  "bbox": [],
  "geometry": {"coordinates":[-108.7833,33.4167],"type":"Point"}
}