{
  "id": 1096733,
  "type": "Feature",
  "properties": {
    "tgn:hierarchy":[
        "tgn:1096733",
        "tgn:7000490",
        "tgn:1000006",
        "tgn:7001834",
        "tgn:7029392"
    ],
    "tgn:id":1096733,
    "tgn:name":"De Grey",
    "tgn:placetype":[
        "aat:300008347"
    ]
},
  "bbox": [],
  "geometry": {"coordinates":[119.15,-20.1667],"type":"Point"}
}