{
  "id": 7379807,
  "type": "Feature",
  "properties": {
    "tgn:hierarchy":[
        "tgn:7379807",
        "tgn:7005583",
        "tgn:1000001",
        "tgn:7005560",
        "tgn:7029392"
    ],
    "tgn:id":7379807,
    "tgn:name":"Mart\u00ednez",
    "tgn:placetype":[
        "aat:300008347"
    ]
},
  "bbox": [],
  "geometry": {"coordinates":[-104.433333,22.866667],"type":"Point"}
}