<<<<<<< HEAD
{
  "id": 7050167,
  "type": "Feature",
  "properties": {
    "tgn:hierarchy":[
        "tgn:7050167",
        "tgn:1001643",
        "tgn:1000003",
        "tgn:7003122",
        "tgn:1000080",
        "tgn:7029392"
    ],
    "tgn:id":7050167,
    "tgn:name":"La Torre",
    "tgn:placetype":[
        "aat:300008347"
    ]
},
  "bbox": [],
  "geometry": {"coordinates":[14.183333,37.25],"type":"Point"}
}
=======
{"geometry":{"type":"Point","coordinates":[14.183333,37.250000]},"type":"Feature","properties":{"hierarchy":["tgn:7050167","tgn:1001643","tgn:1000003","tgn:7003122","tgn:1000080","tgn:7029392"],"placetype":["aat:300008347"],"id":7050167,"name:xx":"La Torre"}}
>>>>>>> 03f74aca74312dbeaf24d7e61306dd6a786dc3d0
