{
  "id": 7048298,
  "type": "Feature",
  "properties": {
    "tgn:hierarchy":[
        "tgn:7048298",
        "tgn:7007850",
        "tgn:1003491",
        "tgn:1000003",
        "tgn:1000080",
        "tgn:7029392"
    ],
    "tgn:id":7048298,
    "tgn:name":"Rada dei Giunchi",
    "tgn:placetype":[
        "aat:300386968"
    ]
},
  "bbox": [],
  "geometry": {"coordinates":[15.616667,38.116667],"type":"Point"}
}