{
  "id": 2278199,
  "type": "Feature",
  "properties": {
    "tgn:hierarchy":[
        "tgn:2278199",
        "tgn:1000001",
        "tgn:7012149",
        "tgn:2001718",
        "tgn:7007708",
        "tgn:7029392"
    ],
    "tgn:id":2278199,
    "tgn:name":"De Bord",
    "tgn:placetype":[
        "aat:300008798"
    ]
},
  "bbox": [],
  "geometry": {"coordinates":[-118.05,44.1833],"type":"Point"}
}