<<<<<<< HEAD
{
  "id": 2251415,
  "type": "Feature",
  "properties": {
    "tgn:hierarchy":[
        "tgn:2251415",
        "tgn:1000001",
        "tgn:7012149",
        "tgn:2002100",
        "tgn:7007826",
        "tgn:7029392"
    ],
    "tgn:id":2251415,
    "tgn:name":"Cometa Tank",
    "tgn:placetype":[
        "aat:300006191"
    ]
},
  "bbox": [],
  "geometry": {"coordinates":[-99.95,28.9],"type":"Point"}
}
=======
{"geometry":{"type":"Point","coordinates":[-99.950000,28.900000]},"type":"Feature","properties":{"hierarchy":["tgn:2251415","tgn:1000001","tgn:7012149","tgn:2002100","tgn:7007826","tgn:7029392"],"placetype":["aat:300006191"],"id":2251415,"name:xx":"Cometa Tank"}}
>>>>>>> 03f74aca74312dbeaf24d7e61306dd6a786dc3d0
