{
  "id": 2743231,
  "type": "Feature",
  "properties": {
    "tgn:hierarchy":[
        "tgn:2743231",
        "tgn:1000001",
        "tgn:7012149",
        "tgn:1002658",
        "tgn:7007706",
        "tgn:7029392"
    ],
    "tgn:id":2743231,
    "tgn:name":"Vandenbush Ditch",
    "tgn:placetype":[
        "aat:300006075"
    ]
},
  "bbox": [],
  "geometry": {"coordinates":[-84.5833,40.3833],"type":"Point"}
}