{
  "id": 7479292,
  "type": "Feature",
  "properties": {
    "tgn:hierarchy":[
        "tgn:7479292",
        "tgn:1000004",
        "tgn:7490934",
        "tgn:1000141",
        "tgn:7029392"
    ],
    "tgn:id":7479292,
    "tgn:name":"Fengli Diaoqiao",
    "tgn:placetype":[
        "aat:300007836"
    ]
},
  "bbox": [],
  "geometry": {"coordinates":[120.451387,23.120429],"type":"Point"}
}