{
  "id": 2391755,
  "type": "Feature",
  "properties": {
    "tgn:hierarchy":[
        "tgn:2391755",
        "tgn:1000001",
        "tgn:7012149",
        "tgn:2000232",
        "tgn:7007158",
        "tgn:7029392"
    ],
    "tgn:id":2391755,
    "tgn:name":"Hillside Spring",
    "tgn:placetype":[
        "aat:300008697"
    ]
},
  "bbox": [],
  "geometry": {"coordinates":[-108.85,40.5667],"type":"Point"}
}