{
  "id": 1089497,
  "type": "Feature",
  "properties": {
    "tgn:hierarchy":[
        "tgn:1089497",
        "tgn:7001242",
        "tgn:7016755",
        "tgn:1000159",
        "tgn:7029392"
    ],
    "tgn:id":1089497,
    "tgn:name":"Senza",
    "tgn:placetype":[
        "aat:300008347"
    ]
},
  "bbox": [],
  "geometry": {"coordinates":[26.3167,3.0333],"type":"Point"}
}