{
  "id": 2111321,
  "type": "Feature",
  "properties": {
    "tgn:hierarchy":[
        "tgn:2111321",
        "tgn:1000001",
        "tgn:7012149",
        "tgn:2002158",
        "tgn:7007919",
        "tgn:7029392"
    ],
    "tgn:id":2111321,
    "tgn:name":"Copper Valley",
    "tgn:placetype":[
        "aat:300008347",
        "aat:300387210"
    ]
},
  "bbox": [],
  "geometry": {"coordinates":[-80.5167,36.9833],"type":"Point"}
}