{
  "id": 2674036,
  "type": "Feature",
  "properties": {
    "tgn:hierarchy":[
        "tgn:2674036",
        "tgn:1000001",
        "tgn:2001419",
        "tgn:7012149",
        "tgn:7007526",
        "tgn:7029392"
    ],
    "tgn:id":2674036,
    "tgn:name":"Snow White Cave",
    "tgn:placetype":[
        "aat:300008746"
    ]
},
  "bbox": [],
  "geometry": {"coordinates":[-118.35,40.15],"type":"Point"}
}