<<<<<<< HEAD
{
  "id": 2339672,
  "type": "Feature",
  "properties": {
    "tgn:hierarchy":[
        "tgn:2339672",
        "tgn:1000001",
        "tgn:7012149",
        "tgn:2000823",
        "tgn:7007255",
        "tgn:7029392"
    ],
    "tgn:id":2339672,
    "tgn:name":"Free Branch",
    "tgn:placetype":[
        "aat:300008699"
    ]
},
  "bbox": [],
  "geometry": {"coordinates":[-88.4167,36.7667],"type":"Point"}
}
=======
{"geometry":{"type":"Point","coordinates":[-88.416700,36.766700]},"type":"Feature","properties":{"hierarchy":["tgn:2339672","tgn:1000001","tgn:7012149","tgn:2000823","tgn:7007255","tgn:7029392"],"placetype":["aat:300008699"],"id":2339672,"name:xx":"Free Branch"}}
>>>>>>> 03f74aca74312dbeaf24d7e61306dd6a786dc3d0
