{
  "id": 7223440,
  "type": "Feature",
  "properties": {
    "tgn:hierarchy":[
        "tgn:7223440",
        "tgn:7002748",
        "tgn:7001399",
        "tgn:1000003",
        "tgn:1000074",
        "tgn:7029392"
    ],
    "tgn:id":7223440,
    "tgn:name":"M\u00e1ndra",
    "tgn:placetype":[
        "aat:300008795"
    ]
},
  "bbox": [],
  "geometry": {"coordinates":[21.736944,39.2375],"type":"Point"}
}