{
  "id": 1010956,
  "type": "Feature",
  "properties": {
    "tgn:hierarchy":[
        "tgn:1010956",
        "tgn:1000001",
        "tgn:7024573",
        "tgn:7029392"
    ],
    "tgn:id":1010956,
    "tgn:name":"Morris Jesup, Kap",
    "tgn:placetype":[
        "aat:300008850"
    ]
},
  "bbox": [],
  "geometry": {"coordinates":[-32.5167,83.6333],"type":"Point"}
}