{
  "id": 2460406,
  "type": "Feature",
  "properties": {
    "tgn:hierarchy":[
        "tgn:2460406",
        "tgn:1000001",
        "tgn:7012149",
        "tgn:7007157",
        "tgn:1002857",
        "tgn:7029392"
    ],
    "tgn:id":2460406,
    "tgn:name":"Little Sand Canyon",
    "tgn:placetype":[
        "aat:300008761"
    ]
},
  "bbox": [],
  "geometry": {"coordinates":[-117.2167,34.1833],"type":"Point"}
}