{
  "id": 7075041,
  "type": "Feature",
  "properties": {
    "tgn:hierarchy":[
        "tgn:7075041",
        "tgn:1000003",
        "tgn:7000094",
        "tgn:7000084",
        "tgn:7029392"
    ],
    "tgn:id":7075041,
    "tgn:name":"Idunagrund",
    "tgn:placetype":[
        "aat:300387036"
    ]
},
  "bbox": [],
  "geometry": {"coordinates":[13.75,54.316667],"type":"Point"}
}