{
  "id": 2310574,
  "type": "Feature",
  "properties": {
    "tgn:hierarchy":[
        "tgn:2310574",
        "tgn:1000001",
        "tgn:7012149",
        "tgn:7014287",
        "tgn:7007568",
        "tgn:7029392"
    ],
    "tgn:id":2310574,
    "tgn:name":"Echo Lake",
    "tgn:placetype":[
        "aat:300008680"
    ]
},
  "bbox": [],
  "geometry": {"coordinates":[-75.2667,43.4167],"type":"Point"}
}