{
  "id": 2467428,
  "type": "Feature",
  "properties": {
    "tgn:hierarchy":[
        "tgn:2467428",
        "tgn:1000001",
        "tgn:1002712",
        "tgn:7012149",
        "tgn:7007159",
        "tgn:7029392"
    ],
    "tgn:id":2467428,
    "tgn:name":"Long Hill",
    "tgn:placetype":[
        "aat:300008798"
    ]
},
  "bbox": [],
  "geometry": {"coordinates":[-72.7167,41.3167],"type":"Point"}
}