{
  "id": 2783698,
  "type": "Feature",
  "properties": {
    "tgn:hierarchy":[
        "tgn:2783698",
        "tgn:1000001",
        "tgn:7012149",
        "tgn:2000930",
        "tgn:7007515",
        "tgn:7029392"
    ],
    "tgn:id":2783698,
    "tgn:name":"Wyman Lake",
    "tgn:placetype":[
        "aat:300006191"
    ]
},
  "bbox": [],
  "geometry": {"coordinates":[-69.9333,45.0833],"type":"Point"}
}