{
  "id": 2755569,
  "type": "Feature",
  "properties": {
    "tgn:hierarchy":[
        "tgn:2755569",
        "tgn:1000001",
        "tgn:7012149",
        "tgn:2002111",
        "tgn:7007827",
        "tgn:7029392"
    ],
    "tgn:id":2755569,
    "tgn:name":"Websters Knolls",
    "tgn:placetype":[
        "aat:300008798"
    ]
},
  "bbox": [],
  "geometry": {"coordinates":[-113.6333,37.95],"type":"Point"}
}