<<<<<<< HEAD
{
  "id": 2760530,
  "type": "Feature",
  "properties": {
    "tgn:hierarchy":[
        "tgn:2760530",
        "tgn:1000001",
        "tgn:2002243",
        "tgn:7012149",
        "tgn:7007920",
        "tgn:7029392"
    ],
    "tgn:id":2760530,
    "tgn:name":"West Fork Trout Creek",
    "tgn:placetype":[
        "aat:300008706"
    ]
},
  "bbox": [],
  "geometry": {"coordinates":[-118.8,48.7167],"type":"Point"}
}
=======
{"geometry":{"type":"Point","coordinates":[-118.800000,48.716700]},"type":"Feature","properties":{"hierarchy":["tgn:2760530","tgn:1000001","tgn:2002243","tgn:7012149","tgn:7007920","tgn:7029392"],"placetype":["aat:300008706"],"id":2760530,"name:xx":"West Fork Trout Creek"}}
>>>>>>> 03f74aca74312dbeaf24d7e61306dd6a786dc3d0
