{
  "id": 2623416,
  "type": "Feature",
  "properties": {
    "tgn:hierarchy":[
        "tgn:2623416",
        "tgn:7002659",
        "tgn:1000001",
        "tgn:2000016",
        "tgn:7012149",
        "tgn:7029392"
    ],
    "tgn:id":2623416,
    "tgn:name":"Rock Creek",
    "tgn:placetype":[
        "aat:300008347"
    ]
},
  "bbox": [],
  "geometry": {"coordinates":[-87.9167,34.5833],"type":"Point"}
}