{
  "id": 7036196,
  "type": "Feature",
  "properties": {
    "tgn:hierarchy":[
        "tgn:7036196",
        "tgn:7002996",
        "tgn:1000003",
        "tgn:7002997",
        "tgn:1000080",
        "tgn:7029392"
    ],
    "tgn:id":7036196,
    "tgn:name":"Mignagola",
    "tgn:placetype":[
        "aat:300008347"
    ]
},
  "bbox": [],
  "geometry": {"coordinates":[12.322222,45.691389],"type":"Point"}
}