{
  "id": 7075849,
  "type": "Feature",
  "properties": {
    "tgn:hierarchy":[
        "tgn:7075849",
        "tgn:1000003",
        "tgn:7003678",
        "tgn:7000084",
        "tgn:7029392"
    ],
    "tgn:id":7075849,
    "tgn:name":"Kuhbett",
    "tgn:placetype":[
        "aat:300008347"
    ]
},
  "bbox": [],
  "geometry": {"coordinates":[8.333333,50.316667],"type":"Point"}
}