{
  "id": 2219687,
  "type": "Feature",
  "properties": {
    "tgn:hierarchy":[
        "tgn:2219687",
        "tgn:1000001",
        "tgn:7006451",
        "tgn:7012149",
        "tgn:2000102",
        "tgn:7029392"
    ],
    "tgn:id":2219687,
    "tgn:name":"Ca\u00f1oncito",
    "tgn:placetype":[
        "aat:300008761"
    ]
},
  "bbox": [],
  "geometry": {"coordinates":[-111.3167,31.4833],"type":"Point"}
}