{
  "id": 1074472,
  "type": "Feature",
  "properties": {
    "tgn:hierarchy":[
        "tgn:1074472",
        "tgn:1000004",
        "tgn:7000198",
        "tgn:1001977",
        "tgn:7029392"
    ],
    "tgn:id":1074472,
    "tgn:name":"Atghara",
    "tgn:placetype":[
        "aat:300008347"
    ]
},
  "bbox": [],
  "geometry": {"coordinates":[88.45,22.6167],"type":"Point"}
}