{
  "id": 1063066,
  "type": "Feature",
  "properties": {
    "tgn:hierarchy":[
        "tgn:1063066",
        "tgn:1000374",
        "tgn:1000003",
        "tgn:1000097",
        "tgn:7029392"
    ],
    "tgn:id":1063066,
    "tgn:name":"H\u00e4stbo",
    "tgn:placetype":[
        "aat:300008347"
    ]
},
  "bbox": [],
  "geometry": {"coordinates":[16.45,60.45],"type":"Point"}
}