{
  "id": 2126125,
  "type": "Feature",
  "properties": {
    "tgn:hierarchy":[
        "tgn:2126125",
        "tgn:1000001",
        "tgn:7012149",
        "tgn:1002920",
        "tgn:7007568",
        "tgn:7029392"
    ],
    "tgn:id":2126125,
    "tgn:name":"Addison Hill",
    "tgn:placetype":[
        "aat:300008798"
    ]
},
  "bbox": [],
  "geometry": {"coordinates":[-77.3167,42.0167],"type":"Point"}
}