<<<<<<< HEAD
{
  "id": 2335740,
  "type": "Feature",
  "properties": {
    "tgn:hierarchy":[
        "tgn:2335740",
        "tgn:1000001",
        "tgn:7016172",
        "tgn:7012149",
        "tgn:2000164",
        "tgn:7029392"
    ],
    "tgn:id":2335740,
    "tgn:name":"Forty Point Lake",
    "tgn:placetype":[
        "aat:300008905"
    ]
},
  "bbox": [],
  "geometry": {"coordinates":[-92.1,34.8],"type":"Point"}
}
=======
{"geometry":{"type":"Point","coordinates":[-92.100000,34.800000]},"type":"Feature","properties":{"hierarchy":["tgn:2335740","tgn:1000001","tgn:7016172","tgn:7012149","tgn:2000164","tgn:7029392"],"placetype":["aat:300008905"],"id":2335740,"name:xx":"Forty Point Lake"}}
>>>>>>> 03f74aca74312dbeaf24d7e61306dd6a786dc3d0
