{
  "id": 7042813,
  "type": "Feature",
  "properties": {
    "tgn:hierarchy":[
        "tgn:7042813",
        "tgn:1000003",
        "tgn:7003122",
        "tgn:7003157",
        "tgn:1000080",
        "tgn:7029392"
    ],
    "tgn:id":7042813,
    "tgn:name":"Scala Ritiro",
    "tgn:placetype":[
        "aat:300008347"
    ]
},
  "bbox": [],
  "geometry": {"coordinates":[15.533333,38.216667],"type":"Point"}
}