{
  "id": 2666788,
  "type": "Feature",
  "properties": {
    "tgn:hierarchy":[
        "tgn:2666788",
        "tgn:1000001",
        "tgn:7012149",
        "tgn:2000450",
        "tgn:7007248",
        "tgn:7029392"
    ],
    "tgn:id":2666788,
    "tgn:name":"Sizemore Lake",
    "tgn:placetype":[
        "aat:300006191"
    ]
},
  "bbox": [],
  "geometry": {"coordinates":[-83.7667,31.4667],"type":"Point"}
}