{
  "id": 2115462,
  "type": "Feature",
  "properties": {
    "tgn:hierarchy":[
        "tgn:2115462",
        "tgn:1000001",
        "tgn:7012149",
        "tgn:7018871",
        "tgn:7007920",
        "tgn:7029392"
    ],
    "tgn:id":2115462,
    "tgn:name":"Cedar Falls",
    "tgn:placetype":[
        "aat:300008347",
        "aat:300387210"
    ]
},
  "bbox": [],
  "geometry": {"coordinates":[-121.7667,47.4167],"type":"Point"}
}