{
  "id": 2638569,
  "type": "Feature",
  "properties": {
    "tgn:hierarchy":[
        "tgn:2638569",
        "tgn:2000919",
        "tgn:1000001",
        "tgn:7012149",
        "tgn:7007515",
        "tgn:7029392"
    ],
    "tgn:id":2638569,
    "tgn:name":"Salmon Point",
    "tgn:placetype":[
        "aat:300008850"
    ]
},
  "bbox": [],
  "geometry": {"coordinates":[-68.3167,47.0167],"type":"Point"}
}