{
  "id": 7506228,
  "type": "Feature",
  "properties": {
    "tgn:hierarchy":[
        "tgn:7506228",
        "tgn:1009227",
        "tgn:1000226",
        "tgn:7018437",
        "tgn:1000006",
        "tgn:7029392"
    ],
    "tgn:id":7506228,
    "tgn:name:en":"Saint Clair",
    "tgn:placetype":[
        "aat:300008347"
    ]
},
  "bbox": [],
  "geometry": {"coordinates":[170.483333,-45.916667],"type":"Point"}
}