{
  "id": 2319988,
  "type": "Feature",
  "properties": {
    "tgn:hierarchy":[
        "tgn:2319988",
        "tgn:1000001",
        "tgn:7012149",
        "tgn:1002999",
        "tgn:7007526",
        "tgn:7029392"
    ],
    "tgn:id":2319988,
    "tgn:name":"Evans Creek",
    "tgn:placetype":[
        "aat:300008706"
    ]
},
  "bbox": [],
  "geometry": {"coordinates":[-119.8833,39.4167],"type":"Point"}
}