{
  "id": 2410443,
  "type": "Feature",
  "properties": {
    "tgn:hierarchy":[
        "tgn:2410443",
        "tgn:7006450",
        "tgn:1000001",
        "tgn:7012149",
        "tgn:7030574",
        "tgn:7029392"
    ],
    "tgn:id":2410443,
    "tgn:name":"Indian Camp Creek",
    "tgn:placetype":[
        "aat:300008706"
    ]
},
  "bbox": [],
  "geometry": {"coordinates":[-139.5833,59.8667],"type":"Point"}
}