<<<<<<< HEAD
{
  "id": 2151697,
  "type": "Feature",
  "properties": {
    "tgn:hierarchy":[
        "tgn:2151697",
        "tgn:1000001",
        "tgn:7012149",
        "tgn:2000488",
        "tgn:7007250",
        "tgn:7029392"
    ],
    "tgn:id":2151697,
    "tgn:name":"Battle Creek Crossing Waterhole Number 2",
    "tgn:placetype":[
        "aat:300008697"
    ]
},
  "bbox": [],
  "geometry": {"coordinates":[-116.4,42.3667],"type":"Point"}
}
=======
{"geometry":{"type":"Point","coordinates":[-116.400000,42.366700]},"type":"Feature","properties":{"hierarchy":["tgn:2151697","tgn:1000001","tgn:7012149","tgn:2000488","tgn:7007250","tgn:7029392"],"placetype":["aat:300008697"],"id":2151697,"name:xx":"Battle Creek Crossing Waterhole Number 2"}}
>>>>>>> 03f74aca74312dbeaf24d7e61306dd6a786dc3d0
