{
  "id": 7210690,
  "type": "Feature",
  "properties": {
    "tgn:hierarchy":[
        "tgn:7210690",
        "tgn:1000003",
        "tgn:7003687",
        "tgn:7000084",
        "tgn:7029392"
    ],
    "tgn:id":7210690,
    "tgn:name":"Bauerwiesen",
    "tgn:placetype":[
        "aat:300008903"
    ]
},
  "bbox": [],
  "geometry": {"coordinates":[12.183333,52.833333],"type":"Point"}
}