{
  "id": 7106603,
  "type": "Feature",
  "properties": {
    "tgn:hierarchy":[
        "tgn:7106603",
        "tgn:7003669",
        "tgn:1000003",
        "tgn:7000084",
        "tgn:7029392"
    ],
    "tgn:id":7106603,
    "tgn:name":"Schlegelhaid",
    "tgn:placetype":[
        "aat:300008347"
    ]
},
  "bbox": [],
  "geometry": {"coordinates":[11.516667,50.316667],"type":"Point"}
}