{
  "id": 7272081,
  "type": "Feature",
  "properties": {
    "tgn:hierarchy":[
        "tgn:7272081",
        "tgn:1000003",
        "tgn:7003624",
        "tgn:7016845",
        "tgn:7029392"
    ],
    "tgn:id":7272081,
    "tgn:name:nl":"Sterkselsch Kanaal",
    "tgn:placetype":[
        "aat:300006075"
    ]
},
  "bbox": [],
  "geometry": {"coordinates":[5.616667,51.35],"type":"Point"}
}