{
  "id": 2362275,
  "type": "Feature",
  "properties": {
    "tgn:hierarchy":[
        "tgn:2362275",
        "tgn:1000001",
        "tgn:7012149",
        "tgn:2000494",
        "tgn:7007250",
        "tgn:7029392"
    ],
    "tgn:id":2362275,
    "tgn:name":"Grays Peak",
    "tgn:placetype":[
        "aat:300008798"
    ]
},
  "bbox": [],
  "geometry": {"coordinates":[-115.05,44.8167],"type":"Point"}
}