<<<<<<< HEAD
{
  "id": 7471916,
  "type": "Feature",
  "properties": {
    "tgn:hierarchy":[
        "tgn:7471916",
        "tgn:1000004",
        "tgn:7467799",
        "tgn:1000141",
        "tgn:7029392"
    ],
    "tgn:id":7471916,
    "tgn:name":"Qihuzi",
    "tgn:placetype":[
        "aat:300008347"
    ]
},
  "bbox": [],
  "geometry": {"coordinates":[120.476255,23.830231],"type":"Point"}
}
=======
{"geometry":{"type":"Point","coordinates":[120.476255,23.830231]},"type":"Feature","properties":{"hierarchy":["tgn:7471916","tgn:1000004","tgn:7467799","tgn:1000141","tgn:7029392"],"placetype":["aat:300008347"],"id":7471916,"name:xx":"Qihuzi"}}
>>>>>>> 03f74aca74312dbeaf24d7e61306dd6a786dc3d0
