{
  "id": 7076649,
  "type": "Feature",
  "properties": {
    "tgn:hierarchy":[
        "tgn:7076649",
        "tgn:7003669",
        "tgn:1000003",
        "tgn:7000084",
        "tgn:7029392"
    ],
    "tgn:id":7076649,
    "tgn:name":"Zilchenricht",
    "tgn:placetype":[
        "aat:300008347"
    ]
},
  "bbox": [],
  "geometry": {"coordinates":[12.183333,49.383333],"type":"Point"}
}