{
  "id": 2219678,
  "type": "Feature",
  "properties": {
    "tgn:hierarchy":[
        "tgn:2219678",
        "tgn:1000001",
        "tgn:7012149",
        "tgn:2001451",
        "tgn:7007566",
        "tgn:7029392"
    ],
    "tgn:id":2219678,
    "tgn:name":"Ca\u00f1on del Piojo",
    "tgn:placetype":[
        "aat:300008761"
    ]
},
  "bbox": [],
  "geometry": {"coordinates":[-107.2167,35.25],"type":"Point"}
}