{
  "id": 2146901,
  "type": "Feature",
  "properties": {
    "tgn:hierarchy":[
        "tgn:2146901",
        "tgn:1000001",
        "tgn:7012149",
        "tgn:7007565",
        "tgn:7029392"
    ],
    "tgn:id":2146901,
    "tgn:name":"Bannen Meadow Brook",
    "tgn:placetype":[
        "aat:300008699"
    ]
},
  "bbox": [],
  "geometry": {"coordinates":[-74.2667,40.1833],"type":"Point"}
}