<<<<<<< HEAD
{
  "id": 7114230,
  "type": "Feature",
  "properties": {
    "tgn:hierarchy":[
        "tgn:7114230",
        "tgn:1000003",
        "tgn:7000094",
        "tgn:7000084",
        "tgn:7029392"
    ],
    "tgn:id":7114230,
    "tgn:name":"Renzower Bauern",
    "tgn:placetype":[
        "aat:300000206"
    ]
},
  "bbox": [],
  "geometry": {"coordinates":[11.166667,53.633333],"type":"Point"}
}
=======
{"geometry":{"type":"Point","coordinates":[11.166667,53.633333]},"type":"Feature","properties":{"hierarchy":["tgn:7114230","tgn:1000003","tgn:7000094","tgn:7000084","tgn:7029392"],"placetype":["aat:300000206"],"id":7114230,"name:xx":"Renzower Bauern"}}
>>>>>>> 03f74aca74312dbeaf24d7e61306dd6a786dc3d0
