{
  "id": 7435921,
  "type": "Feature",
  "properties": {
    "tgn:hierarchy":[
        "tgn:7435921",
        "tgn:1000001",
        "tgn:7005588",
        "tgn:7005560",
        "tgn:7029392"
    ],
    "tgn:id":7435921,
    "tgn:name":"Tetelpa",
    "tgn:placetype":[
        "aat:300008347"
    ]
},
  "bbox": [],
  "geometry": {"coordinates":[-99.233333,18.666667],"type":"Point"}
}