{
  "id": 7557995,
  "type": "Feature",
  "properties": {
    "tgn:hierarchy":[
        "tgn:7557995",
        "tgn:1000004",
        "tgn:7000198",
        "tgn:1001905",
        "tgn:7029392"
    ],
    "tgn:id":7557995,
    "tgn:name:en":"Panso",
    "tgn:placetype":[
        "aat:300008347"
    ]
},
  "bbox": [],
  "geometry": {"coordinates":[94.929573,26.117256],"type":"Point"}
}