<<<<<<< HEAD
{
  "id": 7111638,
  "type": "Feature",
  "properties": {
    "tgn:hierarchy":[
        "tgn:7111638",
        "tgn:1000003",
        "tgn:7003689",
        "tgn:7000084",
        "tgn:7029392"
    ],
    "tgn:id":7111638,
    "tgn:name":"Rippershausen",
    "tgn:placetype":[
        "aat:300008347"
    ]
},
  "bbox": [],
  "geometry": {"coordinates":[10.35,50.6],"type":"Point"}
}
=======
{"geometry":{"type":"Point","coordinates":[10.350000,50.600000]},"type":"Feature","properties":{"hierarchy":["tgn:7111638","tgn:1000003","tgn:7003689","tgn:7000084","tgn:7029392"],"placetype":["aat:300008347"],"id":7111638,"name:xx":"Rippershausen"}}
>>>>>>> 03f74aca74312dbeaf24d7e61306dd6a786dc3d0
