<<<<<<< HEAD
{
  "id": 7241123,
  "type": "Feature",
  "properties": {
    "tgn:hierarchy":[
        "tgn:7241123",
        "tgn:7018239",
        "tgn:1000003",
        "tgn:1000063",
        "tgn:7018236",
        "tgn:7029392"
    ],
    "tgn:id":7241123,
    "tgn:name":"Helstraat",
    "tgn:placetype":[
        "aat:300008347"
    ]
},
  "bbox": [],
  "geometry": {"coordinates":[4.895691,50.867681],"type":"Point"}
}
=======
{"geometry":{"type":"Point","coordinates":[4.895691,50.867681]},"type":"Feature","properties":{"hierarchy":["tgn:7241123","tgn:7018239","tgn:1000003","tgn:1000063","tgn:7018236","tgn:7029392"],"placetype":["aat:300008347"],"id":7241123,"name:xx":"Helstraat"}}
>>>>>>> 03f74aca74312dbeaf24d7e61306dd6a786dc3d0
