{
  "id": 1010110,
  "type": "Feature",
  "properties": {
    "tgn:hierarchy":[
        "tgn:1010110",
        "tgn:1001835",
        "tgn:1000001",
        "tgn:7005560",
        "tgn:7029392"
    ],
    "tgn:id":1010110,
    "tgn:name":"Los Coronados, Islas",
    "tgn:placetype":[
        "aat:300008791",
        "aat:300386853"
    ]
},
  "bbox": [],
  "geometry": {"coordinates":[-117.25,32.416667],"type":"Point"}
}