{
  "id": 2545110,
  "type": "Feature",
  "properties": {
    "tgn:hierarchy":[
        "tgn:2545110",
        "tgn:1000001",
        "tgn:7012149",
        "tgn:1002676",
        "tgn:7007240",
        "tgn:7029392"
    ],
    "tgn:id":2545110,
    "tgn:name":"North Dry Rocks",
    "tgn:placetype":[
        "aat:300132348"
    ]
},
  "bbox": [],
  "geometry": {"coordinates":[-80.2833,25.1167],"type":"Point"}
}