{
  "id": 2487612,
  "type": "Feature",
  "properties": {
    "tgn:hierarchy":[
        "tgn:2487612",
        "tgn:1000001",
        "tgn:2002148",
        "tgn:7012149",
        "tgn:7007919",
        "tgn:7029392"
    ],
    "tgn:id":2487612,
    "tgn:name":"Left Fork Home Creek",
    "tgn:placetype":[
        "aat:300008706"
    ]
},
  "bbox": [],
  "geometry": {"coordinates":[-82.1167,37.3667],"type":"Point"}
}