{
  "id": 2385048,
  "type": "Feature",
  "properties": {
    "tgn:hierarchy":[
        "tgn:2385048",
        "tgn:1000001",
        "tgn:7012149",
        "tgn:2000488",
        "tgn:7007250",
        "tgn:7029392"
    ],
    "tgn:id":2385048,
    "tgn:name":"Heltons Island",
    "tgn:placetype":[
        "aat:300008791"
    ]
},
  "bbox": [],
  "geometry": {"coordinates":[-116.9333,43.6167],"type":"Point"}
}