{
  "id": 2291576,
  "type": "Feature",
  "properties": {
    "tgn:hierarchy":[
        "tgn:2291576",
        "tgn:2000999",
        "tgn:1000001",
        "tgn:7012149",
        "tgn:7007521",
        "tgn:7029392"
    ],
    "tgn:id":2291576,
    "tgn:name":"Dollar Lake",
    "tgn:placetype":[
        "aat:300008680"
    ]
},
  "bbox": [],
  "geometry": {"coordinates":[-93.2667,46.6833],"type":"Point"}
}