{
  "id": 2236751,
  "type": "Feature",
  "properties": {
    "tgn:hierarchy":[
        "tgn:2236751",
        "tgn:7006450",
        "tgn:1000001",
        "tgn:2124053",
        "tgn:7012149",
        "tgn:7029392"
    ],
    "tgn:id":2236751,
    "tgn:name":"Chikootna Creek",
    "tgn:placetype":[
        "aat:300008706"
    ]
},
  "bbox": [],
  "geometry": {"coordinates":[-148.1167,61.8167],"type":"Point"}
}