{
  "id": 2486431,
  "type": "Feature",
  "properties": {
    "tgn:hierarchy":[
        "tgn:2486431",
        "tgn:1000001",
        "tgn:7012149",
        "tgn:2002385",
        "tgn:7007923",
        "tgn:7029392"
    ],
    "tgn:id":2486431,
    "tgn:name":"Leavitt Creek",
    "tgn:placetype":[
        "aat:300008706"
    ]
},
  "bbox": [],
  "geometry": {"coordinates":[-110.35,41.0833],"type":"Point"}
}