<<<<<<< HEAD
{
  "id": 7113669,
  "type": "Feature",
  "properties": {
    "tgn:hierarchy":[
        "tgn:7113669",
        "tgn:1000003",
        "tgn:7003689",
        "tgn:7000084",
        "tgn:7029392"
    ],
    "tgn:id":7113669,
    "tgn:name":"F\u00f6rsterei Rodeberg",
    "tgn:placetype":[
        "aat:300004792"
    ]
},
  "bbox": [],
  "geometry": {"coordinates":[10.916667,51.483333],"type":"Point"}
}
=======
{"geometry":{"type":"Point","coordinates":[10.916667,51.483333]},"type":"Feature","properties":{"hierarchy":["tgn:7113669","tgn:1000003","tgn:7003689","tgn:7000084","tgn:7029392"],"placetype":["aat:300004792"],"id":7113669,"name:xx":"F\u00f6rsterei Rodeberg"}}
>>>>>>> 03f74aca74312dbeaf24d7e61306dd6a786dc3d0
