{
  "id": 7251832,
  "type": "Feature",
  "properties": {
    "tgn:hierarchy":[
        "tgn:7251832",
        "tgn:7003460",
        "tgn:1000003",
        "tgn:1000063",
        "tgn:4012014",
        "tgn:7029392"
    ],
    "tgn:id":7251832,
    "tgn:name":"Marneffe",
    "tgn:placetype":[
        "aat:300008347"
    ]
},
  "bbox": [],
  "geometry": {"coordinates":[5.143263,50.578859],"type":"Point"}
}