{
  "id": 1088895,
  "type": "Feature",
  "properties": {
    "tgn:hierarchy":[
        "tgn:1088895",
        "tgn:1001143",
        "tgn:7001242",
        "tgn:1000159",
        "tgn:7029392"
    ],
    "tgn:id":1088895,
    "tgn:name":"Bumbo",
    "tgn:placetype":[
        "aat:300008347"
    ]
},
  "bbox": [],
  "geometry": {"coordinates":[21.95,-7.0667],"type":"Point"}
}