<<<<<<< HEAD
{
  "id": 2154620,
  "type": "Feature",
  "properties": {
    "tgn:hierarchy":[
        "tgn:2154620",
        "tgn:1000001",
        "tgn:7012149",
        "tgn:7007919",
        "tgn:7029392"
    ],
    "tgn:id":2154620,
    "tgn:name":"Bear Fork",
    "tgn:placetype":[
        "aat:300008699"
    ]
},
  "bbox": [],
  "geometry": {"coordinates":[-82.4833,37.0167],"type":"Point"}
}
=======
{"geometry":{"type":"Point","coordinates":[-82.483300,37.016700]},"type":"Feature","properties":{"hierarchy":["tgn:2154620","tgn:1000001","tgn:7012149","tgn:7007919","tgn:7029392"],"placetype":["aat:300008699"],"id":2154620,"name:xx":"Bear Fork"}}
>>>>>>> 03f74aca74312dbeaf24d7e61306dd6a786dc3d0
