{
  "id": 7346712,
  "type": "Feature",
  "properties": {
    "tgn:hierarchy":[
        "tgn:7346712",
        "tgn:7002849",
        "tgn:1000003",
        "tgn:7009604",
        "tgn:1000095",
        "tgn:7029392"
    ],
    "tgn:id":7346712,
    "tgn:name":"Belandia",
    "tgn:placetype":[
        "aat:300008347"
    ]
},
  "bbox": [],
  "geometry": {"coordinates":[-3.044603,43.031951],"type":"Point"}
}