{
  "id": 7590308,
  "type": "Feature",
  "properties": {
    "tgn:hierarchy":[
        "tgn:7590308",
        "tgn:1000004",
        "tgn:7000198",
        "tgn:7000799",
        "tgn:7029392"
    ],
    "tgn:id":7590308,
    "tgn:name:en":"T\u0101r\u0101garh",
    "tgn:placetype":[
        "aat:300008347"
    ]
},
  "bbox": [],
  "geometry": {"coordinates":[74.283534,33.791307],"type":"Point"}
}