{
  "id": 4011530,
  "type": "Feature",
  "properties": {
    "tgn:hierarchy":[
        "tgn:4011530",
        "tgn:1000003",
        "tgn:1000405",
        "tgn:1000097",
        "tgn:7029392"
    ],
    "tgn:id":4011530,
    "tgn:name":"Urshult",
    "tgn:placetype":[
        "aat:300008347"
    ]
},
  "bbox": [],
  "geometry": {"coordinates":[14.7833,56.5333],"type":"Point"}
}