<<<<<<< HEAD
{
  "id": 2250776,
  "type": "Feature",
  "properties": {
    "tgn:hierarchy":[
        "tgn:2250776",
        "tgn:1000001",
        "tgn:7012149",
        "tgn:7029392"
    ],
    "tgn:id":2250776,
    "tgn:name":"Colter Canyon",
    "tgn:placetype":[
        "aat:300008761"
    ]
},
  "bbox": [],
  "geometry": {"coordinates":[-101.8,40.0],"type":"Point"}
}
=======
{"geometry":{"type":"Point","coordinates":[-101.800000,40.000000]},"type":"Feature","properties":{"hierarchy":["tgn:2250776","tgn:1000001","tgn:7012149","tgn:7029392"],"placetype":["aat:300008761"],"id":2250776,"name:xx":"Colter Canyon"}}
>>>>>>> 03f74aca74312dbeaf24d7e61306dd6a786dc3d0
