{
  "id": 7096455,
  "type": "Feature",
  "properties": {
    "tgn:hierarchy":[
        "tgn:7096455",
        "tgn:1000003",
        "tgn:7003685",
        "tgn:7000084",
        "tgn:7029392"
    ],
    "tgn:id":7096455,
    "tgn:name":"Siedlung Adler",
    "tgn:placetype":[
        "aat:300008347"
    ]
},
  "bbox": [],
  "geometry": {"coordinates":[14.216667,51.433333],"type":"Point"}
}