{
  "id": 1026679,
  "type": "Feature",
  "properties": {
    "tgn:hierarchy":[
        "tgn:1026679",
        "tgn:7007877",
        "tgn:1000003",
        "tgn:1000063",
        "tgn:4012014",
        "tgn:7029392"
    ],
    "tgn:id":1026679,
    "tgn:name":"Ploegsteert",
    "tgn:placetype":[
        "aat:300008347"
    ]
},
  "bbox": [],
  "geometry": {"coordinates":[2.880192,50.72659],"type":"Point"}
}