<<<<<<< HEAD
{
  "id": 7359767,
  "type": "Feature",
  "properties": {
    "tgn:hierarchy":[
        "tgn:7359767",
        "tgn:7005581",
        "tgn:1000001",
        "tgn:7005560",
        "tgn:7029392"
    ],
    "tgn:id":7359767,
    "tgn:name":"Rancho Cuatro Vientos",
    "tgn:placetype":[
        "aat:300000241"
    ]
},
  "bbox": [],
  "geometry": {"coordinates":[-108.433333,29.183333],"type":"Point"}
}
=======
{"geometry":{"type":"Point","coordinates":[-108.433333,29.183333]},"type":"Feature","properties":{"hierarchy":["tgn:7359767","tgn:7005581","tgn:1000001","tgn:7005560","tgn:7029392"],"placetype":["aat:300000241"],"id":7359767,"name:xx":"Rancho Cuatro Vientos"}}
>>>>>>> 03f74aca74312dbeaf24d7e61306dd6a786dc3d0
