{
  "id": 2063112,
  "type": "Feature",
  "properties": {
    "tgn:hierarchy":[
        "tgn:2063112",
        "tgn:1000001",
        "tgn:2001411",
        "tgn:7012149",
        "tgn:7007526",
        "tgn:7029392"
    ],
    "tgn:id":2063112,
    "tgn:name":"Rowland",
    "tgn:placetype":[
        "aat:300008347",
        "aat:300387210"
    ]
},
  "bbox": [],
  "geometry": {"coordinates":[-115.6667,41.9333],"type":"Point"}
}