{
  "id": 1091922,
  "type": "Feature",
  "properties": {
    "tgn:hierarchy":[
        "tgn:1091922",
        "tgn:7001242",
        "tgn:1001838",
        "tgn:1000182",
        "tgn:7029392"
    ],
    "tgn:id":1091922,
    "tgn:name":"Bununu",
    "tgn:placetype":[
        "aat:300008347"
    ]
},
  "bbox": [],
  "geometry": {"coordinates":[9.5833,10.0167],"type":"Point"}
}