{
  "id": 2739950,
  "type": "Feature",
  "properties": {
    "tgn:hierarchy":[
        "tgn:2739950",
        "tgn:1000001",
        "tgn:2000590",
        "tgn:7012149",
        "tgn:7007253",
        "tgn:7029392"
    ],
    "tgn:id":2739950,
    "tgn:name":"Upper Gar Lake",
    "tgn:placetype":[
        "aat:300008680"
    ]
},
  "bbox": [],
  "geometry": {"coordinates":[-95.1167,43.3667],"type":"Point"}
}