{
  "id": 2743672,
  "type": "Feature",
  "properties": {
    "tgn:hierarchy":[
        "tgn:2743672",
        "tgn:1000001",
        "tgn:2001331",
        "tgn:7012149",
        "tgn:7007525",
        "tgn:7029392"
    ],
    "tgn:id":2743672,
    "tgn:name":"Vaughn Lake",
    "tgn:placetype":[
        "aat:300008680"
    ]
},
  "bbox": [],
  "geometry": {"coordinates":[-101.7333,42.3833],"type":"Point"}
}