{
  "id": 7391574,
  "type": "Feature",
  "properties": {
    "tgn:hierarchy":[
        "tgn:7391574",
        "tgn:1000001",
        "tgn:1001960",
        "tgn:7005560",
        "tgn:7029392"
    ],
    "tgn:id":7391574,
    "tgn:name":"Rancho La Sierrita",
    "tgn:placetype":[
        "aat:300008347"
    ]
},
  "bbox": [],
  "geometry": {"coordinates":[-111.25,28.516667],"type":"Point"}
}