<<<<<<< HEAD
{
  "id": 7023000,
  "type": "Feature",
  "properties": {
    "tgn:hierarchy":[
        "tgn:7023000",
        "tgn:1000001",
        "tgn:2001264",
        "tgn:7012149",
        "tgn:7007524",
        "tgn:7029392"
    ],
    "tgn:id":7023000,
    "tgn:name":"George Place",
    "tgn:placetype":[
        "aat:300008347"
    ]
},
  "bbox": [],
  "geometry": {"coordinates":[-109.4833,45.35],"type":"Point"}
}
=======
{"geometry":{"type":"Point","coordinates":[-109.483300,45.350000]},"type":"Feature","properties":{"hierarchy":["tgn:7023000","tgn:1000001","tgn:2001264","tgn:7012149","tgn:7007524","tgn:7029392"],"placetype":["aat:300008347"],"id":7023000,"name:xx":"George Place"}}
>>>>>>> 03f74aca74312dbeaf24d7e61306dd6a786dc3d0
