{
  "id": 2284992,
  "type": "Feature",
  "properties": {
    "tgn:hierarchy":[
        "tgn:2284992",
        "tgn:7002659",
        "tgn:1000001",
        "tgn:7012149",
        "tgn:2000029",
        "tgn:7029392"
    ],
    "tgn:id":2284992,
    "tgn:name":"Devil Den Branch",
    "tgn:placetype":[
        "aat:300008699"
    ]
},
  "bbox": [],
  "geometry": {"coordinates":[-87.85,34.3167],"type":"Point"}
}