{
  "id": 2632893,
  "type": "Feature",
  "properties": {
    "tgn:hierarchy":[
        "tgn:2632893",
        "tgn:1000001",
        "tgn:7012149",
        "tgn:2001449",
        "tgn:7007566",
        "tgn:7029392"
    ],
    "tgn:id":2632893,
    "tgn:name":"Rucker Lake",
    "tgn:placetype":[
        "aat:300008680"
    ]
},
  "bbox": [],
  "geometry": {"coordinates":[-107.05,36.3667],"type":"Point"}
}