<<<<<<< HEAD
{
  "id": 7472027,
  "type": "Feature",
  "properties": {
    "tgn:hierarchy":[
        "tgn:7472027",
        "tgn:1000004",
        "tgn:7467799",
        "tgn:1000141",
        "tgn:7029392"
    ],
    "tgn:id":7472027,
    "tgn:name":"Zhutang Guozhong",
    "tgn:placetype":[
        "aat:300006495"
    ]
},
  "bbox": [],
  "geometry": {"coordinates":[120.426275,23.864053],"type":"Point"}
}
=======
{"geometry":{"type":"Point","coordinates":[120.426275,23.864053]},"type":"Feature","properties":{"hierarchy":["tgn:7472027","tgn:1000004","tgn:7467799","tgn:1000141","tgn:7029392"],"placetype":["aat:300006495"],"id":7472027,"name:xx":"Zhutang Guozhong"}}
>>>>>>> 03f74aca74312dbeaf24d7e61306dd6a786dc3d0
