{
  "id": 7472027,
  "type": "Feature",
  "properties": {
    "tgn:hierarchy":[
        "tgn:7472027",
        "tgn:1000004",
        "tgn:7467799",
        "tgn:1000141",
        "tgn:7029392"
    ],
    "tgn:id":7472027,
    "tgn:name":"Zhutang Guozhong",
    "tgn:placetype":[
        "aat:300006495"
    ]
},
  "bbox": [],
  "geometry": {"coordinates":[120.426275,23.864053],"type":"Point"}
}