{
  "id": 2369243,
  "type": "Feature",
  "properties": {
    "tgn:hierarchy":[
        "tgn:2369243",
        "tgn:1000001",
        "tgn:7012149",
        "tgn:2001851",
        "tgn:7007825",
        "tgn:7029392"
    ],
    "tgn:id":2369243,
    "tgn:name":"Gum Spring Branch",
    "tgn:placetype":[
        "aat:300008699"
    ]
},
  "bbox": [],
  "geometry": {"coordinates":[-82.95,35.9667],"type":"Point"}
}