{
  "id": 1050115,
  "type": "Feature",
  "properties": {
    "tgn:hierarchy":[
        "tgn:1050115",
        "tgn:7002704",
        "tgn:1000003",
        "tgn:1000091",
        "tgn:7029392"
    ],
    "tgn:id":1050115,
    "tgn:name":"Dragalina",
    "tgn:placetype":[
        "aat:300008347"
    ]
},
  "bbox": [],
  "geometry": {"coordinates":[27.3167,44.4333],"type":"Point"}
}