{
  "id": 7406042,
  "type": "Feature",
  "properties": {
    "tgn:hierarchy":[
        "tgn:7406042",
        "tgn:7005585",
        "tgn:1000001",
        "tgn:7005560",
        "tgn:7029392"
    ],
    "tgn:id":7406042,
    "tgn:name":"Higueras",
    "tgn:placetype":[
        "aat:300008347"
    ]
},
  "bbox": [],
  "geometry": {"coordinates":[-101.766667,18.433333],"type":"Point"}
}