{
  "id": 7075782,
  "type": "Feature",
  "properties": {
    "tgn:hierarchy":[
        "tgn:7075782",
        "tgn:7000096",
        "tgn:1000003",
        "tgn:7000084",
        "tgn:7029392"
    ],
    "tgn:id":7075782,
    "tgn:name":"Belziger Landschaftswiesen",
    "tgn:placetype":[
        "aat:300008903"
    ]
},
  "bbox": [],
  "geometry": {"coordinates":[12.666667,52.216667],"type":"Point"}
}