{
  "id": 2456518,
  "type": "Feature",
  "properties": {
    "tgn:hierarchy":[
        "tgn:2456518",
        "tgn:1000001",
        "tgn:7012149",
        "tgn:2001903",
        "tgn:7007825",
        "tgn:7029392"
    ],
    "tgn:id":2456518,
    "tgn:name":"Little Indian Creek",
    "tgn:placetype":[
        "aat:300008706"
    ]
},
  "bbox": [],
  "geometry": {"coordinates":[-85.15,36.25],"type":"Point"}
}