{
  "id": 7429196,
  "type": "Feature",
  "properties": {
    "tgn:hierarchy":[
        "tgn:7429196",
        "tgn:7005583",
        "tgn:1000001",
        "tgn:7005560",
        "tgn:7029392"
    ],
    "tgn:id":7429196,
    "tgn:name":"Presa Guadalupe Victoria",
    "tgn:placetype":[
        "aat:300006191"
    ]
},
  "bbox": [],
  "geometry": {"coordinates":[-104.716667,23.933333],"type":"Point"}
}