{
  "id": 2620234,
  "type": "Feature",
  "properties": {
    "tgn:hierarchy":[
        "tgn:2620234",
        "tgn:1000001",
        "tgn:7012149",
        "tgn:2001500",
        "tgn:7007709",
        "tgn:7029392"
    ],
    "tgn:id":2620234,
    "tgn:name":"Ritters Lake",
    "tgn:placetype":[
        "aat:300006191"
    ]
},
  "bbox": [],
  "geometry": {"coordinates":[-79.7833,35.9833],"type":"Point"}
}