{
  "id": 7549674,
  "type": "Feature",
  "properties": {
    "tgn:hierarchy":[
        "tgn:7549674",
        "tgn:1000004",
        "tgn:7031781",
        "tgn:7000198",
        "tgn:7029392"
    ],
    "tgn:id":7549674,
    "tgn:name:en":"Dharambandha",
    "tgn:placetype":[
        "aat:300008347"
    ]
},
  "bbox": [],
  "geometry": {"coordinates":[82.4175,20.733333],"type":"Point"}
}