{
  "id": 7080222,
  "type": "Feature",
  "properties": {
    "tgn:hierarchy":[
        "tgn:7080222",
        "tgn:1000003",
        "tgn:7003685",
        "tgn:7000084",
        "tgn:7029392"
    ],
    "tgn:id":7080222,
    "tgn:name":"Zedlig",
    "tgn:placetype":[
        "aat:300008347"
    ]
},
  "bbox": [],
  "geometry": {"coordinates":[14.783333,51.366667],"type":"Point"}
}