{
  "id": 2175923,
  "type": "Feature",
  "properties": {
    "tgn:hierarchy":[
        "tgn:2175923",
        "tgn:7014201",
        "tgn:1000001",
        "tgn:7012149",
        "tgn:7007239",
        "tgn:7029392"
    ],
    "tgn:id":2175923,
    "tgn:name":"Black Ditch Bar",
    "tgn:placetype":[
        "aat:300132348"
    ]
},
  "bbox": [],
  "geometry": {"coordinates":[-75.5333,39.5167],"type":"Point"}
}