{
  "id": 2304553,
  "type": "Feature",
  "properties": {
    "tgn:hierarchy":[
        "tgn:2304553",
        "tgn:1000001",
        "tgn:1002601",
        "tgn:7012149",
        "tgn:7007159",
        "tgn:7029392"
    ],
    "tgn:id":2304553,
    "tgn:name":"East Aspetuck River",
    "tgn:placetype":[
        "aat:300008707"
    ]
},
  "bbox": [],
  "geometry": {"coordinates":[-73.35,41.6667],"type":"Point"}
}