{
  "id": 7300270,
  "type": "Feature",
  "properties": {
    "tgn:hierarchy":[
        "tgn:7300270",
        "tgn:7002836",
        "tgn:7016622",
        "tgn:1000003",
        "tgn:1000095",
        "tgn:7029392"
    ],
    "tgn:id":7300270,
    "tgn:name":"Tenagua",
    "tgn:placetype":[
        "aat:300008347"
    ]
},
  "bbox": [],
  "geometry": {"coordinates":[-17.733333,28.716667],"type":"Point"}
}