{
  "id": 7031364,
  "type": "Feature",
  "properties": {
    "tgn:hierarchy":[
        "tgn:7031364",
        "tgn:7002445",
        "tgn:1000003",
        "tgn:7008168",
        "tgn:7008591",
        "tgn:7029392"
    ],
    "tgn:id":7031364,
    "tgn:name:en":"Tackley",
    "tgn:placetype":[
        "aat:300008347",
        "aat:300008372"
    ]
},
  "bbox": [],
  "geometry": {"coordinates":[-1.316667,51.866667],"type":"Point"}
}