{
  "id": 2720157,
  "type": "Feature",
  "properties": {
    "tgn:hierarchy":[
        "tgn:2720157",
        "tgn:1000001",
        "tgn:7012149",
        "tgn:2001980",
        "tgn:7007826",
        "tgn:7029392"
    ],
    "tgn:id":2720157,
    "tgn:name":"Threemile Draw",
    "tgn:placetype":[
        "aat:300008761"
    ]
},
  "bbox": [],
  "geometry": {"coordinates":[-100.35,29.8333],"type":"Point"}
}