{
  "id": 2539663,
  "type": "Feature",
  "properties": {
    "tgn:hierarchy":[
        "tgn:2539663",
        "tgn:7013349",
        "tgn:1000001",
        "tgn:7012149",
        "tgn:7007708",
        "tgn:7029392"
    ],
    "tgn:id":2539663,
    "tgn:name":"New Seeding Spring Number One",
    "tgn:placetype":[
        "aat:300008697"
    ]
},
  "bbox": [],
  "geometry": {"coordinates":[-117.2833,44.4833],"type":"Point"}
}