{
  "id": 2010319,
  "type": "Feature",
  "properties": {
    "tgn:hierarchy":[
        "tgn:2010319",
        "tgn:1000001",
        "tgn:7012149",
        "tgn:7007157",
        "tgn:7014004",
        "tgn:7029392"
    ],
    "tgn:id":2010319,
    "tgn:name":"Bootjack",
    "tgn:placetype":[
        "aat:300008347"
    ]
},
  "bbox": [],
  "geometry": {"coordinates":[-119.8833,37.45],"type":"Point"}
}