{
  "id": 2164619,
  "type": "Feature",
  "properties": {
    "tgn:hierarchy":[
        "tgn:2164619",
        "tgn:1000001",
        "tgn:2001426",
        "tgn:7012149",
        "tgn:7007564",
        "tgn:7029392"
    ],
    "tgn:id":2164619,
    "tgn:name":"Berrys River",
    "tgn:placetype":[
        "aat:300008707"
    ]
},
  "bbox": [],
  "geometry": {"coordinates":[-71.1167,43.3333],"type":"Point"}
}