{
  "id": 2325414,
  "type": "Feature",
  "properties": {
    "tgn:hierarchy":[
        "tgn:2325414",
        "tgn:1000001",
        "tgn:2002134",
        "tgn:7012149",
        "tgn:7007828",
        "tgn:7029392"
    ],
    "tgn:id":2325414,
    "tgn:name":"Ferry Hill",
    "tgn:placetype":[
        "aat:300008798"
    ]
},
  "bbox": [],
  "geometry": {"coordinates":[-72.6833,43.9833],"type":"Point"}
}