{
  "id": 2460888,
  "type": "Feature",
  "properties": {
    "tgn:hierarchy":[
        "tgn:2460888",
        "tgn:1000001",
        "tgn:7012149",
        "tgn:2000911",
        "tgn:7007256",
        "tgn:7029392"
    ],
    "tgn:id":2460888,
    "tgn:name":"Little Sixmile Creek",
    "tgn:placetype":[
        "aat:300008706"
    ]
},
  "bbox": [],
  "geometry": {"coordinates":[-93.0167,31.0333],"type":"Point"}
}