{
  "id": 7495949,
  "type": "Feature",
  "properties": {
    "tgn:hierarchy":[
        "tgn:7495949",
        "tgn:7487020",
        "tgn:1000004",
        "tgn:1000141",
        "tgn:7029392"
    ],
    "tgn:id":7495949,
    "tgn:name":"Liyu Yihao Qiao",
    "tgn:placetype":[
        "aat:300007836"
    ]
},
  "bbox": [],
  "geometry": {"coordinates":[120.760472,24.347239],"type":"Point"}
}