{
  "id": 2135278,
  "type": "Feature",
  "properties": {
    "tgn:hierarchy":[
        "tgn:2135278",
        "tgn:1000001",
        "tgn:2001485",
        "tgn:7012149",
        "tgn:7007709",
        "tgn:7029392"
    ],
    "tgn:id":2135278,
    "tgn:name":"Antioch",
    "tgn:placetype":[
        "aat:300008347"
    ]
},
  "bbox": [],
  "geometry": {"coordinates":[-78.7167,34.2333],"type":"Point"}
}