{
  "id": 1046102,
  "type": "Feature",
  "properties": {
    "tgn:hierarchy":[
        "tgn:1046102",
        "tgn:7005126",
        "tgn:1000003",
        "tgn:7003120",
        "tgn:1000080",
        "tgn:7029392"
    ],
    "tgn:id":1046102,
    "tgn:name":"Ponte di Nava",
    "tgn:placetype":[
        "aat:300008347"
    ]
},
  "bbox": [],
  "geometry": {"coordinates":[7.866667,44.066667],"type":"Point"}
}