{
  "id": 2754617,
  "type": "Feature",
  "properties": {
    "tgn:hierarchy":[
        "tgn:2754617",
        "tgn:1000001",
        "tgn:7012149",
        "tgn:1002387",
        "tgn:7007710",
        "tgn:7029392"
    ],
    "tgn:id":2754617,
    "tgn:name":"Waynesboro Reservoir",
    "tgn:placetype":[
        "aat:300006191"
    ]
},
  "bbox": [],
  "geometry": {"coordinates":[-77.4667,39.7833],"type":"Point"}
}