{
  "id": 7342543,
  "type": "Feature",
  "properties": {
    "tgn:hierarchy":[
        "tgn:7342543",
        "tgn:7002811",
        "tgn:1000003",
        "tgn:7003837",
        "tgn:1000095",
        "tgn:7029392"
    ],
    "tgn:id":7342543,
    "tgn:name":"Casta\u00f1os, Puerto de los",
    "tgn:placetype":[
        "aat:300259572"
    ]
},
  "bbox": [],
  "geometry": {"coordinates":[-6.583333,39.35],"type":"Point"}
}