{
  "id": 2297153,
  "type": "Feature",
  "properties": {
    "tgn:hierarchy":[
        "tgn:2297153",
        "tgn:1000001",
        "tgn:7012149",
        "tgn:2002252",
        "tgn:7007920",
        "tgn:7029392"
    ],
    "tgn:id":2297153,
    "tgn:name":"Dry Creek",
    "tgn:placetype":[
        "aat:300008706"
    ]
},
  "bbox": [],
  "geometry": {"coordinates":[-117.1833,47.05],"type":"Point"}
}