{
  "id": 7376584,
  "type": "Feature",
  "properties": {
    "tgn:hierarchy":[
        "tgn:7376584",
        "tgn:7005581",
        "tgn:1000001",
        "tgn:7005560",
        "tgn:7029392"
    ],
    "tgn:id":7376584,
    "tgn:name":"La Tinaja",
    "tgn:placetype":[
        "aat:300008347"
    ]
},
  "bbox": [],
  "geometry": {"coordinates":[-107.833333,28.75],"type":"Point"}
}