{
  "id": 2592876,
  "type": "Feature",
  "properties": {
    "tgn:hierarchy":[
        "tgn:2592876",
        "tgn:1000001",
        "tgn:7012149",
        "tgn:1002782",
        "tgn:7007710",
        "tgn:7029392"
    ],
    "tgn:id":2592876,
    "tgn:name":"Poplar",
    "tgn:placetype":[
        "aat:300008347"
    ]
},
  "bbox": [],
  "geometry": {"coordinates":[-75.15,39.95],"type":"Point"}
}