{
  "id": 7059030,
  "type": "Feature",
  "properties": {
    "tgn:hierarchy":[
        "tgn:7059030",
        "tgn:7005852",
        "tgn:1000003",
        "tgn:7003237",
        "tgn:1000080",
        "tgn:7029392"
    ],
    "tgn:id":7059030,
    "tgn:name":"Albate",
    "tgn:placetype":[
        "aat:300008347"
    ]
},
  "bbox": [],
  "geometry": {"coordinates":[9.116667,45.783333],"type":"Point"}
}