<<<<<<< HEAD
{
  "id": 2158011,
  "type": "Feature",
  "properties": {
    "tgn:hierarchy":[
        "tgn:2158011",
        "tgn:1000001",
        "tgn:2000921",
        "tgn:7012149",
        "tgn:7007515",
        "tgn:7029392"
    ],
    "tgn:id":2158011,
    "tgn:name":"Beaver Mountain",
    "tgn:placetype":[
        "aat:300008798"
    ]
},
  "bbox": [],
  "geometry": {"coordinates":[-70.6333,44.8667],"type":"Point"}
}
=======
{"geometry":{"type":"Point","coordinates":[-70.633300,44.866700]},"type":"Feature","properties":{"hierarchy":["tgn:2158011","tgn:1000001","tgn:2000921","tgn:7012149","tgn:7007515","tgn:7029392"],"placetype":["aat:300008798"],"id":2158011,"name:xx":"Beaver Mountain"}}
>>>>>>> 03f74aca74312dbeaf24d7e61306dd6a786dc3d0
