{
  "id": 7531270,
  "type": "Feature",
  "properties": {
    "tgn:hierarchy":[
        "tgn:7531270",
        "tgn:7001242",
        "tgn:7016833",
        "tgn:1001092",
        "tgn:7029392"
    ],
    "tgn:id":7531270,
    "tgn:name:en":"Qah\u0101 Company",
    "tgn:placetype":[
        "aat:300007043"
    ]
},
  "bbox": [],
  "geometry": {"coordinates":[31.198447,30.276174],"type":"Point"}
}