{
  "id": 7320048,
  "type": "Feature",
  "properties": {
    "tgn:hierarchy":[
        "tgn:7320048",
        "tgn:1001657",
        "tgn:1000049",
        "tgn:1000002",
        "tgn:7029392"
    ],
    "tgn:id":7320048,
    "tgn:name":"Aldea, Punta",
    "tgn:placetype":[
        "aat:300386846"
    ]
},
  "bbox": [],
  "geometry": {"coordinates":[-71.652222,-30.270556],"type":"Point"}
}