{
  "id": 2418761,
  "type": "Feature",
  "properties": {
    "tgn:hierarchy":[
        "tgn:2418761",
        "tgn:1000001",
        "tgn:7012149",
        "tgn:1002422",
        "tgn:7007251",
        "tgn:7029392"
    ],
    "tgn:id":2418761,
    "tgn:name":"Jalapa",
    "tgn:placetype":[
        "aat:300008347"
    ]
},
  "bbox": [],
  "geometry": {"coordinates":[-90.3167,39.2167],"type":"Point"}
}