<<<<<<< HEAD
{
  "id": 7022047,
  "type": "Feature",
  "properties": {
    "tgn:hierarchy":[
        "tgn:7022047",
        "tgn:1000001",
        "tgn:7012149",
        "tgn:2002164",
        "tgn:7007919",
        "tgn:7029392"
    ],
    "tgn:id":7022047,
    "tgn:name":"Falls Branch",
    "tgn:placetype":[
        "aat:300008699"
    ]
},
  "bbox": [],
  "geometry": {"coordinates":[-81.0833,36.75],"type":"Point"}
}
=======
{"geometry":{"type":"Point","coordinates":[-81.083300,36.750000]},"type":"Feature","properties":{"hierarchy":["tgn:7022047","tgn:1000001","tgn:7012149","tgn:2002164","tgn:7007919","tgn:7029392"],"placetype":["aat:300008699"],"id":7022047,"name:xx":"Falls Branch"}}
>>>>>>> 03f74aca74312dbeaf24d7e61306dd6a786dc3d0
