{
  "id": 2784182,
  "type": "Feature",
  "properties": {
    "tgn:hierarchy":[
        "tgn:2784182",
        "tgn:1000001",
        "tgn:7016172",
        "tgn:7012149",
        "tgn:2000125",
        "tgn:7029392"
    ],
    "tgn:id":2784182,
    "tgn:name":"Yancopin Lake",
    "tgn:placetype":[
        "aat:300008905"
    ]
},
  "bbox": [],
  "geometry": {"coordinates":[-91.1833,33.9167],"type":"Point"}
}