{
  "id": 7441381,
  "type": "Feature",
  "properties": {
    "tgn:hierarchy":[
        "tgn:7441381",
        "tgn:7005583",
        "tgn:1000001",
        "tgn:7005560",
        "tgn:7029392"
    ],
    "tgn:id":7441381,
    "tgn:name":"Santa Ana",
    "tgn:placetype":[
        "aat:300008347"
    ]
},
  "bbox": [],
  "geometry": {"coordinates":[-105.733333,24.35],"type":"Point"}
}