{
  "id": 7384350,
  "type": "Feature",
  "properties": {
    "tgn:hierarchy":[
        "tgn:7384350",
        "tgn:7005581",
        "tgn:1000001",
        "tgn:7005560",
        "tgn:7029392"
    ],
    "tgn:id":7384350,
    "tgn:name":"Pahu\u00edrachic",
    "tgn:placetype":[
        "aat:300008347"
    ]
},
  "bbox": [],
  "geometry": {"coordinates":[-107.466667,28.45],"type":"Point"}
}