{
  "id": 2142136,
  "type": "Feature",
  "properties": {
    "tgn:hierarchy":[
        "tgn:2142136",
        "tgn:7014651",
        "tgn:1000001",
        "tgn:7012149",
        "tgn:7007516",
        "tgn:7029392"
    ],
    "tgn:id":2142136,
    "tgn:name":"Back Creek Point",
    "tgn:placetype":[
        "aat:300008850"
    ]
},
  "bbox": [],
  "geometry": {"coordinates":[-76.4333,39.1167],"type":"Point"}
}