{
  "id": 2753975,
  "type": "Feature",
  "properties": {
    "tgn:hierarchy":[
        "tgn:2753975",
        "tgn:1000001",
        "tgn:7012149",
        "tgn:2002191",
        "tgn:7007919",
        "tgn:7029392"
    ],
    "tgn:id":2753975,
    "tgn:name":"Watson Gap Branch",
    "tgn:placetype":[
        "aat:300008699"
    ]
},
  "bbox": [],
  "geometry": {"coordinates":[-81.7167,36.9167],"type":"Point"}
}