{
  "id": 2238522,
  "type": "Feature",
  "properties": {
    "tgn:hierarchy":[
        "tgn:2238522",
        "tgn:1000001",
        "tgn:2002256",
        "tgn:7012149",
        "tgn:7013961",
        "tgn:7029392"
    ],
    "tgn:id":2238522,
    "tgn:name":"Chop Fork",
    "tgn:placetype":[
        "aat:300008699"
    ]
},
  "bbox": [],
  "geometry": {"coordinates":[-80.5167,38.8333],"type":"Point"}
}