{
  "id": 2393905,
  "type": "Feature",
  "properties": {
    "tgn:hierarchy":[
        "tgn:2393905",
        "tgn:1000001",
        "tgn:7014423",
        "tgn:7012149",
        "tgn:7007517",
        "tgn:7029392"
    ],
    "tgn:id":2393905,
    "tgn:name":"Hog Neck",
    "tgn:placetype":[
        "aat:300008850"
    ]
},
  "bbox": [],
  "geometry": {"coordinates":[-70.6333,41.7167],"type":"Point"}
}