<<<<<<< HEAD
{
  "id": 7170540,
  "type": "Feature",
  "properties": {
    "tgn:hierarchy":[
        "tgn:7170540",
        "tgn:1000003",
        "tgn:7003678",
        "tgn:7000084",
        "tgn:7029392"
    ],
    "tgn:id":7170540,
    "tgn:name":"Henriettenthal",
    "tgn:placetype":[
        "aat:300000206"
    ]
},
  "bbox": [],
  "geometry": {"coordinates":[8.25,50.25],"type":"Point"}
}
=======
{"geometry":{"type":"Point","coordinates":[8.250000,50.250000]},"type":"Feature","properties":{"hierarchy":["tgn:7170540","tgn:1000003","tgn:7003678","tgn:7000084","tgn:7029392"],"placetype":["aat:300000206"],"id":7170540,"name:xx":"Henriettenthal"}}
>>>>>>> 03f74aca74312dbeaf24d7e61306dd6a786dc3d0
