{
  "id": 2652764,
  "type": "Feature",
  "properties": {
    "tgn:hierarchy":[
        "tgn:2652764",
        "tgn:1000001",
        "tgn:7012149",
        "tgn:2001713",
        "tgn:7007708",
        "tgn:7029392"
    ],
    "tgn:id":2652764,
    "tgn:name":"Serpentine Gulch",
    "tgn:placetype":[
        "aat:300008699"
    ]
},
  "bbox": [],
  "geometry": {"coordinates":[-123.5167,42.5167],"type":"Point"}
}