{
  "id": 7580851,
  "type": "Feature",
  "properties": {
    "tgn:hierarchy":[
        "tgn:7580851",
        "tgn:1000004",
        "tgn:7000198",
        "tgn:7000799",
        "tgn:7029392"
    ],
    "tgn:id":7580851,
    "tgn:name:en":"Sumdo",
    "tgn:placetype":[
        "aat:300008347"
    ]
},
  "bbox": [],
  "geometry": {"coordinates":[78.745686,35.082439],"type":"Point"}
}