{
  "id": 2677488,
  "type": "Feature",
  "properties": {
    "tgn:hierarchy":[
        "tgn:2677488",
        "tgn:1000001",
        "tgn:7012149",
        "tgn:2000182",
        "tgn:7007157",
        "tgn:7029392"
    ],
    "tgn:id":2677488,
    "tgn:name":"South Central Drain One",
    "tgn:placetype":[
        "aat:300006075"
    ]
},
  "bbox": [],
  "geometry": {"coordinates":[-115.4333,32.8167],"type":"Point"}
}