{
  "id": 2360822,
  "type": "Feature",
  "properties": {
    "tgn:hierarchy":[
        "tgn:2360822",
        "tgn:1000001",
        "tgn:7012149",
        "tgn:2001758",
        "tgn:7007712",
        "tgn:7029392"
    ],
    "tgn:id":2360822,
    "tgn:name":"Grassy Lake",
    "tgn:placetype":[
        "aat:300008680"
    ]
},
  "bbox": [],
  "geometry": {"coordinates":[-79.2667,33.8667],"type":"Point"}
}