{
  "id": 7041885,
  "type": "Feature",
  "properties": {
    "tgn:hierarchy":[
        "tgn:7041885",
        "tgn:7003005",
        "tgn:7003014",
        "tgn:1000003",
        "tgn:1000080",
        "tgn:7029392"
    ],
    "tgn:id":7041885,
    "tgn:name":"San Cristoforo",
    "tgn:placetype":[
        "aat:300008347"
    ]
},
  "bbox": [],
  "geometry": {"coordinates":[15.55,40.083333],"type":"Point"}
}