{
  "id": 2665762,
  "type": "Feature",
  "properties": {
    "tgn:hierarchy":[
        "tgn:2665762",
        "tgn:1002153",
        "tgn:1000001",
        "tgn:7012149",
        "tgn:7007710",
        "tgn:7029392"
    ],
    "tgn:id":2665762,
    "tgn:name":"Sipes Run",
    "tgn:placetype":[
        "aat:300008699"
    ]
},
  "bbox": [],
  "geometry": {"coordinates":[-79.6667,40.7833],"type":"Point"}
}