{
  "id": 2116618,
  "type": "Feature",
  "properties": {
    "tgn:hierarchy":[
        "tgn:2116618",
        "tgn:1000001",
        "tgn:7012149",
        "tgn:7018871",
        "tgn:7007920",
        "tgn:7029392"
    ],
    "tgn:id":2116618,
    "tgn:name":"Richmond Highlands",
    "tgn:placetype":[
        "aat:300008347"
    ]
},
  "bbox": [],
  "geometry": {"coordinates":[-122.3333,47.75],"type":"Point"}
}