<<<<<<< HEAD
{
  "id": 2335332,
  "type": "Feature",
  "properties": {
    "tgn:hierarchy":[
        "tgn:2335332",
        "tgn:7002659",
        "tgn:1000001",
        "tgn:7012149",
        "tgn:2000047",
        "tgn:7029392"
    ],
    "tgn:id":2335332,
    "tgn:name":"Fort Hollow",
    "tgn:placetype":[
        "aat:300008761"
    ]
},
  "bbox": [],
  "geometry": {"coordinates":[-86.3,34.5167],"type":"Point"}
}
=======
{"geometry":{"type":"Point","coordinates":[-86.300000,34.516700]},"type":"Feature","properties":{"hierarchy":["tgn:2335332","tgn:7002659","tgn:1000001","tgn:7012149","tgn:2000047","tgn:7029392"],"placetype":["aat:300008761"],"id":2335332,"name:xx":"Fort Hollow"}}
>>>>>>> 03f74aca74312dbeaf24d7e61306dd6a786dc3d0
