{
  "id": 2021102,
  "type": "Feature",
  "properties": {
    "tgn:hierarchy":[
        "tgn:2021102",
        "tgn:1000001",
        "tgn:1002479",
        "tgn:7012149",
        "tgn:7007240",
        "tgn:7029392"
    ],
    "tgn:id":2021102,
    "tgn:name":"Ruskin",
    "tgn:placetype":[
        "aat:300008347"
    ]
},
  "bbox": [],
  "geometry": {"coordinates":[-82.4333,27.7167],"type":"Point"}
}