{
  "id": 7506818,
  "type": "Feature",
  "properties": {
    "tgn:hierarchy":[
        "tgn:7506818",
        "tgn:1009227",
        "tgn:1000226",
        "tgn:7018437",
        "tgn:1000006",
        "tgn:7029392"
    ],
    "tgn:id":7506818,
    "tgn:name:en":"Raupo Creek",
    "tgn:placetype":[
        "aat:300008699"
    ]
},
  "bbox": [],
  "geometry": {"coordinates":[169.266667,-44.966667],"type":"Point"}
}