{
  "id": 2559518,
  "type": "Feature",
  "properties": {
    "tgn:hierarchy":[
        "tgn:2559518",
        "tgn:1000001",
        "tgn:7012149",
        "tgn:2001718",
        "tgn:7007708",
        "tgn:7029392"
    ],
    "tgn:id":2559518,
    "tgn:name":"Ontario Island",
    "tgn:placetype":[
        "aat:300008791"
    ]
},
  "bbox": [],
  "geometry": {"coordinates":[-116.95,44.0333],"type":"Point"}
}