{
  "id": 7226384,
  "type": "Feature",
  "properties": {
    "tgn:hierarchy":[
        "tgn:7226384",
        "tgn:7002706",
        "tgn:7002705",
        "tgn:1000003",
        "tgn:1000074",
        "tgn:7029392"
    ],
    "tgn:id":7226384,
    "tgn:name":"Pafr\u00f3ni R\u00e9ma",
    "tgn:placetype":[
        "aat:300008699"
    ]
},
  "bbox": [],
  "geometry": {"coordinates":[21.366944,39.235556],"type":"Point"}
}