{
  "id": 7469768,
  "type": "Feature",
  "properties": {
    "tgn:hierarchy":[
        "tgn:7469768",
        "tgn:7498210",
        "tgn:1000004",
        "tgn:1000141",
        "tgn:7029392"
    ],
    "tgn:id":7469768,
    "tgn:name":"Qipan Shan",
    "tgn:placetype":[
        "aat:300008777"
    ]
},
  "bbox": [],
  "geometry": {"coordinates":[119.933333,25.966667],"type":"Point"}
}