{
  "id": 2713528,
  "type": "Feature",
  "properties": {
    "tgn:hierarchy":[
        "tgn:2713528",
        "tgn:2001623",
        "tgn:1000001",
        "tgn:7012149",
        "tgn:7007707",
        "tgn:7029392"
    ],
    "tgn:id":2713528,
    "tgn:name":"Teague Hollow",
    "tgn:placetype":[
        "aat:300008761"
    ]
},
  "bbox": [],
  "geometry": {"coordinates":[-94.7667,35.6667],"type":"Point"}
}