{
  "id": 2740096,
  "type": "Feature",
  "properties": {
    "tgn:hierarchy":[
        "tgn:2740096",
        "tgn:1000001",
        "tgn:7012149",
        "tgn:2001456",
        "tgn:7007566",
        "tgn:7029392"
    ],
    "tgn:id":2740096,
    "tgn:name":"Upper Holdup Tank",
    "tgn:placetype":[
        "aat:300006191"
    ]
},
  "bbox": [],
  "geometry": {"coordinates":[-107.4833,33.6167],"type":"Point"}
}