{
  "id": 2019262,
  "type": "Feature",
  "properties": {
    "tgn:hierarchy":[
        "tgn:2019262",
        "tgn:1000001",
        "tgn:7012149",
        "tgn:1002631",
        "tgn:7007240",
        "tgn:7029392"
    ],
    "tgn:id":2019262,
    "tgn:name":"Fairfield",
    "tgn:placetype":[
        "aat:300008347"
    ]
},
  "bbox": [],
  "geometry": {"coordinates":[-82.25,29.3667],"type":"Point"}
}