{
  "id": 2726361,
  "type": "Feature",
  "properties": {
    "tgn:hierarchy":[
        "tgn:2726361",
        "tgn:7002659",
        "tgn:1000001",
        "tgn:7012149",
        "tgn:2000029",
        "tgn:7029392"
    ],
    "tgn:id":2726361,
    "tgn:name":"Town Branch",
    "tgn:placetype":[
        "aat:300008699"
    ]
},
  "bbox": [],
  "geometry": {"coordinates":[-87.7333,34.5167],"type":"Point"}
}