{
  "id": 2130195,
  "type": "Feature",
  "properties": {
    "tgn:hierarchy":[
        "tgn:2130195",
        "tgn:1000001",
        "tgn:7012149",
        "tgn:1003018",
        "tgn:7007919",
        "tgn:7029392"
    ],
    "tgn:id":2130195,
    "tgn:name":"Allen Point",
    "tgn:placetype":[
        "aat:300008850"
    ]
},
  "bbox": [],
  "geometry": {"coordinates":[-76.55,38.0167],"type":"Point"}
}