{
  "id": 2152543,
  "type": "Feature",
  "properties": {
    "tgn:hierarchy":[
        "tgn:2152543",
        "tgn:1000001",
        "tgn:7012149",
        "tgn:2001521",
        "tgn:7007709",
        "tgn:7029392"
    ],
    "tgn:id":2152543,
    "tgn:name":"Bay, Lake",
    "tgn:placetype":[
        "aat:300006191"
    ]
},
  "bbox": [],
  "geometry": {"coordinates":[-79.2833,35.1833],"type":"Point"}
}