{
  "id": 7555884,
  "type": "Feature",
  "properties": {
    "tgn:hierarchy":[
        "tgn:7555884",
        "tgn:1000004",
        "tgn:7000198",
        "tgn:1001886",
        "tgn:7029392"
    ],
    "tgn:id":7555884,
    "tgn:name:en":"Perintalmanna",
    "tgn:placetype":[
        "aat:300008347"
    ]
},
  "bbox": [],
  "geometry": {"coordinates":[76.233333,10.983333],"type":"Point"}
}