{
  "id": 2731308,
  "type": "Feature",
  "properties": {
    "tgn:hierarchy":[
        "tgn:2731308",
        "tgn:1000001",
        "tgn:1002278",
        "tgn:7012149",
        "tgn:7007710",
        "tgn:7029392"
    ],
    "tgn:id":2731308,
    "tgn:name":"Tuckers Run",
    "tgn:placetype":[
        "aat:300008699"
    ]
},
  "bbox": [],
  "geometry": {"coordinates":[-78.65,40.8333],"type":"Point"}
}