{
  "id": 2319684,
  "type": "Feature",
  "properties": {
    "tgn:hierarchy":[
        "tgn:2319684",
        "tgn:1000001",
        "tgn:1002293",
        "tgn:7012149",
        "tgn:7007708",
        "tgn:7029392"
    ],
    "tgn:id":2319684,
    "tgn:name":"Eureka Bar",
    "tgn:placetype":[
        "aat:300132348"
    ]
},
  "bbox": [],
  "geometry": {"coordinates":[-123.2167,46.15],"type":"Point"}
}