{
  "id": 7501029,
  "type": "Feature",
  "properties": {
    "tgn:hierarchy":[
        "tgn:7501029",
        "tgn:7487020",
        "tgn:1000004",
        "tgn:1000141",
        "tgn:7029392"
    ],
    "tgn:id":7501029,
    "tgn:name":"Guiziwo",
    "tgn:placetype":[
        "aat:300008347"
    ]
},
  "bbox": [],
  "geometry": {"coordinates":[120.688333,24.459167],"type":"Point"}
}