<<<<<<< HEAD
{
  "id": 2151669,
  "type": "Feature",
  "properties": {
    "tgn:hierarchy":[
        "tgn:2151669",
        "tgn:1000001",
        "tgn:7012149",
        "tgn:2001676",
        "tgn:7007707",
        "tgn:7029392"
    ],
    "tgn:id":2151669,
    "tgn:name":"Battle Creek",
    "tgn:placetype":[
        "aat:300008706"
    ]
},
  "bbox": [],
  "geometry": {"coordinates":[-96.2833,35.4167],"type":"Point"}
}
=======
{"geometry":{"type":"Point","coordinates":[-96.283300,35.416700]},"type":"Feature","properties":{"hierarchy":["tgn:2151669","tgn:1000001","tgn:7012149","tgn:2001676","tgn:7007707","tgn:7029392"],"placetype":["aat:300008706"],"id":2151669,"name:xx":"Battle Creek"}}
>>>>>>> 03f74aca74312dbeaf24d7e61306dd6a786dc3d0
