{
  "id": 2534538,
  "type": "Feature",
  "properties": {
    "tgn:hierarchy":[
        "tgn:2534538",
        "tgn:1000001",
        "tgn:7012149",
        "tgn:2001300",
        "tgn:7007524",
        "tgn:7029392"
    ],
    "tgn:id":2534538,
    "tgn:name":"NW NW Section 21 Mine",
    "tgn:placetype":[
        "aat:300000390"
    ]
},
  "bbox": [],
  "geometry": {"coordinates":[-114.3167,45.5667],"type":"Point"}
}