{
  "id": 2373150,
  "type": "Feature",
  "properties": {
    "tgn:hierarchy":[
        "tgn:2373150",
        "tgn:1000001",
        "tgn:7012149",
        "tgn:2001918",
        "tgn:7007825",
        "tgn:7029392"
    ],
    "tgn:id":2373150,
    "tgn:name":"Halls Mill Pond",
    "tgn:placetype":[
        "aat:300006191"
    ]
},
  "bbox": [],
  "geometry": {"coordinates":[-82.4667,36.45],"type":"Point"}
}