{
  "id": 7567166,
  "type": "Feature",
  "properties": {
    "tgn:hierarchy":[
        "tgn:7567166",
        "tgn:1000004",
        "tgn:1001871",
        "tgn:7000198",
        "tgn:7029392"
    ],
    "tgn:id":7567166,
    "tgn:name:en":"Abdull\u0101pur",
    "tgn:placetype":[
        "aat:300008347"
    ]
},
  "bbox": [],
  "geometry": {"coordinates":[76.074061,28.107981],"type":"Point"}
}