{
  "id": 1049704,
  "type": "Feature",
  "properties": {
    "tgn:hierarchy":[
        "tgn:1049704",
        "tgn:7003825",
        "tgn:1000003",
        "tgn:1000090",
        "tgn:7029392"
    ],
    "tgn:id":1049704,
    "tgn:name":"Avis",
    "tgn:placetype":[
        "aat:300008347",
        "aat:300387218"
    ]
},
  "bbox": [],
  "geometry": {"coordinates":[-7.891,39.053],"type":"Point"}
}