{
  "id": 1067148,
  "type": "Feature",
  "properties": {
    "tgn:hierarchy":[
        "tgn:1067148",
        "tgn:1000004",
        "tgn:7002077",
        "tgn:1000111",
        "tgn:7029392"
    ],
    "tgn:id":1067148,
    "tgn:name":"Chedaoyu",
    "tgn:placetype":[
        "aat:300008347"
    ]
},
  "bbox": [],
  "geometry": {"coordinates":[117.95,40.3667],"type":"Point"}
}