{
  "id": 2371675,
  "type": "Feature",
  "properties": {
    "tgn:hierarchy":[
        "tgn:2371675",
        "tgn:1000001",
        "tgn:7012149",
        "tgn:2001286",
        "tgn:7007524",
        "tgn:7029392"
    ],
    "tgn:id":2371675,
    "tgn:name":"Hale Creek Mine",
    "tgn:placetype":[
        "aat:300000390"
    ]
},
  "bbox": [],
  "geometry": {"coordinates":[-115.9667,48.45],"type":"Point"}
}