{
  "id": 7048816,
  "type": "Feature",
  "properties": {
    "tgn:hierarchy":[
        "tgn:7048816",
        "tgn:1003464",
        "tgn:1000003",
        "tgn:7003241",
        "tgn:1000080",
        "tgn:7029392"
    ],
    "tgn:id":7048816,
    "tgn:name":"Chiaro, Torrente",
    "tgn:placetype":[
        "aat:300008699"
    ]
},
  "bbox": [],
  "geometry": {"coordinates":[14.116667,41.583333],"type":"Point"}
}