{
  "id": 1060133,
  "type": "Feature",
  "properties": {
    "tgn:hierarchy":[
        "tgn:1060133",
        "tgn:1000004",
        "tgn:7013571",
        "tgn:7018214",
        "tgn:7002435",
        "tgn:7029392"
    ],
    "tgn:id":1060133,
    "tgn:name":"Tambey",
    "tgn:placetype":[
        "aat:300008347"
    ]
},
  "bbox": [],
  "geometry": {"coordinates":[71.9167,71.5167],"type":"Point"}
}