{
  "id": 7572060,
  "type": "Feature",
  "properties": {
    "tgn:hierarchy":[
        "tgn:7572060",
        "tgn:1000004",
        "tgn:7000198",
        "tgn:7016788",
        "tgn:7029392"
    ],
    "tgn:id":7572060,
    "tgn:name:en":"Gandher",
    "tgn:placetype":[
        "aat:300008347"
    ]
},
  "bbox": [],
  "geometry": {"coordinates":[75.174013,25.689788],"type":"Point"}
}