<<<<<<< HEAD
{
  "id": 7177548,
  "type": "Feature",
  "properties": {
    "tgn:hierarchy":[
        "tgn:7177548",
        "tgn:1000003",
        "tgn:7003682",
        "tgn:7000084",
        "tgn:7029392"
    ],
    "tgn:id":7177548,
    "tgn:name":"Hanseneck",
    "tgn:placetype":[
        "aat:300008777"
    ]
},
  "bbox": [],
  "geometry": {"coordinates":[7.8,49.233333],"type":"Point"}
}
=======
{"geometry":{"type":"Point","coordinates":[7.800000,49.233333]},"type":"Feature","properties":{"hierarchy":["tgn:7177548","tgn:1000003","tgn:7003682","tgn:7000084","tgn:7029392"],"placetype":["aat:300008777"],"id":7177548,"name:xx":"Hanseneck"}}
>>>>>>> 03f74aca74312dbeaf24d7e61306dd6a786dc3d0
