{
  "id": 2221813,
  "type": "Feature",
  "properties": {
    "tgn:hierarchy":[
        "tgn:2221813",
        "tgn:1000001",
        "tgn:7012149",
        "tgn:2001032",
        "tgn:7007521",
        "tgn:7029392"
    ],
    "tgn:id":2221813,
    "tgn:name":"Carlson Lake",
    "tgn:placetype":[
        "aat:300008680"
    ]
},
  "bbox": [],
  "geometry": {"coordinates":[-94.95,45.2167],"type":"Point"}
}