{
  "id": 7470418,
  "type": "Feature",
  "properties": {
    "tgn:hierarchy":[
        "tgn:7470418",
        "tgn:7487020",
        "tgn:1000004",
        "tgn:1000141",
        "tgn:7029392"
    ],
    "tgn:id":7470418,
    "tgn:name":"Qishifen",
    "tgn:placetype":[
        "aat:300008347"
    ]
},
  "bbox": [],
  "geometry": {"coordinates":[120.808648,24.485055],"type":"Point"}
}