<<<<<<< HEAD
{
  "id": 7470418,
  "type": "Feature",
  "properties": {
    "tgn:hierarchy":[
        "tgn:7470418",
        "tgn:7487020",
        "tgn:1000004",
        "tgn:1000141",
        "tgn:7029392"
    ],
    "tgn:id":7470418,
    "tgn:name":"Qishifen",
    "tgn:placetype":[
        "aat:300008347"
    ]
},
  "bbox": [],
  "geometry": {"coordinates":[120.808648,24.485055],"type":"Point"}
}
=======
{"geometry":{"type":"Point","coordinates":[120.808648,24.485055]},"type":"Feature","properties":{"hierarchy":["tgn:7470418","tgn:7487020","tgn:1000004","tgn:1000141","tgn:7029392"],"placetype":["aat:300008347"],"id":7470418,"name:xx":"Qishifen"}}
>>>>>>> 03f74aca74312dbeaf24d7e61306dd6a786dc3d0
