{
  "id": 2344889,
  "type": "Feature",
  "properties": {
    "tgn:hierarchy":[
        "tgn:2344889",
        "tgn:1000001",
        "tgn:2002310",
        "tgn:7012149",
        "tgn:7007922",
        "tgn:7029392"
    ],
    "tgn:id":2344889,
    "tgn:name":"Garden Valley",
    "tgn:placetype":[
        "aat:300008761"
    ]
},
  "bbox": [],
  "geometry": {"coordinates":[-91.65,44.3333],"type":"Point"}
}