{
  "id": 1122779,
  "type": "Feature",
  "properties": {
    "tgn:hierarchy":[
        "tgn:1122779",
        "tgn:7000895",
        "tgn:1000004",
        "tgn:1001010",
        "tgn:1000120",
        "tgn:7029392"
    ],
    "tgn:id":1122779,
    "tgn:name":"Chikuma-gawa",
    "tgn:placetype":[
        "aat:300008707"
    ]
},
  "bbox": [],
  "geometry": {"coordinates":[138.5833,36.9833],"type":"Point"}
}