{
  "id": 7498479,
  "type": "Feature",
  "properties": {
    "tgn:hierarchy":[
        "tgn:7498479",
        "tgn:1000004",
        "tgn:7491221",
        "tgn:1000141",
        "tgn:7029392"
    ],
    "tgn:id":7498479,
    "tgn:name":"Jiafeng Qiao",
    "tgn:placetype":[
        "aat:300007836"
    ]
},
  "bbox": [],
  "geometry": {"coordinates":[121.10729,22.88273],"type":"Point"}
}