{
  "id": 2173002,
  "type": "Feature",
  "properties": {
    "tgn:hierarchy":[
        "tgn:2173002",
        "tgn:1000001",
        "tgn:2001477",
        "tgn:7012149",
        "tgn:7007709",
        "tgn:7029392"
    ],
    "tgn:id":2173002,
    "tgn:name":"Billys Branch",
    "tgn:placetype":[
        "aat:300008699"
    ]
},
  "bbox": [],
  "geometry": {"coordinates":[-76.7667,34.7833],"type":"Point"}
}