{
  "id": 7235873,
  "type": "Feature",
  "properties": {
    "tgn:hierarchy":[
        "tgn:7235873",
        "tgn:7011270",
        "tgn:7002674",
        "tgn:1000003",
        "tgn:1000074",
        "tgn:7029392"
    ],
    "tgn:id":7235873,
    "tgn:name":"Exom\u00fdtis, \u00c1kra",
    "tgn:placetype":[
        "aat:300008850"
    ]
},
  "bbox": [],
  "geometry": {"coordinates":[25.441217,36.332498],"type":"Point"}
}