<<<<<<< HEAD
{
  "id": 7487234,
  "type": "Feature",
  "properties": {
    "tgn:hierarchy":[
        "tgn:7487234",
        "tgn:1000004",
        "tgn:1000454",
        "tgn:1000141",
        "tgn:7029392"
    ],
    "tgn:id":7487234,
    "tgn:name":"Linzi",
    "tgn:placetype":[
        "aat:300008347"
    ]
},
  "bbox": [],
  "geometry": {"coordinates":[121.44695,25.20025],"type":"Point"}
}
=======
{"geometry":{"type":"Point","coordinates":[121.446950,25.200250]},"type":"Feature","properties":{"hierarchy":["tgn:7487234","tgn:1000004","tgn:1000454","tgn:1000141","tgn:7029392"],"placetype":["aat:300008347"],"id":7487234,"name:xx":"Linzi"}}
>>>>>>> 03f74aca74312dbeaf24d7e61306dd6a786dc3d0
