{
  "id": 2739172,
  "type": "Feature",
  "properties": {
    "tgn:hierarchy":[
        "tgn:2739172",
        "tgn:1000001",
        "tgn:7012149",
        "tgn:2000358",
        "tgn:7007248",
        "tgn:7029392"
    ],
    "tgn:id":2739172,
    "tgn:name":"Unknown",
    "tgn:placetype":[
        "aat:300006191"
    ]
},
  "bbox": [],
  "geometry": {"coordinates":[-84.15,33.9833],"type":"Point"}
}