{
  "id": 1049054,
  "type": "Feature",
  "properties": {
    "tgn:hierarchy":[
        "tgn:1049054",
        "tgn:1000003",
        "tgn:7024118",
        "tgn:7006366",
        "tgn:7029392"
    ],
    "tgn:id":1049054,
    "tgn:name":"Go\u0142dap",
    "tgn:placetype":[
        "aat:300008347"
    ]
},
  "bbox": [],
  "geometry": {"coordinates":[22.3167,54.3167],"type":"Point"}
}