{
  "id": 7336329,
  "type": "Feature",
  "properties": {
    "tgn:hierarchy":[
        "tgn:7336329",
        "tgn:7002759",
        "tgn:7008909",
        "tgn:1000003",
        "tgn:1000095",
        "tgn:7029392"
    ],
    "tgn:id":7336329,
    "tgn:name":"Formigales",
    "tgn:placetype":[
        "aat:300008347"
    ]
},
  "bbox": [],
  "geometry": {"coordinates":[0.297079,42.332776],"type":"Point"}
}