{
  "id": 7133086,
  "type": "Feature",
  "properties": {
    "tgn:hierarchy":[
        "tgn:7133086",
        "tgn:7003692",
        "tgn:1000003",
        "tgn:7000084",
        "tgn:7029392"
    ],
    "tgn:id":7133086,
    "tgn:name":"Mochenwangen",
    "tgn:placetype":[
        "aat:300008347"
    ]
},
  "bbox": [],
  "geometry": {"coordinates":[9.633333,47.883333],"type":"Point"}
}