{
  "id": 7516356,
  "type": "Feature",
  "properties": {
    "tgn:hierarchy":[
        "tgn:7516356",
        "tgn:1009227",
        "tgn:1000226",
        "tgn:7016729",
        "tgn:1000006",
        "tgn:7029392"
    ],
    "tgn:id":7516356,
    "tgn:name:en":"Lansdowne",
    "tgn:placetype":[
        "aat:300000206"
    ]
},
  "bbox": [],
  "geometry": {"coordinates":[173.55,-41.566667],"type":"Point"}
}