<<<<<<< HEAD
{
  "id": 7487751,
  "type": "Feature",
  "properties": {
    "tgn:hierarchy":[
        "tgn:7487751",
        "tgn:1000004",
        "tgn:7490934",
        "tgn:1000141",
        "tgn:7029392"
    ],
    "tgn:id":7487751,
    "tgn:name":"Nanbeishiliao",
    "tgn:placetype":[
        "aat:300008347"
    ]
},
  "bbox": [],
  "geometry": {"coordinates":[120.251389,23.196389],"type":"Point"}
}
=======
{"geometry":{"type":"Point","coordinates":[120.251389,23.196389]},"type":"Feature","properties":{"hierarchy":["tgn:7487751","tgn:1000004","tgn:7490934","tgn:1000141","tgn:7029392"],"placetype":["aat:300008347"],"id":7487751,"name:xx":"Nanbeishiliao"}}
>>>>>>> 03f74aca74312dbeaf24d7e61306dd6a786dc3d0
