{
  "id": 2555397,
  "type": "Feature",
  "properties": {
    "tgn:hierarchy":[
        "tgn:2555397",
        "tgn:7014201",
        "tgn:1000001",
        "tgn:7012149",
        "tgn:7007239",
        "tgn:7029392"
    ],
    "tgn:id":2555397,
    "tgn:name":"Odessa Heights",
    "tgn:placetype":[
        "aat:300008347"
    ]
},
  "bbox": [],
  "geometry": {"coordinates":[-75.65,39.45],"type":"Point"}
}