{
  "id": 2187729,
  "type": "Feature",
  "properties": {
    "tgn:hierarchy":[
        "tgn:2187729",
        "tgn:1000001",
        "tgn:7012149",
        "tgn:2001767",
        "tgn:7007712",
        "tgn:7029392"
    ],
    "tgn:id":2187729,
    "tgn:name":"Booths Pond",
    "tgn:placetype":[
        "aat:300006191"
    ]
},
  "bbox": [],
  "geometry": {"coordinates":[-80.4333,33.9667],"type":"Point"}
}