{
  "id": 7435076,
  "type": "Feature",
  "properties": {
    "tgn:hierarchy":[
        "tgn:7435076",
        "tgn:1001853",
        "tgn:1000001",
        "tgn:7005560",
        "tgn:7029392"
    ],
    "tgn:id":7435076,
    "tgn:name":"Zertuche",
    "tgn:placetype":[
        "aat:300007783"
    ]
},
  "bbox": [],
  "geometry": {"coordinates":[-101.016667,25.666667],"type":"Point"}
}