{
  "id": 2009000,
  "type": "Feature",
  "properties": {
    "tgn:hierarchy":[
        "tgn:2009000",
        "tgn:1000001",
        "tgn:7016172",
        "tgn:7012149",
        "tgn:2000127",
        "tgn:7029392"
    ],
    "tgn:id":2009000,
    "tgn:name":"Mount Olive",
    "tgn:placetype":[
        "aat:300008347"
    ]
},
  "bbox": [],
  "geometry": {"coordinates":[-92.55,35.1833],"type":"Point"}
}