{
  "id": 2337292,
  "type": "Feature",
  "properties": {
    "tgn:hierarchy":[
        "tgn:2337292",
        "tgn:7002659",
        "tgn:1000001",
        "tgn:7012149",
        "tgn:2000035",
        "tgn:7029392"
    ],
    "tgn:id":2337292,
    "tgn:name":"Fourth of July Cave",
    "tgn:placetype":[
        "aat:300008746"
    ]
},
  "bbox": [],
  "geometry": {"coordinates":[-86.3167,34.8333],"type":"Point"}
}