{
  "id": 2747271,
  "type": "Feature",
  "properties": {
    "tgn:hierarchy":[
        "tgn:2747271",
        "tgn:1000001",
        "tgn:7012149",
        "tgn:7007827",
        "tgn:7029392"
    ],
    "tgn:id":2747271,
    "tgn:name":"Wah Wah Cove",
    "tgn:placetype":[
        "aat:300008761"
    ]
},
  "bbox": [],
  "geometry": {"coordinates":[-113.5333,38.55],"type":"Point"}
}