{
  "id": 7228319,
  "type": "Feature",
  "properties": {
    "tgn:hierarchy":[
        "tgn:7228319",
        "tgn:7002750",
        "tgn:7001399",
        "tgn:1000003",
        "tgn:1000074",
        "tgn:7029392"
    ],
    "tgn:id":7228319,
    "tgn:name":"Kokkin\u00f3geion",
    "tgn:placetype":[
        "aat:300008347"
    ]
},
  "bbox": [],
  "geometry": {"coordinates":[22.159167,40.031389],"type":"Point"}
}