{
  "id": 7267914,
  "type": "Feature",
  "properties": {
    "tgn:concordances":{
        "gn:id":"2748771"
    },
    "tgn:hierarchy":[
        "tgn:7267914",
        "tgn:7003614",
        "tgn:1000003",
        "tgn:7016845",
        "tgn:7029392"
    ],
    "tgn:id":7267914,
    "tgn:name:nl":"Padhuis",
    "tgn:placetype":[
        "aat:300008347"
    ]
},
  "bbox": [],
  "geometry": {"coordinates":[6.85,52.666667],"type":"Point"}
}