<<<<<<< HEAD
{
  "id": 7484116,
  "type": "Feature",
  "properties": {
    "tgn:hierarchy":[
        "tgn:7484116",
        "tgn:1000004",
        "tgn:7492971",
        "tgn:1000141",
        "tgn:7029392"
    ],
    "tgn:id":7484116,
    "tgn:name":"Shitou Tifang",
    "tgn:placetype":[
        "aat:300006156"
    ]
},
  "bbox": [],
  "geometry": {"coordinates":[120.595556,22.458056],"type":"Point"}
}
=======
{"geometry":{"type":"Point","coordinates":[120.595556,22.458056]},"type":"Feature","properties":{"hierarchy":["tgn:7484116","tgn:1000004","tgn:7492971","tgn:1000141","tgn:7029392"],"placetype":["aat:300006156"],"id":7484116,"name:xx":"Shitou Tifang"}}
>>>>>>> 03f74aca74312dbeaf24d7e61306dd6a786dc3d0
