<<<<<<< HEAD
{
  "id": 7354830,
  "type": "Feature",
  "properties": {
    "tgn:hierarchy":[
        "tgn:7354830",
        "tgn:7005581",
        "tgn:1000001",
        "tgn:7005560",
        "tgn:7029392"
    ],
    "tgn:id":7354830,
    "tgn:name":"Catorce",
    "tgn:placetype":[
        "aat:300008347"
    ]
},
  "bbox": [],
  "geometry": {"coordinates":[-108.35,28.383333],"type":"Point"}
}
=======
{"geometry":{"type":"Point","coordinates":[-108.350000,28.383333]},"type":"Feature","properties":{"hierarchy":["tgn:7354830","tgn:7005581","tgn:1000001","tgn:7005560","tgn:7029392"],"placetype":["aat:300008347"],"id":7354830,"name:xx":"Catorce"}}
>>>>>>> 03f74aca74312dbeaf24d7e61306dd6a786dc3d0
