{
  "id": 2299744,
  "type": "Feature",
  "properties": {
    "tgn:hierarchy":[
        "tgn:2299744",
        "tgn:1000001",
        "tgn:7012149",
        "tgn:2001455",
        "tgn:7007566",
        "tgn:7029392"
    ],
    "tgn:id":2299744,
    "tgn:name":"Dude Mine",
    "tgn:placetype":[
        "aat:300000390"
    ]
},
  "bbox": [],
  "geometry": {"coordinates":[-107.5833,32.6333],"type":"Point"}
}