{
  "id": 2718619,
  "type": "Feature",
  "properties": {
    "tgn:hierarchy":[
        "tgn:2718619",
        "tgn:1000001",
        "tgn:2001839",
        "tgn:7012149",
        "tgn:7007825",
        "tgn:7029392"
    ],
    "tgn:id":2718619,
    "tgn:name":"Thompson Slough",
    "tgn:placetype":[
        "aat:300008699"
    ]
},
  "bbox": [],
  "geometry": {"coordinates":[-87.9333,36.1333],"type":"Point"}
}