<<<<<<< HEAD
{
  "id": 7054454,
  "type": "Feature",
  "properties": {
    "tgn:hierarchy":[
        "tgn:7054454",
        "tgn:1003447",
        "tgn:7007850",
        "tgn:1000003",
        "tgn:1000080",
        "tgn:7029392"
    ],
    "tgn:id":7054454,
    "tgn:name":"Mongo",
    "tgn:placetype":[
        "aat:300008347"
    ]
},
  "bbox": [],
  "geometry": {"coordinates":[16.383333,38.8],"type":"Point"}
}
=======
{"geometry":{"type":"Point","coordinates":[16.383333,38.800000]},"type":"Feature","properties":{"hierarchy":["tgn:7054454","tgn:1003447","tgn:7007850","tgn:1000003","tgn:1000080","tgn:7029392"],"placetype":["aat:300008347"],"id":7054454,"name:xx":"Mongo"}}
>>>>>>> 03f74aca74312dbeaf24d7e61306dd6a786dc3d0
