{
  "id": 2705375,
  "type": "Feature",
  "properties": {
    "tgn:hierarchy":[
        "tgn:2705375",
        "tgn:7006450",
        "tgn:1000001",
        "tgn:7019698",
        "tgn:7012149",
        "tgn:7029392"
    ],
    "tgn:id":2705375,
    "tgn:name":"Surprise Creek",
    "tgn:placetype":[
        "aat:300008706"
    ]
},
  "bbox": [],
  "geometry": {"coordinates":[-150.0333,60.4333],"type":"Point"}
}