{
  "id": 7230758,
  "type": "Feature",
  "properties": {
    "tgn:hierarchy":[
        "tgn:7230758",
        "tgn:7011161",
        "tgn:7002674",
        "tgn:1000003",
        "tgn:1000074",
        "tgn:7029392"
    ],
    "tgn:id":7230758,
    "tgn:name":"M\u00e1rmaron",
    "tgn:placetype":[
        "aat:300008347"
    ]
},
  "bbox": [],
  "geometry": {"coordinates":[26.113056,38.540833],"type":"Point"}
}