{
  "id": 7498513,
  "type": "Feature",
  "properties": {
    "tgn:hierarchy":[
        "tgn:7498513",
        "tgn:1000004",
        "tgn:7467799",
        "tgn:1000141",
        "tgn:7029392"
    ],
    "tgn:id":7498513,
    "tgn:name":"Changping Qiao",
    "tgn:placetype":[
        "aat:300007836"
    ]
},
  "bbox": [],
  "geometry": {"coordinates":[120.576004,24.005552],"type":"Point"}
}