{
  "id": 7432632,
  "type": "Feature",
  "properties": {
    "tgn:hierarchy":[
        "tgn:7432632",
        "tgn:7005586",
        "tgn:1000001",
        "tgn:7005560",
        "tgn:7029392"
    ],
    "tgn:id":7432632,
    "tgn:name":"Tomates, Boca",
    "tgn:placetype":[
        "aat:300387057"
    ]
},
  "bbox": [],
  "geometry": {"coordinates":[-105.266667,20.666667],"type":"Point"}
}