{
  "id": 2290147,
  "type": "Feature",
  "properties": {
    "tgn:hierarchy":[
        "tgn:2290147",
        "tgn:1000001",
        "tgn:7016172",
        "tgn:7012149",
        "tgn:2000173",
        "tgn:7029392"
    ],
    "tgn:id":2290147,
    "tgn:name":"Dodd Ridge",
    "tgn:placetype":[
        "aat:300266640"
    ]
},
  "bbox": [],
  "geometry": {"coordinates":[-92.3167,35.8167],"type":"Point"}
}