{
  "id": 2505766,
  "type": "Feature",
  "properties": {
    "tgn:hierarchy":[
        "tgn:2505766",
        "tgn:1000001",
        "tgn:7012149",
        "tgn:2001032",
        "tgn:7007521",
        "tgn:7029392"
    ],
    "tgn:id":2505766,
    "tgn:name":"Mennetaga Lake",
    "tgn:placetype":[
        "aat:300008680"
    ]
},
  "bbox": [],
  "geometry": {"coordinates":[-94.85,45.0667],"type":"Point"}
}