{
  "id": 7264643,
  "type": "Feature",
  "properties": {
    "tgn:hierarchy":[
        "tgn:7264643",
        "tgn:1000003",
        "tgn:7003635",
        "tgn:7016845",
        "tgn:7029392"
    ],
    "tgn:id":7264643,
    "tgn:name:nl":"Kreekrakpolder",
    "tgn:placetype":[
        "aat:300006163"
    ]
},
  "bbox": [],
  "geometry": {"coordinates":[4.233333,51.416667],"type":"Point"}
}