{
  "id": 2528328,
  "type": "Feature",
  "properties": {
    "tgn:hierarchy":[
        "tgn:2528328",
        "tgn:1000001",
        "tgn:2000924",
        "tgn:7012149",
        "tgn:7007515",
        "tgn:7029392"
    ],
    "tgn:id":2528328,
    "tgn:name":"Mouse Island",
    "tgn:placetype":[
        "aat:300008791"
    ]
},
  "bbox": [],
  "geometry": {"coordinates":[-68.6167,44.0833],"type":"Point"}
}