{
  "id": 2745804,
  "type": "Feature",
  "properties": {
    "tgn:hierarchy":[
        "tgn:2745804",
        "tgn:1000001",
        "tgn:7012149",
        "tgn:7007922",
        "tgn:7029392"
    ],
    "tgn:id":2745804,
    "tgn:name":"Vismal Creek",
    "tgn:placetype":[
        "aat:300008706"
    ]
},
  "bbox": [],
  "geometry": {"coordinates":[-90.7667,44.4333],"type":"Point"}
}