{
  "id": 2741078,
  "type": "Feature",
  "properties": {
    "tgn:hierarchy":[
        "tgn:2741078",
        "tgn:1000001",
        "tgn:7012149",
        "tgn:2000488",
        "tgn:7007250",
        "tgn:7029392"
    ],
    "tgn:id":2741078,
    "tgn:name":"Upper Swale",
    "tgn:placetype":[
        "aat:300008761"
    ]
},
  "bbox": [],
  "geometry": {"coordinates":[-115.8667,42.05],"type":"Point"}
}