{
  "id": 2629005,
  "type": "Feature",
  "properties": {
    "tgn:hierarchy":[
        "tgn:2629005",
        "tgn:1000001",
        "tgn:7012149",
        "tgn:2000444",
        "tgn:7007248",
        "tgn:7029392"
    ],
    "tgn:id":2629005,
    "tgn:name":"Rose Dew Lake",
    "tgn:placetype":[
        "aat:300008680"
    ]
},
  "bbox": [],
  "geometry": {"coordinates":[-82.55,32.0833],"type":"Point"}
}