{
  "id": 2198290,
  "type": "Feature",
  "properties": {
    "tgn:hierarchy":[
        "tgn:2198290",
        "tgn:7014651",
        "tgn:1000001",
        "tgn:7012149",
        "tgn:7007516",
        "tgn:7029392"
    ],
    "tgn:id":2198290,
    "tgn:name":"Browns Cove",
    "tgn:placetype":[
        "aat:300132316"
    ]
},
  "bbox": [],
  "geometry": {"coordinates":[-76.5667,39.0333],"type":"Point"}
}