{
  "id": 7032192,
  "type": "Feature",
  "properties": {
    "tgn:hierarchy":[
        "tgn:7032192",
        "tgn:1000003",
        "tgn:1000070",
        "tgn:7002895",
        "tgn:7029392"
    ],
    "tgn:id":7032192,
    "tgn:name":"Pont du Bois, Calanque du",
    "tgn:placetype":[
        "aat:300132317"
    ]
},
  "bbox": [],
  "geometry": {"coordinates":[6.728,43.386],"type":"Point"}
}