{
  "id": 2360113,
  "type": "Feature",
  "properties": {
    "tgn:hierarchy":[
        "tgn:2360113",
        "tgn:2000944",
        "tgn:1000001",
        "tgn:7012149",
        "tgn:7007520",
        "tgn:7029392"
    ],
    "tgn:id":2360113,
    "tgn:name":"Grass Lake",
    "tgn:placetype":[
        "aat:300008680"
    ]
},
  "bbox": [],
  "geometry": {"coordinates":[-83.3333,45.1167],"type":"Point"}
}