<<<<<<< HEAD
{
  "id": 7471118,
  "type": "Feature",
  "properties": {
    "tgn:hierarchy":[
        "tgn:7471118",
        "tgn:1000004",
        "tgn:7001009",
        "tgn:1000141",
        "tgn:7029392"
    ],
    "tgn:id":7471118,
    "tgn:name":"Jiushe",
    "tgn:placetype":[
        "aat:300000745"
    ]
},
  "bbox": [],
  "geometry": {"coordinates":[120.6999,24.1859],"type":"Point"}
}
=======
{"geometry":{"type":"Point","coordinates":[120.699900,24.185900]},"type":"Feature","properties":{"hierarchy":["tgn:7471118","tgn:1000004","tgn:7001009","tgn:1000141","tgn:7029392"],"placetype":["aat:300000745"],"id":7471118,"name:xx":"Jiushe"}}
>>>>>>> 03f74aca74312dbeaf24d7e61306dd6a786dc3d0
