{
  "id": 2016628,
  "type": "Feature",
  "properties": {
    "tgn:hierarchy":[
        "tgn:2016628",
        "tgn:1002366",
        "tgn:1000001",
        "tgn:7012149",
        "tgn:7007159",
        "tgn:7029392"
    ],
    "tgn:id":2016628,
    "tgn:name":"Branchville",
    "tgn:placetype":[
        "aat:300008347"
    ]
},
  "bbox": [],
  "geometry": {"coordinates":[-73.4333,41.2667],"type":"Point"}
}