{
  "id": 2444166,
  "type": "Feature",
  "properties": {
    "tgn:hierarchy":[
        "tgn:2444166",
        "tgn:1000001",
        "tgn:7012149",
        "tgn:2001129",
        "tgn:7007522",
        "tgn:7029392"
    ],
    "tgn:id":2444166,
    "tgn:name":"Labelle Estates",
    "tgn:placetype":[
        "aat:300008347"
    ]
},
  "bbox": [],
  "geometry": {"coordinates":[-88.2833,33.5167],"type":"Point"}
}