{
  "id": 7566831,
  "type": "Feature",
  "properties": {
    "tgn:hierarchy":[
        "tgn:7566831",
        "tgn:1000004",
        "tgn:7000198",
        "tgn:7001797",
        "tgn:7029392"
    ],
    "tgn:id":7566831,
    "tgn:name:en":"Pallipatu",
    "tgn:placetype":[
        "aat:300000745"
    ]
},
  "bbox": [],
  "geometry": {"coordinates":[80.245278,13.001667],"type":"Point"}
}