{
  "id": 2474296,
  "type": "Feature",
  "properties": {
    "tgn:hierarchy":[
        "tgn:2474296",
        "tgn:1000001",
        "tgn:7012149",
        "tgn:2001273",
        "tgn:7007524",
        "tgn:7029392"
    ],
    "tgn:id":2474296,
    "tgn:name":"Lower New Year Mine",
    "tgn:placetype":[
        "aat:300000390"
    ]
},
  "bbox": [],
  "geometry": {"coordinates":[-109.3167,47.15],"type":"Point"}
}