{
  "id": 2778248,
  "type": "Feature",
  "properties": {
    "tgn:hierarchy":[
        "tgn:2778248",
        "tgn:1000001",
        "tgn:7012149",
        "tgn:1002732",
        "tgn:7007710",
        "tgn:7029392"
    ],
    "tgn:id":2778248,
    "tgn:name":"Wises Island",
    "tgn:placetype":[
        "aat:300008791"
    ]
},
  "bbox": [],
  "geometry": {"coordinates":[-76.8333,40.75],"type":"Point"}
}