{
  "id": 2641137,
  "type": "Feature",
  "properties": {
    "tgn:hierarchy":[
        "tgn:2641137",
        "tgn:1000001",
        "tgn:7012149",
        "tgn:2000233",
        "tgn:7007158",
        "tgn:7029392"
    ],
    "tgn:id":2641137,
    "tgn:name":"Sand Canyon",
    "tgn:placetype":[
        "aat:300008761"
    ]
},
  "bbox": [],
  "geometry": {"coordinates":[-108.75,37.3833],"type":"Point"}
}