{
  "id": 2434743,
  "type": "Feature",
  "properties": {
    "tgn:hierarchy":[
        "tgn:2434743",
        "tgn:1000001",
        "tgn:7012149",
        "tgn:2002024",
        "tgn:7007826",
        "tgn:7029392"
    ],
    "tgn:id":2434743,
    "tgn:name":"Kennemer Crossing",
    "tgn:placetype":[
        "aat:300008347"
    ]
},
  "bbox": [],
  "geometry": {"coordinates":[-95.5167,33.45],"type":"Point"}
}