{
  "id": 2285641,
  "type": "Feature",
  "properties": {
    "tgn:hierarchy":[
        "tgn:2285641",
        "tgn:1000001",
        "tgn:2000582",
        "tgn:7012149",
        "tgn:7007253",
        "tgn:7029392"
    ],
    "tgn:id":2285641,
    "tgn:name":"Devils Hollow",
    "tgn:placetype":[
        "aat:300008761"
    ]
},
  "bbox": [],
  "geometry": {"coordinates":[-91.15,42.65],"type":"Point"}
}