{
  "id": 1113769,
  "type": "Feature",
  "properties": {
    "tgn:hierarchy":[
        "tgn:1113769",
        "tgn:7002444",
        "tgn:1000003",
        "tgn:7009907",
        "tgn:7008591",
        "tgn:7029392"
    ],
    "tgn:id":1113769,
    "tgn:name:en":"Sanday Sound",
    "tgn:placetype":[
        "aat:300132316"
    ]
},
  "bbox": [],
  "geometry": {"coordinates":[-2.516667,59.183333],"type":"Point"}
}