{
  "id": 2114084,
  "type": "Feature",
  "properties": {
    "tgn:hierarchy":[
        "tgn:2114084",
        "tgn:1000001",
        "tgn:1002235",
        "tgn:7012149",
        "tgn:7007919",
        "tgn:7029392"
    ],
    "tgn:id":2114084,
    "tgn:name":"Ruther Glen",
    "tgn:placetype":[
        "aat:300008347"
    ]
},
  "bbox": [],
  "geometry": {"coordinates":[-77.45,37.9167],"type":"Point"}
}