{
  "id": 2559145,
  "type": "Feature",
  "properties": {
    "tgn:hierarchy":[
        "tgn:2559145",
        "tgn:7002659",
        "tgn:1000001",
        "tgn:7012149",
        "tgn:2000035",
        "tgn:7029392"
    ],
    "tgn:id":2559145,
    "tgn:name":"One Man Pit",
    "tgn:placetype":[
        "aat:300008746"
    ]
},
  "bbox": [],
  "geometry": {"coordinates":[-86.2833,34.6333],"type":"Point"}
}