{
  "id": 1018334,
  "type": "Feature",
  "properties": {
    "tgn:hierarchy":[
        "tgn:1018334",
        "tgn:1000001",
        "tgn:7005591",
        "tgn:7005560",
        "tgn:7029392"
    ],
    "tgn:id":1018334,
    "tgn:name:es":"Santo Domingo Nuxa\u00e1",
    "tgn:placetype":[
        "aat:300008347"
    ]
},
  "bbox": [],
  "geometry": {"coordinates":[-97.123611,17.218611],"type":"Point"}
}