{
  "id": 2730173,
  "type": "Feature",
  "properties": {
    "tgn:hierarchy":[
        "tgn:2730173",
        "tgn:1000001",
        "tgn:7014423",
        "tgn:7012149",
        "tgn:7007517",
        "tgn:7029392"
    ],
    "tgn:id":2730173,
    "tgn:name":"Trout Pond",
    "tgn:placetype":[
        "aat:300008680"
    ]
},
  "bbox": [],
  "geometry": {"coordinates":[-70.8333,42.0833],"type":"Point"}
}