{
  "id": 1008298,
  "type": "Feature",
  "properties": {
    "tgn:hierarchy":[
        "tgn:1008298",
        "tgn:7005685",
        "tgn:1000001",
        "tgn:7013154",
        "tgn:7029392"
    ],
    "tgn:id":1008298,
    "tgn:name":"Nappan Island",
    "tgn:placetype":[
        "aat:300008791"
    ]
},
  "bbox": [],
  "geometry": {"coordinates":[-77.8167,44.3833],"type":"Point"}
}