<<<<<<< HEAD
{
  "id": 2401187,
  "type": "Feature",
  "properties": {
    "tgn:hierarchy":[
        "tgn:2401187",
        "tgn:1000001",
        "tgn:7012149",
        "tgn:2002055",
        "tgn:7007826",
        "tgn:7029392"
    ],
    "tgn:id":2401187,
    "tgn:name":"Horsehead Crossing",
    "tgn:placetype":[
        "aat:300008347"
    ]
},
  "bbox": [],
  "geometry": {"coordinates":[-102.4833,31.2333],"type":"Point"}
}
=======
{"geometry":{"type":"Point","coordinates":[-102.483300,31.233300]},"type":"Feature","properties":{"hierarchy":["tgn:2401187","tgn:1000001","tgn:7012149","tgn:2002055","tgn:7007826","tgn:7029392"],"placetype":["aat:300008347"],"id":2401187,"name:xx":"Horsehead Crossing"}}
>>>>>>> 03f74aca74312dbeaf24d7e61306dd6a786dc3d0
