{
  "id": 1094891,
  "type": "Feature",
  "properties": {
    "tgn:hierarchy":[
        "tgn:1094891",
        "tgn:7001242",
        "tgn:7000579",
        "tgn:7016577",
        "tgn:7029392"
    ],
    "tgn:id":1094891,
    "tgn:name":"Mandouri",
    "tgn:placetype":[
        "aat:300008347"
    ]
},
  "bbox": [],
  "geometry": {"coordinates":[0.8167,10.85],"type":"Point"}
}