{
  "id": 7447072,
  "type": "Feature",
  "properties": {
    "tgn:hierarchy":[
        "tgn:7447072",
        "tgn:7002444",
        "tgn:1000003",
        "tgn:7029508",
        "tgn:7008591",
        "tgn:7029392"
    ],
    "tgn:id":7447072,
    "tgn:name:en":"Skelda Ness",
    "tgn:placetype":[
        "aat:300386846"
    ]
},
  "bbox": [],
  "geometry": {"coordinates":[-1.466667,60.15],"type":"Point"}
}