<<<<<<< HEAD
{
  "id": 2406163,
  "type": "Feature",
  "properties": {
    "tgn:hierarchy":[
        "tgn:2406163",
        "tgn:7002659",
        "tgn:1000001",
        "tgn:7012149",
        "tgn:2000036",
        "tgn:7029392"
    ],
    "tgn:id":2406163,
    "tgn:name":"Humoro",
    "tgn:placetype":[
        "aat:300008347"
    ]
},
  "bbox": [],
  "geometry": {"coordinates":[-86.7667,33.6167],"type":"Point"}
}
=======
{"geometry":{"type":"Point","coordinates":[-86.766700,33.616700]},"type":"Feature","properties":{"hierarchy":["tgn:2406163","tgn:7002659","tgn:1000001","tgn:7012149","tgn:2000036","tgn:7029392"],"placetype":["aat:300008347"],"id":2406163,"name:xx":"Humoro"}}
>>>>>>> 03f74aca74312dbeaf24d7e61306dd6a786dc3d0
