{
  "id": 2437130,
  "type": "Feature",
  "properties": {
    "tgn:hierarchy":[
        "tgn:2437130",
        "tgn:1000001",
        "tgn:7012149",
        "tgn:7007520",
        "tgn:7029392"
    ],
    "tgn:id":2437130,
    "tgn:name":"Kilpecker Creek",
    "tgn:placetype":[
        "aat:300008706"
    ]
},
  "bbox": [],
  "geometry": {"coordinates":[-86.5333,46.1333],"type":"Point"}
}