{
  "id": 2105277,
  "type": "Feature",
  "properties": {
    "tgn:hierarchy":[
        "tgn:2105277",
        "tgn:1000001",
        "tgn:7012149",
        "tgn:2001979",
        "tgn:7007826",
        "tgn:7029392"
    ],
    "tgn:id":2105277,
    "tgn:name":"Judkins",
    "tgn:placetype":[
        "aat:300387016"
    ]
},
  "bbox": [],
  "geometry": {"coordinates":[-102.6167,31.7167],"type":"Point"}
}