<<<<<<< HEAD
{
  "id": 7021185,
  "type": "Feature",
  "properties": {
    "tgn:hierarchy":[
        "tgn:7021185",
        "tgn:1000001",
        "tgn:7012149",
        "tgn:2002272",
        "tgn:7013961",
        "tgn:7029392"
    ],
    "tgn:id":7021185,
    "tgn:name":"Mudlick Branch",
    "tgn:placetype":[
        "aat:300008699"
    ]
},
  "bbox": [],
  "geometry": {"coordinates":[-82.1833,38.0333],"type":"Point"}
}
=======
{"geometry":{"type":"Point","coordinates":[-82.183300,38.033300]},"type":"Feature","properties":{"hierarchy":["tgn:7021185","tgn:1000001","tgn:7012149","tgn:2002272","tgn:7013961","tgn:7029392"],"placetype":["aat:300008699"],"id":7021185,"name:xx":"Mudlick Branch"}}
>>>>>>> 03f74aca74312dbeaf24d7e61306dd6a786dc3d0
