{
  "id": 2622765,
  "type": "Feature",
  "properties": {
    "tgn:hierarchy":[
        "tgn:2622765",
        "tgn:7002659",
        "tgn:1000001",
        "tgn:7012149",
        "tgn:2000041",
        "tgn:7029392"
    ],
    "tgn:id":2622765,
    "tgn:name":"Robinson Hollow",
    "tgn:placetype":[
        "aat:300008761"
    ]
},
  "bbox": [],
  "geometry": {"coordinates":[-86.9333,34.9667],"type":"Point"}
}