{
  "id": 2491963,
  "type": "Feature",
  "properties": {
    "tgn:hierarchy":[
        "tgn:2491963",
        "tgn:7013349",
        "tgn:1000001",
        "tgn:7012149",
        "tgn:7007708",
        "tgn:7029392"
    ],
    "tgn:id":2491963,
    "tgn:name":"Marble Point",
    "tgn:placetype":[
        "aat:300008798"
    ]
},
  "bbox": [],
  "geometry": {"coordinates":[-118.0333,44.7667],"type":"Point"}
}