<<<<<<< HEAD
{
  "id": 2339770,
  "type": "Feature",
  "properties": {
    "tgn:hierarchy":[
        "tgn:2339770",
        "tgn:1000001",
        "tgn:7012149",
        "tgn:1003038",
        "tgn:7007517",
        "tgn:7029392"
    ],
    "tgn:id":2339770,
    "tgn:name":"Freeland Hill",
    "tgn:placetype":[
        "aat:300008798"
    ]
},
  "bbox": [],
  "geometry": {"coordinates":[-71.7833,42.1167],"type":"Point"}
}
=======
{"geometry":{"type":"Point","coordinates":[-71.783300,42.116700]},"type":"Feature","properties":{"hierarchy":["tgn:2339770","tgn:1000001","tgn:7012149","tgn:1003038","tgn:7007517","tgn:7029392"],"placetype":["aat:300008798"],"id":2339770,"name:xx":"Freeland Hill"}}
>>>>>>> 03f74aca74312dbeaf24d7e61306dd6a786dc3d0
