{
  "id": 7233802,
  "type": "Feature",
  "properties": {
    "tgn:hierarchy":[
        "tgn:7233802",
        "tgn:7002690",
        "tgn:7012056",
        "tgn:1000003",
        "tgn:1000074",
        "tgn:7029392"
    ],
    "tgn:id":7233802,
    "tgn:name":"Akto\u00fanda",
    "tgn:placetype":[
        "aat:300008347"
    ]
},
  "bbox": [],
  "geometry": {"coordinates":[24.533333,35.183333],"type":"Point"}
}