{
  "id": 2348239,
  "type": "Feature",
  "properties": {
    "tgn:hierarchy":[
        "tgn:2348239",
        "tgn:1000001",
        "tgn:7012149",
        "tgn:2000927",
        "tgn:7007515",
        "tgn:7029392"
    ],
    "tgn:id":2348239,
    "tgn:name":"Getchell Mountain",
    "tgn:placetype":[
        "aat:300008798"
    ]
},
  "bbox": [],
  "geometry": {"coordinates":[-68.05,45.3667],"type":"Point"}
}