<<<<<<< HEAD
{
  "id": 2408360,
  "type": "Feature",
  "properties": {
    "tgn:hierarchy":[
        "tgn:2408360",
        "tgn:1000001",
        "tgn:7012149",
        "tgn:1002974",
        "tgn:7007251",
        "tgn:7029392"
    ],
    "tgn:id":2408360,
    "tgn:name":"Hustle",
    "tgn:placetype":[
        "aat:300008347"
    ]
},
  "bbox": [],
  "geometry": {"coordinates":[-87.8167,40.4667],"type":"Point"}
}
=======
{"geometry":{"type":"Point","coordinates":[-87.816700,40.466700]},"type":"Feature","properties":{"hierarchy":["tgn:2408360","tgn:1000001","tgn:7012149","tgn:1002974","tgn:7007251","tgn:7029392"],"placetype":["aat:300008347"],"id":2408360,"name:xx":"Hustle"}}
>>>>>>> 03f74aca74312dbeaf24d7e61306dd6a786dc3d0
