{
  "id": 2067112,
  "type": "Feature",
  "properties": {
    "tgn:hierarchy":[
        "tgn:2067112",
        "tgn:1000001",
        "tgn:7012149",
        "tgn:2001457",
        "tgn:7007566",
        "tgn:7029392"
    ],
    "tgn:id":2067112,
    "tgn:name":"Las Mochas",
    "tgn:placetype":[
        "aat:300008347"
    ]
},
  "bbox": [],
  "geometry": {"coordinates":[-105.5667,36.15],"type":"Point"}
}