{
  "id": 2420391,
  "type": "Feature",
  "properties": {
    "tgn:hierarchy":[
        "tgn:2420391",
        "tgn:1000001",
        "tgn:7012149",
        "tgn:2000539",
        "tgn:7007251",
        "tgn:7029392"
    ],
    "tgn:id":2420391,
    "tgn:name":"Jenkins",
    "tgn:placetype":[
        "aat:300008347"
    ]
},
  "bbox": [],
  "geometry": {"coordinates":[-88.9167,37.85],"type":"Point"}
}