{
  "id": 2482321,
  "type": "Feature",
  "properties": {
    "tgn:hierarchy":[
        "tgn:2482321",
        "tgn:1000001",
        "tgn:7012149",
        "tgn:2000910",
        "tgn:7007256",
        "tgn:7029392"
    ],
    "tgn:id":2482321,
    "tgn:name":"Langlinais Ditch",
    "tgn:placetype":[
        "aat:300006075"
    ]
},
  "bbox": [],
  "geometry": {"coordinates":[-92.05,30.0167],"type":"Point"}
}