{
  "id": 7408278,
  "type": "Feature",
  "properties": {
    "tgn:hierarchy":[
        "tgn:7408278",
        "tgn:1000001",
        "tgn:1001893",
        "tgn:7005560",
        "tgn:7029392"
    ],
    "tgn:id":7408278,
    "tgn:name":"Pueblo Nuevo Sol\u00eds",
    "tgn:placetype":[
        "aat:300008347"
    ]
},
  "bbox": [],
  "geometry": {"coordinates":[-100.075,19.958333],"type":"Point"}
}