{
  "id": 7452876,
  "type": "Feature",
  "properties": {
    "tgn:hierarchy":[
        "tgn:7452876",
        "tgn:7002445",
        "tgn:1000003",
        "tgn:7008153",
        "tgn:7008591",
        "tgn:7029392"
    ],
    "tgn:id":7452876,
    "tgn:name:en":"Cant, The",
    "tgn:placetype":[
        "aat:300387036"
    ]
},
  "bbox": [],
  "geometry": {"coordinates":[0.866667,51.45],"type":"Point"}
}