{
  "id": 2238946,
  "type": "Feature",
  "properties": {
    "tgn:hierarchy":[
        "tgn:2238946",
        "tgn:1000001",
        "tgn:7012149",
        "tgn:1002314",
        "tgn:7007240",
        "tgn:7029392"
    ],
    "tgn:id":2238946,
    "tgn:name":"Christmas Point",
    "tgn:placetype":[
        "aat:300008850"
    ]
},
  "bbox": [],
  "geometry": {"coordinates":[-80.2167,25.3833],"type":"Point"}
}