{
  "id": 7592041,
  "type": "Feature",
  "properties": {
    "tgn:hierarchy":[
        "tgn:7592041",
        "tgn:1000004",
        "tgn:7000198",
        "tgn:7000799",
        "tgn:7029392"
    ],
    "tgn:id":7592041,
    "tgn:name:en":"Choaddi",
    "tgn:placetype":[
        "aat:300008347"
    ]
},
  "bbox": [],
  "geometry": {"coordinates":[74.927778,32.684722],"type":"Point"}
}