{
  "id": 2367723,
  "type": "Feature",
  "properties": {
    "tgn:hierarchy":[
        "tgn:2367723",
        "tgn:1000001",
        "tgn:2000600",
        "tgn:7012149",
        "tgn:7007253",
        "tgn:7029392"
    ],
    "tgn:id":2367723,
    "tgn:name":"Grove Branch Ditch",
    "tgn:placetype":[
        "aat:300006075"
    ]
},
  "bbox": [],
  "geometry": {"coordinates":[-93.7167,42.35],"type":"Point"}
}