{
  "id": 2434847,
  "type": "Feature",
  "properties": {
    "tgn:hierarchy":[
        "tgn:2434847",
        "tgn:1000001",
        "tgn:7012149",
        "tgn:1002946",
        "tgn:7007252",
        "tgn:7029392"
    ],
    "tgn:id":2434847,
    "tgn:name":"Kenny Ditch",
    "tgn:placetype":[
        "aat:300006075"
    ]
},
  "bbox": [],
  "geometry": {"coordinates":[-86.8167,40.3333],"type":"Point"}
}