{
  "id": 2712314,
  "type": "Feature",
  "properties": {
    "tgn:hierarchy":[
        "tgn:2712314",
        "tgn:1000001",
        "tgn:7012149",
        "tgn:2001295",
        "tgn:7007524",
        "tgn:7029392"
    ],
    "tgn:id":2712314,
    "tgn:name":"Tattnall",
    "tgn:placetype":[
        "aat:300008347"
    ]
},
  "bbox": [],
  "geometry": {"coordinates":[-107.5333,48.6167],"type":"Point"}
}