{
  "id": 2429449,
  "type": "Feature",
  "properties": {
    "tgn:hierarchy":[
        "tgn:2429449",
        "tgn:1000001",
        "tgn:7012149",
        "tgn:2001709",
        "tgn:7007708",
        "tgn:7029392"
    ],
    "tgn:id":2429449,
    "tgn:name":"Juniper Flat Spring",
    "tgn:placetype":[
        "aat:300008697"
    ]
},
  "bbox": [],
  "geometry": {"coordinates":[-118.8167,43.7667],"type":"Point"}
}