{
  "id": 1065913,
  "type": "Feature",
  "properties": {
    "tgn:hierarchy":[
        "tgn:1065913",
        "tgn:1000004",
        "tgn:7000191",
        "tgn:1000105",
        "tgn:7029392"
    ],
    "tgn:id":1065913,
    "tgn:name":"Ruhea",
    "tgn:placetype":[
        "aat:300008347"
    ]
},
  "bbox": [],
  "geometry": {"coordinates":[88.4167,26.1667],"type":"Point"}
}