<<<<<<< HEAD
{
  "id": 7487838,
  "type": "Feature",
  "properties": {
    "tgn:hierarchy":[
        "tgn:7487838",
        "tgn:1000004",
        "tgn:7001009",
        "tgn:1000141",
        "tgn:7029392"
    ],
    "tgn:id":7487838,
    "tgn:name":"Hongmaojing",
    "tgn:placetype":[
        "aat:300008347"
    ]
},
  "bbox": [],
  "geometry": {"coordinates":[120.5742,24.2333],"type":"Point"}
}
=======
{"geometry":{"type":"Point","coordinates":[120.574200,24.233300]},"type":"Feature","properties":{"hierarchy":["tgn:7487838","tgn:1000004","tgn:7001009","tgn:1000141","tgn:7029392"],"placetype":["aat:300008347"],"id":7487838,"name:xx":"Hongmaojing"}}
>>>>>>> 03f74aca74312dbeaf24d7e61306dd6a786dc3d0
