{
  "id": 2390630,
  "type": "Feature",
  "properties": {
    "tgn:hierarchy":[
        "tgn:2390630",
        "tgn:1000001",
        "tgn:7012149",
        "tgn:2002374",
        "tgn:7007923",
        "tgn:7029392"
    ],
    "tgn:id":2390630,
    "tgn:name":"Highline Ditch",
    "tgn:placetype":[
        "aat:300006075"
    ]
},
  "bbox": [],
  "geometry": {"coordinates":[-106.7833,44.5167],"type":"Point"}
}