{
  "id": 7230821,
  "type": "Feature",
  "properties": {
    "tgn:hierarchy":[
        "tgn:7230821",
        "tgn:7002745",
        "tgn:7017076",
        "tgn:1000003",
        "tgn:1000074",
        "tgn:7029392"
    ],
    "tgn:id":7230821,
    "tgn:name":"Kremm\u00fddi, \u00d3rmos",
    "tgn:placetype":[
        "aat:300132316"
    ]
},
  "bbox": [],
  "geometry": {"coordinates":[23.057368,36.735869],"type":"Point"}
}