<<<<<<< HEAD
{
  "id": 7484244,
  "type": "Feature",
  "properties": {
    "tgn:hierarchy":[
        "tgn:7484244",
        "tgn:7001004",
        "tgn:1000004",
        "tgn:1000141",
        "tgn:7029392"
    ],
    "tgn:id":7484244,
    "tgn:name":"Kengnei",
    "tgn:placetype":[
        "aat:300008347"
    ]
},
  "bbox": [],
  "geometry": {"coordinates":[120.519314,22.990655],"type":"Point"}
}
=======
{"geometry":{"type":"Point","coordinates":[120.519314,22.990655]},"type":"Feature","properties":{"hierarchy":["tgn:7484244","tgn:7001004","tgn:1000004","tgn:1000141","tgn:7029392"],"placetype":["aat:300008347"],"id":7484244,"name:xx":"Kengnei"}}
>>>>>>> 03f74aca74312dbeaf24d7e61306dd6a786dc3d0
