{
  "id": 1067378,
  "type": "Feature",
  "properties": {
    "tgn:hierarchy":[
        "tgn:1067378",
        "tgn:1000004",
        "tgn:1001390",
        "tgn:1000111",
        "tgn:7029392"
    ],
    "tgn:id":1067378,
    "tgn:name":"Dahongtaizi",
    "tgn:placetype":[
        "aat:300008347"
    ]
},
  "bbox": [],
  "geometry": {"coordinates":[121.3833,41.6833],"type":"Point"}
}