<<<<<<< HEAD
{
  "id": 7372892,
  "type": "Feature",
  "properties": {
    "tgn:hierarchy":[
        "tgn:7372892",
        "tgn:7005587",
        "tgn:1000001",
        "tgn:7005560",
        "tgn:7029392"
    ],
    "tgn:id":7372892,
    "tgn:name":"La Palma",
    "tgn:placetype":[
        "aat:300008347"
    ]
},
  "bbox": [],
  "geometry": {"coordinates":[-99.7,20.216667],"type":"Point"}
}
=======
{"geometry":{"type":"Point","coordinates":[-99.700000,20.216667]},"type":"Feature","properties":{"hierarchy":["tgn:7372892","tgn:7005587","tgn:1000001","tgn:7005560","tgn:7029392"],"placetype":["aat:300008347"],"id":7372892,"name:xx":"La Palma"}}
>>>>>>> 03f74aca74312dbeaf24d7e61306dd6a786dc3d0
