{
  "id": 7530955,
  "type": "Feature",
  "properties": {
    "tgn:hierarchy":[
        "tgn:7530955",
        "tgn:7001242",
        "tgn:7016833",
        "tgn:1001083",
        "tgn:7029392"
    ],
    "tgn:id":7530955,
    "tgn:name":"Kull\u012byat al Fun\u016bn at Ta\u0163b\u012bq\u012byah",
    "tgn:placetype":[
        "aat:300006610"
    ]
},
  "bbox": [],
  "geometry": {"coordinates":[31.208394,30.029909],"type":"Point"}
}