{
  "id": 7262737,
  "type": "Feature",
  "properties": {
    "tgn:hierarchy":[
        "tgn:7262737",
        "tgn:1000003",
        "tgn:7003632",
        "tgn:7016845",
        "tgn:7029392"
    ],
    "tgn:id":7262737,
    "tgn:name:nl":"Calandkanaal",
    "tgn:placetype":[
        "aat:300386965"
    ]
},
  "bbox": [],
  "geometry": {"coordinates":[4.166667,51.95],"type":"Point"}
}