{
  "id": 2143171,
  "type": "Feature",
  "properties": {
    "tgn:hierarchy":[
        "tgn:2143171",
        "tgn:1000001",
        "tgn:7012149",
        "tgn:2000439",
        "tgn:7007248",
        "tgn:7029392"
    ],
    "tgn:id":2143171,
    "tgn:name":"Bailey Branch",
    "tgn:placetype":[
        "aat:300008699"
    ]
},
  "bbox": [],
  "geometry": {"coordinates":[-82.35,31.2167],"type":"Point"}
}