{
  "id": 1059301,
  "type": "Feature",
  "properties": {
    "tgn:hierarchy":[
        "tgn:1059301",
        "tgn:7594032",
        "tgn:1000003",
        "tgn:7006542",
        "tgn:7029392"
    ],
    "tgn:id":1059301,
    "tgn:name":"Semeli\u0161k\u0117s",
    "tgn:placetype":[
        "aat:300008347"
    ]
},
  "bbox": [],
  "geometry": {"coordinates":[24.6667,54.6667],"type":"Point"}
}