{
  "id": 7540541,
  "type": "Feature",
  "properties": {
    "tgn:hierarchy":[
        "tgn:7540541",
        "tgn:7001242",
        "tgn:7001311",
        "tgn:7016833",
        "tgn:7029392"
    ],
    "tgn:id":7540541,
    "tgn:name:en":"Qirf al Ba\u1e29r\u012b, W\u0101d\u012b",
    "tgn:placetype":[
        "aat:300379998"
    ]
},
  "bbox": [],
  "geometry": {"coordinates":[32.624807,28.928538],"type":"Point"}
}