{
  "id": 7287507,
  "type": "Feature",
  "properties": {
    "tgn:hierarchy":[
        "tgn:7287507",
        "tgn:1001623",
        "tgn:1000049",
        "tgn:1000002",
        "tgn:7029392"
    ],
    "tgn:id":7287507,
    "tgn:name":"Gallardo, Roca",
    "tgn:placetype":[
        "aat:300011692"
    ]
},
  "bbox": [],
  "geometry": {"coordinates":[-74.95,-45.816667],"type":"Point"}
}