{
  "id": 2033440,
  "type": "Feature",
  "properties": {
    "tgn:hierarchy":[
        "tgn:2033440",
        "tgn:1000001",
        "tgn:7012149",
        "tgn:1003004",
        "tgn:7007252",
        "tgn:7029392"
    ],
    "tgn:id":2033440,
    "tgn:name":"Richmond State Hospital",
    "tgn:placetype":[
        "aat:300006676"
    ]
},
  "bbox": [],
  "geometry": {"coordinates":[-84.9167,39.8333],"type":"Point"}
}