{
  "id": 7294554,
  "type": "Feature",
  "properties": {
    "tgn:hierarchy":[
        "tgn:7294554",
        "tgn:7002758",
        "tgn:7002823",
        "tgn:1000003",
        "tgn:1000095",
        "tgn:7029392"
    ],
    "tgn:id":7294554,
    "tgn:name":"Vega de los Hatos",
    "tgn:placetype":[
        "aat:300008347"
    ]
},
  "bbox": [],
  "geometry": {"coordinates":[-6.816667,37.933333],"type":"Point"}
}