{
  "id": 7087562,
  "type": "Feature",
  "properties": {
    "tgn:hierarchy":[
        "tgn:7087562",
        "tgn:1000003",
        "tgn:7003677",
        "tgn:7000084",
        "tgn:7029392"
    ],
    "tgn:id":7087562,
    "tgn:name":"Wegholm",
    "tgn:placetype":[
        "aat:300387200"
    ]
},
  "bbox": [],
  "geometry": {"coordinates":[8.85,52.383333],"type":"Point"}
}