{
  "id": 2736487,
  "type": "Feature",
  "properties": {
    "tgn:hierarchy":[
        "tgn:2736487",
        "tgn:1000001",
        "tgn:7012149",
        "tgn:1002613",
        "tgn:7007710",
        "tgn:7029392"
    ],
    "tgn:id":2736487,
    "tgn:name":"Twin Run",
    "tgn:placetype":[
        "aat:300008699"
    ]
},
  "bbox": [],
  "geometry": {"coordinates":[-76.8333,41.2667],"type":"Point"}
}