{
  "id": 1071485,
  "type": "Feature",
  "properties": {
    "tgn:hierarchy":[
        "tgn:1071485",
        "tgn:1000956",
        "tgn:1000004",
        "tgn:1000111",
        "tgn:7029392"
    ],
    "tgn:id":1071485,
    "tgn:name":"Shangqingshuicun",
    "tgn:placetype":[
        "aat:300008347"
    ]
},
  "bbox": [],
  "geometry": {"coordinates":[115.6333,39.9333],"type":"Point"}
}