<<<<<<< HEAD
{
  "id": 7054397,
  "type": "Feature",
  "properties": {
    "tgn:hierarchy":[
        "tgn:7054397",
        "tgn:1003464",
        "tgn:1000003",
        "tgn:7003241",
        "tgn:1000080",
        "tgn:7029392"
    ],
    "tgn:id":7054397,
    "tgn:name":"Pagano, Monte",
    "tgn:placetype":[
        "aat:300008795"
    ]
},
  "bbox": [],
  "geometry": {"coordinates":[14.166667,41.766667],"type":"Point"}
}
=======
{"geometry":{"type":"Point","coordinates":[14.166667,41.766667]},"type":"Feature","properties":{"hierarchy":["tgn:7054397","tgn:1003464","tgn:1000003","tgn:7003241","tgn:1000080","tgn:7029392"],"placetype":["aat:300008795"],"id":7054397,"name:xx":"Pagano, Monte"}}
>>>>>>> 03f74aca74312dbeaf24d7e61306dd6a786dc3d0
