{
  "id": 2430714,
  "type": "Feature",
  "properties": {
    "tgn:hierarchy":[
        "tgn:2430714",
        "tgn:1007657",
        "tgn:1002534",
        "tgn:1000001",
        "tgn:7012149",
        "tgn:7007249",
        "tgn:7029392"
    ],
    "tgn:id":2430714,
    "tgn:name":"Kaluakoi Valley",
    "tgn:placetype":[
        "aat:300008761"
    ]
},
  "bbox": [],
  "geometry": {"coordinates":[-159.5667,21.9833],"type":"Point"}
}