{
  "id": 2351298,
  "type": "Feature",
  "properties": {
    "tgn:hierarchy":[
        "tgn:2351298",
        "tgn:1000001",
        "tgn:2001702",
        "tgn:7012149",
        "tgn:7007708",
        "tgn:7029392"
    ],
    "tgn:id":2351298,
    "tgn:name":"Glen Aiken Creek",
    "tgn:placetype":[
        "aat:300008706"
    ]
},
  "bbox": [],
  "geometry": {"coordinates":[-124.1333,43.15],"type":"Point"}
}