{
  "id": 7335931,
  "type": "Feature",
  "properties": {
    "tgn:hierarchy":[
        "tgn:7335931",
        "tgn:7002816",
        "tgn:1001647",
        "tgn:1000003",
        "tgn:1000095",
        "tgn:7029392"
    ],
    "tgn:id":7335931,
    "tgn:name":"Farraldos, Collado de los",
    "tgn:placetype":[
        "aat:300259572"
    ]
},
  "bbox": [],
  "geometry": {"coordinates":[-4.45,39.183333],"type":"Point"}
}