{
  "id": 1130791,
  "type": "Feature",
  "properties": {
    "tgn:hierarchy":[
        "tgn:1130791",
        "tgn:7005685",
        "tgn:1000001",
        "tgn:7024197",
        "tgn:7029392"
    ],
    "tgn:id":1130791,
    "tgn:name":"Tha-anne",
    "tgn:placetype":[
        "aat:300008707"
    ]
},
  "bbox": [],
  "geometry": {"coordinates":[-94.6167,60.5167],"type":"Point"}
}