{
  "id": 7426131,
  "type": "Feature",
  "properties": {
    "tgn:hierarchy":[
        "tgn:7426131",
        "tgn:1000001",
        "tgn:7005594",
        "tgn:7005560",
        "tgn:7029392"
    ],
    "tgn:id":7426131,
    "tgn:name":"San Crist\u00f3bal",
    "tgn:placetype":[
        "aat:300008347"
    ]
},
  "bbox": [],
  "geometry": {"coordinates":[-100.366667,22.533333],"type":"Point"}
}