{
  "id": 7570342,
  "type": "Feature",
  "properties": {
    "tgn:hierarchy":[
        "tgn:7570342",
        "tgn:1000004",
        "tgn:1001871",
        "tgn:7000198",
        "tgn:7029392"
    ],
    "tgn:id":7570342,
    "tgn:name:en":"Khukr\u0101na",
    "tgn:placetype":[
        "aat:300008347"
    ]
},
  "bbox": [],
  "geometry": {"coordinates":[76.89464,29.395639],"type":"Point"}
}