{
  "id": 1085343,
  "type": "Feature",
  "properties": {
    "tgn:hierarchy":[
        "tgn:1085343",
        "tgn:1000004",
        "tgn:7491221",
        "tgn:1000141",
        "tgn:7029392"
    ],
    "tgn:id":1085343,
    "tgn:name":"Luye",
    "tgn:placetype":[
        "aat:300008347"
    ]
},
  "bbox": [],
  "geometry": {"coordinates":[121.1333,22.9167],"type":"Point"}
}