{
  "id": 2410763,
  "type": "Feature",
  "properties": {
    "tgn:hierarchy":[
        "tgn:2410763",
        "tgn:1000001",
        "tgn:7012149",
        "tgn:2000839",
        "tgn:7007255",
        "tgn:7029392"
    ],
    "tgn:id":2410763,
    "tgn:name":"Indian Creek",
    "tgn:placetype":[
        "aat:300008706"
    ]
},
  "bbox": [],
  "geometry": {"coordinates":[-84.55,37.1833],"type":"Point"}
}