{
  "id": 7402653,
  "type": "Feature",
  "properties": {
    "tgn:hierarchy":[
        "tgn:7402653",
        "tgn:1000001",
        "tgn:1001937",
        "tgn:7005560",
        "tgn:7029392"
    ],
    "tgn:id":7402653,
    "tgn:name":"Naranjal",
    "tgn:placetype":[
        "aat:300008347"
    ]
},
  "bbox": [],
  "geometry": {"coordinates":[-88.329167,20.058333],"type":"Point"}
}