{
  "id": 7505073,
  "type": "Feature",
  "properties": {
    "tgn:hierarchy":[
        "tgn:7505073",
        "tgn:1008380",
        "tgn:1000226",
        "tgn:7000512",
        "tgn:1000006",
        "tgn:7029392"
    ],
    "tgn:id":7505073,
    "tgn:name:en":"Luna Rock",
    "tgn:placetype":[
        "aat:300011692"
    ]
},
  "bbox": [],
  "geometry": {"coordinates":[175.633333,-41.333333],"type":"Point"}
}