{
  "id": 7579767,
  "type": "Feature",
  "properties": {
    "tgn:hierarchy":[
        "tgn:7579767",
        "tgn:1000004",
        "tgn:7000198",
        "tgn:1001895",
        "tgn:7029392"
    ],
    "tgn:id":7579767,
    "tgn:name:en":"Uplai Buzurg",
    "tgn:placetype":[
        "aat:300008347"
    ]
},
  "bbox": [],
  "geometry": {"coordinates":[75.491976,17.968532],"type":"Point"}
}