{
  "id": 2056391,
  "type": "Feature",
  "properties": {
    "tgn:hierarchy":[
        "tgn:2056391",
        "tgn:1000001",
        "tgn:7012149",
        "tgn:2001161",
        "tgn:7007522",
        "tgn:7029392"
    ],
    "tgn:id":2056391,
    "tgn:name":"Estill",
    "tgn:placetype":[
        "aat:300008347"
    ]
},
  "bbox": [],
  "geometry": {"coordinates":[-90.8667,33.2167],"type":"Point"}
}