{
  "id": 1138941,
  "type": "Feature",
  "properties": {
    "tgn:hierarchy":[
        "tgn:1138941",
        "tgn:1000004",
        "tgn:1001290",
        "tgn:1000111",
        "tgn:7029392"
    ],
    "tgn:id":1138941,
    "tgn:name":"Erlongshan",
    "tgn:placetype":[
        "aat:300008347"
    ]
},
  "bbox": [],
  "geometry": {"coordinates":[126.7833,50.0667],"type":"Point"}
}