{
  "id": 2751266,
  "type": "Feature",
  "properties": {
    "tgn:hierarchy":[
        "tgn:2751266",
        "tgn:1000001",
        "tgn:7012149",
        "tgn:1003020",
        "tgn:7007920",
        "tgn:7029392"
    ],
    "tgn:id":2751266,
    "tgn:name":"Warm Creek",
    "tgn:placetype":[
        "aat:300008706"
    ]
},
  "bbox": [],
  "geometry": {"coordinates":[-121.8833,48.7667],"type":"Point"}
}