{
  "id": 2052950,
  "type": "Feature",
  "properties": {
    "tgn:hierarchy":[
        "tgn:2052950",
        "tgn:1000001",
        "tgn:7012149",
        "tgn:1002967",
        "tgn:7007520",
        "tgn:7029392"
    ],
    "tgn:id":2052950,
    "tgn:name":"Paw Paw",
    "tgn:placetype":[
        "aat:300008347"
    ]
},
  "bbox": [],
  "geometry": {"coordinates":[-85.8833,42.2167],"type":"Point"}
}