{
  "id": 7022280,
  "type": "Feature",
  "properties": {
    "tgn:hierarchy":[
        "tgn:7022280",
        "tgn:1000001",
        "tgn:7012149",
        "tgn:7007158",
        "tgn:2000253",
        "tgn:7029392"
    ],
    "tgn:id":7022280,
    "tgn:name":"Adams and Bunker Reservoirs",
    "tgn:placetype":[
        "aat:300008680"
    ]
},
  "bbox": [],
  "geometry": {"coordinates":[-104.3667,40.8833],"type":"Point"}
}