{
  "id": 7302729,
  "type": "Feature",
  "properties": {
    "tgn:hierarchy":[
        "tgn:7302729",
        "tgn:7002810",
        "tgn:7001158",
        "tgn:1000003",
        "tgn:1000095",
        "tgn:7029392"
    ],
    "tgn:id":7302729,
    "tgn:name":"Nela",
    "tgn:placetype":[
        "aat:300008347"
    ]
},
  "bbox": [],
  "geometry": {"coordinates":[-3.65,42.983333],"type":"Point"}
}