{
  "id": 2314858,
  "type": "Feature",
  "properties": {
    "tgn:hierarchy":[
        "tgn:2314858",
        "tgn:1000001",
        "tgn:7012149",
        "tgn:2001821",
        "tgn:7007713",
        "tgn:7029392"
    ],
    "tgn:id":2314858,
    "tgn:name":"Elkhorn Draw",
    "tgn:placetype":[
        "aat:300008761"
    ]
},
  "bbox": [],
  "geometry": {"coordinates":[-102.8167,43.85],"type":"Point"}
}