{
  "id": 2460669,
  "type": "Feature",
  "properties": {
    "tgn:hierarchy":[
        "tgn:2460669",
        "tgn:1000001",
        "tgn:2001740",
        "tgn:7012149",
        "tgn:7007712",
        "tgn:7029392"
    ],
    "tgn:id":2460669,
    "tgn:name":"Little Seed Branch",
    "tgn:placetype":[
        "aat:300008699"
    ]
},
  "bbox": [],
  "geometry": {"coordinates":[-79.9833,34.4667],"type":"Point"}
}