{
  "id": 7335384,
  "type": "Feature",
  "properties": {
    "tgn:hierarchy":[
        "tgn:7335384",
        "tgn:7002826",
        "tgn:7001158",
        "tgn:1000003",
        "tgn:1000095",
        "tgn:7029392"
    ],
    "tgn:id":7335384,
    "tgn:name":"Fresno de la Vega",
    "tgn:placetype":[
        "aat:300008347"
    ]
},
  "bbox": [],
  "geometry": {"coordinates":[-5.533333,42.35],"type":"Point"}
}