<<<<<<< HEAD
{
  "id": 2259963,
  "type": "Feature",
  "properties": {
    "tgn:hierarchy":[
        "tgn:2259963",
        "tgn:1000001",
        "tgn:7012149",
        "tgn:2001865",
        "tgn:7007825",
        "tgn:7029392"
    ],
    "tgn:id":2259963,
    "tgn:name":"Coulters Shoals",
    "tgn:placetype":[
        "aat:300132348"
    ]
},
  "bbox": [],
  "geometry": {"coordinates":[-83.3,36.2667],"type":"Point"}
}
=======
{"geometry":{"type":"Point","coordinates":[-83.300000,36.266700]},"type":"Feature","properties":{"hierarchy":["tgn:2259963","tgn:1000001","tgn:7012149","tgn:2001865","tgn:7007825","tgn:7029392"],"placetype":["aat:300132348"],"id":2259963,"name:xx":"Coulters Shoals"}}
>>>>>>> 03f74aca74312dbeaf24d7e61306dd6a786dc3d0
