{
  "id": 1034822,
  "type": "Feature",
  "properties": {
    "tgn:hierarchy":[
        "tgn:1034822",
        "tgn:7002872",
        "tgn:1000003",
        "tgn:1000070",
        "tgn:7029392"
    ],
    "tgn:id":1034822,
    "tgn:name":"Pennedepie",
    "tgn:placetype":[
        "aat:300008347"
    ]
},
  "bbox": [],
  "geometry": {"coordinates":[0.1833,49.4167],"type":"Point"}
}