{
  "id": 1122573,
  "type": "Feature",
  "properties": {
    "tgn:hierarchy":[
        "tgn:1122573",
        "tgn:1000001",
        "tgn:1002359",
        "tgn:7012149",
        "tgn:7007517",
        "tgn:7029392"
    ],
    "tgn:id":1122573,
    "tgn:name":"Castle Neck",
    "tgn:placetype":[
        "aat:300008707"
    ]
},
  "bbox": [],
  "geometry": {"coordinates":[-70.8167,42.6333],"type":"Point"}
}