<<<<<<< HEAD
{
  "id": 2409631,
  "type": "Feature",
  "properties": {
    "tgn:hierarchy":[
        "tgn:2409631",
        "tgn:7006450",
        "tgn:2000069",
        "tgn:1000001",
        "tgn:7012149",
        "tgn:7029392"
    ],
    "tgn:id":2409631,
    "tgn:name":"Ikalugtulik River",
    "tgn:placetype":[
        "aat:300008707"
    ]
},
  "bbox": [],
  "geometry": {"coordinates":[-164.9333,60.6167],"type":"Point"}
}
=======
{"geometry":{"type":"Point","coordinates":[-164.933300,60.616700]},"type":"Feature","properties":{"hierarchy":["tgn:2409631","tgn:7006450","tgn:2000069","tgn:1000001","tgn:7012149","tgn:7029392"],"placetype":["aat:300008707"],"id":2409631,"name:xx":"Ikalugtulik River"}}
>>>>>>> 03f74aca74312dbeaf24d7e61306dd6a786dc3d0
