{
  "id": 2676949,
  "type": "Feature",
  "properties": {
    "tgn:hierarchy":[
        "tgn:2676949",
        "tgn:1000001",
        "tgn:7012149",
        "tgn:7007568",
        "tgn:7029392"
    ],
    "tgn:id":2676949,
    "tgn:name":"South Branch Lindsey Creek",
    "tgn:placetype":[
        "aat:300008706"
    ]
},
  "bbox": [],
  "geometry": {"coordinates":[-76.0667,43.6667],"type":"Point"}
}