{
  "id": 1118779,
  "type": "Feature",
  "properties": {
    "tgn:hierarchy":[
        "tgn:1118779",
        "tgn:7006247",
        "tgn:1000047",
        "tgn:7002456",
        "tgn:1000002",
        "tgn:7029392"
    ],
    "tgn:id":1118779,
    "tgn:name":"Xiriri, Lago",
    "tgn:placetype":[
        "aat:300008680"
    ]
},
  "bbox": [],
  "geometry": {"coordinates":[-55.9333,-1.6167],"type":"Point"}
}