{
  "id": 7112443,
  "type": "Feature",
  "properties": {
    "tgn:hierarchy":[
        "tgn:7112443",
        "tgn:1000003",
        "tgn:7003689",
        "tgn:7000084",
        "tgn:7029392"
    ],
    "tgn:id":7112443,
    "tgn:name":"Rosoppe",
    "tgn:placetype":[
        "aat:300008699"
    ]
},
  "bbox": [],
  "geometry": {"coordinates":[10.166667,51.233333],"type":"Point"}
}