{
  "id": 7367978,
  "type": "Feature",
  "properties": {
    "tgn:hierarchy":[
        "tgn:7367978",
        "tgn:1000001",
        "tgn:1001960",
        "tgn:7005560",
        "tgn:7029392"
    ],
    "tgn:id":7367978,
    "tgn:name":"Johnson, Pico de",
    "tgn:placetype":[
        "aat:300008795"
    ]
},
  "bbox": [],
  "geometry": {"coordinates":[-112.116667,29.216667],"type":"Point"}
}