{
  "id": 7442591,
  "type": "Feature",
  "properties": {
    "tgn:hierarchy":[
        "tgn:7442591",
        "tgn:7002445",
        "tgn:1000003",
        "tgn:7008166",
        "tgn:7008591",
        "tgn:7029392"
    ],
    "tgn:id":7442591,
    "tgn:name:en":"North West Riff",
    "tgn:placetype":[
        "aat:300386970"
    ]
},
  "bbox": [],
  "geometry": {"coordinates":[0.25,54.666667],"type":"Point"}
}