{
  "id": 2135571,
  "type": "Feature",
  "properties": {
    "tgn:hierarchy":[
        "tgn:2135571",
        "tgn:1000001",
        "tgn:7012149",
        "tgn:7007826",
        "tgn:7029392"
    ],
    "tgn:id":2135571,
    "tgn:name":"Apache Canyon",
    "tgn:placetype":[
        "aat:300008761"
    ]
},
  "bbox": [],
  "geometry": {"coordinates":[-105.0167,31.4667],"type":"Point"}
}