{
  "id": 2518902,
  "type": "Feature",
  "properties": {
    "tgn:hierarchy":[
        "tgn:2518902",
        "tgn:1000001",
        "tgn:7012149",
        "tgn:2002010",
        "tgn:7007826",
        "tgn:7029392"
    ],
    "tgn:id":2518902,
    "tgn:name":"Mitre Peak",
    "tgn:placetype":[
        "aat:300008798"
    ]
},
  "bbox": [],
  "geometry": {"coordinates":[-103.7833,30.45],"type":"Point"}
}