<<<<<<< HEAD
{
  "id": 7177543,
  "type": "Feature",
  "properties": {
    "tgn:hierarchy":[
        "tgn:7177543",
        "tgn:7000096",
        "tgn:1000003",
        "tgn:7000084",
        "tgn:7029392"
    ],
    "tgn:id":7177543,
    "tgn:name":"Hansfelde",
    "tgn:placetype":[
        "aat:300008347"
    ]
},
  "bbox": [],
  "geometry": {"coordinates":[13.8,53.533333],"type":"Point"}
}
=======
{"geometry":{"type":"Point","coordinates":[13.800000,53.533333]},"type":"Feature","properties":{"hierarchy":["tgn:7177543","tgn:7000096","tgn:1000003","tgn:7000084","tgn:7029392"],"placetype":["aat:300008347"],"id":7177543,"name:xx":"Hansfelde"}}
>>>>>>> 03f74aca74312dbeaf24d7e61306dd6a786dc3d0
