{
  "id": 2545080,
  "type": "Feature",
  "properties": {
    "tgn:hierarchy":[
        "tgn:2545080",
        "tgn:1000001",
        "tgn:2001779",
        "tgn:7012149",
        "tgn:7007713",
        "tgn:7029392"
    ],
    "tgn:id":2545080,
    "tgn:name":"North Double R Creek",
    "tgn:placetype":[
        "aat:300008706"
    ]
},
  "bbox": [],
  "geometry": {"coordinates":[-103.3167,44.9167],"type":"Point"}
}