{
  "id": 1044818,
  "type": "Feature",
  "properties": {
    "tgn:hierarchy":[
        "tgn:1044818",
        "tgn:1003430",
        "tgn:1000003",
        "tgn:7003126",
        "tgn:1000080",
        "tgn:7029392"
    ],
    "tgn:id":1044818,
    "tgn:name":"Gignod",
    "tgn:placetype":[
        "aat:300008347"
    ]
},
  "bbox": [],
  "geometry": {"coordinates":[7.2833,45.7667],"type":"Point"}
}