{
  "id": 1133803,
  "type": "Feature",
  "properties": {
    "tgn:hierarchy":[
        "tgn:1133803",
        "tgn:1000001",
        "tgn:7012149",
        "tgn:7007157",
        "tgn:7014475",
        "tgn:7029392"
    ],
    "tgn:id":1133803,
    "tgn:name":"Matadero Creek",
    "tgn:placetype":[
        "aat:300008706"
    ]
},
  "bbox": [],
  "geometry": {"coordinates":[-122.15,37.3667],"type":"Point"}
}