{
  "id": 7584119,
  "type": "Feature",
  "properties": {
    "tgn:hierarchy":[
        "tgn:7584119",
        "tgn:1000004",
        "tgn:7000198",
        "tgn:1001894",
        "tgn:7029392"
    ],
    "tgn:id":7584119,
    "tgn:name:en":"Uriya T\u0101l",
    "tgn:placetype":[
        "aat:300008680"
    ]
},
  "bbox": [],
  "geometry": {"coordinates":[78.927792,24.940424],"type":"Point"}
}