{
  "id": 7369964,
  "type": "Feature",
  "properties": {
    "tgn:hierarchy":[
        "tgn:7369964",
        "tgn:1000001",
        "tgn:7005588",
        "tgn:7005560",
        "tgn:7029392"
    ],
    "tgn:id":7369964,
    "tgn:name":"Huazulco",
    "tgn:placetype":[
        "aat:300008347"
    ]
},
  "bbox": [],
  "geometry": {"coordinates":[-98.766667,18.75],"type":"Point"}
}