{
  "id": 7459606,
  "type": "Feature",
  "properties": {
    "tgn:hierarchy":[
        "tgn:7459606",
        "tgn:7002448",
        "tgn:7019159",
        "tgn:1000003",
        "tgn:7008591",
        "tgn:7029392"
    ],
    "tgn:id":7459606,
    "tgn:name:en":"Portmuck Bay",
    "tgn:placetype":[
        "aat:300132316"
    ]
},
  "bbox": [],
  "geometry": {"coordinates":[-5.716667,54.833333],"type":"Point"}
}