{
  "id": 7591076,
  "type": "Feature",
  "properties": {
    "tgn:hierarchy":[
        "tgn:7591076",
        "tgn:1000004",
        "tgn:7000198",
        "tgn:7000799",
        "tgn:7029392"
    ],
    "tgn:id":7591076,
    "tgn:name:en":"Nadrol",
    "tgn:placetype":[
        "aat:300008347"
    ]
},
  "bbox": [],
  "geometry": {"coordinates":[74.894393,32.570639],"type":"Point"}
}