{
  "id": 2064470,
  "type": "Feature",
  "properties": {
    "tgn:hierarchy":[
        "tgn:2064470",
        "tgn:1002215",
        "tgn:1000001",
        "tgn:7012149",
        "tgn:7007565",
        "tgn:7029392"
    ],
    "tgn:id":2064470,
    "tgn:name":"Cookstown",
    "tgn:placetype":[
        "aat:300008347"
    ]
},
  "bbox": [],
  "geometry": {"coordinates":[-74.55,40.0333],"type":"Point"}
}