{
  "id": 7357912,
  "type": "Feature",
  "properties": {
    "tgn:hierarchy":[
        "tgn:7357912",
        "tgn:1000001",
        "tgn:7005594",
        "tgn:7005560",
        "tgn:7029392"
    ],
    "tgn:id":7357912,
    "tgn:name":"Curtida",
    "tgn:placetype":[
        "aat:300008347"
    ]
},
  "bbox": [],
  "geometry": {"coordinates":[-100.433333,21.766667],"type":"Point"}
}