{
  "id": 2140529,
  "type": "Feature",
  "properties": {
    "tgn:hierarchy":[
        "tgn:2140529",
        "tgn:1000001",
        "tgn:2002324",
        "tgn:7012149",
        "tgn:7007922",
        "tgn:7029392"
    ],
    "tgn:id":2140529,
    "tgn:name":"Austin Branch",
    "tgn:placetype":[
        "aat:300008699"
    ]
},
  "bbox": [],
  "geometry": {"coordinates":[-90.6667,42.8167],"type":"Point"}
}