{
  "id": 7328802,
  "type": "Feature",
  "properties": {
    "tgn:hierarchy":[
        "tgn:7328802",
        "tgn:7002827",
        "tgn:1000003",
        "tgn:7002789",
        "tgn:1000095",
        "tgn:7029392"
    ],
    "tgn:id":7328802,
    "tgn:name":"Pradej\u00f3n",
    "tgn:placetype":[
        "aat:300008347"
    ]
},
  "bbox": [],
  "geometry": {"coordinates":[-2.066667,42.333333],"type":"Point"}
}