{
  "id": 7047753,
  "type": "Feature",
  "properties": {
    "tgn:hierarchy":[
        "tgn:7047753",
        "tgn:7003013",
        "tgn:7003005",
        "tgn:1000003",
        "tgn:1000080",
        "tgn:7029392"
    ],
    "tgn:id":7047753,
    "tgn:name":"Casandrino",
    "tgn:placetype":[
        "aat:300008347"
    ]
},
  "bbox": [],
  "geometry": {"coordinates":[14.25,40.933333],"type":"Point"}
}