{
  "id": 7151246,
  "type": "Feature",
  "properties": {
    "tgn:hierarchy":[
        "tgn:7151246",
        "tgn:7000096",
        "tgn:1000003",
        "tgn:7000084",
        "tgn:7029392"
    ],
    "tgn:id":7151246,
    "tgn:name":"Je\u00dfnigker Wiesen",
    "tgn:placetype":[
        "aat:300386990"
    ]
},
  "bbox": [],
  "geometry": {"coordinates":[13.266667,51.716667],"type":"Point"}
}