{
  "id": 7218530,
  "type": "Feature",
  "properties": {
    "tgn:hierarchy":[
        "tgn:7218530",
        "tgn:7011161",
        "tgn:7002674",
        "tgn:1000003",
        "tgn:1000074",
        "tgn:7029392"
    ],
    "tgn:id":7218530,
    "tgn:name":"\u00c1gioi Ap\u00f3stoloi",
    "tgn:placetype":[
        "aat:300007466"
    ]
},
  "bbox": [],
  "geometry": {"coordinates":[26.079167,38.363333],"type":"Point"}
}