{
  "id": 1129636,
  "type": "Feature",
  "properties": {
    "tgn:hierarchy":[
        "tgn:1129636",
        "tgn:1001206",
        "tgn:1000001",
        "tgn:7004624",
        "tgn:7029392"
    ],
    "tgn:id":1129636,
    "tgn:name":"Santa Cruz",
    "tgn:placetype":[
        "aat:300008707"
    ]
},
  "bbox": [],
  "geometry": {"coordinates":[-82.4833,23.0667],"type":"Point"}
}