{
  "id": 7070024,
  "type": "Feature",
  "properties": {
    "tgn:hierarchy":[
        "tgn:7070024",
        "tgn:1000003",
        "tgn:7003678",
        "tgn:7000084",
        "tgn:7029392"
    ],
    "tgn:id":7070024,
    "tgn:name":"Hof Tiergarten",
    "tgn:placetype":[
        "aat:300000206"
    ]
},
  "bbox": [],
  "geometry": {"coordinates":[8.316667,50.483333],"type":"Point"}
}