{
  "id": 2613410,
  "type": "Feature",
  "properties": {
    "tgn:hierarchy":[
        "tgn:2613410",
        "tgn:1000001",
        "tgn:7012149",
        "tgn:7013867",
        "tgn:7007710",
        "tgn:7029392"
    ],
    "tgn:id":2613410,
    "tgn:name":"Reed Island",
    "tgn:placetype":[
        "aat:300008791"
    ]
},
  "bbox": [],
  "geometry": {"coordinates":[-76.35,39.85],"type":"Point"}
}