{
  "id": 2185426,
  "type": "Feature",
  "properties": {
    "tgn:hierarchy":[
        "tgn:2185426",
        "tgn:1000001",
        "tgn:7012149",
        "tgn:2001907",
        "tgn:7007825",
        "tgn:7029392"
    ],
    "tgn:id":2185426,
    "tgn:name":"Bohannon Cave",
    "tgn:placetype":[
        "aat:300008746"
    ]
},
  "bbox": [],
  "geometry": {"coordinates":[-85.3833,36.1333],"type":"Point"}
}