<<<<<<< HEAD
{
  "id": 7354895,
  "type": "Feature",
  "properties": {
    "tgn:hierarchy":[
        "tgn:7354895",
        "tgn:7005580",
        "tgn:1000001",
        "tgn:7005560",
        "tgn:7029392"
    ],
    "tgn:id":7354895,
    "tgn:name":"Chaspac, Arroyo",
    "tgn:placetype":[
        "aat:300008699"
    ]
},
  "bbox": [],
  "geometry": {"coordinates":[-93.433333,17.116667],"type":"Point"}
}
=======
{"geometry":{"type":"Point","coordinates":[-93.433333,17.116667]},"type":"Feature","properties":{"hierarchy":["tgn:7354895","tgn:7005580","tgn:1000001","tgn:7005560","tgn:7029392"],"placetype":["aat:300008699"],"id":7354895,"name:xx":"Chaspac, Arroyo"}}
>>>>>>> 03f74aca74312dbeaf24d7e61306dd6a786dc3d0
