{
  "id": 7354895,
  "type": "Feature",
  "properties": {
    "tgn:hierarchy":[
        "tgn:7354895",
        "tgn:7005580",
        "tgn:1000001",
        "tgn:7005560",
        "tgn:7029392"
    ],
    "tgn:id":7354895,
    "tgn:name":"Chaspac, Arroyo",
    "tgn:placetype":[
        "aat:300008699"
    ]
},
  "bbox": [],
  "geometry": {"coordinates":[-93.433333,17.116667],"type":"Point"}
}