{
  "id": 7318254,
  "type": "Feature",
  "properties": {
    "tgn:hierarchy":[
        "tgn:7318254",
        "tgn:1001630",
        "tgn:1000049",
        "tgn:1000002",
        "tgn:7029392"
    ],
    "tgn:id":7318254,
    "tgn:name":"Checo del Cobre, Sierra",
    "tgn:placetype":[
        "aat:300008795"
    ]
},
  "bbox": [],
  "geometry": {"coordinates":[-70.216667,-27.533333],"type":"Point"}
}