{
  "id": 2613119,
  "type": "Feature",
  "properties": {
    "tgn:hierarchy":[
        "tgn:2613119",
        "tgn:1000001",
        "tgn:7012149",
        "tgn:2002272",
        "tgn:7013961",
        "tgn:7029392"
    ],
    "tgn:id":2613119,
    "tgn:name":"Redwing",
    "tgn:placetype":[
        "aat:300008347"
    ]
},
  "bbox": [],
  "geometry": {"coordinates":[-82.2333,38.1667],"type":"Point"}
}