<<<<<<< HEAD
{
  "id": 7362187,
  "type": "Feature",
  "properties": {
    "tgn:hierarchy":[
        "tgn:7362187",
        "tgn:7005586",
        "tgn:1000001",
        "tgn:7005560",
        "tgn:7029392"
    ],
    "tgn:id":7362187,
    "tgn:name":"El Lim\u00f3n",
    "tgn:placetype":[
        "aat:300000241"
    ]
},
  "bbox": [],
  "geometry": {"coordinates":[-102.75,19.866667],"type":"Point"}
}
=======
{"geometry":{"type":"Point","coordinates":[-102.750000,19.866667]},"type":"Feature","properties":{"hierarchy":["tgn:7362187","tgn:7005586","tgn:1000001","tgn:7005560","tgn:7029392"],"placetype":["aat:300000241"],"id":7362187,"name:xx":"El Lim\u00f3n"}}
>>>>>>> 03f74aca74312dbeaf24d7e61306dd6a786dc3d0
