{
  "id": 2118806,
  "type": "Feature",
  "properties": {
    "tgn:hierarchy":[
        "tgn:2118806",
        "tgn:1000001",
        "tgn:7012149",
        "tgn:2002276",
        "tgn:7013961",
        "tgn:7029392"
    ],
    "tgn:id":2118806,
    "tgn:name":"Kent",
    "tgn:placetype":[
        "aat:300008347"
    ]
},
  "bbox": [],
  "geometry": {"coordinates":[-80.85,39.75],"type":"Point"}
}