{
  "id": 2672403,
  "type": "Feature",
  "properties": {
    "tgn:hierarchy":[
        "tgn:2672403",
        "tgn:7002659",
        "tgn:1000001",
        "tgn:7012149",
        "tgn:2000051",
        "tgn:7029392"
    ],
    "tgn:id":2672403,
    "tgn:name":"Smokey Hole Cave",
    "tgn:placetype":[
        "aat:300008746"
    ]
},
  "bbox": [],
  "geometry": {"coordinates":[-86.5833,34.3333],"type":"Point"}
}