{
  "id": 7491802,
  "type": "Feature",
  "properties": {
    "tgn:hierarchy":[
        "tgn:7491802",
        "tgn:7488858",
        "tgn:1000004",
        "tgn:1000141",
        "tgn:7029392"
    ],
    "tgn:id":7491802,
    "tgn:name":"Shanzhajiao",
    "tgn:placetype":[
        "aat:300008347"
    ]
},
  "bbox": [],
  "geometry": {"coordinates":[120.915008,23.910347],"type":"Point"}
}