{
  "id": 7327982,
  "type": "Feature",
  "properties": {
    "tgn:hierarchy":[
        "tgn:7327982",
        "tgn:7002824",
        "tgn:1000003",
        "tgn:7002786",
        "tgn:1000095",
        "tgn:7029392"
    ],
    "tgn:id":7327982,
    "tgn:name":"Pombal",
    "tgn:placetype":[
        "aat:300008347"
    ]
},
  "bbox": [],
  "geometry": {"coordinates":[-8.933333,43.166667],"type":"Point"}
}