{
  "id": 7529381,
  "type": "Feature",
  "properties": {
    "tgn:hierarchy":[
        "tgn:7529381",
        "tgn:7001242",
        "tgn:1001059",
        "tgn:7016833",
        "tgn:7029392"
    ],
    "tgn:id":7529381,
    "tgn:name":"Tur'at al Ma\u015ff\u00e1",
    "tgn:placetype":[
        "aat:300006075"
    ]
},
  "bbox": [],
  "geometry": {"coordinates":[31.502013,30.992104],"type":"Point"}
}