{
  "id": 7017356,
  "type": "Feature",
  "properties": {
    "tgn:hierarchy":[
        "tgn:7017356",
        "tgn:1000003",
        "tgn:7006656",
        "tgn:7029392"
    ],
    "tgn:id":7017356,
    "tgn:name":"Ialoveni",
    "tgn:placetype":[
        "aat:300387064",
        "aat:300387081",
        "aat:300391502"
    ]
},
  "bbox": [],
  "geometry": {"coordinates":[28.833333,46.833333],"type":"Point"}
}