{
  "id": 2582106,
  "type": "Feature",
  "properties": {
    "tgn:hierarchy":[
        "tgn:2582106",
        "tgn:1000001",
        "tgn:7012149",
        "tgn:7007157",
        "tgn:1002608",
        "tgn:7029392"
    ],
    "tgn:id":2582106,
    "tgn:name":"Pine Creek",
    "tgn:placetype":[
        "aat:300008706"
    ]
},
  "bbox": [],
  "geometry": {"coordinates":[-118.25,34.5667],"type":"Point"}
}