{
  "id": 2684908,
  "type": "Feature",
  "properties": {
    "tgn:hierarchy":[
        "tgn:2684908",
        "tgn:1000001",
        "tgn:7016098",
        "tgn:7012149",
        "tgn:7007516",
        "tgn:7029392"
    ],
    "tgn:id":2684908,
    "tgn:name":"Split Point",
    "tgn:placetype":[
        "aat:300008850"
    ]
},
  "bbox": [],
  "geometry": {"coordinates":[-76.3333,38.1167],"type":"Point"}
}