{
  "id": 2018343,
  "type": "Feature",
  "properties": {
    "tgn:hierarchy":[
        "tgn:2018343",
        "tgn:7013962",
        "tgn:1000001",
        "tgn:7012149",
        "tgn:7015717",
        "tgn:7029392"
    ],
    "tgn:id":2018343,
    "tgn:name":"Hawthorne",
    "tgn:placetype":[
        "aat:300000745"
    ]
},
  "bbox": [],
  "geometry": {"coordinates":[-77.05,38.9667],"type":"Point"}
}