{
  "id": 2530903,
  "type": "Feature",
  "properties": {
    "tgn:hierarchy":[
        "tgn:2530903",
        "tgn:1002153",
        "tgn:1000001",
        "tgn:7012149",
        "tgn:7007710",
        "tgn:7029392"
    ],
    "tgn:id":2530903,
    "tgn:name":"Mudlick Creek",
    "tgn:placetype":[
        "aat:300008706"
    ]
},
  "bbox": [],
  "geometry": {"coordinates":[-79.2167,41.0167],"type":"Point"}
}