{
  "id": 7121686,
  "type": "Feature",
  "properties": {
    "tgn:hierarchy":[
        "tgn:7121686",
        "tgn:7003669",
        "tgn:1000003",
        "tgn:7000084",
        "tgn:7029392"
    ],
    "tgn:id":7121686,
    "tgn:name":"Petzling",
    "tgn:placetype":[
        "aat:300000206"
    ]
},
  "bbox": [],
  "geometry": {"coordinates":[12.416667,48.366667],"type":"Point"}
}