<<<<<<< HEAD
{
  "id": 2339226,
  "type": "Feature",
  "properties": {
    "tgn:hierarchy":[
        "tgn:2339226",
        "tgn:1000001",
        "tgn:7012149",
        "tgn:2000209",
        "tgn:7007158",
        "tgn:7029392"
    ],
    "tgn:id":2339226,
    "tgn:name":"Franktown Parker FPR-2 Reservoir",
    "tgn:placetype":[
        "aat:300006191"
    ]
},
  "bbox": [],
  "geometry": {"coordinates":[-104.7167,39.3667],"type":"Point"}
}
=======
{"geometry":{"type":"Point","coordinates":[-104.716700,39.366700]},"type":"Feature","properties":{"hierarchy":["tgn:2339226","tgn:1000001","tgn:7012149","tgn:2000209","tgn:7007158","tgn:7029392"],"placetype":["aat:300006191"],"id":2339226,"name:xx":"Franktown Parker FPR-2 Reservoir"}}
>>>>>>> 03f74aca74312dbeaf24d7e61306dd6a786dc3d0
