<<<<<<< HEAD
{
  "id": 2158731,
  "type": "Feature",
  "properties": {
    "tgn:hierarchy":[
        "tgn:2158731",
        "tgn:1000001",
        "tgn:7012149",
        "tgn:1002517",
        "tgn:7007523",
        "tgn:7029392"
    ],
    "tgn:id":2158731,
    "tgn:name":"Beck",
    "tgn:placetype":[
        "aat:300008347"
    ]
},
  "bbox": [],
  "geometry": {"coordinates":[-90.3667,38.4],"type":"Point"}
}
=======
{"geometry":{"type":"Point","coordinates":[-90.366700,38.400000]},"type":"Feature","properties":{"hierarchy":["tgn:2158731","tgn:1000001","tgn:7012149","tgn:1002517","tgn:7007523","tgn:7029392"],"placetype":["aat:300008347"],"id":2158731,"name:xx":"Beck"}}
>>>>>>> 03f74aca74312dbeaf24d7e61306dd6a786dc3d0
