{
  "id": 2677787,
  "type": "Feature",
  "properties": {
    "tgn:hierarchy":[
        "tgn:2677787",
        "tgn:1000001",
        "tgn:7012149",
        "tgn:2002376",
        "tgn:7007923",
        "tgn:7029392"
    ],
    "tgn:id":2677787,
    "tgn:name":"South Doe Creek",
    "tgn:placetype":[
        "aat:300008706"
    ]
},
  "bbox": [],
  "geometry": {"coordinates":[-110.7833,43.0667],"type":"Point"}
}