{
  "id": 2746149,
  "type": "Feature",
  "properties": {
    "tgn:hierarchy":[
        "tgn:2746149",
        "tgn:1000001",
        "tgn:7012149",
        "tgn:1002737",
        "tgn:7007520",
        "tgn:7029392"
    ],
    "tgn:id":2746149,
    "tgn:name":"Voorheis Lake",
    "tgn:placetype":[
        "aat:300008680"
    ]
},
  "bbox": [],
  "geometry": {"coordinates":[-83.2833,42.7333],"type":"Point"}
}