{
  "id": 7540325,
  "type": "Feature",
  "properties": {
    "tgn:hierarchy":[
        "tgn:7540325",
        "tgn:7001242",
        "tgn:7016833",
        "tgn:7000122",
        "tgn:7029392"
    ],
    "tgn:id":7540325,
    "tgn:name:en":"Naj' ad Dakkah al Qibl\u012byah, Khawr",
    "tgn:placetype":[
        "aat:300185707"
    ]
},
  "bbox": [],
  "geometry": {"coordinates":[32.733333,23.15],"type":"Point"}
}