{
  "id": 7464387,
  "type": "Feature",
  "properties": {
    "tgn:hierarchy":[
        "tgn:7464387",
        "tgn:7002445",
        "tgn:1000003",
        "tgn:7008127",
        "tgn:7008591",
        "tgn:7029392"
    ],
    "tgn:id":7464387,
    "tgn:name:en":"Brancepeth",
    "tgn:placetype":[
        "aat:300008347"
    ]
},
  "bbox": [],
  "geometry": {"coordinates":[-1.65,54.733333],"type":"Point"}
}