{
  "id": 2279486,
  "type": "Feature",
  "properties": {
    "tgn:hierarchy":[
        "tgn:2279486",
        "tgn:1000001",
        "tgn:7012149",
        "tgn:2002274",
        "tgn:7013961",
        "tgn:7029392"
    ],
    "tgn:id":2279486,
    "tgn:name":"Deadman Hollow",
    "tgn:placetype":[
        "aat:300008761"
    ]
},
  "bbox": [],
  "geometry": {"coordinates":[-81.5667,37.2333],"type":"Point"}
}