{
  "id": 2151342,
  "type": "Feature",
  "properties": {
    "tgn:hierarchy":[
        "tgn:2151342",
        "tgn:1000001",
        "tgn:7012149",
        "tgn:1003038",
        "tgn:7007517",
        "tgn:7029392"
    ],
    "tgn:id":2151342,
    "tgn:name":"Bates Island",
    "tgn:placetype":[
        "aat:300008791"
    ]
},
  "bbox": [],
  "geometry": {"coordinates":[-71.8333,42.0167],"type":"Point"}
}