<<<<<<< HEAD
{
  "id": 2151342,
  "type": "Feature",
  "properties": {
    "tgn:hierarchy":[
        "tgn:2151342",
        "tgn:1000001",
        "tgn:7012149",
        "tgn:1003038",
        "tgn:7007517",
        "tgn:7029392"
    ],
    "tgn:id":2151342,
    "tgn:name":"Bates Island",
    "tgn:placetype":[
        "aat:300008791"
    ]
},
  "bbox": [],
  "geometry": {"coordinates":[-71.8333,42.0167],"type":"Point"}
}
=======
{"geometry":{"type":"Point","coordinates":[-71.833300,42.016700]},"type":"Feature","properties":{"hierarchy":["tgn:2151342","tgn:1000001","tgn:7012149","tgn:1003038","tgn:7007517","tgn:7029392"],"placetype":["aat:300008791"],"id":2151342,"name:xx":"Bates Island"}}
>>>>>>> 03f74aca74312dbeaf24d7e61306dd6a786dc3d0
