<<<<<<< HEAD
{
  "id": 7476166,
  "type": "Feature",
  "properties": {
    "tgn:hierarchy":[
        "tgn:7476166",
        "tgn:7487020",
        "tgn:1000004",
        "tgn:1000141",
        "tgn:7029392"
    ],
    "tgn:id":7476166,
    "tgn:name":"Shoushan Qiao",
    "tgn:placetype":[
        "aat:300007836"
    ]
},
  "bbox": [],
  "geometry": {"coordinates":[120.876719,24.71585],"type":"Point"}
}
=======
{"geometry":{"type":"Point","coordinates":[120.876719,24.715850]},"type":"Feature","properties":{"hierarchy":["tgn:7476166","tgn:7487020","tgn:1000004","tgn:1000141","tgn:7029392"],"placetype":["aat:300007836"],"id":7476166,"name:xx":"Shoushan Qiao"}}
>>>>>>> 03f74aca74312dbeaf24d7e61306dd6a786dc3d0
