{
  "id": 7476166,
  "type": "Feature",
  "properties": {
    "tgn:hierarchy":[
        "tgn:7476166",
        "tgn:7487020",
        "tgn:1000004",
        "tgn:1000141",
        "tgn:7029392"
    ],
    "tgn:id":7476166,
    "tgn:name":"Shoushan Qiao",
    "tgn:placetype":[
        "aat:300007836"
    ]
},
  "bbox": [],
  "geometry": {"coordinates":[120.876719,24.71585],"type":"Point"}
}