<<<<<<< HEAD
{
  "id": 2402403,
  "type": "Feature",
  "properties": {
    "tgn:hierarchy":[
        "tgn:2402403",
        "tgn:1000001",
        "tgn:2000275",
        "tgn:7012149",
        "tgn:7007240",
        "tgn:7029392"
    ],
    "tgn:id":2402403,
    "tgn:name":"Horton Sog",
    "tgn:placetype":[
        "aat:300008905"
    ]
},
  "bbox": [],
  "geometry": {"coordinates":[-83.35,30.0167],"type":"Point"}
}
=======
{"geometry":{"type":"Point","coordinates":[-83.350000,30.016700]},"type":"Feature","properties":{"hierarchy":["tgn:2402403","tgn:1000001","tgn:2000275","tgn:7012149","tgn:7007240","tgn:7029392"],"placetype":["aat:300008905"],"id":2402403,"name:xx":"Horton Sog"}}
>>>>>>> 03f74aca74312dbeaf24d7e61306dd6a786dc3d0
