{
  "id": 2402403,
  "type": "Feature",
  "properties": {
    "tgn:hierarchy":[
        "tgn:2402403",
        "tgn:1000001",
        "tgn:2000275",
        "tgn:7012149",
        "tgn:7007240",
        "tgn:7029392"
    ],
    "tgn:id":2402403,
    "tgn:name":"Horton Sog",
    "tgn:placetype":[
        "aat:300008905"
    ]
},
  "bbox": [],
  "geometry": {"coordinates":[-83.35,30.0167],"type":"Point"}
}