{
  "id": 7521920,
  "type": "Feature",
  "properties": {
    "tgn:hierarchy":[
        "tgn:7521920",
        "tgn:7001242",
        "tgn:7016833",
        "tgn:1001418",
        "tgn:7029392"
    ],
    "tgn:id":7521920,
    "tgn:name:en":"Ab\u016b Mukhayya\u0163, Minq\u0101r",
    "tgn:placetype":[
        "aat:300008749"
    ]
},
  "bbox": [],
  "geometry": {"coordinates":[27.251077,30.676902],"type":"Point"}
}