{
  "id": 7226516,
  "type": "Feature",
  "properties": {
    "tgn:hierarchy":[
        "tgn:7226516",
        "tgn:7011270",
        "tgn:7002674",
        "tgn:1000003",
        "tgn:1000074",
        "tgn:7029392"
    ],
    "tgn:id":7226516,
    "tgn:name":"Smardh\u00e1kion",
    "tgn:placetype":[
        "aat:300008347"
    ]
},
  "bbox": [],
  "geometry": {"coordinates":[25.15,37.583333],"type":"Point"}
}