{
  "id": 7570957,
  "type": "Feature",
  "properties": {
    "tgn:hierarchy":[
        "tgn:7570957",
        "tgn:1000004",
        "tgn:1001871",
        "tgn:7000198",
        "tgn:7029392"
    ],
    "tgn:id":7570957,
    "tgn:name:en":"Ghiar",
    "tgn:placetype":[
        "aat:300008347"
    ]
},
  "bbox": [],
  "geometry": {"coordinates":[77.106179,29.781323],"type":"Point"}
}