{
  "id": 1110889,
  "type": "Feature",
  "properties": {
    "tgn:hierarchy":[
        "tgn:1110889",
        "tgn:1000004",
        "tgn:1000121",
        "tgn:7029392"
    ],
    "tgn:id":1110889,
    "tgn:name":"Ar\u1e0d a\u1e63-\u1e62aww\u0101n",
    "tgn:placetype":[
        "aat:300008805"
    ]
},
  "bbox": [],
  "geometry": {"coordinates":[37.25,30.75],"type":"Point"}
}