{
  "id": 2628683,
  "type": "Feature",
  "properties": {
    "tgn:hierarchy":[
        "tgn:2628683",
        "tgn:1000001",
        "tgn:7012149",
        "tgn:7014318",
        "tgn:7007568",
        "tgn:7029392"
    ],
    "tgn:id":2628683,
    "tgn:name":"Rootville",
    "tgn:placetype":[
        "aat:300008347"
    ]
},
  "bbox": [],
  "geometry": {"coordinates":[-75.2667,42.45],"type":"Point"}
}