{
  "id": 7590732,
  "type": "Feature",
  "properties": {
    "tgn:hierarchy":[
        "tgn:7590732",
        "tgn:1000004",
        "tgn:7000198",
        "tgn:7000799",
        "tgn:7029392"
    ],
    "tgn:id":7590732,
    "tgn:name:en":"Muhri\u0101n",
    "tgn:placetype":[
        "aat:300008347"
    ]
},
  "bbox": [],
  "geometry": {"coordinates":[73.962363,34.40813],"type":"Point"}
}