<<<<<<< HEAD
{
  "id": 7356389,
  "type": "Feature",
  "properties": {
    "tgn:hierarchy":[
        "tgn:7356389",
        "tgn:7005581",
        "tgn:1000001",
        "tgn:7005560",
        "tgn:7029392"
    ],
    "tgn:id":7356389,
    "tgn:name":"Caliente, Ojo",
    "tgn:placetype":[
        "aat:300008697"
    ]
},
  "bbox": [],
  "geometry": {"coordinates":[-107.55,31.3],"type":"Point"}
}
=======
{"geometry":{"type":"Point","coordinates":[-107.550000,31.300000]},"type":"Feature","properties":{"hierarchy":["tgn:7356389","tgn:7005581","tgn:1000001","tgn:7005560","tgn:7029392"],"placetype":["aat:300008697"],"id":7356389,"name:xx":"Caliente, Ojo"}}
>>>>>>> 03f74aca74312dbeaf24d7e61306dd6a786dc3d0
