{
  "id": 7553307,
  "type": "Feature",
  "properties": {
    "tgn:hierarchy":[
        "tgn:7553307",
        "tgn:1000004",
        "tgn:1001869",
        "tgn:7000198",
        "tgn:7029392"
    ],
    "tgn:id":7553307,
    "tgn:name:en":"P\u0101nero T\u0101pu",
    "tgn:placetype":[
        "aat:300008791"
    ]
},
  "bbox": [],
  "geometry": {"coordinates":[69.449167,22.356111],"type":"Point"}
}