{
  "id": 2551389,
  "type": "Feature",
  "properties": {
    "tgn:hierarchy":[
        "tgn:2551389",
        "tgn:1000001",
        "tgn:7016172",
        "tgn:7012149",
        "tgn:2000160",
        "tgn:7029392"
    ],
    "tgn:id":2551389,
    "tgn:name":"Number 1, Ditch",
    "tgn:placetype":[
        "aat:300006075"
    ]
},
  "bbox": [],
  "geometry": {"coordinates":[-90.3333,35.65],"type":"Point"}
}