{
  "id": 7454068,
  "type": "Feature",
  "properties": {
    "tgn:hierarchy":[
        "tgn:7454068",
        "tgn:7002445",
        "tgn:1000003",
        "tgn:7008174",
        "tgn:7008591",
        "tgn:7029392"
    ],
    "tgn:id":7454068,
    "tgn:name:en":"Denstone",
    "tgn:placetype":[
        "aat:300008347"
    ]
},
  "bbox": [],
  "geometry": {"coordinates":[-1.85,52.966667],"type":"Point"}
}