{
  "id": 2243532,
  "type": "Feature",
  "properties": {
    "tgn:hierarchy":[
        "tgn:2243532",
        "tgn:7002659",
        "tgn:1000001",
        "tgn:2000014",
        "tgn:7012149",
        "tgn:7029392"
    ],
    "tgn:id":2243532,
    "tgn:name":"Cleburne",
    "tgn:placetype":[
        "aat:300008347"
    ]
},
  "bbox": [],
  "geometry": {"coordinates":[-85.6167,33.6333],"type":"Point"}
}