{
  "id": 2702671,
  "type": "Feature",
  "properties": {
    "tgn:hierarchy":[
        "tgn:2702671",
        "tgn:1000001",
        "tgn:7012149",
        "tgn:7007708",
        "tgn:7029392"
    ],
    "tgn:id":2702671,
    "tgn:name":"Sulphur Gulch",
    "tgn:placetype":[
        "aat:300008761"
    ]
},
  "bbox": [],
  "geometry": {"coordinates":[-119.0333,44.95],"type":"Point"}
}