{
  "id": 7536479,
  "type": "Feature",
  "properties": {
    "tgn:hierarchy":[
        "tgn:7536479",
        "tgn:7001242",
        "tgn:7016833",
        "tgn:1001225",
        "tgn:7029392"
    ],
    "tgn:id":7536479,
    "tgn:name:en":"Raswat 'Izbat al \u1e28\u0101jjah",
    "tgn:placetype":[
        "aat:300386968"
    ]
},
  "bbox": [],
  "geometry": {"coordinates":[31.784851,31.324303],"type":"Point"}
}