{
  "id": 7080650,
  "type": "Feature",
  "properties": {
    "tgn:hierarchy":[
        "tgn:7080650",
        "tgn:7003669",
        "tgn:1000003",
        "tgn:7000084",
        "tgn:7029392"
    ],
    "tgn:id":7080650,
    "tgn:name":"Winkler",
    "tgn:placetype":[
        "aat:300000206"
    ]
},
  "bbox": [],
  "geometry": {"coordinates":[12.85,48.383333],"type":"Point"}
}