{
  "id": 7575178,
  "type": "Feature",
  "properties": {
    "tgn:hierarchy":[
        "tgn:7575178",
        "tgn:1000004",
        "tgn:7031781",
        "tgn:7000198",
        "tgn:7029392"
    ],
    "tgn:id":7575178,
    "tgn:name:en":"Kodwa",
    "tgn:placetype":[
        "aat:300008347"
    ]
},
  "bbox": [],
  "geometry": {"coordinates":[81.493259,22.355706],"type":"Point"}
}