{
  "id": 7005263,
  "type": "Feature",
  "properties": {
    "tgn:hierarchy":[
        "tgn:7005263",
        "tgn:1000002",
        "tgn:7029392"
    ],
    "tgn:id":7005263,
    "tgn:name":"Fitzroy, Cerro",
    "tgn:placetype":[
        "aat:300008795"
    ]
},
  "bbox": [],
  "geometry": {"coordinates":[-73.05,-48.2667],"type":"Point"}
}