{
  "id": 7164246,
  "type": "Feature",
  "properties": {
    "tgn:hierarchy":[
        "tgn:7164246",
        "tgn:1000003",
        "tgn:7003677",
        "tgn:7000084",
        "tgn:7029392"
    ],
    "tgn:id":7164246,
    "tgn:name":"Im Dieken",
    "tgn:placetype":[
        "aat:300000206"
    ]
},
  "bbox": [],
  "geometry": {"coordinates":[7.766667,51.583333],"type":"Point"}
}