{
  "id": 2101171,
  "type": "Feature",
  "properties": {
    "tgn:hierarchy":[
        "tgn:2101171",
        "tgn:1000001",
        "tgn:7012149",
        "tgn:7022544",
        "tgn:7007825",
        "tgn:7029392"
    ],
    "tgn:id":2101171,
    "tgn:name":"Ramer",
    "tgn:placetype":[
        "aat:300008347"
    ]
},
  "bbox": [],
  "geometry": {"coordinates":[-88.6167,35.0667],"type":"Point"}
}