{
  "id": 1076707,
  "type": "Feature",
  "properties": {
    "tgn:hierarchy":[
        "tgn:1076707",
        "tgn:1000004",
        "tgn:7000198",
        "tgn:1001977",
        "tgn:7029392"
    ],
    "tgn:id":1076707,
    "tgn:name:en":"R\u0101n\u012bganj",
    "tgn:placetype":[
        "aat:300008347"
    ]
},
  "bbox": [],
  "geometry": {"coordinates":[87.130606,23.616397],"type":"Point"}
}