{
  "id": 7433448,
  "type": "Feature",
  "properties": {
    "tgn:hierarchy":[
        "tgn:7433448",
        "tgn:7005587",
        "tgn:1000001",
        "tgn:7005560",
        "tgn:7029392"
    ],
    "tgn:id":7433448,
    "tgn:name":"Tultengo",
    "tgn:placetype":[
        "aat:300008347"
    ]
},
  "bbox": [],
  "geometry": {"coordinates":[-98.45,19.833333],"type":"Point"}
}