{
  "id": 2730958,
  "type": "Feature",
  "properties": {
    "tgn:hierarchy":[
        "tgn:2730958",
        "tgn:1000001",
        "tgn:7012149",
        "tgn:2001029",
        "tgn:7007521",
        "tgn:7029392"
    ],
    "tgn:id":2730958,
    "tgn:name":"Tubby Lake",
    "tgn:placetype":[
        "aat:300008680"
    ]
},
  "bbox": [],
  "geometry": {"coordinates":[-93.4667,47.5667],"type":"Point"}
}