{
  "id": 7322169,
  "type": "Feature",
  "properties": {
    "tgn:hierarchy":[
        "tgn:7322169",
        "tgn:1001630",
        "tgn:1000049",
        "tgn:1000002",
        "tgn:7029392"
    ],
    "tgn:id":7322169,
    "tgn:name":"Caja Grande, Arrecife",
    "tgn:placetype":[
        "aat:300008808"
    ]
},
  "bbox": [],
  "geometry": {"coordinates":[-71.016667,-27.316667],"type":"Point"}
}