{
  "id": 2618316,
  "type": "Feature",
  "properties": {
    "tgn:hierarchy":[
        "tgn:2618316",
        "tgn:1000001",
        "tgn:7006451",
        "tgn:2000092",
        "tgn:7012149",
        "tgn:7029392"
    ],
    "tgn:id":2618316,
    "tgn:name":"Riggs Spring",
    "tgn:placetype":[
        "aat:300008697"
    ]
},
  "bbox": [],
  "geometry": {"coordinates":[-112.3167,36.55],"type":"Point"}
}