{
  "id": 2219850,
  "type": "Feature",
  "properties": {
    "tgn:hierarchy":[
        "tgn:2219850",
        "tgn:1000001",
        "tgn:7012149",
        "tgn:7007157",
        "tgn:2000186",
        "tgn:7029392"
    ],
    "tgn:id":2219850,
    "tgn:name":"Cantrall Mill",
    "tgn:placetype":[
        "aat:300008347"
    ]
},
  "bbox": [],
  "geometry": {"coordinates":[-120.3167,41.3167],"type":"Point"}
}