<<<<<<< HEAD
{
  "id": 2760060,
  "type": "Feature",
  "properties": {
    "tgn:hierarchy":[
        "tgn:2760060",
        "tgn:7006450",
        "tgn:1000001",
        "tgn:7012149",
        "tgn:2000086",
        "tgn:7029392"
    ],
    "tgn:id":2760060,
    "tgn:name":"West Fork Olsen Bay Creek",
    "tgn:placetype":[
        "aat:300008706"
    ]
},
  "bbox": [],
  "geometry": {"coordinates":[-146.1833,60.7833],"type":"Point"}
}
=======
{"geometry":{"type":"Point","coordinates":[-146.183300,60.783300]},"type":"Feature","properties":{"hierarchy":["tgn:2760060","tgn:7006450","tgn:1000001","tgn:7012149","tgn:2000086","tgn:7029392"],"placetype":["aat:300008706"],"id":2760060,"name:xx":"West Fork Olsen Bay Creek"}}
>>>>>>> 03f74aca74312dbeaf24d7e61306dd6a786dc3d0
