{
  "id": 2295886,
  "type": "Feature",
  "properties": {
    "tgn:hierarchy":[
        "tgn:2295886",
        "tgn:1000001",
        "tgn:7012149",
        "tgn:2001455",
        "tgn:7007566",
        "tgn:7029392"
    ],
    "tgn:id":2295886,
    "tgn:name":"Drummond Canyon",
    "tgn:placetype":[
        "aat:300008761"
    ]
},
  "bbox": [],
  "geometry": {"coordinates":[-107.75,32.8833],"type":"Point"}
}