{
  "id": 7586001,
  "type": "Feature",
  "properties": {
    "tgn:hierarchy":[
        "tgn:7586001",
        "tgn:1000004",
        "tgn:7000198",
        "tgn:7000799",
        "tgn:7029392"
    ],
    "tgn:id":7586001,
    "tgn:name:en":"Ben\u0101w\u0101s Kol",
    "tgn:placetype":[
        "aat:300008699"
    ]
},
  "bbox": [],
  "geometry": {"coordinates":[74.815278,34.3125],"type":"Point"}
}