<<<<<<< HEAD
{
  "id": 7477516,
  "type": "Feature",
  "properties": {
    "tgn:hierarchy":[
        "tgn:7477516",
        "tgn:7001010",
        "tgn:1000004",
        "tgn:1000141",
        "tgn:7029392"
    ],
    "tgn:id":7477516,
    "tgn:name":"Fengming Yihao Qiao",
    "tgn:placetype":[
        "aat:300007836"
    ]
},
  "bbox": [],
  "geometry": {"coordinates":[121.441757,23.75547],"type":"Point"}
}
=======
{"geometry":{"type":"Point","coordinates":[121.441757,23.755470]},"type":"Feature","properties":{"hierarchy":["tgn:7477516","tgn:7001010","tgn:1000004","tgn:1000141","tgn:7029392"],"placetype":["aat:300007836"],"id":7477516,"name:xx":"Fengming Yihao Qiao"}}
>>>>>>> 03f74aca74312dbeaf24d7e61306dd6a786dc3d0
