<<<<<<< HEAD
{
  "id": 7021004,
  "type": "Feature",
  "properties": {
    "tgn:hierarchy":[
        "tgn:7021004",
        "tgn:1000001",
        "tgn:7012149",
        "tgn:7029392"
    ],
    "tgn:id":7021004,
    "tgn:name":"Mississinewa River",
    "tgn:placetype":[
        "aat:300008707"
    ]
},
  "bbox": [],
  "geometry": {"coordinates":[-84.75,40.3167],"type":"Point"}
}
=======
{"geometry":{"type":"Point","coordinates":[-84.750000,40.316700]},"type":"Feature","properties":{"hierarchy":["tgn:7021004","tgn:1000001","tgn:7012149","tgn:7029392"],"placetype":["aat:300008707"],"id":7021004,"name:xx":"Mississinewa River"}}
>>>>>>> 03f74aca74312dbeaf24d7e61306dd6a786dc3d0
