{
  "id": 7021004,
  "type": "Feature",
  "properties": {
    "tgn:hierarchy":[
        "tgn:7021004",
        "tgn:1000001",
        "tgn:7012149",
        "tgn:7029392"
    ],
    "tgn:id":7021004,
    "tgn:name":"Mississinewa River",
    "tgn:placetype":[
        "aat:300008707"
    ]
},
  "bbox": [],
  "geometry": {"coordinates":[-84.75,40.3167],"type":"Point"}
}