{
  "id": 7219020,
  "type": "Feature",
  "properties": {
    "tgn:hierarchy":[
        "tgn:7219020",
        "tgn:7002680",
        "tgn:7001395",
        "tgn:1000003",
        "tgn:1000074",
        "tgn:7029392"
    ],
    "tgn:id":7219020,
    "tgn:name":"Akarnanik\u00e1 \u00d3ri",
    "tgn:placetype":[
        "aat:300008795"
    ]
},
  "bbox": [],
  "geometry": {"coordinates":[21.0575,38.550278],"type":"Point"}
}