{
  "id": 2518969,
  "type": "Feature",
  "properties": {
    "tgn:hierarchy":[
        "tgn:2518969",
        "tgn:7002659",
        "tgn:1000001",
        "tgn:7012149",
        "tgn:2000047",
        "tgn:7029392"
    ],
    "tgn:id":2518969,
    "tgn:name":"Mixon Chapel Cave",
    "tgn:placetype":[
        "aat:300008746"
    ]
},
  "bbox": [],
  "geometry": {"coordinates":[-86.3833,34.2167],"type":"Point"}
}