{
  "id": 2774120,
  "type": "Feature",
  "properties": {
    "tgn:hierarchy":[
        "tgn:2774120",
        "tgn:1000001",
        "tgn:7012149",
        "tgn:2002120",
        "tgn:7007827",
        "tgn:7029392"
    ],
    "tgn:id":2774120,
    "tgn:name":"Willow Creek",
    "tgn:placetype":[
        "aat:300008706"
    ]
},
  "bbox": [],
  "geometry": {"coordinates":[-111.3833,39.1167],"type":"Point"}
}