{
  "id": 7437765,
  "type": "Feature",
  "properties": {
    "tgn:hierarchy":[
        "tgn:7437765",
        "tgn:1000001",
        "tgn:1001893",
        "tgn:7005560",
        "tgn:7029392"
    ],
    "tgn:id":7437765,
    "tgn:name":"Teneyac",
    "tgn:placetype":[
        "aat:300008347"
    ]
},
  "bbox": [],
  "geometry": {"coordinates":[-100.15,19.083333],"type":"Point"}
}