{
  "id": 1052416,
  "type": "Feature",
  "properties": {
    "tgn:hierarchy":[
        "tgn:1052416",
        "tgn:7011438",
        "tgn:1000004",
        "tgn:7006646",
        "tgn:7029392"
    ],
    "tgn:id":1052416,
    "tgn:name":"Bagmanlyar",
    "tgn:placetype":[
        "aat:300008347"
    ]
},
  "bbox": [],
  "geometry": {"coordinates":[46.3167,40.65],"type":"Point"}
}