{
  "id": 2710570,
  "type": "Feature",
  "properties": {
    "tgn:hierarchy":[
        "tgn:2710570",
        "tgn:1000001",
        "tgn:2002245",
        "tgn:7012149",
        "tgn:7007920",
        "tgn:7029392"
    ],
    "tgn:id":2710570,
    "tgn:name":"Tamarack Spring",
    "tgn:placetype":[
        "aat:300008697"
    ]
},
  "bbox": [],
  "geometry": {"coordinates":[-117.5833,46.1833],"type":"Point"}
}