{
  "id": 7092466,
  "type": "Feature",
  "properties": {
    "tgn:hierarchy":[
        "tgn:7092466",
        "tgn:7003669",
        "tgn:1000003",
        "tgn:7000084",
        "tgn:7029392"
    ],
    "tgn:id":7092466,
    "tgn:name":"Vordereggelburg",
    "tgn:placetype":[
        "aat:300008347"
    ]
},
  "bbox": [],
  "geometry": {"coordinates":[11.933333,48.083333],"type":"Point"}
}