{
  "id": 7353958,
  "type": "Feature",
  "properties": {
    "tgn:hierarchy":[
        "tgn:7353958",
        "tgn:7005581",
        "tgn:1000001",
        "tgn:7005560",
        "tgn:7029392"
    ],
    "tgn:id":7353958,
    "tgn:name":"Rancho Casa Blanca",
    "tgn:placetype":[
        "aat:300000241"
    ]
},
  "bbox": [],
  "geometry": {"coordinates":[-106.933333,26.216667],"type":"Point"}
}