<<<<<<< HEAD
{
  "id": 7353958,
  "type": "Feature",
  "properties": {
    "tgn:hierarchy":[
        "tgn:7353958",
        "tgn:7005581",
        "tgn:1000001",
        "tgn:7005560",
        "tgn:7029392"
    ],
    "tgn:id":7353958,
    "tgn:name":"Rancho Casa Blanca",
    "tgn:placetype":[
        "aat:300000241"
    ]
},
  "bbox": [],
  "geometry": {"coordinates":[-106.933333,26.216667],"type":"Point"}
}
=======
{"geometry":{"type":"Point","coordinates":[-106.933333,26.216667]},"type":"Feature","properties":{"hierarchy":["tgn:7353958","tgn:7005581","tgn:1000001","tgn:7005560","tgn:7029392"],"placetype":["aat:300000241"],"id":7353958,"name:xx":"Rancho Casa Blanca"}}
>>>>>>> 03f74aca74312dbeaf24d7e61306dd6a786dc3d0
