{
  "id": 2246942,
  "type": "Feature",
  "properties": {
    "tgn:hierarchy":[
        "tgn:2246942",
        "tgn:1000001",
        "tgn:7012149",
        "tgn:2000333",
        "tgn:7007248",
        "tgn:7029392"
    ],
    "tgn:id":2246942,
    "tgn:name":"Cochrans Creek",
    "tgn:placetype":[
        "aat:300008706"
    ]
},
  "bbox": [],
  "geometry": {"coordinates":[-84.2167,34.5833],"type":"Point"}
}