{
  "id": 2334399,
  "type": "Feature",
  "properties": {
    "tgn:hierarchy":[
        "tgn:2334399",
        "tgn:1000001",
        "tgn:2001025",
        "tgn:7012149",
        "tgn:7007521",
        "tgn:7029392"
    ],
    "tgn:id":2334399,
    "tgn:name":"Forest Lake",
    "tgn:placetype":[
        "aat:300008680"
    ]
},
  "bbox": [],
  "geometry": {"coordinates":[-93.6167,44.95],"type":"Point"}
}