{
  "id": 2157435,
  "type": "Feature",
  "properties": {
    "tgn:hierarchy":[
        "tgn:2157435",
        "tgn:1000001",
        "tgn:7012149",
        "tgn:2001717",
        "tgn:7007708",
        "tgn:7029392"
    ],
    "tgn:id":2157435,
    "tgn:name":"Beaver Creek",
    "tgn:placetype":[
        "aat:300008706"
    ]
},
  "bbox": [],
  "geometry": {"coordinates":[-122.65,44.5667],"type":"Point"}
}