<<<<<<< HEAD
{
  "id": 7113419,
  "type": "Feature",
  "properties": {
    "tgn:hierarchy":[
        "tgn:7113419",
        "tgn:1000003",
        "tgn:7003678",
        "tgn:7000084",
        "tgn:7029392"
    ],
    "tgn:id":7113419,
    "tgn:name":"Rodenroth",
    "tgn:placetype":[
        "aat:300008347"
    ]
},
  "bbox": [],
  "geometry": {"coordinates":[8.25,50.6],"type":"Point"}
}
=======
{"geometry":{"type":"Point","coordinates":[8.250000,50.600000]},"type":"Feature","properties":{"hierarchy":["tgn:7113419","tgn:1000003","tgn:7003678","tgn:7000084","tgn:7029392"],"placetype":["aat:300008347"],"id":7113419,"name:xx":"Rodenroth"}}
>>>>>>> 03f74aca74312dbeaf24d7e61306dd6a786dc3d0
