{
  "id": 2229034,
  "type": "Feature",
  "properties": {
    "tgn:hierarchy":[
        "tgn:2229034",
        "tgn:1000001",
        "tgn:7012149",
        "tgn:1002986",
        "tgn:7007568",
        "tgn:7029392"
    ],
    "tgn:id":2229034,
    "tgn:name":"Cedar Island",
    "tgn:placetype":[
        "aat:300008791"
    ]
},
  "bbox": [],
  "geometry": {"coordinates":[-73.4667,43.75],"type":"Point"}
}