{
  "id": 7211431,
  "type": "Feature",
  "properties": {
    "tgn:hierarchy":[
        "tgn:7211431",
        "tgn:7003669",
        "tgn:1000003",
        "tgn:7000084",
        "tgn:7029392"
    ],
    "tgn:id":7211431,
    "tgn:name":"Baisweil",
    "tgn:placetype":[
        "aat:300008347"
    ]
},
  "bbox": [],
  "geometry": {"coordinates":[10.55,47.95],"type":"Point"}
}