{
  "id": 2740444,
  "type": "Feature",
  "properties": {
    "tgn:hierarchy":[
        "tgn:2740444",
        "tgn:1000001",
        "tgn:7012149",
        "tgn:2000930",
        "tgn:7007515",
        "tgn:7029392"
    ],
    "tgn:id":2740444,
    "tgn:name":"Upper Misery Pond",
    "tgn:placetype":[
        "aat:300008680"
    ]
},
  "bbox": [],
  "geometry": {"coordinates":[-69.95,45.5333],"type":"Point"}
}