{
  "id": 2557149,
  "type": "Feature",
  "properties": {
    "tgn:hierarchy":[
        "tgn:2557149",
        "tgn:1000001",
        "tgn:7012149",
        "tgn:2000797",
        "tgn:7007255",
        "tgn:7029392"
    ],
    "tgn:id":2557149,
    "tgn:name":"Old House Branch",
    "tgn:placetype":[
        "aat:300008699"
    ]
},
  "bbox": [],
  "geometry": {"coordinates":[-83.35,36.7167],"type":"Point"}
}