{
  "id": 2478892,
  "type": "Feature",
  "properties": {
    "tgn:hierarchy":[
        "tgn:2478892",
        "tgn:1000001",
        "tgn:7012149",
        "tgn:2001901",
        "tgn:7007825",
        "tgn:7029392"
    ],
    "tgn:id":2478892,
    "tgn:name":"Magazine Hollow",
    "tgn:placetype":[
        "aat:300008761"
    ]
},
  "bbox": [],
  "geometry": {"coordinates":[-84.3833,36.0667],"type":"Point"}
}