<<<<<<< HEAD
{
  "id": 2764631,
  "type": "Feature",
  "properties": {
    "tgn:hierarchy":[
        "tgn:2764631",
        "tgn:1000001",
        "tgn:7012149",
        "tgn:2000493",
        "tgn:7007250",
        "tgn:7029392"
    ],
    "tgn:id":2764631,
    "tgn:name":"Whir Spring",
    "tgn:placetype":[
        "aat:300008697"
    ]
},
  "bbox": [],
  "geometry": {"coordinates":[-114.3667,42.2],"type":"Point"}
}
=======
{"geometry":{"type":"Point","coordinates":[-114.366700,42.200000]},"type":"Feature","properties":{"hierarchy":["tgn:2764631","tgn:1000001","tgn:7012149","tgn:2000493","tgn:7007250","tgn:7029392"],"placetype":["aat:300008697"],"id":2764631,"name:xx":"Whir Spring"}}
>>>>>>> 03f74aca74312dbeaf24d7e61306dd6a786dc3d0
