{
  "id": 7286115,
  "type": "Feature",
  "properties": {
    "tgn:hierarchy":[
        "tgn:7286115",
        "tgn:7016598",
        "tgn:1000049",
        "tgn:1000002",
        "tgn:7029392"
    ],
    "tgn:id":7286115,
    "tgn:name":"Incaguasi, Cerro del",
    "tgn:placetype":[
        "aat:300008795"
    ]
},
  "bbox": [],
  "geometry": {"coordinates":[-69.383333,-25.516667],"type":"Point"}
}