{
  "id": 7523242,
  "type": "Feature",
  "properties": {
    "tgn:hierarchy":[
        "tgn:7523242",
        "tgn:7001242",
        "tgn:7016833",
        "tgn:7001336",
        "tgn:7029392"
    ],
    "tgn:id":7523242,
    "tgn:name:en":"Barq\u0101, Jabal al",
    "tgn:placetype":[
        "aat:300008795"
    ]
},
  "bbox": [],
  "geometry": {"coordinates":[34.534412,29.161155],"type":"Point"}
}