{
  "id": 2686168,
  "type": "Feature",
  "properties": {
    "tgn:hierarchy":[
        "tgn:2686168",
        "tgn:1000001",
        "tgn:7012149",
        "tgn:2001294",
        "tgn:7007524",
        "tgn:7029392"
    ],
    "tgn:id":2686168,
    "tgn:name":"Spring Coulee",
    "tgn:placetype":[
        "aat:300008761"
    ]
},
  "bbox": [],
  "geometry": {"coordinates":[-108.2167,47.5333],"type":"Point"}
}