{
  "id": 2641585,
  "type": "Feature",
  "properties": {
    "tgn:hierarchy":[
        "tgn:2641585",
        "tgn:1000001",
        "tgn:7012149",
        "tgn:1002545",
        "tgn:7007157",
        "tgn:7029392"
    ],
    "tgn:id":2641585,
    "tgn:name":"Sand Gulch",
    "tgn:placetype":[
        "aat:300008761"
    ]
},
  "bbox": [],
  "geometry": {"coordinates":[-117.75,35.4333],"type":"Point"}
}