{
  "id": 2724637,
  "type": "Feature",
  "properties": {
    "tgn:hierarchy":[
        "tgn:2724637",
        "tgn:1000001",
        "tgn:7012149",
        "tgn:2001456",
        "tgn:7007566",
        "tgn:7029392"
    ],
    "tgn:id":2724637,
    "tgn:name":"Tomasino Mill",
    "tgn:placetype":[
        "aat:300008347"
    ]
},
  "bbox": [],
  "geometry": {"coordinates":[-106.6667,34.25],"type":"Point"}
}