{
  "id": 7443059,
  "type": "Feature",
  "properties": {
    "tgn:hierarchy":[
        "tgn:7443059",
        "tgn:7002445",
        "tgn:7008116",
        "tgn:1000003",
        "tgn:7008591",
        "tgn:7029392"
    ],
    "tgn:id":7443059,
    "tgn:name:en":"Stannock, The",
    "tgn:placetype":[
        "aat:300387036"
    ]
},
  "bbox": [],
  "geometry": {"coordinates":[-5.55,50.056944],"type":"Point"}
}