{
  "id": 7252356,
  "type": "Feature",
  "properties": {
    "tgn:hierarchy":[
        "tgn:7252356",
        "tgn:7003456",
        "tgn:1000003",
        "tgn:1000063",
        "tgn:7018236",
        "tgn:7029392"
    ],
    "tgn:id":7252356,
    "tgn:name":"Molenbeek",
    "tgn:placetype":[
        "aat:300008699"
    ]
},
  "bbox": [],
  "geometry": {"coordinates":[4.25,51.05],"type":"Point"}
}