<<<<<<< HEAD
{
  "id": 7023093,
  "type": "Feature",
  "properties": {
    "tgn:hierarchy":[
        "tgn:7023093",
        "tgn:1000001",
        "tgn:7012149",
        "tgn:2001456",
        "tgn:7007566",
        "tgn:7029392"
    ],
    "tgn:id":7023093,
    "tgn:name":"Sawmill Spring",
    "tgn:placetype":[
        "aat:300008697"
    ]
},
  "bbox": [],
  "geometry": {"coordinates":[-107.15,33.9],"type":"Point"}
}
=======
{"geometry":{"type":"Point","coordinates":[-107.150000,33.900000]},"type":"Feature","properties":{"hierarchy":["tgn:7023093","tgn:1000001","tgn:7012149","tgn:2001456","tgn:7007566","tgn:7029392"],"placetype":["aat:300008697"],"id":7023093,"name:xx":"Sawmill Spring"}}
>>>>>>> 03f74aca74312dbeaf24d7e61306dd6a786dc3d0
