{
  "id": 1002193,
  "type": "Feature",
  "properties": {
    "tgn:hierarchy":[
        "tgn:1002193",
        "tgn:1000001",
        "tgn:7012149",
        "tgn:7007255",
        "tgn:7029392"
    ],
    "tgn:id":1002193,
    "tgn:name":"Bracken",
    "tgn:placetype":[
        "aat:300387145",
        "aat:300000771"
    ]
},
  "bbox": [],
  "geometry": {"coordinates":[-84.0833,38.6833],"type":"Point"}
}