{
  "id": 1046914,
  "type": "Feature",
  "properties": {
    "tgn:hierarchy":[
        "tgn:1046914",
        "tgn:7009084",
        "tgn:7003001",
        "tgn:1000003",
        "tgn:1000080",
        "tgn:7029392"
    ],
    "tgn:id":1046914,
    "tgn:name":"Silvi",
    "tgn:placetype":[
        "aat:300008347"
    ]
},
  "bbox": [],
  "geometry": {"coordinates":[14.083333,42.566667],"type":"Point"}
}