{
  "id": 1054587,
  "type": "Feature",
  "properties": {
    "tgn:hierarchy":[
        "tgn:1054587",
        "tgn:1000003",
        "tgn:1003410",
        "tgn:7006660",
        "tgn:7029392"
    ],
    "tgn:id":1054587,
    "tgn:name":"Yaroslavets'",
    "tgn:placetype":[
        "aat:300008347"
    ]
},
  "bbox": [],
  "geometry": {"coordinates":[33.6667,51.55],"type":"Point"}
}