{
  "id": 7034141,
  "type": "Feature",
  "properties": {
    "tgn:hierarchy":[
        "tgn:7034141",
        "tgn:1003468",
        "tgn:1000003",
        "tgn:7010380",
        "tgn:1000080",
        "tgn:7029392"
    ],
    "tgn:id":7034141,
    "tgn:name":"Masseria Mendole",
    "tgn:placetype":[
        "aat:300000206"
    ]
},
  "bbox": [],
  "geometry": {"coordinates":[18.153333,40.4375],"type":"Point"}
}