{
  "id": 2495930,
  "type": "Feature",
  "properties": {
    "tgn:hierarchy":[
        "tgn:2495930",
        "tgn:1000001",
        "tgn:7012149",
        "tgn:2001849",
        "tgn:7007825",
        "tgn:7029392"
    ],
    "tgn:id":2495930,
    "tgn:name":"Mason Springs",
    "tgn:placetype":[
        "aat:300008347"
    ]
},
  "bbox": [],
  "geometry": {"coordinates":[-83.5333,36.4833],"type":"Point"}
}