{
  "id": 7556309,
  "type": "Feature",
  "properties": {
    "tgn:hierarchy":[
        "tgn:7556309",
        "tgn:1000004",
        "tgn:7000198",
        "tgn:7016883",
        "tgn:7029392"
    ],
    "tgn:id":7556309,
    "tgn:name:en":"R\u0101jo M\u0101zra",
    "tgn:placetype":[
        "aat:300008347"
    ]
},
  "bbox": [],
  "geometry": {"coordinates":[75.797509,30.372423],"type":"Point"}
}