{
  "id": 7261502,
  "type": "Feature",
  "properties": {
    "tgn:hierarchy":[
        "tgn:7261502",
        "tgn:1000003",
        "tgn:7003635",
        "tgn:7016845",
        "tgn:7029392"
    ],
    "tgn:id":7261502,
    "tgn:name:nl":"Groot Vuilbaard",
    "tgn:placetype":[
        "aat:300387026"
    ]
},
  "bbox": [],
  "geometry": {"coordinates":[3.766667,51.616667],"type":"Point"}
}