{
  "id": 2432932,
  "type": "Feature",
  "properties": {
    "tgn:hierarchy":[
        "tgn:2432932",
        "tgn:1000001",
        "tgn:7012149",
        "tgn:2000520",
        "tgn:7007251",
        "tgn:7029392"
    ],
    "tgn:id":2432932,
    "tgn:name":"Keg Slough",
    "tgn:placetype":[
        "aat:300008699"
    ]
},
  "bbox": [],
  "geometry": {"coordinates":[-91.0333,41.1667],"type":"Point"}
}