{
  "id": 1104338,
  "type": "Feature",
  "properties": {
    "tgn:hierarchy":[
        "tgn:1104338",
        "tgn:7002445",
        "tgn:1000003",
        "tgn:7008117",
        "tgn:7008591",
        "tgn:7029392"
    ],
    "tgn:id":1104338,
    "tgn:name:en":"Cross Fell",
    "tgn:placetype":[
        "aat:300008795"
    ]
},
  "bbox": [],
  "geometry": {"coordinates":[-2.483333,54.716667],"type":"Point"}
}