<<<<<<< HEAD
{
  "id": 7370518,
  "type": "Feature",
  "properties": {
    "tgn:hierarchy":[
        "tgn:7370518",
        "tgn:1000001",
        "tgn:7005597",
        "tgn:7005560",
        "tgn:7029392"
    ],
    "tgn:id":7370518,
    "tgn:name":"Guayabas, Ca\u00f1\u00f3n de",
    "tgn:placetype":[
        "aat:300008763"
    ]
},
  "bbox": [],
  "geometry": {"coordinates":[-99.383333,24.05],"type":"Point"}
}
=======
{"geometry":{"type":"Point","coordinates":[-99.383333,24.050000]},"type":"Feature","properties":{"hierarchy":["tgn:7370518","tgn:1000001","tgn:7005597","tgn:7005560","tgn:7029392"],"placetype":["aat:300008763"],"id":7370518,"name:xx":"Guayabas, Ca\u00f1\u00f3n de"}}
>>>>>>> 03f74aca74312dbeaf24d7e61306dd6a786dc3d0
