{
  "id": 2276282,
  "type": "Feature",
  "properties": {
    "tgn:hierarchy":[
        "tgn:2276282",
        "tgn:1000001",
        "tgn:7012149",
        "tgn:2000647",
        "tgn:7007253",
        "tgn:7029392"
    ],
    "tgn:id":2276282,
    "tgn:name":"Daugherty Creek",
    "tgn:placetype":[
        "aat:300008706"
    ]
},
  "bbox": [],
  "geometry": {"coordinates":[-94.7333,40.6833],"type":"Point"}
}