{
  "id": 7283264,
  "type": "Feature",
  "properties": {
    "tgn:hierarchy":[
        "tgn:7283264",
        "tgn:1001637",
        "tgn:1000049",
        "tgn:1000002",
        "tgn:7029392"
    ],
    "tgn:id":7283264,
    "tgn:name":"Parra, Punta",
    "tgn:placetype":[
        "aat:300386846"
    ]
},
  "bbox": [],
  "geometry": {"coordinates":[-72.966667,-36.666667],"type":"Point"}
}