{
  "id": 2322595,
  "type": "Feature",
  "properties": {
    "tgn:hierarchy":[
        "tgn:2322595",
        "tgn:1000001",
        "tgn:7012149",
        "tgn:2001924",
        "tgn:7007825",
        "tgn:7029392"
    ],
    "tgn:id":2322595,
    "tgn:name":"Falls Creek Falls Lake",
    "tgn:placetype":[
        "aat:300006191"
    ]
},
  "bbox": [],
  "geometry": {"coordinates":[-85.35,35.65],"type":"Point"}
}