{
  "id": 7460663,
  "type": "Feature",
  "properties": {
    "tgn:hierarchy":[
        "tgn:7460663",
        "tgn:7002444",
        "tgn:1000003",
        "tgn:7029508",
        "tgn:7008591",
        "tgn:7029392"
    ],
    "tgn:id":7460663,
    "tgn:name:en":"Holm of Copister",
    "tgn:placetype":[
        "aat:300008804"
    ]
},
  "bbox": [],
  "geometry": {"coordinates":[-1.15,60.483333],"type":"Point"}
}