{
  "id": 2280041,
  "type": "Feature",
  "properties": {
    "tgn:hierarchy":[
        "tgn:2280041",
        "tgn:1000001",
        "tgn:7012149",
        "tgn:2000809",
        "tgn:7007255",
        "tgn:7029392"
    ],
    "tgn:id":2280041,
    "tgn:name":"Deans Branch",
    "tgn:placetype":[
        "aat:300008699"
    ]
},
  "bbox": [],
  "geometry": {"coordinates":[-82.8667,38.0667],"type":"Point"}
}