<<<<<<< HEAD
{
  "id": 2765662,
  "type": "Feature",
  "properties": {
    "tgn:hierarchy":[
        "tgn:2765662",
        "tgn:1000001",
        "tgn:7012149",
        "tgn:7007158",
        "tgn:7029392"
    ],
    "tgn:id":2765662,
    "tgn:name":"White Creek",
    "tgn:placetype":[
        "aat:300008706"
    ]
},
  "bbox": [],
  "geometry": {"coordinates":[-105.0667,38.1],"type":"Point"}
}
=======
{"geometry":{"type":"Point","coordinates":[-105.066700,38.100000]},"type":"Feature","properties":{"hierarchy":["tgn:2765662","tgn:1000001","tgn:7012149","tgn:7007158","tgn:7029392"],"placetype":["aat:300008706"],"id":2765662,"name:xx":"White Creek"}}
>>>>>>> 03f74aca74312dbeaf24d7e61306dd6a786dc3d0
