{
  "id": 7415234,
  "type": "Feature",
  "properties": {
    "tgn:hierarchy":[
        "tgn:7415234",
        "tgn:1000001",
        "tgn:7005591",
        "tgn:7005560",
        "tgn:7029392"
    ],
    "tgn:id":7415234,
    "tgn:name:es":"Cuajinicuil",
    "tgn:placetype":[
        "aat:300008347"
    ]
},
  "bbox": [],
  "geometry": {"coordinates":[-96.281111,15.8975],"type":"Point"}
}