{
  "id": 7225945,
  "type": "Feature",
  "properties": {
    "tgn:hierarchy":[
        "tgn:7225945",
        "tgn:7011167",
        "tgn:7001338",
        "tgn:1000003",
        "tgn:1000074",
        "tgn:7029392"
    ],
    "tgn:id":7225945,
    "tgn:name":"Perakh\u00f3rion",
    "tgn:placetype":[
        "aat:300008347"
    ]
},
  "bbox": [],
  "geometry": {"coordinates":[20.716667,38.35],"type":"Point"}
}