{
  "id": 2453489,
  "type": "Feature",
  "properties": {
    "tgn:hierarchy":[
        "tgn:2453489",
        "tgn:1000001",
        "tgn:7012149",
        "tgn:2000476",
        "tgn:7007250",
        "tgn:7029392"
    ],
    "tgn:id":2453489,
    "tgn:name":"Little Clearwater River",
    "tgn:placetype":[
        "aat:300008707"
    ]
},
  "bbox": [],
  "geometry": {"coordinates":[-114.9333,45.75],"type":"Point"}
}