{
  "id": 2787063,
  "type": "Feature",
  "properties": {
    "tgn:hierarchy":[
        "tgn:2787063",
        "tgn:1000001",
        "tgn:7012149",
        "tgn:1002611",
        "tgn:7007706",
        "tgn:7029392"
    ],
    "tgn:id":2787063,
    "tgn:name":"Zink Ditch",
    "tgn:placetype":[
        "aat:300006075"
    ]
},
  "bbox": [],
  "geometry": {"coordinates":[-83.7167,41.65],"type":"Point"}
}