<<<<<<< HEAD
{
  "id": 2155799,
  "type": "Feature",
  "properties": {
    "tgn:hierarchy":[
        "tgn:2155799",
        "tgn:2000090",
        "tgn:1000001",
        "tgn:7006451",
        "tgn:7012149",
        "tgn:7029392"
    ],
    "tgn:id":2155799,
    "tgn:name":"Bear Tak",
    "tgn:placetype":[
        "aat:300006191"
    ]
},
  "bbox": [],
  "geometry": {"coordinates":[-109.65,34.1333],"type":"Point"}
}
=======
{"geometry":{"type":"Point","coordinates":[-109.650000,34.133300]},"type":"Feature","properties":{"hierarchy":["tgn:2155799","tgn:2000090","tgn:1000001","tgn:7006451","tgn:7012149","tgn:7029392"],"placetype":["aat:300006191"],"id":2155799,"name:xx":"Bear Tak"}}
>>>>>>> 03f74aca74312dbeaf24d7e61306dd6a786dc3d0
