{
  "id": 2434263,
  "type": "Feature",
  "properties": {
    "tgn:hierarchy":[
        "tgn:2434263",
        "tgn:7006450",
        "tgn:1000001",
        "tgn:2124012",
        "tgn:7012149",
        "tgn:7029392"
    ],
    "tgn:id":2434263,
    "tgn:name":"Kempff Bay",
    "tgn:placetype":[
        "aat:300132316"
    ]
},
  "bbox": [],
  "geometry": {"coordinates":[-154.2167,56.9167],"type":"Point"}
}