{
  "id": 7512283,
  "type": "Feature",
  "properties": {
    "tgn:hierarchy":[
        "tgn:7512283",
        "tgn:1009227",
        "tgn:1000226",
        "tgn:7016729",
        "tgn:1000006",
        "tgn:7029392"
    ],
    "tgn:id":7512283,
    "tgn:name:en":"Impey, Mount",
    "tgn:placetype":[
        "aat:300008795"
    ]
},
  "bbox": [],
  "geometry": {"coordinates":[173.266667,-41.733333],"type":"Point"}
}