{
  "id": 7289316,
  "type": "Feature",
  "properties": {
    "tgn:hierarchy":[
        "tgn:7289316",
        "tgn:1001699",
        "tgn:1000049",
        "tgn:1000002",
        "tgn:7029392"
    ],
    "tgn:id":7289316,
    "tgn:name":"Ingl\u00e9s, Puerto",
    "tgn:placetype":[
        "aat:300132316"
    ]
},
  "bbox": [],
  "geometry": {"coordinates":[-73.899167,-41.799722],"type":"Point"}
}