{
  "id": 2305148,
  "type": "Feature",
  "properties": {
    "tgn:hierarchy":[
        "tgn:2305148",
        "tgn:1000001",
        "tgn:7012149",
        "tgn:7007568",
        "tgn:7029392"
    ],
    "tgn:id":2305148,
    "tgn:name":"East Branch Owego Creek",
    "tgn:placetype":[
        "aat:300008706"
    ]
},
  "bbox": [],
  "geometry": {"coordinates":[-76.1167,42.4333],"type":"Point"}
}