{
  "id": 2221493,
  "type": "Feature",
  "properties": {
    "tgn:hierarchy":[
        "tgn:2221493",
        "tgn:1000001",
        "tgn:7012149",
        "tgn:1002553",
        "tgn:7007920",
        "tgn:7029392"
    ],
    "tgn:id":2221493,
    "tgn:name":"Caribou Creek",
    "tgn:placetype":[
        "aat:300008706"
    ]
},
  "bbox": [],
  "geometry": {"coordinates":[-120.2667,47.1667],"type":"Point"}
}