{
  "id": 2363969,
  "type": "Feature",
  "properties": {
    "tgn:hierarchy":[
        "tgn:2363969",
        "tgn:1000001",
        "tgn:1002601",
        "tgn:7012149",
        "tgn:7007159",
        "tgn:7029392"
    ],
    "tgn:id":2363969,
    "tgn:name":"Green Mountain",
    "tgn:placetype":[
        "aat:300008798"
    ]
},
  "bbox": [],
  "geometry": {"coordinates":[-73.35,41.85],"type":"Point"}
}