{
  "id": 2146282,
  "type": "Feature",
  "properties": {
    "tgn:hierarchy":[
        "tgn:2146282",
        "tgn:1000001",
        "tgn:7012149",
        "tgn:2001898",
        "tgn:7007825",
        "tgn:7029392"
    ],
    "tgn:id":2146282,
    "tgn:name":"Ballplay Creek",
    "tgn:placetype":[
        "aat:300008706"
    ]
},
  "bbox": [],
  "geometry": {"coordinates":[-84.1167,35.4167],"type":"Point"}
}