{
  "id": 7056546,
  "type": "Feature",
  "properties": {
    "tgn:hierarchy":[
        "tgn:7056546",
        "tgn:7003007",
        "tgn:1000003",
        "tgn:7002997",
        "tgn:1000080",
        "tgn:7029392"
    ],
    "tgn:id":7056546,
    "tgn:name":"Biaza",
    "tgn:placetype":[
        "aat:300008347"
    ]
},
  "bbox": [],
  "geometry": {"coordinates":[10.733333,45.683333],"type":"Point"}
}