{
  "id": 2111438,
  "type": "Feature",
  "properties": {
    "tgn:hierarchy":[
        "tgn:2111438",
        "tgn:1000001",
        "tgn:7012149",
        "tgn:2002186",
        "tgn:7007919",
        "tgn:7029392"
    ],
    "tgn:id":2111438,
    "tgn:name":"Davis",
    "tgn:placetype":[
        "aat:300008347",
        "aat:300387210"
    ]
},
  "bbox": [],
  "geometry": {"coordinates":[-79.25,37.9167],"type":"Point"}
}