{
  "id": 7132321,
  "type": "Feature",
  "properties": {
    "tgn:hierarchy":[
        "tgn:7132321",
        "tgn:7000096",
        "tgn:1000003",
        "tgn:7000084",
        "tgn:7029392"
    ],
    "tgn:id":7132321,
    "tgn:name":"Menkiner See",
    "tgn:placetype":[
        "aat:300008680"
    ]
},
  "bbox": [],
  "geometry": {"coordinates":[14.216667,53.416667],"type":"Point"}
}