{
  "id": 1016739,
  "type": "Feature",
  "properties": {
    "tgn:hierarchy":[
        "tgn:1016739",
        "tgn:7005510",
        "tgn:1000001",
        "tgn:7005502",
        "tgn:7029392"
    ],
    "tgn:id":1016739,
    "tgn:name":"Hinche",
    "tgn:placetype":[
        "aat:300008347",
        "aat:300387225",
        "aat:300008375"
    ]
},
  "bbox": [],
  "geometry": {"coordinates":[-72.0167,19.15],"type":"Point"}
}