{
  "id": 7493587,
  "type": "Feature",
  "properties": {
    "tgn:hierarchy":[
        "tgn:7493587",
        "tgn:7001010",
        "tgn:1000004",
        "tgn:1000141",
        "tgn:7029392"
    ],
    "tgn:id":7493587,
    "tgn:name":"Dongzhu Guoxiao",
    "tgn:placetype":[
        "aat:300006495"
    ]
},
  "bbox": [],
  "geometry": {"coordinates":[121.27978,23.213784],"type":"Point"}
}