<<<<<<< HEAD
{
  "id": 7357238,
  "type": "Feature",
  "properties": {
    "tgn:hierarchy":[
        "tgn:7357238",
        "tgn:1000001",
        "tgn:7005591",
        "tgn:7005560",
        "tgn:7029392"
    ],
    "tgn:id":7357238,
    "tgn:name":"El Carrizo",
    "tgn:placetype":[
        "aat:300008347"
    ]
},
  "bbox": [],
  "geometry": {"coordinates":[-98.029167,16.25],"type":"Point"}
}
=======
{"geometry":{"type":"Point","coordinates":[-98.029167,16.250000]},"type":"Feature","properties":{"hierarchy":["tgn:7357238","tgn:1000001","tgn:7005591","tgn:7005560","tgn:7029392"],"placetype":["aat:300008347"],"id":7357238,"name:xx":"El Carrizo"}}
>>>>>>> 03f74aca74312dbeaf24d7e61306dd6a786dc3d0
