<<<<<<< HEAD
{
  "id": 7366578,
  "type": "Feature",
  "properties": {
    "tgn:hierarchy":[
        "tgn:7366578",
        "tgn:1000001",
        "tgn:7005599",
        "tgn:7005560",
        "tgn:7029392"
    ],
    "tgn:id":7366578,
    "tgn:name":"El Rinc\u00f3n",
    "tgn:placetype":[
        "aat:300008347"
    ]
},
  "bbox": [],
  "geometry": {"coordinates":[-94.766667,17.8],"type":"Point"}
}
=======
{"geometry":{"type":"Point","coordinates":[-94.766667,17.800000]},"type":"Feature","properties":{"hierarchy":["tgn:7366578","tgn:1000001","tgn:7005599","tgn:7005560","tgn:7029392"],"placetype":["aat:300008347"],"id":7366578,"name:xx":"El Rinc\u00f3n"}}
>>>>>>> 03f74aca74312dbeaf24d7e61306dd6a786dc3d0
