{
  "id": 2005529,
  "type": "Feature",
  "properties": {
    "tgn:hierarchy":[
        "tgn:2005529",
        "tgn:7002659",
        "tgn:1000001",
        "tgn:7012149",
        "tgn:2000044",
        "tgn:7029392"
    ],
    "tgn:id":2005529,
    "tgn:name":"Triana",
    "tgn:placetype":[
        "aat:300008347"
    ]
},
  "bbox": [],
  "geometry": {"coordinates":[-86.7333,34.5833],"type":"Point"}
}