{
  "id": 2170573,
  "type": "Feature",
  "properties": {
    "tgn:hierarchy":[
        "tgn:2170573",
        "tgn:1000001",
        "tgn:7012149",
        "tgn:2002174",
        "tgn:7007919",
        "tgn:7029392"
    ],
    "tgn:id":2170573,
    "tgn:name":"Big Run",
    "tgn:placetype":[
        "aat:300008699"
    ]
},
  "bbox": [],
  "geometry": {"coordinates":[-80.4833,37.2167],"type":"Point"}
}