{
  "id": 2205282,
  "type": "Feature",
  "properties": {
    "tgn:hierarchy":[
        "tgn:2205282",
        "tgn:1000001",
        "tgn:1002359",
        "tgn:7012149",
        "tgn:7007517",
        "tgn:7029392"
    ],
    "tgn:id":2205282,
    "tgn:name":"Bull Brook",
    "tgn:placetype":[
        "aat:300008699"
    ]
},
  "bbox": [],
  "geometry": {"coordinates":[-70.8833,42.6667],"type":"Point"}
}