{
  "id": 2361482,
  "type": "Feature",
  "properties": {
    "tgn:hierarchy":[
        "tgn:2361482",
        "tgn:1000001",
        "tgn:7013942",
        "tgn:7012149",
        "tgn:7007517",
        "tgn:7029392"
    ],
    "tgn:id":2361482,
    "tgn:name":"Graves Brook",
    "tgn:placetype":[
        "aat:300008699"
    ]
},
  "bbox": [],
  "geometry": {"coordinates":[-72.5833,42.5667],"type":"Point"}
}