{
  "id": 2660712,
  "type": "Feature",
  "properties": {
    "tgn:hierarchy":[
        "tgn:2660712",
        "tgn:1000001",
        "tgn:7012149",
        "tgn:2000829",
        "tgn:7007255",
        "tgn:7029392"
    ],
    "tgn:id":2660712,
    "tgn:name":"Shop Hollow",
    "tgn:placetype":[
        "aat:300008761"
    ]
},
  "bbox": [],
  "geometry": {"coordinates":[-85.6167,36.8167],"type":"Point"}
}