<<<<<<< HEAD
{
  "id": 2768637,
  "type": "Feature",
  "properties": {
    "tgn:hierarchy":[
        "tgn:2768637",
        "tgn:1000001",
        "tgn:7012149",
        "tgn:2001709",
        "tgn:7007708",
        "tgn:7029392"
    ],
    "tgn:id":2768637,
    "tgn:name":"Whiting Spring",
    "tgn:placetype":[
        "aat:300008697"
    ]
},
  "bbox": [],
  "geometry": {"coordinates":[-119.05,43.8],"type":"Point"}
}
=======
{"geometry":{"type":"Point","coordinates":[-119.050000,43.800000]},"type":"Feature","properties":{"hierarchy":["tgn:2768637","tgn:1000001","tgn:7012149","tgn:2001709","tgn:7007708","tgn:7029392"],"placetype":["aat:300008697"],"id":2768637,"name:xx":"Whiting Spring"}}
>>>>>>> 03f74aca74312dbeaf24d7e61306dd6a786dc3d0
