{
  "id": 2355817,
  "type": "Feature",
  "properties": {
    "tgn:hierarchy":[
        "tgn:2355817",
        "tgn:1000001",
        "tgn:7012149",
        "tgn:2001045",
        "tgn:7007521",
        "tgn:7029392"
    ],
    "tgn:id":2355817,
    "tgn:name":"Goose Lake",
    "tgn:placetype":[
        "aat:300008680"
    ]
},
  "bbox": [],
  "geometry": {"coordinates":[-94.5833,44.9833],"type":"Point"}
}