<<<<<<< HEAD
{
  "id": 2256603,
  "type": "Feature",
  "properties": {
    "tgn:hierarchy":[
        "tgn:2256603",
        "tgn:1000001",
        "tgn:7012149",
        "tgn:2002129",
        "tgn:7007827",
        "tgn:7029392"
    ],
    "tgn:id":2256603,
    "tgn:name":"Corcys",
    "tgn:placetype":[
        "aat:300008347"
    ]
},
  "bbox": [],
  "geometry": {"coordinates":[-111.95,41.2167],"type":"Point"}
}
=======
{"geometry":{"type":"Point","coordinates":[-111.950000,41.216700]},"type":"Feature","properties":{"hierarchy":["tgn:2256603","tgn:1000001","tgn:7012149","tgn:2002129","tgn:7007827","tgn:7029392"],"placetype":["aat:300008347"],"id":2256603,"name:xx":"Corcys"}}
>>>>>>> 03f74aca74312dbeaf24d7e61306dd6a786dc3d0
