{
  "id": 2190932,
  "type": "Feature",
  "properties": {
    "tgn:hierarchy":[
        "tgn:2190932",
        "tgn:1000001",
        "tgn:2001596",
        "tgn:7012149",
        "tgn:7007705",
        "tgn:7029392"
    ],
    "tgn:id":2190932,
    "tgn:name":"Boyd Lake",
    "tgn:placetype":[
        "aat:300008680"
    ]
},
  "bbox": [],
  "geometry": {"coordinates":[-99.8167,48.9667],"type":"Point"}
}