{
  "id": 2524106,
  "type": "Feature",
  "properties": {
    "tgn:hierarchy":[
        "tgn:2524106",
        "tgn:1000001",
        "tgn:7012149",
        "tgn:7007157",
        "tgn:1002956",
        "tgn:7029392"
    ],
    "tgn:id":2524106,
    "tgn:name":"Morgan Canyon",
    "tgn:placetype":[
        "aat:300008761"
    ]
},
  "bbox": [],
  "geometry": {"coordinates":[-119.0667,36.55],"type":"Point"}
}