{
  "id": 7380421,
  "type": "Feature",
  "properties": {
    "tgn:hierarchy":[
        "tgn:7380421",
        "tgn:7005581",
        "tgn:1000001",
        "tgn:7005560",
        "tgn:7029392"
    ],
    "tgn:id":7380421,
    "tgn:name":"Matasaguas, Sierra",
    "tgn:placetype":[
        "aat:300008795"
    ]
},
  "bbox": [],
  "geometry": {"coordinates":[-104.583333,29.283333],"type":"Point"}
}