<<<<<<< HEAD
{
  "id": 7470183,
  "type": "Feature",
  "properties": {
    "tgn:hierarchy":[
        "tgn:7470183",
        "tgn:1000004",
        "tgn:7489179",
        "tgn:1000141",
        "tgn:7029392"
    ],
    "tgn:id":7470183,
    "tgn:name":"Xiatong Shan",
    "tgn:placetype":[
        "aat:300008795"
    ]
},
  "bbox": [],
  "geometry": {"coordinates":[121.68519,24.501739],"type":"Point"}
}
=======
{"geometry":{"type":"Point","coordinates":[121.685190,24.501739]},"type":"Feature","properties":{"hierarchy":["tgn:7470183","tgn:1000004","tgn:7489179","tgn:1000141","tgn:7029392"],"placetype":["aat:300008795"],"id":7470183,"name:xx":"Xiatong Shan"}}
>>>>>>> 03f74aca74312dbeaf24d7e61306dd6a786dc3d0
