{
  "id": 7470183,
  "type": "Feature",
  "properties": {
    "tgn:hierarchy":[
        "tgn:7470183",
        "tgn:1000004",
        "tgn:7489179",
        "tgn:1000141",
        "tgn:7029392"
    ],
    "tgn:id":7470183,
    "tgn:name":"Xiatong Shan",
    "tgn:placetype":[
        "aat:300008795"
    ]
},
  "bbox": [],
  "geometry": {"coordinates":[121.68519,24.501739],"type":"Point"}
}