{
  "id": 2561197,
  "type": "Feature",
  "properties": {
    "tgn:hierarchy":[
        "tgn:2561197",
        "tgn:1000001",
        "tgn:1002270",
        "tgn:7012149",
        "tgn:7007708",
        "tgn:7029392"
    ],
    "tgn:id":2561197,
    "tgn:name":"Orville",
    "tgn:placetype":[
        "aat:300008347"
    ]
},
  "bbox": [],
  "geometry": {"coordinates":[-122.7167,45.1333],"type":"Point"}
}