{
  "id": 7364187,
  "type": "Feature",
  "properties": {
    "tgn:hierarchy":[
        "tgn:7364187",
        "tgn:1000001",
        "tgn:7005599",
        "tgn:7005560",
        "tgn:7029392"
    ],
    "tgn:id":7364187,
    "tgn:name":"El Clar\u00edn",
    "tgn:placetype":[
        "aat:300008347"
    ]
},
  "bbox": [],
  "geometry": {"coordinates":[-98.216667,21.75],"type":"Point"}
}