{
  "id": 2382671,
  "type": "Feature",
  "properties": {
    "tgn:hierarchy":[
        "tgn:2382671",
        "tgn:1000001",
        "tgn:7012149",
        "tgn:7007248",
        "tgn:7029392"
    ],
    "tgn:id":2382671,
    "tgn:name":"Haywood Valley",
    "tgn:placetype":[
        "aat:300008761"
    ]
},
  "bbox": [],
  "geometry": {"coordinates":[-85.15,34.5833],"type":"Point"}
}