{
  "id": 7368053,
  "type": "Feature",
  "properties": {
    "tgn:hierarchy":[
        "tgn:7368053",
        "tgn:1000001",
        "tgn:7005597",
        "tgn:7005560",
        "tgn:7029392"
    ],
    "tgn:id":7368053,
    "tgn:name":"Grande, Sierra",
    "tgn:placetype":[
        "aat:300266640"
    ]
},
  "bbox": [],
  "geometry": {"coordinates":[-99.25,23.533333],"type":"Point"}
}