{
  "id": 7538115,
  "type": "Feature",
  "properties": {
    "tgn:hierarchy":[
        "tgn:7538115",
        "tgn:7001242",
        "tgn:7001311",
        "tgn:7016833",
        "tgn:7029392"
    ],
    "tgn:id":7538115,
    "tgn:name:en":"Sh\u00eeb, W\u00e2di",
    "tgn:placetype":[
        "aat:300379998"
    ]
},
  "bbox": [],
  "geometry": {"coordinates":[35.294736,23.668563],"type":"Point"}
}