{
  "id": 2188644,
  "type": "Feature",
  "properties": {
    "tgn:hierarchy":[
        "tgn:2188644",
        "tgn:1000001",
        "tgn:7012149",
        "tgn:2001902",
        "tgn:7007825",
        "tgn:7029392"
    ],
    "tgn:id":2188644,
    "tgn:name":"Botts Lake",
    "tgn:placetype":[
        "aat:300006191"
    ]
},
  "bbox": [],
  "geometry": {"coordinates":[-89.0667,36.35],"type":"Point"}
}