{
  "id": 7559073,
  "type": "Feature",
  "properties": {
    "tgn:hierarchy":[
        "tgn:7559073",
        "tgn:1000004",
        "tgn:7000198",
        "tgn:7016883",
        "tgn:7029392"
    ],
    "tgn:id":7559073,
    "tgn:name:en":"Sardulgarh",
    "tgn:placetype":[
        "aat:300008347"
    ]
},
  "bbox": [],
  "geometry": {"coordinates":[75.236082,29.692242],"type":"Point"}
}