<<<<<<< HEAD
{
  "id": 2250053,
  "type": "Feature",
  "properties": {
    "tgn:hierarchy":[
        "tgn:2250053",
        "tgn:1000001",
        "tgn:1002284",
        "tgn:7012149",
        "tgn:7007568",
        "tgn:7029392"
    ],
    "tgn:id":2250053,
    "tgn:name":"Collins Brook",
    "tgn:placetype":[
        "aat:300008699"
    ]
},
  "bbox": [],
  "geometry": {"coordinates":[-74.0667,44.9333],"type":"Point"}
}
=======
{"geometry":{"type":"Point","coordinates":[-74.066700,44.933300]},"type":"Feature","properties":{"hierarchy":["tgn:2250053","tgn:1000001","tgn:1002284","tgn:7012149","tgn:7007568","tgn:7029392"],"placetype":["aat:300008699"],"id":2250053,"name:xx":"Collins Brook"}}
>>>>>>> 03f74aca74312dbeaf24d7e61306dd6a786dc3d0
