{
  "id": 2136247,
  "type": "Feature",
  "properties": {
    "tgn:hierarchy":[
        "tgn:2136247",
        "tgn:1000001",
        "tgn:7012149",
        "tgn:1003038",
        "tgn:7007517",
        "tgn:7029392"
    ],
    "tgn:id":2136247,
    "tgn:name":"Ararat, Mount",
    "tgn:placetype":[
        "aat:300008798"
    ]
},
  "bbox": [],
  "geometry": {"coordinates":[-71.7833,42.1667],"type":"Point"}
}