{
  "id": 2347759,
  "type": "Feature",
  "properties": {
    "tgn:hierarchy":[
        "tgn:2347759",
        "tgn:1000001",
        "tgn:1002324",
        "tgn:7012149",
        "tgn:7007252",
        "tgn:7029392"
    ],
    "tgn:id":2347759,
    "tgn:name":"Georgetown Ridge",
    "tgn:placetype":[
        "aat:300266640"
    ]
},
  "bbox": [],
  "geometry": {"coordinates":[-84.85,39.1333],"type":"Point"}
}