{
  "id": 2610966,
  "type": "Feature",
  "properties": {
    "tgn:hierarchy":[
        "tgn:2610966",
        "tgn:1000001",
        "tgn:2001419",
        "tgn:7012149",
        "tgn:7007526",
        "tgn:7029392"
    ],
    "tgn:id":2610966,
    "tgn:name":"Red Hill",
    "tgn:placetype":[
        "aat:300008798"
    ]
},
  "bbox": [],
  "geometry": {"coordinates":[-117.9333,40.0667],"type":"Point"}
}