<<<<<<< HEAD
{
  "id": 7365681,
  "type": "Feature",
  "properties": {
    "tgn:hierarchy":[
        "tgn:7365681",
        "tgn:7005579",
        "tgn:1000001",
        "tgn:7005560",
        "tgn:7029392"
    ],
    "tgn:id":7365681,
    "tgn:name":"El Refugio",
    "tgn:placetype":[
        "aat:300008347"
    ]
},
  "bbox": [],
  "geometry": {"coordinates":[-102.25,21.85],"type":"Point"}
}
=======
{"geometry":{"type":"Point","coordinates":[-102.250000,21.850000]},"type":"Feature","properties":{"hierarchy":["tgn:7365681","tgn:7005579","tgn:1000001","tgn:7005560","tgn:7029392"],"placetype":["aat:300008347"],"id":7365681,"name:xx":"El Refugio"}}
>>>>>>> 03f74aca74312dbeaf24d7e61306dd6a786dc3d0
