{
  "id": 2121891,
  "type": "Feature",
  "properties": {
    "tgn:hierarchy":[
        "tgn:2121891",
        "tgn:1000001",
        "tgn:2002318",
        "tgn:7012149",
        "tgn:7007922",
        "tgn:7029392"
    ],
    "tgn:id":2121891,
    "tgn:name":"Moose Junction",
    "tgn:placetype":[
        "aat:300008347",
        "aat:300387210"
    ]
},
  "bbox": [],
  "geometry": {"coordinates":[-92.15,46.2833],"type":"Point"}
}