{
  "id": 7421579,
  "type": "Feature",
  "properties": {
    "tgn:hierarchy":[
        "tgn:7421579",
        "tgn:1000001",
        "tgn:1001960",
        "tgn:7005560",
        "tgn:7029392"
    ],
    "tgn:id":7421579,
    "tgn:name":"Santa Felicita, Cerro",
    "tgn:placetype":[
        "aat:300008795"
    ]
},
  "bbox": [],
  "geometry": {"coordinates":[-112.151389,30.924444],"type":"Point"}
}