{
  "id": 2622252,
  "type": "Feature",
  "properties": {
    "tgn:hierarchy":[
        "tgn:2622252",
        "tgn:1000001",
        "tgn:7012149",
        "tgn:2000894",
        "tgn:7007256",
        "tgn:7029392"
    ],
    "tgn:id":2622252,
    "tgn:name":"Robertson Branch",
    "tgn:placetype":[
        "aat:300008699"
    ]
},
  "bbox": [],
  "geometry": {"coordinates":[-93.1833,31.9667],"type":"Point"}
}