<<<<<<< HEAD
{
  "id": 2762020,
  "type": "Feature",
  "properties": {
    "tgn:hierarchy":[
        "tgn:2762020",
        "tgn:1000001",
        "tgn:7012149",
        "tgn:2000927",
        "tgn:7007515",
        "tgn:7029392"
    ],
    "tgn:id":2762020,
    "tgn:name":"West Sawtelle Pond",
    "tgn:placetype":[
        "aat:300008680"
    ]
},
  "bbox": [],
  "geometry": {"coordinates":[-68.75,46.2667],"type":"Point"}
}
=======
{"geometry":{"type":"Point","coordinates":[-68.750000,46.266700]},"type":"Feature","properties":{"hierarchy":["tgn:2762020","tgn:1000001","tgn:7012149","tgn:2000927","tgn:7007515","tgn:7029392"],"placetype":["aat:300008680"],"id":2762020,"name:xx":"West Sawtelle Pond"}}
>>>>>>> 03f74aca74312dbeaf24d7e61306dd6a786dc3d0
