{
  "id": 7169026,
  "type": "Feature",
  "properties": {
    "tgn:hierarchy":[
        "tgn:7169026",
        "tgn:7003692",
        "tgn:1000003",
        "tgn:7000084",
        "tgn:7029392"
    ],
    "tgn:id":7169026,
    "tgn:name":"Harmensbach",
    "tgn:placetype":[
        "aat:300387200"
    ]
},
  "bbox": [],
  "geometry": {"coordinates":[8.016667,48.233333],"type":"Point"}
}