{
  "id": 7386393,
  "type": "Feature",
  "properties": {
    "tgn:hierarchy":[
        "tgn:7386393",
        "tgn:1001853",
        "tgn:1000001",
        "tgn:7005560",
        "tgn:7029392"
    ],
    "tgn:id":7386393,
    "tgn:name":"Rancher\u00eda",
    "tgn:placetype":[
        "aat:300008347"
    ]
},
  "bbox": [],
  "geometry": {"coordinates":[-100.816667,28.35],"type":"Point"}
}