{
  "id": 7539903,
  "type": "Feature",
  "properties": {
    "tgn:hierarchy":[
        "tgn:7539903",
        "tgn:7001242",
        "tgn:7016833",
        "tgn:1001113",
        "tgn:7029392"
    ],
    "tgn:id":7539903,
    "tgn:name:en":"Samm\u0101k\u012bn al Gharb",
    "tgn:placetype":[
        "aat:300008347"
    ]
},
  "bbox": [],
  "geometry": {"coordinates":[31.886276,30.827359],"type":"Point"}
}