<<<<<<< HEAD
{
  "id": 2331105,
  "type": "Feature",
  "properties": {
    "tgn:hierarchy":[
        "tgn:2331105",
        "tgn:1000001",
        "tgn:7012149",
        "tgn:2002021",
        "tgn:7007826",
        "tgn:7029392"
    ],
    "tgn:id":2331105,
    "tgn:name":"Flat Tank",
    "tgn:placetype":[
        "aat:300006191"
    ]
},
  "bbox": [],
  "geometry": {"coordinates":[-100.4667,29.1],"type":"Point"}
}
=======
{"geometry":{"type":"Point","coordinates":[-100.466700,29.100000]},"type":"Feature","properties":{"hierarchy":["tgn:2331105","tgn:1000001","tgn:7012149","tgn:2002021","tgn:7007826","tgn:7029392"],"placetype":["aat:300006191"],"id":2331105,"name:xx":"Flat Tank"}}
>>>>>>> 03f74aca74312dbeaf24d7e61306dd6a786dc3d0
