{
  "id": 2034319,
  "type": "Feature",
  "properties": {
    "tgn:hierarchy":[
        "tgn:2034319",
        "tgn:1000001",
        "tgn:2000591",
        "tgn:7012149",
        "tgn:7007253",
        "tgn:7029392"
    ],
    "tgn:id":2034319,
    "tgn:name":"Balltown",
    "tgn:placetype":[
        "aat:300008347"
    ]
},
  "bbox": [],
  "geometry": {"coordinates":[-90.8667,42.6333],"type":"Point"}
}