<<<<<<< HEAD
{
  "id": 2332199,
  "type": "Feature",
  "properties": {
    "tgn:hierarchy":[
        "tgn:2332199",
        "tgn:1000001",
        "tgn:1002480",
        "tgn:7012149",
        "tgn:7007564",
        "tgn:7029392"
    ],
    "tgn:id":2332199,
    "tgn:name":"Flints Hill",
    "tgn:placetype":[
        "aat:300008798"
    ]
},
  "bbox": [],
  "geometry": {"coordinates":[-71.55,42.7333],"type":"Point"}
}
=======
{"geometry":{"type":"Point","coordinates":[-71.550000,42.733300]},"type":"Feature","properties":{"hierarchy":["tgn:2332199","tgn:1000001","tgn:1002480","tgn:7012149","tgn:7007564","tgn:7029392"],"placetype":["aat:300008798"],"id":2332199,"name:xx":"Flints Hill"}}
>>>>>>> 03f74aca74312dbeaf24d7e61306dd6a786dc3d0
