{
  "id": 2312734,
  "type": "Feature",
  "properties": {
    "tgn:hierarchy":[
        "tgn:2312734",
        "tgn:1000001",
        "tgn:7012149",
        "tgn:2001458",
        "tgn:7007566",
        "tgn:7029392"
    ],
    "tgn:id":2312734,
    "tgn:name":"El Gato",
    "tgn:placetype":[
        "aat:300008347"
    ]
},
  "bbox": [],
  "geometry": {"coordinates":[-106.2833,34.6167],"type":"Point"}
}