{
  "id": 2467604,
  "type": "Feature",
  "properties": {
    "tgn:hierarchy":[
        "tgn:2467604",
        "tgn:1000001",
        "tgn:7012149",
        "tgn:2002382",
        "tgn:7007923",
        "tgn:7029392"
    ],
    "tgn:id":2467604,
    "tgn:name":"Long Hollow",
    "tgn:placetype":[
        "aat:300008761"
    ]
},
  "bbox": [],
  "geometry": {"coordinates":[-110.45,42.3667],"type":"Point"}
}