<<<<<<< HEAD
{
  "id": 2404473,
  "type": "Feature",
  "properties": {
    "tgn:hierarchy":[
        "tgn:2404473",
        "tgn:1000001",
        "tgn:1002195",
        "tgn:7012149",
        "tgn:7007520",
        "tgn:7029392"
    ],
    "tgn:id":2404473,
    "tgn:name":"Hubbard Lake",
    "tgn:placetype":[
        "aat:300008680"
    ]
},
  "bbox": [],
  "geometry": {"coordinates":[-85.0167,42.0333],"type":"Point"}
}
=======
{"geometry":{"type":"Point","coordinates":[-85.016700,42.033300]},"type":"Feature","properties":{"hierarchy":["tgn:2404473","tgn:1000001","tgn:1002195","tgn:7012149","tgn:7007520","tgn:7029392"],"placetype":["aat:300008680"],"id":2404473,"name:xx":"Hubbard Lake"}}
>>>>>>> 03f74aca74312dbeaf24d7e61306dd6a786dc3d0
