{
  "id": 2707201,
  "type": "Feature",
  "properties": {
    "tgn:hierarchy":[
        "tgn:2707201",
        "tgn:1000001",
        "tgn:2000467",
        "tgn:7012149",
        "tgn:7007250",
        "tgn:7029392"
    ],
    "tgn:id":2707201,
    "tgn:name":"Swede Spring",
    "tgn:placetype":[
        "aat:300008697"
    ]
},
  "bbox": [],
  "geometry": {"coordinates":[-114.0833,42.0833],"type":"Point"}
}