{
  "id": 7289001,
  "type": "Feature",
  "properties": {
    "tgn:hierarchy":[
        "tgn:7289001",
        "tgn:1001768",
        "tgn:1000049",
        "tgn:1000002",
        "tgn:7029392"
    ],
    "tgn:id":7289001,
    "tgn:name":"La Bosta, Quebrada de",
    "tgn:placetype":[
        "aat:300008699"
    ]
},
  "bbox": [],
  "geometry": {"coordinates":[-70.333333,-32.716667],"type":"Point"}
}