{
  "id": 2179121,
  "type": "Feature",
  "properties": {
    "tgn:hierarchy":[
        "tgn:2179121",
        "tgn:1000001",
        "tgn:2001412",
        "tgn:7012149",
        "tgn:7007526",
        "tgn:7029392"
    ],
    "tgn:id":2179121,
    "tgn:name":"Blair Lodes",
    "tgn:placetype":[
        "aat:300000390"
    ]
},
  "bbox": [],
  "geometry": {"coordinates":[-117.6833,37.7833],"type":"Point"}
}