{
  "id": 2675081,
  "type": "Feature",
  "properties": {
    "tgn:hierarchy":[
        "tgn:2675081",
        "tgn:7002659",
        "tgn:1000001",
        "tgn:7012149",
        "tgn:2000047",
        "tgn:7029392"
    ],
    "tgn:id":2675081,
    "tgn:name":"Soda Top",
    "tgn:placetype":[
        "aat:300008798"
    ]
},
  "bbox": [],
  "geometry": {"coordinates":[-86.2833,34.5333],"type":"Point"}
}