{
  "id": 7419181,
  "type": "Feature",
  "properties": {
    "tgn:hierarchy":[
        "tgn:7419181",
        "tgn:1000001",
        "tgn:7005589",
        "tgn:7005560",
        "tgn:7029392"
    ],
    "tgn:id":7419181,
    "tgn:name:es":"San Francisco de Z\u00fa\u00f1iga",
    "tgn:placetype":[
        "aat:300008347"
    ]
},
  "bbox": [],
  "geometry": {"coordinates":[-100.406111,23.38],"type":"Point"}
}