<<<<<<< HEAD
{
  "id": 7248666,
  "type": "Feature",
  "properties": {
    "tgn:hierarchy":[
        "tgn:7248666",
        "tgn:7003458",
        "tgn:1000003",
        "tgn:1000063",
        "tgn:7018236",
        "tgn:7029392"
    ],
    "tgn:id":7248666,
    "tgn:name":"Blauwsteenput",
    "tgn:placetype":[
        "aat:300000206"
    ]
},
  "bbox": [],
  "geometry": {"coordinates":[2.9,51.1],"type":"Point"}
}
=======
{"geometry":{"type":"Point","coordinates":[2.900000,51.100000]},"type":"Feature","properties":{"hierarchy":["tgn:7248666","tgn:7003458","tgn:1000003","tgn:1000063","tgn:7018236","tgn:7029392"],"placetype":["aat:300000206"],"id":7248666,"name:xx":"Blauwsteenput"}}
>>>>>>> 03f74aca74312dbeaf24d7e61306dd6a786dc3d0
