{
  "id": 2266080,
  "type": "Feature",
  "properties": {
    "tgn:hierarchy":[
        "tgn:2266080",
        "tgn:1000001",
        "tgn:7012149",
        "tgn:1003042",
        "tgn:7007920",
        "tgn:7029392"
    ],
    "tgn:id":2266080,
    "tgn:name":"Crawford Creek",
    "tgn:placetype":[
        "aat:300008706"
    ]
},
  "bbox": [],
  "geometry": {"coordinates":[-121.4167,46.2167],"type":"Point"}
}