{
  "id": 7573269,
  "type": "Feature",
  "properties": {
    "tgn:hierarchy":[
        "tgn:7573269",
        "tgn:1000004",
        "tgn:1001869",
        "tgn:7000198",
        "tgn:7029392"
    ],
    "tgn:id":7573269,
    "tgn:name:en":"Far\u0101di",
    "tgn:placetype":[
        "aat:300008347"
    ]
},
  "bbox": [],
  "geometry": {"coordinates":[69.516667,22.95],"type":"Point"}
}