{
  "id": 2211056,
  "type": "Feature",
  "properties": {
    "tgn:hierarchy":[
        "tgn:2211056",
        "tgn:1000001",
        "tgn:2001596",
        "tgn:7012149",
        "tgn:7007705",
        "tgn:7029392"
    ],
    "tgn:id":2211056,
    "tgn:name":"Butler Lake",
    "tgn:placetype":[
        "aat:300008680"
    ]
},
  "bbox": [],
  "geometry": {"coordinates":[-100.05,48.8833],"type":"Point"}
}