{
  "id": 7268337,
  "type": "Feature",
  "properties": {
    "tgn:concordances":{
        "gn:id":"2748008"
    },
    "tgn:hierarchy":[
        "tgn:7268337",
        "tgn:1000003",
        "tgn:7003632",
        "tgn:7016845",
        "tgn:7029392"
    ],
    "tgn:id":7268337,
    "tgn:name:nl":"Roeleveen",
    "tgn:placetype":[
        "aat:300008347"
    ]
},
  "bbox": [],
  "geometry": {"coordinates":[4.416667,52.066667],"type":"Point"}
}