{
  "id": 7293189,
  "type": "Feature",
  "properties": {
    "tgn:hierarchy":[
        "tgn:7293189",
        "tgn:1001702",
        "tgn:1000049",
        "tgn:1000002",
        "tgn:7029392"
    ],
    "tgn:id":7293189,
    "tgn:name":"Puerto Espora",
    "tgn:placetype":[
        "aat:300386968"
    ]
},
  "bbox": [],
  "geometry": {"coordinates":[-69.466667,-52.466667],"type":"Point"}
}