{
  "id": 7536312,
  "type": "Feature",
  "properties": {
    "tgn:hierarchy":[
        "tgn:7536312",
        "tgn:7001242",
        "tgn:7016833",
        "tgn:1001123",
        "tgn:7029392"
    ],
    "tgn:id":7536312,
    "tgn:name":"Ghurrah, B\u016bgh\u0101z al",
    "tgn:placetype":[
        "aat:300008713"
    ]
},
  "bbox": [],
  "geometry": {"coordinates":[32.140655,31.24532],"type":"Point"}
}