{
  "id": 2219497,
  "type": "Feature",
  "properties": {
    "tgn:hierarchy":[
        "tgn:2219497",
        "tgn:1000001",
        "tgn:1002328",
        "tgn:7012149",
        "tgn:7007568",
        "tgn:7029392"
    ],
    "tgn:id":2219497,
    "tgn:name":"Cannonsville Reservoir",
    "tgn:placetype":[
        "aat:300006191"
    ]
},
  "bbox": [],
  "geometry": {"coordinates":[-75.3667,42.0667],"type":"Point"}
}