{
  "id": 7538939,
  "type": "Feature",
  "properties": {
    "tgn:hierarchy":[
        "tgn:7538939",
        "tgn:7001242",
        "tgn:7016833",
        "tgn:7001336",
        "tgn:7029392"
    ],
    "tgn:id":7538939,
    "tgn:name:en":"Sab\u012bl, Ra's as",
    "tgn:placetype":[
        "aat:300386846"
    ]
},
  "bbox": [],
  "geometry": {"coordinates":[33.712281,28.069039],"type":"Point"}
}