{
  "id": 7493754,
  "type": "Feature",
  "properties": {
    "tgn:hierarchy":[
        "tgn:7493754",
        "tgn:1000004",
        "tgn:7491221",
        "tgn:1000141",
        "tgn:7029392"
    ],
    "tgn:id":7493754,
    "tgn:name":"Duwei Shan",
    "tgn:placetype":[
        "aat:300008798"
    ]
},
  "bbox": [],
  "geometry": {"coordinates":[121.373752,23.204396],"type":"Point"}
}