<<<<<<< HEAD
{
  "id": 7056593,
  "type": "Feature",
  "properties": {
    "tgn:hierarchy":[
        "tgn:7056593",
        "tgn:1003429",
        "tgn:1000003",
        "tgn:7003240",
        "tgn:1000080",
        "tgn:7029392"
    ],
    "tgn:id":7056593,
    "tgn:name":"Betelico, Torrente",
    "tgn:placetype":[
        "aat:300008699"
    ]
},
  "bbox": [],
  "geometry": {"coordinates":[13.566667,43.483333],"type":"Point"}
}
=======
{"geometry":{"type":"Point","coordinates":[13.566667,43.483333]},"type":"Feature","properties":{"hierarchy":["tgn:7056593","tgn:1003429","tgn:1000003","tgn:7003240","tgn:1000080","tgn:7029392"],"placetype":["aat:300008699"],"id":7056593,"name:xx":"Betelico, Torrente"}}
>>>>>>> 03f74aca74312dbeaf24d7e61306dd6a786dc3d0
