{
  "id": 2483437,
  "type": "Feature",
  "properties": {
    "tgn:hierarchy":[
        "tgn:2483437",
        "tgn:1000001",
        "tgn:7012149",
        "tgn:2002374",
        "tgn:7007923",
        "tgn:7029392"
    ],
    "tgn:id":2483437,
    "tgn:name":"Last Chance Draw",
    "tgn:placetype":[
        "aat:300008761"
    ]
},
  "bbox": [],
  "geometry": {"coordinates":[-106.5833,44.1833],"type":"Point"}
}