{
  "id": 2644711,
  "type": "Feature",
  "properties": {
    "tgn:hierarchy":[
        "tgn:2644711",
        "tgn:1000001",
        "tgn:7012149",
        "tgn:2000533",
        "tgn:7007251",
        "tgn:7029392"
    ],
    "tgn:id":2644711,
    "tgn:name":"Sargent Slough",
    "tgn:placetype":[
        "aat:300008699"
    ]
},
  "bbox": [],
  "geometry": {"coordinates":[-89.2833,40.5333],"type":"Point"}
}