{
  "id": 2124637,
  "type": "Feature",
  "properties": {
    "tgn:hierarchy":[
        "tgn:2124637",
        "tgn:1000001",
        "tgn:7012149",
        "tgn:2000927",
        "tgn:7007515",
        "tgn:7029392"
    ],
    "tgn:id":2124637,
    "tgn:name":"Abbott Hill",
    "tgn:placetype":[
        "aat:300008798"
    ]
},
  "bbox": [],
  "geometry": {"coordinates":[-69.1167,44.8167],"type":"Point"}
}