{
  "id": 7283054,
  "type": "Feature",
  "properties": {
    "tgn:hierarchy":[
        "tgn:7283054",
        "tgn:1001702",
        "tgn:1000049",
        "tgn:1000002",
        "tgn:7029392"
    ],
    "tgn:id":7283054,
    "tgn:name":"Pato, Isla",
    "tgn:placetype":[
        "aat:300008791"
    ]
},
  "bbox": [],
  "geometry": {"coordinates":[-73.566667,-52.383333],"type":"Point"}
}