<<<<<<< HEAD
{
  "id": 2768966,
  "type": "Feature",
  "properties": {
    "tgn:hierarchy":[
        "tgn:2768966",
        "tgn:1000001",
        "tgn:7012149",
        "tgn:2001275",
        "tgn:7007524",
        "tgn:7029392"
    ],
    "tgn:id":2768966,
    "tgn:name":"Whits Lakes",
    "tgn:placetype":[
        "aat:300008680"
    ]
},
  "bbox": [],
  "geometry": {"coordinates":[-111.1333,44.8167],"type":"Point"}
}
=======
{"geometry":{"type":"Point","coordinates":[-111.133300,44.816700]},"type":"Feature","properties":{"hierarchy":["tgn:2768966","tgn:1000001","tgn:7012149","tgn:2001275","tgn:7007524","tgn:7029392"],"placetype":["aat:300008680"],"id":2768966,"name:xx":"Whits Lakes"}}
>>>>>>> 03f74aca74312dbeaf24d7e61306dd6a786dc3d0
