<<<<<<< HEAD
{
  "id": 2158245,
  "type": "Feature",
  "properties": {
    "tgn:hierarchy":[
        "tgn:2158245",
        "tgn:1000001",
        "tgn:1002194",
        "tgn:7012149",
        "tgn:7007710",
        "tgn:7029392"
    ],
    "tgn:id":2158245,
    "tgn:name":"Beaver Run",
    "tgn:placetype":[
        "aat:300008699"
    ]
},
  "bbox": [],
  "geometry": {"coordinates":[-76.4667,41.5667],"type":"Point"}
}
=======
{"geometry":{"type":"Point","coordinates":[-76.466700,41.566700]},"type":"Feature","properties":{"hierarchy":["tgn:2158245","tgn:1000001","tgn:1002194","tgn:7012149","tgn:7007710","tgn:7029392"],"placetype":["aat:300008699"],"id":2158245,"name:xx":"Beaver Run"}}
>>>>>>> 03f74aca74312dbeaf24d7e61306dd6a786dc3d0
