<<<<<<< HEAD
{
  "id": 7179121,
  "type": "Feature",
  "properties": {
    "tgn:hierarchy":[
        "tgn:7179121",
        "tgn:1000003",
        "tgn:7000094",
        "tgn:7000084",
        "tgn:7029392"
    ],
    "tgn:id":7179121,
    "tgn:name":"Hammer",
    "tgn:placetype":[
        "aat:300008347"
    ]
},
  "bbox": [],
  "geometry": {"coordinates":[13.983333,53.6],"type":"Point"}
}
=======
{"geometry":{"type":"Point","coordinates":[13.983333,53.600000]},"type":"Feature","properties":{"hierarchy":["tgn:7179121","tgn:1000003","tgn:7000094","tgn:7000084","tgn:7029392"],"placetype":["aat:300008347"],"id":7179121,"name:xx":"Hammer"}}
>>>>>>> 03f74aca74312dbeaf24d7e61306dd6a786dc3d0
