{
  "id": 2774438,
  "type": "Feature",
  "properties": {
    "tgn:hierarchy":[
        "tgn:2774438",
        "tgn:1000001",
        "tgn:2001596",
        "tgn:7012149",
        "tgn:7007705",
        "tgn:7029392"
    ],
    "tgn:id":2774438,
    "tgn:name":"Willow Lake",
    "tgn:placetype":[
        "aat:300008680"
    ]
},
  "bbox": [],
  "geometry": {"coordinates":[-100.1333,48.9167],"type":"Point"}
}