{
  "id": 2138785,
  "type": "Feature",
  "properties": {
    "tgn:hierarchy":[
        "tgn:2138785",
        "tgn:1000001",
        "tgn:1002359",
        "tgn:7012149",
        "tgn:7007517",
        "tgn:7029392"
    ],
    "tgn:id":2138785,
    "tgn:name":"Ash Swamp",
    "tgn:placetype":[
        "aat:300008905"
    ]
},
  "bbox": [],
  "geometry": {"coordinates":[-70.9667,42.7667],"type":"Point"}
}