{
  "id": 2325965,
  "type": "Feature",
  "properties": {
    "tgn:hierarchy":[
        "tgn:2325965",
        "tgn:1000001",
        "tgn:2001262",
        "tgn:7012149",
        "tgn:7007524",
        "tgn:7029392"
    ],
    "tgn:id":2325965,
    "tgn:name":"Fifteenmile Creek",
    "tgn:placetype":[
        "aat:300008706"
    ]
},
  "bbox": [],
  "geometry": {"coordinates":[-108.8833,48.2833],"type":"Point"}
}