{
  "id": 7289289,
  "type": "Feature",
  "properties": {
    "tgn:hierarchy":[
        "tgn:7289289",
        "tgn:1001702",
        "tgn:1000049",
        "tgn:1000002",
        "tgn:7029392"
    ],
    "tgn:id":7289289,
    "tgn:name":"Intervine, Punta",
    "tgn:placetype":[
        "aat:300386846"
    ]
},
  "bbox": [],
  "geometry": {"coordinates":[-72.516667,-52.216667],"type":"Point"}
}