{
  "id": 2140945,
  "type": "Feature",
  "properties": {
    "tgn:hierarchy":[
        "tgn:2140945",
        "tgn:1000001",
        "tgn:7012149",
        "tgn:1003041",
        "tgn:7007710",
        "tgn:7029392"
    ],
    "tgn:id":2140945,
    "tgn:name":"Avery Hill",
    "tgn:placetype":[
        "aat:300008798"
    ]
},
  "bbox": [],
  "geometry": {"coordinates":[-75.9167,41.6333],"type":"Point"}
}