{
  "id": 7495239,
  "type": "Feature",
  "properties": {
    "tgn:hierarchy":[
        "tgn:7495239",
        "tgn:7468018",
        "tgn:1000004",
        "tgn:1000141",
        "tgn:7029392"
    ],
    "tgn:id":7495239,
    "tgn:name":"Jianshanpou",
    "tgn:placetype":[
        "aat:300008347"
    ]
},
  "bbox": [],
  "geometry": {"coordinates":[120.516069,23.400122],"type":"Point"}
}