{
  "id": 7566354,
  "type": "Feature",
  "properties": {
    "tgn:hierarchy":[
        "tgn:7566354",
        "tgn:1000004",
        "tgn:7000198",
        "tgn:1001894",
        "tgn:7029392"
    ],
    "tgn:id":7566354,
    "tgn:name:en":"Bar\u0101gaon",
    "tgn:placetype":[
        "aat:300008347"
    ]
},
  "bbox": [],
  "geometry": {"coordinates":[79.018517,24.568175],"type":"Point"}
}