{
  "id": 2394957,
  "type": "Feature",
  "properties": {
    "tgn:hierarchy":[
        "tgn:2394957",
        "tgn:1000001",
        "tgn:7012149",
        "tgn:2000288",
        "tgn:7007240",
        "tgn:7029392"
    ],
    "tgn:id":2394957,
    "tgn:name":"Holder Bay",
    "tgn:placetype":[
        "aat:300008905"
    ]
},
  "bbox": [],
  "geometry": {"coordinates":[-82.3833,30.15],"type":"Point"}
}