{
  "id": 7367006,
  "type": "Feature",
  "properties": {
    "tgn:hierarchy":[
        "tgn:7367006",
        "tgn:7005584",
        "tgn:1000001",
        "tgn:7005560",
        "tgn:7029392"
    ],
    "tgn:id":7367006,
    "tgn:name":"El Rosalito",
    "tgn:placetype":[
        "aat:300008347"
    ]
},
  "bbox": [],
  "geometry": {"coordinates":[-100.716667,21.25],"type":"Point"}
}