{
  "id": 1119248,
  "type": "Feature",
  "properties": {
    "tgn:hierarchy":[
        "tgn:1119248",
        "tgn:1000001",
        "tgn:1002724",
        "tgn:7012149",
        "tgn:7007517",
        "tgn:7029392"
    ],
    "tgn:id":1119248,
    "tgn:name":"Farm Pond",
    "tgn:placetype":[
        "aat:300008688"
    ]
},
  "bbox": [],
  "geometry": {"coordinates":[-71.3333,42.2333],"type":"Point"}
}