{
  "id": 1102620,
  "type": "Feature",
  "properties": {
    "tgn:hierarchy":[
        "tgn:1102620",
        "tgn:7005735",
        "tgn:7005685",
        "tgn:1000001",
        "tgn:7029392"
    ],
    "tgn:id":1102620,
    "tgn:name":"Skagit Valley Recreation Area",
    "tgn:placetype":[
        "aat:300008195"
    ]
},
  "bbox": [],
  "geometry": {"coordinates":[-121.1667,49.1167],"type":"Point"}
}