{
  "id": 2137107,
  "type": "Feature",
  "properties": {
    "tgn:hierarchy":[
        "tgn:2137107",
        "tgn:1000001",
        "tgn:7012149",
        "tgn:2000980",
        "tgn:7007520",
        "tgn:7029392"
    ],
    "tgn:id":2137107,
    "tgn:name":"Arlene",
    "tgn:placetype":[
        "aat:300008347"
    ]
},
  "bbox": [],
  "geometry": {"coordinates":[-85.2833,44.3833],"type":"Point"}
}