{
  "id": 2237759,
  "type": "Feature",
  "properties": {
    "tgn:hierarchy":[
        "tgn:2237759",
        "tgn:1000001",
        "tgn:7012149",
        "tgn:2001122",
        "tgn:7007522",
        "tgn:7029392"
    ],
    "tgn:id":2237759,
    "tgn:name":"Chinquapin Branch",
    "tgn:placetype":[
        "aat:300008699"
    ]
},
  "bbox": [],
  "geometry": {"coordinates":[-89.5333,31.05],"type":"Point"}
}