{
  "id": 2442053,
  "type": "Feature",
  "properties": {
    "tgn:hierarchy":[
        "tgn:2442053",
        "tgn:1000001",
        "tgn:7012149",
        "tgn:2002331",
        "tgn:7007922",
        "tgn:7029392"
    ],
    "tgn:id":2442053,
    "tgn:name":"Korn Coulee",
    "tgn:placetype":[
        "aat:300008761"
    ]
},
  "bbox": [],
  "geometry": {"coordinates":[-90.9167,43.7833],"type":"Point"}
}