{
  "id": 1056908,
  "type": "Feature",
  "properties": {
    "tgn:hierarchy":[
        "tgn:1056908",
        "tgn:1000004",
        "tgn:7011573",
        "tgn:7018214",
        "tgn:7002435",
        "tgn:7029392"
    ],
    "tgn:id":1056908,
    "tgn:name":"Medve\u017eji Oz'ora",
    "tgn:placetype":[
        "aat:300008347"
    ]
},
  "bbox": [],
  "geometry": {"coordinates":[37.9833,55.8667],"type":"Point"}
}