{
  "id": 2445824,
  "type": "Feature",
  "properties": {
    "tgn:hierarchy":[
        "tgn:2445824",
        "tgn:2000919",
        "tgn:1000001",
        "tgn:7012149",
        "tgn:7007515",
        "tgn:7029392"
    ],
    "tgn:id":2445824,
    "tgn:name":"Les Trois Island",
    "tgn:placetype":[
        "aat:300008791"
    ]
},
  "bbox": [],
  "geometry": {"coordinates":[-67.95,47.1833],"type":"Point"}
}