{
  "id": 7496039,
  "type": "Feature",
  "properties": {
    "tgn:hierarchy":[
        "tgn:7496039",
        "tgn:1000004",
        "tgn:7001009",
        "tgn:1000141",
        "tgn:7029392"
    ],
    "tgn:id":7496039,
    "tgn:name":"Guxi Qiao",
    "tgn:placetype":[
        "aat:300007836"
    ]
},
  "bbox": [],
  "geometry": {"coordinates":[120.828808,24.271868],"type":"Point"}
}