<<<<<<< HEAD
{
  "id": 7370041,
  "type": "Feature",
  "properties": {
    "tgn:hierarchy":[
        "tgn:7370041",
        "tgn:7005586",
        "tgn:1000001",
        "tgn:7005560",
        "tgn:7029392"
    ],
    "tgn:id":7370041,
    "tgn:name":"Jalolco",
    "tgn:placetype":[
        "aat:300008699"
    ]
},
  "bbox": [],
  "geometry": {"coordinates":[-104.066667,20.55],"type":"Point"}
}
=======
{"geometry":{"type":"Point","coordinates":[-104.066667,20.550000]},"type":"Feature","properties":{"hierarchy":["tgn:7370041","tgn:7005586","tgn:1000001","tgn:7005560","tgn:7029392"],"placetype":["aat:300008699"],"id":7370041,"name:xx":"Jalolco"}}
>>>>>>> 03f74aca74312dbeaf24d7e61306dd6a786dc3d0
