{
  "id": 7370041,
  "type": "Feature",
  "properties": {
    "tgn:hierarchy":[
        "tgn:7370041",
        "tgn:7005586",
        "tgn:1000001",
        "tgn:7005560",
        "tgn:7029392"
    ],
    "tgn:id":7370041,
    "tgn:name":"Jalolco",
    "tgn:placetype":[
        "aat:300008699"
    ]
},
  "bbox": [],
  "geometry": {"coordinates":[-104.066667,20.55],"type":"Point"}
}