{
  "id": 2667729,
  "type": "Feature",
  "properties": {
    "tgn:hierarchy":[
        "tgn:2667729",
        "tgn:1000001",
        "tgn:7012149",
        "tgn:2000818",
        "tgn:7007255",
        "tgn:7029392"
    ],
    "tgn:id":2667729,
    "tgn:name":"Skullbones Knob",
    "tgn:placetype":[
        "aat:300008798"
    ]
},
  "bbox": [],
  "geometry": {"coordinates":[-84.6333,36.7333],"type":"Point"}
}