<<<<<<< HEAD
{
  "id": 7379083,
  "type": "Feature",
  "properties": {
    "tgn:hierarchy":[
        "tgn:7379083",
        "tgn:1000001",
        "tgn:7005601",
        "tgn:7005560",
        "tgn:7029392"
    ],
    "tgn:id":7379083,
    "tgn:name":"Maravillas",
    "tgn:placetype":[
        "aat:300008347"
    ]
},
  "bbox": [],
  "geometry": {"coordinates":[-102.016667,22.4],"type":"Point"}
}
=======
{"geometry":{"type":"Point","coordinates":[-102.016667,22.400000]},"type":"Feature","properties":{"hierarchy":["tgn:7379083","tgn:1000001","tgn:7005601","tgn:7005560","tgn:7029392"],"placetype":["aat:300008347"],"id":7379083,"name:xx":"Maravillas"}}
>>>>>>> 03f74aca74312dbeaf24d7e61306dd6a786dc3d0
