{
  "id": 7508733,
  "type": "Feature",
  "properties": {
    "tgn:hierarchy":[
        "tgn:7508733",
        "tgn:1009227",
        "tgn:1000226",
        "tgn:1000006",
        "tgn:7016850",
        "tgn:7029392"
    ],
    "tgn:id":7508733,
    "tgn:name:en":"Otoko River",
    "tgn:placetype":[
        "aat:300008699"
    ]
},
  "bbox": [],
  "geometry": {"coordinates":[169.516667,-43.766667],"type":"Point"}
}