{
  "id": 2557917,
  "type": "Feature",
  "properties": {
    "tgn:hierarchy":[
        "tgn:2557917",
        "tgn:1000001",
        "tgn:7012149",
        "tgn:2000891",
        "tgn:7007256",
        "tgn:7029392"
    ],
    "tgn:id":2557917,
    "tgn:name":"Old Stump Lake",
    "tgn:placetype":[
        "aat:300132316"
    ]
},
  "bbox": [],
  "geometry": {"coordinates":[-89.3833,29.35],"type":"Point"}
}