{
  "id": 2174088,
  "type": "Feature",
  "properties": {
    "tgn:hierarchy":[
        "tgn:2174088",
        "tgn:1000001",
        "tgn:7012149",
        "tgn:7029392"
    ],
    "tgn:id":2174088,
    "tgn:name":"Birdie Gulch",
    "tgn:placetype":[
        "aat:300008761"
    ]
},
  "bbox": [],
  "geometry": {"coordinates":[-108.9167,40.9667],"type":"Point"}
}