{
  "id": 2484106,
  "type": "Feature",
  "properties": {
    "tgn:hierarchy":[
        "tgn:2484106",
        "tgn:1000001",
        "tgn:7012149",
        "tgn:7007157",
        "tgn:2000185",
        "tgn:7029392"
    ],
    "tgn:id":2484106,
    "tgn:name":"Laughlin Range",
    "tgn:placetype":[
        "aat:300008798"
    ]
},
  "bbox": [],
  "geometry": {"coordinates":[-123.2667,39.3167],"type":"Point"}
}