<<<<<<< HEAD
{
  "id": 2338428,
  "type": "Feature",
  "properties": {
    "tgn:hierarchy":[
        "tgn:2338428",
        "tgn:1000001",
        "tgn:2000273",
        "tgn:7012149",
        "tgn:7007240",
        "tgn:7029392"
    ],
    "tgn:id":2338428,
    "tgn:name":"Foxworth Mill Creek",
    "tgn:placetype":[
        "aat:300008706"
    ]
},
  "bbox": [],
  "geometry": {"coordinates":[-85.25,30.6167],"type":"Point"}
}
=======
{"geometry":{"type":"Point","coordinates":[-85.250000,30.616700]},"type":"Feature","properties":{"hierarchy":["tgn:2338428","tgn:1000001","tgn:2000273","tgn:7012149","tgn:7007240","tgn:7029392"],"placetype":["aat:300008706"],"id":2338428,"name:xx":"Foxworth Mill Creek"}}
>>>>>>> 03f74aca74312dbeaf24d7e61306dd6a786dc3d0
