{
  "id": 7467460,
  "type": "Feature",
  "properties": {
    "tgn:hierarchy":[
        "tgn:7467460",
        "tgn:1000004",
        "tgn:7467799",
        "tgn:1000141",
        "tgn:7029392"
    ],
    "tgn:id":7467460,
    "tgn:name":"Anxiliao",
    "tgn:placetype":[
        "aat:300008347"
    ]
},
  "bbox": [],
  "geometry": {"coordinates":[120.591314,24.070997],"type":"Point"}
}