{
  "id": 7235719,
  "type": "Feature",
  "properties": {
    "tgn:hierarchy":[
        "tgn:7235719",
        "tgn:7002706",
        "tgn:7002705",
        "tgn:1000003",
        "tgn:1000074",
        "tgn:7029392"
    ],
    "tgn:id":7235719,
    "tgn:name":"Ar\u00e1pissas, \u00d3rmos",
    "tgn:placetype":[
        "aat:300132316"
    ]
},
  "bbox": [],
  "geometry": {"coordinates":[21.066111,39.031111],"type":"Point"}
}