<<<<<<< HEAD
{
  "id": 2255649,
  "type": "Feature",
  "properties": {
    "tgn:hierarchy":[
        "tgn:2255649",
        "tgn:1000001",
        "tgn:7012149",
        "tgn:2000494",
        "tgn:7007250",
        "tgn:7029392"
    ],
    "tgn:id":2255649,
    "tgn:name":"Copet Creek",
    "tgn:placetype":[
        "aat:300008706"
    ]
},
  "bbox": [],
  "geometry": {"coordinates":[-116.0833,45.05],"type":"Point"}
}
=======
{"geometry":{"type":"Point","coordinates":[-116.083300,45.050000]},"type":"Feature","properties":{"hierarchy":["tgn:2255649","tgn:1000001","tgn:7012149","tgn:2000494","tgn:7007250","tgn:7029392"],"placetype":["aat:300008706"],"id":2255649,"name:xx":"Copet Creek"}}
>>>>>>> 03f74aca74312dbeaf24d7e61306dd6a786dc3d0
