{
  "id": 7590785,
  "type": "Feature",
  "properties": {
    "tgn:hierarchy":[
        "tgn:7590785",
        "tgn:1000004",
        "tgn:7000198",
        "tgn:7000799",
        "tgn:7029392"
    ],
    "tgn:id":7590785,
    "tgn:name:en":"Chandi\u0101n",
    "tgn:placetype":[
        "aat:300008347"
    ]
},
  "bbox": [],
  "geometry": {"coordinates":[74.733103,32.857988],"type":"Point"}
}