<<<<<<< HEAD
{
  "id": 2401579,
  "type": "Feature",
  "properties": {
    "tgn:hierarchy":[
        "tgn:2401579",
        "tgn:1000001",
        "tgn:7012149",
        "tgn:7007158",
        "tgn:2000250",
        "tgn:7029392"
    ],
    "tgn:id":2401579,
    "tgn:name":"Horseshoe Gulch",
    "tgn:placetype":[
        "aat:300008761"
    ]
},
  "bbox": [],
  "geometry": {"coordinates":[-105.9833,39.5333],"type":"Point"}
}
=======
{"geometry":{"type":"Point","coordinates":[-105.983300,39.533300]},"type":"Feature","properties":{"hierarchy":["tgn:2401579","tgn:1000001","tgn:7012149","tgn:7007158","tgn:2000250","tgn:7029392"],"placetype":["aat:300008761"],"id":2401579,"name:xx":"Horseshoe Gulch"}}
>>>>>>> 03f74aca74312dbeaf24d7e61306dd6a786dc3d0
