{
  "id": 7347944,
  "type": "Feature",
  "properties": {
    "tgn:hierarchy":[
        "tgn:7347944",
        "tgn:7002759",
        "tgn:7008909",
        "tgn:1000003",
        "tgn:1000095",
        "tgn:7029392"
    ],
    "tgn:id":7347944,
    "tgn:name":"Albalate de Cinca",
    "tgn:placetype":[
        "aat:300008347"
    ]
},
  "bbox": [],
  "geometry": {"coordinates":[0.145332,41.722393],"type":"Point"}
}