{
  "id": 2441817,
  "type": "Feature",
  "properties": {
    "tgn:hierarchy":[
        "tgn:2441817",
        "tgn:1002648",
        "tgn:1000001",
        "tgn:1007799",
        "tgn:7012149",
        "tgn:7007249",
        "tgn:7029392"
    ],
    "tgn:id":2441817,
    "tgn:name":"Kolokolo Cave",
    "tgn:placetype":[
        "aat:300008746"
    ]
},
  "bbox": [],
  "geometry": {"coordinates":[-156.9667,20.7333],"type":"Point"}
}