{
  "id": 2183029,
  "type": "Feature",
  "properties": {
    "tgn:hierarchy":[
        "tgn:2183029",
        "tgn:7006450",
        "tgn:1000001",
        "tgn:7012149",
        "tgn:2000089",
        "tgn:7029392"
    ],
    "tgn:id":2183029,
    "tgn:name":"Blueberry Ridge",
    "tgn:placetype":[
        "aat:300266640"
    ]
},
  "bbox": [],
  "geometry": {"coordinates":[-153.15,65.2167],"type":"Point"}
}