{
  "id": 2306591,
  "type": "Feature",
  "properties": {
    "tgn:hierarchy":[
        "tgn:2306591",
        "tgn:1000001",
        "tgn:2002370",
        "tgn:7012149",
        "tgn:7007923",
        "tgn:7029392"
    ],
    "tgn:id":2306591,
    "tgn:name":"East Fork Dugout Gulch",
    "tgn:placetype":[
        "aat:300008761"
    ]
},
  "bbox": [],
  "geometry": {"coordinates":[-104.0833,44.4167],"type":"Point"}
}