{
  "id": 7512436,
  "type": "Feature",
  "properties": {
    "tgn:hierarchy":[
        "tgn:7512436",
        "tgn:1008380",
        "tgn:7000507",
        "tgn:1000226",
        "tgn:1000006",
        "tgn:7029392"
    ],
    "tgn:id":7512436,
    "tgn:name:en":"Huarua",
    "tgn:placetype":[
        "aat:300008795"
    ]
},
  "bbox": [],
  "geometry": {"coordinates":[174.183333,-35.85],"type":"Point"}
}