{
  "id": 7530847,
  "type": "Feature",
  "properties": {
    "tgn:hierarchy":[
        "tgn:7530847",
        "tgn:7001242",
        "tgn:7016833",
        "tgn:1001087",
        "tgn:7029392"
    ],
    "tgn:id":7530847,
    "tgn:name":"Tur'at an Ni'n\u0101'\u012byah",
    "tgn:placetype":[
        "aat:300006075"
    ]
},
  "bbox": [],
  "geometry": {"coordinates":[30.989039,30.317065],"type":"Point"}
}