{
  "id": 7418396,
  "type": "Feature",
  "properties": {
    "tgn:hierarchy":[
        "tgn:7418396",
        "tgn:1001835",
        "tgn:1000001",
        "tgn:7005560",
        "tgn:7029392"
    ],
    "tgn:id":7418396,
    "tgn:name":"Caitamul, Ca\u00f1\u00f3n",
    "tgn:placetype":[
        "aat:300008763"
    ]
},
  "bbox": [],
  "geometry": {"coordinates":[-116.341111,32.127778],"type":"Point"}
}