{
  "id": 7256203,
  "type": "Feature",
  "properties": {
    "tgn:hierarchy":[
        "tgn:7256203",
        "tgn:7003456",
        "tgn:1000003",
        "tgn:1000063",
        "tgn:7018236",
        "tgn:7029392"
    ],
    "tgn:id":7256203,
    "tgn:name":"Zwanenberg",
    "tgn:placetype":[
        "aat:300008347"
    ]
},
  "bbox": [],
  "geometry": {"coordinates":[4.483333,51.416667],"type":"Point"}
}