<<<<<<< HEAD
{
  "id": 2767085,
  "type": "Feature",
  "properties": {
    "tgn:hierarchy":[
        "tgn:2767085",
        "tgn:1000001",
        "tgn:7012149",
        "tgn:1002821",
        "tgn:7007568",
        "tgn:7029392"
    ],
    "tgn:id":2767085,
    "tgn:name":"White Rock",
    "tgn:placetype":[
        "aat:300008798"
    ]
},
  "bbox": [],
  "geometry": {"coordinates":[-73.2667,42.75],"type":"Point"}
}
=======
{"geometry":{"type":"Point","coordinates":[-73.266700,42.750000]},"type":"Feature","properties":{"hierarchy":["tgn:2767085","tgn:1000001","tgn:7012149","tgn:1002821","tgn:7007568","tgn:7029392"],"placetype":["aat:300008798"],"id":2767085,"name:xx":"White Rock"}}
>>>>>>> 03f74aca74312dbeaf24d7e61306dd6a786dc3d0
