{
  "id": 2208947,
  "type": "Feature",
  "properties": {
    "tgn:hierarchy":[
        "tgn:2208947",
        "tgn:2000090",
        "tgn:1000001",
        "tgn:7006451",
        "tgn:7012149",
        "tgn:7029392"
    ],
    "tgn:id":2208947,
    "tgn:name":"Burnt Corral Spring",
    "tgn:placetype":[
        "aat:300008697"
    ]
},
  "bbox": [],
  "geometry": {"coordinates":[-109.7333,33.5667],"type":"Point"}
}