{
  "id": 7531165,
  "type": "Feature",
  "properties": {
    "tgn:hierarchy":[
        "tgn:7531165",
        "tgn:7001242",
        "tgn:7016833",
        "tgn:1001092",
        "tgn:7029392"
    ],
    "tgn:id":7531165,
    "tgn:name":"Masjid ash Shaykh Sayf",
    "tgn:placetype":[
        "aat:300007544"
    ]
},
  "bbox": [],
  "geometry": {"coordinates":[31.206726,30.135249],"type":"Point"}
}