{
  "id": 7546790,
  "type": "Feature",
  "properties": {
    "tgn:hierarchy":[
        "tgn:7546790",
        "tgn:1001828",
        "tgn:1000004",
        "tgn:7000198",
        "tgn:7029392"
    ],
    "tgn:id":7546790,
    "tgn:name:en":"Appanapalli",
    "tgn:placetype":[
        "aat:300008347"
    ]
},
  "bbox": [],
  "geometry": {"coordinates":[77.866667,16.783333],"type":"Point"}
}