{
  "id": 7010196,
  "type": "Feature",
  "properties": {
    "tgn:hierarchy":[
        "tgn:7010196",
        "tgn:7011648",
        "tgn:1000003",
        "tgn:7006660",
        "tgn:7029392"
    ],
    "tgn:id":7010196,
    "tgn:name":"Mogil'ov",
    "tgn:placetype":[
        "aat:300008347"
    ]
},
  "bbox": [],
  "geometry": {"coordinates":[34.4833,48.8667],"type":"Point"}
}