{
  "id": 2438753,
  "type": "Feature",
  "properties": {
    "tgn:hierarchy":[
        "tgn:2438753",
        "tgn:1000001",
        "tgn:7012149",
        "tgn:7007712",
        "tgn:7029392"
    ],
    "tgn:id":2438753,
    "tgn:name":"Kinley Creek",
    "tgn:placetype":[
        "aat:300008706"
    ]
},
  "bbox": [],
  "geometry": {"coordinates":[-81.1833,34.0833],"type":"Point"}
}