{
  "id": 2707173,
  "type": "Feature",
  "properties": {
    "tgn:hierarchy":[
        "tgn:2707173",
        "tgn:1000001",
        "tgn:2001009",
        "tgn:7012149",
        "tgn:7007521",
        "tgn:7029392"
    ],
    "tgn:id":2707173,
    "tgn:name":"Swede Lake",
    "tgn:placetype":[
        "aat:300008680"
    ]
},
  "bbox": [],
  "geometry": {"coordinates":[-94.35,46.7667],"type":"Point"}
}