{
  "id": 7261048,
  "type": "Feature",
  "properties": {
    "tgn:hierarchy":[
        "tgn:7261048",
        "tgn:7003616",
        "tgn:1000003",
        "tgn:7016845",
        "tgn:7029392"
    ],
    "tgn:id":7261048,
    "tgn:name:nl":"Groote Gaastmeer",
    "tgn:placetype":[
        "aat:300008680"
    ]
},
  "bbox": [],
  "geometry": {"coordinates":[5.516667,52.966667],"type":"Point"}
}