{
  "id": 2461092,
  "type": "Feature",
  "properties": {
    "tgn:hierarchy":[
        "tgn:2461092",
        "tgn:1000001",
        "tgn:7012149",
        "tgn:2002179",
        "tgn:7007919",
        "tgn:7029392"
    ],
    "tgn:id":2461092,
    "tgn:name":"Little Spencer Creek",
    "tgn:placetype":[
        "aat:300008706"
    ]
},
  "bbox": [],
  "geometry": {"coordinates":[-80.15,36.7333],"type":"Point"}
}