<<<<<<< HEAD
{
  "id": 2768830,
  "type": "Feature",
  "properties": {
    "tgn:hierarchy":[
        "tgn:2768830",
        "tgn:1000001",
        "tgn:2000952",
        "tgn:7012149",
        "tgn:7007520",
        "tgn:7029392"
    ],
    "tgn:id":2768830,
    "tgn:name":"Whitney Bay",
    "tgn:placetype":[
        "aat:300132316"
    ]
},
  "bbox": [],
  "geometry": {"coordinates":[-83.85,45.9667],"type":"Point"}
}
=======
{"geometry":{"type":"Point","coordinates":[-83.850000,45.966700]},"type":"Feature","properties":{"hierarchy":["tgn:2768830","tgn:1000001","tgn:2000952","tgn:7012149","tgn:7007520","tgn:7029392"],"placetype":["aat:300132316"],"id":2768830,"name:xx":"Whitney Bay"}}
>>>>>>> 03f74aca74312dbeaf24d7e61306dd6a786dc3d0
