{
  "id": 7035786,
  "type": "Feature",
  "properties": {
    "tgn:hierarchy":[
        "tgn:7035786",
        "tgn:7002991",
        "tgn:1000003",
        "tgn:7002997",
        "tgn:1000080",
        "tgn:7029392"
    ],
    "tgn:id":7035786,
    "tgn:name":"Pieve",
    "tgn:placetype":[
        "aat:300008347"
    ]
},
  "bbox": [],
  "geometry": {"coordinates":[12.190278,46.35],"type":"Point"}
}