{
  "id": 7573459,
  "type": "Feature",
  "properties": {
    "tgn:hierarchy":[
        "tgn:7573459",
        "tgn:1000004",
        "tgn:7000198",
        "tgn:7016788",
        "tgn:7029392"
    ],
    "tgn:id":7573459,
    "tgn:name:en":"K\u0101buli",
    "tgn:placetype":[
        "aat:300008347"
    ]
},
  "bbox": [],
  "geometry": {"coordinates":[71.448565,25.090787],"type":"Point"}
}