{
  "id": 2525189,
  "type": "Feature",
  "properties": {
    "tgn:hierarchy":[
        "tgn:2525189",
        "tgn:1000001",
        "tgn:7012149",
        "tgn:2002362",
        "tgn:7007922",
        "tgn:7029392"
    ],
    "tgn:id":2525189,
    "tgn:name":"Morris, Mount",
    "tgn:placetype":[
        "aat:300008798"
    ]
},
  "bbox": [],
  "geometry": {"coordinates":[-89.1833,44.1167],"type":"Point"}
}