<<<<<<< HEAD
{
  "id": 7174219,
  "type": "Feature",
  "properties": {
    "tgn:hierarchy":[
        "tgn:7174219",
        "tgn:1000003",
        "tgn:7003676",
        "tgn:7000084",
        "tgn:7029392"
    ],
    "tgn:id":7174219,
    "tgn:name":"Gr\u00f6nheim",
    "tgn:placetype":[
        "aat:300008347"
    ]
},
  "bbox": [],
  "geometry": {"coordinates":[7.866667,52.883333],"type":"Point"}
}
=======
{"geometry":{"type":"Point","coordinates":[7.866667,52.883333]},"type":"Feature","properties":{"hierarchy":["tgn:7174219","tgn:1000003","tgn:7003676","tgn:7000084","tgn:7029392"],"placetype":["aat:300008347"],"id":7174219,"name:xx":"Gr\u00f6nheim"}}
>>>>>>> 03f74aca74312dbeaf24d7e61306dd6a786dc3d0
