{
  "id": 2402871,
  "type": "Feature",
  "properties": {
    "tgn:hierarchy":[
        "tgn:2402871",
        "tgn:1000001",
        "tgn:7012149",
        "tgn:2000480",
        "tgn:7007250",
        "tgn:7029392"
    ],
    "tgn:id":2402871,
    "tgn:name":"Hoteling Creek",
    "tgn:placetype":[
        "aat:300008706"
    ]
},
  "bbox": [],
  "geometry": {"coordinates":[-116.7833,46.9667],"type":"Point"}
}