<<<<<<< HEAD
{
  "id": 2402871,
  "type": "Feature",
  "properties": {
    "tgn:hierarchy":[
        "tgn:2402871",
        "tgn:1000001",
        "tgn:7012149",
        "tgn:2000480",
        "tgn:7007250",
        "tgn:7029392"
    ],
    "tgn:id":2402871,
    "tgn:name":"Hoteling Creek",
    "tgn:placetype":[
        "aat:300008706"
    ]
},
  "bbox": [],
  "geometry": {"coordinates":[-116.7833,46.9667],"type":"Point"}
}
=======
{"geometry":{"type":"Point","coordinates":[-116.783300,46.966700]},"type":"Feature","properties":{"hierarchy":["tgn:2402871","tgn:1000001","tgn:7012149","tgn:2000480","tgn:7007250","tgn:7029392"],"placetype":["aat:300008706"],"id":2402871,"name:xx":"Hoteling Creek"}}
>>>>>>> 03f74aca74312dbeaf24d7e61306dd6a786dc3d0
