{
  "id": 7275750,
  "type": "Feature",
  "properties": {
    "tgn:hierarchy":[
        "tgn:7275750",
        "tgn:1001637",
        "tgn:1000049",
        "tgn:1000002",
        "tgn:7029392"
    ],
    "tgn:id":7275750,
    "tgn:name":"Trancalco, Laguna",
    "tgn:placetype":[
        "aat:300008680"
    ]
},
  "bbox": [],
  "geometry": {"coordinates":[-73.433333,-37.933333],"type":"Point"}
}