{
  "id": 1060026,
  "type": "Feature",
  "properties": {
    "tgn:hierarchy":[
        "tgn:1060026",
        "tgn:7013670",
        "tgn:1000004",
        "tgn:7018214",
        "tgn:7002435",
        "tgn:7029392"
    ],
    "tgn:id":1060026,
    "tgn:name":"Tyagun",
    "tgn:placetype":[
        "aat:300008347"
    ]
},
  "bbox": [],
  "geometry": {"coordinates":[85.6333,53.9333],"type":"Point"}
}