{
  "id": 2396087,
  "type": "Feature",
  "properties": {
    "tgn:hierarchy":[
        "tgn:2396087",
        "tgn:1000001",
        "tgn:7012149",
        "tgn:2001846",
        "tgn:7007825",
        "tgn:7029392"
    ],
    "tgn:id":2396087,
    "tgn:name":"Holly Springs Branch",
    "tgn:placetype":[
        "aat:300008699"
    ]
},
  "bbox": [],
  "geometry": {"coordinates":[-82.05,36.4333],"type":"Point"}
}