{
  "id": 7559273,
  "type": "Feature",
  "properties": {
    "tgn:hierarchy":[
        "tgn:7559273",
        "tgn:1000004",
        "tgn:7000198",
        "tgn:7031783",
        "tgn:7029392"
    ],
    "tgn:id":7559273,
    "tgn:name:en":"Rohini",
    "tgn:placetype":[
        "aat:300008347"
    ]
},
  "bbox": [],
  "geometry": {"coordinates":[86.648534,24.475711],"type":"Point"}
}