{
  "id": 2506700,
  "type": "Feature",
  "properties": {
    "tgn:hierarchy":[
        "tgn:2506700",
        "tgn:1000001",
        "tgn:7012149",
        "tgn:2002057",
        "tgn:7007826",
        "tgn:7029392"
    ],
    "tgn:id":2506700,
    "tgn:name":"Mesa Tank",
    "tgn:placetype":[
        "aat:300006191"
    ]
},
  "bbox": [],
  "geometry": {"coordinates":[-104.45,29.8833],"type":"Point"}
}