{
  "id": 2227481,
  "type": "Feature",
  "properties": {
    "tgn:hierarchy":[
        "tgn:2227481",
        "tgn:1000001",
        "tgn:7012149",
        "tgn:7007825",
        "tgn:7029392"
    ],
    "tgn:id":2227481,
    "tgn:name":"Cave Spring Hollow",
    "tgn:placetype":[
        "aat:300008761"
    ]
},
  "bbox": [],
  "geometry": {"coordinates":[-87.5333,35.9833],"type":"Point"}
}