{
  "id": 7414802,
  "type": "Feature",
  "properties": {
    "tgn:hierarchy":[
        "tgn:7414802",
        "tgn:1000001",
        "tgn:7005591",
        "tgn:7005560",
        "tgn:7029392"
    ],
    "tgn:id":7414802,
    "tgn:name:es":"Tolistoque, Sierra",
    "tgn:placetype":[
        "aat:300008795"
    ]
},
  "bbox": [],
  "geometry": {"coordinates":[-94.883611,16.625],"type":"Point"}
}