{
  "id": 2276155,
  "type": "Feature",
  "properties": {
    "tgn:hierarchy":[
        "tgn:2276155",
        "tgn:1000001",
        "tgn:1002216",
        "tgn:7012149",
        "tgn:7007706",
        "tgn:7029392"
    ],
    "tgn:id":2276155,
    "tgn:name":"Darrs Run",
    "tgn:placetype":[
        "aat:300008699"
    ]
},
  "bbox": [],
  "geometry": {"coordinates":[-84.6833,39.55],"type":"Point"}
}