{
  "id": 7128869,
  "type": "Feature",
  "properties": {
    "tgn:hierarchy":[
        "tgn:7128869",
        "tgn:7003669",
        "tgn:1000003",
        "tgn:7000084",
        "tgn:7029392"
    ],
    "tgn:id":7128869,
    "tgn:name":"Oberer Angelberger Forst",
    "tgn:placetype":[
        "aat:300008863"
    ]
},
  "bbox": [],
  "geometry": {"coordinates":[10.583333,48.116667],"type":"Point"}
}