{
  "id": 2252406,
  "type": "Feature",
  "properties": {
    "tgn:hierarchy":[
        "tgn:2252406",
        "tgn:1000001",
        "tgn:7012149",
        "tgn:7007706",
        "tgn:7029392"
    ],
    "tgn:id":2252406,
    "tgn:name":"Congress Lake Outlet",
    "tgn:placetype":[
        "aat:300008699"
    ]
},
  "bbox": [],
  "geometry": {"coordinates":[-81.3167,40.9667],"type":"Point"}
}