<<<<<<< HEAD
{
  "id": 2252406,
  "type": "Feature",
  "properties": {
    "tgn:hierarchy":[
        "tgn:2252406",
        "tgn:1000001",
        "tgn:7012149",
        "tgn:7007706",
        "tgn:7029392"
    ],
    "tgn:id":2252406,
    "tgn:name":"Congress Lake Outlet",
    "tgn:placetype":[
        "aat:300008699"
    ]
},
  "bbox": [],
  "geometry": {"coordinates":[-81.3167,40.9667],"type":"Point"}
}
=======
{"geometry":{"type":"Point","coordinates":[-81.316700,40.966700]},"type":"Feature","properties":{"hierarchy":["tgn:2252406","tgn:1000001","tgn:7012149","tgn:7007706","tgn:7029392"],"placetype":["aat:300008699"],"id":2252406,"name:xx":"Congress Lake Outlet"}}
>>>>>>> 03f74aca74312dbeaf24d7e61306dd6a786dc3d0
