{
  "id": 2199864,
  "type": "Feature",
  "properties": {
    "tgn:hierarchy":[
        "tgn:2199864",
        "tgn:1000001",
        "tgn:7012149",
        "tgn:2002110",
        "tgn:7007827",
        "tgn:7029392"
    ],
    "tgn:id":2199864,
    "tgn:name":"Brusher Canyon",
    "tgn:placetype":[
        "aat:300008761"
    ]
},
  "bbox": [],
  "geometry": {"coordinates":[-109.2167,39.4333],"type":"Point"}
}