{
  "id": 7366249,
  "type": "Feature",
  "properties": {
    "tgn:hierarchy":[
        "tgn:7366249",
        "tgn:7005578",
        "tgn:1000001",
        "tgn:7005560",
        "tgn:7029392"
    ],
    "tgn:id":7366249,
    "tgn:name":"El Pedernal",
    "tgn:placetype":[
        "aat:300008347"
    ]
},
  "bbox": [],
  "geometry": {"coordinates":[-90.583333,17.983333],"type":"Point"}
}