{
  "id": 1090407,
  "type": "Feature",
  "properties": {
    "tgn:hierarchy":[
        "tgn:1090407",
        "tgn:7001242",
        "tgn:1000657",
        "tgn:1000168",
        "tgn:7029392"
    ],
    "tgn:id":1090407,
    "tgn:name":"Souroukaha",
    "tgn:placetype":[
        "aat:300008347"
    ]
},
  "bbox": [],
  "geometry": {"coordinates":[-5.1333,8.2167],"type":"Point"}
}