{
  "id": 7332097,
  "type": "Feature",
  "properties": {
    "tgn:hierarchy":[
        "tgn:7332097",
        "tgn:7007780",
        "tgn:1000003",
        "tgn:7009604",
        "tgn:1000095",
        "tgn:7029392"
    ],
    "tgn:id":7332097,
    "tgn:name":"Izustarri, Punta",
    "tgn:placetype":[
        "aat:300386846"
    ]
},
  "bbox": [],
  "geometry": {"coordinates":[-2.238947,43.308278],"type":"Point"}
}