<<<<<<< HEAD
{
  "id": 2336849,
  "type": "Feature",
  "properties": {
    "tgn:hierarchy":[
        "tgn:2336849",
        "tgn:1000001",
        "tgn:7012149",
        "tgn:7007157",
        "tgn:2000189",
        "tgn:7029392"
    ],
    "tgn:id":2336849,
    "tgn:name":"Fourmile Creek",
    "tgn:placetype":[
        "aat:300008706"
    ]
},
  "bbox": [],
  "geometry": {"coordinates":[-123.3,41.9],"type":"Point"}
}
=======
{"geometry":{"type":"Point","coordinates":[-123.300000,41.900000]},"type":"Feature","properties":{"hierarchy":["tgn:2336849","tgn:1000001","tgn:7012149","tgn:7007157","tgn:2000189","tgn:7029392"],"placetype":["aat:300008706"],"id":2336849,"name:xx":"Fourmile Creek"}}
>>>>>>> 03f74aca74312dbeaf24d7e61306dd6a786dc3d0
