{
  "id": 7316415,
  "type": "Feature",
  "properties": {
    "tgn:hierarchy":[
        "tgn:7316415",
        "tgn:1001630",
        "tgn:1000049",
        "tgn:1000002",
        "tgn:7029392"
    ],
    "tgn:id":7316415,
    "tgn:name":"Carrizo, Aguada",
    "tgn:placetype":[
        "aat:300008697"
    ]
},
  "bbox": [],
  "geometry": {"coordinates":[-71.033333,-28.616667],"type":"Point"}
}