{
  "id": 2373624,
  "type": "Feature",
  "properties": {
    "tgn:hierarchy":[
        "tgn:2373624",
        "tgn:1000001",
        "tgn:7012149",
        "tgn:7007158",
        "tgn:2000250",
        "tgn:7029392"
    ],
    "tgn:id":2373624,
    "tgn:name":"Hamilton Creek",
    "tgn:placetype":[
        "aat:300008706"
    ]
},
  "bbox": [],
  "geometry": {"coordinates":[-106.0333,39.6667],"type":"Point"}
}