<<<<<<< HEAD
{
  "id": 2155141,
  "type": "Feature",
  "properties": {
    "tgn:hierarchy":[
        "tgn:2155141",
        "tgn:1000001",
        "tgn:7012149",
        "tgn:2002344",
        "tgn:7007922",
        "tgn:7029392"
    ],
    "tgn:id":2155141,
    "tgn:name":"Bear Lake",
    "tgn:placetype":[
        "aat:300132316"
    ]
},
  "bbox": [],
  "geometry": {"coordinates":[-91.9167,44.65],"type":"Point"}
}
=======
{"geometry":{"type":"Point","coordinates":[-91.916700,44.650000]},"type":"Feature","properties":{"hierarchy":["tgn:2155141","tgn:1000001","tgn:7012149","tgn:2002344","tgn:7007922","tgn:7029392"],"placetype":["aat:300132316"],"id":2155141,"name:xx":"Bear Lake"}}
>>>>>>> 03f74aca74312dbeaf24d7e61306dd6a786dc3d0
