{
  "id": 7337901,
  "type": "Feature",
  "properties": {
    "tgn:hierarchy":[
        "tgn:7337901",
        "tgn:7002831",
        "tgn:1000003",
        "tgn:7002786",
        "tgn:1000095",
        "tgn:7029392"
    ],
    "tgn:id":7337901,
    "tgn:name":"Celeiros",
    "tgn:placetype":[
        "aat:300008347"
    ]
},
  "bbox": [],
  "geometry": {"coordinates":[-7.383333,42.266667],"type":"Point"}
}