{
  "id": 2545609,
  "type": "Feature",
  "properties": {
    "tgn:hierarchy":[
        "tgn:2545609",
        "tgn:1000001",
        "tgn:2000459",
        "tgn:7012149",
        "tgn:7007250",
        "tgn:7029392"
    ],
    "tgn:id":2545609,
    "tgn:name":"North Fork Canyon Creek",
    "tgn:placetype":[
        "aat:300008706"
    ]
},
  "bbox": [],
  "geometry": {"coordinates":[-115.1833,44.2667],"type":"Point"}
}