{
  "id": 2597438,
  "type": "Feature",
  "properties": {
    "tgn:hierarchy":[
        "tgn:2597438",
        "tgn:1000001",
        "tgn:7012149",
        "tgn:2001253",
        "tgn:7007523",
        "tgn:7029392"
    ],
    "tgn:id":2597438,
    "tgn:name":"Prairie Flower Branch",
    "tgn:placetype":[
        "aat:300008699"
    ]
},
  "bbox": [],
  "geometry": {"coordinates":[-94.45,37.6667],"type":"Point"}
}