<<<<<<< HEAD
{
  "id": 7476344,
  "type": "Feature",
  "properties": {
    "tgn:hierarchy":[
        "tgn:7476344",
        "tgn:7488858",
        "tgn:1000004",
        "tgn:1000141",
        "tgn:7029392"
    ],
    "tgn:id":7476344,
    "tgn:name":"Nangang Gongyequ",
    "tgn:placetype":[
        "aat:300387302"
    ]
},
  "bbox": [],
  "geometry": {"coordinates":[120.664247,23.928647],"type":"Point"}
}
=======
{"geometry":{"type":"Point","coordinates":[120.664247,23.928647]},"type":"Feature","properties":{"hierarchy":["tgn:7476344","tgn:7488858","tgn:1000004","tgn:1000141","tgn:7029392"],"placetype":["aat:300387302"],"id":7476344,"name:xx":"Nangang Gongyequ"}}
>>>>>>> 03f74aca74312dbeaf24d7e61306dd6a786dc3d0
