{
  "id": 1010787,
  "type": "Feature",
  "properties": {
    "tgn:hierarchy":[
        "tgn:1010787",
        "tgn:7006450",
        "tgn:1000001",
        "tgn:7012149",
        "tgn:2124005",
        "tgn:7029392"
    ],
    "tgn:id":1010787,
    "tgn:name":"Icy Cape",
    "tgn:placetype":[
        "aat:300008850"
    ]
},
  "bbox": [],
  "geometry": {"coordinates":[-161.8667,70.3167],"type":"Point"}
}