{
  "id": 2757123,
  "type": "Feature",
  "properties": {
    "tgn:hierarchy":[
        "tgn:2757123",
        "tgn:1000001",
        "tgn:7012149",
        "tgn:1002876",
        "tgn:7007710",
        "tgn:7029392"
    ],
    "tgn:id":2757123,
    "tgn:name":"Werts Hollow",
    "tgn:placetype":[
        "aat:300008761"
    ]
},
  "bbox": [],
  "geometry": {"coordinates":[-76.1667,40.5333],"type":"Point"}
}