{
  "id": 7471021,
  "type": "Feature",
  "properties": {
    "tgn:hierarchy":[
        "tgn:7471021",
        "tgn:1000004",
        "tgn:7001014",
        "tgn:1000141",
        "tgn:7029392"
    ],
    "tgn:id":7471021,
    "tgn:name":"Jiuguzi",
    "tgn:placetype":[
        "aat:300008347"
    ]
},
  "bbox": [],
  "geometry": {"coordinates":[120.365,23.8064],"type":"Point"}
}