{
  "id": 2425964,
  "type": "Feature",
  "properties": {
    "tgn:hierarchy":[
        "tgn:2425964",
        "tgn:1000001",
        "tgn:7016172",
        "tgn:7012149",
        "tgn:2000175",
        "tgn:7029392"
    ],
    "tgn:id":2425964,
    "tgn:name":"Joneed Creek",
    "tgn:placetype":[
        "aat:300008706"
    ]
},
  "bbox": [],
  "geometry": {"coordinates":[-92.6333,35.5333],"type":"Point"}
}