{
  "id": 7170612,
  "type": "Feature",
  "properties": {
    "tgn:hierarchy":[
        "tgn:7170612",
        "tgn:1000003",
        "tgn:7003682",
        "tgn:7000084",
        "tgn:7029392"
    ],
    "tgn:id":7170612,
    "tgn:name":"Hirtscheid",
    "tgn:placetype":[
        "aat:300008347"
    ]
},
  "bbox": [],
  "geometry": {"coordinates":[7.883333,50.633333],"type":"Point"}
}