{
  "id": 2454689,
  "type": "Feature",
  "properties": {
    "tgn:hierarchy":[
        "tgn:2454689",
        "tgn:1000001",
        "tgn:7012149",
        "tgn:2000852",
        "tgn:7007255",
        "tgn:7029392"
    ],
    "tgn:id":2454689,
    "tgn:name":"Little Dog Slaughter Creek",
    "tgn:placetype":[
        "aat:300008706"
    ]
},
  "bbox": [],
  "geometry": {"coordinates":[-84.25,36.85],"type":"Point"}
}