{
  "id": 2702321,
  "type": "Feature",
  "properties": {
    "tgn:hierarchy":[
        "tgn:2702321",
        "tgn:1000001",
        "tgn:7019982",
        "tgn:7012149",
        "tgn:7007517",
        "tgn:7029392"
    ],
    "tgn:id":2702321,
    "tgn:name":"Sullivan Hollow",
    "tgn:placetype":[
        "aat:300008761"
    ]
},
  "bbox": [],
  "geometry": {"coordinates":[-72.85,42.0833],"type":"Point"}
}