<<<<<<< HEAD
{
  "id": 2251184,
  "type": "Feature",
  "properties": {
    "tgn:hierarchy":[
        "tgn:2251184",
        "tgn:1000001",
        "tgn:7012149",
        "tgn:2002087",
        "tgn:7007826",
        "tgn:7029392"
    ],
    "tgn:id":2251184,
    "tgn:name":"Comanche Creek",
    "tgn:placetype":[
        "aat:300008706"
    ]
},
  "bbox": [],
  "geometry": {"coordinates":[-99.4333,29.5],"type":"Point"}
}
=======
{"geometry":{"type":"Point","coordinates":[-99.433300,29.500000]},"type":"Feature","properties":{"hierarchy":["tgn:2251184","tgn:1000001","tgn:7012149","tgn:2002087","tgn:7007826","tgn:7029392"],"placetype":["aat:300008706"],"id":2251184,"name:xx":"Comanche Creek"}}
>>>>>>> 03f74aca74312dbeaf24d7e61306dd6a786dc3d0
