{
  "id": 7118239,
  "type": "Feature",
  "properties": {
    "tgn:hierarchy":[
        "tgn:7118239",
        "tgn:1000003",
        "tgn:7003688",
        "tgn:7000084",
        "tgn:7029392"
    ],
    "tgn:id":7118239,
    "tgn:name":"Peterswarft",
    "tgn:placetype":[
        "aat:300000206"
    ]
},
  "bbox": [],
  "geometry": {"coordinates":[8.633333,54.65],"type":"Point"}
}