{
  "id": 2325783,
  "type": "Feature",
  "properties": {
    "tgn:hierarchy":[
        "tgn:2325783",
        "tgn:1000001",
        "tgn:7012149",
        "tgn:2000219",
        "tgn:7007158",
        "tgn:7029392"
    ],
    "tgn:id":2325783,
    "tgn:name":"Fielden Reservoir",
    "tgn:placetype":[
        "aat:300006191"
    ]
},
  "bbox": [],
  "geometry": {"coordinates":[-105.0667,37.4833],"type":"Point"}
}