<<<<<<< HEAD
{
  "id": 7475913,
  "type": "Feature",
  "properties": {
    "tgn:hierarchy":[
        "tgn:7475913",
        "tgn:7488858",
        "tgn:1000004",
        "tgn:1000141",
        "tgn:7029392"
    ],
    "tgn:id":7475913,
    "tgn:name":"Jingl\u00fc Si",
    "tgn:placetype":[
        "aat:300007595"
    ]
},
  "bbox": [],
  "geometry": {"coordinates":[120.730878,23.777],"type":"Point"}
}
=======
{"geometry":{"type":"Point","coordinates":[120.730878,23.777000]},"type":"Feature","properties":{"hierarchy":["tgn:7475913","tgn:7488858","tgn:1000004","tgn:1000141","tgn:7029392"],"placetype":["aat:300007595"],"id":7475913,"name:xx":"Jingl\u00fc Si"}}
>>>>>>> 03f74aca74312dbeaf24d7e61306dd6a786dc3d0
