{
  "id": 7142934,
  "type": "Feature",
  "properties": {
    "tgn:hierarchy":[
        "tgn:7142934",
        "tgn:1000003",
        "tgn:7003676",
        "tgn:7000084",
        "tgn:7029392"
    ],
    "tgn:id":7142934,
    "tgn:name":"L\u00fcder",
    "tgn:placetype":[
        "aat:300008347"
    ]
},
  "bbox": [],
  "geometry": {"coordinates":[10.666667,52.816667],"type":"Point"}
}