{
  "id": 2773861,
  "type": "Feature",
  "properties": {
    "tgn:hierarchy":[
        "tgn:2773861",
        "tgn:7006450",
        "tgn:1000001",
        "tgn:7019698",
        "tgn:7012149",
        "tgn:7029392"
    ],
    "tgn:id":2773861,
    "tgn:name":"Willow Creek",
    "tgn:placetype":[
        "aat:300008706"
    ]
},
  "bbox": [],
  "geometry": {"coordinates":[-149.5667,60.7833],"type":"Point"}
}