{
  "id": 1017557,
  "type": "Feature",
  "properties": {
    "tgn:hierarchy":[
        "tgn:1017557",
        "tgn:1000001",
        "tgn:7005591",
        "tgn:7005560",
        "tgn:7029392"
    ],
    "tgn:id":1017557,
    "tgn:name":"Huaju\u00e1pan de Le\u00f3n",
    "tgn:placetype":[
        "aat:300008347"
    ]
},
  "bbox": [],
  "geometry": {"coordinates":[-94.316667,16.183333],"type":"Point"}
}