{
  "id": 2369207,
  "type": "Feature",
  "properties": {
    "tgn:hierarchy":[
        "tgn:2369207",
        "tgn:7002659",
        "tgn:1000001",
        "tgn:7012149",
        "tgn:2000035",
        "tgn:7029392"
    ],
    "tgn:id":2369207,
    "tgn:name":"Gum Spring",
    "tgn:placetype":[
        "aat:300008697"
    ]
},
  "bbox": [],
  "geometry": {"coordinates":[-85.9667,34.8667],"type":"Point"}
}