{
  "id": 7386238,
  "type": "Feature",
  "properties": {
    "tgn:hierarchy":[
        "tgn:7386238",
        "tgn:7005586",
        "tgn:1000001",
        "tgn:7005560",
        "tgn:7029392"
    ],
    "tgn:id":7386238,
    "tgn:name":"Ramblas Grande",
    "tgn:placetype":[
        "aat:300008347"
    ]
},
  "bbox": [],
  "geometry": {"coordinates":[-102.783333,20.633333],"type":"Point"}
}