{
  "id": 2705622,
  "type": "Feature",
  "properties": {
    "tgn:hierarchy":[
        "tgn:2705622",
        "tgn:1000001",
        "tgn:7012149",
        "tgn:1002694",
        "tgn:7007252",
        "tgn:7029392"
    ],
    "tgn:id":2705622,
    "tgn:name":"Susans Branch",
    "tgn:placetype":[
        "aat:300008699"
    ]
},
  "bbox": [],
  "geometry": {"coordinates":[-86.4667,39.4833],"type":"Point"}
}