{
  "id": 2413291,
  "type": "Feature",
  "properties": {
    "tgn:hierarchy":[
        "tgn:2413291",
        "tgn:1000001",
        "tgn:7012149",
        "tgn:2001281",
        "tgn:7007524",
        "tgn:7029392"
    ],
    "tgn:id":2413291,
    "tgn:name":"International Creek",
    "tgn:placetype":[
        "aat:300008706"
    ]
},
  "bbox": [],
  "geometry": {"coordinates":[-112.35,46.0333],"type":"Point"}
}