{
  "id": 1079452,
  "type": "Feature",
  "properties": {
    "tgn:hierarchy":[
        "tgn:1079452",
        "tgn:7000249",
        "tgn:1000004",
        "tgn:1000119",
        "tgn:7029392"
    ],
    "tgn:id":1079452,
    "tgn:name":"\u02bbEn Dor",
    "tgn:placetype":[
        "aat:300008347",
        "aat:300008375"
    ]
},
  "bbox": [],
  "geometry": {"coordinates":[35.4167,32.65],"type":"Point"}
}