{
  "id": 2408134,
  "type": "Feature",
  "properties": {
    "tgn:hierarchy":[
        "tgn:2408134",
        "tgn:1000001",
        "tgn:7012149",
        "tgn:2001722",
        "tgn:7007708",
        "tgn:7029392"
    ],
    "tgn:id":2408134,
    "tgn:name":"Hurricane Point",
    "tgn:placetype":[
        "aat:300008798"
    ]
},
  "bbox": [],
  "geometry": {"coordinates":[-117.3167,45.3333],"type":"Point"}
}