<<<<<<< HEAD
{
  "id": 2408134,
  "type": "Feature",
  "properties": {
    "tgn:hierarchy":[
        "tgn:2408134",
        "tgn:1000001",
        "tgn:7012149",
        "tgn:2001722",
        "tgn:7007708",
        "tgn:7029392"
    ],
    "tgn:id":2408134,
    "tgn:name":"Hurricane Point",
    "tgn:placetype":[
        "aat:300008798"
    ]
},
  "bbox": [],
  "geometry": {"coordinates":[-117.3167,45.3333],"type":"Point"}
}
=======
{"geometry":{"type":"Point","coordinates":[-117.316700,45.333300]},"type":"Feature","properties":{"hierarchy":["tgn:2408134","tgn:1000001","tgn:7012149","tgn:2001722","tgn:7007708","tgn:7029392"],"placetype":["aat:300008798"],"id":2408134,"name:xx":"Hurricane Point"}}
>>>>>>> 03f74aca74312dbeaf24d7e61306dd6a786dc3d0
