{
  "id": 7303913,
  "type": "Feature",
  "properties": {
    "tgn:hierarchy":[
        "tgn:7303913",
        "tgn:7002806",
        "tgn:7001158",
        "tgn:1000003",
        "tgn:1000095",
        "tgn:7029392"
    ],
    "tgn:id":7303913,
    "tgn:name":"Navacepeda de Tormes",
    "tgn:placetype":[
        "aat:300008347"
    ]
},
  "bbox": [],
  "geometry": {"coordinates":[-5.25,40.366667],"type":"Point"}
}