{
  "id": 2773889,
  "type": "Feature",
  "properties": {
    "tgn:hierarchy":[
        "tgn:2773889",
        "tgn:1000001",
        "tgn:7012149",
        "tgn:1002392",
        "tgn:7007157",
        "tgn:7029392"
    ],
    "tgn:id":2773889,
    "tgn:name":"Willow Creek",
    "tgn:placetype":[
        "aat:300008706"
    ]
},
  "bbox": [],
  "geometry": {"coordinates":[-119.35,36.6167],"type":"Point"}
}