{
  "id": 2037099,
  "type": "Feature",
  "properties": {
    "tgn:hierarchy":[
        "tgn:2037099",
        "tgn:1000001",
        "tgn:7012149",
        "tgn:2000225",
        "tgn:7007158",
        "tgn:7029392"
    ],
    "tgn:id":2037099,
    "tgn:name":"Saunders",
    "tgn:placetype":[
        "aat:300008347",
        "aat:300387210"
    ]
},
  "bbox": [],
  "geometry": {"coordinates":[-102.0333,37.4667],"type":"Point"}
}