{
  "id": 1114632,
  "type": "Feature",
  "properties": {
    "tgn:hierarchy":[
        "tgn:1114632",
        "tgn:1002132",
        "tgn:1000001",
        "tgn:7012149",
        "tgn:7007919",
        "tgn:7029392"
    ],
    "tgn:id":1114632,
    "tgn:name":"Metompkin Inlet",
    "tgn:placetype":[
        "aat:300185707"
    ]
},
  "bbox": [],
  "geometry": {"coordinates":[-75.5667,37.6667],"type":"Point"}
}