{
  "id": 2679685,
  "type": "Feature",
  "properties": {
    "tgn:hierarchy":[
        "tgn:2679685",
        "tgn:1000001",
        "tgn:7012149",
        "tgn:7007255",
        "tgn:7029392"
    ],
    "tgn:id":2679685,
    "tgn:name":"South Fork Pottinger Creek",
    "tgn:placetype":[
        "aat:300008706"
    ]
},
  "bbox": [],
  "geometry": {"coordinates":[-85.4333,37.6167],"type":"Point"}
}