{
  "id": 1115947,
  "type": "Feature",
  "properties": {
    "tgn:hierarchy":[
        "tgn:1115947",
        "tgn:7015163",
        "tgn:1000003",
        "tgn:7003121",
        "tgn:1000080",
        "tgn:7029392"
    ],
    "tgn:id":1115947,
    "tgn:name":"Coghinas, Lago del",
    "tgn:placetype":[
        "aat:300008680"
    ]
},
  "bbox": [],
  "geometry": {"coordinates":[9.033333,40.75],"type":"Point"}
}