{
  "id": 1058212,
  "type": "Feature",
  "properties": {
    "tgn:hierarchy":[
        "tgn:1058212",
        "tgn:1000004",
        "tgn:4005827",
        "tgn:7018214",
        "tgn:7002435",
        "tgn:7029392"
    ],
    "tgn:id":1058212,
    "tgn:name":"Parfenyevo",
    "tgn:placetype":[
        "aat:300008347"
    ]
},
  "bbox": [],
  "geometry": {"coordinates":[43.3667,58.4833],"type":"Point"}
}