{
  "id": 2114222,
  "type": "Feature",
  "properties": {
    "tgn:hierarchy":[
        "tgn:2114222",
        "tgn:1002132",
        "tgn:1000001",
        "tgn:7012149",
        "tgn:7007919",
        "tgn:7029392"
    ],
    "tgn:id":2114222,
    "tgn:name":"Shields",
    "tgn:placetype":[
        "aat:300008347",
        "aat:300387210"
    ]
},
  "bbox": [],
  "geometry": {"coordinates":[-75.85,37.5667],"type":"Point"}
}