{
  "id": 7549063,
  "type": "Feature",
  "properties": {
    "tgn:hierarchy":[
        "tgn:7549063",
        "tgn:1000004",
        "tgn:7018318",
        "tgn:7000198",
        "tgn:7029392"
    ],
    "tgn:id":7549063,
    "tgn:name:en":"Cabo, Ponta de",
    "tgn:placetype":[
        "aat:300386846"
    ]
},
  "bbox": [],
  "geometry": {"coordinates":[73.766667,15.466667],"type":"Point"}
}