<<<<<<< HEAD
{
  "id": 2254391,
  "type": "Feature",
  "properties": {
    "tgn:hierarchy":[
        "tgn:2254391",
        "tgn:1000001",
        "tgn:7012149",
        "tgn:2001258",
        "tgn:7007523",
        "tgn:7029392"
    ],
    "tgn:id":2254391,
    "tgn:name":"Coon Creek",
    "tgn:placetype":[
        "aat:300008706"
    ]
},
  "bbox": [],
  "geometry": {"coordinates":[-92.5,37.3167],"type":"Point"}
}
=======
{"geometry":{"type":"Point","coordinates":[-92.500000,37.316700]},"type":"Feature","properties":{"hierarchy":["tgn:2254391","tgn:1000001","tgn:7012149","tgn:2001258","tgn:7007523","tgn:7029392"],"placetype":["aat:300008706"],"id":2254391,"name:xx":"Coon Creek"}}
>>>>>>> 03f74aca74312dbeaf24d7e61306dd6a786dc3d0
