{
  "id": 7085575,
  "type": "Feature",
  "properties": {
    "tgn:hierarchy":[
        "tgn:7085575",
        "tgn:7003669",
        "tgn:1000003",
        "tgn:7000084",
        "tgn:7029392"
    ],
    "tgn:id":7085575,
    "tgn:name":"Wallerfing",
    "tgn:placetype":[
        "aat:300008347"
    ]
},
  "bbox": [],
  "geometry": {"coordinates":[12.883333,48.683333],"type":"Point"}
}