{
  "id": 2082166,
  "type": "Feature",
  "properties": {
    "tgn:hierarchy":[
        "tgn:2082166",
        "tgn:1000001",
        "tgn:7012149",
        "tgn:1002788",
        "tgn:7007706",
        "tgn:7029392"
    ],
    "tgn:id":2082166,
    "tgn:name":"Tennyson",
    "tgn:placetype":[
        "aat:300008347",
        "aat:300387210"
    ]
},
  "bbox": [],
  "geometry": {"coordinates":[-83.1167,39.05],"type":"Point"}
}