{
  "id": 2116209,
  "type": "Feature",
  "properties": {
    "tgn:hierarchy":[
        "tgn:2116209",
        "tgn:1000001",
        "tgn:7012149",
        "tgn:7018871",
        "tgn:7007920",
        "tgn:7029392"
    ],
    "tgn:id":2116209,
    "tgn:name":"McMicken Heights",
    "tgn:placetype":[
        "aat:300008347"
    ]
},
  "bbox": [],
  "geometry": {"coordinates":[-122.2667,47.45],"type":"Point"}
}