{
  "id": 2667190,
  "type": "Feature",
  "properties": {
    "tgn:hierarchy":[
        "tgn:2667190",
        "tgn:1000001",
        "tgn:7012149",
        "tgn:2001437",
        "tgn:7007566",
        "tgn:7029392"
    ],
    "tgn:id":2667190,
    "tgn:name":"Skillet Mesa",
    "tgn:placetype":[
        "aat:300266640"
    ]
},
  "bbox": [],
  "geometry": {"coordinates":[-107.9333,32.9333],"type":"Point"}
}