{
  "id": 7343448,
  "type": "Feature",
  "properties": {
    "tgn:hierarchy":[
        "tgn:7343448",
        "tgn:7002804",
        "tgn:1000003",
        "tgn:7002793",
        "tgn:1000095",
        "tgn:7029392"
    ],
    "tgn:id":7343448,
    "tgn:name":"Casas de Torrat",
    "tgn:placetype":[
        "aat:300008347"
    ]
},
  "bbox": [],
  "geometry": {"coordinates":[0.066667,38.666667],"type":"Point"}
}