{
  "id": 7259152,
  "type": "Feature",
  "properties": {
    "tgn:hierarchy":[
        "tgn:7259152",
        "tgn:7018239",
        "tgn:1000003",
        "tgn:1000063",
        "tgn:7018236",
        "tgn:7029392"
    ],
    "tgn:id":7259152,
    "tgn:name":"Vollezele",
    "tgn:placetype":[
        "aat:300008347"
    ]
},
  "bbox": [],
  "geometry": {"coordinates":[4.024348,50.761214],"type":"Point"}
}