{
  "id": 2381730,
  "type": "Feature",
  "properties": {
    "tgn:hierarchy":[
        "tgn:2381730",
        "tgn:1000001",
        "tgn:7012149",
        "tgn:2000233",
        "tgn:7007158",
        "tgn:7029392"
    ],
    "tgn:id":2381730,
    "tgn:name":"Haycamp Point Reservoir",
    "tgn:placetype":[
        "aat:300006191"
    ]
},
  "bbox": [],
  "geometry": {"coordinates":[-108.3667,37.5167],"type":"Point"}
}