<<<<<<< HEAD
{
  "id": 7054687,
  "type": "Feature",
  "properties": {
    "tgn:hierarchy":[
        "tgn:7054687",
        "tgn:7005852",
        "tgn:1000003",
        "tgn:7003237",
        "tgn:1000080",
        "tgn:7029392"
    ],
    "tgn:id":7054687,
    "tgn:name":"Ponna",
    "tgn:placetype":[
        "aat:300387198",
        "aat:300265612"
    ]
},
  "bbox": [],
  "geometry": {"coordinates":[9.083333,45.983333],"type":"Point"}
}
=======
{"geometry":{"type":"Point","coordinates":[9.083333,45.983333]},"type":"Feature","properties":{"hierarchy":["tgn:7054687","tgn:7005852","tgn:1000003","tgn:7003237","tgn:1000080","tgn:7029392"],"placetype":["aat:300387198","aat:300265612"],"id":7054687,"name:xx":"Ponna"}}
>>>>>>> 03f74aca74312dbeaf24d7e61306dd6a786dc3d0
