{
  "id": 7563705,
  "type": "Feature",
  "properties": {
    "tgn:hierarchy":[
        "tgn:7563705",
        "tgn:1000004",
        "tgn:7000198",
        "tgn:7016722",
        "tgn:7029392"
    ],
    "tgn:id":7563705,
    "tgn:name:en":"Sukhnai Nadi",
    "tgn:placetype":[
        "aat:300008699"
    ]
},
  "bbox": [],
  "geometry": {"coordinates":[79.264534,25.283045],"type":"Point"}
}