{
  "id": 2031429,
  "type": "Feature",
  "properties": {
    "tgn:hierarchy":[
        "tgn:2031429",
        "tgn:1000001",
        "tgn:7012149",
        "tgn:1003022",
        "tgn:7007252",
        "tgn:7029392"
    ],
    "tgn:id":2031429,
    "tgn:name":"Collins",
    "tgn:placetype":[
        "aat:300008347"
    ]
},
  "bbox": [],
  "geometry": {"coordinates":[-85.3833,41.1833],"type":"Point"}
}