{
  "id": 1095460,
  "type": "Feature",
  "properties": {
    "tgn:hierarchy":[
        "tgn:1095460",
        "tgn:7001242",
        "tgn:7016833",
        "tgn:1001088",
        "tgn:7029392"
    ],
    "tgn:id":1095460,
    "tgn:name":"Dayr Jabal A\u1e6d \u1e6cayr",
    "tgn:placetype":[
        "aat:300008347"
    ]
},
  "bbox": [],
  "geometry": {"coordinates":[30.752629,28.282421],"type":"Point"}
}