{
  "id": 7288846,
  "type": "Feature",
  "properties": {
    "tgn:hierarchy":[
        "tgn:7288846",
        "tgn:7002464",
        "tgn:1000049",
        "tgn:1000002",
        "tgn:7029392"
    ],
    "tgn:id":7288846,
    "tgn:name":"Islote",
    "tgn:placetype":[
        "aat:300387033"
    ]
},
  "bbox": [],
  "geometry": {"coordinates":[-69.916667,-20.716667],"type":"Point"}
}