{
  "id": 7446068,
  "type": "Feature",
  "properties": {
    "tgn:hierarchy":[
        "tgn:7446068",
        "tgn:7002444",
        "tgn:1000003",
        "tgn:7008094",
        "tgn:7008591",
        "tgn:7029392"
    ],
    "tgn:id":7446068,
    "tgn:name:en":"Stuley Island",
    "tgn:placetype":[
        "aat:300008791"
    ]
},
  "bbox": [],
  "geometry": {"coordinates":[-7.25,57.183333],"type":"Point"}
}