{
  "id": 7309076,
  "type": "Feature",
  "properties": {
    "tgn:hierarchy":[
        "tgn:7309076",
        "tgn:1001699",
        "tgn:1000049",
        "tgn:1000002",
        "tgn:7029392"
    ],
    "tgn:id":7309076,
    "tgn:name":"Mala, Punta",
    "tgn:placetype":[
        "aat:300386846"
    ]
},
  "bbox": [],
  "geometry": {"coordinates":[-74.234722,-43.405278],"type":"Point"}
}