{
  "id": 2040882,
  "type": "Feature",
  "properties": {
    "tgn:hierarchy":[
        "tgn:2040882",
        "tgn:1000001",
        "tgn:7012149",
        "tgn:2000812",
        "tgn:7007255",
        "tgn:7029392"
    ],
    "tgn:id":2040882,
    "tgn:name":"Potters Fork",
    "tgn:placetype":[
        "aat:300008347",
        "aat:300387210"
    ]
},
  "bbox": [],
  "geometry": {"coordinates":[-82.6667,37.1667],"type":"Point"}
}