{
  "id": 7226828,
  "type": "Feature",
  "properties": {
    "tgn:hierarchy":[
        "tgn:7226828",
        "tgn:7002709",
        "tgn:7002705",
        "tgn:1000003",
        "tgn:1000074",
        "tgn:7029392"
    ],
    "tgn:id":7226828,
    "tgn:name":"Kestr\u00edni",
    "tgn:placetype":[
        "aat:300008347"
    ]
},
  "bbox": [],
  "geometry": {"coordinates":[20.197778,39.556111],"type":"Point"}
}