{
  "id": 7279826,
  "type": "Feature",
  "properties": {
    "tgn:hierarchy":[
        "tgn:7279826",
        "tgn:1001708",
        "tgn:1000049",
        "tgn:1000002",
        "tgn:7029392"
    ],
    "tgn:id":7279826,
    "tgn:name":"Reinoso, Cerro",
    "tgn:placetype":[
        "aat:300008795"
    ]
},
  "bbox": [],
  "geometry": {"coordinates":[-70.616667,-33.216667],"type":"Point"}
}