{
  "id": 2108692,
  "type": "Feature",
  "properties": {
    "tgn:hierarchy":[
        "tgn:2108692",
        "tgn:1000001",
        "tgn:7012149",
        "tgn:2002120",
        "tgn:7007827",
        "tgn:7029392"
    ],
    "tgn:id":2108692,
    "tgn:name":"Axtell",
    "tgn:placetype":[
        "aat:300008347"
    ]
},
  "bbox": [],
  "geometry": {"coordinates":[-111.8167,39.05],"type":"Point"}
}