{
  "id": 2557651,
  "type": "Feature",
  "properties": {
    "tgn:hierarchy":[
        "tgn:2557651",
        "tgn:1000001",
        "tgn:7012149",
        "tgn:2002019",
        "tgn:7007826",
        "tgn:7029392"
    ],
    "tgn:id":2557651,
    "tgn:name":"Old Ranch Spring",
    "tgn:placetype":[
        "aat:300008697"
    ]
},
  "bbox": [],
  "geometry": {"coordinates":[-99.4167,30.35],"type":"Point"}
}