<<<<<<< HEAD
{
  "id": 2700064,
  "type": "Feature",
  "properties": {
    "tgn:hierarchy":[
        "tgn:2700064",
        "tgn:1000001",
        "tgn:2001014",
        "tgn:7012149",
        "tgn:7007521",
        "tgn:7029392"
    ],
    "tgn:id":2700064,
    "tgn:name":"Stump River",
    "tgn:placetype":[
        "aat:300008707"
    ]
},
  "bbox": [],
  "geometry": {"coordinates":[-90.1,48.0333],"type":"Point"}
}
=======
{"geometry":{"type":"Point","coordinates":[-90.100000,48.033300]},"type":"Feature","properties":{"hierarchy":["tgn:2700064","tgn:1000001","tgn:2001014","tgn:7012149","tgn:7007521","tgn:7029392"],"placetype":["aat:300008707"],"id":2700064,"name:xx":"Stump River"}}
>>>>>>> 03f74aca74312dbeaf24d7e61306dd6a786dc3d0
