{
  "id": 2275805,
  "type": "Feature",
  "properties": {
    "tgn:hierarchy":[
        "tgn:2275805",
        "tgn:1000001",
        "tgn:2000782",
        "tgn:7012149",
        "tgn:7007255",
        "tgn:7029392"
    ],
    "tgn:id":2275805,
    "tgn:name":"Dark Hollow",
    "tgn:placetype":[
        "aat:300008761"
    ]
},
  "bbox": [],
  "geometry": {"coordinates":[-83.6667,37.1167],"type":"Point"}
}