{
  "id": 2668331,
  "type": "Feature",
  "properties": {
    "tgn:hierarchy":[
        "tgn:2668331",
        "tgn:1000001",
        "tgn:7012149",
        "tgn:2000286",
        "tgn:7007240",
        "tgn:7029392"
    ],
    "tgn:id":2668331,
    "tgn:name":"Slade",
    "tgn:placetype":[
        "aat:300008347"
    ]
},
  "bbox": [],
  "geometry": {"coordinates":[-82.9833,30.2833],"type":"Point"}
}