{
  "id": 7245273,
  "type": "Feature",
  "properties": {
    "tgn:hierarchy":[
        "tgn:7245273",
        "tgn:7003460",
        "tgn:1000003",
        "tgn:1000063",
        "tgn:4012014",
        "tgn:7029392"
    ],
    "tgn:id":7245273,
    "tgn:name":"Bas Laveu",
    "tgn:placetype":[
        "aat:300008347"
    ]
},
  "bbox": [],
  "geometry": {"coordinates":[5.489449,50.612686],"type":"Point"}
}