{
  "id": 7430703,
  "type": "Feature",
  "properties": {
    "tgn:hierarchy":[
        "tgn:7430703",
        "tgn:1001853",
        "tgn:1000001",
        "tgn:7005560",
        "tgn:7029392"
    ],
    "tgn:id":7430703,
    "tgn:name":"Estaci\u00f3n Arocha",
    "tgn:placetype":[
        "aat:300007783"
    ]
},
  "bbox": [],
  "geometry": {"coordinates":[-102.733333,27.033333],"type":"Point"}
}