{
  "id": 2513984,
  "type": "Feature",
  "properties": {
    "tgn:hierarchy":[
        "tgn:2513984",
        "tgn:1000001",
        "tgn:7012149",
        "tgn:2000930",
        "tgn:7007515",
        "tgn:7029392"
    ],
    "tgn:id":2513984,
    "tgn:name":"Millay Hill",
    "tgn:placetype":[
        "aat:300008798"
    ]
},
  "bbox": [],
  "geometry": {"coordinates":[-70.0833,44.9333],"type":"Point"}
}