{
  "id": 7473662,
  "type": "Feature",
  "properties": {
    "tgn:hierarchy":[
        "tgn:7473662",
        "tgn:1000004",
        "tgn:7001009",
        "tgn:1000141",
        "tgn:7029392"
    ],
    "tgn:id":7473662,
    "tgn:name":"Yingpankou",
    "tgn:placetype":[
        "aat:300008347"
    ]
},
  "bbox": [],
  "geometry": {"coordinates":[120.633333,24.355556],"type":"Point"}
}