{
  "id": 7426951,
  "type": "Feature",
  "properties": {
    "tgn:hierarchy":[
        "tgn:7426951",
        "tgn:1000001",
        "tgn:7005594",
        "tgn:7005560",
        "tgn:7029392"
    ],
    "tgn:id":7426951,
    "tgn:name":"Pinihuan",
    "tgn:placetype":[
        "aat:300008347"
    ]
},
  "bbox": [],
  "geometry": {"coordinates":[-99.566667,21.716667],"type":"Point"}
}