{
  "id": 2473969,
  "type": "Feature",
  "properties": {
    "tgn:hierarchy":[
        "tgn:2473969",
        "tgn:1000001",
        "tgn:7012149",
        "tgn:2001447",
        "tgn:7007566",
        "tgn:7029392"
    ],
    "tgn:id":2473969,
    "tgn:name":"Lower Indian Tank",
    "tgn:placetype":[
        "aat:300006191"
    ]
},
  "bbox": [],
  "geometry": {"coordinates":[-105.3833,33.0667],"type":"Point"}
}