{
  "id": 2696875,
  "type": "Feature",
  "properties": {
    "tgn:hierarchy":[
        "tgn:2696875",
        "tgn:1000001",
        "tgn:7012149",
        "tgn:7007157",
        "tgn:2000189",
        "tgn:7029392"
    ],
    "tgn:id":2696875,
    "tgn:name":"Stones Valley",
    "tgn:placetype":[
        "aat:300008761"
    ]
},
  "bbox": [],
  "geometry": {"coordinates":[-123.2167,41.65],"type":"Point"}
}