{
  "id": 7322563,
  "type": "Feature",
  "properties": {
    "tgn:hierarchy":[
        "tgn:7322563",
        "tgn:7002758",
        "tgn:7002821",
        "tgn:1000003",
        "tgn:1000095",
        "tgn:7029392"
    ],
    "tgn:id":7322563,
    "tgn:name":"San Juan, Arroyo de",
    "tgn:placetype":[
        "aat:300008699"
    ]
},
  "bbox": [],
  "geometry": {"coordinates":[-3.383333,37.133333],"type":"Point"}
}