{
  "id": 2338231,
  "type": "Feature",
  "properties": {
    "tgn:hierarchy":[
        "tgn:2338231",
        "tgn:1000001",
        "tgn:2001704",
        "tgn:7012149",
        "tgn:7007708",
        "tgn:7029392"
    ],
    "tgn:id":2338231,
    "tgn:name":"Fox Rock",
    "tgn:placetype":[
        "aat:300008791"
    ]
},
  "bbox": [],
  "geometry": {"coordinates":[-124.6333,42.7667],"type":"Point"}
}