{
  "id": 7522029,
  "type": "Feature",
  "properties": {
    "tgn:hierarchy":[
        "tgn:7522029",
        "tgn:7001242",
        "tgn:7001311",
        "tgn:7016833",
        "tgn:7029392"
    ],
    "tgn:id":7522029,
    "tgn:name:en":"Ab\u016b N\u0101f\u016bkh, W\u0101d\u012b",
    "tgn:placetype":[
        "aat:300379998"
    ]
},
  "bbox": [],
  "geometry": {"coordinates":[32.113453,26.298162],"type":"Point"}
}