{
  "id": 2536890,
  "type": "Feature",
  "properties": {
    "tgn:hierarchy":[
        "tgn:2536890",
        "tgn:1000001",
        "tgn:7012149",
        "tgn:7007158",
        "tgn:2000247",
        "tgn:7029392"
    ],
    "tgn:id":2536890,
    "tgn:name":"Needle Mountains Peak Eight",
    "tgn:placetype":[
        "aat:300008798"
    ]
},
  "bbox": [],
  "geometry": {"coordinates":[-107.55,37.6667],"type":"Point"}
}