<<<<<<< HEAD
{
  "id": 7476514,
  "type": "Feature",
  "properties": {
    "tgn:hierarchy":[
        "tgn:7476514",
        "tgn:1000004",
        "tgn:7489179",
        "tgn:1000141",
        "tgn:7029392"
    ],
    "tgn:id":7476514,
    "tgn:name":"Sijiusan",
    "tgn:placetype":[
        "aat:300008347"
    ]
},
  "bbox": [],
  "geometry": {"coordinates":[121.741894,24.727444],"type":"Point"}
}
=======
{"geometry":{"type":"Point","coordinates":[121.741894,24.727444]},"type":"Feature","properties":{"hierarchy":["tgn:7476514","tgn:1000004","tgn:7489179","tgn:1000141","tgn:7029392"],"placetype":["aat:300008347"],"id":7476514,"name:xx":"Sijiusan"}}
>>>>>>> 03f74aca74312dbeaf24d7e61306dd6a786dc3d0
