{
  "id": 7230754,
  "type": "Feature",
  "properties": {
    "tgn:hierarchy":[
        "tgn:7230754",
        "tgn:7002680",
        "tgn:7001395",
        "tgn:1000003",
        "tgn:1000074",
        "tgn:7029392"
    ],
    "tgn:id":7230754,
    "tgn:name":"Marmb\u00e1s",
    "tgn:placetype":[
        "aat:300008795"
    ]
},
  "bbox": [],
  "geometry": {"coordinates":[21.966667,38.166667],"type":"Point"}
}