<<<<<<< HEAD
{
  "id": 7473692,
  "type": "Feature",
  "properties": {
    "tgn:hierarchy":[
        "tgn:7473692",
        "tgn:7487020",
        "tgn:1000004",
        "tgn:1000141",
        "tgn:7029392"
    ],
    "tgn:id":7473692,
    "tgn:name":"Yancaikeng",
    "tgn:placetype":[
        "aat:300008347"
    ]
},
  "bbox": [],
  "geometry": {"coordinates":[120.8739,24.6116],"type":"Point"}
}
=======
{"geometry":{"type":"Point","coordinates":[120.873900,24.611600]},"type":"Feature","properties":{"hierarchy":["tgn:7473692","tgn:7487020","tgn:1000004","tgn:1000141","tgn:7029392"],"placetype":["aat:300008347"],"id":7473692,"name:xx":"Yancaikeng"}}
>>>>>>> 03f74aca74312dbeaf24d7e61306dd6a786dc3d0
