{
  "id": 1054438,
  "type": "Feature",
  "properties": {
    "tgn:hierarchy":[
        "tgn:1054438",
        "tgn:1003351",
        "tgn:1000004",
        "tgn:7018214",
        "tgn:7002435",
        "tgn:7029392"
    ],
    "tgn:id":1054438,
    "tgn:name":"Itaka",
    "tgn:placetype":[
        "aat:300008347"
    ]
},
  "bbox": [],
  "geometry": {"coordinates":[118.8333,53.9167],"type":"Point"}
}