{
  "id": 7470019,
  "type": "Feature",
  "properties": {
    "tgn:hierarchy":[
        "tgn:7470019",
        "tgn:7488858",
        "tgn:1000004",
        "tgn:1000141",
        "tgn:7029392"
    ],
    "tgn:id":7470019,
    "tgn:name":"Zhongyuan Li",
    "tgn:placetype":[
        "aat:300387173"
    ]
},
  "bbox": [],
  "geometry": {"coordinates":[120.724831,23.991105],"type":"Point"}
}