{
  "id": 7036164,
  "type": "Feature",
  "properties": {
    "tgn:hierarchy":[
        "tgn:7036164",
        "tgn:7003013",
        "tgn:7003005",
        "tgn:1000003",
        "tgn:1000080",
        "tgn:7029392"
    ],
    "tgn:id":7036164,
    "tgn:name":"Castellammare di Stabia, Rada di",
    "tgn:placetype":[
        "aat:300132316"
    ]
},
  "bbox": [],
  "geometry": {"coordinates":[14.416667,40.716667],"type":"Point"}
}