<<<<<<< HEAD
{
  "id": 7488255,
  "type": "Feature",
  "properties": {
    "tgn:hierarchy":[
        "tgn:7488255",
        "tgn:7487020",
        "tgn:1000004",
        "tgn:1000141",
        "tgn:7029392"
    ],
    "tgn:id":7488255,
    "tgn:name":"Kuanren",
    "tgn:placetype":[
        "aat:300008347"
    ]
},
  "bbox": [],
  "geometry": {"coordinates":[120.840148,24.528418],"type":"Point"}
}
=======
{"geometry":{"type":"Point","coordinates":[120.840148,24.528418]},"type":"Feature","properties":{"hierarchy":["tgn:7488255","tgn:7487020","tgn:1000004","tgn:1000141","tgn:7029392"],"placetype":["aat:300008347"],"id":7488255,"name:xx":"Kuanren"}}
>>>>>>> 03f74aca74312dbeaf24d7e61306dd6a786dc3d0
