{
  "id": 1026140,
  "type": "Feature",
  "properties": {
    "tgn:hierarchy":[
        "tgn:1026140",
        "tgn:7003026",
        "tgn:1000003",
        "tgn:1000062",
        "tgn:7029392"
    ],
    "tgn:id":1026140,
    "tgn:name":"Ternberg",
    "tgn:placetype":[
        "aat:300008347"
    ]
},
  "bbox": [],
  "geometry": {"coordinates":[14.3833,47.95],"type":"Point"}
}