<<<<<<< HEAD
{
  "id": 2150483,
  "type": "Feature",
  "properties": {
    "tgn:hierarchy":[
        "tgn:2150483",
        "tgn:1000001",
        "tgn:7012149",
        "tgn:2000225",
        "tgn:7007158",
        "tgn:7029392"
    ],
    "tgn:id":2150483,
    "tgn:name":"Basin Mountain",
    "tgn:placetype":[
        "aat:300008798"
    ]
},
  "bbox": [],
  "geometry": {"coordinates":[-107.95,37.2],"type":"Point"}
}
=======
{"geometry":{"type":"Point","coordinates":[-107.950000,37.200000]},"type":"Feature","properties":{"hierarchy":["tgn:2150483","tgn:1000001","tgn:7012149","tgn:2000225","tgn:7007158","tgn:7029392"],"placetype":["aat:300008798"],"id":2150483,"name:xx":"Basin Mountain"}}
>>>>>>> 03f74aca74312dbeaf24d7e61306dd6a786dc3d0
