{
  "id": 2504210,
  "type": "Feature",
  "properties": {
    "tgn:hierarchy":[
        "tgn:2504210",
        "tgn:1000001",
        "tgn:2002258",
        "tgn:7012149",
        "tgn:7013961",
        "tgn:7029392"
    ],
    "tgn:id":2504210,
    "tgn:name":"Meadow Run",
    "tgn:placetype":[
        "aat:300008699"
    ]
},
  "bbox": [],
  "geometry": {"coordinates":[-81.1167,38.6833],"type":"Point"}
}