<<<<<<< HEAD
{
  "id": 7058542,
  "type": "Feature",
  "properties": {
    "tgn:hierarchy":[
        "tgn:7058542",
        "tgn:1003478",
        "tgn:1000003",
        "tgn:7003120",
        "tgn:1000080",
        "tgn:7029392"
    ],
    "tgn:id":7058542,
    "tgn:name":"Borgone",
    "tgn:placetype":[
        "aat:300008347"
    ]
},
  "bbox": [],
  "geometry": {"coordinates":[8.066667,45.966667],"type":"Point"}
}
=======
{"geometry":{"type":"Point","coordinates":[8.066667,45.966667]},"type":"Feature","properties":{"hierarchy":["tgn:7058542","tgn:1003478","tgn:1000003","tgn:7003120","tgn:1000080","tgn:7029392"],"placetype":["aat:300008347"],"id":7058542,"name:xx":"Borgone"}}
>>>>>>> 03f74aca74312dbeaf24d7e61306dd6a786dc3d0
