{
  "id": 2635715,
  "type": "Feature",
  "properties": {
    "tgn:hierarchy":[
        "tgn:2635715",
        "tgn:1000001",
        "tgn:7012149",
        "tgn:2002066",
        "tgn:7007826",
        "tgn:7029392"
    ],
    "tgn:id":2635715,
    "tgn:name":"Sabine National Forest",
    "tgn:placetype":[
        "aat:300008863"
    ]
},
  "bbox": [],
  "geometry": {"coordinates":[-93.8833,31.5333],"type":"Point"}
}