<<<<<<< HEAD
{
  "id": 7356012,
  "type": "Feature",
  "properties": {
    "tgn:hierarchy":[
        "tgn:7356012",
        "tgn:1000001",
        "tgn:7005599",
        "tgn:7005560",
        "tgn:7029392"
    ],
    "tgn:id":7356012,
    "tgn:name":"C\u00e1rdenas",
    "tgn:placetype":[
        "aat:300007783"
    ]
},
  "bbox": [],
  "geometry": {"coordinates":[-94.15,17.883333],"type":"Point"}
}
=======
{"geometry":{"type":"Point","coordinates":[-94.150000,17.883333]},"type":"Feature","properties":{"hierarchy":["tgn:7356012","tgn:1000001","tgn:7005599","tgn:7005560","tgn:7029392"],"placetype":["aat:300007783"],"id":7356012,"name:xx":"C\u00e1rdenas"}}
>>>>>>> 03f74aca74312dbeaf24d7e61306dd6a786dc3d0
