{
  "id": 7356012,
  "type": "Feature",
  "properties": {
    "tgn:hierarchy":[
        "tgn:7356012",
        "tgn:1000001",
        "tgn:7005599",
        "tgn:7005560",
        "tgn:7029392"
    ],
    "tgn:id":7356012,
    "tgn:name":"C\u00e1rdenas",
    "tgn:placetype":[
        "aat:300007783"
    ]
},
  "bbox": [],
  "geometry": {"coordinates":[-94.15,17.883333],"type":"Point"}
}