<<<<<<< HEAD
{
  "id": 2154712,
  "type": "Feature",
  "properties": {
    "tgn:hierarchy":[
        "tgn:2154712",
        "tgn:1000001",
        "tgn:7012149",
        "tgn:2001291",
        "tgn:7007524",
        "tgn:7029392"
    ],
    "tgn:id":2154712,
    "tgn:name":"Bear Gulch",
    "tgn:placetype":[
        "aat:300008761"
    ]
},
  "bbox": [],
  "geometry": {"coordinates":[-113.8667,46.8167],"type":"Point"}
}
=======
{"geometry":{"type":"Point","coordinates":[-113.866700,46.816700]},"type":"Feature","properties":{"hierarchy":["tgn:2154712","tgn:1000001","tgn:7012149","tgn:2001291","tgn:7007524","tgn:7029392"],"placetype":["aat:300008761"],"id":2154712,"name:xx":"Bear Gulch"}}
>>>>>>> 03f74aca74312dbeaf24d7e61306dd6a786dc3d0
