{
  "id": 7458605,
  "type": "Feature",
  "properties": {
    "tgn:hierarchy":[
        "tgn:7458605",
        "tgn:7002445",
        "tgn:1000003",
        "tgn:7008174",
        "tgn:7008591",
        "tgn:7029392"
    ],
    "tgn:id":7458605,
    "tgn:name:en":"Milwich",
    "tgn:placetype":[
        "aat:300008347"
    ]
},
  "bbox": [],
  "geometry": {"coordinates":[-2.05,52.883333],"type":"Point"}
}