{
  "id": 2259244,
  "type": "Feature",
  "properties": {
    "tgn:hierarchy":[
        "tgn:2259244",
        "tgn:1000001",
        "tgn:7012149",
        "tgn:2000230",
        "tgn:7007158",
        "tgn:7029392"
    ],
    "tgn:id":2259244,
    "tgn:name":"Cottonwood Lake Number 2",
    "tgn:placetype":[
        "aat:300006191"
    ]
},
  "bbox": [],
  "geometry": {"coordinates":[-107.9833,39.0667],"type":"Point"}
}