{
  "id": 2787176,
  "type": "Feature",
  "properties": {
    "tgn:hierarchy":[
        "tgn:2787176",
        "tgn:1000001",
        "tgn:7012149",
        "tgn:2002383",
        "tgn:7007923",
        "tgn:7029392"
    ],
    "tgn:id":2787176,
    "tgn:name":"Zirkel Mesa",
    "tgn:placetype":[
        "aat:300008798"
    ]
},
  "bbox": [],
  "geometry": {"coordinates":[-108.9167,41.7833],"type":"Point"}
}