{
  "id": 7208801,
  "type": "Feature",
  "properties": {
    "tgn:hierarchy":[
        "tgn:7208801",
        "tgn:1000003",
        "tgn:7003677",
        "tgn:7000084",
        "tgn:7029392"
    ],
    "tgn:id":7208801,
    "tgn:name":"Bertasee",
    "tgn:placetype":[
        "aat:300008680"
    ]
},
  "bbox": [],
  "geometry": {"coordinates":[6.783333,51.416667],"type":"Point"}
}