{
  "id": 2113506,
  "type": "Feature",
  "properties": {
    "tgn:hierarchy":[
        "tgn:2113506",
        "tgn:1000001",
        "tgn:2002152",
        "tgn:7012149",
        "tgn:7007919",
        "tgn:7029392"
    ],
    "tgn:id":2113506,
    "tgn:name":"Ontario",
    "tgn:placetype":[
        "aat:300008347"
    ]
},
  "bbox": [],
  "geometry": {"coordinates":[-78.4833,36.9833],"type":"Point"}
}