{
  "id": 1106743,
  "type": "Feature",
  "properties": {
    "tgn:hierarchy":[
        "tgn:1106743",
        "tgn:7006450",
        "tgn:1000001",
        "tgn:7012149",
        "tgn:2124005",
        "tgn:7029392"
    ],
    "tgn:id":1106743,
    "tgn:name":"Tingmerkpuk Mountain",
    "tgn:placetype":[
        "aat:300008795"
    ]
},
  "bbox": [],
  "geometry": {"coordinates":[-162.45,68.55],"type":"Point"}
}