{
  "id": 2217663,
  "type": "Feature",
  "properties": {
    "tgn:hierarchy":[
        "tgn:2217663",
        "tgn:7013272",
        "tgn:1000001",
        "tgn:7012149",
        "tgn:7007710",
        "tgn:7029392"
    ],
    "tgn:id":2217663,
    "tgn:name":"Campbell Lake",
    "tgn:placetype":[
        "aat:300006191"
    ]
},
  "bbox": [],
  "geometry": {"coordinates":[-79.8833,40.5333],"type":"Point"}
}