{
  "id": 2269072,
  "type": "Feature",
  "properties": {
    "tgn:hierarchy":[
        "tgn:2269072",
        "tgn:7002659",
        "tgn:1000001",
        "tgn:7012149",
        "tgn:7029392"
    ],
    "tgn:id":2269072,
    "tgn:name":"Crossway Branch",
    "tgn:placetype":[
        "aat:300008699"
    ]
},
  "bbox": [],
  "geometry": {"coordinates":[-88.1333,34.5333],"type":"Point"}
}