{
  "id": 2270989,
  "type": "Feature",
  "properties": {
    "tgn:hierarchy":[
        "tgn:2270989",
        "tgn:1000001",
        "tgn:7012149",
        "tgn:2000787",
        "tgn:7007255",
        "tgn:7029392"
    ],
    "tgn:id":2270989,
    "tgn:name":"Cubby Cove",
    "tgn:placetype":[
        "aat:300008761"
    ]
},
  "bbox": [],
  "geometry": {"coordinates":[-86.2333,37.25],"type":"Point"}
}