{
  "id": 7265103,
  "type": "Feature",
  "properties": {
    "tgn:hierarchy":[
        "tgn:7265103",
        "tgn:1000003",
        "tgn:7003627",
        "tgn:7016845",
        "tgn:7029392"
    ],
    "tgn:id":7265103,
    "tgn:name:nl":"Huis te Voorne",
    "tgn:placetype":[
        "aat:300008057"
    ]
},
  "bbox": [],
  "geometry": {"coordinates":[5.066667,52.083333],"type":"Point"}
}