{
  "id": 7546005,
  "type": "Feature",
  "properties": {
    "tgn:hierarchy":[
        "tgn:7546005",
        "tgn:1000004",
        "tgn:7000198",
        "tgn:1001882",
        "tgn:7029392"
    ],
    "tgn:id":7546005,
    "tgn:name:en":"Basar\u0101lu",
    "tgn:placetype":[
        "aat:300008347"
    ]
},
  "bbox": [],
  "geometry": {"coordinates":[76.817222,12.706389],"type":"Point"}
}