<<<<<<< HEAD
{
  "id": 7361517,
  "type": "Feature",
  "properties": {
    "tgn:hierarchy":[
        "tgn:7361517",
        "tgn:1000001",
        "tgn:7005589",
        "tgn:7005560",
        "tgn:7029392"
    ],
    "tgn:id":7361517,
    "tgn:name":"El Coronel",
    "tgn:placetype":[
        "aat:300008347"
    ]
},
  "bbox": [],
  "geometry": {"coordinates":[-99.783333,25.033333],"type":"Point"}
}
=======
{"geometry":{"type":"Point","coordinates":[-99.783333,25.033333]},"type":"Feature","properties":{"hierarchy":["tgn:7361517","tgn:1000001","tgn:7005589","tgn:7005560","tgn:7029392"],"placetype":["aat:300008347"],"id":7361517,"name:xx":"El Coronel"}}
>>>>>>> 03f74aca74312dbeaf24d7e61306dd6a786dc3d0
