{
  "id": 7237798,
  "type": "Feature",
  "properties": {
    "tgn:hierarchy":[
        "tgn:7237798",
        "tgn:7003458",
        "tgn:1000003",
        "tgn:1000063",
        "tgn:7018236",
        "tgn:7029392"
    ],
    "tgn:id":7237798,
    "tgn:name":"Hallebast",
    "tgn:placetype":[
        "aat:300008347"
    ]
},
  "bbox": [],
  "geometry": {"coordinates":[2.818523,50.813777],"type":"Point"}
}