{
  "id": 7313558,
  "type": "Feature",
  "properties": {
    "tgn:hierarchy":[
        "tgn:7313558",
        "tgn:1001637",
        "tgn:1000049",
        "tgn:1000002",
        "tgn:7029392"
    ],
    "tgn:id":7313558,
    "tgn:name":"Llico, Estero",
    "tgn:placetype":[
        "aat:300266554",
        "aat:300008699"
    ]
},
  "bbox": [],
  "geometry": {"coordinates":[-73.566667,-37.183333],"type":"Point"}
}