{
  "id": 6005885,
  "type": "Feature",
  "properties": {
    "tgn:hierarchy":[
        "tgn:6005885",
        "tgn:1000004",
        "tgn:1000118",
        "tgn:1001441",
        "tgn:7029392"
    ],
    "tgn:id":6005885,
    "tgn:name":"Tepe Gawra",
    "tgn:placetype":[
        "aat:300008347",
        "aat:300000810",
        "aat:300167671"
    ]
},
  "bbox": [],
  "geometry": {"coordinates":[43.2333,36.5167],"type":"Point"}
}