{
  "id": 7228861,
  "type": "Feature",
  "properties": {
    "tgn:hierarchy":[
        "tgn:7228861",
        "tgn:7002690",
        "tgn:7012056",
        "tgn:1000003",
        "tgn:1000074",
        "tgn:7029392"
    ],
    "tgn:id":7228861,
    "tgn:name":"Gar\u00edpa",
    "tgn:placetype":[
        "aat:300008347"
    ]
},
  "bbox": [],
  "geometry": {"coordinates":[23.983333,35.466667],"type":"Point"}
}