{
  "id": 2368607,
  "type": "Feature",
  "properties": {
    "tgn:hierarchy":[
        "tgn:2368607",
        "tgn:7002659",
        "tgn:1000001",
        "tgn:7012149",
        "tgn:2000057",
        "tgn:7029392"
    ],
    "tgn:id":2368607,
    "tgn:name":"Gulf Hollow",
    "tgn:placetype":[
        "aat:300008761"
    ]
},
  "bbox": [],
  "geometry": {"coordinates":[-86.2667,33.7333],"type":"Point"}
}