{
  "id": 7054725,
  "type": "Feature",
  "properties": {
    "tgn:hierarchy":[
        "tgn:7054725",
        "tgn:7003170",
        "tgn:1000003",
        "tgn:7003125",
        "tgn:1000080",
        "tgn:7029392"
    ],
    "tgn:id":7054725,
    "tgn:name":"Paganelli",
    "tgn:placetype":[
        "aat:300008347"
    ]
},
  "bbox": [],
  "geometry": {"coordinates":[13.116667,42.733333],"type":"Point"}
}