{
  "id": 7265528,
  "type": "Feature",
  "properties": {
    "tgn:concordances":{
        "gn:id":"2752057"
    },
    "tgn:hierarchy":[
        "tgn:7265528",
        "tgn:1000003",
        "tgn:7003624",
        "tgn:7016845",
        "tgn:7029392"
    ],
    "tgn:id":7265528,
    "tgn:name:nl":"Lage Berkt",
    "tgn:placetype":[
        "aat:300008347"
    ]
},
  "bbox": [],
  "geometry": {"coordinates":[5.333333,51.316667],"type":"Point"}
}