{
  "id": 2740504,
  "type": "Feature",
  "properties": {
    "tgn:hierarchy":[
        "tgn:2740504",
        "tgn:1000001",
        "tgn:7012149",
        "tgn:1002943",
        "tgn:7007708",
        "tgn:7029392"
    ],
    "tgn:id":2740504,
    "tgn:name":"Upper Nehalem",
    "tgn:placetype":[
        "aat:300008347"
    ]
},
  "bbox": [],
  "geometry": {"coordinates":[-123.8667,45.7333],"type":"Point"}
}