{
  "id": 2608454,
  "type": "Feature",
  "properties": {
    "tgn:hierarchy":[
        "tgn:2608454",
        "tgn:1000001",
        "tgn:7012149",
        "tgn:2001706",
        "tgn:7007708",
        "tgn:7029392"
    ],
    "tgn:id":2608454,
    "tgn:name":"Rattlesnake Gulch Reservoir",
    "tgn:placetype":[
        "aat:300006191"
    ]
},
  "bbox": [],
  "geometry": {"coordinates":[-123.5167,43.5833],"type":"Point"}
}