{
  "id": 1139655,
  "type": "Feature",
  "properties": {
    "tgn:hierarchy":[
        "tgn:1139655",
        "tgn:1000004",
        "tgn:7002087",
        "tgn:1000111",
        "tgn:7029392"
    ],
    "tgn:id":1139655,
    "tgn:name":"Suining",
    "tgn:placetype":[
        "aat:300008347"
    ]
},
  "bbox": [],
  "geometry": {"coordinates":[105.55,30.5167],"type":"Point"}
}