{
  "id": 2081769,
  "type": "Feature",
  "properties": {
    "tgn:hierarchy":[
        "tgn:2081769",
        "tgn:1002159",
        "tgn:1000001",
        "tgn:7012149",
        "tgn:7007706",
        "tgn:7029392"
    ],
    "tgn:id":2081769,
    "tgn:name":"Santa Fe",
    "tgn:placetype":[
        "aat:300008347"
    ]
},
  "bbox": [],
  "geometry": {"coordinates":[-83.9833,40.4833],"type":"Point"}
}