{
  "id": 2063116,
  "type": "Feature",
  "properties": {
    "tgn:hierarchy":[
        "tgn:2063116",
        "tgn:1000001",
        "tgn:7012149",
        "tgn:2001420",
        "tgn:7007526",
        "tgn:7029392"
    ],
    "tgn:id":2063116,
    "tgn:name":"Ruth",
    "tgn:placetype":[
        "aat:300008347"
    ]
},
  "bbox": [],
  "geometry": {"coordinates":[-114.9833,39.2667],"type":"Point"}
}