{
  "id": 7072905,
  "type": "Feature",
  "properties": {
    "tgn:hierarchy":[
        "tgn:7072905",
        "tgn:1000003",
        "tgn:7000094",
        "tgn:7000084",
        "tgn:7029392"
    ],
    "tgn:id":7072905,
    "tgn:name":"Tannenort",
    "tgn:placetype":[
        "aat:300008347"
    ]
},
  "bbox": [],
  "geometry": {"coordinates":[13.316667,54.25],"type":"Point"}
}