{
  "id": 1053568,
  "type": "Feature",
  "properties": {
    "tgn:hierarchy":[
        "tgn:1053568",
        "tgn:1000004",
        "tgn:7011599",
        "tgn:7018214",
        "tgn:7002435",
        "tgn:7029392"
    ],
    "tgn:id":1053568,
    "tgn:name":"Demidov",
    "tgn:placetype":[
        "aat:300008347"
    ]
},
  "bbox": [],
  "geometry": {"coordinates":[31.5167,55.2667],"type":"Point"}
}