{
  "id": 7147504,
  "type": "Feature",
  "properties": {
    "tgn:hierarchy":[
        "tgn:7147504",
        "tgn:7003669",
        "tgn:1000003",
        "tgn:7000084",
        "tgn:7029392"
    ],
    "tgn:id":7147504,
    "tgn:name":"Kufberg",
    "tgn:placetype":[
        "aat:300000206"
    ]
},
  "bbox": [],
  "geometry": {"coordinates":[12.216667,49.066667],"type":"Point"}
}