{
  "id": 2205068,
  "type": "Feature",
  "properties": {
    "tgn:hierarchy":[
        "tgn:2205068",
        "tgn:7030516",
        "tgn:7006450",
        "tgn:1000001",
        "tgn:7012149",
        "tgn:7029392"
    ],
    "tgn:id":2205068,
    "tgn:name":"Bugle Point",
    "tgn:placetype":[
        "aat:300008850"
    ]
},
  "bbox": [],
  "geometry": {"coordinates":[-175.9667,52.0333],"type":"Point"}
}