{
  "id": 7343879,
  "type": "Feature",
  "properties": {
    "tgn:hierarchy":[
        "tgn:7343879",
        "tgn:7002836",
        "tgn:7016622",
        "tgn:1000003",
        "tgn:1000095",
        "tgn:7029392"
    ],
    "tgn:id":7343879,
    "tgn:name":"Cabras, Pico de las",
    "tgn:placetype":[
        "aat:300008798"
    ]
},
  "bbox": [],
  "geometry": {"coordinates":[-16.633333,28.283333],"type":"Point"}
}