{
  "id": 7431577,
  "type": "Feature",
  "properties": {
    "tgn:hierarchy":[
        "tgn:7431577",
        "tgn:7005586",
        "tgn:1000001",
        "tgn:7005560",
        "tgn:7029392"
    ],
    "tgn:id":7431577,
    "tgn:name":"El Ixtle",
    "tgn:placetype":[
        "aat:300008347"
    ]
},
  "bbox": [],
  "geometry": {"coordinates":[-102.033333,21.283333],"type":"Point"}
}