{
  "id": 2232308,
  "type": "Feature",
  "properties": {
    "tgn:hierarchy":[
        "tgn:2232308",
        "tgn:1000001",
        "tgn:2001742",
        "tgn:7012149",
        "tgn:7007712",
        "tgn:7029392"
    ],
    "tgn:id":2232308,
    "tgn:name":"Chandler Village",
    "tgn:placetype":[
        "aat:300008347"
    ]
},
  "bbox": [],
  "geometry": {"coordinates":[-80.1333,32.9667],"type":"Point"}
}