{
  "id": 7228520,
  "type": "Feature",
  "properties": {
    "tgn:hierarchy":[
        "tgn:7228520",
        "tgn:7002690",
        "tgn:7012056",
        "tgn:1000003",
        "tgn:1000074",
        "tgn:7029392"
    ],
    "tgn:id":7228520,
    "tgn:name":"Glaron\u00edsi, Sk\u00f3pelos",
    "tgn:placetype":[
        "aat:300008808"
    ]
},
  "bbox": [],
  "geometry": {"coordinates":[25.194444,35.4575],"type":"Point"}
}