{
  "id": 1136567,
  "type": "Feature",
  "properties": {
    "tgn:hierarchy":[
        "tgn:1136567",
        "tgn:7006237",
        "tgn:1000047",
        "tgn:7002457",
        "tgn:1000002",
        "tgn:7029392"
    ],
    "tgn:id":1136567,
    "tgn:name":"S\u00e3o Domingos",
    "tgn:placetype":[
        "aat:300008347"
    ]
},
  "bbox": [],
  "geometry": {"coordinates":[-42.7833,-21.6833],"type":"Point"}
}