{
  "id": 2126855,
  "type": "Feature",
  "properties": {
    "tgn:hierarchy":[
        "tgn:2126855",
        "tgn:1000001",
        "tgn:7012149",
        "tgn:7007157",
        "tgn:1002828",
        "tgn:7029392"
    ],
    "tgn:id":2126855,
    "tgn:name":"Agua Caliente Spring",
    "tgn:placetype":[
        "aat:300008697"
    ]
},
  "bbox": [],
  "geometry": {"coordinates":[-116.5333,33.8167],"type":"Point"}
}