{
  "id": 7214962,
  "type": "Feature",
  "properties": {
    "tgn:hierarchy":[
        "tgn:7214962",
        "tgn:7003669",
        "tgn:1000003",
        "tgn:7000084",
        "tgn:7029392"
    ],
    "tgn:id":7214962,
    "tgn:name":"B\u00f6hmhof",
    "tgn:placetype":[
        "aat:300008347"
    ]
},
  "bbox": [],
  "geometry": {"coordinates":[13.116667,49.05],"type":"Point"}
}