<<<<<<< HEAD
{
  "id": 2150735,
  "type": "Feature",
  "properties": {
    "tgn:hierarchy":[
        "tgn:2150735",
        "tgn:1000001",
        "tgn:7012149",
        "tgn:1002918",
        "tgn:7007252",
        "tgn:7029392"
    ],
    "tgn:id":2150735,
    "tgn:name":"Bass Ditch",
    "tgn:placetype":[
        "aat:300006075"
    ]
},
  "bbox": [],
  "geometry": {"coordinates":[-86.9167,41.2],"type":"Point"}
}
=======
{"geometry":{"type":"Point","coordinates":[-86.916700,41.200000]},"type":"Feature","properties":{"hierarchy":["tgn:2150735","tgn:1000001","tgn:7012149","tgn:1002918","tgn:7007252","tgn:7029392"],"placetype":["aat:300006075"],"id":2150735,"name:xx":"Bass Ditch"}}
>>>>>>> 03f74aca74312dbeaf24d7e61306dd6a786dc3d0
