{
  "id": 2630492,
  "type": "Feature",
  "properties": {
    "tgn:hierarchy":[
        "tgn:2630492",
        "tgn:1000001",
        "tgn:7012149",
        "tgn:7007157",
        "tgn:1002748",
        "tgn:7029392"
    ],
    "tgn:id":2630492,
    "tgn:name":"Round Canyon",
    "tgn:placetype":[
        "aat:300008761"
    ]
},
  "bbox": [],
  "geometry": {"coordinates":[-117.6833,33.7167],"type":"Point"}
}