{
  "id": 7017102,
  "type": "Feature",
  "properties": {
    "tgn:hierarchy":[
        "tgn:7017102",
        "tgn:1001945",
        "tgn:1000047",
        "tgn:7002457",
        "tgn:1000002",
        "tgn:7029392"
    ],
    "tgn:id":7017102,
    "tgn:name":"Cotia",
    "tgn:placetype":[
        "aat:300008347",
        "aat:300000874",
        "aat:300008375"
    ]
},
  "bbox": [],
  "geometry": {"coordinates":[-46.9333,-23.6167],"type":"Point"}
}