{
  "id": 2741069,
  "type": "Feature",
  "properties": {
    "tgn:hierarchy":[
        "tgn:2741069",
        "tgn:1000001",
        "tgn:2001417",
        "tgn:7012149",
        "tgn:7007526",
        "tgn:7029392"
    ],
    "tgn:id":2741069,
    "tgn:name":"Upper Summit Spring",
    "tgn:placetype":[
        "aat:300008697"
    ]
},
  "bbox": [],
  "geometry": {"coordinates":[-117.9167,38.3167],"type":"Point"}
}