{
  "id": 7588932,
  "type": "Feature",
  "properties": {
    "tgn:hierarchy":[
        "tgn:7588932",
        "tgn:1000004",
        "tgn:7000198",
        "tgn:7000799",
        "tgn:7029392"
    ],
    "tgn:id":7588932,
    "tgn:name:en":"Salan",
    "tgn:placetype":[
        "aat:300008347"
    ]
},
  "bbox": [],
  "geometry": {"coordinates":[74.088889,33.697222],"type":"Point"}
}