{
  "id": 7446627,
  "type": "Feature",
  "properties": {
    "tgn:hierarchy":[
        "tgn:7446627",
        "tgn:7002445",
        "tgn:1000003",
        "tgn:7012077",
        "tgn:7008591",
        "tgn:7029392"
    ],
    "tgn:id":7446627,
    "tgn:name:en":"Slapton Sands",
    "tgn:placetype":[
        "aat:300008816"
    ]
},
  "bbox": [],
  "geometry": {"coordinates":[-3.633333,50.283333],"type":"Point"}
}