{
  "id": 2328817,
  "type": "Feature",
  "properties": {
    "tgn:hierarchy":[
        "tgn:2328817",
        "tgn:1000001",
        "tgn:7012149",
        "tgn:2001553",
        "tgn:7007709",
        "tgn:7029392"
    ],
    "tgn:id":2328817,
    "tgn:name":"Fishing Creek",
    "tgn:placetype":[
        "aat:300008706"
    ]
},
  "bbox": [],
  "geometry": {"coordinates":[-81.0333,36.1167],"type":"Point"}
}