{
  "id": 7297020,
  "type": "Feature",
  "properties": {
    "tgn:hierarchy":[
        "tgn:7297020",
        "tgn:7001122",
        "tgn:1000003",
        "tgn:7002765",
        "tgn:1000095",
        "tgn:7029392"
    ],
    "tgn:id":7297020,
    "tgn:name":"Toro, Isla del",
    "tgn:placetype":[
        "aat:300008791"
    ]
},
  "bbox": [],
  "geometry": {"coordinates":[2.483333,39.466667],"type":"Point"}
}