<<<<<<< HEAD
{
  "id": 2250040,
  "type": "Feature",
  "properties": {
    "tgn:hierarchy":[
        "tgn:2250040",
        "tgn:1000001",
        "tgn:7012149",
        "tgn:7022542",
        "tgn:7007825",
        "tgn:7029392"
    ],
    "tgn:id":2250040,
    "tgn:name":"Collins Branch",
    "tgn:placetype":[
        "aat:300008699"
    ]
},
  "bbox": [],
  "geometry": {"coordinates":[-84.6833,35.5333],"type":"Point"}
}
=======
{"geometry":{"type":"Point","coordinates":[-84.683300,35.533300]},"type":"Feature","properties":{"hierarchy":["tgn:2250040","tgn:1000001","tgn:7012149","tgn:7022542","tgn:7007825","tgn:7029392"],"placetype":["aat:300008699"],"id":2250040,"name:xx":"Collins Branch"}}
>>>>>>> 03f74aca74312dbeaf24d7e61306dd6a786dc3d0
