{
  "id": 2577017,
  "type": "Feature",
  "properties": {
    "tgn:hierarchy":[
        "tgn:2577017",
        "tgn:1000001",
        "tgn:7012149",
        "tgn:2001207",
        "tgn:7007523",
        "tgn:7029392"
    ],
    "tgn:id":2577017,
    "tgn:name":"Peter Cave Number 1",
    "tgn:placetype":[
        "aat:300008746"
    ]
},
  "bbox": [],
  "geometry": {"coordinates":[-90.9167,37.6333],"type":"Point"}
}