{
  "id": 7290326,
  "type": "Feature",
  "properties": {
    "tgn:hierarchy":[
        "tgn:7290326",
        "tgn:1001702",
        "tgn:1000049",
        "tgn:1000002",
        "tgn:7029392"
    ],
    "tgn:id":7290326,
    "tgn:name":"Do\u00f1a Ana, Estero",
    "tgn:placetype":[
        "aat:300008676"
    ]
},
  "bbox": [],
  "geometry": {"coordinates":[-75.083333,-49.333333],"type":"Point"}
}