{
  "id": 2605659,
  "type": "Feature",
  "properties": {
    "tgn:hierarchy":[
        "tgn:2605659",
        "tgn:1000001",
        "tgn:7012149",
        "tgn:2002112",
        "tgn:7007827",
        "tgn:7029392"
    ],
    "tgn:id":2605659,
    "tgn:name":"Railroad Springs",
    "tgn:placetype":[
        "aat:300008697"
    ]
},
  "bbox": [],
  "geometry": {"coordinates":[-112.1667,39.7833],"type":"Point"}
}