{
  "id": 2000832,
  "type": "Feature",
  "properties": {
    "tgn:hierarchy":[
        "tgn:2000832",
        "tgn:1000001",
        "tgn:7012149",
        "tgn:7007255",
        "tgn:7029392"
    ],
    "tgn:id":2000832,
    "tgn:name":"Muhlenberg",
    "tgn:placetype":[
        "aat:300387145",
        "aat:300000771"
    ]
},
  "bbox": [],
  "geometry": {"coordinates":[-87.15,37.2167],"type":"Point"}
}