{
  "id": 2431830,
  "type": "Feature",
  "properties": {
    "tgn:hierarchy":[
        "tgn:2431830",
        "tgn:1000001",
        "tgn:7012149",
        "tgn:7007250",
        "tgn:7029392"
    ],
    "tgn:id":2431830,
    "tgn:name":"Kauder Creek",
    "tgn:placetype":[
        "aat:300008706"
    ]
},
  "bbox": [],
  "geometry": {"coordinates":[-116.3833,46.6333],"type":"Point"}
}