{
  "id": 7323090,
  "type": "Feature",
  "properties": {
    "tgn:hierarchy":[
        "tgn:7323090",
        "tgn:7002826",
        "tgn:7001158",
        "tgn:1000003",
        "tgn:1000095",
        "tgn:7029392"
    ],
    "tgn:id":7323090,
    "tgn:name":"Ruitel\u00e1n",
    "tgn:placetype":[
        "aat:300008347"
    ]
},
  "bbox": [],
  "geometry": {"coordinates":[-6.966667,42.666667],"type":"Point"}
}