{
  "id": 7228058,
  "type": "Feature",
  "properties": {
    "tgn:hierarchy":[
        "tgn:7228058",
        "tgn:7002715",
        "tgn:7002731",
        "tgn:1000003",
        "tgn:1000074",
        "tgn:7029392"
    ],
    "tgn:id":7228058,
    "tgn:name":"Kastri\u00e1",
    "tgn:placetype":[
        "aat:300008777"
    ]
},
  "bbox": [],
  "geometry": {"coordinates":[23.383333,40.383333],"type":"Point"}
}