{
  "id": 7246253,
  "type": "Feature",
  "properties": {
    "tgn:hierarchy":[
        "tgn:7246253",
        "tgn:7003460",
        "tgn:1000003",
        "tgn:1000063",
        "tgn:4012014",
        "tgn:7029392"
    ],
    "tgn:id":7246253,
    "tgn:name":"Borgoumont",
    "tgn:placetype":[
        "aat:300008347"
    ]
},
  "bbox": [],
  "geometry": {"coordinates":[5.85,50.416667],"type":"Point"}
}