<<<<<<< HEAD
{
  "id": 2159684,
  "type": "Feature",
  "properties": {
    "tgn:hierarchy":[
        "tgn:2159684",
        "tgn:1000001",
        "tgn:2002242",
        "tgn:7012149",
        "tgn:7007920",
        "tgn:7029392"
    ],
    "tgn:id":2159684,
    "tgn:name":"Beebe",
    "tgn:placetype":[
        "aat:300008347"
    ]
},
  "bbox": [],
  "geometry": {"coordinates":[-119.9333,47.8333],"type":"Point"}
}
=======
{"geometry":{"type":"Point","coordinates":[-119.933300,47.833300]},"type":"Feature","properties":{"hierarchy":["tgn:2159684","tgn:1000001","tgn:2002242","tgn:7012149","tgn:7007920","tgn:7029392"],"placetype":["aat:300008347"],"id":2159684,"name:xx":"Beebe"}}
>>>>>>> 03f74aca74312dbeaf24d7e61306dd6a786dc3d0
