{
  "id": 2343392,
  "type": "Feature",
  "properties": {
    "tgn:hierarchy":[
        "tgn:2343392",
        "tgn:1000001",
        "tgn:2001092",
        "tgn:7012149",
        "tgn:7007522",
        "tgn:7029392"
    ],
    "tgn:id":2343392,
    "tgn:name":"Gaines Creek",
    "tgn:placetype":[
        "aat:300008706"
    ]
},
  "bbox": [],
  "geometry": {"coordinates":[-89.45,33.8667],"type":"Point"}
}