{
  "id": 7121379,
  "type": "Feature",
  "properties": {
    "tgn:hierarchy":[
        "tgn:7121379",
        "tgn:7000096",
        "tgn:1000003",
        "tgn:7000084",
        "tgn:7029392"
    ],
    "tgn:id":7121379,
    "tgn:name":"Pitschen",
    "tgn:placetype":[
        "aat:300008347"
    ]
},
  "bbox": [],
  "geometry": {"coordinates":[13.583333,51.866667],"type":"Point"}
}