{
  "id": 2165163,
  "type": "Feature",
  "properties": {
    "tgn:hierarchy":[
        "tgn:2165163",
        "tgn:1000001",
        "tgn:7016172",
        "tgn:2000119",
        "tgn:7012149",
        "tgn:7029392"
    ],
    "tgn:id":2165163,
    "tgn:name":"Bethlehem",
    "tgn:placetype":[
        "aat:300008347"
    ]
},
  "bbox": [],
  "geometry": {"coordinates":[-92.5833,35.2833],"type":"Point"}
}