<<<<<<< HEAD
{
  "id": 2155993,
  "type": "Feature",
  "properties": {
    "tgn:hierarchy":[
        "tgn:2155993",
        "tgn:1000001",
        "tgn:7012149",
        "tgn:7007157",
        "tgn:2000188",
        "tgn:7029392"
    ],
    "tgn:id":2155993,
    "tgn:name":"Bear Wallow Gulch",
    "tgn:placetype":[
        "aat:300008761"
    ]
},
  "bbox": [],
  "geometry": {"coordinates":[-122.8,40.4667],"type":"Point"}
}
=======
{"geometry":{"type":"Point","coordinates":[-122.800000,40.466700]},"type":"Feature","properties":{"hierarchy":["tgn:2155993","tgn:1000001","tgn:7012149","tgn:7007157","tgn:2000188","tgn:7029392"],"placetype":["aat:300008761"],"id":2155993,"name:xx":"Bear Wallow Gulch"}}
>>>>>>> 03f74aca74312dbeaf24d7e61306dd6a786dc3d0
