{
  "id": 7366514,
  "type": "Feature",
  "properties": {
    "tgn:hierarchy":[
        "tgn:7366514",
        "tgn:7005581",
        "tgn:1000001",
        "tgn:7005560",
        "tgn:7029392"
    ],
    "tgn:id":7366514,
    "tgn:name":"El Pinal",
    "tgn:placetype":[
        "aat:300008347"
    ]
},
  "bbox": [],
  "geometry": {"coordinates":[-107.783333,26.633333],"type":"Point"}
}