{
  "id": 2419983,
  "type": "Feature",
  "properties": {
    "tgn:hierarchy":[
        "tgn:2419983",
        "tgn:1000001",
        "tgn:7016172",
        "tgn:2000122",
        "tgn:7012149",
        "tgn:7029392"
    ],
    "tgn:id":2419983,
    "tgn:name":"Jeanette",
    "tgn:placetype":[
        "aat:300008347"
    ]
},
  "bbox": [],
  "geometry": {"coordinates":[-90.4167,35.1667],"type":"Point"}
}