{
  "id": 7236139,
  "type": "Feature",
  "properties": {
    "tgn:hierarchy":[
        "tgn:7236139",
        "tgn:7002741",
        "tgn:7017076",
        "tgn:1000003",
        "tgn:1000074",
        "tgn:7029392"
    ],
    "tgn:id":7236139,
    "tgn:name":"Eti\u00e1",
    "tgn:placetype":[
        "aat:300008347"
    ]
},
  "bbox": [],
  "geometry": {"coordinates":[22.166667,37.85],"type":"Point"}
}