{
  "id": 2499080,
  "type": "Feature",
  "properties": {
    "tgn:hierarchy":[
        "tgn:2499080",
        "tgn:1000001",
        "tgn:7012149",
        "tgn:2000543",
        "tgn:7007252",
        "tgn:7029392"
    ],
    "tgn:id":2499080,
    "tgn:name":"McCarty Ditch",
    "tgn:placetype":[
        "aat:300006075"
    ]
},
  "bbox": [],
  "geometry": {"coordinates":[-87.6833,38.35],"type":"Point"}
}