<<<<<<< HEAD
{
  "id": 2250398,
  "type": "Feature",
  "properties": {
    "tgn:hierarchy":[
        "tgn:2250398",
        "tgn:1000001",
        "tgn:7012149",
        "tgn:2002377",
        "tgn:7007923",
        "tgn:7029392"
    ],
    "tgn:id":2250398,
    "tgn:name":"Colonel Reservoir",
    "tgn:placetype":[
        "aat:300006191"
    ]
},
  "bbox": [],
  "geometry": {"coordinates":[-106.4333,43.3333],"type":"Point"}
}
=======
{"geometry":{"type":"Point","coordinates":[-106.433300,43.333300]},"type":"Feature","properties":{"hierarchy":["tgn:2250398","tgn:1000001","tgn:7012149","tgn:2002377","tgn:7007923","tgn:7029392"],"placetype":["aat:300006191"],"id":2250398,"name:xx":"Colonel Reservoir"}}
>>>>>>> 03f74aca74312dbeaf24d7e61306dd6a786dc3d0
