{
  "id": 2100261,
  "type": "Feature",
  "properties": {
    "tgn:hierarchy":[
        "tgn:2100261",
        "tgn:1000001",
        "tgn:7012149",
        "tgn:2001886",
        "tgn:7007825",
        "tgn:7029392"
    ],
    "tgn:id":2100261,
    "tgn:name":"Mars Hill",
    "tgn:placetype":[
        "aat:300008347",
        "aat:300387210"
    ]
},
  "bbox": [],
  "geometry": {"coordinates":[-87.2833,35.25],"type":"Point"}
}