{
  "id": 2349732,
  "type": "Feature",
  "properties": {
    "tgn:hierarchy":[
        "tgn:2349732",
        "tgn:2002101",
        "tgn:1000001",
        "tgn:7012149",
        "tgn:7007827",
        "tgn:7029392"
    ],
    "tgn:id":2349732,
    "tgn:name":"Gillies Hill",
    "tgn:placetype":[
        "aat:300008798"
    ]
},
  "bbox": [],
  "geometry": {"coordinates":[-112.65,38.45],"type":"Point"}
}