{
  "id": 2687146,
  "type": "Feature",
  "properties": {
    "tgn:hierarchy":[
        "tgn:2687146",
        "tgn:1000001",
        "tgn:7012149",
        "tgn:2000225",
        "tgn:7007158",
        "tgn:7029392"
    ],
    "tgn:id":2687146,
    "tgn:name":"Spring Hollow",
    "tgn:placetype":[
        "aat:300008761"
    ]
},
  "bbox": [],
  "geometry": {"coordinates":[-108.0667,37.15],"type":"Point"}
}