{
  "id": 7569605,
  "type": "Feature",
  "properties": {
    "tgn:hierarchy":[
        "tgn:7569605",
        "tgn:1000004",
        "tgn:7000198",
        "tgn:7016694",
        "tgn:7029392"
    ],
    "tgn:id":7569605,
    "tgn:name:en":"Machhua Pah\u0101r",
    "tgn:placetype":[
        "aat:300008777"
    ]
},
  "bbox": [],
  "geometry": {"coordinates":[86.780278,21.547222],"type":"Point"}
}