{
  "id": 7232201,
  "type": "Feature",
  "properties": {
    "tgn:hierarchy":[
        "tgn:7232201",
        "tgn:7011270",
        "tgn:7002674",
        "tgn:1000003",
        "tgn:1000074",
        "tgn:7029392"
    ],
    "tgn:id":7232201,
    "tgn:name":"Makr\u00f3nisos, N\u00edsos",
    "tgn:placetype":[
        "aat:300008791"
    ]
},
  "bbox": [],
  "geometry": {"coordinates":[24.121667,37.698611],"type":"Point"}
}