{
  "id": 2228918,
  "type": "Feature",
  "properties": {
    "tgn:hierarchy":[
        "tgn:2228918",
        "tgn:2058307",
        "tgn:1000001",
        "tgn:7012149",
        "tgn:1002517",
        "tgn:7007523",
        "tgn:7029392"
    ],
    "tgn:id":2228918,
    "tgn:name":"Cedar Hill Lake Number 2",
    "tgn:placetype":[
        "aat:300006191"
    ]
},
  "bbox": [],
  "geometry": {"coordinates":[-90.65,38.3167],"type":"Point"}
}