{
  "id": 2151320,
  "type": "Feature",
  "properties": {
    "tgn:hierarchy":[
        "tgn:2151320",
        "tgn:1000001",
        "tgn:7012149",
        "tgn:7007158",
        "tgn:7029392"
    ],
    "tgn:id":2151320,
    "tgn:name":"Bates Gulch",
    "tgn:placetype":[
        "aat:300008761"
    ]
},
  "bbox": [],
  "geometry": {"coordinates":[-105.3833,39.7667],"type":"Point"}
}