{
  "id": 7054423,
  "type": "Feature",
  "properties": {
    "tgn:hierarchy":[
        "tgn:7054423",
        "tgn:7003137",
        "tgn:1000003",
        "tgn:7003080",
        "tgn:1000080",
        "tgn:7029392"
    ],
    "tgn:id":7054423,
    "tgn:name":"Montagliano",
    "tgn:placetype":[
        "aat:300008347"
    ]
},
  "bbox": [],
  "geometry": {"coordinates":[13.016667,42.133333],"type":"Point"}
}