{
  "id": 2387651,
  "type": "Feature",
  "properties": {
    "tgn:hierarchy":[
        "tgn:2387651",
        "tgn:1000001",
        "tgn:7016172",
        "tgn:7012149",
        "tgn:2000174",
        "tgn:7029392"
    ],
    "tgn:id":2387651,
    "tgn:name":"Hibank Creek",
    "tgn:placetype":[
        "aat:300008706"
    ]
},
  "bbox": [],
  "geometry": {"coordinates":[-92.55,33.1667],"type":"Point"}
}