{
  "id": 2762801,
  "type": "Feature",
  "properties": {
    "tgn:hierarchy":[
        "tgn:2762801",
        "tgn:1000001",
        "tgn:7012149",
        "tgn:2001709",
        "tgn:7007708",
        "tgn:7029392"
    ],
    "tgn:id":2762801,
    "tgn:name":"Western Quartz Mine",
    "tgn:placetype":[
        "aat:300000390"
    ]
},
  "bbox": [],
  "geometry": {"coordinates":[-118.55,42.55],"type":"Point"}
}