{
  "id": 2593342,
  "type": "Feature",
  "properties": {
    "tgn:hierarchy":[
        "tgn:2593342",
        "tgn:1000001",
        "tgn:7012149",
        "tgn:7007712",
        "tgn:7029392"
    ],
    "tgn:id":2593342,
    "tgn:name":"Popperdam Creek",
    "tgn:placetype":[
        "aat:300008706"
    ]
},
  "bbox": [],
  "geometry": {"coordinates":[-80.0833,32.9333],"type":"Point"}
}