{
  "id": 7565634,
  "type": "Feature",
  "properties": {
    "tgn:hierarchy":[
        "tgn:7565634",
        "tgn:1000004",
        "tgn:7000198",
        "tgn:1001894",
        "tgn:7029392"
    ],
    "tgn:id":7565634,
    "tgn:name:en":"Chaudhronkhera",
    "tgn:placetype":[
        "aat:300008347"
    ]
},
  "bbox": [],
  "geometry": {"coordinates":[79.20631,24.705707],"type":"Point"}
}