{
  "id": 2012548,
  "type": "Feature",
  "properties": {
    "tgn:hierarchy":[
        "tgn:2012548",
        "tgn:1000001",
        "tgn:7012149",
        "tgn:7007157",
        "tgn:2000184",
        "tgn:7029392"
    ],
    "tgn:id":2012548,
    "tgn:name":"Madeline",
    "tgn:placetype":[
        "aat:300008347"
    ]
},
  "bbox": [],
  "geometry": {"coordinates":[-120.4667,41.05],"type":"Point"}
}