{
  "id": 2184402,
  "type": "Feature",
  "properties": {
    "tgn:hierarchy":[
        "tgn:2184402",
        "tgn:1000001",
        "tgn:2001342",
        "tgn:7012149",
        "tgn:7007525",
        "tgn:7029392"
    ],
    "tgn:id":2184402,
    "tgn:name":"Bobkies Island",
    "tgn:placetype":[
        "aat:300008791"
    ]
},
  "bbox": [],
  "geometry": {"coordinates":[-96.7167,41.4333],"type":"Point"}
}