{
  "id": 7036217,
  "type": "Feature",
  "properties": {
    "tgn:hierarchy":[
        "tgn:7036217",
        "tgn:7002991",
        "tgn:1000003",
        "tgn:7002997",
        "tgn:1000080",
        "tgn:7029392"
    ],
    "tgn:id":7036217,
    "tgn:name":"Pozzale",
    "tgn:placetype":[
        "aat:300008347"
    ]
},
  "bbox": [],
  "geometry": {"coordinates":[12.363611,46.438611],"type":"Point"}
}