{
  "id": 7378878,
  "type": "Feature",
  "properties": {
    "tgn:hierarchy":[
        "tgn:7378878",
        "tgn:7005585",
        "tgn:1000001",
        "tgn:7005560",
        "tgn:7029392"
    ],
    "tgn:id":7378878,
    "tgn:name":"Mexquitl\u00e1n",
    "tgn:placetype":[
        "aat:300008347"
    ]
},
  "bbox": [],
  "geometry": {"coordinates":[-98.816667,18.066667],"type":"Point"}
}