{
  "id": 7560734,
  "type": "Feature",
  "properties": {
    "tgn:hierarchy":[
        "tgn:7560734",
        "tgn:1000004",
        "tgn:7000198",
        "tgn:7016722",
        "tgn:7029392"
    ],
    "tgn:id":7560734,
    "tgn:name:en":"Keshopur",
    "tgn:placetype":[
        "aat:300008347"
    ]
},
  "bbox": [],
  "geometry": {"coordinates":[79.208655,26.899803],"type":"Point"}
}