{
  "id": 2673607,
  "type": "Feature",
  "properties": {
    "tgn:hierarchy":[
        "tgn:2673607",
        "tgn:1000001",
        "tgn:7012149",
        "tgn:2001514",
        "tgn:7007709",
        "tgn:7029392"
    ],
    "tgn:id":2673607,
    "tgn:name":"Snooks Nose",
    "tgn:placetype":[
        "aat:300008798"
    ]
},
  "bbox": [],
  "geometry": {"coordinates":[-82.2167,35.6833],"type":"Point"}
}