{
  "id": 7059634,
  "type": "Feature",
  "properties": {
    "tgn:hierarchy":[
        "tgn:7059634",
        "tgn:7003669",
        "tgn:1000003",
        "tgn:7000084",
        "tgn:7029392"
    ],
    "tgn:id":7059634,
    "tgn:name":"Altensdorf",
    "tgn:placetype":[
        "aat:300008347"
    ]
},
  "bbox": [],
  "geometry": {"coordinates":[12.116667,48.733333],"type":"Point"}
}