{
  "id": 2290046,
  "type": "Feature",
  "properties": {
    "tgn:hierarchy":[
        "tgn:2290046",
        "tgn:1002996",
        "tgn:1000001",
        "tgn:7012149",
        "tgn:7007711",
        "tgn:7029392"
    ],
    "tgn:id":2290046,
    "tgn:name":"Doctor Lewis Pond",
    "tgn:placetype":[
        "aat:300008680"
    ]
},
  "bbox": [],
  "geometry": {"coordinates":[-71.7833,41.3333],"type":"Point"}
}