{
  "id": 7246868,
  "type": "Feature",
  "properties": {
    "tgn:hierarchy":[
        "tgn:7246868",
        "tgn:7003466",
        "tgn:1000003",
        "tgn:1000063",
        "tgn:4012014",
        "tgn:7029392"
    ],
    "tgn:id":7246868,
    "tgn:name":"Bouchaille",
    "tgn:placetype":[
        "aat:300008347"
    ]
},
  "bbox": [],
  "geometry": {"coordinates":[5.033333,50.366667],"type":"Point"}
}