{
  "id": 7073168,
  "type": "Feature",
  "properties": {
    "tgn:hierarchy":[
        "tgn:7073168",
        "tgn:1000003",
        "tgn:7003676",
        "tgn:7000084",
        "tgn:7029392"
    ],
    "tgn:id":7073168,
    "tgn:name":"S\u00fcdmoor",
    "tgn:placetype":[
        "aat:300386886"
    ]
},
  "bbox": [],
  "geometry": {"coordinates":[7.683333,52.75],"type":"Point"}
}