{
  "id": 2200205,
  "type": "Feature",
  "properties": {
    "tgn:hierarchy":[
        "tgn:2200205",
        "tgn:2001728",
        "tgn:1000001",
        "tgn:7012149",
        "tgn:7007712",
        "tgn:7029392"
    ],
    "tgn:id":2200205,
    "tgn:name":"Brushy Creek Watershed 18",
    "tgn:placetype":[
        "aat:300006191"
    ]
},
  "bbox": [],
  "geometry": {"coordinates":[-82.5167,34.7333],"type":"Point"}
}