{
  "id": 7334388,
  "type": "Feature",
  "properties": {
    "tgn:hierarchy":[
        "tgn:7334388",
        "tgn:7002758",
        "tgn:7002817",
        "tgn:1000003",
        "tgn:1000095",
        "tgn:7029392"
    ],
    "tgn:id":7334388,
    "tgn:name":"El Higuer\u00f3n",
    "tgn:placetype":[
        "aat:300008347"
    ]
},
  "bbox": [],
  "geometry": {"coordinates":[-4.833333,37.85],"type":"Point"}
}