{
  "id": 1112384,
  "type": "Feature",
  "properties": {
    "tgn:hierarchy":[
        "tgn:1112384",
        "tgn:1001643",
        "tgn:1000003",
        "tgn:7003122",
        "tgn:1000080",
        "tgn:7029392"
    ],
    "tgn:id":1112384,
    "tgn:name":"Gela, Golfo di",
    "tgn:placetype":[
        "aat:300132315"
    ]
},
  "bbox": [],
  "geometry": {"coordinates":[14.166667,37.05],"type":"Point"}
}