{
  "id": 7357088,
  "type": "Feature",
  "properties": {
    "tgn:hierarchy":[
        "tgn:7357088",
        "tgn:1000001",
        "tgn:1001960",
        "tgn:7005560",
        "tgn:7029392"
    ],
    "tgn:id":7357088,
    "tgn:name":"Carrizal",
    "tgn:placetype":[
        "aat:300008347"
    ]
},
  "bbox": [],
  "geometry": {"coordinates":[-109.05,27.083333],"type":"Point"}
}