{
  "id": 7138821,
  "type": "Feature",
  "properties": {
    "tgn:hierarchy":[
        "tgn:7138821",
        "tgn:1000003",
        "tgn:7003689",
        "tgn:7000084",
        "tgn:7029392"
    ],
    "tgn:id":7138821,
    "tgn:name":"Langer-Berg",
    "tgn:placetype":[
        "aat:300008777"
    ]
},
  "bbox": [],
  "geometry": {"coordinates":[11.166667,50.533333],"type":"Point"}
}