{
  "id": 7221522,
  "type": "Feature",
  "properties": {
    "tgn:hierarchy":[
        "tgn:7221522",
        "tgn:7002715",
        "tgn:7002731",
        "tgn:1000003",
        "tgn:1000074",
        "tgn:7029392"
    ],
    "tgn:id":7221522,
    "tgn:name":"\u00c1gia \u00c1nastas\u00eda",
    "tgn:placetype":[
        "aat:300000641"
    ]
},
  "bbox": [],
  "geometry": {"coordinates":[22.955855,40.401917],"type":"Point"}
}