{
  "id": 1122855,
  "type": "Feature",
  "properties": {
    "tgn:hierarchy":[
        "tgn:1122855",
        "tgn:1000004",
        "tgn:7029379",
        "tgn:7029392"
    ],
    "tgn:id":1122855,
    "tgn:name":"Hunguy Gol",
    "tgn:placetype":[
        "aat:300008707"
    ]
},
  "bbox": [],
  "geometry": {"coordinates":[93.416,48.833],"type":"Point"}
}