{
  "id": 2487380,
  "type": "Feature",
  "properties": {
    "tgn:hierarchy":[
        "tgn:2487380",
        "tgn:1000001",
        "tgn:1002286",
        "tgn:7012149",
        "tgn:7007710",
        "tgn:7029392"
    ],
    "tgn:id":2487380,
    "tgn:name":"Left Branch Puncheon Run",
    "tgn:placetype":[
        "aat:300008699"
    ]
},
  "bbox": [],
  "geometry": {"coordinates":[-77.6833,41.1667],"type":"Point"}
}