{
  "id": 7589195,
  "type": "Feature",
  "properties": {
    "tgn:hierarchy":[
        "tgn:7589195",
        "tgn:1000004",
        "tgn:7000198",
        "tgn:7000799",
        "tgn:7029392"
    ],
    "tgn:id":7589195,
    "tgn:name:en":"Neako",
    "tgn:placetype":[
        "aat:300008347"
    ]
},
  "bbox": [],
  "geometry": {"coordinates":[74.200953,33.4288],"type":"Point"}
}