<<<<<<< HEAD
{
  "id": 2331080,
  "type": "Feature",
  "properties": {
    "tgn:hierarchy":[
        "tgn:2331080",
        "tgn:1000001",
        "tgn:7012149",
        "tgn:2001486",
        "tgn:7007709",
        "tgn:7029392"
    ],
    "tgn:id":2331080,
    "tgn:name":"Flat Swamp",
    "tgn:placetype":[
        "aat:300008699"
    ]
},
  "bbox": [],
  "geometry": {"coordinates":[-77.35,35.25],"type":"Point"}
}
=======
{"geometry":{"type":"Point","coordinates":[-77.350000,35.250000]},"type":"Feature","properties":{"hierarchy":["tgn:2331080","tgn:1000001","tgn:7012149","tgn:2001486","tgn:7007709","tgn:7029392"],"placetype":["aat:300008699"],"id":2331080,"name:xx":"Flat Swamp"}}
>>>>>>> 03f74aca74312dbeaf24d7e61306dd6a786dc3d0
