{
  "id": 2331080,
  "type": "Feature",
  "properties": {
    "tgn:hierarchy":[
        "tgn:2331080",
        "tgn:1000001",
        "tgn:7012149",
        "tgn:2001486",
        "tgn:7007709",
        "tgn:7029392"
    ],
    "tgn:id":2331080,
    "tgn:name":"Flat Swamp",
    "tgn:placetype":[
        "aat:300008699"
    ]
},
  "bbox": [],
  "geometry": {"coordinates":[-77.35,35.25],"type":"Point"}
}