{
  "id": 2282248,
  "type": "Feature",
  "properties": {
    "tgn:hierarchy":[
        "tgn:2282248",
        "tgn:1000001",
        "tgn:7012149",
        "tgn:7029392"
    ],
    "tgn:id":2282248,
    "tgn:name":"Deer Lick Creek",
    "tgn:placetype":[
        "aat:300008706"
    ]
},
  "bbox": [],
  "geometry": {"coordinates":[-94.75,36.4833],"type":"Point"}
}