{
  "id": 2247091,
  "type": "Feature",
  "properties": {
    "tgn:hierarchy":[
        "tgn:2247091",
        "tgn:1000001",
        "tgn:7012149",
        "tgn:2002113",
        "tgn:7007827",
        "tgn:7029392"
    ],
    "tgn:id":2247091,
    "tgn:name":"Cockscomb, The",
    "tgn:placetype":[
        "aat:300266640"
    ]
},
  "bbox": [],
  "geometry": {"coordinates":[-111.8167,37.4833],"type":"Point"}
}