<<<<<<< HEAD
{
  "id": 2157040,
  "type": "Feature",
  "properties": {
    "tgn:hierarchy":[
        "tgn:2157040",
        "tgn:7002659",
        "tgn:1000001",
        "tgn:2000010",
        "tgn:7012149",
        "tgn:7029392"
    ],
    "tgn:id":2157040,
    "tgn:name":"Beaver Branch",
    "tgn:placetype":[
        "aat:300008699"
    ]
},
  "bbox": [],
  "geometry": {"coordinates":[-86.7833,32.6833],"type":"Point"}
}
=======
{"geometry":{"type":"Point","coordinates":[-86.783300,32.683300]},"type":"Feature","properties":{"hierarchy":["tgn:2157040","tgn:7002659","tgn:1000001","tgn:2000010","tgn:7012149","tgn:7029392"],"placetype":["aat:300008699"],"id":2157040,"name:xx":"Beaver Branch"}}
>>>>>>> 03f74aca74312dbeaf24d7e61306dd6a786dc3d0
