<<<<<<< HEAD
{
  "id": 2406265,
  "type": "Feature",
  "properties": {
    "tgn:hierarchy":[
        "tgn:2406265",
        "tgn:1000001",
        "tgn:2001096",
        "tgn:7012149",
        "tgn:7007522",
        "tgn:7029392"
    ],
    "tgn:id":2406265,
    "tgn:name":"Humphreys",
    "tgn:placetype":[
        "aat:300008347"
    ]
},
  "bbox": [],
  "geometry": {"coordinates":[-90.8333,32.0667],"type":"Point"}
}
=======
{"geometry":{"type":"Point","coordinates":[-90.833300,32.066700]},"type":"Feature","properties":{"hierarchy":["tgn:2406265","tgn:1000001","tgn:2001096","tgn:7012149","tgn:7007522","tgn:7029392"],"placetype":["aat:300008347"],"id":2406265,"name:xx":"Humphreys"}}
>>>>>>> 03f74aca74312dbeaf24d7e61306dd6a786dc3d0
