{
  "id": 2041064,
  "type": "Feature",
  "properties": {
    "tgn:hierarchy":[
        "tgn:2041064",
        "tgn:1000001",
        "tgn:7012149",
        "tgn:2000825",
        "tgn:7007255",
        "tgn:7029392"
    ],
    "tgn:id":2041064,
    "tgn:name":"Rock Haven",
    "tgn:placetype":[
        "aat:300008347",
        "aat:300387210"
    ]
},
  "bbox": [],
  "geometry": {"coordinates":[-86.05,37.9333],"type":"Point"}
}