{
  "id": 7195120,
  "type": "Feature",
  "properties": {
    "tgn:hierarchy":[
        "tgn:7195120",
        "tgn:1000003",
        "tgn:7003677",
        "tgn:7000084",
        "tgn:7029392"
    ],
    "tgn:id":7195120,
    "tgn:name":"Dorn",
    "tgn:placetype":[
        "aat:300008347"
    ]
},
  "bbox": [],
  "geometry": {"coordinates":[7.616667,50.983333],"type":"Point"}
}