{
  "id": 2369864,
  "type": "Feature",
  "properties": {
    "tgn:hierarchy":[
        "tgn:2369864",
        "tgn:1000001",
        "tgn:7012149",
        "tgn:7007922",
        "tgn:7029392"
    ],
    "tgn:id":2369864,
    "tgn:name":"Gus Johnson Creek",
    "tgn:placetype":[
        "aat:300008706"
    ]
},
  "bbox": [],
  "geometry": {"coordinates":[-90.0833,45.35],"type":"Point"}
}