{
  "id": 7580339,
  "type": "Feature",
  "properties": {
    "tgn:hierarchy":[
        "tgn:7580339",
        "tgn:1000004",
        "tgn:7000198",
        "tgn:1001895",
        "tgn:7029392"
    ],
    "tgn:id":7580339,
    "tgn:name:en":"Sheva Island",
    "tgn:placetype":[
        "aat:300008791"
    ]
},
  "bbox": [],
  "geometry": {"coordinates":[72.95,18.933333],"type":"Point"}
}