{
  "id": 7133094,
  "type": "Feature",
  "properties": {
    "tgn:hierarchy":[
        "tgn:7133094",
        "tgn:1000003",
        "tgn:7003685",
        "tgn:7000084",
        "tgn:7029392"
    ],
    "tgn:id":7133094,
    "tgn:name":"Mobendorf",
    "tgn:placetype":[
        "aat:300008347"
    ]
},
  "bbox": [],
  "geometry": {"coordinates":[13.183333,50.966667],"type":"Point"}
}