{
  "id": 2555616,
  "type": "Feature",
  "properties": {
    "tgn:hierarchy":[
        "tgn:2555616",
        "tgn:1000001",
        "tgn:7012149",
        "tgn:2000415",
        "tgn:7007248",
        "tgn:7029392"
    ],
    "tgn:id":2555616,
    "tgn:name":"Ogeechee Creek",
    "tgn:placetype":[
        "aat:300008706"
    ]
},
  "bbox": [],
  "geometry": {"coordinates":[-81.7667,32.8333],"type":"Point"}
}