{
  "id": 7074878,
  "type": "Feature",
  "properties": {
    "tgn:hierarchy":[
        "tgn:7074878",
        "tgn:1000003",
        "tgn:7003676",
        "tgn:7000084",
        "tgn:7029392"
    ],
    "tgn:id":7074878,
    "tgn:name":"In den H\u00f6ften",
    "tgn:placetype":[
        "aat:300008347"
    ]
},
  "bbox": [],
  "geometry": {"coordinates":[7.283333,52.666667],"type":"Point"}
}