<<<<<<< HEAD
{
  "id": 2400275,
  "type": "Feature",
  "properties": {
    "tgn:hierarchy":[
        "tgn:2400275",
        "tgn:1000001",
        "tgn:2001414",
        "tgn:7012149",
        "tgn:7007526",
        "tgn:7029392"
    ],
    "tgn:id":2400275,
    "tgn:name":"Horse Creek Spring",
    "tgn:placetype":[
        "aat:300008697"
    ]
},
  "bbox": [],
  "geometry": {"coordinates":[-118.1333,41.8667],"type":"Point"}
}
=======
{"geometry":{"type":"Point","coordinates":[-118.133300,41.866700]},"type":"Feature","properties":{"hierarchy":["tgn:2400275","tgn:1000001","tgn:2001414","tgn:7012149","tgn:7007526","tgn:7029392"],"placetype":["aat:300008697"],"id":2400275,"name:xx":"Horse Creek Spring"}}
>>>>>>> 03f74aca74312dbeaf24d7e61306dd6a786dc3d0
