{
  "id": 7500812,
  "type": "Feature",
  "properties": {
    "tgn:hierarchy":[
        "tgn:7500812",
        "tgn:1000004",
        "tgn:7467799",
        "tgn:1000141",
        "tgn:7029392"
    ],
    "tgn:id":7500812,
    "tgn:name":"Wailiao",
    "tgn:placetype":[
        "aat:300008347"
    ]
},
  "bbox": [],
  "geometry": {"coordinates":[120.5851,24.0666],"type":"Point"}
}