{
  "id": 7551128,
  "type": "Feature",
  "properties": {
    "tgn:hierarchy":[
        "tgn:7551128",
        "tgn:1000004",
        "tgn:7000198",
        "tgn:1001895",
        "tgn:7029392"
    ],
    "tgn:id":7551128,
    "tgn:name:en":"D\u0101puri",
    "tgn:placetype":[
        "aat:300008347"
    ]
},
  "bbox": [],
  "geometry": {"coordinates":[73.816667,18.566667],"type":"Point"}
}