{
  "id": 2271027,
  "type": "Feature",
  "properties": {
    "tgn:hierarchy":[
        "tgn:2271027",
        "tgn:1000001",
        "tgn:7012149",
        "tgn:2001457",
        "tgn:7007566",
        "tgn:7029392"
    ],
    "tgn:id":2271027,
    "tgn:name":"Cuchillas",
    "tgn:placetype":[
        "aat:300266640"
    ]
},
  "bbox": [],
  "geometry": {"coordinates":[-105.4833,36.1667],"type":"Point"}
}