{
  "id": 2582793,
  "type": "Feature",
  "properties": {
    "tgn:hierarchy":[
        "tgn:2582793",
        "tgn:1000001",
        "tgn:7012149",
        "tgn:2000386",
        "tgn:7007248",
        "tgn:7029392"
    ],
    "tgn:id":2582793,
    "tgn:name":"Pine Island",
    "tgn:placetype":[
        "aat:300008791"
    ]
},
  "bbox": [],
  "geometry": {"coordinates":[-81.3833,31.3833],"type":"Point"}
}