{
  "id": 7427767,
  "type": "Feature",
  "properties": {
    "tgn:hierarchy":[
        "tgn:7427767",
        "tgn:7005581",
        "tgn:1000001",
        "tgn:7005560",
        "tgn:7029392"
    ],
    "tgn:id":7427767,
    "tgn:name":"La Herradura",
    "tgn:placetype":[
        "aat:300008347"
    ]
},
  "bbox": [],
  "geometry": {"coordinates":[-104.316667,27.65],"type":"Point"}
}