{
  "id": 2621032,
  "type": "Feature",
  "properties": {
    "tgn:hierarchy":[
        "tgn:2621032",
        "tgn:1000001",
        "tgn:7012149",
        "tgn:2000821",
        "tgn:7007255",
        "tgn:7029392"
    ],
    "tgn:id":2621032,
    "tgn:name":"Road Fork",
    "tgn:placetype":[
        "aat:300008699"
    ]
},
  "bbox": [],
  "geometry": {"coordinates":[-83.0333,37.5833],"type":"Point"}
}