{
  "id": 2779658,
  "type": "Feature",
  "properties": {
    "tgn:hierarchy":[
        "tgn:2779658",
        "tgn:1000001",
        "tgn:2000273",
        "tgn:7012149",
        "tgn:7007240",
        "tgn:7029392"
    ],
    "tgn:id":2779658,
    "tgn:name":"Wolf Pond",
    "tgn:placetype":[
        "aat:300008680"
    ]
},
  "bbox": [],
  "geometry": {"coordinates":[-85.0333,30.8833],"type":"Point"}
}