<<<<<<< HEAD
{
  "id": 7115302,
  "type": "Feature",
  "properties": {
    "tgn:hierarchy":[
        "tgn:7115302",
        "tgn:1000003",
        "tgn:7003688",
        "tgn:7000084",
        "tgn:7029392"
    ],
    "tgn:id":7115302,
    "tgn:name":"Oldenburger Graben",
    "tgn:placetype":[
        "aat:300006075"
    ]
},
  "bbox": [],
  "geometry": {"coordinates":[10.95,54.266667],"type":"Point"}
}
=======
{"geometry":{"type":"Point","coordinates":[10.950000,54.266667]},"type":"Feature","properties":{"hierarchy":["tgn:7115302","tgn:1000003","tgn:7003688","tgn:7000084","tgn:7029392"],"placetype":["aat:300006075"],"id":7115302,"name:xx":"Oldenburger Graben"}}
>>>>>>> 03f74aca74312dbeaf24d7e61306dd6a786dc3d0
