{
  "id": 7115302,
  "type": "Feature",
  "properties": {
    "tgn:hierarchy":[
        "tgn:7115302",
        "tgn:1000003",
        "tgn:7003688",
        "tgn:7000084",
        "tgn:7029392"
    ],
    "tgn:id":7115302,
    "tgn:name":"Oldenburger Graben",
    "tgn:placetype":[
        "aat:300006075"
    ]
},
  "bbox": [],
  "geometry": {"coordinates":[10.95,54.266667],"type":"Point"}
}