<<<<<<< HEAD
{
  "id": 7353355,
  "type": "Feature",
  "properties": {
    "tgn:hierarchy":[
        "tgn:7353355",
        "tgn:7005584",
        "tgn:1000001",
        "tgn:7005560",
        "tgn:7029392"
    ],
    "tgn:id":7353355,
    "tgn:name":"Andocut\u00edn",
    "tgn:placetype":[
        "aat:300007783"
    ]
},
  "bbox": [],
  "geometry": {"coordinates":[-100.85,19.95],"type":"Point"}
}
=======
{"geometry":{"type":"Point","coordinates":[-100.850000,19.950000]},"type":"Feature","properties":{"hierarchy":["tgn:7353355","tgn:7005584","tgn:1000001","tgn:7005560","tgn:7029392"],"placetype":["aat:300007783"],"id":7353355,"name:xx":"Andocut\u00edn"}}
>>>>>>> 03f74aca74312dbeaf24d7e61306dd6a786dc3d0
