<<<<<<< HEAD
{
  "id": 2257615,
  "type": "Feature",
  "properties": {
    "tgn:hierarchy":[
        "tgn:2257615",
        "tgn:2000453",
        "tgn:1000001",
        "tgn:7012149",
        "tgn:7007250",
        "tgn:7029392"
    ],
    "tgn:id":2257615,
    "tgn:name":"Corral Creek",
    "tgn:placetype":[
        "aat:300008706"
    ]
},
  "bbox": [],
  "geometry": {"coordinates":[-116.2,44.6333],"type":"Point"}
}
=======
{"geometry":{"type":"Point","coordinates":[-116.200000,44.633300]},"type":"Feature","properties":{"hierarchy":["tgn:2257615","tgn:2000453","tgn:1000001","tgn:7012149","tgn:7007250","tgn:7029392"],"placetype":["aat:300008706"],"id":2257615,"name:xx":"Corral Creek"}}
>>>>>>> 03f74aca74312dbeaf24d7e61306dd6a786dc3d0
