{
  "id": 7062417,
  "type": "Feature",
  "properties": {
    "tgn:hierarchy":[
        "tgn:7062417",
        "tgn:1000003",
        "tgn:7003677",
        "tgn:7000084",
        "tgn:7029392"
    ],
    "tgn:id":7062417,
    "tgn:name":"Auenheim",
    "tgn:placetype":[
        "aat:300008347"
    ]
},
  "bbox": [],
  "geometry": {"coordinates":[6.65,50.983333],"type":"Point"}
}