{
  "id": 7591898,
  "type": "Feature",
  "properties": {
    "tgn:hierarchy":[
        "tgn:7591898",
        "tgn:1000004",
        "tgn:7000198",
        "tgn:7000799",
        "tgn:7029392"
    ],
    "tgn:id":7591898,
    "tgn:name:en":"Dang\u012b\u0101na",
    "tgn:placetype":[
        "aat:300008347"
    ]
},
  "bbox": [],
  "geometry": {"coordinates":[74.863889,32.684722],"type":"Point"}
}