<<<<<<< HEAD
{
  "id": 2336855,
  "type": "Feature",
  "properties": {
    "tgn:hierarchy":[
        "tgn:2336855",
        "tgn:1000001",
        "tgn:7012149",
        "tgn:2000209",
        "tgn:7007158",
        "tgn:7029392"
    ],
    "tgn:id":2336855,
    "tgn:name":"Fourmile Creek",
    "tgn:placetype":[
        "aat:300008706"
    ]
},
  "bbox": [],
  "geometry": {"coordinates":[-105.2,39.15],"type":"Point"}
}
=======
{"geometry":{"type":"Point","coordinates":[-105.200000,39.150000]},"type":"Feature","properties":{"hierarchy":["tgn:2336855","tgn:1000001","tgn:7012149","tgn:2000209","tgn:7007158","tgn:7029392"],"placetype":["aat:300008706"],"id":2336855,"name:xx":"Fourmile Creek"}}
>>>>>>> 03f74aca74312dbeaf24d7e61306dd6a786dc3d0
