{
  "id": 7534340,
  "type": "Feature",
  "properties": {
    "tgn:hierarchy":[
        "tgn:7534340",
        "tgn:7001242",
        "tgn:7016833",
        "tgn:1001418",
        "tgn:7029392"
    ],
    "tgn:id":7534340,
    "tgn:name:en":"Qabr Juhayr",
    "tgn:placetype":[
        "aat:300005926"
    ]
},
  "bbox": [],
  "geometry": {"coordinates":[29.733698,30.65106],"type":"Point"}
}