{
  "id": 7277798,
  "type": "Feature",
  "properties": {
    "tgn:hierarchy":[
        "tgn:7277798",
        "tgn:1001768",
        "tgn:1000049",
        "tgn:1000002",
        "tgn:7029392"
    ],
    "tgn:id":7277798,
    "tgn:name":"Cardones, Punta",
    "tgn:placetype":[
        "aat:300386846"
    ]
},
  "bbox": [],
  "geometry": {"coordinates":[-71.652778,-33.027778],"type":"Point"}
}