{
  "id": 7571304,
  "type": "Feature",
  "properties": {
    "tgn:hierarchy":[
        "tgn:7571304",
        "tgn:1000004",
        "tgn:7000198",
        "tgn:1001895",
        "tgn:7029392"
    ],
    "tgn:id":7571304,
    "tgn:name:en":"K\u0101mag\u0101r Colony",
    "tgn:placetype":[
        "aat:300055621"
    ]
},
  "bbox": [],
  "geometry": {"coordinates":[72.883333,19.05],"type":"Point"}
}