{
  "id": 2559505,
  "type": "Feature",
  "properties": {
    "tgn:hierarchy":[
        "tgn:2559505",
        "tgn:1000001",
        "tgn:7012149",
        "tgn:2001054",
        "tgn:7007521",
        "tgn:7029392"
    ],
    "tgn:id":2559505,
    "tgn:name":"Onstad Lake",
    "tgn:placetype":[
        "aat:300008680"
    ]
},
  "bbox": [],
  "geometry": {"coordinates":[-95.8667,46.2833],"type":"Point"}
}