{
  "id": 7339327,
  "type": "Feature",
  "properties": {
    "tgn:hierarchy":[
        "tgn:7339327",
        "tgn:7002834",
        "tgn:1000003",
        "tgn:7002786",
        "tgn:1000095",
        "tgn:7029392"
    ],
    "tgn:id":7339327,
    "tgn:name":"Cristimil",
    "tgn:placetype":[
        "aat:300008347"
    ]
},
  "bbox": [],
  "geometry": {"coordinates":[-8.183333,42.666667],"type":"Point"}
}