{
  "id": 2632429,
  "type": "Feature",
  "properties": {
    "tgn:hierarchy":[
        "tgn:2632429",
        "tgn:2001731",
        "tgn:1000001",
        "tgn:7012149",
        "tgn:7007712",
        "tgn:7029392"
    ],
    "tgn:id":2632429,
    "tgn:name":"Royal Pines Country Club Estates",
    "tgn:placetype":[
        "aat:300008347"
    ]
},
  "bbox": [],
  "geometry": {"coordinates":[-80.6333,32.45],"type":"Point"}
}