{
  "id": 7516741,
  "type": "Feature",
  "properties": {
    "tgn:hierarchy":[
        "tgn:7516741",
        "tgn:1009227",
        "tgn:7001866",
        "tgn:1000226",
        "tgn:1000006",
        "tgn:7029392"
    ],
    "tgn:id":7516741,
    "tgn:name:en":"Lake Hill",
    "tgn:placetype":[
        "aat:300008795"
    ]
},
  "bbox": [],
  "geometry": {"coordinates":[171.566667,-43.35],"type":"Point"}
}