{
  "id": 2354839,
  "type": "Feature",
  "properties": {
    "tgn:hierarchy":[
        "tgn:2354839",
        "tgn:1000001",
        "tgn:7012149",
        "tgn:2001714",
        "tgn:7007708",
        "tgn:7029392"
    ],
    "tgn:id":2354839,
    "tgn:name":"Goodbye Creek",
    "tgn:placetype":[
        "aat:300008706"
    ]
},
  "bbox": [],
  "geometry": {"coordinates":[-122.1333,42.8833],"type":"Point"}
}