{
  "id": 7294914,
  "type": "Feature",
  "properties": {
    "tgn:hierarchy":[
        "tgn:7294914",
        "tgn:7001155",
        "tgn:1000003",
        "tgn:7002790",
        "tgn:1000095",
        "tgn:7029392"
    ],
    "tgn:id":7294914,
    "tgn:name":"Zuperri, Monte",
    "tgn:placetype":[
        "aat:300266640"
    ]
},
  "bbox": [],
  "geometry": {"coordinates":[-1.833333,43.066667],"type":"Point"}
}