{
  "id": 2640360,
  "type": "Feature",
  "properties": {
    "tgn:hierarchy":[
        "tgn:2640360",
        "tgn:1000001",
        "tgn:7012149",
        "tgn:7007157",
        "tgn:1002858",
        "tgn:7029392"
    ],
    "tgn:id":2640360,
    "tgn:name":"San Felipe Hills",
    "tgn:placetype":[
        "aat:300386831"
    ]
},
  "bbox": [],
  "geometry": {"coordinates":[-116.55,33.1833],"type":"Point"}
}