{
  "id": 1088147,
  "type": "Feature",
  "properties": {
    "tgn:hierarchy":[
        "tgn:1088147",
        "tgn:1001189",
        "tgn:7001242",
        "tgn:1000153",
        "tgn:7029392"
    ],
    "tgn:id":1088147,
    "tgn:name":"Ambam",
    "tgn:placetype":[
        "aat:300008347"
    ]
},
  "bbox": [],
  "geometry": {"coordinates":[11.2833,2.3833],"type":"Point"}
}