{
  "id": 1039309,
  "type": "Feature",
  "properties": {
    "tgn:hierarchy":[
        "tgn:1039309",
        "tgn:1000003",
        "tgn:7003682",
        "tgn:7000084",
        "tgn:7029392"
    ],
    "tgn:id":1039309,
    "tgn:name":"Gr\u00fcnstadt",
    "tgn:placetype":[
        "aat:300008347"
    ]
},
  "bbox": [],
  "geometry": {"coordinates":[8.168056,49.569167],"type":"Point"}
}