{
  "id": 2704135,
  "type": "Feature",
  "properties": {
    "tgn:hierarchy":[
        "tgn:2704135",
        "tgn:1000001",
        "tgn:7012149",
        "tgn:2000476",
        "tgn:7007250",
        "tgn:7029392"
    ],
    "tgn:id":2704135,
    "tgn:name":"Sungold Mine",
    "tgn:placetype":[
        "aat:300000390"
    ]
},
  "bbox": [],
  "geometry": {"coordinates":[-115.5667,45.7167],"type":"Point"}
}