{
  "id": 1079062,
  "type": "Feature",
  "properties": {
    "tgn:hierarchy":[
        "tgn:1079062",
        "tgn:1000004",
        "tgn:7002147",
        "tgn:7000231",
        "tgn:7029392"
    ],
    "tgn:id":1079062,
    "tgn:name":"Dezf\u016bl",
    "tgn:placetype":[
        "aat:300008347"
    ]
},
  "bbox": [],
  "geometry": {"coordinates":[48.4667,32.3833],"type":"Point"}
}