{
  "id": 2516130,
  "type": "Feature",
  "properties": {
    "tgn:hierarchy":[
        "tgn:2516130",
        "tgn:1000001",
        "tgn:7012149",
        "tgn:2001548",
        "tgn:7007709",
        "tgn:7029392"
    ],
    "tgn:id":2516130,
    "tgn:name":"Mine Creek",
    "tgn:placetype":[
        "aat:300008706"
    ]
},
  "bbox": [],
  "geometry": {"coordinates":[-78.6333,35.85],"type":"Point"}
}