{
  "id": 1059166,
  "type": "Feature",
  "properties": {
    "tgn:hierarchy":[
        "tgn:1059166",
        "tgn:1000004",
        "tgn:7012215",
        "tgn:7006653",
        "tgn:7029392"
    ],
    "tgn:id":1059166,
    "tgn:name":"Samtredia",
    "tgn:placetype":[
        "aat:300008347"
    ]
},
  "bbox": [],
  "geometry": {"coordinates":[42.3667,42.1667],"type":"Point"}
}