{
  "id": 7006029,
  "type": "Feature",
  "properties": {
    "tgn:hierarchy":[
        "tgn:7006029",
        "tgn:1000003",
        "tgn:7003151",
        "tgn:7003237",
        "tgn:1000080",
        "tgn:7029392"
    ],
    "tgn:id":7006029,
    "tgn:name":"Lomello",
    "tgn:placetype":[
        "aat:300008347",
        "aat:300008375"
    ]
},
  "bbox": [],
  "geometry": {"coordinates":[8.783333,45.116667],"type":"Point"}
}