{
  "id": 2159411,
  "type": "Feature",
  "properties": {
    "tgn:hierarchy":[
        "tgn:2159411",
        "tgn:1000001",
        "tgn:7012149",
        "tgn:2001497",
        "tgn:7007709",
        "tgn:7029392"
    ],
    "tgn:id":2159411,
    "tgn:name":"Bee Creek",
    "tgn:placetype":[
        "aat:300008706"
    ]
},
  "bbox": [],
  "geometry": {"coordinates":[-83.7833,35.3833],"type":"Point"}
}