{
  "id": 2334619,
  "type": "Feature",
  "properties": {
    "tgn:hierarchy":[
        "tgn:2334619",
        "tgn:1000001",
        "tgn:7012149",
        "tgn:2001308",
        "tgn:7007524",
        "tgn:7029392"
    ],
    "tgn:id":2334619,
    "tgn:name":"Forge Creek",
    "tgn:placetype":[
        "aat:300008706"
    ]
},
  "bbox": [],
  "geometry": {"coordinates":[-110.1167,45.4167],"type":"Point"}
}