<<<<<<< HEAD
{
  "id": 2334619,
  "type": "Feature",
  "properties": {
    "tgn:hierarchy":[
        "tgn:2334619",
        "tgn:1000001",
        "tgn:7012149",
        "tgn:2001308",
        "tgn:7007524",
        "tgn:7029392"
    ],
    "tgn:id":2334619,
    "tgn:name":"Forge Creek",
    "tgn:placetype":[
        "aat:300008706"
    ]
},
  "bbox": [],
  "geometry": {"coordinates":[-110.1167,45.4167],"type":"Point"}
}
=======
{"geometry":{"type":"Point","coordinates":[-110.116700,45.416700]},"type":"Feature","properties":{"hierarchy":["tgn:2334619","tgn:1000001","tgn:7012149","tgn:2001308","tgn:7007524","tgn:7029392"],"placetype":["aat:300008706"],"id":2334619,"name:xx":"Forge Creek"}}
>>>>>>> 03f74aca74312dbeaf24d7e61306dd6a786dc3d0
