{
  "id": 7311576,
  "type": "Feature",
  "properties": {
    "tgn:hierarchy":[
        "tgn:7311576",
        "tgn:1001630",
        "tgn:1000049",
        "tgn:1000002",
        "tgn:7029392"
    ],
    "tgn:id":7311576,
    "tgn:name":"Leones, Cabo",
    "tgn:placetype":[
        "aat:300386846"
    ]
},
  "bbox": [],
  "geometry": {"coordinates":[-71.533333,-28.983333],"type":"Point"}
}