{
  "id": 2584585,
  "type": "Feature",
  "properties": {
    "tgn:hierarchy":[
        "tgn:2584585",
        "tgn:1000001",
        "tgn:2001477",
        "tgn:7012149",
        "tgn:7007709",
        "tgn:7029392"
    ],
    "tgn:id":2584585,
    "tgn:name":"Piney Point",
    "tgn:placetype":[
        "aat:300008850"
    ]
},
  "bbox": [],
  "geometry": {"coordinates":[-76.4167,34.8167],"type":"Point"}
}