{
  "id": 7220483,
  "type": "Feature",
  "properties": {
    "tgn:hierarchy":[
        "tgn:7220483",
        "tgn:7011330",
        "tgn:7002674",
        "tgn:1000003",
        "tgn:1000074",
        "tgn:7029392"
    ],
    "tgn:id":7220483,
    "tgn:name":"Kalouto\u00ed, \u00c1kra",
    "tgn:placetype":[
        "aat:300386846"
    ]
},
  "bbox": [],
  "geometry": {"coordinates":[27.113056,36.64],"type":"Point"}
}