{
  "id": 2387566,
  "type": "Feature",
  "properties": {
    "tgn:hierarchy":[
        "tgn:2387566",
        "tgn:1000001",
        "tgn:7012149",
        "tgn:2002060",
        "tgn:7007826",
        "tgn:7029392"
    ],
    "tgn:id":2387566,
    "tgn:name":"Hi Saw Hollow",
    "tgn:placetype":[
        "aat:300008761"
    ]
},
  "bbox": [],
  "geometry": {"coordinates":[-99.6667,29.7833],"type":"Point"}
}