{
  "id": 7538180,
  "type": "Feature",
  "properties": {
    "tgn:hierarchy":[
        "tgn:7538180",
        "tgn:7001242",
        "tgn:1001075",
        "tgn:7016833",
        "tgn:7029392"
    ],
    "tgn:id":7538180,
    "tgn:name:en":"Muhadhad, Minq\u0101r al",
    "tgn:placetype":[
        "aat:300008749"
    ]
},
  "bbox": [],
  "geometry": {"coordinates":[29.642624,30.398619],"type":"Point"}
}