{
  "id": 1093397,
  "type": "Feature",
  "properties": {
    "tgn:hierarchy":[
        "tgn:1093397",
        "tgn:7001242",
        "tgn:7017573",
        "tgn:1000193",
        "tgn:7029392"
    ],
    "tgn:id":1093397,
    "tgn:name":"Mooketsi",
    "tgn:placetype":[
        "aat:300008347"
    ]
},
  "bbox": [],
  "geometry": {"coordinates":[30.0833,-23.5833],"type":"Point"}
}