{
  "id": 7282929,
  "type": "Feature",
  "properties": {
    "tgn:hierarchy":[
        "tgn:7282929",
        "tgn:1001630",
        "tgn:1000049",
        "tgn:1000002",
        "tgn:7029392"
    ],
    "tgn:id":7282929,
    "tgn:name":"Peinet",
    "tgn:placetype":[
        "aat:300387033"
    ]
},
  "bbox": [],
  "geometry": {"coordinates":[-69.75,-26.716667],"type":"Point"}
}