<<<<<<< HEAD
{
  "id": 7367864,
  "type": "Feature",
  "properties": {
    "tgn:hierarchy":[
        "tgn:7367864",
        "tgn:1000001",
        "tgn:7005601",
        "tgn:7005560",
        "tgn:7029392"
    ],
    "tgn:id":7367864,
    "tgn:name":"Estaci\u00f3n Felipe Pescador",
    "tgn:placetype":[
        "aat:300007783"
    ]
},
  "bbox": [],
  "geometry": {"coordinates":[-102.733333,23.6],"type":"Point"}
}
=======
{"geometry":{"type":"Point","coordinates":[-102.733333,23.600000]},"type":"Feature","properties":{"hierarchy":["tgn:7367864","tgn:1000001","tgn:7005601","tgn:7005560","tgn:7029392"],"placetype":["aat:300007783"],"id":7367864,"name:xx":"Estaci\u00f3n Felipe Pescador"}}
>>>>>>> 03f74aca74312dbeaf24d7e61306dd6a786dc3d0
