{
  "id": 2513632,
  "type": "Feature",
  "properties": {
    "tgn:hierarchy":[
        "tgn:2513632",
        "tgn:1000001",
        "tgn:7012149",
        "tgn:1002708",
        "tgn:7007568",
        "tgn:7029392"
    ],
    "tgn:id":2513632,
    "tgn:name":"Mill Pond",
    "tgn:placetype":[
        "aat:300008680"
    ]
},
  "bbox": [],
  "geometry": {"coordinates":[-73.6833,40.8333],"type":"Point"}
}