{
  "id": 2493167,
  "type": "Feature",
  "properties": {
    "tgn:hierarchy":[
        "tgn:2493167",
        "tgn:1000001",
        "tgn:7012149",
        "tgn:1002751",
        "tgn:7007568",
        "tgn:7029392"
    ],
    "tgn:id":2493167,
    "tgn:name":"Marling, Lake",
    "tgn:placetype":[
        "aat:300008680"
    ]
},
  "bbox": [],
  "geometry": {"coordinates":[-74.6167,41.4167],"type":"Point"}
}