{
  "id": 1113043,
  "type": "Feature",
  "properties": {
    "tgn:hierarchy":[
        "tgn:1113043",
        "tgn:1000003",
        "tgn:7016845",
        "tgn:7029392"
    ],
    "tgn:id":1113043,
    "tgn:name":"Gouwzee",
    "tgn:placetype":[
        "aat:300132316"
    ]
},
  "bbox": [],
  "geometry": {"coordinates":[5.0833,52.4667],"type":"Point"}
}