{
  "id": 2332775,
  "type": "Feature",
  "properties": {
    "tgn:hierarchy":[
        "tgn:2332775",
        "tgn:1000001",
        "tgn:7012149",
        "tgn:2001509",
        "tgn:7007709",
        "tgn:7029392"
    ],
    "tgn:id":2332775,
    "tgn:name":"Flowers Pond Number One",
    "tgn:placetype":[
        "aat:300006191"
    ]
},
  "bbox": [],
  "geometry": {"coordinates":[-78.3333,35.6333],"type":"Point"}
}