<<<<<<< HEAD
{
  "id": 2332775,
  "type": "Feature",
  "properties": {
    "tgn:hierarchy":[
        "tgn:2332775",
        "tgn:1000001",
        "tgn:7012149",
        "tgn:2001509",
        "tgn:7007709",
        "tgn:7029392"
    ],
    "tgn:id":2332775,
    "tgn:name":"Flowers Pond Number One",
    "tgn:placetype":[
        "aat:300006191"
    ]
},
  "bbox": [],
  "geometry": {"coordinates":[-78.3333,35.6333],"type":"Point"}
}
=======
{"geometry":{"type":"Point","coordinates":[-78.333300,35.633300]},"type":"Feature","properties":{"hierarchy":["tgn:2332775","tgn:1000001","tgn:7012149","tgn:2001509","tgn:7007709","tgn:7029392"],"placetype":["aat:300006191"],"id":2332775,"name:xx":"Flowers Pond Number One"}}
>>>>>>> 03f74aca74312dbeaf24d7e61306dd6a786dc3d0
