{
  "id": 2436319,
  "type": "Feature",
  "properties": {
    "tgn:hierarchy":[
        "tgn:2436319",
        "tgn:1002157",
        "tgn:1000001",
        "tgn:7012149",
        "tgn:7007565",
        "tgn:7029392"
    ],
    "tgn:id":2436319,
    "tgn:name":"Kiahs Island",
    "tgn:placetype":[
        "aat:300008791"
    ]
},
  "bbox": [],
  "geometry": {"coordinates":[-74.5167,39.35],"type":"Point"}
}