{
  "id": 2645651,
  "type": "Feature",
  "properties": {
    "tgn:hierarchy":[
        "tgn:2645651",
        "tgn:1000001",
        "tgn:7012149",
        "tgn:2001866",
        "tgn:7007825",
        "tgn:7029392"
    ],
    "tgn:id":2645651,
    "tgn:name":"Sawmill Branch",
    "tgn:placetype":[
        "aat:300008699"
    ]
},
  "bbox": [],
  "geometry": {"coordinates":[-82.8167,35.9167],"type":"Point"}
}