{
  "id": 7027561,
  "type": "Feature",
  "properties": {
    "tgn:hierarchy":[
        "tgn:7027561",
        "tgn:7002445",
        "tgn:1000003",
        "tgn:7008155",
        "tgn:7008591",
        "tgn:7029392"
    ],
    "tgn:id":7027561,
    "tgn:name:en":"East Langton",
    "tgn:placetype":[
        "aat:300008347",
        "aat:300008372"
    ]
},
  "bbox": [],
  "geometry": {"coordinates":[-0.916667,52.516667],"type":"Point"}
}