{
  "id": 2673547,
  "type": "Feature",
  "properties": {
    "tgn:hierarchy":[
        "tgn:2673547",
        "tgn:2000454",
        "tgn:1000001",
        "tgn:7012149",
        "tgn:7007250",
        "tgn:7029392"
    ],
    "tgn:id":2673547,
    "tgn:name":"Snipe Spring",
    "tgn:placetype":[
        "aat:300008697"
    ]
},
  "bbox": [],
  "geometry": {"coordinates":[-112.3333,42.9667],"type":"Point"}
}