{
  "id": 2437615,
  "type": "Feature",
  "properties": {
    "tgn:hierarchy":[
        "tgn:2437615",
        "tgn:1000001",
        "tgn:2001101",
        "tgn:7012149",
        "tgn:7007522",
        "tgn:7029392"
    ],
    "tgn:id":2437615,
    "tgn:name":"King Branch",
    "tgn:placetype":[
        "aat:300008699"
    ]
},
  "bbox": [],
  "geometry": {"coordinates":[-89.45,31.6167],"type":"Point"}
}