{
  "id": 2029511,
  "type": "Feature",
  "properties": {
    "tgn:hierarchy":[
        "tgn:2029511",
        "tgn:1000001",
        "tgn:7013649",
        "tgn:7012149",
        "tgn:7007251",
        "tgn:7029392"
    ],
    "tgn:id":2029511,
    "tgn:name":"Orland Park",
    "tgn:placetype":[
        "aat:300008347"
    ]
},
  "bbox": [],
  "geometry": {"coordinates":[-87.85,41.6167],"type":"Point"}
}