{
  "id": 7291520,
  "type": "Feature",
  "properties": {
    "tgn:hierarchy":[
        "tgn:7291520",
        "tgn:1001708",
        "tgn:1000049",
        "tgn:1000002",
        "tgn:7029392"
    ],
    "tgn:id":7291520,
    "tgn:name":"El Litral",
    "tgn:placetype":[
        "aat:300008795"
    ]
},
  "bbox": [],
  "geometry": {"coordinates":[-70.766667,-33.166667],"type":"Point"}
}