<<<<<<< HEAD
{
  "id": 2154823,
  "type": "Feature",
  "properties": {
    "tgn:hierarchy":[
        "tgn:2154823",
        "tgn:1000001",
        "tgn:2001425",
        "tgn:7012149",
        "tgn:7007564",
        "tgn:7029392"
    ],
    "tgn:id":2154823,
    "tgn:name":"Bear Hill Pond",
    "tgn:placetype":[
        "aat:300008680"
    ]
},
  "bbox": [],
  "geometry": {"coordinates":[-71.35,43.1],"type":"Point"}
}
=======
{"geometry":{"type":"Point","coordinates":[-71.350000,43.100000]},"type":"Feature","properties":{"hierarchy":["tgn:2154823","tgn:1000001","tgn:2001425","tgn:7012149","tgn:7007564","tgn:7029392"],"placetype":["aat:300008680"],"id":2154823,"name:xx":"Bear Hill Pond"}}
>>>>>>> 03f74aca74312dbeaf24d7e61306dd6a786dc3d0
