{
  "id": 2617144,
  "type": "Feature",
  "properties": {
    "tgn:hierarchy":[
        "tgn:2617144",
        "tgn:1000001",
        "tgn:7012149",
        "tgn:7007157",
        "tgn:7014005",
        "tgn:7029392"
    ],
    "tgn:id":2617144,
    "tgn:name":"Richardson Island",
    "tgn:placetype":[
        "aat:300008791"
    ]
},
  "bbox": [],
  "geometry": {"coordinates":[-122.5167,37.9333],"type":"Point"}
}