{
  "id": 2189963,
  "type": "Feature",
  "properties": {
    "tgn:hierarchy":[
        "tgn:2189963",
        "tgn:1000001",
        "tgn:7012149",
        "tgn:2000930",
        "tgn:7007515",
        "tgn:7029392"
    ],
    "tgn:id":2189963,
    "tgn:name":"Bowley Pond",
    "tgn:placetype":[
        "aat:300008680"
    ]
},
  "bbox": [],
  "geometry": {"coordinates":[-69.4833,44.8333],"type":"Point"}
}