{
  "id": 2180481,
  "type": "Feature",
  "properties": {
    "tgn:hierarchy":[
        "tgn:2180481",
        "tgn:1000001",
        "tgn:1002963",
        "tgn:7012149",
        "tgn:7007565",
        "tgn:7029392"
    ],
    "tgn:id":2180481,
    "tgn:name":"Bloodgoods Pond",
    "tgn:placetype":[
        "aat:300006191"
    ]
},
  "bbox": [],
  "geometry": {"coordinates":[-74.2833,40.6167],"type":"Point"}
}