{
  "id": 2092274,
  "type": "Feature",
  "properties": {
    "tgn:hierarchy":[
        "tgn:2092274",
        "tgn:1000001",
        "tgn:1002213",
        "tgn:7012149",
        "tgn:7007710",
        "tgn:7029392"
    ],
    "tgn:id":2092274,
    "tgn:name":"Quakertown",
    "tgn:placetype":[
        "aat:300008347"
    ]
},
  "bbox": [],
  "geometry": {"coordinates":[-75.3333,40.4333],"type":"Point"}
}