<<<<<<< HEAD
{
  "id": 7024571,
  "type": "Feature",
  "properties": {
    "tgn:hierarchy":[
        "tgn:7024571",
        "tgn:7593554",
        "tgn:1000001",
        "tgn:7024573",
        "tgn:7029392"
    ],
    "tgn:id":7024571,
    "tgn:name":"Ortunuviaq",
    "tgn:placetype":[
        "aat:300008850"
    ]
},
  "bbox": [],
  "geometry": {"coordinates":[-33.3667,67.2167],"type":"Point"}
}
=======
{"geometry":{"type":"Point","coordinates":[-33.366700,67.216700]},"type":"Feature","properties":{"hierarchy":["tgn:7024571","tgn:7593554","tgn:1000001","tgn:7024573","tgn:7029392"],"placetype":["aat:300008850"],"id":7024571,"name:xx":"Ortunuviaq"}}
>>>>>>> 03f74aca74312dbeaf24d7e61306dd6a786dc3d0
