{
  "id": 7024571,
  "type": "Feature",
  "properties": {
    "tgn:hierarchy":[
        "tgn:7024571",
        "tgn:7593554",
        "tgn:1000001",
        "tgn:7024573",
        "tgn:7029392"
    ],
    "tgn:id":7024571,
    "tgn:name":"Ortunuviaq",
    "tgn:placetype":[
        "aat:300008850"
    ]
},
  "bbox": [],
  "geometry": {"coordinates":[-33.3667,67.2167],"type":"Point"}
}