{
  "id": 7400401,
  "type": "Feature",
  "properties": {
    "tgn:hierarchy":[
        "tgn:7400401",
        "tgn:1000001",
        "tgn:7005599",
        "tgn:7005560",
        "tgn:7029392"
    ],
    "tgn:id":7400401,
    "tgn:name":"Coyolito",
    "tgn:placetype":[
        "aat:300008347"
    ]
},
  "bbox": [],
  "geometry": {"coordinates":[-98.483333,21.466667],"type":"Point"}
}