{
  "id": 2295745,
  "type": "Feature",
  "properties": {
    "tgn:hierarchy":[
        "tgn:2295745",
        "tgn:1000001",
        "tgn:2001643",
        "tgn:7012149",
        "tgn:7007707",
        "tgn:7029392"
    ],
    "tgn:id":2295745,
    "tgn:name":"Drowning Creek",
    "tgn:placetype":[
        "aat:300008706"
    ]
},
  "bbox": [],
  "geometry": {"coordinates":[-94.7667,36.45],"type":"Point"}
}