<<<<<<< HEAD
{
  "id": 7483499,
  "type": "Feature",
  "properties": {
    "tgn:hierarchy":[
        "tgn:7483499",
        "tgn:1000004",
        "tgn:7490934",
        "tgn:1000141",
        "tgn:7029392"
    ],
    "tgn:id":7483499,
    "tgn:name":"Neishi",
    "tgn:placetype":[
        "aat:300008347"
    ]
},
  "bbox": [],
  "geometry": {"coordinates":[120.535556,23.183889],"type":"Point"}
}
=======
{"geometry":{"type":"Point","coordinates":[120.535556,23.183889]},"type":"Feature","properties":{"hierarchy":["tgn:7483499","tgn:1000004","tgn:7490934","tgn:1000141","tgn:7029392"],"placetype":["aat:300008347"],"id":7483499,"name:xx":"Neishi"}}
>>>>>>> 03f74aca74312dbeaf24d7e61306dd6a786dc3d0
