{
  "id": 7448498,
  "type": "Feature",
  "properties": {
    "tgn:hierarchy":[
        "tgn:7448498",
        "tgn:7002444",
        "tgn:1000003",
        "tgn:7008082",
        "tgn:7008591",
        "tgn:7029392"
    ],
    "tgn:id":7448498,
    "tgn:name:en":"Ruaidhe, Sg\u00f9rr na",
    "tgn:placetype":[
        "aat:300008795"
    ]
},
  "bbox": [],
  "geometry": {"coordinates":[-4.85,57.433333],"type":"Point"}
}