<<<<<<< HEAD
{
  "id": 7369279,
  "type": "Feature",
  "properties": {
    "tgn:hierarchy":[
        "tgn:7369279",
        "tgn:1001853",
        "tgn:1000001",
        "tgn:7005560",
        "tgn:7029392"
    ],
    "tgn:id":7369279,
    "tgn:name":"Hormigas de Afuera",
    "tgn:placetype":[
        "aat:300008347"
    ]
},
  "bbox": [],
  "geometry": {"coordinates":[-103.933333,27.766667],"type":"Point"}
}
=======
{"geometry":{"type":"Point","coordinates":[-103.933333,27.766667]},"type":"Feature","properties":{"hierarchy":["tgn:7369279","tgn:1001853","tgn:1000001","tgn:7005560","tgn:7029392"],"placetype":["aat:300008347"],"id":7369279,"name:xx":"Hormigas de Afuera"}}
>>>>>>> 03f74aca74312dbeaf24d7e61306dd6a786dc3d0
