{
  "id": 7369279,
  "type": "Feature",
  "properties": {
    "tgn:hierarchy":[
        "tgn:7369279",
        "tgn:1001853",
        "tgn:1000001",
        "tgn:7005560",
        "tgn:7029392"
    ],
    "tgn:id":7369279,
    "tgn:name":"Hormigas de Afuera",
    "tgn:placetype":[
        "aat:300008347"
    ]
},
  "bbox": [],
  "geometry": {"coordinates":[-103.933333,27.766667],"type":"Point"}
}