{
  "id": 7192823,
  "type": "Feature",
  "properties": {
    "tgn:hierarchy":[
        "tgn:7192823",
        "tgn:1000003",
        "tgn:7000094",
        "tgn:7000084",
        "tgn:7029392"
    ],
    "tgn:id":7192823,
    "tgn:name":"Fahrenholzer Holz",
    "tgn:placetype":[
        "aat:300008863"
    ]
},
  "bbox": [],
  "geometry": {"coordinates":[12.033333,54.033333],"type":"Point"}
}