<<<<<<< HEAD
{
  "id": 2154832,
  "type": "Feature",
  "properties": {
    "tgn:hierarchy":[
        "tgn:2154832",
        "tgn:1000001",
        "tgn:7012149",
        "tgn:2000471",
        "tgn:7007250",
        "tgn:7029392"
    ],
    "tgn:id":2154832,
    "tgn:name":"Bear Hole Creek",
    "tgn:placetype":[
        "aat:300008706"
    ]
},
  "bbox": [],
  "geometry": {"coordinates":[-115.3667,43.5333],"type":"Point"}
}
=======
{"geometry":{"type":"Point","coordinates":[-115.366700,43.533300]},"type":"Feature","properties":{"hierarchy":["tgn:2154832","tgn:1000001","tgn:7012149","tgn:2000471","tgn:7007250","tgn:7029392"],"placetype":["aat:300008706"],"id":2154832,"name:xx":"Bear Hole Creek"}}
>>>>>>> 03f74aca74312dbeaf24d7e61306dd6a786dc3d0
