{
  "id": 2176997,
  "type": "Feature",
  "properties": {
    "tgn:hierarchy":[
        "tgn:2176997",
        "tgn:1000001",
        "tgn:7012149",
        "tgn:7007919",
        "tgn:7029392"
    ],
    "tgn:id":2176997,
    "tgn:name":"Black Oak Hill",
    "tgn:placetype":[
        "aat:300008798"
    ]
},
  "bbox": [],
  "geometry": {"coordinates":[-79.4167,38.0333],"type":"Point"}
}