<<<<<<< HEAD
{
  "id": 7050838,
  "type": "Feature",
  "properties": {
    "tgn:hierarchy":[
        "tgn:7050838",
        "tgn:7015163",
        "tgn:1000003",
        "tgn:7003121",
        "tgn:1000080",
        "tgn:7029392"
    ],
    "tgn:id":7050838,
    "tgn:name":"Masiennera, Punta",
    "tgn:placetype":[
        "aat:300008795"
    ]
},
  "bbox": [],
  "geometry": {"coordinates":[9.033333,40.466667],"type":"Point"}
}
=======
{"geometry":{"type":"Point","coordinates":[9.033333,40.466667]},"type":"Feature","properties":{"hierarchy":["tgn:7050838","tgn:7015163","tgn:1000003","tgn:7003121","tgn:1000080","tgn:7029392"],"placetype":["aat:300008795"],"id":7050838,"name:xx":"Masiennera, Punta"}}
>>>>>>> 03f74aca74312dbeaf24d7e61306dd6a786dc3d0
