{
  "id": 2590297,
  "type": "Feature",
  "properties": {
    "tgn:hierarchy":[
        "tgn:2590297",
        "tgn:7006450",
        "tgn:1000001",
        "tgn:7012149",
        "tgn:2124005",
        "tgn:7029392"
    ],
    "tgn:id":2590297,
    "tgn:name":"Pokok Lagoon",
    "tgn:placetype":[
        "aat:300132316"
    ]
},
  "bbox": [],
  "geometry": {"coordinates":[-142.7667,70.0333],"type":"Point"}
}