{
  "id": 7335150,
  "type": "Feature",
  "properties": {
    "tgn:hierarchy":[
        "tgn:7335150",
        "tgn:7002824",
        "tgn:1000003",
        "tgn:7002786",
        "tgn:1000095",
        "tgn:7029392"
    ],
    "tgn:id":7335150,
    "tgn:name":"Fruime",
    "tgn:placetype":[
        "aat:300008347"
    ]
},
  "bbox": [],
  "geometry": {"coordinates":[-8.85,42.733333],"type":"Point"}
}