{
  "id": 2691243,
  "type": "Feature",
  "properties": {
    "tgn:hierarchy":[
        "tgn:2691243",
        "tgn:1000001",
        "tgn:2000921",
        "tgn:7012149",
        "tgn:7007515",
        "tgn:7029392"
    ],
    "tgn:id":2691243,
    "tgn:name":"Staples Pond",
    "tgn:placetype":[
        "aat:300008680"
    ]
},
  "bbox": [],
  "geometry": {"coordinates":[-70.2333,44.7167],"type":"Point"}
}