{
  "id": 2637609,
  "type": "Feature",
  "properties": {
    "tgn:hierarchy":[
        "tgn:2637609",
        "tgn:1000001",
        "tgn:7012149",
        "tgn:2000891",
        "tgn:7007256",
        "tgn:7029392"
    ],
    "tgn:id":2637609,
    "tgn:name":"Saint Marys Point",
    "tgn:placetype":[
        "aat:300008850"
    ]
},
  "bbox": [],
  "geometry": {"coordinates":[-89.9333,29.4167],"type":"Point"}
}