{
  "id": 1007379,
  "type": "Feature",
  "properties": {
    "tgn:hierarchy":[
        "tgn:1007379",
        "tgn:7005269",
        "tgn:1000006",
        "tgn:7029392"
    ],
    "tgn:id":1007379,
    "tgn:name":"Henderson Island",
    "tgn:placetype":[
        "aat:300008791"
    ]
},
  "bbox": [],
  "geometry": {"coordinates":[-128.316,-24.366],"type":"Point"}
}