{
  "id": 1040349,
  "type": "Feature",
  "properties": {
    "tgn:hierarchy":[
        "tgn:1040349",
        "tgn:7003669",
        "tgn:1000003",
        "tgn:7000084",
        "tgn:7029392"
    ],
    "tgn:id":1040349,
    "tgn:name":"Mistelbach",
    "tgn:placetype":[
        "aat:300008347"
    ]
},
  "bbox": [],
  "geometry": {"coordinates":[11.516667,49.916667],"type":"Point"}
}