{
  "id": 2174006,
  "type": "Feature",
  "properties": {
    "tgn:hierarchy":[
        "tgn:2174006",
        "tgn:1000001",
        "tgn:1002724",
        "tgn:7012149",
        "tgn:7007517",
        "tgn:7029392"
    ],
    "tgn:id":2174006,
    "tgn:name":"Bird Pond",
    "tgn:placetype":[
        "aat:300006191"
    ]
},
  "bbox": [],
  "geometry": {"coordinates":[-71.2167,42.15],"type":"Point"}
}