{
  "id": 7009087,
  "type": "Feature",
  "properties": {
    "tgn:hierarchy":[
        "tgn:7009087",
        "tgn:7019094",
        "tgn:7002444",
        "tgn:1000003",
        "tgn:7008591",
        "tgn:7029392"
    ],
    "tgn:id":7009087,
    "tgn:name:en":"Oronsay",
    "tgn:placetype":[
        "aat:300008791"
    ]
},
  "bbox": [],
  "geometry": {"coordinates":[-6.266667,56.016667],"type":"Point"}
}