{
  "id": 1119843,
  "type": "Feature",
  "properties": {
    "tgn:hierarchy":[
        "tgn:1119843",
        "tgn:1000001",
        "tgn:7012149",
        "tgn:7014612",
        "tgn:7007568",
        "tgn:7029392"
    ],
    "tgn:id":1119843,
    "tgn:name":"Grassy Sprain Reservoir",
    "tgn:placetype":[
        "aat:300006191"
    ]
},
  "bbox": [],
  "geometry": {"coordinates":[-73.85,40.95],"type":"Point"}
}