<<<<<<< HEAD
{
  "id": 2157298,
  "type": "Feature",
  "properties": {
    "tgn:hierarchy":[
        "tgn:2157298",
        "tgn:1000001",
        "tgn:7012149",
        "tgn:2000909",
        "tgn:7007256",
        "tgn:7029392"
    ],
    "tgn:id":2157298,
    "tgn:name":"Beaver Creek",
    "tgn:placetype":[
        "aat:300008706"
    ]
},
  "bbox": [],
  "geometry": {"coordinates":[-92.2667,32.9],"type":"Point"}
}
=======
{"geometry":{"type":"Point","coordinates":[-92.266700,32.900000]},"type":"Feature","properties":{"hierarchy":["tgn:2157298","tgn:1000001","tgn:7012149","tgn:2000909","tgn:7007256","tgn:7029392"],"placetype":["aat:300008706"],"id":2157298,"name:xx":"Beaver Creek"}}
>>>>>>> 03f74aca74312dbeaf24d7e61306dd6a786dc3d0
