{
  "id": 7434064,
  "type": "Feature",
  "properties": {
    "tgn:hierarchy":[
        "tgn:7434064",
        "tgn:1001853",
        "tgn:1000001",
        "tgn:7005560",
        "tgn:7029392"
    ],
    "tgn:id":7434064,
    "tgn:name":"Ventanillas, Cerro",
    "tgn:placetype":[
        "aat:300008795"
    ]
},
  "bbox": [],
  "geometry": {"coordinates":[-102.75,26.05],"type":"Point"}
}