{
  "id": 7377471,
  "type": "Feature",
  "properties": {
    "tgn:hierarchy":[
        "tgn:7377471",
        "tgn:1000001",
        "tgn:7005591",
        "tgn:7005560",
        "tgn:7029392"
    ],
    "tgn:id":7377471,
    "tgn:name":"La Venta",
    "tgn:placetype":[
        "aat:300008347"
    ]
},
  "bbox": [],
  "geometry": {"coordinates":[-94.816667,16.566667],"type":"Point"}
}