{
  "id": 2181946,
  "type": "Feature",
  "properties": {
    "tgn:hierarchy":[
        "tgn:2181946",
        "tgn:1000001",
        "tgn:7012149",
        "tgn:2001274",
        "tgn:7007524",
        "tgn:7029392"
    ],
    "tgn:id":2181946,
    "tgn:name":"Blue Lake",
    "tgn:placetype":[
        "aat:300008680"
    ]
},
  "bbox": [],
  "geometry": {"coordinates":[-114.05,48.1333],"type":"Point"}
}