{
  "id": 7544376,
  "type": "Feature",
  "properties": {
    "tgn:hierarchy":[
        "tgn:7544376",
        "tgn:7001242",
        "tgn:7016833",
        "tgn:7001336",
        "tgn:7029392"
    ],
    "tgn:id":7544376,
    "tgn:name:en":"Mughid, W\u0101d\u012b",
    "tgn:placetype":[
        "aat:300379998"
    ]
},
  "bbox": [],
  "geometry": {"coordinates":[34.246925,28.793206],"type":"Point"}
}