{
  "id": 7070766,
  "type": "Feature",
  "properties": {
    "tgn:hierarchy":[
        "tgn:7070766",
        "tgn:1000003",
        "tgn:7003682",
        "tgn:7000084",
        "tgn:7029392"
    ],
    "tgn:id":7070766,
    "tgn:name":"Stein-B\u00fchl",
    "tgn:placetype":[
        "aat:300008777"
    ]
},
  "bbox": [],
  "geometry": {"coordinates":[7.933333,49.066667],"type":"Point"}
}