{
  "id": 7039177,
  "type": "Feature",
  "properties": {
    "tgn:hierarchy":[
        "tgn:7039177",
        "tgn:1003468",
        "tgn:1000003",
        "tgn:7010380",
        "tgn:1000080",
        "tgn:7029392"
    ],
    "tgn:id":7039177,
    "tgn:name":"Il Siedi, Canale",
    "tgn:placetype":[
        "aat:300008699"
    ]
},
  "bbox": [],
  "geometry": {"coordinates":[18.041667,40.559444],"type":"Point"}
}