{
  "id": 1113876,
  "type": "Feature",
  "properties": {
    "tgn:hierarchy":[
        "tgn:1113876",
        "tgn:7002443",
        "tgn:1000003",
        "tgn:7008591",
        "tgn:7029392"
    ],
    "tgn:id":1113876,
    "tgn:name:en":"Swansea Bay",
    "tgn:placetype":[
        "aat:300132316"
    ]
},
  "bbox": [],
  "geometry": {"coordinates":[-3.908333,51.583333],"type":"Point"}
}