{
  "id": 7256471,
  "type": "Feature",
  "properties": {
    "tgn:hierarchy":[
        "tgn:7256471",
        "tgn:1000003",
        "tgn:1000063",
        "tgn:7029392"
    ],
    "tgn:id":7256471,
    "tgn:name":"Binnen Ratel",
    "tgn:placetype":[
        "aat:300387036"
    ]
},
  "bbox": [],
  "geometry": {"coordinates":[2.391667,51.158333],"type":"Point"}
}