{
  "id": 2235708,
  "type": "Feature",
  "properties": {
    "tgn:hierarchy":[
        "tgn:2235708",
        "tgn:1000001",
        "tgn:7012149",
        "tgn:2000352",
        "tgn:7007248",
        "tgn:7029392"
    ],
    "tgn:id":2235708,
    "tgn:name":"Chestnut Mountain",
    "tgn:placetype":[
        "aat:300008798"
    ]
},
  "bbox": [],
  "geometry": {"coordinates":[-84.4667,34.7833],"type":"Point"}
}