{
  "id": 2262946,
  "type": "Feature",
  "properties": {
    "tgn:hierarchy":[
        "tgn:2262946",
        "tgn:1000001",
        "tgn:7012149",
        "tgn:1003038",
        "tgn:7007517",
        "tgn:7029392"
    ],
    "tgn:id":2262946,
    "tgn:name":"Cowees Hill",
    "tgn:placetype":[
        "aat:300008798"
    ]
},
  "bbox": [],
  "geometry": {"coordinates":[-71.8667,42.5833],"type":"Point"}
}