{
  "id": 7304750,
  "type": "Feature",
  "properties": {
    "tgn:hierarchy":[
        "tgn:7304750",
        "tgn:7002805",
        "tgn:7002758",
        "tgn:1000003",
        "tgn:1000095",
        "tgn:7029392"
    ],
    "tgn:id":7304750,
    "tgn:name":"La Yedra",
    "tgn:placetype":[
        "aat:300008347"
    ]
},
  "bbox": [],
  "geometry": {"coordinates":[-2.083333,37.25],"type":"Point"}
}