{
  "id": 7573279,
  "type": "Feature",
  "properties": {
    "tgn:hierarchy":[
        "tgn:7573279",
        "tgn:7016678",
        "tgn:7000204",
        "tgn:1006694",
        "tgn:1000004",
        "tgn:7000198",
        "tgn:7029392"
    ],
    "tgn:id":7573279,
    "tgn:name:en":"Inaka",
    "tgn:placetype":[
        "aat:300008347"
    ]
},
  "bbox": [],
  "geometry": {"coordinates":[93.533333,8.066667],"type":"Point"}
}