{
  "id": 7357006,
  "type": "Feature",
  "properties": {
    "tgn:hierarchy":[
        "tgn:7357006",
        "tgn:1000001",
        "tgn:7005595",
        "tgn:7005560",
        "tgn:7029392"
    ],
    "tgn:id":7357006,
    "tgn:name":"Campo Facundo",
    "tgn:placetype":[
        "aat:300008347"
    ]
},
  "bbox": [],
  "geometry": {"coordinates":[-107.533889,24.723056],"type":"Point"}
}