{
  "id": 2372542,
  "type": "Feature",
  "properties": {
    "tgn:hierarchy":[
        "tgn:2372542",
        "tgn:1000001",
        "tgn:7012149",
        "tgn:1002898",
        "tgn:7007826",
        "tgn:7029392"
    ],
    "tgn:id":2372542,
    "tgn:name":"Hall Branch",
    "tgn:placetype":[
        "aat:300008699"
    ]
},
  "bbox": [],
  "geometry": {"coordinates":[-95.4833,32.55],"type":"Point"}
}