{
  "id": 7513794,
  "type": "Feature",
  "properties": {
    "tgn:hierarchy":[
        "tgn:7513794",
        "tgn:1008380",
        "tgn:7520093",
        "tgn:1000226",
        "tgn:1000006",
        "tgn:7029392"
    ],
    "tgn:id":7513794,
    "tgn:name:en":"Georges",
    "tgn:placetype":[
        "aat:300008777"
    ]
},
  "bbox": [],
  "geometry": {"coordinates":[175.316667,-39.916667],"type":"Point"}
}