{
  "id": 1063203,
  "type": "Feature",
  "properties": {
    "tgn:hierarchy":[
        "tgn:1063203",
        "tgn:1000003",
        "tgn:1000462",
        "tgn:1000097",
        "tgn:7029392"
    ],
    "tgn:id":1063203,
    "tgn:name":"Karlholmsbruk",
    "tgn:placetype":[
        "aat:300008347"
    ]
},
  "bbox": [],
  "geometry": {"coordinates":[17.6167,60.5167],"type":"Point"}
}