{
  "id": 7420695,
  "type": "Feature",
  "properties": {
    "tgn:hierarchy":[
        "tgn:7420695",
        "tgn:7005584",
        "tgn:1000001",
        "tgn:7005560",
        "tgn:7029392"
    ],
    "tgn:id":7420695,
    "tgn:name":"Pur\u00edsima de Guadalupe",
    "tgn:placetype":[
        "aat:300008347"
    ]
},
  "bbox": [],
  "geometry": {"coordinates":[-100.6875,21.401111],"type":"Point"}
}