{
  "id": 7335810,
  "type": "Feature",
  "properties": {
    "tgn:hierarchy":[
        "tgn:7335810",
        "tgn:7002844",
        "tgn:7030216",
        "tgn:1000003",
        "tgn:1000095",
        "tgn:7029392"
    ],
    "tgn:id":7335810,
    "tgn:name":"Galacho, Punta del",
    "tgn:placetype":[
        "aat:300386846"
    ]
},
  "bbox": [],
  "geometry": {"coordinates":[0.616667,40.583333],"type":"Point"}
}