{
  "id": 7586045,
  "type": "Feature",
  "properties": {
    "tgn:hierarchy":[
        "tgn:7586045",
        "tgn:1000004",
        "tgn:7000198",
        "tgn:7000799",
        "tgn:7029392"
    ],
    "tgn:id":7586045,
    "tgn:name:en":"Kargom",
    "tgn:placetype":[
        "aat:300008347"
    ]
},
  "bbox": [],
  "geometry": {"coordinates":[74.294567,34.384789],"type":"Point"}
}