{
  "id": 1033475,
  "type": "Feature",
  "properties": {
    "tgn:hierarchy":[
        "tgn:1033475",
        "tgn:7002870",
        "tgn:1000003",
        "tgn:1000070",
        "tgn:7029392"
    ],
    "tgn:id":1033475,
    "tgn:name":"Illhaeusern",
    "tgn:placetype":[
        "aat:300008347"
    ]
},
  "bbox": [],
  "geometry": {"coordinates":[7.4333,48.1833],"type":"Point"}
}