{
  "id": 2637176,
  "type": "Feature",
  "properties": {
    "tgn:hierarchy":[
        "tgn:2637176",
        "tgn:1000001",
        "tgn:7012149",
        "tgn:7007157",
        "tgn:1002859",
        "tgn:7029392"
    ],
    "tgn:id":2637176,
    "tgn:name":"Saint Francis Square",
    "tgn:placetype":[
        "aat:300008347"
    ]
},
  "bbox": [],
  "geometry": {"coordinates":[-122.4167,37.7833],"type":"Point"}
}