{
  "id": 2364866,
  "type": "Feature",
  "properties": {
    "tgn:hierarchy":[
        "tgn:2364866",
        "tgn:1000001",
        "tgn:7012149",
        "tgn:2001077",
        "tgn:7007521",
        "tgn:7029392"
    ],
    "tgn:id":2364866,
    "tgn:name":"Greenfield Hill",
    "tgn:placetype":[
        "aat:300008798"
    ]
},
  "bbox": [],
  "geometry": {"coordinates":[-92.0167,44.3333],"type":"Point"}
}