{
  "id": 2131790,
  "type": "Feature",
  "properties": {
    "tgn:hierarchy":[
        "tgn:2131790",
        "tgn:1000001",
        "tgn:2000263",
        "tgn:7012149",
        "tgn:7007240",
        "tgn:7029392"
    ],
    "tgn:id":2131790,
    "tgn:name":"Amason Creek",
    "tgn:placetype":[
        "aat:300008706"
    ]
},
  "bbox": [],
  "geometry": {"coordinates":[-83.1833,29.4833],"type":"Point"}
}