{
  "id": 7040095,
  "type": "Feature",
  "properties": {
    "tgn:hierarchy":[
        "tgn:7040095",
        "tgn:7009084",
        "tgn:7004154",
        "tgn:1000003",
        "tgn:1000080",
        "tgn:7029392"
    ],
    "tgn:id":7040095,
    "tgn:name":"Scarafano, Monte",
    "tgn:placetype":[
        "aat:300008795"
    ]
},
  "bbox": [],
  "geometry": {"coordinates":[13.816667,42.233333],"type":"Point"}
}