{
  "id": 2763698,
  "type": "Feature",
  "properties": {
    "tgn:hierarchy":[
        "tgn:2763698",
        "tgn:1000001",
        "tgn:7012149",
        "tgn:2001291",
        "tgn:7007524",
        "tgn:7029392"
    ],
    "tgn:id":2763698,
    "tgn:name":"Whaley Mine",
    "tgn:placetype":[
        "aat:300000390"
    ]
},
  "bbox": [],
  "geometry": {"coordinates":[-113.9833,46.6833],"type":"Point"}
}