<<<<<<< HEAD
{
  "id": 2760755,
  "type": "Feature",
  "properties": {
    "tgn:hierarchy":[
        "tgn:2760755",
        "tgn:1000001",
        "tgn:7012149",
        "tgn:1002993",
        "tgn:7007568",
        "tgn:7029392"
    ],
    "tgn:id":2760755,
    "tgn:name":"West Granville",
    "tgn:placetype":[
        "aat:300008347"
    ]
},
  "bbox": [],
  "geometry": {"coordinates":[-73.35,43.4333],"type":"Point"}
}
=======
{"geometry":{"type":"Point","coordinates":[-73.350000,43.433300]},"type":"Feature","properties":{"hierarchy":["tgn:2760755","tgn:1000001","tgn:7012149","tgn:1002993","tgn:7007568","tgn:7029392"],"placetype":["aat:300008347"],"id":2760755,"name:xx":"West Granville"}}
>>>>>>> 03f74aca74312dbeaf24d7e61306dd6a786dc3d0
