{
  "id": 7218871,
  "type": "Feature",
  "properties": {
    "tgn:hierarchy":[
        "tgn:7218871",
        "tgn:7011270",
        "tgn:7002674",
        "tgn:1000003",
        "tgn:1000074",
        "tgn:7029392"
    ],
    "tgn:id":7218871,
    "tgn:name":"F\u00f3kia, Vr\u00e1chos",
    "tgn:placetype":[
        "aat:300011692"
    ]
},
  "bbox": [],
  "geometry": {"coordinates":[25.963333,36.931111],"type":"Point"}
}