{
  "id": 7468770,
  "type": "Feature",
  "properties": {
    "tgn:hierarchy":[
        "tgn:7468770",
        "tgn:7498210",
        "tgn:1000004",
        "tgn:1000141",
        "tgn:7029392"
    ],
    "tgn:id":7468770,
    "tgn:name":"Feng Shan",
    "tgn:placetype":[
        "aat:300008777"
    ]
},
  "bbox": [],
  "geometry": {"coordinates":[120.001363,26.231052],"type":"Point"}
}