{
  "id": 2731293,
  "type": "Feature",
  "properties": {
    "tgn:hierarchy":[
        "tgn:2731293",
        "tgn:1000001",
        "tgn:7012149",
        "tgn:1002961",
        "tgn:7007568",
        "tgn:7029392"
    ],
    "tgn:id":2731293,
    "tgn:name":"Tuckers Corner",
    "tgn:placetype":[
        "aat:300008347"
    ]
},
  "bbox": [],
  "geometry": {"coordinates":[-74.0167,41.6667],"type":"Point"}
}