{
  "id": 2502778,
  "type": "Feature",
  "properties": {
    "tgn:hierarchy":[
        "tgn:2502778",
        "tgn:1000001",
        "tgn:2002134",
        "tgn:7012149",
        "tgn:7007828",
        "tgn:7029392"
    ],
    "tgn:id":2502778,
    "tgn:name":"McMaster Hill",
    "tgn:placetype":[
        "aat:300008798"
    ]
},
  "bbox": [],
  "geometry": {"coordinates":[-72.3333,43.8833],"type":"Point"}
}