{
  "id": 2554108,
  "type": "Feature",
  "properties": {
    "tgn:hierarchy":[
        "tgn:2554108",
        "tgn:1000001",
        "tgn:2001023",
        "tgn:7012149",
        "tgn:7007521",
        "tgn:7029392"
    ],
    "tgn:id":2554108,
    "tgn:name":"Oak Ridge",
    "tgn:placetype":[
        "aat:300266640"
    ]
},
  "bbox": [],
  "geometry": {"coordinates":[-92.35,44.4667],"type":"Point"}
}