{
  "id": 7291181,
  "type": "Feature",
  "properties": {
    "tgn:hierarchy":[
        "tgn:7291181",
        "tgn:1001637",
        "tgn:1000049",
        "tgn:1000002",
        "tgn:7029392"
    ],
    "tgn:id":7291181,
    "tgn:name":"Estaci\u00f3n Escuadr\u00f3n",
    "tgn:placetype":[
        "aat:300007783"
    ]
},
  "bbox": [],
  "geometry": {"coordinates":[-73.15,-36.933333],"type":"Point"}
}