{
  "id": 2117156,
  "type": "Feature",
  "properties": {
    "tgn:hierarchy":[
        "tgn:2117156",
        "tgn:1000001",
        "tgn:7012149",
        "tgn:1002554",
        "tgn:7007920",
        "tgn:7029392"
    ],
    "tgn:id":2117156,
    "tgn:name":"Wishram Heights",
    "tgn:placetype":[
        "aat:300008347"
    ]
},
  "bbox": [],
  "geometry": {"coordinates":[-120.9667,45.65],"type":"Point"}
}