<<<<<<< HEAD
{
  "id": 2150454,
  "type": "Feature",
  "properties": {
    "tgn:hierarchy":[
        "tgn:2150454",
        "tgn:1000001",
        "tgn:7012149",
        "tgn:2000285",
        "tgn:7007240",
        "tgn:7029392"
    ],
    "tgn:id":2150454,
    "tgn:name":"Basin Island",
    "tgn:placetype":[
        "aat:300008791"
    ]
},
  "bbox": [],
  "geometry": {"coordinates":[-86.8833,30.5667],"type":"Point"}
}
=======
{"geometry":{"type":"Point","coordinates":[-86.883300,30.566700]},"type":"Feature","properties":{"hierarchy":["tgn:2150454","tgn:1000001","tgn:7012149","tgn:2000285","tgn:7007240","tgn:7029392"],"placetype":["aat:300008791"],"id":2150454,"name:xx":"Basin Island"}}
>>>>>>> 03f74aca74312dbeaf24d7e61306dd6a786dc3d0
