{
  "id": 2150454,
  "type": "Feature",
  "properties": {
    "tgn:hierarchy":[
        "tgn:2150454",
        "tgn:1000001",
        "tgn:7012149",
        "tgn:2000285",
        "tgn:7007240",
        "tgn:7029392"
    ],
    "tgn:id":2150454,
    "tgn:name":"Basin Island",
    "tgn:placetype":[
        "aat:300008791"
    ]
},
  "bbox": [],
  "geometry": {"coordinates":[-86.8833,30.5667],"type":"Point"}
}