{
  "id": 7422296,
  "type": "Feature",
  "properties": {
    "tgn:hierarchy":[
        "tgn:7422296",
        "tgn:1000001",
        "tgn:1001960",
        "tgn:7005560",
        "tgn:7029392"
    ],
    "tgn:id":7422296,
    "tgn:name":"El Tascalito",
    "tgn:placetype":[
        "aat:300008347"
    ]
},
  "bbox": [],
  "geometry": {"coordinates":[-109.616667,30.933333],"type":"Point"}
}