{
  "id": 2752455,
  "type": "Feature",
  "properties": {
    "tgn:hierarchy":[
        "tgn:2752455",
        "tgn:1000001",
        "tgn:7012149",
        "tgn:1002384",
        "tgn:7007523",
        "tgn:7029392"
    ],
    "tgn:id":2752455,
    "tgn:name":"Washington Lions Lake",
    "tgn:placetype":[
        "aat:300006191"
    ]
},
  "bbox": [],
  "geometry": {"coordinates":[-91.0167,38.55],"type":"Point"}
}