{
  "id": 7135641,
  "type": "Feature",
  "properties": {
    "tgn:hierarchy":[
        "tgn:7135641",
        "tgn:1000003",
        "tgn:7000094",
        "tgn:7000084",
        "tgn:7029392"
    ],
    "tgn:id":7135641,
    "tgn:name":"Vorwerk Nadrensee",
    "tgn:placetype":[
        "aat:300000206"
    ]
},
  "bbox": [],
  "geometry": {"coordinates":[14.333333,53.316667],"type":"Point"}
}