{
  "id": 1080361,
  "type": "Feature",
  "properties": {
    "tgn:hierarchy":[
        "tgn:1080361",
        "tgn:1000993",
        "tgn:1000004",
        "tgn:7000901",
        "tgn:1000120",
        "tgn:7029392"
    ],
    "tgn:id":1080361,
    "tgn:name":"Kajiki",
    "tgn:placetype":[
        "aat:300008347"
    ]
},
  "bbox": [],
  "geometry": {"coordinates":[130.65,31.75],"type":"Point"}
}