{
  "id": 2709878,
  "type": "Feature",
  "properties": {
    "tgn:hierarchy":[
        "tgn:2709878",
        "tgn:1000001",
        "tgn:2002147",
        "tgn:7012149",
        "tgn:7007919",
        "tgn:7029392"
    ],
    "tgn:id":2709878,
    "tgn:name":"Tain Branch",
    "tgn:placetype":[
        "aat:300008699"
    ]
},
  "bbox": [],
  "geometry": {"coordinates":[-77.8333,36.8167],"type":"Point"}
}