{
  "id": 2394972,
  "type": "Feature",
  "properties": {
    "tgn:hierarchy":[
        "tgn:2394972",
        "tgn:1000001",
        "tgn:7012149",
        "tgn:1002983",
        "tgn:7007252",
        "tgn:7029392"
    ],
    "tgn:id":2394972,
    "tgn:name":"Holder Ditch",
    "tgn:placetype":[
        "aat:300006075"
    ]
},
  "bbox": [],
  "geometry": {"coordinates":[-87.1333,40.45],"type":"Point"}
}