<<<<<<< HEAD
{
  "id": 7353232,
  "type": "Feature",
  "properties": {
    "tgn:hierarchy":[
        "tgn:7353232",
        "tgn:1000001",
        "tgn:7005597",
        "tgn:7005560",
        "tgn:7029392"
    ],
    "tgn:id":7353232,
    "tgn:name":"Bayuco de Oro",
    "tgn:placetype":[
        "aat:300185707"
    ]
},
  "bbox": [],
  "geometry": {"coordinates":[-97.783333,24.4],"type":"Point"}
}
=======
{"geometry":{"type":"Point","coordinates":[-97.783333,24.400000]},"type":"Feature","properties":{"hierarchy":["tgn:7353232","tgn:1000001","tgn:7005597","tgn:7005560","tgn:7029392"],"placetype":["aat:300185707"],"id":7353232,"name:xx":"Bayuco de Oro"}}
>>>>>>> 03f74aca74312dbeaf24d7e61306dd6a786dc3d0
