{
  "id": 7318538,
  "type": "Feature",
  "properties": {
    "tgn:hierarchy":[
        "tgn:7318538",
        "tgn:1001702",
        "tgn:1000049",
        "tgn:1000002",
        "tgn:7029392"
    ],
    "tgn:id":7318538,
    "tgn:name":"Corbeta Papudo, Bah\u00eda",
    "tgn:placetype":[
        "aat:300132316"
    ]
},
  "bbox": [],
  "geometry": {"coordinates":[-75.324722,-50.3625],"type":"Point"}
}