{
  "id": 2517715,
  "type": "Feature",
  "properties": {
    "tgn:hierarchy":[
        "tgn:2517715",
        "tgn:1002232",
        "tgn:1000001",
        "tgn:7012149",
        "tgn:7007565",
        "tgn:7029392"
    ],
    "tgn:id":2517715,
    "tgn:name":"Mirey Run",
    "tgn:placetype":[
        "aat:300008699"
    ]
},
  "bbox": [],
  "geometry": {"coordinates":[-74.7333,39.2667],"type":"Point"}
}