{
  "id": 7223800,
  "type": "Feature",
  "properties": {
    "tgn:hierarchy":[
        "tgn:7223800",
        "tgn:7011170",
        "tgn:7002715",
        "tgn:1000003",
        "tgn:1000074",
        "tgn:7029392"
    ],
    "tgn:id":7223800,
    "tgn:name":"Orf\u00e1nion",
    "tgn:placetype":[
        "aat:300008347"
    ]
},
  "bbox": [],
  "geometry": {"coordinates":[23.95,40.783333],"type":"Point"}
}