{
  "id": 7230525,
  "type": "Feature",
  "properties": {
    "tgn:hierarchy":[
        "tgn:7230525",
        "tgn:7011163",
        "tgn:7002674",
        "tgn:1000003",
        "tgn:1000074",
        "tgn:7029392"
    ],
    "tgn:id":7230525,
    "tgn:name":"Khion\u00e1dhes",
    "tgn:placetype":[
        "aat:300008347"
    ]
},
  "bbox": [],
  "geometry": {"coordinates":[26.316667,41.483333],"type":"Point"}
}