{
  "id": 7372501,
  "type": "Feature",
  "properties": {
    "tgn:hierarchy":[
        "tgn:7372501",
        "tgn:7005581",
        "tgn:1000001",
        "tgn:7005560",
        "tgn:7029392"
    ],
    "tgn:id":7372501,
    "tgn:name":"La Junta",
    "tgn:placetype":[
        "aat:300008347"
    ]
},
  "bbox": [],
  "geometry": {"coordinates":[-107.783333,28.383333],"type":"Point"}
}