{
  "id": 2281103,
  "type": "Feature",
  "properties": {
    "tgn:hierarchy":[
        "tgn:2281103",
        "tgn:1000001",
        "tgn:1002738",
        "tgn:7012149",
        "tgn:7007565",
        "tgn:7029392"
    ],
    "tgn:id":2281103,
    "tgn:name":"Deep Hollow Branch",
    "tgn:placetype":[
        "aat:300008699"
    ]
},
  "bbox": [],
  "geometry": {"coordinates":[-74.2333,39.8667],"type":"Point"}
}