{
  "id": 7294537,
  "type": "Feature",
  "properties": {
    "tgn:hierarchy":[
        "tgn:7294537",
        "tgn:7002825",
        "tgn:7016622",
        "tgn:1000003",
        "tgn:1000095",
        "tgn:7029392"
    ],
    "tgn:id":7294537,
    "tgn:name":"Vega de San Mateo",
    "tgn:placetype":[
        "aat:300008347"
    ]
},
  "bbox": [],
  "geometry": {"coordinates":[-15.533333,28.016667],"type":"Point"}
}