{
  "id": 7493768,
  "type": "Feature",
  "properties": {
    "tgn:hierarchy":[
        "tgn:7493768",
        "tgn:1000004",
        "tgn:7491221",
        "tgn:1000141",
        "tgn:7029392"
    ],
    "tgn:id":7493768,
    "tgn:name":"Shiningbu Xi",
    "tgn:placetype":[
        "aat:300008699"
    ]
},
  "bbox": [],
  "geometry": {"coordinates":[121.415923,23.237154],"type":"Point"}
}