{
  "id": 7143566,
  "type": "Feature",
  "properties": {
    "tgn:hierarchy":[
        "tgn:7143566",
        "tgn:1000003",
        "tgn:7003677",
        "tgn:7000084",
        "tgn:7029392"
    ],
    "tgn:id":7143566,
    "tgn:name":"L\u00fcxheim",
    "tgn:placetype":[
        "aat:300008347"
    ]
},
  "bbox": [],
  "geometry": {"coordinates":[6.633333,50.766667],"type":"Point"}
}