{
  "id": 7246990,
  "type": "Feature",
  "properties": {
    "tgn:hierarchy":[
        "tgn:7246990",
        "tgn:7007877",
        "tgn:1000003",
        "tgn:1000063",
        "tgn:4012014",
        "tgn:7029392"
    ],
    "tgn:id":7246990,
    "tgn:name":"Culot du Bois",
    "tgn:placetype":[
        "aat:300008347"
    ]
},
  "bbox": [],
  "geometry": {"coordinates":[3.983333,50.65],"type":"Point"}
}