{
  "id": 7568109,
  "type": "Feature",
  "properties": {
    "tgn:hierarchy":[
        "tgn:7568109",
        "tgn:1000004",
        "tgn:7000198",
        "tgn:7031786",
        "tgn:7029392"
    ],
    "tgn:id":7568109,
    "tgn:name:en":"B\u0101j\u012br Nadi",
    "tgn:placetype":[
        "aat:300008699"
    ]
},
  "bbox": [],
  "geometry": {"coordinates":[78.704523,29.773128],"type":"Point"}
}