{
  "id": 2388757,
  "type": "Feature",
  "properties": {
    "tgn:hierarchy":[
        "tgn:2388757",
        "tgn:1000001",
        "tgn:2000459",
        "tgn:7012149",
        "tgn:7007250",
        "tgn:7029392"
    ],
    "tgn:id":2388757,
    "tgn:name":"Hidden Creek",
    "tgn:placetype":[
        "aat:300008706"
    ]
},
  "bbox": [],
  "geometry": {"coordinates":[-116.0333,44.1667],"type":"Point"}
}