{
  "id": 2640284,
  "type": "Feature",
  "properties": {
    "tgn:hierarchy":[
        "tgn:2640284",
        "tgn:2000258",
        "tgn:1000001",
        "tgn:7012149",
        "tgn:7007240",
        "tgn:7029392"
    ],
    "tgn:id":2640284,
    "tgn:name":"San Carlos Chacatos",
    "tgn:placetype":[
        "aat:300008347",
        "aat:300167671",
        "aat:300008486"
    ]
},
  "bbox": [],
  "geometry": {"coordinates":[-85.6833,30.35],"type":"Point"}
}