{
  "id": 7293748,
  "type": "Feature",
  "properties": {
    "tgn:hierarchy":[
        "tgn:7293748",
        "tgn:7002829",
        "tgn:1000003",
        "tgn:7002786",
        "tgn:1000095",
        "tgn:7029392"
    ],
    "tgn:id":7293748,
    "tgn:name":"Vilaug\u00edn",
    "tgn:placetype":[
        "aat:300008347"
    ]
},
  "bbox": [],
  "geometry": {"coordinates":[-6.866667,43.133333],"type":"Point"}
}