{
  "id": 2786003,
  "type": "Feature",
  "properties": {
    "tgn:hierarchy":[
        "tgn:2786003",
        "tgn:1000001",
        "tgn:7012149",
        "tgn:2001144",
        "tgn:7007522",
        "tgn:7029392"
    ],
    "tgn:id":2786003,
    "tgn:name":"Young Branch",
    "tgn:placetype":[
        "aat:300008699"
    ]
},
  "bbox": [],
  "geometry": {"coordinates":[-88.4667,34.6833],"type":"Point"}
}