{
  "id": 2270591,
  "type": "Feature",
  "properties": {
    "tgn:hierarchy":[
        "tgn:2270591",
        "tgn:1000001",
        "tgn:7012149",
        "tgn:2002194",
        "tgn:7007919",
        "tgn:7029392"
    ],
    "tgn:id":2270591,
    "tgn:name":"Crystal Pool",
    "tgn:placetype":[
        "aat:300006191"
    ]
},
  "bbox": [],
  "geometry": {"coordinates":[-82.15,36.6333],"type":"Point"}
}