<<<<<<< HEAD
{
  "id": 7110628,
  "type": "Feature",
  "properties": {
    "tgn:hierarchy":[
        "tgn:7110628",
        "tgn:1000003",
        "tgn:7000094",
        "tgn:7000084",
        "tgn:7029392"
    ],
    "tgn:id":7110628,
    "tgn:name":"Pulverhof",
    "tgn:placetype":[
        "aat:300008347"
    ]
},
  "bbox": [],
  "geometry": {"coordinates":[11.433333,53.466667],"type":"Point"}
}
=======
{"geometry":{"type":"Point","coordinates":[11.433333,53.466667]},"type":"Feature","properties":{"hierarchy":["tgn:7110628","tgn:1000003","tgn:7000094","tgn:7000084","tgn:7029392"],"placetype":["aat:300008347"],"id":7110628,"name:xx":"Pulverhof"}}
>>>>>>> 03f74aca74312dbeaf24d7e61306dd6a786dc3d0
