{
  "id": 7310427,
  "type": "Feature",
  "properties": {
    "tgn:hierarchy":[
        "tgn:7310427",
        "tgn:1001630",
        "tgn:1000049",
        "tgn:1000002",
        "tgn:7029392"
    ],
    "tgn:id":7310427,
    "tgn:name":"Nicolasa",
    "tgn:placetype":[
        "aat:300000206"
    ]
},
  "bbox": [],
  "geometry": {"coordinates":[-71.033333,-28.516667],"type":"Point"}
}