{
  "id": 2733690,
  "type": "Feature",
  "properties": {
    "tgn:hierarchy":[
        "tgn:2733690",
        "tgn:1000001",
        "tgn:7012149",
        "tgn:1002659",
        "tgn:7007710",
        "tgn:7029392"
    ],
    "tgn:id":2733690,
    "tgn:name":"Turner",
    "tgn:placetype":[
        "aat:300008347"
    ]
},
  "bbox": [],
  "geometry": {"coordinates":[-80.1833,41.2333],"type":"Point"}
}