{
  "id": 2062582,
  "type": "Feature",
  "properties": {
    "tgn:hierarchy":[
        "tgn:2062582",
        "tgn:1000001",
        "tgn:7012149",
        "tgn:2001388",
        "tgn:7007525",
        "tgn:7029392"
    ],
    "tgn:id":2062582,
    "tgn:name":"Red Willow",
    "tgn:placetype":[
        "aat:300387016"
    ]
},
  "bbox": [],
  "geometry": {"coordinates":[-100.4833,40.2167],"type":"Point"}
}