{
  "id": 7355716,
  "type": "Feature",
  "properties": {
    "tgn:hierarchy":[
        "tgn:7355716",
        "tgn:1000001",
        "tgn:7005589",
        "tgn:7005560",
        "tgn:7029392"
    ],
    "tgn:id":7355716,
    "tgn:name":"Cerna",
    "tgn:placetype":[
        "aat:300008347"
    ]
},
  "bbox": [],
  "geometry": {"coordinates":[-99.883333,26.55],"type":"Point"}
}