{
  "id": 7168991,
  "type": "Feature",
  "properties": {
    "tgn:hierarchy":[
        "tgn:7168991",
        "tgn:7003692",
        "tgn:1000003",
        "tgn:7000084",
        "tgn:7029392"
    ],
    "tgn:id":7168991,
    "tgn:name":"Haslerhof",
    "tgn:placetype":[
        "aat:300000206"
    ]
},
  "bbox": [],
  "geometry": {"coordinates":[8.683333,47.85],"type":"Point"}
}