{
  "id": 2494779,
  "type": "Feature",
  "properties": {
    "tgn:hierarchy":[
        "tgn:2494779",
        "tgn:1000001",
        "tgn:2002370",
        "tgn:7012149",
        "tgn:7007923",
        "tgn:7029392"
    ],
    "tgn:id":2494779,
    "tgn:name":"Martin Spring",
    "tgn:placetype":[
        "aat:300008697"
    ]
},
  "bbox": [],
  "geometry": {"coordinates":[-104.45,44.8667],"type":"Point"}
}