{
  "id": 2623339,
  "type": "Feature",
  "properties": {
    "tgn:hierarchy":[
        "tgn:2623339",
        "tgn:1000001",
        "tgn:7012149",
        "tgn:7019676",
        "tgn:7007566",
        "tgn:7029392"
    ],
    "tgn:id":2623339,
    "tgn:name":"Rock Canyon",
    "tgn:placetype":[
        "aat:300008761"
    ]
},
  "bbox": [],
  "geometry": {"coordinates":[-108.3333,35.6667],"type":"Point"}
}