{
  "id": 7163982,
  "type": "Feature",
  "properties": {
    "tgn:hierarchy":[
        "tgn:7163982",
        "tgn:1000003",
        "tgn:7003677",
        "tgn:7000084",
        "tgn:7029392"
    ],
    "tgn:id":7163982,
    "tgn:name":"Hoppen-Berg",
    "tgn:placetype":[
        "aat:300008777"
    ]
},
  "bbox": [],
  "geometry": {"coordinates":[7.816667,51.383333],"type":"Point"}
}