{
  "id": 7296470,
  "type": "Feature",
  "properties": {
    "tgn:hierarchy":[
        "tgn:7296470",
        "tgn:7002824",
        "tgn:1000003",
        "tgn:7002786",
        "tgn:1000095",
        "tgn:7029392"
    ],
    "tgn:id":7296470,
    "tgn:name":"Chanteiro, Ensenada de",
    "tgn:placetype":[
        "aat:300132317"
    ]
},
  "bbox": [],
  "geometry": {"coordinates":[-8.3125,43.448611],"type":"Point"}
}