{
  "id": 2237173,
  "type": "Feature",
  "properties": {
    "tgn:hierarchy":[
        "tgn:2237173",
        "tgn:1000001",
        "tgn:7012149",
        "tgn:2001722",
        "tgn:7007708",
        "tgn:7029392"
    ],
    "tgn:id":2237173,
    "tgn:name":"Chimney Lake",
    "tgn:placetype":[
        "aat:300008680"
    ]
},
  "bbox": [],
  "geometry": {"coordinates":[-117.4167,45.2833],"type":"Point"}
}