{
  "id": 2725451,
  "type": "Feature",
  "properties": {
    "tgn:hierarchy":[
        "tgn:2725451",
        "tgn:1000001",
        "tgn:7012149",
        "tgn:1002633",
        "tgn:7007252",
        "tgn:7029392"
    ],
    "tgn:id":2725451,
    "tgn:name":"Toon Hendricks Ditch",
    "tgn:placetype":[
        "aat:300006075"
    ]
},
  "bbox": [],
  "geometry": {"coordinates":[-86.0833,39.65],"type":"Point"}
}