{
  "id": 2164220,
  "type": "Feature",
  "properties": {
    "tgn:hierarchy":[
        "tgn:2164220",
        "tgn:7006450",
        "tgn:1000001",
        "tgn:2124089",
        "tgn:7012149",
        "tgn:7029392"
    ],
    "tgn:id":2164220,
    "tgn:name":"Berners Bay",
    "tgn:placetype":[
        "aat:300132316"
    ]
},
  "bbox": [],
  "geometry": {"coordinates":[-134.9667,58.7333],"type":"Point"}
}