{
  "id": 2140410,
  "type": "Feature",
  "properties": {
    "tgn:hierarchy":[
        "tgn:2140410",
        "tgn:1000001",
        "tgn:7012149",
        "tgn:2002057",
        "tgn:7007826",
        "tgn:7029392"
    ],
    "tgn:id":2140410,
    "tgn:name":"Auras Canyon",
    "tgn:placetype":[
        "aat:300008761"
    ]
},
  "bbox": [],
  "geometry": {"coordinates":[-104.05,29.45],"type":"Point"}
}