{
  "id": 2617815,
  "type": "Feature",
  "properties": {
    "tgn:hierarchy":[
        "tgn:2617815",
        "tgn:1000001",
        "tgn:7012149",
        "tgn:2001615",
        "tgn:7007706",
        "tgn:7029392"
    ],
    "tgn:id":2617815,
    "tgn:name":"Riders Pond",
    "tgn:placetype":[
        "aat:300006191"
    ]
},
  "bbox": [],
  "geometry": {"coordinates":[-82.6333,38.65],"type":"Point"}
}