{
  "id": 7358328,
  "type": "Feature",
  "properties": {
    "tgn:hierarchy":[
        "tgn:7358328",
        "tgn:1001853",
        "tgn:1000001",
        "tgn:7005560",
        "tgn:7029392"
    ],
    "tgn:id":7358328,
    "tgn:name":"Ejido San Juan del Cohetero",
    "tgn:placetype":[
        "aat:300008347"
    ]
},
  "bbox": [],
  "geometry": {"coordinates":[-101.75,25.583333],"type":"Point"}
}