{
  "id": 7439936,
  "type": "Feature",
  "properties": {
    "tgn:hierarchy":[
        "tgn:7439936",
        "tgn:7005583",
        "tgn:1000001",
        "tgn:7005560",
        "tgn:7029392"
    ],
    "tgn:id":7439936,
    "tgn:name":"San Mart\u00edn",
    "tgn:placetype":[
        "aat:300007783"
    ]
},
  "bbox": [],
  "geometry": {"coordinates":[-106.066667,26.733333],"type":"Point"}
}