{
  "id": 7553143,
  "type": "Feature",
  "properties": {
    "tgn:hierarchy":[
        "tgn:7553143",
        "tgn:1000004",
        "tgn:7000198",
        "tgn:1001894",
        "tgn:7029392"
    ],
    "tgn:id":7553143,
    "tgn:name:en":"Marhi",
    "tgn:placetype":[
        "aat:300008347"
    ]
},
  "bbox": [],
  "geometry": {"coordinates":[79.65573,22.57652],"type":"Point"}
}