{
  "id": 7275477,
  "type": "Feature",
  "properties": {
    "tgn:hierarchy":[
        "tgn:7275477",
        "tgn:1001702",
        "tgn:1000049",
        "tgn:1000002",
        "tgn:7029392"
    ],
    "tgn:id":7275477,
    "tgn:name":"Trompa, Punta",
    "tgn:placetype":[
        "aat:300386846"
    ]
},
  "bbox": [],
  "geometry": {"coordinates":[-71.166667,-54.916667],"type":"Point"}
}