<<<<<<< HEAD
{
  "id": 2769928,
  "type": "Feature",
  "properties": {
    "tgn:hierarchy":[
        "tgn:2769928",
        "tgn:1000001",
        "tgn:7006451",
        "tgn:7012149",
        "tgn:2000100",
        "tgn:7029392"
    ],
    "tgn:id":2769928,
    "tgn:name":"Wilbur Wash",
    "tgn:placetype":[
        "aat:300008701"
    ]
},
  "bbox": [],
  "geometry": {"coordinates":[-111.3667,31.5667],"type":"Point"}
}
=======
{"geometry":{"type":"Point","coordinates":[-111.366700,31.566700]},"type":"Feature","properties":{"hierarchy":["tgn:2769928","tgn:1000001","tgn:7006451","tgn:7012149","tgn:2000100","tgn:7029392"],"placetype":["aat:300008701"],"id":2769928,"name:xx":"Wilbur Wash"}}
>>>>>>> 03f74aca74312dbeaf24d7e61306dd6a786dc3d0
