{
  "id": 2769928,
  "type": "Feature",
  "properties": {
    "tgn:hierarchy":[
        "tgn:2769928",
        "tgn:1000001",
        "tgn:7006451",
        "tgn:7012149",
        "tgn:2000100",
        "tgn:7029392"
    ],
    "tgn:id":2769928,
    "tgn:name":"Wilbur Wash",
    "tgn:placetype":[
        "aat:300008701"
    ]
},
  "bbox": [],
  "geometry": {"coordinates":[-111.3667,31.5667],"type":"Point"}
}