{
  "id": 2203722,
  "type": "Feature",
  "properties": {
    "tgn:hierarchy":[
        "tgn:2203722",
        "tgn:1000001",
        "tgn:1002262",
        "tgn:7012149",
        "tgn:7007568",
        "tgn:7029392"
    ],
    "tgn:id":2203722,
    "tgn:name":"Bucks Brook",
    "tgn:placetype":[
        "aat:300008699"
    ]
},
  "bbox": [],
  "geometry": {"coordinates":[-75.7833,42.7167],"type":"Point"}
}