{
  "id": 2573942,
  "type": "Feature",
  "properties": {
    "tgn:hierarchy":[
        "tgn:2573942",
        "tgn:1000001",
        "tgn:7012149",
        "tgn:2000480",
        "tgn:7007250",
        "tgn:7029392"
    ],
    "tgn:id":2573942,
    "tgn:name":"Pee Wee Gulch",
    "tgn:placetype":[
        "aat:300008761"
    ]
},
  "bbox": [],
  "geometry": {"coordinates":[-116.3833,46.9833],"type":"Point"}
}