{
  "id": 2745232,
  "type": "Feature",
  "properties": {
    "tgn:hierarchy":[
        "tgn:2745232",
        "tgn:1000001",
        "tgn:7012149",
        "tgn:2002157",
        "tgn:7007919",
        "tgn:7029392"
    ],
    "tgn:id":2745232,
    "tgn:name":"Vince Ridge",
    "tgn:placetype":[
        "aat:300266640"
    ]
},
  "bbox": [],
  "geometry": {"coordinates":[-82.25,37.0833],"type":"Point"}
}