{
  "id": 2595821,
  "type": "Feature",
  "properties": {
    "tgn:hierarchy":[
        "tgn:2595821",
        "tgn:1002541",
        "tgn:1000001",
        "tgn:7012149",
        "tgn:7007711",
        "tgn:7029392"
    ],
    "tgn:id":2595821,
    "tgn:name":"Potowomut Neck",
    "tgn:placetype":[
        "aat:300008850"
    ]
},
  "bbox": [],
  "geometry": {"coordinates":[-71.4333,41.65],"type":"Point"}
}