{
  "id": 7367889,
  "type": "Feature",
  "properties": {
    "tgn:hierarchy":[
        "tgn:7367889",
        "tgn:7005586",
        "tgn:1000001",
        "tgn:7005560",
        "tgn:7029392"
    ],
    "tgn:id":7367889,
    "tgn:name":"Faro, Cerro el",
    "tgn:placetype":[
        "aat:300008795"
    ]
},
  "bbox": [],
  "geometry": {"coordinates":[-104.616667,20.35],"type":"Point"}
}