<<<<<<< HEAD
{
  "id": 7367889,
  "type": "Feature",
  "properties": {
    "tgn:hierarchy":[
        "tgn:7367889",
        "tgn:7005586",
        "tgn:1000001",
        "tgn:7005560",
        "tgn:7029392"
    ],
    "tgn:id":7367889,
    "tgn:name":"Faro, Cerro el",
    "tgn:placetype":[
        "aat:300008795"
    ]
},
  "bbox": [],
  "geometry": {"coordinates":[-104.616667,20.35],"type":"Point"}
}
=======
{"geometry":{"type":"Point","coordinates":[-104.616667,20.350000]},"type":"Feature","properties":{"hierarchy":["tgn:7367889","tgn:7005586","tgn:1000001","tgn:7005560","tgn:7029392"],"placetype":["aat:300008795"],"id":7367889,"name:xx":"Faro, Cerro el"}}
>>>>>>> 03f74aca74312dbeaf24d7e61306dd6a786dc3d0
