{
  "id": 7325867,
  "type": "Feature",
  "properties": {
    "tgn:hierarchy":[
        "tgn:7325867",
        "tgn:7002839",
        "tgn:7001158",
        "tgn:1000003",
        "tgn:1000095",
        "tgn:7029392"
    ],
    "tgn:id":7325867,
    "tgn:name":"Santa Ana, Arroyo de",
    "tgn:placetype":[
        "aat:300008699"
    ]
},
  "bbox": [],
  "geometry": {"coordinates":[-4.033333,41.233333],"type":"Point"}
}