{
  "id": 7235760,
  "type": "Feature",
  "properties": {
    "tgn:hierarchy":[
        "tgn:7235760",
        "tgn:7002690",
        "tgn:7012056",
        "tgn:1000003",
        "tgn:1000074",
        "tgn:7029392"
    ],
    "tgn:id":7235760,
    "tgn:name":"Ap\u00f3stoloi",
    "tgn:placetype":[
        "aat:300008347"
    ]
},
  "bbox": [],
  "geometry": {"coordinates":[24.633333,35.25],"type":"Point"}
}