{
  "id": 7576738,
  "type": "Feature",
  "properties": {
    "tgn:hierarchy":[
        "tgn:7576738",
        "tgn:1000004",
        "tgn:7000198",
        "tgn:7016722",
        "tgn:7029392"
    ],
    "tgn:id":7576738,
    "tgn:name:en":"Kharjhar",
    "tgn:placetype":[
        "aat:300008699"
    ]
},
  "bbox": [],
  "geometry": {"coordinates":[82.366667,27.466667],"type":"Point"}
}