{
  "id": 1123513,
  "type": "Feature",
  "properties": {
    "tgn:hierarchy":[
        "tgn:1123513",
        "tgn:1000004",
        "tgn:7000198",
        "tgn:7000799",
        "tgn:7029392"
    ],
    "tgn:id":1123513,
    "tgn:name":"Dras River",
    "tgn:placetype":[
        "aat:300008707",
        "aat:300008699"
    ]
},
  "bbox": [],
  "geometry": {"coordinates":[75.999949,34.58871],"type":"Point"}
}