<<<<<<< HEAD
{
  "id": 7480803,
  "type": "Feature",
  "properties": {
    "tgn:hierarchy":[
        "tgn:7480803",
        "tgn:7001010",
        "tgn:1000004",
        "tgn:1000141",
        "tgn:7029392"
    ],
    "tgn:id":7480803,
    "tgn:name":"Meilun Guozhong",
    "tgn:placetype":[
        "aat:300006495"
    ]
},
  "bbox": [],
  "geometry": {"coordinates":[121.628333,23.997222],"type":"Point"}
}
=======
{"geometry":{"type":"Point","coordinates":[121.628333,23.997222]},"type":"Feature","properties":{"hierarchy":["tgn:7480803","tgn:7001010","tgn:1000004","tgn:1000141","tgn:7029392"],"placetype":["aat:300006495"],"id":7480803,"name:xx":"Meilun Guozhong"}}
>>>>>>> 03f74aca74312dbeaf24d7e61306dd6a786dc3d0
