{
  "id": 7480803,
  "type": "Feature",
  "properties": {
    "tgn:hierarchy":[
        "tgn:7480803",
        "tgn:7001010",
        "tgn:1000004",
        "tgn:1000141",
        "tgn:7029392"
    ],
    "tgn:id":7480803,
    "tgn:name":"Meilun Guozhong",
    "tgn:placetype":[
        "aat:300006495"
    ]
},
  "bbox": [],
  "geometry": {"coordinates":[121.628333,23.997222],"type":"Point"}
}