{
  "id": 2284956,
  "type": "Feature",
  "properties": {
    "tgn:hierarchy":[
        "tgn:2284956",
        "tgn:1000001",
        "tgn:2001429",
        "tgn:7012149",
        "tgn:7007566",
        "tgn:7029392"
    ],
    "tgn:id":2284956,
    "tgn:name":"Devil Canyon",
    "tgn:placetype":[
        "aat:300008761"
    ]
},
  "bbox": [],
  "geometry": {"coordinates":[-108.7833,33.85],"type":"Point"}
}