{
  "id": 1039232,
  "type": "Feature",
  "properties": {
    "tgn:hierarchy":[
        "tgn:1039232",
        "tgn:7003692",
        "tgn:1000003",
        "tgn:7000084",
        "tgn:7029392"
    ],
    "tgn:id":1039232,
    "tgn:name":"Gerabronn",
    "tgn:placetype":[
        "aat:300008347"
    ]
},
  "bbox": [],
  "geometry": {"coordinates":[9.921389,49.251111],"type":"Point"}
}