{
  "id": 7591903,
  "type": "Feature",
  "properties": {
    "tgn:hierarchy":[
        "tgn:7591903",
        "tgn:1000004",
        "tgn:7000198",
        "tgn:7000799",
        "tgn:7029392"
    ],
    "tgn:id":7591903,
    "tgn:name:en":"Tabela",
    "tgn:placetype":[
        "aat:300008347"
    ]
},
  "bbox": [],
  "geometry": {"coordinates":[74.241667,33.163889],"type":"Point"}
}