{
  "id": 7118355,
  "type": "Feature",
  "properties": {
    "tgn:hierarchy":[
        "tgn:7118355",
        "tgn:1000003",
        "tgn:7003676",
        "tgn:7000084",
        "tgn:7029392"
    ],
    "tgn:id":7118355,
    "tgn:name":"Pommoissel",
    "tgn:placetype":[
        "aat:300008347"
    ]
},
  "bbox": [],
  "geometry": {"coordinates":[10.866667,53.166667],"type":"Point"}
}