{
  "id": 2383574,
  "type": "Feature",
  "properties": {
    "tgn:hierarchy":[
        "tgn:2383574",
        "tgn:1000001",
        "tgn:7012149",
        "tgn:2000491",
        "tgn:7007250",
        "tgn:7029392"
    ],
    "tgn:id":2383574,
    "tgn:name":"Heather Lake",
    "tgn:placetype":[
        "aat:300008680"
    ]
},
  "bbox": [],
  "geometry": {"coordinates":[-115.25,46.95],"type":"Point"}
}