{
  "id": 7077364,
  "type": "Feature",
  "properties": {
    "tgn:hierarchy":[
        "tgn:7077364",
        "tgn:1000003",
        "tgn:7003676",
        "tgn:7000084",
        "tgn:7029392"
    ],
    "tgn:id":7077364,
    "tgn:name":"Ziegenberg",
    "tgn:placetype":[
        "aat:300008347"
    ]
},
  "bbox": [],
  "geometry": {"coordinates":[10.016667,52.033333],"type":"Point"}
}