<<<<<<< HEAD
{
  "id": 7055322,
  "type": "Feature",
  "properties": {
    "tgn:hierarchy":[
        "tgn:7055322",
        "tgn:7003129",
        "tgn:1000003",
        "tgn:7008516",
        "tgn:1000080",
        "tgn:7029392"
    ],
    "tgn:id":7055322,
    "tgn:name":"Linaro",
    "tgn:placetype":[
        "aat:300008347"
    ]
},
  "bbox": [],
  "geometry": {"coordinates":[12.1,44.0],"type":"Point"}
}
=======
{"geometry":{"type":"Point","coordinates":[12.100000,44.000000]},"type":"Feature","properties":{"hierarchy":["tgn:7055322","tgn:7003129","tgn:1000003","tgn:7008516","tgn:1000080","tgn:7029392"],"placetype":["aat:300008347"],"id":7055322,"name:xx":"Linaro"}}
>>>>>>> 03f74aca74312dbeaf24d7e61306dd6a786dc3d0
