{
  "id": 1138679,
  "type": "Feature",
  "properties": {
    "tgn:hierarchy":[
        "tgn:1138679",
        "tgn:1000004",
        "tgn:7002435",
        "tgn:7011524",
        "tgn:7029392"
    ],
    "tgn:id":1138679,
    "tgn:name":"Zel\u00ebnaya Roshcha",
    "tgn:placetype":[
        "aat:300008347"
    ]
},
  "bbox": [],
  "geometry": {"coordinates":[52.0333,54.4833],"type":"Point"}
}