{
  "id": 7185212,
  "type": "Feature",
  "properties": {
    "tgn:hierarchy":[
        "tgn:7185212",
        "tgn:1000003",
        "tgn:7003688",
        "tgn:7000084",
        "tgn:7029392"
    ],
    "tgn:id":7185212,
    "tgn:name":"Glindhof",
    "tgn:placetype":[
        "aat:300000206"
    ]
},
  "bbox": [],
  "geometry": {"coordinates":[9.633333,53.85],"type":"Point"}
}