{
  "id": 7442162,
  "type": "Feature",
  "properties": {
    "tgn:hierarchy":[
        "tgn:7442162",
        "tgn:7002445",
        "tgn:1000003",
        "tgn:7008165",
        "tgn:7008591",
        "tgn:7029392"
    ],
    "tgn:id":7442162,
    "tgn:name:en":"Warnham Flats",
    "tgn:placetype":[
        "aat:300386970"
    ]
},
  "bbox": [],
  "geometry": {"coordinates":[-1.75,55.616667],"type":"Point"}
}