{
  "id": 2162147,
  "type": "Feature",
  "properties": {
    "tgn:hierarchy":[
        "tgn:2162147",
        "tgn:1000001",
        "tgn:7012149",
        "tgn:1003038",
        "tgn:7007517",
        "tgn:7029392"
    ],
    "tgn:id":2162147,
    "tgn:name":"Belmont Hill",
    "tgn:placetype":[
        "aat:300008798"
    ]
},
  "bbox": [],
  "geometry": {"coordinates":[-71.7833,42.2667],"type":"Point"}
}