{
  "id": 7389902,
  "type": "Feature",
  "properties": {
    "tgn:hierarchy":[
        "tgn:7389902",
        "tgn:7005581",
        "tgn:1000001",
        "tgn:7005560",
        "tgn:7029392"
    ],
    "tgn:id":7389902,
    "tgn:name":"Salitre, Puerto del",
    "tgn:placetype":[
        "aat:300259572"
    ]
},
  "bbox": [],
  "geometry": {"coordinates":[-107.55,29.466667],"type":"Point"}
}