{
  "id": 2633694,
  "type": "Feature",
  "properties": {
    "tgn:hierarchy":[
        "tgn:2633694",
        "tgn:1000001",
        "tgn:2000698",
        "tgn:7012149",
        "tgn:7007254",
        "tgn:7029392"
    ],
    "tgn:id":2633694,
    "tgn:name":"Rush Creek",
    "tgn:placetype":[
        "aat:300008706"
    ]
},
  "bbox": [],
  "geometry": {"coordinates":[-98.0833,37.35],"type":"Point"}
}