{
  "id": 2300502,
  "type": "Feature",
  "properties": {
    "tgn:hierarchy":[
        "tgn:2300502",
        "tgn:1000001",
        "tgn:7012149",
        "tgn:2001613",
        "tgn:7007706",
        "tgn:7029392"
    ],
    "tgn:id":2300502,
    "tgn:name":"Dumm Ridge",
    "tgn:placetype":[
        "aat:300266640"
    ]
},
  "bbox": [],
  "geometry": {"coordinates":[-82.6667,39.4667],"type":"Point"}
}