{
  "id": 2485538,
  "type": "Feature",
  "properties": {
    "tgn:hierarchy":[
        "tgn:2485538",
        "tgn:1000001",
        "tgn:2001435",
        "tgn:7012149",
        "tgn:7007566",
        "tgn:7029392"
    ],
    "tgn:id":2485538,
    "tgn:name":"Lawyer Tank",
    "tgn:placetype":[
        "aat:300006191"
    ]
},
  "bbox": [],
  "geometry": {"coordinates":[-106.75,32.6333],"type":"Point"}
}