{
  "id": 1046578,
  "type": "Feature",
  "properties": {
    "tgn:hierarchy":[
        "tgn:1046578",
        "tgn:1003440",
        "tgn:1000003",
        "tgn:7003124",
        "tgn:1000080",
        "tgn:7029392"
    ],
    "tgn:id":1046578,
    "tgn:name":"San Martino in Badia",
    "tgn:placetype":[
        "aat:300008347"
    ]
},
  "bbox": [],
  "geometry": {"coordinates":[11.8667,46.6833],"type":"Point"}
}