{
  "id": 2750541,
  "type": "Feature",
  "properties": {
    "tgn:hierarchy":[
        "tgn:2750541",
        "tgn:1000001",
        "tgn:2000469",
        "tgn:7012149",
        "tgn:7007250",
        "tgn:7029392"
    ],
    "tgn:id":2750541,
    "tgn:name":"Wapito Point",
    "tgn:placetype":[
        "aat:300008798"
    ]
},
  "bbox": [],
  "geometry": {"coordinates":[-114.9333,46.7833],"type":"Point"}
}