{
  "id": 2193348,
  "type": "Feature",
  "properties": {
    "tgn:hierarchy":[
        "tgn:2193348",
        "tgn:1000001",
        "tgn:7012149",
        "tgn:2001067",
        "tgn:7007521",
        "tgn:7029392"
    ],
    "tgn:id":2193348,
    "tgn:name":"Breezy Point",
    "tgn:placetype":[
        "aat:300008850"
    ]
},
  "bbox": [],
  "geometry": {"coordinates":[-92.4333,47.8667],"type":"Point"}
}