{
  "id": 2265121,
  "type": "Feature",
  "properties": {
    "tgn:hierarchy":[
        "tgn:2265121",
        "tgn:1000001",
        "tgn:7012149",
        "tgn:7014510",
        "tgn:7007920",
        "tgn:7029392"
    ],
    "tgn:id":2265121,
    "tgn:name":"Cranberry Lake",
    "tgn:placetype":[
        "aat:300008680"
    ]
},
  "bbox": [],
  "geometry": {"coordinates":[-122.2167,48.55],"type":"Point"}
}