{
  "id": 7060647,
  "type": "Feature",
  "properties": {
    "tgn:hierarchy":[
        "tgn:7060647",
        "tgn:7003669",
        "tgn:1000003",
        "tgn:7000084",
        "tgn:7029392"
    ],
    "tgn:id":7060647,
    "tgn:name":"Augenthal",
    "tgn:placetype":[
        "aat:300008347"
    ]
},
  "bbox": [],
  "geometry": {"coordinates":[12.466667,48.35],"type":"Point"}
}