{
  "id": 2619162,
  "type": "Feature",
  "properties": {
    "tgn:hierarchy":[
        "tgn:2619162",
        "tgn:1000001",
        "tgn:7012149",
        "tgn:7029392"
    ],
    "tgn:id":2619162,
    "tgn:name":"Riley Creek",
    "tgn:placetype":[
        "aat:300008706"
    ]
},
  "bbox": [],
  "geometry": {"coordinates":[-88.45,45.9333],"type":"Point"}
}