{
  "id": 7469084,
  "type": "Feature",
  "properties": {
    "tgn:hierarchy":[
        "tgn:7469084",
        "tgn:1000004",
        "tgn:7004300",
        "tgn:1000141",
        "tgn:7029392"
    ],
    "tgn:id":7469084,
    "tgn:name":"Guanghua",
    "tgn:placetype":[
        "aat:300008347"
    ]
},
  "bbox": [],
  "geometry": {"coordinates":[119.566432,23.551761],"type":"Point"}
}