{
  "id": 7314741,
  "type": "Feature",
  "properties": {
    "tgn:hierarchy":[
        "tgn:7314741",
        "tgn:1001692",
        "tgn:1000049",
        "tgn:1000002",
        "tgn:7029392"
    ],
    "tgn:id":7314741,
    "tgn:name":"Lilicura",
    "tgn:placetype":[
        "aat:300008347"
    ]
},
  "bbox": [],
  "geometry": {"coordinates":[-73.466667,-38.583333],"type":"Point"}
}