<<<<<<< HEAD
{
  "id": 2330623,
  "type": "Feature",
  "properties": {
    "tgn:hierarchy":[
        "tgn:2330623",
        "tgn:1000001",
        "tgn:2002367",
        "tgn:7012149",
        "tgn:7007923",
        "tgn:7029392"
    ],
    "tgn:id":2330623,
    "tgn:name":"Flat Creek",
    "tgn:placetype":[
        "aat:300008706"
    ]
},
  "bbox": [],
  "geometry": {"coordinates":[-105.1833,44.6667],"type":"Point"}
}
=======
{"geometry":{"type":"Point","coordinates":[-105.183300,44.666700]},"type":"Feature","properties":{"hierarchy":["tgn:2330623","tgn:1000001","tgn:2002367","tgn:7012149","tgn:7007923","tgn:7029392"],"placetype":["aat:300008706"],"id":2330623,"name:xx":"Flat Creek"}}
>>>>>>> 03f74aca74312dbeaf24d7e61306dd6a786dc3d0
