{
  "id": 2418983,
  "type": "Feature",
  "properties": {
    "tgn:hierarchy":[
        "tgn:2418983",
        "tgn:1000001",
        "tgn:1002293",
        "tgn:7012149",
        "tgn:7007708",
        "tgn:7029392"
    ],
    "tgn:id":2418983,
    "tgn:name":"James O Fisher Reservoir",
    "tgn:placetype":[
        "aat:300006191"
    ]
},
  "bbox": [],
  "geometry": {"coordinates":[-122.8667,45.7833],"type":"Point"}
}