{
  "id": 7410311,
  "type": "Feature",
  "properties": {
    "tgn:hierarchy":[
        "tgn:7410311",
        "tgn:1000001",
        "tgn:7005592",
        "tgn:7005560",
        "tgn:7029392"
    ],
    "tgn:id":7410311,
    "tgn:name":"Mar\u00eda de la Torre, R\u00edo",
    "tgn:placetype":[
        "aat:300008699"
    ]
},
  "bbox": [],
  "geometry": {"coordinates":[-97.269444,19.940278],"type":"Point"}
}