{
  "id": 7356951,
  "type": "Feature",
  "properties": {
    "tgn:hierarchy":[
        "tgn:7356951",
        "tgn:1000001",
        "tgn:1001960",
        "tgn:7005560",
        "tgn:7029392"
    ],
    "tgn:id":7356951,
    "tgn:name":"Chinotahueca",
    "tgn:placetype":[
        "aat:300008347"
    ]
},
  "bbox": [],
  "geometry": {"coordinates":[-109.516667,27.016667],"type":"Point"}
}