<<<<<<< HEAD
{
  "id": 2334544,
  "type": "Feature",
  "properties": {
    "tgn:hierarchy":[
        "tgn:2334544",
        "tgn:1000001",
        "tgn:7012149",
        "tgn:2001500",
        "tgn:7007709",
        "tgn:7029392"
    ],
    "tgn:id":2334544,
    "tgn:name":"Forest Valley",
    "tgn:placetype":[
        "aat:300008347"
    ]
},
  "bbox": [],
  "geometry": {"coordinates":[-79.8333,36.1],"type":"Point"}
}
=======
{"geometry":{"type":"Point","coordinates":[-79.833300,36.100000]},"type":"Feature","properties":{"hierarchy":["tgn:2334544","tgn:1000001","tgn:7012149","tgn:2001500","tgn:7007709","tgn:7029392"],"placetype":["aat:300008347"],"id":2334544,"name:xx":"Forest Valley"}}
>>>>>>> 03f74aca74312dbeaf24d7e61306dd6a786dc3d0
