<<<<<<< HEAD
{
  "id": 2251745,
  "type": "Feature",
  "properties": {
    "tgn:hierarchy":[
        "tgn:2251745",
        "tgn:1000001",
        "tgn:7012149",
        "tgn:1003022",
        "tgn:7007252",
        "tgn:7029392"
    ],
    "tgn:id":2251745,
    "tgn:name":"Compton Ditch",
    "tgn:placetype":[
        "aat:300006075"
    ]
},
  "bbox": [],
  "geometry": {"coordinates":[-85.6167,41.1333],"type":"Point"}
}
=======
{"geometry":{"type":"Point","coordinates":[-85.616700,41.133300]},"type":"Feature","properties":{"hierarchy":["tgn:2251745","tgn:1000001","tgn:7012149","tgn:1003022","tgn:7007252","tgn:7029392"],"placetype":["aat:300006075"],"id":2251745,"name:xx":"Compton Ditch"}}
>>>>>>> 03f74aca74312dbeaf24d7e61306dd6a786dc3d0
