{
  "id": 7536074,
  "type": "Feature",
  "properties": {
    "tgn:hierarchy":[
        "tgn:7536074",
        "tgn:7001242",
        "tgn:7001311",
        "tgn:7016833",
        "tgn:7029392"
    ],
    "tgn:id":7536074,
    "tgn:name:en":"Khr\u0101za, Gebel el-",
    "tgn:placetype":[
        "aat:300008795"
    ]
},
  "bbox": [],
  "geometry": {"coordinates":[32.816667,27.916667],"type":"Point"}
}