{
  "id": 2308726,
  "type": "Feature",
  "properties": {
    "tgn:hierarchy":[
        "tgn:2308726",
        "tgn:7013349",
        "tgn:1000001",
        "tgn:7012149",
        "tgn:7007708",
        "tgn:7029392"
    ],
    "tgn:id":2308726,
    "tgn:name":"East Pine Creek",
    "tgn:placetype":[
        "aat:300008706"
    ]
},
  "bbox": [],
  "geometry": {"coordinates":[-117.1167,45.0333],"type":"Point"}
}