<<<<<<< HEAD
{
  "id": 2409793,
  "type": "Feature",
  "properties": {
    "tgn:hierarchy":[
        "tgn:2409793",
        "tgn:1000001",
        "tgn:7012149",
        "tgn:1002591",
        "tgn:7007255",
        "tgn:7029392"
    ],
    "tgn:id":2409793,
    "tgn:name":"Iller Branch",
    "tgn:placetype":[
        "aat:300008699"
    ]
},
  "bbox": [],
  "geometry": {"coordinates":[-83.1333,38.5667],"type":"Point"}
}
=======
{"geometry":{"type":"Point","coordinates":[-83.133300,38.566700]},"type":"Feature","properties":{"hierarchy":["tgn:2409793","tgn:1000001","tgn:7012149","tgn:1002591","tgn:7007255","tgn:7029392"],"placetype":["aat:300008699"],"id":2409793,"name:xx":"Iller Branch"}}
>>>>>>> 03f74aca74312dbeaf24d7e61306dd6a786dc3d0
