{
  "id": 2316474,
  "type": "Feature",
  "properties": {
    "tgn:hierarchy":[
        "tgn:2316474",
        "tgn:1000001",
        "tgn:7012149",
        "tgn:2000837",
        "tgn:7007255",
        "tgn:7029392"
    ],
    "tgn:id":2316474,
    "tgn:name":"Elswick Fork",
    "tgn:placetype":[
        "aat:300008699"
    ]
},
  "bbox": [],
  "geometry": {"coordinates":[-82.3333,37.3667],"type":"Point"}
}