{
  "id": 2636050,
  "type": "Feature",
  "properties": {
    "tgn:hierarchy":[
        "tgn:2636050",
        "tgn:1000001",
        "tgn:7012149",
        "tgn:2001709",
        "tgn:7007708",
        "tgn:7029392"
    ],
    "tgn:id":2636050,
    "tgn:name":"Saddle Draw",
    "tgn:placetype":[
        "aat:300008761"
    ]
},
  "bbox": [],
  "geometry": {"coordinates":[-118.2333,43.3167],"type":"Point"}
}