{
  "id": 1102335,
  "type": "Feature",
  "properties": {
    "tgn:hierarchy":[
        "tgn:1102335",
        "tgn:1000001",
        "tgn:7012149",
        "tgn:7029392"
    ],
    "tgn:id":1102335,
    "tgn:name":"Interstate State Park",
    "tgn:placetype":[
        "aat:300008192"
    ]
},
  "bbox": [],
  "geometry": {"coordinates":[-92.6667,45.3833],"type":"Point"}
}