{
  "id": 7398758,
  "type": "Feature",
  "properties": {
    "tgn:hierarchy":[
        "tgn:7398758",
        "tgn:1000001",
        "tgn:1001893",
        "tgn:7005560",
        "tgn:7029392"
    ],
    "tgn:id":7398758,
    "tgn:name":"El Moral",
    "tgn:placetype":[
        "aat:300008347"
    ]
},
  "bbox": [],
  "geometry": {"coordinates":[-99.673056,19.020833],"type":"Point"}
}