{
  "id": 7534739,
  "type": "Feature",
  "properties": {
    "tgn:hierarchy":[
        "tgn:7534739",
        "tgn:7001242",
        "tgn:7001311",
        "tgn:7016833",
        "tgn:7029392"
    ],
    "tgn:id":7534739,
    "tgn:name:en":"Mall\u0101\u1e29at Umm 'Ushsh",
    "tgn:placetype":[
        "aat:300386856"
    ]
},
  "bbox": [],
  "geometry": {"coordinates":[31.051046,28.656034],"type":"Point"}
}