{
  "id": 7403778,
  "type": "Feature",
  "properties": {
    "tgn:hierarchy":[
        "tgn:7403778",
        "tgn:7005578",
        "tgn:1000001",
        "tgn:7005560",
        "tgn:7029392"
    ],
    "tgn:id":7403778,
    "tgn:name":"Mar\u00eda de la Luz",
    "tgn:placetype":[
        "aat:300008347"
    ]
},
  "bbox": [],
  "geometry": {"coordinates":[-91.233333,18.523611],"type":"Point"}
}