{
  "id": 2383696,
  "type": "Feature",
  "properties": {
    "tgn:hierarchy":[
        "tgn:2383696",
        "tgn:1000001",
        "tgn:2002103",
        "tgn:7012149",
        "tgn:7007827",
        "tgn:7029392"
    ],
    "tgn:id":2383696,
    "tgn:name":"Heber Spring",
    "tgn:placetype":[
        "aat:300008697"
    ]
},
  "bbox": [],
  "geometry": {"coordinates":[-111.4833,41.7167],"type":"Point"}
}