{
  "id": 2002359,
  "type": "Feature",
  "properties": {
    "tgn:hierarchy":[
        "tgn:2002359",
        "tgn:1000001",
        "tgn:7012149",
        "tgn:7007922",
        "tgn:7029392"
    ],
    "tgn:id":2002359,
    "tgn:name":"Vilas",
    "tgn:placetype":[
        "aat:300387145",
        "aat:300000771"
    ]
},
  "bbox": [],
  "geometry": {"coordinates":[-89.4667,46.0667],"type":"Point"}
}