<<<<<<< HEAD
{
  "id": 2339850,
  "type": "Feature",
  "properties": {
    "tgn:hierarchy":[
        "tgn:2339850",
        "tgn:1000001",
        "tgn:7012149",
        "tgn:1002599",
        "tgn:7007708",
        "tgn:7029392"
    ],
    "tgn:id":2339850,
    "tgn:name":"Freeman Creek",
    "tgn:placetype":[
        "aat:300008706"
    ]
},
  "bbox": [],
  "geometry": {"coordinates":[-124.0,44.4],"type":"Point"}
}
=======
{"geometry":{"type":"Point","coordinates":[-124.000000,44.400000]},"type":"Feature","properties":{"hierarchy":["tgn:2339850","tgn:1000001","tgn:7012149","tgn:1002599","tgn:7007708","tgn:7029392"],"placetype":["aat:300008706"],"id":2339850,"name:xx":"Freeman Creek"}}
>>>>>>> 03f74aca74312dbeaf24d7e61306dd6a786dc3d0
