{
  "id": 7139403,
  "type": "Feature",
  "properties": {
    "tgn:hierarchy":[
        "tgn:7139403",
        "tgn:7003669",
        "tgn:1000003",
        "tgn:7000084",
        "tgn:7029392"
    ],
    "tgn:id":7139403,
    "tgn:name":"Leinach",
    "tgn:placetype":[
        "aat:300008347"
    ]
},
  "bbox": [],
  "geometry": {"coordinates":[10.416667,50.233333],"type":"Point"}
}