<<<<<<< HEAD
{
  "id": 7371566,
  "type": "Feature",
  "properties": {
    "tgn:hierarchy":[
        "tgn:7371566",
        "tgn:7005585",
        "tgn:1000001",
        "tgn:7005560",
        "tgn:7029392"
    ],
    "tgn:id":7371566,
    "tgn:name":"La Morena",
    "tgn:placetype":[
        "aat:300008347"
    ]
},
  "bbox": [],
  "geometry": {"coordinates":[-101.25,17.733333],"type":"Point"}
}
=======
{"geometry":{"type":"Point","coordinates":[-101.250000,17.733333]},"type":"Feature","properties":{"hierarchy":["tgn:7371566","tgn:7005585","tgn:1000001","tgn:7005560","tgn:7029392"],"placetype":["aat:300008347"],"id":7371566,"name:xx":"La Morena"}}
>>>>>>> 03f74aca74312dbeaf24d7e61306dd6a786dc3d0
