{
  "id": 7371566,
  "type": "Feature",
  "properties": {
    "tgn:hierarchy":[
        "tgn:7371566",
        "tgn:7005585",
        "tgn:1000001",
        "tgn:7005560",
        "tgn:7029392"
    ],
    "tgn:id":7371566,
    "tgn:name":"La Morena",
    "tgn:placetype":[
        "aat:300008347"
    ]
},
  "bbox": [],
  "geometry": {"coordinates":[-101.25,17.733333],"type":"Point"}
}