{
  "id": 2201133,
  "type": "Feature",
  "properties": {
    "tgn:hierarchy":[
        "tgn:2201133",
        "tgn:7006450",
        "tgn:1000001",
        "tgn:2124053",
        "tgn:7012149",
        "tgn:7029392"
    ],
    "tgn:id":2201133,
    "tgn:name":"Bubb Creek",
    "tgn:placetype":[
        "aat:300008706"
    ]
},
  "bbox": [],
  "geometry": {"coordinates":[-147.6333,62.05],"type":"Point"}
}