{
  "id": 7546276,
  "type": "Feature",
  "properties": {
    "tgn:hierarchy":[
        "tgn:7546276",
        "tgn:1000004",
        "tgn:7000198",
        "tgn:7016788",
        "tgn:7029392"
    ],
    "tgn:id":7546276,
    "tgn:name:en":"Baksheu",
    "tgn:placetype":[
        "aat:300008347"
    ]
},
  "bbox": [],
  "geometry": {"coordinates":[73.806121,27.594194],"type":"Point"}
}