{
  "id": 2108013,
  "type": "Feature",
  "properties": {
    "tgn:hierarchy":[
        "tgn:2108013",
        "tgn:1000001",
        "tgn:7012149",
        "tgn:1002898",
        "tgn:7007826",
        "tgn:7029392"
    ],
    "tgn:id":2108013,
    "tgn:name":"Thedford",
    "tgn:placetype":[
        "aat:300008347"
    ]
},
  "bbox": [],
  "geometry": {"coordinates":[-95.3833,32.4833],"type":"Point"}
}