{
  "id": 2109262,
  "type": "Feature",
  "properties": {
    "tgn:hierarchy":[
        "tgn:2109262",
        "tgn:1000001",
        "tgn:7012149",
        "tgn:2002112",
        "tgn:7007827",
        "tgn:7029392"
    ],
    "tgn:id":2109262,
    "tgn:name":"Sharp",
    "tgn:placetype":[
        "aat:300387016"
    ]
},
  "bbox": [],
  "geometry": {"coordinates":[-111.8833,39.6167],"type":"Point"}
}