{
  "id": 7202600,
  "type": "Feature",
  "properties": {
    "tgn:hierarchy":[
        "tgn:7202600",
        "tgn:1000003",
        "tgn:7003676",
        "tgn:7000084",
        "tgn:7029392"
    ],
    "tgn:id":7202600,
    "tgn:name":"Br\u00fcttendorf",
    "tgn:placetype":[
        "aat:300008347"
    ]
},
  "bbox": [],
  "geometry": {"coordinates":[9.283333,53.266667],"type":"Point"}
}