{
  "id": 7585694,
  "type": "Feature",
  "properties": {
    "tgn:hierarchy":[
        "tgn:7585694",
        "tgn:1000004",
        "tgn:7000198",
        "tgn:7000799",
        "tgn:7029392"
    ],
    "tgn:id":7585694,
    "tgn:name:en":"Gamber",
    "tgn:placetype":[
        "aat:300008347"
    ]
},
  "bbox": [],
  "geometry": {"coordinates":[74.245049,33.413029],"type":"Point"}
}