{
  "id": 2176535,
  "type": "Feature",
  "properties": {
    "tgn:hierarchy":[
        "tgn:2176535",
        "tgn:1000001",
        "tgn:2000950",
        "tgn:7012149",
        "tgn:7007520",
        "tgn:7029392"
    ],
    "tgn:id":2176535,
    "tgn:name":"Black Lake",
    "tgn:placetype":[
        "aat:300008680"
    ]
},
  "bbox": [],
  "geometry": {"coordinates":[-84.7833,45.1167],"type":"Point"}
}