<<<<<<< HEAD
{
  "id": 2339903,
  "type": "Feature",
  "properties": {
    "tgn:hierarchy":[
        "tgn:2339903",
        "tgn:1000001",
        "tgn:2000201",
        "tgn:7012149",
        "tgn:7007158",
        "tgn:7029392"
    ],
    "tgn:id":2339903,
    "tgn:name":"Freeman Mine",
    "tgn:placetype":[
        "aat:300000390"
    ]
},
  "bbox": [],
  "geometry": {"coordinates":[-105.5,39.75],"type":"Point"}
}
=======
{"geometry":{"type":"Point","coordinates":[-105.500000,39.750000]},"type":"Feature","properties":{"hierarchy":["tgn:2339903","tgn:1000001","tgn:2000201","tgn:7012149","tgn:7007158","tgn:7029392"],"placetype":["aat:300000390"],"id":2339903,"name:xx":"Freeman Mine"}}
>>>>>>> 03f74aca74312dbeaf24d7e61306dd6a786dc3d0
