<<<<<<< HEAD
{
  "id": 7118294,
  "type": "Feature",
  "properties": {
    "tgn:hierarchy":[
        "tgn:7118294",
        "tgn:1000003",
        "tgn:7000094",
        "tgn:7000084",
        "tgn:7029392"
    ],
    "tgn:id":7118294,
    "tgn:name":"Papen-Berg",
    "tgn:placetype":[
        "aat:300008777"
    ]
},
  "bbox": [],
  "geometry": {"coordinates":[12.9,54.2],"type":"Point"}
}
=======
{"geometry":{"type":"Point","coordinates":[12.900000,54.200000]},"type":"Feature","properties":{"hierarchy":["tgn:7118294","tgn:1000003","tgn:7000094","tgn:7000084","tgn:7029392"],"placetype":["aat:300008777"],"id":7118294,"name:xx":"Papen-Berg"}}
>>>>>>> 03f74aca74312dbeaf24d7e61306dd6a786dc3d0
