{
  "id": 7434936,
  "type": "Feature",
  "properties": {
    "tgn:hierarchy":[
        "tgn:7434936",
        "tgn:1000001",
        "tgn:7005600",
        "tgn:7005560",
        "tgn:7029392"
    ],
    "tgn:id":7434936,
    "tgn:name":"Xabanch\u00e9",
    "tgn:placetype":[
        "aat:300008347"
    ]
},
  "bbox": [],
  "geometry": {"coordinates":[-88.75,20.233333],"type":"Point"}
}