{
  "id": 7546346,
  "type": "Feature",
  "properties": {
    "tgn:hierarchy":[
        "tgn:7546346",
        "tgn:1000004",
        "tgn:7000198",
        "tgn:1001996",
        "tgn:7029392"
    ],
    "tgn:id":7546346,
    "tgn:name:en":"Bawarna",
    "tgn:placetype":[
        "aat:300008347"
    ]
},
  "bbox": [],
  "geometry": {"coordinates":[76.485029,32.034385],"type":"Point"}
}