<<<<<<< HEAD
{
  "id": 7361978,
  "type": "Feature",
  "properties": {
    "tgn:hierarchy":[
        "tgn:7361978",
        "tgn:7005581",
        "tgn:1000001",
        "tgn:7005560",
        "tgn:7029392"
    ],
    "tgn:id":7361978,
    "tgn:name":"El Lim\u00f3n",
    "tgn:placetype":[
        "aat:300008347"
    ]
},
  "bbox": [],
  "geometry": {"coordinates":[-108.7,27.6],"type":"Point"}
}
=======
{"geometry":{"type":"Point","coordinates":[-108.700000,27.600000]},"type":"Feature","properties":{"hierarchy":["tgn:7361978","tgn:7005581","tgn:1000001","tgn:7005560","tgn:7029392"],"placetype":["aat:300008347"],"id":7361978,"name:xx":"El Lim\u00f3n"}}
>>>>>>> 03f74aca74312dbeaf24d7e61306dd6a786dc3d0
