{
  "id": 7036763,
  "type": "Feature",
  "properties": {
    "tgn:hierarchy":[
        "tgn:7036763",
        "tgn:7003131",
        "tgn:1000003",
        "tgn:7008516",
        "tgn:1000080",
        "tgn:7029392"
    ],
    "tgn:id":7036763,
    "tgn:name":"Villora",
    "tgn:placetype":[
        "aat:300008347"
    ]
},
  "bbox": [],
  "geometry": {"coordinates":[9.816667,44.683333],"type":"Point"}
}