{
  "id": 7029772,
  "type": "Feature",
  "properties": {
    "tgn:hierarchy":[
        "tgn:7029772",
        "tgn:7002878",
        "tgn:1000003",
        "tgn:1000070",
        "tgn:7029392"
    ],
    "tgn:id":7029772,
    "tgn:name":"Sorde-l'Abbaye",
    "tgn:placetype":[
        "aat:300008347",
        "aat:300000642",
        "aat:300007466"
    ]
},
  "bbox": [],
  "geometry": {"coordinates":[-1.05,43.516],"type":"Point"}
}