{
  "id": 7515580,
  "type": "Feature",
  "properties": {
    "tgn:hierarchy":[
        "tgn:7515580",
        "tgn:1009227",
        "tgn:1000226",
        "tgn:7018437",
        "tgn:1000006",
        "tgn:7029392"
    ],
    "tgn:id":7515580,
    "tgn:name:en":"Mount Allen",
    "tgn:placetype":[
        "aat:300007783"
    ]
},
  "bbox": [],
  "geometry": {"coordinates":[170.35,-45.75],"type":"Point"}
}