{
  "id": 2247911,
  "type": "Feature",
  "properties": {
    "tgn:hierarchy":[
        "tgn:2247911",
        "tgn:1000001",
        "tgn:7012149",
        "tgn:7007709",
        "tgn:7029392"
    ],
    "tgn:id":2247911,
    "tgn:name":"Cokey Swamp",
    "tgn:placetype":[
        "aat:300008699"
    ]
},
  "bbox": [],
  "geometry": {"coordinates":[-77.8167,35.8833],"type":"Point"}
}