{
  "id": 2616825,
  "type": "Feature",
  "properties": {
    "tgn:hierarchy":[
        "tgn:2616825",
        "tgn:2001465",
        "tgn:1000001",
        "tgn:7012149",
        "tgn:7007709",
        "tgn:7029392"
    ],
    "tgn:id":2616825,
    "tgn:name":"Rich Hill Mountain",
    "tgn:placetype":[
        "aat:300008798"
    ]
},
  "bbox": [],
  "geometry": {"coordinates":[-80.9667,36.45],"type":"Point"}
}