<<<<<<< HEAD
{
  "id": 7474285,
  "type": "Feature",
  "properties": {
    "tgn:hierarchy":[
        "tgn:7474285",
        "tgn:1000004",
        "tgn:7001009",
        "tgn:1000141",
        "tgn:7029392"
    ],
    "tgn:id":7474285,
    "tgn:name":"Yuetou",
    "tgn:placetype":[
        "aat:300008347",
        "aat:300387200"
    ]
},
  "bbox": [],
  "geometry": {"coordinates":[120.718779,24.164759],"type":"Point"}
}
=======
{"geometry":{"type":"Point","coordinates":[120.718779,24.164759]},"type":"Feature","properties":{"hierarchy":["tgn:7474285","tgn:1000004","tgn:7001009","tgn:1000141","tgn:7029392"],"placetype":["aat:300008347","aat:300387200"],"id":7474285,"name:xx":"Yuetou"}}
>>>>>>> 03f74aca74312dbeaf24d7e61306dd6a786dc3d0
