<<<<<<< HEAD
{
  "id": 2404186,
  "type": "Feature",
  "properties": {
    "tgn:hierarchy":[
        "tgn:2404186",
        "tgn:1000001",
        "tgn:7016172",
        "tgn:7012149",
        "tgn:2000148",
        "tgn:7029392"
    ],
    "tgn:id":2404186,
    "tgn:name":"Hoxey Hollow",
    "tgn:placetype":[
        "aat:300008761"
    ]
},
  "bbox": [],
  "geometry": {"coordinates":[-93.7,35.9333],"type":"Point"}
}
=======
{"geometry":{"type":"Point","coordinates":[-93.700000,35.933300]},"type":"Feature","properties":{"hierarchy":["tgn:2404186","tgn:1000001","tgn:7016172","tgn:7012149","tgn:2000148","tgn:7029392"],"placetype":["aat:300008761"],"id":2404186,"name:xx":"Hoxey Hollow"}}
>>>>>>> 03f74aca74312dbeaf24d7e61306dd6a786dc3d0
