{
  "id": 2129761,
  "type": "Feature",
  "properties": {
    "tgn:hierarchy":[
        "tgn:2129761",
        "tgn:1000001",
        "tgn:1002205",
        "tgn:7012149",
        "tgn:7013961",
        "tgn:7029392"
    ],
    "tgn:id":2129761,
    "tgn:name":"Alleghany Steel Run",
    "tgn:placetype":[
        "aat:300008699"
    ]
},
  "bbox": [],
  "geometry": {"coordinates":[-80.5667,40.3333],"type":"Point"}
}