{
  "id": 2453077,
  "type": "Feature",
  "properties": {
    "tgn:hierarchy":[
        "tgn:2453077",
        "tgn:1000001",
        "tgn:7012149",
        "tgn:2001706",
        "tgn:7007708",
        "tgn:7029392"
    ],
    "tgn:id":2453077,
    "tgn:name":"Little Canyon",
    "tgn:placetype":[
        "aat:300008761"
    ]
},
  "bbox": [],
  "geometry": {"coordinates":[-123.45,43.4333],"type":"Point"}
}