{
  "id": 2197014,
  "type": "Feature",
  "properties": {
    "tgn:hierarchy":[
        "tgn:2197014",
        "tgn:1000001",
        "tgn:2000273",
        "tgn:7012149",
        "tgn:7007240",
        "tgn:7029392"
    ],
    "tgn:id":2197014,
    "tgn:name":"Broom Bay",
    "tgn:placetype":[
        "aat:300008905"
    ]
},
  "bbox": [],
  "geometry": {"coordinates":[-85.55,30.8833],"type":"Point"}
}