{
  "id": 1073891,
  "type": "Feature",
  "properties": {
    "tgn:hierarchy":[
        "tgn:1073891",
        "tgn:1000004",
        "tgn:7002076",
        "tgn:1000111",
        "tgn:7029392"
    ],
    "tgn:id":1073891,
    "tgn:name":"Zhangwu",
    "tgn:placetype":[
        "aat:300008347"
    ]
},
  "bbox": [],
  "geometry": {"coordinates":[119.55,30.7833],"type":"Point"}
}