{
  "id": 7088304,
  "type": "Feature",
  "properties": {
    "tgn:hierarchy":[
        "tgn:7088304",
        "tgn:1000003",
        "tgn:7003676",
        "tgn:7000084",
        "tgn:7029392"
    ],
    "tgn:id":7088304,
    "tgn:name":"Waltershagen",
    "tgn:placetype":[
        "aat:300008347"
    ]
},
  "bbox": [],
  "geometry": {"coordinates":[9.416667,52.25],"type":"Point"}
}