{
  "id": 2465127,
  "type": "Feature",
  "properties": {
    "tgn:hierarchy":[
        "tgn:2465127",
        "tgn:1000001",
        "tgn:7012149",
        "tgn:2001304",
        "tgn:7007524",
        "tgn:7029392"
    ],
    "tgn:id":2465127,
    "tgn:name":"Lolo National Forest",
    "tgn:placetype":[
        "aat:300008863"
    ]
},
  "bbox": [],
  "geometry": {"coordinates":[-115.5833,47.5833],"type":"Point"}
}