{
  "id": 7321519,
  "type": "Feature",
  "properties": {
    "tgn:hierarchy":[
        "tgn:7321519",
        "tgn:1001702",
        "tgn:1000049",
        "tgn:1000002",
        "tgn:7029392"
    ],
    "tgn:id":7321519,
    "tgn:name":"Browne, Puerto",
    "tgn:placetype":[
        "aat:300132317"
    ]
},
  "bbox": [],
  "geometry": {"coordinates":[-72.866667,-53.216667],"type":"Point"}
}