{
  "id": 2105944,
  "type": "Feature",
  "properties": {
    "tgn:hierarchy":[
        "tgn:2105944",
        "tgn:1000001",
        "tgn:7012149",
        "tgn:2002037",
        "tgn:7007826",
        "tgn:7029392"
    ],
    "tgn:id":2105944,
    "tgn:name":"Mason",
    "tgn:placetype":[
        "aat:300008347"
    ]
},
  "bbox": [],
  "geometry": {"coordinates":[-99.2167,30.7333],"type":"Point"}
}