{
  "id": 7378855,
  "type": "Feature",
  "properties": {
    "tgn:hierarchy":[
        "tgn:7378855",
        "tgn:1000001",
        "tgn:7005597",
        "tgn:7005560",
        "tgn:7029392"
    ],
    "tgn:id":7378855,
    "tgn:name":"Los Ranchitos",
    "tgn:placetype":[
        "aat:300008347"
    ]
},
  "bbox": [],
  "geometry": {"coordinates":[-97.683333,25.816667],"type":"Point"}
}