{
  "id": 7236657,
  "type": "Feature",
  "properties": {
    "tgn:hierarchy":[
        "tgn:7236657",
        "tgn:7011330",
        "tgn:7002674",
        "tgn:1000003",
        "tgn:1000074",
        "tgn:7029392"
    ],
    "tgn:id":7236657,
    "tgn:name":"\u00c9mbonas",
    "tgn:placetype":[
        "aat:300008347"
    ]
},
  "bbox": [],
  "geometry": {"coordinates":[27.866667,36.216667],"type":"Point"}
}