{
  "id": 2112761,
  "type": "Feature",
  "properties": {
    "tgn:hierarchy":[
        "tgn:2112761",
        "tgn:2002138",
        "tgn:1000001",
        "tgn:7012149",
        "tgn:7007919",
        "tgn:7029392"
    ],
    "tgn:id":2112761,
    "tgn:name":"Low Moor",
    "tgn:placetype":[
        "aat:300008347"
    ]
},
  "bbox": [],
  "geometry": {"coordinates":[-79.8833,37.7833],"type":"Point"}
}