{
  "id": 2242123,
  "type": "Feature",
  "properties": {
    "tgn:hierarchy":[
        "tgn:2242123",
        "tgn:1000001",
        "tgn:7012149",
        "tgn:2002380",
        "tgn:7007923",
        "tgn:7029392"
    ],
    "tgn:id":2242123,
    "tgn:name":"Clay Number 1 Reservoir",
    "tgn:placetype":[
        "aat:300006191"
    ]
},
  "bbox": [],
  "geometry": {"coordinates":[-105.1833,41.6833],"type":"Point"}
}