<<<<<<< HEAD
{
  "id": 2150742,
  "type": "Feature",
  "properties": {
    "tgn:hierarchy":[
        "tgn:2150742",
        "tgn:1002157",
        "tgn:1000001",
        "tgn:7012149",
        "tgn:7007565",
        "tgn:7029392"
    ],
    "tgn:id":2150742,
    "tgn:name":"Bass Harbor",
    "tgn:placetype":[
        "aat:300132316"
    ]
},
  "bbox": [],
  "geometry": {"coordinates":[-74.5833,39.3],"type":"Point"}
}
=======
{"geometry":{"type":"Point","coordinates":[-74.583300,39.300000]},"type":"Feature","properties":{"hierarchy":["tgn:2150742","tgn:1002157","tgn:1000001","tgn:7012149","tgn:7007565","tgn:7029392"],"placetype":["aat:300132316"],"id":2150742,"name:xx":"Bass Harbor"}}
>>>>>>> 03f74aca74312dbeaf24d7e61306dd6a786dc3d0
