{
  "id": 2786159,
  "type": "Feature",
  "properties": {
    "tgn:hierarchy":[
        "tgn:2786159",
        "tgn:1000001",
        "tgn:7012149",
        "tgn:2001454",
        "tgn:7007566",
        "tgn:7029392"
    ],
    "tgn:id":2786159,
    "tgn:name":"Young Tank",
    "tgn:placetype":[
        "aat:300006191"
    ]
},
  "bbox": [],
  "geometry": {"coordinates":[-105.75,35.25],"type":"Point"}
}