{
  "id": 2315516,
  "type": "Feature",
  "properties": {
    "tgn:hierarchy":[
        "tgn:2315516",
        "tgn:1000001",
        "tgn:7016172",
        "tgn:2000123",
        "tgn:7012149",
        "tgn:7029392"
    ],
    "tgn:id":2315516,
    "tgn:name":"Ellis Chapel",
    "tgn:placetype":[
        "aat:300008347"
    ]
},
  "bbox": [],
  "geometry": {"coordinates":[-90.8833,35.1833],"type":"Point"}
}