{
  "id": 7305164,
  "type": "Feature",
  "properties": {
    "tgn:hierarchy":[
        "tgn:7305164",
        "tgn:7002835",
        "tgn:7001158",
        "tgn:1000003",
        "tgn:1000095",
        "tgn:7029392"
    ],
    "tgn:id":7305164,
    "tgn:name":"Las Pilas, Sierra de",
    "tgn:placetype":[
        "aat:300266640"
    ]
},
  "bbox": [],
  "geometry": {"coordinates":[-6.566667,40.283333],"type":"Point"}
}