{
  "id": 1087760,
  "type": "Feature",
  "properties": {
    "tgn:hierarchy":[
        "tgn:1087760",
        "tgn:7001242",
        "tgn:1000149",
        "tgn:1000868",
        "tgn:7029392"
    ],
    "tgn:id":1087760,
    "tgn:name":"Chiumbe",
    "tgn:placetype":[
        "aat:300008347"
    ]
},
  "bbox": [],
  "geometry": {"coordinates":[16.1333,-12.4833],"type":"Point"}
}