{
  "id": 7589708,
  "type": "Feature",
  "properties": {
    "tgn:hierarchy":[
        "tgn:7589708",
        "tgn:1000004",
        "tgn:7000198",
        "tgn:7000799",
        "tgn:7029392"
    ],
    "tgn:id":7589708,
    "tgn:name:en":"Chirangal",
    "tgn:placetype":[
        "aat:300008347"
    ]
},
  "bbox": [],
  "geometry": {"coordinates":[74.481955,33.163631],"type":"Point"}
}