{
  "id": 2141729,
  "type": "Feature",
  "properties": {
    "tgn:hierarchy":[
        "tgn:2141729",
        "tgn:1000001",
        "tgn:1002302",
        "tgn:7012149",
        "tgn:7007568",
        "tgn:7029392"
    ],
    "tgn:id":2141729,
    "tgn:name":"Babcock Hollow",
    "tgn:placetype":[
        "aat:300008761"
    ]
},
  "bbox": [],
  "geometry": {"coordinates":[-76.15,42.4833],"type":"Point"}
}