{
  "id": 1080534,
  "type": "Feature",
  "properties": {
    "tgn:hierarchy":[
        "tgn:1080534",
        "tgn:7016675",
        "tgn:1000004",
        "tgn:7000896",
        "tgn:1000120",
        "tgn:7029392"
    ],
    "tgn:id":1080534,
    "tgn:name":"Kinosaki",
    "tgn:placetype":[
        "aat:300008347"
    ]
},
  "bbox": [],
  "geometry": {"coordinates":[134.7833,35.65],"type":"Point"}
}