{
  "id": 2306125,
  "type": "Feature",
  "properties": {
    "tgn:hierarchy":[
        "tgn:2306125",
        "tgn:1000001",
        "tgn:2002144",
        "tgn:7012149",
        "tgn:7007919",
        "tgn:7029392"
    ],
    "tgn:id":2306125,
    "tgn:name":"East Fork Beaverdam Creek",
    "tgn:placetype":[
        "aat:300008706"
    ]
},
  "bbox": [],
  "geometry": {"coordinates":[-79.7167,37.2833],"type":"Point"}
}