{
  "id": 7358720,
  "type": "Feature",
  "properties": {
    "tgn:hierarchy":[
        "tgn:7358720",
        "tgn:7005583",
        "tgn:1000001",
        "tgn:7005560",
        "tgn:7029392"
    ],
    "tgn:id":7358720,
    "tgn:name":"Cristo",
    "tgn:placetype":[
        "aat:300008347"
    ]
},
  "bbox": [],
  "geometry": {"coordinates":[-105.533333,26.45],"type":"Point"}
}