<<<<<<< HEAD
{
  "id": 7365436,
  "type": "Feature",
  "properties": {
    "tgn:hierarchy":[
        "tgn:7365436",
        "tgn:1000001",
        "tgn:7005594",
        "tgn:7005560",
        "tgn:7029392"
    ],
    "tgn:id":7365436,
    "tgn:name":"El Rayo",
    "tgn:placetype":[
        "aat:300008347"
    ]
},
  "bbox": [],
  "geometry": {"coordinates":[-98.566667,21.5],"type":"Point"}
}
=======
{"geometry":{"type":"Point","coordinates":[-98.566667,21.500000]},"type":"Feature","properties":{"hierarchy":["tgn:7365436","tgn:1000001","tgn:7005594","tgn:7005560","tgn:7029392"],"placetype":["aat:300008347"],"id":7365436,"name:xx":"El Rayo"}}
>>>>>>> 03f74aca74312dbeaf24d7e61306dd6a786dc3d0
