{
  "id": 7118498,
  "type": "Feature",
  "properties": {
    "tgn:hierarchy":[
        "tgn:7118498",
        "tgn:1000003",
        "tgn:7003676",
        "tgn:7000084",
        "tgn:7029392"
    ],
    "tgn:id":7118498,
    "tgn:name":"Petersburg",
    "tgn:placetype":[
        "aat:300000206"
    ]
},
  "bbox": [],
  "geometry": {"coordinates":[8.016667,53.583333],"type":"Point"}
}