{
  "id": 2231870,
  "type": "Feature",
  "properties": {
    "tgn:hierarchy":[
        "tgn:2231870",
        "tgn:1000001",
        "tgn:7012149",
        "tgn:2001846",
        "tgn:7007825",
        "tgn:7029392"
    ],
    "tgn:id":2231870,
    "tgn:name":"Chambers Hollow",
    "tgn:placetype":[
        "aat:300008761"
    ]
},
  "bbox": [],
  "geometry": {"coordinates":[-82.15,36.1667],"type":"Point"}
}