{
  "id": 2243971,
  "type": "Feature",
  "properties": {
    "tgn:hierarchy":[
        "tgn:2243971",
        "tgn:7006450",
        "tgn:1000001",
        "tgn:2124053",
        "tgn:7012149",
        "tgn:7029392"
    ],
    "tgn:id":2243971,
    "tgn:name":"Cliff Bay",
    "tgn:placetype":[
        "aat:300132316"
    ]
},
  "bbox": [],
  "geometry": {"coordinates":[-146.5667,62.3667],"type":"Point"}
}