{
  "id": 2483754,
  "type": "Feature",
  "properties": {
    "tgn:hierarchy":[
        "tgn:2483754",
        "tgn:1000001",
        "tgn:2000571",
        "tgn:7012149",
        "tgn:7007253",
        "tgn:7029392"
    ],
    "tgn:id":2483754,
    "tgn:name":"Lateral Number 2",
    "tgn:placetype":[
        "aat:300006075"
    ]
},
  "bbox": [],
  "geometry": {"coordinates":[-94.9833,42.75],"type":"Point"}
}