{
  "id": 2552079,
  "type": "Feature",
  "properties": {
    "tgn:hierarchy":[
        "tgn:2552079",
        "tgn:1000001",
        "tgn:7006451",
        "tgn:7012149",
        "tgn:2000101",
        "tgn:7029392"
    ],
    "tgn:id":2552079,
    "tgn:name":"Number One Dirt Tank",
    "tgn:placetype":[
        "aat:300006191"
    ]
},
  "bbox": [],
  "geometry": {"coordinates":[-110.85,32.6667],"type":"Point"}
}