<<<<<<< HEAD
{
  "id": 2766483,
  "type": "Feature",
  "properties": {
    "tgn:hierarchy":[
        "tgn:2766483",
        "tgn:1000001",
        "tgn:7012149",
        "tgn:1002414",
        "tgn:7007826",
        "tgn:7029392"
    ],
    "tgn:id":2766483,
    "tgn:name":"White Oak Branch",
    "tgn:placetype":[
        "aat:300008699"
    ]
},
  "bbox": [],
  "geometry": {"coordinates":[-97.5,29.2167],"type":"Point"}
}
=======
{"geometry":{"type":"Point","coordinates":[-97.500000,29.216700]},"type":"Feature","properties":{"hierarchy":["tgn:2766483","tgn:1000001","tgn:7012149","tgn:1002414","tgn:7007826","tgn:7029392"],"placetype":["aat:300008699"],"id":2766483,"name:xx":"White Oak Branch"}}
>>>>>>> 03f74aca74312dbeaf24d7e61306dd6a786dc3d0
