<<<<<<< HEAD
{
  "id": 2250516,
  "type": "Feature",
  "properties": {
    "tgn:hierarchy":[
        "tgn:2250516",
        "tgn:1000001",
        "tgn:7012149",
        "tgn:7007157",
        "tgn:1002656",
        "tgn:7029392"
    ],
    "tgn:id":2250516,
    "tgn:name":"Colony Branch Number Four",
    "tgn:placetype":[
        "aat:300006075"
    ]
},
  "bbox": [],
  "geometry": {"coordinates":[-120.65,37.0],"type":"Point"}
}
=======
{"geometry":{"type":"Point","coordinates":[-120.650000,37.000000]},"type":"Feature","properties":{"hierarchy":["tgn:2250516","tgn:1000001","tgn:7012149","tgn:7007157","tgn:1002656","tgn:7029392"],"placetype":["aat:300006075"],"id":2250516,"name:xx":"Colony Branch Number Four"}}
>>>>>>> 03f74aca74312dbeaf24d7e61306dd6a786dc3d0
