{
  "id": 7565980,
  "type": "Feature",
  "properties": {
    "tgn:hierarchy":[
        "tgn:7565980",
        "tgn:1000004",
        "tgn:7000198",
        "tgn:1001894",
        "tgn:7029392"
    ],
    "tgn:id":7565980,
    "tgn:name:en":"Khera N\u0101la",
    "tgn:placetype":[
        "aat:300008699"
    ]
},
  "bbox": [],
  "geometry": {"coordinates":[79.117517,24.628637],"type":"Point"}
}