{
  "id": 7455115,
  "type": "Feature",
  "properties": {
    "tgn:hierarchy":[
        "tgn:7455115",
        "tgn:7002448",
        "tgn:7019203",
        "tgn:1000003",
        "tgn:7008591",
        "tgn:7029392"
    ],
    "tgn:id":7455115,
    "tgn:name:en":"Cecil Manor",
    "tgn:placetype":[
        "aat:300387502"
    ]
},
  "bbox": [],
  "geometry": {"coordinates":[-7.15,54.45],"type":"Point"}
}