{
  "id": 2127614,
  "type": "Feature",
  "properties": {
    "tgn:hierarchy":[
        "tgn:2127614",
        "tgn:1002648",
        "tgn:1000001",
        "tgn:1008191",
        "tgn:7012149",
        "tgn:7007249",
        "tgn:7029392"
    ],
    "tgn:id":2127614,
    "tgn:name":"Alae",
    "tgn:placetype":[
        "aat:300008798"
    ]
},
  "bbox": [],
  "geometry": {"coordinates":[-156.95,21.1667],"type":"Point"}
}