{
  "id": 1022084,
  "type": "Feature",
  "properties": {
    "tgn:hierarchy":[
        "tgn:1022084",
        "tgn:7006237",
        "tgn:1000047",
        "tgn:7002457",
        "tgn:1000002",
        "tgn:7029392"
    ],
    "tgn:id":1022084,
    "tgn:name":"Medina",
    "tgn:placetype":[
        "aat:300008347"
    ]
},
  "bbox": [],
  "geometry": {"coordinates":[-41.5333,-16.25],"type":"Point"}
}