{
  "id": 7160304,
  "type": "Feature",
  "properties": {
    "tgn:hierarchy":[
        "tgn:7160304",
        "tgn:1000003",
        "tgn:7003677",
        "tgn:7000084",
        "tgn:7029392"
    ],
    "tgn:id":7160304,
    "tgn:name":"Hohenfeld",
    "tgn:placetype":[
        "aat:300000206"
    ]
},
  "bbox": [],
  "geometry": {"coordinates":[7.566667,51.95],"type":"Point"}
}