<<<<<<< HEAD
{
  "id": 7470876,
  "type": "Feature",
  "properties": {
    "tgn:hierarchy":[
        "tgn:7470876",
        "tgn:7468018",
        "tgn:1000004",
        "tgn:1000141",
        "tgn:7029392"
    ],
    "tgn:id":7470876,
    "tgn:name":"Xinan",
    "tgn:placetype":[
        "aat:300008347"
    ]
},
  "bbox": [],
  "geometry": {"coordinates":[120.335821,23.505091],"type":"Point"}
}
=======
{"geometry":{"type":"Point","coordinates":[120.335821,23.505091]},"type":"Feature","properties":{"hierarchy":["tgn:7470876","tgn:7468018","tgn:1000004","tgn:1000141","tgn:7029392"],"placetype":["aat:300008347"],"id":7470876,"name:xx":"Xinan"}}
>>>>>>> 03f74aca74312dbeaf24d7e61306dd6a786dc3d0
