<<<<<<< HEAD
{
  "id": 2766408,
  "type": "Feature",
  "properties": {
    "tgn:hierarchy":[
        "tgn:2766408",
        "tgn:2000002",
        "tgn:7002659",
        "tgn:1000001",
        "tgn:7012149",
        "tgn:7029392"
    ],
    "tgn:id":2766408,
    "tgn:name":"White Oak",
    "tgn:placetype":[
        "aat:300008347"
    ]
},
  "bbox": [],
  "geometry": {"coordinates":[-85.3333,31.9],"type":"Point"}
}
=======
{"geometry":{"type":"Point","coordinates":[-85.333300,31.900000]},"type":"Feature","properties":{"hierarchy":["tgn:2766408","tgn:2000002","tgn:7002659","tgn:1000001","tgn:7012149","tgn:7029392"],"placetype":["aat:300008347"],"id":2766408,"name:xx":"White Oak"}}
>>>>>>> 03f74aca74312dbeaf24d7e61306dd6a786dc3d0
