{
  "id": 1055195,
  "type": "Feature",
  "properties": {
    "tgn:hierarchy":[
        "tgn:1055195",
        "tgn:1000004",
        "tgn:7011589",
        "tgn:7018214",
        "tgn:7002435",
        "tgn:7029392"
    ],
    "tgn:id":1055195,
    "tgn:name":"Kazatkul'",
    "tgn:placetype":[
        "aat:300008347"
    ]
},
  "bbox": [],
  "geometry": {"coordinates":[76.0167,55.0333],"type":"Point"}
}