{
  "id": 2784877,
  "type": "Feature",
  "properties": {
    "tgn:hierarchy":[
        "tgn:2784877",
        "tgn:1000001",
        "tgn:7012149",
        "tgn:2000786",
        "tgn:7007255",
        "tgn:7029392"
    ],
    "tgn:id":2784877,
    "tgn:name":"Yellow Creek",
    "tgn:placetype":[
        "aat:300008706"
    ]
},
  "bbox": [],
  "geometry": {"coordinates":[-87.05,37.75],"type":"Point"}
}