{
  "id": 7348073,
  "type": "Feature",
  "properties": {
    "tgn:hierarchy":[
        "tgn:7348073",
        "tgn:7002822",
        "tgn:1001647",
        "tgn:1000003",
        "tgn:1000095",
        "tgn:7029392"
    ],
    "tgn:id":7348073,
    "tgn:name":"Alaminos",
    "tgn:placetype":[
        "aat:300008347"
    ]
},
  "bbox": [],
  "geometry": {"coordinates":[-2.733333,40.866667],"type":"Point"}
}