{
  "id": 7525597,
  "type": "Feature",
  "properties": {
    "tgn:hierarchy":[
        "tgn:7525597",
        "tgn:7001242",
        "tgn:1001075",
        "tgn:7016833",
        "tgn:7029392"
    ],
    "tgn:id":7525597,
    "tgn:name:en":"Daqd\u016bqah",
    "tgn:placetype":[
        "aat:300008347"
    ]
},
  "bbox": [],
  "geometry": {"coordinates":[30.617661,30.85382],"type":"Point"}
}