{
  "id": 2386533,
  "type": "Feature",
  "properties": {
    "tgn:hierarchy":[
        "tgn:2386533",
        "tgn:1000001",
        "tgn:7012149",
        "tgn:7007826",
        "tgn:7029392"
    ],
    "tgn:id":2386533,
    "tgn:name":"Herds Pass Draw",
    "tgn:placetype":[
        "aat:300008761"
    ]
},
  "bbox": [],
  "geometry": {"coordinates":[-104.25,30.8833],"type":"Point"}
}