{
  "id": 7574857,
  "type": "Feature",
  "properties": {
    "tgn:hierarchy":[
        "tgn:7574857",
        "tgn:1000004",
        "tgn:7000198",
        "tgn:7016788",
        "tgn:7029392"
    ],
    "tgn:id":7574857,
    "tgn:name:en":"M\u0101dhor\u0101jpura",
    "tgn:placetype":[
        "aat:300008347"
    ]
},
  "bbox": [],
  "geometry": {"coordinates":[75.644674,26.578118],"type":"Point"}
}