<<<<<<< HEAD
{
  "id": 2253427,
  "type": "Feature",
  "properties": {
    "tgn:hierarchy":[
        "tgn:2253427",
        "tgn:1000001",
        "tgn:7012149",
        "tgn:2001553",
        "tgn:7007709",
        "tgn:7029392"
    ],
    "tgn:id":2253427,
    "tgn:name":"Cook Branch",
    "tgn:placetype":[
        "aat:300008699"
    ]
},
  "bbox": [],
  "geometry": {"coordinates":[-81.1667,36.3667],"type":"Point"}
}
=======
{"geometry":{"type":"Point","coordinates":[-81.166700,36.366700]},"type":"Feature","properties":{"hierarchy":["tgn:2253427","tgn:1000001","tgn:7012149","tgn:2001553","tgn:7007709","tgn:7029392"],"placetype":["aat:300008699"],"id":2253427,"name:xx":"Cook Branch"}}
>>>>>>> 03f74aca74312dbeaf24d7e61306dd6a786dc3d0
