{
  "id": 2459022,
  "type": "Feature",
  "properties": {
    "tgn:hierarchy":[
        "tgn:2459022",
        "tgn:1000001",
        "tgn:7012149",
        "tgn:7007157",
        "tgn:2000189",
        "tgn:7029392"
    ],
    "tgn:id":2459022,
    "tgn:name":"Little Pilot",
    "tgn:placetype":[
        "aat:300008798"
    ]
},
  "bbox": [],
  "geometry": {"coordinates":[-122.5333,41.9667],"type":"Point"}
}