{
  "id": 7592322,
  "type": "Feature",
  "properties": {
    "tgn:hierarchy":[
        "tgn:7592322",
        "tgn:1000004",
        "tgn:7000198",
        "tgn:7000799",
        "tgn:7029392"
    ],
    "tgn:id":7592322,
    "tgn:name:en":"Sh\u0101hz\u0101dpur Bhopa",
    "tgn:placetype":[
        "aat:300008347"
    ]
},
  "bbox": [],
  "geometry": {"coordinates":[74.75376,32.746537],"type":"Point"}
}