<<<<<<< HEAD
{
  "id": 7353674,
  "type": "Feature",
  "properties": {
    "tgn:hierarchy":[
        "tgn:7353674",
        "tgn:7005580",
        "tgn:1000001",
        "tgn:7005560",
        "tgn:7029392"
    ],
    "tgn:id":7353674,
    "tgn:name":"Benito Ju\u00e1rez",
    "tgn:placetype":[
        "aat:300008347"
    ]
},
  "bbox": [],
  "geometry": {"coordinates":[-93.3,16.45],"type":"Point"}
}
=======
{"geometry":{"type":"Point","coordinates":[-93.300000,16.450000]},"type":"Feature","properties":{"hierarchy":["tgn:7353674","tgn:7005580","tgn:1000001","tgn:7005560","tgn:7029392"],"placetype":["aat:300008347"],"id":7353674,"name:xx":"Benito Ju\u00e1rez"}}
>>>>>>> 03f74aca74312dbeaf24d7e61306dd6a786dc3d0
