{
  "id": 7357472,
  "type": "Feature",
  "properties": {
    "tgn:hierarchy":[
        "tgn:7357472",
        "tgn:7005585",
        "tgn:1000001",
        "tgn:7005560",
        "tgn:7029392"
    ],
    "tgn:id":7357472,
    "tgn:name":"Cuitlapa",
    "tgn:placetype":[
        "aat:300008347"
    ]
},
  "bbox": [],
  "geometry": {"coordinates":[-98.25,17.066667],"type":"Point"}
}