{
  "id": 2208648,
  "type": "Feature",
  "properties": {
    "tgn:hierarchy":[
        "tgn:2208648",
        "tgn:1000001",
        "tgn:7012149",
        "tgn:1002387",
        "tgn:7007710",
        "tgn:7029392"
    ],
    "tgn:id":2208648,
    "tgn:name":"Burns Creek",
    "tgn:placetype":[
        "aat:300008706"
    ]
},
  "bbox": [],
  "geometry": {"coordinates":[-77.6333,40.25],"type":"Point"}
}