{
  "id": 7160739,
  "type": "Feature",
  "properties": {
    "tgn:hierarchy":[
        "tgn:7160739",
        "tgn:1000003",
        "tgn:7003677",
        "tgn:7000084",
        "tgn:7029392"
    ],
    "tgn:id":7160739,
    "tgn:name":"Hohes W\u00e4ldchen",
    "tgn:placetype":[
        "aat:300008777"
    ]
},
  "bbox": [],
  "geometry": {"coordinates":[7.533333,50.833333],"type":"Point"}
}