{
  "id": 1060710,
  "type": "Feature",
  "properties": {
    "tgn:hierarchy":[
        "tgn:1060710",
        "tgn:1003351",
        "tgn:1000004",
        "tgn:7018214",
        "tgn:7002435",
        "tgn:7029392"
    ],
    "tgn:id":1060710,
    "tgn:name":"Urluk",
    "tgn:placetype":[
        "aat:300008347"
    ]
},
  "bbox": [],
  "geometry": {"coordinates":[107.9167,50.05],"type":"Point"}
}