{
  "id": 7584387,
  "type": "Feature",
  "properties": {
    "tgn:hierarchy":[
        "tgn:7584387",
        "tgn:1000004",
        "tgn:7000198",
        "tgn:1001894",
        "tgn:7029392"
    ],
    "tgn:id":7584387,
    "tgn:name:en":"Manpas\u0101r N\u0101la",
    "tgn:placetype":[
        "aat:300008699"
    ]
},
  "bbox": [],
  "geometry": {"coordinates":[78.774525,24.843941],"type":"Point"}
}