{
  "id": 7014040,
  "type": "Feature",
  "properties": {
    "tgn:hierarchy":[
        "tgn:7014040",
        "tgn:1000001",
        "tgn:7012149",
        "tgn:7019676",
        "tgn:7007566",
        "tgn:7029392"
    ],
    "tgn:id":7014040,
    "tgn:name":"Gallup",
    "tgn:placetype":[
        "aat:300008347",
        "aat:300008416",
        "aat:300387305",
        "aat:300008375"
    ]
},
  "bbox": [],
  "geometry": {"coordinates":[-108.7333,35.5167],"type":"Point"}
}