{
  "id": 7477030,
  "type": "Feature",
  "properties": {
    "tgn:hierarchy":[
        "tgn:7477030",
        "tgn:7488858",
        "tgn:1000004",
        "tgn:1000141",
        "tgn:7029392"
    ],
    "tgn:id":7477030,
    "tgn:name":"Shuiliudong Xi",
    "tgn:placetype":[
        "aat:300008699"
    ]
},
  "bbox": [],
  "geometry": {"coordinates":[120.872526,24.071475],"type":"Point"}
}