{
  "id": 7567294,
  "type": "Feature",
  "properties": {
    "tgn:hierarchy":[
        "tgn:7567294",
        "tgn:1001828",
        "tgn:1000004",
        "tgn:7000198",
        "tgn:7029392"
    ],
    "tgn:id":7567294,
    "tgn:name:en":"Mallapalli",
    "tgn:placetype":[
        "aat:300008347"
    ]
},
  "bbox": [],
  "geometry": {"coordinates":[78.054167,17.555278],"type":"Point"}
}