{
  "id": 7427688,
  "type": "Feature",
  "properties": {
    "tgn:hierarchy":[
        "tgn:7427688",
        "tgn:1000001",
        "tgn:7005594",
        "tgn:7005560",
        "tgn:7029392"
    ],
    "tgn:id":7427688,
    "tgn:name":"Las Olivas",
    "tgn:placetype":[
        "aat:300008347"
    ]
},
  "bbox": [],
  "geometry": {"coordinates":[-101.866667,23.383333],"type":"Point"}
}