{
  "id": 7451992,
  "type": "Feature",
  "properties": {
    "tgn:hierarchy":[
        "tgn:7451992",
        "tgn:7002443",
        "tgn:1000003",
        "tgn:7008050",
        "tgn:7008591",
        "tgn:7029392"
    ],
    "tgn:id":7451992,
    "tgn:name:en":"Erwood",
    "tgn:placetype":[
        "aat:300008347"
    ]
},
  "bbox": [],
  "geometry": {"coordinates":[-3.333333,52.066667],"type":"Point"}
}