{
  "id": 7577553,
  "type": "Feature",
  "properties": {
    "tgn:hierarchy":[
        "tgn:7577553",
        "tgn:1000004",
        "tgn:7000198",
        "tgn:7016694",
        "tgn:7029392"
    ],
    "tgn:id":7577553,
    "tgn:name:en":"Khir\u0101it\u0101ngri",
    "tgn:placetype":[
        "aat:300008347"
    ]
},
  "bbox": [],
  "geometry": {"coordinates":[85.701783,21.713613],"type":"Point"}
}