{
  "id": 7393331,
  "type": "Feature",
  "properties": {
    "tgn:hierarchy":[
        "tgn:7393331",
        "tgn:1000001",
        "tgn:7005589",
        "tgn:7005560",
        "tgn:7029392"
    ],
    "tgn:id":7393331,
    "tgn:name":"San Antonio Pe\u00f1a Nevada",
    "tgn:placetype":[
        "aat:300008347"
    ]
},
  "bbox": [],
  "geometry": {"coordinates":[-100.483333,23.683333],"type":"Point"}
}