{
  "id": 7379008,
  "type": "Feature",
  "properties": {
    "tgn:hierarchy":[
        "tgn:7379008",
        "tgn:1000001",
        "tgn:1001893",
        "tgn:7005560",
        "tgn:7029392"
    ],
    "tgn:id":7379008,
    "tgn:name":"Los Reyes Acozac",
    "tgn:placetype":[
        "aat:300008347"
    ]
},
  "bbox": [],
  "geometry": {"coordinates":[-98.983333,19.766667],"type":"Point"}
}