<<<<<<< HEAD
{
  "id": 7051923,
  "type": "Feature",
  "properties": {
    "tgn:hierarchy":[
        "tgn:7051923",
        "tgn:7002991",
        "tgn:1000003",
        "tgn:7002997",
        "tgn:1000080",
        "tgn:7029392"
    ],
    "tgn:id":7051923,
    "tgn:name":"Perre, Col",
    "tgn:placetype":[
        "aat:300008795"
    ]
},
  "bbox": [],
  "geometry": {"coordinates":[11.733333,46.033333],"type":"Point"}
}
=======
{"geometry":{"type":"Point","coordinates":[11.733333,46.033333]},"type":"Feature","properties":{"hierarchy":["tgn:7051923","tgn:7002991","tgn:1000003","tgn:7002997","tgn:1000080","tgn:7029392"],"placetype":["aat:300008795"],"id":7051923,"name:xx":"Perre, Col"}}
>>>>>>> 03f74aca74312dbeaf24d7e61306dd6a786dc3d0
