{
  "id": 7080774,
  "type": "Feature",
  "properties": {
    "tgn:hierarchy":[
        "tgn:7080774",
        "tgn:1000003",
        "tgn:7003678",
        "tgn:7000084",
        "tgn:7029392"
    ],
    "tgn:id":7080774,
    "tgn:name":"Worfelden",
    "tgn:placetype":[
        "aat:300008347"
    ]
},
  "bbox": [],
  "geometry": {"coordinates":[8.548611,49.928056],"type":"Point"}
}