{
  "id": 2455157,
  "type": "Feature",
  "properties": {
    "tgn:hierarchy":[
        "tgn:2455157",
        "tgn:7006450",
        "tgn:1000001",
        "tgn:2124053",
        "tgn:7012149",
        "tgn:7029392"
    ],
    "tgn:id":2455157,
    "tgn:name":"Little Falls Creek",
    "tgn:placetype":[
        "aat:300008706"
    ]
},
  "bbox": [],
  "geometry": {"coordinates":[-151.0333,62.4833],"type":"Point"}
}