{
  "id": 2783682,
  "type": "Feature",
  "properties": {
    "tgn:hierarchy":[
        "tgn:2783682",
        "tgn:1000001",
        "tgn:7012149",
        "tgn:2001315",
        "tgn:7007524",
        "tgn:7029392"
    ],
    "tgn:id":2783682,
    "tgn:name":"Wyman Creek",
    "tgn:placetype":[
        "aat:300008706"
    ]
},
  "bbox": [],
  "geometry": {"coordinates":[-108.5667,45.5167],"type":"Point"}
}