{
  "id": 7100590,
  "type": "Feature",
  "properties": {
    "tgn:hierarchy":[
        "tgn:7100590",
        "tgn:7003669",
        "tgn:1000003",
        "tgn:7000084",
        "tgn:7029392"
    ],
    "tgn:id":7100590,
    "tgn:name":"Rotthof",
    "tgn:placetype":[
        "aat:300008347"
    ]
},
  "bbox": [],
  "geometry": {"coordinates":[13.316667,48.433333],"type":"Point"}
}