{
  "id": 7372870,
  "type": "Feature",
  "properties": {
    "tgn:hierarchy":[
        "tgn:7372870",
        "tgn:7005581",
        "tgn:1000001",
        "tgn:7005560",
        "tgn:7029392"
    ],
    "tgn:id":7372870,
    "tgn:name":"Rancho La Flor del Valle",
    "tgn:placetype":[
        "aat:300000241"
    ]
},
  "bbox": [],
  "geometry": {"coordinates":[-104.25,28.783333],"type":"Point"}
}