{
  "id": 7424529,
  "type": "Feature",
  "properties": {
    "tgn:hierarchy":[
        "tgn:7424529",
        "tgn:1000001",
        "tgn:7005597",
        "tgn:7005560",
        "tgn:7029392"
    ],
    "tgn:id":7424529,
    "tgn:name":"Trujillo, R\u00edo",
    "tgn:placetype":[
        "aat:300008699"
    ]
},
  "bbox": [],
  "geometry": {"coordinates":[-98.05,24.15],"type":"Point"}
}