{
  "id": 7096871,
  "type": "Feature",
  "properties": {
    "tgn:hierarchy":[
        "tgn:7096871",
        "tgn:1000003",
        "tgn:7003676",
        "tgn:7000084",
        "tgn:7029392"
    ],
    "tgn:id":7096871,
    "tgn:name":"Vorwerk S\u00f6derhof",
    "tgn:placetype":[
        "aat:300000206"
    ]
},
  "bbox": [],
  "geometry": {"coordinates":[10.283333,52.05],"type":"Point"}
}