{
  "id": 2354216,
  "type": "Feature",
  "properties": {
    "tgn:hierarchy":[
        "tgn:2354216",
        "tgn:1000001",
        "tgn:7012149",
        "tgn:2002125",
        "tgn:7007827",
        "tgn:7029392"
    ],
    "tgn:id":2354216,
    "tgn:name":"Golden Relief Mine",
    "tgn:placetype":[
        "aat:300000390"
    ]
},
  "bbox": [],
  "geometry": {"coordinates":[-111.7333,39.9833],"type":"Point"}
}