{
  "id": 7435715,
  "type": "Feature",
  "properties": {
    "tgn:hierarchy":[
        "tgn:7435715",
        "tgn:7005581",
        "tgn:1000001",
        "tgn:7005560",
        "tgn:7029392"
    ],
    "tgn:id":7435715,
    "tgn:name":"Toro, Arroyo del",
    "tgn:placetype":[
        "aat:300008699"
    ]
},
  "bbox": [],
  "geometry": {"coordinates":[-107.85,29.883333],"type":"Point"}
}