{
  "id": 2650410,
  "type": "Feature",
  "properties": {
    "tgn:hierarchy":[
        "tgn:2650410",
        "tgn:1000001",
        "tgn:7012149",
        "tgn:2000931",
        "tgn:7007515",
        "tgn:7029392"
    ],
    "tgn:id":2650410,
    "tgn:name":"Sears Island Ledge",
    "tgn:placetype":[
        "aat:300132348"
    ]
},
  "bbox": [],
  "geometry": {"coordinates":[-68.8833,44.4167],"type":"Point"}
}