{
  "id": 7093246,
  "type": "Feature",
  "properties": {
    "tgn:hierarchy":[
        "tgn:7093246",
        "tgn:7003669",
        "tgn:1000003",
        "tgn:7000084",
        "tgn:7029392"
    ],
    "tgn:id":7093246,
    "tgn:name":"Schwalbenholz",
    "tgn:placetype":[
        "aat:300008863"
    ]
},
  "bbox": [],
  "geometry": {"coordinates":[10.716667,48.866667],"type":"Point"}
}