{
  "id": 2449944,
  "type": "Feature",
  "properties": {
    "tgn:hierarchy":[
        "tgn:2449944",
        "tgn:1000001",
        "tgn:7012149",
        "tgn:1002505",
        "tgn:7007920",
        "tgn:7029392"
    ],
    "tgn:id":2449944,
    "tgn:name":"Lindsay Lake",
    "tgn:placetype":[
        "aat:300008680"
    ]
},
  "bbox": [],
  "geometry": {"coordinates":[-122.4833,48.2333],"type":"Point"}
}