{
  "id": 7139337,
  "type": "Feature",
  "properties": {
    "tgn:hierarchy":[
        "tgn:7139337",
        "tgn:7003669",
        "tgn:1000003",
        "tgn:7000084",
        "tgn:7029392"
    ],
    "tgn:id":7139337,
    "tgn:name":"Leuthen",
    "tgn:placetype":[
        "aat:300000206"
    ]
},
  "bbox": [],
  "geometry": {"coordinates":[12.95,48.983333],"type":"Point"}
}