{
  "id": 2354442,
  "type": "Feature",
  "properties": {
    "tgn:hierarchy":[
        "tgn:2354442",
        "tgn:1000001",
        "tgn:7012149",
        "tgn:2000481",
        "tgn:7007250",
        "tgn:7029392"
    ],
    "tgn:id":2354442,
    "tgn:name":"Goldstone Mountain",
    "tgn:placetype":[
        "aat:300008798"
    ]
},
  "bbox": [],
  "geometry": {"coordinates":[-113.5667,45.1167],"type":"Point"}
}