{
  "id": 7583601,
  "type": "Feature",
  "properties": {
    "tgn:hierarchy":[
        "tgn:7583601",
        "tgn:1000004",
        "tgn:7000198",
        "tgn:1001894",
        "tgn:7029392"
    ],
    "tgn:id":7583601,
    "tgn:name:en":"N\u0101ke ka Khirk",
    "tgn:placetype":[
        "aat:300008347"
    ]
},
  "bbox": [],
  "geometry": {"coordinates":[78.953548,25.186682],"type":"Point"}
}