<<<<<<< HEAD
{
  "id": 7370740,
  "type": "Feature",
  "properties": {
    "tgn:hierarchy":[
        "tgn:7370740",
        "tgn:1000001",
        "tgn:1001960",
        "tgn:7005560",
        "tgn:7029392"
    ],
    "tgn:id":7370740,
    "tgn:name":"Huiricoba, Arroyo de",
    "tgn:placetype":[
        "aat:300008699"
    ]
},
  "bbox": [],
  "geometry": {"coordinates":[-108.869167,26.695833],"type":"Point"}
}
=======
{"geometry":{"type":"Point","coordinates":[-108.869167,26.695833]},"type":"Feature","properties":{"hierarchy":["tgn:7370740","tgn:1000001","tgn:1001960","tgn:7005560","tgn:7029392"],"placetype":["aat:300008699"],"id":7370740,"name:xx":"Huiricoba, Arroyo de"}}
>>>>>>> 03f74aca74312dbeaf24d7e61306dd6a786dc3d0
