{
  "id": 2008865,
  "type": "Feature",
  "properties": {
    "tgn:hierarchy":[
        "tgn:2008865",
        "tgn:1000001",
        "tgn:7016172",
        "tgn:7012149",
        "tgn:2000129",
        "tgn:7029392"
    ],
    "tgn:id":2008865,
    "tgn:name":"Mammoth Spring",
    "tgn:placetype":[
        "aat:300008347"
    ]
},
  "bbox": [],
  "geometry": {"coordinates":[-91.5333,36.4833],"type":"Point"}
}