{
  "id": 7220569,
  "type": "Feature",
  "properties": {
    "tgn:hierarchy":[
        "tgn:7220569",
        "tgn:7011369",
        "tgn:7017076",
        "tgn:1000003",
        "tgn:1000074",
        "tgn:7029392"
    ],
    "tgn:id":7220569,
    "tgn:name":"V\u00e1sta",
    "tgn:placetype":[
        "aat:300008347"
    ]
},
  "bbox": [],
  "geometry": {"coordinates":[21.983333,37.366667],"type":"Point"}
}