{
  "id": 7151324,
  "type": "Feature",
  "properties": {
    "tgn:hierarchy":[
        "tgn:7151324",
        "tgn:1000003",
        "tgn:7003676",
        "tgn:7000084",
        "tgn:7029392"
    ],
    "tgn:id":7151324,
    "tgn:name":"Int\u00fcsken",
    "tgn:placetype":[
        "aat:300000206"
    ]
},
  "bbox": [],
  "geometry": {"coordinates":[7.883333,53.55],"type":"Point"}
}