{
  "id": 2314602,
  "type": "Feature",
  "properties": {
    "tgn:hierarchy":[
        "tgn:2314602",
        "tgn:1000001",
        "tgn:7012149",
        "tgn:2000850",
        "tgn:7007255",
        "tgn:7029392"
    ],
    "tgn:id":2314602,
    "tgn:name":"Elk Ridge",
    "tgn:placetype":[
        "aat:300266640"
    ]
},
  "bbox": [],
  "geometry": {"coordinates":[-84.7833,36.8167],"type":"Point"}
}