<<<<<<< HEAD
{
  "id": 7365818,
  "type": "Feature",
  "properties": {
    "tgn:hierarchy":[
        "tgn:7365818",
        "tgn:7005587",
        "tgn:1000001",
        "tgn:7005560",
        "tgn:7029392"
    ],
    "tgn:id":7365818,
    "tgn:name":"Epazoyuca",
    "tgn:placetype":[
        "aat:300008795"
    ]
},
  "bbox": [],
  "geometry": {"coordinates":[-98.633333,20.016667],"type":"Point"}
}
=======
{"geometry":{"type":"Point","coordinates":[-98.633333,20.016667]},"type":"Feature","properties":{"hierarchy":["tgn:7365818","tgn:7005587","tgn:1000001","tgn:7005560","tgn:7029392"],"placetype":["aat:300008795"],"id":7365818,"name:xx":"Epazoyuca"}}
>>>>>>> 03f74aca74312dbeaf24d7e61306dd6a786dc3d0
