{
  "id": 1100580,
  "type": "Feature",
  "properties": {
    "tgn:hierarchy":[
        "tgn:1100580",
        "tgn:7002445",
        "tgn:1000003",
        "tgn:7008154",
        "tgn:7008591",
        "tgn:7029392"
    ],
    "tgn:id":1100580,
    "tgn:name":"Hoghton Tower",
    "tgn:placetype":[
        "aat:300071272"
    ]
},
  "bbox": [],
  "geometry": {"coordinates":[-2.5667,53.7333],"type":"Point"}
}