{
  "id": 7049152,
  "type": "Feature",
  "properties": {
    "tgn:hierarchy":[
        "tgn:7049152",
        "tgn:1000003",
        "tgn:7003122",
        "tgn:7003157",
        "tgn:1000080",
        "tgn:7029392"
    ],
    "tgn:id":7049152,
    "tgn:name":"Divieto",
    "tgn:placetype":[
        "aat:300008347"
    ]
},
  "bbox": [],
  "geometry": {"coordinates":[15.433333,38.25],"type":"Point"}
}