{
  "id": 2709588,
  "type": "Feature",
  "properties": {
    "tgn:hierarchy":[
        "tgn:2709588",
        "tgn:1000001",
        "tgn:2001014",
        "tgn:7012149",
        "tgn:7007521",
        "tgn:7029392"
    ],
    "tgn:id":2709588,
    "tgn:name":"Taconite Harbor",
    "tgn:placetype":[
        "aat:300008678"
    ]
},
  "bbox": [],
  "geometry": {"coordinates":[-90.9167,47.5167],"type":"Point"}
}