{
  "id": 1137891,
  "type": "Feature",
  "properties": {
    "tgn:hierarchy":[
        "tgn:1137891",
        "tgn:1000004",
        "tgn:1003407",
        "tgn:7018214",
        "tgn:7002435",
        "tgn:7029392"
    ],
    "tgn:id":1137891,
    "tgn:name":"Maksimovka",
    "tgn:placetype":[
        "aat:300008347"
    ]
},
  "bbox": [],
  "geometry": {"coordinates":[51.1667,52.9833],"type":"Point"}
}