{
  "id": 7214301,
  "type": "Feature",
  "properties": {
    "tgn:hierarchy":[
        "tgn:7214301",
        "tgn:1000003",
        "tgn:7003688",
        "tgn:7000084",
        "tgn:7029392"
    ],
    "tgn:id":7214301,
    "tgn:name":"Bokelse\u00df",
    "tgn:placetype":[
        "aat:300008347"
    ]
},
  "bbox": [],
  "geometry": {"coordinates":[9.683333,53.85],"type":"Point"}
}