{
  "id": 2220564,
  "type": "Feature",
  "properties": {
    "tgn:hierarchy":[
        "tgn:2220564",
        "tgn:1000001",
        "tgn:2001734",
        "tgn:7012149",
        "tgn:7007712",
        "tgn:7029392"
    ],
    "tgn:id":2220564,
    "tgn:name":"Cape Romain Harbor",
    "tgn:placetype":[
        "aat:300132316"
    ]
},
  "bbox": [],
  "geometry": {"coordinates":[-79.35,33.05],"type":"Point"}
}