{
  "id": 1064746,
  "type": "Feature",
  "properties": {
    "tgn:hierarchy":[
        "tgn:1064746",
        "tgn:7002443",
        "tgn:1000003",
        "tgn:7018993",
        "tgn:7008591",
        "tgn:7029392"
    ],
    "tgn:id":1064746,
    "tgn:name:en":"Mathry",
    "tgn:placetype":[
        "aat:300008347"
    ]
},
  "bbox": [],
  "geometry": {"coordinates":[-5.086667,51.946389],"type":"Point"}
}