<<<<<<< HEAD
{
  "id": 7241202,
  "type": "Feature",
  "properties": {
    "tgn:hierarchy":[
        "tgn:7241202",
        "tgn:7003457",
        "tgn:1000003",
        "tgn:1000063",
        "tgn:7018236",
        "tgn:7029392"
    ],
    "tgn:id":7241202,
    "tgn:name":"Kwaremont",
    "tgn:placetype":[
        "aat:300008347"
    ]
},
  "bbox": [],
  "geometry": {"coordinates":[3.523799,50.77677],"type":"Point"}
}
=======
{"geometry":{"type":"Point","coordinates":[3.523799,50.776770]},"type":"Feature","properties":{"hierarchy":["tgn:7241202","tgn:7003457","tgn:1000003","tgn:1000063","tgn:7018236","tgn:7029392"],"placetype":["aat:300008347"],"id":7241202,"name:xx":"Kwaremont"}}
>>>>>>> 03f74aca74312dbeaf24d7e61306dd6a786dc3d0
