<<<<<<< HEAD
{
  "id": 7054902,
  "type": "Feature",
  "properties": {
    "tgn:hierarchy":[
        "tgn:7054902",
        "tgn:1003471",
        "tgn:1000003",
        "tgn:7003240",
        "tgn:1000080",
        "tgn:7029392"
    ],
    "tgn:id":7054902,
    "tgn:name":"Canale del Molino",
    "tgn:placetype":[
        "aat:300006075"
    ]
},
  "bbox": [],
  "geometry": {"coordinates":[13.6,43.383333],"type":"Point"}
}
=======
{"geometry":{"type":"Point","coordinates":[13.600000,43.383333]},"type":"Feature","properties":{"hierarchy":["tgn:7054902","tgn:1003471","tgn:1000003","tgn:7003240","tgn:1000080","tgn:7029392"],"placetype":["aat:300006075"],"id":7054902,"name:xx":"Canale del Molino"}}
>>>>>>> 03f74aca74312dbeaf24d7e61306dd6a786dc3d0
