{
  "id": 2059692,
  "type": "Feature",
  "properties": {
    "tgn:hierarchy":[
        "tgn:2059692",
        "tgn:1000001",
        "tgn:7012149",
        "tgn:2001212",
        "tgn:7007523",
        "tgn:7029392"
    ],
    "tgn:id":2059692,
    "tgn:name":"Mayview",
    "tgn:placetype":[
        "aat:300008347"
    ]
},
  "bbox": [],
  "geometry": {"coordinates":[-93.8167,39.05],"type":"Point"}
}