{
  "id": 2604297,
  "type": "Feature",
  "properties": {
    "tgn:hierarchy":[
        "tgn:2604297",
        "tgn:1000001",
        "tgn:7012149",
        "tgn:2000973",
        "tgn:7007520",
        "tgn:7029392"
    ],
    "tgn:id":2604297,
    "tgn:name":"Rabbit Back Peak",
    "tgn:placetype":[
        "aat:300008798"
    ]
},
  "bbox": [],
  "geometry": {"coordinates":[-84.7167,45.9167],"type":"Point"}
}