{
  "id": 2655218,
  "type": "Feature",
  "properties": {
    "tgn:hierarchy":[
        "tgn:2655218",
        "tgn:1000001",
        "tgn:7012149",
        "tgn:7007255",
        "tgn:7029392"
    ],
    "tgn:id":2655218,
    "tgn:name":"Shannon Run",
    "tgn:placetype":[
        "aat:300008699"
    ]
},
  "bbox": [],
  "geometry": {"coordinates":[-84.6333,37.9833],"type":"Point"}
}