{
  "id": 2687897,
  "type": "Feature",
  "properties": {
    "tgn:hierarchy":[
        "tgn:2687897",
        "tgn:1000001",
        "tgn:7012149",
        "tgn:1002626",
        "tgn:7007826",
        "tgn:7029392"
    ],
    "tgn:id":2687897,
    "tgn:name":"Springboard Lake",
    "tgn:placetype":[
        "aat:300008680"
    ]
},
  "bbox": [],
  "geometry": {"coordinates":[-95.8167,30.95],"type":"Point"}
}