{
  "id": 2277209,
  "type": "Feature",
  "properties": {
    "tgn:hierarchy":[
        "tgn:2277209",
        "tgn:1000001",
        "tgn:7012149",
        "tgn:2001284",
        "tgn:7007524",
        "tgn:7029392"
    ],
    "tgn:id":2277209,
    "tgn:name":"Davis Gulch III Mine",
    "tgn:placetype":[
        "aat:300000390"
    ]
},
  "bbox": [],
  "geometry": {"coordinates":[-112.0333,46.5667],"type":"Point"}
}