{
  "id": 2126422,
  "type": "Feature",
  "properties": {
    "tgn:hierarchy":[
        "tgn:2126422",
        "tgn:1000001",
        "tgn:2001418",
        "tgn:7012149",
        "tgn:7007526",
        "tgn:7029392"
    ],
    "tgn:id":2126422,
    "tgn:name":"Adolph Neher Adit",
    "tgn:placetype":[
        "aat:300000390"
    ]
},
  "bbox": [],
  "geometry": {"coordinates":[-116.7833,37.7167],"type":"Point"}
}