{
  "id": 7560358,
  "type": "Feature",
  "properties": {
    "tgn:hierarchy":[
        "tgn:7560358",
        "tgn:1000004",
        "tgn:7000198",
        "tgn:7016722",
        "tgn:7029392"
    ],
    "tgn:id":7560358,
    "tgn:name:en":"K\u0101simpur",
    "tgn:placetype":[
        "aat:300008347"
    ]
},
  "bbox": [],
  "geometry": {"coordinates":[79.377003,27.2188],"type":"Point"}
}