{
  "id": 7490590,
  "type": "Feature",
  "properties": {
    "tgn:hierarchy":[
        "tgn:7490590",
        "tgn:7001004",
        "tgn:1000004",
        "tgn:1000141",
        "tgn:7029392"
    ],
    "tgn:id":7490590,
    "tgn:name":"Dahu",
    "tgn:placetype":[
        "aat:300008347"
    ]
},
  "bbox": [],
  "geometry": {"coordinates":[120.243056,22.891389],"type":"Point"}
}