<<<<<<< HEAD
{
  "id": 2768400,
  "type": "Feature",
  "properties": {
    "tgn:hierarchy":[
        "tgn:2768400",
        "tgn:2002239",
        "tgn:1000001",
        "tgn:7012149",
        "tgn:7007920",
        "tgn:7029392"
    ],
    "tgn:id":2768400,
    "tgn:name":"Whitetail Butte",
    "tgn:placetype":[
        "aat:300008798"
    ]
},
  "bbox": [],
  "geometry": {"coordinates":[-117.35,46.0333],"type":"Point"}
}
=======
{"geometry":{"type":"Point","coordinates":[-117.350000,46.033300]},"type":"Feature","properties":{"hierarchy":["tgn:2768400","tgn:2002239","tgn:1000001","tgn:7012149","tgn:7007920","tgn:7029392"],"placetype":["aat:300008798"],"id":2768400,"name:xx":"Whitetail Butte"}}
>>>>>>> 03f74aca74312dbeaf24d7e61306dd6a786dc3d0
