{
  "id": 7038687,
  "type": "Feature",
  "properties": {
    "tgn:hierarchy":[
        "tgn:7038687",
        "tgn:7003135",
        "tgn:1000003",
        "tgn:7003080",
        "tgn:1000080",
        "tgn:7029392"
    ],
    "tgn:id":7038687,
    "tgn:name":"Terelle",
    "tgn:placetype":[
        "aat:300008347"
    ]
},
  "bbox": [],
  "geometry": {"coordinates":[13.783333,41.55],"type":"Point"}
}