{
  "id": 7307756,
  "type": "Feature",
  "properties": {
    "tgn:hierarchy":[
        "tgn:7307756",
        "tgn:7008912",
        "tgn:7030216",
        "tgn:1000003",
        "tgn:1000095",
        "tgn:7029392"
    ],
    "tgn:id":7307756,
    "tgn:name":"Llanera, R\u00edo de",
    "tgn:placetype":[
        "aat:300008699"
    ]
},
  "bbox": [],
  "geometry": {"coordinates":[1.392933,41.811956],"type":"Point"}
}