<<<<<<< HEAD
{
  "id": 7378604,
  "type": "Feature",
  "properties": {
    "tgn:hierarchy":[
        "tgn:7378604",
        "tgn:7005581",
        "tgn:1000001",
        "tgn:7005560",
        "tgn:7029392"
    ],
    "tgn:id":7378604,
    "tgn:name":"Rancho Los Piloncillos",
    "tgn:placetype":[
        "aat:300000241"
    ]
},
  "bbox": [],
  "geometry": {"coordinates":[-107.116667,29.1],"type":"Point"}
}
=======
{"geometry":{"type":"Point","coordinates":[-107.116667,29.100000]},"type":"Feature","properties":{"hierarchy":["tgn:7378604","tgn:7005581","tgn:1000001","tgn:7005560","tgn:7029392"],"placetype":["aat:300000241"],"id":7378604,"name:xx":"Rancho Los Piloncillos"}}
>>>>>>> 03f74aca74312dbeaf24d7e61306dd6a786dc3d0
