<<<<<<< HEAD
{
  "id": 7058351,
  "type": "Feature",
  "properties": {
    "tgn:hierarchy":[
        "tgn:7058351",
        "tgn:7005869",
        "tgn:1000003",
        "tgn:7003237",
        "tgn:1000080",
        "tgn:7029392"
    ],
    "tgn:id":7058351,
    "tgn:name":"Boschetto",
    "tgn:placetype":[
        "aat:300008347"
    ]
},
  "bbox": [],
  "geometry": {"coordinates":[10.033333,45.183333],"type":"Point"}
}
=======
{"geometry":{"type":"Point","coordinates":[10.033333,45.183333]},"type":"Feature","properties":{"hierarchy":["tgn:7058351","tgn:7005869","tgn:1000003","tgn:7003237","tgn:1000080","tgn:7029392"],"placetype":["aat:300008347"],"id":7058351,"name:xx":"Boschetto"}}
>>>>>>> 03f74aca74312dbeaf24d7e61306dd6a786dc3d0
