{
  "id": 2157202,
  "type": "Feature",
  "properties": {
    "tgn:hierarchy":[
        "tgn:2157202",
        "tgn:1000001",
        "tgn:7012149",
        "tgn:7007157",
        "tgn:2000186",
        "tgn:7029392"
    ],
    "tgn:id":2157202,
    "tgn:name":"Beaver Creek",
    "tgn:placetype":[
        "aat:300008706"
    ]
},
  "bbox": [],
  "geometry": {"coordinates":[-120.7833,41.75],"type":"Point"}
}