<<<<<<< HEAD
{
  "id": 7175565,
  "type": "Feature",
  "properties": {
    "tgn:hierarchy":[
        "tgn:7175565",
        "tgn:7003692",
        "tgn:1000003",
        "tgn:7000084",
        "tgn:7029392"
    ],
    "tgn:id":7175565,
    "tgn:name":"Gries Berg",
    "tgn:placetype":[
        "aat:300008777"
    ]
},
  "bbox": [],
  "geometry": {"coordinates":[10.45,48.7],"type":"Point"}
}
=======
{"geometry":{"type":"Point","coordinates":[10.450000,48.700000]},"type":"Feature","properties":{"hierarchy":["tgn:7175565","tgn:7003692","tgn:1000003","tgn:7000084","tgn:7029392"],"placetype":["aat:300008777"],"id":7175565,"name:xx":"Gries Berg"}}
>>>>>>> 03f74aca74312dbeaf24d7e61306dd6a786dc3d0
