{
  "id": 2161844,
  "type": "Feature",
  "properties": {
    "tgn:hierarchy":[
        "tgn:2161844",
        "tgn:1000001",
        "tgn:7012149",
        "tgn:2001160",
        "tgn:7007522",
        "tgn:7029392"
    ],
    "tgn:id":2161844,
    "tgn:name":"Bellevule",
    "tgn:placetype":[
        "aat:300008347"
    ]
},
  "bbox": [],
  "geometry": {"coordinates":[-91.0333,32.5667],"type":"Point"}
}