{
  "id": 7219342,
  "type": "Feature",
  "properties": {
    "tgn:hierarchy":[
        "tgn:7219342",
        "tgn:7011161",
        "tgn:7002674",
        "tgn:1000003",
        "tgn:1000074",
        "tgn:7029392"
    ],
    "tgn:id":7219342,
    "tgn:name":"Ag\u00eda Tri\u00e1s, Koryf\u00ed",
    "tgn:placetype":[
        "aat:300008798"
    ]
},
  "bbox": [],
  "geometry": {"coordinates":[26.005833,38.546389],"type":"Point"}
}