{
  "id": 7357058,
  "type": "Feature",
  "properties": {
    "tgn:hierarchy":[
        "tgn:7357058",
        "tgn:1000001",
        "tgn:7005595",
        "tgn:7005560",
        "tgn:7029392"
    ],
    "tgn:id":7357058,
    "tgn:name":"Carrizalejo",
    "tgn:placetype":[
        "aat:300008347"
    ]
},
  "bbox": [],
  "geometry": {"coordinates":[-107.766667,25.766667],"type":"Point"}
}