{
  "id": 7097399,
  "type": "Feature",
  "properties": {
    "tgn:hierarchy":[
        "tgn:7097399",
        "tgn:1000003",
        "tgn:7003677",
        "tgn:7000084",
        "tgn:7029392"
    ],
    "tgn:id":7097399,
    "tgn:name":"Bahnhof Spyck",
    "tgn:placetype":[
        "aat:300007783"
    ]
},
  "bbox": [],
  "geometry": {"coordinates":[6.166667,51.833333],"type":"Point"}
}