{
  "id": 2480637,
  "type": "Feature",
  "properties": {
    "tgn:hierarchy":[
        "tgn:2480637",
        "tgn:1002201",
        "tgn:1000001",
        "tgn:7012149",
        "tgn:7007517",
        "tgn:7029392"
    ],
    "tgn:id":2480637,
    "tgn:name":"Lakes Island",
    "tgn:placetype":[
        "aat:300008791"
    ]
},
  "bbox": [],
  "geometry": {"coordinates":[-71.0667,41.55],"type":"Point"}
}