{
  "id": 2245178,
  "type": "Feature",
  "properties": {
    "tgn:hierarchy":[
        "tgn:2245178",
        "tgn:1000001",
        "tgn:2001016",
        "tgn:7012149",
        "tgn:7007521",
        "tgn:7029392"
    ],
    "tgn:id":2245178,
    "tgn:name":"Cloverleaf Lake",
    "tgn:placetype":[
        "aat:300008680"
    ]
},
  "bbox": [],
  "geometry": {"coordinates":[-94.2833,46.5833],"type":"Point"}
}