{
  "id": 7328702,
  "type": "Feature",
  "properties": {
    "tgn:hierarchy":[
        "tgn:7328702",
        "tgn:7001158",
        "tgn:7002850",
        "tgn:1000003",
        "tgn:1000095",
        "tgn:7029392"
    ],
    "tgn:id":7328702,
    "tgn:name":"Regomillos, Arroyo de los",
    "tgn:placetype":[
        "aat:300008699"
    ]
},
  "bbox": [],
  "geometry": {"coordinates":[-6.116667,41.233333],"type":"Point"}
}