{
  "id": 7444890,
  "type": "Feature",
  "properties": {
    "tgn:hierarchy":[
        "tgn:7444890",
        "tgn:7002444",
        "tgn:1000003",
        "tgn:7008082",
        "tgn:7008591",
        "tgn:7029392"
    ],
    "tgn:id":7444890,
    "tgn:name:en":"Tulloch Station",
    "tgn:placetype":[
        "aat:300007783"
    ]
},
  "bbox": [],
  "geometry": {"coordinates":[-4.716667,56.883333],"type":"Point"}
}