{
  "id": 7406755,
  "type": "Feature",
  "properties": {
    "tgn:hierarchy":[
        "tgn:7406755",
        "tgn:1000001",
        "tgn:1001906",
        "tgn:7005560",
        "tgn:7029392"
    ],
    "tgn:id":7406755,
    "tgn:name":"Los Llanitos",
    "tgn:placetype":[
        "aat:300008347"
    ]
},
  "bbox": [],
  "geometry": {"coordinates":[-105.445833,22.316667],"type":"Point"}
}