{
  "id": 2044323,
  "type": "Feature",
  "properties": {
    "tgn:hierarchy":[
        "tgn:2044323",
        "tgn:1000001",
        "tgn:7012149",
        "tgn:2000874",
        "tgn:7007256",
        "tgn:7029392"
    ],
    "tgn:id":2044323,
    "tgn:name":"Wisner",
    "tgn:placetype":[
        "aat:300008347"
    ]
},
  "bbox": [],
  "geometry": {"coordinates":[-91.65,31.9667],"type":"Point"}
}