<<<<<<< HEAD
{
  "id": 2760794,
  "type": "Feature",
  "properties": {
    "tgn:hierarchy":[
        "tgn:2760794",
        "tgn:1000001",
        "tgn:7012149",
        "tgn:7007157",
        "tgn:2000189",
        "tgn:7029392"
    ],
    "tgn:id":2760794,
    "tgn:name":"West Haight Mountain",
    "tgn:placetype":[
        "aat:300008798"
    ]
},
  "bbox": [],
  "geometry": {"coordinates":[-122.0,41.5333],"type":"Point"}
}
=======
{"geometry":{"type":"Point","coordinates":[-122.000000,41.533300]},"type":"Feature","properties":{"hierarchy":["tgn:2760794","tgn:1000001","tgn:7012149","tgn:7007157","tgn:2000189","tgn:7029392"],"placetype":["aat:300008798"],"id":2760794,"name:xx":"West Haight Mountain"}}
>>>>>>> 03f74aca74312dbeaf24d7e61306dd6a786dc3d0
