{
  "id": 1082222,
  "type": "Feature",
  "properties": {
    "tgn:hierarchy":[
        "tgn:1082222",
        "tgn:1001193",
        "tgn:1006792",
        "tgn:1000004",
        "tgn:7000299",
        "tgn:7029392"
    ],
    "tgn:id":1082222,
    "tgn:name":"Chindo",
    "tgn:placetype":[
        "aat:300008347"
    ]
},
  "bbox": [],
  "geometry": {"coordinates":[126.25,34.4667],"type":"Point"}
}