{
  "id": 2747793,
  "type": "Feature",
  "properties": {
    "tgn:hierarchy":[
        "tgn:2747793",
        "tgn:1000001",
        "tgn:7012149",
        "tgn:2001548",
        "tgn:7007709",
        "tgn:7029392"
    ],
    "tgn:id":2747793,
    "tgn:name":"Wake Forest Reservoir",
    "tgn:placetype":[
        "aat:300006191"
    ]
},
  "bbox": [],
  "geometry": {"coordinates":[-78.4833,35.9667],"type":"Point"}
}