{
  "id": 2186497,
  "type": "Feature",
  "properties": {
    "tgn:hierarchy":[
        "tgn:2186497",
        "tgn:1000001",
        "tgn:7012149",
        "tgn:2001295",
        "tgn:7007524",
        "tgn:7029392"
    ],
    "tgn:id":2186497,
    "tgn:name":"Bone Crossing",
    "tgn:placetype":[
        "aat:300008347"
    ]
},
  "bbox": [],
  "geometry": {"coordinates":[-107.3167,48.5167],"type":"Point"}
}