{
  "id": 7572250,
  "type": "Feature",
  "properties": {
    "tgn:hierarchy":[
        "tgn:7572250",
        "tgn:1000004",
        "tgn:7000198",
        "tgn:1001894",
        "tgn:7029392"
    ],
    "tgn:id":7572250,
    "tgn:name:en":"Hirri River",
    "tgn:placetype":[
        "aat:300008699"
    ]
},
  "bbox": [],
  "geometry": {"coordinates":[80.031855,22.178429],"type":"Point"}
}