{
  "id": 2358961,
  "type": "Feature",
  "properties": {
    "tgn:hierarchy":[
        "tgn:2358961",
        "tgn:1000001",
        "tgn:1002260",
        "tgn:7012149",
        "tgn:7007920",
        "tgn:7029392"
    ],
    "tgn:id":2358961,
    "tgn:name":"Granite Falls Creek",
    "tgn:placetype":[
        "aat:300008706"
    ]
},
  "bbox": [],
  "geometry": {"coordinates":[-120.2333,47.9167],"type":"Point"}
}