{
  "id": 7030410,
  "type": "Feature",
  "properties": {
    "tgn:hierarchy":[
        "tgn:7030410",
        "tgn:1000004",
        "tgn:7001796",
        "tgn:1000111",
        "tgn:7029392"
    ],
    "tgn:id":7030410,
    "tgn:name":"Jiahu",
    "tgn:placetype":[
        "aat:300008347"
    ]
},
  "bbox": [],
  "geometry": {"coordinates":[119.186,26.451],"type":"Point"}
}