{
  "id": 7545636,
  "type": "Feature",
  "properties": {
    "tgn:hierarchy":[
        "tgn:7545636",
        "tgn:1000004",
        "tgn:7000198",
        "tgn:1001894",
        "tgn:7029392"
    ],
    "tgn:id":7545636,
    "tgn:name:en":"Barodia",
    "tgn:placetype":[
        "aat:300008347"
    ]
},
  "bbox": [],
  "geometry": {"coordinates":[76.336125,23.604242],"type":"Point"}
}