{
  "id": 7166484,
  "type": "Feature",
  "properties": {
    "tgn:hierarchy":[
        "tgn:7166484",
        "tgn:1000003",
        "tgn:7003682",
        "tgn:7000084",
        "tgn:7029392"
    ],
    "tgn:id":7166484,
    "tgn:name":"Hasel-Stein",
    "tgn:placetype":[
        "aat:300008777"
    ]
},
  "bbox": [],
  "geometry": {"coordinates":[7.866667,49.15],"type":"Point"}
}