{
  "id": 1074580,
  "type": "Feature",
  "properties": {
    "tgn:hierarchy":[
        "tgn:1074580",
        "tgn:1000004",
        "tgn:7000198",
        "tgn:7000799",
        "tgn:7029392"
    ],
    "tgn:id":1074580,
    "tgn:name":"Bagdom",
    "tgn:placetype":[
        "aat:300008347"
    ]
},
  "bbox": [],
  "geometry": {"coordinates":[74.7167,34.0167],"type":"Point"}
}