{
  "id": 7270506,
  "type": "Feature",
  "properties": {
    "tgn:hierarchy":[
        "tgn:7270506",
        "tgn:1000003",
        "tgn:7003635",
        "tgn:7016845",
        "tgn:7029392"
    ],
    "tgn:id":7270506,
    "tgn:name:nl":"Oude Tonge, Plaat van",
    "tgn:placetype":[
        "aat:300132350"
    ]
},
  "bbox": [],
  "geometry": {"coordinates":[4.116667,51.666667],"type":"Point"}
}