<<<<<<< HEAD
{
  "id": 2406463,
  "type": "Feature",
  "properties": {
    "tgn:hierarchy":[
        "tgn:2406463",
        "tgn:1000001",
        "tgn:7012149",
        "tgn:1002827",
        "tgn:7007252",
        "tgn:7029392"
    ],
    "tgn:id":2406463,
    "tgn:name":"Hungry Hollow",
    "tgn:placetype":[
        "aat:300008761"
    ]
},
  "bbox": [],
  "geometry": {"coordinates":[-85.35,39.0333],"type":"Point"}
}
=======
{"geometry":{"type":"Point","coordinates":[-85.350000,39.033300]},"type":"Feature","properties":{"hierarchy":["tgn:2406463","tgn:1000001","tgn:7012149","tgn:1002827","tgn:7007252","tgn:7029392"],"placetype":["aat:300008761"],"id":2406463,"name:xx":"Hungry Hollow"}}
>>>>>>> 03f74aca74312dbeaf24d7e61306dd6a786dc3d0
