{
  "id": 2570141,
  "type": "Feature",
  "properties": {
    "tgn:hierarchy":[
        "tgn:2570141",
        "tgn:7006450",
        "tgn:1000001",
        "tgn:7012149",
        "tgn:2000082",
        "tgn:7029392"
    ],
    "tgn:id":2570141,
    "tgn:name":"Passage Island",
    "tgn:placetype":[
        "aat:300008791"
    ]
},
  "bbox": [],
  "geometry": {"coordinates":[-132.8667,55.1667],"type":"Point"}
}