{
  "id": 2176899,
  "type": "Feature",
  "properties": {
    "tgn:hierarchy":[
        "tgn:2176899",
        "tgn:1000001",
        "tgn:7012149",
        "tgn:2002111",
        "tgn:7007827",
        "tgn:7029392"
    ],
    "tgn:id":2176899,
    "tgn:name":"Black Mountain",
    "tgn:placetype":[
        "aat:300008798"
    ]
},
  "bbox": [],
  "geometry": {"coordinates":[-112.9333,37.5667],"type":"Point"}
}