{
  "id": 7150105,
  "type": "Feature",
  "properties": {
    "tgn:hierarchy":[
        "tgn:7150105",
        "tgn:1000003",
        "tgn:7003678",
        "tgn:7000084",
        "tgn:7029392"
    ],
    "tgn:id":7150105,
    "tgn:name":"Kratz-Bach",
    "tgn:placetype":[
        "aat:300008699"
    ]
},
  "bbox": [],
  "geometry": {"coordinates":[9.683333,50.55],"type":"Point"}
}