{
  "id": 2582669,
  "type": "Feature",
  "properties": {
    "tgn:hierarchy":[
        "tgn:2582669",
        "tgn:1000001",
        "tgn:7012149",
        "tgn:1002494",
        "tgn:7007710",
        "tgn:7029392"
    ],
    "tgn:id":2582669,
    "tgn:name":"Pine Hill Picnic Area",
    "tgn:placetype":[
        "aat:300055621"
    ]
},
  "bbox": [],
  "geometry": {"coordinates":[-78.0333,40.6333],"type":"Point"}
}