{
  "id": 1100514,
  "type": "Feature",
  "properties": {
    "tgn:hierarchy":[
        "tgn:1100514",
        "tgn:7001242",
        "tgn:7016833",
        "tgn:1001418",
        "tgn:7029392"
    ],
    "tgn:id":1100514,
    "tgn:name":"\u1e62aqq\u00e2ra",
    "tgn:placetype":[
        "aat:300000810",
        "aat:300387004",
        "aat:300000372",
        "aat:300008057"
    ]
},
  "bbox": [],
  "geometry": {"coordinates":[31.2167,29.85],"type":"Point"}
}