{
  "id": 7236704,
  "type": "Feature",
  "properties": {
    "tgn:hierarchy":[
        "tgn:7236704",
        "tgn:7002707",
        "tgn:7002705",
        "tgn:1000003",
        "tgn:1000074",
        "tgn:7029392"
    ],
    "tgn:id":7236704,
    "tgn:name":"Artopo\u00fala",
    "tgn:placetype":[
        "aat:300008347"
    ]
},
  "bbox": [],
  "geometry": {"coordinates":[20.686667,39.495],"type":"Point"}
}