{
  "id": 7443090,
  "type": "Feature",
  "properties": {
    "tgn:hierarchy":[
        "tgn:7443090",
        "tgn:7002445",
        "tgn:1000003",
        "tgn:7011961",
        "tgn:7008591",
        "tgn:7029392"
    ],
    "tgn:id":7443090,
    "tgn:name:en":"Osmington Hill",
    "tgn:placetype":[
        "aat:300008777"
    ]
},
  "bbox": [],
  "geometry": {"coordinates":[-2.426667,50.641667],"type":"Point"}
}