{
  "id": 2009642,
  "type": "Feature",
  "properties": {
    "tgn:hierarchy":[
        "tgn:2009642",
        "tgn:1000001",
        "tgn:7016172",
        "tgn:2000123",
        "tgn:7012149",
        "tgn:7029392"
    ],
    "tgn:id":2009642,
    "tgn:name":"Togo",
    "tgn:placetype":[
        "aat:300008347",
        "aat:300387210"
    ]
},
  "bbox": [],
  "geometry": {"coordinates":[-90.5333,35.3333],"type":"Point"}
}