{
  "id": 2360039,
  "type": "Feature",
  "properties": {
    "tgn:hierarchy":[
        "tgn:2360039",
        "tgn:1000001",
        "tgn:7012149",
        "tgn:1002617",
        "tgn:7007520",
        "tgn:7029392"
    ],
    "tgn:id":2360039,
    "tgn:name":"Grass Island",
    "tgn:placetype":[
        "aat:300008791"
    ]
},
  "bbox": [],
  "geometry": {"coordinates":[-82.7667,42.5833],"type":"Point"}
}