{
  "id": 7513752,
  "type": "Feature",
  "properties": {
    "tgn:hierarchy":[
        "tgn:7513752",
        "tgn:1009227",
        "tgn:7001866",
        "tgn:1000226",
        "tgn:1000006",
        "tgn:7029392"
    ],
    "tgn:id":7513752,
    "tgn:name:en":"Forbes Glacier",
    "tgn:placetype":[
        "aat:300008835"
    ]
},
  "bbox": [],
  "geometry": {"coordinates":[170.616667,-43.45],"type":"Point"}
}