<<<<<<< HEAD
{
  "id": 7247047,
  "type": "Feature",
  "properties": {
    "tgn:hierarchy":[
        "tgn:7247047",
        "tgn:7003466",
        "tgn:1000003",
        "tgn:1000063",
        "tgn:4012014",
        "tgn:7029392"
    ],
    "tgn:id":7247047,
    "tgn:name":"Doumont",
    "tgn:placetype":[
        "aat:300000206"
    ]
},
  "bbox": [],
  "geometry": {"coordinates":[4.7,50.4],"type":"Point"}
}
=======
{"geometry":{"type":"Point","coordinates":[4.700000,50.400000]},"type":"Feature","properties":{"hierarchy":["tgn:7247047","tgn:7003466","tgn:1000003","tgn:1000063","tgn:4012014","tgn:7029392"],"placetype":["aat:300000206"],"id":7247047,"name:xx":"Doumont"}}
>>>>>>> 03f74aca74312dbeaf24d7e61306dd6a786dc3d0
