<<<<<<< HEAD
{
  "id": 2331046,
  "type": "Feature",
  "properties": {
    "tgn:hierarchy":[
        "tgn:2331046",
        "tgn:1000001",
        "tgn:7012149",
        "tgn:7013961",
        "tgn:7029392"
    ],
    "tgn:id":2331046,
    "tgn:name":"Flat Run",
    "tgn:placetype":[
        "aat:300008699"
    ]
},
  "bbox": [],
  "geometry": {"coordinates":[-80.3833,38.7333],"type":"Point"}
}
=======
{"geometry":{"type":"Point","coordinates":[-80.383300,38.733300]},"type":"Feature","properties":{"hierarchy":["tgn:2331046","tgn:1000001","tgn:7012149","tgn:7013961","tgn:7029392"],"placetype":["aat:300008699"],"id":2331046,"name:xx":"Flat Run"}}
>>>>>>> 03f74aca74312dbeaf24d7e61306dd6a786dc3d0
