{
  "id": 2431667,
  "type": "Feature",
  "properties": {
    "tgn:hierarchy":[
        "tgn:2431667",
        "tgn:7002659",
        "tgn:1000001",
        "tgn:7012149",
        "tgn:2000059",
        "tgn:7029392"
    ],
    "tgn:id":2431667,
    "tgn:name":"Katherine Allison Lake",
    "tgn:placetype":[
        "aat:300006191"
    ]
},
  "bbox": [],
  "geometry": {"coordinates":[-88.1167,32.5333],"type":"Point"}
}