{
  "id": 2146426,
  "type": "Feature",
  "properties": {
    "tgn:hierarchy":[
        "tgn:2146426",
        "tgn:2001001",
        "tgn:1000001",
        "tgn:7012149",
        "tgn:7007521",
        "tgn:7029392"
    ],
    "tgn:id":2146426,
    "tgn:name":"Balsam Lake",
    "tgn:placetype":[
        "aat:300008680"
    ]
},
  "bbox": [],
  "geometry": {"coordinates":[-95.6833,46.95],"type":"Point"}
}