{
  "id": 2528011,
  "type": "Feature",
  "properties": {
    "tgn:hierarchy":[
        "tgn:2528011",
        "tgn:1000001",
        "tgn:2001801",
        "tgn:7012149",
        "tgn:7007713",
        "tgn:7029392"
    ],
    "tgn:id":2528011,
    "tgn:name":"Mountain Ranch Spring Number Two",
    "tgn:placetype":[
        "aat:300008697"
    ]
},
  "bbox": [],
  "geometry": {"coordinates":[-103.1667,45.3667],"type":"Point"}
}