{
  "id": 2446454,
  "type": "Feature",
  "properties": {
    "tgn:hierarchy":[
        "tgn:2446454",
        "tgn:1000001",
        "tgn:7014423",
        "tgn:7012149",
        "tgn:7007517",
        "tgn:7029392"
    ],
    "tgn:id":2446454,
    "tgn:name":"Lewis Island",
    "tgn:placetype":[
        "aat:300008791"
    ]
},
  "bbox": [],
  "geometry": {"coordinates":[-70.9333,41.7833],"type":"Point"}
}