{
  "id": 1137780,
  "type": "Feature",
  "properties": {
    "tgn:hierarchy":[
        "tgn:1137780",
        "tgn:1000004",
        "tgn:7011497",
        "tgn:7002435",
        "tgn:7029392"
    ],
    "tgn:id":1137780,
    "tgn:name":"Krasnyj Many\u010d",
    "tgn:placetype":[
        "aat:300008347"
    ]
},
  "bbox": [],
  "geometry": {"coordinates":[42.1667,46.55],"type":"Point"}
}