{
  "id": 2740651,
  "type": "Feature",
  "properties": {
    "tgn:hierarchy":[
        "tgn:2740651",
        "tgn:1000001",
        "tgn:7012149",
        "tgn:2000235",
        "tgn:7007158",
        "tgn:7029392"
    ],
    "tgn:id":2740651,
    "tgn:name":"Upper Platte and Beaver Canal",
    "tgn:placetype":[
        "aat:300006075"
    ]
},
  "bbox": [],
  "geometry": {"coordinates":[-103.6833,40.25],"type":"Point"}
}