{
  "id": 2283505,
  "type": "Feature",
  "properties": {
    "tgn:hierarchy":[
        "tgn:2283505",
        "tgn:7006450",
        "tgn:1000001",
        "tgn:7012149",
        "tgn:2000085",
        "tgn:7029392"
    ],
    "tgn:id":2283505,
    "tgn:name":"Delta Creek",
    "tgn:placetype":[
        "aat:300008706"
    ]
},
  "bbox": [],
  "geometry": {"coordinates":[-146.4167,63.75],"type":"Point"}
}