{
  "id": 7022293,
  "type": "Feature",
  "properties": {
    "tgn:hierarchy":[
        "tgn:7022293",
        "tgn:1000001",
        "tgn:7012149",
        "tgn:7007157",
        "tgn:7029392"
    ],
    "tgn:id":7022293,
    "tgn:name":"Angeles National Forest",
    "tgn:placetype":[
        "aat:300008863"
    ]
},
  "bbox": [],
  "geometry": {"coordinates":[-118.25,34.3667],"type":"Point"}
}