<<<<<<< HEAD
{
  "id": 7022293,
  "type": "Feature",
  "properties": {
    "tgn:hierarchy":[
        "tgn:7022293",
        "tgn:1000001",
        "tgn:7012149",
        "tgn:7007157",
        "tgn:7029392"
    ],
    "tgn:id":7022293,
    "tgn:name":"Angeles National Forest",
    "tgn:placetype":[
        "aat:300008863"
    ]
},
  "bbox": [],
  "geometry": {"coordinates":[-118.25,34.3667],"type":"Point"}
}
=======
{"geometry":{"type":"Point","coordinates":[-118.250000,34.366700]},"type":"Feature","properties":{"hierarchy":["tgn:7022293","tgn:1000001","tgn:7012149","tgn:7007157","tgn:7029392"],"placetype":["aat:300008863"],"id":7022293,"name:xx":"Angeles National Forest"}}
>>>>>>> 03f74aca74312dbeaf24d7e61306dd6a786dc3d0
