{
  "id": 2691478,
  "type": "Feature",
  "properties": {
    "tgn:hierarchy":[
        "tgn:2691478",
        "tgn:1000001",
        "tgn:1002260",
        "tgn:7012149",
        "tgn:7007920",
        "tgn:7029392"
    ],
    "tgn:id":2691478,
    "tgn:name":"Star Peak",
    "tgn:placetype":[
        "aat:300008798"
    ]
},
  "bbox": [],
  "geometry": {"coordinates":[-120.4167,48.25],"type":"Point"}
}