{
  "id": 7415094,
  "type": "Feature",
  "properties": {
    "tgn:hierarchy":[
        "tgn:7415094",
        "tgn:1000001",
        "tgn:7005591",
        "tgn:7005560",
        "tgn:7029392"
    ],
    "tgn:id":7415094,
    "tgn:name:es":"Negro, Cerro",
    "tgn:placetype":[
        "aat:300008795"
    ]
},
  "bbox": [],
  "geometry": {"coordinates":[-97.430833,17.326667],"type":"Point"}
}