{
  "id": 7592308,
  "type": "Feature",
  "properties": {
    "tgn:hierarchy":[
        "tgn:7592308",
        "tgn:1000004",
        "tgn:7000198",
        "tgn:7000799",
        "tgn:7029392"
    ],
    "tgn:id":7592308,
    "tgn:name:en":"Krishnanagar",
    "tgn:placetype":[
        "aat:300008347"
    ]
},
  "bbox": [],
  "geometry": {"coordinates":[74.858333,32.727778],"type":"Point"}
}