{
  "id": 7232336,
  "type": "Feature",
  "properties": {
    "tgn:hierarchy":[
        "tgn:7232336",
        "tgn:7002681",
        "tgn:7001395",
        "tgn:1000003",
        "tgn:1000074",
        "tgn:7029392"
    ],
    "tgn:id":7232336,
    "tgn:name":"Sk\u00edntos, Orm\u00edskos",
    "tgn:placetype":[
        "aat:300132317"
    ]
},
  "bbox": [],
  "geometry": {"coordinates":[23.336502,37.342128],"type":"Point"}
}