{
  "id": 2389050,
  "type": "Feature",
  "properties": {
    "tgn:hierarchy":[
        "tgn:2389050",
        "tgn:1000001",
        "tgn:7012149",
        "tgn:2001708",
        "tgn:7007708",
        "tgn:7029392"
    ],
    "tgn:id":2389050,
    "tgn:name":"Hidden Spring",
    "tgn:placetype":[
        "aat:300008697"
    ]
},
  "bbox": [],
  "geometry": {"coordinates":[-118.6833,44.1333],"type":"Point"}
}