{
  "id": 2783896,
  "type": "Feature",
  "properties": {
    "tgn:hierarchy":[
        "tgn:2783896",
        "tgn:1000001",
        "tgn:2001416",
        "tgn:7012149",
        "tgn:7007526",
        "tgn:7029392"
    ],
    "tgn:id":2783896,
    "tgn:name":"X-Ray Tunnel",
    "tgn:placetype":[
        "aat:300000390"
    ]
},
  "bbox": [],
  "geometry": {"coordinates":[-114.5833,37.9333],"type":"Point"}
}