{
  "id": 7222080,
  "type": "Feature",
  "properties": {
    "tgn:hierarchy":[
        "tgn:7222080",
        "tgn:7011167",
        "tgn:7001338",
        "tgn:1000003",
        "tgn:1000074",
        "tgn:7029392"
    ],
    "tgn:id":7222080,
    "tgn:name":"Mikr\u00f3n Gal\u00e1ron",
    "tgn:placetype":[
        "aat:300008347"
    ]
},
  "bbox": [],
  "geometry": {"coordinates":[20.783333,37.783333],"type":"Point"}
}