<<<<<<< HEAD
{
  "id": 2250311,
  "type": "Feature",
  "properties": {
    "tgn:hierarchy":[
        "tgn:2250311",
        "tgn:1000001",
        "tgn:7012149",
        "tgn:2000290",
        "tgn:7007240",
        "tgn:7029392"
    ],
    "tgn:id":2250311,
    "tgn:name":"Collinsworth Pond",
    "tgn:placetype":[
        "aat:300008680"
    ]
},
  "bbox": [],
  "geometry": {"coordinates":[-86.1167,30.9167],"type":"Point"}
}
=======
{"geometry":{"type":"Point","coordinates":[-86.116700,30.916700]},"type":"Feature","properties":{"hierarchy":["tgn:2250311","tgn:1000001","tgn:7012149","tgn:2000290","tgn:7007240","tgn:7029392"],"placetype":["aat:300008680"],"id":2250311,"name:xx":"Collinsworth Pond"}}
>>>>>>> 03f74aca74312dbeaf24d7e61306dd6a786dc3d0
