{
  "id": 2250311,
  "type": "Feature",
  "properties": {
    "tgn:hierarchy":[
        "tgn:2250311",
        "tgn:1000001",
        "tgn:7012149",
        "tgn:2000290",
        "tgn:7007240",
        "tgn:7029392"
    ],
    "tgn:id":2250311,
    "tgn:name":"Collinsworth Pond",
    "tgn:placetype":[
        "aat:300008680"
    ]
},
  "bbox": [],
  "geometry": {"coordinates":[-86.1167,30.9167],"type":"Point"}
}