<<<<<<< HEAD
{
  "id": 2407824,
  "type": "Feature",
  "properties": {
    "tgn:hierarchy":[
        "tgn:2407824",
        "tgn:1000001",
        "tgn:7012149",
        "tgn:7015666",
        "tgn:7007825",
        "tgn:7029392"
    ],
    "tgn:id":2407824,
    "tgn:name":"Hurricane Branch",
    "tgn:placetype":[
        "aat:300008699"
    ]
},
  "bbox": [],
  "geometry": {"coordinates":[-87.6667,35.7],"type":"Point"}
}
=======
{"geometry":{"type":"Point","coordinates":[-87.666700,35.700000]},"type":"Feature","properties":{"hierarchy":["tgn:2407824","tgn:1000001","tgn:7012149","tgn:7015666","tgn:7007825","tgn:7029392"],"placetype":["aat:300008699"],"id":2407824,"name:xx":"Hurricane Branch"}}
>>>>>>> 03f74aca74312dbeaf24d7e61306dd6a786dc3d0
