{
  "id": 7467220,
  "type": "Feature",
  "properties": {
    "tgn:hierarchy":[
        "tgn:7467220",
        "tgn:7002445",
        "tgn:7008103",
        "tgn:1000003",
        "tgn:7008591",
        "tgn:7029392"
    ],
    "tgn:id":7467220,
    "tgn:name:en":"Billington",
    "tgn:placetype":[
        "aat:300008347"
    ]
},
  "bbox": [],
  "geometry": {"coordinates":[-0.633333,51.883333],"type":"Point"}
}