<<<<<<< HEAD
{
  "id": 2339619,
  "type": "Feature",
  "properties": {
    "tgn:hierarchy":[
        "tgn:2339619",
        "tgn:1000001",
        "tgn:7012149",
        "tgn:2001913",
        "tgn:7007825",
        "tgn:7029392"
    ],
    "tgn:id":2339619,
    "tgn:name":"Fredonia",
    "tgn:placetype":[
        "aat:300008347"
    ]
},
  "bbox": [],
  "geometry": {"coordinates":[-85.4167,35.3833],"type":"Point"}
}
=======
{"geometry":{"type":"Point","coordinates":[-85.416700,35.383300]},"type":"Feature","properties":{"hierarchy":["tgn:2339619","tgn:1000001","tgn:7012149","tgn:2001913","tgn:7007825","tgn:7029392"],"placetype":["aat:300008347"],"id":2339619,"name:xx":"Fredonia"}}
>>>>>>> 03f74aca74312dbeaf24d7e61306dd6a786dc3d0
