{
  "id": 7285813,
  "type": "Feature",
  "properties": {
    "tgn:hierarchy":[
        "tgn:7285813",
        "tgn:1001699",
        "tgn:1000049",
        "tgn:1000002",
        "tgn:7029392"
    ],
    "tgn:id":7285813,
    "tgn:name":"Piure, Canal",
    "tgn:placetype":[
        "aat:300387026"
    ]
},
  "bbox": [],
  "geometry": {"coordinates":[-73.684444,-44.314722],"type":"Point"}
}