<<<<<<< HEAD
{
  "id": 2257251,
  "type": "Feature",
  "properties": {
    "tgn:hierarchy":[
        "tgn:2257251",
        "tgn:1000001",
        "tgn:7012149",
        "tgn:2002020",
        "tgn:7007826",
        "tgn:7029392"
    ],
    "tgn:id":2257251,
    "tgn:name":"Corner Windmill",
    "tgn:placetype":[
        "aat:300008347"
    ]
},
  "bbox": [],
  "geometry": {"coordinates":[-100.5,33.6167],"type":"Point"}
}
=======
{"geometry":{"type":"Point","coordinates":[-100.500000,33.616700]},"type":"Feature","properties":{"hierarchy":["tgn:2257251","tgn:1000001","tgn:7012149","tgn:2002020","tgn:7007826","tgn:7029392"],"placetype":["aat:300008347"],"id":2257251,"name:xx":"Corner Windmill"}}
>>>>>>> 03f74aca74312dbeaf24d7e61306dd6a786dc3d0
