<<<<<<< HEAD
{
  "id": 2254027,
  "type": "Feature",
  "properties": {
    "tgn:hierarchy":[
        "tgn:2254027",
        "tgn:1000001",
        "tgn:7012149",
        "tgn:1002659",
        "tgn:7007710",
        "tgn:7029392"
    ],
    "tgn:id":2254027,
    "tgn:name":"Cool Spring Creek",
    "tgn:placetype":[
        "aat:300008706"
    ]
},
  "bbox": [],
  "geometry": {"coordinates":[-80.2,41.35],"type":"Point"}
}
=======
{"geometry":{"type":"Point","coordinates":[-80.200000,41.350000]},"type":"Feature","properties":{"hierarchy":["tgn:2254027","tgn:1000001","tgn:7012149","tgn:1002659","tgn:7007710","tgn:7029392"],"placetype":["aat:300008706"],"id":2254027,"name:xx":"Cool Spring Creek"}}
>>>>>>> 03f74aca74312dbeaf24d7e61306dd6a786dc3d0
