{
  "id": 2619365,
  "type": "Feature",
  "properties": {
    "tgn:hierarchy":[
        "tgn:2619365",
        "tgn:1000001",
        "tgn:7012149",
        "tgn:2001718",
        "tgn:7007708",
        "tgn:7029392"
    ],
    "tgn:id":2619365,
    "tgn:name":"Rim Spring",
    "tgn:placetype":[
        "aat:300008697"
    ]
},
  "bbox": [],
  "geometry": {"coordinates":[-117.8167,43.8167],"type":"Point"}
}