{
  "id": 2390892,
  "type": "Feature",
  "properties": {
    "tgn:hierarchy":[
        "tgn:2390892",
        "tgn:2002308",
        "tgn:1000001",
        "tgn:7012149",
        "tgn:7007922",
        "tgn:7029392"
    ],
    "tgn:id":2390892,
    "tgn:name":"Hildebrand Lake",
    "tgn:placetype":[
        "aat:300008680"
    ]
},
  "bbox": [],
  "geometry": {"coordinates":[-91.15,46.15],"type":"Point"}
}