{
  "id": 7518494,
  "type": "Feature",
  "properties": {
    "tgn:hierarchy":[
        "tgn:7518494",
        "tgn:1009227",
        "tgn:1000226",
        "tgn:7016822",
        "tgn:1000006",
        "tgn:7029392"
    ],
    "tgn:id":7518494,
    "tgn:name:en":"Mackenzie, Lake",
    "tgn:placetype":[
        "aat:300008680"
    ]
},
  "bbox": [],
  "geometry": {"coordinates":[168.166667,-44.766667],"type":"Point"}
}