{
  "id": 7438665,
  "type": "Feature",
  "properties": {
    "tgn:hierarchy":[
        "tgn:7438665",
        "tgn:7005586",
        "tgn:1000001",
        "tgn:7005560",
        "tgn:7029392"
    ],
    "tgn:id":7438665,
    "tgn:name":"Tehulmixtle, Bah\u00eda de",
    "tgn:placetype":[
        "aat:300132316"
    ]
},
  "bbox": [],
  "geometry": {"coordinates":[-105.600833,20.208333],"type":"Point"}
}