{
  "id": 7323799,
  "type": "Feature",
  "properties": {
    "tgn:hierarchy":[
        "tgn:7323799",
        "tgn:7002824",
        "tgn:1000003",
        "tgn:7002786",
        "tgn:1000095",
        "tgn:7029392"
    ],
    "tgn:id":7323799,
    "tgn:name":"Rod\u00eds",
    "tgn:placetype":[
        "aat:300008347"
    ]
},
  "bbox": [],
  "geometry": {"coordinates":[-8.516667,43.15],"type":"Point"}
}