{
  "id": 7585704,
  "type": "Feature",
  "properties": {
    "tgn:hierarchy":[
        "tgn:7585704",
        "tgn:1000004",
        "tgn:7000198",
        "tgn:7000799",
        "tgn:7029392"
    ],
    "tgn:id":7585704,
    "tgn:name:en":"Burla Nariala",
    "tgn:placetype":[
        "aat:300008347"
    ]
},
  "bbox": [],
  "geometry": {"coordinates":[74.227202,33.272636],"type":"Point"}
}