{
  "id": 2668315,
  "type": "Feature",
  "properties": {
    "tgn:hierarchy":[
        "tgn:2668315",
        "tgn:1000001",
        "tgn:7012149",
        "tgn:7016020",
        "tgn:7007710",
        "tgn:7029392"
    ],
    "tgn:id":2668315,
    "tgn:name":"Slack Hollow",
    "tgn:placetype":[
        "aat:300008761"
    ]
},
  "bbox": [],
  "geometry": {"coordinates":[-78.3333,41.9333],"type":"Point"}
}