{
  "id": 7537687,
  "type": "Feature",
  "properties": {
    "tgn:hierarchy":[
        "tgn:7537687",
        "tgn:7001242",
        "tgn:7016833",
        "tgn:1001088",
        "tgn:7029392"
    ],
    "tgn:id":7537687,
    "tgn:name:en":"Naj' Shaybah",
    "tgn:placetype":[
        "aat:300008347"
    ]
},
  "bbox": [],
  "geometry": {"coordinates":[30.852828,27.829046],"type":"Point"}
}