{
  "id": 7444616,
  "type": "Feature",
  "properties": {
    "tgn:hierarchy":[
        "tgn:7444616",
        "tgn:7002443",
        "tgn:1000003",
        "tgn:7018993",
        "tgn:7008591",
        "tgn:7029392"
    ],
    "tgn:id":7444616,
    "tgn:name:en":"Cilrhedyn",
    "tgn:placetype":[
        "aat:300008347"
    ]
},
  "bbox": [],
  "geometry": {"coordinates":[-4.506389,51.984444],"type":"Point"}
}