{
  "id": 2418501,
  "type": "Feature",
  "properties": {
    "tgn:hierarchy":[
        "tgn:2418501",
        "tgn:1000001",
        "tgn:7012149",
        "tgn:2001980",
        "tgn:7007826",
        "tgn:7029392"
    ],
    "tgn:id":2418501,
    "tgn:name":"Jade Lake",
    "tgn:placetype":[
        "aat:300008680"
    ]
},
  "bbox": [],
  "geometry": {"coordinates":[-100.1667,29.7833],"type":"Point"}
}