{
  "id": 2238304,
  "type": "Feature",
  "properties": {
    "tgn:hierarchy":[
        "tgn:2238304",
        "tgn:1000001",
        "tgn:7012149",
        "tgn:1002955",
        "tgn:7007706",
        "tgn:7029392"
    ],
    "tgn:id":2238304,
    "tgn:name":"Chocolate Run",
    "tgn:placetype":[
        "aat:300008699"
    ]
},
  "bbox": [],
  "geometry": {"coordinates":[-80.85,41.2667],"type":"Point"}
}