<<<<<<< HEAD
{
  "id": 7477235,
  "type": "Feature",
  "properties": {
    "tgn:hierarchy":[
        "tgn:7477235",
        "tgn:1000004",
        "tgn:7004300",
        "tgn:1000141",
        "tgn:7029392"
    ],
    "tgn:id":7477235,
    "tgn:name":"Magong Neigang",
    "tgn:placetype":[
        "aat:300132316"
    ]
},
  "bbox": [],
  "geometry": {"coordinates":[119.573055,23.541153],"type":"Point"}
}
=======
{"geometry":{"type":"Point","coordinates":[119.573055,23.541153]},"type":"Feature","properties":{"hierarchy":["tgn:7477235","tgn:1000004","tgn:7004300","tgn:1000141","tgn:7029392"],"placetype":["aat:300132316"],"id":7477235,"name:xx":"Magong Neigang"}}
>>>>>>> 03f74aca74312dbeaf24d7e61306dd6a786dc3d0
