{
  "id": 7094334,
  "type": "Feature",
  "properties": {
    "tgn:hierarchy":[
        "tgn:7094334",
        "tgn:1000003",
        "tgn:7003676",
        "tgn:7000084",
        "tgn:7029392"
    ],
    "tgn:id":7094334,
    "tgn:name":"Seedorf",
    "tgn:placetype":[
        "aat:300008347"
    ]
},
  "bbox": [],
  "geometry": {"coordinates":[10.516667,53.083333],"type":"Point"}
}