{
  "id": 7082769,
  "type": "Feature",
  "properties": {
    "tgn:hierarchy":[
        "tgn:7082769",
        "tgn:1000003",
        "tgn:7003677",
        "tgn:7000084",
        "tgn:7029392"
    ],
    "tgn:id":7082769,
    "tgn:name":"Westerlindenfeld",
    "tgn:placetype":[
        "aat:300000206"
    ]
},
  "bbox": [],
  "geometry": {"coordinates":[9.166667,51.716667],"type":"Point"}
}