<<<<<<< HEAD
{
  "id": 7352027,
  "type": "Feature",
  "properties": {
    "tgn:hierarchy":[
        "tgn:7352027",
        "tgn:7005585",
        "tgn:1000001",
        "tgn:7005560",
        "tgn:7029392"
    ],
    "tgn:id":7352027,
    "tgn:name":"Arroz",
    "tgn:placetype":[
        "aat:300007783"
    ]
},
  "bbox": [],
  "geometry": {"coordinates":[-99.733333,18.033333],"type":"Point"}
}
=======
{"geometry":{"type":"Point","coordinates":[-99.733333,18.033333]},"type":"Feature","properties":{"hierarchy":["tgn:7352027","tgn:7005585","tgn:1000001","tgn:7005560","tgn:7029392"],"placetype":["aat:300007783"],"id":7352027,"name:xx":"Arroz"}}
>>>>>>> 03f74aca74312dbeaf24d7e61306dd6a786dc3d0
