<<<<<<< HEAD
{
  "id": 7174382,
  "type": "Feature",
  "properties": {
    "tgn:hierarchy":[
        "tgn:7174382",
        "tgn:1000003",
        "tgn:7003688",
        "tgn:7000084",
        "tgn:7029392"
    ],
    "tgn:id":7174382,
    "tgn:name":"Gro\u00dfer Kohldammer Koog",
    "tgn:placetype":[
        "aat:300006163"
    ]
},
  "bbox": [],
  "geometry": {"coordinates":[8.9,54.766667],"type":"Point"}
}
=======
{"geometry":{"type":"Point","coordinates":[8.900000,54.766667]},"type":"Feature","properties":{"hierarchy":["tgn:7174382","tgn:1000003","tgn:7003688","tgn:7000084","tgn:7029392"],"placetype":["aat:300006163"],"id":7174382,"name:xx":"Gro\u00dfer Kohldammer Koog"}}
>>>>>>> 03f74aca74312dbeaf24d7e61306dd6a786dc3d0
