{
  "id": 2192623,
  "type": "Feature",
  "properties": {
    "tgn:hierarchy":[
        "tgn:2192623",
        "tgn:1000001",
        "tgn:7012149",
        "tgn:2001247",
        "tgn:7007523",
        "tgn:7029392"
    ],
    "tgn:id":2192623,
    "tgn:name":"Branson Cave",
    "tgn:placetype":[
        "aat:300008746"
    ]
},
  "bbox": [],
  "geometry": {"coordinates":[-91.45,37.15],"type":"Point"}
}