{
  "id": 7537132,
  "type": "Feature",
  "properties": {
    "tgn:hierarchy":[
        "tgn:7537132",
        "tgn:7001242",
        "tgn:1001059",
        "tgn:7016833",
        "tgn:7029392"
    ],
    "tgn:id":7537132,
    "tgn:name":"Ma\u1e29a\u0163\u0163at Hal\u0101",
    "tgn:placetype":[
        "aat:300007783"
    ]
},
  "bbox": [],
  "geometry": {"coordinates":[31.266667,30.616667],"type":"Point"}
}