{
  "id": 1139190,
  "type": "Feature",
  "properties": {
    "tgn:hierarchy":[
        "tgn:1139190",
        "tgn:1000004",
        "tgn:7002078",
        "tgn:1000111",
        "tgn:7029392"
    ],
    "tgn:id":1139190,
    "tgn:name":"Jinkou",
    "tgn:placetype":[
        "aat:300008347"
    ]
},
  "bbox": [],
  "geometry": {"coordinates":[114.1667,30.3333],"type":"Point"}
}