{
  "id": 7413428,
  "type": "Feature",
  "properties": {
    "tgn:hierarchy":[
        "tgn:7413428",
        "tgn:1000001",
        "tgn:7005596",
        "tgn:7005560",
        "tgn:7029392"
    ],
    "tgn:id":7413428,
    "tgn:name:es":"Arroyo Ciego",
    "tgn:placetype":[
        "aat:300008347"
    ]
},
  "bbox": [],
  "geometry": {"coordinates":[-92.5875,17.604167],"type":"Point"}
}