{
  "id": 2729011,
  "type": "Feature",
  "properties": {
    "tgn:hierarchy":[
        "tgn:2729011",
        "tgn:1000001",
        "tgn:2001260",
        "tgn:7012149",
        "tgn:7007524",
        "tgn:7029392"
    ],
    "tgn:id":2729011,
    "tgn:name":"Trident Meadows",
    "tgn:placetype":[
        "aat:300008905"
    ]
},
  "bbox": [],
  "geometry": {"coordinates":[-113.1667,45.7833],"type":"Point"}
}