{
  "id": 1135894,
  "type": "Feature",
  "properties": {
    "tgn:hierarchy":[
        "tgn:1135894",
        "tgn:1000004",
        "tgn:7001069",
        "tgn:7001063",
        "tgn:1000145",
        "tgn:7029392"
    ],
    "tgn:id":1135894,
    "tgn:name":"Doi, Kinh",
    "tgn:placetype":[
        "aat:300006075"
    ]
},
  "bbox": [],
  "geometry": {"coordinates":[106.6167,10.7167],"type":"Point"}
}