<<<<<<< HEAD
{
  "id": 2253075,
  "type": "Feature",
  "properties": {
    "tgn:hierarchy":[
        "tgn:2253075",
        "tgn:1000001",
        "tgn:7012149",
        "tgn:2002348",
        "tgn:7007922",
        "tgn:7029392"
    ],
    "tgn:id":2253075,
    "tgn:name":"Constellation Lake",
    "tgn:placetype":[
        "aat:300008680"
    ]
},
  "bbox": [],
  "geometry": {"coordinates":[-90.6667,45.8167],"type":"Point"}
}
=======
{"geometry":{"type":"Point","coordinates":[-90.666700,45.816700]},"type":"Feature","properties":{"hierarchy":["tgn:2253075","tgn:1000001","tgn:7012149","tgn:2002348","tgn:7007922","tgn:7029392"],"placetype":["aat:300008680"],"id":2253075,"name:xx":"Constellation Lake"}}
>>>>>>> 03f74aca74312dbeaf24d7e61306dd6a786dc3d0
