{
  "id": 2253075,
  "type": "Feature",
  "properties": {
    "tgn:hierarchy":[
        "tgn:2253075",
        "tgn:1000001",
        "tgn:7012149",
        "tgn:2002348",
        "tgn:7007922",
        "tgn:7029392"
    ],
    "tgn:id":2253075,
    "tgn:name":"Constellation Lake",
    "tgn:placetype":[
        "aat:300008680"
    ]
},
  "bbox": [],
  "geometry": {"coordinates":[-90.6667,45.8167],"type":"Point"}
}