{
  "id": 2483599,
  "type": "Feature",
  "properties": {
    "tgn:hierarchy":[
        "tgn:2483599",
        "tgn:1000001",
        "tgn:7012149",
        "tgn:2001201",
        "tgn:7007523",
        "tgn:7029392"
    ],
    "tgn:id":2483599,
    "tgn:name":"Latchel Branch",
    "tgn:placetype":[
        "aat:300008699"
    ]
},
  "bbox": [],
  "geometry": {"coordinates":[-94.1167,40.1833],"type":"Point"}
}