<<<<<<< HEAD
{
  "id": 2339191,
  "type": "Feature",
  "properties": {
    "tgn:hierarchy":[
        "tgn:2339191",
        "tgn:1000001",
        "tgn:7006451",
        "tgn:2000092",
        "tgn:7012149",
        "tgn:7029392"
    ],
    "tgn:id":2339191,
    "tgn:name":"Franks Reservoir",
    "tgn:placetype":[
        "aat:300006191"
    ]
},
  "bbox": [],
  "geometry": {"coordinates":[-112.15,36.9167],"type":"Point"}
}
=======
{"geometry":{"type":"Point","coordinates":[-112.150000,36.916700]},"type":"Feature","properties":{"hierarchy":["tgn:2339191","tgn:1000001","tgn:7006451","tgn:2000092","tgn:7012149","tgn:7029392"],"placetype":["aat:300006191"],"id":2339191,"name:xx":"Franks Reservoir"}}
>>>>>>> 03f74aca74312dbeaf24d7e61306dd6a786dc3d0
