{
  "id": 2339191,
  "type": "Feature",
  "properties": {
    "tgn:hierarchy":[
        "tgn:2339191",
        "tgn:1000001",
        "tgn:7006451",
        "tgn:2000092",
        "tgn:7012149",
        "tgn:7029392"
    ],
    "tgn:id":2339191,
    "tgn:name":"Franks Reservoir",
    "tgn:placetype":[
        "aat:300006191"
    ]
},
  "bbox": [],
  "geometry": {"coordinates":[-112.15,36.9167],"type":"Point"}
}