{
  "id": 7177654,
  "type": "Feature",
  "properties": {
    "tgn:hierarchy":[
        "tgn:7177654",
        "tgn:1000003",
        "tgn:7003678",
        "tgn:7000084",
        "tgn:7029392"
    ],
    "tgn:id":7177654,
    "tgn:name":"Hagen",
    "tgn:placetype":[
        "aat:300008777"
    ]
},
  "bbox": [],
  "geometry": {"coordinates":[8.716667,51.35],"type":"Point"}
}