{
  "id": 2701031,
  "type": "Feature",
  "properties": {
    "tgn:hierarchy":[
        "tgn:2701031",
        "tgn:1000001",
        "tgn:7012149",
        "tgn:1002883",
        "tgn:7007706",
        "tgn:7029392"
    ],
    "tgn:id":2701031,
    "tgn:name":"Sugar Creek",
    "tgn:placetype":[
        "aat:300008706"
    ]
},
  "bbox": [],
  "geometry": {"coordinates":[-83.0167,41.15],"type":"Point"}
}