{
  "id": 2324661,
  "type": "Feature",
  "properties": {
    "tgn:hierarchy":[
        "tgn:2324661",
        "tgn:1000001",
        "tgn:7012149",
        "tgn:7007708",
        "tgn:7029392"
    ],
    "tgn:id":2324661,
    "tgn:name":"Fendall Creek",
    "tgn:placetype":[
        "aat:300008706"
    ]
},
  "bbox": [],
  "geometry": {"coordinates":[-123.7667,44.2833],"type":"Point"}
}