{
  "id": 1008163,
  "type": "Feature",
  "properties": {
    "tgn:hierarchy":[
        "tgn:1008163",
        "tgn:7001559",
        "tgn:1000004",
        "tgn:7000198",
        "tgn:1001890",
        "tgn:7029392"
    ],
    "tgn:id":1008163,
    "tgn:name:en":"Minicoy Island",
    "tgn:placetype":[
        "aat:300008791"
    ]
},
  "bbox": [],
  "geometry": {"coordinates":[73.0167,8.4833],"type":"Point"}
}