{
  "id": 2002900,
  "type": "Feature",
  "properties": {
    "tgn:hierarchy":[
        "tgn:2002900",
        "tgn:7002659",
        "tgn:1000001",
        "tgn:7012149",
        "tgn:2000062",
        "tgn:7029392"
    ],
    "tgn:id":2002900,
    "tgn:name":"Brookwood",
    "tgn:placetype":[
        "aat:300008347"
    ]
},
  "bbox": [],
  "geometry": {"coordinates":[-87.3167,33.25],"type":"Point"}
}