{
  "id": 7468709,
  "type": "Feature",
  "properties": {
    "tgn:hierarchy":[
        "tgn:7468709",
        "tgn:1000957",
        "tgn:1000004",
        "tgn:1000141",
        "tgn:7029392"
    ],
    "tgn:id":7468709,
    "tgn:name":"Xinshan",
    "tgn:placetype":[
        "aat:300008347"
    ]
},
  "bbox": [],
  "geometry": {"coordinates":[121.699944,25.12552],"type":"Point"}
}