<<<<<<< HEAD
{
  "id": 2769005,
  "type": "Feature",
  "properties": {
    "tgn:hierarchy":[
        "tgn:2769005",
        "tgn:1000001",
        "tgn:7012149",
        "tgn:1002993",
        "tgn:7007568",
        "tgn:7029392"
    ],
    "tgn:id":2769005,
    "tgn:name":"Whittaker Brook",
    "tgn:placetype":[
        "aat:300008699"
    ]
},
  "bbox": [],
  "geometry": {"coordinates":[-73.4333,43.1833],"type":"Point"}
}
=======
{"geometry":{"type":"Point","coordinates":[-73.433300,43.183300]},"type":"Feature","properties":{"hierarchy":["tgn:2769005","tgn:1000001","tgn:7012149","tgn:1002993","tgn:7007568","tgn:7029392"],"placetype":["aat:300008699"],"id":2769005,"name:xx":"Whittaker Brook"}}
>>>>>>> 03f74aca74312dbeaf24d7e61306dd6a786dc3d0
