{
  "id": 7588622,
  "type": "Feature",
  "properties": {
    "tgn:hierarchy":[
        "tgn:7588622",
        "tgn:1000004",
        "tgn:7000198",
        "tgn:1001894",
        "tgn:7029392"
    ],
    "tgn:id":7588622,
    "tgn:name:en":"Luktara",
    "tgn:placetype":[
        "aat:300008347"
    ]
},
  "bbox": [],
  "geometry": {"coordinates":[80.321923,25.610775],"type":"Point"}
}