{
  "id": 2311077,
  "type": "Feature",
  "properties": {
    "tgn:hierarchy":[
        "tgn:2311077",
        "tgn:7014201",
        "tgn:1000001",
        "tgn:7012149",
        "tgn:7007239",
        "tgn:7029392"
    ],
    "tgn:id":2311077,
    "tgn:name":"Edenridge",
    "tgn:placetype":[
        "aat:300008347"
    ]
},
  "bbox": [],
  "geometry": {"coordinates":[-75.55,39.7833],"type":"Point"}
}