{
  "id": 7418017,
  "type": "Feature",
  "properties": {
    "tgn:hierarchy":[
        "tgn:7418017",
        "tgn:1000001",
        "tgn:7005591",
        "tgn:7005560",
        "tgn:7029392"
    ],
    "tgn:id":7418017,
    "tgn:name:es":"Loma Atravesada",
    "tgn:placetype":[
        "aat:300008347"
    ]
},
  "bbox": [],
  "geometry": {"coordinates":[-95.499444,16.1875],"type":"Point"}
}