{
  "id": 2394076,
  "type": "Feature",
  "properties": {
    "tgn:hierarchy":[
        "tgn:2394076",
        "tgn:1000001",
        "tgn:7012149",
        "tgn:2000806",
        "tgn:7007255",
        "tgn:7029392"
    ],
    "tgn:id":2394076,
    "tgn:name":"Hog Wallow Hollow",
    "tgn:placetype":[
        "aat:300008761"
    ]
},
  "bbox": [],
  "geometry": {"coordinates":[-83.75,36.9667],"type":"Point"}
}