{
  "id": 7437241,
  "type": "Feature",
  "properties": {
    "tgn:hierarchy":[
        "tgn:7437241",
        "tgn:1000001",
        "tgn:7005591",
        "tgn:7005560",
        "tgn:7029392"
    ],
    "tgn:id":7437241,
    "tgn:name":"Santiago Lalopa",
    "tgn:placetype":[
        "aat:300008347"
    ]
},
  "bbox": [],
  "geometry": {"coordinates":[-96.25,17.416667],"type":"Point"}
}