{
  "id": 1084253,
  "type": "Feature",
  "properties": {
    "tgn:hierarchy":[
        "tgn:1084253",
        "tgn:1000004",
        "tgn:1001448",
        "tgn:1000135",
        "tgn:7029392"
    ],
    "tgn:id":1084253,
    "tgn:name":"Hinigaran",
    "tgn:placetype":[
        "aat:300008347"
    ]
},
  "bbox": [],
  "geometry": {"coordinates":[122.8333,10.2667],"type":"Point"}
}