{
  "id": 7489164,
  "type": "Feature",
  "properties": {
    "tgn:hierarchy":[
        "tgn:7489164",
        "tgn:7001004",
        "tgn:1000004",
        "tgn:1000141",
        "tgn:7029392"
    ],
    "tgn:id":7489164,
    "tgn:name":"Gongguan",
    "tgn:placetype":[
        "aat:300008347"
    ]
},
  "bbox": [],
  "geometry": {"coordinates":[120.506944,22.948889],"type":"Point"}
}