<<<<<<< HEAD
{
  "id": 7378766,
  "type": "Feature",
  "properties": {
    "tgn:hierarchy":[
        "tgn:7378766",
        "tgn:1000001",
        "tgn:7005593",
        "tgn:7005560",
        "tgn:7029392"
    ],
    "tgn:id":7378766,
    "tgn:name":"Los Pozos",
    "tgn:placetype":[
        "aat:300008347"
    ]
},
  "bbox": [],
  "geometry": {"coordinates":[-99.566667,20.916667],"type":"Point"}
}
=======
{"geometry":{"type":"Point","coordinates":[-99.566667,20.916667]},"type":"Feature","properties":{"hierarchy":["tgn:7378766","tgn:1000001","tgn:7005593","tgn:7005560","tgn:7029392"],"placetype":["aat:300008347"],"id":7378766,"name:xx":"Los Pozos"}}
>>>>>>> 03f74aca74312dbeaf24d7e61306dd6a786dc3d0
