{
  "id": 7378766,
  "type": "Feature",
  "properties": {
    "tgn:hierarchy":[
        "tgn:7378766",
        "tgn:1000001",
        "tgn:7005593",
        "tgn:7005560",
        "tgn:7029392"
    ],
    "tgn:id":7378766,
    "tgn:name":"Los Pozos",
    "tgn:placetype":[
        "aat:300008347"
    ]
},
  "bbox": [],
  "geometry": {"coordinates":[-99.566667,20.916667],"type":"Point"}
}