{
  "id": 7422032,
  "type": "Feature",
  "properties": {
    "tgn:hierarchy":[
        "tgn:7422032",
        "tgn:1000001",
        "tgn:1001960",
        "tgn:7005560",
        "tgn:7029392"
    ],
    "tgn:id":7422032,
    "tgn:name":"Norte, Boca",
    "tgn:placetype":[
        "aat:300266559"
    ]
},
  "bbox": [],
  "geometry": {"coordinates":[-110.05,27.083333],"type":"Point"}
}