<<<<<<< HEAD
{
  "id": 2255261,
  "type": "Feature",
  "properties": {
    "tgn:hierarchy":[
        "tgn:2255261",
        "tgn:1000001",
        "tgn:7012149",
        "tgn:1002679",
        "tgn:7007520",
        "tgn:7029392"
    ],
    "tgn:id":2255261,
    "tgn:name":"Cooper Snell And Ansel Drain",
    "tgn:placetype":[
        "aat:300008699"
    ]
},
  "bbox": [],
  "geometry": {"coordinates":[-83.6167,41.85],"type":"Point"}
}
=======
{"geometry":{"type":"Point","coordinates":[-83.616700,41.850000]},"type":"Feature","properties":{"hierarchy":["tgn:2255261","tgn:1000001","tgn:7012149","tgn:1002679","tgn:7007520","tgn:7029392"],"placetype":["aat:300008699"],"id":2255261,"name:xx":"Cooper Snell And Ansel Drain"}}
>>>>>>> 03f74aca74312dbeaf24d7e61306dd6a786dc3d0
