{
  "id": 7344525,
  "type": "Feature",
  "properties": {
    "tgn:hierarchy":[
        "tgn:7344525",
        "tgn:7002826",
        "tgn:7001158",
        "tgn:1000003",
        "tgn:1000095",
        "tgn:7029392"
    ],
    "tgn:id":7344525,
    "tgn:name":"Antimio de Arriba",
    "tgn:placetype":[
        "aat:300008347"
    ]
},
  "bbox": [],
  "geometry": {"coordinates":[-5.65,42.516667],"type":"Point"}
}