{
  "id": 7575804,
  "type": "Feature",
  "properties": {
    "tgn:hierarchy":[
        "tgn:7575804",
        "tgn:1000004",
        "tgn:7000198",
        "tgn:7016722",
        "tgn:7029392"
    ],
    "tgn:id":7575804,
    "tgn:name:en":"Khair\u0101garh",
    "tgn:placetype":[
        "aat:300008347"
    ]
},
  "bbox": [],
  "geometry": {"coordinates":[77.818898,26.942691],"type":"Point"}
}