{
  "id": 2379016,
  "type": "Feature",
  "properties": {
    "tgn:hierarchy":[
        "tgn:2379016",
        "tgn:1000001",
        "tgn:7016172",
        "tgn:7012149",
        "tgn:2000161",
        "tgn:7029392"
    ],
    "tgn:id":2379016,
    "tgn:name":"Hartley",
    "tgn:placetype":[
        "aat:300008347"
    ]
},
  "bbox": [],
  "geometry": {"coordinates":[-94.1667,34.3667],"type":"Point"}
}