{
  "id": 2339389,
  "type": "Feature",
  "properties": {
    "tgn:hierarchy":[
        "tgn:2339389",
        "tgn:1000001",
        "tgn:7012149",
        "tgn:2001284",
        "tgn:7007524",
        "tgn:7029392"
    ],
    "tgn:id":2339389,
    "tgn:name":"Frazier Creek",
    "tgn:placetype":[
        "aat:300008706"
    ]
},
  "bbox": [],
  "geometry": {"coordinates":[-111.8167,46.9833],"type":"Point"}
}