<<<<<<< HEAD
{
  "id": 2339389,
  "type": "Feature",
  "properties": {
    "tgn:hierarchy":[
        "tgn:2339389",
        "tgn:1000001",
        "tgn:7012149",
        "tgn:2001284",
        "tgn:7007524",
        "tgn:7029392"
    ],
    "tgn:id":2339389,
    "tgn:name":"Frazier Creek",
    "tgn:placetype":[
        "aat:300008706"
    ]
},
  "bbox": [],
  "geometry": {"coordinates":[-111.8167,46.9833],"type":"Point"}
}
=======
{"geometry":{"type":"Point","coordinates":[-111.816700,46.983300]},"type":"Feature","properties":{"hierarchy":["tgn:2339389","tgn:1000001","tgn:7012149","tgn:2001284","tgn:7007524","tgn:7029392"],"placetype":["aat:300008706"],"id":2339389,"name:xx":"Frazier Creek"}}
>>>>>>> 03f74aca74312dbeaf24d7e61306dd6a786dc3d0
