<<<<<<< HEAD
{
  "id": 2332615,
  "type": "Feature",
  "properties": {
    "tgn:hierarchy":[
        "tgn:2332615",
        "tgn:1000001",
        "tgn:7012149",
        "tgn:2001032",
        "tgn:7007521",
        "tgn:7029392"
    ],
    "tgn:id":2332615,
    "tgn:name":"Florida, Lake",
    "tgn:placetype":[
        "aat:300008680"
    ]
},
  "bbox": [],
  "geometry": {"coordinates":[-95.05,45.25],"type":"Point"}
}
=======
{"geometry":{"type":"Point","coordinates":[-95.050000,45.250000]},"type":"Feature","properties":{"hierarchy":["tgn:2332615","tgn:1000001","tgn:7012149","tgn:2001032","tgn:7007521","tgn:7029392"],"placetype":["aat:300008680"],"id":2332615,"name:xx":"Florida, Lake"}}
>>>>>>> 03f74aca74312dbeaf24d7e61306dd6a786dc3d0
