{
  "id": 2766409,
  "type": "Feature",
  "properties": {
    "tgn:hierarchy":[
        "tgn:2766409",
        "tgn:7002659",
        "tgn:1000001",
        "tgn:7012149",
        "tgn:2000029",
        "tgn:7029392"
    ],
    "tgn:id":2766409,
    "tgn:name":"White Oak",
    "tgn:placetype":[
        "aat:300008347"
    ]
},
  "bbox": [],
  "geometry": {"coordinates":[-87.9833,34.5333],"type":"Point"}
}