{
  "id": 2644542,
  "type": "Feature",
  "properties": {
    "tgn:hierarchy":[
        "tgn:2644542",
        "tgn:1000001",
        "tgn:7012149",
        "tgn:2001277",
        "tgn:7007524",
        "tgn:7029392"
    ],
    "tgn:id":2644542,
    "tgn:name":"Sarcee Mountain",
    "tgn:placetype":[
        "aat:300008798"
    ]
},
  "bbox": [],
  "geometry": {"coordinates":[-113.7833,48.9833],"type":"Point"}
}