<<<<<<< HEAD
{
  "id": 7476841,
  "type": "Feature",
  "properties": {
    "tgn:hierarchy":[
        "tgn:7476841",
        "tgn:7488858",
        "tgn:1000004",
        "tgn:1000141",
        "tgn:7029392"
    ],
    "tgn:id":7476841,
    "tgn:name":"Dishi'er Gongmu",
    "tgn:placetype":[
        "aat:300266755"
    ]
},
  "bbox": [],
  "geometry": {"coordinates":[120.930078,23.897226],"type":"Point"}
}
=======
{"geometry":{"type":"Point","coordinates":[120.930078,23.897226]},"type":"Feature","properties":{"hierarchy":["tgn:7476841","tgn:7488858","tgn:1000004","tgn:1000141","tgn:7029392"],"placetype":["aat:300266755"],"id":7476841,"name:xx":"Dishi'er Gongmu"}}
>>>>>>> 03f74aca74312dbeaf24d7e61306dd6a786dc3d0
