{
  "id": 2075284,
  "type": "Feature",
  "properties": {
    "tgn:hierarchy":[
        "tgn:2075284",
        "tgn:1000001",
        "tgn:2001485",
        "tgn:7012149",
        "tgn:7007709",
        "tgn:7029392"
    ],
    "tgn:id":2075284,
    "tgn:name":"Jonesboro Crossing",
    "tgn:placetype":[
        "aat:300008347",
        "aat:300387210"
    ]
},
  "bbox": [],
  "geometry": {"coordinates":[-78.6167,34.3167],"type":"Point"}
}