{
  "id": 2152965,
  "type": "Feature",
  "properties": {
    "tgn:hierarchy":[
        "tgn:2152965",
        "tgn:1000001",
        "tgn:7012149",
        "tgn:2001716",
        "tgn:7007708",
        "tgn:7029392"
    ],
    "tgn:id":2152965,
    "tgn:name":"Beach Mountain",
    "tgn:placetype":[
        "aat:300008798"
    ]
},
  "bbox": [],
  "geometry": {"coordinates":[-122.2833,43.6667],"type":"Point"}
}