<<<<<<< HEAD
{
  "id": 2152965,
  "type": "Feature",
  "properties": {
    "tgn:hierarchy":[
        "tgn:2152965",
        "tgn:1000001",
        "tgn:7012149",
        "tgn:2001716",
        "tgn:7007708",
        "tgn:7029392"
    ],
    "tgn:id":2152965,
    "tgn:name":"Beach Mountain",
    "tgn:placetype":[
        "aat:300008798"
    ]
},
  "bbox": [],
  "geometry": {"coordinates":[-122.2833,43.6667],"type":"Point"}
}
=======
{"geometry":{"type":"Point","coordinates":[-122.283300,43.666700]},"type":"Feature","properties":{"hierarchy":["tgn:2152965","tgn:1000001","tgn:7012149","tgn:2001716","tgn:7007708","tgn:7029392"],"placetype":["aat:300008798"],"id":2152965,"name:xx":"Beach Mountain"}}
>>>>>>> 03f74aca74312dbeaf24d7e61306dd6a786dc3d0
