{
  "id": 2612311,
  "type": "Feature",
  "properties": {
    "tgn:hierarchy":[
        "tgn:2612311",
        "tgn:1000001",
        "tgn:2001484",
        "tgn:7012149",
        "tgn:7007709",
        "tgn:7029392"
    ],
    "tgn:id":2612311,
    "tgn:name":"Red Spur",
    "tgn:placetype":[
        "aat:300266640"
    ]
},
  "bbox": [],
  "geometry": {"coordinates":[-81.6667,35.55],"type":"Point"}
}