{
  "id": 7159073,
  "type": "Feature",
  "properties": {
    "tgn:hierarchy":[
        "tgn:7159073",
        "tgn:1000003",
        "tgn:7003678",
        "tgn:7000084",
        "tgn:7029392"
    ],
    "tgn:id":7159073,
    "tgn:name":"Holzh\u00e4user-Berg",
    "tgn:placetype":[
        "aat:300008777"
    ]
},
  "bbox": [],
  "geometry": {"coordinates":[8.983333,51.316667],"type":"Point"}
}