{
  "id": 7475646,
  "type": "Feature",
  "properties": {
    "tgn:hierarchy":[
        "tgn:7475646",
        "tgn:1000004",
        "tgn:7467799",
        "tgn:1000141",
        "tgn:7029392"
    ],
    "tgn:id":7475646,
    "tgn:name":"Ershui Tifang",
    "tgn:placetype":[
        "aat:300006156"
    ]
},
  "bbox": [],
  "geometry": {"coordinates":[120.61,23.8128],"type":"Point"}
}