<<<<<<< HEAD
{
  "id": 7475646,
  "type": "Feature",
  "properties": {
    "tgn:hierarchy":[
        "tgn:7475646",
        "tgn:1000004",
        "tgn:7467799",
        "tgn:1000141",
        "tgn:7029392"
    ],
    "tgn:id":7475646,
    "tgn:name":"Ershui Tifang",
    "tgn:placetype":[
        "aat:300006156"
    ]
},
  "bbox": [],
  "geometry": {"coordinates":[120.61,23.8128],"type":"Point"}
}
=======
{"geometry":{"type":"Point","coordinates":[120.610000,23.812800]},"type":"Feature","properties":{"hierarchy":["tgn:7475646","tgn:1000004","tgn:7467799","tgn:1000141","tgn:7029392"],"placetype":["aat:300006156"],"id":7475646,"name:xx":"Ershui Tifang"}}
>>>>>>> 03f74aca74312dbeaf24d7e61306dd6a786dc3d0
