{
  "id": 2132227,
  "type": "Feature",
  "properties": {
    "tgn:hierarchy":[
        "tgn:2132227",
        "tgn:1000001",
        "tgn:2000924",
        "tgn:7012149",
        "tgn:7007515",
        "tgn:7029392"
    ],
    "tgn:id":2132227,
    "tgn:name":"Ames Knob",
    "tgn:placetype":[
        "aat:300008798"
    ]
},
  "bbox": [],
  "geometry": {"coordinates":[-68.8833,44.1333],"type":"Point"}
}