{
  "id": 7579728,
  "type": "Feature",
  "properties": {
    "tgn:hierarchy":[
        "tgn:7579728",
        "tgn:1000004",
        "tgn:7000198",
        "tgn:1003539",
        "tgn:7029392"
    ],
    "tgn:id":7579728,
    "tgn:name:en":"Songsak",
    "tgn:placetype":[
        "aat:300008347"
    ]
},
  "bbox": [],
  "geometry": {"coordinates":[90.611651,25.643162],"type":"Point"}
}