{
  "id": 2119674,
  "type": "Feature",
  "properties": {
    "tgn:hierarchy":[
        "tgn:2119674",
        "tgn:1000001",
        "tgn:7012149",
        "tgn:2002299",
        "tgn:7013961",
        "tgn:7029392"
    ],
    "tgn:id":2119674,
    "tgn:name":"Quaker",
    "tgn:placetype":[
        "aat:300008347",
        "aat:300387210"
    ]
},
  "bbox": [],
  "geometry": {"coordinates":[-82.4167,38.05],"type":"Point"}
}