{
  "id": 7149399,
  "type": "Feature",
  "properties": {
    "tgn:hierarchy":[
        "tgn:7149399",
        "tgn:1000003",
        "tgn:7003684",
        "tgn:7000084",
        "tgn:7029392"
    ],
    "tgn:id":7149399,
    "tgn:name":"Krehberg",
    "tgn:placetype":[
        "aat:300008777"
    ]
},
  "bbox": [],
  "geometry": {"coordinates":[7.166667,49.183333],"type":"Point"}
}