{
  "id": 2145660,
  "type": "Feature",
  "properties": {
    "tgn:hierarchy":[
        "tgn:2145660",
        "tgn:1000001",
        "tgn:7012149",
        "tgn:2000980",
        "tgn:7007520",
        "tgn:7029392"
    ],
    "tgn:id":2145660,
    "tgn:name":"Baldy",
    "tgn:placetype":[
        "aat:300008798"
    ]
},
  "bbox": [],
  "geometry": {"coordinates":[-85.0333,44.4833],"type":"Point"}
}