<<<<<<< HEAD
{
  "id": 7023750,
  "type": "Feature",
  "properties": {
    "tgn:hierarchy":[
        "tgn:7023750",
        "tgn:1000001",
        "tgn:7012149",
        "tgn:7007827",
        "tgn:7029392"
    ],
    "tgn:id":7023750,
    "tgn:name":"Three Fords Canyon",
    "tgn:placetype":[
        "aat:300008761"
    ]
},
  "bbox": [],
  "geometry": {"coordinates":[-109.95,39.3],"type":"Point"}
}
=======
{"geometry":{"type":"Point","coordinates":[-109.950000,39.300000]},"type":"Feature","properties":{"hierarchy":["tgn:7023750","tgn:1000001","tgn:7012149","tgn:7007827","tgn:7029392"],"placetype":["aat:300008761"],"id":7023750,"name:xx":"Three Fords Canyon"}}
>>>>>>> 03f74aca74312dbeaf24d7e61306dd6a786dc3d0
