{
  "id": 2727401,
  "type": "Feature",
  "properties": {
    "tgn:hierarchy":[
        "tgn:2727401",
        "tgn:1000001",
        "tgn:2001431",
        "tgn:7012149",
        "tgn:7007566",
        "tgn:7029392"
    ],
    "tgn:id":2727401,
    "tgn:name":"Trail Canyon",
    "tgn:placetype":[
        "aat:300008761"
    ]
},
  "bbox": [],
  "geometry": {"coordinates":[-108.0833,35.1167],"type":"Point"}
}