{
  "id": 2628823,
  "type": "Feature",
  "properties": {
    "tgn:hierarchy":[
        "tgn:2628823",
        "tgn:1000001",
        "tgn:7006451",
        "tgn:7012149",
        "tgn:2000102",
        "tgn:7029392"
    ],
    "tgn:id":2628823,
    "tgn:name":"Rosario Mine",
    "tgn:placetype":[
        "aat:300000390"
    ]
},
  "bbox": [],
  "geometry": {"coordinates":[-110.8333,31.5833],"type":"Point"}
}