{
  "id": 1138933,
  "type": "Feature",
  "properties": {
    "tgn:hierarchy":[
        "tgn:1138933",
        "tgn:1000004",
        "tgn:7002077",
        "tgn:1000111",
        "tgn:7029392"
    ],
    "tgn:id":1138933,
    "tgn:name":"Duji",
    "tgn:placetype":[
        "aat:300008347"
    ]
},
  "bbox": [],
  "geometry": {"coordinates":[116.95,37.7167],"type":"Point"}
}