{
  "id": 7404280,
  "type": "Feature",
  "properties": {
    "tgn:hierarchy":[
        "tgn:7404280",
        "tgn:7016644",
        "tgn:1000001",
        "tgn:7005560",
        "tgn:7029392"
    ],
    "tgn:id":7404280,
    "tgn:name":"El Carmen",
    "tgn:placetype":[
        "aat:300008347"
    ]
},
  "bbox": [],
  "geometry": {"coordinates":[-103.825,18.783333],"type":"Point"}
}