<<<<<<< HEAD
{
  "id": 2760470,
  "type": "Feature",
  "properties": {
    "tgn:hierarchy":[
        "tgn:2760470",
        "tgn:1000001",
        "tgn:7012149",
        "tgn:2001304",
        "tgn:7007524",
        "tgn:7029392"
    ],
    "tgn:id":2760470,
    "tgn:name":"West Fork Swamp Creek",
    "tgn:placetype":[
        "aat:300008706"
    ]
},
  "bbox": [],
  "geometry": {"coordinates":[-115.15,47.4333],"type":"Point"}
}
=======
{"geometry":{"type":"Point","coordinates":[-115.150000,47.433300]},"type":"Feature","properties":{"hierarchy":["tgn:2760470","tgn:1000001","tgn:7012149","tgn:2001304","tgn:7007524","tgn:7029392"],"placetype":["aat:300008706"],"id":2760470,"name:xx":"West Fork Swamp Creek"}}
>>>>>>> 03f74aca74312dbeaf24d7e61306dd6a786dc3d0
