{
  "id": 2077867,
  "type": "Feature",
  "properties": {
    "tgn:hierarchy":[
        "tgn:2077867",
        "tgn:2001566",
        "tgn:1000001",
        "tgn:7012149",
        "tgn:7007705",
        "tgn:7029392"
    ],
    "tgn:id":2077867,
    "tgn:name":"Munich",
    "tgn:placetype":[
        "aat:300008347"
    ]
},
  "bbox": [],
  "geometry": {"coordinates":[-98.8333,48.6667],"type":"Point"}
}