{
  "id": 7060142,
  "type": "Feature",
  "properties": {
    "tgn:hierarchy":[
        "tgn:7060142",
        "tgn:1000003",
        "tgn:7000094",
        "tgn:7000084",
        "tgn:7029392"
    ],
    "tgn:id":7060142,
    "tgn:name":"Altenhagener Bach",
    "tgn:placetype":[
        "aat:300008699"
    ]
},
  "bbox": [],
  "geometry": {"coordinates":[11.683333,54.033333],"type":"Point"}
}