{
  "id": 1075695,
  "type": "Feature",
  "properties": {
    "tgn:hierarchy":[
        "tgn:1075695",
        "tgn:1000004",
        "tgn:7000198",
        "tgn:1001977",
        "tgn:7029392"
    ],
    "tgn:id":1075695,
    "tgn:name:en":"K\u0101simpur",
    "tgn:placetype":[
        "aat:300008347"
    ]
},
  "bbox": [],
  "geometry": {"coordinates":[88.525833,22.7625],"type":"Point"}
}