<<<<<<< HEAD
{
  "id": 2337583,
  "type": "Feature",
  "properties": {
    "tgn:hierarchy":[
        "tgn:2337583",
        "tgn:7002659",
        "tgn:1000001",
        "tgn:2000015",
        "tgn:7012149",
        "tgn:7029392"
    ],
    "tgn:id":2337583,
    "tgn:name":"Fox Branch",
    "tgn:placetype":[
        "aat:300008699"
    ]
},
  "bbox": [],
  "geometry": {"coordinates":[-86.0167,31.3833],"type":"Point"}
}
=======
{"geometry":{"type":"Point","coordinates":[-86.016700,31.383300]},"type":"Feature","properties":{"hierarchy":["tgn:2337583","tgn:7002659","tgn:1000001","tgn:2000015","tgn:7012149","tgn:7029392"],"placetype":["aat:300008699"],"id":2337583,"name:xx":"Fox Branch"}}
>>>>>>> 03f74aca74312dbeaf24d7e61306dd6a786dc3d0
