{
  "id": 2385609,
  "type": "Feature",
  "properties": {
    "tgn:hierarchy":[
        "tgn:2385609",
        "tgn:1000001",
        "tgn:7012149",
        "tgn:1002519",
        "tgn:7007706",
        "tgn:7029392"
    ],
    "tgn:id":2385609,
    "tgn:name":"Henderson Run",
    "tgn:placetype":[
        "aat:300008699"
    ]
},
  "bbox": [],
  "geometry": {"coordinates":[-80.8167,40.2833],"type":"Point"}
}