{
  "id": 7566594,
  "type": "Feature",
  "properties": {
    "tgn:hierarchy":[
        "tgn:7566594",
        "tgn:1000004",
        "tgn:1001832",
        "tgn:7000198",
        "tgn:7029392"
    ],
    "tgn:id":7566594,
    "tgn:name:en":"Alakjh\u0101ri Pah\u0101r",
    "tgn:placetype":[
        "aat:300008795"
    ]
},
  "bbox": [],
  "geometry": {"coordinates":[89.863973,26.251677],"type":"Point"}
}