{
  "id": 2707550,
  "type": "Feature",
  "properties": {
    "tgn:hierarchy":[
        "tgn:2707550",
        "tgn:1000001",
        "tgn:2001799",
        "tgn:7012149",
        "tgn:7007713",
        "tgn:7029392"
    ],
    "tgn:id":2707550,
    "tgn:name":"Sweetland",
    "tgn:placetype":[
        "aat:300008347"
    ]
},
  "bbox": [],
  "geometry": {"coordinates":[-98.9833,44.3333],"type":"Point"}
}