<<<<<<< HEAD
{
  "id": 7484160,
  "type": "Feature",
  "properties": {
    "tgn:hierarchy":[
        "tgn:7484160",
        "tgn:1000004",
        "tgn:7490934",
        "tgn:1000141",
        "tgn:7029392"
    ],
    "tgn:id":7484160,
    "tgn:name":"Xiaqiedong Qiao",
    "tgn:placetype":[
        "aat:300007836"
    ]
},
  "bbox": [],
  "geometry": {"coordinates":[120.365556,23.353056],"type":"Point"}
}
=======
{"geometry":{"type":"Point","coordinates":[120.365556,23.353056]},"type":"Feature","properties":{"hierarchy":["tgn:7484160","tgn:1000004","tgn:7490934","tgn:1000141","tgn:7029392"],"placetype":["aat:300007836"],"id":7484160,"name:xx":"Xiaqiedong Qiao"}}
>>>>>>> 03f74aca74312dbeaf24d7e61306dd6a786dc3d0
