{
  "id": 2574330,
  "type": "Feature",
  "properties": {
    "tgn:hierarchy":[
        "tgn:2574330",
        "tgn:1000001",
        "tgn:1002479",
        "tgn:7012149",
        "tgn:7007240",
        "tgn:7029392"
    ],
    "tgn:id":2574330,
    "tgn:name":"Pelican Cove",
    "tgn:placetype":[
        "aat:300132316"
    ]
},
  "bbox": [],
  "geometry": {"coordinates":[-82.4667,27.7333],"type":"Point"}
}