{
  "id": 1093354,
  "type": "Feature",
  "properties": {
    "tgn:hierarchy":[
        "tgn:1093354",
        "tgn:7001242",
        "tgn:7017574",
        "tgn:1000193",
        "tgn:7029392"
    ],
    "tgn:id":1093354,
    "tgn:name":"Marble Hall",
    "tgn:placetype":[
        "aat:300008347"
    ]
},
  "bbox": [],
  "geometry": {"coordinates":[29.29,-24.95],"type":"Point"}
}