{
  "id": 2774347,
  "type": "Feature",
  "properties": {
    "tgn:hierarchy":[
        "tgn:2774347",
        "tgn:1000001",
        "tgn:7012149",
        "tgn:2002029",
        "tgn:7007826",
        "tgn:7029392"
    ],
    "tgn:id":2774347,
    "tgn:name":"Willow Hollow Tank",
    "tgn:placetype":[
        "aat:300006191"
    ]
},
  "bbox": [],
  "geometry": {"coordinates":[-98.2833,28.5333],"type":"Point"}
}