{
  "id": 2420459,
  "type": "Feature",
  "properties": {
    "tgn:hierarchy":[
        "tgn:2420459",
        "tgn:1000001",
        "tgn:7012149",
        "tgn:2001144",
        "tgn:7007522",
        "tgn:7029392"
    ],
    "tgn:id":2420459,
    "tgn:name":"Jenkins Creek",
    "tgn:placetype":[
        "aat:300008706"
    ]
},
  "bbox": [],
  "geometry": {"coordinates":[-88.4833,34.6333],"type":"Point"}
}