{
  "id": 7485761,
  "type": "Feature",
  "properties": {
    "tgn:hierarchy":[
        "tgn:7485761",
        "tgn:7488858",
        "tgn:1000004",
        "tgn:1000141",
        "tgn:7029392"
    ],
    "tgn:id":7485761,
    "tgn:name":"Niaochaokeng",
    "tgn:placetype":[
        "aat:300008699"
    ]
},
  "bbox": [],
  "geometry": {"coordinates":[120.657222,23.670278],"type":"Point"}
}