<<<<<<< HEAD
{
  "id": 7485761,
  "type": "Feature",
  "properties": {
    "tgn:hierarchy":[
        "tgn:7485761",
        "tgn:7488858",
        "tgn:1000004",
        "tgn:1000141",
        "tgn:7029392"
    ],
    "tgn:id":7485761,
    "tgn:name":"Niaochaokeng",
    "tgn:placetype":[
        "aat:300008699"
    ]
},
  "bbox": [],
  "geometry": {"coordinates":[120.657222,23.670278],"type":"Point"}
}
=======
{"geometry":{"type":"Point","coordinates":[120.657222,23.670278]},"type":"Feature","properties":{"hierarchy":["tgn:7485761","tgn:7488858","tgn:1000004","tgn:1000141","tgn:7029392"],"placetype":["aat:300008699"],"id":7485761,"name:xx":"Niaochaokeng"}}
>>>>>>> 03f74aca74312dbeaf24d7e61306dd6a786dc3d0
