{
  "id": 7419950,
  "type": "Feature",
  "properties": {
    "tgn:hierarchy":[
        "tgn:7419950",
        "tgn:7005579",
        "tgn:1000001",
        "tgn:7005560",
        "tgn:7029392"
    ],
    "tgn:id":7419950,
    "tgn:name":"Villa Licenciado Jes\u00fas Ter\u00e1n",
    "tgn:placetype":[
        "aat:300008347"
    ]
},
  "bbox": [],
  "geometry": {"coordinates":[-102.066667,21.983333],"type":"Point"}
}