{
  "id": 2330514,
  "type": "Feature",
  "properties": {
    "tgn:hierarchy":[
        "tgn:2330514",
        "tgn:2000453",
        "tgn:1000001",
        "tgn:7012149",
        "tgn:7007250",
        "tgn:7029392"
    ],
    "tgn:id":2330514,
    "tgn:name":"Flat Creek",
    "tgn:placetype":[
        "aat:300008706"
    ]
},
  "bbox": [],
  "geometry": {"coordinates":[-116.7167,45.0167],"type":"Point"}
}