{
  "id": 7008756,
  "type": "Feature",
  "properties": {
    "tgn:hierarchy":[
        "tgn:7008756",
        "tgn:1000003",
        "tgn:1000070",
        "tgn:7002897",
        "tgn:7029392"
    ],
    "tgn:id":7008756,
    "tgn:name":"Cruas",
    "tgn:placetype":[
        "aat:300008347"
    ]
},
  "bbox": [],
  "geometry": {"coordinates":[4.7667,44.6667],"type":"Point"}
}