{
  "id": 1026800,
  "type": "Feature",
  "properties": {
    "tgn:hierarchy":[
        "tgn:1026800",
        "tgn:7018238",
        "tgn:1000003",
        "tgn:1000063",
        "tgn:4012014",
        "tgn:7029392"
    ],
    "tgn:id":1026800,
    "tgn:name":"Wavre",
    "tgn:placetype":[
        "aat:300008347",
        "aat:300387220"
    ]
},
  "bbox": [],
  "geometry": {"coordinates":[4.616667,50.716667],"type":"Point"}
}