{
  "id": 2691596,
  "type": "Feature",
  "properties": {
    "tgn:hierarchy":[
        "tgn:2691596",
        "tgn:1000001",
        "tgn:7012149",
        "tgn:2001290",
        "tgn:7007524",
        "tgn:7029392"
    ],
    "tgn:id":2691596,
    "tgn:name":"Stark Mountain",
    "tgn:placetype":[
        "aat:300008798"
    ]
},
  "bbox": [],
  "geometry": {"coordinates":[-114.5667,47.0833],"type":"Point"}
}