{
  "id": 2603345,
  "type": "Feature",
  "properties": {
    "tgn:hierarchy":[
        "tgn:2603345",
        "tgn:1000001",
        "tgn:2002368",
        "tgn:7012149",
        "tgn:7007923",
        "tgn:7029392"
    ],
    "tgn:id":2603345,
    "tgn:name":"Quartzite Peak",
    "tgn:placetype":[
        "aat:300008798"
    ]
},
  "bbox": [],
  "geometry": {"coordinates":[-107.05,41.15],"type":"Point"}
}