{
  "id": 2011942,
  "type": "Feature",
  "properties": {
    "tgn:hierarchy":[
        "tgn:2011942",
        "tgn:1000001",
        "tgn:7012149",
        "tgn:7007157",
        "tgn:1002857",
        "tgn:7029392"
    ],
    "tgn:id":2011942,
    "tgn:name":"Jimgrey",
    "tgn:placetype":[
        "aat:300387016"
    ]
},
  "bbox": [],
  "geometry": {"coordinates":[-117.4667,34.9667],"type":"Point"}
}