{
  "id": 1118624,
  "type": "Feature",
  "properties": {
    "tgn:hierarchy":[
        "tgn:1118624",
        "tgn:7003669",
        "tgn:1000003",
        "tgn:7000084",
        "tgn:7029392"
    ],
    "tgn:id":1118624,
    "tgn:name":"Walchensee",
    "tgn:placetype":[
        "aat:300008680"
    ]
},
  "bbox": [],
  "geometry": {"coordinates":[11.35,47.583333],"type":"Point"}
}