{
  "id": 7433644,
  "type": "Feature",
  "properties": {
    "tgn:hierarchy":[
        "tgn:7433644",
        "tgn:1000001",
        "tgn:1001960",
        "tgn:7005560",
        "tgn:7029392"
    ],
    "tgn:id":7433644,
    "tgn:name":"Verde, Sierra",
    "tgn:placetype":[
        "aat:300008795"
    ]
},
  "bbox": [],
  "geometry": {"coordinates":[-110.016667,28.55],"type":"Point"}
}