{
  "id": 7505113,
  "type": "Feature",
  "properties": {
    "tgn:hierarchy":[
        "tgn:7505113",
        "tgn:1009892",
        "tgn:1000226",
        "tgn:1000006",
        "tgn:7029392"
    ],
    "tgn:id":7505113,
    "tgn:name:en":"Proclamation Island",
    "tgn:placetype":[
        "aat:300008791"
    ]
},
  "bbox": [],
  "geometry": {"coordinates":[179.026111,-47.749444],"type":"Point"}
}