{
  "id": 2433984,
  "type": "Feature",
  "properties": {
    "tgn:hierarchy":[
        "tgn:2433984",
        "tgn:1000001",
        "tgn:7012149",
        "tgn:2001894",
        "tgn:7007825",
        "tgn:7029392"
    ],
    "tgn:id":2433984,
    "tgn:name":"Kellys Bar",
    "tgn:placetype":[
        "aat:300132348"
    ]
},
  "bbox": [],
  "geometry": {"coordinates":[-85.4167,35.0333],"type":"Point"}
}