{
  "id": 7336353,
  "type": "Feature",
  "properties": {
    "tgn:hierarchy":[
        "tgn:7336353",
        "tgn:1001439",
        "tgn:1000003",
        "tgn:7002797",
        "tgn:1000095",
        "tgn:7029392"
    ],
    "tgn:id":7336353,
    "tgn:name":"Falc\u00f3, Cabo",
    "tgn:placetype":[
        "aat:300387499"
    ]
},
  "bbox": [],
  "geometry": {"coordinates":[-1.116667,37.533333],"type":"Point"}
}