{
  "id": 7457715,
  "type": "Feature",
  "properties": {
    "tgn:hierarchy":[
        "tgn:7457715",
        "tgn:7002444",
        "tgn:1000003",
        "tgn:7008082",
        "tgn:7008591",
        "tgn:7029392"
    ],
    "tgn:id":7457715,
    "tgn:name:en":"Macleods Maidens",
    "tgn:placetype":[
        "aat:300011692"
    ]
},
  "bbox": [],
  "geometry": {"coordinates":[-6.583333,57.316667],"type":"Point"}
}