{
  "id": 7255934,
  "type": "Feature",
  "properties": {
    "tgn:hierarchy":[
        "tgn:7255934",
        "tgn:7003461",
        "tgn:1000003",
        "tgn:1000063",
        "tgn:7018236",
        "tgn:7029392"
    ],
    "tgn:id":7255934,
    "tgn:name":"Sint-Antoniusberg",
    "tgn:placetype":[
        "aat:300008347"
    ]
},
  "bbox": [],
  "geometry": {"coordinates":[5.616667,50.866667],"type":"Point"}
}