{
  "id": 2212243,
  "type": "Feature",
  "properties": {
    "tgn:hierarchy":[
        "tgn:2212243",
        "tgn:1000001",
        "tgn:7012149",
        "tgn:7007240",
        "tgn:7029392"
    ],
    "tgn:id":2212243,
    "tgn:name":"Buzzard Roost Branch",
    "tgn:placetype":[
        "aat:300008699"
    ]
},
  "bbox": [],
  "geometry": {"coordinates":[-82.0333,27.35],"type":"Point"}
}