{
  "id": 2339386,
  "type": "Feature",
  "properties": {
    "tgn:hierarchy":[
        "tgn:2339386",
        "tgn:1000001",
        "tgn:7012149",
        "tgn:2001275",
        "tgn:7007524",
        "tgn:7029392"
    ],
    "tgn:id":2339386,
    "tgn:name":"Frazier Creek",
    "tgn:placetype":[
        "aat:300008706"
    ]
},
  "bbox": [],
  "geometry": {"coordinates":[-110.9667,45.9167],"type":"Point"}
}