<<<<<<< HEAD
{
  "id": 2339386,
  "type": "Feature",
  "properties": {
    "tgn:hierarchy":[
        "tgn:2339386",
        "tgn:1000001",
        "tgn:7012149",
        "tgn:2001275",
        "tgn:7007524",
        "tgn:7029392"
    ],
    "tgn:id":2339386,
    "tgn:name":"Frazier Creek",
    "tgn:placetype":[
        "aat:300008706"
    ]
},
  "bbox": [],
  "geometry": {"coordinates":[-110.9667,45.9167],"type":"Point"}
}
=======
{"geometry":{"type":"Point","coordinates":[-110.966700,45.916700]},"type":"Feature","properties":{"hierarchy":["tgn:2339386","tgn:1000001","tgn:7012149","tgn:2001275","tgn:7007524","tgn:7029392"],"placetype":["aat:300008706"],"id":2339386,"name:xx":"Frazier Creek"}}
>>>>>>> 03f74aca74312dbeaf24d7e61306dd6a786dc3d0
