{
  "id": 7274644,
  "type": "Feature",
  "properties": {
    "tgn:hierarchy":[
        "tgn:7274644",
        "tgn:1000003",
        "tgn:7006951",
        "tgn:7016845",
        "tgn:7029392"
    ],
    "tgn:id":7274644,
    "tgn:name:nl":"Wormer Jisp en Nek, Polder",
    "tgn:placetype":[
        "aat:300006163"
    ]
},
  "bbox": [],
  "geometry": {"coordinates":[4.833333,52.516667],"type":"Point"}
}