{
  "id": 7429525,
  "type": "Feature",
  "properties": {
    "tgn:hierarchy":[
        "tgn:7429525",
        "tgn:1000001",
        "tgn:7005595",
        "tgn:7005560",
        "tgn:7029392"
    ],
    "tgn:id":7429525,
    "tgn:name":"Isabeles",
    "tgn:placetype":[
        "aat:300008347"
    ]
},
  "bbox": [],
  "geometry": {"coordinates":[-107.425,24.533333],"type":"Point"}
}