{
  "id": 1062776,
  "type": "Feature",
  "properties": {
    "tgn:hierarchy":[
        "tgn:1062776",
        "tgn:1000374",
        "tgn:1000003",
        "tgn:1000097",
        "tgn:7029392"
    ],
    "tgn:id":1062776,
    "tgn:name":"Arbr\u00e5",
    "tgn:placetype":[
        "aat:300008347"
    ]
},
  "bbox": [],
  "geometry": {"coordinates":[16.4167,61.4833],"type":"Point"}
}