{
  "id": 2241776,
  "type": "Feature",
  "properties": {
    "tgn:hierarchy":[
        "tgn:2241776",
        "tgn:1002808",
        "tgn:1000001",
        "tgn:7012149",
        "tgn:7007711",
        "tgn:7029392"
    ],
    "tgn:id":2241776,
    "tgn:name":"Clarkville Pond",
    "tgn:placetype":[
        "aat:300006191"
    ]
},
  "bbox": [],
  "geometry": {"coordinates":[-71.7833,41.9167],"type":"Point"}
}