<<<<<<< HEAD
{
  "id": 7055391,
  "type": "Feature",
  "properties": {
    "tgn:hierarchy":[
        "tgn:7055391",
        "tgn:1001724",
        "tgn:1000003",
        "tgn:7003121",
        "tgn:1000080",
        "tgn:7029392"
    ],
    "tgn:id":7055391,
    "tgn:name":"Liberotto, Cala",
    "tgn:placetype":[
        "aat:300132317"
    ]
},
  "bbox": [],
  "geometry": {"coordinates":[9.766667,40.433333],"type":"Point"}
}
=======
{"geometry":{"type":"Point","coordinates":[9.766667,40.433333]},"type":"Feature","properties":{"hierarchy":["tgn:7055391","tgn:1001724","tgn:1000003","tgn:7003121","tgn:1000080","tgn:7029392"],"placetype":["aat:300132317"],"id":7055391,"name:xx":"Liberotto, Cala"}}
>>>>>>> 03f74aca74312dbeaf24d7e61306dd6a786dc3d0
