{
  "id": 2311805,
  "type": "Feature",
  "properties": {
    "tgn:hierarchy":[
        "tgn:2311805",
        "tgn:1000001",
        "tgn:7012149",
        "tgn:2001212",
        "tgn:7007523",
        "tgn:7029392"
    ],
    "tgn:id":2311805,
    "tgn:name":"Edwin A Pape Lake",
    "tgn:placetype":[
        "aat:300006191"
    ]
},
  "bbox": [],
  "geometry": {"coordinates":[-93.5667,38.9333],"type":"Point"}
}