{
  "id": 2200904,
  "type": "Feature",
  "properties": {
    "tgn:hierarchy":[
        "tgn:2200904",
        "tgn:1000001",
        "tgn:7012149",
        "tgn:1002576",
        "tgn:7007520",
        "tgn:7029392"
    ],
    "tgn:id":2200904,
    "tgn:name":"Bryant Drain",
    "tgn:placetype":[
        "aat:300006075"
    ]
},
  "bbox": [],
  "geometry": {"coordinates":[-83.2167,43.0667],"type":"Point"}
}