{
  "id": 7569077,
  "type": "Feature",
  "properties": {
    "tgn:hierarchy":[
        "tgn:7569077",
        "tgn:1001828",
        "tgn:1000004",
        "tgn:7000198",
        "tgn:7029392"
    ],
    "tgn:id":7569077,
    "tgn:name:en":"Husain Saw\u0101li Darg\u0101h",
    "tgn:placetype":[
        "aat:300008347"
    ]
},
  "bbox": [],
  "geometry": {"coordinates":[78.390278,17.4125],"type":"Point"}
}