{
  "id": 1135350,
  "type": "Feature",
  "properties": {
    "tgn:hierarchy":[
        "tgn:1135350",
        "tgn:1000001",
        "tgn:1002724",
        "tgn:7012149",
        "tgn:7007517",
        "tgn:7029392"
    ],
    "tgn:id":1135350,
    "tgn:name":"Powissett Brook",
    "tgn:placetype":[
        "aat:300008703"
    ]
},
  "bbox": [],
  "geometry": {"coordinates":[-71.25,42.2167],"type":"Point"}
}