{
  "id": 7202923,
  "type": "Feature",
  "properties": {
    "tgn:hierarchy":[
        "tgn:7202923",
        "tgn:1000003",
        "tgn:7003677",
        "tgn:7000084",
        "tgn:7029392"
    ],
    "tgn:id":7202923,
    "tgn:name":"Br\u00f6cker",
    "tgn:placetype":[
        "aat:300000206"
    ]
},
  "bbox": [],
  "geometry": {"coordinates":[6.833333,52.083333],"type":"Point"}
}