{
  "id": 2415619,
  "type": "Feature",
  "properties": {
    "tgn:hierarchy":[
        "tgn:2415619",
        "tgn:1000001",
        "tgn:2000922",
        "tgn:7012149",
        "tgn:7007515",
        "tgn:7029392"
    ],
    "tgn:id":2415619,
    "tgn:name":"Israel Point",
    "tgn:placetype":[
        "aat:300008850"
    ]
},
  "bbox": [],
  "geometry": {"coordinates":[-68.3333,44.4167],"type":"Point"}
}