{
  "id": 7555925,
  "type": "Feature",
  "properties": {
    "tgn:hierarchy":[
        "tgn:7555925",
        "tgn:1000004",
        "tgn:7000198",
        "tgn:7016788",
        "tgn:7029392"
    ],
    "tgn:id":7555925,
    "tgn:name:en":"Naraina",
    "tgn:placetype":[
        "aat:300008347"
    ]
},
  "bbox": [],
  "geometry": {"coordinates":[75.20608,26.790694],"type":"Point"}
}