{
  "id": 2507074,
  "type": "Feature",
  "properties": {
    "tgn:hierarchy":[
        "tgn:2507074",
        "tgn:1000001",
        "tgn:7006451",
        "tgn:7012149",
        "tgn:2000103",
        "tgn:7029392"
    ],
    "tgn:id":2507074,
    "tgn:name":"Metate Tank",
    "tgn:placetype":[
        "aat:300006191"
    ]
},
  "bbox": [],
  "geometry": {"coordinates":[-112.0667,34.4667],"type":"Point"}
}