{
  "id": 2313927,
  "type": "Feature",
  "properties": {
    "tgn:hierarchy":[
        "tgn:2313927",
        "tgn:1000001",
        "tgn:7012149",
        "tgn:2001154",
        "tgn:7007522",
        "tgn:7029392"
    ],
    "tgn:id":2313927,
    "tgn:name":"Eliphaz",
    "tgn:placetype":[
        "aat:300008347"
    ]
},
  "bbox": [],
  "geometry": {"coordinates":[-90.1167,34.65],"type":"Point"}
}