{
  "id": 7529016,
  "type": "Feature",
  "properties": {
    "tgn:hierarchy":[
        "tgn:7529016",
        "tgn:7001242",
        "tgn:7016833",
        "tgn:1001083",
        "tgn:7029392"
    ],
    "tgn:id":7529016,
    "tgn:name:en":"Umm Ratamah, W\u0101d\u012b",
    "tgn:placetype":[
        "aat:300379998"
    ]
},
  "bbox": [],
  "geometry": {"coordinates":[31.483333,29.75],"type":"Point"}
}