{
  "id": 2251970,
  "type": "Feature",
  "properties": {
    "tgn:hierarchy":[
        "tgn:2251970",
        "tgn:1000001",
        "tgn:7012149",
        "tgn:2001538",
        "tgn:7007709",
        "tgn:7029392"
    ],
    "tgn:id":2251970,
    "tgn:name":"Concord",
    "tgn:placetype":[
        "aat:300008347"
    ]
},
  "bbox": [],
  "geometry": {"coordinates":[-78.4167,34.9667],"type":"Point"}
}