{
  "id": 7197734,
  "type": "Feature",
  "properties": {
    "tgn:hierarchy":[
        "tgn:7197734",
        "tgn:1000003",
        "tgn:7003682",
        "tgn:7000084",
        "tgn:7029392"
    ],
    "tgn:id":7197734,
    "tgn:name":"Ehrenbreitstein",
    "tgn:placetype":[
        "aat:300000745"
    ]
},
  "bbox": [],
  "geometry": {"coordinates":[7.616667,50.35],"type":"Point"}
}