{
  "id": 7522016,
  "type": "Feature",
  "properties": {
    "tgn:hierarchy":[
        "tgn:7522016",
        "tgn:7001242",
        "tgn:7016833",
        "tgn:7029392"
    ],
    "tgn:id":7522016,
    "tgn:name:en":"Ab\u016b Nujaylah, Raw\u1e11",
    "tgn:placetype":[
        "aat:300379998"
    ]
},
  "bbox": [],
  "geometry": {"coordinates":[31.385062,29.727882],"type":"Point"}
}