{
  "id": 2273870,
  "type": "Feature",
  "properties": {
    "tgn:hierarchy":[
        "tgn:2273870",
        "tgn:7006450",
        "tgn:1000001",
        "tgn:7012149",
        "tgn:2000086",
        "tgn:7029392"
    ],
    "tgn:id":2273870,
    "tgn:name":"Dadina Lake",
    "tgn:placetype":[
        "aat:300008680"
    ]
},
  "bbox": [],
  "geometry": {"coordinates":[-144.7833,61.8333],"type":"Point"}
}