{
  "id": 2076416,
  "type": "Feature",
  "properties": {
    "tgn:hierarchy":[
        "tgn:2076416",
        "tgn:1000001",
        "tgn:1007357",
        "tgn:7012149",
        "tgn:2001488",
        "tgn:7007709",
        "tgn:7029392"
    ],
    "tgn:id":2076416,
    "tgn:name":"Rodanthe",
    "tgn:placetype":[
        "aat:300008347"
    ]
},
  "bbox": [],
  "geometry": {"coordinates":[-75.4667,35.5833],"type":"Point"}
}