{
  "id": 7082786,
  "type": "Feature",
  "properties": {
    "tgn:hierarchy":[
        "tgn:7082786",
        "tgn:1000003",
        "tgn:7003676",
        "tgn:7000084",
        "tgn:7029392"
    ],
    "tgn:id":7082786,
    "tgn:name":"Westerhuser Neuland",
    "tgn:placetype":[
        "aat:300000206"
    ]
},
  "bbox": [],
  "geometry": {"coordinates":[7.183333,53.383333],"type":"Point"}
}