{
  "id": 2126638,
  "type": "Feature",
  "properties": {
    "tgn:hierarchy":[
        "tgn:2126638",
        "tgn:1000001",
        "tgn:7012149",
        "tgn:2001711",
        "tgn:7007708",
        "tgn:7029392"
    ],
    "tgn:id":2126638,
    "tgn:name":"Agate Desert",
    "tgn:placetype":[
        "aat:300008805"
    ]
},
  "bbox": [],
  "geometry": {"coordinates":[-122.8833,42.4167],"type":"Point"}
}