{
  "id": 7205967,
  "type": "Feature",
  "properties": {
    "tgn:hierarchy":[
        "tgn:7205967",
        "tgn:7003669",
        "tgn:1000003",
        "tgn:7000084",
        "tgn:7029392"
    ],
    "tgn:id":7205967,
    "tgn:name":"Burgstall Kopf",
    "tgn:placetype":[
        "aat:300008798"
    ]
},
  "bbox": [],
  "geometry": {"coordinates":[12.933333,47.666667],"type":"Point"}
}