{
  "id": 7041966,
  "type": "Feature",
  "properties": {
    "tgn:hierarchy":[
        "tgn:7041966",
        "tgn:7003013",
        "tgn:7003005",
        "tgn:1000003",
        "tgn:1000080",
        "tgn:7029392"
    ],
    "tgn:id":7041966,
    "tgn:name":"Ruscello, Monte",
    "tgn:placetype":[
        "aat:300008795"
    ]
},
  "bbox": [],
  "geometry": {"coordinates":[14.066667,40.883333],"type":"Point"}
}