{
  "id": 7477980,
  "type": "Feature",
  "properties": {
    "tgn:hierarchy":[
        "tgn:7477980",
        "tgn:7001010",
        "tgn:1000004",
        "tgn:1000141",
        "tgn:7029392"
    ],
    "tgn:id":7477980,
    "tgn:name":"Andong Shan",
    "tgn:placetype":[
        "aat:300008798"
    ]
},
  "bbox": [],
  "geometry": {"coordinates":[121.300299,23.841768],"type":"Point"}
}