{
  "id": 2525178,
  "type": "Feature",
  "properties": {
    "tgn:hierarchy":[
        "tgn:2525178",
        "tgn:1000001",
        "tgn:7012149",
        "tgn:2001856",
        "tgn:7007825",
        "tgn:7029392"
    ],
    "tgn:id":2525178,
    "tgn:name":"Morris Spring",
    "tgn:placetype":[
        "aat:300008697"
    ]
},
  "bbox": [],
  "geometry": {"coordinates":[-88.05,35.8333],"type":"Point"}
}