<<<<<<< HEAD
{
  "id": 2409228,
  "type": "Feature",
  "properties": {
    "tgn:hierarchy":[
        "tgn:2409228",
        "tgn:1000001",
        "tgn:2001801",
        "tgn:7012149",
        "tgn:7007713",
        "tgn:7029392"
    ],
    "tgn:id":2409228,
    "tgn:name":"Icebox Canyon",
    "tgn:placetype":[
        "aat:300008761"
    ]
},
  "bbox": [],
  "geometry": {"coordinates":[-103.5,45.8333],"type":"Point"}
}
=======
{"geometry":{"type":"Point","coordinates":[-103.500000,45.833300]},"type":"Feature","properties":{"hierarchy":["tgn:2409228","tgn:1000001","tgn:2001801","tgn:7012149","tgn:7007713","tgn:7029392"],"placetype":["aat:300008761"],"id":2409228,"name:xx":"Icebox Canyon"}}
>>>>>>> 03f74aca74312dbeaf24d7e61306dd6a786dc3d0
