{
  "id": 7530982,
  "type": "Feature",
  "properties": {
    "tgn:hierarchy":[
        "tgn:7530982",
        "tgn:7001242",
        "tgn:7016833",
        "tgn:7001312",
        "tgn:7029392"
    ],
    "tgn:id":7530982,
    "tgn:name:en":"Tir'at M\u012bt al Layt",
    "tgn:placetype":[
        "aat:300006075"
    ]
},
  "bbox": [],
  "geometry": {"coordinates":[31.163639,30.993068],"type":"Point"}
}