{
  "id": 7246888,
  "type": "Feature",
  "properties": {
    "tgn:hierarchy":[
        "tgn:7246888",
        "tgn:7003457",
        "tgn:1000003",
        "tgn:1000063",
        "tgn:7018236",
        "tgn:7029392"
    ],
    "tgn:id":7246888,
    "tgn:name":"Doodhoek",
    "tgn:placetype":[
        "aat:300008347"
    ]
},
  "bbox": [],
  "geometry": {"coordinates":[3.684596,51.242544],"type":"Point"}
}