{
  "id": 7073399,
  "type": "Feature",
  "properties": {
    "tgn:hierarchy":[
        "tgn:7073399",
        "tgn:1000003",
        "tgn:7003676",
        "tgn:7000084",
        "tgn:7029392"
    ],
    "tgn:id":7073399,
    "tgn:name":"S\u00fcdgeorgsfehn",
    "tgn:placetype":[
        "aat:300008347"
    ]
},
  "bbox": [],
  "geometry": {"coordinates":[7.733333,53.233333],"type":"Point"}
}