{
  "id": 7588797,
  "type": "Feature",
  "properties": {
    "tgn:hierarchy":[
        "tgn:7588797",
        "tgn:1000004",
        "tgn:7000198",
        "tgn:1001894",
        "tgn:7029392"
    ],
    "tgn:id":7588797,
    "tgn:name:en":"Deora",
    "tgn:placetype":[
        "aat:300008347"
    ]
},
  "bbox": [],
  "geometry": {"coordinates":[82.349087,24.091168],"type":"Point"}
}