<<<<<<< HEAD
{
  "id": 7489424,
  "type": "Feature",
  "properties": {
    "tgn:hierarchy":[
        "tgn:7489424",
        "tgn:1000004",
        "tgn:7492971",
        "tgn:1000141",
        "tgn:7029392"
    ],
    "tgn:id":7489424,
    "tgn:name":"Dingtouzi",
    "tgn:placetype":[
        "aat:300008347"
    ]
},
  "bbox": [],
  "geometry": {"coordinates":[120.4825,22.509449],"type":"Point"}
}
=======
{"geometry":{"type":"Point","coordinates":[120.482500,22.509449]},"type":"Feature","properties":{"hierarchy":["tgn:7489424","tgn:1000004","tgn:7492971","tgn:1000141","tgn:7029392"],"placetype":["aat:300008347"],"id":7489424,"name:xx":"Dingtouzi"}}
>>>>>>> 03f74aca74312dbeaf24d7e61306dd6a786dc3d0
