{
  "id": 7041930,
  "type": "Feature",
  "properties": {
    "tgn:hierarchy":[
        "tgn:7041930",
        "tgn:7003127",
        "tgn:1000003",
        "tgn:7008516",
        "tgn:1000080",
        "tgn:7029392"
    ],
    "tgn:id":7041930,
    "tgn:name":"Sabbioni",
    "tgn:placetype":[
        "aat:300008347"
    ]
},
  "bbox": [],
  "geometry": {"coordinates":[11.333333,44.283333],"type":"Point"}
}