{
  "id": 7394932,
  "type": "Feature",
  "properties": {
    "tgn:hierarchy":[
        "tgn:7394932",
        "tgn:7005580",
        "tgn:1000001",
        "tgn:7005560",
        "tgn:7029392"
    ],
    "tgn:id":7394932,
    "tgn:name":"San Antonio",
    "tgn:placetype":[
        "aat:300008347"
    ]
},
  "bbox": [],
  "geometry": {"coordinates":[-93.433333,16.55],"type":"Point"}
}