{
  "id": 1027869,
  "type": "Feature",
  "properties": {
    "tgn:hierarchy":[
        "tgn:1027869",
        "tgn:7594007",
        "tgn:1000003",
        "tgn:1000066",
        "tgn:7029392"
    ],
    "tgn:id":1027869,
    "tgn:name":"Hadsund",
    "tgn:placetype":[
        "aat:300008347"
    ]
},
  "bbox": [],
  "geometry": {"coordinates":[10.1333,56.7167],"type":"Point"}
}