<<<<<<< HEAD
{
  "id": 2339337,
  "type": "Feature",
  "properties": {
    "tgn:hierarchy":[
        "tgn:2339337",
        "tgn:1000001",
        "tgn:7012149",
        "tgn:1002742",
        "tgn:7007920",
        "tgn:7029392"
    ],
    "tgn:id":2339337,
    "tgn:name":"Frazer Creek",
    "tgn:placetype":[
        "aat:300008706"
    ]
},
  "bbox": [],
  "geometry": {"coordinates":[-119.8833,48.4],"type":"Point"}
}
=======
{"geometry":{"type":"Point","coordinates":[-119.883300,48.400000]},"type":"Feature","properties":{"hierarchy":["tgn:2339337","tgn:1000001","tgn:7012149","tgn:1002742","tgn:7007920","tgn:7029392"],"placetype":["aat:300008706"],"id":2339337,"name:xx":"Frazer Creek"}}
>>>>>>> 03f74aca74312dbeaf24d7e61306dd6a786dc3d0
