{
  "id": 7078837,
  "type": "Feature",
  "properties": {
    "tgn:hierarchy":[
        "tgn:7078837",
        "tgn:1000003",
        "tgn:7003687",
        "tgn:7000084",
        "tgn:7029392"
    ],
    "tgn:id":7078837,
    "tgn:name":"Zerben",
    "tgn:placetype":[
        "aat:300008347"
    ]
},
  "bbox": [],
  "geometry": {"coordinates":[11.95,52.35],"type":"Point"}
}