{
  "id": 2274618,
  "type": "Feature",
  "properties": {
    "tgn:hierarchy":[
        "tgn:2274618",
        "tgn:1000001",
        "tgn:7012149",
        "tgn:7007157",
        "tgn:2000186",
        "tgn:7029392"
    ],
    "tgn:id":2274618,
    "tgn:name":"Dalton Reservoir",
    "tgn:placetype":[
        "aat:300006191"
    ]
},
  "bbox": [],
  "geometry": {"coordinates":[-121.0167,41.7333],"type":"Point"}
}