{
  "id": 2746995,
  "type": "Feature",
  "properties": {
    "tgn:hierarchy":[
        "tgn:2746995",
        "tgn:1000001",
        "tgn:7012149",
        "tgn:2000978",
        "tgn:7007520",
        "tgn:7029392"
    ],
    "tgn:id":2746995,
    "tgn:name":"Wagner Lake",
    "tgn:placetype":[
        "aat:300008680"
    ]
},
  "bbox": [],
  "geometry": {"coordinates":[-87.5167,45.45],"type":"Point"}
}