{
  "id": 7100840,
  "type": "Feature",
  "properties": {
    "tgn:hierarchy":[
        "tgn:7100840",
        "tgn:7003669",
        "tgn:1000003",
        "tgn:7000084",
        "tgn:7029392"
    ],
    "tgn:id":7100840,
    "tgn:name":"Rottel Bach",
    "tgn:placetype":[
        "aat:300008699"
    ]
},
  "bbox": [],
  "geometry": {"coordinates":[11.483333,49.983333],"type":"Point"}
}