<<<<<<< HEAD
{
  "id": 7480932,
  "type": "Feature",
  "properties": {
    "tgn:hierarchy":[
        "tgn:7480932",
        "tgn:1000004",
        "tgn:7001013",
        "tgn:1000141",
        "tgn:7029392"
    ],
    "tgn:id":7480932,
    "tgn:name":"Shifan Gongmu",
    "tgn:placetype":[
        "aat:300266755"
    ]
},
  "bbox": [],
  "geometry": {"coordinates":[121.319887,25.022135],"type":"Point"}
}
=======
{"geometry":{"type":"Point","coordinates":[121.319887,25.022135]},"type":"Feature","properties":{"hierarchy":["tgn:7480932","tgn:1000004","tgn:7001013","tgn:1000141","tgn:7029392"],"placetype":["aat:300266755"],"id":7480932,"name:xx":"Shifan Gongmu"}}
>>>>>>> 03f74aca74312dbeaf24d7e61306dd6a786dc3d0
