{
  "id": 2235230,
  "type": "Feature",
  "properties": {
    "tgn:hierarchy":[
        "tgn:2235230",
        "tgn:1000001",
        "tgn:7012149",
        "tgn:2001544",
        "tgn:7007709",
        "tgn:7029392"
    ],
    "tgn:id":2235230,
    "tgn:name":"Cherry Tree Branch",
    "tgn:placetype":[
        "aat:300008699"
    ]
},
  "bbox": [],
  "geometry": {"coordinates":[-82.6333,35.2833],"type":"Point"}
}