{
  "id": 2610006,
  "type": "Feature",
  "properties": {
    "tgn:hierarchy":[
        "tgn:2610006",
        "tgn:1000001",
        "tgn:7012149",
        "tgn:1002392",
        "tgn:7007157",
        "tgn:7029392"
    ],
    "tgn:id":2610006,
    "tgn:name":"Recto, Arroyo",
    "tgn:placetype":[
        "aat:300008699"
    ]
},
  "bbox": [],
  "geometry": {"coordinates":[-120.1667,36.0667],"type":"Point"}
}