{
  "id": 7496943,
  "type": "Feature",
  "properties": {
    "tgn:hierarchy":[
        "tgn:7496943",
        "tgn:1000004",
        "tgn:1000959",
        "tgn:1000141",
        "tgn:7029392"
    ],
    "tgn:id":7496943,
    "tgn:name":"Guandu Fangchaoti",
    "tgn:placetype":[
        "aat:300006156"
    ]
},
  "bbox": [],
  "geometry": {"coordinates":[121.479,25.113755],"type":"Point"}
}