{
  "id": 2340287,
  "type": "Feature",
  "properties": {
    "tgn:hierarchy":[
        "tgn:2340287",
        "tgn:1000001",
        "tgn:7012149",
        "tgn:2001709",
        "tgn:7007708",
        "tgn:7029392"
    ],
    "tgn:id":2340287,
    "tgn:name":"French Creek",
    "tgn:placetype":[
        "aat:300008706"
    ]
},
  "bbox": [],
  "geometry": {"coordinates":[-118.75,42.1833],"type":"Point"}
}