{
  "id": 7567242,
  "type": "Feature",
  "properties": {
    "tgn:hierarchy":[
        "tgn:7567242",
        "tgn:1000004",
        "tgn:7000198",
        "tgn:7031786",
        "tgn:7029392"
    ],
    "tgn:id":7567242,
    "tgn:name:en":"Ghota Malla",
    "tgn:placetype":[
        "aat:300008347"
    ]
},
  "bbox": [],
  "geometry": {"coordinates":[78.589086,29.849483],"type":"Point"}
}