{
  "id": 7100778,
  "type": "Feature",
  "properties": {
    "tgn:hierarchy":[
        "tgn:7100778",
        "tgn:1000003",
        "tgn:7003677",
        "tgn:7000084",
        "tgn:7029392"
    ],
    "tgn:id":7100778,
    "tgn:name":"R\u00fctfering",
    "tgn:placetype":[
        "aat:300000206"
    ]
},
  "bbox": [],
  "geometry": {"coordinates":[7.983333,51.716667],"type":"Point"}
}