{
  "id": 1064130,
  "type": "Feature",
  "properties": {
    "tgn:hierarchy":[
        "tgn:1064130",
        "tgn:7003742",
        "tgn:1000003",
        "tgn:7011731",
        "tgn:7029392"
    ],
    "tgn:id":1064130,
    "tgn:name":"K\u00f6niz",
    "tgn:placetype":[
        "aat:300008347"
    ]
},
  "bbox": [],
  "geometry": {"coordinates":[7.4167,46.9333],"type":"Point"}
}