{
  "id": 7591070,
  "type": "Feature",
  "properties": {
    "tgn:hierarchy":[
        "tgn:7591070",
        "tgn:1000004",
        "tgn:7000198",
        "tgn:7000799",
        "tgn:7029392"
    ],
    "tgn:id":7591070,
    "tgn:name:en":"Chak H\u0101sil",
    "tgn:placetype":[
        "aat:300008347"
    ]
},
  "bbox": [],
  "geometry": {"coordinates":[74.870649,32.571622],"type":"Point"}
}