{
  "id": 1114175,
  "type": "Feature",
  "properties": {
    "tgn:hierarchy":[
        "tgn:1114175",
        "tgn:1000003",
        "tgn:7006663",
        "tgn:7029392"
    ],
    "tgn:id":1114175,
    "tgn:name":"Kor\u010dulanski Kanal",
    "tgn:placetype":[
        "aat:300008713"
    ]
},
  "bbox": [],
  "geometry": {"coordinates":[16.75,43.05],"type":"Point"}
}