<<<<<<< HEAD
{
  "id": 7474623,
  "type": "Feature",
  "properties": {
    "tgn:hierarchy":[
        "tgn:7474623",
        "tgn:1000004",
        "tgn:7467799",
        "tgn:1000141",
        "tgn:7029392"
    ],
    "tgn:id":7474623,
    "tgn:name":"Lunjiao Qiao",
    "tgn:placetype":[
        "aat:300007836"
    ]
},
  "bbox": [],
  "geometry": {"coordinates":[120.363918,23.96904],"type":"Point"}
}
=======
{"geometry":{"type":"Point","coordinates":[120.363918,23.969040]},"type":"Feature","properties":{"hierarchy":["tgn:7474623","tgn:1000004","tgn:7467799","tgn:1000141","tgn:7029392"],"placetype":["aat:300007836"],"id":7474623,"name:xx":"Lunjiao Qiao"}}
>>>>>>> 03f74aca74312dbeaf24d7e61306dd6a786dc3d0
