{
  "id": 7474623,
  "type": "Feature",
  "properties": {
    "tgn:hierarchy":[
        "tgn:7474623",
        "tgn:1000004",
        "tgn:7467799",
        "tgn:1000141",
        "tgn:7029392"
    ],
    "tgn:id":7474623,
    "tgn:name":"Lunjiao Qiao",
    "tgn:placetype":[
        "aat:300007836"
    ]
},
  "bbox": [],
  "geometry": {"coordinates":[120.363918,23.96904],"type":"Point"}
}