<<<<<<< HEAD
{
  "id": 2403005,
  "type": "Feature",
  "properties": {
    "tgn:hierarchy":[
        "tgn:2403005",
        "tgn:1000001",
        "tgn:7012149",
        "tgn:7007520",
        "tgn:7029392"
    ],
    "tgn:id":2403005,
    "tgn:name":"Houghton Lake State Forest",
    "tgn:placetype":[
        "aat:300008863"
    ]
},
  "bbox": [],
  "geometry": {"coordinates":[-84.6833,44.2167],"type":"Point"}
}
=======
{"geometry":{"type":"Point","coordinates":[-84.683300,44.216700]},"type":"Feature","properties":{"hierarchy":["tgn:2403005","tgn:1000001","tgn:7012149","tgn:7007520","tgn:7029392"],"placetype":["aat:300008863"],"id":2403005,"name:xx":"Houghton Lake State Forest"}}
>>>>>>> 03f74aca74312dbeaf24d7e61306dd6a786dc3d0
