{
  "id": 2174051,
  "type": "Feature",
  "properties": {
    "tgn:hierarchy":[
        "tgn:2174051",
        "tgn:1000001",
        "tgn:7012149",
        "tgn:1002545",
        "tgn:7007157",
        "tgn:7029392"
    ],
    "tgn:id":2174051,
    "tgn:name":"Bird Spring",
    "tgn:placetype":[
        "aat:300008697"
    ]
},
  "bbox": [],
  "geometry": {"coordinates":[-118.0667,35.4833],"type":"Point"}
}