{
  "id": 2763173,
  "type": "Feature",
  "properties": {
    "tgn:hierarchy":[
        "tgn:2763173",
        "tgn:1000001",
        "tgn:1002902",
        "tgn:7012149",
        "tgn:7007516",
        "tgn:7029392"
    ],
    "tgn:id":2763173,
    "tgn:name":"Westward Point",
    "tgn:placetype":[
        "aat:300008850"
    ]
},
  "bbox": [],
  "geometry": {"coordinates":[-75.85,37.9167],"type":"Point"}
}