{
  "id": 2682655,
  "type": "Feature",
  "properties": {
    "tgn:hierarchy":[
        "tgn:2682655",
        "tgn:1000001",
        "tgn:7012149",
        "tgn:7022240",
        "tgn:7007523",
        "tgn:7029392"
    ],
    "tgn:id":2682655,
    "tgn:name":"Southhampton",
    "tgn:placetype":[
        "aat:300008347"
    ]
},
  "bbox": [],
  "geometry": {"coordinates":[-90.2833,38.5833],"type":"Point"}
}