{
  "id": 7315306,
  "type": "Feature",
  "properties": {
    "tgn:hierarchy":[
        "tgn:7315306",
        "tgn:1001699",
        "tgn:1000049",
        "tgn:1000002",
        "tgn:7029392"
    ],
    "tgn:id":7315306,
    "tgn:name":"Chapilcahu\u00edn, Estero",
    "tgn:placetype":[
        "aat:300008699"
    ]
},
  "bbox": [],
  "geometry": {"coordinates":[-73.05,-40.483333],"type":"Point"}
}