<<<<<<< HEAD
{
  "id": 2150332,
  "type": "Feature",
  "properties": {
    "tgn:hierarchy":[
        "tgn:2150332",
        "tgn:1000001",
        "tgn:2001411",
        "tgn:7012149",
        "tgn:7007526",
        "tgn:7029392"
    ],
    "tgn:id":2150332,
    "tgn:name":"Basin Burns Mine",
    "tgn:placetype":[
        "aat:300000390"
    ]
},
  "bbox": [],
  "geometry": {"coordinates":[-116.0,41.3333],"type":"Point"}
}
=======
{"geometry":{"type":"Point","coordinates":[-116.000000,41.333300]},"type":"Feature","properties":{"hierarchy":["tgn:2150332","tgn:1000001","tgn:2001411","tgn:7012149","tgn:7007526","tgn:7029392"],"placetype":["aat:300000390"],"id":2150332,"name:xx":"Basin Burns Mine"}}
>>>>>>> 03f74aca74312dbeaf24d7e61306dd6a786dc3d0
