{
  "id": 7329915,
  "type": "Feature",
  "properties": {
    "tgn:hierarchy":[
        "tgn:7329915",
        "tgn:7010420",
        "tgn:1000003",
        "tgn:7002795",
        "tgn:1000095",
        "tgn:7029392"
    ],
    "tgn:id":7329915,
    "tgn:name":"Humanes de Madrid",
    "tgn:placetype":[
        "aat:300008347"
    ]
},
  "bbox": [],
  "geometry": {"coordinates":[-3.833333,40.25],"type":"Point"}
}