{
  "id": 2708553,
  "type": "Feature",
  "properties": {
    "tgn:hierarchy":[
        "tgn:2708553",
        "tgn:1000001",
        "tgn:7012149",
        "tgn:1002701",
        "tgn:7007706",
        "tgn:7029392"
    ],
    "tgn:id":2708553,
    "tgn:name":"Sycamore Run",
    "tgn:placetype":[
        "aat:300008699"
    ]
},
  "bbox": [],
  "geometry": {"coordinates":[-81.95,39.85],"type":"Point"}
}