{
  "id": 2270166,
  "type": "Feature",
  "properties": {
    "tgn:hierarchy":[
        "tgn:2270166",
        "tgn:1000001",
        "tgn:1002753",
        "tgn:7012149",
        "tgn:7007828",
        "tgn:7029392"
    ],
    "tgn:id":2270166,
    "tgn:name":"Crystal Brook",
    "tgn:placetype":[
        "aat:300008699"
    ]
},
  "bbox": [],
  "geometry": {"coordinates":[-72.0667,44.9667],"type":"Point"}
}