{
  "id": 2498034,
  "type": "Feature",
  "properties": {
    "tgn:hierarchy":[
        "tgn:2498034",
        "tgn:1000001",
        "tgn:7012149",
        "tgn:7029392"
    ],
    "tgn:id":2498034,
    "tgn:name":"Mayo Creek",
    "tgn:placetype":[
        "aat:300008706"
    ]
},
  "bbox": [],
  "geometry": {"coordinates":[-78.9167,36.3833],"type":"Point"}
}