{
  "id": 1121131,
  "type": "Feature",
  "properties": {
    "tgn:hierarchy":[
        "tgn:1121131",
        "tgn:7006246",
        "tgn:1000047",
        "tgn:7002455",
        "tgn:1000002",
        "tgn:7029392"
    ],
    "tgn:id":1121131,
    "tgn:name":"Alpercatas",
    "tgn:placetype":[
        "aat:300008707"
    ]
},
  "bbox": [],
  "geometry": {"coordinates":[-44.3167,-6.0333],"type":"Point"}
}