{
  "id": 2733214,
  "type": "Feature",
  "properties": {
    "tgn:hierarchy":[
        "tgn:2733214",
        "tgn:1000001",
        "tgn:7012149",
        "tgn:2000233",
        "tgn:7007158",
        "tgn:7029392"
    ],
    "tgn:id":2733214,
    "tgn:name":"Turkey Point Spring",
    "tgn:placetype":[
        "aat:300008697"
    ]
},
  "bbox": [],
  "geometry": {"coordinates":[-108.2167,37.5167],"type":"Point"}
}