{
  "id": 7076796,
  "type": "Feature",
  "properties": {
    "tgn:hierarchy":[
        "tgn:7076796",
        "tgn:1000003",
        "tgn:7003677",
        "tgn:7000084",
        "tgn:7029392"
    ],
    "tgn:id":7076796,
    "tgn:name":"Pleiser L\u00e4ndchen",
    "tgn:placetype":[
        "aat:300055621"
    ]
},
  "bbox": [],
  "geometry": {"coordinates":[7.25,50.733333],"type":"Point"}
}