{
  "id": 2390108,
  "type": "Feature",
  "properties": {
    "tgn:hierarchy":[
        "tgn:2390108",
        "tgn:1000001",
        "tgn:7012149",
        "tgn:2001543",
        "tgn:7007709",
        "tgn:7029392"
    ],
    "tgn:id":2390108,
    "tgn:name":"High Rocks",
    "tgn:placetype":[
        "aat:300008798"
    ]
},
  "bbox": [],
  "geometry": {"coordinates":[-83.6167,35.4833],"type":"Point"}
}