{
  "id": 2563117,
  "type": "Feature",
  "properties": {
    "tgn:hierarchy":[
        "tgn:2563117",
        "tgn:1000001",
        "tgn:7012149",
        "tgn:2002170",
        "tgn:7007919",
        "tgn:7029392"
    ],
    "tgn:id":2563117,
    "tgn:name":"Owens Creek",
    "tgn:placetype":[
        "aat:300008706"
    ]
},
  "bbox": [],
  "geometry": {"coordinates":[-77.9167,37.8167],"type":"Point"}
}