{
  "id": 7273957,
  "type": "Feature",
  "properties": {
    "tgn:concordances":{
        "gn:id":"2744024"
    },
    "tgn:hierarchy":[
        "tgn:7273957",
        "tgn:1000003",
        "tgn:7003635",
        "tgn:7016845",
        "tgn:7029392"
    ],
    "tgn:id":7273957,
    "tgn:name:nl":"Zeedorp",
    "tgn:placetype":[
        "aat:300008347"
    ]
},
  "bbox": [],
  "geometry": {"coordinates":[3.966667,51.383333],"type":"Point"}
}