{
  "id": 1080620,
  "type": "Feature",
  "properties": {
    "tgn:hierarchy":[
        "tgn:1080620",
        "tgn:7000895",
        "tgn:1000004",
        "tgn:1001010",
        "tgn:1000120",
        "tgn:7029392"
    ],
    "tgn:id":1080620,
    "tgn:name":"Koumi",
    "tgn:placetype":[
        "aat:300008347"
    ]
},
  "bbox": [],
  "geometry": {"coordinates":[138.4833,36.0833],"type":"Point"}
}