{
  "id": 7310713,
  "type": "Feature",
  "properties": {
    "tgn:hierarchy":[
        "tgn:7310713",
        "tgn:1001702",
        "tgn:1000049",
        "tgn:1000002",
        "tgn:7029392"
    ],
    "tgn:id":7310713,
    "tgn:name":"Mornington, Archipi\u00e9lago",
    "tgn:placetype":[
        "aat:300008791"
    ]
},
  "bbox": [],
  "geometry": {"coordinates":[-75.333333,-49.75],"type":"Point"}
}