{
  "id": 7508979,
  "type": "Feature",
  "properties": {
    "tgn:hierarchy":[
        "tgn:7508979",
        "tgn:7520092",
        "tgn:1008380",
        "tgn:1000226",
        "tgn:1000006",
        "tgn:7029392"
    ],
    "tgn:id":7508979,
    "tgn:name:en":"Tiniroto",
    "tgn:placetype":[
        "aat:300008347"
    ]
},
  "bbox": [],
  "geometry": {"coordinates":[177.566667,-38.766667],"type":"Point"}
}