{
  "id": 7015524,
  "type": "Feature",
  "properties": {
    "tgn:hierarchy":[
        "tgn:7015524",
        "tgn:7005023",
        "tgn:1000003",
        "tgn:7003237",
        "tgn:1000080",
        "tgn:7029392"
    ],
    "tgn:id":7015524,
    "tgn:name":"Seriana, Valle",
    "tgn:placetype":[
        "aat:300008761"
    ]
},
  "bbox": [],
  "geometry": {"coordinates":[9.916667,45.916667],"type":"Point"}
}