{
  "id": 7145521,
  "type": "Feature",
  "properties": {
    "tgn:hierarchy":[
        "tgn:7145521",
        "tgn:1000003",
        "tgn:7003673",
        "tgn:7000084",
        "tgn:7029392"
    ],
    "tgn:id":7145521,
    "tgn:name":"Knockenthal",
    "tgn:placetype":[
        "aat:300000206"
    ]
},
  "bbox": [],
  "geometry": {"coordinates":[12.85,48.55],"type":"Point"}
}