{
  "id": 1096660,
  "type": "Feature",
  "properties": {
    "tgn:hierarchy":[
        "tgn:1096660",
        "tgn:7000490",
        "tgn:1000006",
        "tgn:7001831",
        "tgn:7029392"
    ],
    "tgn:id":1096660,
    "tgn:name":"Cowarie",
    "tgn:placetype":[
        "aat:300008347"
    ]
},
  "bbox": [],
  "geometry": {"coordinates":[138.2833,-27.6667],"type":"Point"}
}