{
  "id": 2611105,
  "type": "Feature",
  "properties": {
    "tgn:hierarchy":[
        "tgn:2611105",
        "tgn:1000001",
        "tgn:2002367",
        "tgn:7012149",
        "tgn:7007923",
        "tgn:7029392"
    ],
    "tgn:id":2611105,
    "tgn:name":"Red Hill Spring",
    "tgn:placetype":[
        "aat:300008697"
    ]
},
  "bbox": [],
  "geometry": {"coordinates":[-105.7167,44.3667],"type":"Point"}
}