{
  "id": 2607481,
  "type": "Feature",
  "properties": {
    "tgn:hierarchy":[
        "tgn:2607481",
        "tgn:1000001",
        "tgn:7012149",
        "tgn:1002676",
        "tgn:7007240",
        "tgn:7029392"
    ],
    "tgn:id":2607481,
    "tgn:name":"Rankin Key",
    "tgn:placetype":[
        "aat:300008791"
    ]
},
  "bbox": [],
  "geometry": {"coordinates":[-80.7833,25.1167],"type":"Point"}
}