{
  "id": 4012409,
  "type": "Feature",
  "properties": {
    "tgn:hierarchy":[
        "tgn:4012409",
        "tgn:1000001",
        "tgn:7005591",
        "tgn:7005560",
        "tgn:7029392"
    ],
    "tgn:id":4012409,
    "tgn:name":"Yanhuitl\u00e1n",
    "tgn:placetype":[
        "aat:300008347",
        "aat:300008375"
    ]
},
  "bbox": [],
  "geometry": {"coordinates":[-97.333333,17.533333],"type":"Point"}
}