<<<<<<< HEAD
{
  "id": 7482067,
  "type": "Feature",
  "properties": {
    "tgn:hierarchy":[
        "tgn:7482067",
        "tgn:1000004",
        "tgn:7492971",
        "tgn:1000141",
        "tgn:7029392"
    ],
    "tgn:id":7482067,
    "tgn:name":"Fuju Qiao",
    "tgn:placetype":[
        "aat:300007836"
    ]
},
  "bbox": [],
  "geometry": {"coordinates":[120.574935,22.62226],"type":"Point"}
}
=======
{"geometry":{"type":"Point","coordinates":[120.574935,22.622260]},"type":"Feature","properties":{"hierarchy":["tgn:7482067","tgn:1000004","tgn:7492971","tgn:1000141","tgn:7029392"],"placetype":["aat:300007836"],"id":7482067,"name:xx":"Fuju Qiao"}}
>>>>>>> 03f74aca74312dbeaf24d7e61306dd6a786dc3d0
