{
  "id": 2395769,
  "type": "Feature",
  "properties": {
    "tgn:hierarchy":[
        "tgn:2395769",
        "tgn:1000001",
        "tgn:7012149",
        "tgn:1002797",
        "tgn:7007706",
        "tgn:7029392"
    ],
    "tgn:id":2395769,
    "tgn:name":"Hollow Lakes",
    "tgn:placetype":[
        "aat:300008680"
    ]
},
  "bbox": [],
  "geometry": {"coordinates":[-81.25,41.25],"type":"Point"}
}