{
  "id": 2492952,
  "type": "Feature",
  "properties": {
    "tgn:hierarchy":[
        "tgn:2492952",
        "tgn:1000001",
        "tgn:7012149",
        "tgn:7014318",
        "tgn:7007568",
        "tgn:7029392"
    ],
    "tgn:id":2492952,
    "tgn:name":"Markham, Mount",
    "tgn:placetype":[
        "aat:300008798"
    ]
},
  "bbox": [],
  "geometry": {"coordinates":[-75.2167,42.8333],"type":"Point"}
}