{
  "id": 7519703,
  "type": "Feature",
  "properties": {
    "tgn:hierarchy":[
        "tgn:7519703",
        "tgn:1009227",
        "tgn:1000226",
        "tgn:1000006",
        "tgn:7016850",
        "tgn:7029392"
    ],
    "tgn:id":7519703,
    "tgn:name:en":"Blackwater River",
    "tgn:placetype":[
        "aat:300008699"
    ]
},
  "bbox": [],
  "geometry": {"coordinates":[169.533333,-43.683333],"type":"Point"}
}