{
  "id": 2484514,
  "type": "Feature",
  "properties": {
    "tgn:hierarchy":[
        "tgn:2484514",
        "tgn:1000001",
        "tgn:7012149",
        "tgn:2000805",
        "tgn:7007255",
        "tgn:7029392"
    ],
    "tgn:id":2484514,
    "tgn:name":"Laurel Fork Quicksand Creek",
    "tgn:placetype":[
        "aat:300008706"
    ]
},
  "bbox": [],
  "geometry": {"coordinates":[-82.9167,37.4167],"type":"Point"}
}