{
  "id": 7297394,
  "type": "Feature",
  "properties": {
    "tgn:hierarchy":[
        "tgn:7297394",
        "tgn:7002836",
        "tgn:7016622",
        "tgn:1000003",
        "tgn:1000095",
        "tgn:7029392"
    ],
    "tgn:id":7297394,
    "tgn:name":"Tacor\u00f3n, Cala de",
    "tgn:placetype":[
        "aat:300132317"
    ]
},
  "bbox": [],
  "geometry": {"coordinates":[-18.016667,27.683333],"type":"Point"}
}