{
  "id": 2602941,
  "type": "Feature",
  "properties": {
    "tgn:hierarchy":[
        "tgn:2602941",
        "tgn:1000001",
        "tgn:7016172",
        "tgn:7012149",
        "tgn:2000153",
        "tgn:7029392"
    ],
    "tgn:id":2602941,
    "tgn:name":"Qualls Creek",
    "tgn:placetype":[
        "aat:300008706"
    ]
},
  "bbox": [],
  "geometry": {"coordinates":[-93.5667,34.6833],"type":"Point"}
}