{
  "id": 7473294,
  "type": "Feature",
  "properties": {
    "tgn:hierarchy":[
        "tgn:7473294",
        "tgn:1000004",
        "tgn:1000959",
        "tgn:1000141",
        "tgn:7029392"
    ],
    "tgn:id":7473294,
    "tgn:name":"Yinhedong",
    "tgn:placetype":[
        "aat:300008347"
    ]
},
  "bbox": [],
  "geometry": {"coordinates":[121.585205,24.960927],"type":"Point"}
}