{
  "id": 7493493,
  "type": "Feature",
  "properties": {
    "tgn:hierarchy":[
        "tgn:7493493",
        "tgn:7001010",
        "tgn:1000004",
        "tgn:1000141",
        "tgn:7029392"
    ],
    "tgn:id":7493493,
    "tgn:name":"Nanbeilu",
    "tgn:placetype":[
        "aat:300008347"
    ]
},
  "bbox": [],
  "geometry": {"coordinates":[121.265232,23.157375],"type":"Point"}
}