{
  "id": 2456207,
  "type": "Feature",
  "properties": {
    "tgn:hierarchy":[
        "tgn:2456207",
        "tgn:1000001",
        "tgn:2000457",
        "tgn:7012149",
        "tgn:7007250",
        "tgn:7029392"
    ],
    "tgn:id":2456207,
    "tgn:name":"Little Hole",
    "tgn:placetype":[
        "aat:300132316"
    ]
},
  "bbox": [],
  "geometry": {"coordinates":[-112.7833,42.9167],"type":"Point"}
}