{
  "id": 1068811,
  "type": "Feature",
  "properties": {
    "tgn:hierarchy":[
        "tgn:1068811",
        "tgn:1000004",
        "tgn:7002081",
        "tgn:1000111",
        "tgn:7029392"
    ],
    "tgn:id":1068811,
    "tgn:name":"Houcheng",
    "tgn:placetype":[
        "aat:300008347"
    ]
},
  "bbox": [],
  "geometry": {"coordinates":[120.45,31.9167],"type":"Point"}
}