{
  "id": 2452645,
  "type": "Feature",
  "properties": {
    "tgn:hierarchy":[
        "tgn:2452645",
        "tgn:1000001",
        "tgn:2000313",
        "tgn:7012149",
        "tgn:7007248",
        "tgn:7029392"
    ],
    "tgn:id":2452645,
    "tgn:name":"Little Buck Creek",
    "tgn:placetype":[
        "aat:300008706"
    ]
},
  "bbox": [],
  "geometry": {"coordinates":[-85.1333,33.6667],"type":"Point"}
}