{
  "id": 7550553,
  "type": "Feature",
  "properties": {
    "tgn:hierarchy":[
        "tgn:7550553",
        "tgn:1000004",
        "tgn:7000198",
        "tgn:1001894",
        "tgn:7029392"
    ],
    "tgn:id":7550553,
    "tgn:name:en":"Bichia Nad\u012b",
    "tgn:placetype":[
        "aat:300008699"
    ]
},
  "bbox": [],
  "geometry": {"coordinates":[81.290256,24.521595],"type":"Point"}
}