{
  "id": 7263370,
  "type": "Feature",
  "properties": {
    "tgn:hierarchy":[
        "tgn:7263370",
        "tgn:1000003",
        "tgn:7003622",
        "tgn:7016845",
        "tgn:7029392"
    ],
    "tgn:id":7263370,
    "tgn:name:nl":"Diepe Leng",
    "tgn:placetype":[
        "aat:300008699"
    ]
},
  "bbox": [],
  "geometry": {"coordinates":[6.05,51.483333],"type":"Point"}
}