{
  "id": 7401327,
  "type": "Feature",
  "properties": {
    "tgn:hierarchy":[
        "tgn:7401327",
        "tgn:1000001",
        "tgn:7005599",
        "tgn:7005560",
        "tgn:7029392"
    ],
    "tgn:id":7401327,
    "tgn:name":"El Manantial",
    "tgn:placetype":[
        "aat:300008347"
    ]
},
  "bbox": [],
  "geometry": {"coordinates":[-98.241667,21.9625],"type":"Point"}
}