{
  "id": 2232192,
  "type": "Feature",
  "properties": {
    "tgn:hierarchy":[
        "tgn:2232192",
        "tgn:7002659",
        "tgn:1000001",
        "tgn:7012149",
        "tgn:2000047",
        "tgn:7029392"
    ],
    "tgn:id":2232192,
    "tgn:name":"Chandler Branch",
    "tgn:placetype":[
        "aat:300008699"
    ]
},
  "bbox": [],
  "geometry": {"coordinates":[-86.2333,34.4833],"type":"Point"}
}