{
  "id": 2531116,
  "type": "Feature",
  "properties": {
    "tgn:hierarchy":[
        "tgn:2531116",
        "tgn:1000001",
        "tgn:7012149",
        "tgn:2001538",
        "tgn:7007709",
        "tgn:7029392"
    ],
    "tgn:id":2531116,
    "tgn:name":"Mulatto Branch",
    "tgn:placetype":[
        "aat:300008699"
    ]
},
  "bbox": [],
  "geometry": {"coordinates":[-78.5167,34.95],"type":"Point"}
}