{
  "id": 2276295,
  "type": "Feature",
  "properties": {
    "tgn:hierarchy":[
        "tgn:2276295",
        "tgn:1000001",
        "tgn:7012149",
        "tgn:2002282",
        "tgn:7013961",
        "tgn:7029392"
    ],
    "tgn:id":2276295,
    "tgn:name":"Daugherty Mountain",
    "tgn:placetype":[
        "aat:300008798"
    ]
},
  "bbox": [],
  "geometry": {"coordinates":[-80.3667,37.6333],"type":"Point"}
}