{
  "id": 2047279,
  "type": "Feature",
  "properties": {
    "tgn:hierarchy":[
        "tgn:2047279",
        "tgn:1002234",
        "tgn:1000001",
        "tgn:7012149",
        "tgn:7007516",
        "tgn:7029392"
    ],
    "tgn:id":2047279,
    "tgn:name":"Goldsboro",
    "tgn:placetype":[
        "aat:300008347"
    ]
},
  "bbox": [],
  "geometry": {"coordinates":[-75.7833,39.0333],"type":"Point"}
}