{
  "id": 2543322,
  "type": "Feature",
  "properties": {
    "tgn:hierarchy":[
        "tgn:2543322",
        "tgn:1002338",
        "tgn:1000001",
        "tgn:7012149",
        "tgn:7007516",
        "tgn:7029392"
    ],
    "tgn:id":2543322,
    "tgn:name":"Norman Cove Creek",
    "tgn:placetype":[
        "aat:300008706"
    ]
},
  "bbox": [],
  "geometry": {"coordinates":[-76.05,38.25],"type":"Point"}
}