{
  "id": 2183720,
  "type": "Feature",
  "properties": {
    "tgn:hierarchy":[
        "tgn:2183720",
        "tgn:1000001",
        "tgn:7012149",
        "tgn:1002959",
        "tgn:7007826",
        "tgn:7029392"
    ],
    "tgn:id":2183720,
    "tgn:name":"Boar Branch",
    "tgn:placetype":[
        "aat:300008699"
    ]
},
  "bbox": [],
  "geometry": {"coordinates":[-94.3333,30.8833],"type":"Point"}
}