{
  "id": 2397824,
  "type": "Feature",
  "properties": {
    "tgn:hierarchy":[
        "tgn:2397824",
        "tgn:1000001",
        "tgn:7012149",
        "tgn:1002873",
        "tgn:7007568",
        "tgn:7029392"
    ],
    "tgn:id":2397824,
    "tgn:name":"Hony Hill",
    "tgn:placetype":[
        "aat:300008798"
    ]
},
  "bbox": [],
  "geometry": {"coordinates":[-74.3167,42.5667],"type":"Point"}
}