{
  "id": 2307547,
  "type": "Feature",
  "properties": {
    "tgn:hierarchy":[
        "tgn:2307547",
        "tgn:1000001",
        "tgn:7012149",
        "tgn:7007157",
        "tgn:1002857",
        "tgn:7029392"
    ],
    "tgn:id":2307547,
    "tgn:name":"East Fork South Fork Whitewater River",
    "tgn:placetype":[
        "aat:300008707"
    ]
},
  "bbox": [],
  "geometry": {"coordinates":[-116.8167,34.0833],"type":"Point"}
}