{
  "id": 2651029,
  "type": "Feature",
  "properties": {
    "tgn:hierarchy":[
        "tgn:2651029",
        "tgn:1000001",
        "tgn:7012149",
        "tgn:2000928",
        "tgn:7007515",
        "tgn:7029392"
    ],
    "tgn:id":2651029,
    "tgn:name":"Second Ridge",
    "tgn:placetype":[
        "aat:300266640"
    ]
},
  "bbox": [],
  "geometry": {"coordinates":[-69.3667,46.3667],"type":"Point"}
}