{
  "id": 7505020,
  "type": "Feature",
  "properties": {
    "tgn:hierarchy":[
        "tgn:7505020",
        "tgn:7016670",
        "tgn:1008380",
        "tgn:1000226",
        "tgn:1000006",
        "tgn:7029392"
    ],
    "tgn:id":7505020,
    "tgn:name:en":"Ahuriri Village",
    "tgn:placetype":[
        "aat:300008347"
    ]
},
  "bbox": [],
  "geometry": {"coordinates":[177.861944,-39.248889],"type":"Point"}
}