{
  "id": 7090445,
  "type": "Feature",
  "properties": {
    "tgn:hierarchy":[
        "tgn:7090445",
        "tgn:7003692",
        "tgn:1000003",
        "tgn:7000084",
        "tgn:7029392"
    ],
    "tgn:id":7090445,
    "tgn:name":"Vogt",
    "tgn:placetype":[
        "aat:300008347"
    ]
},
  "bbox": [],
  "geometry": {"coordinates":[9.766667,47.766667],"type":"Point"}
}