{
  "id": 2500673,
  "type": "Feature",
  "properties": {
    "tgn:hierarchy":[
        "tgn:2500673",
        "tgn:1000001",
        "tgn:7006451",
        "tgn:7012149",
        "tgn:7029392"
    ],
    "tgn:id":2500673,
    "tgn:name":"McDougal Wash",
    "tgn:placetype":[
        "aat:300008699"
    ]
},
  "bbox": [],
  "geometry": {"coordinates":[-110.6167,33.1167],"type":"Point"}
}