{
  "id": 2690170,
  "type": "Feature",
  "properties": {
    "tgn:hierarchy":[
        "tgn:2690170",
        "tgn:1000001",
        "tgn:2001360",
        "tgn:7012149",
        "tgn:7007525",
        "tgn:7029392"
    ],
    "tgn:id":2690170,
    "tgn:name":"Stafford",
    "tgn:placetype":[
        "aat:300008347"
    ]
},
  "bbox": [],
  "geometry": {"coordinates":[-98.4333,42.3167],"type":"Point"}
}