{
  "id": 2547202,
  "type": "Feature",
  "properties": {
    "tgn:hierarchy":[
        "tgn:2547202",
        "tgn:1000001",
        "tgn:7012149",
        "tgn:2001716",
        "tgn:7007708",
        "tgn:7029392"
    ],
    "tgn:id":2547202,
    "tgn:name":"North Fork Rock Creek",
    "tgn:placetype":[
        "aat:300008706"
    ]
},
  "bbox": [],
  "geometry": {"coordinates":[-122.9833,43.65],"type":"Point"}
}