{
  "id": 7548303,
  "type": "Feature",
  "properties": {
    "tgn:hierarchy":[
        "tgn:7548303",
        "tgn:1000004",
        "tgn:7000198",
        "tgn:7016788",
        "tgn:7029392"
    ],
    "tgn:id":7548303,
    "tgn:name:en":"Bapaur",
    "tgn:placetype":[
        "aat:300008347"
    ]
},
  "bbox": [],
  "geometry": {"coordinates":[76.432871,24.926635],"type":"Point"}
}