<<<<<<< HEAD
{
  "id": 7028975,
  "type": "Feature",
  "properties": {
    "tgn:hierarchy":[
        "tgn:7028975",
        "tgn:7002445",
        "tgn:1000003",
        "tgn:7019057",
        "tgn:7008591",
        "tgn:7029392"
    ],
    "tgn:id":7028975,
    "tgn:name":"Foggathorpe",
    "tgn:placetype":[
        "aat:300008347",
        "aat:300008372"
    ]
},
  "bbox": [],
  "geometry": {"coordinates":[-0.866667,53.816667],"type":"Point"}
}
=======
{"geometry":{"type":"Point","coordinates":[-0.866667,53.816667]},"type":"Feature","properties":{"hierarchy":["tgn:7028975","tgn:7002445","tgn:1000003","tgn:7019057","tgn:7008591","tgn:7029392"],"placetype":["aat:300008347","aat:300008372"],"id":7028975,"name:xx":"Foggathorpe"}}
>>>>>>> 03f74aca74312dbeaf24d7e61306dd6a786dc3d0
