{
  "id": 2756773,
  "type": "Feature",
  "properties": {
    "tgn:hierarchy":[
        "tgn:2756773",
        "tgn:1000001",
        "tgn:7012149",
        "tgn:1002613",
        "tgn:7007710",
        "tgn:7029392"
    ],
    "tgn:id":2756773,
    "tgn:name":"Wells Mountain, The",
    "tgn:placetype":[
        "aat:300008798"
    ]
},
  "bbox": [],
  "geometry": {"coordinates":[-76.9667,41.3667],"type":"Point"}
}