<<<<<<< HEAD
{
  "id": 2256846,
  "type": "Feature",
  "properties": {
    "tgn:hierarchy":[
        "tgn:2256846",
        "tgn:1000001",
        "tgn:7006451",
        "tgn:7012149",
        "tgn:2000098",
        "tgn:7029392"
    ],
    "tgn:id":2256846,
    "tgn:name":"Cork Spring",
    "tgn:placetype":[
        "aat:300008697"
    ]
},
  "bbox": [],
  "geometry": {"coordinates":[-112.7833,36.3167],"type":"Point"}
}
=======
{"geometry":{"type":"Point","coordinates":[-112.783300,36.316700]},"type":"Feature","properties":{"hierarchy":["tgn:2256846","tgn:1000001","tgn:7006451","tgn:7012149","tgn:2000098","tgn:7029392"],"placetype":["aat:300008697"],"id":2256846,"name:xx":"Cork Spring"}}
>>>>>>> 03f74aca74312dbeaf24d7e61306dd6a786dc3d0
