<<<<<<< HEAD
{
  "id": 7172980,
  "type": "Feature",
  "properties": {
    "tgn:hierarchy":[
        "tgn:7172980",
        "tgn:1000003",
        "tgn:7003685",
        "tgn:7000084",
        "tgn:7029392"
    ],
    "tgn:id":7172980,
    "tgn:name":"Gro\u00dfschlaisdorf",
    "tgn:placetype":[
        "aat:300008347"
    ]
},
  "bbox": [],
  "geometry": {"coordinates":[12.75,50.966667],"type":"Point"}
}
=======
{"geometry":{"type":"Point","coordinates":[12.750000,50.966667]},"type":"Feature","properties":{"hierarchy":["tgn:7172980","tgn:1000003","tgn:7003685","tgn:7000084","tgn:7029392"],"placetype":["aat:300008347"],"id":7172980,"name:xx":"Gro\u00dfschlaisdorf"}}
>>>>>>> 03f74aca74312dbeaf24d7e61306dd6a786dc3d0
