{
  "id": 7431261,
  "type": "Feature",
  "properties": {
    "tgn:hierarchy":[
        "tgn:7431261",
        "tgn:7005581",
        "tgn:1000001",
        "tgn:7005560",
        "tgn:7029392"
    ],
    "tgn:id":7431261,
    "tgn:name":"Aserradero Mohinora",
    "tgn:placetype":[
        "aat:300008347"
    ]
},
  "bbox": [],
  "geometry": {"coordinates":[-107.05,25.966667],"type":"Point"}
}