{
  "id": 7385186,
  "type": "Feature",
  "properties": {
    "tgn:hierarchy":[
        "tgn:7385186",
        "tgn:1000001",
        "tgn:1001893",
        "tgn:7005560",
        "tgn:7029392"
    ],
    "tgn:id":7385186,
    "tgn:name":"Nichi",
    "tgn:placetype":[
        "aat:300008347"
    ]
},
  "bbox": [],
  "geometry": {"coordinates":[-100.066667,19.65],"type":"Point"}
}