{
  "id": 2432788,
  "type": "Feature",
  "properties": {
    "tgn:hierarchy":[
        "tgn:2432788",
        "tgn:1000001",
        "tgn:2002261",
        "tgn:7012149",
        "tgn:7013961",
        "tgn:7029392"
    ],
    "tgn:id":2432788,
    "tgn:name":"Keeney Creek",
    "tgn:placetype":[
        "aat:300008706"
    ]
},
  "bbox": [],
  "geometry": {"coordinates":[-80.95,38.0333],"type":"Point"}
}