<<<<<<< HEAD
{
  "id": 7489616,
  "type": "Feature",
  "properties": {
    "tgn:hierarchy":[
        "tgn:7489616",
        "tgn:1000004",
        "tgn:7001013",
        "tgn:1000141",
        "tgn:7029392"
    ],
    "tgn:id":7489616,
    "tgn:name":"Rugushan",
    "tgn:placetype":[
        "aat:300008795"
    ]
},
  "bbox": [],
  "geometry": {"coordinates":[121.184444,24.867222],"type":"Point"}
}
=======
{"geometry":{"type":"Point","coordinates":[121.184444,24.867222]},"type":"Feature","properties":{"hierarchy":["tgn:7489616","tgn:1000004","tgn:7001013","tgn:1000141","tgn:7029392"],"placetype":["aat:300008795"],"id":7489616,"name:xx":"Rugushan"}}
>>>>>>> 03f74aca74312dbeaf24d7e61306dd6a786dc3d0
