{
  "id": 7474629,
  "type": "Feature",
  "properties": {
    "tgn:hierarchy":[
        "tgn:7474629",
        "tgn:1000004",
        "tgn:7467799",
        "tgn:1000141",
        "tgn:7029392"
    ],
    "tgn:id":7474629,
    "tgn:name":"Fanxing Qiao",
    "tgn:placetype":[
        "aat:300007836"
    ]
},
  "bbox": [],
  "geometry": {"coordinates":[120.371854,23.866539],"type":"Point"}
}