<<<<<<< HEAD
{
  "id": 7474629,
  "type": "Feature",
  "properties": {
    "tgn:hierarchy":[
        "tgn:7474629",
        "tgn:1000004",
        "tgn:7467799",
        "tgn:1000141",
        "tgn:7029392"
    ],
    "tgn:id":7474629,
    "tgn:name":"Fanxing Qiao",
    "tgn:placetype":[
        "aat:300007836"
    ]
},
  "bbox": [],
  "geometry": {"coordinates":[120.371854,23.866539],"type":"Point"}
}
=======
{"geometry":{"type":"Point","coordinates":[120.371854,23.866539]},"type":"Feature","properties":{"hierarchy":["tgn:7474629","tgn:1000004","tgn:7467799","tgn:1000141","tgn:7029392"],"placetype":["aat:300007836"],"id":7474629,"name:xx":"Fanxing Qiao"}}
>>>>>>> 03f74aca74312dbeaf24d7e61306dd6a786dc3d0
