{
  "id": 2035369,
  "type": "Feature",
  "properties": {
    "tgn:hierarchy":[
        "tgn:2035369",
        "tgn:1000001",
        "tgn:7012149",
        "tgn:2000618",
        "tgn:7007253",
        "tgn:7029392"
    ],
    "tgn:id":2035369,
    "tgn:name":"Oakville",
    "tgn:placetype":[
        "aat:300008347"
    ]
},
  "bbox": [],
  "geometry": {"coordinates":[-91.0333,41.0833],"type":"Point"}
}