<<<<<<< HEAD
{
  "id": 7475481,
  "type": "Feature",
  "properties": {
    "tgn:hierarchy":[
        "tgn:7475481",
        "tgn:1000004",
        "tgn:7001014",
        "tgn:1000141",
        "tgn:7029392"
    ],
    "tgn:id":7475481,
    "tgn:name":"Wutu Yihao Qiao",
    "tgn:placetype":[
        "aat:300007836"
    ]
},
  "bbox": [],
  "geometry": {"coordinates":[120.598449,23.765388],"type":"Point"}
}
=======
{"geometry":{"type":"Point","coordinates":[120.598449,23.765388]},"type":"Feature","properties":{"hierarchy":["tgn:7475481","tgn:1000004","tgn:7001014","tgn:1000141","tgn:7029392"],"placetype":["aat:300007836"],"id":7475481,"name:xx":"Wutu Yihao Qiao"}}
>>>>>>> 03f74aca74312dbeaf24d7e61306dd6a786dc3d0
