{
  "id": 7475481,
  "type": "Feature",
  "properties": {
    "tgn:hierarchy":[
        "tgn:7475481",
        "tgn:1000004",
        "tgn:7001014",
        "tgn:1000141",
        "tgn:7029392"
    ],
    "tgn:id":7475481,
    "tgn:name":"Wutu Yihao Qiao",
    "tgn:placetype":[
        "aat:300007836"
    ]
},
  "bbox": [],
  "geometry": {"coordinates":[120.598449,23.765388],"type":"Point"}
}