{
  "id": 7512267,
  "type": "Feature",
  "properties": {
    "tgn:hierarchy":[
        "tgn:7512267",
        "tgn:1009227",
        "tgn:1000226",
        "tgn:1000006",
        "tgn:7016850",
        "tgn:7029392"
    ],
    "tgn:id":7512267,
    "tgn:name:en":"Inframeta",
    "tgn:placetype":[
        "aat:300008798"
    ]
},
  "bbox": [],
  "geometry": {"coordinates":[171.066667,-43.033333],"type":"Point"}
}