{
  "id": 2671328,
  "type": "Feature",
  "properties": {
    "tgn:hierarchy":[
        "tgn:2671328",
        "tgn:1000001",
        "tgn:7019982",
        "tgn:7012149",
        "tgn:7007517",
        "tgn:7029392"
    ],
    "tgn:id":2671328,
    "tgn:name":"Smith Hill",
    "tgn:placetype":[
        "aat:300008798"
    ]
},
  "bbox": [],
  "geometry": {"coordinates":[-72.9167,42.3333],"type":"Point"}
}