{
  "id": 2102472,
  "type": "Feature",
  "properties": {
    "tgn:hierarchy":[
        "tgn:2102472",
        "tgn:1000001",
        "tgn:7012149",
        "tgn:2002024",
        "tgn:7007826",
        "tgn:7029392"
    ],
    "tgn:id":2102472,
    "tgn:name":"Atlas",
    "tgn:placetype":[
        "aat:300008347"
    ]
},
  "bbox": [],
  "geometry": {"coordinates":[-95.6167,33.5667],"type":"Point"}
}