{
  "id": 2516740,
  "type": "Feature",
  "properties": {
    "tgn:hierarchy":[
        "tgn:2516740",
        "tgn:1000001",
        "tgn:7012149",
        "tgn:1002814",
        "tgn:7007568",
        "tgn:7029392"
    ],
    "tgn:id":2516740,
    "tgn:name":"Miners Hill",
    "tgn:placetype":[
        "aat:300008798"
    ]
},
  "bbox": [],
  "geometry": {"coordinates":[-74.5833,44.5667],"type":"Point"}
}