{
  "id": 2073489,
  "type": "Feature",
  "properties": {
    "tgn:hierarchy":[
        "tgn:2073489",
        "tgn:1000001",
        "tgn:2001485",
        "tgn:7012149",
        "tgn:7007709",
        "tgn:7029392"
    ],
    "tgn:id":2073489,
    "tgn:name":"Artesia",
    "tgn:placetype":[
        "aat:300008347",
        "aat:300387210"
    ]
},
  "bbox": [],
  "geometry": {"coordinates":[-78.5667,34.3167],"type":"Point"}
}