{
  "id": 2511451,
  "type": "Feature",
  "properties": {
    "tgn:hierarchy":[
        "tgn:2511451",
        "tgn:1000001",
        "tgn:7012149",
        "tgn:2000278",
        "tgn:7007240",
        "tgn:7029392"
    ],
    "tgn:id":2511451,
    "tgn:name":"Mile Branch",
    "tgn:placetype":[
        "aat:300008699"
    ]
},
  "bbox": [],
  "geometry": {"coordinates":[-84.75,30.3333],"type":"Point"}
}