{
  "id": 7163609,
  "type": "Feature",
  "properties": {
    "tgn:hierarchy":[
        "tgn:7163609",
        "tgn:7003669",
        "tgn:1000003",
        "tgn:7000084",
        "tgn:7029392"
    ],
    "tgn:id":7163609,
    "tgn:name":"H\u00fcssbach",
    "tgn:placetype":[
        "aat:300008699"
    ]
},
  "bbox": [],
  "geometry": {"coordinates":[10.483333,49.616667],"type":"Point"}
}