{
  "id": 2426691,
  "type": "Feature",
  "properties": {
    "tgn:hierarchy":[
        "tgn:2426691",
        "tgn:1000001",
        "tgn:7012149",
        "tgn:2001298",
        "tgn:7007524",
        "tgn:7029392"
    ],
    "tgn:id":2426691,
    "tgn:name":"Jones Lake",
    "tgn:placetype":[
        "aat:300008680"
    ]
},
  "bbox": [],
  "geometry": {"coordinates":[-113.1333,47.0333],"type":"Point"}
}