<<<<<<< HEAD
{
  "id": 7111585,
  "type": "Feature",
  "properties": {
    "tgn:hierarchy":[
        "tgn:7111585",
        "tgn:7003669",
        "tgn:1000003",
        "tgn:7000084",
        "tgn:7029392"
    ],
    "tgn:id":7111585,
    "tgn:name":"R\u00f6hrl-Bach",
    "tgn:placetype":[
        "aat:300008699"
    ]
},
  "bbox": [],
  "geometry": {"coordinates":[11.366667,48.016667],"type":"Point"}
}
=======
{"geometry":{"type":"Point","coordinates":[11.366667,48.016667]},"type":"Feature","properties":{"hierarchy":["tgn:7111585","tgn:7003669","tgn:1000003","tgn:7000084","tgn:7029392"],"placetype":["aat:300008699"],"id":7111585,"name:xx":"R\u00f6hrl-Bach"}}
>>>>>>> 03f74aca74312dbeaf24d7e61306dd6a786dc3d0
