{
  "id": 7292748,
  "type": "Feature",
  "properties": {
    "tgn:hierarchy":[
        "tgn:7292748",
        "tgn:1001623",
        "tgn:1000049",
        "tgn:1000002",
        "tgn:7029392"
    ],
    "tgn:id":7292748,
    "tgn:name":"Eva, Punta",
    "tgn:placetype":[
        "aat:300386846"
    ]
},
  "bbox": [],
  "geometry": {"coordinates":[-74.35,-47.816667],"type":"Point"}
}