{
  "id": 7477658,
  "type": "Feature",
  "properties": {
    "tgn:hierarchy":[
        "tgn:7477658",
        "tgn:1000004",
        "tgn:1000454",
        "tgn:1000141",
        "tgn:7029392"
    ],
    "tgn:id":7477658,
    "tgn:name":"Kengnei Xi",
    "tgn:placetype":[
        "aat:300008699"
    ]
},
  "bbox": [],
  "geometry": {"coordinates":[121.991005,25.011969],"type":"Point"}
}