{
  "id": 2142976,
  "type": "Feature",
  "properties": {
    "tgn:hierarchy":[
        "tgn:2142976",
        "tgn:1000001",
        "tgn:7012149",
        "tgn:7007522",
        "tgn:7029392"
    ],
    "tgn:id":2142976,
    "tgn:name":"Bagasha Creek",
    "tgn:placetype":[
        "aat:300008706"
    ]
},
  "bbox": [],
  "geometry": {"coordinates":[-89.5833,33.2833],"type":"Point"}
}