<<<<<<< HEAD
{
  "id": 7367565,
  "type": "Feature",
  "properties": {
    "tgn:hierarchy":[
        "tgn:7367565",
        "tgn:1000001",
        "tgn:7005592",
        "tgn:7005560",
        "tgn:7029392"
    ],
    "tgn:id":7367565,
    "tgn:name":"El Salado",
    "tgn:placetype":[
        "aat:300008347"
    ]
},
  "bbox": [],
  "geometry": {"coordinates":[-98.966667,18.358333],"type":"Point"}
}
=======
{"geometry":{"type":"Point","coordinates":[-98.966667,18.358333]},"type":"Feature","properties":{"hierarchy":["tgn:7367565","tgn:1000001","tgn:7005592","tgn:7005560","tgn:7029392"],"placetype":["aat:300008347"],"id":7367565,"name:xx":"El Salado"}}
>>>>>>> 03f74aca74312dbeaf24d7e61306dd6a786dc3d0
