{
  "id": 2578934,
  "type": "Feature",
  "properties": {
    "tgn:hierarchy":[
        "tgn:2578934",
        "tgn:1000001",
        "tgn:2002109",
        "tgn:7012149",
        "tgn:7007827",
        "tgn:7029392"
    ],
    "tgn:id":2578934,
    "tgn:name":"Philo, Lake",
    "tgn:placetype":[
        "aat:300008680"
    ]
},
  "bbox": [],
  "geometry": {"coordinates":[-111.7333,38.0333],"type":"Point"}
}