{
  "id": 7385565,
  "type": "Feature",
  "properties": {
    "tgn:hierarchy":[
        "tgn:7385565",
        "tgn:1000001",
        "tgn:7005589",
        "tgn:7005560",
        "tgn:7029392"
    ],
    "tgn:id":7385565,
    "tgn:name":"Palo Blanco",
    "tgn:placetype":[
        "aat:300008347"
    ]
},
  "bbox": [],
  "geometry": {"coordinates":[-100.583333,24.05],"type":"Point"}
}