{
  "id": 2019223,
  "type": "Feature",
  "properties": {
    "tgn:hierarchy":[
        "tgn:2019223",
        "tgn:1000001",
        "tgn:7012149",
        "tgn:1002314",
        "tgn:7007240",
        "tgn:7029392"
    ],
    "tgn:id":2019223,
    "tgn:name":"El Portal",
    "tgn:placetype":[
        "aat:300008347"
    ]
},
  "bbox": [],
  "geometry": {"coordinates":[-80.1833,25.85],"type":"Point"}
}