<<<<<<< HEAD
{
  "id": 2404892,
  "type": "Feature",
  "properties": {
    "tgn:hierarchy":[
        "tgn:2404892",
        "tgn:2002137",
        "tgn:1000001",
        "tgn:7012149",
        "tgn:7007919",
        "tgn:7029392"
    ],
    "tgn:id":2404892,
    "tgn:name":"Huckles Pond",
    "tgn:placetype":[
        "aat:300006191"
    ]
},
  "bbox": [],
  "geometry": {"coordinates":[-78.4667,38.1667],"type":"Point"}
}
=======
{"geometry":{"type":"Point","coordinates":[-78.466700,38.166700]},"type":"Feature","properties":{"hierarchy":["tgn:2404892","tgn:2002137","tgn:1000001","tgn:7012149","tgn:7007919","tgn:7029392"],"placetype":["aat:300006191"],"id":2404892,"name:xx":"Huckles Pond"}}
>>>>>>> 03f74aca74312dbeaf24d7e61306dd6a786dc3d0
