{
  "id": 2404892,
  "type": "Feature",
  "properties": {
    "tgn:hierarchy":[
        "tgn:2404892",
        "tgn:2002137",
        "tgn:1000001",
        "tgn:7012149",
        "tgn:7007919",
        "tgn:7029392"
    ],
    "tgn:id":2404892,
    "tgn:name":"Huckles Pond",
    "tgn:placetype":[
        "aat:300006191"
    ]
},
  "bbox": [],
  "geometry": {"coordinates":[-78.4667,38.1667],"type":"Point"}
}