{
  "id": 2059197,
  "type": "Feature",
  "properties": {
    "tgn:hierarchy":[
        "tgn:2059197",
        "tgn:1000001",
        "tgn:7012149",
        "tgn:2001241",
        "tgn:7007523",
        "tgn:7029392"
    ],
    "tgn:id":2059197,
    "tgn:name":"Iron Mountain",
    "tgn:placetype":[
        "aat:300008347"
    ]
},
  "bbox": [],
  "geometry": {"coordinates":[-90.6333,37.6833],"type":"Point"}
}