{
  "id": 7513270,
  "type": "Feature",
  "properties": {
    "tgn:hierarchy":[
        "tgn:7513270",
        "tgn:1008380",
        "tgn:7520093",
        "tgn:1000226",
        "tgn:1000006",
        "tgn:7029392"
    ],
    "tgn:id":7513270,
    "tgn:name:en":"Grant",
    "tgn:placetype":[
        "aat:300008795"
    ]
},
  "bbox": [],
  "geometry": {"coordinates":[175.916667,-40.683333],"type":"Point"}
}