{
  "id": 2097140,
  "type": "Feature",
  "properties": {
    "tgn:hierarchy":[
        "tgn:2097140",
        "tgn:1000001",
        "tgn:2001781",
        "tgn:7012149",
        "tgn:7007713",
        "tgn:7029392"
    ],
    "tgn:id":2097140,
    "tgn:name":"Dante",
    "tgn:placetype":[
        "aat:300008347"
    ]
},
  "bbox": [],
  "geometry": {"coordinates":[-98.1833,43.0333],"type":"Point"}
}