{
  "id": 2451690,
  "type": "Feature",
  "properties": {
    "tgn:hierarchy":[
        "tgn:2451690",
        "tgn:1000001",
        "tgn:2002107",
        "tgn:7012149",
        "tgn:7007827",
        "tgn:7029392"
    ],
    "tgn:id":2451690,
    "tgn:name":"Little Bear Hollow",
    "tgn:placetype":[
        "aat:300008761"
    ]
},
  "bbox": [],
  "geometry": {"coordinates":[-110.8833,40.35],"type":"Point"}
}