{
  "id": 7575368,
  "type": "Feature",
  "properties": {
    "tgn:hierarchy":[
        "tgn:7575368",
        "tgn:1000004",
        "tgn:7000198",
        "tgn:7016722",
        "tgn:7029392"
    ],
    "tgn:id":7575368,
    "tgn:name:en":"Keol\u0101ri Nad\u012b",
    "tgn:placetype":[
        "aat:300008699"
    ]
},
  "bbox": [],
  "geometry": {"coordinates":[79.507186,25.481047],"type":"Point"}
}