{
  "id": 2575712,
  "type": "Feature",
  "properties": {
    "tgn:hierarchy":[
        "tgn:2575712",
        "tgn:1000001",
        "tgn:7012149",
        "tgn:2000977",
        "tgn:7007520",
        "tgn:7029392"
    ],
    "tgn:id":2575712,
    "tgn:name":"Perch Lake",
    "tgn:placetype":[
        "aat:300008680"
    ]
},
  "bbox": [],
  "geometry": {"coordinates":[-85.25,43.6333],"type":"Point"}
}