{
  "id": 1057215,
  "type": "Feature",
  "properties": {
    "tgn:hierarchy":[
        "tgn:1057215",
        "tgn:1000004",
        "tgn:7011600",
        "tgn:7018214",
        "tgn:7002435",
        "tgn:7029392"
    ],
    "tgn:id":1057215,
    "tgn:name":"Muratkovo",
    "tgn:placetype":[
        "aat:300008347"
    ]
},
  "bbox": [],
  "geometry": {"coordinates":[62.3833,58.4333],"type":"Point"}
}