{
  "id": 2510132,
  "type": "Feature",
  "properties": {
    "tgn:hierarchy":[
        "tgn:2510132",
        "tgn:1000001",
        "tgn:7012149",
        "tgn:2000893",
        "tgn:7007256",
        "tgn:7029392"
    ],
    "tgn:id":2510132,
    "tgn:name":"Middle Prairie",
    "tgn:placetype":[
        "aat:300008680"
    ]
},
  "bbox": [],
  "geometry": {"coordinates":[-92.2167,31.4667],"type":"Point"}
}