{
  "id": 7443089,
  "type": "Feature",
  "properties": {
    "tgn:hierarchy":[
        "tgn:7443089",
        "tgn:7002445",
        "tgn:1000003",
        "tgn:7011961",
        "tgn:7008591",
        "tgn:7029392"
    ],
    "tgn:id":7443089,
    "tgn:name:en":"Overcombe",
    "tgn:placetype":[
        "aat:300008347"
    ]
},
  "bbox": [],
  "geometry": {"coordinates":[-2.431944,50.636111],"type":"Point"}
}