{
  "id": 7193389,
  "type": "Feature",
  "properties": {
    "tgn:hierarchy":[
        "tgn:7193389",
        "tgn:7003669",
        "tgn:1000003",
        "tgn:7000084",
        "tgn:7029392"
    ],
    "tgn:id":7193389,
    "tgn:name":"Fella",
    "tgn:placetype":[
        "aat:300008699"
    ]
},
  "bbox": [],
  "geometry": {"coordinates":[9.583333,50.15],"type":"Point"}
}