{
  "id": 1100314,
  "type": "Feature",
  "properties": {
    "tgn:hierarchy":[
        "tgn:1100314",
        "tgn:1001641",
        "tgn:1000003",
        "tgn:7003121",
        "tgn:1000080",
        "tgn:7029392"
    ],
    "tgn:id":1100314,
    "tgn:name":"Monreale, Castello di",
    "tgn:placetype":[
        "aat:300006891"
    ]
},
  "bbox": [],
  "geometry": {"coordinates":[8.8167,39.6333],"type":"Point"}
}