{
  "id": 7036335,
  "type": "Feature",
  "properties": {
    "tgn:hierarchy":[
        "tgn:7036335",
        "tgn:1003506",
        "tgn:1000003",
        "tgn:7002993",
        "tgn:1000080",
        "tgn:7029392"
    ],
    "tgn:id":7036335,
    "tgn:name":"Riulade",
    "tgn:placetype":[
        "aat:300008347"
    ]
},
  "bbox": [],
  "geometry": {"coordinates":[13.216667,46.441111],"type":"Point"}
}