{
  "id": 7365730,
  "type": "Feature",
  "properties": {
    "tgn:hierarchy":[
        "tgn:7365730",
        "tgn:1000001",
        "tgn:7005589",
        "tgn:7005560",
        "tgn:7029392"
    ],
    "tgn:id":7365730,
    "tgn:name":"Tanque Gabino",
    "tgn:placetype":[
        "aat:300006191"
    ]
},
  "bbox": [],
  "geometry": {"coordinates":[-100.283333,27.016667],"type":"Point"}
}