{
  "id": 2246634,
  "type": "Feature",
  "properties": {
    "tgn:hierarchy":[
        "tgn:2246634",
        "tgn:1000001",
        "tgn:7012149",
        "tgn:1002440",
        "tgn:7007568",
        "tgn:7029392"
    ],
    "tgn:id":2246634,
    "tgn:name":"Cobblestone Creek",
    "tgn:placetype":[
        "aat:300008706"
    ]
},
  "bbox": [],
  "geometry": {"coordinates":[-74.7167,43.5667],"type":"Point"}
}