{
  "id": 7557035,
  "type": "Feature",
  "properties": {
    "tgn:hierarchy":[
        "tgn:7557035",
        "tgn:1000004",
        "tgn:7018318",
        "tgn:7000198",
        "tgn:7029392"
    ],
    "tgn:id":7557035,
    "tgn:name:en":"Serula",
    "tgn:placetype":[
        "aat:300008347"
    ]
},
  "bbox": [],
  "geometry": {"coordinates":[73.833333,15.533333],"type":"Point"}
}