{
  "id": 2648479,
  "type": "Feature",
  "properties": {
    "tgn:hierarchy":[
        "tgn:2648479",
        "tgn:1000001",
        "tgn:7012149",
        "tgn:2000217",
        "tgn:7007158",
        "tgn:7029392"
    ],
    "tgn:id":2648479,
    "tgn:name":"Schuylkill Mountain",
    "tgn:placetype":[
        "aat:300008798"
    ]
},
  "bbox": [],
  "geometry": {"coordinates":[-107.0833,38.9333],"type":"Point"}
}