<<<<<<< HEAD
{
  "id": 7367213,
  "type": "Feature",
  "properties": {
    "tgn:hierarchy":[
        "tgn:7367213",
        "tgn:7005586",
        "tgn:1000001",
        "tgn:7005560",
        "tgn:7029392"
    ],
    "tgn:id":7367213,
    "tgn:name":"El Portezuelo",
    "tgn:placetype":[
        "aat:300008347"
    ]
},
  "bbox": [],
  "geometry": {"coordinates":[-103.983333,20.833333],"type":"Point"}
}
=======
{"geometry":{"type":"Point","coordinates":[-103.983333,20.833333]},"type":"Feature","properties":{"hierarchy":["tgn:7367213","tgn:7005586","tgn:1000001","tgn:7005560","tgn:7029392"],"placetype":["aat:300008347"],"id":7367213,"name:xx":"El Portezuelo"}}
>>>>>>> 03f74aca74312dbeaf24d7e61306dd6a786dc3d0
