{
  "id": 7367213,
  "type": "Feature",
  "properties": {
    "tgn:hierarchy":[
        "tgn:7367213",
        "tgn:7005586",
        "tgn:1000001",
        "tgn:7005560",
        "tgn:7029392"
    ],
    "tgn:id":7367213,
    "tgn:name":"El Portezuelo",
    "tgn:placetype":[
        "aat:300008347"
    ]
},
  "bbox": [],
  "geometry": {"coordinates":[-103.983333,20.833333],"type":"Point"}
}