{
  "id": 2155387,
  "type": "Feature",
  "properties": {
    "tgn:hierarchy":[
        "tgn:2155387",
        "tgn:7002659",
        "tgn:1000001",
        "tgn:7012149",
        "tgn:2000063",
        "tgn:7029392"
    ],
    "tgn:id":2155387,
    "tgn:name":"Bear Pen Mountain",
    "tgn:placetype":[
        "aat:300008798"
    ]
},
  "bbox": [],
  "geometry": {"coordinates":[-87.3667,33.8167],"type":"Point"}
}