<<<<<<< HEAD
{
  "id": 2155387,
  "type": "Feature",
  "properties": {
    "tgn:hierarchy":[
        "tgn:2155387",
        "tgn:7002659",
        "tgn:1000001",
        "tgn:7012149",
        "tgn:2000063",
        "tgn:7029392"
    ],
    "tgn:id":2155387,
    "tgn:name":"Bear Pen Mountain",
    "tgn:placetype":[
        "aat:300008798"
    ]
},
  "bbox": [],
  "geometry": {"coordinates":[-87.3667,33.8167],"type":"Point"}
}
=======
{"geometry":{"type":"Point","coordinates":[-87.366700,33.816700]},"type":"Feature","properties":{"hierarchy":["tgn:2155387","tgn:7002659","tgn:1000001","tgn:7012149","tgn:2000063","tgn:7029392"],"placetype":["aat:300008798"],"id":2155387,"name:xx":"Bear Pen Mountain"}}
>>>>>>> 03f74aca74312dbeaf24d7e61306dd6a786dc3d0
