{
  "id": 7592168,
  "type": "Feature",
  "properties": {
    "tgn:hierarchy":[
        "tgn:7592168",
        "tgn:1000004",
        "tgn:7000198",
        "tgn:7000799",
        "tgn:7029392"
    ],
    "tgn:id":7592168,
    "tgn:name:en":"Dadora",
    "tgn:placetype":[
        "aat:300008347"
    ]
},
  "bbox": [],
  "geometry": {"coordinates":[74.563204,32.821087],"type":"Point"}
}