{
  "id": 2695484,
  "type": "Feature",
  "properties": {
    "tgn:hierarchy":[
        "tgn:2695484",
        "tgn:1000001",
        "tgn:1002500",
        "tgn:7012149",
        "tgn:7007240",
        "tgn:7029392"
    ],
    "tgn:id":2695484,
    "tgn:name":"Stingray Creek",
    "tgn:placetype":[
        "aat:300008706"
    ]
},
  "bbox": [],
  "geometry": {"coordinates":[-80.3667,27.6833],"type":"Point"}
}