{
  "id": 2096163,
  "type": "Feature",
  "properties": {
    "tgn:hierarchy":[
        "tgn:2096163",
        "tgn:1000001",
        "tgn:7012149",
        "tgn:2001761",
        "tgn:7007712",
        "tgn:7029392"
    ],
    "tgn:id":2096163,
    "tgn:name":"Longcreek",
    "tgn:placetype":[
        "aat:300008347"
    ]
},
  "bbox": [],
  "geometry": {"coordinates":[-83.25,34.7667],"type":"Point"}
}