<<<<<<< HEAD
{
  "id": 2252270,
  "type": "Feature",
  "properties": {
    "tgn:hierarchy":[
        "tgn:2252270",
        "tgn:1000001",
        "tgn:7012149",
        "tgn:2001288",
        "tgn:7007524",
        "tgn:7029392"
    ],
    "tgn:id":2252270,
    "tgn:name":"Coney Lake",
    "tgn:placetype":[
        "aat:300008680"
    ]
},
  "bbox": [],
  "geometry": {"coordinates":[-111.4833,44.95],"type":"Point"}
}
=======
{"geometry":{"type":"Point","coordinates":[-111.483300,44.950000]},"type":"Feature","properties":{"hierarchy":["tgn:2252270","tgn:1000001","tgn:7012149","tgn:2001288","tgn:7007524","tgn:7029392"],"placetype":["aat:300008680"],"id":2252270,"name:xx":"Coney Lake"}}
>>>>>>> 03f74aca74312dbeaf24d7e61306dd6a786dc3d0
