{
  "id": 1075538,
  "type": "Feature",
  "properties": {
    "tgn:hierarchy":[
        "tgn:1075538",
        "tgn:1000004",
        "tgn:7000198",
        "tgn:1001895",
        "tgn:7029392"
    ],
    "tgn:id":1075538,
    "tgn:name:en":"J\u0101lna",
    "tgn:placetype":[
        "aat:300008347"
    ]
},
  "bbox": [],
  "geometry": {"coordinates":[75.886,19.841],"type":"Point"}
}