{
  "id": 7572672,
  "type": "Feature",
  "properties": {
    "tgn:hierarchy":[
        "tgn:7572672",
        "tgn:1000004",
        "tgn:7000198",
        "tgn:7016694",
        "tgn:7029392"
    ],
    "tgn:id":7572672,
    "tgn:name:en":"Hukitola",
    "tgn:placetype":[
        "aat:300008347"
    ]
},
  "bbox": [],
  "geometry": {"coordinates":[86.789634,20.403466],"type":"Point"}
}