{
  "id": 7563902,
  "type": "Feature",
  "properties": {
    "tgn:hierarchy":[
        "tgn:7563902",
        "tgn:1000004",
        "tgn:7000198",
        "tgn:7016788",
        "tgn:7029392"
    ],
    "tgn:id":7563902,
    "tgn:name:en":"Karn\u012bsar",
    "tgn:placetype":[
        "aat:300008347"
    ]
},
  "bbox": [],
  "geometry": {"coordinates":[74.019221,28.541897],"type":"Point"}
}