{
  "id": 7375045,
  "type": "Feature",
  "properties": {
    "tgn:hierarchy":[
        "tgn:7375045",
        "tgn:7005586",
        "tgn:1000001",
        "tgn:7005560",
        "tgn:7029392"
    ],
    "tgn:id":7375045,
    "tgn:name":"Labor de Sol\u00eds",
    "tgn:placetype":[
        "aat:300008347"
    ]
},
  "bbox": [],
  "geometry": {"coordinates":[-103.983333,20.566667],"type":"Point"}
}