{
  "id": 2605055,
  "type": "Feature",
  "properties": {
    "tgn:hierarchy":[
        "tgn:2605055",
        "tgn:1000001",
        "tgn:7012149",
        "tgn:2002264",
        "tgn:7013961",
        "tgn:7029392"
    ],
    "tgn:id":2605055,
    "tgn:name":"Raders Valley",
    "tgn:placetype":[
        "aat:300008761"
    ]
},
  "bbox": [],
  "geometry": {"coordinates":[-80.4833,37.9167],"type":"Point"}
}