{
  "id": 7073545,
  "type": "Feature",
  "properties": {
    "tgn:hierarchy":[
        "tgn:7073545",
        "tgn:1000003",
        "tgn:7003682",
        "tgn:7000084",
        "tgn:7029392"
    ],
    "tgn:id":7073545,
    "tgn:name":"Teufels Berg",
    "tgn:placetype":[
        "aat:300008795"
    ]
},
  "bbox": [],
  "geometry": {"coordinates":[8.05,49.25],"type":"Point"}
}