{
  "id": 7494523,
  "type": "Feature",
  "properties": {
    "tgn:hierarchy":[
        "tgn:7494523",
        "tgn:7468018",
        "tgn:1000004",
        "tgn:1000141",
        "tgn:7029392"
    ],
    "tgn:id":7494523,
    "tgn:name":"Neiwan",
    "tgn:placetype":[
        "aat:300008347"
    ]
},
  "bbox": [],
  "geometry": {"coordinates":[120.524586,23.320883],"type":"Point"}
}