{
  "id": 7176018,
  "type": "Feature",
  "properties": {
    "tgn:hierarchy":[
        "tgn:7176018",
        "tgn:7003692",
        "tgn:1000003",
        "tgn:7000084",
        "tgn:7029392"
    ],
    "tgn:id":7176018,
    "tgn:name":"Greutberg",
    "tgn:placetype":[
        "aat:300387200"
    ]
},
  "bbox": [],
  "geometry": {"coordinates":[9.883333,47.866667],"type":"Point"}
}