{
  "id": 2737281,
  "type": "Feature",
  "properties": {
    "tgn:hierarchy":[
        "tgn:2737281",
        "tgn:1000001",
        "tgn:7012149",
        "tgn:2001532",
        "tgn:7007709",
        "tgn:7029392"
    ],
    "tgn:id":2737281,
    "tgn:name":"Twomile Branch",
    "tgn:placetype":[
        "aat:300008699"
    ]
},
  "bbox": [],
  "geometry": {"coordinates":[-80.0167,35.5833],"type":"Point"}
}