{
  "id": 2636549,
  "type": "Feature",
  "properties": {
    "tgn:hierarchy":[
        "tgn:2636549",
        "tgn:1000001",
        "tgn:2002369",
        "tgn:7012149",
        "tgn:7007923",
        "tgn:7029392"
    ],
    "tgn:id":2636549,
    "tgn:name":"Sage Creek Divide",
    "tgn:placetype":[
        "aat:300266640"
    ]
},
  "bbox": [],
  "geometry": {"coordinates":[-105.7833,43.0667],"type":"Point"}
}