<<<<<<< HEAD
{
  "id": 2339554,
  "type": "Feature",
  "properties": {
    "tgn:hierarchy":[
        "tgn:2339554",
        "tgn:1000001",
        "tgn:7012149",
        "tgn:2000628",
        "tgn:7007253",
        "tgn:7029392"
    ],
    "tgn:id":2339554,
    "tgn:name":"Frederic",
    "tgn:placetype":[
        "aat:300008347"
    ]
},
  "bbox": [],
  "geometry": {"coordinates":[-92.6667,41.0833],"type":"Point"}
}
=======
{"geometry":{"type":"Point","coordinates":[-92.666700,41.083300]},"type":"Feature","properties":{"hierarchy":["tgn:2339554","tgn:1000001","tgn:7012149","tgn:2000628","tgn:7007253","tgn:7029392"],"placetype":["aat:300008347"],"id":2339554,"name:xx":"Frederic"}}
>>>>>>> 03f74aca74312dbeaf24d7e61306dd6a786dc3d0
