{
  "id": 7033428,
  "type": "Feature",
  "properties": {
    "tgn:hierarchy":[
        "tgn:7033428",
        "tgn:7002996",
        "tgn:1000003",
        "tgn:7002997",
        "tgn:1000080",
        "tgn:7029392"
    ],
    "tgn:id":7033428,
    "tgn:name":"Mure",
    "tgn:placetype":[
        "aat:300008347"
    ]
},
  "bbox": [],
  "geometry": {"coordinates":[12.641944,45.808889],"type":"Point"}
}