{
  "id": 7203959,
  "type": "Feature",
  "properties": {
    "tgn:hierarchy":[
        "tgn:7203959",
        "tgn:1000003",
        "tgn:7003677",
        "tgn:7000084",
        "tgn:7029392"
    ],
    "tgn:id":7203959,
    "tgn:name":"Haltepunkt Br\u00fcggen-West",
    "tgn:placetype":[
        "aat:300007783"
    ]
},
  "bbox": [],
  "geometry": {"coordinates":[6.15,51.233333],"type":"Point"}
}