{
  "id": 2468752,
  "type": "Feature",
  "properties": {
    "tgn:hierarchy":[
        "tgn:2468752",
        "tgn:1000001",
        "tgn:7012149",
        "tgn:7007157",
        "tgn:1002864",
        "tgn:7029392"
    ],
    "tgn:id":2468752,
    "tgn:name":"Long Ridge",
    "tgn:placetype":[
        "aat:300266640"
    ]
},
  "bbox": [],
  "geometry": {"coordinates":[-122.1667,37.2667],"type":"Point"}
}