{
  "id": 2251916,
  "type": "Feature",
  "properties": {
    "tgn:hierarchy":[
        "tgn:2251916",
        "tgn:1000001",
        "tgn:7012149",
        "tgn:2000891",
        "tgn:7007256",
        "tgn:7029392"
    ],
    "tgn:id":2251916,
    "tgn:name":"Concession, Bayou",
    "tgn:placetype":[
        "aat:300008699"
    ]
},
  "bbox": [],
  "geometry": {"coordinates":[-90.05,29.7833],"type":"Point"}
}