<<<<<<< HEAD
{
  "id": 2251916,
  "type": "Feature",
  "properties": {
    "tgn:hierarchy":[
        "tgn:2251916",
        "tgn:1000001",
        "tgn:7012149",
        "tgn:2000891",
        "tgn:7007256",
        "tgn:7029392"
    ],
    "tgn:id":2251916,
    "tgn:name":"Concession, Bayou",
    "tgn:placetype":[
        "aat:300008699"
    ]
},
  "bbox": [],
  "geometry": {"coordinates":[-90.05,29.7833],"type":"Point"}
}
=======
{"geometry":{"type":"Point","coordinates":[-90.050000,29.783300]},"type":"Feature","properties":{"hierarchy":["tgn:2251916","tgn:1000001","tgn:7012149","tgn:2000891","tgn:7007256","tgn:7029392"],"placetype":["aat:300008699"],"id":2251916,"name:xx":"Concession, Bayou"}}
>>>>>>> 03f74aca74312dbeaf24d7e61306dd6a786dc3d0
