{
  "id": 7171420,
  "type": "Feature",
  "properties": {
    "tgn:hierarchy":[
        "tgn:7171420",
        "tgn:7000096",
        "tgn:1000003",
        "tgn:7000084",
        "tgn:7029392"
    ],
    "tgn:id":7171420,
    "tgn:name":"Hertefeld",
    "tgn:placetype":[
        "aat:300008347"
    ]
},
  "bbox": [],
  "geometry": {"coordinates":[12.816667,52.666667],"type":"Point"}
}