{
  "id": 2244472,
  "type": "Feature",
  "properties": {
    "tgn:hierarchy":[
        "tgn:2244472",
        "tgn:1000001",
        "tgn:7012149",
        "tgn:2001708",
        "tgn:7007708",
        "tgn:7029392"
    ],
    "tgn:id":2244472,
    "tgn:name":"Cline Draw",
    "tgn:placetype":[
        "aat:300008701"
    ]
},
  "bbox": [],
  "geometry": {"coordinates":[-118.5833,44.45],"type":"Point"}
}