<<<<<<< HEAD
{
  "id": 2333267,
  "type": "Feature",
  "properties": {
    "tgn:hierarchy":[
        "tgn:2333267",
        "tgn:1000001",
        "tgn:7012149",
        "tgn:2001882",
        "tgn:7007825",
        "tgn:7029392"
    ],
    "tgn:id":2333267,
    "tgn:name":"Fodderstack Mountain",
    "tgn:placetype":[
        "aat:300008798"
    ]
},
  "bbox": [],
  "geometry": {"coordinates":[-81.7333,36.5833],"type":"Point"}
}
=======
{"geometry":{"type":"Point","coordinates":[-81.733300,36.583300]},"type":"Feature","properties":{"hierarchy":["tgn:2333267","tgn:1000001","tgn:7012149","tgn:2001882","tgn:7007825","tgn:7029392"],"placetype":["aat:300008798"],"id":2333267,"name:xx":"Fodderstack Mountain"}}
>>>>>>> 03f74aca74312dbeaf24d7e61306dd6a786dc3d0
