{
  "id": 2735994,
  "type": "Feature",
  "properties": {
    "tgn:hierarchy":[
        "tgn:2735994",
        "tgn:1000001",
        "tgn:2001431",
        "tgn:7012149",
        "tgn:7007566",
        "tgn:7029392"
    ],
    "tgn:id":2735994,
    "tgn:name":"Twin Lakes",
    "tgn:placetype":[
        "aat:300008680"
    ]
},
  "bbox": [],
  "geometry": {"coordinates":[-108.1667,34.9833],"type":"Point"}
}