{
  "id": 1112937,
  "type": "Feature",
  "properties": {
    "tgn:hierarchy":[
        "tgn:1112937",
        "tgn:1000001",
        "tgn:7012149",
        "tgn:1002708",
        "tgn:7007568",
        "tgn:7029392"
    ],
    "tgn:id":1112937,
    "tgn:name":"East Bay",
    "tgn:placetype":[
        "aat:300132316"
    ]
},
  "bbox": [],
  "geometry": {"coordinates":[-73.5167,40.6333],"type":"Point"}
}