{
  "id": 7022119,
  "type": "Feature",
  "properties": {
    "tgn:hierarchy":[
        "tgn:7022119",
        "tgn:1000001",
        "tgn:7012149",
        "tgn:1003018",
        "tgn:7007919",
        "tgn:7029392"
    ],
    "tgn:id":7022119,
    "tgn:name":"Newtons Pond",
    "tgn:placetype":[
        "aat:300006191"
    ]
},
  "bbox": [],
  "geometry": {"coordinates":[-76.6333,38.05],"type":"Point"}
}