{
  "id": 2612929,
  "type": "Feature",
  "properties": {
    "tgn:hierarchy":[
        "tgn:2612929",
        "tgn:1000001",
        "tgn:1002229",
        "tgn:7012149",
        "tgn:7007710",
        "tgn:7029392"
    ],
    "tgn:id":2612929,
    "tgn:name":"Rednor Hollow",
    "tgn:placetype":[
        "aat:300008761"
    ]
},
  "bbox": [],
  "geometry": {"coordinates":[-78.15,41.55],"type":"Point"}
}