{
  "id": 2610306,
  "type": "Feature",
  "properties": {
    "tgn:hierarchy":[
        "tgn:2610306",
        "tgn:1000001",
        "tgn:7016172",
        "tgn:7012149",
        "tgn:2000168",
        "tgn:7029392"
    ],
    "tgn:id":2610306,
    "tgn:name":"Red Buck Hollow",
    "tgn:placetype":[
        "aat:300008761"
    ]
},
  "bbox": [],
  "geometry": {"coordinates":[-93.7333,34.7833],"type":"Point"}
}