{
  "id": 7564049,
  "type": "Feature",
  "properties": {
    "tgn:hierarchy":[
        "tgn:7564049",
        "tgn:1000004",
        "tgn:7000198",
        "tgn:7016722",
        "tgn:7029392"
    ],
    "tgn:id":7564049,
    "tgn:name:en":"Purwa Deoki",
    "tgn:placetype":[
        "aat:300008347"
    ]
},
  "bbox": [],
  "geometry": {"coordinates":[79.875938,26.549741],"type":"Point"}
}