{
  "id": 2773144,
  "type": "Feature",
  "properties": {
    "tgn:hierarchy":[
        "tgn:2773144",
        "tgn:2000090",
        "tgn:1000001",
        "tgn:7006451",
        "tgn:7012149",
        "tgn:7029392"
    ],
    "tgn:id":2773144,
    "tgn:name":"Williams Valley",
    "tgn:placetype":[
        "aat:300008761"
    ]
},
  "bbox": [],
  "geometry": {"coordinates":[-109.1833,33.85],"type":"Point"}
}