{
  "id": 2738631,
  "type": "Feature",
  "properties": {
    "tgn:hierarchy":[
        "tgn:2738631",
        "tgn:1000001",
        "tgn:7012149",
        "tgn:2000332",
        "tgn:7007248",
        "tgn:7029392"
    ],
    "tgn:id":2738631,
    "tgn:name":"Union",
    "tgn:placetype":[
        "aat:300008347"
    ]
},
  "bbox": [],
  "geometry": {"coordinates":[-85.5167,34.8333],"type":"Point"}
}