{
  "id": 2613240,
  "type": "Feature",
  "properties": {
    "tgn:hierarchy":[
        "tgn:2613240",
        "tgn:1000001",
        "tgn:2000307",
        "tgn:7012149",
        "tgn:7007248",
        "tgn:7029392"
    ],
    "tgn:id":2613240,
    "tgn:name":"Reed Branch",
    "tgn:placetype":[
        "aat:300008699"
    ]
},
  "bbox": [],
  "geometry": {"coordinates":[-81.7333,32.2167],"type":"Point"}
}