{
  "id": 2306201,
  "type": "Feature",
  "properties": {
    "tgn:hierarchy":[
        "tgn:2306201",
        "tgn:1000001",
        "tgn:7012149",
        "tgn:2001709",
        "tgn:7007708",
        "tgn:7029392"
    ],
    "tgn:id":2306201,
    "tgn:name":"East Fork Blue Creek",
    "tgn:placetype":[
        "aat:300008706"
    ]
},
  "bbox": [],
  "geometry": {"coordinates":[-119.35,43.8333],"type":"Point"}
}