{
  "id": 7232382,
  "type": "Feature",
  "properties": {
    "tgn:hierarchy":[
        "tgn:7232382",
        "tgn:7002735",
        "tgn:7017076",
        "tgn:1000003",
        "tgn:1000074",
        "tgn:7029392"
    ],
    "tgn:id":7232382,
    "tgn:name":"Kefal\u00e1s",
    "tgn:placetype":[
        "aat:300008347"
    ]
},
  "bbox": [],
  "geometry": {"coordinates":[22.516667,37.033333],"type":"Point"}
}