{
  "id": 2032203,
  "type": "Feature",
  "properties": {
    "tgn:hierarchy":[
        "tgn:2032203",
        "tgn:1000001",
        "tgn:1002306",
        "tgn:7012149",
        "tgn:7007252",
        "tgn:7029392"
    ],
    "tgn:id":2032203,
    "tgn:name":"Hogtown",
    "tgn:placetype":[
        "aat:300008347",
        "aat:300387210"
    ]
},
  "bbox": [],
  "geometry": {"coordinates":[-86.3167,38.35],"type":"Point"}
}