{
  "id": 7230295,
  "type": "Feature",
  "properties": {
    "tgn:hierarchy":[
        "tgn:7230295",
        "tgn:7002735",
        "tgn:7017076",
        "tgn:1000003",
        "tgn:1000074",
        "tgn:7029392"
    ],
    "tgn:id":7230295,
    "tgn:name":"Mavrovo\u00fanion",
    "tgn:placetype":[
        "aat:300008795"
    ]
},
  "bbox": [],
  "geometry": {"coordinates":[22.433333,36.883333],"type":"Point"}
}