{
  "id": 2730033,
  "type": "Feature",
  "properties": {
    "tgn:hierarchy":[
        "tgn:2730033",
        "tgn:1000001",
        "tgn:7012149",
        "tgn:7007158",
        "tgn:2000245",
        "tgn:7029392"
    ],
    "tgn:id":2730033,
    "tgn:name":"Trout Creek Ditch Number 4",
    "tgn:placetype":[
        "aat:300006075"
    ]
},
  "bbox": [],
  "geometry": {"coordinates":[-106.95,40.3667],"type":"Point"}
}