{
  "id": 1071301,
  "type": "Feature",
  "properties": {
    "tgn:hierarchy":[
        "tgn:1071301",
        "tgn:1000004",
        "tgn:7001319",
        "tgn:1000111",
        "tgn:7029392"
    ],
    "tgn:id":1071301,
    "tgn:name":"Sangya",
    "tgn:placetype":[
        "aat:300008347"
    ]
},
  "bbox": [],
  "geometry": {"coordinates":[91.6667,30.8667],"type":"Point"}
}