{
  "id": 2145231,
  "type": "Feature",
  "properties": {
    "tgn:hierarchy":[
        "tgn:2145231",
        "tgn:1000001",
        "tgn:1002275",
        "tgn:7012149",
        "tgn:7007920",
        "tgn:7029392"
    ],
    "tgn:id":2145231,
    "tgn:name":"Bald Mountain",
    "tgn:placetype":[
        "aat:300008798"
    ]
},
  "bbox": [],
  "geometry": {"coordinates":[-122.5667,45.9167],"type":"Point"}
}