{
  "id": 7397908,
  "type": "Feature",
  "properties": {
    "tgn:hierarchy":[
        "tgn:7397908",
        "tgn:1000001",
        "tgn:1001960",
        "tgn:7005560",
        "tgn:7029392"
    ],
    "tgn:id":7397908,
    "tgn:name":"Las Huertas",
    "tgn:placetype":[
        "aat:300008347"
    ]
},
  "bbox": [],
  "geometry": {"coordinates":[-111.568056,30.835556],"type":"Point"}
}