{
  "id": 7563770,
  "type": "Feature",
  "properties": {
    "tgn:hierarchy":[
        "tgn:7563770",
        "tgn:1000004",
        "tgn:7000198",
        "tgn:7016722",
        "tgn:7029392"
    ],
    "tgn:id":7563770,
    "tgn:name:en":"Naw\u0101da T\u0101nda",
    "tgn:placetype":[
        "aat:300008347"
    ]
},
  "bbox": [],
  "geometry": {"coordinates":[79.823838,26.594446],"type":"Point"}
}