{
  "id": 1140685,
  "type": "Feature",
  "properties": {
    "tgn:hierarchy":[
        "tgn:1140685",
        "tgn:1000004",
        "tgn:1001527",
        "tgn:7029379",
        "tgn:7029392"
    ],
    "tgn:id":1140685,
    "tgn:name":"Altanbulag",
    "tgn:placetype":[
        "aat:300008347"
    ]
},
  "bbox": [],
  "geometry": {"coordinates":[106.4333,50.3333],"type":"Point"}
}