{
  "id": 2462965,
  "type": "Feature",
  "properties": {
    "tgn:hierarchy":[
        "tgn:2462965",
        "tgn:1000001",
        "tgn:7012149",
        "tgn:2001951",
        "tgn:7007826",
        "tgn:7029392"
    ],
    "tgn:id":2462965,
    "tgn:name":"Live Oak Creek",
    "tgn:placetype":[
        "aat:300008706"
    ]
},
  "bbox": [],
  "geometry": {"coordinates":[-99.1833,32.35],"type":"Point"}
}