{
  "id": 2378128,
  "type": "Feature",
  "properties": {
    "tgn:hierarchy":[
        "tgn:2378128",
        "tgn:1000001",
        "tgn:7012149",
        "tgn:7014318",
        "tgn:7007568",
        "tgn:7029392"
    ],
    "tgn:id":2378128,
    "tgn:name":"Harris Hill",
    "tgn:placetype":[
        "aat:300008798"
    ]
},
  "bbox": [],
  "geometry": {"coordinates":[-75.2667,42.5333],"type":"Point"}
}