{
  "id": 7305983,
  "type": "Feature",
  "properties": {
    "tgn:hierarchy":[
        "tgn:7305983",
        "tgn:7002805",
        "tgn:7002758",
        "tgn:1000003",
        "tgn:1000095",
        "tgn:7029392"
    ],
    "tgn:id":7305983,
    "tgn:name":"Mati\u00e1n",
    "tgn:placetype":[
        "aat:300008347"
    ]
},
  "bbox": [],
  "geometry": {"coordinates":[-2.45,37.55],"type":"Point"}
}