<<<<<<< HEAD
{
  "id": 2402368,
  "type": "Feature",
  "properties": {
    "tgn:hierarchy":[
        "tgn:2402368",
        "tgn:1000001",
        "tgn:7012149",
        "tgn:2000183",
        "tgn:7007157",
        "tgn:7029392"
    ],
    "tgn:id":2402368,
    "tgn:name":"Horton Lake",
    "tgn:placetype":[
        "aat:300008680"
    ]
},
  "bbox": [],
  "geometry": {"coordinates":[-118.6667,37.3],"type":"Point"}
}
=======
{"geometry":{"type":"Point","coordinates":[-118.666700,37.300000]},"type":"Feature","properties":{"hierarchy":["tgn:2402368","tgn:1000001","tgn:7012149","tgn:2000183","tgn:7007157","tgn:7029392"],"placetype":["aat:300008680"],"id":2402368,"name:xx":"Horton Lake"}}
>>>>>>> 03f74aca74312dbeaf24d7e61306dd6a786dc3d0
