<<<<<<< HEAD
{
  "id": 7057965,
  "type": "Feature",
  "properties": {
    "tgn:hierarchy":[
        "tgn:7057965",
        "tgn:1003440",
        "tgn:1000003",
        "tgn:7003124",
        "tgn:1000080",
        "tgn:7029392"
    ],
    "tgn:id":7057965,
    "tgn:name":"Brez",
    "tgn:placetype":[
        "aat:300008347"
    ]
},
  "bbox": [],
  "geometry": {"coordinates":[11.116667,46.433333],"type":"Point"}
}
=======
{"geometry":{"type":"Point","coordinates":[11.116667,46.433333]},"type":"Feature","properties":{"hierarchy":["tgn:7057965","tgn:1003440","tgn:1000003","tgn:7003124","tgn:1000080","tgn:7029392"],"placetype":["aat:300008347"],"id":7057965,"name:xx":"Brez"}}
>>>>>>> 03f74aca74312dbeaf24d7e61306dd6a786dc3d0
