{
  "id": 2472656,
  "type": "Feature",
  "properties": {
    "tgn:hierarchy":[
        "tgn:2472656",
        "tgn:1000001",
        "tgn:7012149",
        "tgn:1002478",
        "tgn:7007826",
        "tgn:7029392"
    ],
    "tgn:id":2472656,
    "tgn:name":"Lovelace Creek",
    "tgn:placetype":[
        "aat:300008706"
    ]
},
  "bbox": [],
  "geometry": {"coordinates":[-97.0667,32.1167],"type":"Point"}
}