{
  "id": 7403631,
  "type": "Feature",
  "properties": {
    "tgn:hierarchy":[
        "tgn:7403631",
        "tgn:1000001",
        "tgn:1001906",
        "tgn:7005560",
        "tgn:7029392"
    ],
    "tgn:id":7403631,
    "tgn:name":"La Huerta",
    "tgn:placetype":[
        "aat:300008347"
    ]
},
  "bbox": [],
  "geometry": {"coordinates":[-104.925,21.4375],"type":"Point"}
}