{
  "id": 7185293,
  "type": "Feature",
  "properties": {
    "tgn:hierarchy":[
        "tgn:7185293",
        "tgn:1000003",
        "tgn:7000094",
        "tgn:7000084",
        "tgn:7029392"
    ],
    "tgn:id":7185293,
    "tgn:name":"Gransebieth",
    "tgn:placetype":[
        "aat:300008347"
    ]
},
  "bbox": [],
  "geometry": {"coordinates":[12.883333,54.066667],"type":"Point"}
}