{
  "id": 7358710,
  "type": "Feature",
  "properties": {
    "tgn:hierarchy":[
        "tgn:7358710",
        "tgn:1000001",
        "tgn:7005599",
        "tgn:7005560",
        "tgn:7029392"
    ],
    "tgn:id":7358710,
    "tgn:name":"Descanso",
    "tgn:placetype":[
        "aat:300008347"
    ]
},
  "bbox": [],
  "geometry": {"coordinates":[-93.883333,17.266667],"type":"Point"}
}