{
  "id": 2496205,
  "type": "Feature",
  "properties": {
    "tgn:hierarchy":[
        "tgn:2496205",
        "tgn:1000001",
        "tgn:2001183",
        "tgn:7012149",
        "tgn:7007523",
        "tgn:7029392"
    ],
    "tgn:id":2496205,
    "tgn:name":"Masters Island",
    "tgn:placetype":[
        "aat:300008791"
    ]
},
  "bbox": [],
  "geometry": {"coordinates":[-93.7833,37.7667],"type":"Point"}
}