{
  "id": 1022080,
  "type": "Feature",
  "properties": {
    "tgn:hierarchy":[
        "tgn:1022080",
        "tgn:7006257",
        "tgn:1000047",
        "tgn:7002455",
        "tgn:1000002",
        "tgn:7029392"
    ],
    "tgn:id":1022080,
    "tgn:name":"Maxaranguape",
    "tgn:placetype":[
        "aat:300008347"
    ]
},
  "bbox": [],
  "geometry": {"coordinates":[-35.2667,-5.5167],"type":"Point"}
}