{
  "id": 7498005,
  "type": "Feature",
  "properties": {
    "tgn:hierarchy":[
        "tgn:7498005",
        "tgn:1000004",
        "tgn:1000454",
        "tgn:1000141",
        "tgn:7029392"
    ],
    "tgn:id":7498005,
    "tgn:name":"Qiedongjiao Shan",
    "tgn:placetype":[
        "aat:300008798"
    ]
},
  "bbox": [],
  "geometry": {"coordinates":[121.680543,25.041265],"type":"Point"}
}