{
  "id": 7116282,
  "type": "Feature",
  "properties": {
    "tgn:hierarchy":[
        "tgn:7116282",
        "tgn:7003692",
        "tgn:1000003",
        "tgn:7000084",
        "tgn:7029392"
    ],
    "tgn:id":7116282,
    "tgn:name":"Oberweiler",
    "tgn:placetype":[
        "aat:300008347"
    ]
},
  "bbox": [],
  "geometry": {"coordinates":[9.833333,47.75],"type":"Point"}
}