<<<<<<< HEAD
{
  "id": 7116282,
  "type": "Feature",
  "properties": {
    "tgn:hierarchy":[
        "tgn:7116282",
        "tgn:7003692",
        "tgn:1000003",
        "tgn:7000084",
        "tgn:7029392"
    ],
    "tgn:id":7116282,
    "tgn:name":"Oberweiler",
    "tgn:placetype":[
        "aat:300008347"
    ]
},
  "bbox": [],
  "geometry": {"coordinates":[9.833333,47.75],"type":"Point"}
}
=======
{"geometry":{"type":"Point","coordinates":[9.833333,47.750000]},"type":"Feature","properties":{"hierarchy":["tgn:7116282","tgn:7003692","tgn:1000003","tgn:7000084","tgn:7029392"],"placetype":["aat:300008347"],"id":7116282,"name:xx":"Oberweiler"}}
>>>>>>> 03f74aca74312dbeaf24d7e61306dd6a786dc3d0
