{
  "id": 2661464,
  "type": "Feature",
  "properties": {
    "tgn:hierarchy":[
        "tgn:2661464",
        "tgn:1000001",
        "tgn:7012149",
        "tgn:7007922",
        "tgn:7029392"
    ],
    "tgn:id":2661464,
    "tgn:name":"Shoulder Creek",
    "tgn:placetype":[
        "aat:300008706"
    ]
},
  "bbox": [],
  "geometry": {"coordinates":[-90.75,45.3167],"type":"Point"}
}