{
  "id": 7343330,
  "type": "Feature",
  "properties": {
    "tgn:hierarchy":[
        "tgn:7343330",
        "tgn:7002835",
        "tgn:7001158",
        "tgn:1000003",
        "tgn:1000095",
        "tgn:7029392"
    ],
    "tgn:id":7343330,
    "tgn:name":"Ca\u00f1ada Carbonera",
    "tgn:placetype":[
        "aat:300008347"
    ]
},
  "bbox": [],
  "geometry": {"coordinates":[-6.483333,40.75],"type":"Point"}
}