{
  "id": 2086143,
  "type": "Feature",
  "properties": {
    "tgn:hierarchy":[
        "tgn:2086143",
        "tgn:1000001",
        "tgn:1002318",
        "tgn:7012149",
        "tgn:7007710",
        "tgn:7029392"
    ],
    "tgn:id":2086143,
    "tgn:name":"Bachmanville",
    "tgn:placetype":[
        "aat:300008347"
    ]
},
  "bbox": [],
  "geometry": {"coordinates":[-76.5833,40.2333],"type":"Point"}
}