{
  "id": 7019708,
  "type": "Feature",
  "properties": {
    "tgn:hierarchy":[
        "tgn:7019708",
        "tgn:7006450",
        "tgn:1000001",
        "tgn:2124076",
        "tgn:7012149",
        "tgn:7029392"
    ],
    "tgn:id":7019708,
    "tgn:name":"Mud Bay",
    "tgn:placetype":[
        "aat:300008347"
    ]
},
  "bbox": [],
  "geometry": {"coordinates":[-131.7667,55.4167],"type":"Point"}
}