{
  "id": 2512028,
  "type": "Feature",
  "properties": {
    "tgn:hierarchy":[
        "tgn:2512028",
        "tgn:1000001",
        "tgn:7012149",
        "tgn:2000278",
        "tgn:7007240",
        "tgn:7029392"
    ],
    "tgn:id":2512028,
    "tgn:name":"Mill Branch",
    "tgn:placetype":[
        "aat:300008699"
    ]
},
  "bbox": [],
  "geometry": {"coordinates":[-84.9333,30.45],"type":"Point"}
}