{
  "id": 7501491,
  "type": "Feature",
  "properties": {
    "tgn:hierarchy":[
        "tgn:7501491",
        "tgn:1000004",
        "tgn:7490934",
        "tgn:1000141",
        "tgn:7029392"
    ],
    "tgn:id":7501491,
    "tgn:name":"Xuantian Shangdi Miao",
    "tgn:placetype":[
        "aat:300007595"
    ]
},
  "bbox": [],
  "geometry": {"coordinates":[120.28,22.917778],"type":"Point"}
}