{
  "id": 7355636,
  "type": "Feature",
  "properties": {
    "tgn:hierarchy":[
        "tgn:7355636",
        "tgn:7005581",
        "tgn:1000001",
        "tgn:7005560",
        "tgn:7029392"
    ],
    "tgn:id":7355636,
    "tgn:name":"Chiches de Juana, Cerro",
    "tgn:placetype":[
        "aat:300008795"
    ]
},
  "bbox": [],
  "geometry": {"coordinates":[-105.75,28.95],"type":"Point"}
}