{
  "id": 7402514,
  "type": "Feature",
  "properties": {
    "tgn:hierarchy":[
        "tgn:7402514",
        "tgn:1000001",
        "tgn:1001937",
        "tgn:7005560",
        "tgn:7029392"
    ],
    "tgn:id":7402514,
    "tgn:name":"Plan de la Noria",
    "tgn:placetype":[
        "aat:300008347"
    ]
},
  "bbox": [],
  "geometry": {"coordinates":[-88.783333,19.316667],"type":"Point"}
}