<<<<<<< HEAD
{
  "id": 2405755,
  "type": "Feature",
  "properties": {
    "tgn:hierarchy":[
        "tgn:2405755",
        "tgn:1000001",
        "tgn:2000507",
        "tgn:7012149",
        "tgn:7007251",
        "tgn:7029392"
    ],
    "tgn:id":2405755,
    "tgn:name":"Hulda Lake",
    "tgn:placetype":[
        "aat:300008680"
    ]
},
  "bbox": [],
  "geometry": {"coordinates":[-88.1,37.7833],"type":"Point"}
}
=======
{"geometry":{"type":"Point","coordinates":[-88.100000,37.783300]},"type":"Feature","properties":{"hierarchy":["tgn:2405755","tgn:1000001","tgn:2000507","tgn:7012149","tgn:7007251","tgn:7029392"],"placetype":["aat:300008680"],"id":2405755,"name:xx":"Hulda Lake"}}
>>>>>>> 03f74aca74312dbeaf24d7e61306dd6a786dc3d0
