{
  "id": 7063643,
  "type": "Feature",
  "properties": {
    "tgn:hierarchy":[
        "tgn:7063643",
        "tgn:1000003",
        "tgn:7003682",
        "tgn:7000084",
        "tgn:7029392"
    ],
    "tgn:id":7063643,
    "tgn:name":"Anzelterhof",
    "tgn:placetype":[
        "aat:300000206"
    ]
},
  "bbox": [],
  "geometry": {"coordinates":[6.516667,50.183333],"type":"Point"}
}