{
  "id": 2030924,
  "type": "Feature",
  "properties": {
    "tgn:hierarchy":[
        "tgn:2030924",
        "tgn:1000001",
        "tgn:7012149",
        "tgn:2000544",
        "tgn:7007252",
        "tgn:7029392"
    ],
    "tgn:id":2030924,
    "tgn:name":"Antioch",
    "tgn:placetype":[
        "aat:300008347",
        "aat:300387210"
    ]
},
  "bbox": [],
  "geometry": {"coordinates":[-87.2333,39.0833],"type":"Point"}
}