{
  "id": 2507606,
  "type": "Feature",
  "properties": {
    "tgn:hierarchy":[
        "tgn:2507606",
        "tgn:1000001",
        "tgn:7012149",
        "tgn:2000479",
        "tgn:7007250",
        "tgn:7029392"
    ],
    "tgn:id":2507606,
    "tgn:name":"Mica Creek",
    "tgn:placetype":[
        "aat:300008706"
    ]
},
  "bbox": [],
  "geometry": {"coordinates":[-116.8667,47.5833],"type":"Point"}
}