{
  "id": 7576626,
  "type": "Feature",
  "properties": {
    "tgn:hierarchy":[
        "tgn:7576626",
        "tgn:1000004",
        "tgn:7000198",
        "tgn:1001905",
        "tgn:7029392"
    ],
    "tgn:id":7576626,
    "tgn:name:en":"Laruri",
    "tgn:placetype":[
        "aat:300008347"
    ]
},
  "bbox": [],
  "geometry": {"coordinates":[94.842629,25.685526],"type":"Point"}
}