{
  "id": 2759602,
  "type": "Feature",
  "properties": {
    "tgn:hierarchy":[
        "tgn:2759602",
        "tgn:1000001",
        "tgn:7012149",
        "tgn:7007524",
        "tgn:7029392"
    ],
    "tgn:id":2759602,
    "tgn:name":"West Fork Froze To Death Creek",
    "tgn:placetype":[
        "aat:300008706"
    ]
},
  "bbox": [],
  "geometry": {"coordinates":[-107.4333,46.5667],"type":"Point"}
}