{
  "id": 2619715,
  "type": "Feature",
  "properties": {
    "tgn:hierarchy":[
        "tgn:2619715",
        "tgn:1000001",
        "tgn:7012149",
        "tgn:1002904",
        "tgn:7007710",
        "tgn:7029392"
    ],
    "tgn:id":2619715,
    "tgn:name":"Ringer Hill",
    "tgn:placetype":[
        "aat:300008798"
    ]
},
  "bbox": [],
  "geometry": {"coordinates":[-79.1833,39.7333],"type":"Point"}
}