{
  "id": 7285863,
  "type": "Feature",
  "properties": {
    "tgn:hierarchy":[
        "tgn:7285863",
        "tgn:1001637",
        "tgn:1000049",
        "tgn:1000002",
        "tgn:7029392"
    ],
    "tgn:id":7285863,
    "tgn:name":"Pichibureo, R\u00edo",
    "tgn:placetype":[
        "aat:300008699"
    ]
},
  "bbox": [],
  "geometry": {"coordinates":[-72.016667,-37.783333],"type":"Point"}
}