{
  "id": 1089003,
  "type": "Feature",
  "properties": {
    "tgn:hierarchy":[
        "tgn:1089003",
        "tgn:7001242",
        "tgn:7016654",
        "tgn:1000159",
        "tgn:7029392"
    ],
    "tgn:id":1089003,
    "tgn:name":"Ikali",
    "tgn:placetype":[
        "aat:300008347"
    ]
},
  "bbox": [],
  "geometry": {"coordinates":[21.0667,-2.0333],"type":"Point"}
}