{
  "id": 2646518,
  "type": "Feature",
  "properties": {
    "tgn:hierarchy":[
        "tgn:2646518",
        "tgn:1000001",
        "tgn:7012149",
        "tgn:2001254",
        "tgn:7007523",
        "tgn:7029392"
    ],
    "tgn:id":2646518,
    "tgn:name":"Sayersbrook Lake",
    "tgn:placetype":[
        "aat:300006191"
    ]
},
  "bbox": [],
  "geometry": {"coordinates":[-90.9167,37.9833],"type":"Point"}
}