{
  "id": 7464521,
  "type": "Feature",
  "properties": {
    "tgn:hierarchy":[
        "tgn:7464521",
        "tgn:7002445",
        "tgn:1000003",
        "tgn:7008143",
        "tgn:7008591",
        "tgn:7029392"
    ],
    "tgn:id":7464521,
    "tgn:name:en":"Aymestrey",
    "tgn:placetype":[
        "aat:300008347"
    ]
},
  "bbox": [],
  "geometry": {"coordinates":[-2.833333,52.283333],"type":"Point"}
}