{
  "id": 2644605,
  "type": "Feature",
  "properties": {
    "tgn:hierarchy":[
        "tgn:2644605",
        "tgn:1000001",
        "tgn:7012149",
        "tgn:7007157",
        "tgn:1002894",
        "tgn:7029392"
    ],
    "tgn:id":2644605,
    "tgn:name":"Sardine Valley",
    "tgn:placetype":[
        "aat:300008761"
    ]
},
  "bbox": [],
  "geometry": {"coordinates":[-120.15,39.5333],"type":"Point"}
}