{
  "id": 7524504,
  "type": "Feature",
  "properties": {
    "tgn:hierarchy":[
        "tgn:7524504",
        "tgn:7001242",
        "tgn:7016833",
        "tgn:7000124",
        "tgn:7029392"
    ],
    "tgn:id":7524504,
    "tgn:name:en":"Al Waqdah",
    "tgn:placetype":[
        "aat:300008347"
    ]
},
  "bbox": [],
  "geometry": {"coordinates":[31.566667,26.616667],"type":"Point"}
}