{
  "id": 7402359,
  "type": "Feature",
  "properties": {
    "tgn:hierarchy":[
        "tgn:7402359",
        "tgn:1000001",
        "tgn:1001937",
        "tgn:7005560",
        "tgn:7029392"
    ],
    "tgn:id":7402359,
    "tgn:name":"Herradura, Punta",
    "tgn:placetype":[
        "aat:300386846"
    ]
},
  "bbox": [],
  "geometry": {"coordinates":[-87.733333,18.583333],"type":"Point"}
}