{
  "id": 7132917,
  "type": "Feature",
  "properties": {
    "tgn:hierarchy":[
        "tgn:7132917",
        "tgn:7003669",
        "tgn:1000003",
        "tgn:7000084",
        "tgn:7029392"
    ],
    "tgn:id":7132917,
    "tgn:name":"Murrleins-Brunnen",
    "tgn:placetype":[
        "aat:300008697"
    ]
},
  "bbox": [],
  "geometry": {"coordinates":[10.433333,49.883333],"type":"Point"}
}