<<<<<<< HEAD
{
  "id": 2407697,
  "type": "Feature",
  "properties": {
    "tgn:hierarchy":[
        "tgn:2407697",
        "tgn:1000001",
        "tgn:7016172",
        "tgn:7012149",
        "tgn:2000137",
        "tgn:7029392"
    ],
    "tgn:id":2407697,
    "tgn:name":"Huron",
    "tgn:placetype":[
        "aat:300008347"
    ]
},
  "bbox": [],
  "geometry": {"coordinates":[-92.05,36.2167],"type":"Point"}
}
=======
{"geometry":{"type":"Point","coordinates":[-92.050000,36.216700]},"type":"Feature","properties":{"hierarchy":["tgn:2407697","tgn:1000001","tgn:7016172","tgn:7012149","tgn:2000137","tgn:7029392"],"placetype":["aat:300008347"],"id":2407697,"name:xx":"Huron"}}
>>>>>>> 03f74aca74312dbeaf24d7e61306dd6a786dc3d0
