{
  "id": 2536682,
  "type": "Feature",
  "properties": {
    "tgn:hierarchy":[
        "tgn:2536682",
        "tgn:1000001",
        "tgn:7012149",
        "tgn:2002076",
        "tgn:7007826",
        "tgn:7029392"
    ],
    "tgn:id":2536682,
    "tgn:name":"Necessity, Lake",
    "tgn:placetype":[
        "aat:300006191"
    ]
},
  "bbox": [],
  "geometry": {"coordinates":[-98.75,32.6333],"type":"Point"}
}