{
  "id": 2567326,
  "type": "Feature",
  "properties": {
    "tgn:hierarchy":[
        "tgn:2567326",
        "tgn:1000001",
        "tgn:7012149",
        "tgn:2002274",
        "tgn:7013961",
        "tgn:7029392"
    ],
    "tgn:id":2567326,
    "tgn:name":"Panther State Forest",
    "tgn:placetype":[
        "aat:300008863"
    ]
},
  "bbox": [],
  "geometry": {"coordinates":[-81.8667,37.4167],"type":"Point"}
}