{
  "id": 2321520,
  "type": "Feature",
  "properties": {
    "tgn:hierarchy":[
        "tgn:2321520",
        "tgn:1000001",
        "tgn:7012149",
        "tgn:7014334",
        "tgn:7007919",
        "tgn:7029392"
    ],
    "tgn:id":2321520,
    "tgn:name":"Fairplay",
    "tgn:placetype":[
        "aat:300008347"
    ]
},
  "bbox": [],
  "geometry": {"coordinates":[-76.6167,37.8333],"type":"Point"}
}