{
  "id": 2290174,
  "type": "Feature",
  "properties": {
    "tgn:hierarchy":[
        "tgn:2290174",
        "tgn:1000001",
        "tgn:7012149",
        "tgn:2002124",
        "tgn:7007827",
        "tgn:7029392"
    ],
    "tgn:id":2290174,
    "tgn:name":"Dodds Hollow Spring",
    "tgn:placetype":[
        "aat:300008697"
    ]
},
  "bbox": [],
  "geometry": {"coordinates":[-109.5667,40.6667],"type":"Point"}
}