{
  "id": 7156112,
  "type": "Feature",
  "properties": {
    "tgn:hierarchy":[
        "tgn:7156112",
        "tgn:7003692",
        "tgn:1000003",
        "tgn:7000084",
        "tgn:7029392"
    ],
    "tgn:id":7156112,
    "tgn:name":"Kleinansbach",
    "tgn:placetype":[
        "aat:300008347"
    ]
},
  "bbox": [],
  "geometry": {"coordinates":[10.133333,49.283333],"type":"Point"}
}