{
  "id": 7181150,
  "type": "Feature",
  "properties": {
    "tgn:hierarchy":[
        "tgn:7181150",
        "tgn:1000003",
        "tgn:7003676",
        "tgn:7000084",
        "tgn:7029392"
    ],
    "tgn:id":7181150,
    "tgn:name":"Gelbbach",
    "tgn:placetype":[
        "aat:300008699"
    ]
},
  "bbox": [],
  "geometry": {"coordinates":[9.483333,52.166667],"type":"Point"}
}