<<<<<<< HEAD
{
  "id": 7119720,
  "type": "Feature",
  "properties": {
    "tgn:hierarchy":[
        "tgn:7119720",
        "tgn:1000003",
        "tgn:7000094",
        "tgn:7000084",
        "tgn:7029392"
    ],
    "tgn:id":7119720,
    "tgn:name":"Prerowbank",
    "tgn:placetype":[
        "aat:300387036"
    ]
},
  "bbox": [],
  "geometry": {"coordinates":[12.583333,54.5],"type":"Point"}
}
=======
{"geometry":{"type":"Point","coordinates":[12.583333,54.500000]},"type":"Feature","properties":{"hierarchy":["tgn:7119720","tgn:1000003","tgn:7000094","tgn:7000084","tgn:7029392"],"placetype":["aat:300387036"],"id":7119720,"name:xx":"Prerowbank"}}
>>>>>>> 03f74aca74312dbeaf24d7e61306dd6a786dc3d0
