{
  "id": 7506907,
  "type": "Feature",
  "properties": {
    "tgn:hierarchy":[
        "tgn:7506907",
        "tgn:1008380",
        "tgn:1000226",
        "tgn:7018426",
        "tgn:1000006",
        "tgn:7029392"
    ],
    "tgn:id":7506907,
    "tgn:name:en":"Rangitoto Range",
    "tgn:placetype":[
        "aat:300008795"
    ]
},
  "bbox": [],
  "geometry": {"coordinates":[175.583333,-38.416667],"type":"Point"}
}