{
  "id": 1098725,
  "type": "Feature",
  "properties": {
    "tgn:hierarchy":[
        "tgn:1098725",
        "tgn:7006218",
        "tgn:7006211",
        "tgn:1000216",
        "tgn:1000006",
        "tgn:7029392"
    ],
    "tgn:id":1098725,
    "tgn:name":"Mahina",
    "tgn:placetype":[
        "aat:300008347"
    ]
},
  "bbox": [],
  "geometry": {"coordinates":[-149.45,-17.4833],"type":"Point"}
}