{
  "id": 7515758,
  "type": "Feature",
  "properties": {
    "tgn:hierarchy":[
        "tgn:7515758",
        "tgn:1008380",
        "tgn:7000507",
        "tgn:1000226",
        "tgn:1000006",
        "tgn:7029392"
    ],
    "tgn:id":7515758,
    "tgn:name:en":"Manginangina",
    "tgn:placetype":[
        "aat:300008795"
    ]
},
  "bbox": [],
  "geometry": {"coordinates":[173.816667,-35.166667],"type":"Point"}
}