{
  "id": 2756830,
  "type": "Feature",
  "properties": {
    "tgn:hierarchy":[
        "tgn:2756830",
        "tgn:1000001",
        "tgn:2002103",
        "tgn:7012149",
        "tgn:7007827",
        "tgn:7029392"
    ],
    "tgn:id":2756830,
    "tgn:name":"Wellsville Reservoir",
    "tgn:placetype":[
        "aat:300006191"
    ]
},
  "bbox": [],
  "geometry": {"coordinates":[-111.9167,41.6167],"type":"Point"}
}