{
  "id": 7039914,
  "type": "Feature",
  "properties": {
    "tgn:hierarchy":[
        "tgn:7039914",
        "tgn:1001641",
        "tgn:1000003",
        "tgn:7003121",
        "tgn:1000080",
        "tgn:7029392"
    ],
    "tgn:id":7039914,
    "tgn:name":"Segariu",
    "tgn:placetype":[
        "aat:300008347"
    ]
},
  "bbox": [],
  "geometry": {"coordinates":[8.982778,39.563611],"type":"Point"}
}