<<<<<<< HEAD
{
  "id": 7118279,
  "type": "Feature",
  "properties": {
    "tgn:hierarchy":[
        "tgn:7118279",
        "tgn:7003692",
        "tgn:1000003",
        "tgn:7000084",
        "tgn:7029392"
    ],
    "tgn:id":7118279,
    "tgn:name":"Petershausen",
    "tgn:placetype":[
        "aat:300000745"
    ]
},
  "bbox": [],
  "geometry": {"coordinates":[9.2,47.666667],"type":"Point"}
}
=======
{"geometry":{"type":"Point","coordinates":[9.200000,47.666667]},"type":"Feature","properties":{"hierarchy":["tgn:7118279","tgn:7003692","tgn:1000003","tgn:7000084","tgn:7029392"],"placetype":["aat:300000745"],"id":7118279,"name:xx":"Petershausen"}}
>>>>>>> 03f74aca74312dbeaf24d7e61306dd6a786dc3d0
