{
  "id": 2306861,
  "type": "Feature",
  "properties": {
    "tgn:hierarchy":[
        "tgn:2306861",
        "tgn:7006450",
        "tgn:1000001",
        "tgn:7012149",
        "tgn:2000086",
        "tgn:7029392"
    ],
    "tgn:id":2306861,
    "tgn:name":"East Fork Indian Creek",
    "tgn:placetype":[
        "aat:300008706"
    ]
},
  "bbox": [],
  "geometry": {"coordinates":[-144.1833,62.8833],"type":"Point"}
}