<<<<<<< HEAD
{
  "id": 2763010,
  "type": "Feature",
  "properties": {
    "tgn:hierarchy":[
        "tgn:2763010",
        "tgn:1000001",
        "tgn:7012149",
        "tgn:2000487",
        "tgn:7007250",
        "tgn:7029392"
    ],
    "tgn:id":2763010,
    "tgn:name":"Weston Creek Reservoir",
    "tgn:placetype":[
        "aat:300006191"
    ]
},
  "bbox": [],
  "geometry": {"coordinates":[-112.1,42.1167],"type":"Point"}
}
=======
{"geometry":{"type":"Point","coordinates":[-112.100000,42.116700]},"type":"Feature","properties":{"hierarchy":["tgn:2763010","tgn:1000001","tgn:7012149","tgn:2000487","tgn:7007250","tgn:7029392"],"placetype":["aat:300006191"],"id":2763010,"name:xx":"Weston Creek Reservoir"}}
>>>>>>> 03f74aca74312dbeaf24d7e61306dd6a786dc3d0
