{
  "id": 1057408,
  "type": "Feature",
  "properties": {
    "tgn:hierarchy":[
        "tgn:1057408",
        "tgn:1003373",
        "tgn:1000004",
        "tgn:7018214",
        "tgn:7002435",
        "tgn:7029392"
    ],
    "tgn:id":1057408,
    "tgn:name":"Nevanka",
    "tgn:placetype":[
        "aat:300008347"
    ]
},
  "bbox": [],
  "geometry": {"coordinates":[98.95,56.5167],"type":"Point"}
}