{
  "id": 2321321,
  "type": "Feature",
  "properties": {
    "tgn:hierarchy":[
        "tgn:2321321",
        "tgn:1000001",
        "tgn:7012149",
        "tgn:2000411",
        "tgn:7007248",
        "tgn:7029392"
    ],
    "tgn:id":2321321,
    "tgn:name":"Faircloth Lake",
    "tgn:placetype":[
        "aat:300006191"
    ]
},
  "bbox": [],
  "geometry": {"coordinates":[-84.7833,31.7833],"type":"Point"}
}