{
  "id": 7331199,
  "type": "Feature",
  "properties": {
    "tgn:hierarchy":[
        "tgn:7331199",
        "tgn:7002811",
        "tgn:1000003",
        "tgn:7003837",
        "tgn:1000095",
        "tgn:7029392"
    ],
    "tgn:id":7331199,
    "tgn:name":"Grande, Charca",
    "tgn:placetype":[
        "aat:300008688"
    ]
},
  "bbox": [],
  "geometry": {"coordinates":[-6.666667,39.583333],"type":"Point"}
}