{
  "id": 7013329,
  "type": "Feature",
  "properties": {
    "tgn:hierarchy":[
        "tgn:7013329",
        "tgn:1000001",
        "tgn:2000320",
        "tgn:7012149",
        "tgn:7007248",
        "tgn:7029392"
    ],
    "tgn:id":7013329,
    "tgn:name":"Athens",
    "tgn:placetype":[
        "aat:300387277",
        "aat:300008347",
        "aat:300008416",
        "aat:300008389",
        "aat:300387308",
        "aat:300264742",
        "aat:300387302",
        "aat:300387291",
        "aat:300387286"
    ]
},
  "bbox": [],
  "geometry": {"coordinates":[-83.3667,33.95],"type":"Point"}
}