{
  "id": 7352682,
  "type": "Feature",
  "properties": {
    "tgn:hierarchy":[
        "tgn:7352682",
        "tgn:1000001",
        "tgn:7005595",
        "tgn:7005560",
        "tgn:7029392"
    ],
    "tgn:id":7352682,
    "tgn:name":"Basurina",
    "tgn:placetype":[
        "aat:300008347"
    ]
},
  "bbox": [],
  "geometry": {"coordinates":[-107.866667,26.05],"type":"Point"}
}