{
  "id": 2787069,
  "type": "Feature",
  "properties": {
    "tgn:hierarchy":[
        "tgn:2787069",
        "tgn:1000001",
        "tgn:7012149",
        "tgn:1002679",
        "tgn:7007520",
        "tgn:7029392"
    ],
    "tgn:id":2787069,
    "tgn:name":"Zink and Nolan Drain",
    "tgn:placetype":[
        "aat:300008699"
    ]
},
  "bbox": [],
  "geometry": {"coordinates":[-83.4667,42.05],"type":"Point"}
}