{
  "id": 7323461,
  "type": "Feature",
  "properties": {
    "tgn:hierarchy":[
        "tgn:7323461",
        "tgn:7001158",
        "tgn:7002848",
        "tgn:1000003",
        "tgn:1000095",
        "tgn:7029392"
    ],
    "tgn:id":7323461,
    "tgn:name":"Roque, Arroyo de",
    "tgn:placetype":[
        "aat:300266554",
        "aat:300008699"
    ]
},
  "bbox": [],
  "geometry": {"coordinates":[-5.016667,41.966667],"type":"Point"}
}