<<<<<<< HEAD
{
  "id": 7020027,
  "type": "Feature",
  "properties": {
    "tgn:hierarchy":[
        "tgn:7020027",
        "tgn:1000001",
        "tgn:7012149",
        "tgn:2002385",
        "tgn:7007923",
        "tgn:7029392"
    ],
    "tgn:id":7020027,
    "tgn:name":"Rock Hollow",
    "tgn:placetype":[
        "aat:300008761"
    ]
},
  "bbox": [],
  "geometry": {"coordinates":[-110.5167,41.3],"type":"Point"}
}
=======
{"geometry":{"type":"Point","coordinates":[-110.516700,41.300000]},"type":"Feature","properties":{"hierarchy":["tgn:7020027","tgn:1000001","tgn:7012149","tgn:2002385","tgn:7007923","tgn:7029392"],"placetype":["aat:300008761"],"id":7020027,"name:xx":"Rock Hollow"}}
>>>>>>> 03f74aca74312dbeaf24d7e61306dd6a786dc3d0
