{
  "id": 7123853,
  "type": "Feature",
  "properties": {
    "tgn:hierarchy":[
        "tgn:7123853",
        "tgn:7003669",
        "tgn:1000003",
        "tgn:7000084",
        "tgn:7029392"
    ],
    "tgn:id":7123853,
    "tgn:name":"Niederheldenstein",
    "tgn:placetype":[
        "aat:300008347"
    ]
},
  "bbox": [],
  "geometry": {"coordinates":[12.383333,48.25],"type":"Point"}
}