<<<<<<< HEAD
{
  "id": 7023196,
  "type": "Feature",
  "properties": {
    "tgn:hierarchy":[
        "tgn:7023196",
        "tgn:1000001",
        "tgn:7012149",
        "tgn:7007923",
        "tgn:7029392"
    ],
    "tgn:id":7023196,
    "tgn:name":"Sirrine Ditch",
    "tgn:placetype":[
        "aat:300006075"
    ]
},
  "bbox": [],
  "geometry": {"coordinates":[-109.0833,44.9667],"type":"Point"}
}
=======
{"geometry":{"type":"Point","coordinates":[-109.083300,44.966700]},"type":"Feature","properties":{"hierarchy":["tgn:7023196","tgn:1000001","tgn:7012149","tgn:7007923","tgn:7029392"],"placetype":["aat:300006075"],"id":7023196,"name:xx":"Sirrine Ditch"}}
>>>>>>> 03f74aca74312dbeaf24d7e61306dd6a786dc3d0
