{
  "id": 7503830,
  "type": "Feature",
  "properties": {
    "tgn:hierarchy":[
        "tgn:7503830",
        "tgn:1000004",
        "tgn:7491221",
        "tgn:1000141",
        "tgn:7029392"
    ],
    "tgn:id":7503830,
    "tgn:name":"Qianbancuo",
    "tgn:placetype":[
        "aat:300008347"
    ]
},
  "bbox": [],
  "geometry": {"coordinates":[121.000556,22.683056],"type":"Point"}
}