{
  "id": 2028493,
  "type": "Feature",
  "properties": {
    "tgn:hierarchy":[
        "tgn:2028493",
        "tgn:1000001",
        "tgn:7012149",
        "tgn:1002524",
        "tgn:7007251",
        "tgn:7029392"
    ],
    "tgn:id":2028493,
    "tgn:name":"Jerseyville",
    "tgn:placetype":[
        "aat:300008347"
    ]
},
  "bbox": [],
  "geometry": {"coordinates":[-90.3167,39.1167],"type":"Point"}
}