{
  "id": 7319676,
  "type": "Feature",
  "properties": {
    "tgn:hierarchy":[
        "tgn:7319676",
        "tgn:1001768",
        "tgn:1000049",
        "tgn:1000002",
        "tgn:7029392"
    ],
    "tgn:id":7319676,
    "tgn:name":"Alto, Morro",
    "tgn:placetype":[
        "aat:300008777"
    ]
},
  "bbox": [],
  "geometry": {"coordinates":[-70.566667,-32.883333],"type":"Point"}
}