{
  "id": 7506381,
  "type": "Feature",
  "properties": {
    "tgn:hierarchy":[
        "tgn:7506381",
        "tgn:1009227",
        "tgn:1000226",
        "tgn:7016822",
        "tgn:1000006",
        "tgn:7029392"
    ],
    "tgn:id":7506381,
    "tgn:name:en":"Round Peaks",
    "tgn:placetype":[
        "aat:300008798"
    ]
},
  "bbox": [],
  "geometry": {"coordinates":[168.35,-45.05],"type":"Point"}
}