{
  "id": 2664848,
  "type": "Feature",
  "properties": {
    "tgn:hierarchy":[
        "tgn:2664848",
        "tgn:1002132",
        "tgn:1000001",
        "tgn:7012149",
        "tgn:7007919",
        "tgn:7029392"
    ],
    "tgn:id":2664848,
    "tgn:name":"Simoneaston Bay",
    "tgn:placetype":[
        "aat:300132316"
    ]
},
  "bbox": [],
  "geometry": {"coordinates":[-75.45,37.9167],"type":"Point"}
}