{
  "id": 2385406,
  "type": "Feature",
  "properties": {
    "tgn:hierarchy":[
        "tgn:2385406",
        "tgn:7002659",
        "tgn:1000001",
        "tgn:7012149",
        "tgn:2000051",
        "tgn:7029392"
    ],
    "tgn:id":2385406,
    "tgn:name":"Henderson",
    "tgn:placetype":[
        "aat:300008347"
    ]
},
  "bbox": [],
  "geometry": {"coordinates":[-86.8167,34.4833],"type":"Point"}
}