{
  "id": 7576538,
  "type": "Feature",
  "properties": {
    "tgn:hierarchy":[
        "tgn:7576538",
        "tgn:1000004",
        "tgn:1001869",
        "tgn:7000198",
        "tgn:7029392"
    ],
    "tgn:id":7576538,
    "tgn:name:en":"Kandla Bar",
    "tgn:placetype":[
        "aat:300386885"
    ]
},
  "bbox": [],
  "geometry": {"coordinates":[70.25,22.95],"type":"Point"}
}