{
  "id": 1058807,
  "type": "Feature",
  "properties": {
    "tgn:hierarchy":[
        "tgn:1058807",
        "tgn:1000004",
        "tgn:7011573",
        "tgn:7018214",
        "tgn:7002435",
        "tgn:7029392"
    ],
    "tgn:id":1058807,
    "tgn:name":"Rakhmanovo",
    "tgn:placetype":[
        "aat:300008347"
    ]
},
  "bbox": [],
  "geometry": {"coordinates":[38.6167,55.7333],"type":"Point"}
}