{
  "id": 7510309,
  "type": "Feature",
  "properties": {
    "tgn:hierarchy":[
        "tgn:7510309",
        "tgn:1008380",
        "tgn:7000507",
        "tgn:1000226",
        "tgn:1000006",
        "tgn:7029392"
    ],
    "tgn:id":7510309,
    "tgn:name:en":"Te Kie",
    "tgn:placetype":[
        "aat:300008795"
    ]
},
  "bbox": [],
  "geometry": {"coordinates":[173.85,-35.666667],"type":"Point"}
}