{
  "id": 2705684,
  "type": "Feature",
  "properties": {
    "tgn:hierarchy":[
        "tgn:2705684",
        "tgn:7006450",
        "tgn:1000001",
        "tgn:7012149",
        "tgn:2000082",
        "tgn:7029392"
    ],
    "tgn:id":2705684,
    "tgn:name":"Suspiro, Cape",
    "tgn:placetype":[
        "aat:300008850"
    ]
},
  "bbox": [],
  "geometry": {"coordinates":[-133.1333,55.45],"type":"Point"}
}