{
  "id": 7238418,
  "type": "Feature",
  "properties": {
    "tgn:hierarchy":[
        "tgn:7238418",
        "tgn:7003457",
        "tgn:1000003",
        "tgn:1000063",
        "tgn:7018236",
        "tgn:7029392"
    ],
    "tgn:id":7238418,
    "tgn:name":"Harentbeekbos",
    "tgn:placetype":[
        "aat:300008863"
    ]
},
  "bbox": [],
  "geometry": {"coordinates":[3.713805,50.945822],"type":"Point"}
}