{
  "id": 7395243,
  "type": "Feature",
  "properties": {
    "tgn:hierarchy":[
        "tgn:7395243",
        "tgn:7005586",
        "tgn:1000001",
        "tgn:7005560",
        "tgn:7029392"
    ],
    "tgn:id":7395243,
    "tgn:name":"La Haciendita",
    "tgn:placetype":[
        "aat:300008347"
    ]
},
  "bbox": [],
  "geometry": {"coordinates":[-104.883333,20.883333],"type":"Point"}
}