{
  "id": 7030012,
  "type": "Feature",
  "properties": {
    "tgn:hierarchy":[
        "tgn:7030012",
        "tgn:1000003",
        "tgn:7594009",
        "tgn:1000066",
        "tgn:7029392"
    ],
    "tgn:id":7030012,
    "tgn:name":"Sundeved",
    "tgn:placetype":[
        "aat:300008804"
    ]
},
  "bbox": [],
  "geometry": {"coordinates":[9.716,54.95],"type":"Point"}
}