{
  "id": 2710825,
  "type": "Feature",
  "properties": {
    "tgn:hierarchy":[
        "tgn:2710825",
        "tgn:1000001",
        "tgn:7006451",
        "tgn:7012149",
        "tgn:2000103",
        "tgn:7029392"
    ],
    "tgn:id":2710825,
    "tgn:name":"Tangle Peak",
    "tgn:placetype":[
        "aat:300008798"
    ]
},
  "bbox": [],
  "geometry": {"coordinates":[-111.7333,34.1167],"type":"Point"}
}