{
  "id": 2567646,
  "type": "Feature",
  "properties": {
    "tgn:hierarchy":[
        "tgn:2567646",
        "tgn:1000001",
        "tgn:7012149",
        "tgn:1002553",
        "tgn:7007920",
        "tgn:7029392"
    ],
    "tgn:id":2567646,
    "tgn:name":"Para Creek",
    "tgn:placetype":[
        "aat:300008706"
    ]
},
  "bbox": [],
  "geometry": {"coordinates":[-121.1333,47.2667],"type":"Point"}
}