{
  "id": 2619957,
  "type": "Feature",
  "properties": {
    "tgn:hierarchy":[
        "tgn:2619957",
        "tgn:1000001",
        "tgn:7006451",
        "tgn:2000093",
        "tgn:7012149",
        "tgn:7029392"
    ],
    "tgn:id":2619957,
    "tgn:name":"Ripper Spring",
    "tgn:placetype":[
        "aat:300008697"
    ]
},
  "bbox": [],
  "geometry": {"coordinates":[-110.9667,33.45],"type":"Point"}
}