{
  "id": 7501694,
  "type": "Feature",
  "properties": {
    "tgn:hierarchy":[
        "tgn:7501694",
        "tgn:1000004",
        "tgn:7001002",
        "tgn:1000141",
        "tgn:7029392"
    ],
    "tgn:id":7501694,
    "tgn:name":"Disi Gongyuanhua Gongmu",
    "tgn:placetype":[
        "aat:300266755"
    ]
},
  "bbox": [],
  "geometry": {"coordinates":[120.959444,24.790833],"type":"Point"}
}