{
  "id": 2568566,
  "type": "Feature",
  "properties": {
    "tgn:hierarchy":[
        "tgn:2568566",
        "tgn:1000001",
        "tgn:2001484",
        "tgn:7012149",
        "tgn:7007709",
        "tgn:7029392"
    ],
    "tgn:id":2568566,
    "tgn:name":"Park Sumter Terrace Apartments",
    "tgn:placetype":[
        "aat:300008347"
    ]
},
  "bbox": [],
  "geometry": {"coordinates":[-81.55,35.2833],"type":"Point"}
}