{
  "id": 2353217,
  "type": "Feature",
  "properties": {
    "tgn:hierarchy":[
        "tgn:2353217",
        "tgn:1000001",
        "tgn:2001418",
        "tgn:7012149",
        "tgn:7007526",
        "tgn:7029392"
    ],
    "tgn:id":2353217,
    "tgn:name":"Gold Bar",
    "tgn:placetype":[
        "aat:300008347"
    ]
},
  "bbox": [],
  "geometry": {"coordinates":[-116.8833,36.9333],"type":"Point"}
}