<<<<<<< HEAD
{
  "id": 2709553,
  "type": "Feature",
  "properties": {
    "tgn:hierarchy":[
        "tgn:2709553",
        "tgn:1000001",
        "tgn:7012149",
        "tgn:2000709",
        "tgn:7007254",
        "tgn:7029392"
    ],
    "tgn:id":2709553,
    "tgn:name":"Tackett Mound",
    "tgn:placetype":[
        "aat:300008798"
    ]
},
  "bbox": [],
  "geometry": {"coordinates":[-95.3667,37.2667],"type":"Point"}
}
=======
{"geometry":{"type":"Point","coordinates":[-95.366700,37.266700]},"type":"Feature","properties":{"hierarchy":["tgn:2709553","tgn:1000001","tgn:7012149","tgn:2000709","tgn:7007254","tgn:7029392"],"placetype":["aat:300008798"],"id":2709553,"name:xx":"Tackett Mound"}}
>>>>>>> 03f74aca74312dbeaf24d7e61306dd6a786dc3d0
