{
  "id": 2636804,
  "type": "Feature",
  "properties": {
    "tgn:hierarchy":[
        "tgn:2636804",
        "tgn:1000001",
        "tgn:7012149",
        "tgn:2002110",
        "tgn:7007827",
        "tgn:7029392"
    ],
    "tgn:id":2636804,
    "tgn:name":"Sagers",
    "tgn:placetype":[
        "aat:300008347"
    ]
},
  "bbox": [],
  "geometry": {"coordinates":[-109.5833,38.95],"type":"Point"}
}