<<<<<<< HEAD
{
  "id": 2331300,
  "type": "Feature",
  "properties": {
    "tgn:hierarchy":[
        "tgn:2331300",
        "tgn:1000001",
        "tgn:7012149",
        "tgn:2002037",
        "tgn:7007826",
        "tgn:7029392"
    ],
    "tgn:id":2331300,
    "tgn:name":"Flathead Point",
    "tgn:placetype":[
        "aat:300008798"
    ]
},
  "bbox": [],
  "geometry": {"coordinates":[-99.0333,30.5],"type":"Point"}
}
=======
{"geometry":{"type":"Point","coordinates":[-99.033300,30.500000]},"type":"Feature","properties":{"hierarchy":["tgn:2331300","tgn:1000001","tgn:7012149","tgn:2002037","tgn:7007826","tgn:7029392"],"placetype":["aat:300008798"],"id":2331300,"name:xx":"Flathead Point"}}
>>>>>>> 03f74aca74312dbeaf24d7e61306dd6a786dc3d0
