<<<<<<< HEAD
{
  "id": 2767767,
  "type": "Feature",
  "properties": {
    "tgn:hierarchy":[
        "tgn:2767767",
        "tgn:1000001",
        "tgn:7012149",
        "tgn:2000388",
        "tgn:7007248",
        "tgn:7029392"
    ],
    "tgn:id":2767767,
    "tgn:name":"Whitehead Lake",
    "tgn:placetype":[
        "aat:300006191"
    ]
},
  "bbox": [],
  "geometry": {"coordinates":[-83.0833,34.0333],"type":"Point"}
}
=======
{"geometry":{"type":"Point","coordinates":[-83.083300,34.033300]},"type":"Feature","properties":{"hierarchy":["tgn:2767767","tgn:1000001","tgn:7012149","tgn:2000388","tgn:7007248","tgn:7029392"],"placetype":["aat:300006191"],"id":2767767,"name:xx":"Whitehead Lake"}}
>>>>>>> 03f74aca74312dbeaf24d7e61306dd6a786dc3d0
