{
  "id": 2647147,
  "type": "Feature",
  "properties": {
    "tgn:hierarchy":[
        "tgn:2647147",
        "tgn:1000001",
        "tgn:7012149",
        "tgn:7007919",
        "tgn:7029392"
    ],
    "tgn:id":2647147,
    "tgn:name":"Schenks Branch",
    "tgn:placetype":[
        "aat:300008699"
    ]
},
  "bbox": [],
  "geometry": {"coordinates":[-78.4833,38.0333],"type":"Point"}
}