{
  "id": 2535100,
  "type": "Feature",
  "properties": {
    "tgn:hierarchy":[
        "tgn:2535100",
        "tgn:1000001",
        "tgn:7012149",
        "tgn:2001613",
        "tgn:7007706",
        "tgn:7029392"
    ],
    "tgn:id":2535100,
    "tgn:name":"Nancy",
    "tgn:placetype":[
        "aat:300008347"
    ]
},
  "bbox": [],
  "geometry": {"coordinates":[-82.65,39.3833],"type":"Point"}
}