{
  "id": 7321067,
  "type": "Feature",
  "properties": {
    "tgn:hierarchy":[
        "tgn:7321067",
        "tgn:1001630",
        "tgn:1000049",
        "tgn:1000002",
        "tgn:7029392"
    ],
    "tgn:id":7321067,
    "tgn:name":"Blanca, Roca",
    "tgn:placetype":[
        "aat:300011692"
    ]
},
  "bbox": [],
  "geometry": {"coordinates":[-71.066667,-27.75],"type":"Point"}
}