<<<<<<< HEAD
{
  "id": 2761567,
  "type": "Feature",
  "properties": {
    "tgn:hierarchy":[
        "tgn:2761567",
        "tgn:1000001",
        "tgn:7012149",
        "tgn:2001115",
        "tgn:7007522",
        "tgn:7029392"
    ],
    "tgn:id":2761567,
    "tgn:name":"West Pascagoula River",
    "tgn:placetype":[
        "aat:300008707"
    ]
},
  "bbox": [],
  "geometry": {"coordinates":[-88.6,30.5],"type":"Point"}
}
=======
{"geometry":{"type":"Point","coordinates":[-88.600000,30.500000]},"type":"Feature","properties":{"hierarchy":["tgn:2761567","tgn:1000001","tgn:7012149","tgn:2001115","tgn:7007522","tgn:7029392"],"placetype":["aat:300008707"],"id":2761567,"name:xx":"West Pascagoula River"}}
>>>>>>> 03f74aca74312dbeaf24d7e61306dd6a786dc3d0
