{
  "id": 2284529,
  "type": "Feature",
  "properties": {
    "tgn:hierarchy":[
        "tgn:2284529",
        "tgn:2001002",
        "tgn:1000001",
        "tgn:7012149",
        "tgn:7007521",
        "tgn:7029392"
    ],
    "tgn:id":2284529,
    "tgn:name":"Des Moines Lake",
    "tgn:placetype":[
        "aat:300008680"
    ]
},
  "bbox": [],
  "geometry": {"coordinates":[-94.8833,47.6167],"type":"Point"}
}