{
  "id": 2260454,
  "type": "Feature",
  "properties": {
    "tgn:hierarchy":[
        "tgn:2260454",
        "tgn:1000001",
        "tgn:7012149",
        "tgn:2001076",
        "tgn:7007521",
        "tgn:7029392"
    ],
    "tgn:id":2260454,
    "tgn:name":"County Ditch Number Fifteen",
    "tgn:placetype":[
        "aat:300006075"
    ]
},
  "bbox": [],
  "geometry": {"coordinates":[-96.45,45.7333],"type":"Point"}
}