{
  "id": 7204907,
  "type": "Feature",
  "properties": {
    "tgn:hierarchy":[
        "tgn:7204907",
        "tgn:1000003",
        "tgn:7003676",
        "tgn:7000084",
        "tgn:7029392"
    ],
    "tgn:id":7204907,
    "tgn:name":"Bullenhausen",
    "tgn:placetype":[
        "aat:300008347"
    ]
},
  "bbox": [],
  "geometry": {"coordinates":[10.083333,53.45],"type":"Point"}
}