{
  "id": 7072607,
  "type": "Feature",
  "properties": {
    "tgn:hierarchy":[
        "tgn:7072607",
        "tgn:7003669",
        "tgn:1000003",
        "tgn:7000084",
        "tgn:7029392"
    ],
    "tgn:id":7072607,
    "tgn:name":"Thalheim",
    "tgn:placetype":[
        "aat:300008347"
    ]
},
  "bbox": [],
  "geometry": {"coordinates":[10.55,48.733333],"type":"Point"}
}