{
  "id": 7269383,
  "type": "Feature",
  "properties": {
    "tgn:hierarchy":[
        "tgn:7269383",
        "tgn:7003614",
        "tgn:1000003",
        "tgn:7016845",
        "tgn:7029392"
    ],
    "tgn:id":7269383,
    "tgn:name:nl":"Odoornerdennen",
    "tgn:placetype":[
        "aat:300008863"
    ]
},
  "bbox": [],
  "geometry": {"coordinates":[6.85,52.866667],"type":"Point"}
}