{
  "id": 1095222,
  "type": "Feature",
  "properties": {
    "tgn:hierarchy":[
        "tgn:1095222",
        "tgn:7001242",
        "tgn:7016833",
        "tgn:1001083",
        "tgn:7029392"
    ],
    "tgn:id":1095222,
    "tgn:name":"Al \u1e24ayy",
    "tgn:placetype":[
        "aat:300008347"
    ]
},
  "bbox": [],
  "geometry": {"coordinates":[31.307778,29.648333],"type":"Point"}
}