{
  "id": 2203442,
  "type": "Feature",
  "properties": {
    "tgn:hierarchy":[
        "tgn:2203442",
        "tgn:1000001",
        "tgn:7006451",
        "tgn:7012149",
        "tgn:2000103",
        "tgn:7029392"
    ],
    "tgn:id":2203442,
    "tgn:name":"Buckhorn Tank Number Three",
    "tgn:placetype":[
        "aat:300006191"
    ]
},
  "bbox": [],
  "geometry": {"coordinates":[-111.55,34.5667],"type":"Point"}
}