{
  "id": 7061187,
  "type": "Feature",
  "properties": {
    "tgn:hierarchy":[
        "tgn:7061187",
        "tgn:1000003",
        "tgn:7003676",
        "tgn:7000084",
        "tgn:7029392"
    ],
    "tgn:id":7061187,
    "tgn:name":"Angelbecksbusch",
    "tgn:placetype":[
        "aat:300008863"
    ]
},
  "bbox": [],
  "geometry": {"coordinates":[10.133333,52.783333],"type":"Point"}
}