{
  "id": 2321429,
  "type": "Feature",
  "properties": {
    "tgn:hierarchy":[
        "tgn:2321429",
        "tgn:7014651",
        "tgn:1000001",
        "tgn:7012149",
        "tgn:7007516",
        "tgn:7029392"
    ],
    "tgn:id":2321429,
    "tgn:name":"Fairhaven Beach",
    "tgn:placetype":[
        "aat:300008347"
    ]
},
  "bbox": [],
  "geometry": {"coordinates":[-76.4833,39.1333],"type":"Point"}
}