{
  "id": 7143704,
  "type": "Feature",
  "properties": {
    "tgn:hierarchy":[
        "tgn:7143704",
        "tgn:7003669",
        "tgn:1000003",
        "tgn:7000084",
        "tgn:7029392"
    ],
    "tgn:id":7143704,
    "tgn:name":"Loch-Holz",
    "tgn:placetype":[
        "aat:300008863"
    ]
},
  "bbox": [],
  "geometry": {"coordinates":[11.933333,48.083333],"type":"Point"}
}