{
  "id": 7252926,
  "type": "Feature",
  "properties": {
    "tgn:hierarchy":[
        "tgn:7252926",
        "tgn:1000003",
        "tgn:1000063",
        "tgn:7029392"
    ],
    "tgn:id":7252926,
    "tgn:name":"Surbach",
    "tgn:placetype":[
        "aat:300008699"
    ]
},
  "bbox": [],
  "geometry": {"coordinates":[5.783333,49.883333],"type":"Point"}
}