<<<<<<< HEAD
{
  "id": 7114115,
  "type": "Feature",
  "properties": {
    "tgn:hierarchy":[
        "tgn:7114115",
        "tgn:7003692",
        "tgn:1000003",
        "tgn:7000084",
        "tgn:7029392"
    ],
    "tgn:id":7114115,
    "tgn:name":"Rockhalden",
    "tgn:placetype":[
        "aat:300008347"
    ]
},
  "bbox": [],
  "geometry": {"coordinates":[10.15,49.166667],"type":"Point"}
}
=======
{"geometry":{"type":"Point","coordinates":[10.150000,49.166667]},"type":"Feature","properties":{"hierarchy":["tgn:7114115","tgn:7003692","tgn:1000003","tgn:7000084","tgn:7029392"],"placetype":["aat:300008347"],"id":7114115,"name:xx":"Rockhalden"}}
>>>>>>> 03f74aca74312dbeaf24d7e61306dd6a786dc3d0
