{
  "id": 7075285,
  "type": "Feature",
  "properties": {
    "tgn:hierarchy":[
        "tgn:7075285",
        "tgn:1000003",
        "tgn:7003688",
        "tgn:7000084",
        "tgn:7029392"
    ],
    "tgn:id":7075285,
    "tgn:name":"Rittergat",
    "tgn:placetype":[
        "aat:300008713"
    ]
},
  "bbox": [],
  "geometry": {"coordinates":[8.333333,54.55],"type":"Point"}
}