{
  "id": 7295306,
  "type": "Feature",
  "properties": {
    "tgn:hierarchy":[
        "tgn:7295306",
        "tgn:7002813",
        "tgn:7002758",
        "tgn:1000003",
        "tgn:1000095",
        "tgn:7029392"
    ],
    "tgn:id":7295306,
    "tgn:name":"Tambor, Bajillo",
    "tgn:placetype":[
        "aat:300387036"
    ]
},
  "bbox": [],
  "geometry": {"coordinates":[-5.436111,36.152778],"type":"Point"}
}