<<<<<<< HEAD
{
  "id": 2334735,
  "type": "Feature",
  "properties": {
    "tgn:hierarchy":[
        "tgn:2334735",
        "tgn:1000001",
        "tgn:2001409",
        "tgn:7012149",
        "tgn:7007526",
        "tgn:7029392"
    ],
    "tgn:id":2334735,
    "tgn:name":"Fork Mississippi Canyon",
    "tgn:placetype":[
        "aat:300008761"
    ]
},
  "bbox": [],
  "geometry": {"coordinates":[-118.1,39.8333],"type":"Point"}
}
=======
{"geometry":{"type":"Point","coordinates":[-118.100000,39.833300]},"type":"Feature","properties":{"hierarchy":["tgn:2334735","tgn:1000001","tgn:2001409","tgn:7012149","tgn:7007526","tgn:7029392"],"placetype":["aat:300008761"],"id":2334735,"name:xx":"Fork Mississippi Canyon"}}
>>>>>>> 03f74aca74312dbeaf24d7e61306dd6a786dc3d0
