{
  "id": 7137413,
  "type": "Feature",
  "properties": {
    "tgn:hierarchy":[
        "tgn:7137413",
        "tgn:7003669",
        "tgn:1000003",
        "tgn:7000084",
        "tgn:7029392"
    ],
    "tgn:id":7137413,
    "tgn:name":"Lanzendorf",
    "tgn:placetype":[
        "aat:300008347"
    ]
},
  "bbox": [],
  "geometry": {"coordinates":[10.883333,49.316667],"type":"Point"}
}