{
  "id": 7290540,
  "type": "Feature",
  "properties": {
    "tgn:hierarchy":[
        "tgn:7290540",
        "tgn:1001702",
        "tgn:1000049",
        "tgn:1000002",
        "tgn:7029392"
    ],
    "tgn:id":7290540,
    "tgn:name":"Dickson, Lago",
    "tgn:placetype":[
        "aat:300008680"
    ]
},
  "bbox": [],
  "geometry": {"coordinates":[-73.116667,-50.85],"type":"Point"}
}