{
  "id": 2245641,
  "type": "Feature",
  "properties": {
    "tgn:hierarchy":[
        "tgn:2245641",
        "tgn:1000001",
        "tgn:7012149",
        "tgn:7029392"
    ],
    "tgn:id":2245641,
    "tgn:name":"Coal Canyon",
    "tgn:placetype":[
        "aat:300008761"
    ]
},
  "bbox": [],
  "geometry": {"coordinates":[-104.5333,36.9833],"type":"Point"}
}