{
  "id": 7078662,
  "type": "Feature",
  "properties": {
    "tgn:hierarchy":[
        "tgn:7078662",
        "tgn:1000003",
        "tgn:7003689",
        "tgn:7000084",
        "tgn:7029392"
    ],
    "tgn:id":7078662,
    "tgn:name":"Wurzbach, Forst",
    "tgn:placetype":[
        "aat:300008863"
    ]
},
  "bbox": [],
  "geometry": {"coordinates":[11.533333,50.433333],"type":"Point"}
}