{
  "id": 2370653,
  "type": "Feature",
  "properties": {
    "tgn:hierarchy":[
        "tgn:2370653",
        "tgn:1000001",
        "tgn:7012149",
        "tgn:2002005",
        "tgn:7007826",
        "tgn:7029392"
    ],
    "tgn:id":2370653,
    "tgn:name":"Hackberry Mine",
    "tgn:placetype":[
        "aat:300000390"
    ]
},
  "bbox": [],
  "geometry": {"coordinates":[-104.9167,31.1333],"type":"Point"}
}