{
  "id": 2565533,
  "type": "Feature",
  "properties": {
    "tgn:hierarchy":[
        "tgn:2565533",
        "tgn:1002171",
        "tgn:1000001",
        "tgn:7012149",
        "tgn:7007710",
        "tgn:7029392"
    ],
    "tgn:id":2565533,
    "tgn:name":"Painter Run",
    "tgn:placetype":[
        "aat:300008699"
    ]
},
  "bbox": [],
  "geometry": {"coordinates":[-80.4167,40.75],"type":"Point"}
}