{
  "id": 7498789,
  "type": "Feature",
  "properties": {
    "tgn:hierarchy":[
        "tgn:7498789",
        "tgn:1000004",
        "tgn:7001009",
        "tgn:1000141",
        "tgn:7029392"
    ],
    "tgn:id":7498789,
    "tgn:name":"Jing Qiao",
    "tgn:placetype":[
        "aat:300007836"
    ]
},
  "bbox": [],
  "geometry": {"coordinates":[120.622327,24.046127],"type":"Point"}
}