{
  "id": 2332037,
  "type": "Feature",
  "properties": {
    "tgn:hierarchy":[
        "tgn:2332037",
        "tgn:1000001",
        "tgn:7012149",
        "tgn:2000218",
        "tgn:7007158",
        "tgn:7029392"
    ],
    "tgn:id":2332037,
    "tgn:name":"Flint Creek",
    "tgn:placetype":[
        "aat:300008706"
    ]
},
  "bbox": [],
  "geometry": {"coordinates":[-107.45,37.6167],"type":"Point"}
}