{
  "id": 7403616,
  "type": "Feature",
  "properties": {
    "tgn:hierarchy":[
        "tgn:7403616",
        "tgn:1000001",
        "tgn:1001906",
        "tgn:7005560",
        "tgn:7029392"
    ],
    "tgn:id":7403616,
    "tgn:name":"El Limbo",
    "tgn:placetype":[
        "aat:300008347"
    ]
},
  "bbox": [],
  "geometry": {"coordinates":[-104.879167,21.258333],"type":"Point"}
}