{
  "id": 2632054,
  "type": "Feature",
  "properties": {
    "tgn:hierarchy":[
        "tgn:2632054",
        "tgn:1000001",
        "tgn:7016172",
        "tgn:7012149",
        "tgn:2000148",
        "tgn:7029392"
    ],
    "tgn:id":2632054,
    "tgn:name":"Rowe Hollow",
    "tgn:placetype":[
        "aat:300008761"
    ]
},
  "bbox": [],
  "geometry": {"coordinates":[-93.8667,35.9167],"type":"Point"}
}