{
  "id": 7024753,
  "type": "Feature",
  "properties": {
    "tgn:hierarchy":[
        "tgn:7024753",
        "tgn:7002878",
        "tgn:1000003",
        "tgn:1000070",
        "tgn:7029392"
    ],
    "tgn:id":7024753,
    "tgn:name":"Auriac-de-Bourzac",
    "tgn:placetype":[
        "aat:300008347"
    ]
},
  "bbox": [],
  "geometry": {"coordinates":[0.25,45.3667],"type":"Point"}
}