{
  "id": 2238259,
  "type": "Feature",
  "properties": {
    "tgn:hierarchy":[
        "tgn:2238259",
        "tgn:1000001",
        "tgn:7012149",
        "tgn:1002999",
        "tgn:7007526",
        "tgn:7029392"
    ],
    "tgn:id":2238259,
    "tgn:name":"Choates Mine",
    "tgn:placetype":[
        "aat:300000390"
    ]
},
  "bbox": [],
  "geometry": {"coordinates":[-119.6667,39.6833],"type":"Point"}
}