{
  "id": 2506663,
  "type": "Feature",
  "properties": {
    "tgn:hierarchy":[
        "tgn:2506663",
        "tgn:1000001",
        "tgn:7012149",
        "tgn:7007157",
        "tgn:7014475",
        "tgn:7029392"
    ],
    "tgn:id":2506663,
    "tgn:name":"Mesa Ridge",
    "tgn:placetype":[
        "aat:300266640"
    ]
},
  "bbox": [],
  "geometry": {"coordinates":[-121.5667,37.45],"type":"Point"}
}