{
  "id": 7520136,
  "type": "Feature",
  "properties": {
    "tgn:hierarchy":[
        "tgn:7520136",
        "tgn:7001242",
        "tgn:7016833",
        "tgn:1001418",
        "tgn:7029392"
    ],
    "tgn:id":7520136,
    "tgn:name:en":"Gabb\u00e2n et Abu Shaq",
    "tgn:placetype":[
        "aat:300266755"
    ]
},
  "bbox": [],
  "geometry": {"coordinates":[26.333333,31.183333],"type":"Point"}
}