{
  "id": 2577068,
  "type": "Feature",
  "properties": {
    "tgn:hierarchy":[
        "tgn:2577068",
        "tgn:7006450",
        "tgn:1000001",
        "tgn:7012149",
        "tgn:2000089",
        "tgn:7029392"
    ],
    "tgn:id":2577068,
    "tgn:name":"Peter John Mountain",
    "tgn:placetype":[
        "aat:300008798"
    ]
},
  "bbox": [],
  "geometry": {"coordinates":[-144.85,68.0833],"type":"Point"}
}