{
  "id": 2355836,
  "type": "Feature",
  "properties": {
    "tgn:hierarchy":[
        "tgn:2355836",
        "tgn:1000001",
        "tgn:7012149",
        "tgn:2001161",
        "tgn:7007522",
        "tgn:7029392"
    ],
    "tgn:id":2355836,
    "tgn:name":"Goose Lake",
    "tgn:placetype":[
        "aat:300008680"
    ]
},
  "bbox": [],
  "geometry": {"coordinates":[-91.0333,33.15],"type":"Point"}
}