<<<<<<< HEAD
{
  "id": 2158086,
  "type": "Feature",
  "properties": {
    "tgn:hierarchy":[
        "tgn:2158086",
        "tgn:1000001",
        "tgn:7012149",
        "tgn:2000970",
        "tgn:7007520",
        "tgn:7029392"
    ],
    "tgn:id":2158086,
    "tgn:name":"Beaver Pond",
    "tgn:placetype":[
        "aat:300008905"
    ]
},
  "bbox": [],
  "geometry": {"coordinates":[-85.95,44.0],"type":"Point"}
}
=======
{"geometry":{"type":"Point","coordinates":[-85.950000,44.000000]},"type":"Feature","properties":{"hierarchy":["tgn:2158086","tgn:1000001","tgn:7012149","tgn:2000970","tgn:7007520","tgn:7029392"],"placetype":["aat:300008905"],"id":2158086,"name:xx":"Beaver Pond"}}
>>>>>>> 03f74aca74312dbeaf24d7e61306dd6a786dc3d0
