{
  "id": 2706453,
  "type": "Feature",
  "properties": {
    "tgn:hierarchy":[
        "tgn:2706453",
        "tgn:1000001",
        "tgn:7012149",
        "tgn:7014350",
        "tgn:7007922",
        "tgn:7029392"
    ],
    "tgn:id":2706453,
    "tgn:name":"Swan Creek",
    "tgn:placetype":[
        "aat:300008706"
    ]
},
  "bbox": [],
  "geometry": {"coordinates":[-89.25,42.6167],"type":"Point"}
}