{
  "id": 7567578,
  "type": "Feature",
  "properties": {
    "tgn:hierarchy":[
        "tgn:7567578",
        "tgn:1000004",
        "tgn:7000198",
        "tgn:1001996",
        "tgn:7029392"
    ],
    "tgn:id":7567578,
    "tgn:name:en":"Panjeli Jamogi Protected Forest",
    "tgn:placetype":[
        "aat:300008863"
    ]
},
  "bbox": [],
  "geometry": {"coordinates":[77.024444,31.2125],"type":"Point"}
}