{
  "id": 2561692,
  "type": "Feature",
  "properties": {
    "tgn:hierarchy":[
        "tgn:2561692",
        "tgn:1000001",
        "tgn:7012149",
        "tgn:1003041",
        "tgn:7007710",
        "tgn:7029392"
    ],
    "tgn:id":2561692,
    "tgn:name":"Osterhout Creek",
    "tgn:placetype":[
        "aat:300008706"
    ]
},
  "bbox": [],
  "geometry": {"coordinates":[-75.85,41.5333],"type":"Point"}
}