{
  "id": 2302023,
  "type": "Feature",
  "properties": {
    "tgn:hierarchy":[
        "tgn:2302023",
        "tgn:1000001",
        "tgn:7012149",
        "tgn:2002005",
        "tgn:7007826",
        "tgn:7029392"
    ],
    "tgn:id":2302023,
    "tgn:name":"Dusty Draw",
    "tgn:placetype":[
        "aat:300008761"
    ]
},
  "bbox": [],
  "geometry": {"coordinates":[-104.9167,31.3333],"type":"Point"}
}