{
  "id": 1046577,
  "type": "Feature",
  "properties": {
    "tgn:hierarchy":[
        "tgn:1046577",
        "tgn:7002994",
        "tgn:1000003",
        "tgn:7002997",
        "tgn:1000080",
        "tgn:7029392"
    ],
    "tgn:id":1046577,
    "tgn:name":"San Martino di Lupari",
    "tgn:placetype":[
        "aat:300008347"
    ]
},
  "bbox": [],
  "geometry": {"coordinates":[11.85,45.65],"type":"Point"}
}