{
  "id": 7005047,
  "type": "Feature",
  "properties": {
    "tgn:hierarchy":[
        "tgn:7005047",
        "tgn:7003170",
        "tgn:1000003",
        "tgn:7003125",
        "tgn:1000080",
        "tgn:7029392"
    ],
    "tgn:id":7005047,
    "tgn:name":"Nocera Umbra",
    "tgn:placetype":[
        "aat:300008347"
    ]
},
  "bbox": [],
  "geometry": {"coordinates":[12.783333,43.083333],"type":"Point"}
}