{
  "id": 2431000,
  "type": "Feature",
  "properties": {
    "tgn:hierarchy":[
        "tgn:2431000",
        "tgn:1000001",
        "tgn:2000467",
        "tgn:7012149",
        "tgn:7007250",
        "tgn:7029392"
    ],
    "tgn:id":2431000,
    "tgn:name":"Kane Spring",
    "tgn:placetype":[
        "aat:300008697"
    ]
},
  "bbox": [],
  "geometry": {"coordinates":[-113.4333,42.1833],"type":"Point"}
}