{
  "id": 7553932,
  "type": "Feature",
  "properties": {
    "tgn:hierarchy":[
        "tgn:7553932",
        "tgn:1000004",
        "tgn:1001869",
        "tgn:7000198",
        "tgn:7029392"
    ],
    "tgn:id":7553932,
    "tgn:name:en":"Matw\u0101d",
    "tgn:placetype":[
        "aat:300008347"
    ]
},
  "bbox": [],
  "geometry": {"coordinates":[72.833333,20.916667],"type":"Point"}
}