{
  "id": 7029982,
  "type": "Feature",
  "properties": {
    "tgn:hierarchy":[
        "tgn:7029982",
        "tgn:7002445",
        "tgn:1000003",
        "tgn:7008166",
        "tgn:7008591",
        "tgn:7029392"
    ],
    "tgn:id":7029982,
    "tgn:name:ang":"Flatesbi",
    "tgn:name:en":"Flaxby",
    "tgn:placetype":[
        "aat:300008347",
        "aat:300008372"
    ]
},
  "bbox": [],
  "geometry": {"coordinates":[-1.389,54.001],"type":"Point"}
}