{
  "id": 7485907,
  "type": "Feature",
  "properties": {
    "tgn:hierarchy":[
        "tgn:7485907",
        "tgn:1000004",
        "tgn:7490934",
        "tgn:1000141",
        "tgn:7029392"
    ],
    "tgn:id":7485907,
    "tgn:name":"Taiye",
    "tgn:placetype":[
        "aat:300008347"
    ]
},
  "bbox": [],
  "geometry": {"coordinates":[120.224722,22.909167],"type":"Point"}
}