{
  "id": 7526075,
  "type": "Feature",
  "properties": {
    "tgn:hierarchy":[
        "tgn:7526075",
        "tgn:7001242",
        "tgn:7016833",
        "tgn:1001091",
        "tgn:7029392"
    ],
    "tgn:id":7526075,
    "tgn:name":"Al Jam'\u012byah ash Shar'\u012byah",
    "tgn:placetype":[
        "aat:300007544"
    ]
},
  "bbox": [],
  "geometry": {"coordinates":[31.313793,30.047936],"type":"Point"}
}