{
  "id": 7319621,
  "type": "Feature",
  "properties": {
    "tgn:hierarchy":[
        "tgn:7319621",
        "tgn:7016598",
        "tgn:1000049",
        "tgn:1000002",
        "tgn:7029392"
    ],
    "tgn:id":7319621,
    "tgn:name":"Agua Dulce, Cerro",
    "tgn:placetype":[
        "aat:300008795"
    ]
},
  "bbox": [],
  "geometry": {"coordinates":[-68.833333,-23.05],"type":"Point"}
}