{
  "id": 2658190,
  "type": "Feature",
  "properties": {
    "tgn:hierarchy":[
        "tgn:2658190",
        "tgn:1000001",
        "tgn:7012149",
        "tgn:2001888",
        "tgn:7007825",
        "tgn:7029392"
    ],
    "tgn:id":2658190,
    "tgn:name":"Shelton Creek",
    "tgn:placetype":[
        "aat:300008706"
    ]
},
  "bbox": [],
  "geometry": {"coordinates":[-86.3833,35.1167],"type":"Point"}
}