<<<<<<< HEAD
{
  "id": 7371939,
  "type": "Feature",
  "properties": {
    "tgn:hierarchy":[
        "tgn:7371939",
        "tgn:7005586",
        "tgn:1000001",
        "tgn:7005560",
        "tgn:7029392"
    ],
    "tgn:id":7371939,
    "tgn:name":"La Calera",
    "tgn:placetype":[
        "aat:300008347"
    ]
},
  "bbox": [],
  "geometry": {"coordinates":[-104.2,20.2],"type":"Point"}
}
=======
{"geometry":{"type":"Point","coordinates":[-104.200000,20.200000]},"type":"Feature","properties":{"hierarchy":["tgn:7371939","tgn:7005586","tgn:1000001","tgn:7005560","tgn:7029392"],"placetype":["aat:300008347"],"id":7371939,"name:xx":"La Calera"}}
>>>>>>> 03f74aca74312dbeaf24d7e61306dd6a786dc3d0
