{
  "id": 7192826,
  "type": "Feature",
  "properties": {
    "tgn:hierarchy":[
        "tgn:7192826",
        "tgn:7003669",
        "tgn:1000003",
        "tgn:7000084",
        "tgn:7029392"
    ],
    "tgn:id":7192826,
    "tgn:name":"Frauen\u00f6d",
    "tgn:placetype":[
        "aat:300000206"
    ]
},
  "bbox": [],
  "geometry": {"coordinates":[12.116667,47.966667],"type":"Point"}
}