{
  "id": 2000825,
  "type": "Feature",
  "properties": {
    "tgn:hierarchy":[
        "tgn:2000825",
        "tgn:1000001",
        "tgn:7012149",
        "tgn:7007255",
        "tgn:7029392"
    ],
    "tgn:id":2000825,
    "tgn:name":"Meade",
    "tgn:placetype":[
        "aat:300387145",
        "aat:300000771"
    ]
},
  "bbox": [],
  "geometry": {"coordinates":[-86.2333,37.9667],"type":"Point"}
}