{
  "id": 7314979,
  "type": "Feature",
  "properties": {
    "tgn:hierarchy":[
        "tgn:7314979",
        "tgn:1001708",
        "tgn:1000049",
        "tgn:1000002",
        "tgn:7029392"
    ],
    "tgn:id":7314979,
    "tgn:name":"Leyda, Estero de",
    "tgn:placetype":[
        "aat:300008699"
    ]
},
  "bbox": [],
  "geometry": {"coordinates":[-71.566667,-33.65],"type":"Point"}
}