{
  "id": 2062119,
  "type": "Feature",
  "properties": {
    "tgn:hierarchy":[
        "tgn:2062119",
        "tgn:2001317",
        "tgn:1000001",
        "tgn:7012149",
        "tgn:7007525",
        "tgn:7029392"
    ],
    "tgn:id":2062119,
    "tgn:name":"Elgin",
    "tgn:placetype":[
        "aat:300008347"
    ]
},
  "bbox": [],
  "geometry": {"coordinates":[-98.0833,41.9833],"type":"Point"}
}