{
  "id": 2756592,
  "type": "Feature",
  "properties": {
    "tgn:hierarchy":[
        "tgn:2756592",
        "tgn:7019618",
        "tgn:1000001",
        "tgn:7012149",
        "tgn:7007564",
        "tgn:7029392"
    ],
    "tgn:id":2756592,
    "tgn:name":"Wellman Pond",
    "tgn:placetype":[
        "aat:300008680"
    ]
},
  "bbox": [],
  "geometry": {"coordinates":[-72.25,43.0667],"type":"Point"}
}