{
  "id": 1070964,
  "type": "Feature",
  "properties": {
    "tgn:hierarchy":[
        "tgn:1070964",
        "tgn:1000004",
        "tgn:7002081",
        "tgn:1000111",
        "tgn:7029392"
    ],
    "tgn:id":1070964,
    "tgn:name":"Qianjiazhuang",
    "tgn:placetype":[
        "aat:300008347"
    ]
},
  "bbox": [],
  "geometry": {"coordinates":[120.2833,32.2667],"type":"Point"}
}