{
  "id": 7185552,
  "type": "Feature",
  "properties": {
    "tgn:hierarchy":[
        "tgn:7185552",
        "tgn:1000003",
        "tgn:7000094",
        "tgn:7000084",
        "tgn:7029392"
    ],
    "tgn:id":7185552,
    "tgn:name":"Grambow",
    "tgn:placetype":[
        "aat:300008347"
    ]
},
  "bbox": [],
  "geometry": {"coordinates":[14.333333,53.416667],"type":"Point"}
}