<<<<<<< HEAD
{
  "id": 2255669,
  "type": "Feature",
  "properties": {
    "tgn:hierarchy":[
        "tgn:2255669",
        "tgn:1000001",
        "tgn:7012149",
        "tgn:2002114",
        "tgn:7007827",
        "tgn:7029392"
    ],
    "tgn:id":2255669,
    "tgn:name":"Copley Creek",
    "tgn:placetype":[
        "aat:300008706"
    ]
},
  "bbox": [],
  "geometry": {"coordinates":[-112.2167,38.9],"type":"Point"}
}
=======
{"geometry":{"type":"Point","coordinates":[-112.216700,38.900000]},"type":"Feature","properties":{"hierarchy":["tgn:2255669","tgn:1000001","tgn:7012149","tgn:2002114","tgn:7007827","tgn:7029392"],"placetype":["aat:300008706"],"id":2255669,"name:xx":"Copley Creek"}}
>>>>>>> 03f74aca74312dbeaf24d7e61306dd6a786dc3d0
