{
  "id": 7491289,
  "type": "Feature",
  "properties": {
    "tgn:hierarchy":[
        "tgn:7491289",
        "tgn:1000004",
        "tgn:7490934",
        "tgn:1000141",
        "tgn:7029392"
    ],
    "tgn:id":7491289,
    "tgn:name":"Niuxi Shan",
    "tgn:placetype":[
        "aat:300008777"
    ]
},
  "bbox": [],
  "geometry": {"coordinates":[120.379444,22.927222],"type":"Point"}
}