<<<<<<< HEAD
{
  "id": 7352612,
  "type": "Feature",
  "properties": {
    "tgn:hierarchy":[
        "tgn:7352612",
        "tgn:7005580",
        "tgn:1000001",
        "tgn:7005560",
        "tgn:7029392"
    ],
    "tgn:id":7352612,
    "tgn:name":"Buenavista",
    "tgn:placetype":[
        "aat:300008347"
    ]
},
  "bbox": [],
  "geometry": {"coordinates":[-93.55,15.85],"type":"Point"}
}
=======
{"geometry":{"type":"Point","coordinates":[-93.550000,15.850000]},"type":"Feature","properties":{"hierarchy":["tgn:7352612","tgn:7005580","tgn:1000001","tgn:7005560","tgn:7029392"],"placetype":["aat:300008347"],"id":7352612,"name:xx":"Buenavista"}}
>>>>>>> 03f74aca74312dbeaf24d7e61306dd6a786dc3d0
