{
  "id": 2596744,
  "type": "Feature",
  "properties": {
    "tgn:hierarchy":[
        "tgn:2596744",
        "tgn:1000001",
        "tgn:7012149",
        "tgn:2002374",
        "tgn:7007923",
        "tgn:7029392"
    ],
    "tgn:id":2596744,
    "tgn:name":"Powell Creek",
    "tgn:placetype":[
        "aat:300008706"
    ]
},
  "bbox": [],
  "geometry": {"coordinates":[-107.1333,44.3333],"type":"Point"}
}