{
  "id": 2425090,
  "type": "Feature",
  "properties": {
    "tgn:hierarchy":[
        "tgn:2425090",
        "tgn:1000001",
        "tgn:2001013",
        "tgn:7012149",
        "tgn:7007521",
        "tgn:7029392"
    ],
    "tgn:id":2425090,
    "tgn:name":"Johnson Lake",
    "tgn:placetype":[
        "aat:300008680"
    ]
},
  "bbox": [],
  "geometry": {"coordinates":[-95.4833,47.6667],"type":"Point"}
}