{
  "id": 7366066,
  "type": "Feature",
  "properties": {
    "tgn:hierarchy":[
        "tgn:7366066",
        "tgn:7005585",
        "tgn:1000001",
        "tgn:7005560",
        "tgn:7029392"
    ],
    "tgn:id":7366066,
    "tgn:name":"Gallinero",
    "tgn:placetype":[
        "aat:300008347"
    ]
},
  "bbox": [],
  "geometry": {"coordinates":[-99.733333,16.816667],"type":"Point"}
}