{
  "id": 2131085,
  "type": "Feature",
  "properties": {
    "tgn:hierarchy":[
        "tgn:2131085",
        "tgn:1000001",
        "tgn:7012149",
        "tgn:7007157",
        "tgn:1002608",
        "tgn:7029392"
    ],
    "tgn:id":2131085,
    "tgn:name":"Alpine Butte",
    "tgn:placetype":[
        "aat:300008798"
    ]
},
  "bbox": [],
  "geometry": {"coordinates":[-117.8833,34.6167],"type":"Point"}
}