{
  "id": 2785336,
  "type": "Feature",
  "properties": {
    "tgn:hierarchy":[
        "tgn:2785336",
        "tgn:1000001",
        "tgn:7012149",
        "tgn:2001709",
        "tgn:7007708",
        "tgn:7029392"
    ],
    "tgn:id":2785336,
    "tgn:name":"Yellowjacket Creek",
    "tgn:placetype":[
        "aat:300008706"
    ]
},
  "bbox": [],
  "geometry": {"coordinates":[-119.2333,43.9167],"type":"Point"}
}