{
  "id": 2307207,
  "type": "Feature",
  "properties": {
    "tgn:hierarchy":[
        "tgn:2307207",
        "tgn:1000001",
        "tgn:7012149",
        "tgn:7007157",
        "tgn:7014475",
        "tgn:7029392"
    ],
    "tgn:id":2307207,
    "tgn:name":"East Fork Pacheco Creek",
    "tgn:placetype":[
        "aat:300008706"
    ]
},
  "bbox": [],
  "geometry": {"coordinates":[-121.2167,37.1333],"type":"Point"}
}