{
  "id": 7087771,
  "type": "Feature",
  "properties": {
    "tgn:hierarchy":[
        "tgn:7087771",
        "tgn:7003669",
        "tgn:1000003",
        "tgn:7000084",
        "tgn:7029392"
    ],
    "tgn:id":7087771,
    "tgn:name":"Weg",
    "tgn:placetype":[
        "aat:300008347"
    ]
},
  "bbox": [],
  "geometry": {"coordinates":[12.233333,49.116667],"type":"Point"}
}