{
  "id": 1019689,
  "type": "Feature",
  "properties": {
    "tgn:hierarchy":[
        "tgn:1019689",
        "tgn:7006477",
        "tgn:1001328",
        "tgn:1000002",
        "tgn:7029392"
    ],
    "tgn:id":1019689,
    "tgn:name":"Libertador General San Martin",
    "tgn:placetype":[
        "aat:300008347"
    ]
},
  "bbox": [],
  "geometry": {"coordinates":[-64.75,-23.8333],"type":"Point"}
}