{
  "id": 2355244,
  "type": "Feature",
  "properties": {
    "tgn:hierarchy":[
        "tgn:2355244",
        "tgn:1000001",
        "tgn:7012149",
        "tgn:7007522",
        "tgn:7029392"
    ],
    "tgn:id":2355244,
    "tgn:name":"Goodwin Creek",
    "tgn:placetype":[
        "aat:300008706"
    ]
},
  "bbox": [],
  "geometry": {"coordinates":[-89.5667,34.1833],"type":"Point"}
}