{
  "id": 2441313,
  "type": "Feature",
  "properties": {
    "tgn:hierarchy":[
        "tgn:2441313",
        "tgn:1000001",
        "tgn:7012149",
        "tgn:1002830",
        "tgn:7007826",
        "tgn:7029392"
    ],
    "tgn:id":2441313,
    "tgn:name":"Knox Branch",
    "tgn:placetype":[
        "aat:300008699"
    ]
},
  "bbox": [],
  "geometry": {"coordinates":[-96.5167,30.9333],"type":"Point"}
}