{
  "id": 2148532,
  "type": "Feature",
  "properties": {
    "tgn:hierarchy":[
        "tgn:2148532",
        "tgn:1000001",
        "tgn:7012149",
        "tgn:2000219",
        "tgn:7007158",
        "tgn:7029392"
    ],
    "tgn:id":2148532,
    "tgn:name":"Barnes Canyon",
    "tgn:placetype":[
        "aat:300008761"
    ]
},
  "bbox": [],
  "geometry": {"coordinates":[-105.0333,37.3833],"type":"Point"}
}