{
  "id": 2456631,
  "type": "Feature",
  "properties": {
    "tgn:hierarchy":[
        "tgn:2456631",
        "tgn:1000001",
        "tgn:7012149",
        "tgn:2000837",
        "tgn:7007255",
        "tgn:7029392"
    ],
    "tgn:id":2456631,
    "tgn:name":"Little Island Branch",
    "tgn:placetype":[
        "aat:300008699"
    ]
},
  "bbox": [],
  "geometry": {"coordinates":[-82.3333,37.2833],"type":"Point"}
}