{
  "id": 1129962,
  "type": "Feature",
  "properties": {
    "tgn:hierarchy":[
        "tgn:1129962",
        "tgn:7000367",
        "tgn:1000004",
        "tgn:1000133",
        "tgn:7029392"
    ],
    "tgn:id":1129962,
    "tgn:name":"Shigar",
    "tgn:placetype":[
        "aat:300008707"
    ]
},
  "bbox": [],
  "geometry": {"coordinates":[75.7167,35.45],"type":"Point"}
}