{
  "id": 7459598,
  "type": "Feature",
  "properties": {
    "tgn:hierarchy":[
        "tgn:7459598",
        "tgn:7002444",
        "tgn:1000003",
        "tgn:5000460",
        "tgn:7008591",
        "tgn:7029392"
    ],
    "tgn:id":7459598,
    "tgn:name:en":"Port of Menteith",
    "tgn:placetype":[
        "aat:300008347"
    ]
},
  "bbox": [],
  "geometry": {"coordinates":[-4.266667,56.183333],"type":"Point"}
}