{
  "id": 7034509,
  "type": "Feature",
  "properties": {
    "tgn:hierarchy":[
        "tgn:7034509",
        "tgn:1003500",
        "tgn:1000003",
        "tgn:7010380",
        "tgn:1000080",
        "tgn:7029392"
    ],
    "tgn:id":7034509,
    "tgn:name":"Masseria Amendolecchia",
    "tgn:placetype":[
        "aat:300000206"
    ]
},
  "bbox": [],
  "geometry": {"coordinates":[17.093056,40.5825],"type":"Point"}
}