<<<<<<< HEAD
{
  "id": 7478383,
  "type": "Feature",
  "properties": {
    "tgn:hierarchy":[
        "tgn:7478383",
        "tgn:1000004",
        "tgn:7489179",
        "tgn:1000141",
        "tgn:7029392"
    ],
    "tgn:id":7478383,
    "tgn:name":"Dongjin Qiao",
    "tgn:placetype":[
        "aat:300007836"
    ]
},
  "bbox": [],
  "geometry": {"coordinates":[121.768798,24.7364],"type":"Point"}
}
=======
{"geometry":{"type":"Point","coordinates":[121.768798,24.736400]},"type":"Feature","properties":{"hierarchy":["tgn:7478383","tgn:1000004","tgn:7489179","tgn:1000141","tgn:7029392"],"placetype":["aat:300007836"],"id":7478383,"name:xx":"Dongjin Qiao"}}
>>>>>>> 03f74aca74312dbeaf24d7e61306dd6a786dc3d0
