{
  "id": 2740854,
  "type": "Feature",
  "properties": {
    "tgn:hierarchy":[
        "tgn:2740854",
        "tgn:1000001",
        "tgn:7012149",
        "tgn:2002117",
        "tgn:7007827",
        "tgn:7029392"
    ],
    "tgn:id":2740854,
    "tgn:name":"Upper Sage Creek Spring",
    "tgn:placetype":[
        "aat:300008697"
    ]
},
  "bbox": [],
  "geometry": {"coordinates":[-111.2333,41.7667],"type":"Point"}
}