{
  "id": 1002758,
  "type": "Feature",
  "properties": {
    "tgn:hierarchy":[
        "tgn:1002758",
        "tgn:1000001",
        "tgn:7012149",
        "tgn:7007568",
        "tgn:7029392"
    ],
    "tgn:id":1002758,
    "tgn:name":"Oswego",
    "tgn:placetype":[
        "aat:300387145",
        "aat:300000771"
    ]
},
  "bbox": [],
  "geometry": {"coordinates":[-76.15,43.45],"type":"Point"}
}