{
  "id": 7295594,
  "type": "Feature",
  "properties": {
    "tgn:hierarchy":[
        "tgn:7295594",
        "tgn:7002813",
        "tgn:7002758",
        "tgn:1000003",
        "tgn:1000095",
        "tgn:7029392"
    ],
    "tgn:id":7295594,
    "tgn:name":"La Perla",
    "tgn:placetype":[
        "aat:300387036"
    ]
},
  "bbox": [],
  "geometry": {"coordinates":[-5.43,36.0575],"type":"Point"}
}