{
  "id": 2056593,
  "type": "Feature",
  "properties": {
    "tgn:hierarchy":[
        "tgn:2056593",
        "tgn:1000001",
        "tgn:2001100",
        "tgn:7012149",
        "tgn:7007522",
        "tgn:7029392"
    ],
    "tgn:id":2056593,
    "tgn:name":"Hazlehurst",
    "tgn:placetype":[
        "aat:300008347",
        "aat:300008416"
    ]
},
  "bbox": [],
  "geometry": {"coordinates":[-90.3833,31.85],"type":"Point"}
}