{
  "id": 7349828,
  "type": "Feature",
  "properties": {
    "tgn:hierarchy":[
        "tgn:7349828",
        "tgn:1000001",
        "tgn:7005599",
        "tgn:7005560",
        "tgn:7029392"
    ],
    "tgn:id":7349828,
    "tgn:name":"Acateno",
    "tgn:placetype":[
        "aat:300007783"
    ]
},
  "bbox": [],
  "geometry": {"coordinates":[-96.983333,18.983333],"type":"Point"}
}