{
  "id": 2094036,
  "type": "Feature",
  "properties": {
    "tgn:hierarchy":[
        "tgn:2094036",
        "tgn:1000001",
        "tgn:1002266",
        "tgn:7012149",
        "tgn:7007710",
        "tgn:7029392"
    ],
    "tgn:id":2094036,
    "tgn:name":"Valley Forge Christian College",
    "tgn:placetype":[
        "aat:300006610"
    ]
},
  "bbox": [],
  "geometry": {"coordinates":[-75.5333,40.1167],"type":"Point"}
}