{
  "id": 7565333,
  "type": "Feature",
  "properties": {
    "tgn:hierarchy":[
        "tgn:7565333",
        "tgn:1000004",
        "tgn:7000198",
        "tgn:7016722",
        "tgn:7029392"
    ],
    "tgn:id":7565333,
    "tgn:name:en":"Kal\u0101npur",
    "tgn:placetype":[
        "aat:300008347"
    ]
},
  "bbox": [],
  "geometry": {"coordinates":[79.428394,26.468397],"type":"Point"}
}