{
  "id": 2414277,
  "type": "Feature",
  "properties": {
    "tgn:hierarchy":[
        "tgn:2414277",
        "tgn:1000001",
        "tgn:7012149",
        "tgn:2000786",
        "tgn:7007255",
        "tgn:7029392"
    ],
    "tgn:id":2414277,
    "tgn:name":"Iron Ore Hill",
    "tgn:placetype":[
        "aat:300008798"
    ]
},
  "bbox": [],
  "geometry": {"coordinates":[-86.9333,37.8667],"type":"Point"}
}