{
  "id": 2674850,
  "type": "Feature",
  "properties": {
    "tgn:hierarchy":[
        "tgn:2674850",
        "tgn:1000001",
        "tgn:7012149",
        "tgn:2000891",
        "tgn:7007256",
        "tgn:7029392"
    ],
    "tgn:id":2674850,
    "tgn:name":"Socola Canal",
    "tgn:placetype":[
        "aat:300006075"
    ]
},
  "bbox": [],
  "geometry": {"coordinates":[-89.75,29.5167],"type":"Point"}
}