<<<<<<< HEAD
{
  "id": 2764113,
  "type": "Feature",
  "properties": {
    "tgn:hierarchy":[
        "tgn:2764113",
        "tgn:1000001",
        "tgn:1002712",
        "tgn:7012149",
        "tgn:7007159",
        "tgn:7029392"
    ],
    "tgn:id":2764113,
    "tgn:name":"Wheeler Island",
    "tgn:placetype":[
        "aat:300008791"
    ]
},
  "bbox": [],
  "geometry": {"coordinates":[-72.75,41.25],"type":"Point"}
}
=======
{"geometry":{"type":"Point","coordinates":[-72.750000,41.250000]},"type":"Feature","properties":{"hierarchy":["tgn:2764113","tgn:1000001","tgn:1002712","tgn:7012149","tgn:7007159","tgn:7029392"],"placetype":["aat:300008791"],"id":2764113,"name:xx":"Wheeler Island"}}
>>>>>>> 03f74aca74312dbeaf24d7e61306dd6a786dc3d0
