{
  "id": 7339523,
  "type": "Feature",
  "properties": {
    "tgn:hierarchy":[
        "tgn:7339523",
        "tgn:7002806",
        "tgn:7001158",
        "tgn:1000003",
        "tgn:1000095",
        "tgn:7029392"
    ],
    "tgn:id":7339523,
    "tgn:name":"Crespos",
    "tgn:placetype":[
        "aat:300008347"
    ]
},
  "bbox": [],
  "geometry": {"coordinates":[-4.966667,40.866667],"type":"Point"}
}