{
  "id": 7151101,
  "type": "Feature",
  "properties": {
    "tgn:hierarchy":[
        "tgn:7151101",
        "tgn:7003669",
        "tgn:1000003",
        "tgn:7000084",
        "tgn:7029392"
    ],
    "tgn:id":7151101,
    "tgn:name":"Irensfelden",
    "tgn:placetype":[
        "aat:300000206"
    ]
},
  "bbox": [],
  "geometry": {"coordinates":[12.766667,48.95],"type":"Point"}
}