<<<<<<< HEAD
{
  "id": 7476705,
  "type": "Feature",
  "properties": {
    "tgn:hierarchy":[
        "tgn:7476705",
        "tgn:7487020",
        "tgn:1000004",
        "tgn:1000141",
        "tgn:7029392"
    ],
    "tgn:id":7476705,
    "tgn:name":"Daluxi",
    "tgn:placetype":[
        "aat:300008347"
    ]
},
  "bbox": [],
  "geometry": {"coordinates":[120.820618,24.663457],"type":"Point"}
}
=======
{"geometry":{"type":"Point","coordinates":[120.820618,24.663457]},"type":"Feature","properties":{"hierarchy":["tgn:7476705","tgn:7487020","tgn:1000004","tgn:1000141","tgn:7029392"],"placetype":["aat:300008347"],"id":7476705,"name:xx":"Daluxi"}}
>>>>>>> 03f74aca74312dbeaf24d7e61306dd6a786dc3d0
