{
  "id": 7579203,
  "type": "Feature",
  "properties": {
    "tgn:hierarchy":[
        "tgn:7579203",
        "tgn:1000004",
        "tgn:7000198",
        "tgn:7016788",
        "tgn:7029392"
    ],
    "tgn:id":7579203,
    "tgn:name:en":"Sohadra Nad\u012b",
    "tgn:placetype":[
        "aat:300008699"
    ]
},
  "bbox": [],
  "geometry": {"coordinates":[75.73325,26.244393],"type":"Point"}
}