{
  "id": 2432540,
  "type": "Feature",
  "properties": {
    "tgn:hierarchy":[
        "tgn:2432540",
        "tgn:1000001",
        "tgn:2001436",
        "tgn:7012149",
        "tgn:7007566",
        "tgn:7029392"
    ],
    "tgn:id":2432540,
    "tgn:name":"Kee Tank",
    "tgn:placetype":[
        "aat:300006191"
    ]
},
  "bbox": [],
  "geometry": {"coordinates":[-104.35,32.3667],"type":"Point"}
}