<<<<<<< HEAD
{
  "id": 2761903,
  "type": "Feature",
  "properties": {
    "tgn:hierarchy":[
        "tgn:2761903",
        "tgn:1000001",
        "tgn:7012149",
        "tgn:7007157",
        "tgn:1002828",
        "tgn:7029392"
    ],
    "tgn:id":2761903,
    "tgn:name":"West Ridge",
    "tgn:placetype":[
        "aat:300266640"
    ]
},
  "bbox": [],
  "geometry": {"coordinates":[-116.7333,33.7167],"type":"Point"}
}
=======
{"geometry":{"type":"Point","coordinates":[-116.733300,33.716700]},"type":"Feature","properties":{"hierarchy":["tgn:2761903","tgn:1000001","tgn:7012149","tgn:7007157","tgn:1002828","tgn:7029392"],"placetype":["aat:300266640"],"id":2761903,"name:xx":"West Ridge"}}
>>>>>>> 03f74aca74312dbeaf24d7e61306dd6a786dc3d0
