{
  "id": 2687210,
  "type": "Feature",
  "properties": {
    "tgn:hierarchy":[
        "tgn:2687210",
        "tgn:1000001",
        "tgn:2002102",
        "tgn:7012149",
        "tgn:7007827",
        "tgn:7029392"
    ],
    "tgn:id":2687210,
    "tgn:name":"Spring Hollow",
    "tgn:placetype":[
        "aat:300008761"
    ]
},
  "bbox": [],
  "geometry": {"coordinates":[-113.4333,41.9667],"type":"Point"}
}