{
  "id": 2561407,
  "type": "Feature",
  "properties": {
    "tgn:hierarchy":[
        "tgn:2561407",
        "tgn:1000001",
        "tgn:7012149",
        "tgn:1002699",
        "tgn:7007708",
        "tgn:7029392"
    ],
    "tgn:id":2561407,
    "tgn:name":"Osburn Reservoir",
    "tgn:placetype":[
        "aat:300006191"
    ]
},
  "bbox": [],
  "geometry": {"coordinates":[-122.2333,45.4667],"type":"Point"}
}