{
  "id": 7444917,
  "type": "Feature",
  "properties": {
    "tgn:hierarchy":[
        "tgn:7444917",
        "tgn:7002445",
        "tgn:1000003",
        "tgn:7008174",
        "tgn:7008591",
        "tgn:7029392"
    ],
    "tgn:id":7444917,
    "tgn:name:en":"Trysull",
    "tgn:placetype":[
        "aat:300008347"
    ]
},
  "bbox": [],
  "geometry": {"coordinates":[-2.233333,52.533333],"type":"Point"}
}