{
  "id": 2088968,
  "type": "Feature",
  "properties": {
    "tgn:hierarchy":[
        "tgn:2088968",
        "tgn:1000001",
        "tgn:7013387",
        "tgn:7012149",
        "tgn:7007710",
        "tgn:7029392"
    ],
    "tgn:id":2088968,
    "tgn:name":"Greshville",
    "tgn:placetype":[
        "aat:300008347"
    ]
},
  "bbox": [],
  "geometry": {"coordinates":[-75.65,40.3167],"type":"Point"}
}