{
  "id": 7011369,
  "type": "Feature",
  "properties": {
    "tgn:hierarchy":[
        "tgn:7011369",
        "tgn:7017076",
        "tgn:1000003",
        "tgn:1000074",
        "tgn:7029392"
    ],
    "tgn:id":7011369,
    "tgn:name":"Messin\u00eda",
    "tgn:placetype":[
        "aat:300387145",
        "aat:300000772",
        "aat:300387131"
    ]
},
  "bbox": [],
  "geometry": {"coordinates":[21.8333,37.25],"type":"Point"}
}