{
  "id": 7019398,
  "type": "Feature",
  "properties": {
    "tgn:hierarchy":[
        "tgn:7019398",
        "tgn:1000001",
        "tgn:7012149",
        "tgn:2001437",
        "tgn:7007566",
        "tgn:7029392"
    ],
    "tgn:id":7019398,
    "tgn:name":"Glaze Tank",
    "tgn:placetype":[
        "aat:300006191"
    ]
},
  "bbox": [],
  "geometry": {"coordinates":[-108.45,32.3667],"type":"Point"}
}