{
  "id": 2480085,
  "type": "Feature",
  "properties": {
    "tgn:hierarchy":[
        "tgn:2480085",
        "tgn:1000001",
        "tgn:1002194",
        "tgn:7012149",
        "tgn:7007710",
        "tgn:7029392"
    ],
    "tgn:id":2480085,
    "tgn:name":"Lake Knob",
    "tgn:placetype":[
        "aat:300008798"
    ]
},
  "bbox": [],
  "geometry": {"coordinates":[-76.6333,41.5833],"type":"Point"}
}