{
  "id": 2232171,
  "type": "Feature",
  "properties": {
    "tgn:hierarchy":[
        "tgn:2232171",
        "tgn:1000001",
        "tgn:7012149",
        "tgn:1002641",
        "tgn:7007240",
        "tgn:7029392"
    ],
    "tgn:id":2232171,
    "tgn:name":"Chancy Bay",
    "tgn:placetype":[
        "aat:300008905"
    ]
},
  "bbox": [],
  "geometry": {"coordinates":[-80.65,27.0833],"type":"Point"}
}