{
  "id": 1055528,
  "type": "Feature",
  "properties": {
    "tgn:hierarchy":[
        "tgn:1055528",
        "tgn:1000004",
        "tgn:1003399",
        "tgn:7018214",
        "tgn:7002435",
        "tgn:7029392"
    ],
    "tgn:id":1055528,
    "tgn:name":"Koltovskaya",
    "tgn:placetype":[
        "aat:300008347"
    ]
},
  "bbox": [],
  "geometry": {"coordinates":[44.2667,52.7667],"type":"Point"}
}