{
  "id": 2477628,
  "type": "Feature",
  "properties": {
    "tgn:hierarchy":[
        "tgn:2477628",
        "tgn:1000001",
        "tgn:7012149",
        "tgn:1002999",
        "tgn:7007526",
        "tgn:7029392"
    ],
    "tgn:id":2477628,
    "tgn:name":"MC Springs",
    "tgn:placetype":[
        "aat:300008697"
    ]
},
  "bbox": [],
  "geometry": {"coordinates":[-119.6833,41.75],"type":"Point"}
}