{
  "id": 1112401,
  "type": "Feature",
  "properties": {
    "tgn:hierarchy":[
        "tgn:1112401",
        "tgn:1000004",
        "tgn:6002931",
        "tgn:7018214",
        "tgn:7002435",
        "tgn:7029392"
    ],
    "tgn:id":1112401,
    "tgn:name":"Kamcatskiy Zaliz",
    "tgn:placetype":[
        "aat:300132315"
    ]
},
  "bbox": [],
  "geometry": {"coordinates":[162.35,55.5833],"type":"Point"}
}