{
  "id": 2467520,
  "type": "Feature",
  "properties": {
    "tgn:hierarchy":[
        "tgn:2467520",
        "tgn:1000001",
        "tgn:7012149",
        "tgn:2001723",
        "tgn:7007708",
        "tgn:7029392"
    ],
    "tgn:id":2467520,
    "tgn:name":"Long Hollow",
    "tgn:placetype":[
        "aat:300008761"
    ]
},
  "bbox": [],
  "geometry": {"coordinates":[-119.8667,44.75],"type":"Point"}
}