{
  "id": 2431966,
  "type": "Feature",
  "properties": {
    "tgn:hierarchy":[
        "tgn:2431966",
        "tgn:1007657",
        "tgn:1002534",
        "tgn:1000001",
        "tgn:7012149",
        "tgn:7007249",
        "tgn:7029392"
    ],
    "tgn:id":2431966,
    "tgn:name":"Kaunuohua Ridge",
    "tgn:placetype":[
        "aat:300266640"
    ]
},
  "bbox": [],
  "geometry": {"coordinates":[-159.65,22.1333],"type":"Point"}
}