{
  "id": 7337218,
  "type": "Feature",
  "properties": {
    "tgn:hierarchy":[
        "tgn:7337218",
        "tgn:7008911",
        "tgn:1000003",
        "tgn:7002763",
        "tgn:1000095",
        "tgn:7029392"
    ],
    "tgn:id":7337218,
    "tgn:name":"Coa\u00f1a",
    "tgn:placetype":[
        "aat:300008347"
    ]
},
  "bbox": [],
  "geometry": {"coordinates":[-6.75,43.516667],"type":"Point"}
}