{
  "id": 7521461,
  "type": "Feature",
  "properties": {
    "tgn:hierarchy":[
        "tgn:7521461",
        "tgn:7001242",
        "tgn:7001311",
        "tgn:7016833",
        "tgn:7029392"
    ],
    "tgn:id":7521461,
    "tgn:name:en":"Abu Hiban, Wadi",
    "tgn:placetype":[
        "aat:300379998"
    ]
},
  "bbox": [],
  "geometry": {"coordinates":[34.140583,26.001298],"type":"Point"}
}