<<<<<<< HEAD
{
  "id": 7054065,
  "type": "Feature",
  "properties": {
    "tgn:hierarchy":[
        "tgn:7054065",
        "tgn:7003170",
        "tgn:1000003",
        "tgn:7003125",
        "tgn:1000080",
        "tgn:7029392"
    ],
    "tgn:id":7054065,
    "tgn:name":"Montanaldo",
    "tgn:placetype":[
        "aat:300008347"
    ]
},
  "bbox": [],
  "geometry": {"coordinates":[12.5,43.3],"type":"Point"}
}
=======
{"geometry":{"type":"Point","coordinates":[12.500000,43.300000]},"type":"Feature","properties":{"hierarchy":["tgn:7054065","tgn:7003170","tgn:1000003","tgn:7003125","tgn:1000080","tgn:7029392"],"placetype":["aat:300008347"],"id":7054065,"name:xx":"Montanaldo"}}
>>>>>>> 03f74aca74312dbeaf24d7e61306dd6a786dc3d0
