<<<<<<< HEAD
{
  "id": 7170878,
  "type": "Feature",
  "properties": {
    "tgn:hierarchy":[
        "tgn:7170878",
        "tgn:1000003",
        "tgn:7003678",
        "tgn:7000084",
        "tgn:7029392"
    ],
    "tgn:id":7170878,
    "tgn:name":"Himmelsbreite",
    "tgn:placetype":[
        "aat:300008777"
    ]
},
  "bbox": [],
  "geometry": {"coordinates":[8.916667,51.183333],"type":"Point"}
}
=======
{"geometry":{"type":"Point","coordinates":[8.916667,51.183333]},"type":"Feature","properties":{"hierarchy":["tgn:7170878","tgn:1000003","tgn:7003678","tgn:7000084","tgn:7029392"],"placetype":["aat:300008777"],"id":7170878,"name:xx":"Himmelsbreite"}}
>>>>>>> 03f74aca74312dbeaf24d7e61306dd6a786dc3d0
