{
  "id": 2784528,
  "type": "Feature",
  "properties": {
    "tgn:hierarchy":[
        "tgn:2784528",
        "tgn:1000001",
        "tgn:7012149",
        "tgn:2001314",
        "tgn:7007524",
        "tgn:7029392"
    ],
    "tgn:id":2784528,
    "tgn:name":"Yates Creek",
    "tgn:placetype":[
        "aat:300008706"
    ]
},
  "bbox": [],
  "geometry": {"coordinates":[-104.05,46.9167],"type":"Point"}
}