{
  "id": 7526586,
  "type": "Feature",
  "properties": {
    "tgn:hierarchy":[
        "tgn:7526586",
        "tgn:7001242",
        "tgn:7016833",
        "tgn:1001091",
        "tgn:7029392"
    ],
    "tgn:id":7526586,
    "tgn:name":"Mayd\u0101n Am\u012bn Fikr\u012b",
    "tgn:placetype":[
        "aat:300004792"
    ]
},
  "bbox": [],
  "geometry": {"coordinates":[31.292564,30.083424],"type":"Point"}
}