{
  "id": 2605419,
  "type": "Feature",
  "properties": {
    "tgn:hierarchy":[
        "tgn:2605419",
        "tgn:1000001",
        "tgn:7012149",
        "tgn:2002281",
        "tgn:7013961",
        "tgn:7029392"
    ],
    "tgn:id":2605419,
    "tgn:name":"Ragtown",
    "tgn:placetype":[
        "aat:300008347"
    ]
},
  "bbox": [],
  "geometry": {"coordinates":[-80.25,39.6333],"type":"Point"}
}