{
  "id": 2295600,
  "type": "Feature",
  "properties": {
    "tgn:hierarchy":[
        "tgn:2295600",
        "tgn:1000001",
        "tgn:2001802",
        "tgn:7012149",
        "tgn:7007713",
        "tgn:7029392"
    ],
    "tgn:id":2295600,
    "tgn:name":"Drips, The",
    "tgn:placetype":[
        "aat:300008761"
    ]
},
  "bbox": [],
  "geometry": {"coordinates":[-100.0167,44.35],"type":"Point"}
}