{
  "id": 2369056,
  "type": "Feature",
  "properties": {
    "tgn:hierarchy":[
        "tgn:2369056",
        "tgn:1000001",
        "tgn:2001633",
        "tgn:7012149",
        "tgn:7007707",
        "tgn:7029392"
    ],
    "tgn:id":2369056,
    "tgn:name":"Gum Creek",
    "tgn:placetype":[
        "aat:300008706"
    ]
},
  "bbox": [],
  "geometry": {"coordinates":[-94.9667,35.7333],"type":"Point"}
}