{
  "id": 1054768,
  "type": "Feature",
  "properties": {
    "tgn:hierarchy":[
        "tgn:1054768",
        "tgn:1000004",
        "tgn:1003418",
        "tgn:7018214",
        "tgn:7002435",
        "tgn:7029392"
    ],
    "tgn:id":1054768,
    "tgn:name":"Yudinki",
    "tgn:placetype":[
        "aat:300008347"
    ]
},
  "bbox": [],
  "geometry": {"coordinates":[37.2833,54.6167],"type":"Point"}
}