{
  "id": 2210820,
  "type": "Feature",
  "properties": {
    "tgn:hierarchy":[
        "tgn:2210820",
        "tgn:1000001",
        "tgn:7012149",
        "tgn:1002378",
        "tgn:7007710",
        "tgn:7029392"
    ],
    "tgn:id":2210820,
    "tgn:name":"Butcherknife Hill",
    "tgn:placetype":[
        "aat:300008798"
    ]
},
  "bbox": [],
  "geometry": {"coordinates":[-79.45,41.6167],"type":"Point"}
}