<<<<<<< HEAD
{
  "id": 7479207,
  "type": "Feature",
  "properties": {
    "tgn:hierarchy":[
        "tgn:7479207",
        "tgn:1000004",
        "tgn:7490934",
        "tgn:1000141",
        "tgn:7029392"
    ],
    "tgn:id":7479207,
    "tgn:name":"Pimayuan",
    "tgn:placetype":[
        "aat:300008347"
    ]
},
  "bbox": [],
  "geometry": {"coordinates":[120.252778,23.030278],"type":"Point"}
}
=======
{"geometry":{"type":"Point","coordinates":[120.252778,23.030278]},"type":"Feature","properties":{"hierarchy":["tgn:7479207","tgn:1000004","tgn:7490934","tgn:1000141","tgn:7029392"],"placetype":["aat:300008347"],"id":7479207,"name:xx":"Pimayuan"}}
>>>>>>> 03f74aca74312dbeaf24d7e61306dd6a786dc3d0
