{
  "id": 2261007,
  "type": "Feature",
  "properties": {
    "tgn:hierarchy":[
        "tgn:2261007",
        "tgn:1000001",
        "tgn:2001010",
        "tgn:7012149",
        "tgn:7007521",
        "tgn:7029392"
    ],
    "tgn:id":2261007,
    "tgn:name":"County Ditch Number Thirtysix A",
    "tgn:placetype":[
        "aat:300006075"
    ]
},
  "bbox": [],
  "geometry": {"coordinates":[-95.6333,44.9167],"type":"Point"}
}