{
  "id": 7293122,
  "type": "Feature",
  "properties": {
    "tgn:hierarchy":[
        "tgn:7293122",
        "tgn:7016598",
        "tgn:1000049",
        "tgn:1000002",
        "tgn:7029392"
    ],
    "tgn:id":7293122,
    "tgn:name":"El Cobre, Caleta",
    "tgn:placetype":[
        "aat:300132317"
    ]
},
  "bbox": [],
  "geometry": {"coordinates":[-70.516667,-24.233333],"type":"Point"}
}