{
  "id": 7162243,
  "type": "Feature",
  "properties": {
    "tgn:hierarchy":[
        "tgn:7162243",
        "tgn:1000003",
        "tgn:7003677",
        "tgn:7000084",
        "tgn:7029392"
    ],
    "tgn:id":7162243,
    "tgn:name":"Huxoll",
    "tgn:placetype":[
        "aat:300000206"
    ]
},
  "bbox": [],
  "geometry": {"coordinates":[8.983333,51.966667],"type":"Point"}
}