{
  "id": 2653405,
  "type": "Feature",
  "properties": {
    "tgn:hierarchy":[
        "tgn:2653405",
        "tgn:1000001",
        "tgn:7012149",
        "tgn:2002371",
        "tgn:7007923",
        "tgn:7029392"
    ],
    "tgn:id":2653405,
    "tgn:name":"Sevenmile Hill",
    "tgn:placetype":[
        "aat:300008798"
    ]
},
  "bbox": [],
  "geometry": {"coordinates":[-108.3167,42.9167],"type":"Point"}
}