{
  "id": 7062117,
  "type": "Feature",
  "properties": {
    "tgn:hierarchy":[
        "tgn:7062117",
        "tgn:7003669",
        "tgn:1000003",
        "tgn:7000084",
        "tgn:7029392"
    ],
    "tgn:id":7062117,
    "tgn:name":"Ammerthal",
    "tgn:placetype":[
        "aat:300008347"
    ]
},
  "bbox": [],
  "geometry": {"coordinates":[10.983333,47.733333],"type":"Point"}
}