{
  "id": 7505268,
  "type": "Feature",
  "properties": {
    "tgn:hierarchy":[
        "tgn:7505268",
        "tgn:1009227",
        "tgn:7001866",
        "tgn:1000226",
        "tgn:1000006",
        "tgn:7029392"
    ],
    "tgn:id":7505268,
    "tgn:name:en":"Woodend",
    "tgn:placetype":[
        "aat:300008347"
    ]
},
  "bbox": [],
  "geometry": {"coordinates":[172.666667,-43.316667],"type":"Point"}
}