{
  "id": 2402157,
  "type": "Feature",
  "properties": {
    "tgn:hierarchy":[
        "tgn:2402157",
        "tgn:1000001",
        "tgn:7012149",
        "tgn:7007157",
        "tgn:2000185",
        "tgn:7029392"
    ],
    "tgn:id":2402157,
    "tgn:name":"Horsetail Gulch",
    "tgn:placetype":[
        "aat:300008761"
    ]
},
  "bbox": [],
  "geometry": {"coordinates":[-123.6333,39.5333],"type":"Point"}
}