{
  "id": 1042813,
  "type": "Feature",
  "properties": {
    "tgn:hierarchy":[
        "tgn:1042813",
        "tgn:7003498",
        "tgn:7001201",
        "tgn:1000003",
        "tgn:1000078",
        "tgn:7029392"
    ],
    "tgn:id":1042813,
    "tgn:name":"Glenbeigh",
    "tgn:placetype":[
        "aat:300008347"
    ]
},
  "bbox": [],
  "geometry": {"coordinates":[-9.9333,52.05],"type":"Point"}
}