{
  "id": 7383907,
  "type": "Feature",
  "properties": {
    "tgn:hierarchy":[
        "tgn:7383907",
        "tgn:1000001",
        "tgn:7005599",
        "tgn:7005560",
        "tgn:7029392"
    ],
    "tgn:id":7383907,
    "tgn:name":"Oyozontle",
    "tgn:placetype":[
        "aat:300008347"
    ]
},
  "bbox": [],
  "geometry": {"coordinates":[-95.85,18.316667],"type":"Point"}
}