{
  "id": 5002662,
  "type": "Feature",
  "properties": {
    "tgn:hierarchy":[
        "tgn:5002662",
        "tgn:1003483",
        "tgn:1000003",
        "tgn:7003240",
        "tgn:1000080",
        "tgn:7029392"
    ],
    "tgn:id":5002662,
    "tgn:name":"Cartoceto",
    "tgn:placetype":[
        "aat:300008347"
    ]
},
  "bbox": [],
  "geometry": {"coordinates":[12.816667,43.616667],"type":"Point"}
}