<<<<<<< HEAD
{
  "id": 2338600,
  "type": "Feature",
  "properties": {
    "tgn:hierarchy":[
        "tgn:2338600",
        "tgn:7006450",
        "tgn:1000001",
        "tgn:2124053",
        "tgn:7012149",
        "tgn:7029392"
    ],
    "tgn:id":2338600,
    "tgn:name":"Francie Creek",
    "tgn:placetype":[
        "aat:300008706"
    ]
},
  "bbox": [],
  "geometry": {"coordinates":[-149.4833,61.7833],"type":"Point"}
}
=======
{"geometry":{"type":"Point","coordinates":[-149.483300,61.783300]},"type":"Feature","properties":{"hierarchy":["tgn:2338600","tgn:7006450","tgn:1000001","tgn:2124053","tgn:7012149","tgn:7029392"],"placetype":["aat:300008706"],"id":2338600,"name:xx":"Francie Creek"}}
>>>>>>> 03f74aca74312dbeaf24d7e61306dd6a786dc3d0
