<<<<<<< HEAD
{
  "id": 2403363,
  "type": "Feature",
  "properties": {
    "tgn:hierarchy":[
        "tgn:2403363",
        "tgn:1000001",
        "tgn:2001703",
        "tgn:7012149",
        "tgn:7007708",
        "tgn:7029392"
    ],
    "tgn:id":2403363,
    "tgn:name":"Houston Butte",
    "tgn:placetype":[
        "aat:300008798"
    ]
},
  "bbox": [],
  "geometry": {"coordinates":[-120.5167,43.9667],"type":"Point"}
}
=======
{"geometry":{"type":"Point","coordinates":[-120.516700,43.966700]},"type":"Feature","properties":{"hierarchy":["tgn:2403363","tgn:1000001","tgn:2001703","tgn:7012149","tgn:7007708","tgn:7029392"],"placetype":["aat:300008798"],"id":2403363,"name:xx":"Houston Butte"}}
>>>>>>> 03f74aca74312dbeaf24d7e61306dd6a786dc3d0
