{
  "id": 2403363,
  "type": "Feature",
  "properties": {
    "tgn:hierarchy":[
        "tgn:2403363",
        "tgn:1000001",
        "tgn:2001703",
        "tgn:7012149",
        "tgn:7007708",
        "tgn:7029392"
    ],
    "tgn:id":2403363,
    "tgn:name":"Houston Butte",
    "tgn:placetype":[
        "aat:300008798"
    ]
},
  "bbox": [],
  "geometry": {"coordinates":[-120.5167,43.9667],"type":"Point"}
}