<<<<<<< HEAD
{
  "id": 2251207,
  "type": "Feature",
  "properties": {
    "tgn:hierarchy":[
        "tgn:2251207",
        "tgn:1000001",
        "tgn:7012149",
        "tgn:2001449",
        "tgn:7007566",
        "tgn:7029392"
    ],
    "tgn:id":2251207,
    "tgn:name":"Comanche Number Two Tank",
    "tgn:placetype":[
        "aat:300006191"
    ]
},
  "bbox": [],
  "geometry": {"coordinates":[-105.95,36.5167],"type":"Point"}
}
=======
{"geometry":{"type":"Point","coordinates":[-105.950000,36.516700]},"type":"Feature","properties":{"hierarchy":["tgn:2251207","tgn:1000001","tgn:7012149","tgn:2001449","tgn:7007566","tgn:7029392"],"placetype":["aat:300006191"],"id":2251207,"name:xx":"Comanche Number Two Tank"}}
>>>>>>> 03f74aca74312dbeaf24d7e61306dd6a786dc3d0
