{
  "id": 7499593,
  "type": "Feature",
  "properties": {
    "tgn:hierarchy":[
        "tgn:7499593",
        "tgn:7488858",
        "tgn:1000004",
        "tgn:1000141",
        "tgn:7029392"
    ],
    "tgn:id":7499593,
    "tgn:name":"Hongyai Shan Beifeng",
    "tgn:placetype":[
        "aat:300008798"
    ]
},
  "bbox": [],
  "geometry": {"coordinates":[121.141695,23.62495],"type":"Point"}
}