{
  "id": 7008511,
  "type": "Feature",
  "properties": {
    "tgn:hierarchy":[
        "tgn:7008511",
        "tgn:7002443",
        "tgn:1000003",
        "tgn:5000560",
        "tgn:7008591",
        "tgn:7029392"
    ],
    "tgn:id":7008511,
    "tgn:name:en":"Monmouth",
    "tgn:placetype":[
        "aat:300008347",
        "aat:300008375"
    ]
},
  "bbox": [],
  "geometry": {"coordinates":[-2.716667,51.816667],"type":"Point"}
}