{
  "id": 2643066,
  "type": "Feature",
  "properties": {
    "tgn:hierarchy":[
        "tgn:2643066",
        "tgn:7014201",
        "tgn:1000001",
        "tgn:7012149",
        "tgn:7007239",
        "tgn:7029392"
    ],
    "tgn:id":2643066,
    "tgn:name":"Sandy Brae",
    "tgn:placetype":[
        "aat:300008798"
    ]
},
  "bbox": [],
  "geometry": {"coordinates":[-75.75,39.6167],"type":"Point"}
}