{
  "id": 7574968,
  "type": "Feature",
  "properties": {
    "tgn:hierarchy":[
        "tgn:7574968",
        "tgn:1000004",
        "tgn:7000198",
        "tgn:1001895",
        "tgn:7029392"
    ],
    "tgn:id":7574968,
    "tgn:name:en":"Kurul",
    "tgn:placetype":[
        "aat:300008347"
    ]
},
  "bbox": [],
  "geometry": {"coordinates":[75.656604,17.674728],"type":"Point"}
}