{
  "id": 1005769,
  "type": "Feature",
  "properties": {
    "tgn:hierarchy":[
        "tgn:1005769",
        "tgn:7016696",
        "tgn:1000004",
        "tgn:7000894",
        "tgn:7004836",
        "tgn:1000120",
        "tgn:7029392"
    ],
    "tgn:id":1005769,
    "tgn:name":"Tsunashima",
    "tgn:placetype":[
        "aat:300000745"
    ]
},
  "bbox": [],
  "geometry": {"coordinates":[139.6333,35.5333],"type":"Point"}
}