{
  "id": 7497657,
  "type": "Feature",
  "properties": {
    "tgn:hierarchy":[
        "tgn:7497657",
        "tgn:7001004",
        "tgn:1000004",
        "tgn:1000141",
        "tgn:7029392"
    ],
    "tgn:id":7497657,
    "tgn:name":"Mengli Qiao",
    "tgn:placetype":[
        "aat:300007836"
    ]
},
  "bbox": [],
  "geometry": {"coordinates":[120.363521,22.66477],"type":"Point"}
}