{
  "id": 2704679,
  "type": "Feature",
  "properties": {
    "tgn:hierarchy":[
        "tgn:2704679",
        "tgn:1000001",
        "tgn:7012149",
        "tgn:1002785",
        "tgn:7007920",
        "tgn:7029392"
    ],
    "tgn:id":2704679,
    "tgn:name":"Sunset Beach",
    "tgn:placetype":[
        "aat:300008347"
    ]
},
  "bbox": [],
  "geometry": {"coordinates":[-122.5667,47.2167],"type":"Point"}
}