{
  "id": 2720189,
  "type": "Feature",
  "properties": {
    "tgn:hierarchy":[
        "tgn:2720189",
        "tgn:1000001",
        "tgn:7012149",
        "tgn:2001706",
        "tgn:7007708",
        "tgn:7029392"
    ],
    "tgn:id":2720189,
    "tgn:name":"Threemile Lake",
    "tgn:placetype":[
        "aat:300008680"
    ]
},
  "bbox": [],
  "geometry": {"coordinates":[-124.1667,43.75],"type":"Point"}
}