<<<<<<< HEAD
{
  "id": 2337460,
  "type": "Feature",
  "properties": {
    "tgn:hierarchy":[
        "tgn:2337460",
        "tgn:1000001",
        "tgn:1002712",
        "tgn:7012149",
        "tgn:7007159",
        "tgn:7029392"
    ],
    "tgn:id":2337460,
    "tgn:name":"Fowler Island",
    "tgn:placetype":[
        "aat:300008791"
    ]
},
  "bbox": [],
  "geometry": {"coordinates":[-73.1,41.2333],"type":"Point"}
}
=======
{"geometry":{"type":"Point","coordinates":[-73.100000,41.233300]},"type":"Feature","properties":{"hierarchy":["tgn:2337460","tgn:1000001","tgn:1002712","tgn:7012149","tgn:7007159","tgn:7029392"],"placetype":["aat:300008791"],"id":2337460,"name:xx":"Fowler Island"}}
>>>>>>> 03f74aca74312dbeaf24d7e61306dd6a786dc3d0
