<<<<<<< HEAD
{
  "id": 2335892,
  "type": "Feature",
  "properties": {
    "tgn:hierarchy":[
        "tgn:2335892",
        "tgn:2000195",
        "tgn:1000001",
        "tgn:7012149",
        "tgn:7007158",
        "tgn:7029392"
    ],
    "tgn:id":2335892,
    "tgn:name":"Fosset Gulch",
    "tgn:placetype":[
        "aat:300008761"
    ]
},
  "bbox": [],
  "geometry": {"coordinates":[-107.4,37.2],"type":"Point"}
}
=======
{"geometry":{"type":"Point","coordinates":[-107.400000,37.200000]},"type":"Feature","properties":{"hierarchy":["tgn:2335892","tgn:2000195","tgn:1000001","tgn:7012149","tgn:7007158","tgn:7029392"],"placetype":["aat:300008761"],"id":2335892,"name:xx":"Fosset Gulch"}}
>>>>>>> 03f74aca74312dbeaf24d7e61306dd6a786dc3d0
