{
  "id": 2572396,
  "type": "Feature",
  "properties": {
    "tgn:hierarchy":[
        "tgn:2572396",
        "tgn:1000001",
        "tgn:7012149",
        "tgn:7019676",
        "tgn:7007566",
        "tgn:7029392"
    ],
    "tgn:id":2572396,
    "tgn:name":"Peach Orchard Draw",
    "tgn:placetype":[
        "aat:300008761"
    ]
},
  "bbox": [],
  "geometry": {"coordinates":[-108.75,35.0667],"type":"Point"}
}