{
  "id": 2292754,
  "type": "Feature",
  "properties": {
    "tgn:hierarchy":[
        "tgn:2292754",
        "tgn:1000001",
        "tgn:7012149",
        "tgn:1003019",
        "tgn:7007826",
        "tgn:7029392"
    ],
    "tgn:id":2292754,
    "tgn:name":"Dornak Lake",
    "tgn:placetype":[
        "aat:300008680"
    ]
},
  "bbox": [],
  "geometry": {"coordinates":[-96.25,29.1667],"type":"Point"}
}