<<<<<<< HEAD
{
  "id": 2768736,
  "type": "Feature",
  "properties": {
    "tgn:hierarchy":[
        "tgn:2768736",
        "tgn:1000001",
        "tgn:1002614",
        "tgn:7012149",
        "tgn:7007526",
        "tgn:7029392"
    ],
    "tgn:id":2768736,
    "tgn:name":"Whitman Coal Mines",
    "tgn:placetype":[
        "aat:300000390",
        "aat:300386993"
    ]
},
  "bbox": [],
  "geometry": {"coordinates":[-119.45,39.2333],"type":"Point"}
}
=======
{"geometry":{"type":"Point","coordinates":[-119.450000,39.233300]},"type":"Feature","properties":{"hierarchy":["tgn:2768736","tgn:1000001","tgn:1002614","tgn:7012149","tgn:7007526","tgn:7029392"],"placetype":["aat:300000390","aat:300386993"],"id":2768736,"name:xx":"Whitman Coal Mines"}}
>>>>>>> 03f74aca74312dbeaf24d7e61306dd6a786dc3d0
