{
  "id": 2716600,
  "type": "Feature",
  "properties": {
    "tgn:hierarchy":[
        "tgn:2716600",
        "tgn:1000001",
        "tgn:7012149",
        "tgn:2002118",
        "tgn:7007827",
        "tgn:7029392"
    ],
    "tgn:id":2716600,
    "tgn:name":"The Oakwoods",
    "tgn:placetype":[
        "aat:300008347"
    ]
},
  "bbox": [],
  "geometry": {"coordinates":[-111.7833,40.5667],"type":"Point"}
}