{
  "id": 7231848,
  "type": "Feature",
  "properties": {
    "tgn:hierarchy":[
        "tgn:7231848",
        "tgn:7011270",
        "tgn:7002674",
        "tgn:1000003",
        "tgn:1000074",
        "tgn:7029392"
    ],
    "tgn:id":7231848,
    "tgn:name":"Mam\u00e1dhos",
    "tgn:placetype":[
        "aat:300008347"
    ]
},
  "bbox": [],
  "geometry": {"coordinates":[25.016667,37.65],"type":"Point"}
}