{
  "id": 1029456,
  "type": "Feature",
  "properties": {
    "tgn:hierarchy":[
        "tgn:1029456",
        "tgn:7002445",
        "tgn:1000003",
        "tgn:7008178",
        "tgn:7008591",
        "tgn:7029392"
    ],
    "tgn:id":1029456,
    "tgn:name":"Hartshill",
    "tgn:placetype":[
        "aat:300008347"
    ]
},
  "bbox": [],
  "geometry": {"coordinates":[-1.5333,52.5333],"type":"Point"}
}