{
  "id": 2583598,
  "type": "Feature",
  "properties": {
    "tgn:hierarchy":[
        "tgn:2583598",
        "tgn:1000001",
        "tgn:7012149",
        "tgn:2002334",
        "tgn:7007922",
        "tgn:7029392"
    ],
    "tgn:id":2583598,
    "tgn:name":"Pine River",
    "tgn:placetype":[
        "aat:300008347"
    ]
},
  "bbox": [],
  "geometry": {"coordinates":[-89.6167,45.1333],"type":"Point"}
}