{
  "id": 7566490,
  "type": "Feature",
  "properties": {
    "tgn:hierarchy":[
        "tgn:7566490",
        "tgn:1000004",
        "tgn:7000198",
        "tgn:1001894",
        "tgn:7029392"
    ],
    "tgn:id":7566490,
    "tgn:name:en":"Bhains\u0101khera",
    "tgn:placetype":[
        "aat:300008347"
    ]
},
  "bbox": [],
  "geometry": {"coordinates":[79.039949,24.512683],"type":"Point"}
}