<<<<<<< HEAD
{
  "id": 2154775,
  "type": "Feature",
  "properties": {
    "tgn:hierarchy":[
        "tgn:2154775",
        "tgn:1000001",
        "tgn:7012149",
        "tgn:2000287",
        "tgn:7007240",
        "tgn:7029392"
    ],
    "tgn:id":2154775,
    "tgn:name":"Bear Harbor Lake",
    "tgn:placetype":[
        "aat:300008680"
    ]
},
  "bbox": [],
  "geometry": {"coordinates":[-83.6,29.9667],"type":"Point"}
}
=======
{"geometry":{"type":"Point","coordinates":[-83.600000,29.966700]},"type":"Feature","properties":{"hierarchy":["tgn:2154775","tgn:1000001","tgn:7012149","tgn:2000287","tgn:7007240","tgn:7029392"],"placetype":["aat:300008680"],"id":2154775,"name:xx":"Bear Harbor Lake"}}
>>>>>>> 03f74aca74312dbeaf24d7e61306dd6a786dc3d0
