{
  "id": 2262584,
  "type": "Feature",
  "properties": {
    "tgn:hierarchy":[
        "tgn:2262584",
        "tgn:1000001",
        "tgn:7012149",
        "tgn:2001453",
        "tgn:7007566",
        "tgn:7029392"
    ],
    "tgn:id":2262584,
    "tgn:name":"Cow Pass Creek",
    "tgn:placetype":[
        "aat:300008706"
    ]
},
  "bbox": [],
  "geometry": {"coordinates":[-103.9333,35.4833],"type":"Point"}
}