<<<<<<< HEAD
{
  "id": 7242770,
  "type": "Feature",
  "properties": {
    "tgn:hierarchy":[
        "tgn:7242770",
        "tgn:7003465",
        "tgn:1000003",
        "tgn:1000063",
        "tgn:4012014",
        "tgn:7029392"
    ],
    "tgn:id":7242770,
    "tgn:name":"Les Bochets",
    "tgn:placetype":[
        "aat:300008347"
    ]
},
  "bbox": [],
  "geometry": {"coordinates":[5.433333,49.6],"type":"Point"}
}
=======
{"geometry":{"type":"Point","coordinates":[5.433333,49.600000]},"type":"Feature","properties":{"hierarchy":["tgn:7242770","tgn:7003465","tgn:1000003","tgn:1000063","tgn:4012014","tgn:7029392"],"placetype":["aat:300008347"],"id":7242770,"name:xx":"Les Bochets"}}
>>>>>>> 03f74aca74312dbeaf24d7e61306dd6a786dc3d0
