{
  "id": 7445597,
  "type": "Feature",
  "properties": {
    "tgn:hierarchy":[
        "tgn:7445597",
        "tgn:7002445",
        "tgn:1000003",
        "tgn:7008166",
        "tgn:7008591",
        "tgn:7029392"
    ],
    "tgn:id":7445597,
    "tgn:name:en":"Sutton on the Forest",
    "tgn:placetype":[
        "aat:300008347"
    ]
},
  "bbox": [],
  "geometry": {"coordinates":[-1.116667,54.083333],"type":"Point"}
}