{
  "id": 2356653,
  "type": "Feature",
  "properties": {
    "tgn:hierarchy":[
        "tgn:2356653",
        "tgn:1000001",
        "tgn:2001266",
        "tgn:7012149",
        "tgn:7007524",
        "tgn:7029392"
    ],
    "tgn:id":2356653,
    "tgn:name":"Gore Hill",
    "tgn:placetype":[
        "aat:300008798"
    ]
},
  "bbox": [],
  "geometry": {"coordinates":[-111.3333,47.4833],"type":"Point"}
}