{
  "id": 7309734,
  "type": "Feature",
  "properties": {
    "tgn:hierarchy":[
        "tgn:7309734",
        "tgn:1001623",
        "tgn:1000049",
        "tgn:1000002",
        "tgn:7029392"
    ],
    "tgn:id":7309734,
    "tgn:name":"Norte, Roca",
    "tgn:placetype":[
        "aat:300011692"
    ]
},
  "bbox": [],
  "geometry": {"coordinates":[-73.516667,-45.216667],"type":"Point"}
}