{
  "id": 1087906,
  "type": "Feature",
  "properties": {
    "tgn:hierarchy":[
        "tgn:1087906",
        "tgn:7001242",
        "tgn:1000149",
        "tgn:1000867",
        "tgn:7029392"
    ],
    "tgn:id":1087906,
    "tgn:name":"Mucoma",
    "tgn:placetype":[
        "aat:300008347"
    ]
},
  "bbox": [],
  "geometry": {"coordinates":[13.5833,-15.25],"type":"Point"}
}