<<<<<<< HEAD
{
  "id": 7178358,
  "type": "Feature",
  "properties": {
    "tgn:hierarchy":[
        "tgn:7178358",
        "tgn:7003669",
        "tgn:1000003",
        "tgn:7000084",
        "tgn:7029392"
    ],
    "tgn:id":7178358,
    "tgn:name":"Gumppenberg",
    "tgn:placetype":[
        "aat:300008347"
    ]
},
  "bbox": [],
  "geometry": {"coordinates":[11.083333,48.6],"type":"Point"}
}
=======
{"geometry":{"type":"Point","coordinates":[11.083333,48.600000]},"type":"Feature","properties":{"hierarchy":["tgn:7178358","tgn:7003669","tgn:1000003","tgn:7000084","tgn:7029392"],"placetype":["aat:300008347"],"id":7178358,"name:xx":"Gumppenberg"}}
>>>>>>> 03f74aca74312dbeaf24d7e61306dd6a786dc3d0
