{
  "id": 2048815,
  "type": "Feature",
  "properties": {
    "tgn:hierarchy":[
        "tgn:2048815",
        "tgn:1000001",
        "tgn:7016106",
        "tgn:7012149",
        "tgn:7007516",
        "tgn:7029392"
    ],
    "tgn:id":2048815,
    "tgn:name":"Spielman",
    "tgn:placetype":[
        "aat:300008347"
    ]
},
  "bbox": [],
  "geometry": {"coordinates":[-77.75,39.5333],"type":"Point"}
}