{
  "id": 2511052,
  "type": "Feature",
  "properties": {
    "tgn:hierarchy":[
        "tgn:2511052",
        "tgn:7006450",
        "tgn:1000001",
        "tgn:7012149",
        "tgn:2124002",
        "tgn:7029392"
    ],
    "tgn:id":2511052,
    "tgn:name":"Midway Island",
    "tgn:placetype":[
        "aat:300008791"
    ]
},
  "bbox": [],
  "geometry": {"coordinates":[-134.8667,56.3167],"type":"Point"}
}