{
  "id": 7124431,
  "type": "Feature",
  "properties": {
    "tgn:hierarchy":[
        "tgn:7124431",
        "tgn:1000003",
        "tgn:7003677",
        "tgn:7000084",
        "tgn:7029392"
    ],
    "tgn:id":7124431,
    "tgn:name":"Neuhaaren",
    "tgn:placetype":[
        "aat:300008347"
    ]
},
  "bbox": [],
  "geometry": {"coordinates":[6.016667,51.083333],"type":"Point"}
}