{
  "id": 2102004,
  "type": "Feature",
  "properties": {
    "tgn:hierarchy":[
        "tgn:2102004",
        "tgn:1000001",
        "tgn:7012149",
        "tgn:2001892",
        "tgn:7007825",
        "tgn:7029392"
    ],
    "tgn:id":2102004,
    "tgn:name":"Walnut Shade",
    "tgn:placetype":[
        "aat:300008347",
        "aat:300387210"
    ]
},
  "bbox": [],
  "geometry": {"coordinates":[-85.8167,36.5667],"type":"Point"}
}