{
  "id": 2636965,
  "type": "Feature",
  "properties": {
    "tgn:hierarchy":[
        "tgn:2636965",
        "tgn:1000001",
        "tgn:7012149",
        "tgn:2001539",
        "tgn:7007709",
        "tgn:7029392"
    ],
    "tgn:id":2636965,
    "tgn:name":"Saint Andrews College Lake",
    "tgn:placetype":[
        "aat:300006191"
    ]
},
  "bbox": [],
  "geometry": {"coordinates":[-79.4667,34.7333],"type":"Point"}
}