{
  "id": 2563730,
  "type": "Feature",
  "properties": {
    "tgn:hierarchy":[
        "tgn:2563730",
        "tgn:1000001",
        "tgn:2001429",
        "tgn:7012149",
        "tgn:7007566",
        "tgn:7029392"
    ],
    "tgn:id":2563730,
    "tgn:name":"Ox Spring",
    "tgn:placetype":[
        "aat:300008697"
    ]
},
  "bbox": [],
  "geometry": {"coordinates":[-107.8667,34.35],"type":"Point"}
}