{
  "id": 2194713,
  "type": "Feature",
  "properties": {
    "tgn:hierarchy":[
        "tgn:2194713",
        "tgn:1000001",
        "tgn:7012149",
        "tgn:1002406",
        "tgn:7007520",
        "tgn:7029392"
    ],
    "tgn:id":2194713,
    "tgn:name":"Brier Drain",
    "tgn:placetype":[
        "aat:300006075"
    ]
},
  "bbox": [],
  "geometry": {"coordinates":[-83.5667,43.05],"type":"Point"}
}