{
  "id": 2736424,
  "type": "Feature",
  "properties": {
    "tgn:hierarchy":[
        "tgn:2736424",
        "tgn:1000001",
        "tgn:7012149",
        "tgn:2001206",
        "tgn:7007523",
        "tgn:7029392"
    ],
    "tgn:id":2736424,
    "tgn:name":"Twin Ponds",
    "tgn:placetype":[
        "aat:300008680"
    ]
},
  "bbox": [],
  "geometry": {"coordinates":[-91.85,36.6667],"type":"Point"}
}