{
  "id": 2590370,
  "type": "Feature",
  "properties": {
    "tgn:hierarchy":[
        "tgn:2590370",
        "tgn:1000001",
        "tgn:2001411",
        "tgn:7012149",
        "tgn:7007526",
        "tgn:7029392"
    ],
    "tgn:id":2590370,
    "tgn:name":"Polaris Gulch",
    "tgn:placetype":[
        "aat:300008761"
    ]
},
  "bbox": [],
  "geometry": {"coordinates":[-116.1167,41.6833],"type":"Point"}
}