{
  "id": 7050195,
  "type": "Feature",
  "properties": {
    "tgn:hierarchy":[
        "tgn:7050195",
        "tgn:7003162",
        "tgn:1000003",
        "tgn:7009760",
        "tgn:1000080",
        "tgn:7029392"
    ],
    "tgn:id":7050195,
    "tgn:name":"Pieve Vecchia",
    "tgn:placetype":[
        "aat:300008347"
    ]
},
  "bbox": [],
  "geometry": {"coordinates":[11.766667,43.266667],"type":"Point"}
}