{
  "id": 2686197,
  "type": "Feature",
  "properties": {
    "tgn:hierarchy":[
        "tgn:2686197",
        "tgn:1000001",
        "tgn:2000920",
        "tgn:7012149",
        "tgn:7007515",
        "tgn:7029392"
    ],
    "tgn:id":2686197,
    "tgn:name":"Spring Cove",
    "tgn:placetype":[
        "aat:300132316"
    ]
},
  "bbox": [],
  "geometry": {"coordinates":[-70.1833,43.6333],"type":"Point"}
}