{
  "id": 7468731,
  "type": "Feature",
  "properties": {
    "tgn:hierarchy":[
        "tgn:7468731",
        "tgn:1000004",
        "tgn:7467799",
        "tgn:1000141",
        "tgn:7029392"
    ],
    "tgn:id":7468731,
    "tgn:name":"Fengtian Li",
    "tgn:placetype":[
        "aat:300387173"
    ]
},
  "bbox": [],
  "geometry": {"coordinates":[120.372477,23.883034],"type":"Point"}
}