{
  "id": 2341066,
  "type": "Feature",
  "properties": {
    "tgn:hierarchy":[
        "tgn:2341066",
        "tgn:1000001",
        "tgn:7012149",
        "tgn:1002519",
        "tgn:7007706",
        "tgn:7029392"
    ],
    "tgn:id":2341066,
    "tgn:name":"Friendship Park Lake",
    "tgn:placetype":[
        "aat:300006191"
    ]
},
  "bbox": [],
  "geometry": {"coordinates":[-80.75,40.2833],"type":"Point"}
}