{
  "id": 1126170,
  "type": "Feature",
  "properties": {
    "tgn:hierarchy":[
        "tgn:1126170",
        "tgn:1000001",
        "tgn:7012149",
        "tgn:7007524",
        "tgn:7029392"
    ],
    "tgn:id":1126170,
    "tgn:name":"Little Bitterroot",
    "tgn:placetype":[
        "aat:300008707"
    ]
},
  "bbox": [],
  "geometry": {"coordinates":[-114.6833,48.0833],"type":"Point"}
}