{
  "id": 2294956,
  "type": "Feature",
  "properties": {
    "tgn:hierarchy":[
        "tgn:2294956",
        "tgn:1000001",
        "tgn:7012149",
        "tgn:7007255",
        "tgn:7029392"
    ],
    "tgn:id":2294956,
    "tgn:name":"Drakes Creek",
    "tgn:placetype":[
        "aat:300008706"
    ]
},
  "bbox": [],
  "geometry": {"coordinates":[-84.5167,37.5667],"type":"Point"}
}