{
  "id": 2131490,
  "type": "Feature",
  "properties": {
    "tgn:hierarchy":[
        "tgn:2131490",
        "tgn:1000001",
        "tgn:7012149",
        "tgn:2002375",
        "tgn:7007923",
        "tgn:7029392"
    ],
    "tgn:id":2131490,
    "tgn:name":"Altvan",
    "tgn:placetype":[
        "aat:300008347"
    ]
},
  "bbox": [],
  "geometry": {"coordinates":[-104.6833,41.1167],"type":"Point"}
}