{
  "id": 7555044,
  "type": "Feature",
  "properties": {
    "tgn:hierarchy":[
        "tgn:7555044",
        "tgn:1000004",
        "tgn:7000198",
        "tgn:1001996",
        "tgn:7029392"
    ],
    "tgn:id":7555044,
    "tgn:name:en":"Minki\u0101n\u012b",
    "tgn:placetype":[
        "aat:300008347"
    ]
},
  "bbox": [],
  "geometry": {"coordinates":[76.259589,32.335718],"type":"Point"}
}