{
  "id": 7076483,
  "type": "Feature",
  "properties": {
    "tgn:hierarchy":[
        "tgn:7076483",
        "tgn:1000003",
        "tgn:7003678",
        "tgn:7000084",
        "tgn:7029392"
    ],
    "tgn:id":7076483,
    "tgn:name":"L\u00fctzelbach",
    "tgn:placetype":[
        "aat:300008347"
    ]
},
  "bbox": [],
  "geometry": {"coordinates":[9.0775,49.786944],"type":"Point"}
}