{
  "id": 7182416,
  "type": "Feature",
  "properties": {
    "tgn:hierarchy":[
        "tgn:7182416",
        "tgn:7003669",
        "tgn:1000003",
        "tgn:7000084",
        "tgn:7029392"
    ],
    "tgn:id":7182416,
    "tgn:name":"Landkreis F\u00fcrstenfeldbruck",
    "tgn:placetype":[
        "aat:300387198"
    ]
},
  "bbox": [],
  "geometry": {"coordinates":[11.214722,48.189722],"type":"Point"}
}