{
  "id": 2076997,
  "type": "Feature",
  "properties": {
    "tgn:hierarchy":[
        "tgn:2076997",
        "tgn:1000001",
        "tgn:7012149",
        "tgn:1002474",
        "tgn:7007709",
        "tgn:7029392"
    ],
    "tgn:id":2076997,
    "tgn:name":"Union",
    "tgn:placetype":[
        "aat:300008347"
    ]
},
  "bbox": [],
  "geometry": {"coordinates":[-77.0167,36.3333],"type":"Point"}
}