{
  "id": 2245419,
  "type": "Feature",
  "properties": {
    "tgn:hierarchy":[
        "tgn:2245419",
        "tgn:1000001",
        "tgn:7012149",
        "tgn:2001715",
        "tgn:7007708",
        "tgn:7029392"
    ],
    "tgn:id":2245419,
    "tgn:name":"Clyde Fenimore Reservoir",
    "tgn:placetype":[
        "aat:300006191"
    ]
},
  "bbox": [],
  "geometry": {"coordinates":[-120.5167,42.1333],"type":"Point"}
}