{
  "id": 2001111,
  "type": "Feature",
  "properties": {
    "tgn:hierarchy":[
        "tgn:2001111",
        "tgn:1000001",
        "tgn:7012149",
        "tgn:7007522",
        "tgn:7029392"
    ],
    "tgn:id":2001111,
    "tgn:name":"Holmes",
    "tgn:placetype":[
        "aat:300387145",
        "aat:300000771"
    ]
},
  "bbox": [],
  "geometry": {"coordinates":[-90.0333,33.0833],"type":"Point"}
}