{
  "id": 7558722,
  "type": "Feature",
  "properties": {
    "tgn:hierarchy":[
        "tgn:7558722",
        "tgn:1000004",
        "tgn:7031781",
        "tgn:7000198",
        "tgn:7029392"
    ],
    "tgn:id":7558722,
    "tgn:name:en":"Parasw\u0101ni",
    "tgn:placetype":[
        "aat:300008347"
    ]
},
  "bbox": [],
  "geometry": {"coordinates":[82.651263,21.20968],"type":"Point"}
}