{
  "id": 7229216,
  "type": "Feature",
  "properties": {
    "tgn:hierarchy":[
        "tgn:7229216",
        "tgn:7011167",
        "tgn:7001338",
        "tgn:1000003",
        "tgn:1000074",
        "tgn:7029392"
    ],
    "tgn:id":7229216,
    "tgn:name":"Ga\u00eft\u00e1nion",
    "tgn:placetype":[
        "aat:300008347"
    ]
},
  "bbox": [],
  "geometry": {"coordinates":[20.866667,37.783333],"type":"Point"}
}