{
  "id": 2234474,
  "type": "Feature",
  "properties": {
    "tgn:hierarchy":[
        "tgn:2234474",
        "tgn:1000001",
        "tgn:7012149",
        "tgn:2002330",
        "tgn:7007922",
        "tgn:7029392"
    ],
    "tgn:id":2234474,
    "tgn:name":"Cherneyville",
    "tgn:placetype":[
        "aat:300008347"
    ]
},
  "bbox": [],
  "geometry": {"coordinates":[-87.7333,44.4167],"type":"Point"}
}