{
  "id": 2193072,
  "type": "Feature",
  "properties": {
    "tgn:hierarchy":[
        "tgn:2193072",
        "tgn:1000001",
        "tgn:7012149",
        "tgn:7007157",
        "tgn:1002863",
        "tgn:7029392"
    ],
    "tgn:id":2193072,
    "tgn:name":"Breaker Point",
    "tgn:placetype":[
        "aat:300008850"
    ]
},
  "bbox": [],
  "geometry": {"coordinates":[-121.3167,35.7333],"type":"Point"}
}