{
  "id": 2471661,
  "type": "Feature",
  "properties": {
    "tgn:hierarchy":[
        "tgn:2471661",
        "tgn:1000001",
        "tgn:7012149",
        "tgn:2002051",
        "tgn:7007826",
        "tgn:7029392"
    ],
    "tgn:id":2471661,
    "tgn:name":"Lost Mule Canyon",
    "tgn:placetype":[
        "aat:300008761"
    ]
},
  "bbox": [],
  "geometry": {"coordinates":[-102.7167,35.2833],"type":"Point"}
}