{
  "id": 6004765,
  "type": "Feature",
  "properties": {
    "tgn:hierarchy":[
        "tgn:6004765",
        "tgn:7018452",
        "tgn:1001051",
        "tgn:1000004",
        "tgn:1000144",
        "tgn:7029392"
    ],
    "tgn:id":6004765,
    "tgn:name":"Soloi",
    "tgn:placetype":[
        "aat:300008347",
        "aat:300000810",
        "aat:300167671"
    ]
},
  "bbox": [],
  "geometry": {"coordinates":[32.8126,35.1404],"type":"Point"}
}