<<<<<<< HEAD
{
  "id": 7249558,
  "type": "Feature",
  "properties": {
    "tgn:hierarchy":[
        "tgn:7249558",
        "tgn:7003461",
        "tgn:1000003",
        "tgn:1000063",
        "tgn:7018236",
        "tgn:7029392"
    ],
    "tgn:id":7249558,
    "tgn:name":"Montenaken",
    "tgn:placetype":[
        "aat:300008347"
    ]
},
  "bbox": [],
  "geometry": {"coordinates":[5.133202,50.722342],"type":"Point"}
}
=======
{"geometry":{"type":"Point","coordinates":[5.133202,50.722342]},"type":"Feature","properties":{"hierarchy":["tgn:7249558","tgn:7003461","tgn:1000003","tgn:1000063","tgn:7018236","tgn:7029392"],"placetype":["aat:300008347"],"id":7249558,"name:xx":"Montenaken"}}
>>>>>>> 03f74aca74312dbeaf24d7e61306dd6a786dc3d0
