<<<<<<< HEAD
{
  "id": 7373093,
  "type": "Feature",
  "properties": {
    "tgn:hierarchy":[
        "tgn:7373093",
        "tgn:7005584",
        "tgn:1000001",
        "tgn:7005560",
        "tgn:7029392"
    ],
    "tgn:id":7373093,
    "tgn:name":"La Laja",
    "tgn:placetype":[
        "aat:300008347"
    ]
},
  "bbox": [],
  "geometry": {"coordinates":[-100.95,21.1],"type":"Point"}
}
=======
{"geometry":{"type":"Point","coordinates":[-100.950000,21.100000]},"type":"Feature","properties":{"hierarchy":["tgn:7373093","tgn:7005584","tgn:1000001","tgn:7005560","tgn:7029392"],"placetype":["aat:300008347"],"id":7373093,"name:xx":"La Laja"}}
>>>>>>> 03f74aca74312dbeaf24d7e61306dd6a786dc3d0
