{
  "id": 1055741,
  "type": "Feature",
  "properties": {
    "tgn:hierarchy":[
        "tgn:1055741",
        "tgn:1000003",
        "tgn:7011661",
        "tgn:7006660",
        "tgn:7029392"
    ],
    "tgn:id":1055741,
    "tgn:name":"Kozyn",
    "tgn:placetype":[
        "aat:300008347"
    ]
},
  "bbox": [],
  "geometry": {"coordinates":[30.65,50.2333],"type":"Point"}
}