{
  "id": 7166694,
  "type": "Feature",
  "properties": {
    "tgn:hierarchy":[
        "tgn:7166694",
        "tgn:1000003",
        "tgn:7003682",
        "tgn:7000084",
        "tgn:7029392"
    ],
    "tgn:id":7166694,
    "tgn:name":"Haus Eichelseifen",
    "tgn:placetype":[
        "aat:300000206"
    ]
},
  "bbox": [],
  "geometry": {"coordinates":[6.566667,50.15],"type":"Point"}
}