{
  "id": 2592809,
  "type": "Feature",
  "properties": {
    "tgn:hierarchy":[
        "tgn:2592809",
        "tgn:1000001",
        "tgn:7006451",
        "tgn:7012149",
        "tgn:2000098",
        "tgn:7029392"
    ],
    "tgn:id":2592809,
    "tgn:name":"Pope Mine Cove",
    "tgn:placetype":[
        "aat:300132316"
    ]
},
  "bbox": [],
  "geometry": {"coordinates":[-114.6833,35.7333],"type":"Point"}
}