{
  "id": 2555861,
  "type": "Feature",
  "properties": {
    "tgn:hierarchy":[
        "tgn:2555861",
        "tgn:1002135",
        "tgn:1000001",
        "tgn:7012149",
        "tgn:7007252",
        "tgn:7029392"
    ],
    "tgn:id":2555861,
    "tgn:name":"Ohler Branch",
    "tgn:placetype":[
        "aat:300008699"
    ]
},
  "bbox": [],
  "geometry": {"coordinates":[-84.8667,40.8833],"type":"Point"}
}