<<<<<<< HEAD
{
  "id": 2255378,
  "type": "Feature",
  "properties": {
    "tgn:hierarchy":[
        "tgn:2255378",
        "tgn:1000001",
        "tgn:1002347",
        "tgn:7012149",
        "tgn:7007568",
        "tgn:7029392"
    ],
    "tgn:id":2255378,
    "tgn:name":"Coopertown Brook",
    "tgn:placetype":[
        "aat:300008699"
    ]
},
  "bbox": [],
  "geometry": {"coordinates":[-73.6333,41.6333],"type":"Point"}
}
=======
{"geometry":{"type":"Point","coordinates":[-73.633300,41.633300]},"type":"Feature","properties":{"hierarchy":["tgn:2255378","tgn:1000001","tgn:1002347","tgn:7012149","tgn:7007568","tgn:7029392"],"placetype":["aat:300008699"],"id":2255378,"name:xx":"Coopertown Brook"}}
>>>>>>> 03f74aca74312dbeaf24d7e61306dd6a786dc3d0
