{
  "id": 2024686,
  "type": "Feature",
  "properties": {
    "tgn:hierarchy":[
        "tgn:2024686",
        "tgn:1000001",
        "tgn:7012149",
        "tgn:2000344",
        "tgn:7007248",
        "tgn:7029392"
    ],
    "tgn:id":2024686,
    "tgn:name":"Wesley",
    "tgn:placetype":[
        "aat:300008347"
    ]
},
  "bbox": [],
  "geometry": {"coordinates":[-82.3167,32.4833],"type":"Point"}
}