<<<<<<< HEAD
{
  "id": 2331111,
  "type": "Feature",
  "properties": {
    "tgn:hierarchy":[
        "tgn:2331111",
        "tgn:1000001",
        "tgn:7012149",
        "tgn:2001718",
        "tgn:7007708",
        "tgn:7029392"
    ],
    "tgn:id":2331111,
    "tgn:name":"Flat Tire Reservoir",
    "tgn:placetype":[
        "aat:300006191"
    ]
},
  "bbox": [],
  "geometry": {"coordinates":[-117.5833,42.3333],"type":"Point"}
}
=======
{"geometry":{"type":"Point","coordinates":[-117.583300,42.333300]},"type":"Feature","properties":{"hierarchy":["tgn:2331111","tgn:1000001","tgn:7012149","tgn:2001718","tgn:7007708","tgn:7029392"],"placetype":["aat:300006191"],"id":2331111,"name:xx":"Flat Tire Reservoir"}}
>>>>>>> 03f74aca74312dbeaf24d7e61306dd6a786dc3d0
