{
  "id": 2331111,
  "type": "Feature",
  "properties": {
    "tgn:hierarchy":[
        "tgn:2331111",
        "tgn:1000001",
        "tgn:7012149",
        "tgn:2001718",
        "tgn:7007708",
        "tgn:7029392"
    ],
    "tgn:id":2331111,
    "tgn:name":"Flat Tire Reservoir",
    "tgn:placetype":[
        "aat:300006191"
    ]
},
  "bbox": [],
  "geometry": {"coordinates":[-117.5833,42.3333],"type":"Point"}
}