{
  "id": 7323323,
  "type": "Feature",
  "properties": {
    "tgn:hierarchy":[
        "tgn:7323323",
        "tgn:7002834",
        "tgn:1000003",
        "tgn:7002786",
        "tgn:1000095",
        "tgn:7029392"
    ],
    "tgn:id":7323323,
    "tgn:name":"Rosal",
    "tgn:placetype":[
        "aat:300008347"
    ]
},
  "bbox": [],
  "geometry": {"coordinates":[-8.833333,41.933333],"type":"Point"}
}