{
  "id": 2247146,
  "type": "Feature",
  "properties": {
    "tgn:hierarchy":[
        "tgn:2247146",
        "tgn:1000001",
        "tgn:7012149",
        "tgn:1002870",
        "tgn:7007240",
        "tgn:7029392"
    ],
    "tgn:id":2247146,
    "tgn:name":"Cocoplum Waterway",
    "tgn:placetype":[
        "aat:300006075"
    ]
},
  "bbox": [],
  "geometry": {"coordinates":[-82.1667,27.0167],"type":"Point"}
}