{
  "id": 7424282,
  "type": "Feature",
  "properties": {
    "tgn:hierarchy":[
        "tgn:7424282",
        "tgn:1000001",
        "tgn:1001960",
        "tgn:7005560",
        "tgn:7029392"
    ],
    "tgn:id":7424282,
    "tgn:name":"Escuela Superior de Agricultura y Ganader\u00eda",
    "tgn:placetype":[
        "aat:300006495"
    ]
},
  "bbox": [],
  "geometry": {"coordinates":[-111.133333,29.016667],"type":"Point"}
}