{
  "id": 2303150,
  "type": "Feature",
  "properties": {
    "tgn:hierarchy":[
        "tgn:2303150",
        "tgn:1000001",
        "tgn:7012149",
        "tgn:1003044",
        "tgn:7007708",
        "tgn:7029392"
    ],
    "tgn:id":2303150,
    "tgn:name":"Ead Creek",
    "tgn:placetype":[
        "aat:300008706"
    ]
},
  "bbox": [],
  "geometry": {"coordinates":[-123.7167,45.15],"type":"Point"}
}