{
  "id": 2352859,
  "type": "Feature",
  "properties": {
    "tgn:hierarchy":[
        "tgn:2352859",
        "tgn:1000001",
        "tgn:7012149",
        "tgn:7007157",
        "tgn:1002748",
        "tgn:7029392"
    ],
    "tgn:id":2352859,
    "tgn:name":"Gobernadora, Ca\u00f1ada",
    "tgn:placetype":[
        "aat:300008761"
    ]
},
  "bbox": [],
  "geometry": {"coordinates":[-117.5667,33.6333],"type":"Point"}
}