{
  "id": 2573742,
  "type": "Feature",
  "properties": {
    "tgn:hierarchy":[
        "tgn:2573742",
        "tgn:7013388",
        "tgn:1000001",
        "tgn:7012149",
        "tgn:7007517",
        "tgn:7029392"
    ],
    "tgn:id":2573742,
    "tgn:name":"Pecks Pond",
    "tgn:placetype":[
        "aat:300008680"
    ]
},
  "bbox": [],
  "geometry": {"coordinates":[-73.25,42.4667],"type":"Point"}
}