{
  "id": 7221815,
  "type": "Feature",
  "properties": {
    "tgn:hierarchy":[
        "tgn:7221815",
        "tgn:7002751",
        "tgn:7001399",
        "tgn:1000003",
        "tgn:1000074",
        "tgn:7029392"
    ],
    "tgn:id":7221815,
    "tgn:name":"Skant\u00edli, Nis\u00edda",
    "tgn:placetype":[
        "aat:300008791"
    ]
},
  "bbox": [],
  "geometry": {"coordinates":[24.083333,39.05],"type":"Point"}
}