{
  "id": 2180443,
  "type": "Feature",
  "properties": {
    "tgn:hierarchy":[
        "tgn:2180443",
        "tgn:2000919",
        "tgn:1000001",
        "tgn:7012149",
        "tgn:7007515",
        "tgn:7029392"
    ],
    "tgn:id":2180443,
    "tgn:name":"Blood Lake",
    "tgn:placetype":[
        "aat:300008680"
    ]
},
  "bbox": [],
  "geometry": {"coordinates":[-69.7333,46.85],"type":"Point"}
}