{
  "id": 7375909,
  "type": "Feature",
  "properties": {
    "tgn:hierarchy":[
        "tgn:7375909",
        "tgn:1000001",
        "tgn:7005595",
        "tgn:7005560",
        "tgn:7029392"
    ],
    "tgn:id":7375909,
    "tgn:name":"Las Higueras",
    "tgn:placetype":[
        "aat:300008347"
    ]
},
  "bbox": [],
  "geometry": {"coordinates":[-108.466667,25.366667],"type":"Point"}
}