{
  "id": 7586625,
  "type": "Feature",
  "properties": {
    "tgn:hierarchy":[
        "tgn:7586625",
        "tgn:1000004",
        "tgn:7000198",
        "tgn:7000799",
        "tgn:7029392"
    ],
    "tgn:id":7586625,
    "tgn:name:en":"Mowu",
    "tgn:placetype":[
        "aat:300008347"
    ]
},
  "bbox": [],
  "geometry": {"coordinates":[74.762353,34.456669],"type":"Point"}
}