{
  "id": 7583102,
  "type": "Feature",
  "properties": {
    "tgn:hierarchy":[
        "tgn:7583102",
        "tgn:1000004",
        "tgn:7000198",
        "tgn:7016788",
        "tgn:7029392"
    ],
    "tgn:id":7583102,
    "tgn:name:en":"Sol\u0101na",
    "tgn:placetype":[
        "aat:300008347"
    ]
},
  "bbox": [],
  "geometry": {"coordinates":[75.568395,28.06232],"type":"Point"}
}