{
  "id": 2629259,
  "type": "Feature",
  "properties": {
    "tgn:hierarchy":[
        "tgn:2629259",
        "tgn:1000001",
        "tgn:1002657",
        "tgn:7012149",
        "tgn:7007565",
        "tgn:7029392"
    ],
    "tgn:id":2629259,
    "tgn:name":"Rose, Mount",
    "tgn:placetype":[
        "aat:300008798"
    ]
},
  "bbox": [],
  "geometry": {"coordinates":[-74.7167,40.3667],"type":"Point"}
}