{
  "id": 2661338,
  "type": "Feature",
  "properties": {
    "tgn:hierarchy":[
        "tgn:2661338",
        "tgn:1000001",
        "tgn:7012149",
        "tgn:2001456",
        "tgn:7007566",
        "tgn:7029392"
    ],
    "tgn:id":2661338,
    "tgn:name":"Shorty Tank",
    "tgn:placetype":[
        "aat:300006191"
    ]
},
  "bbox": [],
  "geometry": {"coordinates":[-106.8167,33.7333],"type":"Point"}
}