<<<<<<< HEAD
{
  "id": 2764953,
  "type": "Feature",
  "properties": {
    "tgn:hierarchy":[
        "tgn:2764953",
        "tgn:1000001",
        "tgn:7012149",
        "tgn:7007157",
        "tgn:2000191",
        "tgn:7029392"
    ],
    "tgn:id":2764953,
    "tgn:name":"Whisky Bill Peak",
    "tgn:placetype":[
        "aat:300008798"
    ]
},
  "bbox": [],
  "geometry": {"coordinates":[-122.5167,41.1],"type":"Point"}
}
=======
{"geometry":{"type":"Point","coordinates":[-122.516700,41.100000]},"type":"Feature","properties":{"hierarchy":["tgn:2764953","tgn:1000001","tgn:7012149","tgn:7007157","tgn:2000191","tgn:7029392"],"placetype":["aat:300008798"],"id":2764953,"name:xx":"Whisky Bill Peak"}}
>>>>>>> 03f74aca74312dbeaf24d7e61306dd6a786dc3d0
