{
  "id": 7180025,
  "type": "Feature",
  "properties": {
    "tgn:hierarchy":[
        "tgn:7180025",
        "tgn:1000003",
        "tgn:7003676",
        "tgn:7000084",
        "tgn:7029392"
    ],
    "tgn:id":7180025,
    "tgn:name":"Friedeholz",
    "tgn:placetype":[
        "aat:300008863"
    ]
},
  "bbox": [],
  "geometry": {"coordinates":[8.633333,52.866667],"type":"Point"}
}