{
  "id": 7471810,
  "type": "Feature",
  "properties": {
    "tgn:hierarchy":[
        "tgn:7471810",
        "tgn:1000004",
        "tgn:7490934",
        "tgn:1000141",
        "tgn:7029392"
    ],
    "tgn:id":7471810,
    "tgn:name":"Fazitou",
    "tgn:placetype":[
        "aat:300008347"
    ]
},
  "bbox": [],
  "geometry": {"coordinates":[120.1685,23.2675],"type":"Point"}
}