{
  "id": 7371943,
  "type": "Feature",
  "properties": {
    "tgn:hierarchy":[
        "tgn:7371943",
        "tgn:1000001",
        "tgn:7005589",
        "tgn:7005560",
        "tgn:7029392"
    ],
    "tgn:id":7371943,
    "tgn:name":"La Jarita",
    "tgn:placetype":[
        "aat:300008347"
    ]
},
  "bbox": [],
  "geometry": {"coordinates":[-99.783333,27.433333],"type":"Point"}
}