<<<<<<< HEAD
{
  "id": 7371943,
  "type": "Feature",
  "properties": {
    "tgn:hierarchy":[
        "tgn:7371943",
        "tgn:1000001",
        "tgn:7005589",
        "tgn:7005560",
        "tgn:7029392"
    ],
    "tgn:id":7371943,
    "tgn:name":"La Jarita",
    "tgn:placetype":[
        "aat:300008347"
    ]
},
  "bbox": [],
  "geometry": {"coordinates":[-99.783333,27.433333],"type":"Point"}
}
=======
{"geometry":{"type":"Point","coordinates":[-99.783333,27.433333]},"type":"Feature","properties":{"hierarchy":["tgn:7371943","tgn:1000001","tgn:7005589","tgn:7005560","tgn:7029392"],"placetype":["aat:300008347"],"id":7371943,"name:xx":"La Jarita"}}
>>>>>>> 03f74aca74312dbeaf24d7e61306dd6a786dc3d0
