{
  "id": 7203727,
  "type": "Feature",
  "properties": {
    "tgn:hierarchy":[
        "tgn:7203727",
        "tgn:1000003",
        "tgn:7003676",
        "tgn:7000084",
        "tgn:7029392"
    ],
    "tgn:id":7203727,
    "tgn:name":"Br\u00fcne",
    "tgn:placetype":[
        "aat:300008347"
    ]
},
  "bbox": [],
  "geometry": {"coordinates":[9.016667,52.783333],"type":"Point"}
}