{
  "id": 7435824,
  "type": "Feature",
  "properties": {
    "tgn:hierarchy":[
        "tgn:7435824",
        "tgn:7005584",
        "tgn:1000001",
        "tgn:7005560",
        "tgn:7029392"
    ],
    "tgn:id":7435824,
    "tgn:name":"Soria",
    "tgn:placetype":[
        "aat:300008347"
    ]
},
  "bbox": [],
  "geometry": {"coordinates":[-100.816667,20.816667],"type":"Point"}
}