{
  "id": 2299713,
  "type": "Feature",
  "properties": {
    "tgn:hierarchy":[
        "tgn:2299713",
        "tgn:1000001",
        "tgn:7012149",
        "tgn:2002297",
        "tgn:7013961",
        "tgn:7029392"
    ],
    "tgn:id":2299713,
    "tgn:name":"Duckworth Ridge",
    "tgn:placetype":[
        "aat:300266640"
    ]
},
  "bbox": [],
  "geometry": {"coordinates":[-80.8333,39.3667],"type":"Point"}
}