{
  "id": 2223363,
  "type": "Feature",
  "properties": {
    "tgn:hierarchy":[
        "tgn:2223363",
        "tgn:1000001",
        "tgn:7012149",
        "tgn:2001844",
        "tgn:7007825",
        "tgn:7029392"
    ],
    "tgn:id":2223363,
    "tgn:name":"Carson Hills",
    "tgn:placetype":[
        "aat:300008798"
    ]
},
  "bbox": [],
  "geometry": {"coordinates":[-86.1167,35.7167],"type":"Point"}
}