{
  "id": 2786944,
  "type": "Feature",
  "properties": {
    "tgn:hierarchy":[
        "tgn:2786944",
        "tgn:1000001",
        "tgn:2000457",
        "tgn:7012149",
        "tgn:7007250",
        "tgn:7029392"
    ],
    "tgn:id":2786944,
    "tgn:name":"Ziegler Mountain",
    "tgn:placetype":[
        "aat:300008798"
    ]
},
  "bbox": [],
  "geometry": {"coordinates":[-111.8167,43.25],"type":"Point"}
}