{
  "id": 2315055,
  "type": "Feature",
  "properties": {
    "tgn:hierarchy":[
        "tgn:2315055",
        "tgn:1000001",
        "tgn:2001471",
        "tgn:7012149",
        "tgn:7007709",
        "tgn:7029392"
    ],
    "tgn:id":2315055,
    "tgn:name":"Elkton Swamp",
    "tgn:placetype":[
        "aat:300008699"
    ]
},
  "bbox": [],
  "geometry": {"coordinates":[-78.5667,34.4833],"type":"Point"}
}