{
  "id": 7272638,
  "type": "Feature",
  "properties": {
    "tgn:hierarchy":[
        "tgn:7272638",
        "tgn:1000003",
        "tgn:7003632",
        "tgn:7016845",
        "tgn:7029392"
    ],
    "tgn:id":7272638,
    "tgn:name:nl":"Vliet en Dijkveld, Polder",
    "tgn:placetype":[
        "aat:300006163"
    ]
},
  "bbox": [],
  "geometry": {"coordinates":[4.866667,52.016667],"type":"Point"}
}