{
  "id": 2286129,
  "type": "Feature",
  "properties": {
    "tgn:hierarchy":[
        "tgn:2286129",
        "tgn:1000001",
        "tgn:7012149",
        "tgn:7014371",
        "tgn:7007248",
        "tgn:7029392"
    ],
    "tgn:id":2286129,
    "tgn:name":"Dewey City",
    "tgn:placetype":[
        "aat:300008347"
    ]
},
  "bbox": [],
  "geometry": {"coordinates":[-83.9833,30.8333],"type":"Point"}
}