{
  "id": 7590953,
  "type": "Feature",
  "properties": {
    "tgn:hierarchy":[
        "tgn:7590953",
        "tgn:1000004",
        "tgn:7000198",
        "tgn:7000799",
        "tgn:7029392"
    ],
    "tgn:id":7590953,
    "tgn:name:en":"Jam\u0101na Bela",
    "tgn:placetype":[
        "aat:300008347"
    ]
},
  "bbox": [],
  "geometry": {"coordinates":[74.600473,32.771115],"type":"Point"}
}