{
  "id": 2274031,
  "type": "Feature",
  "properties": {
    "tgn:hierarchy":[
        "tgn:2274031",
        "tgn:7006450",
        "tgn:1000001",
        "tgn:7012149",
        "tgn:7029392"
    ],
    "tgn:id":2274031,
    "tgn:name":"Dahigren Peak",
    "tgn:placetype":[
        "aat:300008798"
    ]
},
  "bbox": [],
  "geometry": {"coordinates":[-133.35,57.2333],"type":"Point"}
}