{
  "id": 2537362,
  "type": "Feature",
  "properties": {
    "tgn:hierarchy":[
        "tgn:2537362",
        "tgn:1000001",
        "tgn:7012149",
        "tgn:2002062",
        "tgn:7007826",
        "tgn:7029392"
    ],
    "tgn:id":2537362,
    "tgn:name":"Negro Head",
    "tgn:placetype":[
        "aat:300008798"
    ]
},
  "bbox": [],
  "geometry": {"coordinates":[-103.55,30.8333],"type":"Point"}
}