{
  "id": 7492896,
  "type": "Feature",
  "properties": {
    "tgn:hierarchy":[
        "tgn:7492896",
        "tgn:1000004",
        "tgn:7001014",
        "tgn:1000141",
        "tgn:7029392"
    ],
    "tgn:id":7492896,
    "tgn:name":"Pingding",
    "tgn:placetype":[
        "aat:300008347"
    ]
},
  "bbox": [],
  "geometry": {"coordinates":[120.638365,23.752314],"type":"Point"}
}