{
  "id": 1064862,
  "type": "Feature",
  "properties": {
    "tgn:hierarchy":[
        "tgn:1064862",
        "tgn:1000003",
        "tgn:7006669",
        "tgn:7029392"
    ],
    "tgn:id":1064862,
    "tgn:name":"\u0106uprija",
    "tgn:placetype":[
        "aat:300008347"
    ]
},
  "bbox": [],
  "geometry": {"coordinates":[21.35,43.9333],"type":"Point"}
}