{
  "id": 7217115,
  "type": "Feature",
  "properties": {
    "tgn:hierarchy":[
        "tgn:7217115",
        "tgn:7002741",
        "tgn:7017076",
        "tgn:1000003",
        "tgn:1000074",
        "tgn:7029392"
    ],
    "tgn:id":7217115,
    "tgn:name":"Zaro\u00fakhla",
    "tgn:placetype":[
        "aat:300008347"
    ]
},
  "bbox": [],
  "geometry": {"coordinates":[22.266667,37.983333],"type":"Point"}
}