{
  "id": 7092354,
  "type": "Feature",
  "properties": {
    "tgn:hierarchy":[
        "tgn:7092354",
        "tgn:7003692",
        "tgn:1000003",
        "tgn:7000084",
        "tgn:7029392"
    ],
    "tgn:id":7092354,
    "tgn:name":"Urlauer Ober\u00f6schh\u00f6fe",
    "tgn:placetype":[
        "aat:300000206"
    ]
},
  "bbox": [],
  "geometry": {"coordinates":[10.05,47.766667],"type":"Point"}
}