{
  "id": 2578295,
  "type": "Feature",
  "properties": {
    "tgn:hierarchy":[
        "tgn:2578295",
        "tgn:1000001",
        "tgn:7012149",
        "tgn:2002127",
        "tgn:7007827",
        "tgn:7029392"
    ],
    "tgn:id":2578295,
    "tgn:name":"Phantom Valley",
    "tgn:placetype":[
        "aat:300008761"
    ]
},
  "bbox": [],
  "geometry": {"coordinates":[-112.9833,37.2833],"type":"Point"}
}