{
  "id": 2725628,
  "type": "Feature",
  "properties": {
    "tgn:hierarchy":[
        "tgn:2725628",
        "tgn:1000001",
        "tgn:7006451",
        "tgn:2000094",
        "tgn:7012149",
        "tgn:7029392"
    ],
    "tgn:id":2725628,
    "tgn:name":"Topout Divide",
    "tgn:placetype":[
        "aat:300266640"
    ]
},
  "bbox": [],
  "geometry": {"coordinates":[-110.3167,32.65],"type":"Point"}
}