{
  "id": 7347841,
  "type": "Feature",
  "properties": {
    "tgn:hierarchy":[
        "tgn:7347841",
        "tgn:7002822",
        "tgn:1001647",
        "tgn:1000003",
        "tgn:1000095",
        "tgn:7029392"
    ],
    "tgn:id":7347841,
    "tgn:name":"Albendiego",
    "tgn:placetype":[
        "aat:300008347"
    ]
},
  "bbox": [],
  "geometry": {"coordinates":[-3.05,41.233333],"type":"Point"}
}