{
  "id": 2465120,
  "type": "Feature",
  "properties": {
    "tgn:hierarchy":[
        "tgn:2465120",
        "tgn:1000001",
        "tgn:7012149",
        "tgn:2000291",
        "tgn:7007240",
        "tgn:7029392"
    ],
    "tgn:id":2465120,
    "tgn:name":"Lolly Head Bay",
    "tgn:placetype":[
        "aat:300008905"
    ]
},
  "bbox": [],
  "geometry": {"coordinates":[-85.7333,30.6667],"type":"Point"}
}