{
  "id": 2568069,
  "type": "Feature",
  "properties": {
    "tgn:hierarchy":[
        "tgn:2568069",
        "tgn:1002176",
        "tgn:1000001",
        "tgn:7012149",
        "tgn:7007828",
        "tgn:7029392"
    ],
    "tgn:id":2568069,
    "tgn:name":"Paran Creek",
    "tgn:placetype":[
        "aat:300008706"
    ]
},
  "bbox": [],
  "geometry": {"coordinates":[-73.1833,42.9833],"type":"Point"}
}