{
  "id": 1067539,
  "type": "Feature",
  "properties": {
    "tgn:hierarchy":[
        "tgn:1067539",
        "tgn:1000004",
        "tgn:7002086",
        "tgn:1000111",
        "tgn:7029392"
    ],
    "tgn:id":1067539,
    "tgn:name":"Daquanshan",
    "tgn:placetype":[
        "aat:300008347"
    ]
},
  "bbox": [],
  "geometry": {"coordinates":[113.8167,40.2833],"type":"Point"}
}