{
  "id": 7131349,
  "type": "Feature",
  "properties": {
    "tgn:hierarchy":[
        "tgn:7131349",
        "tgn:7000096",
        "tgn:1000003",
        "tgn:7000084",
        "tgn:7029392"
    ],
    "tgn:id":7131349,
    "tgn:name":"Mittelbusch",
    "tgn:placetype":[
        "aat:300008347"
    ]
},
  "bbox": [],
  "geometry": {"coordinates":[12.933333,52.333333],"type":"Point"}
}