{
  "id": 2174313,
  "type": "Feature",
  "properties": {
    "tgn:hierarchy":[
        "tgn:2174313",
        "tgn:7019618",
        "tgn:1000001",
        "tgn:7012149",
        "tgn:7007564",
        "tgn:7029392"
    ],
    "tgn:id":2174313,
    "tgn:name":"Biscuit Hill",
    "tgn:placetype":[
        "aat:300008798"
    ]
},
  "bbox": [],
  "geometry": {"coordinates":[-72.4667,42.7667],"type":"Point"}
}