{
  "id": 2178063,
  "type": "Feature",
  "properties": {
    "tgn:hierarchy":[
        "tgn:2178063",
        "tgn:1000001",
        "tgn:7012149",
        "tgn:1003038",
        "tgn:7007517",
        "tgn:7029392"
    ],
    "tgn:id":2178063,
    "tgn:name":"Blackburn Village",
    "tgn:placetype":[
        "aat:300008347"
    ]
},
  "bbox": [],
  "geometry": {"coordinates":[-71.8667,42.6167],"type":"Point"}
}