{
  "id": 7105803,
  "type": "Feature",
  "properties": {
    "tgn:hierarchy":[
        "tgn:7105803",
        "tgn:7000096",
        "tgn:1000003",
        "tgn:7000084",
        "tgn:7029392"
    ],
    "tgn:id":7105803,
    "tgn:name":"Schamp-See",
    "tgn:placetype":[
        "aat:300008680"
    ]
},
  "bbox": [],
  "geometry": {"coordinates":[12.783333,52.333333],"type":"Point"}
}