{
  "id": 7076732,
  "type": "Feature",
  "properties": {
    "tgn:hierarchy":[
        "tgn:7076732",
        "tgn:1000003",
        "tgn:7003682",
        "tgn:7000084",
        "tgn:7029392"
    ],
    "tgn:id":7076732,
    "tgn:name":"Hochdorf-Assenheim",
    "tgn:placetype":[
        "aat:300008347"
    ]
},
  "bbox": [],
  "geometry": {"coordinates":[8.281667,49.419444],"type":"Point"}
}