{
  "id": 2380204,
  "type": "Feature",
  "properties": {
    "tgn:hierarchy":[
        "tgn:2380204",
        "tgn:1000001",
        "tgn:7012149",
        "tgn:2000362",
        "tgn:7007248",
        "tgn:7029392"
    ],
    "tgn:id":2380204,
    "tgn:name":"Hatfields Lake",
    "tgn:placetype":[
        "aat:300006191"
    ]
},
  "bbox": [],
  "geometry": {"coordinates":[-85.0833,33.75],"type":"Point"}
}