{
  "id": 2137249,
  "type": "Feature",
  "properties": {
    "tgn:hierarchy":[
        "tgn:2137249",
        "tgn:1000001",
        "tgn:2001424",
        "tgn:7012149",
        "tgn:7007564",
        "tgn:7029392"
    ],
    "tgn:id":2137249,
    "tgn:name":"Armington, Lake",
    "tgn:placetype":[
        "aat:300008680"
    ]
},
  "bbox": [],
  "geometry": {"coordinates":[-71.9667,43.95],"type":"Point"}
}