{
  "id": 7102397,
  "type": "Feature",
  "properties": {
    "tgn:hierarchy":[
        "tgn:7102397",
        "tgn:7000096",
        "tgn:1000003",
        "tgn:7000084",
        "tgn:7029392"
    ],
    "tgn:id":7102397,
    "tgn:name":"Ruhlsdorf",
    "tgn:placetype":[
        "aat:300008347"
    ]
},
  "bbox": [],
  "geometry": {"coordinates":[13.166667,52.133333],"type":"Point"}
}