{
  "id": 2235546,
  "type": "Feature",
  "properties": {
    "tgn:hierarchy":[
        "tgn:2235546",
        "tgn:1000001",
        "tgn:7012149",
        "tgn:2000290",
        "tgn:7007240",
        "tgn:7029392"
    ],
    "tgn:id":2235546,
    "tgn:name":"Chestnut Creek",
    "tgn:placetype":[
        "aat:300008706"
    ]
},
  "bbox": [],
  "geometry": {"coordinates":[-86.0833,30.9333],"type":"Point"}
}