{
  "id": 7561050,
  "type": "Feature",
  "properties": {
    "tgn:hierarchy":[
        "tgn:7561050",
        "tgn:1000004",
        "tgn:7000198",
        "tgn:7016722",
        "tgn:7029392"
    ],
    "tgn:id":7561050,
    "tgn:name:en":"Nagla Barw\u0101ri",
    "tgn:placetype":[
        "aat:300008347"
    ]
},
  "bbox": [],
  "geometry": {"coordinates":[79.445479,27.091012],"type":"Point"}
}