{
  "id": 7114366,
  "type": "Feature",
  "properties": {
    "tgn:hierarchy":[
        "tgn:7114366",
        "tgn:1000003",
        "tgn:7003688",
        "tgn:7000084",
        "tgn:7029392"
    ],
    "tgn:id":7114366,
    "tgn:name":"R\u00f6bel",
    "tgn:placetype":[
        "aat:300008347"
    ]
},
  "bbox": [],
  "geometry": {"coordinates":[10.666667,54.116667],"type":"Point"}
}