{
  "id": 2552870,
  "type": "Feature",
  "properties": {
    "tgn:hierarchy":[
        "tgn:2552870",
        "tgn:1000001",
        "tgn:7012149",
        "tgn:2001115",
        "tgn:7007522",
        "tgn:7029392"
    ],
    "tgn:id":2552870,
    "tgn:name":"O Pines Lake",
    "tgn:placetype":[
        "aat:300006191"
    ]
},
  "bbox": [],
  "geometry": {"coordinates":[-88.6833,30.5667],"type":"Point"}
}