{
  "id": 7488406,
  "type": "Feature",
  "properties": {
    "tgn:hierarchy":[
        "tgn:7488406",
        "tgn:1000004",
        "tgn:7467799",
        "tgn:1000141",
        "tgn:7029392"
    ],
    "tgn:id":7488406,
    "tgn:name":"Nanmeizhuang",
    "tgn:placetype":[
        "aat:300008347"
    ]
},
  "bbox": [],
  "geometry": {"coordinates":[120.521978,24.057336],"type":"Point"}
}