{
  "id": 2025343,
  "type": "Feature",
  "properties": {
    "tgn:hierarchy":[
        "tgn:2025343",
        "tgn:1000001",
        "tgn:2000463",
        "tgn:7012149",
        "tgn:7007250",
        "tgn:7029392"
    ],
    "tgn:id":2025343,
    "tgn:name":"Arco",
    "tgn:placetype":[
        "aat:300008347"
    ]
},
  "bbox": [],
  "geometry": {"coordinates":[-113.2833,43.6333],"type":"Point"}
}