<<<<<<< HEAD
{
  "id": 2153185,
  "type": "Feature",
  "properties": {
    "tgn:hierarchy":[
        "tgn:2153185",
        "tgn:1002143",
        "tgn:1000001",
        "tgn:7012149",
        "tgn:7007252",
        "tgn:7029392"
    ],
    "tgn:id":2153185,
    "tgn:name":"Beal Taylor Ditch",
    "tgn:placetype":[
        "aat:300006075"
    ]
},
  "bbox": [],
  "geometry": {"coordinates":[-85.3167,41.0667],"type":"Point"}
}
=======
{"geometry":{"type":"Point","coordinates":[-85.316700,41.066700]},"type":"Feature","properties":{"hierarchy":["tgn:2153185","tgn:1002143","tgn:1000001","tgn:7012149","tgn:7007252","tgn:7029392"],"placetype":["aat:300006075"],"id":2153185,"name:xx":"Beal Taylor Ditch"}}
>>>>>>> 03f74aca74312dbeaf24d7e61306dd6a786dc3d0
