{
  "id": 7575213,
  "type": "Feature",
  "properties": {
    "tgn:hierarchy":[
        "tgn:7575213",
        "tgn:1000004",
        "tgn:7000198",
        "tgn:7000799",
        "tgn:7029392"
    ],
    "tgn:id":7575213,
    "tgn:name:en":"Kyun Tso",
    "tgn:placetype":[
        "aat:300008680"
    ]
},
  "bbox": [],
  "geometry": {"coordinates":[78.601768,32.921287],"type":"Point"}
}