{
  "id": 7308021,
  "type": "Feature",
  "properties": {
    "tgn:hierarchy":[
        "tgn:7308021",
        "tgn:1001708",
        "tgn:1000049",
        "tgn:1000002",
        "tgn:7029392"
    ],
    "tgn:id":7308021,
    "tgn:name":"Melosa",
    "tgn:placetype":[
        "aat:300008347"
    ]
},
  "bbox": [],
  "geometry": {"coordinates":[-70.233333,-33.85],"type":"Point"}
}