{
  "id": 7591574,
  "type": "Feature",
  "properties": {
    "tgn:hierarchy":[
        "tgn:7591574",
        "tgn:1000004",
        "tgn:7000198",
        "tgn:7000799",
        "tgn:7029392"
    ],
    "tgn:id":7591574,
    "tgn:name:en":"Abdullun Dh\u0101r",
    "tgn:placetype":[
        "aat:300008795"
    ]
},
  "bbox": [],
  "geometry": {"coordinates":[75.283333,34.516667],"type":"Point"}
}