{
  "id": 2714015,
  "type": "Feature",
  "properties": {
    "tgn:hierarchy":[
        "tgn:2714015",
        "tgn:1000001",
        "tgn:7006451",
        "tgn:7012149",
        "tgn:2000102",
        "tgn:7029392"
    ],
    "tgn:id":2714015,
    "tgn:name":"Tejano Spring",
    "tgn:placetype":[
        "aat:300008697"
    ]
},
  "bbox": [],
  "geometry": {"coordinates":[-110.9167,31.5667],"type":"Point"}
}