{
  "id": 7340584,
  "type": "Feature",
  "properties": {
    "tgn:hierarchy":[
        "tgn:7340584",
        "tgn:7002824",
        "tgn:1000003",
        "tgn:7002786",
        "tgn:1000095",
        "tgn:7029392"
    ],
    "tgn:id":7340584,
    "tgn:name":"Canosa",
    "tgn:placetype":[
        "aat:300008347"
    ]
},
  "bbox": [],
  "geometry": {"coordinates":[-9.25,42.983333],"type":"Point"}
}