<<<<<<< HEAD
{
  "id": 2769040,
  "type": "Feature",
  "properties": {
    "tgn:hierarchy":[
        "tgn:2769040",
        "tgn:1000001",
        "tgn:1002480",
        "tgn:7012149",
        "tgn:7007564",
        "tgn:7029392"
    ],
    "tgn:id":2769040,
    "tgn:name":"Whittemore Lake",
    "tgn:placetype":[
        "aat:300008680"
    ]
},
  "bbox": [],
  "geometry": {"coordinates":[-71.9,42.9833],"type":"Point"}
}
=======
{"geometry":{"type":"Point","coordinates":[-71.900000,42.983300]},"type":"Feature","properties":{"hierarchy":["tgn:2769040","tgn:1000001","tgn:1002480","tgn:7012149","tgn:7007564","tgn:7029392"],"placetype":["aat:300008680"],"id":2769040,"name:xx":"Whittemore Lake"}}
>>>>>>> 03f74aca74312dbeaf24d7e61306dd6a786dc3d0
