{
  "id": 2604300,
  "type": "Feature",
  "properties": {
    "tgn:hierarchy":[
        "tgn:2604300",
        "tgn:1000001",
        "tgn:7012149",
        "tgn:2001715",
        "tgn:7007708",
        "tgn:7029392"
    ],
    "tgn:id":2604300,
    "tgn:name":"Rabbit Basin",
    "tgn:placetype":[
        "aat:300386845"
    ]
},
  "bbox": [],
  "geometry": {"coordinates":[-119.8833,42.6667],"type":"Point"}
}