{
  "id": 7430871,
  "type": "Feature",
  "properties": {
    "tgn:hierarchy":[
        "tgn:7430871",
        "tgn:1000001",
        "tgn:7005595",
        "tgn:7005560",
        "tgn:7029392"
    ],
    "tgn:id":7430871,
    "tgn:name":"Campo Caballos",
    "tgn:placetype":[
        "aat:300008347"
    ]
},
  "bbox": [],
  "geometry": {"coordinates":[-108.85,25.866667],"type":"Point"}
}