<<<<<<< HEAD
{
  "id": 2332438,
  "type": "Feature",
  "properties": {
    "tgn:hierarchy":[
        "tgn:2332438",
        "tgn:1000001",
        "tgn:7012149",
        "tgn:7007157",
        "tgn:7029392"
    ],
    "tgn:id":2332438,
    "tgn:name":"Florence Creek",
    "tgn:placetype":[
        "aat:300008706"
    ]
},
  "bbox": [],
  "geometry": {"coordinates":[-119.3,37.75],"type":"Point"}
}
=======
{"geometry":{"type":"Point","coordinates":[-119.300000,37.750000]},"type":"Feature","properties":{"hierarchy":["tgn:2332438","tgn:1000001","tgn:7012149","tgn:7007157","tgn:7029392"],"placetype":["aat:300008706"],"id":2332438,"name:xx":"Florence Creek"}}
>>>>>>> 03f74aca74312dbeaf24d7e61306dd6a786dc3d0
