{
  "id": 2056512,
  "type": "Feature",
  "properties": {
    "tgn:hierarchy":[
        "tgn:2056512",
        "tgn:1000001",
        "tgn:7012149",
        "tgn:2001131",
        "tgn:7007522",
        "tgn:7029392"
    ],
    "tgn:id":2056512,
    "tgn:name":"Goss",
    "tgn:placetype":[
        "aat:300008347"
    ]
},
  "bbox": [],
  "geometry": {"coordinates":[-89.8833,31.35],"type":"Point"}
}