<<<<<<< HEAD
{
  "id": 2764693,
  "type": "Feature",
  "properties": {
    "tgn:hierarchy":[
        "tgn:2764693",
        "tgn:1000001",
        "tgn:2001640",
        "tgn:7012149",
        "tgn:7007707",
        "tgn:7029392"
    ],
    "tgn:id":2764693,
    "tgn:name":"Whiskey Branch",
    "tgn:placetype":[
        "aat:300008699"
    ]
},
  "bbox": [],
  "geometry": {"coordinates":[-95.1,36.8],"type":"Point"}
}
=======
{"geometry":{"type":"Point","coordinates":[-95.100000,36.800000]},"type":"Feature","properties":{"hierarchy":["tgn:2764693","tgn:1000001","tgn:2001640","tgn:7012149","tgn:7007707","tgn:7029392"],"placetype":["aat:300008699"],"id":2764693,"name:xx":"Whiskey Branch"}}
>>>>>>> 03f74aca74312dbeaf24d7e61306dd6a786dc3d0
