{
  "id": 7214819,
  "type": "Feature",
  "properties": {
    "tgn:hierarchy":[
        "tgn:7214819",
        "tgn:1000003",
        "tgn:7003677",
        "tgn:7000084",
        "tgn:7029392"
    ],
    "tgn:id":7214819,
    "tgn:name":"Blens",
    "tgn:placetype":[
        "aat:300008347"
    ]
},
  "bbox": [],
  "geometry": {"coordinates":[6.466667,50.65],"type":"Point"}
}