{
  "id": 7241382,
  "type": "Feature",
  "properties": {
    "tgn:hierarchy":[
        "tgn:7241382",
        "tgn:7003458",
        "tgn:1000003",
        "tgn:1000063",
        "tgn:7018236",
        "tgn:7029392"
    ],
    "tgn:id":7241382,
    "tgn:name":"Klarenhoek",
    "tgn:placetype":[
        "aat:300008347"
    ]
},
  "bbox": [],
  "geometry": {"coordinates":[3.222235,50.798858],"type":"Point"}
}