{
  "id": 7511997,
  "type": "Feature",
  "properties": {
    "tgn:hierarchy":[
        "tgn:7511997",
        "tgn:1008380",
        "tgn:1000226",
        "tgn:7016827",
        "tgn:1000006",
        "tgn:7029392"
    ],
    "tgn:id":7511997,
    "tgn:name:en":"Kaikokopu Stream",
    "tgn:placetype":[
        "aat:300008699"
    ]
},
  "bbox": [],
  "geometry": {"coordinates":[174.183333,-39.083333],"type":"Point"}
}