{
  "id": 7461916,
  "type": "Feature",
  "properties": {
    "tgn:hierarchy":[
        "tgn:7461916",
        "tgn:7002448",
        "tgn:7019217",
        "tgn:1000003",
        "tgn:7008591",
        "tgn:7029392"
    ],
    "tgn:id":7461916,
    "tgn:name:en":"Knockcloghrim",
    "tgn:placetype":[
        "aat:300008347"
    ]
},
  "bbox": [],
  "geometry": {"coordinates":[-6.616667,54.816667],"type":"Point"}
}