{
  "id": 1016934,
  "type": "Feature",
  "properties": {
    "tgn:hierarchy":[
        "tgn:1016934",
        "tgn:7005586",
        "tgn:1000001",
        "tgn:7005560",
        "tgn:7029392"
    ],
    "tgn:id":1016934,
    "tgn:name":"Acatl\u00e1n de Ju\u00e1rez",
    "tgn:placetype":[
        "aat:300008347"
    ]
},
  "bbox": [],
  "geometry": {"coordinates":[-103.583333,20.416667],"type":"Point"}
}