{
  "id": 2055776,
  "type": "Feature",
  "properties": {
    "tgn:hierarchy":[
        "tgn:2055776",
        "tgn:1000001",
        "tgn:7012149",
        "tgn:2001051",
        "tgn:7007521",
        "tgn:7029392"
    ],
    "tgn:id":2055776,
    "tgn:name":"Wilmont",
    "tgn:placetype":[
        "aat:300008347"
    ]
},
  "bbox": [],
  "geometry": {"coordinates":[-95.8167,43.75],"type":"Point"}
}