{
  "id": 1071858,
  "type": "Feature",
  "properties": {
    "tgn:hierarchy":[
        "tgn:1071858",
        "tgn:1000004",
        "tgn:7002087",
        "tgn:1000111",
        "tgn:7029392"
    ],
    "tgn:id":1071858,
    "tgn:name":"Shuikouchang",
    "tgn:placetype":[
        "aat:300008347"
    ]
},
  "bbox": [],
  "geometry": {"coordinates":[103.6667,29.55],"type":"Point"}
}