{
  "id": 7392019,
  "type": "Feature",
  "properties": {
    "tgn:hierarchy":[
        "tgn:7392019",
        "tgn:1000001",
        "tgn:1001960",
        "tgn:7005560",
        "tgn:7029392"
    ],
    "tgn:id":7392019,
    "tgn:name":"Rancho Los Alamitos",
    "tgn:placetype":[
        "aat:300008347"
    ]
},
  "bbox": [],
  "geometry": {"coordinates":[-112.783333,30.833333],"type":"Point"}
}