<<<<<<< HEAD
{
  "id": 2769018,
  "type": "Feature",
  "properties": {
    "tgn:hierarchy":[
        "tgn:2769018",
        "tgn:2000934",
        "tgn:1000001",
        "tgn:7012149",
        "tgn:7007516",
        "tgn:7029392"
    ],
    "tgn:id":2769018,
    "tgn:name":"Whittaker Ridge",
    "tgn:placetype":[
        "aat:300266640"
    ]
},
  "bbox": [],
  "geometry": {"coordinates":[-78.5333,39.6833],"type":"Point"}
}
=======
{"geometry":{"type":"Point","coordinates":[-78.533300,39.683300]},"type":"Feature","properties":{"hierarchy":["tgn:2769018","tgn:2000934","tgn:1000001","tgn:7012149","tgn:7007516","tgn:7029392"],"placetype":["aat:300266640"],"id":2769018,"name:xx":"Whittaker Ridge"}}
>>>>>>> 03f74aca74312dbeaf24d7e61306dd6a786dc3d0
