{
  "id": 7552339,
  "type": "Feature",
  "properties": {
    "tgn:hierarchy":[
        "tgn:7552339",
        "tgn:1000004",
        "tgn:1001869",
        "tgn:7000198",
        "tgn:7029392"
    ],
    "tgn:id":7552339,
    "tgn:name:en":"Moti Mori",
    "tgn:placetype":[
        "aat:300008347"
    ]
},
  "bbox": [],
  "geometry": {"coordinates":[73.606753,23.577294],"type":"Point"}
}