{
  "id": 7436089,
  "type": "Feature",
  "properties": {
    "tgn:hierarchy":[
        "tgn:7436089",
        "tgn:1000001",
        "tgn:7005599",
        "tgn:7005560",
        "tgn:7029392"
    ],
    "tgn:id":7436089,
    "tgn:name":"Santo Tom\u00e1s de las Lomas",
    "tgn:placetype":[
        "aat:300008347"
    ]
},
  "bbox": [],
  "geometry": {"coordinates":[-95.883333,18.333333],"type":"Point"}
}