{
  "id": 2516660,
  "type": "Feature",
  "properties": {
    "tgn:hierarchy":[
        "tgn:2516660",
        "tgn:1000001",
        "tgn:7012149",
        "tgn:7007157",
        "tgn:2000190",
        "tgn:7029392"
    ],
    "tgn:id":2516660,
    "tgn:name":"Mineral Summit",
    "tgn:placetype":[
        "aat:300008798"
    ]
},
  "bbox": [],
  "geometry": {"coordinates":[-121.5667,40.3167],"type":"Point"}
}