{
  "id": 7364972,
  "type": "Feature",
  "properties": {
    "tgn:hierarchy":[
        "tgn:7364972",
        "tgn:1000001",
        "tgn:1001960",
        "tgn:7005560",
        "tgn:7029392"
    ],
    "tgn:id":7364972,
    "tgn:name":"Rancho El Quemado",
    "tgn:placetype":[
        "aat:300000241"
    ]
},
  "bbox": [],
  "geometry": {"coordinates":[-108.566667,30.183333],"type":"Point"}
}