{
  "id": 7239088,
  "type": "Feature",
  "properties": {
    "tgn:hierarchy":[
        "tgn:7239088",
        "tgn:7003461",
        "tgn:1000003",
        "tgn:1000063",
        "tgn:7018236",
        "tgn:7029392"
    ],
    "tgn:id":7239088,
    "tgn:name":"Grootbeersel",
    "tgn:placetype":[
        "aat:300008347"
    ]
},
  "bbox": [],
  "geometry": {"coordinates":[5.766667,51.183333],"type":"Point"}
}