{
  "id": 2161076,
  "type": "Feature",
  "properties": {
    "tgn:hierarchy":[
        "tgn:2161076",
        "tgn:1000001",
        "tgn:7012149",
        "tgn:2001276",
        "tgn:7007524",
        "tgn:7029392"
    ],
    "tgn:id":2161076,
    "tgn:name":"Bell Coulee",
    "tgn:placetype":[
        "aat:300008761"
    ]
},
  "bbox": [],
  "geometry": {"coordinates":[-106.3333,47.65],"type":"Point"}
}