{
  "id": 7202999,
  "type": "Feature",
  "properties": {
    "tgn:hierarchy":[
        "tgn:7202999",
        "tgn:7003669",
        "tgn:1000003",
        "tgn:7000084",
        "tgn:7029392"
    ],
    "tgn:id":7202999,
    "tgn:name":"Boxbrunn",
    "tgn:placetype":[
        "aat:300008347"
    ]
},
  "bbox": [],
  "geometry": {"coordinates":[10.666667,49.266667],"type":"Point"}
}