{
  "id": 7195181,
  "type": "Feature",
  "properties": {
    "tgn:hierarchy":[
        "tgn:7195181",
        "tgn:1000003",
        "tgn:7003678",
        "tgn:7000084",
        "tgn:7029392"
    ],
    "tgn:id":7195181,
    "tgn:name":"Die Hardeck",
    "tgn:placetype":[
        "aat:300008777"
    ]
},
  "bbox": [],
  "geometry": {"coordinates":[9.066667,50.266667],"type":"Point"}
}