{
  "id": 7403573,
  "type": "Feature",
  "properties": {
    "tgn:hierarchy":[
        "tgn:7403573",
        "tgn:1000001",
        "tgn:1001906",
        "tgn:7005560",
        "tgn:7029392"
    ],
    "tgn:id":7403573,
    "tgn:name":"El Cuate",
    "tgn:placetype":[
        "aat:300008347"
    ]
},
  "bbox": [],
  "geometry": {"coordinates":[-104.275,21.279167],"type":"Point"}
}