{
  "id": 2382138,
  "type": "Feature",
  "properties": {
    "tgn:hierarchy":[
        "tgn:2382138",
        "tgn:1000001",
        "tgn:7012149",
        "tgn:2002342",
        "tgn:7007922",
        "tgn:7029392"
    ],
    "tgn:id":2382138,
    "tgn:name":"Haymeadow Creek",
    "tgn:placetype":[
        "aat:300008706"
    ]
},
  "bbox": [],
  "geometry": {"coordinates":[-89.1333,45.65],"type":"Point"}
}