{
  "id": 2185059,
  "type": "Feature",
  "properties": {
    "tgn:hierarchy":[
        "tgn:2185059",
        "tgn:1000001",
        "tgn:2000862",
        "tgn:7012149",
        "tgn:7007256",
        "tgn:7029392"
    ],
    "tgn:id":2185059,
    "tgn:name":"Boggy Bayou",
    "tgn:placetype":[
        "aat:300008699"
    ]
},
  "bbox": [],
  "geometry": {"coordinates":[-94.0333,32.3167],"type":"Point"}
}