{
  "id": 7487115,
  "type": "Feature",
  "properties": {
    "tgn:hierarchy":[
        "tgn:7487115",
        "tgn:1000004",
        "tgn:7004300",
        "tgn:1000141",
        "tgn:7029392"
    ],
    "tgn:id":7487115,
    "tgn:name":"Baikeng",
    "tgn:placetype":[
        "aat:300008347"
    ]
},
  "bbox": [],
  "geometry": {"coordinates":[119.657382,23.593907],"type":"Point"}
}