<<<<<<< HEAD
{
  "id": 2258000,
  "type": "Feature",
  "properties": {
    "tgn:hierarchy":[
        "tgn:2258000",
        "tgn:1000001",
        "tgn:7006451",
        "tgn:2000092",
        "tgn:7012149",
        "tgn:7029392"
    ],
    "tgn:id":2258000,
    "tgn:name":"Corva",
    "tgn:placetype":[
        "aat:300008347"
    ]
},
  "bbox": [],
  "geometry": {"coordinates":[-112.3333,35.2667],"type":"Point"}
}
=======
{"geometry":{"type":"Point","coordinates":[-112.333300,35.266700]},"type":"Feature","properties":{"hierarchy":["tgn:2258000","tgn:1000001","tgn:7006451","tgn:2000092","tgn:7012149","tgn:7029392"],"placetype":["aat:300008347"],"id":2258000,"name:xx":"Corva"}}
>>>>>>> 03f74aca74312dbeaf24d7e61306dd6a786dc3d0
