{
  "id": 2222247,
  "type": "Feature",
  "properties": {
    "tgn:hierarchy":[
        "tgn:2222247",
        "tgn:1000001",
        "tgn:7012149",
        "tgn:7029392"
    ],
    "tgn:id":2222247,
    "tgn:name":"Carolina Bar",
    "tgn:placetype":[
        "aat:300132348"
    ]
},
  "bbox": [],
  "geometry": {"coordinates":[-91.15,33.0167],"type":"Point"}
}