{
  "id": 2463992,
  "type": "Feature",
  "properties": {
    "tgn:hierarchy":[
        "tgn:2463992",
        "tgn:1000001",
        "tgn:7012149",
        "tgn:2000205",
        "tgn:7007158",
        "tgn:7029392"
    ],
    "tgn:id":2463992,
    "tgn:name":"Loco Hill",
    "tgn:placetype":[
        "aat:300008798"
    ]
},
  "bbox": [],
  "geometry": {"coordinates":[-105.4333,37.9167],"type":"Point"}
}