{
  "id": 7536262,
  "type": "Feature",
  "properties": {
    "tgn:hierarchy":[
        "tgn:7536262",
        "tgn:7001242",
        "tgn:7016833",
        "tgn:1001418",
        "tgn:7029392"
    ],
    "tgn:id":7536262,
    "tgn:name:en":"Khunfus, Jaz\u012brat al",
    "tgn:placetype":[
        "aat:300008791"
    ]
},
  "bbox": [],
  "geometry": {"coordinates":[27.916596,31.141227],"type":"Point"}
}