{
  "id": 2317732,
  "type": "Feature",
  "properties": {
    "tgn:hierarchy":[
        "tgn:2317732",
        "tgn:2002140",
        "tgn:1000001",
        "tgn:7012149",
        "tgn:7007919",
        "tgn:7029392"
    ],
    "tgn:id":2317732,
    "tgn:name":"England Ridge",
    "tgn:placetype":[
        "aat:300266640"
    ]
},
  "bbox": [],
  "geometry": {"coordinates":[-79.1167,37.7333],"type":"Point"}
}