{
  "id": 7031489,
  "type": "Feature",
  "properties": {
    "tgn:hierarchy":[
        "tgn:7031489",
        "tgn:7593972",
        "tgn:1000003",
        "tgn:7015657",
        "tgn:7029392"
    ],
    "tgn:id":7031489,
    "tgn:name:en":"Perast",
    "tgn:placetype":[
        "aat:300008347"
    ]
},
  "bbox": [],
  "geometry": {"coordinates":[18.694,42.486],"type":"Point"}
}