{
  "id": 2635768,
  "type": "Feature",
  "properties": {
    "tgn:hierarchy":[
        "tgn:2635768",
        "tgn:1000001",
        "tgn:7012149",
        "tgn:2002163",
        "tgn:7007919",
        "tgn:7029392"
    ],
    "tgn:id":2635768,
    "tgn:name":"Sabot Hill",
    "tgn:placetype":[
        "aat:300008798"
    ]
},
  "bbox": [],
  "geometry": {"coordinates":[-77.75,37.6167],"type":"Point"}
}