{
  "id": 7050788,
  "type": "Feature",
  "properties": {
    "tgn:hierarchy":[
        "tgn:7050788",
        "tgn:7003128",
        "tgn:1000003",
        "tgn:7008516",
        "tgn:1000080",
        "tgn:7029392"
    ],
    "tgn:id":7050788,
    "tgn:name":"Massenzatica",
    "tgn:placetype":[
        "aat:300008347"
    ]
},
  "bbox": [],
  "geometry": {"coordinates":[12.174167,44.927222],"type":"Point"}
}