<<<<<<< HEAD
{
  "id": 7023633,
  "type": "Feature",
  "properties": {
    "tgn:hierarchy":[
        "tgn:7023633",
        "tgn:1000001",
        "tgn:7006451",
        "tgn:7012149",
        "tgn:7029392"
    ],
    "tgn:id":7023633,
    "tgn:name":"Pan Quemado",
    "tgn:placetype":[
        "aat:300008798"
    ]
},
  "bbox": [],
  "geometry": {"coordinates":[-111.4,32.5],"type":"Point"}
}
=======
{"geometry":{"type":"Point","coordinates":[-111.400000,32.500000]},"type":"Feature","properties":{"hierarchy":["tgn:7023633","tgn:1000001","tgn:7006451","tgn:7012149","tgn:7029392"],"placetype":["aat:300008798"],"id":7023633,"name:xx":"Pan Quemado"}}
>>>>>>> 03f74aca74312dbeaf24d7e61306dd6a786dc3d0
