{
  "id": 2566059,
  "type": "Feature",
  "properties": {
    "tgn:hierarchy":[
        "tgn:2566059",
        "tgn:1000001",
        "tgn:7012149",
        "tgn:7007158",
        "tgn:2000250",
        "tgn:7029392"
    ],
    "tgn:id":2566059,
    "tgn:name":"Palmer Gulch",
    "tgn:placetype":[
        "aat:300008761"
    ]
},
  "bbox": [],
  "geometry": {"coordinates":[-106.1667,39.8333],"type":"Point"}
}