<<<<<<< HEAD
{
  "id": 7053377,
  "type": "Feature",
  "properties": {
    "tgn:hierarchy":[
        "tgn:7053377",
        "tgn:7003170",
        "tgn:1000003",
        "tgn:7003125",
        "tgn:1000080",
        "tgn:7029392"
    ],
    "tgn:id":7053377,
    "tgn:name":"Pozzo",
    "tgn:placetype":[
        "aat:300008347"
    ]
},
  "bbox": [],
  "geometry": {"coordinates":[12.5,42.9],"type":"Point"}
}
=======
{"geometry":{"type":"Point","coordinates":[12.500000,42.900000]},"type":"Feature","properties":{"hierarchy":["tgn:7053377","tgn:7003170","tgn:1000003","tgn:7003125","tgn:1000080","tgn:7029392"],"placetype":["aat:300008347"],"id":7053377,"name:xx":"Pozzo"}}
>>>>>>> 03f74aca74312dbeaf24d7e61306dd6a786dc3d0
