{
  "id": 2566700,
  "type": "Feature",
  "properties": {
    "tgn:hierarchy":[
        "tgn:2566700",
        "tgn:1000001",
        "tgn:7016172",
        "tgn:7012149",
        "tgn:2000149",
        "tgn:7029392"
    ],
    "tgn:id":2566700,
    "tgn:name":"Pannell Hollow",
    "tgn:placetype":[
        "aat:300008761"
    ]
},
  "bbox": [],
  "geometry": {"coordinates":[-92.7667,36.2667],"type":"Point"}
}