{
  "id": 2378208,
  "type": "Feature",
  "properties": {
    "tgn:hierarchy":[
        "tgn:2378208",
        "tgn:1000001",
        "tgn:7012149",
        "tgn:1002460",
        "tgn:7007826",
        "tgn:7029392"
    ],
    "tgn:id":2378208,
    "tgn:name":"Harris Lake",
    "tgn:placetype":[
        "aat:300006191"
    ]
},
  "bbox": [],
  "geometry": {"coordinates":[-94.3333,32.55],"type":"Point"}
}