{
  "id": 7213452,
  "type": "Feature",
  "properties": {
    "tgn:hierarchy":[
        "tgn:7213452",
        "tgn:7003669",
        "tgn:1000003",
        "tgn:7000084",
        "tgn:7029392"
    ],
    "tgn:id":7213452,
    "tgn:name":"B\u00f6bing",
    "tgn:placetype":[
        "aat:300008347"
    ]
},
  "bbox": [],
  "geometry": {"coordinates":[10.983333,47.75],"type":"Point"}
}