{
  "id": 7120480,
  "type": "Feature",
  "properties": {
    "tgn:hierarchy":[
        "tgn:7120480",
        "tgn:7003669",
        "tgn:1000003",
        "tgn:7000084",
        "tgn:7029392"
    ],
    "tgn:id":7120480,
    "tgn:name":"Plattenh\u00f6h",
    "tgn:placetype":[
        "aat:300000206"
    ]
},
  "bbox": [],
  "geometry": {"coordinates":[12.566667,49.25],"type":"Point"}
}