{
  "id": 7586294,
  "type": "Feature",
  "properties": {
    "tgn:hierarchy":[
        "tgn:7586294",
        "tgn:1000004",
        "tgn:7000198",
        "tgn:7000799",
        "tgn:7029392"
    ],
    "tgn:id":7586294,
    "tgn:name:en":"Sadganga",
    "tgn:placetype":[
        "aat:300008347"
    ]
},
  "bbox": [],
  "geometry": {"coordinates":[74.351418,34.440124],"type":"Point"}
}