{
  "id": 2626195,
  "type": "Feature",
  "properties": {
    "tgn:hierarchy":[
        "tgn:2626195",
        "tgn:1000001",
        "tgn:7012149",
        "tgn:1002431",
        "tgn:7007826",
        "tgn:7029392"
    ],
    "tgn:id":2626195,
    "tgn:name":"Rocky Creek",
    "tgn:placetype":[
        "aat:300008706"
    ]
},
  "bbox": [],
  "geometry": {"coordinates":[-97.8333,29.4833],"type":"Point"}
}