{
  "id": 1127399,
  "type": "Feature",
  "properties": {
    "tgn:hierarchy":[
        "tgn:1127399",
        "tgn:7001181",
        "tgn:1000003",
        "tgn:1009896",
        "tgn:7029392"
    ],
    "tgn:id":1127399,
    "tgn:name":"Mourne Beg River",
    "tgn:placetype":[
        "aat:300008707"
    ]
},
  "bbox": [],
  "geometry": {"coordinates":[-7.65,54.6833],"type":"Point"}
}