{
  "id": 2712050,
  "type": "Feature",
  "properties": {
    "tgn:hierarchy":[
        "tgn:2712050",
        "tgn:1000001",
        "tgn:7012149",
        "tgn:2001607",
        "tgn:7007705",
        "tgn:7029392"
    ],
    "tgn:id":2712050,
    "tgn:name":"Taskers Coulee",
    "tgn:placetype":[
        "aat:300008761"
    ]
},
  "bbox": [],
  "geometry": {"coordinates":[-102.15,48.6333],"type":"Point"}
}