{
  "id": 1117343,
  "type": "Feature",
  "properties": {
    "tgn:hierarchy":[
        "tgn:1117343",
        "tgn:7005685",
        "tgn:1000001",
        "tgn:7013154",
        "tgn:7029392"
    ],
    "tgn:id":1117343,
    "tgn:name":"Moira Lake",
    "tgn:placetype":[
        "aat:300008680"
    ]
},
  "bbox": [],
  "geometry": {"coordinates":[-77.45,44.4833],"type":"Point"}
}