{
  "id": 2655365,
  "type": "Feature",
  "properties": {
    "tgn:hierarchy":[
        "tgn:2655365",
        "tgn:1000001",
        "tgn:7012149",
        "tgn:2000906",
        "tgn:7007256",
        "tgn:7029392"
    ],
    "tgn:id":2655365,
    "tgn:name":"Sharkey",
    "tgn:placetype":[
        "aat:300008347"
    ]
},
  "bbox": [],
  "geometry": {"coordinates":[-90.4167,30.3667],"type":"Point"}
}