<<<<<<< HEAD
{
  "id": 2761411,
  "type": "Feature",
  "properties": {
    "tgn:hierarchy":[
        "tgn:2761411",
        "tgn:1000001",
        "tgn:7012149",
        "tgn:7013941",
        "tgn:7007568",
        "tgn:7029392"
    ],
    "tgn:id":2761411,
    "tgn:name":"West Mountain",
    "tgn:placetype":[
        "aat:300008798"
    ]
},
  "bbox": [],
  "geometry": {"coordinates":[-74.55,44.5167],"type":"Point"}
}
=======
{"geometry":{"type":"Point","coordinates":[-74.550000,44.516700]},"type":"Feature","properties":{"hierarchy":["tgn:2761411","tgn:1000001","tgn:7012149","tgn:7013941","tgn:7007568","tgn:7029392"],"placetype":["aat:300008798"],"id":2761411,"name:xx":"West Mountain"}}
>>>>>>> 03f74aca74312dbeaf24d7e61306dd6a786dc3d0
