{
  "id": 2761411,
  "type": "Feature",
  "properties": {
    "tgn:hierarchy":[
        "tgn:2761411",
        "tgn:1000001",
        "tgn:7012149",
        "tgn:7013941",
        "tgn:7007568",
        "tgn:7029392"
    ],
    "tgn:id":2761411,
    "tgn:name":"West Mountain",
    "tgn:placetype":[
        "aat:300008798"
    ]
},
  "bbox": [],
  "geometry": {"coordinates":[-74.55,44.5167],"type":"Point"}
}