{
  "id": 2072139,
  "type": "Feature",
  "properties": {
    "tgn:hierarchy":[
        "tgn:2072139",
        "tgn:1000001",
        "tgn:1002206",
        "tgn:7012149",
        "tgn:7007568",
        "tgn:7029392"
    ],
    "tgn:id":2072139,
    "tgn:name":"Sanitaria Springs",
    "tgn:placetype":[
        "aat:300008347"
    ]
},
  "bbox": [],
  "geometry": {"coordinates":[-75.75,42.15],"type":"Point"}
}