<<<<<<< HEAD
{
  "id": 7111298,
  "type": "Feature",
  "properties": {
    "tgn:hierarchy":[
        "tgn:7111298",
        "tgn:1000003",
        "tgn:7000094",
        "tgn:7000084",
        "tgn:7029392"
    ],
    "tgn:id":7111298,
    "tgn:name":"Remlin",
    "tgn:placetype":[
        "aat:300008347"
    ]
},
  "bbox": [],
  "geometry": {"coordinates":[12.666667,53.916667],"type":"Point"}
}
=======
{"geometry":{"type":"Point","coordinates":[12.666667,53.916667]},"type":"Feature","properties":{"hierarchy":["tgn:7111298","tgn:1000003","tgn:7000094","tgn:7000084","tgn:7029392"],"placetype":["aat:300008347"],"id":7111298,"name:xx":"Remlin"}}
>>>>>>> 03f74aca74312dbeaf24d7e61306dd6a786dc3d0
