{
  "id": 1019001,
  "type": "Feature",
  "properties": {
    "tgn:hierarchy":[
        "tgn:1019001",
        "tgn:7017440",
        "tgn:1000001",
        "tgn:7004643",
        "tgn:7029392"
    ],
    "tgn:id":1019001,
    "tgn:name":"Pastillo",
    "tgn:placetype":[
        "aat:300008347"
    ]
},
  "bbox": [],
  "geometry": {"coordinates":[-66.4833,17.9833],"type":"Point"}
}