{
  "id": 1056054,
  "type": "Feature",
  "properties": {
    "tgn:hierarchy":[
        "tgn:1056054",
        "tgn:7006636",
        "tgn:1000003",
        "tgn:7006540",
        "tgn:7029392"
    ],
    "tgn:id":1056054,
    "tgn:name:en":"Kullamaa",
    "tgn:placetype":[
        "aat:300008347"
    ]
},
  "bbox": [],
  "geometry": {"coordinates":[24.067,58.878],"type":"Point"}
}