{
  "id": 7412662,
  "type": "Feature",
  "properties": {
    "tgn:hierarchy":[
        "tgn:7412662",
        "tgn:7005587",
        "tgn:1000001",
        "tgn:7005560",
        "tgn:7029392"
    ],
    "tgn:id":7412662,
    "tgn:name:es":"Ocampo",
    "tgn:placetype":[
        "aat:300008347"
    ]
},
  "bbox": [],
  "geometry": {"coordinates":[-99.236111,20.058333],"type":"Point"}
}