<<<<<<< HEAD
{
  "id": 2255031,
  "type": "Feature",
  "properties": {
    "tgn:hierarchy":[
        "tgn:2255031",
        "tgn:1000001",
        "tgn:7012149",
        "tgn:2000911",
        "tgn:7007256",
        "tgn:7029392"
    ],
    "tgn:id":2255031,
    "tgn:name":"Cooper Creek",
    "tgn:placetype":[
        "aat:300008706"
    ]
},
  "bbox": [],
  "geometry": {"coordinates":[-93.15,31.1667],"type":"Point"}
}
=======
{"geometry":{"type":"Point","coordinates":[-93.150000,31.166700]},"type":"Feature","properties":{"hierarchy":["tgn:2255031","tgn:1000001","tgn:7012149","tgn:2000911","tgn:7007256","tgn:7029392"],"placetype":["aat:300008706"],"id":2255031,"name:xx":"Cooper Creek"}}
>>>>>>> 03f74aca74312dbeaf24d7e61306dd6a786dc3d0
