{
  "id": 2074128,
  "type": "Feature",
  "properties": {
    "tgn:hierarchy":[
        "tgn:2074128",
        "tgn:1000001",
        "tgn:2001471",
        "tgn:7012149",
        "tgn:7007709",
        "tgn:7029392"
    ],
    "tgn:id":2074128,
    "tgn:name":"Clarkton",
    "tgn:placetype":[
        "aat:300008347"
    ]
},
  "bbox": [],
  "geometry": {"coordinates":[-78.65,34.4833],"type":"Point"}
}