<<<<<<< HEAD
{
  "id": 7112403,
  "type": "Feature",
  "properties": {
    "tgn:hierarchy":[
        "tgn:7112403",
        "tgn:1000003",
        "tgn:7003677",
        "tgn:7000084",
        "tgn:7029392"
    ],
    "tgn:id":7112403,
    "tgn:name":"Rheder Bach",
    "tgn:placetype":[
        "aat:300008699"
    ]
},
  "bbox": [],
  "geometry": {"coordinates":[6.666667,51.816667],"type":"Point"}
}
=======
{"geometry":{"type":"Point","coordinates":[6.666667,51.816667]},"type":"Feature","properties":{"hierarchy":["tgn:7112403","tgn:1000003","tgn:7003677","tgn:7000084","tgn:7029392"],"placetype":["aat:300008699"],"id":7112403,"name:xx":"Rheder Bach"}}
>>>>>>> 03f74aca74312dbeaf24d7e61306dd6a786dc3d0
