{
  "id": 2771638,
  "type": "Feature",
  "properties": {
    "tgn:hierarchy":[
        "tgn:2771638",
        "tgn:1002232",
        "tgn:1000001",
        "tgn:7012149",
        "tgn:7007565",
        "tgn:7029392"
    ],
    "tgn:id":2771638,
    "tgn:name":"Wildwood Junction",
    "tgn:placetype":[
        "aat:300008347"
    ]
},
  "bbox": [],
  "geometry": {"coordinates":[-74.85,39.0167],"type":"Point"}
}