{
  "id": 2034457,
  "type": "Feature",
  "properties": {
    "tgn:hierarchy":[
        "tgn:2034457",
        "tgn:1000001",
        "tgn:2000577",
        "tgn:7012149",
        "tgn:7007253",
        "tgn:7029392"
    ],
    "tgn:id":2034457,
    "tgn:name":"Cartersville",
    "tgn:placetype":[
        "aat:300008347",
        "aat:300387210"
    ]
},
  "bbox": [],
  "geometry": {"coordinates":[-93.0667,42.9833],"type":"Point"}
}