{
  "id": 7027894,
  "type": "Feature",
  "properties": {
    "tgn:hierarchy":[
        "tgn:7027894",
        "tgn:7002445",
        "tgn:1000003",
        "tgn:7008157",
        "tgn:7008591",
        "tgn:7029392"
    ],
    "tgn:id":7027894,
    "tgn:name":"Great Steeping",
    "tgn:placetype":[
        "aat:300008347",
        "aat:300008372"
    ]
},
  "bbox": [],
  "geometry": {"coordinates":[0.1667,53.15],"type":"Point"}
}