{
  "id": 1114355,
  "type": "Feature",
  "properties": {
    "tgn:hierarchy":[
        "tgn:1114355",
        "tgn:7594021",
        "tgn:1000003",
        "tgn:1000077",
        "tgn:7029392"
    ],
    "tgn:id":1114355,
    "tgn:name":"Arnarfj\u00f6r\u00f0ur",
    "tgn:placetype":[
        "aat:300008676"
    ]
},
  "bbox": [],
  "geometry": {"coordinates":[-23.6667,65.75],"type":"Point"}
}