<<<<<<< HEAD
{
  "id": 2405149,
  "type": "Feature",
  "properties": {
    "tgn:hierarchy":[
        "tgn:2405149",
        "tgn:1000001",
        "tgn:7012149",
        "tgn:7007157",
        "tgn:1002972",
        "tgn:7029392"
    ],
    "tgn:id":2405149,
    "tgn:name":"Hueneme Canyon",
    "tgn:placetype":[
        "aat:300008761"
    ]
},
  "bbox": [],
  "geometry": {"coordinates":[-119.05,34.1],"type":"Point"}
}
=======
{"geometry":{"type":"Point","coordinates":[-119.050000,34.100000]},"type":"Feature","properties":{"hierarchy":["tgn:2405149","tgn:1000001","tgn:7012149","tgn:7007157","tgn:1002972","tgn:7029392"],"placetype":["aat:300008761"],"id":2405149,"name:xx":"Hueneme Canyon"}}
>>>>>>> 03f74aca74312dbeaf24d7e61306dd6a786dc3d0
