{
  "id": 7426627,
  "type": "Feature",
  "properties": {
    "tgn:hierarchy":[
        "tgn:7426627",
        "tgn:7005581",
        "tgn:1000001",
        "tgn:7005560",
        "tgn:7029392"
    ],
    "tgn:id":7426627,
    "tgn:name":"Los Sauces",
    "tgn:placetype":[
        "aat:300008347"
    ]
},
  "bbox": [],
  "geometry": {"coordinates":[-107.733333,31.566667],"type":"Point"}
}