{
  "id": 7403687,
  "type": "Feature",
  "properties": {
    "tgn:hierarchy":[
        "tgn:7403687",
        "tgn:1000001",
        "tgn:1001906",
        "tgn:7005560",
        "tgn:7029392"
    ],
    "tgn:id":7403687,
    "tgn:name":"Los Baj\u00edos",
    "tgn:placetype":[
        "aat:300008347"
    ]
},
  "bbox": [],
  "geometry": {"coordinates":[-104.358333,21.608333],"type":"Point"}
}