{
  "id": 7531816,
  "type": "Feature",
  "properties": {
    "tgn:hierarchy":[
        "tgn:7531816",
        "tgn:7001242",
        "tgn:7016833",
        "tgn:1001123",
        "tgn:7029392"
    ],
    "tgn:id":7531816,
    "tgn:name":"Manzalah, Fumm Bu\u1e29ayrat al",
    "tgn:placetype":[
        "aat:300266556"
    ]
},
  "bbox": [],
  "geometry": {"coordinates":[32.228889,31.271389],"type":"Point"}
}