{
  "id": 2232803,
  "type": "Feature",
  "properties": {
    "tgn:hierarchy":[
        "tgn:2232803",
        "tgn:1000001",
        "tgn:7012149",
        "tgn:2001711",
        "tgn:7007708",
        "tgn:7029392"
    ],
    "tgn:id":2232803,
    "tgn:name":"Chapman Lake",
    "tgn:placetype":[
        "aat:300008680"
    ]
},
  "bbox": [],
  "geometry": {"coordinates":[-122.5667,42.1833],"type":"Point"}
}