{
  "id": 7250244,
  "type": "Feature",
  "properties": {
    "tgn:hierarchy":[
        "tgn:7250244",
        "tgn:7003460",
        "tgn:1000003",
        "tgn:1000063",
        "tgn:4012014",
        "tgn:7029392"
    ],
    "tgn:id":7250244,
    "tgn:name":"Ober-Emmels",
    "tgn:placetype":[
        "aat:300008347"
    ]
},
  "bbox": [],
  "geometry": {"coordinates":[6.089167,50.299167],"type":"Point"}
}