{
  "id": 7304130,
  "type": "Feature",
  "properties": {
    "tgn:hierarchy":[
        "tgn:7304130",
        "tgn:7002806",
        "tgn:7001158",
        "tgn:1000003",
        "tgn:1000095",
        "tgn:7029392"
    ],
    "tgn:id":7304130,
    "tgn:name":"Narrillos del \u00c1lamo",
    "tgn:placetype":[
        "aat:300008347"
    ]
},
  "bbox": [],
  "geometry": {"coordinates":[-5.466667,40.566667],"type":"Point"}
}