{
  "id": 7220242,
  "type": "Feature",
  "properties": {
    "tgn:hierarchy":[
        "tgn:7220242",
        "tgn:7011330",
        "tgn:7002674",
        "tgn:1000003",
        "tgn:1000074",
        "tgn:7029392"
    ],
    "tgn:id":7220242,
    "tgn:name":"Kam\u00e1ra, \u00c1kra",
    "tgn:placetype":[
        "aat:300386846"
    ]
},
  "bbox": [],
  "geometry": {"coordinates":[27.334167,36.420833],"type":"Point"}
}