{
  "id": 2146835,
  "type": "Feature",
  "properties": {
    "tgn:hierarchy":[
        "tgn:2146835",
        "tgn:1000001",
        "tgn:7012149",
        "tgn:2000486",
        "tgn:7007250",
        "tgn:7029392"
    ],
    "tgn:id":2146835,
    "tgn:name":"Banks Creek",
    "tgn:placetype":[
        "aat:300008706"
    ]
},
  "bbox": [],
  "geometry": {"coordinates":[-116.7667,46.0167],"type":"Point"}
}