{
  "id": 2078260,
  "type": "Feature",
  "properties": {
    "tgn:hierarchy":[
        "tgn:2078260",
        "tgn:1000001",
        "tgn:1002210",
        "tgn:7012149",
        "tgn:7007706",
        "tgn:7029392"
    ],
    "tgn:id":2078260,
    "tgn:name":"Arnheim",
    "tgn:placetype":[
        "aat:300008347"
    ]
},
  "bbox": [],
  "geometry": {"coordinates":[-83.8167,38.9333],"type":"Point"}
}