{
  "id": 7177301,
  "type": "Feature",
  "properties": {
    "tgn:hierarchy":[
        "tgn:7177301",
        "tgn:1000003",
        "tgn:7003676",
        "tgn:7000084",
        "tgn:7029392"
    ],
    "tgn:id":7177301,
    "tgn:name":"Harbarnsen",
    "tgn:placetype":[
        "aat:300008347"
    ]
},
  "bbox": [],
  "geometry": {"coordinates":[9.966667,51.983333],"type":"Point"}
}