<<<<<<< HEAD
{
  "id": 7177301,
  "type": "Feature",
  "properties": {
    "tgn:hierarchy":[
        "tgn:7177301",
        "tgn:1000003",
        "tgn:7003676",
        "tgn:7000084",
        "tgn:7029392"
    ],
    "tgn:id":7177301,
    "tgn:name":"Harbarnsen",
    "tgn:placetype":[
        "aat:300008347"
    ]
},
  "bbox": [],
  "geometry": {"coordinates":[9.966667,51.983333],"type":"Point"}
}
=======
{"geometry":{"type":"Point","coordinates":[9.966667,51.983333]},"type":"Feature","properties":{"hierarchy":["tgn:7177301","tgn:1000003","tgn:7003676","tgn:7000084","tgn:7029392"],"placetype":["aat:300008347"],"id":7177301,"name:xx":"Harbarnsen"}}
>>>>>>> 03f74aca74312dbeaf24d7e61306dd6a786dc3d0
