{
  "id": 7257814,
  "type": "Feature",
  "properties": {
    "tgn:hierarchy":[
        "tgn:7257814",
        "tgn:1000003",
        "tgn:7003632",
        "tgn:7016845",
        "tgn:7029392"
    ],
    "tgn:id":7257814,
    "tgn:name:nl":"Aardbeiendel",
    "tgn:placetype":[
        "aat:300008187"
    ]
},
  "bbox": [],
  "geometry": {"coordinates":[4.483333,52.283333],"type":"Point"}
}