{
  "id": 7568947,
  "type": "Feature",
  "properties": {
    "tgn:hierarchy":[
        "tgn:7568947",
        "tgn:1000004",
        "tgn:7000198",
        "tgn:7016788",
        "tgn:7029392"
    ],
    "tgn:id":7568947,
    "tgn:name:en":"Umarth\u016bna",
    "tgn:placetype":[
        "aat:300008347"
    ]
},
  "bbox": [],
  "geometry": {"coordinates":[75.522197,25.398851],"type":"Point"}
}