{
  "id": 2688888,
  "type": "Feature",
  "properties": {
    "tgn:hierarchy":[
        "tgn:2688888",
        "tgn:1000001",
        "tgn:2000782",
        "tgn:7012149",
        "tgn:7007255",
        "tgn:7029392"
    ],
    "tgn:id":2688888,
    "tgn:name":"Spurlock Fork",
    "tgn:placetype":[
        "aat:300008699"
    ]
},
  "bbox": [],
  "geometry": {"coordinates":[-83.5667,37.2167],"type":"Point"}
}