{
  "id": 7269429,
  "type": "Feature",
  "properties": {
    "tgn:hierarchy":[
        "tgn:7269429",
        "tgn:1000003",
        "tgn:7003632",
        "tgn:7016845",
        "tgn:7029392"
    ],
    "tgn:id":7269429,
    "tgn:name:nl":"Putte, Polder de",
    "tgn:placetype":[
        "aat:300006163"
    ]
},
  "bbox": [],
  "geometry": {"coordinates":[4.65,52.066667],"type":"Point"}
}