{
  "id": 2662925,
  "type": "Feature",
  "properties": {
    "tgn:hierarchy":[
        "tgn:2662925",
        "tgn:2002131",
        "tgn:1000001",
        "tgn:7012149",
        "tgn:7007828",
        "tgn:7029392"
    ],
    "tgn:id":2662925,
    "tgn:name":"Silsby Mountain",
    "tgn:placetype":[
        "aat:300008798"
    ]
},
  "bbox": [],
  "geometry": {"coordinates":[-71.9833,44.3667],"type":"Point"}
}