{
  "id": 1017707,
  "type": "Feature",
  "properties": {
    "tgn:hierarchy":[
        "tgn:1017707",
        "tgn:1001853",
        "tgn:1000001",
        "tgn:7005560",
        "tgn:7029392"
    ],
    "tgn:id":1017707,
    "tgn:name":"La Mancha",
    "tgn:placetype":[
        "aat:300008347"
    ]
},
  "bbox": [],
  "geometry": {"coordinates":[-102.85,24.8333],"type":"Point"}
}