{
  "id": 7545879,
  "type": "Feature",
  "properties": {
    "tgn:hierarchy":[
        "tgn:7545879",
        "tgn:1001828",
        "tgn:1000004",
        "tgn:7000198",
        "tgn:7029392"
    ],
    "tgn:id":7545879,
    "tgn:name:en":"B\u0101sar",
    "tgn:placetype":[
        "aat:300008347"
    ]
},
  "bbox": [],
  "geometry": {"coordinates":[77.966667,18.883333],"type":"Point"}
}