{
  "id": 2479005,
  "type": "Feature",
  "properties": {
    "tgn:hierarchy":[
        "tgn:2479005",
        "tgn:7002659",
        "tgn:1000001",
        "tgn:7012149",
        "tgn:2000030",
        "tgn:7029392"
    ],
    "tgn:id":2479005,
    "tgn:name":"Laddon Creek",
    "tgn:placetype":[
        "aat:300008706"
    ]
},
  "bbox": [],
  "geometry": {"coordinates":[-85.9333,31.0667],"type":"Point"}
}