{
  "id": 7305479,
  "type": "Feature",
  "properties": {
    "tgn:hierarchy":[
        "tgn:7305479",
        "tgn:7002811",
        "tgn:1000003",
        "tgn:7003837",
        "tgn:1000095",
        "tgn:7029392"
    ],
    "tgn:id":7305479,
    "tgn:name":"Las Mestas",
    "tgn:placetype":[
        "aat:300008347"
    ]
},
  "bbox": [],
  "geometry": {"coordinates":[-6.133333,40.416667],"type":"Point"}
}