{
  "id": 2118406,
  "type": "Feature",
  "properties": {
    "tgn:hierarchy":[
        "tgn:2118406",
        "tgn:1000001",
        "tgn:7012149",
        "tgn:2002278",
        "tgn:7013961",
        "tgn:7029392"
    ],
    "tgn:id":2118406,
    "tgn:name":"Glenwood",
    "tgn:placetype":[
        "aat:300008347"
    ]
},
  "bbox": [],
  "geometry": {"coordinates":[-81.1333,37.3333],"type":"Point"}
}