{
  "id": 7163006,
  "type": "Feature",
  "properties": {
    "tgn:hierarchy":[
        "tgn:7163006",
        "tgn:7003669",
        "tgn:1000003",
        "tgn:7000084",
        "tgn:7029392"
    ],
    "tgn:id":7163006,
    "tgn:name":"H\u00fchner Berg",
    "tgn:placetype":[
        "aat:300008777"
    ]
},
  "bbox": [],
  "geometry": {"coordinates":[10.95,50.233333],"type":"Point"}
}