{
  "id": 2565647,
  "type": "Feature",
  "properties": {
    "tgn:hierarchy":[
        "tgn:2565647",
        "tgn:1000001",
        "tgn:7006451",
        "tgn:7012149",
        "tgn:2000102",
        "tgn:7029392"
    ],
    "tgn:id":2565647,
    "tgn:name":"Pajarito Peak",
    "tgn:placetype":[
        "aat:300008798"
    ]
},
  "bbox": [],
  "geometry": {"coordinates":[-111.0833,31.35],"type":"Point"}
}