{
  "id": 2668772,
  "type": "Feature",
  "properties": {
    "tgn:hierarchy":[
        "tgn:2668772",
        "tgn:1000001",
        "tgn:7012149",
        "tgn:2001994",
        "tgn:7007826",
        "tgn:7029392"
    ],
    "tgn:id":2668772,
    "tgn:name":"Slaton Draw",
    "tgn:placetype":[
        "aat:300008761"
    ]
},
  "bbox": [],
  "geometry": {"coordinates":[-101.8167,34.25],"type":"Point"}
}