{
  "id": 2472740,
  "type": "Feature",
  "properties": {
    "tgn:hierarchy":[
        "tgn:2472740",
        "tgn:1000001",
        "tgn:7012149",
        "tgn:2001722",
        "tgn:7007708",
        "tgn:7029392"
    ],
    "tgn:id":2472740,
    "tgn:name":"Lovely",
    "tgn:placetype":[
        "aat:300008347"
    ]
},
  "bbox": [],
  "geometry": {"coordinates":[-117.6667,45.6333],"type":"Point"}
}