{
  "id": 1022257,
  "type": "Feature",
  "properties": {
    "tgn:hierarchy":[
        "tgn:1022257",
        "tgn:1001945",
        "tgn:1000047",
        "tgn:7002457",
        "tgn:1000002",
        "tgn:7029392"
    ],
    "tgn:id":1022257,
    "tgn:name":"Ol\u00edmpia",
    "tgn:placetype":[
        "aat:300008347"
    ]
},
  "bbox": [],
  "geometry": {"coordinates":[-48.9167,-20.7167],"type":"Point"}
}