<<<<<<< HEAD
{
  "id": 2764520,
  "type": "Feature",
  "properties": {
    "tgn:hierarchy":[
        "tgn:2764520",
        "tgn:1000001",
        "tgn:7012149",
        "tgn:2000983",
        "tgn:7007520",
        "tgn:7029392"
    ],
    "tgn:id":2764520,
    "tgn:name":"Whipple Creek",
    "tgn:placetype":[
        "aat:300008706"
    ]
},
  "bbox": [],
  "geometry": {"coordinates":[-85.6833,43.7667],"type":"Point"}
}
=======
{"geometry":{"type":"Point","coordinates":[-85.683300,43.766700]},"type":"Feature","properties":{"hierarchy":["tgn:2764520","tgn:1000001","tgn:7012149","tgn:2000983","tgn:7007520","tgn:7029392"],"placetype":["aat:300008706"],"id":2764520,"name:xx":"Whipple Creek"}}
>>>>>>> 03f74aca74312dbeaf24d7e61306dd6a786dc3d0
