{
  "id": 7560219,
  "type": "Feature",
  "properties": {
    "tgn:hierarchy":[
        "tgn:7560219",
        "tgn:1000004",
        "tgn:7000198",
        "tgn:7016722",
        "tgn:7029392"
    ],
    "tgn:id":7560219,
    "tgn:name:en":"Hazratpur",
    "tgn:placetype":[
        "aat:300008347"
    ]
},
  "bbox": [],
  "geometry": {"coordinates":[79.016506,26.832827],"type":"Point"}
}