{
  "id": 2741313,
  "type": "Feature",
  "properties": {
    "tgn:hierarchy":[
        "tgn:2741313",
        "tgn:1000001",
        "tgn:7012149",
        "tgn:1002999",
        "tgn:7007526",
        "tgn:7029392"
    ],
    "tgn:id":2741313,
    "tgn:name":"Upper Wildcat Spring",
    "tgn:placetype":[
        "aat:300008697"
    ]
},
  "bbox": [],
  "geometry": {"coordinates":[-119.85,39.9667],"type":"Point"}
}