<<<<<<< HEAD
{
  "id": 7477570,
  "type": "Feature",
  "properties": {
    "tgn:hierarchy":[
        "tgn:7477570",
        "tgn:1000004",
        "tgn:1000454",
        "tgn:1000141",
        "tgn:7029392"
    ],
    "tgn:id":7477570,
    "tgn:name":"Sanhao Suidao",
    "tgn:placetype":[
        "aat:300007899"
    ]
},
  "bbox": [],
  "geometry": {"coordinates":[121.816457,25.05771],"type":"Point"}
}
=======
{"geometry":{"type":"Point","coordinates":[121.816457,25.057710]},"type":"Feature","properties":{"hierarchy":["tgn:7477570","tgn:1000004","tgn:1000454","tgn:1000141","tgn:7029392"],"placetype":["aat:300007899"],"id":7477570,"name:xx":"Sanhao Suidao"}}
>>>>>>> 03f74aca74312dbeaf24d7e61306dd6a786dc3d0
