{
  "id": 7477570,
  "type": "Feature",
  "properties": {
    "tgn:hierarchy":[
        "tgn:7477570",
        "tgn:1000004",
        "tgn:1000454",
        "tgn:1000141",
        "tgn:7029392"
    ],
    "tgn:id":7477570,
    "tgn:name":"Sanhao Suidao",
    "tgn:placetype":[
        "aat:300007899"
    ]
},
  "bbox": [],
  "geometry": {"coordinates":[121.816457,25.05771],"type":"Point"}
}