{
  "id": 7473591,
  "type": "Feature",
  "properties": {
    "tgn:hierarchy":[
        "tgn:7473591",
        "tgn:1000004",
        "tgn:7467799",
        "tgn:1000141",
        "tgn:7029392"
    ],
    "tgn:id":7473591,
    "tgn:name":"Dongshiliao",
    "tgn:placetype":[
        "aat:300008347"
    ]
},
  "bbox": [],
  "geometry": {"coordinates":[120.45,24.055833],"type":"Point"}
}