{
  "id": 7551684,
  "type": "Feature",
  "properties": {
    "tgn:hierarchy":[
        "tgn:7551684",
        "tgn:1000004",
        "tgn:1001832",
        "tgn:7000198",
        "tgn:7029392"
    ],
    "tgn:id":7551684,
    "tgn:name:en":"Bor Dikrai Nad\u012b",
    "tgn:placetype":[
        "aat:300008699"
    ]
},
  "bbox": [],
  "geometry": {"coordinates":[92.867557,26.833516],"type":"Point"}
}