{
  "id": 2421993,
  "type": "Feature",
  "properties": {
    "tgn:hierarchy":[
        "tgn:2421993",
        "tgn:1000001",
        "tgn:7012149",
        "tgn:2001398",
        "tgn:7007525",
        "tgn:7029392"
    ],
    "tgn:id":2421993,
    "tgn:name":"Jim Creek",
    "tgn:placetype":[
        "aat:300008706"
    ]
},
  "bbox": [],
  "geometry": {"coordinates":[-103.6333,42.7833],"type":"Point"}
}