{
  "id": 7280681,
  "type": "Feature",
  "properties": {
    "tgn:hierarchy":[
        "tgn:7280681",
        "tgn:1001623",
        "tgn:1000049",
        "tgn:1000002",
        "tgn:7029392"
    ],
    "tgn:id":7280681,
    "tgn:name":"San Jos\u00e9, Isla",
    "tgn:placetype":[
        "aat:300008791"
    ]
},
  "bbox": [],
  "geometry": {"coordinates":[-73.916667,-46.116667],"type":"Point"}
}