<<<<<<< HEAD
{
  "id": 7247274,
  "type": "Feature",
  "properties": {
    "tgn:hierarchy":[
        "tgn:7247274",
        "tgn:7003457",
        "tgn:1000003",
        "tgn:1000063",
        "tgn:7018236",
        "tgn:7029392"
    ],
    "tgn:id":7247274,
    "tgn:name":"Dasselt",
    "tgn:placetype":[
        "aat:300008347"
    ]
},
  "bbox": [],
  "geometry": {"coordinates":[4.025116,50.791167],"type":"Point"}
}
=======
{"geometry":{"type":"Point","coordinates":[4.025116,50.791167]},"type":"Feature","properties":{"hierarchy":["tgn:7247274","tgn:7003457","tgn:1000003","tgn:1000063","tgn:7018236","tgn:7029392"],"placetype":["aat:300008347"],"id":7247274,"name:xx":"Dasselt"}}
>>>>>>> 03f74aca74312dbeaf24d7e61306dd6a786dc3d0
