{
  "id": 7175126,
  "type": "Feature",
  "properties": {
    "tgn:hierarchy":[
        "tgn:7175126",
        "tgn:7003669",
        "tgn:1000003",
        "tgn:7000084",
        "tgn:7029392"
    ],
    "tgn:id":7175126,
    "tgn:name":"Grub",
    "tgn:placetype":[
        "aat:300008347"
    ]
},
  "bbox": [],
  "geometry": {"coordinates":[11.783333,48.166667],"type":"Point"}
}