{
  "id": 2382120,
  "type": "Feature",
  "properties": {
    "tgn:hierarchy":[
        "tgn:2382120",
        "tgn:1000001",
        "tgn:2002146",
        "tgn:7012149",
        "tgn:7007919",
        "tgn:7029392"
    ],
    "tgn:id":2382120,
    "tgn:name":"Haymakertown",
    "tgn:placetype":[
        "aat:300008347"
    ]
},
  "bbox": [],
  "geometry": {"coordinates":[-79.9667,37.45],"type":"Point"}
}