{
  "id": 2126088,
  "type": "Feature",
  "properties": {
    "tgn:hierarchy":[
        "tgn:2126088",
        "tgn:1000001",
        "tgn:7012149",
        "tgn:2000837",
        "tgn:7007255",
        "tgn:7029392"
    ],
    "tgn:id":2126088,
    "tgn:name":"Add Hollow",
    "tgn:placetype":[
        "aat:300008761"
    ]
},
  "bbox": [],
  "geometry": {"coordinates":[-82.1833,37.4167],"type":"Point"}
}