{
  "id": 2524586,
  "type": "Feature",
  "properties": {
    "tgn:hierarchy":[
        "tgn:2524586",
        "tgn:1000001",
        "tgn:7012149",
        "tgn:2001607",
        "tgn:7007705",
        "tgn:7029392"
    ],
    "tgn:id":2524586,
    "tgn:name":"Mork Lake",
    "tgn:placetype":[
        "aat:300008680"
    ]
},
  "bbox": [],
  "geometry": {"coordinates":[-101.5667,48.1167],"type":"Point"}
}