{
  "id": 7318905,
  "type": "Feature",
  "properties": {
    "tgn:hierarchy":[
        "tgn:7318905",
        "tgn:1001702",
        "tgn:1000049",
        "tgn:1000002",
        "tgn:7029392"
    ],
    "tgn:id":7318905,
    "tgn:name":"Bah\u00eda Arquistade",
    "tgn:placetype":[
        "aat:300006495"
    ]
},
  "bbox": [],
  "geometry": {"coordinates":[-67.166667,-55.816667],"type":"Point"}
}