{
  "id": 7467336,
  "type": "Feature",
  "properties": {
    "tgn:hierarchy":[
        "tgn:7467336",
        "tgn:7488858",
        "tgn:1000004",
        "tgn:1000141",
        "tgn:7029392"
    ],
    "tgn:id":7467336,
    "tgn:name":"Afazhuang",
    "tgn:placetype":[
        "aat:300008347"
    ]
},
  "bbox": [],
  "geometry": {"coordinates":[120.6675,23.9553],"type":"Point"}
}