{
  "id": 7565572,
  "type": "Feature",
  "properties": {
    "tgn:hierarchy":[
        "tgn:7565572",
        "tgn:1000004",
        "tgn:7000198",
        "tgn:7016722",
        "tgn:7029392"
    ],
    "tgn:id":7565572,
    "tgn:name:en":"Sar\u0101i",
    "tgn:placetype":[
        "aat:300008347"
    ]
},
  "bbox": [],
  "geometry": {"coordinates":[79.517722,26.779876],"type":"Point"}
}