{
  "id": 7493278,
  "type": "Feature",
  "properties": {
    "tgn:hierarchy":[
        "tgn:7493278",
        "tgn:1000004",
        "tgn:7001014",
        "tgn:1000141",
        "tgn:7029392"
    ],
    "tgn:id":7493278,
    "tgn:name":"Zhujiaoliao Qiao",
    "tgn:placetype":[
        "aat:300007836"
    ]
},
  "bbox": [],
  "geometry": {"coordinates":[120.401034,23.67225],"type":"Point"}
}