{
  "id": 7231595,
  "type": "Feature",
  "properties": {
    "tgn:hierarchy":[
        "tgn:7231595",
        "tgn:7002735",
        "tgn:7017076",
        "tgn:1000003",
        "tgn:1000074",
        "tgn:7029392"
    ],
    "tgn:id":7231595,
    "tgn:name":"Kouro\u00fani, R\u00e1khi",
    "tgn:placetype":[
        "aat:300266640"
    ]
},
  "bbox": [],
  "geometry": {"coordinates":[22.833333,36.816667],"type":"Point"}
}