{
  "id": 7375972,
  "type": "Feature",
  "properties": {
    "tgn:hierarchy":[
        "tgn:7375972",
        "tgn:7005581",
        "tgn:1000001",
        "tgn:7005560",
        "tgn:7029392"
    ],
    "tgn:id":7375972,
    "tgn:name":"Rancho Las Varas",
    "tgn:placetype":[
        "aat:300000241"
    ]
},
  "bbox": [],
  "geometry": {"coordinates":[-107.433333,29.716667],"type":"Point"}
}