{
  "id": 2454312,
  "type": "Feature",
  "properties": {
    "tgn:hierarchy":[
        "tgn:2454312",
        "tgn:1000001",
        "tgn:7012149",
        "tgn:1002737",
        "tgn:7007520",
        "tgn:7029392"
    ],
    "tgn:id":2454312,
    "tgn:name":"Little Crotched Lake",
    "tgn:placetype":[
        "aat:300008680"
    ]
},
  "bbox": [],
  "geometry": {"coordinates":[-83.5833,42.8167],"type":"Point"}
}