{
  "id": 7004770,
  "type": "Feature",
  "properties": {
    "tgn:hierarchy":[
        "tgn:7004770",
        "tgn:1000001",
        "tgn:7029392"
    ],
    "tgn:id":7004770,
    "tgn:name:ar":"\u0628\u0631\u0628\u0627\u062f\u0648\u0633",
    "tgn:name:en":"Barbados",
    "tgn:name:es":"Barbados",
    "tgn:name:fr":"Barbade",
    "tgn:name:ru":"\u0411\u0430\u0440\u0431\u0430\u0434\u043e\u0441",
    "tgn:name:zh":"\u5df4\u5df4\u591a\u65af",
    "tgn:placetype":[
        "aat:300387054",
        "aat:300235115",
        "aat:300387062",
        "aat:300128207",
        "aat:300387174"
    ]
},
  "bbox": [],
  "geometry": {"coordinates":[-59.5333,13.1667],"type":"Point"}
}