{
  "id": 7568840,
  "type": "Feature",
  "properties": {
    "tgn:hierarchy":[
        "tgn:7568840",
        "tgn:1000004",
        "tgn:7000198",
        "tgn:1001996",
        "tgn:7029392"
    ],
    "tgn:id":7568840,
    "tgn:name:en":"Tul Protected Forest",
    "tgn:placetype":[
        "aat:300008863"
    ]
},
  "bbox": [],
  "geometry": {"coordinates":[77.056944,31.158333],"type":"Point"}
}