{
  "id": 7590403,
  "type": "Feature",
  "properties": {
    "tgn:hierarchy":[
        "tgn:7590403",
        "tgn:1000004",
        "tgn:7000198",
        "tgn:7000799",
        "tgn:7029392"
    ],
    "tgn:id":7590403,
    "tgn:name:en":"B\u0101ba Pah\u0101r",
    "tgn:placetype":[
        "aat:300008795"
    ]
},
  "bbox": [],
  "geometry": {"coordinates":[74.405556,33.758333],"type":"Point"}
}