<<<<<<< HEAD
{
  "id": 2767693,
  "type": "Feature",
  "properties": {
    "tgn:hierarchy":[
        "tgn:2767693",
        "tgn:1000001",
        "tgn:7012149",
        "tgn:2002359",
        "tgn:7007922",
        "tgn:7029392"
    ],
    "tgn:id":2767693,
    "tgn:name":"Whitefish Lake",
    "tgn:placetype":[
        "aat:300008680"
    ]
},
  "bbox": [],
  "geometry": {"coordinates":[-89.85,45.9],"type":"Point"}
}
=======
{"geometry":{"type":"Point","coordinates":[-89.850000,45.900000]},"type":"Feature","properties":{"hierarchy":["tgn:2767693","tgn:1000001","tgn:7012149","tgn:2002359","tgn:7007922","tgn:7029392"],"placetype":["aat:300008680"],"id":2767693,"name:xx":"Whitefish Lake"}}
>>>>>>> 03f74aca74312dbeaf24d7e61306dd6a786dc3d0
