{
  "id": 2123035,
  "type": "Feature",
  "properties": {
    "tgn:hierarchy":[
        "tgn:2123035",
        "tgn:1000001",
        "tgn:2002369",
        "tgn:7012149",
        "tgn:7007923",
        "tgn:7029392"
    ],
    "tgn:id":2123035,
    "tgn:name":"Lost Springs",
    "tgn:placetype":[
        "aat:300008347"
    ]
},
  "bbox": [],
  "geometry": {"coordinates":[-104.9167,42.75],"type":"Point"}
}