{
  "id": 2250180,
  "type": "Feature",
  "properties": {
    "tgn:hierarchy":[
        "tgn:2250180",
        "tgn:1000001",
        "tgn:7012149",
        "tgn:2000366",
        "tgn:7007248",
        "tgn:7029392"
    ],
    "tgn:id":2250180,
    "tgn:name":"Collins Lake",
    "tgn:placetype":[
        "aat:300006191"
    ]
},
  "bbox": [],
  "geometry": {"coordinates":[-84.0667,33.3167],"type":"Point"}
}