{
  "id": 2696440,
  "type": "Feature",
  "properties": {
    "tgn:hierarchy":[
        "tgn:2696440",
        "tgn:1000001",
        "tgn:2001418",
        "tgn:7012149",
        "tgn:7007526",
        "tgn:7029392"
    ],
    "tgn:id":2696440,
    "tgn:name":"Stone House",
    "tgn:placetype":[
        "aat:300008347",
        "aat:300167671"
    ]
},
  "bbox": [],
  "geometry": {"coordinates":[-116.7833,38.6667],"type":"Point"}
}