{
  "id": 7532999,
  "type": "Feature",
  "properties": {
    "tgn:hierarchy":[
        "tgn:7532999",
        "tgn:7001242",
        "tgn:7016833",
        "tgn:1001335",
        "tgn:7029392"
    ],
    "tgn:id":7532999,
    "tgn:name:en":"Tur'at Ruwaynah",
    "tgn:placetype":[
        "aat:300006075"
    ]
},
  "bbox": [],
  "geometry": {"coordinates":[30.900111,31.102407],"type":"Point"}
}