{
  "id": 2093006,
  "type": "Feature",
  "properties": {
    "tgn:hierarchy":[
        "tgn:2093006",
        "tgn:1000001",
        "tgn:7012149",
        "tgn:1002659",
        "tgn:7007710",
        "tgn:7029392"
    ],
    "tgn:id":2093006,
    "tgn:name":"Shenango",
    "tgn:placetype":[
        "aat:300008347"
    ]
},
  "bbox": [],
  "geometry": {"coordinates":[-80.3833,41.3667],"type":"Point"}
}