{
  "id": 7282265,
  "type": "Feature",
  "properties": {
    "tgn:hierarchy":[
        "tgn:7282265",
        "tgn:7002464",
        "tgn:1000049",
        "tgn:1000002",
        "tgn:7029392"
    ],
    "tgn:id":7282265,
    "tgn:name":"Putre, Nevados de",
    "tgn:placetype":[
        "aat:300008795"
    ]
},
  "bbox": [],
  "geometry": {"coordinates":[-69.533333,-18.116667],"type":"Point"}
}