{
  "id": 1137676,
  "type": "Feature",
  "properties": {
    "tgn:hierarchy":[
        "tgn:1137676",
        "tgn:1000004",
        "tgn:7011589",
        "tgn:7018214",
        "tgn:7002435",
        "tgn:7029392"
    ],
    "tgn:id":1137676,
    "tgn:name":"Kochki",
    "tgn:placetype":[
        "aat:300008347"
    ]
},
  "bbox": [],
  "geometry": {"coordinates":[80.4833,54.2667],"type":"Point"}
}