{
  "id": 2637725,
  "type": "Feature",
  "properties": {
    "tgn:hierarchy":[
        "tgn:2637725",
        "tgn:1000001",
        "tgn:2002316",
        "tgn:7012149",
        "tgn:7007922",
        "tgn:7029392"
    ],
    "tgn:id":2637725,
    "tgn:name":"Saint Phillips Ridge",
    "tgn:placetype":[
        "aat:300266640"
    ]
},
  "bbox": [],
  "geometry": {"coordinates":[-90.6833,43.3167],"type":"Point"}
}