<<<<<<< HEAD
{
  "id": 2256932,
  "type": "Feature",
  "properties": {
    "tgn:hierarchy":[
        "tgn:2256932",
        "tgn:1000001",
        "tgn:2001024",
        "tgn:7012149",
        "tgn:7007521",
        "tgn:7029392"
    ],
    "tgn:id":2256932,
    "tgn:name":"Cormorant Lake",
    "tgn:placetype":[
        "aat:300008680"
    ]
},
  "bbox": [],
  "geometry": {"coordinates":[-95.95,45.9],"type":"Point"}
}
=======
{"geometry":{"type":"Point","coordinates":[-95.950000,45.900000]},"type":"Feature","properties":{"hierarchy":["tgn:2256932","tgn:1000001","tgn:2001024","tgn:7012149","tgn:7007521","tgn:7029392"],"placetype":["aat:300008680"],"id":2256932,"name:xx":"Cormorant Lake"}}
>>>>>>> 03f74aca74312dbeaf24d7e61306dd6a786dc3d0
