{
  "id": 7158871,
  "type": "Feature",
  "properties": {
    "tgn:hierarchy":[
        "tgn:7158871",
        "tgn:1000003",
        "tgn:7003689",
        "tgn:7000084",
        "tgn:7029392"
    ],
    "tgn:id":7158871,
    "tgn:name":"Hollenbach",
    "tgn:placetype":[
        "aat:300008347"
    ]
},
  "bbox": [],
  "geometry": {"coordinates":[10.383333,51.233333],"type":"Point"}
}