{
  "id": 7214651,
  "type": "Feature",
  "properties": {
    "tgn:hierarchy":[
        "tgn:7214651",
        "tgn:7003669",
        "tgn:1000003",
        "tgn:7000084",
        "tgn:7029392"
    ],
    "tgn:id":7214651,
    "tgn:name":"Birkenau",
    "tgn:placetype":[
        "aat:300000206"
    ]
},
  "bbox": [],
  "geometry": {"coordinates":[12.45,49.116667],"type":"Point"}
}