{
  "id": 2130171,
  "type": "Feature",
  "properties": {
    "tgn:hierarchy":[
        "tgn:2130171",
        "tgn:1000001",
        "tgn:7012149",
        "tgn:2000928",
        "tgn:7007515",
        "tgn:7029392"
    ],
    "tgn:id":2130171,
    "tgn:name":"Allen Mountain",
    "tgn:placetype":[
        "aat:300008798"
    ]
},
  "bbox": [],
  "geometry": {"coordinates":[-69.2167,46.3333],"type":"Point"}
}