{
  "id": 2414902,
  "type": "Feature",
  "properties": {
    "tgn:hierarchy":[
        "tgn:2414902",
        "tgn:1000001",
        "tgn:2002367",
        "tgn:7012149",
        "tgn:7007923",
        "tgn:7029392"
    ],
    "tgn:id":2414902,
    "tgn:name":"Isenberger Reservoir",
    "tgn:placetype":[
        "aat:300006191"
    ]
},
  "bbox": [],
  "geometry": {"coordinates":[-105.35,43.8167],"type":"Point"}
}