<<<<<<< HEAD
{
  "id": 7373476,
  "type": "Feature",
  "properties": {
    "tgn:hierarchy":[
        "tgn:7373476",
        "tgn:1000001",
        "tgn:7005597",
        "tgn:7005560",
        "tgn:7029392"
    ],
    "tgn:id":7373476,
    "tgn:name":"La Gavia",
    "tgn:placetype":[
        "aat:300007783"
    ]
},
  "bbox": [],
  "geometry": {"coordinates":[-98.9,22.55],"type":"Point"}
}
=======
{"geometry":{"type":"Point","coordinates":[-98.900000,22.550000]},"type":"Feature","properties":{"hierarchy":["tgn:7373476","tgn:1000001","tgn:7005597","tgn:7005560","tgn:7029392"],"placetype":["aat:300007783"],"id":7373476,"name:xx":"La Gavia"}}
>>>>>>> 03f74aca74312dbeaf24d7e61306dd6a786dc3d0
