{
  "id": 2552350,
  "type": "Feature",
  "properties": {
    "tgn:hierarchy":[
        "tgn:2552350",
        "tgn:1000001",
        "tgn:7006451",
        "tgn:2000092",
        "tgn:7012149",
        "tgn:7029392"
    ],
    "tgn:id":2552350,
    "tgn:name":"Number Twelve Tank",
    "tgn:placetype":[
        "aat:300006191"
    ]
},
  "bbox": [],
  "geometry": {"coordinates":[-112.6333,35.8667],"type":"Point"}
}