{
  "id": 1071466,
  "type": "Feature",
  "properties": {
    "tgn:hierarchy":[
        "tgn:1071466",
        "tgn:1000004",
        "tgn:7002085",
        "tgn:1000111",
        "tgn:7029392"
    ],
    "tgn:id":1071466,
    "tgn:name":"Shangkou",
    "tgn:placetype":[
        "aat:300008347"
    ]
},
  "bbox": [],
  "geometry": {"coordinates":[118.8833,36.9833],"type":"Point"}
}