{
  "id": 7177480,
  "type": "Feature",
  "properties": {
    "tgn:hierarchy":[
        "tgn:7177480",
        "tgn:7003669",
        "tgn:1000003",
        "tgn:7000084",
        "tgn:7029392"
    ],
    "tgn:id":7177480,
    "tgn:name":"G\u00fcnzenhofen",
    "tgn:placetype":[
        "aat:300008347"
    ]
},
  "bbox": [],
  "geometry": {"coordinates":[12.033333,48.783333],"type":"Point"}
}