{
  "id": 2611151,
  "type": "Feature",
  "properties": {
    "tgn:hierarchy":[
        "tgn:2611151",
        "tgn:1000001",
        "tgn:7012149",
        "tgn:2002043",
        "tgn:7007826",
        "tgn:7029392"
    ],
    "tgn:id":2611151,
    "tgn:name":"Red Hills",
    "tgn:placetype":[
        "aat:300008798"
    ]
},
  "bbox": [],
  "geometry": {"coordinates":[-101.0333,32.45],"type":"Point"}
}