{
  "id": 2196879,
  "type": "Feature",
  "properties": {
    "tgn:hierarchy":[
        "tgn:2196879",
        "tgn:1000001",
        "tgn:7012149",
        "tgn:2001488",
        "tgn:7007709",
        "tgn:7029392"
    ],
    "tgn:id":2196879,
    "tgn:name":"Brooks Point",
    "tgn:placetype":[
        "aat:300008850"
    ]
},
  "bbox": [],
  "geometry": {"coordinates":[-75.5833,35.2667],"type":"Point"}
}