{
  "id": 7485972,
  "type": "Feature",
  "properties": {
    "tgn:hierarchy":[
        "tgn:7485972",
        "tgn:1000004",
        "tgn:7001014",
        "tgn:1000141",
        "tgn:7029392"
    ],
    "tgn:id":7485972,
    "tgn:name":"Shuilin Diyihao Qiao",
    "tgn:placetype":[
        "aat:300007836"
    ]
},
  "bbox": [],
  "geometry": {"coordinates":[120.256389,23.570556],"type":"Point"}
}