<<<<<<< HEAD
{
  "id": 7485972,
  "type": "Feature",
  "properties": {
    "tgn:hierarchy":[
        "tgn:7485972",
        "tgn:1000004",
        "tgn:7001014",
        "tgn:1000141",
        "tgn:7029392"
    ],
    "tgn:id":7485972,
    "tgn:name":"Shuilin Diyihao Qiao",
    "tgn:placetype":[
        "aat:300007836"
    ]
},
  "bbox": [],
  "geometry": {"coordinates":[120.256389,23.570556],"type":"Point"}
}
=======
{"geometry":{"type":"Point","coordinates":[120.256389,23.570556]},"type":"Feature","properties":{"hierarchy":["tgn:7485972","tgn:1000004","tgn:7001014","tgn:1000141","tgn:7029392"],"placetype":["aat:300007836"],"id":7485972,"name:xx":"Shuilin Diyihao Qiao"}}
>>>>>>> 03f74aca74312dbeaf24d7e61306dd6a786dc3d0
