{
  "id": 2379114,
  "type": "Feature",
  "properties": {
    "tgn:hierarchy":[
        "tgn:2379114",
        "tgn:1000001",
        "tgn:7012149",
        "tgn:2001866",
        "tgn:7007825",
        "tgn:7029392"
    ],
    "tgn:id":2379114,
    "tgn:name":"Hartman Mine Number Two",
    "tgn:placetype":[
        "aat:300000390"
    ]
},
  "bbox": [],
  "geometry": {"coordinates":[-82.8667,36.1667],"type":"Point"}
}