{
  "id": 7499942,
  "type": "Feature",
  "properties": {
    "tgn:hierarchy":[
        "tgn:7499942",
        "tgn:7001004",
        "tgn:1000004",
        "tgn:1000141",
        "tgn:7029392"
    ],
    "tgn:id":7499942,
    "tgn:name":"Xinzhuang Qiao",
    "tgn:placetype":[
        "aat:300007836"
    ]
},
  "bbox": [],
  "geometry": {"coordinates":[120.487759,22.564583],"type":"Point"}
}