<<<<<<< HEAD
{
  "id": 2764515,
  "type": "Feature",
  "properties": {
    "tgn:hierarchy":[
        "tgn:2764515",
        "tgn:1000001",
        "tgn:7012149",
        "tgn:2001394",
        "tgn:7007525",
        "tgn:7029392"
    ],
    "tgn:id":2764515,
    "tgn:name":"Whipple Canyon",
    "tgn:placetype":[
        "aat:300008761"
    ]
},
  "bbox": [],
  "geometry": {"coordinates":[-103.9,41.7333],"type":"Point"}
}
=======
{"geometry":{"type":"Point","coordinates":[-103.900000,41.733300]},"type":"Feature","properties":{"hierarchy":["tgn:2764515","tgn:1000001","tgn:7012149","tgn:2001394","tgn:7007525","tgn:7029392"],"placetype":["aat:300008761"],"id":2764515,"name:xx":"Whipple Canyon"}}
>>>>>>> 03f74aca74312dbeaf24d7e61306dd6a786dc3d0
