{
  "id": 2721013,
  "type": "Feature",
  "properties": {
    "tgn:hierarchy":[
        "tgn:2721013",
        "tgn:1000001",
        "tgn:7012149",
        "tgn:7007524",
        "tgn:7029392"
    ],
    "tgn:id":2721013,
    "tgn:name":"Tie Chute Creek",
    "tgn:placetype":[
        "aat:300008706"
    ]
},
  "bbox": [],
  "geometry": {"coordinates":[-114.15,46.65],"type":"Point"}
}