{
  "id": 7320945,
  "type": "Feature",
  "properties": {
    "tgn:hierarchy":[
        "tgn:7320945",
        "tgn:7016598",
        "tgn:1000049",
        "tgn:1000002",
        "tgn:7029392"
    ],
    "tgn:id":7320945,
    "tgn:name":"Ballena, Punta",
    "tgn:placetype":[
        "aat:300386846"
    ]
},
  "bbox": [],
  "geometry": {"coordinates":[-70.733333,-25.816667],"type":"Point"}
}