{
  "id": 2246563,
  "type": "Feature",
  "properties": {
    "tgn:hierarchy":[
        "tgn:2246563",
        "tgn:1000001",
        "tgn:7012149",
        "tgn:2000206",
        "tgn:7007158",
        "tgn:7029392"
    ],
    "tgn:id":2246563,
    "tgn:name":"Cobbett Lake",
    "tgn:placetype":[
        "aat:300008680"
    ]
},
  "bbox": [],
  "geometry": {"coordinates":[-107.9833,39.0333],"type":"Point"}
}