{
  "id": 2242548,
  "type": "Feature",
  "properties": {
    "tgn:hierarchy":[
        "tgn:2242548",
        "tgn:1000001",
        "tgn:7016172",
        "tgn:7012149",
        "tgn:2000153",
        "tgn:7029392"
    ],
    "tgn:id":2242548,
    "tgn:name":"Clear Creek",
    "tgn:placetype":[
        "aat:300008706"
    ]
},
  "bbox": [],
  "geometry": {"coordinates":[-93.7667,34.5667],"type":"Point"}
}