{
  "id": 2732957,
  "type": "Feature",
  "properties": {
    "tgn:hierarchy":[
        "tgn:2732957",
        "tgn:1000001",
        "tgn:7012149",
        "tgn:1002451",
        "tgn:7007919",
        "tgn:7029392"
    ],
    "tgn:id":2732957,
    "tgn:name":"Turkey Hill",
    "tgn:placetype":[
        "aat:300008798"
    ]
},
  "bbox": [],
  "geometry": {"coordinates":[-77.2667,37.55],"type":"Point"}
}