{
  "id": 2356304,
  "type": "Feature",
  "properties": {
    "tgn:hierarchy":[
        "tgn:2356304",
        "tgn:1000001",
        "tgn:2002258",
        "tgn:7012149",
        "tgn:7013961",
        "tgn:7029392"
    ],
    "tgn:id":2356304,
    "tgn:name":"Goosenest Run",
    "tgn:placetype":[
        "aat:300008699"
    ]
},
  "bbox": [],
  "geometry": {"coordinates":[-81.25,38.9167],"type":"Point"}
}