{
  "id": 7419074,
  "type": "Feature",
  "properties": {
    "tgn:hierarchy":[
        "tgn:7419074",
        "tgn:1000001",
        "tgn:7005591",
        "tgn:7005560",
        "tgn:7029392"
    ],
    "tgn:id":7419074,
    "tgn:name":"Bethania",
    "tgn:placetype":[
        "aat:300008347"
    ]
},
  "bbox": [],
  "geometry": {"coordinates":[-95.994167,17.924444],"type":"Point"}
}