{
  "id": 2268506,
  "type": "Feature",
  "properties": {
    "tgn:hierarchy":[
        "tgn:2268506",
        "tgn:1000001",
        "tgn:7012149",
        "tgn:7007157",
        "tgn:2000191",
        "tgn:7029392"
    ],
    "tgn:id":2268506,
    "tgn:name":"Crooks Ridge",
    "tgn:placetype":[
        "aat:300266640"
    ]
},
  "bbox": [],
  "geometry": {"coordinates":[-123.5333,40.3833],"type":"Point"}
}