<<<<<<< HEAD
{
  "id": 7172645,
  "type": "Feature",
  "properties": {
    "tgn:hierarchy":[
        "tgn:7172645",
        "tgn:1000003",
        "tgn:7003677",
        "tgn:7000084",
        "tgn:7029392"
    ],
    "tgn:id":7172645,
    "tgn:name":"Hinterscharde",
    "tgn:placetype":[
        "aat:300000206"
    ]
},
  "bbox": [],
  "geometry": {"coordinates":[7.516667,51.083333],"type":"Point"}
}
=======
{"geometry":{"type":"Point","coordinates":[7.516667,51.083333]},"type":"Feature","properties":{"hierarchy":["tgn:7172645","tgn:1000003","tgn:7003677","tgn:7000084","tgn:7029392"],"placetype":["aat:300000206"],"id":7172645,"name:xx":"Hinterscharde"}}
>>>>>>> 03f74aca74312dbeaf24d7e61306dd6a786dc3d0
