{
  "id": 2510104,
  "type": "Feature",
  "properties": {
    "tgn:hierarchy":[
        "tgn:2510104",
        "tgn:1000001",
        "tgn:7016172",
        "tgn:2000111",
        "tgn:7012149",
        "tgn:7029392"
    ],
    "tgn:id":2510104,
    "tgn:name":"Middle Pond",
    "tgn:placetype":[
        "aat:300006191"
    ]
},
  "bbox": [],
  "geometry": {"coordinates":[-92.5333,33.6667],"type":"Point"}
}