{
  "id": 2723249,
  "type": "Feature",
  "properties": {
    "tgn:hierarchy":[
        "tgn:2723249",
        "tgn:1000001",
        "tgn:7012149",
        "tgn:1002779",
        "tgn:7007710",
        "tgn:7029392"
    ],
    "tgn:id":2723249,
    "tgn:name":"Toad Hollow",
    "tgn:placetype":[
        "aat:300008761"
    ]
},
  "bbox": [],
  "geometry": {"coordinates":[-77.0333,40.5667],"type":"Point"}
}