{
  "id": 7472690,
  "type": "Feature",
  "properties": {
    "tgn:hierarchy":[
        "tgn:7472690",
        "tgn:7487020",
        "tgn:1000004",
        "tgn:1000141",
        "tgn:7029392"
    ],
    "tgn:id":7472690,
    "tgn:name":"Tongjing Cun",
    "tgn:placetype":[
        "aat:300387173"
    ]
},
  "bbox": [],
  "geometry": {"coordinates":[120.9748,24.6639],"type":"Point"}
}