<<<<<<< HEAD
{
  "id": 7472690,
  "type": "Feature",
  "properties": {
    "tgn:hierarchy":[
        "tgn:7472690",
        "tgn:7487020",
        "tgn:1000004",
        "tgn:1000141",
        "tgn:7029392"
    ],
    "tgn:id":7472690,
    "tgn:name":"Tongjing Cun",
    "tgn:placetype":[
        "aat:300387173"
    ]
},
  "bbox": [],
  "geometry": {"coordinates":[120.9748,24.6639],"type":"Point"}
}
=======
{"geometry":{"type":"Point","coordinates":[120.974800,24.663900]},"type":"Feature","properties":{"hierarchy":["tgn:7472690","tgn:7487020","tgn:1000004","tgn:1000141","tgn:7029392"],"placetype":["aat:300387173"],"id":7472690,"name:xx":"Tongjing Cun"}}
>>>>>>> 03f74aca74312dbeaf24d7e61306dd6a786dc3d0
