{
  "id": 2743614,
  "type": "Feature",
  "properties": {
    "tgn:hierarchy":[
        "tgn:2743614",
        "tgn:1000001",
        "tgn:7012149",
        "tgn:1002382",
        "tgn:7007255",
        "tgn:7029392"
    ],
    "tgn:id":2743614,
    "tgn:name":"Vaughn Branch",
    "tgn:placetype":[
        "aat:300008699"
    ]
},
  "bbox": [],
  "geometry": {"coordinates":[-84.8167,38.1833],"type":"Point"}
}