{
  "id": 2110685,
  "type": "Feature",
  "properties": {
    "tgn:hierarchy":[
        "tgn:2110685",
        "tgn:1000001",
        "tgn:7012149",
        "tgn:2002196",
        "tgn:7007919",
        "tgn:7029392"
    ],
    "tgn:id":2110685,
    "tgn:name":"Blacklick",
    "tgn:placetype":[
        "aat:300008347",
        "aat:300387210"
    ]
},
  "bbox": [],
  "geometry": {"coordinates":[-81.25,36.9333],"type":"Point"}
}