{
  "id": 7325754,
  "type": "Feature",
  "properties": {
    "tgn:hierarchy":[
        "tgn:7325754",
        "tgn:7008911",
        "tgn:1000003",
        "tgn:7002763",
        "tgn:1000095",
        "tgn:7029392"
    ],
    "tgn:id":7325754,
    "tgn:name":"San Antol\u00edn, Playa de",
    "tgn:placetype":[
        "aat:300008816"
    ]
},
  "bbox": [],
  "geometry": {"coordinates":[-4.866667,43.45],"type":"Point"}
}