{
  "id": 2492760,
  "type": "Feature",
  "properties": {
    "tgn:hierarchy":[
        "tgn:2492760",
        "tgn:1000001",
        "tgn:7012149",
        "tgn:2000539",
        "tgn:7007251",
        "tgn:7029392"
    ],
    "tgn:id":2492760,
    "tgn:name":"Marion Reservoir",
    "tgn:placetype":[
        "aat:300006191"
    ]
},
  "bbox": [],
  "geometry": {"coordinates":[-88.95,37.6833],"type":"Point"}
}