{
  "id": 2544403,
  "type": "Feature",
  "properties": {
    "tgn:hierarchy":[
        "tgn:2544403",
        "tgn:1002141",
        "tgn:1000001",
        "tgn:7012149",
        "tgn:7007568",
        "tgn:7029392"
    ],
    "tgn:id":2544403,
    "tgn:name":"North Branch Van Campen Creek",
    "tgn:placetype":[
        "aat:300008706"
    ]
},
  "bbox": [],
  "geometry": {"coordinates":[-78.1833,42.2333],"type":"Point"}
}