{
  "id": 1026408,
  "type": "Feature",
  "properties": {
    "tgn:hierarchy":[
        "tgn:1026408",
        "tgn:7003461",
        "tgn:1000003",
        "tgn:1000063",
        "tgn:7018236",
        "tgn:7029392"
    ],
    "tgn:id":1026408,
    "tgn:name":"Eksel",
    "tgn:placetype":[
        "aat:300008347"
    ]
},
  "bbox": [],
  "geometry": {"coordinates":[5.383333,51.15],"type":"Point"}
}