{
  "id": 7562696,
  "type": "Feature",
  "properties": {
    "tgn:hierarchy":[
        "tgn:7562696",
        "tgn:1000004",
        "tgn:7000198",
        "tgn:7016722",
        "tgn:7029392"
    ],
    "tgn:id":7562696,
    "tgn:name:en":"Achintpur",
    "tgn:placetype":[
        "aat:300008347"
    ]
},
  "bbox": [],
  "geometry": {"coordinates":[79.475362,27.871894],"type":"Point"}
}