{
  "id": 2265984,
  "type": "Feature",
  "properties": {
    "tgn:hierarchy":[
        "tgn:2265984",
        "tgn:1000001",
        "tgn:7012149",
        "tgn:7014589",
        "tgn:7007515",
        "tgn:7029392"
    ],
    "tgn:id":2265984,
    "tgn:name":"Crawford",
    "tgn:placetype":[
        "aat:300008347"
    ]
},
  "bbox": [],
  "geometry": {"coordinates":[-67.55,45.05],"type":"Point"}
}