<<<<<<< HEAD
{
  "id": 2407219,
  "type": "Feature",
  "properties": {
    "tgn:hierarchy":[
        "tgn:2407219",
        "tgn:2001728",
        "tgn:1000001",
        "tgn:7012149",
        "tgn:7007712",
        "tgn:7029392"
    ],
    "tgn:id":2407219,
    "tgn:name":"Hunters Trail",
    "tgn:placetype":[
        "aat:300008347"
    ]
},
  "bbox": [],
  "geometry": {"coordinates":[-82.7333,34.55],"type":"Point"}
}
=======
{"geometry":{"type":"Point","coordinates":[-82.733300,34.550000]},"type":"Feature","properties":{"hierarchy":["tgn:2407219","tgn:2001728","tgn:1000001","tgn:7012149","tgn:7007712","tgn:7029392"],"placetype":["aat:300008347"],"id":2407219,"name:xx":"Hunters Trail"}}
>>>>>>> 03f74aca74312dbeaf24d7e61306dd6a786dc3d0
