{
  "id": 2242133,
  "type": "Feature",
  "properties": {
    "tgn:hierarchy":[
        "tgn:2242133",
        "tgn:1002338",
        "tgn:1000001",
        "tgn:7012149",
        "tgn:7007516",
        "tgn:7029392"
    ],
    "tgn:id":2242133,
    "tgn:name":"Clay Point",
    "tgn:placetype":[
        "aat:300008850"
    ]
},
  "bbox": [],
  "geometry": {"coordinates":[-76.2167,38.3333],"type":"Point"}
}