{
  "id": 7121209,
  "type": "Feature",
  "properties": {
    "tgn:hierarchy":[
        "tgn:7121209",
        "tgn:7003669",
        "tgn:1000003",
        "tgn:7000084",
        "tgn:7029392"
    ],
    "tgn:id":7121209,
    "tgn:name":"Pfaffenhof",
    "tgn:placetype":[
        "aat:300000206"
    ]
},
  "bbox": [],
  "geometry": {"coordinates":[13.283333,48.366667],"type":"Point"}
}