{
  "id": 2598469,
  "type": "Feature",
  "properties": {
    "tgn:hierarchy":[
        "tgn:2598469",
        "tgn:1000001",
        "tgn:7012149",
        "tgn:7007919",
        "tgn:7029392"
    ],
    "tgn:id":2598469,
    "tgn:name":"Price Creek",
    "tgn:placetype":[
        "aat:300008706"
    ]
},
  "bbox": [],
  "geometry": {"coordinates":[-81.9167,36.8667],"type":"Point"}
}