{
  "id": 7034590,
  "type": "Feature",
  "properties": {
    "tgn:hierarchy":[
        "tgn:7034590",
        "tgn:1003500",
        "tgn:1000003",
        "tgn:7010380",
        "tgn:1000080",
        "tgn:7029392"
    ],
    "tgn:id":7034590,
    "tgn:name":"Masseria Tosquez",
    "tgn:placetype":[
        "aat:300000206"
    ]
},
  "bbox": [],
  "geometry": {"coordinates":[17.117778,40.563333],"type":"Point"}
}