{
  "id": 2110846,
  "type": "Feature",
  "properties": {
    "tgn:hierarchy":[
        "tgn:2110846",
        "tgn:1000001",
        "tgn:7012149",
        "tgn:7014160",
        "tgn:7007919",
        "tgn:7029392"
    ],
    "tgn:id":2110846,
    "tgn:name":"Bucknell Heights",
    "tgn:placetype":[
        "aat:300008347"
    ]
},
  "bbox": [],
  "geometry": {"coordinates":[-77.0667,38.75],"type":"Point"}
}