{
  "id": 2717200,
  "type": "Feature",
  "properties": {
    "tgn:hierarchy":[
        "tgn:2717200",
        "tgn:1000001",
        "tgn:7012149",
        "tgn:1002773",
        "tgn:7007240",
        "tgn:7029392"
    ],
    "tgn:id":2717200,
    "tgn:name":"Third Point",
    "tgn:placetype":[
        "aat:300008850"
    ]
},
  "bbox": [],
  "geometry": {"coordinates":[-82.6833,28.4167],"type":"Point"}
}