{
  "id": 7151144,
  "type": "Feature",
  "properties": {
    "tgn:hierarchy":[
        "tgn:7151144",
        "tgn:7003669",
        "tgn:1000003",
        "tgn:7000084",
        "tgn:7029392"
    ],
    "tgn:id":7151144,
    "tgn:name":"Kapell",
    "tgn:placetype":[
        "aat:300387173"
    ]
},
  "bbox": [],
  "geometry": {"coordinates":[12.733333,47.866667],"type":"Point"}
}