{
  "id": 2056360,
  "type": "Feature",
  "properties": {
    "tgn:hierarchy":[
        "tgn:2056360",
        "tgn:1000001",
        "tgn:7012149",
        "tgn:2001120",
        "tgn:7007522",
        "tgn:7029392"
    ],
    "tgn:id":2056360,
    "tgn:name":"Electric Mills",
    "tgn:placetype":[
        "aat:300008347"
    ]
},
  "bbox": [],
  "geometry": {"coordinates":[-88.45,32.7667],"type":"Point"}
}