{
  "id": 7541479,
  "type": "Feature",
  "properties": {
    "tgn:hierarchy":[
        "tgn:7541479",
        "tgn:7001242",
        "tgn:7016833",
        "tgn:7001336",
        "tgn:7029392"
    ],
    "tgn:id":7541479,
    "tgn:name:en":"\u015eaww\u0101nah, W\u0101d\u012b a\u015f",
    "tgn:placetype":[
        "aat:300379998"
    ]
},
  "bbox": [],
  "geometry": {"coordinates":[34.145556,29.257778],"type":"Point"}
}