<<<<<<< HEAD
{
  "id": 7361528,
  "type": "Feature",
  "properties": {
    "tgn:hierarchy":[
        "tgn:7361528",
        "tgn:1000001",
        "tgn:7005599",
        "tgn:7005560",
        "tgn:7029392"
    ],
    "tgn:id":7361528,
    "tgn:name":"El Callej\u00f3n",
    "tgn:placetype":[
        "aat:300008347"
    ]
},
  "bbox": [],
  "geometry": {"coordinates":[-96.133333,18.733333],"type":"Point"}
}
=======
{"geometry":{"type":"Point","coordinates":[-96.133333,18.733333]},"type":"Feature","properties":{"hierarchy":["tgn:7361528","tgn:1000001","tgn:7005599","tgn:7005560","tgn:7029392"],"placetype":["aat:300008347"],"id":7361528,"name:xx":"El Callej\u00f3n"}}
>>>>>>> 03f74aca74312dbeaf24d7e61306dd6a786dc3d0
