{
  "id": 2536762,
  "type": "Feature",
  "properties": {
    "tgn:hierarchy":[
        "tgn:2536762",
        "tgn:1000001",
        "tgn:1002337",
        "tgn:7012149",
        "tgn:7007922",
        "tgn:7029392"
    ],
    "tgn:id":2536762,
    "tgn:name":"Neda Creek",
    "tgn:placetype":[
        "aat:300008706"
    ]
},
  "bbox": [],
  "geometry": {"coordinates":[-88.5333,43.4167],"type":"Point"}
}