{
  "id": 2658144,
  "type": "Feature",
  "properties": {
    "tgn:hierarchy":[
        "tgn:2658144",
        "tgn:1000001",
        "tgn:7012149",
        "tgn:7007709",
        "tgn:7029392"
    ],
    "tgn:id":2658144,
    "tgn:name":"Shelter Swamp Creek",
    "tgn:placetype":[
        "aat:300008706"
    ]
},
  "bbox": [],
  "geometry": {"coordinates":[-77.55,34.6167],"type":"Point"}
}