{
  "id": 7480650,
  "type": "Feature",
  "properties": {
    "tgn:hierarchy":[
        "tgn:7480650",
        "tgn:1000004",
        "tgn:7490934",
        "tgn:1000141",
        "tgn:7029392"
    ],
    "tgn:id":7480650,
    "tgn:name":"Beimen Xiang Diyi Gongmu",
    "tgn:placetype":[
        "aat:300266755"
    ]
},
  "bbox": [],
  "geometry": {"coordinates":[120.133911,23.268429],"type":"Point"}
}