{
  "id": 2008021,
  "type": "Feature",
  "properties": {
    "tgn:hierarchy":[
        "tgn:2008021",
        "tgn:1000001",
        "tgn:7016172",
        "tgn:7012149",
        "tgn:2000171",
        "tgn:7029392"
    ],
    "tgn:id":2008021,
    "tgn:name":"Cornhill",
    "tgn:placetype":[
        "aat:300008347",
        "aat:300387210"
    ]
},
  "bbox": [],
  "geometry": {"coordinates":[-94.0333,33.85],"type":"Point"}
}