{
  "id": 2151198,
  "type": "Feature",
  "properties": {
    "tgn:hierarchy":[
        "tgn:2151198",
        "tgn:1000001",
        "tgn:7012149",
        "tgn:1003038",
        "tgn:7007517",
        "tgn:7029392"
    ],
    "tgn:id":2151198,
    "tgn:name":"Batcheller Hill",
    "tgn:placetype":[
        "aat:300008798"
    ]
},
  "bbox": [],
  "geometry": {"coordinates":[-72.05,42.2833],"type":"Point"}
}