{
  "id": 2695479,
  "type": "Feature",
  "properties": {
    "tgn:hierarchy":[
        "tgn:2695479",
        "tgn:1000001",
        "tgn:7012149",
        "tgn:1002875",
        "tgn:7007568",
        "tgn:7029392"
    ],
    "tgn:id":2695479,
    "tgn:name":"Stingers Island",
    "tgn:placetype":[
        "aat:300008791"
    ]
},
  "bbox": [],
  "geometry": {"coordinates":[-77.0667,42.3833],"type":"Point"}
}