{
  "id": 7346726,
  "type": "Feature",
  "properties": {
    "tgn:hierarchy":[
        "tgn:7346726",
        "tgn:7002758",
        "tgn:1001316",
        "tgn:1000003",
        "tgn:1000095",
        "tgn:7029392"
    ],
    "tgn:id":7346726,
    "tgn:name":"B\u00e9jar, R\u00edo",
    "tgn:placetype":[
        "aat:300008699"
    ]
},
  "bbox": [],
  "geometry": {"coordinates":[-3.033333,37.833333],"type":"Point"}
}