{
  "id": 7221388,
  "type": "Feature",
  "properties": {
    "tgn:hierarchy":[
        "tgn:7221388",
        "tgn:7002728",
        "tgn:7002715",
        "tgn:1000003",
        "tgn:1000074",
        "tgn:7029392"
    ],
    "tgn:id":7221388,
    "tgn:name":"Tso\u00fama",
    "tgn:placetype":[
        "aat:300008798"
    ]
},
  "bbox": [],
  "geometry": {"coordinates":[22.313333,41.064444],"type":"Point"}
}