{
  "id": 7508320,
  "type": "Feature",
  "properties": {
    "tgn:hierarchy":[
        "tgn:7508320",
        "tgn:7520092",
        "tgn:1008380",
        "tgn:1000226",
        "tgn:1000006",
        "tgn:7029392"
    ],
    "tgn:id":7508320,
    "tgn:name:en":"Oroi",
    "tgn:placetype":[
        "aat:300008795"
    ]
},
  "bbox": [],
  "geometry": {"coordinates":[177.45,-37.983333],"type":"Point"}
}