{
  "id": 7335018,
  "type": "Feature",
  "properties": {
    "tgn:hierarchy":[
        "tgn:7335018",
        "tgn:7002824",
        "tgn:1000003",
        "tgn:7002786",
        "tgn:1000095",
        "tgn:7029392"
    ],
    "tgn:id":7335018,
    "tgn:name":"Filgueiro",
    "tgn:placetype":[
        "aat:300008347"
    ]
},
  "bbox": [],
  "geometry": {"coordinates":[-8.883333,42.833333],"type":"Point"}
}