<<<<<<< HEAD
{
  "id": 2767709,
  "type": "Feature",
  "properties": {
    "tgn:hierarchy":[
        "tgn:2767709",
        "tgn:1000001",
        "tgn:1002934",
        "tgn:7012149",
        "tgn:7007565",
        "tgn:7029392"
    ],
    "tgn:id":2767709,
    "tgn:name":"Whitehall",
    "tgn:placetype":[
        "aat:300008347"
    ]
},
  "bbox": [],
  "geometry": {"coordinates":[-74.7333,40.95],"type":"Point"}
}
=======
{"geometry":{"type":"Point","coordinates":[-74.733300,40.950000]},"type":"Feature","properties":{"hierarchy":["tgn:2767709","tgn:1000001","tgn:1002934","tgn:7012149","tgn:7007565","tgn:7029392"],"placetype":["aat:300008347"],"id":2767709,"name:xx":"Whitehall"}}
>>>>>>> 03f74aca74312dbeaf24d7e61306dd6a786dc3d0
