{
  "id": 2586190,
  "type": "Feature",
  "properties": {
    "tgn:hierarchy":[
        "tgn:2586190",
        "tgn:1000001",
        "tgn:2001429",
        "tgn:7012149",
        "tgn:7007566",
        "tgn:7029392"
    ],
    "tgn:id":2586190,
    "tgn:name":"Pistol Canyon",
    "tgn:placetype":[
        "aat:300008761"
    ]
},
  "bbox": [],
  "geometry": {"coordinates":[-108.6667,33.5167],"type":"Point"}
}