{
  "id": 1071353,
  "type": "Feature",
  "properties": {
    "tgn:hierarchy":[
        "tgn:1071353",
        "tgn:1000004",
        "tgn:1001390",
        "tgn:1000111",
        "tgn:7029392"
    ],
    "tgn:id":1071353,
    "tgn:name":"Santaizi",
    "tgn:placetype":[
        "aat:300008347"
    ]
},
  "bbox": [],
  "geometry": {"coordinates":[121.5833,41.35],"type":"Point"}
}