{
  "id": 2555312,
  "type": "Feature",
  "properties": {
    "tgn:hierarchy":[
        "tgn:2555312",
        "tgn:2000090",
        "tgn:1000001",
        "tgn:7006451",
        "tgn:7012149",
        "tgn:7029392"
    ],
    "tgn:id":2555312,
    "tgn:name":"Odart Mountain",
    "tgn:placetype":[
        "aat:300008798"
    ]
},
  "bbox": [],
  "geometry": {"coordinates":[-109.6333,33.7167],"type":"Point"}
}