{
  "id": 7473393,
  "type": "Feature",
  "properties": {
    "tgn:hierarchy":[
        "tgn:7473393",
        "tgn:1000004",
        "tgn:7004300",
        "tgn:1000141",
        "tgn:7029392"
    ],
    "tgn:id":7473393,
    "tgn:name":"Yanqing Yu",
    "tgn:placetype":[
        "aat:300008791"
    ]
},
  "bbox": [],
  "geometry": {"coordinates":[119.614418,23.607227],"type":"Point"}
}