{
  "id": 7295798,
  "type": "Feature",
  "properties": {
    "tgn:hierarchy":[
        "tgn:7295798",
        "tgn:7008911",
        "tgn:1000003",
        "tgn:7002763",
        "tgn:1000095",
        "tgn:7029392"
    ],
    "tgn:id":7295798,
    "tgn:name":"Llodero, Marismas de",
    "tgn:placetype":[
        "aat:300387003"
    ]
},
  "bbox": [],
  "geometry": {"coordinates":[-5.918333,43.589722],"type":"Point"}
}