{
  "id": 2085395,
  "type": "Feature",
  "properties": {
    "tgn:hierarchy":[
        "tgn:2085395",
        "tgn:1000001",
        "tgn:7012149",
        "tgn:2001711",
        "tgn:7007708",
        "tgn:7029392"
    ],
    "tgn:id":2085395,
    "tgn:name":"Prospect",
    "tgn:placetype":[
        "aat:300008347"
    ]
},
  "bbox": [],
  "geometry": {"coordinates":[-122.4833,42.75],"type":"Point"}
}