{
  "id": 7506588,
  "type": "Feature",
  "properties": {
    "tgn:hierarchy":[
        "tgn:7506588",
        "tgn:1009227",
        "tgn:1000226",
        "tgn:7016729",
        "tgn:1000006",
        "tgn:7029392"
    ],
    "tgn:id":7506588,
    "tgn:name:en":"Robin Hood Bay",
    "tgn:placetype":[
        "aat:300132316"
    ]
},
  "bbox": [],
  "geometry": {"coordinates":[174.083333,-41.366667],"type":"Point"}
}