{
  "id": 7492950,
  "type": "Feature",
  "properties": {
    "tgn:hierarchy":[
        "tgn:7492950",
        "tgn:1000004",
        "tgn:7001014",
        "tgn:1000141",
        "tgn:7029392"
    ],
    "tgn:id":7492950,
    "tgn:name":"Songjiao",
    "tgn:placetype":[
        "aat:300008347"
    ]
},
  "bbox": [],
  "geometry": {"coordinates":[120.595833,23.524444],"type":"Point"}
}