{
  "id": 7291401,
  "type": "Feature",
  "properties": {
    "tgn:hierarchy":[
        "tgn:7291401",
        "tgn:1001702",
        "tgn:1000049",
        "tgn:1000002",
        "tgn:7029392"
    ],
    "tgn:id":7291401,
    "tgn:name":"Escape, Canal",
    "tgn:placetype":[
        "aat:300387026"
    ]
},
  "bbox": [],
  "geometry": {"coordinates":[-74.45,-49.466667],"type":"Point"}
}