{
  "id": 1010907,
  "type": "Feature",
  "properties": {
    "tgn:hierarchy":[
        "tgn:1010907",
        "tgn:7002849",
        "tgn:1000003",
        "tgn:7009604",
        "tgn:1000095",
        "tgn:7029392"
    ],
    "tgn:id":1010907,
    "tgn:name":"Machichaco, Cabo",
    "tgn:placetype":[
        "aat:300008850"
    ]
},
  "bbox": [],
  "geometry": {"coordinates":[-2.752426,43.456565],"type":"Point"}
}