{
  "id": 2611237,
  "type": "Feature",
  "properties": {
    "tgn:hierarchy":[
        "tgn:2611237",
        "tgn:1000001",
        "tgn:7012149",
        "tgn:2002353",
        "tgn:7007922",
        "tgn:7029392"
    ],
    "tgn:id":2611237,
    "tgn:name":"Red Ike Lake",
    "tgn:placetype":[
        "aat:300008680"
    ]
},
  "bbox": [],
  "geometry": {"coordinates":[-90.95,46.1333],"type":"Point"}
}