{
  "id": 1130394,
  "type": "Feature",
  "properties": {
    "tgn:hierarchy":[
        "tgn:1130394",
        "tgn:1000801",
        "tgn:1000001",
        "tgn:7005554",
        "tgn:7029392"
    ],
    "tgn:id":1130394,
    "tgn:name":"Sulaco, R\u00edo",
    "tgn:placetype":[
        "aat:300008707"
    ]
},
  "bbox": [],
  "geometry": {"coordinates":[-87.7333,15.0167],"type":"Point"}
}