<<<<<<< HEAD
{
  "id": 7484027,
  "type": "Feature",
  "properties": {
    "tgn:hierarchy":[
        "tgn:7484027",
        "tgn:1000004",
        "tgn:7001009",
        "tgn:1000141",
        "tgn:7029392"
    ],
    "tgn:id":7484027,
    "tgn:name":"Xinxishiliao",
    "tgn:placetype":[
        "aat:300008347"
    ]
},
  "bbox": [],
  "geometry": {"coordinates":[120.596111,24.250556],"type":"Point"}
}
=======
{"geometry":{"type":"Point","coordinates":[120.596111,24.250556]},"type":"Feature","properties":{"hierarchy":["tgn:7484027","tgn:1000004","tgn:7001009","tgn:1000141","tgn:7029392"],"placetype":["aat:300008347"],"id":7484027,"name:xx":"Xinxishiliao"}}
>>>>>>> 03f74aca74312dbeaf24d7e61306dd6a786dc3d0
