<<<<<<< HEAD
{
  "id": 2255372,
  "type": "Feature",
  "properties": {
    "tgn:hierarchy":[
        "tgn:2255372",
        "tgn:1000001",
        "tgn:7012149",
        "tgn:2000876",
        "tgn:7007256",
        "tgn:7029392"
    ],
    "tgn:id":2255372,
    "tgn:name":"Coopersville",
    "tgn:placetype":[
        "aat:300008347"
    ]
},
  "bbox": [],
  "geometry": {"coordinates":[-91.8,30.0],"type":"Point"}
}
=======
{"geometry":{"type":"Point","coordinates":[-91.800000,30.000000]},"type":"Feature","properties":{"hierarchy":["tgn:2255372","tgn:1000001","tgn:7012149","tgn:2000876","tgn:7007256","tgn:7029392"],"placetype":["aat:300008347"],"id":2255372,"name:xx":"Coopersville"}}
>>>>>>> 03f74aca74312dbeaf24d7e61306dd6a786dc3d0
