<<<<<<< HEAD
{
  "id": 7059750,
  "type": "Feature",
  "properties": {
    "tgn:hierarchy":[
        "tgn:7059750",
        "tgn:1000003",
        "tgn:7003677",
        "tgn:7000084",
        "tgn:7029392"
    ],
    "tgn:id":7059750,
    "tgn:name":"Ahle",
    "tgn:placetype":[
        "aat:300008347"
    ]
},
  "bbox": [],
  "geometry": {"coordinates":[8.516667,52.2],"type":"Point"}
}
=======
{"geometry":{"type":"Point","coordinates":[8.516667,52.200000]},"type":"Feature","properties":{"hierarchy":["tgn:7059750","tgn:1000003","tgn:7003677","tgn:7000084","tgn:7029392"],"placetype":["aat:300008347"],"id":7059750,"name:xx":"Ahle"}}
>>>>>>> 03f74aca74312dbeaf24d7e61306dd6a786dc3d0
