{
  "id": 2575036,
  "type": "Feature",
  "properties": {
    "tgn:hierarchy":[
        "tgn:2575036",
        "tgn:1000001",
        "tgn:1002249",
        "tgn:7012149",
        "tgn:7007710",
        "tgn:7029392"
    ],
    "tgn:id":2575036,
    "tgn:name":"Penn View",
    "tgn:placetype":[
        "aat:300008347"
    ]
},
  "bbox": [],
  "geometry": {"coordinates":[-77.45,40.8333],"type":"Point"}
}