{
  "id": 1078484,
  "type": "Feature",
  "properties": {
    "tgn:hierarchy":[
        "tgn:1078484",
        "tgn:1000004",
        "tgn:1001336",
        "tgn:1000116",
        "tgn:7029392"
    ],
    "tgn:id":1078484,
    "tgn:name":"Sanggau",
    "tgn:placetype":[
        "aat:300008347"
    ]
},
  "bbox": [],
  "geometry": {"coordinates":[110.5833,0.1333],"type":"Point"}
}