{
  "id": 7551844,
  "type": "Feature",
  "properties": {
    "tgn:hierarchy":[
        "tgn:7551844",
        "tgn:1000004",
        "tgn:7000198",
        "tgn:7031783",
        "tgn:7029392"
    ],
    "tgn:id":7551844,
    "tgn:name:en":"Borio",
    "tgn:placetype":[
        "aat:300008347"
    ]
},
  "bbox": [],
  "geometry": {"coordinates":[87.589692,25.035947],"type":"Point"}
}