{
  "id": 7490255,
  "type": "Feature",
  "properties": {
    "tgn:hierarchy":[
        "tgn:7490255",
        "tgn:7468018",
        "tgn:1000004",
        "tgn:1000141",
        "tgn:7029392"
    ],
    "tgn:id":7490255,
    "tgn:name":"Xiashiguping",
    "tgn:placetype":[
        "aat:300008347"
    ]
},
  "bbox": [],
  "geometry": {"coordinates":[120.639722,23.537778],"type":"Point"}
}