{
  "id": 2752521,
  "type": "Feature",
  "properties": {
    "tgn:hierarchy":[
        "tgn:2752521",
        "tgn:2001732",
        "tgn:1000001",
        "tgn:7012149",
        "tgn:7007712",
        "tgn:7029392"
    ],
    "tgn:id":2752521,
    "tgn:name":"Washington Town",
    "tgn:placetype":[
        "aat:300008347"
    ]
},
  "bbox": [],
  "geometry": {"coordinates":[-80.1667,33.0833],"type":"Point"}
}