{
  "id": 2438736,
  "type": "Feature",
  "properties": {
    "tgn:hierarchy":[
        "tgn:2438736",
        "tgn:1000001",
        "tgn:7012149",
        "tgn:1002742",
        "tgn:7007920",
        "tgn:7029392"
    ],
    "tgn:id":2438736,
    "tgn:name":"Kinkaid Creek",
    "tgn:placetype":[
        "aat:300008706"
    ]
},
  "bbox": [],
  "geometry": {"coordinates":[-118.8667,48.3167],"type":"Point"}
}