{
  "id": 2460057,
  "type": "Feature",
  "properties": {
    "tgn:hierarchy":[
        "tgn:2460057",
        "tgn:1000001",
        "tgn:7006451",
        "tgn:2000094",
        "tgn:7012149",
        "tgn:7029392"
    ],
    "tgn:id":2460057,
    "tgn:name":"Little Rocky Creek",
    "tgn:placetype":[
        "aat:300008706"
    ]
},
  "bbox": [],
  "geometry": {"coordinates":[-109.9667,33.4333],"type":"Point"}
}