{
  "id": 7258478,
  "type": "Feature",
  "properties": {
    "tgn:hierarchy":[
        "tgn:7258478",
        "tgn:7018239",
        "tgn:1000003",
        "tgn:1000063",
        "tgn:7018236",
        "tgn:7029392"
    ],
    "tgn:id":7258478,
    "tgn:name":"Zellik",
    "tgn:placetype":[
        "aat:300008347"
    ]
},
  "bbox": [],
  "geometry": {"coordinates":[4.263365,50.886098],"type":"Point"}
}