{
  "id": 1070085,
  "type": "Feature",
  "properties": {
    "tgn:hierarchy":[
        "tgn:1070085",
        "tgn:1000004",
        "tgn:1001678",
        "tgn:1000111",
        "tgn:7029392"
    ],
    "tgn:id":1070085,
    "tgn:name":"Longming",
    "tgn:placetype":[
        "aat:300008347"
    ]
},
  "bbox": [],
  "geometry": {"coordinates":[107.0333,22.9667],"type":"Point"}
}