<<<<<<< HEAD
{
  "id": 2258477,
  "type": "Feature",
  "properties": {
    "tgn:hierarchy":[
        "tgn:2258477",
        "tgn:1000001",
        "tgn:7012149",
        "tgn:1002456",
        "tgn:7007826",
        "tgn:7029392"
    ],
    "tgn:id":2258477,
    "tgn:name":"Cotton Patch Bayou",
    "tgn:placetype":[
        "aat:300008699"
    ]
},
  "bbox": [],
  "geometry": {"coordinates":[-95.1833,29.7167],"type":"Point"}
}
=======
{"geometry":{"type":"Point","coordinates":[-95.183300,29.716700]},"type":"Feature","properties":{"hierarchy":["tgn:2258477","tgn:1000001","tgn:7012149","tgn:1002456","tgn:7007826","tgn:7029392"],"placetype":["aat:300008699"],"id":2258477,"name:xx":"Cotton Patch Bayou"}}
>>>>>>> 03f74aca74312dbeaf24d7e61306dd6a786dc3d0
