{
  "id": 1116206,
  "type": "Feature",
  "properties": {
    "tgn:hierarchy":[
        "tgn:1116206",
        "tgn:1000650",
        "tgn:1000001",
        "tgn:7005493",
        "tgn:7029392"
    ],
    "tgn:id":1116206,
    "tgn:name":"El Golfete",
    "tgn:placetype":[
        "aat:300008680"
    ]
},
  "bbox": [],
  "geometry": {"coordinates":[-88.8833,15.7333],"type":"Point"}
}