{
  "id": 7590071,
  "type": "Feature",
  "properties": {
    "tgn:hierarchy":[
        "tgn:7590071",
        "tgn:1000004",
        "tgn:7000198",
        "tgn:7016722",
        "tgn:7029392"
    ],
    "tgn:id":7590071,
    "tgn:name:en":"Bhagw\u0101npur",
    "tgn:placetype":[
        "aat:300008347"
    ]
},
  "bbox": [],
  "geometry": {"coordinates":[77.186082,29.794349],"type":"Point"}
}