{
  "id": 2515277,
  "type": "Feature",
  "properties": {
    "tgn:hierarchy":[
        "tgn:2515277",
        "tgn:1000001",
        "tgn:7012149",
        "tgn:7007826",
        "tgn:7029392"
    ],
    "tgn:id":2515277,
    "tgn:name":"Milligan Draw",
    "tgn:placetype":[
        "aat:300008761"
    ]
},
  "bbox": [],
  "geometry": {"coordinates":[-100.1167,30.8833],"type":"Point"}
}