{
  "id": 2627217,
  "type": "Feature",
  "properties": {
    "tgn:hierarchy":[
        "tgn:2627217",
        "tgn:1000001",
        "tgn:7012149",
        "tgn:7007157",
        "tgn:1002858",
        "tgn:7029392"
    ],
    "tgn:id":2627217,
    "tgn:name":"Rodeo Grounds",
    "tgn:placetype":[
        "aat:300055621"
    ]
},
  "bbox": [],
  "geometry": {"coordinates":[-116.4167,32.8167],"type":"Point"}
}