{
  "id": 1059298,
  "type": "Feature",
  "properties": {
    "tgn:hierarchy":[
        "tgn:1059298",
        "tgn:7011551",
        "tgn:1000004",
        "tgn:7018214",
        "tgn:7002435",
        "tgn:7029392"
    ],
    "tgn:id":1059298,
    "tgn:name":"Semcy",
    "tgn:placetype":[
        "aat:300008347"
    ]
},
  "bbox": [],
  "geometry": {"coordinates":[33.4667,52.85],"type":"Point"}
}