{
  "id": 2151604,
  "type": "Feature",
  "properties": {
    "tgn:hierarchy":[
        "tgn:2151604",
        "tgn:1000001",
        "tgn:7012149",
        "tgn:2000361",
        "tgn:7007248",
        "tgn:7029392"
    ],
    "tgn:id":2151604,
    "tgn:name":"Battle Branch",
    "tgn:placetype":[
        "aat:300008699"
    ]
},
  "bbox": [],
  "geometry": {"coordinates":[-82.9667,33.4333],"type":"Point"}
}