<<<<<<< HEAD
{
  "id": 2255982,
  "type": "Feature",
  "properties": {
    "tgn:hierarchy":[
        "tgn:2255982",
        "tgn:1000001",
        "tgn:2001409",
        "tgn:7012149",
        "tgn:7007526",
        "tgn:7029392"
    ],
    "tgn:id":2255982,
    "tgn:name":"Copper Kettle Canyon",
    "tgn:placetype":[
        "aat:300008761"
    ]
},
  "bbox": [],
  "geometry": {"coordinates":[-118.1333,39.85],"type":"Point"}
}
=======
{"geometry":{"type":"Point","coordinates":[-118.133300,39.850000]},"type":"Feature","properties":{"hierarchy":["tgn:2255982","tgn:1000001","tgn:2001409","tgn:7012149","tgn:7007526","tgn:7029392"],"placetype":["aat:300008761"],"id":2255982,"name:xx":"Copper Kettle Canyon"}}
>>>>>>> 03f74aca74312dbeaf24d7e61306dd6a786dc3d0
