{
  "id": 2614975,
  "type": "Feature",
  "properties": {
    "tgn:hierarchy":[
        "tgn:2614975",
        "tgn:1000001",
        "tgn:7012149",
        "tgn:7007157",
        "tgn:7014475",
        "tgn:7029392"
    ],
    "tgn:id":2614975,
    "tgn:name":"Renz Gulch",
    "tgn:placetype":[
        "aat:300008761"
    ]
},
  "bbox": [],
  "geometry": {"coordinates":[-121.6667,36.9833],"type":"Point"}
}