{
  "id": 2084551,
  "type": "Feature",
  "properties": {
    "tgn:hierarchy":[
        "tgn:2084551",
        "tgn:1000001",
        "tgn:7012149",
        "tgn:2001718",
        "tgn:7007708",
        "tgn:7029392"
    ],
    "tgn:id":2084551,
    "tgn:name":"Claude",
    "tgn:placetype":[
        "aat:300387016"
    ]
},
  "bbox": [],
  "geometry": {"coordinates":[-116.9833,43.9833],"type":"Point"}
}