{
  "id": 2660986,
  "type": "Feature",
  "properties": {
    "tgn:hierarchy":[
        "tgn:2660986",
        "tgn:1000001",
        "tgn:7012149",
        "tgn:1002995",
        "tgn:7007710",
        "tgn:7029392"
    ],
    "tgn:id":2660986,
    "tgn:name":"Short Creek",
    "tgn:placetype":[
        "aat:300008706"
    ]
},
  "bbox": [],
  "geometry": {"coordinates":[-80.35,40.0167],"type":"Point"}
}