{
  "id": 7560729,
  "type": "Feature",
  "properties": {
    "tgn:hierarchy":[
        "tgn:7560729",
        "tgn:1000004",
        "tgn:7000198",
        "tgn:7016722",
        "tgn:7029392"
    ],
    "tgn:id":7560729,
    "tgn:name:en":"Mer\u0101pur",
    "tgn:placetype":[
        "aat:300008347"
    ]
},
  "bbox": [],
  "geometry": {"coordinates":[79.449083,27.202882],"type":"Point"}
}