{
  "id": 2187666,
  "type": "Feature",
  "properties": {
    "tgn:hierarchy":[
        "tgn:2187666",
        "tgn:1000001",
        "tgn:1002240",
        "tgn:7012149",
        "tgn:7007255",
        "tgn:7029392"
    ],
    "tgn:id":2187666,
    "tgn:name":"Booth Hollow",
    "tgn:placetype":[
        "aat:300008761"
    ]
},
  "bbox": [],
  "geometry": {"coordinates":[-82.85,38.1833],"type":"Point"}
}