{
  "id": 1060939,
  "type": "Feature",
  "properties": {
    "tgn:hierarchy":[
        "tgn:1060939",
        "tgn:1000004",
        "tgn:7024035",
        "tgn:7006651",
        "tgn:7029392"
    ],
    "tgn:id":1060939,
    "tgn:name:en":"Vardenik",
    "tgn:placetype":[
        "aat:300008347"
    ]
},
  "bbox": [],
  "geometry": {"coordinates":[45.44,40.135],"type":"Point"}
}