{
  "id": 7268599,
  "type": "Feature",
  "properties": {
    "tgn:hierarchy":[
        "tgn:7268599",
        "tgn:1000003",
        "tgn:7003624",
        "tgn:7016845",
        "tgn:7029392"
    ],
    "tgn:id":7268599,
    "tgn:name:nl":"Roosendaalsche Vliet",
    "tgn:placetype":[
        "aat:300387032"
    ]
},
  "bbox": [],
  "geometry": {"coordinates":[4.433333,51.583333],"type":"Point"}
}