{
  "id": 1122817,
  "type": "Feature",
  "properties": {
    "tgn:hierarchy":[
        "tgn:1122817",
        "tgn:1001657",
        "tgn:1000049",
        "tgn:1000002",
        "tgn:7029392"
    ],
    "tgn:id":1122817,
    "tgn:name":"Choapa, R\u00edo",
    "tgn:placetype":[
        "aat:300008707",
        "aat:300008699"
    ]
},
  "bbox": [],
  "geometry": {"coordinates":[-71.556111,-31.621944],"type":"Point"}
}