{
  "id": 2503058,
  "type": "Feature",
  "properties": {
    "tgn:hierarchy":[
        "tgn:2503058",
        "tgn:1000001",
        "tgn:7016172",
        "tgn:7012149",
        "tgn:2000164",
        "tgn:7029392"
    ],
    "tgn:id":2503058,
    "tgn:name":"McNeely Brake",
    "tgn:placetype":[
        "aat:300008905"
    ]
},
  "bbox": [],
  "geometry": {"coordinates":[-92.05,34.5833],"type":"Point"}
}