<<<<<<< HEAD
{
  "id": 2338875,
  "type": "Feature",
  "properties": {
    "tgn:hierarchy":[
        "tgn:2338875",
        "tgn:1000001",
        "tgn:7012149",
        "tgn:2001440",
        "tgn:7007566",
        "tgn:7029392"
    ],
    "tgn:id":2338875,
    "tgn:name":"Frankie Tank",
    "tgn:placetype":[
        "aat:300006191"
    ]
},
  "bbox": [],
  "geometry": {"coordinates":[-108.7,31.5167],"type":"Point"}
}
=======
{"geometry":{"type":"Point","coordinates":[-108.700000,31.516700]},"type":"Feature","properties":{"hierarchy":["tgn:2338875","tgn:1000001","tgn:7012149","tgn:2001440","tgn:7007566","tgn:7029392"],"placetype":["aat:300006191"],"id":2338875,"name:xx":"Frankie Tank"}}
>>>>>>> 03f74aca74312dbeaf24d7e61306dd6a786dc3d0
