{
  "id": 4010144,
  "type": "Feature",
  "properties": {
    "tgn:hierarchy":[
        "tgn:4010144",
        "tgn:1000003",
        "tgn:7012216",
        "tgn:1000070",
        "tgn:7029392"
    ],
    "tgn:id":4010144,
    "tgn:name":"Sauzon",
    "tgn:placetype":[
        "aat:300008347"
    ]
},
  "bbox": [],
  "geometry": {"coordinates":[-3.2167,47.3667],"type":"Point"}
}