{
  "id": 2651999,
  "type": "Feature",
  "properties": {
    "tgn:hierarchy":[
        "tgn:2651999",
        "tgn:1000001",
        "tgn:7016104",
        "tgn:7012149",
        "tgn:7007516",
        "tgn:7029392"
    ],
    "tgn:id":2651999,
    "tgn:name":"Selden Island",
    "tgn:placetype":[
        "aat:300008791"
    ]
},
  "bbox": [],
  "geometry": {"coordinates":[-77.45,39.0667],"type":"Point"}
}