{
  "id": 7435480,
  "type": "Feature",
  "properties": {
    "tgn:hierarchy":[
        "tgn:7435480",
        "tgn:7005581",
        "tgn:1000001",
        "tgn:7005560",
        "tgn:7029392"
    ],
    "tgn:id":7435480,
    "tgn:name":"Torre\u00f1o, Sierra del",
    "tgn:placetype":[
        "aat:300008795"
    ]
},
  "bbox": [],
  "geometry": {"coordinates":[-105.766667,29.116667],"type":"Point"}
}