{
  "id": 2201255,
  "type": "Feature",
  "properties": {
    "tgn:hierarchy":[
        "tgn:2201255",
        "tgn:1000001",
        "tgn:7012149",
        "tgn:7007523",
        "tgn:7029392"
    ],
    "tgn:id":2201255,
    "tgn:name":"Buchanan Valley",
    "tgn:placetype":[
        "aat:300008761"
    ]
},
  "bbox": [],
  "geometry": {"coordinates":[-90.9667,37.0833],"type":"Point"}
}