{
  "id": 1086069,
  "type": "Feature",
  "properties": {
    "tgn:hierarchy":[
        "tgn:1086069",
        "tgn:7002513",
        "tgn:1000004",
        "tgn:7018451",
        "tgn:1000144",
        "tgn:7029392"
    ],
    "tgn:id":1086069,
    "tgn:name":"Bayat",
    "tgn:placetype":[
        "aat:300008347"
    ]
},
  "bbox": [],
  "geometry": {"coordinates":[30.9167,38.9667],"type":"Point"}
}