{
  "id": 7148818,
  "type": "Feature",
  "properties": {
    "tgn:hierarchy":[
        "tgn:7148818",
        "tgn:1000003",
        "tgn:7003687",
        "tgn:7000084",
        "tgn:7029392"
    ],
    "tgn:id":7148818,
    "tgn:name":"Kunst-Berg",
    "tgn:placetype":[
        "aat:300008777"
    ]
},
  "bbox": [],
  "geometry": {"coordinates":[10.766667,51.783333],"type":"Point"}
}