{
  "id": 7286465,
  "type": "Feature",
  "properties": {
    "tgn:hierarchy":[
        "tgn:7286465",
        "tgn:1001630",
        "tgn:1000049",
        "tgn:1000002",
        "tgn:7029392"
    ],
    "tgn:id":7286465,
    "tgn:name":"H\u00e9rcules, Quebrada",
    "tgn:placetype":[
        "aat:300266554",
        "aat:300008699"
    ]
},
  "bbox": [],
  "geometry": {"coordinates":[-70.316667,-27.566667],"type":"Point"}
}