{
  "id": 1022425,
  "type": "Feature",
  "properties": {
    "tgn:hierarchy":[
        "tgn:1022425",
        "tgn:7006237",
        "tgn:1000047",
        "tgn:7002457",
        "tgn:1000002",
        "tgn:7029392"
    ],
    "tgn:id":1022425,
    "tgn:name":"Penha Longa",
    "tgn:placetype":[
        "aat:300008347"
    ]
},
  "bbox": [],
  "geometry": {"coordinates":[-43.0833,-22.0667],"type":"Point"}
}