{
  "id": 7040551,
  "type": "Feature",
  "properties": {
    "tgn:hierarchy":[
        "tgn:7040551",
        "tgn:7003011",
        "tgn:7003005",
        "tgn:1000003",
        "tgn:1000080",
        "tgn:7029392"
    ],
    "tgn:id":7040551,
    "tgn:name":"Santa Croce",
    "tgn:placetype":[
        "aat:300008347"
    ]
},
  "bbox": [],
  "geometry": {"coordinates":[13.983333,41.183333],"type":"Point"}
}