{
  "id": 2196489,
  "type": "Feature",
  "properties": {
    "tgn:hierarchy":[
        "tgn:2196489",
        "tgn:1000001",
        "tgn:7006451",
        "tgn:2000093",
        "tgn:7012149",
        "tgn:7029392"
    ],
    "tgn:id":2196489,
    "tgn:name":"Bronson Trick Tank",
    "tgn:placetype":[
        "aat:300006191"
    ]
},
  "bbox": [],
  "geometry": {"coordinates":[-110.6167,33.6833],"type":"Point"}
}