{
  "id": 2373530,
  "type": "Feature",
  "properties": {
    "tgn:hierarchy":[
        "tgn:2373530",
        "tgn:1000001",
        "tgn:7012149",
        "tgn:7022246",
        "tgn:7007825",
        "tgn:7029392"
    ],
    "tgn:id":2373530,
    "tgn:name":"Hames Hollow",
    "tgn:placetype":[
        "aat:300008761"
    ]
},
  "bbox": [],
  "geometry": {"coordinates":[-85.85,36.05],"type":"Point"}
}