{
  "id": 2209949,
  "type": "Feature",
  "properties": {
    "tgn:hierarchy":[
        "tgn:2209949",
        "tgn:1000001",
        "tgn:7012149",
        "tgn:1002767",
        "tgn:7007920",
        "tgn:7029392"
    ],
    "tgn:id":2209949,
    "tgn:name":"Burt",
    "tgn:placetype":[
        "aat:300008347"
    ]
},
  "bbox": [],
  "geometry": {"coordinates":[-123.45,46.65],"type":"Point"}
}