{
  "id": 2366214,
  "type": "Feature",
  "properties": {
    "tgn:hierarchy":[
        "tgn:2366214",
        "tgn:7013349",
        "tgn:1000001",
        "tgn:7012149",
        "tgn:7007708",
        "tgn:7029392"
    ],
    "tgn:id":2366214,
    "tgn:name":"Griffin Camp Spring",
    "tgn:placetype":[
        "aat:300008697"
    ]
},
  "bbox": [],
  "geometry": {"coordinates":[-118.3167,44.6667],"type":"Point"}
}