{
  "id": 7403247,
  "type": "Feature",
  "properties": {
    "tgn:hierarchy":[
        "tgn:7403247",
        "tgn:1000001",
        "tgn:7005600",
        "tgn:7005560",
        "tgn:7029392"
    ],
    "tgn:id":7403247,
    "tgn:name":"Santa In\u00e9s",
    "tgn:placetype":[
        "aat:300008347"
    ]
},
  "bbox": [],
  "geometry": {"coordinates":[-87.816667,21.283333],"type":"Point"}
}