{
  "id": 7465423,
  "type": "Feature",
  "properties": {
    "tgn:hierarchy":[
        "tgn:7465423",
        "tgn:7002444",
        "tgn:1000003",
        "tgn:7008082",
        "tgn:7008591",
        "tgn:7029392"
    ],
    "tgn:id":7465423,
    "tgn:name:en":"Achiltibuie",
    "tgn:placetype":[
        "aat:300008347"
    ]
},
  "bbox": [],
  "geometry": {"coordinates":[-5.366667,58.016667],"type":"Point"}
}