<<<<<<< HEAD
{
  "id": 2767364,
  "type": "Feature",
  "properties": {
    "tgn:hierarchy":[
        "tgn:2767364",
        "tgn:1000001",
        "tgn:2001477",
        "tgn:7012149",
        "tgn:7007709",
        "tgn:7029392"
    ],
    "tgn:id":2767364,
    "tgn:name":"White Shoal Marsh",
    "tgn:placetype":[
        "aat:300008905"
    ]
},
  "bbox": [],
  "geometry": {"coordinates":[-76.55,34.65],"type":"Point"}
}
=======
{"geometry":{"type":"Point","coordinates":[-76.550000,34.650000]},"type":"Feature","properties":{"hierarchy":["tgn:2767364","tgn:1000001","tgn:2001477","tgn:7012149","tgn:7007709","tgn:7029392"],"placetype":["aat:300008905"],"id":2767364,"name:xx":"White Shoal Marsh"}}
>>>>>>> 03f74aca74312dbeaf24d7e61306dd6a786dc3d0
