{
  "id": 7434711,
  "type": "Feature",
  "properties": {
    "tgn:hierarchy":[
        "tgn:7434711",
        "tgn:7005578",
        "tgn:1000001",
        "tgn:7005560",
        "tgn:7029392"
    ],
    "tgn:id":7434711,
    "tgn:name":"Xcantil",
    "tgn:placetype":[
        "aat:300008347"
    ]
},
  "bbox": [],
  "geometry": {"coordinates":[-90.633333,19.633333],"type":"Point"}
}