{
  "id": 7553035,
  "type": "Feature",
  "properties": {
    "tgn:hierarchy":[
        "tgn:7553035",
        "tgn:1000004",
        "tgn:7000198",
        "tgn:7031786",
        "tgn:7029392"
    ],
    "tgn:id":7553035,
    "tgn:name:en":"Mukh\u012bm",
    "tgn:placetype":[
        "aat:300008347"
    ]
},
  "bbox": [],
  "geometry": {"coordinates":[78.466721,30.576258],"type":"Point"}
}