{
  "id": 1098385,
  "type": "Feature",
  "properties": {
    "tgn:hierarchy":[
        "tgn:1098385",
        "tgn:7000490",
        "tgn:1000006",
        "tgn:7001834",
        "tgn:7029392"
    ],
    "tgn:id":1098385,
    "tgn:name":"Turner",
    "tgn:placetype":[
        "aat:300008347"
    ]
},
  "bbox": [],
  "geometry": {"coordinates":[128.2833,-17.8333],"type":"Point"}
}