{
  "id": 2042589,
  "type": "Feature",
  "properties": {
    "tgn:hierarchy":[
        "tgn:2042589",
        "tgn:1000001",
        "tgn:7012149",
        "tgn:2000910",
        "tgn:7007256",
        "tgn:7029392"
    ],
    "tgn:id":2042589,
    "tgn:name":"Cow Island",
    "tgn:placetype":[
        "aat:300008347"
    ]
},
  "bbox": [],
  "geometry": {"coordinates":[-92.25,29.8833],"type":"Point"}
}