{
  "id": 2528136,
  "type": "Feature",
  "properties": {
    "tgn:hierarchy":[
        "tgn:2528136",
        "tgn:1000001",
        "tgn:7012149",
        "tgn:2002188",
        "tgn:7007919",
        "tgn:7029392"
    ],
    "tgn:id":2528136,
    "tgn:name":"Mountain Top Lake",
    "tgn:placetype":[
        "aat:300008680"
    ]
},
  "bbox": [],
  "geometry": {"coordinates":[-81.9167,36.9667],"type":"Point"}
}