<<<<<<< HEAD
{
  "id": 7175539,
  "type": "Feature",
  "properties": {
    "tgn:hierarchy":[
        "tgn:7175539",
        "tgn:1000003",
        "tgn:7003677",
        "tgn:7000084",
        "tgn:7029392"
    ],
    "tgn:id":7175539,
    "tgn:name":"Griesenbruch",
    "tgn:placetype":[
        "aat:300387200"
    ]
},
  "bbox": [],
  "geometry": {"coordinates":[8.5,52.15],"type":"Point"}
}
=======
{"geometry":{"type":"Point","coordinates":[8.500000,52.150000]},"type":"Feature","properties":{"hierarchy":["tgn:7175539","tgn:1000003","tgn:7003677","tgn:7000084","tgn:7029392"],"placetype":["aat:300387200"],"id":7175539,"name:xx":"Griesenbruch"}}
>>>>>>> 03f74aca74312dbeaf24d7e61306dd6a786dc3d0
