<<<<<<< HEAD
{
  "id": 7353130,
  "type": "Feature",
  "properties": {
    "tgn:hierarchy":[
        "tgn:7353130",
        "tgn:1000001",
        "tgn:1001906",
        "tgn:7005560",
        "tgn:7029392"
    ],
    "tgn:id":7353130,
    "tgn:name":"Aut\u00e1n",
    "tgn:placetype":[
        "aat:300008347"
    ]
},
  "bbox": [],
  "geometry": {"coordinates":[-105.3,21.7],"type":"Point"}
}
=======
{"geometry":{"type":"Point","coordinates":[-105.300000,21.700000]},"type":"Feature","properties":{"hierarchy":["tgn:7353130","tgn:1000001","tgn:1001906","tgn:7005560","tgn:7029392"],"placetype":["aat:300008347"],"id":7353130,"name:xx":"Aut\u00e1n"}}
>>>>>>> 03f74aca74312dbeaf24d7e61306dd6a786dc3d0
