{
  "id": 7579477,
  "type": "Feature",
  "properties": {
    "tgn:hierarchy":[
        "tgn:7579477",
        "tgn:1001828",
        "tgn:1000004",
        "tgn:7000198",
        "tgn:7029392"
    ],
    "tgn:id":7579477,
    "tgn:name:en":"Som\u0101ram",
    "tgn:placetype":[
        "aat:300008347"
    ]
},
  "bbox": [],
  "geometry": {"coordinates":[79.733333,18.983333],"type":"Point"}
}