{
  "id": 7368650,
  "type": "Feature",
  "properties": {
    "tgn:hierarchy":[
        "tgn:7368650",
        "tgn:7005583",
        "tgn:1000001",
        "tgn:7005560",
        "tgn:7029392"
    ],
    "tgn:id":7368650,
    "tgn:name":"Rancho Infiernillo",
    "tgn:placetype":[
        "aat:300000241"
    ]
},
  "bbox": [],
  "geometry": {"coordinates":[-103.266667,24.95],"type":"Point"}
}