{
  "id": 2449646,
  "type": "Feature",
  "properties": {
    "tgn:hierarchy":[
        "tgn:2449646",
        "tgn:1000001",
        "tgn:7012149",
        "tgn:2000890",
        "tgn:7007256",
        "tgn:7029392"
    ],
    "tgn:id":2449646,
    "tgn:name":"Lincoln Park",
    "tgn:placetype":[
        "aat:300008347"
    ]
},
  "bbox": [],
  "geometry": {"coordinates":[-92.0833,32.45],"type":"Point"}
}