<<<<<<< HEAD
{
  "id": 2333396,
  "type": "Feature",
  "properties": {
    "tgn:hierarchy":[
        "tgn:2333396",
        "tgn:1000001",
        "tgn:7012149",
        "tgn:7007157",
        "tgn:1002858",
        "tgn:7029392"
    ],
    "tgn:id":2333396,
    "tgn:name":"Foley Canyon",
    "tgn:placetype":[
        "aat:300008761"
    ]
},
  "bbox": [],
  "geometry": {"coordinates":[-117.4833,33.3667],"type":"Point"}
}
=======
{"geometry":{"type":"Point","coordinates":[-117.483300,33.366700]},"type":"Feature","properties":{"hierarchy":["tgn:2333396","tgn:1000001","tgn:7012149","tgn:7007157","tgn:1002858","tgn:7029392"],"placetype":["aat:300008761"],"id":2333396,"name:xx":"Foley Canyon"}}
>>>>>>> 03f74aca74312dbeaf24d7e61306dd6a786dc3d0
