{
  "id": 7510344,
  "type": "Feature",
  "properties": {
    "tgn:hierarchy":[
        "tgn:7510344",
        "tgn:7520092",
        "tgn:1008380",
        "tgn:1000226",
        "tgn:1000006",
        "tgn:7029392"
    ],
    "tgn:id":7510344,
    "tgn:name:en":"Te Kaha Point",
    "tgn:placetype":[
        "aat:300386846"
    ]
},
  "bbox": [],
  "geometry": {"coordinates":[177.666667,-37.733333],"type":"Point"}
}