<<<<<<< HEAD
{
  "id": 7029639,
  "type": "Feature",
  "properties": {
    "tgn:hierarchy":[
        "tgn:7029639",
        "tgn:7002829",
        "tgn:1000003",
        "tgn:7002786",
        "tgn:1000095",
        "tgn:7029392"
    ],
    "tgn:id":7029639,
    "tgn:name:es":"Samos",
    "tgn:placetype":[
        "aat:300008347"
    ]
},
  "bbox": [],
  "geometry": {"coordinates":[-7.3,42.733333],"type":"Point"}
}
=======
{"geometry":{"type":"Point","coordinates":[-7.300000,42.733333]},"type":"Feature","properties":{"hierarchy":["tgn:7029639","tgn:7002829","tgn:1000003","tgn:7002786","tgn:1000095","tgn:7029392"],"placetype":["aat:300008347"],"id":7029639,"name:es":"Samos"}}
>>>>>>> 03f74aca74312dbeaf24d7e61306dd6a786dc3d0
