{
  "id": 2687416,
  "type": "Feature",
  "properties": {
    "tgn:hierarchy":[
        "tgn:2687416",
        "tgn:1000001",
        "tgn:2001799",
        "tgn:7012149",
        "tgn:7007713",
        "tgn:7029392"
    ],
    "tgn:id":2687416,
    "tgn:name":"Spring Lake",
    "tgn:placetype":[
        "aat:300008680"
    ]
},
  "bbox": [],
  "geometry": {"coordinates":[-98.9167,44.2667],"type":"Point"}
}