{
  "id": 7536240,
  "type": "Feature",
  "properties": {
    "tgn:hierarchy":[
        "tgn:7536240",
        "tgn:7001242",
        "tgn:7001311",
        "tgn:7016833",
        "tgn:7029392"
    ],
    "tgn:id":7536240,
    "tgn:name:en":"Khusheib\u00e2t il-B\u00fbm",
    "tgn:placetype":[
        "aat:300055621"
    ]
},
  "bbox": [],
  "geometry": {"coordinates":[34.736933,24.051085],"type":"Point"}
}