{
  "id": 7541566,
  "type": "Feature",
  "properties": {
    "tgn:hierarchy":[
        "tgn:7541566",
        "tgn:7001242",
        "tgn:7016833",
        "tgn:7000123",
        "tgn:7029392"
    ],
    "tgn:id":7541566,
    "tgn:name:en":"Kil\u1e29, Jaz\u012brat al",
    "tgn:placetype":[
        "aat:300008791"
    ]
},
  "bbox": [],
  "geometry": {"coordinates":[32.243424,26.087573],"type":"Point"}
}