{
  "id": 7418993,
  "type": "Feature",
  "properties": {
    "tgn:hierarchy":[
        "tgn:7418993",
        "tgn:7005579",
        "tgn:1000001",
        "tgn:7005560",
        "tgn:7029392"
    ],
    "tgn:id":7418993,
    "tgn:name":"Las Viboras, Arroyo",
    "tgn:placetype":[
        "aat:300266554",
        "aat:300008699"
    ]
},
  "bbox": [],
  "geometry": {"coordinates":[-102.35,21.85],"type":"Point"}
}