{
  "id": 2391155,
  "type": "Feature",
  "properties": {
    "tgn:hierarchy":[
        "tgn:2391155",
        "tgn:1000001",
        "tgn:1002279",
        "tgn:7012149",
        "tgn:7007706",
        "tgn:7029392"
    ],
    "tgn:id":2391155,
    "tgn:name":"Hill Lakes",
    "tgn:placetype":[
        "aat:300008680"
    ]
},
  "bbox": [],
  "geometry": {"coordinates":[-84.1333,39.1833],"type":"Point"}
}