{
  "id": 7124519,
  "type": "Feature",
  "properties": {
    "tgn:hierarchy":[
        "tgn:7124519",
        "tgn:1000003",
        "tgn:7003678",
        "tgn:7000084",
        "tgn:7029392"
    ],
    "tgn:id":7124519,
    "tgn:name":"Niederellenbach",
    "tgn:placetype":[
        "aat:300008347"
    ]
},
  "bbox": [],
  "geometry": {"coordinates":[9.65,51.05],"type":"Point"}
}