{
  "id": 2495644,
  "type": "Feature",
  "properties": {
    "tgn:hierarchy":[
        "tgn:2495644",
        "tgn:1000001",
        "tgn:7012149",
        "tgn:2002287",
        "tgn:7013961",
        "tgn:7029392"
    ],
    "tgn:id":2495644,
    "tgn:name":"Mash Run",
    "tgn:placetype":[
        "aat:300008699"
    ]
},
  "bbox": [],
  "geometry": {"coordinates":[-79.9167,38.2333],"type":"Point"}
}