{
  "id": 7040645,
  "type": "Feature",
  "properties": {
    "tgn:hierarchy":[
        "tgn:7040645",
        "tgn:1000003",
        "tgn:7003122",
        "tgn:7003157",
        "tgn:1000080",
        "tgn:7029392"
    ],
    "tgn:id":7040645,
    "tgn:name":"Forte San Salvatore",
    "tgn:placetype":[
        "aat:300006909"
    ]
},
  "bbox": [],
  "geometry": {"coordinates":[15.55,38.183333],"type":"Point"}
}