{
  "id": 4004337,
  "type": "Feature",
  "properties": {
    "tgn:hierarchy":[
        "tgn:4004337",
        "tgn:1003428",
        "tgn:1000003",
        "tgn:7003120",
        "tgn:1000080",
        "tgn:7029392"
    ],
    "tgn:id":4004337,
    "tgn:name":"Giarole",
    "tgn:placetype":[
        "aat:300008347"
    ]
},
  "bbox": [],
  "geometry": {"coordinates":[8.566667,45.05],"type":"Point"}
}