{
  "id": 7036286,
  "type": "Feature",
  "properties": {
    "tgn:hierarchy":[
        "tgn:7036286",
        "tgn:1003506",
        "tgn:1000003",
        "tgn:7002993",
        "tgn:1000080",
        "tgn:7029392"
    ],
    "tgn:id":7036286,
    "tgn:name":"Crete di Palasecca",
    "tgn:placetype":[
        "aat:300266640"
    ]
},
  "bbox": [],
  "geometry": {"coordinates":[13.122222,46.454167],"type":"Point"}
}