{
  "id": 2622751,
  "type": "Feature",
  "properties": {
    "tgn:hierarchy":[
        "tgn:2622751",
        "tgn:1000001",
        "tgn:7016172",
        "tgn:7012149",
        "tgn:2000143",
        "tgn:7029392"
    ],
    "tgn:id":2622751,
    "tgn:name":"Robinson Hill",
    "tgn:placetype":[
        "aat:300008798"
    ]
},
  "bbox": [],
  "geometry": {"coordinates":[-90.6833,34.7333],"type":"Point"}
}