{
  "id": 7035091,
  "type": "Feature",
  "properties": {
    "tgn:hierarchy":[
        "tgn:7035091",
        "tgn:1003506",
        "tgn:1000003",
        "tgn:7002993",
        "tgn:1000080",
        "tgn:7029392"
    ],
    "tgn:id":7035091,
    "tgn:name":"Paderno",
    "tgn:placetype":[
        "aat:300008347"
    ]
},
  "bbox": [],
  "geometry": {"coordinates":[13.392778,46.050278],"type":"Point"}
}