{
  "id": 2623197,
  "type": "Feature",
  "properties": {
    "tgn:hierarchy":[
        "tgn:2623197",
        "tgn:1000001",
        "tgn:2000269",
        "tgn:7012149",
        "tgn:7007240",
        "tgn:7029392"
    ],
    "tgn:id":2623197,
    "tgn:name":"Rock Bluff Spring",
    "tgn:placetype":[
        "aat:300008697"
    ]
},
  "bbox": [],
  "geometry": {"coordinates":[-82.9167,29.7833],"type":"Point"}
}