{
  "id": 7367603,
  "type": "Feature",
  "properties": {
    "tgn:hierarchy":[
        "tgn:7367603",
        "tgn:1000001",
        "tgn:7005594",
        "tgn:7005560",
        "tgn:7029392"
    ],
    "tgn:id":7367603,
    "tgn:name":"Estribera",
    "tgn:placetype":[
        "aat:300008347"
    ]
},
  "bbox": [],
  "geometry": {"coordinates":[-99.133333,22.166667],"type":"Point"}
}