{
  "id": 2399806,
  "type": "Feature",
  "properties": {
    "tgn:hierarchy":[
        "tgn:2399806",
        "tgn:1000001",
        "tgn:7012149",
        "tgn:1002980",
        "tgn:7007826",
        "tgn:7029392"
    ],
    "tgn:id":2399806,
    "tgn:name":"Horse Branch",
    "tgn:placetype":[
        "aat:300008699"
    ]
},
  "bbox": [],
  "geometry": {"coordinates":[-95.5333,30.7167],"type":"Point"}
}