{
  "id": 7117422,
  "type": "Feature",
  "properties": {
    "tgn:hierarchy":[
        "tgn:7117422",
        "tgn:1000003",
        "tgn:7003676",
        "tgn:7000084",
        "tgn:7029392"
    ],
    "tgn:id":7117422,
    "tgn:name":"Odingberger Bach",
    "tgn:placetype":[
        "aat:300008699"
    ]
},
  "bbox": [],
  "geometry": {"coordinates":[7.95,52.066667],"type":"Point"}
}