{
  "id": 7475091,
  "type": "Feature",
  "properties": {
    "tgn:hierarchy":[
        "tgn:7475091",
        "tgn:1000004",
        "tgn:7001014",
        "tgn:1000141",
        "tgn:7029392"
    ],
    "tgn:id":7475091,
    "tgn:name":"Tianwei Yihao Qiao",
    "tgn:placetype":[
        "aat:300007836"
    ]
},
  "bbox": [],
  "geometry": {"coordinates":[120.419022,23.758878],"type":"Point"}
}