{
  "id": 7581932,
  "type": "Feature",
  "properties": {
    "tgn:hierarchy":[
        "tgn:7581932",
        "tgn:1000004",
        "tgn:1001871",
        "tgn:7000198",
        "tgn:7029392"
    ],
    "tgn:id":7581932,
    "tgn:name:en":"Kh\u0101t\u012bw\u0101li Johri",
    "tgn:placetype":[
        "aat:300008688"
    ]
},
  "bbox": [],
  "geometry": {"coordinates":[75.598149,28.881392],"type":"Point"}
}