<<<<<<< HEAD
{
  "id": 2155975,
  "type": "Feature",
  "properties": {
    "tgn:hierarchy":[
        "tgn:2155975",
        "tgn:1000001",
        "tgn:7006451",
        "tgn:7012149",
        "tgn:2000099",
        "tgn:7029392"
    ],
    "tgn:id":2155975,
    "tgn:name":"Bear Wallow Canyon",
    "tgn:placetype":[
        "aat:300008761"
    ]
},
  "bbox": [],
  "geometry": {"coordinates":[-110.25,34.15],"type":"Point"}
}
=======
{"geometry":{"type":"Point","coordinates":[-110.250000,34.150000]},"type":"Feature","properties":{"hierarchy":["tgn:2155975","tgn:1000001","tgn:7006451","tgn:7012149","tgn:2000099","tgn:7029392"],"placetype":["aat:300008761"],"id":2155975,"name:xx":"Bear Wallow Canyon"}}
>>>>>>> 03f74aca74312dbeaf24d7e61306dd6a786dc3d0
