{
  "id": 2329290,
  "type": "Feature",
  "properties": {
    "tgn:hierarchy":[
        "tgn:2329290",
        "tgn:2001423",
        "tgn:1000001",
        "tgn:7012149",
        "tgn:7007564",
        "tgn:7029392"
    ],
    "tgn:id":2329290,
    "tgn:name":"Five Finger Point",
    "tgn:placetype":[
        "aat:300008850"
    ]
},
  "bbox": [],
  "geometry": {"coordinates":[-71.5167,43.7667],"type":"Point"}
}