{
  "id": 7296234,
  "type": "Feature",
  "properties": {
    "tgn:hierarchy":[
        "tgn:7296234",
        "tgn:7002758",
        "tgn:7002841",
        "tgn:1000003",
        "tgn:1000095",
        "tgn:7029392"
    ],
    "tgn:id":7296234,
    "tgn:name":"Horcada, Punta de la",
    "tgn:placetype":[
        "aat:300386846"
    ]
},
  "bbox": [],
  "geometry": {"coordinates":[-6.082778,37.078611],"type":"Point"}
}