{
  "id": 7068245,
  "type": "Feature",
  "properties": {
    "tgn:hierarchy":[
        "tgn:7068245",
        "tgn:7000096",
        "tgn:1000003",
        "tgn:7000084",
        "tgn:7029392"
    ],
    "tgn:id":7068245,
    "tgn:name":"Treppel-See",
    "tgn:placetype":[
        "aat:300008680"
    ]
},
  "bbox": [],
  "geometry": {"coordinates":[14.466667,52.15],"type":"Point"}
}