{
  "id": 1133816,
  "type": "Feature",
  "properties": {
    "tgn:hierarchy":[
        "tgn:1133816",
        "tgn:1000001",
        "tgn:7012149",
        "tgn:7007251",
        "tgn:7029392"
    ],
    "tgn:id":1133816,
    "tgn:name":"McCraney Creek",
    "tgn:placetype":[
        "aat:300008706"
    ]
},
  "bbox": [],
  "geometry": {"coordinates":[-91.0833,39.8833],"type":"Point"}
}