{
  "id": 7221615,
  "type": "Feature",
  "properties": {
    "tgn:hierarchy":[
        "tgn:7221615",
        "tgn:7002680",
        "tgn:7001395",
        "tgn:1000003",
        "tgn:1000074",
        "tgn:7029392"
    ],
    "tgn:id":7221615,
    "tgn:name":"Pan\u00f3rmou, \u00d3rmos",
    "tgn:placetype":[
        "aat:300132316"
    ]
},
  "bbox": [],
  "geometry": {"coordinates":[22.25,38.35],"type":"Point"}
}