{
  "id": 7436327,
  "type": "Feature",
  "properties": {
    "tgn:hierarchy":[
        "tgn:7436327",
        "tgn:7005578",
        "tgn:1000001",
        "tgn:7005560",
        "tgn:7029392"
    ],
    "tgn:id":7436327,
    "tgn:name":"Santo Domingo Pixal",
    "tgn:placetype":[
        "aat:300008347"
    ]
},
  "bbox": [],
  "geometry": {"coordinates":[-90.35,19.533333],"type":"Point"}
}