{
  "id": 7385192,
  "type": "Feature",
  "properties": {
    "tgn:hierarchy":[
        "tgn:7385192",
        "tgn:1000001",
        "tgn:7005601",
        "tgn:7005560",
        "tgn:7029392"
    ],
    "tgn:id":7385192,
    "tgn:name":"Palmillas",
    "tgn:placetype":[
        "aat:300008347"
    ]
},
  "bbox": [],
  "geometry": {"coordinates":[-102.35,22.65],"type":"Point"}
}