{
  "id": 2327434,
  "type": "Feature",
  "properties": {
    "tgn:hierarchy":[
        "tgn:2327434",
        "tgn:1000001",
        "tgn:2000470",
        "tgn:7012149",
        "tgn:7007250",
        "tgn:7029392"
    ],
    "tgn:id":2327434,
    "tgn:name":"First Spring Creek",
    "tgn:placetype":[
        "aat:300008706"
    ]
},
  "bbox": [],
  "geometry": {"coordinates":[-114.2333,44.6167],"type":"Point"}
}