{
  "id": 7361881,
  "type": "Feature",
  "properties": {
    "tgn:hierarchy":[
        "tgn:7361881",
        "tgn:1000001",
        "tgn:7005597",
        "tgn:7005560",
        "tgn:7029392"
    ],
    "tgn:id":7361881,
    "tgn:name":"Rancho El Capillo",
    "tgn:placetype":[
        "aat:300000241"
    ]
},
  "bbox": [],
  "geometry": {"coordinates":[-99.45,27.233333],"type":"Point"}
}