{
  "id": 2149392,
  "type": "Feature",
  "properties": {
    "tgn:hierarchy":[
        "tgn:2149392",
        "tgn:1000001",
        "tgn:7012149",
        "tgn:1002862",
        "tgn:7007920",
        "tgn:7029392"
    ],
    "tgn:id":2149392,
    "tgn:name":"Barren Island",
    "tgn:placetype":[
        "aat:300008791"
    ]
},
  "bbox": [],
  "geometry": {"coordinates":[-123.15,48.6167],"type":"Point"}
}