<<<<<<< HEAD
{
  "id": 2253302,
  "type": "Feature",
  "properties": {
    "tgn:hierarchy":[
        "tgn:2253302",
        "tgn:1000001",
        "tgn:7012149",
        "tgn:1002590",
        "tgn:7007826",
        "tgn:7029392"
    ],
    "tgn:id":2253302,
    "tgn:name":"Convict Branch",
    "tgn:placetype":[
        "aat:300008699"
    ]
},
  "bbox": [],
  "geometry": {"coordinates":[-95.8833,31.0833],"type":"Point"}
}
=======
{"geometry":{"type":"Point","coordinates":[-95.883300,31.083300]},"type":"Feature","properties":{"hierarchy":["tgn:2253302","tgn:1000001","tgn:7012149","tgn:1002590","tgn:7007826","tgn:7029392"],"placetype":["aat:300008699"],"id":2253302,"name:xx":"Convict Branch"}}
>>>>>>> 03f74aca74312dbeaf24d7e61306dd6a786dc3d0
