{
  "id": 2780652,
  "type": "Feature",
  "properties": {
    "tgn:hierarchy":[
        "tgn:2780652",
        "tgn:1000001",
        "tgn:7012149",
        "tgn:1002529",
        "tgn:7007520",
        "tgn:7029392"
    ],
    "tgn:id":2780652,
    "tgn:name":"Wood Lake",
    "tgn:placetype":[
        "aat:300008680"
    ]
},
  "bbox": [],
  "geometry": {"coordinates":[-85.3333,42.2667],"type":"Point"}
}