{
  "id": 2718820,
  "type": "Feature",
  "properties": {
    "tgn:hierarchy":[
        "tgn:2718820",
        "tgn:1000001",
        "tgn:7012149",
        "tgn:7007250",
        "tgn:7029392"
    ],
    "tgn:id":2718820,
    "tgn:name":"Thorn Creek Reservoir",
    "tgn:placetype":[
        "aat:300006191"
    ]
},
  "bbox": [],
  "geometry": {"coordinates":[-114.5833,43.1833],"type":"Point"}
}