{
  "id": 1007940,
  "type": "Feature",
  "properties": {
    "tgn:hierarchy":[
        "tgn:1007940",
        "tgn:1000004",
        "tgn:7002076",
        "tgn:1000111",
        "tgn:7029392"
    ],
    "tgn:id":1007940,
    "tgn:name":"Luxi Dao",
    "tgn:placetype":[
        "aat:300008791"
    ]
},
  "bbox": [],
  "geometry": {"coordinates":[121.1833,27.9833],"type":"Point"}
}