{
  "id": 2580557,
  "type": "Feature",
  "properties": {
    "tgn:hierarchy":[
        "tgn:2580557",
        "tgn:1000001",
        "tgn:7012149",
        "tgn:7007710",
        "tgn:7029392"
    ],
    "tgn:id":2580557,
    "tgn:name":"Pigeon Hills",
    "tgn:placetype":[
        "aat:300386831"
    ]
},
  "bbox": [],
  "geometry": {"coordinates":[-76.9333,39.8667],"type":"Point"}
}