{
  "id": 2011505,
  "type": "Feature",
  "properties": {
    "tgn:hierarchy":[
        "tgn:2011505",
        "tgn:1000001",
        "tgn:7012149",
        "tgn:7007157",
        "tgn:1002684",
        "tgn:7029392"
    ],
    "tgn:id":2011505,
    "tgn:name":"Gabilan Acres",
    "tgn:placetype":[
        "aat:300008347"
    ]
},
  "bbox": [],
  "geometry": {"coordinates":[-121.6167,36.75],"type":"Point"}
}