{
  "id": 2123134,
  "type": "Feature",
  "properties": {
    "tgn:hierarchy":[
        "tgn:2123134",
        "tgn:1000001",
        "tgn:7012149",
        "tgn:2002383",
        "tgn:7007923",
        "tgn:7029392"
    ],
    "tgn:id":2123134,
    "tgn:name":"Reliance",
    "tgn:placetype":[
        "aat:300008347"
    ]
},
  "bbox": [],
  "geometry": {"coordinates":[-109.1833,41.6667],"type":"Point"}
}