{
  "id": 2217540,
  "type": "Feature",
  "properties": {
    "tgn:hierarchy":[
        "tgn:2217540",
        "tgn:1000001",
        "tgn:2001737",
        "tgn:7012149",
        "tgn:7007712",
        "tgn:7029392"
    ],
    "tgn:id":2217540,
    "tgn:name":"Campbell Crossroads",
    "tgn:placetype":[
        "aat:300008347"
    ]
},
  "bbox": [],
  "geometry": {"coordinates":[-80.1667,34.6333],"type":"Point"}
}