<<<<<<< HEAD
{
  "id": 2159999,
  "type": "Feature",
  "properties": {
    "tgn:hierarchy":[
        "tgn:2159999",
        "tgn:1000001",
        "tgn:1002221",
        "tgn:7012149",
        "tgn:7007251",
        "tgn:7029392"
    ],
    "tgn:id":2159999,
    "tgn:name":"Beech Landing",
    "tgn:placetype":[
        "aat:300008347"
    ]
},
  "bbox": [],
  "geometry": {"coordinates":[-90.6667,38.9667],"type":"Point"}
}
=======
{"geometry":{"type":"Point","coordinates":[-90.666700,38.966700]},"type":"Feature","properties":{"hierarchy":["tgn:2159999","tgn:1000001","tgn:1002221","tgn:7012149","tgn:7007251","tgn:7029392"],"placetype":["aat:300008347"],"id":2159999,"name:xx":"Beech Landing"}}
>>>>>>> 03f74aca74312dbeaf24d7e61306dd6a786dc3d0
