{
  "id": 2342444,
  "type": "Feature",
  "properties": {
    "tgn:hierarchy":[
        "tgn:2342444",
        "tgn:1000001",
        "tgn:7012149",
        "tgn:1002749",
        "tgn:7007240",
        "tgn:7029392"
    ],
    "tgn:id":2342444,
    "tgn:name":"Fuller, Lake",
    "tgn:placetype":[
        "aat:300008680"
    ]
},
  "bbox": [],
  "geometry": {"coordinates":[-81.5167,28.65],"type":"Point"}
}