{
  "id": 2763645,
  "type": "Feature",
  "properties": {
    "tgn:hierarchy":[
        "tgn:2763645",
        "tgn:1000001",
        "tgn:7012149",
        "tgn:7014318",
        "tgn:7007568",
        "tgn:7029392"
    ],
    "tgn:id":2763645,
    "tgn:name":"Whalen Hill",
    "tgn:placetype":[
        "aat:300008798"
    ]
},
  "bbox": [],
  "geometry": {"coordinates":[-75.05,42.6833],"type":"Point"}
}