{
  "id": 2166265,
  "type": "Feature",
  "properties": {
    "tgn:hierarchy":[
        "tgn:2166265",
        "tgn:1000001",
        "tgn:7012149",
        "tgn:2001860",
        "tgn:7007825",
        "tgn:7029392"
    ],
    "tgn:id":2166265,
    "tgn:name":"Big Bell Estates Lake",
    "tgn:placetype":[
        "aat:300006191"
    ]
},
  "bbox": [],
  "geometry": {"coordinates":[-89.6167,35.1833],"type":"Point"}
}