{
  "id": 2284155,
  "type": "Feature",
  "properties": {
    "tgn:hierarchy":[
        "tgn:2284155",
        "tgn:1000001",
        "tgn:7012149",
        "tgn:7007157",
        "tgn:2000187",
        "tgn:7029392"
    ],
    "tgn:id":2284155,
    "tgn:name":"Denten Creek",
    "tgn:placetype":[
        "aat:300008706"
    ]
},
  "bbox": [],
  "geometry": {"coordinates":[-120.5833,39.7833],"type":"Point"}
}