{
  "id": 2281000,
  "type": "Feature",
  "properties": {
    "tgn:hierarchy":[
        "tgn:2281000",
        "tgn:1000001",
        "tgn:2001483",
        "tgn:7012149",
        "tgn:7007709",
        "tgn:7029392"
    ],
    "tgn:id":2281000,
    "tgn:name":"Deep Gap Branch",
    "tgn:placetype":[
        "aat:300008699"
    ]
},
  "bbox": [],
  "geometry": {"coordinates":[-83.5333,35.0333],"type":"Point"}
}