{
  "id": 2475765,
  "type": "Feature",
  "properties": {
    "tgn:hierarchy":[
        "tgn:2475765",
        "tgn:1000001",
        "tgn:7012149",
        "tgn:2001709",
        "tgn:7007708",
        "tgn:7029392"
    ],
    "tgn:id":2475765,
    "tgn:name":"Lucky Star Mine",
    "tgn:placetype":[
        "aat:300000390"
    ]
},
  "bbox": [],
  "geometry": {"coordinates":[-118.6667,42.3167],"type":"Point"}
}