{
  "id": 2340596,
  "type": "Feature",
  "properties": {
    "tgn:hierarchy":[
        "tgn:2340596",
        "tgn:1000001",
        "tgn:2001430",
        "tgn:7012149",
        "tgn:7007566",
        "tgn:7029392"
    ],
    "tgn:id":2340596,
    "tgn:name":"Frenchman Lake",
    "tgn:placetype":[
        "aat:300008680"
    ]
},
  "bbox": [],
  "geometry": {"coordinates":[-104.9833,32.7667],"type":"Point"}
}