{
  "id": 2294010,
  "type": "Feature",
  "properties": {
    "tgn:hierarchy":[
        "tgn:2294010",
        "tgn:1000001",
        "tgn:7012149",
        "tgn:2000516",
        "tgn:7007251",
        "tgn:7029392"
    ],
    "tgn:id":2294010,
    "tgn:name":"Douglass",
    "tgn:placetype":[
        "aat:300008347"
    ]
},
  "bbox": [],
  "geometry": {"coordinates":[-90.0833,40.7833],"type":"Point"}
}