{
  "id": 2362255,
  "type": "Feature",
  "properties": {
    "tgn:hierarchy":[
        "tgn:2362255",
        "tgn:1000001",
        "tgn:7012149",
        "tgn:2000429",
        "tgn:7007248",
        "tgn:7029392"
    ],
    "tgn:id":2362255,
    "tgn:name":"Grays Landing",
    "tgn:placetype":[
        "aat:300008347"
    ]
},
  "bbox": [],
  "geometry": {"coordinates":[-82.4333,31.9667],"type":"Point"}
}