{
  "id": 1014511,
  "type": "Feature",
  "properties": {
    "tgn:hierarchy":[
        "tgn:1014511",
        "tgn:7005685",
        "tgn:1000001",
        "tgn:7005802",
        "tgn:7029392"
    ],
    "tgn:id":1014511,
    "tgn:name":"Southampton",
    "tgn:placetype":[
        "aat:300008347"
    ]
},
  "bbox": [],
  "geometry": {"coordinates":[-64.35,45.5333],"type":"Point"}
}