{
  "id": 1060155,
  "type": "Feature",
  "properties": {
    "tgn:hierarchy":[
        "tgn:1060155",
        "tgn:1000004",
        "tgn:7011572",
        "tgn:7013394",
        "tgn:7018214",
        "tgn:7002435",
        "tgn:7029392"
    ],
    "tgn:id":1060155,
    "tgn:name":"Tarchovka",
    "tgn:placetype":[
        "aat:300008347"
    ]
},
  "bbox": [],
  "geometry": {"coordinates":[29.9667,60.0667],"type":"Point"}
}