{
  "id": 7289629,
  "type": "Feature",
  "properties": {
    "tgn:hierarchy":[
        "tgn:7289629",
        "tgn:1001708",
        "tgn:1000049",
        "tgn:1000002",
        "tgn:7029392"
    ],
    "tgn:id":7289629,
    "tgn:name":"El Rosario Arriba",
    "tgn:placetype":[
        "aat:300000206"
    ]
},
  "bbox": [],
  "geometry": {"coordinates":[-71.416667,-33.483333],"type":"Point"}
}