{
  "id": 2486264,
  "type": "Feature",
  "properties": {
    "tgn:hierarchy":[
        "tgn:2486264",
        "tgn:1000001",
        "tgn:2000459",
        "tgn:7012149",
        "tgn:7007250",
        "tgn:7029392"
    ],
    "tgn:id":2486264,
    "tgn:name":"Leary Placer Mine",
    "tgn:placetype":[
        "aat:300000390"
    ]
},
  "bbox": [],
  "geometry": {"coordinates":[-115.9167,43.9333],"type":"Point"}
}