{
  "id": 7486371,
  "type": "Feature",
  "properties": {
    "tgn:hierarchy":[
        "tgn:7486371",
        "tgn:1000004",
        "tgn:7001013",
        "tgn:1000141",
        "tgn:7029392"
    ],
    "tgn:id":7486371,
    "tgn:name":"Laofandian",
    "tgn:placetype":[
        "aat:300008347"
    ]
},
  "bbox": [],
  "geometry": {"coordinates":[121.122778,24.934167],"type":"Point"}
}