{
  "id": 7305456,
  "type": "Feature",
  "properties": {
    "tgn:hierarchy":[
        "tgn:7305456",
        "tgn:7002829",
        "tgn:1000003",
        "tgn:7002786",
        "tgn:1000095",
        "tgn:7029392"
    ],
    "tgn:id":7305456,
    "tgn:name":"Laroco",
    "tgn:placetype":[
        "aat:300008347"
    ]
},
  "bbox": [],
  "geometry": {"coordinates":[-7.166667,42.35],"type":"Point"}
}