{
  "id": 1058195,
  "type": "Feature",
  "properties": {
    "tgn:hierarchy":[
        "tgn:1058195",
        "tgn:1000004",
        "tgn:7011573",
        "tgn:7018214",
        "tgn:7002435",
        "tgn:7029392"
    ],
    "tgn:id":1058195,
    "tgn:name":"Pansionat",
    "tgn:placetype":[
        "aat:300008347"
    ]
},
  "bbox": [],
  "geometry": {"coordinates":[37.6833,55.9833],"type":"Point"}
}