{
  "id": 2271533,
  "type": "Feature",
  "properties": {
    "tgn:hierarchy":[
        "tgn:2271533",
        "tgn:1000001",
        "tgn:7012149",
        "tgn:7029392"
    ],
    "tgn:id":2271533,
    "tgn:name":"Cumberland Sound",
    "tgn:placetype":[
        "aat:300132316"
    ]
},
  "bbox": [],
  "geometry": {"coordinates":[-81.4833,30.7167],"type":"Point"}
}