{
  "id": 1092919,
  "type": "Feature",
  "properties": {
    "tgn:hierarchy":[
        "tgn:1092919",
        "tgn:7001242",
        "tgn:7017583",
        "tgn:1000193",
        "tgn:7029392"
    ],
    "tgn:id":1092919,
    "tgn:name":"Braunschweig",
    "tgn:placetype":[
        "aat:300008347"
    ]
},
  "bbox": [],
  "geometry": {"coordinates":[27.3833,-32.7833],"type":"Point"}
}