{
  "id": 7501521,
  "type": "Feature",
  "properties": {
    "tgn:hierarchy":[
        "tgn:7501521",
        "tgn:1000004",
        "tgn:7471332",
        "tgn:1000141",
        "tgn:7029392"
    ],
    "tgn:id":7501521,
    "tgn:name":"Rongshugang",
    "tgn:placetype":[
        "aat:300008347"
    ]
},
  "bbox": [],
  "geometry": {"coordinates":[120.980278,24.75],"type":"Point"}
}