{
  "id": 2076998,
  "type": "Feature",
  "properties": {
    "tgn:hierarchy":[
        "tgn:2076998",
        "tgn:1000001",
        "tgn:7012149",
        "tgn:2001515",
        "tgn:7007709",
        "tgn:7029392"
    ],
    "tgn:id":2076998,
    "tgn:name":"Union",
    "tgn:placetype":[
        "aat:300008347",
        "aat:300387210"
    ]
},
  "bbox": [],
  "geometry": {"coordinates":[-83.3833,35.1167],"type":"Point"}
}