<<<<<<< HEAD
{
  "id": 7240725,
  "type": "Feature",
  "properties": {
    "tgn:hierarchy":[
        "tgn:7240725",
        "tgn:7003460",
        "tgn:1000003",
        "tgn:1000063",
        "tgn:4012014",
        "tgn:7029392"
    ],
    "tgn:id":7240725,
    "tgn:name":"Filot",
    "tgn:placetype":[
        "aat:300008347"
    ]
},
  "bbox": [],
  "geometry": {"coordinates":[5.567359,50.425351],"type":"Point"}
}
=======
{"geometry":{"type":"Point","coordinates":[5.567359,50.425351]},"type":"Feature","properties":{"hierarchy":["tgn:7240725","tgn:7003460","tgn:1000003","tgn:1000063","tgn:4012014","tgn:7029392"],"placetype":["aat:300008347"],"id":7240725,"name:xx":"Filot"}}
>>>>>>> 03f74aca74312dbeaf24d7e61306dd6a786dc3d0
