{
  "id": 7227244,
  "type": "Feature",
  "properties": {
    "tgn:hierarchy":[
        "tgn:7227244",
        "tgn:7011170",
        "tgn:7002715",
        "tgn:1000003",
        "tgn:1000074",
        "tgn:7029392"
    ],
    "tgn:id":7227244,
    "tgn:name":"Ski\u00e1dha",
    "tgn:placetype":[
        "aat:300008347"
    ]
},
  "bbox": [],
  "geometry": {"coordinates":[25.616667,41.166667],"type":"Point"}
}