{
  "id": 7578651,
  "type": "Feature",
  "properties": {
    "tgn:hierarchy":[
        "tgn:7578651",
        "tgn:1000004",
        "tgn:7000198",
        "tgn:1001996",
        "tgn:7029392"
    ],
    "tgn:id":7578651,
    "tgn:name:en":"Sissu",
    "tgn:placetype":[
        "aat:300008347"
    ]
},
  "bbox": [],
  "geometry": {"coordinates":[77.129982,32.47391],"type":"Point"}
}