{
  "id": 2519217,
  "type": "Feature",
  "properties": {
    "tgn:hierarchy":[
        "tgn:2519217",
        "tgn:1000001",
        "tgn:7012149",
        "tgn:7007706",
        "tgn:7029392"
    ],
    "tgn:id":2519217,
    "tgn:name":"Moccasin Creek",
    "tgn:placetype":[
        "aat:300008706"
    ]
},
  "bbox": [],
  "geometry": {"coordinates":[-82.75,39.5667],"type":"Point"}
}