{
  "id": 2687749,
  "type": "Feature",
  "properties": {
    "tgn:hierarchy":[
        "tgn:2687749",
        "tgn:1000001",
        "tgn:7006451",
        "tgn:7012149",
        "tgn:2000103",
        "tgn:7029392"
    ],
    "tgn:id":2687749,
    "tgn:name":"Spring Tank",
    "tgn:placetype":[
        "aat:300006191"
    ]
},
  "bbox": [],
  "geometry": {"coordinates":[-111.95,34.2167],"type":"Point"}
}