<<<<<<< HEAD
{
  "id": 7366794,
  "type": "Feature",
  "properties": {
    "tgn:hierarchy":[
        "tgn:7366794",
        "tgn:1000001",
        "tgn:1001937",
        "tgn:7005560",
        "tgn:7029392"
    ],
    "tgn:id":7366794,
    "tgn:name":"El Placer",
    "tgn:placetype":[
        "aat:300008347"
    ]
},
  "bbox": [],
  "geometry": {"coordinates":[-87.6,19.0],"type":"Point"}
}
=======
{"geometry":{"type":"Point","coordinates":[-87.600000,19.000000]},"type":"Feature","properties":{"hierarchy":["tgn:7366794","tgn:1000001","tgn:1001937","tgn:7005560","tgn:7029392"],"placetype":["aat:300008347"],"id":7366794,"name:xx":"El Placer"}}
>>>>>>> 03f74aca74312dbeaf24d7e61306dd6a786dc3d0
