{
  "id": 7559128,
  "type": "Feature",
  "properties": {
    "tgn:hierarchy":[
        "tgn:7559128",
        "tgn:1000004",
        "tgn:7000198",
        "tgn:7000799",
        "tgn:7029392"
    ],
    "tgn:id":7559128,
    "tgn:name:en":"Rihom",
    "tgn:placetype":[
        "aat:300008347"
    ]
},
  "bbox": [],
  "geometry": {"coordinates":[74.354088,34.27349],"type":"Point"}
}