{
  "id": 1096172,
  "type": "Feature",
  "properties": {
    "tgn:hierarchy":[
        "tgn:1096172",
        "tgn:7000490",
        "tgn:1000006",
        "tgn:7006238",
        "tgn:7029392"
    ],
    "tgn:id":1096172,
    "tgn:name":"Balmoral",
    "tgn:placetype":[
        "aat:300008347"
    ]
},
  "bbox": [],
  "geometry": {"coordinates":[141.8333,-37.2833],"type":"Point"}
}