{
  "id": 2320111,
  "type": "Feature",
  "properties": {
    "tgn:hierarchy":[
        "tgn:2320111",
        "tgn:7002659",
        "tgn:1000001",
        "tgn:7012149",
        "tgn:2000065",
        "tgn:7029392"
    ],
    "tgn:id":2320111,
    "tgn:name":"Evans Lower Bar",
    "tgn:placetype":[
        "aat:300132348"
    ]
},
  "bbox": [],
  "geometry": {"coordinates":[-87.45,31.9667],"type":"Point"}
}