<<<<<<< HEAD
{
  "id": 7366626,
  "type": "Feature",
  "properties": {
    "tgn:hierarchy":[
        "tgn:7366626",
        "tgn:1001853",
        "tgn:1000001",
        "tgn:7005560",
        "tgn:7029392"
    ],
    "tgn:id":7366626,
    "tgn:name":"El Torito",
    "tgn:placetype":[
        "aat:300008347"
    ]
},
  "bbox": [],
  "geometry": {"coordinates":[-103.333333,25.383333],"type":"Point"}
}
=======
{"geometry":{"type":"Point","coordinates":[-103.333333,25.383333]},"type":"Feature","properties":{"hierarchy":["tgn:7366626","tgn:1001853","tgn:1000001","tgn:7005560","tgn:7029392"],"placetype":["aat:300008347"],"id":7366626,"name:xx":"El Torito"}}
>>>>>>> 03f74aca74312dbeaf24d7e61306dd6a786dc3d0
