{
  "id": 7497285,
  "type": "Feature",
  "properties": {
    "tgn:hierarchy":[
        "tgn:7497285",
        "tgn:1000004",
        "tgn:1000454",
        "tgn:1000141",
        "tgn:7029392"
    ],
    "tgn:id":7497285,
    "tgn:name":"Neiping",
    "tgn:placetype":[
        "aat:300008347"
    ]
},
  "bbox": [],
  "geometry": {"coordinates":[121.54735,25.221702],"type":"Point"}
}