{
  "id": 2783498,
  "type": "Feature",
  "properties": {
    "tgn:hierarchy":[
        "tgn:2783498",
        "tgn:1000001",
        "tgn:7012149",
        "tgn:2000967",
        "tgn:7007520",
        "tgn:7029392"
    ],
    "tgn:id":2783498,
    "tgn:name":"Wyant Drain",
    "tgn:placetype":[
        "aat:300006075"
    ]
},
  "bbox": [],
  "geometry": {"coordinates":[-84.7667,43.5167],"type":"Point"}
}