{
  "id": 7456259,
  "type": "Feature",
  "properties": {
    "tgn:hierarchy":[
        "tgn:7456259",
        "tgn:7002445",
        "tgn:7008116",
        "tgn:1000003",
        "tgn:7008591",
        "tgn:7029392"
    ],
    "tgn:id":7456259,
    "tgn:name:en":"Carn Base",
    "tgn:placetype":[
        "aat:300008808"
    ]
},
  "bbox": [],
  "geometry": {"coordinates":[-5.75,50.033333],"type":"Point"}
}