{
  "id": 2419395,
  "type": "Feature",
  "properties": {
    "tgn:hierarchy":[
        "tgn:2419395",
        "tgn:1000001",
        "tgn:7012149",
        "tgn:2001451",
        "tgn:7007566",
        "tgn:7029392"
    ],
    "tgn:id":2419395,
    "tgn:name":"Jara Creek, La",
    "tgn:placetype":[
        "aat:300008699"
    ]
},
  "bbox": [],
  "geometry": {"coordinates":[-106.55,35.8667],"type":"Point"}
}