{
  "id": 2371180,
  "type": "Feature",
  "properties": {
    "tgn:hierarchy":[
        "tgn:2371180",
        "tgn:1000001",
        "tgn:7012149",
        "tgn:2000475",
        "tgn:7007250",
        "tgn:7029392"
    ],
    "tgn:id":2371180,
    "tgn:name":"Hagerman Wildlife Management Area",
    "tgn:placetype":[
        "aat:300008178"
    ]
},
  "bbox": [],
  "geometry": {"coordinates":[-114.8667,42.7667],"type":"Point"}
}