{
  "id": 2176250,
  "type": "Feature",
  "properties": {
    "tgn:hierarchy":[
        "tgn:2176250",
        "tgn:1000001",
        "tgn:7006451",
        "tgn:7012149",
        "tgn:2000101",
        "tgn:7029392"
    ],
    "tgn:id":2176250,
    "tgn:name":"Black Hills Mine",
    "tgn:placetype":[
        "aat:300000390"
    ]
},
  "bbox": [],
  "geometry": {"coordinates":[-110.5333,32.5333],"type":"Point"}
}