{
  "id": 7444311,
  "type": "Feature",
  "properties": {
    "tgn:hierarchy":[
        "tgn:7444311",
        "tgn:7002445",
        "tgn:1000003",
        "tgn:7008178",
        "tgn:7008591",
        "tgn:7029392"
    ],
    "tgn:id":7444311,
    "tgn:name:en":"Wroxall",
    "tgn:placetype":[
        "aat:300008347"
    ]
},
  "bbox": [],
  "geometry": {"coordinates":[-1.666667,52.316667],"type":"Point"}
}