{
  "id": 7337144,
  "type": "Feature",
  "properties": {
    "tgn:hierarchy":[
        "tgn:7337144",
        "tgn:7002829",
        "tgn:1000003",
        "tgn:7002786",
        "tgn:1000095",
        "tgn:7029392"
    ],
    "tgn:id":7337144,
    "tgn:name":"Coelleira, Isla",
    "tgn:placetype":[
        "aat:300008791"
    ]
},
  "bbox": [],
  "geometry": {"coordinates":[-7.616667,43.766667],"type":"Point"}
}