{
  "id": 2379930,
  "type": "Feature",
  "properties": {
    "tgn:hierarchy":[
        "tgn:2379930",
        "tgn:1000001",
        "tgn:7012149",
        "tgn:1002817",
        "tgn:7007523",
        "tgn:7029392"
    ],
    "tgn:id":2379930,
    "tgn:name":"Hatch",
    "tgn:placetype":[
        "aat:300008347"
    ]
},
  "bbox": [],
  "geometry": {"coordinates":[-91.6167,39.5833],"type":"Point"}
}