{
  "id": 7522630,
  "type": "Feature",
  "properties": {
    "tgn:hierarchy":[
        "tgn:7522630",
        "tgn:7001242",
        "tgn:7016833",
        "tgn:1001335",
        "tgn:7029392"
    ],
    "tgn:id":7522630,
    "tgn:name:en":"Ar Ray\u0101yinah",
    "tgn:placetype":[
        "aat:300008347"
    ]
},
  "bbox": [],
  "geometry": {"coordinates":[30.952508,31.009395],"type":"Point"}
}