{
  "id": 7409655,
  "type": "Feature",
  "properties": {
    "tgn:hierarchy":[
        "tgn:7409655",
        "tgn:1000001",
        "tgn:1001893",
        "tgn:7005560",
        "tgn:7029392"
    ],
    "tgn:id":7409655,
    "tgn:name":"El Aguacate",
    "tgn:placetype":[
        "aat:300008347"
    ]
},
  "bbox": [],
  "geometry": {"coordinates":[-100.35,19.208333],"type":"Point"}
}