{
  "id": 2282501,
  "type": "Feature",
  "properties": {
    "tgn:hierarchy":[
        "tgn:2282501",
        "tgn:1000001",
        "tgn:7012149",
        "tgn:1002961",
        "tgn:7007568",
        "tgn:7029392"
    ],
    "tgn:id":2282501,
    "tgn:name":"Deer Shanty Brook",
    "tgn:placetype":[
        "aat:300008699"
    ]
},
  "bbox": [],
  "geometry": {"coordinates":[-74.3833,41.9833],"type":"Point"}
}