{
  "id": 2482357,
  "type": "Feature",
  "properties": {
    "tgn:hierarchy":[
        "tgn:2482357",
        "tgn:7002659",
        "tgn:1000001",
        "tgn:7012149",
        "tgn:2000028",
        "tgn:7029392"
    ],
    "tgn:id":2482357,
    "tgn:name":"Langston Creek",
    "tgn:placetype":[
        "aat:300008706"
    ]
},
  "bbox": [],
  "geometry": {"coordinates":[-87.8833,33.85],"type":"Point"}
}