{
  "id": 7473497,
  "type": "Feature",
  "properties": {
    "tgn:hierarchy":[
        "tgn:7473497",
        "tgn:7001010",
        "tgn:1000004",
        "tgn:1000141",
        "tgn:7029392"
    ],
    "tgn:id":7473497,
    "tgn:name":"Yan Shan",
    "tgn:placetype":[
        "aat:300008798"
    ]
},
  "bbox": [],
  "geometry": {"coordinates":[121.283889,24.005278],"type":"Point"}
}