{
  "id": 7590126,
  "type": "Feature",
  "properties": {
    "tgn:hierarchy":[
        "tgn:7590126",
        "tgn:1000004",
        "tgn:7000198",
        "tgn:7000799",
        "tgn:7029392"
    ],
    "tgn:id":7590126,
    "tgn:name:en":"Phagw\u0101ri",
    "tgn:placetype":[
        "aat:300008347"
    ]
},
  "bbox": [],
  "geometry": {"coordinates":[74.273344,33.834735],"type":"Point"}
}