{
  "id": 1082282,
  "type": "Feature",
  "properties": {
    "tgn:hierarchy":[
        "tgn:1082282",
        "tgn:1000004",
        "tgn:1001372",
        "tgn:7000299",
        "tgn:7029392"
    ],
    "tgn:id":1082282,
    "tgn:name":"Kuryongp'o",
    "tgn:placetype":[
        "aat:300008347"
    ]
},
  "bbox": [],
  "geometry": {"coordinates":[129.5667,35.9833],"type":"Point"}
}