{
  "id": 7589763,
  "type": "Feature",
  "properties": {
    "tgn:hierarchy":[
        "tgn:7589763",
        "tgn:1000004",
        "tgn:7000198",
        "tgn:7016883",
        "tgn:7029392"
    ],
    "tgn:id":7589763,
    "tgn:name:en":"B\u012br Kishan Singh",
    "tgn:placetype":[
        "aat:300008347"
    ]
},
  "bbox": [],
  "geometry": {"coordinates":[76.110249,30.699809],"type":"Point"}
}