<<<<<<< HEAD
{
  "id": 2765445,
  "type": "Feature",
  "properties": {
    "tgn:hierarchy":[
        "tgn:2765445",
        "tgn:1000001",
        "tgn:7012149",
        "tgn:1002974",
        "tgn:7007251",
        "tgn:7029392"
    ],
    "tgn:id":2765445,
    "tgn:name":"White Branch",
    "tgn:placetype":[
        "aat:300008699"
    ]
},
  "bbox": [],
  "geometry": {"coordinates":[-87.5333,40.0333],"type":"Point"}
}
=======
{"geometry":{"type":"Point","coordinates":[-87.533300,40.033300]},"type":"Feature","properties":{"hierarchy":["tgn:2765445","tgn:1000001","tgn:7012149","tgn:1002974","tgn:7007251","tgn:7029392"],"placetype":["aat:300008699"],"id":2765445,"name:xx":"White Branch"}}
>>>>>>> 03f74aca74312dbeaf24d7e61306dd6a786dc3d0
