{
  "id": 2210840,
  "type": "Feature",
  "properties": {
    "tgn:hierarchy":[
        "tgn:2210840",
        "tgn:1000001",
        "tgn:7012149",
        "tgn:2001764",
        "tgn:7007712",
        "tgn:7029392"
    ],
    "tgn:id":2210840,
    "tgn:name":"Butchertown",
    "tgn:placetype":[
        "aat:300008347"
    ]
},
  "bbox": [],
  "geometry": {"coordinates":[-81.0333,34.0167],"type":"Point"}
}