{
  "id": 2496256,
  "type": "Feature",
  "properties": {
    "tgn:hierarchy":[
        "tgn:2496256",
        "tgn:1000001",
        "tgn:2001429",
        "tgn:7012149",
        "tgn:7007566",
        "tgn:7029392"
    ],
    "tgn:id":2496256,
    "tgn:name":"Mata Spring",
    "tgn:placetype":[
        "aat:300008697"
    ]
},
  "bbox": [],
  "geometry": {"coordinates":[-108.5833,33.9667],"type":"Point"}
}