{
  "id": 2076819,
  "type": "Feature",
  "properties": {
    "tgn:hierarchy":[
        "tgn:2076819",
        "tgn:1000001",
        "tgn:7012149",
        "tgn:2001488",
        "tgn:7007709",
        "tgn:7029392"
    ],
    "tgn:id":2076819,
    "tgn:name":"Stumpy Point",
    "tgn:placetype":[
        "aat:300008347"
    ]
},
  "bbox": [],
  "geometry": {"coordinates":[-75.7333,35.6833],"type":"Point"}
}