<<<<<<< HEAD
{
  "id": 7360658,
  "type": "Feature",
  "properties": {
    "tgn:hierarchy":[
        "tgn:7360658",
        "tgn:1000001",
        "tgn:7005594",
        "tgn:7005560",
        "tgn:7029392"
    ],
    "tgn:id":7360658,
    "tgn:name":"Corcovado",
    "tgn:placetype":[
        "aat:300008347"
    ]
},
  "bbox": [],
  "geometry": {"coordinates":[-100.716667,22.4],"type":"Point"}
}
=======
{"geometry":{"type":"Point","coordinates":[-100.716667,22.400000]},"type":"Feature","properties":{"hierarchy":["tgn:7360658","tgn:1000001","tgn:7005594","tgn:7005560","tgn:7029392"],"placetype":["aat:300008347"],"id":7360658,"name:xx":"Corcovado"}}
>>>>>>> 03f74aca74312dbeaf24d7e61306dd6a786dc3d0
