{
  "id": 1020156,
  "type": "Feature",
  "properties": {
    "tgn:hierarchy":[
        "tgn:1020156",
        "tgn:7006477",
        "tgn:1001169",
        "tgn:1000002",
        "tgn:7029392"
    ],
    "tgn:id":1020156,
    "tgn:name":"Vicu\u00f1a Mackenna",
    "tgn:placetype":[
        "aat:300008347"
    ]
},
  "bbox": [],
  "geometry": {"coordinates":[-64.4167,-33.8833],"type":"Point"}
}