{
  "id": 1109486,
  "type": "Feature",
  "properties": {
    "tgn:hierarchy":[
        "tgn:1109486",
        "tgn:1000003",
        "tgn:7006667",
        "tgn:7029392"
    ],
    "tgn:id":1109486,
    "tgn:name":"Plackovica",
    "tgn:placetype":[
        "aat:300008795"
    ]
},
  "bbox": [],
  "geometry": {"coordinates":[22.5333,41.7667],"type":"Point"}
}