<<<<<<< HEAD
{
  "id": 2401596,
  "type": "Feature",
  "properties": {
    "tgn:hierarchy":[
        "tgn:2401596",
        "tgn:1000001",
        "tgn:7012149",
        "tgn:2001275",
        "tgn:7007524",
        "tgn:7029392"
    ],
    "tgn:id":2401596,
    "tgn:name":"Horseshoe Hills",
    "tgn:placetype":[
        "aat:300008697"
    ]
},
  "bbox": [],
  "geometry": {"coordinates":[-111.2667,46.0167],"type":"Point"}
}
=======
{"geometry":{"type":"Point","coordinates":[-111.266700,46.016700]},"type":"Feature","properties":{"hierarchy":["tgn:2401596","tgn:1000001","tgn:7012149","tgn:2001275","tgn:7007524","tgn:7029392"],"placetype":["aat:300008697"],"id":2401596,"name:xx":"Horseshoe Hills"}}
>>>>>>> 03f74aca74312dbeaf24d7e61306dd6a786dc3d0
