{
  "id": 2563623,
  "type": "Feature",
  "properties": {
    "tgn:hierarchy":[
        "tgn:2563623",
        "tgn:1000001",
        "tgn:2002135",
        "tgn:7012149",
        "tgn:7007828",
        "tgn:7029392"
    ],
    "tgn:id":2563623,
    "tgn:name":"Owlshead Mountain",
    "tgn:placetype":[
        "aat:300008798"
    ]
},
  "bbox": [],
  "geometry": {"coordinates":[-72.6833,44.3333],"type":"Point"}
}