{
  "id": 2557237,
  "type": "Feature",
  "properties": {
    "tgn:hierarchy":[
        "tgn:2557237",
        "tgn:7006450",
        "tgn:1000001",
        "tgn:7012149",
        "tgn:2000089",
        "tgn:7029392"
    ],
    "tgn:id":2557237,
    "tgn:name":"Old John Lake",
    "tgn:placetype":[
        "aat:300008680"
    ]
},
  "bbox": [],
  "geometry": {"coordinates":[-145.05,68.0667],"type":"Point"}
}