<<<<<<< HEAD
{
  "id": 7350580,
  "type": "Feature",
  "properties": {
    "tgn:hierarchy":[
        "tgn:7350580",
        "tgn:1000001",
        "tgn:7005594",
        "tgn:7005560",
        "tgn:7029392"
    ],
    "tgn:id":7350580,
    "tgn:name":"Blanco",
    "tgn:placetype":[
        "aat:300008347"
    ]
},
  "bbox": [],
  "geometry": {"coordinates":[-100.75,23.75],"type":"Point"}
}
=======
{"geometry":{"type":"Point","coordinates":[-100.750000,23.750000]},"type":"Feature","properties":{"hierarchy":["tgn:7350580","tgn:1000001","tgn:7005594","tgn:7005560","tgn:7029392"],"placetype":["aat:300008347"],"id":7350580,"name:xx":"Blanco"}}
>>>>>>> 03f74aca74312dbeaf24d7e61306dd6a786dc3d0
