{
  "id": 2569300,
  "type": "Feature",
  "properties": {
    "tgn:hierarchy":[
        "tgn:2569300",
        "tgn:1000001",
        "tgn:7012149",
        "tgn:2000834",
        "tgn:7007255",
        "tgn:7029392"
    ],
    "tgn:id":2569300,
    "tgn:name":"Parks Ridge",
    "tgn:placetype":[
        "aat:300266640"
    ]
},
  "bbox": [],
  "geometry": {"coordinates":[-86.8833,37.5167],"type":"Point"}
}