<<<<<<< HEAD
{
  "id": 7022432,
  "type": "Feature",
  "properties": {
    "tgn:hierarchy":[
        "tgn:7022432",
        "tgn:1000001",
        "tgn:7012149",
        "tgn:7007825",
        "tgn:7029392"
    ],
    "tgn:id":7022432,
    "tgn:name":"Breeden Branch",
    "tgn:placetype":[
        "aat:300008699"
    ]
},
  "bbox": [],
  "geometry": {"coordinates":[-83.2333,35.8833],"type":"Point"}
}
=======
{"geometry":{"type":"Point","coordinates":[-83.233300,35.883300]},"type":"Feature","properties":{"hierarchy":["tgn:7022432","tgn:1000001","tgn:7012149","tgn:7007825","tgn:7029392"],"placetype":["aat:300008699"],"id":7022432,"name:xx":"Breeden Branch"}}
>>>>>>> 03f74aca74312dbeaf24d7e61306dd6a786dc3d0
