{
  "id": 7022432,
  "type": "Feature",
  "properties": {
    "tgn:hierarchy":[
        "tgn:7022432",
        "tgn:1000001",
        "tgn:7012149",
        "tgn:7007825",
        "tgn:7029392"
    ],
    "tgn:id":7022432,
    "tgn:name":"Breeden Branch",
    "tgn:placetype":[
        "aat:300008699"
    ]
},
  "bbox": [],
  "geometry": {"coordinates":[-83.2333,35.8833],"type":"Point"}
}