{
  "id": 2682750,
  "type": "Feature",
  "properties": {
    "tgn:hierarchy":[
        "tgn:2682750",
        "tgn:1000001",
        "tgn:7012149",
        "tgn:2001442",
        "tgn:7007566",
        "tgn:7029392"
    ],
    "tgn:id":2682750,
    "tgn:name":"Southwest 1 Tank",
    "tgn:placetype":[
        "aat:300006191"
    ]
},
  "bbox": [],
  "geometry": {"coordinates":[-105.4667,33.55],"type":"Point"}
}