{
  "id": 2293803,
  "type": "Feature",
  "properties": {
    "tgn:hierarchy":[
        "tgn:2293803",
        "tgn:7006450",
        "tgn:1000001",
        "tgn:7012149",
        "tgn:2000086",
        "tgn:7029392"
    ],
    "tgn:id":2293803,
    "tgn:name":"Doughton Peak",
    "tgn:placetype":[
        "aat:300008798"
    ]
},
  "bbox": [],
  "geometry": {"coordinates":[-143.8833,60.4333],"type":"Point"}
}