{
  "id": 7523422,
  "type": "Feature",
  "properties": {
    "tgn:hierarchy":[
        "tgn:7523422",
        "tgn:7001242",
        "tgn:1001075",
        "tgn:7016833",
        "tgn:7029392"
    ],
    "tgn:id":7523422,
    "tgn:name:en":"A\u015f \u015eaf\u0101\u015f\u012bf",
    "tgn:placetype":[
        "aat:300008347"
    ]
},
  "bbox": [],
  "geometry": {"coordinates":[30.391493,31.010424],"type":"Point"}
}