{
  "id": 2471758,
  "type": "Feature",
  "properties": {
    "tgn:hierarchy":[
        "tgn:2471758",
        "tgn:1000001",
        "tgn:7012149",
        "tgn:2000210",
        "tgn:7007158",
        "tgn:7029392"
    ],
    "tgn:id":2471758,
    "tgn:name":"Lost Reservoir Number Two",
    "tgn:placetype":[
        "aat:300006191"
    ]
},
  "bbox": [],
  "geometry": {"coordinates":[-106.5667,39.6667],"type":"Point"}
}