{
  "id": 1138852,
  "type": "Feature",
  "properties": {
    "tgn:hierarchy":[
        "tgn:1138852",
        "tgn:7002075",
        "tgn:1000004",
        "tgn:1000111",
        "tgn:7029392"
    ],
    "tgn:id":1138852,
    "tgn:name":"Daguan",
    "tgn:placetype":[
        "aat:300008347"
    ]
},
  "bbox": [],
  "geometry": {"coordinates":[117.0167,31.2167],"type":"Point"}
}