{
  "id": 2445538,
  "type": "Feature",
  "properties": {
    "tgn:hierarchy":[
        "tgn:2445538",
        "tgn:1000001",
        "tgn:7012149",
        "tgn:2000210",
        "tgn:7007158",
        "tgn:7029392"
    ],
    "tgn:id":2445538,
    "tgn:name":"Leon",
    "tgn:placetype":[
        "aat:300008347"
    ]
},
  "bbox": [],
  "geometry": {"coordinates":[-107.0833,39.3833],"type":"Point"}
}