{
  "id": 7078248,
  "type": "Feature",
  "properties": {
    "tgn:hierarchy":[
        "tgn:7078248",
        "tgn:1000003",
        "tgn:7003689",
        "tgn:7000084",
        "tgn:7029392"
    ],
    "tgn:id":7078248,
    "tgn:name":"Zw\u00e4tzen",
    "tgn:placetype":[
        "aat:300008347"
    ]
},
  "bbox": [],
  "geometry": {"coordinates":[11.616667,50.966667],"type":"Point"}
}