{
  "id": 2171008,
  "type": "Feature",
  "properties": {
    "tgn:hierarchy":[
        "tgn:2171008",
        "tgn:1000001",
        "tgn:7006451",
        "tgn:7012149",
        "tgn:2000099",
        "tgn:7029392"
    ],
    "tgn:id":2171008,
    "tgn:name":"Big Spring",
    "tgn:placetype":[
        "aat:300008697"
    ]
},
  "bbox": [],
  "geometry": {"coordinates":[-109.9833,34.0833],"type":"Point"}
}