{
  "id": 2238064,
  "type": "Feature",
  "properties": {
    "tgn:hierarchy":[
        "tgn:2238064",
        "tgn:7002659",
        "tgn:1000001",
        "tgn:7012149",
        "tgn:2000038",
        "tgn:7029392"
    ],
    "tgn:id":2238064,
    "tgn:name":"Chisholm Hills",
    "tgn:placetype":[
        "aat:300008347"
    ]
},
  "bbox": [],
  "geometry": {"coordinates":[-87.6667,34.85],"type":"Point"}
}