{
  "id": 7332540,
  "type": "Feature",
  "properties": {
    "tgn:hierarchy":[
        "tgn:7332540",
        "tgn:7002758",
        "tgn:7002821",
        "tgn:1000003",
        "tgn:1000095",
        "tgn:7029392"
    ],
    "tgn:id":7332540,
    "tgn:name":"La Amarguilla",
    "tgn:placetype":[
        "aat:300008347"
    ]
},
  "bbox": [],
  "geometry": {"coordinates":[-2.616667,37.55],"type":"Point"}
}