{
  "id": 7523192,
  "type": "Feature",
  "properties": {
    "tgn:hierarchy":[
        "tgn:7523192",
        "tgn:7001242",
        "tgn:7001311",
        "tgn:7016833",
        "tgn:7029392"
    ],
    "tgn:id":7523192,
    "tgn:name":"Dubb, Ra's",
    "tgn:placetype":[
        "aat:300386846"
    ]
},
  "bbox": [],
  "geometry": {"coordinates":[33.415873,28.03184],"type":"Point"}
}