{
  "id": 2493566,
  "type": "Feature",
  "properties": {
    "tgn:hierarchy":[
        "tgn:2493566",
        "tgn:1000001",
        "tgn:7012149",
        "tgn:2000213",
        "tgn:7007158",
        "tgn:7029392"
    ],
    "tgn:id":2493566,
    "tgn:name":"Marsh Gulch",
    "tgn:placetype":[
        "aat:300008761"
    ]
},
  "bbox": [],
  "geometry": {"coordinates":[-105.3667,39.3667],"type":"Point"}
}