{
  "id": 2570418,
  "type": "Feature",
  "properties": {
    "tgn:hierarchy":[
        "tgn:2570418",
        "tgn:1000001",
        "tgn:7012149",
        "tgn:7007920",
        "tgn:7029392"
    ],
    "tgn:id":2570418,
    "tgn:name":"Patchen Creek",
    "tgn:placetype":[
        "aat:300008706"
    ]
},
  "bbox": [],
  "geometry": {"coordinates":[-117.5333,48.6667],"type":"Point"}
}