{
  "id": 2422712,
  "type": "Feature",
  "properties": {
    "tgn:hierarchy":[
        "tgn:2422712",
        "tgn:2002101",
        "tgn:1000001",
        "tgn:7012149",
        "tgn:7007827",
        "tgn:7029392"
    ],
    "tgn:id":2422712,
    "tgn:name":"Jockey Spring",
    "tgn:placetype":[
        "aat:300008697"
    ]
},
  "bbox": [],
  "geometry": {"coordinates":[-113.5333,38.1667],"type":"Point"}
}