<<<<<<< HEAD
{
  "id": 7176558,
  "type": "Feature",
  "properties": {
    "tgn:hierarchy":[
        "tgn:7176558",
        "tgn:7003669",
        "tgn:1000003",
        "tgn:7000084",
        "tgn:7029392"
    ],
    "tgn:id":7176558,
    "tgn:name":"Gutwiesen",
    "tgn:placetype":[
        "aat:300008347"
    ]
},
  "bbox": [],
  "geometry": {"coordinates":[13.5,48.666667],"type":"Point"}
}
=======
{"geometry":{"type":"Point","coordinates":[13.500000,48.666667]},"type":"Feature","properties":{"hierarchy":["tgn:7176558","tgn:7003669","tgn:1000003","tgn:7000084","tgn:7029392"],"placetype":["aat:300008347"],"id":7176558,"name:xx":"Gutwiesen"}}
>>>>>>> 03f74aca74312dbeaf24d7e61306dd6a786dc3d0
