{
  "id": 1049685,
  "type": "Feature",
  "properties": {
    "tgn:hierarchy":[
        "tgn:1049685",
        "tgn:7003825",
        "tgn:1000003",
        "tgn:1000090",
        "tgn:7029392"
    ],
    "tgn:id":1049685,
    "tgn:name":"Alter do Ch\u00e3o",
    "tgn:placetype":[
        "aat:300008347"
    ]
},
  "bbox": [],
  "geometry": {"coordinates":[-7.658,39.198],"type":"Point"}
}