{
  "id": 7222289,
  "type": "Feature",
  "properties": {
    "tgn:hierarchy":[
        "tgn:7222289",
        "tgn:7002711",
        "tgn:7001338",
        "tgn:1000003",
        "tgn:1000074",
        "tgn:7029392"
    ],
    "tgn:id":7222289,
    "tgn:name":"Odyss\u00e9os, Nis\u00eds",
    "tgn:placetype":[
        "aat:300008791"
    ]
},
  "bbox": [],
  "geometry": {"coordinates":[19.917778,39.586944],"type":"Point"}
}