<<<<<<< HEAD
{
  "id": 7176849,
  "type": "Feature",
  "properties": {
    "tgn:hierarchy":[
        "tgn:7176849",
        "tgn:1000003",
        "tgn:7003678",
        "tgn:7000084",
        "tgn:7029392"
    ],
    "tgn:id":7176849,
    "tgn:name":"Haardt",
    "tgn:placetype":[
        "aat:300008777"
    ]
},
  "bbox": [],
  "geometry": {"coordinates":[9.05,50.35],"type":"Point"}
}
=======
{"geometry":{"type":"Point","coordinates":[9.050000,50.350000]},"type":"Feature","properties":{"hierarchy":["tgn:7176849","tgn:1000003","tgn:7003678","tgn:7000084","tgn:7029392"],"placetype":["aat:300008777"],"id":7176849,"name:xx":"Haardt"}}
>>>>>>> 03f74aca74312dbeaf24d7e61306dd6a786dc3d0
