{
  "id": 7176849,
  "type": "Feature",
  "properties": {
    "tgn:hierarchy":[
        "tgn:7176849",
        "tgn:1000003",
        "tgn:7003678",
        "tgn:7000084",
        "tgn:7029392"
    ],
    "tgn:id":7176849,
    "tgn:name":"Haardt",
    "tgn:placetype":[
        "aat:300008777"
    ]
},
  "bbox": [],
  "geometry": {"coordinates":[9.05,50.35],"type":"Point"}
}