{
  "id": 2332065,
  "type": "Feature",
  "properties": {
    "tgn:hierarchy":[
        "tgn:2332065",
        "tgn:1000001",
        "tgn:7012149",
        "tgn:2001151",
        "tgn:7007522",
        "tgn:7029392"
    ],
    "tgn:id":2332065,
    "tgn:name":"Flint Creek Reservoir",
    "tgn:placetype":[
        "aat:300006191"
    ]
},
  "bbox": [],
  "geometry": {"coordinates":[-89.1167,30.8667],"type":"Point"}
}