<<<<<<< HEAD
{
  "id": 2332065,
  "type": "Feature",
  "properties": {
    "tgn:hierarchy":[
        "tgn:2332065",
        "tgn:1000001",
        "tgn:7012149",
        "tgn:2001151",
        "tgn:7007522",
        "tgn:7029392"
    ],
    "tgn:id":2332065,
    "tgn:name":"Flint Creek Reservoir",
    "tgn:placetype":[
        "aat:300006191"
    ]
},
  "bbox": [],
  "geometry": {"coordinates":[-89.1167,30.8667],"type":"Point"}
}
=======
{"geometry":{"type":"Point","coordinates":[-89.116700,30.866700]},"type":"Feature","properties":{"hierarchy":["tgn:2332065","tgn:1000001","tgn:7012149","tgn:2001151","tgn:7007522","tgn:7029392"],"placetype":["aat:300006191"],"id":2332065,"name:xx":"Flint Creek Reservoir"}}
>>>>>>> 03f74aca74312dbeaf24d7e61306dd6a786dc3d0
