{
  "id": 2536650,
  "type": "Feature",
  "properties": {
    "tgn:hierarchy":[
        "tgn:2536650",
        "tgn:1000001",
        "tgn:7012149",
        "tgn:7021277",
        "tgn:7007707",
        "tgn:7029392"
    ],
    "tgn:id":2536650,
    "tgn:name":"Nebo, Mount",
    "tgn:placetype":[
        "aat:300008798"
    ]
},
  "bbox": [],
  "geometry": {"coordinates":[-95.3667,35.4667],"type":"Point"}
}