{
  "id": 2406143,
  "type": "Feature",
  "properties": {
    "tgn:hierarchy":[
        "tgn:2406143",
        "tgn:1000001",
        "tgn:7006451",
        "tgn:7012149",
        "tgn:2000097",
        "tgn:7029392"
    ],
    "tgn:id":2406143,
    "tgn:name":"Hummingbird Spring",
    "tgn:placetype":[
        "aat:300008697"
    ]
},
  "bbox": [],
  "geometry": {"coordinates":[-113.0667,33.65],"type":"Point"}
}