<<<<<<< HEAD
{
  "id": 2406143,
  "type": "Feature",
  "properties": {
    "tgn:hierarchy":[
        "tgn:2406143",
        "tgn:1000001",
        "tgn:7006451",
        "tgn:7012149",
        "tgn:2000097",
        "tgn:7029392"
    ],
    "tgn:id":2406143,
    "tgn:name":"Hummingbird Spring",
    "tgn:placetype":[
        "aat:300008697"
    ]
},
  "bbox": [],
  "geometry": {"coordinates":[-113.0667,33.65],"type":"Point"}
}
=======
{"geometry":{"type":"Point","coordinates":[-113.066700,33.650000]},"type":"Feature","properties":{"hierarchy":["tgn:2406143","tgn:1000001","tgn:7006451","tgn:7012149","tgn:2000097","tgn:7029392"],"placetype":["aat:300008697"],"id":2406143,"name:xx":"Hummingbird Spring"}}
>>>>>>> 03f74aca74312dbeaf24d7e61306dd6a786dc3d0
