{
  "id": 2228265,
  "type": "Feature",
  "properties": {
    "tgn:hierarchy":[
        "tgn:2228265",
        "tgn:1000001",
        "tgn:7012149",
        "tgn:7007157",
        "tgn:1002608",
        "tgn:7029392"
    ],
    "tgn:id":2228265,
    "tgn:name":"Cedar Creek",
    "tgn:placetype":[
        "aat:300008706"
    ]
},
  "bbox": [],
  "geometry": {"coordinates":[-117.8167,34.3333],"type":"Point"}
}