{
  "id": 2735356,
  "type": "Feature",
  "properties": {
    "tgn:hierarchy":[
        "tgn:2735356",
        "tgn:1000001",
        "tgn:7012149",
        "tgn:7007157",
        "tgn:2000188",
        "tgn:7029392"
    ],
    "tgn:id":2735356,
    "tgn:name":"Twin Buttes",
    "tgn:placetype":[
        "aat:300008798"
    ]
},
  "bbox": [],
  "geometry": {"coordinates":[-121.5833,40.7667],"type":"Point"}
}