<<<<<<< HEAD
{
  "id": 7056399,
  "type": "Feature",
  "properties": {
    "tgn:hierarchy":[
        "tgn:7056399",
        "tgn:1001724",
        "tgn:1000003",
        "tgn:7003121",
        "tgn:1000080",
        "tgn:7029392"
    ],
    "tgn:id":7056399,
    "tgn:name":"Nurtiddi",
    "tgn:placetype":[
        "aat:300008347"
    ]
},
  "bbox": [],
  "geometry": {"coordinates":[9.416667,40.55],"type":"Point"}
}
=======
{"geometry":{"type":"Point","coordinates":[9.416667,40.550000]},"type":"Feature","properties":{"hierarchy":["tgn:7056399","tgn:1001724","tgn:1000003","tgn:7003121","tgn:1000080","tgn:7029392"],"placetype":["aat:300008347"],"id":7056399,"name:xx":"Nurtiddi"}}
>>>>>>> 03f74aca74312dbeaf24d7e61306dd6a786dc3d0
