{
  "id": 2149253,
  "type": "Feature",
  "properties": {
    "tgn:hierarchy":[
        "tgn:2149253",
        "tgn:1000001",
        "tgn:7012149",
        "tgn:1002517",
        "tgn:7007523",
        "tgn:7029392"
    ],
    "tgn:id":2149253,
    "tgn:name":"Barrel Spring",
    "tgn:placetype":[
        "aat:300008697"
    ]
},
  "bbox": [],
  "geometry": {"coordinates":[-90.65,38.1167],"type":"Point"}
}