{
  "id": 7454706,
  "type": "Feature",
  "properties": {
    "tgn:hierarchy":[
        "tgn:7454706",
        "tgn:7002445",
        "tgn:1000003",
        "tgn:7026532",
        "tgn:7008591",
        "tgn:7029392"
    ],
    "tgn:id":7454706,
    "tgn:name:en":"Burderop Park",
    "tgn:placetype":[
        "aat:300387502"
    ]
},
  "bbox": [],
  "geometry": {"coordinates":[-1.766667,51.516667],"type":"Point"}
}