<<<<<<< HEAD
{
  "id": 7487961,
  "type": "Feature",
  "properties": {
    "tgn:hierarchy":[
        "tgn:7487961",
        "tgn:7487020",
        "tgn:1000004",
        "tgn:1000141",
        "tgn:7029392"
    ],
    "tgn:id":7487961,
    "tgn:name":"Nanfang",
    "tgn:placetype":[
        "aat:300008347"
    ]
},
  "bbox": [],
  "geometry": {"coordinates":[120.636667,24.433611],"type":"Point"}
}
=======
{"geometry":{"type":"Point","coordinates":[120.636667,24.433611]},"type":"Feature","properties":{"hierarchy":["tgn:7487961","tgn:7487020","tgn:1000004","tgn:1000141","tgn:7029392"],"placetype":["aat:300008347"],"id":7487961,"name:xx":"Nanfang"}}
>>>>>>> 03f74aca74312dbeaf24d7e61306dd6a786dc3d0
