{
  "id": 7449712,
  "type": "Feature",
  "properties": {
    "tgn:hierarchy":[
        "tgn:7449712",
        "tgn:7002444",
        "tgn:1000003",
        "tgn:7019152",
        "tgn:7008591",
        "tgn:7029392"
    ],
    "tgn:id":7449712,
    "tgn:name:en":"Edendon Water",
    "tgn:placetype":[
        "aat:300008699"
    ]
},
  "bbox": [],
  "geometry": {"coordinates":[-4.116667,56.883333],"type":"Point"}
}