{
  "id": 2562189,
  "type": "Feature",
  "properties": {
    "tgn:hierarchy":[
        "tgn:2562189",
        "tgn:1000001",
        "tgn:1002243",
        "tgn:7012149",
        "tgn:7007520",
        "tgn:7029392"
    ],
    "tgn:id":2562189,
    "tgn:name":"Otter Lake",
    "tgn:placetype":[
        "aat:300008680"
    ]
},
  "bbox": [],
  "geometry": {"coordinates":[-85.85,42.05],"type":"Point"}
}