<<<<<<< HEAD
{
  "id": 7054886,
  "type": "Feature",
  "properties": {
    "tgn:hierarchy":[
        "tgn:7054886",
        "tgn:7003162",
        "tgn:1000003",
        "tgn:7009760",
        "tgn:1000080",
        "tgn:7029392"
    ],
    "tgn:id":7054886,
    "tgn:name":"Molino del Calcione",
    "tgn:placetype":[
        "aat:300008347"
    ]
},
  "bbox": [],
  "geometry": {"coordinates":[11.683333,43.283333],"type":"Point"}
}
=======
{"geometry":{"type":"Point","coordinates":[11.683333,43.283333]},"type":"Feature","properties":{"hierarchy":["tgn:7054886","tgn:7003162","tgn:1000003","tgn:7009760","tgn:1000080","tgn:7029392"],"placetype":["aat:300008347"],"id":7054886,"name:xx":"Molino del Calcione"}}
>>>>>>> 03f74aca74312dbeaf24d7e61306dd6a786dc3d0
