{
  "id": 7564739,
  "type": "Feature",
  "properties": {
    "tgn:hierarchy":[
        "tgn:7564739",
        "tgn:1000004",
        "tgn:7000198",
        "tgn:1001894",
        "tgn:7029392"
    ],
    "tgn:id":7564739,
    "tgn:name:en":"Kumarra N\u0101la",
    "tgn:placetype":[
        "aat:300266554",
        "aat:300008699"
    ]
},
  "bbox": [],
  "geometry": {"coordinates":[79.196798,24.948515],"type":"Point"}
}