{
  "id": 1097145,
  "type": "Feature",
  "properties": {
    "tgn:hierarchy":[
        "tgn:1097145",
        "tgn:7000490",
        "tgn:1000006",
        "tgn:7001828",
        "tgn:7001923",
        "tgn:7029392"
    ],
    "tgn:id":1097145,
    "tgn:name":"Hunters Hill",
    "tgn:placetype":[
        "aat:300008347"
    ]
},
  "bbox": [],
  "geometry": {"coordinates":[151.15,-33.8333],"type":"Point"}
}