{
  "id": 2711562,
  "type": "Feature",
  "properties": {
    "tgn:hierarchy":[
        "tgn:2711562",
        "tgn:1000001",
        "tgn:2001336",
        "tgn:7012149",
        "tgn:7007525",
        "tgn:7029392"
    ],
    "tgn:id":2711562,
    "tgn:name":"Tappan Valley",
    "tgn:placetype":[
        "aat:300008761"
    ]
},
  "bbox": [],
  "geometry": {"coordinates":[-99.65,41.45],"type":"Point"}
}