{
  "id": 2212726,
  "type": "Feature",
  "properties": {
    "tgn:hierarchy":[
        "tgn:2212726",
        "tgn:1000001",
        "tgn:2001410",
        "tgn:7012149",
        "tgn:7007526",
        "tgn:7029392"
    ],
    "tgn:id":2212726,
    "tgn:name":"C C C Reservoir",
    "tgn:placetype":[
        "aat:300006191"
    ]
},
  "bbox": [],
  "geometry": {"coordinates":[-114.95,35.8333],"type":"Point"}
}