{
  "id": 7230700,
  "type": "Feature",
  "properties": {
    "tgn:hierarchy":[
        "tgn:7230700",
        "tgn:7002711",
        "tgn:7001338",
        "tgn:1000003",
        "tgn:1000074",
        "tgn:7029392"
    ],
    "tgn:id":7230700,
    "tgn:name":"Mathr\u00e1kion, N\u00edsos",
    "tgn:placetype":[
        "aat:300008791"
    ]
},
  "bbox": [],
  "geometry": {"coordinates":[19.524167,39.768056],"type":"Point"}
}