{
  "id": 2225510,
  "type": "Feature",
  "properties": {
    "tgn:hierarchy":[
        "tgn:2225510",
        "tgn:1000001",
        "tgn:7012149",
        "tgn:2000807",
        "tgn:7007255",
        "tgn:7029392"
    ],
    "tgn:id":2225510,
    "tgn:name":"Castleman Creek",
    "tgn:placetype":[
        "aat:300008706"
    ]
},
  "bbox": [],
  "geometry": {"coordinates":[-85.6833,37.65],"type":"Point"}
}