{
  "id": 2145446,
  "type": "Feature",
  "properties": {
    "tgn:hierarchy":[
        "tgn:2145446",
        "tgn:1002300",
        "tgn:1000001",
        "tgn:7012149",
        "tgn:7007564",
        "tgn:7029392"
    ],
    "tgn:id":2145446,
    "tgn:name":"Baldhead Mountain",
    "tgn:placetype":[
        "aat:300008798"
    ]
},
  "bbox": [],
  "geometry": {"coordinates":[-71.3667,44.8167],"type":"Point"}
}