{
  "id": 2606090,
  "type": "Feature",
  "properties": {
    "tgn:hierarchy":[
        "tgn:2606090",
        "tgn:1000001",
        "tgn:7012149",
        "tgn:2000410",
        "tgn:7007248",
        "tgn:7029392"
    ],
    "tgn:id":2606090,
    "tgn:name":"Rainey Mountain",
    "tgn:placetype":[
        "aat:300008798"
    ]
},
  "bbox": [],
  "geometry": {"coordinates":[-83.3333,34.8667],"type":"Point"}
}