{
  "id": 7245791,
  "type": "Feature",
  "properties": {
    "tgn:hierarchy":[
        "tgn:7245791",
        "tgn:7003457",
        "tgn:1000003",
        "tgn:1000063",
        "tgn:7018236",
        "tgn:7029392"
    ],
    "tgn:id":7245791,
    "tgn:name":"Bommels",
    "tgn:placetype":[
        "aat:300008347"
    ]
},
  "bbox": [],
  "geometry": {"coordinates":[3.827376,51.000851],"type":"Point"}
}