{
  "id": 1112492,
  "type": "Feature",
  "properties": {
    "tgn:hierarchy":[
        "tgn:1112492",
        "tgn:7016640",
        "tgn:1000050",
        "tgn:1000002",
        "tgn:7029392"
    ],
    "tgn:id":1112492,
    "tgn:name":"Tribug\u00e1, Golfo de",
    "tgn:placetype":[
        "aat:300132315"
    ]
},
  "bbox": [],
  "geometry": {"coordinates":[-77.3333,5.75],"type":"Point"}
}