{
  "id": 2305976,
  "type": "Feature",
  "properties": {
    "tgn:hierarchy":[
        "tgn:2305976",
        "tgn:1000001",
        "tgn:7012149",
        "tgn:2002123",
        "tgn:7007827",
        "tgn:7029392"
    ],
    "tgn:id":2305976,
    "tgn:name":"East Faust Creek",
    "tgn:placetype":[
        "aat:300008706"
    ]
},
  "bbox": [],
  "geometry": {"coordinates":[-112.55,40.2167],"type":"Point"}
}