{
  "id": 1066643,
  "type": "Feature",
  "properties": {
    "tgn:hierarchy":[
        "tgn:1066643",
        "tgn:1000004",
        "tgn:7002077",
        "tgn:1000111",
        "tgn:7029392"
    ],
    "tgn:id":1066643,
    "tgn:name":"Baile",
    "tgn:placetype":[
        "aat:300008347"
    ]
},
  "bbox": [],
  "geometry": {"coordinates":[114.8667,39.95],"type":"Point"}
}