{
  "id": 7072425,
  "type": "Feature",
  "properties": {
    "tgn:hierarchy":[
        "tgn:7072425",
        "tgn:1000003",
        "tgn:7003676",
        "tgn:7000084",
        "tgn:7029392"
    ],
    "tgn:id":7072425,
    "tgn:name":"T\u00e4tendorf-Eppensen",
    "tgn:placetype":[
        "aat:300008347"
    ]
},
  "bbox": [],
  "geometry": {"coordinates":[10.55,53.05],"type":"Point"}
}