{
  "id": 2397799,
  "type": "Feature",
  "properties": {
    "tgn:hierarchy":[
        "tgn:2397799",
        "tgn:1002648",
        "tgn:1000001",
        "tgn:1008191",
        "tgn:7012149",
        "tgn:7007249",
        "tgn:7029392"
    ],
    "tgn:id":2397799,
    "tgn:name":"Honoulimaloo Stream",
    "tgn:placetype":[
        "aat:300008699"
    ]
},
  "bbox": [],
  "geometry": {"coordinates":[-156.7667,21.1333],"type":"Point"}
}