{
  "id": 7309115,
  "type": "Feature",
  "properties": {
    "tgn:hierarchy":[
        "tgn:7309115",
        "tgn:1001623",
        "tgn:1000049",
        "tgn:1000002",
        "tgn:7029392"
    ],
    "tgn:id":7309115,
    "tgn:name":"Macetero, Punta",
    "tgn:placetype":[
        "aat:300386846"
    ]
},
  "bbox": [],
  "geometry": {"coordinates":[-72.783333,-44.45],"type":"Point"}
}