{
  "id": 7074718,
  "type": "Feature",
  "properties": {
    "tgn:hierarchy":[
        "tgn:7074718",
        "tgn:1000003",
        "tgn:7003685",
        "tgn:7000084",
        "tgn:7029392"
    ],
    "tgn:id":7074718,
    "tgn:name":"Haltepunkt Zug",
    "tgn:placetype":[
        "aat:300007783"
    ]
},
  "bbox": [],
  "geometry": {"coordinates":[13.363611,50.875556],"type":"Point"}
}