{
  "id": 2369522,
  "type": "Feature",
  "properties": {
    "tgn:hierarchy":[
        "tgn:2369522",
        "tgn:1000001",
        "tgn:7013942",
        "tgn:7012149",
        "tgn:7007517",
        "tgn:7029392"
    ],
    "tgn:id":2369522,
    "tgn:name":"Gunn Brook",
    "tgn:placetype":[
        "aat:300008699"
    ]
},
  "bbox": [],
  "geometry": {"coordinates":[-72.5333,42.4833],"type":"Point"}
}