<<<<<<< HEAD
{
  "id": 7240232,
  "type": "Feature",
  "properties": {
    "tgn:hierarchy":[
        "tgn:7240232",
        "tgn:7003461",
        "tgn:1000003",
        "tgn:1000063",
        "tgn:7018236",
        "tgn:7029392"
    ],
    "tgn:id":7240232,
    "tgn:name":"Eigenbilzen",
    "tgn:placetype":[
        "aat:300008347"
    ]
},
  "bbox": [],
  "geometry": {"coordinates":[5.583333,50.866667],"type":"Point"}
}
=======
{"geometry":{"type":"Point","coordinates":[5.583333,50.866667]},"type":"Feature","properties":{"hierarchy":["tgn:7240232","tgn:7003461","tgn:1000003","tgn:1000063","tgn:7018236","tgn:7029392"],"placetype":["aat:300008347"],"id":7240232,"name:xx":"Eigenbilzen"}}
>>>>>>> 03f74aca74312dbeaf24d7e61306dd6a786dc3d0
