{
  "id": 2373361,
  "type": "Feature",
  "properties": {
    "tgn:hierarchy":[
        "tgn:2373361",
        "tgn:1000001",
        "tgn:7012149",
        "tgn:7018871",
        "tgn:7007920",
        "tgn:7029392"
    ],
    "tgn:id":2373361,
    "tgn:name":"Ham Lake",
    "tgn:placetype":[
        "aat:300008680"
    ]
},
  "bbox": [],
  "geometry": {"coordinates":[-122.1167,47.3833],"type":"Point"}
}