{
  "id": 7312737,
  "type": "Feature",
  "properties": {
    "tgn:hierarchy":[
        "tgn:7312737",
        "tgn:1001695",
        "tgn:1000049",
        "tgn:1000002",
        "tgn:7029392"
    ],
    "tgn:id":7312737,
    "tgn:name":"La Mina, Cerro",
    "tgn:placetype":[
        "aat:300008795"
    ]
},
  "bbox": [],
  "geometry": {"coordinates":[-71.516667,-34.533333],"type":"Point"}
}