<<<<<<< HEAD
{
  "id": 2409463,
  "type": "Feature",
  "properties": {
    "tgn:hierarchy":[
        "tgn:2409463",
        "tgn:1000001",
        "tgn:2001331",
        "tgn:7012149",
        "tgn:7007525",
        "tgn:7029392"
    ],
    "tgn:id":2409463,
    "tgn:name":"Ideal Valley",
    "tgn:placetype":[
        "aat:300386845"
    ]
},
  "bbox": [],
  "geometry": {"coordinates":[-101.8833,42.35],"type":"Point"}
}
=======
{"geometry":{"type":"Point","coordinates":[-101.883300,42.350000]},"type":"Feature","properties":{"hierarchy":["tgn:2409463","tgn:1000001","tgn:2001331","tgn:7012149","tgn:7007525","tgn:7029392"],"placetype":["aat:300386845"],"id":2409463,"name:xx":"Ideal Valley"}}
>>>>>>> 03f74aca74312dbeaf24d7e61306dd6a786dc3d0
