{
  "id": 7354066,
  "type": "Feature",
  "properties": {
    "tgn:hierarchy":[
        "tgn:7354066",
        "tgn:7005581",
        "tgn:1000001",
        "tgn:7005560",
        "tgn:7029392"
    ],
    "tgn:id":7354066,
    "tgn:name":"Campo 30",
    "tgn:placetype":[
        "aat:300008347"
    ]
},
  "bbox": [],
  "geometry": {"coordinates":[-106.85,28.766667],"type":"Point"}
}