{
  "id": 2595422,
  "type": "Feature",
  "properties": {
    "tgn:hierarchy":[
        "tgn:2595422",
        "tgn:1000001",
        "tgn:7006451",
        "tgn:2000092",
        "tgn:7012149",
        "tgn:7029392"
    ],
    "tgn:id":2595422,
    "tgn:name":"Potato Hill",
    "tgn:placetype":[
        "aat:300008798"
    ]
},
  "bbox": [],
  "geometry": {"coordinates":[-111.9333,35.4833],"type":"Point"}
}