{
  "id": 2194958,
  "type": "Feature",
  "properties": {
    "tgn:hierarchy":[
        "tgn:2194958",
        "tgn:1000001",
        "tgn:1002273",
        "tgn:7012149",
        "tgn:7007252",
        "tgn:7029392"
    ],
    "tgn:id":2194958,
    "tgn:name":"Bright Run",
    "tgn:placetype":[
        "aat:300008699"
    ]
},
  "bbox": [],
  "geometry": {"coordinates":[-85.75,38.5167],"type":"Point"}
}