{
  "id": 2091137,
  "type": "Feature",
  "properties": {
    "tgn:hierarchy":[
        "tgn:2091137",
        "tgn:1000001",
        "tgn:1002194",
        "tgn:7012149",
        "tgn:7007710",
        "tgn:7029392"
    ],
    "tgn:id":2091137,
    "tgn:name":"Neath",
    "tgn:placetype":[
        "aat:300008347",
        "aat:300387210"
    ]
},
  "bbox": [],
  "geometry": {"coordinates":[-76.1333,41.8667],"type":"Point"}
}