{
  "id": 2310433,
  "type": "Feature",
  "properties": {
    "tgn:hierarchy":[
        "tgn:2310433",
        "tgn:1000001",
        "tgn:7012149",
        "tgn:2000235",
        "tgn:7007158",
        "tgn:7029392"
    ],
    "tgn:id":2310433,
    "tgn:name":"Echo Canyon",
    "tgn:placetype":[
        "aat:300008761"
    ]
},
  "bbox": [],
  "geometry": {"coordinates":[-103.8333,40.45],"type":"Point"}
}