{
  "id": 2531051,
  "type": "Feature",
  "properties": {
    "tgn:hierarchy":[
        "tgn:2531051",
        "tgn:1000001",
        "tgn:7012149",
        "tgn:2001293",
        "tgn:7007524",
        "tgn:7029392"
    ],
    "tgn:id":2531051,
    "tgn:name":"Muir",
    "tgn:placetype":[
        "aat:300008347"
    ]
},
  "bbox": [],
  "geometry": {"coordinates":[-110.7833,45.65],"type":"Point"}
}