{
  "id": 7494074,
  "type": "Feature",
  "properties": {
    "tgn:hierarchy":[
        "tgn:7494074",
        "tgn:7468018",
        "tgn:1000004",
        "tgn:1000141",
        "tgn:7029392"
    ],
    "tgn:id":7494074,
    "tgn:name":"Guanghua Guoxiao",
    "tgn:placetype":[
        "aat:300006495"
    ]
},
  "bbox": [],
  "geometry": {"coordinates":[120.670106,23.47225],"type":"Point"}
}