{
  "id": 2432476,
  "type": "Feature",
  "properties": {
    "tgn:hierarchy":[
        "tgn:2432476",
        "tgn:7023902",
        "tgn:1000001",
        "tgn:7012149",
        "tgn:7007249",
        "tgn:7029392"
    ],
    "tgn:id":2432476,
    "tgn:name":"Keawanui Bay",
    "tgn:placetype":[
        "aat:300132316"
    ]
},
  "bbox": [],
  "geometry": {"coordinates":[-155.8833,20.1167],"type":"Point"}
}