{
  "id": 2467773,
  "type": "Feature",
  "properties": {
    "tgn:hierarchy":[
        "tgn:2467773",
        "tgn:1000001",
        "tgn:7012149",
        "tgn:2001711",
        "tgn:7007708",
        "tgn:7029392"
    ],
    "tgn:id":2467773,
    "tgn:name":"Long John Creek",
    "tgn:placetype":[
        "aat:300008706"
    ]
},
  "bbox": [],
  "geometry": {"coordinates":[-122.75,42.05],"type":"Point"}
}