{
  "id": 1092761,
  "type": "Feature",
  "properties": {
    "tgn:hierarchy":[
        "tgn:1092761",
        "tgn:7001242",
        "tgn:1001676",
        "tgn:1000192",
        "tgn:7029392"
    ],
    "tgn:id":1092761,
    "tgn:name":"Sar\u00e1nley",
    "tgn:placetype":[
        "aat:300008347"
    ]
},
  "bbox": [],
  "geometry": {"coordinates":[42.2833,2.3667],"type":"Point"}
}