{
  "id": 2550478,
  "type": "Feature",
  "properties": {
    "tgn:hierarchy":[
        "tgn:2550478",
        "tgn:1000001",
        "tgn:2000264",
        "tgn:7012149",
        "tgn:7007240",
        "tgn:7029392"
    ],
    "tgn:id":2550478,
    "tgn:name":"Northwood",
    "tgn:placetype":[
        "aat:300008347"
    ]
},
  "bbox": [],
  "geometry": {"coordinates":[-81.65,30.4333],"type":"Point"}
}