{
  "id": 7449728,
  "type": "Feature",
  "properties": {
    "tgn:hierarchy":[
        "tgn:7449728",
        "tgn:7002445",
        "tgn:1000003",
        "tgn:7008118",
        "tgn:7008591",
        "tgn:7029392"
    ],
    "tgn:id":7449728,
    "tgn:name:en":"Edale, Vale of",
    "tgn:placetype":[
        "aat:300008761"
    ]
},
  "bbox": [],
  "geometry": {"coordinates":[-1.816667,53.383333],"type":"Point"}
}