<<<<<<< HEAD
{
  "id": 2332332,
  "type": "Feature",
  "properties": {
    "tgn:hierarchy":[
        "tgn:2332332",
        "tgn:1000001",
        "tgn:7012149",
        "tgn:7013941",
        "tgn:7007568",
        "tgn:7029392"
    ],
    "tgn:id":2332332,
    "tgn:name":"Floodwood",
    "tgn:placetype":[
        "aat:300008347"
    ]
},
  "bbox": [],
  "geometry": {"coordinates":[-74.4,44.3333],"type":"Point"}
}
=======
{"geometry":{"type":"Point","coordinates":[-74.400000,44.333300]},"type":"Feature","properties":{"hierarchy":["tgn:2332332","tgn:1000001","tgn:7012149","tgn:7013941","tgn:7007568","tgn:7029392"],"placetype":["aat:300008347"],"id":2332332,"name:xx":"Floodwood"}}
>>>>>>> 03f74aca74312dbeaf24d7e61306dd6a786dc3d0
