{
  "id": 2646522,
  "type": "Feature",
  "properties": {
    "tgn:hierarchy":[
        "tgn:2646522",
        "tgn:1000001",
        "tgn:7012149",
        "tgn:7007919",
        "tgn:7029392"
    ],
    "tgn:id":2646522,
    "tgn:name":"Saylers Creek",
    "tgn:placetype":[
        "aat:300008706"
    ]
},
  "bbox": [],
  "geometry": {"coordinates":[-78.2333,37.2333],"type":"Point"}
}