{
  "id": 7565108,
  "type": "Feature",
  "properties": {
    "tgn:hierarchy":[
        "tgn:7565108",
        "tgn:1000004",
        "tgn:7000198",
        "tgn:7016722",
        "tgn:7029392"
    ],
    "tgn:id":7565108,
    "tgn:name:en":"Purwa Nik\u0101ri",
    "tgn:placetype":[
        "aat:300008347"
    ]
},
  "bbox": [],
  "geometry": {"coordinates":[79.717957,26.894981],"type":"Point"}
}