{
  "id": 2194568,
  "type": "Feature",
  "properties": {
    "tgn:hierarchy":[
        "tgn:2194568",
        "tgn:1000001",
        "tgn:7012149",
        "tgn:2000426",
        "tgn:7007248",
        "tgn:7029392"
    ],
    "tgn:id":2194568,
    "tgn:name":"Bridges Crossroad",
    "tgn:placetype":[
        "aat:300008347"
    ]
},
  "bbox": [],
  "geometry": {"coordinates":[-84.35,31.75],"type":"Point"}
}