{
  "id": 7505489,
  "type": "Feature",
  "properties": {
    "tgn:hierarchy":[
        "tgn:7505489",
        "tgn:1009227",
        "tgn:1000226",
        "tgn:7016729",
        "tgn:1000006",
        "tgn:7029392"
    ],
    "tgn:id":7505489,
    "tgn:name:en":"Whatamango Bay",
    "tgn:placetype":[
        "aat:300132316"
    ]
},
  "bbox": [],
  "geometry": {"coordinates":[174.083333,-41.266667],"type":"Point"}
}