<<<<<<< HEAD
{
  "id": 7473336,
  "type": "Feature",
  "properties": {
    "tgn:hierarchy":[
        "tgn:7473336",
        "tgn:1000004",
        "tgn:7001009",
        "tgn:1000141",
        "tgn:7029392"
    ],
    "tgn:id":7473336,
    "tgn:name":"Dongmao Shan",
    "tgn:placetype":[
        "aat:300008798"
    ]
},
  "bbox": [],
  "geometry": {"coordinates":[120.957818,24.185887],"type":"Point"}
}
=======
{"geometry":{"type":"Point","coordinates":[120.957818,24.185887]},"type":"Feature","properties":{"hierarchy":["tgn:7473336","tgn:1000004","tgn:7001009","tgn:1000141","tgn:7029392"],"placetype":["aat:300008798"],"id":7473336,"name:xx":"Dongmao Shan"}}
>>>>>>> 03f74aca74312dbeaf24d7e61306dd6a786dc3d0
