{
  "id": 7465057,
  "type": "Feature",
  "properties": {
    "tgn:hierarchy":[
        "tgn:7465057",
        "tgn:7002445",
        "tgn:1000003",
        "tgn:7008153",
        "tgn:7008591",
        "tgn:7029392"
    ],
    "tgn:id":7465057,
    "tgn:name:en":"Varne, The",
    "tgn:placetype":[
        "aat:300387036"
    ]
},
  "bbox": [],
  "geometry": {"coordinates":[1.316667,50.966667],"type":"Point"}
}