{
  "id": 2510251,
  "type": "Feature",
  "properties": {
    "tgn:hierarchy":[
        "tgn:2510251",
        "tgn:1000001",
        "tgn:7012149",
        "tgn:1002519",
        "tgn:7007706",
        "tgn:7029392"
    ],
    "tgn:id":2510251,
    "tgn:name":"Middle Ridge",
    "tgn:placetype":[
        "aat:300266640"
    ]
},
  "bbox": [],
  "geometry": {"coordinates":[-80.8167,40.4833],"type":"Point"}
}