{
  "id": 2619182,
  "type": "Feature",
  "properties": {
    "tgn:hierarchy":[
        "tgn:2619182",
        "tgn:1000001",
        "tgn:2000776",
        "tgn:7012149",
        "tgn:7007255",
        "tgn:7029392"
    ],
    "tgn:id":2619182,
    "tgn:name":"Riley Hill",
    "tgn:placetype":[
        "aat:300008798"
    ]
},
  "bbox": [],
  "geometry": {"coordinates":[-87.9833,37.2333],"type":"Point"}
}