{
  "id": 7278477,
  "type": "Feature",
  "properties": {
    "tgn:hierarchy":[
        "tgn:7278477",
        "tgn:1001657",
        "tgn:1000049",
        "tgn:1000002",
        "tgn:7029392"
    ],
    "tgn:id":7278477,
    "tgn:name":"Ba\u00f1itos, Cerros los",
    "tgn:placetype":[
        "aat:300008795"
    ]
},
  "bbox": [],
  "geometry": {"coordinates":[-69.95,-29.683333],"type":"Point"}
}