{
  "id": 7282865,
  "type": "Feature",
  "properties": {
    "tgn:hierarchy":[
        "tgn:7282865",
        "tgn:1001699",
        "tgn:1000049",
        "tgn:1000002",
        "tgn:7029392"
    ],
    "tgn:id":7282865,
    "tgn:name":"Pelchuquin",
    "tgn:placetype":[
        "aat:300008347"
    ]
},
  "bbox": [],
  "geometry": {"coordinates":[-73.066667,-39.616667],"type":"Point"}
}