{
  "id": 1086028,
  "type": "Feature",
  "properties": {
    "tgn:hierarchy":[
        "tgn:1086028",
        "tgn:1001125",
        "tgn:1000004",
        "tgn:7018450",
        "tgn:1000144",
        "tgn:7029392"
    ],
    "tgn:id":1086028,
    "tgn:name":"Bilecik",
    "tgn:placetype":[
        "aat:300008347",
        "aat:300008389",
        "aat:300387223"
    ]
},
  "bbox": [],
  "geometry": {"coordinates":[29.9833,40.1667],"type":"Point"}
}