{
  "id": 2713790,
  "type": "Feature",
  "properties": {
    "tgn:hierarchy":[
        "tgn:2713790",
        "tgn:1000001",
        "tgn:7012149",
        "tgn:2000183",
        "tgn:7007157",
        "tgn:7029392"
    ],
    "tgn:id":2713790,
    "tgn:name":"Tecopa Hot Springs",
    "tgn:placetype":[
        "aat:300008697"
    ]
},
  "bbox": [],
  "geometry": {"coordinates":[-116.2167,35.8667],"type":"Point"}
}