{
  "id": 7143843,
  "type": "Feature",
  "properties": {
    "tgn:hierarchy":[
        "tgn:7143843",
        "tgn:1000003",
        "tgn:7003676",
        "tgn:7000084",
        "tgn:7029392"
    ],
    "tgn:id":7143843,
    "tgn:name":"Klein Linteln",
    "tgn:placetype":[
        "aat:300008347"
    ]
},
  "bbox": [],
  "geometry": {"coordinates":[9.35,52.95],"type":"Point"}
}