{
  "id": 2461686,
  "type": "Feature",
  "properties": {
    "tgn:hierarchy":[
        "tgn:2461686",
        "tgn:1000001",
        "tgn:7012149",
        "tgn:7007157",
        "tgn:1002566",
        "tgn:7029392"
    ],
    "tgn:id":2461686,
    "tgn:name":"Little Thatcher Creek",
    "tgn:placetype":[
        "aat:300008706"
    ]
},
  "bbox": [],
  "geometry": {"coordinates":[-123.0333,39.6167],"type":"Point"}
}