{
  "id": 2409468,
  "type": "Feature",
  "properties": {
    "tgn:hierarchy":[
        "tgn:2409468",
        "tgn:1000001",
        "tgn:7012149",
        "tgn:2002283",
        "tgn:7013961",
        "tgn:7029392"
    ],
    "tgn:id":2409468,
    "tgn:name":"Iden Run",
    "tgn:placetype":[
        "aat:300008699"
    ]
},
  "bbox": [],
  "geometry": {"coordinates":[-78.2167,39.4667],"type":"Point"}
}