<<<<<<< HEAD
{
  "id": 2409468,
  "type": "Feature",
  "properties": {
    "tgn:hierarchy":[
        "tgn:2409468",
        "tgn:1000001",
        "tgn:7012149",
        "tgn:2002283",
        "tgn:7013961",
        "tgn:7029392"
    ],
    "tgn:id":2409468,
    "tgn:name":"Iden Run",
    "tgn:placetype":[
        "aat:300008699"
    ]
},
  "bbox": [],
  "geometry": {"coordinates":[-78.2167,39.4667],"type":"Point"}
}
=======
{"geometry":{"type":"Point","coordinates":[-78.216700,39.466700]},"type":"Feature","properties":{"hierarchy":["tgn:2409468","tgn:1000001","tgn:7012149","tgn:2002283","tgn:7013961","tgn:7029392"],"placetype":["aat:300008699"],"id":2409468,"name:xx":"Iden Run"}}
>>>>>>> 03f74aca74312dbeaf24d7e61306dd6a786dc3d0
