{
  "id": 2271312,
  "type": "Feature",
  "properties": {
    "tgn:hierarchy":[
        "tgn:2271312",
        "tgn:1000001",
        "tgn:7012149",
        "tgn:2001508",
        "tgn:7007709",
        "tgn:7029392"
    ],
    "tgn:id":2271312,
    "tgn:name":"Cullowhee Mountain",
    "tgn:placetype":[
        "aat:300266640"
    ]
},
  "bbox": [],
  "geometry": {"coordinates":[-83.15,35.25],"type":"Point"}
}