{
  "id": 7393053,
  "type": "Feature",
  "properties": {
    "tgn:hierarchy":[
        "tgn:7393053",
        "tgn:1000001",
        "tgn:7005594",
        "tgn:7005560",
        "tgn:7029392"
    ],
    "tgn:id":7393053,
    "tgn:name":"San Joaqu\u00edn",
    "tgn:placetype":[
        "aat:300008347"
    ]
},
  "bbox": [],
  "geometry": {"coordinates":[-99.366667,22.133333],"type":"Point"}
}