{
  "id": 2538495,
  "type": "Feature",
  "properties": {
    "tgn:hierarchy":[
        "tgn:2538495",
        "tgn:1000001",
        "tgn:7012149",
        "tgn:7029392"
    ],
    "tgn:id":2538495,
    "tgn:name":"Neskahi Wash",
    "tgn:placetype":[
        "aat:300008699"
    ]
},
  "bbox": [],
  "geometry": {"coordinates":[-110.5833,36.9833],"type":"Point"}
}