{
  "id": 2646562,
  "type": "Feature",
  "properties": {
    "tgn:hierarchy":[
        "tgn:2646562",
        "tgn:1000001",
        "tgn:1002194",
        "tgn:7012149",
        "tgn:7007710",
        "tgn:7029392"
    ],
    "tgn:id":2646562,
    "tgn:name":"Sayre Reservoir",
    "tgn:placetype":[
        "aat:300006191"
    ]
},
  "bbox": [],
  "geometry": {"coordinates":[-76.4833,41.9667],"type":"Point"}
}