{
  "id": 7180063,
  "type": "Feature",
  "properties": {
    "tgn:hierarchy":[
        "tgn:7180063",
        "tgn:7003669",
        "tgn:1000003",
        "tgn:7000084",
        "tgn:7029392"
    ],
    "tgn:id":7180063,
    "tgn:name":"Geblatsried",
    "tgn:placetype":[
        "aat:300008347"
    ]
},
  "bbox": [],
  "geometry": {"coordinates":[10.716667,47.816667],"type":"Point"}
}