{
  "id": 2251519,
  "type": "Feature",
  "properties": {
    "tgn:hierarchy":[
        "tgn:2251519",
        "tgn:1000001",
        "tgn:7012149",
        "tgn:2002371",
        "tgn:7007923",
        "tgn:7029392"
    ],
    "tgn:id":2251519,
    "tgn:name":"Commissary Spring",
    "tgn:placetype":[
        "aat:300008697"
    ]
},
  "bbox": [],
  "geometry": {"coordinates":[-108.5833,42.6333],"type":"Point"}
}