<<<<<<< HEAD
{
  "id": 2251519,
  "type": "Feature",
  "properties": {
    "tgn:hierarchy":[
        "tgn:2251519",
        "tgn:1000001",
        "tgn:7012149",
        "tgn:2002371",
        "tgn:7007923",
        "tgn:7029392"
    ],
    "tgn:id":2251519,
    "tgn:name":"Commissary Spring",
    "tgn:placetype":[
        "aat:300008697"
    ]
},
  "bbox": [],
  "geometry": {"coordinates":[-108.5833,42.6333],"type":"Point"}
}
=======
{"geometry":{"type":"Point","coordinates":[-108.583300,42.633300]},"type":"Feature","properties":{"hierarchy":["tgn:2251519","tgn:1000001","tgn:7012149","tgn:2002371","tgn:7007923","tgn:7029392"],"placetype":["aat:300008697"],"id":2251519,"name:xx":"Commissary Spring"}}
>>>>>>> 03f74aca74312dbeaf24d7e61306dd6a786dc3d0
