{
  "id": 1043720,
  "type": "Feature",
  "properties": {
    "tgn:hierarchy":[
        "tgn:1043720",
        "tgn:7015163",
        "tgn:1000003",
        "tgn:7003121",
        "tgn:1000080",
        "tgn:7029392"
    ],
    "tgn:id":1043720,
    "tgn:name":"Calangianus",
    "tgn:placetype":[
        "aat:300008347"
    ]
},
  "bbox": [],
  "geometry": {"coordinates":[9.183333,40.933333],"type":"Point"}
}