{
  "id": 2401218,
  "type": "Feature",
  "properties": {
    "tgn:hierarchy":[
        "tgn:2401218",
        "tgn:1000001",
        "tgn:7012149",
        "tgn:2001709",
        "tgn:7007708",
        "tgn:7029392"
    ],
    "tgn:id":2401218,
    "tgn:name":"Horsehead Reservoir",
    "tgn:placetype":[
        "aat:300006191"
    ]
},
  "bbox": [],
  "geometry": {"coordinates":[-119.7667,43.15],"type":"Point"}
}