{
  "id": 7325371,
  "type": "Feature",
  "properties": {
    "tgn:hierarchy":[
        "tgn:7325371",
        "tgn:7002818",
        "tgn:1001647",
        "tgn:1000003",
        "tgn:1000095",
        "tgn:7029392"
    ],
    "tgn:id":7325371,
    "tgn:name":"Santos, Arroyo de los",
    "tgn:placetype":[
        "aat:300008699"
    ]
},
  "bbox": [],
  "geometry": {"coordinates":[-2.266667,39.716667],"type":"Point"}
}