{
  "id": 7487457,
  "type": "Feature",
  "properties": {
    "tgn:hierarchy":[
        "tgn:7487457",
        "tgn:1000004",
        "tgn:7491221",
        "tgn:1000141",
        "tgn:7029392"
    ],
    "tgn:id":7487457,
    "tgn:name":"Kengtou",
    "tgn:placetype":[
        "aat:300008773"
    ]
},
  "bbox": [],
  "geometry": {"coordinates":[121.021667,23.123611],"type":"Point"}
}