{
  "id": 1137613,
  "type": "Feature",
  "properties": {
    "tgn:hierarchy":[
        "tgn:1137613",
        "tgn:1000004",
        "tgn:1003399",
        "tgn:7018214",
        "tgn:7002435",
        "tgn:7029392"
    ],
    "tgn:id":1137613,
    "tgn:name":"Kanayevka",
    "tgn:placetype":[
        "aat:300008347"
    ]
},
  "bbox": [],
  "geometry": {"coordinates":[45.5833,53.1167],"type":"Point"}
}