{
  "id": 7493198,
  "type": "Feature",
  "properties": {
    "tgn:hierarchy":[
        "tgn:7493198",
        "tgn:1000004",
        "tgn:1000454",
        "tgn:1000141",
        "tgn:7029392"
    ],
    "tgn:id":7493198,
    "tgn:name":"Huoshaoliao",
    "tgn:placetype":[
        "aat:300008347"
    ]
},
  "bbox": [],
  "geometry": {"coordinates":[121.452859,24.845549],"type":"Point"}
}