{
  "id": 2547702,
  "type": "Feature",
  "properties": {
    "tgn:hierarchy":[
        "tgn:2547702",
        "tgn:1000001",
        "tgn:7012149",
        "tgn:2001873",
        "tgn:7007825",
        "tgn:7029392"
    ],
    "tgn:id":2547702,
    "tgn:name":"North Fork Valley",
    "tgn:placetype":[
        "aat:300008761"
    ]
},
  "bbox": [],
  "geometry": {"coordinates":[-82.7667,36.4333],"type":"Point"}
}