{
  "id": 7099556,
  "type": "Feature",
  "properties": {
    "tgn:hierarchy":[
        "tgn:7099556",
        "tgn:7003669",
        "tgn:1000003",
        "tgn:7000084",
        "tgn:7029392"
    ],
    "tgn:id":7099556,
    "tgn:name":"Sommerau",
    "tgn:placetype":[
        "aat:300000206"
    ]
},
  "bbox": [],
  "geometry": {"coordinates":[11.233333,48.566667],"type":"Point"}
}