{
  "id": 2394738,
  "type": "Feature",
  "properties": {
    "tgn:hierarchy":[
        "tgn:2394738",
        "tgn:7006450",
        "tgn:1000001",
        "tgn:7030517",
        "tgn:7012149",
        "tgn:7029392"
    ],
    "tgn:id":2394738,
    "tgn:name":"Hoknede Mountain",
    "tgn:placetype":[
        "aat:300008798"
    ]
},
  "bbox": [],
  "geometry": {"coordinates":[-154.8833,60.0167],"type":"Point"}
}