{
  "id": 7332434,
  "type": "Feature",
  "properties": {
    "tgn:hierarchy":[
        "tgn:7332434",
        "tgn:7002834",
        "tgn:1000003",
        "tgn:7002786",
        "tgn:1000095",
        "tgn:7029392"
    ],
    "tgn:id":7332434,
    "tgn:name":"Lago, Ensenada del",
    "tgn:placetype":[
        "aat:300132316"
    ]
},
  "bbox": [],
  "geometry": {"coordinates":[-8.916667,42.216667],"type":"Point"}
}