{
  "id": 7474715,
  "type": "Feature",
  "properties": {
    "tgn:hierarchy":[
        "tgn:7474715",
        "tgn:7468018",
        "tgn:1000004",
        "tgn:1000141",
        "tgn:7029392"
    ],
    "tgn:id":7474715,
    "tgn:name":"Dingyuliao",
    "tgn:placetype":[
        "aat:300008347"
    ]
},
  "bbox": [],
  "geometry": {"coordinates":[120.254444,23.526111],"type":"Point"}
}