{
  "id": 2363515,
  "type": "Feature",
  "properties": {
    "tgn:hierarchy":[
        "tgn:2363515",
        "tgn:1000001",
        "tgn:7016172",
        "tgn:7012149",
        "tgn:7029392"
    ],
    "tgn:id":2363515,
    "tgn:name":"Green Griffin Hollow",
    "tgn:placetype":[
        "aat:300008761"
    ]
},
  "bbox": [],
  "geometry": {"coordinates":[-92.6333,35.7833],"type":"Point"}
}