{
  "id": 1109063,
  "type": "Feature",
  "properties": {
    "tgn:hierarchy":[
        "tgn:1109063",
        "tgn:1000001",
        "tgn:7005589",
        "tgn:7005560",
        "tgn:7029392"
    ],
    "tgn:id":1109063,
    "tgn:name":"Gomas, Sierra de",
    "tgn:placetype":[
        "aat:300008795"
    ]
},
  "bbox": [],
  "geometry": {"coordinates":[-100.533333,26.383333],"type":"Point"}
}