{
  "id": 2236149,
  "type": "Feature",
  "properties": {
    "tgn:hierarchy":[
        "tgn:2236149",
        "tgn:1000001",
        "tgn:7012149",
        "tgn:2001453",
        "tgn:7007566",
        "tgn:7029392"
    ],
    "tgn:id":2236149,
    "tgn:name":"Chical Mesa",
    "tgn:placetype":[
        "aat:300008798"
    ]
},
  "bbox": [],
  "geometry": {"coordinates":[-104.0167,35.3667],"type":"Point"}
}