{
  "id": 2783883,
  "type": "Feature",
  "properties": {
    "tgn:hierarchy":[
        "tgn:2783883",
        "tgn:1000001",
        "tgn:7012149",
        "tgn:2000278",
        "tgn:7007240",
        "tgn:7029392"
    ],
    "tgn:id":2783883,
    "tgn:name":"X L Lake",
    "tgn:placetype":[
        "aat:300008680"
    ]
},
  "bbox": [],
  "geometry": {"coordinates":[-84.6667,30.1333],"type":"Point"}
}