<<<<<<< HEAD
{
  "id": 2257439,
  "type": "Feature",
  "properties": {
    "tgn:hierarchy":[
        "tgn:2257439",
        "tgn:1000001",
        "tgn:7012149",
        "tgn:2001920",
        "tgn:7007825",
        "tgn:7029392"
    ],
    "tgn:id":2257439,
    "tgn:name":"Corona Bar",
    "tgn:placetype":[
        "aat:300132348"
    ]
},
  "bbox": [],
  "geometry": {"coordinates":[-90.0833,35.3833],"type":"Point"}
}
=======
{"geometry":{"type":"Point","coordinates":[-90.083300,35.383300]},"type":"Feature","properties":{"hierarchy":["tgn:2257439","tgn:1000001","tgn:7012149","tgn:2001920","tgn:7007825","tgn:7029392"],"placetype":["aat:300132348"],"id":2257439,"name:xx":"Corona Bar"}}
>>>>>>> 03f74aca74312dbeaf24d7e61306dd6a786dc3d0
