{
  "id": 7377887,
  "type": "Feature",
  "properties": {
    "tgn:hierarchy":[
        "tgn:7377887",
        "tgn:1000001",
        "tgn:7005597",
        "tgn:7005560",
        "tgn:7029392"
    ],
    "tgn:id":7377887,
    "tgn:name":"Las Ovejas",
    "tgn:placetype":[
        "aat:300008347"
    ]
},
  "bbox": [],
  "geometry": {"coordinates":[-99.283333,26.583333],"type":"Point"}
}