{
  "id": 2676045,
  "type": "Feature",
  "properties": {
    "tgn:hierarchy":[
        "tgn:2676045",
        "tgn:1000001",
        "tgn:2001021",
        "tgn:7012149",
        "tgn:7007521",
        "tgn:7029392"
    ],
    "tgn:id":2676045,
    "tgn:name":"Sorenson Creek",
    "tgn:placetype":[
        "aat:300008706"
    ]
},
  "bbox": [],
  "geometry": {"coordinates":[-91.95,43.55],"type":"Point"}
}