{
  "id": 7410174,
  "type": "Feature",
  "properties": {
    "tgn:hierarchy":[
        "tgn:7410174",
        "tgn:1000001",
        "tgn:7005590",
        "tgn:7005560",
        "tgn:7029392"
    ],
    "tgn:id":7410174,
    "tgn:name":"La Fundici\u00f3n",
    "tgn:placetype":[
        "aat:300008347"
    ]
},
  "bbox": [],
  "geometry": {"coordinates":[-102.116667,18.6625],"type":"Point"}
}