<<<<<<< HEAD
{
  "id": 2404699,
  "type": "Feature",
  "properties": {
    "tgn:hierarchy":[
        "tgn:2404699",
        "tgn:7002659",
        "tgn:1000001",
        "tgn:7012149",
        "tgn:7029392"
    ],
    "tgn:id":2404699,
    "tgn:name":"Huckleberry Creek",
    "tgn:placetype":[
        "aat:300008706"
    ]
},
  "bbox": [],
  "geometry": {"coordinates":[-85.7667,31.55],"type":"Point"}
}
=======
{"geometry":{"type":"Point","coordinates":[-85.766700,31.550000]},"type":"Feature","properties":{"hierarchy":["tgn:2404699","tgn:7002659","tgn:1000001","tgn:7012149","tgn:7029392"],"placetype":["aat:300008706"],"id":2404699,"name:xx":"Huckleberry Creek"}}
>>>>>>> 03f74aca74312dbeaf24d7e61306dd6a786dc3d0
