{
  "id": 7554061,
  "type": "Feature",
  "properties": {
    "tgn:hierarchy":[
        "tgn:7554061",
        "tgn:1000004",
        "tgn:7000198",
        "tgn:7000799",
        "tgn:7029392"
    ],
    "tgn:id":7554061,
    "tgn:name:en":"Nior Nis",
    "tgn:placetype":[
        "aat:300008347"
    ]
},
  "bbox": [],
  "geometry": {"coordinates":[78.204237,33.428578],"type":"Point"}
}