{
  "id": 7095883,
  "type": "Feature",
  "properties": {
    "tgn:hierarchy":[
        "tgn:7095883",
        "tgn:1000003",
        "tgn:7003689",
        "tgn:7000084",
        "tgn:7029392"
    ],
    "tgn:id":7095883,
    "tgn:name":"Sch\u00f6n-Berg",
    "tgn:placetype":[
        "aat:300008777"
    ]
},
  "bbox": [],
  "geometry": {"coordinates":[11.183333,50.366667],"type":"Point"}
}