{
  "id": 2116516,
  "type": "Feature",
  "properties": {
    "tgn:hierarchy":[
        "tgn:2116516",
        "tgn:1000001",
        "tgn:2002243",
        "tgn:7012149",
        "tgn:7007920",
        "tgn:7029392"
    ],
    "tgn:id":2116516,
    "tgn:name":"Pollard",
    "tgn:placetype":[
        "aat:300387016"
    ]
},
  "bbox": [],
  "geometry": {"coordinates":[-118.65,48.7167],"type":"Point"}
}