{
  "id": 1005584,
  "type": "Feature",
  "properties": {
    "tgn:hierarchy":[
        "tgn:1005584",
        "tgn:7019028",
        "tgn:7002445",
        "tgn:1000003",
        "tgn:7029506",
        "tgn:7008591",
        "tgn:7029392"
    ],
    "tgn:id":1005584,
    "tgn:name:en":"Selly Oak",
    "tgn:placetype":[
        "aat:300008347",
        "aat:300000874"
    ]
},
  "bbox": [],
  "geometry": {"coordinates":[-1.95,52.433333],"type":"Point"}
}