{
  "id": 2399177,
  "type": "Feature",
  "properties": {
    "tgn:hierarchy":[
        "tgn:2399177",
        "tgn:1000001",
        "tgn:7012149",
        "tgn:7007825",
        "tgn:7029392"
    ],
    "tgn:id":2399177,
    "tgn:name":"Hops Shoals",
    "tgn:placetype":[
        "aat:300132348"
    ]
},
  "bbox": [],
  "geometry": {"coordinates":[-84.2667,35.8833],"type":"Point"}
}