{
  "id": 7157942,
  "type": "Feature",
  "properties": {
    "tgn:hierarchy":[
        "tgn:7157942",
        "tgn:1000003",
        "tgn:7003678",
        "tgn:7000084",
        "tgn:7029392"
    ],
    "tgn:id":7157942,
    "tgn:name":"Kirschgarten",
    "tgn:placetype":[
        "aat:300008347"
    ]
},
  "bbox": [],
  "geometry": {"coordinates":[9.05,50.633333],"type":"Point"}
}