{
  "id": 1015842,
  "type": "Feature",
  "properties": {
    "tgn:hierarchy":[
        "tgn:1015842",
        "tgn:7005685",
        "tgn:1000001",
        "tgn:7005805",
        "tgn:7029392"
    ],
    "tgn:id":1015842,
    "tgn:name":"Bethune",
    "tgn:placetype":[
        "aat:300008347"
    ]
},
  "bbox": [],
  "geometry": {"coordinates":[-105.2833,50.7333],"type":"Point"}
}