{
  "id": 7429649,
  "type": "Feature",
  "properties": {
    "tgn:hierarchy":[
        "tgn:7429649",
        "tgn:7005583",
        "tgn:1000001",
        "tgn:7005560",
        "tgn:7029392"
    ],
    "tgn:id":7429649,
    "tgn:name":"Ojo del Coyote",
    "tgn:placetype":[
        "aat:300008347"
    ]
},
  "bbox": [],
  "geometry": {"coordinates":[-104.783333,24.366667],"type":"Point"}
}