<<<<<<< HEAD
{
  "id": 7361723,
  "type": "Feature",
  "properties": {
    "tgn:hierarchy":[
        "tgn:7361723",
        "tgn:1000001",
        "tgn:7005599",
        "tgn:7005560",
        "tgn:7029392"
    ],
    "tgn:id":7361723,
    "tgn:name":"El Juilero",
    "tgn:placetype":[
        "aat:300008347"
    ]
},
  "bbox": [],
  "geometry": {"coordinates":[-94.4,17.766667],"type":"Point"}
}
=======
{"geometry":{"type":"Point","coordinates":[-94.400000,17.766667]},"type":"Feature","properties":{"hierarchy":["tgn:7361723","tgn:1000001","tgn:7005599","tgn:7005560","tgn:7029392"],"placetype":["aat:300008347"],"id":7361723,"name:xx":"El Juilero"}}
>>>>>>> 03f74aca74312dbeaf24d7e61306dd6a786dc3d0
