{
  "id": 2171457,
  "type": "Feature",
  "properties": {
    "tgn:hierarchy":[
        "tgn:2171457",
        "tgn:1000001",
        "tgn:7012149",
        "tgn:2000225",
        "tgn:7007158",
        "tgn:7029392"
    ],
    "tgn:id":2171457,
    "tgn:name":"Big Stick Ditch",
    "tgn:placetype":[
        "aat:300006075"
    ]
},
  "bbox": [],
  "geometry": {"coordinates":[-108.0333,37.3167],"type":"Point"}
}