{
  "id": 7030246,
  "type": "Feature",
  "properties": {
    "tgn:hierarchy":[
        "tgn:7030246",
        "tgn:7006252",
        "tgn:1000047",
        "tgn:7002455",
        "tgn:1000002",
        "tgn:7029392"
    ],
    "tgn:id":7030246,
    "tgn:name":"Parque Nacional Serra de Capivara",
    "tgn:placetype":[
        "aat:300008189",
        "aat:300387007"
    ]
},
  "bbox": [],
  "geometry": {"coordinates":[-42.44,-8.666],"type":"Point"}
}