{
  "id": 2365978,
  "type": "Feature",
  "properties": {
    "tgn:hierarchy":[
        "tgn:2365978",
        "tgn:1000001",
        "tgn:7012149",
        "tgn:2001709",
        "tgn:7007708",
        "tgn:7029392"
    ],
    "tgn:id":2365978,
    "tgn:name":"Grey Spring",
    "tgn:placetype":[
        "aat:300008697"
    ]
},
  "bbox": [],
  "geometry": {"coordinates":[-118.2667,42.15],"type":"Point"}
}