{
  "id": 2247982,
  "type": "Feature",
  "properties": {
    "tgn:hierarchy":[
        "tgn:2247982",
        "tgn:1000001",
        "tgn:1002259",
        "tgn:7012149",
        "tgn:7007568",
        "tgn:7029392"
    ],
    "tgn:id":2247982,
    "tgn:name":"Colburns",
    "tgn:placetype":[
        "aat:300008347"
    ]
},
  "bbox": [],
  "geometry": {"coordinates":[-79.35,42.1333],"type":"Point"}
}