{
  "id": 2424570,
  "type": "Feature",
  "properties": {
    "tgn:hierarchy":[
        "tgn:2424570",
        "tgn:1000001",
        "tgn:7012149",
        "tgn:7007253",
        "tgn:7029392"
    ],
    "tgn:id":2424570,
    "tgn:name":"Johnson Creek",
    "tgn:placetype":[
        "aat:300008706"
    ]
},
  "bbox": [],
  "geometry": {"coordinates":[-93.0333,42.6667],"type":"Point"}
}