{
  "id": 2403514,
  "type": "Feature",
  "properties": {
    "tgn:hierarchy":[
        "tgn:2403514",
        "tgn:1000001",
        "tgn:7012149",
        "tgn:2000367",
        "tgn:7007248",
        "tgn:7029392"
    ],
    "tgn:id":2403514,
    "tgn:name":"Howard Branch",
    "tgn:placetype":[
        "aat:300008699"
    ]
},
  "bbox": [],
  "geometry": {"coordinates":[-83.65,32.5833],"type":"Point"}
}