<<<<<<< HEAD
{
  "id": 2403514,
  "type": "Feature",
  "properties": {
    "tgn:hierarchy":[
        "tgn:2403514",
        "tgn:1000001",
        "tgn:7012149",
        "tgn:2000367",
        "tgn:7007248",
        "tgn:7029392"
    ],
    "tgn:id":2403514,
    "tgn:name":"Howard Branch",
    "tgn:placetype":[
        "aat:300008699"
    ]
},
  "bbox": [],
  "geometry": {"coordinates":[-83.65,32.5833],"type":"Point"}
}
=======
{"geometry":{"type":"Point","coordinates":[-83.650000,32.583300]},"type":"Feature","properties":{"hierarchy":["tgn:2403514","tgn:1000001","tgn:7012149","tgn:2000367","tgn:7007248","tgn:7029392"],"placetype":["aat:300008699"],"id":2403514,"name:xx":"Howard Branch"}}
>>>>>>> 03f74aca74312dbeaf24d7e61306dd6a786dc3d0
