{
  "id": 1090082,
  "type": "Feature",
  "properties": {
    "tgn:hierarchy":[
        "tgn:1090082",
        "tgn:1001628",
        "tgn:7001242",
        "tgn:1000166",
        "tgn:7029392"
    ],
    "tgn:id":1090082,
    "tgn:name":"Akrofuom",
    "tgn:placetype":[
        "aat:300008347"
    ]
},
  "bbox": [],
  "geometry": {"coordinates":[-1.65,6.1167],"type":"Point"}
}