{
  "id": 7108543,
  "type": "Feature",
  "properties": {
    "tgn:hierarchy":[
        "tgn:7108543",
        "tgn:7000096",
        "tgn:1000003",
        "tgn:7000084",
        "tgn:7029392"
    ],
    "tgn:id":7108543,
    "tgn:name":"Rabenstein",
    "tgn:placetype":[
        "aat:300008057"
    ]
},
  "bbox": [],
  "geometry": {"coordinates":[12.583333,52.033333],"type":"Point"}
}