{
  "id": 2525369,
  "type": "Feature",
  "properties": {
    "tgn:hierarchy":[
        "tgn:2525369",
        "tgn:1000001",
        "tgn:7012149",
        "tgn:1002584",
        "tgn:7007826",
        "tgn:7029392"
    ],
    "tgn:id":2525369,
    "tgn:name":"Morrison Springs Branch",
    "tgn:placetype":[
        "aat:300008699"
    ]
},
  "bbox": [],
  "geometry": {"coordinates":[-97.0333,30.4833],"type":"Point"}
}