{
  "id": 7547897,
  "type": "Feature",
  "properties": {
    "tgn:hierarchy":[
        "tgn:7547897",
        "tgn:1000004",
        "tgn:7000198",
        "tgn:7016722",
        "tgn:7029392"
    ],
    "tgn:id":7547897,
    "tgn:name:en":"Ajgain",
    "tgn:placetype":[
        "aat:300008347"
    ]
},
  "bbox": [],
  "geometry": {"coordinates":[80.62869,26.619277],"type":"Point"}
}