{
  "id": 2117993,
  "type": "Feature",
  "properties": {
    "tgn:hierarchy":[
        "tgn:2117993",
        "tgn:1000001",
        "tgn:7012149",
        "tgn:2002287",
        "tgn:7013961",
        "tgn:7029392"
    ],
    "tgn:id":2117993,
    "tgn:name":"Deer Creek",
    "tgn:placetype":[
        "aat:300008347",
        "aat:300387210"
    ]
},
  "bbox": [],
  "geometry": {"coordinates":[-79.9167,38.3833],"type":"Point"}
}