{
  "id": 2334942,
  "type": "Feature",
  "properties": {
    "tgn:hierarchy":[
        "tgn:2334942",
        "tgn:1000001",
        "tgn:7012149",
        "tgn:2000208",
        "tgn:7007158",
        "tgn:7029392"
    ],
    "tgn:id":2334942,
    "tgn:name":"Forks Reservoir",
    "tgn:placetype":[
        "aat:300006191"
    ]
},
  "bbox": [],
  "geometry": {"coordinates":[-108.6167,37.7667],"type":"Point"}
}