{
  "id": 7492044,
  "type": "Feature",
  "properties": {
    "tgn:hierarchy":[
        "tgn:7492044",
        "tgn:1000004",
        "tgn:7471332",
        "tgn:1000141",
        "tgn:7029392"
    ],
    "tgn:id":7492044,
    "tgn:name":"Mabushupai",
    "tgn:placetype":[
        "aat:300008347"
    ]
},
  "bbox": [],
  "geometry": {"coordinates":[121.067778,24.708611],"type":"Point"}
}