{
  "id": 2049051,
  "type": "Feature",
  "properties": {
    "tgn:hierarchy":[
        "tgn:2049051",
        "tgn:1000001",
        "tgn:7016101",
        "tgn:7012149",
        "tgn:7007516",
        "tgn:7029392"
    ],
    "tgn:id":2049051,
    "tgn:name":"Urbana",
    "tgn:placetype":[
        "aat:300008347"
    ]
},
  "bbox": [],
  "geometry": {"coordinates":[-77.35,39.3167],"type":"Point"}
}