<<<<<<< HEAD
{
  "id": 2769324,
  "type": "Feature",
  "properties": {
    "tgn:hierarchy":[
        "tgn:2769324",
        "tgn:1000001",
        "tgn:7012149",
        "tgn:7007922",
        "tgn:7029392"
    ],
    "tgn:id":2769324,
    "tgn:name":"Wickham Valley",
    "tgn:placetype":[
        "aat:300008761"
    ]
},
  "bbox": [],
  "geometry": {"coordinates":[-91.5333,44.35],"type":"Point"}
}
=======
{"geometry":{"type":"Point","coordinates":[-91.533300,44.350000]},"type":"Feature","properties":{"hierarchy":["tgn:2769324","tgn:1000001","tgn:7012149","tgn:7007922","tgn:7029392"],"placetype":["aat:300008761"],"id":2769324,"name:xx":"Wickham Valley"}}
>>>>>>> 03f74aca74312dbeaf24d7e61306dd6a786dc3d0
