<<<<<<< HEAD
{
  "id": 7172330,
  "type": "Feature",
  "properties": {
    "tgn:hierarchy":[
        "tgn:7172330",
        "tgn:7003692",
        "tgn:1000003",
        "tgn:7000084",
        "tgn:7029392"
    ],
    "tgn:id":7172330,
    "tgn:name":"Herrenh\u00f6lzle",
    "tgn:placetype":[
        "aat:300008347"
    ]
},
  "bbox": [],
  "geometry": {"coordinates":[9.45,49.133333],"type":"Point"}
}
=======
{"geometry":{"type":"Point","coordinates":[9.450000,49.133333]},"type":"Feature","properties":{"hierarchy":["tgn:7172330","tgn:7003692","tgn:1000003","tgn:7000084","tgn:7029392"],"placetype":["aat:300008347"],"id":7172330,"name:xx":"Herrenh\u00f6lzle"}}
>>>>>>> 03f74aca74312dbeaf24d7e61306dd6a786dc3d0
