{
  "id": 2467642,
  "type": "Feature",
  "properties": {
    "tgn:hierarchy":[
        "tgn:2467642",
        "tgn:1000001",
        "tgn:7012149",
        "tgn:7007709",
        "tgn:7029392"
    ],
    "tgn:id":2467642,
    "tgn:name":"Long Hope Creek",
    "tgn:placetype":[
        "aat:300008706"
    ]
},
  "bbox": [],
  "geometry": {"coordinates":[-81.65,36.3167],"type":"Point"}
}