{
  "id": 2271332,
  "type": "Feature",
  "properties": {
    "tgn:hierarchy":[
        "tgn:2271332",
        "tgn:1000001",
        "tgn:7012149",
        "tgn:2002374",
        "tgn:7007923",
        "tgn:7029392"
    ],
    "tgn:id":2271332,
    "tgn:name":"Culp Draw",
    "tgn:placetype":[
        "aat:300008761"
    ]
},
  "bbox": [],
  "geometry": {"coordinates":[-106.0667,44.05],"type":"Point"}
}