{
  "id": 7374983,
  "type": "Feature",
  "properties": {
    "tgn:hierarchy":[
        "tgn:7374983",
        "tgn:1000001",
        "tgn:7005595",
        "tgn:7005560",
        "tgn:7029392"
    ],
    "tgn:id":7374983,
    "tgn:name":"La Cuesta de los Lugos",
    "tgn:placetype":[
        "aat:300008347"
    ]
},
  "bbox": [],
  "geometry": {"coordinates":[-108.266667,25.75],"type":"Point"}
}