{
  "id": 7566556,
  "type": "Feature",
  "properties": {
    "tgn:hierarchy":[
        "tgn:7566556",
        "tgn:1000004",
        "tgn:7000198",
        "tgn:7016722",
        "tgn:7029392"
    ],
    "tgn:id":7566556,
    "tgn:name:en":"Karanpura",
    "tgn:placetype":[
        "aat:300008347"
    ]
},
  "bbox": [],
  "geometry": {"coordinates":[79.219609,25.571171],"type":"Point"}
}