{
  "id": 7498571,
  "type": "Feature",
  "properties": {
    "tgn:hierarchy":[
        "tgn:7498571",
        "tgn:1000004",
        "tgn:7491221",
        "tgn:1000141",
        "tgn:7029392"
    ],
    "tgn:id":7498571,
    "tgn:name":"Xingchang Guoxiao",
    "tgn:placetype":[
        "aat:300006495"
    ]
},
  "bbox": [],
  "geometry": {"coordinates":[121.247749,22.893035],"type":"Point"}
}