{
  "id": 7420899,
  "type": "Feature",
  "properties": {
    "tgn:hierarchy":[
        "tgn:7420899",
        "tgn:7005579",
        "tgn:1000001",
        "tgn:7005560",
        "tgn:7029392"
    ],
    "tgn:id":7420899,
    "tgn:name":"El Rat\u00f3n",
    "tgn:placetype":[
        "aat:300008347"
    ]
},
  "bbox": [],
  "geometry": {"coordinates":[-102.4625,21.966667],"type":"Point"}
}