{
  "id": 7501603,
  "type": "Feature",
  "properties": {
    "tgn:hierarchy":[
        "tgn:7501603",
        "tgn:1000004",
        "tgn:7490934",
        "tgn:1000141",
        "tgn:7029392"
    ],
    "tgn:id":7501603,
    "tgn:name":"Shanxi",
    "tgn:placetype":[
        "aat:300008347"
    ]
},
  "bbox": [],
  "geometry": {"coordinates":[120.321111,22.964167],"type":"Point"}
}