{
  "id": 7569001,
  "type": "Feature",
  "properties": {
    "tgn:hierarchy":[
        "tgn:7569001",
        "tgn:1000004",
        "tgn:7000198",
        "tgn:1001996",
        "tgn:7029392"
    ],
    "tgn:id":7569001,
    "tgn:name:en":"Gochi",
    "tgn:placetype":[
        "aat:300008347"
    ]
},
  "bbox": [],
  "geometry": {"coordinates":[77.086043,31.15228],"type":"Point"}
}