{
  "id": 7350011,
  "type": "Feature",
  "properties": {
    "tgn:hierarchy":[
        "tgn:7350011",
        "tgn:1000001",
        "tgn:7005589",
        "tgn:7005560",
        "tgn:7029392"
    ],
    "tgn:id":7350011,
    "tgn:name":"Rancho Aguitarre\u00f1as",
    "tgn:placetype":[
        "aat:300000241"
    ]
},
  "bbox": [],
  "geometry": {"coordinates":[-100.116667,26.683333],"type":"Point"}
}