{
  "id": 7291165,
  "type": "Feature",
  "properties": {
    "tgn:hierarchy":[
        "tgn:7291165",
        "tgn:7016598",
        "tgn:1000049",
        "tgn:1000002",
        "tgn:7029392"
    ],
    "tgn:id":7291165,
    "tgn:name":"Esmeralda, Cerro",
    "tgn:placetype":[
        "aat:300008795"
    ]
},
  "bbox": [],
  "geometry": {"coordinates":[-70.55,-25.866667],"type":"Point"}
}