{
  "id": 7267625,
  "type": "Feature",
  "properties": {
    "tgn:hierarchy":[
        "tgn:7267625",
        "tgn:1000003",
        "tgn:7003613",
        "tgn:7016845",
        "tgn:7029392"
    ],
    "tgn:id":7267625,
    "tgn:name:nl":"Overschild-Tetjehorn, Polder",
    "tgn:placetype":[
        "aat:300006163"
    ]
},
  "bbox": [],
  "geometry": {"coordinates":[6.766667,53.266667],"type":"Point"}
}