{
  "id": 1134756,
  "type": "Feature",
  "properties": {
    "tgn:hierarchy":[
        "tgn:1134756",
        "tgn:1000001",
        "tgn:7012149",
        "tgn:7007826",
        "tgn:7029392"
    ],
    "tgn:id":1134756,
    "tgn:name":"Sweetwater Creek",
    "tgn:placetype":[
        "aat:300008706"
    ]
},
  "bbox": [],
  "geometry": {"coordinates":[-100.4833,32.25],"type":"Point"}
}