{
  "id": 2742797,
  "type": "Feature",
  "properties": {
    "tgn:hierarchy":[
        "tgn:2742797",
        "tgn:1000001",
        "tgn:7012149",
        "tgn:2000964",
        "tgn:7007520",
        "tgn:7029392"
    ],
    "tgn:id":2742797,
    "tgn:name":"Van Drain",
    "tgn:placetype":[
        "aat:300006075"
    ]
},
  "bbox": [],
  "geometry": {"coordinates":[-83.2333,43.8667],"type":"Point"}
}