{
  "id": 2043945,
  "type": "Feature",
  "properties": {
    "tgn:hierarchy":[
        "tgn:2043945",
        "tgn:1000001",
        "tgn:7012149",
        "tgn:2000913",
        "tgn:7007256",
        "tgn:7029392"
    ],
    "tgn:id":2043945,
    "tgn:name":"Sarepta",
    "tgn:placetype":[
        "aat:300008347"
    ]
},
  "bbox": [],
  "geometry": {"coordinates":[-93.4333,32.8833],"type":"Point"}
}