{
  "id": 2127716,
  "type": "Feature",
  "properties": {
    "tgn:hierarchy":[
        "tgn:2127716",
        "tgn:1000001",
        "tgn:7012149",
        "tgn:2001452",
        "tgn:7007566",
        "tgn:7029392"
    ],
    "tgn:id":2127716,
    "tgn:name":"Alamo Canyon",
    "tgn:placetype":[
        "aat:300008761"
    ]
},
  "bbox": [],
  "geometry": {"coordinates":[-107.8167,36.85],"type":"Point"}
}