<<<<<<< HEAD
{
  "id": 7110058,
  "type": "Feature",
  "properties": {
    "tgn:hierarchy":[
        "tgn:7110058",
        "tgn:1000003",
        "tgn:7003676",
        "tgn:7000084",
        "tgn:7029392"
    ],
    "tgn:id":7110058,
    "tgn:name":"Ravenswiede",
    "tgn:placetype":[
        "aat:300000206"
    ]
},
  "bbox": [],
  "geometry": {"coordinates":[9.2,52.666667],"type":"Point"}
}
=======
{"geometry":{"type":"Point","coordinates":[9.200000,52.666667]},"type":"Feature","properties":{"hierarchy":["tgn:7110058","tgn:1000003","tgn:7003676","tgn:7000084","tgn:7029392"],"placetype":["aat:300000206"],"id":7110058,"name:xx":"Ravenswiede"}}
>>>>>>> 03f74aca74312dbeaf24d7e61306dd6a786dc3d0
