{
  "id": 2750407,
  "type": "Feature",
  "properties": {
    "tgn:hierarchy":[
        "tgn:2750407",
        "tgn:1000001",
        "tgn:7012149",
        "tgn:2002300",
        "tgn:7013961",
        "tgn:7029392"
    ],
    "tgn:id":2750407,
    "tgn:name":"Waneta",
    "tgn:placetype":[
        "aat:300008347"
    ]
},
  "bbox": [],
  "geometry": {"coordinates":[-80.2333,38.5333],"type":"Point"}
}