{
  "id": 7038715,
  "type": "Feature",
  "properties": {
    "tgn:hierarchy":[
        "tgn:7038715",
        "tgn:1003506",
        "tgn:1000003",
        "tgn:7002993",
        "tgn:1000080",
        "tgn:7029392"
    ],
    "tgn:id":7038715,
    "tgn:name":"Tenchia, Monte",
    "tgn:placetype":[
        "aat:300008795"
    ]
},
  "bbox": [],
  "geometry": {"coordinates":[12.966667,46.55],"type":"Point"}
}