{
  "id": 2666685,
  "type": "Feature",
  "properties": {
    "tgn:hierarchy":[
        "tgn:2666685",
        "tgn:1000001",
        "tgn:7012149",
        "tgn:2000491",
        "tgn:7007250",
        "tgn:7029392"
    ],
    "tgn:id":2666685,
    "tgn:name":"Sixteen-to-One Mine",
    "tgn:placetype":[
        "aat:300000390"
    ]
},
  "bbox": [],
  "geometry": {"coordinates":[-115.8667,47.5333],"type":"Point"}
}