<<<<<<< HEAD
{
  "id": 7175843,
  "type": "Feature",
  "properties": {
    "tgn:hierarchy":[
        "tgn:7175843",
        "tgn:1000003",
        "tgn:7003677",
        "tgn:7000084",
        "tgn:7029392"
    ],
    "tgn:id":7175843,
    "tgn:name":"Gro\u00df Vosbeck",
    "tgn:placetype":[
        "aat:300000206"
    ]
},
  "bbox": [],
  "geometry": {"coordinates":[7.05,51.7],"type":"Point"}
}
=======
{"geometry":{"type":"Point","coordinates":[7.050000,51.700000]},"type":"Feature","properties":{"hierarchy":["tgn:7175843","tgn:1000003","tgn:7003677","tgn:7000084","tgn:7029392"],"placetype":["aat:300000206"],"id":7175843,"name:xx":"Gro\u00df Vosbeck"}}
>>>>>>> 03f74aca74312dbeaf24d7e61306dd6a786dc3d0
