{
  "id": 2487623,
  "type": "Feature",
  "properties": {
    "tgn:hierarchy":[
        "tgn:2487623",
        "tgn:1000001",
        "tgn:2002107",
        "tgn:7012149",
        "tgn:7007827",
        "tgn:7029392"
    ],
    "tgn:id":2487623,
    "tgn:name":"Left Fork Indian Canyon",
    "tgn:placetype":[
        "aat:300008761"
    ]
},
  "bbox": [],
  "geometry": {"coordinates":[-110.7333,39.8833],"type":"Point"}
}