{
  "id": 2759062,
  "type": "Feature",
  "properties": {
    "tgn:hierarchy":[
        "tgn:2759062",
        "tgn:1000001",
        "tgn:7012149",
        "tgn:2000480",
        "tgn:7007250",
        "tgn:7029392"
    ],
    "tgn:id":2759062,
    "tgn:name":"West Fork Big Bear Creek",
    "tgn:placetype":[
        "aat:300008706"
    ]
},
  "bbox": [],
  "geometry": {"coordinates":[-116.7167,46.8333],"type":"Point"}
}