{
  "id": 7581078,
  "type": "Feature",
  "properties": {
    "tgn:hierarchy":[
        "tgn:7581078",
        "tgn:1001828",
        "tgn:1000004",
        "tgn:7000198",
        "tgn:7029392"
    ],
    "tgn:id":7581078,
    "tgn:name:en":"Vardamankot",
    "tgn:placetype":[
        "aat:300008347"
    ]
},
  "bbox": [],
  "geometry": {"coordinates":[79.45,17.366667],"type":"Point"}
}