{
  "id": 7026393,
  "type": "Feature",
  "properties": {
    "tgn:hierarchy":[
        "tgn:7026393",
        "tgn:7002445",
        "tgn:1000003",
        "tgn:7026382",
        "tgn:7008591",
        "tgn:7029392"
    ],
    "tgn:id":7026393,
    "tgn:name":"Bagnor",
    "tgn:placetype":[
        "aat:300008347",
        "aat:300008372"
    ]
},
  "bbox": [],
  "geometry": {"coordinates":[-1.35,51.4167],"type":"Point"}
}