{
  "id": 6002572,
  "type": "Feature",
  "properties": {
    "tgn:hierarchy":[
        "tgn:6002572",
        "tgn:7024123",
        "tgn:1000003",
        "tgn:7006366",
        "tgn:7029392"
    ],
    "tgn:id":6002572,
    "tgn:name":"Da\u031cbromierz",
    "tgn:placetype":[
        "aat:300008347",
        "aat:300000835",
        "aat:300008375"
    ]
},
  "bbox": [],
  "geometry": {"coordinates":[16.25,50.9167],"type":"Point"}
}