{
  "id": 2305356,
  "type": "Feature",
  "properties": {
    "tgn:hierarchy":[
        "tgn:2305356",
        "tgn:1000001",
        "tgn:1002347",
        "tgn:7012149",
        "tgn:7007568",
        "tgn:7029392"
    ],
    "tgn:id":2305356,
    "tgn:name":"East Branch Wappinger Creek",
    "tgn:placetype":[
        "aat:300008706"
    ]
},
  "bbox": [],
  "geometry": {"coordinates":[-73.6833,41.7833],"type":"Point"}
}