{
  "id": 7035921,
  "type": "Feature",
  "properties": {
    "tgn:hierarchy":[
        "tgn:7035921",
        "tgn:1003506",
        "tgn:1000003",
        "tgn:7002993",
        "tgn:1000080",
        "tgn:7029392"
    ],
    "tgn:id":7035921,
    "tgn:name":"San Giacomo, Monte",
    "tgn:placetype":[
        "aat:300008795"
    ]
},
  "bbox": [],
  "geometry": {"coordinates":[12.731667,46.506944],"type":"Point"}
}