{
  "id": 1047093,
  "type": "Feature",
  "properties": {
    "tgn:hierarchy":[
        "tgn:1047093",
        "tgn:7003162",
        "tgn:1000003",
        "tgn:7009760",
        "tgn:1000080",
        "tgn:7029392"
    ],
    "tgn:id":1047093,
    "tgn:name":"Terranuova Bracciolini",
    "tgn:placetype":[
        "aat:300008347"
    ]
},
  "bbox": [],
  "geometry": {"coordinates":[11.583333,43.55],"type":"Point"}
}