{
  "id": 7219499,
  "type": "Feature",
  "properties": {
    "tgn:hierarchy":[
        "tgn:7219499",
        "tgn:7011167",
        "tgn:7001338",
        "tgn:1000003",
        "tgn:1000074",
        "tgn:7029392"
    ],
    "tgn:id":7219499,
    "tgn:name":"Vli\u00f3tis, \u00c1kra",
    "tgn:placetype":[
        "aat:300008850"
    ]
},
  "bbox": [],
  "geometry": {"coordinates":[20.566667,38.466667],"type":"Point"}
}