{
  "id": 7175581,
  "type": "Feature",
  "properties": {
    "tgn:hierarchy":[
        "tgn:7175581",
        "tgn:7003669",
        "tgn:1000003",
        "tgn:7000084",
        "tgn:7029392"
    ],
    "tgn:id":7175581,
    "tgn:name":"Gro\u00dfziegenfeld",
    "tgn:placetype":[
        "aat:300008347"
    ]
},
  "bbox": [],
  "geometry": {"coordinates":[11.183333,50.033333],"type":"Point"}
}