{
  "id": 1085575,
  "type": "Feature",
  "properties": {
    "tgn:hierarchy":[
        "tgn:1085575",
        "tgn:7005194",
        "tgn:1000004",
        "tgn:7000977",
        "tgn:1000142",
        "tgn:7029392"
    ],
    "tgn:id":1085575,
    "tgn:name":"Lap Lae",
    "tgn:placetype":[
        "aat:300008347"
    ]
},
  "bbox": [],
  "geometry": {"coordinates":[100.0167,17.6333],"type":"Point"}
}