{
  "id": 7582331,
  "type": "Feature",
  "properties": {
    "tgn:hierarchy":[
        "tgn:7582331",
        "tgn:1000004",
        "tgn:7000198",
        "tgn:7016722",
        "tgn:7029392"
    ],
    "tgn:id":7582331,
    "tgn:name:en":"Taua N\u0101la",
    "tgn:placetype":[
        "aat:300008699"
    ]
},
  "bbox": [],
  "geometry": {"coordinates":[78.388036,24.802951],"type":"Point"}
}