<<<<<<< HEAD
{
  "id": 7482786,
  "type": "Feature",
  "properties": {
    "tgn:hierarchy":[
        "tgn:7482786",
        "tgn:1000004",
        "tgn:7490934",
        "tgn:1000141",
        "tgn:7029392"
    ],
    "tgn:id":7482786,
    "tgn:name":"Daludong",
    "tgn:placetype":[
        "aat:300008347"
    ]
},
  "bbox": [],
  "geometry": {"coordinates":[120.2225,22.963611],"type":"Point"}
}
=======
{"geometry":{"type":"Point","coordinates":[120.222500,22.963611]},"type":"Feature","properties":{"hierarchy":["tgn:7482786","tgn:1000004","tgn:7490934","tgn:1000141","tgn:7029392"],"placetype":["aat:300008347"],"id":7482786,"name:xx":"Daludong"}}
>>>>>>> 03f74aca74312dbeaf24d7e61306dd6a786dc3d0
