{
  "id": 7427076,
  "type": "Feature",
  "properties": {
    "tgn:hierarchy":[
        "tgn:7427076",
        "tgn:7005581",
        "tgn:1000001",
        "tgn:7005560",
        "tgn:7029392"
    ],
    "tgn:id":7427076,
    "tgn:name":"Las Playas",
    "tgn:placetype":[
        "aat:300008347"
    ]
},
  "bbox": [],
  "geometry": {"coordinates":[-106.733333,27.55],"type":"Point"}
}