{
  "id": 2534507,
  "type": "Feature",
  "properties": {
    "tgn:hierarchy":[
        "tgn:2534507",
        "tgn:1000001",
        "tgn:7012149",
        "tgn:2001282",
        "tgn:7007524",
        "tgn:7029392"
    ],
    "tgn:id":2534507,
    "tgn:name":"NW NE Section 2 Mine",
    "tgn:placetype":[
        "aat:300000390"
    ]
},
  "bbox": [],
  "geometry": {"coordinates":[-110.5333,46.9167],"type":"Point"}
}