{
  "id": 2709120,
  "type": "Feature",
  "properties": {
    "tgn:hierarchy":[
        "tgn:2709120",
        "tgn:1000001",
        "tgn:7012149",
        "tgn:7007709",
        "tgn:7029392"
    ],
    "tgn:id":2709120,
    "tgn:name":"Tabbs Creek",
    "tgn:placetype":[
        "aat:300008706"
    ]
},
  "bbox": [],
  "geometry": {"coordinates":[-78.5333,36.35],"type":"Point"}
}