<<<<<<< HEAD
{
  "id": 7354047,
  "type": "Feature",
  "properties": {
    "tgn:hierarchy":[
        "tgn:7354047",
        "tgn:7005586",
        "tgn:1000001",
        "tgn:7005560",
        "tgn:7029392"
    ],
    "tgn:id":7354047,
    "tgn:name":"Chamela",
    "tgn:placetype":[
        "aat:300266554",
        "aat:300008699"
    ]
},
  "bbox": [],
  "geometry": {"coordinates":[-105.066667,19.533333],"type":"Point"}
}
=======
{"geometry":{"type":"Point","coordinates":[-105.066667,19.533333]},"type":"Feature","properties":{"hierarchy":["tgn:7354047","tgn:7005586","tgn:1000001","tgn:7005560","tgn:7029392"],"placetype":["aat:300266554","aat:300008699"],"id":7354047,"name:xx":"Chamela"}}
>>>>>>> 03f74aca74312dbeaf24d7e61306dd6a786dc3d0
