{
  "id": 7070199,
  "type": "Feature",
  "properties": {
    "tgn:hierarchy":[
        "tgn:7070199",
        "tgn:7003669",
        "tgn:1000003",
        "tgn:7000084",
        "tgn:7029392"
    ],
    "tgn:id":7070199,
    "tgn:name":"Stein-Berg",
    "tgn:placetype":[
        "aat:300008777"
    ]
},
  "bbox": [],
  "geometry": {"coordinates":[11.133333,49.766667],"type":"Point"}
}