{
  "id": 2446483,
  "type": "Feature",
  "properties": {
    "tgn:hierarchy":[
        "tgn:2446483",
        "tgn:1000001",
        "tgn:7012149",
        "tgn:2001247",
        "tgn:7007523",
        "tgn:7029392"
    ],
    "tgn:id":2446483,
    "tgn:name":"Lewis Lake",
    "tgn:placetype":[
        "aat:300006191"
    ]
},
  "bbox": [],
  "geometry": {"coordinates":[-91.3167,37.0333],"type":"Point"}
}