{
  "id": 1018175,
  "type": "Feature",
  "properties": {
    "tgn:hierarchy":[
        "tgn:1018175",
        "tgn:1000001",
        "tgn:1001893",
        "tgn:7005560",
        "tgn:7029392"
    ],
    "tgn:id":1018175,
    "tgn:name":"San Francisco Tlalcilalcalpa",
    "tgn:placetype":[
        "aat:300008347"
    ]
},
  "bbox": [],
  "geometry": {"coordinates":[-99.777778,19.292778],"type":"Point"}
}