{
  "id": 7333828,
  "type": "Feature",
  "properties": {
    "tgn:hierarchy":[
        "tgn:7333828",
        "tgn:7002759",
        "tgn:7008909",
        "tgn:1000003",
        "tgn:1000095",
        "tgn:7029392"
    ],
    "tgn:id":7333828,
    "tgn:name":"Eriste, Collado",
    "tgn:placetype":[
        "aat:300259572"
    ]
},
  "bbox": [],
  "geometry": {"coordinates":[0.468626,42.640917],"type":"Point"}
}