{
  "id": 6005494,
  "type": "Feature",
  "properties": {
    "tgn:hierarchy":[
        "tgn:6005494",
        "tgn:1000004",
        "tgn:1001352",
        "tgn:7000231",
        "tgn:7029392"
    ],
    "tgn:id":6005494,
    "tgn:name":"Sirjan",
    "tgn:placetype":[
        "aat:300008347",
        "aat:300008375"
    ]
},
  "bbox": [],
  "geometry": {"coordinates":[55.7333,29.4667],"type":"Point"}
}