{
  "id": 7008428,
  "type": "Feature",
  "properties": {
    "tgn:hierarchy":[
        "tgn:7008428",
        "tgn:7002443",
        "tgn:1000003",
        "tgn:7018974",
        "tgn:7008591",
        "tgn:7029392"
    ],
    "tgn:id":7008428,
    "tgn:name:en":"Margam",
    "tgn:placetype":[
        "aat:300008347"
    ]
},
  "bbox": [],
  "geometry": {"coordinates":[-3.743333,51.562222],"type":"Point"}
}