{
  "id": 2012039,
  "type": "Feature",
  "properties": {
    "tgn:hierarchy":[
        "tgn:2012039",
        "tgn:1000001",
        "tgn:7012149",
        "tgn:7007157",
        "tgn:1002710",
        "tgn:7029392"
    ],
    "tgn:id":2012039,
    "tgn:name":"La Barr Meadows",
    "tgn:placetype":[
        "aat:300008347"
    ]
},
  "bbox": [],
  "geometry": {"coordinates":[-121.0333,39.1667],"type":"Point"}
}