<<<<<<< HEAD
{
  "id": 2767067,
  "type": "Feature",
  "properties": {
    "tgn:hierarchy":[
        "tgn:2767067",
        "tgn:1000001",
        "tgn:7012149",
        "tgn:2000226",
        "tgn:7007158",
        "tgn:7029392"
    ],
    "tgn:id":2767067,
    "tgn:name":"White Rock",
    "tgn:placetype":[
        "aat:300008798"
    ]
},
  "bbox": [],
  "geometry": {"coordinates":[-105.4833,40.6167],"type":"Point"}
}
=======
{"geometry":{"type":"Point","coordinates":[-105.483300,40.616700]},"type":"Feature","properties":{"hierarchy":["tgn:2767067","tgn:1000001","tgn:7012149","tgn:2000226","tgn:7007158","tgn:7029392"],"placetype":["aat:300008798"],"id":2767067,"name:xx":"White Rock"}}
>>>>>>> 03f74aca74312dbeaf24d7e61306dd6a786dc3d0
