{
  "id": 1037061,
  "type": "Feature",
  "properties": {
    "tgn:hierarchy":[
        "tgn:1037061",
        "tgn:7000096",
        "tgn:1000003",
        "tgn:7000084",
        "tgn:7029392"
    ],
    "tgn:id":1037061,
    "tgn:name":"Kiekebusch",
    "tgn:placetype":[
        "aat:300008347"
    ]
},
  "bbox": [],
  "geometry": {"coordinates":[13.55,52.35],"type":"Point"}
}