{
  "id": 1019251,
  "type": "Feature",
  "properties": {
    "tgn:hierarchy":[
        "tgn:1019251",
        "tgn:7006477",
        "tgn:1001519",
        "tgn:1000002",
        "tgn:7029392"
    ],
    "tgn:id":1019251,
    "tgn:name":"Calingasta",
    "tgn:placetype":[
        "aat:300008347"
    ]
},
  "bbox": [],
  "geometry": {"coordinates":[-69.3333,-31.3333],"type":"Point"}
}