{
  "id": 7261290,
  "type": "Feature",
  "properties": {
    "tgn:hierarchy":[
        "tgn:7261290",
        "tgn:1000003",
        "tgn:7003627",
        "tgn:7016845",
        "tgn:7029392"
    ],
    "tgn:id":7261290,
    "tgn:name:nl":"De Paltz",
    "tgn:placetype":[
        "aat:300387200"
    ]
},
  "bbox": [],
  "geometry": {"coordinates":[5.283333,52.133333],"type":"Point"}
}