{
  "id": 2685603,
  "type": "Feature",
  "properties": {
    "tgn:hierarchy":[
        "tgn:2685603",
        "tgn:1000001",
        "tgn:7012149",
        "tgn:1003038",
        "tgn:7007517",
        "tgn:7029392"
    ],
    "tgn:id":2685603,
    "tgn:name":"Spring Basin",
    "tgn:placetype":[
        "aat:300008680"
    ]
},
  "bbox": [],
  "geometry": {"coordinates":[-71.7667,42.4667],"type":"Point"}
}