{
  "id": 2662979,
  "type": "Feature",
  "properties": {
    "tgn:hierarchy":[
        "tgn:2662979",
        "tgn:1000001",
        "tgn:7012149",
        "tgn:2000217",
        "tgn:7007158",
        "tgn:7029392"
    ],
    "tgn:id":2662979,
    "tgn:name":"Silver Basin",
    "tgn:placetype":[
        "aat:300386845"
    ]
},
  "bbox": [],
  "geometry": {"coordinates":[-107.1167,38.9167],"type":"Point"}
}