{
  "id": 1126417,
  "type": "Feature",
  "properties": {
    "tgn:hierarchy":[
        "tgn:1126417",
        "tgn:1000004",
        "tgn:7002077",
        "tgn:1000111",
        "tgn:7029392"
    ],
    "tgn:id":1126417,
    "tgn:name":"Luan",
    "tgn:placetype":[
        "aat:300008707"
    ]
},
  "bbox": [],
  "geometry": {"coordinates":[119.1667,39.3333],"type":"Point"}
}