{
  "id": 7504822,
  "type": "Feature",
  "properties": {
    "tgn:hierarchy":[
        "tgn:7504822",
        "tgn:1009227",
        "tgn:1000226",
        "tgn:7016729",
        "tgn:1000006",
        "tgn:7029392"
    ],
    "tgn:id":7504822,
    "tgn:name:en":"Pillar Creek",
    "tgn:placetype":[
        "aat:300008699"
    ]
},
  "bbox": [],
  "geometry": {"coordinates":[173.383333,-41.171389],"type":"Point"}
}