{
  "id": 2478292,
  "type": "Feature",
  "properties": {
    "tgn:hierarchy":[
        "tgn:2478292",
        "tgn:1000001",
        "tgn:1002985",
        "tgn:7012149",
        "tgn:7007565",
        "tgn:7029392"
    ],
    "tgn:id":2478292,
    "tgn:name":"Macks Island",
    "tgn:placetype":[
        "aat:300008791"
    ]
},
  "bbox": [],
  "geometry": {"coordinates":[-75.0667,40.8333],"type":"Point"}
}