{
  "id": 7435597,
  "type": "Feature",
  "properties": {
    "tgn:hierarchy":[
        "tgn:7435597",
        "tgn:1000001",
        "tgn:7005594",
        "tgn:7005560",
        "tgn:7029392"
    ],
    "tgn:id":7435597,
    "tgn:name":"Villitas",
    "tgn:placetype":[
        "aat:300008347"
    ]
},
  "bbox": [],
  "geometry": {"coordinates":[-99.533333,22.033333],"type":"Point"}
}