{
  "id": 2552078,
  "type": "Feature",
  "properties": {
    "tgn:hierarchy":[
        "tgn:2552078",
        "tgn:1000001",
        "tgn:7012149",
        "tgn:2001713",
        "tgn:7007708",
        "tgn:7029392"
    ],
    "tgn:id":2552078,
    "tgn:name":"Number One Creek",
    "tgn:placetype":[
        "aat:300008706"
    ]
},
  "bbox": [],
  "geometry": {"coordinates":[-123.55,42.65],"type":"Point"}
}