{
  "id": 2441883,
  "type": "Feature",
  "properties": {
    "tgn:hierarchy":[
        "tgn:2441883",
        "tgn:1000001",
        "tgn:7012149",
        "tgn:7007157",
        "tgn:1002566",
        "tgn:7029392"
    ],
    "tgn:id":2441883,
    "tgn:name":"Konocti Bay",
    "tgn:placetype":[
        "aat:300132316"
    ]
},
  "bbox": [],
  "geometry": {"coordinates":[-122.7167,38.9667],"type":"Point"}
}