{
  "id": 2734846,
  "type": "Feature",
  "properties": {
    "tgn:hierarchy":[
        "tgn:2734846",
        "tgn:1000001",
        "tgn:7012149",
        "tgn:2001031",
        "tgn:7007521",
        "tgn:7029392"
    ],
    "tgn:id":2734846,
    "tgn:name":"Twelve, Lake",
    "tgn:placetype":[
        "aat:300008680"
    ]
},
  "bbox": [],
  "geometry": {"coordinates":[-93.05,46.1333],"type":"Point"}
}