{
  "id": 2432771,
  "type": "Feature",
  "properties": {
    "tgn:hierarchy":[
        "tgn:2432771",
        "tgn:1000001",
        "tgn:7012149",
        "tgn:2000378",
        "tgn:7007248",
        "tgn:7029392"
    ],
    "tgn:id":2432771,
    "tgn:name":"Keenes Crossing",
    "tgn:placetype":[
        "aat:300008347"
    ]
},
  "bbox": [],
  "geometry": {"coordinates":[-82.7333,32.5833],"type":"Point"}
}