<<<<<<< HEAD
{
  "id": 2259033,
  "type": "Feature",
  "properties": {
    "tgn:hierarchy":[
        "tgn:2259033",
        "tgn:1000001",
        "tgn:7012149",
        "tgn:2002113",
        "tgn:7007827",
        "tgn:7029392"
    ],
    "tgn:id":2259033,
    "tgn:name":"Cottonwood Creek",
    "tgn:placetype":[
        "aat:300008706"
    ]
},
  "bbox": [],
  "geometry": {"coordinates":[-111.85,37.4667],"type":"Point"}
}
=======
{"geometry":{"type":"Point","coordinates":[-111.850000,37.466700]},"type":"Feature","properties":{"hierarchy":["tgn:2259033","tgn:1000001","tgn:7012149","tgn:2002113","tgn:7007827","tgn:7029392"],"placetype":["aat:300008706"],"id":2259033,"name:xx":"Cottonwood Creek"}}
>>>>>>> 03f74aca74312dbeaf24d7e61306dd6a786dc3d0
