{
  "id": 2360510,
  "type": "Feature",
  "properties": {
    "tgn:hierarchy":[
        "tgn:2360510",
        "tgn:1000001",
        "tgn:7012149",
        "tgn:2000181",
        "tgn:7007157",
        "tgn:7029392"
    ],
    "tgn:id":2360510,
    "tgn:name":"Grassy Creek",
    "tgn:placetype":[
        "aat:300008706"
    ]
},
  "bbox": [],
  "geometry": {"coordinates":[-124.0667,41.05],"type":"Point"}
}