{
  "id": 2430037,
  "type": "Feature",
  "properties": {
    "tgn:hierarchy":[
        "tgn:2430037",
        "tgn:1002648",
        "tgn:1000001",
        "tgn:7019158",
        "tgn:7012149",
        "tgn:7007249",
        "tgn:7029392"
    ],
    "tgn:id":2430037,
    "tgn:name":"Kaea Point",
    "tgn:placetype":[
        "aat:300008850"
    ]
},
  "bbox": [],
  "geometry": {"coordinates":[-156.6667,20.9667],"type":"Point"}
}