{
  "id": 7412020,
  "type": "Feature",
  "properties": {
    "tgn:hierarchy":[
        "tgn:7412020",
        "tgn:7005587",
        "tgn:1000001",
        "tgn:7005560",
        "tgn:7029392"
    ],
    "tgn:id":7412020,
    "tgn:name:es":"El Susto",
    "tgn:placetype":[
        "aat:300008347"
    ]
},
  "bbox": [],
  "geometry": {"coordinates":[-98.483333,20.058333],"type":"Point"}
}