{
  "id": 7577580,
  "type": "Feature",
  "properties": {
    "tgn:hierarchy":[
        "tgn:7577580",
        "tgn:7001819",
        "tgn:1000004",
        "tgn:7000198",
        "tgn:7029392"
    ],
    "tgn:id":7577580,
    "tgn:name:en":"Longju",
    "tgn:placetype":[
        "aat:300008347"
    ]
},
  "bbox": [],
  "geometry": {"coordinates":[93.55,28.633333],"type":"Point"}
}