{
  "id": 2697130,
  "type": "Feature",
  "properties": {
    "tgn:hierarchy":[
        "tgn:2697130",
        "tgn:1000001",
        "tgn:7012149",
        "tgn:7007828",
        "tgn:7029392"
    ],
    "tgn:id":2697130,
    "tgn:name":"Stony Brook",
    "tgn:placetype":[
        "aat:300008699"
    ]
},
  "bbox": [],
  "geometry": {"coordinates":[-72.7333,43.6667],"type":"Point"}
}