{
  "id": 7438805,
  "type": "Feature",
  "properties": {
    "tgn:hierarchy":[
        "tgn:7438805",
        "tgn:1000001",
        "tgn:7005588",
        "tgn:7005560",
        "tgn:7029392"
    ],
    "tgn:id":7438805,
    "tgn:name":"Ticum\u00e1n",
    "tgn:placetype":[
        "aat:300008347"
    ]
},
  "bbox": [],
  "geometry": {"coordinates":[-99.116667,18.75],"type":"Point"}
}