{
  "id": 2545624,
  "type": "Feature",
  "properties": {
    "tgn:hierarchy":[
        "tgn:2545624",
        "tgn:1000001",
        "tgn:7012149",
        "tgn:1002599",
        "tgn:7007708",
        "tgn:7029392"
    ],
    "tgn:id":2545624,
    "tgn:name":"North Fork Cascade Creek",
    "tgn:placetype":[
        "aat:300008706"
    ]
},
  "bbox": [],
  "geometry": {"coordinates":[-123.8667,44.3333],"type":"Point"}
}