{
  "id": 2397125,
  "type": "Feature",
  "properties": {
    "tgn:hierarchy":[
        "tgn:2397125",
        "tgn:1000001",
        "tgn:7012149",
        "tgn:1002997",
        "tgn:7007826",
        "tgn:7029392"
    ],
    "tgn:id":2397125,
    "tgn:name":"Homeymeyer Mountain",
    "tgn:placetype":[
        "aat:300008798"
    ]
},
  "bbox": [],
  "geometry": {"coordinates":[-96.6667,30.15],"type":"Point"}
}