{
  "id": 2228608,
  "type": "Feature",
  "properties": {
    "tgn:hierarchy":[
        "tgn:2228608",
        "tgn:1000001",
        "tgn:7012149",
        "tgn:2002361",
        "tgn:7007922",
        "tgn:7029392"
    ],
    "tgn:id":2228608,
    "tgn:name":"Cedar Creek",
    "tgn:placetype":[
        "aat:300008706"
    ]
},
  "bbox": [],
  "geometry": {"coordinates":[-88.75,44.4333],"type":"Point"}
}