{
  "id": 7314519,
  "type": "Feature",
  "properties": {
    "tgn:hierarchy":[
        "tgn:7314519",
        "tgn:1001699",
        "tgn:1000049",
        "tgn:1000002",
        "tgn:7029392"
    ],
    "tgn:id":7314519,
    "tgn:name":"Linagua, Isla",
    "tgn:placetype":[
        "aat:300008791"
    ]
},
  "bbox": [],
  "geometry": {"coordinates":[-73.733333,-43.15],"type":"Point"}
}