{
  "id": 7276050,
  "type": "Feature",
  "properties": {
    "tgn:hierarchy":[
        "tgn:7276050",
        "tgn:1001692",
        "tgn:1000049",
        "tgn:1000002",
        "tgn:7029392"
    ],
    "tgn:id":7276050,
    "tgn:name":"Tir\u00faa, Cabo",
    "tgn:placetype":[
        "aat:300386846"
    ]
},
  "bbox": [],
  "geometry": {"coordinates":[-73.533333,-38.383333],"type":"Point"}
}