<<<<<<< HEAD
{
  "id": 7245661,
  "type": "Feature",
  "properties": {
    "tgn:hierarchy":[
        "tgn:7245661",
        "tgn:7007877",
        "tgn:1000003",
        "tgn:1000063",
        "tgn:4012014",
        "tgn:7029392"
    ],
    "tgn:id":7245661,
    "tgn:name":"Claire Haie",
    "tgn:placetype":[
        "aat:300008347"
    ]
},
  "bbox": [],
  "geometry": {"coordinates":[4.246543,50.544316],"type":"Point"}
}
=======
{"geometry":{"type":"Point","coordinates":[4.246543,50.544316]},"type":"Feature","properties":{"hierarchy":["tgn:7245661","tgn:7007877","tgn:1000003","tgn:1000063","tgn:4012014","tgn:7029392"],"placetype":["aat:300008347"],"id":7245661,"name:xx":"Claire Haie"}}
>>>>>>> 03f74aca74312dbeaf24d7e61306dd6a786dc3d0
