{
  "id": 2285010,
  "type": "Feature",
  "properties": {
    "tgn:hierarchy":[
        "tgn:2285010",
        "tgn:1000001",
        "tgn:7013387",
        "tgn:7012149",
        "tgn:7007710",
        "tgn:7029392"
    ],
    "tgn:id":2285010,
    "tgn:name":"Devil Head",
    "tgn:placetype":[
        "aat:300008798"
    ]
},
  "bbox": [],
  "geometry": {"coordinates":[-75.6167,40.4333],"type":"Point"}
}