{
  "id": 7419159,
  "type": "Feature",
  "properties": {
    "tgn:hierarchy":[
        "tgn:7419159",
        "tgn:1000001",
        "tgn:7005589",
        "tgn:7005560",
        "tgn:7029392"
    ],
    "tgn:id":7419159,
    "tgn:name:es":"Las Cobras, Laguna",
    "tgn:placetype":[
        "aat:300008680"
    ]
},
  "bbox": [],
  "geometry": {"coordinates":[-100.245833,27.43],"type":"Point"}
}