{
  "id": 7401232,
  "type": "Feature",
  "properties": {
    "tgn:hierarchy":[
        "tgn:7401232",
        "tgn:1000001",
        "tgn:7005599",
        "tgn:7005560",
        "tgn:7029392"
    ],
    "tgn:id":7401232,
    "tgn:name":"Matlalapa",
    "tgn:placetype":[
        "aat:300008347"
    ]
},
  "bbox": [],
  "geometry": {"coordinates":[-97.083333,19.469444],"type":"Point"}
}