{
  "id": 7386902,
  "type": "Feature",
  "properties": {
    "tgn:hierarchy":[
        "tgn:7386902",
        "tgn:7005586",
        "tgn:1000001",
        "tgn:7005560",
        "tgn:7029392"
    ],
    "tgn:id":7386902,
    "tgn:name":"Providencia",
    "tgn:placetype":[
        "aat:300007783"
    ]
},
  "bbox": [],
  "geometry": {"coordinates":[-103.533333,19.766667],"type":"Point"}
}