{
  "id": 7110581,
  "type": "Feature",
  "properties": {
    "tgn:hierarchy":[
        "tgn:7110581",
        "tgn:7003669",
        "tgn:1000003",
        "tgn:7000084",
        "tgn:7029392"
    ],
    "tgn:id":7110581,
    "tgn:name":"Rainer Berg",
    "tgn:placetype":[
        "aat:300008795"
    ]
},
  "bbox": [],
  "geometry": {"coordinates":[11.833333,47.733333],"type":"Point"}
}