{
  "id": 2009026,
  "type": "Feature",
  "properties": {
    "tgn:hierarchy":[
        "tgn:2009026",
        "tgn:1000001",
        "tgn:7016172",
        "tgn:7012149",
        "tgn:2000164",
        "tgn:7029392"
    ],
    "tgn:id":2009026,
    "tgn:name":"Natural Steps",
    "tgn:placetype":[
        "aat:300008347"
    ]
},
  "bbox": [],
  "geometry": {"coordinates":[-92.4667,34.85],"type":"Point"}
}