{
  "id": 7271507,
  "type": "Feature",
  "properties": {
    "tgn:concordances":{
        "gn:id":"2746458"
    },
    "tgn:hierarchy":[
        "tgn:7271507",
        "tgn:1000003",
        "tgn:7003622",
        "tgn:7016845",
        "tgn:7029392"
    ],
    "tgn:id":7271507,
    "tgn:name:nl":"Terhagen",
    "tgn:placetype":[
        "aat:300008347"
    ]
},
  "bbox": [],
  "geometry": {"coordinates":[5.75,50.95],"type":"Point"}
}