{
  "id": 2260104,
  "type": "Feature",
  "properties": {
    "tgn:hierarchy":[
        "tgn:2260104",
        "tgn:1000001",
        "tgn:7012149",
        "tgn:2002129",
        "tgn:7007827",
        "tgn:7029392"
    ],
    "tgn:id":2260104,
    "tgn:name":"Country Club Heights Addition",
    "tgn:placetype":[
        "aat:300008347"
    ]
},
  "bbox": [],
  "geometry": {"coordinates":[-111.9667,41.1833],"type":"Point"}
}