{
  "id": 7412178,
  "type": "Feature",
  "properties": {
    "tgn:hierarchy":[
        "tgn:7412178",
        "tgn:7005580",
        "tgn:1000001",
        "tgn:7005560",
        "tgn:7029392"
    ],
    "tgn:id":7412178,
    "tgn:name:es":"Ignacio Allende",
    "tgn:placetype":[
        "aat:300008347"
    ]
},
  "bbox": [],
  "geometry": {"coordinates":[-93.3625,17.791667],"type":"Point"}
}