{
  "id": 7415479,
  "type": "Feature",
  "properties": {
    "tgn:hierarchy":[
        "tgn:7415479",
        "tgn:1000001",
        "tgn:7005591",
        "tgn:7005560",
        "tgn:7029392"
    ],
    "tgn:id":7415479,
    "tgn:name:es":"El Campanario, Cerro",
    "tgn:placetype":[
        "aat:300008795"
    ]
},
  "bbox": [],
  "geometry": {"coordinates":[-96.069444,16.406111],"type":"Point"}
}