{
  "id": 7081080,
  "type": "Feature",
  "properties": {
    "tgn:hierarchy":[
        "tgn:7081080",
        "tgn:1000003",
        "tgn:7003687",
        "tgn:7000084",
        "tgn:7029392"
    ],
    "tgn:id":7081080,
    "tgn:name":"Winkelbusch",
    "tgn:placetype":[
        "aat:300386990"
    ]
},
  "bbox": [],
  "geometry": {"coordinates":[13.133333,51.816667],"type":"Point"}
}