{
  "id": 7432294,
  "type": "Feature",
  "properties": {
    "tgn:hierarchy":[
        "tgn:7432294",
        "tgn:7005583",
        "tgn:1000001",
        "tgn:7005560",
        "tgn:7029392"
    ],
    "tgn:id":7432294,
    "tgn:name":"Francisco I. Madero",
    "tgn:placetype":[
        "aat:300008347"
    ]
},
  "bbox": [],
  "geometry": {"coordinates":[-104.283333,22.65],"type":"Point"}
}