<<<<<<< HEAD
{
  "id": 2768351,
  "type": "Feature",
  "properties": {
    "tgn:hierarchy":[
        "tgn:2768351",
        "tgn:1000001",
        "tgn:7012149",
        "tgn:2001067",
        "tgn:7007521",
        "tgn:7029392"
    ],
    "tgn:id":2768351,
    "tgn:name":"Whiteside Mine",
    "tgn:placetype":[
        "aat:300000390"
    ]
},
  "bbox": [],
  "geometry": {"coordinates":[-92.7333,47.5],"type":"Point"}
}
=======
{"geometry":{"type":"Point","coordinates":[-92.733300,47.500000]},"type":"Feature","properties":{"hierarchy":["tgn:2768351","tgn:1000001","tgn:7012149","tgn:2001067","tgn:7007521","tgn:7029392"],"placetype":["aat:300000390"],"id":2768351,"name:xx":"Whiteside Mine"}}
>>>>>>> 03f74aca74312dbeaf24d7e61306dd6a786dc3d0
