{
  "id": 1114538,
  "type": "Feature",
  "properties": {
    "tgn:hierarchy":[
        "tgn:1114538",
        "tgn:7001199",
        "tgn:7003494",
        "tgn:1000003",
        "tgn:1000078",
        "tgn:7029392"
    ],
    "tgn:id":1114538,
    "tgn:name":"Wexford Harbour",
    "tgn:placetype":[
        "aat:300008678"
    ]
},
  "bbox": [],
  "geometry": {"coordinates":[-6.4167,52.3333],"type":"Point"}
}