{
  "id": 2414617,
  "type": "Feature",
  "properties": {
    "tgn:hierarchy":[
        "tgn:2414617",
        "tgn:7006450",
        "tgn:1000001",
        "tgn:2124076",
        "tgn:7012149",
        "tgn:7029392"
    ],
    "tgn:id":2414617,
    "tgn:name":"Irvin Thompson Mountain",
    "tgn:placetype":[
        "aat:300008798"
    ]
},
  "bbox": [],
  "geometry": {"coordinates":[-131.7667,55.35],"type":"Point"}
}