{
  "id": 7145598,
  "type": "Feature",
  "properties": {
    "tgn:hierarchy":[
        "tgn:7145598",
        "tgn:1000003",
        "tgn:7003687",
        "tgn:7000084",
        "tgn:7029392"
    ],
    "tgn:id":7145598,
    "tgn:name":"Kleinwangen",
    "tgn:placetype":[
        "aat:300008347"
    ]
},
  "bbox": [],
  "geometry": {"coordinates":[11.55,51.283333],"type":"Point"}
}