{
  "id": 2224778,
  "type": "Feature",
  "properties": {
    "tgn:hierarchy":[
        "tgn:2224778",
        "tgn:1000001",
        "tgn:7012149",
        "tgn:7007157",
        "tgn:1002972",
        "tgn:7029392"
    ],
    "tgn:id":2224778,
    "tgn:name":"Casitas, Lake",
    "tgn:placetype":[
        "aat:300006191"
    ]
},
  "bbox": [],
  "geometry": {"coordinates":[-119.3333,34.3667],"type":"Point"}
}