{
  "id": 7572582,
  "type": "Feature",
  "properties": {
    "tgn:hierarchy":[
        "tgn:7572582",
        "tgn:1000004",
        "tgn:7000198",
        "tgn:1001882",
        "tgn:7029392"
    ],
    "tgn:id":7572582,
    "tgn:name:en":"Hosanagara",
    "tgn:placetype":[
        "aat:300008347"
    ]
},
  "bbox": [],
  "geometry": {"coordinates":[75.066667,13.916667],"type":"Point"}
}