{
  "id": 7527643,
  "type": "Feature",
  "properties": {
    "tgn:hierarchy":[
        "tgn:7527643",
        "tgn:7001242",
        "tgn:7016833",
        "tgn:7001336",
        "tgn:7029392"
    ],
    "tgn:id":7527643,
    "tgn:name:en":"Umm Abr\u0101m, Jabal",
    "tgn:placetype":[
        "aat:300008795"
    ]
},
  "bbox": [],
  "geometry": {"coordinates":[34.331325,28.179114],"type":"Point"}
}