{
  "id": 7123624,
  "type": "Feature",
  "properties": {
    "tgn:hierarchy":[
        "tgn:7123624",
        "tgn:1000003",
        "tgn:7003678",
        "tgn:7000084",
        "tgn:7029392"
    ],
    "tgn:id":7123624,
    "tgn:name":"Niederhofheim",
    "tgn:placetype":[
        "aat:300008347"
    ]
},
  "bbox": [],
  "geometry": {"coordinates":[8.483333,50.133333],"type":"Point"}
}