{
  "id": 1083857,
  "type": "Feature",
  "properties": {
    "tgn:hierarchy":[
        "tgn:1083857",
        "tgn:7002460",
        "tgn:1000004",
        "tgn:1000133",
        "tgn:7029392"
    ],
    "tgn:id":1083857,
    "tgn:name":"Warsak",
    "tgn:placetype":[
        "aat:300008347"
    ]
},
  "bbox": [],
  "geometry": {"coordinates":[71.4167,34.1667],"type":"Point"}
}