{
  "id": 2691826,
  "type": "Feature",
  "properties": {
    "tgn:hierarchy":[
        "tgn:2691826",
        "tgn:1000001",
        "tgn:7012149",
        "tgn:2001961",
        "tgn:7007826",
        "tgn:7029392"
    ],
    "tgn:id":2691826,
    "tgn:name":"Startz Hill",
    "tgn:placetype":[
        "aat:300008798"
    ]
},
  "bbox": [],
  "geometry": {"coordinates":[-98.2833,29.8167],"type":"Point"}
}