{
  "id": 2526104,
  "type": "Feature",
  "properties": {
    "tgn:hierarchy":[
        "tgn:2526104",
        "tgn:7006450",
        "tgn:1000001",
        "tgn:7012149",
        "tgn:2000085",
        "tgn:7029392"
    ],
    "tgn:id":2526104,
    "tgn:name":"Mosquito Fork",
    "tgn:placetype":[
        "aat:300008699"
    ]
},
  "bbox": [],
  "geometry": {"coordinates":[-143.7667,63.9667],"type":"Point"}
}