{
  "id": 2541398,
  "type": "Feature",
  "properties": {
    "tgn:hierarchy":[
        "tgn:2541398",
        "tgn:1000001",
        "tgn:7012149",
        "tgn:7014589",
        "tgn:7007515",
        "tgn:7029392"
    ],
    "tgn:id":2541398,
    "tgn:name":"Nightcap",
    "tgn:placetype":[
        "aat:300008791"
    ]
},
  "bbox": [],
  "geometry": {"coordinates":[-67.75,44.5167],"type":"Point"}
}