{
  "id": 2175955,
  "type": "Feature",
  "properties": {
    "tgn:hierarchy":[
        "tgn:2175955",
        "tgn:1002132",
        "tgn:1000001",
        "tgn:7012149",
        "tgn:7007919",
        "tgn:7029392"
    ],
    "tgn:id":2175955,
    "tgn:name":"Black Duck Cove",
    "tgn:placetype":[
        "aat:300132316"
    ]
},
  "bbox": [],
  "geometry": {"coordinates":[-75.7167,37.4667],"type":"Point"}
}