{
  "id": 2334870,
  "type": "Feature",
  "properties": {
    "tgn:hierarchy":[
        "tgn:2334870",
        "tgn:7014651",
        "tgn:1000001",
        "tgn:7012149",
        "tgn:7007516",
        "tgn:7029392"
    ],
    "tgn:id":2334870,
    "tgn:name":"Forked Creek",
    "tgn:placetype":[
        "aat:300008706"
    ]
},
  "bbox": [],
  "geometry": {"coordinates":[-76.4833,39.0333],"type":"Point"}
}