{
  "id": 2631289,
  "type": "Feature",
  "properties": {
    "tgn:hierarchy":[
        "tgn:2631289",
        "tgn:1000001",
        "tgn:7016172",
        "tgn:7012149",
        "tgn:2000125",
        "tgn:7029392"
    ],
    "tgn:id":2631289,
    "tgn:name":"Round Pond",
    "tgn:placetype":[
        "aat:300008905"
    ]
},
  "bbox": [],
  "geometry": {"coordinates":[-91.15,33.75],"type":"Point"}
}