{
  "id": 7344014,
  "type": "Feature",
  "properties": {
    "tgn:hierarchy":[
        "tgn:7344014",
        "tgn:7002835",
        "tgn:7001158",
        "tgn:1000003",
        "tgn:1000095",
        "tgn:7029392"
    ],
    "tgn:id":7344014,
    "tgn:name":"Campilduero",
    "tgn:placetype":[
        "aat:300008347"
    ]
},
  "bbox": [],
  "geometry": {"coordinates":[-6.566667,40.933333],"type":"Point"}
}