{
  "id": 7366405,
  "type": "Feature",
  "properties": {
    "tgn:hierarchy":[
        "tgn:7366405",
        "tgn:7005578",
        "tgn:1000001",
        "tgn:7005560",
        "tgn:7029392"
    ],
    "tgn:id":7366405,
    "tgn:name":"El Retiro",
    "tgn:placetype":[
        "aat:300008347"
    ]
},
  "bbox": [],
  "geometry": {"coordinates":[-90.633333,18.283333],"type":"Point"}
}