{
  "id": 7531237,
  "type": "Feature",
  "properties": {
    "tgn:hierarchy":[
        "tgn:7531237",
        "tgn:7001242",
        "tgn:7016833",
        "tgn:1001091",
        "tgn:7029392"
    ],
    "tgn:id":7531237,
    "tgn:name":"Masjid at Taw\u1e29\u012bd",
    "tgn:placetype":[
        "aat:300007544"
    ]
},
  "bbox": [],
  "geometry": {"coordinates":[31.251772,30.067301],"type":"Point"}
}