{
  "id": 2001401,
  "type": "Feature",
  "properties": {
    "tgn:hierarchy":[
        "tgn:2001401",
        "tgn:1000001",
        "tgn:7012149",
        "tgn:7007525",
        "tgn:7029392"
    ],
    "tgn:id":2001401,
    "tgn:name":"Thomas",
    "tgn:placetype":[
        "aat:300387145",
        "aat:300000771"
    ]
},
  "bbox": [],
  "geometry": {"coordinates":[-100.55,42.9167],"type":"Point"}
}