{
  "id": 2397287,
  "type": "Feature",
  "properties": {
    "tgn:hierarchy":[
        "tgn:2397287",
        "tgn:1000001",
        "tgn:7006451",
        "tgn:7012149",
        "tgn:2000100",
        "tgn:7029392"
    ],
    "tgn:id":2397287,
    "tgn:name":"Honey Bee Canyon",
    "tgn:placetype":[
        "aat:300008761"
    ]
},
  "bbox": [],
  "geometry": {"coordinates":[-110.9667,32.4833],"type":"Point"}
}