{
  "id": 2432334,
  "type": "Feature",
  "properties": {
    "tgn:hierarchy":[
        "tgn:2432334",
        "tgn:1000001",
        "tgn:7012149",
        "tgn:2000183",
        "tgn:7007157",
        "tgn:7029392"
    ],
    "tgn:id":2432334,
    "tgn:name":"Keane Wonder Springs",
    "tgn:placetype":[
        "aat:300008697"
    ]
},
  "bbox": [],
  "geometry": {"coordinates":[-116.9167,36.6667],"type":"Point"}
}