{
  "id": 2664788,
  "type": "Feature",
  "properties": {
    "tgn:hierarchy":[
        "tgn:2664788",
        "tgn:1000001",
        "tgn:7012149",
        "tgn:2001449",
        "tgn:7007566",
        "tgn:7029392"
    ],
    "tgn:id":2664788,
    "tgn:name":"Simon, Ca\u00f1ada",
    "tgn:placetype":[
        "aat:300008761"
    ]
},
  "bbox": [],
  "geometry": {"coordinates":[-106.9833,36.3667],"type":"Point"}
}