{
  "id": 2272727,
  "type": "Feature",
  "properties": {
    "tgn:hierarchy":[
        "tgn:2272727",
        "tgn:1000001",
        "tgn:7012149",
        "tgn:7007524",
        "tgn:7029392"
    ],
    "tgn:id":2272727,
    "tgn:name":"Custer, Mount",
    "tgn:placetype":[
        "aat:300008798"
    ]
},
  "bbox": [],
  "geometry": {"coordinates":[-114.05,48.9667],"type":"Point"}
}