{
  "id": 2748885,
  "type": "Feature",
  "properties": {
    "tgn:hierarchy":[
        "tgn:2748885",
        "tgn:1000001",
        "tgn:7012149",
        "tgn:2001288",
        "tgn:7007524",
        "tgn:7029392"
    ],
    "tgn:id":2748885,
    "tgn:name":"Wall Creek Lake",
    "tgn:placetype":[
        "aat:300008680"
    ]
},
  "bbox": [],
  "geometry": {"coordinates":[-111.7667,44.9667],"type":"Point"}
}