{
  "id": 2417153,
  "type": "Feature",
  "properties": {
    "tgn:hierarchy":[
        "tgn:2417153",
        "tgn:7006450",
        "tgn:1000001",
        "tgn:7030517",
        "tgn:7012149",
        "tgn:7029392"
    ],
    "tgn:id":2417153,
    "tgn:name":"Jackrabbit Island",
    "tgn:placetype":[
        "aat:300008791"
    ]
},
  "bbox": [],
  "geometry": {"coordinates":[-154.75,59.75],"type":"Point"}
}