{
  "id": 2753054,
  "type": "Feature",
  "properties": {
    "tgn:hierarchy":[
        "tgn:2753054",
        "tgn:1000001",
        "tgn:2002102",
        "tgn:7012149",
        "tgn:7007827",
        "tgn:7029392"
    ],
    "tgn:id":2753054,
    "tgn:name":"Water Hollow",
    "tgn:placetype":[
        "aat:300008761"
    ]
},
  "bbox": [],
  "geometry": {"coordinates":[-112.15,41.9833],"type":"Point"}
}