{
  "id": 2373223,
  "type": "Feature",
  "properties": {
    "tgn:hierarchy":[
        "tgn:2373223",
        "tgn:1000001",
        "tgn:7012149",
        "tgn:7007252",
        "tgn:7029392"
    ],
    "tgn:id":2373223,
    "tgn:name":"Halo Run",
    "tgn:placetype":[
        "aat:300008699"
    ]
},
  "bbox": [],
  "geometry": {"coordinates":[-86.8667,38.1833],"type":"Point"}
}