{
  "id": 2419979,
  "type": "Feature",
  "properties": {
    "tgn:hierarchy":[
        "tgn:2419979",
        "tgn:1000001",
        "tgn:1002189",
        "tgn:7012149",
        "tgn:7007255",
        "tgn:7029392"
    ],
    "tgn:id":2419979,
    "tgn:name":"Jeanclia, Lake",
    "tgn:placetype":[
        "aat:300008680"
    ]
},
  "bbox": [],
  "geometry": {"coordinates":[-84.8333,39.0667],"type":"Point"}
}