{
  "id": 7268393,
  "type": "Feature",
  "properties": {
    "tgn:concordances":{
        "gn:id":"2749986"
    },
    "tgn:hierarchy":[
        "tgn:7268393",
        "tgn:1000003",
        "tgn:7006951",
        "tgn:7016845",
        "tgn:7029392"
    ],
    "tgn:id":7268393,
    "tgn:name:nl":"Noordburen",
    "tgn:placetype":[
        "aat:300008347"
    ]
},
  "bbox": [],
  "geometry": {"coordinates":[4.966667,52.916667],"type":"Point"}
}