{
  "id": 2118716,
  "type": "Feature",
  "properties": {
    "tgn:hierarchy":[
        "tgn:2118716",
        "tgn:1000001",
        "tgn:7012149",
        "tgn:2002274",
        "tgn:7013961",
        "tgn:7029392"
    ],
    "tgn:id":2118716,
    "tgn:name":"Isaban",
    "tgn:placetype":[
        "aat:300008347"
    ]
},
  "bbox": [],
  "geometry": {"coordinates":[-81.8833,37.5167],"type":"Point"}
}