{
  "id": 1000836,
  "type": "Feature",
  "properties": {
    "tgn:hierarchy":[
        "tgn:1000836",
        "tgn:7001242",
        "tgn:1000149",
        "tgn:7029392"
    ],
    "tgn:id":1000836,
    "tgn:name":"Cunene",
    "tgn:placetype":[
        "aat:300387064",
        "aat:300000774"
    ]
},
  "bbox": [],
  "geometry": {"coordinates":[15.435,-16.51],"type":"Point"}
}