{
  "id": 2343983,
  "type": "Feature",
  "properties": {
    "tgn:hierarchy":[
        "tgn:2343983",
        "tgn:1000001",
        "tgn:7012149",
        "tgn:1002594",
        "tgn:7007920",
        "tgn:7029392"
    ],
    "tgn:id":2343983,
    "tgn:name":"Gallup Creek",
    "tgn:placetype":[
        "aat:300008706"
    ]
},
  "bbox": [],
  "geometry": {"coordinates":[-122.1667,46.6167],"type":"Point"}
}