<<<<<<< HEAD
{
  "id": 2409433,
  "type": "Feature",
  "properties": {
    "tgn:hierarchy":[
        "tgn:2409433",
        "tgn:1000001",
        "tgn:2000462",
        "tgn:7012149",
        "tgn:7007250",
        "tgn:7029392"
    ],
    "tgn:id":2409433,
    "tgn:name":"Idamont Mine",
    "tgn:placetype":[
        "aat:300000390"
    ]
},
  "bbox": [],
  "geometry": {"coordinates":[-116.0667,48.6],"type":"Point"}
}
=======
{"geometry":{"type":"Point","coordinates":[-116.066700,48.600000]},"type":"Feature","properties":{"hierarchy":["tgn:2409433","tgn:1000001","tgn:2000462","tgn:7012149","tgn:7007250","tgn:7029392"],"placetype":["aat:300000390"],"id":2409433,"name:xx":"Idamont Mine"}}
>>>>>>> 03f74aca74312dbeaf24d7e61306dd6a786dc3d0
