{
  "id": 7536904,
  "type": "Feature",
  "properties": {
    "tgn:hierarchy":[
        "tgn:7536904",
        "tgn:7001242",
        "tgn:7016833",
        "tgn:1001087",
        "tgn:7029392"
    ],
    "tgn:id":7536904,
    "tgn:name:en":"Kafr Ban\u012b Ghiry\u0101n",
    "tgn:placetype":[
        "aat:300008347"
    ]
},
  "bbox": [],
  "geometry": {"coordinates":[31.186813,30.624056],"type":"Point"}
}