<<<<<<< HEAD
{
  "id": 2405038,
  "type": "Feature",
  "properties": {
    "tgn:hierarchy":[
        "tgn:2405038",
        "tgn:1000001",
        "tgn:2001797",
        "tgn:7012149",
        "tgn:7007713",
        "tgn:7029392"
    ],
    "tgn:id":2405038,
    "tgn:name":"Hudson Flat",
    "tgn:placetype":[
        "aat:300055621"
    ]
},
  "bbox": [],
  "geometry": {"coordinates":[-101.45,44.5],"type":"Point"}
}
=======
{"geometry":{"type":"Point","coordinates":[-101.450000,44.500000]},"type":"Feature","properties":{"hierarchy":["tgn:2405038","tgn:1000001","tgn:2001797","tgn:7012149","tgn:7007713","tgn:7029392"],"placetype":["aat:300055621"],"id":2405038,"name:xx":"Hudson Flat"}}
>>>>>>> 03f74aca74312dbeaf24d7e61306dd6a786dc3d0
