{
  "id": 7367237,
  "type": "Feature",
  "properties": {
    "tgn:hierarchy":[
        "tgn:7367237",
        "tgn:1000001",
        "tgn:7005589",
        "tgn:7005560",
        "tgn:7029392"
    ],
    "tgn:id":7367237,
    "tgn:name":"El Pocito",
    "tgn:placetype":[
        "aat:300008347"
    ]
},
  "bbox": [],
  "geometry": {"coordinates":[-100.366667,23.75],"type":"Point"}
}