{
  "id": 7183777,
  "type": "Feature",
  "properties": {
    "tgn:hierarchy":[
        "tgn:7183777",
        "tgn:7003692",
        "tgn:1000003",
        "tgn:7000084",
        "tgn:7029392"
    ],
    "tgn:id":7183777,
    "tgn:name":"Gottrazhofen",
    "tgn:placetype":[
        "aat:300008347"
    ]
},
  "bbox": [],
  "geometry": {"coordinates":[9.983333,47.733333],"type":"Point"}
}