{
  "id": 2499087,
  "type": "Feature",
  "properties": {
    "tgn:hierarchy":[
        "tgn:2499087",
        "tgn:1000001",
        "tgn:2000459",
        "tgn:7012149",
        "tgn:7007250",
        "tgn:7029392"
    ],
    "tgn:id":2499087,
    "tgn:name":"McCarty Gulch",
    "tgn:placetype":[
        "aat:300008761"
    ]
},
  "bbox": [],
  "geometry": {"coordinates":[-116.0333,43.6333],"type":"Point"}
}