{
  "id": 7058681,
  "type": "Feature",
  "properties": {
    "tgn:hierarchy":[
        "tgn:7058681",
        "tgn:1000003",
        "tgn:7003152",
        "tgn:7003237",
        "tgn:1000080",
        "tgn:7029392"
    ],
    "tgn:id":7058681,
    "tgn:name":"Alpe Gera",
    "tgn:placetype":[
        "aat:300008347"
    ]
},
  "bbox": [],
  "geometry": {"coordinates":[9.933333,46.316667],"type":"Point"}
}