{
  "id": 1013070,
  "type": "Feature",
  "properties": {
    "tgn:hierarchy":[
        "tgn:1013070",
        "tgn:7005694",
        "tgn:7005685",
        "tgn:1000001",
        "tgn:7029392"
    ],
    "tgn:id":1013070,
    "tgn:name":"Barons",
    "tgn:placetype":[
        "aat:300008347"
    ]
},
  "bbox": [],
  "geometry": {"coordinates":[-113.05,49.9833],"type":"Point"}
}