<<<<<<< HEAD
{
  "id": 2763805,
  "type": "Feature",
  "properties": {
    "tgn:hierarchy":[
        "tgn:2763805",
        "tgn:1000001",
        "tgn:2001416",
        "tgn:7012149",
        "tgn:7007526",
        "tgn:7029392"
    ],
    "tgn:id":2763805,
    "tgn:name":"Wheat Grass Spring",
    "tgn:placetype":[
        "aat:300008697"
    ]
},
  "bbox": [],
  "geometry": {"coordinates":[-115.5167,37.7333],"type":"Point"}
}
=======
{"geometry":{"type":"Point","coordinates":[-115.516700,37.733300]},"type":"Feature","properties":{"hierarchy":["tgn:2763805","tgn:1000001","tgn:2001416","tgn:7012149","tgn:7007526","tgn:7029392"],"placetype":["aat:300008697"],"id":2763805,"name:xx":"Wheat Grass Spring"}}
>>>>>>> 03f74aca74312dbeaf24d7e61306dd6a786dc3d0
