{
  "id": 2197207,
  "type": "Feature",
  "properties": {
    "tgn:hierarchy":[
        "tgn:2197207",
        "tgn:1000001",
        "tgn:7012149",
        "tgn:7007252",
        "tgn:7029392"
    ],
    "tgn:id":2197207,
    "tgn:name":"Brower Ditch",
    "tgn:placetype":[
        "aat:300006075"
    ]
},
  "bbox": [],
  "geometry": {"coordinates":[-86.1667,40.8333],"type":"Point"}
}