{
  "id": 2051953,
  "type": "Feature",
  "properties": {
    "tgn:hierarchy":[
        "tgn:2051953",
        "tgn:1000001",
        "tgn:7012149",
        "tgn:2000997",
        "tgn:7007520",
        "tgn:7029392"
    ],
    "tgn:id":2051953,
    "tgn:name":"Fostoria",
    "tgn:placetype":[
        "aat:300008347"
    ]
},
  "bbox": [],
  "geometry": {"coordinates":[-83.3667,43.25],"type":"Point"}
}