{
  "id": 2511304,
  "type": "Feature",
  "properties": {
    "tgn:hierarchy":[
        "tgn:2511304",
        "tgn:1000001",
        "tgn:7012149",
        "tgn:7013961",
        "tgn:7029392"
    ],
    "tgn:id":2511304,
    "tgn:name":"Mikes Run",
    "tgn:placetype":[
        "aat:300008699"
    ]
},
  "bbox": [],
  "geometry": {"coordinates":[-80.9667,38.8667],"type":"Point"}
}