{
  "id": 7015929,
  "type": "Feature",
  "properties": {
    "tgn:hierarchy":[
        "tgn:7015929",
        "tgn:1000003",
        "tgn:7029392"
    ],
    "tgn:id":7015929,
    "tgn:name:hu":"Maros",
    "tgn:name:ro":"Mure\u0219",
    "tgn:placetype":[
        "aat:300008707"
    ]
},
  "bbox": [],
  "geometry": {"coordinates":[20.25,46.25],"type":"Point"}
}