{
  "id": 2108758,
  "type": "Feature",
  "properties": {
    "tgn:hierarchy":[
        "tgn:2108758",
        "tgn:1000001",
        "tgn:2002107",
        "tgn:7012149",
        "tgn:7007827",
        "tgn:7029392"
    ],
    "tgn:id":2108758,
    "tgn:name":"Cedarview",
    "tgn:placetype":[
        "aat:300008347",
        "aat:300387210"
    ]
},
  "bbox": [],
  "geometry": {"coordinates":[-110.0333,40.35],"type":"Point"}
}