{
  "id": 2633847,
  "type": "Feature",
  "properties": {
    "tgn:hierarchy":[
        "tgn:2633847",
        "tgn:1000001",
        "tgn:7012149",
        "tgn:2002353",
        "tgn:7007922",
        "tgn:7029392"
    ],
    "tgn:id":2633847,
    "tgn:name":"Rush Lake",
    "tgn:placetype":[
        "aat:300008680"
    ]
},
  "bbox": [],
  "geometry": {"coordinates":[-91.15,46.05],"type":"Point"}
}