{
  "id": 7401959,
  "type": "Feature",
  "properties": {
    "tgn:hierarchy":[
        "tgn:7401959",
        "tgn:1000001",
        "tgn:7005599",
        "tgn:7005560",
        "tgn:7029392"
    ],
    "tgn:id":7401959,
    "tgn:name":"Paso Lim\u00f3n",
    "tgn:placetype":[
        "aat:300008347"
    ]
},
  "bbox": [],
  "geometry": {"coordinates":[-96.561111,19.15],"type":"Point"}
}