{
  "id": 7291436,
  "type": "Feature",
  "properties": {
    "tgn:hierarchy":[
        "tgn:7291436",
        "tgn:1001702",
        "tgn:1000049",
        "tgn:1000002",
        "tgn:7029392"
    ],
    "tgn:id":7291436,
    "tgn:name":"Eros, Islotes",
    "tgn:placetype":[
        "aat:300008791"
    ]
},
  "bbox": [],
  "geometry": {"coordinates":[-71.966667,-53.083333],"type":"Point"}
}