{
  "id": 2284823,
  "type": "Feature",
  "properties": {
    "tgn:hierarchy":[
        "tgn:2284823",
        "tgn:1000001",
        "tgn:2002368",
        "tgn:7012149",
        "tgn:7007923",
        "tgn:7029392"
    ],
    "tgn:id":2284823,
    "tgn:name":"Detention Reservoir 1492 Number 2",
    "tgn:placetype":[
        "aat:300006191"
    ]
},
  "bbox": [],
  "geometry": {"coordinates":[-107.7167,41.15],"type":"Point"}
}