<<<<<<< HEAD
{
  "id": 7179592,
  "type": "Feature",
  "properties": {
    "tgn:hierarchy":[
        "tgn:7179592",
        "tgn:1000003",
        "tgn:7003677",
        "tgn:7000084",
        "tgn:7029392"
    ],
    "tgn:id":7179592,
    "tgn:name":"Hamb\u00fcchen",
    "tgn:placetype":[
        "aat:300000206"
    ]
},
  "bbox": [],
  "geometry": {"coordinates":[7.416667,51.133333],"type":"Point"}
}
=======
{"geometry":{"type":"Point","coordinates":[7.416667,51.133333]},"type":"Feature","properties":{"hierarchy":["tgn:7179592","tgn:1000003","tgn:7003677","tgn:7000084","tgn:7029392"],"placetype":["aat:300000206"],"id":7179592,"name:xx":"Hamb\u00fcchen"}}
>>>>>>> 03f74aca74312dbeaf24d7e61306dd6a786dc3d0
