{
  "id": 1085362,
  "type": "Feature",
  "properties": {
    "tgn:hierarchy":[
        "tgn:1085362",
        "tgn:7468018",
        "tgn:1000004",
        "tgn:1000141",
        "tgn:7029392"
    ],
    "tgn:id":1085362,
    "tgn:name":"Pei-kang",
    "tgn:placetype":[
        "aat:300008347"
    ]
},
  "bbox": [],
  "geometry": {"coordinates":[120.303276,23.571224],"type":"Point"}
}