{
  "id": 2658116,
  "type": "Feature",
  "properties": {
    "tgn:hierarchy":[
        "tgn:2658116",
        "tgn:1000001",
        "tgn:7012149",
        "tgn:2001714",
        "tgn:7007708",
        "tgn:7029392"
    ],
    "tgn:id":2658116,
    "tgn:name":"Shelter Cove",
    "tgn:placetype":[
        "aat:300132316"
    ]
},
  "bbox": [],
  "geometry": {"coordinates":[-122.0333,43.5667],"type":"Point"}
}