{
  "id": 2171898,
  "type": "Feature",
  "properties": {
    "tgn:hierarchy":[
        "tgn:2171898",
        "tgn:1000001",
        "tgn:2000315",
        "tgn:7012149",
        "tgn:7007248",
        "tgn:7029392"
    ],
    "tgn:id":2171898,
    "tgn:name":"Big Water Lake",
    "tgn:placetype":[
        "aat:300008680"
    ]
},
  "bbox": [],
  "geometry": {"coordinates":[-82.2667,30.9167],"type":"Point"}
}