{
  "id": 7091743,
  "type": "Feature",
  "properties": {
    "tgn:hierarchy":[
        "tgn:7091743",
        "tgn:7003692",
        "tgn:1000003",
        "tgn:7000084",
        "tgn:7029392"
    ],
    "tgn:id":7091743,
    "tgn:name":"Bahnhof Unterm\u00fcnstertal",
    "tgn:placetype":[
        "aat:300007783"
    ]
},
  "bbox": [],
  "geometry": {"coordinates":[7.780833,47.855],"type":"Point"}
}