{
  "id": 7494529,
  "type": "Feature",
  "properties": {
    "tgn:hierarchy":[
        "tgn:7494529",
        "tgn:7468018",
        "tgn:1000004",
        "tgn:1000141",
        "tgn:7029392"
    ],
    "tgn:id":7494529,
    "tgn:name":"Dahudi",
    "tgn:placetype":[
        "aat:300008347"
    ]
},
  "bbox": [],
  "geometry": {"coordinates":[120.56334,23.363979],"type":"Point"}
}