{
  "id": 7592185,
  "type": "Feature",
  "properties": {
    "tgn:hierarchy":[
        "tgn:7592185",
        "tgn:1000004",
        "tgn:7000198",
        "tgn:7000799",
        "tgn:7029392"
    ],
    "tgn:id":7592185,
    "tgn:name:en":"Thindew\u0101li",
    "tgn:placetype":[
        "aat:300266554",
        "aat:300008699"
    ]
},
  "bbox": [],
  "geometry": {"coordinates":[74.565278,32.8375],"type":"Point"}
}