{
  "id": 7490411,
  "type": "Feature",
  "properties": {
    "tgn:hierarchy":[
        "tgn:7490411",
        "tgn:7001004",
        "tgn:1000004",
        "tgn:1000141",
        "tgn:7029392"
    ],
    "tgn:id":7490411,
    "tgn:name":"Shietou",
    "tgn:placetype":[
        "aat:300008347"
    ]
},
  "bbox": [],
  "geometry": {"coordinates":[120.657222,23.022222],"type":"Point"}
}