<<<<<<< HEAD
{
  "id": 2765881,
  "type": "Feature",
  "properties": {
    "tgn:hierarchy":[
        "tgn:2765881",
        "tgn:7006450",
        "tgn:1000001",
        "tgn:7019698",
        "tgn:7012149",
        "tgn:7029392"
    ],
    "tgn:id":2765881,
    "tgn:name":"White Gull Island",
    "tgn:placetype":[
        "aat:300008791"
    ]
},
  "bbox": [],
  "geometry": {"coordinates":[-153.5667,59.6167],"type":"Point"}
}
=======
{"geometry":{"type":"Point","coordinates":[-153.566700,59.616700]},"type":"Feature","properties":{"hierarchy":["tgn:2765881","tgn:7006450","tgn:1000001","tgn:7019698","tgn:7012149","tgn:7029392"],"placetype":["aat:300008791"],"id":2765881,"name:xx":"White Gull Island"}}
>>>>>>> 03f74aca74312dbeaf24d7e61306dd6a786dc3d0
