{
  "id": 2765881,
  "type": "Feature",
  "properties": {
    "tgn:hierarchy":[
        "tgn:2765881",
        "tgn:7006450",
        "tgn:1000001",
        "tgn:7019698",
        "tgn:7012149",
        "tgn:7029392"
    ],
    "tgn:id":2765881,
    "tgn:name":"White Gull Island",
    "tgn:placetype":[
        "aat:300008791"
    ]
},
  "bbox": [],
  "geometry": {"coordinates":[-153.5667,59.6167],"type":"Point"}
}