{
  "id": 7033099,
  "type": "Feature",
  "properties": {
    "tgn:hierarchy":[
        "tgn:7033099",
        "tgn:1000670",
        "tgn:1000002",
        "tgn:1000056",
        "tgn:7029392"
    ],
    "tgn:id":7033099,
    "tgn:name":"El \u00c1spero",
    "tgn:placetype":[
        "aat:300008347",
        "aat:300000810",
        "aat:300167671",
        "aat:300016619"
    ]
},
  "bbox": [],
  "geometry": {"coordinates":[-77.75,-10.82],"type":"Point"}
}