<<<<<<< HEAD
{
  "id": 2338437,
  "type": "Feature",
  "properties": {
    "tgn:hierarchy":[
        "tgn:2338437",
        "tgn:1000001",
        "tgn:7012149",
        "tgn:2001274",
        "tgn:7007524",
        "tgn:7029392"
    ],
    "tgn:id":2338437,
    "tgn:name":"Foy Lake",
    "tgn:placetype":[
        "aat:300008680"
    ]
},
  "bbox": [],
  "geometry": {"coordinates":[-114.35,48.15],"type":"Point"}
}
=======
{"geometry":{"type":"Point","coordinates":[-114.350000,48.150000]},"type":"Feature","properties":{"hierarchy":["tgn:2338437","tgn:1000001","tgn:7012149","tgn:2001274","tgn:7007524","tgn:7029392"],"placetype":["aat:300008680"],"id":2338437,"name:xx":"Foy Lake"}}
>>>>>>> 03f74aca74312dbeaf24d7e61306dd6a786dc3d0
