{
  "id": 7503085,
  "type": "Feature",
  "properties": {
    "tgn:hierarchy":[
        "tgn:7503085",
        "tgn:7001010",
        "tgn:1000004",
        "tgn:1000141",
        "tgn:7029392"
    ],
    "tgn:id":7503085,
    "tgn:name":"Funan Beiqiao",
    "tgn:placetype":[
        "aat:300007836"
    ]
},
  "bbox": [],
  "geometry": {"coordinates":[121.242778,23.1675],"type":"Point"}
}