<<<<<<< HEAD
{
  "id": 7022602,
  "type": "Feature",
  "properties": {
    "tgn:hierarchy":[
        "tgn:7022602",
        "tgn:7006450",
        "tgn:1000001",
        "tgn:7012149",
        "tgn:7029392"
    ],
    "tgn:id":7022602,
    "tgn:name":"Control Creek",
    "tgn:placetype":[
        "aat:300008706"
    ]
},
  "bbox": [],
  "geometry": {"coordinates":[-146.2167,60.7833],"type":"Point"}
}
=======
{"geometry":{"type":"Point","coordinates":[-146.216700,60.783300]},"type":"Feature","properties":{"hierarchy":["tgn:7022602","tgn:7006450","tgn:1000001","tgn:7012149","tgn:7029392"],"placetype":["aat:300008706"],"id":7022602,"name:xx":"Control Creek"}}
>>>>>>> 03f74aca74312dbeaf24d7e61306dd6a786dc3d0
