{
  "id": 2720415,
  "type": "Feature",
  "properties": {
    "tgn:hierarchy":[
        "tgn:2720415",
        "tgn:1000001",
        "tgn:2001785",
        "tgn:7012149",
        "tgn:7007713",
        "tgn:7029392"
    ],
    "tgn:id":2720415,
    "tgn:name":"Thunder Hawk Butte",
    "tgn:placetype":[
        "aat:300008798"
    ]
},
  "bbox": [],
  "geometry": {"coordinates":[-101.95,45.9167],"type":"Point"}
}