{
  "id": 2635458,
  "type": "Feature",
  "properties": {
    "tgn:hierarchy":[
        "tgn:2635458",
        "tgn:1000001",
        "tgn:7012149",
        "tgn:2001288",
        "tgn:7007524",
        "tgn:7029392"
    ],
    "tgn:id":2635458,
    "tgn:name":"SE Section 1/Cal Creek Mine",
    "tgn:placetype":[
        "aat:300000390"
    ]
},
  "bbox": [],
  "geometry": {"coordinates":[-112.0333,45.3333],"type":"Point"}
}