{
  "id": 7392198,
  "type": "Feature",
  "properties": {
    "tgn:hierarchy":[
        "tgn:7392198",
        "tgn:7005581",
        "tgn:1000001",
        "tgn:7005560",
        "tgn:7029392"
    ],
    "tgn:id":7392198,
    "tgn:name":"Rancho Los Cuates",
    "tgn:placetype":[
        "aat:300008347"
    ]
},
  "bbox": [],
  "geometry": {"coordinates":[-104.183333,26.783333],"type":"Point"}
}