{
  "id": 2099438,
  "type": "Feature",
  "properties": {
    "tgn:hierarchy":[
        "tgn:2099438",
        "tgn:1000001",
        "tgn:7012149",
        "tgn:2001882",
        "tgn:7007825",
        "tgn:7029392"
    ],
    "tgn:id":2099438,
    "tgn:name":"Hammon Chapel",
    "tgn:placetype":[
        "aat:300007466",
        "aat:300387210"
    ]
},
  "bbox": [],
  "geometry": {"coordinates":[-81.7167,36.4667],"type":"Point"}
}