{
  "id": 1081327,
  "type": "Feature",
  "properties": {
    "tgn:hierarchy":[
        "tgn:1081327",
        "tgn:7016696",
        "tgn:1000004",
        "tgn:7000894",
        "tgn:1000120",
        "tgn:7029392"
    ],
    "tgn:id":1081327,
    "tgn:name":"Shimoya",
    "tgn:placetype":[
        "aat:300008347"
    ]
},
  "bbox": [],
  "geometry": {"coordinates":[139.35,35.3833],"type":"Point"}
}