<<<<<<< HEAD
{
  "id": 7171299,
  "type": "Feature",
  "properties": {
    "tgn:hierarchy":[
        "tgn:7171299",
        "tgn:7003669",
        "tgn:1000003",
        "tgn:7000084",
        "tgn:7029392"
    ],
    "tgn:id":7171299,
    "tgn:name":"Hirschb\u00fchl",
    "tgn:placetype":[
        "aat:300000206"
    ]
},
  "bbox": [],
  "geometry": {"coordinates":[10.516667,47.65],"type":"Point"}
}
=======
{"geometry":{"type":"Point","coordinates":[10.516667,47.650000]},"type":"Feature","properties":{"hierarchy":["tgn:7171299","tgn:7003669","tgn:1000003","tgn:7000084","tgn:7029392"],"placetype":["aat:300000206"],"id":7171299,"name:xx":"Hirschb\u00fchl"}}
>>>>>>> 03f74aca74312dbeaf24d7e61306dd6a786dc3d0
