{
  "id": 2498270,
  "type": "Feature",
  "properties": {
    "tgn:hierarchy":[
        "tgn:2498270",
        "tgn:1000001",
        "tgn:7012149",
        "tgn:2000231",
        "tgn:7007158",
        "tgn:7029392"
    ],
    "tgn:id":2498270,
    "tgn:name":"Mc Clelland Mountain",
    "tgn:placetype":[
        "aat:300008798"
    ]
},
  "bbox": [],
  "geometry": {"coordinates":[-106.7833,37.7333],"type":"Point"}
}