{
  "id": 1017560,
  "type": "Feature",
  "properties": {
    "tgn:hierarchy":[
        "tgn:1017560",
        "tgn:7005585",
        "tgn:1000001",
        "tgn:7005560",
        "tgn:7029392"
    ],
    "tgn:id":1017560,
    "tgn:name":"Huamuxtitl\u00e1n",
    "tgn:placetype":[
        "aat:300008347"
    ]
},
  "bbox": [],
  "geometry": {"coordinates":[-98.566667,17.816667],"type":"Point"}
}