{
  "id": 2198880,
  "type": "Feature",
  "properties": {
    "tgn:hierarchy":[
        "tgn:2198880",
        "tgn:1000001",
        "tgn:7012149",
        "tgn:2000481",
        "tgn:7007250",
        "tgn:7029392"
    ],
    "tgn:id":2198880,
    "tgn:name":"Bruce Canyon",
    "tgn:placetype":[
        "aat:300008761"
    ]
},
  "bbox": [],
  "geometry": {"coordinates":[-113.25,44.3667],"type":"Point"}
}