<<<<<<< HEAD
{
  "id": 2409689,
  "type": "Feature",
  "properties": {
    "tgn:hierarchy":[
        "tgn:2409689",
        "tgn:1000001",
        "tgn:7012149",
        "tgn:7007157",
        "tgn:2000189",
        "tgn:7029392"
    ],
    "tgn:id":2409689,
    "tgn:name":"Ikes Creek",
    "tgn:placetype":[
        "aat:300008706"
    ]
},
  "bbox": [],
  "geometry": {"coordinates":[-122.1667,41.8333],"type":"Point"}
}
=======
{"geometry":{"type":"Point","coordinates":[-122.166700,41.833300]},"type":"Feature","properties":{"hierarchy":["tgn:2409689","tgn:1000001","tgn:7012149","tgn:7007157","tgn:2000189","tgn:7029392"],"placetype":["aat:300008706"],"id":2409689,"name:xx":"Ikes Creek"}}
>>>>>>> 03f74aca74312dbeaf24d7e61306dd6a786dc3d0
