{
  "id": 2521169,
  "type": "Feature",
  "properties": {
    "tgn:hierarchy":[
        "tgn:2521169",
        "tgn:1000001",
        "tgn:2001416",
        "tgn:7012149",
        "tgn:7007526",
        "tgn:7029392"
    ],
    "tgn:id":2521169,
    "tgn:name":"Monte Spring",
    "tgn:placetype":[
        "aat:300008697"
    ]
},
  "bbox": [],
  "geometry": {"coordinates":[-115.5167,37.6333],"type":"Point"}
}