{
  "id": 7157326,
  "type": "Feature",
  "properties": {
    "tgn:hierarchy":[
        "tgn:7157326",
        "tgn:1000003",
        "tgn:7003685",
        "tgn:7000084",
        "tgn:7029392"
    ],
    "tgn:id":7157326,
    "tgn:name":"Kieritzsch",
    "tgn:placetype":[
        "aat:300008347"
    ]
},
  "bbox": [],
  "geometry": {"coordinates":[12.383333,51.166667],"type":"Point"}
}