{
  "id": 7525210,
  "type": "Feature",
  "properties": {
    "tgn:hierarchy":[
        "tgn:7525210",
        "tgn:7001242",
        "tgn:7016833",
        "tgn:7001334",
        "tgn:7029392"
    ],
    "tgn:id":7525210,
    "tgn:name:en":"Ammonite Scarp",
    "tgn:placetype":[
        "aat:300132353"
    ]
},
  "bbox": [],
  "geometry": {"coordinates":[26.833333,25.85],"type":"Point"}
}