{
  "id": 2004424,
  "type": "Feature",
  "properties": {
    "tgn:hierarchy":[
        "tgn:2004424",
        "tgn:7002659",
        "tgn:1000001",
        "tgn:7012149",
        "tgn:7021514",
        "tgn:7029392"
    ],
    "tgn:id":2004424,
    "tgn:name":"Mentone",
    "tgn:placetype":[
        "aat:300008347"
    ]
},
  "bbox": [],
  "geometry": {"coordinates":[-85.5833,34.5667],"type":"Point"}
}