{
  "id": 1017875,
  "type": "Feature",
  "properties": {
    "tgn:hierarchy":[
        "tgn:1017875",
        "tgn:7005587",
        "tgn:1000001",
        "tgn:7005560",
        "tgn:7029392"
    ],
    "tgn:id":1017875,
    "tgn:name":"Mixquiahuala",
    "tgn:placetype":[
        "aat:300008347"
    ]
},
  "bbox": [],
  "geometry": {"coordinates":[-99.216667,20.233333],"type":"Point"}
}