{
  "id": 2768699,
  "type": "Feature",
  "properties": {
    "tgn:hierarchy":[
        "tgn:2768699",
        "tgn:1000001",
        "tgn:7012149",
        "tgn:2002170",
        "tgn:7007919",
        "tgn:7029392"
    ],
    "tgn:id":2768699,
    "tgn:name":"Whitlock Millpond",
    "tgn:placetype":[
        "aat:300008680"
    ]
},
  "bbox": [],
  "geometry": {"coordinates":[-77.8667,38.0333],"type":"Point"}
}