<<<<<<< HEAD
{
  "id": 2768699,
  "type": "Feature",
  "properties": {
    "tgn:hierarchy":[
        "tgn:2768699",
        "tgn:1000001",
        "tgn:7012149",
        "tgn:2002170",
        "tgn:7007919",
        "tgn:7029392"
    ],
    "tgn:id":2768699,
    "tgn:name":"Whitlock Millpond",
    "tgn:placetype":[
        "aat:300008680"
    ]
},
  "bbox": [],
  "geometry": {"coordinates":[-77.8667,38.0333],"type":"Point"}
}
=======
{"geometry":{"type":"Point","coordinates":[-77.866700,38.033300]},"type":"Feature","properties":{"hierarchy":["tgn:2768699","tgn:1000001","tgn:7012149","tgn:2002170","tgn:7007919","tgn:7029392"],"placetype":["aat:300008680"],"id":2768699,"name:xx":"Whitlock Millpond"}}
>>>>>>> 03f74aca74312dbeaf24d7e61306dd6a786dc3d0
