{
  "id": 2348471,
  "type": "Feature",
  "properties": {
    "tgn:hierarchy":[
        "tgn:2348471",
        "tgn:1000001",
        "tgn:7012149",
        "tgn:7007923",
        "tgn:7029392"
    ],
    "tgn:id":2348471,
    "tgn:name":"Gibbon River",
    "tgn:placetype":[
        "aat:300008707"
    ]
},
  "bbox": [],
  "geometry": {"coordinates":[-110.55,44.75],"type":"Point"}
}