<<<<<<< HEAD
{
  "id": 2766751,
  "type": "Feature",
  "properties": {
    "tgn:hierarchy":[
        "tgn:2766751",
        "tgn:1000001",
        "tgn:7012149",
        "tgn:2002303",
        "tgn:7013961",
        "tgn:7029392"
    ],
    "tgn:id":2766751,
    "tgn:name":"White Oak Run",
    "tgn:placetype":[
        "aat:300008699"
    ]
},
  "bbox": [],
  "geometry": {"coordinates":[-81.2667,39.2333],"type":"Point"}
}
=======
{"geometry":{"type":"Point","coordinates":[-81.266700,39.233300]},"type":"Feature","properties":{"hierarchy":["tgn:2766751","tgn:1000001","tgn:7012149","tgn:2002303","tgn:7013961","tgn:7029392"],"placetype":["aat:300008699"],"id":2766751,"name:xx":"White Oak Run"}}
>>>>>>> 03f74aca74312dbeaf24d7e61306dd6a786dc3d0
