{
  "id": 2341057,
  "type": "Feature",
  "properties": {
    "tgn:hierarchy":[
        "tgn:2341057",
        "tgn:1000001",
        "tgn:7012149",
        "tgn:2001916",
        "tgn:7007825",
        "tgn:7029392"
    ],
    "tgn:id":2341057,
    "tgn:name":"Friendship Hollow",
    "tgn:placetype":[
        "aat:300008761"
    ]
},
  "bbox": [],
  "geometry": {"coordinates":[-85.9333,36.3333],"type":"Point"}
}