<<<<<<< HEAD
{
  "id": 7363018,
  "type": "Feature",
  "properties": {
    "tgn:hierarchy":[
        "tgn:7363018",
        "tgn:1000001",
        "tgn:7005589",
        "tgn:7005560",
        "tgn:7029392"
    ],
    "tgn:id":7363018,
    "tgn:name":"El Cedrito",
    "tgn:placetype":[
        "aat:300008347"
    ]
},
  "bbox": [],
  "geometry": {"coordinates":[-100.183333,26.8],"type":"Point"}
}
=======
{"geometry":{"type":"Point","coordinates":[-100.183333,26.800000]},"type":"Feature","properties":{"hierarchy":["tgn:7363018","tgn:1000001","tgn:7005589","tgn:7005560","tgn:7029392"],"placetype":["aat:300008347"],"id":7363018,"name:xx":"El Cedrito"}}
>>>>>>> 03f74aca74312dbeaf24d7e61306dd6a786dc3d0
