{
  "id": 2235189,
  "type": "Feature",
  "properties": {
    "tgn:hierarchy":[
        "tgn:2235189",
        "tgn:1000001",
        "tgn:7012149",
        "tgn:2001720",
        "tgn:7007708",
        "tgn:7029392"
    ],
    "tgn:id":2235189,
    "tgn:name":"Cherry Spring",
    "tgn:placetype":[
        "aat:300008697"
    ]
},
  "bbox": [],
  "geometry": {"coordinates":[-119.0333,45.6667],"type":"Point"}
}