{
  "id": 2348107,
  "type": "Feature",
  "properties": {
    "tgn:hierarchy":[
        "tgn:2348107",
        "tgn:1000001",
        "tgn:2001638",
        "tgn:7012149",
        "tgn:7007707",
        "tgn:7029392"
    ],
    "tgn:id":2348107,
    "tgn:name":"Geronimo Pond",
    "tgn:placetype":[
        "aat:300008680"
    ]
},
  "bbox": [],
  "geometry": {"coordinates":[-98.45,34.6333],"type":"Point"}
}