{
  "id": 7176451,
  "type": "Feature",
  "properties": {
    "tgn:hierarchy":[
        "tgn:7176451",
        "tgn:1000003",
        "tgn:7003676",
        "tgn:7000084",
        "tgn:7029392"
    ],
    "tgn:id":7176451,
    "tgn:name":"Halstein",
    "tgn:placetype":[
        "aat:300008777"
    ]
},
  "bbox": [],
  "geometry": {"coordinates":[10.716667,52.083333],"type":"Point"}
}