{
  "id": 2078554,
  "type": "Feature",
  "properties": {
    "tgn:hierarchy":[
        "tgn:2078554",
        "tgn:1000001",
        "tgn:7012149",
        "tgn:1002797",
        "tgn:7007706",
        "tgn:7029392"
    ],
    "tgn:id":2078554,
    "tgn:name":"Brady Lake",
    "tgn:placetype":[
        "aat:300008347"
    ]
},
  "bbox": [],
  "geometry": {"coordinates":[-81.3167,41.15],"type":"Point"}
}