{
  "id": 7519351,
  "type": "Feature",
  "properties": {
    "tgn:hierarchy":[
        "tgn:7519351",
        "tgn:1009227",
        "tgn:7001866",
        "tgn:1000226",
        "tgn:1000006",
        "tgn:7506511",
        "tgn:7029392"
    ],
    "tgn:id":7519351,
    "tgn:name:en":"Algidus, Mount",
    "tgn:placetype":[
        "aat:300008795"
    ]
},
  "bbox": [],
  "geometry": {"coordinates":[171.35,-43.25],"type":"Point"}
}