{
  "id": 6006309,
  "type": "Feature",
  "properties": {
    "tgn:hierarchy":[
        "tgn:6006309",
        "tgn:1000004",
        "tgn:7011500",
        "tgn:7002435",
        "tgn:7029392"
    ],
    "tgn:id":6006309,
    "tgn:name":"Verkhne-Angarsk",
    "tgn:placetype":[
        "aat:300008347"
    ]
},
  "bbox": [],
  "geometry": {"coordinates":[111.2333,55.8667],"type":"Point"}
}