{
  "id": 7149860,
  "type": "Feature",
  "properties": {
    "tgn:hierarchy":[
        "tgn:7149860",
        "tgn:7003692",
        "tgn:1000003",
        "tgn:7000084",
        "tgn:7029392"
    ],
    "tgn:id":7149860,
    "tgn:name":"Kr\u00e4utle",
    "tgn:placetype":[
        "aat:300000206"
    ]
},
  "bbox": [],
  "geometry": {"coordinates":[9.916667,48.033333],"type":"Point"}
}