{
  "id": 2446735,
  "type": "Feature",
  "properties": {
    "tgn:hierarchy":[
        "tgn:2446735",
        "tgn:1000001",
        "tgn:7012149",
        "tgn:2001420",
        "tgn:7007526",
        "tgn:7029392"
    ],
    "tgn:id":2446735,
    "tgn:name":"Lexington Cave",
    "tgn:placetype":[
        "aat:300008746"
    ]
},
  "bbox": [],
  "geometry": {"coordinates":[-114.1667,38.8667],"type":"Point"}
}