<<<<<<< HEAD
{
  "id": 7115188,
  "type": "Feature",
  "properties": {
    "tgn:hierarchy":[
        "tgn:7115188",
        "tgn:1000003",
        "tgn:7003682",
        "tgn:7000084",
        "tgn:7029392"
    ],
    "tgn:id":7115188,
    "tgn:name":"Palmberg",
    "tgn:placetype":[
        "aat:300008777"
    ]
},
  "bbox": [],
  "geometry": {"coordinates":[8.233333,49.533333],"type":"Point"}
}
=======
{"geometry":{"type":"Point","coordinates":[8.233333,49.533333]},"type":"Feature","properties":{"hierarchy":["tgn:7115188","tgn:1000003","tgn:7003682","tgn:7000084","tgn:7029392"],"placetype":["aat:300008777"],"id":7115188,"name:xx":"Palmberg"}}
>>>>>>> 03f74aca74312dbeaf24d7e61306dd6a786dc3d0
