{
  "id": 7283138,
  "type": "Feature",
  "properties": {
    "tgn:hierarchy":[
        "tgn:7283138",
        "tgn:1001705",
        "tgn:1000049",
        "tgn:1000002",
        "tgn:7029392"
    ],
    "tgn:id":7283138,
    "tgn:name":"Paso Tuna",
    "tgn:placetype":[
        "aat:300008347"
    ]
},
  "bbox": [],
  "geometry": {"coordinates":[-72.15,-36.016667],"type":"Point"}
}