{
  "id": 7555090,
  "type": "Feature",
  "properties": {
    "tgn:hierarchy":[
        "tgn:7555090",
        "tgn:1000004",
        "tgn:7000198",
        "tgn:1001998",
        "tgn:7029392"
    ],
    "tgn:id":7555090,
    "tgn:name:en":"Mamit",
    "tgn:placetype":[
        "aat:300008347"
    ]
},
  "bbox": [],
  "geometry": {"coordinates":[92.489676,23.927034],"type":"Point"}
}