<<<<<<< HEAD
{
  "id": 2403869,
  "type": "Feature",
  "properties": {
    "tgn:hierarchy":[
        "tgn:2403869",
        "tgn:1000001",
        "tgn:7012149",
        "tgn:7007828",
        "tgn:7029392"
    ],
    "tgn:id":2403869,
    "tgn:name":"Howe Brook",
    "tgn:placetype":[
        "aat:300008699"
    ]
},
  "bbox": [],
  "geometry": {"coordinates":[-72.7833,43.9333],"type":"Point"}
}
=======
{"geometry":{"type":"Point","coordinates":[-72.783300,43.933300]},"type":"Feature","properties":{"hierarchy":["tgn:2403869","tgn:1000001","tgn:7012149","tgn:7007828","tgn:7029392"],"placetype":["aat:300008699"],"id":2403869,"name:xx":"Howe Brook"}}
>>>>>>> 03f74aca74312dbeaf24d7e61306dd6a786dc3d0
