{
  "id": 7577724,
  "type": "Feature",
  "properties": {
    "tgn:hierarchy":[
        "tgn:7577724",
        "tgn:1000004",
        "tgn:1001869",
        "tgn:7000198",
        "tgn:7029392"
    ],
    "tgn:id":7577724,
    "tgn:name:en":"Khokhri",
    "tgn:placetype":[
        "aat:300008347"
    ]
},
  "bbox": [],
  "geometry": {"coordinates":[70.816667,21.816667],"type":"Point"}
}