{
  "id": 7189082,
  "type": "Feature",
  "properties": {
    "tgn:hierarchy":[
        "tgn:7189082",
        "tgn:1000003",
        "tgn:7003678",
        "tgn:7000084",
        "tgn:7029392"
    ],
    "tgn:id":7189082,
    "tgn:name":"Eisen-Berg",
    "tgn:placetype":[
        "aat:300008777"
    ]
},
  "bbox": [],
  "geometry": {"coordinates":[9.333333,50.25],"type":"Point"}
}