<<<<<<< HEAD
{
  "id": 2403136,
  "type": "Feature",
  "properties": {
    "tgn:hierarchy":[
        "tgn:2403136",
        "tgn:1000001",
        "tgn:7012149",
        "tgn:2001506",
        "tgn:7007709",
        "tgn:7029392"
    ],
    "tgn:id":2403136,
    "tgn:name":"House Creek",
    "tgn:placetype":[
        "aat:300008706"
    ]
},
  "bbox": [],
  "geometry": {"coordinates":[-76.4667,35.4],"type":"Point"}
}
=======
{"geometry":{"type":"Point","coordinates":[-76.466700,35.400000]},"type":"Feature","properties":{"hierarchy":["tgn:2403136","tgn:1000001","tgn:7012149","tgn:2001506","tgn:7007709","tgn:7029392"],"placetype":["aat:300008706"],"id":2403136,"name:xx":"House Creek"}}
>>>>>>> 03f74aca74312dbeaf24d7e61306dd6a786dc3d0
