{
  "id": 7004661,
  "type": "Feature",
  "properties": {
    "tgn:hierarchy":[
        "tgn:7004661",
        "tgn:7016687",
        "tgn:1000004",
        "tgn:7000893",
        "tgn:1000120",
        "tgn:7029392"
    ],
    "tgn:id":7004661,
    "tgn:name":"Miyako",
    "tgn:placetype":[
        "aat:300008347",
        "aat:300008389"
    ]
},
  "bbox": [],
  "geometry": {"coordinates":[141.9833,39.6333],"type":"Point"}
}