{
  "id": 2406761,
  "type": "Feature",
  "properties": {
    "tgn:hierarchy":[
        "tgn:2406761",
        "tgn:1000001",
        "tgn:2000497",
        "tgn:7012149",
        "tgn:7007251",
        "tgn:7029392"
    ],
    "tgn:id":2406761,
    "tgn:name":"Hunt Slough",
    "tgn:placetype":[
        "aat:300008699"
    ]
},
  "bbox": [],
  "geometry": {"coordinates":[-89.7333,41.4833],"type":"Point"}
}