<<<<<<< HEAD
{
  "id": 2763120,
  "type": "Feature",
  "properties": {
    "tgn:hierarchy":[
        "tgn:2763120",
        "tgn:2000193",
        "tgn:1000001",
        "tgn:7012149",
        "tgn:7007158",
        "tgn:7029392"
    ],
    "tgn:id":2763120,
    "tgn:name":"Westside Ditch",
    "tgn:placetype":[
        "aat:300006075"
    ]
},
  "bbox": [],
  "geometry": {"coordinates":[-105.85,37.4333],"type":"Point"}
}
=======
{"geometry":{"type":"Point","coordinates":[-105.850000,37.433300]},"type":"Feature","properties":{"hierarchy":["tgn:2763120","tgn:2000193","tgn:1000001","tgn:7012149","tgn:7007158","tgn:7029392"],"placetype":["aat:300006075"],"id":2763120,"name:xx":"Westside Ditch"}}
>>>>>>> 03f74aca74312dbeaf24d7e61306dd6a786dc3d0
