{
  "id": 2704967,
  "type": "Feature",
  "properties": {
    "tgn:hierarchy":[
        "tgn:2704967",
        "tgn:1000001",
        "tgn:1002461",
        "tgn:7012149",
        "tgn:7007159",
        "tgn:7029392"
    ],
    "tgn:id":2704967,
    "tgn:name":"Sunset Ridge",
    "tgn:placetype":[
        "aat:300266640"
    ]
},
  "bbox": [],
  "geometry": {"coordinates":[-72.5833,41.7667],"type":"Point"}
}