{
  "id": 1014099,
  "type": "Feature",
  "properties": {
    "tgn:hierarchy":[
        "tgn:1014099",
        "tgn:7005685",
        "tgn:1000001",
        "tgn:7005799",
        "tgn:7029392"
    ],
    "tgn:id":1014099,
    "tgn:name":"Oromocto",
    "tgn:placetype":[
        "aat:300008347"
    ]
},
  "bbox": [],
  "geometry": {"coordinates":[-66.4667,45.8333],"type":"Point"}
}