{
  "id": 1129160,
  "type": "Feature",
  "properties": {
    "tgn:hierarchy":[
        "tgn:1129160",
        "tgn:1000001",
        "tgn:7012149",
        "tgn:7007708",
        "tgn:7029392"
    ],
    "tgn:id":1129160,
    "tgn:name":"Rogue",
    "tgn:placetype":[
        "aat:300008707"
    ]
},
  "bbox": [],
  "geometry": {"coordinates":[-122.2167,43.05],"type":"Point"}
}