{
  "id": 2412342,
  "type": "Feature",
  "properties": {
    "tgn:hierarchy":[
        "tgn:2412342",
        "tgn:1000001",
        "tgn:7012149",
        "tgn:2001664",
        "tgn:7007707",
        "tgn:7029392"
    ],
    "tgn:id":2412342,
    "tgn:name":"Indian Springs",
    "tgn:placetype":[
        "aat:300008347"
    ]
},
  "bbox": [],
  "geometry": {"coordinates":[-97.5667,35.8833],"type":"Point"}
}