{
  "id": 2228732,
  "type": "Feature",
  "properties": {
    "tgn:hierarchy":[
        "tgn:2228732",
        "tgn:1000001",
        "tgn:7012149",
        "tgn:7007825",
        "tgn:7029392"
    ],
    "tgn:id":2228732,
    "tgn:name":"Cedar Fork",
    "tgn:placetype":[
        "aat:300008699"
    ]
},
  "bbox": [],
  "geometry": {"coordinates":[-84.5333,35.65],"type":"Point"}
}