<<<<<<< HEAD
{
  "id": 2767255,
  "type": "Feature",
  "properties": {
    "tgn:hierarchy":[
        "tgn:2767255",
        "tgn:1000001",
        "tgn:7012149",
        "tgn:2002123",
        "tgn:7007827",
        "tgn:7029392"
    ],
    "tgn:id":2767255,
    "tgn:name":"White Rock Spring",
    "tgn:placetype":[
        "aat:300008697"
    ]
},
  "bbox": [],
  "geometry": {"coordinates":[-112.9,40.3167],"type":"Point"}
}
=======
{"geometry":{"type":"Point","coordinates":[-112.900000,40.316700]},"type":"Feature","properties":{"hierarchy":["tgn:2767255","tgn:1000001","tgn:7012149","tgn:2002123","tgn:7007827","tgn:7029392"],"placetype":["aat:300008697"],"id":2767255,"name:xx":"White Rock Spring"}}
>>>>>>> 03f74aca74312dbeaf24d7e61306dd6a786dc3d0
