{
  "id": 7257688,
  "type": "Feature",
  "properties": {
    "tgn:concordances":{
        "gn:id":"2758752"
    },
    "tgn:hierarchy":[
        "tgn:7257688",
        "tgn:1000003",
        "tgn:7003622",
        "tgn:7016845",
        "tgn:7029392"
    ],
    "tgn:id":7257688,
    "tgn:name:nl":"Boekenderbos",
    "tgn:placetype":[
        "aat:300008347"
    ]
},
  "bbox": [],
  "geometry": {"coordinates":[6.033333,51.316667],"type":"Point"}
}