{
  "id": 7509346,
  "type": "Feature",
  "properties": {
    "tgn:hierarchy":[
        "tgn:7509346",
        "tgn:1009227",
        "tgn:1000226",
        "tgn:7016822",
        "tgn:1000006",
        "tgn:7029392"
    ],
    "tgn:id":7509346,
    "tgn:name:en":"Terror Cove",
    "tgn:placetype":[
        "aat:300132317"
    ]
},
  "bbox": [],
  "geometry": {"coordinates":[166.216667,-50.55],"type":"Point"}
}