{
  "id": 2318842,
  "type": "Feature",
  "properties": {
    "tgn:hierarchy":[
        "tgn:2318842",
        "tgn:1000001",
        "tgn:7012149",
        "tgn:2002022",
        "tgn:7007826",
        "tgn:7029392"
    ],
    "tgn:id":2318842,
    "tgn:name":"Escondido Lake",
    "tgn:placetype":[
        "aat:300006191"
    ]
},
  "bbox": [],
  "geometry": {"coordinates":[-97.9667,27.4833],"type":"Point"}
}