{
  "id": 7484343,
  "type": "Feature",
  "properties": {
    "tgn:hierarchy":[
        "tgn:7484343",
        "tgn:7001001",
        "tgn:1000004",
        "tgn:1000141",
        "tgn:7029392"
    ],
    "tgn:id":7484343,
    "tgn:name":"Jieshoucun",
    "tgn:placetype":[
        "aat:300008347"
    ]
},
  "bbox": [],
  "geometry": {"coordinates":[120.444167,23.458056],"type":"Point"}
}