{
  "id": 2585479,
  "type": "Feature",
  "properties": {
    "tgn:hierarchy":[
        "tgn:2585479",
        "tgn:1000001",
        "tgn:7012149",
        "tgn:7007157",
        "tgn:7029392"
    ],
    "tgn:id":2585479,
    "tgn:name":"Pinto Wash",
    "tgn:placetype":[
        "aat:300008699"
    ]
},
  "bbox": [],
  "geometry": {"coordinates":[-115.8833,32.6333],"type":"Point"}
}