{
  "id": 7545438,
  "type": "Feature",
  "properties": {
    "tgn:hierarchy":[
        "tgn:7545438",
        "tgn:1000004",
        "tgn:7000198",
        "tgn:7031786",
        "tgn:7029392"
    ],
    "tgn:id":7545438,
    "tgn:name:en":"Bheti\u0101ra",
    "tgn:placetype":[
        "aat:300008347"
    ]
},
  "bbox": [],
  "geometry": {"coordinates":[78.515095,30.610519],"type":"Point"}
}