{
  "id": 1088293,
  "type": "Feature",
  "properties": {
    "tgn:hierarchy":[
        "tgn:1088293",
        "tgn:1001189",
        "tgn:7001242",
        "tgn:1000153",
        "tgn:7029392"
    ],
    "tgn:id":1088293,
    "tgn:name":"Yaound\u00e9",
    "tgn:placetype":[
        "aat:300008347",
        "aat:300387218",
        "aat:300008389",
        "aat:300387219",
        "aat:300387512",
        "aat:300387223",
        "aat:300387270",
        "aat:300387302",
        "aat:300387296"
    ]
},
  "bbox": [],
  "geometry": {"coordinates":[11.5833,3.85],"type":"Point"}
}