{
  "id": 2160661,
  "type": "Feature",
  "properties": {
    "tgn:hierarchy":[
        "tgn:2160661",
        "tgn:1000001",
        "tgn:7012149",
        "tgn:1002314",
        "tgn:7007240",
        "tgn:7029392"
    ],
    "tgn:id":2160661,
    "tgn:name":"Bel Aire Canal Number C 1-N",
    "tgn:placetype":[
        "aat:300006075"
    ]
},
  "bbox": [],
  "geometry": {"coordinates":[-80.3833,25.6167],"type":"Point"}
}