{
  "id": 2056973,
  "type": "Feature",
  "properties": {
    "tgn:hierarchy":[
        "tgn:2056973",
        "tgn:2001090",
        "tgn:1000001",
        "tgn:7012149",
        "tgn:7007522",
        "tgn:7029392"
    ],
    "tgn:id":2056973,
    "tgn:name":"Michigan City",
    "tgn:placetype":[
        "aat:300008347"
    ]
},
  "bbox": [],
  "geometry": {"coordinates":[-89.25,34.9667],"type":"Point"}
}