{
  "id": 7217406,
  "type": "Feature",
  "properties": {
    "tgn:hierarchy":[
        "tgn:7217406",
        "tgn:7002751",
        "tgn:7001399",
        "tgn:1000003",
        "tgn:1000074",
        "tgn:7029392"
    ],
    "tgn:id":7217406,
    "tgn:name":"Gio\u00fara, Nis\u00edda",
    "tgn:placetype":[
        "aat:300008791"
    ]
},
  "bbox": [],
  "geometry": {"coordinates":[24.166389,39.389722],"type":"Point"}
}