{
  "id": 2557261,
  "type": "Feature",
  "properties": {
    "tgn:hierarchy":[
        "tgn:2557261",
        "tgn:1000001",
        "tgn:7012149",
        "tgn:2002119",
        "tgn:7007827",
        "tgn:7029392"
    ],
    "tgn:id":2557261,
    "tgn:name":"Old La Sal",
    "tgn:placetype":[
        "aat:300008347"
    ]
},
  "bbox": [],
  "geometry": {"coordinates":[-109.1333,38.3167],"type":"Point"}
}