{
  "id": 7259505,
  "type": "Feature",
  "properties": {
    "tgn:hierarchy":[
        "tgn:7259505",
        "tgn:7018239",
        "tgn:1000003",
        "tgn:1000063",
        "tgn:7018236",
        "tgn:7029392"
    ],
    "tgn:id":7259505,
    "tgn:name":"Wambeek",
    "tgn:placetype":[
        "aat:300008347"
    ]
},
  "bbox": [],
  "geometry": {"coordinates":[4.161695,50.852806],"type":"Point"}
}