{
  "id": 2296811,
  "type": "Feature",
  "properties": {
    "tgn:hierarchy":[
        "tgn:2296811",
        "tgn:1000001",
        "tgn:7012149",
        "tgn:1002400",
        "tgn:7007255",
        "tgn:7029392"
    ],
    "tgn:id":2296811,
    "tgn:name":"Dry Creek",
    "tgn:placetype":[
        "aat:300008706"
    ]
},
  "bbox": [],
  "geometry": {"coordinates":[-84.85,38.7167],"type":"Point"}
}