{
  "id": 7453413,
  "type": "Feature",
  "properties": {
    "tgn:hierarchy":[
        "tgn:7453413",
        "tgn:7002444",
        "tgn:1000003",
        "tgn:7008082",
        "tgn:7008591",
        "tgn:7029392"
    ],
    "tgn:id":7453413,
    "tgn:name:en":"Dionard, Strath",
    "tgn:placetype":[
        "aat:300008761"
    ]
},
  "bbox": [],
  "geometry": {"coordinates":[-4.85,58.433333],"type":"Point"}
}