{
  "id": 2675195,
  "type": "Feature",
  "properties": {
    "tgn:hierarchy":[
        "tgn:2675195",
        "tgn:1000001",
        "tgn:2000921",
        "tgn:7012149",
        "tgn:7007515",
        "tgn:7029392"
    ],
    "tgn:id":2675195,
    "tgn:name":"Sol Ridge",
    "tgn:placetype":[
        "aat:300266640"
    ]
},
  "bbox": [],
  "geometry": {"coordinates":[-70.7833,45.15],"type":"Point"}
}