{
  "id": 7068609,
  "type": "Feature",
  "properties": {
    "tgn:hierarchy":[
        "tgn:7068609",
        "tgn:1000003",
        "tgn:7003688",
        "tgn:7000084",
        "tgn:7029392"
    ],
    "tgn:id":7068609,
    "tgn:name":"Stakendorf",
    "tgn:placetype":[
        "aat:300008347"
    ]
},
  "bbox": [],
  "geometry": {"coordinates":[10.433333,54.383333],"type":"Point"}
}