{
  "id": 2740871,
  "type": "Feature",
  "properties": {
    "tgn:hierarchy":[
        "tgn:2740871",
        "tgn:1000001",
        "tgn:7006451",
        "tgn:7012149",
        "tgn:2000099",
        "tgn:7029392"
    ],
    "tgn:id":2740871,
    "tgn:name":"Upper Sam Canyon Tank",
    "tgn:placetype":[
        "aat:300006191"
    ]
},
  "bbox": [],
  "geometry": {"coordinates":[-110.6333,34.0333],"type":"Point"}
}