{
  "id": 7363622,
  "type": "Feature",
  "properties": {
    "tgn:hierarchy":[
        "tgn:7363622",
        "tgn:1001835",
        "tgn:1000001",
        "tgn:7005560",
        "tgn:7029392"
    ],
    "tgn:id":7363622,
    "tgn:name":"El Mogor",
    "tgn:placetype":[
        "aat:300008347"
    ]
},
  "bbox": [],
  "geometry": {"coordinates":[-116.602778,32.035556],"type":"Point"}
}