{
  "id": 7033220,
  "type": "Feature",
  "properties": {
    "tgn:hierarchy":[
        "tgn:7033220",
        "tgn:7002991",
        "tgn:1000003",
        "tgn:7002997",
        "tgn:1000080",
        "tgn:7029392"
    ],
    "tgn:id":7033220,
    "tgn:name":"Grande, Lago",
    "tgn:placetype":[
        "aat:300008680"
    ]
},
  "bbox": [],
  "geometry": {"coordinates":[12.093611,46.654722],"type":"Point"}
}