{
  "id": 7408831,
  "type": "Feature",
  "properties": {
    "tgn:hierarchy":[
        "tgn:7408831",
        "tgn:1000001",
        "tgn:1001893",
        "tgn:7005560",
        "tgn:7029392"
    ],
    "tgn:id":7408831,
    "tgn:name":"El Cacahuananche",
    "tgn:placetype":[
        "aat:300008347"
    ]
},
  "bbox": [],
  "geometry": {"coordinates":[-100.325,18.483333],"type":"Point"}
}