{
  "id": 1002105,
  "type": "Feature",
  "properties": {
    "tgn:hierarchy":[
        "tgn:1002105",
        "tgn:1000004",
        "tgn:7029392"
    ],
    "tgn:id":1002105,
    "tgn:name":"Punch",
    "tgn:placetype":[
        "aat:300387346"
    ]
},
  "bbox": [],
  "geometry": {"coordinates":[73.8333,33.9167],"type":"Point"}
}