<<<<<<< HEAD
{
  "id": 7053007,
  "type": "Feature",
  "properties": {
    "tgn:hierarchy":[
        "tgn:7053007",
        "tgn:1001724",
        "tgn:1000003",
        "tgn:7003121",
        "tgn:1000080",
        "tgn:7029392"
    ],
    "tgn:id":7053007,
    "tgn:name":"Iameddari, Monte",
    "tgn:placetype":[
        "aat:300008795"
    ]
},
  "bbox": [],
  "geometry": {"coordinates":[8.883333,40.316667],"type":"Point"}
}
=======
{"geometry":{"type":"Point","coordinates":[8.883333,40.316667]},"type":"Feature","properties":{"hierarchy":["tgn:7053007","tgn:1001724","tgn:1000003","tgn:7003121","tgn:1000080","tgn:7029392"],"placetype":["aat:300008795"],"id":7053007,"name:xx":"Iameddari, Monte"}}
>>>>>>> 03f74aca74312dbeaf24d7e61306dd6a786dc3d0
