{
  "id": 7506407,
  "type": "Feature",
  "properties": {
    "tgn:hierarchy":[
        "tgn:7506407",
        "tgn:1009227",
        "tgn:1000226",
        "tgn:7016822",
        "tgn:1000006",
        "tgn:7029392"
    ],
    "tgn:id":7506407,
    "tgn:name:en":"Round Downs",
    "tgn:placetype":[
        "aat:300008795"
    ]
},
  "bbox": [],
  "geometry": {"coordinates":[168.833333,-45.783333],"type":"Point"}
}