{
  "id": 2620021,
  "type": "Feature",
  "properties": {
    "tgn:hierarchy":[
        "tgn:2620021",
        "tgn:1000001",
        "tgn:7012149",
        "tgn:2001846",
        "tgn:7007825",
        "tgn:7029392"
    ],
    "tgn:id":2620021,
    "tgn:name":"Ripshin Lake",
    "tgn:placetype":[
        "aat:300008680"
    ]
},
  "bbox": [],
  "geometry": {"coordinates":[-82.1167,36.1667],"type":"Point"}
}