{
  "id": 7561473,
  "type": "Feature",
  "properties": {
    "tgn:hierarchy":[
        "tgn:7561473",
        "tgn:1000004",
        "tgn:7000198",
        "tgn:7016722",
        "tgn:7029392"
    ],
    "tgn:id":7561473,
    "tgn:name:en":"Basrehar",
    "tgn:placetype":[
        "aat:300008347"
    ]
},
  "bbox": [],
  "geometry": {"coordinates":[79.091517,26.850782],"type":"Point"}
}