<<<<<<< HEAD
{
  "id": 7488279,
  "type": "Feature",
  "properties": {
    "tgn:hierarchy":[
        "tgn:7488279",
        "tgn:1000004",
        "tgn:7001009",
        "tgn:1000141",
        "tgn:7029392"
    ],
    "tgn:id":7488279,
    "tgn:name":"Huilaicuo",
    "tgn:placetype":[
        "aat:300000745"
    ]
},
  "bbox": [],
  "geometry": {"coordinates":[120.638359,24.163224],"type":"Point"}
}
=======
{"geometry":{"type":"Point","coordinates":[120.638359,24.163224]},"type":"Feature","properties":{"hierarchy":["tgn:7488279","tgn:1000004","tgn:7001009","tgn:1000141","tgn:7029392"],"placetype":["aat:300000745"],"id":7488279,"name:xx":"Huilaicuo"}}
>>>>>>> 03f74aca74312dbeaf24d7e61306dd6a786dc3d0
