{
  "id": 7488279,
  "type": "Feature",
  "properties": {
    "tgn:hierarchy":[
        "tgn:7488279",
        "tgn:1000004",
        "tgn:7001009",
        "tgn:1000141",
        "tgn:7029392"
    ],
    "tgn:id":7488279,
    "tgn:name":"Huilaicuo",
    "tgn:placetype":[
        "aat:300000745"
    ]
},
  "bbox": [],
  "geometry": {"coordinates":[120.638359,24.163224],"type":"Point"}
}