{
  "id": 2583787,
  "type": "Feature",
  "properties": {
    "tgn:hierarchy":[
        "tgn:2583787",
        "tgn:2002138",
        "tgn:1000001",
        "tgn:7012149",
        "tgn:7007919",
        "tgn:7029392"
    ],
    "tgn:id":2583787,
    "tgn:name":"Pine Spur Ridge",
    "tgn:placetype":[
        "aat:300266640"
    ]
},
  "bbox": [],
  "geometry": {"coordinates":[-79.8333,37.8667],"type":"Point"}
}