{
  "id": 2722727,
  "type": "Feature",
  "properties": {
    "tgn:hierarchy":[
        "tgn:2722727",
        "tgn:1000001",
        "tgn:1002249",
        "tgn:7012149",
        "tgn:7007710",
        "tgn:7029392"
    ],
    "tgn:id":2722727,
    "tgn:name":"Tiny Cave",
    "tgn:placetype":[
        "aat:300008746"
    ]
},
  "bbox": [],
  "geometry": {"coordinates":[-77.6167,40.85],"type":"Point"}
}