<<<<<<< HEAD
{
  "id": 7363843,
  "type": "Feature",
  "properties": {
    "tgn:hierarchy":[
        "tgn:7363843",
        "tgn:1001835",
        "tgn:1000001",
        "tgn:7005560",
        "tgn:7029392"
    ],
    "tgn:id":7363843,
    "tgn:name":"Rancho El Bano",
    "tgn:placetype":[
        "aat:300000241"
    ]
},
  "bbox": [],
  "geometry": {"coordinates":[-116.333333,32.416667],"type":"Point"}
}
=======
{"geometry":{"type":"Point","coordinates":[-116.333333,32.416667]},"type":"Feature","properties":{"hierarchy":["tgn:7363843","tgn:1001835","tgn:1000001","tgn:7005560","tgn:7029392"],"placetype":["aat:300000241"],"id":7363843,"name:xx":"Rancho El Bano"}}
>>>>>>> 03f74aca74312dbeaf24d7e61306dd6a786dc3d0
