{
  "id": 7527694,
  "type": "Feature",
  "properties": {
    "tgn:hierarchy":[
        "tgn:7527694",
        "tgn:7001242",
        "tgn:7016833",
        "tgn:1001083",
        "tgn:7029392"
    ],
    "tgn:id":7527694,
    "tgn:name:en":"Z\u0101wiyat Umm \u1e28usayn",
    "tgn:placetype":[
        "aat:300008347"
    ]
},
  "bbox": [],
  "geometry": {"coordinates":[31.216667,29.483333],"type":"Point"}
}