{
  "id": 1127918,
  "type": "Feature",
  "properties": {
    "tgn:hierarchy":[
        "tgn:1127918",
        "tgn:1002366",
        "tgn:1000001",
        "tgn:7012149",
        "tgn:7007159",
        "tgn:7029392"
    ],
    "tgn:id":1127918,
    "tgn:name":"Norwalk",
    "tgn:placetype":[
        "aat:300008707"
    ]
},
  "bbox": [],
  "geometry": {"coordinates":[-73.4667,41.3167],"type":"Point"}
}