{
  "id": 2614398,
  "type": "Feature",
  "properties": {
    "tgn:hierarchy":[
        "tgn:2614398",
        "tgn:1000001",
        "tgn:7012149",
        "tgn:2002371",
        "tgn:7007923",
        "tgn:7029392"
    ],
    "tgn:id":2614398,
    "tgn:name":"Reid Draw",
    "tgn:placetype":[
        "aat:300008761"
    ]
},
  "bbox": [],
  "geometry": {"coordinates":[-107.6167,42.8167],"type":"Point"}
}