{
  "id": 7411852,
  "type": "Feature",
  "properties": {
    "tgn:hierarchy":[
        "tgn:7411852",
        "tgn:7005587",
        "tgn:1000001",
        "tgn:7005560",
        "tgn:7029392"
    ],
    "tgn:id":7411852,
    "tgn:name:es":"Acanoa",
    "tgn:placetype":[
        "aat:300008347"
    ]
},
  "bbox": [],
  "geometry": {"coordinates":[-98.258333,20.791667],"type":"Point"}
}