{
  "id": 7152375,
  "type": "Feature",
  "properties": {
    "tgn:hierarchy":[
        "tgn:7152375",
        "tgn:1000003",
        "tgn:7003678",
        "tgn:7000084",
        "tgn:7029392"
    ],
    "tgn:id":7152375,
    "tgn:name":"Gacken-Berg",
    "tgn:placetype":[
        "aat:300008777"
    ]
},
  "bbox": [],
  "geometry": {"coordinates":[8.116667,50.483333],"type":"Point"}
}