{
  "id": 2243861,
  "type": "Feature",
  "properties": {
    "tgn:hierarchy":[
        "tgn:2243861",
        "tgn:7006450",
        "tgn:1000001",
        "tgn:7012149",
        "tgn:2124014",
        "tgn:7029392"
    ],
    "tgn:id":2243861,
    "tgn:name":"Cleveland Lakes",
    "tgn:placetype":[
        "aat:300008680"
    ]
},
  "bbox": [],
  "geometry": {"coordinates":[-159.9333,66.5333],"type":"Point"}
}