{
  "id": 2649753,
  "type": "Feature",
  "properties": {
    "tgn:hierarchy":[
        "tgn:2649753",
        "tgn:1000001",
        "tgn:7012149",
        "tgn:1002687",
        "tgn:7007523",
        "tgn:7029392"
    ],
    "tgn:id":2649753,
    "tgn:name":"Scratchers Branch",
    "tgn:placetype":[
        "aat:300008699"
    ]
},
  "bbox": [],
  "geometry": {"coordinates":[-91.55,39.05],"type":"Point"}
}