{
  "id": 2675473,
  "type": "Feature",
  "properties": {
    "tgn:hierarchy":[
        "tgn:2675473",
        "tgn:1000001",
        "tgn:7012149",
        "tgn:2001287",
        "tgn:7007524",
        "tgn:7029392"
    ],
    "tgn:id":2675473,
    "tgn:name":"Solhaug Spring",
    "tgn:placetype":[
        "aat:300008697"
    ]
},
  "bbox": [],
  "geometry": {"coordinates":[-106.0833,47.6667],"type":"Point"}
}