{
  "id": 7301689,
  "type": "Feature",
  "properties": {
    "tgn:hierarchy":[
        "tgn:7301689",
        "tgn:7002847",
        "tgn:1001647",
        "tgn:1000003",
        "tgn:1000095",
        "tgn:7029392"
    ],
    "tgn:id":7301689,
    "tgn:name":"Minas de Santa Quiteria",
    "tgn:placetype":[
        "aat:300008347"
    ]
},
  "bbox": [],
  "geometry": {"coordinates":[-4.983333,39.466667],"type":"Point"}
}