{
  "id": 1135834,
  "type": "Feature",
  "properties": {
    "tgn:hierarchy":[
        "tgn:1135834",
        "tgn:7002854",
        "tgn:1001318",
        "tgn:1000004",
        "tgn:1000116",
        "tgn:7029392"
    ],
    "tgn:id":1135834,
    "tgn:name":"Banjir Kanal",
    "tgn:placetype":[
        "aat:300006075"
    ]
},
  "bbox": [],
  "geometry": {"coordinates":[106.75,-6.1167],"type":"Point"}
}