<<<<<<< HEAD
{
  "id": 2334016,
  "type": "Feature",
  "properties": {
    "tgn:hierarchy":[
        "tgn:2334016",
        "tgn:1000001",
        "tgn:7012149",
        "tgn:2001821",
        "tgn:7007713",
        "tgn:7029392"
    ],
    "tgn:id":2334016,
    "tgn:name":"Ford Mountain",
    "tgn:placetype":[
        "aat:300008798"
    ]
},
  "bbox": [],
  "geometry": {"coordinates":[-103.55,43.9167],"type":"Point"}
}
=======
{"geometry":{"type":"Point","coordinates":[-103.550000,43.916700]},"type":"Feature","properties":{"hierarchy":["tgn:2334016","tgn:1000001","tgn:7012149","tgn:2001821","tgn:7007713","tgn:7029392"],"placetype":["aat:300008798"],"id":2334016,"name:xx":"Ford Mountain"}}
>>>>>>> 03f74aca74312dbeaf24d7e61306dd6a786dc3d0
