{
  "id": 2334016,
  "type": "Feature",
  "properties": {
    "tgn:hierarchy":[
        "tgn:2334016",
        "tgn:1000001",
        "tgn:7012149",
        "tgn:2001821",
        "tgn:7007713",
        "tgn:7029392"
    ],
    "tgn:id":2334016,
    "tgn:name":"Ford Mountain",
    "tgn:placetype":[
        "aat:300008798"
    ]
},
  "bbox": [],
  "geometry": {"coordinates":[-103.55,43.9167],"type":"Point"}
}