{
  "id": 7401361,
  "type": "Feature",
  "properties": {
    "tgn:hierarchy":[
        "tgn:7401361",
        "tgn:1000001",
        "tgn:7005599",
        "tgn:7005560",
        "tgn:7029392"
    ],
    "tgn:id":7401361,
    "tgn:name":"La Noria",
    "tgn:placetype":[
        "aat:300008347"
    ]
},
  "bbox": [],
  "geometry": {"coordinates":[-98.491667,21.490278],"type":"Point"}
}