<<<<<<< HEAD
{
  "id": 2761624,
  "type": "Feature",
  "properties": {
    "tgn:hierarchy":[
        "tgn:2761624",
        "tgn:1000001",
        "tgn:7012149",
        "tgn:2001210",
        "tgn:7007523",
        "tgn:7029392"
    ],
    "tgn:id":2761624,
    "tgn:name":"West Pin Oak Creek",
    "tgn:placetype":[
        "aat:300008706"
    ]
},
  "bbox": [],
  "geometry": {"coordinates":[-94.0167,38.6833],"type":"Point"}
}
=======
{"geometry":{"type":"Point","coordinates":[-94.016700,38.683300]},"type":"Feature","properties":{"hierarchy":["tgn:2761624","tgn:1000001","tgn:7012149","tgn:2001210","tgn:7007523","tgn:7029392"],"placetype":["aat:300008706"],"id":2761624,"name:xx":"West Pin Oak Creek"}}
>>>>>>> 03f74aca74312dbeaf24d7e61306dd6a786dc3d0
