{
  "id": 7186934,
  "type": "Feature",
  "properties": {
    "tgn:hierarchy":[
        "tgn:7186934",
        "tgn:7003669",
        "tgn:1000003",
        "tgn:7000084",
        "tgn:7029392"
    ],
    "tgn:id":7186934,
    "tgn:name":"Goldberg",
    "tgn:placetype":[
        "aat:300008777"
    ]
},
  "bbox": [],
  "geometry": {"coordinates":[10.75,49.833333],"type":"Point"}
}