{
  "id": 2519387,
  "type": "Feature",
  "properties": {
    "tgn:hierarchy":[
        "tgn:2519387",
        "tgn:1000001",
        "tgn:7006451",
        "tgn:7012149",
        "tgn:2000097",
        "tgn:7029392"
    ],
    "tgn:id":2519387,
    "tgn:name":"Model A Tank",
    "tgn:placetype":[
        "aat:300006191"
    ]
},
  "bbox": [],
  "geometry": {"coordinates":[-111.7333,33.75],"type":"Point"}
}