{
  "id": 7544461,
  "type": "Feature",
  "properties": {
    "tgn:hierarchy":[
        "tgn:7544461",
        "tgn:7001242",
        "tgn:7016833",
        "tgn:1001335",
        "tgn:7029392"
    ],
    "tgn:id":7544461,
    "tgn:name":"Al \u1e28amr\u0101'",
    "tgn:placetype":[
        "aat:300008347"
    ]
},
  "bbox": [],
  "geometry": {"coordinates":[31.125567,31.351398],"type":"Point"}
}