{
  "id": 1041539,
  "type": "Feature",
  "properties": {
    "tgn:hierarchy":[
        "tgn:1041539",
        "tgn:1000003",
        "tgn:7003677",
        "tgn:7000084",
        "tgn:7029392"
    ],
    "tgn:id":1041539,
    "tgn:name":"Veltheim",
    "tgn:placetype":[
        "aat:300008347"
    ]
},
  "bbox": [],
  "geometry": {"coordinates":[8.966667,52.183333],"type":"Point"}
}