{
  "id": 2629295,
  "type": "Feature",
  "properties": {
    "tgn:hierarchy":[
        "tgn:2629295",
        "tgn:1000001",
        "tgn:2000470",
        "tgn:7012149",
        "tgn:7007250",
        "tgn:7029392"
    ],
    "tgn:id":2629295,
    "tgn:name":"Rosebrior Spring",
    "tgn:placetype":[
        "aat:300008697"
    ]
},
  "bbox": [],
  "geometry": {"coordinates":[-114.1833,44.3167],"type":"Point"}
}