{
  "id": 7589305,
  "type": "Feature",
  "properties": {
    "tgn:hierarchy":[
        "tgn:7589305",
        "tgn:1000004",
        "tgn:7000198",
        "tgn:7016883",
        "tgn:7029392"
    ],
    "tgn:id":7589305,
    "tgn:name:en":"Usm\u0101n Khera",
    "tgn:placetype":[
        "aat:300008347"
    ]
},
  "bbox": [],
  "geometry": {"coordinates":[73.902778,30.020833],"type":"Point"}
}