{
  "id": 2409696,
  "type": "Feature",
  "properties": {
    "tgn:hierarchy":[
        "tgn:2409696",
        "tgn:1000001",
        "tgn:7012149",
        "tgn:2001898",
        "tgn:7007825",
        "tgn:7029392"
    ],
    "tgn:id":2409696,
    "tgn:name":"Ikes Peak",
    "tgn:placetype":[
        "aat:300008798"
    ]
},
  "bbox": [],
  "geometry": {"coordinates":[-84.05,35.3833],"type":"Point"}
}