{
  "id": 7575487,
  "type": "Feature",
  "properties": {
    "tgn:hierarchy":[
        "tgn:7575487",
        "tgn:1000004",
        "tgn:7000198",
        "tgn:7016722",
        "tgn:7029392"
    ],
    "tgn:id":7575487,
    "tgn:name:en":"Lagcha",
    "tgn:placetype":[
        "aat:300008347"
    ]
},
  "bbox": [],
  "geometry": {"coordinates":[80.825351,27.83358],"type":"Point"}
}