{
  "id": 2264794,
  "type": "Feature",
  "properties": {
    "tgn:hierarchy":[
        "tgn:2264794",
        "tgn:1000001",
        "tgn:7012149",
        "tgn:1002932",
        "tgn:7007710",
        "tgn:7029392"
    ],
    "tgn:id":2264794,
    "tgn:name":"Craig Hill",
    "tgn:placetype":[
        "aat:300008798"
    ]
},
  "bbox": [],
  "geometry": {"coordinates":[-75.9833,41.65],"type":"Point"}
}