{
  "id": 7592058,
  "type": "Feature",
  "properties": {
    "tgn:hierarchy":[
        "tgn:7592058",
        "tgn:1000004",
        "tgn:7000198",
        "tgn:7000799",
        "tgn:7029392"
    ],
    "tgn:id":7592058,
    "tgn:name:en":"B\u0101wali",
    "tgn:placetype":[
        "aat:300008347"
    ]
},
  "bbox": [],
  "geometry": {"coordinates":[74.982141,32.680322],"type":"Point"}
}