{
  "id": 7588229,
  "type": "Feature",
  "properties": {
    "tgn:hierarchy":[
        "tgn:7588229",
        "tgn:1000004",
        "tgn:7000198",
        "tgn:7000799",
        "tgn:7029392"
    ],
    "tgn:id":7588229,
    "tgn:name:en":"Krishan N\u0101g",
    "tgn:placetype":[
        "aat:300132410"
    ]
},
  "bbox": [],
  "geometry": {"coordinates":[74.966667,34.045833],"type":"Point"}
}