<<<<<<< HEAD
{
  "id": 7365261,
  "type": "Feature",
  "properties": {
    "tgn:hierarchy":[
        "tgn:7365261",
        "tgn:7005581",
        "tgn:1000001",
        "tgn:7005560",
        "tgn:7029392"
    ],
    "tgn:id":7365261,
    "tgn:name":"El Ranchito",
    "tgn:placetype":[
        "aat:300008347"
    ]
},
  "bbox": [],
  "geometry": {"coordinates":[-106.316667,27.133333],"type":"Point"}
}
=======
{"geometry":{"type":"Point","coordinates":[-106.316667,27.133333]},"type":"Feature","properties":{"hierarchy":["tgn:7365261","tgn:7005581","tgn:1000001","tgn:7005560","tgn:7029392"],"placetype":["aat:300008347"],"id":7365261,"name:xx":"El Ranchito"}}
>>>>>>> 03f74aca74312dbeaf24d7e61306dd6a786dc3d0
