{
  "id": 7333087,
  "type": "Feature",
  "properties": {
    "tgn:hierarchy":[
        "tgn:7333087",
        "tgn:7002839",
        "tgn:7001158",
        "tgn:1000003",
        "tgn:1000095",
        "tgn:7029392"
    ],
    "tgn:id":7333087,
    "tgn:name":"La Matilla",
    "tgn:placetype":[
        "aat:300008347"
    ]
},
  "bbox": [],
  "geometry": {"coordinates":[-3.783333,41.183333],"type":"Point"}
}