<<<<<<< HEAD
{
  "id": 2339592,
  "type": "Feature",
  "properties": {
    "tgn:hierarchy":[
        "tgn:2339592",
        "tgn:1000001",
        "tgn:7012149",
        "tgn:1002440",
        "tgn:7007568",
        "tgn:7029392"
    ],
    "tgn:id":2339592,
    "tgn:name":"Frederick, Mount",
    "tgn:placetype":[
        "aat:300008798"
    ]
},
  "bbox": [],
  "geometry": {"coordinates":[-74.7833,43.9833],"type":"Point"}
}
=======
{"geometry":{"type":"Point","coordinates":[-74.783300,43.983300]},"type":"Feature","properties":{"hierarchy":["tgn:2339592","tgn:1000001","tgn:7012149","tgn:1002440","tgn:7007568","tgn:7029392"],"placetype":["aat:300008798"],"id":2339592,"name:xx":"Frederick, Mount"}}
>>>>>>> 03f74aca74312dbeaf24d7e61306dd6a786dc3d0
