{
  "id": 7198555,
  "type": "Feature",
  "properties": {
    "tgn:hierarchy":[
        "tgn:7198555",
        "tgn:1000003",
        "tgn:7000094",
        "tgn:7000084",
        "tgn:7029392"
    ],
    "tgn:id":7198555,
    "tgn:name":"Waldw\u00e4rter Eichholz",
    "tgn:placetype":[
        "aat:300004792"
    ]
},
  "bbox": [],
  "geometry": {"coordinates":[11.583333,53.966667],"type":"Point"}
}