{
  "id": 1096126,
  "type": "Feature",
  "properties": {
    "tgn:hierarchy":[
        "tgn:1096126",
        "tgn:7000490",
        "tgn:1000006",
        "tgn:7001828",
        "tgn:7029392"
    ],
    "tgn:id":1096126,
    "tgn:name":"Ashford",
    "tgn:placetype":[
        "aat:300008347"
    ]
},
  "bbox": [],
  "geometry": {"coordinates":[151.1167,-29.25],"type":"Point"}
}