{
  "id": 2780158,
  "type": "Feature",
  "properties": {
    "tgn:hierarchy":[
        "tgn:2780158",
        "tgn:7006450",
        "tgn:1000001",
        "tgn:7012149",
        "tgn:2000082",
        "tgn:7029392"
    ],
    "tgn:id":2780158,
    "tgn:name":"Wolk Harbor",
    "tgn:placetype":[
        "aat:300132316"
    ]
},
  "bbox": [],
  "geometry": {"coordinates":[-132.75,54.6833],"type":"Point"}
}