{
  "id": 7326799,
  "type": "Feature",
  "properties": {
    "tgn:hierarchy":[
        "tgn:7326799",
        "tgn:7002824",
        "tgn:1000003",
        "tgn:7002786",
        "tgn:1000095",
        "tgn:7029392"
    ],
    "tgn:id":7326799,
    "tgn:name":"San Pedro, Punta de",
    "tgn:placetype":[
        "aat:300386846"
    ]
},
  "bbox": [],
  "geometry": {"coordinates":[-8.433333,43.383333],"type":"Point"}
}