{
  "id": 7500034,
  "type": "Feature",
  "properties": {
    "tgn:hierarchy":[
        "tgn:7500034",
        "tgn:1000004",
        "tgn:1000959",
        "tgn:1000141",
        "tgn:7029392"
    ],
    "tgn:id":7500034,
    "tgn:name":"Huazhong Qiao",
    "tgn:placetype":[
        "aat:300007836"
    ]
},
  "bbox": [],
  "geometry": {"coordinates":[121.495819,25.012304],"type":"Point"}
}