{
  "id": 2195888,
  "type": "Feature",
  "properties": {
    "tgn:hierarchy":[
        "tgn:2195888",
        "tgn:1000001",
        "tgn:7012149",
        "tgn:7014398",
        "tgn:7013961",
        "tgn:7029392"
    ],
    "tgn:id":2195888,
    "tgn:name":"Broadmouth Hollow",
    "tgn:placetype":[
        "aat:300008761"
    ]
},
  "bbox": [],
  "geometry": {"coordinates":[-79.1333,38.7667],"type":"Point"}
}