{
  "id": 7475101,
  "type": "Feature",
  "properties": {
    "tgn:hierarchy":[
        "tgn:7475101",
        "tgn:1000004",
        "tgn:7467799",
        "tgn:1000141",
        "tgn:7029392"
    ],
    "tgn:id":7475101,
    "tgn:name":"Yongguang Guoxiao",
    "tgn:placetype":[
        "aat:300006495"
    ]
},
  "bbox": [],
  "geometry": {"coordinates":[120.302542,23.840569],"type":"Point"}
}