{
  "id": 2298917,
  "type": "Feature",
  "properties": {
    "tgn:hierarchy":[
        "tgn:2298917",
        "tgn:1000001",
        "tgn:7012149",
        "tgn:7007157",
        "tgn:2000187",
        "tgn:7029392"
    ],
    "tgn:id":2298917,
    "tgn:name":"Dublin Jack Ravine",
    "tgn:placetype":[
        "aat:300008761"
    ]
},
  "bbox": [],
  "geometry": {"coordinates":[-120.9667,39.9167],"type":"Point"}
}