{
  "id": 2681308,
  "type": "Feature",
  "properties": {
    "tgn:hierarchy":[
        "tgn:2681308",
        "tgn:1000001",
        "tgn:2001430",
        "tgn:7012149",
        "tgn:7007566",
        "tgn:7029392"
    ],
    "tgn:id":2681308,
    "tgn:name":"South Pasture Tank Number 1",
    "tgn:placetype":[
        "aat:300006191"
    ]
},
  "bbox": [],
  "geometry": {"coordinates":[-105.3167,32.85],"type":"Point"}
}