{
  "id": 1138294,
  "type": "Feature",
  "properties": {
    "tgn:hierarchy":[
        "tgn:1138294",
        "tgn:1000004",
        "tgn:1003408",
        "tgn:7018214",
        "tgn:7002435",
        "tgn:7029392"
    ],
    "tgn:id":1138294,
    "tgn:name":"Rakhmanovka",
    "tgn:placetype":[
        "aat:300008347"
    ]
},
  "bbox": [],
  "geometry": {"coordinates":[49.4833,51.95],"type":"Point"}
}