{
  "id": 2567603,
  "type": "Feature",
  "properties": {
    "tgn:hierarchy":[
        "tgn:2567603",
        "tgn:7006450",
        "tgn:1000001",
        "tgn:2124053",
        "tgn:7012149",
        "tgn:7029392"
    ],
    "tgn:id":2567603,
    "tgn:name":"Papoose Twins",
    "tgn:placetype":[
        "aat:300008680"
    ]
},
  "bbox": [],
  "geometry": {"coordinates":[-150.0833,61.5333],"type":"Point"}
}