{
  "id": 7447689,
  "type": "Feature",
  "properties": {
    "tgn:hierarchy":[
        "tgn:7447689",
        "tgn:7002444",
        "tgn:1000003",
        "tgn:7029508",
        "tgn:7008591",
        "tgn:7029392"
    ],
    "tgn:id":7447689,
    "tgn:name:en":"Stead of Culswick",
    "tgn:placetype":[
        "aat:300132316"
    ]
},
  "bbox": [],
  "geometry": {"coordinates":[-1.516667,60.183333],"type":"Point"}
}