{
  "id": 7381585,
  "type": "Feature",
  "properties": {
    "tgn:hierarchy":[
        "tgn:7381585",
        "tgn:1001836",
        "tgn:1000001",
        "tgn:7005560",
        "tgn:7029392"
    ],
    "tgn:id":7381585,
    "tgn:name":"Mercenarios, Punta",
    "tgn:placetype":[
        "aat:300386846"
    ]
},
  "bbox": [],
  "geometry": {"coordinates":[-111.416667,26.35],"type":"Point"}
}