{
  "id": 2633270,
  "type": "Feature",
  "properties": {
    "tgn:hierarchy":[
        "tgn:2633270",
        "tgn:1000001",
        "tgn:1003037",
        "tgn:7012149",
        "tgn:7007516",
        "tgn:7029392"
    ],
    "tgn:id":2633270,
    "tgn:name":"Rum Harbor",
    "tgn:placetype":[
        "aat:300132316"
    ]
},
  "bbox": [],
  "geometry": {"coordinates":[-75.25,38.05],"type":"Point"}
}