{
  "id": 7477966,
  "type": "Feature",
  "properties": {
    "tgn:hierarchy":[
        "tgn:7477966",
        "tgn:7487020",
        "tgn:1000004",
        "tgn:1000141",
        "tgn:7029392"
    ],
    "tgn:id":7477966,
    "tgn:name":"Gongguanzi Qiao",
    "tgn:placetype":[
        "aat:300007836"
    ]
},
  "bbox": [],
  "geometry": {"coordinates":[120.875742,24.660638],"type":"Point"}
}