<<<<<<< HEAD
{
  "id": 7477966,
  "type": "Feature",
  "properties": {
    "tgn:hierarchy":[
        "tgn:7477966",
        "tgn:7487020",
        "tgn:1000004",
        "tgn:1000141",
        "tgn:7029392"
    ],
    "tgn:id":7477966,
    "tgn:name":"Gongguanzi Qiao",
    "tgn:placetype":[
        "aat:300007836"
    ]
},
  "bbox": [],
  "geometry": {"coordinates":[120.875742,24.660638],"type":"Point"}
}
=======
{"geometry":{"type":"Point","coordinates":[120.875742,24.660638]},"type":"Feature","properties":{"hierarchy":["tgn:7477966","tgn:7487020","tgn:1000004","tgn:1000141","tgn:7029392"],"placetype":["aat:300007836"],"id":7477966,"name:xx":"Gongguanzi Qiao"}}
>>>>>>> 03f74aca74312dbeaf24d7e61306dd6a786dc3d0
