{
  "id": 2432976,
  "type": "Feature",
  "properties": {
    "tgn:hierarchy":[
        "tgn:2432976",
        "tgn:1002648",
        "tgn:1000001",
        "tgn:1007799",
        "tgn:7012149",
        "tgn:7007249",
        "tgn:7029392"
    ],
    "tgn:id":2432976,
    "tgn:name":"Kehewai Ridge",
    "tgn:placetype":[
        "aat:300266640"
    ]
},
  "bbox": [],
  "geometry": {"coordinates":[-156.8167,20.8333],"type":"Point"}
}