{
  "id": 7291815,
  "type": "Feature",
  "properties": {
    "tgn:hierarchy":[
        "tgn:7291815",
        "tgn:1001699",
        "tgn:1000049",
        "tgn:1000002",
        "tgn:7029392"
    ],
    "tgn:id":7291815,
    "tgn:name":"Folilco",
    "tgn:placetype":[
        "aat:300008347"
    ]
},
  "bbox": [],
  "geometry": {"coordinates":[-72.683333,-39.866667],"type":"Point"}
}