{
  "id": 2126999,
  "type": "Feature",
  "properties": {
    "tgn:hierarchy":[
        "tgn:2126999",
        "tgn:1000001",
        "tgn:7006451",
        "tgn:7012149",
        "tgn:2000098",
        "tgn:7029392"
    ],
    "tgn:id":2126999,
    "tgn:name":"Agway Valley",
    "tgn:placetype":[
        "aat:300008761"
    ]
},
  "bbox": [],
  "geometry": {"coordinates":[-113.5167,36.3167],"type":"Point"}
}