{
  "id": 2367991,
  "type": "Feature",
  "properties": {
    "tgn:hierarchy":[
        "tgn:2367991",
        "tgn:1000001",
        "tgn:7012149",
        "tgn:1002742",
        "tgn:7007920",
        "tgn:7029392"
    ],
    "tgn:id":2367991,
    "tgn:name":"Grubbs Cove",
    "tgn:placetype":[
        "aat:300132316"
    ]
},
  "bbox": [],
  "geometry": {"coordinates":[-119.4167,48.9833],"type":"Point"}
}