{
  "id": 2421368,
  "type": "Feature",
  "properties": {
    "tgn:hierarchy":[
        "tgn:2421368",
        "tgn:1000001",
        "tgn:2002262",
        "tgn:7012149",
        "tgn:7013961",
        "tgn:7029392"
    ],
    "tgn:id":2421368,
    "tgn:name":"Jerseywood Run",
    "tgn:placetype":[
        "aat:300008699"
    ]
},
  "bbox": [],
  "geometry": {"coordinates":[-80.6833,38.9833],"type":"Point"}
}