{
  "id": 2558451,
  "type": "Feature",
  "properties": {
    "tgn:hierarchy":[
        "tgn:2558451",
        "tgn:1000001",
        "tgn:7012149",
        "tgn:2001949",
        "tgn:7007826",
        "tgn:7029392"
    ],
    "tgn:id":2558451,
    "tgn:name":"Olive Branch",
    "tgn:placetype":[
        "aat:300008699"
    ]
},
  "bbox": [],
  "geometry": {"coordinates":[-98.0167,30.85],"type":"Point"}
}