{
  "id": 7278273,
  "type": "Feature",
  "properties": {
    "tgn:hierarchy":[
        "tgn:7278273",
        "tgn:1001692",
        "tgn:1000049",
        "tgn:1000002",
        "tgn:7029392"
    ],
    "tgn:id":7278273,
    "tgn:name":"Voipire",
    "tgn:placetype":[
        "aat:300008347"
    ]
},
  "bbox": [],
  "geometry": {"coordinates":[-72.183333,-39.333333],"type":"Point"}
}