{
  "id": 2441897,
  "type": "Feature",
  "properties": {
    "tgn:hierarchy":[
        "tgn:2441897",
        "tgn:2000947",
        "tgn:1000001",
        "tgn:7012149",
        "tgn:7007520",
        "tgn:7029392"
    ],
    "tgn:id":2441897,
    "tgn:name":"Kontio Lake",
    "tgn:placetype":[
        "aat:300008680"
    ]
},
  "bbox": [],
  "geometry": {"coordinates":[-88.3833,46.65],"type":"Point"}
}