{
  "id": 2273858,
  "type": "Feature",
  "properties": {
    "tgn:hierarchy":[
        "tgn:2273858",
        "tgn:1000001",
        "tgn:2002104",
        "tgn:7012149",
        "tgn:7007827",
        "tgn:7029392"
    ],
    "tgn:id":2273858,
    "tgn:name":"Daddy Spring",
    "tgn:placetype":[
        "aat:300008697"
    ]
},
  "bbox": [],
  "geometry": {"coordinates":[-110.25,39.6833],"type":"Point"}
}