{
  "id": 2372351,
  "type": "Feature",
  "properties": {
    "tgn:hierarchy":[
        "tgn:2372351",
        "tgn:1000001",
        "tgn:2000267",
        "tgn:7012149",
        "tgn:7007240",
        "tgn:7029392"
    ],
    "tgn:id":2372351,
    "tgn:name":"Halfway Lake",
    "tgn:placetype":[
        "aat:300008680"
    ]
},
  "bbox": [],
  "geometry": {"coordinates":[-84.45,29.9333],"type":"Point"}
}