{
  "id": 7588791,
  "type": "Feature",
  "properties": {
    "tgn:hierarchy":[
        "tgn:7588791",
        "tgn:1000004",
        "tgn:7000198",
        "tgn:1001894",
        "tgn:7029392"
    ],
    "tgn:id":7588791,
    "tgn:name:en":"Hanummana",
    "tgn:placetype":[
        "aat:300008347"
    ]
},
  "bbox": [],
  "geometry": {"coordinates":[82.09684,24.777953],"type":"Point"}
}