{
  "id": 7296922,
  "type": "Feature",
  "properties": {
    "tgn:hierarchy":[
        "tgn:7296922",
        "tgn:7002759",
        "tgn:7008909",
        "tgn:1000003",
        "tgn:1000095",
        "tgn:7029392"
    ],
    "tgn:id":7296922,
    "tgn:name":"Valdabra, Barranco de",
    "tgn:placetype":[
        "aat:300008699"
    ]
},
  "bbox": [],
  "geometry": {"coordinates":[-0.416667,42.033333],"type":"Point"}
}