{
  "id": 1004648,
  "type": "Feature",
  "properties": {
    "tgn:hierarchy":[
        "tgn:1004648",
        "tgn:7002445",
        "tgn:7018921",
        "tgn:1000003",
        "tgn:7008136",
        "tgn:7008591",
        "tgn:7029392"
    ],
    "tgn:id":1004648,
    "tgn:name:en":"Heston",
    "tgn:placetype":[
        "aat:300008347",
        "aat:300000745"
    ]
},
  "bbox": [],
  "geometry": {"coordinates":[-0.3833,51.4833],"type":"Point"}
}