{
  "id": 7314430,
  "type": "Feature",
  "properties": {
    "tgn:hierarchy":[
        "tgn:7314430",
        "tgn:1001768",
        "tgn:1000049",
        "tgn:1000002",
        "tgn:7029392"
    ],
    "tgn:id":7314430,
    "tgn:name":"Longomiche, Portezuelo",
    "tgn:placetype":[
        "aat:300259572"
    ]
},
  "bbox": [],
  "geometry": {"coordinates":[-70.25,-32.316667],"type":"Point"}
}