{
  "id": 7158677,
  "type": "Feature",
  "properties": {
    "tgn:hierarchy":[
        "tgn:7158677",
        "tgn:1000003",
        "tgn:7003676",
        "tgn:7000084",
        "tgn:7029392"
    ],
    "tgn:id":7158677,
    "tgn:name":"H\u00f6llen-Berg",
    "tgn:placetype":[
        "aat:300008777"
    ]
},
  "bbox": [],
  "geometry": {"coordinates":[10.15,51.616667],"type":"Point"}
}