{
  "id": 2676395,
  "type": "Feature",
  "properties": {
    "tgn:hierarchy":[
        "tgn:2676395",
        "tgn:1000001",
        "tgn:7012149",
        "tgn:2001718",
        "tgn:7007708",
        "tgn:7029392"
    ],
    "tgn:id":2676395,
    "tgn:name":"South Alkali Creek",
    "tgn:placetype":[
        "aat:300008706"
    ]
},
  "bbox": [],
  "geometry": {"coordinates":[-117.1833,43.5667],"type":"Point"}
}