{
  "id": 7272488,
  "type": "Feature",
  "properties": {
    "tgn:concordances":{
        "gn:id":"2745514"
    },
    "tgn:hierarchy":[
        "tgn:7272488",
        "tgn:1000003",
        "tgn:7003622",
        "tgn:7016845",
        "tgn:7029392"
    ],
    "tgn:id":7272488,
    "tgn:name:nl":"Vilgert",
    "tgn:placetype":[
        "aat:300008347"
    ]
},
  "bbox": [],
  "geometry": {"coordinates":[6.166667,51.416667],"type":"Point"}
}