{
  "id": 2632349,
  "type": "Feature",
  "properties": {
    "tgn:hierarchy":[
        "tgn:2632349",
        "tgn:2000918",
        "tgn:1000001",
        "tgn:7012149",
        "tgn:7007515",
        "tgn:7029392"
    ],
    "tgn:id":2632349,
    "tgn:name":"Royal Corner",
    "tgn:placetype":[
        "aat:300008347"
    ]
},
  "bbox": [],
  "geometry": {"coordinates":[-70.2333,44.0167],"type":"Point"}
}