<<<<<<< HEAD
{
  "id": 7177869,
  "type": "Feature",
  "properties": {
    "tgn:hierarchy":[
        "tgn:7177869",
        "tgn:1000003",
        "tgn:7003677",
        "tgn:7000084",
        "tgn:7029392"
    ],
    "tgn:id":7177869,
    "tgn:name":"Hagedorn",
    "tgn:placetype":[
        "aat:300000206"
    ]
},
  "bbox": [],
  "geometry": {"coordinates":[7.866667,51.833333],"type":"Point"}
}
=======
{"geometry":{"type":"Point","coordinates":[7.866667,51.833333]},"type":"Feature","properties":{"hierarchy":["tgn:7177869","tgn:1000003","tgn:7003677","tgn:7000084","tgn:7029392"],"placetype":["aat:300000206"],"id":7177869,"name:xx":"Hagedorn"}}
>>>>>>> 03f74aca74312dbeaf24d7e61306dd6a786dc3d0
