{
  "id": 2634168,
  "type": "Feature",
  "properties": {
    "tgn:hierarchy":[
        "tgn:2634168",
        "tgn:1000001",
        "tgn:2002367",
        "tgn:7012149",
        "tgn:7007923",
        "tgn:7029392"
    ],
    "tgn:id":2634168,
    "tgn:name":"Russell Draw",
    "tgn:placetype":[
        "aat:300008761"
    ]
},
  "bbox": [],
  "geometry": {"coordinates":[-105.5667,44.3833],"type":"Point"}
}