{
  "id": 2627258,
  "type": "Feature",
  "properties": {
    "tgn:hierarchy":[
        "tgn:2627258",
        "tgn:1000001",
        "tgn:2001435",
        "tgn:7012149",
        "tgn:7007566",
        "tgn:7029392"
    ],
    "tgn:id":2627258,
    "tgn:name":"Rodey Canyon",
    "tgn:placetype":[
        "aat:300008761"
    ]
},
  "bbox": [],
  "geometry": {"coordinates":[-107.1333,32.6167],"type":"Point"}
}