{
  "id": 2765115,
  "type": "Feature",
  "properties": {
    "tgn:hierarchy":[
        "tgn:2765115",
        "tgn:2000999",
        "tgn:1000001",
        "tgn:7012149",
        "tgn:7007521",
        "tgn:7029392"
    ],
    "tgn:id":2765115,
    "tgn:name":"Whispering Lake",
    "tgn:placetype":[
        "aat:300008680"
    ]
},
  "bbox": [],
  "geometry": {"coordinates":[-93.5167,46.6333],"type":"Point"}
}