{
  "id": 7565961,
  "type": "Feature",
  "properties": {
    "tgn:hierarchy":[
        "tgn:7565961",
        "tgn:1000004",
        "tgn:7000198",
        "tgn:7016722",
        "tgn:7029392"
    ],
    "tgn:id":7565961,
    "tgn:name:en":"Jam\u0101l\u012bpur",
    "tgn:placetype":[
        "aat:300008347"
    ]
},
  "bbox": [],
  "geometry": {"coordinates":[79.394553,26.389022],"type":"Point"}
}