{
  "id": 1002423,
  "type": "Feature",
  "properties": {
    "tgn:hierarchy":[
        "tgn:1002423",
        "tgn:1000001",
        "tgn:7012149",
        "tgn:7007568",
        "tgn:7029392"
    ],
    "tgn:id":1002423,
    "tgn:name":"Greene",
    "tgn:placetype":[
        "aat:300387145",
        "aat:300000771"
    ]
},
  "bbox": [],
  "geometry": {"coordinates":[-74.2167,42.2667],"type":"Point"}
}