{
  "id": 2605398,
  "type": "Feature",
  "properties": {
    "tgn:hierarchy":[
        "tgn:2605398",
        "tgn:1000001",
        "tgn:7012149",
        "tgn:7029392"
    ],
    "tgn:id":2605398,
    "tgn:name":"Ragsdale Creek",
    "tgn:placetype":[
        "aat:300008706"
    ]
},
  "bbox": [],
  "geometry": {"coordinates":[-86.8833,34.95],"type":"Point"}
}