<<<<<<< HEAD
{
  "id": 2158322,
  "type": "Feature",
  "properties": {
    "tgn:hierarchy":[
        "tgn:2158322",
        "tgn:1000001",
        "tgn:7012149",
        "tgn:7007710",
        "tgn:7029392"
    ],
    "tgn:id":2158322,
    "tgn:name":"Beaver Valley",
    "tgn:placetype":[
        "aat:300008761"
    ]
},
  "bbox": [],
  "geometry": {"coordinates":[-76.2,40.9667],"type":"Point"}
}
=======
{"geometry":{"type":"Point","coordinates":[-76.200000,40.966700]},"type":"Feature","properties":{"hierarchy":["tgn:2158322","tgn:1000001","tgn:7012149","tgn:7007710","tgn:7029392"],"placetype":["aat:300008761"],"id":2158322,"name:xx":"Beaver Valley"}}
>>>>>>> 03f74aca74312dbeaf24d7e61306dd6a786dc3d0
