{
  "id": 2440850,
  "type": "Feature",
  "properties": {
    "tgn:hierarchy":[
        "tgn:2440850",
        "tgn:7006450",
        "tgn:1000001",
        "tgn:7012149",
        "tgn:7029392"
    ],
    "tgn:id":2440850,
    "tgn:name":"Knik River",
    "tgn:placetype":[
        "aat:300008707"
    ]
},
  "bbox": [],
  "geometry": {"coordinates":[-148.6167,61.4167],"type":"Point"}
}