{
  "id": 1022092,
  "type": "Feature",
  "properties": {
    "tgn:hierarchy":[
        "tgn:1022092",
        "tgn:1001942",
        "tgn:1000047",
        "tgn:7002457",
        "tgn:1000002",
        "tgn:7029392"
    ],
    "tgn:id":1022092,
    "tgn:name":"Miguel Couto",
    "tgn:placetype":[
        "aat:300008347"
    ]
},
  "bbox": [],
  "geometry": {"coordinates":[-43.45,-22.7167],"type":"Point"}
}