<<<<<<< HEAD
{
  "id": 7020586,
  "type": "Feature",
  "properties": {
    "tgn:hierarchy":[
        "tgn:7020586",
        "tgn:1000001",
        "tgn:7012149",
        "tgn:2001288",
        "tgn:7007524",
        "tgn:7029392"
    ],
    "tgn:id":7020586,
    "tgn:name":"Sunbeam Mine",
    "tgn:placetype":[
        "aat:300000390"
    ]
},
  "bbox": [],
  "geometry": {"coordinates":[-112.05,45.5167],"type":"Point"}
}
=======
{"geometry":{"type":"Point","coordinates":[-112.050000,45.516700]},"type":"Feature","properties":{"hierarchy":["tgn:7020586","tgn:1000001","tgn:7012149","tgn:2001288","tgn:7007524","tgn:7029392"],"placetype":["aat:300000390"],"id":7020586,"name:xx":"Sunbeam Mine"}}
>>>>>>> 03f74aca74312dbeaf24d7e61306dd6a786dc3d0
