{
  "id": 7272695,
  "type": "Feature",
  "properties": {
    "tgn:hierarchy":[
        "tgn:7272695",
        "tgn:1000003",
        "tgn:7003626",
        "tgn:7016845",
        "tgn:7029392"
    ],
    "tgn:id":7272695,
    "tgn:name:nl":"Vollenhoek",
    "tgn:placetype":[
        "aat:300387200"
    ]
},
  "bbox": [],
  "geometry": {"coordinates":[6.95,52.416667],"type":"Point"}
}