{
  "id": 7576106,
  "type": "Feature",
  "properties": {
    "tgn:hierarchy":[
        "tgn:7576106",
        "tgn:1001828",
        "tgn:1000004",
        "tgn:7000198",
        "tgn:7029392"
    ],
    "tgn:id":7576106,
    "tgn:name:en":"Korosav\u0101da",
    "tgn:placetype":[
        "aat:300008347"
    ]
},
  "bbox": [],
  "geometry": {"coordinates":[84.066667,18.716667],"type":"Point"}
}