{
  "id": 7056689,
  "type": "Feature",
  "properties": {
    "tgn:hierarchy":[
        "tgn:7056689",
        "tgn:1003450",
        "tgn:7007850",
        "tgn:1000003",
        "tgn:1000080",
        "tgn:7029392"
    ],
    "tgn:id":7056689,
    "tgn:name":"Acquaniti, Torrente",
    "tgn:placetype":[
        "aat:300008699"
    ]
},
  "bbox": [],
  "geometry": {"coordinates":[16.85,39.55],"type":"Point"}
}