{
  "id": 7563141,
  "type": "Feature",
  "properties": {
    "tgn:hierarchy":[
        "tgn:7563141",
        "tgn:1000004",
        "tgn:7000198",
        "tgn:7016722",
        "tgn:7029392"
    ],
    "tgn:id":7563141,
    "tgn:name:en":"Geonri",
    "tgn:placetype":[
        "aat:300008347"
    ]
},
  "bbox": [],
  "geometry": {"coordinates":[79.390494,27.807744],"type":"Point"}
}