{
  "id": 2178245,
  "type": "Feature",
  "properties": {
    "tgn:hierarchy":[
        "tgn:2178245",
        "tgn:1000001",
        "tgn:2000924",
        "tgn:7012149",
        "tgn:7007515",
        "tgn:7029392"
    ],
    "tgn:id":2178245,
    "tgn:name":"Blackhorse Island",
    "tgn:placetype":[
        "aat:300008791"
    ]
},
  "bbox": [],
  "geometry": {"coordinates":[-68.5667,44.0167],"type":"Point"}
}