{
  "id": 1096909,
  "type": "Feature",
  "properties": {
    "tgn:hierarchy":[
        "tgn:1096909",
        "tgn:7000490",
        "tgn:1000006",
        "tgn:7001830",
        "tgn:7029392"
    ],
    "tgn:id":1096909,
    "tgn:name":"Forest Hill",
    "tgn:placetype":[
        "aat:300008347"
    ]
},
  "bbox": [],
  "geometry": {"coordinates":[152.3667,-27.5833],"type":"Point"}
}