{
  "id": 7472014,
  "type": "Feature",
  "properties": {
    "tgn:hierarchy":[
        "tgn:7472014",
        "tgn:1000004",
        "tgn:7467799",
        "tgn:1000141",
        "tgn:7029392"
    ],
    "tgn:id":7472014,
    "tgn:name":"Yuancheng Qiao",
    "tgn:placetype":[
        "aat:300007836"
    ]
},
  "bbox": [],
  "geometry": {"coordinates":[120.428918,23.880684],"type":"Point"}
}