<<<<<<< HEAD
{
  "id": 7053519,
  "type": "Feature",
  "properties": {
    "tgn:hierarchy":[
        "tgn:7053519",
        "tgn:1003450",
        "tgn:7007850",
        "tgn:1000003",
        "tgn:1000080",
        "tgn:7029392"
    ],
    "tgn:id":7053519,
    "tgn:name":"Pantanolungo",
    "tgn:placetype":[
        "aat:300008347"
    ]
},
  "bbox": [],
  "geometry": {"coordinates":[16.2,39.233333],"type":"Point"}
}
=======
{"geometry":{"type":"Point","coordinates":[16.200000,39.233333]},"type":"Feature","properties":{"hierarchy":["tgn:7053519","tgn:1003450","tgn:7007850","tgn:1000003","tgn:1000080","tgn:7029392"],"placetype":["aat:300008347"],"id":7053519,"name:xx":"Pantanolungo"}}
>>>>>>> 03f74aca74312dbeaf24d7e61306dd6a786dc3d0
