{
  "id": 2621392,
  "type": "Feature",
  "properties": {
    "tgn:hierarchy":[
        "tgn:2621392",
        "tgn:1000001",
        "tgn:1002724",
        "tgn:7012149",
        "tgn:7007517",
        "tgn:7029392"
    ],
    "tgn:id":2621392,
    "tgn:name":"Roaring Brook Pond",
    "tgn:placetype":[
        "aat:300006191"
    ]
},
  "bbox": [],
  "geometry": {"coordinates":[-71.4333,42.1167],"type":"Point"}
}