<<<<<<< HEAD
{
  "id": 7354571,
  "type": "Feature",
  "properties": {
    "tgn:hierarchy":[
        "tgn:7354571",
        "tgn:1000001",
        "tgn:1001960",
        "tgn:7005560",
        "tgn:7029392"
    ],
    "tgn:id":7354571,
    "tgn:name":"Casita",
    "tgn:placetype":[
        "aat:300008347"
    ]
},
  "bbox": [],
  "geometry": {"coordinates":[-108.85,26.85],"type":"Point"}
}
=======
{"geometry":{"type":"Point","coordinates":[-108.850000,26.850000]},"type":"Feature","properties":{"hierarchy":["tgn:7354571","tgn:1000001","tgn:1001960","tgn:7005560","tgn:7029392"],"placetype":["aat:300008347"],"id":7354571,"name:xx":"Casita"}}
>>>>>>> 03f74aca74312dbeaf24d7e61306dd6a786dc3d0
