{
  "id": 2600501,
  "type": "Feature",
  "properties": {
    "tgn:hierarchy":[
        "tgn:2600501",
        "tgn:1000001",
        "tgn:7012149",
        "tgn:2001871",
        "tgn:7007825",
        "tgn:7029392"
    ],
    "tgn:id":2600501,
    "tgn:name":"Pugh Creek",
    "tgn:placetype":[
        "aat:300008706"
    ]
},
  "bbox": [],
  "geometry": {"coordinates":[-88.9167,35.35],"type":"Point"}
}