{
  "id": 1058687,
  "type": "Feature",
  "properties": {
    "tgn:hierarchy":[
        "tgn:1058687",
        "tgn:1000004",
        "tgn:7011566",
        "tgn:7018214",
        "tgn:7002435",
        "tgn:7029392"
    ],
    "tgn:id":1058687,
    "tgn:name":"Privolzhsk",
    "tgn:placetype":[
        "aat:300008347"
    ]
},
  "bbox": [],
  "geometry": {"coordinates":[41.3333,57.35],"type":"Point"}
}