{
  "id": 2576889,
  "type": "Feature",
  "properties": {
    "tgn:hierarchy":[
        "tgn:2576889",
        "tgn:1000001",
        "tgn:7012149",
        "tgn:2000476",
        "tgn:7007250",
        "tgn:7029392"
    ],
    "tgn:id":2576889,
    "tgn:name":"Pete Creek",
    "tgn:placetype":[
        "aat:300008706"
    ]
},
  "bbox": [],
  "geometry": {"coordinates":[-115.9667,45.2833],"type":"Point"}
}