{
  "id": 2485292,
  "type": "Feature",
  "properties": {
    "tgn:hierarchy":[
        "tgn:2485292",
        "tgn:1000001",
        "tgn:7012149",
        "tgn:1002580",
        "tgn:7007710",
        "tgn:7029392"
    ],
    "tgn:id":2485292,
    "tgn:name":"Lawrence Junction",
    "tgn:placetype":[
        "aat:300008347"
    ]
},
  "bbox": [],
  "geometry": {"coordinates":[-80.3667,40.9667],"type":"Point"}
}