{
  "id": 1114056,
  "type": "Feature",
  "properties": {
    "tgn:hierarchy":[
        "tgn:1114056",
        "tgn:7000897",
        "tgn:1001040",
        "tgn:1000004",
        "tgn:1000120",
        "tgn:7029392"
    ],
    "tgn:id":1114056,
    "tgn:name":"Yuya-wan",
    "tgn:placetype":[
        "aat:300132316"
    ]
},
  "bbox": [],
  "geometry": {"coordinates":[130.9167,34.4167],"type":"Point"}
}