{
  "id": 2780777,
  "type": "Feature",
  "properties": {
    "tgn:hierarchy":[
        "tgn:2780777",
        "tgn:1000001",
        "tgn:7012149",
        "tgn:2001303",
        "tgn:7007524",
        "tgn:7029392"
    ],
    "tgn:id":2780777,
    "tgn:name":"Wood Spring",
    "tgn:placetype":[
        "aat:300008697"
    ]
},
  "bbox": [],
  "geometry": {"coordinates":[-106.6167,45.6667],"type":"Point"}
}