{
  "id": 2570217,
  "type": "Feature",
  "properties": {
    "tgn:hierarchy":[
        "tgn:2570217",
        "tgn:1000001",
        "tgn:7012149",
        "tgn:7007158",
        "tgn:7029392"
    ],
    "tgn:id":2570217,
    "tgn:name":"Pasture Creek",
    "tgn:placetype":[
        "aat:300008706"
    ]
},
  "bbox": [],
  "geometry": {"coordinates":[-107.85,37.65],"type":"Point"}
}