{
  "id": 7557032,
  "type": "Feature",
  "properties": {
    "tgn:hierarchy":[
        "tgn:7557032",
        "tgn:1000004",
        "tgn:7000198",
        "tgn:1001894",
        "tgn:7029392"
    ],
    "tgn:id":7557032,
    "tgn:name:en":"Sesaipura",
    "tgn:placetype":[
        "aat:300008347"
    ]
},
  "bbox": [],
  "geometry": {"coordinates":[77.178035,25.541535],"type":"Point"}
}