{
  "id": 7373581,
  "type": "Feature",
  "properties": {
    "tgn:hierarchy":[
        "tgn:7373581",
        "tgn:1000001",
        "tgn:7005597",
        "tgn:7005560",
        "tgn:7029392"
    ],
    "tgn:id":7373581,
    "tgn:name":"La Gloria",
    "tgn:placetype":[
        "aat:300008347"
    ]
},
  "bbox": [],
  "geometry": {"coordinates":[-99.466667,23.316667],"type":"Point"}
}