{
  "id": 7493582,
  "type": "Feature",
  "properties": {
    "tgn:hierarchy":[
        "tgn:7493582",
        "tgn:1000004",
        "tgn:7491221",
        "tgn:1000141",
        "tgn:7029392"
    ],
    "tgn:id":7493582,
    "tgn:name":"Duwei Xi",
    "tgn:placetype":[
        "aat:300008699"
    ]
},
  "bbox": [],
  "geometry": {"coordinates":[121.397065,23.189467],"type":"Point"}
}