{
  "id": 2745152,
  "type": "Feature",
  "properties": {
    "tgn:hierarchy":[
        "tgn:2745152",
        "tgn:7019618",
        "tgn:1000001",
        "tgn:7012149",
        "tgn:7007564",
        "tgn:7029392"
    ],
    "tgn:id":2745152,
    "tgn:name":"Village Pond",
    "tgn:placetype":[
        "aat:300006191"
    ]
},
  "bbox": [],
  "geometry": {"coordinates":[-72.1833,43.1167],"type":"Point"}
}