{
  "id": 2712516,
  "type": "Feature",
  "properties": {
    "tgn:hierarchy":[
        "tgn:2712516",
        "tgn:1000001",
        "tgn:7012149",
        "tgn:1002678",
        "tgn:7007252",
        "tgn:7029392"
    ],
    "tgn:id":2712516,
    "tgn:name":"Taylor Branch",
    "tgn:placetype":[
        "aat:300008699"
    ]
},
  "bbox": [],
  "geometry": {"coordinates":[-86.3167,39.0167],"type":"Point"}
}