<<<<<<< HEAD
{
  "id": 7119969,
  "type": "Feature",
  "properties": {
    "tgn:hierarchy":[
        "tgn:7119969",
        "tgn:7003669",
        "tgn:1000003",
        "tgn:7000084",
        "tgn:7029392"
    ],
    "tgn:id":7119969,
    "tgn:name":"Plosau",
    "tgn:placetype":[
        "aat:300000206"
    ]
},
  "bbox": [],
  "geometry": {"coordinates":[12.7,47.933333],"type":"Point"}
}
=======
{"geometry":{"type":"Point","coordinates":[12.700000,47.933333]},"type":"Feature","properties":{"hierarchy":["tgn:7119969","tgn:7003669","tgn:1000003","tgn:7000084","tgn:7029392"],"placetype":["aat:300000206"],"id":7119969,"name:xx":"Plosau"}}
>>>>>>> 03f74aca74312dbeaf24d7e61306dd6a786dc3d0
