{
  "id": 7226945,
  "type": "Feature",
  "properties": {
    "tgn:hierarchy":[
        "tgn:7226945",
        "tgn:7002681",
        "tgn:7001395",
        "tgn:1000003",
        "tgn:1000074",
        "tgn:7029392"
    ],
    "tgn:id":7226945,
    "tgn:name":"Po\u00farnos",
    "tgn:placetype":[
        "aat:300008347"
    ]
},
  "bbox": [],
  "geometry": {"coordinates":[23.783333,38.516667],"type":"Point"}
}