{
  "id": 7512862,
  "type": "Feature",
  "properties": {
    "tgn:hierarchy":[
        "tgn:7512862",
        "tgn:1009227",
        "tgn:1000226",
        "tgn:7016822",
        "tgn:1000006",
        "tgn:7029392"
    ],
    "tgn:id":7512862,
    "tgn:name:en":"Hazelburgh Group",
    "tgn:placetype":[
        "aat:300008791"
    ]
},
  "bbox": [],
  "geometry": {"coordinates":[168.466667,-46.816667],"type":"Point"}
}