{
  "id": 2551773,
  "type": "Feature",
  "properties": {
    "tgn:hierarchy":[
        "tgn:2551773",
        "tgn:1000001",
        "tgn:7012149",
        "tgn:2000793",
        "tgn:7007255",
        "tgn:7029392"
    ],
    "tgn:id":2551773,
    "tgn:name":"Number 6, Lake",
    "tgn:placetype":[
        "aat:300006191"
    ]
},
  "bbox": [],
  "geometry": {"coordinates":[-86.4833,37.4333],"type":"Point"}
}