{
  "id": 7030066,
  "type": "Feature",
  "properties": {
    "tgn:hierarchy":[
        "tgn:7030066",
        "tgn:7002445",
        "tgn:1000003",
        "tgn:7019064",
        "tgn:7008591",
        "tgn:7029392"
    ],
    "tgn:id":7030066,
    "tgn:name":"Knapton",
    "tgn:name:ang":"Cnapetone",
    "tgn:placetype":[
        "aat:300008347",
        "aat:300008372"
    ]
},
  "bbox": [],
  "geometry": {"coordinates":[-1.135,53.952],"type":"Point"}
}