<<<<<<< HEAD
{
  "id": 2767007,
  "type": "Feature",
  "properties": {
    "tgn:hierarchy":[
        "tgn:2767007",
        "tgn:1000001",
        "tgn:2001414",
        "tgn:7012149",
        "tgn:7007526",
        "tgn:7029392"
    ],
    "tgn:id":2767007,
    "tgn:name":"White Ridge",
    "tgn:placetype":[
        "aat:300266640"
    ]
},
  "bbox": [],
  "geometry": {"coordinates":[-117.1833,41.5833],"type":"Point"}
}
=======
{"geometry":{"type":"Point","coordinates":[-117.183300,41.583300]},"type":"Feature","properties":{"hierarchy":["tgn:2767007","tgn:1000001","tgn:2001414","tgn:7012149","tgn:7007526","tgn:7029392"],"placetype":["aat:300266640"],"id":2767007,"name:xx":"White Ridge"}}
>>>>>>> 03f74aca74312dbeaf24d7e61306dd6a786dc3d0
