{
  "id": 2756928,
  "type": "Feature",
  "properties": {
    "tgn:hierarchy":[
        "tgn:2756928",
        "tgn:1000001",
        "tgn:7012149",
        "tgn:1003042",
        "tgn:7007920",
        "tgn:7029392"
    ],
    "tgn:id":2756928,
    "tgn:name":"Wenas",
    "tgn:placetype":[
        "aat:300008347"
    ]
},
  "bbox": [],
  "geometry": {"coordinates":[-120.7667,46.8667],"type":"Point"}
}