<<<<<<< HEAD
{
  "id": 7482864,
  "type": "Feature",
  "properties": {
    "tgn:hierarchy":[
        "tgn:7482864",
        "tgn:1000004",
        "tgn:7001009",
        "tgn:1000141",
        "tgn:7029392"
    ],
    "tgn:id":7482864,
    "tgn:name":"Qinghai Guozhong",
    "tgn:placetype":[
        "aat:300006495"
    ]
},
  "bbox": [],
  "geometry": {"coordinates":[120.551111,24.276389],"type":"Point"}
}
=======
{"geometry":{"type":"Point","coordinates":[120.551111,24.276389]},"type":"Feature","properties":{"hierarchy":["tgn:7482864","tgn:1000004","tgn:7001009","tgn:1000141","tgn:7029392"],"placetype":["aat:300006495"],"id":7482864,"name:xx":"Qinghai Guozhong"}}
>>>>>>> 03f74aca74312dbeaf24d7e61306dd6a786dc3d0
