{
  "id": 2355118,
  "type": "Feature",
  "properties": {
    "tgn:hierarchy":[
        "tgn:2355118",
        "tgn:1000001",
        "tgn:7012149",
        "tgn:7007157",
        "tgn:2000184",
        "tgn:7029392"
    ],
    "tgn:id":2355118,
    "tgn:name":"Goodrich Mountain",
    "tgn:placetype":[
        "aat:300008798"
    ]
},
  "bbox": [],
  "geometry": {"coordinates":[-120.95,40.3167],"type":"Point"}
}