{
  "id": 7286840,
  "type": "Feature",
  "properties": {
    "tgn:hierarchy":[
        "tgn:7286840",
        "tgn:7002464",
        "tgn:1000049",
        "tgn:1000002",
        "tgn:7029392"
    ],
    "tgn:id":7286840,
    "tgn:name":"Guaneras, Punta",
    "tgn:placetype":[
        "aat:300386846"
    ]
},
  "bbox": [],
  "geometry": {"coordinates":[-70.15,-19.966667],"type":"Point"}
}