<<<<<<< HEAD
{
  "id": 2330811,
  "type": "Feature",
  "properties": {
    "tgn:hierarchy":[
        "tgn:2330811",
        "tgn:1000001",
        "tgn:7012149",
        "tgn:2001461",
        "tgn:7007568",
        "tgn:7029392"
    ],
    "tgn:id":2330811,
    "tgn:name":"Flat Mountain",
    "tgn:placetype":[
        "aat:300008798"
    ]
},
  "bbox": [],
  "geometry": {"coordinates":[-73.7333,44.2],"type":"Point"}
}
=======
{"geometry":{"type":"Point","coordinates":[-73.733300,44.200000]},"type":"Feature","properties":{"hierarchy":["tgn:2330811","tgn:1000001","tgn:7012149","tgn:2001461","tgn:7007568","tgn:7029392"],"placetype":["aat:300008798"],"id":2330811,"name:xx":"Flat Mountain"}}
>>>>>>> 03f74aca74312dbeaf24d7e61306dd6a786dc3d0
