{
  "id": 2231362,
  "type": "Feature",
  "properties": {
    "tgn:hierarchy":[
        "tgn:2231362",
        "tgn:1000001",
        "tgn:7012149",
        "tgn:7016021",
        "tgn:7007568",
        "tgn:7029392"
    ],
    "tgn:id":2231362,
    "tgn:name":"Chair Rock Creek",
    "tgn:placetype":[
        "aat:300008706"
    ]
},
  "bbox": [],
  "geometry": {"coordinates":[-74.7833,44.0833],"type":"Point"}
}