{
  "id": 7497669,
  "type": "Feature",
  "properties": {
    "tgn:hierarchy":[
        "tgn:7497669",
        "tgn:7001004",
        "tgn:1000004",
        "tgn:1000141",
        "tgn:7029392"
    ],
    "tgn:id":7497669,
    "tgn:name":"Piziwei",
    "tgn:placetype":[
        "aat:300008347"
    ]
},
  "bbox": [],
  "geometry": {"coordinates":[120.415339,22.657335],"type":"Point"}
}