{
  "id": 7043368,
  "type": "Feature",
  "properties": {
    "tgn:hierarchy":[
        "tgn:7043368",
        "tgn:7003011",
        "tgn:7003005",
        "tgn:1000003",
        "tgn:1000080",
        "tgn:7029392"
    ],
    "tgn:id":7043368,
    "tgn:name":"Puglianello",
    "tgn:placetype":[
        "aat:300008347"
    ]
},
  "bbox": [],
  "geometry": {"coordinates":[14.45,41.216667],"type":"Point"}
}