{
  "id": 2683238,
  "type": "Feature",
  "properties": {
    "tgn:hierarchy":[
        "tgn:2683238",
        "tgn:7013313",
        "tgn:1000001",
        "tgn:7012149",
        "tgn:7007826",
        "tgn:7029392"
    ],
    "tgn:id":2683238,
    "tgn:name":"Spanish Village",
    "tgn:placetype":[
        "aat:300008347"
    ]
},
  "bbox": [],
  "geometry": {"coordinates":[-96.8667,28.2667],"type":"Point"}
}