<<<<<<< HEAD
{
  "id": 7352905,
  "type": "Feature",
  "properties": {
    "tgn:hierarchy":[
        "tgn:7352905",
        "tgn:1000001",
        "tgn:7005592",
        "tgn:7005560",
        "tgn:7029392"
    ],
    "tgn:id":7352905,
    "tgn:name":"Atlaxco",
    "tgn:placetype":[
        "aat:300008347"
    ]
},
  "bbox": [],
  "geometry": {"coordinates":[-97.066667,19.183333],"type":"Point"}
}
=======
{"geometry":{"type":"Point","coordinates":[-97.066667,19.183333]},"type":"Feature","properties":{"hierarchy":["tgn:7352905","tgn:1000001","tgn:7005592","tgn:7005560","tgn:7029392"],"placetype":["aat:300008347"],"id":7352905,"name:xx":"Atlaxco"}}
>>>>>>> 03f74aca74312dbeaf24d7e61306dd6a786dc3d0
