<<<<<<< HEAD
{
  "id": 7023434,
  "type": "Feature",
  "properties": {
    "tgn:hierarchy":[
        "tgn:7023434",
        "tgn:1000001",
        "tgn:7012149",
        "tgn:7029392"
    ],
    "tgn:id":7023434,
    "tgn:name":"Mingo Branch",
    "tgn:placetype":[
        "aat:300008699"
    ]
},
  "bbox": [],
  "geometry": {"coordinates":[-88.15,34.6167],"type":"Point"}
}
=======
{"geometry":{"type":"Point","coordinates":[-88.150000,34.616700]},"type":"Feature","properties":{"hierarchy":["tgn:7023434","tgn:1000001","tgn:7012149","tgn:7029392"],"placetype":["aat:300008699"],"id":7023434,"name:xx":"Mingo Branch"}}
>>>>>>> 03f74aca74312dbeaf24d7e61306dd6a786dc3d0
