{
  "id": 7023434,
  "type": "Feature",
  "properties": {
    "tgn:hierarchy":[
        "tgn:7023434",
        "tgn:1000001",
        "tgn:7012149",
        "tgn:7029392"
    ],
    "tgn:id":7023434,
    "tgn:name":"Mingo Branch",
    "tgn:placetype":[
        "aat:300008699"
    ]
},
  "bbox": [],
  "geometry": {"coordinates":[-88.15,34.6167],"type":"Point"}
}