{
  "id": 2396597,
  "type": "Feature",
  "properties": {
    "tgn:hierarchy":[
        "tgn:2396597",
        "tgn:1000001",
        "tgn:7012149",
        "tgn:1002625",
        "tgn:7007706",
        "tgn:7029392"
    ],
    "tgn:id":2396597,
    "tgn:name":"Holton Ditch",
    "tgn:placetype":[
        "aat:300006075"
    ]
},
  "bbox": [],
  "geometry": {"coordinates":[-83.4167,40.0833],"type":"Point"}
}