{
  "id": 7271132,
  "type": "Feature",
  "properties": {
    "tgn:hierarchy":[
        "tgn:7271132",
        "tgn:1000003",
        "tgn:7003613",
        "tgn:7016845",
        "tgn:7029392"
    ],
    "tgn:id":7271132,
    "tgn:name:nl":"Stadspolder",
    "tgn:placetype":[
        "aat:300006163"
    ]
},
  "bbox": [],
  "geometry": {"coordinates":[7.183333,53.216667],"type":"Point"}
}