<<<<<<< HEAD
{
  "id": 2336020,
  "type": "Feature",
  "properties": {
    "tgn:hierarchy":[
        "tgn:2336020",
        "tgn:1000001",
        "tgn:7012149",
        "tgn:1002971",
        "tgn:7007710",
        "tgn:7029392"
    ],
    "tgn:id":2336020,
    "tgn:name":"Foster Corner",
    "tgn:placetype":[
        "aat:300008347"
    ]
},
  "bbox": [],
  "geometry": {"coordinates":[-79.85,41.4],"type":"Point"}
}
=======
{"geometry":{"type":"Point","coordinates":[-79.850000,41.400000]},"type":"Feature","properties":{"hierarchy":["tgn:2336020","tgn:1000001","tgn:7012149","tgn:1002971","tgn:7007710","tgn:7029392"],"placetype":["aat:300008347"],"id":2336020,"name:xx":"Foster Corner"}}
>>>>>>> 03f74aca74312dbeaf24d7e61306dd6a786dc3d0
