<<<<<<< HEAD
{
  "id": 2338190,
  "type": "Feature",
  "properties": {
    "tgn:hierarchy":[
        "tgn:2338190",
        "tgn:1000001",
        "tgn:7012149",
        "tgn:1002440",
        "tgn:7007568",
        "tgn:7029392"
    ],
    "tgn:id":2338190,
    "tgn:name":"Fox Pond",
    "tgn:placetype":[
        "aat:300008680"
    ]
},
  "bbox": [],
  "geometry": {"coordinates":[-74.65,43.8],"type":"Point"}
}
=======
{"geometry":{"type":"Point","coordinates":[-74.650000,43.800000]},"type":"Feature","properties":{"hierarchy":["tgn:2338190","tgn:1000001","tgn:7012149","tgn:1002440","tgn:7007568","tgn:7029392"],"placetype":["aat:300008680"],"id":2338190,"name:xx":"Fox Pond"}}
>>>>>>> 03f74aca74312dbeaf24d7e61306dd6a786dc3d0
