{
  "id": 2054100,
  "type": "Feature",
  "properties": {
    "tgn:hierarchy":[
        "tgn:2054100",
        "tgn:1000001",
        "tgn:7012149",
        "tgn:2001080",
        "tgn:7007521",
        "tgn:7029392"
    ],
    "tgn:id":2054100,
    "tgn:name":"Carnelian Junction",
    "tgn:placetype":[
        "aat:300387016"
    ]
},
  "bbox": [],
  "geometry": {"coordinates":[-92.8167,45.1167],"type":"Point"}
}