{
  "id": 2489127,
  "type": "Feature",
  "properties": {
    "tgn:hierarchy":[
        "tgn:2489127",
        "tgn:2000196",
        "tgn:1000001",
        "tgn:7012149",
        "tgn:7007158",
        "tgn:7029392"
    ],
    "tgn:id":2489127,
    "tgn:name":"Major Spring",
    "tgn:placetype":[
        "aat:300008697"
    ]
},
  "bbox": [],
  "geometry": {"coordinates":[-102.9167,37.0667],"type":"Point"}
}