<<<<<<< HEAD
{
  "id": 7472040,
  "type": "Feature",
  "properties": {
    "tgn:hierarchy":[
        "tgn:7472040",
        "tgn:1000004",
        "tgn:7467799",
        "tgn:1000141",
        "tgn:7029392"
    ],
    "tgn:id":7472040,
    "tgn:name":"Xiqiancuo",
    "tgn:placetype":[
        "aat:300008347"
    ]
},
  "bbox": [],
  "geometry": {"coordinates":[120.480297,23.845728],"type":"Point"}
}
=======
{"geometry":{"type":"Point","coordinates":[120.480297,23.845728]},"type":"Feature","properties":{"hierarchy":["tgn:7472040","tgn:1000004","tgn:7467799","tgn:1000141","tgn:7029392"],"placetype":["aat:300008347"],"id":7472040,"name:xx":"Xiqiancuo"}}
>>>>>>> 03f74aca74312dbeaf24d7e61306dd6a786dc3d0
