{
  "id": 7472040,
  "type": "Feature",
  "properties": {
    "tgn:hierarchy":[
        "tgn:7472040",
        "tgn:1000004",
        "tgn:7467799",
        "tgn:1000141",
        "tgn:7029392"
    ],
    "tgn:id":7472040,
    "tgn:name":"Xiqiancuo",
    "tgn:placetype":[
        "aat:300008347"
    ]
},
  "bbox": [],
  "geometry": {"coordinates":[120.480297,23.845728],"type":"Point"}
}