{
  "id": 2647644,
  "type": "Feature",
  "properties": {
    "tgn:hierarchy":[
        "tgn:2647644",
        "tgn:1000001",
        "tgn:1002601",
        "tgn:7012149",
        "tgn:7007159",
        "tgn:7029392"
    ],
    "tgn:id":2647644,
    "tgn:name":"School Hill",
    "tgn:placetype":[
        "aat:300008798"
    ]
},
  "bbox": [],
  "geometry": {"coordinates":[-73.25,41.8333],"type":"Point"}
}