<<<<<<< HEAD
{
  "id": 7052404,
  "type": "Feature",
  "properties": {
    "tgn:hierarchy":[
        "tgn:7052404",
        "tgn:7003007",
        "tgn:1000003",
        "tgn:7002997",
        "tgn:1000080",
        "tgn:7029392"
    ],
    "tgn:id":7052404,
    "tgn:name":"Monzambano",
    "tgn:placetype":[
        "aat:300008347"
    ]
},
  "bbox": [],
  "geometry": {"coordinates":[10.683333,45.383333],"type":"Point"}
}
=======
{"geometry":{"type":"Point","coordinates":[10.683333,45.383333]},"type":"Feature","properties":{"hierarchy":["tgn:7052404","tgn:7003007","tgn:1000003","tgn:7002997","tgn:1000080","tgn:7029392"],"placetype":["aat:300008347"],"id":7052404,"name:xx":"Monzambano"}}
>>>>>>> 03f74aca74312dbeaf24d7e61306dd6a786dc3d0
