<<<<<<< HEAD
{
  "id": 2408763,
  "type": "Feature",
  "properties": {
    "tgn:hierarchy":[
        "tgn:2408763",
        "tgn:1000001",
        "tgn:7012149",
        "tgn:1002352",
        "tgn:7007710",
        "tgn:7029392"
    ],
    "tgn:id":2408763,
    "tgn:name":"Hyde Lake",
    "tgn:placetype":[
        "aat:300008680"
    ]
},
  "bbox": [],
  "geometry": {"coordinates":[-78.7333,41.3333],"type":"Point"}
}
=======
{"geometry":{"type":"Point","coordinates":[-78.733300,41.333300]},"type":"Feature","properties":{"hierarchy":["tgn:2408763","tgn:1000001","tgn:7012149","tgn:1002352","tgn:7007710","tgn:7029392"],"placetype":["aat:300008680"],"id":2408763,"name:xx":"Hyde Lake"}}
>>>>>>> 03f74aca74312dbeaf24d7e61306dd6a786dc3d0
