{
  "id": 2697054,
  "type": "Feature",
  "properties": {
    "tgn:hierarchy":[
        "tgn:2697054",
        "tgn:1000001",
        "tgn:7012149",
        "tgn:2001209",
        "tgn:7007523",
        "tgn:7029392"
    ],
    "tgn:id":2697054,
    "tgn:name":"Stony Branch",
    "tgn:placetype":[
        "aat:300008699"
    ]
},
  "bbox": [],
  "geometry": {"coordinates":[-94.1167,37.2833],"type":"Point"}
}