{
  "id": 7267629,
  "type": "Feature",
  "properties": {
    "tgn:concordances":{
        "gn:id":"2748828"
    },
    "tgn:hierarchy":[
        "tgn:7267629",
        "tgn:1000003",
        "tgn:7006951",
        "tgn:7016845",
        "tgn:7029392"
    ],
    "tgn:id":7267629,
    "tgn:name:nl":"Overmeer",
    "tgn:placetype":[
        "aat:300008347"
    ]
},
  "bbox": [],
  "geometry": {"coordinates":[5.05,52.25],"type":"Point"}
}