{
  "id": 2601628,
  "type": "Feature",
  "properties": {
    "tgn:hierarchy":[
        "tgn:2601628",
        "tgn:7030516",
        "tgn:7006450",
        "tgn:1000001",
        "tgn:7012149",
        "tgn:7029392"
    ],
    "tgn:id":2601628,
    "tgn:name":"Pustoi Island",
    "tgn:placetype":[
        "aat:300008791"
    ]
},
  "bbox": [],
  "geometry": {"coordinates":[-167.8167,53.3833],"type":"Point"}
}