<<<<<<< HEAD
{
  "id": 7350782,
  "type": "Feature",
  "properties": {
    "tgn:hierarchy":[
        "tgn:7350782",
        "tgn:1001836",
        "tgn:1000001",
        "tgn:7005560",
        "tgn:7029392"
    ],
    "tgn:id":7350782,
    "tgn:name":"Baja, Punta",
    "tgn:placetype":[
        "aat:300386846"
    ]
},
  "bbox": [],
  "geometry": {"coordinates":[-111.202778,25.801667],"type":"Point"}
}
=======
{"geometry":{"type":"Point","coordinates":[-111.202778,25.801667]},"type":"Feature","properties":{"hierarchy":["tgn:7350782","tgn:1001836","tgn:1000001","tgn:7005560","tgn:7029392"],"placetype":["aat:300386846"],"id":7350782,"name:xx":"Baja, Punta"}}
>>>>>>> 03f74aca74312dbeaf24d7e61306dd6a786dc3d0
