{
  "id": 7030028,
  "type": "Feature",
  "properties": {
    "tgn:hierarchy":[
        "tgn:7030028",
        "tgn:1003611",
        "tgn:7002445",
        "tgn:1000003",
        "tgn:7029507",
        "tgn:7008591",
        "tgn:7029392"
    ],
    "tgn:id":7030028,
    "tgn:name":"Hepworth",
    "tgn:placetype":[
        "aat:300008347",
        "aat:300008372"
    ]
},
  "bbox": [],
  "geometry": {"coordinates":[-1.75,53.55],"type":"Point"}
}