{
  "id": 7333979,
  "type": "Feature",
  "properties": {
    "tgn:hierarchy":[
        "tgn:7333979",
        "tgn:7002758",
        "tgn:7002817",
        "tgn:1000003",
        "tgn:1000095",
        "tgn:7029392"
    ],
    "tgn:id":7333979,
    "tgn:name":"Encinas Reales",
    "tgn:placetype":[
        "aat:300008347"
    ]
},
  "bbox": [],
  "geometry": {"coordinates":[-4.483333,37.283333],"type":"Point"}
}