{
  "id": 2736306,
  "type": "Feature",
  "properties": {
    "tgn:hierarchy":[
        "tgn:2736306",
        "tgn:1000001",
        "tgn:7012149",
        "tgn:7007157",
        "tgn:1002858",
        "tgn:7029392"
    ],
    "tgn:id":2736306,
    "tgn:name":"Twin Peaks",
    "tgn:placetype":[
        "aat:300008798"
    ]
},
  "bbox": [],
  "geometry": {"coordinates":[-117.0333,32.9833],"type":"Point"}
}