<<<<<<< HEAD
{
  "id": 7483794,
  "type": "Feature",
  "properties": {
    "tgn:hierarchy":[
        "tgn:7483794",
        "tgn:7001004",
        "tgn:1000004",
        "tgn:1000141",
        "tgn:7029392"
    ],
    "tgn:id":7483794,
    "tgn:name":"Dibahao Qiao",
    "tgn:placetype":[
        "aat:300007836"
    ]
},
  "bbox": [],
  "geometry": {"coordinates":[120.641111,23.155],"type":"Point"}
}
=======
{"geometry":{"type":"Point","coordinates":[120.641111,23.155000]},"type":"Feature","properties":{"hierarchy":["tgn:7483794","tgn:7001004","tgn:1000004","tgn:1000141","tgn:7029392"],"placetype":["aat:300007836"],"id":7483794,"name:xx":"Dibahao Qiao"}}
>>>>>>> 03f74aca74312dbeaf24d7e61306dd6a786dc3d0
