{
  "id": 2577401,
  "type": "Feature",
  "properties": {
    "tgn:hierarchy":[
        "tgn:2577401",
        "tgn:1000001",
        "tgn:7012149",
        "tgn:1002659",
        "tgn:7007710",
        "tgn:7029392"
    ],
    "tgn:id":2577401,
    "tgn:name":"Petersburg",
    "tgn:placetype":[
        "aat:300008347"
    ]
},
  "bbox": [],
  "geometry": {"coordinates":[-80.25,41.4333],"type":"Point"}
}