{
  "id": 7387891,
  "type": "Feature",
  "properties": {
    "tgn:hierarchy":[
        "tgn:7387891",
        "tgn:1000001",
        "tgn:7005595",
        "tgn:7005560",
        "tgn:7029392"
    ],
    "tgn:id":7387891,
    "tgn:name":"Potrerillo, Arroyo",
    "tgn:placetype":[
        "aat:300008699"
    ]
},
  "bbox": [],
  "geometry": {"coordinates":[-107.366667,25.233333],"type":"Point"}
}