{
  "id": 2105942,
  "type": "Feature",
  "properties": {
    "tgn:hierarchy":[
        "tgn:2105942",
        "tgn:1000001",
        "tgn:7012149",
        "tgn:2002048",
        "tgn:7007826",
        "tgn:7029392"
    ],
    "tgn:id":2105942,
    "tgn:name":"Maryneal",
    "tgn:placetype":[
        "aat:300008347"
    ]
},
  "bbox": [],
  "geometry": {"coordinates":[-100.45,32.2333],"type":"Point"}
}