{
  "id": 7319092,
  "type": "Feature",
  "properties": {
    "tgn:hierarchy":[
        "tgn:7319092",
        "tgn:1001699",
        "tgn:1000049",
        "tgn:1000002",
        "tgn:7029392"
    ],
    "tgn:id":7319092,
    "tgn:name":"Lelb\u00fan, Punta",
    "tgn:placetype":[
        "aat:300386846"
    ]
},
  "bbox": [],
  "geometry": {"coordinates":[-73.523889,-42.6625],"type":"Point"}
}