{
  "id": 2703645,
  "type": "Feature",
  "properties": {
    "tgn:hierarchy":[
        "tgn:2703645",
        "tgn:7014201",
        "tgn:1000001",
        "tgn:7012149",
        "tgn:7007239",
        "tgn:7029392"
    ],
    "tgn:id":2703645,
    "tgn:name":"Summit View",
    "tgn:placetype":[
        "aat:300008347"
    ]
},
  "bbox": [],
  "geometry": {"coordinates":[-75.7667,39.6333],"type":"Point"}
}