{
  "id": 2421608,
  "type": "Feature",
  "properties": {
    "tgn:hierarchy":[
        "tgn:2421608",
        "tgn:1000001",
        "tgn:7012149",
        "tgn:2001750",
        "tgn:7007712",
        "tgn:7029392"
    ],
    "tgn:id":2421608,
    "tgn:name":"Jet Branch",
    "tgn:placetype":[
        "aat:300008699"
    ]
},
  "bbox": [],
  "geometry": {"coordinates":[-79.1167,34.15],"type":"Point"}
}