{
  "id": 7519232,
  "type": "Feature",
  "properties": {
    "tgn:hierarchy":[
        "tgn:7519232",
        "tgn:1009227",
        "tgn:1000226",
        "tgn:7018437",
        "tgn:1000006",
        "tgn:7029392"
    ],
    "tgn:id":7519232,
    "tgn:name:en":"Broad Stream",
    "tgn:placetype":[
        "aat:300008699"
    ]
},
  "bbox": [],
  "geometry": {"coordinates":[170.083333,-45.783333],"type":"Point"}
}