{
  "id": 1014872,
  "type": "Feature",
  "properties": {
    "tgn:hierarchy":[
        "tgn:1014872",
        "tgn:7005685",
        "tgn:1000001",
        "tgn:7013154",
        "tgn:7013251",
        "tgn:7029392"
    ],
    "tgn:id":1014872,
    "tgn:name":"Langstaff",
    "tgn:placetype":[
        "aat:300008347"
    ]
},
  "bbox": [],
  "geometry": {"coordinates":[-79.4167,43.8333],"type":"Point"}
}