{
  "id": 7205437,
  "type": "Feature",
  "properties": {
    "tgn:hierarchy":[
        "tgn:7205437",
        "tgn:1000003",
        "tgn:7000094",
        "tgn:7000084",
        "tgn:7029392"
    ],
    "tgn:id":7205437,
    "tgn:name":"Damerow",
    "tgn:placetype":[
        "aat:300000206"
    ]
},
  "bbox": [],
  "geometry": {"coordinates":[12.083333,54.066667],"type":"Point"}
}