<<<<<<< HEAD
{
  "id": 7475702,
  "type": "Feature",
  "properties": {
    "tgn:hierarchy":[
        "tgn:7475702",
        "tgn:7487020",
        "tgn:1000004",
        "tgn:1000141",
        "tgn:7029392"
    ],
    "tgn:id":7475702,
    "tgn:name":"Jiufenliao",
    "tgn:placetype":[
        "aat:300008347"
    ]
},
  "bbox": [],
  "geometry": {"coordinates":[120.9387,24.6354],"type":"Point"}
}
=======
{"geometry":{"type":"Point","coordinates":[120.938700,24.635400]},"type":"Feature","properties":{"hierarchy":["tgn:7475702","tgn:7487020","tgn:1000004","tgn:1000141","tgn:7029392"],"placetype":["aat:300008347"],"id":7475702,"name:xx":"Jiufenliao"}}
>>>>>>> 03f74aca74312dbeaf24d7e61306dd6a786dc3d0
