{
  "id": 2706213,
  "type": "Feature",
  "properties": {
    "tgn:hierarchy":[
        "tgn:2706213",
        "tgn:1000001",
        "tgn:7012149",
        "tgn:7020792",
        "tgn:7007524",
        "tgn:7029392"
    ],
    "tgn:id":2706213,
    "tgn:name":"Swamp Creek",
    "tgn:placetype":[
        "aat:300008706"
    ]
},
  "bbox": [],
  "geometry": {"coordinates":[-113.3333,45.9333],"type":"Point"}
}