{
  "id": 2717823,
  "type": "Feature",
  "properties": {
    "tgn:hierarchy":[
        "tgn:2717823",
        "tgn:7002659",
        "tgn:1000001",
        "tgn:7012149",
        "tgn:2000065",
        "tgn:7029392"
    ],
    "tgn:id":2717823,
    "tgn:name":"Thomas Norris Pond",
    "tgn:placetype":[
        "aat:300006191"
    ]
},
  "bbox": [],
  "geometry": {"coordinates":[-86.9667,32.0333],"type":"Point"}
}