{
  "id": 2409191,
  "type": "Feature",
  "properties": {
    "tgn:hierarchy":[
        "tgn:2409191",
        "tgn:1000001",
        "tgn:7012149",
        "tgn:7007157",
        "tgn:2000189",
        "tgn:7029392"
    ],
    "tgn:id":2409191,
    "tgn:name":"Ice River Caves",
    "tgn:placetype":[
        "aat:300008746"
    ]
},
  "bbox": [],
  "geometry": {"coordinates":[-121.6667,41.3833],"type":"Point"}
}