{
  "id": 7469649,
  "type": "Feature",
  "properties": {
    "tgn:hierarchy":[
        "tgn:7469649",
        "tgn:7468018",
        "tgn:1000004",
        "tgn:1000141",
        "tgn:7029392"
    ],
    "tgn:id":7469649,
    "tgn:name":"Fudingjin",
    "tgn:placetype":[
        "aat:300008347"
    ]
},
  "bbox": [],
  "geometry": {"coordinates":[120.570556,23.526389],"type":"Point"}
}