{
  "id": 2170352,
  "type": "Feature",
  "properties": {
    "tgn:hierarchy":[
        "tgn:2170352",
        "tgn:1000001",
        "tgn:7012149",
        "tgn:7007157",
        "tgn:2000185",
        "tgn:7029392"
    ],
    "tgn:id":2170352,
    "tgn:name":"Big River",
    "tgn:placetype":[
        "aat:300008707"
    ]
},
  "bbox": [],
  "geometry": {"coordinates":[-123.3667,39.3167],"type":"Point"}
}