{
  "id": 7220790,
  "type": "Feature",
  "properties": {
    "tgn:hierarchy":[
        "tgn:7220790",
        "tgn:7002724",
        "tgn:7002715",
        "tgn:1000003",
        "tgn:1000074",
        "tgn:7029392"
    ],
    "tgn:id":7220790,
    "tgn:name":"Vasili\u00e1s",
    "tgn:placetype":[
        "aat:300008347"
    ]
},
  "bbox": [],
  "geometry": {"coordinates":[21.433333,40.566667],"type":"Point"}
}