<<<<<<< HEAD
{
  "id": 2763851,
  "type": "Feature",
  "properties": {
    "tgn:hierarchy":[
        "tgn:2763851",
        "tgn:1000001",
        "tgn:7012149",
        "tgn:2002129",
        "tgn:7007827",
        "tgn:7029392"
    ],
    "tgn:id":2763851,
    "tgn:name":"Wheatgrass Spring",
    "tgn:placetype":[
        "aat:300008697"
    ]
},
  "bbox": [],
  "geometry": {"coordinates":[-111.4833,41.4],"type":"Point"}
}
=======
{"geometry":{"type":"Point","coordinates":[-111.483300,41.400000]},"type":"Feature","properties":{"hierarchy":["tgn:2763851","tgn:1000001","tgn:7012149","tgn:2002129","tgn:7007827","tgn:7029392"],"placetype":["aat:300008697"],"id":2763851,"name:xx":"Wheatgrass Spring"}}
>>>>>>> 03f74aca74312dbeaf24d7e61306dd6a786dc3d0
