{
  "id": 7035329,
  "type": "Feature",
  "properties": {
    "tgn:hierarchy":[
        "tgn:7035329",
        "tgn:1003488",
        "tgn:1000003",
        "tgn:7002993",
        "tgn:1000080",
        "tgn:7029392"
    ],
    "tgn:id":7035329,
    "tgn:name":"Pregoiane, Forcella di",
    "tgn:placetype":[
        "aat:300259572"
    ]
},
  "bbox": [],
  "geometry": {"coordinates":[12.599722,46.323056],"type":"Point"}
}