{
  "id": 2682719,
  "type": "Feature",
  "properties": {
    "tgn:hierarchy":[
        "tgn:2682719",
        "tgn:1000001",
        "tgn:7016172",
        "tgn:7012149",
        "tgn:2000147",
        "tgn:7029392"
    ],
    "tgn:id":2682719,
    "tgn:name":"Southside Addition",
    "tgn:placetype":[
        "aat:300008347"
    ]
},
  "bbox": [],
  "geometry": {"coordinates":[-92.0167,34.95],"type":"Point"}
}