<<<<<<< HEAD
{
  "id": 2330615,
  "type": "Feature",
  "properties": {
    "tgn:hierarchy":[
        "tgn:2330615",
        "tgn:1000001",
        "tgn:7012149",
        "tgn:2002248",
        "tgn:7007920",
        "tgn:7029392"
    ],
    "tgn:id":2330615,
    "tgn:name":"Flat Creek",
    "tgn:placetype":[
        "aat:300008706"
    ]
},
  "bbox": [],
  "geometry": {"coordinates":[-117.05,48.4],"type":"Point"}
}
=======
{"geometry":{"type":"Point","coordinates":[-117.050000,48.400000]},"type":"Feature","properties":{"hierarchy":["tgn:2330615","tgn:1000001","tgn:7012149","tgn:2002248","tgn:7007920","tgn:7029392"],"placetype":["aat:300008706"],"id":2330615,"name:xx":"Flat Creek"}}
>>>>>>> 03f74aca74312dbeaf24d7e61306dd6a786dc3d0
