{
  "id": 7335148,
  "type": "Feature",
  "properties": {
    "tgn:hierarchy":[
        "tgn:7335148",
        "tgn:7002759",
        "tgn:7008909",
        "tgn:1000003",
        "tgn:1000095",
        "tgn:7029392"
    ],
    "tgn:id":7335148,
    "tgn:name":"Frula",
    "tgn:placetype":[
        "aat:300008347"
    ]
},
  "bbox": [],
  "geometry": {"coordinates":[-0.448009,41.910431],"type":"Point"}
}