{
  "id": 7170450,
  "type": "Feature",
  "properties": {
    "tgn:hierarchy":[
        "tgn:7170450",
        "tgn:7003669",
        "tgn:1000003",
        "tgn:7000084",
        "tgn:7029392"
    ],
    "tgn:id":7170450,
    "tgn:name":"He\u00dflach",
    "tgn:placetype":[
        "aat:300008347"
    ]
},
  "bbox": [],
  "geometry": {"coordinates":[11.733333,49.966667],"type":"Point"}
}