<<<<<<< HEAD
{
  "id": 2703926,
  "type": "Feature",
  "properties": {
    "tgn:hierarchy":[
        "tgn:2703926",
        "tgn:1000001",
        "tgn:7012149",
        "tgn:7018871",
        "tgn:7007920",
        "tgn:7029392"
    ],
    "tgn:id":2703926,
    "tgn:name":"Sunday Creek",
    "tgn:placetype":[
        "aat:300008706"
    ]
},
  "bbox": [],
  "geometry": {"coordinates":[-121.35,47.2833],"type":"Point"}
}
=======
{"geometry":{"type":"Point","coordinates":[-121.350000,47.283300]},"type":"Feature","properties":{"hierarchy":["tgn:2703926","tgn:1000001","tgn:7012149","tgn:7018871","tgn:7007920","tgn:7029392"],"placetype":["aat:300008706"],"id":2703926,"name:xx":"Sunday Creek"}}
>>>>>>> 03f74aca74312dbeaf24d7e61306dd6a786dc3d0
