<<<<<<< HEAD
{
  "id": 2258066,
  "type": "Feature",
  "properties": {
    "tgn:hierarchy":[
        "tgn:2258066",
        "tgn:1000001",
        "tgn:7012149",
        "tgn:1002942",
        "tgn:7007920",
        "tgn:7029392"
    ],
    "tgn:id":2258066,
    "tgn:name":"Cosgrave Hill",
    "tgn:placetype":[
        "aat:300008798"
    ]
},
  "bbox": [],
  "geometry": {"coordinates":[-122.6667,47.05],"type":"Point"}
}
=======
{"geometry":{"type":"Point","coordinates":[-122.666700,47.050000]},"type":"Feature","properties":{"hierarchy":["tgn:2258066","tgn:1000001","tgn:7012149","tgn:1002942","tgn:7007920","tgn:7029392"],"placetype":["aat:300008798"],"id":2258066,"name:xx":"Cosgrave Hill"}}
>>>>>>> 03f74aca74312dbeaf24d7e61306dd6a786dc3d0
