{
  "id": 7549893,
  "type": "Feature",
  "properties": {
    "tgn:hierarchy":[
        "tgn:7549893",
        "tgn:1000004",
        "tgn:7000198",
        "tgn:1001977",
        "tgn:7029392"
    ],
    "tgn:id":7549893,
    "tgn:name:en":"Cossipore",
    "tgn:placetype":[
        "aat:300007783"
    ]
},
  "bbox": [],
  "geometry": {"coordinates":[88.397693,22.607937],"type":"Point"}
}