<<<<<<< HEAD
{
  "id": 7474490,
  "type": "Feature",
  "properties": {
    "tgn:hierarchy":[
        "tgn:7474490",
        "tgn:1000004",
        "tgn:7467799",
        "tgn:1000141",
        "tgn:7029392"
    ],
    "tgn:id":7474490,
    "tgn:name":"Taiwangou",
    "tgn:placetype":[
        "aat:300008347"
    ]
},
  "bbox": [],
  "geometry": {"coordinates":[120.489444,24.013611],"type":"Point"}
}
=======
{"geometry":{"type":"Point","coordinates":[120.489444,24.013611]},"type":"Feature","properties":{"hierarchy":["tgn:7474490","tgn:1000004","tgn:7467799","tgn:1000141","tgn:7029392"],"placetype":["aat:300008347"],"id":7474490,"name:xx":"Taiwangou"}}
>>>>>>> 03f74aca74312dbeaf24d7e61306dd6a786dc3d0
