{
  "id": 2478062,
  "type": "Feature",
  "properties": {
    "tgn:hierarchy":[
        "tgn:2478062",
        "tgn:7002659",
        "tgn:1000001",
        "tgn:7012149",
        "tgn:2000051",
        "tgn:7029392"
    ],
    "tgn:id":2478062,
    "tgn:name":"Mack Creek",
    "tgn:placetype":[
        "aat:300008706"
    ]
},
  "bbox": [],
  "geometry": {"coordinates":[-86.9667,34.3167],"type":"Point"}
}