{
  "id": 7293617,
  "type": "Feature",
  "properties": {
    "tgn:hierarchy":[
        "tgn:7293617",
        "tgn:7002811",
        "tgn:1000003",
        "tgn:7003837",
        "tgn:1000095",
        "tgn:7029392"
    ],
    "tgn:id":7293617,
    "tgn:name":"Villa del Campo",
    "tgn:placetype":[
        "aat:300008347"
    ]
},
  "bbox": [],
  "geometry": {"coordinates":[-6.433333,40.133333],"type":"Point"}
}