{
  "id": 7527607,
  "type": "Feature",
  "properties": {
    "tgn:hierarchy":[
        "tgn:7527607",
        "tgn:7001242",
        "tgn:7016833",
        "tgn:1001418",
        "tgn:7029392"
    ],
    "tgn:id":7527607,
    "tgn:name:en":"\u1e28iqfat Umm al Ghizl\u0101n",
    "tgn:placetype":[
        "aat:300006207"
    ]
},
  "bbox": [],
  "geometry": {"coordinates":[25.742007,31.063362],"type":"Point"}
}