<<<<<<< HEAD
{
  "id": 7483623,
  "type": "Feature",
  "properties": {
    "tgn:hierarchy":[
        "tgn:7483623",
        "tgn:1000004",
        "tgn:7490934",
        "tgn:1000141",
        "tgn:7029392"
    ],
    "tgn:id":7483623,
    "tgn:name":"Xucun Qiao",
    "tgn:placetype":[
        "aat:300007836"
    ]
},
  "bbox": [],
  "geometry": {"coordinates":[120.526944,23.183056],"type":"Point"}
}
=======
{"geometry":{"type":"Point","coordinates":[120.526944,23.183056]},"type":"Feature","properties":{"hierarchy":["tgn:7483623","tgn:1000004","tgn:7490934","tgn:1000141","tgn:7029392"],"placetype":["aat:300007836"],"id":7483623,"name:xx":"Xucun Qiao"}}
>>>>>>> 03f74aca74312dbeaf24d7e61306dd6a786dc3d0
