{
  "id": 7168303,
  "type": "Feature",
  "properties": {
    "tgn:hierarchy":[
        "tgn:7168303",
        "tgn:7003692",
        "tgn:1000003",
        "tgn:7000084",
        "tgn:7029392"
    ],
    "tgn:id":7168303,
    "tgn:name":"Ha\u00dffelden",
    "tgn:placetype":[
        "aat:300008347"
    ]
},
  "bbox": [],
  "geometry": {"coordinates":[9.85,49.183333],"type":"Point"}
}