{
  "id": 7534058,
  "type": "Feature",
  "properties": {
    "tgn:hierarchy":[
        "tgn:7534058",
        "tgn:7001242",
        "tgn:7016833",
        "tgn:1001418",
        "tgn:7029392"
    ],
    "tgn:id":7534058,
    "tgn:name:en":"Maghrib, 'Alam el-",
    "tgn:placetype":[
        "aat:300008777"
    ]
},
  "bbox": [],
  "geometry": {"coordinates":[25.083333,30.783333],"type":"Point"}
}