{
  "id": 2189860,
  "type": "Feature",
  "properties": {
    "tgn:hierarchy":[
        "tgn:2189860",
        "tgn:2000918",
        "tgn:1000001",
        "tgn:7012149",
        "tgn:7007515",
        "tgn:7029392"
    ],
    "tgn:id":2189860,
    "tgn:name":"Bowie Hill",
    "tgn:placetype":[
        "aat:300008798"
    ]
},
  "bbox": [],
  "geometry": {"coordinates":[-70.1667,43.9667],"type":"Point"}
}