{
  "id": 2628271,
  "type": "Feature",
  "properties": {
    "tgn:hierarchy":[
        "tgn:2628271",
        "tgn:7002659",
        "tgn:1000001",
        "tgn:2000019",
        "tgn:7012149",
        "tgn:7029392"
    ],
    "tgn:id":2628271,
    "tgn:name":"Rome Pond",
    "tgn:placetype":[
        "aat:300006191"
    ]
},
  "bbox": [],
  "geometry": {"coordinates":[-86.6667,31.1333],"type":"Point"}
}