{
  "id": 7318924,
  "type": "Feature",
  "properties": {
    "tgn:hierarchy":[
        "tgn:7318924",
        "tgn:1001699",
        "tgn:1000049",
        "tgn:1000002",
        "tgn:7029392"
    ],
    "tgn:id":7318924,
    "tgn:name":"Aro, Punta",
    "tgn:placetype":[
        "aat:300386846"
    ]
},
  "bbox": [],
  "geometry": {"coordinates":[-72.85,-42.666667],"type":"Point"}
}