{
  "id": 7188736,
  "type": "Feature",
  "properties": {
    "tgn:hierarchy":[
        "tgn:7188736",
        "tgn:1000003",
        "tgn:7003682",
        "tgn:7000084",
        "tgn:7029392"
    ],
    "tgn:id":7188736,
    "tgn:name":"Erden",
    "tgn:placetype":[
        "aat:300008347"
    ]
},
  "bbox": [],
  "geometry": {"coordinates":[7.016667,49.983333],"type":"Point"}
}