{
  "id": 2100786,
  "type": "Feature",
  "properties": {
    "tgn:hierarchy":[
        "tgn:2100786",
        "tgn:1000001",
        "tgn:7012149",
        "tgn:2001925",
        "tgn:7007825",
        "tgn:7029392"
    ],
    "tgn:id":2100786,
    "tgn:name":"Oak Grove",
    "tgn:placetype":[
        "aat:300008347",
        "aat:300387210"
    ]
},
  "bbox": [],
  "geometry": {"coordinates":[-85.95,35.6833],"type":"Point"}
}