{
  "id": 2561800,
  "type": "Feature",
  "properties": {
    "tgn:hierarchy":[
        "tgn:2561800",
        "tgn:1000001",
        "tgn:7012149",
        "tgn:2000617",
        "tgn:7007253",
        "tgn:7029392"
    ],
    "tgn:id":2561800,
    "tgn:name":"Otis",
    "tgn:placetype":[
        "aat:300008347"
    ]
},
  "bbox": [],
  "geometry": {"coordinates":[-91.6167,41.95],"type":"Point"}
}