{
  "id": 2486448,
  "type": "Feature",
  "properties": {
    "tgn:hierarchy":[
        "tgn:2486448",
        "tgn:1002300",
        "tgn:1000001",
        "tgn:7012149",
        "tgn:7007564",
        "tgn:7029392"
    ],
    "tgn:id":2486448,
    "tgn:name":"Leavitt Stream",
    "tgn:placetype":[
        "aat:300008699"
    ]
},
  "bbox": [],
  "geometry": {"coordinates":[-71.0833,44.5667],"type":"Point"}
}