<<<<<<< HEAD
{
  "id": 7351432,
  "type": "Feature",
  "properties": {
    "tgn:hierarchy":[
        "tgn:7351432",
        "tgn:1000001",
        "tgn:7005595",
        "tgn:7005560",
        "tgn:7029392"
    ],
    "tgn:id":7351432,
    "tgn:name":"Cachuana",
    "tgn:placetype":[
        "aat:300008347"
    ]
},
  "bbox": [],
  "geometry": {"coordinates":[-109.116667,25.933333],"type":"Point"}
}
=======
{"geometry":{"type":"Point","coordinates":[-109.116667,25.933333]},"type":"Feature","properties":{"hierarchy":["tgn:7351432","tgn:1000001","tgn:7005595","tgn:7005560","tgn:7029392"],"placetype":["aat:300008347"],"id":7351432,"name:xx":"Cachuana"}}
>>>>>>> 03f74aca74312dbeaf24d7e61306dd6a786dc3d0
