{
  "id": 2493483,
  "type": "Feature",
  "properties": {
    "tgn:hierarchy":[
        "tgn:2493483",
        "tgn:1000001",
        "tgn:7012149",
        "tgn:2001310",
        "tgn:7007524",
        "tgn:7029392"
    ],
    "tgn:id":2493483,
    "tgn:name":"Marsh Coulee",
    "tgn:placetype":[
        "aat:300008761"
    ]
},
  "bbox": [],
  "geometry": {"coordinates":[-111.45,48.3667],"type":"Point"}
}