{
  "id": 2104781,
  "type": "Feature",
  "properties": {
    "tgn:hierarchy":[
        "tgn:2104781",
        "tgn:1000001",
        "tgn:7012149",
        "tgn:1002839",
        "tgn:7007826",
        "tgn:7029392"
    ],
    "tgn:id":2104781,
    "tgn:name":"Hickey",
    "tgn:placetype":[
        "aat:300008347",
        "aat:300387210"
    ]
},
  "bbox": [],
  "geometry": {"coordinates":[-94.8667,32.0833],"type":"Point"}
}