{
  "id": 1068960,
  "type": "Feature",
  "properties": {
    "tgn:hierarchy":[
        "tgn:1068960",
        "tgn:1000004",
        "tgn:7002088",
        "tgn:1000111",
        "tgn:7029392"
    ],
    "tgn:id":1068960,
    "tgn:name":"Lushar",
    "tgn:placetype":[
        "aat:300008347"
    ]
},
  "bbox": [],
  "geometry": {"coordinates":[101.6667,36.5167],"type":"Point"}
}