{
  "id": 2540847,
  "type": "Feature",
  "properties": {
    "tgn:hierarchy":[
        "tgn:2540847",
        "tgn:1000001",
        "tgn:7012149",
        "tgn:1002789",
        "tgn:7007710",
        "tgn:7029392"
    ],
    "tgn:id":2540847,
    "tgn:name":"Nichecronk Brook",
    "tgn:placetype":[
        "aat:300008699"
    ]
},
  "bbox": [],
  "geometry": {"coordinates":[-74.9333,41.2667],"type":"Point"}
}