{
  "id": 7350298,
  "type": "Feature",
  "properties": {
    "tgn:hierarchy":[
        "tgn:7350298",
        "tgn:1000001",
        "tgn:7005592",
        "tgn:7005560",
        "tgn:7029392"
    ],
    "tgn:id":7350298,
    "tgn:name":"Bienvenido",
    "tgn:placetype":[
        "aat:300008347"
    ]
},
  "bbox": [],
  "geometry": {"coordinates":[-97.75,20.133333],"type":"Point"}
}