<<<<<<< HEAD
{
  "id": 7481223,
  "type": "Feature",
  "properties": {
    "tgn:hierarchy":[
        "tgn:7481223",
        "tgn:1000004",
        "tgn:7491221",
        "tgn:1000141",
        "tgn:7029392"
    ],
    "tgn:id":7481223,
    "tgn:name":"Yun\u00fc Yan",
    "tgn:placetype":[
        "aat:300011692"
    ]
},
  "bbox": [],
  "geometry": {"coordinates":[121.52,22.081111],"type":"Point"}
}
=======
{"geometry":{"type":"Point","coordinates":[121.520000,22.081111]},"type":"Feature","properties":{"hierarchy":["tgn:7481223","tgn:1000004","tgn:7491221","tgn:1000141","tgn:7029392"],"placetype":["aat:300011692"],"id":7481223,"name:xx":"Yun\u00fc Yan"}}
>>>>>>> 03f74aca74312dbeaf24d7e61306dd6a786dc3d0
