{
  "id": 1060311,
  "type": "Feature",
  "properties": {
    "tgn:hierarchy":[
        "tgn:1060311",
        "tgn:1000004",
        "tgn:7011573",
        "tgn:7018214",
        "tgn:7002435",
        "tgn:7029392"
    ],
    "tgn:id":1060311,
    "tgn:name":"Timkovo",
    "tgn:placetype":[
        "aat:300008347"
    ]
},
  "bbox": [],
  "geometry": {"coordinates":[38.6167,55.9333],"type":"Point"}
}