{
  "id": 7197835,
  "type": "Feature",
  "properties": {
    "tgn:hierarchy":[
        "tgn:7197835",
        "tgn:1000003",
        "tgn:7003676",
        "tgn:7000084",
        "tgn:7029392"
    ],
    "tgn:id":7197835,
    "tgn:name":"Duinger Wald",
    "tgn:placetype":[
        "aat:300008863"
    ]
},
  "bbox": [],
  "geometry": {"coordinates":[9.683333,51.983333],"type":"Point"}
}