{
  "id": 2297659,
  "type": "Feature",
  "properties": {
    "tgn:hierarchy":[
        "tgn:2297659",
        "tgn:1000001",
        "tgn:1002185",
        "tgn:7012149",
        "tgn:7007710",
        "tgn:7029392"
    ],
    "tgn:id":2297659,
    "tgn:name":"Dry Gap Run",
    "tgn:placetype":[
        "aat:300008699"
    ]
},
  "bbox": [],
  "geometry": {"coordinates":[-78.45,40.5333],"type":"Point"}
}