{
  "id": 1079607,
  "type": "Feature",
  "properties": {
    "tgn:hierarchy":[
        "tgn:1079607",
        "tgn:7000249",
        "tgn:1000004",
        "tgn:1000119",
        "tgn:7029392"
    ],
    "tgn:id":1079607,
    "tgn:name":"Rama",
    "tgn:placetype":[
        "aat:300008347"
    ]
},
  "bbox": [],
  "geometry": {"coordinates":[35.3667,32.9333],"type":"Point"}
}