{
  "id": 7378678,
  "type": "Feature",
  "properties": {
    "tgn:hierarchy":[
        "tgn:7378678",
        "tgn:1000001",
        "tgn:7005595",
        "tgn:7005560",
        "tgn:7029392"
    ],
    "tgn:id":7378678,
    "tgn:name":"Los Capomos",
    "tgn:placetype":[
        "aat:300008347"
    ]
},
  "bbox": [],
  "geometry": {"coordinates":[-108.515833,26.427222],"type":"Point"}
}