{
  "id": 1033081,
  "type": "Feature",
  "properties": {
    "tgn:hierarchy":[
        "tgn:1033081",
        "tgn:1000003",
        "tgn:7002883",
        "tgn:1000070",
        "tgn:7029392"
    ],
    "tgn:id":1033081,
    "tgn:name":"Favi\u00e8res",
    "tgn:placetype":[
        "aat:300008347"
    ]
},
  "bbox": [],
  "geometry": {"coordinates":[5.95,48.45],"type":"Point"}
}