{
  "id": 2163996,
  "type": "Feature",
  "properties": {
    "tgn:hierarchy":[
        "tgn:2163996",
        "tgn:1000001",
        "tgn:7012149",
        "tgn:2001274",
        "tgn:7007524",
        "tgn:7029392"
    ],
    "tgn:id":2163996,
    "tgn:name":"Bergsicker Creek",
    "tgn:placetype":[
        "aat:300008706"
    ]
},
  "bbox": [],
  "geometry": {"coordinates":[-113.6167,48.1167],"type":"Point"}
}