{
  "id": 2423103,
  "type": "Feature",
  "properties": {
    "tgn:hierarchy":[
        "tgn:2423103",
        "tgn:1000001",
        "tgn:2001476",
        "tgn:7012149",
        "tgn:7007709",
        "tgn:7029392"
    ],
    "tgn:id":2423103,
    "tgn:name":"Joe White Mountain",
    "tgn:placetype":[
        "aat:300008798"
    ]
},
  "bbox": [],
  "geometry": {"coordinates":[-81.7167,35.9833],"type":"Point"}
}