<<<<<<< HEAD
{
  "id": 7477810,
  "type": "Feature",
  "properties": {
    "tgn:hierarchy":[
        "tgn:7477810",
        "tgn:7488858",
        "tgn:1000004",
        "tgn:1000141",
        "tgn:7029392"
    ],
    "tgn:id":7477810,
    "tgn:name":"Shuichongkuang Pubu",
    "tgn:placetype":[
        "aat:300008736"
    ]
},
  "bbox": [],
  "geometry": {"coordinates":[120.859583,23.887023],"type":"Point"}
}
=======
{"geometry":{"type":"Point","coordinates":[120.859583,23.887023]},"type":"Feature","properties":{"hierarchy":["tgn:7477810","tgn:7488858","tgn:1000004","tgn:1000141","tgn:7029392"],"placetype":["aat:300008736"],"id":7477810,"name:xx":"Shuichongkuang Pubu"}}
>>>>>>> 03f74aca74312dbeaf24d7e61306dd6a786dc3d0
