{
  "id": 7072684,
  "type": "Feature",
  "properties": {
    "tgn:hierarchy":[
        "tgn:7072684",
        "tgn:7003669",
        "tgn:1000003",
        "tgn:7000084",
        "tgn:7029392"
    ],
    "tgn:id":7072684,
    "tgn:name":"T\u00e4nnig",
    "tgn:placetype":[
        "aat:300008863"
    ]
},
  "bbox": [],
  "geometry": {"coordinates":[12.066667,50.116667],"type":"Point"}
}