{
  "id": 7592885,
  "type": "Feature",
  "properties": {
    "tgn:hierarchy":[
        "tgn:7592885",
        "tgn:1000004",
        "tgn:7000198",
        "tgn:7000799",
        "tgn:7029392"
    ],
    "tgn:id":7592885,
    "tgn:name:en":"Man\u0101war Tawl",
    "tgn:placetype":[
        "aat:300008699"
    ]
},
  "bbox": [],
  "geometry": {"coordinates":[74.363889,33.022222],"type":"Point"}
}