{
  "id": 2341219,
  "type": "Feature",
  "properties": {
    "tgn:hierarchy":[
        "tgn:2341219",
        "tgn:2002101",
        "tgn:1000001",
        "tgn:7012149",
        "tgn:7007827",
        "tgn:7029392"
    ],
    "tgn:id":2341219,
    "tgn:name":"Frisco Peak",
    "tgn:placetype":[
        "aat:300008798"
    ]
},
  "bbox": [],
  "geometry": {"coordinates":[-113.2833,38.5167],"type":"Point"}
}