{
  "id": 7505865,
  "type": "Feature",
  "properties": {
    "tgn:hierarchy":[
        "tgn:7505865",
        "tgn:1008380",
        "tgn:1000226",
        "tgn:7000512",
        "tgn:1000006",
        "tgn:7029392"
    ],
    "tgn:id":7505865,
    "tgn:name:en":"Tararua Forest Park",
    "tgn:placetype":[
        "aat:300008187"
    ]
},
  "bbox": [],
  "geometry": {"coordinates":[175.383333,-40.766667],"type":"Point"}
}