{
  "id": 7441588,
  "type": "Feature",
  "properties": {
    "tgn:hierarchy":[
        "tgn:7441588",
        "tgn:7002443",
        "tgn:1000003",
        "tgn:7018956",
        "tgn:7008591",
        "tgn:7029392"
    ],
    "tgn:id":7441588,
    "tgn:name:en":"Tredegar Park",
    "tgn:placetype":[
        "aat:300387502"
    ]
},
  "bbox": [],
  "geometry": {"coordinates":[-3.016667,51.566667],"type":"Point"}
}