{
  "id": 7353497,
  "type": "Feature",
  "properties": {
    "tgn:hierarchy":[
        "tgn:7353497",
        "tgn:1001853",
        "tgn:1000001",
        "tgn:7005560",
        "tgn:7029392"
    ],
    "tgn:id":7353497,
    "tgn:name":"Secci\u00f3n Anhelo",
    "tgn:placetype":[
        "aat:300007783"
    ]
},
  "bbox": [],
  "geometry": {"coordinates":[-100.983333,25.983333],"type":"Point"}
}