{
  "id": 2102694,
  "type": "Feature",
  "properties": {
    "tgn:hierarchy":[
        "tgn:2102694",
        "tgn:1000001",
        "tgn:7012149",
        "tgn:1002939",
        "tgn:7007826",
        "tgn:7029392"
    ],
    "tgn:id":2102694,
    "tgn:name":"Benbrook",
    "tgn:placetype":[
        "aat:300008347"
    ]
},
  "bbox": [],
  "geometry": {"coordinates":[-97.45,32.6667],"type":"Point"}
}