{
  "id": 7439227,
  "type": "Feature",
  "properties": {
    "tgn:hierarchy":[
        "tgn:7439227",
        "tgn:1000001",
        "tgn:7005595",
        "tgn:7005560",
        "tgn:7029392"
    ],
    "tgn:id":7439227,
    "tgn:name":"San Vicente",
    "tgn:placetype":[
        "aat:300008347"
    ]
},
  "bbox": [],
  "geometry": {"coordinates":[-107.616667,26.066667],"type":"Point"}
}