{
  "id": 2394707,
  "type": "Feature",
  "properties": {
    "tgn:hierarchy":[
        "tgn:2394707",
        "tgn:1000001",
        "tgn:7012149",
        "tgn:2000960",
        "tgn:7007520",
        "tgn:7029392"
    ],
    "tgn:id":2394707,
    "tgn:name":"Hoist Lake",
    "tgn:placetype":[
        "aat:300008680"
    ]
},
  "bbox": [],
  "geometry": {"coordinates":[-89.15,46.1833],"type":"Point"}
}