{
  "id": 7097893,
  "type": "Feature",
  "properties": {
    "tgn:hierarchy":[
        "tgn:7097893",
        "tgn:7003692",
        "tgn:1000003",
        "tgn:7000084",
        "tgn:7029392"
    ],
    "tgn:id":7097893,
    "tgn:name":"Sprantal",
    "tgn:placetype":[
        "aat:300008347"
    ]
},
  "bbox": [],
  "geometry": {"coordinates":[8.680278,49.003611],"type":"Point"}
}