{
  "id": 2105113,
  "type": "Feature",
  "properties": {
    "tgn:hierarchy":[
        "tgn:2105113",
        "tgn:1000001",
        "tgn:7012149",
        "tgn:2002050",
        "tgn:7007826",
        "tgn:7029392"
    ],
    "tgn:id":2105113,
    "tgn:name":"Huntoon",
    "tgn:placetype":[
        "aat:300387016"
    ]
},
  "bbox": [],
  "geometry": {"coordinates":[-100.6167,36.45],"type":"Point"}
}