{
  "id": 2572232,
  "type": "Feature",
  "properties": {
    "tgn:hierarchy":[
        "tgn:2572232",
        "tgn:1000001",
        "tgn:2001264",
        "tgn:7012149",
        "tgn:7007524",
        "tgn:7029392"
    ],
    "tgn:id":2572232,
    "tgn:name":"Peabody Ditch",
    "tgn:placetype":[
        "aat:300006075"
    ]
},
  "bbox": [],
  "geometry": {"coordinates":[-109.4667,45.3333],"type":"Point"}
}