{
  "id": 2772892,
  "type": "Feature",
  "properties": {
    "tgn:hierarchy":[
        "tgn:2772892",
        "tgn:1002166",
        "tgn:1000001",
        "tgn:7012149",
        "tgn:7007520",
        "tgn:7029392"
    ],
    "tgn:id":2772892,
    "tgn:name":"Williams Lake",
    "tgn:placetype":[
        "aat:300008680"
    ]
},
  "bbox": [],
  "geometry": {"coordinates":[-85.4833,42.6167],"type":"Point"}
}