{
  "id": 2527599,
  "type": "Feature",
  "properties": {
    "tgn:hierarchy":[
        "tgn:2527599",
        "tgn:1000001",
        "tgn:7012149",
        "tgn:2001619",
        "tgn:7007706",
        "tgn:7029392"
    ],
    "tgn:id":2527599,
    "tgn:name":"Mount Zion",
    "tgn:placetype":[
        "aat:300008347"
    ]
},
  "bbox": [],
  "geometry": {"coordinates":[-81.5167,39.8667],"type":"Point"}
}