{
  "id": 2204197,
  "type": "Feature",
  "properties": {
    "tgn:hierarchy":[
        "tgn:2204197",
        "tgn:1000001",
        "tgn:7012149",
        "tgn:7007157",
        "tgn:1002858",
        "tgn:7029392"
    ],
    "tgn:id":2204197,
    "tgn:name":"Buena Vista Lagoon",
    "tgn:placetype":[
        "aat:300008680"
    ]
},
  "bbox": [],
  "geometry": {"coordinates":[-117.3333,33.1667],"type":"Point"}
}