{
  "id": 2575077,
  "type": "Feature",
  "properties": {
    "tgn:hierarchy":[
        "tgn:2575077",
        "tgn:1000001",
        "tgn:7012149",
        "tgn:2001489",
        "tgn:7007709",
        "tgn:7029392"
    ],
    "tgn:id":2575077,
    "tgn:name":"Pennfield",
    "tgn:placetype":[
        "aat:300008347"
    ]
},
  "bbox": [],
  "geometry": {"coordinates":[-80.05,35.9167],"type":"Point"}
}