{
  "id": 2414648,
  "type": "Feature",
  "properties": {
    "tgn:hierarchy":[
        "tgn:2414648",
        "tgn:1000001",
        "tgn:7012149",
        "tgn:2000216",
        "tgn:7007158",
        "tgn:7029392"
    ],
    "tgn:id":2414648,
    "tgn:name":"Irving Hale Creek",
    "tgn:placetype":[
        "aat:300008706"
    ]
},
  "bbox": [],
  "geometry": {"coordinates":[-105.7167,40.1167],"type":"Point"}
}