{
  "id": 2138200,
  "type": "Feature",
  "properties": {
    "tgn:hierarchy":[
        "tgn:2138200",
        "tgn:1000001",
        "tgn:7012149",
        "tgn:2001756",
        "tgn:7007712",
        "tgn:7029392"
    ],
    "tgn:id":2138200,
    "tgn:name":"Arthur",
    "tgn:placetype":[
        "aat:300008347"
    ]
},
  "bbox": [],
  "geometry": {"coordinates":[-81.1333,33.9667],"type":"Point"}
}