{
  "id": 2243195,
  "type": "Feature",
  "properties": {
    "tgn:hierarchy":[
        "tgn:2243195",
        "tgn:1000001",
        "tgn:7012149",
        "tgn:7007157",
        "tgn:2000186",
        "tgn:7029392"
    ],
    "tgn:id":2243195,
    "tgn:name":"Clear Lake Hills",
    "tgn:placetype":[
        "aat:300386831"
    ]
},
  "bbox": [],
  "geometry": {"coordinates":[-121.2167,41.8167],"type":"Point"}
}