{
  "id": 2671568,
  "type": "Feature",
  "properties": {
    "tgn:hierarchy":[
        "tgn:2671568",
        "tgn:1000001",
        "tgn:7012149",
        "tgn:2001049",
        "tgn:7007521",
        "tgn:7029392"
    ],
    "tgn:id":2671568,
    "tgn:name":"Smith Lake",
    "tgn:placetype":[
        "aat:300008680"
    ]
},
  "bbox": [],
  "geometry": {"coordinates":[-95.6833,44.0833],"type":"Point"}
}