{
  "id": 7573775,
  "type": "Feature",
  "properties": {
    "tgn:hierarchy":[
        "tgn:7573775",
        "tgn:1000004",
        "tgn:7000198",
        "tgn:7016694",
        "tgn:7029392"
    ],
    "tgn:id":7573775,
    "tgn:name:en":"Garh Madhupur",
    "tgn:placetype":[
        "aat:300007783"
    ]
},
  "bbox": [],
  "geometry": {"coordinates":[86.072325,20.79945],"type":"Point"}
}