{
  "id": 2289600,
  "type": "Feature",
  "properties": {
    "tgn:hierarchy":[
        "tgn:2289600",
        "tgn:1000001",
        "tgn:7012149",
        "tgn:1002549",
        "tgn:7007919",
        "tgn:7029392"
    ],
    "tgn:id":2289600,
    "tgn:name":"Dixon Landing",
    "tgn:placetype":[
        "aat:300008347"
    ]
},
  "bbox": [],
  "geometry": {"coordinates":[-76.7833,37.5833],"type":"Point"}
}