{
  "id": 2637064,
  "type": "Feature",
  "properties": {
    "tgn:hierarchy":[
        "tgn:2637064",
        "tgn:2001317",
        "tgn:1000001",
        "tgn:7012149",
        "tgn:7007525",
        "tgn:7029392"
    ],
    "tgn:id":2637064,
    "tgn:name":"Saint Clair Creek",
    "tgn:placetype":[
        "aat:300008706"
    ]
},
  "bbox": [],
  "geometry": {"coordinates":[-97.9333,41.9167],"type":"Point"}
}