{
  "id": 2059659,
  "type": "Feature",
  "properties": {
    "tgn:hierarchy":[
        "tgn:2059659",
        "tgn:1000001",
        "tgn:7012149",
        "tgn:2001192",
        "tgn:7007523",
        "tgn:7029392"
    ],
    "tgn:id":2059659,
    "tgn:name":"March",
    "tgn:placetype":[
        "aat:300008347"
    ]
},
  "bbox": [],
  "geometry": {"coordinates":[-93.0833,37.5167],"type":"Point"}
}