{
  "id": 1105890,
  "type": "Feature",
  "properties": {
    "tgn:hierarchy":[
        "tgn:1105890",
        "tgn:7005685",
        "tgn:7005807",
        "tgn:1000001",
        "tgn:7005801",
        "tgn:7029392"
    ],
    "tgn:id":1105890,
    "tgn:name":"Old Man Mountain",
    "tgn:placetype":[
        "aat:300008795"
    ]
},
  "bbox": [],
  "geometry": {"coordinates":[-57.7167,49.1333],"type":"Point"}
}