{
  "id": 2682968,
  "type": "Feature",
  "properties": {
    "tgn:hierarchy":[
        "tgn:2682968",
        "tgn:7006450",
        "tgn:1000001",
        "tgn:7012149",
        "tgn:2000082",
        "tgn:7029392"
    ],
    "tgn:id":2682968,
    "tgn:name":"Spacious Bay",
    "tgn:placetype":[
        "aat:300132316"
    ]
},
  "bbox": [],
  "geometry": {"coordinates":[-131.8167,55.85],"type":"Point"}
}