{
  "id": 2429291,
  "type": "Feature",
  "properties": {
    "tgn:hierarchy":[
        "tgn:2429291",
        "tgn:1000001",
        "tgn:2001410",
        "tgn:7012149",
        "tgn:7007526",
        "tgn:7029392"
    ],
    "tgn:id":2429291,
    "tgn:name":"Jungletown",
    "tgn:placetype":[
        "aat:300008347",
        "aat:300167671",
        "aat:300000517"
    ]
},
  "bbox": [],
  "geometry": {"coordinates":[-115.05,36.2667],"type":"Point"}
}