<<<<<<< HEAD
{
  "id": 7359651,
  "type": "Feature",
  "properties": {
    "tgn:hierarchy":[
        "tgn:7359651",
        "tgn:7005581",
        "tgn:1000001",
        "tgn:7005560",
        "tgn:7029392"
    ],
    "tgn:id":7359651,
    "tgn:name":"Clavelinas, Laguna de las",
    "tgn:placetype":[
        "aat:300387086"
    ]
},
  "bbox": [],
  "geometry": {"coordinates":[-104.566667,27.35],"type":"Point"}
}
=======
{"geometry":{"type":"Point","coordinates":[-104.566667,27.350000]},"type":"Feature","properties":{"hierarchy":["tgn:7359651","tgn:7005581","tgn:1000001","tgn:7005560","tgn:7029392"],"placetype":["aat:300387086"],"id":7359651,"name:xx":"Clavelinas, Laguna de las"}}
>>>>>>> 03f74aca74312dbeaf24d7e61306dd6a786dc3d0
