<<<<<<< HEAD
{
  "id": 7058277,
  "type": "Feature",
  "properties": {
    "tgn:hierarchy":[
        "tgn:7058277",
        "tgn:7003138",
        "tgn:1000003",
        "tgn:7003080",
        "tgn:1000080",
        "tgn:7029392"
    ],
    "tgn:id":7058277,
    "tgn:name":"Aniene, Fiume",
    "tgn:placetype":[
        "aat:300008699"
    ]
},
  "bbox": [],
  "geometry": {"coordinates":[12.5,41.933333],"type":"Point"}
}
=======
{"geometry":{"type":"Point","coordinates":[12.500000,41.933333]},"type":"Feature","properties":{"hierarchy":["tgn:7058277","tgn:7003138","tgn:1000003","tgn:7003080","tgn:1000080","tgn:7029392"],"placetype":["aat:300008699"],"id":7058277,"name:xx":"Aniene, Fiume"}}
>>>>>>> 03f74aca74312dbeaf24d7e61306dd6a786dc3d0
