{
  "id": 2589686,
  "type": "Feature",
  "properties": {
    "tgn:hierarchy":[
        "tgn:2589686",
        "tgn:1000001",
        "tgn:1002934",
        "tgn:7012149",
        "tgn:7007565",
        "tgn:7029392"
    ],
    "tgn:id":2589686,
    "tgn:name":"Point Pleasant",
    "tgn:placetype":[
        "aat:300008347"
    ]
},
  "bbox": [],
  "geometry": {"coordinates":[-74.65,40.9167],"type":"Point"}
}