{
  "id": 7230379,
  "type": "Feature",
  "properties": {
    "tgn:hierarchy":[
        "tgn:7230379",
        "tgn:7002724",
        "tgn:7002715",
        "tgn:1000003",
        "tgn:1000074",
        "tgn:7029392"
    ],
    "tgn:id":7230379,
    "tgn:name":"Mavr\u00f3kambos",
    "tgn:placetype":[
        "aat:300008347"
    ]
},
  "bbox": [],
  "geometry": {"coordinates":[21.233333,40.633333],"type":"Point"}
}