{
  "id": 2030156,
  "type": "Feature",
  "properties": {
    "tgn:hierarchy":[
        "tgn:2030156",
        "tgn:1000001",
        "tgn:1002349",
        "tgn:7012149",
        "tgn:7007251",
        "tgn:7029392"
    ],
    "tgn:id":2030156,
    "tgn:name":"Shumway",
    "tgn:placetype":[
        "aat:300008347"
    ]
},
  "bbox": [],
  "geometry": {"coordinates":[-88.65,39.1833],"type":"Point"}
}