{
  "id": 2412190,
  "type": "Feature",
  "properties": {
    "tgn:hierarchy":[
        "tgn:2412190",
        "tgn:1000001",
        "tgn:7012149",
        "tgn:7007158",
        "tgn:2000246",
        "tgn:7029392"
    ],
    "tgn:id":2412190,
    "tgn:name":"Indian Spring",
    "tgn:placetype":[
        "aat:300008680"
    ]
},
  "bbox": [],
  "geometry": {"coordinates":[-105.6167,37.7667],"type":"Point"}
}