{
  "id": 2288316,
  "type": "Feature",
  "properties": {
    "tgn:hierarchy":[
        "tgn:2288316",
        "tgn:1000001",
        "tgn:7016172",
        "tgn:7012149",
        "tgn:2000140",
        "tgn:7029392"
    ],
    "tgn:id":2288316,
    "tgn:name":"Dirty Creek",
    "tgn:placetype":[
        "aat:300008706"
    ]
},
  "bbox": [],
  "geometry": {"coordinates":[-93.6667,35.55],"type":"Point"}
}