{
  "id": 2395592,
  "type": "Feature",
  "properties": {
    "tgn:hierarchy":[
        "tgn:2395592",
        "tgn:2002308",
        "tgn:1000001",
        "tgn:7012149",
        "tgn:7007922",
        "tgn:7029392"
    ],
    "tgn:id":2395592,
    "tgn:name":"Hollibar Lake",
    "tgn:placetype":[
        "aat:300008680"
    ]
},
  "bbox": [],
  "geometry": {"coordinates":[-91.25,46.45],"type":"Point"}
}