{
  "id": 7543649,
  "type": "Feature",
  "properties": {
    "tgn:hierarchy":[
        "tgn:7543649",
        "tgn:7001242",
        "tgn:1001059",
        "tgn:7016833",
        "tgn:7029392"
    ],
    "tgn:id":7543649,
    "tgn:name":"Munsha'at an Na\u015fr",
    "tgn:placetype":[
        "aat:300008347"
    ]
},
  "bbox": [],
  "geometry": {"coordinates":[31.509108,31.340825],"type":"Point"}
}