{
  "id": 2315229,
  "type": "Feature",
  "properties": {
    "tgn:hierarchy":[
        "tgn:2315229",
        "tgn:1000001",
        "tgn:7012149",
        "tgn:1002451",
        "tgn:7007919",
        "tgn:7029392"
    ],
    "tgn:id":2315229,
    "tgn:name":"Ellerson Mill",
    "tgn:placetype":[
        "aat:300008347"
    ]
},
  "bbox": [],
  "geometry": {"coordinates":[-77.35,37.5833],"type":"Point"}
}