{
  "id": 2651528,
  "type": "Feature",
  "properties": {
    "tgn:hierarchy":[
        "tgn:2651528",
        "tgn:1000001",
        "tgn:2001017",
        "tgn:7012149",
        "tgn:7007521",
        "tgn:7029392"
    ],
    "tgn:id":2651528,
    "tgn:name":"Sedil",
    "tgn:placetype":[
        "aat:300008347"
    ]
},
  "bbox": [],
  "geometry": {"coordinates":[-92.9667,44.75],"type":"Point"}
}