{
  "id": 2113606,
  "type": "Feature",
  "properties": {
    "tgn:hierarchy":[
        "tgn:2113606",
        "tgn:1000001",
        "tgn:7012149",
        "tgn:2002162",
        "tgn:7007919",
        "tgn:7029392"
    ],
    "tgn:id":2113606,
    "tgn:name":"Penvir",
    "tgn:placetype":[
        "aat:300008347",
        "aat:300387210"
    ]
},
  "bbox": [],
  "geometry": {"coordinates":[-80.8667,37.2833],"type":"Point"}
}