<<<<<<< HEAD
{
  "id": 7114399,
  "type": "Feature",
  "properties": {
    "tgn:hierarchy":[
        "tgn:7114399",
        "tgn:7003669",
        "tgn:1000003",
        "tgn:7000084",
        "tgn:7029392"
    ],
    "tgn:id":7114399,
    "tgn:name":"Rieder Kohlstatt",
    "tgn:placetype":[
        "aat:300008795"
    ]
},
  "bbox": [],
  "geometry": {"coordinates":[11.983333,47.7],"type":"Point"}
}
=======
{"geometry":{"type":"Point","coordinates":[11.983333,47.700000]},"type":"Feature","properties":{"hierarchy":["tgn:7114399","tgn:7003669","tgn:1000003","tgn:7000084","tgn:7029392"],"placetype":["aat:300008795"],"id":7114399,"name:xx":"Rieder Kohlstatt"}}
>>>>>>> 03f74aca74312dbeaf24d7e61306dd6a786dc3d0
