{
  "id": 2671419,
  "type": "Feature",
  "properties": {
    "tgn:hierarchy":[
        "tgn:2671419",
        "tgn:1000001",
        "tgn:7012149",
        "tgn:2001980",
        "tgn:7007826",
        "tgn:7029392"
    ],
    "tgn:id":2671419,
    "tgn:name":"Smith Hollow",
    "tgn:placetype":[
        "aat:300008761"
    ]
},
  "bbox": [],
  "geometry": {"coordinates":[-99.75,30.2333],"type":"Point"}
}