{
  "id": 1126877,
  "type": "Feature",
  "properties": {
    "tgn:hierarchy":[
        "tgn:1126877",
        "tgn:1000001",
        "tgn:7012149",
        "tgn:7007524",
        "tgn:7029392"
    ],
    "tgn:id":1126877,
    "tgn:name":"Marias",
    "tgn:placetype":[
        "aat:300008707"
    ]
},
  "bbox": [],
  "geometry": {"coordinates":[-112.2167,48.4833],"type":"Point"}
}