{
  "id": 7043258,
  "type": "Feature",
  "properties": {
    "tgn:hierarchy":[
        "tgn:7043258",
        "tgn:7003168",
        "tgn:1000003",
        "tgn:7009760",
        "tgn:1000080",
        "tgn:7029392"
    ],
    "tgn:id":7043258,
    "tgn:name":"Quercia, Fosso di",
    "tgn:placetype":[
        "aat:300008699"
    ]
},
  "bbox": [],
  "geometry": {"coordinates":[11.733333,42.866667],"type":"Point"}
}