{
  "id": 2504170,
  "type": "Feature",
  "properties": {
    "tgn:hierarchy":[
        "tgn:2504170",
        "tgn:7014651",
        "tgn:1000001",
        "tgn:7012149",
        "tgn:7007516",
        "tgn:7029392"
    ],
    "tgn:id":2504170,
    "tgn:name":"Meadow Point",
    "tgn:placetype":[
        "aat:300008850"
    ]
},
  "bbox": [],
  "geometry": {"coordinates":[-76.4833,38.9833],"type":"Point"}
}