{
  "id": 7109977,
  "type": "Feature",
  "properties": {
    "tgn:hierarchy":[
        "tgn:7109977",
        "tgn:1000003",
        "tgn:7000094",
        "tgn:7000084",
        "tgn:7029392"
    ],
    "tgn:id":7109977,
    "tgn:name":"Putzar",
    "tgn:placetype":[
        "aat:300008347"
    ]
},
  "bbox": [],
  "geometry": {"coordinates":[13.65,53.716667],"type":"Point"}
}