{
  "id": 2265394,
  "type": "Feature",
  "properties": {
    "tgn:hierarchy":[
        "tgn:2265394",
        "tgn:1000001",
        "tgn:2001943",
        "tgn:7012149",
        "tgn:7007826",
        "tgn:7029392"
    ],
    "tgn:id":2265394,
    "tgn:name":"Crane Draw",
    "tgn:placetype":[
        "aat:300008761"
    ]
},
  "bbox": [],
  "geometry": {"coordinates":[-101.6667,32.6833],"type":"Point"}
}