{
  "id": 7590774,
  "type": "Feature",
  "properties": {
    "tgn:hierarchy":[
        "tgn:7590774",
        "tgn:1000004",
        "tgn:7000198",
        "tgn:7000799",
        "tgn:7029392"
    ],
    "tgn:id":7590774,
    "tgn:name:en":"Badw\u0101ni\u0101n",
    "tgn:placetype":[
        "aat:300008347"
    ]
},
  "bbox": [],
  "geometry": {"coordinates":[74.597222,32.847222],"type":"Point"}
}