{
  "id": 1113826,
  "type": "Feature",
  "properties": {
    "tgn:hierarchy":[
        "tgn:1113826",
        "tgn:1000004",
        "tgn:1001610",
        "tgn:1000135",
        "tgn:7029392"
    ],
    "tgn:id":1113826,
    "tgn:name":"Sindangan Bay",
    "tgn:placetype":[
        "aat:300132316"
    ]
},
  "bbox": [],
  "geometry": {"coordinates":[122.8333,8.1833],"type":"Point"}
}