{
  "id": 2729519,
  "type": "Feature",
  "properties": {
    "tgn:hierarchy":[
        "tgn:2729519",
        "tgn:1000001",
        "tgn:7012149",
        "tgn:7007157",
        "tgn:1002972",
        "tgn:7029392"
    ],
    "tgn:id":2729519,
    "tgn:name":"Triunfo Corner",
    "tgn:placetype":[
        "aat:300008347"
    ]
},
  "bbox": [],
  "geometry": {"coordinates":[-118.8167,34.15],"type":"Point"}
}