{
  "id": 2464785,
  "type": "Feature",
  "properties": {
    "tgn:hierarchy":[
        "tgn:2464785",
        "tgn:1000001",
        "tgn:7012149",
        "tgn:2000238",
        "tgn:7007158",
        "tgn:7029392"
    ],
    "tgn:id":2464785,
    "tgn:name":"Logan Hill",
    "tgn:placetype":[
        "aat:300008798"
    ]
},
  "bbox": [],
  "geometry": {"coordinates":[-105.75,39.15],"type":"Point"}
}