{
  "id": 2241081,
  "type": "Feature",
  "properties": {
    "tgn:hierarchy":[
        "tgn:2241081",
        "tgn:1000001",
        "tgn:7012149",
        "tgn:7007522",
        "tgn:7029392"
    ],
    "tgn:id":2241081,
    "tgn:name":"Clark Creek",
    "tgn:placetype":[
        "aat:300008706"
    ]
},
  "bbox": [],
  "geometry": {"coordinates":[-89.5333,33.8667],"type":"Point"}
}