{
  "id": 7409115,
  "type": "Feature",
  "properties": {
    "tgn:hierarchy":[
        "tgn:7409115",
        "tgn:1000001",
        "tgn:7005590",
        "tgn:7005560",
        "tgn:7029392"
    ],
    "tgn:id":7409115,
    "tgn:name":"Huaniqueo",
    "tgn:placetype":[
        "aat:300008347"
    ]
},
  "bbox": [],
  "geometry": {"coordinates":[-100.523611,19.645833],"type":"Point"}
}