<<<<<<< HEAD
{
  "id": 2156765,
  "type": "Feature",
  "properties": {
    "tgn:hierarchy":[
        "tgn:2156765",
        "tgn:1000001",
        "tgn:7012149",
        "tgn:2001293",
        "tgn:7007524",
        "tgn:7029392"
    ],
    "tgn:id":2156765,
    "tgn:name":"Beattie Gulch",
    "tgn:placetype":[
        "aat:300008761"
    ]
},
  "bbox": [],
  "geometry": {"coordinates":[-110.8167,45.05],"type":"Point"}
}
=======
{"geometry":{"type":"Point","coordinates":[-110.816700,45.050000]},"type":"Feature","properties":{"hierarchy":["tgn:2156765","tgn:1000001","tgn:7012149","tgn:2001293","tgn:7007524","tgn:7029392"],"placetype":["aat:300008761"],"id":2156765,"name:xx":"Beattie Gulch"}}
>>>>>>> 03f74aca74312dbeaf24d7e61306dd6a786dc3d0
