{
  "id": 2241193,
  "type": "Feature",
  "properties": {
    "tgn:hierarchy":[
        "tgn:2241193",
        "tgn:1000001",
        "tgn:7012149",
        "tgn:1002746",
        "tgn:7007568",
        "tgn:7029392"
    ],
    "tgn:id":2241193,
    "tgn:name":"Clark Hill",
    "tgn:placetype":[
        "aat:300008798"
    ]
},
  "bbox": [],
  "geometry": {"coordinates":[-76.0167,43.05],"type":"Point"}
}