{
  "id": 2043431,
  "type": "Feature",
  "properties": {
    "tgn:hierarchy":[
        "tgn:2043431",
        "tgn:2000854",
        "tgn:1000001",
        "tgn:7012149",
        "tgn:7007256",
        "tgn:7029392"
    ],
    "tgn:id":2043431,
    "tgn:name":"Mermentau",
    "tgn:placetype":[
        "aat:300008347"
    ]
},
  "bbox": [],
  "geometry": {"coordinates":[-92.5667,30.1833],"type":"Point"}
}