<<<<<<< HEAD
{
  "id": 7054643,
  "type": "Feature",
  "properties": {
    "tgn:hierarchy":[
        "tgn:7054643",
        "tgn:7003134",
        "tgn:1000003",
        "tgn:7008516",
        "tgn:1000080",
        "tgn:7029392"
    ],
    "tgn:id":7054643,
    "tgn:name":"Ponte dell'Agrato",
    "tgn:placetype":[
        "aat:300008347"
    ]
},
  "bbox": [],
  "geometry": {"coordinates":[10.733333,44.716667],"type":"Point"}
}
=======
{"geometry":{"type":"Point","coordinates":[10.733333,44.716667]},"type":"Feature","properties":{"hierarchy":["tgn:7054643","tgn:7003134","tgn:1000003","tgn:7008516","tgn:1000080","tgn:7029392"],"placetype":["aat:300008347"],"id":7054643,"name:xx":"Ponte dell'Agrato"}}
>>>>>>> 03f74aca74312dbeaf24d7e61306dd6a786dc3d0
