{
  "id": 2728127,
  "type": "Feature",
  "properties": {
    "tgn:hierarchy":[
        "tgn:2728127",
        "tgn:1000001",
        "tgn:2001260",
        "tgn:7012149",
        "tgn:7007524",
        "tgn:7029392"
    ],
    "tgn:id":2728127,
    "tgn:name":"Trapper Spring",
    "tgn:placetype":[
        "aat:300008697"
    ]
},
  "bbox": [],
  "geometry": {"coordinates":[-112.7167,45.6333],"type":"Point"}
}