<<<<<<< HEAD
{
  "id": 7376539,
  "type": "Feature",
  "properties": {
    "tgn:hierarchy":[
        "tgn:7376539",
        "tgn:1001835",
        "tgn:1000001",
        "tgn:7005560",
        "tgn:7029392"
    ],
    "tgn:id":7376539,
    "tgn:name":"Rancho Las Lagunitas",
    "tgn:placetype":[
        "aat:300000241"
    ]
},
  "bbox": [],
  "geometry": {"coordinates":[-116.3,32.583333],"type":"Point"}
}
=======
{"geometry":{"type":"Point","coordinates":[-116.300000,32.583333]},"type":"Feature","properties":{"hierarchy":["tgn:7376539","tgn:1001835","tgn:1000001","tgn:7005560","tgn:7029392"],"placetype":["aat:300000241"],"id":7376539,"name:xx":"Rancho Las Lagunitas"}}
>>>>>>> 03f74aca74312dbeaf24d7e61306dd6a786dc3d0
