{
  "id": 2711650,
  "type": "Feature",
  "properties": {
    "tgn:hierarchy":[
        "tgn:2711650",
        "tgn:1000001",
        "tgn:7016172",
        "tgn:2000119",
        "tgn:7012149",
        "tgn:7029392"
    ],
    "tgn:id":2711650,
    "tgn:name":"Tar Kiln Mountain",
    "tgn:placetype":[
        "aat:300008798"
    ]
},
  "bbox": [],
  "geometry": {"coordinates":[-92.75,35.4333],"type":"Point"}
}