{
  "id": 7203128,
  "type": "Feature",
  "properties": {
    "tgn:hierarchy":[
        "tgn:7203128",
        "tgn:1000003",
        "tgn:7003677",
        "tgn:7000084",
        "tgn:7029392"
    ],
    "tgn:id":7203128,
    "tgn:name":"Brochtrup",
    "tgn:placetype":[
        "aat:300387200"
    ]
},
  "bbox": [],
  "geometry": {"coordinates":[7.516667,51.766667],"type":"Point"}
}