<<<<<<< HEAD
{
  "id": 7481078,
  "type": "Feature",
  "properties": {
    "tgn:hierarchy":[
        "tgn:7481078",
        "tgn:7468018",
        "tgn:1000004",
        "tgn:1000141",
        "tgn:7029392"
    ],
    "tgn:id":7481078,
    "tgn:name":"Xincuo Qiao",
    "tgn:placetype":[
        "aat:300007836"
    ]
},
  "bbox": [],
  "geometry": {"coordinates":[120.174537,23.393046],"type":"Point"}
}
=======
{"geometry":{"type":"Point","coordinates":[120.174537,23.393046]},"type":"Feature","properties":{"hierarchy":["tgn:7481078","tgn:7468018","tgn:1000004","tgn:1000141","tgn:7029392"],"placetype":["aat:300007836"],"id":7481078,"name:xx":"Xincuo Qiao"}}
>>>>>>> 03f74aca74312dbeaf24d7e61306dd6a786dc3d0
