{
  "id": 7481078,
  "type": "Feature",
  "properties": {
    "tgn:hierarchy":[
        "tgn:7481078",
        "tgn:7468018",
        "tgn:1000004",
        "tgn:1000141",
        "tgn:7029392"
    ],
    "tgn:id":7481078,
    "tgn:name":"Xincuo Qiao",
    "tgn:placetype":[
        "aat:300007836"
    ]
},
  "bbox": [],
  "geometry": {"coordinates":[120.174537,23.393046],"type":"Point"}
}