{
  "id": 2452387,
  "type": "Feature",
  "properties": {
    "tgn:hierarchy":[
        "tgn:2452387",
        "tgn:1000001",
        "tgn:7012149",
        "tgn:2000927",
        "tgn:7007515",
        "tgn:7029392"
    ],
    "tgn:id":2452387,
    "tgn:name":"Little Bowlin Brook",
    "tgn:placetype":[
        "aat:300008699"
    ]
},
  "bbox": [],
  "geometry": {"coordinates":[-68.6667,46.0333],"type":"Point"}
}