{
  "id": 2109353,
  "type": "Feature",
  "properties": {
    "tgn:hierarchy":[
        "tgn:2109353",
        "tgn:1000001",
        "tgn:7012149",
        "tgn:2002124",
        "tgn:7007827",
        "tgn:7029392"
    ],
    "tgn:id":2109353,
    "tgn:name":"Vernal",
    "tgn:placetype":[
        "aat:300008347"
    ]
},
  "bbox": [],
  "geometry": {"coordinates":[-109.5167,40.45],"type":"Point"}
}