{
  "id": 7332067,
  "type": "Feature",
  "properties": {
    "tgn:hierarchy":[
        "tgn:7332067",
        "tgn:7007088",
        "tgn:1000003",
        "tgn:7009604",
        "tgn:1000095",
        "tgn:7029392"
    ],
    "tgn:id":7332067,
    "tgn:name":"Labraza",
    "tgn:placetype":[
        "aat:300008347"
    ]
},
  "bbox": [],
  "geometry": {"coordinates":[-2.416667,42.566667],"type":"Point"}
}