{
  "id": 7400033,
  "type": "Feature",
  "properties": {
    "tgn:hierarchy":[
        "tgn:7400033",
        "tgn:1000001",
        "tgn:7005593",
        "tgn:7005560",
        "tgn:7029392"
    ],
    "tgn:id":7400033,
    "tgn:name":"Piedra Agujerada, Cerro",
    "tgn:placetype":[
        "aat:300008795"
    ]
},
  "bbox": [],
  "geometry": {"coordinates":[-99.533333,21.266667],"type":"Point"}
}