{
  "id": 2545863,
  "type": "Feature",
  "properties": {
    "tgn:hierarchy":[
        "tgn:2545863",
        "tgn:1000001",
        "tgn:7012149",
        "tgn:2001315",
        "tgn:7007524",
        "tgn:7029392"
    ],
    "tgn:id":2545863,
    "tgn:name":"North Fork Crooked Creek",
    "tgn:placetype":[
        "aat:300008706"
    ]
},
  "bbox": [],
  "geometry": {"coordinates":[-108.5333,46.1167],"type":"Point"}
}