<<<<<<< HEAD
{
  "id": 2330294,
  "type": "Feature",
  "properties": {
    "tgn:hierarchy":[
        "tgn:2330294",
        "tgn:1000001",
        "tgn:7012149",
        "tgn:2000491",
        "tgn:7007250",
        "tgn:7029392"
    ],
    "tgn:id":2330294,
    "tgn:name":"Flash Peak",
    "tgn:placetype":[
        "aat:300008798"
    ]
},
  "bbox": [],
  "geometry": {"coordinates":[-115.8667,47.3],"type":"Point"}
}
=======
{"geometry":{"type":"Point","coordinates":[-115.866700,47.300000]},"type":"Feature","properties":{"hierarchy":["tgn:2330294","tgn:1000001","tgn:7012149","tgn:2000491","tgn:7007250","tgn:7029392"],"placetype":["aat:300008798"],"id":2330294,"name:xx":"Flash Peak"}}
>>>>>>> 03f74aca74312dbeaf24d7e61306dd6a786dc3d0
