{
  "id": 7220893,
  "type": "Feature",
  "properties": {
    "tgn:hierarchy":[
        "tgn:7220893",
        "tgn:7002706",
        "tgn:7002705",
        "tgn:1000003",
        "tgn:1000074",
        "tgn:7029392"
    ],
    "tgn:id":7220893,
    "tgn:name":"\u00c1gios Athan\u00e1sios",
    "tgn:placetype":[
        "aat:300008347"
    ]
},
  "bbox": [],
  "geometry": {"coordinates":[21.139444,39.243056],"type":"Point"}
}