<<<<<<< HEAD
{
  "id": 7474910,
  "type": "Feature",
  "properties": {
    "tgn:hierarchy":[
        "tgn:7474910",
        "tgn:1000004",
        "tgn:7467799",
        "tgn:1000141",
        "tgn:7029392"
    ],
    "tgn:id":7474910,
    "tgn:name":"Fangyuan Haiti",
    "tgn:placetype":[
        "aat:300006156"
    ]
},
  "bbox": [],
  "geometry": {"coordinates":[120.31143,23.921149],"type":"Point"}
}
=======
{"geometry":{"type":"Point","coordinates":[120.311430,23.921149]},"type":"Feature","properties":{"hierarchy":["tgn:7474910","tgn:1000004","tgn:7467799","tgn:1000141","tgn:7029392"],"placetype":["aat:300006156"],"id":7474910,"name:xx":"Fangyuan Haiti"}}
>>>>>>> 03f74aca74312dbeaf24d7e61306dd6a786dc3d0
