{
  "id": 2399180,
  "type": "Feature",
  "properties": {
    "tgn:hierarchy":[
        "tgn:2399180",
        "tgn:1000001",
        "tgn:7012149",
        "tgn:1002593",
        "tgn:7007568",
        "tgn:7029392"
    ],
    "tgn:id":2399180,
    "tgn:name":"Hopsicker Pond",
    "tgn:placetype":[
        "aat:300008680"
    ]
},
  "bbox": [],
  "geometry": {"coordinates":[-75.2667,43.7833],"type":"Point"}
}