{
  "id": 2627825,
  "type": "Feature",
  "properties": {
    "tgn:hierarchy":[
        "tgn:2627825",
        "tgn:1000001",
        "tgn:2001780",
        "tgn:7012149",
        "tgn:7007713",
        "tgn:7029392"
    ],
    "tgn:id":2627825,
    "tgn:name":"Rogo Bay",
    "tgn:placetype":[
        "aat:300132316"
    ]
},
  "bbox": [],
  "geometry": {"coordinates":[-100.3667,45.65],"type":"Point"}
}