{
  "id": 7359846,
  "type": "Feature",
  "properties": {
    "tgn:hierarchy":[
        "tgn:7359846",
        "tgn:1000001",
        "tgn:1001960",
        "tgn:7005560",
        "tgn:7029392"
    ],
    "tgn:id":7359846,
    "tgn:name":"Dorantes",
    "tgn:placetype":[
        "aat:300387007"
    ]
},
  "bbox": [],
  "geometry": {"coordinates":[-109.933333,29.583333],"type":"Point"}
}