<<<<<<< HEAD
{
  "id": 7359846,
  "type": "Feature",
  "properties": {
    "tgn:hierarchy":[
        "tgn:7359846",
        "tgn:1000001",
        "tgn:1001960",
        "tgn:7005560",
        "tgn:7029392"
    ],
    "tgn:id":7359846,
    "tgn:name":"Dorantes",
    "tgn:placetype":[
        "aat:300387007"
    ]
},
  "bbox": [],
  "geometry": {"coordinates":[-109.933333,29.583333],"type":"Point"}
}
=======
{"geometry":{"type":"Point","coordinates":[-109.933333,29.583333]},"type":"Feature","properties":{"hierarchy":["tgn:7359846","tgn:1000001","tgn:1001960","tgn:7005560","tgn:7029392"],"placetype":["aat:300387007"],"id":7359846,"name:xx":"Dorantes"}}
>>>>>>> 03f74aca74312dbeaf24d7e61306dd6a786dc3d0
