{
  "id": 1045320,
  "type": "Feature",
  "properties": {
    "tgn:hierarchy":[
        "tgn:1045320",
        "tgn:1001724",
        "tgn:1000003",
        "tgn:7003121",
        "tgn:1000080",
        "tgn:7029392"
    ],
    "tgn:id":1045320,
    "tgn:name":"Meana Sardo",
    "tgn:placetype":[
        "aat:300008347"
    ]
},
  "bbox": [],
  "geometry": {"coordinates":[9.072222,39.945833],"type":"Point"}
}