{
  "id": 2706112,
  "type": "Feature",
  "properties": {
    "tgn:hierarchy":[
        "tgn:2706112",
        "tgn:1000001",
        "tgn:7006451",
        "tgn:7012149",
        "tgn:2000098",
        "tgn:7029392"
    ],
    "tgn:id":2706112,
    "tgn:name":"Swale Tank",
    "tgn:placetype":[
        "aat:300006191"
    ]
},
  "bbox": [],
  "geometry": {"coordinates":[-113.3667,34.75],"type":"Point"}
}