{
  "id": 7365225,
  "type": "Feature",
  "properties": {
    "tgn:hierarchy":[
        "tgn:7365225",
        "tgn:1000001",
        "tgn:7005596",
        "tgn:7005560",
        "tgn:7029392"
    ],
    "tgn:id":7365225,
    "tgn:name":"Emilio Lopez Zamora",
    "tgn:placetype":[
        "aat:300008347"
    ]
},
  "bbox": [],
  "geometry": {"coordinates":[-91.066667,17.783333],"type":"Point"}
}