{
  "id": 2386536,
  "type": "Feature",
  "properties": {
    "tgn:hierarchy":[
        "tgn:2386536",
        "tgn:1000001",
        "tgn:7012149",
        "tgn:2000441",
        "tgn:7007248",
        "tgn:7029392"
    ],
    "tgn:id":2386536,
    "tgn:name":"Herds Pond",
    "tgn:placetype":[
        "aat:300006191"
    ]
},
  "bbox": [],
  "geometry": {"coordinates":[-83.8833,32.7667],"type":"Point"}
}