<<<<<<< HEAD
{
  "id": 7375164,
  "type": "Feature",
  "properties": {
    "tgn:hierarchy":[
        "tgn:7375164",
        "tgn:1001853",
        "tgn:1000001",
        "tgn:7005560",
        "tgn:7029392"
    ],
    "tgn:id":7375164,
    "tgn:name":"Rancho del Le\u00f3n",
    "tgn:placetype":[
        "aat:300000241"
    ]
},
  "bbox": [],
  "geometry": {"coordinates":[-101.4,28.95],"type":"Point"}
}
=======
{"geometry":{"type":"Point","coordinates":[-101.400000,28.950000]},"type":"Feature","properties":{"hierarchy":["tgn:7375164","tgn:1001853","tgn:1000001","tgn:7005560","tgn:7029392"],"placetype":["aat:300000241"],"id":7375164,"name:xx":"Rancho del Le\u00f3n"}}
>>>>>>> 03f74aca74312dbeaf24d7e61306dd6a786dc3d0
