{
  "id": 2452408,
  "type": "Feature",
  "properties": {
    "tgn:hierarchy":[
        "tgn:2452408",
        "tgn:2001001",
        "tgn:1000001",
        "tgn:7012149",
        "tgn:7007521",
        "tgn:7029392"
    ],
    "tgn:id":2452408,
    "tgn:name":"Little Boyer Lake",
    "tgn:placetype":[
        "aat:300008680"
    ]
},
  "bbox": [],
  "geometry": {"coordinates":[-96.05,46.8667],"type":"Point"}
}