{
  "id": 7035282,
  "type": "Feature",
  "properties": {
    "tgn:hierarchy":[
        "tgn:7035282",
        "tgn:7003006",
        "tgn:1000003",
        "tgn:7002997",
        "tgn:1000080",
        "tgn:7029392"
    ],
    "tgn:id":7035282,
    "tgn:name":"Reghena",
    "tgn:placetype":[
        "aat:300008699"
    ]
},
  "bbox": [],
  "geometry": {"coordinates":[12.834722,45.770833],"type":"Point"}
}