{
  "id": 2005486,
  "type": "Feature",
  "properties": {
    "tgn:hierarchy":[
        "tgn:2005486",
        "tgn:7002659",
        "tgn:1000001",
        "tgn:7012149",
        "tgn:2000029",
        "tgn:7029392"
    ],
    "tgn:id":2005486,
    "tgn:name":"Tharptown",
    "tgn:placetype":[
        "aat:300008347"
    ]
},
  "bbox": [],
  "geometry": {"coordinates":[-87.6167,34.5167],"type":"Point"}
}