{
  "id": 7286957,
  "type": "Feature",
  "properties": {
    "tgn:hierarchy":[
        "tgn:7286957",
        "tgn:1001702",
        "tgn:1000049",
        "tgn:1000002",
        "tgn:7029392"
    ],
    "tgn:id":7286957,
    "tgn:name":"Glaura, Punta",
    "tgn:placetype":[
        "aat:300386846"
    ]
},
  "bbox": [],
  "geometry": {"coordinates":[-72.966667,-53.033333],"type":"Point"}
}