{
  "id": 7522262,
  "type": "Feature",
  "properties": {
    "tgn:hierarchy":[
        "tgn:7522262",
        "tgn:7001242",
        "tgn:7016833",
        "tgn:1001114",
        "tgn:7029392"
    ],
    "tgn:id":7522262,
    "tgn:name:en":"Al \u1e28ar\u0101dinah",
    "tgn:placetype":[
        "aat:300008347"
    ]
},
  "bbox": [],
  "geometry": {"coordinates":[30.802993,27.420467],"type":"Point"}
}