<<<<<<< HEAD
{
  "id": 7358627,
  "type": "Feature",
  "properties": {
    "tgn:hierarchy":[
        "tgn:7358627",
        "tgn:1000001",
        "tgn:7005600",
        "tgn:7005560",
        "tgn:7029392"
    ],
    "tgn:id":7358627,
    "tgn:name":"Cozamil",
    "tgn:placetype":[
        "aat:300008347"
    ]
},
  "bbox": [],
  "geometry": {"coordinates":[-88.366667,20.433333],"type":"Point"}
}
=======
{"geometry":{"type":"Point","coordinates":[-88.366667,20.433333]},"type":"Feature","properties":{"hierarchy":["tgn:7358627","tgn:1000001","tgn:7005600","tgn:7005560","tgn:7029392"],"placetype":["aat:300008347"],"id":7358627,"name:xx":"Cozamil"}}
>>>>>>> 03f74aca74312dbeaf24d7e61306dd6a786dc3d0
