{
  "id": 7281653,
  "type": "Feature",
  "properties": {
    "tgn:hierarchy":[
        "tgn:7281653",
        "tgn:1001623",
        "tgn:1000049",
        "tgn:1000002",
        "tgn:7029392"
    ],
    "tgn:id":7281653,
    "tgn:name":"Su\u00e1rez, Punta",
    "tgn:placetype":[
        "aat:300386846"
    ]
},
  "bbox": [],
  "geometry": {"coordinates":[-74.183333,-47.016667],"type":"Point"}
}