{
  "id": 1019369,
  "type": "Feature",
  "properties": {
    "tgn:hierarchy":[
        "tgn:1019369",
        "tgn:7006477",
        "tgn:1001237",
        "tgn:1000002",
        "tgn:7029392"
    ],
    "tgn:id":1019369,
    "tgn:name":"Crespo",
    "tgn:placetype":[
        "aat:300008347"
    ]
},
  "bbox": [],
  "geometry": {"coordinates":[-60.3333,-32.0833],"type":"Point"}
}