<<<<<<< HEAD
{
  "id": 2254268,
  "type": "Feature",
  "properties": {
    "tgn:hierarchy":[
        "tgn:2254268",
        "tgn:1000001",
        "tgn:7012149",
        "tgn:7007157",
        "tgn:2000184",
        "tgn:7029392"
    ],
    "tgn:id":2254268,
    "tgn:name":"Coon Camp Spring",
    "tgn:placetype":[
        "aat:300008697"
    ]
},
  "bbox": [],
  "geometry": {"coordinates":[-120.7833,40.8667],"type":"Point"}
}
=======
{"geometry":{"type":"Point","coordinates":[-120.783300,40.866700]},"type":"Feature","properties":{"hierarchy":["tgn:2254268","tgn:1000001","tgn:7012149","tgn:7007157","tgn:2000184","tgn:7029392"],"placetype":["aat:300008697"],"id":2254268,"name:xx":"Coon Camp Spring"}}
>>>>>>> 03f74aca74312dbeaf24d7e61306dd6a786dc3d0
