{
  "id": 2320825,
  "type": "Feature",
  "properties": {
    "tgn:hierarchy":[
        "tgn:2320825",
        "tgn:1000001",
        "tgn:7012149",
        "tgn:2002374",
        "tgn:7007923",
        "tgn:7029392"
    ],
    "tgn:id":2320825,
    "tgn:name":"Eychaner Reservoir",
    "tgn:placetype":[
        "aat:300006191"
    ]
},
  "bbox": [],
  "geometry": {"coordinates":[-107.0167,43.9333],"type":"Point"}
}