{
  "id": 7232845,
  "type": "Feature",
  "properties": {
    "tgn:hierarchy":[
        "tgn:7232845",
        "tgn:7002739",
        "tgn:7017076",
        "tgn:1000003",
        "tgn:1000074",
        "tgn:7029392"
    ],
    "tgn:id":7232845,
    "tgn:name":"\u00cdria, \u00c1kra",
    "tgn:placetype":[
        "aat:300008850"
    ]
},
  "bbox": [],
  "geometry": {"coordinates":[23.003566,37.460011],"type":"Point"}
}