<<<<<<< HEAD
{
  "id": 2334303,
  "type": "Feature",
  "properties": {
    "tgn:hierarchy":[
        "tgn:2334303",
        "tgn:1000001",
        "tgn:7012149",
        "tgn:7007157",
        "tgn:1002859",
        "tgn:7029392"
    ],
    "tgn:id":2334303,
    "tgn:name":"Forest Hill",
    "tgn:placetype":[
        "aat:300008347"
    ]
},
  "bbox": [],
  "geometry": {"coordinates":[-122.45,37.7333],"type":"Point"}
}
=======
{"geometry":{"type":"Point","coordinates":[-122.450000,37.733300]},"type":"Feature","properties":{"hierarchy":["tgn:2334303","tgn:1000001","tgn:7012149","tgn:7007157","tgn:1002859","tgn:7029392"],"placetype":["aat:300008347"],"id":2334303,"name:xx":"Forest Hill"}}
>>>>>>> 03f74aca74312dbeaf24d7e61306dd6a786dc3d0
