{
  "id": 2244591,
  "type": "Feature",
  "properties": {
    "tgn:hierarchy":[
        "tgn:2244591",
        "tgn:1000001",
        "tgn:7012149",
        "tgn:2001697",
        "tgn:7007707",
        "tgn:7029392"
    ],
    "tgn:id":2244591,
    "tgn:name":"Clinton Lake",
    "tgn:placetype":[
        "aat:300006191"
    ]
},
  "bbox": [],
  "geometry": {"coordinates":[-99.2167,35.4333],"type":"Point"}
}