{
  "id": 7475666,
  "type": "Feature",
  "properties": {
    "tgn:hierarchy":[
        "tgn:7475666",
        "tgn:7488858",
        "tgn:1000004",
        "tgn:1000141",
        "tgn:7029392"
    ],
    "tgn:id":7475666,
    "tgn:name":"Zhongkeng",
    "tgn:placetype":[
        "aat:300008347"
    ]
},
  "bbox": [],
  "geometry": {"coordinates":[120.838495,23.761789],"type":"Point"}
}