{
  "id": 7513565,
  "type": "Feature",
  "properties": {
    "tgn:hierarchy":[
        "tgn:7513565",
        "tgn:1009227",
        "tgn:1000226",
        "tgn:1000006",
        "tgn:7016850",
        "tgn:7029392"
    ],
    "tgn:id":7513565,
    "tgn:name:en":"Geologist Creek",
    "tgn:placetype":[
        "aat:300008699"
    ]
},
  "bbox": [],
  "geometry": {"coordinates":[171.15,-42.866667],"type":"Point"}
}