{
  "id": 7342533,
  "type": "Feature",
  "properties": {
    "tgn:hierarchy":[
        "tgn:7342533",
        "tgn:7002818",
        "tgn:1001647",
        "tgn:1000003",
        "tgn:1000095",
        "tgn:7029392"
    ],
    "tgn:id":7342533,
    "tgn:name":"Castej\u00f3n",
    "tgn:placetype":[
        "aat:300008347"
    ]
},
  "bbox": [],
  "geometry": {"coordinates":[-2.516667,40.383333],"type":"Point"}
}