{
  "id": 2078453,
  "type": "Feature",
  "properties": {
    "tgn:hierarchy":[
        "tgn:2078453",
        "tgn:1000001",
        "tgn:7012149",
        "tgn:1002476",
        "tgn:7007706",
        "tgn:7029392"
    ],
    "tgn:id":2078453,
    "tgn:name":"Berrysville",
    "tgn:placetype":[
        "aat:300008347"
    ]
},
  "bbox": [],
  "geometry": {"coordinates":[-83.55,39.1167],"type":"Point"}
}