{
  "id": 2182032,
  "type": "Feature",
  "properties": {
    "tgn:hierarchy":[
        "tgn:2182032",
        "tgn:1000001",
        "tgn:7012149",
        "tgn:2000219",
        "tgn:7007158",
        "tgn:7029392"
    ],
    "tgn:id":2182032,
    "tgn:name":"Blue Lakes",
    "tgn:placetype":[
        "aat:300008680"
    ]
},
  "bbox": [],
  "geometry": {"coordinates":[-105.0333,37.8833],"type":"Point"}
}