{
  "id": 7195869,
  "type": "Feature",
  "properties": {
    "tgn:hierarchy":[
        "tgn:7195869",
        "tgn:1000003",
        "tgn:7003678",
        "tgn:7000084",
        "tgn:7029392"
    ],
    "tgn:id":7195869,
    "tgn:name":"Dickenr\u00fcck",
    "tgn:placetype":[
        "aat:300000206"
    ]
},
  "bbox": [],
  "geometry": {"coordinates":[9.75,50.966667],"type":"Point"}
}