{
  "id": 2131825,
  "type": "Feature",
  "properties": {
    "tgn:hierarchy":[
        "tgn:2131825",
        "tgn:1000001",
        "tgn:2001411",
        "tgn:7012149",
        "tgn:7007526",
        "tgn:7029392"
    ],
    "tgn:id":2131825,
    "tgn:name":"Amazon Mine",
    "tgn:placetype":[
        "aat:300000390"
    ]
},
  "bbox": [],
  "geometry": {"coordinates":[-116.4333,41.4667],"type":"Point"}
}