<<<<<<< HEAD
{
  "id": 2406299,
  "type": "Feature",
  "properties": {
    "tgn:hierarchy":[
        "tgn:2406299",
        "tgn:7006450",
        "tgn:1000001",
        "tgn:7019698",
        "tgn:7012149",
        "tgn:7029392"
    ],
    "tgn:id":2406299,
    "tgn:name":"Humpy Creek",
    "tgn:placetype":[
        "aat:300008706"
    ]
},
  "bbox": [],
  "geometry": {"coordinates":[-151.0167,59.6],"type":"Point"}
}
=======
{"geometry":{"type":"Point","coordinates":[-151.016700,59.600000]},"type":"Feature","properties":{"hierarchy":["tgn:2406299","tgn:7006450","tgn:1000001","tgn:7019698","tgn:7012149","tgn:7029392"],"placetype":["aat:300008706"],"id":2406299,"name:xx":"Humpy Creek"}}
>>>>>>> 03f74aca74312dbeaf24d7e61306dd6a786dc3d0
