{
  "id": 2534590,
  "type": "Feature",
  "properties": {
    "tgn:hierarchy":[
        "tgn:2534590",
        "tgn:1000001",
        "tgn:7012149",
        "tgn:2001281",
        "tgn:7007524",
        "tgn:7029392"
    ],
    "tgn:id":2534590,
    "tgn:name":"NW SW Section 24 Mine",
    "tgn:placetype":[
        "aat:300000390"
    ]
},
  "bbox": [],
  "geometry": {"coordinates":[-111.9167,46.4167],"type":"Point"}
}