{
  "id": 2662566,
  "type": "Feature",
  "properties": {
    "tgn:hierarchy":[
        "tgn:2662566",
        "tgn:1000001",
        "tgn:7012149",
        "tgn:2000234",
        "tgn:7007158",
        "tgn:7029392"
    ],
    "tgn:id":2662566,
    "tgn:name":"Signal Hill",
    "tgn:placetype":[
        "aat:300008798"
    ]
},
  "bbox": [],
  "geometry": {"coordinates":[-107.6833,38.5167],"type":"Point"}
}