{
  "id": 2686278,
  "type": "Feature",
  "properties": {
    "tgn:hierarchy":[
        "tgn:2686278",
        "tgn:1000001",
        "tgn:7012149",
        "tgn:2000219",
        "tgn:7007158",
        "tgn:7029392"
    ],
    "tgn:id":2686278,
    "tgn:name":"Spring Creek",
    "tgn:placetype":[
        "aat:300008706"
    ]
},
  "bbox": [],
  "geometry": {"coordinates":[-105.1167,37.3667],"type":"Point"}
}