{
  "id": 2347176,
  "type": "Feature",
  "properties": {
    "tgn:hierarchy":[
        "tgn:2347176",
        "tgn:1000001",
        "tgn:7012149",
        "tgn:7007250",
        "tgn:7029392"
    ],
    "tgn:id":2347176,
    "tgn:name":"Gentile Valley",
    "tgn:placetype":[
        "aat:300008761"
    ]
},
  "bbox": [],
  "geometry": {"coordinates":[-111.7833,42.5167],"type":"Point"}
}