{
  "id": 2216841,
  "type": "Feature",
  "properties": {
    "tgn:hierarchy":[
        "tgn:2216841",
        "tgn:1000001",
        "tgn:7012149",
        "tgn:7007157",
        "tgn:1002863",
        "tgn:7029392"
    ],
    "tgn:id":2216841,
    "tgn:name":"Camp Hill",
    "tgn:placetype":[
        "aat:300008798"
    ]
},
  "bbox": [],
  "geometry": {"coordinates":[-120.6333,35.1333],"type":"Point"}
}