{
  "id": 2536175,
  "type": "Feature",
  "properties": {
    "tgn:hierarchy":[
        "tgn:2536175",
        "tgn:1000001",
        "tgn:7006451",
        "tgn:2000092",
        "tgn:7012149",
        "tgn:7029392"
    ],
    "tgn:id":2536175,
    "tgn:name":"Nautiloid Creek",
    "tgn:placetype":[
        "aat:300008706"
    ]
},
  "bbox": [],
  "geometry": {"coordinates":[-111.7833,36.4833],"type":"Point"}
}