{
  "id": 7038371,
  "type": "Feature",
  "properties": {
    "tgn:hierarchy":[
        "tgn:7038371",
        "tgn:7009084",
        "tgn:7003000",
        "tgn:1000003",
        "tgn:1000080",
        "tgn:7029392"
    ],
    "tgn:id":7038371,
    "tgn:name":"Torino di Sangro",
    "tgn:placetype":[
        "aat:300008347"
    ]
},
  "bbox": [],
  "geometry": {"coordinates":[14.533333,42.183333],"type":"Point"}
}