{
  "id": 1134335,
  "type": "Feature",
  "properties": {
    "tgn:hierarchy":[
        "tgn:1134335",
        "tgn:1000001",
        "tgn:7012149",
        "tgn:7007826",
        "tgn:7029392"
    ],
    "tgn:id":1134335,
    "tgn:name":"Red Oak Creek",
    "tgn:placetype":[
        "aat:300008706"
    ]
},
  "bbox": [],
  "geometry": {"coordinates":[-96.95,32.5833],"type":"Point"}
}