{
  "id": 7041617,
  "type": "Feature",
  "properties": {
    "tgn:hierarchy":[
        "tgn:7041617",
        "tgn:1001730",
        "tgn:1000003",
        "tgn:7003121",
        "tgn:1000080",
        "tgn:7029392"
    ],
    "tgn:id":7041617,
    "tgn:name":"San Giovanni di Sinis",
    "tgn:placetype":[
        "aat:300008347"
    ]
},
  "bbox": [],
  "geometry": {"coordinates":[8.44,39.881944],"type":"Point"}
}