{
  "id": 1123822,
  "type": "Feature",
  "properties": {
    "tgn:hierarchy":[
        "tgn:1123822",
        "tgn:7011701",
        "tgn:1000003",
        "tgn:7006657",
        "tgn:7029392"
    ],
    "tgn:id":1123822,
    "tgn:name":"Esa",
    "tgn:placetype":[
        "aat:300008707"
    ]
},
  "bbox": [],
  "geometry": {"coordinates":[28.675,54.89],"type":"Point"}
}