{
  "id": 2457255,
  "type": "Feature",
  "properties": {
    "tgn:hierarchy":[
        "tgn:2457255",
        "tgn:1000001",
        "tgn:7012149",
        "tgn:2001519",
        "tgn:7007709",
        "tgn:7029392"
    ],
    "tgn:id":2457255,
    "tgn:name":"Little Laurel Branch",
    "tgn:placetype":[
        "aat:300008699"
    ]
},
  "bbox": [],
  "geometry": {"coordinates":[-82.0167,35.9167],"type":"Point"}
}