{
  "id": 7087575,
  "type": "Feature",
  "properties": {
    "tgn:hierarchy":[
        "tgn:7087575",
        "tgn:7003669",
        "tgn:1000003",
        "tgn:7000084",
        "tgn:7029392"
    ],
    "tgn:id":7087575,
    "tgn:name":"Wegerts\u00f6d",
    "tgn:placetype":[
        "aat:300000206"
    ]
},
  "bbox": [],
  "geometry": {"coordinates":[13.233333,48.45],"type":"Point"}
}