{
  "id": 2233076,
  "type": "Feature",
  "properties": {
    "tgn:hierarchy":[
        "tgn:2233076",
        "tgn:1000001",
        "tgn:7012149",
        "tgn:2000488",
        "tgn:7007250",
        "tgn:7029392"
    ],
    "tgn:id":2233076,
    "tgn:name":"Charity Spring",
    "tgn:placetype":[
        "aat:300008697"
    ]
},
  "bbox": [],
  "geometry": {"coordinates":[-116.5333,42.8833],"type":"Point"}
}