<<<<<<< HEAD
{
  "id": 2155507,
  "type": "Feature",
  "properties": {
    "tgn:hierarchy":[
        "tgn:2155507",
        "tgn:1000001",
        "tgn:7012149",
        "tgn:1002767",
        "tgn:7007920",
        "tgn:7029392"
    ],
    "tgn:id":2155507,
    "tgn:name":"Bear River",
    "tgn:placetype":[
        "aat:300008707"
    ]
},
  "bbox": [],
  "geometry": {"coordinates":[-123.9,46.3333],"type":"Point"}
}
=======
{"geometry":{"type":"Point","coordinates":[-123.900000,46.333300]},"type":"Feature","properties":{"hierarchy":["tgn:2155507","tgn:1000001","tgn:7012149","tgn:1002767","tgn:7007920","tgn:7029392"],"placetype":["aat:300008707"],"id":2155507,"name:xx":"Bear River"}}
>>>>>>> 03f74aca74312dbeaf24d7e61306dd6a786dc3d0
