<<<<<<< HEAD
{
  "id": 2157098,
  "type": "Feature",
  "properties": {
    "tgn:hierarchy":[
        "tgn:2157098",
        "tgn:1002300",
        "tgn:1000001",
        "tgn:7012149",
        "tgn:7007564",
        "tgn:7029392"
    ],
    "tgn:id":2157098,
    "tgn:name":"Beaver Brook",
    "tgn:placetype":[
        "aat:300008699"
    ]
},
  "bbox": [],
  "geometry": {"coordinates":[-71.5,44.8333],"type":"Point"}
}
=======
{"geometry":{"type":"Point","coordinates":[-71.500000,44.833300]},"type":"Feature","properties":{"hierarchy":["tgn:2157098","tgn:1002300","tgn:1000001","tgn:7012149","tgn:7007564","tgn:7029392"],"placetype":["aat:300008699"],"id":2157098,"name:xx":"Beaver Brook"}}
>>>>>>> 03f74aca74312dbeaf24d7e61306dd6a786dc3d0
