{
  "id": 2232496,
  "type": "Feature",
  "properties": {
    "tgn:hierarchy":[
        "tgn:2232496",
        "tgn:1000001",
        "tgn:7006451",
        "tgn:7012149",
        "tgn:2000097",
        "tgn:7029392"
    ],
    "tgn:id":2232496,
    "tgn:name":"Chaparral",
    "tgn:placetype":[
        "aat:300008347"
    ]
},
  "bbox": [],
  "geometry": {"coordinates":[-112.1667,33.6333],"type":"Point"}
}