{
  "id": 2578918,
  "type": "Feature",
  "properties": {
    "tgn:hierarchy":[
        "tgn:2578918",
        "tgn:1000001",
        "tgn:2001432",
        "tgn:7012149",
        "tgn:7007566",
        "tgn:7029392"
    ],
    "tgn:id":2578918,
    "tgn:name":"Phillips, Mount",
    "tgn:placetype":[
        "aat:300008798"
    ]
},
  "bbox": [],
  "geometry": {"coordinates":[-105.15,36.4667],"type":"Point"}
}