{
  "id": 2072181,
  "type": "Feature",
  "properties": {
    "tgn:hierarchy":[
        "tgn:2072181",
        "tgn:1000001",
        "tgn:7012149",
        "tgn:2001461",
        "tgn:7007568",
        "tgn:7029392"
    ],
    "tgn:id":2072181,
    "tgn:name":"Schroon Lake",
    "tgn:placetype":[
        "aat:300008347"
    ]
},
  "bbox": [],
  "geometry": {"coordinates":[-73.75,43.8333],"type":"Point"}
}