{
  "id": 1045395,
  "type": "Feature",
  "properties": {
    "tgn:hierarchy":[
        "tgn:1045395",
        "tgn:7024843",
        "tgn:1000003",
        "tgn:7008516",
        "tgn:1000080",
        "tgn:7029392"
    ],
    "tgn:id":1045395,
    "tgn:name":"Miramare",
    "tgn:placetype":[
        "aat:300008347"
    ]
},
  "bbox": [],
  "geometry": {"coordinates":[12.624444,44.035278],"type":"Point"}
}