<<<<<<< HEAD
{
  "id": 7026478,
  "type": "Feature",
  "properties": {
    "tgn:hierarchy":[
        "tgn:7026478",
        "tgn:7002445",
        "tgn:1000003",
        "tgn:7008168",
        "tgn:7008591",
        "tgn:7029392"
    ],
    "tgn:id":7026478,
    "tgn:name:en":"Watchfield",
    "tgn:placetype":[
        "aat:300008347",
        "aat:300008372"
    ]
},
  "bbox": [],
  "geometry": {"coordinates":[-1.633333,51.6],"type":"Point"}
}
=======
{"geometry":{"type":"Point","coordinates":[-1.633333,51.600000]},"type":"Feature","properties":{"hierarchy":["tgn:7026478","tgn:7002445","tgn:1000003","tgn:7008168","tgn:7008591","tgn:7029392"],"placetype":["aat:300008347","aat:300008372"],"name:en":"Watchfield","id":7026478}}
>>>>>>> 03f74aca74312dbeaf24d7e61306dd6a786dc3d0
