{
  "id": 2701226,
  "type": "Feature",
  "properties": {
    "tgn:hierarchy":[
        "tgn:2701226",
        "tgn:1000001",
        "tgn:1002840",
        "tgn:7012149",
        "tgn:7007828",
        "tgn:7029392"
    ],
    "tgn:id":2701226,
    "tgn:name":"Sugar Hollow Pond",
    "tgn:placetype":[
        "aat:300008680"
    ]
},
  "bbox": [],
  "geometry": {"coordinates":[-73.0167,43.75],"type":"Point"}
}