{
  "id": 2560296,
  "type": "Feature",
  "properties": {
    "tgn:hierarchy":[
        "tgn:2560296",
        "tgn:1000001",
        "tgn:7012149",
        "tgn:2002129",
        "tgn:7007827",
        "tgn:7029392"
    ],
    "tgn:id":2560296,
    "tgn:name":"Orchard Grove Addition",
    "tgn:placetype":[
        "aat:300008347"
    ]
},
  "bbox": [],
  "geometry": {"coordinates":[-111.9667,41.25],"type":"Point"}
}