{
  "id": 1064403,
  "type": "Feature",
  "properties": {
    "tgn:hierarchy":[
        "tgn:1064403",
        "tgn:1000003",
        "tgn:7003755",
        "tgn:7011731",
        "tgn:7029392"
    ],
    "tgn:id":1064403,
    "tgn:name":"Sennwald",
    "tgn:placetype":[
        "aat:300008347"
    ]
},
  "bbox": [],
  "geometry": {"coordinates":[9.5167,47.2667],"type":"Point"}
}