{
  "id": 2475977,
  "type": "Feature",
  "properties": {
    "tgn:hierarchy":[
        "tgn:2475977",
        "tgn:1000001",
        "tgn:7012149",
        "tgn:2001504",
        "tgn:7007709",
        "tgn:7029392"
    ],
    "tgn:id":2475977,
    "tgn:name":"Lugana Lake",
    "tgn:placetype":[
        "aat:300006191"
    ]
},
  "bbox": [],
  "geometry": {"coordinates":[-82.4667,35.3167],"type":"Point"}
}