{
  "id": 2605678,
  "type": "Feature",
  "properties": {
    "tgn:hierarchy":[
        "tgn:2605678",
        "tgn:1000001",
        "tgn:7006451",
        "tgn:2000092",
        "tgn:7012149",
        "tgn:7029392"
    ],
    "tgn:id":2605678,
    "tgn:name":"Railroad Trick Tank",
    "tgn:placetype":[
        "aat:300006191"
    ]
},
  "bbox": [],
  "geometry": {"coordinates":[-111.4667,35.0333],"type":"Point"}
}