{
  "id": 1011807,
  "type": "Feature",
  "properties": {
    "tgn:hierarchy":[
        "tgn:1011807",
        "tgn:1006959",
        "tgn:1000004",
        "tgn:1001556",
        "tgn:1000135",
        "tgn:7029392"
    ],
    "tgn:id":1011807,
    "tgn:name":"Desolation Point",
    "tgn:placetype":[
        "aat:300386846"
    ]
},
  "bbox": [],
  "geometry": {"coordinates":[125.65,10.4667],"type":"Point"}
}