<<<<<<< HEAD
{
  "id": 7488288,
  "type": "Feature",
  "properties": {
    "tgn:hierarchy":[
        "tgn:7488288",
        "tgn:7469009",
        "tgn:1000004",
        "tgn:1000141",
        "tgn:7029392"
    ],
    "tgn:id":7488288,
    "tgn:name":"Huxia",
    "tgn:placetype":[
        "aat:300008347"
    ]
},
  "bbox": [],
  "geometry": {"coordinates":[118.254167,24.430278],"type":"Point"}
}
=======
{"geometry":{"type":"Point","coordinates":[118.254167,24.430278]},"type":"Feature","properties":{"hierarchy":["tgn:7488288","tgn:7469009","tgn:1000004","tgn:1000141","tgn:7029392"],"placetype":["aat:300008347"],"id":7488288,"name:xx":"Huxia"}}
>>>>>>> 03f74aca74312dbeaf24d7e61306dd6a786dc3d0
