{
  "id": 7503321,
  "type": "Feature",
  "properties": {
    "tgn:hierarchy":[
        "tgn:7503321",
        "tgn:1000004",
        "tgn:7004300",
        "tgn:1000141",
        "tgn:7029392"
    ],
    "tgn:id":7503321,
    "tgn:name":"Daping",
    "tgn:placetype":[
        "aat:300386846"
    ]
},
  "bbox": [],
  "geometry": {"coordinates":[119.680278,23.260278],"type":"Point"}
}