{
  "id": 7290743,
  "type": "Feature",
  "properties": {
    "tgn:hierarchy":[
        "tgn:7290743",
        "tgn:1001702",
        "tgn:1000049",
        "tgn:1000002",
        "tgn:7029392"
    ],
    "tgn:id":7290743,
    "tgn:name":"Desolada, Bah\u00eda",
    "tgn:placetype":[
        "aat:300132316"
    ]
},
  "bbox": [],
  "geometry": {"coordinates":[-71.416667,-54.75],"type":"Point"}
}