{
  "id": 2410684,
  "type": "Feature",
  "properties": {
    "tgn:hierarchy":[
        "tgn:2410684",
        "tgn:1000001",
        "tgn:7012149",
        "tgn:2000290",
        "tgn:7007240",
        "tgn:7029392"
    ],
    "tgn:id":2410684,
    "tgn:name":"Indian Creek",
    "tgn:placetype":[
        "aat:300008706"
    ]
},
  "bbox": [],
  "geometry": {"coordinates":[-86.0667,30.6833],"type":"Point"}
}