{
  "id": 1067006,
  "type": "Feature",
  "properties": {
    "tgn:hierarchy":[
        "tgn:1067006",
        "tgn:1000004",
        "tgn:7002081",
        "tgn:1000111",
        "tgn:7029392"
    ],
    "tgn:id":1067006,
    "tgn:name":"Caopu",
    "tgn:placetype":[
        "aat:300008347"
    ]
},
  "bbox": [],
  "geometry": {"coordinates":[118.8167,34.5667],"type":"Point"}
}