{
  "id": 2569145,
  "type": "Feature",
  "properties": {
    "tgn:hierarchy":[
        "tgn:2569145",
        "tgn:1000001",
        "tgn:1002275",
        "tgn:7012149",
        "tgn:7007920",
        "tgn:7029392"
    ],
    "tgn:id":2569145,
    "tgn:name":"Parkersville",
    "tgn:placetype":[
        "aat:300008347"
    ]
},
  "bbox": [],
  "geometry": {"coordinates":[-122.3667,45.5667],"type":"Point"}
}