{
  "id": 1097483,
  "type": "Feature",
  "properties": {
    "tgn:hierarchy":[
        "tgn:1097483",
        "tgn:7000490",
        "tgn:1000006",
        "tgn:7001830",
        "tgn:7029392"
    ],
    "tgn:id":1097483,
    "tgn:name":"Marlborough",
    "tgn:placetype":[
        "aat:300008347"
    ]
},
  "bbox": [],
  "geometry": {"coordinates":[149.8333,-22.85],"type":"Point"}
}