{
  "id": 2719168,
  "type": "Feature",
  "properties": {
    "tgn:hierarchy":[
        "tgn:2719168",
        "tgn:1000001",
        "tgn:2001415",
        "tgn:7012149",
        "tgn:7007526",
        "tgn:7029392"
    ],
    "tgn:id":2719168,
    "tgn:name":"Thorpe Canyon",
    "tgn:placetype":[
        "aat:300008761"
    ]
},
  "bbox": [],
  "geometry": {"coordinates":[-117.0333,39.4833],"type":"Point"}
}