{
  "id": 7208250,
  "type": "Feature",
  "properties": {
    "tgn:hierarchy":[
        "tgn:7208250",
        "tgn:1000003",
        "tgn:7003676",
        "tgn:7000084",
        "tgn:7029392"
    ],
    "tgn:id":7208250,
    "tgn:name":"B\u00fcltum",
    "tgn:placetype":[
        "aat:300008347"
    ]
},
  "bbox": [],
  "geometry": {"coordinates":[10.066667,52.033333],"type":"Point"}
}