<<<<<<< HEAD
{
  "id": 2339258,
  "type": "Feature",
  "properties": {
    "tgn:hierarchy":[
        "tgn:2339258",
        "tgn:1000001",
        "tgn:7012149",
        "tgn:2002382",
        "tgn:7007923",
        "tgn:7029392"
    ],
    "tgn:id":2339258,
    "tgn:name":"Franz Reservoir",
    "tgn:placetype":[
        "aat:300006191"
    ]
},
  "bbox": [],
  "geometry": {"coordinates":[-110.1,43.0667],"type":"Point"}
}
=======
{"geometry":{"type":"Point","coordinates":[-110.100000,43.066700]},"type":"Feature","properties":{"hierarchy":["tgn:2339258","tgn:1000001","tgn:7012149","tgn:2002382","tgn:7007923","tgn:7029392"],"placetype":["aat:300006191"],"id":2339258,"name:xx":"Franz Reservoir"}}
>>>>>>> 03f74aca74312dbeaf24d7e61306dd6a786dc3d0
