{
  "id": 7269387,
  "type": "Feature",
  "properties": {
    "tgn:concordances":{
        "gn:id":"2748351"
    },
    "tgn:hierarchy":[
        "tgn:7269387",
        "tgn:1000003",
        "tgn:7003626",
        "tgn:7016845",
        "tgn:7029392"
    ],
    "tgn:id":7269387,
    "tgn:name:nl":"Radewijk",
    "tgn:placetype":[
        "aat:300008347"
    ]
},
  "bbox": [],
  "geometry": {"coordinates":[6.733333,52.566667],"type":"Point"}
}