{
  "id": 7413373,
  "type": "Feature",
  "properties": {
    "tgn:hierarchy":[
        "tgn:7413373",
        "tgn:7005587",
        "tgn:1000001",
        "tgn:7005560",
        "tgn:7029392"
    ],
    "tgn:id":7413373,
    "tgn:name:es":"Benito Ju\u00e1rez",
    "tgn:placetype":[
        "aat:300008347"
    ]
},
  "bbox": [],
  "geometry": {"coordinates":[-98.830556,20.366667],"type":"Point"}
}