{
  "id": 7194440,
  "type": "Feature",
  "properties": {
    "tgn:hierarchy":[
        "tgn:7194440",
        "tgn:7003692",
        "tgn:1000003",
        "tgn:7000084",
        "tgn:7029392"
    ],
    "tgn:id":7194440,
    "tgn:name":"Dammhof",
    "tgn:placetype":[
        "aat:300000206"
    ]
},
  "bbox": [],
  "geometry": {"coordinates":[8.916667,49.166667],"type":"Point"}
}