<<<<<<< HEAD
{
  "id": 2155407,
  "type": "Feature",
  "properties": {
    "tgn:hierarchy":[
        "tgn:2155407",
        "tgn:1000001",
        "tgn:7012149",
        "tgn:2001290",
        "tgn:7007524",
        "tgn:7029392"
    ],
    "tgn:id":2155407,
    "tgn:name":"Bear Point",
    "tgn:placetype":[
        "aat:300008798"
    ]
},
  "bbox": [],
  "geometry": {"coordinates":[-114.7167,46.9167],"type":"Point"}
}
=======
{"geometry":{"type":"Point","coordinates":[-114.716700,46.916700]},"type":"Feature","properties":{"hierarchy":["tgn:2155407","tgn:1000001","tgn:7012149","tgn:2001290","tgn:7007524","tgn:7029392"],"placetype":["aat:300008798"],"id":2155407,"name:xx":"Bear Point"}}
>>>>>>> 03f74aca74312dbeaf24d7e61306dd6a786dc3d0
