{
  "id": 2421517,
  "type": "Feature",
  "properties": {
    "tgn:hierarchy":[
        "tgn:2421517",
        "tgn:1000001",
        "tgn:7012149",
        "tgn:2001249",
        "tgn:7007523",
        "tgn:7029392"
    ],
    "tgn:id":2421517,
    "tgn:name":"Jessie Hollow",
    "tgn:placetype":[
        "aat:300008761"
    ]
},
  "bbox": [],
  "geometry": {"coordinates":[-93.45,36.75],"type":"Point"}
}