{
  "id": 1114173,
  "type": "Feature",
  "properties": {
    "tgn:hierarchy":[
        "tgn:1114173",
        "tgn:1000004",
        "tgn:1000120",
        "tgn:7029392"
    ],
    "tgn:id":1114173,
    "tgn:name":"Kii-suid\u014d",
    "tgn:placetype":[
        "aat:300008713"
    ]
},
  "bbox": [],
  "geometry": {"coordinates":[134.9167,33.9167],"type":"Point"}
}