{
  "id": 2691568,
  "type": "Feature",
  "properties": {
    "tgn:hierarchy":[
        "tgn:2691568",
        "tgn:1000001",
        "tgn:2001025",
        "tgn:7012149",
        "tgn:7007521",
        "tgn:7029392"
    ],
    "tgn:id":2691568,
    "tgn:name":"Staring Lake",
    "tgn:placetype":[
        "aat:300008680"
    ]
},
  "bbox": [],
  "geometry": {"coordinates":[-93.45,44.8333],"type":"Point"}
}