{
  "id": 7552781,
  "type": "Feature",
  "properties": {
    "tgn:hierarchy":[
        "tgn:7552781",
        "tgn:1000004",
        "tgn:7000198",
        "tgn:1001882",
        "tgn:7029392"
    ],
    "tgn:id":7552781,
    "tgn:name:en":"Muddebih\u0101l",
    "tgn:placetype":[
        "aat:300008347"
    ]
},
  "bbox": [],
  "geometry": {"coordinates":[76.133333,16.333333],"type":"Point"}
}