{
  "id": 2512902,
  "type": "Feature",
  "properties": {
    "tgn:hierarchy":[
        "tgn:2512902",
        "tgn:1000001",
        "tgn:7012149",
        "tgn:1002690",
        "tgn:7007710",
        "tgn:7029392"
    ],
    "tgn:id":2512902,
    "tgn:name":"Mill Creek",
    "tgn:placetype":[
        "aat:300008706"
    ]
},
  "bbox": [],
  "geometry": {"coordinates":[-75.3333,40.0333],"type":"Point"}
}