{
  "id": 1014409,
  "type": "Feature",
  "properties": {
    "tgn:hierarchy":[
        "tgn:1014409",
        "tgn:7005685",
        "tgn:1000001",
        "tgn:7005802",
        "tgn:7029392"
    ],
    "tgn:id":1014409,
    "tgn:name":"Berwick",
    "tgn:placetype":[
        "aat:300008347"
    ]
},
  "bbox": [],
  "geometry": {"coordinates":[-64.7333,45.05],"type":"Point"}
}