{
  "id": 7443362,
  "type": "Feature",
  "properties": {
    "tgn:hierarchy":[
        "tgn:7443362",
        "tgn:7002443",
        "tgn:7026278",
        "tgn:1000003",
        "tgn:7008591",
        "tgn:7029392"
    ],
    "tgn:id":7443362,
    "tgn:name:en":"Welsh Channel",
    "tgn:placetype":[
        "aat:300008713"
    ]
},
  "bbox": [],
  "geometry": {"coordinates":[-3.333333,53.366667],"type":"Point"}
}