<<<<<<< HEAD
{
  "id": 2259545,
  "type": "Feature",
  "properties": {
    "tgn:hierarchy":[
        "tgn:2259545",
        "tgn:1000001",
        "tgn:7012149",
        "tgn:7007157",
        "tgn:1002857",
        "tgn:7029392"
    ],
    "tgn:id":2259545,
    "tgn:name":"Cottonwood Wash",
    "tgn:placetype":[
        "aat:300008699"
    ]
},
  "bbox": [],
  "geometry": {"coordinates":[-115.6833,34.8],"type":"Point"}
}
=======
{"geometry":{"type":"Point","coordinates":[-115.683300,34.800000]},"type":"Feature","properties":{"hierarchy":["tgn:2259545","tgn:1000001","tgn:7012149","tgn:7007157","tgn:1002857","tgn:7029392"],"placetype":["aat:300008699"],"id":2259545,"name:xx":"Cottonwood Wash"}}
>>>>>>> 03f74aca74312dbeaf24d7e61306dd6a786dc3d0
