{
  "id": 2527593,
  "type": "Feature",
  "properties": {
    "tgn:hierarchy":[
        "tgn:2527593",
        "tgn:1000001",
        "tgn:7012149",
        "tgn:2000894",
        "tgn:7007256",
        "tgn:7029392"
    ],
    "tgn:id":2527593,
    "tgn:name":"Mount Zion",
    "tgn:placetype":[
        "aat:300008347"
    ]
},
  "bbox": [],
  "geometry": {"coordinates":[-93.3333,32.15],"type":"Point"}
}