{
  "id": 2520942,
  "type": "Feature",
  "properties": {
    "tgn:hierarchy":[
        "tgn:2520942",
        "tgn:1000001",
        "tgn:2001941",
        "tgn:7012149",
        "tgn:7007826",
        "tgn:7029392"
    ],
    "tgn:id":2520942,
    "tgn:name":"Mont Blanc",
    "tgn:placetype":[
        "aat:300008798"
    ]
},
  "bbox": [],
  "geometry": {"coordinates":[-98.5833,29.6667],"type":"Point"}
}