<<<<<<< HEAD
{
  "id": 7483602,
  "type": "Feature",
  "properties": {
    "tgn:hierarchy":[
        "tgn:7483602",
        "tgn:7487020",
        "tgn:1000004",
        "tgn:1000141",
        "tgn:7029392"
    ],
    "tgn:id":7483602,
    "tgn:name":"Longxing Qiao",
    "tgn:placetype":[
        "aat:300007836"
    ]
},
  "bbox": [],
  "geometry": {"coordinates":[120.730278,24.459722],"type":"Point"}
}
=======
{"geometry":{"type":"Point","coordinates":[120.730278,24.459722]},"type":"Feature","properties":{"hierarchy":["tgn:7483602","tgn:7487020","tgn:1000004","tgn:1000141","tgn:7029392"],"placetype":["aat:300007836"],"id":7483602,"name:xx":"Longxing Qiao"}}
>>>>>>> 03f74aca74312dbeaf24d7e61306dd6a786dc3d0
