{
  "id": 2440845,
  "type": "Feature",
  "properties": {
    "tgn:hierarchy":[
        "tgn:2440845",
        "tgn:1000001",
        "tgn:7013686",
        "tgn:7012149",
        "tgn:7007517",
        "tgn:7029392"
    ],
    "tgn:id":2440845,
    "tgn:name":"Knightville Reservoir",
    "tgn:placetype":[
        "aat:300006191"
    ]
},
  "bbox": [],
  "geometry": {"coordinates":[-72.85,42.2833],"type":"Point"}
}