{
  "id": 7569716,
  "type": "Feature",
  "properties": {
    "tgn:hierarchy":[
        "tgn:7569716",
        "tgn:1000004",
        "tgn:7000198",
        "tgn:7031786",
        "tgn:7029392"
    ],
    "tgn:id":7569716,
    "tgn:name:en":"Hair\u0101kholi",
    "tgn:placetype":[
        "aat:300008347"
    ]
},
  "bbox": [],
  "geometry": {"coordinates":[78.72144,29.952189],"type":"Point"}
}