{
  "id": 1107717,
  "type": "Feature",
  "properties": {
    "tgn:hierarchy":[
        "tgn:1107717",
        "tgn:1001094",
        "tgn:1000004",
        "tgn:1000135",
        "tgn:7029392"
    ],
    "tgn:id":1107717,
    "tgn:name":"Mayon Volcano",
    "tgn:placetype":[
        "aat:300132325"
    ]
},
  "bbox": [],
  "geometry": {"coordinates":[123.6833,13.25],"type":"Point"}
}