{
  "id": 7227607,
  "type": "Feature",
  "properties": {
    "tgn:hierarchy":[
        "tgn:7227607",
        "tgn:7002690",
        "tgn:7012056",
        "tgn:1000003",
        "tgn:1000074",
        "tgn:7029392"
    ],
    "tgn:id":7227607,
    "tgn:name":"Kondoyioryian\u00e1",
    "tgn:placetype":[
        "aat:300008347"
    ]
},
  "bbox": [],
  "geometry": {"coordinates":[23.85,35.433333],"type":"Point"}
}