<<<<<<< HEAD
{
  "id": 7471930,
  "type": "Feature",
  "properties": {
    "tgn:hierarchy":[
        "tgn:7471930",
        "tgn:7001010",
        "tgn:1000004",
        "tgn:1000141",
        "tgn:7029392"
    ],
    "tgn:id":7471930,
    "tgn:name":"Changchun Suidao",
    "tgn:placetype":[
        "aat:300007899"
    ]
},
  "bbox": [],
  "geometry": {"coordinates":[121.607967,24.162373],"type":"Point"}
}
=======
{"geometry":{"type":"Point","coordinates":[121.607967,24.162373]},"type":"Feature","properties":{"hierarchy":["tgn:7471930","tgn:7001010","tgn:1000004","tgn:1000141","tgn:7029392"],"placetype":["aat:300007899"],"id":7471930,"name:xx":"Changchun Suidao"}}
>>>>>>> 03f74aca74312dbeaf24d7e61306dd6a786dc3d0
