{
  "id": 2601609,
  "type": "Feature",
  "properties": {
    "tgn:hierarchy":[
        "tgn:2601609",
        "tgn:1000001",
        "tgn:7012149",
        "tgn:2001769",
        "tgn:7007712",
        "tgn:7029392"
    ],
    "tgn:id":2601609,
    "tgn:name":"Pushing Branch",
    "tgn:placetype":[
        "aat:300008699"
    ]
},
  "bbox": [],
  "geometry": {"coordinates":[-79.9167,33.65],"type":"Point"}
}