{
  "id": 7490868,
  "type": "Feature",
  "properties": {
    "tgn:hierarchy":[
        "tgn:7490868",
        "tgn:7001004",
        "tgn:1000004",
        "tgn:1000141",
        "tgn:7029392"
    ],
    "tgn:id":7490868,
    "tgn:name":"Shitou",
    "tgn:placetype":[
        "aat:300008347"
    ]
},
  "bbox": [],
  "geometry": {"coordinates":[120.333333,22.633333],"type":"Point"}
}