<<<<<<< HEAD
{
  "id": 7029628,
  "type": "Feature",
  "properties": {
    "tgn:hierarchy":[
        "tgn:7029628",
        "tgn:1000003",
        "tgn:7006951",
        "tgn:7016845",
        "tgn:7029392"
    ],
    "tgn:id":7029628,
    "tgn:name":"Nieuwer Amstel",
    "tgn:placetype":[
        "aat:300008347"
    ]
},
  "bbox": [],
  "geometry": {"coordinates":[4.866,52.3],"type":"Point"}
}
=======
{"geometry":{"type":"Point","coordinates":[4.866000,52.300000]},"type":"Feature","properties":{"hierarchy":["tgn:7029628","tgn:1000003","tgn:7006951","tgn:7016845","tgn:7029392"],"placetype":["aat:300008347"],"id":7029628,"name:xx":"Nieuwer Amstel"}}
>>>>>>> 03f74aca74312dbeaf24d7e61306dd6a786dc3d0
