<<<<<<< HEAD
{
  "id": 7361497,
  "type": "Feature",
  "properties": {
    "tgn:hierarchy":[
        "tgn:7361497",
        "tgn:1000001",
        "tgn:7005596",
        "tgn:7005560",
        "tgn:7029392"
    ],
    "tgn:id":7361497,
    "tgn:name":"El Cortijo Nuevo",
    "tgn:placetype":[
        "aat:300008347"
    ]
},
  "bbox": [],
  "geometry": {"coordinates":[-91.3,17.266667],"type":"Point"}
}
=======
{"geometry":{"type":"Point","coordinates":[-91.300000,17.266667]},"type":"Feature","properties":{"hierarchy":["tgn:7361497","tgn:1000001","tgn:7005596","tgn:7005560","tgn:7029392"],"placetype":["aat:300008347"],"id":7361497,"name:xx":"El Cortijo Nuevo"}}
>>>>>>> 03f74aca74312dbeaf24d7e61306dd6a786dc3d0
