{
  "id": 1139726,
  "type": "Feature",
  "properties": {
    "tgn:hierarchy":[
        "tgn:1139726",
        "tgn:1000004",
        "tgn:1001390",
        "tgn:1000111",
        "tgn:7029392"
    ],
    "tgn:id":1139726,
    "tgn:name":"Toudaogou",
    "tgn:placetype":[
        "aat:300008347"
    ]
},
  "bbox": [],
  "geometry": {"coordinates":[121.6667,41.6167],"type":"Point"}
}