{
  "id": 7525966,
  "type": "Feature",
  "properties": {
    "tgn:hierarchy":[
        "tgn:7525966",
        "tgn:7001242",
        "tgn:7016833",
        "tgn:7000123",
        "tgn:7029392"
    ],
    "tgn:id":7525966,
    "tgn:name:en":"S\u012bd\u012b \u1e28ass\u0101n",
    "tgn:placetype":[
        "aat:300005926"
    ]
},
  "bbox": [],
  "geometry": {"coordinates":[32.533333,25.583333],"type":"Point"}
}