{
  "id": 7563367,
  "type": "Feature",
  "properties": {
    "tgn:hierarchy":[
        "tgn:7563367",
        "tgn:1000004",
        "tgn:7000198",
        "tgn:1001894",
        "tgn:7029392"
    ],
    "tgn:id":7563367,
    "tgn:name:en":"Chakeri",
    "tgn:placetype":[
        "aat:300008347"
    ]
},
  "bbox": [],
  "geometry": {"coordinates":[79.080886,24.066574],"type":"Point"}
}