{
  "id": 2561081,
  "type": "Feature",
  "properties": {
    "tgn:hierarchy":[
        "tgn:2561081",
        "tgn:1000001",
        "tgn:7012149",
        "tgn:1002637",
        "tgn:7007826",
        "tgn:7029392"
    ],
    "tgn:id":2561081,
    "tgn:name":"Orrs",
    "tgn:placetype":[
        "aat:300008347"
    ]
},
  "bbox": [],
  "geometry": {"coordinates":[-94.5167,32.8333],"type":"Point"}
}