{
  "id": 2198993,
  "type": "Feature",
  "properties": {
    "tgn:hierarchy":[
        "tgn:2198993",
        "tgn:1000001",
        "tgn:7012149",
        "tgn:2002330",
        "tgn:7007922",
        "tgn:7029392"
    ],
    "tgn:id":2198993,
    "tgn:name":"Bruemmer Creek",
    "tgn:placetype":[
        "aat:300008706"
    ]
},
  "bbox": [],
  "geometry": {"coordinates":[-87.5167,44.6333],"type":"Point"}
}