{
  "id": 1060946,
  "type": "Feature",
  "properties": {
    "tgn:hierarchy":[
        "tgn:1060946",
        "tgn:6001314",
        "tgn:1000004",
        "tgn:7018214",
        "tgn:7002435",
        "tgn:7029392"
    ],
    "tgn:id":1060946,
    "tgn:name":"Varlamovo",
    "tgn:placetype":[
        "aat:300008347"
    ]
},
  "bbox": [],
  "geometry": {"coordinates":[60.5833,54.6667],"type":"Point"}
}