{
  "id": 7315392,
  "type": "Feature",
  "properties": {
    "tgn:hierarchy":[
        "tgn:7315392",
        "tgn:1001702",
        "tgn:1000049",
        "tgn:1000002",
        "tgn:7029392"
    ],
    "tgn:id":7315392,
    "tgn:name":"Chancery, Punta",
    "tgn:placetype":[
        "aat:300386846"
    ]
},
  "bbox": [],
  "geometry": {"coordinates":[-74.633333,-52.866667],"type":"Point"}
}