{
  "id": 2696030,
  "type": "Feature",
  "properties": {
    "tgn:hierarchy":[
        "tgn:2696030",
        "tgn:1000001",
        "tgn:1002245",
        "tgn:7012149",
        "tgn:7007568",
        "tgn:7029392"
    ],
    "tgn:id":2696030,
    "tgn:name":"Stoddard Creek",
    "tgn:placetype":[
        "aat:300008706"
    ]
},
  "bbox": [],
  "geometry": {"coordinates":[-78.75,42.05],"type":"Point"}
}