{
  "id": 7342766,
  "type": "Feature",
  "properties": {
    "tgn:hierarchy":[
        "tgn:7342766",
        "tgn:7002831",
        "tgn:1000003",
        "tgn:7002786",
        "tgn:1000095",
        "tgn:7029392"
    ],
    "tgn:id":7342766,
    "tgn:name":"Casoyo, R\u00edo",
    "tgn:placetype":[
        "aat:300008699"
    ]
},
  "bbox": [],
  "geometry": {"coordinates":[-6.916667,42.416667],"type":"Point"}
}