{
  "id": 7235269,
  "type": "Feature",
  "properties": {
    "tgn:hierarchy":[
        "tgn:7235269",
        "tgn:7002690",
        "tgn:7012056",
        "tgn:1000003",
        "tgn:1000074",
        "tgn:7029392"
    ],
    "tgn:id":7235269,
    "tgn:name":"Flom\u00e9s",
    "tgn:placetype":[
        "aat:300008795"
    ]
},
  "bbox": [],
  "geometry": {"coordinates":[23.966667,35.433333],"type":"Point"}
}