{
  "id": 7129266,
  "type": "Feature",
  "properties": {
    "tgn:hierarchy":[
        "tgn:7129266",
        "tgn:7003669",
        "tgn:1000003",
        "tgn:7000084",
        "tgn:7029392"
    ],
    "tgn:id":7129266,
    "tgn:name":"Mantelberg",
    "tgn:placetype":[
        "aat:300008777"
    ]
},
  "bbox": [],
  "geometry": {"coordinates":[10.616667,49.633333],"type":"Point"}
}