{
  "id": 7495982,
  "type": "Feature",
  "properties": {
    "tgn:hierarchy":[
        "tgn:7495982",
        "tgn:1000004",
        "tgn:1000454",
        "tgn:1000141",
        "tgn:7029392"
    ],
    "tgn:id":7495982,
    "tgn:name":"Jingming Daoyuan",
    "tgn:placetype":[
        "aat:300007595"
    ]
},
  "bbox": [],
  "geometry": {"coordinates":[121.458042,24.961252],"type":"Point"}
}