{
  "id": 2217125,
  "type": "Feature",
  "properties": {
    "tgn:hierarchy":[
        "tgn:2217125",
        "tgn:1000001",
        "tgn:7013942",
        "tgn:7012149",
        "tgn:7007517",
        "tgn:7029392"
    ],
    "tgn:id":2217125,
    "tgn:name":"Camp Rowe",
    "tgn:placetype":[
        "aat:300008347"
    ]
},
  "bbox": [],
  "geometry": {"coordinates":[-72.8833,42.6833],"type":"Point"}
}