{
  "id": 7272864,
  "type": "Feature",
  "properties": {
    "tgn:hierarchy":[
        "tgn:7272864",
        "tgn:1000003",
        "tgn:7003627",
        "tgn:7016845",
        "tgn:7029392"
    ],
    "tgn:id":7272864,
    "tgn:name:nl":"Waardassacker en Holendrecht, Polder",
    "tgn:placetype":[
        "aat:300006163"
    ]
},
  "bbox": [],
  "geometry": {"coordinates":[4.95,52.266667],"type":"Point"}
}