{
  "id": 1020494,
  "type": "Feature",
  "properties": {
    "tgn:hierarchy":[
        "tgn:1020494",
        "tgn:7006246",
        "tgn:1000047",
        "tgn:7002455",
        "tgn:1000002",
        "tgn:7029392"
    ],
    "tgn:id":1020494,
    "tgn:name":"Olho d'\u00c1gua das Cunh\u00e3s",
    "tgn:placetype":[
        "aat:300008347"
    ]
},
  "bbox": [],
  "geometry": {"coordinates":[-44.5667,-4.7167],"type":"Point"}
}