{
  "id": 2562961,
  "type": "Feature",
  "properties": {
    "tgn:hierarchy":[
        "tgn:2562961",
        "tgn:1000001",
        "tgn:7012149",
        "tgn:2000233",
        "tgn:7007158",
        "tgn:7029392"
    ],
    "tgn:id":2562961,
    "tgn:name":"Owen Basin",
    "tgn:placetype":[
        "aat:300386845"
    ]
},
  "bbox": [],
  "geometry": {"coordinates":[-108.0833,37.4333],"type":"Point"}
}