{
  "id": 7181285,
  "type": "Feature",
  "properties": {
    "tgn:hierarchy":[
        "tgn:7181285",
        "tgn:7003692",
        "tgn:1000003",
        "tgn:7000084",
        "tgn:7029392"
    ],
    "tgn:id":7181285,
    "tgn:name":"Gaiberg",
    "tgn:placetype":[
        "aat:300008347"
    ]
},
  "bbox": [],
  "geometry": {"coordinates":[8.749722,49.366389],"type":"Point"}
}