{
  "id": 7437804,
  "type": "Feature",
  "properties": {
    "tgn:hierarchy":[
        "tgn:7437804",
        "tgn:1000001",
        "tgn:7005599",
        "tgn:7005560",
        "tgn:7029392"
    ],
    "tgn:id":7437804,
    "tgn:name":"Tampico, Punta de",
    "tgn:placetype":[
        "aat:300386846"
    ]
},
  "bbox": [],
  "geometry": {"coordinates":[-97.783333,22.266667],"type":"Point"}
}