{
  "id": 7425895,
  "type": "Feature",
  "properties": {
    "tgn:hierarchy":[
        "tgn:7425895",
        "tgn:1000001",
        "tgn:7005594",
        "tgn:7005560",
        "tgn:7029392"
    ],
    "tgn:id":7425895,
    "tgn:name":"Bocas, R\u00edo",
    "tgn:placetype":[
        "aat:300008699"
    ]
},
  "bbox": [],
  "geometry": {"coordinates":[-101.183333,22.333333],"type":"Point"}
}