{
  "id": 7552343,
  "type": "Feature",
  "properties": {
    "tgn:hierarchy":[
        "tgn:7552343",
        "tgn:1000004",
        "tgn:7000198",
        "tgn:1001895",
        "tgn:7029392"
    ],
    "tgn:id":7552343,
    "tgn:name:en":"Morgaon",
    "tgn:placetype":[
        "aat:300008347"
    ]
},
  "bbox": [],
  "geometry": {"coordinates":[74.317276,18.27834],"type":"Point"}
}