{
  "id": 2239646,
  "type": "Feature",
  "properties": {
    "tgn:hierarchy":[
        "tgn:2239646",
        "tgn:1000001",
        "tgn:7012149",
        "tgn:2001275",
        "tgn:7007524",
        "tgn:7029392"
    ],
    "tgn:id":2239646,
    "tgn:name":"Churn Creek",
    "tgn:placetype":[
        "aat:300008706"
    ]
},
  "bbox": [],
  "geometry": {"coordinates":[-110.9833,45.7167],"type":"Point"}
}