{
  "id": 2306742,
  "type": "Feature",
  "properties": {
    "tgn:hierarchy":[
        "tgn:2306742",
        "tgn:1000001",
        "tgn:7012149",
        "tgn:2001721",
        "tgn:7007708",
        "tgn:7029392"
    ],
    "tgn:id":2306742,
    "tgn:name":"East Fork Grande Ronde River",
    "tgn:placetype":[
        "aat:300008707"
    ]
},
  "bbox": [],
  "geometry": {"coordinates":[-118.2167,45.0667],"type":"Point"}
}