{
  "id": 1102394,
  "type": "Feature",
  "properties": {
    "tgn:hierarchy":[
        "tgn:1102394",
        "tgn:1000001",
        "tgn:7012149",
        "tgn:7007157",
        "tgn:1002863",
        "tgn:7029392"
    ],
    "tgn:id":1102394,
    "tgn:name":"Morro Bay State Park",
    "tgn:placetype":[
        "aat:300008192"
    ]
},
  "bbox": [],
  "geometry": {"coordinates":[-120.8167,35.35],"type":"Point"}
}