{
  "id": 2601682,
  "type": "Feature",
  "properties": {
    "tgn:hierarchy":[
        "tgn:2601682",
        "tgn:1000001",
        "tgn:7012149",
        "tgn:1002892",
        "tgn:7007520",
        "tgn:7029392"
    ],
    "tgn:id":2601682,
    "tgn:name":"Putnam Drain",
    "tgn:placetype":[
        "aat:300006075"
    ]
},
  "bbox": [],
  "geometry": {"coordinates":[-84.3333,42.9167],"type":"Point"}
}