{
  "id": 2512167,
  "type": "Feature",
  "properties": {
    "tgn:hierarchy":[
        "tgn:2512167",
        "tgn:1000001",
        "tgn:2001840",
        "tgn:7012149",
        "tgn:7007825",
        "tgn:7029392"
    ],
    "tgn:id":2512167,
    "tgn:name":"Mill Branch",
    "tgn:placetype":[
        "aat:300008699"
    ]
},
  "bbox": [],
  "geometry": {"coordinates":[-85.05,35.6667],"type":"Point"}
}