{
  "id": 7378936,
  "type": "Feature",
  "properties": {
    "tgn:hierarchy":[
        "tgn:7378936",
        "tgn:1000001",
        "tgn:7005595",
        "tgn:7005560",
        "tgn:7029392"
    ],
    "tgn:id":7378936,
    "tgn:name":"Los Charcos",
    "tgn:placetype":[
        "aat:300008347"
    ]
},
  "bbox": [],
  "geometry": {"coordinates":[-108.516667,26.766667],"type":"Point"}
}