{
  "id": 7472804,
  "type": "Feature",
  "properties": {
    "tgn:hierarchy":[
        "tgn:7472804",
        "tgn:1000004",
        "tgn:7467799",
        "tgn:1000141",
        "tgn:7029392"
    ],
    "tgn:id":7472804,
    "tgn:name":"Dongfangchuang",
    "tgn:placetype":[
        "aat:300008347"
    ]
},
  "bbox": [],
  "geometry": {"coordinates":[120.514873,24.063483],"type":"Point"}
}