{
  "id": 2479669,
  "type": "Feature",
  "properties": {
    "tgn:hierarchy":[
        "tgn:2479669",
        "tgn:1000001",
        "tgn:1002260",
        "tgn:7012149",
        "tgn:7007920",
        "tgn:7029392"
    ],
    "tgn:id":2479669,
    "tgn:name":"Lake Chelan Hills",
    "tgn:placetype":[
        "aat:300008347"
    ]
},
  "bbox": [],
  "geometry": {"coordinates":[-120.05,47.85],"type":"Point"}
}