<<<<<<< HEAD
{
  "id": 7486420,
  "type": "Feature",
  "properties": {
    "tgn:hierarchy":[
        "tgn:7486420",
        "tgn:7487020",
        "tgn:1000004",
        "tgn:1000141",
        "tgn:7029392"
    ],
    "tgn:id":7486420,
    "tgn:name":"Maoyu",
    "tgn:placetype":[
        "aat:300008347"
    ]
},
  "bbox": [],
  "geometry": {"coordinates":[120.663611,24.431111],"type":"Point"}
}
=======
{"geometry":{"type":"Point","coordinates":[120.663611,24.431111]},"type":"Feature","properties":{"hierarchy":["tgn:7486420","tgn:7487020","tgn:1000004","tgn:1000141","tgn:7029392"],"placetype":["aat:300008347"],"id":7486420,"name:xx":"Maoyu"}}
>>>>>>> 03f74aca74312dbeaf24d7e61306dd6a786dc3d0
