<<<<<<< HEAD
{
  "id": 2708983,
  "type": "Feature",
  "properties": {
    "tgn:hierarchy":[
        "tgn:2708983",
        "tgn:1000001",
        "tgn:7016172",
        "tgn:2000121",
        "tgn:7012149",
        "tgn:7029392"
    ],
    "tgn:id":2708983,
    "tgn:name":"T J House Reservoir",
    "tgn:placetype":[
        "aat:300006191"
    ]
},
  "bbox": [],
  "geometry": {"coordinates":[-94.0667,35.5333],"type":"Point"}
}
=======
{"geometry":{"type":"Point","coordinates":[-94.066700,35.533300]},"type":"Feature","properties":{"hierarchy":["tgn:2708983","tgn:1000001","tgn:7016172","tgn:2000121","tgn:7012149","tgn:7029392"],"placetype":["aat:300006191"],"id":2708983,"name:xx":"T J House Reservoir"}}
>>>>>>> 03f74aca74312dbeaf24d7e61306dd6a786dc3d0
