{
  "id": 2288708,
  "type": "Feature",
  "properties": {
    "tgn:hierarchy":[
        "tgn:2288708",
        "tgn:1000001",
        "tgn:7012149",
        "tgn:2001237",
        "tgn:7007523",
        "tgn:7029392"
    ],
    "tgn:id":2288708,
    "tgn:name":"Ditch Number 1",
    "tgn:placetype":[
        "aat:300006075"
    ]
},
  "bbox": [],
  "geometry": {"coordinates":[-90.6167,36.5333],"type":"Point"}
}