{
  "id": 1099381,
  "type": "Feature",
  "properties": {
    "tgn:hierarchy":[
        "tgn:1099381",
        "tgn:7000430",
        "tgn:1000006",
        "tgn:7029392"
    ],
    "tgn:id":1099381,
    "tgn:name":"Kingston",
    "tgn:placetype":[
        "aat:300008347",
        "aat:300008375"
    ]
},
  "bbox": [],
  "geometry": {"coordinates":[167.95,-29.0667],"type":"Point"}
}