{
  "id": 2594769,
  "type": "Feature",
  "properties": {
    "tgn:hierarchy":[
        "tgn:2594769",
        "tgn:1000001",
        "tgn:7012149",
        "tgn:2001859",
        "tgn:7007825",
        "tgn:7029392"
    ],
    "tgn:id":2594769,
    "tgn:name":"Possum Creek",
    "tgn:placetype":[
        "aat:300008706"
    ]
},
  "bbox": [],
  "geometry": {"coordinates":[-89.45,36.0667],"type":"Point"}
}