{
  "id": 2082392,
  "type": "Feature",
  "properties": {
    "tgn:hierarchy":[
        "tgn:2082392",
        "tgn:1000001",
        "tgn:7012149",
        "tgn:2001612",
        "tgn:7007706",
        "tgn:7029392"
    ],
    "tgn:id":2082392,
    "tgn:name":"Vinton",
    "tgn:placetype":[
        "aat:300008347"
    ]
},
  "bbox": [],
  "geometry": {"coordinates":[-82.3333,38.9667],"type":"Point"}
}