{
  "id": 2748815,
  "type": "Feature",
  "properties": {
    "tgn:hierarchy":[
        "tgn:2748815",
        "tgn:1000001",
        "tgn:7012149",
        "tgn:2001906",
        "tgn:7007825",
        "tgn:7029392"
    ],
    "tgn:id":2748815,
    "tgn:name":"Walkertown Branch",
    "tgn:placetype":[
        "aat:300008699"
    ]
},
  "bbox": [],
  "geometry": {"coordinates":[-84.3833,35.0333],"type":"Point"}
}