{
  "id": 2288110,
  "type": "Feature",
  "properties": {
    "tgn:hierarchy":[
        "tgn:2288110",
        "tgn:1000001",
        "tgn:7012149",
        "tgn:1002631",
        "tgn:7007240",
        "tgn:7029392"
    ],
    "tgn:id":2288110,
    "tgn:name":"Dinner Sink Pond",
    "tgn:placetype":[
        "aat:300008905"
    ]
},
  "bbox": [],
  "geometry": {"coordinates":[-82.4667,29.1833],"type":"Point"}
}