{
  "id": 7232101,
  "type": "Feature",
  "properties": {
    "tgn:hierarchy":[
        "tgn:7232101",
        "tgn:7002741",
        "tgn:7017076",
        "tgn:1000003",
        "tgn:1000074",
        "tgn:7029392"
    ],
    "tgn:id":7232101,
    "tgn:name":"K\u00e1lamos",
    "tgn:placetype":[
        "aat:300008795"
    ]
},
  "bbox": [],
  "geometry": {"coordinates":[23.05,38.516667],"type":"Point"}
}