{
  "id": 7290945,
  "type": "Feature",
  "properties": {
    "tgn:hierarchy":[
        "tgn:7290945",
        "tgn:1001702",
        "tgn:1000049",
        "tgn:1000002",
        "tgn:7029392"
    ],
    "tgn:id":7290945,
    "tgn:name":"Curle, Punta",
    "tgn:placetype":[
        "aat:300386846"
    ]
},
  "bbox": [],
  "geometry": {"coordinates":[-74.466667,-49.516667],"type":"Point"}
}