{
  "id": 7141116,
  "type": "Feature",
  "properties": {
    "tgn:hierarchy":[
        "tgn:7141116",
        "tgn:1000003",
        "tgn:7003676",
        "tgn:7000084",
        "tgn:7029392"
    ],
    "tgn:id":7141116,
    "tgn:name":"L\u00fcsche",
    "tgn:placetype":[
        "aat:300008347"
    ]
},
  "bbox": [],
  "geometry": {"coordinates":[10.433333,52.733333],"type":"Point"}
}