{
  "id": 7387025,
  "type": "Feature",
  "properties": {
    "tgn:hierarchy":[
        "tgn:7387025",
        "tgn:7005581",
        "tgn:1000001",
        "tgn:7005560",
        "tgn:7029392"
    ],
    "tgn:id":7387025,
    "tgn:name":"Pericos, Cerro",
    "tgn:placetype":[
        "aat:300008795"
    ]
},
  "bbox": [],
  "geometry": {"coordinates":[-107.333333,26.55],"type":"Point"}
}