{
  "id": 7039156,
  "type": "Feature",
  "properties": {
    "tgn:hierarchy":[
        "tgn:7039156",
        "tgn:7015163",
        "tgn:1000003",
        "tgn:7003121",
        "tgn:1000080",
        "tgn:7029392"
    ],
    "tgn:id":7039156,
    "tgn:name":"Silanis, Riu",
    "tgn:placetype":[
        "aat:300008699"
    ]
},
  "bbox": [],
  "geometry": {"coordinates":[8.883333,40.85],"type":"Point"}
}