{
  "id": 7008073,
  "type": "Feature",
  "properties": {
    "tgn:hierarchy":[
        "tgn:7008073",
        "tgn:7002811",
        "tgn:1000003",
        "tgn:7003837",
        "tgn:1000095",
        "tgn:7029392"
    ],
    "tgn:id":7008073,
    "tgn:name":"Mont\u00e1nchez",
    "tgn:placetype":[
        "aat:300008347"
    ]
},
  "bbox": [],
  "geometry": {"coordinates":[-6.15,39.216667],"type":"Point"}
}