{
  "id": 2739921,
  "type": "Feature",
  "properties": {
    "tgn:hierarchy":[
        "tgn:2739921",
        "tgn:1000001",
        "tgn:7012149",
        "tgn:1002350",
        "tgn:7007157",
        "tgn:7029392"
    ],
    "tgn:id":2739921,
    "tgn:name":"Upper Forni",
    "tgn:placetype":[
        "aat:300008347"
    ]
},
  "bbox": [],
  "geometry": {"coordinates":[-120.1667,38.8167],"type":"Point"}
}