<<<<<<< HEAD
{
  "id": 2156533,
  "type": "Feature",
  "properties": {
    "tgn:hierarchy":[
        "tgn:2156533",
        "tgn:1000001",
        "tgn:7012149",
        "tgn:2000481",
        "tgn:7007250",
        "tgn:7029392"
    ],
    "tgn:id":2156533,
    "tgn:name":"Beartrap Spring",
    "tgn:placetype":[
        "aat:300008697"
    ]
},
  "bbox": [],
  "geometry": {"coordinates":[-114.4333,45.3833],"type":"Point"}
}
=======
{"geometry":{"type":"Point","coordinates":[-114.433300,45.383300]},"type":"Feature","properties":{"hierarchy":["tgn:2156533","tgn:1000001","tgn:7012149","tgn:2000481","tgn:7007250","tgn:7029392"],"placetype":["aat:300008697"],"id":2156533,"name:xx":"Beartrap Spring"}}
>>>>>>> 03f74aca74312dbeaf24d7e61306dd6a786dc3d0
