{
  "id": 2737661,
  "type": "Feature",
  "properties": {
    "tgn:hierarchy":[
        "tgn:2737661",
        "tgn:1000001",
        "tgn:7012149",
        "tgn:7015666",
        "tgn:7007825",
        "tgn:7029392"
    ],
    "tgn:id":2737661,
    "tgn:name":"Tyler Ridge",
    "tgn:placetype":[
        "aat:300266640"
    ]
},
  "bbox": [],
  "geometry": {"coordinates":[-87.2667,35.7833],"type":"Point"}
}