{
  "id": 7297810,
  "type": "Feature",
  "properties": {
    "tgn:hierarchy":[
        "tgn:7297810",
        "tgn:7001158",
        "tgn:7002850",
        "tgn:1000003",
        "tgn:1000095",
        "tgn:7029392"
    ],
    "tgn:id":7297810,
    "tgn:name":"Sesn\u00e1ndez, Sierra de",
    "tgn:placetype":[
        "aat:300266640"
    ]
},
  "bbox": [],
  "geometry": {"coordinates":[-6.116667,41.766667],"type":"Point"}
}