{
  "id": 7391207,
  "type": "Feature",
  "properties": {
    "tgn:hierarchy":[
        "tgn:7391207",
        "tgn:7005581",
        "tgn:1000001",
        "tgn:7005560",
        "tgn:7029392"
    ],
    "tgn:id":7391207,
    "tgn:name":"Rancho Santa Cruz",
    "tgn:placetype":[
        "aat:300008347"
    ]
},
  "bbox": [],
  "geometry": {"coordinates":[-105.75,28.75],"type":"Point"}
}