{
  "id": 2234483,
  "type": "Feature",
  "properties": {
    "tgn:hierarchy":[
        "tgn:2234483",
        "tgn:1000001",
        "tgn:7012149",
        "tgn:1002742",
        "tgn:7007920",
        "tgn:7029392"
    ],
    "tgn:id":2234483,
    "tgn:name":"Cherokee",
    "tgn:placetype":[
        "aat:300008347"
    ]
},
  "bbox": [],
  "geometry": {"coordinates":[-119.45,48.45],"type":"Point"}
}