{
  "id": 2000061,
  "type": "Feature",
  "properties": {
    "tgn:hierarchy":[
        "tgn:2000061",
        "tgn:7002659",
        "tgn:1000001",
        "tgn:7012149",
        "tgn:7029392"
    ],
    "tgn:id":2000061,
    "tgn:name":"Tallapoosa",
    "tgn:placetype":[
        "aat:300387145",
        "aat:300000771"
    ]
},
  "bbox": [],
  "geometry": {"coordinates":[-85.8333,32.8167],"type":"Point"}
}