{
  "id": 2619794,
  "type": "Feature",
  "properties": {
    "tgn:hierarchy":[
        "tgn:2619794",
        "tgn:1000001",
        "tgn:2000199",
        "tgn:7012149",
        "tgn:7007158",
        "tgn:7029392"
    ],
    "tgn:id":2619794,
    "tgn:name":"Rinker Peak",
    "tgn:placetype":[
        "aat:300008798"
    ]
},
  "bbox": [],
  "geometry": {"coordinates":[-106.4333,39.0333],"type":"Point"}
}