{
  "id": 7424716,
  "type": "Feature",
  "properties": {
    "tgn:hierarchy":[
        "tgn:7424716",
        "tgn:1000001",
        "tgn:1001960",
        "tgn:7005560",
        "tgn:7029392"
    ],
    "tgn:id":7424716,
    "tgn:name":"El Santir, Cerro",
    "tgn:placetype":[
        "aat:300008795"
    ]
},
  "bbox": [],
  "geometry": {"coordinates":[-109.966667,29.766667],"type":"Point"}
}