{
  "id": 2352274,
  "type": "Feature",
  "properties": {
    "tgn:hierarchy":[
        "tgn:2352274",
        "tgn:1000001",
        "tgn:1002712",
        "tgn:7012149",
        "tgn:7007159",
        "tgn:7029392"
    ],
    "tgn:id":2352274,
    "tgn:name":"Goat Brook",
    "tgn:placetype":[
        "aat:300008699"
    ]
},
  "bbox": [],
  "geometry": {"coordinates":[-73.1333,41.5333],"type":"Point"}
}