{
  "id": 7095650,
  "type": "Feature",
  "properties": {
    "tgn:hierarchy":[
        "tgn:7095650",
        "tgn:1000003",
        "tgn:7003688",
        "tgn:7000084",
        "tgn:7029392"
    ],
    "tgn:id":7095650,
    "tgn:name":"Sch\u00f6nberger Zuschlag",
    "tgn:placetype":[
        "aat:300008863"
    ]
},
  "bbox": [],
  "geometry": {"coordinates":[10.45,53.666667],"type":"Point"}
}