{
  "id": 2513693,
  "type": "Feature",
  "properties": {
    "tgn:hierarchy":[
        "tgn:2513693",
        "tgn:1000001",
        "tgn:7012149",
        "tgn:2000927",
        "tgn:7007515",
        "tgn:7029392"
    ],
    "tgn:id":2513693,
    "tgn:name":"Mill Privilege Lake",
    "tgn:placetype":[
        "aat:300008680"
    ]
},
  "bbox": [],
  "geometry": {"coordinates":[-68.0167,45.3333],"type":"Point"}
}