{
  "id": 2064669,
  "type": "Feature",
  "properties": {
    "tgn:hierarchy":[
        "tgn:2064669",
        "tgn:1000001",
        "tgn:7014090",
        "tgn:7012149",
        "tgn:7007565",
        "tgn:7029392"
    ],
    "tgn:id":2064669,
    "tgn:name":"Englishtown",
    "tgn:placetype":[
        "aat:300008347"
    ]
},
  "bbox": [],
  "geometry": {"coordinates":[-74.35,40.2833],"type":"Point"}
}