{
  "id": 7540024,
  "type": "Feature",
  "properties": {
    "tgn:hierarchy":[
        "tgn:7540024",
        "tgn:7001242",
        "tgn:7016833",
        "tgn:7000122",
        "tgn:7029392"
    ],
    "tgn:id":7540024,
    "tgn:name:en":"Nag' Qarratla",
    "tgn:placetype":[
        "aat:300008347"
    ]
},
  "bbox": [],
  "geometry": {"coordinates":[32.866667,24.233333],"type":"Point"}
}