{
  "id": 2685893,
  "type": "Feature",
  "properties": {
    "tgn:hierarchy":[
        "tgn:2685893",
        "tgn:1000001",
        "tgn:7012149",
        "tgn:1002486",
        "tgn:7007826",
        "tgn:7029392"
    ],
    "tgn:id":2685893,
    "tgn:name":"Spring Branch",
    "tgn:placetype":[
        "aat:300008699"
    ]
},
  "bbox": [],
  "geometry": {"coordinates":[-95.35,31.1833],"type":"Point"}
}