{
  "id": 7348296,
  "type": "Feature",
  "properties": {
    "tgn:hierarchy":[
        "tgn:7348296",
        "tgn:7008911",
        "tgn:1000003",
        "tgn:7002763",
        "tgn:1000095",
        "tgn:7029392"
    ],
    "tgn:id":7348296,
    "tgn:name":"Ag\u00fcera",
    "tgn:placetype":[
        "aat:300008347"
    ]
},
  "bbox": [],
  "geometry": {"coordinates":[-5.95,43.45],"type":"Point"}
}