{
  "id": 2669901,
  "type": "Feature",
  "properties": {
    "tgn:hierarchy":[
        "tgn:2669901",
        "tgn:1000001",
        "tgn:7012149",
        "tgn:7007157",
        "tgn:1002972",
        "tgn:7029392"
    ],
    "tgn:id":2669901,
    "tgn:name":"Sloan Canyon",
    "tgn:placetype":[
        "aat:300008761"
    ]
},
  "bbox": [],
  "geometry": {"coordinates":[-118.6333,34.4833],"type":"Point"}
}