{
  "id": 7063949,
  "type": "Feature",
  "properties": {
    "tgn:hierarchy":[
        "tgn:7063949",
        "tgn:1000003",
        "tgn:7003676",
        "tgn:7000084",
        "tgn:7029392"
    ],
    "tgn:id":7063949,
    "tgn:name":"Auguststadt",
    "tgn:placetype":[
        "aat:300000745"
    ]
},
  "bbox": [],
  "geometry": {"coordinates":[10.533333,52.183333],"type":"Point"}
}