{
  "id": 2282274,
  "type": "Feature",
  "properties": {
    "tgn:hierarchy":[
        "tgn:2282274",
        "tgn:1000001",
        "tgn:7012149",
        "tgn:1002800",
        "tgn:7007710",
        "tgn:7029392"
    ],
    "tgn:id":2282274,
    "tgn:name":"Deer Lick Hollow",
    "tgn:placetype":[
        "aat:300008761"
    ]
},
  "bbox": [],
  "geometry": {"coordinates":[-77.65,41.7167],"type":"Point"}
}