{
  "id": 7218285,
  "type": "Feature",
  "properties": {
    "tgn:hierarchy":[
        "tgn:7218285",
        "tgn:7011167",
        "tgn:7001338",
        "tgn:1000003",
        "tgn:1000074",
        "tgn:7029392"
    ],
    "tgn:id":7218285,
    "tgn:name":"Xirok\u00e1stellon",
    "tgn:placetype":[
        "aat:300008347"
    ]
},
  "bbox": [],
  "geometry": {"coordinates":[20.95,37.75],"type":"Point"}
}