{
  "id": 7205159,
  "type": "Feature",
  "properties": {
    "tgn:hierarchy":[
        "tgn:7205159",
        "tgn:1000003",
        "tgn:7003677",
        "tgn:7000084",
        "tgn:7029392"
    ],
    "tgn:id":7205159,
    "tgn:name":"B\u00fchren",
    "tgn:placetype":[
        "aat:300000206"
    ]
},
  "bbox": [],
  "geometry": {"coordinates":[7.516667,51.283333],"type":"Point"}
}