{
  "id": 2654237,
  "type": "Feature",
  "properties": {
    "tgn:hierarchy":[
        "tgn:2654237",
        "tgn:1000001",
        "tgn:7012149",
        "tgn:2000907",
        "tgn:7007256",
        "tgn:7029392"
    ],
    "tgn:id":2654237,
    "tgn:name":"Shady Bradley Lake",
    "tgn:placetype":[
        "aat:300008680"
    ]
},
  "bbox": [],
  "geometry": {"coordinates":[-91.35,31.75],"type":"Point"}
}