{
  "id": 2717949,
  "type": "Feature",
  "properties": {
    "tgn:hierarchy":[
        "tgn:2717949",
        "tgn:7002659",
        "tgn:1000001",
        "tgn:2000016",
        "tgn:7012149",
        "tgn:7029392"
    ],
    "tgn:id":2717949,
    "tgn:name":"Thomason Cave",
    "tgn:placetype":[
        "aat:300008746"
    ]
},
  "bbox": [],
  "geometry": {"coordinates":[-87.9667,34.7833],"type":"Point"}
}