{
  "id": 2309101,
  "type": "Feature",
  "properties": {
    "tgn:hierarchy":[
        "tgn:2309101",
        "tgn:1000001",
        "tgn:7012149",
        "tgn:2001665",
        "tgn:7007707",
        "tgn:7029392"
    ],
    "tgn:id":2309101,
    "tgn:name":"East Sandy Creek",
    "tgn:placetype":[
        "aat:300008706"
    ]
},
  "bbox": [],
  "geometry": {"coordinates":[-97.45,34.0167],"type":"Point"}
}