{
  "id": 2771626,
  "type": "Feature",
  "properties": {
    "tgn:hierarchy":[
        "tgn:2771626",
        "tgn:1000001",
        "tgn:7012149",
        "tgn:2001233",
        "tgn:7007523",
        "tgn:7029392"
    ],
    "tgn:id":2771626,
    "tgn:name":"Wildwood Cave",
    "tgn:placetype":[
        "aat:300008746"
    ]
},
  "bbox": [],
  "geometry": {"coordinates":[-92.1333,37.7833],"type":"Point"}
}