{
  "id": 2044194,
  "type": "Feature",
  "properties": {
    "tgn:hierarchy":[
        "tgn:2044194",
        "tgn:1000001",
        "tgn:7012149",
        "tgn:2000885",
        "tgn:7007256",
        "tgn:7029392"
    ],
    "tgn:id":2044194,
    "tgn:name":"Union Landing",
    "tgn:placetype":[
        "aat:300008347",
        "aat:300387210"
    ]
},
  "bbox": [],
  "geometry": {"coordinates":[-90.6833,30.3167],"type":"Point"}
}