{
  "id": 7589034,
  "type": "Feature",
  "properties": {
    "tgn:hierarchy":[
        "tgn:7589034",
        "tgn:1000004",
        "tgn:7000198",
        "tgn:7000799",
        "tgn:7029392"
    ],
    "tgn:id":7589034,
    "tgn:name:en":"Nih\u0101la",
    "tgn:placetype":[
        "aat:300008347"
    ]
},
  "bbox": [],
  "geometry": {"coordinates":[74.150509,33.112355],"type":"Point"}
}