{
  "id": 7521193,
  "type": "Feature",
  "properties": {
    "tgn:hierarchy":[
        "tgn:7521193",
        "tgn:7001242",
        "tgn:7016833",
        "tgn:1001123",
        "tgn:7029392"
    ],
    "tgn:id":7521193,
    "tgn:name":"Ab\u016b Bitt\u012b, Maq\u0163a'",
    "tgn:placetype":[
        "aat:300008713"
    ]
},
  "bbox": [],
  "geometry": {"coordinates":[32.027778,31.316667],"type":"Point"}
}