<<<<<<< HEAD
{
  "id": 7247380,
  "type": "Feature",
  "properties": {
    "tgn:hierarchy":[
        "tgn:7247380",
        "tgn:7007877",
        "tgn:1000003",
        "tgn:1000063",
        "tgn:4012014",
        "tgn:7029392"
    ],
    "tgn:id":7247380,
    "tgn:name":"Chapelle-\u00e0-Oie, Ruisseau de",
    "tgn:placetype":[
        "aat:300008699"
    ]
},
  "bbox": [],
  "geometry": {"coordinates":[3.635037,50.577511],"type":"Point"}
}
=======
{"geometry":{"type":"Point","coordinates":[3.635037,50.577511]},"type":"Feature","properties":{"hierarchy":["tgn:7247380","tgn:7007877","tgn:1000003","tgn:1000063","tgn:4012014","tgn:7029392"],"placetype":["aat:300008699"],"id":7247380,"name:xx":"Chapelle-\u00e0-Oie, Ruisseau de"}}
>>>>>>> 03f74aca74312dbeaf24d7e61306dd6a786dc3d0
