{
  "id": 2314085,
  "type": "Feature",
  "properties": {
    "tgn:hierarchy":[
        "tgn:2314085",
        "tgn:1002247",
        "tgn:1000001",
        "tgn:7012149",
        "tgn:7007516",
        "tgn:7029392"
    ],
    "tgn:id":2314085,
    "tgn:name":"Elk",
    "tgn:placetype":[
        "aat:300008347"
    ]
},
  "bbox": [],
  "geometry": {"coordinates":[-75.8333,39.5333],"type":"Point"}
}