{
  "id": 2224233,
  "type": "Feature",
  "properties": {
    "tgn:hierarchy":[
        "tgn:2224233",
        "tgn:1000001",
        "tgn:7012149",
        "tgn:2001868",
        "tgn:7007825",
        "tgn:7029392"
    ],
    "tgn:id":2224233,
    "tgn:name":"Casablanca",
    "tgn:placetype":[
        "aat:300008347"
    ]
},
  "bbox": [],
  "geometry": {"coordinates":[-83.3167,36.2167],"type":"Point"}
}