{
  "id": 7404401,
  "type": "Feature",
  "properties": {
    "tgn:hierarchy":[
        "tgn:7404401",
        "tgn:7005585",
        "tgn:1000001",
        "tgn:7005560",
        "tgn:7029392"
    ],
    "tgn:id":7404401,
    "tgn:name":"Agua Escondida",
    "tgn:placetype":[
        "aat:300008347"
    ]
},
  "bbox": [],
  "geometry": {"coordinates":[-100.483333,18.116667],"type":"Point"}
}