{
  "id": 2183928,
  "type": "Feature",
  "properties": {
    "tgn:hierarchy":[
        "tgn:2183928",
        "tgn:1000001",
        "tgn:7012149",
        "tgn:2002297",
        "tgn:7013961",
        "tgn:7029392"
    ],
    "tgn:id":2183928,
    "tgn:name":"Boardtree Run",
    "tgn:placetype":[
        "aat:300008699"
    ]
},
  "bbox": [],
  "geometry": {"coordinates":[-80.7667,39.5167],"type":"Point"}
}