{
  "id": 2377982,
  "type": "Feature",
  "properties": {
    "tgn:hierarchy":[
        "tgn:2377982",
        "tgn:1000001",
        "tgn:7006451",
        "tgn:2000095",
        "tgn:7012149",
        "tgn:7029392"
    ],
    "tgn:id":2377982,
    "tgn:name":"Harris Camp Spring",
    "tgn:placetype":[
        "aat:300008697"
    ]
},
  "bbox": [],
  "geometry": {"coordinates":[-109.2667,32.8333],"type":"Point"}
}