{
  "id": 2178139,
  "type": "Feature",
  "properties": {
    "tgn:hierarchy":[
        "tgn:2178139",
        "tgn:1000001",
        "tgn:7012149",
        "tgn:2001274",
        "tgn:7007524",
        "tgn:7029392"
    ],
    "tgn:id":2178139,
    "tgn:name":"Blackfoot Lake",
    "tgn:placetype":[
        "aat:300008680"
    ]
},
  "bbox": [],
  "geometry": {"coordinates":[-113.9167,48.1667],"type":"Point"}
}