{
  "id": 7179500,
  "type": "Feature",
  "properties": {
    "tgn:hierarchy":[
        "tgn:7179500",
        "tgn:1000003",
        "tgn:7003677",
        "tgn:7000084",
        "tgn:7029392"
    ],
    "tgn:id":7179500,
    "tgn:name":"Gr\u00fcvingholz",
    "tgn:placetype":[
        "aat:300008863"
    ]
},
  "bbox": [],
  "geometry": {"coordinates":[7.466667,51.566667],"type":"Point"}
}