{
  "id": 7464220,
  "type": "Feature",
  "properties": {
    "tgn:hierarchy":[
        "tgn:7464220",
        "tgn:7002445",
        "tgn:1000003",
        "tgn:7008129",
        "tgn:7008591",
        "tgn:7029392"
    ],
    "tgn:id":7464220,
    "tgn:name:en":"Bexhill Reef",
    "tgn:placetype":[
        "aat:300008808"
    ]
},
  "bbox": [],
  "geometry": {"coordinates":[0.483333,50.833333],"type":"Point"}
}