{
  "id": 2645551,
  "type": "Feature",
  "properties": {
    "tgn:hierarchy":[
        "tgn:2645551",
        "tgn:1002201",
        "tgn:1000001",
        "tgn:7012149",
        "tgn:7007517",
        "tgn:7029392"
    ],
    "tgn:id":2645551,
    "tgn:name":"Sawdy Pond",
    "tgn:placetype":[
        "aat:300008680"
    ]
},
  "bbox": [],
  "geometry": {"coordinates":[-71.1333,41.6167],"type":"Point"}
}