{
  "id": 2083971,
  "type": "Feature",
  "properties": {
    "tgn:hierarchy":[
        "tgn:2083971",
        "tgn:2001627",
        "tgn:1000001",
        "tgn:7012149",
        "tgn:7007707",
        "tgn:7029392"
    ],
    "tgn:id":2083971,
    "tgn:name":"Sayre",
    "tgn:placetype":[
        "aat:300008347"
    ]
},
  "bbox": [],
  "geometry": {"coordinates":[-99.6333,35.2833],"type":"Point"}
}