{
  "id": 1057694,
  "type": "Feature",
  "properties": {
    "tgn:hierarchy":[
        "tgn:1057694",
        "tgn:1000004",
        "tgn:6004412",
        "tgn:7018214",
        "tgn:7002435",
        "tgn:7029392"
    ],
    "tgn:id":1057694,
    "tgn:name":"Novokarasuk",
    "tgn:placetype":[
        "aat:300008347"
    ]
},
  "bbox": [],
  "geometry": {"coordinates":[71.7667,56.2667],"type":"Point"}
}