{
  "id": 7549767,
  "type": "Feature",
  "properties": {
    "tgn:hierarchy":[
        "tgn:7549767",
        "tgn:1000004",
        "tgn:7000198",
        "tgn:1001894",
        "tgn:7029392"
    ],
    "tgn:id":7549767,
    "tgn:name:en":"B\u012bj\u0101garh Fort",
    "tgn:placetype":[
        "aat:300006909"
    ]
},
  "bbox": [],
  "geometry": {"coordinates":[75.35,21.683333],"type":"Point"}
}