<<<<<<< HEAD
{
  "id": 2156806,
  "type": "Feature",
  "properties": {
    "tgn:hierarchy":[
        "tgn:2156806",
        "tgn:1000001",
        "tgn:1002249",
        "tgn:7012149",
        "tgn:7007710",
        "tgn:7029392"
    ],
    "tgn:id":2156806,
    "tgn:name":"Beatty Hollow",
    "tgn:placetype":[
        "aat:300008761"
    ]
},
  "bbox": [],
  "geometry": {"coordinates":[-77.7167,41.0],"type":"Point"}
}
=======
{"geometry":{"type":"Point","coordinates":[-77.716700,41.000000]},"type":"Feature","properties":{"hierarchy":["tgn:2156806","tgn:1000001","tgn:1002249","tgn:7012149","tgn:7007710","tgn:7029392"],"placetype":["aat:300008761"],"id":2156806,"name:xx":"Beatty Hollow"}}
>>>>>>> 03f74aca74312dbeaf24d7e61306dd6a786dc3d0
