{
  "id": 7233649,
  "type": "Feature",
  "properties": {
    "tgn:hierarchy":[
        "tgn:7233649",
        "tgn:7002752",
        "tgn:7001399",
        "tgn:1000003",
        "tgn:1000074",
        "tgn:7029392"
    ],
    "tgn:id":7233649,
    "tgn:name":"D\u00edlofon",
    "tgn:placetype":[
        "aat:300008347"
    ]
},
  "bbox": [],
  "geometry": {"coordinates":[21.6125,39.543056],"type":"Point"}
}