{
  "id": 7439924,
  "type": "Feature",
  "properties": {
    "tgn:hierarchy":[
        "tgn:7439924",
        "tgn:7005581",
        "tgn:1000001",
        "tgn:7005560",
        "tgn:7029392"
    ],
    "tgn:id":7439924,
    "tgn:name":"Rancho San Mart\u00edn",
    "tgn:placetype":[
        "aat:300000241"
    ]
},
  "bbox": [],
  "geometry": {"coordinates":[-106.55,30.816667],"type":"Point"}
}