{
  "id": 2174513,
  "type": "Feature",
  "properties": {
    "tgn:hierarchy":[
        "tgn:2174513",
        "tgn:7006450",
        "tgn:1000001",
        "tgn:7012149",
        "tgn:2000089",
        "tgn:7029392"
    ],
    "tgn:id":2174513,
    "tgn:name":"Bishop Rock",
    "tgn:placetype":[
        "aat:300008798"
    ]
},
  "bbox": [],
  "geometry": {"coordinates":[-157.35,64.8167],"type":"Point"}
}