{
  "id": 2183167,
  "type": "Feature",
  "properties": {
    "tgn:hierarchy":[
        "tgn:2183167",
        "tgn:1000001",
        "tgn:2001734",
        "tgn:7012149",
        "tgn:7007712",
        "tgn:7029392"
    ],
    "tgn:id":2183167,
    "tgn:name":"Bluehouse Swamp",
    "tgn:placetype":[
        "aat:300008905"
    ]
},
  "bbox": [],
  "geometry": {"coordinates":[-80.0667,32.9833],"type":"Point"}
}