<<<<<<< HEAD
{
  "id": 2335408,
  "type": "Feature",
  "properties": {
    "tgn:hierarchy":[
        "tgn:2335408",
        "tgn:1000001",
        "tgn:7013942",
        "tgn:7012149",
        "tgn:7007517",
        "tgn:7029392"
    ],
    "tgn:id":2335408,
    "tgn:name":"Fort Morrison",
    "tgn:placetype":[
        "aat:300008347"
    ]
},
  "bbox": [],
  "geometry": {"coordinates":[-72.6833,42.6833],"type":"Point"}
}
=======
{"geometry":{"type":"Point","coordinates":[-72.683300,42.683300]},"type":"Feature","properties":{"hierarchy":["tgn:2335408","tgn:1000001","tgn:7013942","tgn:7012149","tgn:7007517","tgn:7029392"],"placetype":["aat:300008347"],"id":2335408,"name:xx":"Fort Morrison"}}
>>>>>>> 03f74aca74312dbeaf24d7e61306dd6a786dc3d0
