<<<<<<< HEAD
{
  "id": 7112672,
  "type": "Feature",
  "properties": {
    "tgn:hierarchy":[
        "tgn:7112672",
        "tgn:1000003",
        "tgn:7003685",
        "tgn:7000084",
        "tgn:7029392"
    ],
    "tgn:id":7112672,
    "tgn:name":"Rosenthal",
    "tgn:placetype":[
        "aat:300008347"
    ]
},
  "bbox": [],
  "geometry": {"coordinates":[14.9,50.95],"type":"Point"}
}
=======
{"geometry":{"type":"Point","coordinates":[14.900000,50.950000]},"type":"Feature","properties":{"hierarchy":["tgn:7112672","tgn:1000003","tgn:7003685","tgn:7000084","tgn:7029392"],"placetype":["aat:300008347"],"id":7112672,"name:xx":"Rosenthal"}}
>>>>>>> 03f74aca74312dbeaf24d7e61306dd6a786dc3d0
