{
  "id": 7008037,
  "type": "Feature",
  "properties": {
    "tgn:hierarchy":[
        "tgn:7008037",
        "tgn:1000003",
        "tgn:7002883",
        "tgn:1000070",
        "tgn:7029392"
    ],
    "tgn:id":7008037,
    "tgn:name":"Saint-Ouen-l'Aum\u00f4ne",
    "tgn:placetype":[
        "aat:300008347"
    ]
},
  "bbox": [],
  "geometry": {"coordinates":[2.1167,49.0333],"type":"Point"}
}