{
  "id": 2150131,
  "type": "Feature",
  "properties": {
    "tgn:hierarchy":[
        "tgn:2150131",
        "tgn:1000001",
        "tgn:7012149",
        "tgn:1002952",
        "tgn:7007826",
        "tgn:7029392"
    ],
    "tgn:id":2150131,
    "tgn:name":"Barton Springs",
    "tgn:placetype":[
        "aat:300008697"
    ]
},
  "bbox": [],
  "geometry": {"coordinates":[-97.7667,30.25],"type":"Point"}
}