<<<<<<< HEAD
{
  "id": 2150131,
  "type": "Feature",
  "properties": {
    "tgn:hierarchy":[
        "tgn:2150131",
        "tgn:1000001",
        "tgn:7012149",
        "tgn:1002952",
        "tgn:7007826",
        "tgn:7029392"
    ],
    "tgn:id":2150131,
    "tgn:name":"Barton Springs",
    "tgn:placetype":[
        "aat:300008697"
    ]
},
  "bbox": [],
  "geometry": {"coordinates":[-97.7667,30.25],"type":"Point"}
}
=======
{"geometry":{"type":"Point","coordinates":[-97.766700,30.250000]},"type":"Feature","properties":{"hierarchy":["tgn:2150131","tgn:1000001","tgn:7012149","tgn:1002952","tgn:7007826","tgn:7029392"],"placetype":["aat:300008697"],"id":2150131,"name:xx":"Barton Springs"}}
>>>>>>> 03f74aca74312dbeaf24d7e61306dd6a786dc3d0
