{
  "id": 7328982,
  "type": "Feature",
  "properties": {
    "tgn:hierarchy":[
        "tgn:7328982",
        "tgn:7002847",
        "tgn:1001647",
        "tgn:1000003",
        "tgn:1000095",
        "tgn:7029392"
    ],
    "tgn:id":7328982,
    "tgn:name":"Pusa, R\u00edo",
    "tgn:placetype":[
        "aat:300008699"
    ]
},
  "bbox": [],
  "geometry": {"coordinates":[-4.566667,39.916667],"type":"Point"}
}