{
  "id": 7011109,
  "type": "Feature",
  "properties": {
    "tgn:hierarchy":[
        "tgn:7011109",
        "tgn:1000003",
        "tgn:7003828",
        "tgn:1000090",
        "tgn:7029392"
    ],
    "tgn:id":7011109,
    "tgn:name":"Viseu",
    "tgn:placetype":[
        "aat:300387277",
        "aat:300008347",
        "aat:300387222",
        "aat:300387308",
        "aat:300387319",
        "aat:300008375",
        "aat:300020533"
    ]
},
  "bbox": [],
  "geometry": {"coordinates":[-7.909714,40.661014],"type":"Point"}
}