{
  "id": 2499052,
  "type": "Feature",
  "properties": {
    "tgn:hierarchy":[
        "tgn:2499052",
        "tgn:1000001",
        "tgn:7012149",
        "tgn:2001108",
        "tgn:7007522",
        "tgn:7029392"
    ],
    "tgn:id":2499052,
    "tgn:name":"McCarty Bayou",
    "tgn:placetype":[
        "aat:300008699"
    ]
},
  "bbox": [],
  "geometry": {"coordinates":[-89.65,30.3833],"type":"Point"}
}