{
  "id": 2541566,
  "type": "Feature",
  "properties": {
    "tgn:hierarchy":[
        "tgn:2541566",
        "tgn:1000001",
        "tgn:7012149",
        "tgn:2001716",
        "tgn:7007708",
        "tgn:7029392"
    ],
    "tgn:id":2541566,
    "tgn:name":"Nimrod Butte",
    "tgn:placetype":[
        "aat:300008798"
    ]
},
  "bbox": [],
  "geometry": {"coordinates":[-122.4167,44.0333],"type":"Point"}
}