<<<<<<< HEAD
{
  "id": 7058780,
  "type": "Feature",
  "properties": {
    "tgn:hierarchy":[
        "tgn:7058780",
        "tgn:7003007",
        "tgn:1000003",
        "tgn:7002997",
        "tgn:1000080",
        "tgn:7029392"
    ],
    "tgn:id":7058780,
    "tgn:name":"Bonaldo",
    "tgn:placetype":[
        "aat:300008347"
    ]
},
  "bbox": [],
  "geometry": {"coordinates":[11.333333,45.333333],"type":"Point"}
}
=======
{"geometry":{"type":"Point","coordinates":[11.333333,45.333333]},"type":"Feature","properties":{"hierarchy":["tgn:7058780","tgn:7003007","tgn:1000003","tgn:7002997","tgn:1000080","tgn:7029392"],"placetype":["aat:300008347"],"id":7058780,"name:xx":"Bonaldo"}}
>>>>>>> 03f74aca74312dbeaf24d7e61306dd6a786dc3d0
