{
  "id": 2035381,
  "type": "Feature",
  "properties": {
    "tgn:hierarchy":[
        "tgn:2035381",
        "tgn:1000001",
        "tgn:7012149",
        "tgn:2000613",
        "tgn:7007253",
        "tgn:7029392"
    ],
    "tgn:id":2035381,
    "tgn:name":"Olin",
    "tgn:placetype":[
        "aat:300008347"
    ]
},
  "bbox": [],
  "geometry": {"coordinates":[-91.1333,41.9833],"type":"Point"}
}