{
  "id": 2673598,
  "type": "Feature",
  "properties": {
    "tgn:hierarchy":[
        "tgn:2673598",
        "tgn:1000001",
        "tgn:7012149",
        "tgn:2001120",
        "tgn:7007522",
        "tgn:7029392"
    ],
    "tgn:id":2673598,
    "tgn:name":"Snoody Creek",
    "tgn:placetype":[
        "aat:300008706"
    ]
},
  "bbox": [],
  "geometry": {"coordinates":[-88.65,32.7667],"type":"Point"}
}