{
  "id": 7204745,
  "type": "Feature",
  "properties": {
    "tgn:hierarchy":[
        "tgn:7204745",
        "tgn:7003692",
        "tgn:1000003",
        "tgn:7000084",
        "tgn:7029392"
    ],
    "tgn:id":7204745,
    "tgn:name":"B\u00fcchelbronn",
    "tgn:placetype":[
        "aat:300008347"
    ]
},
  "bbox": [],
  "geometry": {"coordinates":[8.816667,48.733333],"type":"Point"}
}