{
  "id": 7211125,
  "type": "Feature",
  "properties": {
    "tgn:hierarchy":[
        "tgn:7211125",
        "tgn:1000003",
        "tgn:7003677",
        "tgn:7000084",
        "tgn:7029392"
    ],
    "tgn:id":7211125,
    "tgn:name":"Beiert",
    "tgn:placetype":[
        "aat:300000206"
    ]
},
  "bbox": [],
  "geometry": {"coordinates":[7.366667,50.75],"type":"Point"}
}