{
  "id": 7550922,
  "type": "Feature",
  "properties": {
    "tgn:hierarchy":[
        "tgn:7550922",
        "tgn:1000004",
        "tgn:7000198",
        "tgn:1001894",
        "tgn:7029392"
    ],
    "tgn:id":7550922,
    "tgn:name:en":"D\u012bgod",
    "tgn:placetype":[
        "aat:300008347"
    ]
},
  "bbox": [],
  "geometry": {"coordinates":[77.568369,25.031534],"type":"Point"}
}