{
  "id": 7466124,
  "type": "Feature",
  "properties": {
    "tgn:hierarchy":[
        "tgn:7466124",
        "tgn:7019053",
        "tgn:7002445",
        "tgn:1000003",
        "tgn:7029505",
        "tgn:7008591",
        "tgn:7029392"
    ],
    "tgn:id":7466124,
    "tgn:name:en":"Barnbrough",
    "tgn:placetype":[
        "aat:300008347"
    ]
},
  "bbox": [],
  "geometry": {"coordinates":[-1.266667,53.516667],"type":"Point"}
}