{
  "id": 2037393,
  "type": "Feature",
  "properties": {
    "tgn:hierarchy":[
        "tgn:2037393",
        "tgn:1000001",
        "tgn:2000677",
        "tgn:7012149",
        "tgn:7007254",
        "tgn:7029392"
    ],
    "tgn:id":2037393,
    "tgn:name":"Winfield",
    "tgn:placetype":[
        "aat:300008347"
    ]
},
  "bbox": [],
  "geometry": {"coordinates":[-96.9833,37.2333],"type":"Point"}
}