{
  "id": 7326424,
  "type": "Feature",
  "properties": {
    "tgn:hierarchy":[
        "tgn:7326424",
        "tgn:7002834",
        "tgn:1000003",
        "tgn:7002786",
        "tgn:1000095",
        "tgn:7029392"
    ],
    "tgn:id":7326424,
    "tgn:name":"Perral, Arroyo",
    "tgn:placetype":[
        "aat:300008699"
    ]
},
  "bbox": [],
  "geometry": {"coordinates":[-8.616667,42.166667],"type":"Point"}
}