<<<<<<< HEAD
{
  "id": 7475979,
  "type": "Feature",
  "properties": {
    "tgn:hierarchy":[
        "tgn:7475979",
        "tgn:1000004",
        "tgn:7471332",
        "tgn:1000141",
        "tgn:7029392"
    ],
    "tgn:id":7475979,
    "tgn:name":"Bopomo Houyuan",
    "tgn:placetype":[
        "aat:300008187"
    ]
},
  "bbox": [],
  "geometry": {"coordinates":[121.005659,24.735862],"type":"Point"}
}
=======
{"geometry":{"type":"Point","coordinates":[121.005659,24.735862]},"type":"Feature","properties":{"hierarchy":["tgn:7475979","tgn:1000004","tgn:7471332","tgn:1000141","tgn:7029392"],"placetype":["aat:300008187"],"id":7475979,"name:xx":"Bopomo Houyuan"}}
>>>>>>> 03f74aca74312dbeaf24d7e61306dd6a786dc3d0
