{
  "id": 2268845,
  "type": "Feature",
  "properties": {
    "tgn:hierarchy":[
        "tgn:2268845",
        "tgn:1000001",
        "tgn:7012149",
        "tgn:2001851",
        "tgn:7007825",
        "tgn:7029392"
    ],
    "tgn:id":2268845,
    "tgn:name":"Cross Mountain Prospect",
    "tgn:placetype":[
        "aat:300000390"
    ]
},
  "bbox": [],
  "geometry": {"coordinates":[-82.9167,35.9167],"type":"Point"}
}