{
  "id": 7592671,
  "type": "Feature",
  "properties": {
    "tgn:hierarchy":[
        "tgn:7592671",
        "tgn:1000004",
        "tgn:7000198",
        "tgn:7000799",
        "tgn:7029392"
    ],
    "tgn:id":7592671,
    "tgn:name:en":"Garhi",
    "tgn:placetype":[
        "aat:300008347"
    ]
},
  "bbox": [],
  "geometry": {"coordinates":[74.783047,32.899],"type":"Point"}
}