{
  "id": 7402610,
  "type": "Feature",
  "properties": {
    "tgn:hierarchy":[
        "tgn:7402610",
        "tgn:1000001",
        "tgn:1001937",
        "tgn:7005560",
        "tgn:7029392"
    ],
    "tgn:id":7402610,
    "tgn:name":"Chum Kop\u00f3",
    "tgn:placetype":[
        "aat:300008347"
    ]
},
  "bbox": [],
  "geometry": {"coordinates":[-87.566667,20.179167],"type":"Point"}
}