{
  "id": 7236568,
  "type": "Feature",
  "properties": {
    "tgn:hierarchy":[
        "tgn:7236568",
        "tgn:7002706",
        "tgn:7002705",
        "tgn:1000003",
        "tgn:1000074",
        "tgn:7029392"
    ],
    "tgn:id":7236568,
    "tgn:name":"\u00c1no Kalent\u00edni",
    "tgn:placetype":[
        "aat:300008347"
    ]
},
  "bbox": [],
  "geometry": {"coordinates":[21.185278,39.25],"type":"Point"}
}