{
  "id": 7552953,
  "type": "Feature",
  "properties": {
    "tgn:hierarchy":[
        "tgn:7552953",
        "tgn:1000004",
        "tgn:7000198",
        "tgn:1001894",
        "tgn:7029392"
    ],
    "tgn:id":7552953,
    "tgn:name:en":"Mard\u0101npur",
    "tgn:placetype":[
        "aat:300008347"
    ]
},
  "bbox": [],
  "geometry": {"coordinates":[77.461897,22.652283],"type":"Point"}
}