{
  "id": 1046040,
  "type": "Feature",
  "properties": {
    "tgn:hierarchy":[
        "tgn:1046040",
        "tgn:7007850",
        "tgn:1003491",
        "tgn:1000003",
        "tgn:1000080",
        "tgn:7029392"
    ],
    "tgn:id":1046040,
    "tgn:name":"Plat\u00ec",
    "tgn:placetype":[
        "aat:300008347"
    ]
},
  "bbox": [],
  "geometry": {"coordinates":[16.05,38.216667],"type":"Point"}
}