{
  "id": 2244937,
  "type": "Feature",
  "properties": {
    "tgn:hierarchy":[
        "tgn:2244937",
        "tgn:1000001",
        "tgn:7012149",
        "tgn:7007157",
        "tgn:2000184",
        "tgn:7029392"
    ],
    "tgn:id":2244937,
    "tgn:name":"Clover Butte",
    "tgn:placetype":[
        "aat:300008798"
    ]
},
  "bbox": [],
  "geometry": {"coordinates":[-121.05,40.4667],"type":"Point"}
}