{
  "id": 2181827,
  "type": "Feature",
  "properties": {
    "tgn:hierarchy":[
        "tgn:2181827",
        "tgn:1000001",
        "tgn:7012149",
        "tgn:2002287",
        "tgn:7013961",
        "tgn:7029392"
    ],
    "tgn:id":2181827,
    "tgn:name":"Blue Knob",
    "tgn:placetype":[
        "aat:300008798"
    ]
},
  "bbox": [],
  "geometry": {"coordinates":[-80.2667,38.1667],"type":"Point"}
}