{
  "id": 2563647,
  "type": "Feature",
  "properties": {
    "tgn:hierarchy":[
        "tgn:2563647",
        "tgn:1000001",
        "tgn:7012149",
        "tgn:2001718",
        "tgn:7007708",
        "tgn:7029392"
    ],
    "tgn:id":2563647,
    "tgn:name":"Owyhee Butte",
    "tgn:placetype":[
        "aat:300008798"
    ]
},
  "bbox": [],
  "geometry": {"coordinates":[-117.6333,42.95],"type":"Point"}
}