{
  "id": 7045100,
  "type": "Feature",
  "properties": {
    "tgn:hierarchy":[
        "tgn:7045100",
        "tgn:7015163",
        "tgn:1000003",
        "tgn:7003121",
        "tgn:1000080",
        "tgn:7029392"
    ],
    "tgn:id":7045100,
    "tgn:name":"Corona Majore, Punta",
    "tgn:placetype":[
        "aat:300008795"
    ]
},
  "bbox": [],
  "geometry": {"coordinates":[8.666667,40.616667],"type":"Point"}
}