{
  "id": 2652585,
  "type": "Feature",
  "properties": {
    "tgn:hierarchy":[
        "tgn:2652585",
        "tgn:1000001",
        "tgn:7012149",
        "tgn:1002521",
        "tgn:7007920",
        "tgn:7029392"
    ],
    "tgn:id":2652585,
    "tgn:name":"Sentinel Peak",
    "tgn:placetype":[
        "aat:300008798"
    ]
},
  "bbox": [],
  "geometry": {"coordinates":[-123.3333,47.7667],"type":"Point"}
}