{
  "id": 7434956,
  "type": "Feature",
  "properties": {
    "tgn:hierarchy":[
        "tgn:7434956",
        "tgn:7005581",
        "tgn:1000001",
        "tgn:7005560",
        "tgn:7029392"
    ],
    "tgn:id":7434956,
    "tgn:name":"Vuelta de \u00c1lamos",
    "tgn:placetype":[
        "aat:300387007"
    ]
},
  "bbox": [],
  "geometry": {"coordinates":[-107.983333,30.75],"type":"Point"}
}