{
  "id": 2084068,
  "type": "Feature",
  "properties": {
    "tgn:hierarchy":[
        "tgn:2084068",
        "tgn:1000001",
        "tgn:7012149",
        "tgn:2001674",
        "tgn:7007707",
        "tgn:7029392"
    ],
    "tgn:id":2084068,
    "tgn:name":"Sumner",
    "tgn:placetype":[
        "aat:300008347"
    ]
},
  "bbox": [],
  "geometry": {"coordinates":[-97.1167,36.3167],"type":"Point"}
}