{
  "id": 7502324,
  "type": "Feature",
  "properties": {
    "tgn:hierarchy":[
        "tgn:7502324",
        "tgn:7001010",
        "tgn:1000004",
        "tgn:1000141",
        "tgn:7029392"
    ],
    "tgn:id":7502324,
    "tgn:name":"Baqi",
    "tgn:placetype":[
        "aat:300008347"
    ]
},
  "bbox": [],
  "geometry": {"coordinates":[121.556944,23.728056],"type":"Point"}
}