{
  "id": 7310176,
  "type": "Feature",
  "properties": {
    "tgn:hierarchy":[
        "tgn:7310176",
        "tgn:1001692",
        "tgn:1000049",
        "tgn:1000002",
        "tgn:7029392"
    ],
    "tgn:id":7310176,
    "tgn:name":"Niqu\u00e9n",
    "tgn:placetype":[
        "aat:300008347"
    ]
},
  "bbox": [],
  "geometry": {"coordinates":[-72.583333,-39.333333],"type":"Point"}
}