{
  "id": 1055159,
  "type": "Feature",
  "properties": {
    "tgn:hierarchy":[
        "tgn:1055159",
        "tgn:1000004",
        "tgn:7013207",
        "tgn:7018214",
        "tgn:7002435",
        "tgn:7029392"
    ],
    "tgn:id":1055159,
    "tgn:name":"Katrichev",
    "tgn:placetype":[
        "aat:300008347"
    ]
},
  "bbox": [],
  "geometry": {"coordinates":[45.55,49.3833],"type":"Point"}
}