<<<<<<< HEAD
{
  "id": 2406535,
  "type": "Feature",
  "properties": {
    "tgn:hierarchy":[
        "tgn:2406535",
        "tgn:1000001",
        "tgn:7016172",
        "tgn:7012149",
        "tgn:2000126",
        "tgn:7029392"
    ],
    "tgn:id":2406535,
    "tgn:name":"Hungry Run Creek",
    "tgn:placetype":[
        "aat:300008706"
    ]
},
  "bbox": [],
  "geometry": {"coordinates":[-91.8,33.7167],"type":"Point"}
}
=======
{"geometry":{"type":"Point","coordinates":[-91.800000,33.716700]},"type":"Feature","properties":{"hierarchy":["tgn:2406535","tgn:1000001","tgn:7016172","tgn:7012149","tgn:2000126","tgn:7029392"],"placetype":["aat:300008706"],"id":2406535,"name:xx":"Hungry Run Creek"}}
>>>>>>> 03f74aca74312dbeaf24d7e61306dd6a786dc3d0
