{
  "id": 2391988,
  "type": "Feature",
  "properties": {
    "tgn:hierarchy":[
        "tgn:2391988",
        "tgn:1002648",
        "tgn:1000001",
        "tgn:7019158",
        "tgn:7012149",
        "tgn:7007249",
        "tgn:7029392"
    ],
    "tgn:id":2391988,
    "tgn:name":"Hina, Mauna",
    "tgn:placetype":[
        "aat:300008798"
    ]
},
  "bbox": [],
  "geometry": {"coordinates":[-156.1833,20.7167],"type":"Point"}
}