{
  "id": 1081353,
  "type": "Feature",
  "properties": {
    "tgn:hierarchy":[
        "tgn:1081353",
        "tgn:1000971",
        "tgn:1000004",
        "tgn:7000894",
        "tgn:1000120",
        "tgn:7029392"
    ],
    "tgn:id":1081353,
    "tgn:name":"Shirako",
    "tgn:placetype":[
        "aat:300008347"
    ]
},
  "bbox": [],
  "geometry": {"coordinates":[140.3833,35.4333],"type":"Point"}
}