<<<<<<< HEAD
{
  "id": 2338214,
  "type": "Feature",
  "properties": {
    "tgn:hierarchy":[
        "tgn:2338214",
        "tgn:7013272",
        "tgn:1000001",
        "tgn:7012149",
        "tgn:7007710",
        "tgn:7029392"
    ],
    "tgn:id":2338214,
    "tgn:name":"Fox Ridge",
    "tgn:placetype":[
        "aat:300008347"
    ]
},
  "bbox": [],
  "geometry": {"coordinates":[-80.0167,40.55],"type":"Point"}
}
=======
{"geometry":{"type":"Point","coordinates":[-80.016700,40.550000]},"type":"Feature","properties":{"hierarchy":["tgn:2338214","tgn:7013272","tgn:1000001","tgn:7012149","tgn:7007710","tgn:7029392"],"placetype":["aat:300008347"],"id":2338214,"name:xx":"Fox Ridge"}}
>>>>>>> 03f74aca74312dbeaf24d7e61306dd6a786dc3d0
