{
  "id": 2614207,
  "type": "Feature",
  "properties": {
    "tgn:hierarchy":[
        "tgn:2614207",
        "tgn:7002659",
        "tgn:1000001",
        "tgn:7012149",
        "tgn:2000060",
        "tgn:7029392"
    ],
    "tgn:id":2614207,
    "tgn:name":"Refuge",
    "tgn:placetype":[
        "aat:300008347"
    ]
},
  "bbox": [],
  "geometry": {"coordinates":[-86.1167,33.65],"type":"Point"}
}