<<<<<<< HEAD
{
  "id": 2258460,
  "type": "Feature",
  "properties": {
    "tgn:hierarchy":[
        "tgn:2258460",
        "tgn:1000001",
        "tgn:1002222",
        "tgn:7012149",
        "tgn:7007520",
        "tgn:7029392"
    ],
    "tgn:id":2258460,
    "tgn:name":"Cotton Lake",
    "tgn:placetype":[
        "aat:300008680"
    ]
},
  "bbox": [],
  "geometry": {"coordinates":[-85.1667,42.2],"type":"Point"}
}
=======
{"geometry":{"type":"Point","coordinates":[-85.166700,42.200000]},"type":"Feature","properties":{"hierarchy":["tgn:2258460","tgn:1000001","tgn:1002222","tgn:7012149","tgn:7007520","tgn:7029392"],"placetype":["aat:300008680"],"id":2258460,"name:xx":"Cotton Lake"}}
>>>>>>> 03f74aca74312dbeaf24d7e61306dd6a786dc3d0
