{
  "id": 2702879,
  "type": "Feature",
  "properties": {
    "tgn:hierarchy":[
        "tgn:2702879",
        "tgn:1000001",
        "tgn:7012149",
        "tgn:7007157",
        "tgn:7029392"
    ],
    "tgn:id":2702879,
    "tgn:name":"Sulphur Spring Canyon",
    "tgn:placetype":[
        "aat:300008761"
    ]
},
  "bbox": [],
  "geometry": {"coordinates":[-121.5333,37.5667],"type":"Point"}
}