{
  "id": 7345142,
  "type": "Feature",
  "properties": {
    "tgn:hierarchy":[
        "tgn:7345142",
        "tgn:7001165",
        "tgn:1000003",
        "tgn:7002793",
        "tgn:1000095",
        "tgn:7029392"
    ],
    "tgn:id":7345142,
    "tgn:name":"Algimia de Alfara",
    "tgn:placetype":[
        "aat:300008347"
    ]
},
  "bbox": [],
  "geometry": {"coordinates":[-0.366667,39.75],"type":"Point"}
}