{
  "id": 7414907,
  "type": "Feature",
  "properties": {
    "tgn:hierarchy":[
        "tgn:7414907",
        "tgn:7005584",
        "tgn:1000001",
        "tgn:7005560",
        "tgn:7029392"
    ],
    "tgn:id":7414907,
    "tgn:name":"La Paz",
    "tgn:placetype":[
        "aat:300008347"
    ]
},
  "bbox": [],
  "geometry": {"coordinates":[-101.746111,20.226389],"type":"Point"}
}