{
  "id": 2395100,
  "type": "Feature",
  "properties": {
    "tgn:hierarchy":[
        "tgn:2395100",
        "tgn:1000001",
        "tgn:7012149",
        "tgn:7007157",
        "tgn:2000189",
        "tgn:7029392"
    ],
    "tgn:id":2395100,
    "tgn:name":"Hole in the Ground Lake",
    "tgn:placetype":[
        "aat:300006191"
    ]
},
  "bbox": [],
  "geometry": {"coordinates":[-122.4833,41.5333],"type":"Point"}
}