{
  "id": 7585892,
  "type": "Feature",
  "properties": {
    "tgn:hierarchy":[
        "tgn:7585892",
        "tgn:1000004",
        "tgn:7000198",
        "tgn:7000799",
        "tgn:7029392"
    ],
    "tgn:id":7585892,
    "tgn:name:en":"Chh\u016bl N\u0101r",
    "tgn:placetype":[
        "aat:300008699"
    ]
},
  "bbox": [],
  "geometry": {"coordinates":[74.794444,34.305556],"type":"Point"}
}