{
  "id": 1066789,
  "type": "Feature",
  "properties": {
    "tgn:hierarchy":[
        "tgn:1066789",
        "tgn:1000004",
        "tgn:7005232",
        "tgn:1000111",
        "tgn:7029392"
    ],
    "tgn:id":1066789,
    "tgn:name":"Baoxikou",
    "tgn:placetype":[
        "aat:300008347"
    ]
},
  "bbox": [],
  "geometry": {"coordinates":[115.2333,23.2667],"type":"Point"}
}