{
  "id": 7405260,
  "type": "Feature",
  "properties": {
    "tgn:hierarchy":[
        "tgn:7405260",
        "tgn:7005585",
        "tgn:1000001",
        "tgn:7005560",
        "tgn:7029392"
    ],
    "tgn:id":7405260,
    "tgn:name":"Carrizalito, Cerro",
    "tgn:placetype":[
        "aat:300008795"
    ]
},
  "bbox": [],
  "geometry": {"coordinates":[-99.816667,17.45],"type":"Point"}
}