{
  "id": 2131048,
  "type": "Feature",
  "properties": {
    "tgn:hierarchy":[
        "tgn:2131048",
        "tgn:1000001",
        "tgn:7012149",
        "tgn:7007157",
        "tgn:1002894",
        "tgn:7029392"
    ],
    "tgn:id":2131048,
    "tgn:name":"Alpha Mine",
    "tgn:placetype":[
        "aat:300000390"
    ]
},
  "bbox": [],
  "geometry": {"coordinates":[-120.85,39.5167],"type":"Point"}
}