{
  "id": 2182997,
  "type": "Feature",
  "properties": {
    "tgn:hierarchy":[
        "tgn:2182997",
        "tgn:1000001",
        "tgn:7012149",
        "tgn:7007157",
        "tgn:2000189",
        "tgn:7029392"
    ],
    "tgn:id":2182997,
    "tgn:name":"Blueberry Lake",
    "tgn:placetype":[
        "aat:300008680"
    ]
},
  "bbox": [],
  "geometry": {"coordinates":[-123.1333,41.4833],"type":"Point"}
}