<<<<<<< HEAD
{
  "id": 7170061,
  "type": "Feature",
  "properties": {
    "tgn:hierarchy":[
        "tgn:7170061",
        "tgn:1000003",
        "tgn:7003682",
        "tgn:7000084",
        "tgn:7029392"
    ],
    "tgn:id":7170061,
    "tgn:name":"Herbstm\u00fchle",
    "tgn:placetype":[
        "aat:300008347"
    ]
},
  "bbox": [],
  "geometry": {"coordinates":[6.216667,50.0],"type":"Point"}
}
=======
{"geometry":{"type":"Point","coordinates":[6.216667,50.000000]},"type":"Feature","properties":{"hierarchy":["tgn:7170061","tgn:1000003","tgn:7003682","tgn:7000084","tgn:7029392"],"placetype":["aat:300008347"],"id":7170061,"name:xx":"Herbstm\u00fchle"}}
>>>>>>> 03f74aca74312dbeaf24d7e61306dd6a786dc3d0
