<<<<<<< HEAD
{
  "id": 2764747,
  "type": "Feature",
  "properties": {
    "tgn:hierarchy":[
        "tgn:2764747",
        "tgn:1000001",
        "tgn:7012149",
        "tgn:2001304",
        "tgn:7007524",
        "tgn:7029392"
    ],
    "tgn:id":2764747,
    "tgn:name":"Whiskey Creek",
    "tgn:placetype":[
        "aat:300008706"
    ]
},
  "bbox": [],
  "geometry": {"coordinates":[-114.5,47.4833],"type":"Point"}
}
=======
{"geometry":{"type":"Point","coordinates":[-114.500000,47.483300]},"type":"Feature","properties":{"hierarchy":["tgn:2764747","tgn:1000001","tgn:7012149","tgn:2001304","tgn:7007524","tgn:7029392"],"placetype":["aat:300008706"],"id":2764747,"name:xx":"Whiskey Creek"}}
>>>>>>> 03f74aca74312dbeaf24d7e61306dd6a786dc3d0
