{
  "id": 7282850,
  "type": "Feature",
  "properties": {
    "tgn:hierarchy":[
        "tgn:7282850",
        "tgn:1001637",
        "tgn:1000049",
        "tgn:1000002",
        "tgn:7029392"
    ],
    "tgn:id":7282850,
    "tgn:name":"Pelehuito",
    "tgn:placetype":[
        "aat:300387200"
    ]
},
  "bbox": [],
  "geometry": {"coordinates":[-72.266667,-36.616667],"type":"Point"}
}