{
  "id": 7278476,
  "type": "Feature",
  "properties": {
    "tgn:hierarchy":[
        "tgn:7278476",
        "tgn:1001705",
        "tgn:1000049",
        "tgn:1000002",
        "tgn:7029392"
    ],
    "tgn:id":7278476,
    "tgn:name":"Barrancas, Cerro",
    "tgn:placetype":[
        "aat:300008795"
    ]
},
  "bbox": [],
  "geometry": {"coordinates":[-70.416667,-36.183333],"type":"Point"}
}