{
  "id": 2651824,
  "type": "Feature",
  "properties": {
    "tgn:hierarchy":[
        "tgn:2651824",
        "tgn:1000001",
        "tgn:2001419",
        "tgn:7012149",
        "tgn:7007526",
        "tgn:7029392"
    ],
    "tgn:id":2651824,
    "tgn:name":"Segerstrom-Heizer Mine",
    "tgn:placetype":[
        "aat:300000390"
    ]
},
  "bbox": [],
  "geometry": {"coordinates":[-118.1333,40.0333],"type":"Point"}
}