{
  "id": 7428206,
  "type": "Feature",
  "properties": {
    "tgn:hierarchy":[
        "tgn:7428206",
        "tgn:7005581",
        "tgn:1000001",
        "tgn:7005560",
        "tgn:7029392"
    ],
    "tgn:id":7428206,
    "tgn:name":"Jacales",
    "tgn:placetype":[
        "aat:300008347"
    ]
},
  "bbox": [],
  "geometry": {"coordinates":[-104.85,27.35],"type":"Point"}
}