<<<<<<< HEAD
{
  "id": 2253561,
  "type": "Feature",
  "properties": {
    "tgn:hierarchy":[
        "tgn:2253561",
        "tgn:1000001",
        "tgn:7012149",
        "tgn:7029392"
    ],
    "tgn:id":2253561,
    "tgn:name":"Cook Hollow",
    "tgn:placetype":[
        "aat:300008761"
    ]
},
  "bbox": [],
  "geometry": {"coordinates":[-77.4833,42.0167],"type":"Point"}
}
=======
{"geometry":{"type":"Point","coordinates":[-77.483300,42.016700]},"type":"Feature","properties":{"hierarchy":["tgn:2253561","tgn:1000001","tgn:7012149","tgn:7029392"],"placetype":["aat:300008761"],"id":2253561,"name:xx":"Cook Hollow"}}
>>>>>>> 03f74aca74312dbeaf24d7e61306dd6a786dc3d0
