{
  "id": 2253561,
  "type": "Feature",
  "properties": {
    "tgn:hierarchy":[
        "tgn:2253561",
        "tgn:1000001",
        "tgn:7012149",
        "tgn:7029392"
    ],
    "tgn:id":2253561,
    "tgn:name":"Cook Hollow",
    "tgn:placetype":[
        "aat:300008761"
    ]
},
  "bbox": [],
  "geometry": {"coordinates":[-77.4833,42.0167],"type":"Point"}
}