{
  "id": 2140029,
  "type": "Feature",
  "properties": {
    "tgn:hierarchy":[
        "tgn:2140029",
        "tgn:1000001",
        "tgn:2000779",
        "tgn:7012149",
        "tgn:7007255",
        "tgn:7029392"
    ],
    "tgn:id":2140029,
    "tgn:name":"Atwood Hollow",
    "tgn:placetype":[
        "aat:300008761"
    ]
},
  "bbox": [],
  "geometry": {"coordinates":[-84.95,37.4833],"type":"Point"}
}