{
  "id": 2704272,
  "type": "Feature",
  "properties": {
    "tgn:hierarchy":[
        "tgn:2704272",
        "tgn:7006450",
        "tgn:1000001",
        "tgn:7012149",
        "tgn:2000082",
        "tgn:7029392"
    ],
    "tgn:id":2704272,
    "tgn:name":"Sunny Cove",
    "tgn:placetype":[
        "aat:300132316"
    ]
},
  "bbox": [],
  "geometry": {"coordinates":[-132.25,55.25],"type":"Point"}
}