{
  "id": 7134506,
  "type": "Feature",
  "properties": {
    "tgn:hierarchy":[
        "tgn:7134506",
        "tgn:7003692",
        "tgn:1000003",
        "tgn:7000084",
        "tgn:7029392"
    ],
    "tgn:id":7134506,
    "tgn:name":"M\u00fcller",
    "tgn:placetype":[
        "aat:300000206"
    ]
},
  "bbox": [],
  "geometry": {"coordinates":[10.066667,47.816667],"type":"Point"}
}