{
  "id": 7161715,
  "type": "Feature",
  "properties": {
    "tgn:hierarchy":[
        "tgn:7161715",
        "tgn:1000003",
        "tgn:7003676",
        "tgn:7000084",
        "tgn:7029392"
    ],
    "tgn:id":7161715,
    "tgn:name":"Hohe Berge",
    "tgn:placetype":[
        "aat:300008777"
    ]
},
  "bbox": [],
  "geometry": {"coordinates":[10.816667,53.066667],"type":"Point"}
}