{
  "id": 2145374,
  "type": "Feature",
  "properties": {
    "tgn:hierarchy":[
        "tgn:2145374",
        "tgn:1000001",
        "tgn:7006451",
        "tgn:2000091",
        "tgn:7012149",
        "tgn:7029392"
    ],
    "tgn:id":2145374,
    "tgn:name":"Bald Ridge Number Two Tank",
    "tgn:placetype":[
        "aat:300006191"
    ]
},
  "bbox": [],
  "geometry": {"coordinates":[-110.15,32.3667],"type":"Point"}
}