{
  "id": 7430725,
  "type": "Feature",
  "properties": {
    "tgn:hierarchy":[
        "tgn:7430725",
        "tgn:1001853",
        "tgn:1000001",
        "tgn:7005560",
        "tgn:7029392"
    ],
    "tgn:id":7430725,
    "tgn:name":"La Cauca",
    "tgn:placetype":[
        "aat:300008347"
    ]
},
  "bbox": [],
  "geometry": {"coordinates":[-103.766667,27.15],"type":"Point"}
}