{
  "id": 2563661,
  "type": "Feature",
  "properties": {
    "tgn:hierarchy":[
        "tgn:2563661",
        "tgn:1000001",
        "tgn:7012149",
        "tgn:2001718",
        "tgn:7007708",
        "tgn:7029392"
    ],
    "tgn:id":2563661,
    "tgn:name":"Owyhee River Cave",
    "tgn:placetype":[
        "aat:300008746"
    ]
},
  "bbox": [],
  "geometry": {"coordinates":[-117.85,42.9833],"type":"Point"}
}