{
  "id": 2432162,
  "type": "Feature",
  "properties": {
    "tgn:hierarchy":[
        "tgn:2432162",
        "tgn:1000001",
        "tgn:1002191",
        "tgn:7012149",
        "tgn:7007826",
        "tgn:7029392"
    ],
    "tgn:id":2432162,
    "tgn:name":"Kay Mountain",
    "tgn:placetype":[
        "aat:300008798"
    ]
},
  "bbox": [],
  "geometry": {"coordinates":[-97.6833,31.8333],"type":"Point"}
}