<<<<<<< HEAD
{
  "id": 2764357,
  "type": "Feature",
  "properties": {
    "tgn:hierarchy":[
        "tgn:2764357",
        "tgn:1000001",
        "tgn:7012149",
        "tgn:7007708",
        "tgn:7029392"
    ],
    "tgn:id":2764357,
    "tgn:name":"Whetstone Butte",
    "tgn:placetype":[
        "aat:300008798"
    ]
},
  "bbox": [],
  "geometry": {"coordinates":[-123.8,42.25],"type":"Point"}
}
=======
{"geometry":{"type":"Point","coordinates":[-123.800000,42.250000]},"type":"Feature","properties":{"hierarchy":["tgn:2764357","tgn:1000001","tgn:7012149","tgn:7007708","tgn:7029392"],"placetype":["aat:300008798"],"id":2764357,"name:xx":"Whetstone Butte"}}
>>>>>>> 03f74aca74312dbeaf24d7e61306dd6a786dc3d0
