{
  "id": 1066271,
  "type": "Feature",
  "properties": {
    "tgn:hierarchy":[
        "tgn:1066271",
        "tgn:7002185",
        "tgn:1000004",
        "tgn:1000108",
        "tgn:7029392"
    ],
    "tgn:id":1066271,
    "tgn:name":"Shingbwiyang",
    "tgn:placetype":[
        "aat:300008347"
    ]
},
  "bbox": [],
  "geometry": {"coordinates":[96.1667,26.6833],"type":"Point"}
}