{
  "id": 7004238,
  "type": "Feature",
  "properties": {
    "tgn:hierarchy":[
        "tgn:7004238",
        "tgn:1000004",
        "tgn:7001048",
        "tgn:1000145",
        "tgn:7029392"
    ],
    "tgn:id":7004238,
    "tgn:name":"Di\u1ec7n Bi\u00ean Ph\u1ee7",
    "tgn:placetype":[
        "aat:300008347",
        "aat:300000835",
        "aat:300387275",
        "aat:300008372"
    ]
},
  "bbox": [],
  "geometry": {"coordinates":[103.0333,21.3833],"type":"Point"}
}