{
  "id": 2476397,
  "type": "Feature",
  "properties": {
    "tgn:hierarchy":[
        "tgn:2476397",
        "tgn:1000001",
        "tgn:7012149",
        "tgn:2002164",
        "tgn:7007919",
        "tgn:7029392"
    ],
    "tgn:id":2476397,
    "tgn:name":"Lundy Knob",
    "tgn:placetype":[
        "aat:300008798"
    ]
},
  "bbox": [],
  "geometry": {"coordinates":[-81.05,36.6833],"type":"Point"}
}