{
  "id": 7547373,
  "type": "Feature",
  "properties": {
    "tgn:hierarchy":[
        "tgn:7547373",
        "tgn:1000004",
        "tgn:7000198",
        "tgn:7016722",
        "tgn:7029392"
    ],
    "tgn:id":7547373,
    "tgn:name:en":"Bhad\u0101n",
    "tgn:placetype":[
        "aat:300008347"
    ]
},
  "bbox": [],
  "geometry": {"coordinates":[78.758449,26.97833],"type":"Point"}
}