{
  "id": 1030955,
  "type": "Feature",
  "properties": {
    "tgn:hierarchy":[
        "tgn:1030955",
        "tgn:7002445",
        "tgn:1000003",
        "tgn:5000227",
        "tgn:7008591",
        "tgn:7029392"
    ],
    "tgn:id":1030955,
    "tgn:name:en":"Upton",
    "tgn:placetype":[
        "aat:300008347"
    ]
},
  "bbox": [],
  "geometry": {"coordinates":[-2.216667,52.066667],"type":"Point"}
}