{
  "id": 7563840,
  "type": "Feature",
  "properties": {
    "tgn:hierarchy":[
        "tgn:7563840",
        "tgn:1000004",
        "tgn:7000198",
        "tgn:1001894",
        "tgn:7029392"
    ],
    "tgn:id":7563840,
    "tgn:name:en":"Gora Protected Forest",
    "tgn:placetype":[
        "aat:300008865"
    ]
},
  "bbox": [],
  "geometry": {"coordinates":[79.31276,24.979872],"type":"Point"}
}