{
  "id": 7000229,
  "type": "Feature",
  "properties": {
    "tgn:hierarchy":[
        "tgn:7000229",
        "tgn:1000004",
        "tgn:1001869",
        "tgn:7000198",
        "tgn:7029392"
    ],
    "tgn:id":7000229,
    "tgn:name:en":"G\u0101ndh\u012bnagar",
    "tgn:placetype":[
        "aat:300008347",
        "aat:300387220",
        "aat:300387221",
        "aat:300008375"
    ]
},
  "bbox": [],
  "geometry": {"coordinates":[72.683333,23.216667],"type":"Point"}
}