{
  "id": 2021436,
  "type": "Feature",
  "properties": {
    "tgn:hierarchy":[
        "tgn:2021436",
        "tgn:1000001",
        "tgn:7012149",
        "tgn:1002749",
        "tgn:7007240",
        "tgn:7029392"
    ],
    "tgn:id":2021436,
    "tgn:name":"Taft",
    "tgn:placetype":[
        "aat:300008347"
    ]
},
  "bbox": [],
  "geometry": {"coordinates":[-81.35,28.4167],"type":"Point"}
}