{
  "id": 2763775,
  "type": "Feature",
  "properties": {
    "tgn:hierarchy":[
        "tgn:2763775",
        "tgn:1000001",
        "tgn:7012149",
        "tgn:2002053",
        "tgn:7007826",
        "tgn:7029392"
    ],
    "tgn:id":2763775,
    "tgn:name":"Whatley Creek",
    "tgn:placetype":[
        "aat:300008706"
    ]
},
  "bbox": [],
  "geometry": {"coordinates":[-98.0833,32.75],"type":"Point"}
}