{
  "id": 7340407,
  "type": "Feature",
  "properties": {
    "tgn:hierarchy":[
        "tgn:7340407",
        "tgn:7002815",
        "tgn:1000003",
        "tgn:7002793",
        "tgn:1000095",
        "tgn:7029392"
    ],
    "tgn:id":7340407,
    "tgn:name":"Cuevas, R\u00edo de",
    "tgn:placetype":[
        "aat:300008699"
    ]
},
  "bbox": [],
  "geometry": {"coordinates":[0.266667,40.216667],"type":"Point"}
}