<<<<<<< HEAD
{
  "id": 2769960,
  "type": "Feature",
  "properties": {
    "tgn:hierarchy":[
        "tgn:2769960",
        "tgn:1000001",
        "tgn:7012149",
        "tgn:2000724",
        "tgn:7007254",
        "tgn:7029392"
    ],
    "tgn:id":2769960,
    "tgn:name":"Wilburton Pond",
    "tgn:placetype":[
        "aat:300008680"
    ]
},
  "bbox": [],
  "geometry": {"coordinates":[-101.75,37.15],"type":"Point"}
}
=======
{"geometry":{"type":"Point","coordinates":[-101.750000,37.150000]},"type":"Feature","properties":{"hierarchy":["tgn:2769960","tgn:1000001","tgn:7012149","tgn:2000724","tgn:7007254","tgn:7029392"],"placetype":["aat:300008680"],"id":2769960,"name:xx":"Wilburton Pond"}}
>>>>>>> 03f74aca74312dbeaf24d7e61306dd6a786dc3d0
