{
  "id": 7154631,
  "type": "Feature",
  "properties": {
    "tgn:hierarchy":[
        "tgn:7154631",
        "tgn:1000003",
        "tgn:7003677",
        "tgn:7000084",
        "tgn:7029392"
    ],
    "tgn:id":7154631,
    "tgn:name":"Ketteler Horst",
    "tgn:placetype":[
        "aat:300008863"
    ]
},
  "bbox": [],
  "geometry": {"coordinates":[7.866667,51.883333],"type":"Point"}
}