<<<<<<< HEAD
{
  "id": 7021959,
  "type": "Feature",
  "properties": {
    "tgn:hierarchy":[
        "tgn:7021959",
        "tgn:1000001",
        "tgn:7006451",
        "tgn:7012149",
        "tgn:2000097",
        "tgn:7029392"
    ],
    "tgn:id":7021959,
    "tgn:name":"Mud Spring",
    "tgn:placetype":[
        "aat:300008697"
    ]
},
  "bbox": [],
  "geometry": {"coordinates":[-111.35,33.7],"type":"Point"}
}
=======
{"geometry":{"type":"Point","coordinates":[-111.350000,33.700000]},"type":"Feature","properties":{"hierarchy":["tgn:7021959","tgn:1000001","tgn:7006451","tgn:7012149","tgn:2000097","tgn:7029392"],"placetype":["aat:300008697"],"id":7021959,"name:xx":"Mud Spring"}}
>>>>>>> 03f74aca74312dbeaf24d7e61306dd6a786dc3d0
