{
  "id": 2595543,
  "type": "Feature",
  "properties": {
    "tgn:hierarchy":[
        "tgn:2595543",
        "tgn:1000001",
        "tgn:2002256",
        "tgn:7012149",
        "tgn:7013961",
        "tgn:7029392"
    ],
    "tgn:id":2595543,
    "tgn:name":"Potato Knob",
    "tgn:placetype":[
        "aat:300008798"
    ]
},
  "bbox": [],
  "geometry": {"coordinates":[-80.95,38.65],"type":"Point"}
}