<<<<<<< HEAD
{
  "id": 7475503,
  "type": "Feature",
  "properties": {
    "tgn:hierarchy":[
        "tgn:7475503",
        "tgn:1000004",
        "tgn:7489179",
        "tgn:1000141",
        "tgn:7029392"
    ],
    "tgn:id":7475503,
    "tgn:name":"Lujin",
    "tgn:placetype":[
        "aat:300008347"
    ]
},
  "bbox": [],
  "geometry": {"coordinates":[121.77893,24.537593],"type":"Point"}
}
=======
{"geometry":{"type":"Point","coordinates":[121.778930,24.537593]},"type":"Feature","properties":{"hierarchy":["tgn:7475503","tgn:1000004","tgn:7489179","tgn:1000141","tgn:7029392"],"placetype":["aat:300008347"],"id":7475503,"name:xx":"Lujin"}}
>>>>>>> 03f74aca74312dbeaf24d7e61306dd6a786dc3d0
