{
  "id": 7106182,
  "type": "Feature",
  "properties": {
    "tgn:hierarchy":[
        "tgn:7106182",
        "tgn:7003669",
        "tgn:1000003",
        "tgn:7000084",
        "tgn:7029392"
    ],
    "tgn:id":7106182,
    "tgn:name":"Scheuereck Berg",
    "tgn:placetype":[
        "aat:300008795"
    ]
},
  "bbox": [],
  "geometry": {"coordinates":[13.333333,49.066667],"type":"Point"}
}