{
  "id": 2288696,
  "type": "Feature",
  "properties": {
    "tgn:hierarchy":[
        "tgn:2288696",
        "tgn:1000001",
        "tgn:7012149",
        "tgn:2002379",
        "tgn:7007923",
        "tgn:7029392"
    ],
    "tgn:id":2288696,
    "tgn:name":"Ditch H-41",
    "tgn:placetype":[
        "aat:300006075"
    ]
},
  "bbox": [],
  "geometry": {"coordinates":[-109.0333,44.5667],"type":"Point"}
}