<<<<<<< HEAD
{
  "id": 7058443,
  "type": "Feature",
  "properties": {
    "tgn:hierarchy":[
        "tgn:7058443",
        "tgn:7003127",
        "tgn:1000003",
        "tgn:7008516",
        "tgn:1000080",
        "tgn:7029392"
    ],
    "tgn:id":7058443,
    "tgn:name":"Amola di Piano",
    "tgn:placetype":[
        "aat:300008347"
    ]
},
  "bbox": [],
  "geometry": {"coordinates":[11.166667,44.65],"type":"Point"}
}
=======
{"geometry":{"type":"Point","coordinates":[11.166667,44.650000]},"type":"Feature","properties":{"hierarchy":["tgn:7058443","tgn:7003127","tgn:1000003","tgn:7008516","tgn:1000080","tgn:7029392"],"placetype":["aat:300008347"],"id":7058443,"name:xx":"Amola di Piano"}}
>>>>>>> 03f74aca74312dbeaf24d7e61306dd6a786dc3d0
