<<<<<<< HEAD
{
  "id": 2332326,
  "type": "Feature",
  "properties": {
    "tgn:hierarchy":[
        "tgn:2332326",
        "tgn:1000001",
        "tgn:2000922",
        "tgn:7012149",
        "tgn:7007515",
        "tgn:7029392"
    ],
    "tgn:id":2332326,
    "tgn:name":"Floods Meadow",
    "tgn:placetype":[
        "aat:300008905"
    ]
},
  "bbox": [],
  "geometry": {"coordinates":[-68.5167,44.4833],"type":"Point"}
}
=======
{"geometry":{"type":"Point","coordinates":[-68.516700,44.483300]},"type":"Feature","properties":{"hierarchy":["tgn:2332326","tgn:1000001","tgn:2000922","tgn:7012149","tgn:7007515","tgn:7029392"],"placetype":["aat:300008905"],"id":2332326,"name:xx":"Floods Meadow"}}
>>>>>>> 03f74aca74312dbeaf24d7e61306dd6a786dc3d0
