{
  "id": 7061279,
  "type": "Feature",
  "properties": {
    "tgn:hierarchy":[
        "tgn:7061279",
        "tgn:7003692",
        "tgn:1000003",
        "tgn:7000084",
        "tgn:7029392"
    ],
    "tgn:id":7061279,
    "tgn:name":"Badersberg",
    "tgn:placetype":[
        "aat:300008749"
    ]
},
  "bbox": [],
  "geometry": {"coordinates":[10.033333,49.433333],"type":"Point"}
}