{
  "id": 2622634,
  "type": "Feature",
  "properties": {
    "tgn:hierarchy":[
        "tgn:2622634",
        "tgn:1000001",
        "tgn:7012149",
        "tgn:2000526",
        "tgn:7007251",
        "tgn:7029392"
    ],
    "tgn:id":2622634,
    "tgn:name":"Robinson Creek",
    "tgn:placetype":[
        "aat:300008706"
    ]
},
  "bbox": [],
  "geometry": {"coordinates":[-89.85,37.9667],"type":"Point"}
}