{
  "id": 7563513,
  "type": "Feature",
  "properties": {
    "tgn:hierarchy":[
        "tgn:7563513",
        "tgn:1000004",
        "tgn:7000198",
        "tgn:7016722",
        "tgn:7029392"
    ],
    "tgn:id":7563513,
    "tgn:name:en":"R\u016bri Kal\u0101n Protected Forest",
    "tgn:placetype":[
        "aat:300008865"
    ]
},
  "bbox": [],
  "geometry": {"coordinates":[79.456523,25.328388],"type":"Point"}
}