<<<<<<< HEAD
{
  "id": 7489346,
  "type": "Feature",
  "properties": {
    "tgn:hierarchy":[
        "tgn:7489346",
        "tgn:1000004",
        "tgn:7490934",
        "tgn:1000141",
        "tgn:7029392"
    ],
    "tgn:id":7489346,
    "tgn:name":"Huoshaodian",
    "tgn:placetype":[
        "aat:300008347"
    ]
},
  "bbox": [],
  "geometry": {"coordinates":[120.301944,23.285278],"type":"Point"}
}
=======
{"geometry":{"type":"Point","coordinates":[120.301944,23.285278]},"type":"Feature","properties":{"hierarchy":["tgn:7489346","tgn:1000004","tgn:7490934","tgn:1000141","tgn:7029392"],"placetype":["aat:300008347"],"id":7489346,"name:xx":"Huoshaodian"}}
>>>>>>> 03f74aca74312dbeaf24d7e61306dd6a786dc3d0
