{
  "id": 2464617,
  "type": "Feature",
  "properties": {
    "tgn:hierarchy":[
        "tgn:2464617",
        "tgn:1002538",
        "tgn:1000001",
        "tgn:7012149",
        "tgn:7007239",
        "tgn:7029392"
    ],
    "tgn:id":2464617,
    "tgn:name":"Log Pond",
    "tgn:placetype":[
        "aat:300008680"
    ]
},
  "bbox": [],
  "geometry": {"coordinates":[-75.4167,39.2667],"type":"Point"}
}