{
  "id": 2080303,
  "type": "Feature",
  "properties": {
    "tgn:hierarchy":[
        "tgn:2080303",
        "tgn:1000001",
        "tgn:7012149",
        "tgn:1002788",
        "tgn:7007706",
        "tgn:7029392"
    ],
    "tgn:id":2080303,
    "tgn:name":"Latham",
    "tgn:placetype":[
        "aat:300008347"
    ]
},
  "bbox": [],
  "geometry": {"coordinates":[-83.2333,39.0833],"type":"Point"}
}