{
  "id": 7591965,
  "type": "Feature",
  "properties": {
    "tgn:hierarchy":[
        "tgn:7591965",
        "tgn:1000004",
        "tgn:7000198",
        "tgn:7000799",
        "tgn:7029392"
    ],
    "tgn:id":7591965,
    "tgn:name:en":"Mard\u0101l",
    "tgn:placetype":[
        "aat:300008347"
    ]
},
  "bbox": [],
  "geometry": {"coordinates":[74.915059,32.983317],"type":"Point"}
}