{
  "id": 2397603,
  "type": "Feature",
  "properties": {
    "tgn:hierarchy":[
        "tgn:2397603",
        "tgn:1000001",
        "tgn:1002209",
        "tgn:7012149",
        "tgn:7007252",
        "tgn:7029392"
    ],
    "tgn:id":2397603,
    "tgn:name":"Honeycut Hollow",
    "tgn:placetype":[
        "aat:300008761"
    ]
},
  "bbox": [],
  "geometry": {"coordinates":[-86.3333,39.1167],"type":"Point"}
}