{
  "id": 7588722,
  "type": "Feature",
  "properties": {
    "tgn:hierarchy":[
        "tgn:7588722",
        "tgn:1000004",
        "tgn:7000198",
        "tgn:7000799",
        "tgn:7029392"
    ],
    "tgn:id":7588722,
    "tgn:name:en":"Nuts Labbar",
    "tgn:placetype":[
        "aat:300008347"
    ]
},
  "bbox": [],
  "geometry": {"coordinates":[74.560089,34.016184],"type":"Point"}
}