{
  "id": 2430639,
  "type": "Feature",
  "properties": {
    "tgn:hierarchy":[
        "tgn:2430639",
        "tgn:1000001",
        "tgn:7012149",
        "tgn:2001274",
        "tgn:7007524",
        "tgn:7029392"
    ],
    "tgn:id":2430639,
    "tgn:name":"Kalispell Bay",
    "tgn:placetype":[
        "aat:300132316"
    ]
},
  "bbox": [],
  "geometry": {"coordinates":[-114.1833,48.0667],"type":"Point"}
}