{
  "id": 7160930,
  "type": "Feature",
  "properties": {
    "tgn:hierarchy":[
        "tgn:7160930",
        "tgn:7003669",
        "tgn:1000003",
        "tgn:7000084",
        "tgn:7029392"
    ],
    "tgn:id":7160930,
    "tgn:name":"Hohe Steig",
    "tgn:placetype":[
        "aat:300008777"
    ]
},
  "bbox": [],
  "geometry": {"coordinates":[10.383333,49.433333],"type":"Point"}
}