{
  "id": 2599693,
  "type": "Feature",
  "properties": {
    "tgn:hierarchy":[
        "tgn:2599693",
        "tgn:1000001",
        "tgn:7006451",
        "tgn:2000092",
        "tgn:7012149",
        "tgn:7029392"
    ],
    "tgn:id":2599693,
    "tgn:name":"Prospect Valley",
    "tgn:placetype":[
        "aat:300008761"
    ]
},
  "bbox": [],
  "geometry": {"coordinates":[-113.1667,35.8667],"type":"Point"}
}