{
  "id": 2486700,
  "type": "Feature",
  "properties": {
    "tgn:hierarchy":[
        "tgn:2486700",
        "tgn:1000001",
        "tgn:7012149",
        "tgn:1002465",
        "tgn:7007252",
        "tgn:7029392"
    ],
    "tgn:id":2486700,
    "tgn:name":"Ledgewood Lake",
    "tgn:placetype":[
        "aat:300006191"
    ]
},
  "bbox": [],
  "geometry": {"coordinates":[-86.4333,39.7667],"type":"Point"}
}