{
  "id": 1127045,
  "type": "Feature",
  "properties": {
    "tgn:hierarchy":[
        "tgn:1127045",
        "tgn:7001242",
        "tgn:7016752",
        "tgn:1000763",
        "tgn:7029392"
    ],
    "tgn:id":1127045,
    "tgn:name":"Mekerra",
    "tgn:placetype":[
        "aat:300008707"
    ]
},
  "bbox": [],
  "geometry": {"coordinates":[-0.7333,34.9833],"type":"Point"}
}