<<<<<<< HEAD
{
  "id": 2402049,
  "type": "Feature",
  "properties": {
    "tgn:hierarchy":[
        "tgn:2402049",
        "tgn:1000001",
        "tgn:2001418",
        "tgn:7012149",
        "tgn:7007526",
        "tgn:7029392"
    ],
    "tgn:id":2402049,
    "tgn:name":"Horseshoe Reservoir",
    "tgn:placetype":[
        "aat:300006191"
    ]
},
  "bbox": [],
  "geometry": {"coordinates":[-116.3333,36.4],"type":"Point"}
}
=======
{"geometry":{"type":"Point","coordinates":[-116.333300,36.400000]},"type":"Feature","properties":{"hierarchy":["tgn:2402049","tgn:1000001","tgn:2001418","tgn:7012149","tgn:7007526","tgn:7029392"],"placetype":["aat:300006191"],"id":2402049,"name:xx":"Horseshoe Reservoir"}}
>>>>>>> 03f74aca74312dbeaf24d7e61306dd6a786dc3d0
