{
  "id": 7535425,
  "type": "Feature",
  "properties": {
    "tgn:hierarchy":[
        "tgn:7535425",
        "tgn:7001242",
        "tgn:7016833",
        "tgn:7001334",
        "tgn:7029392"
    ],
    "tgn:id":7535425,
    "tgn:name:en":"Huwayshah al Qibl\u012byah, 'Ayn al",
    "tgn:placetype":[
        "aat:300008697"
    ]
},
  "bbox": [],
  "geometry": {"coordinates":[30.568932,24.595776],"type":"Point"}
}