{
  "id": 2683985,
  "type": "Feature",
  "properties": {
    "tgn:hierarchy":[
        "tgn:2683985",
        "tgn:1000001",
        "tgn:1002328",
        "tgn:7012149",
        "tgn:7007568",
        "tgn:7029392"
    ],
    "tgn:id":2683985,
    "tgn:name":"Spencer Brook",
    "tgn:placetype":[
        "aat:300008699"
    ]
},
  "bbox": [],
  "geometry": {"coordinates":[-75.15,42.0667],"type":"Point"}
}