{
  "id": 7386252,
  "type": "Feature",
  "properties": {
    "tgn:hierarchy":[
        "tgn:7386252",
        "tgn:1000001",
        "tgn:7005597",
        "tgn:7005560",
        "tgn:7029392"
    ],
    "tgn:id":7386252,
    "tgn:name":"Rajada, Loma",
    "tgn:placetype":[
        "aat:300008777"
    ]
},
  "bbox": [],
  "geometry": {"coordinates":[-98.933333,23.633333],"type":"Point"}
}