<<<<<<< HEAD
{
  "id": 2250024,
  "type": "Feature",
  "properties": {
    "tgn:hierarchy":[
        "tgn:2250024",
        "tgn:1000001",
        "tgn:2000303",
        "tgn:7012149",
        "tgn:7007248",
        "tgn:7029392"
    ],
    "tgn:id":2250024,
    "tgn:name":"Collins Branch",
    "tgn:placetype":[
        "aat:300008699"
    ]
},
  "bbox": [],
  "geometry": {"coordinates":[-83.4333,32.3833],"type":"Point"}
}
=======
{"geometry":{"type":"Point","coordinates":[-83.433300,32.383300]},"type":"Feature","properties":{"hierarchy":["tgn:2250024","tgn:1000001","tgn:2000303","tgn:7012149","tgn:7007248","tgn:7029392"],"placetype":["aat:300008699"],"id":2250024,"name:xx":"Collins Branch"}}
>>>>>>> 03f74aca74312dbeaf24d7e61306dd6a786dc3d0
