{
  "id": 2759582,
  "type": "Feature",
  "properties": {
    "tgn:hierarchy":[
        "tgn:2759582",
        "tgn:7002659",
        "tgn:1000001",
        "tgn:7012149",
        "tgn:2000044",
        "tgn:7029392"
    ],
    "tgn:id":2759582,
    "tgn:name":"West Fork Flint River",
    "tgn:placetype":[
        "aat:300008707"
    ]
},
  "bbox": [],
  "geometry": {"coordinates":[-86.5667,34.95],"type":"Point"}
}