<<<<<<< HEAD
{
  "id": 2404428,
  "type": "Feature",
  "properties": {
    "tgn:hierarchy":[
        "tgn:2404428",
        "tgn:1000001",
        "tgn:7012149",
        "tgn:1002654",
        "tgn:7007706",
        "tgn:7029392"
    ],
    "tgn:id":2404428,
    "tgn:name":"Hubbard Creek",
    "tgn:placetype":[
        "aat:300008706"
    ]
},
  "bbox": [],
  "geometry": {"coordinates":[-81.85,41.0667],"type":"Point"}
}
=======
{"geometry":{"type":"Point","coordinates":[-81.850000,41.066700]},"type":"Feature","properties":{"hierarchy":["tgn:2404428","tgn:1000001","tgn:7012149","tgn:1002654","tgn:7007706","tgn:7029392"],"placetype":["aat:300008706"],"id":2404428,"name:xx":"Hubbard Creek"}}
>>>>>>> 03f74aca74312dbeaf24d7e61306dd6a786dc3d0
