{
  "id": 2698956,
  "type": "Feature",
  "properties": {
    "tgn:hierarchy":[
        "tgn:2698956",
        "tgn:1000001",
        "tgn:2001185",
        "tgn:7012149",
        "tgn:7007523",
        "tgn:7029392"
    ],
    "tgn:id":2698956,
    "tgn:name":"Strawberry Ridge",
    "tgn:placetype":[
        "aat:300266640"
    ]
},
  "bbox": [],
  "geometry": {"coordinates":[-93.0667,36.9167],"type":"Point"}
}