{
  "id": 7586427,
  "type": "Feature",
  "properties": {
    "tgn:hierarchy":[
        "tgn:7586427",
        "tgn:1000004",
        "tgn:7000198",
        "tgn:7000799",
        "tgn:7029392"
    ],
    "tgn:id":7586427,
    "tgn:name:en":"Soen\u0101r",
    "tgn:placetype":[
        "aat:300008347"
    ]
},
  "bbox": [],
  "geometry": {"coordinates":[74.818883,34.413653],"type":"Point"}
}