{
  "id": 2007746,
  "type": "Feature",
  "properties": {
    "tgn:hierarchy":[
        "tgn:2007746",
        "tgn:1000001",
        "tgn:7016172",
        "tgn:7012149",
        "tgn:2000159",
        "tgn:7029392"
    ],
    "tgn:id":2007746,
    "tgn:name":"Billstown",
    "tgn:placetype":[
        "aat:300008347",
        "aat:300387210"
    ]
},
  "bbox": [],
  "geometry": {"coordinates":[-93.5667,33.9667],"type":"Point"}
}