{
  "id": 7513670,
  "type": "Feature",
  "properties": {
    "tgn:hierarchy":[
        "tgn:7513670",
        "tgn:1009227",
        "tgn:1000226",
        "tgn:1000006",
        "tgn:7016850",
        "tgn:7029392"
    ],
    "tgn:id":7513670,
    "tgn:name:en":"Fraser Creek",
    "tgn:placetype":[
        "aat:300008699"
    ]
},
  "bbox": [],
  "geometry": {"coordinates":[171.333333,-42.483333],"type":"Point"}
}