{
  "id": 2267199,
  "type": "Feature",
  "properties": {
    "tgn:hierarchy":[
        "tgn:2267199",
        "tgn:1000001",
        "tgn:7012149",
        "tgn:7007825",
        "tgn:7029392"
    ],
    "tgn:id":2267199,
    "tgn:name":"Cricket Creek",
    "tgn:placetype":[
        "aat:300008706"
    ]
},
  "bbox": [],
  "geometry": {"coordinates":[-85.05,36.4833],"type":"Point"}
}