{
  "id": 7491078,
  "type": "Feature",
  "properties": {
    "tgn:hierarchy":[
        "tgn:7491078",
        "tgn:1000004",
        "tgn:7001014",
        "tgn:1000141",
        "tgn:7029392"
    ],
    "tgn:id":7491078,
    "tgn:name":"Sankuailiao",
    "tgn:placetype":[
        "aat:300008347"
    ]
},
  "bbox": [],
  "geometry": {"coordinates":[120.317423,23.708588],"type":"Point"}
}