{
  "id": 7327419,
  "type": "Feature",
  "properties": {
    "tgn:hierarchy":[
        "tgn:7327419",
        "tgn:7002844",
        "tgn:7030216",
        "tgn:1000003",
        "tgn:1000095",
        "tgn:7029392"
    ],
    "tgn:id":7327419,
    "tgn:name":"Pandals, Sierra de",
    "tgn:placetype":[
        "aat:300266640"
    ]
},
  "bbox": [],
  "geometry": {"coordinates":[0.466667,41.033333],"type":"Point"}
}