{
  "id": 2078287,
  "type": "Feature",
  "properties": {
    "tgn:hierarchy":[
        "tgn:2078287",
        "tgn:1000001",
        "tgn:7012149",
        "tgn:1002883",
        "tgn:7007706",
        "tgn:7029392"
    ],
    "tgn:id":2078287,
    "tgn:name":"Attica",
    "tgn:placetype":[
        "aat:300008347"
    ]
},
  "bbox": [],
  "geometry": {"coordinates":[-82.8833,41.05],"type":"Point"}
}