{
  "id": 7311863,
  "type": "Feature",
  "properties": {
    "tgn:hierarchy":[
        "tgn:7311863",
        "tgn:7016598",
        "tgn:1000049",
        "tgn:1000002",
        "tgn:7029392"
    ],
    "tgn:id":7311863,
    "tgn:name":"Las Lozas, Quebrada",
    "tgn:placetype":[
        "aat:300266554",
        "aat:300008699"
    ]
},
  "bbox": [],
  "geometry": {"coordinates":[-70.683333,-25.883333],"type":"Point"}
}