<<<<<<< HEAD
{
  "id": 2760869,
  "type": "Feature",
  "properties": {
    "tgn:hierarchy":[
        "tgn:2760869",
        "tgn:1000001",
        "tgn:7012149",
        "tgn:1002440",
        "tgn:7007568",
        "tgn:7029392"
    ],
    "tgn:id":2760869,
    "tgn:name":"West Hill",
    "tgn:placetype":[
        "aat:300008798"
    ]
},
  "bbox": [],
  "geometry": {"coordinates":[-74.3,43.3667],"type":"Point"}
}
=======
{"geometry":{"type":"Point","coordinates":[-74.300000,43.366700]},"type":"Feature","properties":{"hierarchy":["tgn:2760869","tgn:1000001","tgn:7012149","tgn:1002440","tgn:7007568","tgn:7029392"],"placetype":["aat:300008798"],"id":2760869,"name:xx":"West Hill"}}
>>>>>>> 03f74aca74312dbeaf24d7e61306dd6a786dc3d0
