{
  "id": 2224025,
  "type": "Feature",
  "properties": {
    "tgn:hierarchy":[
        "tgn:2224025",
        "tgn:1000001",
        "tgn:7012149",
        "tgn:2001298",
        "tgn:7007524",
        "tgn:7029392"
    ],
    "tgn:id":2224025,
    "tgn:name":"Caruthers Lake",
    "tgn:placetype":[
        "aat:300006191"
    ]
},
  "bbox": [],
  "geometry": {"coordinates":[-113.0833,46.3333],"type":"Point"}
}