{
  "id": 2001144,
  "type": "Feature",
  "properties": {
    "tgn:hierarchy":[
        "tgn:2001144",
        "tgn:1000001",
        "tgn:7012149",
        "tgn:7007522",
        "tgn:7029392"
    ],
    "tgn:id":2001144,
    "tgn:name":"Prentiss",
    "tgn:placetype":[
        "aat:300387145",
        "aat:300000771"
    ]
},
  "bbox": [],
  "geometry": {"coordinates":[-88.55,34.6167],"type":"Point"}
}