{
  "id": 7589971,
  "type": "Feature",
  "properties": {
    "tgn:hierarchy":[
        "tgn:7589971",
        "tgn:1000004",
        "tgn:7000198",
        "tgn:7000799",
        "tgn:7029392"
    ],
    "tgn:id":7589971,
    "tgn:name:en":"Chhungar",
    "tgn:placetype":[
        "aat:300008347"
    ]
},
  "bbox": [],
  "geometry": {"coordinates":[74.308333,33.963889],"type":"Point"}
}