{
  "id": 7372566,
  "type": "Feature",
  "properties": {
    "tgn:hierarchy":[
        "tgn:7372566",
        "tgn:1001853",
        "tgn:1000001",
        "tgn:7005560",
        "tgn:7029392"
    ],
    "tgn:id":7372566,
    "tgn:name":"La Norita",
    "tgn:placetype":[
        "aat:300008347"
    ]
},
  "bbox": [],
  "geometry": {"coordinates":[-101.216667,26.016667],"type":"Point"}
}