{
  "id": 1074167,
  "type": "Feature",
  "properties": {
    "tgn:hierarchy":[
        "tgn:1074167",
        "tgn:7002075",
        "tgn:1000004",
        "tgn:1000111",
        "tgn:7029392"
    ],
    "tgn:id":1074167,
    "tgn:name":"Zhusigang",
    "tgn:placetype":[
        "aat:300008347"
    ]
},
  "bbox": [],
  "geometry": {"coordinates":[118.3667,31.1833],"type":"Point"}
}