{
  "id": 2691493,
  "type": "Feature",
  "properties": {
    "tgn:hierarchy":[
        "tgn:2691493",
        "tgn:1000001",
        "tgn:7012149",
        "tgn:1003008",
        "tgn:7007710",
        "tgn:7029392"
    ],
    "tgn:id":2691493,
    "tgn:name":"Star Pond",
    "tgn:placetype":[
        "aat:300008680"
    ]
},
  "bbox": [],
  "geometry": {"coordinates":[-75.3833,41.9667],"type":"Point"}
}