{
  "id": 7127627,
  "type": "Feature",
  "properties": {
    "tgn:hierarchy":[
        "tgn:7127627",
        "tgn:7003692",
        "tgn:1000003",
        "tgn:7000084",
        "tgn:7029392"
    ],
    "tgn:id":7127627,
    "tgn:name":"Oberndorf",
    "tgn:placetype":[
        "aat:300008347"
    ]
},
  "bbox": [],
  "geometry": {"coordinates":[8.933333,48.533333],"type":"Point"}
}