{
  "id": 1097838,
  "type": "Feature",
  "properties": {
    "tgn:hierarchy":[
        "tgn:1097838",
        "tgn:7000490",
        "tgn:1000006",
        "tgn:7001831",
        "tgn:7029392"
    ],
    "tgn:id":1097838,
    "tgn:name":"Nunjikompita",
    "tgn:placetype":[
        "aat:300008347"
    ]
},
  "bbox": [],
  "geometry": {"coordinates":[134.3167,-32.2667],"type":"Point"}
}