{
  "id": 2739862,
  "type": "Feature",
  "properties": {
    "tgn:hierarchy":[
        "tgn:2739862",
        "tgn:1000001",
        "tgn:7012149",
        "tgn:1002944",
        "tgn:7007568",
        "tgn:7029392"
    ],
    "tgn:id":2739862,
    "tgn:name":"Upper Fairfield",
    "tgn:placetype":[
        "aat:300008347"
    ]
},
  "bbox": [],
  "geometry": {"coordinates":[-76.2833,42.2667],"type":"Point"}
}