{
  "id": 7054598,
  "type": "Feature",
  "properties": {
    "tgn:hierarchy":[
        "tgn:7054598",
        "tgn:7009084",
        "tgn:7004154",
        "tgn:1000003",
        "tgn:1000080",
        "tgn:7029392"
    ],
    "tgn:id":7054598,
    "tgn:name":"Lonaro Fano",
    "tgn:placetype":[
        "aat:300008347"
    ]
},
  "bbox": [],
  "geometry": {"coordinates":[13.183333,42.516667],"type":"Point"}
}