{
  "id": 7429816,
  "type": "Feature",
  "properties": {
    "tgn:hierarchy":[
        "tgn:7429816",
        "tgn:1001853",
        "tgn:1000001",
        "tgn:7005560",
        "tgn:7029392"
    ],
    "tgn:id":7429816,
    "tgn:name":"Santa Mar\u00eda",
    "tgn:placetype":[
        "aat:300008347"
    ]
},
  "bbox": [],
  "geometry": {"coordinates":[-103.233333,25.866667],"type":"Point"}
}