{
  "id": 7167056,
  "type": "Feature",
  "properties": {
    "tgn:hierarchy":[
        "tgn:7167056",
        "tgn:1000003",
        "tgn:7003677",
        "tgn:7000084",
        "tgn:7029392"
    ],
    "tgn:id":7167056,
    "tgn:name":"Heid-Berg",
    "tgn:placetype":[
        "aat:300008777"
    ]
},
  "bbox": [],
  "geometry": {"coordinates":[6.55,50.45],"type":"Point"}
}