{
  "id": 7388424,
  "type": "Feature",
  "properties": {
    "tgn:hierarchy":[
        "tgn:7388424",
        "tgn:7005581",
        "tgn:1000001",
        "tgn:7005560",
        "tgn:7029392"
    ],
    "tgn:id":7388424,
    "tgn:name":"Rancho Potrero de Tortugas",
    "tgn:placetype":[
        "aat:300000241"
    ]
},
  "bbox": [],
  "geometry": {"coordinates":[-104.266667,28.866667],"type":"Point"}
}