{
  "id": 2550519,
  "type": "Feature",
  "properties": {
    "tgn:hierarchy":[
        "tgn:2550519",
        "tgn:1000001",
        "tgn:7014352",
        "tgn:7012149",
        "tgn:7007564",
        "tgn:7029392"
    ],
    "tgn:id":2550519,
    "tgn:name":"Northwood Narrows",
    "tgn:placetype":[
        "aat:300008347"
    ]
},
  "bbox": [],
  "geometry": {"coordinates":[-71.2333,43.2167],"type":"Point"}
}