<<<<<<< HEAD
{
  "id": 7240502,
  "type": "Feature",
  "properties": {
    "tgn:hierarchy":[
        "tgn:7240502",
        "tgn:7003460",
        "tgn:1000003",
        "tgn:1000063",
        "tgn:4012014",
        "tgn:7029392"
    ],
    "tgn:id":7240502,
    "tgn:name":"Espeler",
    "tgn:placetype":[
        "aat:300008347"
    ]
},
  "bbox": [],
  "geometry": {"coordinates":[6.053056,50.2025],"type":"Point"}
}
=======
{"geometry":{"type":"Point","coordinates":[6.053056,50.202500]},"type":"Feature","properties":{"hierarchy":["tgn:7240502","tgn:7003460","tgn:1000003","tgn:1000063","tgn:4012014","tgn:7029392"],"placetype":["aat:300008347"],"id":7240502,"name:xx":"Espeler"}}
>>>>>>> 03f74aca74312dbeaf24d7e61306dd6a786dc3d0
