{
  "id": 2773616,
  "type": "Feature",
  "properties": {
    "tgn:hierarchy":[
        "tgn:2773616",
        "tgn:1000001",
        "tgn:7012149",
        "tgn:7007520",
        "tgn:7029392"
    ],
    "tgn:id":2773616,
    "tgn:name":"Willoughby Branch",
    "tgn:placetype":[
        "aat:300008699"
    ]
},
  "bbox": [],
  "geometry": {"coordinates":[-82.9667,43.15],"type":"Point"}
}