{
  "id": 2423518,
  "type": "Feature",
  "properties": {
    "tgn:hierarchy":[
        "tgn:2423518",
        "tgn:7006450",
        "tgn:1000001",
        "tgn:7030547",
        "tgn:7012149",
        "tgn:7029392"
    ],
    "tgn:id":2423518,
    "tgn:name":"John Hansen Creek",
    "tgn:placetype":[
        "aat:300008706"
    ]
},
  "bbox": [],
  "geometry": {"coordinates":[-151.4167,64.1833],"type":"Point"}
}