{
  "id": 2275555,
  "type": "Feature",
  "properties": {
    "tgn:hierarchy":[
        "tgn:2275555",
        "tgn:1000001",
        "tgn:7012149",
        "tgn:2000903",
        "tgn:7007256",
        "tgn:7029392"
    ],
    "tgn:id":2275555,
    "tgn:name":"Darby",
    "tgn:placetype":[
        "aat:300008347"
    ]
},
  "bbox": [],
  "geometry": {"coordinates":[-91.9167,30.3833],"type":"Point"}
}