{
  "id": 7451611,
  "type": "Feature",
  "properties": {
    "tgn:hierarchy":[
        "tgn:7451611",
        "tgn:7019094",
        "tgn:7002444",
        "tgn:1000003",
        "tgn:7008591",
        "tgn:7029392"
    ],
    "tgn:id":7451611,
    "tgn:name:en":"Easdale Island",
    "tgn:placetype":[
        "aat:300008791"
    ]
},
  "bbox": [],
  "geometry": {"coordinates":[-5.65,56.283333],"type":"Point"}
}