{
  "id": 2716124,
  "type": "Feature",
  "properties": {
    "tgn:hierarchy":[
        "tgn:2716124",
        "tgn:1000001",
        "tgn:1002614",
        "tgn:7012149",
        "tgn:7007526",
        "tgn:7029392"
    ],
    "tgn:id":2716124,
    "tgn:name":"Thanksgiving Mine",
    "tgn:placetype":[
        "aat:300000390"
    ]
},
  "bbox": [],
  "geometry": {"coordinates":[-119.25,38.95],"type":"Point"}
}