{
  "id": 7198840,
  "type": "Feature",
  "properties": {
    "tgn:hierarchy":[
        "tgn:7198840",
        "tgn:7003669",
        "tgn:1000003",
        "tgn:7000084",
        "tgn:7029392"
    ],
    "tgn:id":7198840,
    "tgn:name":"Eggenried",
    "tgn:placetype":[
        "aat:300387173"
    ]
},
  "bbox": [],
  "geometry": {"coordinates":[13.133333,48.95],"type":"Point"}
}