{
  "id": 2231564,
  "type": "Feature",
  "properties": {
    "tgn:hierarchy":[
        "tgn:2231564",
        "tgn:1000001",
        "tgn:7012149",
        "tgn:2000181",
        "tgn:7007157",
        "tgn:7029392"
    ],
    "tgn:id":2231564,
    "tgn:name":"Chalk Mountains",
    "tgn:placetype":[
        "aat:300386831"
    ]
},
  "bbox": [],
  "geometry": {"coordinates":[-123.8667,40.4333],"type":"Point"}
}