{
  "id": 2696045,
  "type": "Feature",
  "properties": {
    "tgn:hierarchy":[
        "tgn:2696045",
        "tgn:1000001",
        "tgn:7006451",
        "tgn:7012149",
        "tgn:2000103",
        "tgn:7029392"
    ],
    "tgn:id":2696045,
    "tgn:name":"Stoddard Mine",
    "tgn:placetype":[
        "aat:300000390"
    ]
},
  "bbox": [],
  "geometry": {"coordinates":[-112.1833,34.4167],"type":"Point"}
}