{
  "id": 2470080,
  "type": "Feature",
  "properties": {
    "tgn:hierarchy":[
        "tgn:2470080",
        "tgn:1000001",
        "tgn:7012149",
        "tgn:7007524",
        "tgn:7029392"
    ],
    "tgn:id":2470080,
    "tgn:name":"Loony Hollow",
    "tgn:placetype":[
        "aat:300008761"
    ]
},
  "bbox": [],
  "geometry": {"coordinates":[-104.9333,46.55],"type":"Point"}
}