{
  "id": 2296494,
  "type": "Feature",
  "properties": {
    "tgn:hierarchy":[
        "tgn:2296494",
        "tgn:2002101",
        "tgn:1000001",
        "tgn:7012149",
        "tgn:7007827",
        "tgn:7029392"
    ],
    "tgn:id":2296494,
    "tgn:name":"Dry Canyon",
    "tgn:placetype":[
        "aat:300008761"
    ]
},
  "bbox": [],
  "geometry": {"coordinates":[-113.5333,38.2667],"type":"Point"}
}