<<<<<<< HEAD
{
  "id": 7487822,
  "type": "Feature",
  "properties": {
    "tgn:hierarchy":[
        "tgn:7487822",
        "tgn:1000004",
        "tgn:7491221",
        "tgn:1000141",
        "tgn:7029392"
    ],
    "tgn:id":7487822,
    "tgn:name":"Hongshi",
    "tgn:placetype":[
        "aat:300008347"
    ]
},
  "bbox": [],
  "geometry": {"coordinates":[121.160556,23.065833],"type":"Point"}
}
=======
{"geometry":{"type":"Point","coordinates":[121.160556,23.065833]},"type":"Feature","properties":{"hierarchy":["tgn:7487822","tgn:1000004","tgn:7491221","tgn:1000141","tgn:7029392"],"placetype":["aat:300008347"],"id":7487822,"name:xx":"Hongshi"}}
>>>>>>> 03f74aca74312dbeaf24d7e61306dd6a786dc3d0
