{
  "id": 7487822,
  "type": "Feature",
  "properties": {
    "tgn:hierarchy":[
        "tgn:7487822",
        "tgn:1000004",
        "tgn:7491221",
        "tgn:1000141",
        "tgn:7029392"
    ],
    "tgn:id":7487822,
    "tgn:name":"Hongshi",
    "tgn:placetype":[
        "aat:300008347"
    ]
},
  "bbox": [],
  "geometry": {"coordinates":[121.160556,23.065833],"type":"Point"}
}