{
  "id": 7138236,
  "type": "Feature",
  "properties": {
    "tgn:hierarchy":[
        "tgn:7138236",
        "tgn:1000003",
        "tgn:7003676",
        "tgn:7000084",
        "tgn:7029392"
    ],
    "tgn:id":7138236,
    "tgn:name":"Lemwerder",
    "tgn:placetype":[
        "aat:300008347"
    ]
},
  "bbox": [],
  "geometry": {"coordinates":[8.616667,53.166667],"type":"Point"}
}