{
  "id": 1024952,
  "type": "Feature",
  "properties": {
    "tgn:hierarchy":[
        "tgn:1024952",
        "tgn:7002646",
        "tgn:1000002",
        "tgn:1000058",
        "tgn:7029392"
    ],
    "tgn:id":1024952,
    "tgn:name":"Pl\u00e1cido Rosas",
    "tgn:placetype":[
        "aat:300008347"
    ]
},
  "bbox": [],
  "geometry": {"coordinates":[-53.7333,-32.75],"type":"Point"}
}