{
  "id": 2364505,
  "type": "Feature",
  "properties": {
    "tgn:hierarchy":[
        "tgn:2364505",
        "tgn:1000001",
        "tgn:7012149",
        "tgn:2001500",
        "tgn:7007709",
        "tgn:7029392"
    ],
    "tgn:id":2364505,
    "tgn:name":"Green Valley",
    "tgn:placetype":[
        "aat:300008347"
    ]
},
  "bbox": [],
  "geometry": {"coordinates":[-79.8333,36.0833],"type":"Point"}
}