<<<<<<< HEAD
{
  "id": 2254726,
  "type": "Feature",
  "properties": {
    "tgn:hierarchy":[
        "tgn:2254726",
        "tgn:1000001",
        "tgn:2000920",
        "tgn:7012149",
        "tgn:7007515",
        "tgn:7029392"
    ],
    "tgn:id":2254726,
    "tgn:name":"Coon Road Swamp",
    "tgn:placetype":[
        "aat:300008905"
    ]
},
  "bbox": [],
  "geometry": {"coordinates":[-70.5333,44.0667],"type":"Point"}
}
=======
{"geometry":{"type":"Point","coordinates":[-70.533300,44.066700]},"type":"Feature","properties":{"hierarchy":["tgn:2254726","tgn:1000001","tgn:2000920","tgn:7012149","tgn:7007515","tgn:7029392"],"placetype":["aat:300008905"],"id":2254726,"name:xx":"Coon Road Swamp"}}
>>>>>>> 03f74aca74312dbeaf24d7e61306dd6a786dc3d0
