{
  "id": 7260483,
  "type": "Feature",
  "properties": {
    "tgn:concordances":{
        "gn:id":"2756709"
    },
    "tgn:hierarchy":[
        "tgn:7260483",
        "tgn:1000003",
        "tgn:7003622",
        "tgn:7016845",
        "tgn:7029392"
    ],
    "tgn:id":7260483,
    "tgn:name:nl":"Donk",
    "tgn:placetype":[
        "aat:300008347"
    ]
},
  "bbox": [],
  "geometry": {"coordinates":[6.066667,51.316667],"type":"Point"}
}