{
  "id": 7585816,
  "type": "Feature",
  "properties": {
    "tgn:hierarchy":[
        "tgn:7585816",
        "tgn:1000004",
        "tgn:7000198",
        "tgn:7000799",
        "tgn:7029392"
    ],
    "tgn:id":7585816,
    "tgn:name:en":"Galganjan Forest",
    "tgn:placetype":[
        "aat:300008863"
    ]
},
  "bbox": [],
  "geometry": {"coordinates":[74.208333,34.413889],"type":"Point"}
}