{
  "id": 7397192,
  "type": "Feature",
  "properties": {
    "tgn:hierarchy":[
        "tgn:7397192",
        "tgn:1000001",
        "tgn:7005594",
        "tgn:7005560",
        "tgn:7029392"
    ],
    "tgn:id":7397192,
    "tgn:name":"San Rom\u00e1n",
    "tgn:placetype":[
        "aat:300008347"
    ]
},
  "bbox": [],
  "geometry": {"coordinates":[-98.983333,21.95],"type":"Point"}
}