{
  "id": 7367489,
  "type": "Feature",
  "properties": {
    "tgn:hierarchy":[
        "tgn:7367489",
        "tgn:7005581",
        "tgn:1000001",
        "tgn:7005560",
        "tgn:7029392"
    ],
    "tgn:id":7367489,
    "tgn:name":"El Rucio",
    "tgn:placetype":[
        "aat:300008347"
    ]
},
  "bbox": [],
  "geometry": {"coordinates":[-108.05,30.066667],"type":"Point"}
}