{
  "id": 2723129,
  "type": "Feature",
  "properties": {
    "tgn:hierarchy":[
        "tgn:2723129",
        "tgn:1000001",
        "tgn:7012149",
        "tgn:7007520",
        "tgn:7029392"
    ],
    "tgn:id":2723129,
    "tgn:name":"Tittabawassee River State Forest",
    "tgn:placetype":[
        "aat:300008863"
    ]
},
  "bbox": [],
  "geometry": {"coordinates":[-84.4333,43.7667],"type":"Point"}
}