{
  "id": 7230541,
  "type": "Feature",
  "properties": {
    "tgn:hierarchy":[
        "tgn:7230541",
        "tgn:7011330",
        "tgn:7002674",
        "tgn:1000003",
        "tgn:1000074",
        "tgn:7029392"
    ],
    "tgn:id":7230541,
    "tgn:name":"Kh\u00edlos, \u00c1kra",
    "tgn:placetype":[
        "aat:300386846"
    ]
},
  "bbox": [],
  "geometry": {"coordinates":[26.366667,36.516667],"type":"Point"}
}