{
  "id": 2056780,
  "type": "Feature",
  "properties": {
    "tgn:hierarchy":[
        "tgn:2056780",
        "tgn:1000001",
        "tgn:2001091",
        "tgn:7012149",
        "tgn:7007522",
        "tgn:7029392"
    ],
    "tgn:id":2056780,
    "tgn:name":"Lamont",
    "tgn:placetype":[
        "aat:300008347"
    ]
},
  "bbox": [],
  "geometry": {"coordinates":[-91.0667,33.5333],"type":"Point"}
}