{
  "id": 7262344,
  "type": "Feature",
  "properties": {
    "tgn:hierarchy":[
        "tgn:7262344",
        "tgn:1000003",
        "tgn:7003635",
        "tgn:7016845",
        "tgn:7029392"
    ],
    "tgn:id":7262344,
    "tgn:name:nl":"Elisabethpolder",
    "tgn:placetype":[
        "aat:300006163"
    ]
},
  "bbox": [],
  "geometry": {"coordinates":[3.716667,51.333333],"type":"Point"}
}