{
  "id": 7482079,
  "type": "Feature",
  "properties": {
    "tgn:hierarchy":[
        "tgn:7482079",
        "tgn:1000004",
        "tgn:7492971",
        "tgn:1000141",
        "tgn:7029392"
    ],
    "tgn:id":7482079,
    "tgn:name":"Guangfu Qiao",
    "tgn:placetype":[
        "aat:300007836"
    ]
},
  "bbox": [],
  "geometry": {"coordinates":[120.564702,22.643156],"type":"Point"}
}