{
  "id": 1097419,
  "type": "Feature",
  "properties": {
    "tgn:hierarchy":[
        "tgn:1097419",
        "tgn:7000490",
        "tgn:1000006",
        "tgn:7001831",
        "tgn:7029392"
    ],
    "tgn:id":1097419,
    "tgn:name":"Lucindale",
    "tgn:placetype":[
        "aat:300008347"
    ]
},
  "bbox": [],
  "geometry": {"coordinates":[140.4167,-36.9833],"type":"Point"}
}