{
  "id": 1018397,
  "type": "Feature",
  "properties": {
    "tgn:hierarchy":[
        "tgn:1018397",
        "tgn:1000001",
        "tgn:7005601",
        "tgn:7005560",
        "tgn:7029392"
    ],
    "tgn:id":1018397,
    "tgn:name":"Te\u00fal de Gonz\u00e1lez Ortega",
    "tgn:placetype":[
        "aat:300008347"
    ]
},
  "bbox": [],
  "geometry": {"coordinates":[-103.483333,21.466667],"type":"Point"}
}