{
  "id": 2602500,
  "type": "Feature",
  "properties": {
    "tgn:hierarchy":[
        "tgn:2602500",
        "tgn:1000001",
        "tgn:1002271",
        "tgn:7012149",
        "tgn:7007920",
        "tgn:7029392"
    ],
    "tgn:id":2602500,
    "tgn:name":"Pysht River",
    "tgn:placetype":[
        "aat:300008707"
    ]
},
  "bbox": [],
  "geometry": {"coordinates":[-124.2667,48.15],"type":"Point"}
}