{
  "id": 2307773,
  "type": "Feature",
  "properties": {
    "tgn:hierarchy":[
        "tgn:2307773",
        "tgn:1000001",
        "tgn:7012149",
        "tgn:7007827",
        "tgn:7029392"
    ],
    "tgn:id":2307773,
    "tgn:name":"East Fork Whiterocks River",
    "tgn:placetype":[
        "aat:300008707"
    ]
},
  "bbox": [],
  "geometry": {"coordinates":[-109.9167,40.7833],"type":"Point"}
}