{
  "id": 2111049,
  "type": "Feature",
  "properties": {
    "tgn:hierarchy":[
        "tgn:2111049",
        "tgn:1000001",
        "tgn:7012149",
        "tgn:7014160",
        "tgn:7007919",
        "tgn:7029392"
    ],
    "tgn:id":2111049,
    "tgn:name":"Chapel Acres",
    "tgn:placetype":[
        "aat:300008347"
    ]
},
  "bbox": [],
  "geometry": {"coordinates":[-77.2333,38.7333],"type":"Point"}
}