{
  "id": 7232601,
  "type": "Feature",
  "properties": {
    "tgn:hierarchy":[
        "tgn:7232601",
        "tgn:7002748",
        "tgn:7001399",
        "tgn:1000003",
        "tgn:1000074",
        "tgn:7029392"
    ],
    "tgn:id":7232601,
    "tgn:name":"Magoul\u00edtsa",
    "tgn:placetype":[
        "aat:300008347"
    ]
},
  "bbox": [],
  "geometry": {"coordinates":[21.760833,39.438889],"type":"Point"}
}