{
  "id": 7473619,
  "type": "Feature",
  "properties": {
    "tgn:hierarchy":[
        "tgn:7473619",
        "tgn:7468018",
        "tgn:1000004",
        "tgn:1000141",
        "tgn:7029392"
    ],
    "tgn:id":7473619,
    "tgn:name":"Dongshi",
    "tgn:placetype":[
        "aat:300008347"
    ]
},
  "bbox": [],
  "geometry": {"coordinates":[120.150031,23.456893],"type":"Point"}
}