<<<<<<< HEAD
{
  "id": 2403935,
  "type": "Feature",
  "properties": {
    "tgn:hierarchy":[
        "tgn:2403935",
        "tgn:1000001",
        "tgn:7012149",
        "tgn:2000623",
        "tgn:7007253",
        "tgn:7029392"
    ],
    "tgn:id":2403935,
    "tgn:name":"Howell",
    "tgn:placetype":[
        "aat:300008347"
    ]
},
  "bbox": [],
  "geometry": {"coordinates":[-92.9667,41.3667],"type":"Point"}
}
=======
{"geometry":{"type":"Point","coordinates":[-92.966700,41.366700]},"type":"Feature","properties":{"hierarchy":["tgn:2403935","tgn:1000001","tgn:7012149","tgn:2000623","tgn:7007253","tgn:7029392"],"placetype":["aat:300008347"],"id":2403935,"name:xx":"Howell"}}
>>>>>>> 03f74aca74312dbeaf24d7e61306dd6a786dc3d0
