{
  "id": 2098526,
  "type": "Feature",
  "properties": {
    "tgn:hierarchy":[
        "tgn:2098526",
        "tgn:1000001",
        "tgn:7012149",
        "tgn:2001851",
        "tgn:7007825",
        "tgn:7029392"
    ],
    "tgn:id":2098526,
    "tgn:name":"Clevenger",
    "tgn:placetype":[
        "aat:300008347",
        "aat:300387210"
    ]
},
  "bbox": [],
  "geometry": {"coordinates":[-83.25,35.9667],"type":"Point"}
}