{
  "id": 2237908,
  "type": "Feature",
  "properties": {
    "tgn:hierarchy":[
        "tgn:2237908",
        "tgn:1000001",
        "tgn:2001417",
        "tgn:7012149",
        "tgn:7007526",
        "tgn:7029392"
    ],
    "tgn:id":2237908,
    "tgn:name":"Chipmunk Spring",
    "tgn:placetype":[
        "aat:300008697"
    ]
},
  "bbox": [],
  "geometry": {"coordinates":[-118.8667,38.6167],"type":"Point"}
}