{
  "id": 7372221,
  "type": "Feature",
  "properties": {
    "tgn:hierarchy":[
        "tgn:7372221",
        "tgn:7005583",
        "tgn:1000001",
        "tgn:7005560",
        "tgn:7029392"
    ],
    "tgn:id":7372221,
    "tgn:name":"La Joya",
    "tgn:placetype":[
        "aat:300008347"
    ]
},
  "bbox": [],
  "geometry": {"coordinates":[-104.266667,23.866667],"type":"Point"}
}