{
  "id": 2266238,
  "type": "Feature",
  "properties": {
    "tgn:hierarchy":[
        "tgn:2266238",
        "tgn:1000001",
        "tgn:7012149",
        "tgn:1002835",
        "tgn:7007706",
        "tgn:7029392"
    ],
    "tgn:id":2266238,
    "tgn:name":"Crawley Lake",
    "tgn:placetype":[
        "aat:300006191"
    ]
},
  "bbox": [],
  "geometry": {"coordinates":[-83.2833,39.2833],"type":"Point"}
}