{
  "id": 2272493,
  "type": "Feature",
  "properties": {
    "tgn:hierarchy":[
        "tgn:2272493",
        "tgn:1000001",
        "tgn:7012149",
        "tgn:1002785",
        "tgn:7007920",
        "tgn:7029392"
    ],
    "tgn:id":2272493,
    "tgn:name":"Curtis Ridge",
    "tgn:placetype":[
        "aat:300266640"
    ]
},
  "bbox": [],
  "geometry": {"coordinates":[-121.75,46.8667],"type":"Point"}
}