{
  "id": 7269608,
  "type": "Feature",
  "properties": {
    "tgn:hierarchy":[
        "tgn:7269608",
        "tgn:7003619",
        "tgn:1000003",
        "tgn:7016845",
        "tgn:7029392"
    ],
    "tgn:id":7269608,
    "tgn:name:nl":"Meervelderbosch",
    "tgn:placetype":[
        "aat:300008863"
    ]
},
  "bbox": [],
  "geometry": {"coordinates":[5.816667,52.233333],"type":"Point"}
}