{
  "id": 2222567,
  "type": "Feature",
  "properties": {
    "tgn:hierarchy":[
        "tgn:2222567",
        "tgn:1000001",
        "tgn:7012149",
        "tgn:2002301",
        "tgn:7013961",
        "tgn:7029392"
    ],
    "tgn:id":2222567,
    "tgn:name":"Carpenter Ridge",
    "tgn:placetype":[
        "aat:300266640"
    ]
},
  "bbox": [],
  "geometry": {"coordinates":[-80.7167,39.6333],"type":"Point"}
}