{
  "id": 2757966,
  "type": "Feature",
  "properties": {
    "tgn:hierarchy":[
        "tgn:2757966",
        "tgn:1000001",
        "tgn:7012149",
        "tgn:2001716",
        "tgn:7007708",
        "tgn:7029392"
    ],
    "tgn:id":2757966,
    "tgn:name":"West Branch North Fork Siuslaw River",
    "tgn:placetype":[
        "aat:300008707"
    ]
},
  "bbox": [],
  "geometry": {"coordinates":[-123.9667,44.15],"type":"Point"}
}