<<<<<<< HEAD
{
  "id": 7243410,
  "type": "Feature",
  "properties": {
    "tgn:hierarchy":[
        "tgn:7243410",
        "tgn:7003460",
        "tgn:1000003",
        "tgn:1000063",
        "tgn:4012014",
        "tgn:7029392"
    ],
    "tgn:id":7243410,
    "tgn:name":"Lassence",
    "tgn:placetype":[
        "aat:300008347"
    ]
},
  "bbox": [],
  "geometry": {"coordinates":[5.883333,50.55],"type":"Point"}
}
=======
{"geometry":{"type":"Point","coordinates":[5.883333,50.550000]},"type":"Feature","properties":{"hierarchy":["tgn:7243410","tgn:7003460","tgn:1000003","tgn:1000063","tgn:4012014","tgn:7029392"],"placetype":["aat:300008347"],"id":7243410,"name:xx":"Lassence"}}
>>>>>>> 03f74aca74312dbeaf24d7e61306dd6a786dc3d0
