{
  "id": 7463580,
  "type": "Feature",
  "properties": {
    "tgn:hierarchy":[
        "tgn:7463580",
        "tgn:7002444",
        "tgn:1000003",
        "tgn:7009907",
        "tgn:7008591",
        "tgn:7029392"
    ],
    "tgn:id":7463580,
    "tgn:name:en":"Huip, Holm of",
    "tgn:placetype":[
        "aat:300008791"
    ]
},
  "bbox": [],
  "geometry": {"coordinates":[-2.65,59.166667],"type":"Point"}
}