{
  "id": 7321805,
  "type": "Feature",
  "properties": {
    "tgn:hierarchy":[
        "tgn:7321805",
        "tgn:1001702",
        "tgn:1000049",
        "tgn:1000002",
        "tgn:7029392"
    ],
    "tgn:id":7321805,
    "tgn:name":"Becerra, Estero",
    "tgn:placetype":[
        "aat:300008676"
    ]
},
  "bbox": [],
  "geometry": {"coordinates":[-72.05,-53.966667],"type":"Point"}
}