{
  "id": 2140499,
  "type": "Feature",
  "properties": {
    "tgn:hierarchy":[
        "tgn:2140499",
        "tgn:1000001",
        "tgn:7012149",
        "tgn:2000493",
        "tgn:7007250",
        "tgn:7029392"
    ],
    "tgn:id":2140499,
    "tgn:name":"Austin",
    "tgn:placetype":[
        "aat:300008347"
    ]
},
  "bbox": [],
  "geometry": {"coordinates":[-114.8333,42.65],"type":"Point"}
}