{
  "id": 1039962,
  "type": "Feature",
  "properties": {
    "tgn:hierarchy":[
        "tgn:1039962",
        "tgn:7003692",
        "tgn:1000003",
        "tgn:7000084",
        "tgn:7029392"
    ],
    "tgn:id":1039962,
    "tgn:name":"L\u00f6ffingen",
    "tgn:placetype":[
        "aat:300008347"
    ]
},
  "bbox": [],
  "geometry": {"coordinates":[8.35,47.883333],"type":"Point"}
}