{
  "id": 7417109,
  "type": "Feature",
  "properties": {
    "tgn:hierarchy":[
        "tgn:7417109",
        "tgn:1000001",
        "tgn:7005591",
        "tgn:7005560",
        "tgn:7029392"
    ],
    "tgn:id":7417109,
    "tgn:name:es":"Paso Ancho",
    "tgn:placetype":[
        "aat:300008347"
    ]
},
  "bbox": [],
  "geometry": {"coordinates":[-96.911111,16.383056],"type":"Point"}
}