{
  "id": 2356467,
  "type": "Feature",
  "properties": {
    "tgn:hierarchy":[
        "tgn:2356467",
        "tgn:1000001",
        "tgn:7012149",
        "tgn:1002570",
        "tgn:7007706",
        "tgn:7029392"
    ],
    "tgn:id":2356467,
    "tgn:name":"Gordon Creek",
    "tgn:placetype":[
        "aat:300008706"
    ]
},
  "bbox": [],
  "geometry": {"coordinates":[-81.2167,41.6333],"type":"Point"}
}