{
  "id": 2287565,
  "type": "Feature",
  "properties": {
    "tgn:hierarchy":[
        "tgn:2287565",
        "tgn:1000001",
        "tgn:7012149",
        "tgn:2000618",
        "tgn:7007253",
        "tgn:7029392"
    ],
    "tgn:id":2287565,
    "tgn:name":"Diggins Slough",
    "tgn:placetype":[
        "aat:300008699"
    ]
},
  "bbox": [],
  "geometry": {"coordinates":[-91.1167,41.1167],"type":"Point"}
}