{
  "id": 7014351,
  "type": "Feature",
  "properties": {
    "tgn:hierarchy":[
        "tgn:7014351",
        "tgn:1000001",
        "tgn:7012149",
        "tgn:1003030",
        "tgn:7007251",
        "tgn:7029392"
    ],
    "tgn:id":7014351,
    "tgn:name":"Rockford",
    "tgn:placetype":[
        "aat:300387277",
        "aat:300008347",
        "aat:300008416",
        "aat:300008389",
        "aat:300387308",
        "aat:300387312"
    ]
},
  "bbox": [],
  "geometry": {"coordinates":[-89.0833,42.2667],"type":"Point"}
}