{
  "id": 7222101,
  "type": "Feature",
  "properties": {
    "tgn:hierarchy":[
        "tgn:7222101",
        "tgn:7011170",
        "tgn:7002715",
        "tgn:1000003",
        "tgn:1000074",
        "tgn:7029392"
    ],
    "tgn:id":7222101,
    "tgn:name":"Mikrokh\u00f3rion",
    "tgn:placetype":[
        "aat:300008347"
    ]
},
  "bbox": [],
  "geometry": {"coordinates":[24.45,41.316667],"type":"Point"}
}