{
  "id": 7284732,
  "type": "Feature",
  "properties": {
    "tgn:hierarchy":[
        "tgn:7284732",
        "tgn:1001695",
        "tgn:1000049",
        "tgn:1000002",
        "tgn:7029392"
    ],
    "tgn:id":7284732,
    "tgn:name":"Pihuch\u00e9n",
    "tgn:placetype":[
        "aat:300008347"
    ]
},
  "bbox": [],
  "geometry": {"coordinates":[-71.616667,-34.483333],"type":"Point"}
}