{
  "id": 2473519,
  "type": "Feature",
  "properties": {
    "tgn:hierarchy":[
        "tgn:2473519",
        "tgn:1000001",
        "tgn:2001429",
        "tgn:7012149",
        "tgn:7007566",
        "tgn:7029392"
    ],
    "tgn:id":2473519,
    "tgn:name":"Lower Cold Spring",
    "tgn:placetype":[
        "aat:300008697"
    ]
},
  "bbox": [],
  "geometry": {"coordinates":[-108.55,33.7667],"type":"Point"}
}