{
  "id": 2461665,
  "type": "Feature",
  "properties": {
    "tgn:hierarchy":[
        "tgn:2461665",
        "tgn:1000001",
        "tgn:2002366",
        "tgn:7012149",
        "tgn:7007923",
        "tgn:7029392"
    ],
    "tgn:id":2461665,
    "tgn:name":"Little Tepee Creek",
    "tgn:placetype":[
        "aat:300008706"
    ]
},
  "bbox": [],
  "geometry": {"coordinates":[-107.8833,44.8667],"type":"Point"}
}