{
  "id": 7276137,
  "type": "Feature",
  "properties": {
    "tgn:hierarchy":[
        "tgn:7276137",
        "tgn:1001702",
        "tgn:1000049",
        "tgn:1000002",
        "tgn:7029392"
    ],
    "tgn:id":7276137,
    "tgn:name":"Toro, Puerto",
    "tgn:placetype":[
        "aat:300132317"
    ]
},
  "bbox": [],
  "geometry": {"coordinates":[-67.066667,-55.066667],"type":"Point"}
}