{
  "id": 2698467,
  "type": "Feature",
  "properties": {
    "tgn:hierarchy":[
        "tgn:2698467",
        "tgn:1000001",
        "tgn:2002108",
        "tgn:7012149",
        "tgn:7007827",
        "tgn:7029392"
    ],
    "tgn:id":2698467,
    "tgn:name":"Straight Hollow South Debris Basin Reservoir",
    "tgn:placetype":[
        "aat:300006191"
    ]
},
  "bbox": [],
  "geometry": {"coordinates":[-111.1333,39.0333],"type":"Point"}
}