{
  "id": 2480325,
  "type": "Feature",
  "properties": {
    "tgn:hierarchy":[
        "tgn:2480325",
        "tgn:1000001",
        "tgn:7012149",
        "tgn:1002613",
        "tgn:7007710",
        "tgn:7029392"
    ],
    "tgn:id":2480325,
    "tgn:name":"Lake Run",
    "tgn:placetype":[
        "aat:300008699"
    ]
},
  "bbox": [],
  "geometry": {"coordinates":[-76.6833,41.35],"type":"Point"}
}