{
  "id": 7540800,
  "type": "Feature",
  "properties": {
    "tgn:hierarchy":[
        "tgn:7540800",
        "tgn:7001242",
        "tgn:1001075",
        "tgn:7016833",
        "tgn:7029392"
    ],
    "tgn:id":7540800,
    "tgn:name:en":"Qaryat \u015eal\u0101\u1e29 ad D\u012bn",
    "tgn:placetype":[
        "aat:300008347"
    ]
},
  "bbox": [],
  "geometry": {"coordinates":[30.721488,30.592272],"type":"Point"}
}