{
  "id": 1028026,
  "type": "Feature",
  "properties": {
    "tgn:hierarchy":[
        "tgn:1028026",
        "tgn:1000003",
        "tgn:7594009",
        "tgn:1000066",
        "tgn:7029392"
    ],
    "tgn:id":1028026,
    "tgn:name":"N\u00f8rre \u00c5by",
    "tgn:placetype":[
        "aat:300008347"
    ]
},
  "bbox": [],
  "geometry": {"coordinates":[9.8833,55.4667],"type":"Point"}
}