{
  "id": 2307126,
  "type": "Feature",
  "properties": {
    "tgn:hierarchy":[
        "tgn:2307126",
        "tgn:1000001",
        "tgn:2002318",
        "tgn:7012149",
        "tgn:7007922",
        "tgn:7029392"
    ],
    "tgn:id":2307126,
    "tgn:name":"East Fork Moose River",
    "tgn:placetype":[
        "aat:300008707"
    ]
},
  "bbox": [],
  "geometry": {"coordinates":[-91.8667,46.3833],"type":"Point"}
}