{
  "id": 2682404,
  "type": "Feature",
  "properties": {
    "tgn:hierarchy":[
        "tgn:2682404",
        "tgn:1000001",
        "tgn:7012149",
        "tgn:2000472",
        "tgn:7007250",
        "tgn:7029392"
    ],
    "tgn:id":2682404,
    "tgn:name":"South Worm Creek Basin",
    "tgn:placetype":[
        "aat:300386845"
    ]
},
  "bbox": [],
  "geometry": {"coordinates":[-111.6667,42.1667],"type":"Point"}
}