<<<<<<< HEAD
{
  "id": 7114144,
  "type": "Feature",
  "properties": {
    "tgn:hierarchy":[
        "tgn:7114144",
        "tgn:7003692",
        "tgn:1000003",
        "tgn:7000084",
        "tgn:7029392"
    ],
    "tgn:id":7114144,
    "tgn:name":"Riedkanal",
    "tgn:placetype":[
        "aat:300008699"
    ]
},
  "bbox": [],
  "geometry": {"coordinates":[8.183333,48.9],"type":"Point"}
}
=======
{"geometry":{"type":"Point","coordinates":[8.183333,48.900000]},"type":"Feature","properties":{"hierarchy":["tgn:7114144","tgn:7003692","tgn:1000003","tgn:7000084","tgn:7029392"],"placetype":["aat:300008699"],"id":7114144,"name:xx":"Riedkanal"}}
>>>>>>> 03f74aca74312dbeaf24d7e61306dd6a786dc3d0
