{
  "id": 7559661,
  "type": "Feature",
  "properties": {
    "tgn:hierarchy":[
        "tgn:7559661",
        "tgn:1000004",
        "tgn:7000198",
        "tgn:7016722",
        "tgn:7029392"
    ],
    "tgn:id":7559661,
    "tgn:name:en":"Kursenda",
    "tgn:placetype":[
        "aat:300008347"
    ]
},
  "bbox": [],
  "geometry": {"coordinates":[79.236959,26.277722],"type":"Point"}
}