{
  "id": 2622230,
  "type": "Feature",
  "properties": {
    "tgn:hierarchy":[
        "tgn:2622230",
        "tgn:1000001",
        "tgn:7012149",
        "tgn:7007712",
        "tgn:7029392"
    ],
    "tgn:id":2622230,
    "tgn:name":"Roberts Swamp",
    "tgn:placetype":[
        "aat:300008699"
    ]
},
  "bbox": [],
  "geometry": {"coordinates":[-81.0833,33.5167],"type":"Point"}
}