{
  "id": 7484911,
  "type": "Feature",
  "properties": {
    "tgn:hierarchy":[
        "tgn:7484911",
        "tgn:1000004",
        "tgn:7491221",
        "tgn:1000141",
        "tgn:7029392"
    ],
    "tgn:id":7484911,
    "tgn:name":"Fengxikou",
    "tgn:placetype":[
        "aat:300008777"
    ]
},
  "bbox": [],
  "geometry": {"coordinates":[120.886667,22.268333],"type":"Point"}
}