<<<<<<< HEAD
{
  "id": 7484911,
  "type": "Feature",
  "properties": {
    "tgn:hierarchy":[
        "tgn:7484911",
        "tgn:1000004",
        "tgn:7491221",
        "tgn:1000141",
        "tgn:7029392"
    ],
    "tgn:id":7484911,
    "tgn:name":"Fengxikou",
    "tgn:placetype":[
        "aat:300008777"
    ]
},
  "bbox": [],
  "geometry": {"coordinates":[120.886667,22.268333],"type":"Point"}
}
=======
{"geometry":{"type":"Point","coordinates":[120.886667,22.268333]},"type":"Feature","properties":{"hierarchy":["tgn:7484911","tgn:1000004","tgn:7491221","tgn:1000141","tgn:7029392"],"placetype":["aat:300008777"],"id":7484911,"name:xx":"Fengxikou"}}
>>>>>>> 03f74aca74312dbeaf24d7e61306dd6a786dc3d0
