{
  "id": 2141071,
  "type": "Feature",
  "properties": {
    "tgn:hierarchy":[
        "tgn:2141071",
        "tgn:1000001",
        "tgn:2000872",
        "tgn:7012149",
        "tgn:7007256",
        "tgn:7029392"
    ],
    "tgn:id":2141071,
    "tgn:name":"Avondale Boy Scout Lake",
    "tgn:placetype":[
        "aat:300006191"
    ]
},
  "bbox": [],
  "geometry": {"coordinates":[-90.95,30.8667],"type":"Point"}
}