{
  "id": 1022340,
  "type": "Feature",
  "properties": {
    "tgn:hierarchy":[
        "tgn:1022340",
        "tgn:7006064",
        "tgn:1000047",
        "tgn:7002455",
        "tgn:1000002",
        "tgn:7029392"
    ],
    "tgn:id":1022340,
    "tgn:name":"Parambu",
    "tgn:placetype":[
        "aat:300008347"
    ]
},
  "bbox": [],
  "geometry": {"coordinates":[-40.7167,-6.2167],"type":"Point"}
}