{
  "id": 1090096,
  "type": "Feature",
  "properties": {
    "tgn:hierarchy":[
        "tgn:1090096",
        "tgn:7001242",
        "tgn:7018307",
        "tgn:1000166",
        "tgn:7029392"
    ],
    "tgn:id":1090096,
    "tgn:name":"Bawku",
    "tgn:placetype":[
        "aat:300008347"
    ]
},
  "bbox": [],
  "geometry": {"coordinates":[-0.1833,11.0833],"type":"Point"}
}