{
  "id": 2592368,
  "type": "Feature",
  "properties": {
    "tgn:hierarchy":[
        "tgn:2592368",
        "tgn:1000001",
        "tgn:7012149",
        "tgn:2001066",
        "tgn:7007521",
        "tgn:7029392"
    ],
    "tgn:id":2592368,
    "tgn:name":"Pool Number One",
    "tgn:placetype":[
        "aat:300006191"
    ]
},
  "bbox": [],
  "geometry": {"coordinates":[-96.05,48.95],"type":"Point"}
}