{
  "id": 2736661,
  "type": "Feature",
  "properties": {
    "tgn:hierarchy":[
        "tgn:2736661",
        "tgn:1000001",
        "tgn:7012149",
        "tgn:2001930",
        "tgn:7007825",
        "tgn:7029392"
    ],
    "tgn:id":2736661,
    "tgn:name":"Twin Springs Estates",
    "tgn:placetype":[
        "aat:300008347"
    ]
},
  "bbox": [],
  "geometry": {"coordinates":[-86.7667,35.9833],"type":"Point"}
}