{
  "id": 7136427,
  "type": "Feature",
  "properties": {
    "tgn:hierarchy":[
        "tgn:7136427",
        "tgn:1000003",
        "tgn:7003682",
        "tgn:7000084",
        "tgn:7029392"
    ],
    "tgn:id":7136427,
    "tgn:name":"Moritzheim",
    "tgn:placetype":[
        "aat:300008347"
    ]
},
  "bbox": [],
  "geometry": {"coordinates":[7.266667,50.05],"type":"Point"}
}