{
  "id": 7494387,
  "type": "Feature",
  "properties": {
    "tgn:hierarchy":[
        "tgn:7494387",
        "tgn:7001010",
        "tgn:1000004",
        "tgn:1000141",
        "tgn:7029392"
    ],
    "tgn:id":7494387,
    "tgn:name":"Guangfu Tifang",
    "tgn:placetype":[
        "aat:300006156"
    ]
},
  "bbox": [],
  "geometry": {"coordinates":[121.417096,23.685459],"type":"Point"}
}