{
  "id": 7503057,
  "type": "Feature",
  "properties": {
    "tgn:hierarchy":[
        "tgn:7503057",
        "tgn:7487020",
        "tgn:1000004",
        "tgn:1000141",
        "tgn:7029392"
    ],
    "tgn:id":7503057,
    "tgn:name":"Meiyuan",
    "tgn:placetype":[
        "aat:300008347"
    ]
},
  "bbox": [],
  "geometry": {"coordinates":[120.966225,24.385072],"type":"Point"}
}