{
  "id": 7217304,
  "type": "Feature",
  "properties": {
    "tgn:hierarchy":[
        "tgn:7217304",
        "tgn:7011161",
        "tgn:7002674",
        "tgn:1000003",
        "tgn:1000074",
        "tgn:7029392"
    ],
    "tgn:id":7217304,
    "tgn:name":"Gri\u00e1",
    "tgn:placetype":[
        "aat:300008798"
    ]
},
  "bbox": [],
  "geometry": {"coordinates":[26.092778,38.518611],"type":"Point"}
}