{
  "id": 2383201,
  "type": "Feature",
  "properties": {
    "tgn:hierarchy":[
        "tgn:2383201",
        "tgn:1000001",
        "tgn:7012149",
        "tgn:2000926",
        "tgn:7007515",
        "tgn:7029392"
    ],
    "tgn:id":2383201,
    "tgn:name":"Heald Pond",
    "tgn:placetype":[
        "aat:300008680"
    ]
},
  "bbox": [],
  "geometry": {"coordinates":[-70.8667,44.2167],"type":"Point"}
}