{
  "id": 7308847,
  "type": "Feature",
  "properties": {
    "tgn:hierarchy":[
        "tgn:7308847",
        "tgn:1001702",
        "tgn:1000049",
        "tgn:1000002",
        "tgn:7029392"
    ],
    "tgn:id":7308847,
    "tgn:name":"Los Tres Morros",
    "tgn:placetype":[
        "aat:300008795"
    ]
},
  "bbox": [],
  "geometry": {"coordinates":[-71.25,-53.333333],"type":"Point"}
}