{
  "id": 1087877,
  "type": "Feature",
  "properties": {
    "tgn:hierarchy":[
        "tgn:1087877",
        "tgn:7001242",
        "tgn:1000836",
        "tgn:1000149",
        "tgn:7029392"
    ],
    "tgn:id":1087877,
    "tgn:name":"M\u00f4ngua",
    "tgn:placetype":[
        "aat:300008347"
    ]
},
  "bbox": [],
  "geometry": {"coordinates":[15.3667,-16.7167],"type":"Point"}
}