{
  "id": 1038487,
  "type": "Feature",
  "properties": {
    "tgn:hierarchy":[
        "tgn:1038487",
        "tgn:7003692",
        "tgn:1000003",
        "tgn:7000084",
        "tgn:7029392"
    ],
    "tgn:id":1038487,
    "tgn:name":"Berkheim",
    "tgn:placetype":[
        "aat:300008347"
    ]
},
  "bbox": [],
  "geometry": {"coordinates":[10.083333,48.05],"type":"Point"}
}