{
  "id": 7332968,
  "type": "Feature",
  "properties": {
    "tgn:hierarchy":[
        "tgn:7332968",
        "tgn:7008912",
        "tgn:7030216",
        "tgn:1000003",
        "tgn:1000095",
        "tgn:7029392"
    ],
    "tgn:id":7332968,
    "tgn:name":"Juvell, Coll de",
    "tgn:placetype":[
        "aat:300259572"
    ]
},
  "bbox": [],
  "geometry": {"coordinates":[1.598358,42.270736],"type":"Point"}
}