<<<<<<< HEAD
{
  "id": 2255078,
  "type": "Feature",
  "properties": {
    "tgn:hierarchy":[
        "tgn:2255078",
        "tgn:1000001",
        "tgn:7012149",
        "tgn:2001304",
        "tgn:7007524",
        "tgn:7029392"
    ],
    "tgn:id":2255078,
    "tgn:name":"Cooper Creek Mine",
    "tgn:placetype":[
        "aat:300000390"
    ]
},
  "bbox": [],
  "geometry": {"coordinates":[-115.7,47.5],"type":"Point"}
}
=======
{"geometry":{"type":"Point","coordinates":[-115.700000,47.500000]},"type":"Feature","properties":{"hierarchy":["tgn:2255078","tgn:1000001","tgn:7012149","tgn:2001304","tgn:7007524","tgn:7029392"],"placetype":["aat:300000390"],"id":2255078,"name:xx":"Cooper Creek Mine"}}
>>>>>>> 03f74aca74312dbeaf24d7e61306dd6a786dc3d0
