{
  "id": 7077355,
  "type": "Feature",
  "properties": {
    "tgn:hierarchy":[
        "tgn:7077355",
        "tgn:7000096",
        "tgn:1000003",
        "tgn:7000084",
        "tgn:7029392"
    ],
    "tgn:id":7077355,
    "tgn:name":"Ziegen-Graben",
    "tgn:placetype":[
        "aat:300008699"
    ]
},
  "bbox": [],
  "geometry": {"coordinates":[14.55,52.616667],"type":"Point"}
}