{
  "id": 2204751,
  "type": "Feature",
  "properties": {
    "tgn:hierarchy":[
        "tgn:2204751",
        "tgn:1000001",
        "tgn:7012149",
        "tgn:1002562",
        "tgn:7007251",
        "tgn:7029392"
    ],
    "tgn:id":2204751,
    "tgn:name":"Buffalo Rock",
    "tgn:placetype":[
        "aat:300008798"
    ]
},
  "bbox": [],
  "geometry": {"coordinates":[-88.9167,41.3167],"type":"Point"}
}