{
  "id": 1036436,
  "type": "Feature",
  "properties": {
    "tgn:hierarchy":[
        "tgn:1036436",
        "tgn:1000003",
        "tgn:7003687",
        "tgn:7000084",
        "tgn:7029392"
    ],
    "tgn:id":1036436,
    "tgn:name":"Bennstedt",
    "tgn:placetype":[
        "aat:300008347"
    ]
},
  "bbox": [],
  "geometry": {"coordinates":[11.833333,51.483333],"type":"Point"}
}