{
  "id": 1133994,
  "type": "Feature",
  "properties": {
    "tgn:hierarchy":[
        "tgn:1133994",
        "tgn:1000001",
        "tgn:7012149",
        "tgn:7007826",
        "tgn:7029392"
    ],
    "tgn:id":1133994,
    "tgn:name":"North Croton Creek",
    "tgn:placetype":[
        "aat:300008706"
    ]
},
  "bbox": [],
  "geometry": {"coordinates":[-100.55,33.4667],"type":"Point"}
}