{
  "id": 2625817,
  "type": "Feature",
  "properties": {
    "tgn:hierarchy":[
        "tgn:2625817",
        "tgn:1000001",
        "tgn:7012149",
        "tgn:2001252",
        "tgn:7007523",
        "tgn:7029392"
    ],
    "tgn:id":2625817,
    "tgn:name":"Rocky Branch",
    "tgn:placetype":[
        "aat:300008699"
    ]
},
  "bbox": [],
  "geometry": {"coordinates":[-92.0333,37.25],"type":"Point"}
}