{
  "id": 7420254,
  "type": "Feature",
  "properties": {
    "tgn:hierarchy":[
        "tgn:7420254",
        "tgn:7005584",
        "tgn:1000001",
        "tgn:7005560",
        "tgn:7029392"
    ],
    "tgn:id":7420254,
    "tgn:name":"El Rucio",
    "tgn:placetype":[
        "aat:300008347"
    ]
},
  "bbox": [],
  "geometry": {"coordinates":[-99.875,21.292222],"type":"Point"}
}