{
  "id": 7214198,
  "type": "Feature",
  "properties": {
    "tgn:hierarchy":[
        "tgn:7214198",
        "tgn:1000003",
        "tgn:7003682",
        "tgn:7000084",
        "tgn:7029392"
    ],
    "tgn:id":7214198,
    "tgn:name":"Birkenk\u00f6pfe",
    "tgn:placetype":[
        "aat:300266640"
    ]
},
  "bbox": [],
  "geometry": {"coordinates":[7.783333,49.516667],"type":"Point"}
}