{
  "id": 2368585,
  "type": "Feature",
  "properties": {
    "tgn:hierarchy":[
        "tgn:2368585",
        "tgn:1002139",
        "tgn:1000001",
        "tgn:7012149",
        "tgn:7007568",
        "tgn:7029392"
    ],
    "tgn:id":2368585,
    "tgn:name":"Gulf Creek",
    "tgn:placetype":[
        "aat:300008706"
    ]
},
  "bbox": [],
  "geometry": {"coordinates":[-73.9667,42.45],"type":"Point"}
}