{
  "id": 7227713,
  "type": "Feature",
  "properties": {
    "tgn:hierarchy":[
        "tgn:7227713",
        "tgn:7011170",
        "tgn:7002715",
        "tgn:1000003",
        "tgn:1000074",
        "tgn:7029392"
    ],
    "tgn:id":7227713,
    "tgn:name":"Kat\u00e1khloron",
    "tgn:placetype":[
        "aat:300008057"
    ]
},
  "bbox": [],
  "geometry": {"coordinates":[24.016667,41.45],"type":"Point"}
}