{
  "id": 7571667,
  "type": "Feature",
  "properties": {
    "tgn:hierarchy":[
        "tgn:7571667",
        "tgn:1000004",
        "tgn:7000198",
        "tgn:7016722",
        "tgn:7029392"
    ],
    "tgn:id":7571667,
    "tgn:name:en":"Gobind\u0101pur",
    "tgn:placetype":[
        "aat:300008347"
    ]
},
  "bbox": [],
  "geometry": {"coordinates":[79.399663,28.403681],"type":"Point"}
}