{
  "id": 2737675,
  "type": "Feature",
  "properties": {
    "tgn:hierarchy":[
        "tgn:2737675",
        "tgn:1000001",
        "tgn:7012149",
        "tgn:1002506",
        "tgn:7007919",
        "tgn:7029392"
    ],
    "tgn:id":2737675,
    "tgn:name":"Tylers Beach",
    "tgn:placetype":[
        "aat:300008347"
    ]
},
  "bbox": [],
  "geometry": {"coordinates":[-76.6667,37.0667],"type":"Point"}
}