{
  "id": 7579105,
  "type": "Feature",
  "properties": {
    "tgn:hierarchy":[
        "tgn:7579105",
        "tgn:1000004",
        "tgn:7000198",
        "tgn:7000799",
        "tgn:7029392"
    ],
    "tgn:id":7579105,
    "tgn:name:en":"Skio",
    "tgn:placetype":[
        "aat:300008347"
    ]
},
  "bbox": [],
  "geometry": {"coordinates":[77.260786,33.989176],"type":"Point"}
}