{
  "id": 2514822,
  "type": "Feature",
  "properties": {
    "tgn:hierarchy":[
        "tgn:2514822",
        "tgn:1000001",
        "tgn:7012149",
        "tgn:2000415",
        "tgn:7007248",
        "tgn:7029392"
    ],
    "tgn:id":2514822,
    "tgn:name":"Miller Pond",
    "tgn:placetype":[
        "aat:300006191"
    ]
},
  "bbox": [],
  "geometry": {"coordinates":[-81.6833,32.6833],"type":"Point"}
}