{
  "id": 7136125,
  "type": "Feature",
  "properties": {
    "tgn:hierarchy":[
        "tgn:7136125",
        "tgn:1000003",
        "tgn:7003677",
        "tgn:7000084",
        "tgn:7029392"
    ],
    "tgn:id":7136125,
    "tgn:name":"M\u00fchlenbusch",
    "tgn:placetype":[
        "aat:300008863"
    ]
},
  "bbox": [],
  "geometry": {"coordinates":[6.733333,51.116667],"type":"Point"}
}