{
  "id": 4008825,
  "type": "Feature",
  "properties": {
    "tgn:hierarchy":[
        "tgn:4008825",
        "tgn:7003131",
        "tgn:1000003",
        "tgn:7008516",
        "tgn:1000080",
        "tgn:7029392"
    ],
    "tgn:id":4008825,
    "tgn:name":"Porcigatone",
    "tgn:placetype":[
        "aat:300008347"
    ]
},
  "bbox": [],
  "geometry": {"coordinates":[9.733333,44.516667],"type":"Point"}
}