{
  "id": 7311385,
  "type": "Feature",
  "properties": {
    "tgn:hierarchy":[
        "tgn:7311385",
        "tgn:1001705",
        "tgn:1000049",
        "tgn:1000002",
        "tgn:7029392"
    ],
    "tgn:id":7311385,
    "tgn:name":"Monsalve, Tetas de",
    "tgn:placetype":[
        "aat:300008795"
    ]
},
  "bbox": [],
  "geometry": {"coordinates":[-70.55,-35.666667],"type":"Point"}
}