{
  "id": 2642935,
  "type": "Feature",
  "properties": {
    "tgn:hierarchy":[
        "tgn:2642935",
        "tgn:1000001",
        "tgn:7012149",
        "tgn:2000208",
        "tgn:7007158",
        "tgn:7029392"
    ],
    "tgn:id":2642935,
    "tgn:name":"Sandstone Mountain",
    "tgn:placetype":[
        "aat:300008798"
    ]
},
  "bbox": [],
  "geometry": {"coordinates":[-108.0333,37.7167],"type":"Point"}
}