<<<<<<< HEAD
{
  "id": 7488045,
  "type": "Feature",
  "properties": {
    "tgn:hierarchy":[
        "tgn:7488045",
        "tgn:1000004",
        "tgn:7492971",
        "tgn:1000141",
        "tgn:7029392"
    ],
    "tgn:id":7488045,
    "tgn:name":"Luokangquan",
    "tgn:placetype":[
        "aat:300008347"
    ]
},
  "bbox": [],
  "geometry": {"coordinates":[120.55967,22.585345],"type":"Point"}
}
=======
{"geometry":{"type":"Point","coordinates":[120.559670,22.585345]},"type":"Feature","properties":{"hierarchy":["tgn:7488045","tgn:1000004","tgn:7492971","tgn:1000141","tgn:7029392"],"placetype":["aat:300008347"],"id":7488045,"name:xx":"Luokangquan"}}
>>>>>>> 03f74aca74312dbeaf24d7e61306dd6a786dc3d0
