{
  "id": 2665869,
  "type": "Feature",
  "properties": {
    "tgn:hierarchy":[
        "tgn:2665869",
        "tgn:7006450",
        "tgn:1000001",
        "tgn:7012149",
        "tgn:2000089",
        "tgn:7029392"
    ],
    "tgn:id":2665869,
    "tgn:name":"Sischu Creek",
    "tgn:placetype":[
        "aat:300008706"
    ]
},
  "bbox": [],
  "geometry": {"coordinates":[-152.9167,64.0333],"type":"Point"}
}