{
  "id": 2106050,
  "type": "Feature",
  "properties": {
    "tgn:hierarchy":[
        "tgn:2106050",
        "tgn:1000001",
        "tgn:7012149",
        "tgn:2001987",
        "tgn:7007826",
        "tgn:7029392"
    ],
    "tgn:id":2106050,
    "tgn:name":"Miguel",
    "tgn:placetype":[
        "aat:300008347",
        "aat:300387210"
    ]
},
  "bbox": [],
  "geometry": {"coordinates":[-98.8167,28.9167],"type":"Point"}
}