{
  "id": 2273133,
  "type": "Feature",
  "properties": {
    "tgn:hierarchy":[
        "tgn:2273133",
        "tgn:1000001",
        "tgn:7012149",
        "tgn:2002377",
        "tgn:7007923",
        "tgn:7029392"
    ],
    "tgn:id":2273133,
    "tgn:name":"Cyclone Ridge",
    "tgn:placetype":[
        "aat:300266640"
    ]
},
  "bbox": [],
  "geometry": {"coordinates":[-107.45,42.8833],"type":"Point"}
}