{
  "id": 2644476,
  "type": "Feature",
  "properties": {
    "tgn:hierarchy":[
        "tgn:2644476",
        "tgn:1000001",
        "tgn:7012149",
        "tgn:2000852",
        "tgn:7007255",
        "tgn:7029392"
    ],
    "tgn:id":2644476,
    "tgn:name":"Sarah Sparks Branch",
    "tgn:placetype":[
        "aat:300008699"
    ]
},
  "bbox": [],
  "geometry": {"coordinates":[-84.0833,36.6667],"type":"Point"}
}