{
  "id": 7548523,
  "type": "Feature",
  "properties": {
    "tgn:hierarchy":[
        "tgn:7548523",
        "tgn:1000004",
        "tgn:7000198",
        "tgn:7000799",
        "tgn:7029392"
    ],
    "tgn:id":7548523,
    "tgn:name:en":"Budil",
    "tgn:placetype":[
        "aat:300008347"
    ]
},
  "bbox": [],
  "geometry": {"coordinates":[74.647308,33.376843],"type":"Point"}
}