{
  "id": 7271074,
  "type": "Feature",
  "properties": {
    "tgn:hierarchy":[
        "tgn:7271074",
        "tgn:1000003",
        "tgn:7003613",
        "tgn:7016845",
        "tgn:7029392"
    ],
    "tgn:id":7271074,
    "tgn:name:nl":"Spijkstermaar",
    "tgn:placetype":[
        "aat:300006075"
    ]
},
  "bbox": [],
  "geometry": {"coordinates":[6.833333,53.366667],"type":"Point"}
}