{
  "id": 2008386,
  "type": "Feature",
  "properties": {
    "tgn:hierarchy":[
        "tgn:2008386",
        "tgn:1000001",
        "tgn:7016172",
        "tgn:7012149",
        "tgn:2000178",
        "tgn:7029392"
    ],
    "tgn:id":2008386,
    "tgn:name":"Grays",
    "tgn:placetype":[
        "aat:300008347"
    ]
},
  "bbox": [],
  "geometry": {"coordinates":[-91.2333,35.2167],"type":"Point"}
}