{
  "id": 7526160,
  "type": "Feature",
  "properties": {
    "tgn:hierarchy":[
        "tgn:7526160",
        "tgn:7001242",
        "tgn:7016833",
        "tgn:1001091",
        "tgn:7029392"
    ],
    "tgn:id":7526160,
    "tgn:name":"Makhbaz \u0100l\u012b",
    "tgn:placetype":[
        "aat:300004792"
    ]
},
  "bbox": [],
  "geometry": {"coordinates":[31.297456,30.04268],"type":"Point"}
}