{
  "id": 2581818,
  "type": "Feature",
  "properties": {
    "tgn:hierarchy":[
        "tgn:2581818",
        "tgn:1000001",
        "tgn:7012149",
        "tgn:2000522",
        "tgn:7007251",
        "tgn:7029392"
    ],
    "tgn:id":2581818,
    "tgn:name":"Pinckneyville Reservoir",
    "tgn:placetype":[
        "aat:300006191"
    ]
},
  "bbox": [],
  "geometry": {"coordinates":[-89.3833,38.0833],"type":"Point"}
}