{
  "id": 2173755,
  "type": "Feature",
  "properties": {
    "tgn:hierarchy":[
        "tgn:2173755",
        "tgn:1000001",
        "tgn:7012149",
        "tgn:2001872",
        "tgn:7007825",
        "tgn:7029392"
    ],
    "tgn:id":2173755,
    "tgn:name":"Bird Branch",
    "tgn:placetype":[
        "aat:300008699"
    ]
},
  "bbox": [],
  "geometry": {"coordinates":[-88.15,35.2333],"type":"Point"}
}