{
  "id": 1072232,
  "type": "Feature",
  "properties": {
    "tgn:hierarchy":[
        "tgn:1072232",
        "tgn:1000004",
        "tgn:7002081",
        "tgn:1000111",
        "tgn:7029392"
    ],
    "tgn:id":1072232,
    "tgn:name":"Tianjingzhen",
    "tgn:placetype":[
        "aat:300008347"
    ]
},
  "bbox": [],
  "geometry": {"coordinates":[120.7667,31.4667],"type":"Point"}
}