{
  "id": 7470622,
  "type": "Feature",
  "properties": {
    "tgn:hierarchy":[
        "tgn:7470622",
        "tgn:1000957",
        "tgn:1000004",
        "tgn:1000141",
        "tgn:7029392"
    ],
    "tgn:id":7470622,
    "tgn:name":"Xiandonghu",
    "tgn:placetype":[
        "aat:300008347"
    ]
},
  "bbox": [],
  "geometry": {"coordinates":[121.679933,25.124213],"type":"Point"}
}