{
  "id": 1085409,
  "type": "Feature",
  "properties": {
    "tgn:hierarchy":[
        "tgn:1085409",
        "tgn:1000004",
        "tgn:1000454",
        "tgn:1000141",
        "tgn:7029392"
    ],
    "tgn:id":1085409,
    "tgn:name":"Wu-lai",
    "tgn:placetype":[
        "aat:300008347"
    ]
},
  "bbox": [],
  "geometry": {"coordinates":[121.551331,24.86397],"type":"Point"}
}