{
  "id": 7400526,
  "type": "Feature",
  "properties": {
    "tgn:hierarchy":[
        "tgn:7400526",
        "tgn:1000001",
        "tgn:7005599",
        "tgn:7005560",
        "tgn:7029392"
    ],
    "tgn:id":7400526,
    "tgn:name":"El Progreso",
    "tgn:placetype":[
        "aat:300008347"
    ]
},
  "bbox": [],
  "geometry": {"coordinates":[-95.719444,18.273611],"type":"Point"}
}