{
  "id": 7583327,
  "type": "Feature",
  "properties": {
    "tgn:hierarchy":[
        "tgn:7583327",
        "tgn:1000004",
        "tgn:1001871",
        "tgn:7000198",
        "tgn:7029392"
    ],
    "tgn:id":7583327,
    "tgn:name:en":"R\u0101mnagar",
    "tgn:placetype":[
        "aat:300008347"
    ]
},
  "bbox": [],
  "geometry": {"coordinates":[76.751163,30.017443],"type":"Point"}
}