{
  "id": 7123108,
  "type": "Feature",
  "properties": {
    "tgn:hierarchy":[
        "tgn:7123108",
        "tgn:1000003",
        "tgn:7003678",
        "tgn:7000084",
        "tgn:7029392"
    ],
    "tgn:id":7123108,
    "tgn:name":"Neuem\u00fchle",
    "tgn:placetype":[
        "aat:300008347"
    ]
},
  "bbox": [],
  "geometry": {"coordinates":[9.483333,51.283333],"type":"Point"}
}