{
  "id": 1014697,
  "type": "Feature",
  "properties": {
    "tgn:hierarchy":[
        "tgn:1014697",
        "tgn:7005685",
        "tgn:1000001",
        "tgn:7013154",
        "tgn:7029392"
    ],
    "tgn:id":1014697,
    "tgn:name":"Courtland",
    "tgn:placetype":[
        "aat:300008347"
    ]
},
  "bbox": [],
  "geometry": {"coordinates":[-80.6333,42.85],"type":"Point"}
}