{
  "id": 1082415,
  "type": "Feature",
  "properties": {
    "tgn:hierarchy":[
        "tgn:1082415",
        "tgn:1000004",
        "tgn:1001372",
        "tgn:7000299",
        "tgn:7029392"
    ],
    "tgn:id":1082415,
    "tgn:name":"Yech'\u014fn",
    "tgn:placetype":[
        "aat:300008347"
    ]
},
  "bbox": [],
  "geometry": {"coordinates":[128.45,36.65],"type":"Point"}
}