<<<<<<< HEAD
{
  "id": 7350515,
  "type": "Feature",
  "properties": {
    "tgn:hierarchy":[
        "tgn:7350515",
        "tgn:1000001",
        "tgn:1001960",
        "tgn:7005560",
        "tgn:7029392"
    ],
    "tgn:id":7350515,
    "tgn:name":"Rancho B\u00e1chomocobe",
    "tgn:placetype":[
        "aat:300000241"
    ]
},
  "bbox": [],
  "geometry": {"coordinates":[-109.75,26.9],"type":"Point"}
}
=======
{"geometry":{"type":"Point","coordinates":[-109.750000,26.900000]},"type":"Feature","properties":{"hierarchy":["tgn:7350515","tgn:1000001","tgn:1001960","tgn:7005560","tgn:7029392"],"placetype":["aat:300000241"],"id":7350515,"name:xx":"Rancho B\u00e1chomocobe"}}
>>>>>>> 03f74aca74312dbeaf24d7e61306dd6a786dc3d0
