{
  "id": 7485453,
  "type": "Feature",
  "properties": {
    "tgn:hierarchy":[
        "tgn:7485453",
        "tgn:7001004",
        "tgn:1000004",
        "tgn:1000141",
        "tgn:7029392"
    ],
    "tgn:id":7485453,
    "tgn:name":"Huashan Qiao",
    "tgn:placetype":[
        "aat:300007836"
    ]
},
  "bbox": [],
  "geometry": {"coordinates":[120.230833,22.868333],"type":"Point"}
}