<<<<<<< HEAD
{
  "id": 7485453,
  "type": "Feature",
  "properties": {
    "tgn:hierarchy":[
        "tgn:7485453",
        "tgn:7001004",
        "tgn:1000004",
        "tgn:1000141",
        "tgn:7029392"
    ],
    "tgn:id":7485453,
    "tgn:name":"Huashan Qiao",
    "tgn:placetype":[
        "aat:300007836"
    ]
},
  "bbox": [],
  "geometry": {"coordinates":[120.230833,22.868333],"type":"Point"}
}
=======
{"geometry":{"type":"Point","coordinates":[120.230833,22.868333]},"type":"Feature","properties":{"hierarchy":["tgn:7485453","tgn:7001004","tgn:1000004","tgn:1000141","tgn:7029392"],"placetype":["aat:300007836"],"id":7485453,"name:xx":"Huashan Qiao"}}
>>>>>>> 03f74aca74312dbeaf24d7e61306dd6a786dc3d0
