{
  "id": 7593008,
  "type": "Feature",
  "properties": {
    "tgn:hierarchy":[
        "tgn:7593008",
        "tgn:1000004",
        "tgn:7000198",
        "tgn:7000799",
        "tgn:7029392"
    ],
    "tgn:id":7593008,
    "tgn:name:en":"Chh\u0101nigund",
    "tgn:placetype":[
        "aat:300008699"
    ]
},
  "bbox": [],
  "geometry": {"coordinates":[76.058333,34.566667],"type":"Point"}
}