{
  "id": 2553513,
  "type": "Feature",
  "properties": {
    "tgn:hierarchy":[
        "tgn:2553513",
        "tgn:1000001",
        "tgn:7012149",
        "tgn:7007827",
        "tgn:7029392"
    ],
    "tgn:id":2553513,
    "tgn:name":"Oak Creek",
    "tgn:placetype":[
        "aat:300008706"
    ]
},
  "bbox": [],
  "geometry": {"coordinates":[-110.8333,38.1333],"type":"Point"}
}