{
  "id": 1032590,
  "type": "Feature",
  "properties": {
    "tgn:hierarchy":[
        "tgn:1032590",
        "tgn:1000003",
        "tgn:7002883",
        "tgn:1000070",
        "tgn:7029392"
    ],
    "tgn:id":1032590,
    "tgn:name":"Chanteloup",
    "tgn:placetype":[
        "aat:300008347"
    ]
},
  "bbox": [],
  "geometry": {"coordinates":[2.7333,48.85],"type":"Point"}
}