{
  "id": 2187712,
  "type": "Feature",
  "properties": {
    "tgn:hierarchy":[
        "tgn:2187712",
        "tgn:1000001",
        "tgn:7012149",
        "tgn:2001724",
        "tgn:7007710",
        "tgn:7029392"
    ],
    "tgn:id":2187712,
    "tgn:name":"Boothe Run",
    "tgn:placetype":[
        "aat:300008699"
    ]
},
  "bbox": [],
  "geometry": {"coordinates":[-80.35,39.9833],"type":"Point"}
}