<<<<<<< HEAD
{
  "id": 7351975,
  "type": "Feature",
  "properties": {
    "tgn:hierarchy":[
        "tgn:7351975",
        "tgn:1000001",
        "tgn:7005601",
        "tgn:7005560",
        "tgn:7029392"
    ],
    "tgn:id":7351975,
    "tgn:name":"Calabazas",
    "tgn:placetype":[
        "aat:300008347"
    ]
},
  "bbox": [],
  "geometry": {"coordinates":[-102.75,23.433333],"type":"Point"}
}
=======
{"geometry":{"type":"Point","coordinates":[-102.750000,23.433333]},"type":"Feature","properties":{"hierarchy":["tgn:7351975","tgn:1000001","tgn:7005601","tgn:7005560","tgn:7029392"],"placetype":["aat:300008347"],"id":7351975,"name:xx":"Calabazas"}}
>>>>>>> 03f74aca74312dbeaf24d7e61306dd6a786dc3d0
