{
  "id": 7310700,
  "type": "Feature",
  "properties": {
    "tgn:hierarchy":[
        "tgn:7310700",
        "tgn:1001702",
        "tgn:1000049",
        "tgn:1000002",
        "tgn:7029392"
    ],
    "tgn:id":7310700,
    "tgn:name":"Morri\u00f3n, Mogote del",
    "tgn:placetype":[
        "aat:300008791"
    ]
},
  "bbox": [],
  "geometry": {"coordinates":[-72.45,-53.583333],"type":"Point"}
}