{
  "id": 7367615,
  "type": "Feature",
  "properties": {
    "tgn:hierarchy":[
        "tgn:7367615",
        "tgn:7016644",
        "tgn:1000001",
        "tgn:7005560",
        "tgn:7029392"
    ],
    "tgn:id":7367615,
    "tgn:name":"Estrecho",
    "tgn:placetype":[
        "aat:300008347"
    ]
},
  "bbox": [],
  "geometry": {"coordinates":[-104.516667,19.133333],"type":"Point"}
}