{
  "id": 2625596,
  "type": "Feature",
  "properties": {
    "tgn:hierarchy":[
        "tgn:2625596",
        "tgn:1000001",
        "tgn:2001432",
        "tgn:7012149",
        "tgn:7007566",
        "tgn:7029392"
    ],
    "tgn:id":2625596,
    "tgn:name":"Rockwell Lake",
    "tgn:placetype":[
        "aat:300008680"
    ]
},
  "bbox": [],
  "geometry": {"coordinates":[-104.1167,36.7667],"type":"Point"}
}