{
  "id": 2399833,
  "type": "Feature",
  "properties": {
    "tgn:hierarchy":[
        "tgn:2399833",
        "tgn:1000001",
        "tgn:7006451",
        "tgn:7012149",
        "tgn:2000101",
        "tgn:7029392"
    ],
    "tgn:id":2399833,
    "tgn:name":"Horse Camp Basin",
    "tgn:placetype":[
        "aat:300386845"
    ]
},
  "bbox": [],
  "geometry": {"coordinates":[-111.2833,33.45],"type":"Point"}
}