{
  "id": 2520506,
  "type": "Feature",
  "properties": {
    "tgn:hierarchy":[
        "tgn:2520506",
        "tgn:1000001",
        "tgn:2001418",
        "tgn:7012149",
        "tgn:7007526",
        "tgn:7029392"
    ],
    "tgn:id":2520506,
    "tgn:name":"Monitor Belmont Mine",
    "tgn:placetype":[
        "aat:300000390"
    ]
},
  "bbox": [],
  "geometry": {"coordinates":[-116.85,38.5667],"type":"Point"}
}