<<<<<<< HEAD
{
  "id": 7179599,
  "type": "Feature",
  "properties": {
    "tgn:hierarchy":[
        "tgn:7179599",
        "tgn:1000003",
        "tgn:7003676",
        "tgn:7000084",
        "tgn:7029392"
    ],
    "tgn:id":7179599,
    "tgn:name":"Hambrak",
    "tgn:placetype":[
        "aat:300000206"
    ]
},
  "bbox": [],
  "geometry": {"coordinates":[8.533333,52.6],"type":"Point"}
}
=======
{"geometry":{"type":"Point","coordinates":[8.533333,52.600000]},"type":"Feature","properties":{"hierarchy":["tgn:7179599","tgn:1000003","tgn:7003676","tgn:7000084","tgn:7029392"],"placetype":["aat:300000206"],"id":7179599,"name:xx":"Hambrak"}}
>>>>>>> 03f74aca74312dbeaf24d7e61306dd6a786dc3d0
