{
  "id": 2489727,
  "type": "Feature",
  "properties": {
    "tgn:hierarchy":[
        "tgn:2489727",
        "tgn:1000001",
        "tgn:7012149",
        "tgn:2001309",
        "tgn:7007524",
        "tgn:7029392"
    ],
    "tgn:id":2489727,
    "tgn:name":"Malone",
    "tgn:placetype":[
        "aat:300008347"
    ]
},
  "bbox": [],
  "geometry": {"coordinates":[-112.1667,47.9333],"type":"Point"}
}