{
  "id": 2499480,
  "type": "Feature",
  "properties": {
    "tgn:hierarchy":[
        "tgn:2499480",
        "tgn:7006450",
        "tgn:1000001",
        "tgn:7012149",
        "tgn:2124005",
        "tgn:7029392"
    ],
    "tgn:id":2499480,
    "tgn:name":"McClure Islands",
    "tgn:placetype":[
        "aat:300386853"
    ]
},
  "bbox": [],
  "geometry": {"coordinates":[-147.3833,70.35],"type":"Point"}
}