<<<<<<< HEAD
{
  "id": 2333165,
  "type": "Feature",
  "properties": {
    "tgn:hierarchy":[
        "tgn:2333165",
        "tgn:1000001",
        "tgn:7012149",
        "tgn:2001888",
        "tgn:7007825",
        "tgn:7029392"
    ],
    "tgn:id":2333165,
    "tgn:name":"Flynn Branch",
    "tgn:placetype":[
        "aat:300008699"
    ]
},
  "bbox": [],
  "geometry": {"coordinates":[-86.65,35.0333],"type":"Point"}
}
=======
{"geometry":{"type":"Point","coordinates":[-86.650000,35.033300]},"type":"Feature","properties":{"hierarchy":["tgn:2333165","tgn:1000001","tgn:7012149","tgn:2001888","tgn:7007825","tgn:7029392"],"placetype":["aat:300008699"],"id":2333165,"name:xx":"Flynn Branch"}}
>>>>>>> 03f74aca74312dbeaf24d7e61306dd6a786dc3d0
