<<<<<<< HEAD
{
  "id": 7027150,
  "type": "Feature",
  "properties": {
    "tgn:hierarchy":[
        "tgn:7027150",
        "tgn:7002445",
        "tgn:1000003",
        "tgn:7008143",
        "tgn:7008591",
        "tgn:7029392"
    ],
    "tgn:id":7027150,
    "tgn:name":"Tarrington",
    "tgn:placetype":[
        "aat:300008347",
        "aat:300008372"
    ]
},
  "bbox": [],
  "geometry": {"coordinates":[-2.5667,52.0667],"type":"Point"}
}
=======
{"geometry":{"type":"Point","coordinates":[-2.566700,52.066700]},"type":"Feature","properties":{"hierarchy":["tgn:7027150","tgn:7002445","tgn:1000003","tgn:7008143","tgn:7008591","tgn:7029392"],"placetype":["aat:300008347","aat:300008372"],"id":7027150,"name:xx":"Tarrington"}}
>>>>>>> 03f74aca74312dbeaf24d7e61306dd6a786dc3d0
