{
  "id": 2636713,
  "type": "Feature",
  "properties": {
    "tgn:hierarchy":[
        "tgn:2636713",
        "tgn:1000001",
        "tgn:7012149",
        "tgn:7007524",
        "tgn:7029392"
    ],
    "tgn:id":2636713,
    "tgn:name":"Sagebrush Creek",
    "tgn:placetype":[
        "aat:300008706"
    ]
},
  "bbox": [],
  "geometry": {"coordinates":[-105.9333,45.7833],"type":"Point"}
}