<<<<<<< HEAD
{
  "id": 7057582,
  "type": "Feature",
  "properties": {
    "tgn:hierarchy":[
        "tgn:7057582",
        "tgn:7007850",
        "tgn:1000003",
        "tgn:1000080",
        "tgn:7029392"
    ],
    "tgn:id":7057582,
    "tgn:name":"Aspromonte",
    "tgn:placetype":[
        "aat:300008795"
    ]
},
  "bbox": [],
  "geometry": {"coordinates":[16.0,38.166667],"type":"Point"}
}
=======
{"geometry":{"type":"Point","coordinates":[16.000000,38.166667]},"type":"Feature","properties":{"hierarchy":["tgn:7057582","tgn:7007850","tgn:1000003","tgn:1000080","tgn:7029392"],"placetype":["aat:300008795"],"id":7057582,"name:xx":"Aspromonte"}}
>>>>>>> 03f74aca74312dbeaf24d7e61306dd6a786dc3d0
