{
  "id": 2074649,
  "type": "Feature",
  "properties": {
    "tgn:hierarchy":[
        "tgn:2074649",
        "tgn:1000001",
        "tgn:7013557",
        "tgn:7012149",
        "tgn:7007709",
        "tgn:7029392"
    ],
    "tgn:id":2074649,
    "tgn:name":"Fitch",
    "tgn:placetype":[
        "aat:300008347",
        "aat:300387210"
    ]
},
  "bbox": [],
  "geometry": {"coordinates":[-79.35,36.3167],"type":"Point"}
}