<<<<<<< HEAD
{
  "id": 7378524,
  "type": "Feature",
  "properties": {
    "tgn:hierarchy":[
        "tgn:7378524",
        "tgn:1000001",
        "tgn:1001906",
        "tgn:7005560",
        "tgn:7029392"
    ],
    "tgn:id":7378524,
    "tgn:name":"Las Cuevas",
    "tgn:placetype":[
        "aat:300008347"
    ]
},
  "bbox": [],
  "geometry": {"coordinates":[-104.583333,21.5],"type":"Point"}
}
=======
{"geometry":{"type":"Point","coordinates":[-104.583333,21.500000]},"type":"Feature","properties":{"hierarchy":["tgn:7378524","tgn:1000001","tgn:1001906","tgn:7005560","tgn:7029392"],"placetype":["aat:300008347"],"id":7378524,"name:xx":"Las Cuevas"}}
>>>>>>> 03f74aca74312dbeaf24d7e61306dd6a786dc3d0
