{
  "id": 2453855,
  "type": "Feature",
  "properties": {
    "tgn:hierarchy":[
        "tgn:2453855",
        "tgn:1000001",
        "tgn:7012149",
        "tgn:2001713",
        "tgn:7007708",
        "tgn:7029392"
    ],
    "tgn:id":2453855,
    "tgn:name":"Little Craggy Creek",
    "tgn:placetype":[
        "aat:300008706"
    ]
},
  "bbox": [],
  "geometry": {"coordinates":[-123.3167,42.05],"type":"Point"}
}