{
  "id": 2185627,
  "type": "Feature",
  "properties": {
    "tgn:hierarchy":[
        "tgn:2185627",
        "tgn:1000001",
        "tgn:7012149",
        "tgn:2000752",
        "tgn:7007254",
        "tgn:7029392"
    ],
    "tgn:id":2185627,
    "tgn:name":"Boiling Springs",
    "tgn:placetype":[
        "aat:300008697"
    ]
},
  "bbox": [],
  "geometry": {"coordinates":[-98.55,38.15],"type":"Point"}
}