{
  "id": 2692195,
  "type": "Feature",
  "properties": {
    "tgn:hierarchy":[
        "tgn:2692195",
        "tgn:1000001",
        "tgn:7012149",
        "tgn:1002987",
        "tgn:7007706",
        "tgn:7029392"
    ],
    "tgn:id":2692195,
    "tgn:name":"Station Creek",
    "tgn:placetype":[
        "aat:300008706"
    ]
},
  "bbox": [],
  "geometry": {"coordinates":[-84.2667,39.4333],"type":"Point"}
}