{
  "id": 2168094,
  "type": "Feature",
  "properties": {
    "tgn:hierarchy":[
        "tgn:2168094",
        "tgn:1000001",
        "tgn:2000470",
        "tgn:7012149",
        "tgn:7007250",
        "tgn:7029392"
    ],
    "tgn:id":2168094,
    "tgn:name":"Big Fall Creek Lake",
    "tgn:placetype":[
        "aat:300008680"
    ]
},
  "bbox": [],
  "geometry": {"coordinates":[-114.2333,43.8667],"type":"Point"}
}