{
  "id": 2580461,
  "type": "Feature",
  "properties": {
    "tgn:hierarchy":[
        "tgn:2580461",
        "tgn:1000001",
        "tgn:7012149",
        "tgn:2000225",
        "tgn:7007158",
        "tgn:7029392"
    ],
    "tgn:id":2580461,
    "tgn:name":"Pigeon Creek",
    "tgn:placetype":[
        "aat:300008706"
    ]
},
  "bbox": [],
  "geometry": {"coordinates":[-107.65,37.6167],"type":"Point"}
}