{
  "id": 1012900,
  "type": "Feature",
  "properties": {
    "tgn:hierarchy":[
        "tgn:1012900",
        "tgn:7017310",
        "tgn:1000003",
        "tgn:7006663",
        "tgn:7029392"
    ],
    "tgn:id":1012900,
    "tgn:name":"Pelje\u0161ac",
    "tgn:placetype":[
        "aat:300008804"
    ]
},
  "bbox": [],
  "geometry": {"coordinates":[17.3333,42.9667],"type":"Point"}
}