<<<<<<< HEAD
{
  "id": 7372058,
  "type": "Feature",
  "properties": {
    "tgn:hierarchy":[
        "tgn:7372058",
        "tgn:1000001",
        "tgn:7005597",
        "tgn:7005560",
        "tgn:7029392"
    ],
    "tgn:id":7372058,
    "tgn:name":"Lajas, Arroyo de las",
    "tgn:placetype":[
        "aat:300008699"
    ]
},
  "bbox": [],
  "geometry": {"coordinates":[-97.783333,23.033333],"type":"Point"}
}
=======
{"geometry":{"type":"Point","coordinates":[-97.783333,23.033333]},"type":"Feature","properties":{"hierarchy":["tgn:7372058","tgn:1000001","tgn:7005597","tgn:7005560","tgn:7029392"],"placetype":["aat:300008699"],"id":7372058,"name:xx":"Lajas, Arroyo de las"}}
>>>>>>> 03f74aca74312dbeaf24d7e61306dd6a786dc3d0
