{
  "id": 2687122,
  "type": "Feature",
  "properties": {
    "tgn:hierarchy":[
        "tgn:2687122",
        "tgn:7002659",
        "tgn:1000001",
        "tgn:7012149",
        "tgn:2000055",
        "tgn:7029392"
    ],
    "tgn:id":2687122,
    "tgn:name":"Spring Hill Number One Mine",
    "tgn:placetype":[
        "aat:300000390"
    ]
},
  "bbox": [],
  "geometry": {"coordinates":[-85.5833,33.4667],"type":"Point"}
}