{
  "id": 7341453,
  "type": "Feature",
  "properties": {
    "tgn:hierarchy":[
        "tgn:7341453",
        "tgn:7008911",
        "tgn:1000003",
        "tgn:7002763",
        "tgn:1000095",
        "tgn:7029392"
    ],
    "tgn:id":7341453,
    "tgn:name":"Berrue\u00f1o",
    "tgn:placetype":[
        "aat:300008347"
    ]
},
  "bbox": [],
  "geometry": {"coordinates":[-6.066667,43.15],"type":"Point"}
}