{
  "id": 2531708,
  "type": "Feature",
  "properties": {
    "tgn:hierarchy":[
        "tgn:2531708",
        "tgn:1000001",
        "tgn:7012149",
        "tgn:2002018",
        "tgn:7007826",
        "tgn:7029392"
    ],
    "tgn:id":2531708,
    "tgn:name":"Mullen Creek",
    "tgn:placetype":[
        "aat:300008706"
    ]
},
  "bbox": [],
  "geometry": {"coordinates":[-99.4667,29.9167],"type":"Point"}
}