{
  "id": 2428026,
  "type": "Feature",
  "properties": {
    "tgn:hierarchy":[
        "tgn:2428026",
        "tgn:1000001",
        "tgn:7012149",
        "tgn:2002099",
        "tgn:7007826",
        "tgn:7029392"
    ],
    "tgn:id":2428026,
    "tgn:name":"Juanes Tank",
    "tgn:placetype":[
        "aat:300006191"
    ]
},
  "bbox": [],
  "geometry": {"coordinates":[-99.1333,26.8333],"type":"Point"}
}