{
  "id": 7369488,
  "type": "Feature",
  "properties": {
    "tgn:hierarchy":[
        "tgn:7369488",
        "tgn:7005583",
        "tgn:1000001",
        "tgn:7005560",
        "tgn:7029392"
    ],
    "tgn:id":7369488,
    "tgn:name":"Jaboncillo",
    "tgn:placetype":[
        "aat:300008347"
    ]
},
  "bbox": [],
  "geometry": {"coordinates":[-103.733333,26.016667],"type":"Point"}
}