{
  "id": 2037247,
  "type": "Feature",
  "properties": {
    "tgn:hierarchy":[
        "tgn:2037247",
        "tgn:1000001",
        "tgn:7012149",
        "tgn:2000744",
        "tgn:7007254",
        "tgn:7029392"
    ],
    "tgn:id":2037247,
    "tgn:name":"Trenton",
    "tgn:placetype":[
        "aat:300387016"
    ]
},
  "bbox": [],
  "geometry": {"coordinates":[-97.6333,38.8833],"type":"Point"}
}