{
  "id": 2605696,
  "type": "Feature",
  "properties": {
    "tgn:hierarchy":[
        "tgn:2605696",
        "tgn:1000001",
        "tgn:2002108",
        "tgn:7012149",
        "tgn:7007827",
        "tgn:7029392"
    ],
    "tgn:id":2605696,
    "tgn:name":"Rain Canyon",
    "tgn:placetype":[
        "aat:300008761"
    ]
},
  "bbox": [],
  "geometry": {"coordinates":[-110.0667,39.3667],"type":"Point"}
}