{
  "id": 2207556,
  "type": "Feature",
  "properties": {
    "tgn:hierarchy":[
        "tgn:2207556",
        "tgn:1000001",
        "tgn:7012149",
        "tgn:1002918",
        "tgn:7007252",
        "tgn:7029392"
    ],
    "tgn:id":2207556,
    "tgn:name":"Burbank Ditch",
    "tgn:placetype":[
        "aat:300006075"
    ]
},
  "bbox": [],
  "geometry": {"coordinates":[-86.7833,41.1833],"type":"Point"}
}