{
  "id": 7503749,
  "type": "Feature",
  "properties": {
    "tgn:hierarchy":[
        "tgn:7503749",
        "tgn:7001004",
        "tgn:1000004",
        "tgn:1000141",
        "tgn:7029392"
    ],
    "tgn:id":7503749,
    "tgn:name":"Qiwei Baozhong Yimin Miao",
    "tgn:placetype":[
        "aat:300007595"
    ]
},
  "bbox": [],
  "geometry": {"coordinates":[120.497778,22.891667],"type":"Point"}
}