{
  "id": 2005834,
  "type": "Feature",
  "properties": {
    "tgn:hierarchy":[
        "tgn:2005834",
        "tgn:7002659",
        "tgn:1000001",
        "tgn:7012149",
        "tgn:2000059",
        "tgn:7029392"
    ],
    "tgn:id":2005834,
    "tgn:name":"York",
    "tgn:placetype":[
        "aat:300008347"
    ]
},
  "bbox": [],
  "geometry": {"coordinates":[-88.2833,32.4833],"type":"Point"}
}