{
  "id": 2570610,
  "type": "Feature",
  "properties": {
    "tgn:hierarchy":[
        "tgn:2570610",
        "tgn:1000001",
        "tgn:7012149",
        "tgn:1002588",
        "tgn:7007520",
        "tgn:7029392"
    ],
    "tgn:id":2570610,
    "tgn:name":"Patrick Drain",
    "tgn:placetype":[
        "aat:300008699"
    ]
},
  "bbox": [],
  "geometry": {"coordinates":[-84.3167,41.9167],"type":"Point"}
}