{
  "id": 2009196,
  "type": "Feature",
  "properties": {
    "tgn:hierarchy":[
        "tgn:2009196",
        "tgn:1000001",
        "tgn:7016172",
        "tgn:2000116",
        "tgn:7012149",
        "tgn:7029392"
    ],
    "tgn:id":2009196,
    "tgn:name":"Pearson",
    "tgn:placetype":[
        "aat:300008347"
    ]
},
  "bbox": [],
  "geometry": {"coordinates":[-92.1167,35.4333],"type":"Point"}
}