<<<<<<< HEAD
{
  "id": 2405279,
  "type": "Feature",
  "properties": {
    "tgn:hierarchy":[
        "tgn:2405279",
        "tgn:1000001",
        "tgn:7012149",
        "tgn:2001883",
        "tgn:7007825",
        "tgn:7029392"
    ],
    "tgn:id":2405279,
    "tgn:name":"Huffaker Shoals",
    "tgn:placetype":[
        "aat:300132348"
    ]
},
  "bbox": [],
  "geometry": {"coordinates":[-83.7167,35.95],"type":"Point"}
}
=======
{"geometry":{"type":"Point","coordinates":[-83.716700,35.950000]},"type":"Feature","properties":{"hierarchy":["tgn:2405279","tgn:1000001","tgn:7012149","tgn:2001883","tgn:7007825","tgn:7029392"],"placetype":["aat:300132348"],"id":2405279,"name:xx":"Huffaker Shoals"}}
>>>>>>> 03f74aca74312dbeaf24d7e61306dd6a786dc3d0
