{
  "id": 7048604,
  "type": "Feature",
  "properties": {
    "tgn:hierarchy":[
        "tgn:7048604",
        "tgn:1003473",
        "tgn:1000003",
        "tgn:7009760",
        "tgn:1000080",
        "tgn:7029392"
    ],
    "tgn:id":7048604,
    "tgn:name":"Casa Fava",
    "tgn:placetype":[
        "aat:300008347"
    ]
},
  "bbox": [],
  "geometry": {"coordinates":[9.75,44.333333],"type":"Point"}
}