{
  "id": 2268573,
  "type": "Feature",
  "properties": {
    "tgn:hierarchy":[
        "tgn:2268573",
        "tgn:2000855",
        "tgn:1000001",
        "tgn:7012149",
        "tgn:7007256",
        "tgn:7029392"
    ],
    "tgn:id":2268573,
    "tgn:name":"Crosby Lake",
    "tgn:placetype":[
        "aat:300008680"
    ]
},
  "bbox": [],
  "geometry": {"coordinates":[-92.95,30.5833],"type":"Point"}
}