{
  "id": 7278223,
  "type": "Feature",
  "properties": {
    "tgn:hierarchy":[
        "tgn:7278223",
        "tgn:1001637",
        "tgn:1000049",
        "tgn:1000002",
        "tgn:7029392"
    ],
    "tgn:id":7278223,
    "tgn:name":"El Soldado, Caleta",
    "tgn:placetype":[
        "aat:300132317"
    ]
},
  "bbox": [],
  "geometry": {"coordinates":[-73.141667,-36.6875],"type":"Point"}
}