{
  "id": 7219485,
  "type": "Feature",
  "properties": {
    "tgn:hierarchy":[
        "tgn:7219485",
        "tgn:4003773",
        "tgn:7001395",
        "tgn:1000003",
        "tgn:1000074",
        "tgn:7029392"
    ],
    "tgn:id":7219485,
    "tgn:name":"Vo\u00efdh\u00f3rrema",
    "tgn:placetype":[
        "aat:300008699"
    ]
},
  "bbox": [],
  "geometry": {"coordinates":[22.283333,38.916667],"type":"Point"}
}