{
  "id": 7133436,
  "type": "Feature",
  "properties": {
    "tgn:hierarchy":[
        "tgn:7133436",
        "tgn:7003692",
        "tgn:1000003",
        "tgn:7000084",
        "tgn:7029392"
    ],
    "tgn:id":7133436,
    "tgn:name":"M\u00fchlebach",
    "tgn:placetype":[
        "aat:300008699"
    ]
},
  "bbox": [],
  "geometry": {"coordinates":[8.783333,47.766667],"type":"Point"}
}