<<<<<<< HEAD
{
  "id": 7051531,
  "type": "Feature",
  "properties": {
    "tgn:hierarchy":[
        "tgn:7051531",
        "tgn:7003013",
        "tgn:7003005",
        "tgn:1000003",
        "tgn:1000080",
        "tgn:7029392"
    ],
    "tgn:id":7051531,
    "tgn:name":"Stazione Napoli Centrale",
    "tgn:placetype":[
        "aat:300007783"
    ]
},
  "bbox": [],
  "geometry": {"coordinates":[14.283333,40.85],"type":"Point"}
}
=======
{"geometry":{"type":"Point","coordinates":[14.283333,40.850000]},"type":"Feature","properties":{"hierarchy":["tgn:7051531","tgn:7003013","tgn:7003005","tgn:1000003","tgn:1000080","tgn:7029392"],"placetype":["aat:300007783"],"id":7051531,"name:xx":"Stazione Napoli Centrale"}}
>>>>>>> 03f74aca74312dbeaf24d7e61306dd6a786dc3d0
