{
  "id": 2335900,
  "type": "Feature",
  "properties": {
    "tgn:hierarchy":[
        "tgn:2335900",
        "tgn:1000001",
        "tgn:7006451",
        "tgn:2000092",
        "tgn:7012149",
        "tgn:7029392"
    ],
    "tgn:id":2335900,
    "tgn:name":"Fossil Canyon",
    "tgn:placetype":[
        "aat:300008761"
    ]
},
  "bbox": [],
  "geometry": {"coordinates":[-112.5333,36.3333],"type":"Point"}
}