<<<<<<< HEAD
{
  "id": 2335900,
  "type": "Feature",
  "properties": {
    "tgn:hierarchy":[
        "tgn:2335900",
        "tgn:1000001",
        "tgn:7006451",
        "tgn:2000092",
        "tgn:7012149",
        "tgn:7029392"
    ],
    "tgn:id":2335900,
    "tgn:name":"Fossil Canyon",
    "tgn:placetype":[
        "aat:300008761"
    ]
},
  "bbox": [],
  "geometry": {"coordinates":[-112.5333,36.3333],"type":"Point"}
}
=======
{"geometry":{"type":"Point","coordinates":[-112.533300,36.333300]},"type":"Feature","properties":{"hierarchy":["tgn:2335900","tgn:1000001","tgn:7006451","tgn:2000092","tgn:7012149","tgn:7029392"],"placetype":["aat:300008761"],"id":2335900,"name:xx":"Fossil Canyon"}}
>>>>>>> 03f74aca74312dbeaf24d7e61306dd6a786dc3d0
