{
  "id": 2147044,
  "type": "Feature",
  "properties": {
    "tgn:hierarchy":[
        "tgn:2147044",
        "tgn:1000001",
        "tgn:7012149",
        "tgn:2001449",
        "tgn:7007566",
        "tgn:7029392"
    ],
    "tgn:id":2147044,
    "tgn:name":"Bano Tank",
    "tgn:placetype":[
        "aat:300006191"
    ]
},
  "bbox": [],
  "geometry": {"coordinates":[-106.4333,36.5167],"type":"Point"}
}