{
  "id": 1008137,
  "type": "Feature",
  "properties": {
    "tgn:hierarchy":[
        "tgn:1008137",
        "tgn:1000821",
        "tgn:7001242",
        "tgn:1000180",
        "tgn:7029392"
    ],
    "tgn:id":1008137,
    "tgn:name":"Metundo, Ilha",
    "tgn:placetype":[
        "aat:300008791"
    ]
},
  "bbox": [],
  "geometry": {"coordinates":[40.6667,-11.15],"type":"Point"}
}