{
  "id": 7526874,
  "type": "Feature",
  "properties": {
    "tgn:hierarchy":[
        "tgn:7526874",
        "tgn:7001242",
        "tgn:7016833",
        "tgn:1001091",
        "tgn:7029392"
    ],
    "tgn:id":7526874,
    "tgn:name":"K\u016bbr\u012b al Ab\u0101j\u012byah",
    "tgn:placetype":[
        "aat:300007836"
    ]
},
  "bbox": [],
  "geometry": {"coordinates":[31.263369,30.026401],"type":"Point"}
}