{
  "id": 7406342,
  "type": "Feature",
  "properties": {
    "tgn:hierarchy":[
        "tgn:7406342",
        "tgn:7005585",
        "tgn:1000001",
        "tgn:7005560",
        "tgn:7029392"
    ],
    "tgn:id":7406342,
    "tgn:name":"Tehuixtepec",
    "tgn:placetype":[
        "aat:300008347"
    ]
},
  "bbox": [],
  "geometry": {"coordinates":[-98.466667,16.933333],"type":"Point"}
}