{
  "id": 7294092,
  "type": "Feature",
  "properties": {
    "tgn:hierarchy":[
        "tgn:7294092",
        "tgn:7002803",
        "tgn:1001647",
        "tgn:1000003",
        "tgn:1000095",
        "tgn:7029392"
    ],
    "tgn:id":7294092,
    "tgn:name":"Vandelaras de Abajo",
    "tgn:placetype":[
        "aat:300008347"
    ]
},
  "bbox": [],
  "geometry": {"coordinates":[-2.216667,38.95],"type":"Point"}
}