{
  "id": 7362944,
  "type": "Feature",
  "properties": {
    "tgn:hierarchy":[
        "tgn:7362944",
        "tgn:7005581",
        "tgn:1000001",
        "tgn:7005560",
        "tgn:7029392"
    ],
    "tgn:id":7362944,
    "tgn:name":"El Anc\u00f3n",
    "tgn:placetype":[
        "aat:300008347"
    ]
},
  "bbox": [],
  "geometry": {"coordinates":[-104.533333,29.566667],"type":"Point"}
}