{
  "id": 2486102,
  "type": "Feature",
  "properties": {
    "tgn:hierarchy":[
        "tgn:2486102",
        "tgn:1000001",
        "tgn:7012149",
        "tgn:2000811",
        "tgn:7007255",
        "tgn:7029392"
    ],
    "tgn:id":2486102,
    "tgn:name":"Leadmine Branch",
    "tgn:placetype":[
        "aat:300008699"
    ]
},
  "bbox": [],
  "geometry": {"coordinates":[-83.2833,37.1833],"type":"Point"}
}