{
  "id": 7033473,
  "type": "Feature",
  "properties": {
    "tgn:hierarchy":[
        "tgn:7033473",
        "tgn:1000003",
        "tgn:7003236",
        "tgn:1000080",
        "tgn:7029392"
    ],
    "tgn:id":7033473,
    "tgn:name":"Branega, Torrente",
    "tgn:placetype":[
        "aat:300008699"
    ]
},
  "bbox": [],
  "geometry": {"coordinates":[8.783333,44.416667],"type":"Point"}
}