{
  "id": 7418367,
  "type": "Feature",
  "properties": {
    "tgn:hierarchy":[
        "tgn:7418367",
        "tgn:1000001",
        "tgn:1001937",
        "tgn:7005560",
        "tgn:7029392"
    ],
    "tgn:id":7418367,
    "tgn:name":"El Yunque, Roca",
    "tgn:placetype":[
        "aat:300011692"
    ]
},
  "bbox": [],
  "geometry": {"coordinates":[-86.752778,21.2675],"type":"Point"}
}