{
  "id": 7199833,
  "type": "Feature",
  "properties": {
    "tgn:hierarchy":[
        "tgn:7199833",
        "tgn:1000003",
        "tgn:7003677",
        "tgn:7000084",
        "tgn:7029392"
    ],
    "tgn:id":7199833,
    "tgn:name":"D\u00fcrsch-Bach",
    "tgn:placetype":[
        "aat:300008699"
    ]
},
  "bbox": [],
  "geometry": {"coordinates":[7.25,50.983333],"type":"Point"}
}