<<<<<<< HEAD
{
  "id": 2252123,
  "type": "Feature",
  "properties": {
    "tgn:hierarchy":[
        "tgn:2252123",
        "tgn:7030516",
        "tgn:7006450",
        "tgn:1000001",
        "tgn:7012149",
        "tgn:7029392"
    ],
    "tgn:id":2252123,
    "tgn:name":"Cone Hill",
    "tgn:placetype":[
        "aat:300008798"
    ]
},
  "bbox": [],
  "geometry": {"coordinates":[-170.3667,57.4],"type":"Point"}
}
=======
{"geometry":{"type":"Point","coordinates":[-170.366700,57.400000]},"type":"Feature","properties":{"hierarchy":["tgn:2252123","tgn:7030516","tgn:7006450","tgn:1000001","tgn:7012149","tgn:7029392"],"placetype":["aat:300008798"],"id":2252123,"name:xx":"Cone Hill"}}
>>>>>>> 03f74aca74312dbeaf24d7e61306dd6a786dc3d0
