<<<<<<< HEAD
{
  "id": 7026543,
  "type": "Feature",
  "properties": {
    "tgn:hierarchy":[
        "tgn:7026543",
        "tgn:7002445",
        "tgn:1000003",
        "tgn:7008132",
        "tgn:7008591",
        "tgn:7029392"
    ],
    "tgn:id":7026543,
    "tgn:name:en":"Ampney Crucis",
    "tgn:placetype":[
        "aat:300008347",
        "aat:300008372"
    ]
},
  "bbox": [],
  "geometry": {"coordinates":[-1.9,51.716667],"type":"Point"}
}
=======
{"geometry":{"type":"Point","coordinates":[-1.900000,51.716667]},"type":"Feature","properties":{"hierarchy":["tgn:7026543","tgn:7002445","tgn:1000003","tgn:7008132","tgn:7008591","tgn:7029392"],"placetype":["aat:300008347","aat:300008372"],"name:en":"Ampney Crucis","id":7026543}}
>>>>>>> 03f74aca74312dbeaf24d7e61306dd6a786dc3d0
