{
  "id": 2709360,
  "type": "Feature",
  "properties": {
    "tgn:hierarchy":[
        "tgn:2709360",
        "tgn:1000001",
        "tgn:7012149",
        "tgn:7007157",
        "tgn:1002608",
        "tgn:7029392"
    ],
    "tgn:id":2709360,
    "tgn:name":"Table Rock",
    "tgn:placetype":[
        "aat:300008798"
    ]
},
  "bbox": [],
  "geometry": {"coordinates":[-118.3833,34.5167],"type":"Point"}
}