{
  "id": 7500727,
  "type": "Feature",
  "properties": {
    "tgn:hierarchy":[
        "tgn:7500727",
        "tgn:7487020",
        "tgn:1000004",
        "tgn:1000141",
        "tgn:7029392"
    ],
    "tgn:id":7500727,
    "tgn:name":"Cizijiao",
    "tgn:placetype":[
        "aat:300008347"
    ]
},
  "bbox": [],
  "geometry": {"coordinates":[120.693889,24.421944],"type":"Point"}
}