{
  "id": 1009721,
  "type": "Feature",
  "properties": {
    "tgn:hierarchy":[
        "tgn:1009721",
        "tgn:1000001",
        "tgn:7012149",
        "tgn:1002505",
        "tgn:7007920",
        "tgn:7029392"
    ],
    "tgn:id":1009721,
    "tgn:name":"Whidbey Island",
    "tgn:placetype":[
        "aat:300008791"
    ]
},
  "bbox": [],
  "geometry": {"coordinates":[-122.6667,48.2833],"type":"Point"}
}