{
  "id": 7469387,
  "type": "Feature",
  "properties": {
    "tgn:hierarchy":[
        "tgn:7469387",
        "tgn:7469009",
        "tgn:1000004",
        "tgn:1000141",
        "tgn:7029392"
    ],
    "tgn:id":7469387,
    "tgn:name":"Zhonglan",
    "tgn:placetype":[
        "aat:300008347"
    ]
},
  "bbox": [],
  "geometry": {"coordinates":[118.383333,24.457778],"type":"Point"}
}