{
  "id": 2477058,
  "type": "Feature",
  "properties": {
    "tgn:hierarchy":[
        "tgn:2477058",
        "tgn:1000001",
        "tgn:7012149",
        "tgn:2001440",
        "tgn:7007566",
        "tgn:7029392"
    ],
    "tgn:id":2477058,
    "tgn:name":"Lynch Tank",
    "tgn:placetype":[
        "aat:300006191"
    ]
},
  "bbox": [],
  "geometry": {"coordinates":[-108.7167,31.4167],"type":"Point"}
}