{
  "id": 2073057,
  "type": "Feature",
  "properties": {
    "tgn:hierarchy":[
        "tgn:2073057",
        "tgn:1000001",
        "tgn:7012149",
        "tgn:1002944",
        "tgn:7007568",
        "tgn:7029392"
    ],
    "tgn:id":2073057,
    "tgn:name":"West Candor",
    "tgn:placetype":[
        "aat:300008347",
        "aat:300387210"
    ]
},
  "bbox": [],
  "geometry": {"coordinates":[-76.4167,42.2167],"type":"Point"}
}