<<<<<<< HEAD
{
  "id": 2154466,
  "type": "Feature",
  "properties": {
    "tgn:hierarchy":[
        "tgn:2154466",
        "tgn:1000001",
        "tgn:7012149",
        "tgn:2002371",
        "tgn:7007923",
        "tgn:7029392"
    ],
    "tgn:id":2154466,
    "tgn:name":"Bear Creek",
    "tgn:placetype":[
        "aat:300008706"
    ]
},
  "bbox": [],
  "geometry": {"coordinates":[-109.75,43.5333],"type":"Point"}
}
=======
{"geometry":{"type":"Point","coordinates":[-109.750000,43.533300]},"type":"Feature","properties":{"hierarchy":["tgn:2154466","tgn:1000001","tgn:7012149","tgn:2002371","tgn:7007923","tgn:7029392"],"placetype":["aat:300008706"],"id":2154466,"name:xx":"Bear Creek"}}
>>>>>>> 03f74aca74312dbeaf24d7e61306dd6a786dc3d0
