{
  "id": 2247773,
  "type": "Feature",
  "properties": {
    "tgn:hierarchy":[
        "tgn:2247773",
        "tgn:1000001",
        "tgn:7012149",
        "tgn:2001676",
        "tgn:7007707",
        "tgn:7029392"
    ],
    "tgn:id":2247773,
    "tgn:name":"Cohee Lake",
    "tgn:placetype":[
        "aat:300006191"
    ]
},
  "bbox": [],
  "geometry": {"coordinates":[-96.3833,35.3167],"type":"Point"}
}