{
  "id": 7230613,
  "type": "Feature",
  "properties": {
    "tgn:hierarchy":[
        "tgn:7230613",
        "tgn:7002735",
        "tgn:7017076",
        "tgn:1000003",
        "tgn:1000074",
        "tgn:7029392"
    ],
    "tgn:id":7230613,
    "tgn:name":"Kalteza\u00ed",
    "tgn:placetype":[
        "aat:300008347"
    ]
},
  "bbox": [],
  "geometry": {"coordinates":[22.316667,37.316667],"type":"Point"}
}