<<<<<<< HEAD
{
  "id": 7476614,
  "type": "Feature",
  "properties": {
    "tgn:hierarchy":[
        "tgn:7476614",
        "tgn:7487020",
        "tgn:1000004",
        "tgn:1000141",
        "tgn:7029392"
    ],
    "tgn:id":7476614,
    "tgn:name":"Zaizhuqi",
    "tgn:placetype":[
        "aat:300008347"
    ]
},
  "bbox": [],
  "geometry": {"coordinates":[120.919484,24.611411],"type":"Point"}
}
=======
{"geometry":{"type":"Point","coordinates":[120.919484,24.611411]},"type":"Feature","properties":{"hierarchy":["tgn:7476614","tgn:7487020","tgn:1000004","tgn:1000141","tgn:7029392"],"placetype":["aat:300008347"],"id":7476614,"name:xx":"Zaizhuqi"}}
>>>>>>> 03f74aca74312dbeaf24d7e61306dd6a786dc3d0
