{
  "id": 2631978,
  "type": "Feature",
  "properties": {
    "tgn:hierarchy":[
        "tgn:2631978",
        "tgn:1000001",
        "tgn:7012149",
        "tgn:1002899",
        "tgn:7007920",
        "tgn:7029392"
    ],
    "tgn:id":2631978,
    "tgn:name":"Rowan",
    "tgn:placetype":[
        "aat:300008347"
    ]
},
  "bbox": [],
  "geometry": {"coordinates":[-121.85,48.2667],"type":"Point"}
}