{
  "id": 2586789,
  "type": "Feature",
  "properties": {
    "tgn:hierarchy":[
        "tgn:2586789",
        "tgn:7006450",
        "tgn:1000001",
        "tgn:7012149",
        "tgn:7029392"
    ],
    "tgn:id":2586789,
    "tgn:name":"Placer River",
    "tgn:placetype":[
        "aat:300008707"
    ]
},
  "bbox": [],
  "geometry": {"coordinates":[-149.0333,60.6167],"type":"Point"}
}