{
  "id": 1029336,
  "type": "Feature",
  "properties": {
    "tgn:hierarchy":[
        "tgn:1029336",
        "tgn:1003611",
        "tgn:7002445",
        "tgn:1000003",
        "tgn:7029507",
        "tgn:7008591",
        "tgn:7029392"
    ],
    "tgn:id":1029336,
    "tgn:name":"Golcar",
    "tgn:placetype":[
        "aat:300008347",
        "aat:300008372"
    ]
},
  "bbox": [],
  "geometry": {"coordinates":[-1.85,53.633333],"type":"Point"}
}