{
  "id": 2479649,
  "type": "Feature",
  "properties": {
    "tgn:hierarchy":[
        "tgn:2479649",
        "tgn:1000001",
        "tgn:7012149",
        "tgn:2001371",
        "tgn:7007525",
        "tgn:7029392"
    ],
    "tgn:id":2479649,
    "tgn:name":"Lake Canyon",
    "tgn:placetype":[
        "aat:300008761"
    ]
},
  "bbox": [],
  "geometry": {"coordinates":[-100.7167,40.8167],"type":"Point"}
}