{
  "id": 7565259,
  "type": "Feature",
  "properties": {
    "tgn:hierarchy":[
        "tgn:7565259",
        "tgn:1000004",
        "tgn:7000198",
        "tgn:7016788",
        "tgn:7029392"
    ],
    "tgn:id":7565259,
    "tgn:name:en":"Khaw\u0101i",
    "tgn:placetype":[
        "aat:300008347"
    ]
},
  "bbox": [],
  "geometry": {"coordinates":[71.448713,27.827947],"type":"Point"}
}