{
  "id": 1110914,
  "type": "Feature",
  "properties": {
    "tgn:hierarchy":[
        "tgn:1110914",
        "tgn:7009084",
        "tgn:7004154",
        "tgn:1000003",
        "tgn:1000080",
        "tgn:7029392"
    ],
    "tgn:id":1110914,
    "tgn:name":"Fucino, Conca del",
    "tgn:placetype":[
        "aat:300008680",
        "aat:300008805"
    ]
},
  "bbox": [],
  "geometry": {"coordinates":[13.516667,42.016667],"type":"Point"}
}