{
  "id": 7477717,
  "type": "Feature",
  "properties": {
    "tgn:hierarchy":[
        "tgn:7477717",
        "tgn:1000004",
        "tgn:7004300",
        "tgn:1000141",
        "tgn:7029392"
    ],
    "tgn:id":7477717,
    "tgn:name":"Changti",
    "tgn:placetype":[
        "aat:300008791"
    ]
},
  "bbox": [],
  "geometry": {"coordinates":[119.641874,23.622177],"type":"Point"}
}