{
  "id": 7589683,
  "type": "Feature",
  "properties": {
    "tgn:hierarchy":[
        "tgn:7589683",
        "tgn:1000004",
        "tgn:7000198",
        "tgn:7000799",
        "tgn:7029392"
    ],
    "tgn:id":7589683,
    "tgn:name:en":"Chab",
    "tgn:placetype":[
        "aat:300008347"
    ]
},
  "bbox": [],
  "geometry": {"coordinates":[74.984391,32.754607],"type":"Point"}
}