{
  "id": 7526540,
  "type": "Feature",
  "properties": {
    "tgn:hierarchy":[
        "tgn:7526540",
        "tgn:7001242",
        "tgn:1001075",
        "tgn:7016833",
        "tgn:7029392"
    ],
    "tgn:id":7526540,
    "tgn:name:en":"Wak\u0101'ilah, Jaz\u012brat al",
    "tgn:placetype":[
        "aat:300008791"
    ]
},
  "bbox": [],
  "geometry": {"coordinates":[30.625278,31.143333],"type":"Point"}
}