<<<<<<< HEAD
{
  "id": 2761168,
  "type": "Feature",
  "properties": {
    "tgn:hierarchy":[
        "tgn:2761168",
        "tgn:1000001",
        "tgn:7012149",
        "tgn:1003017",
        "tgn:7007710",
        "tgn:7029392"
    ],
    "tgn:id":2761168,
    "tgn:name":"West Latrobe",
    "tgn:placetype":[
        "aat:300008347"
    ]
},
  "bbox": [],
  "geometry": {"coordinates":[-79.3833,40.3],"type":"Point"}
}
=======
{"geometry":{"type":"Point","coordinates":[-79.383300,40.300000]},"type":"Feature","properties":{"hierarchy":["tgn:2761168","tgn:1000001","tgn:7012149","tgn:1003017","tgn:7007710","tgn:7029392"],"placetype":["aat:300008347"],"id":2761168,"name:xx":"West Latrobe"}}
>>>>>>> 03f74aca74312dbeaf24d7e61306dd6a786dc3d0
