{
  "id": 7425178,
  "type": "Feature",
  "properties": {
    "tgn:hierarchy":[
        "tgn:7425178",
        "tgn:1000001",
        "tgn:1001960",
        "tgn:7005560",
        "tgn:7029392"
    ],
    "tgn:id":7425178,
    "tgn:name":"San Quintin",
    "tgn:placetype":[
        "aat:300008347"
    ]
},
  "bbox": [],
  "geometry": {"coordinates":[-108.783333,30.15],"type":"Point"}
}