{
  "id": 2106597,
  "type": "Feature",
  "properties": {
    "tgn:hierarchy":[
        "tgn:2106597",
        "tgn:1000001",
        "tgn:7012149",
        "tgn:1003031",
        "tgn:7007826",
        "tgn:7029392"
    ],
    "tgn:id":2106597,
    "tgn:name":"Paradise",
    "tgn:placetype":[
        "aat:300008347"
    ]
},
  "bbox": [],
  "geometry": {"coordinates":[-97.6833,33.15],"type":"Point"}
}