{
  "id": 1063301,
  "type": "Feature",
  "properties": {
    "tgn:hierarchy":[
        "tgn:1063301",
        "tgn:1000003",
        "tgn:7003777",
        "tgn:1000097",
        "tgn:7029392"
    ],
    "tgn:id":1063301,
    "tgn:name":"Liding\u00f6",
    "tgn:placetype":[
        "aat:300008347"
    ]
},
  "bbox": [],
  "geometry": {"coordinates":[18.1667,59.3667],"type":"Point"}
}