<<<<<<< HEAD
{
  "id": 2766773,
  "type": "Feature",
  "properties": {
    "tgn:hierarchy":[
        "tgn:2766773",
        "tgn:1000001",
        "tgn:7012149",
        "tgn:1002948",
        "tgn:7007826",
        "tgn:7029392"
    ],
    "tgn:id":2766773,
    "tgn:name":"White Oak Springs",
    "tgn:placetype":[
        "aat:300008347"
    ]
},
  "bbox": [],
  "geometry": {"coordinates":[-95.0667,33.15],"type":"Point"}
}
=======
{"geometry":{"type":"Point","coordinates":[-95.066700,33.150000]},"type":"Feature","properties":{"hierarchy":["tgn:2766773","tgn:1000001","tgn:7012149","tgn:1002948","tgn:7007826","tgn:7029392"],"placetype":["aat:300008347"],"id":2766773,"name:xx":"White Oak Springs"}}
>>>>>>> 03f74aca74312dbeaf24d7e61306dd6a786dc3d0
