{
  "id": 2766773,
  "type": "Feature",
  "properties": {
    "tgn:hierarchy":[
        "tgn:2766773",
        "tgn:1000001",
        "tgn:7012149",
        "tgn:1002948",
        "tgn:7007826",
        "tgn:7029392"
    ],
    "tgn:id":2766773,
    "tgn:name":"White Oak Springs",
    "tgn:placetype":[
        "aat:300008347"
    ]
},
  "bbox": [],
  "geometry": {"coordinates":[-95.0667,33.15],"type":"Point"}
}