{
  "id": 2719769,
  "type": "Feature",
  "properties": {
    "tgn:hierarchy":[
        "tgn:2719769",
        "tgn:7006450",
        "tgn:1000001",
        "tgn:7012149",
        "tgn:2124005",
        "tgn:7029392"
    ],
    "tgn:id":2719769,
    "tgn:name":"Three River Mountain",
    "tgn:placetype":[
        "aat:300008798"
    ]
},
  "bbox": [],
  "geometry": {"coordinates":[-151.6333,68.0333],"type":"Point"}
}