{
  "id": 2745148,
  "type": "Feature",
  "properties": {
    "tgn:hierarchy":[
        "tgn:2745148",
        "tgn:7006450",
        "tgn:1000001",
        "tgn:7012149",
        "tgn:7019760",
        "tgn:7029392"
    ],
    "tgn:id":2745148,
    "tgn:name":"Village Point",
    "tgn:placetype":[
        "aat:300008850"
    ]
},
  "bbox": [],
  "geometry": {"coordinates":[-134.5667,57.3333],"type":"Point"}
}