{
  "id": 2344638,
  "type": "Feature",
  "properties": {
    "tgn:hierarchy":[
        "tgn:2344638",
        "tgn:1000001",
        "tgn:7012149",
        "tgn:2001972",
        "tgn:7007826",
        "tgn:7029392"
    ],
    "tgn:id":2344638,
    "tgn:name":"Garcia Lake",
    "tgn:placetype":[
        "aat:300008680"
    ]
},
  "bbox": [],
  "geometry": {"coordinates":[-102.9167,34.85],"type":"Point"}
}