<<<<<<< HEAD
{
  "id": 2151220,
  "type": "Feature",
  "properties": {
    "tgn:hierarchy":[
        "tgn:2151220",
        "tgn:1002300",
        "tgn:1000001",
        "tgn:7012149",
        "tgn:7007564",
        "tgn:7029392"
    ],
    "tgn:id":2151220,
    "tgn:name":"Bateman Brook",
    "tgn:placetype":[
        "aat:300008699"
    ]
},
  "bbox": [],
  "geometry": {"coordinates":[-71.2333,44.9667],"type":"Point"}
}
=======
{"geometry":{"type":"Point","coordinates":[-71.233300,44.966700]},"type":"Feature","properties":{"hierarchy":["tgn:2151220","tgn:1002300","tgn:1000001","tgn:7012149","tgn:7007564","tgn:7029392"],"placetype":["aat:300008699"],"id":2151220,"name:xx":"Bateman Brook"}}
>>>>>>> 03f74aca74312dbeaf24d7e61306dd6a786dc3d0
