{
  "id": 2706188,
  "type": "Feature",
  "properties": {
    "tgn:hierarchy":[
        "tgn:2706188",
        "tgn:1000001",
        "tgn:7012149",
        "tgn:7007157",
        "tgn:2000190",
        "tgn:7029392"
    ],
    "tgn:id":2706188,
    "tgn:name":"Swamp Creek",
    "tgn:placetype":[
        "aat:300008706"
    ]
},
  "bbox": [],
  "geometry": {"coordinates":[-121.4833,40.2833],"type":"Point"}
}