{
  "id": 2064415,
  "type": "Feature",
  "properties": {
    "tgn:hierarchy":[
        "tgn:2064415",
        "tgn:1000001",
        "tgn:7014090",
        "tgn:7012149",
        "tgn:7007565",
        "tgn:7029392"
    ],
    "tgn:id":2064415,
    "tgn:name":"Claytons Corner",
    "tgn:placetype":[
        "aat:300008347"
    ]
},
  "bbox": [],
  "geometry": {"coordinates":[-74.2833,40.3167],"type":"Point"}
}