{
  "id": 2161586,
  "type": "Feature",
  "properties": {
    "tgn:hierarchy":[
        "tgn:2161586",
        "tgn:1000001",
        "tgn:7012149",
        "tgn:7007157",
        "tgn:2000187",
        "tgn:7029392"
    ],
    "tgn:id":2161586,
    "tgn:name":"Bellas Creek",
    "tgn:placetype":[
        "aat:300008706"
    ]
},
  "bbox": [],
  "geometry": {"coordinates":[-120.9833,40.0833],"type":"Point"}
}