<<<<<<< HEAD
{
  "id": 7479712,
  "type": "Feature",
  "properties": {
    "tgn:hierarchy":[
        "tgn:7479712",
        "tgn:1000004",
        "tgn:7001013",
        "tgn:1000141",
        "tgn:7029392"
    ],
    "tgn:id":7479712,
    "tgn:name":"Qiwen Guoxiao",
    "tgn:placetype":[
        "aat:300006495"
    ]
},
  "bbox": [],
  "geometry": {"coordinates":[121.116667,24.9775],"type":"Point"}
}
=======
{"geometry":{"type":"Point","coordinates":[121.116667,24.977500]},"type":"Feature","properties":{"hierarchy":["tgn:7479712","tgn:1000004","tgn:7001013","tgn:1000141","tgn:7029392"],"placetype":["aat:300006495"],"id":7479712,"name:xx":"Qiwen Guoxiao"}}
>>>>>>> 03f74aca74312dbeaf24d7e61306dd6a786dc3d0
