{
  "id": 2433138,
  "type": "Feature",
  "properties": {
    "tgn:hierarchy":[
        "tgn:2433138",
        "tgn:7006450",
        "tgn:1000001",
        "tgn:2124012",
        "tgn:7012149",
        "tgn:7029392"
    ],
    "tgn:id":2433138,
    "tgn:name":"Kekur Point",
    "tgn:placetype":[
        "aat:300008850"
    ]
},
  "bbox": [],
  "geometry": {"coordinates":[-152.7833,57.85],"type":"Point"}
}