{
  "id": 7503574,
  "type": "Feature",
  "properties": {
    "tgn:hierarchy":[
        "tgn:7503574",
        "tgn:7001004",
        "tgn:1000004",
        "tgn:1000141",
        "tgn:7029392"
    ],
    "tgn:id":7503574,
    "tgn:name":"Nanliao",
    "tgn:placetype":[
        "aat:300008347"
    ]
},
  "bbox": [],
  "geometry": {"coordinates":[120.485833,22.870278],"type":"Point"}
}