{
  "id": 7322121,
  "type": "Feature",
  "properties": {
    "tgn:hierarchy":[
        "tgn:7322121",
        "tgn:7002464",
        "tgn:1000049",
        "tgn:1000002",
        "tgn:7029392"
    ],
    "tgn:id":7322121,
    "tgn:name":"Calajualla, R\u00edo",
    "tgn:placetype":[
        "aat:300008699"
    ]
},
  "bbox": [],
  "geometry": {"coordinates":[-68.916667,-19.683333],"type":"Point"}
}