{
  "id": 2387340,
  "type": "Feature",
  "properties": {
    "tgn:hierarchy":[
        "tgn:2387340",
        "tgn:1000001",
        "tgn:2000313",
        "tgn:7012149",
        "tgn:7007248",
        "tgn:7029392"
    ],
    "tgn:id":2387340,
    "tgn:name":"Hesterlee Creek",
    "tgn:placetype":[
        "aat:300008706"
    ]
},
  "bbox": [],
  "geometry": {"coordinates":[-84.9833,33.6167],"type":"Point"}
}