<<<<<<< HEAD
{
  "id": 2406552,
  "type": "Feature",
  "properties": {
    "tgn:hierarchy":[
        "tgn:2406552",
        "tgn:1000001",
        "tgn:7012149",
        "tgn:1002402",
        "tgn:7007523",
        "tgn:7029392"
    ],
    "tgn:id":2406552,
    "tgn:name":"Hunke Creek",
    "tgn:placetype":[
        "aat:300008706"
    ]
},
  "bbox": [],
  "geometry": {"coordinates":[-91.5833,38.4333],"type":"Point"}
}
=======
{"geometry":{"type":"Point","coordinates":[-91.583300,38.433300]},"type":"Feature","properties":{"hierarchy":["tgn:2406552","tgn:1000001","tgn:7012149","tgn:1002402","tgn:7007523","tgn:7029392"],"placetype":["aat:300008706"],"id":2406552,"name:xx":"Hunke Creek"}}
>>>>>>> 03f74aca74312dbeaf24d7e61306dd6a786dc3d0
