{
  "id": 2136406,
  "type": "Feature",
  "properties": {
    "tgn:hierarchy":[
        "tgn:2136406",
        "tgn:1000001",
        "tgn:7012149",
        "tgn:2000974",
        "tgn:7007520",
        "tgn:7029392"
    ],
    "tgn:id":2136406,
    "tgn:name":"Arcadia Lake",
    "tgn:placetype":[
        "aat:300008680"
    ]
},
  "bbox": [],
  "geometry": {"coordinates":[-86.2333,44.4833],"type":"Point"}
}