{
  "id": 7284374,
  "type": "Feature",
  "properties": {
    "tgn:hierarchy":[
        "tgn:7284374",
        "tgn:1001695",
        "tgn:1000049",
        "tgn:1000002",
        "tgn:7029392"
    ],
    "tgn:id":7284374,
    "tgn:name":"Punta del Diablo, Cerro",
    "tgn:placetype":[
        "aat:300008795"
    ]
},
  "bbox": [],
  "geometry": {"coordinates":[-70.733333,-34.583333],"type":"Point"}
}