{
  "id": 1064800,
  "type": "Feature",
  "properties": {
    "tgn:hierarchy":[
        "tgn:1064800",
        "tgn:7002443",
        "tgn:5000552",
        "tgn:1000003",
        "tgn:7008591",
        "tgn:7029392"
    ],
    "tgn:id":1064800,
    "tgn:name":"Pumsaint",
    "tgn:placetype":[
        "aat:300008347"
    ]
},
  "bbox": [],
  "geometry": {"coordinates":[-3.95,52.033333],"type":"Point"}
}