<<<<<<< HEAD
{
  "id": 2763193,
  "type": "Feature",
  "properties": {
    "tgn:hierarchy":[
        "tgn:2763193",
        "tgn:1000001",
        "tgn:7012149",
        "tgn:2000907",
        "tgn:7007256",
        "tgn:7029392"
    ],
    "tgn:id":2763193,
    "tgn:name":"Westwood",
    "tgn:placetype":[
        "aat:300008347"
    ]
},
  "bbox": [],
  "geometry": {"coordinates":[-91.3167,32.1833],"type":"Point"}
}
=======
{"geometry":{"type":"Point","coordinates":[-91.316700,32.183300]},"type":"Feature","properties":{"hierarchy":["tgn:2763193","tgn:1000001","tgn:7012149","tgn:2000907","tgn:7007256","tgn:7029392"],"placetype":["aat:300008347"],"id":2763193,"name:xx":"Westwood"}}
>>>>>>> 03f74aca74312dbeaf24d7e61306dd6a786dc3d0
