<<<<<<< HEAD
{
  "id": 7473519,
  "type": "Feature",
  "properties": {
    "tgn:hierarchy":[
        "tgn:7473519",
        "tgn:1000004",
        "tgn:1000454",
        "tgn:1000141",
        "tgn:7029392"
    ],
    "tgn:id":7473519,
    "tgn:name":"Dingliaokeng",
    "tgn:placetype":[
        "aat:300008347"
    ]
},
  "bbox": [],
  "geometry": {"coordinates":[121.401448,24.934989],"type":"Point"}
}
=======
{"geometry":{"type":"Point","coordinates":[121.401448,24.934989]},"type":"Feature","properties":{"hierarchy":["tgn:7473519","tgn:1000004","tgn:1000454","tgn:1000141","tgn:7029392"],"placetype":["aat:300008347"],"id":7473519,"name:xx":"Dingliaokeng"}}
>>>>>>> 03f74aca74312dbeaf24d7e61306dd6a786dc3d0
