{
  "id": 7473519,
  "type": "Feature",
  "properties": {
    "tgn:hierarchy":[
        "tgn:7473519",
        "tgn:1000004",
        "tgn:1000454",
        "tgn:1000141",
        "tgn:7029392"
    ],
    "tgn:id":7473519,
    "tgn:name":"Dingliaokeng",
    "tgn:placetype":[
        "aat:300008347"
    ]
},
  "bbox": [],
  "geometry": {"coordinates":[121.401448,24.934989],"type":"Point"}
}