{
  "id": 7168618,
  "type": "Feature",
  "properties": {
    "tgn:hierarchy":[
        "tgn:7168618",
        "tgn:1000003",
        "tgn:7003676",
        "tgn:7000084",
        "tgn:7029392"
    ],
    "tgn:id":7168618,
    "tgn:name":"Heiligen-Berg",
    "tgn:placetype":[
        "aat:300008777"
    ]
},
  "bbox": [],
  "geometry": {"coordinates":[9.783333,51.633333],"type":"Point"}
}