{
  "id": 2738369,
  "type": "Feature",
  "properties": {
    "tgn:hierarchy":[
        "tgn:2738369",
        "tgn:1000001",
        "tgn:7012149",
        "tgn:1002708",
        "tgn:7007568",
        "tgn:7029392"
    ],
    "tgn:id":2738369,
    "tgn:name":"Uncle Daniels Point",
    "tgn:placetype":[
        "aat:300008850"
    ]
},
  "bbox": [],
  "geometry": {"coordinates":[-73.7333,40.6167],"type":"Point"}
}