{
  "id": 1127246,
  "type": "Feature",
  "properties": {
    "tgn:hierarchy":[
        "tgn:1127246",
        "tgn:1000003",
        "tgn:7003678",
        "tgn:7000084",
        "tgn:7029392"
    ],
    "tgn:id":1127246,
    "tgn:name":"Modau",
    "tgn:placetype":[
        "aat:300008707",
        "aat:300008699"
    ]
},
  "bbox": [],
  "geometry": {"coordinates":[8.46,49.813611],"type":"Point"}
}