{
  "id": 1123320,
  "type": "Feature",
  "properties": {
    "tgn:hierarchy":[
        "tgn:1123320",
        "tgn:1000004",
        "tgn:7016744",
        "tgn:1000135",
        "tgn:7029392"
    ],
    "tgn:id":1123320,
    "tgn:name":"Davao",
    "tgn:placetype":[
        "aat:300008707"
    ]
},
  "bbox": [],
  "geometry": {"coordinates":[125.6333,7.0833],"type":"Point"}
}