{
  "id": 7217996,
  "type": "Feature",
  "properties": {
    "tgn:hierarchy":[
        "tgn:7217996",
        "tgn:7011330",
        "tgn:7002674",
        "tgn:1000003",
        "tgn:1000074",
        "tgn:7029392"
    ],
    "tgn:id":7217996,
    "tgn:name":"Yenn\u00e1dhion",
    "tgn:placetype":[
        "aat:300008347"
    ]
},
  "bbox": [],
  "geometry": {"coordinates":[27.933333,36.016667],"type":"Point"}
}