{
  "id": 2595676,
  "type": "Feature",
  "properties": {
    "tgn:hierarchy":[
        "tgn:2595676",
        "tgn:1000001",
        "tgn:7012149",
        "tgn:1002818",
        "tgn:7007252",
        "tgn:7029392"
    ],
    "tgn:id":2595676,
    "tgn:name":"Potent Run",
    "tgn:placetype":[
        "aat:300008699"
    ]
},
  "bbox": [],
  "geometry": {"coordinates":[-85.05,40.2833],"type":"Point"}
}