{
  "id": 7502236,
  "type": "Feature",
  "properties": {
    "tgn:hierarchy":[
        "tgn:7502236",
        "tgn:7001004",
        "tgn:1000004",
        "tgn:1000141",
        "tgn:7029392"
    ],
    "tgn:id":7502236,
    "tgn:name":"Wulilin Qiao",
    "tgn:placetype":[
        "aat:300007836"
    ]
},
  "bbox": [],
  "geometry": {"coordinates":[120.295,22.768333],"type":"Point"}
}