{
  "id": 2616145,
  "type": "Feature",
  "properties": {
    "tgn:hierarchy":[
        "tgn:2616145",
        "tgn:1000001",
        "tgn:7012149",
        "tgn:7007252",
        "tgn:7029392"
    ],
    "tgn:id":2616145,
    "tgn:name":"Rhodes Creek",
    "tgn:placetype":[
        "aat:300008706"
    ]
},
  "bbox": [],
  "geometry": {"coordinates":[-86.5667,39.4833],"type":"Point"}
}