{
  "id": 2780001,
  "type": "Feature",
  "properties": {
    "tgn:hierarchy":[
        "tgn:2780001",
        "tgn:1000001",
        "tgn:7012149",
        "tgn:2000831",
        "tgn:7007255",
        "tgn:7029392"
    ],
    "tgn:id":2780001,
    "tgn:name":"Wolfpen Branch",
    "tgn:placetype":[
        "aat:300008699"
    ]
},
  "bbox": [],
  "geometry": {"coordinates":[-83.2833,38.05],"type":"Point"}
}