{
  "id": 7428165,
  "type": "Feature",
  "properties": {
    "tgn:hierarchy":[
        "tgn:7428165",
        "tgn:1000001",
        "tgn:7005594",
        "tgn:7005560",
        "tgn:7029392"
    ],
    "tgn:id":7428165,
    "tgn:name":"Las Flores",
    "tgn:placetype":[
        "aat:300008347"
    ]
},
  "bbox": [],
  "geometry": {"coordinates":[-101.05,23.916667],"type":"Point"}
}