{
  "id": 7112470,
  "type": "Feature",
  "properties": {
    "tgn:hierarchy":[
        "tgn:7112470",
        "tgn:1000003",
        "tgn:7003689",
        "tgn:7000084",
        "tgn:7029392"
    ],
    "tgn:id":7112470,
    "tgn:name":"Rohne-Berg",
    "tgn:placetype":[
        "aat:300008777"
    ]
},
  "bbox": [],
  "geometry": {"coordinates":[10.35,51.483333],"type":"Point"}
}