{
  "id": 7404428,
  "type": "Feature",
  "properties": {
    "tgn:hierarchy":[
        "tgn:7404428",
        "tgn:7005585",
        "tgn:1000001",
        "tgn:7005560",
        "tgn:7029392"
    ],
    "tgn:id":7404428,
    "tgn:name":"Rinc\u00f3n de las Palmas, Filo",
    "tgn:placetype":[
        "aat:300266640"
    ]
},
  "bbox": [],
  "geometry": {"coordinates":[-100.833333,18.033333],"type":"Point"}
}