{
  "id": 7481353,
  "type": "Feature",
  "properties": {
    "tgn:hierarchy":[
        "tgn:7481353",
        "tgn:1000004",
        "tgn:7492971",
        "tgn:1000141",
        "tgn:7029392"
    ],
    "tgn:id":7481353,
    "tgn:name":"Fengtian Guoxiao",
    "tgn:placetype":[
        "aat:300006495"
    ]
},
  "bbox": [],
  "geometry": {"coordinates":[120.5402,22.6271],"type":"Point"}
}