{
  "id": 7043751,
  "type": "Feature",
  "properties": {
    "tgn:hierarchy":[
        "tgn:7043751",
        "tgn:7009084",
        "tgn:7004154",
        "tgn:1000003",
        "tgn:1000080",
        "tgn:7029392"
    ],
    "tgn:id":7043751,
    "tgn:name":"Gagliano Aterno",
    "tgn:placetype":[
        "aat:300008347"
    ]
},
  "bbox": [],
  "geometry": {"coordinates":[13.683333,42.116667],"type":"Point"}
}