{
  "id": 7259150,
  "type": "Feature",
  "properties": {
    "tgn:hierarchy":[
        "tgn:7259150",
        "tgn:7003457",
        "tgn:1000003",
        "tgn:1000063",
        "tgn:7018236",
        "tgn:7029392"
    ],
    "tgn:id":7259150,
    "tgn:name":"Volpenswege",
    "tgn:placetype":[
        "aat:300008347"
    ]
},
  "bbox": [],
  "geometry": {"coordinates":[3.683333,51.15],"type":"Point"}
}