{
  "id": 7376576,
  "type": "Feature",
  "properties": {
    "tgn:hierarchy":[
        "tgn:7376576",
        "tgn:1000001",
        "tgn:7005597",
        "tgn:7005560",
        "tgn:7029392"
    ],
    "tgn:id":7376576,
    "tgn:name":"La Tinaja",
    "tgn:placetype":[
        "aat:300266554",
        "aat:300008699"
    ]
},
  "bbox": [],
  "geometry": {"coordinates":[-99.216667,23.416667],"type":"Point"}
}