<<<<<<< HEAD
{
  "id": 2403070,
  "type": "Feature",
  "properties": {
    "tgn:hierarchy":[
        "tgn:2403070",
        "tgn:1000001",
        "tgn:7012149",
        "tgn:2000226",
        "tgn:7007158",
        "tgn:7029392"
    ],
    "tgn:id":2403070,
    "tgn:name":"Hourglass Lake",
    "tgn:placetype":[
        "aat:300008680"
    ]
},
  "bbox": [],
  "geometry": {"coordinates":[-105.7167,40.3333],"type":"Point"}
}
=======
{"geometry":{"type":"Point","coordinates":[-105.716700,40.333300]},"type":"Feature","properties":{"hierarchy":["tgn:2403070","tgn:1000001","tgn:7012149","tgn:2000226","tgn:7007158","tgn:7029392"],"placetype":["aat:300008680"],"id":2403070,"name:xx":"Hourglass Lake"}}
>>>>>>> 03f74aca74312dbeaf24d7e61306dd6a786dc3d0
