{
  "id": 2403070,
  "type": "Feature",
  "properties": {
    "tgn:hierarchy":[
        "tgn:2403070",
        "tgn:1000001",
        "tgn:7012149",
        "tgn:2000226",
        "tgn:7007158",
        "tgn:7029392"
    ],
    "tgn:id":2403070,
    "tgn:name":"Hourglass Lake",
    "tgn:placetype":[
        "aat:300008680"
    ]
},
  "bbox": [],
  "geometry": {"coordinates":[-105.7167,40.3333],"type":"Point"}
}