<<<<<<< HEAD
{
  "id": 2158541,
  "type": "Feature",
  "properties": {
    "tgn:hierarchy":[
        "tgn:2158541",
        "tgn:1000001",
        "tgn:7012149",
        "tgn:2000519",
        "tgn:7007251",
        "tgn:7029392"
    ],
    "tgn:id":2158541,
    "tgn:name":"Beaverdam Lake",
    "tgn:placetype":[
        "aat:300008680"
    ]
},
  "bbox": [],
  "geometry": {"coordinates":[-88.4833,37.0667],"type":"Point"}
}
=======
{"geometry":{"type":"Point","coordinates":[-88.483300,37.066700]},"type":"Feature","properties":{"hierarchy":["tgn:2158541","tgn:1000001","tgn:7012149","tgn:2000519","tgn:7007251","tgn:7029392"],"placetype":["aat:300008680"],"id":2158541,"name:xx":"Beaverdam Lake"}}
>>>>>>> 03f74aca74312dbeaf24d7e61306dd6a786dc3d0
