{
  "id": 2569031,
  "type": "Feature",
  "properties": {
    "tgn:hierarchy":[
        "tgn:2569031",
        "tgn:1000001",
        "tgn:7012149",
        "tgn:1002935",
        "tgn:7007919",
        "tgn:7029392"
    ],
    "tgn:id":2569031,
    "tgn:name":"Parker Run",
    "tgn:placetype":[
        "aat:300008699"
    ]
},
  "bbox": [],
  "geometry": {"coordinates":[-77.15,36.85],"type":"Point"}
}