{
  "id": 7307465,
  "type": "Feature",
  "properties": {
    "tgn:hierarchy":[
        "tgn:7307465",
        "tgn:7002803",
        "tgn:1001647",
        "tgn:1000003",
        "tgn:1000095",
        "tgn:7029392"
    ],
    "tgn:id":7307465,
    "tgn:name":"Estaci\u00f3n de Los Hitos",
    "tgn:placetype":[
        "aat:300007783"
    ]
},
  "bbox": [],
  "geometry": {"coordinates":[-1.683333,38.716667],"type":"Point"}
}