<<<<<<< HEAD
{
  "id": 7028991,
  "type": "Feature",
  "properties": {
    "tgn:hierarchy":[
        "tgn:7028991",
        "tgn:7002445",
        "tgn:1000003",
        "tgn:7019064",
        "tgn:7008591",
        "tgn:7029392"
    ],
    "tgn:id":7028991,
    "tgn:name":"Askham Bryan",
    "tgn:placetype":[
        "aat:300008347",
        "aat:300008372"
    ]
},
  "bbox": [],
  "geometry": {"coordinates":[-1.152,53.918],"type":"Point"}
}
=======
{"geometry":{"type":"Point","coordinates":[-1.152000,53.918000]},"type":"Feature","properties":{"hierarchy":["tgn:7028991","tgn:7002445","tgn:1000003","tgn:7019064","tgn:7008591","tgn:7029392"],"placetype":["aat:300008347","aat:300008372"],"id":7028991,"name:xx":"Askham Bryan"}}
>>>>>>> 03f74aca74312dbeaf24d7e61306dd6a786dc3d0
