{
  "id": 2693710,
  "type": "Feature",
  "properties": {
    "tgn:hierarchy":[
        "tgn:2693710",
        "tgn:2002143",
        "tgn:1000001",
        "tgn:7012149",
        "tgn:7007919",
        "tgn:7029392"
    ],
    "tgn:id":2693710,
    "tgn:name":"Stephenson Cave Number 3",
    "tgn:placetype":[
        "aat:300008746"
    ]
},
  "bbox": [],
  "geometry": {"coordinates":[-79.6167,38.1833],"type":"Point"}
}