{
  "id": 7570900,
  "type": "Feature",
  "properties": {
    "tgn:hierarchy":[
        "tgn:7570900",
        "tgn:1000004",
        "tgn:7000198",
        "tgn:1001894",
        "tgn:7029392"
    ],
    "tgn:id":7570900,
    "tgn:name:en":"Kali\u0101npur",
    "tgn:placetype":[
        "aat:300008347"
    ]
},
  "bbox": [],
  "geometry": {"coordinates":[74.638772,22.871054],"type":"Point"}
}