<<<<<<< HEAD
{
  "id": 7179094,
  "type": "Feature",
  "properties": {
    "tgn:hierarchy":[
        "tgn:7179094",
        "tgn:1000003",
        "tgn:7003677",
        "tgn:7000084",
        "tgn:7029392"
    ],
    "tgn:id":7179094,
    "tgn:name":"Hammerbruch",
    "tgn:placetype":[
        "aat:300387200"
    ]
},
  "bbox": [],
  "geometry": {"coordinates":[6.4,51.616667],"type":"Point"}
}
=======
{"geometry":{"type":"Point","coordinates":[6.400000,51.616667]},"type":"Feature","properties":{"hierarchy":["tgn:7179094","tgn:1000003","tgn:7003677","tgn:7000084","tgn:7029392"],"placetype":["aat:300387200"],"id":7179094,"name:xx":"Hammerbruch"}}
>>>>>>> 03f74aca74312dbeaf24d7e61306dd6a786dc3d0
