{
  "id": 1087634,
  "type": "Feature",
  "properties": {
    "tgn:hierarchy":[
        "tgn:1087634",
        "tgn:7001242",
        "tgn:1000149",
        "tgn:1000954",
        "tgn:7029392"
    ],
    "tgn:id":1087634,
    "tgn:name":"Benza",
    "tgn:placetype":[
        "aat:300008347"
    ]
},
  "bbox": [],
  "geometry": {"coordinates":[12.95,-6.2667],"type":"Point"}
}