{
  "id": 2649471,
  "type": "Feature",
  "properties": {
    "tgn:hierarchy":[
        "tgn:2649471",
        "tgn:1000001",
        "tgn:7012149",
        "tgn:7007157",
        "tgn:7014516",
        "tgn:7029392"
    ],
    "tgn:id":2649471,
    "tgn:name":"Scotts Ridge",
    "tgn:placetype":[
        "aat:300266640"
    ]
},
  "bbox": [],
  "geometry": {"coordinates":[-122.9333,38.55],"type":"Point"}
}