{
  "id": 2712129,
  "type": "Feature",
  "properties": {
    "tgn:hierarchy":[
        "tgn:2712129",
        "tgn:1002176",
        "tgn:1000001",
        "tgn:7012149",
        "tgn:7007828",
        "tgn:7029392"
    ],
    "tgn:id":2712129,
    "tgn:name":"Tate Mountain",
    "tgn:placetype":[
        "aat:300008798"
    ]
},
  "bbox": [],
  "geometry": {"coordinates":[-73.2333,43.15],"type":"Point"}
}