{
  "id": 1113051,
  "type": "Feature",
  "properties": {
    "tgn:hierarchy":[
        "tgn:1113051",
        "tgn:7017255",
        "tgn:1000001",
        "tgn:7004771",
        "tgn:7029392"
    ],
    "tgn:id":1113051,
    "tgn:name":"Grande Anse Bay",
    "tgn:placetype":[
        "aat:300132316"
    ]
},
  "bbox": [],
  "geometry": {"coordinates":[-61.75,12.0333],"type":"Point"}
}