{
  "id": 7454360,
  "type": "Feature",
  "properties": {
    "tgn:hierarchy":[
        "tgn:7454360",
        "tgn:7002448",
        "tgn:7008700",
        "tgn:1000003",
        "tgn:7008591",
        "tgn:7029392"
    ],
    "tgn:id":7454360,
    "tgn:name:en":"Corranny",
    "tgn:placetype":[
        "aat:300008347"
    ]
},
  "bbox": [],
  "geometry": {"coordinates":[-7.266667,54.25],"type":"Point"}
}