{
  "id": 2047319,
  "type": "Feature",
  "properties": {
    "tgn:hierarchy":[
        "tgn:2047319",
        "tgn:1002238",
        "tgn:1000001",
        "tgn:7012149",
        "tgn:7007516",
        "tgn:7029392"
    ],
    "tgn:id":2047319,
    "tgn:name":"Greenmount",
    "tgn:placetype":[
        "aat:300008347"
    ]
},
  "bbox": [],
  "geometry": {"coordinates":[-76.85,39.6167],"type":"Point"}
}