{
  "id": 7313799,
  "type": "Feature",
  "properties": {
    "tgn:hierarchy":[
        "tgn:7313799",
        "tgn:1001695",
        "tgn:1000049",
        "tgn:1000002",
        "tgn:7029392"
    ],
    "tgn:id":7313799,
    "tgn:name":"Llanos",
    "tgn:placetype":[
        "aat:300387200"
    ]
},
  "bbox": [],
  "geometry": {"coordinates":[-71.616667,-34.233333],"type":"Point"}
}