<<<<<<< HEAD
{
  "id": 2764304,
  "type": "Feature",
  "properties": {
    "tgn:hierarchy":[
        "tgn:2764304",
        "tgn:1000001",
        "tgn:7012149",
        "tgn:2000960",
        "tgn:7007520",
        "tgn:7029392"
    ],
    "tgn:id":2764304,
    "tgn:name":"Whelp Creek",
    "tgn:placetype":[
        "aat:300008706"
    ]
},
  "bbox": [],
  "geometry": {"coordinates":[-90.05,46.5667],"type":"Point"}
}
=======
{"geometry":{"type":"Point","coordinates":[-90.050000,46.566700]},"type":"Feature","properties":{"hierarchy":["tgn:2764304","tgn:1000001","tgn:7012149","tgn:2000960","tgn:7007520","tgn:7029392"],"placetype":["aat:300008706"],"id":2764304,"name:xx":"Whelp Creek"}}
>>>>>>> 03f74aca74312dbeaf24d7e61306dd6a786dc3d0
