{
  "id": 2764304,
  "type": "Feature",
  "properties": {
    "tgn:hierarchy":[
        "tgn:2764304",
        "tgn:1000001",
        "tgn:7012149",
        "tgn:2000960",
        "tgn:7007520",
        "tgn:7029392"
    ],
    "tgn:id":2764304,
    "tgn:name":"Whelp Creek",
    "tgn:placetype":[
        "aat:300008706"
    ]
},
  "bbox": [],
  "geometry": {"coordinates":[-90.05,46.5667],"type":"Point"}
}