{
  "id": 7440607,
  "type": "Feature",
  "properties": {
    "tgn:hierarchy":[
        "tgn:7440607",
        "tgn:7005583",
        "tgn:1000001",
        "tgn:7005560",
        "tgn:7029392"
    ],
    "tgn:id":7440607,
    "tgn:name":"San Manuel",
    "tgn:placetype":[
        "aat:300008347"
    ]
},
  "bbox": [],
  "geometry": {"coordinates":[-105.607222,24.042222],"type":"Point"}
}