{
  "id": 7111362,
  "type": "Feature",
  "properties": {
    "tgn:hierarchy":[
        "tgn:7111362",
        "tgn:7000096",
        "tgn:1000003",
        "tgn:7000084",
        "tgn:7029392"
    ],
    "tgn:id":7111362,
    "tgn:name":"Rohr-Teich",
    "tgn:placetype":[
        "aat:300008680"
    ]
},
  "bbox": [],
  "geometry": {"coordinates":[14.316667,51.666667],"type":"Point"}
}