{
  "id": 2156252,
  "type": "Feature",
  "properties": {
    "tgn:hierarchy":[
        "tgn:2156252",
        "tgn:1000001",
        "tgn:7012149",
        "tgn:2001451",
        "tgn:7007566",
        "tgn:7029392"
    ],
    "tgn:id":2156252,
    "tgn:name":"Bearhead Peak",
    "tgn:placetype":[
        "aat:300008798"
    ]
},
  "bbox": [],
  "geometry": {"coordinates":[-106.4667,35.7167],"type":"Point"}
}