<<<<<<< HEAD
{
  "id": 2156252,
  "type": "Feature",
  "properties": {
    "tgn:hierarchy":[
        "tgn:2156252",
        "tgn:1000001",
        "tgn:7012149",
        "tgn:2001451",
        "tgn:7007566",
        "tgn:7029392"
    ],
    "tgn:id":2156252,
    "tgn:name":"Bearhead Peak",
    "tgn:placetype":[
        "aat:300008798"
    ]
},
  "bbox": [],
  "geometry": {"coordinates":[-106.4667,35.7167],"type":"Point"}
}
=======
{"geometry":{"type":"Point","coordinates":[-106.466700,35.716700]},"type":"Feature","properties":{"hierarchy":["tgn:2156252","tgn:1000001","tgn:7012149","tgn:2001451","tgn:7007566","tgn:7029392"],"placetype":["aat:300008798"],"id":2156252,"name:xx":"Bearhead Peak"}}
>>>>>>> 03f74aca74312dbeaf24d7e61306dd6a786dc3d0
