{
  "id": 2345610,
  "type": "Feature",
  "properties": {
    "tgn:hierarchy":[
        "tgn:2345610",
        "tgn:1000001",
        "tgn:7012149",
        "tgn:2002125",
        "tgn:7007827",
        "tgn:7029392"
    ],
    "tgn:id":2345610,
    "tgn:name":"Garret Ridge",
    "tgn:placetype":[
        "aat:300266640"
    ]
},
  "bbox": [],
  "geometry": {"coordinates":[-111.3333,39.85],"type":"Point"}
}