{
  "id": 7580892,
  "type": "Feature",
  "properties": {
    "tgn:hierarchy":[
        "tgn:7580892",
        "tgn:1000004",
        "tgn:7000198",
        "tgn:7031786",
        "tgn:7029392"
    ],
    "tgn:id":7580892,
    "tgn:name:en":"Timli",
    "tgn:placetype":[
        "aat:300008347"
    ]
},
  "bbox": [],
  "geometry": {"coordinates":[77.719838,30.371937],"type":"Point"}
}