{
  "id": 2632553,
  "type": "Feature",
  "properties": {
    "tgn:hierarchy":[
        "tgn:2632553",
        "tgn:1000001",
        "tgn:2000307",
        "tgn:7012149",
        "tgn:7007248",
        "tgn:7029392"
    ],
    "tgn:id":2632553,
    "tgn:name":"Rozier Pond",
    "tgn:placetype":[
        "aat:300006191"
    ]
},
  "bbox": [],
  "geometry": {"coordinates":[-81.6167,32.2833],"type":"Point"}
}