{
  "id": 2420251,
  "type": "Feature",
  "properties": {
    "tgn:hierarchy":[
        "tgn:2420251",
        "tgn:1000001",
        "tgn:7012149",
        "tgn:2001038",
        "tgn:7007521",
        "tgn:7029392"
    ],
    "tgn:id":2420251,
    "tgn:name":"Jefferson, Lake",
    "tgn:placetype":[
        "aat:300008680"
    ]
},
  "bbox": [],
  "geometry": {"coordinates":[-93.7667,44.2667],"type":"Point"}
}