{
  "id": 2401133,
  "type": "Feature",
  "properties": {
    "tgn:hierarchy":[
        "tgn:2401133",
        "tgn:7006450",
        "tgn:1000001",
        "tgn:7012149",
        "tgn:2000089",
        "tgn:7029392"
    ],
    "tgn:id":2401133,
    "tgn:name":"Horsefly Creek",
    "tgn:placetype":[
        "aat:300008706"
    ]
},
  "bbox": [],
  "geometry": {"coordinates":[-157.6667,62.8833],"type":"Point"}
}