<<<<<<< HEAD
{
  "id": 2401133,
  "type": "Feature",
  "properties": {
    "tgn:hierarchy":[
        "tgn:2401133",
        "tgn:7006450",
        "tgn:1000001",
        "tgn:7012149",
        "tgn:2000089",
        "tgn:7029392"
    ],
    "tgn:id":2401133,
    "tgn:name":"Horsefly Creek",
    "tgn:placetype":[
        "aat:300008706"
    ]
},
  "bbox": [],
  "geometry": {"coordinates":[-157.6667,62.8833],"type":"Point"}
}
=======
{"geometry":{"type":"Point","coordinates":[-157.666700,62.883300]},"type":"Feature","properties":{"hierarchy":["tgn:2401133","tgn:7006450","tgn:1000001","tgn:7012149","tgn:2000089","tgn:7029392"],"placetype":["aat:300008706"],"id":2401133,"name:xx":"Horsefly Creek"}}
>>>>>>> 03f74aca74312dbeaf24d7e61306dd6a786dc3d0
