{
  "id": 7222195,
  "type": "Feature",
  "properties": {
    "tgn:hierarchy":[
        "tgn:7222195",
        "tgn:7002725",
        "tgn:7002715",
        "tgn:1000003",
        "tgn:1000074",
        "tgn:7029392"
    ],
    "tgn:id":7222195,
    "tgn:name":"Sisam\u00eda",
    "tgn:placetype":[
        "aat:300008347"
    ]
},
  "bbox": [],
  "geometry": {"coordinates":[23.416667,40.95],"type":"Point"}
}