{
  "id": 2511586,
  "type": "Feature",
  "properties": {
    "tgn:hierarchy":[
        "tgn:2511586",
        "tgn:1000001",
        "tgn:7012149",
        "tgn:2001036",
        "tgn:7007521",
        "tgn:7029392"
    ],
    "tgn:id":2511586,
    "tgn:name":"Milepost Seven Tailings Ponds",
    "tgn:placetype":[
        "aat:300006191"
    ]
},
  "bbox": [],
  "geometry": {"coordinates":[-91.35,47.2833],"type":"Point"}
}