{
  "id": 2644234,
  "type": "Feature",
  "properties": {
    "tgn:hierarchy":[
        "tgn:2644234",
        "tgn:1000001",
        "tgn:7012149",
        "tgn:2001453",
        "tgn:7007566",
        "tgn:7029392"
    ],
    "tgn:id":2644234,
    "tgn:name":"Santiago, Ca\u00f1on",
    "tgn:placetype":[
        "aat:300008761"
    ]
},
  "bbox": [],
  "geometry": {"coordinates":[-104.6167,35.5333],"type":"Point"}
}