{
  "id": 2496059,
  "type": "Feature",
  "properties": {
    "tgn:hierarchy":[
        "tgn:2496059",
        "tgn:1000001",
        "tgn:7012149",
        "tgn:1002472",
        "tgn:7007568",
        "tgn:7029392"
    ],
    "tgn:id":2496059,
    "tgn:name":"Massawepie Pond",
    "tgn:placetype":[
        "aat:300008680"
    ]
},
  "bbox": [],
  "geometry": {"coordinates":[-75.0833,44.0167],"type":"Point"}
}