{
  "id": 7230455,
  "type": "Feature",
  "properties": {
    "tgn:hierarchy":[
        "tgn:7230455",
        "tgn:7002751",
        "tgn:7001399",
        "tgn:1000003",
        "tgn:1000074",
        "tgn:7029392"
    ],
    "tgn:id":7230455,
    "tgn:name":"Krioner\u00edtis",
    "tgn:placetype":[
        "aat:300008347"
    ]
},
  "bbox": [],
  "geometry": {"coordinates":[23.283333,38.933333],"type":"Point"}
}