{
  "id": 2553411,
  "type": "Feature",
  "properties": {
    "tgn:hierarchy":[
        "tgn:2553411",
        "tgn:1000001",
        "tgn:7012149",
        "tgn:7007826",
        "tgn:7029392"
    ],
    "tgn:id":2553411,
    "tgn:name":"Oak Branch",
    "tgn:placetype":[
        "aat:300008699"
    ]
},
  "bbox": [],
  "geometry": {"coordinates":[-96.5833,32.2333],"type":"Point"}
}