{
  "id": 7567484,
  "type": "Feature",
  "properties": {
    "tgn:hierarchy":[
        "tgn:7567484",
        "tgn:1000004",
        "tgn:7000198",
        "tgn:7031786",
        "tgn:7029392"
    ],
    "tgn:id":7567484,
    "tgn:name:en":"S\u012bla",
    "tgn:placetype":[
        "aat:300008347"
    ]
},
  "bbox": [],
  "geometry": {"coordinates":[78.669574,29.816228],"type":"Point"}
}