{
  "id": 7280534,
  "type": "Feature",
  "properties": {
    "tgn:hierarchy":[
        "tgn:7280534",
        "tgn:1001705",
        "tgn:1000049",
        "tgn:1000002",
        "tgn:7029392"
    ],
    "tgn:id":7280534,
    "tgn:name":"Talp\u00e9n",
    "tgn:placetype":[
        "aat:300000206"
    ]
},
  "bbox": [],
  "geometry": {"coordinates":[-72.283333,-35.233333],"type":"Point"}
}