{
  "id": 2519609,
  "type": "Feature",
  "properties": {
    "tgn:hierarchy":[
        "tgn:2519609",
        "tgn:1000001",
        "tgn:2001418",
        "tgn:7012149",
        "tgn:7007526",
        "tgn:7029392"
    ],
    "tgn:id":2519609,
    "tgn:name":"Mogul Canyon",
    "tgn:placetype":[
        "aat:300008761"
    ]
},
  "bbox": [],
  "geometry": {"coordinates":[-116.9667,38.6667],"type":"Point"}
}