{
  "id": 7349275,
  "type": "Feature",
  "properties": {
    "tgn:hierarchy":[
        "tgn:7349275",
        "tgn:1000001",
        "tgn:7005599",
        "tgn:7005560",
        "tgn:7029392"
    ],
    "tgn:id":7349275,
    "tgn:name":"Agua Dulce, Arroyo",
    "tgn:placetype":[
        "aat:300008699"
    ]
},
  "bbox": [],
  "geometry": {"coordinates":[-94.15,18.133333],"type":"Point"}
}