{
  "id": 2357512,
  "type": "Feature",
  "properties": {
    "tgn:hierarchy":[
        "tgn:2357512",
        "tgn:1000001",
        "tgn:2000469",
        "tgn:7012149",
        "tgn:7007250",
        "tgn:7029392"
    ],
    "tgn:id":2357512,
    "tgn:name":"Governor Creek",
    "tgn:placetype":[
        "aat:300008706"
    ]
},
  "bbox": [],
  "geometry": {"coordinates":[-115.5333,46.7667],"type":"Point"}
}