{
  "id": 2102534,
  "type": "Feature",
  "properties": {
    "tgn:hierarchy":[
        "tgn:2102534",
        "tgn:1000001",
        "tgn:7012149",
        "tgn:2002092",
        "tgn:7007826",
        "tgn:7029392"
    ],
    "tgn:id":2102534,
    "tgn:name":"Bacon",
    "tgn:placetype":[
        "aat:300387016"
    ]
},
  "bbox": [],
  "geometry": {"coordinates":[-98.5333,33.9833],"type":"Point"}
}