{
  "id": 2343862,
  "type": "Feature",
  "properties": {
    "tgn:hierarchy":[
        "tgn:2343862",
        "tgn:1000001",
        "tgn:7012149",
        "tgn:7007157",
        "tgn:7014004",
        "tgn:7029392"
    ],
    "tgn:id":2343862,
    "tgn:name":"Gallison Lake",
    "tgn:placetype":[
        "aat:300008680"
    ]
},
  "bbox": [],
  "geometry": {"coordinates":[-119.3167,37.7667],"type":"Point"}
}