{
  "id": 2244541,
  "type": "Feature",
  "properties": {
    "tgn:hierarchy":[
        "tgn:2244541",
        "tgn:1000001",
        "tgn:7012149",
        "tgn:2001490",
        "tgn:7007709",
        "tgn:7029392"
    ],
    "tgn:id":2244541,
    "tgn:name":"Clinton",
    "tgn:placetype":[
        "aat:300008347"
    ]
},
  "bbox": [],
  "geometry": {"coordinates":[-80.45,35.75],"type":"Point"}
}