{
  "id": 2461685,
  "type": "Feature",
  "properties": {
    "tgn:hierarchy":[
        "tgn:2461685",
        "tgn:1002165",
        "tgn:1000001",
        "tgn:7012149",
        "tgn:7007517",
        "tgn:7029392"
    ],
    "tgn:id":2461685,
    "tgn:name":"Little Thatch Island",
    "tgn:placetype":[
        "aat:300008791"
    ]
},
  "bbox": [],
  "geometry": {"coordinates":[-70.45,41.5667],"type":"Point"}
}