{
  "id": 2169573,
  "type": "Feature",
  "properties": {
    "tgn:hierarchy":[
        "tgn:2169573",
        "tgn:1000001",
        "tgn:7012149",
        "tgn:2001295",
        "tgn:7007524",
        "tgn:7029392"
    ],
    "tgn:id":2169573,
    "tgn:name":"Big McNeil Slough",
    "tgn:placetype":[
        "aat:300006191"
    ]
},
  "bbox": [],
  "geometry": {"coordinates":[-107.5167,48.5333],"type":"Point"}
}