{
  "id": 1079288,
  "type": "Feature",
  "properties": {
    "tgn:hierarchy":[
        "tgn:1079288",
        "tgn:1000004",
        "tgn:7000228",
        "tgn:7000231",
        "tgn:7029392"
    ],
    "tgn:id":1079288,
    "tgn:name":"S\u016brak",
    "tgn:placetype":[
        "aat:300008347"
    ]
},
  "bbox": [],
  "geometry": {"coordinates":[58.8333,25.6667],"type":"Point"}
}