<<<<<<< HEAD
{
  "id": 7363750,
  "type": "Feature",
  "properties": {
    "tgn:hierarchy":[
        "tgn:7363750",
        "tgn:1000001",
        "tgn:7005595",
        "tgn:7005560",
        "tgn:7029392"
    ],
    "tgn:id":7363750,
    "tgn:name":"El Chilar",
    "tgn:placetype":[
        "aat:300008347"
    ]
},
  "bbox": [],
  "geometry": {"coordinates":[-106.34,24.2175],"type":"Point"}
}
=======
{"geometry":{"type":"Point","coordinates":[-106.340000,24.217500]},"type":"Feature","properties":{"hierarchy":["tgn:7363750","tgn:1000001","tgn:7005595","tgn:7005560","tgn:7029392"],"placetype":["aat:300008347"],"id":7363750,"name:xx":"El Chilar"}}
>>>>>>> 03f74aca74312dbeaf24d7e61306dd6a786dc3d0
