{
  "id": 7420060,
  "type": "Feature",
  "properties": {
    "tgn:hierarchy":[
        "tgn:7420060",
        "tgn:1000001",
        "tgn:7005589",
        "tgn:7005560",
        "tgn:7029392"
    ],
    "tgn:id":7420060,
    "tgn:name:es":"El Barro",
    "tgn:placetype":[
        "aat:300008347"
    ]
},
  "bbox": [],
  "geometry": {"coordinates":[-99.440278,26.486111],"type":"Point"}
}