{
  "id": 7419895,
  "type": "Feature",
  "properties": {
    "tgn:hierarchy":[
        "tgn:7419895",
        "tgn:1001836",
        "tgn:1000001",
        "tgn:7005560",
        "tgn:7029392"
    ],
    "tgn:id":7419895,
    "tgn:name":"San Venancio, R\u00edo",
    "tgn:placetype":[
        "aat:300008699"
    ]
},
  "bbox": [],
  "geometry": {"coordinates":[-110.155556,23.218611],"type":"Point"}
}