{
  "id": 2026283,
  "type": "Feature",
  "properties": {
    "tgn:hierarchy":[
        "tgn:2026283",
        "tgn:1000001",
        "tgn:2000505",
        "tgn:7012149",
        "tgn:7007251",
        "tgn:7029392"
    ],
    "tgn:id":2026283,
    "tgn:name":"Albion",
    "tgn:placetype":[
        "aat:300008347"
    ]
},
  "bbox": [],
  "geometry": {"coordinates":[-88.05,38.3667],"type":"Point"}
}