<<<<<<< HEAD
{
  "id": 7241539,
  "type": "Feature",
  "properties": {
    "tgn:hierarchy":[
        "tgn:7241539",
        "tgn:7003457",
        "tgn:1000003",
        "tgn:1000063",
        "tgn:7018236",
        "tgn:7029392"
    ],
    "tgn:id":7241539,
    "tgn:name":"Kleinen Buizemont",
    "tgn:placetype":[
        "aat:300008347"
    ]
},
  "bbox": [],
  "geometry": {"coordinates":[3.882795,50.759678],"type":"Point"}
}
=======
{"geometry":{"type":"Point","coordinates":[3.882795,50.759678]},"type":"Feature","properties":{"hierarchy":["tgn:7241539","tgn:7003457","tgn:1000003","tgn:1000063","tgn:7018236","tgn:7029392"],"placetype":["aat:300008347"],"id":7241539,"name:xx":"Kleinen Buizemont"}}
>>>>>>> 03f74aca74312dbeaf24d7e61306dd6a786dc3d0
