{
  "id": 7526064,
  "type": "Feature",
  "properties": {
    "tgn:hierarchy":[
        "tgn:7526064",
        "tgn:7001242",
        "tgn:7016833",
        "tgn:1001091",
        "tgn:7029392"
    ],
    "tgn:id":7526064,
    "tgn:name":"Al Markaz al Qawm\u012b lil Imti\u1e29\u0101n\u0101t wa at Taqw\u012bm at Tarbaw\u012b",
    "tgn:placetype":[
        "aat:300004792"
    ]
},
  "bbox": [],
  "geometry": {"coordinates":[31.311813,30.009238],"type":"Point"}
}