{
  "id": 7547432,
  "type": "Feature",
  "properties": {
    "tgn:hierarchy":[
        "tgn:7547432",
        "tgn:1000004",
        "tgn:1001832",
        "tgn:7000198",
        "tgn:7029392"
    ],
    "tgn:id":7547432,
    "tgn:name:en":"\u0100hataguri",
    "tgn:placetype":[
        "aat:300008347"
    ]
},
  "bbox": [],
  "geometry": {"coordinates":[93.866667,26.833333],"type":"Point"}
}