{
  "id": 2246805,
  "type": "Feature",
  "properties": {
    "tgn:hierarchy":[
        "tgn:2246805",
        "tgn:1000001",
        "tgn:1002753",
        "tgn:7012149",
        "tgn:7007828",
        "tgn:7029392"
    ],
    "tgn:id":2246805,
    "tgn:name":"Coche Brook",
    "tgn:placetype":[
        "aat:300008699"
    ]
},
  "bbox": [],
  "geometry": {"coordinates":[-72.0333,44.9333],"type":"Point"}
}