{
  "id": 2238942,
  "type": "Feature",
  "properties": {
    "tgn:hierarchy":[
        "tgn:2238942",
        "tgn:1000001",
        "tgn:2001410",
        "tgn:7012149",
        "tgn:7007526",
        "tgn:7029392"
    ],
    "tgn:id":2238942,
    "tgn:name":"Christmas Mine",
    "tgn:placetype":[
        "aat:300000390"
    ]
},
  "bbox": [],
  "geometry": {"coordinates":[-115.45,35.7167],"type":"Point"}
}