{
  "id": 7517808,
  "type": "Feature",
  "properties": {
    "tgn:hierarchy":[
        "tgn:7517808",
        "tgn:1008380",
        "tgn:1000226",
        "tgn:7000512",
        "tgn:1000006",
        "tgn:7029392"
    ],
    "tgn:id":7517808,
    "tgn:name:en":"Ngauranga",
    "tgn:placetype":[
        "aat:300008347"
    ]
},
  "bbox": [],
  "geometry": {"coordinates":[174.816667,-41.25],"type":"Point"}
}