{
  "id": 2413034,
  "type": "Feature",
  "properties": {
    "tgn:hierarchy":[
        "tgn:2413034",
        "tgn:1000001",
        "tgn:2001746",
        "tgn:7012149",
        "tgn:7007712",
        "tgn:7029392"
    ],
    "tgn:id":2413034,
    "tgn:name":"Inlet Harbor",
    "tgn:placetype":[
        "aat:300008347"
    ]
},
  "bbox": [],
  "geometry": {"coordinates":[-79.0167,33.5333],"type":"Point"}
}