{
  "id": 7586412,
  "type": "Feature",
  "properties": {
    "tgn:hierarchy":[
        "tgn:7586412",
        "tgn:1000004",
        "tgn:7000198",
        "tgn:7000799",
        "tgn:7029392"
    ],
    "tgn:id":7586412,
    "tgn:name:en":"Paiwan Chakul",
    "tgn:placetype":[
        "aat:300008347"
    ]
},
  "bbox": [],
  "geometry": {"coordinates":[74.090777,34.31041],"type":"Point"}
}