{
  "id": 2441461,
  "type": "Feature",
  "properties": {
    "tgn:hierarchy":[
        "tgn:2441461",
        "tgn:7006450",
        "tgn:1000001",
        "tgn:7030517",
        "tgn:7012149",
        "tgn:7029392"
    ],
    "tgn:id":2441461,
    "tgn:name":"Knutson Bay",
    "tgn:placetype":[
        "aat:300132316"
    ]
},
  "bbox": [],
  "geometry": {"coordinates":[-154.1833,59.7833],"type":"Point"}
}