<<<<<<< HEAD
{
  "id": 2256259,
  "type": "Feature",
  "properties": {
    "tgn:hierarchy":[
        "tgn:2256259",
        "tgn:1000001",
        "tgn:7012149",
        "tgn:2002273",
        "tgn:7013961",
        "tgn:7029392"
    ],
    "tgn:id":2256259,
    "tgn:name":"Copperas Mine Fork",
    "tgn:placetype":[
        "aat:300008699"
    ]
},
  "bbox": [],
  "geometry": {"coordinates":[-82.1,37.8],"type":"Point"}
}
=======
{"geometry":{"type":"Point","coordinates":[-82.100000,37.800000]},"type":"Feature","properties":{"hierarchy":["tgn:2256259","tgn:1000001","tgn:7012149","tgn:2002273","tgn:7013961","tgn:7029392"],"placetype":["aat:300008699"],"id":2256259,"name:xx":"Copperas Mine Fork"}}
>>>>>>> 03f74aca74312dbeaf24d7e61306dd6a786dc3d0
