{
  "id": 7313861,
  "type": "Feature",
  "properties": {
    "tgn:hierarchy":[
        "tgn:7313861",
        "tgn:1001630",
        "tgn:1000049",
        "tgn:1000002",
        "tgn:7029392"
    ],
    "tgn:id":7313861,
    "tgn:name":"La Vega",
    "tgn:placetype":[
        "aat:300008347"
    ]
},
  "bbox": [],
  "geometry": {"coordinates":[-70.433333,-28.833333],"type":"Point"}
}