<<<<<<< HEAD
{
  "id": 7369308,
  "type": "Feature",
  "properties": {
    "tgn:hierarchy":[
        "tgn:7369308",
        "tgn:1000001",
        "tgn:7005597",
        "tgn:7005560",
        "tgn:7029392"
    ],
    "tgn:id":7369308,
    "tgn:name":"Jabal\u00ed",
    "tgn:placetype":[
        "aat:300008347"
    ]
},
  "bbox": [],
  "geometry": {"coordinates":[-98.2,25.783333],"type":"Point"}
}
=======
{"geometry":{"type":"Point","coordinates":[-98.200000,25.783333]},"type":"Feature","properties":{"hierarchy":["tgn:7369308","tgn:1000001","tgn:7005597","tgn:7005560","tgn:7029392"],"placetype":["aat:300008347"],"id":7369308,"name:xx":"Jabal\u00ed"}}
>>>>>>> 03f74aca74312dbeaf24d7e61306dd6a786dc3d0
