{
  "id": 7129463,
  "type": "Feature",
  "properties": {
    "tgn:hierarchy":[
        "tgn:7129463",
        "tgn:7003692",
        "tgn:1000003",
        "tgn:7000084",
        "tgn:7029392"
    ],
    "tgn:id":7129463,
    "tgn:name":"Massenbachhausen",
    "tgn:placetype":[
        "aat:300008347"
    ]
},
  "bbox": [],
  "geometry": {"coordinates":[9.043333,49.177778],"type":"Point"}
}