{
  "id": 2160725,
  "type": "Feature",
  "properties": {
    "tgn:hierarchy":[
        "tgn:2160725",
        "tgn:1000001",
        "tgn:7012149",
        "tgn:7007255",
        "tgn:7029392"
    ],
    "tgn:id":2160725,
    "tgn:name":"Belcher Creek",
    "tgn:placetype":[
        "aat:300008706"
    ]
},
  "bbox": [],
  "geometry": {"coordinates":[-86.6667,37.0167],"type":"Point"}
}