{
  "id": 2611837,
  "type": "Feature",
  "properties": {
    "tgn:hierarchy":[
        "tgn:2611837",
        "tgn:1000001",
        "tgn:7012149",
        "tgn:2002121",
        "tgn:7007827",
        "tgn:7029392"
    ],
    "tgn:id":2611837,
    "tgn:name":"Red Pine Ridge",
    "tgn:placetype":[
        "aat:300266640"
    ]
},
  "bbox": [],
  "geometry": {"coordinates":[-111.9333,38.6167],"type":"Point"}
}