{
  "id": 2125916,
  "type": "Feature",
  "properties": {
    "tgn:hierarchy":[
        "tgn:2125916",
        "tgn:1000001",
        "tgn:7006451",
        "tgn:7012149",
        "tgn:2000096",
        "tgn:7029392"
    ],
    "tgn:id":2125916,
    "tgn:name":"Adams Mine",
    "tgn:placetype":[
        "aat:300000390"
    ]
},
  "bbox": [],
  "geometry": {"coordinates":[-113.4833,33.3833],"type":"Point"}
}