{
  "id": 2075533,
  "type": "Feature",
  "properties": {
    "tgn:hierarchy":[
        "tgn:2075533",
        "tgn:1000001",
        "tgn:7012149",
        "tgn:2001516",
        "tgn:7007709",
        "tgn:7029392"
    ],
    "tgn:id":2075533,
    "tgn:name":"Luck",
    "tgn:placetype":[
        "aat:300008347",
        "aat:300387210"
    ]
},
  "bbox": [],
  "geometry": {"coordinates":[-82.85,35.7333],"type":"Point"}
}