{
  "id": 7497751,
  "type": "Feature",
  "properties": {
    "tgn:hierarchy":[
        "tgn:7497751",
        "tgn:1000004",
        "tgn:7492971",
        "tgn:1000141",
        "tgn:7029392"
    ],
    "tgn:id":7497751,
    "tgn:name":"Fuxing Luqiao",
    "tgn:placetype":[
        "aat:300007836"
    ]
},
  "bbox": [],
  "geometry": {"coordinates":[120.489388,22.668384],"type":"Point"}
}