{
  "id": 7411531,
  "type": "Feature",
  "properties": {
    "tgn:hierarchy":[
        "tgn:7411531",
        "tgn:7005587",
        "tgn:1000001",
        "tgn:7005560",
        "tgn:7029392"
    ],
    "tgn:id":7411531,
    "tgn:name:es":"El Mirlo",
    "tgn:placetype":[
        "aat:300008347"
    ]
},
  "bbox": [],
  "geometry": {"coordinates":[-98.525,19.758333],"type":"Point"}
}