<<<<<<< HEAD
{
  "id": 7472333,
  "type": "Feature",
  "properties": {
    "tgn:hierarchy":[
        "tgn:7472333",
        "tgn:1000004",
        "tgn:7001014",
        "tgn:1000141",
        "tgn:7029392"
    ],
    "tgn:id":7472333,
    "tgn:name":"Wukuaicuo",
    "tgn:placetype":[
        "aat:300008347"
    ]
},
  "bbox": [],
  "geometry": {"coordinates":[120.166111,23.646389],"type":"Point"}
}
=======
{"geometry":{"type":"Point","coordinates":[120.166111,23.646389]},"type":"Feature","properties":{"hierarchy":["tgn:7472333","tgn:1000004","tgn:7001014","tgn:1000141","tgn:7029392"],"placetype":["aat:300008347"],"id":7472333,"name:xx":"Wukuaicuo"}}
>>>>>>> 03f74aca74312dbeaf24d7e61306dd6a786dc3d0
