{
  "id": 2638449,
  "type": "Feature",
  "properties": {
    "tgn:hierarchy":[
        "tgn:2638449",
        "tgn:7006450",
        "tgn:2000069",
        "tgn:1000001",
        "tgn:7012149",
        "tgn:7029392"
    ],
    "tgn:id":2638449,
    "tgn:name":"Salmon Berry Lake",
    "tgn:placetype":[
        "aat:300008680"
    ]
},
  "bbox": [],
  "geometry": {"coordinates":[-155.1167,61.2333],"type":"Point"}
}