{
  "id": 2520600,
  "type": "Feature",
  "properties": {
    "tgn:hierarchy":[
        "tgn:2520600",
        "tgn:1000001",
        "tgn:7012149",
        "tgn:2001724",
        "tgn:7007710",
        "tgn:7029392"
    ],
    "tgn:id":2520600,
    "tgn:name":"Monkey Hollow",
    "tgn:placetype":[
        "aat:300008761"
    ]
},
  "bbox": [],
  "geometry": {"coordinates":[-80.4333,39.7667],"type":"Point"}
}