{
  "id": 2361756,
  "type": "Feature",
  "properties": {
    "tgn:hierarchy":[
        "tgn:2361756",
        "tgn:1000001",
        "tgn:7012149",
        "tgn:2002127",
        "tgn:7007827",
        "tgn:7029392"
    ],
    "tgn:id":2361756,
    "tgn:name":"Graveyard Wash",
    "tgn:placetype":[
        "aat:300008761"
    ]
},
  "bbox": [],
  "geometry": {"coordinates":[-113.6833,37.15],"type":"Point"}
}