{
  "id": 7112563,
  "type": "Feature",
  "properties": {
    "tgn:hierarchy":[
        "tgn:7112563",
        "tgn:1000003",
        "tgn:7003678",
        "tgn:7000084",
        "tgn:7029392"
    ],
    "tgn:id":7112563,
    "tgn:name":"Rimmels",
    "tgn:placetype":[
        "aat:300008347"
    ]
},
  "bbox": [],
  "geometry": {"coordinates":[9.833333,50.616667],"type":"Point"}
}