{
  "id": 7373574,
  "type": "Feature",
  "properties": {
    "tgn:hierarchy":[
        "tgn:7373574",
        "tgn:1000001",
        "tgn:7005597",
        "tgn:7005560",
        "tgn:7029392"
    ],
    "tgn:id":7373574,
    "tgn:name":"La Gloria",
    "tgn:placetype":[
        "aat:300008347"
    ]
},
  "bbox": [],
  "geometry": {"coordinates":[-97.616667,25.866667],"type":"Point"}
}