{
  "id": 7262699,
  "type": "Feature",
  "properties": {
    "tgn:concordances":{
        "gn:id":"2758122"
    },
    "tgn:hierarchy":[
        "tgn:7262699",
        "tgn:1000003",
        "tgn:7003622",
        "tgn:7016845",
        "tgn:7029392"
    ],
    "tgn:id":7262699,
    "tgn:name:nl":"Bulkemsbroek",
    "tgn:placetype":[
        "aat:300008347"
    ]
},
  "bbox": [],
  "geometry": {"coordinates":[5.966667,50.833333],"type":"Point"}
}