{
  "id": 2445236,
  "type": "Feature",
  "properties": {
    "tgn:hierarchy":[
        "tgn:2445236",
        "tgn:1000001",
        "tgn:7012149",
        "tgn:2000225",
        "tgn:7007158",
        "tgn:7029392"
    ],
    "tgn:id":2445236,
    "tgn:name":"Lemon Reservoir",
    "tgn:placetype":[
        "aat:300006191"
    ]
},
  "bbox": [],
  "geometry": {"coordinates":[-107.65,37.3667],"type":"Point"}
}