{
  "id": 2465829,
  "type": "Feature",
  "properties": {
    "tgn:hierarchy":[
        "tgn:2465829",
        "tgn:1000001",
        "tgn:7012149",
        "tgn:2001198",
        "tgn:7007523",
        "tgn:7029392"
    ],
    "tgn:id":2465829,
    "tgn:name":"Lone Star",
    "tgn:placetype":[
        "aat:300008347"
    ]
},
  "bbox": [],
  "geometry": {"coordinates":[-94.25,40.3333],"type":"Point"}
}