{
  "id": 2309880,
  "type": "Feature",
  "properties": {
    "tgn:hierarchy":[
        "tgn:2309880",
        "tgn:1000001",
        "tgn:7012149",
        "tgn:2001882",
        "tgn:7007825",
        "tgn:7029392"
    ],
    "tgn:id":2309880,
    "tgn:name":"Eastman",
    "tgn:placetype":[
        "aat:300008347",
        "aat:300167671"
    ]
},
  "bbox": [],
  "geometry": {"coordinates":[-81.9667,36.35],"type":"Point"}
}