{
  "id": 7011371,
  "type": "Feature",
  "properties": {
    "tgn:hierarchy":[
        "tgn:7011371",
        "tgn:7002445",
        "tgn:7008116",
        "tgn:1000003",
        "tgn:7011368",
        "tgn:7008591",
        "tgn:7029392"
    ],
    "tgn:id":7011371,
    "tgn:name:en":"Samson",
    "tgn:placetype":[
        "aat:300008791"
    ]
},
  "bbox": [],
  "geometry": {"coordinates":[-6.352609,49.93228],"type":"Point"}
}