<<<<<<< HEAD
{
  "id": 2766745,
  "type": "Feature",
  "properties": {
    "tgn:hierarchy":[
        "tgn:2766745",
        "tgn:2002142",
        "tgn:1000001",
        "tgn:7012149",
        "tgn:7007919",
        "tgn:7029392"
    ],
    "tgn:id":2766745,
    "tgn:name":"White Oak Run",
    "tgn:placetype":[
        "aat:300008699"
    ]
},
  "bbox": [],
  "geometry": {"coordinates":[-79.2667,38.3167],"type":"Point"}
}
=======
{"geometry":{"type":"Point","coordinates":[-79.266700,38.316700]},"type":"Feature","properties":{"hierarchy":["tgn:2766745","tgn:2002142","tgn:1000001","tgn:7012149","tgn:7007919","tgn:7029392"],"placetype":["aat:300008699"],"id":2766745,"name:xx":"White Oak Run"}}
>>>>>>> 03f74aca74312dbeaf24d7e61306dd6a786dc3d0
