{
  "id": 2766745,
  "type": "Feature",
  "properties": {
    "tgn:hierarchy":[
        "tgn:2766745",
        "tgn:2002142",
        "tgn:1000001",
        "tgn:7012149",
        "tgn:7007919",
        "tgn:7029392"
    ],
    "tgn:id":2766745,
    "tgn:name":"White Oak Run",
    "tgn:placetype":[
        "aat:300008699"
    ]
},
  "bbox": [],
  "geometry": {"coordinates":[-79.2667,38.3167],"type":"Point"}
}