{
  "id": 2076628,
  "type": "Feature",
  "properties": {
    "tgn:hierarchy":[
        "tgn:2076628",
        "tgn:1000001",
        "tgn:2001483",
        "tgn:7012149",
        "tgn:7007709",
        "tgn:7029392"
    ],
    "tgn:id":2076628,
    "tgn:name":"Shooting Creek",
    "tgn:placetype":[
        "aat:300008347"
    ]
},
  "bbox": [],
  "geometry": {"coordinates":[-83.6667,35.0167],"type":"Point"}
}