<<<<<<< HEAD
{
  "id": 7356988,
  "type": "Feature",
  "properties": {
    "tgn:hierarchy":[
        "tgn:7356988",
        "tgn:1000001",
        "tgn:7005595",
        "tgn:7005560",
        "tgn:7029392"
    ],
    "tgn:id":7356988,
    "tgn:name":"Campolifer",
    "tgn:placetype":[
        "aat:300008347"
    ]
},
  "bbox": [],
  "geometry": {"coordinates":[-108.716667,25.566667],"type":"Point"}
}
=======
{"geometry":{"type":"Point","coordinates":[-108.716667,25.566667]},"type":"Feature","properties":{"hierarchy":["tgn:7356988","tgn:1000001","tgn:7005595","tgn:7005560","tgn:7029392"],"placetype":["aat:300008347"],"id":7356988,"name:xx":"Campolifer"}}
>>>>>>> 03f74aca74312dbeaf24d7e61306dd6a786dc3d0
