{
  "id": 7356988,
  "type": "Feature",
  "properties": {
    "tgn:hierarchy":[
        "tgn:7356988",
        "tgn:1000001",
        "tgn:7005595",
        "tgn:7005560",
        "tgn:7029392"
    ],
    "tgn:id":7356988,
    "tgn:name":"Campolifer",
    "tgn:placetype":[
        "aat:300008347"
    ]
},
  "bbox": [],
  "geometry": {"coordinates":[-108.716667,25.566667],"type":"Point"}
}