{
  "id": 7287055,
  "type": "Feature",
  "properties": {
    "tgn:hierarchy":[
        "tgn:7287055",
        "tgn:7002464",
        "tgn:1000049",
        "tgn:1000002",
        "tgn:7029392"
    ],
    "tgn:id":7287055,
    "tgn:name":"Guallatiri, Quebrada de",
    "tgn:placetype":[
        "aat:300266554",
        "aat:300008699"
    ]
},
  "bbox": [],
  "geometry": {"coordinates":[-69.183333,-18.533333],"type":"Point"}
}