{
  "id": 7186852,
  "type": "Feature",
  "properties": {
    "tgn:hierarchy":[
        "tgn:7186852",
        "tgn:1000003",
        "tgn:7003676",
        "tgn:7000084",
        "tgn:7029392"
    ],
    "tgn:id":7186852,
    "tgn:name":"F\u00f6sterei Georgsplatz",
    "tgn:placetype":[
        "aat:300004792"
    ]
},
  "bbox": [],
  "geometry": {"coordinates":[9.533333,52.266667],"type":"Point"}
}