{
  "id": 7397529,
  "type": "Feature",
  "properties": {
    "tgn:hierarchy":[
        "tgn:7397529",
        "tgn:1000001",
        "tgn:7005601",
        "tgn:7005560",
        "tgn:7029392"
    ],
    "tgn:id":7397529,
    "tgn:name":"San Nicol\u00e1s",
    "tgn:placetype":[
        "aat:300008347"
    ]
},
  "bbox": [],
  "geometry": {"coordinates":[-102.983333,21.616667],"type":"Point"}
}