{
  "id": 7269817,
  "type": "Feature",
  "properties": {
    "tgn:concordances":{
        "gn:id":"2750969"
    },
    "tgn:hierarchy":[
        "tgn:7269817",
        "tgn:1000003",
        "tgn:7003624",
        "tgn:7016845",
        "tgn:7029392"
    ],
    "tgn:id":7269817,
    "tgn:name:nl":"Melle",
    "tgn:placetype":[
        "aat:300008347"
    ]
},
  "bbox": [],
  "geometry": {"coordinates":[5.633333,51.666667],"type":"Point"}
}