{
  "id": 2778358,
  "type": "Feature",
  "properties": {
    "tgn:hierarchy":[
        "tgn:2778358",
        "tgn:1000001",
        "tgn:7012149",
        "tgn:7022218",
        "tgn:7007919",
        "tgn:7029392"
    ],
    "tgn:id":2778358,
    "tgn:name":"Witch Duck Point",
    "tgn:placetype":[
        "aat:300008850"
    ]
},
  "bbox": [],
  "geometry": {"coordinates":[-76.1167,36.8667],"type":"Point"}
}