{
  "id": 2113152,
  "type": "Feature",
  "properties": {
    "tgn:hierarchy":[
        "tgn:2113152",
        "tgn:1000001",
        "tgn:7012149",
        "tgn:2002164",
        "tgn:7007919",
        "tgn:7029392"
    ],
    "tgn:id":2113152,
    "tgn:name":"Mouth of Wilson",
    "tgn:placetype":[
        "aat:300008347"
    ]
},
  "bbox": [],
  "geometry": {"coordinates":[-81.3333,36.5833],"type":"Point"}
}