{
  "id": 7501711,
  "type": "Feature",
  "properties": {
    "tgn:hierarchy":[
        "tgn:7501711",
        "tgn:1000004",
        "tgn:7001002",
        "tgn:1000141",
        "tgn:7029392"
    ],
    "tgn:id":7501711,
    "tgn:name":"Dapingding",
    "tgn:placetype":[
        "aat:300008347"
    ]
},
  "bbox": [],
  "geometry": {"coordinates":[120.928889,24.782778],"type":"Point"}
}