{
  "id": 7234627,
  "type": "Feature",
  "properties": {
    "tgn:hierarchy":[
        "tgn:7234627",
        "tgn:7011170",
        "tgn:7002715",
        "tgn:1000003",
        "tgn:1000074",
        "tgn:7029392"
    ],
    "tgn:id":7234627,
    "tgn:name":"Agor\u00e1",
    "tgn:placetype":[
        "aat:300008347"
    ]
},
  "bbox": [],
  "geometry": {"coordinates":[24.316667,41.133333],"type":"Point"}
}