{
  "id": 2056483,
  "type": "Feature",
  "properties": {
    "tgn:hierarchy":[
        "tgn:2056483",
        "tgn:1000001",
        "tgn:7012149",
        "tgn:2001133",
        "tgn:7007522",
        "tgn:7029392"
    ],
    "tgn:id":2056483,
    "tgn:name":"Gibson",
    "tgn:placetype":[
        "aat:300008347"
    ]
},
  "bbox": [],
  "geometry": {"coordinates":[-88.6833,33.8333],"type":"Point"}
}