{
  "id": 2453542,
  "type": "Feature",
  "properties": {
    "tgn:hierarchy":[
        "tgn:2453542",
        "tgn:1000001",
        "tgn:7012149",
        "tgn:7007709",
        "tgn:7029392"
    ],
    "tgn:id":2453542,
    "tgn:name":"Little Cokey Swamp",
    "tgn:placetype":[
        "aat:300008699"
    ]
},
  "bbox": [],
  "geometry": {"coordinates":[-77.8167,35.8833],"type":"Point"}
}