{
  "id": 2706544,
  "type": "Feature",
  "properties": {
    "tgn:hierarchy":[
        "tgn:2706544",
        "tgn:1000001",
        "tgn:2000574",
        "tgn:7012149",
        "tgn:7007253",
        "tgn:7029392"
    ],
    "tgn:id":2706544,
    "tgn:name":"Swan Lake",
    "tgn:placetype":[
        "aat:300006191"
    ]
},
  "bbox": [],
  "geometry": {"coordinates":[-94.8333,42.0333],"type":"Point"}
}