{
  "id": 2391773,
  "type": "Feature",
  "properties": {
    "tgn:hierarchy":[
        "tgn:2391773",
        "tgn:1000001",
        "tgn:7012149",
        "tgn:2001254",
        "tgn:7007523",
        "tgn:7029392"
    ],
    "tgn:id":2391773,
    "tgn:name":"Hillside View Lake",
    "tgn:placetype":[
        "aat:300006191"
    ]
},
  "bbox": [],
  "geometry": {"coordinates":[-90.8167,38.1333],"type":"Point"}
}