{
  "id": 2579953,
  "type": "Feature",
  "properties": {
    "tgn:hierarchy":[
        "tgn:2579953",
        "tgn:1000001",
        "tgn:7012149",
        "tgn:7007158",
        "tgn:7029392"
    ],
    "tgn:id":2579953,
    "tgn:name":"Piedra Falls Ditch",
    "tgn:placetype":[
        "aat:300006075"
    ]
},
  "bbox": [],
  "geometry": {"coordinates":[-107.1333,37.4333],"type":"Point"}
}