{
  "id": 2397972,
  "type": "Feature",
  "properties": {
    "tgn:hierarchy":[
        "tgn:2397972",
        "tgn:1000001",
        "tgn:2000460",
        "tgn:7012149",
        "tgn:7007250",
        "tgn:7029392"
    ],
    "tgn:id":2397972,
    "tgn:name":"Hoodoo Mountain",
    "tgn:placetype":[
        "aat:300008798"
    ]
},
  "bbox": [],
  "geometry": {"coordinates":[-116.95,48.0667],"type":"Point"}
}