{
  "id": 2322800,
  "type": "Feature",
  "properties": {
    "tgn:hierarchy":[
        "tgn:2322800",
        "tgn:1000001",
        "tgn:7012149",
        "tgn:7007157",
        "tgn:2000189",
        "tgn:7029392"
    ],
    "tgn:id":2322800,
    "tgn:name":"Fan Gulch",
    "tgn:placetype":[
        "aat:300008761"
    ]
},
  "bbox": [],
  "geometry": {"coordinates":[-122.0167,41.1833],"type":"Point"}
}