{
  "id": 2434660,
  "type": "Feature",
  "properties": {
    "tgn:hierarchy":[
        "tgn:2434660",
        "tgn:1000001",
        "tgn:2001419",
        "tgn:7012149",
        "tgn:7007526",
        "tgn:7029392"
    ],
    "tgn:id":2434660,
    "tgn:name":"Kennedy Mine",
    "tgn:placetype":[
        "aat:300000390"
    ]
},
  "bbox": [],
  "geometry": {"coordinates":[-117.7333,40.2667],"type":"Point"}
}