{
  "id": 7540126,
  "type": "Feature",
  "properties": {
    "tgn:hierarchy":[
        "tgn:7540126",
        "tgn:7001242",
        "tgn:7001105",
        "tgn:7016833",
        "tgn:7029392"
    ],
    "tgn:id":7540126,
    "tgn:name":"Qa\u015fr al Ban\u0101t",
    "tgn:placetype":[
        "aat:300000833"
    ]
},
  "bbox": [],
  "geometry": {"coordinates":[30.55,29.383333],"type":"Point"}
}