{
  "id": 7550765,
  "type": "Feature",
  "properties": {
    "tgn:hierarchy":[
        "tgn:7550765",
        "tgn:1000004",
        "tgn:7000198",
        "tgn:1003539",
        "tgn:7029392"
    ],
    "tgn:id":7550765,
    "tgn:name:en":"D\u0101mbu",
    "tgn:placetype":[
        "aat:300008347"
    ]
},
  "bbox": [],
  "geometry": {"coordinates":[90.842495,25.664258],"type":"Point"}
}