{
  "id": 2536818,
  "type": "Feature",
  "properties": {
    "tgn:hierarchy":[
        "tgn:2536818",
        "tgn:1000001",
        "tgn:7012149",
        "tgn:2000547",
        "tgn:7007252",
        "tgn:7029392"
    ],
    "tgn:id":2536818,
    "tgn:name":"Needham Booher Ditch",
    "tgn:placetype":[
        "aat:300006075"
    ]
},
  "bbox": [],
  "geometry": {"coordinates":[-86.7333,40.05],"type":"Point"}
}