{
  "id": 7579137,
  "type": "Feature",
  "properties": {
    "tgn:hierarchy":[
        "tgn:7579137",
        "tgn:1000004",
        "tgn:1001842",
        "tgn:7000198",
        "tgn:7029392"
    ],
    "tgn:id":7579137,
    "tgn:name:en":"War Kh\u0101s",
    "tgn:placetype":[
        "aat:300008347"
    ]
},
  "bbox": [],
  "geometry": {"coordinates":[84.519183,24.731387],"type":"Point"}
}