{
  "id": 2176996,
  "type": "Feature",
  "properties": {
    "tgn:hierarchy":[
        "tgn:2176996",
        "tgn:1000001",
        "tgn:7012149",
        "tgn:7007157",
        "tgn:2000190",
        "tgn:7029392"
    ],
    "tgn:id":2176996,
    "tgn:name":"Black Oak Grove",
    "tgn:placetype":[
        "aat:300132451"
    ]
},
  "bbox": [],
  "geometry": {"coordinates":[-121.8333,40.1833],"type":"Point"}
}