<<<<<<< HEAD
{
  "id": 2402080,
  "type": "Feature",
  "properties": {
    "tgn:hierarchy":[
        "tgn:2402080",
        "tgn:1000001",
        "tgn:7006451",
        "tgn:2000092",
        "tgn:7012149",
        "tgn:7029392"
    ],
    "tgn:id":2402080,
    "tgn:name":"Horseshoe Spring",
    "tgn:placetype":[
        "aat:300008697"
    ]
},
  "bbox": [],
  "geometry": {"coordinates":[-111.4,34.7667],"type":"Point"}
}
=======
{"geometry":{"type":"Point","coordinates":[-111.400000,34.766700]},"type":"Feature","properties":{"hierarchy":["tgn:2402080","tgn:1000001","tgn:7006451","tgn:2000092","tgn:7012149","tgn:7029392"],"placetype":["aat:300008697"],"id":2402080,"name:xx":"Horseshoe Spring"}}
>>>>>>> 03f74aca74312dbeaf24d7e61306dd6a786dc3d0
