{
  "id": 2431717,
  "type": "Feature",
  "properties": {
    "tgn:hierarchy":[
        "tgn:2431717",
        "tgn:7006450",
        "tgn:1000001",
        "tgn:2124053",
        "tgn:7012149",
        "tgn:7029392"
    ],
    "tgn:id":2431717,
    "tgn:name":"Katie Lake",
    "tgn:placetype":[
        "aat:300008680"
    ]
},
  "bbox": [],
  "geometry": {"coordinates":[-149.8167,62.3833],"type":"Point"}
}