{
  "id": 7328062,
  "type": "Feature",
  "properties": {
    "tgn:hierarchy":[
        "tgn:7328062",
        "tgn:7002810",
        "tgn:7001158",
        "tgn:1000003",
        "tgn:1000095",
        "tgn:7029392"
    ],
    "tgn:id":7328062,
    "tgn:name":"Quintanilla-San Garc\u00eda",
    "tgn:placetype":[
        "aat:300008347"
    ]
},
  "bbox": [],
  "geometry": {"coordinates":[-3.183333,42.55],"type":"Point"}
}