{
  "id": 7451950,
  "type": "Feature",
  "properties": {
    "tgn:hierarchy":[
        "tgn:7451950",
        "tgn:7002445",
        "tgn:1000003",
        "tgn:7011430",
        "tgn:7008591",
        "tgn:7029392"
    ],
    "tgn:id":7451950,
    "tgn:name:en":"Freshwater Bay",
    "tgn:placetype":[
        "aat:300132316"
    ]
},
  "bbox": [],
  "geometry": {"coordinates":[-1.510278,50.669167],"type":"Point"}
}