{
  "id": 7191649,
  "type": "Feature",
  "properties": {
    "tgn:hierarchy":[
        "tgn:7191649",
        "tgn:1000003",
        "tgn:7003682",
        "tgn:7000084",
        "tgn:7029392"
    ],
    "tgn:id":7191649,
    "tgn:name":"Farren-Berg",
    "tgn:placetype":[
        "aat:300008777"
    ]
},
  "bbox": [],
  "geometry": {"coordinates":[7.933333,49.083333],"type":"Point"}
}