{
  "id": 1075480,
  "type": "Feature",
  "properties": {
    "tgn:hierarchy":[
        "tgn:1075480",
        "tgn:1001828",
        "tgn:1000004",
        "tgn:7000198",
        "tgn:7029392"
    ],
    "tgn:id":1075480,
    "tgn:name:en":"Hindupur",
    "tgn:placetype":[
        "aat:300008347"
    ]
},
  "bbox": [],
  "geometry": {"coordinates":[77.493333,13.828889],"type":"Point"}
}