{
  "id": 2641750,
  "type": "Feature",
  "properties": {
    "tgn:hierarchy":[
        "tgn:2641750",
        "tgn:1000001",
        "tgn:7012149",
        "tgn:2000490",
        "tgn:7007250",
        "tgn:7029392"
    ],
    "tgn:id":2641750,
    "tgn:name":"Sand Hollow",
    "tgn:placetype":[
        "aat:300008761"
    ]
},
  "bbox": [],
  "geometry": {"coordinates":[-112.75,42.5167],"type":"Point"}
}