{
  "id": 1042790,
  "type": "Feature",
  "properties": {
    "tgn:hierarchy":[
        "tgn:1042790",
        "tgn:7001199",
        "tgn:7003492",
        "tgn:1000003",
        "tgn:1000078",
        "tgn:7029392"
    ],
    "tgn:id":1042790,
    "tgn:name":"Edenderry",
    "tgn:placetype":[
        "aat:300008347"
    ]
},
  "bbox": [],
  "geometry": {"coordinates":[-7.05,53.35],"type":"Point"}
}