<<<<<<< HEAD
{
  "id": 2153315,
  "type": "Feature",
  "properties": {
    "tgn:hierarchy":[
        "tgn:2153315",
        "tgn:1000001",
        "tgn:7012149",
        "tgn:2002247",
        "tgn:7007920",
        "tgn:7029392"
    ],
    "tgn:id":2153315,
    "tgn:name":"Bean Canyon",
    "tgn:placetype":[
        "aat:300008761"
    ]
},
  "bbox": [],
  "geometry": {"coordinates":[-118.2667,47.85],"type":"Point"}
}
=======
{"geometry":{"type":"Point","coordinates":[-118.266700,47.850000]},"type":"Feature","properties":{"hierarchy":["tgn:2153315","tgn:1000001","tgn:7012149","tgn:2002247","tgn:7007920","tgn:7029392"],"placetype":["aat:300008761"],"id":2153315,"name:xx":"Bean Canyon"}}
>>>>>>> 03f74aca74312dbeaf24d7e61306dd6a786dc3d0
