{
  "id": 1011240,
  "type": "Feature",
  "properties": {
    "tgn:hierarchy":[
        "tgn:1011240",
        "tgn:1000003",
        "tgn:1000929",
        "tgn:1000090",
        "tgn:7029392"
    ],
    "tgn:id":1011240,
    "tgn:name":"Sines, Cabo de",
    "tgn:placetype":[
        "aat:300008850"
    ]
},
  "bbox": [],
  "geometry": {"coordinates":[8.886,37.957],"type":"Point"}
}