{
  "id": 2728339,
  "type": "Feature",
  "properties": {
    "tgn:hierarchy":[
        "tgn:2728339",
        "tgn:1000001",
        "tgn:1002218",
        "tgn:7012149",
        "tgn:7007157",
        "tgn:7029392"
    ],
    "tgn:id":2728339,
    "tgn:name":"Traynor Lateral",
    "tgn:placetype":[
        "aat:300006075"
    ]
},
  "bbox": [],
  "geometry": {"coordinates":[-121.7333,39.35],"type":"Point"}
}