{
  "id": 2583281,
  "type": "Feature",
  "properties": {
    "tgn:hierarchy":[
        "tgn:2583281",
        "tgn:1000001",
        "tgn:2001409",
        "tgn:7012149",
        "tgn:7007526",
        "tgn:7029392"
    ],
    "tgn:id":2583281,
    "tgn:name":"Pine Mountain",
    "tgn:placetype":[
        "aat:300008798"
    ]
},
  "bbox": [],
  "geometry": {"coordinates":[-117.9667,39.9833],"type":"Point"}
}