{
  "id": 2459944,
  "type": "Feature",
  "properties": {
    "tgn:hierarchy":[
        "tgn:2459944",
        "tgn:1000001",
        "tgn:7012149",
        "tgn:2000352",
        "tgn:7007248",
        "tgn:7029392"
    ],
    "tgn:id":2459944,
    "tgn:name":"Little Rock Creek",
    "tgn:placetype":[
        "aat:300008706"
    ]
},
  "bbox": [],
  "geometry": {"coordinates":[-84.3333,34.7333],"type":"Point"}
}