{
  "id": 2527002,
  "type": "Feature",
  "properties": {
    "tgn:hierarchy":[
        "tgn:2527002",
        "tgn:1000001",
        "tgn:7012149",
        "tgn:2001706",
        "tgn:7007708",
        "tgn:7029392"
    ],
    "tgn:id":2527002,
    "tgn:name":"Mount Baldy Log Pond",
    "tgn:placetype":[
        "aat:300006191"
    ]
},
  "bbox": [],
  "geometry": {"coordinates":[-123.2833,43.6333],"type":"Point"}
}