{
  "id": 7459531,
  "type": "Feature",
  "properties": {
    "tgn:hierarchy":[
        "tgn:7459531",
        "tgn:7002445",
        "tgn:1000003",
        "tgn:7012077",
        "tgn:7008591",
        "tgn:7029392"
    ],
    "tgn:id":7459531,
    "tgn:name:en":"Mew Stone",
    "tgn:placetype":[
        "aat:300008791"
    ]
},
  "bbox": [],
  "geometry": {"coordinates":[-3.533333,50.333333],"type":"Point"}
}