{
  "id": 7263494,
  "type": "Feature",
  "properties": {
    "tgn:concordances":{
        "gn:id":"2755492"
    },
    "tgn:hierarchy":[
        "tgn:7263494",
        "tgn:7003619",
        "tgn:1000003",
        "tgn:7016845",
        "tgn:7029392"
    ],
    "tgn:id":7263494,
    "tgn:name:nl":"Glinden",
    "tgn:placetype":[
        "aat:300008347"
    ]
},
  "bbox": [],
  "geometry": {"coordinates":[5.55,52.116667],"type":"Point"}
}