{
  "id": 2147337,
  "type": "Feature",
  "properties": {
    "tgn:hierarchy":[
        "tgn:2147337",
        "tgn:1000001",
        "tgn:7012149",
        "tgn:2000221",
        "tgn:7007158",
        "tgn:7029392"
    ],
    "tgn:id":2147337,
    "tgn:name":"Barbara Gulch",
    "tgn:placetype":[
        "aat:300008761"
    ]
},
  "bbox": [],
  "geometry": {"coordinates":[-105.2333,39.8667],"type":"Point"}
}