<<<<<<< HEAD
{
  "id": 2153205,
  "type": "Feature",
  "properties": {
    "tgn:hierarchy":[
        "tgn:2153205",
        "tgn:1000001",
        "tgn:7012149",
        "tgn:2000421",
        "tgn:7007248",
        "tgn:7029392"
    ],
    "tgn:id":2153205,
    "tgn:name":"Beall",
    "tgn:placetype":[
        "aat:300008347"
    ]
},
  "bbox": [],
  "geometry": {"coordinates":[-84.55,32.7333],"type":"Point"}
}
=======
{"geometry":{"type":"Point","coordinates":[-84.550000,32.733300]},"type":"Feature","properties":{"hierarchy":["tgn:2153205","tgn:1000001","tgn:7012149","tgn:2000421","tgn:7007248","tgn:7029392"],"placetype":["aat:300008347"],"id":2153205,"name:xx":"Beall"}}
>>>>>>> 03f74aca74312dbeaf24d7e61306dd6a786dc3d0
