{
  "id": 7148531,
  "type": "Feature",
  "properties": {
    "tgn:hierarchy":[
        "tgn:7148531",
        "tgn:1000003",
        "tgn:7003677",
        "tgn:7000084",
        "tgn:7029392"
    ],
    "tgn:id":7148531,
    "tgn:name":"Landwehr",
    "tgn:placetype":[
        "aat:300387200"
    ]
},
  "bbox": [],
  "geometry": {"coordinates":[7.55,51.583333],"type":"Point"}
}