<<<<<<< HEAD
{
  "id": 2768720,
  "type": "Feature",
  "properties": {
    "tgn:hierarchy":[
        "tgn:2768720",
        "tgn:1000001",
        "tgn:7012149",
        "tgn:1002782",
        "tgn:7007710",
        "tgn:7029392"
    ],
    "tgn:id":2768720,
    "tgn:name":"Whitman",
    "tgn:placetype":[
        "aat:300008347"
    ]
},
  "bbox": [],
  "geometry": {"coordinates":[-75.15,39.9167],"type":"Point"}
}
=======
{"geometry":{"type":"Point","coordinates":[-75.150000,39.916700]},"type":"Feature","properties":{"hierarchy":["tgn:2768720","tgn:1000001","tgn:7012149","tgn:1002782","tgn:7007710","tgn:7029392"],"placetype":["aat:300008347"],"id":2768720,"name:xx":"Whitman"}}
>>>>>>> 03f74aca74312dbeaf24d7e61306dd6a786dc3d0
