{
  "id": 1117352,
  "type": "Feature",
  "properties": {
    "tgn:hierarchy":[
        "tgn:1117352",
        "tgn:1009227",
        "tgn:1000226",
        "tgn:7016822",
        "tgn:1000006",
        "tgn:7029392"
    ],
    "tgn:id":1117352,
    "tgn:name:en":"Monowai, Lake",
    "tgn:placetype":[
        "aat:300008680"
    ]
},
  "bbox": [],
  "geometry": {"coordinates":[167.45,-45.866667],"type":"Point"}
}