{
  "id": 7229339,
  "type": "Feature",
  "properties": {
    "tgn:hierarchy":[
        "tgn:7229339",
        "tgn:7002681",
        "tgn:7001395",
        "tgn:1000003",
        "tgn:1000074",
        "tgn:7029392"
    ],
    "tgn:id":7229339,
    "tgn:name":"Lavr\u00edou, Lim\u00e9nas",
    "tgn:placetype":[
        "aat:300132316"
    ]
},
  "bbox": [],
  "geometry": {"coordinates":[24.064817,37.708157],"type":"Point"}
}