{
  "id": 2655262,
  "type": "Feature",
  "properties": {
    "tgn:hierarchy":[
        "tgn:2655262",
        "tgn:1000001",
        "tgn:7012149",
        "tgn:1002591",
        "tgn:7007255",
        "tgn:7029392"
    ],
    "tgn:id":2655262,
    "tgn:name":"Shanty Branch",
    "tgn:placetype":[
        "aat:300008699"
    ]
},
  "bbox": [],
  "geometry": {"coordinates":[-83.2333,38.5667],"type":"Point"}
}