{
  "id": 7550502,
  "type": "Feature",
  "properties": {
    "tgn:hierarchy":[
        "tgn:7550502",
        "tgn:1000004",
        "tgn:7000198",
        "tgn:1001895",
        "tgn:7029392"
    ],
    "tgn:id":7550502,
    "tgn:name:en":"Charan",
    "tgn:placetype":[
        "aat:300008347"
    ]
},
  "bbox": [],
  "geometry": {"coordinates":[73.966667,17.066667],"type":"Point"}
}