<<<<<<< HEAD
{
  "id": 7356093,
  "type": "Feature",
  "properties": {
    "tgn:hierarchy":[
        "tgn:7356093",
        "tgn:1000001",
        "tgn:7005597",
        "tgn:7005560",
        "tgn:7029392"
    ],
    "tgn:id":7356093,
    "tgn:name":"Camarote",
    "tgn:placetype":[
        "aat:300008347"
    ]
},
  "bbox": [],
  "geometry": {"coordinates":[-97.8,26.0],"type":"Point"}
}
=======
{"geometry":{"type":"Point","coordinates":[-97.800000,26.000000]},"type":"Feature","properties":{"hierarchy":["tgn:7356093","tgn:1000001","tgn:7005597","tgn:7005560","tgn:7029392"],"placetype":["aat:300008347"],"id":7356093,"name:xx":"Camarote"}}
>>>>>>> 03f74aca74312dbeaf24d7e61306dd6a786dc3d0
