{
  "id": 7505074,
  "type": "Feature",
  "properties": {
    "tgn:hierarchy":[
        "tgn:7505074",
        "tgn:1008380",
        "tgn:1000226",
        "tgn:7000512",
        "tgn:1000006",
        "tgn:7029392"
    ],
    "tgn:id":7505074,
    "tgn:name:en":"Hunter Bank",
    "tgn:placetype":[
        "aat:300386970"
    ]
},
  "bbox": [],
  "geometry": {"coordinates":[174.816667,-40.966667],"type":"Point"}
}