{
  "id": 1019372,
  "type": "Feature",
  "properties": {
    "tgn:hierarchy":[
        "tgn:1019372",
        "tgn:7006477",
        "tgn:1001427",
        "tgn:1000002",
        "tgn:7029392"
    ],
    "tgn:id":1019372,
    "tgn:name":"Cuadro Nacional",
    "tgn:placetype":[
        "aat:300008347"
    ]
},
  "bbox": [],
  "geometry": {"coordinates":[-68.2833,-34.6167],"type":"Point"}
}