{
  "id": 7470353,
  "type": "Feature",
  "properties": {
    "tgn:hierarchy":[
        "tgn:7470353",
        "tgn:7488858",
        "tgn:1000004",
        "tgn:1000141",
        "tgn:7029392"
    ],
    "tgn:id":7470353,
    "tgn:name":"Hehuan Shan Dongfeng",
    "tgn:placetype":[
        "aat:300008795"
    ]
},
  "bbox": [],
  "geometry": {"coordinates":[121.280833,24.135833],"type":"Point"}
}