{
  "id": 7000939,
  "type": "Feature",
  "properties": {
    "tgn:hierarchy":[
        "tgn:7000939",
        "tgn:7005195",
        "tgn:1000004",
        "tgn:1000142",
        "tgn:7029392"
    ],
    "tgn:id":7000939,
    "tgn:name":"Phangnga, Changwat",
    "tgn:placetype":[
        "aat:300387145",
        "aat:300000774"
    ]
},
  "bbox": [],
  "geometry": {"coordinates":[98.6667,8.25],"type":"Point"}
}