<<<<<<< HEAD
{
  "id": 7484211,
  "type": "Feature",
  "properties": {
    "tgn:hierarchy":[
        "tgn:7484211",
        "tgn:1000004",
        "tgn:7001009",
        "tgn:1000141",
        "tgn:7029392"
    ],
    "tgn:id":7484211,
    "tgn:name":"Xiachoushui",
    "tgn:placetype":[
        "aat:300008347"
    ]
},
  "bbox": [],
  "geometry": {"coordinates":[120.562222,24.279444],"type":"Point"}
}
=======
{"geometry":{"type":"Point","coordinates":[120.562222,24.279444]},"type":"Feature","properties":{"hierarchy":["tgn:7484211","tgn:1000004","tgn:7001009","tgn:1000141","tgn:7029392"],"placetype":["aat:300008347"],"id":7484211,"name:xx":"Xiachoushui"}}
>>>>>>> 03f74aca74312dbeaf24d7e61306dd6a786dc3d0
