{
  "id": 7051691,
  "type": "Feature",
  "properties": {
    "tgn:hierarchy":[
        "tgn:7051691",
        "tgn:1003440",
        "tgn:1000003",
        "tgn:7003124",
        "tgn:1000080",
        "tgn:7029392"
    ],
    "tgn:id":7051691,
    "tgn:name":"Marebbe",
    "tgn:placetype":[
        "aat:300387198",
        "aat:300265612"
    ]
},
  "bbox": [],
  "geometry": {"coordinates":[11.933333,46.666667],"type":"Point"}
}