{
  "id": 7331194,
  "type": "Feature",
  "properties": {
    "tgn:hierarchy":[
        "tgn:7331194",
        "tgn:7002818",
        "tgn:1001647",
        "tgn:1000003",
        "tgn:1000095",
        "tgn:7029392"
    ],
    "tgn:id":7331194,
    "tgn:name":"Grande, Laguna",
    "tgn:placetype":[
        "aat:300008680"
    ]
},
  "bbox": [],
  "geometry": {"coordinates":[-2.05,40.55],"type":"Point"}
}