{
  "id": 7548471,
  "type": "Feature",
  "properties": {
    "tgn:hierarchy":[
        "tgn:7548471",
        "tgn:1000004",
        "tgn:7000198",
        "tgn:7016788",
        "tgn:7029392"
    ],
    "tgn:id":7548471,
    "tgn:name:en":"Devariya",
    "tgn:placetype":[
        "aat:300008347"
    ]
},
  "bbox": [],
  "geometry": {"coordinates":[74.157142,25.281264],"type":"Point"}
}