{
  "id": 2437555,
  "type": "Feature",
  "properties": {
    "tgn:hierarchy":[
        "tgn:2437555",
        "tgn:1000001",
        "tgn:7012149",
        "tgn:7014510",
        "tgn:7007920",
        "tgn:7029392"
    ],
    "tgn:id":2437555,
    "tgn:name":"Kindy Creek",
    "tgn:placetype":[
        "aat:300008706"
    ]
},
  "bbox": [],
  "geometry": {"coordinates":[-121.1333,48.3667],"type":"Point"}
}