{
  "id": 7086355,
  "type": "Feature",
  "properties": {
    "tgn:hierarchy":[
        "tgn:7086355",
        "tgn:7003692",
        "tgn:1000003",
        "tgn:7000084",
        "tgn:7029392"
    ],
    "tgn:id":7086355,
    "tgn:name":"Weinstadt",
    "tgn:placetype":[
        "aat:300387173"
    ]
},
  "bbox": [],
  "geometry": {"coordinates":[9.383333,48.816667],"type":"Point"}
}