{
  "id": 2222539,
  "type": "Feature",
  "properties": {
    "tgn:hierarchy":[
        "tgn:2222539",
        "tgn:1000001",
        "tgn:7012149",
        "tgn:2000209",
        "tgn:7007158",
        "tgn:7029392"
    ],
    "tgn:id":2222539,
    "tgn:name":"Carpenter Peak",
    "tgn:placetype":[
        "aat:300008798"
    ]
},
  "bbox": [],
  "geometry": {"coordinates":[-105.0833,39.4167],"type":"Point"}
}