<<<<<<< HEAD
{
  "id": 2709770,
  "type": "Feature",
  "properties": {
    "tgn:hierarchy":[
        "tgn:2709770",
        "tgn:7006450",
        "tgn:1000001",
        "tgn:2124077",
        "tgn:7012149",
        "tgn:7029392"
    ],
    "tgn:id":2709770,
    "tgn:name":"Tahini River",
    "tgn:placetype":[
        "aat:300008707"
    ]
},
  "bbox": [],
  "geometry": {"coordinates":[-135.9833,59.6],"type":"Point"}
}
=======
{"geometry":{"type":"Point","coordinates":[-135.983300,59.600000]},"type":"Feature","properties":{"hierarchy":["tgn:2709770","tgn:7006450","tgn:1000001","tgn:2124077","tgn:7012149","tgn:7029392"],"placetype":["aat:300008707"],"id":2709770,"name:xx":"Tahini River"}}
>>>>>>> 03f74aca74312dbeaf24d7e61306dd6a786dc3d0
