{
  "id": 2250885,
  "type": "Feature",
  "properties": {
    "tgn:hierarchy":[
        "tgn:2250885",
        "tgn:1000001",
        "tgn:1002985",
        "tgn:7012149",
        "tgn:7007565",
        "tgn:7029392"
    ],
    "tgn:id":2250885,
    "tgn:name":"Columbia Lake",
    "tgn:placetype":[
        "aat:300006191"
    ]
},
  "bbox": [],
  "geometry": {"coordinates":[-75.0833,40.9167],"type":"Point"}
}