<<<<<<< HEAD
{
  "id": 7114294,
  "type": "Feature",
  "properties": {
    "tgn:hierarchy":[
        "tgn:7114294",
        "tgn:1000003",
        "tgn:7003682",
        "tgn:7000084",
        "tgn:7029392"
    ],
    "tgn:id":7114294,
    "tgn:name":"R\u00f6mer Berg",
    "tgn:placetype":[
        "aat:300008777"
    ]
},
  "bbox": [],
  "geometry": {"coordinates":[6.65,49.833333],"type":"Point"}
}
=======
{"geometry":{"type":"Point","coordinates":[6.650000,49.833333]},"type":"Feature","properties":{"hierarchy":["tgn:7114294","tgn:1000003","tgn:7003682","tgn:7000084","tgn:7029392"],"placetype":["aat:300008777"],"id":7114294,"name:xx":"R\u00f6mer Berg"}}
>>>>>>> 03f74aca74312dbeaf24d7e61306dd6a786dc3d0
