{
  "id": 7502934,
  "type": "Feature",
  "properties": {
    "tgn:hierarchy":[
        "tgn:7502934",
        "tgn:1000004",
        "tgn:7491221",
        "tgn:1000141",
        "tgn:7029392"
    ],
    "tgn:id":7502934,
    "tgn:name":"Xinfu Qiao",
    "tgn:placetype":[
        "aat:300007836"
    ]
},
  "bbox": [],
  "geometry": {"coordinates":[121.169444,23.046389],"type":"Point"}
}