{
  "id": 2179920,
  "type": "Feature",
  "properties": {
    "tgn:hierarchy":[
        "tgn:2179920",
        "tgn:1000001",
        "tgn:7012149",
        "tgn:2001723",
        "tgn:7007708",
        "tgn:7029392"
    ],
    "tgn:id":2179920,
    "tgn:name":"Blevins Spring",
    "tgn:placetype":[
        "aat:300008697"
    ]
},
  "bbox": [],
  "geometry": {"coordinates":[-119.9333,44.45],"type":"Point"}
}