{
  "id": 7392885,
  "type": "Feature",
  "properties": {
    "tgn:hierarchy":[
        "tgn:7392885",
        "tgn:1000001",
        "tgn:7005596",
        "tgn:7005560",
        "tgn:7029392"
    ],
    "tgn:id":7392885,
    "tgn:name":"San Francisco",
    "tgn:placetype":[
        "aat:300008347"
    ]
},
  "bbox": [],
  "geometry": {"coordinates":[-92.566667,18.316667],"type":"Point"}
}