{
  "id": 1097084,
  "type": "Feature",
  "properties": {
    "tgn:hierarchy":[
        "tgn:1097084",
        "tgn:7000490",
        "tgn:1000006",
        "tgn:7001829",
        "tgn:7029392"
    ],
    "tgn:id":1097084,
    "tgn:name":"Harts Range Police Station",
    "tgn:placetype":[
        "aat:300008347"
    ]
},
  "bbox": [],
  "geometry": {"coordinates":[134.9167,-22.9833],"type":"Point"}
}