{
  "id": 1088399,
  "type": "Feature",
  "properties": {
    "tgn:hierarchy":[
        "tgn:1088399",
        "tgn:7001242",
        "tgn:1000983",
        "tgn:1000155",
        "tgn:7029392"
    ],
    "tgn:id":1088399,
    "tgn:name":"Mayaka",
    "tgn:placetype":[
        "aat:300008347"
    ]
},
  "bbox": [],
  "geometry": {"coordinates":[16.8667,5.2833],"type":"Point"}
}