{
  "id": 7482072,
  "type": "Feature",
  "properties": {
    "tgn:hierarchy":[
        "tgn:7482072",
        "tgn:1000004",
        "tgn:7492971",
        "tgn:1000141",
        "tgn:7029392"
    ],
    "tgn:id":7482072,
    "tgn:name":"Dao'an Qiao",
    "tgn:placetype":[
        "aat:300007836"
    ]
},
  "bbox": [],
  "geometry": {"coordinates":[120.519837,22.638723],"type":"Point"}
}