<<<<<<< HEAD
{
  "id": 7482072,
  "type": "Feature",
  "properties": {
    "tgn:hierarchy":[
        "tgn:7482072",
        "tgn:1000004",
        "tgn:7492971",
        "tgn:1000141",
        "tgn:7029392"
    ],
    "tgn:id":7482072,
    "tgn:name":"Dao'an Qiao",
    "tgn:placetype":[
        "aat:300007836"
    ]
},
  "bbox": [],
  "geometry": {"coordinates":[120.519837,22.638723],"type":"Point"}
}
=======
{"geometry":{"type":"Point","coordinates":[120.519837,22.638723]},"type":"Feature","properties":{"hierarchy":["tgn:7482072","tgn:1000004","tgn:7492971","tgn:1000141","tgn:7029392"],"placetype":["aat:300007836"],"id":7482072,"name:xx":"Dao'an Qiao"}}
>>>>>>> 03f74aca74312dbeaf24d7e61306dd6a786dc3d0
