<<<<<<< HEAD
{
  "id": 2336366,
  "type": "Feature",
  "properties": {
    "tgn:hierarchy":[
        "tgn:2336366",
        "tgn:1000001",
        "tgn:7012149",
        "tgn:2002361",
        "tgn:7007922",
        "tgn:7029392"
    ],
    "tgn:id":2336366,
    "tgn:name":"Fountain Creek",
    "tgn:placetype":[
        "aat:300008706"
    ]
},
  "bbox": [],
  "geometry": {"coordinates":[-88.8167,44.5167],"type":"Point"}
}
=======
{"geometry":{"type":"Point","coordinates":[-88.816700,44.516700]},"type":"Feature","properties":{"hierarchy":["tgn:2336366","tgn:1000001","tgn:7012149","tgn:2002361","tgn:7007922","tgn:7029392"],"placetype":["aat:300008706"],"id":2336366,"name:xx":"Fountain Creek"}}
>>>>>>> 03f74aca74312dbeaf24d7e61306dd6a786dc3d0
