{
  "id": 7531109,
  "type": "Feature",
  "properties": {
    "tgn:hierarchy":[
        "tgn:7531109",
        "tgn:7001242",
        "tgn:7016833",
        "tgn:1001087",
        "tgn:7029392"
    ],
    "tgn:id":7531109,
    "tgn:name":"Tur'at Rumm\u0101nah",
    "tgn:placetype":[
        "aat:300006075"
    ]
},
  "bbox": [],
  "geometry": {"coordinates":[31.051478,30.227727],"type":"Point"}
}