{
  "id": 7256218,
  "type": "Feature",
  "properties": {
    "tgn:hierarchy":[
        "tgn:7256218",
        "tgn:7003461",
        "tgn:1000003",
        "tgn:1000063",
        "tgn:7018236",
        "tgn:7029392"
    ],
    "tgn:id":7256218,
    "tgn:name":"Wetsberg",
    "tgn:placetype":[
        "aat:300008777"
    ]
},
  "bbox": [],
  "geometry": {"coordinates":[5.05,51.066667],"type":"Point"}
}