{
  "id": 7421174,
  "type": "Feature",
  "properties": {
    "tgn:hierarchy":[
        "tgn:7421174",
        "tgn:7005584",
        "tgn:1000001",
        "tgn:7005560",
        "tgn:7029392"
    ],
    "tgn:id":7421174,
    "tgn:name":"La Trinidad",
    "tgn:placetype":[
        "aat:300008347"
    ]
},
  "bbox": [],
  "geometry": {"coordinates":[-101.4625,21.315],"type":"Point"}
}