{
  "id": 7327604,
  "type": "Feature",
  "properties": {
    "tgn:hierarchy":[
        "tgn:7327604",
        "tgn:7002804",
        "tgn:1000003",
        "tgn:7002793",
        "tgn:1000095",
        "tgn:7029392"
    ],
    "tgn:id":7327604,
    "tgn:name":"R\u00e1fol de Almunia",
    "tgn:placetype":[
        "aat:300008347"
    ]
},
  "bbox": [],
  "geometry": {"coordinates":[-0.05,38.816667],"type":"Point"}
}