{
  "id": 7548902,
  "type": "Feature",
  "properties": {
    "tgn:hierarchy":[
        "tgn:7548902",
        "tgn:1000004",
        "tgn:7000198",
        "tgn:1001886",
        "tgn:7029392"
    ],
    "tgn:id":7548902,
    "tgn:name:en":"Devikolam",
    "tgn:placetype":[
        "aat:300008347"
    ]
},
  "bbox": [],
  "geometry": {"coordinates":[77.083333,10.066667],"type":"Point"}
}