{
  "id": 2532991,
  "type": "Feature",
  "properties": {
    "tgn:hierarchy":[
        "tgn:2532991",
        "tgn:1000001",
        "tgn:7012149",
        "tgn:2000219",
        "tgn:7007158",
        "tgn:7029392"
    ],
    "tgn:id":2532991,
    "tgn:name":"Murray Reservoir",
    "tgn:placetype":[
        "aat:300006191"
    ]
},
  "bbox": [],
  "geometry": {"coordinates":[-105.3333,37.85],"type":"Point"}
}