{
  "id": 1073515,
  "type": "Feature",
  "properties": {
    "tgn:hierarchy":[
        "tgn:1073515",
        "tgn:1000004",
        "tgn:7002076",
        "tgn:1000111",
        "tgn:7029392"
    ],
    "tgn:id":1073515,
    "tgn:name":"Yigaolou",
    "tgn:placetype":[
        "aat:300008347"
    ]
},
  "bbox": [],
  "geometry": {"coordinates":[120.3167,30.9333],"type":"Point"}
}