<<<<<<< HEAD
{
  "id": 2254440,
  "type": "Feature",
  "properties": {
    "tgn:hierarchy":[
        "tgn:2254440",
        "tgn:1000001",
        "tgn:1002293",
        "tgn:7012149",
        "tgn:7007708",
        "tgn:7029392"
    ],
    "tgn:id":2254440,
    "tgn:name":"Coon Creek",
    "tgn:placetype":[
        "aat:300008706"
    ]
},
  "bbox": [],
  "geometry": {"coordinates":[-123.1333,45.8167],"type":"Point"}
}
=======
{"geometry":{"type":"Point","coordinates":[-123.133300,45.816700]},"type":"Feature","properties":{"hierarchy":["tgn:2254440","tgn:1000001","tgn:1002293","tgn:7012149","tgn:7007708","tgn:7029392"],"placetype":["aat:300008706"],"id":2254440,"name:xx":"Coon Creek"}}
>>>>>>> 03f74aca74312dbeaf24d7e61306dd6a786dc3d0
