{
  "id": 7011261,
  "type": "Feature",
  "properties": {
    "tgn:hierarchy":[
        "tgn:7011261",
        "tgn:7002445",
        "tgn:1000003",
        "tgn:7012032",
        "tgn:7008591",
        "tgn:7029392"
    ],
    "tgn:id":7011261,
    "tgn:name:en":"Wellington",
    "tgn:placetype":[
        "aat:300008347"
    ]
},
  "bbox": [],
  "geometry": {"coordinates":[-3.233333,50.983333],"type":"Point"}
}