{
  "id": 7515127,
  "type": "Feature",
  "properties": {
    "tgn:hierarchy":[
        "tgn:7515127",
        "tgn:1009227",
        "tgn:1000226",
        "tgn:1000006",
        "tgn:7016850",
        "tgn:7029392"
    ],
    "tgn:id":7515127,
    "tgn:name:en":"Cringe Creek",
    "tgn:placetype":[
        "aat:300008699"
    ]
},
  "bbox": [],
  "geometry": {"coordinates":[169.416667,-43.983333],"type":"Point"}
}