{
  "id": 1122980,
  "type": "Feature",
  "properties": {
    "tgn:hierarchy":[
        "tgn:1122980",
        "tgn:7006450",
        "tgn:1000001",
        "tgn:7012149",
        "tgn:7029392"
    ],
    "tgn:id":1122980,
    "tgn:name":"Coleen River",
    "tgn:placetype":[
        "aat:300008707"
    ]
},
  "bbox": [],
  "geometry": {"coordinates":[-142.491,67.072],"type":"Point"}
}