{
  "id": 7564387,
  "type": "Feature",
  "properties": {
    "tgn:hierarchy":[
        "tgn:7564387",
        "tgn:1000004",
        "tgn:7000198",
        "tgn:7016722",
        "tgn:7029392"
    ],
    "tgn:id":7564387,
    "tgn:name:en":"Jidepur",
    "tgn:placetype":[
        "aat:300008347"
    ]
},
  "bbox": [],
  "geometry": {"coordinates":[79.715596,26.965888],"type":"Point"}
}