<<<<<<< HEAD
{
  "id": 7059672,
  "type": "Feature",
  "properties": {
    "tgn:hierarchy":[
        "tgn:7059672",
        "tgn:1000003",
        "tgn:7000094",
        "tgn:7000084",
        "tgn:7029392"
    ],
    "tgn:id":7059672,
    "tgn:name":"Allerstorf",
    "tgn:placetype":[
        "aat:300008347"
    ]
},
  "bbox": [],
  "geometry": {"coordinates":[12.533333,54.183333],"type":"Point"}
}
=======
{"geometry":{"type":"Point","coordinates":[12.533333,54.183333]},"type":"Feature","properties":{"hierarchy":["tgn:7059672","tgn:1000003","tgn:7000094","tgn:7000084","tgn:7029392"],"placetype":["aat:300008347"],"id":7059672,"name:xx":"Allerstorf"}}
>>>>>>> 03f74aca74312dbeaf24d7e61306dd6a786dc3d0
