{
  "id": 1012284,
  "type": "Feature",
  "properties": {
    "tgn:hierarchy":[
        "tgn:1012284",
        "tgn:1006417",
        "tgn:7005685",
        "tgn:1000001",
        "tgn:1000296",
        "tgn:7029392"
    ],
    "tgn:id":1012284,
    "tgn:name":"Passage Point",
    "tgn:placetype":[
        "aat:300386846"
    ]
},
  "bbox": [],
  "geometry": {"coordinates":[-115.2833,73.4833],"type":"Point"}
}