{
  "id": 2069295,
  "type": "Feature",
  "properties": {
    "tgn:hierarchy":[
        "tgn:2069295",
        "tgn:1000001",
        "tgn:7012149",
        "tgn:7014287",
        "tgn:7007568",
        "tgn:7029392"
    ],
    "tgn:id":2069295,
    "tgn:name":"Frenchville",
    "tgn:placetype":[
        "aat:300008347"
    ]
},
  "bbox": [],
  "geometry": {"coordinates":[-75.35,43.3167],"type":"Point"}
}