{
  "id": 1031073,
  "type": "Feature",
  "properties": {
    "tgn:hierarchy":[
        "tgn:1031073",
        "tgn:7002445",
        "tgn:1000003",
        "tgn:7008175",
        "tgn:7008591",
        "tgn:7029392"
    ],
    "tgn:id":1031073,
    "tgn:name":"Westscott",
    "tgn:placetype":[
        "aat:300008347"
    ]
},
  "bbox": [],
  "geometry": {"coordinates":[-0.3667,51.2167],"type":"Point"}
}