{
  "id": 1101930,
  "type": "Feature",
  "properties": {
    "tgn:hierarchy":[
        "tgn:1101930",
        "tgn:7005135",
        "tgn:1000001",
        "tgn:7005118",
        "tgn:7029392"
    ],
    "tgn:id":1101930,
    "tgn:name":"Virgin Islands National Park",
    "tgn:placetype":[
        "aat:300008189"
    ]
},
  "bbox": [],
  "geometry": {"coordinates":[-64.7333,18.3333],"type":"Point"}
}