{
  "id": 7060296,
  "type": "Feature",
  "properties": {
    "tgn:hierarchy":[
        "tgn:7060296",
        "tgn:1000003",
        "tgn:7003688",
        "tgn:7000084",
        "tgn:7029392"
    ],
    "tgn:id":7060296,
    "tgn:name":"Altenfeldsdeich",
    "tgn:placetype":[
        "aat:300008347"
    ]
},
  "bbox": [],
  "geometry": {"coordinates":[9.55,53.716667],"type":"Point"}
}