{
  "id": 2168140,
  "type": "Feature",
  "properties": {
    "tgn:hierarchy":[
        "tgn:2168140",
        "tgn:1000001",
        "tgn:7016172",
        "tgn:7012149",
        "tgn:2000157",
        "tgn:7029392"
    ],
    "tgn:id":2168140,
    "tgn:name":"Big Fish Pond",
    "tgn:placetype":[
        "aat:300006191"
    ]
},
  "bbox": [],
  "geometry": {"coordinates":[-92.95,34.9667],"type":"Point"}
}