{
  "id": 2070008,
  "type": "Feature",
  "properties": {
    "tgn:hierarchy":[
        "tgn:2070008",
        "tgn:1000001",
        "tgn:7012149",
        "tgn:1002882",
        "tgn:7007568",
        "tgn:7029392"
    ],
    "tgn:id":2070008,
    "tgn:name":"Kidders",
    "tgn:placetype":[
        "aat:300008347"
    ]
},
  "bbox": [],
  "geometry": {"coordinates":[-76.6833,42.6333],"type":"Point"}
}