<<<<<<< HEAD
{
  "id": 7484051,
  "type": "Feature",
  "properties": {
    "tgn:hierarchy":[
        "tgn:7484051",
        "tgn:1000004",
        "tgn:7001009",
        "tgn:1000141",
        "tgn:7029392"
    ],
    "tgn:id":7484051,
    "tgn:name":"Menqiantian",
    "tgn:placetype":[
        "aat:300008347"
    ]
},
  "bbox": [],
  "geometry": {"coordinates":[120.709722,24.301389],"type":"Point"}
}
=======
{"geometry":{"type":"Point","coordinates":[120.709722,24.301389]},"type":"Feature","properties":{"hierarchy":["tgn:7484051","tgn:1000004","tgn:7001009","tgn:1000141","tgn:7029392"],"placetype":["aat:300008347"],"id":7484051,"name:xx":"Menqiantian"}}
>>>>>>> 03f74aca74312dbeaf24d7e61306dd6a786dc3d0
