{
  "id": 2179513,
  "type": "Feature",
  "properties": {
    "tgn:hierarchy":[
        "tgn:2179513",
        "tgn:1000001",
        "tgn:7012149",
        "tgn:2002005",
        "tgn:7007826",
        "tgn:7029392"
    ],
    "tgn:id":2179513,
    "tgn:name":"Blanco Draw",
    "tgn:placetype":[
        "aat:300008761"
    ]
},
  "bbox": [],
  "geometry": {"coordinates":[-105.3833,31.55],"type":"Point"}
}