{
  "id": 2224039,
  "type": "Feature",
  "properties": {
    "tgn:hierarchy":[
        "tgn:2224039",
        "tgn:1000001",
        "tgn:2001483",
        "tgn:7012149",
        "tgn:7007709",
        "tgn:7029392"
    ],
    "tgn:id":2224039,
    "tgn:name":"Carver Branch",
    "tgn:placetype":[
        "aat:300008699"
    ]
},
  "bbox": [],
  "geometry": {"coordinates":[-83.8667,35.05],"type":"Point"}
}