{
  "id": 2334643,
  "type": "Feature",
  "properties": {
    "tgn:hierarchy":[
        "tgn:2334643",
        "tgn:1000001",
        "tgn:7013686",
        "tgn:7012149",
        "tgn:7007517",
        "tgn:7029392"
    ],
    "tgn:id":2334643,
    "tgn:name":"Forge Pond",
    "tgn:placetype":[
        "aat:300006191"
    ]
},
  "bbox": [],
  "geometry": {"coordinates":[-72.4667,42.2667],"type":"Point"}
}