<<<<<<< HEAD
{
  "id": 2334643,
  "type": "Feature",
  "properties": {
    "tgn:hierarchy":[
        "tgn:2334643",
        "tgn:1000001",
        "tgn:7013686",
        "tgn:7012149",
        "tgn:7007517",
        "tgn:7029392"
    ],
    "tgn:id":2334643,
    "tgn:name":"Forge Pond",
    "tgn:placetype":[
        "aat:300006191"
    ]
},
  "bbox": [],
  "geometry": {"coordinates":[-72.4667,42.2667],"type":"Point"}
}
=======
{"geometry":{"type":"Point","coordinates":[-72.466700,42.266700]},"type":"Feature","properties":{"hierarchy":["tgn:2334643","tgn:1000001","tgn:7013686","tgn:7012149","tgn:7007517","tgn:7029392"],"placetype":["aat:300006191"],"id":2334643,"name:xx":"Forge Pond"}}
>>>>>>> 03f74aca74312dbeaf24d7e61306dd6a786dc3d0
