{
  "id": 1029878,
  "type": "Feature",
  "properties": {
    "tgn:hierarchy":[
        "tgn:1029878",
        "tgn:7002445",
        "tgn:1000003",
        "tgn:7008145",
        "tgn:7008591",
        "tgn:7029392"
    ],
    "tgn:id":1029878,
    "tgn:name:en":"London Colney",
    "tgn:placetype":[
        "aat:300008347"
    ]
},
  "bbox": [],
  "geometry": {"coordinates":[-0.283333,51.716667],"type":"Point"}
}