{
  "id": 7300873,
  "type": "Feature",
  "properties": {
    "tgn:hierarchy":[
        "tgn:7300873",
        "tgn:7002811",
        "tgn:1000003",
        "tgn:7003837",
        "tgn:1000095",
        "tgn:7029392"
    ],
    "tgn:id":7300873,
    "tgn:name":"Moraleja",
    "tgn:placetype":[
        "aat:300008347"
    ]
},
  "bbox": [],
  "geometry": {"coordinates":[-6.65,40.066667],"type":"Point"}
}