{
  "id": 2290003,
  "type": "Feature",
  "properties": {
    "tgn:hierarchy":[
        "tgn:2290003",
        "tgn:1000001",
        "tgn:7012149",
        "tgn:7029392"
    ],
    "tgn:id":2290003,
    "tgn:name":"Docs Pass Canyon",
    "tgn:placetype":[
        "aat:300008761"
    ]
},
  "bbox": [],
  "geometry": {"coordinates":[-114.0833,37.4333],"type":"Point"}
}