{
  "id": 7509266,
  "type": "Feature",
  "properties": {
    "tgn:hierarchy":[
        "tgn:7509266",
        "tgn:1009227",
        "tgn:1000226",
        "tgn:7520095",
        "tgn:1000006",
        "tgn:7029392"
    ],
    "tgn:id":7509266,
    "tgn:name:en":"Tidal Creek",
    "tgn:placetype":[
        "aat:300008699"
    ]
},
  "bbox": [],
  "geometry": {"coordinates":[172.083333,-41.383333],"type":"Point"}
}