{
  "id": 7439925,
  "type": "Feature",
  "properties": {
    "tgn:hierarchy":[
        "tgn:7439925",
        "tgn:1000001",
        "tgn:1001960",
        "tgn:7005560",
        "tgn:7029392"
    ],
    "tgn:id":7439925,
    "tgn:name":"Rancho San Mart\u00edn",
    "tgn:placetype":[
        "aat:300000241"
    ]
},
  "bbox": [],
  "geometry": {"coordinates":[-111.866667,30.566667],"type":"Point"}
}