{
  "id": 2735188,
  "type": "Feature",
  "properties": {
    "tgn:hierarchy":[
        "tgn:2735188",
        "tgn:1000001",
        "tgn:7012149",
        "tgn:7007157",
        "tgn:7029392"
    ],
    "tgn:id":2735188,
    "tgn:name":"Twentythree, Canyon",
    "tgn:placetype":[
        "aat:300008761"
    ]
},
  "bbox": [],
  "geometry": {"coordinates":[-120.0333,39.4667],"type":"Point"}
}