{
  "id": 7116985,
  "type": "Feature",
  "properties": {
    "tgn:hierarchy":[
        "tgn:7116985",
        "tgn:1000003",
        "tgn:7003678",
        "tgn:7000084",
        "tgn:7029392"
    ],
    "tgn:id":7116985,
    "tgn:name":"Oberthalhausen",
    "tgn:placetype":[
        "aat:300008347"
    ]
},
  "bbox": [],
  "geometry": {"coordinates":[9.616667,50.933333],"type":"Point"}
}