{
  "id": 2555393,
  "type": "Feature",
  "properties": {
    "tgn:hierarchy":[
        "tgn:2555393",
        "tgn:1000001",
        "tgn:2002259",
        "tgn:7012149",
        "tgn:7013961",
        "tgn:7029392"
    ],
    "tgn:id":2555393,
    "tgn:name":"Odessa",
    "tgn:placetype":[
        "aat:300008347"
    ]
},
  "bbox": [],
  "geometry": {"coordinates":[-81.2333,38.4167],"type":"Point"}
}