<<<<<<< HEAD
{
  "id": 7171244,
  "type": "Feature",
  "properties": {
    "tgn:hierarchy":[
        "tgn:7171244",
        "tgn:7003669",
        "tgn:1000003",
        "tgn:7000084",
        "tgn:7029392"
    ],
    "tgn:id":7171244,
    "tgn:name":"Hendungen",
    "tgn:placetype":[
        "aat:300008347"
    ]
},
  "bbox": [],
  "geometry": {"coordinates":[10.35,50.4],"type":"Point"}
}
=======
{"geometry":{"type":"Point","coordinates":[10.350000,50.400000]},"type":"Feature","properties":{"hierarchy":["tgn:7171244","tgn:7003669","tgn:1000003","tgn:7000084","tgn:7029392"],"placetype":["aat:300008347"],"id":7171244,"name:xx":"Hendungen"}}
>>>>>>> 03f74aca74312dbeaf24d7e61306dd6a786dc3d0
