{
  "id": 7462015,
  "type": "Feature",
  "properties": {
    "tgn:hierarchy":[
        "tgn:7462015",
        "tgn:7002444",
        "tgn:1000003",
        "tgn:7029508",
        "tgn:7008591",
        "tgn:7029392"
    ],
    "tgn:id":7462015,
    "tgn:name:en":"Hevdadale Head",
    "tgn:placetype":[
        "aat:300008850"
    ]
},
  "bbox": [],
  "geometry": {"coordinates":[-1.433333,60.583333],"type":"Point"}
}