<<<<<<< HEAD
{
  "id": 7356577,
  "type": "Feature",
  "properties": {
    "tgn:hierarchy":[
        "tgn:7356577",
        "tgn:7005586",
        "tgn:1000001",
        "tgn:7005560",
        "tgn:7029392"
    ],
    "tgn:id":7356577,
    "tgn:name":"Camich\u00edn",
    "tgn:placetype":[
        "aat:300008347"
    ]
},
  "bbox": [],
  "geometry": {"coordinates":[-104.033333,19.633333],"type":"Point"}
}
=======
{"geometry":{"type":"Point","coordinates":[-104.033333,19.633333]},"type":"Feature","properties":{"hierarchy":["tgn:7356577","tgn:7005586","tgn:1000001","tgn:7005560","tgn:7029392"],"placetype":["aat:300008347"],"id":7356577,"name:xx":"Camich\u00edn"}}
>>>>>>> 03f74aca74312dbeaf24d7e61306dd6a786dc3d0
