{
  "id": 7031855,
  "type": "Feature",
  "properties": {
    "tgn:hierarchy":[
        "tgn:7031855",
        "tgn:1000004",
        "tgn:7001535",
        "tgn:7000201",
        "tgn:7000198",
        "tgn:7029392"
    ],
    "tgn:id":7031855,
    "tgn:name:en":"Red Fort",
    "tgn:placetype":[
        "aat:300008090",
        "aat:300008347",
        "aat:300005734",
        "aat:300006909",
        "aat:300387291"
    ]
},
  "bbox": [],
  "geometry": {"coordinates":[77.233333,28.633333],"type":"Point"}
}