<<<<<<< HEAD
{
  "id": 7364390,
  "type": "Feature",
  "properties": {
    "tgn:hierarchy":[
        "tgn:7364390",
        "tgn:1000001",
        "tgn:7005590",
        "tgn:7005560",
        "tgn:7029392"
    ],
    "tgn:id":7364390,
    "tgn:name":"El C\u00f3bano",
    "tgn:placetype":[
        "aat:300008347"
    ]
},
  "bbox": [],
  "geometry": {"coordinates":[-102.0,19.15],"type":"Point"}
}
=======
{"geometry":{"type":"Point","coordinates":[-102.000000,19.150000]},"type":"Feature","properties":{"hierarchy":["tgn:7364390","tgn:1000001","tgn:7005590","tgn:7005560","tgn:7029392"],"placetype":["aat:300008347"],"id":7364390,"name:xx":"El C\u00f3bano"}}
>>>>>>> 03f74aca74312dbeaf24d7e61306dd6a786dc3d0
