{
  "id": 7221449,
  "type": "Feature",
  "properties": {
    "tgn:hierarchy":[
        "tgn:7221449",
        "tgn:7011161",
        "tgn:7002674",
        "tgn:1000003",
        "tgn:1000074",
        "tgn:7029392"
    ],
    "tgn:id":7221449,
    "tgn:name":"Vol\u00f3petres",
    "tgn:placetype":[
        "aat:300387200"
    ]
},
  "bbox": [],
  "geometry": {"coordinates":[25.8875,38.531389],"type":"Point"}
}