{
  "id": 7592064,
  "type": "Feature",
  "properties": {
    "tgn:hierarchy":[
        "tgn:7592064",
        "tgn:1000004",
        "tgn:7000198",
        "tgn:7000799",
        "tgn:7029392"
    ],
    "tgn:id":7592064,
    "tgn:name:en":"Tuk\u0101r",
    "tgn:placetype":[
        "aat:300008347"
    ]
},
  "bbox": [],
  "geometry": {"coordinates":[74.975,32.666667],"type":"Point"}
}