{
  "id": 2214563,
  "type": "Feature",
  "properties": {
    "tgn:hierarchy":[
        "tgn:2214563",
        "tgn:1000001",
        "tgn:7012149",
        "tgn:2001619",
        "tgn:7007706",
        "tgn:7029392"
    ],
    "tgn:id":2214563,
    "tgn:name":"Caldwell Lake",
    "tgn:placetype":[
        "aat:300006191"
    ]
},
  "bbox": [],
  "geometry": {"coordinates":[-81.5167,39.7667],"type":"Point"}
}