<<<<<<< HEAD
{
  "id": 7471866,
  "type": "Feature",
  "properties": {
    "tgn:hierarchy":[
        "tgn:7471866",
        "tgn:1000004",
        "tgn:7489179",
        "tgn:1000141",
        "tgn:7029392"
    ],
    "tgn:id":7471866,
    "tgn:name":"Wujie",
    "tgn:placetype":[
        "aat:300008347"
    ]
},
  "bbox": [],
  "geometry": {"coordinates":[121.798059,24.685589],"type":"Point"}
}
=======
{"geometry":{"type":"Point","coordinates":[121.798059,24.685589]},"type":"Feature","properties":{"hierarchy":["tgn:7471866","tgn:1000004","tgn:7489179","tgn:1000141","tgn:7029392"],"placetype":["aat:300008347"],"id":7471866,"name:xx":"Wujie"}}
>>>>>>> 03f74aca74312dbeaf24d7e61306dd6a786dc3d0
