{
  "id": 7147603,
  "type": "Feature",
  "properties": {
    "tgn:hierarchy":[
        "tgn:7147603",
        "tgn:1000003",
        "tgn:7003687",
        "tgn:7000084",
        "tgn:7029392"
    ],
    "tgn:id":7147603,
    "tgn:name":"Kr\u00e4hen-Berg",
    "tgn:placetype":[
        "aat:300008777"
    ]
},
  "bbox": [],
  "geometry": {"coordinates":[11.766667,51.816667],"type":"Point"}
}