{
  "id": 7390901,
  "type": "Feature",
  "properties": {
    "tgn:hierarchy":[
        "tgn:7390901",
        "tgn:1001853",
        "tgn:1000001",
        "tgn:7005560",
        "tgn:7029392"
    ],
    "tgn:id":7390901,
    "tgn:name":"San Alberto",
    "tgn:placetype":[
        "aat:300008347"
    ]
},
  "bbox": [],
  "geometry": {"coordinates":[-103.35,27.433333],"type":"Point"}
}