<<<<<<< HEAD
{
  "id": 7174689,
  "type": "Feature",
  "properties": {
    "tgn:hierarchy":[
        "tgn:7174689",
        "tgn:7003669",
        "tgn:1000003",
        "tgn:7000084",
        "tgn:7029392"
    ],
    "tgn:id":7174689,
    "tgn:name":"Gr\u00fcbesberg",
    "tgn:placetype":[
        "aat:300008777"
    ]
},
  "bbox": [],
  "geometry": {"coordinates":[10.6,49.35],"type":"Point"}
}
=======
{"geometry":{"type":"Point","coordinates":[10.600000,49.350000]},"type":"Feature","properties":{"hierarchy":["tgn:7174689","tgn:7003669","tgn:1000003","tgn:7000084","tgn:7029392"],"placetype":["aat:300008777"],"id":7174689,"name:xx":"Gr\u00fcbesberg"}}
>>>>>>> 03f74aca74312dbeaf24d7e61306dd6a786dc3d0
