{
  "id": 2231970,
  "type": "Feature",
  "properties": {
    "tgn:hierarchy":[
        "tgn:2231970",
        "tgn:1000001",
        "tgn:7012149",
        "tgn:7007566",
        "tgn:7029392"
    ],
    "tgn:id":2231970,
    "tgn:name":"Chamizal Creek",
    "tgn:placetype":[
        "aat:300008706"
    ]
},
  "bbox": [],
  "geometry": {"coordinates":[-105.65,36.05],"type":"Point"}
}