{
  "id": 2348541,
  "type": "Feature",
  "properties": {
    "tgn:hierarchy":[
        "tgn:2348541",
        "tgn:1000001",
        "tgn:7012149",
        "tgn:7007157",
        "tgn:1002675",
        "tgn:7029392"
    ],
    "tgn:id":2348541,
    "tgn:name":"Gibbs Lake",
    "tgn:placetype":[
        "aat:300008680"
    ]
},
  "bbox": [],
  "geometry": {"coordinates":[-119.1833,37.8833],"type":"Point"}
}