{
  "id": 2147334,
  "type": "Feature",
  "properties": {
    "tgn:hierarchy":[
        "tgn:2147334",
        "tgn:1000001",
        "tgn:7012149",
        "tgn:2002382",
        "tgn:7007923",
        "tgn:7029392"
    ],
    "tgn:id":2147334,
    "tgn:name":"Barbara Budd Ditch",
    "tgn:placetype":[
        "aat:300006075"
    ]
},
  "bbox": [],
  "geometry": {"coordinates":[-110.3667,42.5333],"type":"Point"}
}