{
  "id": 1037162,
  "type": "Feature",
  "properties": {
    "tgn:hierarchy":[
        "tgn:1037162",
        "tgn:1000003",
        "tgn:7003687",
        "tgn:7000084",
        "tgn:7029392"
    ],
    "tgn:id":1037162,
    "tgn:name":"Langeneichst\u00e4dt",
    "tgn:placetype":[
        "aat:300008347"
    ]
},
  "bbox": [],
  "geometry": {"coordinates":[11.75,51.35],"type":"Point"}
}