{
  "id": 2540645,
  "type": "Feature",
  "properties": {
    "tgn:hierarchy":[
        "tgn:2540645",
        "tgn:1000001",
        "tgn:7012149",
        "tgn:1002750",
        "tgn:7007252",
        "tgn:7029392"
    ],
    "tgn:id":2540645,
    "tgn:name":"Newton Stewart",
    "tgn:placetype":[
        "aat:300008347"
    ]
},
  "bbox": [],
  "geometry": {"coordinates":[-86.6167,38.3667],"type":"Point"}
}