{
  "id": 2276526,
  "type": "Feature",
  "properties": {
    "tgn:hierarchy":[
        "tgn:2276526",
        "tgn:1000001",
        "tgn:7012149",
        "tgn:2000406",
        "tgn:7007248",
        "tgn:7029392"
    ],
    "tgn:id":2276526,
    "tgn:name":"Davette Spring",
    "tgn:placetype":[
        "aat:300008697"
    ]
},
  "bbox": [],
  "geometry": {"coordinates":[-85.0333,34.0667],"type":"Point"}
}