{
  "id": 2473564,
  "type": "Feature",
  "properties": {
    "tgn:hierarchy":[
        "tgn:2473564",
        "tgn:1000001",
        "tgn:7012149",
        "tgn:2002270",
        "tgn:7013961",
        "tgn:7029392"
    ],
    "tgn:id":2473564,
    "tgn:name":"Lower Creek",
    "tgn:placetype":[
        "aat:300008706"
    ]
},
  "bbox": [],
  "geometry": {"coordinates":[-81.3667,38.1667],"type":"Point"}
}