{
  "id": 7515010,
  "type": "Feature",
  "properties": {
    "tgn:hierarchy":[
        "tgn:7515010",
        "tgn:1009227",
        "tgn:7001866",
        "tgn:1000226",
        "tgn:1000006",
        "tgn:7029392"
    ],
    "tgn:id":7515010,
    "tgn:name:en":"Carn Brea",
    "tgn:placetype":[
        "aat:300008798"
    ]
},
  "bbox": [],
  "geometry": {"coordinates":[171.65,-43.233333],"type":"Point"}
}