{
  "id": 7500345,
  "type": "Feature",
  "properties": {
    "tgn:hierarchy":[
        "tgn:7500345",
        "tgn:7001004",
        "tgn:1000004",
        "tgn:1000141",
        "tgn:7029392"
    ],
    "tgn:id":7500345,
    "tgn:name":"Jixiang Erhao Qiao",
    "tgn:placetype":[
        "aat:300007836"
    ]
},
  "bbox": [],
  "geometry": {"coordinates":[120.505278,22.852222],"type":"Point"}
}