{
  "id": 7285082,
  "type": "Feature",
  "properties": {
    "tgn:hierarchy":[
        "tgn:7285082",
        "tgn:1001699",
        "tgn:1000049",
        "tgn:1000002",
        "tgn:7029392"
    ],
    "tgn:id":7285082,
    "tgn:name":"Puerto Nuevo",
    "tgn:placetype":[
        "aat:300000206"
    ]
},
  "bbox": [],
  "geometry": {"coordinates":[-72.583333,-40.25],"type":"Point"}
}