{
  "id": 2602201,
  "type": "Feature",
  "properties": {
    "tgn:hierarchy":[
        "tgn:2602201",
        "tgn:1002648",
        "tgn:1000001",
        "tgn:1007799",
        "tgn:7012149",
        "tgn:7007249",
        "tgn:7029392"
    ],
    "tgn:id":2602201,
    "tgn:name":"Puualealea",
    "tgn:placetype":[
        "aat:300008798"
    ]
},
  "bbox": [],
  "geometry": {"coordinates":[-156.9167,20.85],"type":"Point"}
}