{
  "id": 1014549,
  "type": "Feature",
  "properties": {
    "tgn:hierarchy":[
        "tgn:1014549",
        "tgn:7005685",
        "tgn:1000001",
        "tgn:7013154",
        "tgn:7029392"
    ],
    "tgn:id":1014549,
    "tgn:name":"Alton",
    "tgn:placetype":[
        "aat:300008347"
    ]
},
  "bbox": [],
  "geometry": {"coordinates":[-80.0667,43.8667],"type":"Point"}
}