{
  "id": 2527871,
  "type": "Feature",
  "properties": {
    "tgn:hierarchy":[
        "tgn:2527871",
        "tgn:7002659",
        "tgn:1000001",
        "tgn:7012149",
        "tgn:2000036",
        "tgn:7029392"
    ],
    "tgn:id":2527871,
    "tgn:name":"Mountain Lake",
    "tgn:placetype":[
        "aat:300006191"
    ]
},
  "bbox": [],
  "geometry": {"coordinates":[-86.6167,33.5833],"type":"Point"}
}