{
  "id": 2457114,
  "type": "Feature",
  "properties": {
    "tgn:hierarchy":[
        "tgn:2457114",
        "tgn:1000001",
        "tgn:7012149",
        "tgn:2001067",
        "tgn:7007521",
        "tgn:7029392"
    ],
    "tgn:id":2457114,
    "tgn:name":"Little Lake",
    "tgn:placetype":[
        "aat:300008680"
    ]
},
  "bbox": [],
  "geometry": {"coordinates":[-92.3333,47.3333],"type":"Point"}
}