{
  "id": 2418921,
  "type": "Feature",
  "properties": {
    "tgn:hierarchy":[
        "tgn:2418921",
        "tgn:1000001",
        "tgn:7012149",
        "tgn:2002294",
        "tgn:7013961",
        "tgn:7029392"
    ],
    "tgn:id":2418921,
    "tgn:name":"James Harless Spring",
    "tgn:placetype":[
        "aat:300008697"
    ]
},
  "bbox": [],
  "geometry": {"coordinates":[-80.7667,37.8167],"type":"Point"}
}