<<<<<<< HEAD
{
  "id": 2337588,
  "type": "Feature",
  "properties": {
    "tgn:hierarchy":[
        "tgn:2337588",
        "tgn:1000001",
        "tgn:7012149",
        "tgn:2000414",
        "tgn:7007248",
        "tgn:7029392"
    ],
    "tgn:id":2337588,
    "tgn:name":"Fox Branch",
    "tgn:placetype":[
        "aat:300008699"
    ]
},
  "bbox": [],
  "geometry": {"coordinates":[-84.3667,32.2833],"type":"Point"}
}
=======
{"geometry":{"type":"Point","coordinates":[-84.366700,32.283300]},"type":"Feature","properties":{"hierarchy":["tgn:2337588","tgn:1000001","tgn:7012149","tgn:2000414","tgn:7007248","tgn:7029392"],"placetype":["aat:300008699"],"id":2337588,"name:xx":"Fox Branch"}}
>>>>>>> 03f74aca74312dbeaf24d7e61306dd6a786dc3d0
