{
  "id": 2467275,
  "type": "Feature",
  "properties": {
    "tgn:hierarchy":[
        "tgn:2467275",
        "tgn:1000001",
        "tgn:7006451",
        "tgn:2000092",
        "tgn:7012149",
        "tgn:7029392"
    ],
    "tgn:id":2467275,
    "tgn:name":"Long Draw Water Catchment",
    "tgn:placetype":[
        "aat:300386845"
    ]
},
  "bbox": [],
  "geometry": {"coordinates":[-110.85,34.4833],"type":"Point"}
}