{
  "id": 2619499,
  "type": "Feature",
  "properties": {
    "tgn:hierarchy":[
        "tgn:2619499",
        "tgn:1000001",
        "tgn:7012149",
        "tgn:7007157",
        "tgn:7029392"
    ],
    "tgn:id":2619499,
    "tgn:name":"Rincon Creek",
    "tgn:placetype":[
        "aat:300008706"
    ]
},
  "bbox": [],
  "geometry": {"coordinates":[-119.4333,34.4667],"type":"Point"}
}