{
  "id": 2708039,
  "type": "Feature",
  "properties": {
    "tgn:hierarchy":[
        "tgn:2708039",
        "tgn:1000001",
        "tgn:7012149",
        "tgn:7007522",
        "tgn:7029392"
    ],
    "tgn:id":2708039,
    "tgn:name":"Swilley Branch",
    "tgn:placetype":[
        "aat:300008699"
    ]
},
  "bbox": [],
  "geometry": {"coordinates":[-90.2167,31.7333],"type":"Point"}
}