{
  "id": 7591364,
  "type": "Feature",
  "properties": {
    "tgn:hierarchy":[
        "tgn:7591364",
        "tgn:1000004",
        "tgn:7000198",
        "tgn:7000799",
        "tgn:7029392"
    ],
    "tgn:id":7591364,
    "tgn:name:en":"Ratn\u0101l",
    "tgn:placetype":[
        "aat:300008347"
    ]
},
  "bbox": [],
  "geometry": {"coordinates":[74.894675,32.589865],"type":"Point"}
}