{
  "id": 7172564,
  "type": "Feature",
  "properties": {
    "tgn:hierarchy":[
        "tgn:7172564",
        "tgn:1000003",
        "tgn:7003682",
        "tgn:7000084",
        "tgn:7029392"
    ],
    "tgn:id":7172564,
    "tgn:name":"Herrchen-Berg",
    "tgn:placetype":[
        "aat:300008777"
    ]
},
  "bbox": [],
  "geometry": {"coordinates":[7.416667,54.533333],"type":"Point"}
}