{
  "id": 1065669,
  "type": "Feature",
  "properties": {
    "tgn:hierarchy":[
        "tgn:1065669",
        "tgn:1000004",
        "tgn:7000190",
        "tgn:1000105",
        "tgn:7029392"
    ],
    "tgn:id":1065669,
    "tgn:name":"Dasmina",
    "tgn:placetype":[
        "aat:300008347"
    ]
},
  "bbox": [],
  "geometry": {"coordinates":[90.5833,22.2833],"type":"Point"}
}