<<<<<<< HEAD
{
  "id": 7364512,
  "type": "Feature",
  "properties": {
    "tgn:hierarchy":[
        "tgn:7364512",
        "tgn:1000001",
        "tgn:7005597",
        "tgn:7005560",
        "tgn:7029392"
    ],
    "tgn:id":7364512,
    "tgn:name":"Rancho El Yaral",
    "tgn:placetype":[
        "aat:300000241"
    ]
},
  "bbox": [],
  "geometry": {"coordinates":[-99.75,27.5],"type":"Point"}
}
=======
{"geometry":{"type":"Point","coordinates":[-99.750000,27.500000]},"type":"Feature","properties":{"hierarchy":["tgn:7364512","tgn:1000001","tgn:7005597","tgn:7005560","tgn:7029392"],"placetype":["aat:300000241"],"id":7364512,"name:xx":"Rancho El Yaral"}}
>>>>>>> 03f74aca74312dbeaf24d7e61306dd6a786dc3d0
