{
  "id": 2771337,
  "type": "Feature",
  "properties": {
    "tgn:hierarchy":[
        "tgn:2771337",
        "tgn:1000001",
        "tgn:7012149",
        "tgn:7029392"
    ],
    "tgn:id":2771337,
    "tgn:name":"Wilder Creek",
    "tgn:placetype":[
        "aat:300008706"
    ]
},
  "bbox": [],
  "geometry": {"coordinates":[-118.4333,41.8667],"type":"Point"}
}