<<<<<<< HEAD
{
  "id": 7051672,
  "type": "Feature",
  "properties": {
    "tgn:hierarchy":[
        "tgn:7051672",
        "tgn:7003006",
        "tgn:1000003",
        "tgn:7002997",
        "tgn:1000080",
        "tgn:7029392"
    ],
    "tgn:id":7051672,
    "tgn:name":"Marghera, Porto",
    "tgn:placetype":[
        "aat:300008678"
    ]
},
  "bbox": [],
  "geometry": {"coordinates":[12.233333,45.466667],"type":"Point"}
}
=======
{"geometry":{"type":"Point","coordinates":[12.233333,45.466667]},"type":"Feature","properties":{"hierarchy":["tgn:7051672","tgn:7003006","tgn:1000003","tgn:7002997","tgn:1000080","tgn:7029392"],"placetype":["aat:300008678"],"id":7051672,"name:xx":"Marghera, Porto"}}
>>>>>>> 03f74aca74312dbeaf24d7e61306dd6a786dc3d0
