<<<<<<< HEAD
{
  "id": 7352847,
  "type": "Feature",
  "properties": {
    "tgn:hierarchy":[
        "tgn:7352847",
        "tgn:1000001",
        "tgn:7005593",
        "tgn:7005560",
        "tgn:7029392"
    ],
    "tgn:id":7352847,
    "tgn:name":"Buena Vista",
    "tgn:placetype":[
        "aat:300008347"
    ]
},
  "bbox": [],
  "geometry": {"coordinates":[-100.283333,20.65],"type":"Point"}
}
=======
{"geometry":{"type":"Point","coordinates":[-100.283333,20.650000]},"type":"Feature","properties":{"hierarchy":["tgn:7352847","tgn:1000001","tgn:7005593","tgn:7005560","tgn:7029392"],"placetype":["aat:300008347"],"id":7352847,"name:xx":"Buena Vista"}}
>>>>>>> 03f74aca74312dbeaf24d7e61306dd6a786dc3d0
