{
  "id": 7510993,
  "type": "Feature",
  "properties": {
    "tgn:hierarchy":[
        "tgn:7510993",
        "tgn:1008380",
        "tgn:7000507",
        "tgn:1000226",
        "tgn:1000006",
        "tgn:7029392"
    ],
    "tgn:id":7510993,
    "tgn:name:en":"Tauroa",
    "tgn:placetype":[
        "aat:300008795"
    ]
},
  "bbox": [],
  "geometry": {"coordinates":[174.083333,-35.883333],"type":"Point"}
}