{
  "id": 7316152,
  "type": "Feature",
  "properties": {
    "tgn:hierarchy":[
        "tgn:7316152",
        "tgn:1001699",
        "tgn:1000049",
        "tgn:1000002",
        "tgn:7029392"
    ],
    "tgn:id":7316152,
    "tgn:name":"Isla Caucahu\u00e9",
    "tgn:placetype":[
        "aat:300008791"
    ]
},
  "bbox": [],
  "geometry": {"coordinates":[-73.390833,-42.14],"type":"Point"}
}