{
  "id": 6006371,
  "type": "Feature",
  "properties": {
    "tgn:hierarchy":[
        "tgn:6006371",
        "tgn:7002445",
        "tgn:1000003",
        "tgn:7012034",
        "tgn:7008591",
        "tgn:7029392"
    ],
    "tgn:id":6006371,
    "tgn:name:en":"Wroxeter",
    "tgn:placetype":[
        "aat:300008347",
        "aat:300387218",
        "aat:300008375"
    ]
},
  "bbox": [],
  "geometry": {"coordinates":[-2.65,52.666667],"type":"Point"}
}