<<<<<<< HEAD
{
  "id": 2402631,
  "type": "Feature",
  "properties": {
    "tgn:hierarchy":[
        "tgn:2402631",
        "tgn:1000001",
        "tgn:2001418",
        "tgn:7012149",
        "tgn:7007526",
        "tgn:7029392"
    ],
    "tgn:id":2402631,
    "tgn:name":"Hot Creek Butte",
    "tgn:placetype":[
        "aat:300008798"
    ]
},
  "bbox": [],
  "geometry": {"coordinates":[-115.15,38.3667],"type":"Point"}
}
=======
{"geometry":{"type":"Point","coordinates":[-115.150000,38.366700]},"type":"Feature","properties":{"hierarchy":["tgn:2402631","tgn:1000001","tgn:2001418","tgn:7012149","tgn:7007526","tgn:7029392"],"placetype":["aat:300008798"],"id":2402631,"name:xx":"Hot Creek Butte"}}
>>>>>>> 03f74aca74312dbeaf24d7e61306dd6a786dc3d0
