<<<<<<< HEAD
{
  "id": 7170936,
  "type": "Feature",
  "properties": {
    "tgn:hierarchy":[
        "tgn:7170936",
        "tgn:1000003",
        "tgn:7003687",
        "tgn:7000084",
        "tgn:7029392"
    ],
    "tgn:id":7170936,
    "tgn:name":"Herzwinkel",
    "tgn:placetype":[
        "aat:300008863"
    ]
},
  "bbox": [],
  "geometry": {"coordinates":[12.2,51.966667],"type":"Point"}
}
=======
{"geometry":{"type":"Point","coordinates":[12.200000,51.966667]},"type":"Feature","properties":{"hierarchy":["tgn:7170936","tgn:1000003","tgn:7003687","tgn:7000084","tgn:7029392"],"placetype":["aat:300008863"],"id":7170936,"name:xx":"Herzwinkel"}}
>>>>>>> 03f74aca74312dbeaf24d7e61306dd6a786dc3d0
