<<<<<<< HEAD
{
  "id": 7357908,
  "type": "Feature",
  "properties": {
    "tgn:hierarchy":[
        "tgn:7357908",
        "tgn:1001853",
        "tgn:1000001",
        "tgn:7005560",
        "tgn:7029392"
    ],
    "tgn:id":7357908,
    "tgn:name":"Rancho de la Curva",
    "tgn:placetype":[
        "aat:300000241"
    ]
},
  "bbox": [],
  "geometry": {"coordinates":[-101.1,25.15],"type":"Point"}
}
=======
{"geometry":{"type":"Point","coordinates":[-101.100000,25.150000]},"type":"Feature","properties":{"hierarchy":["tgn:7357908","tgn:1001853","tgn:1000001","tgn:7005560","tgn:7029392"],"placetype":["aat:300000241"],"id":7357908,"name:xx":"Rancho de la Curva"}}
>>>>>>> 03f74aca74312dbeaf24d7e61306dd6a786dc3d0
