{
  "id": 7032276,
  "type": "Feature",
  "properties": {
    "tgn:hierarchy":[
        "tgn:7032276",
        "tgn:7001680",
        "tgn:7001242",
        "tgn:1000184",
        "tgn:7029392"
    ],
    "tgn:id":7032276,
    "tgn:name:fr":"Cambuston",
    "tgn:placetype":[
        "aat:300008347"
    ]
},
  "bbox": [],
  "geometry": {"coordinates":[55.65,-20.9166],"type":"Point"}
}