<<<<<<< HEAD
{
  "id": 2339829,
  "type": "Feature",
  "properties": {
    "tgn:hierarchy":[
        "tgn:2339829",
        "tgn:1000001",
        "tgn:7012149",
        "tgn:2000418",
        "tgn:7007248",
        "tgn:7029392"
    ],
    "tgn:id":2339829,
    "tgn:name":"Freeman Creek",
    "tgn:placetype":[
        "aat:300008706"
    ]
},
  "bbox": [],
  "geometry": {"coordinates":[-83.3167,34.5333],"type":"Point"}
}
=======
{"geometry":{"type":"Point","coordinates":[-83.316700,34.533300]},"type":"Feature","properties":{"hierarchy":["tgn:2339829","tgn:1000001","tgn:7012149","tgn:2000418","tgn:7007248","tgn:7029392"],"placetype":["aat:300008706"],"id":2339829,"name:xx":"Freeman Creek"}}
>>>>>>> 03f74aca74312dbeaf24d7e61306dd6a786dc3d0
