<<<<<<< HEAD
{
  "id": 7376047,
  "type": "Feature",
  "properties": {
    "tgn:hierarchy":[
        "tgn:7376047",
        "tgn:7005583",
        "tgn:1000001",
        "tgn:7005560",
        "tgn:7029392"
    ],
    "tgn:id":7376047,
    "tgn:name":"Llano Grande",
    "tgn:placetype":[
        "aat:300008347"
    ]
},
  "bbox": [],
  "geometry": {"coordinates":[-105.2,23.866667],"type":"Point"}
}
=======
{"geometry":{"type":"Point","coordinates":[-105.200000,23.866667]},"type":"Feature","properties":{"hierarchy":["tgn:7376047","tgn:7005583","tgn:1000001","tgn:7005560","tgn:7029392"],"placetype":["aat:300008347"],"id":7376047,"name:xx":"Llano Grande"}}
>>>>>>> 03f74aca74312dbeaf24d7e61306dd6a786dc3d0
