{
  "id": 2295195,
  "type": "Feature",
  "properties": {
    "tgn:hierarchy":[
        "tgn:2295195",
        "tgn:1000001",
        "tgn:7012149",
        "tgn:1002682",
        "tgn:7007710",
        "tgn:7029392"
    ],
    "tgn:id":2295195,
    "tgn:name":"Dresser Hill",
    "tgn:placetype":[
        "aat:300008798"
    ]
},
  "bbox": [],
  "geometry": {"coordinates":[-75.35,41.2167],"type":"Point"}
}