{
  "id": 7581819,
  "type": "Feature",
  "properties": {
    "tgn:hierarchy":[
        "tgn:7581819",
        "tgn:1000004",
        "tgn:7000198",
        "tgn:7031783",
        "tgn:7029392"
    ],
    "tgn:id":7581819,
    "tgn:name:en":"Singarsi Peak",
    "tgn:placetype":[
        "aat:300008798"
    ]
},
  "bbox": [],
  "geometry": {"coordinates":[87.466667,24.633333],"type":"Point"}
}