{
  "id": 2613526,
  "type": "Feature",
  "properties": {
    "tgn:hierarchy":[
        "tgn:2613526",
        "tgn:1000001",
        "tgn:7012149",
        "tgn:7007157",
        "tgn:1002828",
        "tgn:7029392"
    ],
    "tgn:id":2613526,
    "tgn:name":"Reed Valley",
    "tgn:placetype":[
        "aat:300008761"
    ]
},
  "bbox": [],
  "geometry": {"coordinates":[-116.8333,33.6167],"type":"Point"}
}