{
  "id": 2511039,
  "type": "Feature",
  "properties": {
    "tgn:hierarchy":[
        "tgn:2511039",
        "tgn:1000001",
        "tgn:7012149",
        "tgn:1002612",
        "tgn:7007710",
        "tgn:7029392"
    ],
    "tgn:id":2511039,
    "tgn:name":"Midway Crevasse",
    "tgn:placetype":[
        "aat:300008761"
    ]
},
  "bbox": [],
  "geometry": {"coordinates":[-76.2667,41.3167],"type":"Point"}
}