<<<<<<< HEAD
{
  "id": 7377101,
  "type": "Feature",
  "properties": {
    "tgn:hierarchy":[
        "tgn:7377101",
        "tgn:7005581",
        "tgn:1000001",
        "tgn:7005560",
        "tgn:7029392"
    ],
    "tgn:id":7377101,
    "tgn:name":"La Pe\u00f1ita",
    "tgn:placetype":[
        "aat:300008347"
    ]
},
  "bbox": [],
  "geometry": {"coordinates":[-107.7,29.483333],"type":"Point"}
}
=======
{"geometry":{"type":"Point","coordinates":[-107.700000,29.483333]},"type":"Feature","properties":{"hierarchy":["tgn:7377101","tgn:7005581","tgn:1000001","tgn:7005560","tgn:7029392"],"placetype":["aat:300008347"],"id":7377101,"name:xx":"La Pe\u00f1ita"}}
>>>>>>> 03f74aca74312dbeaf24d7e61306dd6a786dc3d0
