{
  "id": 2147432,
  "type": "Feature",
  "properties": {
    "tgn:hierarchy":[
        "tgn:2147432",
        "tgn:1000001",
        "tgn:7012149",
        "tgn:2000627",
        "tgn:7007253",
        "tgn:7029392"
    ],
    "tgn:id":2147432,
    "tgn:name":"Barber Creek",
    "tgn:placetype":[
        "aat:300008706"
    ]
},
  "bbox": [],
  "geometry": {"coordinates":[-95.8833,42.1833],"type":"Point"}
}