{
  "id": 2133470,
  "type": "Feature",
  "properties": {
    "tgn:hierarchy":[
        "tgn:2133470",
        "tgn:1000001",
        "tgn:7012149",
        "tgn:1002447",
        "tgn:7007252",
        "tgn:7029392"
    ],
    "tgn:id":2133470,
    "tgn:name":"Andis Ditch",
    "tgn:placetype":[
        "aat:300006075"
    ]
},
  "bbox": [],
  "geometry": {"coordinates":[-85.75,39.7167],"type":"Point"}
}