{
  "id": 2190622,
  "type": "Feature",
  "properties": {
    "tgn:hierarchy":[
        "tgn:2190622",
        "tgn:1000001",
        "tgn:7012149",
        "tgn:2002383",
        "tgn:7007923",
        "tgn:7029392"
    ],
    "tgn:id":2190622,
    "tgn:name":"Box Spring Reservoir",
    "tgn:placetype":[
        "aat:300006191"
    ]
},
  "bbox": [],
  "geometry": {"coordinates":[-109.9667,41.1667],"type":"Point"}
}