{
  "id": 7591788,
  "type": "Feature",
  "properties": {
    "tgn:hierarchy":[
        "tgn:7591788",
        "tgn:1000004",
        "tgn:7000198",
        "tgn:7000799",
        "tgn:7029392"
    ],
    "tgn:id":7591788,
    "tgn:name:en":"Sikligar Kali\u0101n",
    "tgn:placetype":[
        "aat:300008347"
    ]
},
  "bbox": [],
  "geometry": {"coordinates":[74.841667,32.675],"type":"Point"}
}