{
  "id": 7549557,
  "type": "Feature",
  "properties": {
    "tgn:hierarchy":[
        "tgn:7549557",
        "tgn:1000004",
        "tgn:7000198",
        "tgn:1001894",
        "tgn:7029392"
    ],
    "tgn:id":7549557,
    "tgn:name:en":"Chambla Nad\u012b",
    "tgn:placetype":[
        "aat:300008699"
    ]
},
  "bbox": [],
  "geometry": {"coordinates":[75.419743,23.356043],"type":"Point"}
}