{
  "id": 7569152,
  "type": "Feature",
  "properties": {
    "tgn:hierarchy":[
        "tgn:7569152",
        "tgn:1000004",
        "tgn:7000198",
        "tgn:7016788",
        "tgn:7029392"
    ],
    "tgn:id":7569152,
    "tgn:name:en":"Jori",
    "tgn:placetype":[
        "aat:300008347"
    ]
},
  "bbox": [],
  "geometry": {"coordinates":[74.929226,28.539162],"type":"Point"}
}