{
  "id": 7486479,
  "type": "Feature",
  "properties": {
    "tgn:hierarchy":[
        "tgn:7486479",
        "tgn:1000004",
        "tgn:7489179",
        "tgn:1000141",
        "tgn:7029392"
    ],
    "tgn:id":7486479,
    "tgn:name":"Xiao'ao",
    "tgn:placetype":[
        "aat:300008347"
    ]
},
  "bbox": [],
  "geometry": {"coordinates":[121.848889,24.889167],"type":"Point"}
}