<<<<<<< HEAD
{
  "id": 7366071,
  "type": "Feature",
  "properties": {
    "tgn:hierarchy":[
        "tgn:7366071",
        "tgn:1000001",
        "tgn:7005590",
        "tgn:7005560",
        "tgn:7029392"
    ],
    "tgn:id":7366071,
    "tgn:name":"Gallinas",
    "tgn:placetype":[
        "aat:300000241"
    ]
},
  "bbox": [],
  "geometry": {"coordinates":[-102.116667,20.066667],"type":"Point"}
}
=======
{"geometry":{"type":"Point","coordinates":[-102.116667,20.066667]},"type":"Feature","properties":{"hierarchy":["tgn:7366071","tgn:1000001","tgn:7005590","tgn:7005560","tgn:7029392"],"placetype":["aat:300000241"],"id":7366071,"name:xx":"Gallinas"}}
>>>>>>> 03f74aca74312dbeaf24d7e61306dd6a786dc3d0
