{
  "id": 2509567,
  "type": "Feature",
  "properties": {
    "tgn:hierarchy":[
        "tgn:2509567",
        "tgn:1000001",
        "tgn:7012149",
        "tgn:2002164",
        "tgn:7007919",
        "tgn:7029392"
    ],
    "tgn:id":2509567,
    "tgn:name":"Middle Fox Creek",
    "tgn:placetype":[
        "aat:300008706"
    ]
},
  "bbox": [],
  "geometry": {"coordinates":[-81.2833,36.7333],"type":"Point"}
}