{
  "id": 1040616,
  "type": "Feature",
  "properties": {
    "tgn:hierarchy":[
        "tgn:1040616",
        "tgn:1000003",
        "tgn:7003677",
        "tgn:7000084",
        "tgn:7029392"
    ],
    "tgn:id":1040616,
    "tgn:name":"Oestrich",
    "tgn:placetype":[
        "aat:300008347"
    ]
},
  "bbox": [],
  "geometry": {"coordinates":[7.6333,51.3667],"type":"Point"}
}