{
  "id": 2586602,
  "type": "Feature",
  "properties": {
    "tgn:hierarchy":[
        "tgn:2586602",
        "tgn:1000001",
        "tgn:2001590",
        "tgn:7012149",
        "tgn:7007705",
        "tgn:7029392"
    ],
    "tgn:id":2586602,
    "tgn:name":"Pittsburgh",
    "tgn:placetype":[
        "aat:300008347"
    ]
},
  "bbox": [],
  "geometry": {"coordinates":[-97.1667,48.6167],"type":"Point"}
}