{
  "id": 2617055,
  "type": "Feature",
  "properties": {
    "tgn:hierarchy":[
        "tgn:2617055",
        "tgn:1000001",
        "tgn:7012149",
        "tgn:1002862",
        "tgn:7007920",
        "tgn:7029392"
    ],
    "tgn:id":2617055,
    "tgn:name":"Richardson",
    "tgn:placetype":[
        "aat:300008347"
    ]
},
  "bbox": [],
  "geometry": {"coordinates":[-122.8833,48.45],"type":"Point"}
}