{
  "id": 2101245,
  "type": "Feature",
  "properties": {
    "tgn:hierarchy":[
        "tgn:2101245",
        "tgn:1000001",
        "tgn:7012149",
        "tgn:2001849",
        "tgn:7007825",
        "tgn:7029392"
    ],
    "tgn:id":2101245,
    "tgn:name":"Ritchie",
    "tgn:placetype":[
        "aat:300008347",
        "aat:300387210"
    ]
},
  "bbox": [],
  "geometry": {"coordinates":[-83.4667,36.4667],"type":"Point"}
}