{
  "id": 2434380,
  "type": "Feature",
  "properties": {
    "tgn:hierarchy":[
        "tgn:2434380",
        "tgn:1000001",
        "tgn:7012149",
        "tgn:2001711",
        "tgn:7007708",
        "tgn:7029392"
    ],
    "tgn:id":2434380,
    "tgn:name":"Kendall Slough",
    "tgn:placetype":[
        "aat:300008680"
    ]
},
  "bbox": [],
  "geometry": {"coordinates":[-122.9333,42.4333],"type":"Point"}
}