{
  "id": 7317849,
  "type": "Feature",
  "properties": {
    "tgn:hierarchy":[
        "tgn:7317849",
        "tgn:1001657",
        "tgn:1000049",
        "tgn:1000002",
        "tgn:7029392"
    ],
    "tgn:id":7317849,
    "tgn:name":"Cortadera, Quebrada",
    "tgn:placetype":[
        "aat:300008699"
    ]
},
  "bbox": [],
  "geometry": {"coordinates":[-71.05,-29.283333],"type":"Point"}
}