{
  "id": 2421127,
  "type": "Feature",
  "properties": {
    "tgn:hierarchy":[
        "tgn:2421127",
        "tgn:7014010",
        "tgn:1000001",
        "tgn:1002344",
        "tgn:7012149",
        "tgn:7007517",
        "tgn:7029392"
    ],
    "tgn:id":2421127,
    "tgn:name":"Jernegan Pond",
    "tgn:placetype":[
        "aat:300008680"
    ]
},
  "bbox": [],
  "geometry": {"coordinates":[-70.5333,41.3833],"type":"Point"}
}