{
  "id": 2262325,
  "type": "Feature",
  "properties": {
    "tgn:hierarchy":[
        "tgn:2262325",
        "tgn:1000001",
        "tgn:7012149",
        "tgn:2002375",
        "tgn:7007923",
        "tgn:7029392"
    ],
    "tgn:id":2262325,
    "tgn:name":"Cow Creek",
    "tgn:placetype":[
        "aat:300008706"
    ]
},
  "bbox": [],
  "geometry": {"coordinates":[-104.4833,41.45],"type":"Point"}
}