{
  "id": 2503908,
  "type": "Feature",
  "properties": {
    "tgn:hierarchy":[
        "tgn:2503908",
        "tgn:1000001",
        "tgn:7012149",
        "tgn:1002795",
        "tgn:7007826",
        "tgn:7029392"
    ],
    "tgn:id":2503908,
    "tgn:name":"Meadow Creek",
    "tgn:placetype":[
        "aat:300008706"
    ]
},
  "bbox": [],
  "geometry": {"coordinates":[-94.9333,30.9333],"type":"Point"}
}