{
  "id": 2383677,
  "type": "Feature",
  "properties": {
    "tgn:hierarchy":[
        "tgn:2383677",
        "tgn:1000001",
        "tgn:1002282",
        "tgn:7012149",
        "tgn:7007252",
        "tgn:7029392"
    ],
    "tgn:id":2383677,
    "tgn:name":"Heavilon Ditch",
    "tgn:placetype":[
        "aat:300006075"
    ]
},
  "bbox": [],
  "geometry": {"coordinates":[-86.5667,40.2833],"type":"Point"}
}