{
  "id": 7496305,
  "type": "Feature",
  "properties": {
    "tgn:hierarchy":[
        "tgn:7496305",
        "tgn:7001004",
        "tgn:1000004",
        "tgn:1000141",
        "tgn:7029392"
    ],
    "tgn:id":7496305,
    "tgn:name":"Cukeng Qiao",
    "tgn:placetype":[
        "aat:300007836"
    ]
},
  "bbox": [],
  "geometry": {"coordinates":[120.540641,22.951403],"type":"Point"}
}