{
  "id": 2366489,
  "type": "Feature",
  "properties": {
    "tgn:hierarchy":[
        "tgn:2366489",
        "tgn:1000001",
        "tgn:7012149",
        "tgn:2001543",
        "tgn:7007709",
        "tgn:7029392"
    ],
    "tgn:id":2366489,
    "tgn:name":"Grill Cove",
    "tgn:placetype":[
        "aat:300008761"
    ]
},
  "bbox": [],
  "geometry": {"coordinates":[-83.7833,35.5167],"type":"Point"}
}