{
  "id": 7062386,
  "type": "Feature",
  "properties": {
    "tgn:hierarchy":[
        "tgn:7062386",
        "tgn:1000003",
        "tgn:7000094",
        "tgn:7000084",
        "tgn:7029392"
    ],
    "tgn:id":7062386,
    "tgn:name":"Babst",
    "tgn:placetype":[
        "aat:300008347"
    ]
},
  "bbox": [],
  "geometry": {"coordinates":[11.75,53.883333],"type":"Point"}
}