{
  "id": 1015570,
  "type": "Feature",
  "properties": {
    "tgn:hierarchy":[
        "tgn:1015570",
        "tgn:7005685",
        "tgn:1000001",
        "tgn:7005804",
        "tgn:7029392"
    ],
    "tgn:id":1015570,
    "tgn:name":"Poste-de-la-Baleine",
    "tgn:placetype":[
        "aat:300008347"
    ]
},
  "bbox": [],
  "geometry": {"coordinates":[-77.8333,55.3333],"type":"Point"}
}