{
  "id": 7092677,
  "type": "Feature",
  "properties": {
    "tgn:hierarchy":[
        "tgn:7092677",
        "tgn:7003669",
        "tgn:1000003",
        "tgn:7000084",
        "tgn:7029392"
    ],
    "tgn:id":7092677,
    "tgn:name":"Vorderbaumberg",
    "tgn:placetype":[
        "aat:300008347"
    ]
},
  "bbox": [],
  "geometry": {"coordinates":[12.016667,48.383333],"type":"Point"}
}