{
  "id": 1074561,
  "type": "Feature",
  "properties": {
    "tgn:hierarchy":[
        "tgn:1074561",
        "tgn:1000004",
        "tgn:7000198",
        "tgn:1001977",
        "tgn:7029392"
    ],
    "tgn:id":1074561,
    "tgn:name:en":"B\u0101sudebpur",
    "tgn:placetype":[
        "aat:300008347",
        "aat:300008375"
    ]
},
  "bbox": [],
  "geometry": {"coordinates":[87.629164,21.82014],"type":"Point"}
}