{
  "id": 1045666,
  "type": "Feature",
  "properties": {
    "tgn:hierarchy":[
        "tgn:1045666",
        "tgn:1000003",
        "tgn:1001651",
        "tgn:7003122",
        "tgn:1000080",
        "tgn:7029392"
    ],
    "tgn:id":1045666,
    "tgn:name":"Nicolosi",
    "tgn:placetype":[
        "aat:300008347"
    ]
},
  "bbox": [],
  "geometry": {"coordinates":[15.016667,37.616667],"type":"Point"}
}