{
  "id": 7274780,
  "type": "Feature",
  "properties": {
    "tgn:concordances":{
        "gn:id":"2744052"
    },
    "tgn:hierarchy":[
        "tgn:7274780",
        "tgn:1000003",
        "tgn:7003624",
        "tgn:7016845",
        "tgn:7029392"
    ],
    "tgn:id":7274780,
    "tgn:name:nl":"Zandspui",
    "tgn:placetype":[
        "aat:300008347"
    ]
},
  "bbox": [],
  "geometry": {"coordinates":[4.666667,51.55],"type":"Point"}
}