{
  "id": 2165358,
  "type": "Feature",
  "properties": {
    "tgn:hierarchy":[
        "tgn:2165358",
        "tgn:7002659",
        "tgn:1000001",
        "tgn:2000011",
        "tgn:7012149",
        "tgn:7029392"
    ],
    "tgn:id":2165358,
    "tgn:name":"Betty Gap Mountain",
    "tgn:placetype":[
        "aat:300008798"
    ]
},
  "bbox": [],
  "geometry": {"coordinates":[-88.2833,32.0333],"type":"Point"}
}