{
  "id": 2381612,
  "type": "Feature",
  "properties": {
    "tgn:hierarchy":[
        "tgn:2381612",
        "tgn:1002933",
        "tgn:1000001",
        "tgn:7012149",
        "tgn:7007239",
        "tgn:7029392"
    ],
    "tgn:id":2381612,
    "tgn:name":"Hay Hummock",
    "tgn:placetype":[
        "aat:300008791"
    ]
},
  "bbox": [],
  "geometry": {"coordinates":[-75.25,38.85],"type":"Point"}
}