{
  "id": 2633340,
  "type": "Feature",
  "properties": {
    "tgn:hierarchy":[
        "tgn:2633340",
        "tgn:1000001",
        "tgn:7012149",
        "tgn:2001392",
        "tgn:7007525",
        "tgn:7029392"
    ],
    "tgn:id":2633340,
    "tgn:name":"Rumsey",
    "tgn:placetype":[
        "aat:300008347"
    ]
},
  "bbox": [],
  "geometry": {"coordinates":[-95.9833,41.1333],"type":"Point"}
}