{
  "id": 2621592,
  "type": "Feature",
  "properties": {
    "tgn:hierarchy":[
        "tgn:2621592",
        "tgn:1000001",
        "tgn:7012149",
        "tgn:2001709",
        "tgn:7007708",
        "tgn:7029392"
    ],
    "tgn:id":2621592,
    "tgn:name":"Roaring Springs Creek",
    "tgn:placetype":[
        "aat:300008706"
    ]
},
  "bbox": [],
  "geometry": {"coordinates":[-118.9167,42.6167],"type":"Point"}
}