<<<<<<< HEAD
{
  "id": 7021713,
  "type": "Feature",
  "properties": {
    "tgn:hierarchy":[
        "tgn:7021713",
        "tgn:1000001",
        "tgn:2001747",
        "tgn:7012149",
        "tgn:7007712",
        "tgn:7029392"
    ],
    "tgn:id":7021713,
    "tgn:name":"Pine Brook Forest",
    "tgn:placetype":[
        "aat:300008347"
    ]
},
  "bbox": [],
  "geometry": {"coordinates":[-82.3,34.7333],"type":"Point"}
}
=======
{"geometry":{"type":"Point","coordinates":[-82.300000,34.733300]},"type":"Feature","properties":{"hierarchy":["tgn:7021713","tgn:1000001","tgn:2001747","tgn:7012149","tgn:7007712","tgn:7029392"],"placetype":["aat:300008347"],"id":7021713,"name:xx":"Pine Brook Forest"}}
>>>>>>> 03f74aca74312dbeaf24d7e61306dd6a786dc3d0
