{
  "id": 7337885,
  "type": "Feature",
  "properties": {
    "tgn:hierarchy":[
        "tgn:7337885",
        "tgn:7002829",
        "tgn:1000003",
        "tgn:7002786",
        "tgn:1000095",
        "tgn:7029392"
    ],
    "tgn:id":7337885,
    "tgn:name":"C\u00e9ltigos",
    "tgn:placetype":[
        "aat:300008347"
    ]
},
  "bbox": [],
  "geometry": {"coordinates":[-7.383333,42.833333],"type":"Point"}
}