{
  "id": 7026275,
  "type": "Feature",
  "properties": {
    "tgn:hierarchy":[
        "tgn:7026275",
        "tgn:7002445",
        "tgn:1000003",
        "tgn:7008131",
        "tgn:1028596",
        "tgn:7008591",
        "tgn:7029392"
    ],
    "tgn:id":7026275,
    "tgn:name:en":"Black Notley",
    "tgn:placetype":[
        "aat:300008347",
        "aat:300000874"
    ]
},
  "bbox": [],
  "geometry": {"coordinates":[0.55,51.85],"type":"Point"}
}