{
  "id": 7437874,
  "type": "Feature",
  "properties": {
    "tgn:hierarchy":[
        "tgn:7437874",
        "tgn:1000001",
        "tgn:7005589",
        "tgn:7005560",
        "tgn:7029392"
    ],
    "tgn:id":7437874,
    "tgn:name":"Seco, Arroyo",
    "tgn:placetype":[
        "aat:300008699"
    ]
},
  "bbox": [],
  "geometry": {"coordinates":[-100.083333,24.95],"type":"Point"}
}