{
  "id": 1080559,
  "type": "Feature",
  "properties": {
    "tgn:hierarchy":[
        "tgn:1080559",
        "tgn:1000976",
        "tgn:1000004",
        "tgn:7000893",
        "tgn:1000120",
        "tgn:7029392"
    ],
    "tgn:id":1080559,
    "tgn:name":"Kitakata",
    "tgn:placetype":[
        "aat:300008347"
    ]
},
  "bbox": [],
  "geometry": {"coordinates":[139.8667,37.6333],"type":"Point"}
}