<<<<<<< HEAD
{
  "id": 2760726,
  "type": "Feature",
  "properties": {
    "tgn:hierarchy":[
        "tgn:2760726",
        "tgn:1000001",
        "tgn:2000955",
        "tgn:7012149",
        "tgn:7007520",
        "tgn:7029392"
    ],
    "tgn:id":2760726,
    "tgn:name":"West Gladstone",
    "tgn:placetype":[
        "aat:300008347"
    ]
},
  "bbox": [],
  "geometry": {"coordinates":[-87.05,45.8333],"type":"Point"}
}
=======
{"geometry":{"type":"Point","coordinates":[-87.050000,45.833300]},"type":"Feature","properties":{"hierarchy":["tgn:2760726","tgn:1000001","tgn:2000955","tgn:7012149","tgn:7007520","tgn:7029392"],"placetype":["aat:300008347"],"id":2760726,"name:xx":"West Gladstone"}}
>>>>>>> 03f74aca74312dbeaf24d7e61306dd6a786dc3d0
