{
  "id": 2466855,
  "type": "Feature",
  "properties": {
    "tgn:hierarchy":[
        "tgn:2466855",
        "tgn:2001557",
        "tgn:1000001",
        "tgn:7012149",
        "tgn:7007705",
        "tgn:7029392"
    ],
    "tgn:id":2466855,
    "tgn:name":"Long Butte",
    "tgn:placetype":[
        "aat:300008798"
    ]
},
  "bbox": [],
  "geometry": {"coordinates":[-102.25,46.15],"type":"Point"}
}