{
  "id": 7033901,
  "type": "Feature",
  "properties": {
    "tgn:hierarchy":[
        "tgn:7033901",
        "tgn:7003136",
        "tgn:1000003",
        "tgn:7003080",
        "tgn:1000080",
        "tgn:7029392"
    ],
    "tgn:id":7033901,
    "tgn:name":"Guardia, Punta della",
    "tgn:placetype":[
        "aat:300386846"
    ]
},
  "bbox": [],
  "geometry": {"coordinates":[12.95,40.883333],"type":"Point"}
}