{
  "id": 2425029,
  "type": "Feature",
  "properties": {
    "tgn:hierarchy":[
        "tgn:2425029",
        "tgn:1000001",
        "tgn:7012149",
        "tgn:7007157",
        "tgn:1002621",
        "tgn:7029392"
    ],
    "tgn:id":2425029,
    "tgn:name":"Johnson Lake",
    "tgn:placetype":[
        "aat:300008680"
    ]
},
  "bbox": [],
  "geometry": {"coordinates":[-119.5167,37.5667],"type":"Point"}
}