{
  "id": 2546113,
  "type": "Feature",
  "properties": {
    "tgn:hierarchy":[
        "tgn:2546113",
        "tgn:1000001",
        "tgn:7012149",
        "tgn:2001273",
        "tgn:7007524",
        "tgn:7029392"
    ],
    "tgn:id":2546113,
    "tgn:name":"North Fork Elk Creek",
    "tgn:placetype":[
        "aat:300008706"
    ]
},
  "bbox": [],
  "geometry": {"coordinates":[-108.8167,46.9667],"type":"Point"}
}