{
  "id": 7488609,
  "type": "Feature",
  "properties": {
    "tgn:hierarchy":[
        "tgn:7488609",
        "tgn:1000004",
        "tgn:7471332",
        "tgn:1000141",
        "tgn:7029392"
    ],
    "tgn:id":7488609,
    "tgn:name":"Luming Qiao",
    "tgn:placetype":[
        "aat:300007836"
    ]
},
  "bbox": [],
  "geometry": {"coordinates":[121.079722,24.885833],"type":"Point"}
}