{
  "id": 7010073,
  "type": "Feature",
  "properties": {
    "tgn:hierarchy":[
        "tgn:7010073",
        "tgn:1001475",
        "tgn:1000003",
        "tgn:1000069",
        "tgn:7029392"
    ],
    "tgn:id":7010073,
    "tgn:name":"Rokuan kansallispuisto",
    "tgn:placetype":[
        "aat:300008189"
    ]
},
  "bbox": [],
  "geometry": {"coordinates":[26.55,64.5333],"type":"Point"}
}