{
  "id": 2618807,
  "type": "Feature",
  "properties": {
    "tgn:hierarchy":[
        "tgn:2618807",
        "tgn:1000001",
        "tgn:7012149",
        "tgn:2000811",
        "tgn:7007255",
        "tgn:7029392"
    ],
    "tgn:id":2618807,
    "tgn:name":"Right Fork Trace Fork",
    "tgn:placetype":[
        "aat:300008699"
    ]
},
  "bbox": [],
  "geometry": {"coordinates":[-83.1667,37.0833],"type":"Point"}
}