<<<<<<< HEAD
{
  "id": 2338021,
  "type": "Feature",
  "properties": {
    "tgn:hierarchy":[
        "tgn:2338021",
        "tgn:1000001",
        "tgn:7012149",
        "tgn:2002359",
        "tgn:7007922",
        "tgn:7029392"
    ],
    "tgn:id":2338021,
    "tgn:name":"Fox Island",
    "tgn:placetype":[
        "aat:300008791"
    ]
},
  "bbox": [],
  "geometry": {"coordinates":[-89.8667,46.1333],"type":"Point"}
}
=======
{"geometry":{"type":"Point","coordinates":[-89.866700,46.133300]},"type":"Feature","properties":{"hierarchy":["tgn:2338021","tgn:1000001","tgn:7012149","tgn:2002359","tgn:7007922","tgn:7029392"],"placetype":["aat:300008791"],"id":2338021,"name:xx":"Fox Island"}}
>>>>>>> 03f74aca74312dbeaf24d7e61306dd6a786dc3d0
