{
  "id": 2338021,
  "type": "Feature",
  "properties": {
    "tgn:hierarchy":[
        "tgn:2338021",
        "tgn:1000001",
        "tgn:7012149",
        "tgn:2002359",
        "tgn:7007922",
        "tgn:7029392"
    ],
    "tgn:id":2338021,
    "tgn:name":"Fox Island",
    "tgn:placetype":[
        "aat:300008791"
    ]
},
  "bbox": [],
  "geometry": {"coordinates":[-89.8667,46.1333],"type":"Point"}
}