{
  "id": 2228325,
  "type": "Feature",
  "properties": {
    "tgn:hierarchy":[
        "tgn:2228325",
        "tgn:2000665",
        "tgn:1000001",
        "tgn:7012149",
        "tgn:7007254",
        "tgn:7029392"
    ],
    "tgn:id":2228325,
    "tgn:name":"Cedar Creek",
    "tgn:placetype":[
        "aat:300008706"
    ]
},
  "bbox": [],
  "geometry": {"coordinates":[-94.8333,37.8667],"type":"Point"}
}