{
  "id": 7302438,
  "type": "Feature",
  "properties": {
    "tgn:hierarchy":[
        "tgn:7302438",
        "tgn:7002810",
        "tgn:7001158",
        "tgn:1000003",
        "tgn:1000095",
        "tgn:7029392"
    ],
    "tgn:id":7302438,
    "tgn:name":"Orbaneja del Castillo",
    "tgn:placetype":[
        "aat:300008347"
    ]
},
  "bbox": [],
  "geometry": {"coordinates":[-3.783333,42.833333],"type":"Point"}
}