{
  "id": 2772943,
  "type": "Feature",
  "properties": {
    "tgn:hierarchy":[
        "tgn:2772943",
        "tgn:1000001",
        "tgn:7012149",
        "tgn:2001190",
        "tgn:7007523",
        "tgn:7029392"
    ],
    "tgn:id":2772943,
    "tgn:name":"Williams Lead Mine",
    "tgn:placetype":[
        "aat:300000390"
    ]
},
  "bbox": [],
  "geometry": {"coordinates":[-91.1667,38.15],"type":"Point"}
}