{
  "id": 7501672,
  "type": "Feature",
  "properties": {
    "tgn:hierarchy":[
        "tgn:7501672",
        "tgn:1000004",
        "tgn:7492971",
        "tgn:1000141",
        "tgn:7029392"
    ],
    "tgn:id":7501672,
    "tgn:name":"Fuxing Daqiao",
    "tgn:placetype":[
        "aat:300007836"
    ]
},
  "bbox": [],
  "geometry": {"coordinates":[120.823333,22.055833],"type":"Point"}
}