{
  "id": 1051747,
  "type": "Feature",
  "properties": {
    "tgn:hierarchy":[
        "tgn:1051747",
        "tgn:1000004",
        "tgn:7012261",
        "tgn:7006661",
        "tgn:7029392"
    ],
    "tgn:id":1051747,
    "tgn:name":"Shurchi",
    "tgn:placetype":[
        "aat:300008347"
    ]
},
  "bbox": [],
  "geometry": {"coordinates":[67.8167,38.0167],"type":"Point"}
}