<<<<<<< HEAD
{
  "id": 7478582,
  "type": "Feature",
  "properties": {
    "tgn:hierarchy":[
        "tgn:7478582",
        "tgn:7487020",
        "tgn:1000004",
        "tgn:1000141",
        "tgn:7029392"
    ],
    "tgn:id":7478582,
    "tgn:name":"Wugu Guoxiao",
    "tgn:placetype":[
        "aat:300006495"
    ]
},
  "bbox": [],
  "geometry": {"coordinates":[120.823031,24.52057],"type":"Point"}
}
=======
{"geometry":{"type":"Point","coordinates":[120.823031,24.520570]},"type":"Feature","properties":{"hierarchy":["tgn:7478582","tgn:7487020","tgn:1000004","tgn:1000141","tgn:7029392"],"placetype":["aat:300006495"],"id":7478582,"name:xx":"Wugu Guoxiao"}}
>>>>>>> 03f74aca74312dbeaf24d7e61306dd6a786dc3d0
