{
  "id": 2107535,
  "type": "Feature",
  "properties": {
    "tgn:hierarchy":[
        "tgn:2107535",
        "tgn:1000001",
        "tgn:7012149",
        "tgn:1002460",
        "tgn:7007826",
        "tgn:7029392"
    ],
    "tgn:id":2107535,
    "tgn:name":"Scottsville",
    "tgn:placetype":[
        "aat:300008347"
    ]
},
  "bbox": [],
  "geometry": {"coordinates":[-94.2333,32.5333],"type":"Point"}
}