<<<<<<< HEAD
{
  "id": 7170378,
  "type": "Feature",
  "properties": {
    "tgn:hierarchy":[
        "tgn:7170378",
        "tgn:1000003",
        "tgn:7003682",
        "tgn:7000084",
        "tgn:7029392"
    ],
    "tgn:id":7170378,
    "tgn:name":"Hitzelbach",
    "tgn:placetype":[
        "aat:300008699"
    ]
},
  "bbox": [],
  "geometry": {"coordinates":[7.25,50.0],"type":"Point"}
}
=======
{"geometry":{"type":"Point","coordinates":[7.250000,50.000000]},"type":"Feature","properties":{"hierarchy":["tgn:7170378","tgn:1000003","tgn:7003682","tgn:7000084","tgn:7029392"],"placetype":["aat:300008699"],"id":7170378,"name:xx":"Hitzelbach"}}
>>>>>>> 03f74aca74312dbeaf24d7e61306dd6a786dc3d0
