{
  "id": 7173565,
  "type": "Feature",
  "properties": {
    "tgn:hierarchy":[
        "tgn:7173565",
        "tgn:1000003",
        "tgn:7003677",
        "tgn:7000084",
        "tgn:7029392"
    ],
    "tgn:id":7173565,
    "tgn:name":"Gr\u00fcneberg",
    "tgn:placetype":[
        "aat:300000206"
    ]
},
  "bbox": [],
  "geometry": {"coordinates":[7.883333,51.65],"type":"Point"}
}