{
  "id": 7417507,
  "type": "Feature",
  "properties": {
    "tgn:hierarchy":[
        "tgn:7417507",
        "tgn:1000001",
        "tgn:7005591",
        "tgn:7005560",
        "tgn:7029392"
    ],
    "tgn:id":7417507,
    "tgn:name:es":"Estaci\u00f3n La Margarita",
    "tgn:placetype":[
        "aat:300007783"
    ]
},
  "bbox": [],
  "geometry": {"coordinates":[-96.561944,18.514167],"type":"Point"}
}