{
  "id": 7348718,
  "type": "Feature",
  "properties": {
    "tgn:hierarchy":[
        "tgn:7348718",
        "tgn:1001835",
        "tgn:1000001",
        "tgn:7005560",
        "tgn:7029392"
    ],
    "tgn:id":7348718,
    "tgn:name":"Alamito, Ca\u00f1\u00f3n del",
    "tgn:placetype":[
        "aat:300008763"
    ]
},
  "bbox": [],
  "geometry": {"coordinates":[-115.716667,31.566667],"type":"Point"}
}