{
  "id": 2240576,
  "type": "Feature",
  "properties": {
    "tgn:hierarchy":[
        "tgn:2240576",
        "tgn:1000001",
        "tgn:1002328",
        "tgn:7012149",
        "tgn:7007568",
        "tgn:7029392"
    ],
    "tgn:id":2240576,
    "tgn:name":"Clabber Peak",
    "tgn:placetype":[
        "aat:300008798"
    ]
},
  "bbox": [],
  "geometry": {"coordinates":[-75.2667,42.1167],"type":"Point"}
}