{
  "id": 2628175,
  "type": "Feature",
  "properties": {
    "tgn:hierarchy":[
        "tgn:2628175",
        "tgn:1000001",
        "tgn:7012149",
        "tgn:1002368",
        "tgn:7007919",
        "tgn:7029392"
    ],
    "tgn:id":2628175,
    "tgn:name":"Rolls Hollow",
    "tgn:placetype":[
        "aat:300008761"
    ]
},
  "bbox": [],
  "geometry": {"coordinates":[-78.05,38.8833],"type":"Point"}
}