{
  "id": 7379718,
  "type": "Feature",
  "properties": {
    "tgn:hierarchy":[
        "tgn:7379718",
        "tgn:1000001",
        "tgn:7005590",
        "tgn:7005560",
        "tgn:7029392"
    ],
    "tgn:id":7379718,
    "tgn:name":"Los Ultimos",
    "tgn:placetype":[
        "aat:300008347"
    ]
},
  "bbox": [],
  "geometry": {"coordinates":[-102.533333,19.183333],"type":"Point"}
}