{
  "id": 2574632,
  "type": "Feature",
  "properties": {
    "tgn:hierarchy":[
        "tgn:2574632",
        "tgn:1000001",
        "tgn:7012149",
        "tgn:2001764",
        "tgn:7007712",
        "tgn:7029392"
    ],
    "tgn:id":2574632,
    "tgn:name":"Pen Branch",
    "tgn:placetype":[
        "aat:300008699"
    ]
},
  "bbox": [],
  "geometry": {"coordinates":[-80.9833,34.0167],"type":"Point"}
}