{
  "id": 7357455,
  "type": "Feature",
  "properties": {
    "tgn:hierarchy":[
        "tgn:7357455",
        "tgn:1000001",
        "tgn:7005589",
        "tgn:7005560",
        "tgn:7029392"
    ],
    "tgn:id":7357455,
    "tgn:name":"Ejido El Fraile",
    "tgn:placetype":[
        "aat:300008347"
    ]
},
  "bbox": [],
  "geometry": {"coordinates":[-99.933333,25.333333],"type":"Point"}
}