<<<<<<< HEAD
{
  "id": 2253216,
  "type": "Feature",
  "properties": {
    "tgn:hierarchy":[
        "tgn:2253216",
        "tgn:1000001",
        "tgn:7012149",
        "tgn:2000959",
        "tgn:7007520",
        "tgn:7029392"
    ],
    "tgn:id":2253216,
    "tgn:name":"Contos, Lake",
    "tgn:placetype":[
        "aat:300008680"
    ]
},
  "bbox": [],
  "geometry": {"coordinates":[-84.55,44.0],"type":"Point"}
}
=======
{"geometry":{"type":"Point","coordinates":[-84.550000,44.000000]},"type":"Feature","properties":{"hierarchy":["tgn:2253216","tgn:1000001","tgn:7012149","tgn:2000959","tgn:7007520","tgn:7029392"],"placetype":["aat:300008680"],"id":2253216,"name:xx":"Contos, Lake"}}
>>>>>>> 03f74aca74312dbeaf24d7e61306dd6a786dc3d0
