{
  "id": 2381118,
  "type": "Feature",
  "properties": {
    "tgn:hierarchy":[
        "tgn:2381118",
        "tgn:1000001",
        "tgn:7012149",
        "tgn:2002213",
        "tgn:7007919",
        "tgn:7029392"
    ],
    "tgn:id":2381118,
    "tgn:name":"Hawkins Pond",
    "tgn:placetype":[
        "aat:300008680"
    ]
},
  "bbox": [],
  "geometry": {"coordinates":[-76.2667,37.0667],"type":"Point"}
}