{
  "id": 7369879,
  "type": "Feature",
  "properties": {
    "tgn:hierarchy":[
        "tgn:7369879",
        "tgn:1000001",
        "tgn:1001960",
        "tgn:7005560",
        "tgn:7029392"
    ],
    "tgn:id":7369879,
    "tgn:name":"Huasimita, Cerro",
    "tgn:placetype":[
        "aat:300008795"
    ]
},
  "bbox": [],
  "geometry": {"coordinates":[-109.666667,28.533333],"type":"Point"}
}