{
  "id": 7332577,
  "type": "Feature",
  "properties": {
    "tgn:hierarchy":[
        "tgn:7332577",
        "tgn:7002849",
        "tgn:1000003",
        "tgn:7009604",
        "tgn:1000095",
        "tgn:7029392"
    ],
    "tgn:id":7332577,
    "tgn:name":"Ir\u00e1uregui",
    "tgn:placetype":[
        "aat:300008347"
    ]
},
  "bbox": [],
  "geometry": {"coordinates":[-2.989652,43.248002],"type":"Point"}
}