<<<<<<< HEAD
{
  "id": 2156302,
  "type": "Feature",
  "properties": {
    "tgn:hierarchy":[
        "tgn:2156302",
        "tgn:1000001",
        "tgn:7012149",
        "tgn:2001544",
        "tgn:7007709",
        "tgn:7029392"
    ],
    "tgn:id":2156302,
    "tgn:name":"Bearpen Branch",
    "tgn:placetype":[
        "aat:300008699"
    ]
},
  "bbox": [],
  "geometry": {"coordinates":[-82.7167,35.3167],"type":"Point"}
}
=======
{"geometry":{"type":"Point","coordinates":[-82.716700,35.316700]},"type":"Feature","properties":{"hierarchy":["tgn:2156302","tgn:1000001","tgn:7012149","tgn:2001544","tgn:7007709","tgn:7029392"],"placetype":["aat:300008699"],"id":2156302,"name:xx":"Bearpen Branch"}}
>>>>>>> 03f74aca74312dbeaf24d7e61306dd6a786dc3d0
