{
  "id": 2517495,
  "type": "Feature",
  "properties": {
    "tgn:hierarchy":[
        "tgn:2517495",
        "tgn:1000001",
        "tgn:7012149",
        "tgn:1002418",
        "tgn:7007920",
        "tgn:7029392"
    ],
    "tgn:id":2517495,
    "tgn:name":"Minot Peak",
    "tgn:placetype":[
        "aat:300008798"
    ]
},
  "bbox": [],
  "geometry": {"coordinates":[-123.4167,46.8833],"type":"Point"}
}