<<<<<<< HEAD
{
  "id": 2151746,
  "type": "Feature",
  "properties": {
    "tgn:hierarchy":[
        "tgn:2151746",
        "tgn:1000001",
        "tgn:7012149",
        "tgn:1002943",
        "tgn:7007708",
        "tgn:7029392"
    ],
    "tgn:id":2151746,
    "tgn:name":"Battle Lake",
    "tgn:placetype":[
        "aat:300008680"
    ]
},
  "bbox": [],
  "geometry": {"coordinates":[-123.75,45.3],"type":"Point"}
}
=======
{"geometry":{"type":"Point","coordinates":[-123.750000,45.300000]},"type":"Feature","properties":{"hierarchy":["tgn:2151746","tgn:1000001","tgn:7012149","tgn:1002943","tgn:7007708","tgn:7029392"],"placetype":["aat:300008680"],"id":2151746,"name:xx":"Battle Lake"}}
>>>>>>> 03f74aca74312dbeaf24d7e61306dd6a786dc3d0
