{
  "id": 2499944,
  "type": "Feature",
  "properties": {
    "tgn:hierarchy":[
        "tgn:2499944",
        "tgn:1000001",
        "tgn:7012149",
        "tgn:7007157",
        "tgn:2000185",
        "tgn:7029392"
    ],
    "tgn:id":2499944,
    "tgn:name":"McCoy Spring",
    "tgn:placetype":[
        "aat:300008697"
    ]
},
  "bbox": [],
  "geometry": {"coordinates":[-122.9333,39.6667],"type":"Point"}
}