{
  "id": 2435658,
  "type": "Feature",
  "properties": {
    "tgn:hierarchy":[
        "tgn:2435658",
        "tgn:1000001",
        "tgn:7012149",
        "tgn:2001713",
        "tgn:7007708",
        "tgn:7029392"
    ],
    "tgn:id":2435658,
    "tgn:name":"Kester Mine",
    "tgn:placetype":[
        "aat:300000390"
    ]
},
  "bbox": [],
  "geometry": {"coordinates":[-123.4167,42.05],"type":"Point"}
}