{
  "id": 7555577,
  "type": "Feature",
  "properties": {
    "tgn:hierarchy":[
        "tgn:7555577",
        "tgn:1000004",
        "tgn:7000198",
        "tgn:1001895",
        "tgn:7029392"
    ],
    "tgn:id":7555577,
    "tgn:name:en":"Moh\u0101ri",
    "tgn:placetype":[
        "aat:300008347"
    ]
},
  "bbox": [],
  "geometry": {"coordinates":[79.674418,21.308914],"type":"Point"}
}