{
  "id": 2645036,
  "type": "Feature",
  "properties": {
    "tgn:hierarchy":[
        "tgn:2645036",
        "tgn:1000001",
        "tgn:7012149",
        "tgn:1002586",
        "tgn:7007710",
        "tgn:7029392"
    ],
    "tgn:id":2645036,
    "tgn:name":"Saucon Valley Terrace",
    "tgn:placetype":[
        "aat:300008347"
    ]
},
  "bbox": [],
  "geometry": {"coordinates":[-75.3667,40.5667],"type":"Point"}
}