{
  "id": 7192910,
  "type": "Feature",
  "properties": {
    "tgn:hierarchy":[
        "tgn:7192910",
        "tgn:7000096",
        "tgn:1000003",
        "tgn:7000084",
        "tgn:7029392"
    ],
    "tgn:id":7192910,
    "tgn:name":"Flemmingwiesen",
    "tgn:placetype":[
        "aat:300008901"
    ]
},
  "bbox": [],
  "geometry": {"coordinates":[13.366667,52.05],"type":"Point"}
}