{
  "id": 2382649,
  "type": "Feature",
  "properties": {
    "tgn:hierarchy":[
        "tgn:2382649",
        "tgn:1000001",
        "tgn:7016172",
        "tgn:7012149",
        "tgn:2000139",
        "tgn:7029392"
    ],
    "tgn:id":2382649,
    "tgn:name":"Haywood",
    "tgn:placetype":[
        "aat:300008347"
    ]
},
  "bbox": [],
  "geometry": {"coordinates":[-91.9167,34.35],"type":"Point"}
}