{
  "id": 2749599,
  "type": "Feature",
  "properties": {
    "tgn:hierarchy":[
        "tgn:2749599",
        "tgn:1000001",
        "tgn:7012149",
        "tgn:7007523",
        "tgn:7029392"
    ],
    "tgn:id":2749599,
    "tgn:name":"Walnut Creek",
    "tgn:placetype":[
        "aat:300008706"
    ]
},
  "bbox": [],
  "geometry": {"coordinates":[-93.9667,37.8667],"type":"Point"}
}