<<<<<<< HEAD
{
  "id": 2336097,
  "type": "Feature",
  "properties": {
    "tgn:hierarchy":[
        "tgn:2336097",
        "tgn:7013349",
        "tgn:1000001",
        "tgn:7012149",
        "tgn:7007708",
        "tgn:7029392"
    ],
    "tgn:id":2336097,
    "tgn:name":"Foster Gulch",
    "tgn:placetype":[
        "aat:300008761"
    ]
},
  "bbox": [],
  "geometry": {"coordinates":[-117.1167,44.8167],"type":"Point"}
}
=======
{"geometry":{"type":"Point","coordinates":[-117.116700,44.816700]},"type":"Feature","properties":{"hierarchy":["tgn:2336097","tgn:7013349","tgn:1000001","tgn:7012149","tgn:7007708","tgn:7029392"],"placetype":["aat:300008761"],"id":2336097,"name:xx":"Foster Gulch"}}
>>>>>>> 03f74aca74312dbeaf24d7e61306dd6a786dc3d0
