{
  "id": 7460162,
  "type": "Feature",
  "properties": {
    "tgn:hierarchy":[
        "tgn:7460162",
        "tgn:7002444",
        "tgn:1000003",
        "tgn:7008082",
        "tgn:7008591",
        "tgn:7029392"
    ],
    "tgn:id":7460162,
    "tgn:name:en":"Horse Sound",
    "tgn:placetype":[
        "aat:300266558"
    ]
},
  "bbox": [],
  "geometry": {"coordinates":[-5.333333,57.983333],"type":"Point"}
}