{
  "id": 7043574,
  "type": "Feature",
  "properties": {
    "tgn:hierarchy":[
        "tgn:7043574",
        "tgn:7009084",
        "tgn:7004154",
        "tgn:1000003",
        "tgn:1000080",
        "tgn:7029392"
    ],
    "tgn:id":7043574,
    "tgn:name":"Cecco d'Antonio, Monte",
    "tgn:placetype":[
        "aat:300008795"
    ]
},
  "bbox": [],
  "geometry": {"coordinates":[13.65,42.366667],"type":"Point"}
}