{
  "id": 2488223,
  "type": "Feature",
  "properties": {
    "tgn:hierarchy":[
        "tgn:2488223",
        "tgn:7006450",
        "tgn:1000001",
        "tgn:7012149",
        "tgn:2124002",
        "tgn:7029392"
    ],
    "tgn:id":2488223,
    "tgn:name":"Magoun Islands",
    "tgn:placetype":[
        "aat:300386853"
    ]
},
  "bbox": [],
  "geometry": {"coordinates":[-135.55,57.1667],"type":"Point"}
}