{
  "id": 2665851,
  "type": "Feature",
  "properties": {
    "tgn:hierarchy":[
        "tgn:2665851",
        "tgn:1000001",
        "tgn:7012149",
        "tgn:2002168",
        "tgn:7007919",
        "tgn:7029392"
    ],
    "tgn:id":2665851,
    "tgn:name":"Sirons Mill",
    "tgn:placetype":[
        "aat:300008347"
    ]
},
  "bbox": [],
  "geometry": {"coordinates":[-79.4667,38.3833],"type":"Point"}
}