{
  "id": 1014123,
  "type": "Feature",
  "properties": {
    "tgn:hierarchy":[
        "tgn:1014123",
        "tgn:7005685",
        "tgn:1000001",
        "tgn:7005799",
        "tgn:7029392"
    ],
    "tgn:id":1014123,
    "tgn:name":"Saint-L\u00e9onard",
    "tgn:placetype":[
        "aat:300008347"
    ]
},
  "bbox": [],
  "geometry": {"coordinates":[-67.9167,47.1667],"type":"Point"}
}