{
  "id": 7049111,
  "type": "Feature",
  "properties": {
    "tgn:hierarchy":[
        "tgn:7049111",
        "tgn:1001641",
        "tgn:1000003",
        "tgn:7003121",
        "tgn:1000080",
        "tgn:7029392"
    ],
    "tgn:id":7049111,
    "tgn:name":"Geremeas, Riu",
    "tgn:placetype":[
        "aat:300008699"
    ]
},
  "bbox": [],
  "geometry": {"coordinates":[9.383611,39.164167],"type":"Point"}
}