{
  "id": 7566121,
  "type": "Feature",
  "properties": {
    "tgn:hierarchy":[
        "tgn:7566121",
        "tgn:1000004",
        "tgn:1001832",
        "tgn:7000198",
        "tgn:7029392"
    ],
    "tgn:id":7566121,
    "tgn:name:en":"Singim\u0101ri",
    "tgn:placetype":[
        "aat:300008347"
    ]
},
  "bbox": [],
  "geometry": {"coordinates":[90.200219,26.395905],"type":"Point"}
}