<<<<<<< HEAD
{
  "id": 7359995,
  "type": "Feature",
  "properties": {
    "tgn:hierarchy":[
        "tgn:7359995",
        "tgn:7005580",
        "tgn:1000001",
        "tgn:7005560",
        "tgn:7029392"
    ],
    "tgn:id":7359995,
    "tgn:name":"Conchos, Arroyo",
    "tgn:placetype":[
        "aat:300008699"
    ]
},
  "bbox": [],
  "geometry": {"coordinates":[-93.5,17.133333],"type":"Point"}
}
=======
{"geometry":{"type":"Point","coordinates":[-93.500000,17.133333]},"type":"Feature","properties":{"hierarchy":["tgn:7359995","tgn:7005580","tgn:1000001","tgn:7005560","tgn:7029392"],"placetype":["aat:300008699"],"id":7359995,"name:xx":"Conchos, Arroyo"}}
>>>>>>> 03f74aca74312dbeaf24d7e61306dd6a786dc3d0
