{
  "id": 7009952,
  "type": "Feature",
  "properties": {
    "tgn:hierarchy":[
        "tgn:7009952",
        "tgn:1003455",
        "tgn:1000003",
        "tgn:7010380",
        "tgn:1000080",
        "tgn:7029392"
    ],
    "tgn:id":7009952,
    "tgn:name":"San Paolo di Civitate",
    "tgn:placetype":[
        "aat:300008347",
        "aat:300000810",
        "aat:300008375"
    ]
},
  "bbox": [],
  "geometry": {"coordinates":[15.25,41.733333],"type":"Point"}
}