{
  "id": 7100193,
  "type": "Feature",
  "properties": {
    "tgn:hierarchy":[
        "tgn:7100193",
        "tgn:7003692",
        "tgn:1000003",
        "tgn:7000084",
        "tgn:7029392"
    ],
    "tgn:id":7100193,
    "tgn:name":"R\u00f6telnberg",
    "tgn:placetype":[
        "aat:300000206"
    ]
},
  "bbox": [],
  "geometry": {"coordinates":[9.933333,47.933333],"type":"Point"}
}