{
  "id": 7396673,
  "type": "Feature",
  "properties": {
    "tgn:hierarchy":[
        "tgn:7396673",
        "tgn:1001835",
        "tgn:1000001",
        "tgn:7005560",
        "tgn:7029392"
    ],
    "tgn:id":7396673,
    "tgn:name":"San Miguel",
    "tgn:placetype":[
        "aat:300008347"
    ]
},
  "bbox": [],
  "geometry": {"coordinates":[-113.983333,28.566667],"type":"Point"}
}