{
  "id": 7342625,
  "type": "Feature",
  "properties": {
    "tgn:hierarchy":[
        "tgn:7342625",
        "tgn:7002835",
        "tgn:7001158",
        "tgn:1000003",
        "tgn:1000095",
        "tgn:7029392"
    ],
    "tgn:id":7342625,
    "tgn:name":"Carmeldo, Regato de",
    "tgn:placetype":[
        "aat:300008699"
    ]
},
  "bbox": [],
  "geometry": {"coordinates":[-5.55,40.733333],"type":"Point"}
}