{
  "id": 7045885,
  "type": "Feature",
  "properties": {
    "tgn:hierarchy":[
        "tgn:7045885",
        "tgn:1003468",
        "tgn:1000003",
        "tgn:7010380",
        "tgn:1000080",
        "tgn:7029392"
    ],
    "tgn:id":7045885,
    "tgn:name":"Contessa, Punta della",
    "tgn:placetype":[
        "aat:300386846"
    ]
},
  "bbox": [],
  "geometry": {"coordinates":[18.045278,40.5975],"type":"Point"}
}