{
  "id": 2141902,
  "type": "Feature",
  "properties": {
    "tgn:hierarchy":[
        "tgn:2141902",
        "tgn:1000001",
        "tgn:7012149",
        "tgn:7019676",
        "tgn:7007566",
        "tgn:7029392"
    ],
    "tgn:id":2141902,
    "tgn:name":"Baca, Laguna de",
    "tgn:placetype":[
        "aat:300006191"
    ]
},
  "bbox": [],
  "geometry": {"coordinates":[-106.7667,35.3667],"type":"Point"}
}