<<<<<<< HEAD
{
  "id": 7352744,
  "type": "Feature",
  "properties": {
    "tgn:hierarchy":[
        "tgn:7352744",
        "tgn:1000001",
        "tgn:7005590",
        "tgn:7005560",
        "tgn:7029392"
    ],
    "tgn:id":7352744,
    "tgn:name":"Buenavista",
    "tgn:placetype":[
        "aat:300008347"
    ]
},
  "bbox": [],
  "geometry": {"coordinates":[-101.766667,19.783333],"type":"Point"}
}
=======
{"geometry":{"type":"Point","coordinates":[-101.766667,19.783333]},"type":"Feature","properties":{"hierarchy":["tgn:7352744","tgn:1000001","tgn:7005590","tgn:7005560","tgn:7029392"],"placetype":["aat:300008347"],"id":7352744,"name:xx":"Buenavista"}}
>>>>>>> 03f74aca74312dbeaf24d7e61306dd6a786dc3d0
