{
  "id": 2739413,
  "type": "Feature",
  "properties": {
    "tgn:hierarchy":[
        "tgn:2739413",
        "tgn:1000001",
        "tgn:2002368",
        "tgn:7012149",
        "tgn:7007923",
        "tgn:7029392"
    ],
    "tgn:id":2739413,
    "tgn:name":"Upper Big Gulch",
    "tgn:placetype":[
        "aat:300008761"
    ]
},
  "bbox": [],
  "geometry": {"coordinates":[-107.1667,41.05],"type":"Point"}
}