{
  "id": 2407125,
  "type": "Feature",
  "properties": {
    "tgn:hierarchy":[
        "tgn:2407125",
        "tgn:1000001",
        "tgn:7012149",
        "tgn:1002959",
        "tgn:7007826",
        "tgn:7029392"
    ],
    "tgn:id":2407125,
    "tgn:name":"Hunters Creek",
    "tgn:placetype":[
        "aat:300008706"
    ]
},
  "bbox": [],
  "geometry": {"coordinates":[-94.3833,30.7667],"type":"Point"}
}