{
  "id": 2493540,
  "type": "Feature",
  "properties": {
    "tgn:hierarchy":[
        "tgn:2493540",
        "tgn:1000001",
        "tgn:7012149",
        "tgn:2001706",
        "tgn:7007708",
        "tgn:7029392"
    ],
    "tgn:id":2493540,
    "tgn:name":"Marsh Creek Pond",
    "tgn:placetype":[
        "aat:300006191"
    ]
},
  "bbox": [],
  "geometry": {"coordinates":[-123.1333,43.7833],"type":"Point"}
}