{
  "id": 7188230,
  "type": "Feature",
  "properties": {
    "tgn:hierarchy":[
        "tgn:7188230",
        "tgn:1000003",
        "tgn:7003688",
        "tgn:7000084",
        "tgn:7029392"
    ],
    "tgn:id":7188230,
    "tgn:name":"Estruphof",
    "tgn:placetype":[
        "aat:300000206"
    ]
},
  "bbox": [],
  "geometry": {"coordinates":[9.55,54.716667],"type":"Point"}
}