<<<<<<< HEAD
{
  "id": 7373959,
  "type": "Feature",
  "properties": {
    "tgn:hierarchy":[
        "tgn:7373959",
        "tgn:1000001",
        "tgn:7005595",
        "tgn:7005560",
        "tgn:7029392"
    ],
    "tgn:id":7373959,
    "tgn:name":"La Cofrad\u00eda",
    "tgn:placetype":[
        "aat:300008347"
    ]
},
  "bbox": [],
  "geometry": {"coordinates":[-107.35,25.683333],"type":"Point"}
}
=======
{"geometry":{"type":"Point","coordinates":[-107.350000,25.683333]},"type":"Feature","properties":{"hierarchy":["tgn:7373959","tgn:1000001","tgn:7005595","tgn:7005560","tgn:7029392"],"placetype":["aat:300008347"],"id":7373959,"name:xx":"La Cofrad\u00eda"}}
>>>>>>> 03f74aca74312dbeaf24d7e61306dd6a786dc3d0
