{
  "id": 2691500,
  "type": "Feature",
  "properties": {
    "tgn:hierarchy":[
        "tgn:2691500",
        "tgn:1000001",
        "tgn:7012149",
        "tgn:2000488",
        "tgn:7007250",
        "tgn:7029392"
    ],
    "tgn:id":2691500,
    "tgn:name":"Star Reservoir",
    "tgn:placetype":[
        "aat:300006191"
    ]
},
  "bbox": [],
  "geometry": {"coordinates":[-116.75,42.45],"type":"Point"}
}