{
  "id": 2061717,
  "type": "Feature",
  "properties": {
    "tgn:hierarchy":[
        "tgn:2061717",
        "tgn:1000001",
        "tgn:7012149",
        "tgn:2001291",
        "tgn:7007524",
        "tgn:7029392"
    ],
    "tgn:id":2061717,
    "tgn:name":"Seeley Lake",
    "tgn:placetype":[
        "aat:300008347"
    ]
},
  "bbox": [],
  "geometry": {"coordinates":[-113.4833,47.1667],"type":"Point"}
}