{
  "id": 7387097,
  "type": "Feature",
  "properties": {
    "tgn:hierarchy":[
        "tgn:7387097",
        "tgn:1000001",
        "tgn:1001960",
        "tgn:7005560",
        "tgn:7029392"
    ],
    "tgn:id":7387097,
    "tgn:name":"Perinola, Sierra de la",
    "tgn:placetype":[
        "aat:300008777",
        "aat:300008795"
    ]
},
  "bbox": [],
  "geometry": {"coordinates":[-111.016667,27.983333],"type":"Point"}
}