<<<<<<< HEAD
{
  "id": 2402516,
  "type": "Feature",
  "properties": {
    "tgn:hierarchy":[
        "tgn:2402516",
        "tgn:1000001",
        "tgn:7012149",
        "tgn:7007159",
        "tgn:7029392"
    ],
    "tgn:id":2402516,
    "tgn:name":"Hosmer Mountain",
    "tgn:placetype":[
        "aat:300008798"
    ]
},
  "bbox": [],
  "geometry": {"coordinates":[-72.2167,41.7],"type":"Point"}
}
=======
{"geometry":{"type":"Point","coordinates":[-72.216700,41.700000]},"type":"Feature","properties":{"hierarchy":["tgn:2402516","tgn:1000001","tgn:7012149","tgn:7007159","tgn:7029392"],"placetype":["aat:300008798"],"id":2402516,"name:xx":"Hosmer Mountain"}}
>>>>>>> 03f74aca74312dbeaf24d7e61306dd6a786dc3d0
