{
  "id": 7201709,
  "type": "Feature",
  "properties": {
    "tgn:hierarchy":[
        "tgn:7201709",
        "tgn:7003669",
        "tgn:1000003",
        "tgn:7000084",
        "tgn:7029392"
    ],
    "tgn:id":7201709,
    "tgn:name":"Buchberg",
    "tgn:placetype":[
        "aat:300008777"
    ]
},
  "bbox": [],
  "geometry": {"coordinates":[11.433333,49.25],"type":"Point"}
}