{
  "id": 7266890,
  "type": "Feature",
  "properties": {
    "tgn:concordances":{
        "gn:id":"2754016"
    },
    "tgn:hierarchy":[
        "tgn:7266890",
        "tgn:7003616",
        "tgn:1000003",
        "tgn:7016845",
        "tgn:7029392"
    ],
    "tgn:id":7266890,
    "tgn:name:nl":"Hoek Makkinga",
    "tgn:placetype":[
        "aat:300008347"
    ]
},
  "bbox": [],
  "geometry": {"coordinates":[6.233333,52.983333],"type":"Point"}
}