{
  "id": 7555695,
  "type": "Feature",
  "properties": {
    "tgn:hierarchy":[
        "tgn:7555695",
        "tgn:1000004",
        "tgn:1001871",
        "tgn:7000198",
        "tgn:7029392"
    ],
    "tgn:id":7555695,
    "tgn:name:en":"Pah\u0101ri ki Mandi",
    "tgn:placetype":[
        "aat:300008347"
    ]
},
  "bbox": [],
  "geometry": {"coordinates":[75.730322,28.563575],"type":"Point"}
}