{
  "id": 7527707,
  "type": "Feature",
  "properties": {
    "tgn:hierarchy":[
        "tgn:7527707",
        "tgn:7001242",
        "tgn:1001075",
        "tgn:7016833",
        "tgn:7029392"
    ],
    "tgn:id":7527707,
    "tgn:name:en":"Z\u0101wiyat Nu'aym",
    "tgn:placetype":[
        "aat:300008347"
    ]
},
  "bbox": [],
  "geometry": {"coordinates":[30.342778,31.053056],"type":"Point"}
}