{
  "id": 2757766,
  "type": "Feature",
  "properties": {
    "tgn:hierarchy":[
        "tgn:2757766",
        "tgn:1000001",
        "tgn:7012149",
        "tgn:1002800",
        "tgn:7007710",
        "tgn:7029392"
    ],
    "tgn:id":2757766,
    "tgn:name":"West Branch Genesee River",
    "tgn:placetype":[
        "aat:300008707"
    ]
},
  "bbox": [],
  "geometry": {"coordinates":[-77.8667,41.8667],"type":"Point"}
}