{
  "id": 7578029,
  "type": "Feature",
  "properties": {
    "tgn:hierarchy":[
        "tgn:7578029",
        "tgn:1000004",
        "tgn:7000198",
        "tgn:1001894",
        "tgn:7029392"
    ],
    "tgn:id":7578029,
    "tgn:name:en":"Kundanpur",
    "tgn:placetype":[
        "aat:300008347"
    ]
},
  "bbox": [],
  "geometry": {"coordinates":[74.434983,22.728612],"type":"Point"}
}