{
  "id": 2232435,
  "type": "Feature",
  "properties": {
    "tgn:hierarchy":[
        "tgn:2232435",
        "tgn:7006450",
        "tgn:1000001",
        "tgn:7012149",
        "tgn:2124002",
        "tgn:7029392"
    ],
    "tgn:id":2232435,
    "tgn:name":"Channel Rock",
    "tgn:placetype":[
        "aat:300132348"
    ]
},
  "bbox": [],
  "geometry": {"coordinates":[-135.35,57.05],"type":"Point"}
}