{
  "id": 7536626,
  "type": "Feature",
  "properties": {
    "tgn:hierarchy":[
        "tgn:7536626",
        "tgn:7001242",
        "tgn:7016833",
        "tgn:1001087",
        "tgn:7029392"
    ],
    "tgn:id":7536626,
    "tgn:name:en":"Kafr 'A\u0163\u0101'",
    "tgn:placetype":[
        "aat:300008347"
    ]
},
  "bbox": [],
  "geometry": {"coordinates":[30.987816,30.321744],"type":"Point"}
}