{
  "id": 2418689,
  "type": "Feature",
  "properties": {
    "tgn:hierarchy":[
        "tgn:2418689",
        "tgn:1000001",
        "tgn:7012149",
        "tgn:7007825",
        "tgn:7029392"
    ],
    "tgn:id":2418689,
    "tgn:name":"Jakes Creek",
    "tgn:placetype":[
        "aat:300008706"
    ]
},
  "bbox": [],
  "geometry": {"coordinates":[-89.9667,35.3833],"type":"Point"}
}