{
  "id": 2630117,
  "type": "Feature",
  "properties": {
    "tgn:hierarchy":[
        "tgn:2630117",
        "tgn:1000001",
        "tgn:7012149",
        "tgn:2002250",
        "tgn:7007920",
        "tgn:7029392"
    ],
    "tgn:id":2630117,
    "tgn:name":"Rotter Bay",
    "tgn:placetype":[
        "aat:300132316"
    ]
},
  "bbox": [],
  "geometry": {"coordinates":[-118.1833,48.4333],"type":"Point"}
}