{
  "id": 7434187,
  "type": "Feature",
  "properties": {
    "tgn:hierarchy":[
        "tgn:7434187",
        "tgn:1001835",
        "tgn:1000001",
        "tgn:7005560",
        "tgn:7029392"
    ],
    "tgn:id":7434187,
    "tgn:name":"El Chenque N\u00famero Ocho",
    "tgn:placetype":[
        "aat:300008347"
    ]
},
  "bbox": [],
  "geometry": {"coordinates":[-115.350833,32.450833],"type":"Point"}
}