{
  "id": 7548677,
  "type": "Feature",
  "properties": {
    "tgn:hierarchy":[
        "tgn:7548677",
        "tgn:1000004",
        "tgn:1001869",
        "tgn:7000198",
        "tgn:7029392"
    ],
    "tgn:id":7548677,
    "tgn:name:en":"Chiol",
    "tgn:placetype":[
        "aat:300008347"
    ]
},
  "bbox": [],
  "geometry": {"coordinates":[73.116667,20.433333],"type":"Point"}
}