{
  "id": 2216267,
  "type": "Feature",
  "properties": {
    "tgn:hierarchy":[
        "tgn:2216267",
        "tgn:1000001",
        "tgn:7012149",
        "tgn:1002969",
        "tgn:7007826",
        "tgn:7029392"
    ],
    "tgn:id":2216267,
    "tgn:name":"Camp Branch",
    "tgn:placetype":[
        "aat:300008699"
    ]
},
  "bbox": [],
  "geometry": {"coordinates":[-95.9833,32.5333],"type":"Point"}
}