{
  "id": 2439259,
  "type": "Feature",
  "properties": {
    "tgn:hierarchy":[
        "tgn:2439259",
        "tgn:1000001",
        "tgn:2124025",
        "tgn:7012149",
        "tgn:7007516",
        "tgn:7029392"
    ],
    "tgn:id":2439259,
    "tgn:name":"Kirby Landing",
    "tgn:placetype":[
        "aat:300008347"
    ]
},
  "bbox": [],
  "geometry": {"coordinates":[-75.8667,39.2333],"type":"Point"}
}