{
  "id": 7545307,
  "type": "Feature",
  "properties": {
    "tgn:hierarchy":[
        "tgn:7545307",
        "tgn:1000004",
        "tgn:1001842",
        "tgn:7000198",
        "tgn:7029392"
    ],
    "tgn:id":7545307,
    "tgn:name:en":"Amba",
    "tgn:placetype":[
        "aat:300008347"
    ]
},
  "bbox": [],
  "geometry": {"coordinates":[84.281689,24.628209],"type":"Point"}
}