{
  "id": 7263096,
  "type": "Feature",
  "properties": {
    "tgn:hierarchy":[
        "tgn:7263096",
        "tgn:7003614",
        "tgn:1000003",
        "tgn:7016845",
        "tgn:7029392"
    ],
    "tgn:id":7263096,
    "tgn:name:nl":"De Braak",
    "tgn:placetype":[
        "aat:300387502"
    ]
},
  "bbox": [],
  "geometry": {"coordinates":[6.566667,53.15],"type":"Point"}
}