{
  "id": 2692953,
  "type": "Feature",
  "properties": {
    "tgn:hierarchy":[
        "tgn:2692953",
        "tgn:7002659",
        "tgn:1000001",
        "tgn:7012149",
        "tgn:2000049",
        "tgn:7029392"
    ],
    "tgn:id":2692953,
    "tgn:name":"Steels Lake",
    "tgn:placetype":[
        "aat:300006191"
    ]
},
  "bbox": [],
  "geometry": {"coordinates":[-87.1833,31.7333],"type":"Point"}
}