{
  "id": 2124267,
  "type": "Feature",
  "properties": {
    "tgn:hierarchy":[
        "tgn:2124267",
        "tgn:1000001",
        "tgn:7006451",
        "tgn:7012149",
        "tgn:2000104",
        "tgn:7029392"
    ],
    "tgn:id":2124267,
    "tgn:name":"A 8.9 N Lateral",
    "tgn:placetype":[
        "aat:300006075"
    ]
},
  "bbox": [],
  "geometry": {"coordinates":[-114.5833,32.6167],"type":"Point"}
}