<<<<<<< HEAD
{
  "id": 7056616,
  "type": "Feature",
  "properties": {
    "tgn:hierarchy":[
        "tgn:7056616",
        "tgn:1003478",
        "tgn:1000003",
        "tgn:7003120",
        "tgn:1000080",
        "tgn:7029392"
    ],
    "tgn:id":7056616,
    "tgn:name":"Agaro",
    "tgn:placetype":[
        "aat:300008347"
    ]
},
  "bbox": [],
  "geometry": {"coordinates":[8.3,46.3],"type":"Point"}
}
=======
{"geometry":{"type":"Point","coordinates":[8.300000,46.300000]},"type":"Feature","properties":{"hierarchy":["tgn:7056616","tgn:1003478","tgn:1000003","tgn:7003120","tgn:1000080","tgn:7029392"],"placetype":["aat:300008347"],"id":7056616,"name:xx":"Agaro"}}
>>>>>>> 03f74aca74312dbeaf24d7e61306dd6a786dc3d0
