{
  "id": 7107750,
  "type": "Feature",
  "properties": {
    "tgn:hierarchy":[
        "tgn:7107750",
        "tgn:7003669",
        "tgn:1000003",
        "tgn:7000084",
        "tgn:7029392"
    ],
    "tgn:id":7107750,
    "tgn:name":"Reichartshausen",
    "tgn:placetype":[
        "aat:300008347"
    ]
},
  "bbox": [],
  "geometry": {"coordinates":[9.281944,49.659722],"type":"Point"}
}