{
  "id": 2463139,
  "type": "Feature",
  "properties": {
    "tgn:hierarchy":[
        "tgn:2463139",
        "tgn:1000001",
        "tgn:2001436",
        "tgn:7012149",
        "tgn:7007566",
        "tgn:7029392"
    ],
    "tgn:id":2463139,
    "tgn:name":"Livingston Canal",
    "tgn:placetype":[
        "aat:300006075"
    ]
},
  "bbox": [],
  "geometry": {"coordinates":[-103.9833,32.1833],"type":"Point"}
}