<<<<<<< HEAD
{
  "id": 7363719,
  "type": "Feature",
  "properties": {
    "tgn:hierarchy":[
        "tgn:7363719",
        "tgn:1000001",
        "tgn:7005594",
        "tgn:7005560",
        "tgn:7029392"
    ],
    "tgn:id":7363719,
    "tgn:name":"El Gavil\u00e1n",
    "tgn:placetype":[
        "aat:300008347"
    ]
},
  "bbox": [],
  "geometry": {"coordinates":[-100.05,22.533333],"type":"Point"}
}
=======
{"geometry":{"type":"Point","coordinates":[-100.050000,22.533333]},"type":"Feature","properties":{"hierarchy":["tgn:7363719","tgn:1000001","tgn:7005594","tgn:7005560","tgn:7029392"],"placetype":["aat:300008347"],"id":7363719,"name:xx":"El Gavil\u00e1n"}}
>>>>>>> 03f74aca74312dbeaf24d7e61306dd6a786dc3d0
