{
  "id": 7363719,
  "type": "Feature",
  "properties": {
    "tgn:hierarchy":[
        "tgn:7363719",
        "tgn:1000001",
        "tgn:7005594",
        "tgn:7005560",
        "tgn:7029392"
    ],
    "tgn:id":7363719,
    "tgn:name":"El Gavil\u00e1n",
    "tgn:placetype":[
        "aat:300008347"
    ]
},
  "bbox": [],
  "geometry": {"coordinates":[-100.05,22.533333],"type":"Point"}
}