{
  "id": 2376462,
  "type": "Feature",
  "properties": {
    "tgn:hierarchy":[
        "tgn:2376462",
        "tgn:1000001",
        "tgn:7012149",
        "tgn:2000550",
        "tgn:7007252",
        "tgn:7029392"
    ],
    "tgn:id":2376462,
    "tgn:name":"Harding Pond",
    "tgn:placetype":[
        "aat:300006191"
    ]
},
  "bbox": [],
  "geometry": {"coordinates":[-86.55,38.0167],"type":"Point"}
}