{
  "id": 2656339,
  "type": "Feature",
  "properties": {
    "tgn:hierarchy":[
        "tgn:2656339",
        "tgn:1000001",
        "tgn:2002108",
        "tgn:7012149",
        "tgn:7007827",
        "tgn:7029392"
    ],
    "tgn:id":2656339,
    "tgn:name":"Shearing Corral Draw",
    "tgn:placetype":[
        "aat:300008761"
    ]
},
  "bbox": [],
  "geometry": {"coordinates":[-111.0667,39.0167],"type":"Point"}
}