{
  "id": 2392147,
  "type": "Feature",
  "properties": {
    "tgn:hierarchy":[
        "tgn:2392147",
        "tgn:1000001",
        "tgn:7012149",
        "tgn:2000806",
        "tgn:7007255",
        "tgn:7029392"
    ],
    "tgn:id":2392147,
    "tgn:name":"Hinkle Branch",
    "tgn:placetype":[
        "aat:300008699"
    ]
},
  "bbox": [],
  "geometry": {"coordinates":[-83.7667,36.9333],"type":"Point"}
}