{
  "id": 2459523,
  "type": "Feature",
  "properties": {
    "tgn:hierarchy":[
        "tgn:2459523",
        "tgn:1000001",
        "tgn:7012149",
        "tgn:1002839",
        "tgn:7007826",
        "tgn:7029392"
    ],
    "tgn:id":2459523,
    "tgn:name":"Little Rabbit Creek",
    "tgn:placetype":[
        "aat:300008706"
    ]
},
  "bbox": [],
  "geometry": {"coordinates":[-94.9333,32.2333],"type":"Point"}
}