<<<<<<< HEAD
{
  "id": 2339259,
  "type": "Feature",
  "properties": {
    "tgn:hierarchy":[
        "tgn:2339259",
        "tgn:1000001",
        "tgn:7006451",
        "tgn:2000095",
        "tgn:7012149",
        "tgn:7029392"
    ],
    "tgn:id":2339259,
    "tgn:name":"Franz Spring",
    "tgn:placetype":[
        "aat:300008697"
    ]
},
  "bbox": [],
  "geometry": {"coordinates":[-109.0667,33.5333],"type":"Point"}
}
=======
{"geometry":{"type":"Point","coordinates":[-109.066700,33.533300]},"type":"Feature","properties":{"hierarchy":["tgn:2339259","tgn:1000001","tgn:7006451","tgn:2000095","tgn:7012149","tgn:7029392"],"placetype":["aat:300008697"],"id":2339259,"name:xx":"Franz Spring"}}
>>>>>>> 03f74aca74312dbeaf24d7e61306dd6a786dc3d0
