{
  "id": 2214866,
  "type": "Feature",
  "properties": {
    "tgn:hierarchy":[
        "tgn:2214866",
        "tgn:1000001",
        "tgn:2000779",
        "tgn:7012149",
        "tgn:7007255",
        "tgn:7029392"
    ],
    "tgn:id":2214866,
    "tgn:name":"Calhoun Creek",
    "tgn:placetype":[
        "aat:300008706"
    ]
},
  "bbox": [],
  "geometry": {"coordinates":[-84.8833,37.2833],"type":"Point"}
}