{
  "id": 7211696,
  "type": "Feature",
  "properties": {
    "tgn:hierarchy":[
        "tgn:7211696",
        "tgn:7003669",
        "tgn:1000003",
        "tgn:7000084",
        "tgn:7029392"
    ],
    "tgn:id":7211696,
    "tgn:name":"Bergenstetten",
    "tgn:placetype":[
        "aat:300008347"
    ]
},
  "bbox": [],
  "geometry": {"coordinates":[10.15,48.183333],"type":"Point"}
}