{
  "id": 7328047,
  "type": "Feature",
  "properties": {
    "tgn:hierarchy":[
        "tgn:7328047",
        "tgn:7002831",
        "tgn:1000003",
        "tgn:7002786",
        "tgn:1000095",
        "tgn:7029392"
    ],
    "tgn:id":7328047,
    "tgn:name":"Quintas, Arroyo de las",
    "tgn:placetype":[
        "aat:300008699"
    ]
},
  "bbox": [],
  "geometry": {"coordinates":[-7.416667,41.916667],"type":"Point"}
}