<<<<<<< HEAD
{
  "id": 2158037,
  "type": "Feature",
  "properties": {
    "tgn:hierarchy":[
        "tgn:2158037",
        "tgn:1000001",
        "tgn:7012149",
        "tgn:2000476",
        "tgn:7007250",
        "tgn:7029392"
    ],
    "tgn:id":2158037,
    "tgn:name":"Beaver Point",
    "tgn:placetype":[
        "aat:300008850"
    ]
},
  "bbox": [],
  "geometry": {"coordinates":[-114.7667,45.7333],"type":"Point"}
}
=======
{"geometry":{"type":"Point","coordinates":[-114.766700,45.733300]},"type":"Feature","properties":{"hierarchy":["tgn:2158037","tgn:1000001","tgn:7012149","tgn:2000476","tgn:7007250","tgn:7029392"],"placetype":["aat:300008850"],"id":2158037,"name:xx":"Beaver Point"}}
>>>>>>> 03f74aca74312dbeaf24d7e61306dd6a786dc3d0
