{
  "id": 2726509,
  "type": "Feature",
  "properties": {
    "tgn:hierarchy":[
        "tgn:2726509",
        "tgn:1000001",
        "tgn:2000773",
        "tgn:7012149",
        "tgn:7007255",
        "tgn:7029392"
    ],
    "tgn:id":2726509,
    "tgn:name":"Town Creek",
    "tgn:placetype":[
        "aat:300008706"
    ]
},
  "bbox": [],
  "geometry": {"coordinates":[-86.5167,37.8667],"type":"Point"}
}