{
  "id": 2530429,
  "type": "Feature",
  "properties": {
    "tgn:hierarchy":[
        "tgn:2530429",
        "tgn:1000001",
        "tgn:7012149",
        "tgn:2001901",
        "tgn:7007825",
        "tgn:7029392"
    ],
    "tgn:id":2530429,
    "tgn:name":"Muddy Branch",
    "tgn:placetype":[
        "aat:300008699"
    ]
},
  "bbox": [],
  "geometry": {"coordinates":[-84.5333,36.0167],"type":"Point"}
}