{
  "id": 1112486,
  "type": "Feature",
  "properties": {
    "tgn:hierarchy":[
        "tgn:1112486",
        "tgn:1000001",
        "tgn:7005591",
        "tgn:7005560",
        "tgn:7029392"
    ],
    "tgn:id":1112486,
    "tgn:name":"Tehuantepec, Golfo de",
    "tgn:placetype":[
        "aat:300132315"
    ]
},
  "bbox": [],
  "geometry": {"coordinates":[-94.801,16.006],"type":"Point"}
}