{
  "id": 2370533,
  "type": "Feature",
  "properties": {
    "tgn:hierarchy":[
        "tgn:2370533",
        "tgn:1000001",
        "tgn:7012149",
        "tgn:2001516",
        "tgn:7007709",
        "tgn:7029392"
    ],
    "tgn:id":2370533,
    "tgn:name":"Hack Knob",
    "tgn:placetype":[
        "aat:300008798"
    ]
},
  "bbox": [],
  "geometry": {"coordinates":[-82.6167,35.95],"type":"Point"}
}