{
  "id": 2241167,
  "type": "Feature",
  "properties": {
    "tgn:hierarchy":[
        "tgn:2241167",
        "tgn:1000001",
        "tgn:7012149",
        "tgn:2000181",
        "tgn:7007157",
        "tgn:7029392"
    ],
    "tgn:id":2241167,
    "tgn:name":"Clark Grove",
    "tgn:placetype":[
        "aat:300132451"
    ]
},
  "bbox": [],
  "geometry": {"coordinates":[-123.9167,40.3167],"type":"Point"}
}