{
  "id": 2437840,
  "type": "Feature",
  "properties": {
    "tgn:hierarchy":[
        "tgn:2437840",
        "tgn:1000001",
        "tgn:7014352",
        "tgn:7012149",
        "tgn:7007564",
        "tgn:7029392"
    ],
    "tgn:id":2437840,
    "tgn:name":"King Hill",
    "tgn:placetype":[
        "aat:300008798"
    ]
},
  "bbox": [],
  "geometry": {"coordinates":[-71.2167,42.9333],"type":"Point"}
}