{
  "id": 2022466,
  "type": "Feature",
  "properties": {
    "tgn:hierarchy":[
        "tgn:2022466",
        "tgn:1000001",
        "tgn:7012149",
        "tgn:2000396",
        "tgn:7007248",
        "tgn:7029392"
    ],
    "tgn:id":2022466,
    "tgn:name":"Cohutta Springs",
    "tgn:placetype":[
        "aat:300008347"
    ]
},
  "bbox": [],
  "geometry": {"coordinates":[-84.7167,34.8833],"type":"Point"}
}