{
  "id": 2671964,
  "type": "Feature",
  "properties": {
    "tgn:hierarchy":[
        "tgn:2671964",
        "tgn:1000001",
        "tgn:7012149",
        "tgn:2002302",
        "tgn:7013961",
        "tgn:7029392"
    ],
    "tgn:id":2671964,
    "tgn:name":"Smith Run",
    "tgn:placetype":[
        "aat:300008699"
    ]
},
  "bbox": [],
  "geometry": {"coordinates":[-81.5333,38.95],"type":"Point"}
}