{
  "id": 2636596,
  "type": "Feature",
  "properties": {
    "tgn:hierarchy":[
        "tgn:2636596",
        "tgn:1000001",
        "tgn:7012149",
        "tgn:2002247",
        "tgn:7007920",
        "tgn:7029392"
    ],
    "tgn:id":2636596,
    "tgn:name":"Sage Hen Draw",
    "tgn:placetype":[
        "aat:300008761"
    ]
},
  "bbox": [],
  "geometry": {"coordinates":[-118.6667,47.85],"type":"Point"}
}