{
  "id": 7278167,
  "type": "Feature",
  "properties": {
    "tgn:hierarchy":[
        "tgn:7278167",
        "tgn:1001623",
        "tgn:1000049",
        "tgn:1000002",
        "tgn:7029392"
    ],
    "tgn:id":7278167,
    "tgn:name":"Lampazo, Puerto",
    "tgn:placetype":[
        "aat:300008678"
    ]
},
  "bbox": [],
  "geometry": {"coordinates":[-73.75,-44.916667],"type":"Point"}
}