{
  "id": 7305500,
  "type": "Feature",
  "properties": {
    "tgn:hierarchy":[
        "tgn:7305500",
        "tgn:1001439",
        "tgn:1000003",
        "tgn:7002797",
        "tgn:1000095",
        "tgn:7029392"
    ],
    "tgn:id":7305500,
    "tgn:name":"Las Lomas de Last\u00f3n",
    "tgn:placetype":[
        "aat:300008347"
    ]
},
  "bbox": [],
  "geometry": {"coordinates":[-1.816667,37.833333],"type":"Point"}
}