{
  "id": 7015695,
  "type": "Feature",
  "properties": {
    "tgn:hierarchy":[
        "tgn:7015695",
        "tgn:1000001",
        "tgn:7013596",
        "tgn:7013649",
        "tgn:7012149",
        "tgn:7007251",
        "tgn:7029392"
    ],
    "tgn:id":7015695,
    "tgn:name":"Hegewisch",
    "tgn:placetype":[
        "aat:300000745"
    ]
},
  "bbox": [],
  "geometry": {"coordinates":[-87.5333,41.65],"type":"Point"}
}