{
  "id": 2388575,
  "type": "Feature",
  "properties": {
    "tgn:hierarchy":[
        "tgn:2388575",
        "tgn:1000001",
        "tgn:7012149",
        "tgn:2001917",
        "tgn:7007825",
        "tgn:7029392"
    ],
    "tgn:id":2388575,
    "tgn:name":"Hicks Hollow",
    "tgn:placetype":[
        "aat:300008761"
    ]
},
  "bbox": [],
  "geometry": {"coordinates":[-88.0333,36.6667],"type":"Point"}
}