{
  "id": 7308950,
  "type": "Feature",
  "properties": {
    "tgn:hierarchy":[
        "tgn:7308950",
        "tgn:1001768",
        "tgn:1000049",
        "tgn:1000002",
        "tgn:7029392"
    ],
    "tgn:id":7308950,
    "tgn:name":"Madera, Cerro",
    "tgn:placetype":[
        "aat:300008777"
    ]
},
  "bbox": [],
  "geometry": {"coordinates":[-71.483333,-32.883333],"type":"Point"}
}