{
  "id": 7146036,
  "type": "Feature",
  "properties": {
    "tgn:hierarchy":[
        "tgn:7146036",
        "tgn:1000003",
        "tgn:7003682",
        "tgn:7000084",
        "tgn:7029392"
    ],
    "tgn:id":7146036,
    "tgn:name":"Knaben-Berg",
    "tgn:placetype":[
        "aat:300008777"
    ]
},
  "bbox": [],
  "geometry": {"coordinates":[7.766667,50.716667],"type":"Point"}
}