{
  "id": 2170252,
  "type": "Feature",
  "properties": {
    "tgn:hierarchy":[
        "tgn:2170252",
        "tgn:1000001",
        "tgn:7006451",
        "tgn:2000093",
        "tgn:7012149",
        "tgn:7029392"
    ],
    "tgn:id":2170252,
    "tgn:name":"Big Ridge",
    "tgn:placetype":[
        "aat:300266640"
    ]
},
  "bbox": [],
  "geometry": {"coordinates":[-111.0167,34.2167],"type":"Point"}
}