{
  "id": 7477057,
  "type": "Feature",
  "properties": {
    "tgn:hierarchy":[
        "tgn:7477057",
        "tgn:7487020",
        "tgn:1000004",
        "tgn:1000141",
        "tgn:7029392"
    ],
    "tgn:id":7477057,
    "tgn:name":"Mingde",
    "tgn:placetype":[
        "aat:300008347"
    ]
},
  "bbox": [],
  "geometry": {"coordinates":[120.880174,24.584813],"type":"Point"}
}