<<<<<<< HEAD
{
  "id": 7477057,
  "type": "Feature",
  "properties": {
    "tgn:hierarchy":[
        "tgn:7477057",
        "tgn:7487020",
        "tgn:1000004",
        "tgn:1000141",
        "tgn:7029392"
    ],
    "tgn:id":7477057,
    "tgn:name":"Mingde",
    "tgn:placetype":[
        "aat:300008347"
    ]
},
  "bbox": [],
  "geometry": {"coordinates":[120.880174,24.584813],"type":"Point"}
}
=======
{"geometry":{"type":"Point","coordinates":[120.880174,24.584813]},"type":"Feature","properties":{"hierarchy":["tgn:7477057","tgn:7487020","tgn:1000004","tgn:1000141","tgn:7029392"],"placetype":["aat:300008347"],"id":7477057,"name:xx":"Mingde"}}
>>>>>>> 03f74aca74312dbeaf24d7e61306dd6a786dc3d0
