{
  "id": 2737691,
  "type": "Feature",
  "properties": {
    "tgn:hierarchy":[
        "tgn:2737691",
        "tgn:1000001",
        "tgn:1002286",
        "tgn:7012149",
        "tgn:7007710",
        "tgn:7029392"
    ],
    "tgn:id":2737691,
    "tgn:name":"Tylersville Spring",
    "tgn:placetype":[
        "aat:300008697"
    ]
},
  "bbox": [],
  "geometry": {"coordinates":[-77.4167,40.9833],"type":"Point"}
}