{
  "id": 7033985,
  "type": "Feature",
  "properties": {
    "tgn:hierarchy":[
        "tgn:7033985",
        "tgn:1001641",
        "tgn:1000003",
        "tgn:7003121",
        "tgn:1000080",
        "tgn:7029392"
    ],
    "tgn:id":7033985,
    "tgn:name":"Su Concali",
    "tgn:placetype":[
        "aat:300008795"
    ]
},
  "bbox": [],
  "geometry": {"coordinates":[8.903056,39.208611],"type":"Point"}
}