{
  "id": 7469411,
  "type": "Feature",
  "properties": {
    "tgn:hierarchy":[
        "tgn:7469411",
        "tgn:1000004",
        "tgn:1000454",
        "tgn:1000141",
        "tgn:7029392"
    ],
    "tgn:id":7469411,
    "tgn:name":"Zhongkeng",
    "tgn:placetype":[
        "aat:300008347"
    ]
},
  "bbox": [],
  "geometry": {"coordinates":[121.432136,25.116925],"type":"Point"}
}