{
  "id": 2108505,
  "type": "Feature",
  "properties": {
    "tgn:hierarchy":[
        "tgn:2108505",
        "tgn:1000001",
        "tgn:7012149",
        "tgn:2001996",
        "tgn:7007826",
        "tgn:7029392"
    ],
    "tgn:id":2108505,
    "tgn:name":"Whiteway",
    "tgn:placetype":[
        "aat:300008347",
        "aat:300387210"
    ]
},
  "bbox": [],
  "geometry": {"coordinates":[-97.9667,31.6333],"type":"Point"}
}