{
  "id": 2337750,
  "type": "Feature",
  "properties": {
    "tgn:hierarchy":[
        "tgn:2337750",
        "tgn:1000001",
        "tgn:7012149",
        "tgn:2001201",
        "tgn:7007523",
        "tgn:7029392"
    ],
    "tgn:id":2337750,
    "tgn:name":"Fox Creek",
    "tgn:placetype":[
        "aat:300008706"
    ]
},
  "bbox": [],
  "geometry": {"coordinates":[-93.85,40.2667],"type":"Point"}
}