<<<<<<< HEAD
{
  "id": 2337750,
  "type": "Feature",
  "properties": {
    "tgn:hierarchy":[
        "tgn:2337750",
        "tgn:1000001",
        "tgn:7012149",
        "tgn:2001201",
        "tgn:7007523",
        "tgn:7029392"
    ],
    "tgn:id":2337750,
    "tgn:name":"Fox Creek",
    "tgn:placetype":[
        "aat:300008706"
    ]
},
  "bbox": [],
  "geometry": {"coordinates":[-93.85,40.2667],"type":"Point"}
}
=======
{"geometry":{"type":"Point","coordinates":[-93.850000,40.266700]},"type":"Feature","properties":{"hierarchy":["tgn:2337750","tgn:1000001","tgn:7012149","tgn:2001201","tgn:7007523","tgn:7029392"],"placetype":["aat:300008706"],"id":2337750,"name:xx":"Fox Creek"}}
>>>>>>> 03f74aca74312dbeaf24d7e61306dd6a786dc3d0
