{
  "id": 7436044,
  "type": "Feature",
  "properties": {
    "tgn:hierarchy":[
        "tgn:7436044",
        "tgn:7005581",
        "tgn:1000001",
        "tgn:7005560",
        "tgn:7029392"
    ],
    "tgn:id":7436044,
    "tgn:name":"Sombreretillo, Cerro",
    "tgn:placetype":[
        "aat:300008777"
    ]
},
  "bbox": [],
  "geometry": {"coordinates":[-107.383333,30.683333],"type":"Point"}
}