{
  "id": 2663187,
  "type": "Feature",
  "properties": {
    "tgn:hierarchy":[
        "tgn:2663187",
        "tgn:1000001",
        "tgn:7012149",
        "tgn:7007248",
        "tgn:7029392"
    ],
    "tgn:id":2663187,
    "tgn:name":"Silver Creek",
    "tgn:placetype":[
        "aat:300008706"
    ]
},
  "bbox": [],
  "geometry": {"coordinates":[-85.15,34.05],"type":"Point"}
}