<<<<<<< HEAD
{
  "id": 7021320,
  "type": "Feature",
  "properties": {
    "tgn:hierarchy":[
        "tgn:7021320",
        "tgn:1000001",
        "tgn:7012149",
        "tgn:2002287",
        "tgn:7013961",
        "tgn:7029392"
    ],
    "tgn:id":7021320,
    "tgn:name":"Hughes Creek Lower Cave",
    "tgn:placetype":[
        "aat:300008746"
    ]
},
  "bbox": [],
  "geometry": {"coordinates":[-80.25,38.1167],"type":"Point"}
}
=======
{"geometry":{"type":"Point","coordinates":[-80.250000,38.116700]},"type":"Feature","properties":{"hierarchy":["tgn:7021320","tgn:1000001","tgn:7012149","tgn:2002287","tgn:7013961","tgn:7029392"],"placetype":["aat:300008746"],"id":7021320,"name:xx":"Hughes Creek Lower Cave"}}
>>>>>>> 03f74aca74312dbeaf24d7e61306dd6a786dc3d0
