<<<<<<< HEAD
{
  "id": 2151955,
  "type": "Feature",
  "properties": {
    "tgn:hierarchy":[
        "tgn:2151955",
        "tgn:1000001",
        "tgn:7012149",
        "tgn:2000230",
        "tgn:7007158",
        "tgn:7029392"
    ],
    "tgn:id":2151955,
    "tgn:name":"Baugh Reservoir",
    "tgn:placetype":[
        "aat:300006191"
    ]
},
  "bbox": [],
  "geometry": {"coordinates":[-108.2,39.2167],"type":"Point"}
}
=======
{"geometry":{"type":"Point","coordinates":[-108.200000,39.216700]},"type":"Feature","properties":{"hierarchy":["tgn:2151955","tgn:1000001","tgn:7012149","tgn:2000230","tgn:7007158","tgn:7029392"],"placetype":["aat:300006191"],"id":2151955,"name:xx":"Baugh Reservoir"}}
>>>>>>> 03f74aca74312dbeaf24d7e61306dd6a786dc3d0
