{
  "id": 2246627,
  "type": "Feature",
  "properties": {
    "tgn:hierarchy":[
        "tgn:2246627",
        "tgn:1000001",
        "tgn:2000773",
        "tgn:7012149",
        "tgn:7007255",
        "tgn:7029392"
    ],
    "tgn:id":2246627,
    "tgn:name":"Cobblers Knob",
    "tgn:placetype":[
        "aat:300008347"
    ]
},
  "bbox": [],
  "geometry": {"coordinates":[-86.3833,37.5667],"type":"Point"}
}