{
  "id": 2421288,
  "type": "Feature",
  "properties": {
    "tgn:hierarchy":[
        "tgn:2421288",
        "tgn:2000855",
        "tgn:1000001",
        "tgn:7012149",
        "tgn:7007256",
        "tgn:7029392"
    ],
    "tgn:id":2421288,
    "tgn:name":"Jerry Wright Lake",
    "tgn:placetype":[
        "aat:300008680"
    ]
},
  "bbox": [],
  "geometry": {"coordinates":[-92.8833,30.7167],"type":"Point"}
}