{
  "id": 2232302,
  "type": "Feature",
  "properties": {
    "tgn:hierarchy":[
        "tgn:2232302",
        "tgn:1000001",
        "tgn:7006451",
        "tgn:7012149",
        "tgn:2000099",
        "tgn:7029392"
    ],
    "tgn:id":2232302,
    "tgn:name":"Chandler Springs",
    "tgn:placetype":[
        "aat:300008697"
    ]
},
  "bbox": [],
  "geometry": {"coordinates":[-110.4667,35.3667],"type":"Point"}
}