<<<<<<< HEAD
{
  "id": 7023717,
  "type": "Feature",
  "properties": {
    "tgn:hierarchy":[
        "tgn:7023717",
        "tgn:1000001",
        "tgn:7012149",
        "tgn:7007521",
        "tgn:7029392"
    ],
    "tgn:id":7023717,
    "tgn:name":"Pug Hole Lake",
    "tgn:placetype":[
        "aat:300008680"
    ]
},
  "bbox": [],
  "geometry": {"coordinates":[-94.0,46.7833],"type":"Point"}
}
=======
{"geometry":{"type":"Point","coordinates":[-94.000000,46.783300]},"type":"Feature","properties":{"hierarchy":["tgn:7023717","tgn:1000001","tgn:7012149","tgn:7007521","tgn:7029392"],"placetype":["aat:300008680"],"id":7023717,"name:xx":"Pug Hole Lake"}}
>>>>>>> 03f74aca74312dbeaf24d7e61306dd6a786dc3d0
