{
  "id": 2461371,
  "type": "Feature",
  "properties": {
    "tgn:hierarchy":[
        "tgn:2461371",
        "tgn:1000001",
        "tgn:7012149",
        "tgn:2001067",
        "tgn:7007521",
        "tgn:7029392"
    ],
    "tgn:id":2461371,
    "tgn:name":"Little Sucker River",
    "tgn:placetype":[
        "aat:300008707"
    ]
},
  "bbox": [],
  "geometry": {"coordinates":[-91.85,46.9333],"type":"Point"}
}