{
  "id": 7562797,
  "type": "Feature",
  "properties": {
    "tgn:hierarchy":[
        "tgn:7562797",
        "tgn:1000004",
        "tgn:7000198",
        "tgn:7016722",
        "tgn:7029392"
    ],
    "tgn:id":7562797,
    "tgn:name:en":"G\u016bnj Kal\u0101n",
    "tgn:placetype":[
        "aat:300008347"
    ]
},
  "bbox": [],
  "geometry": {"coordinates":[79.229972,26.433387],"type":"Point"}
}