{
  "id": 7493068,
  "type": "Feature",
  "properties": {
    "tgn:hierarchy":[
        "tgn:7493068",
        "tgn:7488858",
        "tgn:1000004",
        "tgn:1000141",
        "tgn:7029392"
    ],
    "tgn:id":7493068,
    "tgn:name":"Bishanyan",
    "tgn:placetype":[
        "aat:300132356"
    ]
},
  "bbox": [],
  "geometry": {"coordinates":[120.633333,23.966667],"type":"Point"}
}