{
  "id": 7373390,
  "type": "Feature",
  "properties": {
    "tgn:hierarchy":[
        "tgn:7373390",
        "tgn:1000001",
        "tgn:7005589",
        "tgn:7005560",
        "tgn:7029392"
    ],
    "tgn:id":7373390,
    "tgn:name":"La Lasilla, Ca\u00f1\u00f3n de",
    "tgn:placetype":[
        "aat:300008763"
    ]
},
  "bbox": [],
  "geometry": {"coordinates":[-100.066667,24.916667],"type":"Point"}
}