<<<<<<< HEAD
{
  "id": 2760372,
  "type": "Feature",
  "properties": {
    "tgn:hierarchy":[
        "tgn:2760372",
        "tgn:7002659",
        "tgn:1000001",
        "tgn:7012149",
        "tgn:2000038",
        "tgn:7029392"
    ],
    "tgn:id":2760372,
    "tgn:name":"West Fork Sixmile Creek",
    "tgn:placetype":[
        "aat:300008706"
    ]
},
  "bbox": [],
  "geometry": {"coordinates":[-87.5333,34.9333],"type":"Point"}
}
=======
{"geometry":{"type":"Point","coordinates":[-87.533300,34.933300]},"type":"Feature","properties":{"hierarchy":["tgn:2760372","tgn:7002659","tgn:1000001","tgn:7012149","tgn:2000038","tgn:7029392"],"placetype":["aat:300008706"],"id":2760372,"name:xx":"West Fork Sixmile Creek"}}
>>>>>>> 03f74aca74312dbeaf24d7e61306dd6a786dc3d0
