{
  "id": 2742990,
  "type": "Feature",
  "properties": {
    "tgn:hierarchy":[
        "tgn:2742990",
        "tgn:1000001",
        "tgn:1002286",
        "tgn:7012149",
        "tgn:7007710",
        "tgn:7029392"
    ],
    "tgn:id":2742990,
    "tgn:name":"Van Sickle Hollow",
    "tgn:placetype":[
        "aat:300008761"
    ]
},
  "bbox": [],
  "geometry": {"coordinates":[-77.7333,41.3833],"type":"Point"}
}