{
  "id": 7285109,
  "type": "Feature",
  "properties": {
    "tgn:hierarchy":[
        "tgn:7285109",
        "tgn:1001768",
        "tgn:1000049",
        "tgn:1000002",
        "tgn:7029392"
    ],
    "tgn:id":7285109,
    "tgn:name":"Polcura, Quebrada",
    "tgn:placetype":[
        "aat:300008699"
    ]
},
  "bbox": [],
  "geometry": {"coordinates":[-70.883333,-32.233333],"type":"Point"}
}