{
  "id": 7497015,
  "type": "Feature",
  "properties": {
    "tgn:hierarchy":[
        "tgn:7497015",
        "tgn:7001004",
        "tgn:1000004",
        "tgn:1000141",
        "tgn:7029392"
    ],
    "tgn:id":7497015,
    "tgn:name":"Qianzhen Guoxiao",
    "tgn:placetype":[
        "aat:300006495"
    ]
},
  "bbox": [],
  "geometry": {"coordinates":[120.308857,22.5861],"type":"Point"}
}