<<<<<<< HEAD
{
  "id": 2400883,
  "type": "Feature",
  "properties": {
    "tgn:hierarchy":[
        "tgn:2400883",
        "tgn:1000001",
        "tgn:7012149",
        "tgn:1003042",
        "tgn:7007920",
        "tgn:7029392"
    ],
    "tgn:id":2400883,
    "tgn:name":"Horse Ridge",
    "tgn:placetype":[
        "aat:300266640"
    ]
},
  "bbox": [],
  "geometry": {"coordinates":[-120.9667,46.7333],"type":"Point"}
}
=======
{"geometry":{"type":"Point","coordinates":[-120.966700,46.733300]},"type":"Feature","properties":{"hierarchy":["tgn:2400883","tgn:1000001","tgn:7012149","tgn:1003042","tgn:7007920","tgn:7029392"],"placetype":["aat:300266640"],"id":2400883,"name:xx":"Horse Ridge"}}
>>>>>>> 03f74aca74312dbeaf24d7e61306dd6a786dc3d0
