{
  "id": 2400883,
  "type": "Feature",
  "properties": {
    "tgn:hierarchy":[
        "tgn:2400883",
        "tgn:1000001",
        "tgn:7012149",
        "tgn:1003042",
        "tgn:7007920",
        "tgn:7029392"
    ],
    "tgn:id":2400883,
    "tgn:name":"Horse Ridge",
    "tgn:placetype":[
        "aat:300266640"
    ]
},
  "bbox": [],
  "geometry": {"coordinates":[-120.9667,46.7333],"type":"Point"}
}