{
  "id": 2233326,
  "type": "Feature",
  "properties": {
    "tgn:hierarchy":[
        "tgn:2233326",
        "tgn:1000001",
        "tgn:7012149",
        "tgn:1002971",
        "tgn:7007710",
        "tgn:7029392"
    ],
    "tgn:id":2233326,
    "tgn:name":"Charley Run",
    "tgn:placetype":[
        "aat:300008699"
    ]
},
  "bbox": [],
  "geometry": {"coordinates":[-79.7333,41.45],"type":"Point"}
}