{
  "id": 7293258,
  "type": "Feature",
  "properties": {
    "tgn:hierarchy":[
        "tgn:7293258",
        "tgn:7002758",
        "tgn:7002823",
        "tgn:1000003",
        "tgn:1000095",
        "tgn:7029392"
    ],
    "tgn:id":7293258,
    "tgn:name":"Casa de Martinazo",
    "tgn:placetype":[
        "aat:300005433"
    ]
},
  "bbox": [],
  "geometry": {"coordinates":[-6.441389,37.025833],"type":"Point"}
}