<<<<<<< HEAD
{
  "id": 7485067,
  "type": "Feature",
  "properties": {
    "tgn:hierarchy":[
        "tgn:7485067",
        "tgn:7468018",
        "tgn:1000004",
        "tgn:1000141",
        "tgn:7029392"
    ],
    "tgn:id":7485067,
    "tgn:name":"Shexing Qiao",
    "tgn:placetype":[
        "aat:300007836"
    ]
},
  "bbox": [],
  "geometry": {"coordinates":[120.727222,23.556389],"type":"Point"}
}
=======
{"geometry":{"type":"Point","coordinates":[120.727222,23.556389]},"type":"Feature","properties":{"hierarchy":["tgn:7485067","tgn:7468018","tgn:1000004","tgn:1000141","tgn:7029392"],"placetype":["aat:300007836"],"id":7485067,"name:xx":"Shexing Qiao"}}
>>>>>>> 03f74aca74312dbeaf24d7e61306dd6a786dc3d0
