{
  "id": 1024360,
  "type": "Feature",
  "properties": {
    "tgn:hierarchy":[
        "tgn:1024360",
        "tgn:1000508",
        "tgn:1000002",
        "tgn:1000056",
        "tgn:7029392"
    ],
    "tgn:id":1024360,
    "tgn:name":"Andaray",
    "tgn:placetype":[
        "aat:300008347"
    ]
},
  "bbox": [],
  "geometry": {"coordinates":[-72.8333,-15.8167],"type":"Point"}
}