<<<<<<< HEAD
{
  "id": 7368262,
  "type": "Feature",
  "properties": {
    "tgn:hierarchy":[
        "tgn:7368262",
        "tgn:1000001",
        "tgn:7005591",
        "tgn:7005560",
        "tgn:7029392"
    ],
    "tgn:id":7368262,
    "tgn:name":"Josefinos",
    "tgn:placetype":[
        "aat:300008347"
    ]
},
  "bbox": [],
  "geometry": {"coordinates":[-96.15,17.65],"type":"Point"}
}
=======
{"geometry":{"type":"Point","coordinates":[-96.150000,17.650000]},"type":"Feature","properties":{"hierarchy":["tgn:7368262","tgn:1000001","tgn:7005591","tgn:7005560","tgn:7029392"],"placetype":["aat:300008347"],"id":7368262,"name:xx":"Josefinos"}}
>>>>>>> 03f74aca74312dbeaf24d7e61306dd6a786dc3d0
