{
  "id": 7360538,
  "type": "Feature",
  "properties": {
    "tgn:hierarchy":[
        "tgn:7360538",
        "tgn:7005581",
        "tgn:1000001",
        "tgn:7005560",
        "tgn:7029392"
    ],
    "tgn:id":7360538,
    "tgn:name":"Rancho Ecovichic",
    "tgn:placetype":[
        "aat:300000241"
    ]
},
  "bbox": [],
  "geometry": {"coordinates":[-107.65,27.683333],"type":"Point"}
}