{
  "id": 2240006,
  "type": "Feature",
  "properties": {
    "tgn:hierarchy":[
        "tgn:2240006",
        "tgn:1000001",
        "tgn:7012149",
        "tgn:2002280",
        "tgn:7013961",
        "tgn:7029392"
    ],
    "tgn:id":2240006,
    "tgn:name":"Cinderella Impoundment Number Two",
    "tgn:placetype":[
        "aat:300006191"
    ]
},
  "bbox": [],
  "geometry": {"coordinates":[-82.2333,37.6667],"type":"Point"}
}