{
  "id": 2608749,
  "type": "Feature",
  "properties": {
    "tgn:hierarchy":[
        "tgn:2608749",
        "tgn:1000001",
        "tgn:7012149",
        "tgn:2001720",
        "tgn:7007708",
        "tgn:7029392"
    ],
    "tgn:id":2608749,
    "tgn:name":"Rattlesnake Ridge",
    "tgn:placetype":[
        "aat:300266640"
    ]
},
  "bbox": [],
  "geometry": {"coordinates":[-118.3333,45.65],"type":"Point"}
}