{
  "id": 2529550,
  "type": "Feature",
  "properties": {
    "tgn:hierarchy":[
        "tgn:2529550",
        "tgn:1000001",
        "tgn:7012149",
        "tgn:1002980",
        "tgn:7007826",
        "tgn:7029392"
    ],
    "tgn:id":2529550,
    "tgn:name":"Mud Lake",
    "tgn:placetype":[
        "aat:300008680"
    ]
},
  "bbox": [],
  "geometry": {"coordinates":[-95.4333,30.85],"type":"Point"}
}