{
  "id": 2645859,
  "type": "Feature",
  "properties": {
    "tgn:hierarchy":[
        "tgn:2645859",
        "tgn:1000001",
        "tgn:7012149",
        "tgn:2002381",
        "tgn:7007923",
        "tgn:7029392"
    ],
    "tgn:id":2645859,
    "tgn:name":"Sawmill Creek",
    "tgn:placetype":[
        "aat:300008706"
    ]
},
  "bbox": [],
  "geometry": {"coordinates":[-107.3333,44.6333],"type":"Point"}
}