{
  "id": 2663110,
  "type": "Feature",
  "properties": {
    "tgn:hierarchy":[
        "tgn:2663110",
        "tgn:1000001",
        "tgn:7012149",
        "tgn:2000763",
        "tgn:7007254",
        "tgn:7029392"
    ],
    "tgn:id":2663110,
    "tgn:name":"Silver City Dome",
    "tgn:placetype":[
        "aat:300008798"
    ]
},
  "bbox": [],
  "geometry": {"coordinates":[-95.7833,37.75],"type":"Point"}
}