{
  "id": 2741106,
  "type": "Feature",
  "properties": {
    "tgn:hierarchy":[
        "tgn:2741106",
        "tgn:2000090",
        "tgn:1000001",
        "tgn:7006451",
        "tgn:7012149",
        "tgn:7029392"
    ],
    "tgn:id":2741106,
    "tgn:name":"Upper Tank",
    "tgn:placetype":[
        "aat:300006191"
    ]
},
  "bbox": [],
  "geometry": {"coordinates":[-109.15,34.4167],"type":"Point"}
}