{
  "id": 2324420,
  "type": "Feature",
  "properties": {
    "tgn:hierarchy":[
        "tgn:2324420",
        "tgn:1000001",
        "tgn:7012149",
        "tgn:1003048",
        "tgn:7007919",
        "tgn:7029392"
    ],
    "tgn:id":2324420,
    "tgn:name":"Felgates Creek",
    "tgn:placetype":[
        "aat:300008706"
    ]
},
  "bbox": [],
  "geometry": {"coordinates":[-76.55,37.2167],"type":"Point"}
}