{
  "id": 1053456,
  "type": "Feature",
  "properties": {
    "tgn:hierarchy":[
        "tgn:1053456",
        "tgn:7012158",
        "tgn:1000003",
        "tgn:7006657",
        "tgn:7029392"
    ],
    "tgn:id":1053456,
    "tgn:name":"Dyatlovo",
    "tgn:placetype":[
        "aat:300008347"
    ]
},
  "bbox": [],
  "geometry": {"coordinates":[25.4667,53.4667],"type":"Point"}
}