{
  "id": 2775831,
  "type": "Feature",
  "properties": {
    "tgn:hierarchy":[
        "tgn:2775831",
        "tgn:1000001",
        "tgn:7012149",
        "tgn:2000977",
        "tgn:7007520",
        "tgn:7029392"
    ],
    "tgn:id":2775831,
    "tgn:name":"Wilson Lake",
    "tgn:placetype":[
        "aat:300008680"
    ]
},
  "bbox": [],
  "geometry": {"coordinates":[-85.15,43.65],"type":"Point"}
}