{
  "id": 2774362,
  "type": "Feature",
  "properties": {
    "tgn:hierarchy":[
        "tgn:2774362",
        "tgn:1000001",
        "tgn:2001339",
        "tgn:7012149",
        "tgn:7007525",
        "tgn:7029392"
    ],
    "tgn:id":2774362,
    "tgn:name":"Willow Island",
    "tgn:placetype":[
        "aat:300008791"
    ]
},
  "bbox": [],
  "geometry": {"coordinates":[-100.0833,40.8667],"type":"Point"}
}