{
  "id": 7427276,
  "type": "Feature",
  "properties": {
    "tgn:hierarchy":[
        "tgn:7427276",
        "tgn:7005581",
        "tgn:1000001",
        "tgn:7005560",
        "tgn:7029392"
    ],
    "tgn:id":7427276,
    "tgn:name":"Las Juntas",
    "tgn:placetype":[
        "aat:300008347"
    ]
},
  "bbox": [],
  "geometry": {"coordinates":[-107.066667,27.866667],"type":"Point"}
}