<<<<<<< HEAD
{
  "id": 2154630,
  "type": "Feature",
  "properties": {
    "tgn:hierarchy":[
        "tgn:2154630",
        "tgn:1000001",
        "tgn:7012149",
        "tgn:7014589",
        "tgn:7007515",
        "tgn:7029392"
    ],
    "tgn:id":2154630,
    "tgn:name":"Bear Frap Landing",
    "tgn:placetype":[
        "aat:300008347"
    ]
},
  "bbox": [],
  "geometry": {"coordinates":[-67.7833,45.2333],"type":"Point"}
}
=======
{"geometry":{"type":"Point","coordinates":[-67.783300,45.233300]},"type":"Feature","properties":{"hierarchy":["tgn:2154630","tgn:1000001","tgn:7012149","tgn:7014589","tgn:7007515","tgn:7029392"],"placetype":["aat:300008347"],"id":2154630,"name:xx":"Bear Frap Landing"}}
>>>>>>> 03f74aca74312dbeaf24d7e61306dd6a786dc3d0
