{
  "id": 7307848,
  "type": "Feature",
  "properties": {
    "tgn:hierarchy":[
        "tgn:7307848",
        "tgn:1001657",
        "tgn:1000049",
        "tgn:1000002",
        "tgn:7029392"
    ],
    "tgn:id":7307848,
    "tgn:name":"Oeste, Punta",
    "tgn:placetype":[
        "aat:300386846"
    ]
},
  "bbox": [],
  "geometry": {"coordinates":[-71.466667,-30.166667],"type":"Point"}
}