{
  "id": 2601180,
  "type": "Feature",
  "properties": {
    "tgn:hierarchy":[
        "tgn:2601180",
        "tgn:1000001",
        "tgn:7012149",
        "tgn:2001506",
        "tgn:7007709",
        "tgn:7029392"
    ],
    "tgn:id":2601180,
    "tgn:name":"Pungo Lake Canal",
    "tgn:placetype":[
        "aat:300006075"
    ]
},
  "bbox": [],
  "geometry": {"coordinates":[-76.55,35.65],"type":"Point"}
}