{
  "id": 2634222,
  "type": "Feature",
  "properties": {
    "tgn:hierarchy":[
        "tgn:2634222",
        "tgn:1000001",
        "tgn:7012149",
        "tgn:2000794",
        "tgn:7007255",
        "tgn:7029392"
    ],
    "tgn:id":2634222,
    "tgn:name":"Russell Island",
    "tgn:placetype":[
        "aat:300008791"
    ]
},
  "bbox": [],
  "geometry": {"coordinates":[-85.4667,37.2667],"type":"Point"}
}