{
  "id": 7590463,
  "type": "Feature",
  "properties": {
    "tgn:hierarchy":[
        "tgn:7590463",
        "tgn:1000004",
        "tgn:7000198",
        "tgn:7000799",
        "tgn:7029392"
    ],
    "tgn:id":7590463,
    "tgn:name:en":"Chor Kunji\u0101n",
    "tgn:placetype":[
        "aat:300008347"
    ]
},
  "bbox": [],
  "geometry": {"coordinates":[73.85,34.355556],"type":"Point"}
}