{
  "id": 7538330,
  "type": "Feature",
  "properties": {
    "tgn:hierarchy":[
        "tgn:7538330",
        "tgn:7001242",
        "tgn:7016833",
        "tgn:1001123",
        "tgn:7029392"
    ],
    "tgn:id":7538330,
    "tgn:name":"Riqqah, Barr ar",
    "tgn:placetype":[
        "aat:300008733"
    ]
},
  "bbox": [],
  "geometry": {"coordinates":[32.096944,31.1025],"type":"Point"}
}