{
  "id": 7057738,
  "type": "Feature",
  "properties": {
    "tgn:hierarchy":[
        "tgn:7057738",
        "tgn:7005852",
        "tgn:1000003",
        "tgn:7003237",
        "tgn:1000080",
        "tgn:7029392"
    ],
    "tgn:id":7057738,
    "tgn:name":"Bugiallo",
    "tgn:placetype":[
        "aat:300008347"
    ]
},
  "bbox": [],
  "geometry": {"coordinates":[9.383333,46.183333],"type":"Point"}
}