{
  "id": 7166325,
  "type": "Feature",
  "properties": {
    "tgn:hierarchy":[
        "tgn:7166325",
        "tgn:1000003",
        "tgn:7003676",
        "tgn:7000084",
        "tgn:7029392"
    ],
    "tgn:id":7166325,
    "tgn:name":"Heitmannsh\u00e4usern",
    "tgn:placetype":[
        "aat:300008347"
    ]
},
  "bbox": [],
  "geometry": {"coordinates":[8.566667,52.683333],"type":"Point"}
}