{
  "id": 2538909,
  "type": "Feature",
  "properties": {
    "tgn:hierarchy":[
        "tgn:2538909",
        "tgn:1000001",
        "tgn:7012149",
        "tgn:7007157",
        "tgn:2000189",
        "tgn:7029392"
    ],
    "tgn:id":2538909,
    "tgn:name":"New Barn Gulch",
    "tgn:placetype":[
        "aat:300008761"
    ]
},
  "bbox": [],
  "geometry": {"coordinates":[-122.95,41.75],"type":"Point"}
}