{
  "id": 2313819,
  "type": "Feature",
  "properties": {
    "tgn:hierarchy":[
        "tgn:2313819",
        "tgn:1000001",
        "tgn:7012149",
        "tgn:2002374",
        "tgn:7007923",
        "tgn:7029392"
    ],
    "tgn:id":2313819,
    "tgn:name":"Elgin Creek",
    "tgn:placetype":[
        "aat:300008706"
    ]
},
  "bbox": [],
  "geometry": {"coordinates":[-106.8833,44.2333],"type":"Point"}
}