{
  "id": 2600658,
  "type": "Feature",
  "properties": {
    "tgn:hierarchy":[
        "tgn:2600658",
        "tgn:1000001",
        "tgn:7016172",
        "tgn:7012149",
        "tgn:2000140",
        "tgn:7029392"
    ],
    "tgn:id":2600658,
    "tgn:name":"Pullman Hollow",
    "tgn:placetype":[
        "aat:300008761"
    ]
},
  "bbox": [],
  "geometry": {"coordinates":[-93.4333,35.6167],"type":"Point"}
}