{
  "id": 2290966,
  "type": "Feature",
  "properties": {
    "tgn:hierarchy":[
        "tgn:2290966",
        "tgn:7006450",
        "tgn:1000001",
        "tgn:7012149",
        "tgn:2124002",
        "tgn:7029392"
    ],
    "tgn:id":2290966,
    "tgn:name":"Dog Point",
    "tgn:placetype":[
        "aat:300008850"
    ]
},
  "bbox": [],
  "geometry": {"coordinates":[-135.4167,57.1667],"type":"Point"}
}