{
  "id": 7334530,
  "type": "Feature",
  "properties": {
    "tgn:hierarchy":[
        "tgn:7334530",
        "tgn:7002820",
        "tgn:7030216",
        "tgn:1000003",
        "tgn:1000095",
        "tgn:7029392"
    ],
    "tgn:id":7334530,
    "tgn:name":"El Grao",
    "tgn:placetype":[
        "aat:300008347"
    ]
},
  "bbox": [],
  "geometry": {"coordinates":[3.15,42.25],"type":"Point"}
}