{
  "id": 7562042,
  "type": "Feature",
  "properties": {
    "tgn:hierarchy":[
        "tgn:7562042",
        "tgn:1000004",
        "tgn:7000198",
        "tgn:7016722",
        "tgn:7029392"
    ],
    "tgn:id":7562042,
    "tgn:name:en":"Nagla Shibl\u0101l",
    "tgn:placetype":[
        "aat:300008347"
    ]
},
  "bbox": [],
  "geometry": {"coordinates":[79.327529,27.061842],"type":"Point"}
}