{
  "id": 2393671,
  "type": "Feature",
  "properties": {
    "tgn:hierarchy":[
        "tgn:2393671",
        "tgn:7019618",
        "tgn:1000001",
        "tgn:7012149",
        "tgn:7007564",
        "tgn:7029392"
    ],
    "tgn:id":2393671,
    "tgn:name":"Hog Hill",
    "tgn:placetype":[
        "aat:300008798"
    ]
},
  "bbox": [],
  "geometry": {"coordinates":[-72.05,42.7167],"type":"Point"}
}