{
  "id": 2640645,
  "type": "Feature",
  "properties": {
    "tgn:hierarchy":[
        "tgn:2640645",
        "tgn:1000001",
        "tgn:7012149",
        "tgn:7007157",
        "tgn:1002858",
        "tgn:7029392"
    ],
    "tgn:id":2640645,
    "tgn:name":"San Marcos Creek",
    "tgn:placetype":[
        "aat:300008706"
    ]
},
  "bbox": [],
  "geometry": {"coordinates":[-117.15,33.1333],"type":"Point"}
}