{
  "id": 1086530,
  "type": "Feature",
  "properties": {
    "tgn:hierarchy":[
        "tgn:1086530",
        "tgn:1001101",
        "tgn:1000004",
        "tgn:7018453",
        "tgn:1000144",
        "tgn:7029392"
    ],
    "tgn:id":1086530,
    "tgn:name":"Kara\u015far",
    "tgn:placetype":[
        "aat:300008347"
    ]
},
  "bbox": [],
  "geometry": {"coordinates":[32.0167,40.3333],"type":"Point"}
}