{
  "id": 2255242,
  "type": "Feature",
  "properties": {
    "tgn:hierarchy":[
        "tgn:2255242",
        "tgn:1000001",
        "tgn:2001786",
        "tgn:7012149",
        "tgn:7007713",
        "tgn:7029392"
    ],
    "tgn:id":2255242,
    "tgn:name":"Cooper Ridge",
    "tgn:placetype":[
        "aat:300266640"
    ]
},
  "bbox": [],
  "geometry": {"coordinates":[-103.8667,43.8333],"type":"Point"}
}