{
  "id": 7331388,
  "type": "Feature",
  "properties": {
    "tgn:hierarchy":[
        "tgn:7331388",
        "tgn:7002759",
        "tgn:7002843",
        "tgn:1000003",
        "tgn:1000095",
        "tgn:7029392"
    ],
    "tgn:id":7331388,
    "tgn:name":"La Codo\u00f1era",
    "tgn:placetype":[
        "aat:300008347"
    ]
},
  "bbox": [],
  "geometry": {"coordinates":[-0.083333,40.933333],"type":"Point"}
}