{
  "id": 7553931,
  "type": "Feature",
  "properties": {
    "tgn:hierarchy":[
        "tgn:7553931",
        "tgn:1000004",
        "tgn:7000198",
        "tgn:1001894",
        "tgn:7029392"
    ],
    "tgn:id":7553931,
    "tgn:name:en":"Mau",
    "tgn:placetype":[
        "aat:300008347"
    ]
},
  "bbox": [],
  "geometry": {"coordinates":[77.127254,23.95387],"type":"Point"}
}