{
  "id": 2279621,
  "type": "Feature",
  "properties": {
    "tgn:hierarchy":[
        "tgn:2279621",
        "tgn:1000001",
        "tgn:2000953",
        "tgn:7012149",
        "tgn:7007520",
        "tgn:7029392"
    ],
    "tgn:id":2279621,
    "tgn:name":"Deadman Swamp",
    "tgn:placetype":[
        "aat:300008905"
    ]
},
  "bbox": [],
  "geometry": {"coordinates":[-84.9167,43.8167],"type":"Point"}
}