{
  "id": 2425681,
  "type": "Feature",
  "properties": {
    "tgn:hierarchy":[
        "tgn:2425681",
        "tgn:1000001",
        "tgn:7012149",
        "tgn:2002378",
        "tgn:7007923",
        "tgn:7029392"
    ],
    "tgn:id":2425681,
    "tgn:name":"Johnston Number 1 Reservoir",
    "tgn:placetype":[
        "aat:300006191"
    ]
},
  "bbox": [],
  "geometry": {"coordinates":[-104.6167,43.2833],"type":"Point"}
}