<<<<<<< HEAD
{
  "id": 2769376,
  "type": "Feature",
  "properties": {
    "tgn:hierarchy":[
        "tgn:2769376",
        "tgn:1000001",
        "tgn:7012149",
        "tgn:1002691",
        "tgn:7007826",
        "tgn:7029392"
    ],
    "tgn:id":2769376,
    "tgn:name":"Wickizer Pond",
    "tgn:placetype":[
        "aat:300008905"
    ]
},
  "bbox": [],
  "geometry": {"coordinates":[-95.2833,30.1333],"type":"Point"}
}
=======
{"geometry":{"type":"Point","coordinates":[-95.283300,30.133300]},"type":"Feature","properties":{"hierarchy":["tgn:2769376","tgn:1000001","tgn:7012149","tgn:1002691","tgn:7007826","tgn:7029392"],"placetype":["aat:300008905"],"id":2769376,"name:xx":"Wickizer Pond"}}
>>>>>>> 03f74aca74312dbeaf24d7e61306dd6a786dc3d0
