{
  "id": 7256259,
  "type": "Feature",
  "properties": {
    "tgn:hierarchy":[
        "tgn:7256259",
        "tgn:7003457",
        "tgn:1000003",
        "tgn:1000063",
        "tgn:7018236",
        "tgn:7029392"
    ],
    "tgn:id":7256259,
    "tgn:name":"Westdeelrechtstraat",
    "tgn:placetype":[
        "aat:300008347"
    ]
},
  "bbox": [],
  "geometry": {"coordinates":[3.916667,51.133333],"type":"Point"}
}