{
  "id": 2574929,
  "type": "Feature",
  "properties": {
    "tgn:hierarchy":[
        "tgn:2574929",
        "tgn:1000001",
        "tgn:7012149",
        "tgn:2001454",
        "tgn:7007566",
        "tgn:7029392"
    ],
    "tgn:id":2574929,
    "tgn:name":"Penitente Peak",
    "tgn:placetype":[
        "aat:300008798"
    ]
},
  "bbox": [],
  "geometry": {"coordinates":[-105.75,35.7833],"type":"Point"}
}