{
  "id": 2413005,
  "type": "Feature",
  "properties": {
    "tgn:hierarchy":[
        "tgn:2413005",
        "tgn:1000001",
        "tgn:7012149",
        "tgn:2002384",
        "tgn:7007923",
        "tgn:7029392"
    ],
    "tgn:id":2413005,
    "tgn:name":"Inkwell Spring",
    "tgn:placetype":[
        "aat:300008697"
    ]
},
  "bbox": [],
  "geometry": {"coordinates":[-110.8333,44.4667],"type":"Point"}
}