{
  "id": 7501199,
  "type": "Feature",
  "properties": {
    "tgn:hierarchy":[
        "tgn:7501199",
        "tgn:1000004",
        "tgn:7467799",
        "tgn:1000141",
        "tgn:7029392"
    ],
    "tgn:id":7501199,
    "tgn:name":"Xiahanbao",
    "tgn:placetype":[
        "aat:300008347"
    ]
},
  "bbox": [],
  "geometry": {"coordinates":[120.380556,24.024167],"type":"Point"}
}