{
  "id": 1110698,
  "type": "Feature",
  "properties": {
    "tgn:hierarchy":[
        "tgn:1110698",
        "tgn:1001942",
        "tgn:1000047",
        "tgn:7002457",
        "tgn:1000002",
        "tgn:7017095",
        "tgn:7029392"
    ],
    "tgn:id":1110698,
    "tgn:name":"Pedra Branca, Serra da",
    "tgn:placetype":[
        "aat:300266640"
    ]
},
  "bbox": [],
  "geometry": {"coordinates":[-43.4833,-22.9333],"type":"Point"}
}