{
  "id": 2161732,
  "type": "Feature",
  "properties": {
    "tgn:hierarchy":[
        "tgn:2161732",
        "tgn:1000001",
        "tgn:7012149",
        "tgn:1002789",
        "tgn:7007710",
        "tgn:7029392"
    ],
    "tgn:id":2161732,
    "tgn:name":"Belle, Lake",
    "tgn:placetype":[
        "aat:300008680"
    ]
},
  "bbox": [],
  "geometry": {"coordinates":[-75.15,41.2667],"type":"Point"}
}