{
  "id": 7318305,
  "type": "Feature",
  "properties": {
    "tgn:hierarchy":[
        "tgn:7318305",
        "tgn:1001702",
        "tgn:1000049",
        "tgn:1000002",
        "tgn:7029392"
    ],
    "tgn:id":7318305,
    "tgn:name":"Corneta, Islote",
    "tgn:placetype":[
        "aat:300008791"
    ]
},
  "bbox": [],
  "geometry": {"coordinates":[-72.183333,-54.133333],"type":"Point"}
}