<<<<<<< HEAD
{
  "id": 2150707,
  "type": "Feature",
  "properties": {
    "tgn:hierarchy":[
        "tgn:2150707",
        "tgn:1000001",
        "tgn:7006451",
        "tgn:7012149",
        "tgn:2000101",
        "tgn:7029392"
    ],
    "tgn:id":2150707,
    "tgn:name":"Bass Canyon",
    "tgn:placetype":[
        "aat:300008761"
    ]
},
  "bbox": [],
  "geometry": {"coordinates":[-111.0333,32.5167],"type":"Point"}
}
=======
{"geometry":{"type":"Point","coordinates":[-111.033300,32.516700]},"type":"Feature","properties":{"hierarchy":["tgn:2150707","tgn:1000001","tgn:7006451","tgn:7012149","tgn:2000101","tgn:7029392"],"placetype":["aat:300008761"],"id":2150707,"name:xx":"Bass Canyon"}}
>>>>>>> 03f74aca74312dbeaf24d7e61306dd6a786dc3d0
