{
  "id": 2509713,
  "type": "Feature",
  "properties": {
    "tgn:hierarchy":[
        "tgn:2509713",
        "tgn:1000001",
        "tgn:7012149",
        "tgn:2001452",
        "tgn:7007566",
        "tgn:7029392"
    ],
    "tgn:id":2509713,
    "tgn:name":"Middle Jones Canyon",
    "tgn:placetype":[
        "aat:300008761"
    ]
},
  "bbox": [],
  "geometry": {"coordinates":[-108.25,36.9833],"type":"Point"}
}