{
  "id": 7589374,
  "type": "Feature",
  "properties": {
    "tgn:hierarchy":[
        "tgn:7589374",
        "tgn:1000004",
        "tgn:7000198",
        "tgn:7000799",
        "tgn:7029392"
    ],
    "tgn:id":7589374,
    "tgn:name:en":"Dungi Mani\u0101lan Forest",
    "tgn:placetype":[
        "aat:300008863"
    ]
},
  "bbox": [],
  "geometry": {"coordinates":[74.208333,33.355556],"type":"Point"}
}