{
  "id": 2470987,
  "type": "Feature",
  "properties": {
    "tgn:hierarchy":[
        "tgn:2470987",
        "tgn:1000001",
        "tgn:2001323",
        "tgn:7012149",
        "tgn:7007525",
        "tgn:7029392"
    ],
    "tgn:id":2470987,
    "tgn:name":"Lost Creek",
    "tgn:placetype":[
        "aat:300008706"
    ]
},
  "bbox": [],
  "geometry": {"coordinates":[-99.1667,42.9667],"type":"Point"}
}