{
  "id": 2586040,
  "type": "Feature",
  "properties": {
    "tgn:hierarchy":[
        "tgn:2586040",
        "tgn:1000001",
        "tgn:1002480",
        "tgn:7012149",
        "tgn:7007564",
        "tgn:7029392"
    ],
    "tgn:id":2586040,
    "tgn:name":"Piscataquog Mountain",
    "tgn:placetype":[
        "aat:300008798"
    ]
},
  "bbox": [],
  "geometry": {"coordinates":[-71.7667,42.9167],"type":"Point"}
}