<<<<<<< HEAD
{
  "id": 2155671,
  "type": "Feature",
  "properties": {
    "tgn:hierarchy":[
        "tgn:2155671",
        "tgn:1000001",
        "tgn:7012149",
        "tgn:2002162",
        "tgn:7007919",
        "tgn:7029392"
    ],
    "tgn:id":2155671,
    "tgn:name":"Bear Spring Branch",
    "tgn:placetype":[
        "aat:300008699"
    ]
},
  "bbox": [],
  "geometry": {"coordinates":[-80.65,37.2167],"type":"Point"}
}
=======
{"geometry":{"type":"Point","coordinates":[-80.650000,37.216700]},"type":"Feature","properties":{"hierarchy":["tgn:2155671","tgn:1000001","tgn:7012149","tgn:2002162","tgn:7007919","tgn:7029392"],"placetype":["aat:300008699"],"id":2155671,"name:xx":"Bear Spring Branch"}}
>>>>>>> 03f74aca74312dbeaf24d7e61306dd6a786dc3d0
