{
  "id": 2155671,
  "type": "Feature",
  "properties": {
    "tgn:hierarchy":[
        "tgn:2155671",
        "tgn:1000001",
        "tgn:7012149",
        "tgn:2002162",
        "tgn:7007919",
        "tgn:7029392"
    ],
    "tgn:id":2155671,
    "tgn:name":"Bear Spring Branch",
    "tgn:placetype":[
        "aat:300008699"
    ]
},
  "bbox": [],
  "geometry": {"coordinates":[-80.65,37.2167],"type":"Point"}
}