{
  "id": 7431482,
  "type": "Feature",
  "properties": {
    "tgn:hierarchy":[
        "tgn:7431482",
        "tgn:7005581",
        "tgn:1000001",
        "tgn:7005560",
        "tgn:7029392"
    ],
    "tgn:id":7431482,
    "tgn:name":"Agua de los Leones",
    "tgn:placetype":[
        "aat:300008347"
    ]
},
  "bbox": [],
  "geometry": {"coordinates":[-107.916667,29.15],"type":"Point"}
}