{
  "id": 2565169,
  "type": "Feature",
  "properties": {
    "tgn:hierarchy":[
        "tgn:2565169",
        "tgn:1000001",
        "tgn:2001416",
        "tgn:7012149",
        "tgn:7007526",
        "tgn:7029392"
    ],
    "tgn:id":2565169,
    "tgn:name":"Pahranagat Valley",
    "tgn:placetype":[
        "aat:300008761"
    ]
},
  "bbox": [],
  "geometry": {"coordinates":[-115.1667,37.6833],"type":"Point"}
}