{
  "id": 7220827,
  "type": "Feature",
  "properties": {
    "tgn:hierarchy":[
        "tgn:7220827",
        "tgn:7002681",
        "tgn:7001395",
        "tgn:1000003",
        "tgn:1000074",
        "tgn:7029392"
    ],
    "tgn:id":7220827,
    "tgn:name":"Varn\u00e1vas",
    "tgn:placetype":[
        "aat:300008777"
    ]
},
  "bbox": [],
  "geometry": {"coordinates":[23.933333,38.233333],"type":"Point"}
}