<<<<<<< HEAD
{
  "id": 2256797,
  "type": "Feature",
  "properties": {
    "tgn:hierarchy":[
        "tgn:2256797",
        "tgn:1000001",
        "tgn:7006451",
        "tgn:7012149",
        "tgn:2000103",
        "tgn:7029392"
    ],
    "tgn:id":2256797,
    "tgn:name":"Corief Hill Water Tank",
    "tgn:placetype":[
        "aat:300006191"
    ]
},
  "bbox": [],
  "geometry": {"coordinates":[-111.9167,34.5667],"type":"Point"}
}
=======
{"geometry":{"type":"Point","coordinates":[-111.916700,34.566700]},"type":"Feature","properties":{"hierarchy":["tgn:2256797","tgn:1000001","tgn:7006451","tgn:7012149","tgn:2000103","tgn:7029392"],"placetype":["aat:300006191"],"id":2256797,"name:xx":"Corief Hill Water Tank"}}
>>>>>>> 03f74aca74312dbeaf24d7e61306dd6a786dc3d0
