{
  "id": 2465436,
  "type": "Feature",
  "properties": {
    "tgn:hierarchy":[
        "tgn:2465436",
        "tgn:1000001",
        "tgn:7012149",
        "tgn:2001255",
        "tgn:7007523",
        "tgn:7029392"
    ],
    "tgn:id":2465436,
    "tgn:name":"Lone Hill",
    "tgn:placetype":[
        "aat:300008798"
    ]
},
  "bbox": [],
  "geometry": {"coordinates":[-90.45,37.1167],"type":"Point"}
}