{
  "id": 2301210,
  "type": "Feature",
  "properties": {
    "tgn:hierarchy":[
        "tgn:2301210",
        "tgn:1000001",
        "tgn:7012149",
        "tgn:2002289",
        "tgn:7013961",
        "tgn:7029392"
    ],
    "tgn:id":2301210,
    "tgn:name":"Dunlap Branch",
    "tgn:placetype":[
        "aat:300008699"
    ]
},
  "bbox": [],
  "geometry": {"coordinates":[-81.8833,38.5833],"type":"Point"}
}