<<<<<<< HEAD
{
  "id": 2339340,
  "type": "Feature",
  "properties": {
    "tgn:hierarchy":[
        "tgn:2339340",
        "tgn:1000001",
        "tgn:7012149",
        "tgn:2001312",
        "tgn:7007524",
        "tgn:7029392"
    ],
    "tgn:id":2339340,
    "tgn:name":"Frazer Lake",
    "tgn:placetype":[
        "aat:300006191"
    ]
},
  "bbox": [],
  "geometry": {"coordinates":[-106.0167,48.05],"type":"Point"}
}
=======
{"geometry":{"type":"Point","coordinates":[-106.016700,48.050000]},"type":"Feature","properties":{"hierarchy":["tgn:2339340","tgn:1000001","tgn:7012149","tgn:2001312","tgn:7007524","tgn:7029392"],"placetype":["aat:300006191"],"id":2339340,"name:xx":"Frazer Lake"}}
>>>>>>> 03f74aca74312dbeaf24d7e61306dd6a786dc3d0
