{
  "id": 2731527,
  "type": "Feature",
  "properties": {
    "tgn:hierarchy":[
        "tgn:2731527",
        "tgn:1000001",
        "tgn:7012149",
        "tgn:7007157",
        "tgn:1002684",
        "tgn:7029392"
    ],
    "tgn:id":2731527,
    "tgn:name":"Tule Canyon",
    "tgn:placetype":[
        "aat:300008761"
    ]
},
  "bbox": [],
  "geometry": {"coordinates":[-121.0667,35.9167],"type":"Point"}
}