{
  "id": 7479791,
  "type": "Feature",
  "properties": {
    "tgn:hierarchy":[
        "tgn:7479791",
        "tgn:1000004",
        "tgn:7490934",
        "tgn:1000141",
        "tgn:7029392"
    ],
    "tgn:id":7479791,
    "tgn:name":"Zhengwang Fu",
    "tgn:placetype":[
        "aat:300007595"
    ]
},
  "bbox": [],
  "geometry": {"coordinates":[120.101389,23.090278],"type":"Point"}
}