<<<<<<< HEAD
{
  "id": 7479791,
  "type": "Feature",
  "properties": {
    "tgn:hierarchy":[
        "tgn:7479791",
        "tgn:1000004",
        "tgn:7490934",
        "tgn:1000141",
        "tgn:7029392"
    ],
    "tgn:id":7479791,
    "tgn:name":"Zhengwang Fu",
    "tgn:placetype":[
        "aat:300007595"
    ]
},
  "bbox": [],
  "geometry": {"coordinates":[120.101389,23.090278],"type":"Point"}
}
=======
{"geometry":{"type":"Point","coordinates":[120.101389,23.090278]},"type":"Feature","properties":{"hierarchy":["tgn:7479791","tgn:1000004","tgn:7490934","tgn:1000141","tgn:7029392"],"placetype":["aat:300007595"],"id":7479791,"name:xx":"Zhengwang Fu"}}
>>>>>>> 03f74aca74312dbeaf24d7e61306dd6a786dc3d0
