{
  "id": 2138009,
  "type": "Feature",
  "properties": {
    "tgn:hierarchy":[
        "tgn:2138009",
        "tgn:1000001",
        "tgn:7012149",
        "tgn:2001716",
        "tgn:7007708",
        "tgn:7029392"
    ],
    "tgn:id":2138009,
    "tgn:name":"Arrowhead Point",
    "tgn:placetype":[
        "aat:300008850"
    ]
},
  "bbox": [],
  "geometry": {"coordinates":[-124.0833,43.8667],"type":"Point"}
}