<<<<<<< HEAD
{
  "id": 2331126,
  "type": "Feature",
  "properties": {
    "tgn:hierarchy":[
        "tgn:2331126",
        "tgn:1000001",
        "tgn:2000202",
        "tgn:7012149",
        "tgn:7007158",
        "tgn:7029392"
    ],
    "tgn:id":2331126,
    "tgn:name":"Flat Top",
    "tgn:placetype":[
        "aat:300008798"
    ]
},
  "bbox": [],
  "geometry": {"coordinates":[-106.1667,37.15],"type":"Point"}
}
=======
{"geometry":{"type":"Point","coordinates":[-106.166700,37.150000]},"type":"Feature","properties":{"hierarchy":["tgn:2331126","tgn:1000001","tgn:2000202","tgn:7012149","tgn:7007158","tgn:7029392"],"placetype":["aat:300008798"],"id":2331126,"name:xx":"Flat Top"}}
>>>>>>> 03f74aca74312dbeaf24d7e61306dd6a786dc3d0
