{
  "id": 7413623,
  "type": "Feature",
  "properties": {
    "tgn:hierarchy":[
        "tgn:7413623",
        "tgn:7005587",
        "tgn:1000001",
        "tgn:7005560",
        "tgn:7029392"
    ],
    "tgn:id":7413623,
    "tgn:name:es":"El Progreso",
    "tgn:placetype":[
        "aat:300008347"
    ]
},
  "bbox": [],
  "geometry": {"coordinates":[-98.243056,20.393056],"type":"Point"}
}