{
  "id": 7496593,
  "type": "Feature",
  "properties": {
    "tgn:hierarchy":[
        "tgn:7496593",
        "tgn:7001004",
        "tgn:1000004",
        "tgn:1000141",
        "tgn:7029392"
    ],
    "tgn:id":7496593,
    "tgn:name":"Shanlin Daqiao",
    "tgn:placetype":[
        "aat:300007836"
    ]
},
  "bbox": [],
  "geometry": {"coordinates":[120.550763,22.990294],"type":"Point"}
}