{
  "id": 7229504,
  "type": "Feature",
  "properties": {
    "tgn:hierarchy":[
        "tgn:7229504",
        "tgn:7002681",
        "tgn:7001395",
        "tgn:1000003",
        "tgn:1000074",
        "tgn:7029392"
    ],
    "tgn:id":7229504,
    "tgn:name":"Karatz\u00e1dhes",
    "tgn:placetype":[
        "aat:300008777"
    ]
},
  "bbox": [],
  "geometry": {"coordinates":[23.35,38.083333],"type":"Point"}
}