{
  "id": 7588852,
  "type": "Feature",
  "properties": {
    "tgn:hierarchy":[
        "tgn:7588852",
        "tgn:1000004",
        "tgn:7000198",
        "tgn:7000799",
        "tgn:7029392"
    ],
    "tgn:id":7588852,
    "tgn:name:en":"Khui Forest",
    "tgn:placetype":[
        "aat:300008863"
    ]
},
  "bbox": [],
  "geometry": {"coordinates":[74.175574,33.402916],"type":"Point"}
}