{
  "id": 1033288,
  "type": "Feature",
  "properties": {
    "tgn:hierarchy":[
        "tgn:1033288",
        "tgn:1000003",
        "tgn:7002883",
        "tgn:1000070",
        "tgn:7029392"
    ],
    "tgn:id":1033288,
    "tgn:name":"Gometz-la-ville",
    "tgn:placetype":[
        "aat:300008347"
    ]
},
  "bbox": [],
  "geometry": {"coordinates":[2.1167,48.6667],"type":"Point"}
}