<<<<<<< HEAD
{
  "id": 2150246,
  "type": "Feature",
  "properties": {
    "tgn:hierarchy":[
        "tgn:2150246",
        "tgn:1000001",
        "tgn:7012149",
        "tgn:7007520",
        "tgn:7029392"
    ],
    "tgn:id":2150246,
    "tgn:name":"Base Line Lake",
    "tgn:placetype":[
        "aat:300008680"
    ]
},
  "bbox": [],
  "geometry": {"coordinates":[-83.8833,42.4167],"type":"Point"}
}
=======
{"geometry":{"type":"Point","coordinates":[-83.883300,42.416700]},"type":"Feature","properties":{"hierarchy":["tgn:2150246","tgn:1000001","tgn:7012149","tgn:7007520","tgn:7029392"],"placetype":["aat:300008680"],"id":2150246,"name:xx":"Base Line Lake"}}
>>>>>>> 03f74aca74312dbeaf24d7e61306dd6a786dc3d0
