<<<<<<< HEAD
{
  "id": 7051892,
  "type": "Feature",
  "properties": {
    "tgn:hierarchy":[
        "tgn:7051892",
        "tgn:7009084",
        "tgn:1003484",
        "tgn:1000003",
        "tgn:1000080",
        "tgn:7029392"
    ],
    "tgn:id":7051892,
    "tgn:name":"Pescara, Valle della",
    "tgn:placetype":[
        "aat:300008761"
    ]
},
  "bbox": [],
  "geometry": {"coordinates":[14.0,42.25],"type":"Point"}
}
=======
{"geometry":{"type":"Point","coordinates":[14.000000,42.250000]},"type":"Feature","properties":{"hierarchy":["tgn:7051892","tgn:7009084","tgn:1003484","tgn:1000003","tgn:1000080","tgn:7029392"],"placetype":["aat:300008761"],"id":7051892,"name:xx":"Pescara, Valle della"}}
>>>>>>> 03f74aca74312dbeaf24d7e61306dd6a786dc3d0
