<<<<<<< HEAD
{
  "id": 2763245,
  "type": "Feature",
  "properties": {
    "tgn:hierarchy":[
        "tgn:2763245",
        "tgn:1000001",
        "tgn:7012149",
        "tgn:1002468",
        "tgn:7007252",
        "tgn:7029392"
    ],
    "tgn:id":2763245,
    "tgn:name":"Westwood Park Reservoir",
    "tgn:placetype":[
        "aat:300006191"
    ]
},
  "bbox": [],
  "geometry": {"coordinates":[-85.4333,39.8833],"type":"Point"}
}
=======
{"geometry":{"type":"Point","coordinates":[-85.433300,39.883300]},"type":"Feature","properties":{"hierarchy":["tgn:2763245","tgn:1000001","tgn:7012149","tgn:1002468","tgn:7007252","tgn:7029392"],"placetype":["aat:300006191"],"id":2763245,"name:xx":"Westwood Park Reservoir"}}
>>>>>>> 03f74aca74312dbeaf24d7e61306dd6a786dc3d0
