{
  "id": 7316943,
  "type": "Feature",
  "properties": {
    "tgn:hierarchy":[
        "tgn:7316943",
        "tgn:7016598",
        "tgn:1000049",
        "tgn:1000002",
        "tgn:7029392"
    ],
    "tgn:id":7316943,
    "tgn:name":"Cuadrilla Diez",
    "tgn:placetype":[
        "aat:300008347"
    ]
},
  "bbox": [],
  "geometry": {"coordinates":[-69.683333,-25.383333],"type":"Point"}
}