{
  "id": 2221923,
  "type": "Feature",
  "properties": {
    "tgn:hierarchy":[
        "tgn:2221923",
        "tgn:1000001",
        "tgn:7012149",
        "tgn:2002168",
        "tgn:7007919",
        "tgn:7029392"
    ],
    "tgn:id":2221923,
    "tgn:name":"Carlyle, Mount",
    "tgn:placetype":[
        "aat:300008798"
    ]
},
  "bbox": [],
  "geometry": {"coordinates":[-79.55,38.25],"type":"Point"}
}