{
  "id": 2576040,
  "type": "Feature",
  "properties": {
    "tgn:hierarchy":[
        "tgn:2576040",
        "tgn:1000001",
        "tgn:7012149",
        "tgn:2002164",
        "tgn:7007919",
        "tgn:7029392"
    ],
    "tgn:id":2576040,
    "tgn:name":"Perkins Knob",
    "tgn:placetype":[
        "aat:300008798"
    ]
},
  "bbox": [],
  "geometry": {"coordinates":[-81.1333,36.75],"type":"Point"}
}