{
  "id": 2543583,
  "type": "Feature",
  "properties": {
    "tgn:hierarchy":[
        "tgn:2543583",
        "tgn:1000001",
        "tgn:7012149",
        "tgn:2001718",
        "tgn:7007708",
        "tgn:7029392"
    ],
    "tgn:id":2543583,
    "tgn:name":"North Alkali Creek Siphon",
    "tgn:placetype":[
        "aat:300006075"
    ]
},
  "bbox": [],
  "geometry": {"coordinates":[-117.0667,43.6167],"type":"Point"}
}