{
  "id": 2014446,
  "type": "Feature",
  "properties": {
    "tgn:hierarchy":[
        "tgn:2014446",
        "tgn:1000001",
        "tgn:7012149",
        "tgn:7007157",
        "tgn:1002621",
        "tgn:7029392"
    ],
    "tgn:id":2014446,
    "tgn:name":"Storey",
    "tgn:placetype":[
        "aat:300008347"
    ]
},
  "bbox": [],
  "geometry": {"coordinates":[-120.0167,36.9667],"type":"Point"}
}