{
  "id": 2487958,
  "type": "Feature",
  "properties": {
    "tgn:hierarchy":[
        "tgn:2487958",
        "tgn:1000001",
        "tgn:7006451",
        "tgn:7012149",
        "tgn:2000098",
        "tgn:7029392"
    ],
    "tgn:id":2487958,
    "tgn:name":"Maggie Mine",
    "tgn:placetype":[
        "aat:300000390"
    ]
},
  "bbox": [],
  "geometry": {"coordinates":[-113.65,34.3333],"type":"Point"}
}