{
  "id": 2203608,
  "type": "Feature",
  "properties": {
    "tgn:hierarchy":[
        "tgn:2203608",
        "tgn:1000001",
        "tgn:7012149",
        "tgn:2002288",
        "tgn:7013961",
        "tgn:7029392"
    ],
    "tgn:id":2203608,
    "tgn:name":"Bucklick Run",
    "tgn:placetype":[
        "aat:300008699"
    ]
},
  "bbox": [],
  "geometry": {"coordinates":[-79.7167,39.2667],"type":"Point"}
}