{
  "id": 7391177,
  "type": "Feature",
  "properties": {
    "tgn:hierarchy":[
        "tgn:7391177",
        "tgn:7005580",
        "tgn:1000001",
        "tgn:7005560",
        "tgn:7029392"
    ],
    "tgn:id":7391177,
    "tgn:name":"Roberto Barrios",
    "tgn:placetype":[
        "aat:300008347"
    ]
},
  "bbox": [],
  "geometry": {"coordinates":[-92.966667,15.333333],"type":"Point"}
}