{
  "id": 2314508,
  "type": "Feature",
  "properties": {
    "tgn:hierarchy":[
        "tgn:2314508",
        "tgn:1000001",
        "tgn:7012149",
        "tgn:2001288",
        "tgn:7007524",
        "tgn:7029392"
    ],
    "tgn:id":2314508,
    "tgn:name":"Elk Mountain",
    "tgn:placetype":[
        "aat:300008798"
    ]
},
  "bbox": [],
  "geometry": {"coordinates":[-111.4667,45.55],"type":"Point"}
}