{
  "id": 7035113,
  "type": "Feature",
  "properties": {
    "tgn:hierarchy":[
        "tgn:7035113",
        "tgn:1003506",
        "tgn:1000003",
        "tgn:7002993",
        "tgn:1000080",
        "tgn:7029392"
    ],
    "tgn:id":7035113,
    "tgn:name":"Merso Soprano",
    "tgn:placetype":[
        "aat:300008347"
    ]
},
  "bbox": [],
  "geometry": {"coordinates":[13.528056,46.123889],"type":"Point"}
}