<<<<<<< HEAD
{
  "id": 2760367,
  "type": "Feature",
  "properties": {
    "tgn:hierarchy":[
        "tgn:2760367",
        "tgn:1000001",
        "tgn:2002369",
        "tgn:7012149",
        "tgn:7007923",
        "tgn:7029392"
    ],
    "tgn:id":2760367,
    "tgn:name":"West Fork Simpson Draw",
    "tgn:placetype":[
        "aat:300008761"
    ]
},
  "bbox": [],
  "geometry": {"coordinates":[-105.2333,42.8333],"type":"Point"}
}
=======
{"geometry":{"type":"Point","coordinates":[-105.233300,42.833300]},"type":"Feature","properties":{"hierarchy":["tgn:2760367","tgn:1000001","tgn:2002369","tgn:7012149","tgn:7007923","tgn:7029392"],"placetype":["aat:300008761"],"id":2760367,"name:xx":"West Fork Simpson Draw"}}
>>>>>>> 03f74aca74312dbeaf24d7e61306dd6a786dc3d0
