{
  "id": 2721309,
  "type": "Feature",
  "properties": {
    "tgn:hierarchy":[
        "tgn:2721309",
        "tgn:1000001",
        "tgn:7012149",
        "tgn:7007157",
        "tgn:1002675",
        "tgn:7029392"
    ],
    "tgn:id":2721309,
    "tgn:name":"Tiger Mines",
    "tgn:placetype":[
        "aat:300000390"
    ]
},
  "bbox": [],
  "geometry": {"coordinates":[-119.25,38.4333],"type":"Point"}
}