{
  "id": 2206996,
  "type": "Feature",
  "properties": {
    "tgn:hierarchy":[
        "tgn:2206996",
        "tgn:1000001",
        "tgn:2001418",
        "tgn:7012149",
        "tgn:7007526",
        "tgn:7029392"
    ],
    "tgn:id":2206996,
    "tgn:name":"Bunch Brush Canyon",
    "tgn:placetype":[
        "aat:300008761"
    ]
},
  "bbox": [],
  "geometry": {"coordinates":[-116.7167,38.4167],"type":"Point"}
}