{
  "id": 7223055,
  "type": "Feature",
  "properties": {
    "tgn:hierarchy":[
        "tgn:7223055",
        "tgn:7002690",
        "tgn:7012056",
        "tgn:1000003",
        "tgn:1000074",
        "tgn:7029392"
    ],
    "tgn:id":7223055,
    "tgn:name":"Pl\u00e1tanos",
    "tgn:placetype":[
        "aat:300008347"
    ]
},
  "bbox": [],
  "geometry": {"coordinates":[24.916667,35.016667],"type":"Point"}
}