{
  "id": 2274114,
  "type": "Feature",
  "properties": {
    "tgn:hierarchy":[
        "tgn:2274114",
        "tgn:1000001",
        "tgn:7016172",
        "tgn:7012149",
        "tgn:2000164",
        "tgn:7029392"
    ],
    "tgn:id":2274114,
    "tgn:name":"Dailey Lake",
    "tgn:placetype":[
        "aat:300006191"
    ]
},
  "bbox": [],
  "geometry": {"coordinates":[-92.4667,34.6667],"type":"Point"}
}