{
  "id": 2633012,
  "type": "Feature",
  "properties": {
    "tgn:hierarchy":[
        "tgn:2633012",
        "tgn:1000001",
        "tgn:7012149",
        "tgn:7029392"
    ],
    "tgn:id":2633012,
    "tgn:name":"Rudolf Run",
    "tgn:placetype":[
        "aat:300008699"
    ]
},
  "bbox": [],
  "geometry": {"coordinates":[-80.1833,39.7833],"type":"Point"}
}