{
  "id": 1096464,
  "type": "Feature",
  "properties": {
    "tgn:hierarchy":[
        "tgn:1096464",
        "tgn:7000490",
        "tgn:1000006",
        "tgn:7001831",
        "tgn:7029392"
    ],
    "tgn:id":1096464,
    "tgn:name":"Caloote",
    "tgn:placetype":[
        "aat:300008347"
    ]
},
  "bbox": [],
  "geometry": {"coordinates":[139.2667,-34.9667],"type":"Point"}
}