{
  "id": 2353676,
  "type": "Feature",
  "properties": {
    "tgn:hierarchy":[
        "tgn:2353676",
        "tgn:1000001",
        "tgn:7012149",
        "tgn:1002581",
        "tgn:7007710",
        "tgn:7029392"
    ],
    "tgn:id":2353676,
    "tgn:name":"Gold Mine",
    "tgn:placetype":[
        "aat:300008347"
    ]
},
  "bbox": [],
  "geometry": {"coordinates":[-76.5333,40.5167],"type":"Point"}
}