{
  "id": 2330523,
  "type": "Feature",
  "properties": {
    "tgn:hierarchy":[
        "tgn:2330523",
        "tgn:1000001",
        "tgn:7012149",
        "tgn:7007252",
        "tgn:7029392"
    ],
    "tgn:id":2330523,
    "tgn:name":"Flat Creek",
    "tgn:placetype":[
        "aat:300008706"
    ]
},
  "bbox": [],
  "geometry": {"coordinates":[-87.3667,38.4333],"type":"Point"}
}