{
  "id": 7101475,
  "type": "Feature",
  "properties": {
    "tgn:hierarchy":[
        "tgn:7101475",
        "tgn:1000003",
        "tgn:7003689",
        "tgn:7000084",
        "tgn:7029392"
    ],
    "tgn:id":7101475,
    "tgn:name":"Rupp-Berg",
    "tgn:placetype":[
        "aat:300008777"
    ]
},
  "bbox": [],
  "geometry": {"coordinates":[10.633333,50.683333],"type":"Point"}
}