{
  "id": 7287230,
  "type": "Feature",
  "properties": {
    "tgn:hierarchy":[
        "tgn:7287230",
        "tgn:7002464",
        "tgn:1000049",
        "tgn:1000002",
        "tgn:7029392"
    ],
    "tgn:id":7287230,
    "tgn:name":"Guailas, Quebrada",
    "tgn:placetype":[
        "aat:300266554",
        "aat:300008699"
    ]
},
  "bbox": [],
  "geometry": {"coordinates":[-69.65,-18.066667],"type":"Point"}
}