{
  "id": 7525590,
  "type": "Feature",
  "properties": {
    "tgn:hierarchy":[
        "tgn:7525590",
        "tgn:7001242",
        "tgn:7001311",
        "tgn:7016833",
        "tgn:7029392"
    ],
    "tgn:id":7525590,
    "tgn:name:en":"D\u0101rah, W\u0101d\u012b",
    "tgn:placetype":[
        "aat:300379998"
    ]
},
  "bbox": [],
  "geometry": {"coordinates":[33.371867,28.036683],"type":"Point"}
}