{
  "id": 2468098,
  "type": "Feature",
  "properties": {
    "tgn:hierarchy":[
        "tgn:2468098",
        "tgn:1000001",
        "tgn:7012149",
        "tgn:2002247",
        "tgn:7007920",
        "tgn:7029392"
    ],
    "tgn:id":2468098,
    "tgn:name":"Long Lake",
    "tgn:placetype":[
        "aat:300006191"
    ]
},
  "bbox": [],
  "geometry": {"coordinates":[-117.8333,47.8333],"type":"Point"}
}