{
  "id": 7017123,
  "type": "Feature",
  "properties": {
    "tgn:hierarchy":[
        "tgn:7017123",
        "tgn:1001945",
        "tgn:1000047",
        "tgn:7002457",
        "tgn:1000002",
        "tgn:7029392"
    ],
    "tgn:id":7017123,
    "tgn:name":"Suzano",
    "tgn:placetype":[
        "aat:300008347",
        "aat:300008389",
        "aat:300000874"
    ]
},
  "bbox": [],
  "geometry": {"coordinates":[-46.3333,-23.5333],"type":"Point"}
}