{
  "id": 7532345,
  "type": "Feature",
  "properties": {
    "tgn:hierarchy":[
        "tgn:7532345",
        "tgn:7001242",
        "tgn:7016833",
        "tgn:1001092",
        "tgn:7029392"
    ],
    "tgn:id":7532345,
    "tgn:name":"Tur'at Abu an Naj\u0101",
    "tgn:placetype":[
        "aat:300006075"
    ]
},
  "bbox": [],
  "geometry": {"coordinates":[31.230589,30.128374],"type":"Point"}
}