{
  "id": 1082522,
  "type": "Feature",
  "properties": {
    "tgn:hierarchy":[
        "tgn:1082522",
        "tgn:1000004",
        "tgn:7000845",
        "tgn:1000125",
        "tgn:7029392"
    ],
    "tgn:id":1082522,
    "tgn:name":"Muang Sing",
    "tgn:placetype":[
        "aat:300008347"
    ]
},
  "bbox": [],
  "geometry": {"coordinates":[101.15,21.1833],"type":"Point"}
}