<<<<<<< HEAD
{
  "id": 7364682,
  "type": "Feature",
  "properties": {
    "tgn:hierarchy":[
        "tgn:7364682",
        "tgn:1000001",
        "tgn:7005597",
        "tgn:7005560",
        "tgn:7029392"
    ],
    "tgn:id":7364682,
    "tgn:name":"El Zapotal",
    "tgn:placetype":[
        "aat:300008347"
    ]
},
  "bbox": [],
  "geometry": {"coordinates":[-98.983333,24.6],"type":"Point"}
}
=======
{"geometry":{"type":"Point","coordinates":[-98.983333,24.600000]},"type":"Feature","properties":{"hierarchy":["tgn:7364682","tgn:1000001","tgn:7005597","tgn:7005560","tgn:7029392"],"placetype":["aat:300008347"],"id":7364682,"name:xx":"El Zapotal"}}
>>>>>>> 03f74aca74312dbeaf24d7e61306dd6a786dc3d0
