<<<<<<< HEAD
{
  "id": 2765222,
  "type": "Feature",
  "properties": {
    "tgn:hierarchy":[
        "tgn:2765222",
        "tgn:1000001",
        "tgn:7012149",
        "tgn:2000476",
        "tgn:7007250",
        "tgn:7029392"
    ],
    "tgn:id":2765222,
    "tgn:name":"Whistling Pig Canyon",
    "tgn:placetype":[
        "aat:300008761"
    ]
},
  "bbox": [],
  "geometry": {"coordinates":[-115.6667,45.6],"type":"Point"}
}
=======
{"geometry":{"type":"Point","coordinates":[-115.666700,45.600000]},"type":"Feature","properties":{"hierarchy":["tgn:2765222","tgn:1000001","tgn:7012149","tgn:2000476","tgn:7007250","tgn:7029392"],"placetype":["aat:300008761"],"id":2765222,"name:xx":"Whistling Pig Canyon"}}
>>>>>>> 03f74aca74312dbeaf24d7e61306dd6a786dc3d0
