{
  "id": 7444712,
  "type": "Feature",
  "properties": {
    "tgn:hierarchy":[
        "tgn:7444712",
        "tgn:7002445",
        "tgn:1000003",
        "tgn:7012032",
        "tgn:7008591",
        "tgn:7029392"
    ],
    "tgn:id":7444712,
    "tgn:name:en":"Kilve",
    "tgn:placetype":[
        "aat:300008347"
    ]
},
  "bbox": [],
  "geometry": {"coordinates":[-3.219722,51.179444],"type":"Point"}
}