{
  "id": 7401521,
  "type": "Feature",
  "properties": {
    "tgn:hierarchy":[
        "tgn:7401521",
        "tgn:1000001",
        "tgn:7005599",
        "tgn:7005560",
        "tgn:7029392"
    ],
    "tgn:id":7401521,
    "tgn:name":"Los Limones",
    "tgn:placetype":[
        "aat:300008347"
    ]
},
  "bbox": [],
  "geometry": {"coordinates":[-94.133333,17.847222],"type":"Point"}
}