{
  "id": 2138417,
  "type": "Feature",
  "properties": {
    "tgn:hierarchy":[
        "tgn:2138417",
        "tgn:1000001",
        "tgn:7012149",
        "tgn:1002441",
        "tgn:7007706",
        "tgn:7029392"
    ],
    "tgn:id":2138417,
    "tgn:name":"Asbury",
    "tgn:placetype":[
        "aat:300008347"
    ]
},
  "bbox": [],
  "geometry": {"coordinates":[-84.3333,39.05],"type":"Point"}
}