{
  "id": 2549499,
  "type": "Feature",
  "properties": {
    "tgn:hierarchy":[
        "tgn:2549499",
        "tgn:1000001",
        "tgn:2001416",
        "tgn:7012149",
        "tgn:7007526",
        "tgn:7029392"
    ],
    "tgn:id":2549499,
    "tgn:name":"North Spring",
    "tgn:placetype":[
        "aat:300008697"
    ]
},
  "bbox": [],
  "geometry": {"coordinates":[-114.2333,37.5167],"type":"Point"}
}