{
  "id": 2086067,
  "type": "Feature",
  "properties": {
    "tgn:hierarchy":[
        "tgn:2086067",
        "tgn:1000001",
        "tgn:7012149",
        "tgn:1002501",
        "tgn:7007710",
        "tgn:7029392"
    ],
    "tgn:id":2086067,
    "tgn:name":"Armagh",
    "tgn:placetype":[
        "aat:300008347"
    ]
},
  "bbox": [],
  "geometry": {"coordinates":[-79.0167,40.45],"type":"Point"}
}