<<<<<<< HEAD
{
  "id": 2157727,
  "type": "Feature",
  "properties": {
    "tgn:hierarchy":[
        "tgn:2157727",
        "tgn:1000001",
        "tgn:7012149",
        "tgn:2001711",
        "tgn:7007708",
        "tgn:7029392"
    ],
    "tgn:id":2157727,
    "tgn:name":"Beaver Fork",
    "tgn:placetype":[
        "aat:300008699"
    ]
},
  "bbox": [],
  "geometry": {"coordinates":[-122.3,42.5],"type":"Point"}
}
=======
{"geometry":{"type":"Point","coordinates":[-122.300000,42.500000]},"type":"Feature","properties":{"hierarchy":["tgn:2157727","tgn:1000001","tgn:7012149","tgn:2001711","tgn:7007708","tgn:7029392"],"placetype":["aat:300008699"],"id":2157727,"name:xx":"Beaver Fork"}}
>>>>>>> 03f74aca74312dbeaf24d7e61306dd6a786dc3d0
