<<<<<<< HEAD
{
  "id": 2258083,
  "type": "Feature",
  "properties": {
    "tgn:hierarchy":[
        "tgn:2258083",
        "tgn:1000001",
        "tgn:7012149",
        "tgn:2001438",
        "tgn:7007566",
        "tgn:7029392"
    ],
    "tgn:id":2258083,
    "tgn:name":"Cosme Tank",
    "tgn:placetype":[
        "aat:300006191"
    ]
},
  "bbox": [],
  "geometry": {"coordinates":[-105.1,35.0333],"type":"Point"}
}
=======
{"geometry":{"type":"Point","coordinates":[-105.100000,35.033300]},"type":"Feature","properties":{"hierarchy":["tgn:2258083","tgn:1000001","tgn:7012149","tgn:2001438","tgn:7007566","tgn:7029392"],"placetype":["aat:300006191"],"id":2258083,"name:xx":"Cosme Tank"}}
>>>>>>> 03f74aca74312dbeaf24d7e61306dd6a786dc3d0
