{
  "id": 7202747,
  "type": "Feature",
  "properties": {
    "tgn:hierarchy":[
        "tgn:7202747",
        "tgn:7003692",
        "tgn:1000003",
        "tgn:7000084",
        "tgn:7029392"
    ],
    "tgn:id":7202747,
    "tgn:name":"Breiteck",
    "tgn:placetype":[
        "aat:300000206"
    ]
},
  "bbox": [],
  "geometry": {"coordinates":[8.133333,48.033333],"type":"Point"}
}