{
  "id": 2167890,
  "type": "Feature",
  "properties": {
    "tgn:hierarchy":[
        "tgn:2167890",
        "tgn:1000001",
        "tgn:7012149",
        "tgn:2001447",
        "tgn:7007566",
        "tgn:7029392"
    ],
    "tgn:id":2167890,
    "tgn:name":"Big Dog Canyon",
    "tgn:placetype":[
        "aat:300008761"
    ]
},
  "bbox": [],
  "geometry": {"coordinates":[-104.85,32.0333],"type":"Point"}
}