{
  "id": 7591101,
  "type": "Feature",
  "properties": {
    "tgn:hierarchy":[
        "tgn:7591101",
        "tgn:1000004",
        "tgn:7000198",
        "tgn:7000799",
        "tgn:7029392"
    ],
    "tgn:id":7591101,
    "tgn:name:en":"Sati",
    "tgn:placetype":[
        "aat:300008347"
    ]
},
  "bbox": [],
  "geometry": {"coordinates":[74.990278,32.572222],"type":"Point"}
}