<<<<<<< HEAD
{
  "id": 2768988,
  "type": "Feature",
  "properties": {
    "tgn:hierarchy":[
        "tgn:2768988",
        "tgn:1000001",
        "tgn:7012149",
        "tgn:2001230",
        "tgn:7007523",
        "tgn:7029392"
    ],
    "tgn:id":2768988,
    "tgn:name":"Whitson Hollow",
    "tgn:placetype":[
        "aat:300008761"
    ]
},
  "bbox": [],
  "geometry": {"coordinates":[-91.9,37.6833],"type":"Point"}
}
=======
{"geometry":{"type":"Point","coordinates":[-91.900000,37.683300]},"type":"Feature","properties":{"hierarchy":["tgn:2768988","tgn:1000001","tgn:7012149","tgn:2001230","tgn:7007523","tgn:7029392"],"placetype":["aat:300008761"],"id":2768988,"name:xx":"Whitson Hollow"}}
>>>>>>> 03f74aca74312dbeaf24d7e61306dd6a786dc3d0
