{
  "id": 7412803,
  "type": "Feature",
  "properties": {
    "tgn:hierarchy":[
        "tgn:7412803",
        "tgn:7005580",
        "tgn:1000001",
        "tgn:7005560",
        "tgn:7029392"
    ],
    "tgn:id":7412803,
    "tgn:name":"El Carmen",
    "tgn:placetype":[
        "aat:300008347"
    ]
},
  "bbox": [],
  "geometry": {"coordinates":[-92.155556,16.986111],"type":"Point"}
}