{
  "id": 2557867,
  "type": "Feature",
  "properties": {
    "tgn:hierarchy":[
        "tgn:2557867",
        "tgn:1000001",
        "tgn:7012149",
        "tgn:2001437",
        "tgn:7007566",
        "tgn:7029392"
    ],
    "tgn:id":2557867,
    "tgn:name":"Old Smokey Group",
    "tgn:placetype":[
        "aat:300000390"
    ]
},
  "bbox": [],
  "geometry": {"coordinates":[-108.55,32.8333],"type":"Point"}
}