{
  "id": 2249135,
  "type": "Feature",
  "properties": {
    "tgn:hierarchy":[
        "tgn:2249135",
        "tgn:1000001",
        "tgn:7012149",
        "tgn:7007157",
        "tgn:1002710",
        "tgn:7029392"
    ],
    "tgn:id":2249135,
    "tgn:name":"Cole Ditch",
    "tgn:placetype":[
        "aat:300006075"
    ]
},
  "bbox": [],
  "geometry": {"coordinates":[-121.15,39.0667],"type":"Point"}
}