{
  "id": 2603769,
  "type": "Feature",
  "properties": {
    "tgn:hierarchy":[
        "tgn:2603769",
        "tgn:1000001",
        "tgn:2000863",
        "tgn:7012149",
        "tgn:7007256",
        "tgn:7029392"
    ],
    "tgn:id":2603769,
    "tgn:name":"Quicksand Gully",
    "tgn:placetype":[
        "aat:300008699"
    ]
},
  "bbox": [],
  "geometry": {"coordinates":[-93.65,30.1167],"type":"Point"}
}