<<<<<<< HEAD
{
  "id": 2768521,
  "type": "Feature",
  "properties": {
    "tgn:hierarchy":[
        "tgn:2768521",
        "tgn:1000001",
        "tgn:7012149",
        "tgn:2001295",
        "tgn:7007524",
        "tgn:7029392"
    ],
    "tgn:id":2768521,
    "tgn:name":"Whitewater Creek",
    "tgn:placetype":[
        "aat:300008706"
    ]
},
  "bbox": [],
  "geometry": {"coordinates":[-107.4167,48.5333],"type":"Point"}
}
=======
{"geometry":{"type":"Point","coordinates":[-107.416700,48.533300]},"type":"Feature","properties":{"hierarchy":["tgn:2768521","tgn:1000001","tgn:7012149","tgn:2001295","tgn:7007524","tgn:7029392"],"placetype":["aat:300008706"],"id":2768521,"name:xx":"Whitewater Creek"}}
>>>>>>> 03f74aca74312dbeaf24d7e61306dd6a786dc3d0
