{
  "id": 2768521,
  "type": "Feature",
  "properties": {
    "tgn:hierarchy":[
        "tgn:2768521",
        "tgn:1000001",
        "tgn:7012149",
        "tgn:2001295",
        "tgn:7007524",
        "tgn:7029392"
    ],
    "tgn:id":2768521,
    "tgn:name":"Whitewater Creek",
    "tgn:placetype":[
        "aat:300008706"
    ]
},
  "bbox": [],
  "geometry": {"coordinates":[-107.4167,48.5333],"type":"Point"}
}