{
  "id": 2051093,
  "type": "Feature",
  "properties": {
    "tgn:hierarchy":[
        "tgn:2051093",
        "tgn:1000001",
        "tgn:7012149",
        "tgn:1002760",
        "tgn:7007520",
        "tgn:7029392"
    ],
    "tgn:id":2051093,
    "tgn:name":"Allendale",
    "tgn:placetype":[
        "aat:300008347"
    ]
},
  "bbox": [],
  "geometry": {"coordinates":[-85.95,42.9667],"type":"Point"}
}