{
  "id": 7205179,
  "type": "Feature",
  "properties": {
    "tgn:hierarchy":[
        "tgn:7205179",
        "tgn:1000003",
        "tgn:7003677",
        "tgn:7000084",
        "tgn:7029392"
    ],
    "tgn:id":7205179,
    "tgn:name":"D\u00e4mmerwald",
    "tgn:placetype":[
        "aat:300008863"
    ]
},
  "bbox": [],
  "geometry": {"coordinates":[6.783333,51.733333],"type":"Point"}
}