{
  "id": 7104782,
  "type": "Feature",
  "properties": {
    "tgn:hierarchy":[
        "tgn:7104782",
        "tgn:1000003",
        "tgn:7003687",
        "tgn:7000084",
        "tgn:7029392"
    ],
    "tgn:id":7104782,
    "tgn:name":"Schlo\u00df-Berg",
    "tgn:placetype":[
        "aat:300008777"
    ]
},
  "bbox": [],
  "geometry": {"coordinates":[11.266667,51.583333],"type":"Point"}
}