{
  "id": 2703453,
  "type": "Feature",
  "properties": {
    "tgn:hierarchy":[
        "tgn:2703453",
        "tgn:1000001",
        "tgn:7012149",
        "tgn:2001049",
        "tgn:7007521",
        "tgn:7029392"
    ],
    "tgn:id":2703453,
    "tgn:name":"Summit Lake",
    "tgn:placetype":[
        "aat:300008680"
    ]
},
  "bbox": [],
  "geometry": {"coordinates":[-95.85,43.9833],"type":"Point"}
}