{
  "id": 2571235,
  "type": "Feature",
  "properties": {
    "tgn:hierarchy":[
        "tgn:2571235",
        "tgn:1000001",
        "tgn:7012149",
        "tgn:2002100",
        "tgn:7007826",
        "tgn:7029392"
    ],
    "tgn:id":2571235,
    "tgn:name":"Patton Tank",
    "tgn:placetype":[
        "aat:300006191"
    ]
},
  "bbox": [],
  "geometry": {"coordinates":[-100.0167,29.05],"type":"Point"}
}