{
  "id": 2731851,
  "type": "Feature",
  "properties": {
    "tgn:hierarchy":[
        "tgn:2731851",
        "tgn:1000001",
        "tgn:2001436",
        "tgn:7012149",
        "tgn:7007566",
        "tgn:7029392"
    ],
    "tgn:id":2731851,
    "tgn:name":"Tumbleweed Draw",
    "tgn:placetype":[
        "aat:300008761"
    ]
},
  "bbox": [],
  "geometry": {"coordinates":[-104.4833,32.75],"type":"Point"}
}