{
  "id": 2439177,
  "type": "Feature",
  "properties": {
    "tgn:hierarchy":[
        "tgn:2439177",
        "tgn:1000001",
        "tgn:7012149",
        "tgn:7007524",
        "tgn:7029392"
    ],
    "tgn:id":2439177,
    "tgn:name":"Kipps Coulee",
    "tgn:placetype":[
        "aat:300008761"
    ]
},
  "bbox": [],
  "geometry": {"coordinates":[-112.65,48.3833],"type":"Point"}
}