{
  "id": 7356438,
  "type": "Feature",
  "properties": {
    "tgn:hierarchy":[
        "tgn:7356438",
        "tgn:7005581",
        "tgn:1000001",
        "tgn:7005560",
        "tgn:7029392"
    ],
    "tgn:id":7356438,
    "tgn:name":"Cerro Prieto",
    "tgn:placetype":[
        "aat:300008347"
    ]
},
  "bbox": [],
  "geometry": {"coordinates":[-106.583333,27.016667],"type":"Point"}
}