{
  "id": 2437157,
  "type": "Feature",
  "properties": {
    "tgn:hierarchy":[
        "tgn:2437157",
        "tgn:1000001",
        "tgn:1002257",
        "tgn:7012149",
        "tgn:7007919",
        "tgn:7029392"
    ],
    "tgn:id":2437157,
    "tgn:name":"Kimages Hill",
    "tgn:placetype":[
        "aat:300008798"
    ]
},
  "bbox": [],
  "geometry": {"coordinates":[-77.2167,37.3333],"type":"Point"}
}