{
  "id": 2781578,
  "type": "Feature",
  "properties": {
    "tgn:hierarchy":[
        "tgn:2781578",
        "tgn:1000001",
        "tgn:2001786",
        "tgn:7012149",
        "tgn:7007713",
        "tgn:7029392"
    ],
    "tgn:id":2781578,
    "tgn:name":"Woodpecker Ridge",
    "tgn:placetype":[
        "aat:300266640"
    ]
},
  "bbox": [],
  "geometry": {"coordinates":[-103.4167,43.8167],"type":"Point"}
}