<<<<<<< HEAD
{
  "id": 7058683,
  "type": "Feature",
  "properties": {
    "tgn:hierarchy":[
        "tgn:7058683",
        "tgn:7005852",
        "tgn:1000003",
        "tgn:7003237",
        "tgn:1000080",
        "tgn:7029392"
    ],
    "tgn:id":7058683,
    "tgn:name":"Alpe Forno",
    "tgn:placetype":[
        "aat:300008347"
    ]
},
  "bbox": [],
  "geometry": {"coordinates":[9.45,46.033333],"type":"Point"}
}
=======
{"geometry":{"type":"Point","coordinates":[9.450000,46.033333]},"type":"Feature","properties":{"hierarchy":["tgn:7058683","tgn:7005852","tgn:1000003","tgn:7003237","tgn:1000080","tgn:7029392"],"placetype":["aat:300008347"],"id":7058683,"name:xx":"Alpe Forno"}}
>>>>>>> 03f74aca74312dbeaf24d7e61306dd6a786dc3d0
