{
  "id": 2752210,
  "type": "Feature",
  "properties": {
    "tgn:hierarchy":[
        "tgn:2752210",
        "tgn:1000001",
        "tgn:7012149",
        "tgn:7007252",
        "tgn:7029392"
    ],
    "tgn:id":2752210,
    "tgn:name":"Washam Ditch",
    "tgn:placetype":[
        "aat:300006075"
    ]
},
  "bbox": [],
  "geometry": {"coordinates":[-86.05,41.1833],"type":"Point"}
}