{
  "id": 7384558,
  "type": "Feature",
  "properties": {
    "tgn:hierarchy":[
        "tgn:7384558",
        "tgn:1000001",
        "tgn:7005595",
        "tgn:7005560",
        "tgn:7029392"
    ],
    "tgn:id":7384558,
    "tgn:name":"Navachiste, Sierra de",
    "tgn:placetype":[
        "aat:300008795"
    ]
},
  "bbox": [],
  "geometry": {"coordinates":[-108.966667,25.533333],"type":"Point"}
}