{
  "id": 7329674,
  "type": "Feature",
  "properties": {
    "tgn:hierarchy":[
        "tgn:7329674",
        "tgn:7002829",
        "tgn:1000003",
        "tgn:7002786",
        "tgn:1000095",
        "tgn:7029392"
    ],
    "tgn:id":7329674,
    "tgn:name":"Lamas",
    "tgn:placetype":[
        "aat:300008347"
    ]
},
  "bbox": [],
  "geometry": {"coordinates":[-7.033333,42.833333],"type":"Point"}
}