{
  "id": 2064867,
  "type": "Feature",
  "properties": {
    "tgn:hierarchy":[
        "tgn:2064867",
        "tgn:1000001",
        "tgn:1002695",
        "tgn:7012149",
        "tgn:7007565",
        "tgn:7029392"
    ],
    "tgn:id":2064867,
    "tgn:name":"Green Pond",
    "tgn:placetype":[
        "aat:300008347"
    ]
},
  "bbox": [],
  "geometry": {"coordinates":[-74.4667,41.0167],"type":"Point"}
}