{
  "id": 7278486,
  "type": "Feature",
  "properties": {
    "tgn:hierarchy":[
        "tgn:7278486",
        "tgn:1001623",
        "tgn:1000049",
        "tgn:1000002",
        "tgn:7029392"
    ],
    "tgn:id":7278486,
    "tgn:name":"Zulema, Punta",
    "tgn:placetype":[
        "aat:300386846"
    ]
},
  "bbox": [],
  "geometry": {"coordinates":[-74.583333,-47.816667],"type":"Point"}
}