{
  "id": 2097318,
  "type": "Feature",
  "properties": {
    "tgn:hierarchy":[
        "tgn:2097318",
        "tgn:1000001",
        "tgn:2001811",
        "tgn:7012149",
        "tgn:7007713",
        "tgn:7029392"
    ],
    "tgn:id":2097318,
    "tgn:name":"Lennox",
    "tgn:placetype":[
        "aat:300008347"
    ]
},
  "bbox": [],
  "geometry": {"coordinates":[-96.8833,43.35],"type":"Point"}
}