{
  "id": 7219934,
  "type": "Feature",
  "properties": {
    "tgn:hierarchy":[
        "tgn:7219934",
        "tgn:7011163",
        "tgn:7002674",
        "tgn:1000003",
        "tgn:1000074",
        "tgn:7029392"
    ],
    "tgn:id":7219934,
    "tgn:name":"\u00c1gios Vas\u00edleios, Vr\u00e1chos",
    "tgn:placetype":[
        "aat:300011692"
    ]
},
  "bbox": [],
  "geometry": {"coordinates":[26.534167,39.018056],"type":"Point"}
}