<<<<<<< HEAD
{
  "id": 2157756,
  "type": "Feature",
  "properties": {
    "tgn:hierarchy":[
        "tgn:2157756",
        "tgn:1000001",
        "tgn:7012149",
        "tgn:7007157",
        "tgn:1002858",
        "tgn:7029392"
    ],
    "tgn:id":2157756,
    "tgn:name":"Beaver Hollow",
    "tgn:placetype":[
        "aat:300008761"
    ]
},
  "bbox": [],
  "geometry": {"coordinates":[-116.8,32.7167],"type":"Point"}
}
=======
{"geometry":{"type":"Point","coordinates":[-116.800000,32.716700]},"type":"Feature","properties":{"hierarchy":["tgn:2157756","tgn:1000001","tgn:7012149","tgn:7007157","tgn:1002858","tgn:7029392"],"placetype":["aat:300008761"],"id":2157756,"name:xx":"Beaver Hollow"}}
>>>>>>> 03f74aca74312dbeaf24d7e61306dd6a786dc3d0
