{
  "id": 1083043,
  "type": "Feature",
  "properties": {
    "tgn:hierarchy":[
        "tgn:1083043",
        "tgn:1001163",
        "tgn:1000004",
        "tgn:7029379",
        "tgn:7029392"
    ],
    "tgn:id":1083043,
    "tgn:name":"Sharga",
    "tgn:placetype":[
        "aat:300008347"
    ]
},
  "bbox": [],
  "geometry": {"coordinates":[102.08,49.05],"type":"Point"}
}