{
  "id": 2601848,
  "type": "Feature",
  "properties": {
    "tgn:hierarchy":[
        "tgn:2601848",
        "tgn:1002483",
        "tgn:7019080",
        "tgn:1000001",
        "tgn:7012149",
        "tgn:7007249",
        "tgn:7029392"
    ],
    "tgn:id":2601848,
    "tgn:name":"Puu Kailio",
    "tgn:placetype":[
        "aat:300008798"
    ]
},
  "bbox": [],
  "geometry": {"coordinates":[-158.1167,21.4667],"type":"Point"}
}