{
  "id": 2735249,
  "type": "Feature",
  "properties": {
    "tgn:hierarchy":[
        "tgn:2735249",
        "tgn:1000001",
        "tgn:7012149",
        "tgn:7007158",
        "tgn:2000247",
        "tgn:7029392"
    ],
    "tgn:id":2735249,
    "tgn:name":"Twilight Peak",
    "tgn:placetype":[
        "aat:300008798"
    ]
},
  "bbox": [],
  "geometry": {"coordinates":[-107.7167,37.65],"type":"Point"}
}