<<<<<<< HEAD
{
  "id": 7055938,
  "type": "Feature",
  "properties": {
    "tgn:hierarchy":[
        "tgn:7055938",
        "tgn:7003150",
        "tgn:1000003",
        "tgn:7003237",
        "tgn:1000080",
        "tgn:7029392"
    ],
    "tgn:id":7055938,
    "tgn:name":"Opera",
    "tgn:placetype":[
        "aat:300008347"
    ]
},
  "bbox": [],
  "geometry": {"coordinates":[9.2,45.366667],"type":"Point"}
}
=======
{"geometry":{"type":"Point","coordinates":[9.200000,45.366667]},"type":"Feature","properties":{"hierarchy":["tgn:7055938","tgn:7003150","tgn:1000003","tgn:7003237","tgn:1000080","tgn:7029392"],"placetype":["aat:300008347"],"id":7055938,"name:xx":"Opera"}}
>>>>>>> 03f74aca74312dbeaf24d7e61306dd6a786dc3d0
