{
  "id": 7412236,
  "type": "Feature",
  "properties": {
    "tgn:hierarchy":[
        "tgn:7412236",
        "tgn:7005587",
        "tgn:1000001",
        "tgn:7005560",
        "tgn:7029392"
    ],
    "tgn:id":7412236,
    "tgn:name:es":"Camelia",
    "tgn:placetype":[
        "aat:300008347"
    ]
},
  "bbox": [],
  "geometry": {"coordinates":[-98.719444,20.152778],"type":"Point"}
}