{
  "id": 7163614,
  "type": "Feature",
  "properties": {
    "tgn:hierarchy":[
        "tgn:7163614",
        "tgn:1000003",
        "tgn:7003688",
        "tgn:7000084",
        "tgn:7029392"
    ],
    "tgn:id":7163614,
    "tgn:name":"H\u00fcsfeld",
    "tgn:placetype":[
        "aat:300000206"
    ]
},
  "bbox": [],
  "geometry": {"coordinates":[9.95,54.75],"type":"Point"}
}