{
  "id": 7474748,
  "type": "Feature",
  "properties": {
    "tgn:hierarchy":[
        "tgn:7474748",
        "tgn:1000004",
        "tgn:7001009",
        "tgn:1000141",
        "tgn:7029392"
    ],
    "tgn:id":7474748,
    "tgn:name":"Yongxingli",
    "tgn:placetype":[
        "aat:300008347"
    ]
},
  "bbox": [],
  "geometry": {"coordinates":[120.666667,24.116667],"type":"Point"}
}