{
  "id": 2181995,
  "type": "Feature",
  "properties": {
    "tgn:hierarchy":[
        "tgn:2181995",
        "tgn:1000001",
        "tgn:7012149",
        "tgn:1002594",
        "tgn:7007920",
        "tgn:7029392"
    ],
    "tgn:id":2181995,
    "tgn:name":"Blue Lake",
    "tgn:placetype":[
        "aat:300008680"
    ]
},
  "bbox": [],
  "geometry": {"coordinates":[-121.6833,46.3833],"type":"Point"}
}