{
  "id": 1140977,
  "type": "Feature",
  "properties": {
    "tgn:hierarchy":[
        "tgn:1140977",
        "tgn:7000490",
        "tgn:1000006",
        "tgn:7001834",
        "tgn:7029392"
    ],
    "tgn:id":1140977,
    "tgn:name":"Glenroy",
    "tgn:placetype":[
        "aat:300008347",
        "aat:300008375"
    ]
},
  "bbox": [],
  "geometry": {"coordinates":[114.8167,-21.7667],"type":"Point"}
}