{
  "id": 2396017,
  "type": "Feature",
  "properties": {
    "tgn:hierarchy":[
        "tgn:2396017",
        "tgn:1000001",
        "tgn:7012149",
        "tgn:2002384",
        "tgn:7007923",
        "tgn:7029392"
    ],
    "tgn:id":2396017,
    "tgn:name":"Holly Lake",
    "tgn:placetype":[
        "aat:300008680"
    ]
},
  "bbox": [],
  "geometry": {"coordinates":[-110.7833,43.7833],"type":"Point"}
}