{
  "id": 7117436,
  "type": "Feature",
  "properties": {
    "tgn:hierarchy":[
        "tgn:7117436",
        "tgn:7003692",
        "tgn:1000003",
        "tgn:7000084",
        "tgn:7029392"
    ],
    "tgn:id":7117436,
    "tgn:name":"Oberstelzhausen",
    "tgn:placetype":[
        "aat:300008347"
    ]
},
  "bbox": [],
  "geometry": {"coordinates":[10.216667,49.15],"type":"Point"}
}