{
  "id": 1101771,
  "type": "Feature",
  "properties": {
    "tgn:hierarchy":[
        "tgn:1101771",
        "tgn:7002759",
        "tgn:7008909",
        "tgn:1000003",
        "tgn:1000095",
        "tgn:7029392"
    ],
    "tgn:id":1101771,
    "tgn:name":"Ordesa, Parque Nacional de",
    "tgn:placetype":[
        "aat:300008189",
        "aat:300008187"
    ]
},
  "bbox": [],
  "geometry": {"coordinates":[0.083333,42.65],"type":"Point"}
}