{
  "id": 7374542,
  "type": "Feature",
  "properties": {
    "tgn:hierarchy":[
        "tgn:7374542",
        "tgn:1000001",
        "tgn:7005597",
        "tgn:7005560",
        "tgn:7029392"
    ],
    "tgn:id":7374542,
    "tgn:name":"La Crucita",
    "tgn:placetype":[
        "aat:300008347"
    ]
},
  "bbox": [],
  "geometry": {"coordinates":[-99.366667,24.75],"type":"Point"}
}