{
  "id": 2230534,
  "type": "Feature",
  "properties": {
    "tgn:hierarchy":[
        "tgn:2230534",
        "tgn:1000001",
        "tgn:7006451",
        "tgn:2000093",
        "tgn:7012149",
        "tgn:7029392"
    ],
    "tgn:id":2230534,
    "tgn:name":"Center Mountain",
    "tgn:placetype":[
        "aat:300008798"
    ]
},
  "bbox": [],
  "geometry": {"coordinates":[-110.9167,33.85],"type":"Point"}
}