{
  "id": 7009189,
  "type": "Feature",
  "properties": {
    "tgn:hierarchy":[
        "tgn:7009189",
        "tgn:1000003",
        "tgn:7002888",
        "tgn:1000070",
        "tgn:7029392"
    ],
    "tgn:id":7009189,
    "tgn:name":"Frouard",
    "tgn:placetype":[
        "aat:300008347"
    ]
},
  "bbox": [],
  "geometry": {"coordinates":[6.1333,48.7667],"type":"Point"}
}