{
  "id": 2552278,
  "type": "Feature",
  "properties": {
    "tgn:hierarchy":[
        "tgn:2552278",
        "tgn:1000001",
        "tgn:7012149",
        "tgn:2001885",
        "tgn:7007825",
        "tgn:7029392"
    ],
    "tgn:id":2552278,
    "tgn:name":"Number Thirty, Island",
    "tgn:placetype":[
        "aat:300008791"
    ]
},
  "bbox": [],
  "geometry": {"coordinates":[-89.95,35.6833],"type":"Point"}
}