{
  "id": 7305994,
  "type": "Feature",
  "properties": {
    "tgn:hierarchy":[
        "tgn:7305994",
        "tgn:7008911",
        "tgn:1000003",
        "tgn:7002763",
        "tgn:1000095",
        "tgn:7029392"
    ],
    "tgn:id":7305994,
    "tgn:name":"Manjoya",
    "tgn:placetype":[
        "aat:300008347"
    ]
},
  "bbox": [],
  "geometry": {"coordinates":[-5.833333,43.35],"type":"Point"}
}