{
  "id": 2291293,
  "type": "Feature",
  "properties": {
    "tgn:hierarchy":[
        "tgn:2291293",
        "tgn:1000001",
        "tgn:2000939",
        "tgn:7012149",
        "tgn:7007516",
        "tgn:7029392"
    ],
    "tgn:id":2291293,
    "tgn:name":"Dogwood Harbor",
    "tgn:placetype":[
        "aat:300132316"
    ]
},
  "bbox": [],
  "geometry": {"coordinates":[-76.3167,38.6833],"type":"Point"}
}