{
  "id": 2529661,
  "type": "Feature",
  "properties": {
    "tgn:hierarchy":[
        "tgn:2529661",
        "tgn:1000001",
        "tgn:7012149",
        "tgn:2001377",
        "tgn:7007525",
        "tgn:7029392"
    ],
    "tgn:id":2529661,
    "tgn:name":"Mud Lakes",
    "tgn:placetype":[
        "aat:300008680"
    ]
},
  "bbox": [],
  "geometry": {"coordinates":[-102.75,41.4667],"type":"Point"}
}