{
  "id": 2334285,
  "type": "Feature",
  "properties": {
    "tgn:hierarchy":[
        "tgn:2334285",
        "tgn:1002309",
        "tgn:1000001",
        "tgn:7012149",
        "tgn:7007565",
        "tgn:7029392"
    ],
    "tgn:id":2334285,
    "tgn:name":"Forest Grove",
    "tgn:placetype":[
        "aat:300008347"
    ]
},
  "bbox": [],
  "geometry": {"coordinates":[-75.0333,39.5167],"type":"Point"}
}