{
  "id": 2722809,
  "type": "Feature",
  "properties": {
    "tgn:hierarchy":[
        "tgn:2722809",
        "tgn:1000001",
        "tgn:2001736",
        "tgn:7012149",
        "tgn:7007712",
        "tgn:7029392"
    ],
    "tgn:id":2722809,
    "tgn:name":"Tip Top",
    "tgn:placetype":[
        "aat:300008347"
    ]
},
  "bbox": [],
  "geometry": {"coordinates":[-81.0667,34.65],"type":"Point"}
}