{
  "id": 7055153,
  "type": "Feature",
  "properties": {
    "tgn:hierarchy":[
        "tgn:7055153",
        "tgn:7005765",
        "tgn:1000003",
        "tgn:7003237",
        "tgn:1000080",
        "tgn:7029392"
    ],
    "tgn:id":7055153,
    "tgn:name":"Ossimo",
    "tgn:placetype":[
        "aat:300387198",
        "aat:300265612"
    ]
},
  "bbox": [],
  "geometry": {"coordinates":[10.216667,45.933333],"type":"Point"}
}