{
  "id": 7304106,
  "type": "Feature",
  "properties": {
    "tgn:hierarchy":[
        "tgn:7304106",
        "tgn:7002832",
        "tgn:7001158",
        "tgn:1000003",
        "tgn:1000095",
        "tgn:7029392"
    ],
    "tgn:id":7304106,
    "tgn:name":"Nava, Arroyo de la",
    "tgn:placetype":[
        "aat:300008699"
    ]
},
  "bbox": [],
  "geometry": {"coordinates":[-4.55,42.016667],"type":"Point"}
}