{
  "id": 7295725,
  "type": "Feature",
  "properties": {
    "tgn:hierarchy":[
        "tgn:7295725",
        "tgn:7002759",
        "tgn:7002845",
        "tgn:1000003",
        "tgn:1000095",
        "tgn:7029392"
    ],
    "tgn:id":7295725,
    "tgn:name":"Villanueva de Jal\u00f3n",
    "tgn:placetype":[
        "aat:300008347"
    ]
},
  "bbox": [],
  "geometry": {"coordinates":[-1.516667,41.483333],"type":"Point"}
}