{
  "id": 7316551,
  "type": "Feature",
  "properties": {
    "tgn:hierarchy":[
        "tgn:7316551",
        "tgn:1001695",
        "tgn:1000049",
        "tgn:1000002",
        "tgn:7029392"
    ],
    "tgn:id":7316551,
    "tgn:name":"Carrizalillo",
    "tgn:placetype":[
        "aat:300387200"
    ]
},
  "bbox": [],
  "geometry": {"coordinates":[-71.566667,-34.233333],"type":"Point"}
}