{
  "id": 7519078,
  "type": "Feature",
  "properties": {
    "tgn:hierarchy":[
        "tgn:7519078",
        "tgn:1008380",
        "tgn:1000226",
        "tgn:7000512",
        "tgn:1000006",
        "tgn:7029392"
    ],
    "tgn:id":7519078,
    "tgn:name:en":"Arapawaiti",
    "tgn:placetype":[
        "aat:300386846"
    ]
},
  "bbox": [],
  "geometry": {"coordinates":[174.916667,-40.816667],"type":"Point"}
}