{
  "id": 7195102,
  "type": "Feature",
  "properties": {
    "tgn:hierarchy":[
        "tgn:7195102",
        "tgn:1000003",
        "tgn:7003677",
        "tgn:7000084",
        "tgn:7029392"
    ],
    "tgn:id":7195102,
    "tgn:name":"Bahnhof Dornap-Hahnenfurth",
    "tgn:placetype":[
        "aat:300007783"
    ]
},
  "bbox": [],
  "geometry": {"coordinates":[7.0425,51.25],"type":"Point"}
}