{
  "id": 7053303,
  "type": "Feature",
  "properties": {
    "tgn:hierarchy":[
        "tgn:7053303",
        "tgn:7003168",
        "tgn:1000003",
        "tgn:7009760",
        "tgn:1000080",
        "tgn:7029392"
    ],
    "tgn:id":7053303,
    "tgn:name":"Maggio, Monte",
    "tgn:placetype":[
        "aat:300008795"
    ]
},
  "bbox": [],
  "geometry": {"coordinates":[11.183333,43.366667],"type":"Point"}
}