{
  "id": 7283890,
  "type": "Feature",
  "properties": {
    "tgn:hierarchy":[
        "tgn:7283890",
        "tgn:1001699",
        "tgn:1000049",
        "tgn:1000002",
        "tgn:7029392"
    ],
    "tgn:id":7283890,
    "tgn:name":"Puralaco, Cerros de",
    "tgn:placetype":[
        "aat:300008795"
    ]
},
  "bbox": [],
  "geometry": {"coordinates":[-73.15,-39.333333],"type":"Point"}
}