{
  "id": 2314789,
  "type": "Feature",
  "properties": {
    "tgn:hierarchy":[
        "tgn:2314789",
        "tgn:1000001",
        "tgn:7012149",
        "tgn:2000812",
        "tgn:7007255",
        "tgn:7029392"
    ],
    "tgn:id":2314789,
    "tgn:name":"Elkhorn Branch",
    "tgn:placetype":[
        "aat:300008699"
    ]
},
  "bbox": [],
  "geometry": {"coordinates":[-82.85,37.1833],"type":"Point"}
}