{
  "id": 1058560,
  "type": "Feature",
  "properties": {
    "tgn:hierarchy":[
        "tgn:1058560",
        "tgn:1000004",
        "tgn:7012941",
        "tgn:7018214",
        "tgn:7002435",
        "tgn:7029392"
    ],
    "tgn:id":1058560,
    "tgn:name":"Polovo",
    "tgn:placetype":[
        "aat:300008347"
    ]
},
  "bbox": [],
  "geometry": {"coordinates":[32.45,57.0167],"type":"Point"}
}