{
  "id": 7547315,
  "type": "Feature",
  "properties": {
    "tgn:hierarchy":[
        "tgn:7547315",
        "tgn:1000004",
        "tgn:1001869",
        "tgn:7000198",
        "tgn:7029392"
    ],
    "tgn:id":7547315,
    "tgn:name:en":"Ban Creek",
    "tgn:placetype":[
        "aat:300266571"
    ]
},
  "bbox": [],
  "geometry": {"coordinates":[72.533333,21.733333],"type":"Point"}
}