{
  "id": 7207262,
  "type": "Feature",
  "properties": {
    "tgn:hierarchy":[
        "tgn:7207262",
        "tgn:1000003",
        "tgn:7003688",
        "tgn:7000084",
        "tgn:7029392"
    ],
    "tgn:id":7207262,
    "tgn:name":"Butter Loch",
    "tgn:placetype":[
        "aat:300008713"
    ]
},
  "bbox": [],
  "geometry": {"coordinates":[8.833333,54.583333],"type":"Point"}
}