{
  "id": 2429062,
  "type": "Feature",
  "properties": {
    "tgn:hierarchy":[
        "tgn:2429062",
        "tgn:1000001",
        "tgn:2001418",
        "tgn:7012149",
        "tgn:7007526",
        "tgn:7029392"
    ],
    "tgn:id":2429062,
    "tgn:name":"Junction",
    "tgn:placetype":[
        "aat:300008347"
    ]
},
  "bbox": [],
  "geometry": {"coordinates":[-117.1167,39.0833],"type":"Point"}
}