<<<<<<< HEAD
{
  "id": 2769255,
  "type": "Feature",
  "properties": {
    "tgn:hierarchy":[
        "tgn:2769255",
        "tgn:1000001",
        "tgn:7012149",
        "tgn:2002341",
        "tgn:7007922",
        "tgn:7029392"
    ],
    "tgn:id":2769255,
    "tgn:name":"Wichser Lake",
    "tgn:placetype":[
        "aat:300008680"
    ]
},
  "bbox": [],
  "geometry": {"coordinates":[-88.6667,45.2333],"type":"Point"}
}
=======
{"geometry":{"type":"Point","coordinates":[-88.666700,45.233300]},"type":"Feature","properties":{"hierarchy":["tgn:2769255","tgn:1000001","tgn:7012149","tgn:2002341","tgn:7007922","tgn:7029392"],"placetype":["aat:300008680"],"id":2769255,"name:xx":"Wichser Lake"}}
>>>>>>> 03f74aca74312dbeaf24d7e61306dd6a786dc3d0
