{
  "id": 2718629,
  "type": "Feature",
  "properties": {
    "tgn:hierarchy":[
        "tgn:2718629",
        "tgn:1000001",
        "tgn:7012149",
        "tgn:2000183",
        "tgn:7007157",
        "tgn:7029392"
    ],
    "tgn:id":2718629,
    "tgn:name":"Thompson Spring",
    "tgn:placetype":[
        "aat:300008697"
    ]
},
  "bbox": [],
  "geometry": {"coordinates":[-117.45,36.2167],"type":"Point"}
}