{
  "id": 7014036,
  "type": "Feature",
  "properties": {
    "tgn:hierarchy":[
        "tgn:7014036",
        "tgn:1003373",
        "tgn:1000004",
        "tgn:7018214",
        "tgn:7002435",
        "tgn:7029392"
    ],
    "tgn:id":7014036,
    "tgn:name":"Bratsk",
    "tgn:placetype":[
        "aat:300008347",
        "aat:300008389",
        "aat:300387302",
        "aat:300387312",
        "aat:300387280"
    ]
},
  "bbox": [],
  "geometry": {"coordinates":[101.8333,56.3333],"type":"Point"}
}