{
  "id": 2305292,
  "type": "Feature",
  "properties": {
    "tgn:hierarchy":[
        "tgn:2305292",
        "tgn:1000001",
        "tgn:7012149",
        "tgn:1002945",
        "tgn:7007710",
        "tgn:7029392"
    ],
    "tgn:id":2305292,
    "tgn:name":"East Branch Stony Fork",
    "tgn:placetype":[
        "aat:300008699"
    ]
},
  "bbox": [],
  "geometry": {"coordinates":[-77.3333,41.7167],"type":"Point"}
}