{
  "id": 7344304,
  "type": "Feature",
  "properties": {
    "tgn:hierarchy":[
        "tgn:7344304",
        "tgn:7007780",
        "tgn:1000003",
        "tgn:7009604",
        "tgn:1000095",
        "tgn:7029392"
    ],
    "tgn:id":7344304,
    "tgn:name":"Arrietas",
    "tgn:placetype":[
        "aat:300008347"
    ]
},
  "bbox": [],
  "geometry": {"coordinates":[-2.301713,42.976268],"type":"Point"}
}