{
  "id": 7507900,
  "type": "Feature",
  "properties": {
    "tgn:hierarchy":[
        "tgn:7507900",
        "tgn:1009227",
        "tgn:1000226",
        "tgn:7016822",
        "tgn:1000006",
        "tgn:7029392"
    ],
    "tgn:id":7507900,
    "tgn:name:en":"Perpendicular Head",
    "tgn:placetype":[
        "aat:300008850"
    ]
},
  "bbox": [],
  "geometry": {"coordinates":[166.25,-50.866667],"type":"Point"}
}