{
  "id": 2744961,
  "type": "Feature",
  "properties": {
    "tgn:hierarchy":[
        "tgn:2744961",
        "tgn:1000001",
        "tgn:7012149",
        "tgn:2000390",
        "tgn:7007248",
        "tgn:7029392"
    ],
    "tgn:id":2744961,
    "tgn:name":"View, The",
    "tgn:placetype":[
        "aat:300055621"
    ]
},
  "bbox": [],
  "geometry": {"coordinates":[-84.6667,32.8667],"type":"Point"}
}