{
  "id": 2581579,
  "type": "Feature",
  "properties": {
    "tgn:hierarchy":[
        "tgn:2581579",
        "tgn:1000001",
        "tgn:7012149",
        "tgn:2000818",
        "tgn:7007255",
        "tgn:7029392"
    ],
    "tgn:id":2581579,
    "tgn:name":"Pilot Rock",
    "tgn:placetype":[
        "aat:300008798"
    ]
},
  "bbox": [],
  "geometry": {"coordinates":[-84.5667,36.8167],"type":"Point"}
}