<<<<<<< HEAD
{
  "id": 2404889,
  "type": "Feature",
  "properties": {
    "tgn:hierarchy":[
        "tgn:2404889",
        "tgn:1000001",
        "tgn:7012149",
        "tgn:1002682",
        "tgn:7007710",
        "tgn:7029392"
    ],
    "tgn:id":2404889,
    "tgn:name":"Huckleberry Swamp",
    "tgn:placetype":[
        "aat:300008905"
    ]
},
  "bbox": [],
  "geometry": {"coordinates":[-75.3,41.0667],"type":"Point"}
}
=======
{"geometry":{"type":"Point","coordinates":[-75.300000,41.066700]},"type":"Feature","properties":{"hierarchy":["tgn:2404889","tgn:1000001","tgn:7012149","tgn:1002682","tgn:7007710","tgn:7029392"],"placetype":["aat:300008905"],"id":2404889,"name:xx":"Huckleberry Swamp"}}
>>>>>>> 03f74aca74312dbeaf24d7e61306dd6a786dc3d0
