{
  "id": 2052995,
  "type": "Feature",
  "properties": {
    "tgn:hierarchy":[
        "tgn:2052995",
        "tgn:1000001",
        "tgn:7012149",
        "tgn:2000964",
        "tgn:7007520",
        "tgn:7029392"
    ],
    "tgn:id":2052995,
    "tgn:name":"Pigeon",
    "tgn:placetype":[
        "aat:300008347"
    ]
},
  "bbox": [],
  "geometry": {"coordinates":[-83.2667,43.8167],"type":"Point"}
}