{
  "id": 7361333,
  "type": "Feature",
  "properties": {
    "tgn:hierarchy":[
        "tgn:7361333",
        "tgn:1001853",
        "tgn:1000001",
        "tgn:7005560",
        "tgn:7029392"
    ],
    "tgn:id":7361333,
    "tgn:name":"El Consuelo",
    "tgn:placetype":[
        "aat:300008347"
    ]
},
  "bbox": [],
  "geometry": {"coordinates":[-103.266667,25.566667],"type":"Point"}
}