{
  "id": 7481062,
  "type": "Feature",
  "properties": {
    "tgn:hierarchy":[
        "tgn:7481062",
        "tgn:1000004",
        "tgn:7001014",
        "tgn:1000141",
        "tgn:7029392"
    ],
    "tgn:id":7481062,
    "tgn:name":"Wengang",
    "tgn:placetype":[
        "aat:300387033"
    ]
},
  "bbox": [],
  "geometry": {"coordinates":[120.226944,23.750833],"type":"Point"}
}