{
  "id": 2222702,
  "type": "Feature",
  "properties": {
    "tgn:hierarchy":[
        "tgn:2222702",
        "tgn:1000001",
        "tgn:7012149",
        "tgn:7007523",
        "tgn:7029392"
    ],
    "tgn:id":2222702,
    "tgn:name":"Carr Creek",
    "tgn:placetype":[
        "aat:300008706"
    ]
},
  "bbox": [],
  "geometry": {"coordinates":[-91.15,37.2333],"type":"Point"}
}