<<<<<<< HEAD
{
  "id": 7363038,
  "type": "Feature",
  "properties": {
    "tgn:hierarchy":[
        "tgn:7363038",
        "tgn:1000001",
        "tgn:7005597",
        "tgn:7005560",
        "tgn:7029392"
    ],
    "tgn:id":7363038,
    "tgn:name":"Rancho El Catan",
    "tgn:placetype":[
        "aat:300000241"
    ]
},
  "bbox": [],
  "geometry": {"coordinates":[-99.0,26.116667],"type":"Point"}
}
=======
{"geometry":{"type":"Point","coordinates":[-99.000000,26.116667]},"type":"Feature","properties":{"hierarchy":["tgn:7363038","tgn:1000001","tgn:7005597","tgn:7005560","tgn:7029392"],"placetype":["aat:300000241"],"id":7363038,"name:xx":"Rancho El Catan"}}
>>>>>>> 03f74aca74312dbeaf24d7e61306dd6a786dc3d0
