{
  "id": 7204067,
  "type": "Feature",
  "properties": {
    "tgn:hierarchy":[
        "tgn:7204067",
        "tgn:1000003",
        "tgn:7003687",
        "tgn:7000084",
        "tgn:7029392"
    ],
    "tgn:id":7204067,
    "tgn:name":"Braune Wasser",
    "tgn:placetype":[
        "aat:300008699"
    ]
},
  "bbox": [],
  "geometry": {"coordinates":[10.716667,51.783333],"type":"Point"}
}