{
  "id": 2359357,
  "type": "Feature",
  "properties": {
    "tgn:hierarchy":[
        "tgn:2359357",
        "tgn:1000001",
        "tgn:7012149",
        "tgn:2000838",
        "tgn:7007255",
        "tgn:7029392"
    ],
    "tgn:id":2359357,
    "tgn:name":"Granny Townsend Branch",
    "tgn:placetype":[
        "aat:300008699"
    ]
},
  "bbox": [],
  "geometry": {"coordinates":[-83.6667,37.7833],"type":"Point"}
}