<<<<<<< HEAD
{
  "id": 7360015,
  "type": "Feature",
  "properties": {
    "tgn:hierarchy":[
        "tgn:7360015",
        "tgn:1000001",
        "tgn:1001960",
        "tgn:7005560",
        "tgn:7029392"
    ],
    "tgn:id":7360015,
    "tgn:name":"Cuchilla, Cerro",
    "tgn:placetype":[
        "aat:300008795"
    ]
},
  "bbox": [],
  "geometry": {"coordinates":[-110.35,31.3],"type":"Point"}
}
=======
{"geometry":{"type":"Point","coordinates":[-110.350000,31.300000]},"type":"Feature","properties":{"hierarchy":["tgn:7360015","tgn:1000001","tgn:1001960","tgn:7005560","tgn:7029392"],"placetype":["aat:300008795"],"id":7360015,"name:xx":"Cuchilla, Cerro"}}
>>>>>>> 03f74aca74312dbeaf24d7e61306dd6a786dc3d0
