<<<<<<< HEAD
{
  "id": 2409965,
  "type": "Feature",
  "properties": {
    "tgn:hierarchy":[
        "tgn:2409965",
        "tgn:1000001",
        "tgn:2000458",
        "tgn:7012149",
        "tgn:7007250",
        "tgn:7029392"
    ],
    "tgn:id":2409965,
    "tgn:name":"Imperial Gulch",
    "tgn:placetype":[
        "aat:300008761"
    ]
},
  "bbox": [],
  "geometry": {"coordinates":[-114.4167,43.5667],"type":"Point"}
}
=======
{"geometry":{"type":"Point","coordinates":[-114.416700,43.566700]},"type":"Feature","properties":{"hierarchy":["tgn:2409965","tgn:1000001","tgn:2000458","tgn:7012149","tgn:7007250","tgn:7029392"],"placetype":["aat:300008761"],"id":2409965,"name:xx":"Imperial Gulch"}}
>>>>>>> 03f74aca74312dbeaf24d7e61306dd6a786dc3d0
