{
  "id": 2248037,
  "type": "Feature",
  "properties": {
    "tgn:hierarchy":[
        "tgn:2248037",
        "tgn:1000001",
        "tgn:2002132",
        "tgn:7012149",
        "tgn:7007828",
        "tgn:7029392"
    ],
    "tgn:id":2248037,
    "tgn:name":"Colchester Shoal",
    "tgn:placetype":[
        "aat:300132348"
    ]
},
  "bbox": [],
  "geometry": {"coordinates":[-73.3333,44.5333],"type":"Point"}
}