{
  "id": 7107497,
  "type": "Feature",
  "properties": {
    "tgn:hierarchy":[
        "tgn:7107497",
        "tgn:7003669",
        "tgn:1000003",
        "tgn:7000084",
        "tgn:7029392"
    ],
    "tgn:id":7107497,
    "tgn:name":"Pro\u00df",
    "tgn:placetype":[
        "aat:300008347"
    ]
},
  "bbox": [],
  "geometry": {"coordinates":[11.383333,50.066667],"type":"Point"}
}