{
  "id": 7520105,
  "type": "Feature",
  "properties": {
    "tgn:hierarchy":[
        "tgn:7520105",
        "tgn:7001242",
        "tgn:7001311",
        "tgn:7016833",
        "tgn:7029392"
    ],
    "tgn:id":7520105,
    "tgn:name:en":"Abu Shiqeili, W\u00e2di",
    "tgn:placetype":[
        "aat:300379998"
    ]
},
  "bbox": [],
  "geometry": {"coordinates":[34.052732,26.502496],"type":"Point"}
}