<<<<<<< HEAD
{
  "id": 2339370,
  "type": "Feature",
  "properties": {
    "tgn:hierarchy":[
        "tgn:2339370",
        "tgn:7006450",
        "tgn:1000001",
        "tgn:7012149",
        "tgn:2000079",
        "tgn:7029392"
    ],
    "tgn:id":2339370,
    "tgn:name":"Frazier Creek",
    "tgn:placetype":[
        "aat:300008706"
    ]
},
  "bbox": [],
  "geometry": {"coordinates":[-166.1833,65.3167],"type":"Point"}
}
=======
{"geometry":{"type":"Point","coordinates":[-166.183300,65.316700]},"type":"Feature","properties":{"hierarchy":["tgn:2339370","tgn:7006450","tgn:1000001","tgn:7012149","tgn:2000079","tgn:7029392"],"placetype":["aat:300008706"],"id":2339370,"name:xx":"Frazier Creek"}}
>>>>>>> 03f74aca74312dbeaf24d7e61306dd6a786dc3d0
