{
  "id": 7220299,
  "type": "Feature",
  "properties": {
    "tgn:hierarchy":[
        "tgn:7220299",
        "tgn:7011270",
        "tgn:7002674",
        "tgn:1000003",
        "tgn:1000074",
        "tgn:7029392"
    ],
    "tgn:id":7220299,
    "tgn:name":"Vayi\u00e1, \u00d3rmos",
    "tgn:placetype":[
        "aat:300132316"
    ]
},
  "bbox": [],
  "geometry": {"coordinates":[25.733333,36.383333],"type":"Point"}
}