{
  "id": 2782172,
  "type": "Feature",
  "properties": {
    "tgn:hierarchy":[
        "tgn:2782172",
        "tgn:2001728",
        "tgn:1000001",
        "tgn:7012149",
        "tgn:7007712",
        "tgn:7029392"
    ],
    "tgn:id":2782172,
    "tgn:name":"Woodson Pond",
    "tgn:placetype":[
        "aat:300006191"
    ]
},
  "bbox": [],
  "geometry": {"coordinates":[-82.45,34.75],"type":"Point"}
}