{
  "id": 7228427,
  "type": "Feature",
  "properties": {
    "tgn:hierarchy":[
        "tgn:7228427",
        "tgn:7002706",
        "tgn:7002705",
        "tgn:1000003",
        "tgn:1000074",
        "tgn:7029392"
    ],
    "tgn:id":7228427,
    "tgn:name":"Kastan\u00e9a",
    "tgn:placetype":[
        "aat:300008347"
    ]
},
  "bbox": [],
  "geometry": {"coordinates":[21.297222,39.313056],"type":"Point"}
}