{
  "id": 7505899,
  "type": "Feature",
  "properties": {
    "tgn:hierarchy":[
        "tgn:7505899",
        "tgn:7016670",
        "tgn:1008380",
        "tgn:1000226",
        "tgn:1000006",
        "tgn:7029392"
    ],
    "tgn:id":7505899,
    "tgn:name:en":"Tapui o Marua Hine",
    "tgn:placetype":[
        "aat:300008795"
    ]
},
  "bbox": [],
  "geometry": {"coordinates":[176.166667,-39.15],"type":"Point"}
}