{
  "id": 7581245,
  "type": "Feature",
  "properties": {
    "tgn:hierarchy":[
        "tgn:7581245",
        "tgn:1000004",
        "tgn:7000198",
        "tgn:1001895",
        "tgn:7029392"
    ],
    "tgn:id":7581245,
    "tgn:name:en":"Vasind",
    "tgn:placetype":[
        "aat:300008347"
    ]
},
  "bbox": [],
  "geometry": {"coordinates":[73.266667,19.416667],"type":"Point"}
}