{
  "id": 7405217,
  "type": "Feature",
  "properties": {
    "tgn:hierarchy":[
        "tgn:7405217",
        "tgn:7016644",
        "tgn:1000001",
        "tgn:7005560",
        "tgn:7029392"
    ],
    "tgn:id":7405217,
    "tgn:name":"San Juan",
    "tgn:placetype":[
        "aat:300008347"
    ]
},
  "bbox": [],
  "geometry": {"coordinates":[-103.529167,19.141667],"type":"Point"}
}