{
  "id": 2069272,
  "type": "Feature",
  "properties": {
    "tgn:hierarchy":[
        "tgn:2069272",
        "tgn:1000001",
        "tgn:1002328",
        "tgn:7012149",
        "tgn:7007568",
        "tgn:7029392"
    ],
    "tgn:id":2069272,
    "tgn:name":"Franklin",
    "tgn:placetype":[
        "aat:300008347"
    ]
},
  "bbox": [],
  "geometry": {"coordinates":[-75.15,42.3333],"type":"Point"}
}