<<<<<<< HEAD
{
  "id": 2337687,
  "type": "Feature",
  "properties": {
    "tgn:hierarchy":[
        "tgn:2337687",
        "tgn:7002659",
        "tgn:1000001",
        "tgn:7012149",
        "tgn:2000036",
        "tgn:7029392"
    ],
    "tgn:id":2337687,
    "tgn:name":"Fox Creek",
    "tgn:placetype":[
        "aat:300008706"
    ]
},
  "bbox": [],
  "geometry": {"coordinates":[-87.2667,33.4167],"type":"Point"}
}
=======
{"geometry":{"type":"Point","coordinates":[-87.266700,33.416700]},"type":"Feature","properties":{"hierarchy":["tgn:2337687","tgn:7002659","tgn:1000001","tgn:7012149","tgn:2000036","tgn:7029392"],"placetype":["aat:300008706"],"id":2337687,"name:xx":"Fox Creek"}}
>>>>>>> 03f74aca74312dbeaf24d7e61306dd6a786dc3d0
