{
  "id": 2537443,
  "type": "Feature",
  "properties": {
    "tgn:hierarchy":[
        "tgn:2537443",
        "tgn:1000001",
        "tgn:7012149",
        "tgn:2002288",
        "tgn:7013961",
        "tgn:7029392"
    ],
    "tgn:id":2537443,
    "tgn:name":"Negro Hollow",
    "tgn:placetype":[
        "aat:300008761"
    ]
},
  "bbox": [],
  "geometry": {"coordinates":[-79.8167,39.2833],"type":"Point"}
}