{
  "id": 2530877,
  "type": "Feature",
  "properties": {
    "tgn:hierarchy":[
        "tgn:2530877",
        "tgn:1000001",
        "tgn:7012149",
        "tgn:2002192",
        "tgn:7007919",
        "tgn:7029392"
    ],
    "tgn:id":2530877,
    "tgn:name":"Mudley Branch",
    "tgn:placetype":[
        "aat:300008699"
    ]
},
  "bbox": [],
  "geometry": {"coordinates":[-81.3667,37.1667],"type":"Point"}
}