{
  "id": 2783091,
  "type": "Feature",
  "properties": {
    "tgn:hierarchy":[
        "tgn:2783091",
        "tgn:1000001",
        "tgn:7012149",
        "tgn:7014344",
        "tgn:7007919",
        "tgn:7029392"
    ],
    "tgn:id":2783091,
    "tgn:name":"Wright Branch",
    "tgn:placetype":[
        "aat:300008699"
    ]
},
  "bbox": [],
  "geometry": {"coordinates":[-80.2333,37.35],"type":"Point"}
}