{
  "id": 2696189,
  "type": "Feature",
  "properties": {
    "tgn:hierarchy":[
        "tgn:2696189",
        "tgn:1000001",
        "tgn:7016172",
        "tgn:7012149",
        "tgn:2000149",
        "tgn:7029392"
    ],
    "tgn:id":2696189,
    "tgn:name":"Stone",
    "tgn:placetype":[
        "aat:300008347"
    ]
},
  "bbox": [],
  "geometry": {"coordinates":[-92.6333,36.3333],"type":"Point"}
}