<<<<<<< HEAD
{
  "id": 7113447,
  "type": "Feature",
  "properties": {
    "tgn:hierarchy":[
        "tgn:7113447",
        "tgn:1000003",
        "tgn:7003682",
        "tgn:7000084",
        "tgn:7029392"
    ],
    "tgn:id":7113447,
    "tgn:name":"Rieschweiler",
    "tgn:placetype":[
        "aat:300000745"
    ]
},
  "bbox": [],
  "geometry": {"coordinates":[7.5,49.25],"type":"Point"}
}
=======
{"geometry":{"type":"Point","coordinates":[7.500000,49.250000]},"type":"Feature","properties":{"hierarchy":["tgn:7113447","tgn:1000003","tgn:7003682","tgn:7000084","tgn:7029392"],"placetype":["aat:300000745"],"id":7113447,"name:xx":"Rieschweiler"}}
>>>>>>> 03f74aca74312dbeaf24d7e61306dd6a786dc3d0
