{
  "id": 7224924,
  "type": "Feature",
  "properties": {
    "tgn:hierarchy":[
        "tgn:7224924",
        "tgn:7002681",
        "tgn:7001395",
        "tgn:1000003",
        "tgn:1000074",
        "tgn:7029392"
    ],
    "tgn:id":7224924,
    "tgn:name":"N\u00e9on Ir\u00e1klion",
    "tgn:placetype":[
        "aat:300000745"
    ]
},
  "bbox": [],
  "geometry": {"coordinates":[23.766667,38.05],"type":"Point"}
}