{
  "id": 2268650,
  "type": "Feature",
  "properties": {
    "tgn:hierarchy":[
        "tgn:2268650",
        "tgn:1000001",
        "tgn:7012149",
        "tgn:2000280",
        "tgn:7007240",
        "tgn:7029392"
    ],
    "tgn:id":2268650,
    "tgn:name":"Cross Branch",
    "tgn:placetype":[
        "aat:300008699"
    ]
},
  "bbox": [],
  "geometry": {"coordinates":[-81.9667,30.65],"type":"Point"}
}