{
  "id": 2283323,
  "type": "Feature",
  "properties": {
    "tgn:hierarchy":[
        "tgn:2283323",
        "tgn:7006450",
        "tgn:1000001",
        "tgn:7012149",
        "tgn:2000082",
        "tgn:7029392"
    ],
    "tgn:id":2283323,
    "tgn:name":"Dell Island",
    "tgn:placetype":[
        "aat:300008791"
    ]
},
  "bbox": [],
  "geometry": {"coordinates":[-132.65,55.25],"type":"Point"}
}