{
  "id": 7300557,
  "type": "Feature",
  "properties": {
    "tgn:hierarchy":[
        "tgn:7300557",
        "tgn:7002832",
        "tgn:7001158",
        "tgn:1000003",
        "tgn:1000095",
        "tgn:7029392"
    ],
    "tgn:id":7300557,
    "tgn:name":"Valdeca\u00f1as de Cerrato",
    "tgn:placetype":[
        "aat:300008347"
    ]
},
  "bbox": [],
  "geometry": {"coordinates":[-4.183333,41.983333],"type":"Point"}
}