{
  "id": 1093493,
  "type": "Feature",
  "properties": {
    "tgn:hierarchy":[
        "tgn:1093493",
        "tgn:7001242",
        "tgn:7016562",
        "tgn:1000193",
        "tgn:7029392"
    ],
    "tgn:id":1093493,
    "tgn:name":"Perdeberg",
    "tgn:placetype":[
        "aat:300008347"
    ]
},
  "bbox": [],
  "geometry": {"coordinates":[25.0833,-28.9833],"type":"Point"}
}