{
  "id": 2245108,
  "type": "Feature",
  "properties": {
    "tgn:hierarchy":[
        "tgn:2245108",
        "tgn:1000001",
        "tgn:7012149",
        "tgn:7007157",
        "tgn:1002566",
        "tgn:7029392"
    ],
    "tgn:id":2245108,
    "tgn:name":"Clover Valley",
    "tgn:placetype":[
        "aat:300008761"
    ]
},
  "bbox": [],
  "geometry": {"coordinates":[-122.8333,39.15],"type":"Point"}
}