{
  "id": 2590685,
  "type": "Feature",
  "properties": {
    "tgn:hierarchy":[
        "tgn:2590685",
        "tgn:7013349",
        "tgn:1000001",
        "tgn:7012149",
        "tgn:7007708",
        "tgn:7029392"
    ],
    "tgn:id":2590685,
    "tgn:name":"Pole Gulch Reservoir",
    "tgn:placetype":[
        "aat:300006191"
    ]
},
  "bbox": [],
  "geometry": {"coordinates":[-117.7667,44.45],"type":"Point"}
}