{
  "id": 2278949,
  "type": "Feature",
  "properties": {
    "tgn:hierarchy":[
        "tgn:2278949",
        "tgn:1000001",
        "tgn:1002221",
        "tgn:7012149",
        "tgn:7007251",
        "tgn:7029392"
    ],
    "tgn:id":2278949,
    "tgn:name":"Dead Mans Island",
    "tgn:placetype":[
        "aat:300008791"
    ]
},
  "bbox": [],
  "geometry": {"coordinates":[-90.75,39.2833],"type":"Point"}
}