{
  "id": 7535302,
  "type": "Feature",
  "properties": {
    "tgn:hierarchy":[
        "tgn:7535302",
        "tgn:7001242",
        "tgn:7016833",
        "tgn:1001225",
        "tgn:7029392"
    ],
    "tgn:id":7535302,
    "tgn:name:en":"Kafr al 'A\u0163aw\u012b",
    "tgn:placetype":[
        "aat:300008347"
    ]
},
  "bbox": [],
  "geometry": {"coordinates":[31.774194,31.337502],"type":"Point"}
}