{
  "id": 2227769,
  "type": "Feature",
  "properties": {
    "tgn:hierarchy":[
        "tgn:2227769",
        "tgn:1000001",
        "tgn:2001260",
        "tgn:7012149",
        "tgn:7007524",
        "tgn:7029392"
    ],
    "tgn:id":2227769,
    "tgn:name":"Cayuse Spring",
    "tgn:placetype":[
        "aat:300008697"
    ]
},
  "bbox": [],
  "geometry": {"coordinates":[-111.8667,44.7167],"type":"Point"}
}