{
  "id": 7036147,
  "type": "Feature",
  "properties": {
    "tgn:hierarchy":[
        "tgn:7036147",
        "tgn:7002996",
        "tgn:1000003",
        "tgn:7002997",
        "tgn:1000080",
        "tgn:7029392"
    ],
    "tgn:id":7036147,
    "tgn:name":"Santa Maria",
    "tgn:placetype":[
        "aat:300008347"
    ]
},
  "bbox": [],
  "geometry": {"coordinates":[12.229444,45.992222],"type":"Point"}
}