{
  "id": 7183475,
  "type": "Feature",
  "properties": {
    "tgn:hierarchy":[
        "tgn:7183475",
        "tgn:1000003",
        "tgn:7003676",
        "tgn:7000084",
        "tgn:7029392"
    ],
    "tgn:id":7183475,
    "tgn:name":"Giltener Heide",
    "tgn:placetype":[
        "aat:300386887"
    ]
},
  "bbox": [],
  "geometry": {"coordinates":[9.516667,52.716667],"type":"Point"}
}