{
  "id": 2437263,
  "type": "Feature",
  "properties": {
    "tgn:hierarchy":[
        "tgn:2437263",
        "tgn:1000001",
        "tgn:7012149",
        "tgn:2002113",
        "tgn:7007827",
        "tgn:7029392"
    ],
    "tgn:id":2437263,
    "tgn:name":"Kimball Valley",
    "tgn:placetype":[
        "aat:300008761"
    ]
},
  "bbox": [],
  "geometry": {"coordinates":[-112.05,37.1833],"type":"Point"}
}