{
  "id": 2101612,
  "type": "Feature",
  "properties": {
    "tgn:hierarchy":[
        "tgn:2101612",
        "tgn:1000001",
        "tgn:7012149",
        "tgn:2001896",
        "tgn:7007825",
        "tgn:7029392"
    ],
    "tgn:id":2101612,
    "tgn:name":"Spencer Hill",
    "tgn:placetype":[
        "aat:300008347",
        "aat:300387210"
    ]
},
  "bbox": [],
  "geometry": {"coordinates":[-87.15,35.4333],"type":"Point"}
}