{
  "id": 2280357,
  "type": "Feature",
  "properties": {
    "tgn:hierarchy":[
        "tgn:2280357",
        "tgn:1000001",
        "tgn:7012149",
        "tgn:2002057",
        "tgn:7007826",
        "tgn:7029392"
    ],
    "tgn:id":2280357,
    "tgn:name":"Deck Spring",
    "tgn:placetype":[
        "aat:300008697"
    ]
},
  "bbox": [],
  "geometry": {"coordinates":[-104.4333,29.8833],"type":"Point"}
}