{
  "id": 7084702,
  "type": "Feature",
  "properties": {
    "tgn:hierarchy":[
        "tgn:7084702",
        "tgn:1000003",
        "tgn:7003676",
        "tgn:7000084",
        "tgn:7029392"
    ],
    "tgn:id":7084702,
    "tgn:name":"Wei\u00dfes Moor",
    "tgn:placetype":[
        "aat:300386886"
    ]
},
  "bbox": [],
  "geometry": {"coordinates":[9.583333,53.366667],"type":"Point"}
}