{
  "id": 2322865,
  "type": "Feature",
  "properties": {
    "tgn:hierarchy":[
        "tgn:2322865",
        "tgn:7006450",
        "tgn:1000001",
        "tgn:2124012",
        "tgn:7012149",
        "tgn:7029392"
    ],
    "tgn:id":2322865,
    "tgn:name":"Fang Point",
    "tgn:placetype":[
        "aat:300008850"
    ]
},
  "bbox": [],
  "geometry": {"coordinates":[-153.15,57.1833],"type":"Point"}
}