{
  "id": 1011772,
  "type": "Feature",
  "properties": {
    "tgn:hierarchy":[
        "tgn:1011772",
        "tgn:1000003",
        "tgn:7005238",
        "tgn:7029392"
    ],
    "tgn:id":1011772,
    "tgn:name":"Corbiere Point",
    "tgn:placetype":[
        "aat:300386846"
    ]
},
  "bbox": [],
  "geometry": {"coordinates":[-2.25,49.1667],"type":"Point"}
}