{
  "id": 2543589,
  "type": "Feature",
  "properties": {
    "tgn:hierarchy":[
        "tgn:2543589",
        "tgn:1000001",
        "tgn:7016172",
        "tgn:7012149",
        "tgn:2000143",
        "tgn:7029392"
    ],
    "tgn:id":2543589,
    "tgn:name":"North Alligator Bayou",
    "tgn:placetype":[
        "aat:300008699"
    ]
},
  "bbox": [],
  "geometry": {"coordinates":[-90.55,34.8833],"type":"Point"}
}