<<<<<<< HEAD
{
  "id": 2768035,
  "type": "Feature",
  "properties": {
    "tgn:hierarchy":[
        "tgn:2768035",
        "tgn:1000001",
        "tgn:7012149",
        "tgn:2001522",
        "tgn:7007709",
        "tgn:7029392"
    ],
    "tgn:id":2768035,
    "tgn:name":"Whiteoak Swamp",
    "tgn:placetype":[
        "aat:300008699"
    ]
},
  "bbox": [],
  "geometry": {"coordinates":[-78.0833,35.8],"type":"Point"}
}
=======
{"geometry":{"type":"Point","coordinates":[-78.083300,35.800000]},"type":"Feature","properties":{"hierarchy":["tgn:2768035","tgn:1000001","tgn:7012149","tgn:2001522","tgn:7007709","tgn:7029392"],"placetype":["aat:300008699"],"id":2768035,"name:xx":"Whiteoak Swamp"}}
>>>>>>> 03f74aca74312dbeaf24d7e61306dd6a786dc3d0
