{
  "id": 2045262,
  "type": "Feature",
  "properties": {
    "tgn:hierarchy":[
        "tgn:2045262",
        "tgn:1000001",
        "tgn:7012149",
        "tgn:7014589",
        "tgn:7007515",
        "tgn:7029392"
    ],
    "tgn:id":2045262,
    "tgn:name":"North Lubec",
    "tgn:placetype":[
        "aat:300008347"
    ]
},
  "bbox": [],
  "geometry": {"coordinates":[-67.0167,44.8667],"type":"Point"}
}