{
  "id": 2358374,
  "type": "Feature",
  "properties": {
    "tgn:hierarchy":[
        "tgn:2358374",
        "tgn:1000001",
        "tgn:7012149",
        "tgn:7007158",
        "tgn:7029392"
    ],
    "tgn:id":2358374,
    "tgn:name":"Grand Mesa",
    "tgn:placetype":[
        "aat:300055621"
    ]
},
  "bbox": [],
  "geometry": {"coordinates":[-107.9333,39.0667],"type":"Point"}
}