{
  "id": 7580334,
  "type": "Feature",
  "properties": {
    "tgn:hierarchy":[
        "tgn:7580334",
        "tgn:1000004",
        "tgn:1001869",
        "tgn:7000198",
        "tgn:7029392"
    ],
    "tgn:id":7580334,
    "tgn:name:en":"Shi\u0101nagar",
    "tgn:placetype":[
        "aat:300008347"
    ]
},
  "bbox": [],
  "geometry": {"coordinates":[71.766667,22.016667],"type":"Point"}
}