{
  "id": 2600324,
  "type": "Feature",
  "properties": {
    "tgn:hierarchy":[
        "tgn:2600324",
        "tgn:1000001",
        "tgn:7012149",
        "tgn:2001452",
        "tgn:7007566",
        "tgn:7029392"
    ],
    "tgn:id":2600324,
    "tgn:name":"Pueblito Spring",
    "tgn:placetype":[
        "aat:300008697"
    ]
},
  "bbox": [],
  "geometry": {"coordinates":[-107.8333,36.8167],"type":"Point"}
}