<<<<<<< HEAD
{
  "id": 7051804,
  "type": "Feature",
  "properties": {
    "tgn:hierarchy":[
        "tgn:7051804",
        "tgn:1000003",
        "tgn:7003241",
        "tgn:1000080",
        "tgn:7029392"
    ],
    "tgn:id":7051804,
    "tgn:name":"Il Monte",
    "tgn:placetype":[
        "aat:300008795"
    ]
},
  "bbox": [],
  "geometry": {"coordinates":[14.366667,41.733333],"type":"Point"}
}
=======
{"geometry":{"type":"Point","coordinates":[14.366667,41.733333]},"type":"Feature","properties":{"hierarchy":["tgn:7051804","tgn:1000003","tgn:7003241","tgn:1000080","tgn:7029392"],"placetype":["aat:300008795"],"id":7051804,"name:xx":"Il Monte"}}
>>>>>>> 03f74aca74312dbeaf24d7e61306dd6a786dc3d0
