{
  "id": 2503669,
  "type": "Feature",
  "properties": {
    "tgn:hierarchy":[
        "tgn:2503669",
        "tgn:7002659",
        "tgn:1000001",
        "tgn:7012149",
        "tgn:2000039",
        "tgn:7029392"
    ],
    "tgn:id":2503669,
    "tgn:name":"Meadow Branch",
    "tgn:placetype":[
        "aat:300008699"
    ]
},
  "bbox": [],
  "geometry": {"coordinates":[-87.3833,34.6833],"type":"Point"}
}