{
  "id": 2205560,
  "type": "Feature",
  "properties": {
    "tgn:hierarchy":[
        "tgn:2205560",
        "tgn:1000001",
        "tgn:2001418",
        "tgn:7012149",
        "tgn:7007526",
        "tgn:7029392"
    ],
    "tgn:id":2205560,
    "tgn:name":"Bull Creek Reservoir",
    "tgn:placetype":[
        "aat:300006191"
    ]
},
  "bbox": [],
  "geometry": {"coordinates":[-115.5833,38.8667],"type":"Point"}
}