{
  "id": 2562765,
  "type": "Feature",
  "properties": {
    "tgn:hierarchy":[
        "tgn:2562765",
        "tgn:1000001",
        "tgn:7016172",
        "tgn:7012149",
        "tgn:7029392"
    ],
    "tgn:id":2562765,
    "tgn:name":"Overcup Ditch",
    "tgn:placetype":[
        "aat:300006075"
    ]
},
  "bbox": [],
  "geometry": {"coordinates":[-91.2167,35.4167],"type":"Point"}
}