<<<<<<< HEAD
{
  "id": 2760413,
  "type": "Feature",
  "properties": {
    "tgn:hierarchy":[
        "tgn:2760413",
        "tgn:1000001",
        "tgn:2001797",
        "tgn:7012149",
        "tgn:7007713",
        "tgn:7029392"
    ],
    "tgn:id":2760413,
    "tgn:name":"West Fork Spotted Bear Creek",
    "tgn:placetype":[
        "aat:300008706"
    ]
},
  "bbox": [],
  "geometry": {"coordinates":[-101.7667,44.4167],"type":"Point"}
}
=======
{"geometry":{"type":"Point","coordinates":[-101.766700,44.416700]},"type":"Feature","properties":{"hierarchy":["tgn:2760413","tgn:1000001","tgn:2001797","tgn:7012149","tgn:7007713","tgn:7029392"],"placetype":["aat:300008706"],"id":2760413,"name:xx":"West Fork Spotted Bear Creek"}}
>>>>>>> 03f74aca74312dbeaf24d7e61306dd6a786dc3d0
