<<<<<<< HEAD
{
  "id": 7365467,
  "type": "Feature",
  "properties": {
    "tgn:hierarchy":[
        "tgn:7365467",
        "tgn:7005581",
        "tgn:1000001",
        "tgn:7005560",
        "tgn:7029392"
    ],
    "tgn:id":7365467,
    "tgn:name":"Fresno, Arroyo del",
    "tgn:placetype":[
        "aat:300266554",
        "aat:300008699"
    ]
},
  "bbox": [],
  "geometry": {"coordinates":[-107.916667,30.616667],"type":"Point"}
}
=======
{"geometry":{"type":"Point","coordinates":[-107.916667,30.616667]},"type":"Feature","properties":{"hierarchy":["tgn:7365467","tgn:7005581","tgn:1000001","tgn:7005560","tgn:7029392"],"placetype":["aat:300266554","aat:300008699"],"id":7365467,"name:xx":"Fresno, Arroyo del"}}
>>>>>>> 03f74aca74312dbeaf24d7e61306dd6a786dc3d0
