{
  "id": 2283453,
  "type": "Feature",
  "properties": {
    "tgn:hierarchy":[
        "tgn:2283453",
        "tgn:1000001",
        "tgn:7012149",
        "tgn:2002378",
        "tgn:7007923",
        "tgn:7029392"
    ],
    "tgn:id":2283453,
    "tgn:name":"Delores Draw",
    "tgn:placetype":[
        "aat:300008761"
    ]
},
  "bbox": [],
  "geometry": {"coordinates":[-104.0667,42.9167],"type":"Point"}
}