<<<<<<< HEAD
{
  "id": 7174495,
  "type": "Feature",
  "properties": {
    "tgn:hierarchy":[
        "tgn:7174495",
        "tgn:7000096",
        "tgn:1000003",
        "tgn:7000084",
        "tgn:7029392"
    ],
    "tgn:id":7174495,
    "tgn:name":"Gruboer Holz",
    "tgn:placetype":[
        "aat:300008863"
    ]
},
  "bbox": [],
  "geometry": {"coordinates":[12.533333,52.066667],"type":"Point"}
}
=======
{"geometry":{"type":"Point","coordinates":[12.533333,52.066667]},"type":"Feature","properties":{"hierarchy":["tgn:7174495","tgn:7000096","tgn:1000003","tgn:7000084","tgn:7029392"],"placetype":["aat:300008863"],"id":7174495,"name:xx":"Gruboer Holz"}}
>>>>>>> 03f74aca74312dbeaf24d7e61306dd6a786dc3d0
