{
  "id": 7298469,
  "type": "Feature",
  "properties": {
    "tgn:hierarchy":[
        "tgn:7298469",
        "tgn:7002810",
        "tgn:7001158",
        "tgn:1000003",
        "tgn:1000095",
        "tgn:7029392"
    ],
    "tgn:id":7298469,
    "tgn:name":"Valle de Carranza",
    "tgn:placetype":[
        "aat:300387346"
    ]
},
  "bbox": [],
  "geometry": {"coordinates":[-3.333333,43.166667],"type":"Point"}
}