{
  "id": 7390912,
  "type": "Feature",
  "properties": {
    "tgn:hierarchy":[
        "tgn:7390912",
        "tgn:7005581",
        "tgn:1000001",
        "tgn:7005560",
        "tgn:7029392"
    ],
    "tgn:id":7390912,
    "tgn:name":"Rio Escondido",
    "tgn:placetype":[
        "aat:300008347"
    ]
},
  "bbox": [],
  "geometry": {"coordinates":[-108.033333,31.116667],"type":"Point"}
}