{
  "id": 2207165,
  "type": "Feature",
  "properties": {
    "tgn:hierarchy":[
        "tgn:2207165",
        "tgn:1000001",
        "tgn:1002186",
        "tgn:7012149",
        "tgn:7007251",
        "tgn:7029392"
    ],
    "tgn:id":2207165,
    "tgn:name":"Bunje",
    "tgn:placetype":[
        "aat:300008347"
    ]
},
  "bbox": [],
  "geometry": {"coordinates":[-89.5833,38.9833],"type":"Point"}
}