{
  "id": 2688624,
  "type": "Feature",
  "properties": {
    "tgn:hierarchy":[
        "tgn:2688624",
        "tgn:1000001",
        "tgn:1002493",
        "tgn:7012149",
        "tgn:7007565",
        "tgn:7029392"
    ],
    "tgn:id":2688624,
    "tgn:name":"Spruce Run",
    "tgn:placetype":[
        "aat:300008699"
    ]
},
  "bbox": [],
  "geometry": {"coordinates":[-74.85,40.75],"type":"Point"}
}