<<<<<<< HEAD
{
  "id": 7352793,
  "type": "Feature",
  "properties": {
    "tgn:hierarchy":[
        "tgn:7352793",
        "tgn:1000001",
        "tgn:1001960",
        "tgn:7005560",
        "tgn:7029392"
    ],
    "tgn:id":7352793,
    "tgn:name":"Batacostecori",
    "tgn:placetype":[
        "aat:300387007"
    ]
},
  "bbox": [],
  "geometry": {"coordinates":[-109.683333,27.166667],"type":"Point"}
}
=======
{"geometry":{"type":"Point","coordinates":[-109.683333,27.166667]},"type":"Feature","properties":{"hierarchy":["tgn:7352793","tgn:1000001","tgn:1001960","tgn:7005560","tgn:7029392"],"placetype":["aat:300387007"],"id":7352793,"name:xx":"Batacostecori"}}
>>>>>>> 03f74aca74312dbeaf24d7e61306dd6a786dc3d0
