<<<<<<< HEAD
{
  "id": 2158132,
  "type": "Feature",
  "properties": {
    "tgn:hierarchy":[
        "tgn:2158132",
        "tgn:1000001",
        "tgn:2002135",
        "tgn:7012149",
        "tgn:7007828",
        "tgn:7029392"
    ],
    "tgn:id":2158132,
    "tgn:name":"Beaver Pond",
    "tgn:placetype":[
        "aat:300008680"
    ]
},
  "bbox": [],
  "geometry": {"coordinates":[-72.7167,44.05],"type":"Point"}
}
=======
{"geometry":{"type":"Point","coordinates":[-72.716700,44.050000]},"type":"Feature","properties":{"hierarchy":["tgn:2158132","tgn:1000001","tgn:2002135","tgn:7012149","tgn:7007828","tgn:7029392"],"placetype":["aat:300008680"],"id":2158132,"name:xx":"Beaver Pond"}}
>>>>>>> 03f74aca74312dbeaf24d7e61306dd6a786dc3d0
