{
  "id": 2158132,
  "type": "Feature",
  "properties": {
    "tgn:hierarchy":[
        "tgn:2158132",
        "tgn:1000001",
        "tgn:2002135",
        "tgn:7012149",
        "tgn:7007828",
        "tgn:7029392"
    ],
    "tgn:id":2158132,
    "tgn:name":"Beaver Pond",
    "tgn:placetype":[
        "aat:300008680"
    ]
},
  "bbox": [],
  "geometry": {"coordinates":[-72.7167,44.05],"type":"Point"}
}