<<<<<<< HEAD
{
  "id": 7367739,
  "type": "Feature",
  "properties": {
    "tgn:hierarchy":[
        "tgn:7367739",
        "tgn:1000001",
        "tgn:7005589",
        "tgn:7005560",
        "tgn:7029392"
    ],
    "tgn:id":7367739,
    "tgn:name":"El Salitre",
    "tgn:placetype":[
        "aat:300008347"
    ]
},
  "bbox": [],
  "geometry": {"coordinates":[-99.7675,24.970278],"type":"Point"}
}
=======
{"geometry":{"type":"Point","coordinates":[-99.767500,24.970278]},"type":"Feature","properties":{"hierarchy":["tgn:7367739","tgn:1000001","tgn:7005589","tgn:7005560","tgn:7029392"],"placetype":["aat:300008347"],"id":7367739,"name:xx":"El Salitre"}}
>>>>>>> 03f74aca74312dbeaf24d7e61306dd6a786dc3d0
