{
  "id": 2684070,
  "type": "Feature",
  "properties": {
    "tgn:hierarchy":[
        "tgn:2684070",
        "tgn:1000001",
        "tgn:2002106",
        "tgn:7012149",
        "tgn:7007827",
        "tgn:7029392"
    ],
    "tgn:id":2684070,
    "tgn:name":"Spencer Estates",
    "tgn:placetype":[
        "aat:300008347"
    ]
},
  "bbox": [],
  "geometry": {"coordinates":[-111.9333,41.0167],"type":"Point"}
}