{
  "id": 2210618,
  "type": "Feature",
  "properties": {
    "tgn:hierarchy":[
        "tgn:2210618",
        "tgn:1000001",
        "tgn:7012149",
        "tgn:2001205",
        "tgn:7007523",
        "tgn:7029392"
    ],
    "tgn:id":2210618,
    "tgn:name":"Buster Branch",
    "tgn:placetype":[
        "aat:300008699"
    ]
},
  "bbox": [],
  "geometry": {"coordinates":[-92.8667,39.1167],"type":"Point"}
}