{
  "id": 1129038,
  "type": "Feature",
  "properties": {
    "tgn:hierarchy":[
        "tgn:1129038",
        "tgn:1000004",
        "tgn:7029392"
    ],
    "tgn:id":1129038,
    "tgn:name":"Song Koi",
    "tgn:placetype":[
        "aat:300008707"
    ]
},
  "bbox": [],
  "geometry": {"coordinates":[106.5833,20.25],"type":"Point"}
}