{
  "id": 7282952,
  "type": "Feature",
  "properties": {
    "tgn:hierarchy":[
        "tgn:7282952",
        "tgn:1001768",
        "tgn:1000049",
        "tgn:1000002",
        "tgn:7029392"
    ],
    "tgn:id":7282952,
    "tgn:name":"Pedro Pablo, Portezuelo de",
    "tgn:placetype":[
        "aat:300259572"
    ]
},
  "bbox": [],
  "geometry": {"coordinates":[-70.183333,-32.583333],"type":"Point"}
}