{
  "id": 2614832,
  "type": "Feature",
  "properties": {
    "tgn:hierarchy":[
        "tgn:2614832",
        "tgn:1000001",
        "tgn:7012149",
        "tgn:2002264",
        "tgn:7013961",
        "tgn:7029392"
    ],
    "tgn:id":2614832,
    "tgn:name":"Renicks Valley Pit",
    "tgn:placetype":[
        "aat:300008746"
    ]
},
  "bbox": [],
  "geometry": {"coordinates":[-80.2833,38.05],"type":"Point"}
}