{
  "id": 2460177,
  "type": "Feature",
  "properties": {
    "tgn:hierarchy":[
        "tgn:2460177",
        "tgn:1000001",
        "tgn:1002221",
        "tgn:7012149",
        "tgn:7007251",
        "tgn:7029392"
    ],
    "tgn:id":2460177,
    "tgn:name":"Little Round Pond",
    "tgn:placetype":[
        "aat:300008680"
    ]
},
  "bbox": [],
  "geometry": {"coordinates":[-90.6833,39.0333],"type":"Point"}
}