{
  "id": 2479373,
  "type": "Feature",
  "properties": {
    "tgn:hierarchy":[
        "tgn:2479373",
        "tgn:1000001",
        "tgn:2001431",
        "tgn:7012149",
        "tgn:7007566",
        "tgn:7029392"
    ],
    "tgn:id":2479373,
    "tgn:name":"Laguna Pueblo Pit",
    "tgn:placetype":[
        "aat:300000390"
    ]
},
  "bbox": [],
  "geometry": {"coordinates":[-107.3833,35.0333],"type":"Point"}
}