{
  "id": 1067159,
  "type": "Feature",
  "properties": {
    "tgn:hierarchy":[
        "tgn:1067159",
        "tgn:1000004",
        "tgn:7005232",
        "tgn:1000111",
        "tgn:7029392"
    ],
    "tgn:id":1067159,
    "tgn:name":"Chencun",
    "tgn:placetype":[
        "aat:300008347"
    ]
},
  "bbox": [],
  "geometry": {"coordinates":[113.2167,22.9667],"type":"Point"}
}