{
  "id": 2288157,
  "type": "Feature",
  "properties": {
    "tgn:hierarchy":[
        "tgn:2288157",
        "tgn:1000001",
        "tgn:7012149",
        "tgn:7007920",
        "tgn:7029392"
    ],
    "tgn:id":2288157,
    "tgn:name":"Diobsud Creek",
    "tgn:placetype":[
        "aat:300008706"
    ]
},
  "bbox": [],
  "geometry": {"coordinates":[-121.5667,48.6333],"type":"Point"}
}