{
  "id": 2765770,
  "type": "Feature",
  "properties": {
    "tgn:hierarchy":[
        "tgn:2765770",
        "tgn:1000001",
        "tgn:7012149",
        "tgn:1002561",
        "tgn:7007252",
        "tgn:7029392"
    ],
    "tgn:id":2765770,
    "tgn:name":"White Ditch",
    "tgn:placetype":[
        "aat:300006075"
    ]
},
  "bbox": [],
  "geometry": {"coordinates":[-86.8167,41.7333],"type":"Point"}
}