{
  "id": 2279723,
  "type": "Feature",
  "properties": {
    "tgn:hierarchy":[
        "tgn:2279723",
        "tgn:7002659",
        "tgn:1000001",
        "tgn:7012149",
        "tgn:2000028",
        "tgn:7029392"
    ],
    "tgn:id":2279723,
    "tgn:name":"Deadwater Creek",
    "tgn:placetype":[
        "aat:300008706"
    ]
},
  "bbox": [],
  "geometry": {"coordinates":[-87.7167,33.7333],"type":"Point"}
}