{
  "id": 7269558,
  "type": "Feature",
  "properties": {
    "tgn:concordances":{
        "gn:id":"2751167"
    },
    "tgn:hierarchy":[
        "tgn:7269558",
        "tgn:1000003",
        "tgn:7003626",
        "tgn:7016845",
        "tgn:7029392"
    ],
    "tgn:id":7269558,
    "tgn:name:nl":"Marijenkampen",
    "tgn:placetype":[
        "aat:300008347"
    ]
},
  "bbox": [],
  "geometry": {"coordinates":[6.05,52.816667],"type":"Point"}
}