{
  "id": 7534250,
  "type": "Feature",
  "properties": {
    "tgn:hierarchy":[
        "tgn:7534250",
        "tgn:7001242",
        "tgn:7016833",
        "tgn:7001312",
        "tgn:7029392"
    ],
    "tgn:id":7534250,
    "tgn:name:en":"Kafr Shubr\u0101 Qall\u016bj",
    "tgn:placetype":[
        "aat:300008347"
    ]
},
  "bbox": [],
  "geometry": {"coordinates":[31.201416,30.766052],"type":"Point"}
}