{
  "id": 2737591,
  "type": "Feature",
  "properties": {
    "tgn:hierarchy":[
        "tgn:2737591",
        "tgn:1002338",
        "tgn:1000001",
        "tgn:7012149",
        "tgn:7007516",
        "tgn:7029392"
    ],
    "tgn:id":2737591,
    "tgn:name":"Tyler Creek",
    "tgn:placetype":[
        "aat:300008706"
    ]
},
  "bbox": [],
  "geometry": {"coordinates":[-76.2333,38.35],"type":"Point"}
}