{
  "id": 2146049,
  "type": "Feature",
  "properties": {
    "tgn:hierarchy":[
        "tgn:2146049",
        "tgn:1000001",
        "tgn:7012149",
        "tgn:2000974",
        "tgn:7007520",
        "tgn:7029392"
    ],
    "tgn:id":2146049,
    "tgn:name":"Ball Pond",
    "tgn:placetype":[
        "aat:300008680"
    ]
},
  "bbox": [],
  "geometry": {"coordinates":[-85.8667,44.45],"type":"Point"}
}