<<<<<<< HEAD
{
  "id": 2250606,
  "type": "Feature",
  "properties": {
    "tgn:hierarchy":[
        "tgn:2250606",
        "tgn:7006450",
        "tgn:1000001",
        "tgn:7012149",
        "tgn:2000089",
        "tgn:7029392"
    ],
    "tgn:id":2250606,
    "tgn:name":"Colorado Creek Mine",
    "tgn:placetype":[
        "aat:300000390"
    ]
},
  "bbox": [],
  "geometry": {"coordinates":[-155.9833,63.5833],"type":"Point"}
}
=======
{"geometry":{"type":"Point","coordinates":[-155.983300,63.583300]},"type":"Feature","properties":{"hierarchy":["tgn:2250606","tgn:7006450","tgn:1000001","tgn:7012149","tgn:2000089","tgn:7029392"],"placetype":["aat:300000390"],"id":2250606,"name:xx":"Colorado Creek Mine"}}
>>>>>>> 03f74aca74312dbeaf24d7e61306dd6a786dc3d0
