{
  "id": 2527612,
  "type": "Feature",
  "properties": {
    "tgn:hierarchy":[
        "tgn:2527612",
        "tgn:1000001",
        "tgn:7012149",
        "tgn:1002694",
        "tgn:7007252",
        "tgn:7029392"
    ],
    "tgn:id":2527612,
    "tgn:name":"Mount Zion Corner",
    "tgn:placetype":[
        "aat:300008347"
    ]
},
  "bbox": [],
  "geometry": {"coordinates":[-86.55,39.5167],"type":"Point"}
}