{
  "id": 2194249,
  "type": "Feature",
  "properties": {
    "tgn:hierarchy":[
        "tgn:2194249",
        "tgn:1000001",
        "tgn:7012149",
        "tgn:7007157",
        "tgn:1002863",
        "tgn:7029392"
    ],
    "tgn:id":2194249,
    "tgn:name":"Bridge Canyon",
    "tgn:placetype":[
        "aat:300008761"
    ]
},
  "bbox": [],
  "geometry": {"coordinates":[-120.7167,35.7333],"type":"Point"}
}