{
  "id": 2473104,
  "type": "Feature",
  "properties": {
    "tgn:hierarchy":[
        "tgn:2473104",
        "tgn:1000001",
        "tgn:7012149",
        "tgn:2002035",
        "tgn:7007826",
        "tgn:7029392"
    ],
    "tgn:id":2473104,
    "tgn:name":"Lowe Lake",
    "tgn:placetype":[
        "aat:300008680"
    ]
},
  "bbox": [],
  "geometry": {"coordinates":[-98.7667,28.4667],"type":"Point"}
}