{
  "id": 7107490,
  "type": "Feature",
  "properties": {
    "tgn:hierarchy":[
        "tgn:7107490",
        "tgn:1000003",
        "tgn:7003688",
        "tgn:7000084",
        "tgn:7029392"
    ],
    "tgn:id":7107490,
    "tgn:name":"Prosteich",
    "tgn:placetype":[
        "aat:300000206"
    ]
},
  "bbox": [],
  "geometry": {"coordinates":[9.95,54.566667],"type":"Point"}
}