{
  "id": 2438532,
  "type": "Feature",
  "properties": {
    "tgn:hierarchy":[
        "tgn:2438532",
        "tgn:1000001",
        "tgn:7012149",
        "tgn:2000928",
        "tgn:7007515",
        "tgn:7029392"
    ],
    "tgn:id":2438532,
    "tgn:name":"Kingsbury",
    "tgn:placetype":[
        "aat:300008347"
    ]
},
  "bbox": [],
  "geometry": {"coordinates":[-69.6333,45.1167],"type":"Point"}
}