{
  "id": 2217715,
  "type": "Feature",
  "properties": {
    "tgn:hierarchy":[
        "tgn:2217715",
        "tgn:1000001",
        "tgn:7012149",
        "tgn:2001925",
        "tgn:7007825",
        "tgn:7029392"
    ],
    "tgn:id":2217715,
    "tgn:name":"Campbell Pit",
    "tgn:placetype":[
        "aat:300008746"
    ]
},
  "bbox": [],
  "geometry": {"coordinates":[-85.75,35.5333],"type":"Point"}
}