{
  "id": 7525047,
  "type": "Feature",
  "properties": {
    "tgn:hierarchy":[
        "tgn:7525047",
        "tgn:7001242",
        "tgn:7016833",
        "tgn:1001083",
        "tgn:7029392"
    ],
    "tgn:id":7525047,
    "tgn:name:en":"Dab\u0101b, W\u0101d\u012b ad",
    "tgn:placetype":[
        "aat:300379998"
    ]
},
  "bbox": [],
  "geometry": {"coordinates":[31.45,29.833333],"type":"Point"}
}