{
  "id": 7147718,
  "type": "Feature",
  "properties": {
    "tgn:hierarchy":[
        "tgn:7147718",
        "tgn:1000003",
        "tgn:7003688",
        "tgn:7000084",
        "tgn:7029392"
    ],
    "tgn:id":7147718,
    "tgn:name":"K\u00fcckenkorb",
    "tgn:placetype":[
        "aat:300000206"
    ]
},
  "bbox": [],
  "geometry": {"coordinates":[10.05,54.45],"type":"Point"}
}