<<<<<<< HEAD
{
  "id": 2766561,
  "type": "Feature",
  "properties": {
    "tgn:hierarchy":[
        "tgn:2766561",
        "tgn:1000001",
        "tgn:2000773",
        "tgn:7012149",
        "tgn:7007255",
        "tgn:7029392"
    ],
    "tgn:id":2766561,
    "tgn:name":"White Oak Creek",
    "tgn:placetype":[
        "aat:300008706"
    ]
},
  "bbox": [],
  "geometry": {"coordinates":[-86.35,37.6667],"type":"Point"}
}
=======
{"geometry":{"type":"Point","coordinates":[-86.350000,37.666700]},"type":"Feature","properties":{"hierarchy":["tgn:2766561","tgn:1000001","tgn:2000773","tgn:7012149","tgn:7007255","tgn:7029392"],"placetype":["aat:300008706"],"id":2766561,"name:xx":"White Oak Creek"}}
>>>>>>> 03f74aca74312dbeaf24d7e61306dd6a786dc3d0
