{
  "id": 7234353,
  "type": "Feature",
  "properties": {
    "tgn:hierarchy":[
        "tgn:7234353",
        "tgn:7002715",
        "tgn:7002731",
        "tgn:1000003",
        "tgn:1000074",
        "tgn:7029392"
    ],
    "tgn:id":7234353,
    "tgn:name":"A\u00efdh\u00f3nia",
    "tgn:placetype":[
        "aat:300008057"
    ]
},
  "bbox": [],
  "geometry": {"coordinates":[23.133333,40.816667],"type":"Point"}
}