{
  "id": 7131539,
  "type": "Feature",
  "properties": {
    "tgn:hierarchy":[
        "tgn:7131539",
        "tgn:1000003",
        "tgn:7003688",
        "tgn:7000084",
        "tgn:7029392"
    ],
    "tgn:id":7131539,
    "tgn:name":"Marienkoog",
    "tgn:placetype":[
        "aat:300008347"
    ]
},
  "bbox": [],
  "geometry": {"coordinates":[8.716667,54.766667],"type":"Point"}
}