{
  "id": 2461081,
  "type": "Feature",
  "properties": {
    "tgn:hierarchy":[
        "tgn:2461081",
        "tgn:1000001",
        "tgn:7012149",
        "tgn:1002676",
        "tgn:7007240",
        "tgn:7029392"
    ],
    "tgn:id":2461081,
    "tgn:name":"Little Spanish Key",
    "tgn:placetype":[
        "aat:300008791"
    ]
},
  "bbox": [],
  "geometry": {"coordinates":[-81.3667,24.7667],"type":"Point"}
}