{
  "id": 2655444,
  "type": "Feature",
  "properties": {
    "tgn:hierarchy":[
        "tgn:2655444",
        "tgn:7002659",
        "tgn:1000001",
        "tgn:7012149",
        "tgn:2000025",
        "tgn:7029392"
    ],
    "tgn:id":2655444,
    "tgn:name":"Sharp Branch",
    "tgn:placetype":[
        "aat:300008699"
    ]
},
  "bbox": [],
  "geometry": {"coordinates":[-86.05,32.4833],"type":"Point"}
}