{
  "id": 2157258,
  "type": "Feature",
  "properties": {
    "tgn:hierarchy":[
        "tgn:2157258",
        "tgn:1000001",
        "tgn:7012149",
        "tgn:2000491",
        "tgn:7007250",
        "tgn:7029392"
    ],
    "tgn:id":2157258,
    "tgn:name":"Beaver Creek",
    "tgn:placetype":[
        "aat:300008706"
    ]
},
  "bbox": [],
  "geometry": {"coordinates":[-115.4667,47.05],"type":"Point"}
}