<<<<<<< HEAD
{
  "id": 7112564,
  "type": "Feature",
  "properties": {
    "tgn:hierarchy":[
        "tgn:7112564",
        "tgn:7003692",
        "tgn:1000003",
        "tgn:7000084",
        "tgn:7029392"
    ],
    "tgn:id":7112564,
    "tgn:name":"Rimmeldingen",
    "tgn:placetype":[
        "aat:300004792"
    ]
},
  "bbox": [],
  "geometry": {"coordinates":[9.933333,47.85],"type":"Point"}
}
=======
{"geometry":{"type":"Point","coordinates":[9.933333,47.850000]},"type":"Feature","properties":{"hierarchy":["tgn:7112564","tgn:7003692","tgn:1000003","tgn:7000084","tgn:7029392"],"placetype":["aat:300004792"],"id":7112564,"name:xx":"Rimmeldingen"}}
>>>>>>> 03f74aca74312dbeaf24d7e61306dd6a786dc3d0
