{
  "id": 7228731,
  "type": "Feature",
  "properties": {
    "tgn:hierarchy":[
        "tgn:7228731",
        "tgn:1042193",
        "tgn:7002705",
        "tgn:1000003",
        "tgn:1000074",
        "tgn:7029392"
    ],
    "tgn:id":7228731,
    "tgn:name":"Kleiso\u00fara",
    "tgn:placetype":[
        "aat:300008347"
    ]
},
  "bbox": [],
  "geometry": {"coordinates":[20.889444,39.361111],"type":"Point"}
}