{
  "id": 2446237,
  "type": "Feature",
  "properties": {
    "tgn:hierarchy":[
        "tgn:2446237",
        "tgn:1000001",
        "tgn:7012149",
        "tgn:2001721",
        "tgn:7007708",
        "tgn:7029392"
    ],
    "tgn:id":2446237,
    "tgn:name":"Lewis Branch",
    "tgn:placetype":[
        "aat:300008699"
    ]
},
  "bbox": [],
  "geometry": {"coordinates":[-118.0667,45.4833],"type":"Point"}
}