{
  "id": 7431612,
  "type": "Feature",
  "properties": {
    "tgn:hierarchy":[
        "tgn:7431612",
        "tgn:1001853",
        "tgn:1000001",
        "tgn:7005560",
        "tgn:7029392"
    ],
    "tgn:id":7431612,
    "tgn:name":"La Zemuda",
    "tgn:placetype":[
        "aat:300008347"
    ]
},
  "bbox": [],
  "geometry": {"coordinates":[-102.116667,28.133333],"type":"Point"}
}