<<<<<<< HEAD
{
  "id": 2333829,
  "type": "Feature",
  "properties": {
    "tgn:hierarchy":[
        "tgn:2333829",
        "tgn:1000001",
        "tgn:7012149",
        "tgn:2002341",
        "tgn:7007922",
        "tgn:7029392"
    ],
    "tgn:id":2333829,
    "tgn:name":"Forbes Creek",
    "tgn:placetype":[
        "aat:300008706"
    ]
},
  "bbox": [],
  "geometry": {"coordinates":[-88.3833,45.3167],"type":"Point"}
}
=======
{"geometry":{"type":"Point","coordinates":[-88.383300,45.316700]},"type":"Feature","properties":{"hierarchy":["tgn:2333829","tgn:1000001","tgn:7012149","tgn:2002341","tgn:7007922","tgn:7029392"],"placetype":["aat:300008706"],"id":2333829,"name:xx":"Forbes Creek"}}
>>>>>>> 03f74aca74312dbeaf24d7e61306dd6a786dc3d0
