{
  "id": 2363259,
  "type": "Feature",
  "properties": {
    "tgn:hierarchy":[
        "tgn:2363259",
        "tgn:1000001",
        "tgn:7012149",
        "tgn:2002179",
        "tgn:7007919",
        "tgn:7029392"
    ],
    "tgn:id":2363259,
    "tgn:name":"Green Branch",
    "tgn:placetype":[
        "aat:300008699"
    ]
},
  "bbox": [],
  "geometry": {"coordinates":[-80.1167,36.8167],"type":"Point"}
}