{
  "id": 7296083,
  "type": "Feature",
  "properties": {
    "tgn:hierarchy":[
        "tgn:7296083",
        "tgn:7002816",
        "tgn:1001647",
        "tgn:1000003",
        "tgn:1000095",
        "tgn:7029392"
    ],
    "tgn:id":7296083,
    "tgn:name":"Yezosa, Cerro",
    "tgn:placetype":[
        "aat:300008795"
    ]
},
  "bbox": [],
  "geometry": {"coordinates":[-3.666667,38.85],"type":"Point"}
}