{
  "id": 2218711,
  "type": "Feature",
  "properties": {
    "tgn:hierarchy":[
        "tgn:2218711",
        "tgn:1000001",
        "tgn:7016172",
        "tgn:7012149",
        "tgn:2000149",
        "tgn:7029392"
    ],
    "tgn:id":2218711,
    "tgn:name":"Cane Island",
    "tgn:placetype":[
        "aat:300008791"
    ]
},
  "bbox": [],
  "geometry": {"coordinates":[-92.5667,36.3333],"type":"Point"}
}