{
  "id": 2252873,
  "type": "Feature",
  "properties": {
    "tgn:hierarchy":[
        "tgn:2252873",
        "tgn:1002247",
        "tgn:1000001",
        "tgn:7012149",
        "tgn:7007516",
        "tgn:7029392"
    ],
    "tgn:id":2252873,
    "tgn:name":"Conowingo Manor",
    "tgn:placetype":[
        "aat:300008347"
    ]
},
  "bbox": [],
  "geometry": {"coordinates":[-76.15,39.6667],"type":"Point"}
}