{
  "id": 7035354,
  "type": "Feature",
  "properties": {
    "tgn:hierarchy":[
        "tgn:7035354",
        "tgn:1003488",
        "tgn:1000003",
        "tgn:7002993",
        "tgn:1000080",
        "tgn:7029392"
    ],
    "tgn:id":7035354,
    "tgn:name":"Valdestali",
    "tgn:placetype":[
        "aat:300008347"
    ]
},
  "bbox": [],
  "geometry": {"coordinates":[12.757778,46.208611],"type":"Point"}
}