{
  "id": 2628820,
  "type": "Feature",
  "properties": {
    "tgn:hierarchy":[
        "tgn:2628820",
        "tgn:1000001",
        "tgn:7012149",
        "tgn:7014510",
        "tgn:7007920",
        "tgn:7029392"
    ],
    "tgn:id":2628820,
    "tgn:name":"Rosario Beach",
    "tgn:placetype":[
        "aat:300008347"
    ]
},
  "bbox": [],
  "geometry": {"coordinates":[-122.65,48.4167],"type":"Point"}
}