{
  "id": 2421173,
  "type": "Feature",
  "properties": {
    "tgn:hierarchy":[
        "tgn:2421173",
        "tgn:1000001",
        "tgn:7012149",
        "tgn:2001288",
        "tgn:7007524",
        "tgn:7029392"
    ],
    "tgn:id":2421173,
    "tgn:name":"Jerome Rock Lakes",
    "tgn:placetype":[
        "aat:300008680"
    ]
},
  "bbox": [],
  "geometry": {"coordinates":[-111.4667,45.3833],"type":"Point"}
}