{
  "id": 2629371,
  "type": "Feature",
  "properties": {
    "tgn:hierarchy":[
        "tgn:2629371",
        "tgn:1000001",
        "tgn:1002286",
        "tgn:7012149",
        "tgn:7007710",
        "tgn:7029392"
    ],
    "tgn:id":2629371,
    "tgn:name":"Rosecrans Bog Natural Area",
    "tgn:placetype":[
        "aat:300055621"
    ]
},
  "bbox": [],
  "geometry": {"coordinates":[-77.2833,41.0667],"type":"Point"}
}