{
  "id": 2623486,
  "type": "Feature",
  "properties": {
    "tgn:hierarchy":[
        "tgn:2623486",
        "tgn:1000001",
        "tgn:7012149",
        "tgn:2000230",
        "tgn:7007158",
        "tgn:7029392"
    ],
    "tgn:id":2623486,
    "tgn:name":"Rock Creek",
    "tgn:placetype":[
        "aat:300008706"
    ]
},
  "bbox": [],
  "geometry": {"coordinates":[-107.8167,39.1167],"type":"Point"}
}