{
  "id": 7168685,
  "type": "Feature",
  "properties": {
    "tgn:hierarchy":[
        "tgn:7168685",
        "tgn:1000003",
        "tgn:7003676",
        "tgn:7000084",
        "tgn:7029392"
    ],
    "tgn:id":7168685,
    "tgn:name":"Hebelermeer",
    "tgn:placetype":[
        "aat:300008347"
    ]
},
  "bbox": [],
  "geometry": {"coordinates":[7.083333,52.733333],"type":"Point"}
}