{
  "id": 1120490,
  "type": "Feature",
  "properties": {
    "tgn:hierarchy":[
        "tgn:1120490",
        "tgn:1000003",
        "tgn:7003677",
        "tgn:7000084",
        "tgn:7029392"
    ],
    "tgn:id":1120490,
    "tgn:name":"Sorpe Staubecken",
    "tgn:placetype":[
        "aat:300006191"
    ]
},
  "bbox": [],
  "geometry": {"coordinates":[7.95,51.333333],"type":"Point"}
}