{
  "id": 2158276,
  "type": "Feature",
  "properties": {
    "tgn:hierarchy":[
        "tgn:2158276",
        "tgn:1000001",
        "tgn:7016172",
        "tgn:7012149",
        "tgn:7029392"
    ],
    "tgn:id":2158276,
    "tgn:name":"Beaver Slough",
    "tgn:placetype":[
        "aat:300008699"
    ]
},
  "bbox": [],
  "geometry": {"coordinates":[-93.2833,33.8833],"type":"Point"}
}