{
  "id": 7498918,
  "type": "Feature",
  "properties": {
    "tgn:hierarchy":[
        "tgn:7498918",
        "tgn:1000004",
        "tgn:1000959",
        "tgn:1000141",
        "tgn:7029392"
    ],
    "tgn:id":7498918,
    "tgn:name":"Wacuo",
    "tgn:placetype":[
        "aat:300008347"
    ]
},
  "bbox": [],
  "geometry": {"coordinates":[121.588328,25.107779],"type":"Point"}
}