{
  "id": 7478085,
  "type": "Feature",
  "properties": {
    "tgn:hierarchy":[
        "tgn:7478085",
        "tgn:1000004",
        "tgn:7467799",
        "tgn:1000141",
        "tgn:7029392"
    ],
    "tgn:id":7478085,
    "tgn:name":"Yuchinei",
    "tgn:placetype":[
        "aat:300008347"
    ]
},
  "bbox": [],
  "geometry": {"coordinates":[120.603768,23.933062],"type":"Point"}
}