{
  "id": 7583184,
  "type": "Feature",
  "properties": {
    "tgn:hierarchy":[
        "tgn:7583184",
        "tgn:1000004",
        "tgn:7000198",
        "tgn:7016788",
        "tgn:7029392"
    ],
    "tgn:id":7583184,
    "tgn:name:en":"R\u0101mdev Temple",
    "tgn:placetype":[
        "aat:300007595"
    ]
},
  "bbox": [],
  "geometry": {"coordinates":[72.774388,27.547042],"type":"Point"}
}