{
  "id": 1062789,
  "type": "Feature",
  "properties": {
    "tgn:hierarchy":[
        "tgn:1062789",
        "tgn:1000403",
        "tgn:1000003",
        "tgn:1000097",
        "tgn:7029392"
    ],
    "tgn:id":1062789,
    "tgn:name":"B\u00e4ckehagen",
    "tgn:placetype":[
        "aat:300008347"
    ]
},
  "bbox": [],
  "geometry": {"coordinates":[15.5667,60.65],"type":"Point"}
}