{
  "id": 7436896,
  "type": "Feature",
  "properties": {
    "tgn:hierarchy":[
        "tgn:7436896",
        "tgn:1001853",
        "tgn:1000001",
        "tgn:7005560",
        "tgn:7029392"
    ],
    "tgn:id":7436896,
    "tgn:name":"Tarabilla, Picacho de la",
    "tgn:placetype":[
        "aat:300008798"
    ]
},
  "bbox": [],
  "geometry": {"coordinates":[-101.65,25.016667],"type":"Point"}
}