<<<<<<< HEAD
{
  "id": 7477073,
  "type": "Feature",
  "properties": {
    "tgn:hierarchy":[
        "tgn:7477073",
        "tgn:1000004",
        "tgn:7004300",
        "tgn:1000141",
        "tgn:7029392"
    ],
    "tgn:id":7477073,
    "tgn:name":"Zhushi Miao",
    "tgn:placetype":[
        "aat:300007595"
    ]
},
  "bbox": [],
  "geometry": {"coordinates":[119.597979,23.533783],"type":"Point"}
}
=======
{"geometry":{"type":"Point","coordinates":[119.597979,23.533783]},"type":"Feature","properties":{"hierarchy":["tgn:7477073","tgn:1000004","tgn:7004300","tgn:1000141","tgn:7029392"],"placetype":["aat:300007595"],"id":7477073,"name:xx":"Zhushi Miao"}}
>>>>>>> 03f74aca74312dbeaf24d7e61306dd6a786dc3d0
