{
  "id": 7477073,
  "type": "Feature",
  "properties": {
    "tgn:hierarchy":[
        "tgn:7477073",
        "tgn:1000004",
        "tgn:7004300",
        "tgn:1000141",
        "tgn:7029392"
    ],
    "tgn:id":7477073,
    "tgn:name":"Zhushi Miao",
    "tgn:placetype":[
        "aat:300007595"
    ]
},
  "bbox": [],
  "geometry": {"coordinates":[119.597979,23.533783],"type":"Point"}
}