{
  "id": 2000026,
  "type": "Feature",
  "properties": {
    "tgn:hierarchy":[
        "tgn:2000026",
        "tgn:7002659",
        "tgn:1000001",
        "tgn:7012149",
        "tgn:7029392"
    ],
    "tgn:id":2000026,
    "tgn:name":"Escambia",
    "tgn:placetype":[
        "aat:300387145",
        "aat:300000771"
    ]
},
  "bbox": [],
  "geometry": {"coordinates":[-87.15,31.15],"type":"Point"}
}