{
  "id": 7558110,
  "type": "Feature",
  "properties": {
    "tgn:hierarchy":[
        "tgn:7558110",
        "tgn:1000004",
        "tgn:7000198",
        "tgn:7016788",
        "tgn:7029392"
    ],
    "tgn:id":7558110,
    "tgn:name:en":"S\u0101ng\u0101ner",
    "tgn:placetype":[
        "aat:300008347"
    ]
},
  "bbox": [],
  "geometry": {"coordinates":[75.783333,26.816667],"type":"Point"}
}