{
  "id": 2659542,
  "type": "Feature",
  "properties": {
    "tgn:hierarchy":[
        "tgn:2659542",
        "tgn:1000001",
        "tgn:7012149",
        "tgn:2001888",
        "tgn:7007825",
        "tgn:7029392"
    ],
    "tgn:id":2659542,
    "tgn:name":"Shingle Hollow",
    "tgn:placetype":[
        "aat:300008761"
    ]
},
  "bbox": [],
  "geometry": {"coordinates":[-86.5667,35.0833],"type":"Point"}
}