{
  "id": 7020331,
  "type": "Feature",
  "properties": {
    "tgn:hierarchy":[
        "tgn:7020331",
        "tgn:1000001",
        "tgn:7012149",
        "tgn:2000853",
        "tgn:7007255",
        "tgn:7029392"
    ],
    "tgn:id":7020331,
    "tgn:name":"Bear Branch",
    "tgn:placetype":[
        "aat:300008699"
    ]
},
  "bbox": [],
  "geometry": {"coordinates":[-83.5167,37.75],"type":"Point"}
}