<<<<<<< HEAD
{
  "id": 7020331,
  "type": "Feature",
  "properties": {
    "tgn:hierarchy":[
        "tgn:7020331",
        "tgn:1000001",
        "tgn:7012149",
        "tgn:2000853",
        "tgn:7007255",
        "tgn:7029392"
    ],
    "tgn:id":7020331,
    "tgn:name":"Bear Branch",
    "tgn:placetype":[
        "aat:300008699"
    ]
},
  "bbox": [],
  "geometry": {"coordinates":[-83.5167,37.75],"type":"Point"}
}
=======
{"geometry":{"type":"Point","coordinates":[-83.516700,37.750000]},"type":"Feature","properties":{"hierarchy":["tgn:7020331","tgn:1000001","tgn:7012149","tgn:2000853","tgn:7007255","tgn:7029392"],"placetype":["aat:300008699"],"id":7020331,"name:xx":"Bear Branch"}}
>>>>>>> 03f74aca74312dbeaf24d7e61306dd6a786dc3d0
