{
  "id": 7587475,
  "type": "Feature",
  "properties": {
    "tgn:hierarchy":[
        "tgn:7587475",
        "tgn:1000004",
        "tgn:7000198",
        "tgn:7000799",
        "tgn:7029392"
    ],
    "tgn:id":7587475,
    "tgn:name:en":"B\u0101gh Chandpura",
    "tgn:placetype":[
        "aat:300008347"
    ]
},
  "bbox": [],
  "geometry": {"coordinates":[74.888114,34.157498],"type":"Point"}
}