{
  "id": 1107877,
  "type": "Feature",
  "properties": {
    "tgn:hierarchy":[
        "tgn:1107877",
        "tgn:7000490",
        "tgn:1000006",
        "tgn:7001828",
        "tgn:7029392"
    ],
    "tgn:id":1107877,
    "tgn:name":"Birling",
    "tgn:placetype":[
        "aat:300008777"
    ]
},
  "bbox": [],
  "geometry": {"coordinates":[150.7167,-33.95],"type":"Point"}
}