{
  "id": 2784293,
  "type": "Feature",
  "properties": {
    "tgn:hierarchy":[
        "tgn:2784293",
        "tgn:1000001",
        "tgn:7012149",
        "tgn:1002350",
        "tgn:7007157",
        "tgn:7029392"
    ],
    "tgn:id":2784293,
    "tgn:name":"Yankee John Creek",
    "tgn:placetype":[
        "aat:300008706"
    ]
},
  "bbox": [],
  "geometry": {"coordinates":[-120.6833,38.8167],"type":"Point"}
}