{
  "id": 2308462,
  "type": "Feature",
  "properties": {
    "tgn:hierarchy":[
        "tgn:2308462",
        "tgn:1000001",
        "tgn:7012149",
        "tgn:7007158",
        "tgn:2000246",
        "tgn:7029392"
    ],
    "tgn:id":2308462,
    "tgn:name":"East Middle Creek",
    "tgn:placetype":[
        "aat:300008706"
    ]
},
  "bbox": [],
  "geometry": {"coordinates":[-106.2167,38.3167],"type":"Point"}
}