<<<<<<< HEAD
{
  "id": 7050080,
  "type": "Feature",
  "properties": {
    "tgn:hierarchy":[
        "tgn:7050080",
        "tgn:1000003",
        "tgn:7003122",
        "tgn:1000080",
        "tgn:7029392"
    ],
    "tgn:id":7050080,
    "tgn:name":"Lazzaretto",
    "tgn:placetype":[
        "aat:300008791"
    ]
},
  "bbox": [],
  "geometry": {"coordinates":[12.483333,38.0],"type":"Point"}
}
=======
{"geometry":{"type":"Point","coordinates":[12.483333,38.000000]},"type":"Feature","properties":{"hierarchy":["tgn:7050080","tgn:1000003","tgn:7003122","tgn:1000080","tgn:7029392"],"placetype":["aat:300008791"],"id":7050080,"name:xx":"Lazzaretto"}}
>>>>>>> 03f74aca74312dbeaf24d7e61306dd6a786dc3d0
