{
  "id": 2486416,
  "type": "Feature",
  "properties": {
    "tgn:hierarchy":[
        "tgn:2486416",
        "tgn:1000001",
        "tgn:7016172",
        "tgn:7012149",
        "tgn:2000126",
        "tgn:7029392"
    ],
    "tgn:id":2486416,
    "tgn:name":"Leavits",
    "tgn:placetype":[
        "aat:300008347"
    ]
},
  "bbox": [],
  "geometry": {"coordinates":[-91.45,33.5167],"type":"Point"}
}