<<<<<<< HEAD
{
  "id": 2761196,
  "type": "Feature",
  "properties": {
    "tgn:hierarchy":[
        "tgn:2761196",
        "tgn:1000001",
        "tgn:7012149",
        "tgn:7007523",
        "tgn:7029392"
    ],
    "tgn:id":2761196,
    "tgn:name":"West Lick Creek",
    "tgn:placetype":[
        "aat:300008706"
    ]
},
  "bbox": [],
  "geometry": {"coordinates":[-91.7,39.2167],"type":"Point"}
}
=======
{"geometry":{"type":"Point","coordinates":[-91.700000,39.216700]},"type":"Feature","properties":{"hierarchy":["tgn:2761196","tgn:1000001","tgn:7012149","tgn:7007523","tgn:7029392"],"placetype":["aat:300008706"],"id":2761196,"name:xx":"West Lick Creek"}}
>>>>>>> 03f74aca74312dbeaf24d7e61306dd6a786dc3d0
