{
  "id": 2006516,
  "type": "Feature",
  "properties": {
    "tgn:hierarchy":[
        "tgn:2006516",
        "tgn:1000001",
        "tgn:7006451",
        "tgn:2000091",
        "tgn:7012149",
        "tgn:7029392"
    ],
    "tgn:id":2006516,
    "tgn:name":"Apache",
    "tgn:placetype":[
        "aat:300008347",
        "aat:300387210"
    ]
},
  "bbox": [],
  "geometry": {"coordinates":[-109.1167,31.6833],"type":"Point"}
}