{
  "id": 2137664,
  "type": "Feature",
  "properties": {
    "tgn:hierarchy":[
        "tgn:2137664",
        "tgn:1002541",
        "tgn:1000001",
        "tgn:7012149",
        "tgn:7007711",
        "tgn:7029392"
    ],
    "tgn:id":2137664,
    "tgn:name":"Arnold Pond",
    "tgn:placetype":[
        "aat:300008680"
    ]
},
  "bbox": [],
  "geometry": {"coordinates":[-71.7333,41.65],"type":"Point"}
}