{
  "id": 2035406,
  "type": "Feature",
  "properties": {
    "tgn:hierarchy":[
        "tgn:2035406",
        "tgn:1000001",
        "tgn:7012149",
        "tgn:2000626",
        "tgn:7007253",
        "tgn:7029392"
    ],
    "tgn:id":2035406,
    "tgn:name":"Otranto",
    "tgn:placetype":[
        "aat:300008347"
    ]
},
  "bbox": [],
  "geometry": {"coordinates":[-92.9833,43.45],"type":"Point"}
}