<<<<<<< HEAD
{
  "id": 2338164,
  "type": "Feature",
  "properties": {
    "tgn:hierarchy":[
        "tgn:2338164",
        "tgn:1000001",
        "tgn:7012149",
        "tgn:2000973",
        "tgn:7007520",
        "tgn:7029392"
    ],
    "tgn:id":2338164,
    "tgn:name":"Fox Point",
    "tgn:placetype":[
        "aat:300008850"
    ]
},
  "bbox": [],
  "geometry": {"coordinates":[-85.6167,46.0],"type":"Point"}
}
=======
{"geometry":{"type":"Point","coordinates":[-85.616700,46.000000]},"type":"Feature","properties":{"hierarchy":["tgn:2338164","tgn:1000001","tgn:7012149","tgn:2000973","tgn:7007520","tgn:7029392"],"placetype":["aat:300008850"],"id":2338164,"name:xx":"Fox Point"}}
>>>>>>> 03f74aca74312dbeaf24d7e61306dd6a786dc3d0
