<<<<<<< HEAD
{
  "id": 7475861,
  "type": "Feature",
  "properties": {
    "tgn:hierarchy":[
        "tgn:7475861",
        "tgn:7488858",
        "tgn:1000004",
        "tgn:1000141",
        "tgn:7029392"
    ],
    "tgn:id":7475861,
    "tgn:name":"Dingcaonan",
    "tgn:placetype":[
        "aat:300008347"
    ]
},
  "bbox": [],
  "geometry": {"coordinates":[120.907672,23.939191],"type":"Point"}
}
=======
{"geometry":{"type":"Point","coordinates":[120.907672,23.939191]},"type":"Feature","properties":{"hierarchy":["tgn:7475861","tgn:7488858","tgn:1000004","tgn:1000141","tgn:7029392"],"placetype":["aat:300008347"],"id":7475861,"name:xx":"Dingcaonan"}}
>>>>>>> 03f74aca74312dbeaf24d7e61306dd6a786dc3d0
