{
  "id": 7152543,
  "type": "Feature",
  "properties": {
    "tgn:hierarchy":[
        "tgn:7152543",
        "tgn:7003669",
        "tgn:1000003",
        "tgn:7000084",
        "tgn:7029392"
    ],
    "tgn:id":7152543,
    "tgn:name":"Kaltenreuth",
    "tgn:placetype":[
        "aat:300008347"
    ]
},
  "bbox": [],
  "geometry": {"coordinates":[11.266667,50.133333],"type":"Point"}
}