<<<<<<< HEAD
{
  "id": 2403928,
  "type": "Feature",
  "properties": {
    "tgn:hierarchy":[
        "tgn:2403928",
        "tgn:1000001",
        "tgn:7012149",
        "tgn:1002779",
        "tgn:7007710",
        "tgn:7029392"
    ],
    "tgn:id":2403928,
    "tgn:name":"Howe Run",
    "tgn:placetype":[
        "aat:300008699"
    ]
},
  "bbox": [],
  "geometry": {"coordinates":[-77.1,40.5],"type":"Point"}
}
=======
{"geometry":{"type":"Point","coordinates":[-77.100000,40.500000]},"type":"Feature","properties":{"hierarchy":["tgn:2403928","tgn:1000001","tgn:7012149","tgn:1002779","tgn:7007710","tgn:7029392"],"placetype":["aat:300008699"],"id":2403928,"name:xx":"Howe Run"}}
>>>>>>> 03f74aca74312dbeaf24d7e61306dd6a786dc3d0
