{
  "id": 2590093,
  "type": "Feature",
  "properties": {
    "tgn:hierarchy":[
        "tgn:2590093",
        "tgn:1000001",
        "tgn:2001581",
        "tgn:7012149",
        "tgn:7007705",
        "tgn:7029392"
    ],
    "tgn:id":2590093,
    "tgn:name":"Poison Lake",
    "tgn:placetype":[
        "aat:300008680"
    ]
},
  "bbox": [],
  "geometry": {"coordinates":[-100.5667,48.2333],"type":"Point"}
}