<<<<<<< HEAD
{
  "id": 2402344,
  "type": "Feature",
  "properties": {
    "tgn:hierarchy":[
        "tgn:2402344",
        "tgn:1000001",
        "tgn:7012149",
        "tgn:2001753",
        "tgn:7007712",
        "tgn:7029392"
    ],
    "tgn:id":2402344,
    "tgn:name":"Horton Creek",
    "tgn:placetype":[
        "aat:300008706"
    ]
},
  "bbox": [],
  "geometry": {"coordinates":[-80.6167,34.5833],"type":"Point"}
}
=======
{"geometry":{"type":"Point","coordinates":[-80.616700,34.583300]},"type":"Feature","properties":{"hierarchy":["tgn:2402344","tgn:1000001","tgn:7012149","tgn:2001753","tgn:7007712","tgn:7029392"],"placetype":["aat:300008706"],"id":2402344,"name:xx":"Horton Creek"}}
>>>>>>> 03f74aca74312dbeaf24d7e61306dd6a786dc3d0
