{
  "id": 2416609,
  "type": "Feature",
  "properties": {
    "tgn:hierarchy":[
        "tgn:2416609",
        "tgn:1000001",
        "tgn:2001746",
        "tgn:7012149",
        "tgn:7007712",
        "tgn:7029392"
    ],
    "tgn:id":2416609,
    "tgn:name":"Jack Hill",
    "tgn:placetype":[
        "aat:300266640"
    ]
},
  "bbox": [],
  "geometry": {"coordinates":[-79.5167,33.2667],"type":"Point"}
}