{
  "id": 2031765,
  "type": "Feature",
  "properties": {
    "tgn:hierarchy":[
        "tgn:2031765",
        "tgn:1000001",
        "tgn:7012149",
        "tgn:1002370",
        "tgn:7007252",
        "tgn:7029392"
    ],
    "tgn:id":2031765,
    "tgn:name":"Everton",
    "tgn:placetype":[
        "aat:300008347"
    ]
},
  "bbox": [],
  "geometry": {"coordinates":[-85.0833,39.55],"type":"Point"}
}