{
  "id": 7515036,
  "type": "Feature",
  "properties": {
    "tgn:hierarchy":[
        "tgn:7515036",
        "tgn:7520092",
        "tgn:1008380",
        "tgn:1000226",
        "tgn:1000006",
        "tgn:7029392"
    ],
    "tgn:id":7515036,
    "tgn:name:en":"Cape Runaway",
    "tgn:placetype":[
        "aat:300008347"
    ]
},
  "bbox": [],
  "geometry": {"coordinates":[178.016667,-37.566667],"type":"Point"}
}