{
  "id": 2076761,
  "type": "Feature",
  "properties": {
    "tgn:hierarchy":[
        "tgn:2076761",
        "tgn:1000001",
        "tgn:7012149",
        "tgn:2001532",
        "tgn:7007709",
        "tgn:7029392"
    ],
    "tgn:id":2076761,
    "tgn:name":"Staley",
    "tgn:placetype":[
        "aat:300008347"
    ]
},
  "bbox": [],
  "geometry": {"coordinates":[-79.55,35.7833],"type":"Point"}
}