{
  "id": 1112780,
  "type": "Feature",
  "properties": {
    "tgn:hierarchy":[
        "tgn:1112780",
        "tgn:7006247",
        "tgn:1000047",
        "tgn:7002456",
        "tgn:1000002",
        "tgn:7029392"
    ],
    "tgn:id":1112780,
    "tgn:name":"Caxiuana, Ba\u00eda de",
    "tgn:placetype":[
        "aat:300132316"
    ]
},
  "bbox": [],
  "geometry": {"coordinates":[-51.3333,-1.75],"type":"Point"}
}