{
  "id": 7228163,
  "type": "Feature",
  "properties": {
    "tgn:hierarchy":[
        "tgn:7228163",
        "tgn:7002681",
        "tgn:7001395",
        "tgn:1000003",
        "tgn:1000074",
        "tgn:7029392"
    ],
    "tgn:id":7228163,
    "tgn:name":"Gor\u00e9mi, \u00c1kra",
    "tgn:placetype":[
        "aat:300008850"
    ]
},
  "bbox": [],
  "geometry": {"coordinates":[24.716667,37.866667],"type":"Point"}
}