<<<<<<< HEAD
{
  "id": 2153536,
  "type": "Feature",
  "properties": {
    "tgn:hierarchy":[
        "tgn:2153536",
        "tgn:1000001",
        "tgn:2000271",
        "tgn:7012149",
        "tgn:7007240",
        "tgn:7029392"
    ],
    "tgn:id":2153536,
    "tgn:name":"Bear Bay",
    "tgn:placetype":[
        "aat:300008905"
    ]
},
  "bbox": [],
  "geometry": {"coordinates":[-82.75,30.5],"type":"Point"}
}
=======
{"geometry":{"type":"Point","coordinates":[-82.750000,30.500000]},"type":"Feature","properties":{"hierarchy":["tgn:2153536","tgn:1000001","tgn:2000271","tgn:7012149","tgn:7007240","tgn:7029392"],"placetype":["aat:300008905"],"id":2153536,"name:xx":"Bear Bay"}}
>>>>>>> 03f74aca74312dbeaf24d7e61306dd6a786dc3d0
