{
  "id": 2779741,
  "type": "Feature",
  "properties": {
    "tgn:hierarchy":[
        "tgn:2779741",
        "tgn:1000001",
        "tgn:1002273",
        "tgn:7012149",
        "tgn:7007252",
        "tgn:7029392"
    ],
    "tgn:id":2779741,
    "tgn:name":"Wolf Run",
    "tgn:placetype":[
        "aat:300008699"
    ]
},
  "bbox": [],
  "geometry": {"coordinates":[-85.7833,38.55],"type":"Point"}
}