{
  "id": 2748249,
  "type": "Feature",
  "properties": {
    "tgn:hierarchy":[
        "tgn:2748249",
        "tgn:1000001",
        "tgn:2001427",
        "tgn:7012149",
        "tgn:7007564",
        "tgn:7029392"
    ],
    "tgn:id":2748249,
    "tgn:name":"Walker Brook",
    "tgn:placetype":[
        "aat:300008699"
    ]
},
  "bbox": [],
  "geometry": {"coordinates":[-72.3333,43.4167],"type":"Point"}
}