{
  "id": 2074209,
  "type": "Feature",
  "properties": {
    "tgn:hierarchy":[
        "tgn:2074209",
        "tgn:1000001",
        "tgn:2001479",
        "tgn:7012149",
        "tgn:7007709",
        "tgn:7029392"
    ],
    "tgn:id":2074209,
    "tgn:name":"Cooksville",
    "tgn:placetype":[
        "aat:300008347",
        "aat:300387210"
    ]
},
  "bbox": [],
  "geometry": {"coordinates":[-81.4667,35.5833],"type":"Point"}
}