<<<<<<< HEAD
{
  "id": 7053980,
  "type": "Feature",
  "properties": {
    "tgn:hierarchy":[
        "tgn:7053980",
        "tgn:7003166",
        "tgn:1000003",
        "tgn:7009760",
        "tgn:1000080",
        "tgn:7029392"
    ],
    "tgn:id":7053980,
    "tgn:name":"Montecatini",
    "tgn:placetype":[
        "aat:300008347"
    ]
},
  "bbox": [],
  "geometry": {"coordinates":[10.75,43.383333],"type":"Point"}
}
=======
{"geometry":{"type":"Point","coordinates":[10.750000,43.383333]},"type":"Feature","properties":{"hierarchy":["tgn:7053980","tgn:7003166","tgn:1000003","tgn:7009760","tgn:1000080","tgn:7029392"],"placetype":["aat:300008347"],"id":7053980,"name:xx":"Montecatini"}}
>>>>>>> 03f74aca74312dbeaf24d7e61306dd6a786dc3d0
