{
  "id": 7265821,
  "type": "Feature",
  "properties": {
    "tgn:concordances":{
        "gn:id":"2752670"
    },
    "tgn:hierarchy":[
        "tgn:7265821",
        "tgn:1000003",
        "tgn:7003613",
        "tgn:7016845",
        "tgn:7029392"
    ],
    "tgn:id":7265821,
    "tgn:name:nl":"Klein-Ulsda",
    "tgn:placetype":[
        "aat:300008347"
    ]
},
  "bbox": [],
  "geometry": {"coordinates":[7.15,53.15],"type":"Point"}
}