{
  "id": 7515936,
  "type": "Feature",
  "properties": {
    "tgn:hierarchy":[
        "tgn:7515936",
        "tgn:1008380",
        "tgn:7000507",
        "tgn:1000226",
        "tgn:1000006",
        "tgn:7029392"
    ],
    "tgn:id":7515936,
    "tgn:name:en":"Omahu Stream",
    "tgn:placetype":[
        "aat:300008699"
    ]
},
  "bbox": [],
  "geometry": {"coordinates":[173.883333,-35.633333],"type":"Point"}
}