{
  "id": 2377991,
  "type": "Feature",
  "properties": {
    "tgn:hierarchy":[
        "tgn:2377991",
        "tgn:1000001",
        "tgn:2001429",
        "tgn:7012149",
        "tgn:7007566",
        "tgn:7029392"
    ],
    "tgn:id":2377991,
    "tgn:name":"Harris Canyon",
    "tgn:placetype":[
        "aat:300008761"
    ]
},
  "bbox": [],
  "geometry": {"coordinates":[-108.6167,34.0667],"type":"Point"}
}