{
  "id": 2163633,
  "type": "Feature",
  "properties": {
    "tgn:hierarchy":[
        "tgn:2163633",
        "tgn:1000001",
        "tgn:7012149",
        "tgn:1002354",
        "tgn:7007255",
        "tgn:7029392"
    ],
    "tgn:id":2163633,
    "tgn:name":"Bentley Branch",
    "tgn:placetype":[
        "aat:300008699"
    ]
},
  "bbox": [],
  "geometry": {"coordinates":[-83.0667,38.05],"type":"Point"}
}