{
  "id": 2245619,
  "type": "Feature",
  "properties": {
    "tgn:hierarchy":[
        "tgn:2245619",
        "tgn:1000001",
        "tgn:2001418",
        "tgn:7012149",
        "tgn:7007526",
        "tgn:7029392"
    ],
    "tgn:id":2245619,
    "tgn:name":"Coal Burner Spring",
    "tgn:placetype":[
        "aat:300008697"
    ]
},
  "bbox": [],
  "geometry": {"coordinates":[-116.3667,39.0667],"type":"Point"}
}