{
  "id": 2171896,
  "type": "Feature",
  "properties": {
    "tgn:hierarchy":[
        "tgn:2171896",
        "tgn:1000001",
        "tgn:7012149",
        "tgn:2000471",
        "tgn:7007250",
        "tgn:7029392"
    ],
    "tgn:id":2171896,
    "tgn:name":"Big Water Hole",
    "tgn:placetype":[
        "aat:300132316"
    ]
},
  "bbox": [],
  "geometry": {"coordinates":[-115.1333,43.1167],"type":"Point"}
}