{
  "id": 7236516,
  "type": "Feature",
  "properties": {
    "tgn:hierarchy":[
        "tgn:7236516",
        "tgn:7002707",
        "tgn:7002705",
        "tgn:1000003",
        "tgn:1000074",
        "tgn:7029392"
    ],
    "tgn:id":7236516,
    "tgn:name":"\u00c1gios Min\u00e1s",
    "tgn:placetype":[
        "aat:300008347"
    ]
},
  "bbox": [],
  "geometry": {"coordinates":[20.669167,39.946667],"type":"Point"}
}