{
  "id": 7323390,
  "type": "Feature",
  "properties": {
    "tgn:hierarchy":[
        "tgn:7323390",
        "tgn:7008911",
        "tgn:1000003",
        "tgn:7002763",
        "tgn:1000095",
        "tgn:7029392"
    ],
    "tgn:id":7323390,
    "tgn:name":"R\u00edocabo",
    "tgn:placetype":[
        "aat:300008347"
    ]
},
  "bbox": [],
  "geometry": {"coordinates":[-6.816667,43.466667],"type":"Point"}
}