{
  "id": 7285110,
  "type": "Feature",
  "properties": {
    "tgn:hierarchy":[
        "tgn:7285110",
        "tgn:1001657",
        "tgn:1000049",
        "tgn:1000002",
        "tgn:7029392"
    ],
    "tgn:id":7285110,
    "tgn:name":"Polcura, Quebrada",
    "tgn:placetype":[
        "aat:300008699"
    ]
},
  "bbox": [],
  "geometry": {"coordinates":[-70.683333,-31.466667],"type":"Point"}
}