{
  "id": 7548845,
  "type": "Feature",
  "properties": {
    "tgn:hierarchy":[
        "tgn:7548845",
        "tgn:1000004",
        "tgn:7000198",
        "tgn:7000799",
        "tgn:7029392"
    ],
    "tgn:id":7548845,
    "tgn:name:en":"Chishot",
    "tgn:placetype":[
        "aat:300008347"
    ]
},
  "bbox": [],
  "geometry": {"coordinates":[76.276662,33.376888],"type":"Point"}
}