{
  "id": 7325934,
  "type": "Feature",
  "properties": {
    "tgn:hierarchy":[
        "tgn:7325934",
        "tgn:7002808",
        "tgn:7030216",
        "tgn:1000003",
        "tgn:1000095",
        "tgn:7029392"
    ],
    "tgn:id":7325934,
    "tgn:name":"San Juli\u00e1n de Cerdanyola",
    "tgn:placetype":[
        "aat:300008347"
    ]
},
  "bbox": [],
  "geometry": {"coordinates":[1.892209,42.223417],"type":"Point"}
}