{
  "id": 2467066,
  "type": "Feature",
  "properties": {
    "tgn:hierarchy":[
        "tgn:2467066",
        "tgn:1000001",
        "tgn:7012149",
        "tgn:2000354",
        "tgn:7007248",
        "tgn:7029392"
    ],
    "tgn:id":2467066,
    "tgn:name":"Long Creek",
    "tgn:placetype":[
        "aat:300008706"
    ]
},
  "bbox": [],
  "geometry": {"coordinates":[-81.5167,31.1167],"type":"Point"}
}