{
  "id": 7148409,
  "type": "Feature",
  "properties": {
    "tgn:hierarchy":[
        "tgn:7148409",
        "tgn:1000003",
        "tgn:7003676",
        "tgn:7000084",
        "tgn:7029392"
    ],
    "tgn:id":7148409,
    "tgn:name":"Krummes Tief",
    "tgn:placetype":[
        "aat:300008699"
    ]
},
  "bbox": [],
  "geometry": {"coordinates":[7.416667,53.35],"type":"Point"}
}