{
  "id": 2660501,
  "type": "Feature",
  "properties": {
    "tgn:hierarchy":[
        "tgn:2660501",
        "tgn:1000001",
        "tgn:7012149",
        "tgn:1002671",
        "tgn:7007523",
        "tgn:7029392"
    ],
    "tgn:id":2660501,
    "tgn:name":"Shoestring Hollow",
    "tgn:placetype":[
        "aat:300008761"
    ]
},
  "bbox": [],
  "geometry": {"coordinates":[-92.3833,38.2333],"type":"Point"}
}