{
  "id": 2731489,
  "type": "Feature",
  "properties": {
    "tgn:hierarchy":[
        "tgn:2731489",
        "tgn:1000001",
        "tgn:7012149",
        "tgn:7007157",
        "tgn:1002956",
        "tgn:7029392"
    ],
    "tgn:id":2731489,
    "tgn:name":"Tulainyo Lake",
    "tgn:placetype":[
        "aat:300008680"
    ]
},
  "bbox": [],
  "geometry": {"coordinates":[-118.2667,36.5833],"type":"Point"}
}