{
  "id": 1049854,
  "type": "Feature",
  "properties": {
    "tgn:hierarchy":[
        "tgn:1049854",
        "tgn:1000882",
        "tgn:1000003",
        "tgn:1000090",
        "tgn:7029392"
    ],
    "tgn:id":1049854,
    "tgn:name":"Odivelas",
    "tgn:placetype":[
        "aat:300008347"
    ]
},
  "bbox": [],
  "geometry": {"coordinates":[-9.187,38.168],"type":"Point"}
}