{
  "id": 2281988,
  "type": "Feature",
  "properties": {
    "tgn:hierarchy":[
        "tgn:2281988",
        "tgn:1000001",
        "tgn:7006451",
        "tgn:7012149",
        "tgn:2000097",
        "tgn:7029392"
    ],
    "tgn:id":2281988,
    "tgn:name":"Deer Hill",
    "tgn:placetype":[
        "aat:300008798"
    ]
},
  "bbox": [],
  "geometry": {"coordinates":[-111.1333,33.6333],"type":"Point"}
}