{
  "id": 2329364,
  "type": "Feature",
  "properties": {
    "tgn:hierarchy":[
        "tgn:2329364",
        "tgn:1000001",
        "tgn:7012149",
        "tgn:1002441",
        "tgn:7007706",
        "tgn:7029392"
    ],
    "tgn:id":2329364,
    "tgn:name":"Five Mile Bar",
    "tgn:placetype":[
        "aat:300132348"
    ]
},
  "bbox": [],
  "geometry": {"coordinates":[-84.3833,39.0333],"type":"Point"}
}