{
  "id": 2370930,
  "type": "Feature",
  "properties": {
    "tgn:hierarchy":[
        "tgn:2370930",
        "tgn:7006450",
        "tgn:1000001",
        "tgn:2124089",
        "tgn:7012149",
        "tgn:7029392"
    ],
    "tgn:id":2370930,
    "tgn:name":"Hades Highway",
    "tgn:placetype":[
        "aat:300008835"
    ]
},
  "bbox": [],
  "geometry": {"coordinates":[-133.9167,58.65],"type":"Point"}
}