{
  "id": 2201766,
  "type": "Feature",
  "properties": {
    "tgn:hierarchy":[
        "tgn:2201766",
        "tgn:1000001",
        "tgn:7012149",
        "tgn:2002381",
        "tgn:7007923",
        "tgn:7029392"
    ],
    "tgn:id":2201766,
    "tgn:name":"Buck Creek",
    "tgn:placetype":[
        "aat:300008706"
    ]
},
  "bbox": [],
  "geometry": {"coordinates":[-107.2333,44.6833],"type":"Point"}
}