{
  "id": 7469405,
  "type": "Feature",
  "properties": {
    "tgn:hierarchy":[
        "tgn:7469405",
        "tgn:1000004",
        "tgn:7490934",
        "tgn:1000141",
        "tgn:7029392"
    ],
    "tgn:id":7469405,
    "tgn:name":"Zhongkeng",
    "tgn:placetype":[
        "aat:300008347"
    ]
},
  "bbox": [],
  "geometry": {"coordinates":[120.376944,22.866389],"type":"Point"}
}