{
  "id": 2698655,
  "type": "Feature",
  "properties": {
    "tgn:hierarchy":[
        "tgn:2698655",
        "tgn:1000001",
        "tgn:7012149",
        "tgn:1002950",
        "tgn:7007568",
        "tgn:7029392"
    ],
    "tgn:id":2698655,
    "tgn:name":"Stratton",
    "tgn:placetype":[
        "aat:300008347"
    ]
},
  "bbox": [],
  "geometry": {"coordinates":[-76.5333,42.3333],"type":"Point"}
}