{
  "id": 7485071,
  "type": "Feature",
  "properties": {
    "tgn:hierarchy":[
        "tgn:7485071",
        "tgn:1000004",
        "tgn:7001014",
        "tgn:1000141",
        "tgn:7029392"
    ],
    "tgn:id":7485071,
    "tgn:name":"Shuiliandong",
    "tgn:placetype":[
        "aat:300008347"
    ]
},
  "bbox": [],
  "geometry": {"coordinates":[120.692222,23.578056],"type":"Point"}
}