{
  "id": 7206574,
  "type": "Feature",
  "properties": {
    "tgn:hierarchy":[
        "tgn:7206574",
        "tgn:7003692",
        "tgn:1000003",
        "tgn:7000084",
        "tgn:7029392"
    ],
    "tgn:id":7206574,
    "tgn:name":"Dachshurst",
    "tgn:placetype":[
        "aat:300000206"
    ]
},
  "bbox": [],
  "geometry": {"coordinates":[7.85,48.533333],"type":"Point"}
}