{
  "id": 7436336,
  "type": "Feature",
  "properties": {
    "tgn:hierarchy":[
        "tgn:7436336",
        "tgn:1000001",
        "tgn:7005597",
        "tgn:7005560",
        "tgn:7029392"
    ],
    "tgn:id":7436336,
    "tgn:name":"Santo Domingo del Charco",
    "tgn:placetype":[
        "aat:300008347"
    ]
},
  "bbox": [],
  "geometry": {"coordinates":[-97.966667,24.166667],"type":"Point"}
}