{
  "id": 1090610,
  "type": "Feature",
  "properties": {
    "tgn:hierarchy":[
        "tgn:1090610",
        "tgn:7001242",
        "tgn:1000424",
        "tgn:1000171",
        "tgn:7029392"
    ],
    "tgn:id":1090610,
    "tgn:name":"Sagleipie",
    "tgn:placetype":[
        "aat:300008347",
        "aat:300008375"
    ]
},
  "bbox": [],
  "geometry": {"coordinates":[-8.8333,6.95],"type":"Point"}
}