{
  "id": 7090392,
  "type": "Feature",
  "properties": {
    "tgn:hierarchy":[
        "tgn:7090392",
        "tgn:7000096",
        "tgn:1000003",
        "tgn:7000084",
        "tgn:7029392"
    ],
    "tgn:id":7090392,
    "tgn:name":"Vo\u00dfkanal",
    "tgn:placetype":[
        "aat:300006075"
    ]
},
  "bbox": [],
  "geometry": {"coordinates":[13.35,52.983333],"type":"Point"}
}