{
  "id": 2760736,
  "type": "Feature",
  "properties": {
    "tgn:hierarchy":[
        "tgn:2760736",
        "tgn:1000001",
        "tgn:7012149",
        "tgn:2000613",
        "tgn:7007253",
        "tgn:7029392"
    ],
    "tgn:id":2760736,
    "tgn:name":"West Goose Lake",
    "tgn:placetype":[
        "aat:300008680"
    ]
},
  "bbox": [],
  "geometry": {"coordinates":[-90.9833,41.9833],"type":"Point"}
}