<<<<<<< HEAD
{
  "id": 2760736,
  "type": "Feature",
  "properties": {
    "tgn:hierarchy":[
        "tgn:2760736",
        "tgn:1000001",
        "tgn:7012149",
        "tgn:2000613",
        "tgn:7007253",
        "tgn:7029392"
    ],
    "tgn:id":2760736,
    "tgn:name":"West Goose Lake",
    "tgn:placetype":[
        "aat:300008680"
    ]
},
  "bbox": [],
  "geometry": {"coordinates":[-90.9833,41.9833],"type":"Point"}
}
=======
{"geometry":{"type":"Point","coordinates":[-90.983300,41.983300]},"type":"Feature","properties":{"hierarchy":["tgn:2760736","tgn:1000001","tgn:7012149","tgn:2000613","tgn:7007253","tgn:7029392"],"placetype":["aat:300008680"],"id":2760736,"name:xx":"West Goose Lake"}}
>>>>>>> 03f74aca74312dbeaf24d7e61306dd6a786dc3d0
