{
  "id": 7213443,
  "type": "Feature",
  "properties": {
    "tgn:hierarchy":[
        "tgn:7213443",
        "tgn:7000096",
        "tgn:1000003",
        "tgn:7000084",
        "tgn:7029392"
    ],
    "tgn:id":7213443,
    "tgn:name":"Boblitz",
    "tgn:placetype":[
        "aat:300008347"
    ]
},
  "bbox": [],
  "geometry": {"coordinates":[13.983333,51.833333],"type":"Point"}
}