{
  "id": 2602805,
  "type": "Feature",
  "properties": {
    "tgn:hierarchy":[
        "tgn:2602805",
        "tgn:1000001",
        "tgn:7012149",
        "tgn:1002613",
        "tgn:7007710",
        "tgn:7029392"
    ],
    "tgn:id":2602805,
    "tgn:name":"Quaker Hill",
    "tgn:placetype":[
        "aat:300008798"
    ]
},
  "bbox": [],
  "geometry": {"coordinates":[-76.9667,41.3167],"type":"Point"}
}