{
  "id": 7444847,
  "type": "Feature",
  "properties": {
    "tgn:hierarchy":[
        "tgn:7444847",
        "tgn:7002445",
        "tgn:7008116",
        "tgn:1000003",
        "tgn:7008591",
        "tgn:7029392"
    ],
    "tgn:id":7444847,
    "tgn:name:en":"Werrington",
    "tgn:placetype":[
        "aat:300008347"
    ]
},
  "bbox": [],
  "geometry": {"coordinates":[-4.366667,50.666667],"type":"Point"}
}