{
  "id": 2289574,
  "type": "Feature",
  "properties": {
    "tgn:hierarchy":[
        "tgn:2289574",
        "tgn:1000001",
        "tgn:7016172",
        "tgn:2000109",
        "tgn:7012149",
        "tgn:7029392"
    ],
    "tgn:id":2289574,
    "tgn:name":"Dixon Hollow",
    "tgn:placetype":[
        "aat:300008761"
    ]
},
  "bbox": [],
  "geometry": {"coordinates":[-92.9333,36.3667],"type":"Point"}
}