{
  "id": 7557572,
  "type": "Feature",
  "properties": {
    "tgn:hierarchy":[
        "tgn:7557572",
        "tgn:1000004",
        "tgn:7031781",
        "tgn:7000198",
        "tgn:7029392"
    ],
    "tgn:id":7557572,
    "tgn:name:en":"Parsa",
    "tgn:placetype":[
        "aat:300008347"
    ]
},
  "bbox": [],
  "geometry": {"coordinates":[82.816024,22.845548],"type":"Point"}
}