{
  "id": 2633130,
  "type": "Feature",
  "properties": {
    "tgn:hierarchy":[
        "tgn:2633130",
        "tgn:1000001",
        "tgn:7012149",
        "tgn:7007920",
        "tgn:7029392"
    ],
    "tgn:id":2633130,
    "tgn:name":"Rufus Woods Lake",
    "tgn:placetype":[
        "aat:300006191"
    ]
},
  "bbox": [],
  "geometry": {"coordinates":[-119.6333,47.9833],"type":"Point"}
}