{
  "id": 2276858,
  "type": "Feature",
  "properties": {
    "tgn:hierarchy":[
        "tgn:2276858",
        "tgn:1000001",
        "tgn:7012149",
        "tgn:2000906",
        "tgn:7007256",
        "tgn:7029392"
    ],
    "tgn:id":2276858,
    "tgn:name":"Davis Branch",
    "tgn:placetype":[
        "aat:300008699"
    ]
},
  "bbox": [],
  "geometry": {"coordinates":[-90.3333,30.7833],"type":"Point"}
}