{
  "id": 2249146,
  "type": "Feature",
  "properties": {
    "tgn:hierarchy":[
        "tgn:2249146",
        "tgn:1000001",
        "tgn:7012149",
        "tgn:2000182",
        "tgn:7007157",
        "tgn:7029392"
    ],
    "tgn:id":2249146,
    "tgn:name":"Cole Drain",
    "tgn:placetype":[
        "aat:300006075"
    ]
},
  "bbox": [],
  "geometry": {"coordinates":[-115.5333,33.0333],"type":"Point"}
}