{
  "id": 2273711,
  "type": "Feature",
  "properties": {
    "tgn:hierarchy":[
        "tgn:2273711",
        "tgn:1000001",
        "tgn:7012149",
        "tgn:2001451",
        "tgn:7007566",
        "tgn:7029392"
    ],
    "tgn:id":2273711,
    "tgn:name":"D Martinez Spring",
    "tgn:placetype":[
        "aat:300008697"
    ]
},
  "bbox": [],
  "geometry": {"coordinates":[-106.9167,36.05],"type":"Point"}
}