{
  "id": 2463548,
  "type": "Feature",
  "properties": {
    "tgn:hierarchy":[
        "tgn:2463548",
        "tgn:1000001",
        "tgn:7012149",
        "tgn:2002099",
        "tgn:7007826",
        "tgn:7029392"
    ],
    "tgn:id":2463548,
    "tgn:name":"Lobitas Tank",
    "tgn:placetype":[
        "aat:300006191"
    ]
},
  "bbox": [],
  "geometry": {"coordinates":[-99.0667,26.9667],"type":"Point"}
}