{
  "id": 7417437,
  "type": "Feature",
  "properties": {
    "tgn:hierarchy":[
        "tgn:7417437",
        "tgn:7005584",
        "tgn:1000001",
        "tgn:7005560",
        "tgn:7029392"
    ],
    "tgn:id":7417437,
    "tgn:name":"San Rom\u00e1n",
    "tgn:placetype":[
        "aat:300008347"
    ]
},
  "bbox": [],
  "geometry": {"coordinates":[-100.888889,20.609722],"type":"Point"}
}