{
  "id": 2129049,
  "type": "Feature",
  "properties": {
    "tgn:hierarchy":[
        "tgn:2129049",
        "tgn:1000001",
        "tgn:7012149",
        "tgn:2001162",
        "tgn:7007522",
        "tgn:7029392"
    ],
    "tgn:id":2129049,
    "tgn:name":"Alexanders Branch",
    "tgn:placetype":[
        "aat:300008699"
    ]
},
  "bbox": [],
  "geometry": {"coordinates":[-88.5833,31.7167],"type":"Point"}
}