{
  "id": 2493366,
  "type": "Feature",
  "properties": {
    "tgn:hierarchy":[
        "tgn:2493366",
        "tgn:1000001",
        "tgn:2001747",
        "tgn:7012149",
        "tgn:7007712",
        "tgn:7029392"
    ],
    "tgn:id":2493366,
    "tgn:name":"Marrow Bone Creek",
    "tgn:placetype":[
        "aat:300008706"
    ]
},
  "bbox": [],
  "geometry": {"coordinates":[-82.3667,34.75],"type":"Point"}
}