{
  "id": 7302921,
  "type": "Feature",
  "properties": {
    "tgn:hierarchy":[
        "tgn:7302921",
        "tgn:7002835",
        "tgn:7001158",
        "tgn:1000003",
        "tgn:1000095",
        "tgn:7029392"
    ],
    "tgn:id":7302921,
    "tgn:name":"Olmedo de Camaces",
    "tgn:placetype":[
        "aat:300008347"
    ]
},
  "bbox": [],
  "geometry": {"coordinates":[-6.616667,40.883333],"type":"Point"}
}