{
  "id": 7024507,
  "type": "Feature",
  "properties": {
    "tgn:hierarchy":[
        "tgn:7024507",
        "tgn:7593554",
        "tgn:1000001",
        "tgn:7024573",
        "tgn:7029392"
    ],
    "tgn:id":7024507,
    "tgn:name":"Qeqertaq",
    "tgn:placetype":[
        "aat:300008791"
    ]
},
  "bbox": [],
  "geometry": {"coordinates":[-50.25,63.0167],"type":"Point"}
}