<<<<<<< HEAD
{
  "id": 7024507,
  "type": "Feature",
  "properties": {
    "tgn:hierarchy":[
        "tgn:7024507",
        "tgn:7593554",
        "tgn:1000001",
        "tgn:7024573",
        "tgn:7029392"
    ],
    "tgn:id":7024507,
    "tgn:name":"Qeqertaq",
    "tgn:placetype":[
        "aat:300008791"
    ]
},
  "bbox": [],
  "geometry": {"coordinates":[-50.25,63.0167],"type":"Point"}
}
=======
{"geometry":{"type":"Point","coordinates":[-50.250000,63.016700]},"type":"Feature","properties":{"hierarchy":["tgn:7024507","tgn:7593554","tgn:1000001","tgn:7024573","tgn:7029392"],"placetype":["aat:300008791"],"id":7024507,"name:xx":"Qeqertaq"}}
>>>>>>> 03f74aca74312dbeaf24d7e61306dd6a786dc3d0
