{
  "id": 7028810,
  "type": "Feature",
  "properties": {
    "tgn:hierarchy":[
        "tgn:7028810",
        "tgn:7002445",
        "tgn:1000003",
        "tgn:7019057",
        "tgn:7008591",
        "tgn:7029392"
    ],
    "tgn:id":7028810,
    "tgn:name:en":"Boynton",
    "tgn:placetype":[
        "aat:300008347",
        "aat:300008372"
    ]
},
  "bbox": [],
  "geometry": {"coordinates":[-0.25,54.083333],"type":"Point"}
}