{
  "id": 7299506,
  "type": "Feature",
  "properties": {
    "tgn:hierarchy":[
        "tgn:7299506",
        "tgn:7002820",
        "tgn:7030216",
        "tgn:1000003",
        "tgn:1000095",
        "tgn:7029392"
    ],
    "tgn:id":7299506,
    "tgn:name":"Torroella de Montgr\u00ed",
    "tgn:placetype":[
        "aat:300008347"
    ]
},
  "bbox": [],
  "geometry": {"coordinates":[3.126837,42.041114],"type":"Point"}
}