{
  "id": 2265830,
  "type": "Feature",
  "properties": {
    "tgn:hierarchy":[
        "tgn:2265830",
        "tgn:1000001",
        "tgn:7012149",
        "tgn:2002371",
        "tgn:7007923",
        "tgn:7029392"
    ],
    "tgn:id":2265830,
    "tgn:name":"Crater Lake",
    "tgn:placetype":[
        "aat:300008680"
    ]
},
  "bbox": [],
  "geometry": {"coordinates":[-109.4667,43.1667],"type":"Point"}
}