{
  "id": 7034723,
  "type": "Feature",
  "properties": {
    "tgn:hierarchy":[
        "tgn:7034723",
        "tgn:1000003",
        "tgn:7003236",
        "tgn:1000080",
        "tgn:7029392"
    ],
    "tgn:id":7034723,
    "tgn:name":"Sant' Anna, Punta",
    "tgn:placetype":[
        "aat:300386846"
    ]
},
  "bbox": [],
  "geometry": {"coordinates":[9.381667,44.286944],"type":"Point"}
}