<<<<<<< HEAD
{
  "id": 7248874,
  "type": "Feature",
  "properties": {
    "tgn:hierarchy":[
        "tgn:7248874",
        "tgn:7007877",
        "tgn:1000003",
        "tgn:1000063",
        "tgn:4012014",
        "tgn:7029392"
    ],
    "tgn:id":7248874,
    "tgn:name":"Bois de Ville",
    "tgn:placetype":[
        "aat:300008347"
    ]
},
  "bbox": [],
  "geometry": {"coordinates":[3.790245,50.564055],"type":"Point"}
}
=======
{"geometry":{"type":"Point","coordinates":[3.790245,50.564055]},"type":"Feature","properties":{"hierarchy":["tgn:7248874","tgn:7007877","tgn:1000003","tgn:1000063","tgn:4012014","tgn:7029392"],"placetype":["aat:300008347"],"id":7248874,"name:xx":"Bois de Ville"}}
>>>>>>> 03f74aca74312dbeaf24d7e61306dd6a786dc3d0
