{
  "id": 2616735,
  "type": "Feature",
  "properties": {
    "tgn:hierarchy":[
        "tgn:2616735",
        "tgn:1000001",
        "tgn:7012149",
        "tgn:2001850",
        "tgn:7007825",
        "tgn:7029392"
    ],
    "tgn:id":2616735,
    "tgn:name":"Rich Cave",
    "tgn:placetype":[
        "aat:300008746"
    ]
},
  "bbox": [],
  "geometry": {"coordinates":[-85.4333,36.5667],"type":"Point"}
}