<<<<<<< HEAD
{
  "id": 7372428,
  "type": "Feature",
  "properties": {
    "tgn:hierarchy":[
        "tgn:7372428",
        "tgn:7005584",
        "tgn:1000001",
        "tgn:7005560",
        "tgn:7029392"
    ],
    "tgn:id":7372428,
    "tgn:name":"La Estancia",
    "tgn:placetype":[
        "aat:300008347"
    ]
},
  "bbox": [],
  "geometry": {"coordinates":[-101.916667,20.3],"type":"Point"}
}
=======
{"geometry":{"type":"Point","coordinates":[-101.916667,20.300000]},"type":"Feature","properties":{"hierarchy":["tgn:7372428","tgn:7005584","tgn:1000001","tgn:7005560","tgn:7029392"],"placetype":["aat:300008347"],"id":7372428,"name:xx":"La Estancia"}}
>>>>>>> 03f74aca74312dbeaf24d7e61306dd6a786dc3d0
