{
  "id": 2262860,
  "type": "Feature",
  "properties": {
    "tgn:hierarchy":[
        "tgn:2262860",
        "tgn:1000001",
        "tgn:2001816",
        "tgn:7012149",
        "tgn:7007713",
        "tgn:7029392"
    ],
    "tgn:id":2262860,
    "tgn:name":"Cowboy Draw",
    "tgn:placetype":[
        "aat:300008761"
    ]
},
  "bbox": [],
  "geometry": {"coordinates":[-102.2833,44.7167],"type":"Point"}
}