{
  "id": 2495713,
  "type": "Feature",
  "properties": {
    "tgn:hierarchy":[
        "tgn:2495713",
        "tgn:1000001",
        "tgn:7012149",
        "tgn:2001526",
        "tgn:7007709",
        "tgn:7029392"
    ],
    "tgn:id":2495713,
    "tgn:name":"Mason Bay",
    "tgn:placetype":[
        "aat:300132316"
    ]
},
  "bbox": [],
  "geometry": {"coordinates":[-76.6833,35.1333],"type":"Point"}
}