{
  "id": 7505859,
  "type": "Feature",
  "properties": {
    "tgn:hierarchy":[
        "tgn:7505859",
        "tgn:1009227",
        "tgn:1000226",
        "tgn:1000006",
        "tgn:7016850",
        "tgn:7029392"
    ],
    "tgn:id":7505859,
    "tgn:name:en":"Tara Tama",
    "tgn:placetype":[
        "aat:300008798"
    ]
},
  "bbox": [],
  "geometry": {"coordinates":[171.416667,-42.816667],"type":"Point"}
}