{
  "id": 7307457,
  "type": "Feature",
  "properties": {
    "tgn:hierarchy":[
        "tgn:7307457",
        "tgn:7001165",
        "tgn:1000003",
        "tgn:7002793",
        "tgn:1000095",
        "tgn:7029392"
    ],
    "tgn:id":7307457,
    "tgn:name":"Losilla",
    "tgn:placetype":[
        "aat:300008347"
    ]
},
  "bbox": [],
  "geometry": {"coordinates":[-1.083333,38.966667],"type":"Point"}
}