<<<<<<< HEAD
{
  "id": 2251559,
  "type": "Feature",
  "properties": {
    "tgn:hierarchy":[
        "tgn:2251559",
        "tgn:7013388",
        "tgn:1000001",
        "tgn:7012149",
        "tgn:7007517",
        "tgn:7029392"
    ],
    "tgn:id":2251559,
    "tgn:name":"Commons Brook",
    "tgn:placetype":[
        "aat:300008699"
    ]
},
  "bbox": [],
  "geometry": {"coordinates":[-73.1833,42.3167],"type":"Point"}
}
=======
{"geometry":{"type":"Point","coordinates":[-73.183300,42.316700]},"type":"Feature","properties":{"hierarchy":["tgn:2251559","tgn:7013388","tgn:1000001","tgn:7012149","tgn:7007517","tgn:7029392"],"placetype":["aat:300008699"],"id":2251559,"name:xx":"Commons Brook"}}
>>>>>>> 03f74aca74312dbeaf24d7e61306dd6a786dc3d0
