<<<<<<< HEAD
{
  "id": 2152790,
  "type": "Feature",
  "properties": {
    "tgn:hierarchy":[
        "tgn:2152790",
        "tgn:1000001",
        "tgn:7012149",
        "tgn:2000908",
        "tgn:7007256",
        "tgn:7029392"
    ],
    "tgn:id":2152790,
    "tgn:name":"Bayou la Loutre",
    "tgn:placetype":[
        "aat:300008699"
    ]
},
  "bbox": [],
  "geometry": {"coordinates":[-90.9167,29.4],"type":"Point"}
}
=======
{"geometry":{"type":"Point","coordinates":[-90.916700,29.400000]},"type":"Feature","properties":{"hierarchy":["tgn:2152790","tgn:1000001","tgn:7012149","tgn:2000908","tgn:7007256","tgn:7029392"],"placetype":["aat:300008699"],"id":2152790,"name:xx":"Bayou la Loutre"}}
>>>>>>> 03f74aca74312dbeaf24d7e61306dd6a786dc3d0
