{
  "id": 7398311,
  "type": "Feature",
  "properties": {
    "tgn:hierarchy":[
        "tgn:7398311",
        "tgn:1000001",
        "tgn:1001960",
        "tgn:7005560",
        "tgn:7029392"
    ],
    "tgn:id":7398311,
    "tgn:name":"La Descubridora",
    "tgn:placetype":[
        "aat:300266554",
        "aat:300008699"
    ]
},
  "bbox": [],
  "geometry": {"coordinates":[-111.202778,30.921667],"type":"Point"}
}