<<<<<<< HEAD
{
  "id": 7477299,
  "type": "Feature",
  "properties": {
    "tgn:hierarchy":[
        "tgn:7477299",
        "tgn:1000004",
        "tgn:7001013",
        "tgn:1000141",
        "tgn:7029392"
    ],
    "tgn:id":7477299,
    "tgn:name":"Lincuo",
    "tgn:placetype":[
        "aat:300008347"
    ]
},
  "bbox": [],
  "geometry": {"coordinates":[121.060511,25.028364],"type":"Point"}
}
=======
{"geometry":{"type":"Point","coordinates":[121.060511,25.028364]},"type":"Feature","properties":{"hierarchy":["tgn:7477299","tgn:1000004","tgn:7001013","tgn:1000141","tgn:7029392"],"placetype":["aat:300008347"],"id":7477299,"name:xx":"Lincuo"}}
>>>>>>> 03f74aca74312dbeaf24d7e61306dd6a786dc3d0
