{
  "id": 7477299,
  "type": "Feature",
  "properties": {
    "tgn:hierarchy":[
        "tgn:7477299",
        "tgn:1000004",
        "tgn:7001013",
        "tgn:1000141",
        "tgn:7029392"
    ],
    "tgn:id":7477299,
    "tgn:name":"Lincuo",
    "tgn:placetype":[
        "aat:300008347"
    ]
},
  "bbox": [],
  "geometry": {"coordinates":[121.060511,25.028364],"type":"Point"}
}