{
  "id": 7562066,
  "type": "Feature",
  "properties": {
    "tgn:hierarchy":[
        "tgn:7562066",
        "tgn:1000004",
        "tgn:7000198",
        "tgn:7016722",
        "tgn:7029392"
    ],
    "tgn:id":7562066,
    "tgn:name:en":"Ars\u0101ra",
    "tgn:placetype":[
        "aat:300008347"
    ]
},
  "bbox": [],
  "geometry": {"coordinates":[79.269173,27.066902],"type":"Point"}
}