{
  "id": 7528056,
  "type": "Feature",
  "properties": {
    "tgn:hierarchy":[
        "tgn:7528056",
        "tgn:7001242",
        "tgn:7001311",
        "tgn:7016833",
        "tgn:7029392"
    ],
    "tgn:id":7528056,
    "tgn:name:en":"Umm Dar\u00e2heib, W\u00e2di",
    "tgn:placetype":[
        "aat:300379998"
    ]
},
  "bbox": [],
  "geometry": {"coordinates":[33.498904,25.620078],"type":"Point"}
}