{
  "id": 2421256,
  "type": "Feature",
  "properties": {
    "tgn:hierarchy":[
        "tgn:2421256",
        "tgn:1000001",
        "tgn:7012149",
        "tgn:1003020",
        "tgn:7007920",
        "tgn:7029392"
    ],
    "tgn:id":2421256,
    "tgn:name":"Jerry Lakes",
    "tgn:placetype":[
        "aat:300008680"
    ]
},
  "bbox": [],
  "geometry": {"coordinates":[-120.9167,48.75],"type":"Point"}
}