{
  "id": 7585007,
  "type": "Feature",
  "properties": {
    "tgn:hierarchy":[
        "tgn:7585007",
        "tgn:1000004",
        "tgn:7000198",
        "tgn:1001894",
        "tgn:7029392"
    ],
    "tgn:id":7585007,
    "tgn:name:en":"Khemkheri",
    "tgn:placetype":[
        "aat:300007595"
    ]
},
  "bbox": [],
  "geometry": {"coordinates":[77.998207,24.078657],"type":"Point"}
}