{
  "id": 2380287,
  "type": "Feature",
  "properties": {
    "tgn:hierarchy":[
        "tgn:2380287",
        "tgn:1000001",
        "tgn:1002195",
        "tgn:7012149",
        "tgn:7007520",
        "tgn:7029392"
    ],
    "tgn:id":2380287,
    "tgn:name":"Hatmaker",
    "tgn:placetype":[
        "aat:300008347"
    ]
},
  "bbox": [],
  "geometry": {"coordinates":[-85.1167,41.8333],"type":"Point"}
}