{
  "id": 7316644,
  "type": "Feature",
  "properties": {
    "tgn:hierarchy":[
        "tgn:7316644",
        "tgn:1001623",
        "tgn:1000049",
        "tgn:1000002",
        "tgn:7029392"
    ],
    "tgn:id":7316644,
    "tgn:name":"Capt, Punta",
    "tgn:placetype":[
        "aat:300386846"
    ]
},
  "bbox": [],
  "geometry": {"coordinates":[-74.533333,-47.95],"type":"Point"}
}