{
  "id": 7369225,
  "type": "Feature",
  "properties": {
    "tgn:hierarchy":[
        "tgn:7369225",
        "tgn:1001836",
        "tgn:1000001",
        "tgn:7005560",
        "tgn:7029392"
    ],
    "tgn:id":7369225,
    "tgn:name":"Guadalupe",
    "tgn:placetype":[
        "aat:300008347"
    ]
},
  "bbox": [],
  "geometry": {"coordinates":[-111.972778,25.590833],"type":"Point"}
}