{
  "id": 2433037,
  "type": "Feature",
  "properties": {
    "tgn:hierarchy":[
        "tgn:2433037",
        "tgn:1000001",
        "tgn:7012149",
        "tgn:2001538",
        "tgn:7007709",
        "tgn:7029392"
    ],
    "tgn:id":2433037,
    "tgn:name":"Keith Branch",
    "tgn:placetype":[
        "aat:300008699"
    ]
},
  "bbox": [],
  "geometry": {"coordinates":[-78.2833,34.6833],"type":"Point"}
}