{
  "id": 7244112,
  "type": "Feature",
  "properties": {
    "tgn:hierarchy":[
        "tgn:7244112",
        "tgn:7003457",
        "tgn:1000003",
        "tgn:1000063",
        "tgn:7018236",
        "tgn:7029392"
    ],
    "tgn:id":7244112,
    "tgn:name":"Kalkhoven",
    "tgn:placetype":[
        "aat:300008347"
    ]
},
  "bbox": [],
  "geometry": {"coordinates":[3.55,50.766667],"type":"Point"}
}