{
  "id": 2134892,
  "type": "Feature",
  "properties": {
    "tgn:hierarchy":[
        "tgn:2134892",
        "tgn:1000001",
        "tgn:7012149",
        "tgn:2002114",
        "tgn:7007827",
        "tgn:7029392"
    ],
    "tgn:id":2134892,
    "tgn:name":"Antelope Mountain",
    "tgn:placetype":[
        "aat:300008798"
    ]
},
  "bbox": [],
  "geometry": {"coordinates":[-113.3833,39.2333],"type":"Point"}
}