{
  "id": 2518598,
  "type": "Feature",
  "properties": {
    "tgn:hierarchy":[
        "tgn:2518598",
        "tgn:1000001",
        "tgn:7012149",
        "tgn:7007157",
        "tgn:2000190",
        "tgn:7029392"
    ],
    "tgn:id":2518598,
    "tgn:name":"Mitchell Gulch",
    "tgn:placetype":[
        "aat:300008761"
    ]
},
  "bbox": [],
  "geometry": {"coordinates":[-122.4333,40.2667],"type":"Point"}
}