{
  "id": 2688903,
  "type": "Feature",
  "properties": {
    "tgn:hierarchy":[
        "tgn:2688903",
        "tgn:1000001",
        "tgn:7012149",
        "tgn:2002118",
        "tgn:7007827",
        "tgn:7029392"
    ],
    "tgn:id":2688903,
    "tgn:name":"Spurrier",
    "tgn:placetype":[
        "aat:300008347"
    ]
},
  "bbox": [],
  "geometry": {"coordinates":[-111.8833,40.65],"type":"Point"}
}