{
  "id": 7316889,
  "type": "Feature",
  "properties": {
    "tgn:hierarchy":[
        "tgn:7316889",
        "tgn:7002464",
        "tgn:1000049",
        "tgn:1000002",
        "tgn:7029392"
    ],
    "tgn:id":7316889,
    "tgn:name":"Chironta, Quebrada",
    "tgn:placetype":[
        "aat:300266554",
        "aat:300008699"
    ]
},
  "bbox": [],
  "geometry": {"coordinates":[-69.783333,-18.316667],"type":"Point"}
}