<<<<<<< HEAD
{
  "id": 2253313,
  "type": "Feature",
  "properties": {
    "tgn:hierarchy":[
        "tgn:2253313",
        "tgn:1000001",
        "tgn:7012149",
        "tgn:2001526",
        "tgn:7007709",
        "tgn:7029392"
    ],
    "tgn:id":2253313,
    "tgn:name":"Convoy Gut",
    "tgn:placetype":[
        "aat:300008699"
    ]
},
  "bbox": [],
  "geometry": {"coordinates":[-76.6,35.3167],"type":"Point"}
}
=======
{"geometry":{"type":"Point","coordinates":[-76.600000,35.316700]},"type":"Feature","properties":{"hierarchy":["tgn:2253313","tgn:1000001","tgn:7012149","tgn:2001526","tgn:7007709","tgn:7029392"],"placetype":["aat:300008699"],"id":2253313,"name:xx":"Convoy Gut"}}
>>>>>>> 03f74aca74312dbeaf24d7e61306dd6a786dc3d0
