{
  "id": 2276197,
  "type": "Feature",
  "properties": {
    "tgn:hierarchy":[
        "tgn:2276197",
        "tgn:1000001",
        "tgn:7012149",
        "tgn:2000183",
        "tgn:7007157",
        "tgn:7029392"
    ],
    "tgn:id":2276197,
    "tgn:name":"Darwin Canyon",
    "tgn:placetype":[
        "aat:300008761"
    ]
},
  "bbox": [],
  "geometry": {"coordinates":[-117.5333,36.2333],"type":"Point"}
}