{
  "id": 7590678,
  "type": "Feature",
  "properties": {
    "tgn:hierarchy":[
        "tgn:7590678",
        "tgn:1000004",
        "tgn:7000198",
        "tgn:7000799",
        "tgn:7029392"
    ],
    "tgn:id":7590678,
    "tgn:name:en":"Jera",
    "tgn:placetype":[
        "aat:300008347"
    ]
},
  "bbox": [],
  "geometry": {"coordinates":[74.363889,33.891667],"type":"Point"}
}