{
  "id": 2779745,
  "type": "Feature",
  "properties": {
    "tgn:hierarchy":[
        "tgn:2779745",
        "tgn:1000001",
        "tgn:7012149",
        "tgn:1002371",
        "tgn:7007255",
        "tgn:7029392"
    ],
    "tgn:id":2779745,
    "tgn:name":"Wolf Run",
    "tgn:placetype":[
        "aat:300008699"
    ]
},
  "bbox": [],
  "geometry": {"coordinates":[-84.5167,38.0167],"type":"Point"}
}