{
  "id": 2322684,
  "type": "Feature",
  "properties": {
    "tgn:hierarchy":[
        "tgn:2322684",
        "tgn:1000001",
        "tgn:7012149",
        "tgn:2002010",
        "tgn:7007826",
        "tgn:7029392"
    ],
    "tgn:id":2322684,
    "tgn:name":"Falls Spring",
    "tgn:placetype":[
        "aat:300008697"
    ]
},
  "bbox": [],
  "geometry": {"coordinates":[-104.0167,30.9833],"type":"Point"}
}