{
  "id": 7577845,
  "type": "Feature",
  "properties": {
    "tgn:hierarchy":[
        "tgn:7577845",
        "tgn:1000004",
        "tgn:7000198",
        "tgn:7031783",
        "tgn:7029392"
    ],
    "tgn:id":7577845,
    "tgn:name:en":"Luia",
    "tgn:placetype":[
        "aat:300008347"
    ]
},
  "bbox": [],
  "geometry": {"coordinates":[85.523997,22.39315],"type":"Point"}
}