{
  "id": 7316968,
  "type": "Feature",
  "properties": {
    "tgn:hierarchy":[
        "tgn:7316968",
        "tgn:1001699",
        "tgn:1000049",
        "tgn:1000002",
        "tgn:7029392"
    ],
    "tgn:id":7316968,
    "tgn:name":"Conev, Punta",
    "tgn:placetype":[
        "aat:300386846"
    ]
},
  "bbox": [],
  "geometry": {"coordinates":[-73.133333,-42.333333],"type":"Point"}
}