{
  "id": 7137048,
  "type": "Feature",
  "properties": {
    "tgn:hierarchy":[
        "tgn:7137048",
        "tgn:1000003",
        "tgn:7003678",
        "tgn:7000084",
        "tgn:7029392"
    ],
    "tgn:id":7137048,
    "tgn:name":"Lerchen Berg",
    "tgn:placetype":[
        "aat:300008777"
    ]
},
  "bbox": [],
  "geometry": {"coordinates":[9.35,50.433333],"type":"Point"}
}