{
  "id": 7225824,
  "type": "Feature",
  "properties": {
    "tgn:hierarchy":[
        "tgn:7225824",
        "tgn:7002680",
        "tgn:7001395",
        "tgn:1000003",
        "tgn:1000074",
        "tgn:7029392"
    ],
    "tgn:id":7225824,
    "tgn:name":"Psil\u00ed Korif\u00ed",
    "tgn:placetype":[
        "aat:300008795"
    ]
},
  "bbox": [],
  "geometry": {"coordinates":[21.283333,38.85],"type":"Point"}
}