{
  "id": 7549786,
  "type": "Feature",
  "properties": {
    "tgn:hierarchy":[
        "tgn:7549786",
        "tgn:1000004",
        "tgn:7000198",
        "tgn:1001977",
        "tgn:7029392"
    ],
    "tgn:id":7549786,
    "tgn:name:en":"Contai Road",
    "tgn:placetype":[
        "aat:300007783"
    ]
},
  "bbox": [],
  "geometry": {"coordinates":[87.336296,22.070098],"type":"Point"}
}