{
  "id": 2652444,
  "type": "Feature",
  "properties": {
    "tgn:hierarchy":[
        "tgn:2652444",
        "tgn:1000001",
        "tgn:2000779",
        "tgn:7012149",
        "tgn:7007255",
        "tgn:7029392"
    ],
    "tgn:id":2652444,
    "tgn:name":"Seng Branch",
    "tgn:placetype":[
        "aat:300008699"
    ]
},
  "bbox": [],
  "geometry": {"coordinates":[-84.9333,37.4833],"type":"Point"}
}