{
  "id": 7000654,
  "type": "Feature",
  "properties": {
    "tgn:hierarchy":[
        "tgn:7000654",
        "tgn:7001242",
        "tgn:7000605",
        "tgn:1000172",
        "tgn:7029392"
    ],
    "tgn:id":7000654,
    "tgn:name":"Hil\u0101l, Ra's al",
    "tgn:placetype":[
        "aat:300008850"
    ]
},
  "bbox": [],
  "geometry": {"coordinates":[22.1667,32.95],"type":"Point"}
}