{
  "id": 2308883,
  "type": "Feature",
  "properties": {
    "tgn:hierarchy":[
        "tgn:2308883",
        "tgn:1000001",
        "tgn:7012149",
        "tgn:2001207",
        "tgn:7007523",
        "tgn:7029392"
    ],
    "tgn:id":2308883,
    "tgn:name":"East Prong Indian Creek",
    "tgn:placetype":[
        "aat:300008706"
    ]
},
  "bbox": [],
  "geometry": {"coordinates":[-91.0667,37.6667],"type":"Point"}
}