{
  "id": 7256052,
  "type": "Feature",
  "properties": {
    "tgn:hierarchy":[
        "tgn:7256052",
        "tgn:7003458",
        "tgn:1000003",
        "tgn:1000063",
        "tgn:7018236",
        "tgn:7029392"
    ],
    "tgn:id":7256052,
    "tgn:name":"Sint-Denijs",
    "tgn:placetype":[
        "aat:300008347"
    ]
},
  "bbox": [],
  "geometry": {"coordinates":[3.366271,50.751981],"type":"Point"}
}