{
  "id": 2187130,
  "type": "Feature",
  "properties": {
    "tgn:hierarchy":[
        "tgn:2187130",
        "tgn:1000001",
        "tgn:7012149",
        "tgn:7007157",
        "tgn:1002748",
        "tgn:7029392"
    ],
    "tgn:id":2187130,
    "tgn:name":"Bonta Reservoir",
    "tgn:placetype":[
        "aat:300006191"
    ]
},
  "bbox": [],
  "geometry": {"coordinates":[-117.8333,33.6167],"type":"Point"}
}