{
  "id": 2644058,
  "type": "Feature",
  "properties": {
    "tgn:hierarchy":[
        "tgn:2644058",
        "tgn:1000001",
        "tgn:7012149",
        "tgn:7007158",
        "tgn:7029392"
    ],
    "tgn:id":2644058,
    "tgn:name":"Santa Fe Peak",
    "tgn:placetype":[
        "aat:300008798"
    ]
},
  "bbox": [],
  "geometry": {"coordinates":[-105.8333,39.5667],"type":"Point"}
}