{
  "id": 2231405,
  "type": "Feature",
  "properties": {
    "tgn:hierarchy":[
        "tgn:2231405",
        "tgn:1000001",
        "tgn:7012149",
        "tgn:2002182",
        "tgn:7007919",
        "tgn:7029392"
    ],
    "tgn:id":2231405,
    "tgn:name":"Chalgrove Lake",
    "tgn:placetype":[
        "aat:300006191"
    ]
},
  "bbox": [],
  "geometry": {"coordinates":[-78.45,37.2333],"type":"Point"}
}