{
  "id": 1004343,
  "type": "Feature",
  "properties": {
    "tgn:hierarchy":[
        "tgn:1004343",
        "tgn:7018899",
        "tgn:7002445",
        "tgn:1000003",
        "tgn:7008136",
        "tgn:7008591",
        "tgn:7029392"
    ],
    "tgn:id":1004343,
    "tgn:name:en":"Dagenham",
    "tgn:placetype":[
        "aat:300008347",
        "aat:300000745",
        "aat:300387220"
    ]
},
  "bbox": [],
  "geometry": {"coordinates":[0.1333,51.55],"type":"Point"}
}