{
  "id": 2435843,
  "type": "Feature",
  "properties": {
    "tgn:hierarchy":[
        "tgn:2435843",
        "tgn:1000001",
        "tgn:1002359",
        "tgn:7012149",
        "tgn:7007517",
        "tgn:7029392"
    ],
    "tgn:id":2435843,
    "tgn:name":"Kettle Island",
    "tgn:placetype":[
        "aat:300008791"
    ]
},
  "bbox": [],
  "geometry": {"coordinates":[-70.7167,42.5667],"type":"Point"}
}