{
  "id": 7590405,
  "type": "Feature",
  "properties": {
    "tgn:hierarchy":[
        "tgn:7590405",
        "tgn:1000004",
        "tgn:7000198",
        "tgn:7000799",
        "tgn:7029392"
    ],
    "tgn:id":7590405,
    "tgn:name:en":"Kuli\u0101n",
    "tgn:placetype":[
        "aat:300008347"
    ]
},
  "bbox": [],
  "geometry": {"coordinates":[74.359269,33.762928],"type":"Point"}
}