{
  "id": 2497830,
  "type": "Feature",
  "properties": {
    "tgn:hierarchy":[
        "tgn:2497830",
        "tgn:1000001",
        "tgn:2001174",
        "tgn:7012149",
        "tgn:7007523",
        "tgn:7029392"
    ],
    "tgn:id":2497830,
    "tgn:name":"Mayfield Creek",
    "tgn:placetype":[
        "aat:300008706"
    ]
},
  "bbox": [],
  "geometry": {"coordinates":[-90.0167,37.45],"type":"Point"}
}