{
  "id": 2702284,
  "type": "Feature",
  "properties": {
    "tgn:hierarchy":[
        "tgn:2702284",
        "tgn:1000001",
        "tgn:2001704",
        "tgn:7012149",
        "tgn:7007708",
        "tgn:7029392"
    ],
    "tgn:id":2702284,
    "tgn:name":"Sullivan Creek",
    "tgn:placetype":[
        "aat:300008706"
    ]
},
  "bbox": [],
  "geometry": {"coordinates":[-124.5333,42.8167],"type":"Point"}
}