{
  "id": 7429371,
  "type": "Feature",
  "properties": {
    "tgn:hierarchy":[
        "tgn:7429371",
        "tgn:1001853",
        "tgn:1000001",
        "tgn:7005560",
        "tgn:7029392"
    ],
    "tgn:id":7429371,
    "tgn:name":"El Siete de Enero",
    "tgn:placetype":[
        "aat:300008347"
    ]
},
  "bbox": [],
  "geometry": {"coordinates":[-102.95,25.216667],"type":"Point"}
}