{
  "id": 2445471,
  "type": "Feature",
  "properties": {
    "tgn:hierarchy":[
        "tgn:2445471",
        "tgn:1000001",
        "tgn:7012149",
        "tgn:1002800",
        "tgn:7007710",
        "tgn:7029392"
    ],
    "tgn:id":2445471,
    "tgn:name":"Lent Hollow",
    "tgn:placetype":[
        "aat:300008761"
    ]
},
  "bbox": [],
  "geometry": {"coordinates":[-77.95,41.85],"type":"Point"}
}