{
  "id": 7426257,
  "type": "Feature",
  "properties": {
    "tgn:hierarchy":[
        "tgn:7426257",
        "tgn:7005581",
        "tgn:1000001",
        "tgn:7005560",
        "tgn:7029392"
    ],
    "tgn:id":7426257,
    "tgn:name":"El \u00c1lamo",
    "tgn:placetype":[
        "aat:300008347"
    ]
},
  "bbox": [],
  "geometry": {"coordinates":[-104.033333,29.066667],"type":"Point"}
}