{
  "id": 2617050,
  "type": "Feature",
  "properties": {
    "tgn:hierarchy":[
        "tgn:2617050",
        "tgn:1000001",
        "tgn:7012149",
        "tgn:1002440",
        "tgn:7007568",
        "tgn:7029392"
    ],
    "tgn:id":2617050,
    "tgn:name":"Richards Vly",
    "tgn:placetype":[
        "aat:300008905"
    ]
},
  "bbox": [],
  "geometry": {"coordinates":[-74.8167,43.35],"type":"Point"}
}