{
  "id": 1022453,
  "type": "Feature",
  "properties": {
    "tgn:hierarchy":[
        "tgn:1022453",
        "tgn:7005439",
        "tgn:1000047",
        "tgn:7002455",
        "tgn:1000002",
        "tgn:7029392"
    ],
    "tgn:id":1022453,
    "tgn:name":"Picu\u00ed",
    "tgn:placetype":[
        "aat:300008347"
    ]
},
  "bbox": [],
  "geometry": {"coordinates":[-36.3333,-6.4667],"type":"Point"}
}