{
  "id": 2184910,
  "type": "Feature",
  "properties": {
    "tgn:hierarchy":[
        "tgn:2184910",
        "tgn:2000919",
        "tgn:1000001",
        "tgn:7012149",
        "tgn:7007515",
        "tgn:7029392"
    ],
    "tgn:id":2184910,
    "tgn:name":"Bogan Brook",
    "tgn:placetype":[
        "aat:300008699"
    ]
},
  "bbox": [],
  "geometry": {"coordinates":[-68.15,46.4833],"type":"Point"}
}