{
  "id": 2157336,
  "type": "Feature",
  "properties": {
    "tgn:hierarchy":[
        "tgn:2157336",
        "tgn:1000001",
        "tgn:7012149",
        "tgn:2001279",
        "tgn:7007524",
        "tgn:7029392"
    ],
    "tgn:id":2157336,
    "tgn:name":"Beaver Creek",
    "tgn:placetype":[
        "aat:300008706"
    ]
},
  "bbox": [],
  "geometry": {"coordinates":[-113.5167,46.4667],"type":"Point"}
}