{
  "id": 2429421,
  "type": "Feature",
  "properties": {
    "tgn:hierarchy":[
        "tgn:2429421",
        "tgn:1000001",
        "tgn:7012149",
        "tgn:7007709",
        "tgn:7029392"
    ],
    "tgn:id":2429421,
    "tgn:name":"Juniper Creek",
    "tgn:placetype":[
        "aat:300008706"
    ]
},
  "bbox": [],
  "geometry": {"coordinates":[-78.0833,35.7667],"type":"Point"}
}