<<<<<<< HEAD
{
  "id": 2153091,
  "type": "Feature",
  "properties": {
    "tgn:hierarchy":[
        "tgn:2153091",
        "tgn:1000001",
        "tgn:7012149",
        "tgn:2001288",
        "tgn:7007524",
        "tgn:7029392"
    ],
    "tgn:id":2153091,
    "tgn:name":"Beacon Point",
    "tgn:placetype":[
        "aat:300008347"
    ]
},
  "bbox": [],
  "geometry": {"coordinates":[-111.35,45.3833],"type":"Point"}
}
=======
{"geometry":{"type":"Point","coordinates":[-111.350000,45.383300]},"type":"Feature","properties":{"hierarchy":["tgn:2153091","tgn:1000001","tgn:7012149","tgn:2001288","tgn:7007524","tgn:7029392"],"placetype":["aat:300008347"],"id":2153091,"name:xx":"Beacon Point"}}
>>>>>>> 03f74aca74312dbeaf24d7e61306dd6a786dc3d0
