{
  "id": 2714400,
  "type": "Feature",
  "properties": {
    "tgn:hierarchy":[
        "tgn:2714400",
        "tgn:1000001",
        "tgn:7014423",
        "tgn:7012149",
        "tgn:7007517",
        "tgn:7029392"
    ],
    "tgn:id":2714400,
    "tgn:name":"Tempes Knob",
    "tgn:placetype":[
        "aat:300008798"
    ]
},
  "bbox": [],
  "geometry": {"coordinates":[-70.65,41.7167],"type":"Point"}
}