{
  "id": 7418037,
  "type": "Feature",
  "properties": {
    "tgn:hierarchy":[
        "tgn:7418037",
        "tgn:1000001",
        "tgn:7005591",
        "tgn:7005560",
        "tgn:7029392"
    ],
    "tgn:id":7418037,
    "tgn:name:es":"Gitana, Isla",
    "tgn:placetype":[
        "aat:300008791"
    ]
},
  "bbox": [],
  "geometry": {"coordinates":[-94.269444,16.180556],"type":"Point"}
}