<<<<<<< HEAD
{
  "id": 7379955,
  "type": "Feature",
  "properties": {
    "tgn:hierarchy":[
        "tgn:7379955",
        "tgn:1000001",
        "tgn:7005599",
        "tgn:7005560",
        "tgn:7029392"
    ],
    "tgn:id":7379955,
    "tgn:name":"Mata Arriero",
    "tgn:placetype":[
        "aat:300008347"
    ]
},
  "bbox": [],
  "geometry": {"coordinates":[-96.333333,18.95],"type":"Point"}
}
=======
{"geometry":{"type":"Point","coordinates":[-96.333333,18.950000]},"type":"Feature","properties":{"hierarchy":["tgn:7379955","tgn:1000001","tgn:7005599","tgn:7005560","tgn:7029392"],"placetype":["aat:300008347"],"id":7379955,"name:xx":"Mata Arriero"}}
>>>>>>> 03f74aca74312dbeaf24d7e61306dd6a786dc3d0
