{
  "id": 1083875,
  "type": "Feature",
  "properties": {
    "tgn:hierarchy":[
        "tgn:1083875",
        "tgn:7016849",
        "tgn:1000004",
        "tgn:1000119",
        "tgn:7029392"
    ],
    "tgn:id":1083875,
    "tgn:name:en":"Tulkarm",
    "tgn:placetype":[
        "aat:300008347",
        "aat:300008375"
    ]
},
  "bbox": [],
  "geometry": {"coordinates":[35.016,32.31],"type":"Point"}
}