{
  "id": 2223907,
  "type": "Feature",
  "properties": {
    "tgn:hierarchy":[
        "tgn:2223907",
        "tgn:1000001",
        "tgn:2000315",
        "tgn:7012149",
        "tgn:7007248",
        "tgn:7029392"
    ],
    "tgn:id":2223907,
    "tgn:name":"Carters Prairie",
    "tgn:placetype":[
        "aat:300008905"
    ]
},
  "bbox": [],
  "geometry": {"coordinates":[-82.15,30.9667],"type":"Point"}
}