{
  "id": 2692768,
  "type": "Feature",
  "properties": {
    "tgn:hierarchy":[
        "tgn:2692768",
        "tgn:1000001",
        "tgn:7012149",
        "tgn:2001276",
        "tgn:7007524",
        "tgn:7029392"
    ],
    "tgn:id":2692768,
    "tgn:name":"Steel Mule Reservoir",
    "tgn:placetype":[
        "aat:300006191"
    ]
},
  "bbox": [],
  "geometry": {"coordinates":[-107.6167,47.1833],"type":"Point"}
}