{
  "id": 2772382,
  "type": "Feature",
  "properties": {
    "tgn:hierarchy":[
        "tgn:2772382",
        "tgn:1000001",
        "tgn:7012149",
        "tgn:2001555",
        "tgn:7007709",
        "tgn:7029392"
    ],
    "tgn:id":2772382,
    "tgn:name":"William Shugart Lake",
    "tgn:placetype":[
        "aat:300006191"
    ]
},
  "bbox": [],
  "geometry": {"coordinates":[-80.6833,36.15],"type":"Point"}
}