<<<<<<< HEAD
{
  "id": 2406601,
  "type": "Feature",
  "properties": {
    "tgn:hierarchy":[
        "tgn:2406601",
        "tgn:1000001",
        "tgn:7012149",
        "tgn:2001500",
        "tgn:7007709",
        "tgn:7029392"
    ],
    "tgn:id":2406601,
    "tgn:name":"Hunsuckle Lake",
    "tgn:placetype":[
        "aat:300006191"
    ]
},
  "bbox": [],
  "geometry": {"coordinates":[-79.8667,36.1667],"type":"Point"}
}
=======
{"geometry":{"type":"Point","coordinates":[-79.866700,36.166700]},"type":"Feature","properties":{"hierarchy":["tgn:2406601","tgn:1000001","tgn:7012149","tgn:2001500","tgn:7007709","tgn:7029392"],"placetype":["aat:300006191"],"id":2406601,"name:xx":"Hunsuckle Lake"}}
>>>>>>> 03f74aca74312dbeaf24d7e61306dd6a786dc3d0
