{
  "id": 2394047,
  "type": "Feature",
  "properties": {
    "tgn:hierarchy":[
        "tgn:2394047",
        "tgn:1000001",
        "tgn:2001429",
        "tgn:7012149",
        "tgn:7007566",
        "tgn:7029392"
    ],
    "tgn:id":2394047,
    "tgn:name":"Hog Tank",
    "tgn:placetype":[
        "aat:300006191"
    ]
},
  "bbox": [],
  "geometry": {"coordinates":[-107.7333,33.7833],"type":"Point"}
}