{
  "id": 1011847,
  "type": "Feature",
  "properties": {
    "tgn:hierarchy":[
        "tgn:1011847",
        "tgn:1000001",
        "tgn:7012149",
        "tgn:7014612",
        "tgn:7007568",
        "tgn:7029392"
    ],
    "tgn:id":1011847,
    "tgn:name":"Edgewater Point",
    "tgn:placetype":[
        "aat:300386846"
    ]
},
  "bbox": [],
  "geometry": {"coordinates":[-73.7333,40.9167],"type":"Point"}
}