{
  "id": 1131116,
  "type": "Feature",
  "properties": {
    "tgn:hierarchy":[
        "tgn:1131116",
        "tgn:1002083",
        "tgn:1000050",
        "tgn:1000002",
        "tgn:7029392"
    ],
    "tgn:id":1131116,
    "tgn:name":"Tun\u00eda, R\u00edo",
    "tgn:placetype":[
        "aat:300008707"
    ]
},
  "bbox": [],
  "geometry": {"coordinates":[-72.726,1.186],"type":"Point"}
}