<<<<<<< HEAD
{
  "id": 7470064,
  "type": "Feature",
  "properties": {
    "tgn:hierarchy":[
        "tgn:7470064",
        "tgn:1000004",
        "tgn:1000959",
        "tgn:1000141",
        "tgn:7029392"
    ],
    "tgn:id":7470064,
    "tgn:name":"Hengkengzi",
    "tgn:placetype":[
        "aat:300008347"
    ]
},
  "bbox": [],
  "geometry": {"coordinates":[121.6,25.033333],"type":"Point"}
}
=======
{"geometry":{"type":"Point","coordinates":[121.600000,25.033333]},"type":"Feature","properties":{"hierarchy":["tgn:7470064","tgn:1000004","tgn:1000959","tgn:1000141","tgn:7029392"],"placetype":["aat:300008347"],"id":7470064,"name:xx":"Hengkengzi"}}
>>>>>>> 03f74aca74312dbeaf24d7e61306dd6a786dc3d0
