{
  "id": 7184027,
  "type": "Feature",
  "properties": {
    "tgn:hierarchy":[
        "tgn:7184027",
        "tgn:1000003",
        "tgn:7003685",
        "tgn:7000084",
        "tgn:7029392"
    ],
    "tgn:id":7184027,
    "tgn:name":"Gottesberg",
    "tgn:placetype":[
        "aat:300000745"
    ]
},
  "bbox": [],
  "geometry": {"coordinates":[12.483333,50.433333],"type":"Point"}
}