<<<<<<< HEAD
{
  "id": 2150328,
  "type": "Feature",
  "properties": {
    "tgn:hierarchy":[
        "tgn:2150328",
        "tgn:1000001",
        "tgn:7012149",
        "tgn:2001461",
        "tgn:7007568",
        "tgn:7029392"
    ],
    "tgn:id":2150328,
    "tgn:name":"Basin Brook",
    "tgn:placetype":[
        "aat:300008699"
    ]
},
  "bbox": [],
  "geometry": {"coordinates":[-73.8833,44.1167],"type":"Point"}
}
=======
{"geometry":{"type":"Point","coordinates":[-73.883300,44.116700]},"type":"Feature","properties":{"hierarchy":["tgn:2150328","tgn:1000001","tgn:7012149","tgn:2001461","tgn:7007568","tgn:7029392"],"placetype":["aat:300008699"],"id":2150328,"name:xx":"Basin Brook"}}
>>>>>>> 03f74aca74312dbeaf24d7e61306dd6a786dc3d0
