{
  "id": 1019886,
  "type": "Feature",
  "properties": {
    "tgn:hierarchy":[
        "tgn:1019886",
        "tgn:1001195",
        "tgn:7006477",
        "tgn:1000002",
        "tgn:7029392"
    ],
    "tgn:id":1019886,
    "tgn:name":"Puerto Bermejo",
    "tgn:placetype":[
        "aat:300008347"
    ]
},
  "bbox": [],
  "geometry": {"coordinates":[-58.5667,-26.9167],"type":"Point"}
}