{
  "id": 1124985,
  "type": "Feature",
  "properties": {
    "tgn:hierarchy":[
        "tgn:1124985",
        "tgn:1000003",
        "tgn:7003676",
        "tgn:7000084",
        "tgn:7029392"
    ],
    "tgn:id":1124985,
    "tgn:name":"Ise",
    "tgn:placetype":[
        "aat:300008707",
        "aat:300008699"
    ]
},
  "bbox": [],
  "geometry": {"coordinates":[10.533333,52.483333],"type":"Point"}
}