{
  "id": 2483789,
  "type": "Feature",
  "properties": {
    "tgn:hierarchy":[
        "tgn:2483789",
        "tgn:1000001",
        "tgn:2002107",
        "tgn:7012149",
        "tgn:7007827",
        "tgn:7029392"
    ],
    "tgn:id":2483789,
    "tgn:name":"Lateral Number 5",
    "tgn:placetype":[
        "aat:300006075"
    ]
},
  "bbox": [],
  "geometry": {"coordinates":[-110.1833,40.2167],"type":"Point"}
}