{
  "id": 7035976,
  "type": "Feature",
  "properties": {
    "tgn:hierarchy":[
        "tgn:7035976",
        "tgn:7002991",
        "tgn:1000003",
        "tgn:7002997",
        "tgn:1000080",
        "tgn:7029392"
    ],
    "tgn:id":7035976,
    "tgn:name":"Ambata, Forcella d'",
    "tgn:placetype":[
        "aat:300259572"
    ]
},
  "bbox": [],
  "geometry": {"coordinates":[12.427222,46.606944],"type":"Point"}
}