{
  "id": 2711837,
  "type": "Feature",
  "properties": {
    "tgn:hierarchy":[
        "tgn:2711837",
        "tgn:1000001",
        "tgn:7012149",
        "tgn:1002354",
        "tgn:7007255",
        "tgn:7029392"
    ],
    "tgn:id":2711837,
    "tgn:name":"Tarkiln Creek",
    "tgn:placetype":[
        "aat:300008706"
    ]
},
  "bbox": [],
  "geometry": {"coordinates":[-83.1667,38.25],"type":"Point"}
}