<<<<<<< HEAD
{
  "id": 7364427,
  "type": "Feature",
  "properties": {
    "tgn:hierarchy":[
        "tgn:7364427",
        "tgn:1000001",
        "tgn:7005597",
        "tgn:7005560",
        "tgn:7029392"
    ],
    "tgn:id":7364427,
    "tgn:name":"El Sarnoso, Cerro",
    "tgn:placetype":[
        "aat:300008777"
    ]
},
  "bbox": [],
  "geometry": {"coordinates":[-98.716667,24.866667],"type":"Point"}
}
=======
{"geometry":{"type":"Point","coordinates":[-98.716667,24.866667]},"type":"Feature","properties":{"hierarchy":["tgn:7364427","tgn:1000001","tgn:7005597","tgn:7005560","tgn:7029392"],"placetype":["aat:300008777"],"id":7364427,"name:xx":"El Sarnoso, Cerro"}}
>>>>>>> 03f74aca74312dbeaf24d7e61306dd6a786dc3d0
