{
  "id": 7099231,
  "type": "Feature",
  "properties": {
    "tgn:hierarchy":[
        "tgn:7099231",
        "tgn:1000003",
        "tgn:7003682",
        "tgn:7000084",
        "tgn:7029392"
    ],
    "tgn:id":7099231,
    "tgn:name":"Selbach",
    "tgn:placetype":[
        "aat:300008347"
    ]
},
  "bbox": [],
  "geometry": {"coordinates":[7.75,50.75],"type":"Point"}
}