{
  "id": 7099443,
  "type": "Feature",
  "properties": {
    "tgn:hierarchy":[
        "tgn:7099443",
        "tgn:7003669",
        "tgn:1000003",
        "tgn:7000084",
        "tgn:7029392"
    ],
    "tgn:id":7099443,
    "tgn:name":"Seinsheim",
    "tgn:placetype":[
        "aat:300008347"
    ]
},
  "bbox": [],
  "geometry": {"coordinates":[10.216667,49.633333],"type":"Point"}
}