<<<<<<< HEAD
{
  "id": 7358654,
  "type": "Feature",
  "properties": {
    "tgn:hierarchy":[
        "tgn:7358654",
        "tgn:7005583",
        "tgn:1000001",
        "tgn:7005560",
        "tgn:7029392"
    ],
    "tgn:id":7358654,
    "tgn:name":"Colorado, Alto",
    "tgn:placetype":[
        "aat:300008795"
    ]
},
  "bbox": [],
  "geometry": {"coordinates":[-105.583333,24.083333],"type":"Point"}
}
=======
{"geometry":{"type":"Point","coordinates":[-105.583333,24.083333]},"type":"Feature","properties":{"hierarchy":["tgn:7358654","tgn:7005583","tgn:1000001","tgn:7005560","tgn:7029392"],"placetype":["aat:300008795"],"id":7358654,"name:xx":"Colorado, Alto"}}
>>>>>>> 03f74aca74312dbeaf24d7e61306dd6a786dc3d0
