<<<<<<< HEAD
{
  "id": 7245196,
  "type": "Feature",
  "properties": {
    "tgn:hierarchy":[
        "tgn:7245196",
        "tgn:7018239",
        "tgn:1000003",
        "tgn:1000063",
        "tgn:7018236",
        "tgn:7029392"
    ],
    "tgn:id":7245196,
    "tgn:name":"Achterheide",
    "tgn:placetype":[
        "aat:300008347"
    ]
},
  "bbox": [],
  "geometry": {"coordinates":[4.7,50.95],"type":"Point"}
}
=======
{"geometry":{"type":"Point","coordinates":[4.700000,50.950000]},"type":"Feature","properties":{"hierarchy":["tgn:7245196","tgn:7018239","tgn:1000003","tgn:1000063","tgn:7018236","tgn:7029392"],"placetype":["aat:300008347"],"id":7245196,"name:xx":"Achterheide"}}
>>>>>>> 03f74aca74312dbeaf24d7e61306dd6a786dc3d0
