{
  "id": 2134186,
  "type": "Feature",
  "properties": {
    "tgn:hierarchy":[
        "tgn:2134186",
        "tgn:1000001",
        "tgn:7012149",
        "tgn:1002636",
        "tgn:7007708",
        "tgn:7029392"
    ],
    "tgn:id":2134186,
    "tgn:name":"Ankeny Hill",
    "tgn:placetype":[
        "aat:300266640"
    ]
},
  "bbox": [],
  "geometry": {"coordinates":[-123.05,44.8167],"type":"Point"}
}