{
  "id": 2273507,
  "type": "Feature",
  "properties": {
    "tgn:hierarchy":[
        "tgn:2273507",
        "tgn:7002659",
        "tgn:1000001",
        "tgn:7012149",
        "tgn:2000029",
        "tgn:7029392"
    ],
    "tgn:id":2273507,
    "tgn:name":"Cypress Pond",
    "tgn:placetype":[
        "aat:300008905"
    ]
},
  "bbox": [],
  "geometry": {"coordinates":[-88.0833,34.45],"type":"Point"}
}