{
  "id": 7199722,
  "type": "Feature",
  "properties": {
    "tgn:hierarchy":[
        "tgn:7199722",
        "tgn:1000003",
        "tgn:7003689",
        "tgn:7000084",
        "tgn:7029392"
    ],
    "tgn:id":7199722,
    "tgn:name":"Eichel-Berg",
    "tgn:placetype":[
        "aat:300008777"
    ]
},
  "bbox": [],
  "geometry": {"coordinates":[10.283333,51.016667],"type":"Point"}
}