{
  "id": 2750908,
  "type": "Feature",
  "properties": {
    "tgn:hierarchy":[
        "tgn:2750908",
        "tgn:1000001",
        "tgn:7012149",
        "tgn:2002053",
        "tgn:7007826",
        "tgn:7029392"
    ],
    "tgn:id":2750908,
    "tgn:name":"Ward Mountain",
    "tgn:placetype":[
        "aat:300008798"
    ]
},
  "bbox": [],
  "geometry": {"coordinates":[-98.25,32.6333],"type":"Point"}
}