{
  "id": 7437701,
  "type": "Feature",
  "properties": {
    "tgn:hierarchy":[
        "tgn:7437701",
        "tgn:1000001",
        "tgn:1001960",
        "tgn:7005560",
        "tgn:7029392"
    ],
    "tgn:id":7437701,
    "tgn:name":"Tinajera",
    "tgn:placetype":[
        "aat:300008347"
    ]
},
  "bbox": [],
  "geometry": {"coordinates":[-110.016667,27.55],"type":"Point"}
}