{
  "id": 2416429,
  "type": "Feature",
  "properties": {
    "tgn:hierarchy":[
        "tgn:2416429",
        "tgn:1000001",
        "tgn:7012149",
        "tgn:1002597",
        "tgn:7007826",
        "tgn:7029392"
    ],
    "tgn:id":2416429,
    "tgn:name":"Jack Brown Lake",
    "tgn:placetype":[
        "aat:300006191"
    ]
},
  "bbox": [],
  "geometry": {"coordinates":[-96.45,31.3833],"type":"Point"}
}