<<<<<<< HEAD
{
  "id": 7021952,
  "type": "Feature",
  "properties": {
    "tgn:hierarchy":[
        "tgn:7021952",
        "tgn:1000001",
        "tgn:7006451",
        "tgn:7012149",
        "tgn:2000097",
        "tgn:7029392"
    ],
    "tgn:id":7021952,
    "tgn:name":"Fish Creek Mountain",
    "tgn:placetype":[
        "aat:300008798"
    ]
},
  "bbox": [],
  "geometry": {"coordinates":[-111.25,33.5],"type":"Point"}
}
=======
{"geometry":{"type":"Point","coordinates":[-111.250000,33.500000]},"type":"Feature","properties":{"hierarchy":["tgn:7021952","tgn:1000001","tgn:7006451","tgn:7012149","tgn:2000097","tgn:7029392"],"placetype":["aat:300008798"],"id":7021952,"name:xx":"Fish Creek Mountain"}}
>>>>>>> 03f74aca74312dbeaf24d7e61306dd6a786dc3d0
