{
  "id": 2287951,
  "type": "Feature",
  "properties": {
    "tgn:hierarchy":[
        "tgn:2287951",
        "tgn:1000001",
        "tgn:7012149",
        "tgn:2000224",
        "tgn:7007158",
        "tgn:7029392"
    ],
    "tgn:id":2287951,
    "tgn:name":"Dinero Tunnel",
    "tgn:placetype":[
        "aat:300000390"
    ]
},
  "bbox": [],
  "geometry": {"coordinates":[-106.3667,39.25],"type":"Point"}
}