{
  "id": 2565577,
  "type": "Feature",
  "properties": {
    "tgn:hierarchy":[
        "tgn:2565577",
        "tgn:1000001",
        "tgn:7012149",
        "tgn:1002632",
        "tgn:7007251",
        "tgn:7029392"
    ],
    "tgn:id":2565577,
    "tgn:name":"Paintrock Creek",
    "tgn:placetype":[
        "aat:300008706"
    ]
},
  "bbox": [],
  "geometry": {"coordinates":[-88.8333,38.5167],"type":"Point"}
}