{
  "id": 7538503,
  "type": "Feature",
  "properties": {
    "tgn:hierarchy":[
        "tgn:7538503",
        "tgn:7001242",
        "tgn:7001311",
        "tgn:7016833",
        "tgn:7029392"
    ],
    "tgn:id":7538503,
    "tgn:name:en":"Romit, W\u00e2di",
    "tgn:placetype":[
        "aat:300379998"
    ]
},
  "bbox": [],
  "geometry": {"coordinates":[34.940737,24.380292],"type":"Point"}
}