{
  "id": 7594152,
  "type": "Feature",
  "properties": {
    "tgn:hierarchy":[
        "tgn:7594152",
        "tgn:1001262",
        "tgn:1000004",
        "tgn:7018456",
        "tgn:1000144",
        "tgn:7029392"
    ],
    "tgn:id":7594152,
    "tgn:name":"Gedikli H\u00fcy\u00fck",
    "tgn:placetype":[
        "aat:300000810",
        "aat:300008024"
    ]
},
  "bbox": [],
  "geometry": {"coordinates":[36.806115,37.210016],"type":"Point"}
}