{
  "id": 7560725,
  "type": "Feature",
  "properties": {
    "tgn:hierarchy":[
        "tgn:7560725",
        "tgn:1000004",
        "tgn:7000198",
        "tgn:7016722",
        "tgn:7029392"
    ],
    "tgn:id":7560725,
    "tgn:name:en":"Bhol\u0101nagaria",
    "tgn:placetype":[
        "aat:300008347"
    ]
},
  "bbox": [],
  "geometry": {"coordinates":[79.474717,27.192845],"type":"Point"}
}