{
  "id": 2679237,
  "type": "Feature",
  "properties": {
    "tgn:hierarchy":[
        "tgn:2679237",
        "tgn:1000001",
        "tgn:2002103",
        "tgn:7012149",
        "tgn:7007827",
        "tgn:7029392"
    ],
    "tgn:id":2679237,
    "tgn:name":"South Fork Little Bear River",
    "tgn:placetype":[
        "aat:300008707"
    ]
},
  "bbox": [],
  "geometry": {"coordinates":[-111.8167,41.3833],"type":"Point"}
}