{
  "id": 2634726,
  "type": "Feature",
  "properties": {
    "tgn:hierarchy":[
        "tgn:2634726",
        "tgn:1000001",
        "tgn:1002316",
        "tgn:7012149",
        "tgn:7007922",
        "tgn:7029392"
    ],
    "tgn:id":2634726,
    "tgn:name":"Rutland Branch",
    "tgn:placetype":[
        "aat:300008699"
    ]
},
  "bbox": [],
  "geometry": {"coordinates":[-89.3333,42.8833],"type":"Point"}
}