{
  "id": 7546975,
  "type": "Feature",
  "properties": {
    "tgn:hierarchy":[
        "tgn:7546975",
        "tgn:1000004",
        "tgn:1001869",
        "tgn:7000198",
        "tgn:7029392"
    ],
    "tgn:id":7546975,
    "tgn:name:en":"Adw\u0101l",
    "tgn:placetype":[
        "aat:300008347"
    ]
},
  "bbox": [],
  "geometry": {"coordinates":[71.916667,22.433333],"type":"Point"}
}