{
  "id": 2372821,
  "type": "Feature",
  "properties": {
    "tgn:hierarchy":[
        "tgn:2372821",
        "tgn:1000001",
        "tgn:7016172",
        "tgn:7012149",
        "tgn:2000137",
        "tgn:7029392"
    ],
    "tgn:id":2372821,
    "tgn:name":"Hall Prospect",
    "tgn:placetype":[
        "aat:300000390"
    ]
},
  "bbox": [],
  "geometry": {"coordinates":[-91.7667,35.95],"type":"Point"}
}