{
  "id": 7388381,
  "type": "Feature",
  "properties": {
    "tgn:hierarchy":[
        "tgn:7388381",
        "tgn:1000001",
        "tgn:7005595",
        "tgn:7005560",
        "tgn:7029392"
    ],
    "tgn:id":7388381,
    "tgn:name":"Puerto Viejo, Bah\u00eda de",
    "tgn:placetype":[
        "aat:300132316"
    ]
},
  "bbox": [],
  "geometry": {"coordinates":[-106.45,23.216667],"type":"Point"}
}