<<<<<<< HEAD
{
  "id": 2156580,
  "type": "Feature",
  "properties": {
    "tgn:hierarchy":[
        "tgn:2156580",
        "tgn:1000001",
        "tgn:2002146",
        "tgn:7012149",
        "tgn:7007919",
        "tgn:7029392"
    ],
    "tgn:id":2156580,
    "tgn:name":"Bearwallow Creek",
    "tgn:placetype":[
        "aat:300008706"
    ]
},
  "bbox": [],
  "geometry": {"coordinates":[-79.6667,37.4833],"type":"Point"}
}
=======
{"geometry":{"type":"Point","coordinates":[-79.666700,37.483300]},"type":"Feature","properties":{"hierarchy":["tgn:2156580","tgn:1000001","tgn:2002146","tgn:7012149","tgn:7007919","tgn:7029392"],"placetype":["aat:300008706"],"id":2156580,"name:xx":"Bearwallow Creek"}}
>>>>>>> 03f74aca74312dbeaf24d7e61306dd6a786dc3d0
