{
  "id": 2156580,
  "type": "Feature",
  "properties": {
    "tgn:hierarchy":[
        "tgn:2156580",
        "tgn:1000001",
        "tgn:2002146",
        "tgn:7012149",
        "tgn:7007919",
        "tgn:7029392"
    ],
    "tgn:id":2156580,
    "tgn:name":"Bearwallow Creek",
    "tgn:placetype":[
        "aat:300008706"
    ]
},
  "bbox": [],
  "geometry": {"coordinates":[-79.6667,37.4833],"type":"Point"}
}