{
  "id": 7536336,
  "type": "Feature",
  "properties": {
    "tgn:hierarchy":[
        "tgn:7536336",
        "tgn:7001242",
        "tgn:7001311",
        "tgn:7016833",
        "tgn:7029392"
    ],
    "tgn:id":7536336,
    "tgn:name:en":"Ghur\u0101b, Sa\u0163\u1e29",
    "tgn:placetype":[
        "aat:300132339"
    ]
},
  "bbox": [],
  "geometry": {"coordinates":[31.097025,28.993133],"type":"Point"}
}