{
  "id": 2098853,
  "type": "Feature",
  "properties": {
    "tgn:hierarchy":[
        "tgn:2098853",
        "tgn:1000001",
        "tgn:7012149",
        "tgn:2001865",
        "tgn:7007825",
        "tgn:7029392"
    ],
    "tgn:id":2098853,
    "tgn:name":"Dotson",
    "tgn:placetype":[
        "aat:300008347",
        "aat:300387210"
    ]
},
  "bbox": [],
  "geometry": {"coordinates":[-83.4833,36.3333],"type":"Point"}
}