{
  "id": 2642096,
  "type": "Feature",
  "properties": {
    "tgn:hierarchy":[
        "tgn:2642096",
        "tgn:7014651",
        "tgn:1000001",
        "tgn:7012149",
        "tgn:7007516",
        "tgn:7029392"
    ],
    "tgn:id":2642096,
    "tgn:name":"Sand Point Marsh",
    "tgn:placetype":[
        "aat:300008905"
    ]
},
  "bbox": [],
  "geometry": {"coordinates":[-76.5167,38.8667],"type":"Point"}
}