{
  "id": 7086186,
  "type": "Feature",
  "properties": {
    "tgn:hierarchy":[
        "tgn:7086186",
        "tgn:1000003",
        "tgn:7003687",
        "tgn:7000084",
        "tgn:7029392"
    ],
    "tgn:id":7086186,
    "tgn:name":"Weidenbach",
    "tgn:placetype":[
        "aat:300008347"
    ]
},
  "bbox": [],
  "geometry": {"coordinates":[11.666667,51.383333],"type":"Point"}
}