{
  "id": 7536892,
  "type": "Feature",
  "properties": {
    "tgn:hierarchy":[
        "tgn:7536892",
        "tgn:7001242",
        "tgn:7016833",
        "tgn:1001087",
        "tgn:7029392"
    ],
    "tgn:id":7536892,
    "tgn:name:en":"Kafr B\u016b al \u1e28asan",
    "tgn:placetype":[
        "aat:300008347"
    ]
},
  "bbox": [],
  "geometry": {"coordinates":[31.093024,30.567257],"type":"Point"}
}