{
  "id": 2407129,
  "type": "Feature",
  "properties": {
    "tgn:hierarchy":[
        "tgn:2407129",
        "tgn:1000001",
        "tgn:7012149",
        "tgn:2000390",
        "tgn:7007248",
        "tgn:7029392"
    ],
    "tgn:id":2407129,
    "tgn:name":"Hunters Crossroad",
    "tgn:placetype":[
        "aat:300008347"
    ]
},
  "bbox": [],
  "geometry": {"coordinates":[-84.75,32.95],"type":"Point"}
}