<<<<<<< HEAD
{
  "id": 7352150,
  "type": "Feature",
  "properties": {
    "tgn:hierarchy":[
        "tgn:7352150",
        "tgn:1000001",
        "tgn:7005589",
        "tgn:7005560",
        "tgn:7029392"
    ],
    "tgn:id":7352150,
    "tgn:name":"Altamira",
    "tgn:placetype":[
        "aat:300008347"
    ]
},
  "bbox": [],
  "geometry": {"coordinates":[-99.781944,24.921111],"type":"Point"}
}
=======
{"geometry":{"type":"Point","coordinates":[-99.781944,24.921111]},"type":"Feature","properties":{"hierarchy":["tgn:7352150","tgn:1000001","tgn:7005589","tgn:7005560","tgn:7029392"],"placetype":["aat:300008347"],"id":7352150,"name:xx":"Altamira"}}
>>>>>>> 03f74aca74312dbeaf24d7e61306dd6a786dc3d0
