<<<<<<< HEAD
{
  "id": 2401393,
  "type": "Feature",
  "properties": {
    "tgn:hierarchy":[
        "tgn:2401393",
        "tgn:1000001",
        "tgn:7012149",
        "tgn:2002379",
        "tgn:7007923",
        "tgn:7029392"
    ],
    "tgn:id":2401393,
    "tgn:name":"Horses Head",
    "tgn:placetype":[
        "aat:300008798"
    ]
},
  "bbox": [],
  "geometry": {"coordinates":[-109.6833,44.1833],"type":"Point"}
}
=======
{"geometry":{"type":"Point","coordinates":[-109.683300,44.183300]},"type":"Feature","properties":{"hierarchy":["tgn:2401393","tgn:1000001","tgn:7012149","tgn:2002379","tgn:7007923","tgn:7029392"],"placetype":["aat:300008798"],"id":2401393,"name:xx":"Horses Head"}}
>>>>>>> 03f74aca74312dbeaf24d7e61306dd6a786dc3d0
