{
  "id": 7393157,
  "type": "Feature",
  "properties": {
    "tgn:hierarchy":[
        "tgn:7393157",
        "tgn:1000001",
        "tgn:7005594",
        "tgn:7005560",
        "tgn:7029392"
    ],
    "tgn:id":7393157,
    "tgn:name":"San Francisco",
    "tgn:placetype":[
        "aat:300008347"
    ]
},
  "bbox": [],
  "geometry": {"coordinates":[-100.983333,22.933333],"type":"Point"}
}