{
  "id": 7397480,
  "type": "Feature",
  "properties": {
    "tgn:hierarchy":[
        "tgn:7397480",
        "tgn:1000001",
        "tgn:1001960",
        "tgn:7005560",
        "tgn:7029392"
    ],
    "tgn:id":7397480,
    "tgn:name":"Rancho Santa Rosa",
    "tgn:placetype":[
        "aat:300000241"
    ]
},
  "bbox": [],
  "geometry": {"coordinates":[-112.55,31.783333],"type":"Point"}
}