<<<<<<< HEAD
{
  "id": 7115518,
  "type": "Feature",
  "properties": {
    "tgn:hierarchy":[
        "tgn:7115518",
        "tgn:1000003",
        "tgn:7003676",
        "tgn:7000084",
        "tgn:7029392"
    ],
    "tgn:id":7115518,
    "tgn:name":"Oster-Berg",
    "tgn:placetype":[
        "aat:300008777"
    ]
},
  "bbox": [],
  "geometry": {"coordinates":[10.366667,52.366667],"type":"Point"}
}
=======
{"geometry":{"type":"Point","coordinates":[10.366667,52.366667]},"type":"Feature","properties":{"hierarchy":["tgn:7115518","tgn:1000003","tgn:7003676","tgn:7000084","tgn:7029392"],"placetype":["aat:300008777"],"id":7115518,"name:xx":"Oster-Berg"}}
>>>>>>> 03f74aca74312dbeaf24d7e61306dd6a786dc3d0
