{
  "id": 2004562,
  "type": "Feature",
  "properties": {
    "tgn:hierarchy":[
        "tgn:2004562",
        "tgn:7002659",
        "tgn:1000001",
        "tgn:7012149",
        "tgn:2000054",
        "tgn:7029392"
    ],
    "tgn:id":2004562,
    "tgn:name":"Monticello",
    "tgn:placetype":[
        "aat:300008347",
        "aat:300387210"
    ]
},
  "bbox": [],
  "geometry": {"coordinates":[-85.7667,31.8167],"type":"Point"}
}