<<<<<<< HEAD
{
  "id": 7025181,
  "type": "Feature",
  "properties": {
    "tgn:hierarchy":[
        "tgn:7025181",
        "tgn:7002445",
        "tgn:1000003",
        "tgn:7008118",
        "tgn:7008591",
        "tgn:7029392"
    ],
    "tgn:id":7025181,
    "tgn:name:ang":"Aitun",
    "tgn:placetype":[
        "aat:300008347"
    ]
},
  "bbox": [],
  "geometry": {"coordinates":[-1.8333,52.9333],"type":"Point"}
}
=======
{"geometry":{"type":"Point","coordinates":[-1.833300,52.933300]},"type":"Feature","properties":{"hierarchy":["tgn:7025181","tgn:7002445","tgn:1000003","tgn:7008118","tgn:7008591","tgn:7029392"],"placetype":["aat:300008347"],"id":7025181,"name:ang":"Aitun"}}
>>>>>>> 03f74aca74312dbeaf24d7e61306dd6a786dc3d0
