{
  "id": 2585913,
  "type": "Feature",
  "properties": {
    "tgn:hierarchy":[
        "tgn:2585913",
        "tgn:1000001",
        "tgn:1002239",
        "tgn:7012149",
        "tgn:7007706",
        "tgn:7029392"
    ],
    "tgn:id":2585913,
    "tgn:name":"Pipes Fork",
    "tgn:placetype":[
        "aat:300008699"
    ]
},
  "bbox": [],
  "geometry": {"coordinates":[-81.0167,40.5833],"type":"Point"}
}