{
  "id": 2698697,
  "type": "Feature",
  "properties": {
    "tgn:hierarchy":[
        "tgn:2698697",
        "tgn:1000001",
        "tgn:7012149",
        "tgn:2002371",
        "tgn:7007923",
        "tgn:7029392"
    ],
    "tgn:id":2698697,
    "tgn:name":"Stratton Hollow",
    "tgn:placetype":[
        "aat:300386845"
    ]
},
  "bbox": [],
  "geometry": {"coordinates":[-107.6333,42.2667],"type":"Point"}
}