{
  "id": 2567350,
  "type": "Feature",
  "properties": {
    "tgn:hierarchy":[
        "tgn:2567350",
        "tgn:1000001",
        "tgn:7012149",
        "tgn:2001544",
        "tgn:7007709",
        "tgn:7029392"
    ],
    "tgn:id":2567350,
    "tgn:name":"Panthertail Mountain",
    "tgn:placetype":[
        "aat:300008798"
    ]
},
  "bbox": [],
  "geometry": {"coordinates":[-82.9667,35.15],"type":"Point"}
}