{
  "id": 2030768,
  "type": "Feature",
  "properties": {
    "tgn:hierarchy":[
        "tgn:2030768",
        "tgn:1000001",
        "tgn:1002186",
        "tgn:7012149",
        "tgn:7007251",
        "tgn:7029392"
    ],
    "tgn:id":2030768,
    "tgn:name":"Woburn",
    "tgn:placetype":[
        "aat:300008347"
    ]
},
  "bbox": [],
  "geometry": {"coordinates":[-89.3333,38.95],"type":"Point"}
}