{
  "id": 2636242,
  "type": "Feature",
  "properties": {
    "tgn:hierarchy":[
        "tgn:2636242",
        "tgn:1000001",
        "tgn:7012149",
        "tgn:7007157",
        "tgn:1002608",
        "tgn:7029392"
    ],
    "tgn:id":2636242,
    "tgn:name":"Saddleback Butte",
    "tgn:placetype":[
        "aat:300008798"
    ]
},
  "bbox": [],
  "geometry": {"coordinates":[-117.7833,34.6667],"type":"Point"}
}