{
  "id": 1088210,
  "type": "Feature",
  "properties": {
    "tgn:hierarchy":[
        "tgn:1088210",
        "tgn:1001189",
        "tgn:7001242",
        "tgn:1000153",
        "tgn:7029392"
    ],
    "tgn:id":1088210,
    "tgn:name":"Kribi",
    "tgn:placetype":[
        "aat:300008347"
    ]
},
  "bbox": [],
  "geometry": {"coordinates":[9.9333,2.9333],"type":"Point"}
}