{
  "id": 2272468,
  "type": "Feature",
  "properties": {
    "tgn:hierarchy":[
        "tgn:2272468",
        "tgn:1000001",
        "tgn:7012149",
        "tgn:1002821",
        "tgn:7007568",
        "tgn:7029392"
    ],
    "tgn:id":2272468,
    "tgn:name":"Curtis Mountain",
    "tgn:placetype":[
        "aat:300008798"
    ]
},
  "bbox": [],
  "geometry": {"coordinates":[-73.5333,42.5167],"type":"Point"}
}