{
  "id": 2331380,
  "type": "Feature",
  "properties": {
    "tgn:hierarchy":[
        "tgn:2331380",
        "tgn:1000001",
        "tgn:7012149",
        "tgn:2002188",
        "tgn:7007919",
        "tgn:7029392"
    ],
    "tgn:id":2331380,
    "tgn:name":"Flatrock",
    "tgn:placetype":[
        "aat:300008347"
    ]
},
  "bbox": [],
  "geometry": {"coordinates":[-81.9667,37.05],"type":"Point"}
}