<<<<<<< HEAD
{
  "id": 2331380,
  "type": "Feature",
  "properties": {
    "tgn:hierarchy":[
        "tgn:2331380",
        "tgn:1000001",
        "tgn:7012149",
        "tgn:2002188",
        "tgn:7007919",
        "tgn:7029392"
    ],
    "tgn:id":2331380,
    "tgn:name":"Flatrock",
    "tgn:placetype":[
        "aat:300008347"
    ]
},
  "bbox": [],
  "geometry": {"coordinates":[-81.9667,37.05],"type":"Point"}
}
=======
{"geometry":{"type":"Point","coordinates":[-81.966700,37.050000]},"type":"Feature","properties":{"hierarchy":["tgn:2331380","tgn:1000001","tgn:7012149","tgn:2002188","tgn:7007919","tgn:7029392"],"placetype":["aat:300008347"],"id":2331380,"name:xx":"Flatrock"}}
>>>>>>> 03f74aca74312dbeaf24d7e61306dd6a786dc3d0
