{
  "id": 7345370,
  "type": "Feature",
  "properties": {
    "tgn:hierarchy":[
        "tgn:7345370",
        "tgn:7002847",
        "tgn:1001647",
        "tgn:1000003",
        "tgn:1000095",
        "tgn:7029392"
    ],
    "tgn:id":7345370,
    "tgn:name":"Alcaudete de la Jaya",
    "tgn:placetype":[
        "aat:300008347"
    ]
},
  "bbox": [],
  "geometry": {"coordinates":[-4.866667,39.783333],"type":"Point"}
}