{
  "id": 7394931,
  "type": "Feature",
  "properties": {
    "tgn:hierarchy":[
        "tgn:7394931",
        "tgn:1000001",
        "tgn:7005591",
        "tgn:7005560",
        "tgn:7029392"
    ],
    "tgn:id":7394931,
    "tgn:name":"San Antonio",
    "tgn:placetype":[
        "aat:300008347"
    ]
},
  "bbox": [],
  "geometry": {"coordinates":[-95.483333,16.566667],"type":"Point"}
}