{
  "id": 7109200,
  "type": "Feature",
  "properties": {
    "tgn:hierarchy":[
        "tgn:7109200",
        "tgn:7003692",
        "tgn:1000003",
        "tgn:7000084",
        "tgn:7029392"
    ],
    "tgn:id":7109200,
    "tgn:name":"Rannwald",
    "tgn:placetype":[
        "aat:300008863"
    ]
},
  "bbox": [],
  "geometry": {"coordinates":[8.616667,48.916667],"type":"Point"}
}