{
  "id": 7545441,
  "type": "Feature",
  "properties": {
    "tgn:hierarchy":[
        "tgn:7545441",
        "tgn:1000004",
        "tgn:7000198",
        "tgn:1001977",
        "tgn:7029392"
    ],
    "tgn:id":7545441,
    "tgn:name:en":"B\u0101rnia",
    "tgn:placetype":[
        "aat:300008347"
    ]
},
  "bbox": [],
  "geometry": {"coordinates":[88.421336,23.724479],"type":"Point"}
}