{
  "id": 2352062,
  "type": "Feature",
  "properties": {
    "tgn:hierarchy":[
        "tgn:2352062",
        "tgn:1000001",
        "tgn:7012149",
        "tgn:2002122",
        "tgn:7007827",
        "tgn:7029392"
    ],
    "tgn:id":2352062,
    "tgn:name":"Glory Hole",
    "tgn:placetype":[
        "aat:300386845"
    ]
},
  "bbox": [],
  "geometry": {"coordinates":[-111.6333,40.7667],"type":"Point"}
}