{
  "id": 2159461,
  "type": "Feature",
  "properties": {
    "tgn:hierarchy":[
        "tgn:2159461",
        "tgn:1000001",
        "tgn:1002500",
        "tgn:7012149",
        "tgn:7007240",
        "tgn:7029392"
    ],
    "tgn:id":2159461,
    "tgn:name":"Bee Gum Point",
    "tgn:placetype":[
        "aat:300008850"
    ]
},
  "bbox": [],
  "geometry": {"coordinates":[-80.3833,27.6833],"type":"Point"}
}