{
  "id": 2746823,
  "type": "Feature",
  "properties": {
    "tgn:hierarchy":[
        "tgn:2746823",
        "tgn:1000001",
        "tgn:7012149",
        "tgn:2000927",
        "tgn:7007515",
        "tgn:7029392"
    ],
    "tgn:id":2746823,
    "tgn:name":"Wadleigh Pond",
    "tgn:placetype":[
        "aat:300008680"
    ]
},
  "bbox": [],
  "geometry": {"coordinates":[-68.8167,45.6667],"type":"Point"}
}