{
  "id": 7478501,
  "type": "Feature",
  "properties": {
    "tgn:hierarchy":[
        "tgn:7478501",
        "tgn:1000004",
        "tgn:7489179",
        "tgn:1000141",
        "tgn:7029392"
    ],
    "tgn:id":7478501,
    "tgn:name":"Xiaowei Guoxiao",
    "tgn:placetype":[
        "aat:300006495"
    ]
},
  "bbox": [],
  "geometry": {"coordinates":[121.811982,24.696432],"type":"Point"}
}