<<<<<<< HEAD
{
  "id": 2408091,
  "type": "Feature",
  "properties": {
    "tgn:hierarchy":[
        "tgn:2408091",
        "tgn:1000001",
        "tgn:7016172",
        "tgn:7012149",
        "tgn:2000161",
        "tgn:7029392"
    ],
    "tgn:id":2408091,
    "tgn:name":"Hurricane Knob",
    "tgn:placetype":[
        "aat:300008798"
    ]
},
  "bbox": [],
  "geometry": {"coordinates":[-93.9667,34.4167],"type":"Point"}
}
=======
{"geometry":{"type":"Point","coordinates":[-93.966700,34.416700]},"type":"Feature","properties":{"hierarchy":["tgn:2408091","tgn:1000001","tgn:7016172","tgn:7012149","tgn:2000161","tgn:7029392"],"placetype":["aat:300008798"],"id":2408091,"name:xx":"Hurricane Knob"}}
>>>>>>> 03f74aca74312dbeaf24d7e61306dd6a786dc3d0
