{
  "id": 2594230,
  "type": "Feature",
  "properties": {
    "tgn:hierarchy":[
        "tgn:2594230",
        "tgn:1000001",
        "tgn:7012149",
        "tgn:1002700",
        "tgn:7007520",
        "tgn:7029392"
    ],
    "tgn:id":2594230,
    "tgn:name":"Porter Drain",
    "tgn:placetype":[
        "aat:300006075"
    ]
},
  "bbox": [],
  "geometry": {"coordinates":[-85.9667,43.2167],"type":"Point"}
}