{
  "id": 7227642,
  "type": "Feature",
  "properties": {
    "tgn:hierarchy":[
        "tgn:7227642",
        "tgn:7002680",
        "tgn:7001395",
        "tgn:1000003",
        "tgn:1000074",
        "tgn:7029392"
    ],
    "tgn:id":7227642,
    "tgn:name":"K\u00e1to Arakhov\u00edtika",
    "tgn:placetype":[
        "aat:300008347"
    ]
},
  "bbox": [],
  "geometry": {"coordinates":[21.85,38.333333],"type":"Point"}
}