{
  "id": 7038617,
  "type": "Feature",
  "properties": {
    "tgn:hierarchy":[
        "tgn:7038617",
        "tgn:1003450",
        "tgn:7007850",
        "tgn:1000003",
        "tgn:1000080",
        "tgn:7029392"
    ],
    "tgn:id":7038617,
    "tgn:name":"Masseria Terrianna",
    "tgn:placetype":[
        "aat:300000206"
    ]
},
  "bbox": [],
  "geometry": {"coordinates":[16.583333,39.916667],"type":"Point"}
}