{
  "id": 7415578,
  "type": "Feature",
  "properties": {
    "tgn:hierarchy":[
        "tgn:7415578",
        "tgn:7005584",
        "tgn:1000001",
        "tgn:7005560",
        "tgn:7029392"
    ],
    "tgn:id":7415578,
    "tgn:name":"San Jos\u00e9 de la Laguna",
    "tgn:placetype":[
        "aat:300008347"
    ]
},
  "bbox": [],
  "geometry": {"coordinates":[-100.671667,20.938333],"type":"Point"}
}