{
  "id": 2178396,
  "type": "Feature",
  "properties": {
    "tgn:hierarchy":[
        "tgn:2178396",
        "tgn:1000001",
        "tgn:1002267",
        "tgn:7012149",
        "tgn:7007919",
        "tgn:7029392"
    ],
    "tgn:id":2178396,
    "tgn:name":"Blackman Creek",
    "tgn:placetype":[
        "aat:300008706"
    ]
},
  "bbox": [],
  "geometry": {"coordinates":[-77.7667,37.3833],"type":"Point"}
}