{
  "id": 2148846,
  "type": "Feature",
  "properties": {
    "tgn:hierarchy":[
        "tgn:2148846",
        "tgn:1000001",
        "tgn:7012149",
        "tgn:2002069",
        "tgn:7007826",
        "tgn:7029392"
    ],
    "tgn:id":2148846,
    "tgn:name":"Barnett Springs Creek",
    "tgn:placetype":[
        "aat:300008706"
    ]
},
  "bbox": [],
  "geometry": {"coordinates":[-98.6667,31.1167],"type":"Point"}
}