{
  "id": 7388277,
  "type": "Feature",
  "properties": {
    "tgn:hierarchy":[
        "tgn:7388277",
        "tgn:7005581",
        "tgn:1000001",
        "tgn:7005560",
        "tgn:7029392"
    ],
    "tgn:id":7388277,
    "tgn:name":"Parrale\u00f1o",
    "tgn:placetype":[
        "aat:300008347"
    ]
},
  "bbox": [],
  "geometry": {"coordinates":[-105.233333,27.666667],"type":"Point"}
}