{
  "id": 7506291,
  "type": "Feature",
  "properties": {
    "tgn:hierarchy":[
        "tgn:7506291",
        "tgn:1009227",
        "tgn:1000226",
        "tgn:7018437",
        "tgn:1000006",
        "tgn:7029392"
    ],
    "tgn:id":7506291,
    "tgn:name:en":"Rumbling Burn",
    "tgn:placetype":[
        "aat:300008699"
    ]
},
  "bbox": [],
  "geometry": {"coordinates":[169.05,-44.55],"type":"Point"}
}