{
  "id": 7464197,
  "type": "Feature",
  "properties": {
    "tgn:hierarchy":[
        "tgn:7464197",
        "tgn:7002444",
        "tgn:1000003",
        "tgn:7008082",
        "tgn:7008591",
        "tgn:7029392"
    ],
    "tgn:id":7464197,
    "tgn:name:en":"Bhearnais, Amhainn",
    "tgn:placetype":[
        "aat:300008699"
    ]
},
  "bbox": [],
  "geometry": {"coordinates":[-5.25,57.45],"type":"Point"}
}