{
  "id": 2610845,
  "type": "Feature",
  "properties": {
    "tgn:hierarchy":[
        "tgn:2610845",
        "tgn:1000001",
        "tgn:7012149",
        "tgn:7007157",
        "tgn:2000188",
        "tgn:7029392"
    ],
    "tgn:id":2610845,
    "tgn:name":"Red Gulch",
    "tgn:placetype":[
        "aat:300008761"
    ]
},
  "bbox": [],
  "geometry": {"coordinates":[-122.5167,40.6333],"type":"Point"}
}