{
  "id": 7291835,
  "type": "Feature",
  "properties": {
    "tgn:hierarchy":[
        "tgn:7291835",
        "tgn:1001695",
        "tgn:1000049",
        "tgn:1000002",
        "tgn:7029392"
    ],
    "tgn:id":7291835,
    "tgn:name":"Flores, Caj\u00f3n de",
    "tgn:placetype":[
        "aat:300008699"
    ]
},
  "bbox": [],
  "geometry": {"coordinates":[-70.25,-34.416667],"type":"Point"}
}