{
  "id": 2479835,
  "type": "Feature",
  "properties": {
    "tgn:hierarchy":[
        "tgn:2479835",
        "tgn:1000001",
        "tgn:2000458",
        "tgn:7012149",
        "tgn:7007250",
        "tgn:7029392"
    ],
    "tgn:id":2479835,
    "tgn:name":"Lake Creek Lakes",
    "tgn:placetype":[
        "aat:300008680"
    ]
},
  "bbox": [],
  "geometry": {"coordinates":[-114.3167,43.7667],"type":"Point"}
}