{
  "id": 2285008,
  "type": "Feature",
  "properties": {
    "tgn:hierarchy":[
        "tgn:2285008",
        "tgn:1000001",
        "tgn:7012149",
        "tgn:2000226",
        "tgn:7007158",
        "tgn:7029392"
    ],
    "tgn:id":2285008,
    "tgn:name":"Devil Gulch",
    "tgn:placetype":[
        "aat:300008761"
    ]
},
  "bbox": [],
  "geometry": {"coordinates":[-105.2167,40.5833],"type":"Point"}
}