<<<<<<< HEAD
{
  "id": 2403020,
  "type": "Feature",
  "properties": {
    "tgn:hierarchy":[
        "tgn:2403020",
        "tgn:1000001",
        "tgn:2001429",
        "tgn:7012149",
        "tgn:7007566",
        "tgn:7029392"
    ],
    "tgn:id":2403020,
    "tgn:name":"Houghton Tank",
    "tgn:placetype":[
        "aat:300006191"
    ]
},
  "bbox": [],
  "geometry": {"coordinates":[-108.2833,33.45],"type":"Point"}
}
=======
{"geometry":{"type":"Point","coordinates":[-108.283300,33.450000]},"type":"Feature","properties":{"hierarchy":["tgn:2403020","tgn:1000001","tgn:2001429","tgn:7012149","tgn:7007566","tgn:7029392"],"placetype":["aat:300006191"],"id":2403020,"name:xx":"Houghton Tank"}}
>>>>>>> 03f74aca74312dbeaf24d7e61306dd6a786dc3d0
