<<<<<<< HEAD
{
  "id": 7022580,
  "type": "Feature",
  "properties": {
    "tgn:hierarchy":[
        "tgn:7022580",
        "tgn:1000001",
        "tgn:7012149",
        "tgn:7007248",
        "tgn:7029392"
    ],
    "tgn:id":7022580,
    "tgn:name":"Conasauga Creek",
    "tgn:placetype":[
        "aat:300008706"
    ]
},
  "bbox": [],
  "geometry": {"coordinates":[-84.55,34.8833],"type":"Point"}
}
=======
{"geometry":{"type":"Point","coordinates":[-84.550000,34.883300]},"type":"Feature","properties":{"hierarchy":["tgn:7022580","tgn:1000001","tgn:7012149","tgn:7007248","tgn:7029392"],"placetype":["aat:300008706"],"id":7022580,"name:xx":"Conasauga Creek"}}
>>>>>>> 03f74aca74312dbeaf24d7e61306dd6a786dc3d0
