{
  "id": 2105838,
  "type": "Feature",
  "properties": {
    "tgn:hierarchy":[
        "tgn:2105838",
        "tgn:1000001",
        "tgn:2001941",
        "tgn:7012149",
        "tgn:7007826",
        "tgn:7029392"
    ],
    "tgn:id":2105838,
    "tgn:name":"Macdona",
    "tgn:placetype":[
        "aat:300008347"
    ]
},
  "bbox": [],
  "geometry": {"coordinates":[-98.6833,29.3167],"type":"Point"}
}