{
  "id": 7550826,
  "type": "Feature",
  "properties": {
    "tgn:hierarchy":[
        "tgn:7550826",
        "tgn:1000004",
        "tgn:7000198",
        "tgn:7016788",
        "tgn:7029392"
    ],
    "tgn:id":7550826,
    "tgn:name:en":"Dig\u0101wora Railroad Station",
    "tgn:placetype":[
        "aat:300007783"
    ]
},
  "bbox": [],
  "geometry": {"coordinates":[76.619259,27.321724],"type":"Point"}
}