{
  "id": 1096838,
  "type": "Feature",
  "properties": {
    "tgn:hierarchy":[
        "tgn:1096838",
        "tgn:7000490",
        "tgn:1000006",
        "tgn:7006238",
        "tgn:7029392"
    ],
    "tgn:id":1096838,
    "tgn:name":"Eltham",
    "tgn:placetype":[
        "aat:300008347"
    ]
},
  "bbox": [],
  "geometry": {"coordinates":[145.15,-37.7333],"type":"Point"}
}