{
  "id": 2483886,
  "type": "Feature",
  "properties": {
    "tgn:hierarchy":[
        "tgn:2483886",
        "tgn:1000001",
        "tgn:2001411",
        "tgn:7012149",
        "tgn:7007526",
        "tgn:7029392"
    ],
    "tgn:id":2483886,
    "tgn:name":"Latham Creek",
    "tgn:placetype":[
        "aat:300008706"
    ]
},
  "bbox": [],
  "geometry": {"coordinates":[-114.8333,40.5667],"type":"Point"}
}