{
  "id": 2248871,
  "type": "Feature",
  "properties": {
    "tgn:hierarchy":[
        "tgn:2248871",
        "tgn:1000001",
        "tgn:7012149",
        "tgn:1003038",
        "tgn:7007517",
        "tgn:7029392"
    ],
    "tgn:id":2248871,
    "tgn:name":"Coldbrook Springs",
    "tgn:placetype":[
        "aat:300008347"
    ]
},
  "bbox": [],
  "geometry": {"coordinates":[-72.0333,42.3833],"type":"Point"}
}