{
  "id": 7341858,
  "type": "Feature",
  "properties": {
    "tgn:hierarchy":[
        "tgn:7341858",
        "tgn:7002829",
        "tgn:1000003",
        "tgn:7002786",
        "tgn:1000095",
        "tgn:7029392"
    ],
    "tgn:id":7341858,
    "tgn:name":"Boedo, R\u00edo",
    "tgn:placetype":[
        "aat:300008699"
    ]
},
  "bbox": [],
  "geometry": {"coordinates":[-7.866667,43.166667],"type":"Point"}
}