{
  "id": 7497951,
  "type": "Feature",
  "properties": {
    "tgn:hierarchy":[
        "tgn:7497951",
        "tgn:7001004",
        "tgn:1000004",
        "tgn:1000141",
        "tgn:7029392"
    ],
    "tgn:id":7497951,
    "tgn:name":"Zhenxing Qiao",
    "tgn:placetype":[
        "aat:300007836"
    ]
},
  "bbox": [],
  "geometry": {"coordinates":[120.313725,22.590469],"type":"Point"}
}