{
  "id": 7384400,
  "type": "Feature",
  "properties": {
    "tgn:hierarchy":[
        "tgn:7384400",
        "tgn:7005581",
        "tgn:1000001",
        "tgn:7005560",
        "tgn:7029392"
    ],
    "tgn:id":7384400,
    "tgn:name":"Mogote, Cerro del",
    "tgn:placetype":[
        "aat:300008777"
    ]
},
  "bbox": [],
  "geometry": {"coordinates":[-105.25,27.433333],"type":"Point"}
}