{
  "id": 2264018,
  "type": "Feature",
  "properties": {
    "tgn:hierarchy":[
        "tgn:2264018",
        "tgn:1000001",
        "tgn:7012149",
        "tgn:2001969",
        "tgn:7007826",
        "tgn:7029392"
    ],
    "tgn:id":2264018,
    "tgn:name":"Coyote Peak",
    "tgn:placetype":[
        "aat:300008798"
    ]
},
  "bbox": [],
  "geometry": {"coordinates":[-104.8833,31.9833],"type":"Point"}
}