{
  "id": 7280294,
  "type": "Feature",
  "properties": {
    "tgn:hierarchy":[
        "tgn:7280294",
        "tgn:7016598",
        "tgn:1000049",
        "tgn:1000002",
        "tgn:7029392"
    ],
    "tgn:id":7280294,
    "tgn:name":"Tames, Quebrada de",
    "tgn:placetype":[
        "aat:300266554",
        "aat:300008699"
    ]
},
  "bbox": [],
  "geometry": {"coordinates":[-70.283333,-22.666667],"type":"Point"}
}