{
  "id": 7540967,
  "type": "Feature",
  "properties": {
    "tgn:hierarchy":[
        "tgn:7540967",
        "tgn:7001242",
        "tgn:7016833",
        "tgn:7001336",
        "tgn:7029392"
    ],
    "tgn:id":7540967,
    "tgn:name:en":"Ab\u016b Ruweis, W\u0101d\u012b",
    "tgn:placetype":[
        "aat:300379998"
    ]
},
  "bbox": [],
  "geometry": {"coordinates":[34.454934,28.659321],"type":"Point"}
}