{
  "id": 2251374,
  "type": "Feature",
  "properties": {
    "tgn:hierarchy":[
        "tgn:2251374",
        "tgn:1000001",
        "tgn:7016172",
        "tgn:7012149",
        "tgn:2000145",
        "tgn:7029392"
    ],
    "tgn:id":2251374,
    "tgn:name":"Comet",
    "tgn:placetype":[
        "aat:300008347"
    ]
},
  "bbox": [],
  "geometry": {"coordinates":[-94.2333,33.6833],"type":"Point"}
}