{
  "id": 7121275,
  "type": "Feature",
  "properties": {
    "tgn:hierarchy":[
        "tgn:7121275",
        "tgn:1000003",
        "tgn:7000094",
        "tgn:7000084",
        "tgn:7029392"
    ],
    "tgn:id":7121275,
    "tgn:name":"Parow",
    "tgn:placetype":[
        "aat:300008347"
    ]
},
  "bbox": [],
  "geometry": {"coordinates":[13.083333,54.35],"type":"Point"}
}