{
  "id": 7292899,
  "type": "Feature",
  "properties": {
    "tgn:hierarchy":[
        "tgn:7292899",
        "tgn:1001637",
        "tgn:1000049",
        "tgn:1000002",
        "tgn:7029392"
    ],
    "tgn:id":7292899,
    "tgn:name":"El Cruce",
    "tgn:placetype":[
        "aat:300008347"
    ]
},
  "bbox": [],
  "geometry": {"coordinates":[-72.716667,-36.283333],"type":"Point"}
}