{
  "id": 7458499,
  "type": "Feature",
  "properties": {
    "tgn:hierarchy":[
        "tgn:7458499",
        "tgn:7002445",
        "tgn:1000003",
        "tgn:7008160",
        "tgn:7008591",
        "tgn:7029392"
    ],
    "tgn:id":7458499,
    "tgn:name:en":"Pandora Sand",
    "tgn:placetype":[
        "aat:300386970"
    ]
},
  "bbox": [],
  "geometry": {"coordinates":[0.366667,52.85],"type":"Point"}
}