<<<<<<< HEAD
{
  "id": 7244126,
  "type": "Feature",
  "properties": {
    "tgn:hierarchy":[
        "tgn:7244126",
        "tgn:7003457",
        "tgn:1000003",
        "tgn:1000063",
        "tgn:7018236",
        "tgn:7029392"
    ],
    "tgn:id":7244126,
    "tgn:name":"Kakelenberg",
    "tgn:placetype":[
        "aat:300008347"
    ]
},
  "bbox": [],
  "geometry": {"coordinates":[3.883391,50.798723],"type":"Point"}
}
=======
{"geometry":{"type":"Point","coordinates":[3.883391,50.798723]},"type":"Feature","properties":{"hierarchy":["tgn:7244126","tgn:7003457","tgn:1000003","tgn:1000063","tgn:7018236","tgn:7029392"],"placetype":["aat:300008347"],"id":7244126,"name:xx":"Kakelenberg"}}
>>>>>>> 03f74aca74312dbeaf24d7e61306dd6a786dc3d0
