{
  "id": 2488476,
  "type": "Feature",
  "properties": {
    "tgn:hierarchy":[
        "tgn:2488476",
        "tgn:1000001",
        "tgn:2001413",
        "tgn:7012149",
        "tgn:7007526",
        "tgn:7029392"
    ],
    "tgn:id":2488476,
    "tgn:name":"Mahogany Hills",
    "tgn:placetype":[
        "aat:300386831"
    ]
},
  "bbox": [],
  "geometry": {"coordinates":[-116.15,39.4333],"type":"Point"}
}