{
  "id": 2461828,
  "type": "Feature",
  "properties": {
    "tgn:hierarchy":[
        "tgn:2461828",
        "tgn:1000001",
        "tgn:7006451",
        "tgn:7012149",
        "tgn:2000098",
        "tgn:7029392"
    ],
    "tgn:id":2461828,
    "tgn:name":"Little Toroweap Reservoir",
    "tgn:placetype":[
        "aat:300006191"
    ]
},
  "bbox": [],
  "geometry": {"coordinates":[-113.0333,36.45],"type":"Point"}
}