{
  "id": 1093394,
  "type": "Feature",
  "properties": {
    "tgn:hierarchy":[
        "tgn:1093394",
        "tgn:7001242",
        "tgn:7017584",
        "tgn:1000193",
        "tgn:7029392"
    ],
    "tgn:id":1093394,
    "tgn:name":"Montagu",
    "tgn:placetype":[
        "aat:300008347"
    ]
},
  "bbox": [],
  "geometry": {"coordinates":[20.1167,-33.7833],"type":"Point"}
}