{
  "id": 7288680,
  "type": "Feature",
  "properties": {
    "tgn:hierarchy":[
        "tgn:7288680",
        "tgn:1001708",
        "tgn:1000049",
        "tgn:1000002",
        "tgn:7029392"
    ],
    "tgn:id":7288680,
    "tgn:name":"Hueso de Ballena",
    "tgn:placetype":[
        "aat:300008777"
    ]
},
  "bbox": [],
  "geometry": {"coordinates":[-72.016667,-34.133333],"type":"Point"}
}