{
  "id": 2385383,
  "type": "Feature",
  "properties": {
    "tgn:hierarchy":[
        "tgn:2385383",
        "tgn:1000001",
        "tgn:2001410",
        "tgn:7012149",
        "tgn:7007526",
        "tgn:7029392"
    ],
    "tgn:id":2385383,
    "tgn:name":"Hen Spring",
    "tgn:placetype":[
        "aat:300008697"
    ]
},
  "bbox": [],
  "geometry": {"coordinates":[-114.0833,36.65],"type":"Point"}
}