{
  "id": 7511793,
  "type": "Feature",
  "properties": {
    "tgn:hierarchy":[
        "tgn:7511793",
        "tgn:1009227",
        "tgn:7001866",
        "tgn:1000226",
        "tgn:1000006",
        "tgn:7029392"
    ],
    "tgn:id":7511793,
    "tgn:name:en":"Kapunatiki Creek",
    "tgn:placetype":[
        "aat:300008699"
    ]
},
  "bbox": [],
  "geometry": {"coordinates":[171.45,-44.216667],"type":"Point"}
}