{
  "id": 2056487,
  "type": "Feature",
  "properties": {
    "tgn:hierarchy":[
        "tgn:2056487",
        "tgn:2001088",
        "tgn:1000001",
        "tgn:7012149",
        "tgn:7007522",
        "tgn:7029392"
    ],
    "tgn:id":2056487,
    "tgn:name":"Gillsburg",
    "tgn:placetype":[
        "aat:300008347"
    ]
},
  "bbox": [],
  "geometry": {"coordinates":[-90.65,31.0167],"type":"Point"}
}