<<<<<<< HEAD
{
  "id": 2259380,
  "type": "Feature",
  "properties": {
    "tgn:hierarchy":[
        "tgn:2259380",
        "tgn:1000001",
        "tgn:7012149",
        "tgn:1002545",
        "tgn:7007157",
        "tgn:7029392"
    ],
    "tgn:id":2259380,
    "tgn:name":"Cottonwood Spring",
    "tgn:placetype":[
        "aat:300008697"
    ]
},
  "bbox": [],
  "geometry": {"coordinates":[-118.6667,35.45],"type":"Point"}
}
=======
{"geometry":{"type":"Point","coordinates":[-118.666700,35.450000]},"type":"Feature","properties":{"hierarchy":["tgn:2259380","tgn:1000001","tgn:7012149","tgn:1002545","tgn:7007157","tgn:7029392"],"placetype":["aat:300008697"],"id":2259380,"name:xx":"Cottonwood Spring"}}
>>>>>>> 03f74aca74312dbeaf24d7e61306dd6a786dc3d0
