{
  "id": 7167393,
  "type": "Feature",
  "properties": {
    "tgn:hierarchy":[
        "tgn:7167393",
        "tgn:1000003",
        "tgn:7003677",
        "tgn:7000084",
        "tgn:7029392"
    ],
    "tgn:id":7167393,
    "tgn:name":"Haufe",
    "tgn:placetype":[
        "aat:300000206"
    ]
},
  "bbox": [],
  "geometry": {"coordinates":[7.45,51.116667],"type":"Point"}
}