{
  "id": 2737637,
  "type": "Feature",
  "properties": {
    "tgn:hierarchy":[
        "tgn:2737637",
        "tgn:1000001",
        "tgn:7012149",
        "tgn:2000237",
        "tgn:7007158",
        "tgn:7029392"
    ],
    "tgn:id":2737637,
    "tgn:name":"Tyler Mine",
    "tgn:placetype":[
        "aat:300000390"
    ]
},
  "bbox": [],
  "geometry": {"coordinates":[-107.6333,38.2667],"type":"Point"}
}