{
  "id": 7018981,
  "type": "Feature",
  "properties": {
    "tgn:hierarchy":[
        "tgn:7018981",
        "tgn:1000001",
        "tgn:7012149",
        "tgn:1002694",
        "tgn:7007252",
        "tgn:7029392"
    ],
    "tgn:id":7018981,
    "tgn:name":"Waverly Woods",
    "tgn:placetype":[
        "aat:300008347"
    ]
},
  "bbox": [],
  "geometry": {"coordinates":[-86.2667,39.55],"type":"Point"}
}