<<<<<<< HEAD
{
  "id": 7480629,
  "type": "Feature",
  "properties": {
    "tgn:hierarchy":[
        "tgn:7480629",
        "tgn:1000004",
        "tgn:7490934",
        "tgn:1000141",
        "tgn:7029392"
    ],
    "tgn:id":7480629,
    "tgn:name":"Guolu Guoxiao",
    "tgn:placetype":[
        "aat:300006495"
    ]
},
  "bbox": [],
  "geometry": {"coordinates":[120.2086,23.3069],"type":"Point"}
}
=======
{"geometry":{"type":"Point","coordinates":[120.208600,23.306900]},"type":"Feature","properties":{"hierarchy":["tgn:7480629","tgn:1000004","tgn:7490934","tgn:1000141","tgn:7029392"],"placetype":["aat:300006495"],"id":7480629,"name:xx":"Guolu Guoxiao"}}
>>>>>>> 03f74aca74312dbeaf24d7e61306dd6a786dc3d0
