{
  "id": 7130061,
  "type": "Feature",
  "properties": {
    "tgn:hierarchy":[
        "tgn:7130061",
        "tgn:1000003",
        "tgn:7003677",
        "tgn:7000084",
        "tgn:7029392"
    ],
    "tgn:id":7130061,
    "tgn:name":"Meintrup",
    "tgn:placetype":[
        "aat:300000206"
    ]
},
  "bbox": [],
  "geometry": {"coordinates":[8.25,51.833333],"type":"Point"}
}