{
  "id": 2219727,
  "type": "Feature",
  "properties": {
    "tgn:hierarchy":[
        "tgn:2219727",
        "tgn:1000001",
        "tgn:7012149",
        "tgn:2001451",
        "tgn:7007566",
        "tgn:7029392"
    ],
    "tgn:id":2219727,
    "tgn:name":"Canovas, Loma",
    "tgn:placetype":[
        "aat:300008798"
    ]
},
  "bbox": [],
  "geometry": {"coordinates":[-106.55,35.6167],"type":"Point"}
}