{
  "id": 7375021,
  "type": "Feature",
  "properties": {
    "tgn:hierarchy":[
        "tgn:7375021",
        "tgn:1000001",
        "tgn:7005595",
        "tgn:7005560",
        "tgn:7029392"
    ],
    "tgn:id":7375021,
    "tgn:name":"Labradas",
    "tgn:placetype":[
        "aat:300008347"
    ]
},
  "bbox": [],
  "geometry": {"coordinates":[-106.366667,23.783333],"type":"Point"}
}