{
  "id": 7250478,
  "type": "Feature",
  "properties": {
    "tgn:hierarchy":[
        "tgn:7250478",
        "tgn:7018239",
        "tgn:1000003",
        "tgn:1000063",
        "tgn:7018236",
        "tgn:7029392"
    ],
    "tgn:id":7250478,
    "tgn:name":"Putkapel",
    "tgn:placetype":[
        "aat:300008347"
    ]
},
  "bbox": [],
  "geometry": {"coordinates":[4.716667,50.933333],"type":"Point"}
}