{
  "id": 2448073,
  "type": "Feature",
  "properties": {
    "tgn:hierarchy":[
        "tgn:2448073",
        "tgn:1000001",
        "tgn:7016172",
        "tgn:7012149",
        "tgn:7029392"
    ],
    "tgn:id":2448073,
    "tgn:name":"Lighthouse Ditch",
    "tgn:placetype":[
        "aat:300006075"
    ]
},
  "bbox": [],
  "geometry": {"coordinates":[-90.4667,35.95],"type":"Point"}
}