<<<<<<< HEAD
{
  "id": 2339232,
  "type": "Feature",
  "properties": {
    "tgn:hierarchy":[
        "tgn:2339232",
        "tgn:1000001",
        "tgn:7012149",
        "tgn:2001969",
        "tgn:7007826",
        "tgn:7029392"
    ],
    "tgn:id":2339232,
    "tgn:name":"Franky Tank",
    "tgn:placetype":[
        "aat:300006191"
    ]
},
  "bbox": [],
  "geometry": {"coordinates":[-104.6833,31.7],"type":"Point"}
}
=======
{"geometry":{"type":"Point","coordinates":[-104.683300,31.700000]},"type":"Feature","properties":{"hierarchy":["tgn:2339232","tgn:1000001","tgn:7012149","tgn:2001969","tgn:7007826","tgn:7029392"],"placetype":["aat:300006191"],"id":2339232,"name:xx":"Franky Tank"}}
>>>>>>> 03f74aca74312dbeaf24d7e61306dd6a786dc3d0
