{
  "id": 2384616,
  "type": "Feature",
  "properties": {
    "tgn:hierarchy":[
        "tgn:2384616",
        "tgn:1000001",
        "tgn:7012149",
        "tgn:1002961",
        "tgn:7007568",
        "tgn:7029392"
    ],
    "tgn:id":2384616,
    "tgn:name":"Hell, The",
    "tgn:placetype":[
        "aat:300055621"
    ]
},
  "bbox": [],
  "geometry": {"coordinates":[-73.9833,41.85],"type":"Point"}
}