{
  "id": 7569714,
  "type": "Feature",
  "properties": {
    "tgn:hierarchy":[
        "tgn:7569714",
        "tgn:1000004",
        "tgn:7000198",
        "tgn:7031786",
        "tgn:7029392"
    ],
    "tgn:id":7569714,
    "tgn:name:en":"Khamana",
    "tgn:placetype":[
        "aat:300008347"
    ]
},
  "bbox": [],
  "geometry": {"coordinates":[78.52779,29.947506],"type":"Point"}
}