{
  "id": 2511524,
  "type": "Feature",
  "properties": {
    "tgn:hierarchy":[
        "tgn:2511524",
        "tgn:1000001",
        "tgn:7012149",
        "tgn:2002381",
        "tgn:7007923",
        "tgn:7029392"
    ],
    "tgn:id":2511524,
    "tgn:name":"Mile Draw",
    "tgn:placetype":[
        "aat:300008761"
    ]
},
  "bbox": [],
  "geometry": {"coordinates":[-106.5167,44.85],"type":"Point"}
}