{
  "id": 2664070,
  "type": "Feature",
  "properties": {
    "tgn:hierarchy":[
        "tgn:2664070",
        "tgn:1000001",
        "tgn:7006451",
        "tgn:2000091",
        "tgn:7012149",
        "tgn:7029392"
    ],
    "tgn:id":2664070,
    "tgn:name":"Silver Prince Mine",
    "tgn:placetype":[
        "aat:300000390"
    ]
},
  "bbox": [],
  "geometry": {"coordinates":[-109.2833,31.9667],"type":"Point"}
}