{
  "id": 2604972,
  "type": "Feature",
  "properties": {
    "tgn:hierarchy":[
        "tgn:2604972",
        "tgn:1000001",
        "tgn:7012149",
        "tgn:2000722",
        "tgn:7007254",
        "tgn:7029392"
    ],
    "tgn:id":2604972,
    "tgn:name":"Racket Creek",
    "tgn:placetype":[
        "aat:300008706"
    ]
},
  "bbox": [],
  "geometry": {"coordinates":[-95.7833,37.3333],"type":"Point"}
}