{
  "id": 7056030,
  "type": "Feature",
  "properties": {
    "tgn:hierarchy":[
        "tgn:7056030",
        "tgn:1003447",
        "tgn:7007850",
        "tgn:1000003",
        "tgn:1000080",
        "tgn:7029392"
    ],
    "tgn:id":7056030,
    "tgn:name":"Miglierina",
    "tgn:placetype":[
        "aat:300008347"
    ]
},
  "bbox": [],
  "geometry": {"coordinates":[16.466667,38.95],"type":"Point"}
}