{
  "id": 2171843,
  "type": "Feature",
  "properties": {
    "tgn:hierarchy":[
        "tgn:2171843",
        "tgn:1000001",
        "tgn:2002366",
        "tgn:7012149",
        "tgn:7007923",
        "tgn:7029392"
    ],
    "tgn:id":2171843,
    "tgn:name":"Big Von Reservoir",
    "tgn:placetype":[
        "aat:300006191"
    ]
},
  "bbox": [],
  "geometry": {"coordinates":[-108.4333,44.2167],"type":"Point"}
}