{
  "id": 2202563,
  "type": "Feature",
  "properties": {
    "tgn:hierarchy":[
        "tgn:2202563",
        "tgn:1000001",
        "tgn:7012149",
        "tgn:2002271",
        "tgn:7013961",
        "tgn:7029392"
    ],
    "tgn:id":2202563,
    "tgn:name":"Buck Run",
    "tgn:placetype":[
        "aat:300008699"
    ]
},
  "bbox": [],
  "geometry": {"coordinates":[-80.65,39.1333],"type":"Point"}
}