{
  "id": 1130849,
  "type": "Feature",
  "properties": {
    "tgn:hierarchy":[
        "tgn:1130849",
        "tgn:1000002",
        "tgn:1000059",
        "tgn:7029392"
    ],
    "tgn:id":1130849,
    "tgn:name":"Tigre, R\u00edo",
    "tgn:placetype":[
        "aat:300008707"
    ]
},
  "bbox": [],
  "geometry": {"coordinates":[-62.518,9.358],"type":"Point"}
}