{
  "id": 7278586,
  "type": "Feature",
  "properties": {
    "tgn:hierarchy":[
        "tgn:7278586",
        "tgn:1001637",
        "tgn:1000049",
        "tgn:1000002",
        "tgn:7029392"
    ],
    "tgn:id":7278586,
    "tgn:name":"Valiente, Cerro",
    "tgn:placetype":[
        "aat:300008795"
    ]
},
  "bbox": [],
  "geometry": {"coordinates":[-71.516667,-36.45],"type":"Point"}
}