{
  "id": 2016411,
  "type": "Feature",
  "properties": {
    "tgn:hierarchy":[
        "tgn:2016411",
        "tgn:1000001",
        "tgn:7012149",
        "tgn:2000217",
        "tgn:7007158",
        "tgn:7029392"
    ],
    "tgn:id":2016411,
    "tgn:name":"Tincup",
    "tgn:placetype":[
        "aat:300008347",
        "aat:300387247"
    ]
},
  "bbox": [],
  "geometry": {"coordinates":[-106.4667,38.75],"type":"Point"}
}