{
  "id": 7068217,
  "type": "Feature",
  "properties": {
    "tgn:hierarchy":[
        "tgn:7068217",
        "tgn:1000003",
        "tgn:7003688",
        "tgn:7000084",
        "tgn:7029392"
    ],
    "tgn:id":7068217,
    "tgn:name":"Tresdorfer See",
    "tgn:placetype":[
        "aat:300008680"
    ]
},
  "bbox": [],
  "geometry": {"coordinates":[10.466667,54.233333],"type":"Point"}
}