{
  "id": 7128276,
  "type": "Feature",
  "properties": {
    "tgn:hierarchy":[
        "tgn:7128276",
        "tgn:1000003",
        "tgn:7003676",
        "tgn:7000084",
        "tgn:7029392"
    ],
    "tgn:id":7128276,
    "tgn:name":"Nienbergen",
    "tgn:placetype":[
        "aat:300008347"
    ]
},
  "bbox": [],
  "geometry": {"coordinates":[10.95,52.866667],"type":"Point"}
}