{
  "id": 7479315,
  "type": "Feature",
  "properties": {
    "tgn:hierarchy":[
        "tgn:7479315",
        "tgn:1000004",
        "tgn:7490934",
        "tgn:1000141",
        "tgn:7029392"
    ],
    "tgn:id":7479315,
    "tgn:name":"Heping Qiao",
    "tgn:placetype":[
        "aat:300007836"
    ]
},
  "bbox": [],
  "geometry": {"coordinates":[120.384167,23.36],"type":"Point"}
}