<<<<<<< HEAD
{
  "id": 7479315,
  "type": "Feature",
  "properties": {
    "tgn:hierarchy":[
        "tgn:7479315",
        "tgn:1000004",
        "tgn:7490934",
        "tgn:1000141",
        "tgn:7029392"
    ],
    "tgn:id":7479315,
    "tgn:name":"Heping Qiao",
    "tgn:placetype":[
        "aat:300007836"
    ]
},
  "bbox": [],
  "geometry": {"coordinates":[120.384167,23.36],"type":"Point"}
}
=======
{"geometry":{"type":"Point","coordinates":[120.384167,23.360000]},"type":"Feature","properties":{"hierarchy":["tgn:7479315","tgn:1000004","tgn:7490934","tgn:1000141","tgn:7029392"],"placetype":["aat:300007836"],"id":7479315,"name:xx":"Heping Qiao"}}
>>>>>>> 03f74aca74312dbeaf24d7e61306dd6a786dc3d0
