{
  "id": 2317296,
  "type": "Feature",
  "properties": {
    "tgn:hierarchy":[
        "tgn:2317296",
        "tgn:1000001",
        "tgn:1002328",
        "tgn:7012149",
        "tgn:7007568",
        "tgn:7029392"
    ],
    "tgn:id":2317296,
    "tgn:name":"Emmons Pond",
    "tgn:placetype":[
        "aat:300008680"
    ]
},
  "bbox": [],
  "geometry": {"coordinates":[-75.0167,42.4167],"type":"Point"}
}