{
  "id": 7297300,
  "type": "Feature",
  "properties": {
    "tgn:hierarchy":[
        "tgn:7297300",
        "tgn:7008911",
        "tgn:1000003",
        "tgn:7002763",
        "tgn:1000095",
        "tgn:7029392"
    ],
    "tgn:id":7297300,
    "tgn:name":"Tamagordas",
    "tgn:placetype":[
        "aat:300008347"
    ]
},
  "bbox": [],
  "geometry": {"coordinates":[-6.816667,43.283333],"type":"Point"}
}