{
  "id": 2254237,
  "type": "Feature",
  "properties": {
    "tgn:hierarchy":[
        "tgn:2254237",
        "tgn:1000001",
        "tgn:7012149",
        "tgn:1002680",
        "tgn:7007523",
        "tgn:7029392"
    ],
    "tgn:id":2254237,
    "tgn:name":"Coon Branch",
    "tgn:placetype":[
        "aat:300008699"
    ]
},
  "bbox": [],
  "geometry": {"coordinates":[-92.1167,39.4833],"type":"Point"}
}