<<<<<<< HEAD
{
  "id": 2254237,
  "type": "Feature",
  "properties": {
    "tgn:hierarchy":[
        "tgn:2254237",
        "tgn:1000001",
        "tgn:7012149",
        "tgn:1002680",
        "tgn:7007523",
        "tgn:7029392"
    ],
    "tgn:id":2254237,
    "tgn:name":"Coon Branch",
    "tgn:placetype":[
        "aat:300008699"
    ]
},
  "bbox": [],
  "geometry": {"coordinates":[-92.1167,39.4833],"type":"Point"}
}
=======
{"geometry":{"type":"Point","coordinates":[-92.116700,39.483300]},"type":"Feature","properties":{"hierarchy":["tgn:2254237","tgn:1000001","tgn:7012149","tgn:1002680","tgn:7007523","tgn:7029392"],"placetype":["aat:300008699"],"id":2254237,"name:xx":"Coon Branch"}}
>>>>>>> 03f74aca74312dbeaf24d7e61306dd6a786dc3d0
