{
  "id": 2135505,
  "type": "Feature",
  "properties": {
    "tgn:hierarchy":[
        "tgn:2135505",
        "tgn:1000001",
        "tgn:7012149",
        "tgn:7014589",
        "tgn:7007515",
        "tgn:7029392"
    ],
    "tgn:id":2135505,
    "tgn:name":"Anvil Meadow",
    "tgn:placetype":[
        "aat:300008905"
    ]
},
  "bbox": [],
  "geometry": {"coordinates":[-67.8167,45.55],"type":"Point"}
}