{
  "id": 2333156,
  "type": "Feature",
  "properties": {
    "tgn:hierarchy":[
        "tgn:2333156",
        "tgn:1000001",
        "tgn:2001411",
        "tgn:7012149",
        "tgn:7007526",
        "tgn:7029392"
    ],
    "tgn:id":2333156,
    "tgn:name":"Flyn and Hager Spring",
    "tgn:placetype":[
        "aat:300008697"
    ]
},
  "bbox": [],
  "geometry": {"coordinates":[-115.5167,40.1333],"type":"Point"}
}