<<<<<<< HEAD
{
  "id": 2333156,
  "type": "Feature",
  "properties": {
    "tgn:hierarchy":[
        "tgn:2333156",
        "tgn:1000001",
        "tgn:2001411",
        "tgn:7012149",
        "tgn:7007526",
        "tgn:7029392"
    ],
    "tgn:id":2333156,
    "tgn:name":"Flyn and Hager Spring",
    "tgn:placetype":[
        "aat:300008697"
    ]
},
  "bbox": [],
  "geometry": {"coordinates":[-115.5167,40.1333],"type":"Point"}
}
=======
{"geometry":{"type":"Point","coordinates":[-115.516700,40.133300]},"type":"Feature","properties":{"hierarchy":["tgn:2333156","tgn:1000001","tgn:2001411","tgn:7012149","tgn:7007526","tgn:7029392"],"placetype":["aat:300008697"],"id":2333156,"name:xx":"Flyn and Hager Spring"}}
>>>>>>> 03f74aca74312dbeaf24d7e61306dd6a786dc3d0
