<<<<<<< HEAD
{
  "id": 7119309,
  "type": "Feature",
  "properties": {
    "tgn:hierarchy":[
        "tgn:7119309",
        "tgn:1000003",
        "tgn:7003688",
        "tgn:7000084",
        "tgn:7029392"
    ],
    "tgn:id":7119309,
    "tgn:name":"Poggenpohl",
    "tgn:placetype":[
        "aat:300000206"
    ]
},
  "bbox": [],
  "geometry": {"coordinates":[10.983333,54.2],"type":"Point"}
}
=======
{"geometry":{"type":"Point","coordinates":[10.983333,54.200000]},"type":"Feature","properties":{"hierarchy":["tgn:7119309","tgn:1000003","tgn:7003688","tgn:7000084","tgn:7029392"],"placetype":["aat:300000206"],"id":7119309,"name:xx":"Poggenpohl"}}
>>>>>>> 03f74aca74312dbeaf24d7e61306dd6a786dc3d0
