{
  "id": 2086631,
  "type": "Feature",
  "properties": {
    "tgn:hierarchy":[
        "tgn:2086631",
        "tgn:1000001",
        "tgn:7012149",
        "tgn:2001724",
        "tgn:7007710",
        "tgn:7029392"
    ],
    "tgn:id":2086631,
    "tgn:name":"Brave",
    "tgn:placetype":[
        "aat:300008347"
    ]
},
  "bbox": [],
  "geometry": {"coordinates":[-80.25,39.7167],"type":"Point"}
}