{
  "id": 7493865,
  "type": "Feature",
  "properties": {
    "tgn:hierarchy":[
        "tgn:7493865",
        "tgn:1000004",
        "tgn:7491221",
        "tgn:1000141",
        "tgn:7029392"
    ],
    "tgn:id":7493865,
    "tgn:name":"Manahan Xi",
    "tgn:placetype":[
        "aat:300008699"
    ]
},
  "bbox": [],
  "geometry": {"coordinates":[121.275129,23.024754],"type":"Point"}
}