{
  "id": 2666122,
  "type": "Feature",
  "properties": {
    "tgn:hierarchy":[
        "tgn:2666122",
        "tgn:1000001",
        "tgn:7012149",
        "tgn:2002168",
        "tgn:7007919",
        "tgn:7029392"
    ],
    "tgn:id":2666122,
    "tgn:name":"Sittlington Hill",
    "tgn:placetype":[
        "aat:300008798"
    ]
},
  "bbox": [],
  "geometry": {"coordinates":[-79.4667,38.3167],"type":"Point"}
}