{
  "id": 7543844,
  "type": "Feature",
  "properties": {
    "tgn:hierarchy":[
        "tgn:7543844",
        "tgn:7001242",
        "tgn:7016833",
        "tgn:1001225",
        "tgn:7029392"
    ],
    "tgn:id":7543844,
    "tgn:name":"An N\u0101\u015fir\u012byah",
    "tgn:placetype":[
        "aat:300008347"
    ]
},
  "bbox": [],
  "geometry": {"coordinates":[31.642403,31.342711],"type":"Point"}
}