{
  "id": 7589879,
  "type": "Feature",
  "properties": {
    "tgn:hierarchy":[
        "tgn:7589879",
        "tgn:1000004",
        "tgn:7000198",
        "tgn:7000799",
        "tgn:7029392"
    ],
    "tgn:id":7589879,
    "tgn:name:en":"Loh\u0101rakot",
    "tgn:placetype":[
        "aat:300008347"
    ]
},
  "bbox": [],
  "geometry": {"coordinates":[74.504178,33.052433],"type":"Point"}
}