{
  "id": 7581382,
  "type": "Feature",
  "properties": {
    "tgn:hierarchy":[
        "tgn:7581382",
        "tgn:1000004",
        "tgn:7000198",
        "tgn:1001578",
        "tgn:7029392"
    ],
    "tgn:id":7581382,
    "tgn:name:en":"Surma River",
    "tgn:placetype":[
        "aat:300008699"
    ]
},
  "bbox": [],
  "geometry": {"coordinates":[91.233333,24.566667],"type":"Point"}
}