{
  "id": 7432184,
  "type": "Feature",
  "properties": {
    "tgn:hierarchy":[
        "tgn:7432184",
        "tgn:1000001",
        "tgn:7005595",
        "tgn:7005560",
        "tgn:7029392"
    ],
    "tgn:id":7432184,
    "tgn:name":"El Tecomate",
    "tgn:placetype":[
        "aat:300008347"
    ]
},
  "bbox": [],
  "geometry": {"coordinates":[-106.05,23.666667],"type":"Point"}
}