{
  "id": 2599224,
  "type": "Feature",
  "properties": {
    "tgn:hierarchy":[
        "tgn:2599224",
        "tgn:1000001",
        "tgn:7012149",
        "tgn:2001855",
        "tgn:7007825",
        "tgn:7029392"
    ],
    "tgn:id":2599224,
    "tgn:name":"Prock Hollow",
    "tgn:placetype":[
        "aat:300008761"
    ]
},
  "bbox": [],
  "geometry": {"coordinates":[-86.8167,36.2833],"type":"Point"}
}