{
  "id": 2375155,
  "type": "Feature",
  "properties": {
    "tgn:hierarchy":[
        "tgn:2375155",
        "tgn:1000001",
        "tgn:7012149",
        "tgn:2002382",
        "tgn:7007923",
        "tgn:7029392"
    ],
    "tgn:id":2375155,
    "tgn:name":"Hanna Number 2 Ditch",
    "tgn:placetype":[
        "aat:300006075"
    ]
},
  "bbox": [],
  "geometry": {"coordinates":[-109.9167,42.5667],"type":"Point"}
}