{
  "id": 7197064,
  "type": "Feature",
  "properties": {
    "tgn:hierarchy":[
        "tgn:7197064",
        "tgn:1000003",
        "tgn:7000094",
        "tgn:7000084",
        "tgn:7029392"
    ],
    "tgn:id":7197064,
    "tgn:name":"Dar\u00dfer Ort",
    "tgn:placetype":[
        "aat:300008850"
    ]
},
  "bbox": [],
  "geometry": {"coordinates":[12.516667,54.483333],"type":"Point"}
}