<<<<<<< HEAD
{
  "id": 2254395,
  "type": "Feature",
  "properties": {
    "tgn:hierarchy":[
        "tgn:2254395",
        "tgn:1000001",
        "tgn:7012149",
        "tgn:2001189",
        "tgn:7007523",
        "tgn:7029392"
    ],
    "tgn:id":2254395,
    "tgn:name":"Coon Creek",
    "tgn:placetype":[
        "aat:300008706"
    ]
},
  "bbox": [],
  "geometry": {"coordinates":[-92.9167,38.8167],"type":"Point"}
}
=======
{"geometry":{"type":"Point","coordinates":[-92.916700,38.816700]},"type":"Feature","properties":{"hierarchy":["tgn:2254395","tgn:1000001","tgn:7012149","tgn:2001189","tgn:7007523","tgn:7029392"],"placetype":["aat:300008706"],"id":2254395,"name:xx":"Coon Creek"}}
>>>>>>> 03f74aca74312dbeaf24d7e61306dd6a786dc3d0
