{
  "id": 7277346,
  "type": "Feature",
  "properties": {
    "tgn:hierarchy":[
        "tgn:7277346",
        "tgn:1001699",
        "tgn:1000049",
        "tgn:1000002",
        "tgn:7029392"
    ],
    "tgn:id":7277346,
    "tgn:name":"Cerros Yanteles",
    "tgn:placetype":[
        "aat:300008795"
    ]
},
  "bbox": [],
  "geometry": {"coordinates":[-72.785556,-43.465278],"type":"Point"}
}