{
  "id": 7302100,
  "type": "Feature",
  "properties": {
    "tgn:hierarchy":[
        "tgn:7302100",
        "tgn:7002836",
        "tgn:7016622",
        "tgn:1000003",
        "tgn:1000095",
        "tgn:7029392"
    ],
    "tgn:id":7302100,
    "tgn:name":"M\u00e9dano, Puerto",
    "tgn:placetype":[
        "aat:300132317"
    ]
},
  "bbox": [],
  "geometry": {"coordinates":[-16.533333,28.033333],"type":"Point"}
}