{
  "id": 1037791,
  "type": "Feature",
  "properties": {
    "tgn:hierarchy":[
        "tgn:1037791",
        "tgn:7000096",
        "tgn:1000003",
        "tgn:7000084",
        "tgn:7029392"
    ],
    "tgn:id":1037791,
    "tgn:name":"Storkow",
    "tgn:placetype":[
        "aat:300008347"
    ]
},
  "bbox": [],
  "geometry": {"coordinates":[14.283333,53.316667],"type":"Point"}
}