{
  "id": 2154948,
  "type": "Feature",
  "properties": {
    "tgn:hierarchy":[
        "tgn:2154948",
        "tgn:1000001",
        "tgn:2000316",
        "tgn:7012149",
        "tgn:7007248",
        "tgn:7029392"
    ],
    "tgn:id":2154948,
    "tgn:name":"Bear Island",
    "tgn:placetype":[
        "aat:300008791"
    ]
},
  "bbox": [],
  "geometry": {"coordinates":[-81.1333,31.8333],"type":"Point"}
}