{
  "id": 2605956,
  "type": "Feature",
  "properties": {
    "tgn:hierarchy":[
        "tgn:2605956",
        "tgn:1000001",
        "tgn:7012149",
        "tgn:2002383",
        "tgn:7007923",
        "tgn:7029392"
    ],
    "tgn:id":2605956,
    "tgn:name":"Rainbow Mine",
    "tgn:placetype":[
        "aat:300000390"
    ]
},
  "bbox": [],
  "geometry": {"coordinates":[-109.2167,41.5167],"type":"Point"}
}