{
  "id": 1091453,
  "type": "Feature",
  "properties": {
    "tgn:hierarchy":[
        "tgn:1091453",
        "tgn:7001242",
        "tgn:1000179",
        "tgn:7593698",
        "tgn:7029392"
    ],
    "tgn:id":1091453,
    "tgn:name":"Taourirt",
    "tgn:placetype":[
        "aat:300008347"
    ]
},
  "bbox": [],
  "geometry": {"coordinates":[-2.8833,34.4167],"type":"Point"}
}