<<<<<<< HEAD
{
  "id": 2252749,
  "type": "Feature",
  "properties": {
    "tgn:hierarchy":[
        "tgn:2252749",
        "tgn:1000001",
        "tgn:7012149",
        "tgn:2002382",
        "tgn:7007923",
        "tgn:7029392"
    ],
    "tgn:id":2252749,
    "tgn:name":"Connie Glacier",
    "tgn:placetype":[
        "aat:300008835"
    ]
},
  "bbox": [],
  "geometry": {"coordinates":[-109.6833,43.2667],"type":"Point"}
}
=======
{"geometry":{"type":"Point","coordinates":[-109.683300,43.266700]},"type":"Feature","properties":{"hierarchy":["tgn:2252749","tgn:1000001","tgn:7012149","tgn:2002382","tgn:7007923","tgn:7029392"],"placetype":["aat:300008835"],"id":2252749,"name:xx":"Connie Glacier"}}
>>>>>>> 03f74aca74312dbeaf24d7e61306dd6a786dc3d0
