{
  "id": 7476561,
  "type": "Feature",
  "properties": {
    "tgn:hierarchy":[
        "tgn:7476561",
        "tgn:7488858",
        "tgn:1000004",
        "tgn:1000141",
        "tgn:7029392"
    ],
    "tgn:id":7476561,
    "tgn:name":"Zhuzikeng Qiao",
    "tgn:placetype":[
        "aat:300007836"
    ]
},
  "bbox": [],
  "geometry": {"coordinates":[120.799261,23.842733],"type":"Point"}
}