{
  "id": 7439310,
  "type": "Feature",
  "properties": {
    "tgn:hierarchy":[
        "tgn:7439310",
        "tgn:1000001",
        "tgn:7005601",
        "tgn:7005560",
        "tgn:7029392"
    ],
    "tgn:id":7439310,
    "tgn:name":"Tecolotes, Cerro",
    "tgn:placetype":[
        "aat:300008795"
    ]
},
  "bbox": [],
  "geometry": {"coordinates":[-101.983333,24.65],"type":"Point"}
}