{
  "id": 7334836,
  "type": "Feature",
  "properties": {
    "tgn:hierarchy":[
        "tgn:7334836",
        "tgn:7002827",
        "tgn:1000003",
        "tgn:7002789",
        "tgn:1000095",
        "tgn:7029392"
    ],
    "tgn:id":7334836,
    "tgn:name":"Pantano de la Grajera",
    "tgn:placetype":[
        "aat:300006191"
    ]
},
  "bbox": [],
  "geometry": {"coordinates":[-2.503996,42.444386],"type":"Point"}
}