{
  "id": 2228599,
  "type": "Feature",
  "properties": {
    "tgn:hierarchy":[
        "tgn:2228599",
        "tgn:1000001",
        "tgn:7012149",
        "tgn:2002248",
        "tgn:7007920",
        "tgn:7029392"
    ],
    "tgn:id":2228599,
    "tgn:name":"Cedar Creek",
    "tgn:placetype":[
        "aat:300008706"
    ]
},
  "bbox": [],
  "geometry": {"coordinates":[-117.35,48.1667],"type":"Point"}
}