{
  "id": 2783427,
  "type": "Feature",
  "properties": {
    "tgn:hierarchy":[
        "tgn:2783427",
        "tgn:1000001",
        "tgn:7012149",
        "tgn:2001449",
        "tgn:7007566",
        "tgn:7029392"
    ],
    "tgn:id":2783427,
    "tgn:name":"Wsest Boundary Tank",
    "tgn:placetype":[
        "aat:300006191"
    ]
},
  "bbox": [],
  "geometry": {"coordinates":[-106.1667,36.7833],"type":"Point"}
}