{
  "id": 2105666,
  "type": "Feature",
  "properties": {
    "tgn:hierarchy":[
        "tgn:2105666",
        "tgn:1000001",
        "tgn:7012149",
        "tgn:2002025",
        "tgn:7007826",
        "tgn:7029392"
    ],
    "tgn:id":2105666,
    "tgn:name":"Littlefield",
    "tgn:placetype":[
        "aat:300008347"
    ]
},
  "bbox": [],
  "geometry": {"coordinates":[-102.3167,33.9167],"type":"Point"}
}