{
  "id": 2001866,
  "type": "Feature",
  "properties": {
    "tgn:hierarchy":[
        "tgn:2001866",
        "tgn:1000001",
        "tgn:7012149",
        "tgn:7007825",
        "tgn:7029392"
    ],
    "tgn:id":2001866,
    "tgn:name":"Greene",
    "tgn:placetype":[
        "aat:300387145",
        "aat:300000771"
    ]
},
  "bbox": [],
  "geometry": {"coordinates":[-82.85,36.15],"type":"Point"}
}