{
  "id": 7139132,
  "type": "Feature",
  "properties": {
    "tgn:hierarchy":[
        "tgn:7139132",
        "tgn:1000003",
        "tgn:7003678",
        "tgn:7000084",
        "tgn:7029392"
    ],
    "tgn:id":7139132,
    "tgn:name":"Leisenwald",
    "tgn:placetype":[
        "aat:300008347"
    ]
},
  "bbox": [],
  "geometry": {"coordinates":[9.233333,50.316667],"type":"Point"}
}