{
  "id": 4003860,
  "type": "Feature",
  "properties": {
    "tgn:hierarchy":[
        "tgn:4003860",
        "tgn:7006349",
        "tgn:1000003",
        "tgn:7006278",
        "tgn:7029392"
    ],
    "tgn:id":4003860,
    "tgn:name":"Feketekapu",
    "tgn:placetype":[
        "aat:300008347"
    ]
},
  "bbox": [],
  "geometry": {"coordinates":[18.6667,45.95],"type":"Point"}
}