{
  "id": 2343417,
  "type": "Feature",
  "properties": {
    "tgn:hierarchy":[
        "tgn:2343417",
        "tgn:1000001",
        "tgn:7012149",
        "tgn:2001108",
        "tgn:7007522",
        "tgn:7029392"
    ],
    "tgn:id":2343417,
    "tgn:name":"Gainesville",
    "tgn:placetype":[
        "aat:300008347"
    ]
},
  "bbox": [],
  "geometry": {"coordinates":[-89.6333,30.35],"type":"Point"}
}