<<<<<<< HEAD
{
  "id": 2409906,
  "type": "Feature",
  "properties": {
    "tgn:hierarchy":[
        "tgn:2409906",
        "tgn:1002172",
        "tgn:1000001",
        "tgn:7012149",
        "tgn:7007710",
        "tgn:7029392"
    ],
    "tgn:id":2409906,
    "tgn:name":"Imlertown Run",
    "tgn:placetype":[
        "aat:300008699"
    ]
},
  "bbox": [],
  "geometry": {"coordinates":[-78.4333,40.1167],"type":"Point"}
}
=======
{"geometry":{"type":"Point","coordinates":[-78.433300,40.116700]},"type":"Feature","properties":{"hierarchy":["tgn:2409906","tgn:1002172","tgn:1000001","tgn:7012149","tgn:7007710","tgn:7029392"],"placetype":["aat:300008699"],"id":2409906,"name:xx":"Imlertown Run"}}
>>>>>>> 03f74aca74312dbeaf24d7e61306dd6a786dc3d0
