{
  "id": 2509695,
  "type": "Feature",
  "properties": {
    "tgn:hierarchy":[
        "tgn:2509695",
        "tgn:2000944",
        "tgn:1000001",
        "tgn:7012149",
        "tgn:7007520",
        "tgn:7029392"
    ],
    "tgn:id":2509695,
    "tgn:name":"Middle Island",
    "tgn:placetype":[
        "aat:300008791"
    ]
},
  "bbox": [],
  "geometry": {"coordinates":[-83.3167,45.1833],"type":"Point"}
}