{
  "id": 2152689,
  "type": "Feature",
  "properties": {
    "tgn:hierarchy":[
        "tgn:2152689",
        "tgn:1000001",
        "tgn:7012149",
        "tgn:2000817",
        "tgn:7007255",
        "tgn:7029392"
    ],
    "tgn:id":2152689,
    "tgn:name":"Bayou Creek",
    "tgn:placetype":[
        "aat:300008706"
    ]
},
  "bbox": [],
  "geometry": {"coordinates":[-88.85,37.05],"type":"Point"}
}