<<<<<<< HEAD
{
  "id": 2257791,
  "type": "Feature",
  "properties": {
    "tgn:hierarchy":[
        "tgn:2257791",
        "tgn:1000001",
        "tgn:2001418",
        "tgn:7012149",
        "tgn:7007526",
        "tgn:7029392"
    ],
    "tgn:id":2257791,
    "tgn:name":"Corral Spring",
    "tgn:placetype":[
        "aat:300008697"
    ]
},
  "bbox": [],
  "geometry": {"coordinates":[-116.3667,37.7833],"type":"Point"}
}
=======
{"geometry":{"type":"Point","coordinates":[-116.366700,37.783300]},"type":"Feature","properties":{"hierarchy":["tgn:2257791","tgn:1000001","tgn:2001418","tgn:7012149","tgn:7007526","tgn:7029392"],"placetype":["aat:300008697"],"id":2257791,"name:xx":"Corral Spring"}}
>>>>>>> 03f74aca74312dbeaf24d7e61306dd6a786dc3d0
