{
  "id": 2257791,
  "type": "Feature",
  "properties": {
    "tgn:hierarchy":[
        "tgn:2257791",
        "tgn:1000001",
        "tgn:2001418",
        "tgn:7012149",
        "tgn:7007526",
        "tgn:7029392"
    ],
    "tgn:id":2257791,
    "tgn:name":"Corral Spring",
    "tgn:placetype":[
        "aat:300008697"
    ]
},
  "bbox": [],
  "geometry": {"coordinates":[-116.3667,37.7833],"type":"Point"}
}