{
  "id": 7368167,
  "type": "Feature",
  "properties": {
    "tgn:hierarchy":[
        "tgn:7368167",
        "tgn:1000001",
        "tgn:7005589",
        "tgn:7005560",
        "tgn:7029392"
    ],
    "tgn:id":7368167,
    "tgn:name":"Iguana, Sierra de la",
    "tgn:placetype":[
        "aat:300008795"
    ]
},
  "bbox": [],
  "geometry": {"coordinates":[-100.333333,26.75],"type":"Point"}
}