{
  "id": 2045850,
  "type": "Feature",
  "properties": {
    "tgn:hierarchy":[
        "tgn:2045850",
        "tgn:1000001",
        "tgn:2000920",
        "tgn:7012149",
        "tgn:7007515",
        "tgn:7029392"
    ],
    "tgn:id":2045850,
    "tgn:name":"West Gray",
    "tgn:placetype":[
        "aat:300008347",
        "aat:300387210"
    ]
},
  "bbox": [],
  "geometry": {"coordinates":[-70.3667,43.85],"type":"Point"}
}