{
  "id": 7585757,
  "type": "Feature",
  "properties": {
    "tgn:hierarchy":[
        "tgn:7585757",
        "tgn:1000004",
        "tgn:7000198",
        "tgn:7000799",
        "tgn:7029392"
    ],
    "tgn:id":7585757,
    "tgn:name:en":"Zindri",
    "tgn:placetype":[
        "aat:300008699"
    ]
},
  "bbox": [],
  "geometry": {"coordinates":[74.416667,34.341667],"type":"Point"}
}