<<<<<<< HEAD
{
  "id": 2156069,
  "type": "Feature",
  "properties": {
    "tgn:hierarchy":[
        "tgn:2156069",
        "tgn:1000001",
        "tgn:7012149",
        "tgn:2001713",
        "tgn:7007708",
        "tgn:7029392"
    ],
    "tgn:id":2156069,
    "tgn:name":"Bearcamp Ridge",
    "tgn:placetype":[
        "aat:300266640"
    ]
},
  "bbox": [],
  "geometry": {"coordinates":[-123.65,42.0167],"type":"Point"}
}
=======
{"geometry":{"type":"Point","coordinates":[-123.650000,42.016700]},"type":"Feature","properties":{"hierarchy":["tgn:2156069","tgn:1000001","tgn:7012149","tgn:2001713","tgn:7007708","tgn:7029392"],"placetype":["aat:300266640"],"id":2156069,"name:xx":"Bearcamp Ridge"}}
>>>>>>> 03f74aca74312dbeaf24d7e61306dd6a786dc3d0
