{
  "id": 7269095,
  "type": "Feature",
  "properties": {
    "tgn:concordances":{
        "gn:id":"2749785"
    },
    "tgn:hierarchy":[
        "tgn:7269095",
        "tgn:1000003",
        "tgn:7003624",
        "tgn:7016845",
        "tgn:7029392"
    ],
    "tgn:id":7269095,
    "tgn:name:nl":"Notsel",
    "tgn:placetype":[
        "aat:300008347"
    ]
},
  "bbox": [],
  "geometry": {"coordinates":[4.783333,51.533333],"type":"Point"}
}