{
  "id": 2367824,
  "type": "Feature",
  "properties": {
    "tgn:hierarchy":[
        "tgn:2367824",
        "tgn:1000001",
        "tgn:7012149",
        "tgn:1003017",
        "tgn:7007710",
        "tgn:7029392"
    ],
    "tgn:id":2367824,
    "tgn:name":"Grove Run Spring",
    "tgn:placetype":[
        "aat:300008697"
    ]
},
  "bbox": [],
  "geometry": {"coordinates":[-79.2167,40.15],"type":"Point"}
}