{
  "id": 7417610,
  "type": "Feature",
  "properties": {
    "tgn:hierarchy":[
        "tgn:7417610",
        "tgn:1000001",
        "tgn:7005591",
        "tgn:7005560",
        "tgn:7029392"
    ],
    "tgn:id":7417610,
    "tgn:name:es":"El Bajo",
    "tgn:placetype":[
        "aat:300008347"
    ]
},
  "bbox": [],
  "geometry": {"coordinates":[-95.031111,16.894722],"type":"Point"}
}