{
  "id": 7043299,
  "type": "Feature",
  "properties": {
    "tgn:hierarchy":[
        "tgn:7043299",
        "tgn:1003478",
        "tgn:1000003",
        "tgn:7003120",
        "tgn:1000080",
        "tgn:7029392"
    ],
    "tgn:id":7043299,
    "tgn:name":"Quarna Sopra",
    "tgn:placetype":[
        "aat:300008347"
    ]
},
  "bbox": [],
  "geometry": {"coordinates":[8.366667,45.866667],"type":"Point"}
}