{
  "id": 2511565,
  "type": "Feature",
  "properties": {
    "tgn:hierarchy":[
        "tgn:2511565",
        "tgn:1000001",
        "tgn:7012149",
        "tgn:7007710",
        "tgn:7029392"
    ],
    "tgn:id":2511565,
    "tgn:name":"Mile Run",
    "tgn:placetype":[
        "aat:300008699"
    ]
},
  "bbox": [],
  "geometry": {"coordinates":[-77.0833,41.0667],"type":"Point"}
}