<<<<<<< HEAD
{
  "id": 7028314,
  "type": "Feature",
  "properties": {
    "tgn:hierarchy":[
        "tgn:7028314",
        "tgn:7002445",
        "tgn:1000003",
        "tgn:7008160",
        "tgn:7008591",
        "tgn:7029392"
    ],
    "tgn:id":7028314,
    "tgn:name":"Old Buckenham",
    "tgn:placetype":[
        "aat:300008347",
        "aat:300008372"
    ]
},
  "bbox": [],
  "geometry": {"coordinates":[1.05,52.483333],"type":"Point"}
}
=======
{"geometry":{"type":"Point","coordinates":[1.050000,52.483333]},"type":"Feature","properties":{"hierarchy":["tgn:7028314","tgn:7002445","tgn:1000003","tgn:7008160","tgn:7008591","tgn:7029392"],"placetype":["aat:300008347","aat:300008372"],"id":7028314,"name:xx":"Old Buckenham"}}
>>>>>>> 03f74aca74312dbeaf24d7e61306dd6a786dc3d0
