{
  "id": 7566253,
  "type": "Feature",
  "properties": {
    "tgn:hierarchy":[
        "tgn:7566253",
        "tgn:1000004",
        "tgn:7000198",
        "tgn:1001894",
        "tgn:7029392"
    ],
    "tgn:id":7566253,
    "tgn:name:en":"Kush\u0101i",
    "tgn:placetype":[
        "aat:300008347"
    ]
},
  "bbox": [],
  "geometry": {"coordinates":[79.179156,24.584716],"type":"Point"}
}