{
  "id": 1097620,
  "type": "Feature",
  "properties": {
    "tgn:hierarchy":[
        "tgn:1097620",
        "tgn:7000490",
        "tgn:1000006",
        "tgn:7006238",
        "tgn:7029392"
    ],
    "tgn:id":1097620,
    "tgn:name":"Morwell",
    "tgn:placetype":[
        "aat:300008347"
    ]
},
  "bbox": [],
  "geometry": {"coordinates":[146.4167,-38.2333],"type":"Point"}
}