{
  "id": 2686243,
  "type": "Feature",
  "properties": {
    "tgn:hierarchy":[
        "tgn:2686243",
        "tgn:1000001",
        "tgn:7012149",
        "tgn:7007157",
        "tgn:7014516",
        "tgn:7029392"
    ],
    "tgn:id":2686243,
    "tgn:name":"Spring Creek",
    "tgn:placetype":[
        "aat:300008706"
    ]
},
  "bbox": [],
  "geometry": {"coordinates":[-123.1333,38.5167],"type":"Point"}
}