{
  "id": 2102190,
  "type": "Feature",
  "properties": {
    "tgn:hierarchy":[
        "tgn:2102190",
        "tgn:1000001",
        "tgn:7012149",
        "tgn:2001884",
        "tgn:7007825",
        "tgn:7029392"
    ],
    "tgn:id":2102190,
    "tgn:name":"Wynnburg",
    "tgn:placetype":[
        "aat:300008347"
    ]
},
  "bbox": [],
  "geometry": {"coordinates":[-89.4667,36.3167],"type":"Point"}
}