{
  "id": 2276086,
  "type": "Feature",
  "properties": {
    "tgn:hierarchy":[
        "tgn:2276086",
        "tgn:1000001",
        "tgn:7012149",
        "tgn:2000181",
        "tgn:7007157",
        "tgn:7029392"
    ],
    "tgn:id":2276086,
    "tgn:name":"Darnell Creek",
    "tgn:placetype":[
        "aat:300008706"
    ]
},
  "bbox": [],
  "geometry": {"coordinates":[-123.9667,40.45],"type":"Point"}
}