{
  "id": 2495265,
  "type": "Feature",
  "properties": {
    "tgn:hierarchy":[
        "tgn:2495265",
        "tgn:7002659",
        "tgn:1000001",
        "tgn:7012149",
        "tgn:2000048",
        "tgn:7029392"
    ],
    "tgn:id":2495265,
    "tgn:name":"Mary Ida Point",
    "tgn:placetype":[
        "aat:300008850"
    ]
},
  "bbox": [],
  "geometry": {"coordinates":[-87.9833,31.0167],"type":"Point"}
}