{
  "id": 2225586,
  "type": "Feature",
  "properties": {
    "tgn:hierarchy":[
        "tgn:2225586",
        "tgn:1000001",
        "tgn:7012149",
        "tgn:7007157",
        "tgn:1002684",
        "tgn:7029392"
    ],
    "tgn:id":2225586,
    "tgn:name":"Castro Canyon",
    "tgn:placetype":[
        "aat:300008761"
    ]
},
  "bbox": [],
  "geometry": {"coordinates":[-121.7167,36.2167],"type":"Point"}
}