<<<<<<< HEAD
{
  "id": 2400136,
  "type": "Feature",
  "properties": {
    "tgn:hierarchy":[
        "tgn:2400136",
        "tgn:2001562",
        "tgn:1000001",
        "tgn:7012149",
        "tgn:7007705",
        "tgn:7029392"
    ],
    "tgn:id":2400136,
    "tgn:name":"Horse Creek",
    "tgn:placetype":[
        "aat:300008706"
    ]
},
  "bbox": [],
  "geometry": {"coordinates":[-103.6833,46.0167],"type":"Point"}
}
=======
{"geometry":{"type":"Point","coordinates":[-103.683300,46.016700]},"type":"Feature","properties":{"hierarchy":["tgn:2400136","tgn:2001562","tgn:1000001","tgn:7012149","tgn:7007705","tgn:7029392"],"placetype":["aat:300008706"],"id":2400136,"name:xx":"Horse Creek"}}
>>>>>>> 03f74aca74312dbeaf24d7e61306dd6a786dc3d0
