{
  "id": 2331635,
  "type": "Feature",
  "properties": {
    "tgn:hierarchy":[
        "tgn:2331635",
        "tgn:1000001",
        "tgn:7012149",
        "tgn:1002875",
        "tgn:7007568",
        "tgn:7029392"
    ],
    "tgn:id":2331635,
    "tgn:name":"Fleet Cove",
    "tgn:placetype":[
        "aat:300132316"
    ]
},
  "bbox": [],
  "geometry": {"coordinates":[-77.0667,42.3833],"type":"Point"}
}