{
  "id": 7407784,
  "type": "Feature",
  "properties": {
    "tgn:hierarchy":[
        "tgn:7407784",
        "tgn:7005580",
        "tgn:1000001",
        "tgn:7005560",
        "tgn:7029392"
    ],
    "tgn:id":7407784,
    "tgn:name":"Mizpilla, Cerro",
    "tgn:placetype":[
        "aat:300008795"
    ]
},
  "bbox": [],
  "geometry": {"coordinates":[-92.533333,16.45],"type":"Point"}
}