{
  "id": 2271486,
  "type": "Feature",
  "properties": {
    "tgn:hierarchy":[
        "tgn:2271486",
        "tgn:1000001",
        "tgn:2000201",
        "tgn:7012149",
        "tgn:7007158",
        "tgn:7029392"
    ],
    "tgn:id":2271486,
    "tgn:name":"Cumberland Gulch",
    "tgn:placetype":[
        "aat:300008761"
    ]
},
  "bbox": [],
  "geometry": {"coordinates":[-105.6167,39.8167],"type":"Point"}
}