{
  "id": 2561900,
  "type": "Feature",
  "properties": {
    "tgn:hierarchy":[
        "tgn:2561900",
        "tgn:1000001",
        "tgn:7012149",
        "tgn:1003002",
        "tgn:7007922",
        "tgn:7029392"
    ],
    "tgn:id":2561900,
    "tgn:name":"Ottawa",
    "tgn:placetype":[
        "aat:300008347"
    ]
},
  "bbox": [],
  "geometry": {"coordinates":[-88.4333,42.9667],"type":"Point"}
}