{
  "id": 7160382,
  "type": "Feature",
  "properties": {
    "tgn:hierarchy":[
        "tgn:7160382",
        "tgn:7003692",
        "tgn:1000003",
        "tgn:7000084",
        "tgn:7029392"
    ],
    "tgn:id":7160382,
    "tgn:name":"Hofbauernhof",
    "tgn:placetype":[
        "aat:300000206"
    ]
},
  "bbox": [],
  "geometry": {"coordinates":[8.25,48.216667],"type":"Point"}
}