{
  "id": 2604001,
  "type": "Feature",
  "properties": {
    "tgn:hierarchy":[
        "tgn:2604001",
        "tgn:7002659",
        "tgn:1000001",
        "tgn:7012149",
        "tgn:2000029",
        "tgn:7029392"
    ],
    "tgn:id":2604001,
    "tgn:name":"Quinn Branch",
    "tgn:placetype":[
        "aat:300008699"
    ]
},
  "bbox": [],
  "geometry": {"coordinates":[-87.9167,34.4333],"type":"Point"}
}