{
  "id": 2396548,
  "type": "Feature",
  "properties": {
    "tgn:hierarchy":[
        "tgn:2396548",
        "tgn:1000001",
        "tgn:7012149",
        "tgn:7022542",
        "tgn:7007825",
        "tgn:7029392"
    ],
    "tgn:id":2396548,
    "tgn:name":"Holt Mine",
    "tgn:placetype":[
        "aat:300000390"
    ]
},
  "bbox": [],
  "geometry": {"coordinates":[-84.5667,35.6167],"type":"Point"}
}