{
  "id": 1017356,
  "type": "Feature",
  "properties": {
    "tgn:hierarchy":[
        "tgn:1017356",
        "tgn:1000001",
        "tgn:7005589",
        "tgn:7005560",
        "tgn:7029392"
    ],
    "tgn:id":1017356,
    "tgn:name":"Doctor Gonz\u00e1lez",
    "tgn:placetype":[
        "aat:300008347"
    ]
},
  "bbox": [],
  "geometry": {"coordinates":[-99.95,25.866667],"type":"Point"}
}