{
  "id": 7001773,
  "type": "Feature",
  "properties": {
    "tgn:hierarchy":[
        "tgn:7001773",
        "tgn:7016670",
        "tgn:1008380",
        "tgn:1000226",
        "tgn:1000006",
        "tgn:7029392"
    ],
    "tgn:id":7001773,
    "tgn:name:en":"Napier",
    "tgn:placetype":[
        "aat:300008347",
        "aat:300008389",
        "aat:300120599"
    ]
},
  "bbox": [],
  "geometry": {"coordinates":[176.916667,-39.483333],"type":"Point"}
}