{
  "id": 7315878,
  "type": "Feature",
  "properties": {
    "tgn:hierarchy":[
        "tgn:7315878",
        "tgn:1001708",
        "tgn:1000049",
        "tgn:1000002",
        "tgn:7029392"
    ],
    "tgn:id":7315878,
    "tgn:name":"Cementerio, Cerro",
    "tgn:placetype":[
        "aat:300008777"
    ]
},
  "bbox": [],
  "geometry": {"coordinates":[-71.45,-33.866667],"type":"Point"}
}