{
  "id": 7000672,
  "type": "Feature",
  "properties": {
    "tgn:hierarchy":[
        "tgn:7000672",
        "tgn:1010044",
        "tgn:7006219",
        "tgn:1000006",
        "tgn:7029392"
    ],
    "tgn:id":7000672,
    "tgn:name":"Alofi",
    "tgn:placetype":[
        "aat:300008791"
    ]
},
  "bbox": [],
  "geometry": {"coordinates":[-178.0833,-14.45],"type":"Point"}
}