{
  "id": 2345434,
  "type": "Feature",
  "properties": {
    "tgn:hierarchy":[
        "tgn:2345434",
        "tgn:1000001",
        "tgn:7012149",
        "tgn:2001458",
        "tgn:7007566",
        "tgn:7029392"
    ],
    "tgn:id":2345434,
    "tgn:name":"Garner Mine",
    "tgn:placetype":[
        "aat:300000390"
    ]
},
  "bbox": [],
  "geometry": {"coordinates":[-105.3833,34.4833],"type":"Point"}
}