{
  "id": 2332342,
  "type": "Feature",
  "properties": {
    "tgn:hierarchy":[
        "tgn:2332342",
        "tgn:1000001",
        "tgn:7012149",
        "tgn:1002518",
        "tgn:7007568",
        "tgn:7029392"
    ],
    "tgn:id":2332342,
    "tgn:name":"Floodwood Pond",
    "tgn:placetype":[
        "aat:300008680"
    ]
},
  "bbox": [],
  "geometry": {"coordinates":[-76.1833,43.7167],"type":"Point"}
}