{
  "id": 7282115,
  "type": "Feature",
  "properties": {
    "tgn:hierarchy":[
        "tgn:7282115",
        "tgn:7002464",
        "tgn:1000049",
        "tgn:1000002",
        "tgn:7029392"
    ],
    "tgn:id":7282115,
    "tgn:name":"Soronal, Cerro",
    "tgn:placetype":[
        "aat:300008795"
    ]
},
  "bbox": [],
  "geometry": {"coordinates":[-70.033333,-20.566667],"type":"Point"}
}