{
  "id": 7309811,
  "type": "Feature",
  "properties": {
    "tgn:hierarchy":[
        "tgn:7309811",
        "tgn:1001695",
        "tgn:1000049",
        "tgn:1000002",
        "tgn:7029392"
    ],
    "tgn:id":7309811,
    "tgn:name":"Mocho, Morro",
    "tgn:placetype":[
        "aat:300008795"
    ]
},
  "bbox": [],
  "geometry": {"coordinates":[-70.633333,-34.116667],"type":"Point"}
}