{
  "id": 2625747,
  "type": "Feature",
  "properties": {
    "tgn:hierarchy":[
        "tgn:2625747",
        "tgn:1000001",
        "tgn:7012149",
        "tgn:1002793",
        "tgn:7007240",
        "tgn:7029392"
    ],
    "tgn:id":2625747,
    "tgn:name":"Rocky Branch",
    "tgn:placetype":[
        "aat:300008699"
    ]
},
  "bbox": [],
  "geometry": {"coordinates":[-81.7333,27.7667],"type":"Point"}
}