{
  "id": 7093404,
  "type": "Feature",
  "properties": {
    "tgn:hierarchy":[
        "tgn:7093404",
        "tgn:1000003",
        "tgn:7000094",
        "tgn:7000084",
        "tgn:7029392"
    ],
    "tgn:id":7093404,
    "tgn:name":"Seelvitz",
    "tgn:placetype":[
        "aat:300008347"
    ]
},
  "bbox": [],
  "geometry": {"coordinates":[13.55,54.366667],"type":"Point"}
}