{
  "id": 7201396,
  "type": "Feature",
  "properties": {
    "tgn:hierarchy":[
        "tgn:7201396",
        "tgn:1000003",
        "tgn:7003676",
        "tgn:7000084",
        "tgn:7029392"
    ],
    "tgn:id":7201396,
    "tgn:name":"Breliendamm",
    "tgn:placetype":[
        "aat:300000206"
    ]
},
  "bbox": [],
  "geometry": {"coordinates":[9.816667,52.733333],"type":"Point"}
}