{
  "id": 2305675,
  "type": "Feature",
  "properties": {
    "tgn:hierarchy":[
        "tgn:2305675",
        "tgn:1000001",
        "tgn:7006451",
        "tgn:7012149",
        "tgn:2000103",
        "tgn:7029392"
    ],
    "tgn:id":2305675,
    "tgn:name":"East Copper Spring",
    "tgn:placetype":[
        "aat:300008697"
    ]
},
  "bbox": [],
  "geometry": {"coordinates":[-112.5333,34.4833],"type":"Point"}
}