{
  "id": 2309909,
  "type": "Feature",
  "properties": {
    "tgn:hierarchy":[
        "tgn:2309909",
        "tgn:1000001",
        "tgn:1002308",
        "tgn:7012149",
        "tgn:7007710",
        "tgn:7029392"
    ],
    "tgn:id":2309909,
    "tgn:name":"Eastman Hill",
    "tgn:placetype":[
        "aat:300008798"
    ]
},
  "bbox": [],
  "geometry": {"coordinates":[-79.65,41.8167],"type":"Point"}
}