{
  "id": 2340078,
  "type": "Feature",
  "properties": {
    "tgn:hierarchy":[
        "tgn:2340078",
        "tgn:1000001",
        "tgn:7012149",
        "tgn:2000491",
        "tgn:7007250",
        "tgn:7029392"
    ],
    "tgn:id":2340078,
    "tgn:name":"Freezeout Ridge",
    "tgn:placetype":[
        "aat:300266640"
    ]
},
  "bbox": [],
  "geometry": {"coordinates":[-116.0167,47.0167],"type":"Point"}
}