{
  "id": 7471333,
  "type": "Feature",
  "properties": {
    "tgn:hierarchy":[
        "tgn:7471333",
        "tgn:1000004",
        "tgn:7471332",
        "tgn:1000141",
        "tgn:7029392"
    ],
    "tgn:id":7471333,
    "tgn:name":"Xinzhuangzi Xi",
    "tgn:placetype":[
        "aat:300008699"
    ]
},
  "bbox": [],
  "geometry": {"coordinates":[120.966667,24.916667],"type":"Point"}
}