{
  "id": 7475685,
  "type": "Feature",
  "properties": {
    "tgn:hierarchy":[
        "tgn:7475685",
        "tgn:7488858",
        "tgn:1000004",
        "tgn:1000141",
        "tgn:7029392"
    ],
    "tgn:id":7475685,
    "tgn:name":"Shipai",
    "tgn:placetype":[
        "aat:300008347"
    ]
},
  "bbox": [],
  "geometry": {"coordinates":[120.788025,23.79664],"type":"Point"}
}