{
  "id": 2235025,
  "type": "Feature",
  "properties": {
    "tgn:hierarchy":[
        "tgn:2235025",
        "tgn:1000001",
        "tgn:2001782",
        "tgn:7012149",
        "tgn:7007713",
        "tgn:7029392"
    ],
    "tgn:id":2235025,
    "tgn:name":"Cherry Lake",
    "tgn:placetype":[
        "aat:300008680"
    ]
},
  "bbox": [],
  "geometry": {"coordinates":[-97.5167,44.5333],"type":"Point"}
}