{
  "id": 1073118,
  "type": "Feature",
  "properties": {
    "tgn:hierarchy":[
        "tgn:1073118",
        "tgn:1000004",
        "tgn:7001745",
        "tgn:1000111",
        "tgn:7029392"
    ],
    "tgn:id":1073118,
    "tgn:name":"Xinqu",
    "tgn:placetype":[
        "aat:300008347"
    ]
},
  "bbox": [],
  "geometry": {"coordinates":[85.25,44.95],"type":"Point"}
}