{
  "id": 7578752,
  "type": "Feature",
  "properties": {
    "tgn:hierarchy":[
        "tgn:7578752",
        "tgn:1000004",
        "tgn:1001869",
        "tgn:7000198",
        "tgn:7029392"
    ],
    "tgn:id":7578752,
    "tgn:name:en":"Tamsi River",
    "tgn:placetype":[
        "aat:300008699"
    ]
},
  "bbox": [],
  "geometry": {"coordinates":[73.45,22.216667],"type":"Point"}
}