{
  "id": 7205248,
  "type": "Feature",
  "properties": {
    "tgn:hierarchy":[
        "tgn:7205248",
        "tgn:1000003",
        "tgn:7003688",
        "tgn:7000084",
        "tgn:7029392"
    ],
    "tgn:id":7205248,
    "tgn:name":"Christinenhof",
    "tgn:placetype":[
        "aat:300000206"
    ]
},
  "bbox": [],
  "geometry": {"coordinates":[8.733333,54.75],"type":"Point"}
}