<<<<<<< HEAD
{
  "id": 2151527,
  "type": "Feature",
  "properties": {
    "tgn:hierarchy":[
        "tgn:2151527",
        "tgn:1000001",
        "tgn:1002260",
        "tgn:7012149",
        "tgn:7007920",
        "tgn:7029392"
    ],
    "tgn:id":2151527,
    "tgn:name":"Battalion Lake",
    "tgn:placetype":[
        "aat:300008680"
    ]
},
  "bbox": [],
  "geometry": {"coordinates":[-120.7833,48.3333],"type":"Point"}
}
=======
{"geometry":{"type":"Point","coordinates":[-120.783300,48.333300]},"type":"Feature","properties":{"hierarchy":["tgn:2151527","tgn:1000001","tgn:1002260","tgn:7012149","tgn:7007920","tgn:7029392"],"placetype":["aat:300008680"],"id":2151527,"name:xx":"Battalion Lake"}}
>>>>>>> 03f74aca74312dbeaf24d7e61306dd6a786dc3d0
