{
  "id": 7031948,
  "type": "Feature",
  "properties": {
    "tgn:hierarchy":[
        "tgn:7031948",
        "tgn:7001242",
        "tgn:7030585",
        "tgn:1000198",
        "tgn:7029392"
    ],
    "tgn:id":7031948,
    "tgn:name:en":"Visrivier Canyon",
    "tgn:placetype":[
        "aat:300008763"
    ]
},
  "bbox": [],
  "geometry": {"coordinates":[17.593,-27.666],"type":"Point"}
}