{
  "id": 2440267,
  "type": "Feature",
  "properties": {
    "tgn:hierarchy":[
        "tgn:2440267",
        "tgn:1000001",
        "tgn:2001805",
        "tgn:7012149",
        "tgn:7007713",
        "tgn:7029392"
    ],
    "tgn:id":2440267,
    "tgn:name":"Klinking Beard Draw",
    "tgn:placetype":[
        "aat:300008701"
    ]
},
  "bbox": [],
  "geometry": {"coordinates":[-101.25,43.5667],"type":"Point"}
}