{
  "id": 7151499,
  "type": "Feature",
  "properties": {
    "tgn:hierarchy":[
        "tgn:7151499",
        "tgn:7003669",
        "tgn:1000003",
        "tgn:7000084",
        "tgn:7029392"
    ],
    "tgn:id":7151499,
    "tgn:name":"Jenhausen",
    "tgn:placetype":[
        "aat:300008347"
    ]
},
  "bbox": [],
  "geometry": {"coordinates":[11.233333,47.833333],"type":"Point"}
}