<<<<<<< HEAD
{
  "id": 7360069,
  "type": "Feature",
  "properties": {
    "tgn:hierarchy":[
        "tgn:7360069",
        "tgn:1000001",
        "tgn:1001893",
        "tgn:7005560",
        "tgn:7029392"
    ],
    "tgn:id":7360069,
    "tgn:name":"Canal de Conexi\u00f3n",
    "tgn:placetype":[
        "aat:300006075"
    ]
},
  "bbox": [],
  "geometry": {"coordinates":[-114.7,32.733333],"type":"Point"}
}
=======
{"geometry":{"type":"Point","coordinates":[-114.700000,32.733333]},"type":"Feature","properties":{"hierarchy":["tgn:7360069","tgn:1000001","tgn:1001893","tgn:7005560","tgn:7029392"],"placetype":["aat:300006075"],"id":7360069,"name:xx":"Canal de Conexi\u00f3n"}}
>>>>>>> 03f74aca74312dbeaf24d7e61306dd6a786dc3d0
