{
  "id": 7356110,
  "type": "Feature",
  "properties": {
    "tgn:hierarchy":[
        "tgn:7356110",
        "tgn:1000001",
        "tgn:7005599",
        "tgn:7005560",
        "tgn:7029392"
    ],
    "tgn:id":7356110,
    "tgn:name":"Camarilla",
    "tgn:placetype":[
        "aat:300008347"
    ]
},
  "bbox": [],
  "geometry": {"coordinates":[-95.55,18.633333],"type":"Point"}
}