{
  "id": 2748192,
  "type": "Feature",
  "properties": {
    "tgn:hierarchy":[
        "tgn:2748192",
        "tgn:1000001",
        "tgn:7012149",
        "tgn:2001241",
        "tgn:7007523",
        "tgn:7029392"
    ],
    "tgn:id":2748192,
    "tgn:name":"Walker Branch",
    "tgn:placetype":[
        "aat:300008699"
    ]
},
  "bbox": [],
  "geometry": {"coordinates":[-90.45,37.85],"type":"Point"}
}