{
  "id": 2609882,
  "type": "Feature",
  "properties": {
    "tgn:hierarchy":[
        "tgn:2609882",
        "tgn:1000001",
        "tgn:7006451",
        "tgn:7012149",
        "tgn:7029392"
    ],
    "tgn:id":2609882,
    "tgn:name":"Reavis Creek",
    "tgn:placetype":[
        "aat:300008706"
    ]
},
  "bbox": [],
  "geometry": {"coordinates":[-111.1667,33.45],"type":"Point"}
}