{
  "id": 2611358,
  "type": "Feature",
  "properties": {
    "tgn:hierarchy":[
        "tgn:2611358",
        "tgn:1000001",
        "tgn:7012149",
        "tgn:2001667",
        "tgn:7007707",
        "tgn:7029392"
    ],
    "tgn:id":2611358,
    "tgn:name":"Red Lake",
    "tgn:placetype":[
        "aat:300008905"
    ]
},
  "bbox": [],
  "geometry": {"coordinates":[-95.0333,33.8833],"type":"Point"}
}