<<<<<<< HEAD
{
  "id": 7051421,
  "type": "Feature",
  "properties": {
    "tgn:hierarchy":[
        "tgn:7051421",
        "tgn:1003440",
        "tgn:1000003",
        "tgn:7003124",
        "tgn:1000080",
        "tgn:7029392"
    ],
    "tgn:id":7051421,
    "tgn:name":"La Cellettina",
    "tgn:placetype":[
        "aat:300008347"
    ]
},
  "bbox": [],
  "geometry": {"coordinates":[11.616667,49.2],"type":"Point"}
}
=======
{"geometry":{"type":"Point","coordinates":[11.616667,49.200000]},"type":"Feature","properties":{"hierarchy":["tgn:7051421","tgn:1003440","tgn:1000003","tgn:7003124","tgn:1000080","tgn:7029392"],"placetype":["aat:300008347"],"id":7051421,"name:xx":"La Cellettina"}}
>>>>>>> 03f74aca74312dbeaf24d7e61306dd6a786dc3d0
