{
  "id": 7434882,
  "type": "Feature",
  "properties": {
    "tgn:hierarchy":[
        "tgn:7434882",
        "tgn:1000001",
        "tgn:7005590",
        "tgn:7005560",
        "tgn:7029392"
    ],
    "tgn:id":7434882,
    "tgn:name":"Zinzimeo",
    "tgn:placetype":[
        "aat:300007783"
    ]
},
  "bbox": [],
  "geometry": {"coordinates":[-100.95,19.883333],"type":"Point"}
}