<<<<<<< HEAD
{
  "id": 7474977,
  "type": "Feature",
  "properties": {
    "tgn:hierarchy":[
        "tgn:7474977",
        "tgn:1000004",
        "tgn:7001014",
        "tgn:1000141",
        "tgn:7029392"
    ],
    "tgn:id":7474977,
    "tgn:name":"Douliu Shi",
    "tgn:placetype":[
        "aat:300387173"
    ]
},
  "bbox": [],
  "geometry": {"coordinates":[120.550278,23.716389],"type":"Point"}
}
=======
{"geometry":{"type":"Point","coordinates":[120.550278,23.716389]},"type":"Feature","properties":{"hierarchy":["tgn:7474977","tgn:1000004","tgn:7001014","tgn:1000141","tgn:7029392"],"placetype":["aat:300387173"],"id":7474977,"name:xx":"Douliu Shi"}}
>>>>>>> 03f74aca74312dbeaf24d7e61306dd6a786dc3d0
