{
  "id": 2581539,
  "type": "Feature",
  "properties": {
    "tgn:hierarchy":[
        "tgn:2581539",
        "tgn:2001837",
        "tgn:1000001",
        "tgn:7012149",
        "tgn:7007825",
        "tgn:7029392"
    ],
    "tgn:id":2581539,
    "tgn:name":"Pilot Mountain",
    "tgn:placetype":[
        "aat:300008798"
    ]
},
  "bbox": [],
  "geometry": {"coordinates":[-84.2667,36.1333],"type":"Point"}
}