<<<<<<< HEAD
{
  "id": 2253808,
  "type": "Feature",
  "properties": {
    "tgn:hierarchy":[
        "tgn:2253808",
        "tgn:7002659",
        "tgn:1000001",
        "tgn:2000017",
        "tgn:7012149",
        "tgn:7029392"
    ],
    "tgn:id":2253808,
    "tgn:name":"Cooks Crossroads",
    "tgn:placetype":[
        "aat:300008347"
    ]
},
  "bbox": [],
  "geometry": {"coordinates":[-86.9667,31.5667],"type":"Point"}
}
=======
{"geometry":{"type":"Point","coordinates":[-86.966700,31.566700]},"type":"Feature","properties":{"hierarchy":["tgn:2253808","tgn:7002659","tgn:1000001","tgn:2000017","tgn:7012149","tgn:7029392"],"placetype":["aat:300008347"],"id":2253808,"name:xx":"Cooks Crossroads"}}
>>>>>>> 03f74aca74312dbeaf24d7e61306dd6a786dc3d0
