{
  "id": 2410364,
  "type": "Feature",
  "properties": {
    "tgn:hierarchy":[
        "tgn:2410364",
        "tgn:2002137",
        "tgn:1000001",
        "tgn:7012149",
        "tgn:7007919",
        "tgn:7029392"
    ],
    "tgn:id":2410364,
    "tgn:name":"Indian Branch",
    "tgn:placetype":[
        "aat:300008699"
    ]
},
  "bbox": [],
  "geometry": {"coordinates":[-78.4167,37.9833],"type":"Point"}
}