{
  "id": 2190806,
  "type": "Feature",
  "properties": {
    "tgn:hierarchy":[
        "tgn:2190806",
        "tgn:1000001",
        "tgn:7016172",
        "tgn:7012149",
        "tgn:2000147",
        "tgn:7029392"
    ],
    "tgn:id":2190806,
    "tgn:name":"Boyd",
    "tgn:placetype":[
        "aat:300008347"
    ]
},
  "bbox": [],
  "geometry": {"coordinates":[-91.9167,34.5333],"type":"Point"}
}