{
  "id": 7453357,
  "type": "Feature",
  "properties": {
    "tgn:hierarchy":[
        "tgn:7453357",
        "tgn:7002445",
        "tgn:1000003",
        "tgn:7008127",
        "tgn:7008591",
        "tgn:7029392"
    ],
    "tgn:id":7453357,
    "tgn:name:en":"Caldron Snout",
    "tgn:placetype":[
        "aat:300008736"
    ]
},
  "bbox": [],
  "geometry": {"coordinates":[-2.283333,54.65],"type":"Point"}
}