{
  "id": 2315690,
  "type": "Feature",
  "properties": {
    "tgn:hierarchy":[
        "tgn:2315690",
        "tgn:1000001",
        "tgn:2001426",
        "tgn:7012149",
        "tgn:7007564",
        "tgn:7029392"
    ],
    "tgn:id":2315690,
    "tgn:name":"Ellison Brook",
    "tgn:placetype":[
        "aat:300008699"
    ]
},
  "bbox": [],
  "geometry": {"coordinates":[-70.9167,43.0833],"type":"Point"}
}