{
  "id": 2392103,
  "type": "Feature",
  "properties": {
    "tgn:hierarchy":[
        "tgn:2392103",
        "tgn:1000001",
        "tgn:7012149",
        "tgn:2001206",
        "tgn:7007523",
        "tgn:7029392"
    ],
    "tgn:id":2392103,
    "tgn:name":"Hines Hill",
    "tgn:placetype":[
        "aat:300008798"
    ]
},
  "bbox": [],
  "geometry": {"coordinates":[-91.85,36.7167],"type":"Point"}
}