{
  "id": 2213390,
  "type": "Feature",
  "properties": {
    "tgn:hierarchy":[
        "tgn:2213390",
        "tgn:1000001",
        "tgn:7012149",
        "tgn:2002129",
        "tgn:7007827",
        "tgn:7029392"
    ],
    "tgn:id":2213390,
    "tgn:name":"Cabin Hollow",
    "tgn:placetype":[
        "aat:300008761"
    ]
},
  "bbox": [],
  "geometry": {"coordinates":[-111.4667,41.3833],"type":"Point"}
}