{
  "id": 7233156,
  "type": "Feature",
  "properties": {
    "tgn:hierarchy":[
        "tgn:7233156",
        "tgn:7002750",
        "tgn:7001399",
        "tgn:1000003",
        "tgn:1000074",
        "tgn:7029392"
    ],
    "tgn:id":7233156,
    "tgn:name":"K\u00e1to \u00d3limbos, \u00d3ros",
    "tgn:placetype":[
        "aat:300008795"
    ]
},
  "bbox": [],
  "geometry": {"coordinates":[22.466667,39.916667],"type":"Point"}
}