<<<<<<< HEAD
{
  "id": 2150195,
  "type": "Feature",
  "properties": {
    "tgn:hierarchy":[
        "tgn:2150195",
        "tgn:1000001",
        "tgn:2000464",
        "tgn:7012149",
        "tgn:7007250",
        "tgn:7029392"
    ],
    "tgn:id":2150195,
    "tgn:name":"Basalt Creek",
    "tgn:placetype":[
        "aat:300008706"
    ]
},
  "bbox": [],
  "geometry": {"coordinates":[-114.7333,43.4667],"type":"Point"}
}
=======
{"geometry":{"type":"Point","coordinates":[-114.733300,43.466700]},"type":"Feature","properties":{"hierarchy":["tgn:2150195","tgn:1000001","tgn:2000464","tgn:7012149","tgn:7007250","tgn:7029392"],"placetype":["aat:300008706"],"id":2150195,"name:xx":"Basalt Creek"}}
>>>>>>> 03f74aca74312dbeaf24d7e61306dd6a786dc3d0
