{
  "id": 7497485,
  "type": "Feature",
  "properties": {
    "tgn:hierarchy":[
        "tgn:7497485",
        "tgn:1000004",
        "tgn:7492971",
        "tgn:1000141",
        "tgn:7029392"
    ],
    "tgn:id":7497485,
    "tgn:name":"Kecuo",
    "tgn:placetype":[
        "aat:300008347"
    ]
},
  "bbox": [],
  "geometry": {"coordinates":[120.471364,22.595896],"type":"Point"}
}