<<<<<<< HEAD
{
  "id": 7355917,
  "type": "Feature",
  "properties": {
    "tgn:hierarchy":[
        "tgn:7355917",
        "tgn:7005584",
        "tgn:1000001",
        "tgn:7005560",
        "tgn:7029392"
    ],
    "tgn:id":7355917,
    "tgn:name":"Carbonera de Guadalupe",
    "tgn:placetype":[
        "aat:300008347"
    ]
},
  "bbox": [],
  "geometry": {"coordinates":[-100.466667,21.15],"type":"Point"}
}
=======
{"geometry":{"type":"Point","coordinates":[-100.466667,21.150000]},"type":"Feature","properties":{"hierarchy":["tgn:7355917","tgn:7005584","tgn:1000001","tgn:7005560","tgn:7029392"],"placetype":["aat:300008347"],"id":7355917,"name:xx":"Carbonera de Guadalupe"}}
>>>>>>> 03f74aca74312dbeaf24d7e61306dd6a786dc3d0
