{
  "id": 7457585,
  "type": "Feature",
  "properties": {
    "tgn:hierarchy":[
        "tgn:7457585",
        "tgn:7002443",
        "tgn:1000003",
        "tgn:7008050",
        "tgn:7008591",
        "tgn:7029392"
    ],
    "tgn:id":7457585,
    "tgn:name:en":"Pennant-Melangell",
    "tgn:placetype":[
        "aat:300008347"
    ]
},
  "bbox": [],
  "geometry": {"coordinates":[-3.45,52.816667],"type":"Point"}
}