{
  "id": 7343956,
  "type": "Feature",
  "properties": {
    "tgn:hierarchy":[
        "tgn:7343956",
        "tgn:7002758",
        "tgn:7002821",
        "tgn:1000003",
        "tgn:1000095",
        "tgn:7029392"
    ],
    "tgn:id":7343956,
    "tgn:name":"Caparacena",
    "tgn:placetype":[
        "aat:300008347"
    ]
},
  "bbox": [],
  "geometry": {"coordinates":[-3.716667,37.266667],"type":"Point"}
}