<<<<<<< HEAD
{
  "id": 7054099,
  "type": "Feature",
  "properties": {
    "tgn:hierarchy":[
        "tgn:7054099",
        "tgn:7003011",
        "tgn:7003005",
        "tgn:1000003",
        "tgn:1000080",
        "tgn:7029392"
    ],
    "tgn:id":7054099,
    "tgn:name":"Lupo, Fosso del",
    "tgn:placetype":[
        "aat:300008699"
    ]
},
  "bbox": [],
  "geometry": {"coordinates":[13.9,41.416667],"type":"Point"}
}
=======
{"geometry":{"type":"Point","coordinates":[13.900000,41.416667]},"type":"Feature","properties":{"hierarchy":["tgn:7054099","tgn:7003011","tgn:7003005","tgn:1000003","tgn:1000080","tgn:7029392"],"placetype":["aat:300008699"],"id":7054099,"name:xx":"Lupo, Fosso del"}}
>>>>>>> 03f74aca74312dbeaf24d7e61306dd6a786dc3d0
