<<<<<<< HEAD
{
  "id": 2335368,
  "type": "Feature",
  "properties": {
    "tgn:hierarchy":[
        "tgn:2335368",
        "tgn:1000001",
        "tgn:7012149",
        "tgn:1002467",
        "tgn:7007919",
        "tgn:7029392"
    ],
    "tgn:id":2335368,
    "tgn:name":"Fort Lee",
    "tgn:placetype":[
        "aat:300008347"
    ]
},
  "bbox": [],
  "geometry": {"coordinates":[-77.3333,37.4833],"type":"Point"}
}
=======
{"geometry":{"type":"Point","coordinates":[-77.333300,37.483300]},"type":"Feature","properties":{"hierarchy":["tgn:2335368","tgn:1000001","tgn:7012149","tgn:1002467","tgn:7007919","tgn:7029392"],"placetype":["aat:300008347"],"id":2335368,"name:xx":"Fort Lee"}}
>>>>>>> 03f74aca74312dbeaf24d7e61306dd6a786dc3d0
