{
  "id": 2347169,
  "type": "Feature",
  "properties": {
    "tgn:hierarchy":[
        "tgn:2347169",
        "tgn:1000001",
        "tgn:7012149",
        "tgn:2000975",
        "tgn:7007520",
        "tgn:7029392"
    ],
    "tgn:id":2347169,
    "tgn:name":"Gentian",
    "tgn:placetype":[
        "aat:300008347"
    ]
},
  "bbox": [],
  "geometry": {"coordinates":[-87.4667,46.4167],"type":"Point"}
}