{
  "id": 7414461,
  "type": "Feature",
  "properties": {
    "tgn:hierarchy":[
        "tgn:7414461",
        "tgn:7005584",
        "tgn:1000001",
        "tgn:7005560",
        "tgn:7029392"
    ],
    "tgn:id":7414461,
    "tgn:name":"El Para\u00edso",
    "tgn:placetype":[
        "aat:300008347"
    ]
},
  "bbox": [],
  "geometry": {"coordinates":[-101.0375,20.316389],"type":"Point"}
}