{
  "id": 1096671,
  "type": "Feature",
  "properties": {
    "tgn:hierarchy":[
        "tgn:1096671",
        "tgn:7000490",
        "tgn:1000006",
        "tgn:7006238",
        "tgn:7029392"
    ],
    "tgn:id":1096671,
    "tgn:name":"Cressy",
    "tgn:placetype":[
        "aat:300008347"
    ]
},
  "bbox": [],
  "geometry": {"coordinates":[143.6333,-38.0333],"type":"Point"}
}