{
  "id": 2512338,
  "type": "Feature",
  "properties": {
    "tgn:hierarchy":[
        "tgn:2512338",
        "tgn:1000001",
        "tgn:7012149",
        "tgn:2002116",
        "tgn:7007827",
        "tgn:7029392"
    ],
    "tgn:id":2512338,
    "tgn:name":"Mill Canyon",
    "tgn:placetype":[
        "aat:300008761"
    ]
},
  "bbox": [],
  "geometry": {"coordinates":[-112.3167,38.3333],"type":"Point"}
}