{
  "id": 2132160,
  "type": "Feature",
  "properties": {
    "tgn:hierarchy":[
        "tgn:2132160",
        "tgn:1000001",
        "tgn:7012149",
        "tgn:1003042",
        "tgn:7007920",
        "tgn:7029392"
    ],
    "tgn:id":2132160,
    "tgn:name":"American River",
    "tgn:placetype":[
        "aat:300008347"
    ]
},
  "bbox": [],
  "geometry": {"coordinates":[-121.15,46.9667],"type":"Point"}
}