{
  "id": 7516335,
  "type": "Feature",
  "properties": {
    "tgn:hierarchy":[
        "tgn:7516335",
        "tgn:1009227",
        "tgn:7001866",
        "tgn:1000226",
        "tgn:1000006",
        "tgn:7029392"
    ],
    "tgn:id":7516335,
    "tgn:name:en":"Lauriston",
    "tgn:placetype":[
        "aat:300008347"
    ]
},
  "bbox": [],
  "geometry": {"coordinates":[171.783333,-43.733333],"type":"Point"}
}