{
  "id": 7067656,
  "type": "Feature",
  "properties": {
    "tgn:hierarchy":[
        "tgn:7067656",
        "tgn:1000003",
        "tgn:7003687",
        "tgn:7000084",
        "tgn:7029392"
    ],
    "tgn:id":7067656,
    "tgn:name":"Tr\u00e4nken-Berg",
    "tgn:placetype":[
        "aat:300008777"
    ]
},
  "bbox": [],
  "geometry": {"coordinates":[11.733333,52.216667],"type":"Point"}
}