{
  "id": 7428910,
  "type": "Feature",
  "properties": {
    "tgn:hierarchy":[
        "tgn:7428910",
        "tgn:7005586",
        "tgn:1000001",
        "tgn:7005560",
        "tgn:7029392"
    ],
    "tgn:id":7428910,
    "tgn:name":"Tlacosanua",
    "tgn:placetype":[
        "aat:300008347"
    ]
},
  "bbox": [],
  "geometry": {"coordinates":[-103.166667,22.266667],"type":"Point"}
}