{
  "id": 7331687,
  "type": "Feature",
  "properties": {
    "tgn:hierarchy":[
        "tgn:7331687",
        "tgn:7002826",
        "tgn:7001158",
        "tgn:1000003",
        "tgn:1000095",
        "tgn:7029392"
    ],
    "tgn:id":7331687,
    "tgn:name":"La Pola de Gord\u00f3n",
    "tgn:placetype":[
        "aat:300008347"
    ]
},
  "bbox": [],
  "geometry": {"coordinates":[-5.683333,42.85],"type":"Point"}
}