{
  "id": 7084924,
  "type": "Feature",
  "properties": {
    "tgn:hierarchy":[
        "tgn:7084924",
        "tgn:1000003",
        "tgn:7003688",
        "tgn:7000084",
        "tgn:7029392"
    ],
    "tgn:id":7084924,
    "tgn:name":"Wei\u00dfer Hirsch",
    "tgn:placetype":[
        "aat:300000206"
    ]
},
  "bbox": [],
  "geometry": {"coordinates":[10.816667,53.666667],"type":"Point"}
}