{
  "id": 7497796,
  "type": "Feature",
  "properties": {
    "tgn:hierarchy":[
        "tgn:7497796",
        "tgn:1000004",
        "tgn:7001009",
        "tgn:1000141",
        "tgn:7029392"
    ],
    "tgn:id":7497796,
    "tgn:name":"Yinlian Yi Qiao",
    "tgn:placetype":[
        "aat:300007836"
    ]
},
  "bbox": [],
  "geometry": {"coordinates":[120.724021,24.085448],"type":"Point"}
}