{
  "id": 2290348,
  "type": "Feature",
  "properties": {
    "tgn:hierarchy":[
        "tgn:2290348",
        "tgn:1000001",
        "tgn:7012149",
        "tgn:2001706",
        "tgn:7007708",
        "tgn:7029392"
    ],
    "tgn:id":2290348,
    "tgn:name":"Dodson Butte",
    "tgn:placetype":[
        "aat:300008798"
    ]
},
  "bbox": [],
  "geometry": {"coordinates":[-123.2333,43.1167],"type":"Point"}
}