{
  "id": 2242818,
  "type": "Feature",
  "properties": {
    "tgn:hierarchy":[
        "tgn:2242818",
        "tgn:1000001",
        "tgn:1002260",
        "tgn:7012149",
        "tgn:7007920",
        "tgn:7029392"
    ],
    "tgn:id":2242818,
    "tgn:name":"Clear Creek",
    "tgn:placetype":[
        "aat:300008706"
    ]
},
  "bbox": [],
  "geometry": {"coordinates":[-120.85,48.4333],"type":"Point"}
}