{
  "id": 7467287,
  "type": "Feature",
  "properties": {
    "tgn:hierarchy":[
        "tgn:7467287",
        "tgn:7487020",
        "tgn:1000004",
        "tgn:1000141",
        "tgn:7029392"
    ],
    "tgn:id":7467287,
    "tgn:name":"Qianliang Shan",
    "tgn:placetype":[
        "aat:300008798",
        "aat:300387002"
    ]
},
  "bbox": [],
  "geometry": {"coordinates":[120.949069,24.368582],"type":"Point"}
}