{
  "id": 7455534,
  "type": "Feature",
  "properties": {
    "tgn:hierarchy":[
        "tgn:7455534",
        "tgn:7002445",
        "tgn:1000003",
        "tgn:7008118",
        "tgn:7008591",
        "tgn:7029392"
    ],
    "tgn:id":7455534,
    "tgn:name:en":"Codnor Park Station",
    "tgn:placetype":[
        "aat:300007783"
    ]
},
  "bbox": [],
  "geometry": {"coordinates":[-1.35,53.05],"type":"Point"}
}