{
  "id": 2350651,
  "type": "Feature",
  "properties": {
    "tgn:hierarchy":[
        "tgn:2350651",
        "tgn:7006450",
        "tgn:1000001",
        "tgn:7030547",
        "tgn:7012149",
        "tgn:7029392"
    ],
    "tgn:id":2350651,
    "tgn:name":"Glacier Peak",
    "tgn:placetype":[
        "aat:300008798"
    ]
},
  "bbox": [],
  "geometry": {"coordinates":[-150.7833,63.5667],"type":"Point"}
}