{
  "id": 2516538,
  "type": "Feature",
  "properties": {
    "tgn:hierarchy":[
        "tgn:2516538",
        "tgn:1002145",
        "tgn:1000001",
        "tgn:7012149",
        "tgn:7007157",
        "tgn:7029392"
    ],
    "tgn:id":2516538,
    "tgn:name":"Mineral Mountain",
    "tgn:placetype":[
        "aat:300008798"
    ]
},
  "bbox": [],
  "geometry": {"coordinates":[-119.6167,38.5167],"type":"Point"}
}