{
  "id": 7199901,
  "type": "Feature",
  "properties": {
    "tgn:hierarchy":[
        "tgn:7199901",
        "tgn:7003669",
        "tgn:1000003",
        "tgn:7000084",
        "tgn:7029392"
    ],
    "tgn:id":7199901,
    "tgn:name":"Eichel-Berg",
    "tgn:placetype":[
        "aat:300008777"
    ]
},
  "bbox": [],
  "geometry": {"coordinates":[10.716667,50.366667],"type":"Point"}
}