{
  "id": 7556741,
  "type": "Feature",
  "properties": {
    "tgn:hierarchy":[
        "tgn:7556741",
        "tgn:1000004",
        "tgn:1001842",
        "tgn:7000198",
        "tgn:7029392"
    ],
    "tgn:id":7556741,
    "tgn:name:en":"Ram Bhawan",
    "tgn:placetype":[
        "aat:300007783"
    ]
},
  "bbox": [],
  "geometry": {"coordinates":[85.239056,25.252835],"type":"Point"}
}