{
  "id": 7513806,
  "type": "Feature",
  "properties": {
    "tgn:hierarchy":[
        "tgn:7513806",
        "tgn:1009227",
        "tgn:1000226",
        "tgn:7016822",
        "tgn:1000006",
        "tgn:7029392"
    ],
    "tgn:id":7513806,
    "tgn:name:en":"Flat Hill",
    "tgn:placetype":[
        "aat:300008795"
    ]
},
  "bbox": [],
  "geometry": {"coordinates":[168.816667,-45.65],"type":"Point"}
}