{
  "id": 7401808,
  "type": "Feature",
  "properties": {
    "tgn:hierarchy":[
        "tgn:7401808",
        "tgn:1000001",
        "tgn:7005599",
        "tgn:7005560",
        "tgn:7029392"
    ],
    "tgn:id":7401808,
    "tgn:name":"El Tamarindo",
    "tgn:placetype":[
        "aat:300008347"
    ]
},
  "bbox": [],
  "geometry": {"coordinates":[-96.454167,18.948611],"type":"Point"}
}