<<<<<<< HEAD
{
  "id": 7021000,
  "type": "Feature",
  "properties": {
    "tgn:hierarchy":[
        "tgn:7021000",
        "tgn:1000001",
        "tgn:7012149",
        "tgn:2000494",
        "tgn:7007250",
        "tgn:7029392"
    ],
    "tgn:id":7021000,
    "tgn:name":"Warner Pond",
    "tgn:placetype":[
        "aat:300008680",
        "aat:300006191"
    ]
},
  "bbox": [],
  "geometry": {"coordinates":[-115.95,44.4833],"type":"Point"}
}
=======
{"geometry":{"type":"Point","coordinates":[-115.950000,44.483300]},"type":"Feature","properties":{"hierarchy":["tgn:7021000","tgn:1000001","tgn:7012149","tgn:2000494","tgn:7007250","tgn:7029392"],"placetype":["aat:300008680","aat:300006191"],"id":7021000,"name:xx":"Warner Pond"}}
>>>>>>> 03f74aca74312dbeaf24d7e61306dd6a786dc3d0
