{
  "id": 2162616,
  "type": "Feature",
  "properties": {
    "tgn:hierarchy":[
        "tgn:2162616",
        "tgn:1000001",
        "tgn:7012149",
        "tgn:2000205",
        "tgn:7007158",
        "tgn:7029392"
    ],
    "tgn:id":2162616,
    "tgn:name":"Bench Lake",
    "tgn:placetype":[
        "aat:300008680"
    ]
},
  "bbox": [],
  "geometry": {"coordinates":[-105.5667,37.9667],"type":"Point"}
}