{
  "id": 1072495,
  "type": "Feature",
  "properties": {
    "tgn:hierarchy":[
        "tgn:1072495",
        "tgn:1000004",
        "tgn:7001838",
        "tgn:1000111",
        "tgn:7029392"
    ],
    "tgn:id":1072495,
    "tgn:name":"Wangyefu",
    "tgn:placetype":[
        "aat:300008347"
    ]
},
  "bbox": [],
  "geometry": {"coordinates":[118.3833,41.8333],"type":"Point"}
}