{
  "id": 7477660,
  "type": "Feature",
  "properties": {
    "tgn:hierarchy":[
        "tgn:7477660",
        "tgn:1000004",
        "tgn:1000454",
        "tgn:1000141",
        "tgn:7029392"
    ],
    "tgn:id":7477660,
    "tgn:name":"Sanchagang Shan",
    "tgn:placetype":[
        "aat:300008777"
    ]
},
  "bbox": [],
  "geometry": {"coordinates":[121.8818,25.0421],"type":"Point"}
}