<<<<<<< HEAD
{
  "id": 7477660,
  "type": "Feature",
  "properties": {
    "tgn:hierarchy":[
        "tgn:7477660",
        "tgn:1000004",
        "tgn:1000454",
        "tgn:1000141",
        "tgn:7029392"
    ],
    "tgn:id":7477660,
    "tgn:name":"Sanchagang Shan",
    "tgn:placetype":[
        "aat:300008777"
    ]
},
  "bbox": [],
  "geometry": {"coordinates":[121.8818,25.0421],"type":"Point"}
}
=======
{"geometry":{"type":"Point","coordinates":[121.881800,25.042100]},"type":"Feature","properties":{"hierarchy":["tgn:7477660","tgn:1000004","tgn:1000454","tgn:1000141","tgn:7029392"],"placetype":["aat:300008777"],"id":7477660,"name:xx":"Sanchagang Shan"}}
>>>>>>> 03f74aca74312dbeaf24d7e61306dd6a786dc3d0
