{
  "id": 1055782,
  "type": "Feature",
  "properties": {
    "tgn:hierarchy":[
        "tgn:1055782",
        "tgn:6000729",
        "tgn:1000004",
        "tgn:7018214",
        "tgn:7002435",
        "tgn:7029392"
    ],
    "tgn:id":1055782,
    "tgn:name":"Krasnaya Yaruga",
    "tgn:placetype":[
        "aat:300008347"
    ]
},
  "bbox": [],
  "geometry": {"coordinates":[35.6833,50.8333],"type":"Point"}
}