{
  "id": 7521914,
  "type": "Feature",
  "properties": {
    "tgn:hierarchy":[
        "tgn:7521914",
        "tgn:7001242",
        "tgn:7001311",
        "tgn:7016833",
        "tgn:7029392"
    ],
    "tgn:id":7521914,
    "tgn:name:en":"Ab\u016b Murrah, Jabal",
    "tgn:placetype":[
        "aat:300008795"
    ]
},
  "bbox": [],
  "geometry": {"coordinates":[33.79854,26.795498],"type":"Point"}
}