{
  "id": 7272819,
  "type": "Feature",
  "properties": {
    "tgn:hierarchy":[
        "tgn:7272819",
        "tgn:1000003",
        "tgn:7003632",
        "tgn:7016845",
        "tgn:7029392"
    ],
    "tgn:id":7272819,
    "tgn:name:nl":"Recreatieterrein Vredepolder",
    "tgn:placetype":[
        "aat:300008187"
    ]
},
  "bbox": [],
  "geometry": {"coordinates":[4.516667,51.833333],"type":"Point"}
}