{
  "id": 2035468,
  "type": "Feature",
  "properties": {
    "tgn:hierarchy":[
        "tgn:2035468",
        "tgn:1000001",
        "tgn:2000569",
        "tgn:7012149",
        "tgn:7007253",
        "tgn:7029392"
    ],
    "tgn:id":2035468,
    "tgn:name":"Plainfield",
    "tgn:placetype":[
        "aat:300008347"
    ]
},
  "bbox": [],
  "geometry": {"coordinates":[-92.5333,42.8333],"type":"Point"}
}