{
  "id": 7571293,
  "type": "Feature",
  "properties": {
    "tgn:hierarchy":[
        "tgn:7571293",
        "tgn:1000004",
        "tgn:1001842",
        "tgn:7000198",
        "tgn:7029392"
    ],
    "tgn:id":7571293,
    "tgn:name:en":"Ghusiya Kal\u0101n",
    "tgn:placetype":[
        "aat:300008347"
    ]
},
  "bbox": [],
  "geometry": {"coordinates":[84.24833,25.183758],"type":"Point"}
}