{
  "id": 2210577,
  "type": "Feature",
  "properties": {
    "tgn:hierarchy":[
        "tgn:2210577",
        "tgn:1000001",
        "tgn:7012149",
        "tgn:2001158",
        "tgn:7007522",
        "tgn:7029392"
    ],
    "tgn:id":2210577,
    "tgn:name":"Bussel Creek",
    "tgn:placetype":[
        "aat:300008706"
    ]
},
  "bbox": [],
  "geometry": {"coordinates":[-88.8333,34.5667],"type":"Point"}
}