{
  "id": 2758093,
  "type": "Feature",
  "properties": {
    "tgn:hierarchy":[
        "tgn:2758093",
        "tgn:1000001",
        "tgn:7012149",
        "tgn:2002354",
        "tgn:7007922",
        "tgn:7029392"
    ],
    "tgn:id":2758093,
    "tgn:name":"West Branch Shioc River",
    "tgn:placetype":[
        "aat:300008707"
    ]
},
  "bbox": [],
  "geometry": {"coordinates":[-88.4333,44.75],"type":"Point"}
}