{
  "id": 2600644,
  "type": "Feature",
  "properties": {
    "tgn:hierarchy":[
        "tgn:2600644",
        "tgn:1000001",
        "tgn:7012149",
        "tgn:7007709",
        "tgn:7029392"
    ],
    "tgn:id":2600644,
    "tgn:name":"Pulley Pond",
    "tgn:placetype":[
        "aat:300006191"
    ]
},
  "bbox": [],
  "geometry": {"coordinates":[-77.65,35.35],"type":"Point"}
}