{
  "id": 7343358,
  "type": "Feature",
  "properties": {
    "tgn:hierarchy":[
        "tgn:7343358",
        "tgn:7002758",
        "tgn:7002821",
        "tgn:1000003",
        "tgn:1000095",
        "tgn:7029392"
    ],
    "tgn:id":7343358,
    "tgn:name":"Campot\u00e9jar",
    "tgn:placetype":[
        "aat:300008347"
    ]
},
  "bbox": [],
  "geometry": {"coordinates":[-3.616667,37.483333],"type":"Point"}
}