{
  "id": 7581343,
  "type": "Feature",
  "properties": {
    "tgn:hierarchy":[
        "tgn:7581343",
        "tgn:1000004",
        "tgn:7000198",
        "tgn:1003539",
        "tgn:7029392"
    ],
    "tgn:id":7581343,
    "tgn:name:en":"Sutnga",
    "tgn:placetype":[
        "aat:300008347"
    ]
},
  "bbox": [],
  "geometry": {"coordinates":[92.437478,25.37042],"type":"Point"}
}