<<<<<<< HEAD
{
  "id": 7177351,
  "type": "Feature",
  "properties": {
    "tgn:hierarchy":[
        "tgn:7177351",
        "tgn:1000003",
        "tgn:7003677",
        "tgn:7000084",
        "tgn:7029392"
    ],
    "tgn:id":7177351,
    "tgn:name":"Haldem",
    "tgn:placetype":[
        "aat:300008347"
    ]
},
  "bbox": [],
  "geometry": {"coordinates":[8.383333,52.433333],"type":"Point"}
}
=======
{"geometry":{"type":"Point","coordinates":[8.383333,52.433333]},"type":"Feature","properties":{"hierarchy":["tgn:7177351","tgn:1000003","tgn:7003677","tgn:7000084","tgn:7029392"],"placetype":["aat:300008347"],"id":7177351,"name:xx":"Haldem"}}
>>>>>>> 03f74aca74312dbeaf24d7e61306dd6a786dc3d0
