{
  "id": 1055858,
  "type": "Feature",
  "properties": {
    "tgn:hierarchy":[
        "tgn:1055858",
        "tgn:1008198",
        "tgn:1000004",
        "tgn:1003406",
        "tgn:7018214",
        "tgn:7002435",
        "tgn:7029392"
    ],
    "tgn:id":1055858,
    "tgn:name":"Krasnyj",
    "tgn:placetype":[
        "aat:300008347"
    ]
},
  "bbox": [],
  "geometry": {"coordinates":[141.25,46.25],"type":"Point"}
}