{
  "id": 2238137,
  "type": "Feature",
  "properties": {
    "tgn:hierarchy":[
        "tgn:2238137",
        "tgn:1000001",
        "tgn:7012149",
        "tgn:7007828",
        "tgn:7029392"
    ],
    "tgn:id":2238137,
    "tgn:name":"Chittenden Brook",
    "tgn:placetype":[
        "aat:300008699"
    ]
},
  "bbox": [],
  "geometry": {"coordinates":[-72.9333,43.8167],"type":"Point"}
}