{
  "id": 2659064,
  "type": "Feature",
  "properties": {
    "tgn:hierarchy":[
        "tgn:2659064",
        "tgn:1000001",
        "tgn:7012149",
        "tgn:2002250",
        "tgn:7007920",
        "tgn:7029392"
    ],
    "tgn:id":2659064,
    "tgn:name":"Sherwood Mountain",
    "tgn:placetype":[
        "aat:300008798"
    ]
},
  "bbox": [],
  "geometry": {"coordinates":[-117.9333,47.8667],"type":"Point"}
}