{
  "id": 2593827,
  "type": "Feature",
  "properties": {
    "tgn:hierarchy":[
        "tgn:2593827",
        "tgn:7006450",
        "tgn:1000001",
        "tgn:7012149",
        "tgn:2000088",
        "tgn:7029392"
    ],
    "tgn:id":2593827,
    "tgn:name":"Port Camden",
    "tgn:placetype":[
        "aat:300132316"
    ]
},
  "bbox": [],
  "geometry": {"coordinates":[-133.9167,56.7167],"type":"Point"}
}