{
  "id": 7174565,
  "type": "Feature",
  "properties": {
    "tgn:hierarchy":[
        "tgn:7174565",
        "tgn:7000096",
        "tgn:1000003",
        "tgn:7000084",
        "tgn:7029392"
    ],
    "tgn:id":7174565,
    "tgn:name":"Gro\u00dfer Kelpinsee",
    "tgn:placetype":[
        "aat:300008680"
    ]
},
  "bbox": [],
  "geometry": {"coordinates":[13.733333,53.05],"type":"Point"}
}