{
  "id": 7538649,
  "type": "Feature",
  "properties": {
    "tgn:hierarchy":[
        "tgn:7538649",
        "tgn:7001242",
        "tgn:7016833",
        "tgn:7001312",
        "tgn:7029392"
    ],
    "tgn:id":7538649,
    "tgn:name:en":"Muj\u016bl",
    "tgn:placetype":[
        "aat:300008347"
    ]
},
  "bbox": [],
  "geometry": {"coordinates":[31.224723,31.027121],"type":"Point"}
}