{
  "id": 2381351,
  "type": "Feature",
  "properties": {
    "tgn:hierarchy":[
        "tgn:2381351",
        "tgn:1000001",
        "tgn:2001703",
        "tgn:7012149",
        "tgn:7007708",
        "tgn:7029392"
    ],
    "tgn:id":2381351,
    "tgn:name":"Hawthorne Spring",
    "tgn:placetype":[
        "aat:300008697"
    ]
},
  "bbox": [],
  "geometry": {"coordinates":[-120.5833,44.4667],"type":"Point"}
}