{
  "id": 7535653,
  "type": "Feature",
  "properties": {
    "tgn:hierarchy":[
        "tgn:7535653",
        "tgn:7001242",
        "tgn:7016833",
        "tgn:7001334",
        "tgn:7029392"
    ],
    "tgn:id":7535653,
    "tgn:name:en":"Khandaq, 'Ayn al",
    "tgn:placetype":[
        "aat:300008697"
    ]
},
  "bbox": [],
  "geometry": {"coordinates":[30.520521,25.377216],"type":"Point"}
}