{
  "id": 7591883,
  "type": "Feature",
  "properties": {
    "tgn:hierarchy":[
        "tgn:7591883",
        "tgn:1000004",
        "tgn:7000198",
        "tgn:7000799",
        "tgn:7029392"
    ],
    "tgn:id":7591883,
    "tgn:name:en":"R\u0101jpur Kaular",
    "tgn:placetype":[
        "aat:300008347"
    ]
},
  "bbox": [],
  "geometry": {"coordinates":[74.933333,32.670833],"type":"Point"}
}