{
  "id": 7447843,
  "type": "Feature",
  "properties": {
    "tgn:hierarchy":[
        "tgn:7447843",
        "tgn:7002445",
        "tgn:7008114",
        "tgn:1000003",
        "tgn:7008591",
        "tgn:7029392"
    ],
    "tgn:id":7447843,
    "tgn:name:en":"Saighton",
    "tgn:placetype":[
        "aat:300008347"
    ]
},
  "bbox": [],
  "geometry": {"coordinates":[-2.833333,53.15],"type":"Point"}
}