{
  "id": 2712333,
  "type": "Feature",
  "properties": {
    "tgn:hierarchy":[
        "tgn:2712333",
        "tgn:1000001",
        "tgn:7012149",
        "tgn:7007826",
        "tgn:7029392"
    ],
    "tgn:id":2712333,
    "tgn:name":"Tatum Creek",
    "tgn:placetype":[
        "aat:300008706"
    ]
},
  "bbox": [],
  "geometry": {"coordinates":[-94.5667,32.3167],"type":"Point"}
}