{
  "id": 2587836,
  "type": "Feature",
  "properties": {
    "tgn:hierarchy":[
        "tgn:2587836",
        "tgn:1000001",
        "tgn:7012149",
        "tgn:7007827",
        "tgn:7029392"
    ],
    "tgn:id":2587836,
    "tgn:name":"Pleasant Valley",
    "tgn:placetype":[
        "aat:300008761"
    ]
},
  "bbox": [],
  "geometry": {"coordinates":[-110.15,40.0833],"type":"Point"}
}