{
  "id": 2481813,
  "type": "Feature",
  "properties": {
    "tgn:hierarchy":[
        "tgn:2481813",
        "tgn:1000001",
        "tgn:7006451",
        "tgn:2000092",
        "tgn:7012149",
        "tgn:7029392"
    ],
    "tgn:id":2481813,
    "tgn:name":"Landmark Tank",
    "tgn:placetype":[
        "aat:300006191"
    ]
},
  "bbox": [],
  "geometry": {"coordinates":[-111.3667,34.7167],"type":"Point"}
}