{
  "id": 7404465,
  "type": "Feature",
  "properties": {
    "tgn:hierarchy":[
        "tgn:7404465",
        "tgn:7005578",
        "tgn:1000001",
        "tgn:7005560",
        "tgn:7029392"
    ],
    "tgn:id":7404465,
    "tgn:name":"El Horno, Ensenada",
    "tgn:placetype":[
        "aat:300008679"
    ]
},
  "bbox": [],
  "geometry": {"coordinates":[-91.383333,18.783333],"type":"Point"}
}