<<<<<<< HEAD
{
  "id": 7350246,
  "type": "Feature",
  "properties": {
    "tgn:hierarchy":[
        "tgn:7350246",
        "tgn:1000001",
        "tgn:1001960",
        "tgn:7005560",
        "tgn:7029392"
    ],
    "tgn:id":7350246,
    "tgn:name":"Bacabachi, Arroyo",
    "tgn:placetype":[
        "aat:300266554",
        "aat:300008699"
    ]
},
  "bbox": [],
  "geometry": {"coordinates":[-109.183333,26.8],"type":"Point"}
}
=======
{"geometry":{"type":"Point","coordinates":[-109.183333,26.800000]},"type":"Feature","properties":{"hierarchy":["tgn:7350246","tgn:1000001","tgn:1001960","tgn:7005560","tgn:7029392"],"placetype":["aat:300266554","aat:300008699"],"id":7350246,"name:xx":"Bacabachi, Arroyo"}}
>>>>>>> 03f74aca74312dbeaf24d7e61306dd6a786dc3d0
