{
  "id": 7432268,
  "type": "Feature",
  "properties": {
    "tgn:hierarchy":[
        "tgn:7432268",
        "tgn:1001853",
        "tgn:1000001",
        "tgn:7005560",
        "tgn:7029392"
    ],
    "tgn:id":7432268,
    "tgn:name":"San Gustavo",
    "tgn:placetype":[
        "aat:300008347"
    ]
},
  "bbox": [],
  "geometry": {"coordinates":[-101.233333,29.283333],"type":"Point"}
}