{
  "id": 7219191,
  "type": "Feature",
  "properties": {
    "tgn:hierarchy":[
        "tgn:7219191",
        "tgn:7002707",
        "tgn:7002705",
        "tgn:1000003",
        "tgn:1000074",
        "tgn:7029392"
    ],
    "tgn:id":7219191,
    "tgn:name":"Vounoplagi\u00e1",
    "tgn:placetype":[
        "aat:300008347"
    ]
},
  "bbox": [],
  "geometry": {"coordinates":[20.785833,39.691667],"type":"Point"}
}