<<<<<<< HEAD
{
  "id": 2407757,
  "type": "Feature",
  "properties": {
    "tgn:hierarchy":[
        "tgn:2407757",
        "tgn:7002659",
        "tgn:1000001",
        "tgn:7012149",
        "tgn:2000064",
        "tgn:7029392"
    ],
    "tgn:id":2407757,
    "tgn:name":"Hurricane Branch",
    "tgn:placetype":[
        "aat:300008699"
    ]
},
  "bbox": [],
  "geometry": {"coordinates":[-88.1,31.1667],"type":"Point"}
}
=======
{"geometry":{"type":"Point","coordinates":[-88.100000,31.166700]},"type":"Feature","properties":{"hierarchy":["tgn:2407757","tgn:7002659","tgn:1000001","tgn:7012149","tgn:2000064","tgn:7029392"],"placetype":["aat:300008699"],"id":2407757,"name:xx":"Hurricane Branch"}}
>>>>>>> 03f74aca74312dbeaf24d7e61306dd6a786dc3d0
