<<<<<<< HEAD
{
  "id": 2766774,
  "type": "Feature",
  "properties": {
    "tgn:hierarchy":[
        "tgn:2766774",
        "tgn:1000001",
        "tgn:7012149",
        "tgn:2001217",
        "tgn:7007523",
        "tgn:7029392"
    ],
    "tgn:id":2766774,
    "tgn:name":"White Oak Springs Branch",
    "tgn:placetype":[
        "aat:300008699"
    ]
},
  "bbox": [],
  "geometry": {"coordinates":[-90.3333,37.6167],"type":"Point"}
}
=======
{"geometry":{"type":"Point","coordinates":[-90.333300,37.616700]},"type":"Feature","properties":{"hierarchy":["tgn:2766774","tgn:1000001","tgn:7012149","tgn:2001217","tgn:7007523","tgn:7029392"],"placetype":["aat:300008699"],"id":2766774,"name:xx":"White Oak Springs Branch"}}
>>>>>>> 03f74aca74312dbeaf24d7e61306dd6a786dc3d0
