{
  "id": 2421211,
  "type": "Feature",
  "properties": {
    "tgn:hierarchy":[
        "tgn:2421211",
        "tgn:1000001",
        "tgn:7012149",
        "tgn:7007920",
        "tgn:7029392"
    ],
    "tgn:id":2421211,
    "tgn:name":"Jerry Canyon",
    "tgn:placetype":[
        "aat:300008761"
    ]
},
  "bbox": [],
  "geometry": {"coordinates":[-120.1167,46.05],"type":"Point"}
}