{
  "id": 2377081,
  "type": "Feature",
  "properties": {
    "tgn:hierarchy":[
        "tgn:2377081",
        "tgn:1000001",
        "tgn:7012149",
        "tgn:2001907",
        "tgn:7007825",
        "tgn:7029392"
    ],
    "tgn:id":2377081,
    "tgn:name":"Harley Subdivision",
    "tgn:placetype":[
        "aat:300008347"
    ]
},
  "bbox": [],
  "geometry": {"coordinates":[-85.5167,36.1833],"type":"Point"}
}