{
  "id": 2204863,
  "type": "Feature",
  "properties": {
    "tgn:hierarchy":[
        "tgn:2204863",
        "tgn:1000001",
        "tgn:7012149",
        "tgn:7007158",
        "tgn:7029392"
    ],
    "tgn:id":2204863,
    "tgn:name":"Buffehr Lake",
    "tgn:placetype":[
        "aat:300008680"
    ]
},
  "bbox": [],
  "geometry": {"coordinates":[-106.1833,39.3667],"type":"Point"}
}