{
  "id": 7294814,
  "type": "Feature",
  "properties": {
    "tgn:hierarchy":[
        "tgn:7294814",
        "tgn:1001702",
        "tgn:1000049",
        "tgn:1000002",
        "tgn:7029392"
    ],
    "tgn:id":7294814,
    "tgn:name":"Abra, Isla",
    "tgn:placetype":[
        "aat:300008791"
    ]
},
  "bbox": [],
  "geometry": {"coordinates":[-73.083333,-53.366667],"type":"Point"}
}