{
  "id": 1003418,
  "type": "Feature",
  "properties": {
    "tgn:hierarchy":[
        "tgn:1003418",
        "tgn:1000004",
        "tgn:7018214",
        "tgn:7002435",
        "tgn:7029392"
    ],
    "tgn:id":1003418,
    "tgn:name":"Tulskaya Oblast'",
    "tgn:placetype":[
        "aat:300387145",
        "aat:300235107"
    ]
},
  "bbox": [],
  "geometry": {"coordinates":[37.8333,54.3333],"type":"Point"}
}