{
  "id": 7545532,
  "type": "Feature",
  "properties": {
    "tgn:hierarchy":[
        "tgn:7545532",
        "tgn:1000004",
        "tgn:7000198",
        "tgn:1001895",
        "tgn:7029392"
    ],
    "tgn:id":7545532,
    "tgn:name:en":"Bh\u012bm\u0101shankar",
    "tgn:placetype":[
        "aat:300008347"
    ]
},
  "bbox": [],
  "geometry": {"coordinates":[73.533333,19.066667],"type":"Point"}
}