{
  "id": 7300386,
  "type": "Feature",
  "properties": {
    "tgn:hierarchy":[
        "tgn:7300386",
        "tgn:7002813",
        "tgn:7002758",
        "tgn:1000003",
        "tgn:1000095",
        "tgn:7029392"
    ],
    "tgn:id":7300386,
    "tgn:name":"Trocadero, Ca\u00f1o del",
    "tgn:placetype":[
        "aat:300387084"
    ]
},
  "bbox": [],
  "geometry": {"coordinates":[-6.183333,36.533333],"type":"Point"}
}