{
  "id": 7468933,
  "type": "Feature",
  "properties": {
    "tgn:hierarchy":[
        "tgn:7468933",
        "tgn:1000004",
        "tgn:7001013",
        "tgn:1000141",
        "tgn:7029392"
    ],
    "tgn:id":7468933,
    "tgn:name":"Fengweikeng",
    "tgn:placetype":[
        "aat:300008347"
    ]
},
  "bbox": [],
  "geometry": {"coordinates":[121.337508,25.029619],"type":"Point"}
}