{
  "id": 2319942,
  "type": "Feature",
  "properties": {
    "tgn:hierarchy":[
        "tgn:2319942",
        "tgn:1000001",
        "tgn:7012149",
        "tgn:2001854",
        "tgn:7007825",
        "tgn:7029392"
    ],
    "tgn:id":2319942,
    "tgn:name":"Evans Branch",
    "tgn:placetype":[
        "aat:300008699"
    ]
},
  "bbox": [],
  "geometry": {"coordinates":[-84.6833,35.9167],"type":"Point"}
}