{
  "id": 2521723,
  "type": "Feature",
  "properties": {
    "tgn:hierarchy":[
        "tgn:2521723",
        "tgn:1000001",
        "tgn:7012149",
        "tgn:2001697",
        "tgn:7007707",
        "tgn:7029392"
    ],
    "tgn:id":2521723,
    "tgn:name":"Monument Creek",
    "tgn:placetype":[
        "aat:300008706"
    ]
},
  "bbox": [],
  "geometry": {"coordinates":[-99.2333,35.35],"type":"Point"}
}