{
  "id": 2101137,
  "type": "Feature",
  "properties": {
    "tgn:hierarchy":[
        "tgn:2101137",
        "tgn:1000001",
        "tgn:7012149",
        "tgn:2001892",
        "tgn:7007825",
        "tgn:7029392"
    ],
    "tgn:id":2101137,
    "tgn:name":"Prosperity",
    "tgn:placetype":[
        "aat:300008347",
        "aat:300387210"
    ]
},
  "bbox": [],
  "geometry": {"coordinates":[-85.8667,36.4833],"type":"Point"}
}