{
  "id": 2695810,
  "type": "Feature",
  "properties": {
    "tgn:hierarchy":[
        "tgn:2695810",
        "tgn:1000001",
        "tgn:7012149",
        "tgn:7007157",
        "tgn:2000186",
        "tgn:7029392"
    ],
    "tgn:id":2695810,
    "tgn:name":"Stock Tank 2",
    "tgn:placetype":[
        "aat:300006191"
    ]
},
  "bbox": [],
  "geometry": {"coordinates":[-120.5333,41.6667],"type":"Point"}
}