{
  "id": 1033443,
  "type": "Feature",
  "properties": {
    "tgn:hierarchy":[
        "tgn:1033443",
        "tgn:7002870",
        "tgn:1000003",
        "tgn:1000070",
        "tgn:7029392"
    ],
    "tgn:id":1033443,
    "tgn:name":"Hirsingue",
    "tgn:placetype":[
        "aat:300008347"
    ]
},
  "bbox": [],
  "geometry": {"coordinates":[7.25,47.5833],"type":"Point"}
}