<<<<<<< HEAD
{
  "id": 2337747,
  "type": "Feature",
  "properties": {
    "tgn:hierarchy":[
        "tgn:2337747",
        "tgn:1000001",
        "tgn:7012149",
        "tgn:7007523",
        "tgn:7029392"
    ],
    "tgn:id":2337747,
    "tgn:name":"Fox Creek",
    "tgn:placetype":[
        "aat:300008706"
    ]
},
  "bbox": [],
  "geometry": {"coordinates":[-90.75,38.5333],"type":"Point"}
}
=======
{"geometry":{"type":"Point","coordinates":[-90.750000,38.533300]},"type":"Feature","properties":{"hierarchy":["tgn:2337747","tgn:1000001","tgn:7012149","tgn:7007523","tgn:7029392"],"placetype":["aat:300008706"],"id":2337747,"name:xx":"Fox Creek"}}
>>>>>>> 03f74aca74312dbeaf24d7e61306dd6a786dc3d0
