{
  "id": 2035753,
  "type": "Feature",
  "properties": {
    "tgn:hierarchy":[
        "tgn:2035753",
        "tgn:1000001",
        "tgn:7012149",
        "tgn:2000643",
        "tgn:7007253",
        "tgn:7029392"
    ],
    "tgn:id":2035753,
    "tgn:name":"Tennant",
    "tgn:placetype":[
        "aat:300008347"
    ]
},
  "bbox": [],
  "geometry": {"coordinates":[-95.4333,41.5833],"type":"Point"}
}