{
  "id": 2593069,
  "type": "Feature",
  "properties": {
    "tgn:hierarchy":[
        "tgn:2593069",
        "tgn:1000001",
        "tgn:7012149",
        "tgn:1002821",
        "tgn:7007568",
        "tgn:7029392"
    ],
    "tgn:id":2593069,
    "tgn:name":"Poplar Hill",
    "tgn:placetype":[
        "aat:300008798"
    ]
},
  "bbox": [],
  "geometry": {"coordinates":[-73.3167,42.75],"type":"Point"}
}