{
  "id": 2440440,
  "type": "Feature",
  "properties": {
    "tgn:hierarchy":[
        "tgn:2440440",
        "tgn:7006450",
        "tgn:1000001",
        "tgn:2124076",
        "tgn:7012149",
        "tgn:7029392"
    ],
    "tgn:id":2440440,
    "tgn:name":"Klu Bay",
    "tgn:placetype":[
        "aat:300132316"
    ]
},
  "bbox": [],
  "geometry": {"coordinates":[-131.45,55.8333],"type":"Point"}
}