{
  "id": 7267123,
  "type": "Feature",
  "properties": {
    "tgn:hierarchy":[
        "tgn:7267123",
        "tgn:7003616",
        "tgn:1000003",
        "tgn:7016845",
        "tgn:7029392"
    ],
    "tgn:id":7267123,
    "tgn:name:nl":"Oldetrijnesterbrug",
    "tgn:placetype":[
        "aat:300007836"
    ]
},
  "bbox": [],
  "geometry": {"coordinates":[5.933333,52.85],"type":"Point"}
}