{
  "id": 2318059,
  "type": "Feature",
  "properties": {
    "tgn:hierarchy":[
        "tgn:2318059",
        "tgn:1000001",
        "tgn:7012149",
        "tgn:2001538",
        "tgn:7007709",
        "tgn:7029392"
    ],
    "tgn:id":2318059,
    "tgn:name":"Enoch Mill Creek",
    "tgn:placetype":[
        "aat:300008706"
    ]
},
  "bbox": [],
  "geometry": {"coordinates":[-78.2667,34.65],"type":"Point"}
}