{
  "id": 1072492,
  "type": "Feature",
  "properties": {
    "tgn:hierarchy":[
        "tgn:1072492",
        "tgn:1000004",
        "tgn:7002081",
        "tgn:1000111",
        "tgn:7029392"
    ],
    "tgn:id":1072492,
    "tgn:name":"Wangxiuqiao",
    "tgn:placetype":[
        "aat:300008347"
    ]
},
  "bbox": [],
  "geometry": {"coordinates":[121.05,31.6333],"type":"Point"}
}