<<<<<<< HEAD
{
  "id": 7364593,
  "type": "Feature",
  "properties": {
    "tgn:hierarchy":[
        "tgn:7364593",
        "tgn:1000001",
        "tgn:7005589",
        "tgn:7005560",
        "tgn:7029392"
    ],
    "tgn:id":7364593,
    "tgn:name":"El Saucito",
    "tgn:placetype":[
        "aat:300008347"
    ]
},
  "bbox": [],
  "geometry": {"coordinates":[-99.85,25.583333],"type":"Point"}
}
=======
{"geometry":{"type":"Point","coordinates":[-99.850000,25.583333]},"type":"Feature","properties":{"hierarchy":["tgn:7364593","tgn:1000001","tgn:7005589","tgn:7005560","tgn:7029392"],"placetype":["aat:300008347"],"id":7364593,"name:xx":"El Saucito"}}
>>>>>>> 03f74aca74312dbeaf24d7e61306dd6a786dc3d0
