<<<<<<< HEAD
{
  "id": 7378935,
  "type": "Feature",
  "properties": {
    "tgn:hierarchy":[
        "tgn:7378935",
        "tgn:1001853",
        "tgn:1000001",
        "tgn:7005560",
        "tgn:7029392"
    ],
    "tgn:id":7378935,
    "tgn:name":"Los Charcos, Arroyo de",
    "tgn:placetype":[
        "aat:300266554",
        "aat:300008699"
    ]
},
  "bbox": [],
  "geometry": {"coordinates":[-103.1,26.433333],"type":"Point"}
}
=======
{"geometry":{"type":"Point","coordinates":[-103.100000,26.433333]},"type":"Feature","properties":{"hierarchy":["tgn:7378935","tgn:1001853","tgn:1000001","tgn:7005560","tgn:7029392"],"placetype":["aat:300266554","aat:300008699"],"id":7378935,"name:xx":"Los Charcos, Arroyo de"}}
>>>>>>> 03f74aca74312dbeaf24d7e61306dd6a786dc3d0
