{
  "id": 2087984,
  "type": "Feature",
  "properties": {
    "tgn:hierarchy":[
        "tgn:2087984",
        "tgn:1000001",
        "tgn:7012149",
        "tgn:1003017",
        "tgn:7007710",
        "tgn:7029392"
    ],
    "tgn:id":2087984,
    "tgn:name":"East Charleroi",
    "tgn:placetype":[
        "aat:300387016"
    ]
},
  "bbox": [],
  "geometry": {"coordinates":[-79.8833,40.1333],"type":"Point"}
}