{
  "id": 2469969,
  "type": "Feature",
  "properties": {
    "tgn:hierarchy":[
        "tgn:2469969",
        "tgn:1000001",
        "tgn:2001009",
        "tgn:7012149",
        "tgn:7007521",
        "tgn:7029392"
    ],
    "tgn:id":2469969,
    "tgn:name":"Loon Lake",
    "tgn:placetype":[
        "aat:300008680"
    ]
},
  "bbox": [],
  "geometry": {"coordinates":[-94.45,46.85],"type":"Point"}
}