{
  "id": 7080384,
  "type": "Feature",
  "properties": {
    "tgn:hierarchy":[
        "tgn:7080384",
        "tgn:7003692",
        "tgn:1000003",
        "tgn:7000084",
        "tgn:7029392"
    ],
    "tgn:id":7080384,
    "tgn:name":"Winterbauernhof",
    "tgn:placetype":[
        "aat:300000206"
    ]
},
  "bbox": [],
  "geometry": {"coordinates":[8.333333,48.233333],"type":"Point"}
}