<<<<<<< HEAD
{
  "id": 2255219,
  "type": "Feature",
  "properties": {
    "tgn:hierarchy":[
        "tgn:2255219",
        "tgn:1002227",
        "tgn:1000001",
        "tgn:7012149",
        "tgn:7007565",
        "tgn:7029392"
    ],
    "tgn:id":2255219,
    "tgn:name":"Cooper Point",
    "tgn:placetype":[
        "aat:300008850"
    ]
},
  "bbox": [],
  "geometry": {"coordinates":[-75.1167,39.95],"type":"Point"}
}
=======
{"geometry":{"type":"Point","coordinates":[-75.116700,39.950000]},"type":"Feature","properties":{"hierarchy":["tgn:2255219","tgn:1002227","tgn:1000001","tgn:7012149","tgn:7007565","tgn:7029392"],"placetype":["aat:300008850"],"id":2255219,"name:xx":"Cooper Point"}}
>>>>>>> 03f74aca74312dbeaf24d7e61306dd6a786dc3d0
