{
  "id": 7501061,
  "type": "Feature",
  "properties": {
    "tgn:hierarchy":[
        "tgn:7501061",
        "tgn:1000004",
        "tgn:7490934",
        "tgn:1000141",
        "tgn:7029392"
    ],
    "tgn:id":7501061,
    "tgn:name":"Shenkengzi",
    "tgn:placetype":[
        "aat:300387033"
    ]
},
  "bbox": [],
  "geometry": {"coordinates":[120.3375,22.936111],"type":"Point"}
}