{
  "id": 2304758,
  "type": "Feature",
  "properties": {
    "tgn:hierarchy":[
        "tgn:2304758",
        "tgn:1000001",
        "tgn:7012149",
        "tgn:7007253",
        "tgn:7029392"
    ],
    "tgn:id":2304758,
    "tgn:name":"East Boyer River",
    "tgn:placetype":[
        "aat:300008707"
    ]
},
  "bbox": [],
  "geometry": {"coordinates":[-95.0833,42.0167],"type":"Point"}
}