{
  "id": 2741487,
  "type": "Feature",
  "properties": {
    "tgn:hierarchy":[
        "tgn:2741487",
        "tgn:1000001",
        "tgn:7012149",
        "tgn:1002403",
        "tgn:7007709",
        "tgn:7029392"
    ],
    "tgn:id":2741487,
    "tgn:name":"Ure Island",
    "tgn:placetype":[
        "aat:300008791"
    ]
},
  "bbox": [],
  "geometry": {"coordinates":[-76.5667,36.5167],"type":"Point"}
}