<<<<<<< HEAD
{
  "id": 2403130,
  "type": "Feature",
  "properties": {
    "tgn:hierarchy":[
        "tgn:2403130",
        "tgn:1000001",
        "tgn:7012149",
        "tgn:2001300",
        "tgn:7007524",
        "tgn:7029392"
    ],
    "tgn:id":2403130,
    "tgn:name":"House Creek",
    "tgn:placetype":[
        "aat:300008706"
    ]
},
  "bbox": [],
  "geometry": {"coordinates":[-114.2,45.8667],"type":"Point"}
}
=======
{"geometry":{"type":"Point","coordinates":[-114.200000,45.866700]},"type":"Feature","properties":{"hierarchy":["tgn:2403130","tgn:1000001","tgn:7012149","tgn:2001300","tgn:7007524","tgn:7029392"],"placetype":["aat:300008706"],"id":2403130,"name:xx":"House Creek"}}
>>>>>>> 03f74aca74312dbeaf24d7e61306dd6a786dc3d0
