{
  "id": 2658582,
  "type": "Feature",
  "properties": {
    "tgn:hierarchy":[
        "tgn:2658582",
        "tgn:1000001",
        "tgn:7012149",
        "tgn:7007157",
        "tgn:7014516",
        "tgn:7029392"
    ],
    "tgn:id":2658582,
    "tgn:name":"Sheridan",
    "tgn:placetype":[
        "aat:300008347"
    ]
},
  "bbox": [],
  "geometry": {"coordinates":[-123.0333,38.45],"type":"Point"}
}