{
  "id": 7244289,
  "type": "Feature",
  "properties": {
    "tgn:hierarchy":[
        "tgn:7244289",
        "tgn:7018237",
        "tgn:1000003",
        "tgn:1000063",
        "tgn:7029392"
    ],
    "tgn:id":7244289,
    "tgn:name":"Kelle",
    "tgn:placetype":[
        "aat:300008347"
    ]
},
  "bbox": [],
  "geometry": {"coordinates":[4.433333,50.833333],"type":"Point"}
}