{
  "id": 7242570,
  "type": "Feature",
  "properties": {
    "tgn:hierarchy":[
        "tgn:7242570",
        "tgn:7003465",
        "tgn:1000003",
        "tgn:1000063",
        "tgn:4012014",
        "tgn:7029392"
    ],
    "tgn:id":7242570,
    "tgn:name":"Les Baraques",
    "tgn:placetype":[
        "aat:300008347"
    ]
},
  "bbox": [],
  "geometry": {"coordinates":[5.216667,50.016667],"type":"Point"}
}