<<<<<<< HEAD
{
  "id": 7242570,
  "type": "Feature",
  "properties": {
    "tgn:hierarchy":[
        "tgn:7242570",
        "tgn:7003465",
        "tgn:1000003",
        "tgn:1000063",
        "tgn:4012014",
        "tgn:7029392"
    ],
    "tgn:id":7242570,
    "tgn:name":"Les Baraques",
    "tgn:placetype":[
        "aat:300008347"
    ]
},
  "bbox": [],
  "geometry": {"coordinates":[5.216667,50.016667],"type":"Point"}
}
=======
{"geometry":{"type":"Point","coordinates":[5.216667,50.016667]},"type":"Feature","properties":{"hierarchy":["tgn:7242570","tgn:7003465","tgn:1000003","tgn:1000063","tgn:4012014","tgn:7029392"],"placetype":["aat:300008347"],"id":7242570,"name:xx":"Les Baraques"}}
>>>>>>> 03f74aca74312dbeaf24d7e61306dd6a786dc3d0
