{
  "id": 7531245,
  "type": "Feature",
  "properties": {
    "tgn:hierarchy":[
        "tgn:7531245",
        "tgn:7001242",
        "tgn:7016833",
        "tgn:1001091",
        "tgn:7029392"
    ],
    "tgn:id":7531245,
    "tgn:name":"Masjid Mahmashah al Qad\u012bm",
    "tgn:placetype":[
        "aat:300007544"
    ]
},
  "bbox": [],
  "geometry": {"coordinates":[31.261917,30.079059],"type":"Point"}
}