{
  "id": 7229334,
  "type": "Feature",
  "properties": {
    "tgn:hierarchy":[
        "tgn:7229334",
        "tgn:7002707",
        "tgn:7002705",
        "tgn:1000003",
        "tgn:1000074",
        "tgn:7029392"
    ],
    "tgn:id":7229334,
    "tgn:name":"L\u00e1zaina",
    "tgn:placetype":[
        "aat:300008347"
    ]
},
  "bbox": [],
  "geometry": {"coordinates":[20.953333,39.518889],"type":"Point"}
}