<<<<<<< HEAD
{
  "id": 2336877,
  "type": "Feature",
  "properties": {
    "tgn:hierarchy":[
        "tgn:2336877",
        "tgn:2000565",
        "tgn:1000001",
        "tgn:7012149",
        "tgn:7007253",
        "tgn:7029392"
    ],
    "tgn:id":2336877,
    "tgn:name":"Fourmile Creek",
    "tgn:placetype":[
        "aat:300008706"
    ]
},
  "bbox": [],
  "geometry": {"coordinates":[-94.75,41.6333],"type":"Point"}
}
=======
{"geometry":{"type":"Point","coordinates":[-94.750000,41.633300]},"type":"Feature","properties":{"hierarchy":["tgn:2336877","tgn:2000565","tgn:1000001","tgn:7012149","tgn:7007253","tgn:7029392"],"placetype":["aat:300008706"],"id":2336877,"name:xx":"Fourmile Creek"}}
>>>>>>> 03f74aca74312dbeaf24d7e61306dd6a786dc3d0
