{
  "id": 2336877,
  "type": "Feature",
  "properties": {
    "tgn:hierarchy":[
        "tgn:2336877",
        "tgn:2000565",
        "tgn:1000001",
        "tgn:7012149",
        "tgn:7007253",
        "tgn:7029392"
    ],
    "tgn:id":2336877,
    "tgn:name":"Fourmile Creek",
    "tgn:placetype":[
        "aat:300008706"
    ]
},
  "bbox": [],
  "geometry": {"coordinates":[-94.75,41.6333],"type":"Point"}
}