{
  "id": 1092154,
  "type": "Feature",
  "properties": {
    "tgn:hierarchy":[
        "tgn:1092154",
        "tgn:7001242",
        "tgn:7000542",
        "tgn:1000182",
        "tgn:7029392"
    ],
    "tgn:id":1092154,
    "tgn:name":"Maiduguri",
    "tgn:placetype":[
        "aat:300008347",
        "aat:300008389",
        "aat:300387512",
        "aat:300387221",
        "aat:300387270",
        "aat:300387302",
        "aat:300387286",
        "aat:300387296"
    ]
},
  "bbox": [],
  "geometry": {"coordinates":[13.2667,11.8833],"type":"Point"}
}