{
  "id": 7187595,
  "type": "Feature",
  "properties": {
    "tgn:hierarchy":[
        "tgn:7187595",
        "tgn:7003692",
        "tgn:1000003",
        "tgn:7000084",
        "tgn:7029392"
    ],
    "tgn:id":7187595,
    "tgn:name":"Etzenbacher H\u00f6he",
    "tgn:placetype":[
        "aat:300008795"
    ]
},
  "bbox": [],
  "geometry": {"coordinates":[7.766667,47.883333],"type":"Point"}
}