{
  "id": 2515350,
  "type": "Feature",
  "properties": {
    "tgn:hierarchy":[
        "tgn:2515350",
        "tgn:7002659",
        "tgn:1000001",
        "tgn:7012149",
        "tgn:2000062",
        "tgn:7029392"
    ],
    "tgn:id":2515350,
    "tgn:name":"Million Dollar Lake",
    "tgn:placetype":[
        "aat:300006191"
    ]
},
  "bbox": [],
  "geometry": {"coordinates":[-87.1333,33.2667],"type":"Point"}
}