{
  "id": 2148450,
  "type": "Feature",
  "properties": {
    "tgn:hierarchy":[
        "tgn:2148450",
        "tgn:1000001",
        "tgn:7016172",
        "tgn:7012149",
        "tgn:2000176",
        "tgn:7029392"
    ],
    "tgn:id":2148450,
    "tgn:name":"Barnard Hollow",
    "tgn:placetype":[
        "aat:300008761"
    ]
},
  "bbox": [],
  "geometry": {"coordinates":[-93.9833,35.7667],"type":"Point"}
}