{
  "id": 1055828,
  "type": "Feature",
  "properties": {
    "tgn:hierarchy":[
        "tgn:1055828",
        "tgn:1003361",
        "tgn:1000003",
        "tgn:7006660",
        "tgn:7029392"
    ],
    "tgn:id":1055828,
    "tgn:name":"Krasnokutsk",
    "tgn:placetype":[
        "aat:300008347"
    ]
},
  "bbox": [],
  "geometry": {"coordinates":[35.2167,50.05],"type":"Point"}
}