{
  "id": 2497022,
  "type": "Feature",
  "properties": {
    "tgn:hierarchy":[
        "tgn:2497022",
        "tgn:1000001",
        "tgn:7016172",
        "tgn:7012149",
        "tgn:2000164",
        "tgn:7029392"
    ],
    "tgn:id":2497022,
    "tgn:name":"Maumelle Harbor",
    "tgn:placetype":[
        "aat:300132316"
    ]
},
  "bbox": [],
  "geometry": {"coordinates":[-92.55,34.85],"type":"Point"}
}