{
  "id": 7371543,
  "type": "Feature",
  "properties": {
    "tgn:hierarchy":[
        "tgn:7371543",
        "tgn:1000001",
        "tgn:7005599",
        "tgn:7005560",
        "tgn:7029392"
    ],
    "tgn:id":7371543,
    "tgn:name":"La Defensa",
    "tgn:placetype":[
        "aat:300008347"
    ]
},
  "bbox": [],
  "geometry": {"coordinates":[-96.95,20.116667],"type":"Point"}
}