{
  "id": 7418330,
  "type": "Feature",
  "properties": {
    "tgn:hierarchy":[
        "tgn:7418330",
        "tgn:7005579",
        "tgn:1000001",
        "tgn:7005560",
        "tgn:7029392"
    ],
    "tgn:id":7418330,
    "tgn:name":"El LuCerro, Tanque",
    "tgn:placetype":[
        "aat:300008688"
    ]
},
  "bbox": [],
  "geometry": {"coordinates":[-102.15,21.766667],"type":"Point"}
}