{
  "id": 7478956,
  "type": "Feature",
  "properties": {
    "tgn:hierarchy":[
        "tgn:7478956",
        "tgn:7001010",
        "tgn:1000004",
        "tgn:1000141",
        "tgn:7029392"
    ],
    "tgn:id":7478956,
    "tgn:name":"Daijiao Shan",
    "tgn:placetype":[
        "aat:300008798"
    ]
},
  "bbox": [],
  "geometry": {"coordinates":[121.437778,24.251111],"type":"Point"}
}