<<<<<<< HEAD
{
  "id": 7240133,
  "type": "Feature",
  "properties": {
    "tgn:hierarchy":[
        "tgn:7240133",
        "tgn:7003457",
        "tgn:1000003",
        "tgn:1000063",
        "tgn:7018236",
        "tgn:7029392"
    ],
    "tgn:id":7240133,
    "tgn:name":"Eeuwhoek",
    "tgn:placetype":[
        "aat:300008347"
    ]
},
  "bbox": [],
  "geometry": {"coordinates":[3.55,50.8],"type":"Point"}
}
=======
{"geometry":{"type":"Point","coordinates":[3.550000,50.800000]},"type":"Feature","properties":{"hierarchy":["tgn:7240133","tgn:7003457","tgn:1000003","tgn:1000063","tgn:7018236","tgn:7029392"],"placetype":["aat:300008347"],"id":7240133,"name:xx":"Eeuwhoek"}}
>>>>>>> 03f74aca74312dbeaf24d7e61306dd6a786dc3d0
