{
  "id": 2486321,
  "type": "Feature",
  "properties": {
    "tgn:hierarchy":[
        "tgn:2486321",
        "tgn:1000001",
        "tgn:7012149",
        "tgn:7007157",
        "tgn:1002656",
        "tgn:7029392"
    ],
    "tgn:id":2486321,
    "tgn:name":"Leatherman Lateral",
    "tgn:placetype":[
        "aat:300006075"
    ]
},
  "bbox": [],
  "geometry": {"coordinates":[-120.65,37.3833],"type":"Point"}
}