{
  "id": 2397037,
  "type": "Feature",
  "properties": {
    "tgn:hierarchy":[
        "tgn:2397037",
        "tgn:1000001",
        "tgn:7012149",
        "tgn:7007158",
        "tgn:2000246",
        "tgn:7029392"
    ],
    "tgn:id":2397037,
    "tgn:name":"Homestead Gulch",
    "tgn:placetype":[
        "aat:300008761"
    ]
},
  "bbox": [],
  "geometry": {"coordinates":[-106.8333,38.2833],"type":"Point"}
}