{
  "id": 2198615,
  "type": "Feature",
  "properties": {
    "tgn:hierarchy":[
        "tgn:2198615",
        "tgn:1000001",
        "tgn:7012149",
        "tgn:2000494",
        "tgn:7007250",
        "tgn:7029392"
    ],
    "tgn:id":2198615,
    "tgn:name":"Browns Pond",
    "tgn:placetype":[
        "aat:300006191"
    ]
},
  "bbox": [],
  "geometry": {"coordinates":[-115.95,44.9167],"type":"Point"}
}