{
  "id": 7270378,
  "type": "Feature",
  "properties": {
    "tgn:hierarchy":[
        "tgn:7270378",
        "tgn:1000003",
        "tgn:7003626",
        "tgn:7016845",
        "tgn:7029392"
    ],
    "tgn:id":7270378,
    "tgn:name:nl":"Nieuwe Graven",
    "tgn:placetype":[
        "aat:300006075"
    ]
},
  "bbox": [],
  "geometry": {"coordinates":[6.633333,52.35],"type":"Point"}
}