{
  "id": 7428301,
  "type": "Feature",
  "properties": {
    "tgn:hierarchy":[
        "tgn:7428301",
        "tgn:1000001",
        "tgn:7005594",
        "tgn:7005560",
        "tgn:7029392"
    ],
    "tgn:id":7428301,
    "tgn:name":"El Duraznillo",
    "tgn:placetype":[
        "aat:300008347"
    ]
},
  "bbox": [],
  "geometry": {"coordinates":[-99.716667,22.033333],"type":"Point"}
}