<<<<<<< HEAD
{
  "id": 7474817,
  "type": "Feature",
  "properties": {
    "tgn:hierarchy":[
        "tgn:7474817",
        "tgn:1000004",
        "tgn:7467799",
        "tgn:1000141",
        "tgn:7029392"
    ],
    "tgn:id":7474817,
    "tgn:name":"Xinjie Daqiao",
    "tgn:placetype":[
        "aat:300007836"
    ]
},
  "bbox": [],
  "geometry": {"coordinates":[120.304128,23.902251],"type":"Point"}
}
=======
{"geometry":{"type":"Point","coordinates":[120.304128,23.902251]},"type":"Feature","properties":{"hierarchy":["tgn:7474817","tgn:1000004","tgn:7467799","tgn:1000141","tgn:7029392"],"placetype":["aat:300007836"],"id":7474817,"name:xx":"Xinjie Daqiao"}}
>>>>>>> 03f74aca74312dbeaf24d7e61306dd6a786dc3d0
