{
  "id": 2062878,
  "type": "Feature",
  "properties": {
    "tgn:hierarchy":[
        "tgn:2062878",
        "tgn:1000001",
        "tgn:2001411",
        "tgn:7012149",
        "tgn:7007526",
        "tgn:7029392"
    ],
    "tgn:id":2062878,
    "tgn:name":"Elko",
    "tgn:placetype":[
        "aat:300008347"
    ]
},
  "bbox": [],
  "geometry": {"coordinates":[-115.75,40.8167],"type":"Point"}
}