{
  "id": 2196359,
  "type": "Feature",
  "properties": {
    "tgn:hierarchy":[
        "tgn:2196359",
        "tgn:1000001",
        "tgn:7012149",
        "tgn:7029392"
    ],
    "tgn:id":2196359,
    "tgn:name":"Brokeoff Mountains",
    "tgn:placetype":[
        "aat:300386831"
    ]
},
  "bbox": [],
  "geometry": {"coordinates":[-104.9667,32.1167],"type":"Point"}
}