{
  "id": 7001490,
  "type": "Feature",
  "properties": {
    "tgn:hierarchy":[
        "tgn:7001490",
        "tgn:1000004",
        "tgn:1000138",
        "tgn:7000381",
        "tgn:7029392"
    ],
    "tgn:id":7001490,
    "tgn:name":"Kampong Mandai Kechil",
    "tgn:placetype":[
        "aat:300008347"
    ]
},
  "bbox": [],
  "geometry": {"coordinates":[103.7667,1.4333],"type":"Point"}
}