{
  "id": 2259459,
  "type": "Feature",
  "properties": {
    "tgn:hierarchy":[
        "tgn:2259459",
        "tgn:1000001",
        "tgn:7012149",
        "tgn:2002374",
        "tgn:7007923",
        "tgn:7029392"
    ],
    "tgn:id":2259459,
    "tgn:name":"Cottonwood Spring",
    "tgn:placetype":[
        "aat:300008697"
    ]
},
  "bbox": [],
  "geometry": {"coordinates":[-106.8833,43.9167],"type":"Point"}
}