{
  "id": 1069797,
  "type": "Feature",
  "properties": {
    "tgn:hierarchy":[
        "tgn:1069797",
        "tgn:1000004",
        "tgn:7002372",
        "tgn:1000111",
        "tgn:7029392"
    ],
    "tgn:id":1069797,
    "tgn:name":"Liaoyuan",
    "tgn:placetype":[
        "aat:300008347"
    ]
},
  "bbox": [],
  "geometry": {"coordinates":[125.1667,42.8833],"type":"Point"}
}