{
  "id": 2131125,
  "type": "Feature",
  "properties": {
    "tgn:hierarchy":[
        "tgn:2131125",
        "tgn:1000001",
        "tgn:7012149",
        "tgn:7007157",
        "tgn:2000191",
        "tgn:7029392"
    ],
    "tgn:id":2131125,
    "tgn:name":"Alpine Lake",
    "tgn:placetype":[
        "aat:300008680"
    ]
},
  "bbox": [],
  "geometry": {"coordinates":[-122.9833,40.9333],"type":"Point"}
}