{
  "id": 2653751,
  "type": "Feature",
  "properties": {
    "tgn:hierarchy":[
        "tgn:2653751",
        "tgn:1000001",
        "tgn:2002261",
        "tgn:7012149",
        "tgn:7013961",
        "tgn:7029392"
    ],
    "tgn:id":2653751,
    "tgn:name":"Sewell Mountain",
    "tgn:placetype":[
        "aat:300008798"
    ]
},
  "bbox": [],
  "geometry": {"coordinates":[-80.8333,37.9333],"type":"Point"}
}