{
  "id": 2759868,
  "type": "Feature",
  "properties": {
    "tgn:hierarchy":[
        "tgn:2759868",
        "tgn:1000001",
        "tgn:2000470",
        "tgn:7012149",
        "tgn:7007250",
        "tgn:7029392"
    ],
    "tgn:id":2759868,
    "tgn:name":"West Fork Little Loon Creek",
    "tgn:placetype":[
        "aat:300008706"
    ]
},
  "bbox": [],
  "geometry": {"coordinates":[-114.9667,44.6667],"type":"Point"}
}