{
  "id": 2436324,
  "type": "Feature",
  "properties": {
    "tgn:hierarchy":[
        "tgn:2436324",
        "tgn:7006450",
        "tgn:1000001",
        "tgn:7012149",
        "tgn:2000079",
        "tgn:7029392"
    ],
    "tgn:id":2436324,
    "tgn:name":"Kialegak Point",
    "tgn:placetype":[
        "aat:300008850"
    ]
},
  "bbox": [],
  "geometry": {"coordinates":[-169.5167,62.9667],"type":"Point"}
}