{
  "id": 2477235,
  "type": "Feature",
  "properties": {
    "tgn:hierarchy":[
        "tgn:2477235",
        "tgn:1000001",
        "tgn:7012149",
        "tgn:1002487",
        "tgn:7007252",
        "tgn:7029392"
    ],
    "tgn:id":2477235,
    "tgn:name":"Lynn Run",
    "tgn:placetype":[
        "aat:300008699"
    ]
},
  "bbox": [],
  "geometry": {"coordinates":[-86.2167,40.4167],"type":"Point"}
}