{
  "id": 7205627,
  "type": "Feature",
  "properties": {
    "tgn:hierarchy":[
        "tgn:7205627",
        "tgn:1000003",
        "tgn:7003676",
        "tgn:7000084",
        "tgn:7029392"
    ],
    "tgn:id":7205627,
    "tgn:name":"Dambeck",
    "tgn:placetype":[
        "aat:300008347"
    ]
},
  "bbox": [],
  "geometry": {"coordinates":[11.116667,53.116667],"type":"Point"}
}