{
  "id": 1140016,
  "type": "Feature",
  "properties": {
    "tgn:hierarchy":[
        "tgn:1140016",
        "tgn:1000004",
        "tgn:1001390",
        "tgn:1000111",
        "tgn:7029392"
    ],
    "tgn:id":1140016,
    "tgn:name":"Yongxing",
    "tgn:placetype":[
        "aat:300008347"
    ]
},
  "bbox": [],
  "geometry": {"coordinates":[123.8667,40.1833],"type":"Point"}
}