<<<<<<< HEAD
{
  "id": 7059021,
  "type": "Feature",
  "properties": {
    "tgn:hierarchy":[
        "tgn:7059021",
        "tgn:1003460",
        "tgn:1000003",
        "tgn:7009760",
        "tgn:1000080",
        "tgn:7029392"
    ],
    "tgn:id":7059021,
    "tgn:name":"Stazione d' Alberese",
    "tgn:placetype":[
        "aat:300007783"
    ]
},
  "bbox": [],
  "geometry": {"coordinates":[11.133333,42.633333],"type":"Point"}
}
=======
{"geometry":{"type":"Point","coordinates":[11.133333,42.633333]},"type":"Feature","properties":{"hierarchy":["tgn:7059021","tgn:1003460","tgn:1000003","tgn:7009760","tgn:1000080","tgn:7029392"],"placetype":["aat:300007783"],"id":7059021,"name:xx":"Stazione d' Alberese"}}
>>>>>>> 03f74aca74312dbeaf24d7e61306dd6a786dc3d0
