{
  "id": 2365945,
  "type": "Feature",
  "properties": {
    "tgn:hierarchy":[
        "tgn:2365945",
        "tgn:1000001",
        "tgn:7012149",
        "tgn:2000551",
        "tgn:7007252",
        "tgn:7029392"
    ],
    "tgn:id":2365945,
    "tgn:name":"Grey Lake",
    "tgn:placetype":[
        "aat:300006191"
    ]
},
  "bbox": [],
  "geometry": {"coordinates":[-87.2333,38.3167],"type":"Point"}
}