{
  "id": 7273256,
  "type": "Feature",
  "properties": {
    "tgn:hierarchy":[
        "tgn:7273256",
        "tgn:7003619",
        "tgn:1000003",
        "tgn:7016845",
        "tgn:7029392"
    ],
    "tgn:id":7273256,
    "tgn:name:nl":"Westerheide",
    "tgn:placetype":[
        "aat:300008187"
    ]
},
  "bbox": [],
  "geometry": {"coordinates":[5.833333,52.016667],"type":"Point"}
}