{
  "id": 2222880,
  "type": "Feature",
  "properties": {
    "tgn:hierarchy":[
        "tgn:2222880",
        "tgn:1000001",
        "tgn:7012149",
        "tgn:1002387",
        "tgn:7007710",
        "tgn:7029392"
    ],
    "tgn:id":2222880,
    "tgn:name":"Carrick Valley",
    "tgn:placetype":[
        "aat:300008347"
    ]
},
  "bbox": [],
  "geometry": {"coordinates":[-77.85,40.05],"type":"Point"}
}