{
  "id": 7147510,
  "type": "Feature",
  "properties": {
    "tgn:hierarchy":[
        "tgn:7147510",
        "tgn:1000003",
        "tgn:7003688",
        "tgn:7000084",
        "tgn:7029392"
    ],
    "tgn:id":7147510,
    "tgn:name":"Kudensee",
    "tgn:placetype":[
        "aat:300008347"
    ]
},
  "bbox": [],
  "geometry": {"coordinates":[9.216667,53.933333],"type":"Point"}
}