{
  "id": 2305326,
  "type": "Feature",
  "properties": {
    "tgn:hierarchy":[
        "tgn:2305326",
        "tgn:1000001",
        "tgn:7012149",
        "tgn:2002100",
        "tgn:7007826",
        "tgn:7029392"
    ],
    "tgn:id":2305326,
    "tgn:name":"East Branch Tortuga Creek",
    "tgn:placetype":[
        "aat:300008706"
    ]
},
  "bbox": [],
  "geometry": {"coordinates":[-99.6333,28.8333],"type":"Point"}
}