{
  "id": 7093088,
  "type": "Feature",
  "properties": {
    "tgn:hierarchy":[
        "tgn:7093088",
        "tgn:1000003",
        "tgn:7003676",
        "tgn:7000084",
        "tgn:7029392"
    ],
    "tgn:id":7093088,
    "tgn:name":"Schotenberg",
    "tgn:placetype":[
        "aat:300008863"
    ]
},
  "bbox": [],
  "geometry": {"coordinates":[9.466667,52.733333],"type":"Point"}
}