{
  "id": 7417444,
  "type": "Feature",
  "properties": {
    "tgn:hierarchy":[
        "tgn:7417444",
        "tgn:7005584",
        "tgn:1000001",
        "tgn:7005560",
        "tgn:7029392"
    ],
    "tgn:id":7417444,
    "tgn:name":"Santos Degollado",
    "tgn:placetype":[
        "aat:300008347"
    ]
},
  "bbox": [],
  "geometry": {"coordinates":[-100.856389,20.547222],"type":"Point"}
}