{
  "id": 2204641,
  "type": "Feature",
  "properties": {
    "tgn:hierarchy":[
        "tgn:2204641",
        "tgn:1000001",
        "tgn:7012149",
        "tgn:2001049",
        "tgn:7007521",
        "tgn:7029392"
    ],
    "tgn:id":2204641,
    "tgn:name":"Buffalo Lake",
    "tgn:placetype":[
        "aat:300008680"
    ]
},
  "bbox": [],
  "geometry": {"coordinates":[-95.5667,44.0667],"type":"Point"}
}