{
  "id": 1137239,
  "type": "Feature",
  "properties": {
    "tgn:hierarchy":[
        "tgn:1137239",
        "tgn:1000004",
        "tgn:7011500",
        "tgn:7002435",
        "tgn:7029392"
    ],
    "tgn:id":1137239,
    "tgn:name":"Bar",
    "tgn:placetype":[
        "aat:300008347"
    ]
},
  "bbox": [],
  "geometry": {"coordinates":[107.6667,51.3333],"type":"Point"}
}