{
  "id": 7529336,
  "type": "Feature",
  "properties": {
    "tgn:hierarchy":[
        "tgn:7529336",
        "tgn:7001242",
        "tgn:7016833",
        "tgn:1001225",
        "tgn:7029392"
    ],
    "tgn:id":7529336,
    "tgn:name":"Kull\u012byat at Tij\u0101rah",
    "tgn:placetype":[
        "aat:300006610"
    ]
},
  "bbox": [],
  "geometry": {"coordinates":[31.683062,31.440974],"type":"Point"}
}