{
  "id": 1073694,
  "type": "Feature",
  "properties": {
    "tgn:hierarchy":[
        "tgn:1073694",
        "tgn:1000004",
        "tgn:7018118",
        "tgn:1000111",
        "tgn:7029392"
    ],
    "tgn:id":1073694,
    "tgn:name":"Yuanyang",
    "tgn:placetype":[
        "aat:300008347"
    ]
},
  "bbox": [],
  "geometry": {"coordinates":[102.8167,23.2167],"type":"Point"}
}