<<<<<<< HEAD
{
  "id": 2766600,
  "type": "Feature",
  "properties": {
    "tgn:hierarchy":[
        "tgn:2766600",
        "tgn:1002148",
        "tgn:1000001",
        "tgn:7012149",
        "tgn:7007826",
        "tgn:7029392"
    ],
    "tgn:id":2766600,
    "tgn:name":"White Oak Creek",
    "tgn:placetype":[
        "aat:300008706"
    ]
},
  "bbox": [],
  "geometry": {"coordinates":[-95.4833,31.8667],"type":"Point"}
}
=======
{"geometry":{"type":"Point","coordinates":[-95.483300,31.866700]},"type":"Feature","properties":{"hierarchy":["tgn:2766600","tgn:1002148","tgn:1000001","tgn:7012149","tgn:7007826","tgn:7029392"],"placetype":["aat:300008706"],"id":2766600,"name:xx":"White Oak Creek"}}
>>>>>>> 03f74aca74312dbeaf24d7e61306dd6a786dc3d0
