<<<<<<< HEAD
{
  "id": 2769988,
  "type": "Feature",
  "properties": {
    "tgn:hierarchy":[
        "tgn:2769988",
        "tgn:1000001",
        "tgn:7012149",
        "tgn:1002882",
        "tgn:7007568",
        "tgn:7029392"
    ],
    "tgn:id":2769988,
    "tgn:name":"Wilcox Creek",
    "tgn:placetype":[
        "aat:300008706"
    ]
},
  "bbox": [],
  "geometry": {"coordinates":[-76.8833,42.75],"type":"Point"}
}
=======
{"geometry":{"type":"Point","coordinates":[-76.883300,42.750000]},"type":"Feature","properties":{"hierarchy":["tgn:2769988","tgn:1000001","tgn:7012149","tgn:1002882","tgn:7007568","tgn:7029392"],"placetype":["aat:300008706"],"id":2769988,"name:xx":"Wilcox Creek"}}
>>>>>>> 03f74aca74312dbeaf24d7e61306dd6a786dc3d0
