{
  "id": 7502220,
  "type": "Feature",
  "properties": {
    "tgn:hierarchy":[
        "tgn:7502220",
        "tgn:7001004",
        "tgn:1000004",
        "tgn:1000141",
        "tgn:7029392"
    ],
    "tgn:id":7502220,
    "tgn:name":"Yingpanding",
    "tgn:placetype":[
        "aat:300008347"
    ]
},
  "bbox": [],
  "geometry": {"coordinates":[120.377778,22.879167],"type":"Point"}
}