<<<<<<< HEAD
{
  "id": 7350510,
  "type": "Feature",
  "properties": {
    "tgn:hierarchy":[
        "tgn:7350510",
        "tgn:7005581",
        "tgn:1000001",
        "tgn:7005560",
        "tgn:7029392"
    ],
    "tgn:id":7350510,
    "tgn:name":"Bachurichic, Arroyo",
    "tgn:placetype":[
        "aat:300008699"
    ]
},
  "bbox": [],
  "geometry": {"coordinates":[-107.55,28.2],"type":"Point"}
}
=======
{"geometry":{"type":"Point","coordinates":[-107.550000,28.200000]},"type":"Feature","properties":{"hierarchy":["tgn:7350510","tgn:7005581","tgn:1000001","tgn:7005560","tgn:7029392"],"placetype":["aat:300008699"],"id":7350510,"name:xx":"Bachurichic, Arroyo"}}
>>>>>>> 03f74aca74312dbeaf24d7e61306dd6a786dc3d0
