{
  "id": 7086152,
  "type": "Feature",
  "properties": {
    "tgn:hierarchy":[
        "tgn:7086152",
        "tgn:1000003",
        "tgn:7003677",
        "tgn:7000084",
        "tgn:7029392"
    ],
    "tgn:id":7086152,
    "tgn:name":"Weidenhausen",
    "tgn:placetype":[
        "aat:300008347"
    ]
},
  "bbox": [],
  "geometry": {"coordinates":[8.366667,50.983333],"type":"Point"}
}