{
  "id": 7116098,
  "type": "Feature",
  "properties": {
    "tgn:hierarchy":[
        "tgn:7116098",
        "tgn:7003692",
        "tgn:1000003",
        "tgn:7000084",
        "tgn:7029392"
    ],
    "tgn:id":7116098,
    "tgn:name":"Oberweiler",
    "tgn:placetype":[
        "aat:300008347"
    ]
},
  "bbox": [],
  "geometry": {"coordinates":[9.928889,49.273611],"type":"Point"}
}