{
  "id": 2355739,
  "type": "Feature",
  "properties": {
    "tgn:hierarchy":[
        "tgn:2355739",
        "tgn:1000001",
        "tgn:7012149",
        "tgn:2001952",
        "tgn:7007826",
        "tgn:7029392"
    ],
    "tgn:id":2355739,
    "tgn:name":"Goose Island Passing Basin",
    "tgn:placetype":[
        "aat:300008678"
    ]
},
  "bbox": [],
  "geometry": {"coordinates":[-97.3167,25.9667],"type":"Point"}
}