{
  "id": 2465765,
  "type": "Feature",
  "properties": {
    "tgn:hierarchy":[
        "tgn:2465765",
        "tgn:1000001",
        "tgn:7012149",
        "tgn:2001843",
        "tgn:7007825",
        "tgn:7029392"
    ],
    "tgn:id":2465765,
    "tgn:name":"Lone Ridge",
    "tgn:placetype":[
        "aat:300266640"
    ]
},
  "bbox": [],
  "geometry": {"coordinates":[-84.2333,36.4667],"type":"Point"}
}