{
  "id": 7288130,
  "type": "Feature",
  "properties": {
    "tgn:hierarchy":[
        "tgn:7288130",
        "tgn:7016598",
        "tgn:1000049",
        "tgn:1000002",
        "tgn:7029392"
    ],
    "tgn:id":7288130,
    "tgn:name":"Jorgillo, Quebrada de",
    "tgn:placetype":[
        "aat:300266554",
        "aat:300008699"
    ]
},
  "bbox": [],
  "geometry": {"coordinates":[-70.466667,-23.75],"type":"Point"}
}