{
  "id": 1103937,
  "type": "Feature",
  "properties": {
    "tgn:hierarchy":[
        "tgn:1103937",
        "tgn:1000001",
        "tgn:7012149",
        "tgn:2002291",
        "tgn:7013961",
        "tgn:7029392"
    ],
    "tgn:id":1103937,
    "tgn:name":"Bickle Knob",
    "tgn:placetype":[
        "aat:300008795"
    ]
},
  "bbox": [],
  "geometry": {"coordinates":[-79.7167,38.9333],"type":"Point"}
}