<<<<<<< HEAD
{
  "id": 2761956,
  "type": "Feature",
  "properties": {
    "tgn:hierarchy":[
        "tgn:2761956",
        "tgn:1000001",
        "tgn:1002712",
        "tgn:7012149",
        "tgn:7007159",
        "tgn:7029392"
    ],
    "tgn:id":2761956,
    "tgn:name":"West Rock Ridge",
    "tgn:placetype":[
        "aat:300266640"
    ]
},
  "bbox": [],
  "geometry": {"coordinates":[-72.95,41.3667],"type":"Point"}
}
=======
{"geometry":{"type":"Point","coordinates":[-72.950000,41.366700]},"type":"Feature","properties":{"hierarchy":["tgn:2761956","tgn:1000001","tgn:1002712","tgn:7012149","tgn:7007159","tgn:7029392"],"placetype":["aat:300266640"],"id":2761956,"name:xx":"West Rock Ridge"}}
>>>>>>> 03f74aca74312dbeaf24d7e61306dd6a786dc3d0
