{
  "id": 7218597,
  "type": "Feature",
  "properties": {
    "tgn:hierarchy":[
        "tgn:7218597",
        "tgn:7011270",
        "tgn:7002674",
        "tgn:1000003",
        "tgn:1000074",
        "tgn:7029392"
    ],
    "tgn:id":7218597,
    "tgn:name":"Stav\u00f3lia, Vr\u00e1chos",
    "tgn:placetype":[
        "aat:300011692"
    ]
},
  "bbox": [],
  "geometry": {"coordinates":[25.255278,36.735833],"type":"Point"}
}