{
  "id": 2705633,
  "type": "Feature",
  "properties": {
    "tgn:hierarchy":[
        "tgn:2705633",
        "tgn:7006450",
        "tgn:1000001",
        "tgn:7012149",
        "tgn:7019760",
        "tgn:7029392"
    ],
    "tgn:id":2705633,
    "tgn:name":"Sushilna Island",
    "tgn:placetype":[
        "aat:300008791"
    ]
},
  "bbox": [],
  "geometry": {"coordinates":[-136.3667,57.8333],"type":"Point"}
}