{
  "id": 7492607,
  "type": "Feature",
  "properties": {
    "tgn:hierarchy":[
        "tgn:7492607",
        "tgn:1000004",
        "tgn:7004300",
        "tgn:1000141",
        "tgn:7029392"
    ],
    "tgn:id":7492607,
    "tgn:name":"Pingshan Yu",
    "tgn:placetype":[
        "aat:300008791"
    ]
},
  "bbox": [],
  "geometry": {"coordinates":[119.605155,23.63899],"type":"Point"}
}