{
  "id": 2547966,
  "type": "Feature",
  "properties": {
    "tgn:hierarchy":[
        "tgn:2547966",
        "tgn:1000001",
        "tgn:7012149",
        "tgn:1002871",
        "tgn:7007568",
        "tgn:7029392"
    ],
    "tgn:id":2547966,
    "tgn:name":"North Greenfield",
    "tgn:placetype":[
        "aat:300008347"
    ]
},
  "bbox": [],
  "geometry": {"coordinates":[-73.85,43.15],"type":"Point"}
}