{
  "id": 7328661,
  "type": "Feature",
  "properties": {
    "tgn:hierarchy":[
        "tgn:7328661",
        "tgn:7002820",
        "tgn:7030216",
        "tgn:1000003",
        "tgn:1000095",
        "tgn:7029392"
    ],
    "tgn:id":7328661,
    "tgn:name":"Pla Juanal, Collado de",
    "tgn:placetype":[
        "aat:300259572"
    ]
},
  "bbox": [],
  "geometry": {"coordinates":[2.703997,42.412207],"type":"Point"}
}