{
  "id": 2725163,
  "type": "Feature",
  "properties": {
    "tgn:hierarchy":[
        "tgn:2725163",
        "tgn:1000001",
        "tgn:7012149",
        "tgn:2002381",
        "tgn:7007923",
        "tgn:7029392"
    ],
    "tgn:id":2725163,
    "tgn:name":"Tongue River Ditch Number 1",
    "tgn:placetype":[
        "aat:300006075"
    ]
},
  "bbox": [],
  "geometry": {"coordinates":[-107.25,44.8833],"type":"Point"}
}