{
  "id": 1090869,
  "type": "Feature",
  "properties": {
    "tgn:hierarchy":[
        "tgn:1090869",
        "tgn:1001103",
        "tgn:7001242",
        "tgn:1000173",
        "tgn:7029392"
    ],
    "tgn:id":1090869,
    "tgn:name":"Betafo",
    "tgn:placetype":[
        "aat:300008347"
    ]
},
  "bbox": [],
  "geometry": {"coordinates":[46.8333,-19.8333],"type":"Point"}
}