{
  "id": 2048760,
  "type": "Feature",
  "properties": {
    "tgn:hierarchy":[
        "tgn:2048760",
        "tgn:1002247",
        "tgn:1000001",
        "tgn:7012149",
        "tgn:7007516",
        "tgn:7029392"
    ],
    "tgn:id":2048760,
    "tgn:name":"Singerly",
    "tgn:placetype":[
        "aat:300387016"
    ]
},
  "bbox": [],
  "geometry": {"coordinates":[-75.8333,39.6333],"type":"Point"}
}