{
  "id": 1081170,
  "type": "Feature",
  "properties": {
    "tgn:hierarchy":[
        "tgn:1081170",
        "tgn:1000961",
        "tgn:1000004",
        "tgn:7000901",
        "tgn:1000120",
        "tgn:7029392"
    ],
    "tgn:id":1081170,
    "tgn:name":"Saganoseki",
    "tgn:placetype":[
        "aat:300008347"
    ]
},
  "bbox": [],
  "geometry": {"coordinates":[131.85,33.2667],"type":"Point"}
}