{
  "id": 2511384,
  "type": "Feature",
  "properties": {
    "tgn:hierarchy":[
        "tgn:2511384",
        "tgn:1000001",
        "tgn:7012149",
        "tgn:2001869",
        "tgn:7007825",
        "tgn:7029392"
    ],
    "tgn:id":2511384,
    "tgn:name":"Milbro Heights",
    "tgn:placetype":[
        "aat:300008347"
    ]
},
  "bbox": [],
  "geometry": {"coordinates":[-85.2667,34.9833],"type":"Point"}
}