{
  "id": 2322061,
  "type": "Feature",
  "properties": {
    "tgn:hierarchy":[
        "tgn:2322061",
        "tgn:2000453",
        "tgn:1000001",
        "tgn:7012149",
        "tgn:7007250",
        "tgn:7029392"
    ],
    "tgn:id":2322061,
    "tgn:name":"Fall Creek",
    "tgn:placetype":[
        "aat:300008706"
    ]
},
  "bbox": [],
  "geometry": {"coordinates":[-116.3667,45.2333],"type":"Point"}
}