<<<<<<< HEAD
{
  "id": 7368746,
  "type": "Feature",
  "properties": {
    "tgn:hierarchy":[
        "tgn:7368746",
        "tgn:7005583",
        "tgn:1000001",
        "tgn:7005560",
        "tgn:7029392"
    ],
    "tgn:id":7368746,
    "tgn:name":"Guadalupe",
    "tgn:placetype":[
        "aat:300008347"
    ]
},
  "bbox": [],
  "geometry": {"coordinates":[-104.9,24.4],"type":"Point"}
}
=======
{"geometry":{"type":"Point","coordinates":[-104.900000,24.400000]},"type":"Feature","properties":{"hierarchy":["tgn:7368746","tgn:7005583","tgn:1000001","tgn:7005560","tgn:7029392"],"placetype":["aat:300008347"],"id":7368746,"name:xx":"Guadalupe"}}
>>>>>>> 03f74aca74312dbeaf24d7e61306dd6a786dc3d0
