{
  "id": 2270365,
  "type": "Feature",
  "properties": {
    "tgn:hierarchy":[
        "tgn:2270365",
        "tgn:1000001",
        "tgn:7012149",
        "tgn:1002557",
        "tgn:7007252",
        "tgn:7029392"
    ],
    "tgn:id":2270365,
    "tgn:name":"Crystal Lake",
    "tgn:placetype":[
        "aat:300008680"
    ]
},
  "bbox": [],
  "geometry": {"coordinates":[-85.9833,41.2333],"type":"Point"}
}