{
  "id": 2127063,
  "type": "Feature",
  "properties": {
    "tgn:hierarchy":[
        "tgn:2127063",
        "tgn:1002648",
        "tgn:1000001",
        "tgn:7012149",
        "tgn:7007249",
        "tgn:7029392"
    ],
    "tgn:id":2127063,
    "tgn:name":"Ahole Rock",
    "tgn:placetype":[
        "aat:300008791"
    ]
},
  "bbox": [],
  "geometry": {"coordinates":[-156.05,20.6333],"type":"Point"}
}