{
  "id": 2023093,
  "type": "Feature",
  "properties": {
    "tgn:hierarchy":[
        "tgn:2023093",
        "tgn:1000001",
        "tgn:7012149",
        "tgn:2000363",
        "tgn:7007248",
        "tgn:7029392"
    ],
    "tgn:id":2023093,
    "tgn:name":"Hamilton",
    "tgn:placetype":[
        "aat:300008347"
    ]
},
  "bbox": [],
  "geometry": {"coordinates":[-84.8667,32.75],"type":"Point"}
}