{
  "id": 7370992,
  "type": "Feature",
  "properties": {
    "tgn:hierarchy":[
        "tgn:7370992",
        "tgn:7005587",
        "tgn:1000001",
        "tgn:7005560",
        "tgn:7029392"
    ],
    "tgn:id":7370992,
    "tgn:name":"Huixticola",
    "tgn:placetype":[
        "aat:300008347"
    ]
},
  "bbox": [],
  "geometry": {"coordinates":[-98.85,20.55],"type":"Point"}
}