{
  "id": 2646533,
  "type": "Feature",
  "properties": {
    "tgn:hierarchy":[
        "tgn:2646533",
        "tgn:1000001",
        "tgn:7012149",
        "tgn:7007253",
        "tgn:7029392"
    ],
    "tgn:id":2646533,
    "tgn:name":"Saylings Creek",
    "tgn:placetype":[
        "aat:300008706"
    ]
},
  "bbox": [],
  "geometry": {"coordinates":[-94.5667,40.9167],"type":"Point"}
}