{
  "id": 1084921,
  "type": "Feature",
  "properties": {
    "tgn:hierarchy":[
        "tgn:1084921",
        "tgn:1000004",
        "tgn:1000138",
        "tgn:7000381",
        "tgn:7029392"
    ],
    "tgn:id":1084921,
    "tgn:name":"Bukit Timah",
    "tgn:placetype":[
        "aat:300008347"
    ]
},
  "bbox": [],
  "geometry": {"coordinates":[103.7667,1.3333],"type":"Point"}
}