<<<<<<< HEAD
{
  "id": 7378800,
  "type": "Feature",
  "properties": {
    "tgn:hierarchy":[
        "tgn:7378800",
        "tgn:1000001",
        "tgn:1001960",
        "tgn:7005560",
        "tgn:7029392"
    ],
    "tgn:id":7378800,
    "tgn:name":"Los Capomos",
    "tgn:placetype":[
        "aat:300008347"
    ]
},
  "bbox": [],
  "geometry": {"coordinates":[-109.05,26.733333],"type":"Point"}
}
=======
{"geometry":{"type":"Point","coordinates":[-109.050000,26.733333]},"type":"Feature","properties":{"hierarchy":["tgn:7378800","tgn:1000001","tgn:1001960","tgn:7005560","tgn:7029392"],"placetype":["aat:300008347"],"id":7378800,"name:xx":"Los Capomos"}}
>>>>>>> 03f74aca74312dbeaf24d7e61306dd6a786dc3d0
