{
  "id": 2054017,
  "type": "Feature",
  "properties": {
    "tgn:hierarchy":[
        "tgn:2054017",
        "tgn:1000001",
        "tgn:7012149",
        "tgn:2001028",
        "tgn:7007521",
        "tgn:7029392"
    ],
    "tgn:id":2054017,
    "tgn:name":"Bradford",
    "tgn:placetype":[
        "aat:300008347"
    ]
},
  "bbox": [],
  "geometry": {"coordinates":[-93.3667,45.5167],"type":"Point"}
}