{
  "id": 2169028,
  "type": "Feature",
  "properties": {
    "tgn:hierarchy":[
        "tgn:2169028",
        "tgn:1000001",
        "tgn:7012149",
        "tgn:2001906",
        "tgn:7007825",
        "tgn:7029392"
    ],
    "tgn:id":2169028,
    "tgn:name":"Big Island",
    "tgn:placetype":[
        "aat:300008791"
    ]
},
  "bbox": [],
  "geometry": {"coordinates":[-84.4833,35.1833],"type":"Point"}
}