{
  "id": 7316532,
  "type": "Feature",
  "properties": {
    "tgn:hierarchy":[
        "tgn:7316532",
        "tgn:7002464",
        "tgn:1000049",
        "tgn:1000002",
        "tgn:7029392"
    ],
    "tgn:id":7316532,
    "tgn:name":"Casiri Macho, Laguna",
    "tgn:placetype":[
        "aat:300008679"
    ]
},
  "bbox": [],
  "geometry": {"coordinates":[-69.066667,-18.066667],"type":"Point"}
}