{
  "id": 2164593,
  "type": "Feature",
  "properties": {
    "tgn:hierarchy":[
        "tgn:2164593",
        "tgn:1000001",
        "tgn:7012149",
        "tgn:1002418",
        "tgn:7007920",
        "tgn:7029392"
    ],
    "tgn:id":2164593,
    "tgn:name":"Berryman Creek",
    "tgn:placetype":[
        "aat:300008706"
    ]
},
  "bbox": [],
  "geometry": {"coordinates":[-123.7833,47.0667],"type":"Point"}
}