{
  "id": 1032661,
  "type": "Feature",
  "properties": {
    "tgn:hierarchy":[
        "tgn:1032661",
        "tgn:1000003",
        "tgn:1000070",
        "tgn:7002897",
        "tgn:7029392"
    ],
    "tgn:id":1032661,
    "tgn:name":"Chevenoz",
    "tgn:placetype":[
        "aat:300008347"
    ]
},
  "bbox": [],
  "geometry": {"coordinates":[6.65,46.3333],"type":"Point"}
}