{
  "id": 2474386,
  "type": "Feature",
  "properties": {
    "tgn:hierarchy":[
        "tgn:2474386",
        "tgn:1000001",
        "tgn:7012149",
        "tgn:7007157",
        "tgn:1002863",
        "tgn:7029392"
    ],
    "tgn:id":2474386,
    "tgn:name":"Lower Piletas Canyon",
    "tgn:placetype":[
        "aat:300008761"
    ]
},
  "bbox": [],
  "geometry": {"coordinates":[-120.1167,35.2667],"type":"Point"}
}