{
  "id": 7216675,
  "type": "Feature",
  "properties": {
    "tgn:hierarchy":[
        "tgn:7216675",
        "tgn:1000003",
        "tgn:7003673",
        "tgn:7000084",
        "tgn:7029392"
    ],
    "tgn:id":7216675,
    "tgn:name":"Alte S\u00fcder Elbe",
    "tgn:placetype":[
        "aat:300387032"
    ]
},
  "bbox": [],
  "geometry": {"coordinates":[9.816667,53.516667],"type":"Point"}
}