{
  "id": 2502272,
  "type": "Feature",
  "properties": {
    "tgn:hierarchy":[
        "tgn:2502272",
        "tgn:1000001",
        "tgn:7012149",
        "tgn:2001519",
        "tgn:7007709",
        "tgn:7029392"
    ],
    "tgn:id":2502272,
    "tgn:name":"McKinney Cove",
    "tgn:placetype":[
        "aat:300008347"
    ]
},
  "bbox": [],
  "geometry": {"coordinates":[-82.1333,36.0167],"type":"Point"}
}