{
  "id": 2373151,
  "type": "Feature",
  "properties": {
    "tgn:hierarchy":[
        "tgn:2373151",
        "tgn:1000001",
        "tgn:7012149",
        "tgn:2001755",
        "tgn:7007712",
        "tgn:7029392"
    ],
    "tgn:id":2373151,
    "tgn:name":"Halls Millpond",
    "tgn:placetype":[
        "aat:300008680"
    ]
},
  "bbox": [],
  "geometry": {"coordinates":[-80.3667,34.2667],"type":"Point"}
}