{
  "id": 2201724,
  "type": "Feature",
  "properties": {
    "tgn:hierarchy":[
        "tgn:2201724",
        "tgn:1000001",
        "tgn:7012149",
        "tgn:2001854",
        "tgn:7007825",
        "tgn:7029392"
    ],
    "tgn:id":2201724,
    "tgn:name":"Buck Creek",
    "tgn:placetype":[
        "aat:300008706"
    ]
},
  "bbox": [],
  "geometry": {"coordinates":[-84.9833,35.85],"type":"Point"}
}