{
  "id": 2560152,
  "type": "Feature",
  "properties": {
    "tgn:hierarchy":[
        "tgn:2560152",
        "tgn:1000001",
        "tgn:1002194",
        "tgn:7012149",
        "tgn:7007710",
        "tgn:7029392"
    ],
    "tgn:id":2560152,
    "tgn:name":"Orange Hill",
    "tgn:placetype":[
        "aat:300008798"
    ]
},
  "bbox": [],
  "geometry": {"coordinates":[-76.4667,41.9333],"type":"Point"}
}