{
  "id": 7052389,
  "type": "Feature",
  "properties": {
    "tgn:hierarchy":[
        "tgn:7052389",
        "tgn:7005852",
        "tgn:1000003",
        "tgn:7003237",
        "tgn:1000080",
        "tgn:7029392"
    ],
    "tgn:id":7052389,
    "tgn:name":"Morbio",
    "tgn:placetype":[
        "aat:300008347"
    ]
},
  "bbox": [],
  "geometry": {"coordinates":[9.266667,46.133333],"type":"Point"}
}