{
  "id": 7395271,
  "type": "Feature",
  "properties": {
    "tgn:hierarchy":[
        "tgn:7395271",
        "tgn:7005584",
        "tgn:1000001",
        "tgn:7005560",
        "tgn:7029392"
    ],
    "tgn:id":7395271,
    "tgn:name":"San Jos\u00e9 de Malpaso",
    "tgn:placetype":[
        "aat:300008347"
    ]
},
  "bbox": [],
  "geometry": {"coordinates":[-101.65,21.166667],"type":"Point"}
}