{
  "id": 7537448,
  "type": "Feature",
  "properties": {
    "tgn:hierarchy":[
        "tgn:7537448",
        "tgn:7001242",
        "tgn:7016833",
        "tgn:1001087",
        "tgn:7029392"
    ],
    "tgn:id":7537448,
    "tgn:name:en":"Shanaw\u0101n",
    "tgn:placetype":[
        "aat:300008347"
    ]
},
  "bbox": [],
  "geometry": {"coordinates":[31.00702,30.501618],"type":"Point"}
}