{
  "id": 7481680,
  "type": "Feature",
  "properties": {
    "tgn:hierarchy":[
        "tgn:7481680",
        "tgn:1000004",
        "tgn:7489179",
        "tgn:1000141",
        "tgn:7029392"
    ],
    "tgn:id":7481680,
    "tgn:name":"Nanmeiyouyan Shan",
    "tgn:placetype":[
        "aat:300008798"
    ]
},
  "bbox": [],
  "geometry": {"coordinates":[121.365833,24.502778],"type":"Point"}
}