{
  "id": 7521751,
  "type": "Feature",
  "properties": {
    "tgn:hierarchy":[
        "tgn:7521751",
        "tgn:7001242",
        "tgn:7016833",
        "tgn:7001336",
        "tgn:7029392"
    ],
    "tgn:id":7521751,
    "tgn:name:en":"Ab\u016b Khashib, Jabal",
    "tgn:placetype":[
        "aat:300008795"
    ]
},
  "bbox": [],
  "geometry": {"coordinates":[34.59909,29.072651],"type":"Point"}
}