<<<<<<< HEAD
{
  "id": 7058309,
  "type": "Feature",
  "properties": {
    "tgn:hierarchy":[
        "tgn:7058309",
        "tgn:7003134",
        "tgn:1000003",
        "tgn:7008516",
        "tgn:1000080",
        "tgn:7029392"
    ],
    "tgn:id":7058309,
    "tgn:name":"Botteghe",
    "tgn:placetype":[
        "aat:300008347"
    ]
},
  "bbox": [],
  "geometry": {"coordinates":[10.583333,44.616667],"type":"Point"}
}
=======
{"geometry":{"type":"Point","coordinates":[10.583333,44.616667]},"type":"Feature","properties":{"hierarchy":["tgn:7058309","tgn:7003134","tgn:1000003","tgn:7008516","tgn:1000080","tgn:7029392"],"placetype":["aat:300008347"],"id":7058309,"name:xx":"Botteghe"}}
>>>>>>> 03f74aca74312dbeaf24d7e61306dd6a786dc3d0
