<<<<<<< HEAD
{
  "id": 2338590,
  "type": "Feature",
  "properties": {
    "tgn:hierarchy":[
        "tgn:2338590",
        "tgn:1000001",
        "tgn:7012149",
        "tgn:7013941",
        "tgn:7007568",
        "tgn:7029392"
    ],
    "tgn:id":2338590,
    "tgn:name":"Frances, Lake",
    "tgn:placetype":[
        "aat:300008680"
    ]
},
  "bbox": [],
  "geometry": {"coordinates":[-74.3167,44.6833],"type":"Point"}
}
=======
{"geometry":{"type":"Point","coordinates":[-74.316700,44.683300]},"type":"Feature","properties":{"hierarchy":["tgn:2338590","tgn:1000001","tgn:7012149","tgn:7013941","tgn:7007568","tgn:7029392"],"placetype":["aat:300008680"],"id":2338590,"name:xx":"Frances, Lake"}}
>>>>>>> 03f74aca74312dbeaf24d7e61306dd6a786dc3d0
