{
  "id": 7472655,
  "type": "Feature",
  "properties": {
    "tgn:hierarchy":[
        "tgn:7472655",
        "tgn:1000004",
        "tgn:7467799",
        "tgn:1000141",
        "tgn:7029392"
    ],
    "tgn:id":7472655,
    "tgn:name":"Xiaxiqian Tifang",
    "tgn:placetype":[
        "aat:300006156"
    ]
},
  "bbox": [],
  "geometry": {"coordinates":[120.3945,23.8383],"type":"Point"}
}