{
  "id": 7552373,
  "type": "Feature",
  "properties": {
    "tgn:hierarchy":[
        "tgn:7552373",
        "tgn:1001828",
        "tgn:1000004",
        "tgn:7000198",
        "tgn:7029392"
    ],
    "tgn:id":7552373,
    "tgn:name:en":"Pal\u0101sa",
    "tgn:placetype":[
        "aat:300008347"
    ]
},
  "bbox": [],
  "geometry": {"coordinates":[84.416667,18.766667],"type":"Point"}
}