{
  "id": 2696043,
  "type": "Feature",
  "properties": {
    "tgn:hierarchy":[
        "tgn:2696043",
        "tgn:1000001",
        "tgn:7012149",
        "tgn:2000998",
        "tgn:7007520",
        "tgn:7029392"
    ],
    "tgn:id":2696043,
    "tgn:name":"Stoddard Lake",
    "tgn:placetype":[
        "aat:300008680"
    ]
},
  "bbox": [],
  "geometry": {"coordinates":[-85.4667,44.3667],"type":"Point"}
}