{
  "id": 2650248,
  "type": "Feature",
  "properties": {
    "tgn:hierarchy":[
        "tgn:2650248",
        "tgn:1000001",
        "tgn:7014352",
        "tgn:7012149",
        "tgn:7007564",
        "tgn:7029392"
    ],
    "tgn:id":2650248,
    "tgn:name":"Seal Rocks",
    "tgn:placetype":[
        "aat:300132348"
    ]
},
  "bbox": [],
  "geometry": {"coordinates":[-70.7167,43.0167],"type":"Point"}
}