{
  "id": 7526682,
  "type": "Feature",
  "properties": {
    "tgn:hierarchy":[
        "tgn:7526682",
        "tgn:7001242",
        "tgn:7016833",
        "tgn:1001088",
        "tgn:7029392"
    ],
    "tgn:id":7526682,
    "tgn:name:en":"S\u012bd\u012b Mub\u0101rak",
    "tgn:placetype":[
        "aat:300005926"
    ]
},
  "bbox": [],
  "geometry": {"coordinates":[30.866667,28.65],"type":"Point"}
}