{
  "id": 7533102,
  "type": "Feature",
  "properties": {
    "tgn:hierarchy":[
        "tgn:7533102",
        "tgn:7001242",
        "tgn:7016833",
        "tgn:1001335",
        "tgn:7029392"
    ],
    "tgn:id":7533102,
    "tgn:name:en":"Ma\u015fraf \u1e28ulays",
    "tgn:placetype":[
        "aat:300006075"
    ]
},
  "bbox": [],
  "geometry": {"coordinates":[30.941492,31.121856],"type":"Point"}
}