<<<<<<< HEAD
{
  "id": 2408177,
  "type": "Feature",
  "properties": {
    "tgn:hierarchy":[
        "tgn:2408177",
        "tgn:1000001",
        "tgn:7012149",
        "tgn:2001867",
        "tgn:7007825",
        "tgn:7029392"
    ],
    "tgn:id":2408177,
    "tgn:name":"Hurricane, The",
    "tgn:placetype":[
        "aat:300008761"
    ]
},
  "bbox": [],
  "geometry": {"coordinates":[-85.8,35.2833],"type":"Point"}
}
=======
{"geometry":{"type":"Point","coordinates":[-85.800000,35.283300]},"type":"Feature","properties":{"hierarchy":["tgn:2408177","tgn:1000001","tgn:7012149","tgn:2001867","tgn:7007825","tgn:7029392"],"placetype":["aat:300008761"],"id":2408177,"name:xx":"Hurricane, The"}}
>>>>>>> 03f74aca74312dbeaf24d7e61306dd6a786dc3d0
