{
  "id": 1019694,
  "type": "Feature",
  "properties": {
    "tgn:hierarchy":[
        "tgn:1019694",
        "tgn:1001160",
        "tgn:7006477",
        "tgn:1000002",
        "tgn:7029392"
    ],
    "tgn:id":1019694,
    "tgn:name":"Lober\u00eda",
    "tgn:placetype":[
        "aat:300008347"
    ]
},
  "bbox": [],
  "geometry": {"coordinates":[-58.7833,-38.15],"type":"Point"}
}