{
  "id": 7237554,
  "type": "Feature",
  "properties": {
    "tgn:hierarchy":[
        "tgn:7237554",
        "tgn:7011270",
        "tgn:7002674",
        "tgn:1000003",
        "tgn:1000074",
        "tgn:7029392"
    ],
    "tgn:id":7237554,
    "tgn:name":"Tragon\u00edsi, Nis\u00edda",
    "tgn:placetype":[
        "aat:300008791"
    ]
},
  "bbox": [],
  "geometry": {"coordinates":[25.483333,37.45],"type":"Point"}
}