{
  "id": 2701266,
  "type": "Feature",
  "properties": {
    "tgn:hierarchy":[
        "tgn:2701266",
        "tgn:1000001",
        "tgn:7012149",
        "tgn:2000213",
        "tgn:7007158",
        "tgn:7029392"
    ],
    "tgn:id":2701266,
    "tgn:name":"Sugar Loaf",
    "tgn:placetype":[
        "aat:300008798"
    ]
},
  "bbox": [],
  "geometry": {"coordinates":[-105.0167,38.5833],"type":"Point"}
}