{
  "id": 2471334,
  "type": "Feature",
  "properties": {
    "tgn:hierarchy":[
        "tgn:2471334",
        "tgn:1000001",
        "tgn:7012149",
        "tgn:7007157",
        "tgn:7014004",
        "tgn:7029392"
    ],
    "tgn:id":2471334,
    "tgn:name":"Lost Lake",
    "tgn:placetype":[
        "aat:300008680"
    ]
},
  "bbox": [],
  "geometry": {"coordinates":[-119.5167,37.7333],"type":"Point"}
}