{
  "id": 7146090,
  "type": "Feature",
  "properties": {
    "tgn:hierarchy":[
        "tgn:7146090",
        "tgn:1000003",
        "tgn:7003688",
        "tgn:7000084",
        "tgn:7029392"
    ],
    "tgn:id":7146090,
    "tgn:name":"Kleinsolt",
    "tgn:placetype":[
        "aat:300008347"
    ]
},
  "bbox": [],
  "geometry": {"coordinates":[9.516667,54.733333],"type":"Point"}
}