{
  "id": 7302575,
  "type": "Feature",
  "properties": {
    "tgn:hierarchy":[
        "tgn:7302575",
        "tgn:7001158",
        "tgn:7002850",
        "tgn:1000003",
        "tgn:1000095",
        "tgn:7029392"
    ],
    "tgn:id":7302575,
    "tgn:name":"Murias",
    "tgn:placetype":[
        "aat:300008347"
    ]
},
  "bbox": [],
  "geometry": {"coordinates":[-6.666667,42.133333],"type":"Point"}
}