{
  "id": 7183019,
  "type": "Feature",
  "properties": {
    "tgn:hierarchy":[
        "tgn:7183019",
        "tgn:1000003",
        "tgn:7003687",
        "tgn:7000084",
        "tgn:7029392"
    ],
    "tgn:id":7183019,
    "tgn:name":"Galgen-Berg",
    "tgn:placetype":[
        "aat:300266640"
    ]
},
  "bbox": [],
  "geometry": {"coordinates":[10.85,51.933333],"type":"Point"}
}