{
  "id": 7333822,
  "type": "Feature",
  "properties": {
    "tgn:hierarchy":[
        "tgn:7333822",
        "tgn:1001439",
        "tgn:1000003",
        "tgn:7002797",
        "tgn:1000095",
        "tgn:7029392"
    ],
    "tgn:id":7333822,
    "tgn:name":"Ermita del Ramonete",
    "tgn:placetype":[
        "aat:300008347"
    ]
},
  "bbox": [],
  "geometry": {"coordinates":[-1.483333,37.533333],"type":"Point"}
}