{
  "id": 7341069,
  "type": "Feature",
  "properties": {
    "tgn:hierarchy":[
        "tgn:7341069",
        "tgn:7002759",
        "tgn:7008909",
        "tgn:1000003",
        "tgn:1000095",
        "tgn:7029392"
    ],
    "tgn:id":7341069,
    "tgn:name":"Buesa",
    "tgn:placetype":[
        "aat:300008347"
    ]
},
  "bbox": [],
  "geometry": {"coordinates":[-0.108376,42.584982],"type":"Point"}
}