{
  "id": 1109134,
  "type": "Feature",
  "properties": {
    "tgn:hierarchy":[
        "tgn:1109134",
        "tgn:7001242",
        "tgn:1000149",
        "tgn:1000868",
        "tgn:7029392"
    ],
    "tgn:id":1109134,
    "tgn:name":"Humbi, Serra",
    "tgn:placetype":[
        "aat:300008795"
    ]
},
  "bbox": [],
  "geometry": {"coordinates":[15.428,-12.17],"type":"Point"}
}