{
  "id": 7513676,
  "type": "Feature",
  "properties": {
    "tgn:hierarchy":[
        "tgn:7513676",
        "tgn:1009227",
        "tgn:1000226",
        "tgn:7018437",
        "tgn:1000006",
        "tgn:7029392"
    ],
    "tgn:id":7513676,
    "tgn:name:en":"Frankton Arm",
    "tgn:placetype":[
        "aat:300132316"
    ]
},
  "bbox": [],
  "geometry": {"coordinates":[168.666667,-45.05],"type":"Point"}
}