{
  "id": 7091392,
  "type": "Feature",
  "properties": {
    "tgn:hierarchy":[
        "tgn:7091392",
        "tgn:7003669",
        "tgn:1000003",
        "tgn:7000084",
        "tgn:7029392"
    ],
    "tgn:id":7091392,
    "tgn:name":"Vogel-Bach",
    "tgn:placetype":[
        "aat:300008699"
    ]
},
  "bbox": [],
  "geometry": {"coordinates":[11.066667,47.75],"type":"Point"}
}