{
  "id": 2746967,
  "type": "Feature",
  "properties": {
    "tgn:hierarchy":[
        "tgn:2746967",
        "tgn:1000001",
        "tgn:7012149",
        "tgn:1002353",
        "tgn:7007252",
        "tgn:7029392"
    ],
    "tgn:id":2746967,
    "tgn:name":"Wagner Ditch",
    "tgn:placetype":[
        "aat:300006075"
    ]
},
  "bbox": [],
  "geometry": {"coordinates":[-85.9167,41.45],"type":"Point"}
}