{
  "id": 2551972,
  "type": "Feature",
  "properties": {
    "tgn:hierarchy":[
        "tgn:2551972",
        "tgn:1000001",
        "tgn:7006451",
        "tgn:2000092",
        "tgn:7012149",
        "tgn:7029392"
    ],
    "tgn:id":2551972,
    "tgn:name":"Number Five, Tank",
    "tgn:placetype":[
        "aat:300006191"
    ]
},
  "bbox": [],
  "geometry": {"coordinates":[-111.9333,36.4333],"type":"Point"}
}