{
  "id": 7256717,
  "type": "Feature",
  "properties": {
    "tgn:hierarchy":[
        "tgn:7256717",
        "tgn:7004783",
        "tgn:7593114",
        "tgn:7593112",
        "tgn:1000001",
        "tgn:7029392"
    ],
    "tgn:id":7256717,
    "tgn:name:nl":"Claes Gut",
    "tgn:placetype":[
        "aat:300266554",
        "aat:300008699"
    ]
},
  "bbox": [],
  "geometry": {"coordinates":[-62.983333,17.466667],"type":"Point"}
}