{
  "id": 2289919,
  "type": "Feature",
  "properties": {
    "tgn:hierarchy":[
        "tgn:2289919",
        "tgn:1000001",
        "tgn:7012149",
        "tgn:1003031",
        "tgn:7007826",
        "tgn:7029392"
    ],
    "tgn:id":2289919,
    "tgn:name":"Doc Gan Hollow",
    "tgn:placetype":[
        "aat:300008761"
    ]
},
  "bbox": [],
  "geometry": {"coordinates":[-97.8333,33.35],"type":"Point"}
}