<<<<<<< HEAD
{
  "id": 2402225,
  "type": "Feature",
  "properties": {
    "tgn:hierarchy":[
        "tgn:2402225",
        "tgn:1000001",
        "tgn:7012149",
        "tgn:1003042",
        "tgn:7007920",
        "tgn:7029392"
    ],
    "tgn:id":2402225,
    "tgn:name":"Horsethief Point",
    "tgn:placetype":[
        "aat:300008798"
    ]
},
  "bbox": [],
  "geometry": {"coordinates":[-119.8833,46.5333],"type":"Point"}
}
=======
{"geometry":{"type":"Point","coordinates":[-119.883300,46.533300]},"type":"Feature","properties":{"hierarchy":["tgn:2402225","tgn:1000001","tgn:7012149","tgn:1003042","tgn:7007920","tgn:7029392"],"placetype":["aat:300008798"],"id":2402225,"name:xx":"Horsethief Point"}}
>>>>>>> 03f74aca74312dbeaf24d7e61306dd6a786dc3d0
