{
  "id": 2246160,
  "type": "Feature",
  "properties": {
    "tgn:hierarchy":[
        "tgn:2246160",
        "tgn:1000001",
        "tgn:7012149",
        "tgn:2001452",
        "tgn:7007566",
        "tgn:7029392"
    ],
    "tgn:id":2246160,
    "tgn:name":"Coalbank Canyon",
    "tgn:placetype":[
        "aat:300008761"
    ]
},
  "bbox": [],
  "geometry": {"coordinates":[-108.25,36.9333],"type":"Point"}
}