{
  "id": 2694402,
  "type": "Feature",
  "properties": {
    "tgn:hierarchy":[
        "tgn:2694402",
        "tgn:7013349",
        "tgn:1000001",
        "tgn:7012149",
        "tgn:7007708",
        "tgn:7029392"
    ],
    "tgn:id":2694402,
    "tgn:name":"Steward Ditch",
    "tgn:placetype":[
        "aat:300006075"
    ]
},
  "bbox": [],
  "geometry": {"coordinates":[-117.4833,44.8667],"type":"Point"}
}