{
  "id": 7298671,
  "type": "Feature",
  "properties": {
    "tgn:hierarchy":[
        "tgn:7298671",
        "tgn:7002826",
        "tgn:7001158",
        "tgn:1000003",
        "tgn:1000095",
        "tgn:7029392"
    ],
    "tgn:id":7298671,
    "tgn:name":"Valle, Arroyo del",
    "tgn:placetype":[
        "aat:300266554",
        "aat:300008699"
    ]
},
  "bbox": [],
  "geometry": {"coordinates":[-5.933333,42.35],"type":"Point"}
}