{
  "id": 2244845,
  "type": "Feature",
  "properties": {
    "tgn:hierarchy":[
        "tgn:2244845",
        "tgn:1000001",
        "tgn:7012149",
        "tgn:2002193",
        "tgn:7007919",
        "tgn:7029392"
    ],
    "tgn:id":2244845,
    "tgn:name":"Clouds, Lake of the",
    "tgn:placetype":[
        "aat:300006191"
    ]
},
  "bbox": [],
  "geometry": {"coordinates":[-78.0333,38.9833],"type":"Point"}
}