{
  "id": 2042847,
  "type": "Feature",
  "properties": {
    "tgn:hierarchy":[
        "tgn:2042847",
        "tgn:1000001",
        "tgn:2000863",
        "tgn:7012149",
        "tgn:7007256",
        "tgn:7029392"
    ],
    "tgn:id":2042847,
    "tgn:name":"Ged",
    "tgn:placetype":[
        "aat:300008347"
    ]
},
  "bbox": [],
  "geometry": {"coordinates":[-93.5833,30.1333],"type":"Point"}
}