<<<<<<< HEAD
{
  "id": 2253918,
  "type": "Feature",
  "properties": {
    "tgn:hierarchy":[
        "tgn:2253918",
        "tgn:1002153",
        "tgn:1000001",
        "tgn:7012149",
        "tgn:7007710",
        "tgn:7029392"
    ],
    "tgn:id":2253918,
    "tgn:name":"Cooks Summit",
    "tgn:placetype":[
        "aat:300008347"
    ]
},
  "bbox": [],
  "geometry": {"coordinates":[-79.5333,40.7],"type":"Point"}
}
=======
{"geometry":{"type":"Point","coordinates":[-79.533300,40.700000]},"type":"Feature","properties":{"hierarchy":["tgn:2253918","tgn:1002153","tgn:1000001","tgn:7012149","tgn:7007710","tgn:7029392"],"placetype":["aat:300008347"],"id":2253918,"name:xx":"Cooks Summit"}}
>>>>>>> 03f74aca74312dbeaf24d7e61306dd6a786dc3d0
