{
  "id": 7428144,
  "type": "Feature",
  "properties": {
    "tgn:hierarchy":[
        "tgn:7428144",
        "tgn:1000001",
        "tgn:7005594",
        "tgn:7005560",
        "tgn:7029392"
    ],
    "tgn:id":7428144,
    "tgn:name":"El Picacho",
    "tgn:placetype":[
        "aat:300008347"
    ]
},
  "bbox": [],
  "geometry": {"coordinates":[-101.283333,23.616667],"type":"Point"}
}