{
  "id": 2174526,
  "type": "Feature",
  "properties": {
    "tgn:hierarchy":[
        "tgn:2174526",
        "tgn:1000001",
        "tgn:7012149",
        "tgn:2000491",
        "tgn:7007250",
        "tgn:7029392"
    ],
    "tgn:id":2174526,
    "tgn:name":"Bishop Spring",
    "tgn:placetype":[
        "aat:300008697"
    ]
},
  "bbox": [],
  "geometry": {"coordinates":[-116.2833,47.9667],"type":"Point"}
}