{
  "id": 1030355,
  "type": "Feature",
  "properties": {
    "tgn:hierarchy":[
        "tgn:1030355",
        "tgn:7002445",
        "tgn:7008114",
        "tgn:1000003",
        "tgn:7008591",
        "tgn:7029392"
    ],
    "tgn:id":1030355,
    "tgn:name:en":"Pott Shrigley",
    "tgn:placetype":[
        "aat:300008347"
    ]
},
  "bbox": [],
  "geometry": {"coordinates":[-2.083333,53.316667],"type":"Point"}
}