{
  "id": 2459809,
  "type": "Feature",
  "properties": {
    "tgn:hierarchy":[
        "tgn:2459809",
        "tgn:1000001",
        "tgn:7012149",
        "tgn:2000885",
        "tgn:7007256",
        "tgn:7029392"
    ],
    "tgn:id":2459809,
    "tgn:name":"Little River",
    "tgn:placetype":[
        "aat:300008347"
    ]
},
  "bbox": [],
  "geometry": {"coordinates":[-90.5667,30.5833],"type":"Point"}
}