{
  "id": 7589292,
  "type": "Feature",
  "properties": {
    "tgn:hierarchy":[
        "tgn:7589292",
        "tgn:1000004",
        "tgn:7000198",
        "tgn:7000799",
        "tgn:7029392"
    ],
    "tgn:id":7589292,
    "tgn:name:en":"Qasba L\u0101r",
    "tgn:placetype":[
        "aat:300008347"
    ]
},
  "bbox": [],
  "geometry": {"coordinates":[74.755077,34.257501],"type":"Point"}
}