{
  "id": 2778840,
  "type": "Feature",
  "properties": {
    "tgn:hierarchy":[
        "tgn:2778840",
        "tgn:7002659",
        "tgn:1000001",
        "tgn:2000019",
        "tgn:7012149",
        "tgn:7029392"
    ],
    "tgn:id":2778840,
    "tgn:name":"Wolf Creek",
    "tgn:placetype":[
        "aat:300008706"
    ]
},
  "bbox": [],
  "geometry": {"coordinates":[-86.45,31.4833],"type":"Point"}
}