{
  "id": 2226463,
  "type": "Feature",
  "properties": {
    "tgn:hierarchy":[
        "tgn:2226463",
        "tgn:7006450",
        "tgn:1000001",
        "tgn:7012149",
        "tgn:2124002",
        "tgn:7029392"
    ],
    "tgn:id":2226463,
    "tgn:name":"Catherine Island",
    "tgn:placetype":[
        "aat:300008791"
    ]
},
  "bbox": [],
  "geometry": {"coordinates":[-134.8833,57.3667],"type":"Point"}
}