{
  "id": 7328826,
  "type": "Feature",
  "properties": {
    "tgn:hierarchy":[
        "tgn:7328826",
        "tgn:7002759",
        "tgn:7002845",
        "tgn:1000003",
        "tgn:1000095",
        "tgn:7029392"
    ],
    "tgn:id":7328826,
    "tgn:name":"Pozuelo de Arag\u00f3n",
    "tgn:placetype":[
        "aat:300008347"
    ]
},
  "bbox": [],
  "geometry": {"coordinates":[-1.416667,41.766667],"type":"Point"}
}