{
  "id": 2743463,
  "type": "Feature",
  "properties": {
    "tgn:hierarchy":[
        "tgn:2743463",
        "tgn:1000001",
        "tgn:7012149",
        "tgn:2000425",
        "tgn:7007248",
        "tgn:7029392"
    ],
    "tgn:id":2743463,
    "tgn:name":"Varnadoe Lake",
    "tgn:placetype":[
        "aat:300006191"
    ]
},
  "bbox": [],
  "geometry": {"coordinates":[-82.8333,31.8667],"type":"Point"}
}