{
  "id": 2543304,
  "type": "Feature",
  "properties": {
    "tgn:hierarchy":[
        "tgn:2543304",
        "tgn:1000001",
        "tgn:2000499",
        "tgn:7012149",
        "tgn:7007251",
        "tgn:7029392"
    ],
    "tgn:id":2543304,
    "tgn:name":"Norman Branch",
    "tgn:placetype":[
        "aat:300008699"
    ]
},
  "bbox": [],
  "geometry": {"coordinates":[-87.8333,39.3167],"type":"Point"}
}