{
  "id": 2786691,
  "type": "Feature",
  "properties": {
    "tgn:hierarchy":[
        "tgn:2786691",
        "tgn:1000001",
        "tgn:7012149",
        "tgn:1002685",
        "tgn:7007251",
        "tgn:7029392"
    ],
    "tgn:id":2786691,
    "tgn:name":"Zanesville",
    "tgn:placetype":[
        "aat:300008347"
    ]
},
  "bbox": [],
  "geometry": {"coordinates":[-89.65,39.3167],"type":"Point"}
}