{
  "id": 7138108,
  "type": "Feature",
  "properties": {
    "tgn:hierarchy":[
        "tgn:7138108",
        "tgn:1000003",
        "tgn:7003682",
        "tgn:7000084",
        "tgn:7029392"
    ],
    "tgn:id":7138108,
    "tgn:name":"Langheck",
    "tgn:placetype":[
        "aat:300008863"
    ]
},
  "bbox": [],
  "geometry": {"coordinates":[7.066667,50.333333],"type":"Point"}
}