{
  "id": 7426770,
  "type": "Feature",
  "properties": {
    "tgn:hierarchy":[
        "tgn:7426770",
        "tgn:1000001",
        "tgn:7005594",
        "tgn:7005560",
        "tgn:7029392"
    ],
    "tgn:id":7426770,
    "tgn:name":"Mexiquito",
    "tgn:placetype":[
        "aat:300008347"
    ]
},
  "bbox": [],
  "geometry": {"coordinates":[-101.05,22.916667],"type":"Point"}
}