{
  "id": 1088665,
  "type": "Feature",
  "properties": {
    "tgn:hierarchy":[
        "tgn:1088665",
        "tgn:7001242",
        "tgn:1001022",
        "tgn:1000158",
        "tgn:7029392"
    ],
    "tgn:id":1088665,
    "tgn:name":"L\u00e9kana",
    "tgn:placetype":[
        "aat:300008347"
    ]
},
  "bbox": [],
  "geometry": {"coordinates":[14.5833,-2.3167],"type":"Point"}
}