{
  "id": 2128995,
  "type": "Feature",
  "properties": {
    "tgn:hierarchy":[
        "tgn:2128995",
        "tgn:1000001",
        "tgn:2002318",
        "tgn:7012149",
        "tgn:7007922",
        "tgn:7029392"
    ],
    "tgn:id":2128995,
    "tgn:name":"Alexander Lake",
    "tgn:placetype":[
        "aat:300008680"
    ]
},
  "bbox": [],
  "geometry": {"coordinates":[-91.6667,46.2167],"type":"Point"}
}