<<<<<<< HEAD
{
  "id": 2769865,
  "type": "Feature",
  "properties": {
    "tgn:hierarchy":[
        "tgn:2769865",
        "tgn:1000001",
        "tgn:7016172",
        "tgn:7012149",
        "tgn:2000160",
        "tgn:7029392"
    ],
    "tgn:id":2769865,
    "tgn:name":"Wilbeth",
    "tgn:placetype":[
        "aat:300008347"
    ]
},
  "bbox": [],
  "geometry": {"coordinates":[-90.3333,35.5333],"type":"Point"}
}
=======
{"geometry":{"type":"Point","coordinates":[-90.333300,35.533300]},"type":"Feature","properties":{"hierarchy":["tgn:2769865","tgn:1000001","tgn:7016172","tgn:7012149","tgn:2000160","tgn:7029392"],"placetype":["aat:300008347"],"id":2769865,"name:xx":"Wilbeth"}}
>>>>>>> 03f74aca74312dbeaf24d7e61306dd6a786dc3d0
