{
  "id": 2133280,
  "type": "Feature",
  "properties": {
    "tgn:hierarchy":[
        "tgn:2133280",
        "tgn:1000001",
        "tgn:7012149",
        "tgn:2000493",
        "tgn:7007250",
        "tgn:7029392"
    ],
    "tgn:id":2133280,
    "tgn:name":"Anderson Place",
    "tgn:placetype":[
        "aat:300008347"
    ]
},
  "bbox": [],
  "geometry": {"coordinates":[-114.95,42.2333],"type":"Point"}
}