{
  "id": 2746258,
  "type": "Feature",
  "properties": {
    "tgn:hierarchy":[
        "tgn:2746258",
        "tgn:7006450",
        "tgn:1000001",
        "tgn:2000071",
        "tgn:7012149",
        "tgn:7029392"
    ],
    "tgn:id":2746258,
    "tgn:name":"Vukpalik Creek",
    "tgn:placetype":[
        "aat:300008706"
    ]
},
  "bbox": [],
  "geometry": {"coordinates":[-156.8667,60.3167],"type":"Point"}
}