{
  "id": 7244973,
  "type": "Feature",
  "properties": {
    "tgn:hierarchy":[
        "tgn:7244973",
        "tgn:7003458",
        "tgn:1000003",
        "tgn:1000063",
        "tgn:7018236",
        "tgn:7029392"
    ],
    "tgn:id":7244973,
    "tgn:name":"Avekapelle",
    "tgn:placetype":[
        "aat:300008347"
    ]
},
  "bbox": [],
  "geometry": {"coordinates":[2.732678,51.066231],"type":"Point"}
}