{
  "id": 7292857,
  "type": "Feature",
  "properties": {
    "tgn:hierarchy":[
        "tgn:7292857",
        "tgn:1001768",
        "tgn:1000049",
        "tgn:1000002",
        "tgn:7029392"
    ],
    "tgn:id":7292857,
    "tgn:name":"El Molle, Quebrada",
    "tgn:placetype":[
        "aat:300266554",
        "aat:300008699"
    ]
},
  "bbox": [],
  "geometry": {"coordinates":[-70.533333,-32.95],"type":"Point"}
}