{
  "id": 7046717,
  "type": "Feature",
  "properties": {
    "tgn:hierarchy":[
        "tgn:7046717",
        "tgn:1003440",
        "tgn:1000003",
        "tgn:7003124",
        "tgn:1000080",
        "tgn:7029392"
    ],
    "tgn:id":7046717,
    "tgn:name":"Collepietra",
    "tgn:placetype":[
        "aat:300008347"
    ]
},
  "bbox": [],
  "geometry": {"coordinates":[11.45,46.483333],"type":"Point"}
}