{
  "id": 7047228,
  "type": "Feature",
  "properties": {
    "tgn:hierarchy":[
        "tgn:7047228",
        "tgn:1003506",
        "tgn:1000003",
        "tgn:7002993",
        "tgn:1000080",
        "tgn:7029392"
    ],
    "tgn:id":7047228,
    "tgn:name":"Cleuis",
    "tgn:placetype":[
        "aat:300008347"
    ]
},
  "bbox": [],
  "geometry": {"coordinates":[12.999722,46.560556],"type":"Point"}
}