{
  "id": 7039769,
  "type": "Feature",
  "properties": {
    "tgn:hierarchy":[
        "tgn:7039769",
        "tgn:1001641",
        "tgn:1000003",
        "tgn:7003121",
        "tgn:1000080",
        "tgn:7029392"
    ],
    "tgn:id":7039769,
    "tgn:name":"Serpentara, \u00ccsola",
    "tgn:placetype":[
        "aat:300008791"
    ]
},
  "bbox": [],
  "geometry": {"coordinates":[9.606944,39.139444],"type":"Point"}
}