<<<<<<< HEAD
{
  "id": 7368182,
  "type": "Feature",
  "properties": {
    "tgn:hierarchy":[
        "tgn:7368182",
        "tgn:1000001",
        "tgn:7005597",
        "tgn:7005560",
        "tgn:7029392"
    ],
    "tgn:id":7368182,
    "tgn:name":"Ignacio Zaragoza",
    "tgn:placetype":[
        "aat:300008347"
    ]
},
  "bbox": [],
  "geometry": {"coordinates":[-98.783333,23.183333],"type":"Point"}
}
=======
{"geometry":{"type":"Point","coordinates":[-98.783333,23.183333]},"type":"Feature","properties":{"hierarchy":["tgn:7368182","tgn:1000001","tgn:7005597","tgn:7005560","tgn:7029392"],"placetype":["aat:300008347"],"id":7368182,"name:xx":"Ignacio Zaragoza"}}
>>>>>>> 03f74aca74312dbeaf24d7e61306dd6a786dc3d0
