{
  "id": 7286718,
  "type": "Feature",
  "properties": {
    "tgn:hierarchy":[
        "tgn:7286718",
        "tgn:1001702",
        "tgn:1000049",
        "tgn:1000002",
        "tgn:7029392"
    ],
    "tgn:id":7286718,
    "tgn:name":"Guard, Bah\u00eda",
    "tgn:placetype":[
        "aat:300132316"
    ]
},
  "bbox": [],
  "geometry": {"coordinates":[-74.683333,-50.583333],"type":"Point"}
}