{
  "id": 2311307,
  "type": "Feature",
  "properties": {
    "tgn:hierarchy":[
        "tgn:2311307",
        "tgn:1000001",
        "tgn:7012149",
        "tgn:1002426",
        "tgn:7007255",
        "tgn:7029392"
    ],
    "tgn:id":2311307,
    "tgn:name":"Edgington",
    "tgn:placetype":[
        "aat:300008347"
    ]
},
  "bbox": [],
  "geometry": {"coordinates":[-82.8667,38.6667],"type":"Point"}
}