<<<<<<< HEAD
{
  "id": 7117523,
  "type": "Feature",
  "properties": {
    "tgn:hierarchy":[
        "tgn:7117523",
        "tgn:1000003",
        "tgn:7003677",
        "tgn:7000084",
        "tgn:7029392"
    ],
    "tgn:id":7117523,
    "tgn:name":"Osthus",
    "tgn:placetype":[
        "aat:300000206"
    ]
},
  "bbox": [],
  "geometry": {"coordinates":[8.5,51.95],"type":"Point"}
}
=======
{"geometry":{"type":"Point","coordinates":[8.500000,51.950000]},"type":"Feature","properties":{"hierarchy":["tgn:7117523","tgn:1000003","tgn:7003677","tgn:7000084","tgn:7029392"],"placetype":["aat:300000206"],"id":7117523,"name:xx":"Osthus"}}
>>>>>>> 03f74aca74312dbeaf24d7e61306dd6a786dc3d0
