<<<<<<< HEAD
{
  "id": 2332086,
  "type": "Feature",
  "properties": {
    "tgn:hierarchy":[
        "tgn:2332086",
        "tgn:1000001",
        "tgn:7012149",
        "tgn:2001770",
        "tgn:7007712",
        "tgn:7029392"
    ],
    "tgn:id":2332086,
    "tgn:name":"Flint Hill",
    "tgn:placetype":[
        "aat:300008347"
    ]
},
  "bbox": [],
  "geometry": {"coordinates":[-81.0333,34.9],"type":"Point"}
}
=======
{"geometry":{"type":"Point","coordinates":[-81.033300,34.900000]},"type":"Feature","properties":{"hierarchy":["tgn:2332086","tgn:1000001","tgn:7012149","tgn:2001770","tgn:7007712","tgn:7029392"],"placetype":["aat:300008347"],"id":2332086,"name:xx":"Flint Hill"}}
>>>>>>> 03f74aca74312dbeaf24d7e61306dd6a786dc3d0
