{
  "id": 2616868,
  "type": "Feature",
  "properties": {
    "tgn:hierarchy":[
        "tgn:2616868",
        "tgn:1000001",
        "tgn:2000920",
        "tgn:7012149",
        "tgn:7007515",
        "tgn:7029392"
    ],
    "tgn:id":2616868,
    "tgn:name":"Rich Mill Pond",
    "tgn:placetype":[
        "aat:300008680"
    ]
},
  "bbox": [],
  "geometry": {"coordinates":[-70.5667,43.7833],"type":"Point"}
}