{
  "id": 7569826,
  "type": "Feature",
  "properties": {
    "tgn:hierarchy":[
        "tgn:7569826",
        "tgn:1000004",
        "tgn:7000198",
        "tgn:7016788",
        "tgn:7029392"
    ],
    "tgn:id":7569826,
    "tgn:name:en":"Say\u0101na",
    "tgn:placetype":[
        "aat:300008347"
    ]
},
  "bbox": [],
  "geometry": {"coordinates":[75.667321,25.551575],"type":"Point"}
}