{
  "id": 2740161,
  "type": "Feature",
  "properties": {
    "tgn:hierarchy":[
        "tgn:2740161",
        "tgn:1000001",
        "tgn:7012149",
        "tgn:2002341",
        "tgn:7007922",
        "tgn:7029392"
    ],
    "tgn:id":2740161,
    "tgn:name":"Upper Island Lake",
    "tgn:placetype":[
        "aat:300008680"
    ]
},
  "bbox": [],
  "geometry": {"coordinates":[-88.55,45.25],"type":"Point"}
}