{
  "id": 2680134,
  "type": "Feature",
  "properties": {
    "tgn:hierarchy":[
        "tgn:2680134",
        "tgn:1000001",
        "tgn:7012149",
        "tgn:2000487",
        "tgn:7007250",
        "tgn:7029392"
    ],
    "tgn:id":2680134,
    "tgn:name":"South Fork Sublette Canyon",
    "tgn:placetype":[
        "aat:300008761"
    ]
},
  "bbox": [],
  "geometry": {"coordinates":[-112.5167,42.2667],"type":"Point"}
}