{
  "id": 2297509,
  "type": "Feature",
  "properties": {
    "tgn:hierarchy":[
        "tgn:2297509",
        "tgn:1000001",
        "tgn:7012149",
        "tgn:2002295",
        "tgn:7013961",
        "tgn:7029392"
    ],
    "tgn:id":2297509,
    "tgn:name":"Dry Fork",
    "tgn:placetype":[
        "aat:300008699"
    ]
},
  "bbox": [],
  "geometry": {"coordinates":[-80.0833,39.3833],"type":"Point"}
}