{
  "id": 2430884,
  "type": "Feature",
  "properties": {
    "tgn:hierarchy":[
        "tgn:2430884",
        "tgn:7030516",
        "tgn:7006450",
        "tgn:1000001",
        "tgn:7012149",
        "tgn:7029392"
    ],
    "tgn:id":2430884,
    "tgn:name":"Kanaga Volcano",
    "tgn:placetype":[
        "aat:300008798"
    ]
},
  "bbox": [],
  "geometry": {"coordinates":[-177.15,51.9167],"type":"Point"}
}