{
  "id": 1024445,
  "type": "Feature",
  "properties": {
    "tgn:hierarchy":[
        "tgn:1024445",
        "tgn:1000665",
        "tgn:1000002",
        "tgn:1000056",
        "tgn:7029392"
    ],
    "tgn:id":1024445,
    "tgn:name":"Chiclayo",
    "tgn:placetype":[
        "aat:300008347",
        "aat:300008389",
        "aat:300387512",
        "aat:300387220",
        "aat:300387270",
        "aat:300387285"
    ]
},
  "bbox": [],
  "geometry": {"coordinates":[-79.85,-6.7667],"type":"Point"}
}