{
  "id": 1114179,
  "type": "Feature",
  "properties": {
    "tgn:hierarchy":[
        "tgn:1114179",
        "tgn:7000528",
        "tgn:7000529",
        "tgn:1000006",
        "tgn:7029392"
    ],
    "tgn:id":1114179,
    "tgn:name":"Lahi, Ava",
    "tgn:placetype":[
        "aat:300008713"
    ]
},
  "bbox": [],
  "geometry": {"coordinates":[-175.1833,-21.0333],"type":"Point"}
}