{
  "id": 2076189,
  "type": "Feature",
  "properties": {
    "tgn:hierarchy":[
        "tgn:2076189",
        "tgn:1000001",
        "tgn:7012149",
        "tgn:1002403",
        "tgn:7007709",
        "tgn:7029392"
    ],
    "tgn:id":2076189,
    "tgn:name":"Powell Crossroads",
    "tgn:placetype":[
        "aat:300008347",
        "aat:300387210"
    ]
},
  "bbox": [],
  "geometry": {"coordinates":[-76.65,36.3333],"type":"Point"}
}