{
  "id": 2205209,
  "type": "Feature",
  "properties": {
    "tgn:hierarchy":[
        "tgn:2205209",
        "tgn:1000001",
        "tgn:7012149",
        "tgn:7007709",
        "tgn:7029392"
    ],
    "tgn:id":2205209,
    "tgn:name":"Bull Bay",
    "tgn:placetype":[
        "aat:300132316"
    ]
},
  "bbox": [],
  "geometry": {"coordinates":[-76.3333,35.9333],"type":"Point"}
}