{
  "id": 2549676,
  "type": "Feature",
  "properties": {
    "tgn:hierarchy":[
        "tgn:2549676",
        "tgn:1000001",
        "tgn:7012149",
        "tgn:2000929",
        "tgn:7007515",
        "tgn:7029392"
    ],
    "tgn:id":2549676,
    "tgn:name":"North Sugarloaf Island",
    "tgn:placetype":[
        "aat:300008791"
    ]
},
  "bbox": [],
  "geometry": {"coordinates":[-69.7667,43.75],"type":"Point"}
}