<<<<<<< HEAD
{
  "id": 7353310,
  "type": "Feature",
  "properties": {
    "tgn:hierarchy":[
        "tgn:7353310",
        "tgn:7005585",
        "tgn:1000001",
        "tgn:7005560",
        "tgn:7029392"
    ],
    "tgn:id":7353310,
    "tgn:name":"Axoxuca",
    "tgn:placetype":[
        "aat:300008347"
    ]
},
  "bbox": [],
  "geometry": {"coordinates":[-98.633333,17.533333],"type":"Point"}
}
=======
{"geometry":{"type":"Point","coordinates":[-98.633333,17.533333]},"type":"Feature","properties":{"hierarchy":["tgn:7353310","tgn:7005585","tgn:1000001","tgn:7005560","tgn:7029392"],"placetype":["aat:300008347"],"id":7353310,"name:xx":"Axoxuca"}}
>>>>>>> 03f74aca74312dbeaf24d7e61306dd6a786dc3d0
