{
  "id": 2523102,
  "type": "Feature",
  "properties": {
    "tgn:hierarchy":[
        "tgn:2523102",
        "tgn:7002659",
        "tgn:1000001",
        "tgn:7012149",
        "tgn:2000060",
        "tgn:7029392"
    ],
    "tgn:id":2523102,
    "tgn:name":"Moorefield",
    "tgn:placetype":[
        "aat:300008347"
    ]
},
  "bbox": [],
  "geometry": {"coordinates":[-86.0833,33.4167],"type":"Point"}
}