{
  "id": 7019179,
  "type": "Feature",
  "properties": {
    "tgn:hierarchy":[
        "tgn:7019179",
        "tgn:1000001",
        "tgn:7012149",
        "tgn:7007253",
        "tgn:7029392"
    ],
    "tgn:id":7019179,
    "tgn:name":"Decatur",
    "tgn:placetype":[
        "aat:300387145",
        "aat:300000771"
    ]
},
  "bbox": [],
  "geometry": {"coordinates":[-93.7833,40.75],"type":"Point"}
}