<<<<<<< HEAD
{
  "id": 7057657,
  "type": "Feature",
  "properties": {
    "tgn:hierarchy":[
        "tgn:7057657",
        "tgn:7002991",
        "tgn:1000003",
        "tgn:7002997",
        "tgn:1000080",
        "tgn:7029392"
    ],
    "tgn:id":7057657,
    "tgn:name":"Arsiera",
    "tgn:placetype":[
        "aat:300008347"
    ]
},
  "bbox": [],
  "geometry": {"coordinates":[12.2275,46.373333],"type":"Point"}
}
=======
{"geometry":{"type":"Point","coordinates":[12.227500,46.373333]},"type":"Feature","properties":{"hierarchy":["tgn:7057657","tgn:7002991","tgn:1000003","tgn:7002997","tgn:1000080","tgn:7029392"],"placetype":["aat:300008347"],"id":7057657,"name:xx":"Arsiera"}}
>>>>>>> 03f74aca74312dbeaf24d7e61306dd6a786dc3d0
