<<<<<<< HEAD
{
  "id": 2407414,
  "type": "Feature",
  "properties": {
    "tgn:hierarchy":[
        "tgn:2407414",
        "tgn:1000001",
        "tgn:2001267",
        "tgn:7012149",
        "tgn:7007524",
        "tgn:7029392"
    ],
    "tgn:id":2407414,
    "tgn:name":"Huntley Coulee",
    "tgn:placetype":[
        "aat:300008761"
    ]
},
  "bbox": [],
  "geometry": {"coordinates":[-111.2167,47.7],"type":"Point"}
}
=======
{"geometry":{"type":"Point","coordinates":[-111.216700,47.700000]},"type":"Feature","properties":{"hierarchy":["tgn:2407414","tgn:1000001","tgn:2001267","tgn:7012149","tgn:7007524","tgn:7029392"],"placetype":["aat:300008761"],"id":2407414,"name:xx":"Huntley Coulee"}}
>>>>>>> 03f74aca74312dbeaf24d7e61306dd6a786dc3d0
