{
  "id": 2204628,
  "type": "Feature",
  "properties": {
    "tgn:hierarchy":[
        "tgn:2204628",
        "tgn:1000001",
        "tgn:7012149",
        "tgn:1002787",
        "tgn:7007523",
        "tgn:7029392"
    ],
    "tgn:id":2204628,
    "tgn:name":"Buffalo Knob",
    "tgn:placetype":[
        "aat:300008798"
    ]
},
  "bbox": [],
  "geometry": {"coordinates":[-91.05,39.2667],"type":"Point"}
}