{
  "id": 7242620,
  "type": "Feature",
  "properties": {
    "tgn:hierarchy":[
        "tgn:7242620",
        "tgn:7003460",
        "tgn:1000003",
        "tgn:1000063",
        "tgn:4012014",
        "tgn:7029392"
    ],
    "tgn:id":7242620,
    "tgn:name":"Lanaye",
    "tgn:placetype":[
        "aat:300008347"
    ]
},
  "bbox": [],
  "geometry": {"coordinates":[5.683333,50.783333],"type":"Point"}
}