{
  "id": 2620434,
  "type": "Feature",
  "properties": {
    "tgn:hierarchy":[
        "tgn:2620434",
        "tgn:1002149",
        "tgn:1000001",
        "tgn:7012149",
        "tgn:7007826",
        "tgn:7029392"
    ],
    "tgn:id":2620434,
    "tgn:name":"River Ridge",
    "tgn:placetype":[
        "aat:300266640"
    ]
},
  "bbox": [],
  "geometry": {"coordinates":[-94.1167,31.0167],"type":"Point"}
}