{
  "id": 7418452,
  "type": "Feature",
  "properties": {
    "tgn:hierarchy":[
        "tgn:7418452",
        "tgn:7005584",
        "tgn:1000001",
        "tgn:7005560",
        "tgn:7029392"
    ],
    "tgn:id":7418452,
    "tgn:name":"Tierra Blanca",
    "tgn:placetype":[
        "aat:300008347"
    ]
},
  "bbox": [],
  "geometry": {"coordinates":[-100.750278,21.046667],"type":"Point"}
}