{
  "id": 7072026,
  "type": "Feature",
  "properties": {
    "tgn:hierarchy":[
        "tgn:7072026",
        "tgn:7003669",
        "tgn:1000003",
        "tgn:7000084",
        "tgn:7029392"
    ],
    "tgn:id":7072026,
    "tgn:name":"Sulzthal",
    "tgn:placetype":[
        "aat:300008347"
    ]
},
  "bbox": [],
  "geometry": {"coordinates":[10.033333,50.133333],"type":"Point"}
}