{
  "id": 2287347,
  "type": "Feature",
  "properties": {
    "tgn:hierarchy":[
        "tgn:2287347",
        "tgn:1000001",
        "tgn:7012149",
        "tgn:1002599",
        "tgn:7007708",
        "tgn:7029392"
    ],
    "tgn:id":2287347,
    "tgn:name":"Dicks Ridge",
    "tgn:placetype":[
        "aat:300266640"
    ]
},
  "bbox": [],
  "geometry": {"coordinates":[-124.05,44.35],"type":"Point"}
}