<<<<<<< HEAD
{
  "id": 2336560,
  "type": "Feature",
  "properties": {
    "tgn:hierarchy":[
        "tgn:2336560",
        "tgn:1000001",
        "tgn:7012149",
        "tgn:2001716",
        "tgn:7007708",
        "tgn:7029392"
    ],
    "tgn:id":2336560,
    "tgn:name":"Four In One Cone",
    "tgn:placetype":[
        "aat:300008798"
    ]
},
  "bbox": [],
  "geometry": {"coordinates":[-121.8,44.2],"type":"Point"}
}
=======
{"geometry":{"type":"Point","coordinates":[-121.800000,44.200000]},"type":"Feature","properties":{"hierarchy":["tgn:2336560","tgn:1000001","tgn:7012149","tgn:2001716","tgn:7007708","tgn:7029392"],"placetype":["aat:300008798"],"id":2336560,"name:xx":"Four In One Cone"}}
>>>>>>> 03f74aca74312dbeaf24d7e61306dd6a786dc3d0
