{
  "id": 2577034,
  "type": "Feature",
  "properties": {
    "tgn:hierarchy":[
        "tgn:2577034",
        "tgn:2000768",
        "tgn:1000001",
        "tgn:7012149",
        "tgn:7007255",
        "tgn:7029392"
    ],
    "tgn:id":2577034,
    "tgn:name":"Peter Creek",
    "tgn:placetype":[
        "aat:300008347"
    ]
},
  "bbox": [],
  "geometry": {"coordinates":[-85.9667,36.8333],"type":"Point"}
}