{
  "id": 2314743,
  "type": "Feature",
  "properties": {
    "tgn:hierarchy":[
        "tgn:2314743",
        "tgn:1000001",
        "tgn:7012149",
        "tgn:2001706",
        "tgn:7007708",
        "tgn:7029392"
    ],
    "tgn:id":2314743,
    "tgn:name":"Elk Valley",
    "tgn:placetype":[
        "aat:300008761"
    ]
},
  "bbox": [],
  "geometry": {"coordinates":[-123.6833,42.8833],"type":"Point"}
}