{
  "id": 7236179,
  "type": "Feature",
  "properties": {
    "tgn:hierarchy":[
        "tgn:7236179",
        "tgn:7002752",
        "tgn:7001399",
        "tgn:1000003",
        "tgn:1000074",
        "tgn:7029392"
    ],
    "tgn:id":7236179,
    "tgn:name":"\u00c1gios ton Mete\u00f3ron",
    "tgn:placetype":[
        "aat:300000641"
    ]
},
  "bbox": [],
  "geometry": {"coordinates":[21.633333,39.716667],"type":"Point"}
}