{
  "id": 7039280,
  "type": "Feature",
  "properties": {
    "tgn:hierarchy":[
        "tgn:7039280",
        "tgn:1003505",
        "tgn:1000003",
        "tgn:7002993",
        "tgn:1000080",
        "tgn:7029392"
    ],
    "tgn:id":7039280,
    "tgn:name":"Sottile, Punta",
    "tgn:placetype":[
        "aat:300386846"
    ]
},
  "bbox": [],
  "geometry": {"coordinates":[13.720556,45.604444],"type":"Point"}
}