{
  "id": 7533405,
  "type": "Feature",
  "properties": {
    "tgn:hierarchy":[
        "tgn:7533405",
        "tgn:7001242",
        "tgn:7001311",
        "tgn:7016833",
        "tgn:7029392"
    ],
    "tgn:id":7533405,
    "tgn:name:en":"\u1e28amal, Raw\u1e11 al",
    "tgn:placetype":[
        "aat:300008761"
    ]
},
  "bbox": [],
  "geometry": {"coordinates":[32.454371,29.160265],"type":"Point"}
}