{
  "id": 7561261,
  "type": "Feature",
  "properties": {
    "tgn:hierarchy":[
        "tgn:7561261",
        "tgn:1000004",
        "tgn:7000198",
        "tgn:7016722",
        "tgn:7029392"
    ],
    "tgn:id":7561261,
    "tgn:name:en":"Shimbhu Nagla",
    "tgn:placetype":[
        "aat:300008347"
    ]
},
  "bbox": [],
  "geometry": {"coordinates":[79.403352,27.998751],"type":"Point"}
}