{
  "id": 2203098,
  "type": "Feature",
  "properties": {
    "tgn:hierarchy":[
        "tgn:2203098",
        "tgn:1000001",
        "tgn:7012149",
        "tgn:1003038",
        "tgn:7007517",
        "tgn:7029392"
    ],
    "tgn:id":2203098,
    "tgn:name":"Buckhill Pond",
    "tgn:placetype":[
        "aat:300006191"
    ]
},
  "bbox": [],
  "geometry": {"coordinates":[-71.9833,42.2833],"type":"Point"}
}