{
  "id": 2728802,
  "type": "Feature",
  "properties": {
    "tgn:hierarchy":[
        "tgn:2728802",
        "tgn:1000001",
        "tgn:7016172",
        "tgn:2000111",
        "tgn:7012149",
        "tgn:7029392"
    ],
    "tgn:id":2728802,
    "tgn:name":"Tri-County Lake",
    "tgn:placetype":[
        "aat:300006191"
    ]
},
  "bbox": [],
  "geometry": {"coordinates":[-92.35,33.7667],"type":"Point"}
}