{
  "id": 2727566,
  "type": "Feature",
  "properties": {
    "tgn:hierarchy":[
        "tgn:2727566",
        "tgn:1000001",
        "tgn:7012149",
        "tgn:7007157",
        "tgn:1002608",
        "tgn:7029392"
    ],
    "tgn:id":2727566,
    "tgn:name":"Trail Fork",
    "tgn:placetype":[
        "aat:300008699"
    ]
},
  "bbox": [],
  "geometry": {"coordinates":[-118.0667,34.2667],"type":"Point"}
}