{
  "id": 7033166,
  "type": "Feature",
  "properties": {
    "tgn:hierarchy":[
        "tgn:7033166",
        "tgn:1003506",
        "tgn:1000003",
        "tgn:7002993",
        "tgn:1000080",
        "tgn:7029392"
    ],
    "tgn:id":7033166,
    "tgn:name":"Pertegada",
    "tgn:placetype":[
        "aat:300008347"
    ]
},
  "bbox": [],
  "geometry": {"coordinates":[13.047778,45.722222],"type":"Point"}
}