{
  "id": 2292729,
  "type": "Feature",
  "properties": {
    "tgn:hierarchy":[
        "tgn:2292729",
        "tgn:1000001",
        "tgn:7012149",
        "tgn:2001136",
        "tgn:7007522",
        "tgn:7029392"
    ],
    "tgn:id":2292729,
    "tgn:name":"Dorman Branch",
    "tgn:placetype":[
        "aat:300008699"
    ]
},
  "bbox": [],
  "geometry": {"coordinates":[-89.0167,32.55],"type":"Point"}
}