{
  "id": 2247163,
  "type": "Feature",
  "properties": {
    "tgn:hierarchy":[
        "tgn:2247163",
        "tgn:1000001",
        "tgn:7012149",
        "tgn:1002411",
        "tgn:7007919",
        "tgn:7029392"
    ],
    "tgn:id":2247163,
    "tgn:name":"Cod Point",
    "tgn:placetype":[
        "aat:300008850"
    ]
},
  "bbox": [],
  "geometry": {"coordinates":[-76.45,37.3167],"type":"Point"}
}