{
  "id": 7333107,
  "type": "Feature",
  "properties": {
    "tgn:hierarchy":[
        "tgn:7333107",
        "tgn:7002759",
        "tgn:7008909",
        "tgn:1000003",
        "tgn:1000095",
        "tgn:7029392"
    ],
    "tgn:id":7333107,
    "tgn:name":"Lamata",
    "tgn:placetype":[
        "aat:300008347"
    ]
},
  "bbox": [],
  "geometry": {"coordinates":[0.177299,42.278903],"type":"Point"}
}