{
  "id": 7575720,
  "type": "Feature",
  "properties": {
    "tgn:hierarchy":[
        "tgn:7575720",
        "tgn:1000004",
        "tgn:1001871",
        "tgn:7000198",
        "tgn:7029392"
    ],
    "tgn:id":7575720,
    "tgn:name:en":"Kanhri",
    "tgn:placetype":[
        "aat:300008347"
    ]
},
  "bbox": [],
  "geometry": {"coordinates":[75.931768,29.674395],"type":"Point"}
}