{
  "id": 7386108,
  "type": "Feature",
  "properties": {
    "tgn:hierarchy":[
        "tgn:7386108",
        "tgn:7005586",
        "tgn:1000001",
        "tgn:7005560",
        "tgn:7029392"
    ],
    "tgn:id":7386108,
    "tgn:name":"Pitallal del Sur",
    "tgn:placetype":[
        "aat:300008347"
    ]
},
  "bbox": [],
  "geometry": {"coordinates":[-105.25,20.65],"type":"Point"}
}