{
  "id": 7440710,
  "type": "Feature",
  "properties": {
    "tgn:hierarchy":[
        "tgn:7440710",
        "tgn:7005583",
        "tgn:1000001",
        "tgn:7005560",
        "tgn:7029392"
    ],
    "tgn:id":7440710,
    "tgn:name":"Santa B\u00e1rbara",
    "tgn:placetype":[
        "aat:300008347"
    ]
},
  "bbox": [],
  "geometry": {"coordinates":[-104.566667,25.233333],"type":"Point"}
}