{
  "id": 2152670,
  "type": "Feature",
  "properties": {
    "tgn:hierarchy":[
        "tgn:2152670",
        "tgn:1000001",
        "tgn:2001331",
        "tgn:7012149",
        "tgn:7007525",
        "tgn:7029392"
    ],
    "tgn:id":2152670,
    "tgn:name":"Bayonne",
    "tgn:placetype":[
        "aat:300008347"
    ]
},
  "bbox": [],
  "geometry": {"coordinates":[-101.9667,42.7833],"type":"Point"}
}