{
  "id": 7059971,
  "type": "Feature",
  "properties": {
    "tgn:hierarchy":[
        "tgn:7059971",
        "tgn:1000003",
        "tgn:7003677",
        "tgn:7000084",
        "tgn:7029392"
    ],
    "tgn:id":7059971,
    "tgn:name":"Altenh\u00f6he",
    "tgn:placetype":[
        "aat:300008347"
    ]
},
  "bbox": [],
  "geometry": {"coordinates":[7.233333,51.133333],"type":"Point"}
}