<<<<<<< HEAD
{
  "id": 7059971,
  "type": "Feature",
  "properties": {
    "tgn:hierarchy":[
        "tgn:7059971",
        "tgn:1000003",
        "tgn:7003677",
        "tgn:7000084",
        "tgn:7029392"
    ],
    "tgn:id":7059971,
    "tgn:name":"Altenh\u00f6he",
    "tgn:placetype":[
        "aat:300008347"
    ]
},
  "bbox": [],
  "geometry": {"coordinates":[7.233333,51.133333],"type":"Point"}
}
=======
{"geometry":{"type":"Point","coordinates":[7.233333,51.133333]},"type":"Feature","properties":{"hierarchy":["tgn:7059971","tgn:1000003","tgn:7003677","tgn:7000084","tgn:7029392"],"placetype":["aat:300008347"],"id":7059971,"name:xx":"Altenh\u00f6he"}}
>>>>>>> 03f74aca74312dbeaf24d7e61306dd6a786dc3d0
