{
  "id": 2750015,
  "type": "Feature",
  "properties": {
    "tgn:hierarchy":[
        "tgn:2750015",
        "tgn:1000001",
        "tgn:7012149",
        "tgn:2001461",
        "tgn:7007568",
        "tgn:7029392"
    ],
    "tgn:id":2750015,
    "tgn:name":"Walter Coon Brook",
    "tgn:placetype":[
        "aat:300008699"
    ]
},
  "bbox": [],
  "geometry": {"coordinates":[-73.9667,43.9833],"type":"Point"}
}