{
  "id": 7009134,
  "type": "Feature",
  "properties": {
    "tgn:hierarchy":[
        "tgn:7009134",
        "tgn:1000003",
        "tgn:7002883",
        "tgn:1000070",
        "tgn:7029392"
    ],
    "tgn:id":7009134,
    "tgn:name":"Dammarie-l\u00e8s-Lys",
    "tgn:placetype":[
        "aat:300008347"
    ]
},
  "bbox": [],
  "geometry": {"coordinates":[2.65,48.5167],"type":"Point"}
}