{
  "id": 1028453,
  "type": "Feature",
  "properties": {
    "tgn:hierarchy":[
        "tgn:1028453",
        "tgn:7002445",
        "tgn:1000003",
        "tgn:7008165",
        "tgn:7008591",
        "tgn:7029392"
    ],
    "tgn:id":1028453,
    "tgn:name:en":"Bellingham",
    "tgn:placetype":[
        "aat:300008347"
    ]
},
  "bbox": [],
  "geometry": {"coordinates":[-2.233333,55.15],"type":"Point"}
}