{
  "id": 2728759,
  "type": "Feature",
  "properties": {
    "tgn:hierarchy":[
        "tgn:2728759",
        "tgn:1000001",
        "tgn:1002262",
        "tgn:7012149",
        "tgn:7007568",
        "tgn:7029392"
    ],
    "tgn:id":2728759,
    "tgn:name":"Trestle Lake",
    "tgn:placetype":[
        "aat:300006191"
    ]
},
  "bbox": [],
  "geometry": {"coordinates":[-75.5667,42.4167],"type":"Point"}
}