{
  "id": 7355882,
  "type": "Feature",
  "properties": {
    "tgn:hierarchy":[
        "tgn:7355882",
        "tgn:7005581",
        "tgn:1000001",
        "tgn:7005560",
        "tgn:7029392"
    ],
    "tgn:id":7355882,
    "tgn:name":"Chicorimpa",
    "tgn:placetype":[
        "aat:300008347"
    ]
},
  "bbox": [],
  "geometry": {"coordinates":[-106.683333,25.616667],"type":"Point"}
}