{
  "id": 2305877,
  "type": "Feature",
  "properties": {
    "tgn:hierarchy":[
        "tgn:2305877",
        "tgn:1000001",
        "tgn:7012149",
        "tgn:7007157",
        "tgn:1002828",
        "tgn:7029392"
    ],
    "tgn:id":2305877,
    "tgn:name":"East Double Canyon",
    "tgn:placetype":[
        "aat:300008761"
    ]
},
  "bbox": [],
  "geometry": {"coordinates":[-116.0333,33.7333],"type":"Point"}
}