{
  "id": 1094439,
  "type": "Feature",
  "properties": {
    "tgn:hierarchy":[
        "tgn:1094439",
        "tgn:7001242",
        "tgn:1000201",
        "tgn:1001213",
        "tgn:7029392"
    ],
    "tgn:id":1094439,
    "tgn:name":"Shibarni",
    "tgn:placetype":[
        "aat:300008347"
    ]
},
  "bbox": [],
  "geometry": {"coordinates":[24.4167,14.8333],"type":"Point"}
}