{
  "id": 7589451,
  "type": "Feature",
  "properties": {
    "tgn:hierarchy":[
        "tgn:7589451",
        "tgn:1000004",
        "tgn:7000198",
        "tgn:7000799",
        "tgn:7029392"
    ],
    "tgn:id":7589451,
    "tgn:name:en":"Phera na Kot",
    "tgn:placetype":[
        "aat:300008347"
    ]
},
  "bbox": [],
  "geometry": {"coordinates":[74.388889,33.165278],"type":"Point"}
}