<<<<<<< HEAD
{
  "id": 2259158,
  "type": "Feature",
  "properties": {
    "tgn:hierarchy":[
        "tgn:2259158",
        "tgn:1000001",
        "tgn:7012149",
        "tgn:2002118",
        "tgn:7007827",
        "tgn:7029392"
    ],
    "tgn:id":2259158,
    "tgn:name":"Cottonwood Gulch",
    "tgn:placetype":[
        "aat:300008761"
    ]
},
  "bbox": [],
  "geometry": {"coordinates":[-111.75,40.85],"type":"Point"}
}
=======
{"geometry":{"type":"Point","coordinates":[-111.750000,40.850000]},"type":"Feature","properties":{"hierarchy":["tgn:2259158","tgn:1000001","tgn:7012149","tgn:2002118","tgn:7007827","tgn:7029392"],"placetype":["aat:300008761"],"id":2259158,"name:xx":"Cottonwood Gulch"}}
>>>>>>> 03f74aca74312dbeaf24d7e61306dd6a786dc3d0
