{
  "id": 2701476,
  "type": "Feature",
  "properties": {
    "tgn:hierarchy":[
        "tgn:2701476",
        "tgn:1000001",
        "tgn:7012149",
        "tgn:2001442",
        "tgn:7007566",
        "tgn:7029392"
    ],
    "tgn:id":2701476,
    "tgn:name":"Sugar Stake Claim",
    "tgn:placetype":[
        "aat:300000390"
    ]
},
  "bbox": [],
  "geometry": {"coordinates":[-105.8167,33.5167],"type":"Point"}
}