{
  "id": 7532258,
  "type": "Feature",
  "properties": {
    "tgn:hierarchy":[
        "tgn:7532258",
        "tgn:7001242",
        "tgn:7016833",
        "tgn:1001091",
        "tgn:7029392"
    ],
    "tgn:id":7532258,
    "tgn:name":"Mad\u012bnat al Marwah",
    "tgn:placetype":[
        "aat:300000745"
    ]
},
  "bbox": [],
  "geometry": {"coordinates":[31.327644,30.078184],"type":"Point"}
}