{
  "id": 1074997,
  "type": "Feature",
  "properties": {
    "tgn:hierarchy":[
        "tgn:1074997",
        "tgn:1000004",
        "tgn:7000198",
        "tgn:1001882",
        "tgn:7029392"
    ],
    "tgn:id":1074997,
    "tgn:name:en":"Chikodi",
    "tgn:placetype":[
        "aat:300008347"
    ]
},
  "bbox": [],
  "geometry": {"coordinates":[74.585,16.428],"type":"Point"}
}