{
  "id": 1058137,
  "type": "Feature",
  "properties": {
    "tgn:hierarchy":[
        "tgn:1058137",
        "tgn:7006644",
        "tgn:1000003",
        "tgn:7006540",
        "tgn:7029392"
    ],
    "tgn:id":1058137,
    "tgn:name:en":"P\u00e4rsti",
    "tgn:placetype":[
        "aat:300008347"
    ]
},
  "bbox": [],
  "geometry": {"coordinates":[25.525,58.425],"type":"Point"}
}