{
  "id": 7132029,
  "type": "Feature",
  "properties": {
    "tgn:hierarchy":[
        "tgn:7132029",
        "tgn:7003692",
        "tgn:1000003",
        "tgn:7000084",
        "tgn:7029392"
    ],
    "tgn:id":7132029,
    "tgn:name":"Mistelbrunn",
    "tgn:placetype":[
        "aat:300008347"
    ]
},
  "bbox": [],
  "geometry": {"coordinates":[8.366667,47.95],"type":"Point"}
}