{
  "id": 7584200,
  "type": "Feature",
  "properties": {
    "tgn:hierarchy":[
        "tgn:7584200",
        "tgn:1000004",
        "tgn:7000198",
        "tgn:1001894",
        "tgn:7029392"
    ],
    "tgn:id":7584200,
    "tgn:name:en":"Paigwa Pah\u0101r",
    "tgn:placetype":[
        "aat:300008795"
    ]
},
  "bbox": [],
  "geometry": {"coordinates":[78.927964,24.880982],"type":"Point"}
}