{
  "id": 2591590,
  "type": "Feature",
  "properties": {
    "tgn:hierarchy":[
        "tgn:2591590",
        "tgn:1002933",
        "tgn:1000001",
        "tgn:7012149",
        "tgn:7007239",
        "tgn:7029392"
    ],
    "tgn:id":2591590,
    "tgn:name":"Pond Acres",
    "tgn:placetype":[
        "aat:300008347"
    ]
},
  "bbox": [],
  "geometry": {"coordinates":[-75.0667,38.55],"type":"Point"}
}