{
  "id": 7283121,
  "type": "Feature",
  "properties": {
    "tgn:hierarchy":[
        "tgn:7283121",
        "tgn:1001630",
        "tgn:1000049",
        "tgn:1000002",
        "tgn:7029392"
    ],
    "tgn:id":7283121,
    "tgn:name":"Pasto Grande",
    "tgn:placetype":[
        "aat:300387200"
    ]
},
  "bbox": [],
  "geometry": {"coordinates":[-69.516667,-27.633333],"type":"Point"}
}