{
  "id": 2624585,
  "type": "Feature",
  "properties": {
    "tgn:hierarchy":[
        "tgn:2624585",
        "tgn:1000001",
        "tgn:7012149",
        "tgn:2001452",
        "tgn:7007566",
        "tgn:7029392"
    ],
    "tgn:id":2624585,
    "tgn:name":"Rock Ridge",
    "tgn:placetype":[
        "aat:300266640"
    ]
},
  "bbox": [],
  "geometry": {"coordinates":[-108.8667,36.5167],"type":"Point"}
}