{
  "id": 7518019,
  "type": "Feature",
  "properties": {
    "tgn:hierarchy":[
        "tgn:7518019",
        "tgn:1008380",
        "tgn:1000226",
        "tgn:7016827",
        "tgn:1000006",
        "tgn:7029392"
    ],
    "tgn:id":7518019,
    "tgn:name:en":"Makara Stream",
    "tgn:placetype":[
        "aat:300008699"
    ]
},
  "bbox": [],
  "geometry": {"coordinates":[174.366667,-39.116667],"type":"Point"}
}