{
  "id": 2161204,
  "type": "Feature",
  "properties": {
    "tgn:hierarchy":[
        "tgn:2161204",
        "tgn:1000001",
        "tgn:7014352",
        "tgn:7012149",
        "tgn:7007564",
        "tgn:7029392"
    ],
    "tgn:id":2161204,
    "tgn:name":"Bell Hill",
    "tgn:placetype":[
        "aat:300008798"
    ]
},
  "bbox": [],
  "geometry": {"coordinates":[-71.2667,42.9333],"type":"Point"}
}