{
  "id": 1092040,
  "type": "Feature",
  "properties": {
    "tgn:hierarchy":[
        "tgn:1092040",
        "tgn:7001242",
        "tgn:1001919",
        "tgn:1000182",
        "tgn:7029392"
    ],
    "tgn:id":1092040,
    "tgn:name":"Ikare-Akoko",
    "tgn:placetype":[
        "aat:300387277",
        "aat:300008347",
        "aat:300008375",
        "aat:300387286"
    ]
},
  "bbox": [],
  "geometry": {"coordinates":[5.75,7.5167],"type":"Point"}
}