{
  "id": 7531821,
  "type": "Feature",
  "properties": {
    "tgn:hierarchy":[
        "tgn:7531821",
        "tgn:7001242",
        "tgn:7016833",
        "tgn:1001123",
        "tgn:7029392"
    ],
    "tgn:id":7531821,
    "tgn:name":"El-D\u00eeba Fort (old)",
    "tgn:placetype":[
        "aat:300006909"
    ]
},
  "bbox": [],
  "geometry": {"coordinates":[32.064722,31.358333],"type":"Point"}
}