{
  "id": 7334149,
  "type": "Feature",
  "properties": {
    "tgn:hierarchy":[
        "tgn:7334149",
        "tgn:7008911",
        "tgn:1000003",
        "tgn:7002763",
        "tgn:1000095",
        "tgn:7029392"
    ],
    "tgn:id":7334149,
    "tgn:name":"El Solano",
    "tgn:placetype":[
        "aat:300008347"
    ]
},
  "bbox": [],
  "geometry": {"coordinates":[-5.55,43.366667],"type":"Point"}
}