{
  "id": 7039331,
  "type": "Feature",
  "properties": {
    "tgn:hierarchy":[
        "tgn:7039331",
        "tgn:1003468",
        "tgn:1000003",
        "tgn:7010380",
        "tgn:1000080",
        "tgn:7029392"
    ],
    "tgn:id":7039331,
    "tgn:name":"Surano",
    "tgn:placetype":[
        "aat:300008347"
    ]
},
  "bbox": [],
  "geometry": {"coordinates":[18.333333,40.016667],"type":"Point"}
}