{
  "id": 2106421,
  "type": "Feature",
  "properties": {
    "tgn:hierarchy":[
        "tgn:2106421",
        "tgn:1000001",
        "tgn:7012149",
        "tgn:1002839",
        "tgn:7007826",
        "tgn:7029392"
    ],
    "tgn:id":2106421,
    "tgn:name":"Oak Hill",
    "tgn:placetype":[
        "aat:300008347",
        "aat:300387210"
    ]
},
  "bbox": [],
  "geometry": {"coordinates":[-94.6833,32.2667],"type":"Point"}
}