{
  "id": 7584838,
  "type": "Feature",
  "properties": {
    "tgn:hierarchy":[
        "tgn:7584838",
        "tgn:1000004",
        "tgn:7000198",
        "tgn:1001894",
        "tgn:7029392"
    ],
    "tgn:id":7584838,
    "tgn:name:en":"S\u016bpa N\u0101la",
    "tgn:placetype":[
        "aat:300008699"
    ]
},
  "bbox": [],
  "geometry": {"coordinates":[78.922895,24.915138],"type":"Point"}
}