{
  "id": 2352059,
  "type": "Feature",
  "properties": {
    "tgn:hierarchy":[
        "tgn:2352059",
        "tgn:1000001",
        "tgn:7012149",
        "tgn:2001902",
        "tgn:7007825",
        "tgn:7029392"
    ],
    "tgn:id":2352059,
    "tgn:name":"Glory Hole",
    "tgn:placetype":[
        "aat:300008680"
    ]
},
  "bbox": [],
  "geometry": {"coordinates":[-89.3333,36.4167],"type":"Point"}
}