{
  "id": 2454165,
  "type": "Feature",
  "properties": {
    "tgn:hierarchy":[
        "tgn:2454165",
        "tgn:1000001",
        "tgn:7012149",
        "tgn:1002599",
        "tgn:7007708",
        "tgn:7029392"
    ],
    "tgn:id":2454165,
    "tgn:name":"Little Creek",
    "tgn:placetype":[
        "aat:300008706"
    ]
},
  "bbox": [],
  "geometry": {"coordinates":[-124.0667,44.3833],"type":"Point"}
}