{
  "id": 7022846,
  "type": "Feature",
  "properties": {
    "tgn:hierarchy":[
        "tgn:7022846",
        "tgn:1000001",
        "tgn:7012149",
        "tgn:2000406",
        "tgn:7007248",
        "tgn:7029392"
    ],
    "tgn:id":7022846,
    "tgn:name":"Dorene, Lake",
    "tgn:placetype":[
        "aat:300006191"
    ]
},
  "bbox": [],
  "geometry": {"coordinates":[-85.05,33.9667],"type":"Point"}
}