{
  "id": 7177201,
  "type": "Feature",
  "properties": {
    "tgn:hierarchy":[
        "tgn:7177201",
        "tgn:1000003",
        "tgn:7003688",
        "tgn:7000084",
        "tgn:7029392"
    ],
    "tgn:id":7177201,
    "tgn:name":"F\u00f6rsterei Hagener Holz",
    "tgn:placetype":[
        "aat:300004792"
    ]
},
  "bbox": [],
  "geometry": {"coordinates":[10.533333,54.033333],"type":"Point"}
}