<<<<<<< HEAD
{
  "id": 7177201,
  "type": "Feature",
  "properties": {
    "tgn:hierarchy":[
        "tgn:7177201",
        "tgn:1000003",
        "tgn:7003688",
        "tgn:7000084",
        "tgn:7029392"
    ],
    "tgn:id":7177201,
    "tgn:name":"F\u00f6rsterei Hagener Holz",
    "tgn:placetype":[
        "aat:300004792"
    ]
},
  "bbox": [],
  "geometry": {"coordinates":[10.533333,54.033333],"type":"Point"}
}
=======
{"geometry":{"type":"Point","coordinates":[10.533333,54.033333]},"type":"Feature","properties":{"hierarchy":["tgn:7177201","tgn:1000003","tgn:7003688","tgn:7000084","tgn:7029392"],"placetype":["aat:300004792"],"id":7177201,"name:xx":"F\u00f6rsterei Hagener Holz"}}
>>>>>>> 03f74aca74312dbeaf24d7e61306dd6a786dc3d0
