{
  "id": 7035582,
  "type": "Feature",
  "properties": {
    "tgn:hierarchy":[
        "tgn:7035582",
        "tgn:7002991",
        "tgn:1000003",
        "tgn:7002997",
        "tgn:1000080",
        "tgn:7029392"
    ],
    "tgn:id":7035582,
    "tgn:name":"Toc, Monte",
    "tgn:placetype":[
        "aat:300008795"
    ]
},
  "bbox": [],
  "geometry": {"coordinates":[12.3375,46.240833],"type":"Point"}
}