{
  "id": 2480879,
  "type": "Feature",
  "properties": {
    "tgn:hierarchy":[
        "tgn:2480879",
        "tgn:1000001",
        "tgn:7012149",
        "tgn:1002700",
        "tgn:7007520",
        "tgn:7029392"
    ],
    "tgn:id":2480879,
    "tgn:name":"Lakewood",
    "tgn:placetype":[
        "aat:300008347"
    ]
},
  "bbox": [],
  "geometry": {"coordinates":[-86.2333,43.3667],"type":"Point"}
}