<<<<<<< HEAD
{
  "id": 2152827,
  "type": "Feature",
  "properties": {
    "tgn:hierarchy":[
        "tgn:2152827",
        "tgn:1000001",
        "tgn:7012149",
        "tgn:1002645",
        "tgn:7007920",
        "tgn:7029392"
    ],
    "tgn:id":2152827,
    "tgn:name":"Bayshore",
    "tgn:placetype":[
        "aat:300008347"
    ]
},
  "bbox": [],
  "geometry": {"coordinates":[-123.0333,47.2333],"type":"Point"}
}
=======
{"geometry":{"type":"Point","coordinates":[-123.033300,47.233300]},"type":"Feature","properties":{"hierarchy":["tgn:2152827","tgn:1000001","tgn:7012149","tgn:1002645","tgn:7007920","tgn:7029392"],"placetype":["aat:300008347"],"id":2152827,"name:xx":"Bayshore"}}
>>>>>>> 03f74aca74312dbeaf24d7e61306dd6a786dc3d0
