{
  "id": 7549238,
  "type": "Feature",
  "properties": {
    "tgn:hierarchy":[
        "tgn:7549238",
        "tgn:1009838",
        "tgn:7000204",
        "tgn:1000004",
        "tgn:7000198",
        "tgn:7029392"
    ],
    "tgn:id":7549238,
    "tgn:name:en":"East Island",
    "tgn:placetype":[
        "aat:300008791"
    ]
},
  "bbox": [],
  "geometry": {"coordinates":[93.05,13.65],"type":"Point"}
}