{
  "id": 7227821,
  "type": "Feature",
  "properties": {
    "tgn:hierarchy":[
        "tgn:7227821",
        "tgn:7002715",
        "tgn:7002731",
        "tgn:1000003",
        "tgn:1000074",
        "tgn:7029392"
    ],
    "tgn:id":7227821,
    "tgn:name":"Livad\u00e1kion",
    "tgn:placetype":[
        "aat:300008347"
    ]
},
  "bbox": [],
  "geometry": {"coordinates":[22.964308,40.509477],"type":"Point"}
}