{
  "id": 2279479,
  "type": "Feature",
  "properties": {
    "tgn:hierarchy":[
        "tgn:2279479",
        "tgn:1000001",
        "tgn:7012149",
        "tgn:1002945",
        "tgn:7007710",
        "tgn:7029392"
    ],
    "tgn:id":2279479,
    "tgn:name":"Deadman Hollow",
    "tgn:placetype":[
        "aat:300008761"
    ]
},
  "bbox": [],
  "geometry": {"coordinates":[-77.4833,41.7167],"type":"Point"}
}