{
  "id": 7244675,
  "type": "Feature",
  "properties": {
    "tgn:hierarchy":[
        "tgn:7244675",
        "tgn:7007877",
        "tgn:1000003",
        "tgn:1000063",
        "tgn:4012014",
        "tgn:7029392"
    ],
    "tgn:id":7244675,
    "tgn:name":"Aremberg, Ruisseau d'",
    "tgn:placetype":[
        "aat:300008699"
    ]
},
  "bbox": [],
  "geometry": {"coordinates":[3.866667,50.733333],"type":"Point"}
}