{
  "id": 7263151,
  "type": "Feature",
  "properties": {
    "tgn:hierarchy":[
        "tgn:7263151",
        "tgn:1000003",
        "tgn:7003624",
        "tgn:7016845",
        "tgn:7029392"
    ],
    "tgn:id":7263151,
    "tgn:name:nl":"De Efteling",
    "tgn:placetype":[
        "aat:300008347"
    ]
},
  "bbox": [],
  "geometry": {"coordinates":[5.05,51.65],"type":"Point"}
}