{
  "id": 2342847,
  "type": "Feature",
  "properties": {
    "tgn:hierarchy":[
        "tgn:2342847",
        "tgn:1000001",
        "tgn:7012149",
        "tgn:2001461",
        "tgn:7007568",
        "tgn:7029392"
    ],
    "tgn:id":2342847,
    "tgn:name":"Furnace Point",
    "tgn:placetype":[
        "aat:300008850"
    ]
},
  "bbox": [],
  "geometry": {"coordinates":[-73.4167,44.1833],"type":"Point"}
}