{
  "id": 1125075,
  "type": "Feature",
  "properties": {
    "tgn:hierarchy":[
        "tgn:1125075",
        "tgn:1001834",
        "tgn:1000047",
        "tgn:7002455",
        "tgn:1000002",
        "tgn:7029392"
    ],
    "tgn:id":1125075,
    "tgn:name":"Jacar\u00e9",
    "tgn:placetype":[
        "aat:300008707"
    ]
},
  "bbox": [],
  "geometry": {"coordinates":[-63.5833,-5.8167],"type":"Point"}
}