{
  "id": 7362598,
  "type": "Feature",
  "properties": {
    "tgn:hierarchy":[
        "tgn:7362598",
        "tgn:7005586",
        "tgn:1000001",
        "tgn:7005560",
        "tgn:7029392"
    ],
    "tgn:id":7362598,
    "tgn:name":"El Carrizal",
    "tgn:placetype":[
        "aat:300008347"
    ]
},
  "bbox": [],
  "geometry": {"coordinates":[-104.15,20.766667],"type":"Point"}
}