<<<<<<< HEAD
{
  "id": 7362598,
  "type": "Feature",
  "properties": {
    "tgn:hierarchy":[
        "tgn:7362598",
        "tgn:7005586",
        "tgn:1000001",
        "tgn:7005560",
        "tgn:7029392"
    ],
    "tgn:id":7362598,
    "tgn:name":"El Carrizal",
    "tgn:placetype":[
        "aat:300008347"
    ]
},
  "bbox": [],
  "geometry": {"coordinates":[-104.15,20.766667],"type":"Point"}
}
=======
{"geometry":{"type":"Point","coordinates":[-104.150000,20.766667]},"type":"Feature","properties":{"hierarchy":["tgn:7362598","tgn:7005586","tgn:1000001","tgn:7005560","tgn:7029392"],"placetype":["aat:300008347"],"id":7362598,"name:xx":"El Carrizal"}}
>>>>>>> 03f74aca74312dbeaf24d7e61306dd6a786dc3d0
