{
  "id": 7263185,
  "type": "Feature",
  "properties": {
    "tgn:concordances":{
        "gn:id":"2757569"
    },
    "tgn:hierarchy":[
        "tgn:7263185",
        "tgn:1000003",
        "tgn:7003622",
        "tgn:7016845",
        "tgn:7029392"
    ],
    "tgn:id":7263185,
    "tgn:name:nl":"De Hei",
    "tgn:placetype":[
        "aat:300008347"
    ]
},
  "bbox": [],
  "geometry": {"coordinates":[6.15,51.483333],"type":"Point"}
}