{
  "id": 2348507,
  "type": "Feature",
  "properties": {
    "tgn:hierarchy":[
        "tgn:2348507",
        "tgn:1002300",
        "tgn:1000001",
        "tgn:7012149",
        "tgn:7007564",
        "tgn:7029392"
    ],
    "tgn:id":2348507,
    "tgn:name":"Gibbs Brook",
    "tgn:placetype":[
        "aat:300008699"
    ]
},
  "bbox": [],
  "geometry": {"coordinates":[-71.3667,44.2167],"type":"Point"}
}