{
  "id": 2090153,
  "type": "Feature",
  "properties": {
    "tgn:hierarchy":[
        "tgn:2090153",
        "tgn:1000001",
        "tgn:1002272",
        "tgn:7012149",
        "tgn:7007710",
        "tgn:7029392"
    ],
    "tgn:id":2090153,
    "tgn:name":"Limestone",
    "tgn:placetype":[
        "aat:300008347"
    ]
},
  "bbox": [],
  "geometry": {"coordinates":[-79.3167,41.1167],"type":"Point"}
}