{
  "id": 1140909,
  "type": "Feature",
  "properties": {
    "tgn:hierarchy":[
        "tgn:1140909",
        "tgn:7001242",
        "tgn:1001912",
        "tgn:1000182",
        "tgn:7029392"
    ],
    "tgn:id":1140909,
    "tgn:name":"Duku",
    "tgn:placetype":[
        "aat:300008347"
    ]
},
  "bbox": [],
  "geometry": {"coordinates":[4.9167,11.1833],"type":"Point"}
}