<<<<<<< HEAD
{
  "id": 7240941,
  "type": "Feature",
  "properties": {
    "tgn:hierarchy":[
        "tgn:7240941",
        "tgn:7003457",
        "tgn:1000003",
        "tgn:1000063",
        "tgn:7018236",
        "tgn:7029392"
    ],
    "tgn:id":7240941,
    "tgn:name":"Fontein",
    "tgn:placetype":[
        "aat:300008347"
    ]
},
  "bbox": [],
  "geometry": {"coordinates":[3.747215,51.205512],"type":"Point"}
}
=======
{"geometry":{"type":"Point","coordinates":[3.747215,51.205512]},"type":"Feature","properties":{"hierarchy":["tgn:7240941","tgn:7003457","tgn:1000003","tgn:1000063","tgn:7018236","tgn:7029392"],"placetype":["aat:300008347"],"id":7240941,"name:xx":"Fontein"}}
>>>>>>> 03f74aca74312dbeaf24d7e61306dd6a786dc3d0
