{
  "id": 7012441,
  "type": "Feature",
  "properties": {
    "tgn:hierarchy":[
        "tgn:7012441",
        "tgn:1000003",
        "tgn:7003688",
        "tgn:7000084",
        "tgn:7029392"
    ],
    "tgn:id":7012441,
    "tgn:name":"Elmshorn",
    "tgn:placetype":[
        "aat:300008347"
    ]
},
  "bbox": [],
  "geometry": {"coordinates":[9.65,53.75],"type":"Point"}
}