{
  "id": 7151373,
  "type": "Feature",
  "properties": {
    "tgn:hierarchy":[
        "tgn:7151373",
        "tgn:1000003",
        "tgn:7000094",
        "tgn:7000084",
        "tgn:7029392"
    ],
    "tgn:id":7151373,
    "tgn:name":"Kaninchen Werder",
    "tgn:placetype":[
        "aat:300008791"
    ]
},
  "bbox": [],
  "geometry": {"coordinates":[13.066667,53.266667],"type":"Point"}
}