{
  "id": 1119822,
  "type": "Feature",
  "properties": {
    "tgn:hierarchy":[
        "tgn:1119822",
        "tgn:1000001",
        "tgn:7012149",
        "tgn:7007923",
        "tgn:7029392"
    ],
    "tgn:id":1119822,
    "tgn:name":"Glendo Reservoir",
    "tgn:placetype":[
        "aat:300006191"
    ]
},
  "bbox": [],
  "geometry": {"coordinates":[-104.9333,42.4667],"type":"Point"}
}