{
  "id": 2515520,
  "type": "Feature",
  "properties": {
    "tgn:hierarchy":[
        "tgn:2515520",
        "tgn:1000001",
        "tgn:1003037",
        "tgn:7012149",
        "tgn:7007516",
        "tgn:7029392"
    ],
    "tgn:id":2515520,
    "tgn:name":"Mills Island",
    "tgn:placetype":[
        "aat:300008791"
    ]
},
  "bbox": [],
  "geometry": {"coordinates":[-75.3333,38.0333],"type":"Point"}
}