{
  "id": 7315958,
  "type": "Feature",
  "properties": {
    "tgn:hierarchy":[
        "tgn:7315958",
        "tgn:1001702",
        "tgn:1000049",
        "tgn:1000002",
        "tgn:7029392"
    ],
    "tgn:id":7315958,
    "tgn:name":"Carmona, Punta",
    "tgn:placetype":[
        "aat:300386846"
    ]
},
  "bbox": [],
  "geometry": {"coordinates":[-72.583333,-54.15],"type":"Point"}
}