<<<<<<< HEAD
{
  "id": 2700142,
  "type": "Feature",
  "properties": {
    "tgn:hierarchy":[
        "tgn:2700142",
        "tgn:1000001",
        "tgn:7012149",
        "tgn:7022218",
        "tgn:7007919",
        "tgn:7029392"
    ],
    "tgn:id":2700142,
    "tgn:name":"Stumpy Lake",
    "tgn:placetype":[
        "aat:300006191"
    ]
},
  "bbox": [],
  "geometry": {"coordinates":[-76.1333,36.75],"type":"Point"}
}
=======
{"geometry":{"type":"Point","coordinates":[-76.133300,36.750000]},"type":"Feature","properties":{"hierarchy":["tgn:2700142","tgn:1000001","tgn:7012149","tgn:7022218","tgn:7007919","tgn:7029392"],"placetype":["aat:300006191"],"id":2700142,"name:xx":"Stumpy Lake"}}
>>>>>>> 03f74aca74312dbeaf24d7e61306dd6a786dc3d0
