{
  "id": 2746321,
  "type": "Feature",
  "properties": {
    "tgn:hierarchy":[
        "tgn:2746321",
        "tgn:1000001",
        "tgn:7012149",
        "tgn:2001532",
        "tgn:7007709",
        "tgn:7029392"
    ],
    "tgn:id":2746321,
    "tgn:name":"W A McCrary Lake",
    "tgn:placetype":[
        "aat:300006191"
    ]
},
  "bbox": [],
  "geometry": {"coordinates":[-79.85,35.7167],"type":"Point"}
}