<<<<<<< HEAD
{
  "id": 7056741,
  "type": "Feature",
  "properties": {
    "tgn:hierarchy":[
        "tgn:7056741",
        "tgn:7003127",
        "tgn:1000003",
        "tgn:7008516",
        "tgn:1000080",
        "tgn:7029392"
    ],
    "tgn:id":7056741,
    "tgn:name":"Bersagliera",
    "tgn:placetype":[
        "aat:300008347"
    ]
},
  "bbox": [],
  "geometry": {"coordinates":[11.1,44.45],"type":"Point"}
}
=======
{"geometry":{"type":"Point","coordinates":[11.100000,44.450000]},"type":"Feature","properties":{"hierarchy":["tgn:7056741","tgn:7003127","tgn:1000003","tgn:7008516","tgn:1000080","tgn:7029392"],"placetype":["aat:300008347"],"id":7056741,"name:xx":"Bersagliera"}}
>>>>>>> 03f74aca74312dbeaf24d7e61306dd6a786dc3d0
