{
  "id": 7335282,
  "type": "Feature",
  "properties": {
    "tgn:hierarchy":[
        "tgn:7335282",
        "tgn:7001158",
        "tgn:7002848",
        "tgn:1000003",
        "tgn:1000095",
        "tgn:7029392"
    ],
    "tgn:id":7335282,
    "tgn:name":"Gordaliza de la Loma",
    "tgn:placetype":[
        "aat:300008347"
    ]
},
  "bbox": [],
  "geometry": {"coordinates":[-5.133333,42.133333],"type":"Point"}
}