{
  "id": 2175651,
  "type": "Feature",
  "properties": {
    "tgn:hierarchy":[
        "tgn:2175651",
        "tgn:1000001",
        "tgn:7012149",
        "tgn:2000216",
        "tgn:7007158",
        "tgn:7029392"
    ],
    "tgn:id":2175651,
    "tgn:name":"Black Creek",
    "tgn:placetype":[
        "aat:300008706"
    ]
},
  "bbox": [],
  "geometry": {"coordinates":[-106.3667,40.25],"type":"Point"}
}