{
  "id": 2421296,
  "type": "Feature",
  "properties": {
    "tgn:hierarchy":[
        "tgn:2421296",
        "tgn:1000001",
        "tgn:2000470",
        "tgn:7012149",
        "tgn:7007250",
        "tgn:7029392"
    ],
    "tgn:id":2421296,
    "tgn:name":"Jerrys Creek",
    "tgn:placetype":[
        "aat:300008706"
    ]
},
  "bbox": [],
  "geometry": {"coordinates":[-114.6833,44.35],"type":"Point"}
}