{
  "id": 2447654,
  "type": "Feature",
  "properties": {
    "tgn:hierarchy":[
        "tgn:2447654",
        "tgn:1000001",
        "tgn:7012149",
        "tgn:2002168",
        "tgn:7007919",
        "tgn:7029392"
    ],
    "tgn:id":2447654,
    "tgn:name":"Lick Points",
    "tgn:placetype":[
        "aat:300266640"
    ]
},
  "bbox": [],
  "geometry": {"coordinates":[-79.7833,38.3167],"type":"Point"}
}