{
  "id": 2644536,
  "type": "Feature",
  "properties": {
    "tgn:hierarchy":[
        "tgn:2644536",
        "tgn:1000001",
        "tgn:7012149",
        "tgn:2001454",
        "tgn:7007566",
        "tgn:7029392"
    ],
    "tgn:id":2644536,
    "tgn:name":"Sarca Creek, Agua",
    "tgn:placetype":[
        "aat:300008699"
    ]
},
  "bbox": [],
  "geometry": {"coordinates":[-105.8333,35.6667],"type":"Point"}
}