{
  "id": 2692881,
  "type": "Feature",
  "properties": {
    "tgn:hierarchy":[
        "tgn:2692881",
        "tgn:1000001",
        "tgn:2001581",
        "tgn:7012149",
        "tgn:7007705",
        "tgn:7029392"
    ],
    "tgn:id":2692881,
    "tgn:name":"Steele Lake",
    "tgn:placetype":[
        "aat:300008680"
    ]
},
  "bbox": [],
  "geometry": {"coordinates":[-100.2333,47.8667],"type":"Point"}
}