<<<<<<< HEAD
{
  "id": 7174182,
  "type": "Feature",
  "properties": {
    "tgn:hierarchy":[
        "tgn:7174182",
        "tgn:1000003",
        "tgn:7003677",
        "tgn:7000084",
        "tgn:7029392"
    ],
    "tgn:id":7174182,
    "tgn:name":"Gr\u00f6pperhof",
    "tgn:placetype":[
        "aat:300000206"
    ]
},
  "bbox": [],
  "geometry": {"coordinates":[9.016667,51.933333],"type":"Point"}
}
=======
{"geometry":{"type":"Point","coordinates":[9.016667,51.933333]},"type":"Feature","properties":{"hierarchy":["tgn:7174182","tgn:1000003","tgn:7003677","tgn:7000084","tgn:7029392"],"placetype":["aat:300000206"],"id":7174182,"name:xx":"Gr\u00f6pperhof"}}
>>>>>>> 03f74aca74312dbeaf24d7e61306dd6a786dc3d0
