{
  "id": 2197881,
  "type": "Feature",
  "properties": {
    "tgn:hierarchy":[
        "tgn:2197881",
        "tgn:1000001",
        "tgn:7012149",
        "tgn:2001711",
        "tgn:7007708",
        "tgn:7029392"
    ],
    "tgn:id":2197881,
    "tgn:name":"Brown Reservoir",
    "tgn:placetype":[
        "aat:300006191"
    ]
},
  "bbox": [],
  "geometry": {"coordinates":[-122.9667,42.1667],"type":"Point"}
}