{
  "id": 1107106,
  "type": "Feature",
  "properties": {
    "tgn:hierarchy":[
        "tgn:1107106",
        "tgn:1000001",
        "tgn:7006451",
        "tgn:2000091",
        "tgn:7012149",
        "tgn:7029392"
    ],
    "tgn:id":1107106,
    "tgn:name":"Apache Peak",
    "tgn:placetype":[
        "aat:300008798"
    ]
},
  "bbox": [],
  "geometry": {"coordinates":[-110.4167,31.8167],"type":"Point"}
}