{
  "id": 7591975,
  "type": "Feature",
  "properties": {
    "tgn:hierarchy":[
        "tgn:7591975",
        "tgn:1000004",
        "tgn:7000198",
        "tgn:7000799",
        "tgn:7029392"
    ],
    "tgn:id":7591975,
    "tgn:name:en":"P\u0101tthi",
    "tgn:placetype":[
        "aat:300008347"
    ]
},
  "bbox": [],
  "geometry": {"coordinates":[74.84228,32.991604],"type":"Point"}
}