{
  "id": 7507755,
  "type": "Feature",
  "properties": {
    "tgn:hierarchy":[
        "tgn:7507755",
        "tgn:1009227",
        "tgn:1000226",
        "tgn:7018437",
        "tgn:1000006",
        "tgn:7029392"
    ],
    "tgn:id":7507755,
    "tgn:name:en":"Pisgah Spur",
    "tgn:placetype":[
        "aat:300387002"
    ]
},
  "bbox": [],
  "geometry": {"coordinates":[170.45,-45.066667],"type":"Point"}
}