{
  "id": 2352586,
  "type": "Feature",
  "properties": {
    "tgn:hierarchy":[
        "tgn:2352586",
        "tgn:1000001",
        "tgn:7012149",
        "tgn:2001279",
        "tgn:7007524",
        "tgn:7029392"
    ],
    "tgn:id":2352586,
    "tgn:name":"Goat Mountain Lakes",
    "tgn:placetype":[
        "aat:300008680"
    ]
},
  "bbox": [],
  "geometry": {"coordinates":[-113.05,46.3667],"type":"Point"}
}