{
  "id": 7338992,
  "type": "Feature",
  "properties": {
    "tgn:hierarchy":[
        "tgn:7338992",
        "tgn:7002849",
        "tgn:1000003",
        "tgn:7009604",
        "tgn:1000095",
        "tgn:7029392"
    ],
    "tgn:id":7338992,
    "tgn:name":"El Casta\u00f1o",
    "tgn:placetype":[
        "aat:300008347"
    ]
},
  "bbox": [],
  "geometry": {"coordinates":[-3.166667,43.266667],"type":"Point"}
}