{
  "id": 1059607,
  "type": "Feature",
  "properties": {
    "tgn:hierarchy":[
        "tgn:1059607",
        "tgn:1000003",
        "tgn:7016798",
        "tgn:7006660",
        "tgn:7029392"
    ],
    "tgn:id":1059607,
    "tgn:name":"Solotvyna",
    "tgn:placetype":[
        "aat:300008347"
    ]
},
  "bbox": [],
  "geometry": {"coordinates":[23.8667,47.95],"type":"Point"}
}