{
  "id": 2558607,
  "type": "Feature",
  "properties": {
    "tgn:hierarchy":[
        "tgn:2558607",
        "tgn:1000001",
        "tgn:7012149",
        "tgn:7014612",
        "tgn:7007568",
        "tgn:7029392"
    ],
    "tgn:id":2558607,
    "tgn:name":"Oliver Pond",
    "tgn:placetype":[
        "aat:300008680"
    ]
},
  "bbox": [],
  "geometry": {"coordinates":[-73.8333,41.1833],"type":"Point"}
}