{
  "id": 2595489,
  "type": "Feature",
  "properties": {
    "tgn:hierarchy":[
        "tgn:2595489",
        "tgn:1000001",
        "tgn:7012149",
        "tgn:2000833",
        "tgn:7007255",
        "tgn:7029392"
    ],
    "tgn:id":2595489,
    "tgn:name":"Potato Hill Knob",
    "tgn:placetype":[
        "aat:300008798"
    ]
},
  "bbox": [],
  "geometry": {"coordinates":[-85.5667,37.7167],"type":"Point"}
}