<<<<<<< HEAD
{
  "id": 2337847,
  "type": "Feature",
  "properties": {
    "tgn:hierarchy":[
        "tgn:2337847",
        "tgn:1000001",
        "tgn:7012149",
        "tgn:2001883",
        "tgn:7007825",
        "tgn:7029392"
    ],
    "tgn:id":2337847,
    "tgn:name":"Fox Fire",
    "tgn:placetype":[
        "aat:300008347"
    ]
},
  "bbox": [],
  "geometry": {"coordinates":[-84.05,35.8667],"type":"Point"}
}
=======
{"geometry":{"type":"Point","coordinates":[-84.050000,35.866700]},"type":"Feature","properties":{"hierarchy":["tgn:2337847","tgn:1000001","tgn:7012149","tgn:2001883","tgn:7007825","tgn:7029392"],"placetype":["aat:300008347"],"id":2337847,"name:xx":"Fox Fire"}}
>>>>>>> 03f74aca74312dbeaf24d7e61306dd6a786dc3d0
