<<<<<<< HEAD
{
  "id": 7485441,
  "type": "Feature",
  "properties": {
    "tgn:hierarchy":[
        "tgn:7485441",
        "tgn:1000004",
        "tgn:7492971",
        "tgn:1000141",
        "tgn:7029392"
    ],
    "tgn:id":7485441,
    "tgn:name":"Wanyinggong Ci",
    "tgn:placetype":[
        "aat:300007595"
    ]
},
  "bbox": [],
  "geometry": {"coordinates":[120.727222,22.074722],"type":"Point"}
}
=======
{"geometry":{"type":"Point","coordinates":[120.727222,22.074722]},"type":"Feature","properties":{"hierarchy":["tgn:7485441","tgn:1000004","tgn:7492971","tgn:1000141","tgn:7029392"],"placetype":["aat:300007595"],"id":7485441,"name:xx":"Wanyinggong Ci"}}
>>>>>>> 03f74aca74312dbeaf24d7e61306dd6a786dc3d0
