{
  "id": 2062917,
  "type": "Feature",
  "properties": {
    "tgn:hierarchy":[
        "tgn:2062917",
        "tgn:1000001",
        "tgn:7012149",
        "tgn:2001420",
        "tgn:7007526",
        "tgn:7029392"
    ],
    "tgn:id":2062917,
    "tgn:name":"Greens",
    "tgn:placetype":[
        "aat:300387016"
    ]
},
  "bbox": [],
  "geometry": {"coordinates":[-114.7333,40.0333],"type":"Point"}
}