{
  "id": 7045904,
  "type": "Feature",
  "properties": {
    "tgn:hierarchy":[
        "tgn:7045904",
        "tgn:7007850",
        "tgn:7024842",
        "tgn:1000003",
        "tgn:1000080",
        "tgn:7029392"
    ],
    "tgn:id":7045904,
    "tgn:name":"Conidoni",
    "tgn:placetype":[
        "aat:300008347"
    ]
},
  "bbox": [],
  "geometry": {"coordinates":[16.033333,38.716667],"type":"Point"}
}