{
  "id": 2701479,
  "type": "Feature",
  "properties": {
    "tgn:hierarchy":[
        "tgn:2701479",
        "tgn:1000001",
        "tgn:7012149",
        "tgn:2001503",
        "tgn:7007709",
        "tgn:7029392"
    ],
    "tgn:id":2701479,
    "tgn:name":"Sugar Top",
    "tgn:placetype":[
        "aat:300008798"
    ]
},
  "bbox": [],
  "geometry": {"coordinates":[-82.8167,35.4667],"type":"Point"}
}