{
  "id": 2606192,
  "type": "Feature",
  "properties": {
    "tgn:hierarchy":[
        "tgn:2606192",
        "tgn:7006450",
        "tgn:1000001",
        "tgn:7012149",
        "tgn:2000086",
        "tgn:7029392"
    ],
    "tgn:id":2606192,
    "tgn:name":"Rainy Glacier",
    "tgn:placetype":[
        "aat:300008835"
    ]
},
  "bbox": [],
  "geometry": {"coordinates":[-148.5333,60.6333],"type":"Point"}
}