{
  "id": 1103504,
  "type": "Feature",
  "properties": {
    "tgn:hierarchy":[
        "tgn:1103504",
        "tgn:1000003",
        "tgn:7003677",
        "tgn:7000084",
        "tgn:7004982",
        "tgn:7029392"
    ],
    "tgn:id":1103504,
    "tgn:name":"Westerholz",
    "tgn:placetype":[
        "aat:300132451"
    ]
},
  "bbox": [],
  "geometry": {"coordinates":[7.4667,51.5333],"type":"Point"}
}