{
  "id": 2519201,
  "type": "Feature",
  "properties": {
    "tgn:hierarchy":[
        "tgn:2519201",
        "tgn:1000001",
        "tgn:7012149",
        "tgn:2000481",
        "tgn:7007250",
        "tgn:7029392"
    ],
    "tgn:id":2519201,
    "tgn:name":"Moccasin Creek",
    "tgn:placetype":[
        "aat:300008706"
    ]
},
  "bbox": [],
  "geometry": {"coordinates":[-114.0833,45.0833],"type":"Point"}
}