{
  "id": 7091523,
  "type": "Feature",
  "properties": {
    "tgn:hierarchy":[
        "tgn:7091523",
        "tgn:1000003",
        "tgn:7003688",
        "tgn:7000084",
        "tgn:7029392"
    ],
    "tgn:id":7091523,
    "tgn:name":"Vordorf",
    "tgn:placetype":[
        "aat:300000206"
    ]
},
  "bbox": [],
  "geometry": {"coordinates":[10.533333,54.05],"type":"Point"}
}