<<<<<<< HEAD
{
  "id": 7377783,
  "type": "Feature",
  "properties": {
    "tgn:hierarchy":[
        "tgn:7377783",
        "tgn:7005580",
        "tgn:1000001",
        "tgn:7005560",
        "tgn:7029392"
    ],
    "tgn:id":7377783,
    "tgn:name":"La Ventosa",
    "tgn:placetype":[
        "aat:300008347"
    ]
},
  "bbox": [],
  "geometry": {"coordinates":[-93.4,16.816667],"type":"Point"}
}
=======
{"geometry":{"type":"Point","coordinates":[-93.400000,16.816667]},"type":"Feature","properties":{"hierarchy":["tgn:7377783","tgn:7005580","tgn:1000001","tgn:7005560","tgn:7029392"],"placetype":["aat:300008347"],"id":7377783,"name:xx":"La Ventosa"}}
>>>>>>> 03f74aca74312dbeaf24d7e61306dd6a786dc3d0
