{
  "id": 1090097,
  "type": "Feature",
  "properties": {
    "tgn:hierarchy":[
        "tgn:1090097",
        "tgn:1001640",
        "tgn:7001242",
        "tgn:1000166",
        "tgn:7029392"
    ],
    "tgn:id":1090097,
    "tgn:name":"Bechem",
    "tgn:placetype":[
        "aat:300008347"
    ]
},
  "bbox": [],
  "geometry": {"coordinates":[-2.0333,7.0833],"type":"Point"}
}