{
  "id": 2129694,
  "type": "Feature",
  "properties": {
    "tgn:hierarchy":[
        "tgn:2129694",
        "tgn:1000001",
        "tgn:7012149",
        "tgn:7007157",
        "tgn:1002608",
        "tgn:7029392"
    ],
    "tgn:id":2129694,
    "tgn:name":"Alla",
    "tgn:placetype":[
        "aat:300008347"
    ]
},
  "bbox": [],
  "geometry": {"coordinates":[-118.4167,33.9667],"type":"Point"}
}