{
  "id": 7431775,
  "type": "Feature",
  "properties": {
    "tgn:hierarchy":[
        "tgn:7431775",
        "tgn:7005586",
        "tgn:1000001",
        "tgn:7005560",
        "tgn:7029392"
    ],
    "tgn:id":7431775,
    "tgn:name":"Ojuelos",
    "tgn:placetype":[
        "aat:300008347"
    ]
},
  "bbox": [],
  "geometry": {"coordinates":[-102.691667,21.266667],"type":"Point"}
}