{
  "id": 7534394,
  "type": "Feature",
  "properties": {
    "tgn:hierarchy":[
        "tgn:7534394",
        "tgn:7001242",
        "tgn:7016833",
        "tgn:1001335",
        "tgn:7029392"
    ],
    "tgn:id":7534394,
    "tgn:name:en":"Kafr Y\u016bsuf",
    "tgn:placetype":[
        "aat:300008347"
    ]
},
  "bbox": [],
  "geometry": {"coordinates":[30.867703,31.207045],"type":"Point"}
}