<<<<<<< HEAD
{
  "id": 7172568,
  "type": "Feature",
  "properties": {
    "tgn:hierarchy":[
        "tgn:7172568",
        "tgn:1000003",
        "tgn:7003677",
        "tgn:7000084",
        "tgn:7029392"
    ],
    "tgn:id":7172568,
    "tgn:name":"Herrath",
    "tgn:placetype":[
        "aat:300008347"
    ]
},
  "bbox": [],
  "geometry": {"coordinates":[6.366667,51.1],"type":"Point"}
}
=======
{"geometry":{"type":"Point","coordinates":[6.366667,51.100000]},"type":"Feature","properties":{"hierarchy":["tgn:7172568","tgn:1000003","tgn:7003677","tgn:7000084","tgn:7029392"],"placetype":["aat:300008347"],"id":7172568,"name:xx":"Herrath"}}
>>>>>>> 03f74aca74312dbeaf24d7e61306dd6a786dc3d0
