{
  "id": 2774974,
  "type": "Feature",
  "properties": {
    "tgn:hierarchy":[
        "tgn:2774974",
        "tgn:1000001",
        "tgn:7006451",
        "tgn:7012149",
        "tgn:2000103",
        "tgn:7029392"
    ],
    "tgn:id":2774974,
    "tgn:name":"Willow Wash Spring",
    "tgn:placetype":[
        "aat:300008697"
    ]
},
  "bbox": [],
  "geometry": {"coordinates":[-112.5167,35.5833],"type":"Point"}
}