{
  "id": 7219476,
  "type": "Feature",
  "properties": {
    "tgn:hierarchy":[
        "tgn:7219476",
        "tgn:7011330",
        "tgn:7002674",
        "tgn:1000003",
        "tgn:1000074",
        "tgn:7029392"
    ],
    "tgn:id":7219476,
    "tgn:name":"V\u00f3lakas, \u00c1kra",
    "tgn:placetype":[
        "aat:300008850"
    ]
},
  "bbox": [],
  "geometry": {"coordinates":[27.233333,35.466667],"type":"Point"}
}