{
  "id": 7279729,
  "type": "Feature",
  "properties": {
    "tgn:hierarchy":[
        "tgn:7279729",
        "tgn:1001768",
        "tgn:1000049",
        "tgn:1000002",
        "tgn:7029392"
    ],
    "tgn:id":7279729,
    "tgn:name":"Rinconada La Represa",
    "tgn:placetype":[
        "aat:300387200"
    ]
},
  "bbox": [],
  "geometry": {"coordinates":[-71.05,-32.616667],"type":"Point"}
}