<<<<<<< HEAD
{
  "id": 2762487,
  "type": "Feature",
  "properties": {
    "tgn:hierarchy":[
        "tgn:2762487",
        "tgn:1000001",
        "tgn:7013686",
        "tgn:7012149",
        "tgn:7007517",
        "tgn:7029392"
    ],
    "tgn:id":2762487,
    "tgn:name":"West Ware",
    "tgn:placetype":[
        "aat:300008347"
    ]
},
  "bbox": [],
  "geometry": {"coordinates":[-72.3167,42.2667],"type":"Point"}
}
=======
{"geometry":{"type":"Point","coordinates":[-72.316700,42.266700]},"type":"Feature","properties":{"hierarchy":["tgn:2762487","tgn:1000001","tgn:7013686","tgn:7012149","tgn:7007517","tgn:7029392"],"placetype":["aat:300008347"],"id":2762487,"name:xx":"West Ware"}}
>>>>>>> 03f74aca74312dbeaf24d7e61306dd6a786dc3d0
