{
  "id": 2547498,
  "type": "Feature",
  "properties": {
    "tgn:hierarchy":[
        "tgn:2547498",
        "tgn:1000001",
        "tgn:7012149",
        "tgn:2000471",
        "tgn:7007250",
        "tgn:7029392"
    ],
    "tgn:id":2547498,
    "tgn:name":"North Fork Steel Creek",
    "tgn:placetype":[
        "aat:300008706"
    ]
},
  "bbox": [],
  "geometry": {"coordinates":[-115.2667,43.7167],"type":"Point"}
}