{
  "id": 2014236,
  "type": "Feature",
  "properties": {
    "tgn:hierarchy":[
        "tgn:2014236",
        "tgn:1000001",
        "tgn:7012149",
        "tgn:2000181",
        "tgn:7007157",
        "tgn:7029392"
    ],
    "tgn:id":2014236,
    "tgn:name":"Shelter Cove",
    "tgn:placetype":[
        "aat:300008347"
    ]
},
  "bbox": [],
  "geometry": {"coordinates":[-124.0667,40.0167],"type":"Point"}
}