{
  "id": 7389763,
  "type": "Feature",
  "properties": {
    "tgn:hierarchy":[
        "tgn:7389763",
        "tgn:1000001",
        "tgn:7005591",
        "tgn:7005560",
        "tgn:7029392"
    ],
    "tgn:id":7389763,
    "tgn:name":"Salina Cruz, Bah\u00eda",
    "tgn:placetype":[
        "aat:300132316"
    ]
},
  "bbox": [],
  "geometry": {"coordinates":[-95.183333,16.166667],"type":"Point"}
}