{
  "id": 7346905,
  "type": "Feature",
  "properties": {
    "tgn:hierarchy":[
        "tgn:7346905",
        "tgn:7002831",
        "tgn:1000003",
        "tgn:7002786",
        "tgn:1000095",
        "tgn:7029392"
    ],
    "tgn:id":7346905,
    "tgn:name":"Beiro",
    "tgn:placetype":[
        "aat:300008347"
    ]
},
  "bbox": [],
  "geometry": {"coordinates":[-8.15,42.35],"type":"Point"}
}