{
  "id": 7563217,
  "type": "Feature",
  "properties": {
    "tgn:hierarchy":[
        "tgn:7563217",
        "tgn:1000004",
        "tgn:7000198",
        "tgn:7016722",
        "tgn:7029392"
    ],
    "tgn:id":7563217,
    "tgn:name:en":"Albela",
    "tgn:placetype":[
        "aat:300008347"
    ]
},
  "bbox": [],
  "geometry": {"coordinates":[79.608917,27.747623],"type":"Point"}
}