{
  "id": 7046903,
  "type": "Feature",
  "properties": {
    "tgn:hierarchy":[
        "tgn:7046903",
        "tgn:7005126",
        "tgn:1000003",
        "tgn:7003120",
        "tgn:1000080",
        "tgn:7029392"
    ],
    "tgn:id":7046903,
    "tgn:name":"Case Arfel",
    "tgn:placetype":[
        "aat:300008347"
    ]
},
  "bbox": [],
  "geometry": {"coordinates":[7.783333,44.25],"type":"Point"}
}