{
  "id": 7573194,
  "type": "Feature",
  "properties": {
    "tgn:hierarchy":[
        "tgn:7573194",
        "tgn:1009838",
        "tgn:7000204",
        "tgn:1000004",
        "tgn:7000198",
        "tgn:7029392"
    ],
    "tgn:id":7573194,
    "tgn:name:en":"Juanita Shoal",
    "tgn:placetype":[
        "aat:300387036"
    ]
},
  "bbox": [],
  "geometry": {"coordinates":[93.666667,15.983333],"type":"Point"}
}