{
  "id": 7574744,
  "type": "Feature",
  "properties": {
    "tgn:hierarchy":[
        "tgn:7574744",
        "tgn:1000004",
        "tgn:7000198",
        "tgn:1001894",
        "tgn:7029392"
    ],
    "tgn:id":7574744,
    "tgn:name:en":"Kishangarh",
    "tgn:placetype":[
        "aat:300008347"
    ]
},
  "bbox": [],
  "geometry": {"coordinates":[79.750688,24.46979],"type":"Point"}
}