{
  "id": 2246831,
  "type": "Feature",
  "properties": {
    "tgn:hierarchy":[
        "tgn:2246831",
        "tgn:1000001",
        "tgn:7012149",
        "tgn:2001449",
        "tgn:7007566",
        "tgn:7029392"
    ],
    "tgn:id":2246831,
    "tgn:name":"Cochina Spring",
    "tgn:placetype":[
        "aat:300008697"
    ]
},
  "bbox": [],
  "geometry": {"coordinates":[-106.6167,36.0167],"type":"Point"}
}