{
  "id": 7468901,
  "type": "Feature",
  "properties": {
    "tgn:hierarchy":[
        "tgn:7468901",
        "tgn:1000004",
        "tgn:7490934",
        "tgn:1000141",
        "tgn:7029392"
    ],
    "tgn:id":7468901,
    "tgn:name":"Xinshi Zhan",
    "tgn:placetype":[
        "aat:300007783"
    ]
},
  "bbox": [],
  "geometry": {"coordinates":[120.289673,23.068095],"type":"Point"}
}