<<<<<<< HEAD
{
  "id": 2763936,
  "type": "Feature",
  "properties": {
    "tgn:hierarchy":[
        "tgn:2763936",
        "tgn:1000001",
        "tgn:1002273",
        "tgn:7012149",
        "tgn:7007252",
        "tgn:7029392"
    ],
    "tgn:id":2763936,
    "tgn:name":"Wheel Run",
    "tgn:placetype":[
        "aat:300008699"
    ]
},
  "bbox": [],
  "geometry": {"coordinates":[-85.7667,38.5833],"type":"Point"}
}
=======
{"geometry":{"type":"Point","coordinates":[-85.766700,38.583300]},"type":"Feature","properties":{"hierarchy":["tgn:2763936","tgn:1000001","tgn:1002273","tgn:7012149","tgn:7007252","tgn:7029392"],"placetype":["aat:300008699"],"id":2763936,"name:xx":"Wheel Run"}}
>>>>>>> 03f74aca74312dbeaf24d7e61306dd6a786dc3d0
