<<<<<<< HEAD
{
  "id": 2763216,
  "type": "Feature",
  "properties": {
    "tgn:hierarchy":[
        "tgn:2763216",
        "tgn:1000001",
        "tgn:7012149",
        "tgn:2002118",
        "tgn:7007827",
        "tgn:7029392"
    ],
    "tgn:id":2763216,
    "tgn:name":"Westwood",
    "tgn:placetype":[
        "aat:300008347"
    ]
},
  "bbox": [],
  "geometry": {"coordinates":[-111.9667,40.6333],"type":"Point"}
}
=======
{"geometry":{"type":"Point","coordinates":[-111.966700,40.633300]},"type":"Feature","properties":{"hierarchy":["tgn:2763216","tgn:1000001","tgn:7012149","tgn:2002118","tgn:7007827","tgn:7029392"],"placetype":["aat:300008347"],"id":2763216,"name:xx":"Westwood"}}
>>>>>>> 03f74aca74312dbeaf24d7e61306dd6a786dc3d0
