{
  "id": 2455357,
  "type": "Feature",
  "properties": {
    "tgn:hierarchy":[
        "tgn:2455357",
        "tgn:1000001",
        "tgn:2002261",
        "tgn:7012149",
        "tgn:7013961",
        "tgn:7029392"
    ],
    "tgn:id":2455357,
    "tgn:name":"Little Fork",
    "tgn:placetype":[
        "aat:300008699"
    ]
},
  "bbox": [],
  "geometry": {"coordinates":[-81.2667,37.9833],"type":"Point"}
}