{
  "id": 7039905,
  "type": "Feature",
  "properties": {
    "tgn:hierarchy":[
        "tgn:7039905",
        "tgn:1000003",
        "tgn:7003236",
        "tgn:7003144",
        "tgn:1000080",
        "tgn:7029392"
    ],
    "tgn:id":7039905,
    "tgn:name":"Segno",
    "tgn:placetype":[
        "aat:300008347"
    ]
},
  "bbox": [],
  "geometry": {"coordinates":[8.383333,44.25],"type":"Point"}
}