{
  "id": 2571451,
  "type": "Feature",
  "properties": {
    "tgn:hierarchy":[
        "tgn:2571451",
        "tgn:1000001",
        "tgn:7012149",
        "tgn:2000490",
        "tgn:7007250",
        "tgn:7029392"
    ],
    "tgn:id":2571451,
    "tgn:name":"Pauline",
    "tgn:placetype":[
        "aat:300008347"
    ]
},
  "bbox": [],
  "geometry": {"coordinates":[-112.55,42.5667],"type":"Point"}
}