{
  "id": 7502537,
  "type": "Feature",
  "properties": {
    "tgn:hierarchy":[
        "tgn:7502537",
        "tgn:1000004",
        "tgn:7001009",
        "tgn:1000141",
        "tgn:7029392"
    ],
    "tgn:id":7502537,
    "tgn:name":"Shangshe",
    "tgn:placetype":[
        "aat:300008347"
    ]
},
  "bbox": [],
  "geometry": {"coordinates":[120.804146,24.228269],"type":"Point"}
}