{
  "id": 2062381,
  "type": "Feature",
  "properties": {
    "tgn:hierarchy":[
        "tgn:2062381",
        "tgn:1000001",
        "tgn:2001370",
        "tgn:7012149",
        "tgn:7007525",
        "tgn:7029392"
    ],
    "tgn:id":2062381,
    "tgn:name":"Martell",
    "tgn:placetype":[
        "aat:300008347"
    ]
},
  "bbox": [],
  "geometry": {"coordinates":[-96.75,40.6333],"type":"Point"}
}