{
  "id": 2573628,
  "type": "Feature",
  "properties": {
    "tgn:hierarchy":[
        "tgn:2573628",
        "tgn:1000001",
        "tgn:7012149",
        "tgn:2000983",
        "tgn:7007520",
        "tgn:7029392"
    ],
    "tgn:id":2573628,
    "tgn:name":"Peck Lake",
    "tgn:placetype":[
        "aat:300008680"
    ]
},
  "bbox": [],
  "geometry": {"coordinates":[-85.8833,43.4833],"type":"Point"}
}