{
  "id": 2723520,
  "type": "Feature",
  "properties": {
    "tgn:hierarchy":[
        "tgn:2723520",
        "tgn:1000001",
        "tgn:7012149",
        "tgn:2001133",
        "tgn:7007522",
        "tgn:7029392"
    ],
    "tgn:id":2723520,
    "tgn:name":"Todd Branch",
    "tgn:placetype":[
        "aat:300008699"
    ]
},
  "bbox": [],
  "geometry": {"coordinates":[-88.3167,33.9167],"type":"Point"}
}