{
  "id": 7345546,
  "type": "Feature",
  "properties": {
    "tgn:hierarchy":[
        "tgn:7345546",
        "tgn:7002836",
        "tgn:7016622",
        "tgn:1000003",
        "tgn:1000095",
        "tgn:7029392"
    ],
    "tgn:id":7345546,
    "tgn:name":"Alcal\u00e1",
    "tgn:placetype":[
        "aat:300008347"
    ]
},
  "bbox": [],
  "geometry": {"coordinates":[-16.816667,28.183333],"type":"Point"}
}