{
  "id": 2483743,
  "type": "Feature",
  "properties": {
    "tgn:hierarchy":[
        "tgn:2483743",
        "tgn:1000001",
        "tgn:7012149",
        "tgn:2000493",
        "tgn:7007250",
        "tgn:7029392"
    ],
    "tgn:id":2483743,
    "tgn:name":"Lateral Number 15",
    "tgn:placetype":[
        "aat:300006075"
    ]
},
  "bbox": [],
  "geometry": {"coordinates":[-114.5167,42.3833],"type":"Point"}
}