{
  "id": 7123954,
  "type": "Feature",
  "properties": {
    "tgn:hierarchy":[
        "tgn:7123954",
        "tgn:7003669",
        "tgn:1000003",
        "tgn:7000084",
        "tgn:7029392"
    ],
    "tgn:id":7123954,
    "tgn:name":"Neuhausen",
    "tgn:placetype":[
        "aat:300008347"
    ]
},
  "bbox": [],
  "geometry": {"coordinates":[11.65,48.433333],"type":"Point"}
}