{
  "id": 2041897,
  "type": "Feature",
  "properties": {
    "tgn:hierarchy":[
        "tgn:2041897",
        "tgn:1000001",
        "tgn:7012149",
        "tgn:1002720",
        "tgn:7007255",
        "tgn:7029392"
    ],
    "tgn:id":2041897,
    "tgn:name":"Weston",
    "tgn:placetype":[
        "aat:300008347",
        "aat:300387210"
    ]
},
  "bbox": [],
  "geometry": {"coordinates":[-83.95,38.2833],"type":"Point"}
}