{
  "id": 2382108,
  "type": "Feature",
  "properties": {
    "tgn:hierarchy":[
        "tgn:2382108",
        "tgn:2000090",
        "tgn:1000001",
        "tgn:7006451",
        "tgn:7012149",
        "tgn:7029392"
    ],
    "tgn:id":2382108,
    "tgn:name":"Hayground Tank Number One",
    "tgn:placetype":[
        "aat:300006191"
    ]
},
  "bbox": [],
  "geometry": {"coordinates":[-109.45,33.8167],"type":"Point"}
}