<<<<<<< HEAD
{
  "id": 7052122,
  "type": "Feature",
  "properties": {
    "tgn:hierarchy":[
        "tgn:7052122",
        "tgn:7015163",
        "tgn:1000003",
        "tgn:7003121",
        "tgn:1000080",
        "tgn:7029392"
    ],
    "tgn:id":7052122,
    "tgn:name":"Mannu, Planu",
    "tgn:placetype":[
        "aat:300386856"
    ]
},
  "bbox": [],
  "geometry": {"coordinates":[8.933333,40.45],"type":"Point"}
}
=======
{"geometry":{"type":"Point","coordinates":[8.933333,40.450000]},"type":"Feature","properties":{"hierarchy":["tgn:7052122","tgn:7015163","tgn:1000003","tgn:7003121","tgn:1000080","tgn:7029392"],"placetype":["aat:300386856"],"id":7052122,"name:xx":"Mannu, Planu"}}
>>>>>>> 03f74aca74312dbeaf24d7e61306dd6a786dc3d0
