{
  "id": 7293786,
  "type": "Feature",
  "properties": {
    "tgn:hierarchy":[
        "tgn:7293786",
        "tgn:7002844",
        "tgn:7030216",
        "tgn:1000003",
        "tgn:1000095",
        "tgn:7029392"
    ],
    "tgn:id":7293786,
    "tgn:name":"Vilardida",
    "tgn:placetype":[
        "aat:300008347"
    ]
},
  "bbox": [],
  "geometry": {"coordinates":[1.363013,41.285903],"type":"Point"}
}