{
  "id": 2557295,
  "type": "Feature",
  "properties": {
    "tgn:hierarchy":[
        "tgn:2557295",
        "tgn:1000001",
        "tgn:7012149",
        "tgn:2000822",
        "tgn:7007255",
        "tgn:7029392"
    ],
    "tgn:id":2557295,
    "tgn:name":"Old Lick Creek",
    "tgn:placetype":[
        "aat:300008706"
    ]
},
  "bbox": [],
  "geometry": {"coordinates":[-85.1333,37.45],"type":"Point"}
}