{
  "id": 7503257,
  "type": "Feature",
  "properties": {
    "tgn:hierarchy":[
        "tgn:7503257",
        "tgn:7487020",
        "tgn:1000004",
        "tgn:1000141",
        "tgn:7029392"
    ],
    "tgn:id":7503257,
    "tgn:name":"Shuizhai",
    "tgn:placetype":[
        "aat:300008347"
    ]
},
  "bbox": [],
  "geometry": {"coordinates":[120.879336,24.344328],"type":"Point"}
}