{
  "id": 7484050,
  "type": "Feature",
  "properties": {
    "tgn:hierarchy":[
        "tgn:7484050",
        "tgn:1000004",
        "tgn:7001009",
        "tgn:1000141",
        "tgn:7029392"
    ],
    "tgn:id":7484050,
    "tgn:name":"Bazihu",
    "tgn:placetype":[
        "aat:300008347"
    ]
},
  "bbox": [],
  "geometry": {"coordinates":[120.669167,24.303056],"type":"Point"}
}