{
  "id": 1061746,
  "type": "Feature",
  "properties": {
    "tgn:hierarchy":[
        "tgn:1061746",
        "tgn:7002758",
        "tgn:7002841",
        "tgn:1000003",
        "tgn:1000095",
        "tgn:7029392"
    ],
    "tgn:id":1061746,
    "tgn:name":"Almad\u00e9n de la Plata",
    "tgn:placetype":[
        "aat:300008347"
    ]
},
  "bbox": [],
  "geometry": {"coordinates":[-6.066667,37.866667],"type":"Point"}
}