<<<<<<< HEAD
{
  "id": 7472034,
  "type": "Feature",
  "properties": {
    "tgn:hierarchy":[
        "tgn:7472034",
        "tgn:1000004",
        "tgn:7467799",
        "tgn:1000141",
        "tgn:7029392"
    ],
    "tgn:id":7472034,
    "tgn:name":"Lunzi",
    "tgn:placetype":[
        "aat:300008347"
    ]
},
  "bbox": [],
  "geometry": {"coordinates":[120.456914,23.905769],"type":"Point"}
}
=======
{"geometry":{"type":"Point","coordinates":[120.456914,23.905769]},"type":"Feature","properties":{"hierarchy":["tgn:7472034","tgn:1000004","tgn:7467799","tgn:1000141","tgn:7029392"],"placetype":["aat:300008347"],"id":7472034,"name:xx":"Lunzi"}}
>>>>>>> 03f74aca74312dbeaf24d7e61306dd6a786dc3d0
