{
  "id": 2240426,
  "type": "Feature",
  "properties": {
    "tgn:hierarchy":[
        "tgn:2240426",
        "tgn:7002659",
        "tgn:1000001",
        "tgn:2000013",
        "tgn:7012149",
        "tgn:7029392"
    ],
    "tgn:id":2240426,
    "tgn:name":"City Lake",
    "tgn:placetype":[
        "aat:300006191"
    ]
},
  "bbox": [],
  "geometry": {"coordinates":[-85.7833,33.3167],"type":"Point"}
}