{
  "id": 7515068,
  "type": "Feature",
  "properties": {
    "tgn:hierarchy":[
        "tgn:7515068",
        "tgn:1009227",
        "tgn:1000226",
        "tgn:7016729",
        "tgn:1000006",
        "tgn:7029392"
    ],
    "tgn:id":7515068,
    "tgn:name:en":"Camp Hill",
    "tgn:placetype":[
        "aat:300008795"
    ]
},
  "bbox": [],
  "geometry": {"coordinates":[173.633333,-41.216667],"type":"Point"}
}