{
  "id": 2027258,
  "type": "Feature",
  "properties": {
    "tgn:hierarchy":[
        "tgn:2027258",
        "tgn:1000001",
        "tgn:7012149",
        "tgn:2000538",
        "tgn:7007251",
        "tgn:7029392"
    ],
    "tgn:id":2027258,
    "tgn:name":"Como",
    "tgn:placetype":[
        "aat:300008347"
    ]
},
  "bbox": [],
  "geometry": {"coordinates":[-89.7667,41.75],"type":"Point"}
}