{
  "id": 7118549,
  "type": "Feature",
  "properties": {
    "tgn:hierarchy":[
        "tgn:7118549",
        "tgn:1000003",
        "tgn:7003688",
        "tgn:7000084",
        "tgn:7029392"
    ],
    "tgn:id":7118549,
    "tgn:name":"Pandertief",
    "tgn:placetype":[
        "aat:300008713"
    ]
},
  "bbox": [],
  "geometry": {"coordinates":[8.433333,54.95],"type":"Point"}
}