{
  "id": 7324814,
  "type": "Feature",
  "properties": {
    "tgn:hierarchy":[
        "tgn:7324814",
        "tgn:7002820",
        "tgn:7030216",
        "tgn:1000003",
        "tgn:1000095",
        "tgn:7029392"
    ],
    "tgn:id":7324814,
    "tgn:name":"San Miguel, Sierra de",
    "tgn:placetype":[
        "aat:300266640"
    ]
},
  "bbox": [],
  "geometry": {"coordinates":[2.408103,42.102641],"type":"Point"}
}