{
  "id": 2754806,
  "type": "Feature",
  "properties": {
    "tgn:hierarchy":[
        "tgn:2754806",
        "tgn:1000001",
        "tgn:7012149",
        "tgn:7029392"
    ],
    "tgn:id":2754806,
    "tgn:name":"Weatherly Branch",
    "tgn:placetype":[
        "aat:300008699"
    ]
},
  "bbox": [],
  "geometry": {"coordinates":[-84.8833,34.9833],"type":"Point"}
}