{
  "id": 7016312,
  "type": "Feature",
  "properties": {
    "tgn:hierarchy":[
        "tgn:7016312",
        "tgn:1000001",
        "tgn:1002246",
        "tgn:7012149",
        "tgn:7007568",
        "tgn:7029392"
    ],
    "tgn:id":7016312,
    "tgn:name":"Sterling",
    "tgn:placetype":[
        "aat:300008347",
        "aat:300387016"
    ]
},
  "bbox": [],
  "geometry": {"coordinates":[-76.6333,43.3167],"type":"Point"}
}