{
  "id": 7421003,
  "type": "Feature",
  "properties": {
    "tgn:hierarchy":[
        "tgn:7421003",
        "tgn:1000001",
        "tgn:7005589",
        "tgn:7005560",
        "tgn:7029392"
    ],
    "tgn:id":7421003,
    "tgn:name:es":"Casa Blanca",
    "tgn:placetype":[
        "aat:300008347"
    ]
},
  "bbox": [],
  "geometry": {"coordinates":[-100.718611,25.671667],"type":"Point"}
}