{
  "id": 2538274,
  "type": "Feature",
  "properties": {
    "tgn:hierarchy":[
        "tgn:2538274",
        "tgn:1000001",
        "tgn:7006451",
        "tgn:7012149",
        "tgn:2000103",
        "tgn:7029392"
    ],
    "tgn:id":2538274,
    "tgn:name":"Nelson Tank",
    "tgn:placetype":[
        "aat:300006191"
    ]
},
  "bbox": [],
  "geometry": {"coordinates":[-112.9333,34.2167],"type":"Point"}
}