{
  "id": 1039873,
  "type": "Feature",
  "properties": {
    "tgn:hierarchy":[
        "tgn:1039873",
        "tgn:7003669",
        "tgn:1000003",
        "tgn:7000084",
        "tgn:7029392"
    ],
    "tgn:id":1039873,
    "tgn:name":"Kirchenthumbach",
    "tgn:placetype":[
        "aat:300008347"
    ]
},
  "bbox": [],
  "geometry": {"coordinates":[11.716667,49.75],"type":"Point"}
}