{
  "id": 2557296,
  "type": "Feature",
  "properties": {
    "tgn:hierarchy":[
        "tgn:2557296",
        "tgn:1000001",
        "tgn:7012149",
        "tgn:2002117",
        "tgn:7007827",
        "tgn:7029392"
    ],
    "tgn:id":2557296,
    "tgn:name":"Old Limber Pine",
    "tgn:placetype":[
        "aat:300008347"
    ]
},
  "bbox": [],
  "geometry": {"coordinates":[-111.4667,41.9167],"type":"Point"}
}