<<<<<<< HEAD
{
  "id": 2401240,
  "type": "Feature",
  "properties": {
    "tgn:hierarchy":[
        "tgn:2401240",
        "tgn:1000001",
        "tgn:7012149",
        "tgn:2002168",
        "tgn:7007919",
        "tgn:7029392"
    ],
    "tgn:id":2401240,
    "tgn:name":"Horsehole Hollow",
    "tgn:placetype":[
        "aat:300008761"
    ]
},
  "bbox": [],
  "geometry": {"coordinates":[-79.4667,38.2167],"type":"Point"}
}
=======
{"geometry":{"type":"Point","coordinates":[-79.466700,38.216700]},"type":"Feature","properties":{"hierarchy":["tgn:2401240","tgn:1000001","tgn:7012149","tgn:2002168","tgn:7007919","tgn:7029392"],"placetype":["aat:300008761"],"id":2401240,"name:xx":"Horsehole Hollow"}}
>>>>>>> 03f74aca74312dbeaf24d7e61306dd6a786dc3d0
