{
  "id": 7029881,
  "type": "Feature",
  "properties": {
    "tgn:hierarchy":[
        "tgn:7029881",
        "tgn:7002445",
        "tgn:1000003",
        "tgn:7008154",
        "tgn:7008591",
        "tgn:7029392"
    ],
    "tgn:id":7029881,
    "tgn:name":"Bracewell",
    "tgn:name:ang":"Braisuelle",
    "tgn:placetype":[
        "aat:300008347",
        "aat:300008372"
    ]
},
  "bbox": [],
  "geometry": {"coordinates":[-2.216667,53.933333],"type":"Point"}
}