{
  "id": 1085804,
  "type": "Feature",
  "properties": {
    "tgn:hierarchy":[
        "tgn:1085804",
        "tgn:7000419",
        "tgn:7018452",
        "tgn:1000004",
        "tgn:1000144",
        "tgn:7029392"
    ],
    "tgn:id":1085804,
    "tgn:name":"\u00c7eltik\u00e7i",
    "tgn:placetype":[
        "aat:300008347"
    ]
},
  "bbox": [],
  "geometry": {"coordinates":[30.4667,37.55],"type":"Point"}
}