{
  "id": 7395021,
  "type": "Feature",
  "properties": {
    "tgn:hierarchy":[
        "tgn:7395021",
        "tgn:1000001",
        "tgn:1001960",
        "tgn:7005560",
        "tgn:7029392"
    ],
    "tgn:id":7395021,
    "tgn:name":"Rancho San Jos\u00e9 de la Ventana",
    "tgn:placetype":[
        "aat:300000241"
    ]
},
  "bbox": [],
  "geometry": {"coordinates":[-109.766667,28.483333],"type":"Point"}
}