{
  "id": 7566534,
  "type": "Feature",
  "properties": {
    "tgn:hierarchy":[
        "tgn:7566534",
        "tgn:1000004",
        "tgn:7000198",
        "tgn:1001894",
        "tgn:7029392"
    ],
    "tgn:id":7566534,
    "tgn:name:en":"Bhainsw\u0101ri Reserved Forest",
    "tgn:placetype":[
        "aat:300008865"
    ]
},
  "bbox": [],
  "geometry": {"coordinates":[79.008853,24.530349],"type":"Point"}
}