{
  "id": 7569375,
  "type": "Feature",
  "properties": {
    "tgn:hierarchy":[
        "tgn:7569375",
        "tgn:1000004",
        "tgn:7000198",
        "tgn:7016722",
        "tgn:7029392"
    ],
    "tgn:id":7569375,
    "tgn:name:en":"Umarpur",
    "tgn:placetype":[
        "aat:300008347"
    ]
},
  "bbox": [],
  "geometry": {"coordinates":[77.472297,29.641684],"type":"Point"}
}