{
  "id": 2036428,
  "type": "Feature",
  "properties": {
    "tgn:hierarchy":[
        "tgn:2036428",
        "tgn:1000001",
        "tgn:7012149",
        "tgn:2000712",
        "tgn:7007254",
        "tgn:7029392"
    ],
    "tgn:id":2036428,
    "tgn:name":"Goldenrod",
    "tgn:placetype":[
        "aat:300387016"
    ]
},
  "bbox": [],
  "geometry": {"coordinates":[-98.2333,39.05],"type":"Point"}
}