{
  "id": 2456234,
  "type": "Feature",
  "properties": {
    "tgn:hierarchy":[
        "tgn:2456234",
        "tgn:1000001",
        "tgn:2001427",
        "tgn:7012149",
        "tgn:7007564",
        "tgn:7029392"
    ],
    "tgn:id":2456234,
    "tgn:name":"Little Home Hill",
    "tgn:placetype":[
        "aat:300008798"
    ]
},
  "bbox": [],
  "geometry": {"coordinates":[-72.35,43.55],"type":"Point"}
}