{
  "id": 2249483,
  "type": "Feature",
  "properties": {
    "tgn:hierarchy":[
        "tgn:2249483",
        "tgn:1002165",
        "tgn:1000001",
        "tgn:7012149",
        "tgn:7007517",
        "tgn:7029392"
    ],
    "tgn:id":2249483,
    "tgn:name":"Coleman Pond",
    "tgn:placetype":[
        "aat:300008680"
    ]
},
  "bbox": [],
  "geometry": {"coordinates":[-70.35,41.6333],"type":"Point"}
}