{
  "id": 7204281,
  "type": "Feature",
  "properties": {
    "tgn:hierarchy":[
        "tgn:7204281",
        "tgn:1000003",
        "tgn:7003676",
        "tgn:7000084",
        "tgn:7029392"
    ],
    "tgn:id":7204281,
    "tgn:name":"Brauerplaten",
    "tgn:placetype":[
        "aat:300387036"
    ]
},
  "bbox": [],
  "geometry": {"coordinates":[6.716667,53.65],"type":"Point"}
}