{
  "id": 2491899,
  "type": "Feature",
  "properties": {
    "tgn:hierarchy":[
        "tgn:2491899",
        "tgn:2000946",
        "tgn:1000001",
        "tgn:7012149",
        "tgn:7007520",
        "tgn:7029392"
    ],
    "tgn:id":2491899,
    "tgn:name":"Marble Drain",
    "tgn:placetype":[
        "aat:300008699"
    ]
},
  "bbox": [],
  "geometry": {"coordinates":[-83.65,44.1167],"type":"Point"}
}