<<<<<<< HEAD
{
  "id": 7476858,
  "type": "Feature",
  "properties": {
    "tgn:hierarchy":[
        "tgn:7476858",
        "tgn:7487020",
        "tgn:1000004",
        "tgn:1000141",
        "tgn:7029392"
    ],
    "tgn:id":7476858,
    "tgn:name":"Wufu Gong",
    "tgn:placetype":[
        "aat:300007595"
    ]
},
  "bbox": [],
  "geometry": {"coordinates":[120.759508,24.612524],"type":"Point"}
}
=======
{"geometry":{"type":"Point","coordinates":[120.759508,24.612524]},"type":"Feature","properties":{"hierarchy":["tgn:7476858","tgn:7487020","tgn:1000004","tgn:1000141","tgn:7029392"],"placetype":["aat:300007595"],"id":7476858,"name:xx":"Wufu Gong"}}
>>>>>>> 03f74aca74312dbeaf24d7e61306dd6a786dc3d0
