{
  "id": 7438097,
  "type": "Feature",
  "properties": {
    "tgn:hierarchy":[
        "tgn:7438097",
        "tgn:1001853",
        "tgn:1000001",
        "tgn:7005560",
        "tgn:7029392"
    ],
    "tgn:id":7438097,
    "tgn:name":"Sauz Mocho",
    "tgn:placetype":[
        "aat:300008347"
    ]
},
  "bbox": [],
  "geometry": {"coordinates":[-101.183333,27.966667],"type":"Point"}
}