{
  "id": 2631765,
  "type": "Feature",
  "properties": {
    "tgn:hierarchy":[
        "tgn:2631765",
        "tgn:1000001",
        "tgn:7012149",
        "tgn:1002528",
        "tgn:7007710",
        "tgn:7029392"
    ],
    "tgn:id":2631765,
    "tgn:name":"Roundtop",
    "tgn:placetype":[
        "aat:300008347"
    ]
},
  "bbox": [],
  "geometry": {"coordinates":[-77.3167,40.65],"type":"Point"}
}