{
  "id": 1057447,
  "type": "Feature",
  "properties": {
    "tgn:hierarchy":[
        "tgn:1057447",
        "tgn:1000003",
        "tgn:7012067",
        "tgn:7006660",
        "tgn:7029392"
    ],
    "tgn:id":1057447,
    "tgn:name":"Nizhnyaya Olkhovaya",
    "tgn:placetype":[
        "aat:300008347"
    ]
},
  "bbox": [],
  "geometry": {"coordinates":[39.5833,48.7333],"type":"Point"}
}