{
  "id": 7143747,
  "type": "Feature",
  "properties": {
    "tgn:hierarchy":[
        "tgn:7143747",
        "tgn:1000003",
        "tgn:7003678",
        "tgn:7000084",
        "tgn:7029392"
    ],
    "tgn:id":7143747,
    "tgn:name":"Kloppenheim",
    "tgn:placetype":[
        "aat:300008347"
    ]
},
  "bbox": [],
  "geometry": {"coordinates":[8.75,50.233333],"type":"Point"}
}