{
  "id": 2658756,
  "type": "Feature",
  "properties": {
    "tgn:hierarchy":[
        "tgn:2658756",
        "tgn:1000001",
        "tgn:7012149",
        "tgn:7029392"
    ],
    "tgn:id":2658756,
    "tgn:name":"Sherman Creek",
    "tgn:placetype":[
        "aat:300008706"
    ]
},
  "bbox": [],
  "geometry": {"coordinates":[-75.4167,41.9333],"type":"Point"}
}