{
  "id": 2446588,
  "type": "Feature",
  "properties": {
    "tgn:hierarchy":[
        "tgn:2446588",
        "tgn:7006450",
        "tgn:1000001",
        "tgn:7012149",
        "tgn:2124014",
        "tgn:7029392"
    ],
    "tgn:id":2446588,
    "tgn:name":"Lewis Rich Channel",
    "tgn:placetype":[
        "aat:300008699"
    ]
},
  "bbox": [],
  "geometry": {"coordinates":[-161.6833,66.7333],"type":"Point"}
}