{
  "id": 2342816,
  "type": "Feature",
  "properties": {
    "tgn:hierarchy":[
        "tgn:2342816",
        "tgn:1000001",
        "tgn:7012149",
        "tgn:2001882",
        "tgn:7007825",
        "tgn:7029392"
    ],
    "tgn:id":2342816,
    "tgn:name":"Furnace Creek",
    "tgn:placetype":[
        "aat:300008706"
    ]
},
  "bbox": [],
  "geometry": {"coordinates":[-81.7833,36.35],"type":"Point"}
}