{
  "id": 2770029,
  "type": "Feature",
  "properties": {
    "tgn:hierarchy":[
        "tgn:2770029",
        "tgn:1000001",
        "tgn:2000774",
        "tgn:7012149",
        "tgn:7007255",
        "tgn:7029392"
    ],
    "tgn:id":2770029,
    "tgn:name":"Wilcox Number 3 Lake",
    "tgn:placetype":[
        "aat:300008680"
    ]
},
  "bbox": [],
  "geometry": {"coordinates":[-85.7667,37.9667],"type":"Point"}
}