<<<<<<< HEAD
{
  "id": 2403817,
  "type": "Feature",
  "properties": {
    "tgn:hierarchy":[
        "tgn:2403817",
        "tgn:1000001",
        "tgn:7012149",
        "tgn:2002342",
        "tgn:7007922",
        "tgn:7029392"
    ],
    "tgn:id":2403817,
    "tgn:name":"Howards Creek",
    "tgn:placetype":[
        "aat:300008706"
    ]
},
  "bbox": [],
  "geometry": {"coordinates":[-89.85,45.8],"type":"Point"}
}
=======
{"geometry":{"type":"Point","coordinates":[-89.850000,45.800000]},"type":"Feature","properties":{"hierarchy":["tgn:2403817","tgn:1000001","tgn:7012149","tgn:2002342","tgn:7007922","tgn:7029392"],"placetype":["aat:300008706"],"id":2403817,"name:xx":"Howards Creek"}}
>>>>>>> 03f74aca74312dbeaf24d7e61306dd6a786dc3d0
