{
  "id": 7374684,
  "type": "Feature",
  "properties": {
    "tgn:hierarchy":[
        "tgn:7374684",
        "tgn:1001835",
        "tgn:1000001",
        "tgn:7005560",
        "tgn:7029392"
    ],
    "tgn:id":7374684,
    "tgn:name":"Rancho La Mesa",
    "tgn:placetype":[
        "aat:300000241"
    ]
},
  "bbox": [],
  "geometry": {"coordinates":[-116.933333,32.333333],"type":"Point"}
}