<<<<<<< HEAD
{
  "id": 2768922,
  "type": "Feature",
  "properties": {
    "tgn:hierarchy":[
        "tgn:2768922",
        "tgn:1000001",
        "tgn:7012149",
        "tgn:7013941",
        "tgn:7007568",
        "tgn:7029392"
    ],
    "tgn:id":2768922,
    "tgn:name":"Whitney Point",
    "tgn:placetype":[
        "aat:300008850"
    ]
},
  "bbox": [],
  "geometry": {"coordinates":[-74.3167,44.3],"type":"Point"}
}
=======
{"geometry":{"type":"Point","coordinates":[-74.316700,44.300000]},"type":"Feature","properties":{"hierarchy":["tgn:2768922","tgn:1000001","tgn:7012149","tgn:7013941","tgn:7007568","tgn:7029392"],"placetype":["aat:300008850"],"id":2768922,"name:xx":"Whitney Point"}}
>>>>>>> 03f74aca74312dbeaf24d7e61306dd6a786dc3d0
