{
  "id": 7138885,
  "type": "Feature",
  "properties": {
    "tgn:hierarchy":[
        "tgn:7138885",
        "tgn:1000003",
        "tgn:7000094",
        "tgn:7000084",
        "tgn:7029392"
    ],
    "tgn:id":7138885,
    "tgn:name":"Libnower M\u00fchlbach",
    "tgn:placetype":[
        "aat:300008699"
    ]
},
  "bbox": [],
  "geometry": {"coordinates":[13.783333,53.866667],"type":"Point"}
}