{
  "id": 7501266,
  "type": "Feature",
  "properties": {
    "tgn:hierarchy":[
        "tgn:7501266",
        "tgn:1000004",
        "tgn:7001009",
        "tgn:1000141",
        "tgn:7029392"
    ],
    "tgn:id":7501266,
    "tgn:name":"Dadu Tifang",
    "tgn:placetype":[
        "aat:300006156"
    ]
},
  "bbox": [],
  "geometry": {"coordinates":[120.5434,24.1284],"type":"Point"}
}