{
  "id": 7327317,
  "type": "Feature",
  "properties": {
    "tgn:hierarchy":[
        "tgn:7327317",
        "tgn:7002835",
        "tgn:7001158",
        "tgn:1000003",
        "tgn:1000095",
        "tgn:7029392"
    ],
    "tgn:id":7327317,
    "tgn:name":"Pedraza de Yeltes",
    "tgn:placetype":[
        "aat:300008347"
    ]
},
  "bbox": [],
  "geometry": {"coordinates":[-6.333333,40.733333],"type":"Point"}
}