{
  "id": 2043542,
  "type": "Feature",
  "properties": {
    "tgn:hierarchy":[
        "tgn:2043542",
        "tgn:1000001",
        "tgn:7012149",
        "tgn:2000908",
        "tgn:7007256",
        "tgn:7029392"
    ],
    "tgn:id":2043542,
    "tgn:name":"Mulberry",
    "tgn:placetype":[
        "aat:300008347",
        "aat:300387210"
    ]
},
  "bbox": [],
  "geometry": {"coordinates":[-90.7167,29.55],"type":"Point"}
}