{
  "id": 2155289,
  "type": "Feature",
  "properties": {
    "tgn:hierarchy":[
        "tgn:2155289",
        "tgn:1000001",
        "tgn:7012149",
        "tgn:7007710",
        "tgn:7029392"
    ],
    "tgn:id":2155289,
    "tgn:name":"Bear Mountain",
    "tgn:placetype":[
        "aat:300008798"
    ]
},
  "bbox": [],
  "geometry": {"coordinates":[-77.2833,40.8833],"type":"Point"}
}