{
  "id": 7070568,
  "type": "Feature",
  "properties": {
    "tgn:hierarchy":[
        "tgn:7070568",
        "tgn:1000003",
        "tgn:7003687",
        "tgn:7000084",
        "tgn:7029392"
    ],
    "tgn:id":7070568,
    "tgn:name":"Steinfelde",
    "tgn:placetype":[
        "aat:300008347"
    ]
},
  "bbox": [],
  "geometry": {"coordinates":[11.783333,52.966667],"type":"Point"}
}