{
  "id": 7286338,
  "type": "Feature",
  "properties": {
    "tgn:hierarchy":[
        "tgn:7286338",
        "tgn:1001699",
        "tgn:1000049",
        "tgn:1000002",
        "tgn:7029392"
    ],
    "tgn:id":7286338,
    "tgn:name":"Holcura, Punta",
    "tgn:placetype":[
        "aat:300386846"
    ]
},
  "bbox": [],
  "geometry": {"coordinates":[-73.466667,-42.433333],"type":"Point"}
}