{
  "id": 2081984,
  "type": "Feature",
  "properties": {
    "tgn:hierarchy":[
        "tgn:2081984",
        "tgn:1000001",
        "tgn:1002307",
        "tgn:7012149",
        "tgn:7007706",
        "tgn:7029392"
    ],
    "tgn:id":2081984,
    "tgn:name":"Spore",
    "tgn:placetype":[
        "aat:300387016"
    ]
},
  "bbox": [],
  "geometry": {"coordinates":[-83.0333,40.85],"type":"Point"}
}