{
  "id": 1137950,
  "type": "Feature",
  "properties": {
    "tgn:hierarchy":[
        "tgn:1137950",
        "tgn:1000004",
        "tgn:7011608",
        "tgn:7018214",
        "tgn:7002435",
        "tgn:7029392"
    ],
    "tgn:id":1137950,
    "tgn:name":"Mikhaylovskoye",
    "tgn:placetype":[
        "aat:300008347"
    ]
},
  "bbox": [],
  "geometry": {"coordinates":[37.6667,58.3833],"type":"Point"}
}