{
  "id": 2450852,
  "type": "Feature",
  "properties": {
    "tgn:hierarchy":[
        "tgn:2450852",
        "tgn:1000001",
        "tgn:7012149",
        "tgn:2002119",
        "tgn:7007827",
        "tgn:7029392"
    ],
    "tgn:id":2450852,
    "tgn:name":"Lisbon Mine",
    "tgn:placetype":[
        "aat:300000390"
    ]
},
  "bbox": [],
  "geometry": {"coordinates":[-109.2667,38.25],"type":"Point"}
}