{
  "id": 7366879,
  "type": "Feature",
  "properties": {
    "tgn:hierarchy":[
        "tgn:7366879",
        "tgn:1000001",
        "tgn:7005596",
        "tgn:7005560",
        "tgn:7029392"
    ],
    "tgn:id":7366879,
    "tgn:name":"Esquipulas",
    "tgn:placetype":[
        "aat:300008347"
    ]
},
  "bbox": [],
  "geometry": {"coordinates":[-93.35,18.116667],"type":"Point"}
}