<<<<<<< HEAD
{
  "id": 7476962,
  "type": "Feature",
  "properties": {
    "tgn:hierarchy":[
        "tgn:7476962",
        "tgn:1000004",
        "tgn:1000454",
        "tgn:1000141",
        "tgn:7029392"
    ],
    "tgn:id":7476962,
    "tgn:name":"Chang'an Gong",
    "tgn:placetype":[
        "aat:300007595"
    ]
},
  "bbox": [],
  "geometry": {"coordinates":[121.915229,25.09162],"type":"Point"}
}
=======
{"geometry":{"type":"Point","coordinates":[121.915229,25.091620]},"type":"Feature","properties":{"hierarchy":["tgn:7476962","tgn:1000004","tgn:1000454","tgn:1000141","tgn:7029392"],"placetype":["aat:300007595"],"id":7476962,"name:xx":"Chang'an Gong"}}
>>>>>>> 03f74aca74312dbeaf24d7e61306dd6a786dc3d0
