{
  "id": 7120655,
  "type": "Feature",
  "properties": {
    "tgn:hierarchy":[
        "tgn:7120655",
        "tgn:7003669",
        "tgn:1000003",
        "tgn:7000084",
        "tgn:7029392"
    ],
    "tgn:id":7120655,
    "tgn:name":"Plattenhof",
    "tgn:placetype":[
        "aat:300000206"
    ]
},
  "bbox": [],
  "geometry": {"coordinates":[13.45,48.733333],"type":"Point"}
}