{
  "id": 2245581,
  "type": "Feature",
  "properties": {
    "tgn:hierarchy":[
        "tgn:2245581",
        "tgn:1000001",
        "tgn:2001267",
        "tgn:7012149",
        "tgn:7007524",
        "tgn:7029392"
    ],
    "tgn:id":2245581,
    "tgn:name":"Coal Banks Landing",
    "tgn:placetype":[
        "aat:300008347"
    ]
},
  "bbox": [],
  "geometry": {"coordinates":[-110.2167,48.0333],"type":"Point"}
}