{
  "id": 2459061,
  "type": "Feature",
  "properties": {
    "tgn:hierarchy":[
        "tgn:2459061",
        "tgn:1000001",
        "tgn:7012149",
        "tgn:1002593",
        "tgn:7007568",
        "tgn:7029392"
    ],
    "tgn:id":2459061,
    "tgn:name":"Little Pine Creek",
    "tgn:placetype":[
        "aat:300008706"
    ]
},
  "bbox": [],
  "geometry": {"coordinates":[-75.1833,43.7333],"type":"Point"}
}