{
  "id": 7370409,
  "type": "Feature",
  "properties": {
    "tgn:hierarchy":[
        "tgn:7370409",
        "tgn:7005583",
        "tgn:1000001",
        "tgn:7005560",
        "tgn:7029392"
    ],
    "tgn:id":7370409,
    "tgn:name":"Huertas, Arroyo de las",
    "tgn:placetype":[
        "aat:300266554",
        "aat:300008699"
    ]
},
  "bbox": [],
  "geometry": {"coordinates":[-105.666667,26.133333],"type":"Point"}
}