{
  "id": 1109326,
  "type": "Feature",
  "properties": {
    "tgn:hierarchy":[
        "tgn:1109326",
        "tgn:1000001",
        "tgn:7005562",
        "tgn:7029392"
    ],
    "tgn:id":1109326,
    "tgn:name":"Maribios, Cordillera de los",
    "tgn:placetype":[
        "aat:300386831"
    ]
},
  "bbox": [],
  "geometry": {"coordinates":[-86.783,12.566],"type":"Point"}
}