{
  "id": 2645086,
  "type": "Feature",
  "properties": {
    "tgn:hierarchy":[
        "tgn:2645086",
        "tgn:1000001",
        "tgn:2000270",
        "tgn:7012149",
        "tgn:7007240",
        "tgn:7029392"
    ],
    "tgn:id":2645086,
    "tgn:name":"Saul Creek",
    "tgn:placetype":[
        "aat:300008706"
    ]
},
  "bbox": [],
  "geometry": {"coordinates":[-85.0667,29.8333],"type":"Point"}
}