{
  "id": 7569285,
  "type": "Feature",
  "properties": {
    "tgn:hierarchy":[
        "tgn:7569285",
        "tgn:1000004",
        "tgn:7000198",
        "tgn:7031786",
        "tgn:7029392"
    ],
    "tgn:id":7569285,
    "tgn:name:en":"Bandhli",
    "tgn:placetype":[
        "aat:300008347"
    ]
},
  "bbox": [],
  "geometry": {"coordinates":[78.623553,29.991761],"type":"Point"}
}