{
  "id": 7044031,
  "type": "Feature",
  "properties": {
    "tgn:hierarchy":[
        "tgn:7044031",
        "tgn:1001730",
        "tgn:1000003",
        "tgn:7003121",
        "tgn:1000080",
        "tgn:7029392"
    ],
    "tgn:id":7044031,
    "tgn:name":"Torre di Capo Mannu",
    "tgn:placetype":[
        "aat:300004847"
    ]
},
  "bbox": [],
  "geometry": {"coordinates":[8.383333,40.033333],"type":"Point"}
}