{
  "id": 2343201,
  "type": "Feature",
  "properties": {
    "tgn:hierarchy":[
        "tgn:2343201",
        "tgn:1000001",
        "tgn:7012149",
        "tgn:2001453",
        "tgn:7007566",
        "tgn:7029392"
    ],
    "tgn:id":2343201,
    "tgn:name":"Gacho Tank",
    "tgn:placetype":[
        "aat:300006191"
    ]
},
  "bbox": [],
  "geometry": {"coordinates":[-103.8667,35.4167],"type":"Point"}
}