{
  "id": 2313139,
  "type": "Feature",
  "properties": {
    "tgn:hierarchy":[
        "tgn:2313139",
        "tgn:1000001",
        "tgn:7012149",
        "tgn:2001125",
        "tgn:7007522",
        "tgn:7029392"
    ],
    "tgn:id":2313139,
    "tgn:name":"Elbow Lake",
    "tgn:placetype":[
        "aat:300008680"
    ]
},
  "bbox": [],
  "geometry": {"coordinates":[-89.6667,32.6667],"type":"Point"}
}