{
  "id": 7439195,
  "type": "Feature",
  "properties": {
    "tgn:hierarchy":[
        "tgn:7439195",
        "tgn:1001835",
        "tgn:1000001",
        "tgn:7005560",
        "tgn:7029392"
    ],
    "tgn:id":7439195,
    "tgn:name":"San Vicente, Valle",
    "tgn:placetype":[
        "aat:300008761"
    ]
},
  "bbox": [],
  "geometry": {"coordinates":[-116.166667,31.333333],"type":"Point"}
}