{
  "id": 7092716,
  "type": "Feature",
  "properties": {
    "tgn:hierarchy":[
        "tgn:7092716",
        "tgn:1000003",
        "tgn:7003677",
        "tgn:7000084",
        "tgn:7029392"
    ],
    "tgn:id":7092716,
    "tgn:name":"Vorbruch",
    "tgn:placetype":[
        "aat:300000206"
    ]
},
  "bbox": [],
  "geometry": {"coordinates":[8.15,52.016667],"type":"Point"}
}