{
  "id": 7189350,
  "type": "Feature",
  "properties": {
    "tgn:hierarchy":[
        "tgn:7189350",
        "tgn:7003669",
        "tgn:1000003",
        "tgn:7000084",
        "tgn:7029392"
    ],
    "tgn:id":7189350,
    "tgn:name":"Eschl-Berg",
    "tgn:placetype":[
        "aat:300008777"
    ]
},
  "bbox": [],
  "geometry": {"coordinates":[12.783333,48.166667],"type":"Point"}
}