{
  "id": 2444561,
  "type": "Feature",
  "properties": {
    "tgn:hierarchy":[
        "tgn:2444561",
        "tgn:1000001",
        "tgn:7012149",
        "tgn:2001514",
        "tgn:7007709",
        "tgn:7029392"
    ],
    "tgn:id":2444561,
    "tgn:name":"Left Prong Catawba River",
    "tgn:placetype":[
        "aat:300008707"
    ]
},
  "bbox": [],
  "geometry": {"coordinates":[-82.25,35.5667],"type":"Point"}
}