{
  "id": 1132180,
  "type": "Feature",
  "properties": {
    "tgn:hierarchy":[
        "tgn:1132180",
        "tgn:1000004",
        "tgn:1000111",
        "tgn:7029392"
    ],
    "tgn:id":1132180,
    "tgn:name":"Zhulong He",
    "tgn:placetype":[
        "aat:300008707"
    ]
},
  "bbox": [],
  "geometry": {"coordinates":[115.9167,38.8333],"type":"Point"}
}