{
  "id": 2514981,
  "type": "Feature",
  "properties": {
    "tgn:hierarchy":[
        "tgn:2514981",
        "tgn:1000001",
        "tgn:7012149",
        "tgn:2002060",
        "tgn:7007826",
        "tgn:7029392"
    ],
    "tgn:id":2514981,
    "tgn:name":"Miller Springs",
    "tgn:placetype":[
        "aat:300008697"
    ]
},
  "bbox": [],
  "geometry": {"coordinates":[-99.8167,29.8833],"type":"Point"}
}