<<<<<<< HEAD
{
  "id": 2259099,
  "type": "Feature",
  "properties": {
    "tgn:hierarchy":[
        "tgn:2259099",
        "tgn:1000001",
        "tgn:2001436",
        "tgn:7012149",
        "tgn:7007566",
        "tgn:7029392"
    ],
    "tgn:id":2259099,
    "tgn:name":"Cottonwood Draw",
    "tgn:placetype":[
        "aat:300008761"
    ]
},
  "bbox": [],
  "geometry": {"coordinates":[-104.3833,32.0667],"type":"Point"}
}
=======
{"geometry":{"type":"Point","coordinates":[-104.383300,32.066700]},"type":"Feature","properties":{"hierarchy":["tgn:2259099","tgn:1000001","tgn:2001436","tgn:7012149","tgn:7007566","tgn:7029392"],"placetype":["aat:300008761"],"id":2259099,"name:xx":"Cottonwood Draw"}}
>>>>>>> 03f74aca74312dbeaf24d7e61306dd6a786dc3d0
