{
  "id": 2303610,
  "type": "Feature",
  "properties": {
    "tgn:hierarchy":[
        "tgn:2303610",
        "tgn:1000001",
        "tgn:7012149",
        "tgn:1003000",
        "tgn:7007520",
        "tgn:7029392"
    ],
    "tgn:id":2303610,
    "tgn:name":"Eagle Lake",
    "tgn:placetype":[
        "aat:300008680"
    ]
},
  "bbox": [],
  "geometry": {"coordinates":[-84.05,42.3833],"type":"Point"}
}