{
  "id": 7587357,
  "type": "Feature",
  "properties": {
    "tgn:hierarchy":[
        "tgn:7587357",
        "tgn:1000004",
        "tgn:7000198",
        "tgn:7000799",
        "tgn:7029392"
    ],
    "tgn:id":7587357,
    "tgn:name:en":"Pohal",
    "tgn:placetype":[
        "aat:300008347"
    ]
},
  "bbox": [],
  "geometry": {"coordinates":[74.888889,34.105556],"type":"Point"}
}