{
  "id": 7181122,
  "type": "Feature",
  "properties": {
    "tgn:hierarchy":[
        "tgn:7181122",
        "tgn:7003692",
        "tgn:1000003",
        "tgn:7000084",
        "tgn:7029392"
    ],
    "tgn:id":7181122,
    "tgn:name":"Fronreute",
    "tgn:placetype":[
        "aat:300000206"
    ]
},
  "bbox": [],
  "geometry": {"coordinates":[9.516667,47.866667],"type":"Point"}
}