{
  "id": 2007203,
  "type": "Feature",
  "properties": {
    "tgn:hierarchy":[
        "tgn:2007203",
        "tgn:1000001",
        "tgn:7006451",
        "tgn:2000095",
        "tgn:7012149",
        "tgn:7029392"
    ],
    "tgn:id":2007203,
    "tgn:name":"Plantsite",
    "tgn:placetype":[
        "aat:300008347"
    ]
},
  "bbox": [],
  "geometry": {"coordinates":[-109.3167,33.05],"type":"Point"}
}