<<<<<<< HEAD
{
  "id": 7369645,
  "type": "Feature",
  "properties": {
    "tgn:hierarchy":[
        "tgn:7369645",
        "tgn:1000001",
        "tgn:1001960",
        "tgn:7005560",
        "tgn:7029392"
    ],
    "tgn:id":7369645,
    "tgn:name":"Rancho Guaguasili",
    "tgn:placetype":[
        "aat:300000241"
    ]
},
  "bbox": [],
  "geometry": {"coordinates":[-108.916667,28.5],"type":"Point"}
}
=======
{"geometry":{"type":"Point","coordinates":[-108.916667,28.500000]},"type":"Feature","properties":{"hierarchy":["tgn:7369645","tgn:1000001","tgn:1001960","tgn:7005560","tgn:7029392"],"placetype":["aat:300000241"],"id":7369645,"name:xx":"Rancho Guaguasili"}}
>>>>>>> 03f74aca74312dbeaf24d7e61306dd6a786dc3d0
