{
  "id": 7034991,
  "type": "Feature",
  "properties": {
    "tgn:hierarchy":[
        "tgn:7034991",
        "tgn:1003488",
        "tgn:1000003",
        "tgn:7002993",
        "tgn:1000080",
        "tgn:7029392"
    ],
    "tgn:id":7034991,
    "tgn:name":"Roppa Buffon, Monte",
    "tgn:placetype":[
        "aat:300008795"
    ]
},
  "bbox": [],
  "geometry": {"coordinates":[12.752778,46.331944],"type":"Point"}
}