{
  "id": 2514552,
  "type": "Feature",
  "properties": {
    "tgn:hierarchy":[
        "tgn:2514552",
        "tgn:1000001",
        "tgn:7012149",
        "tgn:1002920",
        "tgn:7007568",
        "tgn:7029392"
    ],
    "tgn:id":2514552,
    "tgn:name":"Miller Hill",
    "tgn:placetype":[
        "aat:300008798"
    ]
},
  "bbox": [],
  "geometry": {"coordinates":[-77.3833,42.2833],"type":"Point"}
}