{
  "id": 2529561,
  "type": "Feature",
  "properties": {
    "tgn:hierarchy":[
        "tgn:2529561",
        "tgn:1000001",
        "tgn:1002275",
        "tgn:7012149",
        "tgn:7007920",
        "tgn:7029392"
    ],
    "tgn:id":2529561,
    "tgn:name":"Mud Lake",
    "tgn:placetype":[
        "aat:300008680"
    ]
},
  "bbox": [],
  "geometry": {"coordinates":[-122.7167,45.85],"type":"Point"}
}