{
  "id": 7526622,
  "type": "Feature",
  "properties": {
    "tgn:hierarchy":[
        "tgn:7526622",
        "tgn:7001242",
        "tgn:7016833",
        "tgn:1001091",
        "tgn:7029392"
    ],
    "tgn:id":7526622,
    "tgn:name":"Masjid al Anw\u0101r al Mu\u1e29ammad\u012byah",
    "tgn:placetype":[
        "aat:300007544"
    ]
},
  "bbox": [],
  "geometry": {"coordinates":[31.305473,30.115929],"type":"Point"}
}