{
  "id": 7551177,
  "type": "Feature",
  "properties": {
    "tgn:hierarchy":[
        "tgn:7551177",
        "tgn:1000004",
        "tgn:7000198",
        "tgn:7016788",
        "tgn:7029392"
    ],
    "tgn:id":7551177,
    "tgn:name:en":"Diplana",
    "tgn:placetype":[
        "aat:300007783"
    ]
},
  "bbox": [],
  "geometry": {"coordinates":[74.881018,29.182367],"type":"Point"}
}