{
  "id": 2417293,
  "type": "Feature",
  "properties": {
    "tgn:hierarchy":[
        "tgn:2417293",
        "tgn:1000001",
        "tgn:7012149",
        "tgn:7029392"
    ],
    "tgn:id":2417293,
    "tgn:name":"Jacks Creek",
    "tgn:placetype":[
        "aat:300008706"
    ]
},
  "bbox": [],
  "geometry": {"coordinates":[-83.0333,35.0167],"type":"Point"}
}