{
  "id": 2206734,
  "type": "Feature",
  "properties": {
    "tgn:hierarchy":[
        "tgn:2206734",
        "tgn:1000001",
        "tgn:7012149",
        "tgn:2001036",
        "tgn:7007521",
        "tgn:7029392"
    ],
    "tgn:id":2206734,
    "tgn:name":"Bullrush Lake",
    "tgn:placetype":[
        "aat:300008680"
    ]
},
  "bbox": [],
  "geometry": {"coordinates":[-91.25,47.9833],"type":"Point"}
}