{
  "id": 2061610,
  "type": "Feature",
  "properties": {
    "tgn:hierarchy":[
        "tgn:2061610",
        "tgn:1000001",
        "tgn:7012149",
        "tgn:2001309",
        "tgn:7007524",
        "tgn:7029392"
    ],
    "tgn:id":2061610,
    "tgn:name":"Pendroy",
    "tgn:placetype":[
        "aat:300008347"
    ]
},
  "bbox": [],
  "geometry": {"coordinates":[-112.2833,48.0667],"type":"Point"}
}