{
  "id": 7417244,
  "type": "Feature",
  "properties": {
    "tgn:hierarchy":[
        "tgn:7417244",
        "tgn:1000001",
        "tgn:7005596",
        "tgn:7005560",
        "tgn:7029392"
    ],
    "tgn:id":7417244,
    "tgn:name:es":"El Bari Primero",
    "tgn:placetype":[
        "aat:300008347"
    ]
},
  "bbox": [],
  "geometry": {"coordinates":[-94.083333,18.216667],"type":"Point"}
}