{
  "id": 2471312,
  "type": "Feature",
  "properties": {
    "tgn:hierarchy":[
        "tgn:2471312",
        "tgn:2000105",
        "tgn:1000001",
        "tgn:7016172",
        "tgn:7012149",
        "tgn:7029392"
    ],
    "tgn:id":2471312,
    "tgn:name":"Lost Lake",
    "tgn:placetype":[
        "aat:300008680"
    ]
},
  "bbox": [],
  "geometry": {"coordinates":[-91.1167,34.1167],"type":"Point"}
}