<<<<<<< HEAD
{
  "id": 2151436,
  "type": "Feature",
  "properties": {
    "tgn:hierarchy":[
        "tgn:2151436",
        "tgn:1000001",
        "tgn:7012149",
        "tgn:7007157",
        "tgn:1002957",
        "tgn:7029392"
    ],
    "tgn:id":2151436,
    "tgn:name":"Bath Mountain",
    "tgn:placetype":[
        "aat:300008798"
    ]
},
  "bbox": [],
  "geometry": {"coordinates":[-119.45,38.05],"type":"Point"}
}
=======
{"geometry":{"type":"Point","coordinates":[-119.450000,38.050000]},"type":"Feature","properties":{"hierarchy":["tgn:2151436","tgn:1000001","tgn:7012149","tgn:7007157","tgn:1002957","tgn:7029392"],"placetype":["aat:300008798"],"id":2151436,"name:xx":"Bath Mountain"}}
>>>>>>> 03f74aca74312dbeaf24d7e61306dd6a786dc3d0
