<<<<<<< HEAD
{
  "id": 2401682,
  "type": "Feature",
  "properties": {
    "tgn:hierarchy":[
        "tgn:2401682",
        "tgn:1000001",
        "tgn:1002369",
        "tgn:7012149",
        "tgn:7007251",
        "tgn:7029392"
    ],
    "tgn:id":2401682,
    "tgn:name":"Horseshoe Lake",
    "tgn:placetype":[
        "aat:300008680"
    ]
},
  "bbox": [],
  "geometry": {"coordinates":[-89.1,38.9],"type":"Point"}
}
=======
{"geometry":{"type":"Point","coordinates":[-89.100000,38.900000]},"type":"Feature","properties":{"hierarchy":["tgn:2401682","tgn:1000001","tgn:1002369","tgn:7012149","tgn:7007251","tgn:7029392"],"placetype":["aat:300008680"],"id":2401682,"name:xx":"Horseshoe Lake"}}
>>>>>>> 03f74aca74312dbeaf24d7e61306dd6a786dc3d0
