{
  "id": 2280593,
  "type": "Feature",
  "properties": {
    "tgn:hierarchy":[
        "tgn:2280593",
        "tgn:1000001",
        "tgn:7012149",
        "tgn:2001690",
        "tgn:7007707",
        "tgn:7029392"
    ],
    "tgn:id":2280593,
    "tgn:name":"Deep Branch",
    "tgn:placetype":[
        "aat:300008699"
    ]
},
  "bbox": [],
  "geometry": {"coordinates":[-94.9833,35.55],"type":"Point"}
}