{
  "id": 2241588,
  "type": "Feature",
  "properties": {
    "tgn:hierarchy":[
        "tgn:2241588",
        "tgn:1000001",
        "tgn:7012149",
        "tgn:2000828",
        "tgn:7007255",
        "tgn:7029392"
    ],
    "tgn:id":2241588,
    "tgn:name":"Clarks Corner",
    "tgn:placetype":[
        "aat:300008347"
    ]
},
  "bbox": [],
  "geometry": {"coordinates":[-85.65,37.0333],"type":"Point"}
}