{
  "id": 7041703,
  "type": "Feature",
  "properties": {
    "tgn:hierarchy":[
        "tgn:7041703",
        "tgn:7003006",
        "tgn:1000003",
        "tgn:7002997",
        "tgn:1000080",
        "tgn:7029392"
    ],
    "tgn:id":7041703,
    "tgn:name":"San Giorgio di Livenza",
    "tgn:placetype":[
        "aat:300008347"
    ]
},
  "bbox": [],
  "geometry": {"coordinates":[12.787222,45.644167],"type":"Point"}
}