{
  "id": 7593699,
  "type": "Feature",
  "properties": {
    "tgn:hierarchy":[
        "tgn:7593699",
        "tgn:7001242",
        "tgn:7016752",
        "tgn:7029392"
    ],
    "tgn:id":7593699,
    "tgn:name":"Mila",
    "tgn:placetype":[
        "aat:300387064",
        "aat:300000772"
    ]
},
  "bbox": [],
  "geometry": {"coordinates":[6.166,36.416],"type":"Point"}
}