<<<<<<< HEAD
{
  "id": 2409973,
  "type": "Feature",
  "properties": {
    "tgn:hierarchy":[
        "tgn:2409973",
        "tgn:1000001",
        "tgn:2001412",
        "tgn:7012149",
        "tgn:7007526",
        "tgn:7029392"
    ],
    "tgn:id":2409973,
    "tgn:name":"Imperial Mine",
    "tgn:placetype":[
        "aat:300000390"
    ]
},
  "bbox": [],
  "geometry": {"coordinates":[-117.5167,37.55],"type":"Point"}
}
=======
{"geometry":{"type":"Point","coordinates":[-117.516700,37.550000]},"type":"Feature","properties":{"hierarchy":["tgn:2409973","tgn:1000001","tgn:2001412","tgn:7012149","tgn:7007526","tgn:7029392"],"placetype":["aat:300000390"],"id":2409973,"name:xx":"Imperial Mine"}}
>>>>>>> 03f74aca74312dbeaf24d7e61306dd6a786dc3d0
