{
  "id": 2560264,
  "type": "Feature",
  "properties": {
    "tgn:hierarchy":[
        "tgn:2560264",
        "tgn:1000001",
        "tgn:7012149",
        "tgn:2000226",
        "tgn:7007158",
        "tgn:7029392"
    ],
    "tgn:id":2560264,
    "tgn:name":"Orchard Cove",
    "tgn:placetype":[
        "aat:300132316"
    ]
},
  "bbox": [],
  "geometry": {"coordinates":[-105.1667,40.5667],"type":"Point"}
}