{
  "id": 1024710,
  "type": "Feature",
  "properties": {
    "tgn:hierarchy":[
        "tgn:1024710",
        "tgn:1000508",
        "tgn:1000002",
        "tgn:1000056",
        "tgn:7029392"
    ],
    "tgn:id":1024710,
    "tgn:name":"Punta de Bomb\u00f3n",
    "tgn:placetype":[
        "aat:300008347"
    ]
},
  "bbox": [],
  "geometry": {"coordinates":[-71.8333,-17.1667],"type":"Point"}
}