{
  "id": 2613362,
  "type": "Feature",
  "properties": {
    "tgn:hierarchy":[
        "tgn:2613362",
        "tgn:1000001",
        "tgn:2002259",
        "tgn:7012149",
        "tgn:7013961",
        "tgn:7029392"
    ],
    "tgn:id":2613362,
    "tgn:name":"Reed Fork",
    "tgn:placetype":[
        "aat:300008699"
    ]
},
  "bbox": [],
  "geometry": {"coordinates":[-81.1667,38.5167],"type":"Point"}
}