<<<<<<< HEAD
{
  "id": 2404250,
  "type": "Feature",
  "properties": {
    "tgn:hierarchy":[
        "tgn:2404250",
        "tgn:2000919",
        "tgn:1000001",
        "tgn:7012149",
        "tgn:7007515",
        "tgn:7029392"
    ],
    "tgn:id":2404250,
    "tgn:name":"Hoyt Brook",
    "tgn:placetype":[
        "aat:300008699"
    ]
},
  "bbox": [],
  "geometry": {"coordinates":[-67.8667,46.3167],"type":"Point"}
}
=======
{"geometry":{"type":"Point","coordinates":[-67.866700,46.316700]},"type":"Feature","properties":{"hierarchy":["tgn:2404250","tgn:2000919","tgn:1000001","tgn:7012149","tgn:7007515","tgn:7029392"],"placetype":["aat:300008699"],"id":2404250,"name:xx":"Hoyt Brook"}}
>>>>>>> 03f74aca74312dbeaf24d7e61306dd6a786dc3d0
