{
  "id": 7320433,
  "type": "Feature",
  "properties": {
    "tgn:hierarchy":[
        "tgn:7320433",
        "tgn:1001702",
        "tgn:1000049",
        "tgn:1000002",
        "tgn:7029392"
    ],
    "tgn:id":7320433,
    "tgn:name":"Barrancas, Banco",
    "tgn:placetype":[
        "aat:300387036"
    ]
},
  "bbox": [],
  "geometry": {"coordinates":[-69.85,-52.533333],"type":"Point"}
}