{
  "id": 2041879,
  "type": "Feature",
  "properties": {
    "tgn:hierarchy":[
        "tgn:2041879",
        "tgn:1000001",
        "tgn:7012149",
        "tgn:2000811",
        "tgn:7007255",
        "tgn:7029392"
    ],
    "tgn:id":2041879,
    "tgn:name":"Wendover",
    "tgn:placetype":[
        "aat:300008347"
    ]
},
  "bbox": [],
  "geometry": {"coordinates":[-83.35,37.1167],"type":"Point"}
}