<<<<<<< HEAD
{
  "id": 7362662,
  "type": "Feature",
  "properties": {
    "tgn:hierarchy":[
        "tgn:7362662",
        "tgn:1000001",
        "tgn:7005589",
        "tgn:7005560",
        "tgn:7029392"
    ],
    "tgn:id":7362662,
    "tgn:name":"El Ebanito",
    "tgn:placetype":[
        "aat:300008347"
    ]
},
  "bbox": [],
  "geometry": {"coordinates":[-99.816667,25.116667],"type":"Point"}
}
=======
{"geometry":{"type":"Point","coordinates":[-99.816667,25.116667]},"type":"Feature","properties":{"hierarchy":["tgn:7362662","tgn:1000001","tgn:7005589","tgn:7005560","tgn:7029392"],"placetype":["aat:300008347"],"id":7362662,"name:xx":"El Ebanito"}}
>>>>>>> 03f74aca74312dbeaf24d7e61306dd6a786dc3d0
