{
  "id": 7324418,
  "type": "Feature",
  "properties": {
    "tgn:hierarchy":[
        "tgn:7324418",
        "tgn:7002758",
        "tgn:7002823",
        "tgn:1000003",
        "tgn:1000095",
        "tgn:7029392"
    ],
    "tgn:id":7324418,
    "tgn:name":"Sebo, Punta del",
    "tgn:placetype":[
        "aat:300386846"
    ]
},
  "bbox": [],
  "geometry": {"coordinates":[-6.933333,37.216667],"type":"Point"}
}