{
  "id": 2126112,
  "type": "Feature",
  "properties": {
    "tgn:hierarchy":[
        "tgn:2126112",
        "tgn:1000001",
        "tgn:7012149",
        "tgn:2000980",
        "tgn:7007520",
        "tgn:7029392"
    ],
    "tgn:id":2126112,
    "tgn:name":"Addis Creek",
    "tgn:placetype":[
        "aat:300008706"
    ]
},
  "bbox": [],
  "geometry": {"coordinates":[-84.9833,44.4167],"type":"Point"}
}