{
  "id": 7313954,
  "type": "Feature",
  "properties": {
    "tgn:hierarchy":[
        "tgn:7313954",
        "tgn:1001695",
        "tgn:1000049",
        "tgn:1000002",
        "tgn:7029392"
    ],
    "tgn:id":7313954,
    "tgn:name":"Los Maquis",
    "tgn:placetype":[
        "aat:300008777"
    ]
},
  "bbox": [],
  "geometry": {"coordinates":[-71.85,-34.216667],"type":"Point"}
}