<<<<<<< HEAD
{
  "id": 2251772,
  "type": "Feature",
  "properties": {
    "tgn:hierarchy":[
        "tgn:2251772",
        "tgn:1000001",
        "tgn:7012149",
        "tgn:2000911",
        "tgn:7007256",
        "tgn:7029392"
    ],
    "tgn:id":2251772,
    "tgn:name":"Comrade",
    "tgn:placetype":[
        "aat:300008347"
    ]
},
  "bbox": [],
  "geometry": {"coordinates":[-92.95,31.3167],"type":"Point"}
}
=======
{"geometry":{"type":"Point","coordinates":[-92.950000,31.316700]},"type":"Feature","properties":{"hierarchy":["tgn:2251772","tgn:1000001","tgn:7012149","tgn:2000911","tgn:7007256","tgn:7029392"],"placetype":["aat:300008347"],"id":2251772,"name:xx":"Comrade"}}
>>>>>>> 03f74aca74312dbeaf24d7e61306dd6a786dc3d0
