{
  "id": 2251772,
  "type": "Feature",
  "properties": {
    "tgn:hierarchy":[
        "tgn:2251772",
        "tgn:1000001",
        "tgn:7012149",
        "tgn:2000911",
        "tgn:7007256",
        "tgn:7029392"
    ],
    "tgn:id":2251772,
    "tgn:name":"Comrade",
    "tgn:placetype":[
        "aat:300008347"
    ]
},
  "bbox": [],
  "geometry": {"coordinates":[-92.95,31.3167],"type":"Point"}
}