{
  "id": 2590789,
  "type": "Feature",
  "properties": {
    "tgn:hierarchy":[
        "tgn:2590789",
        "tgn:1000001",
        "tgn:7012149",
        "tgn:2001879",
        "tgn:7007825",
        "tgn:7029392"
    ],
    "tgn:id":2590789,
    "tgn:name":"Polecat",
    "tgn:placetype":[
        "aat:300008347"
    ]
},
  "bbox": [],
  "geometry": {"coordinates":[-87.8667,35.95],"type":"Point"}
}