{
  "id": 7429623,
  "type": "Feature",
  "properties": {
    "tgn:hierarchy":[
        "tgn:7429623",
        "tgn:1001853",
        "tgn:1000001",
        "tgn:7005560",
        "tgn:7029392"
    ],
    "tgn:id":7429623,
    "tgn:name":"La Encantada de Guadalupe",
    "tgn:placetype":[
        "aat:300008347"
    ]
},
  "bbox": [],
  "geometry": {"coordinates":[-102.183333,25.766667],"type":"Point"}
}