<<<<<<< HEAD
{
  "id": 2154454,
  "type": "Feature",
  "properties": {
    "tgn:hierarchy":[
        "tgn:2154454",
        "tgn:1000001",
        "tgn:7012149",
        "tgn:2002347",
        "tgn:7007922",
        "tgn:7029392"
    ],
    "tgn:id":2154454,
    "tgn:name":"Bear Creek",
    "tgn:placetype":[
        "aat:300008706"
    ]
},
  "bbox": [],
  "geometry": {"coordinates":[-89.3833,44.4333],"type":"Point"}
}
=======
{"geometry":{"type":"Point","coordinates":[-89.383300,44.433300]},"type":"Feature","properties":{"hierarchy":["tgn:2154454","tgn:1000001","tgn:7012149","tgn:2002347","tgn:7007922","tgn:7029392"],"placetype":["aat:300008706"],"id":2154454,"name:xx":"Bear Creek"}}
>>>>>>> 03f74aca74312dbeaf24d7e61306dd6a786dc3d0
