{
  "id": 7325234,
  "type": "Feature",
  "properties": {
    "tgn:hierarchy":[
        "tgn:7325234",
        "tgn:7002832",
        "tgn:7001158",
        "tgn:1000003",
        "tgn:1000095",
        "tgn:7029392"
    ],
    "tgn:id":7325234,
    "tgn:name":"San Mart\u00edn del Valle",
    "tgn:placetype":[
        "aat:300008347"
    ]
},
  "bbox": [],
  "geometry": {"coordinates":[-4.783333,42.433333],"type":"Point"}
}