{
  "id": 2620920,
  "type": "Feature",
  "properties": {
    "tgn:hierarchy":[
        "tgn:2620920",
        "tgn:1000001",
        "tgn:7012149",
        "tgn:1003033",
        "tgn:7007706",
        "tgn:7029392"
    ],
    "tgn:id":2620920,
    "tgn:name":"Roachton",
    "tgn:placetype":[
        "aat:300008347"
    ]
},
  "bbox": [],
  "geometry": {"coordinates":[-83.65,41.5167],"type":"Point"}
}