{
  "id": 2335870,
  "type": "Feature",
  "properties": {
    "tgn:hierarchy":[
        "tgn:2335870",
        "tgn:1000001",
        "tgn:7012149",
        "tgn:1002785",
        "tgn:7007920",
        "tgn:7029392"
    ],
    "tgn:id":2335870,
    "tgn:name":"Foss Hill",
    "tgn:placetype":[
        "aat:300008798"
    ]
},
  "bbox": [],
  "geometry": {"coordinates":[-122.6333,47.0333],"type":"Point"}
}