{
  "id": 2785351,
  "type": "Feature",
  "properties": {
    "tgn:hierarchy":[
        "tgn:2785351",
        "tgn:1000001",
        "tgn:7012149",
        "tgn:2001455",
        "tgn:7007566",
        "tgn:7029392"
    ],
    "tgn:id":2785351,
    "tgn:name":"Yellowjacket Mine Number 1",
    "tgn:placetype":[
        "aat:300000390"
    ]
},
  "bbox": [],
  "geometry": {"coordinates":[-107.2167,33.0833],"type":"Point"}
}