{
  "id": 7492665,
  "type": "Feature",
  "properties": {
    "tgn:hierarchy":[
        "tgn:7492665",
        "tgn:1000004",
        "tgn:7001014",
        "tgn:1000141",
        "tgn:7029392"
    ],
    "tgn:id":7492665,
    "tgn:name":"Suqin",
    "tgn:placetype":[
        "aat:300008347"
    ]
},
  "bbox": [],
  "geometry": {"coordinates":[120.262778,23.621111],"type":"Point"}
}