{
  "id": 2366374,
  "type": "Feature",
  "properties": {
    "tgn:hierarchy":[
        "tgn:2366374",
        "tgn:1000001",
        "tgn:7012149",
        "tgn:2001722",
        "tgn:7007708",
        "tgn:7029392"
    ],
    "tgn:id":2366374,
    "tgn:name":"Griffith Creek",
    "tgn:placetype":[
        "aat:300008706"
    ]
},
  "bbox": [],
  "geometry": {"coordinates":[-117.0667,45.25],"type":"Point"}
}