{
  "id": 2637332,
  "type": "Feature",
  "properties": {
    "tgn:hierarchy":[
        "tgn:2637332",
        "tgn:1000001",
        "tgn:7012149",
        "tgn:1002545",
        "tgn:7007157",
        "tgn:7029392"
    ],
    "tgn:id":2637332,
    "tgn:name":"Saint John Mine",
    "tgn:placetype":[
        "aat:300000390"
    ]
},
  "bbox": [],
  "geometry": {"coordinates":[-118.2167,35.45],"type":"Point"}
}