{
  "id": 2454118,
  "type": "Feature",
  "properties": {
    "tgn:hierarchy":[
        "tgn:2454118",
        "tgn:1000001",
        "tgn:7012149",
        "tgn:1002924",
        "tgn:7007568",
        "tgn:7029392"
    ],
    "tgn:id":2454118,
    "tgn:name":"Little Creek",
    "tgn:placetype":[
        "aat:300008706"
    ]
},
  "bbox": [],
  "geometry": {"coordinates":[-72.45,41.0167],"type":"Point"}
}