{
  "id": 1112046,
  "type": "Feature",
  "properties": {
    "tgn:hierarchy":[
        "tgn:1112046",
        "tgn:7015163",
        "tgn:1000003",
        "tgn:7003121",
        "tgn:1000080",
        "tgn:7029392"
    ],
    "tgn:id":1112046,
    "tgn:name":"La Nurra",
    "tgn:placetype":[
        "aat:300055621",
        "aat:300387346"
    ]
},
  "bbox": [],
  "geometry": {"coordinates":[8.25,40.75],"type":"Point"}
}