{
  "id": 2276217,
  "type": "Feature",
  "properties": {
    "tgn:hierarchy":[
        "tgn:2276217",
        "tgn:1000001",
        "tgn:7012149",
        "tgn:2001713",
        "tgn:7007708",
        "tgn:7029392"
    ],
    "tgn:id":2276217,
    "tgn:name":"Dasher Meadow",
    "tgn:placetype":[
        "aat:300055621"
    ]
},
  "bbox": [],
  "geometry": {"coordinates":[-123.75,42.3667],"type":"Point"}
}