<<<<<<< HEAD
{
  "id": 2257572,
  "type": "Feature",
  "properties": {
    "tgn:hierarchy":[
        "tgn:2257572",
        "tgn:1000001",
        "tgn:7012149",
        "tgn:1003042",
        "tgn:7007920",
        "tgn:7029392"
    ],
    "tgn:id":2257572,
    "tgn:name":"Corral Canyon",
    "tgn:placetype":[
        "aat:300008761"
    ]
},
  "bbox": [],
  "geometry": {"coordinates":[-120.1,46.6833],"type":"Point"}
}
=======
{"geometry":{"type":"Point","coordinates":[-120.100000,46.683300]},"type":"Feature","properties":{"hierarchy":["tgn:2257572","tgn:1000001","tgn:7012149","tgn:1003042","tgn:7007920","tgn:7029392"],"placetype":["aat:300008761"],"id":2257572,"name:xx":"Corral Canyon"}}
>>>>>>> 03f74aca74312dbeaf24d7e61306dd6a786dc3d0
