{
  "id": 7244186,
  "type": "Feature",
  "properties": {
    "tgn:hierarchy":[
        "tgn:7244186",
        "tgn:7003461",
        "tgn:1000003",
        "tgn:1000063",
        "tgn:7018236",
        "tgn:7029392"
    ],
    "tgn:id":7244186,
    "tgn:name":"Kapelbeek",
    "tgn:placetype":[
        "aat:300008699"
    ]
},
  "bbox": [],
  "geometry": {"coordinates":[5.066667,50.916667],"type":"Point"}
}