{
  "id": 2751142,
  "type": "Feature",
  "properties": {
    "tgn:hierarchy":[
        "tgn:2751142",
        "tgn:1000001",
        "tgn:2002256",
        "tgn:7012149",
        "tgn:7013961",
        "tgn:7029392"
    ],
    "tgn:id":2751142,
    "tgn:name":"Ware Mountain",
    "tgn:placetype":[
        "aat:300008798"
    ]
},
  "bbox": [],
  "geometry": {"coordinates":[-80.5333,38.6167],"type":"Point"}
}