{
  "id": 2269583,
  "type": "Feature",
  "properties": {
    "tgn:hierarchy":[
        "tgn:2269583",
        "tgn:1000001",
        "tgn:7012149",
        "tgn:1002749",
        "tgn:7007240",
        "tgn:7029392"
    ],
    "tgn:id":2269583,
    "tgn:name":"Crowell, Lake",
    "tgn:placetype":[
        "aat:300008680"
    ]
},
  "bbox": [],
  "geometry": {"coordinates":[-81.4833,28.4167],"type":"Point"}
}