{
  "id": 2461389,
  "type": "Feature",
  "properties": {
    "tgn:hierarchy":[
        "tgn:2461389",
        "tgn:1000001",
        "tgn:2001175",
        "tgn:7012149",
        "tgn:7007523",
        "tgn:7029392"
    ],
    "tgn:id":2461389,
    "tgn:name":"Little Sugar Creek",
    "tgn:placetype":[
        "aat:300008706"
    ]
},
  "bbox": [],
  "geometry": {"coordinates":[-94.9167,39.5833],"type":"Point"}
}