{
  "id": 7590565,
  "type": "Feature",
  "properties": {
    "tgn:hierarchy":[
        "tgn:7590565",
        "tgn:1000004",
        "tgn:7000198",
        "tgn:7000799",
        "tgn:7029392"
    ],
    "tgn:id":7590565,
    "tgn:name:en":"Lanji Bhurji",
    "tgn:placetype":[
        "aat:300008347"
    ]
},
  "bbox": [],
  "geometry": {"coordinates":[74.357333,33.87398],"type":"Point"}
}