{
  "id": 2661911,
  "type": "Feature",
  "properties": {
    "tgn:hierarchy":[
        "tgn:2661911",
        "tgn:1000001",
        "tgn:7012149",
        "tgn:1002553",
        "tgn:7007920",
        "tgn:7029392"
    ],
    "tgn:id":2661911,
    "tgn:name":"Shushuskin Canyon",
    "tgn:placetype":[
        "aat:300008761"
    ]
},
  "bbox": [],
  "geometry": {"coordinates":[-120.5667,46.9167],"type":"Point"}
}