<<<<<<< HEAD
{
  "id": 2153126,
  "type": "Feature",
  "properties": {
    "tgn:hierarchy":[
        "tgn:2153126",
        "tgn:2002130",
        "tgn:1000001",
        "tgn:7012149",
        "tgn:7007828",
        "tgn:7029392"
    ],
    "tgn:id":2153126,
    "tgn:name":"Beadles Cove",
    "tgn:placetype":[
        "aat:300132316"
    ]
},
  "bbox": [],
  "geometry": {"coordinates":[-73.3667,43.85],"type":"Point"}
}
=======
{"geometry":{"type":"Point","coordinates":[-73.366700,43.850000]},"type":"Feature","properties":{"hierarchy":["tgn:2153126","tgn:2002130","tgn:1000001","tgn:7012149","tgn:7007828","tgn:7029392"],"placetype":["aat:300132316"],"id":2153126,"name:xx":"Beadles Cove"}}
>>>>>>> 03f74aca74312dbeaf24d7e61306dd6a786dc3d0
