{
  "id": 2153126,
  "type": "Feature",
  "properties": {
    "tgn:hierarchy":[
        "tgn:2153126",
        "tgn:2002130",
        "tgn:1000001",
        "tgn:7012149",
        "tgn:7007828",
        "tgn:7029392"
    ],
    "tgn:id":2153126,
    "tgn:name":"Beadles Cove",
    "tgn:placetype":[
        "aat:300132316"
    ]
},
  "bbox": [],
  "geometry": {"coordinates":[-73.3667,43.85],"type":"Point"}
}