{
  "id": 7150536,
  "type": "Feature",
  "properties": {
    "tgn:hierarchy":[
        "tgn:7150536",
        "tgn:1000003",
        "tgn:7003678",
        "tgn:7000084",
        "tgn:7029392"
    ],
    "tgn:id":7150536,
    "tgn:name":"Kr\u00f6ckelbach",
    "tgn:placetype":[
        "aat:300008347"
    ]
},
  "bbox": [],
  "geometry": {"coordinates":[8.801944,49.6575],"type":"Point"}
}