{
  "id": 2089768,
  "type": "Feature",
  "properties": {
    "tgn:hierarchy":[
        "tgn:2089768",
        "tgn:1000001",
        "tgn:7012149",
        "tgn:2001724",
        "tgn:7007710",
        "tgn:7029392"
    ],
    "tgn:id":2089768,
    "tgn:name":"Khedive",
    "tgn:placetype":[
        "aat:300008347"
    ]
},
  "bbox": [],
  "geometry": {"coordinates":[-80.0333,39.8833],"type":"Point"}
}