{
  "id": 1064168,
  "type": "Feature",
  "properties": {
    "tgn:hierarchy":[
        "tgn:1064168",
        "tgn:7003748",
        "tgn:1000003",
        "tgn:7011731",
        "tgn:7029392"
    ],
    "tgn:id":1064168,
    "tgn:name":"Langwies",
    "tgn:placetype":[
        "aat:300008347"
    ]
},
  "bbox": [],
  "geometry": {"coordinates":[9.7333,46.8333],"type":"Point"}
}