{
  "id": 7349880,
  "type": "Feature",
  "properties": {
    "tgn:hierarchy":[
        "tgn:7349880",
        "tgn:7005586",
        "tgn:1000001",
        "tgn:7005560",
        "tgn:7029392"
    ],
    "tgn:id":7349880,
    "tgn:name":"Agua Zarca",
    "tgn:placetype":[
        "aat:300008347"
    ]
},
  "bbox": [],
  "geometry": {"coordinates":[-104.983333,19.583333],"type":"Point"}
}