{
  "id": 2638971,
  "type": "Feature",
  "properties": {
    "tgn:hierarchy":[
        "tgn:2638971",
        "tgn:1000001",
        "tgn:7012149",
        "tgn:2000182",
        "tgn:7007157",
        "tgn:7029392"
    ],
    "tgn:id":2638971,
    "tgn:name":"Salt Creek Slough",
    "tgn:placetype":[
        "aat:300008706"
    ]
},
  "bbox": [],
  "geometry": {"coordinates":[-115.7333,32.7667],"type":"Point"}
}