{
  "id": 7534416,
  "type": "Feature",
  "properties": {
    "tgn:hierarchy":[
        "tgn:7534416",
        "tgn:7001242",
        "tgn:1001075",
        "tgn:7016833",
        "tgn:7029392"
    ],
    "tgn:id":7534416,
    "tgn:name:en":"\u0162\u012bbah",
    "tgn:placetype":[
        "aat:300008347"
    ]
},
  "bbox": [],
  "geometry": {"coordinates":[30.481247,30.835097],"type":"Point"}
}