{
  "id": 2724344,
  "type": "Feature",
  "properties": {
    "tgn:hierarchy":[
        "tgn:2724344",
        "tgn:1000001",
        "tgn:7006451",
        "tgn:7012149",
        "tgn:2000098",
        "tgn:7029392"
    ],
    "tgn:id":2724344,
    "tgn:name":"Tom Lamb Reservoir",
    "tgn:placetype":[
        "aat:300006191"
    ]
},
  "bbox": [],
  "geometry": {"coordinates":[-112.7667,36.65],"type":"Point"}
}