{
  "id": 7058059,
  "type": "Feature",
  "properties": {
    "tgn:hierarchy":[
        "tgn:7058059",
        "tgn:1003471",
        "tgn:1000003",
        "tgn:7003240",
        "tgn:1000080",
        "tgn:7029392"
    ],
    "tgn:id":7058059,
    "tgn:name":"Appignano",
    "tgn:placetype":[
        "aat:300008347"
    ]
},
  "bbox": [],
  "geometry": {"coordinates":[13.333333,43.35],"type":"Point"}
}