{
  "id": 1111774,
  "type": "Feature",
  "properties": {
    "tgn:hierarchy":[
        "tgn:1111774",
        "tgn:7002444",
        "tgn:1000003",
        "tgn:7008082",
        "tgn:7008591",
        "tgn:7029392"
    ],
    "tgn:id":1111774,
    "tgn:name:en":"Spean, Glen",
    "tgn:placetype":[
        "aat:300008761"
    ]
},
  "bbox": [],
  "geometry": {"coordinates":[-4.75,56.883333],"type":"Point"}
}