{
  "id": 7010736,
  "type": "Feature",
  "properties": {
    "tgn:hierarchy":[
        "tgn:7010736",
        "tgn:7006448",
        "tgn:1000003",
        "tgn:7006417",
        "tgn:7029392"
    ],
    "tgn:id":7010736,
    "tgn:name":"Butrint",
    "tgn:placetype":[
        "aat:300008347",
        "aat:300000810",
        "aat:300167671",
        "aat:300263063"
    ]
},
  "bbox": [],
  "geometry": {"coordinates":[20.033,39.75],"type":"Point"}
}