{
  "id": 2398228,
  "type": "Feature",
  "properties": {
    "tgn:hierarchy":[
        "tgn:2398228",
        "tgn:1000001",
        "tgn:2001016",
        "tgn:7012149",
        "tgn:7007521",
        "tgn:7029392"
    ],
    "tgn:id":2398228,
    "tgn:name":"Hooligans Hole",
    "tgn:placetype":[
        "aat:300008680"
    ]
},
  "bbox": [],
  "geometry": {"coordinates":[-94.15,46.6667],"type":"Point"}
}