{
  "id": 2505030,
  "type": "Feature",
  "properties": {
    "tgn:hierarchy":[
        "tgn:2505030",
        "tgn:7013272",
        "tgn:1000001",
        "tgn:7012149",
        "tgn:7007710",
        "tgn:7029392"
    ],
    "tgn:id":2505030,
    "tgn:name":"Meeks Run",
    "tgn:placetype":[
        "aat:300008699"
    ]
},
  "bbox": [],
  "geometry": {"coordinates":[-80.1833,40.4833],"type":"Point"}
}