{
  "id": 2371685,
  "type": "Feature",
  "properties": {
    "tgn:hierarchy":[
        "tgn:2371685",
        "tgn:1000001",
        "tgn:7012149",
        "tgn:2000232",
        "tgn:7007158",
        "tgn:7029392"
    ],
    "tgn:id":2371685,
    "tgn:name":"Hale Gulch",
    "tgn:placetype":[
        "aat:300008761"
    ]
},
  "bbox": [],
  "geometry": {"coordinates":[-108.0333,40.3333],"type":"Point"}
}