{
  "id": 2227423,
  "type": "Feature",
  "properties": {
    "tgn:hierarchy":[
        "tgn:2227423",
        "tgn:1000001",
        "tgn:7012149",
        "tgn:2001909",
        "tgn:7007825",
        "tgn:7029392"
    ],
    "tgn:id":2227423,
    "tgn:name":"Cave Spring",
    "tgn:placetype":[
        "aat:300008697"
    ]
},
  "bbox": [],
  "geometry": {"coordinates":[-84.6333,35.85],"type":"Point"}
}