<<<<<<< HEAD
{
  "id": 7029349,
  "type": "Feature",
  "properties": {
    "tgn:hierarchy":[
        "tgn:7029349",
        "tgn:7002445",
        "tgn:1000003",
        "tgn:7019057",
        "tgn:7008591",
        "tgn:7029392"
    ],
    "tgn:id":7029349,
    "tgn:name:en":"Sigglesthorne",
    "tgn:placetype":[
        "aat:300008347",
        "aat:300008372"
    ]
},
  "bbox": [],
  "geometry": {"coordinates":[-0.233333,53.9],"type":"Point"}
}
=======
{"geometry":{"type":"Point","coordinates":[-0.233333,53.900000]},"type":"Feature","properties":{"hierarchy":["tgn:7029349","tgn:7002445","tgn:1000003","tgn:7019057","tgn:7008591","tgn:7029392"],"placetype":["aat:300008347","aat:300008372"],"name:en":"Sigglesthorne","id":7029349}}
>>>>>>> 03f74aca74312dbeaf24d7e61306dd6a786dc3d0
