{
  "id": 7392104,
  "type": "Feature",
  "properties": {
    "tgn:hierarchy":[
        "tgn:7392104",
        "tgn:1000001",
        "tgn:7005597",
        "tgn:7005560",
        "tgn:7029392"
    ],
    "tgn:id":7392104,
    "tgn:name":"Rancho Viveros",
    "tgn:placetype":[
        "aat:300008347"
    ]
},
  "bbox": [],
  "geometry": {"coordinates":[-99.4975,24.430833],"type":"Point"}
}