{
  "id": 2748152,
  "type": "Feature",
  "properties": {
    "tgn:hierarchy":[
        "tgn:2748152",
        "tgn:1000001",
        "tgn:7012149",
        "tgn:2001714",
        "tgn:7007708",
        "tgn:7029392"
    ],
    "tgn:id":2748152,
    "tgn:name":"Walker Basin Canal",
    "tgn:placetype":[
        "aat:300006075"
    ]
},
  "bbox": [],
  "geometry": {"coordinates":[-121.5667,43.5833],"type":"Point"}
}