{
  "id": 2566826,
  "type": "Feature",
  "properties": {
    "tgn:hierarchy":[
        "tgn:2566826",
        "tgn:1000001",
        "tgn:7012149",
        "tgn:2001207",
        "tgn:7007523",
        "tgn:7029392"
    ],
    "tgn:id":2566826,
    "tgn:name":"Panther Branch",
    "tgn:placetype":[
        "aat:300008699"
    ]
},
  "bbox": [],
  "geometry": {"coordinates":[-90.9167,37.6667],"type":"Point"}
}