<<<<<<< HEAD
{
  "id": 7362102,
  "type": "Feature",
  "properties": {
    "tgn:hierarchy":[
        "tgn:7362102",
        "tgn:7005581",
        "tgn:1000001",
        "tgn:7005560",
        "tgn:7029392"
    ],
    "tgn:id":7362102,
    "tgn:name":"El Derramadero de Abajo",
    "tgn:placetype":[
        "aat:300008347"
    ]
},
  "bbox": [],
  "geometry": {"coordinates":[-106.783333,28.35],"type":"Point"}
}
=======
{"geometry":{"type":"Point","coordinates":[-106.783333,28.350000]},"type":"Feature","properties":{"hierarchy":["tgn:7362102","tgn:7005581","tgn:1000001","tgn:7005560","tgn:7029392"],"placetype":["aat:300008347"],"id":7362102,"name:xx":"El Derramadero de Abajo"}}
>>>>>>> 03f74aca74312dbeaf24d7e61306dd6a786dc3d0
