{
  "id": 7033478,
  "type": "Feature",
  "properties": {
    "tgn:hierarchy":[
        "tgn:7033478",
        "tgn:1003460",
        "tgn:1000003",
        "tgn:7009760",
        "tgn:1000080",
        "tgn:7029392"
    ],
    "tgn:id":7033478,
    "tgn:name":"Isola Rossa, Scoglio",
    "tgn:placetype":[
        "aat:300011692"
    ]
},
  "bbox": [],
  "geometry": {"coordinates":[11.131667,42.377778],"type":"Point"}
}