{
  "id": 2328771,
  "type": "Feature",
  "properties": {
    "tgn:hierarchy":[
        "tgn:2328771",
        "tgn:7030516",
        "tgn:7006450",
        "tgn:1000001",
        "tgn:7012149",
        "tgn:7029392"
    ],
    "tgn:id":2328771,
    "tgn:name":"Fishhook Ridge",
    "tgn:placetype":[
        "aat:300266640"
    ]
},
  "bbox": [],
  "geometry": {"coordinates":[173.1833,52.9167],"type":"Point"}
}