{
  "id": 2363200,
  "type": "Feature",
  "properties": {
    "tgn:hierarchy":[
        "tgn:2363200",
        "tgn:1000001",
        "tgn:7016172",
        "tgn:7012149",
        "tgn:2000164",
        "tgn:7029392"
    ],
    "tgn:id":2363200,
    "tgn:name":"Green Bear Lake",
    "tgn:placetype":[
        "aat:300006191"
    ]
},
  "bbox": [],
  "geometry": {"coordinates":[-92.4833,34.7167],"type":"Point"}
}