{
  "id": 2434042,
  "type": "Feature",
  "properties": {
    "tgn:hierarchy":[
        "tgn:2434042",
        "tgn:1000001",
        "tgn:7012149",
        "tgn:7007157",
        "tgn:1002608",
        "tgn:1008999",
        "tgn:7029392"
    ],
    "tgn:id":2434042,
    "tgn:name":"Kelp Point",
    "tgn:placetype":[
        "aat:300008850"
    ]
},
  "bbox": [],
  "geometry": {"coordinates":[-118.5333,33.4333],"type":"Point"}
}