{
  "id": 1099437,
  "type": "Feature",
  "properties": {
    "tgn:hierarchy":[
        "tgn:1099437",
        "tgn:1000826",
        "tgn:7006160",
        "tgn:1000006",
        "tgn:7029392"
    ],
    "tgn:id":1099437,
    "tgn:name":"Boru",
    "tgn:placetype":[
        "aat:300008347"
    ]
},
  "bbox": [],
  "geometry": {"coordinates":[148.8333,-10.25],"type":"Point"}
}