{
  "id": 2163460,
  "type": "Feature",
  "properties": {
    "tgn:hierarchy":[
        "tgn:2163460",
        "tgn:1000001",
        "tgn:1002488",
        "tgn:7012149",
        "tgn:7007516",
        "tgn:7029392"
    ],
    "tgn:id":2163460,
    "tgn:name":"Benson Branch",
    "tgn:placetype":[
        "aat:300008699"
    ]
},
  "bbox": [],
  "geometry": {"coordinates":[-76.9667,39.25],"type":"Point"}
}