<<<<<<< HEAD
{
  "id": 2256217,
  "type": "Feature",
  "properties": {
    "tgn:hierarchy":[
        "tgn:2256217",
        "tgn:1000001",
        "tgn:7012149",
        "tgn:1002837",
        "tgn:7007255",
        "tgn:7029392"
    ],
    "tgn:id":2256217,
    "tgn:name":"Copperas Branch",
    "tgn:placetype":[
        "aat:300008699"
    ]
},
  "bbox": [],
  "geometry": {"coordinates":[-83.5,38.2167],"type":"Point"}
}
=======
{"geometry":{"type":"Point","coordinates":[-83.500000,38.216700]},"type":"Feature","properties":{"hierarchy":["tgn:2256217","tgn:1000001","tgn:7012149","tgn:1002837","tgn:7007255","tgn:7029392"],"placetype":["aat:300008699"],"id":2256217,"name:xx":"Copperas Branch"}}
>>>>>>> 03f74aca74312dbeaf24d7e61306dd6a786dc3d0
