{
  "id": 2516743,
  "type": "Feature",
  "properties": {
    "tgn:hierarchy":[
        "tgn:2516743",
        "tgn:7006450",
        "tgn:1000001",
        "tgn:7012149",
        "tgn:2000086",
        "tgn:7029392"
    ],
    "tgn:id":2516743,
    "tgn:name":"Miners Lake",
    "tgn:placetype":[
        "aat:300008680"
    ]
},
  "bbox": [],
  "geometry": {"coordinates":[-147.4333,61.0667],"type":"Point"}
}