{
  "id": 7532047,
  "type": "Feature",
  "properties": {
    "tgn:hierarchy":[
        "tgn:7532047",
        "tgn:7001242",
        "tgn:7016833",
        "tgn:1001335",
        "tgn:7029392"
    ],
    "tgn:id":7532047,
    "tgn:name:en":"S\u00eedi el-Marz\u00fbqi",
    "tgn:placetype":[
        "aat:300005926"
    ]
},
  "bbox": [],
  "geometry": {"coordinates":[31.144167,31.575556],"type":"Point"}
}