{
  "id": 7502949,
  "type": "Feature",
  "properties": {
    "tgn:hierarchy":[
        "tgn:7502949",
        "tgn:1000004",
        "tgn:7491221",
        "tgn:1000141",
        "tgn:7029392"
    ],
    "tgn:id":7502949,
    "tgn:name":"Haiduan Erhao Ti",
    "tgn:placetype":[
        "aat:300006156"
    ]
},
  "bbox": [],
  "geometry": {"coordinates":[121.181944,23.113056],"type":"Point"}
}