{
  "id": 2062607,
  "type": "Feature",
  "properties": {
    "tgn:hierarchy":[
        "tgn:2062607",
        "tgn:1000001",
        "tgn:7012149",
        "tgn:2001396",
        "tgn:7007525",
        "tgn:7029392"
    ],
    "tgn:id":2062607,
    "tgn:name":"Rushville",
    "tgn:placetype":[
        "aat:300008347"
    ]
},
  "bbox": [],
  "geometry": {"coordinates":[-102.45,42.7167],"type":"Point"}
}