{
  "id": 2009460,
  "type": "Feature",
  "properties": {
    "tgn:hierarchy":[
        "tgn:2009460",
        "tgn:1000001",
        "tgn:7016172",
        "tgn:2000120",
        "tgn:7012149",
        "tgn:7029392"
    ],
    "tgn:id":2009460,
    "tgn:name":"Schug",
    "tgn:placetype":[
        "aat:300008347",
        "aat:300387210"
    ]
},
  "bbox": [],
  "geometry": {"coordinates":[-90.4333,35.95],"type":"Point"}
}