{
  "id": 2626624,
  "type": "Feature",
  "properties": {
    "tgn:hierarchy":[
        "tgn:2626624",
        "tgn:1000001",
        "tgn:7012149",
        "tgn:7007157",
        "tgn:2000188",
        "tgn:7029392"
    ],
    "tgn:id":2626624,
    "tgn:name":"Rocky Ledge Butte",
    "tgn:placetype":[
        "aat:300008798"
    ]
},
  "bbox": [],
  "geometry": {"coordinates":[-121.6167,40.85],"type":"Point"}
}