<<<<<<< HEAD
{
  "id": 2155378,
  "type": "Feature",
  "properties": {
    "tgn:hierarchy":[
        "tgn:2155378",
        "tgn:1000001",
        "tgn:7012149",
        "tgn:2001195",
        "tgn:7007523",
        "tgn:7029392"
    ],
    "tgn:id":2155378,
    "tgn:name":"Bear Pen Hollow",
    "tgn:placetype":[
        "aat:300008761"
    ]
},
  "bbox": [],
  "geometry": {"coordinates":[-91.2667,37.4833],"type":"Point"}
}
=======
{"geometry":{"type":"Point","coordinates":[-91.266700,37.483300]},"type":"Feature","properties":{"hierarchy":["tgn:2155378","tgn:1000001","tgn:7012149","tgn:2001195","tgn:7007523","tgn:7029392"],"placetype":["aat:300008761"],"id":2155378,"name:xx":"Bear Pen Hollow"}}
>>>>>>> 03f74aca74312dbeaf24d7e61306dd6a786dc3d0
