{
  "id": 2712193,
  "type": "Feature",
  "properties": {
    "tgn:hierarchy":[
        "tgn:2712193",
        "tgn:1000001",
        "tgn:7012149",
        "tgn:2002008",
        "tgn:7007826",
        "tgn:7029392"
    ],
    "tgn:id":2712193,
    "tgn:name":"Tater Hill",
    "tgn:placetype":[
        "aat:300008798"
    ]
},
  "bbox": [],
  "geometry": {"coordinates":[-98.2833,33.2167],"type":"Point"}
}