{
  "id": 2016051,
  "type": "Feature",
  "properties": {
    "tgn:hierarchy":[
        "tgn:2016051",
        "tgn:1000001",
        "tgn:7012149",
        "tgn:2000234",
        "tgn:7007158",
        "tgn:7029392"
    ],
    "tgn:id":2016051,
    "tgn:name":"Nucla",
    "tgn:placetype":[
        "aat:300008347"
    ]
},
  "bbox": [],
  "geometry": {"coordinates":[-108.5333,38.2667],"type":"Point"}
}