{
  "id": 2432483,
  "type": "Feature",
  "properties": {
    "tgn:hierarchy":[
        "tgn:2432483",
        "tgn:7023902",
        "tgn:1000001",
        "tgn:7012149",
        "tgn:7007249",
        "tgn:7029392"
    ],
    "tgn:id":2432483,
    "tgn:name":"Keaweiki",
    "tgn:placetype":[
        "aat:300008850"
    ]
},
  "bbox": [],
  "geometry": {"coordinates":[-155.9167,19.4667],"type":"Point"}
}