{
  "id": 1036654,
  "type": "Feature",
  "properties": {
    "tgn:hierarchy":[
        "tgn:1036654",
        "tgn:1000003",
        "tgn:7003687",
        "tgn:7000084",
        "tgn:7029392"
    ],
    "tgn:id":1036654,
    "tgn:name":"Elend",
    "tgn:placetype":[
        "aat:300008347"
    ]
},
  "bbox": [],
  "geometry": {"coordinates":[10.683333,51.733333],"type":"Point"}
}