{
  "id": 2672180,
  "type": "Feature",
  "properties": {
    "tgn:hierarchy":[
        "tgn:2672180",
        "tgn:2001726",
        "tgn:1000001",
        "tgn:7012149",
        "tgn:7007712",
        "tgn:7029392"
    ],
    "tgn:id":2672180,
    "tgn:name":"Smiths Lake",
    "tgn:placetype":[
        "aat:300006191"
    ]
},
  "bbox": [],
  "geometry": {"coordinates":[-81.7833,33.6667],"type":"Point"}
}