{
  "id": 2380893,
  "type": "Feature",
  "properties": {
    "tgn:hierarchy":[
        "tgn:2380893",
        "tgn:7006450",
        "tgn:1000001",
        "tgn:7012149",
        "tgn:7019760",
        "tgn:7029392"
    ],
    "tgn:id":2380893,
    "tgn:name":"Hawk Point",
    "tgn:placetype":[
        "aat:300008850"
    ]
},
  "bbox": [],
  "geometry": {"coordinates":[-134.7667,58.0833],"type":"Point"}
}