{
  "id": 2002811,
  "type": "Feature",
  "properties": {
    "tgn:hierarchy":[
        "tgn:2002811",
        "tgn:7002659",
        "tgn:1000001",
        "tgn:2000004",
        "tgn:7012149",
        "tgn:7029392"
    ],
    "tgn:id":2002811,
    "tgn:name":"Blount Springs",
    "tgn:placetype":[
        "aat:300008347"
    ]
},
  "bbox": [],
  "geometry": {"coordinates":[-86.7833,33.9167],"type":"Point"}
}