{
  "id": 2142057,
  "type": "Feature",
  "properties": {
    "tgn:hierarchy":[
        "tgn:2142057",
        "tgn:1000001",
        "tgn:1002493",
        "tgn:7012149",
        "tgn:7007565",
        "tgn:7029392"
    ],
    "tgn:id":2142057,
    "tgn:name":"Back Brook",
    "tgn:placetype":[
        "aat:300008699"
    ]
},
  "bbox": [],
  "geometry": {"coordinates":[-74.8667,40.4167],"type":"Point"}
}