{
  "id": 7136071,
  "type": "Feature",
  "properties": {
    "tgn:hierarchy":[
        "tgn:7136071",
        "tgn:7000096",
        "tgn:1000003",
        "tgn:7000084",
        "tgn:7029392"
    ],
    "tgn:id":7136071,
    "tgn:name":"M\u00fctzlitzer Wiesen",
    "tgn:placetype":[
        "aat:300386990"
    ]
},
  "bbox": [],
  "geometry": {"coordinates":[12.516667,52.566667],"type":"Point"}
}