{
  "id": 1103595,
  "type": "Feature",
  "properties": {
    "tgn:hierarchy":[
        "tgn:1103595",
        "tgn:7016674",
        "tgn:1000004",
        "tgn:1000120",
        "tgn:7029392"
    ],
    "tgn:id":1103595,
    "tgn:name":"\u014cyorogi-san",
    "tgn:placetype":[
        "aat:300008795"
    ]
},
  "bbox": [],
  "geometry": {"coordinates":[132.85,35.0833],"type":"Point"}
}