{
  "id": 2352558,
  "type": "Feature",
  "properties": {
    "tgn:hierarchy":[
        "tgn:2352558",
        "tgn:1000001",
        "tgn:7012149",
        "tgn:2001279",
        "tgn:7007524",
        "tgn:7029392"
    ],
    "tgn:id":2352558,
    "tgn:name":"Goat Mountain",
    "tgn:placetype":[
        "aat:300008798"
    ]
},
  "bbox": [],
  "geometry": {"coordinates":[-113.05,46.3833],"type":"Point"}
}