{
  "id": 2121507,
  "type": "Feature",
  "properties": {
    "tgn:hierarchy":[
        "tgn:2121507",
        "tgn:1000001",
        "tgn:7012149",
        "tgn:2002333",
        "tgn:7007922",
        "tgn:7029392"
    ],
    "tgn:id":2121507,
    "tgn:name":"Kempster",
    "tgn:placetype":[
        "aat:300008347"
    ]
},
  "bbox": [],
  "geometry": {"coordinates":[-89.1667,45.2833],"type":"Point"}
}