{
  "id": 7562969,
  "type": "Feature",
  "properties": {
    "tgn:hierarchy":[
        "tgn:7562969",
        "tgn:1000004",
        "tgn:7000198",
        "tgn:7016722",
        "tgn:7029392"
    ],
    "tgn:id":7562969,
    "tgn:name:en":"R\u0101mpur",
    "tgn:placetype":[
        "aat:300008347"
    ]
},
  "bbox": [],
  "geometry": {"coordinates":[79.462327,27.048873],"type":"Point"}
}