{
  "id": 7427346,
  "type": "Feature",
  "properties": {
    "tgn:hierarchy":[
        "tgn:7427346",
        "tgn:1000001",
        "tgn:7005601",
        "tgn:7005560",
        "tgn:7029392"
    ],
    "tgn:id":7427346,
    "tgn:name":"San Jos\u00e9 de los Ranchos",
    "tgn:placetype":[
        "aat:300008347"
    ]
},
  "bbox": [],
  "geometry": {"coordinates":[-103.783333,23.466667],"type":"Point"}
}