{
  "id": 2579417,
  "type": "Feature",
  "properties": {
    "tgn:hierarchy":[
        "tgn:2579417",
        "tgn:1000001",
        "tgn:7012149",
        "tgn:2002359",
        "tgn:7007922",
        "tgn:7029392"
    ],
    "tgn:id":2579417,
    "tgn:name":"Pickerel Lake",
    "tgn:placetype":[
        "aat:300008680"
    ]
},
  "bbox": [],
  "geometry": {"coordinates":[-89.3833,45.9667],"type":"Point"}
}