{
  "id": 7011075,
  "type": "Feature",
  "properties": {
    "tgn:hierarchy":[
        "tgn:7011075",
        "tgn:7002445",
        "tgn:1000003",
        "tgn:7012034",
        "tgn:7008591",
        "tgn:7029392"
    ],
    "tgn:id":7011075,
    "tgn:name:en":"Broseley",
    "tgn:placetype":[
        "aat:300008347"
    ]
},
  "bbox": [],
  "geometry": {"coordinates":[-2.483333,52.616667],"type":"Point"}
}