{
  "id": 7323863,
  "type": "Feature",
  "properties": {
    "tgn:hierarchy":[
        "tgn:7323863",
        "tgn:7002810",
        "tgn:7001158",
        "tgn:1000003",
        "tgn:1000095",
        "tgn:7029392"
    ],
    "tgn:id":7323863,
    "tgn:name":"R\u00edoseras, R\u00edo",
    "tgn:placetype":[
        "aat:300008699"
    ]
},
  "bbox": [],
  "geometry": {"coordinates":[-3.683333,42.433333],"type":"Point"}
}