{
  "id": 2672144,
  "type": "Feature",
  "properties": {
    "tgn:hierarchy":[
        "tgn:2672144",
        "tgn:1000001",
        "tgn:7012149",
        "tgn:1002397",
        "tgn:7007568",
        "tgn:7029392"
    ],
    "tgn:id":2672144,
    "tgn:name":"Smiths Corners",
    "tgn:placetype":[
        "aat:300008347"
    ]
},
  "bbox": [],
  "geometry": {"coordinates":[-74.3667,43.05],"type":"Point"}
}