{
  "id": 2234512,
  "type": "Feature",
  "properties": {
    "tgn:hierarchy":[
        "tgn:2234512",
        "tgn:1000001",
        "tgn:2001014",
        "tgn:7012149",
        "tgn:7007521",
        "tgn:7029392"
    ],
    "tgn:id":2234512,
    "tgn:name":"Cherokee Creek",
    "tgn:placetype":[
        "aat:300008706"
    ]
},
  "bbox": [],
  "geometry": {"coordinates":[-90.8333,47.9333],"type":"Point"}
}