{
  "id": 1080945,
  "type": "Feature",
  "properties": {
    "tgn:hierarchy":[
        "tgn:1080945",
        "tgn:1000980",
        "tgn:1000004",
        "tgn:7000894",
        "tgn:1000120",
        "tgn:7029392"
    ],
    "tgn:id":1080945,
    "tgn:name":"Nakanoj\u014d",
    "tgn:placetype":[
        "aat:300008347"
    ]
},
  "bbox": [],
  "geometry": {"coordinates":[138.8333,36.5833],"type":"Point"}
}