{
  "id": 7522341,
  "type": "Feature",
  "properties": {
    "tgn:hierarchy":[
        "tgn:7522341",
        "tgn:7001242",
        "tgn:7016833",
        "tgn:1001418",
        "tgn:7029392"
    ],
    "tgn:id":7522341,
    "tgn:name:en":"Daww\u0101r al \u1e28\u0101jj Rasl\u0101n",
    "tgn:placetype":[
        "aat:300008347"
    ]
},
  "bbox": [],
  "geometry": {"coordinates":[29.433333,30.766667],"type":"Point"}
}