{
  "id": 7498017,
  "type": "Feature",
  "properties": {
    "tgn:hierarchy":[
        "tgn:7498017",
        "tgn:1000957",
        "tgn:1000004",
        "tgn:1000141",
        "tgn:7029392"
    ],
    "tgn:id":7498017,
    "tgn:name":"Baifu Guozhong",
    "tgn:placetype":[
        "aat:300006495"
    ]
},
  "bbox": [],
  "geometry": {"coordinates":[121.697842,25.082812],"type":"Point"}
}