<<<<<<< HEAD
{
  "id": 2258126,
  "type": "Feature",
  "properties": {
    "tgn:hierarchy":[
        "tgn:2258126",
        "tgn:1000001",
        "tgn:7012149",
        "tgn:2000910",
        "tgn:7007256",
        "tgn:7029392"
    ],
    "tgn:id":2258126,
    "tgn:name":"Cossinade",
    "tgn:placetype":[
        "aat:300008347"
    ]
},
  "bbox": [],
  "geometry": {"coordinates":[-92.3167,30.0333],"type":"Point"}
}
=======
{"geometry":{"type":"Point","coordinates":[-92.316700,30.033300]},"type":"Feature","properties":{"hierarchy":["tgn:2258126","tgn:1000001","tgn:7012149","tgn:2000910","tgn:7007256","tgn:7029392"],"placetype":["aat:300008347"],"id":2258126,"name:xx":"Cossinade"}}
>>>>>>> 03f74aca74312dbeaf24d7e61306dd6a786dc3d0
