{
  "id": 2258126,
  "type": "Feature",
  "properties": {
    "tgn:hierarchy":[
        "tgn:2258126",
        "tgn:1000001",
        "tgn:7012149",
        "tgn:2000910",
        "tgn:7007256",
        "tgn:7029392"
    ],
    "tgn:id":2258126,
    "tgn:name":"Cossinade",
    "tgn:placetype":[
        "aat:300008347"
    ]
},
  "bbox": [],
  "geometry": {"coordinates":[-92.3167,30.0333],"type":"Point"}
}