{
  "id": 2749640,
  "type": "Feature",
  "properties": {
    "tgn:hierarchy":[
        "tgn:2749640",
        "tgn:1000001",
        "tgn:7012149",
        "tgn:1002966",
        "tgn:7007826",
        "tgn:7029392"
    ],
    "tgn:id":2749640,
    "tgn:name":"Walnut Creek",
    "tgn:placetype":[
        "aat:300008706"
    ]
},
  "bbox": [],
  "geometry": {"coordinates":[-94.7333,32.7333],"type":"Point"}
}