{
  "id": 2778210,
  "type": "Feature",
  "properties": {
    "tgn:hierarchy":[
        "tgn:2778210",
        "tgn:1000001",
        "tgn:7012149",
        "tgn:2002195",
        "tgn:7007919",
        "tgn:7029392"
    ],
    "tgn:id":2778210,
    "tgn:name":"Wise, Lake",
    "tgn:placetype":[
        "aat:300008680"
    ]
},
  "bbox": [],
  "geometry": {"coordinates":[-82.5167,36.9667],"type":"Point"}
}