{
  "id": 2235563,
  "type": "Feature",
  "properties": {
    "tgn:hierarchy":[
        "tgn:2235563",
        "tgn:1000001",
        "tgn:2001474",
        "tgn:7012149",
        "tgn:7007709",
        "tgn:7029392"
    ],
    "tgn:id":2235563,
    "tgn:name":"Chestnut Flat Branch",
    "tgn:placetype":[
        "aat:300008699"
    ]
},
  "bbox": [],
  "geometry": {"coordinates":[-81.7667,35.6167],"type":"Point"}
}