{
  "id": 7245426,
  "type": "Feature",
  "properties": {
    "tgn:hierarchy":[
        "tgn:7245426",
        "tgn:7007877",
        "tgn:1000003",
        "tgn:1000063",
        "tgn:4012014",
        "tgn:7029392"
    ],
    "tgn:id":7245426,
    "tgn:name":"Bassilly",
    "tgn:placetype":[
        "aat:300008347"
    ]
},
  "bbox": [],
  "geometry": {"coordinates":[3.93661,50.672607],"type":"Point"}
}