{
  "id": 2451701,
  "type": "Feature",
  "properties": {
    "tgn:hierarchy":[
        "tgn:2451701",
        "tgn:1000001",
        "tgn:7012149",
        "tgn:7007157",
        "tgn:1002957",
        "tgn:7029392"
    ],
    "tgn:id":2451701,
    "tgn:name":"Little Bear Lake",
    "tgn:placetype":[
        "aat:300008680"
    ]
},
  "bbox": [],
  "geometry": {"coordinates":[-119.7833,38.0667],"type":"Point"}
}