{
  "id": 2329790,
  "type": "Feature",
  "properties": {
    "tgn:hierarchy":[
        "tgn:2329790",
        "tgn:1000001",
        "tgn:2001414",
        "tgn:7012149",
        "tgn:7007526",
        "tgn:7029392"
    ],
    "tgn:id":2329790,
    "tgn:name":"Fivemile Spring",
    "tgn:placetype":[
        "aat:300008697"
    ]
},
  "bbox": [],
  "geometry": {"coordinates":[-119.0833,41.5833],"type":"Point"}
}