{
  "id": 7473719,
  "type": "Feature",
  "properties": {
    "tgn:hierarchy":[
        "tgn:7473719",
        "tgn:1000004",
        "tgn:1000454",
        "tgn:1000141",
        "tgn:7029392"
    ],
    "tgn:id":7473719,
    "tgn:name":"Fulu Qiao",
    "tgn:placetype":[
        "aat:300007836"
    ]
},
  "bbox": [],
  "geometry": {"coordinates":[121.676236,24.96716],"type":"Point"}
}