{
  "id": 2516899,
  "type": "Feature",
  "properties": {
    "tgn:hierarchy":[
        "tgn:2516899",
        "tgn:1000001",
        "tgn:7012149",
        "tgn:2001503",
        "tgn:7007709",
        "tgn:7029392"
    ],
    "tgn:id":2516899,
    "tgn:name":"Mingus Ridge",
    "tgn:placetype":[
        "aat:300266640"
    ]
},
  "bbox": [],
  "geometry": {"coordinates":[-83.0833,35.45],"type":"Point"}
}