<<<<<<< HEAD
{
  "id": 7365162,
  "type": "Feature",
  "properties": {
    "tgn:hierarchy":[
        "tgn:7365162",
        "tgn:1000001",
        "tgn:7005590",
        "tgn:7005560",
        "tgn:7029392"
    ],
    "tgn:id":7365162,
    "tgn:name":"Francisco Villa",
    "tgn:placetype":[
        "aat:300008347"
    ]
},
  "bbox": [],
  "geometry": {"coordinates":[-102.566667,19.083333],"type":"Point"}
}
=======
{"geometry":{"type":"Point","coordinates":[-102.566667,19.083333]},"type":"Feature","properties":{"hierarchy":["tgn:7365162","tgn:1000001","tgn:7005590","tgn:7005560","tgn:7029392"],"placetype":["aat:300008347"],"id":7365162,"name:xx":"Francisco Villa"}}
>>>>>>> 03f74aca74312dbeaf24d7e61306dd6a786dc3d0
