{
  "id": 7433281,
  "type": "Feature",
  "properties": {
    "tgn:hierarchy":[
        "tgn:7433281",
        "tgn:1000001",
        "tgn:7005592",
        "tgn:7005560",
        "tgn:7029392"
    ],
    "tgn:id":7433281,
    "tgn:name":"Tlacuilotepec",
    "tgn:placetype":[
        "aat:300008347"
    ]
},
  "bbox": [],
  "geometry": {"coordinates":[-98.066667,20.333333],"type":"Point"}
}