{
  "id": 2280406,
  "type": "Feature",
  "properties": {
    "tgn:hierarchy":[
        "tgn:2280406",
        "tgn:1000001",
        "tgn:7012149",
        "tgn:1002645",
        "tgn:7007920",
        "tgn:7029392"
    ],
    "tgn:id":2280406,
    "tgn:name":"Decker Creek",
    "tgn:placetype":[
        "aat:300008706"
    ]
},
  "bbox": [],
  "geometry": {"coordinates":[-123.45,47.25],"type":"Point"}
}