{
  "id": 2562507,
  "type": "Feature",
  "properties": {
    "tgn:hierarchy":[
        "tgn:2562507",
        "tgn:1000001",
        "tgn:7012149",
        "tgn:7007522",
        "tgn:7029392"
    ],
    "tgn:id":2562507,
    "tgn:name":"Ousley Creek",
    "tgn:placetype":[
        "aat:300008706"
    ]
},
  "bbox": [],
  "geometry": {"coordinates":[-89.7333,32.8333],"type":"Point"}
}