{
  "id": 7285336,
  "type": "Feature",
  "properties": {
    "tgn:hierarchy":[
        "tgn:7285336",
        "tgn:1001623",
        "tgn:1000049",
        "tgn:1000002",
        "tgn:7029392"
    ],
    "tgn:id":7285336,
    "tgn:name":"Pocha, Punta",
    "tgn:placetype":[
        "aat:300386846"
    ]
},
  "bbox": [],
  "geometry": {"coordinates":[-74.483333,-47.366667],"type":"Point"}
}