{
  "id": 2021869,
  "type": "Feature",
  "properties": {
    "tgn:hierarchy":[
        "tgn:2021869",
        "tgn:1000001",
        "tgn:7012149",
        "tgn:2000338",
        "tgn:7007248",
        "tgn:7029392"
    ],
    "tgn:id":2021869,
    "tgn:name":"Acree",
    "tgn:placetype":[
        "aat:300008347"
    ]
},
  "bbox": [],
  "geometry": {"coordinates":[-83.9833,31.55],"type":"Point"}
}