{
  "id": 2521523,
  "type": "Feature",
  "properties": {
    "tgn:hierarchy":[
        "tgn:2521523",
        "tgn:1000001",
        "tgn:7012149",
        "tgn:2001496",
        "tgn:7007709",
        "tgn:7029392"
    ],
    "tgn:id":2521523,
    "tgn:name":"Monticello Woods",
    "tgn:placetype":[
        "aat:300008347"
    ]
},
  "bbox": [],
  "geometry": {"coordinates":[-81.1167,35.2333],"type":"Point"}
}