{
  "id": 2604510,
  "type": "Feature",
  "properties": {
    "tgn:hierarchy":[
        "tgn:2604510",
        "tgn:1000001",
        "tgn:2001009",
        "tgn:7012149",
        "tgn:7007521",
        "tgn:7029392"
    ],
    "tgn:id":2604510,
    "tgn:name":"Rabbit Lake",
    "tgn:placetype":[
        "aat:300008680"
    ]
},
  "bbox": [],
  "geometry": {"coordinates":[-94.1333,47.0667],"type":"Point"}
}