{
  "id": 2325794,
  "type": "Feature",
  "properties": {
    "tgn:hierarchy":[
        "tgn:2325794",
        "tgn:1000001",
        "tgn:7012149",
        "tgn:7015666",
        "tgn:7007825",
        "tgn:7029392"
    ],
    "tgn:id":2325794,
    "tgn:name":"Fielders Branch",
    "tgn:placetype":[
        "aat:300008699"
    ]
},
  "bbox": [],
  "geometry": {"coordinates":[-87.3833,35.75],"type":"Point"}
}