{
  "id": 7287328,
  "type": "Feature",
  "properties": {
    "tgn:hierarchy":[
        "tgn:7287328",
        "tgn:1001623",
        "tgn:1000049",
        "tgn:1000002",
        "tgn:7029392"
    ],
    "tgn:id":7287328,
    "tgn:name":"Garc\u00eda, Isla",
    "tgn:placetype":[
        "aat:300008791"
    ]
},
  "bbox": [],
  "geometry": {"coordinates":[-74.966667,-47.783333],"type":"Point"}
}