{
  "id": 7440314,
  "type": "Feature",
  "properties": {
    "tgn:hierarchy":[
        "tgn:7440314",
        "tgn:1000001",
        "tgn:7005594",
        "tgn:7005560",
        "tgn:7029392"
    ],
    "tgn:id":7440314,
    "tgn:name":"San Pedro",
    "tgn:placetype":[
        "aat:300007783"
    ]
},
  "bbox": [],
  "geometry": {"coordinates":[-100.85,22.166667],"type":"Point"}
}