{
  "id": 7571022,
  "type": "Feature",
  "properties": {
    "tgn:hierarchy":[
        "tgn:7571022",
        "tgn:1000004",
        "tgn:1001869",
        "tgn:7000198",
        "tgn:7029392"
    ],
    "tgn:id":7571022,
    "tgn:name:en":"Haripura",
    "tgn:placetype":[
        "aat:300008347"
    ]
},
  "bbox": [],
  "geometry": {"coordinates":[73.466667,20.916667],"type":"Point"}
}