{
  "id": 2374526,
  "type": "Feature",
  "properties": {
    "tgn:hierarchy":[
        "tgn:2374526",
        "tgn:1000001",
        "tgn:7006451",
        "tgn:7012149",
        "tgn:2000103",
        "tgn:7029392"
    ],
    "tgn:id":2374526,
    "tgn:name":"Hance Tank",
    "tgn:placetype":[
        "aat:300006191"
    ]
},
  "bbox": [],
  "geometry": {"coordinates":[-111.6833,34.55],"type":"Point"}
}