{
  "id": 2753986,
  "type": "Feature",
  "properties": {
    "tgn:hierarchy":[
        "tgn:2753986",
        "tgn:1000001",
        "tgn:7016172",
        "tgn:7012149",
        "tgn:2000177",
        "tgn:7029392"
    ],
    "tgn:id":2753986,
    "tgn:name":"Watson Hill",
    "tgn:placetype":[
        "aat:300008798"
    ]
},
  "bbox": [],
  "geometry": {"coordinates":[-91.9333,35.1667],"type":"Point"}
}