{
  "id": 2335083,
  "type": "Feature",
  "properties": {
    "tgn:hierarchy":[
        "tgn:2335083",
        "tgn:1000001",
        "tgn:7012149",
        "tgn:7029392"
    ],
    "tgn:id":2335083,
    "tgn:name":"Forsha Creek",
    "tgn:placetype":[
        "aat:300008706"
    ]
},
  "bbox": [],
  "geometry": {"coordinates":[-97.9333,40.0833],"type":"Point"}
}