{
  "id": 7472028,
  "type": "Feature",
  "properties": {
    "tgn:hierarchy":[
        "tgn:7472028",
        "tgn:1000004",
        "tgn:7467799",
        "tgn:1000141",
        "tgn:7029392"
    ],
    "tgn:id":7472028,
    "tgn:name":"Yude Guoxiao",
    "tgn:placetype":[
        "aat:300006495"
    ]
},
  "bbox": [],
  "geometry": {"coordinates":[120.385607,23.874435],"type":"Point"}
}