<<<<<<< HEAD
{
  "id": 7472028,
  "type": "Feature",
  "properties": {
    "tgn:hierarchy":[
        "tgn:7472028",
        "tgn:1000004",
        "tgn:7467799",
        "tgn:1000141",
        "tgn:7029392"
    ],
    "tgn:id":7472028,
    "tgn:name":"Yude Guoxiao",
    "tgn:placetype":[
        "aat:300006495"
    ]
},
  "bbox": [],
  "geometry": {"coordinates":[120.385607,23.874435],"type":"Point"}
}
=======
{"geometry":{"type":"Point","coordinates":[120.385607,23.874435]},"type":"Feature","properties":{"hierarchy":["tgn:7472028","tgn:1000004","tgn:7467799","tgn:1000141","tgn:7029392"],"placetype":["aat:300006495"],"id":7472028,"name:xx":"Yude Guoxiao"}}
>>>>>>> 03f74aca74312dbeaf24d7e61306dd6a786dc3d0
