{
  "id": 7569549,
  "type": "Feature",
  "properties": {
    "tgn:hierarchy":[
        "tgn:7569549",
        "tgn:1000004",
        "tgn:7000198",
        "tgn:7031786",
        "tgn:7029392"
    ],
    "tgn:id":7569549,
    "tgn:name:en":"Sur\u0101lgaon",
    "tgn:placetype":[
        "aat:300008347"
    ]
},
  "bbox": [],
  "geometry": {"coordinates":[78.618802,29.966531],"type":"Point"}
}