{
  "id": 2041503,
  "type": "Feature",
  "properties": {
    "tgn:hierarchy":[
        "tgn:2041503",
        "tgn:1000001",
        "tgn:7012149",
        "tgn:2000818",
        "tgn:7007255",
        "tgn:7029392"
    ],
    "tgn:id":2041503,
    "tgn:name":"Strunk",
    "tgn:placetype":[
        "aat:300008347"
    ]
},
  "bbox": [],
  "geometry": {"coordinates":[-84.4333,36.6167],"type":"Point"}
}