{
  "id": 7037116,
  "type": "Feature",
  "properties": {
    "tgn:hierarchy":[
        "tgn:7037116",
        "tgn:7003150",
        "tgn:1000003",
        "tgn:7003237",
        "tgn:1000080",
        "tgn:7029392"
    ],
    "tgn:id":7037116,
    "tgn:name":"Vidigulfo",
    "tgn:placetype":[
        "aat:300008347"
    ]
},
  "bbox": [],
  "geometry": {"coordinates":[9.233333,45.283333],"type":"Point"}
}