{
  "id": 2171777,
  "type": "Feature",
  "properties": {
    "tgn:hierarchy":[
        "tgn:2171777",
        "tgn:1000001",
        "tgn:2001016",
        "tgn:7012149",
        "tgn:7007521",
        "tgn:7029392"
    ],
    "tgn:id":2171777,
    "tgn:name":"Big Trout Lake",
    "tgn:placetype":[
        "aat:300008680"
    ]
},
  "bbox": [],
  "geometry": {"coordinates":[-94.15,46.7167],"type":"Point"}
}