{
  "id": 2707131,
  "type": "Feature",
  "properties": {
    "tgn:hierarchy":[
        "tgn:2707131",
        "tgn:1000001",
        "tgn:7012149",
        "tgn:7007157",
        "tgn:2000188",
        "tgn:7029392"
    ],
    "tgn:id":2707131,
    "tgn:name":"Swede Creek Plains",
    "tgn:placetype":[
        "aat:300008805"
    ]
},
  "bbox": [],
  "geometry": {"coordinates":[-122.1333,40.65],"type":"Point"}
}