{
  "id": 7584752,
  "type": "Feature",
  "properties": {
    "tgn:hierarchy":[
        "tgn:7584752",
        "tgn:1000004",
        "tgn:7000198",
        "tgn:1001894",
        "tgn:7029392"
    ],
    "tgn:id":7584752,
    "tgn:name:en":"Barethi",
    "tgn:placetype":[
        "aat:300008347"
    ]
},
  "bbox": [],
  "geometry": {"coordinates":[78.044103,24.09139],"type":"Point"}
}