{
  "id": 7365987,
  "type": "Feature",
  "properties": {
    "tgn:hierarchy":[
        "tgn:7365987",
        "tgn:1001853",
        "tgn:1000001",
        "tgn:7005560",
        "tgn:7029392"
    ],
    "tgn:id":7365987,
    "tgn:name":"El Refugio",
    "tgn:placetype":[
        "aat:300008347"
    ]
},
  "bbox": [],
  "geometry": {"coordinates":[-103.166667,25.416667],"type":"Point"}
}