{
  "id": 1021271,
  "type": "Feature",
  "properties": {
    "tgn:hierarchy":[
        "tgn:1021271",
        "tgn:1001955",
        "tgn:1000047",
        "tgn:7002455",
        "tgn:1000002",
        "tgn:7029392"
    ],
    "tgn:id":1021271,
    "tgn:name":"Cristin\u00e1polis",
    "tgn:placetype":[
        "aat:300008347"
    ]
},
  "bbox": [],
  "geometry": {"coordinates":[-37.7667,-11.4833],"type":"Point"}
}