{
  "id": 7568409,
  "type": "Feature",
  "properties": {
    "tgn:hierarchy":[
        "tgn:7568409",
        "tgn:1000004",
        "tgn:7000198",
        "tgn:1001996",
        "tgn:7029392"
    ],
    "tgn:id":7568409,
    "tgn:name:en":"Ky\u0101nti ki Chay\u0101li Protected Forest",
    "tgn:placetype":[
        "aat:300008863"
    ]
},
  "bbox": [],
  "geometry": {"coordinates":[77.044444,31.177222],"type":"Point"}
}