{
  "id": 2569810,
  "type": "Feature",
  "properties": {
    "tgn:hierarchy":[
        "tgn:2569810",
        "tgn:1000001",
        "tgn:7012149",
        "tgn:7007919",
        "tgn:7029392"
    ],
    "tgn:id":2569810,
    "tgn:name":"Parting Creek",
    "tgn:placetype":[
        "aat:300008706"
    ]
},
  "bbox": [],
  "geometry": {"coordinates":[-75.7667,37.5333],"type":"Point"}
}