{
  "id": 2182602,
  "type": "Feature",
  "properties": {
    "tgn:hierarchy":[
        "tgn:2182602",
        "tgn:1000001",
        "tgn:7012149",
        "tgn:2000363",
        "tgn:7007248",
        "tgn:7029392"
    ],
    "tgn:id":2182602,
    "tgn:name":"Blue Spring",
    "tgn:placetype":[
        "aat:300008697"
    ]
},
  "bbox": [],
  "geometry": {"coordinates":[-84.95,32.7333],"type":"Point"}
}