{
  "id": 2573501,
  "type": "Feature",
  "properties": {
    "tgn:hierarchy":[
        "tgn:2573501",
        "tgn:1000001",
        "tgn:7012149",
        "tgn:2001980",
        "tgn:7007826",
        "tgn:7029392"
    ],
    "tgn:id":2573501,
    "tgn:name":"Pecan Hollow",
    "tgn:placetype":[
        "aat:300008761"
    ]
},
  "bbox": [],
  "geometry": {"coordinates":[-99.9667,30.25],"type":"Point"}
}