{
  "id": 7394670,
  "type": "Feature",
  "properties": {
    "tgn:hierarchy":[
        "tgn:7394670",
        "tgn:1001853",
        "tgn:1000001",
        "tgn:7005560",
        "tgn:7029392"
    ],
    "tgn:id":7394670,
    "tgn:name":"Tanque San Ambrosio",
    "tgn:placetype":[
        "aat:300006191"
    ]
},
  "bbox": [],
  "geometry": {"coordinates":[-101.966667,27.65],"type":"Point"}
}