{
  "id": 7182527,
  "type": "Feature",
  "properties": {
    "tgn:hierarchy":[
        "tgn:7182527",
        "tgn:7003669",
        "tgn:1000003",
        "tgn:7000084",
        "tgn:7029392"
    ],
    "tgn:id":7182527,
    "tgn:name":"Geiersberg",
    "tgn:placetype":[
        "aat:300008777"
    ]
},
  "bbox": [],
  "geometry": {"coordinates":[10.433333,49.85],"type":"Point"}
}