{
  "id": 1137765,
  "type": "Feature",
  "properties": {
    "tgn:hierarchy":[
        "tgn:1137765",
        "tgn:1000004",
        "tgn:7002435",
        "tgn:7011524",
        "tgn:7029392"
    ],
    "tgn:id":1137765,
    "tgn:name":"Krasnyy Bor",
    "tgn:placetype":[
        "aat:300008347"
    ]
},
  "bbox": [],
  "geometry": {"coordinates":[53.1667,55.8667],"type":"Point"}
}