{
  "id": 7564395,
  "type": "Feature",
  "properties": {
    "tgn:hierarchy":[
        "tgn:7564395",
        "tgn:1000004",
        "tgn:7000198",
        "tgn:7016722",
        "tgn:7029392"
    ],
    "tgn:id":7564395,
    "tgn:name:en":"Tikri Kal\u0101n",
    "tgn:placetype":[
        "aat:300008347"
    ]
},
  "bbox": [],
  "geometry": {"coordinates":[79.679515,26.970714],"type":"Point"}
}