{
  "id": 2125479,
  "type": "Feature",
  "properties": {
    "tgn:hierarchy":[
        "tgn:2125479",
        "tgn:1000001",
        "tgn:7012149",
        "tgn:1002545",
        "tgn:7007157",
        "tgn:7029392"
    ],
    "tgn:id":2125479,
    "tgn:name":"Actis",
    "tgn:placetype":[
        "aat:300008347"
    ]
},
  "bbox": [],
  "geometry": {"coordinates":[-118.1333,34.95],"type":"Point"}
}