{
  "id": 2536504,
  "type": "Feature",
  "properties": {
    "tgn:hierarchy":[
        "tgn:2536504",
        "tgn:1000001",
        "tgn:7012149",
        "tgn:2002194",
        "tgn:7007919",
        "tgn:7029392"
    ],
    "tgn:id":2536504,
    "tgn:name":"Neals Cave",
    "tgn:placetype":[
        "aat:300008746"
    ]
},
  "bbox": [],
  "geometry": {"coordinates":[-81.8833,36.6167],"type":"Point"}
}