{
  "id": 1130212,
  "type": "Feature",
  "properties": {
    "tgn:hierarchy":[
        "tgn:1130212",
        "tgn:1000001",
        "tgn:7012149",
        "tgn:2001486",
        "tgn:7007709",
        "tgn:7029392"
    ],
    "tgn:id":1130212,
    "tgn:name":"South",
    "tgn:placetype":[
        "aat:300008707"
    ]
},
  "bbox": [],
  "geometry": {"coordinates":[-76.95,34.8333],"type":"Point"}
}