{
  "id": 7369937,
  "type": "Feature",
  "properties": {
    "tgn:hierarchy":[
        "tgn:7369937",
        "tgn:1001853",
        "tgn:1000001",
        "tgn:7005560",
        "tgn:7029392"
    ],
    "tgn:id":7369937,
    "tgn:name":"Jalapa",
    "tgn:placetype":[
        "aat:300008347"
    ]
},
  "bbox": [],
  "geometry": {"coordinates":[-101.55,24.883333],"type":"Point"}
}