{
  "id": 2460791,
  "type": "Feature",
  "properties": {
    "tgn:hierarchy":[
        "tgn:2460791",
        "tgn:1000001",
        "tgn:7012149",
        "tgn:2001067",
        "tgn:7007521",
        "tgn:7029392"
    ],
    "tgn:id":2460791,
    "tgn:name":"Little Shoepack Lake",
    "tgn:placetype":[
        "aat:300008680"
    ]
},
  "bbox": [],
  "geometry": {"coordinates":[-92.8667,48.4833],"type":"Point"}
}