{
  "id": 7306363,
  "type": "Feature",
  "properties": {
    "tgn:hierarchy":[
        "tgn:7306363",
        "tgn:7002836",
        "tgn:7016622",
        "tgn:1000003",
        "tgn:1000095",
        "tgn:7029392"
    ],
    "tgn:id":7306363,
    "tgn:name":"Lores, Punta de los",
    "tgn:placetype":[
        "aat:300386846"
    ]
},
  "bbox": [],
  "geometry": {"coordinates":[-16.416667,28.483333],"type":"Point"}
}