{
  "id": 7308300,
  "type": "Feature",
  "properties": {
    "tgn:hierarchy":[
        "tgn:7308300",
        "tgn:1001695",
        "tgn:1000049",
        "tgn:1000002",
        "tgn:7029392"
    ],
    "tgn:id":7308300,
    "tgn:name":"Matancilla",
    "tgn:placetype":[
        "aat:300004792"
    ]
},
  "bbox": [],
  "geometry": {"coordinates":[-71.55,-34.616667],"type":"Point"}
}