<<<<<<< HEAD
{
  "id": 7362200,
  "type": "Feature",
  "properties": {
    "tgn:hierarchy":[
        "tgn:7362200",
        "tgn:1000001",
        "tgn:1001960",
        "tgn:7005560",
        "tgn:7029392"
    ],
    "tgn:id":7362200,
    "tgn:name":"Rancho El Diablo",
    "tgn:placetype":[
        "aat:300000241"
    ]
},
  "bbox": [],
  "geometry": {"coordinates":[-109.033333,31.283333],"type":"Point"}
}
=======
{"geometry":{"type":"Point","coordinates":[-109.033333,31.283333]},"type":"Feature","properties":{"hierarchy":["tgn:7362200","tgn:1000001","tgn:1001960","tgn:7005560","tgn:7029392"],"placetype":["aat:300000241"],"id":7362200,"name:xx":"Rancho El Diablo"}}
>>>>>>> 03f74aca74312dbeaf24d7e61306dd6a786dc3d0
