{
  "id": 7362200,
  "type": "Feature",
  "properties": {
    "tgn:hierarchy":[
        "tgn:7362200",
        "tgn:1000001",
        "tgn:1001960",
        "tgn:7005560",
        "tgn:7029392"
    ],
    "tgn:id":7362200,
    "tgn:name":"Rancho El Diablo",
    "tgn:placetype":[
        "aat:300000241"
    ]
},
  "bbox": [],
  "geometry": {"coordinates":[-109.033333,31.283333],"type":"Point"}
}