{
  "id": 2199212,
  "type": "Feature",
  "properties": {
    "tgn:hierarchy":[
        "tgn:2199212",
        "tgn:1000001",
        "tgn:7012149",
        "tgn:7007254",
        "tgn:7029392"
    ],
    "tgn:id":2199212,
    "tgn:name":"Bruno Creek",
    "tgn:placetype":[
        "aat:300008706"
    ]
},
  "bbox": [],
  "geometry": {"coordinates":[-96.8833,38.35],"type":"Point"}
}