{
  "id": 2377024,
  "type": "Feature",
  "properties": {
    "tgn:hierarchy":[
        "tgn:2377024",
        "tgn:1000001",
        "tgn:7012149",
        "tgn:1002392",
        "tgn:7007157",
        "tgn:7029392"
    ],
    "tgn:id":2377024,
    "tgn:name":"Harlan Stevens Ditch",
    "tgn:placetype":[
        "aat:300006075"
    ]
},
  "bbox": [],
  "geometry": {"coordinates":[-119.7833,36.5667],"type":"Point"}
}