{
  "id": 7128433,
  "type": "Feature",
  "properties": {
    "tgn:hierarchy":[
        "tgn:7128433",
        "tgn:1000003",
        "tgn:7003684",
        "tgn:7000084",
        "tgn:7029392"
    ],
    "tgn:id":7128433,
    "tgn:name":"Nuhweiler",
    "tgn:placetype":[
        "aat:300000206"
    ]
},
  "bbox": [],
  "geometry": {"coordinates":[6.95,49.55],"type":"Point"}
}