{
  "id": 7301424,
  "type": "Feature",
  "properties": {
    "tgn:hierarchy":[
        "tgn:7301424",
        "tgn:7008911",
        "tgn:1000003",
        "tgn:7002763",
        "tgn:1000095",
        "tgn:7029392"
    ],
    "tgn:id":7301424,
    "tgn:name":"Mer\u00e1s",
    "tgn:placetype":[
        "aat:300008347"
    ]
},
  "bbox": [],
  "geometry": {"coordinates":[-6.466667,43.466667],"type":"Point"}
}