{
  "id": 7079537,
  "type": "Feature",
  "properties": {
    "tgn:hierarchy":[
        "tgn:7079537",
        "tgn:7003669",
        "tgn:1000003",
        "tgn:7000084",
        "tgn:7029392"
    ],
    "tgn:id":7079537,
    "tgn:name":"Zeitl Bach",
    "tgn:placetype":[
        "aat:300008699"
    ]
},
  "bbox": [],
  "geometry": {"coordinates":[11.316667,48.333333],"type":"Point"}
}