{
  "id": 2531208,
  "type": "Feature",
  "properties": {
    "tgn:hierarchy":[
        "tgn:2531208",
        "tgn:1000001",
        "tgn:7012149",
        "tgn:2000917",
        "tgn:7007256",
        "tgn:7029392"
    ],
    "tgn:id":2531208,
    "tgn:name":"Mulberry Hill",
    "tgn:placetype":[
        "aat:300008347"
    ]
},
  "bbox": [],
  "geometry": {"coordinates":[-92.8333,32.0667],"type":"Point"}
}