{
  "id": 7415740,
  "type": "Feature",
  "properties": {
    "tgn:hierarchy":[
        "tgn:7415740",
        "tgn:1000001",
        "tgn:7005591",
        "tgn:7005560",
        "tgn:7029392"
    ],
    "tgn:id":7415740,
    "tgn:name:es":"El Cocol",
    "tgn:placetype":[
        "aat:300008347"
    ]
},
  "bbox": [],
  "geometry": {"coordinates":[-97.543056,16.656111],"type":"Point"}
}