{
  "id": 7558061,
  "type": "Feature",
  "properties": {
    "tgn:hierarchy":[
        "tgn:7558061",
        "tgn:1000004",
        "tgn:7000198",
        "tgn:7016694",
        "tgn:7029392"
    ],
    "tgn:id":7558061,
    "tgn:name:en":"Pud\u0101m\u0101ri",
    "tgn:placetype":[
        "aat:300008347"
    ]
},
  "bbox": [],
  "geometry": {"coordinates":[84.483333,19.45],"type":"Point"}
}