<<<<<<< HEAD
{
  "id": 7024771,
  "type": "Feature",
  "properties": {
    "tgn:hierarchy":[
        "tgn:7024771",
        "tgn:7002445",
        "tgn:7008103",
        "tgn:1000003",
        "tgn:7008591",
        "tgn:7029392"
    ],
    "tgn:id":7024771,
    "tgn:name":"Riseley",
    "tgn:name:ang":"Riselai",
    "tgn:placetype":[
        "aat:300008347"
    ]
},
  "bbox": [],
  "geometry": {"coordinates":[-0.466667,52.25],"type":"Point"}
}
=======
{"geometry":{"type":"Point","coordinates":[-0.466667,52.250000]},"type":"Feature","properties":{"hierarchy":["tgn:7024771","tgn:7002445","tgn:7008103","tgn:1000003","tgn:7008591","tgn:7029392"],"placetype":["aat:300008347"],"id":7024771,"name:xx":"Riseley","name:ang":"Riselai"}}
>>>>>>> 03f74aca74312dbeaf24d7e61306dd6a786dc3d0
