<<<<<<< HEAD
{
  "id": 2761131,
  "type": "Feature",
  "properties": {
    "tgn:hierarchy":[
        "tgn:2761131",
        "tgn:1000001",
        "tgn:2002315",
        "tgn:7012149",
        "tgn:7007922",
        "tgn:7029392"
    ],
    "tgn:id":2761131,
    "tgn:name":"West Lake",
    "tgn:placetype":[
        "aat:300008680"
    ]
},
  "bbox": [],
  "geometry": {"coordinates":[-89.3167,43.5333],"type":"Point"}
}
=======
{"geometry":{"type":"Point","coordinates":[-89.316700,43.533300]},"type":"Feature","properties":{"hierarchy":["tgn:2761131","tgn:1000001","tgn:2002315","tgn:7012149","tgn:7007922","tgn:7029392"],"placetype":["aat:300008680"],"id":2761131,"name:xx":"West Lake"}}
>>>>>>> 03f74aca74312dbeaf24d7e61306dd6a786dc3d0
