{
  "id": 2567456,
  "type": "Feature",
  "properties": {
    "tgn:hierarchy":[
        "tgn:2567456",
        "tgn:1000001",
        "tgn:7012149",
        "tgn:2000887",
        "tgn:7007256",
        "tgn:7029392"
    ],
    "tgn:id":2567456,
    "tgn:name":"Papaw Bayou",
    "tgn:placetype":[
        "aat:300008699"
    ]
},
  "bbox": [],
  "geometry": {"coordinates":[-92.0167,32.8167],"type":"Point"}
}