{
  "id": 2354527,
  "type": "Feature",
  "properties": {
    "tgn:hierarchy":[
        "tgn:2354527",
        "tgn:1000001",
        "tgn:7012149",
        "tgn:2002087",
        "tgn:7007826",
        "tgn:7029392"
    ],
    "tgn:id":2354527,
    "tgn:name":"Golondrina Waterhole",
    "tgn:placetype":[
        "aat:300006191"
    ]
},
  "bbox": [],
  "geometry": {"coordinates":[-100.0167,29.1667],"type":"Point"}
}