{
  "id": 7340681,
  "type": "Feature",
  "properties": {
    "tgn:hierarchy":[
        "tgn:7340681",
        "tgn:7002758",
        "tgn:1001316",
        "tgn:1000003",
        "tgn:1000095",
        "tgn:7029392"
    ],
    "tgn:id":7340681,
    "tgn:name":"Cabeza Gorda",
    "tgn:placetype":[
        "aat:300008347"
    ]
},
  "bbox": [],
  "geometry": {"coordinates":[-2.616667,38.183333],"type":"Point"}
}