{
  "id": 2633672,
  "type": "Feature",
  "properties": {
    "tgn:hierarchy":[
        "tgn:2633672",
        "tgn:1000001",
        "tgn:7012149",
        "tgn:7007157",
        "tgn:2000186",
        "tgn:7029392"
    ],
    "tgn:id":2633672,
    "tgn:name":"Rush Creek",
    "tgn:placetype":[
        "aat:300008706"
    ]
},
  "bbox": [],
  "geometry": {"coordinates":[-120.8333,41.3167],"type":"Point"}
}