{
  "id": 2519977,
  "type": "Feature",
  "properties": {
    "tgn:hierarchy":[
        "tgn:2519977",
        "tgn:1000001",
        "tgn:7012149",
        "tgn:2001439",
        "tgn:7007566",
        "tgn:7029392"
    ],
    "tgn:id":2519977,
    "tgn:name":"Molina Spring",
    "tgn:placetype":[
        "aat:300008697"
    ]
},
  "bbox": [],
  "geometry": {"coordinates":[-103.6167,35.4167],"type":"Point"}
}