{
  "id": 7255034,
  "type": "Feature",
  "properties": {
    "tgn:hierarchy":[
        "tgn:7255034",
        "tgn:7003466",
        "tgn:1000003",
        "tgn:1000063",
        "tgn:4012014",
        "tgn:7029392"
    ],
    "tgn:id":7255034,
    "tgn:name":"Tilleul de la Chapelle",
    "tgn:placetype":[
        "aat:300008347"
    ]
},
  "bbox": [],
  "geometry": {"coordinates":[5.25,50.116667],"type":"Point"}
}