<<<<<<< HEAD
{
  "id": 2761933,
  "type": "Feature",
  "properties": {
    "tgn:hierarchy":[
        "tgn:2761933",
        "tgn:1000001",
        "tgn:7012149",
        "tgn:1003038",
        "tgn:7007517",
        "tgn:7029392"
    ],
    "tgn:id":2761933,
    "tgn:name":"West River Reservoir",
    "tgn:placetype":[
        "aat:300006191"
    ]
},
  "bbox": [],
  "geometry": {"coordinates":[-71.6,42.1],"type":"Point"}
}
=======
{"geometry":{"type":"Point","coordinates":[-71.600000,42.100000]},"type":"Feature","properties":{"hierarchy":["tgn:2761933","tgn:1000001","tgn:7012149","tgn:1003038","tgn:7007517","tgn:7029392"],"placetype":["aat:300006191"],"id":2761933,"name:xx":"West River Reservoir"}}
>>>>>>> 03f74aca74312dbeaf24d7e61306dd6a786dc3d0
