{
  "id": 7430142,
  "type": "Feature",
  "properties": {
    "tgn:hierarchy":[
        "tgn:7430142",
        "tgn:1001835",
        "tgn:1000001",
        "tgn:7005560",
        "tgn:7029392"
    ],
    "tgn:id":7430142,
    "tgn:name":"El Espantado",
    "tgn:placetype":[
        "aat:300008347"
    ]
},
  "bbox": [],
  "geometry": {"coordinates":[-116.383333,31.916667],"type":"Point"}
}