{
  "id": 2308847,
  "type": "Feature",
  "properties": {
    "tgn:hierarchy":[
        "tgn:2308847",
        "tgn:1000001",
        "tgn:7012149",
        "tgn:2002170",
        "tgn:7007919",
        "tgn:7029392"
    ],
    "tgn:id":2308847,
    "tgn:name":"East Prong Beaverdam Creek",
    "tgn:placetype":[
        "aat:300008706"
    ]
},
  "bbox": [],
  "geometry": {"coordinates":[-78.2333,38.0167],"type":"Point"}
}