<<<<<<< HEAD
{
  "id": 7371769,
  "type": "Feature",
  "properties": {
    "tgn:hierarchy":[
        "tgn:7371769",
        "tgn:1001853",
        "tgn:1000001",
        "tgn:7005560",
        "tgn:7029392"
    ],
    "tgn:id":7371769,
    "tgn:name":"La India, Sierra de",
    "tgn:placetype":[
        "aat:300266640"
    ]
},
  "bbox": [],
  "geometry": {"coordinates":[-101.283333,25.066667],"type":"Point"}
}
=======
{"geometry":{"type":"Point","coordinates":[-101.283333,25.066667]},"type":"Feature","properties":{"hierarchy":["tgn:7371769","tgn:1001853","tgn:1000001","tgn:7005560","tgn:7029392"],"placetype":["aat:300266640"],"id":7371769,"name:xx":"La India, Sierra de"}}
>>>>>>> 03f74aca74312dbeaf24d7e61306dd6a786dc3d0
