<<<<<<< HEAD
{
  "id": 2336607,
  "type": "Feature",
  "properties": {
    "tgn:hierarchy":[
        "tgn:2336607",
        "tgn:1000001",
        "tgn:7012149",
        "tgn:1002545",
        "tgn:7007157",
        "tgn:7029392"
    ],
    "tgn:id":2336607,
    "tgn:name":"Four Oaks Mine",
    "tgn:placetype":[
        "aat:300000390"
    ]
},
  "bbox": [],
  "geometry": {"coordinates":[-118.3167,35.3833],"type":"Point"}
}
=======
{"geometry":{"type":"Point","coordinates":[-118.316700,35.383300]},"type":"Feature","properties":{"hierarchy":["tgn:2336607","tgn:1000001","tgn:7012149","tgn:1002545","tgn:7007157","tgn:7029392"],"placetype":["aat:300000390"],"id":2336607,"name:xx":"Four Oaks Mine"}}
>>>>>>> 03f74aca74312dbeaf24d7e61306dd6a786dc3d0
