{
  "id": 2336607,
  "type": "Feature",
  "properties": {
    "tgn:hierarchy":[
        "tgn:2336607",
        "tgn:1000001",
        "tgn:7012149",
        "tgn:1002545",
        "tgn:7007157",
        "tgn:7029392"
    ],
    "tgn:id":2336607,
    "tgn:name":"Four Oaks Mine",
    "tgn:placetype":[
        "aat:300000390"
    ]
},
  "bbox": [],
  "geometry": {"coordinates":[-118.3167,35.3833],"type":"Point"}
}