{
  "id": 2620468,
  "type": "Feature",
  "properties": {
    "tgn:hierarchy":[
        "tgn:2620468",
        "tgn:1000001",
        "tgn:7012149",
        "tgn:7007520",
        "tgn:7029392"
    ],
    "tgn:id":2620468,
    "tgn:name":"River Styx",
    "tgn:placetype":[
        "aat:300008699"
    ]
},
  "bbox": [],
  "geometry": {"coordinates":[-84.7667,43.25],"type":"Point"}
}