{
  "id": 7501969,
  "type": "Feature",
  "properties": {
    "tgn:hierarchy":[
        "tgn:7501969",
        "tgn:1000004",
        "tgn:7492971",
        "tgn:1000141",
        "tgn:7029392"
    ],
    "tgn:id":7501969,
    "tgn:name":"Dakuwei",
    "tgn:placetype":[
        "aat:300008347"
    ]
},
  "bbox": [],
  "geometry": {"coordinates":[120.739722,21.944444],"type":"Point"}
}