{
  "id": 2563986,
  "type": "Feature",
  "properties": {
    "tgn:hierarchy":[
        "tgn:2563986",
        "tgn:1000001",
        "tgn:7012149",
        "tgn:2001526",
        "tgn:7007709",
        "tgn:7029392"
    ],
    "tgn:id":2563986,
    "tgn:name":"Oyster Creek Point",
    "tgn:placetype":[
        "aat:300008850"
    ]
},
  "bbox": [],
  "geometry": {"coordinates":[-76.4833,35.2333],"type":"Point"}
}