{
  "id": 7510801,
  "type": "Feature",
  "properties": {
    "tgn:hierarchy":[
        "tgn:7510801",
        "tgn:1009227",
        "tgn:1000226",
        "tgn:7018437",
        "tgn:1000006",
        "tgn:7029392"
    ],
    "tgn:id":7510801,
    "tgn:name:en":"Souter Peak",
    "tgn:placetype":[
        "aat:300008798"
    ]
},
  "bbox": [],
  "geometry": {"coordinates":[168.966667,-44.066667],"type":"Point"}
}