{
  "id": 7285471,
  "type": "Feature",
  "properties": {
    "tgn:hierarchy":[
        "tgn:7285471",
        "tgn:1001623",
        "tgn:1000049",
        "tgn:1000002",
        "tgn:7029392"
    ],
    "tgn:id":7285471,
    "tgn:name":"Quemado, Islote",
    "tgn:placetype":[
        "aat:300008791"
    ]
},
  "bbox": [],
  "geometry": {"coordinates":[-72.833333,-45.416667],"type":"Point"}
}