{
  "id": 7550040,
  "type": "Feature",
  "properties": {
    "tgn:hierarchy":[
        "tgn:7550040",
        "tgn:1000004",
        "tgn:7000198",
        "tgn:7016788",
        "tgn:7029392"
    ],
    "tgn:id":7550040,
    "tgn:name:en":"B\u012blon\u012b",
    "tgn:placetype":[
        "aat:300008347"
    ]
},
  "bbox": [],
  "geometry": {"coordinates":[77.249916,26.497801],"type":"Point"}
}