{
  "id": 2062082,
  "type": "Feature",
  "properties": {
    "tgn:hierarchy":[
        "tgn:2062082",
        "tgn:1000001",
        "tgn:2001339",
        "tgn:7012149",
        "tgn:7007525",
        "tgn:7029392"
    ],
    "tgn:id":2062082,
    "tgn:name":"Darr",
    "tgn:placetype":[
        "aat:300008347"
    ]
},
  "bbox": [],
  "geometry": {"coordinates":[-99.8833,40.8167],"type":"Point"}
}