<<<<<<< HEAD
{
  "id": 2158986,
  "type": "Feature",
  "properties": {
    "tgn:hierarchy":[
        "tgn:2158986",
        "tgn:1000001",
        "tgn:2000922",
        "tgn:7012149",
        "tgn:7007515",
        "tgn:7029392"
    ],
    "tgn:id":2158986,
    "tgn:name":"Beckwith Hill",
    "tgn:placetype":[
        "aat:300008798"
    ]
},
  "bbox": [],
  "geometry": {"coordinates":[-68.3833,44.5],"type":"Point"}
}
=======
{"geometry":{"type":"Point","coordinates":[-68.383300,44.500000]},"type":"Feature","properties":{"hierarchy":["tgn:2158986","tgn:1000001","tgn:2000922","tgn:7012149","tgn:7007515","tgn:7029392"],"placetype":["aat:300008798"],"id":2158986,"name:xx":"Beckwith Hill"}}
>>>>>>> 03f74aca74312dbeaf24d7e61306dd6a786dc3d0
