<<<<<<< HEAD
{
  "id": 2152654,
  "type": "Feature",
  "properties": {
    "tgn:hierarchy":[
        "tgn:2152654",
        "tgn:7014651",
        "tgn:1000001",
        "tgn:7012149",
        "tgn:7007516",
        "tgn:7029392"
    ],
    "tgn:id":2152654,
    "tgn:name":"Baynard",
    "tgn:placetype":[
        "aat:300008347"
    ]
},
  "bbox": [],
  "geometry": {"coordinates":[-76.6667,38.8333],"type":"Point"}
}
=======
{"geometry":{"type":"Point","coordinates":[-76.666700,38.833300]},"type":"Feature","properties":{"hierarchy":["tgn:2152654","tgn:7014651","tgn:1000001","tgn:7012149","tgn:7007516","tgn:7029392"],"placetype":["aat:300008347"],"id":2152654,"name:xx":"Baynard"}}
>>>>>>> 03f74aca74312dbeaf24d7e61306dd6a786dc3d0
