{
  "id": 7538552,
  "type": "Feature",
  "properties": {
    "tgn:hierarchy":[
        "tgn:7538552",
        "tgn:7001242",
        "tgn:7016833",
        "tgn:1001335",
        "tgn:7029392"
    ],
    "tgn:id":7538552,
    "tgn:name:en":"Mas'\u016bd, Jaz\u012brat",
    "tgn:placetype":[
        "aat:300008791"
    ]
},
  "bbox": [],
  "geometry": {"coordinates":[30.804444,31.415833],"type":"Point"}
}