{
  "id": 2215790,
  "type": "Feature",
  "properties": {
    "tgn:hierarchy":[
        "tgn:2215790",
        "tgn:1000001",
        "tgn:7012149",
        "tgn:2002377",
        "tgn:7007923",
        "tgn:7029392"
    ],
    "tgn:id":2215790,
    "tgn:name":"Camel Hump Reservoir",
    "tgn:placetype":[
        "aat:300006191"
    ]
},
  "bbox": [],
  "geometry": {"coordinates":[-106.5333,43.3167],"type":"Point"}
}