{
  "id": 7282898,
  "type": "Feature",
  "properties": {
    "tgn:hierarchy":[
        "tgn:7282898",
        "tgn:1001657",
        "tgn:1000049",
        "tgn:1000002",
        "tgn:7029392"
    ],
    "tgn:id":7282898,
    "tgn:name":"Pelado, Cerro",
    "tgn:placetype":[
        "aat:300008795"
    ]
},
  "bbox": [],
  "geometry": {"coordinates":[-71.083333,-31.533333],"type":"Point"}
}