{
  "id": 1000641,
  "type": "Feature",
  "properties": {
    "tgn:hierarchy":[
        "tgn:1000641",
        "tgn:1000002",
        "tgn:1000056",
        "tgn:7029392"
    ],
    "tgn:id":1000641,
    "tgn:name":"Ica",
    "tgn:placetype":[
        "aat:300387064",
        "aat:300000772",
        "aat:300236112"
    ]
},
  "bbox": [],
  "geometry": {"coordinates":[-75.499,-14.332],"type":"Point"}
}