{
  "id": 2734967,
  "type": "Feature",
  "properties": {
    "tgn:hierarchy":[
        "tgn:2734967",
        "tgn:1000001",
        "tgn:2001411",
        "tgn:7012149",
        "tgn:7007526",
        "tgn:7029392"
    ],
    "tgn:id":2734967,
    "tgn:name":"Twelvemile Spring",
    "tgn:placetype":[
        "aat:300008697"
    ]
},
  "bbox": [],
  "geometry": {"coordinates":[-114.9333,41.2333],"type":"Point"}
}