{
  "id": 2690717,
  "type": "Feature",
  "properties": {
    "tgn:hierarchy":[
        "tgn:2690717",
        "tgn:1000001",
        "tgn:2001413",
        "tgn:7012149",
        "tgn:7007526",
        "tgn:7029392"
    ],
    "tgn:id":2690717,
    "tgn:name":"Standard Copper Mine",
    "tgn:placetype":[
        "aat:300000390"
    ]
},
  "bbox": [],
  "geometry": {"coordinates":[-115.8667,39.6667],"type":"Point"}
}