{
  "id": 1062924,
  "type": "Feature",
  "properties": {
    "tgn:hierarchy":[
        "tgn:1062924",
        "tgn:1000003",
        "tgn:7010031",
        "tgn:1000097",
        "tgn:7029392"
    ],
    "tgn:id":1062924,
    "tgn:name":"Edsgatan",
    "tgn:placetype":[
        "aat:300008347"
    ]
},
  "bbox": [],
  "geometry": {"coordinates":[13.5167,59.4333],"type":"Point"}
}