{
  "id": 2288390,
  "type": "Feature",
  "properties": {
    "tgn:hierarchy":[
        "tgn:2288390",
        "tgn:1000001",
        "tgn:7012149",
        "tgn:2002114",
        "tgn:7007827",
        "tgn:7029392"
    ],
    "tgn:id":2288390,
    "tgn:name":"Disappointment Hills",
    "tgn:placetype":[
        "aat:300386831"
    ]
},
  "bbox": [],
  "geometry": {"coordinates":[-113.6833,39.4667],"type":"Point"}
}