{
  "id": 2750745,
  "type": "Feature",
  "properties": {
    "tgn:hierarchy":[
        "tgn:2750745",
        "tgn:1000001",
        "tgn:7012149",
        "tgn:2000281",
        "tgn:7007240",
        "tgn:7029392"
    ],
    "tgn:id":2750745,
    "tgn:name":"Ward Cove",
    "tgn:placetype":[
        "aat:300132316"
    ]
},
  "bbox": [],
  "geometry": {"coordinates":[-86.4333,30.4833],"type":"Point"}
}