{
  "id": 7544958,
  "type": "Feature",
  "properties": {
    "tgn:hierarchy":[
        "tgn:7544958",
        "tgn:1000004",
        "tgn:1001869",
        "tgn:7000198",
        "tgn:7029392"
    ],
    "tgn:id":7544958,
    "tgn:name:en":"Bachar",
    "tgn:placetype":[
        "aat:300007783"
    ]
},
  "bbox": [],
  "geometry": {"coordinates":[73.166667,21.95],"type":"Point"}
}