{
  "id": 7559943,
  "type": "Feature",
  "properties": {
    "tgn:hierarchy":[
        "tgn:7559943",
        "tgn:1000004",
        "tgn:7000198",
        "tgn:7016788",
        "tgn:7029392"
    ],
    "tgn:id":7559943,
    "tgn:name:en":"Sabr\u0101mpura",
    "tgn:placetype":[
        "aat:300008347"
    ]
},
  "bbox": [],
  "geometry": {"coordinates":[75.6339,26.9568],"type":"Point"}
}