{
  "id": 2071306,
  "type": "Feature",
  "properties": {
    "tgn:hierarchy":[
        "tgn:2071306",
        "tgn:1000001",
        "tgn:7012149",
        "tgn:1002708",
        "tgn:7007568",
        "tgn:7029392"
    ],
    "tgn:id":2071306,
    "tgn:name":"North Hills",
    "tgn:placetype":[
        "aat:300008347"
    ]
},
  "bbox": [],
  "geometry": {"coordinates":[-73.6667,40.7667],"type":"Point"}
}