{
  "id": 2341429,
  "type": "Feature",
  "properties": {
    "tgn:hierarchy":[
        "tgn:2341429",
        "tgn:1000001",
        "tgn:7012149",
        "tgn:2000494",
        "tgn:7007250",
        "tgn:7029392"
    ],
    "tgn:id":2341429,
    "tgn:name":"Frog Lake",
    "tgn:placetype":[
        "aat:300008680"
    ]
},
  "bbox": [],
  "geometry": {"coordinates":[-115.9333,45.15],"type":"Point"}
}