{
  "id": 1049202,
  "type": "Feature",
  "properties": {
    "tgn:hierarchy":[
        "tgn:1049202",
        "tgn:1000003",
        "tgn:7024126",
        "tgn:7006366",
        "tgn:7029392"
    ],
    "tgn:id":1049202,
    "tgn:name":"Le\u017cajsk",
    "tgn:placetype":[
        "aat:300008347"
    ]
},
  "bbox": [],
  "geometry": {"coordinates":[22.4333,50.2667],"type":"Point"}
}