<<<<<<< HEAD
{
  "id": 7481306,
  "type": "Feature",
  "properties": {
    "tgn:hierarchy":[
        "tgn:7481306",
        "tgn:1000004",
        "tgn:7471332",
        "tgn:1000141",
        "tgn:7029392"
    ],
    "tgn:id":7481306,
    "tgn:name":"Baofa Qiao",
    "tgn:placetype":[
        "aat:300007836"
    ]
},
  "bbox": [],
  "geometry": {"coordinates":[121.186667,24.7875],"type":"Point"}
}
=======
{"geometry":{"type":"Point","coordinates":[121.186667,24.787500]},"type":"Feature","properties":{"hierarchy":["tgn:7481306","tgn:1000004","tgn:7471332","tgn:1000141","tgn:7029392"],"placetype":["aat:300007836"],"id":7481306,"name:xx":"Baofa Qiao"}}
>>>>>>> 03f74aca74312dbeaf24d7e61306dd6a786dc3d0
