{
  "id": 7027130,
  "type": "Feature",
  "properties": {
    "tgn:hierarchy":[
        "tgn:7027130",
        "tgn:1000003",
        "tgn:7011765",
        "tgn:7029392"
    ],
    "tgn:id":7027130,
    "tgn:name":"\u017dilinsk\u00fd",
    "tgn:placetype":[
        "aat:300387064",
        "aat:300236112"
    ]
},
  "bbox": [],
  "geometry": {"coordinates":[19.166667,49.166667],"type":"Point"}
}