{
  "id": 1139767,
  "type": "Feature",
  "properties": {
    "tgn:hierarchy":[
        "tgn:1139767",
        "tgn:7002075",
        "tgn:1000004",
        "tgn:1000111",
        "tgn:7029392"
    ],
    "tgn:id":1139767,
    "tgn:name":"Wujiang",
    "tgn:placetype":[
        "aat:300008347"
    ]
},
  "bbox": [],
  "geometry": {"coordinates":[118.4667,31.8667],"type":"Point"}
}