{
  "id": 7491879,
  "type": "Feature",
  "properties": {
    "tgn:hierarchy":[
        "tgn:7491879",
        "tgn:7487020",
        "tgn:1000004",
        "tgn:1000141",
        "tgn:7029392"
    ],
    "tgn:id":7491879,
    "tgn:name":"Shuiliudong",
    "tgn:placetype":[
        "aat:300008347"
    ]
},
  "bbox": [],
  "geometry": {"coordinates":[120.853968,24.371847],"type":"Point"}
}