{
  "id": 7215882,
  "type": "Feature",
  "properties": {
    "tgn:hierarchy":[
        "tgn:7215882",
        "tgn:7003692",
        "tgn:1000003",
        "tgn:7000084",
        "tgn:7029392"
    ],
    "tgn:id":7215882,
    "tgn:name":"Akenbach",
    "tgn:placetype":[
        "aat:300000206"
    ]
},
  "bbox": [],
  "geometry": {"coordinates":[9.433333,47.783333],"type":"Point"}
}