{
  "id": 1079898,
  "type": "Feature",
  "properties": {
    "tgn:hierarchy":[
        "tgn:1079898",
        "tgn:7000895",
        "tgn:1000004",
        "tgn:7016854",
        "tgn:1000120",
        "tgn:7029392"
    ],
    "tgn:id":1079898,
    "tgn:name":"D\u014dshi",
    "tgn:placetype":[
        "aat:300008347"
    ]
},
  "bbox": [],
  "geometry": {"coordinates":[139.0333,35.5333],"type":"Point"}
}