{
  "id": 2321464,
  "type": "Feature",
  "properties": {
    "tgn:hierarchy":[
        "tgn:2321464",
        "tgn:1000001",
        "tgn:1002539",
        "tgn:7012149",
        "tgn:7007516",
        "tgn:7029392"
    ],
    "tgn:id":2321464,
    "tgn:name":"Fairlee Neck",
    "tgn:placetype":[
        "aat:300008850"
    ]
},
  "bbox": [],
  "geometry": {"coordinates":[-76.1833,39.25],"type":"Point"}
}