{
  "id": 2194681,
  "type": "Feature",
  "properties": {
    "tgn:hierarchy":[
        "tgn:2194681",
        "tgn:1000001",
        "tgn:7012149",
        "tgn:7007251",
        "tgn:7029392"
    ],
    "tgn:id":2194681,
    "tgn:name":"Brier Creek",
    "tgn:placetype":[
        "aat:300008706"
    ]
},
  "bbox": [],
  "geometry": {"coordinates":[-88.7167,37.6833],"type":"Point"}
}