<<<<<<< HEAD
{
  "id": 7486649,
  "type": "Feature",
  "properties": {
    "tgn:hierarchy":[
        "tgn:7486649",
        "tgn:1000004",
        "tgn:7001014",
        "tgn:1000141",
        "tgn:7029392"
    ],
    "tgn:id":7486649,
    "tgn:name":"Baiyicuo",
    "tgn:placetype":[
        "aat:300387002"
    ]
},
  "bbox": [],
  "geometry": {"coordinates":[120.6,23.65],"type":"Point"}
}
=======
{"geometry":{"type":"Point","coordinates":[120.600000,23.650000]},"type":"Feature","properties":{"hierarchy":["tgn:7486649","tgn:1000004","tgn:7001014","tgn:1000141","tgn:7029392"],"placetype":["aat:300387002"],"id":7486649,"name:xx":"Baiyicuo"}}
>>>>>>> 03f74aca74312dbeaf24d7e61306dd6a786dc3d0
