{
  "id": 7588961,
  "type": "Feature",
  "properties": {
    "tgn:hierarchy":[
        "tgn:7588961",
        "tgn:1000004",
        "tgn:1001869",
        "tgn:7000198",
        "tgn:7029392"
    ],
    "tgn:id":7588961,
    "tgn:name:en":"Hodka",
    "tgn:placetype":[
        "aat:300008347"
    ]
},
  "bbox": [],
  "geometry": {"coordinates":[69.602601,23.659112],"type":"Point"}
}