{
  "id": 2469719,
  "type": "Feature",
  "properties": {
    "tgn:hierarchy":[
        "tgn:2469719",
        "tgn:1000001",
        "tgn:7012149",
        "tgn:7007250",
        "tgn:7029392"
    ],
    "tgn:id":2469719,
    "tgn:name":"Lookout Peak",
    "tgn:placetype":[
        "aat:300008798"
    ]
},
  "bbox": [],
  "geometry": {"coordinates":[-116.15,44.5167],"type":"Point"}
}