{
  "id": 2633183,
  "type": "Feature",
  "properties": {
    "tgn:hierarchy":[
        "tgn:2633183",
        "tgn:7002659",
        "tgn:1000001",
        "tgn:7012149",
        "tgn:2000035",
        "tgn:7029392"
    ],
    "tgn:id":2633183,
    "tgn:name":"Ruiler Cave",
    "tgn:placetype":[
        "aat:300008746"
    ]
},
  "bbox": [],
  "geometry": {"coordinates":[-86.3333,34.6167],"type":"Point"}
}