<<<<<<< HEAD
{
  "id": 7366300,
  "type": "Feature",
  "properties": {
    "tgn:hierarchy":[
        "tgn:7366300",
        "tgn:1000001",
        "tgn:7005597",
        "tgn:7005560",
        "tgn:7029392"
    ],
    "tgn:id":7366300,
    "tgn:name":"Escondida, Laguna",
    "tgn:placetype":[
        "aat:300008903"
    ]
},
  "bbox": [],
  "geometry": {"coordinates":[-97.933333,22.3],"type":"Point"}
}
=======
{"geometry":{"type":"Point","coordinates":[-97.933333,22.300000]},"type":"Feature","properties":{"hierarchy":["tgn:7366300","tgn:1000001","tgn:7005597","tgn:7005560","tgn:7029392"],"placetype":["aat:300008903"],"id":7366300,"name:xx":"Escondida, Laguna"}}
>>>>>>> 03f74aca74312dbeaf24d7e61306dd6a786dc3d0
