{
  "id": 2325499,
  "type": "Feature",
  "properties": {
    "tgn:hierarchy":[
        "tgn:2325499",
        "tgn:1000001",
        "tgn:7012149",
        "tgn:2001856",
        "tgn:7007825",
        "tgn:7029392"
    ],
    "tgn:id":2325499,
    "tgn:name":"Festus Jackson Lake",
    "tgn:placetype":[
        "aat:300006191"
    ]
},
  "bbox": [],
  "geometry": {"coordinates":[-88.1833,35.55],"type":"Point"}
}