{
  "id": 7459706,
  "type": "Feature",
  "properties": {
    "tgn:hierarchy":[
        "tgn:7459706",
        "tgn:7002445",
        "tgn:1000003",
        "tgn:7008117",
        "tgn:7008591",
        "tgn:7029392"
    ],
    "tgn:id":7459706,
    "tgn:name:en":"Natland",
    "tgn:placetype":[
        "aat:300008347"
    ]
},
  "bbox": [],
  "geometry": {"coordinates":[-2.733333,54.283333],"type":"Point"}
}