{
  "id": 1110002,
  "type": "Feature",
  "properties": {
    "tgn:hierarchy":[
        "tgn:1110002",
        "tgn:1000985",
        "tgn:7016529",
        "tgn:7016531",
        "tgn:1000004",
        "tgn:1000120",
        "tgn:7029392"
    ],
    "tgn:id":1110002,
    "tgn:name":"Hidaka-sammyaku",
    "tgn:placetype":[
        "aat:300386831"
    ]
},
  "bbox": [],
  "geometry": {"coordinates":[142.75,42.6667],"type":"Point"}
}