{
  "id": 2504343,
  "type": "Feature",
  "properties": {
    "tgn:hierarchy":[
        "tgn:2504343",
        "tgn:1000001",
        "tgn:7012149",
        "tgn:2002380",
        "tgn:7007923",
        "tgn:7029392"
    ],
    "tgn:id":2504343,
    "tgn:name":"Meadowdale",
    "tgn:placetype":[
        "aat:300008347"
    ]
},
  "bbox": [],
  "geometry": {"coordinates":[-104.6833,42.55],"type":"Point"}
}