{
  "id": 2290800,
  "type": "Feature",
  "properties": {
    "tgn:hierarchy":[
        "tgn:2290800",
        "tgn:1000001",
        "tgn:7012149",
        "tgn:7007157",
        "tgn:2000188",
        "tgn:7029392"
    ],
    "tgn:id":2290800,
    "tgn:name":"Dog Creek Mountain",
    "tgn:placetype":[
        "aat:300008798"
    ]
},
  "bbox": [],
  "geometry": {"coordinates":[-122.5167,40.8833],"type":"Point"}
}