{
  "id": 7591006,
  "type": "Feature",
  "properties": {
    "tgn:hierarchy":[
        "tgn:7591006",
        "tgn:1000004",
        "tgn:7000198",
        "tgn:7000799",
        "tgn:7029392"
    ],
    "tgn:id":7591006,
    "tgn:name:en":"Kam\u0101id",
    "tgn:placetype":[
        "aat:300008347"
    ]
},
  "bbox": [],
  "geometry": {"coordinates":[74.412563,32.9577],"type":"Point"}
}