{
  "id": 7344763,
  "type": "Feature",
  "properties": {
    "tgn:hierarchy":[
        "tgn:7344763",
        "tgn:7002827",
        "tgn:1000003",
        "tgn:7002789",
        "tgn:1000095",
        "tgn:7029392"
    ],
    "tgn:id":7344763,
    "tgn:name":"Amunartia",
    "tgn:placetype":[
        "aat:300008347"
    ]
},
  "bbox": [],
  "geometry": {"coordinates":[-3.033333,42.35],"type":"Point"}
}