{
  "id": 2674937,
  "type": "Feature",
  "properties": {
    "tgn:hierarchy":[
        "tgn:2674937",
        "tgn:1000001",
        "tgn:7012149",
        "tgn:2001451",
        "tgn:7007566",
        "tgn:7029392"
    ],
    "tgn:id":2674937,
    "tgn:name":"Soda Dam Springs",
    "tgn:placetype":[
        "aat:300000390"
    ]
},
  "bbox": [],
  "geometry": {"coordinates":[-106.6833,35.7833],"type":"Point"}
}