{
  "id": 7160867,
  "type": "Feature",
  "properties": {
    "tgn:hierarchy":[
        "tgn:7160867",
        "tgn:7003669",
        "tgn:1000003",
        "tgn:7000084",
        "tgn:7029392"
    ],
    "tgn:id":7160867,
    "tgn:name":"Hochwimm",
    "tgn:placetype":[
        "aat:300008347"
    ]
},
  "bbox": [],
  "geometry": {"coordinates":[12.85,48.616667],"type":"Point"}
}