{
  "id": 2320567,
  "type": "Feature",
  "properties": {
    "tgn:hierarchy":[
        "tgn:2320567",
        "tgn:1000001",
        "tgn:7012149",
        "tgn:2001713",
        "tgn:7007708",
        "tgn:7029392"
    ],
    "tgn:id":2320567,
    "tgn:name":"Ewe Creek",
    "tgn:placetype":[
        "aat:300008706"
    ]
},
  "bbox": [],
  "geometry": {"coordinates":[-123.4333,42.4833],"type":"Point"}
}