{
  "id": 7569011,
  "type": "Feature",
  "properties": {
    "tgn:hierarchy":[
        "tgn:7569011",
        "tgn:1000004",
        "tgn:7000198",
        "tgn:1001996",
        "tgn:7029392"
    ],
    "tgn:id":7569011,
    "tgn:name:en":"Tikri Protected Forest",
    "tgn:placetype":[
        "aat:300008863"
    ]
},
  "bbox": [],
  "geometry": {"coordinates":[77.108333,31.163889],"type":"Point"}
}