{
  "id": 7276605,
  "type": "Feature",
  "properties": {
    "tgn:hierarchy":[
        "tgn:7276605",
        "tgn:1001702",
        "tgn:1000049",
        "tgn:1000002",
        "tgn:7029392"
    ],
    "tgn:id":7276605,
    "tgn:name":"Acosta, Isla",
    "tgn:placetype":[
        "aat:300008791"
    ]
},
  "bbox": [],
  "geometry": {"coordinates":[-72.183333,-53.916667],"type":"Point"}
}