{
  "id": 7402942,
  "type": "Feature",
  "properties": {
    "tgn:hierarchy":[
        "tgn:7402942",
        "tgn:1000001",
        "tgn:1001906",
        "tgn:7005560",
        "tgn:7029392"
    ],
    "tgn:id":7402942,
    "tgn:name":"La Escondida",
    "tgn:placetype":[
        "aat:300008347"
    ]
},
  "bbox": [],
  "geometry": {"coordinates":[-104.283333,21.816667],"type":"Point"}
}