{
  "id": 7196834,
  "type": "Feature",
  "properties": {
    "tgn:hierarchy":[
        "tgn:7196834",
        "tgn:1000003",
        "tgn:7003685",
        "tgn:7000084",
        "tgn:7029392"
    ],
    "tgn:id":7196834,
    "tgn:name":"Das Reich",
    "tgn:placetype":[
        "aat:300000206"
    ]
},
  "bbox": [],
  "geometry": {"coordinates":[12.916667,51.233333],"type":"Point"}
}