{
  "id": 2560721,
  "type": "Feature",
  "properties": {
    "tgn:hierarchy":[
        "tgn:2560721",
        "tgn:1000001",
        "tgn:2001435",
        "tgn:7012149",
        "tgn:7007566",
        "tgn:7029392"
    ],
    "tgn:id":2560721,
    "tgn:name":"Organ Peak",
    "tgn:placetype":[
        "aat:300008798"
    ]
},
  "bbox": [],
  "geometry": {"coordinates":[-106.5333,32.3167],"type":"Point"}
}