<<<<<<< HEAD
{
  "id": 2768877,
  "type": "Feature",
  "properties": {
    "tgn:hierarchy":[
        "tgn:2768877",
        "tgn:1000001",
        "tgn:7012149",
        "tgn:1002478",
        "tgn:7007826",
        "tgn:7029392"
    ],
    "tgn:id":2768877,
    "tgn:name":"Whitney Creek",
    "tgn:placetype":[
        "aat:300008706"
    ]
},
  "bbox": [],
  "geometry": {"coordinates":[-97.3,31.9833],"type":"Point"}
}
=======
{"geometry":{"type":"Point","coordinates":[-97.300000,31.983300]},"type":"Feature","properties":{"hierarchy":["tgn:2768877","tgn:1000001","tgn:7012149","tgn:1002478","tgn:7007826","tgn:7029392"],"placetype":["aat:300008706"],"id":2768877,"name:xx":"Whitney Creek"}}
>>>>>>> 03f74aca74312dbeaf24d7e61306dd6a786dc3d0
