{
  "id": 2530001,
  "type": "Feature",
  "properties": {
    "tgn:hierarchy":[
        "tgn:2530001",
        "tgn:1000001",
        "tgn:7012149",
        "tgn:2001255",
        "tgn:7007523",
        "tgn:7029392"
    ],
    "tgn:id":2530001,
    "tgn:name":"Mud Spring",
    "tgn:placetype":[
        "aat:300008697"
    ]
},
  "bbox": [],
  "geometry": {"coordinates":[-90.2833,36.9667],"type":"Point"}
}