<<<<<<< HEAD
{
  "id": 2403518,
  "type": "Feature",
  "properties": {
    "tgn:hierarchy":[
        "tgn:2403518",
        "tgn:1000001",
        "tgn:7012149",
        "tgn:2000823",
        "tgn:7007255",
        "tgn:7029392"
    ],
    "tgn:id":2403518,
    "tgn:name":"Howard Branch",
    "tgn:placetype":[
        "aat:300008699"
    ]
},
  "bbox": [],
  "geometry": {"coordinates":[-88.3833,36.9667],"type":"Point"}
}
=======
{"geometry":{"type":"Point","coordinates":[-88.383300,36.966700]},"type":"Feature","properties":{"hierarchy":["tgn:2403518","tgn:1000001","tgn:7012149","tgn:2000823","tgn:7007255","tgn:7029392"],"placetype":["aat:300008699"],"id":2403518,"name:xx":"Howard Branch"}}
>>>>>>> 03f74aca74312dbeaf24d7e61306dd6a786dc3d0
