{
  "id": 2492841,
  "type": "Feature",
  "properties": {
    "tgn:hierarchy":[
        "tgn:2492841",
        "tgn:1000001",
        "tgn:2000924",
        "tgn:7012149",
        "tgn:7007515",
        "tgn:7029392"
    ],
    "tgn:id":2492841,
    "tgn:name":"Mark Island",
    "tgn:placetype":[
        "aat:300008791"
    ]
},
  "bbox": [],
  "geometry": {"coordinates":[-68.9833,44.1667],"type":"Point"}
}