{
  "id": 7221767,
  "type": "Feature",
  "properties": {
    "tgn:hierarchy":[
        "tgn:7221767",
        "tgn:7002681",
        "tgn:7001395",
        "tgn:1000003",
        "tgn:1000074",
        "tgn:7029392"
    ],
    "tgn:id":7221767,
    "tgn:name":"Mil\u00e1kion",
    "tgn:placetype":[
        "aat:300008347"
    ]
},
  "bbox": [],
  "geometry": {"coordinates":[24.066667,38.383333],"type":"Point"}
}