{
  "id": 2052915,
  "type": "Feature",
  "properties": {
    "tgn:hierarchy":[
        "tgn:2052915",
        "tgn:1000001",
        "tgn:7012149",
        "tgn:1002892",
        "tgn:7007520",
        "tgn:7029392"
    ],
    "tgn:id":2052915,
    "tgn:name":"Owosso",
    "tgn:placetype":[
        "aat:300008347"
    ]
},
  "bbox": [],
  "geometry": {"coordinates":[-84.1667,42.9833],"type":"Point"}
}