{
  "id": 2153579,
  "type": "Feature",
  "properties": {
    "tgn:hierarchy":[
        "tgn:2153579",
        "tgn:7002659",
        "tgn:1000001",
        "tgn:7012149",
        "tgn:2000066",
        "tgn:7029392"
    ],
    "tgn:id":2153579,
    "tgn:name":"Bear Branch",
    "tgn:placetype":[
        "aat:300008699"
    ]
},
  "bbox": [],
  "geometry": {"coordinates":[-87.15,34.0333],"type":"Point"}
}