{
  "id": 7016140,
  "type": "Feature",
  "properties": {
    "tgn:hierarchy":[
        "tgn:7016140",
        "tgn:1001053",
        "tgn:1000004",
        "tgn:7018451",
        "tgn:1000144",
        "tgn:7029392"
    ],
    "tgn:id":7016140,
    "tgn:name":"Bergama",
    "tgn:placetype":[
        "aat:300008347",
        "aat:300000810",
        "aat:300008389",
        "aat:300008375"
    ]
},
  "bbox": [],
  "geometry": {"coordinates":[27.1667,39.1333],"type":"Point"}
}