<<<<<<< HEAD
{
  "id": 7354836,
  "type": "Feature",
  "properties": {
    "tgn:hierarchy":[
        "tgn:7354836",
        "tgn:1000001",
        "tgn:7005597",
        "tgn:7005560",
        "tgn:7029392"
    ],
    "tgn:id":7354836,
    "tgn:name":"Catetera, Laguna la",
    "tgn:placetype":[
        "aat:300008903"
    ]
},
  "bbox": [],
  "geometry": {"coordinates":[-97.216667,25.883333],"type":"Point"}
}
=======
{"geometry":{"type":"Point","coordinates":[-97.216667,25.883333]},"type":"Feature","properties":{"hierarchy":["tgn:7354836","tgn:1000001","tgn:7005597","tgn:7005560","tgn:7029392"],"placetype":["aat:300008903"],"id":7354836,"name:xx":"Catetera, Laguna la"}}
>>>>>>> 03f74aca74312dbeaf24d7e61306dd6a786dc3d0
