{
  "id": 1091221,
  "type": "Feature",
  "properties": {
    "tgn:hierarchy":[
        "tgn:1091221",
        "tgn:7001242",
        "tgn:1001741",
        "tgn:1000175",
        "tgn:7029392"
    ],
    "tgn:id":1091221,
    "tgn:name":"Nampala",
    "tgn:placetype":[
        "aat:300008347"
    ]
},
  "bbox": [],
  "geometry": {"coordinates":[-5.5167,15.3167],"type":"Point"}
}