{
  "id": 2115552,
  "type": "Feature",
  "properties": {
    "tgn:hierarchy":[
        "tgn:2115552",
        "tgn:1000001",
        "tgn:7012149",
        "tgn:7014510",
        "tgn:7007920",
        "tgn:7029392"
    ],
    "tgn:id":2115552,
    "tgn:name":"Concrete",
    "tgn:placetype":[
        "aat:300008347"
    ]
},
  "bbox": [],
  "geometry": {"coordinates":[-121.7333,48.5333],"type":"Point"}
}