{
  "id": 7542992,
  "type": "Feature",
  "properties": {
    "tgn:hierarchy":[
        "tgn:7542992",
        "tgn:7001242",
        "tgn:7016833",
        "tgn:7001336",
        "tgn:7029392"
    ],
    "tgn:id":7542992,
    "tgn:name:en":"Hayy\u0101lah, Jabal",
    "tgn:placetype":[
        "aat:300008795"
    ]
},
  "bbox": [],
  "geometry": {"coordinates":[34.300069,28.69271],"type":"Point"}
}