{
  "id": 2528793,
  "type": "Feature",
  "properties": {
    "tgn:hierarchy":[
        "tgn:2528793",
        "tgn:1000001",
        "tgn:2000275",
        "tgn:7012149",
        "tgn:7007240",
        "tgn:7029392"
    ],
    "tgn:id":2528793,
    "tgn:name":"Mud Creek",
    "tgn:placetype":[
        "aat:300008706"
    ]
},
  "bbox": [],
  "geometry": {"coordinates":[-83.2333,29.8667],"type":"Point"}
}