{
  "id": 2418733,
  "type": "Feature",
  "properties": {
    "tgn:hierarchy":[
        "tgn:2418733",
        "tgn:1000001",
        "tgn:7012149",
        "tgn:2002276",
        "tgn:7013961",
        "tgn:7029392"
    ],
    "tgn:id":2418733,
    "tgn:name":"Jakes Run",
    "tgn:placetype":[
        "aat:300008699"
    ]
},
  "bbox": [],
  "geometry": {"coordinates":[-80.6833,40.0167],"type":"Point"}
}