{
  "id": 2348959,
  "type": "Feature",
  "properties": {
    "tgn:hierarchy":[
        "tgn:2348959",
        "tgn:1000001",
        "tgn:7012149",
        "tgn:1002984",
        "tgn:7007523",
        "tgn:7029392"
    ],
    "tgn:id":2348959,
    "tgn:name":"Giesel Hollow",
    "tgn:placetype":[
        "aat:300008761"
    ]
},
  "bbox": [],
  "geometry": {"coordinates":[-91.2667,38.7833],"type":"Point"}
}