{
  "id": 2449022,
  "type": "Feature",
  "properties": {
    "tgn:hierarchy":[
        "tgn:2449022",
        "tgn:1000001",
        "tgn:2000263",
        "tgn:7012149",
        "tgn:7007240",
        "tgn:7029392"
    ],
    "tgn:id":2449022,
    "tgn:name":"Lime Sink",
    "tgn:placetype":[
        "aat:300386845"
    ]
},
  "bbox": [],
  "geometry": {"coordinates":[-83.1167,29.45],"type":"Point"}
}