{
  "id": 2281910,
  "type": "Feature",
  "properties": {
    "tgn:hierarchy":[
        "tgn:2281910",
        "tgn:1000001",
        "tgn:7012149",
        "tgn:2001297",
        "tgn:7007524",
        "tgn:7029392"
    ],
    "tgn:id":2281910,
    "tgn:name":"Deer Creek Spring",
    "tgn:placetype":[
        "aat:300008697"
    ]
},
  "bbox": [],
  "geometry": {"coordinates":[-106.05,45.6333],"type":"Point"}
}