{
  "id": 7496298,
  "type": "Feature",
  "properties": {
    "tgn:hierarchy":[
        "tgn:7496298",
        "tgn:1000004",
        "tgn:1000454",
        "tgn:1000141",
        "tgn:7029392"
    ],
    "tgn:id":7496298,
    "tgn:name":"Peifu Qiao",
    "tgn:placetype":[
        "aat:300007836"
    ]
},
  "bbox": [],
  "geometry": {"coordinates":[121.493494,24.952144],"type":"Point"}
}