{
  "id": 1027283,
  "type": "Feature",
  "properties": {
    "tgn:hierarchy":[
        "tgn:1027283",
        "tgn:7027131",
        "tgn:1000003",
        "tgn:7011765",
        "tgn:7029392"
    ],
    "tgn:id":1027283,
    "tgn:name":"Kokava nad Rimavicou",
    "tgn:placetype":[
        "aat:300008347"
    ]
},
  "bbox": [],
  "geometry": {"coordinates":[19.8333,48.5667],"type":"Point"}
}