{
  "id": 2516653,
  "type": "Feature",
  "properties": {
    "tgn:hierarchy":[
        "tgn:2516653",
        "tgn:1000001",
        "tgn:7012149",
        "tgn:2000346",
        "tgn:7007248",
        "tgn:7029392"
    ],
    "tgn:id":2516653,
    "tgn:name":"Mineral Springs Creek",
    "tgn:placetype":[
        "aat:300008706"
    ]
},
  "bbox": [],
  "geometry": {"coordinates":[-84.3167,34.85],"type":"Point"}
}