{
  "id": 1129710,
  "type": "Feature",
  "properties": {
    "tgn:hierarchy":[
        "tgn:1129710",
        "tgn:1000003",
        "tgn:1000070",
        "tgn:7029392"
    ],
    "tgn:id":1129710,
    "tgn:name":"Sasse",
    "tgn:placetype":[
        "aat:300008707"
    ]
},
  "bbox": [],
  "geometry": {"coordinates":[5.9167,44.25],"type":"Point"}
}