{
  "id": 2729377,
  "type": "Feature",
  "properties": {
    "tgn:hierarchy":[
        "tgn:2729377",
        "tgn:1000001",
        "tgn:7012149",
        "tgn:2001878",
        "tgn:7007825",
        "tgn:7029392"
    ],
    "tgn:id":2729377,
    "tgn:name":"Triplett Hollow",
    "tgn:placetype":[
        "aat:300008761"
    ]
},
  "bbox": [],
  "geometry": {"coordinates":[-87.85,36.2833],"type":"Point"}
}