{
  "id": 7389901,
  "type": "Feature",
  "properties": {
    "tgn:hierarchy":[
        "tgn:7389901",
        "tgn:7005583",
        "tgn:1000001",
        "tgn:7005560",
        "tgn:7029392"
    ],
    "tgn:id":7389901,
    "tgn:name":"Salitre de Abajo",
    "tgn:placetype":[
        "aat:300008347"
    ]
},
  "bbox": [],
  "geometry": {"coordinates":[-106.066667,25.833333],"type":"Point"}
}