{
  "id": 1086349,
  "type": "Feature",
  "properties": {
    "tgn:hierarchy":[
        "tgn:1086349",
        "tgn:1001060",
        "tgn:1000004",
        "tgn:7018456",
        "tgn:1000144",
        "tgn:7029392"
    ],
    "tgn:id":1086349,
    "tgn:name":"Gerger",
    "tgn:placetype":[
        "aat:300008347"
    ]
},
  "bbox": [],
  "geometry": {"coordinates":[38.8333,37.9667],"type":"Point"}
}