{
  "id": 7563748,
  "type": "Feature",
  "properties": {
    "tgn:hierarchy":[
        "tgn:7563748",
        "tgn:1000004",
        "tgn:7000198",
        "tgn:7016722",
        "tgn:7029392"
    ],
    "tgn:id":7563748,
    "tgn:name:en":"N\u0101hli",
    "tgn:placetype":[
        "aat:300008347"
    ]
},
  "bbox": [],
  "geometry": {"coordinates":[79.761959,26.562872],"type":"Point"}
}