{
  "id": 7537564,
  "type": "Feature",
  "properties": {
    "tgn:hierarchy":[
        "tgn:7537564",
        "tgn:7001242",
        "tgn:1001075",
        "tgn:7016833",
        "tgn:7029392"
    ],
    "tgn:id":7537564,
    "tgn:name:en":"Nashw, Kawm an",
    "tgn:placetype":[
        "aat:300008777"
    ]
},
  "bbox": [],
  "geometry": {"coordinates":[30.166667,31.15],"type":"Point"}
}