{
  "id": 7559394,
  "type": "Feature",
  "properties": {
    "tgn:hierarchy":[
        "tgn:7559394",
        "tgn:1000004",
        "tgn:7031781",
        "tgn:7000198",
        "tgn:7029392"
    ],
    "tgn:id":7559394,
    "tgn:name:en":"Pendra",
    "tgn:placetype":[
        "aat:300008347"
    ]
},
  "bbox": [],
  "geometry": {"coordinates":[81.958577,22.777035],"type":"Point"}
}