{
  "id": 2132807,
  "type": "Feature",
  "properties": {
    "tgn:hierarchy":[
        "tgn:2132807",
        "tgn:1000001",
        "tgn:7012149",
        "tgn:2000891",
        "tgn:7007256",
        "tgn:7029392"
    ],
    "tgn:id":2132807,
    "tgn:name":"Anderson Bay",
    "tgn:placetype":[
        "aat:300132316"
    ]
},
  "bbox": [],
  "geometry": {"coordinates":[-89.55,29.4167],"type":"Point"}
}