{
  "id": 1130190,
  "type": "Feature",
  "properties": {
    "tgn:hierarchy":[
        "tgn:1130190",
        "tgn:1000003",
        "tgn:1000468",
        "tgn:7006278",
        "tgn:7029392"
    ],
    "tgn:id":1130190,
    "tgn:name":"Sorok-patak",
    "tgn:placetype":[
        "aat:300008707"
    ]
},
  "bbox": [],
  "geometry": {"coordinates":[16.8333,47.1167],"type":"Point"}
}