{
  "id": 7557842,
  "type": "Feature",
  "properties": {
    "tgn:hierarchy":[
        "tgn:7557842",
        "tgn:1000004",
        "tgn:7000198",
        "tgn:1001886",
        "tgn:7029392"
    ],
    "tgn:id":7557842,
    "tgn:name:en":"Pathan\u0101mthitta",
    "tgn:placetype":[
        "aat:300008347"
    ]
},
  "bbox": [],
  "geometry": {"coordinates":[76.783333,9.266667],"type":"Point"}
}