{
  "id": 7176322,
  "type": "Feature",
  "properties": {
    "tgn:hierarchy":[
        "tgn:7176322",
        "tgn:7003669",
        "tgn:1000003",
        "tgn:7000084",
        "tgn:7029392"
    ],
    "tgn:id":7176322,
    "tgn:name":"Haag",
    "tgn:placetype":[
        "aat:300008347"
    ]
},
  "bbox": [],
  "geometry": {"coordinates":[10.483333,49.75],"type":"Point"}
}