{
  "id": 1120427,
  "type": "Feature",
  "properties": {
    "tgn:hierarchy":[
        "tgn:1120427",
        "tgn:1000001",
        "tgn:7012149",
        "tgn:1002298",
        "tgn:7007157",
        "tgn:7029392"
    ],
    "tgn:id":1120427,
    "tgn:name":"San Pablo Reservoir",
    "tgn:placetype":[
        "aat:300006191"
    ]
},
  "bbox": [],
  "geometry": {"coordinates":[-122.25,37.9333],"type":"Point"}
}