{
  "id": 1078969,
  "type": "Feature",
  "properties": {
    "tgn:hierarchy":[
        "tgn:1078969",
        "tgn:1000004",
        "tgn:7001282",
        "tgn:7000231",
        "tgn:7029392"
    ],
    "tgn:id":1078969,
    "tgn:name":"Ardak\u0101n",
    "tgn:placetype":[
        "aat:300008347"
    ]
},
  "bbox": [],
  "geometry": {"coordinates":[51.9833,30.2667],"type":"Point"}
}