<<<<<<< HEAD
{
  "id": 2769489,
  "type": "Feature",
  "properties": {
    "tgn:hierarchy":[
        "tgn:2769489",
        "tgn:1000001",
        "tgn:2000201",
        "tgn:7012149",
        "tgn:7007158",
        "tgn:7029392"
    ],
    "tgn:id":2769489,
    "tgn:name":"Wide-awake Gulch",
    "tgn:placetype":[
        "aat:300008761"
    ]
},
  "bbox": [],
  "geometry": {"coordinates":[-105.7667,39.6667],"type":"Point"}
}
=======
{"geometry":{"type":"Point","coordinates":[-105.766700,39.666700]},"type":"Feature","properties":{"hierarchy":["tgn:2769489","tgn:1000001","tgn:2000201","tgn:7012149","tgn:7007158","tgn:7029392"],"placetype":["aat:300008761"],"id":2769489,"name:xx":"Wide-awake Gulch"}}
>>>>>>> 03f74aca74312dbeaf24d7e61306dd6a786dc3d0
