{
  "id": 2106007,
  "type": "Feature",
  "properties": {
    "tgn:hierarchy":[
        "tgn:2106007",
        "tgn:1000001",
        "tgn:7012149",
        "tgn:1002315",
        "tgn:7007826",
        "tgn:7029392"
    ],
    "tgn:id":2106007,
    "tgn:name":"Mesquite",
    "tgn:placetype":[
        "aat:300008347"
    ]
},
  "bbox": [],
  "geometry": {"coordinates":[-96.5833,32.7667],"type":"Point"}
}