{
  "id": 7528758,
  "type": "Feature",
  "properties": {
    "tgn:hierarchy":[
        "tgn:7528758",
        "tgn:7001242",
        "tgn:7016833",
        "tgn:7001335",
        "tgn:7029392"
    ],
    "tgn:id":7528758,
    "tgn:name:en":"Umm Khushayb, Habr",
    "tgn:placetype":[
        "aat:300386870"
    ]
},
  "bbox": [],
  "geometry": {"coordinates":[32.714302,30.367041],"type":"Point"}
}