{
  "id": 2221884,
  "type": "Feature",
  "properties": {
    "tgn:hierarchy":[
        "tgn:2221884",
        "tgn:1000001",
        "tgn:7012149",
        "tgn:2001291",
        "tgn:7007524",
        "tgn:7029392"
    ],
    "tgn:id":2221884,
    "tgn:name":"Carlton Lake",
    "tgn:placetype":[
        "aat:300008680"
    ]
},
  "bbox": [],
  "geometry": {"coordinates":[-114.2167,46.6833],"type":"Point"}
}