{
  "id": 7580691,
  "type": "Feature",
  "properties": {
    "tgn:hierarchy":[
        "tgn:7580691",
        "tgn:1000004",
        "tgn:7000198",
        "tgn:7016694",
        "tgn:7029392"
    ],
    "tgn:id":7580691,
    "tgn:name:en":"Suktel River",
    "tgn:placetype":[
        "aat:300008699"
    ]
},
  "bbox": [],
  "geometry": {"coordinates":[83.75,20.766667],"type":"Point"}
}