{
  "id": 2689954,
  "type": "Feature",
  "properties": {
    "tgn:hierarchy":[
        "tgn:2689954",
        "tgn:7006450",
        "tgn:1000001",
        "tgn:7030517",
        "tgn:7012149",
        "tgn:7029392"
    ],
    "tgn:id":2689954,
    "tgn:name":"Squirrel Point",
    "tgn:placetype":[
        "aat:300008850"
    ]
},
  "bbox": [],
  "geometry": {"coordinates":[-154.25,59.6667],"type":"Point"}
}