{
  "id": 2732163,
  "type": "Feature",
  "properties": {
    "tgn:hierarchy":[
        "tgn:2732163",
        "tgn:1000001",
        "tgn:7006451",
        "tgn:2000093",
        "tgn:7012149",
        "tgn:7029392"
    ],
    "tgn:id":2732163,
    "tgn:name":"Tunnel Spring",
    "tgn:placetype":[
        "aat:300008697"
    ]
},
  "bbox": [],
  "geometry": {"coordinates":[-110.8833,33.2667],"type":"Point"}
}