{
  "id": 7229399,
  "type": "Feature",
  "properties": {
    "tgn:hierarchy":[
        "tgn:7229399",
        "tgn:7002725",
        "tgn:7002715",
        "tgn:1000003",
        "tgn:1000074",
        "tgn:7029392"
    ],
    "tgn:id":7229399,
    "tgn:name":"Ere\u00edpia Kyr\u00e1don",
    "tgn:placetype":[
        "aat:300008057"
    ]
},
  "bbox": [],
  "geometry": {"coordinates":[22.991944,40.924167],"type":"Point"}
}