{
  "id": 7593557,
  "type": "Feature",
  "properties": {
    "tgn:hierarchy":[
        "tgn:7593557",
        "tgn:7005424",
        "tgn:1000001",
        "tgn:7005388",
        "tgn:7029392"
    ],
    "tgn:id":7593557,
    "tgn:name":"Pueblo Nuevo",
    "tgn:placetype":[
        "aat:300008347"
    ]
},
  "bbox": [],
  "geometry": {"coordinates":[-71.163,19.578],"type":"Point"}
}