{
  "id": 2322914,
  "type": "Feature",
  "properties": {
    "tgn:hierarchy":[
        "tgn:2322914",
        "tgn:1000001",
        "tgn:7012149",
        "tgn:2000291",
        "tgn:7007240",
        "tgn:7029392"
    ],
    "tgn:id":2322914,
    "tgn:name":"Fanning Branch",
    "tgn:placetype":[
        "aat:300008699"
    ]
},
  "bbox": [],
  "geometry": {"coordinates":[-85.7333,30.5667],"type":"Point"}
}