{
  "id": 2567252,
  "type": "Feature",
  "properties": {
    "tgn:hierarchy":[
        "tgn:2567252",
        "tgn:1000001",
        "tgn:2001945",
        "tgn:7012149",
        "tgn:7007826",
        "tgn:7029392"
    ],
    "tgn:id":2567252,
    "tgn:name":"Panther Peaks",
    "tgn:placetype":[
        "aat:300008798"
    ]
},
  "bbox": [],
  "geometry": {"coordinates":[-102.9333,30.05],"type":"Point"}
}