{
  "id": 7149063,
  "type": "Feature",
  "properties": {
    "tgn:hierarchy":[
        "tgn:7149063",
        "tgn:7003669",
        "tgn:1000003",
        "tgn:7000084",
        "tgn:7029392"
    ],
    "tgn:id":7149063,
    "tgn:name":"K\u00fcmmersbuch",
    "tgn:placetype":[
        "aat:300008347"
    ]
},
  "bbox": [],
  "geometry": {"coordinates":[11.816667,49.516667],"type":"Point"}
}