{
  "id": 7591631,
  "type": "Feature",
  "properties": {
    "tgn:hierarchy":[
        "tgn:7591631",
        "tgn:1000004",
        "tgn:7000198",
        "tgn:7000799",
        "tgn:7029392"
    ],
    "tgn:id":7591631,
    "tgn:name:en":"Thikri\u0101n",
    "tgn:placetype":[
        "aat:300008347"
    ]
},
  "bbox": [],
  "geometry": {"coordinates":[74.752778,32.620833],"type":"Point"}
}