{
  "id": 2015070,
  "type": "Feature",
  "properties": {
    "tgn:hierarchy":[
        "tgn:2015070",
        "tgn:1000001",
        "tgn:7012149",
        "tgn:7007157",
        "tgn:1002710",
        "tgn:7029392"
    ],
    "tgn:id":2015070,
    "tgn:name":"Yuba Pass",
    "tgn:placetype":[
        "aat:300387016"
    ]
},
  "bbox": [],
  "geometry": {"coordinates":[-120.5833,39.3167],"type":"Point"}
}