{
  "id": 2625935,
  "type": "Feature",
  "properties": {
    "tgn:hierarchy":[
        "tgn:2625935",
        "tgn:1000001",
        "tgn:2002144",
        "tgn:7012149",
        "tgn:7007919",
        "tgn:7029392"
    ],
    "tgn:id":2625935,
    "tgn:name":"Rocky Branch",
    "tgn:placetype":[
        "aat:300008699"
    ]
},
  "bbox": [],
  "geometry": {"coordinates":[-79.6167,37.25],"type":"Point"}
}