{
  "id": 2415919,
  "type": "Feature",
  "properties": {
    "tgn:hierarchy":[
        "tgn:2415919",
        "tgn:1000001",
        "tgn:7012149",
        "tgn:7022240",
        "tgn:7007523",
        "tgn:7029392"
    ],
    "tgn:id":2415919,
    "tgn:name":"Ivory",
    "tgn:placetype":[
        "aat:300008347"
    ]
},
  "bbox": [],
  "geometry": {"coordinates":[-90.2667,38.5167],"type":"Point"}
}