{
  "id": 7506130,
  "type": "Feature",
  "properties": {
    "tgn:hierarchy":[
        "tgn:7506130",
        "tgn:1008380",
        "tgn:1000226",
        "tgn:7016827",
        "tgn:1000006",
        "tgn:7029392"
    ],
    "tgn:id":7506130,
    "tgn:name:en":"Schnapper Rock",
    "tgn:placetype":[
        "aat:300011692"
    ]
},
  "bbox": [],
  "geometry": {"coordinates":[174.016667,-39.066667],"type":"Point"}
}