{
  "id": 7035890,
  "type": "Feature",
  "properties": {
    "tgn:hierarchy":[
        "tgn:7035890",
        "tgn:7002991",
        "tgn:1000003",
        "tgn:7002997",
        "tgn:1000080",
        "tgn:7029392"
    ],
    "tgn:id":7035890,
    "tgn:name":"Carro, Monte",
    "tgn:placetype":[
        "aat:300008795"
    ]
},
  "bbox": [],
  "geometry": {"coordinates":[12.658611,46.600833],"type":"Point"}
}