<<<<<<< HEAD
{
  "id": 7170015,
  "type": "Feature",
  "properties": {
    "tgn:hierarchy":[
        "tgn:7170015",
        "tgn:1000003",
        "tgn:7003685",
        "tgn:7000084",
        "tgn:7029392"
    ],
    "tgn:id":7170015,
    "tgn:name":"Hetzdorf",
    "tgn:placetype":[
        "aat:300008347"
    ]
},
  "bbox": [],
  "geometry": {"coordinates":[12.95,51.183333],"type":"Point"}
}
=======
{"geometry":{"type":"Point","coordinates":[12.950000,51.183333]},"type":"Feature","properties":{"hierarchy":["tgn:7170015","tgn:1000003","tgn:7003685","tgn:7000084","tgn:7029392"],"placetype":["aat:300008347"],"id":7170015,"name:xx":"Hetzdorf"}}
>>>>>>> 03f74aca74312dbeaf24d7e61306dd6a786dc3d0
