{
  "id": 7271667,
  "type": "Feature",
  "properties": {
    "tgn:concordances":{
        "gn:id":"2746361"
    },
    "tgn:hierarchy":[
        "tgn:7271667",
        "tgn:1000003",
        "tgn:7003613",
        "tgn:7016845",
        "tgn:7029392"
    ],
    "tgn:id":7271667,
    "tgn:name:nl":"Thesinge",
    "tgn:placetype":[
        "aat:300008347"
    ]
},
  "bbox": [],
  "geometry": {"coordinates":[6.65,53.266667],"type":"Point"}
}