{
  "id": 1054814,
  "type": "Feature",
  "properties": {
    "tgn:hierarchy":[
        "tgn:1054814",
        "tgn:7006625",
        "tgn:7006632",
        "tgn:1000003",
        "tgn:7006540",
        "tgn:7029392"
    ],
    "tgn:id":1054814,
    "tgn:name":"K\u00e4ina",
    "tgn:placetype":[
        "aat:300008347"
    ]
},
  "bbox": [],
  "geometry": {"coordinates":[22.796,58.825],"type":"Point"}
}