{
  "id": 2749743,
  "type": "Feature",
  "properties": {
    "tgn:hierarchy":[
        "tgn:2749743",
        "tgn:1000001",
        "tgn:7014423",
        "tgn:7012149",
        "tgn:7007517",
        "tgn:7029392"
    ],
    "tgn:id":2749743,
    "tgn:name":"Walnut Hill",
    "tgn:placetype":[
        "aat:300008798"
    ]
},
  "bbox": [],
  "geometry": {"coordinates":[-70.85,42.15],"type":"Point"}
}