{
  "id": 2346215,
  "type": "Feature",
  "properties": {
    "tgn:hierarchy":[
        "tgn:2346215",
        "tgn:1000001",
        "tgn:1002245",
        "tgn:7012149",
        "tgn:7007568",
        "tgn:7029392"
    ],
    "tgn:id":2346215,
    "tgn:name":"Gates Creek",
    "tgn:placetype":[
        "aat:300008706"
    ]
},
  "bbox": [],
  "geometry": {"coordinates":[-78.3333,42.2833],"type":"Point"}
}