{
  "id": 7582130,
  "type": "Feature",
  "properties": {
    "tgn:hierarchy":[
        "tgn:7582130",
        "tgn:1000004",
        "tgn:7000198",
        "tgn:7016722",
        "tgn:7029392"
    ],
    "tgn:id":7582130,
    "tgn:name:en":"Solda Reserved Forest",
    "tgn:placetype":[
        "aat:300008865"
    ]
},
  "bbox": [],
  "geometry": {"coordinates":[78.824136,24.252468],"type":"Point"}
}