{
  "id": 7349566,
  "type": "Feature",
  "properties": {
    "tgn:hierarchy":[
        "tgn:7349566",
        "tgn:1000001",
        "tgn:1001960",
        "tgn:7005560",
        "tgn:7029392"
    ],
    "tgn:id":7349566,
    "tgn:name":"Aguajito, Arroyo del",
    "tgn:placetype":[
        "aat:300266554",
        "aat:300008699"
    ]
},
  "bbox": [],
  "geometry": {"coordinates":[-108.95,27.15],"type":"Point"}
}