{
  "id": 2053376,
  "type": "Feature",
  "properties": {
    "tgn:hierarchy":[
        "tgn:2053376",
        "tgn:1000001",
        "tgn:7012149",
        "tgn:1002679",
        "tgn:7007520",
        "tgn:7029392"
    ],
    "tgn:id":2053376,
    "tgn:name":"South Rockwood",
    "tgn:placetype":[
        "aat:300008347"
    ]
},
  "bbox": [],
  "geometry": {"coordinates":[-83.25,42.05],"type":"Point"}
}