{
  "id": 7586686,
  "type": "Feature",
  "properties": {
    "tgn:hierarchy":[
        "tgn:7586686",
        "tgn:1000004",
        "tgn:7000198",
        "tgn:7000799",
        "tgn:7029392"
    ],
    "tgn:id":7586686,
    "tgn:name:en":"Bat\u0101nw\u0101la N\u0101r",
    "tgn:placetype":[
        "aat:300008699"
    ]
},
  "bbox": [],
  "geometry": {"coordinates":[74.089731,34.316339],"type":"Point"}
}