{
  "id": 7294632,
  "type": "Feature",
  "properties": {
    "tgn:hierarchy":[
        "tgn:7294632",
        "tgn:7002758",
        "tgn:1001316",
        "tgn:1000003",
        "tgn:1000095",
        "tgn:7029392"
    ],
    "tgn:id":7294632,
    "tgn:name":"Venta del Charco",
    "tgn:placetype":[
        "aat:300008347"
    ]
},
  "bbox": [],
  "geometry": {"coordinates":[-4.266667,38.216667],"type":"Point"}
}