{
  "id": 2403750,
  "type": "Feature",
  "properties": {
    "tgn:hierarchy":[
        "tgn:2403750",
        "tgn:1000001",
        "tgn:7012149",
        "tgn:2001506",
        "tgn:7007709",
        "tgn:7029392"
    ],
    "tgn:id":2403750,
    "tgn:name":"Howard Reef",
    "tgn:placetype":[
        "aat:300132348"
    ]
},
  "bbox": [],
  "geometry": {"coordinates":[-75.9667,35.1333],"type":"Point"}
}