{
  "id": 7474287,
  "type": "Feature",
  "properties": {
    "tgn:hierarchy":[
        "tgn:7474287",
        "tgn:7001004",
        "tgn:1000004",
        "tgn:1000141",
        "tgn:7029392"
    ],
    "tgn:id":7474287,
    "tgn:name":"Yueshijie",
    "tgn:placetype":[
        "aat:300008347"
    ]
},
  "bbox": [],
  "geometry": {"coordinates":[120.390556,22.886389],"type":"Point"}
}