{
  "id": 2697377,
  "type": "Feature",
  "properties": {
    "tgn:hierarchy":[
        "tgn:2697377",
        "tgn:1000001",
        "tgn:1002712",
        "tgn:7012149",
        "tgn:7007159",
        "tgn:7029392"
    ],
    "tgn:id":2697377,
    "tgn:name":"Stony Island",
    "tgn:placetype":[
        "aat:300008791"
    ]
},
  "bbox": [],
  "geometry": {"coordinates":[-72.85,41.2333],"type":"Point"}
}