<<<<<<< HEAD
{
  "id": 7367277,
  "type": "Feature",
  "properties": {
    "tgn:hierarchy":[
        "tgn:7367277",
        "tgn:1000001",
        "tgn:7005589",
        "tgn:7005560",
        "tgn:7029392"
    ],
    "tgn:id":7367277,
    "tgn:name":"El Rucio",
    "tgn:placetype":[
        "aat:300008347"
    ]
},
  "bbox": [],
  "geometry": {"coordinates":[-100.433333,24.7],"type":"Point"}
}
=======
{"geometry":{"type":"Point","coordinates":[-100.433333,24.700000]},"type":"Feature","properties":{"hierarchy":["tgn:7367277","tgn:1000001","tgn:7005589","tgn:7005560","tgn:7029392"],"placetype":["aat:300008347"],"id":7367277,"name:xx":"El Rucio"}}
>>>>>>> 03f74aca74312dbeaf24d7e61306dd6a786dc3d0
