{
  "id": 7408678,
  "type": "Feature",
  "properties": {
    "tgn:hierarchy":[
        "tgn:7408678",
        "tgn:7005580",
        "tgn:1000001",
        "tgn:7005560",
        "tgn:7029392"
    ],
    "tgn:id":7408678,
    "tgn:name":"San Agust\u00edn",
    "tgn:placetype":[
        "aat:300008347"
    ]
},
  "bbox": [],
  "geometry": {"coordinates":[-91.433333,16.465278],"type":"Point"}
}