{
  "id": 7369312,
  "type": "Feature",
  "properties": {
    "tgn:hierarchy":[
        "tgn:7369312",
        "tgn:1000001",
        "tgn:7005590",
        "tgn:7005560",
        "tgn:7029392"
    ],
    "tgn:id":7369312,
    "tgn:name":"Jabal\u00ed",
    "tgn:placetype":[
        "aat:300008347"
    ]
},
  "bbox": [],
  "geometry": {"coordinates":[-102.516667,18.633333],"type":"Point"}
}