{
  "id": 2503329,
  "type": "Feature",
  "properties": {
    "tgn:hierarchy":[
        "tgn:2503329",
        "tgn:1000001",
        "tgn:2000197",
        "tgn:7012149",
        "tgn:7007158",
        "tgn:7029392"
    ],
    "tgn:id":2503329,
    "tgn:name":"McRae Arroyo",
    "tgn:placetype":[
        "aat:300008699"
    ]
},
  "bbox": [],
  "geometry": {"coordinates":[-103.0333,38.15],"type":"Point"}
}