{
  "id": 1117143,
  "type": "Feature",
  "properties": {
    "tgn:hierarchy":[
        "tgn:1117143",
        "tgn:7005685",
        "tgn:1000001",
        "tgn:7005805",
        "tgn:7029392"
    ],
    "tgn:id":1117143,
    "tgn:name":"Macoun Lake",
    "tgn:placetype":[
        "aat:300008680"
    ]
},
  "bbox": [],
  "geometry": {"coordinates":[-103.8333,56.5333],"type":"Point"}
}