{
  "id": 2057600,
  "type": "Feature",
  "properties": {
    "tgn:hierarchy":[
        "tgn:2057600",
        "tgn:1000001",
        "tgn:7012149",
        "tgn:2001139",
        "tgn:7007522",
        "tgn:7029392"
    ],
    "tgn:id":2057600,
    "tgn:name":"Terza",
    "tgn:placetype":[
        "aat:300008347",
        "aat:300387210"
    ]
},
  "bbox": [],
  "geometry": {"coordinates":[-89.85,34.35],"type":"Point"}
}