{
  "id": 2536771,
  "type": "Feature",
  "properties": {
    "tgn:hierarchy":[
        "tgn:2536771",
        "tgn:1000001",
        "tgn:7012149",
        "tgn:2000824",
        "tgn:7007255",
        "tgn:7029392"
    ],
    "tgn:id":2536771,
    "tgn:name":"Neddy Fork",
    "tgn:placetype":[
        "aat:300008699"
    ]
},
  "bbox": [],
  "geometry": {"coordinates":[-82.5167,37.6833],"type":"Point"}
}