<<<<<<< HEAD
{
  "id": 2408948,
  "type": "Feature",
  "properties": {
    "tgn:hierarchy":[
        "tgn:2408948",
        "tgn:1000001",
        "tgn:7006451",
        "tgn:2000093",
        "tgn:7012149",
        "tgn:7029392"
    ],
    "tgn:id":2408948,
    "tgn:name":"I S Hole",
    "tgn:placetype":[
        "aat:300008761"
    ]
},
  "bbox": [],
  "geometry": {"coordinates":[-110.4833,33.7333],"type":"Point"}
}
=======
{"geometry":{"type":"Point","coordinates":[-110.483300,33.733300]},"type":"Feature","properties":{"hierarchy":["tgn:2408948","tgn:1000001","tgn:7006451","tgn:2000093","tgn:7012149","tgn:7029392"],"placetype":["aat:300008761"],"id":2408948,"name:xx":"I S Hole"}}
>>>>>>> 03f74aca74312dbeaf24d7e61306dd6a786dc3d0
