{
  "id": 2498759,
  "type": "Feature",
  "properties": {
    "tgn:hierarchy":[
        "tgn:2498759",
        "tgn:1000001",
        "tgn:2000862",
        "tgn:7012149",
        "tgn:7007256",
        "tgn:7029392"
    ],
    "tgn:id":2498759,
    "tgn:name":"McCain Creek",
    "tgn:placetype":[
        "aat:300008706"
    ]
},
  "bbox": [],
  "geometry": {"coordinates":[-93.8167,32.5833],"type":"Point"}
}