{
  "id": 2625052,
  "type": "Feature",
  "properties": {
    "tgn:hierarchy":[
        "tgn:2625052",
        "tgn:7006450",
        "tgn:1000001",
        "tgn:7012149",
        "tgn:2000085",
        "tgn:7029392"
    ],
    "tgn:id":2625052,
    "tgn:name":"Rock of Ages",
    "tgn:placetype":[
        "aat:300008791"
    ]
},
  "bbox": [],
  "geometry": {"coordinates":[-141.8833,65.2167],"type":"Point"}
}