{
  "id": 7521477,
  "type": "Feature",
  "properties": {
    "tgn:hierarchy":[
        "tgn:7521477",
        "tgn:7001242",
        "tgn:7016833",
        "tgn:1001418",
        "tgn:7029392"
    ],
    "tgn:id":7521477,
    "tgn:name:en":"Ab\u016b \u1e28ash\u0101yfah, Jaz\u012brat",
    "tgn:placetype":[
        "aat:300008791"
    ]
},
  "bbox": [],
  "geometry": {"coordinates":[27.640556,31.193056],"type":"Point"}
}