{
  "id": 7177470,
  "type": "Feature",
  "properties": {
    "tgn:hierarchy":[
        "tgn:7177470",
        "tgn:7003692",
        "tgn:1000003",
        "tgn:7000084",
        "tgn:7029392"
    ],
    "tgn:id":7177470,
    "tgn:name":"G\u00fcnzgen",
    "tgn:placetype":[
        "aat:300008347"
    ]
},
  "bbox": [],
  "geometry": {"coordinates":[8.466667,47.583333],"type":"Point"}
}