{
  "id": 7587609,
  "type": "Feature",
  "properties": {
    "tgn:hierarchy":[
        "tgn:7587609",
        "tgn:1000004",
        "tgn:7000198",
        "tgn:7016883",
        "tgn:7029392"
    ],
    "tgn:id":7587609,
    "tgn:name:en":"R\u0101m T\u012brth",
    "tgn:placetype":[
        "aat:300007558"
    ]
},
  "bbox": [],
  "geometry": {"coordinates":[74.75396,31.677147],"type":"Point"}
}