{
  "id": 2065868,
  "type": "Feature",
  "properties": {
    "tgn:hierarchy":[
        "tgn:2065868",
        "tgn:1000001",
        "tgn:1002985",
        "tgn:7012149",
        "tgn:7007565",
        "tgn:7029392"
    ],
    "tgn:id":2065868,
    "tgn:name":"Phillipsburg",
    "tgn:placetype":[
        "aat:300008347"
    ]
},
  "bbox": [],
  "geometry": {"coordinates":[-75.1833,40.6833],"type":"Point"}
}