<<<<<<< HEAD
{
  "id": 7177094,
  "type": "Feature",
  "properties": {
    "tgn:hierarchy":[
        "tgn:7177094",
        "tgn:7003692",
        "tgn:1000003",
        "tgn:7000084",
        "tgn:7029392"
    ],
    "tgn:id":7177094,
    "tgn:name":"Hard-Berg",
    "tgn:placetype":[
        "aat:300008777"
    ]
},
  "bbox": [],
  "geometry": {"coordinates":[8.883333,47.733333],"type":"Point"}
}
=======
{"geometry":{"type":"Point","coordinates":[8.883333,47.733333]},"type":"Feature","properties":{"hierarchy":["tgn:7177094","tgn:7003692","tgn:1000003","tgn:7000084","tgn:7029392"],"placetype":["aat:300008777"],"id":7177094,"name:xx":"Hard-Berg"}}
>>>>>>> 03f74aca74312dbeaf24d7e61306dd6a786dc3d0
