{
  "id": 7325273,
  "type": "Feature",
  "properties": {
    "tgn:hierarchy":[
        "tgn:7325273",
        "tgn:7008911",
        "tgn:1000003",
        "tgn:7002763",
        "tgn:1000095",
        "tgn:7029392"
    ],
    "tgn:id":7325273,
    "tgn:name":"San Mart\u00edn de Arango",
    "tgn:placetype":[
        "aat:300008347"
    ]
},
  "bbox": [],
  "geometry": {"coordinates":[-6.166667,43.466667],"type":"Point"}
}