{
  "id": 7562427,
  "type": "Feature",
  "properties": {
    "tgn:hierarchy":[
        "tgn:7562427",
        "tgn:1000004",
        "tgn:7000198",
        "tgn:7016722",
        "tgn:7029392"
    ],
    "tgn:id":7562427,
    "tgn:name:en":"Hindaura",
    "tgn:placetype":[
        "aat:300008347"
    ]
},
  "bbox": [],
  "geometry": {"coordinates":[79.329301,27.916346],"type":"Point"}
}