{
  "id": 7193852,
  "type": "Feature",
  "properties": {
    "tgn:hierarchy":[
        "tgn:7193852",
        "tgn:1000003",
        "tgn:7003685",
        "tgn:7000084",
        "tgn:7029392"
    ],
    "tgn:id":7193852,
    "tgn:name":"Feldgut Lindenhof",
    "tgn:placetype":[
        "aat:300000206"
    ]
},
  "bbox": [],
  "geometry": {"coordinates":[13.366667,50.866667],"type":"Point"}
}