{
  "id": 2771488,
  "type": "Feature",
  "properties": {
    "tgn:hierarchy":[
        "tgn:2771488",
        "tgn:1000001",
        "tgn:2000470",
        "tgn:7012149",
        "tgn:7007250",
        "tgn:7029392"
    ],
    "tgn:id":2771488,
    "tgn:name":"Wildhorse Lakes",
    "tgn:placetype":[
        "aat:300008680"
    ]
},
  "bbox": [],
  "geometry": {"coordinates":[-114.1167,43.75],"type":"Point"}
}