{
  "id": 7545288,
  "type": "Feature",
  "properties": {
    "tgn:hierarchy":[
        "tgn:7545288",
        "tgn:1000004",
        "tgn:1001832",
        "tgn:7000198",
        "tgn:7029392"
    ],
    "tgn:id":7545288,
    "tgn:name:en":"Bhauraguri",
    "tgn:placetype":[
        "aat:300008347"
    ]
},
  "bbox": [],
  "geometry": {"coordinates":[90.073491,26.42602],"type":"Point"}
}