{
  "id": 7269599,
  "type": "Feature",
  "properties": {
    "tgn:hierarchy":[
        "tgn:7269599",
        "tgn:7003619",
        "tgn:1000003",
        "tgn:7016845",
        "tgn:7029392"
    ],
    "tgn:id":7269599,
    "tgn:name:nl":"Memelinkhoeve",
    "tgn:placetype":[
        "aat:300000206"
    ]
},
  "bbox": [],
  "geometry": {"coordinates":[5.733333,52.133333],"type":"Point"}
}