{
  "id": 7506812,
  "type": "Feature",
  "properties": {
    "tgn:hierarchy":[
        "tgn:7506812",
        "tgn:1008380",
        "tgn:1000226",
        "tgn:7016827",
        "tgn:1000006",
        "tgn:7029392"
    ],
    "tgn:id":7506812,
    "tgn:name:en":"Rautini Stream",
    "tgn:placetype":[
        "aat:300008699"
    ]
},
  "bbox": [],
  "geometry": {"coordinates":[173.766667,-39.333333],"type":"Point"}
}