{
  "id": 2176873,
  "type": "Feature",
  "properties": {
    "tgn:hierarchy":[
        "tgn:2176873",
        "tgn:1000001",
        "tgn:7012149",
        "tgn:1002986",
        "tgn:7007568",
        "tgn:7029392"
    ],
    "tgn:id":2176873,
    "tgn:name":"Black Mountain",
    "tgn:placetype":[
        "aat:300008798"
    ]
},
  "bbox": [],
  "geometry": {"coordinates":[-74.1333,43.5667],"type":"Point"}
}