{
  "id": 7552087,
  "type": "Feature",
  "properties": {
    "tgn:hierarchy":[
        "tgn:7552087",
        "tgn:1000004",
        "tgn:1001842",
        "tgn:7000198",
        "tgn:7029392"
    ],
    "tgn:id":7552087,
    "tgn:name:en":"Deo",
    "tgn:placetype":[
        "aat:300008347"
    ]
},
  "bbox": [],
  "geometry": {"coordinates":[84.437119,24.658461],"type":"Point"}
}