{
  "id": 1128165,
  "type": "Feature",
  "properties": {
    "tgn:hierarchy":[
        "tgn:1128165",
        "tgn:1000722",
        "tgn:1000046",
        "tgn:1000002",
        "tgn:7029392"
    ],
    "tgn:id":1128165,
    "tgn:name":"Orth\u00f3n, R\u00edo",
    "tgn:placetype":[
        "aat:300008707"
    ]
},
  "bbox": [],
  "geometry": {"coordinates":[-66.029,-10.815],"type":"Point"}
}