{
  "id": 2517390,
  "type": "Feature",
  "properties": {
    "tgn:hierarchy":[
        "tgn:2517390",
        "tgn:1000001",
        "tgn:2000920",
        "tgn:7012149",
        "tgn:7007515",
        "tgn:7029392"
    ],
    "tgn:id":2517390,
    "tgn:name":"Minnow Brook",
    "tgn:placetype":[
        "aat:300008699"
    ]
},
  "bbox": [],
  "geometry": {"coordinates":[-70.3167,43.7333],"type":"Point"}
}