<<<<<<< HEAD
{
  "id": 2155606,
  "type": "Feature",
  "properties": {
    "tgn:hierarchy":[
        "tgn:2155606",
        "tgn:1000001",
        "tgn:7012149",
        "tgn:2001297",
        "tgn:7007524",
        "tgn:7029392"
    ],
    "tgn:id":2155606,
    "tgn:name":"Bear Skull Mountain",
    "tgn:placetype":[
        "aat:300008798"
    ]
},
  "bbox": [],
  "geometry": {"coordinates":[-105.4333,45.1333],"type":"Point"}
}
=======
{"geometry":{"type":"Point","coordinates":[-105.433300,45.133300]},"type":"Feature","properties":{"hierarchy":["tgn:2155606","tgn:1000001","tgn:7012149","tgn:2001297","tgn:7007524","tgn:7029392"],"placetype":["aat:300008798"],"id":2155606,"name:xx":"Bear Skull Mountain"}}
>>>>>>> 03f74aca74312dbeaf24d7e61306dd6a786dc3d0
