{
  "id": 2358026,
  "type": "Feature",
  "properties": {
    "tgn:hierarchy":[
        "tgn:2358026",
        "tgn:1000001",
        "tgn:2000459",
        "tgn:7012149",
        "tgn:7007250",
        "tgn:7029392"
    ],
    "tgn:id":2358026,
    "tgn:name":"Graham Peak",
    "tgn:placetype":[
        "aat:300008798"
    ]
},
  "bbox": [],
  "geometry": {"coordinates":[-115.2833,43.9667],"type":"Point"}
}