{
  "id": 2623048,
  "type": "Feature",
  "properties": {
    "tgn:hierarchy":[
        "tgn:2623048",
        "tgn:1000001",
        "tgn:7006451",
        "tgn:7012149",
        "tgn:2000101",
        "tgn:7029392"
    ],
    "tgn:id":2623048,
    "tgn:name":"Roblas Butte",
    "tgn:placetype":[
        "aat:300008798"
    ]
},
  "bbox": [],
  "geometry": {"coordinates":[-111.2167,33.3167],"type":"Point"}
}