{
  "id": 2338411,
  "type": "Feature",
  "properties": {
    "tgn:hierarchy":[
        "tgn:2338411",
        "tgn:1000001",
        "tgn:7012149",
        "tgn:1002682",
        "tgn:7007710",
        "tgn:7029392"
    ],
    "tgn:id":2338411,
    "tgn:name":"Foxtown Hill",
    "tgn:placetype":[
        "aat:300008798"
    ]
},
  "bbox": [],
  "geometry": {"coordinates":[-75.1667,40.9667],"type":"Point"}
}