<<<<<<< HEAD
{
  "id": 2338411,
  "type": "Feature",
  "properties": {
    "tgn:hierarchy":[
        "tgn:2338411",
        "tgn:1000001",
        "tgn:7012149",
        "tgn:1002682",
        "tgn:7007710",
        "tgn:7029392"
    ],
    "tgn:id":2338411,
    "tgn:name":"Foxtown Hill",
    "tgn:placetype":[
        "aat:300008798"
    ]
},
  "bbox": [],
  "geometry": {"coordinates":[-75.1667,40.9667],"type":"Point"}
}
=======
{"geometry":{"type":"Point","coordinates":[-75.166700,40.966700]},"type":"Feature","properties":{"hierarchy":["tgn:2338411","tgn:1000001","tgn:7012149","tgn:1002682","tgn:7007710","tgn:7029392"],"placetype":["aat:300008798"],"id":2338411,"name:xx":"Foxtown Hill"}}
>>>>>>> 03f74aca74312dbeaf24d7e61306dd6a786dc3d0
