{
  "id": 7332117,
  "type": "Feature",
  "properties": {
    "tgn:hierarchy":[
        "tgn:7332117",
        "tgn:7002849",
        "tgn:1000003",
        "tgn:7009604",
        "tgn:1000095",
        "tgn:7029392"
    ],
    "tgn:id":7332117,
    "tgn:name":"Izaro, Isla de",
    "tgn:placetype":[
        "aat:300008791"
    ]
},
  "bbox": [],
  "geometry": {"coordinates":[-2.683547,43.424983],"type":"Point"}
}