{
  "id": 1136043,
  "type": "Feature",
  "properties": {
    "tgn:hierarchy":[
        "tgn:1136043",
        "tgn:7003013",
        "tgn:7003005",
        "tgn:1000003",
        "tgn:1000080",
        "tgn:7029392"
    ],
    "tgn:id":1136043,
    "tgn:name":"Procida, Canale di",
    "tgn:placetype":[
        "aat:300006075"
    ]
},
  "bbox": [],
  "geometry": {"coordinates":[14.033333,40.783333],"type":"Point"}
}