{
  "id": 2777541,
  "type": "Feature",
  "properties": {
    "tgn:hierarchy":[
        "tgn:2777541",
        "tgn:1000001",
        "tgn:2001187",
        "tgn:7012149",
        "tgn:7007523",
        "tgn:7029392"
    ],
    "tgn:id":2777541,
    "tgn:name":"Winner",
    "tgn:placetype":[
        "aat:300008347"
    ]
},
  "bbox": [],
  "geometry": {"coordinates":[-94.4833,39.3167],"type":"Point"}
}