{
  "id": 1011451,
  "type": "Feature",
  "properties": {
    "tgn:hierarchy":[
        "tgn:1011451",
        "tgn:7002443",
        "tgn:7026970",
        "tgn:1000003",
        "tgn:7008591",
        "tgn:7029392"
    ],
    "tgn:id":1011451,
    "tgn:name:en":"Great Ormes Head",
    "tgn:placetype":[
        "aat:300008850",
        "aat:300387499"
    ]
},
  "bbox": [],
  "geometry": {"coordinates":[-3.916667,53.366667],"type":"Point"}
}