{
  "id": 2034223,
  "type": "Feature",
  "properties": {
    "tgn:hierarchy":[
        "tgn:2034223",
        "tgn:1000001",
        "tgn:7012149",
        "tgn:2000559",
        "tgn:7007252",
        "tgn:7029392"
    ],
    "tgn:id":2034223,
    "tgn:name":"Youngstown",
    "tgn:placetype":[
        "aat:300008347"
    ]
},
  "bbox": [],
  "geometry": {"coordinates":[-87.3667,39.35],"type":"Point"}
}