{
  "id": 7571731,
  "type": "Feature",
  "properties": {
    "tgn:hierarchy":[
        "tgn:7571731",
        "tgn:1000004",
        "tgn:7000198",
        "tgn:7000799",
        "tgn:7029392"
    ],
    "tgn:id":7571731,
    "tgn:name:en":"Haw\u0101l",
    "tgn:placetype":[
        "aat:300008347"
    ]
},
  "bbox": [],
  "geometry": {"coordinates":[75.960198,33.539777],"type":"Point"}
}