{
  "id": 7525084,
  "type": "Feature",
  "properties": {
    "tgn:hierarchy":[
        "tgn:7525084",
        "tgn:7001242",
        "tgn:7016833",
        "tgn:1001418",
        "tgn:7029392"
    ],
    "tgn:id":7525084,
    "tgn:name:en":"\u0100b\u0101r al Buwayb",
    "tgn:placetype":[
        "aat:300006207"
    ]
},
  "bbox": [],
  "geometry": {"coordinates":[25.984043,31.110316],"type":"Point"}
}