{
  "id": 1005691,
  "type": "Feature",
  "properties": {
    "tgn:hierarchy":[
        "tgn:1005691",
        "tgn:1000003",
        "tgn:7003677",
        "tgn:7000084",
        "tgn:7004982",
        "tgn:7029392"
    ],
    "tgn:id":1005691,
    "tgn:name":"Syburg",
    "tgn:placetype":[
        "aat:300000745",
        "aat:300387332"
    ]
},
  "bbox": [],
  "geometry": {"coordinates":[7.4833,51.4167],"type":"Point"}
}