{
  "id": 2045139,
  "type": "Feature",
  "properties": {
    "tgn:hierarchy":[
        "tgn:2045139",
        "tgn:1000001",
        "tgn:2000924",
        "tgn:7012149",
        "tgn:7007515",
        "tgn:7029392"
    ],
    "tgn:id":2045139,
    "tgn:name":"Martinsville",
    "tgn:placetype":[
        "aat:300008347"
    ]
},
  "bbox": [],
  "geometry": {"coordinates":[-69.2167,43.9333],"type":"Point"}
}