{
  "id": 7233640,
  "type": "Feature",
  "properties": {
    "tgn:hierarchy":[
        "tgn:7233640",
        "tgn:7011369",
        "tgn:7017076",
        "tgn:1000003",
        "tgn:1000074",
        "tgn:7029392"
    ],
    "tgn:id":7233640,
    "tgn:name":"Dhim\u00e1ndra",
    "tgn:placetype":[
        "aat:300008347"
    ]
},
  "bbox": [],
  "geometry": {"coordinates":[21.916667,37.35],"type":"Point"}
}