{
  "id": 7142148,
  "type": "Feature",
  "properties": {
    "tgn:hierarchy":[
        "tgn:7142148",
        "tgn:7003669",
        "tgn:1000003",
        "tgn:7000084",
        "tgn:7029392"
    ],
    "tgn:id":7142148,
    "tgn:name":"Lindig",
    "tgn:placetype":[
        "aat:300008863"
    ]
},
  "bbox": [],
  "geometry": {"coordinates":[9.05,50.033333],"type":"Point"}
}