{
  "id": 7336665,
  "type": "Feature",
  "properties": {
    "tgn:hierarchy":[
        "tgn:7336665",
        "tgn:7002835",
        "tgn:7001158",
        "tgn:1000003",
        "tgn:1000095",
        "tgn:7029392"
    ],
    "tgn:id":7336665,
    "tgn:name":"Gavil\u00e1n",
    "tgn:placetype":[
        "aat:300008347"
    ]
},
  "bbox": [],
  "geometry": {"coordinates":[-6.383333,40.65],"type":"Point"}
}