{
  "id": 2653372,
  "type": "Feature",
  "properties": {
    "tgn:hierarchy":[
        "tgn:2653372",
        "tgn:1000001",
        "tgn:7020939",
        "tgn:7012149",
        "tgn:7007922",
        "tgn:7029392"
    ],
    "tgn:id":2653372,
    "tgn:name":"Sevenmile Creek",
    "tgn:placetype":[
        "aat:300008706"
    ]
},
  "bbox": [],
  "geometry": {"coordinates":[-88.5833,43.7667],"type":"Point"}
}