{
  "id": 2075779,
  "type": "Feature",
  "properties": {
    "tgn:hierarchy":[
        "tgn:2075779",
        "tgn:1000001",
        "tgn:7012149",
        "tgn:2001542",
        "tgn:7007709",
        "tgn:7029392"
    ],
    "tgn:id":2075779,
    "tgn:name":"Mountain Park",
    "tgn:placetype":[
        "aat:300008347",
        "aat:300387210"
    ]
},
  "bbox": [],
  "geometry": {"coordinates":[-80.85,36.3667],"type":"Point"}
}