{
  "id": 7217875,
  "type": "Feature",
  "properties": {
    "tgn:hierarchy":[
        "tgn:7217875",
        "tgn:7011161",
        "tgn:7002674",
        "tgn:1000003",
        "tgn:1000074",
        "tgn:7029392"
    ],
    "tgn:id":7217875,
    "tgn:name":"Chor\u00ed",
    "tgn:placetype":[
        "aat:300008347"
    ]
},
  "bbox": [],
  "geometry": {"coordinates":[25.934444,38.470833],"type":"Point"}
}