{
  "id": 2161550,
  "type": "Feature",
  "properties": {
    "tgn:hierarchy":[
        "tgn:2161550",
        "tgn:1000001",
        "tgn:7012149",
        "tgn:7013867",
        "tgn:7007710",
        "tgn:7029392"
    ],
    "tgn:id":2161550,
    "tgn:name":"Bellaire",
    "tgn:placetype":[
        "aat:300008347"
    ]
},
  "bbox": [],
  "geometry": {"coordinates":[-76.5667,40.1833],"type":"Point"}
}