{
  "id": 2266856,
  "type": "Feature",
  "properties": {
    "tgn:hierarchy":[
        "tgn:2266856",
        "tgn:1000001",
        "tgn:7012149",
        "tgn:7007520",
        "tgn:7029392"
    ],
    "tgn:id":2266856,
    "tgn:name":"Crescent Pond",
    "tgn:placetype":[
        "aat:300008680"
    ]
},
  "bbox": [],
  "geometry": {"coordinates":[-88.1167,46.2167],"type":"Point"}
}