{
  "id": 2074150,
  "type": "Feature",
  "properties": {
    "tgn:hierarchy":[
        "tgn:2074150",
        "tgn:2001463",
        "tgn:1000001",
        "tgn:7012149",
        "tgn:7007709",
        "tgn:7029392"
    ],
    "tgn:id":2074150,
    "tgn:name":"Clover Garden",
    "tgn:placetype":[
        "aat:300008347"
    ]
},
  "bbox": [],
  "geometry": {"coordinates":[-79.45,36.1833],"type":"Point"}
}