{
  "id": 2522770,
  "type": "Feature",
  "properties": {
    "tgn:hierarchy":[
        "tgn:2522770",
        "tgn:1000001",
        "tgn:7012149",
        "tgn:2000230",
        "tgn:7007158",
        "tgn:7029392"
    ],
    "tgn:id":2522770,
    "tgn:name":"Moore Creek",
    "tgn:placetype":[
        "aat:300008706"
    ]
},
  "bbox": [],
  "geometry": {"coordinates":[-108.7333,38.85],"type":"Point"}
}