{
  "id": 1097834,
  "type": "Feature",
  "properties": {
    "tgn:hierarchy":[
        "tgn:1097834",
        "tgn:7000490",
        "tgn:1000006",
        "tgn:7006238",
        "tgn:7029392"
    ],
    "tgn:id":1097834,
    "tgn:name":"Numurkah",
    "tgn:placetype":[
        "aat:300008347"
    ]
},
  "bbox": [],
  "geometry": {"coordinates":[145.4333,-36.0833],"type":"Point"}
}