{
  "id": 7247470,
  "type": "Feature",
  "properties": {
    "tgn:hierarchy":[
        "tgn:7247470",
        "tgn:7003457",
        "tgn:1000003",
        "tgn:1000063",
        "tgn:7018236",
        "tgn:7029392"
    ],
    "tgn:id":7247470,
    "tgn:name":"De Akker",
    "tgn:placetype":[
        "aat:300008347"
    ]
},
  "bbox": [],
  "geometry": {"coordinates":[3.834184,51.198917],"type":"Point"}
}