{
  "id": 2735244,
  "type": "Feature",
  "properties": {
    "tgn:hierarchy":[
        "tgn:2735244",
        "tgn:1000001",
        "tgn:7012149",
        "tgn:1002553",
        "tgn:7007920",
        "tgn:7029392"
    ],
    "tgn:id":2735244,
    "tgn:name":"Twilight Lake",
    "tgn:placetype":[
        "aat:300008680"
    ]
},
  "bbox": [],
  "geometry": {"coordinates":[-121.4167,47.3333],"type":"Point"}
}