{
  "id": 7464059,
  "type": "Feature",
  "properties": {
    "tgn:hierarchy":[
        "tgn:7464059",
        "tgn:7002445",
        "tgn:1000003",
        "tgn:7008127",
        "tgn:7008591",
        "tgn:7029392"
    ],
    "tgn:id":7464059,
    "tgn:name:en":"Balder, River",
    "tgn:placetype":[
        "aat:300008699"
    ]
},
  "bbox": [],
  "geometry": {"coordinates":[-1.983333,54.583333],"type":"Point"}
}