<<<<<<< HEAD
{
  "id": 7176796,
  "type": "Feature",
  "properties": {
    "tgn:hierarchy":[
        "tgn:7176796",
        "tgn:7003669",
        "tgn:1000003",
        "tgn:7000084",
        "tgn:7029392"
    ],
    "tgn:id":7176796,
    "tgn:name":"G\u00fcterwald",
    "tgn:placetype":[
        "aat:300008863"
    ]
},
  "bbox": [],
  "geometry": {"coordinates":[10.066667,49.733333],"type":"Point"}
}
=======
{"geometry":{"type":"Point","coordinates":[10.066667,49.733333]},"type":"Feature","properties":{"hierarchy":["tgn:7176796","tgn:7003669","tgn:1000003","tgn:7000084","tgn:7029392"],"placetype":["aat:300008863"],"id":7176796,"name:xx":"G\u00fcterwald"}}
>>>>>>> 03f74aca74312dbeaf24d7e61306dd6a786dc3d0
