{
  "id": 2734845,
  "type": "Feature",
  "properties": {
    "tgn:hierarchy":[
        "tgn:2734845",
        "tgn:1000001",
        "tgn:7006451",
        "tgn:7012149",
        "tgn:2000097",
        "tgn:7029392"
    ],
    "tgn:id":2734845,
    "tgn:name":"Twelve, Canal",
    "tgn:placetype":[
        "aat:300006075",
        "aat:300000833"
    ]
},
  "bbox": [],
  "geometry": {"coordinates":[-112.2667,33.3833],"type":"Point"}
}