{
  "id": 7424294,
  "type": "Feature",
  "properties": {
    "tgn:hierarchy":[
        "tgn:7424294",
        "tgn:1000001",
        "tgn:1001960",
        "tgn:7005560",
        "tgn:7029392"
    ],
    "tgn:id":7424294,
    "tgn:name":"El Carmen",
    "tgn:placetype":[
        "aat:300008347"
    ]
},
  "bbox": [],
  "geometry": {"coordinates":[-111.35,29.45],"type":"Point"}
}