{
  "id": 7211064,
  "type": "Feature",
  "properties": {
    "tgn:hierarchy":[
        "tgn:7211064",
        "tgn:7003692",
        "tgn:1000003",
        "tgn:7000084",
        "tgn:7029392"
    ],
    "tgn:id":7211064,
    "tgn:name":"Berghausen",
    "tgn:placetype":[
        "aat:300008347"
    ]
},
  "bbox": [],
  "geometry": {"coordinates":[8.529444,49.006389],"type":"Point"}
}