{
  "id": 1048667,
  "type": "Feature",
  "properties": {
    "tgn:hierarchy":[
        "tgn:1048667",
        "tgn:7003651",
        "tgn:1000003",
        "tgn:1000088",
        "tgn:7029392"
    ],
    "tgn:id":1048667,
    "tgn:name":"Mysen",
    "tgn:placetype":[
        "aat:300008347"
    ]
},
  "bbox": [],
  "geometry": {"coordinates":[11.3333,59.55],"type":"Point"}
}