{
  "id": 7276991,
  "type": "Feature",
  "properties": {
    "tgn:hierarchy":[
        "tgn:7276991",
        "tgn:1001702",
        "tgn:1000049",
        "tgn:1000002",
        "tgn:7029392"
    ],
    "tgn:id":7276991,
    "tgn:name":"Vidal Gormaz, Canal",
    "tgn:placetype":[
        "aat:300387026"
    ]
},
  "bbox": [],
  "geometry": {"coordinates":[-74.966667,-51.866667],"type":"Point"}
}