<<<<<<< HEAD
{
  "id": 2155784,
  "type": "Feature",
  "properties": {
    "tgn:hierarchy":[
        "tgn:2155784",
        "tgn:1000001",
        "tgn:7012149",
        "tgn:1002932",
        "tgn:7007710",
        "tgn:7029392"
    ],
    "tgn:id":2155784,
    "tgn:name":"Bear Swamp Creek",
    "tgn:placetype":[
        "aat:300008706"
    ]
},
  "bbox": [],
  "geometry": {"coordinates":[-75.5833,41.7333],"type":"Point"}
}
=======
{"geometry":{"type":"Point","coordinates":[-75.583300,41.733300]},"type":"Feature","properties":{"hierarchy":["tgn:2155784","tgn:1000001","tgn:7012149","tgn:1002932","tgn:7007710","tgn:7029392"],"placetype":["aat:300008706"],"id":2155784,"name:xx":"Bear Swamp Creek"}}
>>>>>>> 03f74aca74312dbeaf24d7e61306dd6a786dc3d0
