{
  "id": 7483477,
  "type": "Feature",
  "properties": {
    "tgn:hierarchy":[
        "tgn:7483477",
        "tgn:1000004",
        "tgn:7491221",
        "tgn:1000141",
        "tgn:7029392"
    ],
    "tgn:id":7483477,
    "tgn:name":"Malala'ou Xi",
    "tgn:placetype":[
        "aat:300008699"
    ]
},
  "bbox": [],
  "geometry": {"coordinates":[120.960556,22.868889],"type":"Point"}
}