{
  "id": 7240444,
  "type": "Feature",
  "properties": {
    "tgn:hierarchy":[
        "tgn:7240444",
        "tgn:7007877",
        "tgn:1000003",
        "tgn:1000063",
        "tgn:4012014",
        "tgn:7029392"
    ],
    "tgn:id":7240444,
    "tgn:name":"Ere",
    "tgn:placetype":[
        "aat:300008347"
    ]
},
  "bbox": [],
  "geometry": {"coordinates":[3.36765,50.58226],"type":"Point"}
}