<<<<<<< HEAD
{
  "id": 7020852,
  "type": "Feature",
  "properties": {
    "tgn:hierarchy":[
        "tgn:7020852",
        "tgn:1000001",
        "tgn:7012149",
        "tgn:7029392"
    ],
    "tgn:id":7020852,
    "tgn:name":"Joseph Creek",
    "tgn:placetype":[
        "aat:300008706"
    ]
},
  "bbox": [],
  "geometry": {"coordinates":[-117.15,45.7],"type":"Point"}
}
=======
{"geometry":{"type":"Point","coordinates":[-117.150000,45.700000]},"type":"Feature","properties":{"hierarchy":["tgn:7020852","tgn:1000001","tgn:7012149","tgn:7029392"],"placetype":["aat:300008706"],"id":7020852,"name:xx":"Joseph Creek"}}
>>>>>>> 03f74aca74312dbeaf24d7e61306dd6a786dc3d0
