{
  "id": 7213992,
  "type": "Feature",
  "properties": {
    "tgn:hierarchy":[
        "tgn:7213992",
        "tgn:7003669",
        "tgn:1000003",
        "tgn:7000084",
        "tgn:7029392"
    ],
    "tgn:id":7213992,
    "tgn:name":"Birkenzant",
    "tgn:placetype":[
        "aat:300008347"
    ]
},
  "bbox": [],
  "geometry": {"coordinates":[12.183333,49.15],"type":"Point"}
}