{
  "id": 7347493,
  "type": "Feature",
  "properties": {
    "tgn:hierarchy":[
        "tgn:7347493",
        "tgn:7002759",
        "tgn:7008909",
        "tgn:1000003",
        "tgn:1000095",
        "tgn:7029392"
    ],
    "tgn:id":7347493,
    "tgn:name":"Artasona",
    "tgn:placetype":[
        "aat:300008347"
    ]
},
  "bbox": [],
  "geometry": {"coordinates":[0.240681,42.13509],"type":"Point"}
}