{
  "id": 2509265,
  "type": "Feature",
  "properties": {
    "tgn:hierarchy":[
        "tgn:2509265",
        "tgn:1000001",
        "tgn:7012149",
        "tgn:2000481",
        "tgn:7007250",
        "tgn:7029392"
    ],
    "tgn:id":2509265,
    "tgn:name":"Middle Fork Peak",
    "tgn:placetype":[
        "aat:300008798"
    ]
},
  "bbox": [],
  "geometry": {"coordinates":[-114.65,44.95],"type":"Point"}
}