{
  "id": 1079364,
  "type": "Feature",
  "properties": {
    "tgn:hierarchy":[
        "tgn:1079364",
        "tgn:1000004",
        "tgn:7002004",
        "tgn:7000231",
        "tgn:7029392"
    ],
    "tgn:id":1079364,
    "tgn:name":"Zarn\u0101n",
    "tgn:placetype":[
        "aat:300008347"
    ]
},
  "bbox": [],
  "geometry": {"coordinates":[51.15,35.6833],"type":"Point"}
}