{
  "id": 2272070,
  "type": "Feature",
  "properties": {
    "tgn:hierarchy":[
        "tgn:2272070",
        "tgn:1000001",
        "tgn:7012149",
        "tgn:2000878",
        "tgn:7007256",
        "tgn:7029392"
    ],
    "tgn:id":2272070,
    "tgn:name":"Curr Creek",
    "tgn:placetype":[
        "aat:300008706"
    ]
},
  "bbox": [],
  "geometry": {"coordinates":[-92.5833,32.35],"type":"Point"}
}