{
  "id": 1035400,
  "type": "Feature",
  "properties": {
    "tgn:hierarchy":[
        "tgn:1035400",
        "tgn:1000003",
        "tgn:1000070",
        "tgn:7002897",
        "tgn:7029392"
    ],
    "tgn:id":1035400,
    "tgn:name":"Saint-Just-en-Chevalet",
    "tgn:placetype":[
        "aat:300008347"
    ]
},
  "bbox": [],
  "geometry": {"coordinates":[3.8333,45.9167],"type":"Point"}
}