{
  "id": 7155236,
  "type": "Feature",
  "properties": {
    "tgn:hierarchy":[
        "tgn:7155236",
        "tgn:7003692",
        "tgn:1000003",
        "tgn:7000084",
        "tgn:7029392"
    ],
    "tgn:id":7155236,
    "tgn:name":"Kirchheim",
    "tgn:placetype":[
        "aat:300000745"
    ]
},
  "bbox": [],
  "geometry": {"coordinates":[8.673889,49.381111],"type":"Point"}
}