{
  "id": 7280665,
  "type": "Feature",
  "properties": {
    "tgn:hierarchy":[
        "tgn:7280665",
        "tgn:1001708",
        "tgn:1000049",
        "tgn:1000002",
        "tgn:7029392"
    ],
    "tgn:id":7280665,
    "tgn:name":"San Jos\u00e9 de Nos",
    "tgn:placetype":[
        "aat:300008347"
    ]
},
  "bbox": [],
  "geometry": {"coordinates":[-70.733333,-33.633333],"type":"Point"}
}