<<<<<<< HEAD
{
  "id": 7356481,
  "type": "Feature",
  "properties": {
    "tgn:hierarchy":[
        "tgn:7356481",
        "tgn:1000001",
        "tgn:7005600",
        "tgn:7005560",
        "tgn:7029392"
    ],
    "tgn:id":7356481,
    "tgn:name":"Chimay",
    "tgn:placetype":[
        "aat:300008347"
    ]
},
  "bbox": [],
  "geometry": {"coordinates":[-89.583333,20.85],"type":"Point"}
}
=======
{"geometry":{"type":"Point","coordinates":[-89.583333,20.850000]},"type":"Feature","properties":{"hierarchy":["tgn:7356481","tgn:1000001","tgn:7005600","tgn:7005560","tgn:7029392"],"placetype":["aat:300008347"],"id":7356481,"name:xx":"Chimay"}}
>>>>>>> 03f74aca74312dbeaf24d7e61306dd6a786dc3d0
