{
  "id": 7397355,
  "type": "Feature",
  "properties": {
    "tgn:hierarchy":[
        "tgn:7397355",
        "tgn:7005583",
        "tgn:1000001",
        "tgn:7005560",
        "tgn:7029392"
    ],
    "tgn:id":7397355,
    "tgn:name":"San Salvador",
    "tgn:placetype":[
        "aat:300008347"
    ]
},
  "bbox": [],
  "geometry": {"coordinates":[-104.085278,24.625833],"type":"Point"}
}