{
  "id": 2351470,
  "type": "Feature",
  "properties": {
    "tgn:hierarchy":[
        "tgn:2351470",
        "tgn:1000001",
        "tgn:7012149",
        "tgn:1002392",
        "tgn:7007157",
        "tgn:7029392"
    ],
    "tgn:id":2351470,
    "tgn:name":"Glen Meadow Creek",
    "tgn:placetype":[
        "aat:300008706"
    ]
},
  "bbox": [],
  "geometry": {"coordinates":[-119.1667,37.0833],"type":"Point"}
}