<<<<<<< HEAD
{
  "id": 2258201,
  "type": "Feature",
  "properties": {
    "tgn:hierarchy":[
        "tgn:2258201",
        "tgn:1000001",
        "tgn:7012149",
        "tgn:2001709",
        "tgn:7007708",
        "tgn:7029392"
    ],
    "tgn:id":2258201,
    "tgn:name":"Cote Lake",
    "tgn:placetype":[
        "aat:300008680"
    ]
},
  "bbox": [],
  "geometry": {"coordinates":[-119.3167,43.3667],"type":"Point"}
}
=======
{"geometry":{"type":"Point","coordinates":[-119.316700,43.366700]},"type":"Feature","properties":{"hierarchy":["tgn:2258201","tgn:1000001","tgn:7012149","tgn:2001709","tgn:7007708","tgn:7029392"],"placetype":["aat:300008680"],"id":2258201,"name:xx":"Cote Lake"}}
>>>>>>> 03f74aca74312dbeaf24d7e61306dd6a786dc3d0
