{
  "id": 2655304,
  "type": "Feature",
  "properties": {
    "tgn:hierarchy":[
        "tgn:2655304",
        "tgn:1000001",
        "tgn:7012149",
        "tgn:7016021",
        "tgn:7007568",
        "tgn:7029392"
    ],
    "tgn:id":2655304,
    "tgn:name":"Shanty Rock Flow",
    "tgn:placetype":[
        "aat:300132316"
    ]
},
  "bbox": [],
  "geometry": {"coordinates":[-74.8333,44.15],"type":"Point"}
}