{
  "id": 2405421,
  "type": "Feature",
  "properties": {
    "tgn:hierarchy":[
        "tgn:2405421",
        "tgn:1000001",
        "tgn:7012149",
        "tgn:2001452",
        "tgn:7007566",
        "tgn:7029392"
    ],
    "tgn:id":2405421,
    "tgn:name":"Hugh Lake",
    "tgn:placetype":[
        "aat:300008680"
    ]
},
  "bbox": [],
  "geometry": {"coordinates":[-108.1667,36.55],"type":"Point"}
}