{
  "id": 7405593,
  "type": "Feature",
  "properties": {
    "tgn:hierarchy":[
        "tgn:7405593",
        "tgn:1000001",
        "tgn:1001906",
        "tgn:7005560",
        "tgn:7029392"
    ],
    "tgn:id":7405593,
    "tgn:name":"Agualamito",
    "tgn:placetype":[
        "aat:300008347"
    ]
},
  "bbox": [],
  "geometry": {"coordinates":[-104.816667,21.966667],"type":"Point"}
}