{
  "id": 2375825,
  "type": "Feature",
  "properties": {
    "tgn:hierarchy":[
        "tgn:2375825",
        "tgn:1000001",
        "tgn:7012149",
        "tgn:2002268",
        "tgn:7013961",
        "tgn:7029392"
    ],
    "tgn:id":2375825,
    "tgn:name":"Happy Hollow",
    "tgn:placetype":[
        "aat:300008761"
    ]
},
  "bbox": [],
  "geometry": {"coordinates":[-81.6667,38.6333],"type":"Point"}
}