<<<<<<< HEAD
{
  "id": 7369419,
  "type": "Feature",
  "properties": {
    "tgn:hierarchy":[
        "tgn:7369419",
        "tgn:7005581",
        "tgn:1000001",
        "tgn:7005560",
        "tgn:7029392"
    ],
    "tgn:id":7369419,
    "tgn:name":"Rancho Huacopa",
    "tgn:placetype":[
        "aat:300000241"
    ]
},
  "bbox": [],
  "geometry": {"coordinates":[-108.3,29.133333],"type":"Point"}
}
=======
{"geometry":{"type":"Point","coordinates":[-108.300000,29.133333]},"type":"Feature","properties":{"hierarchy":["tgn:7369419","tgn:7005581","tgn:1000001","tgn:7005560","tgn:7029392"],"placetype":["aat:300000241"],"id":7369419,"name:xx":"Rancho Huacopa"}}
>>>>>>> 03f74aca74312dbeaf24d7e61306dd6a786dc3d0
