{
  "id": 7350863,
  "type": "Feature",
  "properties": {
    "tgn:hierarchy":[
        "tgn:7350863",
        "tgn:7005581",
        "tgn:1000001",
        "tgn:7005560",
        "tgn:7029392"
    ],
    "tgn:id":7350863,
    "tgn:name":"Arcabuces, Cerro",
    "tgn:placetype":[
        "aat:300008795"
    ]
},
  "bbox": [],
  "geometry": {"coordinates":[-107.283333,30.35],"type":"Point"}
}