{
  "id": 1087393,
  "type": "Feature",
  "properties": {
    "tgn:hierarchy":[
        "tgn:1087393",
        "tgn:7001242",
        "tgn:7016752",
        "tgn:1000799",
        "tgn:7029392"
    ],
    "tgn:id":1087393,
    "tgn:name":"Bordj Omar Driss",
    "tgn:placetype":[
        "aat:300008347"
    ]
},
  "bbox": [],
  "geometry": {"coordinates":[6.65,28.0667],"type":"Point"}
}