{
  "id": 2468405,
  "type": "Feature",
  "properties": {
    "tgn:hierarchy":[
        "tgn:2468405",
        "tgn:1000001",
        "tgn:7012149",
        "tgn:2000839",
        "tgn:7007255",
        "tgn:7029392"
    ],
    "tgn:id":2468405,
    "tgn:name":"Long Point",
    "tgn:placetype":[
        "aat:300008798"
    ]
},
  "bbox": [],
  "geometry": {"coordinates":[-84.2833,37.1167],"type":"Point"}
}