{
  "id": 7162023,
  "type": "Feature",
  "properties": {
    "tgn:hierarchy":[
        "tgn:7162023",
        "tgn:7003692",
        "tgn:1000003",
        "tgn:7000084",
        "tgn:7029392"
    ],
    "tgn:id":7162023,
    "tgn:name":"Iberst",
    "tgn:placetype":[
        "aat:300008795"
    ]
},
  "bbox": [],
  "geometry": {"coordinates":[8.216667,48.733333],"type":"Point"}
}