{
  "id": 2051148,
  "type": "Feature",
  "properties": {
    "tgn:hierarchy":[
        "tgn:2051148",
        "tgn:1000001",
        "tgn:7012149",
        "tgn:2000975",
        "tgn:7007520",
        "tgn:7029392"
    ],
    "tgn:id":2051148,
    "tgn:name":"Arnold",
    "tgn:placetype":[
        "aat:300008347"
    ]
},
  "bbox": [],
  "geometry": {"coordinates":[-87.4833,46.05],"type":"Point"}
}