{
  "id": 7131302,
  "type": "Feature",
  "properties": {
    "tgn:hierarchy":[
        "tgn:7131302",
        "tgn:7003669",
        "tgn:1000003",
        "tgn:7000084",
        "tgn:7029392"
    ],
    "tgn:id":7131302,
    "tgn:name":"Mark",
    "tgn:placetype":[
        "aat:300000206"
    ]
},
  "bbox": [],
  "geometry": {"coordinates":[10.733333,47.716667],"type":"Point"}
}