{
  "id": 1017395,
  "type": "Feature",
  "properties": {
    "tgn:hierarchy":[
        "tgn:1017395",
        "tgn:1000001",
        "tgn:1001960",
        "tgn:7005560",
        "tgn:7029392"
    ],
    "tgn:id":1017395,
    "tgn:name":"El Coz\u00f3n",
    "tgn:placetype":[
        "aat:300008347"
    ]
},
  "bbox": [],
  "geometry": {"coordinates":[-112.561111,31.299722],"type":"Point"}
}