{
  "id": 2760455,
  "type": "Feature",
  "properties": {
    "tgn:hierarchy":[
        "tgn:2760455",
        "tgn:1000001",
        "tgn:7012149",
        "tgn:7007158",
        "tgn:7029392"
    ],
    "tgn:id":2760455,
    "tgn:name":"West Fork Story Gulch",
    "tgn:placetype":[
        "aat:300008761"
    ]
},
  "bbox": [],
  "geometry": {"coordinates":[-108.1167,39.6667],"type":"Point"}
}