<<<<<<< HEAD
{
  "id": 2760455,
  "type": "Feature",
  "properties": {
    "tgn:hierarchy":[
        "tgn:2760455",
        "tgn:1000001",
        "tgn:7012149",
        "tgn:7007158",
        "tgn:7029392"
    ],
    "tgn:id":2760455,
    "tgn:name":"West Fork Story Gulch",
    "tgn:placetype":[
        "aat:300008761"
    ]
},
  "bbox": [],
  "geometry": {"coordinates":[-108.1167,39.6667],"type":"Point"}
}
=======
{"geometry":{"type":"Point","coordinates":[-108.116700,39.666700]},"type":"Feature","properties":{"hierarchy":["tgn:2760455","tgn:1000001","tgn:7012149","tgn:7007158","tgn:7029392"],"placetype":["aat:300008761"],"id":2760455,"name:xx":"West Fork Story Gulch"}}
>>>>>>> 03f74aca74312dbeaf24d7e61306dd6a786dc3d0
