{
  "id": 1055537,
  "type": "Feature",
  "properties": {
    "tgn:hierarchy":[
        "tgn:1055537",
        "tgn:1000004",
        "tgn:7011528",
        "tgn:7002435",
        "tgn:7029392"
    ],
    "tgn:id":1055537,
    "tgn:name":"Kolymskaya",
    "tgn:placetype":[
        "aat:300008347"
    ]
},
  "bbox": [],
  "geometry": {"coordinates":[158.5833,68.8333],"type":"Point"}
}