{
  "id": 7151192,
  "type": "Feature",
  "properties": {
    "tgn:hierarchy":[
        "tgn:7151192",
        "tgn:1000003",
        "tgn:7003676",
        "tgn:7000084",
        "tgn:7029392"
    ],
    "tgn:id":7151192,
    "tgn:name":"Kaiserhof",
    "tgn:placetype":[
        "aat:300000206"
    ]
},
  "bbox": [],
  "geometry": {"coordinates":[7.983333,53.683333],"type":"Point"}
}