<<<<<<< HEAD
{
  "id": 7478873,
  "type": "Feature",
  "properties": {
    "tgn:hierarchy":[
        "tgn:7478873",
        "tgn:7487020",
        "tgn:1000004",
        "tgn:1000141",
        "tgn:7029392"
    ],
    "tgn:id":7478873,
    "tgn:name":"Xian Shan",
    "tgn:placetype":[
        "aat:300008798"
    ]
},
  "bbox": [],
  "geometry": {"coordinates":[120.953024,24.54237],"type":"Point"}
}
=======
{"geometry":{"type":"Point","coordinates":[120.953024,24.542370]},"type":"Feature","properties":{"hierarchy":["tgn:7478873","tgn:7487020","tgn:1000004","tgn:1000141","tgn:7029392"],"placetype":["aat:300008798"],"id":7478873,"name:xx":"Xian Shan"}}
>>>>>>> 03f74aca74312dbeaf24d7e61306dd6a786dc3d0
