{
  "id": 7376532,
  "type": "Feature",
  "properties": {
    "tgn:hierarchy":[
        "tgn:7376532",
        "tgn:7005583",
        "tgn:1000001",
        "tgn:7005560",
        "tgn:7029392"
    ],
    "tgn:id":7376532,
    "tgn:name":"Las Lajas",
    "tgn:placetype":[
        "aat:300008347"
    ]
},
  "bbox": [],
  "geometry": {"coordinates":[-105.533333,24.383333],"type":"Point"}
}