{
  "id": 2364020,
  "type": "Feature",
  "properties": {
    "tgn:hierarchy":[
        "tgn:2364020",
        "tgn:1000001",
        "tgn:7012149",
        "tgn:1002994",
        "tgn:7007708",
        "tgn:7029392"
    ],
    "tgn:id":2364020,
    "tgn:name":"Green Mountain",
    "tgn:placetype":[
        "aat:300008798"
    ]
},
  "bbox": [],
  "geometry": {"coordinates":[-123.1333,45.7333],"type":"Point"}
}