{
  "id": 2150800,
  "type": "Feature",
  "properties": {
    "tgn:hierarchy":[
        "tgn:2150800",
        "tgn:1000001",
        "tgn:2000953",
        "tgn:7012149",
        "tgn:7007520",
        "tgn:7029392"
    ],
    "tgn:id":2150800,
    "tgn:name":"Bass Lake",
    "tgn:placetype":[
        "aat:300008680"
    ]
},
  "bbox": [],
  "geometry": {"coordinates":[-85.0667,43.8667],"type":"Point"}
}