{
  "id": 7068726,
  "type": "Feature",
  "properties": {
    "tgn:hierarchy":[
        "tgn:7068726",
        "tgn:7003669",
        "tgn:1000003",
        "tgn:7000084",
        "tgn:7029392"
    ],
    "tgn:id":7068726,
    "tgn:name":"Stadlhof",
    "tgn:placetype":[
        "aat:300000206"
    ]
},
  "bbox": [],
  "geometry": {"coordinates":[12.266667,49.116667],"type":"Point"}
}