{
  "id": 2182122,
  "type": "Feature",
  "properties": {
    "tgn:hierarchy":[
        "tgn:2182122",
        "tgn:1000001",
        "tgn:7012149",
        "tgn:2002326",
        "tgn:7007922",
        "tgn:7029392"
    ],
    "tgn:id":2182122,
    "tgn:name":"Blue Mounds Creek",
    "tgn:placetype":[
        "aat:300008706"
    ]
},
  "bbox": [],
  "geometry": {"coordinates":[-89.8333,43.1333],"type":"Point"}
}