{
  "id": 7009862,
  "type": "Feature",
  "properties": {
    "tgn:hierarchy":[
        "tgn:7009862",
        "tgn:1000003",
        "tgn:7003781",
        "tgn:1000097",
        "tgn:7029392"
    ],
    "tgn:id":7009862,
    "tgn:name":"Str\u00e4ngn\u00e4s",
    "tgn:placetype":[
        "aat:300008347"
    ]
},
  "bbox": [],
  "geometry": {"coordinates":[17.0333,59.3833],"type":"Point"}
}