{
  "id": 7271446,
  "type": "Feature",
  "properties": {
    "tgn:hierarchy":[
        "tgn:7271446",
        "tgn:7003616",
        "tgn:1000003",
        "tgn:7016845",
        "tgn:7029392"
    ],
    "tgn:id":7271446,
    "tgn:name:nl":"Talstrazathe",
    "tgn:placetype":[
        "aat:300387502"
    ]
},
  "bbox": [],
  "geometry": {"coordinates":[5.683333,53.116667],"type":"Point"}
}