{
  "id": 2749160,
  "type": "Feature",
  "properties": {
    "tgn:hierarchy":[
        "tgn:2749160",
        "tgn:1000001",
        "tgn:7012149",
        "tgn:2001104",
        "tgn:7007522",
        "tgn:7029392"
    ],
    "tgn:id":2749160,
    "tgn:name":"Wallace Mill Branch",
    "tgn:placetype":[
        "aat:300008699"
    ]
},
  "bbox": [],
  "geometry": {"coordinates":[-90.85,31.55],"type":"Point"}
}