{
  "id": 2776909,
  "type": "Feature",
  "properties": {
    "tgn:hierarchy":[
        "tgn:2776909",
        "tgn:1000001",
        "tgn:7012149",
        "tgn:2001535",
        "tgn:7007709",
        "tgn:7029392"
    ],
    "tgn:id":2776909,
    "tgn:name":"Windwood",
    "tgn:placetype":[
        "aat:300008347"
    ]
},
  "bbox": [],
  "geometry": {"coordinates":[-79.7667,36.45],"type":"Point"}
}