{
  "id": 2235209,
  "type": "Feature",
  "properties": {
    "tgn:hierarchy":[
        "tgn:2235209",
        "tgn:1000001",
        "tgn:7012149",
        "tgn:2002087",
        "tgn:7007826",
        "tgn:7029392"
    ],
    "tgn:id":2235209,
    "tgn:name":"Cherry Spring Hollow",
    "tgn:placetype":[
        "aat:300008761"
    ]
},
  "bbox": [],
  "geometry": {"coordinates":[-99.4667,29.55],"type":"Point"}
}