{
  "id": 7272774,
  "type": "Feature",
  "properties": {
    "tgn:hierarchy":[
        "tgn:7272774",
        "tgn:7003614",
        "tgn:1000003",
        "tgn:7016845",
        "tgn:7029392"
    ],
    "tgn:id":7272774,
    "tgn:name:nl":"Voorste Landen",
    "tgn:placetype":[
        "aat:300387200"
    ]
},
  "bbox": [],
  "geometry": {"coordinates":[6.816667,52.983333],"type":"Point"}
}