{
  "id": 7473786,
  "type": "Feature",
  "properties": {
    "tgn:hierarchy":[
        "tgn:7473786",
        "tgn:7468018",
        "tgn:1000004",
        "tgn:1000141",
        "tgn:7029392"
    ],
    "tgn:id":7473786,
    "tgn:name":"Dongcuo",
    "tgn:placetype":[
        "aat:300008347"
    ]
},
  "bbox": [],
  "geometry": {"coordinates":[120.336763,23.555762],"type":"Point"}
}