{
  "id": 7421484,
  "type": "Feature",
  "properties": {
    "tgn:hierarchy":[
        "tgn:7421484",
        "tgn:1001836",
        "tgn:1000001",
        "tgn:7005560",
        "tgn:7029392"
    ],
    "tgn:id":7421484,
    "tgn:name":"Los \u00c1ngeles",
    "tgn:placetype":[
        "aat:300008347"
    ]
},
  "bbox": [],
  "geometry": {"coordinates":[-113.283889,27.481944],"type":"Point"}
}