{
  "id": 2572356,
  "type": "Feature",
  "properties": {
    "tgn:hierarchy":[
        "tgn:2572356",
        "tgn:1002153",
        "tgn:1000001",
        "tgn:7012149",
        "tgn:7007710",
        "tgn:7029392"
    ],
    "tgn:id":2572356,
    "tgn:name":"Peach Hill",
    "tgn:placetype":[
        "aat:300008798"
    ]
},
  "bbox": [],
  "geometry": {"coordinates":[-79.5333,40.9167],"type":"Point"}
}