{
  "id": 2435648,
  "type": "Feature",
  "properties": {
    "tgn:hierarchy":[
        "tgn:2435648",
        "tgn:1000001",
        "tgn:7006451",
        "tgn:2000092",
        "tgn:7012149",
        "tgn:7029392"
    ],
    "tgn:id":2435648,
    "tgn:name":"Kessler Tank",
    "tgn:placetype":[
        "aat:300006191"
    ]
},
  "bbox": [],
  "geometry": {"coordinates":[-112.3167,35.1333],"type":"Point"}
}