{
  "id": 2590860,
  "type": "Feature",
  "properties": {
    "tgn:hierarchy":[
        "tgn:2590860",
        "tgn:1000001",
        "tgn:7012149",
        "tgn:2001991",
        "tgn:7007826",
        "tgn:7029392"
    ],
    "tgn:id":2590860,
    "tgn:name":"Polecat Creek",
    "tgn:placetype":[
        "aat:300008706"
    ]
},
  "bbox": [],
  "geometry": {"coordinates":[-101.4333,31.9333],"type":"Point"}
}