<<<<<<< HEAD
{
  "id": 7051017,
  "type": "Feature",
  "properties": {
    "tgn:hierarchy":[
        "tgn:7051017",
        "tgn:1000003",
        "tgn:7003122",
        "tgn:1001762",
        "tgn:1000080",
        "tgn:7029392"
    ],
    "tgn:id":7051017,
    "tgn:name":"Piano Scala",
    "tgn:placetype":[
        "aat:300008347"
    ]
},
  "bbox": [],
  "geometry": {"coordinates":[12.5,37.7],"type":"Point"}
}
=======
{"geometry":{"type":"Point","coordinates":[12.500000,37.700000]},"type":"Feature","properties":{"hierarchy":["tgn:7051017","tgn:1000003","tgn:7003122","tgn:1001762","tgn:1000080","tgn:7029392"],"placetype":["aat:300008347"],"id":7051017,"name:xx":"Piano Scala"}}
>>>>>>> 03f74aca74312dbeaf24d7e61306dd6a786dc3d0
