{
  "id": 2122156,
  "type": "Feature",
  "properties": {
    "tgn:hierarchy":[
        "tgn:2122156",
        "tgn:1000001",
        "tgn:7012149",
        "tgn:2002364",
        "tgn:7007922",
        "tgn:7029392"
    ],
    "tgn:id":2122156,
    "tgn:name":"Port Edwards",
    "tgn:placetype":[
        "aat:300008347"
    ]
},
  "bbox": [],
  "geometry": {"coordinates":[-89.85,44.35],"type":"Point"}
}