{
  "id": 7023762,
  "type": "Feature",
  "properties": {
    "tgn:hierarchy":[
        "tgn:7023762",
        "tgn:1000001",
        "tgn:7012149",
        "tgn:7007568",
        "tgn:7029392"
    ],
    "tgn:id":7023762,
    "tgn:name":"Toad Pond",
    "tgn:placetype":[
        "aat:300008680"
    ]
},
  "bbox": [],
  "geometry": {"coordinates":[-74.85,44.1167],"type":"Point"}
}