{
  "id": 7279885,
  "type": "Feature",
  "properties": {
    "tgn:hierarchy":[
        "tgn:7279885",
        "tgn:7002464",
        "tgn:1000049",
        "tgn:1000002",
        "tgn:7029392"
    ],
    "tgn:id":7279885,
    "tgn:name":"Ramadas",
    "tgn:placetype":[
        "aat:300008347"
    ]
},
  "bbox": [],
  "geometry": {"coordinates":[-69.283333,-20.783333],"type":"Point"}
}