{
  "id": 2750044,
  "type": "Feature",
  "properties": {
    "tgn:hierarchy":[
        "tgn:2750044",
        "tgn:1000001",
        "tgn:7012149",
        "tgn:1002353",
        "tgn:7007252",
        "tgn:7029392"
    ],
    "tgn:id":2750044,
    "tgn:name":"Walter Wisler Ditch",
    "tgn:placetype":[
        "aat:300006075"
    ]
},
  "bbox": [],
  "geometry": {"coordinates":[-86.0167,41.4667],"type":"Point"}
}