{
  "id": 1043544,
  "type": "Feature",
  "properties": {
    "tgn:hierarchy":[
        "tgn:1043544",
        "tgn:1001643",
        "tgn:1000003",
        "tgn:7003122",
        "tgn:1000080",
        "tgn:7029392"
    ],
    "tgn:id":1043544,
    "tgn:name":"Bompensiere",
    "tgn:placetype":[
        "aat:300008347"
    ]
},
  "bbox": [],
  "geometry": {"coordinates":[13.783333,37.466667],"type":"Point"}
}