{
  "id": 2241734,
  "type": "Feature",
  "properties": {
    "tgn:hierarchy":[
        "tgn:2241734",
        "tgn:7013388",
        "tgn:1000001",
        "tgn:7012149",
        "tgn:7007517",
        "tgn:7029392"
    ],
    "tgn:id":2241734,
    "tgn:name":"Clarksburg State Forest",
    "tgn:placetype":[
        "aat:300008863"
    ]
},
  "bbox": [],
  "geometry": {"coordinates":[-73.15,42.7167],"type":"Point"}
}