{
  "id": 7557918,
  "type": "Feature",
  "properties": {
    "tgn:hierarchy":[
        "tgn:7557918",
        "tgn:7016678",
        "tgn:7000204",
        "tgn:7549372",
        "tgn:1000004",
        "tgn:7000198",
        "tgn:7029392"
    ],
    "tgn:id":7557918,
    "tgn:name:en":"S\u0101n\u0113nya",
    "tgn:placetype":[
        "aat:300008347"
    ]
},
  "bbox": [],
  "geometry": {"coordinates":[93.033333,8.466667],"type":"Point"}
}