<<<<<<< HEAD
{
  "id": 7118915,
  "type": "Feature",
  "properties": {
    "tgn:hierarchy":[
        "tgn:7118915",
        "tgn:1000003",
        "tgn:7003678",
        "tgn:7000084",
        "tgn:7029392"
    ],
    "tgn:id":7118915,
    "tgn:name":"Pielhof",
    "tgn:placetype":[
        "aat:300000206"
    ]
},
  "bbox": [],
  "geometry": {"coordinates":[9.883333,50.516667],"type":"Point"}
}
=======
{"geometry":{"type":"Point","coordinates":[9.883333,50.516667]},"type":"Feature","properties":{"hierarchy":["tgn:7118915","tgn:1000003","tgn:7003678","tgn:7000084","tgn:7029392"],"placetype":["aat:300000206"],"id":7118915,"name:xx":"Pielhof"}}
>>>>>>> 03f74aca74312dbeaf24d7e61306dd6a786dc3d0
