{
  "id": 2372614,
  "type": "Feature",
  "properties": {
    "tgn:hierarchy":[
        "tgn:2372614",
        "tgn:1000001",
        "tgn:7012149",
        "tgn:7007516",
        "tgn:7029392"
    ],
    "tgn:id":2372614,
    "tgn:name":"Hall Creek",
    "tgn:placetype":[
        "aat:300008706"
    ]
},
  "bbox": [],
  "geometry": {"coordinates":[-76.5667,38.7167],"type":"Point"}
}