{
  "id": 2461421,
  "type": "Feature",
  "properties": {
    "tgn:hierarchy":[
        "tgn:2461421",
        "tgn:1000001",
        "tgn:7012149",
        "tgn:2002247",
        "tgn:7007920",
        "tgn:7029392"
    ],
    "tgn:id":2461421,
    "tgn:name":"Little Sullivan Lake",
    "tgn:placetype":[
        "aat:300008680"
    ]
},
  "bbox": [],
  "geometry": {"coordinates":[-118.8167,47.4167],"type":"Point"}
}