{
  "id": 2612741,
  "type": "Feature",
  "properties": {
    "tgn:hierarchy":[
        "tgn:2612741",
        "tgn:1000001",
        "tgn:7012149",
        "tgn:1002628",
        "tgn:7007240",
        "tgn:7029392"
    ],
    "tgn:id":2612741,
    "tgn:name":"Redfish Point",
    "tgn:placetype":[
        "aat:300008850"
    ]
},
  "bbox": [],
  "geometry": {"coordinates":[-82.4667,27.5167],"type":"Point"}
}