{
  "id": 7173691,
  "type": "Feature",
  "properties": {
    "tgn:hierarchy":[
        "tgn:7173691",
        "tgn:7003669",
        "tgn:1000003",
        "tgn:7000084",
        "tgn:7029392"
    ],
    "tgn:id":7173691,
    "tgn:name":"Grosser R\u00f6telsee-Weiher",
    "tgn:placetype":[
        "aat:300008688"
    ]
},
  "bbox": [],
  "geometry": {"coordinates":[12.616667,49.216667],"type":"Point"}
}