{
  "id": 7059370,
  "type": "Feature",
  "properties": {
    "tgn:hierarchy":[
        "tgn:7059370",
        "tgn:1000003",
        "tgn:7003678",
        "tgn:7000084",
        "tgn:7029392"
    ],
    "tgn:id":7059370,
    "tgn:name":"Allmenrod",
    "tgn:placetype":[
        "aat:300008347"
    ]
},
  "bbox": [],
  "geometry": {"coordinates":[9.316667,50.633333],"type":"Point"}
}