{
  "id": 7215424,
  "type": "Feature",
  "properties": {
    "tgn:hierarchy":[
        "tgn:7215424",
        "tgn:1000003",
        "tgn:7003676",
        "tgn:7000084",
        "tgn:7029392"
    ],
    "tgn:id":7215424,
    "tgn:name":"Bahnhof Altenbruch",
    "tgn:placetype":[
        "aat:300007783"
    ]
},
  "bbox": [],
  "geometry": {"coordinates":[8.783333,53.833333],"type":"Point"}
}