{
  "id": 7277748,
  "type": "Feature",
  "properties": {
    "tgn:hierarchy":[
        "tgn:7277748",
        "tgn:1001768",
        "tgn:1000049",
        "tgn:1000002",
        "tgn:7029392"
    ],
    "tgn:id":7277748,
    "tgn:name":"Muelle Policarpo Toro",
    "tgn:placetype":[
        "aat:300120779"
    ]
},
  "bbox": [],
  "geometry": {"coordinates":[-71.620833,-33.579167],"type":"Point"}
}