{
  "id": 2148607,
  "type": "Feature",
  "properties": {
    "tgn:hierarchy":[
        "tgn:2148607",
        "tgn:1000001",
        "tgn:2001181",
        "tgn:7012149",
        "tgn:7007523",
        "tgn:7029392"
    ],
    "tgn:id":2148607,
    "tgn:name":"Barnes Hollow",
    "tgn:placetype":[
        "aat:300008761"
    ]
},
  "bbox": [],
  "geometry": {"coordinates":[-91.1833,36.8333],"type":"Point"}
}