{
  "id": 2233014,
  "type": "Feature",
  "properties": {
    "tgn:hierarchy":[
        "tgn:2233014",
        "tgn:1000001",
        "tgn:7012149",
        "tgn:7007157",
        "tgn:2000185",
        "tgn:7029392"
    ],
    "tgn:id":2233014,
    "tgn:name":"Charcoal Ridge",
    "tgn:placetype":[
        "aat:300266640"
    ]
},
  "bbox": [],
  "geometry": {"coordinates":[-122.9667,39.6167],"type":"Point"}
}