{
  "id": 1086435,
  "type": "Feature",
  "properties": {
    "tgn:hierarchy":[
        "tgn:1086435",
        "tgn:7000420",
        "tgn:7018452",
        "tgn:1000004",
        "tgn:1000144",
        "tgn:7029392"
    ],
    "tgn:id":1086435,
    "tgn:name":"Kumdanli",
    "tgn:placetype":[
        "aat:300008347"
    ]
},
  "bbox": [],
  "geometry": {"coordinates":[30.9833,38.3167],"type":"Point"}
}