<<<<<<< HEAD
{
  "id": 7472445,
  "type": "Feature",
  "properties": {
    "tgn:hierarchy":[
        "tgn:7472445",
        "tgn:1000004",
        "tgn:7467799",
        "tgn:1000141",
        "tgn:7029392"
    ],
    "tgn:id":7472445,
    "tgn:name":"Lunjiaoliao Qiao",
    "tgn:placetype":[
        "aat:300007836"
    ]
},
  "bbox": [],
  "geometry": {"coordinates":[120.379708,23.933073],"type":"Point"}
}
=======
{"geometry":{"type":"Point","coordinates":[120.379708,23.933073]},"type":"Feature","properties":{"hierarchy":["tgn:7472445","tgn:1000004","tgn:7467799","tgn:1000141","tgn:7029392"],"placetype":["aat:300007836"],"id":7472445,"name:xx":"Lunjiaoliao Qiao"}}
>>>>>>> 03f74aca74312dbeaf24d7e61306dd6a786dc3d0
