{
  "id": 2241720,
  "type": "Feature",
  "properties": {
    "tgn:hierarchy":[
        "tgn:2241720",
        "tgn:1000001",
        "tgn:7012149",
        "tgn:7014334",
        "tgn:7007919",
        "tgn:7029392"
    ],
    "tgn:id":2241720,
    "tgn:name":"Clarks Run",
    "tgn:placetype":[
        "aat:300008699"
    ]
},
  "bbox": [],
  "geometry": {"coordinates":[-76.75,37.9667],"type":"Point"}
}