{
  "id": 2211348,
  "type": "Feature",
  "properties": {
    "tgn:hierarchy":[
        "tgn:2211348",
        "tgn:1000001",
        "tgn:7012149",
        "tgn:2001297",
        "tgn:7007524",
        "tgn:7029392"
    ],
    "tgn:id":2211348,
    "tgn:name":"Butte Spring",
    "tgn:placetype":[
        "aat:300008697"
    ]
},
  "bbox": [],
  "geometry": {"coordinates":[-105.9167,45.4667],"type":"Point"}
}