{
  "id": 7378065,
  "type": "Feature",
  "properties": {
    "tgn:hierarchy":[
        "tgn:7378065",
        "tgn:1000001",
        "tgn:7005589",
        "tgn:7005560",
        "tgn:7029392"
    ],
    "tgn:id":7378065,
    "tgn:name":"Las Comas, Arroyo",
    "tgn:placetype":[
        "aat:300266554",
        "aat:300008699"
    ]
},
  "bbox": [],
  "geometry": {"coordinates":[-100.483333,27.333333],"type":"Point"}
}