{
  "id": 2335937,
  "type": "Feature",
  "properties": {
    "tgn:hierarchy":[
        "tgn:2335937",
        "tgn:1000001",
        "tgn:2001264",
        "tgn:7012149",
        "tgn:7007524",
        "tgn:7029392"
    ],
    "tgn:id":2335937,
    "tgn:name":"Fossil Lake",
    "tgn:placetype":[
        "aat:300008680"
    ]
},
  "bbox": [],
  "geometry": {"coordinates":[-109.7833,45.0833],"type":"Point"}
}