{
  "id": 7574355,
  "type": "Feature",
  "properties": {
    "tgn:hierarchy":[
        "tgn:7574355",
        "tgn:1000004",
        "tgn:1001832",
        "tgn:7000198",
        "tgn:7029392"
    ],
    "tgn:id":7574355,
    "tgn:name:en":"Jaipur",
    "tgn:placetype":[
        "aat:300008347"
    ]
},
  "bbox": [],
  "geometry": {"coordinates":[95.39595,27.261918],"type":"Point"}
}