{
  "id": 2189851,
  "type": "Feature",
  "properties": {
    "tgn:hierarchy":[
        "tgn:2189851",
        "tgn:1000001",
        "tgn:2001095",
        "tgn:7012149",
        "tgn:7007522",
        "tgn:7029392"
    ],
    "tgn:id":2189851,
    "tgn:name":"Bowie Branch",
    "tgn:placetype":[
        "aat:300008699"
    ]
},
  "bbox": [],
  "geometry": {"coordinates":[-89.2833,33.3333],"type":"Point"}
}