{
  "id": 2420871,
  "type": "Feature",
  "properties": {
    "tgn:hierarchy":[
        "tgn:2420871",
        "tgn:1002338",
        "tgn:1000001",
        "tgn:7012149",
        "tgn:7007516",
        "tgn:7029392"
    ],
    "tgn:id":2420871,
    "tgn:name":"Jenny Island",
    "tgn:placetype":[
        "aat:300008791"
    ]
},
  "bbox": [],
  "geometry": {"coordinates":[-76.05,38.2167],"type":"Point"}
}