{
  "id": 2398104,
  "type": "Feature",
  "properties": {
    "tgn:hierarchy":[
        "tgn:2398104",
        "tgn:1000001",
        "tgn:7012149",
        "tgn:7007157",
        "tgn:7014516",
        "tgn:7029392"
    ],
    "tgn:id":2398104,
    "tgn:name":"Hooker Creek",
    "tgn:placetype":[
        "aat:300008706"
    ]
},
  "bbox": [],
  "geometry": {"coordinates":[-122.45,38.3667],"type":"Point"}
}