{
  "id": 2766673,
  "type": "Feature",
  "properties": {
    "tgn:hierarchy":[
        "tgn:2766673",
        "tgn:1000001",
        "tgn:7012149",
        "tgn:2000907",
        "tgn:7007256",
        "tgn:7029392"
    ],
    "tgn:id":2766673,
    "tgn:name":"White Oak Lake",
    "tgn:placetype":[
        "aat:300008680"
    ]
},
  "bbox": [],
  "geometry": {"coordinates":[-91.1667,32.05],"type":"Point"}
}