{
  "id": 7104030,
  "type": "Feature",
  "properties": {
    "tgn:hierarchy":[
        "tgn:7104030",
        "tgn:7003692",
        "tgn:1000003",
        "tgn:7000084",
        "tgn:7029392"
    ],
    "tgn:id":7104030,
    "tgn:name":"Schachen",
    "tgn:placetype":[
        "aat:300008777"
    ]
},
  "bbox": [],
  "geometry": {"coordinates":[9.466667,48.35],"type":"Point"}
}