{
  "id": 7527366,
  "type": "Feature",
  "properties": {
    "tgn:hierarchy":[
        "tgn:7527366",
        "tgn:7001242",
        "tgn:7016833",
        "tgn:7000122",
        "tgn:7029392"
    ],
    "tgn:id":7527366,
    "tgn:name:en":"S\u012bd\u012b Sharaf",
    "tgn:placetype":[
        "aat:300005926"
    ]
},
  "bbox": [],
  "geometry": {"coordinates":[32.683333,23.016667],"type":"Point"}
}