{
  "id": 2580707,
  "type": "Feature",
  "properties": {
    "tgn:hierarchy":[
        "tgn:2580707",
        "tgn:1000001",
        "tgn:1002294",
        "tgn:7012149",
        "tgn:7007710",
        "tgn:7029392"
    ],
    "tgn:id":2580707,
    "tgn:name":"Pigeon Run",
    "tgn:placetype":[
        "aat:300008699"
    ]
},
  "bbox": [],
  "geometry": {"coordinates":[-76.3167,41.35],"type":"Point"}
}