{
  "id": 7592946,
  "type": "Feature",
  "properties": {
    "tgn:hierarchy":[
        "tgn:7592946",
        "tgn:1000004",
        "tgn:7000198",
        "tgn:7000799",
        "tgn:7029392"
    ],
    "tgn:id":7592946,
    "tgn:name:en":"Pro\u0101n",
    "tgn:placetype":[
        "aat:300008347"
    ]
},
  "bbox": [],
  "geometry": {"coordinates":[74.758333,32.756944],"type":"Point"}
}