{
  "id": 7512509,
  "type": "Feature",
  "properties": {
    "tgn:hierarchy":[
        "tgn:7512509",
        "tgn:1008380",
        "tgn:7520093",
        "tgn:1000226",
        "tgn:1000006",
        "tgn:7029392"
    ],
    "tgn:id":7512509,
    "tgn:name:en":"Horopito",
    "tgn:placetype":[
        "aat:300008347"
    ]
},
  "bbox": [],
  "geometry": {"coordinates":[175.383333,-39.35],"type":"Point"}
}