<<<<<<< HEAD
{
  "id": 2409673,
  "type": "Feature",
  "properties": {
    "tgn:hierarchy":[
        "tgn:2409673",
        "tgn:1000001",
        "tgn:7006451",
        "tgn:2000092",
        "tgn:7012149",
        "tgn:7029392"
    ],
    "tgn:id":2409673,
    "tgn:name":"Ike Tank",
    "tgn:placetype":[
        "aat:300006191"
    ]
},
  "bbox": [],
  "geometry": {"coordinates":[-112.0333,35.1],"type":"Point"}
}
=======
{"geometry":{"type":"Point","coordinates":[-112.033300,35.100000]},"type":"Feature","properties":{"hierarchy":["tgn:2409673","tgn:1000001","tgn:7006451","tgn:2000092","tgn:7012149","tgn:7029392"],"placetype":["aat:300006191"],"id":2409673,"name:xx":"Ike Tank"}}
>>>>>>> 03f74aca74312dbeaf24d7e61306dd6a786dc3d0
