{
  "id": 2759670,
  "type": "Feature",
  "properties": {
    "tgn:hierarchy":[
        "tgn:2759670",
        "tgn:1000001",
        "tgn:2001265",
        "tgn:7012149",
        "tgn:7007524",
        "tgn:7029392"
    ],
    "tgn:id":2759670,
    "tgn:name":"West Fork Hanley Creek",
    "tgn:placetype":[
        "aat:300008706"
    ]
},
  "bbox": [],
  "geometry": {"coordinates":[-104.65,45.9333],"type":"Point"}
}