{
  "id": 2540235,
  "type": "Feature",
  "properties": {
    "tgn:hierarchy":[
        "tgn:2540235",
        "tgn:1000001",
        "tgn:7012149",
        "tgn:7007157",
        "tgn:2000184",
        "tgn:7029392"
    ],
    "tgn:id":2540235,
    "tgn:name":"Newland Reservoir",
    "tgn:placetype":[
        "aat:300006191"
    ]
},
  "bbox": [],
  "geometry": {"coordinates":[-120.0667,41.0833],"type":"Point"}
}