{
  "id": 7525797,
  "type": "Feature",
  "properties": {
    "tgn:hierarchy":[
        "tgn:7525797",
        "tgn:7001242",
        "tgn:7016833",
        "tgn:7000124",
        "tgn:7029392"
    ],
    "tgn:id":7525797,
    "tgn:name:en":"Ban\u012b 'Aysh",
    "tgn:placetype":[
        "aat:300008347"
    ]
},
  "bbox": [],
  "geometry": {"coordinates":[31.85,26.316667],"type":"Point"}
}