<<<<<<< HEAD
{
  "id": 2332874,
  "type": "Feature",
  "properties": {
    "tgn:hierarchy":[
        "tgn:2332874",
        "tgn:1000001",
        "tgn:7012149",
        "tgn:1002429",
        "tgn:7007826",
        "tgn:7029392"
    ],
    "tgn:id":2332874,
    "tgn:name":"Floyds Creek",
    "tgn:placetype":[
        "aat:300008706"
    ]
},
  "bbox": [],
  "geometry": {"coordinates":[-95.8833,30.4167],"type":"Point"}
}
=======
{"geometry":{"type":"Point","coordinates":[-95.883300,30.416700]},"type":"Feature","properties":{"hierarchy":["tgn:2332874","tgn:1000001","tgn:7012149","tgn:1002429","tgn:7007826","tgn:7029392"],"placetype":["aat:300008706"],"id":2332874,"name:xx":"Floyds Creek"}}
>>>>>>> 03f74aca74312dbeaf24d7e61306dd6a786dc3d0
