{
  "id": 7094175,
  "type": "Feature",
  "properties": {
    "tgn:hierarchy":[
        "tgn:7094175",
        "tgn:1000003",
        "tgn:7003677",
        "tgn:7000084",
        "tgn:7029392"
    ],
    "tgn:id":7094175,
    "tgn:name":"Schuter",
    "tgn:placetype":[
        "aat:300387200"
    ]
},
  "bbox": [],
  "geometry": {"coordinates":[7.85,51.916667],"type":"Point"}
}