{
  "id": 7221496,
  "type": "Feature",
  "properties": {
    "tgn:hierarchy":[
        "tgn:7221496",
        "tgn:7011164",
        "tgn:7002674",
        "tgn:1000003",
        "tgn:1000074",
        "tgn:7029392"
    ],
    "tgn:id":7221496,
    "tgn:name":"Kastan\u00e9a",
    "tgn:placetype":[
        "aat:300008347"
    ]
},
  "bbox": [],
  "geometry": {"coordinates":[26.677222,37.754444],"type":"Point"}
}