{
  "id": 1057206,
  "type": "Feature",
  "properties": {
    "tgn:hierarchy":[
        "tgn:1057206",
        "tgn:1000004",
        "tgn:6003149",
        "tgn:7002435",
        "tgn:7029392"
    ],
    "tgn:id":1057206,
    "tgn:name":"Mulda",
    "tgn:placetype":[
        "aat:300008347"
    ]
},
  "bbox": [],
  "geometry": {"coordinates":[63.8667,67.4833],"type":"Point"}
}