{
  "id": 2662380,
  "type": "Feature",
  "properties": {
    "tgn:hierarchy":[
        "tgn:2662380",
        "tgn:1000001",
        "tgn:7006451",
        "tgn:2000093",
        "tgn:7012149",
        "tgn:7029392"
    ],
    "tgn:id":2662380,
    "tgn:name":"Sierra Ancha Experimental Forest",
    "tgn:placetype":[
        "aat:300008863"
    ]
},
  "bbox": [],
  "geometry": {"coordinates":[-110.95,33.7833],"type":"Point"}
}