{
  "id": 1059864,
  "type": "Feature",
  "properties": {
    "tgn:hierarchy":[
        "tgn:1059864",
        "tgn:1000003",
        "tgn:7011999",
        "tgn:7006660",
        "tgn:7029392"
    ],
    "tgn:id":1059864,
    "tgn:name":"Stryzhavka",
    "tgn:placetype":[
        "aat:300008347"
    ]
},
  "bbox": [],
  "geometry": {"coordinates":[28.4667,49.3167],"type":"Point"}
}