<<<<<<< HEAD
{
  "id": 2153402,
  "type": "Feature",
  "properties": {
    "tgn:hierarchy":[
        "tgn:2153402",
        "tgn:1000001",
        "tgn:7012149",
        "tgn:2001231",
        "tgn:7007523",
        "tgn:7029392"
    ],
    "tgn:id":2153402,
    "tgn:name":"Bean Lake",
    "tgn:placetype":[
        "aat:300008680"
    ]
},
  "bbox": [],
  "geometry": {"coordinates":[-95.0,39.4833],"type":"Point"}
}
=======
{"geometry":{"type":"Point","coordinates":[-95.000000,39.483300]},"type":"Feature","properties":{"hierarchy":["tgn:2153402","tgn:1000001","tgn:7012149","tgn:2001231","tgn:7007523","tgn:7029392"],"placetype":["aat:300008680"],"id":2153402,"name:xx":"Bean Lake"}}
>>>>>>> 03f74aca74312dbeaf24d7e61306dd6a786dc3d0
