{
  "id": 1091610,
  "type": "Feature",
  "properties": {
    "tgn:hierarchy":[
        "tgn:1091610",
        "tgn:7001242",
        "tgn:1000940",
        "tgn:1000180",
        "tgn:7029392"
    ],
    "tgn:id":1091610,
    "tgn:name":"Moatize",
    "tgn:placetype":[
        "aat:300008347"
    ]
},
  "bbox": [],
  "geometry": {"coordinates":[33.7167,-16.0667],"type":"Point"}
}