{
  "id": 2382366,
  "type": "Feature",
  "properties": {
    "tgn:hierarchy":[
        "tgn:2382366",
        "tgn:1000001",
        "tgn:7012149",
        "tgn:7007157",
        "tgn:2000185",
        "tgn:7029392"
    ],
    "tgn:id":2382366,
    "tgn:name":"Hayshed Basin",
    "tgn:placetype":[
        "aat:300386845"
    ]
},
  "bbox": [],
  "geometry": {"coordinates":[-123.05,39.7333],"type":"Point"}
}