{
  "id": 2250894,
  "type": "Feature",
  "properties": {
    "tgn:hierarchy":[
        "tgn:2250894",
        "tgn:1000001",
        "tgn:7012149",
        "tgn:7007157",
        "tgn:2000189",
        "tgn:7029392"
    ],
    "tgn:id":2250894,
    "tgn:name":"Columbia Mine",
    "tgn:placetype":[
        "aat:300000390"
    ]
},
  "bbox": [],
  "geometry": {"coordinates":[-122.9333,41.7667],"type":"Point"}
}