<<<<<<< HEAD
{
  "id": 2250894,
  "type": "Feature",
  "properties": {
    "tgn:hierarchy":[
        "tgn:2250894",
        "tgn:1000001",
        "tgn:7012149",
        "tgn:7007157",
        "tgn:2000189",
        "tgn:7029392"
    ],
    "tgn:id":2250894,
    "tgn:name":"Columbia Mine",
    "tgn:placetype":[
        "aat:300000390"
    ]
},
  "bbox": [],
  "geometry": {"coordinates":[-122.9333,41.7667],"type":"Point"}
}
=======
{"geometry":{"type":"Point","coordinates":[-122.933300,41.766700]},"type":"Feature","properties":{"hierarchy":["tgn:2250894","tgn:1000001","tgn:7012149","tgn:7007157","tgn:2000189","tgn:7029392"],"placetype":["aat:300000390"],"id":2250894,"name:xx":"Columbia Mine"}}
>>>>>>> 03f74aca74312dbeaf24d7e61306dd6a786dc3d0
