{
  "id": 7132003,
  "type": "Feature",
  "properties": {
    "tgn:hierarchy":[
        "tgn:7132003",
        "tgn:7003669",
        "tgn:1000003",
        "tgn:7000084",
        "tgn:7029392"
    ],
    "tgn:id":7132003,
    "tgn:name":"Marienberg",
    "tgn:placetype":[
        "aat:300008347"
    ]
},
  "bbox": [],
  "geometry": {"coordinates":[12.116667,47.916667],"type":"Point"}
}