{
  "id": 7374763,
  "type": "Feature",
  "properties": {
    "tgn:hierarchy":[
        "tgn:7374763",
        "tgn:7005581",
        "tgn:1000001",
        "tgn:7005560",
        "tgn:7029392"
    ],
    "tgn:id":7374763,
    "tgn:name":"La Boquilla, Cerro",
    "tgn:placetype":[
        "aat:300008795"
    ]
},
  "bbox": [],
  "geometry": {"coordinates":[-104.766667,29.25],"type":"Point"}
}