{
  "id": 7280694,
  "type": "Feature",
  "properties": {
    "tgn:hierarchy":[
        "tgn:7280694",
        "tgn:7002464",
        "tgn:1000049",
        "tgn:1000002",
        "tgn:7029392"
    ],
    "tgn:id":7280694,
    "tgn:name":"San Jos\u00e9",
    "tgn:placetype":[
        "aat:300006207"
    ]
},
  "bbox": [],
  "geometry": {"coordinates":[-69.75,-20.183333],"type":"Point"}
}