{
  "id": 7316037,
  "type": "Feature",
  "properties": {
    "tgn:hierarchy":[
        "tgn:7316037",
        "tgn:1001702",
        "tgn:1000049",
        "tgn:1000002",
        "tgn:7029392"
    ],
    "tgn:id":7316037,
    "tgn:name":"Cascada, Puerto",
    "tgn:placetype":[
        "aat:300008678"
    ]
},
  "bbox": [],
  "geometry": {"coordinates":[-73.333333,-52.633333],"type":"Point"}
}