{
  "id": 2500083,
  "type": "Feature",
  "properties": {
    "tgn:hierarchy":[
        "tgn:2500083",
        "tgn:1000001",
        "tgn:7012149",
        "tgn:2000988",
        "tgn:7007520",
        "tgn:7029392"
    ],
    "tgn:id":2500083,
    "tgn:name":"McCreedie Lake",
    "tgn:placetype":[
        "aat:300008680"
    ]
},
  "bbox": [],
  "geometry": {"coordinates":[-84.0667,44.7667],"type":"Point"}
}