{
  "id": 1064811,
  "type": "Feature",
  "properties": {
    "tgn:hierarchy":[
        "tgn:1064811",
        "tgn:7008532",
        "tgn:7002443",
        "tgn:1000003",
        "tgn:7008591",
        "tgn:7029392"
    ],
    "tgn:id":1064811,
    "tgn:name:en":"Rhosneigr",
    "tgn:placetype":[
        "aat:300008347"
    ]
},
  "bbox": [],
  "geometry": {"coordinates":[-4.516667,53.233333],"type":"Point"}
}