{
  "id": 2450847,
  "type": "Feature",
  "properties": {
    "tgn:hierarchy":[
        "tgn:2450847",
        "tgn:1000001",
        "tgn:7012149",
        "tgn:2002119",
        "tgn:7007827",
        "tgn:7029392"
    ],
    "tgn:id":2450847,
    "tgn:name":"Lisbon Canyon",
    "tgn:placetype":[
        "aat:300008761"
    ]
},
  "bbox": [],
  "geometry": {"coordinates":[-109.1333,38.15],"type":"Point"}
}