{
  "id": 2216596,
  "type": "Feature",
  "properties": {
    "tgn:hierarchy":[
        "tgn:2216596",
        "tgn:1000001",
        "tgn:7012149",
        "tgn:2001752",
        "tgn:7007712",
        "tgn:7029392"
    ],
    "tgn:id":2216596,
    "tgn:name":"Camp Creek",
    "tgn:placetype":[
        "aat:300008706"
    ]
},
  "bbox": [],
  "geometry": {"coordinates":[-80.6167,34.2667],"type":"Point"}
}