{
  "id": 7165478,
  "type": "Feature",
  "properties": {
    "tgn:hierarchy":[
        "tgn:7165478",
        "tgn:1000003",
        "tgn:7003682",
        "tgn:7000084",
        "tgn:7029392"
    ],
    "tgn:id":7165478,
    "tgn:name":"Hummerich",
    "tgn:placetype":[
        "aat:300008777"
    ]
},
  "bbox": [],
  "geometry": {"coordinates":[7.316667,50.416667],"type":"Point"}
}