{
  "id": 7179028,
  "type": "Feature",
  "properties": {
    "tgn:hierarchy":[
        "tgn:7179028",
        "tgn:1000003",
        "tgn:7003688",
        "tgn:7000084",
        "tgn:7029392"
    ],
    "tgn:id":7179028,
    "tgn:name":"Habichtshorst",
    "tgn:placetype":[
        "aat:300008347"
    ]
},
  "bbox": [],
  "geometry": {"coordinates":[9.85,53.75],"type":"Point"}
}