{
  "id": 2195792,
  "type": "Feature",
  "properties": {
    "tgn:hierarchy":[
        "tgn:2195792",
        "tgn:1000001",
        "tgn:2002263",
        "tgn:7012149",
        "tgn:7013961",
        "tgn:7029392"
    ],
    "tgn:id":2195792,
    "tgn:name":"Broad Run",
    "tgn:placetype":[
        "aat:300008699"
    ]
},
  "bbox": [],
  "geometry": {"coordinates":[-79.3167,38.9667],"type":"Point"}
}