{
  "id": 2503551,
  "type": "Feature",
  "properties": {
    "tgn:hierarchy":[
        "tgn:2503551",
        "tgn:1000001",
        "tgn:1002302",
        "tgn:7012149",
        "tgn:7007568",
        "tgn:7029392"
    ],
    "tgn:id":2503551,
    "tgn:name":"Mead Brook",
    "tgn:placetype":[
        "aat:300008699"
    ]
},
  "bbox": [],
  "geometry": {"coordinates":[-75.9667,42.5667],"type":"Point"}
}