<<<<<<< HEAD
{
  "id": 2706534,
  "type": "Feature",
  "properties": {
    "tgn:hierarchy":[
        "tgn:2706534",
        "tgn:1000001",
        "tgn:7012149",
        "tgn:2000473",
        "tgn:7007250",
        "tgn:7029392"
    ],
    "tgn:id":2706534,
    "tgn:name":"Swan Lake",
    "tgn:placetype":[
        "aat:300006191"
    ]
},
  "bbox": [],
  "geometry": {"coordinates":[-111.0667,44.1],"type":"Point"}
}
=======
{"geometry":{"type":"Point","coordinates":[-111.066700,44.100000]},"type":"Feature","properties":{"hierarchy":["tgn:2706534","tgn:1000001","tgn:7012149","tgn:2000473","tgn:7007250","tgn:7029392"],"placetype":["aat:300006191"],"id":2706534,"name:xx":"Swan Lake"}}
>>>>>>> 03f74aca74312dbeaf24d7e61306dd6a786dc3d0
