{
  "id": 2168942,
  "type": "Feature",
  "properties": {
    "tgn:hierarchy":[
        "tgn:2168942",
        "tgn:1000001",
        "tgn:7016172",
        "tgn:2000120",
        "tgn:7012149",
        "tgn:7029392"
    ],
    "tgn:id":2168942,
    "tgn:name":"Big Island",
    "tgn:placetype":[
        "aat:300008791"
    ]
},
  "bbox": [],
  "geometry": {"coordinates":[-90.4333,35.9167],"type":"Point"}
}