{
  "id": 2787106,
  "type": "Feature",
  "properties": {
    "tgn:hierarchy":[
        "tgn:2787106",
        "tgn:7002659",
        "tgn:1000001",
        "tgn:7012149",
        "tgn:2000059",
        "tgn:7029392"
    ],
    "tgn:id":2787106,
    "tgn:name":"Zion Hill",
    "tgn:placetype":[
        "aat:300008347"
    ]
},
  "bbox": [],
  "geometry": {"coordinates":[-88.0667,32.5167],"type":"Point"}
}