{
  "id": 2133819,
  "type": "Feature",
  "properties": {
    "tgn:hierarchy":[
        "tgn:2133819",
        "tgn:1000001",
        "tgn:7012149",
        "tgn:1002350",
        "tgn:7007157",
        "tgn:7029392"
    ],
    "tgn:id":2133819,
    "tgn:name":"Angel Creek",
    "tgn:placetype":[
        "aat:300008706"
    ]
},
  "bbox": [],
  "geometry": {"coordinates":[-120.3333,38.9667],"type":"Point"}
}