{
  "id": 2475144,
  "type": "Feature",
  "properties": {
    "tgn:hierarchy":[
        "tgn:2475144",
        "tgn:1000001",
        "tgn:7012149",
        "tgn:2000278",
        "tgn:7007240",
        "tgn:7029392"
    ],
    "tgn:id":2475144,
    "tgn:name":"Lowry",
    "tgn:placetype":[
        "aat:300008347"
    ]
},
  "bbox": [],
  "geometry": {"coordinates":[-84.7667,30.4167],"type":"Point"}
}