<<<<<<< HEAD
{
  "id": 7473772,
  "type": "Feature",
  "properties": {
    "tgn:hierarchy":[
        "tgn:7473772",
        "tgn:1000004",
        "tgn:7001009",
        "tgn:1000141",
        "tgn:7029392"
    ],
    "tgn:id":7473772,
    "tgn:name":"Dongyang Li",
    "tgn:placetype":[
        "aat:300387200"
    ]
},
  "bbox": [],
  "geometry": {"coordinates":[120.7484,24.237728],"type":"Point"}
}
=======
{"geometry":{"type":"Point","coordinates":[120.748400,24.237728]},"type":"Feature","properties":{"hierarchy":["tgn:7473772","tgn:1000004","tgn:7001009","tgn:1000141","tgn:7029392"],"placetype":["aat:300387200"],"id":7473772,"name:xx":"Dongyang Li"}}
>>>>>>> 03f74aca74312dbeaf24d7e61306dd6a786dc3d0
