{
  "id": 2230243,
  "type": "Feature",
  "properties": {
    "tgn:hierarchy":[
        "tgn:2230243",
        "tgn:1000001",
        "tgn:7012149",
        "tgn:2000488",
        "tgn:7007250",
        "tgn:7029392"
    ],
    "tgn:id":2230243,
    "tgn:name":"Cemetery Gulch",
    "tgn:placetype":[
        "aat:300008761"
    ]
},
  "bbox": [],
  "geometry": {"coordinates":[-116.7333,43.0167],"type":"Point"}
}