{
  "id": 2571035,
  "type": "Feature",
  "properties": {
    "tgn:hierarchy":[
        "tgn:2571035",
        "tgn:1000001",
        "tgn:7012149",
        "tgn:2001969",
        "tgn:7007826",
        "tgn:7029392"
    ],
    "tgn:id":2571035,
    "tgn:name":"Patterson Pothole",
    "tgn:placetype":[
        "aat:300386845"
    ]
},
  "bbox": [],
  "geometry": {"coordinates":[-104.7833,31.7667],"type":"Point"}
}