{
  "id": 7286908,
  "type": "Feature",
  "properties": {
    "tgn:hierarchy":[
        "tgn:7286908",
        "tgn:7016598",
        "tgn:1000049",
        "tgn:1000002",
        "tgn:7029392"
    ],
    "tgn:id":7286908,
    "tgn:name":"Grit\u00f3n, Caleta del",
    "tgn:placetype":[
        "aat:300132317"
    ]
},
  "bbox": [],
  "geometry": {"coordinates":[-70.533333,-25.483333],"type":"Point"}
}