{
  "id": 2643972,
  "type": "Feature",
  "properties": {
    "tgn:hierarchy":[
        "tgn:2643972",
        "tgn:1000001",
        "tgn:7012149",
        "tgn:7007157",
        "tgn:1002858",
        "tgn:7029392"
    ],
    "tgn:id":2643972,
    "tgn:name":"Santa Clara Cove",
    "tgn:placetype":[
        "aat:300132316"
    ]
},
  "bbox": [],
  "geometry": {"coordinates":[-117.2333,32.7833],"type":"Point"}
}