{
  "id": 7388815,
  "type": "Feature",
  "properties": {
    "tgn:hierarchy":[
        "tgn:7388815",
        "tgn:7005584",
        "tgn:1000001",
        "tgn:7005560",
        "tgn:7029392"
    ],
    "tgn:id":7388815,
    "tgn:name":"Pur\u00edsima del Rinc\u00f3n",
    "tgn:placetype":[
        "aat:300008347"
    ]
},
  "bbox": [],
  "geometry": {"coordinates":[-101.866667,21.033333],"type":"Point"}
}