{
  "id": 1010470,
  "type": "Feature",
  "properties": {
    "tgn:hierarchy":[
        "tgn:1010470",
        "tgn:1000004",
        "tgn:1001517",
        "tgn:7018454",
        "tgn:1000144",
        "tgn:7029392"
    ],
    "tgn:id":1010470,
    "tgn:name":"Bafra Burnu",
    "tgn:placetype":[
        "aat:300008850"
    ]
},
  "bbox": [],
  "geometry": {"coordinates":[35.9667,41.7333],"type":"Point"}
}