{
  "id": 2299767,
  "type": "Feature",
  "properties": {
    "tgn:hierarchy":[
        "tgn:2299767",
        "tgn:1000001",
        "tgn:2001415",
        "tgn:7012149",
        "tgn:7007526",
        "tgn:7029392"
    ],
    "tgn:id":2299767,
    "tgn:name":"Dudley B Shaft",
    "tgn:placetype":[
        "aat:300000390"
    ]
},
  "bbox": [],
  "geometry": {"coordinates":[-117.0667,39.4667],"type":"Point"}
}