{
  "id": 2524998,
  "type": "Feature",
  "properties": {
    "tgn:hierarchy":[
        "tgn:2524998",
        "tgn:1000001",
        "tgn:1002349",
        "tgn:7012149",
        "tgn:7007251",
        "tgn:7029392"
    ],
    "tgn:id":2524998,
    "tgn:name":"Morris Creek",
    "tgn:placetype":[
        "aat:300008706"
    ]
},
  "bbox": [],
  "geometry": {"coordinates":[-88.65,39.1667],"type":"Point"}
}