{
  "id": 7527688,
  "type": "Feature",
  "properties": {
    "tgn:hierarchy":[
        "tgn:7527688",
        "tgn:7001242",
        "tgn:7001311",
        "tgn:7016833",
        "tgn:7029392"
    ],
    "tgn:id":7527688,
    "tgn:name:en":"Zayd, W\u0101d\u012b",
    "tgn:placetype":[
        "aat:300379998"
    ]
},
  "bbox": [],
  "geometry": {"coordinates":[32.945771,24.727204],"type":"Point"}
}