{
  "id": 7469328,
  "type": "Feature",
  "properties": {
    "tgn:hierarchy":[
        "tgn:7469328",
        "tgn:7001004",
        "tgn:1000004",
        "tgn:1000141",
        "tgn:7029392"
    ],
    "tgn:id":7469328,
    "tgn:name":"Xishan",
    "tgn:placetype":[
        "aat:300008347"
    ]
},
  "bbox": [],
  "geometry": {"coordinates":[120.410465,22.480289],"type":"Point"}
}