<<<<<<< HEAD
{
  "id": 7485526,
  "type": "Feature",
  "properties": {
    "tgn:hierarchy":[
        "tgn:7485526",
        "tgn:1000004",
        "tgn:7492971",
        "tgn:1000141",
        "tgn:7029392"
    ],
    "tgn:id":7485526,
    "tgn:name":"Heping Qiao",
    "tgn:placetype":[
        "aat:300007836"
    ]
},
  "bbox": [],
  "geometry": {"coordinates":[120.720833,22.034167],"type":"Point"}
}
=======
{"geometry":{"type":"Point","coordinates":[120.720833,22.034167]},"type":"Feature","properties":{"hierarchy":["tgn:7485526","tgn:1000004","tgn:7492971","tgn:1000141","tgn:7029392"],"placetype":["aat:300007836"],"id":7485526,"name:xx":"Heping Qiao"}}
>>>>>>> 03f74aca74312dbeaf24d7e61306dd6a786dc3d0
