{
  "id": 7128284,
  "type": "Feature",
  "properties": {
    "tgn:hierarchy":[
        "tgn:7128284",
        "tgn:1000003",
        "tgn:7003677",
        "tgn:7000084",
        "tgn:7029392"
    ],
    "tgn:id":7128284,
    "tgn:name":"Niemen",
    "tgn:placetype":[
        "aat:300055621"
    ]
},
  "bbox": [],
  "geometry": {"coordinates":[7.233333,51.733333],"type":"Point"}
}