{
  "id": 2588518,
  "type": "Feature",
  "properties": {
    "tgn:hierarchy":[
        "tgn:2588518",
        "tgn:1000001",
        "tgn:7012149",
        "tgn:7013941",
        "tgn:7007568",
        "tgn:7029392"
    ],
    "tgn:id":2588518,
    "tgn:name":"Plumadore Brook",
    "tgn:placetype":[
        "aat:300008699"
    ]
},
  "bbox": [],
  "geometry": {"coordinates":[-74.1167,44.65],"type":"Point"}
}