{
  "id": 7533642,
  "type": "Feature",
  "properties": {
    "tgn:hierarchy":[
        "tgn:7533642",
        "tgn:7001242",
        "tgn:7016833",
        "tgn:1001088",
        "tgn:7029392"
    ],
    "tgn:id":7533642,
    "tgn:name:en":"Jar\u0101bi', Jaz\u012brat al",
    "tgn:placetype":[
        "aat:300008791"
    ]
},
  "bbox": [],
  "geometry": {"coordinates":[30.833333,28.566667],"type":"Point"}
}