{
  "id": 7442864,
  "type": "Feature",
  "properties": {
    "tgn:hierarchy":[
        "tgn:7442864",
        "tgn:7002445",
        "tgn:7008116",
        "tgn:1000003",
        "tgn:7008591",
        "tgn:7029392"
    ],
    "tgn:id":7442864,
    "tgn:name:en":"Greeb Point",
    "tgn:placetype":[
        "aat:300386846"
    ]
},
  "bbox": [],
  "geometry": {"coordinates":[-4.983333,50.158333],"type":"Point"}
}