{
  "id": 2478883,
  "type": "Feature",
  "properties": {
    "tgn:hierarchy":[
        "tgn:2478883",
        "tgn:1000001",
        "tgn:7012149",
        "tgn:2001543",
        "tgn:7007709",
        "tgn:7029392"
    ],
    "tgn:id":2478883,
    "tgn:name":"Magazine Branch",
    "tgn:placetype":[
        "aat:300008699"
    ]
},
  "bbox": [],
  "geometry": {"coordinates":[-83.9333,35.45],"type":"Point"}
}