{
  "id": 1068576,
  "type": "Feature",
  "properties": {
    "tgn:hierarchy":[
        "tgn:1068576",
        "tgn:1000004",
        "tgn:7002084",
        "tgn:1000111",
        "tgn:7029392"
    ],
    "tgn:id":1068576,
    "tgn:name":"Hancheng",
    "tgn:placetype":[
        "aat:300008347"
    ]
},
  "bbox": [],
  "geometry": {"coordinates":[110.4333,35.4667],"type":"Point"}
}