{
  "id": 7548183,
  "type": "Feature",
  "properties": {
    "tgn:hierarchy":[
        "tgn:7548183",
        "tgn:1000004",
        "tgn:7000198",
        "tgn:1001895",
        "tgn:7029392"
    ],
    "tgn:id":7548183,
    "tgn:name:en":"Bh\u0101ndup",
    "tgn:placetype":[
        "aat:300007783"
    ]
},
  "bbox": [],
  "geometry": {"coordinates":[72.933333,19.133333],"type":"Point"}
}