{
  "id": 1126543,
  "type": "Feature",
  "properties": {
    "tgn:hierarchy":[
        "tgn:1126543",
        "tgn:7002878",
        "tgn:1000003",
        "tgn:1000070",
        "tgn:7029392"
    ],
    "tgn:id":1126543,
    "tgn:name":"Luy",
    "tgn:placetype":[
        "aat:300008707"
    ]
},
  "bbox": [],
  "geometry": {"coordinates":[-1.1333,43.6667],"type":"Point"}
}