{
  "id": 2499266,
  "type": "Feature",
  "properties": {
    "tgn:hierarchy":[
        "tgn:2499266",
        "tgn:1000001",
        "tgn:1002539",
        "tgn:7012149",
        "tgn:7007516",
        "tgn:7029392"
    ],
    "tgn:id":2499266,
    "tgn:name":"McCleans Corner",
    "tgn:placetype":[
        "aat:300008347"
    ]
},
  "bbox": [],
  "geometry": {"coordinates":[-76.1833,39.1833],"type":"Point"}
}