{
  "id": 7022474,
  "type": "Feature",
  "properties": {
    "tgn:hierarchy":[
        "tgn:7022474",
        "tgn:1000001",
        "tgn:7012149",
        "tgn:7029392"
    ],
    "tgn:id":7022474,
    "tgn:name":"Camel Hump Knob",
    "tgn:placetype":[
        "aat:300008798"
    ]
},
  "bbox": [],
  "geometry": {"coordinates":[-83.2167,35.7167],"type":"Point"}
}