<<<<<<< HEAD
{
  "id": 7023173,
  "type": "Feature",
  "properties": {
    "tgn:hierarchy":[
        "tgn:7023173",
        "tgn:1000001",
        "tgn:7012149",
        "tgn:7029392"
    ],
    "tgn:id":7023173,
    "tgn:name":"Shipley Hill",
    "tgn:placetype":[
        "aat:300008798"
    ]
},
  "bbox": [],
  "geometry": {"coordinates":[-71.6333,42.65],"type":"Point"}
}
=======
{"geometry":{"type":"Point","coordinates":[-71.633300,42.650000]},"type":"Feature","properties":{"hierarchy":["tgn:7023173","tgn:1000001","tgn:7012149","tgn:7029392"],"placetype":["aat:300008798"],"id":7023173,"name:xx":"Shipley Hill"}}
>>>>>>> 03f74aca74312dbeaf24d7e61306dd6a786dc3d0
