{
  "id": 1096941,
  "type": "Feature",
  "properties": {
    "tgn:hierarchy":[
        "tgn:1096941",
        "tgn:7000490",
        "tgn:1000006",
        "tgn:7006238",
        "tgn:7029392"
    ],
    "tgn:id":1096941,
    "tgn:name":"Gembrook",
    "tgn:placetype":[
        "aat:300008347"
    ]
},
  "bbox": [],
  "geometry": {"coordinates":[145.55,-37.95],"type":"Point"}
}