{
  "id": 2017155,
  "type": "Feature",
  "properties": {
    "tgn:hierarchy":[
        "tgn:2017155",
        "tgn:1000001",
        "tgn:1002714",
        "tgn:7012149",
        "tgn:7007159",
        "tgn:7029392"
    ],
    "tgn:id":2017155,
    "tgn:name":"Nautilus Park",
    "tgn:placetype":[
        "aat:300008187"
    ]
},
  "bbox": [],
  "geometry": {"coordinates":[-72.05,41.3667],"type":"Point"}
}