{
  "id": 2563062,
  "type": "Feature",
  "properties": {
    "tgn:hierarchy":[
        "tgn:2563062",
        "tgn:1000001",
        "tgn:2001096",
        "tgn:7012149",
        "tgn:7007522",
        "tgn:7029392"
    ],
    "tgn:id":2563062,
    "tgn:name":"Owens Branch",
    "tgn:placetype":[
        "aat:300008699"
    ]
},
  "bbox": [],
  "geometry": {"coordinates":[-90.7667,31.85],"type":"Point"}
}