<<<<<<< HEAD
{
  "id": 7118156,
  "type": "Feature",
  "properties": {
    "tgn:hierarchy":[
        "tgn:7118156",
        "tgn:7003669",
        "tgn:1000003",
        "tgn:7000084",
        "tgn:7029392"
    ],
    "tgn:id":7118156,
    "tgn:name":"Obersch\u00f6nbuch",
    "tgn:placetype":[
        "aat:300000206"
    ]
},
  "bbox": [],
  "geometry": {"coordinates":[11.9,48.583333],"type":"Point"}
}
=======
{"geometry":{"type":"Point","coordinates":[11.900000,48.583333]},"type":"Feature","properties":{"hierarchy":["tgn:7118156","tgn:7003669","tgn:1000003","tgn:7000084","tgn:7029392"],"placetype":["aat:300000206"],"id":7118156,"name:xx":"Obersch\u00f6nbuch"}}
>>>>>>> 03f74aca74312dbeaf24d7e61306dd6a786dc3d0
