{
  "id": 7338988,
  "type": "Feature",
  "properties": {
    "tgn:hierarchy":[
        "tgn:7338988",
        "tgn:7002808",
        "tgn:7030216",
        "tgn:1000003",
        "tgn:1000095",
        "tgn:7029392"
    ],
    "tgn:id":7338988,
    "tgn:name":"El Castell\u00f3",
    "tgn:placetype":[
        "aat:300008798"
    ]
},
  "bbox": [],
  "geometry": {"coordinates":[1.516524,41.448287],"type":"Point"}
}