{
  "id": 7383765,
  "type": "Feature",
  "properties": {
    "tgn:hierarchy":[
        "tgn:7383765",
        "tgn:1000001",
        "tgn:1001960",
        "tgn:7005560",
        "tgn:7029392"
    ],
    "tgn:id":7383765,
    "tgn:name":"Nacimiento",
    "tgn:placetype":[
        "aat:300007783"
    ]
},
  "bbox": [],
  "geometry": {"coordinates":[-109.616667,28.25],"type":"Point"}
}