{
  "id": 7536925,
  "type": "Feature",
  "properties": {
    "tgn:hierarchy":[
        "tgn:7536925",
        "tgn:7001242",
        "tgn:7016833",
        "tgn:7000122",
        "tgn:7029392"
    ],
    "tgn:id":7536925,
    "tgn:name:en":"Jabal al \u1e28ay\u0101t\u012b, Khawr",
    "tgn:placetype":[
        "aat:300185707"
    ]
},
  "bbox": [],
  "geometry": {"coordinates":[32.766667,23.166667],"type":"Point"}
}