{
  "id": 2743816,
  "type": "Feature",
  "properties": {
    "tgn:hierarchy":[
        "tgn:2743816",
        "tgn:1000001",
        "tgn:7012149",
        "tgn:7019676",
        "tgn:7007566",
        "tgn:7029392"
    ],
    "tgn:id":2743816,
    "tgn:name":"Vega Tank",
    "tgn:placetype":[
        "aat:300006191"
    ]
},
  "bbox": [],
  "geometry": {"coordinates":[-107.4667,35.6167],"type":"Point"}
}