{
  "id": 1127558,
  "type": "Feature",
  "properties": {
    "tgn:hierarchy":[
        "tgn:1127558",
        "tgn:7003170",
        "tgn:1000003",
        "tgn:7003125",
        "tgn:1000080",
        "tgn:7029392"
    ],
    "tgn:id":1127558,
    "tgn:name":"Naia",
    "tgn:placetype":[
        "aat:300008707",
        "aat:300008699"
    ]
},
  "bbox": [],
  "geometry": {"coordinates":[12.366667,42.766667],"type":"Point"}
}