<<<<<<< HEAD
{
  "id": 2405914,
  "type": "Feature",
  "properties": {
    "tgn:hierarchy":[
        "tgn:2405914",
        "tgn:1000001",
        "tgn:2001429",
        "tgn:7012149",
        "tgn:7007566",
        "tgn:7029392"
    ],
    "tgn:id":2405914,
    "tgn:name":"Hulsey Lake",
    "tgn:placetype":[
        "aat:300008680"
    ]
},
  "bbox": [],
  "geometry": {"coordinates":[-108.9,33.9167],"type":"Point"}
}
=======
{"geometry":{"type":"Point","coordinates":[-108.900000,33.916700]},"type":"Feature","properties":{"hierarchy":["tgn:2405914","tgn:1000001","tgn:2001429","tgn:7012149","tgn:7007566","tgn:7029392"],"placetype":["aat:300008680"],"id":2405914,"name:xx":"Hulsey Lake"}}
>>>>>>> 03f74aca74312dbeaf24d7e61306dd6a786dc3d0
