{
  "id": 7271057,
  "type": "Feature",
  "properties": {
    "tgn:concordances":{
        "gn:id":"2746908"
    },
    "tgn:hierarchy":[
        "tgn:7271057",
        "tgn:1000003",
        "tgn:7006951",
        "tgn:7016845",
        "tgn:7029392"
    ],
    "tgn:id":7271057,
    "tgn:name:nl":"Spoorbuurt",
    "tgn:placetype":[
        "aat:300008347"
    ]
},
  "bbox": [],
  "geometry": {"coordinates":[4.816667,52.866667],"type":"Point"}
}