{
  "id": 2125481,
  "type": "Feature",
  "properties": {
    "tgn:hierarchy":[
        "tgn:2125481",
        "tgn:1000001",
        "tgn:7012149",
        "tgn:1002995",
        "tgn:7007710",
        "tgn:7029392"
    ],
    "tgn:id":2125481,
    "tgn:name":"Active Sludge Pond",
    "tgn:placetype":[
        "aat:300006191"
    ]
},
  "bbox": [],
  "geometry": {"coordinates":[-80.0167,40.1167],"type":"Point"}
}