{
  "id": 7462801,
  "type": "Feature",
  "properties": {
    "tgn:hierarchy":[
        "tgn:7462801",
        "tgn:7002444",
        "tgn:1000003",
        "tgn:7009907",
        "tgn:7008591",
        "tgn:7029392"
    ],
    "tgn:id":7462801,
    "tgn:name:en":"Links Ness",
    "tgn:placetype":[
        "aat:300008850"
    ]
},
  "bbox": [],
  "geometry": {"coordinates":[-2.666667,59.15],"type":"Point"}
}