{
  "id": 2136203,
  "type": "Feature",
  "properties": {
    "tgn:hierarchy":[
        "tgn:2136203",
        "tgn:1000001",
        "tgn:7012149",
        "tgn:7007826",
        "tgn:7029392"
    ],
    "tgn:id":2136203,
    "tgn:name":"Aransas Bay",
    "tgn:placetype":[
        "aat:300132316"
    ]
},
  "bbox": [],
  "geometry": {"coordinates":[-96.9833,28.05],"type":"Point"}
}