{
  "id": 2322796,
  "type": "Feature",
  "properties": {
    "tgn:hierarchy":[
        "tgn:2322796",
        "tgn:1000001",
        "tgn:7012149",
        "tgn:2001713",
        "tgn:7007708",
        "tgn:7029392"
    ],
    "tgn:id":2322796,
    "tgn:name":"Fan Creek",
    "tgn:placetype":[
        "aat:300008706"
    ]
},
  "bbox": [],
  "geometry": {"coordinates":[-123.3333,42.0833],"type":"Point"}
}