{
  "id": 2026527,
  "type": "Feature",
  "properties": {
    "tgn:hierarchy":[
        "tgn:2026527",
        "tgn:1000001",
        "tgn:7012149",
        "tgn:2000508",
        "tgn:7007251",
        "tgn:7029392"
    ],
    "tgn:id":2026527,
    "tgn:name":"Belle Prairie City",
    "tgn:placetype":[
        "aat:300008347"
    ]
},
  "bbox": [],
  "geometry": {"coordinates":[-88.55,38.2167],"type":"Point"}
}