{
  "id": 2441478,
  "type": "Feature",
  "properties": {
    "tgn:hierarchy":[
        "tgn:2441478",
        "tgn:1007657",
        "tgn:1002534",
        "tgn:1000001",
        "tgn:7012149",
        "tgn:7007249",
        "tgn:7029392"
    ],
    "tgn:id":2441478,
    "tgn:name":"Koaie Stream",
    "tgn:placetype":[
        "aat:300008699"
    ]
},
  "bbox": [],
  "geometry": {"coordinates":[-159.55,22.0833],"type":"Point"}
}