<<<<<<< HEAD
{
  "id": 2253749,
  "type": "Feature",
  "properties": {
    "tgn:hierarchy":[
        "tgn:2253749",
        "tgn:7002659",
        "tgn:1000001",
        "tgn:7012149",
        "tgn:2000031",
        "tgn:7029392"
    ],
    "tgn:id":2253749,
    "tgn:name":"Cooks Branch",
    "tgn:placetype":[
        "aat:300008699"
    ]
},
  "bbox": [],
  "geometry": {"coordinates":[-88.0833,32.8333],"type":"Point"}
}
=======
{"geometry":{"type":"Point","coordinates":[-88.083300,32.833300]},"type":"Feature","properties":{"hierarchy":["tgn:2253749","tgn:7002659","tgn:1000001","tgn:7012149","tgn:2000031","tgn:7029392"],"placetype":["aat:300008699"],"id":2253749,"name:xx":"Cooks Branch"}}
>>>>>>> 03f74aca74312dbeaf24d7e61306dd6a786dc3d0
