{
  "id": 2216617,
  "type": "Feature",
  "properties": {
    "tgn:hierarchy":[
        "tgn:2216617",
        "tgn:1000001",
        "tgn:7012149",
        "tgn:2001949",
        "tgn:7007826",
        "tgn:7029392"
    ],
    "tgn:id":2216617,
    "tgn:name":"Camp Creek",
    "tgn:placetype":[
        "aat:300008706"
    ]
},
  "bbox": [],
  "geometry": {"coordinates":[-98.15,30.6167],"type":"Point"}
}