{
  "id": 2780935,
  "type": "Feature",
  "properties": {
    "tgn:hierarchy":[
        "tgn:2780935",
        "tgn:1000001",
        "tgn:1002275",
        "tgn:7012149",
        "tgn:7007920",
        "tgn:7029392"
    ],
    "tgn:id":2780935,
    "tgn:name":"Woodburn Hill",
    "tgn:placetype":[
        "aat:300008798"
    ]
},
  "bbox": [],
  "geometry": {"coordinates":[-122.35,45.5833],"type":"Point"}
}