{
  "id": 7528587,
  "type": "Feature",
  "properties": {
    "tgn:hierarchy":[
        "tgn:7528587",
        "tgn:7001242",
        "tgn:7016833",
        "tgn:7001335",
        "tgn:7029392"
    ],
    "tgn:id":7528587,
    "tgn:name:en":"Umm 'Iz\u0327\u0101m, Kath\u012bb",
    "tgn:placetype":[
        "aat:300008750"
    ]
},
  "bbox": [],
  "geometry": {"coordinates":[32.683333,30.316667],"type":"Point"}
}