{
  "id": 7261646,
  "type": "Feature",
  "properties": {
    "tgn:hierarchy":[
        "tgn:7261646",
        "tgn:1000003",
        "tgn:7006951",
        "tgn:7016845",
        "tgn:7029392"
    ],
    "tgn:id":7261646,
    "tgn:name:nl":"Haaksgronden",
    "tgn:placetype":[
        "aat:300387036"
    ]
},
  "bbox": [],
  "geometry": {"coordinates":[4.566667,52.966667],"type":"Point"}
}