{
  "id": 7141276,
  "type": "Feature",
  "properties": {
    "tgn:hierarchy":[
        "tgn:7141276",
        "tgn:7000096",
        "tgn:1000003",
        "tgn:7000084",
        "tgn:7029392"
    ],
    "tgn:id":7141276,
    "tgn:name":"Malchow",
    "tgn:placetype":[
        "aat:300008347"
    ]
},
  "bbox": [],
  "geometry": {"coordinates":[13.916667,53.416667],"type":"Point"}
}