{
  "id": 7019996,
  "type": "Feature",
  "properties": {
    "tgn:hierarchy":[
        "tgn:7019996",
        "tgn:1000001",
        "tgn:7012149",
        "tgn:7029392"
    ],
    "tgn:id":7019996,
    "tgn:name":"Cottonwood Valley",
    "tgn:placetype":[
        "aat:300386845",
        "aat:300008761"
    ]
},
  "bbox": [],
  "geometry": {"coordinates":[-114.5833,35.3667],"type":"Point"}
}