{
  "id": 7015109,
  "type": "Feature",
  "properties": {
    "tgn:hierarchy":[
        "tgn:7015109",
        "tgn:1000003",
        "tgn:7006670",
        "tgn:7029392"
    ],
    "tgn:id":7015109,
    "tgn:name":"Litija, Ob\u010dina",
    "tgn:placetype":[
        "aat:300387064",
        "aat:300387081"
    ]
},
  "bbox": [],
  "geometry": {"coordinates":[14.8333,46.0333],"type":"Point"}
}