{
  "id": 7341806,
  "type": "Feature",
  "properties": {
    "tgn:hierarchy":[
        "tgn:7341806",
        "tgn:7002759",
        "tgn:7008909",
        "tgn:1000003",
        "tgn:1000095",
        "tgn:7029392"
    ],
    "tgn:id":7341806,
    "tgn:name":"Bergua",
    "tgn:placetype":[
        "aat:300008347"
    ]
},
  "bbox": [],
  "geometry": {"coordinates":[-0.170229,42.533728],"type":"Point"}
}