{
  "id": 7499703,
  "type": "Feature",
  "properties": {
    "tgn:hierarchy":[
        "tgn:7499703",
        "tgn:1000004",
        "tgn:1000959",
        "tgn:1000141",
        "tgn:7029392"
    ],
    "tgn:id":7499703,
    "tgn:name":"Zhongshan Zhan",
    "tgn:placetype":[
        "aat:300007783"
    ]
},
  "bbox": [],
  "geometry": {"coordinates":[121.520128,25.052814],"type":"Point"}
}