{
  "id": 2442927,
  "type": "Feature",
  "properties": {
    "tgn:hierarchy":[
        "tgn:2442927",
        "tgn:1000001",
        "tgn:7012149",
        "tgn:2000960",
        "tgn:7007520",
        "tgn:7029392"
    ],
    "tgn:id":2442927,
    "tgn:name":"Kunschke Lake",
    "tgn:placetype":[
        "aat:300008680"
    ]
},
  "bbox": [],
  "geometry": {"coordinates":[-89.6667,46.25],"type":"Point"}
}