{
  "id": 2668079,
  "type": "Feature",
  "properties": {
    "tgn:hierarchy":[
        "tgn:2668079",
        "tgn:1000001",
        "tgn:7016172",
        "tgn:7012149",
        "tgn:2000176",
        "tgn:7029392"
    ],
    "tgn:id":2668079,
    "tgn:name":"Skylight",
    "tgn:placetype":[
        "aat:300008347"
    ]
},
  "bbox": [],
  "geometry": {"coordinates":[-94.3833,35.8333],"type":"Point"}
}