{
  "id": 7364428,
  "type": "Feature",
  "properties": {
    "tgn:hierarchy":[
        "tgn:7364428",
        "tgn:1000001",
        "tgn:7005597",
        "tgn:7005560",
        "tgn:7029392"
    ],
    "tgn:id":7364428,
    "tgn:name":"El Sarnoso",
    "tgn:placetype":[
        "aat:300008347"
    ]
},
  "bbox": [],
  "geometry": {"coordinates":[-98.666667,24.866667],"type":"Point"}
}