{
  "id": 7109650,
  "type": "Feature",
  "properties": {
    "tgn:hierarchy":[
        "tgn:7109650",
        "tgn:7003669",
        "tgn:1000003",
        "tgn:7000084",
        "tgn:7029392"
    ],
    "tgn:id":7109650,
    "tgn:name":"Ramsler",
    "tgn:placetype":[
        "aat:300000206"
    ]
},
  "bbox": [],
  "geometry": {"coordinates":[12.666667,47.733333],"type":"Point"}
}