{
  "id": 2307519,
  "type": "Feature",
  "properties": {
    "tgn:hierarchy":[
        "tgn:2307519",
        "tgn:1000001",
        "tgn:7012149",
        "tgn:2002248",
        "tgn:7007920",
        "tgn:7029392"
    ],
    "tgn:id":2307519,
    "tgn:name":"East Fork Small Creek",
    "tgn:placetype":[
        "aat:300008706"
    ]
},
  "bbox": [],
  "geometry": {"coordinates":[-117.4833,48.3833],"type":"Point"}
}