{
  "id": 2677169,
  "type": "Feature",
  "properties": {
    "tgn:hierarchy":[
        "tgn:2677169",
        "tgn:1000001",
        "tgn:1002738",
        "tgn:7012149",
        "tgn:7007565",
        "tgn:7029392"
    ],
    "tgn:id":2677169,
    "tgn:name":"South Branch Stouts Creek",
    "tgn:placetype":[
        "aat:300008706"
    ]
},
  "bbox": [],
  "geometry": {"coordinates":[-74.1667,39.8333],"type":"Point"}
}