{
  "id": 7379270,
  "type": "Feature",
  "properties": {
    "tgn:hierarchy":[
        "tgn:7379270",
        "tgn:7005583",
        "tgn:1000001",
        "tgn:7005560",
        "tgn:7029392"
    ],
    "tgn:id":7379270,
    "tgn:name":"Rancho Los Sauces de Cardona",
    "tgn:placetype":[
        "aat:300000241"
    ]
},
  "bbox": [],
  "geometry": {"coordinates":[-105.366667,26.016667],"type":"Point"}
}