{
  "id": 2398471,
  "type": "Feature",
  "properties": {
    "tgn:hierarchy":[
        "tgn:2398471",
        "tgn:1000001",
        "tgn:7012149",
        "tgn:2000802",
        "tgn:7007255",
        "tgn:7029392"
    ],
    "tgn:id":2398471,
    "tgn:name":"Hooten Branch",
    "tgn:placetype":[
        "aat:300008699"
    ]
},
  "bbox": [],
  "geometry": {"coordinates":[-84.0667,37.4167],"type":"Point"}
}