{
  "id": 2599479,
  "type": "Feature",
  "properties": {
    "tgn:hierarchy":[
        "tgn:2599479",
        "tgn:1000001",
        "tgn:7012149",
        "tgn:2001507",
        "tgn:7007709",
        "tgn:7029392"
    ],
    "tgn:id":2599479,
    "tgn:name":"Prospect Branch",
    "tgn:placetype":[
        "aat:300008699"
    ]
},
  "bbox": [],
  "geometry": {"coordinates":[-80.95,35.9833],"type":"Point"}
}