{
  "id": 7336443,
  "type": "Feature",
  "properties": {
    "tgn:hierarchy":[
        "tgn:7336443",
        "tgn:7002808",
        "tgn:7030216",
        "tgn:1000003",
        "tgn:1000095",
        "tgn:7029392"
    ],
    "tgn:id":7336443,
    "tgn:name":"G\u00e9lida",
    "tgn:placetype":[
        "aat:300008347"
    ]
},
  "bbox": [],
  "geometry": {"coordinates":[1.860957,41.4404],"type":"Point"}
}