{
  "id": 7229350,
  "type": "Feature",
  "properties": {
    "tgn:hierarchy":[
        "tgn:7229350",
        "tgn:7002743",
        "tgn:7017076",
        "tgn:1000003",
        "tgn:1000074",
        "tgn:7029392"
    ],
    "tgn:id":7229350,
    "tgn:name":"Latz\u00f3\u00efon",
    "tgn:placetype":[
        "aat:300008347"
    ]
},
  "bbox": [],
  "geometry": {"coordinates":[21.566667,37.716667],"type":"Point"}
}