{
  "id": 2640771,
  "type": "Feature",
  "properties": {
    "tgn:hierarchy":[
        "tgn:2640771",
        "tgn:1000001",
        "tgn:7012149",
        "tgn:1009002",
        "tgn:7007157",
        "tgn:1002867",
        "tgn:7029392"
    ],
    "tgn:id":2640771,
    "tgn:name":"San Pedro Point",
    "tgn:placetype":[
        "aat:300008850"
    ]
},
  "bbox": [],
  "geometry": {"coordinates":[-119.5167,34.0333],"type":"Point"}
}