{
  "id": 1015221,
  "type": "Feature",
  "properties": {
    "tgn:hierarchy":[
        "tgn:1015221",
        "tgn:7005685",
        "tgn:1000001",
        "tgn:7013154",
        "tgn:7029392"
    ],
    "tgn:id":1015221,
    "tgn:name":"Whitney",
    "tgn:placetype":[
        "aat:300008347"
    ]
},
  "bbox": [],
  "geometry": {"coordinates":[-78.25,45.4833],"type":"Point"}
}