{
  "id": 2660333,
  "type": "Feature",
  "properties": {
    "tgn:hierarchy":[
        "tgn:2660333",
        "tgn:1000001",
        "tgn:7012149",
        "tgn:7007522",
        "tgn:7029392"
    ],
    "tgn:id":2660333,
    "tgn:name":"Shockaloo Creek",
    "tgn:placetype":[
        "aat:300008706"
    ]
},
  "bbox": [],
  "geometry": {"coordinates":[-89.5333,32.35],"type":"Point"}
}