{
  "id": 7394563,
  "type": "Feature",
  "properties": {
    "tgn:hierarchy":[
        "tgn:7394563",
        "tgn:7005587",
        "tgn:1000001",
        "tgn:7005560",
        "tgn:7029392"
    ],
    "tgn:id":7394563,
    "tgn:name":"San Alejo",
    "tgn:placetype":[
        "aat:300008347"
    ]
},
  "bbox": [],
  "geometry": {"coordinates":[-98.283333,20.15],"type":"Point"}
}