{
  "id": 7517304,
  "type": "Feature",
  "properties": {
    "tgn:hierarchy":[
        "tgn:7517304",
        "tgn:1009227",
        "tgn:1000226",
        "tgn:7016822",
        "tgn:1000006",
        "tgn:7029392"
    ],
    "tgn:id":7517304,
    "tgn:name:en":"North Head",
    "tgn:placetype":[
        "aat:300008850"
    ]
},
  "bbox": [],
  "geometry": {"coordinates":[168.533333,-46.733333],"type":"Point"}
}