{
  "id": 2473937,
  "type": "Feature",
  "properties": {
    "tgn:hierarchy":[
        "tgn:2473937",
        "tgn:1000001",
        "tgn:7012149",
        "tgn:2000495",
        "tgn:7007250",
        "tgn:7029392"
    ],
    "tgn:id":2473937,
    "tgn:name":"Lower Hornet Reservoir",
    "tgn:placetype":[
        "aat:300006191"
    ]
},
  "bbox": [],
  "geometry": {"coordinates":[-116.7167,44.7833],"type":"Point"}
}