{
  "id": 1076563,
  "type": "Feature",
  "properties": {
    "tgn:hierarchy":[
        "tgn:1076563",
        "tgn:1000004",
        "tgn:7031781",
        "tgn:7000198",
        "tgn:7029392"
    ],
    "tgn:id":1076563,
    "tgn:name:en":"Pathalgaon",
    "tgn:placetype":[
        "aat:300008347"
    ]
},
  "bbox": [],
  "geometry": {"coordinates":[83.463554,22.556561],"type":"Point"}
}