{
  "id": 2653882,
  "type": "Feature",
  "properties": {
    "tgn:hierarchy":[
        "tgn:2653882",
        "tgn:1000001",
        "tgn:7012149",
        "tgn:1002406",
        "tgn:7007520",
        "tgn:7029392"
    ],
    "tgn:id":2653882,
    "tgn:name":"Seymour McKinley Drain",
    "tgn:placetype":[
        "aat:300006075"
    ]
},
  "bbox": [],
  "geometry": {"coordinates":[-83.85,43.0167],"type":"Point"}
}