{
  "id": 1125488,
  "type": "Feature",
  "properties": {
    "tgn:hierarchy":[
        "tgn:1125488",
        "tgn:1000004",
        "tgn:7011590",
        "tgn:7018214",
        "tgn:7002435",
        "tgn:7029392"
    ],
    "tgn:id":1125488,
    "tgn:name":"Keb'",
    "tgn:placetype":[
        "aat:300008707"
    ]
},
  "bbox": [],
  "geometry": {"coordinates":[28.4667,57.7333],"type":"Point"}
}