<<<<<<< HEAD
{
  "id": 7479813,
  "type": "Feature",
  "properties": {
    "tgn:hierarchy":[
        "tgn:7479813",
        "tgn:1000004",
        "tgn:7490934",
        "tgn:1000141",
        "tgn:7029392"
    ],
    "tgn:id":7479813,
    "tgn:name":"Hongshuiquan Xi",
    "tgn:placetype":[
        "aat:300008699"
    ]
},
  "bbox": [],
  "geometry": {"coordinates":[120.42632,23.013414],"type":"Point"}
}
=======
{"geometry":{"type":"Point","coordinates":[120.426320,23.013414]},"type":"Feature","properties":{"hierarchy":["tgn:7479813","tgn:1000004","tgn:7490934","tgn:1000141","tgn:7029392"],"placetype":["aat:300008699"],"id":7479813,"name:xx":"Hongshuiquan Xi"}}
>>>>>>> 03f74aca74312dbeaf24d7e61306dd6a786dc3d0
