{
  "id": 7145725,
  "type": "Feature",
  "properties": {
    "tgn:hierarchy":[
        "tgn:7145725",
        "tgn:1000003",
        "tgn:7000094",
        "tgn:7000084",
        "tgn:7029392"
    ],
    "tgn:id":7145725,
    "tgn:name":"Kollicker Berge",
    "tgn:placetype":[
        "aat:300266640"
    ]
},
  "bbox": [],
  "geometry": {"coordinates":[13.65,54.55],"type":"Point"}
}