{
  "id": 2015997,
  "type": "Feature",
  "properties": {
    "tgn:hierarchy":[
        "tgn:2015997",
        "tgn:1000001",
        "tgn:7012149",
        "tgn:2000230",
        "tgn:7007158",
        "tgn:7029392"
    ],
    "tgn:id":2015997,
    "tgn:name":"Molina",
    "tgn:placetype":[
        "aat:300008347"
    ]
},
  "bbox": [],
  "geometry": {"coordinates":[-108.05,39.1833],"type":"Point"}
}