{
  "id": 7263067,
  "type": "Feature",
  "properties": {
    "tgn:hierarchy":[
        "tgn:7263067",
        "tgn:1000003",
        "tgn:7003624",
        "tgn:7016845",
        "tgn:7029392"
    ],
    "tgn:id":7263067,
    "tgn:name:nl":"De Bunthorst",
    "tgn:placetype":[
        "aat:300387502"
    ]
},
  "bbox": [],
  "geometry": {"coordinates":[5.816667,51.583333],"type":"Point"}
}