{
  "id": 2372214,
  "type": "Feature",
  "properties": {
    "tgn:hierarchy":[
        "tgn:2372214",
        "tgn:1000001",
        "tgn:7012149",
        "tgn:2000931",
        "tgn:7007515",
        "tgn:7029392"
    ],
    "tgn:id":2372214,
    "tgn:name":"Halfmoon Stream",
    "tgn:placetype":[
        "aat:300008699"
    ]
},
  "bbox": [],
  "geometry": {"coordinates":[-68.9167,44.55],"type":"Point"}
}