{
  "id": 7328541,
  "type": "Feature",
  "properties": {
    "tgn:hierarchy":[
        "tgn:7328541",
        "tgn:7002758",
        "tgn:7002817",
        "tgn:1000003",
        "tgn:1000095",
        "tgn:7029392"
    ],
    "tgn:id":7328541,
    "tgn:name":"Quinta, Laguna de la",
    "tgn:placetype":[
        "aat:300008692"
    ]
},
  "bbox": [],
  "geometry": {"coordinates":[-4.266667,37.75],"type":"Point"}
}