<<<<<<< HEAD
{
  "id": 2333546,
  "type": "Feature",
  "properties": {
    "tgn:hierarchy":[
        "tgn:2333546",
        "tgn:1000001",
        "tgn:7012149",
        "tgn:2002379",
        "tgn:7007923",
        "tgn:7029392"
    ],
    "tgn:id":2333546,
    "tgn:name":"Folsom Peak",
    "tgn:placetype":[
        "aat:300008798"
    ]
},
  "bbox": [],
  "geometry": {"coordinates":[-110.5333,44.8667],"type":"Point"}
}
=======
{"geometry":{"type":"Point","coordinates":[-110.533300,44.866700]},"type":"Feature","properties":{"hierarchy":["tgn:2333546","tgn:1000001","tgn:7012149","tgn:2002379","tgn:7007923","tgn:7029392"],"placetype":["aat:300008798"],"id":2333546,"name:xx":"Folsom Peak"}}
>>>>>>> 03f74aca74312dbeaf24d7e61306dd6a786dc3d0
