{
  "id": 2412421,
  "type": "Feature",
  "properties": {
    "tgn:hierarchy":[
        "tgn:2412421",
        "tgn:7002659",
        "tgn:1000001",
        "tgn:7012149",
        "tgn:2000039",
        "tgn:7029392"
    ],
    "tgn:id":2412421,
    "tgn:name":"Indian Tomb Hollow",
    "tgn:placetype":[
        "aat:300008761"
    ]
},
  "bbox": [],
  "geometry": {"coordinates":[-87.25,34.3667],"type":"Point"}
}