{
  "id": 2052134,
  "type": "Feature",
  "properties": {
    "tgn:hierarchy":[
        "tgn:2052134",
        "tgn:1000001",
        "tgn:7012149",
        "tgn:1003005",
        "tgn:7007520",
        "tgn:7029392"
    ],
    "tgn:id":2052134,
    "tgn:name":"Harper Woods",
    "tgn:placetype":[
        "aat:300008347"
    ]
},
  "bbox": [],
  "geometry": {"coordinates":[-82.9167,42.4167],"type":"Point"}
}