{
  "id": 7449172,
  "type": "Feature",
  "properties": {
    "tgn:hierarchy":[
        "tgn:7449172",
        "tgn:7002445",
        "tgn:1000003",
        "tgn:7008160",
        "tgn:7008591",
        "tgn:7029392"
    ],
    "tgn:id":7449172,
    "tgn:name:en":"Seal Sand",
    "tgn:placetype":[
        "aat:300386970"
    ]
},
  "bbox": [],
  "geometry": {"coordinates":[0.333333,52.883333],"type":"Point"}
}