{
  "id": 7401842,
  "type": "Feature",
  "properties": {
    "tgn:hierarchy":[
        "tgn:7401842",
        "tgn:1000001",
        "tgn:7005599",
        "tgn:7005560",
        "tgn:7029392"
    ],
    "tgn:id":7401842,
    "tgn:name":"Atoyac, R\u00edo",
    "tgn:placetype":[
        "aat:300008699"
    ]
},
  "bbox": [],
  "geometry": {"coordinates":[-96.283333,18.883333],"type":"Point"}
}