<<<<<<< HEAD
{
  "id": 7373034,
  "type": "Feature",
  "properties": {
    "tgn:hierarchy":[
        "tgn:7373034",
        "tgn:1000001",
        "tgn:7005601",
        "tgn:7005560",
        "tgn:7029392"
    ],
    "tgn:id":7373034,
    "tgn:name":"Rancho La Fortuna",
    "tgn:placetype":[
        "aat:300000241"
    ]
},
  "bbox": [],
  "geometry": {"coordinates":[-101.816667,24.033333],"type":"Point"}
}
=======
{"geometry":{"type":"Point","coordinates":[-101.816667,24.033333]},"type":"Feature","properties":{"hierarchy":["tgn:7373034","tgn:1000001","tgn:7005601","tgn:7005560","tgn:7029392"],"placetype":["aat:300000241"],"id":7373034,"name:xx":"Rancho La Fortuna"}}
>>>>>>> 03f74aca74312dbeaf24d7e61306dd6a786dc3d0
