{
  "id": 2436930,
  "type": "Feature",
  "properties": {
    "tgn:hierarchy":[
        "tgn:2436930",
        "tgn:1000001",
        "tgn:2000922",
        "tgn:7012149",
        "tgn:7007515",
        "tgn:7029392"
    ],
    "tgn:id":2436930,
    "tgn:name":"Kilkenny Stream",
    "tgn:placetype":[
        "aat:300008699"
    ]
},
  "bbox": [],
  "geometry": {"coordinates":[-68.3833,44.55],"type":"Point"}
}