{
  "id": 7587806,
  "type": "Feature",
  "properties": {
    "tgn:hierarchy":[
        "tgn:7587806",
        "tgn:1000004",
        "tgn:7000198",
        "tgn:1001977",
        "tgn:7029392"
    ],
    "tgn:id":7587806,
    "tgn:name:en":"Berghom",
    "tgn:placetype":[
        "aat:300008347"
    ]
},
  "bbox": [],
  "geometry": {"coordinates":[88.706148,22.872221],"type":"Point"}
}