<<<<<<< HEAD
{
  "id": 7471350,
  "type": "Feature",
  "properties": {
    "tgn:hierarchy":[
        "tgn:7471350",
        "tgn:7468018",
        "tgn:1000004",
        "tgn:1000141",
        "tgn:7029392"
    ],
    "tgn:id":7471350,
    "tgn:name":"Fanlu Xiang",
    "tgn:placetype":[
        "aat:300387173"
    ]
},
  "bbox": [],
  "geometry": {"coordinates":[120.6,23.433333],"type":"Point"}
}
=======
{"geometry":{"type":"Point","coordinates":[120.600000,23.433333]},"type":"Feature","properties":{"hierarchy":["tgn:7471350","tgn:7468018","tgn:1000004","tgn:1000141","tgn:7029392"],"placetype":["aat:300387173"],"id":7471350,"name:xx":"Fanlu Xiang"}}
>>>>>>> 03f74aca74312dbeaf24d7e61306dd6a786dc3d0
