{
  "id": 7588588,
  "type": "Feature",
  "properties": {
    "tgn:hierarchy":[
        "tgn:7588588",
        "tgn:1000004",
        "tgn:7000198",
        "tgn:1001977",
        "tgn:7029392"
    ],
    "tgn:id":7588588,
    "tgn:name:en":"Rajapur",
    "tgn:placetype":[
        "aat:300008347"
    ]
},
  "bbox": [],
  "geometry": {"coordinates":[88.528333,22.218333],"type":"Point"}
}