{
  "id": 7504210,
  "type": "Feature",
  "properties": {
    "tgn:hierarchy":[
        "tgn:7504210",
        "tgn:1009227",
        "tgn:1000226",
        "tgn:7520095",
        "tgn:1000006",
        "tgn:7029392"
    ],
    "tgn:id":7504210,
    "tgn:name:en":"Walsh",
    "tgn:placetype":[
        "aat:300008699"
    ]
},
  "bbox": [],
  "geometry": {"coordinates":[172.45,-40.833333],"type":"Point"}
}