{
  "id": 1117956,
  "type": "Feature",
  "properties": {
    "tgn:hierarchy":[
        "tgn:1117956",
        "tgn:7005685",
        "tgn:1000001",
        "tgn:7005734",
        "tgn:7029392"
    ],
    "tgn:id":1117956,
    "tgn:name":"Russell Lake",
    "tgn:placetype":[
        "aat:300008680"
    ]
},
  "bbox": [],
  "geometry": {"coordinates":[-101.5333,56.25],"type":"Point"}
}