{
  "id": 7295556,
  "type": "Feature",
  "properties": {
    "tgn:hierarchy":[
        "tgn:7295556",
        "tgn:7002813",
        "tgn:7002758",
        "tgn:1000003",
        "tgn:1000095",
        "tgn:7029392"
    ],
    "tgn:id":7295556,
    "tgn:name":"Phare, Piedra",
    "tgn:placetype":[
        "aat:300011692"
    ]
},
  "bbox": [],
  "geometry": {"coordinates":[-6.048611,36.175],"type":"Point"}
}