{
  "id": 2598013,
  "type": "Feature",
  "properties": {
    "tgn:hierarchy":[
        "tgn:2598013",
        "tgn:7002659",
        "tgn:1000001",
        "tgn:7012149",
        "tgn:7029392"
    ],
    "tgn:id":2598013,
    "tgn:name":"Prescott Creek",
    "tgn:placetype":[
        "aat:300008706"
    ]
},
  "bbox": [],
  "geometry": {"coordinates":[-87.15,33.6333],"type":"Point"}
}