{
  "id": 2276379,
  "type": "Feature",
  "properties": {
    "tgn:hierarchy":[
        "tgn:2276379",
        "tgn:1000001",
        "tgn:7012149",
        "tgn:2000491",
        "tgn:7007250",
        "tgn:7029392"
    ],
    "tgn:id":2276379,
    "tgn:name":"Dave Ingram Creek",
    "tgn:placetype":[
        "aat:300008706"
    ]
},
  "bbox": [],
  "geometry": {"coordinates":[-115.1667,46.9667],"type":"Point"}
}