{
  "id": 7457206,
  "type": "Feature",
  "properties": {
    "tgn:hierarchy":[
        "tgn:7457206",
        "tgn:7002448",
        "tgn:1000003",
        "tgn:7019199",
        "tgn:7008591",
        "tgn:7029392"
    ],
    "tgn:id":7457206,
    "tgn:name:en":"Mount Norris",
    "tgn:placetype":[
        "aat:300008347"
    ]
},
  "bbox": [],
  "geometry": {"coordinates":[-6.466667,54.233333],"type":"Point"}
}