{
  "id": 7220717,
  "type": "Feature",
  "properties": {
    "tgn:hierarchy":[
        "tgn:7220717",
        "tgn:7011164",
        "tgn:7002674",
        "tgn:1000003",
        "tgn:1000074",
        "tgn:7029392"
    ],
    "tgn:id":7220717,
    "tgn:name":"Kal\u00e1mion",
    "tgn:placetype":[
        "aat:300008347"
    ]
},
  "bbox": [],
  "geometry": {"coordinates":[26.966944,37.767778],"type":"Point"}
}