{
  "id": 2744415,
  "type": "Feature",
  "properties": {
    "tgn:hierarchy":[
        "tgn:2744415",
        "tgn:1000001",
        "tgn:7012149",
        "tgn:7007158",
        "tgn:2000242",
        "tgn:7029392"
    ],
    "tgn:id":2744415,
    "tgn:name":"Vertrees Reservoir",
    "tgn:placetype":[
        "aat:300006191"
    ]
},
  "bbox": [],
  "geometry": {"coordinates":[-104.4333,38.0333],"type":"Point"}
}