{
  "id": 2026178,
  "type": "Feature",
  "properties": {
    "tgn:hierarchy":[
        "tgn:2026178",
        "tgn:1000001",
        "tgn:7012149",
        "tgn:2000473",
        "tgn:7007250",
        "tgn:7029392"
    ],
    "tgn:id":2026178,
    "tgn:name":"Teton",
    "tgn:placetype":[
        "aat:300008347"
    ]
},
  "bbox": [],
  "geometry": {"coordinates":[-111.6667,43.8833],"type":"Point"}
}