<<<<<<< HEAD
{
  "id": 7379566,
  "type": "Feature",
  "properties": {
    "tgn:hierarchy":[
        "tgn:7379566",
        "tgn:1000001",
        "tgn:1001906",
        "tgn:7005560",
        "tgn:7029392"
    ],
    "tgn:id":7379566,
    "tgn:name":"Milpas Viejas",
    "tgn:placetype":[
        "aat:300008347"
    ]
},
  "bbox": [],
  "geometry": {"coordinates":[-105.473611,22.365833],"type":"Point"}
}
=======
{"geometry":{"type":"Point","coordinates":[-105.473611,22.365833]},"type":"Feature","properties":{"hierarchy":["tgn:7379566","tgn:1000001","tgn:1001906","tgn:7005560","tgn:7029392"],"placetype":["aat:300008347"],"id":7379566,"name:xx":"Milpas Viejas"}}
>>>>>>> 03f74aca74312dbeaf24d7e61306dd6a786dc3d0
