{
  "id": 2655473,
  "type": "Feature",
  "properties": {
    "tgn:hierarchy":[
        "tgn:2655473",
        "tgn:1000001",
        "tgn:7012149",
        "tgn:1002918",
        "tgn:7007252",
        "tgn:7029392"
    ],
    "tgn:id":2655473,
    "tgn:name":"Sharp Ditch",
    "tgn:placetype":[
        "aat:300006075"
    ]
},
  "bbox": [],
  "geometry": {"coordinates":[-86.7833,41.1667],"type":"Point"}
}