<<<<<<< HEAD
{
  "id": 2765187,
  "type": "Feature",
  "properties": {
    "tgn:hierarchy":[
        "tgn:2765187",
        "tgn:1000001",
        "tgn:7012149",
        "tgn:2001162",
        "tgn:7007522",
        "tgn:7029392"
    ],
    "tgn:id":2765187,
    "tgn:name":"Whistler",
    "tgn:placetype":[
        "aat:300008347"
    ]
},
  "bbox": [],
  "geometry": {"coordinates":[-88.8,31.6833],"type":"Point"}
}
=======
{"geometry":{"type":"Point","coordinates":[-88.800000,31.683300]},"type":"Feature","properties":{"hierarchy":["tgn:2765187","tgn:1000001","tgn:7012149","tgn:2001162","tgn:7007522","tgn:7029392"],"placetype":["aat:300008347"],"id":2765187,"name:xx":"Whistler"}}
>>>>>>> 03f74aca74312dbeaf24d7e61306dd6a786dc3d0
