{
  "id": 2457134,
  "type": "Feature",
  "properties": {
    "tgn:hierarchy":[
        "tgn:2457134",
        "tgn:1000001",
        "tgn:7012149",
        "tgn:7016021",
        "tgn:7007568",
        "tgn:7029392"
    ],
    "tgn:id":2457134,
    "tgn:name":"Little Lake",
    "tgn:placetype":[
        "aat:300008680"
    ]
},
  "bbox": [],
  "geometry": {"coordinates":[-75.1333,44.35],"type":"Point"}
}