{
  "id": 2782228,
  "type": "Feature",
  "properties": {
    "tgn:hierarchy":[
        "tgn:2782228",
        "tgn:1000001",
        "tgn:7012149",
        "tgn:1002964",
        "tgn:7007706",
        "tgn:7029392"
    ],
    "tgn:id":2782228,
    "tgn:name":"Woodview Park",
    "tgn:placetype":[
        "aat:300008347"
    ]
},
  "bbox": [],
  "geometry": {"coordinates":[-83.35,40.25],"type":"Point"}
}