{
  "id": 7287130,
  "type": "Feature",
  "properties": {
    "tgn:hierarchy":[
        "tgn:7287130",
        "tgn:1001623",
        "tgn:1000049",
        "tgn:1000002",
        "tgn:7029392"
    ],
    "tgn:id":7287130,
    "tgn:name":"Gemelas, Cerro",
    "tgn:placetype":[
        "aat:300008795"
    ]
},
  "bbox": [],
  "geometry": {"coordinates":[-72.533333,-45.683333],"type":"Point"}
}