{
  "id": 2681858,
  "type": "Feature",
  "properties": {
    "tgn:hierarchy":[
        "tgn:2681858",
        "tgn:1000001",
        "tgn:1002260",
        "tgn:7012149",
        "tgn:7007920",
        "tgn:7029392"
    ],
    "tgn:id":2681858,
    "tgn:name":"South Shaser Creek",
    "tgn:placetype":[
        "aat:300008706"
    ]
},
  "bbox": [],
  "geometry": {"coordinates":[-120.6667,47.35],"type":"Point"}
}