{
  "id": 7508937,
  "type": "Feature",
  "properties": {
    "tgn:hierarchy":[
        "tgn:7508937",
        "tgn:1009227",
        "tgn:1000226",
        "tgn:1000006",
        "tgn:7016850",
        "tgn:7029392"
    ],
    "tgn:id":7508937,
    "tgn:name:en":"Tiroroa",
    "tgn:placetype":[
        "aat:300008347"
    ]
},
  "bbox": [],
  "geometry": {"coordinates":[171.75,-41.833333],"type":"Point"}
}