{
  "id": 2118365,
  "type": "Feature",
  "properties": {
    "tgn:hierarchy":[
        "tgn:2118365",
        "tgn:1000001",
        "tgn:2002256",
        "tgn:7012149",
        "tgn:7013961",
        "tgn:7029392"
    ],
    "tgn:id":2118365,
    "tgn:name":"Gillespie",
    "tgn:placetype":[
        "aat:300387016"
    ]
},
  "bbox": [],
  "geometry": {"coordinates":[-80.6167,38.65],"type":"Point"}
}