{
  "id": 7527084,
  "type": "Feature",
  "properties": {
    "tgn:hierarchy":[
        "tgn:7527084",
        "tgn:7001242",
        "tgn:1001075",
        "tgn:7016833",
        "tgn:7029392"
    ],
    "tgn:id":7527084,
    "tgn:name:en":"Yusri Canal",
    "tgn:placetype":[
        "aat:300006075"
    ]
},
  "bbox": [],
  "geometry": {"coordinates":[30.066667,31.066667],"type":"Point"}
}