{
  "id": 2467333,
  "type": "Feature",
  "properties": {
    "tgn:hierarchy":[
        "tgn:2467333",
        "tgn:1000001",
        "tgn:7012149",
        "tgn:1002839",
        "tgn:7007826",
        "tgn:7029392"
    ],
    "tgn:id":2467333,
    "tgn:name":"Long Glade Lake",
    "tgn:placetype":[
        "aat:300006191"
    ]
},
  "bbox": [],
  "geometry": {"coordinates":[-94.65,32.3167],"type":"Point"}
}