{
  "id": 1082716,
  "type": "Feature",
  "properties": {
    "tgn:hierarchy":[
        "tgn:1082716",
        "tgn:7000317",
        "tgn:1000004",
        "tgn:7016831",
        "tgn:1000128",
        "tgn:7029392"
    ],
    "tgn:id":1082716,
    "tgn:name":"Chabang Tiga",
    "tgn:placetype":[
        "aat:300008347"
    ]
},
  "bbox": [],
  "geometry": {"coordinates":[103.1333,5.3167],"type":"Point"}
}