{
  "id": 7527524,
  "type": "Feature",
  "properties": {
    "tgn:hierarchy":[
        "tgn:7527524",
        "tgn:7001242",
        "tgn:7016833",
        "tgn:1001418",
        "tgn:7029392"
    ],
    "tgn:id":7527524,
    "tgn:name:en":"Z\u0101wiyat al \u1e28aw\u0101lah",
    "tgn:placetype":[
        "aat:300387007"
    ]
},
  "bbox": [],
  "geometry": {"coordinates":[27.479162,31.195724],"type":"Point"}
}