{
  "id": 1079073,
  "type": "Feature",
  "properties": {
    "tgn:hierarchy":[
        "tgn:1079073",
        "tgn:1000004",
        "tgn:1001528",
        "tgn:7000231",
        "tgn:7029392"
    ],
    "tgn:id":1079073,
    "tgn:name":"Eyv\u0101nak\u012b",
    "tgn:placetype":[
        "aat:300008347"
    ]
},
  "bbox": [],
  "geometry": {"coordinates":[52.0667,35.35],"type":"Point"}
}