{
  "id": 7046429,
  "type": "Feature",
  "properties": {
    "tgn:hierarchy":[
        "tgn:7046429",
        "tgn:7003170",
        "tgn:1000003",
        "tgn:7003125",
        "tgn:1000080",
        "tgn:7029392"
    ],
    "tgn:id":7046429,
    "tgn:name":"Casia Grande",
    "tgn:placetype":[
        "aat:300008795"
    ]
},
  "bbox": [],
  "geometry": {"coordinates":[12.733333,43.45],"type":"Point"}
}