{
  "id": 7415514,
  "type": "Feature",
  "properties": {
    "tgn:hierarchy":[
        "tgn:7415514",
        "tgn:1000001",
        "tgn:7005591",
        "tgn:7005560",
        "tgn:7029392"
    ],
    "tgn:id":7415514,
    "tgn:name:es":"Santo Tom\u00e1s Mazaltepec",
    "tgn:placetype":[
        "aat:300008347"
    ]
},
  "bbox": [],
  "geometry": {"coordinates":[-96.866667,17.15],"type":"Point"}
}