{
  "id": 7056223,
  "type": "Feature",
  "properties": {
    "tgn:hierarchy":[
        "tgn:7056223",
        "tgn:7015163",
        "tgn:1000003",
        "tgn:7003121",
        "tgn:1000080",
        "tgn:7029392"
    ],
    "tgn:id":7056223,
    "tgn:name":"Pischinaris, Monte",
    "tgn:placetype":[
        "aat:300008795"
    ]
},
  "bbox": [],
  "geometry": {"coordinates":[8.378611,40.533889],"type":"Point"}
}