{
  "id": 7502034,
  "type": "Feature",
  "properties": {
    "tgn:hierarchy":[
        "tgn:7502034",
        "tgn:1000004",
        "tgn:7490934",
        "tgn:1000141",
        "tgn:7029392"
    ],
    "tgn:id":7502034,
    "tgn:name":"Pizitou Pi",
    "tgn:placetype":[
        "aat:300008680"
    ]
},
  "bbox": [],
  "geometry": {"coordinates":[120.314722,22.997778],"type":"Point"}
}