{
  "id": 7062224,
  "type": "Feature",
  "properties": {
    "tgn:hierarchy":[
        "tgn:7062224",
        "tgn:1000003",
        "tgn:7003685",
        "tgn:7000084",
        "tgn:7029392"
    ],
    "tgn:id":7062224,
    "tgn:name":"Auerbach",
    "tgn:placetype":[
        "aat:300008347"
    ]
},
  "bbox": [],
  "geometry": {"coordinates":[12.916667,50.683333],"type":"Point"}
}