<<<<<<< HEAD
{
  "id": 2252001,
  "type": "Feature",
  "properties": {
    "tgn:hierarchy":[
        "tgn:2252001",
        "tgn:1000001",
        "tgn:7012149",
        "tgn:2000205",
        "tgn:7007158",
        "tgn:7029392"
    ],
    "tgn:id":2252001,
    "tgn:name":"Concord Hill",
    "tgn:placetype":[
        "aat:300008798"
    ]
},
  "bbox": [],
  "geometry": {"coordinates":[-105.35,38.1],"type":"Point"}
}
=======
{"geometry":{"type":"Point","coordinates":[-105.350000,38.100000]},"type":"Feature","properties":{"hierarchy":["tgn:2252001","tgn:1000001","tgn:7012149","tgn:2000205","tgn:7007158","tgn:7029392"],"placetype":["aat:300008798"],"id":2252001,"name:xx":"Concord Hill"}}
>>>>>>> 03f74aca74312dbeaf24d7e61306dd6a786dc3d0
