{
  "id": 7505147,
  "type": "Feature",
  "properties": {
    "tgn:hierarchy":[
        "tgn:7505147",
        "tgn:1009227",
        "tgn:1000226",
        "tgn:7016822",
        "tgn:1000006",
        "tgn:7029392"
    ],
    "tgn:id":7505147,
    "tgn:name:en":"Monowai Island",
    "tgn:placetype":[
        "aat:300008791"
    ]
},
  "bbox": [],
  "geometry": {"coordinates":[169.048333,-52.571667],"type":"Point"}
}