<<<<<<< HEAD
{
  "id": 7478227,
  "type": "Feature",
  "properties": {
    "tgn:hierarchy":[
        "tgn:7478227",
        "tgn:1000004",
        "tgn:7001013",
        "tgn:1000141",
        "tgn:7029392"
    ],
    "tgn:id":7478227,
    "tgn:name":"Dingbu",
    "tgn:placetype":[
        "aat:300008347"
    ]
},
  "bbox": [],
  "geometry": {"coordinates":[121.216124,25.080231],"type":"Point"}
}
=======
{"geometry":{"type":"Point","coordinates":[121.216124,25.080231]},"type":"Feature","properties":{"hierarchy":["tgn:7478227","tgn:1000004","tgn:7001013","tgn:1000141","tgn:7029392"],"placetype":["aat:300008347"],"id":7478227,"name:xx":"Dingbu"}}
>>>>>>> 03f74aca74312dbeaf24d7e61306dd6a786dc3d0
