{
  "id": 2158450,
  "type": "Feature",
  "properties": {
    "tgn:hierarchy":[
        "tgn:2158450",
        "tgn:1000001",
        "tgn:7012149",
        "tgn:7007523",
        "tgn:7029392"
    ],
    "tgn:id":2158450,
    "tgn:name":"Beaverdam Creek",
    "tgn:placetype":[
        "aat:300008706"
    ]
},
  "bbox": [],
  "geometry": {"coordinates":[-90.65,36.75],"type":"Point"}
}