{
  "id": 2723320,
  "type": "Feature",
  "properties": {
    "tgn:hierarchy":[
        "tgn:2723320",
        "tgn:1000001",
        "tgn:2001943",
        "tgn:7012149",
        "tgn:7007826",
        "tgn:7029392"
    ],
    "tgn:id":2723320,
    "tgn:name":"Tobacco Tank",
    "tgn:placetype":[
        "aat:300006191"
    ]
},
  "bbox": [],
  "geometry": {"coordinates":[-101.55,32.6833],"type":"Point"}
}