{
  "id": 7569071,
  "type": "Feature",
  "properties": {
    "tgn:hierarchy":[
        "tgn:7569071",
        "tgn:1001828",
        "tgn:1000004",
        "tgn:7000198",
        "tgn:7029392"
    ],
    "tgn:id":7569071,
    "tgn:name:en":"Masjidpur",
    "tgn:placetype":[
        "aat:300008347"
    ]
},
  "bbox": [],
  "geometry": {"coordinates":[78.341389,17.465],"type":"Point"}
}