{
  "id": 7593601,
  "type": "Feature",
  "properties": {
    "tgn:hierarchy":[
        "tgn:7593601",
        "tgn:1000001",
        "tgn:7005605",
        "tgn:7029392"
    ],
    "tgn:id":7593601,
    "tgn:name":"Saint Mary Cayon",
    "tgn:placetype":[
        "aat:300387064",
        "aat:300387092"
    ]
},
  "bbox": [],
  "geometry": {"coordinates":[-62.733,17.35],"type":"Point"}
}