{
  "id": 7241228,
  "type": "Feature",
  "properties": {
    "tgn:hierarchy":[
        "tgn:7241228",
        "tgn:7007877",
        "tgn:1000003",
        "tgn:1000063",
        "tgn:4012014",
        "tgn:7029392"
    ],
    "tgn:id":7241228,
    "tgn:name":"Le Ch\u00eane",
    "tgn:placetype":[
        "aat:300008347"
    ]
},
  "bbox": [],
  "geometry": {"coordinates":[4.316667,50.35],"type":"Point"}
}