{
  "id": 2787197,
  "type": "Feature",
  "properties": {
    "tgn:hierarchy":[
        "tgn:2787197",
        "tgn:1000001",
        "tgn:7012149",
        "tgn:7007253",
        "tgn:7029392"
    ],
    "tgn:id":2787197,
    "tgn:name":"Zoar Creek",
    "tgn:placetype":[
        "aat:300008706"
    ]
},
  "bbox": [],
  "geometry": {"coordinates":[-95.85,43.3667],"type":"Point"}
}