{
  "id": 2767720,
  "type": "Feature",
  "properties": {
    "tgn:hierarchy":[
        "tgn:2767720",
        "tgn:7014651",
        "tgn:1000001",
        "tgn:7012149",
        "tgn:7007516",
        "tgn:7029392"
    ],
    "tgn:id":2767720,
    "tgn:name":"Whitehall Creek",
    "tgn:placetype":[
        "aat:300008706"
    ]
},
  "bbox": [],
  "geometry": {"coordinates":[-76.45,39.0333],"type":"Point"}
}