{
  "id": 2299086,
  "type": "Feature",
  "properties": {
    "tgn:hierarchy":[
        "tgn:2299086",
        "tgn:1000001",
        "tgn:7012149",
        "tgn:2000609",
        "tgn:7007253",
        "tgn:7029392"
    ],
    "tgn:id":2299086,
    "tgn:name":"Duck Creek",
    "tgn:placetype":[
        "aat:300008706"
    ]
},
  "bbox": [],
  "geometry": {"coordinates":[-90.45,42.1833],"type":"Point"}
}