{
  "id": 2459587,
  "type": "Feature",
  "properties": {
    "tgn:hierarchy":[
        "tgn:2459587",
        "tgn:1000001",
        "tgn:2002369",
        "tgn:7012149",
        "tgn:7007923",
        "tgn:7029392"
    ],
    "tgn:id":2459587,
    "tgn:name":"Little Rat Creek",
    "tgn:placetype":[
        "aat:300008706"
    ]
},
  "bbox": [],
  "geometry": {"coordinates":[-105.0667,43.25],"type":"Point"}
}