<<<<<<< HEAD
{
  "id": 2403769,
  "type": "Feature",
  "properties": {
    "tgn:hierarchy":[
        "tgn:2403769",
        "tgn:1000001",
        "tgn:7006451",
        "tgn:2000092",
        "tgn:7012149",
        "tgn:7029392"
    ],
    "tgn:id":2403769,
    "tgn:name":"Howard Seep",
    "tgn:placetype":[
        "aat:300008697"
    ]
},
  "bbox": [],
  "geometry": {"coordinates":[-111.7333,35.45],"type":"Point"}
}
=======
{"geometry":{"type":"Point","coordinates":[-111.733300,35.450000]},"type":"Feature","properties":{"hierarchy":["tgn:2403769","tgn:1000001","tgn:7006451","tgn:2000092","tgn:7012149","tgn:7029392"],"placetype":["aat:300008697"],"id":2403769,"name:xx":"Howard Seep"}}
>>>>>>> 03f74aca74312dbeaf24d7e61306dd6a786dc3d0
