<<<<<<< HEAD
{
  "id": 7020686,
  "type": "Feature",
  "properties": {
    "tgn:hierarchy":[
        "tgn:7020686",
        "tgn:1000001",
        "tgn:7012149",
        "tgn:7029392"
    ],
    "tgn:id":7020686,
    "tgn:name":"Eleven Point River",
    "tgn:placetype":[
        "aat:300008707"
    ]
},
  "bbox": [],
  "geometry": {"coordinates":[-91.9833,37.0167],"type":"Point"}
}
=======
{"geometry":{"type":"Point","coordinates":[-91.983300,37.016700]},"type":"Feature","properties":{"hierarchy":["tgn:7020686","tgn:1000001","tgn:7012149","tgn:7029392"],"placetype":["aat:300008707"],"id":7020686,"name:xx":"Eleven Point River"}}
>>>>>>> 03f74aca74312dbeaf24d7e61306dd6a786dc3d0
