{
  "id": 7244515,
  "type": "Feature",
  "properties": {
    "tgn:hierarchy":[
        "tgn:7244515",
        "tgn:7003457",
        "tgn:1000003",
        "tgn:1000063",
        "tgn:7018236",
        "tgn:7029392"
    ],
    "tgn:id":7244515,
    "tgn:name":"Kwaadhoek",
    "tgn:placetype":[
        "aat:300008347"
    ]
},
  "bbox": [],
  "geometry": {"coordinates":[4.033333,51.166667],"type":"Point"}
}