{
  "id": 2776942,
  "type": "Feature",
  "properties": {
    "tgn:hierarchy":[
        "tgn:2776942",
        "tgn:1000001",
        "tgn:7012149",
        "tgn:2002381",
        "tgn:7007923",
        "tgn:7029392"
    ],
    "tgn:id":2776942,
    "tgn:name":"Windy Canyon Creek",
    "tgn:placetype":[
        "aat:300008706"
    ]
},
  "bbox": [],
  "geometry": {"coordinates":[-107.2167,44.75],"type":"Point"}
}