<<<<<<< HEAD
{
  "id": 2402413,
  "type": "Feature",
  "properties": {
    "tgn:hierarchy":[
        "tgn:2402413",
        "tgn:1000001",
        "tgn:7012149",
        "tgn:2001254",
        "tgn:7007523",
        "tgn:7029392"
    ],
    "tgn:id":2402413,
    "tgn:name":"Horton Town",
    "tgn:placetype":[
        "aat:300008347"
    ]
},
  "bbox": [],
  "geometry": {"coordinates":[-90.9167,37.7667],"type":"Point"}
}
=======
{"geometry":{"type":"Point","coordinates":[-90.916700,37.766700]},"type":"Feature","properties":{"hierarchy":["tgn:2402413","tgn:1000001","tgn:7012149","tgn:2001254","tgn:7007523","tgn:7029392"],"placetype":["aat:300008347"],"id":2402413,"name:xx":"Horton Town"}}
>>>>>>> 03f74aca74312dbeaf24d7e61306dd6a786dc3d0
