{
  "id": 2402413,
  "type": "Feature",
  "properties": {
    "tgn:hierarchy":[
        "tgn:2402413",
        "tgn:1000001",
        "tgn:7012149",
        "tgn:2001254",
        "tgn:7007523",
        "tgn:7029392"
    ],
    "tgn:id":2402413,
    "tgn:name":"Horton Town",
    "tgn:placetype":[
        "aat:300008347"
    ]
},
  "bbox": [],
  "geometry": {"coordinates":[-90.9167,37.7667],"type":"Point"}
}