{
  "id": 2571387,
  "type": "Feature",
  "properties": {
    "tgn:hierarchy":[
        "tgn:2571387",
        "tgn:1000001",
        "tgn:7012149",
        "tgn:7013941",
        "tgn:7007568",
        "tgn:7029392"
    ],
    "tgn:id":2571387,
    "tgn:name":"Paul Smiths Easy Street",
    "tgn:placetype":[
        "aat:300008347"
    ]
},
  "bbox": [],
  "geometry": {"coordinates":[-74.2167,44.4333],"type":"Point"}
}