{
  "id": 2456574,
  "type": "Feature",
  "properties": {
    "tgn:hierarchy":[
        "tgn:2456574",
        "tgn:1000001",
        "tgn:7012149",
        "tgn:2000986",
        "tgn:7007520",
        "tgn:7029392"
    ],
    "tgn:id":2456574,
    "tgn:name":"Little Iron River",
    "tgn:placetype":[
        "aat:300008707"
    ]
},
  "bbox": [],
  "geometry": {"coordinates":[-89.7333,46.7333],"type":"Point"}
}