<<<<<<< HEAD
{
  "id": 2407528,
  "type": "Feature",
  "properties": {
    "tgn:hierarchy":[
        "tgn:2407528",
        "tgn:1000001",
        "tgn:7012149",
        "tgn:7021516",
        "tgn:7007706",
        "tgn:7029392"
    ],
    "tgn:id":2407528,
    "tgn:name":"Huntsburg",
    "tgn:placetype":[
        "aat:300008347"
    ]
},
  "bbox": [],
  "geometry": {"coordinates":[-81.05,41.5333],"type":"Point"}
}
=======
{"geometry":{"type":"Point","coordinates":[-81.050000,41.533300]},"type":"Feature","properties":{"hierarchy":["tgn:2407528","tgn:1000001","tgn:7012149","tgn:7021516","tgn:7007706","tgn:7029392"],"placetype":["aat:300008347"],"id":2407528,"name:xx":"Huntsburg"}}
>>>>>>> 03f74aca74312dbeaf24d7e61306dd6a786dc3d0
