<<<<<<< HEAD
{
  "id": 2251859,
  "type": "Feature",
  "properties": {
    "tgn:hierarchy":[
        "tgn:2251859",
        "tgn:1000001",
        "tgn:7012149",
        "tgn:2002371",
        "tgn:7007923",
        "tgn:7029392"
    ],
    "tgn:id":2251859,
    "tgn:name":"Conant Creek",
    "tgn:placetype":[
        "aat:300008706"
    ]
},
  "bbox": [],
  "geometry": {"coordinates":[-108.0333,42.7833],"type":"Point"}
}
=======
{"geometry":{"type":"Point","coordinates":[-108.033300,42.783300]},"type":"Feature","properties":{"hierarchy":["tgn:2251859","tgn:1000001","tgn:7012149","tgn:2002371","tgn:7007923","tgn:7029392"],"placetype":["aat:300008706"],"id":2251859,"name:xx":"Conant Creek"}}
>>>>>>> 03f74aca74312dbeaf24d7e61306dd6a786dc3d0
