{
  "id": 2251859,
  "type": "Feature",
  "properties": {
    "tgn:hierarchy":[
        "tgn:2251859",
        "tgn:1000001",
        "tgn:7012149",
        "tgn:2002371",
        "tgn:7007923",
        "tgn:7029392"
    ],
    "tgn:id":2251859,
    "tgn:name":"Conant Creek",
    "tgn:placetype":[
        "aat:300008706"
    ]
},
  "bbox": [],
  "geometry": {"coordinates":[-108.0333,42.7833],"type":"Point"}
}