{
  "id": 7295523,
  "type": "Feature",
  "properties": {
    "tgn:hierarchy":[
        "tgn:7295523",
        "tgn:7002826",
        "tgn:7001158",
        "tgn:1000003",
        "tgn:1000095",
        "tgn:7029392"
    ],
    "tgn:id":7295523,
    "tgn:name":"Villanueva de las Manzanas",
    "tgn:placetype":[
        "aat:300008347"
    ]
},
  "bbox": [],
  "geometry": {"coordinates":[-5.483333,42.466667],"type":"Point"}
}