{
  "id": 7416885,
  "type": "Feature",
  "properties": {
    "tgn:hierarchy":[
        "tgn:7416885",
        "tgn:1000001",
        "tgn:7005591",
        "tgn:7005560",
        "tgn:7029392"
    ],
    "tgn:id":7416885,
    "tgn:name:es":"El Porvenir Ballesteros",
    "tgn:placetype":[
        "aat:300008347"
    ]
},
  "bbox": [],
  "geometry": {"coordinates":[-96.914167,16.069167],"type":"Point"}
}