{
  "id": 7529010,
  "type": "Feature",
  "properties": {
    "tgn:hierarchy":[
        "tgn:7529010",
        "tgn:7001242",
        "tgn:7016833",
        "tgn:1001110",
        "tgn:7029392"
    ],
    "tgn:id":7529010,
    "tgn:name:en":"Umm Risays, Jabal",
    "tgn:placetype":[
        "aat:300008795"
    ]
},
  "bbox": [],
  "geometry": {"coordinates":[32.242785,29.533837],"type":"Point"}
}