{
  "id": 2134072,
  "type": "Feature",
  "properties": {
    "tgn:hierarchy":[
        "tgn:2134072",
        "tgn:7006450",
        "tgn:1000001",
        "tgn:7012149",
        "tgn:2000082",
        "tgn:7029392"
    ],
    "tgn:id":2134072,
    "tgn:name":"Anguilla Bay",
    "tgn:placetype":[
        "aat:300132316"
    ]
},
  "bbox": [],
  "geometry": {"coordinates":[-133.5667,55.65],"type":"Point"}
}