{
  "id": 7197503,
  "type": "Feature",
  "properties": {
    "tgn:hierarchy":[
        "tgn:7197503",
        "tgn:7000096",
        "tgn:1000003",
        "tgn:7000084",
        "tgn:7029392"
    ],
    "tgn:id":7197503,
    "tgn:name":"Dannenfelde",
    "tgn:placetype":[
        "aat:300008347"
    ]
},
  "bbox": [],
  "geometry": {"coordinates":[12.616667,52.95],"type":"Point"}
}