{
  "id": 7217980,
  "type": "Feature",
  "properties": {
    "tgn:hierarchy":[
        "tgn:7217980",
        "tgn:7002690",
        "tgn:7012056",
        "tgn:1000003",
        "tgn:1000074",
        "tgn:7029392"
    ],
    "tgn:id":7217980,
    "tgn:name":"Angirov\u00f3lion Yeoryioupol\u00e9os",
    "tgn:placetype":[
        "aat:300386968"
    ]
},
  "bbox": [],
  "geometry": {"coordinates":[24.25,35.366667],"type":"Point"}
}