{
  "id": 2681369,
  "type": "Feature",
  "properties": {
    "tgn:hierarchy":[
        "tgn:2681369",
        "tgn:1000001",
        "tgn:7012149",
        "tgn:7029392"
    ],
    "tgn:id":2681369,
    "tgn:name":"South Pine River Lateral",
    "tgn:placetype":[
        "aat:300006075"
    ]
},
  "bbox": [],
  "geometry": {"coordinates":[-107.5167,37.0167],"type":"Point"}
}