{
  "id": 7418910,
  "type": "Feature",
  "properties": {
    "tgn:hierarchy":[
        "tgn:7418910",
        "tgn:7005584",
        "tgn:1000001",
        "tgn:7005560",
        "tgn:7029392"
    ],
    "tgn:id":7418910,
    "tgn:name":"La Yerbabuena",
    "tgn:placetype":[
        "aat:300008347"
    ]
},
  "bbox": [],
  "geometry": {"coordinates":[-100.375,21.031111],"type":"Point"}
}