{
  "id": 7228992,
  "type": "Feature",
  "properties": {
    "tgn:hierarchy":[
        "tgn:7228992",
        "tgn:7002707",
        "tgn:7002705",
        "tgn:1000003",
        "tgn:1000074",
        "tgn:7029392"
    ],
    "tgn:id":7228992,
    "tgn:name":"Leptokary\u00e1",
    "tgn:placetype":[
        "aat:300008347"
    ]
},
  "bbox": [],
  "geometry": {"coordinates":[20.915556,39.825278],"type":"Point"}
}