{
  "id": 2353938,
  "type": "Feature",
  "properties": {
    "tgn:hierarchy":[
        "tgn:2353938",
        "tgn:1000001",
        "tgn:7012149",
        "tgn:2000183",
        "tgn:7007157",
        "tgn:7029392"
    ],
    "tgn:id":2353938,
    "tgn:name":"Goldbug Mine",
    "tgn:placetype":[
        "aat:300000390"
    ]
},
  "bbox": [],
  "geometry": {"coordinates":[-117.15,36.0167],"type":"Point"}
}