{
  "id": 2632785,
  "type": "Feature",
  "properties": {
    "tgn:hierarchy":[
        "tgn:2632785",
        "tgn:1000001",
        "tgn:2002313",
        "tgn:7012149",
        "tgn:7007922",
        "tgn:7029392"
    ],
    "tgn:id":2632785,
    "tgn:name":"Ruby Lake",
    "tgn:placetype":[
        "aat:300008680"
    ]
},
  "bbox": [],
  "geometry": {"coordinates":[-91.45,45.2667],"type":"Point"}
}