{
  "id": 7420775,
  "type": "Feature",
  "properties": {
    "tgn:hierarchy":[
        "tgn:7420775",
        "tgn:1000001",
        "tgn:7005589",
        "tgn:7005560",
        "tgn:7029392"
    ],
    "tgn:id":7420775,
    "tgn:name:es":"Estaci\u00f3n Lobos",
    "tgn:placetype":[
        "aat:300007783"
    ]
},
  "bbox": [],
  "geometry": {"coordinates":[-99.998611,25.734167],"type":"Point"}
}