{
  "id": 2164539,
  "type": "Feature",
  "properties": {
    "tgn:hierarchy":[
        "tgn:2164539",
        "tgn:1000001",
        "tgn:2000198",
        "tgn:7012149",
        "tgn:7007158",
        "tgn:7029392"
    ],
    "tgn:id":2164539,
    "tgn:name":"Berry Ridge",
    "tgn:placetype":[
        "aat:300266640"
    ]
},
  "bbox": [],
  "geometry": {"coordinates":[-105.35,40.1667],"type":"Point"}
}