{
  "id": 7369878,
  "type": "Feature",
  "properties": {
    "tgn:hierarchy":[
        "tgn:7369878",
        "tgn:1000001",
        "tgn:7005599",
        "tgn:7005560",
        "tgn:7029392"
    ],
    "tgn:id":7369878,
    "tgn:name":"Huasmochite",
    "tgn:placetype":[
        "aat:300008347"
    ]
},
  "bbox": [],
  "geometry": {"coordinates":[-95.933333,18.25],"type":"Point"}
}