{
  "id": 2283583,
  "type": "Feature",
  "properties": {
    "tgn:hierarchy":[
        "tgn:2283583",
        "tgn:1000001",
        "tgn:7012149",
        "tgn:7007158",
        "tgn:7029392"
    ],
    "tgn:id":2283583,
    "tgn:name":"Demaree Canyon",
    "tgn:placetype":[
        "aat:300008761"
    ]
},
  "bbox": [],
  "geometry": {"coordinates":[-108.85,39.4667],"type":"Point"}
}