{
  "id": 2294478,
  "type": "Feature",
  "properties": {
    "tgn:hierarchy":[
        "tgn:2294478",
        "tgn:1000001",
        "tgn:7012149",
        "tgn:2000423",
        "tgn:7007248",
        "tgn:7029392"
    ],
    "tgn:id":2294478,
    "tgn:name":"Downstream Twin Pond",
    "tgn:placetype":[
        "aat:300006191"
    ]
},
  "bbox": [],
  "geometry": {"coordinates":[-82.1667,31.9833],"type":"Point"}
}