<<<<<<< HEAD
{
  "id": 7484352,
  "type": "Feature",
  "properties": {
    "tgn:hierarchy":[
        "tgn:7484352",
        "tgn:1000004",
        "tgn:7490934",
        "tgn:1000141",
        "tgn:7029392"
    ],
    "tgn:id":7484352,
    "tgn:name":"Ganzhai",
    "tgn:placetype":[
        "aat:300008347"
    ]
},
  "bbox": [],
  "geometry": {"coordinates":[120.44,23.385],"type":"Point"}
}
=======
{"geometry":{"type":"Point","coordinates":[120.440000,23.385000]},"type":"Feature","properties":{"hierarchy":["tgn:7484352","tgn:1000004","tgn:7490934","tgn:1000141","tgn:7029392"],"placetype":["aat:300008347"],"id":7484352,"name:xx":"Ganzhai"}}
>>>>>>> 03f74aca74312dbeaf24d7e61306dd6a786dc3d0
