{
  "id": 7254926,
  "type": "Feature",
  "properties": {
    "tgn:hierarchy":[
        "tgn:7254926",
        "tgn:7003461",
        "tgn:1000003",
        "tgn:1000063",
        "tgn:7018236",
        "tgn:7029392"
    ],
    "tgn:id":7254926,
    "tgn:name":"Tiewinkel",
    "tgn:placetype":[
        "aat:300008347"
    ]
},
  "bbox": [],
  "geometry": {"coordinates":[5.233333,50.966667],"type":"Point"}
}