{
  "id": 7258415,
  "type": "Feature",
  "properties": {
    "tgn:concordances":{
        "gn:id":"2758577"
    },
    "tgn:hierarchy":[
        "tgn:7258415",
        "tgn:7003619",
        "tgn:1000003",
        "tgn:7016845",
        "tgn:7029392"
    ],
    "tgn:id":7258415,
    "tgn:name:nl":"Boschheurne",
    "tgn:placetype":[
        "aat:300008347"
    ]
},
  "bbox": [],
  "geometry": {"coordinates":[6.466667,52.116667],"type":"Point"}
}