<<<<<<< HEAD
{
  "id": 7246492,
  "type": "Feature",
  "properties": {
    "tgn:hierarchy":[
        "tgn:7246492",
        "tgn:7003465",
        "tgn:1000003",
        "tgn:1000063",
        "tgn:4012014",
        "tgn:7029392"
    ],
    "tgn:id":7246492,
    "tgn:name":"Burnonbois",
    "tgn:placetype":[
        "aat:300008863"
    ]
},
  "bbox": [],
  "geometry": {"coordinates":[5.183333,49.966667],"type":"Point"}
}
=======
{"geometry":{"type":"Point","coordinates":[5.183333,49.966667]},"type":"Feature","properties":{"hierarchy":["tgn:7246492","tgn:7003465","tgn:1000003","tgn:1000063","tgn:4012014","tgn:7029392"],"placetype":["aat:300008863"],"id":7246492,"name:xx":"Burnonbois"}}
>>>>>>> 03f74aca74312dbeaf24d7e61306dd6a786dc3d0
