{
  "id": 7397514,
  "type": "Feature",
  "properties": {
    "tgn:hierarchy":[
        "tgn:7397514",
        "tgn:7005586",
        "tgn:1000001",
        "tgn:7005560",
        "tgn:7029392"
    ],
    "tgn:id":7397514,
    "tgn:name":"San Sebasti\u00e1n el Grande",
    "tgn:placetype":[
        "aat:300008347"
    ]
},
  "bbox": [],
  "geometry": {"coordinates":[-103.416667,20.516667],"type":"Point"}
}