{
  "id": 2269118,
  "type": "Feature",
  "properties": {
    "tgn:hierarchy":[
        "tgn:2269118",
        "tgn:1000001",
        "tgn:2001945",
        "tgn:7012149",
        "tgn:7007826",
        "tgn:7029392"
    ],
    "tgn:id":2269118,
    "tgn:name":"Croton Spring",
    "tgn:placetype":[
        "aat:300008697"
    ]
},
  "bbox": [],
  "geometry": {"coordinates":[-103.3333,29.3333],"type":"Point"}
}