{
  "id": 7145499,
  "type": "Feature",
  "properties": {
    "tgn:hierarchy":[
        "tgn:7145499",
        "tgn:1000003",
        "tgn:7003676",
        "tgn:7000084",
        "tgn:7029392"
    ],
    "tgn:id":7145499,
    "tgn:name":"Kolltes-Berg",
    "tgn:placetype":[
        "aat:300008777"
    ]
},
  "bbox": [],
  "geometry": {"coordinates":[10.65,51.716667],"type":"Point"}
}