{
  "id": 2710332,
  "type": "Feature",
  "properties": {
    "tgn:hierarchy":[
        "tgn:2710332",
        "tgn:1000001",
        "tgn:7012149",
        "tgn:2001274",
        "tgn:7007524",
        "tgn:7029392"
    ],
    "tgn:id":2710332,
    "tgn:name":"Talmadge Lake",
    "tgn:placetype":[
        "aat:300008680"
    ]
},
  "bbox": [],
  "geometry": {"coordinates":[-114.05,48.1333],"type":"Point"}
}