{
  "id": 2369517,
  "type": "Feature",
  "properties": {
    "tgn:hierarchy":[
        "tgn:2369517",
        "tgn:1000001",
        "tgn:2001417",
        "tgn:7012149",
        "tgn:7007526",
        "tgn:7029392"
    ],
    "tgn:id":2369517,
    "tgn:name":"Gunmetal Mine",
    "tgn:placetype":[
        "aat:300000390"
    ]
},
  "bbox": [],
  "geometry": {"coordinates":[-117.8833,38.3833],"type":"Point"}
}