{
  "id": 2206994,
  "type": "Feature",
  "properties": {
    "tgn:hierarchy":[
        "tgn:2206994",
        "tgn:1000001",
        "tgn:7012149",
        "tgn:2000852",
        "tgn:7007255",
        "tgn:7029392"
    ],
    "tgn:id":2206994,
    "tgn:name":"Bunch Branch",
    "tgn:placetype":[
        "aat:300008699"
    ]
},
  "bbox": [],
  "geometry": {"coordinates":[-84.15,36.6167],"type":"Point"}
}