<<<<<<< HEAD
{
  "id": 2252617,
  "type": "Feature",
  "properties": {
    "tgn:hierarchy":[
        "tgn:2252617",
        "tgn:1000001",
        "tgn:7012149",
        "tgn:2001844",
        "tgn:7007825",
        "tgn:7029392"
    ],
    "tgn:id":2252617,
    "tgn:name":"Connell Creek",
    "tgn:placetype":[
        "aat:300008706"
    ]
},
  "bbox": [],
  "geometry": {"coordinates":[-86.0167,35.8667],"type":"Point"}
}
=======
{"geometry":{"type":"Point","coordinates":[-86.016700,35.866700]},"type":"Feature","properties":{"hierarchy":["tgn:2252617","tgn:1000001","tgn:7012149","tgn:2001844","tgn:7007825","tgn:7029392"],"placetype":["aat:300008706"],"id":2252617,"name:xx":"Connell Creek"}}
>>>>>>> 03f74aca74312dbeaf24d7e61306dd6a786dc3d0
