{
  "id": 2338048,
  "type": "Feature",
  "properties": {
    "tgn:hierarchy":[
        "tgn:2338048",
        "tgn:1000001",
        "tgn:7012149",
        "tgn:1002661",
        "tgn:7007252",
        "tgn:7029392"
    ],
    "tgn:id":2338048,
    "tgn:name":"Fox Lake",
    "tgn:placetype":[
        "aat:300008680"
    ]
},
  "bbox": [],
  "geometry": {"coordinates":[-85.8667,40.5833],"type":"Point"}
}