{
  "id": 2554688,
  "type": "Feature",
  "properties": {
    "tgn:hierarchy":[
        "tgn:2554688",
        "tgn:1000001",
        "tgn:7012149",
        "tgn:2001500",
        "tgn:7007709",
        "tgn:7029392"
    ],
    "tgn:id":2554688,
    "tgn:name":"Oaks West",
    "tgn:placetype":[
        "aat:300008347"
    ]
},
  "bbox": [],
  "geometry": {"coordinates":[-79.8833,36.0333],"type":"Point"}
}