<<<<<<< HEAD
{
  "id": 7051526,
  "type": "Feature",
  "properties": {
    "tgn:hierarchy":[
        "tgn:7051526",
        "tgn:1000003",
        "tgn:7003122",
        "tgn:1000080",
        "tgn:7029392"
    ],
    "tgn:id":7051526,
    "tgn:name":"Petrazza, Piano",
    "tgn:placetype":[
        "aat:300008805"
    ]
},
  "bbox": [],
  "geometry": {"coordinates":[15.516667,38.2],"type":"Point"}
}
=======
{"geometry":{"type":"Point","coordinates":[15.516667,38.200000]},"type":"Feature","properties":{"hierarchy":["tgn:7051526","tgn:1000003","tgn:7003122","tgn:1000080","tgn:7029392"],"placetype":["aat:300008805"],"id":7051526,"name:xx":"Petrazza, Piano"}}
>>>>>>> 03f74aca74312dbeaf24d7e61306dd6a786dc3d0
