{
  "id": 2371934,
  "type": "Feature",
  "properties": {
    "tgn:hierarchy":[
        "tgn:2371934",
        "tgn:1000001",
        "tgn:7012149",
        "tgn:7007157",
        "tgn:2000184",
        "tgn:7029392"
    ],
    "tgn:id":2371934,
    "tgn:name":"Half Cabin Reservoir",
    "tgn:placetype":[
        "aat:300006191"
    ]
},
  "bbox": [],
  "geometry": {"coordinates":[-121.2333,40.6667],"type":"Point"}
}