{
  "id": 1046658,
  "type": "Feature",
  "properties": {
    "tgn:hierarchy":[
        "tgn:1046658",
        "tgn:7003127",
        "tgn:1000003",
        "tgn:7008516",
        "tgn:1000080",
        "tgn:7029392"
    ],
    "tgn:id":1046658,
    "tgn:name":"Sant'Agata Bolognese",
    "tgn:placetype":[
        "aat:300008347"
    ]
},
  "bbox": [],
  "geometry": {"coordinates":[11.133333,44.666667],"type":"Point"}
}