<<<<<<< HEAD
{
  "id": 2254038,
  "type": "Feature",
  "properties": {
    "tgn:hierarchy":[
        "tgn:2254038",
        "tgn:1000001",
        "tgn:7012149",
        "tgn:2002302",
        "tgn:7013961",
        "tgn:7029392"
    ],
    "tgn:id":2254038,
    "tgn:name":"Cool Spring Run",
    "tgn:placetype":[
        "aat:300008699"
    ]
},
  "bbox": [],
  "geometry": {"coordinates":[-81.2833,39.05],"type":"Point"}
}
=======
{"geometry":{"type":"Point","coordinates":[-81.283300,39.050000]},"type":"Feature","properties":{"hierarchy":["tgn:2254038","tgn:1000001","tgn:7012149","tgn:2002302","tgn:7013961","tgn:7029392"],"placetype":["aat:300008699"],"id":2254038,"name:xx":"Cool Spring Run"}}
>>>>>>> 03f74aca74312dbeaf24d7e61306dd6a786dc3d0
