{
  "id": 7319597,
  "type": "Feature",
  "properties": {
    "tgn:hierarchy":[
        "tgn:7319597",
        "tgn:1001708",
        "tgn:1000049",
        "tgn:1000002",
        "tgn:7029392"
    ],
    "tgn:id":7319597,
    "tgn:name":"Almendro, Portezuelo",
    "tgn:placetype":[
        "aat:300259572"
    ]
},
  "bbox": [],
  "geometry": {"coordinates":[-70.716667,-32.983333],"type":"Point"}
}