{
  "id": 1022393,
  "type": "Feature",
  "properties": {
    "tgn:hierarchy":[
        "tgn:1022393",
        "tgn:1001945",
        "tgn:1000047",
        "tgn:7002457",
        "tgn:1000002",
        "tgn:7029392"
    ],
    "tgn:id":1022393,
    "tgn:name":"Paulo de Faria",
    "tgn:placetype":[
        "aat:300008347"
    ]
},
  "bbox": [],
  "geometry": {"coordinates":[-49.3833,-20.0333],"type":"Point"}
}