{
  "id": 7380633,
  "type": "Feature",
  "properties": {
    "tgn:hierarchy":[
        "tgn:7380633",
        "tgn:1000001",
        "tgn:1001960",
        "tgn:7005560",
        "tgn:7029392"
    ],
    "tgn:id":7380633,
    "tgn:name":"Madera, Sierra de la",
    "tgn:placetype":[
        "aat:300008795"
    ]
},
  "bbox": [],
  "geometry": {"coordinates":[-108.866667,30.333333],"type":"Point"}
}