{
  "id": 2498234,
  "type": "Feature",
  "properties": {
    "tgn:hierarchy":[
        "tgn:2498234",
        "tgn:1000001",
        "tgn:7012149",
        "tgn:2000964",
        "tgn:7007520",
        "tgn:7029392"
    ],
    "tgn:id":2498234,
    "tgn:name":"Mazure Drain",
    "tgn:placetype":[
        "aat:300006075"
    ]
},
  "bbox": [],
  "geometry": {"coordinates":[-82.8667,43.8333],"type":"Point"}
}