{
  "id": 7289752,
  "type": "Feature",
  "properties": {
    "tgn:hierarchy":[
        "tgn:7289752",
        "tgn:1001708",
        "tgn:1000049",
        "tgn:1000002",
        "tgn:7029392"
    ],
    "tgn:id":7289752,
    "tgn:name":"El Carrizo, Estero",
    "tgn:placetype":[
        "aat:300266554",
        "aat:300008699"
    ]
},
  "bbox": [],
  "geometry": {"coordinates":[-70.566667,-33.333333],"type":"Point"}
}