{
  "id": 2171139,
  "type": "Feature",
  "properties": {
    "tgn:hierarchy":[
        "tgn:2171139",
        "tgn:1000001",
        "tgn:7012149",
        "tgn:2001864",
        "tgn:7007825",
        "tgn:7029392"
    ],
    "tgn:id":2171139,
    "tgn:name":"Big Spring",
    "tgn:placetype":[
        "aat:300008697"
    ]
},
  "bbox": [],
  "geometry": {"coordinates":[-86.9167,35.2333],"type":"Point"}
}