{
  "id": 2040936,
  "type": "Feature",
  "properties": {
    "tgn:hierarchy":[
        "tgn:2040936",
        "tgn:2000765",
        "tgn:1000001",
        "tgn:7012149",
        "tgn:7007255",
        "tgn:7029392"
    ],
    "tgn:id":2040936,
    "tgn:name":"Purdy",
    "tgn:placetype":[
        "aat:300008347",
        "aat:300387210"
    ]
},
  "bbox": [],
  "geometry": {"coordinates":[-85.1833,37.15],"type":"Point"}
}