{
  "id": 1124766,
  "type": "Feature",
  "properties": {
    "tgn:hierarchy":[
        "tgn:1124766",
        "tgn:1000001",
        "tgn:7012149",
        "tgn:1002357",
        "tgn:7007706",
        "tgn:7029392"
    ],
    "tgn:id":1124766,
    "tgn:name":"Huron",
    "tgn:placetype":[
        "aat:300008707"
    ]
},
  "bbox": [],
  "geometry": {"coordinates":[-82.6333,41.2833],"type":"Point"}
}