{
  "id": 7042435,
  "type": "Feature",
  "properties": {
    "tgn:hierarchy":[
        "tgn:7042435",
        "tgn:7015163",
        "tgn:1000003",
        "tgn:7003121",
        "tgn:1000080",
        "tgn:7029392"
    ],
    "tgn:id":7042435,
    "tgn:name":"Rosso, Monte",
    "tgn:placetype":[
        "aat:300008777"
    ]
},
  "bbox": [],
  "geometry": {"coordinates":[8.408889,40.66],"type":"Point"}
}