{
  "id": 7162308,
  "type": "Feature",
  "properties": {
    "tgn:hierarchy":[
        "tgn:7162308",
        "tgn:1000003",
        "tgn:7003677",
        "tgn:7000084",
        "tgn:7029392"
    ],
    "tgn:id":7162308,
    "tgn:name":"H\u00fclshorst",
    "tgn:placetype":[
        "aat:300000206"
    ]
},
  "bbox": [],
  "geometry": {"coordinates":[7.533333,52.05],"type":"Point"}
}