{
  "id": 2522277,
  "type": "Feature",
  "properties": {
    "tgn:hierarchy":[
        "tgn:2522277",
        "tgn:2001558",
        "tgn:1000001",
        "tgn:7012149",
        "tgn:7007705",
        "tgn:7029392"
    ],
    "tgn:id":2522277,
    "tgn:name":"Moon Lake",
    "tgn:placetype":[
        "aat:300008680"
    ]
},
  "bbox": [],
  "geometry": {"coordinates":[-98.15,46.85],"type":"Point"}
}