{
  "id": 7009063,
  "type": "Feature",
  "properties": {
    "tgn:hierarchy":[
        "tgn:7009063",
        "tgn:1000003",
        "tgn:1000070",
        "tgn:7002897",
        "tgn:7029392"
    ],
    "tgn:id":7009063,
    "tgn:name":"Cr\u00e9mieu",
    "tgn:placetype":[
        "aat:300008347"
    ]
},
  "bbox": [],
  "geometry": {"coordinates":[5.25,45.7167],"type":"Point"}
}