{
  "id": 2653925,
  "type": "Feature",
  "properties": {
    "tgn:hierarchy":[
        "tgn:2653925",
        "tgn:1000001",
        "tgn:7012149",
        "tgn:2001869",
        "tgn:7007825",
        "tgn:7029392"
    ],
    "tgn:id":2653925,
    "tgn:name":"Shack Branch",
    "tgn:placetype":[
        "aat:300008699"
    ]
},
  "bbox": [],
  "geometry": {"coordinates":[-85.1667,35.4333],"type":"Point"}
}