<<<<<<< HEAD
{
  "id": 2766575,
  "type": "Feature",
  "properties": {
    "tgn:hierarchy":[
        "tgn:2766575",
        "tgn:1000001",
        "tgn:7012149",
        "tgn:1002619",
        "tgn:7007523",
        "tgn:7029392"
    ],
    "tgn:id":2766575,
    "tgn:name":"White Oak Creek",
    "tgn:placetype":[
        "aat:300008706"
    ]
},
  "bbox": [],
  "geometry": {"coordinates":[-92.75,39.8667],"type":"Point"}
}
=======
{"geometry":{"type":"Point","coordinates":[-92.750000,39.866700]},"type":"Feature","properties":{"hierarchy":["tgn:2766575","tgn:1000001","tgn:7012149","tgn:1002619","tgn:7007523","tgn:7029392"],"placetype":["aat:300008706"],"id":2766575,"name:xx":"White Oak Creek"}}
>>>>>>> 03f74aca74312dbeaf24d7e61306dd6a786dc3d0
