{
  "id": 2124500,
  "type": "Feature",
  "properties": {
    "tgn:hierarchy":[
        "tgn:2124500",
        "tgn:1000001",
        "tgn:7012149",
        "tgn:2000929",
        "tgn:7007515",
        "tgn:7029392"
    ],
    "tgn:id":2124500,
    "tgn:name":"Abagadasset River",
    "tgn:placetype":[
        "aat:300008707"
    ]
},
  "bbox": [],
  "geometry": {"coordinates":[-69.8333,44.15],"type":"Point"}
}