{
  "id": 2147356,
  "type": "Feature",
  "properties": {
    "tgn:hierarchy":[
        "tgn:2147356",
        "tgn:1000001",
        "tgn:7012149",
        "tgn:2002327",
        "tgn:7007922",
        "tgn:7029392"
    ],
    "tgn:id":2147356,
    "tgn:name":"Barbara, Lake",
    "tgn:placetype":[
        "aat:300008680"
    ]
},
  "bbox": [],
  "geometry": {"coordinates":[-90.05,46.25],"type":"Point"}
}