{
  "id": 7434356,
  "type": "Feature",
  "properties": {
    "tgn:hierarchy":[
        "tgn:7434356",
        "tgn:1000001",
        "tgn:7005590",
        "tgn:7005560",
        "tgn:7029392"
    ],
    "tgn:id":7434356,
    "tgn:name":"Tres Mezquites",
    "tgn:placetype":[
        "aat:300008347"
    ]
},
  "bbox": [],
  "geometry": {"coordinates":[-101.616667,20.266667],"type":"Point"}
}