{
  "id": 2541337,
  "type": "Feature",
  "properties": {
    "tgn:hierarchy":[
        "tgn:2541337",
        "tgn:1000001",
        "tgn:2001269",
        "tgn:7012149",
        "tgn:7007524",
        "tgn:7029392"
    ],
    "tgn:id":2541337,
    "tgn:name":"Nielsen Coulee",
    "tgn:placetype":[
        "aat:300008761"
    ]
},
  "bbox": [],
  "geometry": {"coordinates":[-105.4833,48.6333],"type":"Point"}
}