{
  "id": 2210200,
  "type": "Feature",
  "properties": {
    "tgn:hierarchy":[
        "tgn:2210200",
        "tgn:1000001",
        "tgn:2002370",
        "tgn:7012149",
        "tgn:7007923",
        "tgn:7029392"
    ],
    "tgn:id":2210200,
    "tgn:name":"Busby Draw",
    "tgn:placetype":[
        "aat:300008761"
    ]
},
  "bbox": [],
  "geometry": {"coordinates":[-104.5667,44.2333],"type":"Point"}
}