{
  "id": 7279308,
  "type": "Feature",
  "properties": {
    "tgn:hierarchy":[
        "tgn:7279308",
        "tgn:1001702",
        "tgn:1000049",
        "tgn:1000002",
        "tgn:7029392"
    ],
    "tgn:id":7279308,
    "tgn:name":"Rocosa, Punta",
    "tgn:placetype":[
        "aat:300386846"
    ]
},
  "bbox": [],
  "geometry": {"coordinates":[-75.433333,-50.683333],"type":"Point"}
}