{
  "id": 2399139,
  "type": "Feature",
  "properties": {
    "tgn:hierarchy":[
        "tgn:2399139",
        "tgn:1000001",
        "tgn:7019560",
        "tgn:7012149",
        "tgn:7007566",
        "tgn:7029392"
    ],
    "tgn:id":2399139,
    "tgn:name":"Hopper Tank",
    "tgn:placetype":[
        "aat:300006191"
    ]
},
  "bbox": [],
  "geometry": {"coordinates":[-104.0833,34.2667],"type":"Point"}
}