{
  "id": 2269820,
  "type": "Feature",
  "properties": {
    "tgn:hierarchy":[
        "tgn:2269820",
        "tgn:1000001",
        "tgn:7012149",
        "tgn:2002046",
        "tgn:7007826",
        "tgn:7029392"
    ],
    "tgn:id":2269820,
    "tgn:name":"Crows Nest Tank",
    "tgn:placetype":[
        "aat:300006191"
    ]
},
  "bbox": [],
  "geometry": {"coordinates":[-100.6167,34.1333],"type":"Point"}
}