{
  "id": 7032873,
  "type": "Feature",
  "properties": {
    "tgn:hierarchy":[
        "tgn:7032873",
        "tgn:1002052",
        "tgn:1000004",
        "tgn:1000140",
        "tgn:7029392"
    ],
    "tgn:id":7032873,
    "tgn:name":"Arslan Tash",
    "tgn:placetype":[
        "aat:300008347",
        "aat:300000810",
        "aat:300008057"
    ]
},
  "bbox": [],
  "geometry": {"coordinates":[38.406,36.85],"type":"Point"}
}