{
  "id": 2464094,
  "type": "Feature",
  "properties": {
    "tgn:hierarchy":[
        "tgn:2464094",
        "tgn:1000001",
        "tgn:7012149",
        "tgn:2002168",
        "tgn:7007919",
        "tgn:7029392"
    ],
    "tgn:id":2464094,
    "tgn:name":"Locust Fork",
    "tgn:placetype":[
        "aat:300008699"
    ]
},
  "bbox": [],
  "geometry": {"coordinates":[-79.4167,38.25],"type":"Point"}
}