{
  "id": 7551569,
  "type": "Feature",
  "properties": {
    "tgn:hierarchy":[
        "tgn:7551569",
        "tgn:1000004",
        "tgn:7031781",
        "tgn:7000198",
        "tgn:7029392"
    ],
    "tgn:id":7551569,
    "tgn:name:en":"D\u0101spur",
    "tgn:placetype":[
        "aat:300008347"
    ]
},
  "bbox": [],
  "geometry": {"coordinates":[82.866667,19.966667],"type":"Point"}
}