{
  "id": 7155188,
  "type": "Feature",
  "properties": {
    "tgn:hierarchy":[
        "tgn:7155188",
        "tgn:1000003",
        "tgn:7003688",
        "tgn:7000084",
        "tgn:7029392"
    ],
    "tgn:id":7155188,
    "tgn:name":"Kleine Breite",
    "tgn:placetype":[
        "aat:300132316"
    ]
},
  "bbox": [],
  "geometry": {"coordinates":[9.616667,54.516667],"type":"Point"}
}