{
  "id": 2519415,
  "type": "Feature",
  "properties": {
    "tgn:hierarchy":[
        "tgn:2519415",
        "tgn:1000001",
        "tgn:7012149",
        "tgn:7020792",
        "tgn:7007524",
        "tgn:7029392"
    ],
    "tgn:id":2519415,
    "tgn:name":"Modesty Creek",
    "tgn:placetype":[
        "aat:300008706"
    ]
},
  "bbox": [],
  "geometry": {"coordinates":[-112.9833,46.25],"type":"Point"}
}