{
  "id": 2740740,
  "type": "Feature",
  "properties": {
    "tgn:hierarchy":[
        "tgn:2740740",
        "tgn:1000001",
        "tgn:7012149",
        "tgn:2002119",
        "tgn:7007827",
        "tgn:7029392"
    ],
    "tgn:id":2740740,
    "tgn:name":"Upper Rattlesnake Ranch Number One Reservoir",
    "tgn:placetype":[
        "aat:300006191"
    ]
},
  "bbox": [],
  "geometry": {"coordinates":[-109.2833,38.2833],"type":"Point"}
}