{
  "id": 2065759,
  "type": "Feature",
  "properties": {
    "tgn:hierarchy":[
        "tgn:2065759",
        "tgn:1000001",
        "tgn:7014449",
        "tgn:7012149",
        "tgn:7007565",
        "tgn:7029392"
    ],
    "tgn:id":2065759,
    "tgn:name":"Palatine",
    "tgn:placetype":[
        "aat:300008347",
        "aat:300387210"
    ]
},
  "bbox": [],
  "geometry": {"coordinates":[-75.1667,39.55],"type":"Point"}
}