{
  "id": 7226064,
  "type": "Feature",
  "properties": {
    "tgn:hierarchy":[
        "tgn:7226064",
        "tgn:7011167",
        "tgn:7001338",
        "tgn:1000003",
        "tgn:1000074",
        "tgn:7029392"
    ],
    "tgn:id":7226064,
    "tgn:name":"Mo\u00fanta, \u00c1kra",
    "tgn:placetype":[
        "aat:300008850"
    ]
},
  "bbox": [],
  "geometry": {"coordinates":[20.783333,38.05],"type":"Point"}
}