{
  "id": 7258320,
  "type": "Feature",
  "properties": {
    "tgn:hierarchy":[
        "tgn:7258320",
        "tgn:1000003",
        "tgn:7003626",
        "tgn:7016845",
        "tgn:7029392"
    ],
    "tgn:id":7258320,
    "tgn:name:nl":"Beerzerzand",
    "tgn:placetype":[
        "aat:300008347",
        "aat:300387200"
    ]
},
  "bbox": [],
  "geometry": {"coordinates":[6.533333,52.516667],"type":"Point"}
}