{
  "id": 7235666,
  "type": "Feature",
  "properties": {
    "tgn:hierarchy":[
        "tgn:7235666",
        "tgn:1042193",
        "tgn:7002705",
        "tgn:1000003",
        "tgn:1000074",
        "tgn:7029392"
    ],
    "tgn:id":7235666,
    "tgn:name":"Ag\u00edou Io\u00e1nnou, \u00d3rmos",
    "tgn:placetype":[
        "aat:300132316"
    ]
},
  "bbox": [],
  "geometry": {"coordinates":[20.467778,39.270833],"type":"Point"}
}