<<<<<<< HEAD
{
  "id": 2766928,
  "type": "Feature",
  "properties": {
    "tgn:hierarchy":[
        "tgn:2766928",
        "tgn:1000001",
        "tgn:7012149",
        "tgn:1002882",
        "tgn:7007568",
        "tgn:7029392"
    ],
    "tgn:id":2766928,
    "tgn:name":"White Point",
    "tgn:placetype":[
        "aat:300008850"
    ]
},
  "bbox": [],
  "geometry": {"coordinates":[-76.9667,42.8],"type":"Point"}
}
=======
{"geometry":{"type":"Point","coordinates":[-76.966700,42.800000]},"type":"Feature","properties":{"hierarchy":["tgn:2766928","tgn:1000001","tgn:7012149","tgn:1002882","tgn:7007568","tgn:7029392"],"placetype":["aat:300008850"],"id":2766928,"name:xx":"White Point"}}
>>>>>>> 03f74aca74312dbeaf24d7e61306dd6a786dc3d0
