{
  "id": 2400802,
  "type": "Feature",
  "properties": {
    "tgn:hierarchy":[
        "tgn:2400802",
        "tgn:1002165",
        "tgn:1000001",
        "tgn:7012149",
        "tgn:7007517",
        "tgn:7029392"
    ],
    "tgn:id":2400802,
    "tgn:name":"Horse Pond",
    "tgn:placetype":[
        "aat:300008680"
    ]
},
  "bbox": [],
  "geometry": {"coordinates":[-70.2333,41.65],"type":"Point"}
}