{
  "id": 2457776,
  "type": "Feature",
  "properties": {
    "tgn:hierarchy":[
        "tgn:2457776",
        "tgn:1000001",
        "tgn:7012149",
        "tgn:1003041",
        "tgn:7007710",
        "tgn:7029392"
    ],
    "tgn:id":2457776,
    "tgn:name":"Little Mehoopany Creek",
    "tgn:placetype":[
        "aat:300008706"
    ]
},
  "bbox": [],
  "geometry": {"coordinates":[-76.1833,41.5833],"type":"Point"}
}