{
  "id": 7344937,
  "type": "Feature",
  "properties": {
    "tgn:hierarchy":[
        "tgn:7344937",
        "tgn:7002758",
        "tgn:7002821",
        "tgn:1000003",
        "tgn:1000095",
        "tgn:7029392"
    ],
    "tgn:id":7344937,
    "tgn:name":"Alquife, Rambla de",
    "tgn:placetype":[
        "aat:300008699"
    ]
},
  "bbox": [],
  "geometry": {"coordinates":[-3.116667,37.266667],"type":"Point"}
}