<<<<<<< HEAD
{
  "id": 2336515,
  "type": "Feature",
  "properties": {
    "tgn:hierarchy":[
        "tgn:2336515",
        "tgn:1000001",
        "tgn:2001790",
        "tgn:7012149",
        "tgn:7007713",
        "tgn:7029392"
    ],
    "tgn:id":2336515,
    "tgn:name":"Four Creek",
    "tgn:placetype":[
        "aat:300008706"
    ]
},
  "bbox": [],
  "geometry": {"coordinates":[-100.35,45.2333],"type":"Point"}
}
=======
{"geometry":{"type":"Point","coordinates":[-100.350000,45.233300]},"type":"Feature","properties":{"hierarchy":["tgn:2336515","tgn:1000001","tgn:2001790","tgn:7012149","tgn:7007713","tgn:7029392"],"placetype":["aat:300008706"],"id":2336515,"name:xx":"Four Creek"}}
>>>>>>> 03f74aca74312dbeaf24d7e61306dd6a786dc3d0
