{
  "id": 7522046,
  "type": "Feature",
  "properties": {
    "tgn:hierarchy":[
        "tgn:7522046",
        "tgn:7001242",
        "tgn:7001311",
        "tgn:7016833",
        "tgn:7029392"
    ],
    "tgn:id":7522046,
    "tgn:name:en":"Ab\u016b Ra\u1e29\u0101yah, Jabal",
    "tgn:placetype":[
        "aat:300008795"
    ]
},
  "bbox": [],
  "geometry": {"coordinates":[34.071655,23.118318],"type":"Point"}
}