{
  "id": 2158534,
  "type": "Feature",
  "properties": {
    "tgn:hierarchy":[
        "tgn:2158534",
        "tgn:1000001",
        "tgn:7012149",
        "tgn:1002679",
        "tgn:7007520",
        "tgn:7029392"
    ],
    "tgn:id":2158534,
    "tgn:name":"Beaverdam Drain",
    "tgn:placetype":[
        "aat:300008699"
    ]
},
  "bbox": [],
  "geometry": {"coordinates":[-83.3833,42.0333],"type":"Point"}
}