{
  "id": 2763296,
  "type": "Feature",
  "properties": {
    "tgn:hierarchy":[
        "tgn:2763296",
        "tgn:7006450",
        "tgn:1000001",
        "tgn:7012149",
        "tgn:2000079",
        "tgn:7029392"
    ],
    "tgn:id":2763296,
    "tgn:name":"Wet Gulch",
    "tgn:placetype":[
        "aat:300008761"
    ]
},
  "bbox": [],
  "geometry": {"coordinates":[-165.3333,64.5667],"type":"Point"}
}