{
  "id": 7310228,
  "type": "Feature",
  "properties": {
    "tgn:hierarchy":[
        "tgn:7310228",
        "tgn:7002464",
        "tgn:1000049",
        "tgn:1000002",
        "tgn:7029392"
    ],
    "tgn:id":7310228,
    "tgn:name":"Mulluri, Portezuelo",
    "tgn:placetype":[
        "aat:300259572"
    ]
},
  "bbox": [],
  "geometry": {"coordinates":[-69.133333,-18.966667],"type":"Point"}
}