{
  "id": 2337759,
  "type": "Feature",
  "properties": {
    "tgn:hierarchy":[
        "tgn:2337759",
        "tgn:1000001",
        "tgn:2001260",
        "tgn:7012149",
        "tgn:7007524",
        "tgn:7029392"
    ],
    "tgn:id":2337759,
    "tgn:name":"Fox Creek",
    "tgn:placetype":[
        "aat:300008706"
    ]
},
  "bbox": [],
  "geometry": {"coordinates":[-113.25,45.2333],"type":"Point"}
}