<<<<<<< HEAD
{
  "id": 2337759,
  "type": "Feature",
  "properties": {
    "tgn:hierarchy":[
        "tgn:2337759",
        "tgn:1000001",
        "tgn:2001260",
        "tgn:7012149",
        "tgn:7007524",
        "tgn:7029392"
    ],
    "tgn:id":2337759,
    "tgn:name":"Fox Creek",
    "tgn:placetype":[
        "aat:300008706"
    ]
},
  "bbox": [],
  "geometry": {"coordinates":[-113.25,45.2333],"type":"Point"}
}
=======
{"geometry":{"type":"Point","coordinates":[-113.250000,45.233300]},"type":"Feature","properties":{"hierarchy":["tgn:2337759","tgn:1000001","tgn:2001260","tgn:7012149","tgn:7007524","tgn:7029392"],"placetype":["aat:300008706"],"id":2337759,"name:xx":"Fox Creek"}}
>>>>>>> 03f74aca74312dbeaf24d7e61306dd6a786dc3d0
