{
  "id": 1131576,
  "type": "Feature",
  "properties": {
    "tgn:hierarchy":[
        "tgn:1131576",
        "tgn:7000509",
        "tgn:1008380",
        "tgn:1000226",
        "tgn:1000006",
        "tgn:7029392"
    ],
    "tgn:id":1131576,
    "tgn:name":"Waihou",
    "tgn:placetype":[
        "aat:300008707",
        "aat:300008699"
    ]
},
  "bbox": [],
  "geometry": {"coordinates":[175.533333,-37.166667],"type":"Point"}
}