{
  "id": 7454475,
  "type": "Feature",
  "properties": {
    "tgn:hierarchy":[
        "tgn:7454475",
        "tgn:7002445",
        "tgn:1000003",
        "tgn:7008166",
        "tgn:7008591",
        "tgn:7029392"
    ],
    "tgn:id":7454475,
    "tgn:name:en":"Burton Salmon",
    "tgn:placetype":[
        "aat:300008347"
    ]
},
  "bbox": [],
  "geometry": {"coordinates":[-1.266667,53.733333],"type":"Point"}
}