{
  "id": 7015644,
  "type": "Feature",
  "properties": {
    "tgn:hierarchy":[
        "tgn:7015644",
        "tgn:7015101",
        "tgn:1000003",
        "tgn:7006670",
        "tgn:7029392"
    ],
    "tgn:id":7015644,
    "tgn:name":"Kamnik",
    "tgn:placetype":[
        "aat:300008347",
        "aat:300387222",
        "aat:300008375"
    ]
},
  "bbox": [],
  "geometry": {"coordinates":[14.5833,46.2333],"type":"Point"}
}