{
  "id": 2444264,
  "type": "Feature",
  "properties": {
    "tgn:hierarchy":[
        "tgn:2444264",
        "tgn:1000001",
        "tgn:7012149",
        "tgn:7007157",
        "tgn:7029392"
    ],
    "tgn:id":2444264,
    "tgn:name":"Lacey Valley",
    "tgn:placetype":[
        "aat:300008761"
    ]
},
  "bbox": [],
  "geometry": {"coordinates":[-120.4333,39.4167],"type":"Point"}
}