{
  "id": 2284598,
  "type": "Feature",
  "properties": {
    "tgn:hierarchy":[
        "tgn:2284598",
        "tgn:1000001",
        "tgn:2001409",
        "tgn:7012149",
        "tgn:7007526",
        "tgn:7029392"
    ],
    "tgn:id":2284598,
    "tgn:name":"Desert Crystal Salt Works",
    "tgn:placetype":[
        "aat:300000390"
    ]
},
  "bbox": [],
  "geometry": {"coordinates":[-118.7667,39.8833],"type":"Point"}
}