{
  "id": 2327883,
  "type": "Feature",
  "properties": {
    "tgn:hierarchy":[
        "tgn:2327883",
        "tgn:1000001",
        "tgn:7012149",
        "tgn:1002950",
        "tgn:7007568",
        "tgn:7029392"
    ],
    "tgn:id":2327883,
    "tgn:name":"Fish Kill",
    "tgn:placetype":[
        "aat:300008699"
    ]
},
  "bbox": [],
  "geometry": {"coordinates":[-76.6167,42.35],"type":"Point"}
}