{
  "id": 2530713,
  "type": "Feature",
  "properties": {
    "tgn:hierarchy":[
        "tgn:2530713",
        "tgn:1000001",
        "tgn:7012149",
        "tgn:7007158",
        "tgn:2000245",
        "tgn:7029392"
    ],
    "tgn:id":2530713,
    "tgn:name":"Muddy Pass Lake",
    "tgn:placetype":[
        "aat:300008680"
    ]
},
  "bbox": [],
  "geometry": {"coordinates":[-106.5833,40.3833],"type":"Point"}
}