{
  "id": 7454997,
  "type": "Feature",
  "properties": {
    "tgn:hierarchy":[
        "tgn:7454997",
        "tgn:7002445",
        "tgn:1000003",
        "tgn:7008118",
        "tgn:7008591",
        "tgn:7029392"
    ],
    "tgn:id":7454997,
    "tgn:name:en":"Dale Abbey",
    "tgn:placetype":[
        "aat:300008347"
    ]
},
  "bbox": [],
  "geometry": {"coordinates":[-1.35,52.933333],"type":"Point"}
}