{
  "id": 2683904,
  "type": "Feature",
  "properties": {
    "tgn:hierarchy":[
        "tgn:2683904",
        "tgn:1000001",
        "tgn:7012149",
        "tgn:2001121",
        "tgn:7007522",
        "tgn:7029392"
    ],
    "tgn:id":2683904,
    "tgn:name":"Spence Branch",
    "tgn:placetype":[
        "aat:300008699"
    ]
},
  "bbox": [],
  "geometry": {"coordinates":[-89.35,34.5167],"type":"Point"}
}