{
  "id": 2582191,
  "type": "Feature",
  "properties": {
    "tgn:hierarchy":[
        "tgn:2582191",
        "tgn:1000001",
        "tgn:7012149",
        "tgn:7007524",
        "tgn:7029392"
    ],
    "tgn:id":2582191,
    "tgn:name":"Pine Creek",
    "tgn:placetype":[
        "aat:300008706"
    ]
},
  "bbox": [],
  "geometry": {"coordinates":[-104.7167,46.6167],"type":"Point"}
}