{
  "id": 2636703,
  "type": "Feature",
  "properties": {
    "tgn:hierarchy":[
        "tgn:2636703",
        "tgn:1000001",
        "tgn:1002283",
        "tgn:7012149",
        "tgn:7007520",
        "tgn:7029392"
    ],
    "tgn:id":2636703,
    "tgn:name":"Sage and Hafner Drain",
    "tgn:placetype":[
        "aat:300006075"
    ]
},
  "bbox": [],
  "geometry": {"coordinates":[-84.7667,43.0167],"type":"Point"}
}