<<<<<<< HEAD
{
  "id": 2705012,
  "type": "Feature",
  "properties": {
    "tgn:hierarchy":[
        "tgn:2705012",
        "tgn:1000001",
        "tgn:7012149",
        "tgn:7007157",
        "tgn:1002858",
        "tgn:7029392"
    ],
    "tgn:id":2705012,
    "tgn:name":"Sunset Wash",
    "tgn:placetype":[
        "aat:300008699"
    ]
},
  "bbox": [],
  "geometry": {"coordinates":[-116.2667,33.1],"type":"Point"}
}
=======
{"geometry":{"type":"Point","coordinates":[-116.266700,33.100000]},"type":"Feature","properties":{"hierarchy":["tgn:2705012","tgn:1000001","tgn:7012149","tgn:7007157","tgn:1002858","tgn:7029392"],"placetype":["aat:300008699"],"id":2705012,"name:xx":"Sunset Wash"}}
>>>>>>> 03f74aca74312dbeaf24d7e61306dd6a786dc3d0
