{
  "id": 7366289,
  "type": "Feature",
  "properties": {
    "tgn:hierarchy":[
        "tgn:7366289",
        "tgn:7005578",
        "tgn:1000001",
        "tgn:7005560",
        "tgn:7029392"
    ],
    "tgn:id":7366289,
    "tgn:name":"Escondido, Puerto",
    "tgn:placetype":[
        "aat:300266557"
    ]
},
  "bbox": [],
  "geometry": {"coordinates":[-91.416667,18.866667],"type":"Point"}
}