{
  "id": 2298383,
  "type": "Feature",
  "properties": {
    "tgn:hierarchy":[
        "tgn:2298383",
        "tgn:1000001",
        "tgn:7012149",
        "tgn:7007706",
        "tgn:7029392"
    ],
    "tgn:id":2298383,
    "tgn:name":"Dry Ridge",
    "tgn:placetype":[
        "aat:300266640"
    ]
},
  "bbox": [],
  "geometry": {"coordinates":[-82.55,38.7833],"type":"Point"}
}