{
  "id": 7546543,
  "type": "Feature",
  "properties": {
    "tgn:hierarchy":[
        "tgn:7546543",
        "tgn:1000004",
        "tgn:7000198",
        "tgn:1001977",
        "tgn:7029392"
    ],
    "tgn:id":7546543,
    "tgn:name:en":"Bay\u0101rm\u0101ri \u0100b\u0101d",
    "tgn:placetype":[
        "aat:300387200"
    ]
},
  "bbox": [],
  "geometry": {"coordinates":[88.766667,22.433333],"type":"Point"}
}