{
  "id": 7391826,
  "type": "Feature",
  "properties": {
    "tgn:hierarchy":[
        "tgn:7391826",
        "tgn:1000001",
        "tgn:1001960",
        "tgn:7005560",
        "tgn:7029392"
    ],
    "tgn:id":7391826,
    "tgn:name":"Rancho Veinte de Noviembre",
    "tgn:placetype":[
        "aat:300008347"
    ]
},
  "bbox": [],
  "geometry": {"coordinates":[-111.616667,28.55],"type":"Point"}
}