{
  "id": 2460306,
  "type": "Feature",
  "properties": {
    "tgn:hierarchy":[
        "tgn:2460306",
        "tgn:1000001",
        "tgn:7012149",
        "tgn:2001706",
        "tgn:7007708",
        "tgn:7029392"
    ],
    "tgn:id":2460306,
    "tgn:name":"Little Salander Creek",
    "tgn:placetype":[
        "aat:300008706"
    ]
},
  "bbox": [],
  "geometry": {"coordinates":[-123.8667,43.5833],"type":"Point"}
}