<<<<<<< HEAD
{
  "id": 7489372,
  "type": "Feature",
  "properties": {
    "tgn:hierarchy":[
        "tgn:7489372",
        "tgn:1000004",
        "tgn:1000959",
        "tgn:1000141",
        "tgn:7029392"
    ],
    "tgn:id":7489372,
    "tgn:name":"Yide Li",
    "tgn:placetype":[
        "aat:300387173"
    ]
},
  "bbox": [],
  "geometry": {"coordinates":[121.4776,25.1298],"type":"Point"}
}
=======
{"geometry":{"type":"Point","coordinates":[121.477600,25.129800]},"type":"Feature","properties":{"hierarchy":["tgn:7489372","tgn:1000004","tgn:1000959","tgn:1000141","tgn:7029392"],"placetype":["aat:300387173"],"id":7489372,"name:xx":"Yide Li"}}
>>>>>>> 03f74aca74312dbeaf24d7e61306dd6a786dc3d0
