{
  "id": 7489372,
  "type": "Feature",
  "properties": {
    "tgn:hierarchy":[
        "tgn:7489372",
        "tgn:1000004",
        "tgn:1000959",
        "tgn:1000141",
        "tgn:7029392"
    ],
    "tgn:id":7489372,
    "tgn:name":"Yide Li",
    "tgn:placetype":[
        "aat:300387173"
    ]
},
  "bbox": [],
  "geometry": {"coordinates":[121.4776,25.1298],"type":"Point"}
}