<<<<<<< HEAD
{
  "id": 2257882,
  "type": "Feature",
  "properties": {
    "tgn:hierarchy":[
        "tgn:2257882",
        "tgn:1000001",
        "tgn:7012149",
        "tgn:2001460",
        "tgn:7007566",
        "tgn:7029392"
    ],
    "tgn:id":2257882,
    "tgn:name":"Correo",
    "tgn:placetype":[
        "aat:300008347"
    ]
},
  "bbox": [],
  "geometry": {"coordinates":[-107.1833,34.95],"type":"Point"}
}
=======
{"geometry":{"type":"Point","coordinates":[-107.183300,34.950000]},"type":"Feature","properties":{"hierarchy":["tgn:2257882","tgn:1000001","tgn:7012149","tgn:2001460","tgn:7007566","tgn:7029392"],"placetype":["aat:300008347"],"id":2257882,"name:xx":"Correo"}}
>>>>>>> 03f74aca74312dbeaf24d7e61306dd6a786dc3d0
