{
  "id": 1042403,
  "type": "Feature",
  "properties": {
    "tgn:hierarchy":[
        "tgn:1042403",
        "tgn:1000348",
        "tgn:1000003",
        "tgn:7006278",
        "tgn:7029392"
    ],
    "tgn:id":1042403,
    "tgn:name":"Mez\u0151k\u00f6vesd",
    "tgn:placetype":[
        "aat:300008347"
    ]
},
  "bbox": [],
  "geometry": {"coordinates":[20.5333,47.8167],"type":"Point"}
}