{
  "id": 7554041,
  "type": "Feature",
  "properties": {
    "tgn:hierarchy":[
        "tgn:7554041",
        "tgn:1000004",
        "tgn:1001842",
        "tgn:7000198",
        "tgn:7029392"
    ],
    "tgn:id":7554041,
    "tgn:name:en":"M\u0101hi Nad\u012b",
    "tgn:placetype":[
        "aat:300008699"
    ]
},
  "bbox": [],
  "geometry": {"coordinates":[85.075144,25.757775],"type":"Point"}
}