{
  "id": 7459528,
  "type": "Feature",
  "properties": {
    "tgn:hierarchy":[
        "tgn:7459528",
        "tgn:7002444",
        "tgn:1000003",
        "tgn:7008082",
        "tgn:7008591",
        "tgn:7029392"
    ],
    "tgn:id":7459528,
    "tgn:name:en":"Mey Bay",
    "tgn:placetype":[
        "aat:300132316"
    ]
},
  "bbox": [],
  "geometry": {"coordinates":[-3.216667,58.65],"type":"Point"}
}