<<<<<<< HEAD
{
  "id": 2761572,
  "type": "Feature",
  "properties": {
    "tgn:hierarchy":[
        "tgn:2761572",
        "tgn:1000001",
        "tgn:2001786",
        "tgn:7012149",
        "tgn:7007713",
        "tgn:7029392"
    ],
    "tgn:id":2761572,
    "tgn:name":"West Pass Creek",
    "tgn:placetype":[
        "aat:300008706"
    ]
},
  "bbox": [],
  "geometry": {"coordinates":[-103.8167,43.6167],"type":"Point"}
}
=======
{"geometry":{"type":"Point","coordinates":[-103.816700,43.616700]},"type":"Feature","properties":{"hierarchy":["tgn:2761572","tgn:1000001","tgn:2001786","tgn:7012149","tgn:7007713","tgn:7029392"],"placetype":["aat:300008706"],"id":2761572,"name:xx":"West Pass Creek"}}
>>>>>>> 03f74aca74312dbeaf24d7e61306dd6a786dc3d0
