{
  "id": 2508020,
  "type": "Feature",
  "properties": {
    "tgn:hierarchy":[
        "tgn:2508020",
        "tgn:1000001",
        "tgn:7012149",
        "tgn:7007825",
        "tgn:7029392"
    ],
    "tgn:id":2508020,
    "tgn:name":"Middle Beaver Creek Canal",
    "tgn:placetype":[
        "aat:300006075"
    ]
},
  "bbox": [],
  "geometry": {"coordinates":[-89.6167,35.45],"type":"Point"}
}