{
  "id": 7472499,
  "type": "Feature",
  "properties": {
    "tgn:hierarchy":[
        "tgn:7472499",
        "tgn:1000004",
        "tgn:7492971",
        "tgn:1000141",
        "tgn:7029392"
    ],
    "tgn:id":7472499,
    "tgn:name":"Xiawuluo",
    "tgn:placetype":[
        "aat:300008347"
    ]
},
  "bbox": [],
  "geometry": {"coordinates":[120.516389,22.7725],"type":"Point"}
}