<<<<<<< HEAD
{
  "id": 7472499,
  "type": "Feature",
  "properties": {
    "tgn:hierarchy":[
        "tgn:7472499",
        "tgn:1000004",
        "tgn:7492971",
        "tgn:1000141",
        "tgn:7029392"
    ],
    "tgn:id":7472499,
    "tgn:name":"Xiawuluo",
    "tgn:placetype":[
        "aat:300008347"
    ]
},
  "bbox": [],
  "geometry": {"coordinates":[120.516389,22.7725],"type":"Point"}
}
=======
{"geometry":{"type":"Point","coordinates":[120.516389,22.772500]},"type":"Feature","properties":{"hierarchy":["tgn:7472499","tgn:1000004","tgn:7492971","tgn:1000141","tgn:7029392"],"placetype":["aat:300008347"],"id":7472499,"name:xx":"Xiawuluo"}}
>>>>>>> 03f74aca74312dbeaf24d7e61306dd6a786dc3d0
