{
  "id": 7572644,
  "type": "Feature",
  "properties": {
    "tgn:hierarchy":[
        "tgn:7572644",
        "tgn:1000004",
        "tgn:7000198",
        "tgn:1001882",
        "tgn:7029392"
    ],
    "tgn:id":7572644,
    "tgn:name:en":"Jigani",
    "tgn:placetype":[
        "aat:300008347"
    ]
},
  "bbox": [],
  "geometry": {"coordinates":[77.65,12.766667],"type":"Point"}
}