{
  "id": 2598428,
  "type": "Feature",
  "properties": {
    "tgn:hierarchy":[
        "tgn:2598428",
        "tgn:7002659",
        "tgn:1000001",
        "tgn:7012149",
        "tgn:7029392"
    ],
    "tgn:id":2598428,
    "tgn:name":"Price Creek",
    "tgn:placetype":[
        "aat:300008706"
    ]
},
  "bbox": [],
  "geometry": {"coordinates":[-86.9167,33.8167],"type":"Point"}
}