{
  "id": 7279873,
  "type": "Feature",
  "properties": {
    "tgn:hierarchy":[
        "tgn:7279873",
        "tgn:1001699",
        "tgn:1000049",
        "tgn:1000002",
        "tgn:7029392"
    ],
    "tgn:id":7279873,
    "tgn:name":"Ramadillas",
    "tgn:placetype":[
        "aat:300387200"
    ]
},
  "bbox": [],
  "geometry": {"coordinates":[-73.15,-40.266667],"type":"Point"}
}