{
  "id": 7439428,
  "type": "Feature",
  "properties": {
    "tgn:hierarchy":[
        "tgn:7439428",
        "tgn:1000001",
        "tgn:7005591",
        "tgn:7005560",
        "tgn:7029392"
    ],
    "tgn:id":7439428,
    "tgn:name":"San Rafael",
    "tgn:placetype":[
        "aat:300008347"
    ]
},
  "bbox": [],
  "geometry": {"coordinates":[-97.083333,16.15],"type":"Point"}
}