{
  "id": 7582492,
  "type": "Feature",
  "properties": {
    "tgn:hierarchy":[
        "tgn:7582492",
        "tgn:1000004",
        "tgn:7000198",
        "tgn:1001894",
        "tgn:7029392"
    ],
    "tgn:id":7582492,
    "tgn:name:en":"Bamhorilal",
    "tgn:placetype":[
        "aat:300008347"
    ]
},
  "bbox": [],
  "geometry": {"coordinates":[78.435182,24.246063],"type":"Point"}
}