{
  "id": 1093314,
  "type": "Feature",
  "properties": {
    "tgn:hierarchy":[
        "tgn:1093314",
        "tgn:7001242",
        "tgn:7017576",
        "tgn:1000193",
        "tgn:7029392"
    ],
    "tgn:id":1093314,
    "tgn:name":"Lewisham Location",
    "tgn:placetype":[
        "aat:300008347"
    ]
},
  "bbox": [],
  "geometry": {"coordinates":[27.75,-26.1333],"type":"Point"}
}