{
  "id": 2704945,
  "type": "Feature",
  "properties": {
    "tgn:hierarchy":[
        "tgn:2704945",
        "tgn:1000001",
        "tgn:7014423",
        "tgn:7012149",
        "tgn:7007517",
        "tgn:7029392"
    ],
    "tgn:id":2704945,
    "tgn:name":"Sunset Point",
    "tgn:placetype":[
        "aat:300008850"
    ]
},
  "bbox": [],
  "geometry": {"coordinates":[-70.8833,42.2667],"type":"Point"}
}