<<<<<<< HEAD
{
  "id": 2404525,
  "type": "Feature",
  "properties": {
    "tgn:hierarchy":[
        "tgn:2404525",
        "tgn:1000001",
        "tgn:7012149",
        "tgn:1003040",
        "tgn:7007568",
        "tgn:7029392"
    ],
    "tgn:id":2404525,
    "tgn:name":"Hubbards Pond",
    "tgn:placetype":[
        "aat:300006191"
    ]
},
  "bbox": [],
  "geometry": {"coordinates":[-78.2333,42.8],"type":"Point"}
}
=======
{"geometry":{"type":"Point","coordinates":[-78.233300,42.800000]},"type":"Feature","properties":{"hierarchy":["tgn:2404525","tgn:1000001","tgn:7012149","tgn:1003040","tgn:7007568","tgn:7029392"],"placetype":["aat:300006191"],"id":2404525,"name:xx":"Hubbards Pond"}}
>>>>>>> 03f74aca74312dbeaf24d7e61306dd6a786dc3d0
