{
  "id": 2498583,
  "type": "Feature",
  "properties": {
    "tgn:hierarchy":[
        "tgn:2498583",
        "tgn:7006450",
        "tgn:1000001",
        "tgn:7012149",
        "tgn:2000085",
        "tgn:7029392"
    ],
    "tgn:id":2498583,
    "tgn:name":"McArthur Creek",
    "tgn:placetype":[
        "aat:300008706"
    ]
},
  "bbox": [],
  "geometry": {"coordinates":[-141.0167,63.2667],"type":"Point"}
}