{
  "id": 2047876,
  "type": "Feature",
  "properties": {
    "tgn:hierarchy":[
        "tgn:2047876",
        "tgn:7016100",
        "tgn:1000001",
        "tgn:7012149",
        "tgn:7007516",
        "tgn:7029392"
    ],
    "tgn:id":2047876,
    "tgn:name":"Marshalls Corner",
    "tgn:placetype":[
        "aat:300008347",
        "aat:300387210"
    ]
},
  "bbox": [],
  "geometry": {"coordinates":[-77.0333,38.5333],"type":"Point"}
}