{
  "id": 7578788,
  "type": "Feature",
  "properties": {
    "tgn:hierarchy":[
        "tgn:7578788",
        "tgn:1000004",
        "tgn:7000198",
        "tgn:7016788",
        "tgn:7029392"
    ],
    "tgn:id":7578788,
    "tgn:name:en":"Udit",
    "tgn:placetype":[
        "aat:300008347"
    ]
},
  "bbox": [],
  "geometry": {"coordinates":[72.723684,27.556291],"type":"Point"}
}