{
  "id": 2640894,
  "type": "Feature",
  "properties": {
    "tgn:hierarchy":[
        "tgn:2640894",
        "tgn:2001422",
        "tgn:1000001",
        "tgn:7012149",
        "tgn:7007564",
        "tgn:7029392"
    ],
    "tgn:id":2640894,
    "tgn:name":"Sanborn Hill",
    "tgn:placetype":[
        "aat:300008798"
    ]
},
  "bbox": [],
  "geometry": {"coordinates":[-71.35,43.35],"type":"Point"}
}