{
  "id": 2115666,
  "type": "Feature",
  "properties": {
    "tgn:hierarchy":[
        "tgn:2115666",
        "tgn:1000001",
        "tgn:7012149",
        "tgn:1002942",
        "tgn:7007920",
        "tgn:7029392"
    ],
    "tgn:id":2115666,
    "tgn:name":"East Olympia",
    "tgn:placetype":[
        "aat:300008347"
    ]
},
  "bbox": [],
  "geometry": {"coordinates":[-122.8333,46.9667],"type":"Point"}
}