{
  "id": 1026723,
  "type": "Feature",
  "properties": {
    "tgn:hierarchy":[
        "tgn:1026723",
        "tgn:7003460",
        "tgn:1000003",
        "tgn:1000063",
        "tgn:4012014",
        "tgn:7029392"
    ],
    "tgn:id":1026723,
    "tgn:name":"Seraing",
    "tgn:placetype":[
        "aat:300008347",
        "aat:300008375",
        "aat:300387302"
    ]
},
  "bbox": [],
  "geometry": {"coordinates":[5.507894,50.61178],"type":"Point"}
}