{
  "id": 7186184,
  "type": "Feature",
  "properties": {
    "tgn:hierarchy":[
        "tgn:7186184",
        "tgn:1000003",
        "tgn:7003677",
        "tgn:7000084",
        "tgn:7029392"
    ],
    "tgn:id":7186184,
    "tgn:name":"Gerlage",
    "tgn:placetype":[
        "aat:300387200"
    ]
},
  "bbox": [],
  "geometry": {"coordinates":[8.616667,52.483333],"type":"Point"}
}