{
  "id": 7414392,
  "type": "Feature",
  "properties": {
    "tgn:hierarchy":[
        "tgn:7414392",
        "tgn:7005580",
        "tgn:1000001",
        "tgn:7005560",
        "tgn:7029392"
    ],
    "tgn:id":7414392,
    "tgn:name":"\u00c1ngel A. Corzo",
    "tgn:placetype":[
        "aat:300008347"
    ]
},
  "bbox": [],
  "geometry": {"coordinates":[-93.616667,17.225],"type":"Point"}
}