{
  "id": 2462712,
  "type": "Feature",
  "properties": {
    "tgn:hierarchy":[
        "tgn:2462712",
        "tgn:1000001",
        "tgn:7012149",
        "tgn:2001455",
        "tgn:7007566",
        "tgn:7029392"
    ],
    "tgn:id":2462712,
    "tgn:name":"Little Wonder Mine",
    "tgn:placetype":[
        "aat:300000390"
    ]
},
  "bbox": [],
  "geometry": {"coordinates":[-107.7667,33.45],"type":"Point"}
}