{
  "id": 2361337,
  "type": "Feature",
  "properties": {
    "tgn:hierarchy":[
        "tgn:2361337",
        "tgn:1000001",
        "tgn:7012149",
        "tgn:2002112",
        "tgn:7007827",
        "tgn:7029392"
    ],
    "tgn:id":2361337,
    "tgn:name":"Gravel Spring",
    "tgn:placetype":[
        "aat:300008697"
    ]
},
  "bbox": [],
  "geometry": {"coordinates":[-111.75,39.6833],"type":"Point"}
}