{
  "id": 1098528,
  "type": "Feature",
  "properties": {
    "tgn:hierarchy":[
        "tgn:1098528",
        "tgn:7000490",
        "tgn:1000006",
        "tgn:7001834",
        "tgn:7029392"
    ],
    "tgn:id":1098528,
    "tgn:name":"Wickepin",
    "tgn:placetype":[
        "aat:300008347"
    ]
},
  "bbox": [],
  "geometry": {"coordinates":[117.5167,-32.75],"type":"Point"}
}