{
  "id": 2438425,
  "type": "Feature",
  "properties": {
    "tgn:hierarchy":[
        "tgn:2438425",
        "tgn:1000001",
        "tgn:7012149",
        "tgn:7007709",
        "tgn:7029392"
    ],
    "tgn:id":2438425,
    "tgn:name":"Kings Mountain",
    "tgn:placetype":[
        "aat:300266640"
    ]
},
  "bbox": [],
  "geometry": {"coordinates":[-81.3333,35.1667],"type":"Point"}
}