{
  "id": 2702714,
  "type": "Feature",
  "properties": {
    "tgn:hierarchy":[
        "tgn:2702714",
        "tgn:1000001",
        "tgn:7012149",
        "tgn:2002087",
        "tgn:7007826",
        "tgn:7029392"
    ],
    "tgn:id":2702714,
    "tgn:name":"Sulphur Mountain",
    "tgn:placetype":[
        "aat:300008798"
    ]
},
  "bbox": [],
  "geometry": {"coordinates":[-99.9667,29.1667],"type":"Point"}
}