{
  "id": 1007953,
  "type": "Feature",
  "properties": {
    "tgn:hierarchy":[
        "tgn:1007953",
        "tgn:7018487",
        "tgn:1000004",
        "tgn:7004542",
        "tgn:1000111",
        "tgn:7029392"
    ],
    "tgn:id":1007953,
    "tgn:name":"Ma Wan",
    "tgn:placetype":[
        "aat:300008791"
    ]
},
  "bbox": [],
  "geometry": {"coordinates":[114.05,22.35],"type":"Point"}
}