{
  "id": 2283045,
  "type": "Feature",
  "properties": {
    "tgn:hierarchy":[
        "tgn:2283045",
        "tgn:1000001",
        "tgn:7012149",
        "tgn:2001708",
        "tgn:7007708",
        "tgn:7029392"
    ],
    "tgn:id":2283045,
    "tgn:name":"Del Spring",
    "tgn:placetype":[
        "aat:300008697"
    ]
},
  "bbox": [],
  "geometry": {"coordinates":[-119.65,44.8667],"type":"Point"}
}