<<<<<<< HEAD
{
  "id": 2764450,
  "type": "Feature",
  "properties": {
    "tgn:hierarchy":[
        "tgn:2764450",
        "tgn:1000001",
        "tgn:1002665",
        "tgn:7012149",
        "tgn:7007517",
        "tgn:7029392"
    ],
    "tgn:id":2764450,
    "tgn:name":"Whidden Corner",
    "tgn:placetype":[
        "aat:300008347"
    ]
},
  "bbox": [],
  "geometry": {"coordinates":[-71.4167,42.6167],"type":"Point"}
}
=======
{"geometry":{"type":"Point","coordinates":[-71.416700,42.616700]},"type":"Feature","properties":{"hierarchy":["tgn:2764450","tgn:1000001","tgn:1002665","tgn:7012149","tgn:7007517","tgn:7029392"],"placetype":["aat:300008347"],"id":2764450,"name:xx":"Whidden Corner"}}
>>>>>>> 03f74aca74312dbeaf24d7e61306dd6a786dc3d0
