{
  "id": 7193448,
  "type": "Feature",
  "properties": {
    "tgn:hierarchy":[
        "tgn:7193448",
        "tgn:1000003",
        "tgn:7003676",
        "tgn:7000084",
        "tgn:7029392"
    ],
    "tgn:id":7193448,
    "tgn:name":"Gut Eyhausen",
    "tgn:placetype":[
        "aat:300000206"
    ]
},
  "bbox": [],
  "geometry": {"coordinates":[7.983333,53.183333],"type":"Point"}
}