{
  "id": 2280915,
  "type": "Feature",
  "properties": {
    "tgn:hierarchy":[
        "tgn:2280915",
        "tgn:1000001",
        "tgn:2002368",
        "tgn:7012149",
        "tgn:7007923",
        "tgn:7029392"
    ],
    "tgn:id":2280915,
    "tgn:name":"Deep Creek Butte",
    "tgn:placetype":[
        "aat:300008798"
    ]
},
  "bbox": [],
  "geometry": {"coordinates":[-107.5667,41.1333],"type":"Point"}
}