{
  "id": 7577288,
  "type": "Feature",
  "properties": {
    "tgn:hierarchy":[
        "tgn:7577288",
        "tgn:1000004",
        "tgn:7000198",
        "tgn:7016788",
        "tgn:7029392"
    ],
    "tgn:id":7577288,
    "tgn:name:en":"Khemli",
    "tgn:placetype":[
        "aat:300007783"
    ]
},
  "bbox": [],
  "geometry": {"coordinates":[73.846624,24.693501],"type":"Point"}
}