{
  "id": 7415109,
  "type": "Feature",
  "properties": {
    "tgn:hierarchy":[
        "tgn:7415109",
        "tgn:7005584",
        "tgn:1000001",
        "tgn:7005560",
        "tgn:7029392"
    ],
    "tgn:id":7415109,
    "tgn:name":"Cuevas de Moreno",
    "tgn:placetype":[
        "aat:300008795"
    ]
},
  "bbox": [],
  "geometry": {"coordinates":[-100.804444,20.158056],"type":"Point"}
}