{
  "id": 2300451,
  "type": "Feature",
  "properties": {
    "tgn:hierarchy":[
        "tgn:2300451",
        "tgn:1000001",
        "tgn:7012149",
        "tgn:2001067",
        "tgn:7007521",
        "tgn:7029392"
    ],
    "tgn:id":2300451,
    "tgn:name":"Duluth Harbor Basin Southern Section",
    "tgn:placetype":[
        "aat:300132316"
    ]
},
  "bbox": [],
  "geometry": {"coordinates":[-92.0833,46.75],"type":"Point"}
}