{
  "id": 7548083,
  "type": "Feature",
  "properties": {
    "tgn:hierarchy":[
        "tgn:7548083",
        "tgn:1000004",
        "tgn:7000198",
        "tgn:7016722",
        "tgn:7029392"
    ],
    "tgn:id":7548083,
    "tgn:name:en":"Bhamora",
    "tgn:placetype":[
        "aat:300008347"
    ]
},
  "bbox": [],
  "geometry": {"coordinates":[79.299094,28.208812],"type":"Point"}
}