{
  "id": 1048301,
  "type": "Feature",
  "properties": {
    "tgn:hierarchy":[
        "tgn:1048301",
        "tgn:7002448",
        "tgn:7019203",
        "tgn:1000003",
        "tgn:7008591",
        "tgn:7029392"
    ],
    "tgn:id":1048301,
    "tgn:name:en":"Ballygawley",
    "tgn:placetype":[
        "aat:300008347"
    ]
},
  "bbox": [],
  "geometry": {"coordinates":[-7.033333,54.466667],"type":"Point"}
}