{
  "id": 1009361,
  "type": "Feature",
  "properties": {
    "tgn:hierarchy":[
        "tgn:1009361",
        "tgn:1001826",
        "tgn:1000047",
        "tgn:7002456",
        "tgn:1000002",
        "tgn:7029392"
    ],
    "tgn:id":1009361,
    "tgn:name":"Tamaquari, Ilha",
    "tgn:placetype":[
        "aat:300008791"
    ]
},
  "bbox": [],
  "geometry": {"coordinates":[-64.85,-0.4667],"type":"Point"}
}