{
  "id": 1139232,
  "type": "Feature",
  "properties": {
    "tgn:hierarchy":[
        "tgn:1139232",
        "tgn:1000004",
        "tgn:1001390",
        "tgn:1000111",
        "tgn:7029392"
    ],
    "tgn:id":1139232,
    "tgn:name":"Laobian",
    "tgn:placetype":[
        "aat:300008347"
    ]
},
  "bbox": [],
  "geometry": {"coordinates":[123.1667,41.9667],"type":"Point"}
}