{
  "id": 1012415,
  "type": "Feature",
  "properties": {
    "tgn:hierarchy":[
        "tgn:1012415",
        "tgn:7002445",
        "tgn:1000003",
        "tgn:7011430",
        "tgn:7008591",
        "tgn:7029392"
    ],
    "tgn:id":1012415,
    "tgn:name:en":"Saint Catherine's Point",
    "tgn:placetype":[
        "aat:300386846"
    ]
},
  "bbox": [],
  "geometry": {"coordinates":[-1.266667,50.583333],"type":"Point"}
}