<<<<<<< HEAD
{
  "id": 7116871,
  "type": "Feature",
  "properties": {
    "tgn:hierarchy":[
        "tgn:7116871",
        "tgn:1000003",
        "tgn:7003688",
        "tgn:7000084",
        "tgn:7029392"
    ],
    "tgn:id":7116871,
    "tgn:name":"Orther Reede",
    "tgn:placetype":[
        "aat:300132316"
    ]
},
  "bbox": [],
  "geometry": {"coordinates":[11.066667,54.416667],"type":"Point"}
}
=======
{"geometry":{"type":"Point","coordinates":[11.066667,54.416667]},"type":"Feature","properties":{"hierarchy":["tgn:7116871","tgn:1000003","tgn:7003688","tgn:7000084","tgn:7029392"],"placetype":["aat:300132316"],"id":7116871,"name:xx":"Orther Reede"}}
>>>>>>> 03f74aca74312dbeaf24d7e61306dd6a786dc3d0
