{
  "id": 1059028,
  "type": "Feature",
  "properties": {
    "tgn:hierarchy":[
        "tgn:1059028",
        "tgn:1000004",
        "tgn:1003416",
        "tgn:7014786",
        "tgn:7029392"
    ],
    "tgn:id":1059028,
    "tgn:name":"Rudnichnyy",
    "tgn:placetype":[
        "aat:300008347"
    ]
},
  "bbox": [],
  "geometry": {"coordinates":[79.0167,44.65],"type":"Point"}
}