<<<<<<< HEAD
{
  "id": 2765034,
  "type": "Feature",
  "properties": {
    "tgn:hierarchy":[
        "tgn:2765034",
        "tgn:1000001",
        "tgn:7012149",
        "tgn:2001709",
        "tgn:7007708",
        "tgn:7029392"
    ],
    "tgn:id":2765034,
    "tgn:name":"Whisky Hill",
    "tgn:placetype":[
        "aat:300008798"
    ]
},
  "bbox": [],
  "geometry": {"coordinates":[-118.6667,42.4167],"type":"Point"}
}
=======
{"geometry":{"type":"Point","coordinates":[-118.666700,42.416700]},"type":"Feature","properties":{"hierarchy":["tgn:2765034","tgn:1000001","tgn:7012149","tgn:2001709","tgn:7007708","tgn:7029392"],"placetype":["aat:300008798"],"id":2765034,"name:xx":"Whisky Hill"}}
>>>>>>> 03f74aca74312dbeaf24d7e61306dd6a786dc3d0
