{
  "id": 7455555,
  "type": "Feature",
  "properties": {
    "tgn:hierarchy":[
        "tgn:7455555",
        "tgn:7002443",
        "tgn:1000003",
        "tgn:7018973",
        "tgn:7008591",
        "tgn:7029392"
    ],
    "tgn:id":7455555,
    "tgn:name:en":"Cockett",
    "tgn:placetype":[
        "aat:300007783"
    ]
},
  "bbox": [],
  "geometry": {"coordinates":[-3.983333,51.633333],"type":"Point"}
}