{
  "id": 2559580,
  "type": "Feature",
  "properties": {
    "tgn:hierarchy":[
        "tgn:2559580",
        "tgn:7006450",
        "tgn:1000001",
        "tgn:7012149",
        "tgn:2124005",
        "tgn:7029392"
    ],
    "tgn:id":2559580,
    "tgn:name":"Oolah Valley",
    "tgn:placetype":[
        "aat:300008761"
    ]
},
  "bbox": [],
  "geometry": {"coordinates":[-150.4167,68.0667],"type":"Point"}
}