{
  "id": 7424421,
  "type": "Feature",
  "properties": {
    "tgn:hierarchy":[
        "tgn:7424421",
        "tgn:1000001",
        "tgn:1001906",
        "tgn:7005560",
        "tgn:7029392"
    ],
    "tgn:id":7424421,
    "tgn:name":"Santa Marta, Estero",
    "tgn:placetype":[
        "aat:300387055"
    ]
},
  "bbox": [],
  "geometry": {"coordinates":[-105.415556,22.196389],"type":"Point"}
}