{
  "id": 7501764,
  "type": "Feature",
  "properties": {
    "tgn:hierarchy":[
        "tgn:7501764",
        "tgn:1000004",
        "tgn:7490934",
        "tgn:1000141",
        "tgn:7029392"
    ],
    "tgn:id":7501764,
    "tgn:name":"Qijiao Qiao",
    "tgn:placetype":[
        "aat:300007836"
    ]
},
  "bbox": [],
  "geometry": {"coordinates":[120.37,22.963889],"type":"Point"}
}