{
  "id": 2499864,
  "type": "Feature",
  "properties": {
    "tgn:hierarchy":[
        "tgn:2499864",
        "tgn:1000001",
        "tgn:2001473",
        "tgn:7012149",
        "tgn:7007709",
        "tgn:7029392"
    ],
    "tgn:id":2499864,
    "tgn:name":"McCoy Cove",
    "tgn:placetype":[
        "aat:300008761"
    ]
},
  "bbox": [],
  "geometry": {"coordinates":[-82.2833,35.6333],"type":"Point"}
}