{
  "id": 2413376,
  "type": "Feature",
  "properties": {
    "tgn:hierarchy":[
        "tgn:2413376",
        "tgn:1000001",
        "tgn:7012149",
        "tgn:2000638",
        "tgn:7007253",
        "tgn:7029392"
    ],
    "tgn:id":2413376,
    "tgn:name":"Iola",
    "tgn:placetype":[
        "aat:300008347"
    ]
},
  "bbox": [],
  "geometry": {"coordinates":[-95.3667,41.3167],"type":"Point"}
}