{
  "id": 2256615,
  "type": "Feature",
  "properties": {
    "tgn:hierarchy":[
        "tgn:2256615",
        "tgn:1000001",
        "tgn:7012149",
        "tgn:2001453",
        "tgn:7007566",
        "tgn:7029392"
    ],
    "tgn:id":2256615,
    "tgn:name":"Cordava, Canon",
    "tgn:placetype":[
        "aat:300008761"
    ]
},
  "bbox": [],
  "geometry": {"coordinates":[-104.3333,35.7167],"type":"Point"}
}