<<<<<<< HEAD
{
  "id": 2256615,
  "type": "Feature",
  "properties": {
    "tgn:hierarchy":[
        "tgn:2256615",
        "tgn:1000001",
        "tgn:7012149",
        "tgn:2001453",
        "tgn:7007566",
        "tgn:7029392"
    ],
    "tgn:id":2256615,
    "tgn:name":"Cordava, Canon",
    "tgn:placetype":[
        "aat:300008761"
    ]
},
  "bbox": [],
  "geometry": {"coordinates":[-104.3333,35.7167],"type":"Point"}
}
=======
{"geometry":{"type":"Point","coordinates":[-104.333300,35.716700]},"type":"Feature","properties":{"hierarchy":["tgn:2256615","tgn:1000001","tgn:7012149","tgn:2001453","tgn:7007566","tgn:7029392"],"placetype":["aat:300008761"],"id":2256615,"name:xx":"Cordava, Canon"}}
>>>>>>> 03f74aca74312dbeaf24d7e61306dd6a786dc3d0
