{
  "id": 2600248,
  "type": "Feature",
  "properties": {
    "tgn:hierarchy":[
        "tgn:2600248",
        "tgn:1000001",
        "tgn:7012149",
        "tgn:2001907",
        "tgn:7007825",
        "tgn:7029392"
    ],
    "tgn:id":2600248,
    "tgn:name":"Puckett Pond",
    "tgn:placetype":[
        "aat:300008680"
    ]
},
  "bbox": [],
  "geometry": {"coordinates":[-85.3833,36.2167],"type":"Point"}
}