{
  "id": 7536192,
  "type": "Feature",
  "properties": {
    "tgn:hierarchy":[
        "tgn:7536192",
        "tgn:7001242",
        "tgn:1001059",
        "tgn:7016833",
        "tgn:7029392"
    ],
    "tgn:id":7536192,
    "tgn:name:en":"Kafr ar R\u016bk",
    "tgn:placetype":[
        "aat:300008347"
    ]
},
  "bbox": [],
  "geometry": {"coordinates":[31.405209,30.829321],"type":"Point"}
}