{
  "id": 7483762,
  "type": "Feature",
  "properties": {
    "tgn:hierarchy":[
        "tgn:7483762",
        "tgn:1000004",
        "tgn:7001009",
        "tgn:1000141",
        "tgn:7029392"
    ],
    "tgn:id":7483762,
    "tgn:name":"Houkan",
    "tgn:placetype":[
        "aat:300008347"
    ]
},
  "bbox": [],
  "geometry": {"coordinates":[120.661944,24.355],"type":"Point"}
}