{
  "id": 2008354,
  "type": "Feature",
  "properties": {
    "tgn:hierarchy":[
        "tgn:2008354",
        "tgn:1000001",
        "tgn:7016172",
        "tgn:2000119",
        "tgn:7012149",
        "tgn:7029392"
    ],
    "tgn:id":2008354,
    "tgn:name":"Gobblers Point",
    "tgn:placetype":[
        "aat:300008347",
        "aat:300387210"
    ]
},
  "bbox": [],
  "geometry": {"coordinates":[-92.7667,35.4167],"type":"Point"}
}