{
  "id": 7214701,
  "type": "Feature",
  "properties": {
    "tgn:hierarchy":[
        "tgn:7214701",
        "tgn:1000003",
        "tgn:7003678",
        "tgn:7000084",
        "tgn:7029392"
    ],
    "tgn:id":7214701,
    "tgn:name":"Beuerbach",
    "tgn:placetype":[
        "aat:300008347"
    ]
},
  "bbox": [],
  "geometry": {"coordinates":[8.216667,50.283333],"type":"Point"}
}