{
  "id": 2780493,
  "type": "Feature",
  "properties": {
    "tgn:hierarchy":[
        "tgn:2780493",
        "tgn:1000001",
        "tgn:2000470",
        "tgn:7012149",
        "tgn:7007250",
        "tgn:7029392"
    ],
    "tgn:id":2780493,
    "tgn:name":"Wood Creek",
    "tgn:placetype":[
        "aat:300008706"
    ]
},
  "bbox": [],
  "geometry": {"coordinates":[-114.2833,44.4167],"type":"Point"}
}