<<<<<<< HEAD
{
  "id": 2400681,
  "type": "Feature",
  "properties": {
    "tgn:hierarchy":[
        "tgn:2400681",
        "tgn:1000001",
        "tgn:2002102",
        "tgn:7012149",
        "tgn:7007827",
        "tgn:7029392"
    ],
    "tgn:id":2400681,
    "tgn:name":"Horse Mountain Reservoir",
    "tgn:placetype":[
        "aat:300006191"
    ]
},
  "bbox": [],
  "geometry": {"coordinates":[-113.35,41.5667],"type":"Point"}
}
=======
{"geometry":{"type":"Point","coordinates":[-113.350000,41.566700]},"type":"Feature","properties":{"hierarchy":["tgn:2400681","tgn:1000001","tgn:2002102","tgn:7012149","tgn:7007827","tgn:7029392"],"placetype":["aat:300006191"],"id":2400681,"name:xx":"Horse Mountain Reservoir"}}
>>>>>>> 03f74aca74312dbeaf24d7e61306dd6a786dc3d0
