{
  "id": 7030122,
  "type": "Feature",
  "properties": {
    "tgn:hierarchy":[
        "tgn:7030122",
        "tgn:1003567",
        "tgn:7002445",
        "tgn:1000003",
        "tgn:7029507",
        "tgn:7008591",
        "tgn:7029392"
    ],
    "tgn:id":7030122,
    "tgn:name":"West Morton",
    "tgn:placetype":[
        "aat:300008347",
        "aat:300008372"
    ]
},
  "bbox": [],
  "geometry": {"coordinates":[-1.864,53.868],"type":"Point"}
}