{
  "id": 2290803,
  "type": "Feature",
  "properties": {
    "tgn:hierarchy":[
        "tgn:2290803",
        "tgn:1000001",
        "tgn:7012149",
        "tgn:2001312",
        "tgn:7007524",
        "tgn:7029392"
    ],
    "tgn:id":2290803,
    "tgn:name":"Dog Creek Reservoir",
    "tgn:placetype":[
        "aat:300006191"
    ]
},
  "bbox": [],
  "geometry": {"coordinates":[-106.8333,47.9833],"type":"Point"}
}