{
  "id": 2552419,
  "type": "Feature",
  "properties": {
    "tgn:hierarchy":[
        "tgn:2552419",
        "tgn:1000001",
        "tgn:2002324",
        "tgn:7012149",
        "tgn:7007922",
        "tgn:7029392"
    ],
    "tgn:id":2552419,
    "tgn:name":"Number Two Hundred One, Island",
    "tgn:placetype":[
        "aat:300008791"
    ]
},
  "bbox": [],
  "geometry": {"coordinates":[-90.8667,42.6667],"type":"Point"}
}