{
  "id": 1017749,
  "type": "Feature",
  "properties": {
    "tgn:hierarchy":[
        "tgn:1017749",
        "tgn:1000001",
        "tgn:7005596",
        "tgn:7005560",
        "tgn:7029392"
    ],
    "tgn:id":1017749,
    "tgn:name:es":"Las Flores",
    "tgn:placetype":[
        "aat:300008347"
    ]
},
  "bbox": [],
  "geometry": {"coordinates":[-93.779167,18.195833],"type":"Point"}
}