<<<<<<< HEAD
{
  "id": 7475430,
  "type": "Feature",
  "properties": {
    "tgn:hierarchy":[
        "tgn:7475430",
        "tgn:1000004",
        "tgn:7001014",
        "tgn:1000141",
        "tgn:7029392"
    ],
    "tgn:id":7475430,
    "tgn:name":"Caoling",
    "tgn:placetype":[
        "aat:300008347"
    ]
},
  "bbox": [],
  "geometry": {"coordinates":[120.693889,23.582778],"type":"Point"}
}
=======
{"geometry":{"type":"Point","coordinates":[120.693889,23.582778]},"type":"Feature","properties":{"hierarchy":["tgn:7475430","tgn:1000004","tgn:7001014","tgn:1000141","tgn:7029392"],"placetype":["aat:300008347"],"id":7475430,"name:xx":"Caoling"}}
>>>>>>> 03f74aca74312dbeaf24d7e61306dd6a786dc3d0
