{
  "id": 7475430,
  "type": "Feature",
  "properties": {
    "tgn:hierarchy":[
        "tgn:7475430",
        "tgn:1000004",
        "tgn:7001014",
        "tgn:1000141",
        "tgn:7029392"
    ],
    "tgn:id":7475430,
    "tgn:name":"Caoling",
    "tgn:placetype":[
        "aat:300008347"
    ]
},
  "bbox": [],
  "geometry": {"coordinates":[120.693889,23.582778],"type":"Point"}
}