{
  "id": 1116747,
  "type": "Feature",
  "properties": {
    "tgn:hierarchy":[
        "tgn:1116747",
        "tgn:7005685",
        "tgn:1000001",
        "tgn:7013154",
        "tgn:7029392"
    ],
    "tgn:id":1116747,
    "tgn:name":"Joseph, Lake",
    "tgn:placetype":[
        "aat:300008680"
    ]
},
  "bbox": [],
  "geometry": {"coordinates":[-79.7333,45.1667],"type":"Point"}
}