{
  "id": 2179719,
  "type": "Feature",
  "properties": {
    "tgn:hierarchy":[
        "tgn:2179719",
        "tgn:1000001",
        "tgn:7012149",
        "tgn:2001254",
        "tgn:7007523",
        "tgn:7029392"
    ],
    "tgn:id":2179719,
    "tgn:name":"Blanton Limonite Bank",
    "tgn:placetype":[
        "aat:300000390"
    ]
},
  "bbox": [],
  "geometry": {"coordinates":[-91.05,38.1667],"type":"Point"}
}