{
  "id": 2364628,
  "type": "Feature",
  "properties": {
    "tgn:hierarchy":[
        "tgn:2364628",
        "tgn:1000001",
        "tgn:7012149",
        "tgn:7014021",
        "tgn:7007709",
        "tgn:7029392"
    ],
    "tgn:id":2364628,
    "tgn:name":"Greenbriar",
    "tgn:placetype":[
        "aat:300008347"
    ]
},
  "bbox": [],
  "geometry": {"coordinates":[-80.75,35.25],"type":"Point"}
}