{
  "id": 2181382,
  "type": "Feature",
  "properties": {
    "tgn:hierarchy":[
        "tgn:2181382",
        "tgn:1000001",
        "tgn:2002102",
        "tgn:7012149",
        "tgn:7007827",
        "tgn:7029392"
    ],
    "tgn:id":2181382,
    "tgn:name":"Blue Creek Valley",
    "tgn:placetype":[
        "aat:300008761"
    ]
},
  "bbox": [],
  "geometry": {"coordinates":[-112.4333,41.95],"type":"Point"}
}