{
  "id": 7413876,
  "type": "Feature",
  "properties": {
    "tgn:hierarchy":[
        "tgn:7413876",
        "tgn:1000001",
        "tgn:7005596",
        "tgn:7005560",
        "tgn:7029392"
    ],
    "tgn:id":7413876,
    "tgn:name:es":"Canobanal Segunda Secci\u00f3n",
    "tgn:placetype":[
        "aat:300008347"
    ]
},
  "bbox": [],
  "geometry": {"coordinates":[-93.416667,17.6125],"type":"Point"}
}