{
  "id": 2062861,
  "type": "Feature",
  "properties": {
    "tgn:hierarchy":[
        "tgn:2062861",
        "tgn:1000001",
        "tgn:2001411",
        "tgn:7012149",
        "tgn:7007526",
        "tgn:7029392"
    ],
    "tgn:id":2062861,
    "tgn:name":"Deeth",
    "tgn:placetype":[
        "aat:300008347"
    ]
},
  "bbox": [],
  "geometry": {"coordinates":[-115.2667,41.05],"type":"Point"}
}