{
  "id": 1136709,
  "type": "Feature",
  "properties": {
    "tgn:hierarchy":[
        "tgn:1136709",
        "tgn:7002445",
        "tgn:1000003",
        "tgn:7008175",
        "tgn:7008591",
        "tgn:7029392"
    ],
    "tgn:id":1136709,
    "tgn:name":"Headley",
    "tgn:placetype":[
        "aat:300008347"
    ]
},
  "bbox": [],
  "geometry": {"coordinates":[-0.2667,51.2833],"type":"Point"}
}