{
  "id": 1009933,
  "type": "Feature",
  "properties": {
    "tgn:hierarchy":[
        "tgn:1009933",
        "tgn:1003500",
        "tgn:1000003",
        "tgn:7010380",
        "tgn:1000080",
        "tgn:7029392"
    ],
    "tgn:id":1009933,
    "tgn:name":"Cheradi, Isole",
    "tgn:placetype":[
        "aat:300008791",
        "aat:300386853"
    ]
},
  "bbox": [],
  "geometry": {"coordinates":[17.1525,40.441111],"type":"Point"}
}