<<<<<<< HEAD
{
  "id": 7350665,
  "type": "Feature",
  "properties": {
    "tgn:hierarchy":[
        "tgn:7350665",
        "tgn:1000001",
        "tgn:7005595",
        "tgn:7005560",
        "tgn:7029392"
    ],
    "tgn:id":7350665,
    "tgn:name":"Baimena",
    "tgn:placetype":[
        "aat:300008347"
    ]
},
  "bbox": [],
  "geometry": {"coordinates":[-108.293333,26.522778],"type":"Point"}
}
=======
{"geometry":{"type":"Point","coordinates":[-108.293333,26.522778]},"type":"Feature","properties":{"hierarchy":["tgn:7350665","tgn:1000001","tgn:7005595","tgn:7005560","tgn:7029392"],"placetype":["aat:300008347"],"id":7350665,"name:xx":"Baimena"}}
>>>>>>> 03f74aca74312dbeaf24d7e61306dd6a786dc3d0
