{
  "id": 7269262,
  "type": "Feature",
  "properties": {
    "tgn:hierarchy":[
        "tgn:7269262",
        "tgn:1000003",
        "tgn:7006951",
        "tgn:7016845",
        "tgn:7029392"
    ],
    "tgn:id":7269262,
    "tgn:name:nl":"Ockesnol",
    "tgn:placetype":[
        "aat:300008777"
    ]
},
  "bbox": [],
  "geometry": {"coordinates":[4.75,53.05],"type":"Point"}
}