{
  "id": 7591223,
  "type": "Feature",
  "properties": {
    "tgn:hierarchy":[
        "tgn:7591223",
        "tgn:1000004",
        "tgn:7000198",
        "tgn:7000799",
        "tgn:7029392"
    ],
    "tgn:id":7591223,
    "tgn:name:en":"Buni Karal",
    "tgn:placetype":[
        "aat:300008347"
    ]
},
  "bbox": [],
  "geometry": {"coordinates":[74.097222,33.197222],"type":"Point"}
}