{
  "id": 7066257,
  "type": "Feature",
  "properties": {
    "tgn:hierarchy":[
        "tgn:7066257",
        "tgn:7003669",
        "tgn:1000003",
        "tgn:7000084",
        "tgn:7029392"
    ],
    "tgn:id":7066257,
    "tgn:name":"Ummenhofen",
    "tgn:placetype":[
        "aat:300008347"
    ]
},
  "bbox": [],
  "geometry": {"coordinates":[10.733333,47.983333],"type":"Point"}
}