{
  "id": 7250271,
  "type": "Feature",
  "properties": {
    "tgn:hierarchy":[
        "tgn:7250271",
        "tgn:7007877",
        "tgn:1000003",
        "tgn:1000063",
        "tgn:4012014",
        "tgn:7029392"
    ],
    "tgn:id":7250271,
    "tgn:name":"Moulard",
    "tgn:placetype":[
        "aat:300008347"
    ]
},
  "bbox": [],
  "geometry": {"coordinates":[4.166667,50.166667],"type":"Point"}
}