{
  "id": 2243592,
  "type": "Feature",
  "properties": {
    "tgn:hierarchy":[
        "tgn:2243592",
        "tgn:1000001",
        "tgn:7012149",
        "tgn:1002661",
        "tgn:7007252",
        "tgn:7029392"
    ],
    "tgn:id":2243592,
    "tgn:name":"Clemans Smith Ditch",
    "tgn:placetype":[
        "aat:300006075"
    ]
},
  "bbox": [],
  "geometry": {"coordinates":[-86.15,40.95],"type":"Point"}
}