{
  "id": 1023903,
  "type": "Feature",
  "properties": {
    "tgn:hierarchy":[
        "tgn:1023903",
        "tgn:7002476",
        "tgn:1000050",
        "tgn:1000002",
        "tgn:7029392"
    ],
    "tgn:id":1023903,
    "tgn:name":"Pailitas",
    "tgn:placetype":[
        "aat:300008347"
    ]
},
  "bbox": [],
  "geometry": {"coordinates":[-73.6333,8.9667],"type":"Point"}
}