{
  "id": 2126023,
  "type": "Feature",
  "properties": {
    "tgn:hierarchy":[
        "tgn:2126023",
        "tgn:1000001",
        "tgn:7012149",
        "tgn:2001083",
        "tgn:7007521",
        "tgn:7029392"
    ],
    "tgn:id":2126023,
    "tgn:name":"Adams Valley",
    "tgn:placetype":[
        "aat:300008761"
    ]
},
  "bbox": [],
  "geometry": {"coordinates":[-91.8667,44.15],"type":"Point"}
}