{
  "id": 1056303,
  "type": "Feature",
  "properties": {
    "tgn:hierarchy":[
        "tgn:1056303",
        "tgn:1000003",
        "tgn:7011999",
        "tgn:7006660",
        "tgn:7029392"
    ],
    "tgn:id":1056303,
    "tgn:name":"Ladyzhin",
    "tgn:placetype":[
        "aat:300008347"
    ]
},
  "bbox": [],
  "geometry": {"coordinates":[29.25,48.6833],"type":"Point"}
}