{
  "id": 2213708,
  "type": "Feature",
  "properties": {
    "tgn:hierarchy":[
        "tgn:2213708",
        "tgn:7006450",
        "tgn:1000001",
        "tgn:7012149",
        "tgn:2000089",
        "tgn:7029392"
    ],
    "tgn:id":2213708,
    "tgn:name":"Cache Lake",
    "tgn:placetype":[
        "aat:300008680"
    ]
},
  "bbox": [],
  "geometry": {"coordinates":[-146.5833,66.7667],"type":"Point"}
}