{
  "id": 2753774,
  "type": "Feature",
  "properties": {
    "tgn:hierarchy":[
        "tgn:2753774",
        "tgn:1000001",
        "tgn:2002368",
        "tgn:7012149",
        "tgn:7007923",
        "tgn:7029392"
    ],
    "tgn:id":2753774,
    "tgn:name":"Watkins Creek",
    "tgn:placetype":[
        "aat:300008706"
    ]
},
  "bbox": [],
  "geometry": {"coordinates":[-106.2167,41.5833],"type":"Point"}
}