{
  "id": 7359185,
  "type": "Feature",
  "properties": {
    "tgn:hierarchy":[
        "tgn:7359185",
        "tgn:7005581",
        "tgn:1000001",
        "tgn:7005560",
        "tgn:7029392"
    ],
    "tgn:id":7359185,
    "tgn:name":"Pres\u00f3n de la Cruz",
    "tgn:placetype":[
        "aat:300006191"
    ]
},
  "bbox": [],
  "geometry": {"coordinates":[-106.583333,29.783333],"type":"Point"}
}