{
  "id": 7335056,
  "type": "Feature",
  "properties": {
    "tgn:hierarchy":[
        "tgn:7335056",
        "tgn:7002836",
        "tgn:7016622",
        "tgn:1000003",
        "tgn:1000095",
        "tgn:7029392"
    ],
    "tgn:id":7335056,
    "tgn:name":"Gotera, Punta",
    "tgn:placetype":[
        "aat:300386846"
    ]
},
  "bbox": [],
  "geometry": {"coordinates":[-16.333333,28.55],"type":"Point"}
}