{
  "id": 7412962,
  "type": "Feature",
  "properties": {
    "tgn:hierarchy":[
        "tgn:7412962",
        "tgn:1000001",
        "tgn:7005596",
        "tgn:7005560",
        "tgn:7029392"
    ],
    "tgn:id":7412962,
    "tgn:name:es":"El Plato, R\u00edo",
    "tgn:placetype":[
        "aat:300008699"
    ]
},
  "bbox": [],
  "geometry": {"coordinates":[-91.208333,17.416667],"type":"Point"}
}