{
  "id": 7374666,
  "type": "Feature",
  "properties": {
    "tgn:hierarchy":[
        "tgn:7374666",
        "tgn:1000001",
        "tgn:7005601",
        "tgn:7005560",
        "tgn:7029392"
    ],
    "tgn:id":7374666,
    "tgn:name":"La Mesilla",
    "tgn:placetype":[
        "aat:300008347"
    ]
},
  "bbox": [],
  "geometry": {"coordinates":[-101.466667,22.55],"type":"Point"}
}