{
  "id": 7112700,
  "type": "Feature",
  "properties": {
    "tgn:hierarchy":[
        "tgn:7112700",
        "tgn:7003669",
        "tgn:1000003",
        "tgn:7000084",
        "tgn:7029392"
    ],
    "tgn:id":7112700,
    "tgn:name":"R\u00f6gling",
    "tgn:placetype":[
        "aat:300008347"
    ]
},
  "bbox": [],
  "geometry": {"coordinates":[10.95,48.85],"type":"Point"}
}