{
  "id": 1112420,
  "type": "Feature",
  "properties": {
    "tgn:hierarchy":[
        "tgn:1112420",
        "tgn:1003455",
        "tgn:1000003",
        "tgn:7010380",
        "tgn:1000080",
        "tgn:7029392"
    ],
    "tgn:id":1112420,
    "tgn:name":"Manfred\u00f3nia, Golfo di",
    "tgn:placetype":[
        "aat:300132315"
    ]
},
  "bbox": [],
  "geometry": {"coordinates":[16.083333,41.583333],"type":"Point"}
}