{
  "id": 2491377,
  "type": "Feature",
  "properties": {
    "tgn:hierarchy":[
        "tgn:2491377",
        "tgn:1000001",
        "tgn:7012149",
        "tgn:2001209",
        "tgn:7007523",
        "tgn:7029392"
    ],
    "tgn:id":2491377,
    "tgn:name":"Maple Grove",
    "tgn:placetype":[
        "aat:300008347"
    ]
},
  "bbox": [],
  "geometry": {"coordinates":[-94.1167,37.25],"type":"Point"}
}