<<<<<<< HEAD
{
  "id": 2335857,
  "type": "Feature",
  "properties": {
    "tgn:hierarchy":[
        "tgn:2335857",
        "tgn:1000001",
        "tgn:7012149",
        "tgn:2001072",
        "tgn:7007521",
        "tgn:7029392"
    ],
    "tgn:id":2335857,
    "tgn:name":"Fosilen Lake",
    "tgn:placetype":[
        "aat:300008680"
    ]
},
  "bbox": [],
  "geometry": {"coordinates":[-93.3833,43.8833],"type":"Point"}
}
=======
{"geometry":{"type":"Point","coordinates":[-93.383300,43.883300]},"type":"Feature","properties":{"hierarchy":["tgn:2335857","tgn:1000001","tgn:7012149","tgn:2001072","tgn:7007521","tgn:7029392"],"placetype":["aat:300008680"],"id":2335857,"name:xx":"Fosilen Lake"}}
>>>>>>> 03f74aca74312dbeaf24d7e61306dd6a786dc3d0
