{
  "id": 7574415,
  "type": "Feature",
  "properties": {
    "tgn:hierarchy":[
        "tgn:7574415",
        "tgn:1000004",
        "tgn:7000198",
        "tgn:1001895",
        "tgn:7029392"
    ],
    "tgn:id":7574415,
    "tgn:name:en":"K\u0101tep\u016brna Nad\u012b",
    "tgn:placetype":[
        "aat:300008699"
    ]
},
  "bbox": [],
  "geometry": {"coordinates":[77.293767,20.848108],"type":"Point"}
}