<<<<<<< HEAD
{
  "id": 7480072,
  "type": "Feature",
  "properties": {
    "tgn:hierarchy":[
        "tgn:7480072",
        "tgn:1000004",
        "tgn:7490934",
        "tgn:1000141",
        "tgn:7029392"
    ],
    "tgn:id":7480072,
    "tgn:name":"Dagang Guoxiao",
    "tgn:placetype":[
        "aat:300006495"
    ]
},
  "bbox": [],
  "geometry": {"coordinates":[120.188056,23.013611],"type":"Point"}
}
=======
{"geometry":{"type":"Point","coordinates":[120.188056,23.013611]},"type":"Feature","properties":{"hierarchy":["tgn:7480072","tgn:1000004","tgn:7490934","tgn:1000141","tgn:7029392"],"placetype":["aat:300006495"],"id":7480072,"name:xx":"Dagang Guoxiao"}}
>>>>>>> 03f74aca74312dbeaf24d7e61306dd6a786dc3d0
