{
  "id": 7480072,
  "type": "Feature",
  "properties": {
    "tgn:hierarchy":[
        "tgn:7480072",
        "tgn:1000004",
        "tgn:7490934",
        "tgn:1000141",
        "tgn:7029392"
    ],
    "tgn:id":7480072,
    "tgn:name":"Dagang Guoxiao",
    "tgn:placetype":[
        "aat:300006495"
    ]
},
  "bbox": [],
  "geometry": {"coordinates":[120.188056,23.013611],"type":"Point"}
}