{
  "id": 2305163,
  "type": "Feature",
  "properties": {
    "tgn:hierarchy":[
        "tgn:2305163",
        "tgn:1000001",
        "tgn:7012149",
        "tgn:7007710",
        "tgn:7029392"
    ],
    "tgn:id":2305163,
    "tgn:name":"East Branch Perkiomen Creek",
    "tgn:placetype":[
        "aat:300008706"
    ]
},
  "bbox": [],
  "geometry": {"coordinates":[-75.2167,40.4167],"type":"Point"}
}