{
  "id": 7582069,
  "type": "Feature",
  "properties": {
    "tgn:hierarchy":[
        "tgn:7582069",
        "tgn:1000004",
        "tgn:7000198",
        "tgn:7016722",
        "tgn:7029392"
    ],
    "tgn:id":7582069,
    "tgn:name:en":"Jakhaura Railway Station",
    "tgn:placetype":[
        "aat:300007783"
    ]
},
  "bbox": [],
  "geometry": {"coordinates":[78.400768,24.87191],"type":"Point"}
}