{
  "id": 2539982,
  "type": "Feature",
  "properties": {
    "tgn:hierarchy":[
        "tgn:2539982",
        "tgn:1000001",
        "tgn:7012149",
        "tgn:2001288",
        "tgn:7007524",
        "tgn:7029392"
    ],
    "tgn:id":2539982,
    "tgn:name":"Newberry Ditch",
    "tgn:placetype":[
        "aat:300006075"
    ]
},
  "bbox": [],
  "geometry": {"coordinates":[-112.1167,45.0833],"type":"Point"}
}