{
  "id": 2409469,
  "type": "Feature",
  "properties": {
    "tgn:hierarchy":[
        "tgn:2409469",
        "tgn:1000001",
        "tgn:7012149",
        "tgn:1002681",
        "tgn:7007568",
        "tgn:7029392"
    ],
    "tgn:id":2409469,
    "tgn:name":"Ides Cove",
    "tgn:placetype":[
        "aat:300132316"
    ]
},
  "bbox": [],
  "geometry": {"coordinates":[-77.5333,43.2167],"type":"Point"}
}