{
  "id": 1065147,
  "type": "Feature",
  "properties": {
    "tgn:hierarchy":[
        "tgn:1065147",
        "tgn:1000003",
        "tgn:7006669",
        "tgn:7029392"
    ],
    "tgn:id":1065147,
    "tgn:name":"Novi Pazar",
    "tgn:placetype":[
        "aat:300387277",
        "aat:300008347",
        "aat:300000810",
        "aat:300387218",
        "aat:300008375",
        "aat:300387302"
    ]
},
  "bbox": [],
  "geometry": {"coordinates":[20.4833,43.15],"type":"Point"}
}