{
  "id": 1074423,
  "type": "Feature",
  "properties": {
    "tgn:hierarchy":[
        "tgn:1074423",
        "tgn:1000004",
        "tgn:7000198",
        "tgn:1001977",
        "tgn:7029392"
    ],
    "tgn:id":1074423,
    "tgn:name":"Amta",
    "tgn:placetype":[
        "aat:300008347"
    ]
},
  "bbox": [],
  "geometry": {"coordinates":[88.010394,22.583438],"type":"Point"}
}