{
  "id": 7337831,
  "type": "Feature",
  "properties": {
    "tgn:hierarchy":[
        "tgn:7337831",
        "tgn:7008912",
        "tgn:7030216",
        "tgn:1000003",
        "tgn:1000095",
        "tgn:7029392"
    ],
    "tgn:id":7337831,
    "tgn:name":"Cervi\u00e1",
    "tgn:placetype":[
        "aat:300008347"
    ]
},
  "bbox": [],
  "geometry": {"coordinates":[0.859764,41.42484],"type":"Point"}
}