{
  "id": 2619789,
  "type": "Feature",
  "properties": {
    "tgn:hierarchy":[
        "tgn:2619789",
        "tgn:1000001",
        "tgn:7012149",
        "tgn:2001309",
        "tgn:7007524",
        "tgn:7029392"
    ],
    "tgn:id":2619789,
    "tgn:name":"Rinker Creek",
    "tgn:placetype":[
        "aat:300008706"
    ]
},
  "bbox": [],
  "geometry": {"coordinates":[-112.6833,47.95],"type":"Point"}
}