{
  "id": 7398625,
  "type": "Feature",
  "properties": {
    "tgn:hierarchy":[
        "tgn:7398625",
        "tgn:1000001",
        "tgn:7005593",
        "tgn:7005560",
        "tgn:7029392"
    ],
    "tgn:id":7398625,
    "tgn:name":"Presa Paso de Tablas",
    "tgn:placetype":[
        "aat:300006191"
    ]
},
  "bbox": [],
  "geometry": {"coordinates":[-99.845833,20.541667],"type":"Point"}
}