{
  "id": 1139463,
  "type": "Feature",
  "properties": {
    "tgn:hierarchy":[
        "tgn:1139463",
        "tgn:1000004",
        "tgn:1001390",
        "tgn:1000111",
        "tgn:7029392"
    ],
    "tgn:id":1139463,
    "tgn:name":"Qingduizi",
    "tgn:placetype":[
        "aat:300008347"
    ]
},
  "bbox": [],
  "geometry": {"coordinates":[121.8667,41.45],"type":"Point"}
}