{
  "id": 2591637,
  "type": "Feature",
  "properties": {
    "tgn:hierarchy":[
        "tgn:2591637",
        "tgn:7019618",
        "tgn:1000001",
        "tgn:7012149",
        "tgn:7007564",
        "tgn:7029392"
    ],
    "tgn:id":2591637,
    "tgn:name":"Pond Brook",
    "tgn:placetype":[
        "aat:300008699"
    ]
},
  "bbox": [],
  "geometry": {"coordinates":[-72.4833,42.9167],"type":"Point"}
}