{
  "id": 7589283,
  "type": "Feature",
  "properties": {
    "tgn:hierarchy":[
        "tgn:7589283",
        "tgn:1000004",
        "tgn:7000198",
        "tgn:7000799",
        "tgn:7029392"
    ],
    "tgn:id":7589283,
    "tgn:name:en":"B\u0101gh-i-Zam\u0101n",
    "tgn:placetype":[
        "aat:300008347"
    ]
},
  "bbox": [],
  "geometry": {"coordinates":[74.775,34.272222],"type":"Point"}
}