{
  "id": 2527515,
  "type": "Feature",
  "properties": {
    "tgn:hierarchy":[
        "tgn:2527515",
        "tgn:1000001",
        "tgn:7012149",
        "tgn:2001136",
        "tgn:7007522",
        "tgn:7029392"
    ],
    "tgn:id":2527515,
    "tgn:name":"Mount Vernon",
    "tgn:placetype":[
        "aat:300008347"
    ]
},
  "bbox": [],
  "geometry": {"coordinates":[-89.0667,32.2333],"type":"Point"}
}