{
  "id": 1105044,
  "type": "Feature",
  "properties": {
    "tgn:hierarchy":[
        "tgn:1105044",
        "tgn:1000001",
        "tgn:7012149",
        "tgn:2000183",
        "tgn:7007157",
        "tgn:7029392"
    ],
    "tgn:id":1105044,
    "tgn:name":"Inyo, Mount",
    "tgn:placetype":[
        "aat:300008795"
    ]
},
  "bbox": [],
  "geometry": {"coordinates":[-117.9833,36.7333],"type":"Point"}
}