{
  "id": 2685296,
  "type": "Feature",
  "properties": {
    "tgn:hierarchy":[
        "tgn:2685296",
        "tgn:1000001",
        "tgn:2001268",
        "tgn:7012149",
        "tgn:7007524",
        "tgn:7029392"
    ],
    "tgn:id":2685296,
    "tgn:name":"Spotted Eagle Lake",
    "tgn:placetype":[
        "aat:300006191"
    ]
},
  "bbox": [],
  "geometry": {"coordinates":[-105.85,46.3833],"type":"Point"}
}