{
  "id": 7225927,
  "type": "Feature",
  "properties": {
    "tgn:hierarchy":[
        "tgn:7225927",
        "tgn:7011270",
        "tgn:7002674",
        "tgn:1000003",
        "tgn:1000074",
        "tgn:7029392"
    ],
    "tgn:id":7225927,
    "tgn:name":"P\u00e9ran Triovas\u00e1los",
    "tgn:placetype":[
        "aat:300008347"
    ]
},
  "bbox": [],
  "geometry": {"coordinates":[24.433333,36.733333],"type":"Point"}
}