{
  "id": 2035013,
  "type": "Feature",
  "properties": {
    "tgn:hierarchy":[
        "tgn:2035013",
        "tgn:1000001",
        "tgn:7012149",
        "tgn:2000658",
        "tgn:7007253",
        "tgn:7029392"
    ],
    "tgn:id":2035013,
    "tgn:name":"Joice",
    "tgn:placetype":[
        "aat:300008347"
    ]
},
  "bbox": [],
  "geometry": {"coordinates":[-93.45,43.35],"type":"Point"}
}