{
  "id": 7490055,
  "type": "Feature",
  "properties": {
    "tgn:hierarchy":[
        "tgn:7490055",
        "tgn:1000004",
        "tgn:7490934",
        "tgn:1000141",
        "tgn:7029392"
    ],
    "tgn:id":7490055,
    "tgn:name":"Dapaizhu",
    "tgn:placetype":[
        "aat:300008347"
    ]
},
  "bbox": [],
  "geometry": {"coordinates":[120.410833,23.368333],"type":"Point"}
}