{
  "id": 2178405,
  "type": "Feature",
  "properties": {
    "tgn:hierarchy":[
        "tgn:2178405",
        "tgn:1000001",
        "tgn:7012149",
        "tgn:1002565",
        "tgn:7007252",
        "tgn:7029392"
    ],
    "tgn:id":2178405,
    "tgn:name":"Blackman Lake",
    "tgn:placetype":[
        "aat:300008680"
    ]
},
  "bbox": [],
  "geometry": {"coordinates":[-85.2833,41.55],"type":"Point"}
}