<<<<<<< HEAD
{
  "id": 7023825,
  "type": "Feature",
  "properties": {
    "tgn:hierarchy":[
        "tgn:7023825",
        "tgn:7003168",
        "tgn:1000003",
        "tgn:7009760",
        "tgn:1000080",
        "tgn:7029392"
    ],
    "tgn:id":7023825,
    "tgn:name":"Castellina in Chianti",
    "tgn:placetype":[
        "aat:300008347"
    ]
},
  "bbox": [],
  "geometry": {"coordinates":[11.283333,43.466667],"type":"Point"}
}
=======
{"geometry":{"type":"Point","coordinates":[11.283333,43.466667]},"type":"Feature","properties":{"hierarchy":["tgn:7023825","tgn:7003168","tgn:1000003","tgn:7009760","tgn:1000080","tgn:7029392"],"placetype":["aat:300008347"],"id":7023825,"name:xx":"Castellina in Chianti"}}
>>>>>>> 03f74aca74312dbeaf24d7e61306dd6a786dc3d0
