{
  "id": 2135146,
  "type": "Feature",
  "properties": {
    "tgn:hierarchy":[
        "tgn:2135146",
        "tgn:1000001",
        "tgn:7012149",
        "tgn:2001721",
        "tgn:7007708",
        "tgn:7029392"
    ],
    "tgn:id":2135146,
    "tgn:name":"Anthony Butte",
    "tgn:placetype":[
        "aat:300008798"
    ]
},
  "bbox": [],
  "geometry": {"coordinates":[-118.2167,45.0333],"type":"Point"}
}