{
  "id": 1003812,
  "type": "Feature",
  "properties": {
    "tgn:hierarchy":[
        "tgn:1003812",
        "tgn:1000003",
        "tgn:7003685",
        "tgn:7000084",
        "tgn:7029392"
    ],
    "tgn:id":1003812,
    "tgn:name":"Oberlausitz",
    "tgn:placetype":[
        "aat:300387346"
    ]
},
  "bbox": [],
  "geometry": {"coordinates":[14.333333,51.166667],"type":"Point"}
}