{
  "id": 2444992,
  "type": "Feature",
  "properties": {
    "tgn:hierarchy":[
        "tgn:2444992",
        "tgn:1000001",
        "tgn:7012149",
        "tgn:7007522",
        "tgn:7029392"
    ],
    "tgn:id":2444992,
    "tgn:name":"Leitch Mill Branch",
    "tgn:placetype":[
        "aat:300008699"
    ]
},
  "bbox": [],
  "geometry": {"coordinates":[-88.3833,34.9167],"type":"Point"}
}