{
  "id": 7402731,
  "type": "Feature",
  "properties": {
    "tgn:hierarchy":[
        "tgn:7402731",
        "tgn:1000001",
        "tgn:1001937",
        "tgn:7005560",
        "tgn:7029392"
    ],
    "tgn:id":7402731,
    "tgn:name":"Molas",
    "tgn:placetype":[
        "aat:300008347"
    ]
},
  "bbox": [],
  "geometry": {"coordinates":[-86.7375,20.591667],"type":"Point"}
}