{
  "id": 2727285,
  "type": "Feature",
  "properties": {
    "tgn:hierarchy":[
        "tgn:2727285",
        "tgn:1000001",
        "tgn:7012149",
        "tgn:7007710",
        "tgn:7029392"
    ],
    "tgn:id":2727285,
    "tgn:name":"Tracy Run",
    "tgn:placetype":[
        "aat:300008699"
    ]
},
  "bbox": [],
  "geometry": {"coordinates":[-78.8667,41.9333],"type":"Point"}
}