{
  "id": 2539971,
  "type": "Feature",
  "properties": {
    "tgn:hierarchy":[
        "tgn:2539971",
        "tgn:2001172",
        "tgn:1000001",
        "tgn:7012149",
        "tgn:7007523",
        "tgn:7029392"
    ],
    "tgn:id":2539971,
    "tgn:name":"Newberry Branch",
    "tgn:placetype":[
        "aat:300008699"
    ]
},
  "bbox": [],
  "geometry": {"coordinates":[-94.1167,38.2167],"type":"Point"}
}