{
  "id": 7393116,
  "type": "Feature",
  "properties": {
    "tgn:hierarchy":[
        "tgn:7393116",
        "tgn:1000001",
        "tgn:7005591",
        "tgn:7005560",
        "tgn:7029392"
    ],
    "tgn:id":7393116,
    "tgn:name":"San Juan Bautista Valle Nacional",
    "tgn:placetype":[
        "aat:300008347"
    ]
},
  "bbox": [],
  "geometry": {"coordinates":[-96.316667,17.783333],"type":"Point"}
}