<<<<<<< HEAD
{
  "id": 2331227,
  "type": "Feature",
  "properties": {
    "tgn:hierarchy":[
        "tgn:2331227",
        "tgn:1000001",
        "tgn:2002107",
        "tgn:7012149",
        "tgn:7007827",
        "tgn:7029392"
    ],
    "tgn:id":2331227,
    "tgn:name":"Flat Top Mountain",
    "tgn:placetype":[
        "aat:300008798"
    ]
},
  "bbox": [],
  "geometry": {"coordinates":[-110.25,40.6167],"type":"Point"}
}
=======
{"geometry":{"type":"Point","coordinates":[-110.250000,40.616700]},"type":"Feature","properties":{"hierarchy":["tgn:2331227","tgn:1000001","tgn:2002107","tgn:7012149","tgn:7007827","tgn:7029392"],"placetype":["aat:300008798"],"id":2331227,"name:xx":"Flat Top Mountain"}}
>>>>>>> 03f74aca74312dbeaf24d7e61306dd6a786dc3d0
