{
  "id": 7330222,
  "type": "Feature",
  "properties": {
    "tgn:hierarchy":[
        "tgn:7330222",
        "tgn:7002827",
        "tgn:1000003",
        "tgn:7002789",
        "tgn:1000095",
        "tgn:7029392"
    ],
    "tgn:id":7330222,
    "tgn:name":"Hormilleja",
    "tgn:placetype":[
        "aat:300008347"
    ]
},
  "bbox": [],
  "geometry": {"coordinates":[-2.731549,42.45628],"type":"Point"}
}