<<<<<<< HEAD
{
  "id": 2331836,
  "type": "Feature",
  "properties": {
    "tgn:hierarchy":[
        "tgn:2331836",
        "tgn:1000001",
        "tgn:2002367",
        "tgn:7012149",
        "tgn:7007923",
        "tgn:7029392"
    ],
    "tgn:id":2331836,
    "tgn:name":"Fletcher Canyon",
    "tgn:placetype":[
        "aat:300008761"
    ]
},
  "bbox": [],
  "geometry": {"coordinates":[-105.9833,43.5833],"type":"Point"}
}
=======
{"geometry":{"type":"Point","coordinates":[-105.983300,43.583300]},"type":"Feature","properties":{"hierarchy":["tgn:2331836","tgn:1000001","tgn:2002367","tgn:7012149","tgn:7007923","tgn:7029392"],"placetype":["aat:300008761"],"id":2331836,"name:xx":"Fletcher Canyon"}}
>>>>>>> 03f74aca74312dbeaf24d7e61306dd6a786dc3d0
