{
  "id": 2331836,
  "type": "Feature",
  "properties": {
    "tgn:hierarchy":[
        "tgn:2331836",
        "tgn:1000001",
        "tgn:2002367",
        "tgn:7012149",
        "tgn:7007923",
        "tgn:7029392"
    ],
    "tgn:id":2331836,
    "tgn:name":"Fletcher Canyon",
    "tgn:placetype":[
        "aat:300008761"
    ]
},
  "bbox": [],
  "geometry": {"coordinates":[-105.9833,43.5833],"type":"Point"}
}