{
  "id": 2427421,
  "type": "Feature",
  "properties": {
    "tgn:hierarchy":[
        "tgn:2427421",
        "tgn:1000001",
        "tgn:7012149",
        "tgn:7007157",
        "tgn:1002859",
        "tgn:7029392"
    ],
    "tgn:id":2427421,
    "tgn:name":"Jordan Park",
    "tgn:placetype":[
        "aat:300008347"
    ]
},
  "bbox": [],
  "geometry": {"coordinates":[-122.45,37.7833],"type":"Point"}
}