{
  "id": 2138403,
  "type": "Feature",
  "properties": {
    "tgn:hierarchy":[
        "tgn:2138403",
        "tgn:1000001",
        "tgn:7012149",
        "tgn:2002377",
        "tgn:7007923",
        "tgn:7029392"
    ],
    "tgn:id":2138403,
    "tgn:name":"Asbestos Spring",
    "tgn:placetype":[
        "aat:300008697"
    ]
},
  "bbox": [],
  "geometry": {"coordinates":[-106.3167,42.7333],"type":"Point"}
}