<<<<<<< HEAD
{
  "id": 2409095,
  "type": "Feature",
  "properties": {
    "tgn:hierarchy":[
        "tgn:2409095",
        "tgn:1000001",
        "tgn:7012149",
        "tgn:2001461",
        "tgn:7007568",
        "tgn:7029392"
    ],
    "tgn:id":2409095,
    "tgn:name":"Ice Cave, The",
    "tgn:placetype":[
        "aat:300008746"
    ]
},
  "bbox": [],
  "geometry": {"coordinates":[-73.8333,44.1],"type":"Point"}
}
=======
{"geometry":{"type":"Point","coordinates":[-73.833300,44.100000]},"type":"Feature","properties":{"hierarchy":["tgn:2409095","tgn:1000001","tgn:7012149","tgn:2001461","tgn:7007568","tgn:7029392"],"placetype":["aat:300008746"],"id":2409095,"name:xx":"Ice Cave, The"}}
>>>>>>> 03f74aca74312dbeaf24d7e61306dd6a786dc3d0
