{
  "id": 7492390,
  "type": "Feature",
  "properties": {
    "tgn:hierarchy":[
        "tgn:7492390",
        "tgn:1000004",
        "tgn:7004300",
        "tgn:1000141",
        "tgn:7029392"
    ],
    "tgn:id":7492390,
    "tgn:name":"Tanbian",
    "tgn:placetype":[
        "aat:300008347"
    ]
},
  "bbox": [],
  "geometry": {"coordinates":[119.607397,23.595259],"type":"Point"}
}