<<<<<<< HEAD
{
  "id": 7052612,
  "type": "Feature",
  "properties": {
    "tgn:hierarchy":[
        "tgn:7052612",
        "tgn:1003478",
        "tgn:1000003",
        "tgn:7003120",
        "tgn:1000080",
        "tgn:7029392"
    ],
    "tgn:id":7052612,
    "tgn:name":"Invorio Inferiore",
    "tgn:placetype":[
        "aat:300008347"
    ]
},
  "bbox": [],
  "geometry": {"coordinates":[8.483333,45.75],"type":"Point"}
}
=======
{"geometry":{"type":"Point","coordinates":[8.483333,45.750000]},"type":"Feature","properties":{"hierarchy":["tgn:7052612","tgn:1003478","tgn:1000003","tgn:7003120","tgn:1000080","tgn:7029392"],"placetype":["aat:300008347"],"id":7052612,"name:xx":"Invorio Inferiore"}}
>>>>>>> 03f74aca74312dbeaf24d7e61306dd6a786dc3d0
