{
  "id": 2212509,
  "type": "Feature",
  "properties": {
    "tgn:hierarchy":[
        "tgn:2212509",
        "tgn:1000001",
        "tgn:7016102",
        "tgn:7012149",
        "tgn:7007516",
        "tgn:7029392"
    ],
    "tgn:id":2212509,
    "tgn:name":"Bynum Run",
    "tgn:placetype":[
        "aat:300008699"
    ]
},
  "bbox": [],
  "geometry": {"coordinates":[-76.3667,39.5667],"type":"Point"}
}