{
  "id": 2630521,
  "type": "Feature",
  "properties": {
    "tgn:hierarchy":[
        "tgn:2630521",
        "tgn:1000001",
        "tgn:7012149",
        "tgn:1003021",
        "tgn:7007252",
        "tgn:7029392"
    ],
    "tgn:id":2630521,
    "tgn:name":"Round Grove",
    "tgn:placetype":[
        "aat:300008347"
    ]
},
  "bbox": [],
  "geometry": {"coordinates":[-87.0167,40.5833],"type":"Point"}
}