{
  "id": 2442552,
  "type": "Feature",
  "properties": {
    "tgn:hierarchy":[
        "tgn:2442552",
        "tgn:1000001",
        "tgn:1002286",
        "tgn:7012149",
        "tgn:7007710",
        "tgn:7029392"
    ],
    "tgn:id":2442552,
    "tgn:name":"Kryder Hollow",
    "tgn:placetype":[
        "aat:300008761"
    ]
},
  "bbox": [],
  "geometry": {"coordinates":[-77.3333,41.1833],"type":"Point"}
}