{
  "id": 7264747,
  "type": "Feature",
  "properties": {
    "tgn:hierarchy":[
        "tgn:7264747",
        "tgn:1000003",
        "tgn:7003626",
        "tgn:7016845",
        "tgn:7029392"
    ],
    "tgn:id":7264747,
    "tgn:name:nl":"Kerkgracht",
    "tgn:placetype":[
        "aat:300006075"
    ]
},
  "bbox": [],
  "geometry": {"coordinates":[6.116667,52.683333],"type":"Point"}
}