{
  "id": 7432480,
  "type": "Feature",
  "properties": {
    "tgn:hierarchy":[
        "tgn:7432480",
        "tgn:1000001",
        "tgn:7005592",
        "tgn:7005560",
        "tgn:7029392"
    ],
    "tgn:id":7432480,
    "tgn:name":"Zacatepec de Bravo",
    "tgn:placetype":[
        "aat:300008347"
    ]
},
  "bbox": [],
  "geometry": {"coordinates":[-96.85,18.25],"type":"Point"}
}