{
  "id": 2776174,
  "type": "Feature",
  "properties": {
    "tgn:hierarchy":[
        "tgn:2776174",
        "tgn:1000001",
        "tgn:7012149",
        "tgn:1002472",
        "tgn:7007568",
        "tgn:7029392"
    ],
    "tgn:id":2776174,
    "tgn:name":"Wilt Brook",
    "tgn:placetype":[
        "aat:300008699"
    ]
},
  "bbox": [],
  "geometry": {"coordinates":[-75.0333,43.2833],"type":"Point"}
}