{
  "id": 7103371,
  "type": "Feature",
  "properties": {
    "tgn:hierarchy":[
        "tgn:7103371",
        "tgn:7003692",
        "tgn:1000003",
        "tgn:7000084",
        "tgn:7029392"
    ],
    "tgn:id":7103371,
    "tgn:name":"Roterberg",
    "tgn:placetype":[
        "aat:300008777"
    ]
},
  "bbox": [],
  "geometry": {"coordinates":[8.866667,49.233333],"type":"Point"}
}