{
  "id": 1006372,
  "type": "Feature",
  "properties": {
    "tgn:hierarchy":[
        "tgn:1006372",
        "tgn:7006247",
        "tgn:1000047",
        "tgn:7002456",
        "tgn:1000002",
        "tgn:7029392"
    ],
    "tgn:id":1006372,
    "tgn:name":"Bacuri, Ilha do",
    "tgn:placetype":[
        "aat:300008791"
    ]
},
  "bbox": [],
  "geometry": {"coordinates":[-49.7167,-2.9167],"type":"Point"}
}