{
  "id": 2780120,
  "type": "Feature",
  "properties": {
    "tgn:hierarchy":[
        "tgn:2780120",
        "tgn:1000001",
        "tgn:2001734",
        "tgn:7012149",
        "tgn:7007712",
        "tgn:7029392"
    ],
    "tgn:id":2780120,
    "tgn:name":"Wolfpit Run",
    "tgn:placetype":[
        "aat:300008699"
    ]
},
  "bbox": [],
  "geometry": {"coordinates":[-79.95,32.7333],"type":"Point"}
}