{
  "id": 7410876,
  "type": "Feature",
  "properties": {
    "tgn:hierarchy":[
        "tgn:7410876",
        "tgn:1000001",
        "tgn:7005590",
        "tgn:7005560",
        "tgn:7029392"
    ],
    "tgn:id":7410876,
    "tgn:name":"Querusco",
    "tgn:placetype":[
        "aat:300008347"
    ]
},
  "bbox": [],
  "geometry": {"coordinates":[-100.783333,18.472222],"type":"Point"}
}