{
  "id": 7551889,
  "type": "Feature",
  "properties": {
    "tgn:hierarchy":[
        "tgn:7551889",
        "tgn:1000004",
        "tgn:7000198",
        "tgn:7000799",
        "tgn:7029392"
    ],
    "tgn:id":7551889,
    "tgn:name:en":"Dorzong",
    "tgn:placetype":[
        "aat:300008347"
    ]
},
  "bbox": [],
  "geometry": {"coordinates":[77.033199,33.280744],"type":"Point"}
}