{
  "id": 2228983,
  "type": "Feature",
  "properties": {
    "tgn:hierarchy":[
        "tgn:2228983",
        "tgn:1000001",
        "tgn:7012149",
        "tgn:2002042",
        "tgn:7007826",
        "tgn:7029392"
    ],
    "tgn:id":2228983,
    "tgn:name":"Cedar Hollow",
    "tgn:placetype":[
        "aat:300008761"
    ]
},
  "bbox": [],
  "geometry": {"coordinates":[-98.6667,31.4333],"type":"Point"}
}