{
  "id": 7170168,
  "type": "Feature",
  "properties": {
    "tgn:hierarchy":[
        "tgn:7170168",
        "tgn:1000003",
        "tgn:7003676",
        "tgn:7000084",
        "tgn:7029392"
    ],
    "tgn:id":7170168,
    "tgn:name":"Hinter dem Hahnenkamp",
    "tgn:placetype":[
        "aat:300008347"
    ]
},
  "bbox": [],
  "geometry": {"coordinates":[8.333333,53.116667],"type":"Point"}
}