{
  "id": 2560422,
  "type": "Feature",
  "properties": {
    "tgn:hierarchy":[
        "tgn:2560422",
        "tgn:1000001",
        "tgn:7012149",
        "tgn:1002567",
        "tgn:7007240",
        "tgn:7029392"
    ],
    "tgn:id":2560422,
    "tgn:name":"Orchid Lake",
    "tgn:placetype":[
        "aat:300008680"
    ]
},
  "bbox": [],
  "geometry": {"coordinates":[-81.6667,28.85],"type":"Point"}
}