{
  "id": 2264492,
  "type": "Feature",
  "properties": {
    "tgn:hierarchy":[
        "tgn:2264492",
        "tgn:1000001",
        "tgn:7012149",
        "tgn:2001548",
        "tgn:7007709",
        "tgn:7029392"
    ],
    "tgn:id":2264492,
    "tgn:name":"Crabtree Creek",
    "tgn:placetype":[
        "aat:300008706"
    ]
},
  "bbox": [],
  "geometry": {"coordinates":[-78.8333,35.75],"type":"Point"}
}