{
  "id": 2276168,
  "type": "Feature",
  "properties": {
    "tgn:hierarchy":[
        "tgn:2276168",
        "tgn:1000001",
        "tgn:7012149",
        "tgn:2001291",
        "tgn:7007524",
        "tgn:7029392"
    ],
    "tgn:id":2276168,
    "tgn:name":"Dart Creek",
    "tgn:placetype":[
        "aat:300008706"
    ]
},
  "bbox": [],
  "geometry": {"coordinates":[-113.5667,47.5167],"type":"Point"}
}