{
  "id": 7125566,
  "type": "Feature",
  "properties": {
    "tgn:hierarchy":[
        "tgn:7125566",
        "tgn:7003669",
        "tgn:1000003",
        "tgn:7000084",
        "tgn:7029392"
    ],
    "tgn:id":7125566,
    "tgn:name":"Niedersonthofner See",
    "tgn:placetype":[
        "aat:300008680"
    ]
},
  "bbox": [],
  "geometry": {"coordinates":[10.266667,47.633333],"type":"Point"}
}