{
  "id": 7431102,
  "type": "Feature",
  "properties": {
    "tgn:hierarchy":[
        "tgn:7431102",
        "tgn:1000001",
        "tgn:7005595",
        "tgn:7005560",
        "tgn:7029392"
    ],
    "tgn:id":7431102,
    "tgn:name":"LLano de los L\u00f3pez",
    "tgn:placetype":[
        "aat:300008347"
    ]
},
  "bbox": [],
  "geometry": {"coordinates":[-108.733333,26.366667],"type":"Point"}
}