<<<<<<< HEAD
{
  "id": 2251110,
  "type": "Feature",
  "properties": {
    "tgn:hierarchy":[
        "tgn:2251110",
        "tgn:1000001",
        "tgn:7012149",
        "tgn:7016021",
        "tgn:7007568",
        "tgn:7029392"
    ],
    "tgn:id":2251110,
    "tgn:name":"Colvin Pond",
    "tgn:placetype":[
        "aat:300008680"
    ]
},
  "bbox": [],
  "geometry": {"coordinates":[-74.75,44.1],"type":"Point"}
}
=======
{"geometry":{"type":"Point","coordinates":[-74.750000,44.100000]},"type":"Feature","properties":{"hierarchy":["tgn:2251110","tgn:1000001","tgn:7012149","tgn:7016021","tgn:7007568","tgn:7029392"],"placetype":["aat:300008680"],"id":2251110,"name:xx":"Colvin Pond"}}
>>>>>>> 03f74aca74312dbeaf24d7e61306dd6a786dc3d0
