{
  "id": 2378937,
  "type": "Feature",
  "properties": {
    "tgn:hierarchy":[
        "tgn:2378937",
        "tgn:1000001",
        "tgn:7012149",
        "tgn:2001821",
        "tgn:7007713",
        "tgn:7029392"
    ],
    "tgn:id":2378937,
    "tgn:name":"Hart Table",
    "tgn:placetype":[
        "aat:300008798"
    ]
},
  "bbox": [],
  "geometry": {"coordinates":[-102.6333,43.7833],"type":"Point"}
}