<<<<<<< HEAD
{
  "id": 2150952,
  "type": "Feature",
  "properties": {
    "tgn:hierarchy":[
        "tgn:2150952",
        "tgn:1000001",
        "tgn:7012149",
        "tgn:7007158",
        "tgn:7029392"
    ],
    "tgn:id":2150952,
    "tgn:name":"Bassam Ridge",
    "tgn:placetype":[
        "aat:300266640"
    ]
},
  "bbox": [],
  "geometry": {"coordinates":[-105.9333,38.8167],"type":"Point"}
}
=======
{"geometry":{"type":"Point","coordinates":[-105.933300,38.816700]},"type":"Feature","properties":{"hierarchy":["tgn:2150952","tgn:1000001","tgn:7012149","tgn:7007158","tgn:7029392"],"placetype":["aat:300266640"],"id":2150952,"name:xx":"Bassam Ridge"}}
>>>>>>> 03f74aca74312dbeaf24d7e61306dd6a786dc3d0
