{
  "id": 2150952,
  "type": "Feature",
  "properties": {
    "tgn:hierarchy":[
        "tgn:2150952",
        "tgn:1000001",
        "tgn:7012149",
        "tgn:7007158",
        "tgn:7029392"
    ],
    "tgn:id":2150952,
    "tgn:name":"Bassam Ridge",
    "tgn:placetype":[
        "aat:300266640"
    ]
},
  "bbox": [],
  "geometry": {"coordinates":[-105.9333,38.8167],"type":"Point"}
}