{
  "id": 2683727,
  "type": "Feature",
  "properties": {
    "tgn:hierarchy":[
        "tgn:2683727",
        "tgn:2000919",
        "tgn:1000001",
        "tgn:7012149",
        "tgn:7007515",
        "tgn:7029392"
    ],
    "tgn:id":2683727,
    "tgn:name":"Spectacle Brook",
    "tgn:placetype":[
        "aat:300008699"
    ]
},
  "bbox": [],
  "geometry": {"coordinates":[-68.75,46.5333],"type":"Point"}
}