<<<<<<< HEAD
{
  "id": 7051462,
  "type": "Feature",
  "properties": {
    "tgn:hierarchy":[
        "tgn:7051462",
        "tgn:7003170",
        "tgn:1000003",
        "tgn:7003125",
        "tgn:1000080",
        "tgn:7029392"
    ],
    "tgn:id":7051462,
    "tgn:name":"Piagge",
    "tgn:placetype":[
        "aat:300008347"
    ]
},
  "bbox": [],
  "geometry": {"coordinates":[12.733333,43.25],"type":"Point"}
}
=======
{"geometry":{"type":"Point","coordinates":[12.733333,43.250000]},"type":"Feature","properties":{"hierarchy":["tgn:7051462","tgn:7003170","tgn:1000003","tgn:7003125","tgn:1000080","tgn:7029392"],"placetype":["aat:300008347"],"id":7051462,"name:xx":"Piagge"}}
>>>>>>> 03f74aca74312dbeaf24d7e61306dd6a786dc3d0
