{
  "id": 7276447,
  "type": "Feature",
  "properties": {
    "tgn:hierarchy":[
        "tgn:7276447",
        "tgn:1001702",
        "tgn:1000049",
        "tgn:1000002",
        "tgn:7029392"
    ],
    "tgn:id":7276447,
    "tgn:name":"Tarlton, Monte",
    "tgn:placetype":[
        "aat:300008795"
    ]
},
  "bbox": [],
  "geometry": {"coordinates":[-75.436944,-50.404444],"type":"Point"}
}