{
  "id": 7294083,
  "type": "Feature",
  "properties": {
    "tgn:hierarchy":[
        "tgn:7294083",
        "tgn:7002813",
        "tgn:7002758",
        "tgn:1000003",
        "tgn:1000095",
        "tgn:7029392"
    ],
    "tgn:id":7294083,
    "tgn:name":"Vaquera, Sierra",
    "tgn:placetype":[
        "aat:300008795"
    ]
},
  "bbox": [],
  "geometry": {"coordinates":[-5.45,36.95],"type":"Point"}
}