{
  "id": 2143696,
  "type": "Feature",
  "properties": {
    "tgn:hierarchy":[
        "tgn:2143696",
        "tgn:7006450",
        "tgn:1000001",
        "tgn:7012149",
        "tgn:2000088",
        "tgn:7029392"
    ],
    "tgn:id":2143696,
    "tgn:name":"Baird Glacier",
    "tgn:placetype":[
        "aat:300008835"
    ]
},
  "bbox": [],
  "geometry": {"coordinates":[-132.4167,57.2167],"type":"Point"}
}