{
  "id": 7015074,
  "type": "Feature",
  "properties": {
    "tgn:hierarchy":[
        "tgn:7015074",
        "tgn:1000001",
        "tgn:7004772",
        "tgn:7029392"
    ],
    "tgn:id":7015074,
    "tgn:name":"Dennery",
    "tgn:placetype":[
        "aat:300387064",
        "aat:300000762",
        "aat:300236112"
    ]
},
  "bbox": [],
  "geometry": {"coordinates":[-60.916,13.916],"type":"Point"}
}