{
  "id": 2139309,
  "type": "Feature",
  "properties": {
    "tgn:hierarchy":[
        "tgn:2139309",
        "tgn:1000001",
        "tgn:7012149",
        "tgn:1002350",
        "tgn:7007157",
        "tgn:7029392"
    ],
    "tgn:id":2139309,
    "tgn:name":"Aspen Creek",
    "tgn:placetype":[
        "aat:300008706"
    ]
},
  "bbox": [],
  "geometry": {"coordinates":[-120.0667,38.7833],"type":"Point"}
}