{
  "id": 1006744,
  "type": "Feature",
  "properties": {
    "tgn:hierarchy":[
        "tgn:1006744",
        "tgn:1000003",
        "tgn:7594273",
        "tgn:1000070",
        "tgn:7029392"
    ],
    "tgn:id":1006744,
    "tgn:name":"Cavallo, I",
    "tgn:placetype":[
        "aat:300008791"
    ]
},
  "bbox": [],
  "geometry": {"coordinates":[9.25,41.3667],"type":"Point"}
}