{
  "id": 2386472,
  "type": "Feature",
  "properties": {
    "tgn:hierarchy":[
        "tgn:2386472",
        "tgn:1000001",
        "tgn:7012149",
        "tgn:2002346",
        "tgn:7007922",
        "tgn:7029392"
    ],
    "tgn:id":2386472,
    "tgn:name":"Herby Lake",
    "tgn:placetype":[
        "aat:300008680"
    ]
},
  "bbox": [],
  "geometry": {"coordinates":[-92.6333,45.5833],"type":"Point"}
}