{
  "id": 2053815,
  "type": "Feature",
  "properties": {
    "tgn:hierarchy":[
        "tgn:2053815",
        "tgn:1000001",
        "tgn:7012149",
        "tgn:2001071",
        "tgn:7007521",
        "tgn:7029392"
    ],
    "tgn:id":2053815,
    "tgn:name":"Albany",
    "tgn:placetype":[
        "aat:300008347"
    ]
},
  "bbox": [],
  "geometry": {"coordinates":[-94.5667,45.6167],"type":"Point"}
}