{
  "id": 2369407,
  "type": "Feature",
  "properties": {
    "tgn:hierarchy":[
        "tgn:2369407",
        "tgn:1000001",
        "tgn:7012149",
        "tgn:2001497",
        "tgn:7007709",
        "tgn:7029392"
    ],
    "tgn:id":2369407,
    "tgn:name":"Gumstock Branch",
    "tgn:placetype":[
        "aat:300008699"
    ]
},
  "bbox": [],
  "geometry": {"coordinates":[-83.95,35.2333],"type":"Point"}
}