{
  "id": 2181182,
  "type": "Feature",
  "properties": {
    "tgn:hierarchy":[
        "tgn:2181182",
        "tgn:1000001",
        "tgn:7012149",
        "tgn:7007157",
        "tgn:2000190",
        "tgn:7029392"
    ],
    "tgn:id":2181182,
    "tgn:name":"Blue Canyon",
    "tgn:placetype":[
        "aat:300008761"
    ]
},
  "bbox": [],
  "geometry": {"coordinates":[-122.5833,39.9667],"type":"Point"}
}