{
  "id": 2291898,
  "type": "Feature",
  "properties": {
    "tgn:hierarchy":[
        "tgn:2291898",
        "tgn:1000001",
        "tgn:7012149",
        "tgn:2001715",
        "tgn:7007708",
        "tgn:7029392"
    ],
    "tgn:id":2291898,
    "tgn:name":"Dome, The",
    "tgn:placetype":[
        "aat:300008798"
    ]
},
  "bbox": [],
  "geometry": {"coordinates":[-120.8333,42.4667],"type":"Point"}
}