{
  "id": 2603326,
  "type": "Feature",
  "properties": {
    "tgn:hierarchy":[
        "tgn:2603326",
        "tgn:1000001",
        "tgn:7012149",
        "tgn:7007158",
        "tgn:2000247",
        "tgn:7029392"
    ],
    "tgn:id":2603326,
    "tgn:name":"Quartzite Creek",
    "tgn:placetype":[
        "aat:300008706"
    ]
},
  "bbox": [],
  "geometry": {"coordinates":[-107.5333,37.7167],"type":"Point"}
}