{
  "id": 7003182,
  "type": "Feature",
  "properties": {
    "tgn:hierarchy":[
        "tgn:7003182",
        "tgn:7003025",
        "tgn:1000003",
        "tgn:1000062",
        "tgn:7029392"
    ],
    "tgn:id":7003182,
    "tgn:name":"Erste Wiener Hochquellenleitung",
    "tgn:placetype":[
        "aat:300006165",
        "aat:300386965"
    ]
},
  "bbox": [],
  "geometry": {"coordinates":[16.2833,48.1667],"type":"Point"}
}