<<<<<<< HEAD
{
  "id": 2339885,
  "type": "Feature",
  "properties": {
    "tgn:hierarchy":[
        "tgn:2339885",
        "tgn:1000001",
        "tgn:7012149",
        "tgn:1002862",
        "tgn:7007920",
        "tgn:7029392"
    ],
    "tgn:id":2339885,
    "tgn:name":"Freeman Island",
    "tgn:placetype":[
        "aat:300008791"
    ]
},
  "bbox": [],
  "geometry": {"coordinates":[-122.95,48.6833],"type":"Point"}
}
=======
{"geometry":{"type":"Point","coordinates":[-122.950000,48.683300]},"type":"Feature","properties":{"hierarchy":["tgn:2339885","tgn:1000001","tgn:7012149","tgn:1002862","tgn:7007920","tgn:7029392"],"placetype":["aat:300008791"],"id":2339885,"name:xx":"Freeman Island"}}
>>>>>>> 03f74aca74312dbeaf24d7e61306dd6a786dc3d0
