{
  "id": 1067777,
  "type": "Feature",
  "properties": {
    "tgn:hierarchy":[
        "tgn:1067777",
        "tgn:1000004",
        "tgn:7002081",
        "tgn:1000111",
        "tgn:7029392"
    ],
    "tgn:id":1067777,
    "tgn:name":"Donghai",
    "tgn:placetype":[
        "aat:300008347"
    ]
},
  "bbox": [],
  "geometry": {"coordinates":[118.7667,34.5167],"type":"Point"}
}