{
  "id": 2609394,
  "type": "Feature",
  "properties": {
    "tgn:hierarchy":[
        "tgn:2609394",
        "tgn:7006450",
        "tgn:1000001",
        "tgn:7012149",
        "tgn:2000089",
        "tgn:7029392"
    ],
    "tgn:id":2609394,
    "tgn:name":"Ray River Hot Spring",
    "tgn:placetype":[
        "aat:300008697"
    ]
},
  "bbox": [],
  "geometry": {"coordinates":[-150.9167,65.95],"type":"Point"}
}