{
  "id": 2622740,
  "type": "Feature",
  "properties": {
    "tgn:hierarchy":[
        "tgn:2622740",
        "tgn:1000001",
        "tgn:7012149",
        "tgn:2001298",
        "tgn:7007524",
        "tgn:7029392"
    ],
    "tgn:id":2622740,
    "tgn:name":"Robinson Gulch",
    "tgn:placetype":[
        "aat:300008761"
    ]
},
  "bbox": [],
  "geometry": {"coordinates":[-112.95,46.3833],"type":"Point"}
}