{
  "id": 7106258,
  "type": "Feature",
  "properties": {
    "tgn:hierarchy":[
        "tgn:7106258",
        "tgn:7003669",
        "tgn:1000003",
        "tgn:7000084",
        "tgn:7029392"
    ],
    "tgn:id":7106258,
    "tgn:name":"Schalchern",
    "tgn:placetype":[
        "aat:300008347"
    ]
},
  "bbox": [],
  "geometry": {"coordinates":[11.566667,47.716667],"type":"Point"}
}