{
  "id": 2678712,
  "type": "Feature",
  "properties": {
    "tgn:hierarchy":[
        "tgn:2678712",
        "tgn:1000001",
        "tgn:7012149",
        "tgn:2002123",
        "tgn:7007827",
        "tgn:7029392"
    ],
    "tgn:id":2678712,
    "tgn:name":"South Fork Durse Canyon",
    "tgn:placetype":[
        "aat:300008761"
    ]
},
  "bbox": [],
  "geometry": {"coordinates":[-113.8833,39.9167],"type":"Point"}
}