{
  "id": 7183175,
  "type": "Feature",
  "properties": {
    "tgn:hierarchy":[
        "tgn:7183175",
        "tgn:7003669",
        "tgn:1000003",
        "tgn:7000084",
        "tgn:7029392"
    ],
    "tgn:id":7183175,
    "tgn:name":"Geh\u00e4u",
    "tgn:placetype":[
        "aat:300008863"
    ]
},
  "bbox": [],
  "geometry": {"coordinates":[10.816667,48.966667],"type":"Point"}
}