{
  "id": 2758550,
  "type": "Feature",
  "properties": {
    "tgn:hierarchy":[
        "tgn:2758550",
        "tgn:1000001",
        "tgn:7012149",
        "tgn:7007826",
        "tgn:7029392"
    ],
    "tgn:id":2758550,
    "tgn:name":"West Coffee Creek",
    "tgn:placetype":[
        "aat:300008706"
    ]
},
  "bbox": [],
  "geometry": {"coordinates":[-99.2667,33.8333],"type":"Point"}
}