{
  "id": 2374521,
  "type": "Feature",
  "properties": {
    "tgn:hierarchy":[
        "tgn:2374521",
        "tgn:1002247",
        "tgn:1000001",
        "tgn:7012149",
        "tgn:7007516",
        "tgn:7029392"
    ],
    "tgn:id":2374521,
    "tgn:name":"Hance Point",
    "tgn:placetype":[
        "aat:300008850"
    ]
},
  "bbox": [],
  "geometry": {"coordinates":[-75.9667,39.55],"type":"Point"}
}