<<<<<<< HEAD
{
  "id": 7028805,
  "type": "Feature",
  "properties": {
    "tgn:hierarchy":[
        "tgn:7028805",
        "tgn:7002445",
        "tgn:1000003",
        "tgn:7019057",
        "tgn:7008591",
        "tgn:7029392"
    ],
    "tgn:id":7028805,
    "tgn:name":"Bilton",
    "tgn:placetype":[
        "aat:300008347",
        "aat:300008372"
    ]
},
  "bbox": [],
  "geometry": {"coordinates":[-0.22,53.783],"type":"Point"}
}
=======
{"geometry":{"type":"Point","coordinates":[-0.220000,53.783000]},"type":"Feature","properties":{"hierarchy":["tgn:7028805","tgn:7002445","tgn:1000003","tgn:7019057","tgn:7008591","tgn:7029392"],"placetype":["aat:300008347","aat:300008372"],"id":7028805,"name:xx":"Bilton"}}
>>>>>>> 03f74aca74312dbeaf24d7e61306dd6a786dc3d0
