{
  "id": 1050001,
  "type": "Feature",
  "properties": {
    "tgn:hierarchy":[
        "tgn:1050001",
        "tgn:1000003",
        "tgn:1000443",
        "tgn:1000091",
        "tgn:7029392"
    ],
    "tgn:id":1050001,
    "tgn:name":"Agnita",
    "tgn:placetype":[
        "aat:300008347"
    ]
},
  "bbox": [],
  "geometry": {"coordinates":[24.6667,45.9833],"type":"Point"}
}