{
  "id": 2306704,
  "type": "Feature",
  "properties": {
    "tgn:hierarchy":[
        "tgn:2306704",
        "tgn:1000001",
        "tgn:7012149",
        "tgn:2000527",
        "tgn:7007251",
        "tgn:7029392"
    ],
    "tgn:id":2306704,
    "tgn:name":"East Fork Fox River",
    "tgn:placetype":[
        "aat:300008707"
    ]
},
  "bbox": [],
  "geometry": {"coordinates":[-87.9833,38.7667],"type":"Point"}
}