{
  "id": 2475027,
  "type": "Feature",
  "properties": {
    "tgn:hierarchy":[
        "tgn:2475027",
        "tgn:1000001",
        "tgn:7012149",
        "tgn:2000441",
        "tgn:7007248",
        "tgn:7029392"
    ],
    "tgn:id":2475027,
    "tgn:name":"Lower Yarbrough Lake",
    "tgn:placetype":[
        "aat:300006191"
    ]
},
  "bbox": [],
  "geometry": {"coordinates":[-82.7667,32.9667],"type":"Point"}
}