{
  "id": 2322814,
  "type": "Feature",
  "properties": {
    "tgn:hierarchy":[
        "tgn:2322814",
        "tgn:1000001",
        "tgn:7012149",
        "tgn:2001288",
        "tgn:7007524",
        "tgn:7029392"
    ],
    "tgn:id":2322814,
    "tgn:name":"Fan Mountain",
    "tgn:placetype":[
        "aat:300008798"
    ]
},
  "bbox": [],
  "geometry": {"coordinates":[-111.5167,45.2833],"type":"Point"}
}