{
  "id": 2764413,
  "type": "Feature",
  "properties": {
    "tgn:hierarchy":[
        "tgn:2764413",
        "tgn:1000001",
        "tgn:7012149",
        "tgn:7007158",
        "tgn:2000245",
        "tgn:7029392"
    ],
    "tgn:id":2764413,
    "tgn:name":"Whetstone Reservoir",
    "tgn:placetype":[
        "aat:300006191"
    ]
},
  "bbox": [],
  "geometry": {"coordinates":[-106.9333,40.3667],"type":"Point"}
}