{
  "id": 2134481,
  "type": "Feature",
  "properties": {
    "tgn:hierarchy":[
        "tgn:2134481",
        "tgn:1000001",
        "tgn:7012149",
        "tgn:7007252",
        "tgn:7029392"
    ],
    "tgn:id":2134481,
    "tgn:name":"Ansberry Bird Ditch",
    "tgn:placetype":[
        "aat:300006075"
    ]
},
  "bbox": [],
  "geometry": {"coordinates":[-86.3167,40.6333],"type":"Point"}
}