{
  "id": 2474576,
  "type": "Feature",
  "properties": {
    "tgn:hierarchy":[
        "tgn:2474576",
        "tgn:1000001",
        "tgn:7012149",
        "tgn:7007157",
        "tgn:1002894",
        "tgn:7029392"
    ],
    "tgn:id":2474576,
    "tgn:name":"Lower Salmon Lake",
    "tgn:placetype":[
        "aat:300006191"
    ]
},
  "bbox": [],
  "geometry": {"coordinates":[-120.6333,39.65],"type":"Point"}
}