<<<<<<< HEAD
{
  "id": 7474701,
  "type": "Feature",
  "properties": {
    "tgn:hierarchy":[
        "tgn:7474701",
        "tgn:1000004",
        "tgn:7001009",
        "tgn:1000141",
        "tgn:7029392"
    ],
    "tgn:id":7474701,
    "tgn:name":"Duojiatun Shan",
    "tgn:placetype":[
        "aat:300008798"
    ]
},
  "bbox": [],
  "geometry": {"coordinates":[121.381111,24.367778],"type":"Point"}
}
=======
{"geometry":{"type":"Point","coordinates":[121.381111,24.367778]},"type":"Feature","properties":{"hierarchy":["tgn:7474701","tgn:1000004","tgn:7001009","tgn:1000141","tgn:7029392"],"placetype":["aat:300008798"],"id":7474701,"name:xx":"Duojiatun Shan"}}
>>>>>>> 03f74aca74312dbeaf24d7e61306dd6a786dc3d0
