<<<<<<< HEAD
{
  "id": 2252772,
  "type": "Feature",
  "properties": {
    "tgn:hierarchy":[
        "tgn:2252772",
        "tgn:1000001",
        "tgn:2001410",
        "tgn:7012149",
        "tgn:7007526",
        "tgn:7029392"
    ],
    "tgn:id":2252772,
    "tgn:name":"Connoly Wash",
    "tgn:placetype":[
        "aat:300008699"
    ]
},
  "bbox": [],
  "geometry": {"coordinates":[-114.1,36.2333],"type":"Point"}
}
=======
{"geometry":{"type":"Point","coordinates":[-114.100000,36.233300]},"type":"Feature","properties":{"hierarchy":["tgn:2252772","tgn:1000001","tgn:2001410","tgn:7012149","tgn:7007526","tgn:7029392"],"placetype":["aat:300008699"],"id":2252772,"name:xx":"Connoly Wash"}}
>>>>>>> 03f74aca74312dbeaf24d7e61306dd6a786dc3d0
