{
  "id": 7420481,
  "type": "Feature",
  "properties": {
    "tgn:hierarchy":[
        "tgn:7420481",
        "tgn:7005584",
        "tgn:1000001",
        "tgn:7005560",
        "tgn:7029392"
    ],
    "tgn:id":7420481,
    "tgn:name":"Viborillas",
    "tgn:placetype":[
        "aat:300008347"
    ]
},
  "bbox": [],
  "geometry": {"coordinates":[-100.454167,21.454167],"type":"Point"}
}