{
  "id": 7440395,
  "type": "Feature",
  "properties": {
    "tgn:hierarchy":[
        "tgn:7440395",
        "tgn:7005580",
        "tgn:1000001",
        "tgn:7005560",
        "tgn:7029392"
    ],
    "tgn:id":7440395,
    "tgn:name":"San Luis",
    "tgn:placetype":[
        "aat:300008347"
    ]
},
  "bbox": [],
  "geometry": {"coordinates":[-92.25,15.033333],"type":"Point"}
}