{
  "id": 7205104,
  "type": "Feature",
  "properties": {
    "tgn:hierarchy":[
        "tgn:7205104",
        "tgn:1000003",
        "tgn:7003676",
        "tgn:7000084",
        "tgn:7029392"
    ],
    "tgn:id":7205104,
    "tgn:name":"Burweg",
    "tgn:placetype":[
        "aat:300008347"
    ]
},
  "bbox": [],
  "geometry": {"coordinates":[9.283333,53.633333],"type":"Point"}
}