{
  "id": 7560492,
  "type": "Feature",
  "properties": {
    "tgn:hierarchy":[
        "tgn:7560492",
        "tgn:1000004",
        "tgn:7000198",
        "tgn:7016722",
        "tgn:7029392"
    ],
    "tgn:id":7560492,
    "tgn:name:en":"Day\u0101li ka Nagla",
    "tgn:placetype":[
        "aat:300008347"
    ]
},
  "bbox": [],
  "geometry": {"coordinates":[79.246677,26.834024],"type":"Point"}
}