{
  "id": 7568389,
  "type": "Feature",
  "properties": {
    "tgn:hierarchy":[
        "tgn:7568389",
        "tgn:1001828",
        "tgn:1000004",
        "tgn:7000198",
        "tgn:7029392"
    ],
    "tgn:id":7568389,
    "tgn:name:en":"Parweda",
    "tgn:placetype":[
        "aat:300008347"
    ]
},
  "bbox": [],
  "geometry": {"coordinates":[78.0975,17.405278],"type":"Point"}
}