{
  "id": 2408609,
  "type": "Feature",
  "properties": {
    "tgn:hierarchy":[
        "tgn:2408609",
        "tgn:1000001",
        "tgn:7012149",
        "tgn:7007157",
        "tgn:1002791",
        "tgn:7029392"
    ],
    "tgn:id":2408609,
    "tgn:name":"Huysink Lake",
    "tgn:placetype":[
        "aat:300008680"
    ]
},
  "bbox": [],
  "geometry": {"coordinates":[-120.5333,39.2833],"type":"Point"}
}