<<<<<<< HEAD
{
  "id": 2408609,
  "type": "Feature",
  "properties": {
    "tgn:hierarchy":[
        "tgn:2408609",
        "tgn:1000001",
        "tgn:7012149",
        "tgn:7007157",
        "tgn:1002791",
        "tgn:7029392"
    ],
    "tgn:id":2408609,
    "tgn:name":"Huysink Lake",
    "tgn:placetype":[
        "aat:300008680"
    ]
},
  "bbox": [],
  "geometry": {"coordinates":[-120.5333,39.2833],"type":"Point"}
}
=======
{"geometry":{"type":"Point","coordinates":[-120.533300,39.283300]},"type":"Feature","properties":{"hierarchy":["tgn:2408609","tgn:1000001","tgn:7012149","tgn:7007157","tgn:1002791","tgn:7029392"],"placetype":["aat:300008680"],"id":2408609,"name:xx":"Huysink Lake"}}
>>>>>>> 03f74aca74312dbeaf24d7e61306dd6a786dc3d0
