{
  "id": 7418607,
  "type": "Feature",
  "properties": {
    "tgn:hierarchy":[
        "tgn:7418607",
        "tgn:1001835",
        "tgn:1000001",
        "tgn:7005560",
        "tgn:7029392"
    ],
    "tgn:id":7418607,
    "tgn:name":"Ancha, Ca\u00f1ada",
    "tgn:placetype":[
        "aat:300266554",
        "aat:300008699"
    ]
},
  "bbox": [],
  "geometry": {"coordinates":[-116.518889,32.098056],"type":"Point"}
}