{
  "id": 2074028,
  "type": "Feature",
  "properties": {
    "tgn:hierarchy":[
        "tgn:2074028",
        "tgn:1000001",
        "tgn:7012149",
        "tgn:2001491",
        "tgn:7007709",
        "tgn:7029392"
    ],
    "tgn:id":2074028,
    "tgn:name":"Charity",
    "tgn:placetype":[
        "aat:300008347",
        "aat:300387210"
    ]
},
  "bbox": [],
  "geometry": {"coordinates":[-77.9333,34.8167],"type":"Point"}
}