{
  "id": 7449832,
  "type": "Feature",
  "properties": {
    "tgn:hierarchy":[
        "tgn:7449832",
        "tgn:7002444",
        "tgn:1000003",
        "tgn:7019091",
        "tgn:7008591",
        "tgn:7029392"
    ],
    "tgn:id":7449832,
    "tgn:name:en":"Glen Burn",
    "tgn:placetype":[
        "aat:300008699"
    ]
},
  "bbox": [],
  "geometry": {"coordinates":[-4.866667,55.733333],"type":"Point"}
}