{
  "id": 7471128,
  "type": "Feature",
  "properties": {
    "tgn:hierarchy":[
        "tgn:7471128",
        "tgn:7468018",
        "tgn:1000004",
        "tgn:1000141",
        "tgn:7029392"
    ],
    "tgn:id":7471128,
    "tgn:name":"Xinpi",
    "tgn:placetype":[
        "aat:300008347"
    ]
},
  "bbox": [],
  "geometry": {"coordinates":[120.333056,23.486944],"type":"Point"}
}