<<<<<<< HEAD
{
  "id": 7354211,
  "type": "Feature",
  "properties": {
    "tgn:hierarchy":[
        "tgn:7354211",
        "tgn:1000001",
        "tgn:7005595",
        "tgn:7005560",
        "tgn:7029392"
    ],
    "tgn:id":7354211,
    "tgn:name":"Casas Nuevas",
    "tgn:placetype":[
        "aat:300008347"
    ]
},
  "bbox": [],
  "geometry": {"coordinates":[-108.466667,25.85],"type":"Point"}
}
=======
{"geometry":{"type":"Point","coordinates":[-108.466667,25.850000]},"type":"Feature","properties":{"hierarchy":["tgn:7354211","tgn:1000001","tgn:7005595","tgn:7005560","tgn:7029392"],"placetype":["aat:300008347"],"id":7354211,"name:xx":"Casas Nuevas"}}
>>>>>>> 03f74aca74312dbeaf24d7e61306dd6a786dc3d0
