{
  "id": 7134348,
  "type": "Feature",
  "properties": {
    "tgn:hierarchy":[
        "tgn:7134348",
        "tgn:7003669",
        "tgn:1000003",
        "tgn:7000084",
        "tgn:7029392"
    ],
    "tgn:id":7134348,
    "tgn:name":"M\u00fchlbach",
    "tgn:placetype":[
        "aat:300008699"
    ]
},
  "bbox": [],
  "geometry": {"coordinates":[10.616667,49.05],"type":"Point"}
}