{
  "id": 2308152,
  "type": "Feature",
  "properties": {
    "tgn:hierarchy":[
        "tgn:2308152",
        "tgn:1000001",
        "tgn:7012149",
        "tgn:2002081",
        "tgn:7007826",
        "tgn:7029392"
    ],
    "tgn:id":2308152,
    "tgn:name":"East Jim Ned Creek",
    "tgn:placetype":[
        "aat:300008706"
    ]
},
  "bbox": [],
  "geometry": {"coordinates":[-99.7333,32.2333],"type":"Point"}
}