{
  "id": 2562844,
  "type": "Feature",
  "properties": {
    "tgn:hierarchy":[
        "tgn:2562844",
        "tgn:1000001",
        "tgn:7006451",
        "tgn:2000091",
        "tgn:7012149",
        "tgn:7029392"
    ],
    "tgn:id":2562844,
    "tgn:name":"Overlook Ridge",
    "tgn:placetype":[
        "aat:300266640"
    ]
},
  "bbox": [],
  "geometry": {"coordinates":[-109.4333,32.1333],"type":"Point"}
}