{
  "id": 7381722,
  "type": "Feature",
  "properties": {
    "tgn:hierarchy":[
        "tgn:7381722",
        "tgn:1000001",
        "tgn:7005593",
        "tgn:7005560",
        "tgn:7029392"
    ],
    "tgn:id":7381722,
    "tgn:name":"Mesa del Le\u00f3n",
    "tgn:placetype":[
        "aat:300008347"
    ]
},
  "bbox": [],
  "geometry": {"coordinates":[-99.55,20.716667],"type":"Point"}
}