<<<<<<< HEAD
{
  "id": 2407260,
  "type": "Feature",
  "properties": {
    "tgn:hierarchy":[
        "tgn:2407260",
        "tgn:1000001",
        "tgn:2002144",
        "tgn:7012149",
        "tgn:7007919",
        "tgn:7029392"
    ],
    "tgn:id":2407260,
    "tgn:name":"Hunting Creek",
    "tgn:placetype":[
        "aat:300008706"
    ]
},
  "bbox": [],
  "geometry": {"coordinates":[-79.6167,37.15],"type":"Point"}
}
=======
{"geometry":{"type":"Point","coordinates":[-79.616700,37.150000]},"type":"Feature","properties":{"hierarchy":["tgn:2407260","tgn:1000001","tgn:2002144","tgn:7012149","tgn:7007919","tgn:7029392"],"placetype":["aat:300008706"],"id":2407260,"name:xx":"Hunting Creek"}}
>>>>>>> 03f74aca74312dbeaf24d7e61306dd6a786dc3d0
