<<<<<<< HEAD
{
  "id": 2338950,
  "type": "Feature",
  "properties": {
    "tgn:hierarchy":[
        "tgn:2338950",
        "tgn:1000001",
        "tgn:7012149",
        "tgn:7007254",
        "tgn:7029392"
    ],
    "tgn:id":2338950,
    "tgn:name":"Franklin Creek",
    "tgn:placetype":[
        "aat:300008706"
    ]
},
  "bbox": [],
  "geometry": {"coordinates":[-96.6,37.5],"type":"Point"}
}
=======
{"geometry":{"type":"Point","coordinates":[-96.600000,37.500000]},"type":"Feature","properties":{"hierarchy":["tgn:2338950","tgn:1000001","tgn:7012149","tgn:7007254","tgn:7029392"],"placetype":["aat:300008706"],"id":2338950,"name:xx":"Franklin Creek"}}
>>>>>>> 03f74aca74312dbeaf24d7e61306dd6a786dc3d0
