{
  "id": 7052136,
  "type": "Feature",
  "properties": {
    "tgn:hierarchy":[
        "tgn:7052136",
        "tgn:7003166",
        "tgn:1000003",
        "tgn:7009760",
        "tgn:1000080",
        "tgn:7029392"
    ],
    "tgn:id":7052136,
    "tgn:name":"La Casina",
    "tgn:placetype":[
        "aat:300008347"
    ]
},
  "bbox": [],
  "geometry": {"coordinates":[10.633333,43.416667],"type":"Point"}
}