{
  "id": 7093740,
  "type": "Feature",
  "properties": {
    "tgn:hierarchy":[
        "tgn:7093740",
        "tgn:7003692",
        "tgn:1000003",
        "tgn:7000084",
        "tgn:7029392"
    ],
    "tgn:id":7093740,
    "tgn:name":"Schwaben",
    "tgn:placetype":[
        "aat:300008863"
    ]
},
  "bbox": [],
  "geometry": {"coordinates":[8.616667,47.65],"type":"Point"}
}