{
  "id": 7384911,
  "type": "Feature",
  "properties": {
    "tgn:hierarchy":[
        "tgn:7384911",
        "tgn:1001835",
        "tgn:1000001",
        "tgn:7005560",
        "tgn:7029392"
    ],
    "tgn:id":7384911,
    "tgn:name":"Negro, Cerro",
    "tgn:placetype":[
        "aat:300008795"
    ]
},
  "bbox": [],
  "geometry": {"coordinates":[-115.766667,31.816667],"type":"Point"}
}