{
  "id": 7281466,
  "type": "Feature",
  "properties": {
    "tgn:hierarchy":[
        "tgn:7281466",
        "tgn:1001702",
        "tgn:1000049",
        "tgn:1000002",
        "tgn:7029392"
    ],
    "tgn:id":7281466,
    "tgn:name":"Segura, Caleta",
    "tgn:placetype":[
        "aat:300132317"
    ]
},
  "bbox": [],
  "geometry": {"coordinates":[-68.216667,-54.916667],"type":"Point"}
}