{
  "id": 7225000,
  "type": "Feature",
  "properties": {
    "tgn:hierarchy":[
        "tgn:7225000",
        "tgn:7002735",
        "tgn:7017076",
        "tgn:1000003",
        "tgn:1000074",
        "tgn:7029392"
    ],
    "tgn:id":7225000,
    "tgn:name":"Sto\u00fapas, \u00d3rmos",
    "tgn:placetype":[
        "aat:300132316"
    ]
},
  "bbox": [],
  "geometry": {"coordinates":[22.25,36.85],"type":"Point"}
}