{
  "id": 2243458,
  "type": "Feature",
  "properties": {
    "tgn:hierarchy":[
        "tgn:2243458",
        "tgn:1000001",
        "tgn:7012149",
        "tgn:2001029",
        "tgn:7007521",
        "tgn:7029392"
    ],
    "tgn:id":2243458,
    "tgn:name":"Clearwater Lake",
    "tgn:placetype":[
        "aat:300008680"
    ]
},
  "bbox": [],
  "geometry": {"coordinates":[-93.4667,47.3833],"type":"Point"}
}