{
  "id": 7400830,
  "type": "Feature",
  "properties": {
    "tgn:hierarchy":[
        "tgn:7400830",
        "tgn:1000001",
        "tgn:7005599",
        "tgn:7005560",
        "tgn:7029392"
    ],
    "tgn:id":7400830,
    "tgn:name":"Palma Sola",
    "tgn:placetype":[
        "aat:300008347"
    ]
},
  "bbox": [],
  "geometry": {"coordinates":[-96.916667,19.890278],"type":"Point"}
}