{
  "id": 2283793,
  "type": "Feature",
  "properties": {
    "tgn:hierarchy":[
        "tgn:2283793",
        "tgn:1000001",
        "tgn:7012149",
        "tgn:7014589",
        "tgn:7007515",
        "tgn:7029392"
    ],
    "tgn:id":2283793,
    "tgn:name":"Denbow Neck",
    "tgn:placetype":[
        "aat:300008850"
    ]
},
  "bbox": [],
  "geometry": {"coordinates":[-67.0833,44.8667],"type":"Point"}
}