{
  "id": 7275474,
  "type": "Feature",
  "properties": {
    "tgn:hierarchy":[
        "tgn:7275474",
        "tgn:1001705",
        "tgn:1000049",
        "tgn:1000002",
        "tgn:7029392"
    ],
    "tgn:id":7275474,
    "tgn:name":"Troncos, Cerro",
    "tgn:placetype":[
        "aat:300008795"
    ]
},
  "bbox": [],
  "geometry": {"coordinates":[-70.55,-35.483333],"type":"Point"}
}