{
  "id": 2024044,
  "type": "Feature",
  "properties": {
    "tgn:hierarchy":[
        "tgn:2024044",
        "tgn:1000001",
        "tgn:7012149",
        "tgn:2000378",
        "tgn:7007248",
        "tgn:7029392"
    ],
    "tgn:id":2024044,
    "tgn:name":"Rentz",
    "tgn:placetype":[
        "aat:300008347"
    ]
},
  "bbox": [],
  "geometry": {"coordinates":[-82.9833,32.3833],"type":"Point"}
}