{
  "id": 2481099,
  "type": "Feature",
  "properties": {
    "tgn:hierarchy":[
        "tgn:2481099",
        "tgn:1000001",
        "tgn:7012149",
        "tgn:1002742",
        "tgn:7007920",
        "tgn:7029392"
    ],
    "tgn:id":2481099,
    "tgn:name":"Lamb Creek",
    "tgn:placetype":[
        "aat:300008706"
    ]
},
  "bbox": [],
  "geometry": {"coordinates":[-120.2167,48.7333],"type":"Point"}
}