{
  "id": 7235528,
  "type": "Feature",
  "properties": {
    "tgn:hierarchy":[
        "tgn:7235528",
        "tgn:7002735",
        "tgn:7017076",
        "tgn:1000003",
        "tgn:1000074",
        "tgn:7029392"
    ],
    "tgn:id":7235528,
    "tgn:name":"Filipp\u00e1kion",
    "tgn:placetype":[
        "aat:300008347"
    ]
},
  "bbox": [],
  "geometry": {"coordinates":[21.933333,37.016667],"type":"Point"}
}