{
  "id": 2654858,
  "type": "Feature",
  "properties": {
    "tgn:hierarchy":[
        "tgn:2654858",
        "tgn:1000001",
        "tgn:7012149",
        "tgn:2001027",
        "tgn:7007521",
        "tgn:7029392"
    ],
    "tgn:id":2654858,
    "tgn:name":"Shallow Lake",
    "tgn:placetype":[
        "aat:300008680"
    ]
},
  "bbox": [],
  "geometry": {"coordinates":[-94.8667,46.9667],"type":"Point"}
}