{
  "id": 2083693,
  "type": "Feature",
  "properties": {
    "tgn:hierarchy":[
        "tgn:2083693",
        "tgn:1000001",
        "tgn:2001646",
        "tgn:7012149",
        "tgn:7007707",
        "tgn:7029392"
    ],
    "tgn:id":2083693,
    "tgn:name":"North Enid",
    "tgn:placetype":[
        "aat:300008347"
    ]
},
  "bbox": [],
  "geometry": {"coordinates":[-97.8667,36.4333],"type":"Point"}
}