{
  "id": 7574952,
  "type": "Feature",
  "properties": {
    "tgn:hierarchy":[
        "tgn:7574952",
        "tgn:1000004",
        "tgn:7000198",
        "tgn:7016788",
        "tgn:7029392"
    ],
    "tgn:id":7574952,
    "tgn:name:en":"Kush\u0101lpura",
    "tgn:placetype":[
        "aat:300008347"
    ]
},
  "bbox": [],
  "geometry": {"coordinates":[73.95636,26.096823],"type":"Point"}
}