<<<<<<< HEAD
{
  "id": 2766695,
  "type": "Feature",
  "properties": {
    "tgn:hierarchy":[
        "tgn:2766695",
        "tgn:1000001",
        "tgn:7016172",
        "tgn:7012149",
        "tgn:2000168",
        "tgn:7029392"
    ],
    "tgn:id":2766695,
    "tgn:name":"White Oak Mountain",
    "tgn:placetype":[
        "aat:300008798"
    ]
},
  "bbox": [],
  "geometry": {"coordinates":[-93.9333,34.9667],"type":"Point"}
}
=======
{"geometry":{"type":"Point","coordinates":[-93.933300,34.966700]},"type":"Feature","properties":{"hierarchy":["tgn:2766695","tgn:1000001","tgn:7016172","tgn:7012149","tgn:2000168","tgn:7029392"],"placetype":["aat:300008798"],"id":2766695,"name:xx":"White Oak Mountain"}}
>>>>>>> 03f74aca74312dbeaf24d7e61306dd6a786dc3d0
