<<<<<<< HEAD
{
  "id": 2407120,
  "type": "Feature",
  "properties": {
    "tgn:hierarchy":[
        "tgn:2407120",
        "tgn:1000001",
        "tgn:7012149",
        "tgn:7007709",
        "tgn:7029392"
    ],
    "tgn:id":2407120,
    "tgn:name":"Hunters Creek",
    "tgn:placetype":[
        "aat:300008706"
    ]
},
  "bbox": [],
  "geometry": {"coordinates":[-77.0333,34.8333],"type":"Point"}
}
=======
{"geometry":{"type":"Point","coordinates":[-77.033300,34.833300]},"type":"Feature","properties":{"hierarchy":["tgn:2407120","tgn:1000001","tgn:7012149","tgn:7007709","tgn:7029392"],"placetype":["aat:300008706"],"id":2407120,"name:xx":"Hunters Creek"}}
>>>>>>> 03f74aca74312dbeaf24d7e61306dd6a786dc3d0
