{
  "id": 2112678,
  "type": "Feature",
  "properties": {
    "tgn:hierarchy":[
        "tgn:2112678",
        "tgn:1000001",
        "tgn:7012149",
        "tgn:2002191",
        "tgn:7007919",
        "tgn:7029392"
    ],
    "tgn:id":2112678,
    "tgn:name":"Lick Skillet",
    "tgn:placetype":[
        "aat:300008347",
        "aat:300387210"
    ]
},
  "bbox": [],
  "geometry": {"coordinates":[-81.7833,36.8833],"type":"Point"}
}