<<<<<<< HEAD
{
  "id": 7480747,
  "type": "Feature",
  "properties": {
    "tgn:hierarchy":[
        "tgn:7480747",
        "tgn:1000004",
        "tgn:7471332",
        "tgn:1000141",
        "tgn:7029392"
    ],
    "tgn:id":7480747,
    "tgn:name":"Xilang",
    "tgn:placetype":[
        "aat:300008347"
    ]
},
  "bbox": [],
  "geometry": {"coordinates":[121.256111,24.781667],"type":"Point"}
}
=======
{"geometry":{"type":"Point","coordinates":[121.256111,24.781667]},"type":"Feature","properties":{"hierarchy":["tgn:7480747","tgn:1000004","tgn:7471332","tgn:1000141","tgn:7029392"],"placetype":["aat:300008347"],"id":7480747,"name:xx":"Xilang"}}
>>>>>>> 03f74aca74312dbeaf24d7e61306dd6a786dc3d0
