{
  "id": 7169010,
  "type": "Feature",
  "properties": {
    "tgn:hierarchy":[
        "tgn:7169010",
        "tgn:1000003",
        "tgn:7003687",
        "tgn:7000084",
        "tgn:7029392"
    ],
    "tgn:id":7169010,
    "tgn:name":"Harms-Berg",
    "tgn:placetype":[
        "aat:300008777"
    ]
},
  "bbox": [],
  "geometry": {"coordinates":[10.866667,51.75],"type":"Point"}
}