{
  "id": 1063319,
  "type": "Feature",
  "properties": {
    "tgn:hierarchy":[
        "tgn:1063319",
        "tgn:1000003",
        "tgn:7003773",
        "tgn:1000097",
        "tgn:7029392"
    ],
    "tgn:id":1063319,
    "tgn:name":"Lit",
    "tgn:placetype":[
        "aat:300008347"
    ]
},
  "bbox": [],
  "geometry": {"coordinates":[14.8333,63.3333],"type":"Point"}
}