<<<<<<< HEAD
{
  "id": 7058719,
  "type": "Feature",
  "properties": {
    "tgn:hierarchy":[
        "tgn:7058719",
        "tgn:7005023",
        "tgn:1000003",
        "tgn:7003237",
        "tgn:1000080",
        "tgn:7029392"
    ],
    "tgn:id":7058719,
    "tgn:name":"Alm\u00e8",
    "tgn:placetype":[
        "aat:300008347"
    ]
},
  "bbox": [],
  "geometry": {"coordinates":[9.616667,45.733333],"type":"Point"}
}
=======
{"geometry":{"type":"Point","coordinates":[9.616667,45.733333]},"type":"Feature","properties":{"hierarchy":["tgn:7058719","tgn:7005023","tgn:1000003","tgn:7003237","tgn:1000080","tgn:7029392"],"placetype":["aat:300008347"],"id":7058719,"name:xx":"Alm\u00e8"}}
>>>>>>> 03f74aca74312dbeaf24d7e61306dd6a786dc3d0
