{
  "id": 7356040,
  "type": "Feature",
  "properties": {
    "tgn:hierarchy":[
        "tgn:7356040",
        "tgn:1000001",
        "tgn:1001960",
        "tgn:7005560",
        "tgn:7029392"
    ],
    "tgn:id":7356040,
    "tgn:name":"Chihuis, Cerro",
    "tgn:placetype":[
        "aat:300008795"
    ]
},
  "bbox": [],
  "geometry": {"coordinates":[-111.033333,31.266667],"type":"Point"}
}