{
  "id": 2442841,
  "type": "Feature",
  "properties": {
    "tgn:hierarchy":[
        "tgn:2442841",
        "tgn:7006450",
        "tgn:1000001",
        "tgn:2000071",
        "tgn:7012149",
        "tgn:7029392"
    ],
    "tgn:id":2442841,
    "tgn:name":"Kulukak Point",
    "tgn:placetype":[
        "aat:300008850"
    ]
},
  "bbox": [],
  "geometry": {"coordinates":[-159.6333,58.8333],"type":"Point"}
}