{
  "id": 2389256,
  "type": "Feature",
  "properties": {
    "tgn:hierarchy":[
        "tgn:2389256",
        "tgn:1000001",
        "tgn:7012149",
        "tgn:2002005",
        "tgn:7007826",
        "tgn:7029392"
    ],
    "tgn:id":2389256,
    "tgn:name":"Hideaway Tank",
    "tgn:placetype":[
        "aat:300006191"
    ]
},
  "bbox": [],
  "geometry": {"coordinates":[-105.9833,31.5667],"type":"Point"}
}