{
  "id": 7131367,
  "type": "Feature",
  "properties": {
    "tgn:hierarchy":[
        "tgn:7131367",
        "tgn:7000096",
        "tgn:1000003",
        "tgn:7000084",
        "tgn:7029392"
    ],
    "tgn:id":7131367,
    "tgn:name":"Mittelbrack",
    "tgn:placetype":[
        "aat:300008680"
    ]
},
  "bbox": [],
  "geometry": {"coordinates":[11.75,52.983333],"type":"Point"}
}