{
  "id": 7510808,
  "type": "Feature",
  "properties": {
    "tgn:hierarchy":[
        "tgn:7510808",
        "tgn:1009227",
        "tgn:7001866",
        "tgn:1000226",
        "tgn:1000006",
        "tgn:7029392"
    ],
    "tgn:id":7510808,
    "tgn:name:en":"Somerton",
    "tgn:placetype":[
        "aat:300008347"
    ]
},
  "bbox": [],
  "geometry": {"coordinates":[171.916667,-43.75],"type":"Point"}
}