{
  "id": 2290723,
  "type": "Feature",
  "properties": {
    "tgn:hierarchy":[
        "tgn:2290723",
        "tgn:2000453",
        "tgn:1000001",
        "tgn:7012149",
        "tgn:7007250",
        "tgn:7029392"
    ],
    "tgn:id":2290723,
    "tgn:name":"Dog Creek",
    "tgn:placetype":[
        "aat:300008706"
    ]
},
  "bbox": [],
  "geometry": {"coordinates":[-116.2667,44.5167],"type":"Point"}
}