{
  "id": 7320708,
  "type": "Feature",
  "properties": {
    "tgn:hierarchy":[
        "tgn:7320708",
        "tgn:7016598",
        "tgn:1000049",
        "tgn:1000002",
        "tgn:7029392"
    ],
    "tgn:id":7320708,
    "tgn:name":"Bandurria del Norte, Punta",
    "tgn:placetype":[
        "aat:300386846"
    ]
},
  "bbox": [],
  "geometry": {"coordinates":[-70.266667,-22.416667],"type":"Point"}
}