{
  "id": 1015740,
  "type": "Feature",
  "properties": {
    "tgn:hierarchy":[
        "tgn:1015740",
        "tgn:7005685",
        "tgn:1000001",
        "tgn:7005804",
        "tgn:7029392"
    ],
    "tgn:id":1015740,
    "tgn:name":"Sainte-Clothilde",
    "tgn:placetype":[
        "aat:300008347"
    ]
},
  "bbox": [],
  "geometry": {"coordinates":[-72.2667,45.9667],"type":"Point"}
}