{
  "id": 7189209,
  "type": "Feature",
  "properties": {
    "tgn:hierarchy":[
        "tgn:7189209",
        "tgn:1000003",
        "tgn:7003682",
        "tgn:7000084",
        "tgn:7029392"
    ],
    "tgn:id":7189209,
    "tgn:name":"Eppelsheim",
    "tgn:placetype":[
        "aat:300008347"
    ]
},
  "bbox": [],
  "geometry": {"coordinates":[8.165278,49.705556],"type":"Point"}
}