<<<<<<< HEAD
{
  "id": 2156517,
  "type": "Feature",
  "properties": {
    "tgn:hierarchy":[
        "tgn:2156517",
        "tgn:2002130",
        "tgn:1000001",
        "tgn:7012149",
        "tgn:7007828",
        "tgn:7029392"
    ],
    "tgn:id":2156517,
    "tgn:name":"Beartrap Island",
    "tgn:placetype":[
        "aat:300008791"
    ]
},
  "bbox": [],
  "geometry": {"coordinates":[-73.1833,43.8333],"type":"Point"}
}
=======
{"geometry":{"type":"Point","coordinates":[-73.183300,43.833300]},"type":"Feature","properties":{"hierarchy":["tgn:2156517","tgn:2002130","tgn:1000001","tgn:7012149","tgn:7007828","tgn:7029392"],"placetype":["aat:300008791"],"id":2156517,"name:xx":"Beartrap Island"}}
>>>>>>> 03f74aca74312dbeaf24d7e61306dd6a786dc3d0
