{
  "id": 7014451,
  "type": "Feature",
  "properties": {
    "tgn:hierarchy":[
        "tgn:7014451",
        "tgn:1000001",
        "tgn:7012149",
        "tgn:7007157",
        "tgn:1002684",
        "tgn:7029392"
    ],
    "tgn:id":7014451,
    "tgn:name":"Salinas",
    "tgn:placetype":[
        "aat:300387277",
        "aat:300008347",
        "aat:300008416",
        "aat:300008389",
        "aat:300387308"
    ]
},
  "bbox": [],
  "geometry": {"coordinates":[-121.65,36.6667],"type":"Point"}
}