{
  "id": 7470034,
  "type": "Feature",
  "properties": {
    "tgn:hierarchy":[
        "tgn:7470034",
        "tgn:7498210",
        "tgn:1000004",
        "tgn:1000141",
        "tgn:7029392"
    ],
    "tgn:id":7470034,
    "tgn:name":"Zhongwokou",
    "tgn:placetype":[
        "aat:300008347"
    ]
},
  "bbox": [],
  "geometry": {"coordinates":[119.966667,26.216667],"type":"Point"}
}