{
  "id": 7467248,
  "type": "Feature",
  "properties": {
    "tgn:hierarchy":[
        "tgn:7467248",
        "tgn:7002445",
        "tgn:1000003",
        "tgn:7008165",
        "tgn:7008591",
        "tgn:7029392"
    ],
    "tgn:id":7467248,
    "tgn:name:en":"Big Harcar",
    "tgn:placetype":[
        "aat:300008791"
    ]
},
  "bbox": [],
  "geometry": {"coordinates":[-1.616667,55.633333],"type":"Point"}
}