{
  "id": 2162098,
  "type": "Feature",
  "properties": {
    "tgn:hierarchy":[
        "tgn:2162098",
        "tgn:1000001",
        "tgn:7012149",
        "tgn:2000784",
        "tgn:7007255",
        "tgn:7029392"
    ],
    "tgn:id":2162098,
    "tgn:name":"Belmar Branch",
    "tgn:placetype":[
        "aat:300008699"
    ]
},
  "bbox": [],
  "geometry": {"coordinates":[-88.2167,37.35],"type":"Point"}
}