{
  "id": 2177491,
  "type": "Feature",
  "properties": {
    "tgn:hierarchy":[
        "tgn:2177491",
        "tgn:1000001",
        "tgn:7012149",
        "tgn:1002392",
        "tgn:7007157",
        "tgn:7029392"
    ],
    "tgn:id":2177491,
    "tgn:name":"Black Rock Reservoir",
    "tgn:placetype":[
        "aat:300006191"
    ]
},
  "bbox": [],
  "geometry": {"coordinates":[-119.0167,36.9167],"type":"Point"}
}