{
  "id": 7590024,
  "type": "Feature",
  "properties": {
    "tgn:hierarchy":[
        "tgn:7590024",
        "tgn:1000004",
        "tgn:7000198",
        "tgn:7000799",
        "tgn:7029392"
    ],
    "tgn:id":7590024,
    "tgn:name:en":"Mehr",
    "tgn:placetype":[
        "aat:300008347"
    ]
},
  "bbox": [],
  "geometry": {"coordinates":[73.994444,34.655556],"type":"Point"}
}