{
  "id": 2460318,
  "type": "Feature",
  "properties": {
    "tgn:hierarchy":[
        "tgn:2460318",
        "tgn:1000001",
        "tgn:7012149",
        "tgn:7007251",
        "tgn:7029392"
    ],
    "tgn:id":2460318,
    "tgn:name":"Little Saline River",
    "tgn:placetype":[
        "aat:300008707"
    ]
},
  "bbox": [],
  "geometry": {"coordinates":[-88.7333,37.5333],"type":"Point"}
}