{
  "id": 2303293,
  "type": "Feature",
  "properties": {
    "tgn:hierarchy":[
        "tgn:2303293",
        "tgn:1000001",
        "tgn:7012149",
        "tgn:2001613",
        "tgn:7007706",
        "tgn:7029392"
    ],
    "tgn:id":2303293,
    "tgn:name":"Eagle Claw, Lake",
    "tgn:placetype":[
        "aat:300006191"
    ]
},
  "bbox": [],
  "geometry": {"coordinates":[-82.45,39.65],"type":"Point"}
}