{
  "id": 2616725,
  "type": "Feature",
  "properties": {
    "tgn:hierarchy":[
        "tgn:2616725",
        "tgn:1000001",
        "tgn:7012149",
        "tgn:2001519",
        "tgn:7007709",
        "tgn:7029392"
    ],
    "tgn:id":2616725,
    "tgn:name":"Rich Branch",
    "tgn:placetype":[
        "aat:300008699"
    ]
},
  "bbox": [],
  "geometry": {"coordinates":[-82.2167,36.1167],"type":"Point"}
}