{
  "id": 7551408,
  "type": "Feature",
  "properties": {
    "tgn:hierarchy":[
        "tgn:7551408",
        "tgn:1000004",
        "tgn:7000198",
        "tgn:7016788",
        "tgn:7029392"
    ],
    "tgn:id":7551408,
    "tgn:name:en":"Bolia Kal\u0101n",
    "tgn:placetype":[
        "aat:300008347"
    ]
},
  "bbox": [],
  "geometry": {"coordinates":[75.927237,24.261895],"type":"Point"}
}