{
  "id": 2062382,
  "type": "Feature",
  "properties": {
    "tgn:hierarchy":[
        "tgn:2062382",
        "tgn:1000001",
        "tgn:2001366",
        "tgn:7012149",
        "tgn:7007525",
        "tgn:7029392"
    ],
    "tgn:id":2062382,
    "tgn:name":"Martin",
    "tgn:placetype":[
        "aat:300387016"
    ]
},
  "bbox": [],
  "geometry": {"coordinates":[-101.6833,41.25],"type":"Point"}
}