{
  "id": 7301901,
  "type": "Feature",
  "properties": {
    "tgn:hierarchy":[
        "tgn:7301901",
        "tgn:7002807",
        "tgn:1000003",
        "tgn:7003837",
        "tgn:1000095",
        "tgn:7029392"
    ],
    "tgn:id":7301901,
    "tgn:name":"Mejar\u00e1, Puerto",
    "tgn:placetype":[
        "aat:300259572"
    ]
},
  "bbox": [],
  "geometry": {"coordinates":[-5.45,38.683333],"type":"Point"}
}