{
  "id": 7281989,
  "type": "Feature",
  "properties": {
    "tgn:hierarchy":[
        "tgn:7281989",
        "tgn:1001699",
        "tgn:1000049",
        "tgn:1000002",
        "tgn:7029392"
    ],
    "tgn:id":7281989,
    "tgn:name":"San Pedro, Punta",
    "tgn:placetype":[
        "aat:300386846"
    ]
},
  "bbox": [],
  "geometry": {"coordinates":[-73.916667,-40.933333],"type":"Point"}
}