{
  "id": 2315852,
  "type": "Feature",
  "properties": {
    "tgn:hierarchy":[
        "tgn:2315852",
        "tgn:1000001",
        "tgn:2001182",
        "tgn:7012149",
        "tgn:7007523",
        "tgn:7029392"
    ],
    "tgn:id":2315852,
    "tgn:name":"Elm Branch",
    "tgn:placetype":[
        "aat:300008699"
    ]
},
  "bbox": [],
  "geometry": {"coordinates":[-94.3167,38.55],"type":"Point"}
}