<<<<<<< HEAD
{
  "id": 2767416,
  "type": "Feature",
  "properties": {
    "tgn:hierarchy":[
        "tgn:2767416",
        "tgn:1000001",
        "tgn:7012149",
        "tgn:2000959",
        "tgn:7007520",
        "tgn:7029392"
    ],
    "tgn:id":2767416,
    "tgn:name":"White Star",
    "tgn:placetype":[
        "aat:300008347"
    ]
},
  "bbox": [],
  "geometry": {"coordinates":[-84.35,43.9667],"type":"Point"}
}
=======
{"geometry":{"type":"Point","coordinates":[-84.350000,43.966700]},"type":"Feature","properties":{"hierarchy":["tgn:2767416","tgn:1000001","tgn:7012149","tgn:2000959","tgn:7007520","tgn:7029392"],"placetype":["aat:300008347"],"id":2767416,"name:xx":"White Star"}}
>>>>>>> 03f74aca74312dbeaf24d7e61306dd6a786dc3d0
