{
  "id": 2395287,
  "type": "Feature",
  "properties": {
    "tgn:hierarchy":[
        "tgn:2395287",
        "tgn:1000001",
        "tgn:1002216",
        "tgn:7012149",
        "tgn:7007706",
        "tgn:7029392"
    ],
    "tgn:id":2395287,
    "tgn:name":"Holiday Lake",
    "tgn:placetype":[
        "aat:300006191"
    ]
},
  "bbox": [],
  "geometry": {"coordinates":[-84.65,39.4333],"type":"Point"}
}