{
  "id": 2450074,
  "type": "Feature",
  "properties": {
    "tgn:hierarchy":[
        "tgn:2450074",
        "tgn:2000456",
        "tgn:1000001",
        "tgn:7012149",
        "tgn:7007250",
        "tgn:7029392"
    ],
    "tgn:id":2450074,
    "tgn:name":"Lindstrom Peak",
    "tgn:placetype":[
        "aat:300008798"
    ]
},
  "bbox": [],
  "geometry": {"coordinates":[-116.55,47.2333],"type":"Point"}
}