{
  "id": 7590956,
  "type": "Feature",
  "properties": {
    "tgn:hierarchy":[
        "tgn:7590956",
        "tgn:1000004",
        "tgn:7000198",
        "tgn:7000799",
        "tgn:7029392"
    ],
    "tgn:id":7590956,
    "tgn:name:en":"Chande Chak",
    "tgn:placetype":[
        "aat:300167671"
    ]
},
  "bbox": [],
  "geometry": {"coordinates":[74.6375,32.758333],"type":"Point"}
}