{
  "id": 1096734,
  "type": "Feature",
  "properties": {
    "tgn:hierarchy":[
        "tgn:1096734",
        "tgn:7000490",
        "tgn:1000006",
        "tgn:7001834",
        "tgn:7029392"
    ],
    "tgn:id":1096734,
    "tgn:name":"Deakin",
    "tgn:placetype":[
        "aat:300008347"
    ]
},
  "bbox": [],
  "geometry": {"coordinates":[128.95,-30.75],"type":"Point"}
}