{
  "id": 2490975,
  "type": "Feature",
  "properties": {
    "tgn:hierarchy":[
        "tgn:2490975",
        "tgn:1000001",
        "tgn:7012149",
        "tgn:7029392"
    ],
    "tgn:id":2490975,
    "tgn:name":"Manti-La Sal National Forest-La Sal Division",
    "tgn:placetype":[
        "aat:300008863"
    ]
},
  "bbox": [],
  "geometry": {"coordinates":[-109.4833,37.8667],"type":"Point"}
}