{
  "id": 1109012,
  "type": "Feature",
  "properties": {
    "tgn:hierarchy":[
        "tgn:1109012",
        "tgn:1000715",
        "tgn:1000001",
        "tgn:7005554",
        "tgn:7029392"
    ],
    "tgn:id":1109012,
    "tgn:name":"Entre R\u00edos, Cordillera",
    "tgn:placetype":[
        "aat:300386831"
    ]
},
  "bbox": [],
  "geometry": {"coordinates":[-85.6167,14.0833],"type":"Point"}
}