{
  "id": 2683142,
  "type": "Feature",
  "properties": {
    "tgn:hierarchy":[
        "tgn:2683142",
        "tgn:1000001",
        "tgn:7012149",
        "tgn:7007157",
        "tgn:2000188",
        "tgn:7029392"
    ],
    "tgn:id":2683142,
    "tgn:name":"Spanish Gulch",
    "tgn:placetype":[
        "aat:300008761"
    ]
},
  "bbox": [],
  "geometry": {"coordinates":[-122.5333,40.6667],"type":"Point"}
}