{
  "id": 2150857,
  "type": "Feature",
  "properties": {
    "tgn:hierarchy":[
        "tgn:2150857",
        "tgn:1000001",
        "tgn:7012149",
        "tgn:1002424",
        "tgn:7007706",
        "tgn:7029392"
    ],
    "tgn:id":2150857,
    "tgn:name":"Bass Lake",
    "tgn:placetype":[
        "aat:300008680"
    ]
},
  "bbox": [],
  "geometry": {"coordinates":[-84.05,39.8167],"type":"Point"}
}