<<<<<<< HEAD
{
  "id": 2150857,
  "type": "Feature",
  "properties": {
    "tgn:hierarchy":[
        "tgn:2150857",
        "tgn:1000001",
        "tgn:7012149",
        "tgn:1002424",
        "tgn:7007706",
        "tgn:7029392"
    ],
    "tgn:id":2150857,
    "tgn:name":"Bass Lake",
    "tgn:placetype":[
        "aat:300008680"
    ]
},
  "bbox": [],
  "geometry": {"coordinates":[-84.05,39.8167],"type":"Point"}
}
=======
{"geometry":{"type":"Point","coordinates":[-84.050000,39.816700]},"type":"Feature","properties":{"hierarchy":["tgn:2150857","tgn:1000001","tgn:7012149","tgn:1002424","tgn:7007706","tgn:7029392"],"placetype":["aat:300008680"],"id":2150857,"name:xx":"Bass Lake"}}
>>>>>>> 03f74aca74312dbeaf24d7e61306dd6a786dc3d0
