<<<<<<< HEAD
{
  "id": 2151078,
  "type": "Feature",
  "properties": {
    "tgn:hierarchy":[
        "tgn:2151078",
        "tgn:1000001",
        "tgn:7012149",
        "tgn:1002994",
        "tgn:7007708",
        "tgn:7029392"
    ],
    "tgn:id":2151078,
    "tgn:name":"Bastion Reservoir",
    "tgn:placetype":[
        "aat:300006191"
    ]
},
  "bbox": [],
  "geometry": {"coordinates":[-122.9,45.5],"type":"Point"}
}
=======
{"geometry":{"type":"Point","coordinates":[-122.900000,45.500000]},"type":"Feature","properties":{"hierarchy":["tgn:2151078","tgn:1000001","tgn:7012149","tgn:1002994","tgn:7007708","tgn:7029392"],"placetype":["aat:300006191"],"id":2151078,"name:xx":"Bastion Reservoir"}}
>>>>>>> 03f74aca74312dbeaf24d7e61306dd6a786dc3d0
