{
  "id": 2588855,
  "type": "Feature",
  "properties": {
    "tgn:hierarchy":[
        "tgn:2588855",
        "tgn:2232884",
        "tgn:1000001",
        "tgn:1002344",
        "tgn:7012149",
        "tgn:7007517",
        "tgn:7029392"
    ],
    "tgn:id":2588855,
    "tgn:name":"Pocha Pond",
    "tgn:placetype":[
        "aat:300008680"
    ]
},
  "bbox": [],
  "geometry": {"coordinates":[-70.45,41.35],"type":"Point"}
}