{
  "id": 7416162,
  "type": "Feature",
  "properties": {
    "tgn:hierarchy":[
        "tgn:7416162",
        "tgn:1000001",
        "tgn:7005591",
        "tgn:7005560",
        "tgn:7029392"
    ],
    "tgn:id":7416162,
    "tgn:name:es":"Tres Picos, Sierra",
    "tgn:placetype":[
        "aat:300008795"
    ]
},
  "bbox": [],
  "geometry": {"coordinates":[-94.528333,17.125],"type":"Point"}
}