{
  "id": 7494239,
  "type": "Feature",
  "properties": {
    "tgn:hierarchy":[
        "tgn:7494239",
        "tgn:1000004",
        "tgn:7492971",
        "tgn:1000141",
        "tgn:7029392"
    ],
    "tgn:id":7494239,
    "tgn:name":"Huanliuqiu Feng",
    "tgn:placetype":[
        "aat:300008777"
    ]
},
  "bbox": [],
  "geometry": {"coordinates":[120.665709,22.879864],"type":"Point"}
}