{
  "id": 2575083,
  "type": "Feature",
  "properties": {
    "tgn:hierarchy":[
        "tgn:2575083",
        "tgn:1000001",
        "tgn:7012149",
        "tgn:7013961",
        "tgn:7029392"
    ],
    "tgn:id":2575083,
    "tgn:name":"Pennike Run",
    "tgn:placetype":[
        "aat:300008699"
    ]
},
  "bbox": [],
  "geometry": {"coordinates":[-81.6167,39.0333],"type":"Point"}
}