<<<<<<< HEAD
{
  "id": 7022589,
  "type": "Feature",
  "properties": {
    "tgn:hierarchy":[
        "tgn:7022589",
        "tgn:1000001",
        "tgn:7012149",
        "tgn:7007248",
        "tgn:7029392"
    ],
    "tgn:id":7022589,
    "tgn:name":"Kelley Lake",
    "tgn:placetype":[
        "aat:300006191"
    ]
},
  "bbox": [],
  "geometry": {"coordinates":[-84.4667,33.2833],"type":"Point"}
}
=======
{"geometry":{"type":"Point","coordinates":[-84.466700,33.283300]},"type":"Feature","properties":{"hierarchy":["tgn:7022589","tgn:1000001","tgn:7012149","tgn:7007248","tgn:7029392"],"placetype":["aat:300006191"],"id":7022589,"name:xx":"Kelley Lake"}}
>>>>>>> 03f74aca74312dbeaf24d7e61306dd6a786dc3d0
