{
  "id": 2551845,
  "type": "Feature",
  "properties": {
    "tgn:hierarchy":[
        "tgn:2551845",
        "tgn:1000001",
        "tgn:7012149",
        "tgn:2001208",
        "tgn:7007523",
        "tgn:7029392"
    ],
    "tgn:id":2551845,
    "tgn:name":"Number 85 Lake",
    "tgn:placetype":[
        "aat:300006191"
    ]
},
  "bbox": [],
  "geometry": {"coordinates":[-94.55,38.8833],"type":"Point"}
}