{
  "id": 7227694,
  "type": "Feature",
  "properties": {
    "tgn:hierarchy":[
        "tgn:7227694",
        "tgn:7011167",
        "tgn:7001338",
        "tgn:1000003",
        "tgn:1000074",
        "tgn:7029392"
    ],
    "tgn:id":7227694,
    "tgn:name":"Kat\u00e1rrakhon",
    "tgn:placetype":[
        "aat:300008347"
    ]
},
  "bbox": [],
  "geometry": {"coordinates":[20.716667,38.166667],"type":"Point"}
}