{
  "id": 2301344,
  "type": "Feature",
  "properties": {
    "tgn:hierarchy":[
        "tgn:2301344",
        "tgn:1002996",
        "tgn:1000001",
        "tgn:7012149",
        "tgn:7007711",
        "tgn:7029392"
    ],
    "tgn:id":2301344,
    "tgn:name":"Dunn Corner",
    "tgn:placetype":[
        "aat:300008347"
    ]
},
  "bbox": [],
  "geometry": {"coordinates":[-71.7667,41.35],"type":"Point"}
}