{
  "id": 7347029,
  "type": "Feature",
  "properties": {
    "tgn:hierarchy":[
        "tgn:7347029",
        "tgn:7002849",
        "tgn:1000003",
        "tgn:7009604",
        "tgn:1000095",
        "tgn:7029392"
    ],
    "tgn:id":7347029,
    "tgn:name":"Asterrica",
    "tgn:placetype":[
        "aat:300008347"
    ]
},
  "bbox": [],
  "geometry": {"coordinates":[-2.457886,43.325713],"type":"Point"}
}