{
  "id": 2622587,
  "type": "Feature",
  "properties": {
    "tgn:hierarchy":[
        "tgn:2622587",
        "tgn:1000001",
        "tgn:7012149",
        "tgn:2002112",
        "tgn:7007827",
        "tgn:7029392"
    ],
    "tgn:id":2622587,
    "tgn:name":"Robinson Canyon",
    "tgn:placetype":[
        "aat:300008761"
    ]
},
  "bbox": [],
  "geometry": {"coordinates":[-112.1333,39.9667],"type":"Point"}
}