{
  "id": 2103261,
  "type": "Feature",
  "properties": {
    "tgn:hierarchy":[
        "tgn:2103261",
        "tgn:1000001",
        "tgn:7012149",
        "tgn:2002089",
        "tgn:7007826",
        "tgn:7029392"
    ],
    "tgn:id":2103261,
    "tgn:name":"Chester",
    "tgn:placetype":[
        "aat:300008347"
    ]
},
  "bbox": [],
  "geometry": {"coordinates":[-94.5833,30.9167],"type":"Point"}
}