{
  "id": 7212761,
  "type": "Feature",
  "properties": {
    "tgn:hierarchy":[
        "tgn:7212761",
        "tgn:1000003",
        "tgn:7003682",
        "tgn:7000084",
        "tgn:7029392"
    ],
    "tgn:id":7212761,
    "tgn:name":"Bocks-Berg",
    "tgn:placetype":[
        "aat:300008777"
    ]
},
  "bbox": [],
  "geometry": {"coordinates":[6.933333,50.316667],"type":"Point"}
}