<<<<<<< HEAD
{
  "id": 7052577,
  "type": "Feature",
  "properties": {
    "tgn:hierarchy":[
        "tgn:7052577",
        "tgn:1001724",
        "tgn:1000003",
        "tgn:7003121",
        "tgn:1000080",
        "tgn:7029392"
    ],
    "tgn:id":7052577,
    "tgn:name":"Irveri, Monte",
    "tgn:placetype":[
        "aat:300008795"
    ]
},
  "bbox": [],
  "geometry": {"coordinates":[9.65,40.3],"type":"Point"}
}
=======
{"geometry":{"type":"Point","coordinates":[9.650000,40.300000]},"type":"Feature","properties":{"hierarchy":["tgn:7052577","tgn:1001724","tgn:1000003","tgn:7003121","tgn:1000080","tgn:7029392"],"placetype":["aat:300008795"],"id":7052577,"name:xx":"Irveri, Monte"}}
>>>>>>> 03f74aca74312dbeaf24d7e61306dd6a786dc3d0
