<<<<<<< HEAD
{
  "id": 7119186,
  "type": "Feature",
  "properties": {
    "tgn:hierarchy":[
        "tgn:7119186",
        "tgn:7003669",
        "tgn:1000003",
        "tgn:7000084",
        "tgn:7029392"
    ],
    "tgn:id":7119186,
    "tgn:name":"Perkabach",
    "tgn:placetype":[
        "aat:300008699"
    ]
},
  "bbox": [],
  "geometry": {"coordinates":[11.85,48.783333],"type":"Point"}
}
=======
{"geometry":{"type":"Point","coordinates":[11.850000,48.783333]},"type":"Feature","properties":{"hierarchy":["tgn:7119186","tgn:7003669","tgn:1000003","tgn:7000084","tgn:7029392"],"placetype":["aat:300008699"],"id":7119186,"name:xx":"Perkabach"}}
>>>>>>> 03f74aca74312dbeaf24d7e61306dd6a786dc3d0
