<<<<<<< HEAD
{
  "id": 7113234,
  "type": "Feature",
  "properties": {
    "tgn:hierarchy":[
        "tgn:7113234",
        "tgn:7003669",
        "tgn:1000003",
        "tgn:7000084",
        "tgn:7029392"
    ],
    "tgn:id":7113234,
    "tgn:name":"Riesenberg",
    "tgn:placetype":[
        "aat:300008795"
    ]
},
  "bbox": [],
  "geometry": {"coordinates":[12.1,47.716667],"type":"Point"}
}
=======
{"geometry":{"type":"Point","coordinates":[12.100000,47.716667]},"type":"Feature","properties":{"hierarchy":["tgn:7113234","tgn:7003669","tgn:1000003","tgn:7000084","tgn:7029392"],"placetype":["aat:300008795"],"id":7113234,"name:xx":"Riesenberg"}}
>>>>>>> 03f74aca74312dbeaf24d7e61306dd6a786dc3d0
