<<<<<<< HEAD
{
  "id": 2768047,
  "type": "Feature",
  "properties": {
    "tgn:hierarchy":[
        "tgn:2768047",
        "tgn:1000001",
        "tgn:1002260",
        "tgn:7012149",
        "tgn:7007920",
        "tgn:7029392"
    ],
    "tgn:id":2768047,
    "tgn:name":"Whitepine Creek",
    "tgn:placetype":[
        "aat:300008706"
    ]
},
  "bbox": [],
  "geometry": {"coordinates":[-121.0333,47.6833],"type":"Point"}
}
=======
{"geometry":{"type":"Point","coordinates":[-121.033300,47.683300]},"type":"Feature","properties":{"hierarchy":["tgn:2768047","tgn:1000001","tgn:1002260","tgn:7012149","tgn:7007920","tgn:7029392"],"placetype":["aat:300008706"],"id":2768047,"name:xx":"Whitepine Creek"}}
>>>>>>> 03f74aca74312dbeaf24d7e61306dd6a786dc3d0
