{
  "id": 2547533,
  "type": "Feature",
  "properties": {
    "tgn:hierarchy":[
        "tgn:2547533",
        "tgn:1000001",
        "tgn:7012149",
        "tgn:2001931",
        "tgn:7007825",
        "tgn:7029392"
    ],
    "tgn:id":2547533,
    "tgn:name":"North Fork Suggs Creek",
    "tgn:placetype":[
        "aat:300008706"
    ]
},
  "bbox": [],
  "geometry": {"coordinates":[-86.45,36.15],"type":"Point"}
}