<<<<<<< HEAD
{
  "id": 2253281,
  "type": "Feature",
  "properties": {
    "tgn:hierarchy":[
        "tgn:2253281",
        "tgn:1000001",
        "tgn:7012149",
        "tgn:1002392",
        "tgn:7007157",
        "tgn:7029392"
    ],
    "tgn:id":2253281,
    "tgn:name":"Converse Basin Grove",
    "tgn:placetype":[
        "aat:300132451"
    ]
},
  "bbox": [],
  "geometry": {"coordinates":[-118.9667,36.8],"type":"Point"}
}
=======
{"geometry":{"type":"Point","coordinates":[-118.966700,36.800000]},"type":"Feature","properties":{"hierarchy":["tgn:2253281","tgn:1000001","tgn:7012149","tgn:1002392","tgn:7007157","tgn:7029392"],"placetype":["aat:300132451"],"id":2253281,"name:xx":"Converse Basin Grove"}}
>>>>>>> 03f74aca74312dbeaf24d7e61306dd6a786dc3d0
