{
  "id": 2687642,
  "type": "Feature",
  "properties": {
    "tgn:hierarchy":[
        "tgn:2687642",
        "tgn:1000001",
        "tgn:2000464",
        "tgn:7012149",
        "tgn:7007250",
        "tgn:7029392"
    ],
    "tgn:id":2687642,
    "tgn:name":"Spring Ridge",
    "tgn:placetype":[
        "aat:300266640"
    ]
},
  "bbox": [],
  "geometry": {"coordinates":[-115.0167,43.4833],"type":"Point"}
}