<<<<<<< HEAD
{
  "id": 7170268,
  "type": "Feature",
  "properties": {
    "tgn:hierarchy":[
        "tgn:7170268",
        "tgn:1000003",
        "tgn:7003676",
        "tgn:7000084",
        "tgn:7029392"
    ],
    "tgn:id":7170268,
    "tgn:name":"He\u00dflinger Bach",
    "tgn:placetype":[
        "aat:300008699"
    ]
},
  "bbox": [],
  "geometry": {"coordinates":[9.25,52.15],"type":"Point"}
}
=======
{"geometry":{"type":"Point","coordinates":[9.250000,52.150000]},"type":"Feature","properties":{"hierarchy":["tgn:7170268","tgn:1000003","tgn:7003676","tgn:7000084","tgn:7029392"],"placetype":["aat:300008699"],"id":7170268,"name:xx":"He\u00dflinger Bach"}}
>>>>>>> 03f74aca74312dbeaf24d7e61306dd6a786dc3d0
