{
  "id": 2161845,
  "type": "Feature",
  "properties": {
    "tgn:hierarchy":[
        "tgn:2161845",
        "tgn:7014201",
        "tgn:1000001",
        "tgn:7012149",
        "tgn:7007239",
        "tgn:7029392"
    ],
    "tgn:id":2161845,
    "tgn:name":"Bellewood",
    "tgn:placetype":[
        "aat:300008347"
    ]
},
  "bbox": [],
  "geometry": {"coordinates":[-75.5167,39.7833],"type":"Point"}
}