{
  "id": 7283536,
  "type": "Feature",
  "properties": {
    "tgn:hierarchy":[
        "tgn:7283536",
        "tgn:1001630",
        "tgn:1000049",
        "tgn:1000002",
        "tgn:7029392"
    ],
    "tgn:id":7283536,
    "tgn:name":"Pajonales, Morro",
    "tgn:placetype":[
        "aat:300008777"
    ]
},
  "bbox": [],
  "geometry": {"coordinates":[-70.966667,-27.85],"type":"Point"}
}