{
  "id": 2395440,
  "type": "Feature",
  "properties": {
    "tgn:hierarchy":[
        "tgn:2395440",
        "tgn:1000001",
        "tgn:7012149",
        "tgn:2002040",
        "tgn:7007826",
        "tgn:7029392"
    ],
    "tgn:id":2395440,
    "tgn:name":"Holland Draw",
    "tgn:placetype":[
        "aat:300008761"
    ]
},
  "bbox": [],
  "geometry": {"coordinates":[-99.4833,30.8167],"type":"Point"}
}