{
  "id": 1076169,
  "type": "Feature",
  "properties": {
    "tgn:hierarchy":[
        "tgn:1076169",
        "tgn:1001828",
        "tgn:1000004",
        "tgn:7000198",
        "tgn:7029392"
    ],
    "tgn:id":1076169,
    "tgn:name:en":"Mandapeta",
    "tgn:placetype":[
        "aat:300008347"
    ]
},
  "bbox": [],
  "geometry": {"coordinates":[81.933333,16.866667],"type":"Point"}
}