{
  "id": 2749174,
  "type": "Feature",
  "properties": {
    "tgn:hierarchy":[
        "tgn:2749174",
        "tgn:1000001",
        "tgn:7012149",
        "tgn:2001288",
        "tgn:7007524",
        "tgn:7029392"
    ],
    "tgn:id":2749174,
    "tgn:name":"Wallace Peak",
    "tgn:placetype":[
        "aat:300008798"
    ]
},
  "bbox": [],
  "geometry": {"coordinates":[-111.8167,45.5667],"type":"Point"}
}