{
  "id": 1006798,
  "type": "Feature",
  "properties": {
    "tgn:hierarchy":[
        "tgn:1006798",
        "tgn:1000004",
        "tgn:7002076",
        "tgn:1000111",
        "tgn:7029392"
    ],
    "tgn:id":1006798,
    "tgn:name":"Chitou Shan",
    "tgn:placetype":[
        "aat:300008791"
    ]
},
  "bbox": [],
  "geometry": {"coordinates":[120.8167,27.65],"type":"Point"}
}