{
  "id": 7319030,
  "type": "Feature",
  "properties": {
    "tgn:hierarchy":[
        "tgn:7319030",
        "tgn:1001702",
        "tgn:1000049",
        "tgn:1000002",
        "tgn:7029392"
    ],
    "tgn:id":7319030,
    "tgn:name":"Araya, Punta",
    "tgn:placetype":[
        "aat:300386846"
    ]
},
  "bbox": [],
  "geometry": {"coordinates":[-73.183333,-53.066667],"type":"Point"}
}