{
  "id": 7083486,
  "type": "Feature",
  "properties": {
    "tgn:hierarchy":[
        "tgn:7083486",
        "tgn:1000003",
        "tgn:7003677",
        "tgn:7000084",
        "tgn:7029392"
    ],
    "tgn:id":7083486,
    "tgn:name":"Westerbauerschaft",
    "tgn:placetype":[
        "aat:300387200"
    ]
},
  "bbox": [],
  "geometry": {"coordinates":[7.133333,52.233333],"type":"Point"}
}