{
  "id": 1128510,
  "type": "Feature",
  "properties": {
    "tgn:hierarchy":[
        "tgn:1128510",
        "tgn:1000001",
        "tgn:7012149",
        "tgn:2001067",
        "tgn:7007521",
        "tgn:7029392"
    ],
    "tgn:id":1128510,
    "tgn:name":"Pelican",
    "tgn:placetype":[
        "aat:300008707"
    ]
},
  "bbox": [],
  "geometry": {"coordinates":[-92.8333,48.0333],"type":"Point"}
}