<<<<<<< HEAD
{
  "id": 7173422,
  "type": "Feature",
  "properties": {
    "tgn:hierarchy":[
        "tgn:7173422",
        "tgn:7003669",
        "tgn:1000003",
        "tgn:7000084",
        "tgn:7029392"
    ],
    "tgn:id":7173422,
    "tgn:name":"Gro\u00df Pinzing",
    "tgn:placetype":[
        "aat:300000745"
    ]
},
  "bbox": [],
  "geometry": {"coordinates":[12.733333,49.266667],"type":"Point"}
}
=======
{"geometry":{"type":"Point","coordinates":[12.733333,49.266667]},"type":"Feature","properties":{"hierarchy":["tgn:7173422","tgn:7003669","tgn:1000003","tgn:7000084","tgn:7029392"],"placetype":["aat:300000745"],"id":7173422,"name:xx":"Gro\u00df Pinzing"}}
>>>>>>> 03f74aca74312dbeaf24d7e61306dd6a786dc3d0
