{
  "id": 7496672,
  "type": "Feature",
  "properties": {
    "tgn:hierarchy":[
        "tgn:7496672",
        "tgn:7487020",
        "tgn:1000004",
        "tgn:1000141",
        "tgn:7029392"
    ],
    "tgn:id":7496672,
    "tgn:name":"Jiuxionglin Shan",
    "tgn:placetype":[
        "aat:300008798"
    ]
},
  "bbox": [],
  "geometry": {"coordinates":[120.860758,24.433161],"type":"Point"}
}