{
  "id": 7593118,
  "type": "Feature",
  "properties": {
    "tgn:hierarchy":[
        "tgn:7593118",
        "tgn:7005278",
        "tgn:7001242",
        "tgn:7005277",
        "tgn:7029392"
    ],
    "tgn:id":7593118,
    "tgn:name":"Ruperts Battery",
    "tgn:placetype":[
        "aat:300387007"
    ]
},
  "bbox": [],
  "geometry": {"coordinates":[-5.716,-15.916],"type":"Point"}
}