<<<<<<< HEAD
{
  "id": 7372416,
  "type": "Feature",
  "properties": {
    "tgn:hierarchy":[
        "tgn:7372416",
        "tgn:1000001",
        "tgn:7005601",
        "tgn:7005560",
        "tgn:7029392"
    ],
    "tgn:id":7372416,
    "tgn:name":"La Estancia",
    "tgn:placetype":[
        "aat:300008347"
    ]
},
  "bbox": [],
  "geometry": {"coordinates":[-103.0,21.833333],"type":"Point"}
}
=======
{"geometry":{"type":"Point","coordinates":[-103.000000,21.833333]},"type":"Feature","properties":{"hierarchy":["tgn:7372416","tgn:1000001","tgn:7005601","tgn:7005560","tgn:7029392"],"placetype":["aat:300008347"],"id":7372416,"name:xx":"La Estancia"}}
>>>>>>> 03f74aca74312dbeaf24d7e61306dd6a786dc3d0
