{
  "id": 2285063,
  "type": "Feature",
  "properties": {
    "tgn:hierarchy":[
        "tgn:2285063",
        "tgn:1000001",
        "tgn:2001429",
        "tgn:7012149",
        "tgn:7007566",
        "tgn:7029392"
    ],
    "tgn:id":2285063,
    "tgn:name":"Devil Tank Number One",
    "tgn:placetype":[
        "aat:300006191"
    ]
},
  "bbox": [],
  "geometry": {"coordinates":[-108.75,33.8333],"type":"Point"}
}