{
  "id": 2770251,
  "type": "Feature",
  "properties": {
    "tgn:hierarchy":[
        "tgn:2770251",
        "tgn:1000001",
        "tgn:7006451",
        "tgn:7012149",
        "tgn:2000103",
        "tgn:7029392"
    ],
    "tgn:id":2770251,
    "tgn:name":"Wild Hog Basin",
    "tgn:placetype":[
        "aat:300386845"
    ]
},
  "bbox": [],
  "geometry": {"coordinates":[-112.95,34.4833],"type":"Point"}
}