{
  "id": 7560716,
  "type": "Feature",
  "properties": {
    "tgn:hierarchy":[
        "tgn:7560716",
        "tgn:1000004",
        "tgn:7000198",
        "tgn:7016722",
        "tgn:7029392"
    ],
    "tgn:id":7560716,
    "tgn:name:en":"Badh\u016bra",
    "tgn:placetype":[
        "aat:300008347"
    ]
},
  "bbox": [],
  "geometry": {"coordinates":[79.516685,27.644195],"type":"Point"}
}