{
  "id": 7322260,
  "type": "Feature",
  "properties": {
    "tgn:hierarchy":[
        "tgn:7322260",
        "tgn:1001705",
        "tgn:1000049",
        "tgn:1000002",
        "tgn:7029392"
    ],
    "tgn:id":7322260,
    "tgn:name":"Barroso, R\u00edo",
    "tgn:placetype":[
        "aat:300008699"
    ]
},
  "bbox": [],
  "geometry": {"coordinates":[-70.816667,-35.316667],"type":"Point"}
}