{
  "id": 2535049,
  "type": "Feature",
  "properties": {
    "tgn:hierarchy":[
        "tgn:2535049",
        "tgn:1000001",
        "tgn:7012149",
        "tgn:2001123",
        "tgn:7007522",
        "tgn:7029392"
    ],
    "tgn:id":2535049,
    "tgn:name":"Nanabe Creek",
    "tgn:placetype":[
        "aat:300008706"
    ]
},
  "bbox": [],
  "geometry": {"coordinates":[-88.5667,32.3833],"type":"Point"}
}