{
  "id": 2083985,
  "type": "Feature",
  "properties": {
    "tgn:hierarchy":[
        "tgn:2083985",
        "tgn:1000001",
        "tgn:7012149",
        "tgn:2001662",
        "tgn:7007707",
        "tgn:7029392"
    ],
    "tgn:id":2083985,
    "tgn:name":"Shady Point",
    "tgn:placetype":[
        "aat:300008347"
    ]
},
  "bbox": [],
  "geometry": {"coordinates":[-94.65,35.1167],"type":"Point"}
}