{
  "id": 7019321,
  "type": "Feature",
  "properties": {
    "tgn:hierarchy":[
        "tgn:7019321",
        "tgn:1000001",
        "tgn:2000322",
        "tgn:7012149",
        "tgn:7007248",
        "tgn:7029392"
    ],
    "tgn:id":7019321,
    "tgn:name":"Mundys Millpond",
    "tgn:placetype":[
        "aat:300006191"
    ]
},
  "bbox": [],
  "geometry": {"coordinates":[-84.3833,33.4833],"type":"Point"}
}