{
  "id": 7394239,
  "type": "Feature",
  "properties": {
    "tgn:hierarchy":[
        "tgn:7394239",
        "tgn:1000001",
        "tgn:7005601",
        "tgn:7005560",
        "tgn:7029392"
    ],
    "tgn:id":7394239,
    "tgn:name":"Tanque San La Isabet",
    "tgn:placetype":[
        "aat:300006191"
    ]
},
  "bbox": [],
  "geometry": {"coordinates":[-102.033333,24.25],"type":"Point"}
}