{
  "id": 2358040,
  "type": "Feature",
  "properties": {
    "tgn:hierarchy":[
        "tgn:2358040",
        "tgn:1000001",
        "tgn:1002714",
        "tgn:7012149",
        "tgn:7007159",
        "tgn:7029392"
    ],
    "tgn:id":2358040,
    "tgn:name":"Graham Pond",
    "tgn:placetype":[
        "aat:300008680"
    ]
},
  "bbox": [],
  "geometry": {"coordinates":[-72.0167,41.5667],"type":"Point"}
}