{
  "id": 7157907,
  "type": "Feature",
  "properties": {
    "tgn:hierarchy":[
        "tgn:7157907",
        "tgn:1000003",
        "tgn:7003685",
        "tgn:7000084",
        "tgn:7029392"
    ],
    "tgn:id":7157907,
    "tgn:name":"Kleiner Eulenstein",
    "tgn:placetype":[
        "aat:300011692"
    ]
},
  "bbox": [],
  "geometry": {"coordinates":[12.966667,51.166667],"type":"Point"}
}