{
  "id": 1128576,
  "type": "Feature",
  "properties": {
    "tgn:hierarchy":[
        "tgn:1128576",
        "tgn:7005685",
        "tgn:1000001",
        "tgn:7029392"
    ],
    "tgn:id":1128576,
    "tgn:name":"Petitot",
    "tgn:placetype":[
        "aat:300008707"
    ]
},
  "bbox": [],
  "geometry": {"coordinates":[-123.4833,60.2333],"type":"Point"}
}