{
  "id": 7461144,
  "type": "Feature",
  "properties": {
    "tgn:hierarchy":[
        "tgn:7461144",
        "tgn:7002443",
        "tgn:5000552",
        "tgn:1000003",
        "tgn:7008591",
        "tgn:7029392"
    ],
    "tgn:id":7461144,
    "tgn:name:en":"Llangunnor",
    "tgn:placetype":[
        "aat:300008347"
    ]
},
  "bbox": [],
  "geometry": {"coordinates":[-4.275556,51.855556],"type":"Point"}
}