<<<<<<< HEAD
{
  "id": 7028526,
  "type": "Feature",
  "properties": {
    "tgn:hierarchy":[
        "tgn:7028526",
        "tgn:7002445",
        "tgn:1000003",
        "tgn:7008160",
        "tgn:7008591",
        "tgn:7029392"
    ],
    "tgn:id":7028526,
    "tgn:name:en":"Metton",
    "tgn:placetype":[
        "aat:300008347",
        "aat:300008372"
    ]
},
  "bbox": [],
  "geometry": {"coordinates":[1.254,52.884],"type":"Point"}
}
=======
{"geometry":{"type":"Point","coordinates":[1.254000,52.884000]},"type":"Feature","properties":{"hierarchy":["tgn:7028526","tgn:7002445","tgn:1000003","tgn:7008160","tgn:7008591","tgn:7029392"],"placetype":["aat:300008347","aat:300008372"],"name:en":"Metton","id":7028526}}
>>>>>>> 03f74aca74312dbeaf24d7e61306dd6a786dc3d0
