<<<<<<< HEAD
{
  "id": 2334683,
  "type": "Feature",
  "properties": {
    "tgn:hierarchy":[
        "tgn:2334683",
        "tgn:1000001",
        "tgn:7012149",
        "tgn:2000933",
        "tgn:7007515",
        "tgn:7029392"
    ],
    "tgn:id":2334683,
    "tgn:name":"Foristall Corners",
    "tgn:placetype":[
        "aat:300008347"
    ]
},
  "bbox": [],
  "geometry": {"coordinates":[-70.65,43.2],"type":"Point"}
}
=======
{"geometry":{"type":"Point","coordinates":[-70.650000,43.200000]},"type":"Feature","properties":{"hierarchy":["tgn:2334683","tgn:1000001","tgn:7012149","tgn:2000933","tgn:7007515","tgn:7029392"],"placetype":["aat:300008347"],"id":2334683,"name:xx":"Foristall Corners"}}
>>>>>>> 03f74aca74312dbeaf24d7e61306dd6a786dc3d0
