<<<<<<< HEAD
{
  "id": 2253771,
  "type": "Feature",
  "properties": {
    "tgn:hierarchy":[
        "tgn:2253771",
        "tgn:1000001",
        "tgn:7012149",
        "tgn:7007157",
        "tgn:1002608",
        "tgn:7029392"
    ],
    "tgn:id":2253771,
    "tgn:name":"Cooks Canyon",
    "tgn:placetype":[
        "aat:300008761"
    ]
},
  "bbox": [],
  "geometry": {"coordinates":[-118.2333,34.2667],"type":"Point"}
}
=======
{"geometry":{"type":"Point","coordinates":[-118.233300,34.266700]},"type":"Feature","properties":{"hierarchy":["tgn:2253771","tgn:1000001","tgn:7012149","tgn:7007157","tgn:1002608","tgn:7029392"],"placetype":["aat:300008761"],"id":2253771,"name:xx":"Cooks Canyon"}}
>>>>>>> 03f74aca74312dbeaf24d7e61306dd6a786dc3d0
