{
  "id": 2226627,
  "type": "Feature",
  "properties": {
    "tgn:hierarchy":[
        "tgn:2226627",
        "tgn:1000001",
        "tgn:7012149",
        "tgn:1002920",
        "tgn:7007568",
        "tgn:7029392"
    ],
    "tgn:id":2226627,
    "tgn:name":"Caton Swamp",
    "tgn:placetype":[
        "aat:300008905"
    ]
},
  "bbox": [],
  "geometry": {"coordinates":[-77.0167,42.0333],"type":"Point"}
}