{
  "id": 2502147,
  "type": "Feature",
  "properties": {
    "tgn:hierarchy":[
        "tgn:2502147",
        "tgn:1000001",
        "tgn:7012149",
        "tgn:7013941",
        "tgn:7007568",
        "tgn:7029392"
    ],
    "tgn:id":2502147,
    "tgn:name":"McKillip Mountain",
    "tgn:placetype":[
        "aat:300008798"
    ]
},
  "bbox": [],
  "geometry": {"coordinates":[-73.9333,44.5167],"type":"Point"}
}