{
  "id": 7409435,
  "type": "Feature",
  "properties": {
    "tgn:hierarchy":[
        "tgn:7409435",
        "tgn:1000001",
        "tgn:1001893",
        "tgn:7005560",
        "tgn:7029392"
    ],
    "tgn:id":7409435,
    "tgn:name":"San Crist\u00f3bal Poxtla",
    "tgn:placetype":[
        "aat:300008347"
    ]
},
  "bbox": [],
  "geometry": {"coordinates":[-98.791667,19.133333],"type":"Point"}
}