{
  "id": 2199988,
  "type": "Feature",
  "properties": {
    "tgn:hierarchy":[
        "tgn:2199988",
        "tgn:1000001",
        "tgn:7012149",
        "tgn:2002058",
        "tgn:7007826",
        "tgn:7029392"
    ],
    "tgn:id":2199988,
    "tgn:name":"Brushy Butte",
    "tgn:placetype":[
        "aat:300008798"
    ]
},
  "bbox": [],
  "geometry": {"coordinates":[-101.6667,34.9667],"type":"Point"}
}