{
  "id": 7045444,
  "type": "Feature",
  "properties": {
    "tgn:hierarchy":[
        "tgn:7045444",
        "tgn:7003127",
        "tgn:1000003",
        "tgn:7008516",
        "tgn:1000080",
        "tgn:7029392"
    ],
    "tgn:id":7045444,
    "tgn:name":"Fondo Volta",
    "tgn:placetype":[
        "aat:300008347"
    ]
},
  "bbox": [],
  "geometry": {"coordinates":[11.65,44.616667],"type":"Point"}
}