{
  "id": 2670497,
  "type": "Feature",
  "properties": {
    "tgn:hierarchy":[
        "tgn:2670497",
        "tgn:1000001",
        "tgn:7012149",
        "tgn:1002919",
        "tgn:7007252",
        "tgn:7029392"
    ],
    "tgn:id":2670497,
    "tgn:name":"Smathers Ditch",
    "tgn:placetype":[
        "aat:300006075"
    ]
},
  "bbox": [],
  "geometry": {"coordinates":[-85.0833,41.5333],"type":"Point"}
}