{
  "id": 7497208,
  "type": "Feature",
  "properties": {
    "tgn:hierarchy":[
        "tgn:7497208",
        "tgn:7001004",
        "tgn:1000004",
        "tgn:1000141",
        "tgn:7029392"
    ],
    "tgn:id":7497208,
    "tgn:name":"Fengteng Gong",
    "tgn:placetype":[
        "aat:300007595"
    ]
},
  "bbox": [],
  "geometry": {"coordinates":[120.377163,22.574835],"type":"Point"}
}