{
  "id": 2034913,
  "type": "Feature",
  "properties": {
    "tgn:hierarchy":[
        "tgn:2034913",
        "tgn:1000001",
        "tgn:7012149",
        "tgn:2000653",
        "tgn:7007253",
        "tgn:7029392"
    ],
    "tgn:id":2034913,
    "tgn:name":"Harvard",
    "tgn:placetype":[
        "aat:300008347"
    ]
},
  "bbox": [],
  "geometry": {"coordinates":[-93.2667,40.6833],"type":"Point"}
}