{
  "id": 2747319,
  "type": "Feature",
  "properties": {
    "tgn:hierarchy":[
        "tgn:2747319",
        "tgn:1000001",
        "tgn:7012149",
        "tgn:1002554",
        "tgn:7007920",
        "tgn:7029392"
    ],
    "tgn:id":2747319,
    "tgn:name":"Wahkiaous Canyon",
    "tgn:placetype":[
        "aat:300008761"
    ]
},
  "bbox": [],
  "geometry": {"coordinates":[-121.1333,45.8667],"type":"Point"}
}