{
  "id": 7590644,
  "type": "Feature",
  "properties": {
    "tgn:hierarchy":[
        "tgn:7590644",
        "tgn:1000004",
        "tgn:7000198",
        "tgn:7000799",
        "tgn:7029392"
    ],
    "tgn:id":7590644,
    "tgn:name:en":"Rarw\u0101n Khurd",
    "tgn:placetype":[
        "aat:300008347"
    ]
},
  "bbox": [],
  "geometry": {"coordinates":[74.95,32.525],"type":"Point"}
}