<<<<<<< HEAD
{
  "id": 7059675,
  "type": "Feature",
  "properties": {
    "tgn:hierarchy":[
        "tgn:7059675",
        "tgn:7003669",
        "tgn:1000003",
        "tgn:7000084",
        "tgn:7029392"
    ],
    "tgn:id":7059675,
    "tgn:name":"Allersing",
    "tgn:placetype":[
        "aat:300008347"
    ]
},
  "bbox": [],
  "geometry": {"coordinates":[12.3,48.066667],"type":"Point"}
}
=======
{"geometry":{"type":"Point","coordinates":[12.300000,48.066667]},"type":"Feature","properties":{"hierarchy":["tgn:7059675","tgn:7003669","tgn:1000003","tgn:7000084","tgn:7029392"],"placetype":["aat:300008347"],"id":7059675,"name:xx":"Allersing"}}
>>>>>>> 03f74aca74312dbeaf24d7e61306dd6a786dc3d0
