{
  "id": 1098720,
  "type": "Feature",
  "properties": {
    "tgn:hierarchy":[
        "tgn:1098720",
        "tgn:1008209",
        "tgn:7006218",
        "tgn:1000216",
        "tgn:1000006",
        "tgn:7029392"
    ],
    "tgn:id":1098720,
    "tgn:name":"Haapiti",
    "tgn:placetype":[
        "aat:300008347"
    ]
},
  "bbox": [],
  "geometry": {"coordinates":[-149.8667,-17.55],"type":"Point"}
}