<<<<<<< HEAD
{
  "id": 7478548,
  "type": "Feature",
  "properties": {
    "tgn:hierarchy":[
        "tgn:7478548",
        "tgn:1000004",
        "tgn:7467799",
        "tgn:1000141",
        "tgn:7029392"
    ],
    "tgn:id":7478548,
    "tgn:name":"Fuzhen Qiao",
    "tgn:placetype":[
        "aat:300007836"
    ]
},
  "bbox": [],
  "geometry": {"coordinates":[120.585861,23.967662],"type":"Point"}
}
=======
{"geometry":{"type":"Point","coordinates":[120.585861,23.967662]},"type":"Feature","properties":{"hierarchy":["tgn:7478548","tgn:1000004","tgn:7467799","tgn:1000141","tgn:7029392"],"placetype":["aat:300007836"],"id":7478548,"name:xx":"Fuzhen Qiao"}}
>>>>>>> 03f74aca74312dbeaf24d7e61306dd6a786dc3d0
