{
  "id": 7033551,
  "type": "Feature",
  "properties": {
    "tgn:hierarchy":[
        "tgn:7033551",
        "tgn:7003128",
        "tgn:1000003",
        "tgn:7008516",
        "tgn:1000080",
        "tgn:7029392"
    ],
    "tgn:id":7033551,
    "tgn:name":"Bonifica Valle Trebba",
    "tgn:placetype":[
        "aat:300387200"
    ]
},
  "bbox": [],
  "geometry": {"coordinates":[12.113056,44.738333],"type":"Point"}
}