{
  "id": 7455052,
  "type": "Feature",
  "properties": {
    "tgn:hierarchy":[
        "tgn:7455052",
        "tgn:7002445",
        "tgn:1000003",
        "tgn:7008165",
        "tgn:7008591",
        "tgn:7029392"
    ],
    "tgn:id":7455052,
    "tgn:name:en":"Colville Rock",
    "tgn:placetype":[
        "aat:300008808"
    ]
},
  "bbox": [],
  "geometry": {"coordinates":[-1.466667,55.083333],"type":"Point"}
}