{
  "id": 2427342,
  "type": "Feature",
  "properties": {
    "tgn:hierarchy":[
        "tgn:2427342",
        "tgn:1000001",
        "tgn:7012149",
        "tgn:2002273",
        "tgn:7013961",
        "tgn:7029392"
    ],
    "tgn:id":2427342,
    "tgn:name":"Jordan Fork",
    "tgn:placetype":[
        "aat:300008699"
    ]
},
  "bbox": [],
  "geometry": {"coordinates":[-81.7167,37.75],"type":"Point"}
}