{
  "id": 1072191,
  "type": "Feature",
  "properties": {
    "tgn:hierarchy":[
        "tgn:1072191",
        "tgn:1000004",
        "tgn:7001838",
        "tgn:1000111",
        "tgn:7029392"
    ],
    "tgn:id":1072191,
    "tgn:name":"Tarhu",
    "tgn:placetype":[
        "aat:300008347"
    ]
},
  "bbox": [],
  "geometry": {"coordinates":[107.8833,41.0833],"type":"Point"}
}