{
  "id": 2664685,
  "type": "Feature",
  "properties": {
    "tgn:hierarchy":[
        "tgn:2664685",
        "tgn:7002659",
        "tgn:1000001",
        "tgn:7012149",
        "tgn:2000057",
        "tgn:7029392"
    ],
    "tgn:id":2664685,
    "tgn:name":"Simmons Mountain",
    "tgn:placetype":[
        "aat:300008798"
    ]
},
  "bbox": [],
  "geometry": {"coordinates":[-86.4667,33.7333],"type":"Point"}
}