{
  "id": 2718249,
  "type": "Feature",
  "properties": {
    "tgn:hierarchy":[
        "tgn:2718249",
        "tgn:1000001",
        "tgn:7012149",
        "tgn:1003020",
        "tgn:7007920",
        "tgn:7029392"
    ],
    "tgn:id":2718249,
    "tgn:name":"Thompson Creek",
    "tgn:placetype":[
        "aat:300008706"
    ]
},
  "bbox": [],
  "geometry": {"coordinates":[-121.85,48.85],"type":"Point"}
}