{
  "id": 7076943,
  "type": "Feature",
  "properties": {
    "tgn:hierarchy":[
        "tgn:7076943",
        "tgn:7000096",
        "tgn:1000003",
        "tgn:7000084",
        "tgn:7029392"
    ],
    "tgn:id":7076943,
    "tgn:name":"Landkreis Elbe-Elster",
    "tgn:placetype":[
        "aat:300387198"
    ]
},
  "bbox": [],
  "geometry": {"coordinates":[13.44,51.633889],"type":"Point"}
}