{
  "id": 7297115,
  "type": "Feature",
  "properties": {
    "tgn:hierarchy":[
        "tgn:7297115",
        "tgn:7002836",
        "tgn:7016622",
        "tgn:1000003",
        "tgn:1000095",
        "tgn:7029392"
    ],
    "tgn:id":7297115,
    "tgn:name":"Taucho",
    "tgn:placetype":[
        "aat:300008347"
    ]
},
  "bbox": [],
  "geometry": {"coordinates":[-16.716667,28.15],"type":"Point"}
}