{
  "id": 2241210,
  "type": "Feature",
  "properties": {
    "tgn:hierarchy":[
        "tgn:2241210",
        "tgn:1000001",
        "tgn:7012149",
        "tgn:7007255",
        "tgn:7029392"
    ],
    "tgn:id":2241210,
    "tgn:name":"Clark Hollow",
    "tgn:placetype":[
        "aat:300008761"
    ]
},
  "bbox": [],
  "geometry": {"coordinates":[-85.5167,36.8667],"type":"Point"}
}