{
  "id": 7158403,
  "type": "Feature",
  "properties": {
    "tgn:hierarchy":[
        "tgn:7158403",
        "tgn:1000003",
        "tgn:7003678",
        "tgn:7000084",
        "tgn:7029392"
    ],
    "tgn:id":7158403,
    "tgn:name":"H\u00f6llerskopf",
    "tgn:placetype":[
        "aat:300008777"
    ]
},
  "bbox": [],
  "geometry": {"coordinates":[9.133333,50.533333],"type":"Point"}
}