<<<<<<< HEAD
{
  "id": 7371459,
  "type": "Feature",
  "properties": {
    "tgn:hierarchy":[
        "tgn:7371459",
        "tgn:1001853",
        "tgn:1000001",
        "tgn:7005560",
        "tgn:7029392"
    ],
    "tgn:id":7371459,
    "tgn:name":"Hacienda Terreros",
    "tgn:placetype":[
        "aat:300008347"
    ]
},
  "bbox": [],
  "geometry": {"coordinates":[-101.833333,27.383333],"type":"Point"}
}
=======
{"geometry":{"type":"Point","coordinates":[-101.833333,27.383333]},"type":"Feature","properties":{"hierarchy":["tgn:7371459","tgn:1001853","tgn:1000001","tgn:7005560","tgn:7029392"],"placetype":["aat:300008347"],"id":7371459,"name:xx":"Hacienda Terreros"}}
>>>>>>> 03f74aca74312dbeaf24d7e61306dd6a786dc3d0
