{
  "id": 7225543,
  "type": "Feature",
  "properties": {
    "tgn:hierarchy":[
        "tgn:7225543",
        "tgn:7002745",
        "tgn:7017076",
        "tgn:1000003",
        "tgn:1000074",
        "tgn:7029392"
    ],
    "tgn:id":7225543,
    "tgn:name":"Perlengi\u00e1nika",
    "tgn:placetype":[
        "aat:300008347"
    ]
},
  "bbox": [],
  "geometry": {"coordinates":[22.95,36.266667],"type":"Point"}
}