{
  "id": 7497522,
  "type": "Feature",
  "properties": {
    "tgn:hierarchy":[
        "tgn:7497522",
        "tgn:1000004",
        "tgn:7001009",
        "tgn:1000141",
        "tgn:7029392"
    ],
    "tgn:id":7497522,
    "tgn:name":"Guangzheng Qiao",
    "tgn:placetype":[
        "aat:300007836"
    ]
},
  "bbox": [],
  "geometry": {"coordinates":[120.746882,24.197009],"type":"Point"}
}