{
  "id": 2544977,
  "type": "Feature",
  "properties": {
    "tgn:hierarchy":[
        "tgn:2544977",
        "tgn:1000001",
        "tgn:7012149",
        "tgn:7007706",
        "tgn:7029392"
    ],
    "tgn:id":2544977,
    "tgn:name":"North Crooked Creek",
    "tgn:placetype":[
        "aat:300008706"
    ]
},
  "bbox": [],
  "geometry": {"coordinates":[-81.7333,39.9667],"type":"Point"}
}