{
  "id": 2641897,
  "type": "Feature",
  "properties": {
    "tgn:hierarchy":[
        "tgn:2641897",
        "tgn:1000001",
        "tgn:7012149",
        "tgn:2001058",
        "tgn:7007521",
        "tgn:7029392"
    ],
    "tgn:id":2641897,
    "tgn:name":"Sand Lake",
    "tgn:placetype":[
        "aat:300008680"
    ]
},
  "bbox": [],
  "geometry": {"coordinates":[-95.55,47.6333],"type":"Point"}
}