{
  "id": 2550388,
  "type": "Feature",
  "properties": {
    "tgn:hierarchy":[
        "tgn:2550388",
        "tgn:1000001",
        "tgn:7014423",
        "tgn:7012149",
        "tgn:7007517",
        "tgn:7029392"
    ],
    "tgn:id":2550388,
    "tgn:name":"Northwest Duxbury",
    "tgn:placetype":[
        "aat:300008347"
    ]
},
  "bbox": [],
  "geometry": {"coordinates":[-70.7333,42.05],"type":"Point"}
}