{
  "id": 2764513,
  "type": "Feature",
  "properties": {
    "tgn:hierarchy":[
        "tgn:2764513",
        "tgn:1000001",
        "tgn:2001424",
        "tgn:7012149",
        "tgn:7007564",
        "tgn:7029392"
    ],
    "tgn:id":2764513,
    "tgn:name":"Whipple Brook",
    "tgn:placetype":[
        "aat:300008699"
    ]
},
  "bbox": [],
  "geometry": {"coordinates":[-72.0833,43.85],"type":"Point"}
}