{
  "id": 7516100,
  "type": "Feature",
  "properties": {
    "tgn:hierarchy":[
        "tgn:7516100",
        "tgn:1009227",
        "tgn:1000226",
        "tgn:7018437",
        "tgn:1000006",
        "tgn:7029392"
    ],
    "tgn:id":7516100,
    "tgn:name:en":"Moonlight",
    "tgn:placetype":[
        "aat:300008347"
    ]
},
  "bbox": [],
  "geometry": {"coordinates":[170.333333,-45.416667],"type":"Point"}
}