{
  "id": 2026270,
  "type": "Feature",
  "properties": {
    "tgn:hierarchy":[
        "tgn:2026270",
        "tgn:1000001",
        "tgn:7012149",
        "tgn:2000508",
        "tgn:7007251",
        "tgn:7029392"
    ],
    "tgn:id":2026270,
    "tgn:name":"Aden",
    "tgn:placetype":[
        "aat:300008347",
        "aat:300387210"
    ]
},
  "bbox": [],
  "geometry": {"coordinates":[-88.45,38.2333],"type":"Point"}
}