{
  "id": 2067237,
  "type": "Feature",
  "properties": {
    "tgn:hierarchy":[
        "tgn:2067237",
        "tgn:1000001",
        "tgn:7012149",
        "tgn:2001446",
        "tgn:7007566",
        "tgn:7029392"
    ],
    "tgn:id":2067237,
    "tgn:name":"Mora",
    "tgn:placetype":[
        "aat:300008347",
        "aat:300008416"
    ]
},
  "bbox": [],
  "geometry": {"coordinates":[-105.3167,35.9667],"type":"Point"}
}