{
  "id": 7156497,
  "type": "Feature",
  "properties": {
    "tgn:hierarchy":[
        "tgn:7156497",
        "tgn:1000003",
        "tgn:7003676",
        "tgn:7000084",
        "tgn:7029392"
    ],
    "tgn:id":7156497,
    "tgn:name":"Kleines Sager Meer",
    "tgn:placetype":[
        "aat:300008680"
    ]
},
  "bbox": [],
  "geometry": {"coordinates":[8.133333,52.966667],"type":"Point"}
}