{
  "id": 2413615,
  "type": "Feature",
  "properties": {
    "tgn:hierarchy":[
        "tgn:2413615",
        "tgn:1000001",
        "tgn:7006451",
        "tgn:7012149",
        "tgn:2000101",
        "tgn:7029392"
    ],
    "tgn:id":2413615,
    "tgn:name":"Irene Well",
    "tgn:placetype":[
        "aat:300006191"
    ]
},
  "bbox": [],
  "geometry": {"coordinates":[-110.7667,32.5667],"type":"Point"}
}