{
  "id": 2595445,
  "type": "Feature",
  "properties": {
    "tgn:hierarchy":[
        "tgn:2595445",
        "tgn:1000001",
        "tgn:7012149",
        "tgn:2000797",
        "tgn:7007255",
        "tgn:7029392"
    ],
    "tgn:id":2595445,
    "tgn:name":"Potato Hill",
    "tgn:placetype":[
        "aat:300008798"
    ]
},
  "bbox": [],
  "geometry": {"coordinates":[-82.8833,36.8833],"type":"Point"}
}