{
  "id": 1029244,
  "type": "Feature",
  "properties": {
    "tgn:hierarchy":[
        "tgn:1029244",
        "tgn:7002445",
        "tgn:1000003",
        "tgn:7008175",
        "tgn:7008591",
        "tgn:7029392"
    ],
    "tgn:id":1029244,
    "tgn:name":"Fetcham",
    "tgn:placetype":[
        "aat:300008347"
    ]
},
  "bbox": [],
  "geometry": {"coordinates":[-0.3667,51.2833],"type":"Point"}
}