<<<<<<< HEAD
{
  "id": 2259947,
  "type": "Feature",
  "properties": {
    "tgn:hierarchy":[
        "tgn:2259947",
        "tgn:1000001",
        "tgn:7012149",
        "tgn:2000214",
        "tgn:7007158",
        "tgn:7029392"
    ],
    "tgn:id":2259947,
    "tgn:name":"Coulter Reservoir",
    "tgn:placetype":[
        "aat:300006191"
    ]
},
  "bbox": [],
  "geometry": {"coordinates":[-107.6833,39.75],"type":"Point"}
}
=======
{"geometry":{"type":"Point","coordinates":[-107.683300,39.750000]},"type":"Feature","properties":{"hierarchy":["tgn:2259947","tgn:1000001","tgn:7012149","tgn:2000214","tgn:7007158","tgn:7029392"],"placetype":["aat:300006191"],"id":2259947,"name:xx":"Coulter Reservoir"}}
>>>>>>> 03f74aca74312dbeaf24d7e61306dd6a786dc3d0
