{
  "id": 2202577,
  "type": "Feature",
  "properties": {
    "tgn:hierarchy":[
        "tgn:2202577",
        "tgn:1000001",
        "tgn:2002258",
        "tgn:7012149",
        "tgn:7013961",
        "tgn:7029392"
    ],
    "tgn:id":2202577,
    "tgn:name":"Buck Shuck Run",
    "tgn:placetype":[
        "aat:300008699"
    ]
},
  "bbox": [],
  "geometry": {"coordinates":[-81.1333,38.9833],"type":"Point"}
}