{
  "id": 2011592,
  "type": "Feature",
  "properties": {
    "tgn:hierarchy":[
        "tgn:2011592",
        "tgn:1000001",
        "tgn:7012149",
        "tgn:7007157",
        "tgn:1002608",
        "tgn:7029392"
    ],
    "tgn:id":2011592,
    "tgn:name":"Gorman",
    "tgn:placetype":[
        "aat:300008347"
    ]
},
  "bbox": [],
  "geometry": {"coordinates":[-118.85,34.7833],"type":"Point"}
}