{
  "id": 2677168,
  "type": "Feature",
  "properties": {
    "tgn:hierarchy":[
        "tgn:2677168",
        "tgn:1000001",
        "tgn:7012149",
        "tgn:1002588",
        "tgn:7007520",
        "tgn:7029392"
    ],
    "tgn:id":2677168,
    "tgn:name":"South Branch Stony Creek",
    "tgn:placetype":[
        "aat:300008706"
    ]
},
  "bbox": [],
  "geometry": {"coordinates":[-84.1333,41.7833],"type":"Point"}
}