{
  "id": 7459887,
  "type": "Feature",
  "properties": {
    "tgn:hierarchy":[
        "tgn:7459887",
        "tgn:7002445",
        "tgn:7011980",
        "tgn:1000003",
        "tgn:7008591",
        "tgn:7029392"
    ],
    "tgn:id":7459887,
    "tgn:name:en":"Old North Road Station",
    "tgn:placetype":[
        "aat:300007783"
    ]
},
  "bbox": [],
  "geometry": {"coordinates":[-0.066667,52.166667],"type":"Point"}
}