{
  "id": 7043046,
  "type": "Feature",
  "properties": {
    "tgn:hierarchy":[
        "tgn:7043046",
        "tgn:1003506",
        "tgn:1000003",
        "tgn:7002993",
        "tgn:1000080",
        "tgn:7029392"
    ],
    "tgn:id":7043046,
    "tgn:name":"Remanzacco",
    "tgn:placetype":[
        "aat:300008347"
    ]
},
  "bbox": [],
  "geometry": {"coordinates":[13.324444,46.086667],"type":"Point"}
}