{
  "id": 1045301,
  "type": "Feature",
  "properties": {
    "tgn:hierarchy":[
        "tgn:1045301",
        "tgn:7003128",
        "tgn:1000003",
        "tgn:7008516",
        "tgn:1000080",
        "tgn:7029392"
    ],
    "tgn:id":1045301,
    "tgn:name":"Massa Fiscaglia",
    "tgn:placetype":[
        "aat:300008347"
    ]
},
  "bbox": [],
  "geometry": {"coordinates":[12.028889,44.796944],"type":"Point"}
}