{
  "id": 2525539,
  "type": "Feature",
  "properties": {
    "tgn:hierarchy":[
        "tgn:2525539",
        "tgn:1000001",
        "tgn:7012149",
        "tgn:2001609",
        "tgn:7007705",
        "tgn:7029392"
    ],
    "tgn:id":2525539,
    "tgn:name":"Mort Adams Spring",
    "tgn:placetype":[
        "aat:300008697"
    ]
},
  "bbox": [],
  "geometry": {"coordinates":[-103.2333,48.1833],"type":"Point"}
}