{
  "id": 7554497,
  "type": "Feature",
  "properties": {
    "tgn:hierarchy":[
        "tgn:7554497",
        "tgn:1000004",
        "tgn:7000198",
        "tgn:1003539",
        "tgn:7029392"
    ],
    "tgn:id":7554497,
    "tgn:name:en":"Nongkrem",
    "tgn:placetype":[
        "aat:300008347"
    ]
},
  "bbox": [],
  "geometry": {"coordinates":[91.879906,25.496568],"type":"Point"}
}