{
  "id": 2111053,
  "type": "Feature",
  "properties": {
    "tgn:hierarchy":[
        "tgn:2111053",
        "tgn:1000001",
        "tgn:7012149",
        "tgn:2002179",
        "tgn:7007919",
        "tgn:7029392"
    ],
    "tgn:id":2111053,
    "tgn:name":"Charity",
    "tgn:placetype":[
        "aat:300008347",
        "aat:300387210"
    ]
},
  "bbox": [],
  "geometry": {"coordinates":[-80.2167,36.8167],"type":"Point"}
}