{
  "id": 7504664,
  "type": "Feature",
  "properties": {
    "tgn:hierarchy":[
        "tgn:7504664",
        "tgn:1008380",
        "tgn:1000226",
        "tgn:7018426",
        "tgn:1000006",
        "tgn:7029392"
    ],
    "tgn:id":7504664,
    "tgn:name:en":"Town Reach",
    "tgn:placetype":[
        "aat:300386862"
    ]
},
  "bbox": [],
  "geometry": {"coordinates":[176.175,-37.675],"type":"Point"}
}