{
  "id": 1004943,
  "type": "Feature",
  "properties": {
    "tgn:hierarchy":[
        "tgn:1004943",
        "tgn:7003150",
        "tgn:1000003",
        "tgn:7003237",
        "tgn:7005903",
        "tgn:1000080",
        "tgn:7029392"
    ],
    "tgn:id":1004943,
    "tgn:name":"Lambrate",
    "tgn:placetype":[
        "aat:300008347",
        "aat:300387336"
    ]
},
  "bbox": [],
  "geometry": {"coordinates":[9.25,45.4833],"type":"Point"}
}