{
  "id": 2548649,
  "type": "Feature",
  "properties": {
    "tgn:hierarchy":[
        "tgn:2548649",
        "tgn:1000001",
        "tgn:7012149",
        "tgn:2002342",
        "tgn:7007922",
        "tgn:7029392"
    ],
    "tgn:id":2548649,
    "tgn:name":"North Nokomis Lake",
    "tgn:placetype":[
        "aat:300008680"
    ]
},
  "bbox": [],
  "geometry": {"coordinates":[-89.45,45.85],"type":"Point"}
}