{
  "id": 1035276,
  "type": "Feature",
  "properties": {
    "tgn:hierarchy":[
        "tgn:1035276",
        "tgn:1000003",
        "tgn:7002875",
        "tgn:1000070",
        "tgn:7029392"
    ],
    "tgn:id":1035276,
    "tgn:name":"Saint-Broing-les-Moines",
    "tgn:placetype":[
        "aat:300008347"
    ]
},
  "bbox": [],
  "geometry": {"coordinates":[4.8333,47.6833],"type":"Point"}
}