{
  "id": 7307113,
  "type": "Feature",
  "properties": {
    "tgn:hierarchy":[
        "tgn:7307113",
        "tgn:7002839",
        "tgn:7001158",
        "tgn:1000003",
        "tgn:1000095",
        "tgn:7029392"
    ],
    "tgn:id":7307113,
    "tgn:name":"Mart\u00edn Miguel",
    "tgn:placetype":[
        "aat:300008347"
    ]
},
  "bbox": [],
  "geometry": {"coordinates":[-4.266667,40.95],"type":"Point"}
}