{
  "id": 7556838,
  "type": "Feature",
  "properties": {
    "tgn:hierarchy":[
        "tgn:7556838",
        "tgn:1000004",
        "tgn:7000198",
        "tgn:7016788",
        "tgn:7029392"
    ],
    "tgn:id":7556838,
    "tgn:name:en":"P\u012bpald\u0101",
    "tgn:placetype":[
        "aat:300008347"
    ]
},
  "bbox": [],
  "geometry": {"coordinates":[76.341578,26.395405],"type":"Point"}
}