<<<<<<< HEAD
{
  "id": 7471262,
  "type": "Feature",
  "properties": {
    "tgn:hierarchy":[
        "tgn:7471262",
        "tgn:1000004",
        "tgn:7492971",
        "tgn:1000141",
        "tgn:7029392"
    ],
    "tgn:id":7471262,
    "tgn:name":"Houdacuo",
    "tgn:placetype":[
        "aat:300008347"
    ]
},
  "bbox": [],
  "geometry": {"coordinates":[120.38973,22.494895],"type":"Point"}
}
=======
{"geometry":{"type":"Point","coordinates":[120.389730,22.494895]},"type":"Feature","properties":{"hierarchy":["tgn:7471262","tgn:1000004","tgn:7492971","tgn:1000141","tgn:7029392"],"placetype":["aat:300008347"],"id":7471262,"name:xx":"Houdacuo"}}
>>>>>>> 03f74aca74312dbeaf24d7e61306dd6a786dc3d0
