{
  "id": 7429647,
  "type": "Feature",
  "properties": {
    "tgn:hierarchy":[
        "tgn:7429647",
        "tgn:7005583",
        "tgn:1000001",
        "tgn:7005560",
        "tgn:7029392"
    ],
    "tgn:id":7429647,
    "tgn:name":"Estaci\u00f3n Sabalo",
    "tgn:placetype":[
        "aat:300007783"
    ]
},
  "bbox": [],
  "geometry": {"coordinates":[-104.733333,24.333333],"type":"Point"}
}