{
  "id": 7184003,
  "type": "Feature",
  "properties": {
    "tgn:hierarchy":[
        "tgn:7184003",
        "tgn:7003669",
        "tgn:1000003",
        "tgn:7000084",
        "tgn:7029392"
    ],
    "tgn:id":7184003,
    "tgn:name":"Gottfriedinger Schwaig",
    "tgn:placetype":[
        "aat:300008347"
    ]
},
  "bbox": [],
  "geometry": {"coordinates":[12.533333,48.65],"type":"Point"}
}