{
  "id": 2359996,
  "type": "Feature",
  "properties": {
    "tgn:hierarchy":[
        "tgn:2359996",
        "tgn:1000001",
        "tgn:7012149",
        "tgn:2002371",
        "tgn:7007923",
        "tgn:7029392"
    ],
    "tgn:id":2359996,
    "tgn:name":"Grass Creek",
    "tgn:placetype":[
        "aat:300008706"
    ]
},
  "bbox": [],
  "geometry": {"coordinates":[-109.85,43.5167],"type":"Point"}
}