{
  "id": 2517123,
  "type": "Feature",
  "properties": {
    "tgn:hierarchy":[
        "tgn:2517123",
        "tgn:1000001",
        "tgn:7012149",
        "tgn:2002270",
        "tgn:7013961",
        "tgn:7029392"
    ],
    "tgn:id":2517123,
    "tgn:name":"Mink Shoals",
    "tgn:placetype":[
        "aat:300132348"
    ]
},
  "bbox": [],
  "geometry": {"coordinates":[-81.5833,38.3833],"type":"Point"}
}