{
  "id": 7324510,
  "type": "Feature",
  "properties": {
    "tgn:hierarchy":[
        "tgn:7324510",
        "tgn:7002849",
        "tgn:1000003",
        "tgn:7009604",
        "tgn:1000095",
        "tgn:7029392"
    ],
    "tgn:id":7324510,
    "tgn:name":"Santa Mar\u00eda de Lezama",
    "tgn:placetype":[
        "aat:300008347"
    ]
},
  "bbox": [],
  "geometry": {"coordinates":[-2.834379,43.274279],"type":"Point"}
}