{
  "id": 7314030,
  "type": "Feature",
  "properties": {
    "tgn:hierarchy":[
        "tgn:7314030",
        "tgn:1001692",
        "tgn:1000049",
        "tgn:1000002",
        "tgn:7029392"
    ],
    "tgn:id":7314030,
    "tgn:name":"Llallehue, Estero",
    "tgn:placetype":[
        "aat:300008699"
    ]
},
  "bbox": [],
  "geometry": {"coordinates":[-73.216667,-38.85],"type":"Point"}
}