<<<<<<< HEAD
{
  "id": 7170414,
  "type": "Feature",
  "properties": {
    "tgn:hierarchy":[
        "tgn:7170414",
        "tgn:7003669",
        "tgn:1000003",
        "tgn:7000084",
        "tgn:7029392"
    ],
    "tgn:id":7170414,
    "tgn:name":"Hinterau",
    "tgn:placetype":[
        "aat:300008347"
    ]
},
  "bbox": [],
  "geometry": {"coordinates":[12.9,48.3],"type":"Point"}
}
=======
{"geometry":{"type":"Point","coordinates":[12.900000,48.300000]},"type":"Feature","properties":{"hierarchy":["tgn:7170414","tgn:7003669","tgn:1000003","tgn:7000084","tgn:7029392"],"placetype":["aat:300008347"],"id":7170414,"name:xx":"Hinterau"}}
>>>>>>> 03f74aca74312dbeaf24d7e61306dd6a786dc3d0
