{
  "id": 2296059,
  "type": "Feature",
  "properties": {
    "tgn:hierarchy":[
        "tgn:2296059",
        "tgn:7002659",
        "tgn:1000001",
        "tgn:7012149",
        "tgn:2000060",
        "tgn:7029392"
    ],
    "tgn:id":2296059,
    "tgn:name":"Dry Branch",
    "tgn:placetype":[
        "aat:300008699"
    ]
},
  "bbox": [],
  "geometry": {"coordinates":[-85.8333,33.5167],"type":"Point"}
}