{
  "id": 2654565,
  "type": "Feature",
  "properties": {
    "tgn:hierarchy":[
        "tgn:2654565",
        "tgn:1000001",
        "tgn:7012149",
        "tgn:1002862",
        "tgn:7007920",
        "tgn:7029392"
    ],
    "tgn:id":2654565,
    "tgn:name":"Shag Rock",
    "tgn:placetype":[
        "aat:300008791"
    ]
},
  "bbox": [],
  "geometry": {"coordinates":[-122.8667,48.5833],"type":"Point"}
}