{
  "id": 1090379,
  "type": "Feature",
  "properties": {
    "tgn:hierarchy":[
        "tgn:1090379",
        "tgn:7001242",
        "tgn:1000684",
        "tgn:1000168",
        "tgn:7029392"
    ],
    "tgn:id":1090379,
    "tgn:name":"Man",
    "tgn:placetype":[
        "aat:300008347",
        "aat:300387264",
        "aat:300008375",
        "aat:300387291",
        "aat:300387286"
    ]
},
  "bbox": [],
  "geometry": {"coordinates":[-7.6167,7.5667],"type":"Point"}
}