{
  "id": 7291361,
  "type": "Feature",
  "properties": {
    "tgn:hierarchy":[
        "tgn:7291361",
        "tgn:1001623",
        "tgn:1000049",
        "tgn:1000002",
        "tgn:7029392"
    ],
    "tgn:id":7291361,
    "tgn:name":"Fr\u00edo, Lago",
    "tgn:placetype":[
        "aat:300008680"
    ]
},
  "bbox": [],
  "geometry": {"coordinates":[-71.933333,-45.666667],"type":"Point"}
}