{
  "id": 2205930,
  "type": "Feature",
  "properties": {
    "tgn:hierarchy":[
        "tgn:2205930",
        "tgn:1000001",
        "tgn:7012149",
        "tgn:2000216",
        "tgn:7007158",
        "tgn:7029392"
    ],
    "tgn:id":2205930,
    "tgn:name":"Bull Run",
    "tgn:placetype":[
        "aat:300008699"
    ]
},
  "bbox": [],
  "geometry": {"coordinates":[-106.2667,39.9333],"type":"Point"}
}