{
  "id": 2614309,
  "type": "Feature",
  "properties": {
    "tgn:hierarchy":[
        "tgn:2614309",
        "tgn:1000001",
        "tgn:7012149",
        "tgn:2002119",
        "tgn:7007827",
        "tgn:7029392"
    ],
    "tgn:id":2614309,
    "tgn:name":"Register Rock",
    "tgn:placetype":[
        "aat:300008791"
    ]
},
  "bbox": [],
  "geometry": {"coordinates":[-110.8667,37.2333],"type":"Point"}
}