<<<<<<< HEAD
{
  "id": 2403663,
  "type": "Feature",
  "properties": {
    "tgn:hierarchy":[
        "tgn:2403663",
        "tgn:1000001",
        "tgn:7016172",
        "tgn:2000113",
        "tgn:7012149",
        "tgn:7029392"
    ],
    "tgn:id":2403663,
    "tgn:name":"Howard Island",
    "tgn:placetype":[
        "aat:300055621"
    ]
},
  "bbox": [],
  "geometry": {"coordinates":[-91.1167,33.1333],"type":"Point"}
}
=======
{"geometry":{"type":"Point","coordinates":[-91.116700,33.133300]},"type":"Feature","properties":{"hierarchy":["tgn:2403663","tgn:1000001","tgn:7016172","tgn:2000113","tgn:7012149","tgn:7029392"],"placetype":["aat:300055621"],"id":2403663,"name:xx":"Howard Island"}}
>>>>>>> 03f74aca74312dbeaf24d7e61306dd6a786dc3d0
