{
  "id": 7074704,
  "type": "Feature",
  "properties": {
    "tgn:hierarchy":[
        "tgn:7074704",
        "tgn:7003669",
        "tgn:1000003",
        "tgn:7000084",
        "tgn:7029392"
    ],
    "tgn:id":7074704,
    "tgn:name":"Kolmsdorf",
    "tgn:placetype":[
        "aat:300008347"
    ]
},
  "bbox": [],
  "geometry": {"coordinates":[10.75,49.883333],"type":"Point"}
}