<<<<<<< HEAD
{
  "id": 2767846,
  "type": "Feature",
  "properties": {
    "tgn:hierarchy":[
        "tgn:2767846",
        "tgn:2000854",
        "tgn:1000001",
        "tgn:7012149",
        "tgn:7007256",
        "tgn:7029392"
    ],
    "tgn:id":2767846,
    "tgn:name":"Whitehouse",
    "tgn:placetype":[
        "aat:300008347"
    ]
},
  "bbox": [],
  "geometry": {"coordinates":[-92.6,30.3],"type":"Point"}
}
=======
{"geometry":{"type":"Point","coordinates":[-92.600000,30.300000]},"type":"Feature","properties":{"hierarchy":["tgn:2767846","tgn:2000854","tgn:1000001","tgn:7012149","tgn:7007256","tgn:7029392"],"placetype":["aat:300008347"],"id":2767846,"name:xx":"Whitehouse"}}
>>>>>>> 03f74aca74312dbeaf24d7e61306dd6a786dc3d0
