{
  "id": 7232585,
  "type": "Feature",
  "properties": {
    "tgn:hierarchy":[
        "tgn:7232585",
        "tgn:7011167",
        "tgn:7001338",
        "tgn:1000003",
        "tgn:1000074",
        "tgn:7029392"
    ],
    "tgn:id":7232585,
    "tgn:name":"Makhair\u00e1dhon",
    "tgn:placetype":[
        "aat:300008347"
    ]
},
  "bbox": [],
  "geometry": {"coordinates":[20.816667,37.766667],"type":"Point"}
}