{
  "id": 7226129,
  "type": "Feature",
  "properties": {
    "tgn:hierarchy":[
        "tgn:7226129",
        "tgn:7002681",
        "tgn:7001395",
        "tgn:1000003",
        "tgn:1000074",
        "tgn:7029392"
    ],
    "tgn:id":7226129,
    "tgn:name":"Souryi\u00e9s, \u00c1kra",
    "tgn:placetype":[
        "aat:300008850"
    ]
},
  "bbox": [],
  "geometry": {"coordinates":[23.283333,37.266667],"type":"Point"}
}