{
  "id": 7319579,
  "type": "Feature",
  "properties": {
    "tgn:hierarchy":[
        "tgn:7319579",
        "tgn:7002464",
        "tgn:1000049",
        "tgn:1000002",
        "tgn:7029392"
    ],
    "tgn:id":7319579,
    "tgn:name":"Alona",
    "tgn:placetype":[
        "aat:300008347"
    ]
},
  "bbox": [],
  "geometry": {"coordinates":[-68.983333,-20.633333],"type":"Point"}
}