{
  "id": 7474133,
  "type": "Feature",
  "properties": {
    "tgn:hierarchy":[
        "tgn:7474133",
        "tgn:1000004",
        "tgn:7489179",
        "tgn:1000141",
        "tgn:7029392"
    ],
    "tgn:id":7474133,
    "tgn:name":"Yuantong Si",
    "tgn:placetype":[
        "aat:300007595"
    ]
},
  "bbox": [],
  "geometry": {"coordinates":[121.773333,24.857222],"type":"Point"}
}