{
  "id": 7010972,
  "type": "Feature",
  "properties": {
    "tgn:hierarchy":[
        "tgn:7010972",
        "tgn:1000810",
        "tgn:1000003",
        "tgn:1000090",
        "tgn:7029392"
    ],
    "tgn:id":7010972,
    "tgn:name":"Moura",
    "tgn:placetype":[
        "aat:300008347",
        "aat:300387218"
    ]
},
  "bbox": [],
  "geometry": {"coordinates":[-7.448,38.14],"type":"Point"}
}