{
  "id": 7275211,
  "type": "Feature",
  "properties": {
    "tgn:hierarchy":[
        "tgn:7275211",
        "tgn:1001699",
        "tgn:1000049",
        "tgn:1000002",
        "tgn:7029392"
    ],
    "tgn:id":7275211,
    "tgn:name":"Urano, Islote",
    "tgn:placetype":[
        "aat:300008791"
    ]
},
  "bbox": [],
  "geometry": {"coordinates":[-74.016667,-43.766667],"type":"Point"}
}