<<<<<<< HEAD
{
  "id": 7351392,
  "type": "Feature",
  "properties": {
    "tgn:hierarchy":[
        "tgn:7351392",
        "tgn:1000001",
        "tgn:1001960",
        "tgn:7005560",
        "tgn:7029392"
    ],
    "tgn:id":7351392,
    "tgn:name":"B\u00e1mori",
    "tgn:placetype":[
        "aat:300387007"
    ]
},
  "bbox": [],
  "geometry": {"coordinates":[-110.216667,29.25],"type":"Point"}
}
=======
{"geometry":{"type":"Point","coordinates":[-110.216667,29.250000]},"type":"Feature","properties":{"hierarchy":["tgn:7351392","tgn:1000001","tgn:1001960","tgn:7005560","tgn:7029392"],"placetype":["aat:300387007"],"id":7351392,"name:xx":"B\u00e1mori"}}
>>>>>>> 03f74aca74312dbeaf24d7e61306dd6a786dc3d0
