{
  "id": 1036580,
  "type": "Feature",
  "properties": {
    "tgn:hierarchy":[
        "tgn:1036580",
        "tgn:7000096",
        "tgn:1000003",
        "tgn:7000084",
        "tgn:7029392"
    ],
    "tgn:id":1036580,
    "tgn:name":"Dallgow",
    "tgn:placetype":[
        "aat:300008347"
    ]
},
  "bbox": [],
  "geometry": {"coordinates":[13.083333,52.516667],"type":"Point"}
}