{
  "id": 2462219,
  "type": "Feature",
  "properties": {
    "tgn:hierarchy":[
        "tgn:2462219",
        "tgn:1000001",
        "tgn:2000600",
        "tgn:7012149",
        "tgn:7007253",
        "tgn:7029392"
    ],
    "tgn:id":2462219,
    "tgn:name":"Little Wall Lake",
    "tgn:placetype":[
        "aat:300008680"
    ]
},
  "bbox": [],
  "geometry": {"coordinates":[-93.6333,42.2667],"type":"Point"}
}