{
  "id": 2527194,
  "type": "Feature",
  "properties": {
    "tgn:hierarchy":[
        "tgn:2527194",
        "tgn:1000001",
        "tgn:1002493",
        "tgn:7012149",
        "tgn:7007565",
        "tgn:7029392"
    ],
    "tgn:id":2527194,
    "tgn:name":"Mount Joy",
    "tgn:placetype":[
        "aat:300008347"
    ]
},
  "bbox": [],
  "geometry": {"coordinates":[-75.1833,40.5833],"type":"Point"}
}