{
  "id": 7544356,
  "type": "Feature",
  "properties": {
    "tgn:hierarchy":[
        "tgn:7544356",
        "tgn:7001242",
        "tgn:1001059",
        "tgn:7016833",
        "tgn:7029392"
    ],
    "tgn:id":7544356,
    "tgn:name:en":"Zaw\u0101'ir, Maq\u0163a'",
    "tgn:placetype":[
        "aat:300008713"
    ]
},
  "bbox": [],
  "geometry": {"coordinates":[31.929167,31.284722],"type":"Point"}
}