{
  "id": 2549479,
  "type": "Feature",
  "properties": {
    "tgn:hierarchy":[
        "tgn:2549479",
        "tgn:2000456",
        "tgn:1000001",
        "tgn:7012149",
        "tgn:7007250",
        "tgn:7029392"
    ],
    "tgn:id":2549479,
    "tgn:name":"North South Ski Bowl",
    "tgn:placetype":[
        "aat:300008347"
    ]
},
  "bbox": [],
  "geometry": {"coordinates":[-116.65,47.1167],"type":"Point"}
}