{
  "id": 7467176,
  "type": "Feature",
  "properties": {
    "tgn:hierarchy":[
        "tgn:7467176",
        "tgn:7002444",
        "tgn:1000003",
        "tgn:5000451",
        "tgn:7008591",
        "tgn:7029392"
    ],
    "tgn:id":7467176,
    "tgn:name:en":"Bridge of Achbreck",
    "tgn:placetype":[
        "aat:300008347"
    ]
},
  "bbox": [],
  "geometry": {"coordinates":[-3.316667,57.333333],"type":"Point"}
}