{
  "id": 2232188,
  "type": "Feature",
  "properties": {
    "tgn:hierarchy":[
        "tgn:2232188",
        "tgn:1000001",
        "tgn:7012149",
        "tgn:1002794",
        "tgn:7007708",
        "tgn:7029392"
    ],
    "tgn:id":2232188,
    "tgn:name":"Chandler",
    "tgn:placetype":[
        "aat:300008347"
    ]
},
  "bbox": [],
  "geometry": {"coordinates":[-123.6833,44.7833],"type":"Point"}
}