{
  "id": 1018946,
  "type": "Feature",
  "properties": {
    "tgn:hierarchy":[
        "tgn:1018946",
        "tgn:7017437",
        "tgn:1000001",
        "tgn:7004643",
        "tgn:7029392"
    ],
    "tgn:id":1018946,
    "tgn:name":"El Polvor\u00edn",
    "tgn:placetype":[
        "aat:300008347"
    ]
},
  "bbox": [],
  "geometry": {"coordinates":[-66.2833,18.4333],"type":"Point"}
}