{
  "id": 7405722,
  "type": "Feature",
  "properties": {
    "tgn:hierarchy":[
        "tgn:7405722",
        "tgn:7005585",
        "tgn:1000001",
        "tgn:7005560",
        "tgn:7029392"
    ],
    "tgn:id":7405722,
    "tgn:name":"Tepetlazingo",
    "tgn:placetype":[
        "aat:300008347"
    ]
},
  "bbox": [],
  "geometry": {"coordinates":[-98.833333,18.016667],"type":"Point"}
}