{
  "id": 1015446,
  "type": "Feature",
  "properties": {
    "tgn:hierarchy":[
        "tgn:1015446",
        "tgn:7005685",
        "tgn:1000001",
        "tgn:7005804",
        "tgn:7029392"
    ],
    "tgn:id":1015446,
    "tgn:name":"La Guadeloupe",
    "tgn:placetype":[
        "aat:300008347"
    ]
},
  "bbox": [],
  "geometry": {"coordinates":[-70.95,45.9667],"type":"Point"}
}