{
  "id": 2246815,
  "type": "Feature",
  "properties": {
    "tgn:hierarchy":[
        "tgn:2246815",
        "tgn:1000001",
        "tgn:7006451",
        "tgn:7012149",
        "tgn:7029392"
    ],
    "tgn:id":2246815,
    "tgn:name":"Coches Canyon",
    "tgn:placetype":[
        "aat:300008761"
    ]
},
  "bbox": [],
  "geometry": {"coordinates":[-111.3667,31.4667],"type":"Point"}
}