{
  "id": 2306372,
  "type": "Feature",
  "properties": {
    "tgn:hierarchy":[
        "tgn:2306372",
        "tgn:7006450",
        "tgn:1000001",
        "tgn:7012149",
        "tgn:2000086",
        "tgn:7029392"
    ],
    "tgn:id":2306372,
    "tgn:name":"East Fork Chistochina River",
    "tgn:placetype":[
        "aat:300008707"
    ]
},
  "bbox": [],
  "geometry": {"coordinates":[-144.4667,62.9833],"type":"Point"}
}