<<<<<<< HEAD
{
  "id": 2150201,
  "type": "Feature",
  "properties": {
    "tgn:hierarchy":[
        "tgn:2150201",
        "tgn:1000001",
        "tgn:7012149",
        "tgn:2002248",
        "tgn:7007920",
        "tgn:7029392"
    ],
    "tgn:id":2150201,
    "tgn:name":"Basalt Hill",
    "tgn:placetype":[
        "aat:300008798"
    ]
},
  "bbox": [],
  "geometry": {"coordinates":[-117.3667,48.9167],"type":"Point"}
}
=======
{"geometry":{"type":"Point","coordinates":[-117.366700,48.916700]},"type":"Feature","properties":{"hierarchy":["tgn:2150201","tgn:1000001","tgn:7012149","tgn:2002248","tgn:7007920","tgn:7029392"],"placetype":["aat:300008798"],"id":2150201,"name:xx":"Basalt Hill"}}
>>>>>>> 03f74aca74312dbeaf24d7e61306dd6a786dc3d0
