{
  "id": 2202344,
  "type": "Feature",
  "properties": {
    "tgn:hierarchy":[
        "tgn:2202344",
        "tgn:1000001",
        "tgn:7006451",
        "tgn:2000095",
        "tgn:7012149",
        "tgn:7029392"
    ],
    "tgn:id":2202344,
    "tgn:name":"Buck Park Tank",
    "tgn:placetype":[
        "aat:300006191"
    ]
},
  "bbox": [],
  "geometry": {"coordinates":[-109.2833,33.2167],"type":"Point"}
}