{
  "id": 7491144,
  "type": "Feature",
  "properties": {
    "tgn:hierarchy":[
        "tgn:7491144",
        "tgn:1000004",
        "tgn:7001009",
        "tgn:1000141",
        "tgn:7029392"
    ],
    "tgn:id":7491144,
    "tgn:name":"Shiwan Shan",
    "tgn:placetype":[
        "aat:300008798"
    ]
},
  "bbox": [],
  "geometry": {"coordinates":[121.061389,24.313889],"type":"Point"}
}