{
  "id": 7446186,
  "type": "Feature",
  "properties": {
    "tgn:hierarchy":[
        "tgn:7446186",
        "tgn:7002445",
        "tgn:1000003",
        "tgn:7008117",
        "tgn:7008591",
        "tgn:7029392"
    ],
    "tgn:id":7446186,
    "tgn:name:en":"Scalehouses",
    "tgn:placetype":[
        "aat:300008347"
    ]
},
  "bbox": [],
  "geometry": {"coordinates":[-2.633333,54.783333],"type":"Point"}
}