{
  "id": 1114012,
  "type": "Feature",
  "properties": {
    "tgn:hierarchy":[
        "tgn:1114012",
        "tgn:7002445",
        "tgn:7008116",
        "tgn:1000003",
        "tgn:7008591",
        "tgn:7029392"
    ],
    "tgn:id":1114012,
    "tgn:name:en":"Watergate Bay",
    "tgn:placetype":[
        "aat:300132316"
    ]
},
  "bbox": [],
  "geometry": {"coordinates":[-5.05,50.466667],"type":"Point"}
}