{
  "id": 2500524,
  "type": "Feature",
  "properties": {
    "tgn:hierarchy":[
        "tgn:2500524",
        "tgn:1000001",
        "tgn:7012149",
        "tgn:2002174",
        "tgn:7007919",
        "tgn:7029392"
    ],
    "tgn:id":2500524,
    "tgn:name":"McDonald Hollow",
    "tgn:placetype":[
        "aat:300008761"
    ]
},
  "bbox": [],
  "geometry": {"coordinates":[-80.4833,37.2333],"type":"Point"}
}