<<<<<<< HEAD
{
  "id": 7171805,
  "type": "Feature",
  "properties": {
    "tgn:hierarchy":[
        "tgn:7171805",
        "tgn:1000003",
        "tgn:7003687",
        "tgn:7000084",
        "tgn:7029392"
    ],
    "tgn:id":7171805,
    "tgn:name":"Hilgesdorf",
    "tgn:placetype":[
        "aat:300008347"
    ]
},
  "bbox": [],
  "geometry": {"coordinates":[11.2,52.3],"type":"Point"}
}
=======
{"geometry":{"type":"Point","coordinates":[11.200000,52.300000]},"type":"Feature","properties":{"hierarchy":["tgn:7171805","tgn:1000003","tgn:7003687","tgn:7000084","tgn:7029392"],"placetype":["aat:300008347"],"id":7171805,"name:xx":"Hilgesdorf"}}
>>>>>>> 03f74aca74312dbeaf24d7e61306dd6a786dc3d0
