<<<<<<< HEAD
{
  "id": 2765540,
  "type": "Feature",
  "properties": {
    "tgn:hierarchy":[
        "tgn:2765540",
        "tgn:1000001",
        "tgn:7012149",
        "tgn:7007826",
        "tgn:7029392"
    ],
    "tgn:id":2765540,
    "tgn:name":"White Canyon",
    "tgn:placetype":[
        "aat:300008761"
    ]
},
  "bbox": [],
  "geometry": {"coordinates":[-100.4167,32.8833],"type":"Point"}
}
=======
{"geometry":{"type":"Point","coordinates":[-100.416700,32.883300]},"type":"Feature","properties":{"hierarchy":["tgn:2765540","tgn:1000001","tgn:7012149","tgn:7007826","tgn:7029392"],"placetype":["aat:300008761"],"id":2765540,"name:xx":"White Canyon"}}
>>>>>>> 03f74aca74312dbeaf24d7e61306dd6a786dc3d0
