{
  "id": 2765540,
  "type": "Feature",
  "properties": {
    "tgn:hierarchy":[
        "tgn:2765540",
        "tgn:1000001",
        "tgn:7012149",
        "tgn:7007826",
        "tgn:7029392"
    ],
    "tgn:id":2765540,
    "tgn:name":"White Canyon",
    "tgn:placetype":[
        "aat:300008761"
    ]
},
  "bbox": [],
  "geometry": {"coordinates":[-100.4167,32.8833],"type":"Point"}
}