{
  "id": 1006336,
  "type": "Feature",
  "properties": {
    "tgn:hierarchy":[
        "tgn:1006336",
        "tgn:7005332",
        "tgn:1000001",
        "tgn:7029392"
    ],
    "tgn:id":1006336,
    "tgn:name":"Athol Island",
    "tgn:placetype":[
        "aat:300008791"
    ]
},
  "bbox": [],
  "geometry": {"coordinates":[-77.2667,25.0833],"type":"Point"}
}