<<<<<<< HEAD
{
  "id": 2335773,
  "type": "Feature",
  "properties": {
    "tgn:hierarchy":[
        "tgn:2335773",
        "tgn:7006450",
        "tgn:1000001",
        "tgn:7012149",
        "tgn:2000085",
        "tgn:7029392"
    ],
    "tgn:id":2335773,
    "tgn:name":"Fortyfive Pup",
    "tgn:placetype":[
        "aat:300008699"
    ]
},
  "bbox": [],
  "geometry": {"coordinates":[-142.2,64.2333],"type":"Point"}
}
=======
{"geometry":{"type":"Point","coordinates":[-142.200000,64.233300]},"type":"Feature","properties":{"hierarchy":["tgn:2335773","tgn:7006450","tgn:1000001","tgn:7012149","tgn:2000085","tgn:7029392"],"placetype":["aat:300008699"],"id":2335773,"name:xx":"Fortyfive Pup"}}
>>>>>>> 03f74aca74312dbeaf24d7e61306dd6a786dc3d0
