{
  "id": 7418536,
  "type": "Feature",
  "properties": {
    "tgn:hierarchy":[
        "tgn:7418536",
        "tgn:7005579",
        "tgn:1000001",
        "tgn:7005560",
        "tgn:7029392"
    ],
    "tgn:id":7418536,
    "tgn:name":"El Venado, Cerro",
    "tgn:placetype":[
        "aat:300008795"
    ]
},
  "bbox": [],
  "geometry": {"coordinates":[-102.495833,21.775],"type":"Point"}
}