{
  "id": 2121231,
  "type": "Feature",
  "properties": {
    "tgn:hierarchy":[
        "tgn:2121231",
        "tgn:1000001",
        "tgn:7012149",
        "tgn:1002537",
        "tgn:7007922",
        "tgn:7029392"
    ],
    "tgn:id":2121231,
    "tgn:name":"Fox River",
    "tgn:placetype":[
        "aat:300008347"
    ]
},
  "bbox": [],
  "geometry": {"coordinates":[-88.1833,42.55],"type":"Point"}
}