{
  "id": 2033382,
  "type": "Feature",
  "properties": {
    "tgn:hierarchy":[
        "tgn:2033382",
        "tgn:1000001",
        "tgn:7012149",
        "tgn:1002750",
        "tgn:7007252",
        "tgn:7029392"
    ],
    "tgn:id":2033382,
    "tgn:name":"Pumpkin Center",
    "tgn:placetype":[
        "aat:300008347",
        "aat:300387210"
    ]
},
  "bbox": [],
  "geometry": {"coordinates":[-86.35,38.5833],"type":"Point"}
}