{
  "id": 1077960,
  "type": "Feature",
  "properties": {
    "tgn:hierarchy":[
        "tgn:1077960",
        "tgn:1000004",
        "tgn:1001323",
        "tgn:1000116",
        "tgn:7029392"
    ],
    "tgn:id":1077960,
    "tgn:name":"Lamongan",
    "tgn:placetype":[
        "aat:300008347"
    ]
},
  "bbox": [],
  "geometry": {"coordinates":[112.4333,-7.0833],"type":"Point"}
}