<<<<<<< HEAD
{
  "id": 2405829,
  "type": "Feature",
  "properties": {
    "tgn:hierarchy":[
        "tgn:2405829",
        "tgn:2001423",
        "tgn:1000001",
        "tgn:7012149",
        "tgn:7007564",
        "tgn:7029392"
    ],
    "tgn:id":2405829,
    "tgn:name":"Hull Island",
    "tgn:placetype":[
        "aat:300008791"
    ]
},
  "bbox": [],
  "geometry": {"coordinates":[-71.4,43.6667],"type":"Point"}
}
=======
{"geometry":{"type":"Point","coordinates":[-71.400000,43.666700]},"type":"Feature","properties":{"hierarchy":["tgn:2405829","tgn:2001423","tgn:1000001","tgn:7012149","tgn:7007564","tgn:7029392"],"placetype":["aat:300008791"],"id":2405829,"name:xx":"Hull Island"}}
>>>>>>> 03f74aca74312dbeaf24d7e61306dd6a786dc3d0
