{
  "id": 2611505,
  "type": "Feature",
  "properties": {
    "tgn:hierarchy":[
        "tgn:2611505",
        "tgn:1002176",
        "tgn:1000001",
        "tgn:7012149",
        "tgn:7007828",
        "tgn:7029392"
    ],
    "tgn:id":2611505,
    "tgn:name":"Red Mill Pond Brook",
    "tgn:placetype":[
        "aat:300008699"
    ]
},
  "bbox": [],
  "geometry": {"coordinates":[-73.0167,42.8833],"type":"Point"}
}