<<<<<<< HEAD
{
  "id": 7378896,
  "type": "Feature",
  "properties": {
    "tgn:hierarchy":[
        "tgn:7378896",
        "tgn:1001835",
        "tgn:1000001",
        "tgn:7005560",
        "tgn:7029392"
    ],
    "tgn:id":7378896,
    "tgn:name":"Escuela Mexico",
    "tgn:placetype":[
        "aat:300006495"
    ]
},
  "bbox": [],
  "geometry": {"coordinates":[-115.116667,32.570556],"type":"Point"}
}
=======
{"geometry":{"type":"Point","coordinates":[-115.116667,32.570556]},"type":"Feature","properties":{"hierarchy":["tgn:7378896","tgn:1001835","tgn:1000001","tgn:7005560","tgn:7029392"],"placetype":["aat:300006495"],"id":7378896,"name:xx":"Escuela Mexico"}}
>>>>>>> 03f74aca74312dbeaf24d7e61306dd6a786dc3d0
