{
  "id": 1078763,
  "type": "Feature",
  "properties": {
    "tgn:hierarchy":[
        "tgn:1078763",
        "tgn:1000004",
        "tgn:1001502",
        "tgn:1008727",
        "tgn:1000116",
        "tgn:7029392"
    ],
    "tgn:id":1078763,
    "tgn:name":"Teluksamak",
    "tgn:placetype":[
        "aat:300008347"
    ]
},
  "bbox": [],
  "geometry": {"coordinates":[103.05,0.8667],"type":"Point"}
}