{
  "id": 2167256,
  "type": "Feature",
  "properties": {
    "tgn:hierarchy":[
        "tgn:2167256",
        "tgn:1000001",
        "tgn:7012149",
        "tgn:2000839",
        "tgn:7007255",
        "tgn:7029392"
    ],
    "tgn:id":2167256,
    "tgn:name":"Big Clifty Creek",
    "tgn:placetype":[
        "aat:300008706"
    ]
},
  "bbox": [],
  "geometry": {"coordinates":[-84.35,37.1333],"type":"Point"}
}