{
  "id": 2461327,
  "type": "Feature",
  "properties": {
    "tgn:hierarchy":[
        "tgn:2461327",
        "tgn:1000001",
        "tgn:7012149",
        "tgn:2002190",
        "tgn:7007919",
        "tgn:7029392"
    ],
    "tgn:id":2461327,
    "tgn:name":"Little Stony Creek",
    "tgn:placetype":[
        "aat:300008706"
    ]
},
  "bbox": [],
  "geometry": {"coordinates":[-78.6167,38.9667],"type":"Point"}
}