{
  "id": 1052870,
  "type": "Feature",
  "properties": {
    "tgn:hierarchy":[
        "tgn:1052870",
        "tgn:1000003",
        "tgn:7012067",
        "tgn:7006660",
        "tgn:7029392"
    ],
    "tgn:id":1052870,
    "tgn:name":"Bokovo Platovo",
    "tgn:placetype":[
        "aat:300008347"
    ]
},
  "bbox": [],
  "geometry": {"coordinates":[39.0167,48.1167],"type":"Point"}
}