<<<<<<< HEAD
{
  "id": 2250667,
  "type": "Feature",
  "properties": {
    "tgn:hierarchy":[
        "tgn:2250667",
        "tgn:1000001",
        "tgn:2001431",
        "tgn:7012149",
        "tgn:7007566",
        "tgn:7029392"
    ],
    "tgn:id":2250667,
    "tgn:name":"Colorado, Cerrito",
    "tgn:placetype":[
        "aat:300008798"
    ]
},
  "bbox": [],
  "geometry": {"coordinates":[-107.9,35.1167],"type":"Point"}
}
=======
{"geometry":{"type":"Point","coordinates":[-107.900000,35.116700]},"type":"Feature","properties":{"hierarchy":["tgn:2250667","tgn:1000001","tgn:2001431","tgn:7012149","tgn:7007566","tgn:7029392"],"placetype":["aat:300008798"],"id":2250667,"name:xx":"Colorado, Cerrito"}}
>>>>>>> 03f74aca74312dbeaf24d7e61306dd6a786dc3d0
