{
  "id": 2310243,
  "type": "Feature",
  "properties": {
    "tgn:hierarchy":[
        "tgn:2310243",
        "tgn:1000001",
        "tgn:7012149",
        "tgn:2001873",
        "tgn:7007825",
        "tgn:7029392"
    ],
    "tgn:id":2310243,
    "tgn:name":"Ebbing and Flowing Spring",
    "tgn:placetype":[
        "aat:300008697"
    ]
},
  "bbox": [],
  "geometry": {"coordinates":[-82.95,36.4167],"type":"Point"}
}