{
  "id": 2028346,
  "type": "Feature",
  "properties": {
    "tgn:hierarchy":[
        "tgn:2028346",
        "tgn:1000001",
        "tgn:7013649",
        "tgn:7012149",
        "tgn:7007251",
        "tgn:7029392"
    ],
    "tgn:id":2028346,
    "tgn:name":"Hoffman Estates",
    "tgn:placetype":[
        "aat:300008347"
    ]
},
  "bbox": [],
  "geometry": {"coordinates":[-88.0667,42.0333],"type":"Point"}
}