{
  "id": 2348362,
  "type": "Feature",
  "properties": {
    "tgn:hierarchy":[
        "tgn:2348362",
        "tgn:1000001",
        "tgn:7012149",
        "tgn:2000616",
        "tgn:7007253",
        "tgn:7029392"
    ],
    "tgn:id":2348362,
    "tgn:name":"Ghost Hollow",
    "tgn:placetype":[
        "aat:300008761"
    ]
},
  "bbox": [],
  "geometry": {"coordinates":[-91.5833,40.5333],"type":"Point"}
}