<<<<<<< HEAD
{
  "id": 2764056,
  "type": "Feature",
  "properties": {
    "tgn:hierarchy":[
        "tgn:2764056",
        "tgn:1000001",
        "tgn:7012149",
        "tgn:2001964",
        "tgn:7007826",
        "tgn:7029392"
    ],
    "tgn:id":2764056,
    "tgn:name":"Wheeler Creek",
    "tgn:placetype":[
        "aat:300008706"
    ]
},
  "bbox": [],
  "geometry": {"coordinates":[-97.0333,33.6667],"type":"Point"}
}
=======
{"geometry":{"type":"Point","coordinates":[-97.033300,33.666700]},"type":"Feature","properties":{"hierarchy":["tgn:2764056","tgn:1000001","tgn:7012149","tgn:2001964","tgn:7007826","tgn:7029392"],"placetype":["aat:300008706"],"id":2764056,"name:xx":"Wheeler Creek"}}
>>>>>>> 03f74aca74312dbeaf24d7e61306dd6a786dc3d0
