{
  "id": 7100201,
  "type": "Feature",
  "properties": {
    "tgn:hierarchy":[
        "tgn:7100201",
        "tgn:7000096",
        "tgn:1000003",
        "tgn:7000084",
        "tgn:7029392"
    ],
    "tgn:id":7100201,
    "tgn:name":"Rote Laacke",
    "tgn:placetype":[
        "aat:300386990"
    ]
},
  "bbox": [],
  "geometry": {"coordinates":[12.366667,52.833333],"type":"Point"}
}