{
  "id": 2492210,
  "type": "Feature",
  "properties": {
    "tgn:hierarchy":[
        "tgn:2492210",
        "tgn:1000001",
        "tgn:7012149",
        "tgn:2000281",
        "tgn:7007240",
        "tgn:7029392"
    ],
    "tgn:id":2492210,
    "tgn:name":"Mare Creek",
    "tgn:placetype":[
        "aat:300008706"
    ]
},
  "bbox": [],
  "geometry": {"coordinates":[-86.6667,30.95],"type":"Point"}
}