{
  "id": 2618019,
  "type": "Feature",
  "properties": {
    "tgn:hierarchy":[
        "tgn:2618019",
        "tgn:1000001",
        "tgn:2002255",
        "tgn:7012149",
        "tgn:7013961",
        "tgn:7029392"
    ],
    "tgn:id":2618019,
    "tgn:name":"Ridgeview Hollow",
    "tgn:placetype":[
        "aat:300008761"
    ]
},
  "bbox": [],
  "geometry": {"coordinates":[-81.7667,38.1167],"type":"Point"}
}