<<<<<<< HEAD
{
  "id": 7478849,
  "type": "Feature",
  "properties": {
    "tgn:hierarchy":[
        "tgn:7478849",
        "tgn:1000004",
        "tgn:7489179",
        "tgn:1000141",
        "tgn:7029392"
    ],
    "tgn:id":7478849,
    "tgn:name":"Sijiu'er",
    "tgn:placetype":[
        "aat:300008347"
    ]
},
  "bbox": [],
  "geometry": {"coordinates":[121.7545,24.727],"type":"Point"}
}
=======
{"geometry":{"type":"Point","coordinates":[121.754500,24.727000]},"type":"Feature","properties":{"hierarchy":["tgn:7478849","tgn:1000004","tgn:7489179","tgn:1000141","tgn:7029392"],"placetype":["aat:300008347"],"id":7478849,"name:xx":"Sijiu'er"}}
>>>>>>> 03f74aca74312dbeaf24d7e61306dd6a786dc3d0
