{
  "id": 7517893,
  "type": "Feature",
  "properties": {
    "tgn:hierarchy":[
        "tgn:7517893",
        "tgn:1009227",
        "tgn:7001866",
        "tgn:1000226",
        "tgn:1000006",
        "tgn:7029392"
    ],
    "tgn:id":7517893,
    "tgn:name:en":"McDonald, Mount",
    "tgn:placetype":[
        "aat:300008795"
    ]
},
  "bbox": [],
  "geometry": {"coordinates":[172.516667,-43.033333],"type":"Point"}
}