{
  "id": 1016851,
  "type": "Feature",
  "properties": {
    "tgn:hierarchy":[
        "tgn:1016851",
        "tgn:1009858",
        "tgn:1009583",
        "tgn:1000647",
        "tgn:1000001",
        "tgn:7005554",
        "tgn:7029392"
    ],
    "tgn:id":1016851,
    "tgn:name":"Utila",
    "tgn:placetype":[
        "aat:300008347"
    ]
},
  "bbox": [],
  "geometry": {"coordinates":[-86.85,16.0833],"type":"Point"}
}