{
  "id": 2743664,
  "type": "Feature",
  "properties": {
    "tgn:hierarchy":[
        "tgn:2743664",
        "tgn:2000768",
        "tgn:1000001",
        "tgn:7012149",
        "tgn:7007255",
        "tgn:7029392"
    ],
    "tgn:id":2743664,
    "tgn:name":"Vaughn Knob",
    "tgn:placetype":[
        "aat:300008798"
    ]
},
  "bbox": [],
  "geometry": {"coordinates":[-85.85,37.1333],"type":"Point"}
}