<<<<<<< HEAD
{
  "id": 2156611,
  "type": "Feature",
  "properties": {
    "tgn:hierarchy":[
        "tgn:2156611",
        "tgn:1000001",
        "tgn:7012149",
        "tgn:2002304",
        "tgn:7013961",
        "tgn:7029392"
    ],
    "tgn:id":2156611,
    "tgn:name":"Bearwallow Ridge",
    "tgn:placetype":[
        "aat:300266640"
    ]
},
  "bbox": [],
  "geometry": {"coordinates":[-81.4,37.6167],"type":"Point"}
}
=======
{"geometry":{"type":"Point","coordinates":[-81.400000,37.616700]},"type":"Feature","properties":{"hierarchy":["tgn:2156611","tgn:1000001","tgn:7012149","tgn:2002304","tgn:7013961","tgn:7029392"],"placetype":["aat:300266640"],"id":2156611,"name:xx":"Bearwallow Ridge"}}
>>>>>>> 03f74aca74312dbeaf24d7e61306dd6a786dc3d0
