{
  "id": 7553813,
  "type": "Feature",
  "properties": {
    "tgn:hierarchy":[
        "tgn:7553813",
        "tgn:1001828",
        "tgn:1000004",
        "tgn:7000198",
        "tgn:7029392"
    ],
    "tgn:id":7553813,
    "tgn:name:en":"N\u012blarevu River",
    "tgn:placetype":[
        "aat:300008699"
    ]
},
  "bbox": [],
  "geometry": {"coordinates":[82.333333,16.716667],"type":"Point"}
}