{
  "id": 2444869,
  "type": "Feature",
  "properties": {
    "tgn:hierarchy":[
        "tgn:2444869",
        "tgn:1000001",
        "tgn:7012149",
        "tgn:1003047",
        "tgn:7007710",
        "tgn:7029392"
    ],
    "tgn:id":2444869,
    "tgn:name":"Leibs Creek",
    "tgn:placetype":[
        "aat:300008706"
    ]
},
  "bbox": [],
  "geometry": {"coordinates":[-76.5667,39.75],"type":"Point"}
}