{
  "id": 2258347,
  "type": "Feature",
  "properties": {
    "tgn:hierarchy":[
        "tgn:2258347",
        "tgn:1000001",
        "tgn:7012149",
        "tgn:7007825",
        "tgn:7029392"
    ],
    "tgn:id":2258347,
    "tgn:name":"Cottnell Branch",
    "tgn:placetype":[
        "aat:300008699"
    ]
},
  "bbox": [],
  "geometry": {"coordinates":[-88.7667,36.1333],"type":"Point"}
}