<<<<<<< HEAD
{
  "id": 2258347,
  "type": "Feature",
  "properties": {
    "tgn:hierarchy":[
        "tgn:2258347",
        "tgn:1000001",
        "tgn:7012149",
        "tgn:7007825",
        "tgn:7029392"
    ],
    "tgn:id":2258347,
    "tgn:name":"Cottnell Branch",
    "tgn:placetype":[
        "aat:300008699"
    ]
},
  "bbox": [],
  "geometry": {"coordinates":[-88.7667,36.1333],"type":"Point"}
}
=======
{"geometry":{"type":"Point","coordinates":[-88.766700,36.133300]},"type":"Feature","properties":{"hierarchy":["tgn:2258347","tgn:1000001","tgn:7012149","tgn:7007825","tgn:7029392"],"placetype":["aat:300008699"],"id":2258347,"name:xx":"Cottnell Branch"}}
>>>>>>> 03f74aca74312dbeaf24d7e61306dd6a786dc3d0
