<<<<<<< HEAD
{
  "id": 7172316,
  "type": "Feature",
  "properties": {
    "tgn:hierarchy":[
        "tgn:7172316",
        "tgn:1000003",
        "tgn:7003689",
        "tgn:7000084",
        "tgn:7029392"
    ],
    "tgn:id":7172316,
    "tgn:name":"Herrenm\u00fchle",
    "tgn:placetype":[
        "aat:300008347"
    ]
},
  "bbox": [],
  "geometry": {"coordinates":[10.8,50.75],"type":"Point"}
}
=======
{"geometry":{"type":"Point","coordinates":[10.800000,50.750000]},"type":"Feature","properties":{"hierarchy":["tgn:7172316","tgn:1000003","tgn:7003689","tgn:7000084","tgn:7029392"],"placetype":["aat:300008347"],"id":7172316,"name:xx":"Herrenm\u00fchle"}}
>>>>>>> 03f74aca74312dbeaf24d7e61306dd6a786dc3d0
