{
  "id": 7063966,
  "type": "Feature",
  "properties": {
    "tgn:hierarchy":[
        "tgn:7063966",
        "tgn:1000003",
        "tgn:7003688",
        "tgn:7000084",
        "tgn:7029392"
    ],
    "tgn:id":7063966,
    "tgn:name":"Augustenhof",
    "tgn:placetype":[
        "aat:300008347"
    ]
},
  "bbox": [],
  "geometry": {"coordinates":[11.033333,54.266667],"type":"Point"}
}