{
  "id": 7396543,
  "type": "Feature",
  "properties": {
    "tgn:hierarchy":[
        "tgn:7396543",
        "tgn:1000001",
        "tgn:1001893",
        "tgn:7005560",
        "tgn:7029392"
    ],
    "tgn:id":7396543,
    "tgn:name":"Santa Cruz, R\u00edo de",
    "tgn:placetype":[
        "aat:300008699"
    ]
},
  "bbox": [],
  "geometry": {"coordinates":[-112.233333,33.316667],"type":"Point"}
}