<<<<<<< HEAD
{
  "id": 2406982,
  "type": "Feature",
  "properties": {
    "tgn:hierarchy":[
        "tgn:2406982",
        "tgn:1000001",
        "tgn:7012149",
        "tgn:1002926",
        "tgn:7007568",
        "tgn:7029392"
    ],
    "tgn:id":2406982,
    "tgn:name":"Hunter Lake",
    "tgn:placetype":[
        "aat:300008680"
    ]
},
  "bbox": [],
  "geometry": {"coordinates":[-74.9,41.7167],"type":"Point"}
}
=======
{"geometry":{"type":"Point","coordinates":[-74.900000,41.716700]},"type":"Feature","properties":{"hierarchy":["tgn:2406982","tgn:1000001","tgn:7012149","tgn:1002926","tgn:7007568","tgn:7029392"],"placetype":["aat:300008680"],"id":2406982,"name:xx":"Hunter Lake"}}
>>>>>>> 03f74aca74312dbeaf24d7e61306dd6a786dc3d0
