{
  "id": 2149185,
  "type": "Feature",
  "properties": {
    "tgn:hierarchy":[
        "tgn:2149185",
        "tgn:1000001",
        "tgn:7012149",
        "tgn:2001449",
        "tgn:7007566",
        "tgn:7029392"
    ],
    "tgn:id":2149185,
    "tgn:name":"Barranquenos Spring",
    "tgn:placetype":[
        "aat:300008697"
    ]
},
  "bbox": [],
  "geometry": {"coordinates":[-106.5333,36.0667],"type":"Point"}
}