{
  "id": 2622852,
  "type": "Feature",
  "properties": {
    "tgn:hierarchy":[
        "tgn:2622852",
        "tgn:2000918",
        "tgn:1000001",
        "tgn:7012149",
        "tgn:7007515",
        "tgn:7029392"
    ],
    "tgn:id":2622852,
    "tgn:name":"Robinson Mountain",
    "tgn:placetype":[
        "aat:300008798"
    ]
},
  "bbox": [],
  "geometry": {"coordinates":[-70.1167,44.0667],"type":"Point"}
}