{
  "id": 2478276,
  "type": "Feature",
  "properties": {
    "tgn:hierarchy":[
        "tgn:2478276",
        "tgn:1000001",
        "tgn:7012149",
        "tgn:2000488",
        "tgn:7007250",
        "tgn:7029392"
    ],
    "tgn:id":2478276,
    "tgn:name":"Macks Creek",
    "tgn:placetype":[
        "aat:300008706"
    ]
},
  "bbox": [],
  "geometry": {"coordinates":[-116.8167,43.2167],"type":"Point"}
}