{
  "id": 2506966,
  "type": "Feature",
  "properties": {
    "tgn:hierarchy":[
        "tgn:2506966",
        "tgn:1000001",
        "tgn:7012149",
        "tgn:1003024",
        "tgn:7007251",
        "tgn:7029392"
    ],
    "tgn:id":2506966,
    "tgn:name":"Messenger Woods",
    "tgn:placetype":[
        "aat:300132451"
    ]
},
  "bbox": [],
  "geometry": {"coordinates":[-87.95,41.5667],"type":"Point"}
}