{
  "id": 7535168,
  "type": "Feature",
  "properties": {
    "tgn:hierarchy":[
        "tgn:7535168",
        "tgn:7001242",
        "tgn:7016833",
        "tgn:1001418",
        "tgn:7029392"
    ],
    "tgn:id":7535168,
    "tgn:name:en":"S\u0101niyat al Fatf\u016bt\u012byah",
    "tgn:placetype":[
        "aat:300006207"
    ]
},
  "bbox": [],
  "geometry": {"coordinates":[28.433333,31.033333],"type":"Point"}
}