{
  "id": 2668731,
  "type": "Feature",
  "properties": {
    "tgn:hierarchy":[
        "tgn:2668731",
        "tgn:1000001",
        "tgn:7012149",
        "tgn:1002988",
        "tgn:7007710",
        "tgn:7029392"
    ],
    "tgn:id":2668731,
    "tgn:name":"Slater Run",
    "tgn:placetype":[
        "aat:300008699"
    ]
},
  "bbox": [],
  "geometry": {"coordinates":[-79.25,41.7333],"type":"Point"}
}