{
  "id": 7463727,
  "type": "Feature",
  "properties": {
    "tgn:hierarchy":[
        "tgn:7463727",
        "tgn:7002445",
        "tgn:1000003",
        "tgn:7012077",
        "tgn:7008591",
        "tgn:7029392"
    ],
    "tgn:id":7463727,
    "tgn:name:en":"Lee Moor",
    "tgn:placetype":[
        "aat:300386886"
    ]
},
  "bbox": [],
  "geometry": {"coordinates":[-3.983333,50.45],"type":"Point"}
}