{
  "id": 7056781,
  "type": "Feature",
  "properties": {
    "tgn:hierarchy":[
        "tgn:7056781",
        "tgn:7004597",
        "tgn:1000003",
        "tgn:7008516",
        "tgn:1000080",
        "tgn:7029392"
    ],
    "tgn:id":7056781,
    "tgn:name":"Benedello",
    "tgn:placetype":[
        "aat:300008347"
    ]
},
  "bbox": [],
  "geometry": {"coordinates":[10.866667,44.366667],"type":"Point"}
}