{
  "id": 7342414,
  "type": "Feature",
  "properties": {
    "tgn:hierarchy":[
        "tgn:7342414",
        "tgn:7008911",
        "tgn:1000003",
        "tgn:7002763",
        "tgn:1000095",
        "tgn:7029392"
    ],
    "tgn:id":7342414,
    "tgn:name":"Canedo",
    "tgn:placetype":[
        "aat:300008347"
    ]
},
  "bbox": [],
  "geometry": {"coordinates":[-6.566667,43.55],"type":"Point"}
}