{
  "id": 2710789,
  "type": "Feature",
  "properties": {
    "tgn:hierarchy":[
        "tgn:2710789",
        "tgn:1000001",
        "tgn:7012149",
        "tgn:1002553",
        "tgn:7007920",
        "tgn:7029392"
    ],
    "tgn:id":2710789,
    "tgn:name":"Taneum Point",
    "tgn:placetype":[
        "aat:300008798"
    ]
},
  "bbox": [],
  "geometry": {"coordinates":[-120.9333,47.1167],"type":"Point"}
}