<<<<<<< HEAD
{
  "id": 7352066,
  "type": "Feature",
  "properties": {
    "tgn:hierarchy":[
        "tgn:7352066",
        "tgn:7005581",
        "tgn:1000001",
        "tgn:7005560",
        "tgn:7029392"
    ],
    "tgn:id":7352066,
    "tgn:name":"Bosque Bonito",
    "tgn:placetype":[
        "aat:300008347"
    ]
},
  "bbox": [],
  "geometry": {"coordinates":[-105.1,30.7],"type":"Point"}
}
=======
{"geometry":{"type":"Point","coordinates":[-105.100000,30.700000]},"type":"Feature","properties":{"hierarchy":["tgn:7352066","tgn:7005581","tgn:1000001","tgn:7005560","tgn:7029392"],"placetype":["aat:300008347"],"id":7352066,"name:xx":"Bosque Bonito"}}
>>>>>>> 03f74aca74312dbeaf24d7e61306dd6a786dc3d0
