{
  "id": 7582591,
  "type": "Feature",
  "properties": {
    "tgn:hierarchy":[
        "tgn:7582591",
        "tgn:1000004",
        "tgn:7000198",
        "tgn:1001894",
        "tgn:7029392"
    ],
    "tgn:id":7582591,
    "tgn:name:en":"Pitholi",
    "tgn:placetype":[
        "aat:300008347"
    ]
},
  "bbox": [],
  "geometry": {"coordinates":[78.870371,24.049473],"type":"Point"}
}