{
  "id": 2136742,
  "type": "Feature",
  "properties": {
    "tgn:hierarchy":[
        "tgn:2136742",
        "tgn:1000001",
        "tgn:2000465",
        "tgn:7012149",
        "tgn:7007250",
        "tgn:7029392"
    ],
    "tgn:id":2136742,
    "tgn:name":"Arena Canal",
    "tgn:placetype":[
        "aat:300006075"
    ]
},
  "bbox": [],
  "geometry": {"coordinates":[-116.9333,43.6833],"type":"Point"}
}