{
  "id": 2258112,
  "type": "Feature",
  "properties": {
    "tgn:hierarchy":[
        "tgn:2258112",
        "tgn:1000001",
        "tgn:7012149",
        "tgn:2000183",
        "tgn:7007157",
        "tgn:7029392"
    ],
    "tgn:id":2258112,
    "tgn:name":"Coso Springs",
    "tgn:placetype":[
        "aat:300008697"
    ]
},
  "bbox": [],
  "geometry": {"coordinates":[-117.6167,36.1667],"type":"Point"}
}