{
  "id": 7193663,
  "type": "Feature",
  "properties": {
    "tgn:hierarchy":[
        "tgn:7193663",
        "tgn:1000003",
        "tgn:7003685",
        "tgn:7000084",
        "tgn:7029392"
    ],
    "tgn:id":7193663,
    "tgn:name":"Feldh\u00e4user",
    "tgn:placetype":[
        "aat:300008347"
    ]
},
  "bbox": [],
  "geometry": {"coordinates":[14.766667,51.166667],"type":"Point"}
}