{
  "id": 2020379,
  "type": "Feature",
  "properties": {
    "tgn:hierarchy":[
        "tgn:2020379",
        "tgn:1000001",
        "tgn:7012149",
        "tgn:1002314",
        "tgn:7007240",
        "tgn:7029392"
    ],
    "tgn:id":2020379,
    "tgn:name":"Miami International Mall",
    "tgn:placetype":[
        "aat:300247594"
    ]
},
  "bbox": [],
  "geometry": {"coordinates":[-80.3833,25.75],"type":"Point"}
}