{
  "id": 7543945,
  "type": "Feature",
  "properties": {
    "tgn:hierarchy":[
        "tgn:7543945",
        "tgn:7001242",
        "tgn:7016833",
        "tgn:7001335",
        "tgn:7029392"
    ],
    "tgn:id":7543945,
    "tgn:name":"A\u0163 \u0162\u0101sah",
    "tgn:placetype":[
        "aat:300008347"
    ]
},
  "bbox": [],
  "geometry": {"coordinates":[32.637778,30.559167],"type":"Point"}
}