{
  "id": 1015393,
  "type": "Feature",
  "properties": {
    "tgn:hierarchy":[
        "tgn:1015393",
        "tgn:7005685",
        "tgn:1000001",
        "tgn:7005804",
        "tgn:7029392"
    ],
    "tgn:id":1015393,
    "tgn:name":"Garthby Station",
    "tgn:placetype":[
        "aat:300008347"
    ]
},
  "bbox": [],
  "geometry": {"coordinates":[-71.3833,45.8333],"type":"Point"}
}