{
  "id": 2425210,
  "type": "Feature",
  "properties": {
    "tgn:hierarchy":[
        "tgn:2425210",
        "tgn:1000001",
        "tgn:7012149",
        "tgn:2001292",
        "tgn:7007524",
        "tgn:7029392"
    ],
    "tgn:id":2425210,
    "tgn:name":"Johnson Mine",
    "tgn:placetype":[
        "aat:300000390"
    ]
},
  "bbox": [],
  "geometry": {"coordinates":[-108.5833,46.45],"type":"Point"}
}