{
  "id": 2610798,
  "type": "Feature",
  "properties": {
    "tgn:hierarchy":[
        "tgn:2610798",
        "tgn:1000001",
        "tgn:7012149",
        "tgn:2000289",
        "tgn:7007240",
        "tgn:7029392"
    ],
    "tgn:id":2610798,
    "tgn:name":"Red Fish Creek",
    "tgn:placetype":[
        "aat:300008706"
    ]
},
  "bbox": [],
  "geometry": {"coordinates":[-84.2833,30.0667],"type":"Point"}
}