{
  "id": 2783169,
  "type": "Feature",
  "properties": {
    "tgn:hierarchy":[
        "tgn:2783169",
        "tgn:1000001",
        "tgn:7012149",
        "tgn:2001236",
        "tgn:7007523",
        "tgn:7029392"
    ],
    "tgn:id":2783169,
    "tgn:name":"Wright Hollow",
    "tgn:placetype":[
        "aat:300008761"
    ]
},
  "bbox": [],
  "geometry": {"coordinates":[-90.7833,37.4333],"type":"Point"}
}