{
  "id": 7566864,
  "type": "Feature",
  "properties": {
    "tgn:hierarchy":[
        "tgn:7566864",
        "tgn:1001828",
        "tgn:1000004",
        "tgn:7000198",
        "tgn:7029392"
    ],
    "tgn:id":7566864,
    "tgn:name:en":"Itki\u0101l",
    "tgn:placetype":[
        "aat:300008347"
    ]
},
  "bbox": [],
  "geometry": {"coordinates":[78.775278,17.762778],"type":"Point"}
}