{
  "id": 7590718,
  "type": "Feature",
  "properties": {
    "tgn:hierarchy":[
        "tgn:7590718",
        "tgn:1000004",
        "tgn:7000198",
        "tgn:7000799",
        "tgn:7029392"
    ],
    "tgn:id":7590718,
    "tgn:name:en":"Par\u0101ra",
    "tgn:placetype":[
        "aat:300008347"
    ]
},
  "bbox": [],
  "geometry": {"coordinates":[73.811741,34.352126],"type":"Point"}
}