{
  "id": 7165859,
  "type": "Feature",
  "properties": {
    "tgn:hierarchy":[
        "tgn:7165859",
        "tgn:7003669",
        "tgn:1000003",
        "tgn:7000084",
        "tgn:7029392"
    ],
    "tgn:id":7165859,
    "tgn:name":"Hardthof",
    "tgn:placetype":[
        "aat:300000206"
    ]
},
  "bbox": [],
  "geometry": {"coordinates":[10.283333,49.066667],"type":"Point"}
}