{
  "id": 1106457,
  "type": "Feature",
  "properties": {
    "tgn:hierarchy":[
        "tgn:1106457",
        "tgn:1000004",
        "tgn:1001448",
        "tgn:1000135",
        "tgn:7029392"
    ],
    "tgn:id":1106457,
    "tgn:name":"Silay, Mount",
    "tgn:placetype":[
        "aat:300008795"
    ]
},
  "bbox": [],
  "geometry": {"coordinates":[123.2333,10.7833],"type":"Point"}
}