{
  "id": 7232045,
  "type": "Feature",
  "properties": {
    "tgn:hierarchy":[
        "tgn:7232045",
        "tgn:7011170",
        "tgn:7002715",
        "tgn:1000003",
        "tgn:1000074",
        "tgn:7029392"
    ],
    "tgn:id":7232045,
    "tgn:name":"K\u00e9khros",
    "tgn:placetype":[
        "aat:300008347"
    ]
},
  "bbox": [],
  "geometry": {"coordinates":[25.85,41.233333],"type":"Point"}
}