{
  "id": 1120250,
  "type": "Feature",
  "properties": {
    "tgn:hierarchy":[
        "tgn:1120250",
        "tgn:7008912",
        "tgn:7030216",
        "tgn:1000003",
        "tgn:1000095",
        "tgn:7029392"
    ],
    "tgn:id":1120250,
    "tgn:name":"Oliana, Embalse de",
    "tgn:placetype":[
        "aat:300006191"
    ]
},
  "bbox": [],
  "geometry": {"coordinates":[1.3333,42.1667],"type":"Point"}
}