{
  "id": 2580402,
  "type": "Feature",
  "properties": {
    "tgn:hierarchy":[
        "tgn:2580402",
        "tgn:1000001",
        "tgn:2001431",
        "tgn:7012149",
        "tgn:7007566",
        "tgn:7029392"
    ],
    "tgn:id":2580402,
    "tgn:name":"Pig-a-ti-ana",
    "tgn:placetype":[
        "aat:300008798"
    ]
},
  "bbox": [],
  "geometry": {"coordinates":[-108.2667,34.8833],"type":"Point"}
}