{
  "id": 2461090,
  "type": "Feature",
  "properties": {
    "tgn:hierarchy":[
        "tgn:2461090",
        "tgn:7006450",
        "tgn:1000001",
        "tgn:7012149",
        "tgn:2000079",
        "tgn:7029392"
    ],
    "tgn:id":2461090,
    "tgn:name":"Little Specimen Gulch",
    "tgn:placetype":[
        "aat:300008761"
    ]
},
  "bbox": [],
  "geometry": {"coordinates":[-165.3667,64.5667],"type":"Point"}
}