{
  "id": 7015948,
  "type": "Feature",
  "properties": {
    "tgn:hierarchy":[
        "tgn:7015948",
        "tgn:1000001",
        "tgn:7012149",
        "tgn:2000890",
        "tgn:7007256",
        "tgn:7029392"
    ],
    "tgn:id":7015948,
    "tgn:name":"Bawcomville",
    "tgn:placetype":[
        "aat:300008347"
    ]
},
  "bbox": [],
  "geometry": {"coordinates":[-92.1667,32.4667],"type":"Point"}
}