{
  "id": 2268364,
  "type": "Feature",
  "properties": {
    "tgn:hierarchy":[
        "tgn:2268364",
        "tgn:1000001",
        "tgn:7012149",
        "tgn:1002613",
        "tgn:7007710",
        "tgn:7029392"
    ],
    "tgn:id":2268364,
    "tgn:name":"Crooked Riffles Hollow",
    "tgn:placetype":[
        "aat:300008761"
    ]
},
  "bbox": [],
  "geometry": {"coordinates":[-76.8667,41.3333],"type":"Point"}
}