{
  "id": 2734478,
  "type": "Feature",
  "properties": {
    "tgn:hierarchy":[
        "tgn:2734478",
        "tgn:2001002",
        "tgn:1000001",
        "tgn:7012149",
        "tgn:7007521",
        "tgn:7029392"
    ],
    "tgn:id":2734478,
    "tgn:name":"Turtle River",
    "tgn:placetype":[
        "aat:300008707"
    ]
},
  "bbox": [],
  "geometry": {"coordinates":[-94.95,47.6333],"type":"Point"}
}