{
  "id": 7214568,
  "type": "Feature",
  "properties": {
    "tgn:hierarchy":[
        "tgn:7214568",
        "tgn:7003669",
        "tgn:1000003",
        "tgn:7000084",
        "tgn:7029392"
    ],
    "tgn:id":7214568,
    "tgn:name":"Blindenried",
    "tgn:placetype":[
        "aat:300008347"
    ]
},
  "bbox": [],
  "geometry": {"coordinates":[11.966667,47.833333],"type":"Point"}
}