<<<<<<< HEAD
{
  "id": 7371850,
  "type": "Feature",
  "properties": {
    "tgn:hierarchy":[
        "tgn:7371850",
        "tgn:1000001",
        "tgn:7005597",
        "tgn:7005560",
        "tgn:7029392"
    ],
    "tgn:id":7371850,
    "tgn:name":"La Mula",
    "tgn:placetype":[
        "aat:300008347"
    ]
},
  "bbox": [],
  "geometry": {"coordinates":[-99.283333,23.6],"type":"Point"}
}
=======
{"geometry":{"type":"Point","coordinates":[-99.283333,23.600000]},"type":"Feature","properties":{"hierarchy":["tgn:7371850","tgn:1000001","tgn:7005597","tgn:7005560","tgn:7029392"],"placetype":["aat:300008347"],"id":7371850,"name:xx":"La Mula"}}
>>>>>>> 03f74aca74312dbeaf24d7e61306dd6a786dc3d0
