{
  "id": 2435739,
  "type": "Feature",
  "properties": {
    "tgn:hierarchy":[
        "tgn:2435739",
        "tgn:1000001",
        "tgn:7012149",
        "tgn:2000437",
        "tgn:7007248",
        "tgn:7029392"
    ],
    "tgn:id":2435739,
    "tgn:name":"Ketner Branch",
    "tgn:placetype":[
        "aat:300008699"
    ]
},
  "bbox": [],
  "geometry": {"coordinates":[-85.3333,34.85],"type":"Point"}
}