<<<<<<< HEAD
{
  "id": 7055720,
  "type": "Feature",
  "properties": {
    "tgn:hierarchy":[
        "tgn:7055720",
        "tgn:7003154",
        "tgn:1000003",
        "tgn:7003120",
        "tgn:1000080",
        "tgn:7029392"
    ],
    "tgn:id":7055720,
    "tgn:name":"Levanna Occidentale",
    "tgn:placetype":[
        "aat:300008798"
    ]
},
  "bbox": [],
  "geometry": {"coordinates":[7.166667,45.416667],"type":"Point"}
}
=======
{"geometry":{"type":"Point","coordinates":[7.166667,45.416667]},"type":"Feature","properties":{"hierarchy":["tgn:7055720","tgn:7003154","tgn:1000003","tgn:7003120","tgn:1000080","tgn:7029392"],"placetype":["aat:300008798"],"id":7055720,"name:xx":"Levanna Occidentale"}}
>>>>>>> 03f74aca74312dbeaf24d7e61306dd6a786dc3d0
