{
  "id": 2221171,
  "type": "Feature",
  "properties": {
    "tgn:hierarchy":[
        "tgn:2221171",
        "tgn:2002365",
        "tgn:1000001",
        "tgn:7012149",
        "tgn:7007923",
        "tgn:7029392"
    ],
    "tgn:id":2221171,
    "tgn:name":"Carcass Ridge",
    "tgn:placetype":[
        "aat:300266640"
    ]
},
  "bbox": [],
  "geometry": {"coordinates":[-105.9167,42.2333],"type":"Point"}
}