{
  "id": 2180644,
  "type": "Feature",
  "properties": {
    "tgn:hierarchy":[
        "tgn:2180644",
        "tgn:1000001",
        "tgn:2001011",
        "tgn:7012149",
        "tgn:7007521",
        "tgn:7029392"
    ],
    "tgn:id":2180644,
    "tgn:name":"Bloom Lake",
    "tgn:placetype":[
        "aat:300008680"
    ]
},
  "bbox": [],
  "geometry": {"coordinates":[-92.7667,45.35],"type":"Point"}
}