{
  "id": 2454199,
  "type": "Feature",
  "properties": {
    "tgn:hierarchy":[
        "tgn:2454199",
        "tgn:1000001",
        "tgn:2001938",
        "tgn:7012149",
        "tgn:7007826",
        "tgn:7029392"
    ],
    "tgn:id":2454199,
    "tgn:name":"Little Creek",
    "tgn:placetype":[
        "aat:300008706"
    ]
},
  "bbox": [],
  "geometry": {"coordinates":[-99.45,29.7333],"type":"Point"}
}