{
  "id": 7224952,
  "type": "Feature",
  "properties": {
    "tgn:hierarchy":[
        "tgn:7224952",
        "tgn:7002706",
        "tgn:7002705",
        "tgn:1000003",
        "tgn:1000074",
        "tgn:7029392"
    ],
    "tgn:id":7224952,
    "tgn:name":"Neoch\u00f3rion",
    "tgn:placetype":[
        "aat:300008347"
    ]
},
  "bbox": [],
  "geometry": {"coordinates":[21.018889,39.069444],"type":"Point"}
}