{
  "id": 2450292,
  "type": "Feature",
  "properties": {
    "tgn:hierarchy":[
        "tgn:2450292",
        "tgn:1000001",
        "tgn:1002493",
        "tgn:7012149",
        "tgn:7007565",
        "tgn:7029392"
    ],
    "tgn:id":2450292,
    "tgn:name":"Lingerts Pond",
    "tgn:placetype":[
        "aat:300006191"
    ]
},
  "bbox": [],
  "geometry": {"coordinates":[-74.9167,40.6333],"type":"Point"}
}