{
  "id": 2471424,
  "type": "Feature",
  "properties": {
    "tgn:hierarchy":[
        "tgn:2471424",
        "tgn:1000001",
        "tgn:7012149",
        "tgn:1002737",
        "tgn:7007520",
        "tgn:7029392"
    ],
    "tgn:id":2471424,
    "tgn:name":"Lost Lake",
    "tgn:placetype":[
        "aat:300008905"
    ]
},
  "bbox": [],
  "geometry": {"coordinates":[-83.3167,42.75],"type":"Point"}
}