{
  "id": 2120501,
  "type": "Feature",
  "properties": {
    "tgn:hierarchy":[
        "tgn:2120501",
        "tgn:1000001",
        "tgn:2002261",
        "tgn:7012149",
        "tgn:7013961",
        "tgn:7029392"
    ],
    "tgn:id":2120501,
    "tgn:name":"Willis Branch",
    "tgn:placetype":[
        "aat:300008347"
    ]
},
  "bbox": [],
  "geometry": {"coordinates":[-81.25,37.8833],"type":"Point"}
}