{
  "id": 7229461,
  "type": "Feature",
  "properties": {
    "tgn:hierarchy":[
        "tgn:7229461",
        "tgn:7002681",
        "tgn:7001395",
        "tgn:1000003",
        "tgn:1000074",
        "tgn:7029392"
    ],
    "tgn:id":7229461,
    "tgn:name":"Kynoso\u00fara, \u00c1kra",
    "tgn:placetype":[
        "aat:300008850"
    ]
},
  "bbox": [],
  "geometry": {"coordinates":[23.578889,37.947222],"type":"Point"}
}