{
  "id": 1016584,
  "type": "Feature",
  "properties": {
    "tgn:hierarchy":[
        "tgn:1016584",
        "tgn:7017254",
        "tgn:1000001",
        "tgn:7004771",
        "tgn:7029392"
    ],
    "tgn:id":1016584,
    "tgn:name":"Grand Bay",
    "tgn:placetype":[
        "aat:300008347"
    ]
},
  "bbox": [],
  "geometry": {"coordinates":[-61.7333,12.1333],"type":"Point"}
}