{
  "id": 1020294,
  "type": "Feature",
  "properties": {
    "tgn:hierarchy":[
        "tgn:1020294",
        "tgn:1000662",
        "tgn:1000046",
        "tgn:1000002",
        "tgn:7029392"
    ],
    "tgn:id":1020294,
    "tgn:name":"Coroico",
    "tgn:placetype":[
        "aat:300008347"
    ]
},
  "bbox": [],
  "geometry": {"coordinates":[-67.75,-16.15],"type":"Point"}
}