{
  "id": 2697768,
  "type": "Feature",
  "properties": {
    "tgn:hierarchy":[
        "tgn:2697768",
        "tgn:1000001",
        "tgn:7012149",
        "tgn:1002968",
        "tgn:7007706",
        "tgn:7029392"
    ],
    "tgn:id":2697768,
    "tgn:name":"Storm Ditch",
    "tgn:placetype":[
        "aat:300006075"
    ]
},
  "bbox": [],
  "geometry": {"coordinates":[-84.7333,40.8667],"type":"Point"}
}