{
  "id": 2157161,
  "type": "Feature",
  "properties": {
    "tgn:hierarchy":[
        "tgn:2157161",
        "tgn:1000001",
        "tgn:7006451",
        "tgn:7012149",
        "tgn:2000098",
        "tgn:7029392"
    ],
    "tgn:id":2157161,
    "tgn:name":"Beaver Cove",
    "tgn:placetype":[
        "aat:300132316"
    ]
},
  "bbox": [],
  "geometry": {"coordinates":[-114.5667,35.2333],"type":"Point"}
}