{
  "id": 2432297,
  "type": "Feature",
  "properties": {
    "tgn:hierarchy":[
        "tgn:2432297",
        "tgn:1000001",
        "tgn:7006451",
        "tgn:7012149",
        "tgn:2000099",
        "tgn:7029392"
    ],
    "tgn:id":2432297,
    "tgn:name":"Keams Canyon",
    "tgn:placetype":[
        "aat:300008761"
    ]
},
  "bbox": [],
  "geometry": {"coordinates":[-110.0667,35.8833],"type":"Point"}
}