{
  "id": 2079125,
  "type": "Feature",
  "properties": {
    "tgn:hierarchy":[
        "tgn:2079125",
        "tgn:1000001",
        "tgn:1002304",
        "tgn:7012149",
        "tgn:7007706",
        "tgn:7029392"
    ],
    "tgn:id":2079125,
    "tgn:name":"Coshocton",
    "tgn:placetype":[
        "aat:300008347"
    ]
},
  "bbox": [],
  "geometry": {"coordinates":[-81.85,40.2667],"type":"Point"}
}