{
  "id": 7573179,
  "type": "Feature",
  "properties": {
    "tgn:hierarchy":[
        "tgn:7573179",
        "tgn:1001828",
        "tgn:1000004",
        "tgn:7000198",
        "tgn:7029392"
    ],
    "tgn:id":7573179,
    "tgn:name:en":"J\u016bkal",
    "tgn:placetype":[
        "aat:300008347"
    ]
},
  "bbox": [],
  "geometry": {"coordinates":[77.616667,18.35],"type":"Point"}
}