{
  "id": 2664063,
  "type": "Feature",
  "properties": {
    "tgn:hierarchy":[
        "tgn:2664063",
        "tgn:1000001",
        "tgn:7012149",
        "tgn:1002557",
        "tgn:7007252",
        "tgn:7029392"
    ],
    "tgn:id":2664063,
    "tgn:name":"Silver Point",
    "tgn:placetype":[
        "aat:300008347"
    ]
},
  "bbox": [],
  "geometry": {"coordinates":[-85.7667,41.3167],"type":"Point"}
}