{
  "id": 2741998,
  "type": "Feature",
  "properties": {
    "tgn:hierarchy":[
        "tgn:2741998",
        "tgn:1000001",
        "tgn:2000920",
        "tgn:7012149",
        "tgn:7007515",
        "tgn:7029392"
    ],
    "tgn:id":2741998,
    "tgn:name":"Vaill Island",
    "tgn:placetype":[
        "aat:300008791"
    ]
},
  "bbox": [],
  "geometry": {"coordinates":[-70.15,43.6667],"type":"Point"}
}