{
  "id": 7543900,
  "type": "Feature",
  "properties": {
    "tgn:hierarchy":[
        "tgn:7543900",
        "tgn:7001242",
        "tgn:7016833",
        "tgn:1001088",
        "tgn:7029392"
    ],
    "tgn:id":7543900,
    "tgn:name:en":"Sawd\u0101', Til\u0101l",
    "tgn:placetype":[
        "aat:300008777"
    ]
},
  "bbox": [],
  "geometry": {"coordinates":[30.563057,28.504375],"type":"Point"}
}