{
  "id": 7473338,
  "type": "Feature",
  "properties": {
    "tgn:hierarchy":[
        "tgn:7473338",
        "tgn:7001010",
        "tgn:1000004",
        "tgn:1000141",
        "tgn:7029392"
    ],
    "tgn:id":7473338,
    "tgn:name":"Dongluntian Shan",
    "tgn:placetype":[
        "aat:300008798"
    ]
},
  "bbox": [],
  "geometry": {"coordinates":[121.195,23.191667],"type":"Point"}
}