<<<<<<< HEAD
{
  "id": 7473338,
  "type": "Feature",
  "properties": {
    "tgn:hierarchy":[
        "tgn:7473338",
        "tgn:7001010",
        "tgn:1000004",
        "tgn:1000141",
        "tgn:7029392"
    ],
    "tgn:id":7473338,
    "tgn:name":"Dongluntian Shan",
    "tgn:placetype":[
        "aat:300008798"
    ]
},
  "bbox": [],
  "geometry": {"coordinates":[121.195,23.191667],"type":"Point"}
}
=======
{"geometry":{"type":"Point","coordinates":[121.195000,23.191667]},"type":"Feature","properties":{"hierarchy":["tgn:7473338","tgn:7001010","tgn:1000004","tgn:1000141","tgn:7029392"],"placetype":["aat:300008798"],"id":7473338,"name:xx":"Dongluntian Shan"}}
>>>>>>> 03f74aca74312dbeaf24d7e61306dd6a786dc3d0
