{
  "id": 7430659,
  "type": "Feature",
  "properties": {
    "tgn:hierarchy":[
        "tgn:7430659",
        "tgn:1000001",
        "tgn:7005595",
        "tgn:7005560",
        "tgn:7029392"
    ],
    "tgn:id":7430659,
    "tgn:name":"La Sierrita de Germ\u00e1n",
    "tgn:placetype":[
        "aat:300008347"
    ]
},
  "bbox": [],
  "geometry": {"coordinates":[-107.683333,26.016667],"type":"Point"}
}