{
  "id": 2151682,
  "type": "Feature",
  "properties": {
    "tgn:hierarchy":[
        "tgn:2151682",
        "tgn:1000001",
        "tgn:7012149",
        "tgn:2001821",
        "tgn:7007713",
        "tgn:7029392"
    ],
    "tgn:id":2151682,
    "tgn:name":"Battle Creek",
    "tgn:placetype":[
        "aat:300008706"
    ]
},
  "bbox": [],
  "geometry": {"coordinates":[-103.6167,43.9167],"type":"Point"}
}