{
  "id": 7432008,
  "type": "Feature",
  "properties": {
    "tgn:hierarchy":[
        "tgn:7432008",
        "tgn:7005586",
        "tgn:1000001",
        "tgn:7005560",
        "tgn:7029392"
    ],
    "tgn:id":7432008,
    "tgn:name":"El Tropez\u00f3n",
    "tgn:placetype":[
        "aat:300008347"
    ]
},
  "bbox": [],
  "geometry": {"coordinates":[-102.033333,21.55],"type":"Point"}
}