{
  "id": 7452196,
  "type": "Feature",
  "properties": {
    "tgn:hierarchy":[
        "tgn:7452196",
        "tgn:7002445",
        "tgn:1000003",
        "tgn:7008117",
        "tgn:7008591",
        "tgn:7029392"
    ],
    "tgn:id":7452196,
    "tgn:name:en":"Foulney Island",
    "tgn:placetype":[
        "aat:300008791"
    ]
},
  "bbox": [],
  "geometry": {"coordinates":[-3.15,54.05],"type":"Point"}
}