{
  "id": 2394852,
  "type": "Feature",
  "properties": {
    "tgn:hierarchy":[
        "tgn:2394852",
        "tgn:7002659",
        "tgn:1000001",
        "tgn:7012149",
        "tgn:2000036",
        "tgn:7029392"
    ],
    "tgn:id":2394852,
    "tgn:name":"Holcomb Lake",
    "tgn:placetype":[
        "aat:300006191"
    ]
},
  "bbox": [],
  "geometry": {"coordinates":[-86.5333,33.6333],"type":"Point"}
}