{
  "id": 2229179,
  "type": "Feature",
  "properties": {
    "tgn:hierarchy":[
        "tgn:2229179",
        "tgn:1000001",
        "tgn:7012149",
        "tgn:2001068",
        "tgn:7007521",
        "tgn:7029392"
    ],
    "tgn:id":2229179,
    "tgn:name":"Cedar Lake",
    "tgn:placetype":[
        "aat:300008347"
    ]
},
  "bbox": [],
  "geometry": {"coordinates":[-93.4333,44.5833],"type":"Point"}
}