{
  "id": 7529183,
  "type": "Feature",
  "properties": {
    "tgn:hierarchy":[
        "tgn:7529183",
        "tgn:7001242",
        "tgn:1001059",
        "tgn:7016833",
        "tgn:7029392"
    ],
    "tgn:id":7529183,
    "tgn:name":"Tur'at 'Al\u012b Ri\u1e11\u0101",
    "tgn:placetype":[
        "aat:300006075"
    ]
},
  "bbox": [],
  "geometry": {"coordinates":[31.545604,30.856603],"type":"Point"}
}