{
  "id": 7165115,
  "type": "Feature",
  "properties": {
    "tgn:hierarchy":[
        "tgn:7165115",
        "tgn:1000003",
        "tgn:7003677",
        "tgn:7000084",
        "tgn:7029392"
    ],
    "tgn:id":7165115,
    "tgn:name":"H\u00f6merberg",
    "tgn:placetype":[
        "aat:300000206"
    ]
},
  "bbox": [],
  "geometry": {"coordinates":[9.016667,51.833333],"type":"Point"}
}