{
  "id": 7411846,
  "type": "Feature",
  "properties": {
    "tgn:hierarchy":[
        "tgn:7411846",
        "tgn:7005587",
        "tgn:1000001",
        "tgn:7005560",
        "tgn:7029392"
    ],
    "tgn:id":7411846,
    "tgn:name:es":"Pohuantitla",
    "tgn:placetype":[
        "aat:300008347"
    ]
},
  "bbox": [],
  "geometry": {"coordinates":[-98.308333,20.866667],"type":"Point"}
}