{
  "id": 2309716,
  "type": "Feature",
  "properties": {
    "tgn:hierarchy":[
        "tgn:2309716",
        "tgn:1000001",
        "tgn:2002316",
        "tgn:7012149",
        "tgn:7007922",
        "tgn:7029392"
    ],
    "tgn:id":2309716,
    "tgn:name":"Easter Rock",
    "tgn:placetype":[
        "aat:300008347"
    ]
},
  "bbox": [],
  "geometry": {"coordinates":[-90.7167,43.15],"type":"Point"}
}