{
  "id": 2328650,
  "type": "Feature",
  "properties": {
    "tgn:hierarchy":[
        "tgn:2328650",
        "tgn:1000001",
        "tgn:1002249",
        "tgn:7012149",
        "tgn:7007710",
        "tgn:7029392"
    ],
    "tgn:id":2328650,
    "tgn:name":"Fishermans Paradise",
    "tgn:placetype":[
        "aat:300008347"
    ]
},
  "bbox": [],
  "geometry": {"coordinates":[-77.7833,40.8667],"type":"Point"}
}