{
  "id": 1029411,
  "type": "Feature",
  "properties": {
    "tgn:hierarchy":[
        "tgn:1029411",
        "tgn:7002445",
        "tgn:7008116",
        "tgn:1000003",
        "tgn:7008591",
        "tgn:7029392"
    ],
    "tgn:id":1029411,
    "tgn:name:en":"Gunnislake",
    "tgn:placetype":[
        "aat:300008347"
    ]
},
  "bbox": [],
  "geometry": {"coordinates":[-4.216667,50.533333],"type":"Point"}
}