{
  "id": 2057072,
  "type": "Feature",
  "properties": {
    "tgn:hierarchy":[
        "tgn:2057072",
        "tgn:2001090",
        "tgn:1000001",
        "tgn:7012149",
        "tgn:7007522",
        "tgn:7029392"
    ],
    "tgn:id":2057072,
    "tgn:name":"New Canaan",
    "tgn:placetype":[
        "aat:300008347",
        "aat:300387210"
    ]
},
  "bbox": [],
  "geometry": {"coordinates":[-89.1167,34.9333],"type":"Point"}
}