{
  "id": 2551515,
  "type": "Feature",
  "properties": {
    "tgn:hierarchy":[
        "tgn:2551515",
        "tgn:1000001",
        "tgn:7012149",
        "tgn:2001212",
        "tgn:7007523",
        "tgn:7029392"
    ],
    "tgn:id":2551515,
    "tgn:name":"Number 190 Reservoir",
    "tgn:placetype":[
        "aat:300006191"
    ]
},
  "bbox": [],
  "geometry": {"coordinates":[-93.6333,39.1833],"type":"Point"}
}