{
  "id": 2235086,
  "type": "Feature",
  "properties": {
    "tgn:hierarchy":[
        "tgn:2235086",
        "tgn:1000001",
        "tgn:7012149",
        "tgn:7007826",
        "tgn:7029392"
    ],
    "tgn:id":2235086,
    "tgn:name":"Cherry Point Gully",
    "tgn:placetype":[
        "aat:300008761"
    ]
},
  "bbox": [],
  "geometry": {"coordinates":[-94.8667,29.8833],"type":"Point"}
}