{
  "id": 7448403,
  "type": "Feature",
  "properties": {
    "tgn:hierarchy":[
        "tgn:7448403",
        "tgn:7002444",
        "tgn:1000003",
        "tgn:7009907",
        "tgn:7008591",
        "tgn:7029392"
    ],
    "tgn:id":7448403,
    "tgn:name:en":"Spur Ness",
    "tgn:placetype":[
        "aat:300008850"
    ]
},
  "bbox": [],
  "geometry": {"coordinates":[-2.683333,59.183333],"type":"Point"}
}