{
  "id": 2325920,
  "type": "Feature",
  "properties": {
    "tgn:hierarchy":[
        "tgn:2325920",
        "tgn:1000001",
        "tgn:7012149",
        "tgn:1003042",
        "tgn:7007920",
        "tgn:7029392"
    ],
    "tgn:id":2325920,
    "tgn:name":"Fifes Ridge",
    "tgn:placetype":[
        "aat:300266640"
    ]
},
  "bbox": [],
  "geometry": {"coordinates":[-121.2333,46.9667],"type":"Point"}
}