{
  "id": 2689266,
  "type": "Feature",
  "properties": {
    "tgn:hierarchy":[
        "tgn:2689266",
        "tgn:1000001",
        "tgn:7012149",
        "tgn:2000490",
        "tgn:7007250",
        "tgn:7029392"
    ],
    "tgn:id":2689266,
    "tgn:name":"Squaw Creek",
    "tgn:placetype":[
        "aat:300008706"
    ]
},
  "bbox": [],
  "geometry": {"coordinates":[-112.6833,42.5833],"type":"Point"}
}