{
  "id": 2569058,
  "type": "Feature",
  "properties": {
    "tgn:hierarchy":[
        "tgn:2569058",
        "tgn:1000001",
        "tgn:7012149",
        "tgn:1002990",
        "tgn:7007708",
        "tgn:7029392"
    ],
    "tgn:id":2569058,
    "tgn:name":"Parker Springs",
    "tgn:placetype":[
        "aat:300008697"
    ]
},
  "bbox": [],
  "geometry": {"coordinates":[-117.9167,45.0333],"type":"Point"}
}