{
  "id": 2473563,
  "type": "Feature",
  "properties": {
    "tgn:hierarchy":[
        "tgn:2473563",
        "tgn:1000001",
        "tgn:2002257",
        "tgn:7012149",
        "tgn:7013961",
        "tgn:7029392"
    ],
    "tgn:id":2473563,
    "tgn:name":"Lower Creek",
    "tgn:placetype":[
        "aat:300008706"
    ]
},
  "bbox": [],
  "geometry": {"coordinates":[-82.15,38.4667],"type":"Point"}
}