{
  "id": 7480770,
  "type": "Feature",
  "properties": {
    "tgn:hierarchy":[
        "tgn:7480770",
        "tgn:7001010",
        "tgn:1000004",
        "tgn:1000141",
        "tgn:7029392"
    ],
    "tgn:id":7480770,
    "tgn:name":"Fahuashan Cihuitang",
    "tgn:placetype":[
        "aat:300007595"
    ]
},
  "bbox": [],
  "geometry": {"coordinates":[121.549722,23.986389],"type":"Point"}
}