<<<<<<< HEAD
{
  "id": 7480770,
  "type": "Feature",
  "properties": {
    "tgn:hierarchy":[
        "tgn:7480770",
        "tgn:7001010",
        "tgn:1000004",
        "tgn:1000141",
        "tgn:7029392"
    ],
    "tgn:id":7480770,
    "tgn:name":"Fahuashan Cihuitang",
    "tgn:placetype":[
        "aat:300007595"
    ]
},
  "bbox": [],
  "geometry": {"coordinates":[121.549722,23.986389],"type":"Point"}
}
=======
{"geometry":{"type":"Point","coordinates":[121.549722,23.986389]},"type":"Feature","properties":{"hierarchy":["tgn:7480770","tgn:7001010","tgn:1000004","tgn:1000141","tgn:7029392"],"placetype":["aat:300007595"],"id":7480770,"name:xx":"Fahuashan Cihuitang"}}
>>>>>>> 03f74aca74312dbeaf24d7e61306dd6a786dc3d0
