{
  "id": 7590262,
  "type": "Feature",
  "properties": {
    "tgn:hierarchy":[
        "tgn:7590262",
        "tgn:1000004",
        "tgn:7000198",
        "tgn:7000799",
        "tgn:7029392"
    ],
    "tgn:id":7590262,
    "tgn:name:en":"Burji N\u0101r",
    "tgn:placetype":[
        "aat:300008699"
    ]
},
  "bbox": [],
  "geometry": {"coordinates":[73.945694,34.320148],"type":"Point"}
}