{
  "id": 2458588,
  "type": "Feature",
  "properties": {
    "tgn:hierarchy":[
        "tgn:2458588",
        "tgn:1000001",
        "tgn:7012149",
        "tgn:1002756",
        "tgn:7007240",
        "tgn:7029392"
    ],
    "tgn:id":2458588,
    "tgn:name":"Little North Prong",
    "tgn:placetype":[
        "aat:300008699"
    ]
},
  "bbox": [],
  "geometry": {"coordinates":[-81.0333,28.1167],"type":"Point"}
}