<<<<<<< HEAD
{
  "id": 7111074,
  "type": "Feature",
  "properties": {
    "tgn:hierarchy":[
        "tgn:7111074",
        "tgn:1000003",
        "tgn:7003677",
        "tgn:7000084",
        "tgn:7029392"
    ],
    "tgn:id":7111074,
    "tgn:name":"Remsto\u00df",
    "tgn:placetype":[
        "aat:300000206"
    ]
},
  "bbox": [],
  "geometry": {"coordinates":[8.7,51.383333],"type":"Point"}
}
=======
{"geometry":{"type":"Point","coordinates":[8.700000,51.383333]},"type":"Feature","properties":{"hierarchy":["tgn:7111074","tgn:1000003","tgn:7003677","tgn:7000084","tgn:7029392"],"placetype":["aat:300000206"],"id":7111074,"name:xx":"Remsto\u00df"}}
>>>>>>> 03f74aca74312dbeaf24d7e61306dd6a786dc3d0
