{
  "id": 2571218,
  "type": "Feature",
  "properties": {
    "tgn:hierarchy":[
        "tgn:2571218",
        "tgn:1000001",
        "tgn:7012149",
        "tgn:7007706",
        "tgn:7029392"
    ],
    "tgn:id":2571218,
    "tgn:name":"Patton Run",
    "tgn:placetype":[
        "aat:300008699"
    ]
},
  "bbox": [],
  "geometry": {"coordinates":[-80.9167,40.1833],"type":"Point"}
}