{
  "id": 2763437,
  "type": "Feature",
  "properties": {
    "tgn:hierarchy":[
        "tgn:2763437",
        "tgn:1000001",
        "tgn:7012149",
        "tgn:2001191",
        "tgn:7007523",
        "tgn:7029392"
    ],
    "tgn:id":2763437,
    "tgn:name":"Wetzel Branch",
    "tgn:placetype":[
        "aat:300008699"
    ]
},
  "bbox": [],
  "geometry": {"coordinates":[-93.85,37.3833],"type":"Point"}
}