{
  "id": 7117709,
  "type": "Feature",
  "properties": {
    "tgn:hierarchy":[
        "tgn:7117709",
        "tgn:7003669",
        "tgn:1000003",
        "tgn:7000084",
        "tgn:7029392"
    ],
    "tgn:id":7117709,
    "tgn:name":"Obers\u00f6chering",
    "tgn:placetype":[
        "aat:300008347"
    ]
},
  "bbox": [],
  "geometry": {"coordinates":[11.216667,47.733333],"type":"Point"}
}