{
  "id": 7243715,
  "type": "Feature",
  "properties": {
    "tgn:hierarchy":[
        "tgn:7243715",
        "tgn:7007877",
        "tgn:1000003",
        "tgn:1000063",
        "tgn:4012014",
        "tgn:7029392"
    ],
    "tgn:id":7243715,
    "tgn:name":"Houtaing",
    "tgn:placetype":[
        "aat:300008347"
    ]
},
  "bbox": [],
  "geometry": {"coordinates":[3.681009,50.638517],"type":"Point"}
}