{
  "id": 7572177,
  "type": "Feature",
  "properties": {
    "tgn:hierarchy":[
        "tgn:7572177",
        "tgn:1000004",
        "tgn:7000198",
        "tgn:1001894",
        "tgn:7029392"
    ],
    "tgn:id":7572177,
    "tgn:name:en":"Hindori\u0101",
    "tgn:placetype":[
        "aat:300008347"
    ]
},
  "bbox": [],
  "geometry": {"coordinates":[79.569039,23.902644],"type":"Point"}
}