{
  "id": 2479212,
  "type": "Feature",
  "properties": {
    "tgn:hierarchy":[
        "tgn:2479212",
        "tgn:1000001",
        "tgn:7012149",
        "tgn:7007157",
        "tgn:1003050",
        "tgn:7029392"
    ],
    "tgn:id":2479212,
    "tgn:name":"Lafferty Peak",
    "tgn:placetype":[
        "aat:300008798"
    ]
},
  "bbox": [],
  "geometry": {"coordinates":[-121.3833,39.3167],"type":"Point"}
}