{
  "id": 1069757,
  "type": "Feature",
  "properties": {
    "tgn:hierarchy":[
        "tgn:1069757",
        "tgn:1000004",
        "tgn:7005232",
        "tgn:1000111",
        "tgn:7029392"
    ],
    "tgn:id":1069757,
    "tgn:name":"Liangkou",
    "tgn:placetype":[
        "aat:300008347"
    ]
},
  "bbox": [],
  "geometry": {"coordinates":[113.7167,23.7167],"type":"Point"}
}