<<<<<<< HEAD
{
  "id": 7371746,
  "type": "Feature",
  "properties": {
    "tgn:hierarchy":[
        "tgn:7371746",
        "tgn:1000001",
        "tgn:7005591",
        "tgn:7005560",
        "tgn:7029392"
    ],
    "tgn:id":7371746,
    "tgn:name":"La Cal",
    "tgn:placetype":[
        "aat:300008347"
    ]
},
  "bbox": [],
  "geometry": {"coordinates":[-96.7,17.033333],"type":"Point"}
}
=======
{"geometry":{"type":"Point","coordinates":[-96.700000,17.033333]},"type":"Feature","properties":{"hierarchy":["tgn:7371746","tgn:1000001","tgn:7005591","tgn:7005560","tgn:7029392"],"placetype":["aat:300008347"],"id":7371746,"name:xx":"La Cal"}}
>>>>>>> 03f74aca74312dbeaf24d7e61306dd6a786dc3d0
