{
  "id": 2306299,
  "type": "Feature",
  "properties": {
    "tgn:hierarchy":[
        "tgn:2306299",
        "tgn:1000001",
        "tgn:7012149",
        "tgn:7007827",
        "tgn:7029392"
    ],
    "tgn:id":2306299,
    "tgn:name":"East Fork Canal",
    "tgn:placetype":[
        "aat:300006075"
    ]
},
  "bbox": [],
  "geometry": {"coordinates":[-111.9833,38.1333],"type":"Point"}
}