<<<<<<< HEAD
{
  "id": 7056607,
  "type": "Feature",
  "properties": {
    "tgn:hierarchy":[
        "tgn:7056607",
        "tgn:7003163",
        "tgn:1000003",
        "tgn:7009760",
        "tgn:1000080",
        "tgn:7029392"
    ],
    "tgn:id":7056607,
    "tgn:name":"Aghezzola",
    "tgn:placetype":[
        "aat:300008347"
    ]
},
  "bbox": [],
  "geometry": {"coordinates":[11.5,44.083333],"type":"Point"}
}
=======
{"geometry":{"type":"Point","coordinates":[11.500000,44.083333]},"type":"Feature","properties":{"hierarchy":["tgn:7056607","tgn:7003163","tgn:1000003","tgn:7009760","tgn:1000080","tgn:7029392"],"placetype":["aat:300008347"],"id":7056607,"name:xx":"Aghezzola"}}
>>>>>>> 03f74aca74312dbeaf24d7e61306dd6a786dc3d0
