{
  "id": 7456156,
  "type": "Feature",
  "properties": {
    "tgn:hierarchy":[
        "tgn:7456156",
        "tgn:7019094",
        "tgn:7002444",
        "tgn:1000003",
        "tgn:7008591",
        "tgn:7029392"
    ],
    "tgn:id":7456156,
    "tgn:name:en":"Crossapol Bay",
    "tgn:placetype":[
        "aat:300132316"
    ]
},
  "bbox": [],
  "geometry": {"coordinates":[-6.65,56.566667],"type":"Point"}
}