{
  "id": 1025251,
  "type": "Feature",
  "properties": {
    "tgn:hierarchy":[
        "tgn:1025251",
        "tgn:1001985",
        "tgn:1000002",
        "tgn:1000059",
        "tgn:7029392"
    ],
    "tgn:id":1025251,
    "tgn:name":"Rosario",
    "tgn:placetype":[
        "aat:300008347"
    ]
},
  "bbox": [],
  "geometry": {"coordinates":[-72.3167,10.3167],"type":"Point"}
}