{
  "id": 7411497,
  "type": "Feature",
  "properties": {
    "tgn:hierarchy":[
        "tgn:7411497",
        "tgn:7005580",
        "tgn:1000001",
        "tgn:7005560",
        "tgn:7029392"
    ],
    "tgn:id":7411497,
    "tgn:name":"Santa Cruz, R\u00edo",
    "tgn:placetype":[
        "aat:300008699"
    ]
},
  "bbox": [],
  "geometry": {"coordinates":[-91.716667,17.033333],"type":"Point"}
}