<<<<<<< HEAD
{
  "id": 7378135,
  "type": "Feature",
  "properties": {
    "tgn:hierarchy":[
        "tgn:7378135",
        "tgn:1000001",
        "tgn:7005589",
        "tgn:7005560",
        "tgn:7029392"
    ],
    "tgn:id":7378135,
    "tgn:name":"Las Pe\u00f1as",
    "tgn:placetype":[
        "aat:300008347"
    ]
},
  "bbox": [],
  "geometry": {"coordinates":[-98.583333,26.0],"type":"Point"}
}
=======
{"geometry":{"type":"Point","coordinates":[-98.583333,26.000000]},"type":"Feature","properties":{"hierarchy":["tgn:7378135","tgn:1000001","tgn:7005589","tgn:7005560","tgn:7029392"],"placetype":["aat:300008347"],"id":7378135,"name:xx":"Las Pe\u00f1as"}}
>>>>>>> 03f74aca74312dbeaf24d7e61306dd6a786dc3d0
