{
  "id": 7525028,
  "type": "Feature",
  "properties": {
    "tgn:hierarchy":[
        "tgn:7525028",
        "tgn:7001242",
        "tgn:1001059",
        "tgn:7016833",
        "tgn:7029392"
    ],
    "tgn:id":7525028,
    "tgn:name:en":"Al Qib\u0101b al Kubr\u00e1",
    "tgn:placetype":[
        "aat:300008347"
    ]
},
  "bbox": [],
  "geometry": {"coordinates":[31.527833,31.086891],"type":"Point"}
}