{
  "id": 7565623,
  "type": "Feature",
  "properties": {
    "tgn:hierarchy":[
        "tgn:7565623",
        "tgn:1000004",
        "tgn:7000198",
        "tgn:1001894",
        "tgn:7029392"
    ],
    "tgn:id":7565623,
    "tgn:name:en":"Nanhi Tehri Protected Forest",
    "tgn:placetype":[
        "aat:300008865"
    ]
},
  "bbox": [],
  "geometry": {"coordinates":[79.056657,24.695823],"type":"Point"}
}