{
  "id": 2571383,
  "type": "Feature",
  "properties": {
    "tgn:hierarchy":[
        "tgn:2571383",
        "tgn:1000001",
        "tgn:7012149",
        "tgn:2002377",
        "tgn:7007923",
        "tgn:7029392"
    ],
    "tgn:id":2571383,
    "tgn:name":"Paul Reservoir",
    "tgn:placetype":[
        "aat:300006191"
    ]
},
  "bbox": [],
  "geometry": {"coordinates":[-106.55,43.2167],"type":"Point"}
}