{
  "id": 2651975,
  "type": "Feature",
  "properties": {
    "tgn:hierarchy":[
        "tgn:2651975",
        "tgn:1000001",
        "tgn:7012149",
        "tgn:2001907",
        "tgn:7007825",
        "tgn:7029392"
    ],
    "tgn:id":2651975,
    "tgn:name":"Selby",
    "tgn:placetype":[
        "aat:300008347"
    ]
},
  "bbox": [],
  "geometry": {"coordinates":[-85.4667,36.2167],"type":"Point"}
}