{
  "id": 7302071,
  "type": "Feature",
  "properties": {
    "tgn:hierarchy":[
        "tgn:7302071",
        "tgn:7002805",
        "tgn:7002758",
        "tgn:1000003",
        "tgn:1000095",
        "tgn:7029392"
    ],
    "tgn:id":7302071,
    "tgn:name":"Mesa Rold\u00e1n",
    "tgn:placetype":[
        "aat:300008347"
    ]
},
  "bbox": [],
  "geometry": {"coordinates":[-1.916667,36.95],"type":"Point"}
}