{
  "id": 2656329,
  "type": "Feature",
  "properties": {
    "tgn:hierarchy":[
        "tgn:2656329",
        "tgn:1000001",
        "tgn:7012149",
        "tgn:2002248",
        "tgn:7007920",
        "tgn:7029392"
    ],
    "tgn:id":2656329,
    "tgn:name":"Shearer Lake",
    "tgn:placetype":[
        "aat:300008680"
    ]
},
  "bbox": [],
  "geometry": {"coordinates":[-117.0333,48.2167],"type":"Point"}
}