{
  "id": 7537844,
  "type": "Feature",
  "properties": {
    "tgn:hierarchy":[
        "tgn:7537844",
        "tgn:7001242",
        "tgn:7016833",
        "tgn:7001336",
        "tgn:7029392"
    ],
    "tgn:id":7537844,
    "tgn:name:en":"Shaykh Riy\u0101\u1e29",
    "tgn:placetype":[
        "aat:300132316"
    ]
},
  "bbox": [],
  "geometry": {"coordinates":[33.656477,28.153002],"type":"Point"}
}