{
  "id": 2213569,
  "type": "Feature",
  "properties": {
    "tgn:hierarchy":[
        "tgn:2213569",
        "tgn:1000001",
        "tgn:7012149",
        "tgn:2000840",
        "tgn:7007255",
        "tgn:7029392"
    ],
    "tgn:id":2213569,
    "tgn:name":"Cable Knob",
    "tgn:placetype":[
        "aat:300008798"
    ]
},
  "bbox": [],
  "geometry": {"coordinates":[-84.4167,37.3333],"type":"Point"}
}