{
  "id": 7465865,
  "type": "Feature",
  "properties": {
    "tgn:hierarchy":[
        "tgn:7465865",
        "tgn:7002445",
        "tgn:1000003",
        "tgn:7008166",
        "tgn:7008591",
        "tgn:7029392"
    ],
    "tgn:id":7465865,
    "tgn:name:en":"Barton",
    "tgn:placetype":[
        "aat:300008347"
    ]
},
  "bbox": [],
  "geometry": {"coordinates":[-1.65,54.466667],"type":"Point"}
}