{
  "id": 2185791,
  "type": "Feature",
  "properties": {
    "tgn:hierarchy":[
        "tgn:2185791",
        "tgn:7014010",
        "tgn:1000001",
        "tgn:1002344",
        "tgn:7012149",
        "tgn:7007517",
        "tgn:7029392"
    ],
    "tgn:id":2185791,
    "tgn:name":"Bold Water Point",
    "tgn:placetype":[
        "aat:300008850"
    ]
},
  "bbox": [],
  "geometry": {"coordinates":[-70.55,41.3667],"type":"Point"}
}