{
  "id": 2589484,
  "type": "Feature",
  "properties": {
    "tgn:hierarchy":[
        "tgn:2589484",
        "tgn:1002366",
        "tgn:1000001",
        "tgn:7012149",
        "tgn:7007159",
        "tgn:7029392"
    ],
    "tgn:id":2589484,
    "tgn:name":"Point Hedden",
    "tgn:placetype":[
        "aat:300008850"
    ]
},
  "bbox": [],
  "geometry": {"coordinates":[-73.45,41.5167],"type":"Point"}
}