{
  "id": 2084253,
  "type": "Feature",
  "properties": {
    "tgn:hierarchy":[
        "tgn:2084253",
        "tgn:1000001",
        "tgn:7012149",
        "tgn:2001689",
        "tgn:7007707",
        "tgn:7029392"
    ],
    "tgn:id":2084253,
    "tgn:name":"Wewoka",
    "tgn:placetype":[
        "aat:300008347"
    ]
},
  "bbox": [],
  "geometry": {"coordinates":[-96.4833,35.15],"type":"Point"}
}