{
  "id": 2530934,
  "type": "Feature",
  "properties": {
    "tgn:hierarchy":[
        "tgn:2530934",
        "tgn:1000001",
        "tgn:7012149",
        "tgn:2002291",
        "tgn:7013961",
        "tgn:7029392"
    ],
    "tgn:id":2530934,
    "tgn:name":"Mudlick Run",
    "tgn:placetype":[
        "aat:300008699"
    ]
},
  "bbox": [],
  "geometry": {"coordinates":[-80.0833,38.55],"type":"Point"}
}