{
  "id": 7333834,
  "type": "Feature",
  "properties": {
    "tgn:hierarchy":[
        "tgn:7333834",
        "tgn:7008912",
        "tgn:7030216",
        "tgn:1000003",
        "tgn:1000095",
        "tgn:7029392"
    ],
    "tgn:id":7333834,
    "tgn:name":"Erillavall",
    "tgn:placetype":[
        "aat:300008347"
    ]
},
  "bbox": [],
  "geometry": {"coordinates":[0.824875,42.525125],"type":"Point"}
}