{
  "id": 7367112,
  "type": "Feature",
  "properties": {
    "tgn:hierarchy":[
        "tgn:7367112",
        "tgn:1000001",
        "tgn:1001960",
        "tgn:7005560",
        "tgn:7029392"
    ],
    "tgn:id":7367112,
    "tgn:name":"El Tren",
    "tgn:placetype":[
        "aat:300008347"
    ]
},
  "bbox": [],
  "geometry": {"coordinates":[-109.333333,30.133333],"type":"Point"}
}