{
  "id": 2708062,
  "type": "Feature",
  "properties": {
    "tgn:hierarchy":[
        "tgn:2708062",
        "tgn:1000001",
        "tgn:1002194",
        "tgn:7012149",
        "tgn:7007710",
        "tgn:7029392"
    ],
    "tgn:id":2708062,
    "tgn:name":"Swimming Dam",
    "tgn:placetype":[
        "aat:300006191"
    ]
},
  "bbox": [],
  "geometry": {"coordinates":[-76.6167,41.65],"type":"Point"}
}