{
  "id": 7127899,
  "type": "Feature",
  "properties": {
    "tgn:hierarchy":[
        "tgn:7127899",
        "tgn:1000003",
        "tgn:7003678",
        "tgn:7000084",
        "tgn:7029392"
    ],
    "tgn:id":7127899,
    "tgn:name":"Ober-Mooser Teich",
    "tgn:placetype":[
        "aat:300008688"
    ]
},
  "bbox": [],
  "geometry": {"coordinates":[9.366667,50.45],"type":"Point"}
}