<<<<<<< HEAD
{
  "id": 2402103,
  "type": "Feature",
  "properties": {
    "tgn:hierarchy":[
        "tgn:2402103",
        "tgn:1000001",
        "tgn:7006451",
        "tgn:7012149",
        "tgn:2000103",
        "tgn:7029392"
    ],
    "tgn:id":2402103,
    "tgn:name":"Horseshoe Tank",
    "tgn:placetype":[
        "aat:300006191"
    ]
},
  "bbox": [],
  "geometry": {"coordinates":[-112.15,34.8],"type":"Point"}
}
=======
{"geometry":{"type":"Point","coordinates":[-112.150000,34.800000]},"type":"Feature","properties":{"hierarchy":["tgn:2402103","tgn:1000001","tgn:7006451","tgn:7012149","tgn:2000103","tgn:7029392"],"placetype":["aat:300006191"],"id":2402103,"name:xx":"Horseshoe Tank"}}
>>>>>>> 03f74aca74312dbeaf24d7e61306dd6a786dc3d0
