{
  "id": 1015519,
  "type": "Feature",
  "properties": {
    "tgn:hierarchy":[
        "tgn:1015519",
        "tgn:7005685",
        "tgn:1000001",
        "tgn:7005804",
        "tgn:7029392"
    ],
    "tgn:id":1015519,
    "tgn:name":"Montmagny",
    "tgn:placetype":[
        "aat:300008347"
    ]
},
  "bbox": [],
  "geometry": {"coordinates":[-70.55,46.9833],"type":"Point"}
}