{
  "id": 1031111,
  "type": "Feature",
  "properties": {
    "tgn:hierarchy":[
        "tgn:1031111",
        "tgn:7002445",
        "tgn:1000003",
        "tgn:7008165",
        "tgn:7008591",
        "tgn:7029392"
    ],
    "tgn:id":1031111,
    "tgn:name:en":"Whittingham",
    "tgn:placetype":[
        "aat:300008347"
    ]
},
  "bbox": [],
  "geometry": {"coordinates":[-1.883333,55.383333],"type":"Point"}
}