{
  "id": 2146067,
  "type": "Feature",
  "properties": {
    "tgn:hierarchy":[
        "tgn:2146067",
        "tgn:1000001",
        "tgn:7016172",
        "tgn:7012149",
        "tgn:2000146",
        "tgn:7029392"
    ],
    "tgn:id":2146067,
    "tgn:name":"Ball Spring",
    "tgn:placetype":[
        "aat:300008697"
    ]
},
  "bbox": [],
  "geometry": {"coordinates":[-93.6833,35.1833],"type":"Point"}
}