{
  "id": 2606169,
  "type": "Feature",
  "properties": {
    "tgn:hierarchy":[
        "tgn:2606169",
        "tgn:7006450",
        "tgn:1000001",
        "tgn:7012149",
        "tgn:2000089",
        "tgn:7029392"
    ],
    "tgn:id":2606169,
    "tgn:name":"Rainy Creek",
    "tgn:placetype":[
        "aat:300008706"
    ]
},
  "bbox": [],
  "geometry": {"coordinates":[-150.7833,63.55],"type":"Point"}
}