{
  "id": 2054664,
  "type": "Feature",
  "properties": {
    "tgn:hierarchy":[
        "tgn:2054664",
        "tgn:1000001",
        "tgn:7012149",
        "tgn:2001084",
        "tgn:7007521",
        "tgn:7029392"
    ],
    "tgn:id":2054664,
    "tgn:name":"Highland",
    "tgn:placetype":[
        "aat:300008347",
        "aat:300387210"
    ]
},
  "bbox": [],
  "geometry": {"coordinates":[-94.0167,45.1167],"type":"Point"}
}