{
  "id": 7324011,
  "type": "Feature",
  "properties": {
    "tgn:hierarchy":[
        "tgn:7324011",
        "tgn:7002759",
        "tgn:7002845",
        "tgn:1000003",
        "tgn:1000095",
        "tgn:7029392"
    ],
    "tgn:id":7324011,
    "tgn:name":"Sediles",
    "tgn:placetype":[
        "aat:300008347"
    ]
},
  "bbox": [],
  "geometry": {"coordinates":[-1.533333,41.35],"type":"Point"}
}