{
  "id": 2364839,
  "type": "Feature",
  "properties": {
    "tgn:hierarchy":[
        "tgn:2364839",
        "tgn:1000001",
        "tgn:2000264",
        "tgn:7012149",
        "tgn:7007240",
        "tgn:7029392"
    ],
    "tgn:id":2364839,
    "tgn:name":"Greenfield",
    "tgn:placetype":[
        "aat:300008347"
    ]
},
  "bbox": [],
  "geometry": {"coordinates":[-81.4333,30.35],"type":"Point"}
}