{
  "id": 7295787,
  "type": "Feature",
  "properties": {
    "tgn:hierarchy":[
        "tgn:7295787",
        "tgn:7008911",
        "tgn:1000003",
        "tgn:7002763",
        "tgn:1000095",
        "tgn:7029392"
    ],
    "tgn:id":7295787,
    "tgn:name":"Dique Principe de Asturias",
    "tgn:placetype":[
        "aat:300387387"
    ]
},
  "bbox": [],
  "geometry": {"coordinates":[-5.689722,43.566944],"type":"Point"}
}