{
  "id": 2329441,
  "type": "Feature",
  "properties": {
    "tgn:hierarchy":[
        "tgn:2329441",
        "tgn:1000001",
        "tgn:7012149",
        "tgn:1002983",
        "tgn:7007252",
        "tgn:7029392"
    ],
    "tgn:id":2329441,
    "tgn:name":"Five Points",
    "tgn:placetype":[
        "aat:300008347"
    ]
},
  "bbox": [],
  "geometry": {"coordinates":[-87.3167,40.3167],"type":"Point"}
}