{
  "id": 7333180,
  "type": "Feature",
  "properties": {
    "tgn:hierarchy":[
        "tgn:7333180",
        "tgn:7008911",
        "tgn:1000003",
        "tgn:7002763",
        "tgn:1000095",
        "tgn:7029392"
    ],
    "tgn:id":7333180,
    "tgn:name":"Juncedo-Campo",
    "tgn:placetype":[
        "aat:300008347"
    ]
},
  "bbox": [],
  "geometry": {"coordinates":[-5.916667,43.516667],"type":"Point"}
}