{
  "id": 7515116,
  "type": "Feature",
  "properties": {
    "tgn:hierarchy":[
        "tgn:7515116",
        "tgn:1009227",
        "tgn:1000226",
        "tgn:7018437",
        "tgn:1000006",
        "tgn:7029392"
    ],
    "tgn:id":7515116,
    "tgn:name:en":"Crook Burn",
    "tgn:placetype":[
        "aat:300008699"
    ]
},
  "bbox": [],
  "geometry": {"coordinates":[169.516667,-46.066667],"type":"Point"}
}