{
  "id": 2747822,
  "type": "Feature",
  "properties": {
    "tgn:hierarchy":[
        "tgn:2747822",
        "tgn:1000001",
        "tgn:7012149",
        "tgn:2001060",
        "tgn:7007521",
        "tgn:7029392"
    ],
    "tgn:id":2747822,
    "tgn:name":"Wakefield Lake",
    "tgn:placetype":[
        "aat:300008680"
    ]
},
  "bbox": [],
  "geometry": {"coordinates":[-93.0333,44.9833],"type":"Point"}
}