{
  "id": 1044150,
  "type": "Feature",
  "properties": {
    "tgn:hierarchy":[
        "tgn:1044150",
        "tgn:7003005",
        "tgn:7003014",
        "tgn:1000003",
        "tgn:1000080",
        "tgn:7029392"
    ],
    "tgn:id":1044150,
    "tgn:name":"Ceraso",
    "tgn:placetype":[
        "aat:300008347"
    ]
},
  "bbox": [],
  "geometry": {"coordinates":[15.25,40.183333],"type":"Point"}
}