{
  "id": 2132089,
  "type": "Feature",
  "properties": {
    "tgn:hierarchy":[
        "tgn:2132089",
        "tgn:1000001",
        "tgn:7012149",
        "tgn:7007157",
        "tgn:2000187",
        "tgn:7029392"
    ],
    "tgn:id":2132089,
    "tgn:name":"American House Ravine",
    "tgn:placetype":[
        "aat:300008761"
    ]
},
  "bbox": [],
  "geometry": {"coordinates":[-121.0167,39.65],"type":"Point"}
}