{
  "id": 7564164,
  "type": "Feature",
  "properties": {
    "tgn:hierarchy":[
        "tgn:7564164",
        "tgn:1000004",
        "tgn:7000198",
        "tgn:7016788",
        "tgn:7029392"
    ],
    "tgn:id":7564164,
    "tgn:name:en":"Dh\u0101mchula Dhora",
    "tgn:placetype":[
        "aat:300008750"
    ]
},
  "bbox": [],
  "geometry": {"coordinates":[74.57456,28.312361],"type":"Point"}
}