{
  "id": 2685095,
  "type": "Feature",
  "properties": {
    "tgn:hierarchy":[
        "tgn:2685095",
        "tgn:1000001",
        "tgn:7012149",
        "tgn:2000491",
        "tgn:7007250",
        "tgn:7029392"
    ],
    "tgn:id":2685095,
    "tgn:name":"Spooky Butte",
    "tgn:placetype":[
        "aat:300008798"
    ]
},
  "bbox": [],
  "geometry": {"coordinates":[-116.15,47.3333],"type":"Point"}
}