{
  "id": 7496376,
  "type": "Feature",
  "properties": {
    "tgn:hierarchy":[
        "tgn:7496376",
        "tgn:7487020",
        "tgn:1000004",
        "tgn:1000141",
        "tgn:7029392"
    ],
    "tgn:id":7496376,
    "tgn:name":"Zhepoukeng",
    "tgn:placetype":[
        "aat:300008347"
    ]
},
  "bbox": [],
  "geometry": {"coordinates":[120.899399,24.418341],"type":"Point"}
}