<<<<<<< HEAD
{
  "id": 7057104,
  "type": "Feature",
  "properties": {
    "tgn:hierarchy":[
        "tgn:7057104",
        "tgn:1000003",
        "tgn:7003121",
        "tgn:1000080",
        "tgn:7029392"
    ],
    "tgn:id":7057104,
    "tgn:name":"Barbagia",
    "tgn:placetype":[
        "aat:300387346"
    ]
},
  "bbox": [],
  "geometry": {"coordinates":[9.083333,40.0],"type":"Point"}
}
=======
{"geometry":{"type":"Point","coordinates":[9.083333,40.000000]},"type":"Feature","properties":{"hierarchy":["tgn:7057104","tgn:1000003","tgn:7003121","tgn:1000080","tgn:7029392"],"placetype":["aat:300387346"],"id":7057104,"name:xx":"Barbagia"}}
>>>>>>> 03f74aca74312dbeaf24d7e61306dd6a786dc3d0
