{
  "id": 2168550,
  "type": "Feature",
  "properties": {
    "tgn:hierarchy":[
        "tgn:2168550",
        "tgn:1000001",
        "tgn:7012149",
        "tgn:1002593",
        "tgn:7007568",
        "tgn:7029392"
    ],
    "tgn:id":2168550,
    "tgn:name":"Big Hill",
    "tgn:placetype":[
        "aat:300008798"
    ]
},
  "bbox": [],
  "geometry": {"coordinates":[-75.2667,44.1333],"type":"Point"}
}