{
  "id": 7382412,
  "type": "Feature",
  "properties": {
    "tgn:hierarchy":[
        "tgn:7382412",
        "tgn:7005584",
        "tgn:1000001",
        "tgn:7005560",
        "tgn:7029392"
    ],
    "tgn:id":7382412,
    "tgn:name":"Ojo Seco",
    "tgn:placetype":[
        "aat:300007783"
    ]
},
  "bbox": [],
  "geometry": {"coordinates":[-100.766667,20.383333],"type":"Point"}
}