{
  "id": 2129273,
  "type": "Feature",
  "properties": {
    "tgn:hierarchy":[
        "tgn:2129273",
        "tgn:1000001",
        "tgn:7012149",
        "tgn:7018871",
        "tgn:7007920",
        "tgn:7029392"
    ],
    "tgn:id":2129273,
    "tgn:name":"Alice Creek",
    "tgn:placetype":[
        "aat:300008706"
    ]
},
  "bbox": [],
  "geometry": {"coordinates":[-121.6167,47.3833],"type":"Point"}
}