{
  "id": 7316983,
  "type": "Feature",
  "properties": {
    "tgn:hierarchy":[
        "tgn:7316983",
        "tgn:7002464",
        "tgn:1000049",
        "tgn:1000002",
        "tgn:7029392"
    ],
    "tgn:id":7316983,
    "tgn:name":"Condorire, R\u00edo",
    "tgn:placetype":[
        "aat:300008699"
    ]
},
  "bbox": [],
  "geometry": {"coordinates":[-69.216667,-18.033333],"type":"Point"}
}