{
  "id": 7408578,
  "type": "Feature",
  "properties": {
    "tgn:hierarchy":[
        "tgn:7408578",
        "tgn:1000001",
        "tgn:1001893",
        "tgn:7005560",
        "tgn:7029392"
    ],
    "tgn:id":7408578,
    "tgn:name":"Tejocotes",
    "tgn:placetype":[
        "aat:300008347"
    ]
},
  "bbox": [],
  "geometry": {"coordinates":[-99.833333,18.625],"type":"Point"}
}