{
  "id": 7018804,
  "type": "Feature",
  "properties": {
    "tgn:hierarchy":[
        "tgn:7018804",
        "tgn:7005685",
        "tgn:1000001",
        "tgn:7013154",
        "tgn:7029392"
    ],
    "tgn:id":7018804,
    "tgn:name":"Welland Ship Canal",
    "tgn:placetype":[
        "aat:300006075"
    ]
},
  "bbox": [],
  "geometry": {"coordinates":[-79.2167,43.2167],"type":"Point"}
}