{
  "id": 2185392,
  "type": "Feature",
  "properties": {
    "tgn:hierarchy":[
        "tgn:2185392",
        "tgn:1000001",
        "tgn:2001013",
        "tgn:7012149",
        "tgn:7007521",
        "tgn:7029392"
    ],
    "tgn:id":2185392,
    "tgn:name":"Bogus Lake",
    "tgn:placetype":[
        "aat:300008680"
    ]
},
  "bbox": [],
  "geometry": {"coordinates":[-95.2333,47.15],"type":"Point"}
}