<<<<<<< HEAD
{
  "id": 7488212,
  "type": "Feature",
  "properties": {
    "tgn:hierarchy":[
        "tgn:7488212",
        "tgn:1000004",
        "tgn:7001009",
        "tgn:1000141",
        "tgn:7029392"
    ],
    "tgn:id":7488212,
    "tgn:name":"Nanikengxiang",
    "tgn:placetype":[
        "aat:300008773"
    ]
},
  "bbox": [],
  "geometry": {"coordinates":[120.739666,24.053537],"type":"Point"}
}
=======
{"geometry":{"type":"Point","coordinates":[120.739666,24.053537]},"type":"Feature","properties":{"hierarchy":["tgn:7488212","tgn:1000004","tgn:7001009","tgn:1000141","tgn:7029392"],"placetype":["aat:300008773"],"id":7488212,"name:xx":"Nanikengxiang"}}
>>>>>>> 03f74aca74312dbeaf24d7e61306dd6a786dc3d0
