{
  "id": 1095547,
  "type": "Feature",
  "properties": {
    "tgn:hierarchy":[
        "tgn:1095547",
        "tgn:7001242",
        "tgn:1001059",
        "tgn:7016833",
        "tgn:7029392"
    ],
    "tgn:id":1095547,
    "tgn:name":"Kafr at Tam\u012bm\u012b",
    "tgn:placetype":[
        "aat:300008347"
    ]
},
  "bbox": [],
  "geometry": {"coordinates":[31.361073,30.610477],"type":"Point"}
}