{
  "id": 7153679,
  "type": "Feature",
  "properties": {
    "tgn:hierarchy":[
        "tgn:7153679",
        "tgn:1000003",
        "tgn:7003677",
        "tgn:7000084",
        "tgn:7029392"
    ],
    "tgn:id":7153679,
    "tgn:name":"F\u00f6rsterei Kalkh\u00e4uschen",
    "tgn:placetype":[
        "aat:300004792"
    ]
},
  "bbox": [],
  "geometry": {"coordinates":[6.166667,50.683333],"type":"Point"}
}