{
  "id": 2390390,
  "type": "Feature",
  "properties": {
    "tgn:hierarchy":[
        "tgn:2390390",
        "tgn:1000001",
        "tgn:7012149",
        "tgn:2001854",
        "tgn:7007825",
        "tgn:7029392"
    ],
    "tgn:id":2390390,
    "tgn:name":"Highland Homesite Addition",
    "tgn:placetype":[
        "aat:300008347"
    ]
},
  "bbox": [],
  "geometry": {"coordinates":[-84.9833,35.95],"type":"Point"}
}