{
  "id": 2578510,
  "type": "Feature",
  "properties": {
    "tgn:hierarchy":[
        "tgn:2578510",
        "tgn:1000001",
        "tgn:1002228",
        "tgn:7012149",
        "tgn:7007709",
        "tgn:7029392"
    ],
    "tgn:id":2578510,
    "tgn:name":"Philadelphia",
    "tgn:placetype":[
        "aat:300008347"
    ]
},
  "bbox": [],
  "geometry": {"coordinates":[-76.0333,36.25],"type":"Point"}
}