{
  "id": 2372922,
  "type": "Feature",
  "properties": {
    "tgn:hierarchy":[
        "tgn:2372922",
        "tgn:7006450",
        "tgn:1000001",
        "tgn:7030517",
        "tgn:7012149",
        "tgn:7029392"
    ],
    "tgn:id":2372922,
    "tgn:name":"Hallersville Creek",
    "tgn:placetype":[
        "aat:300008706"
    ]
},
  "bbox": [],
  "geometry": {"coordinates":[-156.7667,59.0333],"type":"Point"}
}