{
  "id": 2380019,
  "type": "Feature",
  "properties": {
    "tgn:hierarchy":[
        "tgn:2380019",
        "tgn:1000001",
        "tgn:7012149",
        "tgn:1002591",
        "tgn:7007255",
        "tgn:7029392"
    ],
    "tgn:id":2380019,
    "tgn:name":"Hatcher Branch",
    "tgn:placetype":[
        "aat:300008699"
    ]
},
  "bbox": [],
  "geometry": {"coordinates":[-83.45,38.5167],"type":"Point"}
}