{
  "id": 7225522,
  "type": "Feature",
  "properties": {
    "tgn:hierarchy":[
        "tgn:7225522",
        "tgn:7002735",
        "tgn:7017076",
        "tgn:1000003",
        "tgn:1000074",
        "tgn:7029392"
    ],
    "tgn:id":7225522,
    "tgn:name":"Ps\u00edlos",
    "tgn:placetype":[
        "aat:300008795"
    ]
},
  "bbox": [],
  "geometry": {"coordinates":[22.866667,37.216667],"type":"Point"}
}