{
  "id": 7146528,
  "type": "Feature",
  "properties": {
    "tgn:hierarchy":[
        "tgn:7146528",
        "tgn:7003692",
        "tgn:1000003",
        "tgn:7000084",
        "tgn:7029392"
    ],
    "tgn:id":7146528,
    "tgn:name":"Kleinsachsenheim",
    "tgn:placetype":[
        "aat:300008347"
    ]
},
  "bbox": [],
  "geometry": {"coordinates":[9.083333,48.966667],"type":"Point"}
}