{
  "id": 2550441,
  "type": "Feature",
  "properties": {
    "tgn:hierarchy":[
        "tgn:2550441",
        "tgn:1000001",
        "tgn:2001477",
        "tgn:7012149",
        "tgn:7007709",
        "tgn:7029392"
    ],
    "tgn:id":2550441,
    "tgn:name":"Northwest Prong Newport River",
    "tgn:placetype":[
        "aat:300008707"
    ]
},
  "bbox": [],
  "geometry": {"coordinates":[-76.9333,34.8333],"type":"Point"}
}