{
  "id": 7295814,
  "type": "Feature",
  "properties": {
    "tgn:hierarchy":[
        "tgn:7295814",
        "tgn:7002760",
        "tgn:1000003",
        "tgn:1000095",
        "tgn:7029392"
    ],
    "tgn:id":7295814,
    "tgn:name":"Jorge, Canal de",
    "tgn:placetype":[
        "aat:300387026"
    ]
},
  "bbox": [],
  "geometry": {"coordinates":[-3.464444,43.423056],"type":"Point"}
}