<<<<<<< HEAD
{
  "id": 2253732,
  "type": "Feature",
  "properties": {
    "tgn:hierarchy":[
        "tgn:2253732",
        "tgn:1000001",
        "tgn:7012149",
        "tgn:2001706",
        "tgn:7007708",
        "tgn:7029392"
    ],
    "tgn:id":2253732,
    "tgn:name":"Cookhouse Creek",
    "tgn:placetype":[
        "aat:300008706"
    ]
},
  "bbox": [],
  "geometry": {"coordinates":[-123.5,42.95],"type":"Point"}
}
=======
{"geometry":{"type":"Point","coordinates":[-123.500000,42.950000]},"type":"Feature","properties":{"hierarchy":["tgn:2253732","tgn:1000001","tgn:7012149","tgn:2001706","tgn:7007708","tgn:7029392"],"placetype":["aat:300008706"],"id":2253732,"name:xx":"Cookhouse Creek"}}
>>>>>>> 03f74aca74312dbeaf24d7e61306dd6a786dc3d0
