{
  "id": 2122719,
  "type": "Feature",
  "properties": {
    "tgn:hierarchy":[
        "tgn:2122719",
        "tgn:1000001",
        "tgn:7012149",
        "tgn:1002815",
        "tgn:7007922",
        "tgn:7029392"
    ],
    "tgn:id":2122719,
    "tgn:name":"Wind Point",
    "tgn:placetype":[
        "aat:300008347"
    ]
},
  "bbox": [],
  "geometry": {"coordinates":[-87.75,42.7833],"type":"Point"}
}