{
  "id": 2050642,
  "type": "Feature",
  "properties": {
    "tgn:hierarchy":[
        "tgn:2050642",
        "tgn:1000001",
        "tgn:1002359",
        "tgn:7012149",
        "tgn:7007517",
        "tgn:7029392"
    ],
    "tgn:id":2050642,
    "tgn:name":"South Groveland",
    "tgn:placetype":[
        "aat:300008347"
    ]
},
  "bbox": [],
  "geometry": {"coordinates":[-71.0333,42.7333],"type":"Point"}
}