{
  "id": 2404596,
  "type": "Feature",
  "properties": {
    "tgn:hierarchy":[
        "tgn:2404596",
        "tgn:1000001",
        "tgn:7012149",
        "tgn:7007520",
        "tgn:7029392"
    ],
    "tgn:id":2404596,
    "tgn:name":"Huber Creek",
    "tgn:placetype":[
        "aat:300008706"
    ]
},
  "bbox": [],
  "geometry": {"coordinates":[-87.1833,46.2667],"type":"Point"}
}