<<<<<<< HEAD
{
  "id": 2404596,
  "type": "Feature",
  "properties": {
    "tgn:hierarchy":[
        "tgn:2404596",
        "tgn:1000001",
        "tgn:7012149",
        "tgn:7007520",
        "tgn:7029392"
    ],
    "tgn:id":2404596,
    "tgn:name":"Huber Creek",
    "tgn:placetype":[
        "aat:300008706"
    ]
},
  "bbox": [],
  "geometry": {"coordinates":[-87.1833,46.2667],"type":"Point"}
}
=======
{"geometry":{"type":"Point","coordinates":[-87.183300,46.266700]},"type":"Feature","properties":{"hierarchy":["tgn:2404596","tgn:1000001","tgn:7012149","tgn:7007520","tgn:7029392"],"placetype":["aat:300008706"],"id":2404596,"name:xx":"Huber Creek"}}
>>>>>>> 03f74aca74312dbeaf24d7e61306dd6a786dc3d0
