{
  "id": 7551708,
  "type": "Feature",
  "properties": {
    "tgn:hierarchy":[
        "tgn:7551708",
        "tgn:1000004",
        "tgn:7000198",
        "tgn:7016788",
        "tgn:7029392"
    ],
    "tgn:id":7551708,
    "tgn:name:en":"Deb\u0101ri",
    "tgn:placetype":[
        "aat:300007783"
    ]
},
  "bbox": [],
  "geometry": {"coordinates":[73.804881,24.619793],"type":"Point"}
}