{
  "id": 2225303,
  "type": "Feature",
  "properties": {
    "tgn:hierarchy":[
        "tgn:2225303",
        "tgn:1000001",
        "tgn:7012149",
        "tgn:7007157",
        "tgn:1002706",
        "tgn:7029392"
    ],
    "tgn:id":2225303,
    "tgn:name":"Castle Peak",
    "tgn:placetype":[
        "aat:300008798"
    ]
},
  "bbox": [],
  "geometry": {"coordinates":[-122.2667,38.3833],"type":"Point"}
}