{
  "id": 2669332,
  "type": "Feature",
  "properties": {
    "tgn:hierarchy":[
        "tgn:2669332",
        "tgn:1000001",
        "tgn:7012149",
        "tgn:7007157",
        "tgn:1002915",
        "tgn:7029392"
    ],
    "tgn:id":2669332,
    "tgn:name":"Slick Rock Canyon",
    "tgn:placetype":[
        "aat:300008761"
    ]
},
  "bbox": [],
  "geometry": {"coordinates":[-121.3333,37.45],"type":"Point"}
}