{
  "id": 2572915,
  "type": "Feature",
  "properties": {
    "tgn:hierarchy":[
        "tgn:2572915",
        "tgn:1000001",
        "tgn:2002107",
        "tgn:7012149",
        "tgn:7007827",
        "tgn:7029392"
    ],
    "tgn:id":2572915,
    "tgn:name":"Pearl Canyon",
    "tgn:placetype":[
        "aat:300008761"
    ]
},
  "bbox": [],
  "geometry": {"coordinates":[-110.6833,39.8167],"type":"Point"}
}