{
  "id": 2282235,
  "type": "Feature",
  "properties": {
    "tgn:hierarchy":[
        "tgn:2282235",
        "tgn:1000001",
        "tgn:7012149",
        "tgn:2001724",
        "tgn:7007710",
        "tgn:7029392"
    ],
    "tgn:id":2282235,
    "tgn:name":"Deer Lick",
    "tgn:placetype":[
        "aat:300008347"
    ]
},
  "bbox": [],
  "geometry": {"coordinates":[-80.2667,39.9667],"type":"Point"}
}