<<<<<<< HEAD
{
  "id": 7479381,
  "type": "Feature",
  "properties": {
    "tgn:hierarchy":[
        "tgn:7479381",
        "tgn:1000004",
        "tgn:7490934",
        "tgn:1000141",
        "tgn:7029392"
    ],
    "tgn:id":7479381,
    "tgn:name":"Kengzinei",
    "tgn:placetype":[
        "aat:300008347"
    ]
},
  "bbox": [],
  "geometry": {"coordinates":[120.47213,23.191317],"type":"Point"}
}
=======
{"geometry":{"type":"Point","coordinates":[120.472130,23.191317]},"type":"Feature","properties":{"hierarchy":["tgn:7479381","tgn:1000004","tgn:7490934","tgn:1000141","tgn:7029392"],"placetype":["aat:300008347"],"id":7479381,"name:xx":"Kengzinei"}}
>>>>>>> 03f74aca74312dbeaf24d7e61306dd6a786dc3d0
