{
  "id": 2599805,
  "type": "Feature",
  "properties": {
    "tgn:hierarchy":[
        "tgn:2599805",
        "tgn:1000001",
        "tgn:2001632",
        "tgn:7012149",
        "tgn:7007707",
        "tgn:7029392"
    ],
    "tgn:id":2599805,
    "tgn:name":"Provence",
    "tgn:placetype":[
        "aat:300008347"
    ]
},
  "bbox": [],
  "geometry": {"coordinates":[-97.0167,34.15],"type":"Point"}
}