{
  "id": 2513909,
  "type": "Feature",
  "properties": {
    "tgn:hierarchy":[
        "tgn:2513909",
        "tgn:1000001",
        "tgn:7012149",
        "tgn:7007709",
        "tgn:7029392"
    ],
    "tgn:id":2513909,
    "tgn:name":"Mill Swamp",
    "tgn:placetype":[
        "aat:300008699"
    ]
},
  "bbox": [],
  "geometry": {"coordinates":[-77.0167,35.6667],"type":"Point"}
}