{
  "id": 7298327,
  "type": "Feature",
  "properties": {
    "tgn:hierarchy":[
        "tgn:7298327",
        "tgn:7002824",
        "tgn:1000003",
        "tgn:7002786",
        "tgn:1000095",
        "tgn:7029392"
    ],
    "tgn:id":7298327,
    "tgn:name":"Send\u00f3n",
    "tgn:placetype":[
        "aat:300008347"
    ]
},
  "bbox": [],
  "geometry": {"coordinates":[-8.966667,42.883333],"type":"Point"}
}