{
  "id": 2127754,
  "type": "Feature",
  "properties": {
    "tgn:hierarchy":[
        "tgn:2127754",
        "tgn:1000001",
        "tgn:7012149",
        "tgn:7007157",
        "tgn:1002972",
        "tgn:7029392"
    ],
    "tgn:id":2127754,
    "tgn:name":"Alamo Mountain",
    "tgn:placetype":[
        "aat:300008798"
    ]
},
  "bbox": [],
  "geometry": {"coordinates":[-118.95,34.6667],"type":"Point"}
}