{
  "id": 2161304,
  "type": "Feature",
  "properties": {
    "tgn:hierarchy":[
        "tgn:2161304",
        "tgn:1000001",
        "tgn:7012149",
        "tgn:2002182",
        "tgn:7007919",
        "tgn:7029392"
    ],
    "tgn:id":2161304,
    "tgn:name":"Bell Lake",
    "tgn:placetype":[
        "aat:300006191"
    ]
},
  "bbox": [],
  "geometry": {"coordinates":[-78.5667,37.1667],"type":"Point"}
}