{
  "id": 7050368,
  "type": "Feature",
  "properties": {
    "tgn:hierarchy":[
        "tgn:7050368",
        "tgn:7003170",
        "tgn:1000003",
        "tgn:7003125",
        "tgn:1000080",
        "tgn:7029392"
    ],
    "tgn:id":7050368,
    "tgn:name":"Nottoria",
    "tgn:placetype":[
        "aat:300008347"
    ]
},
  "bbox": [],
  "geometry": {"coordinates":[13.15,42.716667],"type":"Point"}
}