<<<<<<< HEAD
{
  "id": 7474267,
  "type": "Feature",
  "properties": {
    "tgn:hierarchy":[
        "tgn:7474267",
        "tgn:1000004",
        "tgn:7467799",
        "tgn:1000141",
        "tgn:7029392"
    ],
    "tgn:id":7474267,
    "tgn:name":"Dingbuxiang",
    "tgn:placetype":[
        "aat:300008347"
    ]
},
  "bbox": [],
  "geometry": {"coordinates":[120.628,23.8047],"type":"Point"}
}
=======
{"geometry":{"type":"Point","coordinates":[120.628000,23.804700]},"type":"Feature","properties":{"hierarchy":["tgn:7474267","tgn:1000004","tgn:7467799","tgn:1000141","tgn:7029392"],"placetype":["aat:300008347"],"id":7474267,"name:xx":"Dingbuxiang"}}
>>>>>>> 03f74aca74312dbeaf24d7e61306dd6a786dc3d0
