{
  "id": 2191754,
  "type": "Feature",
  "properties": {
    "tgn:hierarchy":[
        "tgn:2191754",
        "tgn:1000001",
        "tgn:7012149",
        "tgn:1002518",
        "tgn:7007568",
        "tgn:7029392"
    ],
    "tgn:id":2191754,
    "tgn:name":"Bradley Point",
    "tgn:placetype":[
        "aat:300008850"
    ]
},
  "bbox": [],
  "geometry": {"coordinates":[-76.0167,44.3333],"type":"Point"}
}