{
  "id": 2711026,
  "type": "Feature",
  "properties": {
    "tgn:hierarchy":[
        "tgn:2711026",
        "tgn:1000001",
        "tgn:7012149",
        "tgn:2001455",
        "tgn:7007566",
        "tgn:7029392"
    ],
    "tgn:id":2711026,
    "tgn:name":"Tank Sixteen",
    "tgn:placetype":[
        "aat:300006191"
    ]
},
  "bbox": [],
  "geometry": {"coordinates":[-107.45,33.0833],"type":"Point"}
}