<<<<<<< HEAD
{
  "id": 7483866,
  "type": "Feature",
  "properties": {
    "tgn:hierarchy":[
        "tgn:7483866",
        "tgn:1000004",
        "tgn:7001009",
        "tgn:1000141",
        "tgn:7029392"
    ],
    "tgn:id":7483866,
    "tgn:name":"Nanbu Tifang",
    "tgn:placetype":[
        "aat:300006156"
    ]
},
  "bbox": [],
  "geometry": {"coordinates":[120.563333,24.338333],"type":"Point"}
}
=======
{"geometry":{"type":"Point","coordinates":[120.563333,24.338333]},"type":"Feature","properties":{"hierarchy":["tgn:7483866","tgn:1000004","tgn:7001009","tgn:1000141","tgn:7029392"],"placetype":["aat:300006156"],"id":7483866,"name:xx":"Nanbu Tifang"}}
>>>>>>> 03f74aca74312dbeaf24d7e61306dd6a786dc3d0
