{
  "id": 7460402,
  "type": "Feature",
  "properties": {
    "tgn:hierarchy":[
        "tgn:7460402",
        "tgn:7002444",
        "tgn:7019115",
        "tgn:1000003",
        "tgn:7008591",
        "tgn:7029392"
    ],
    "tgn:id":7460402,
    "tgn:name:en":"Hopes Water",
    "tgn:placetype":[
        "aat:300008699"
    ]
},
  "bbox": [],
  "geometry": {"coordinates":[-2.783333,55.933333],"type":"Point"}
}