{
  "id": 2350632,
  "type": "Feature",
  "properties": {
    "tgn:hierarchy":[
        "tgn:2350632",
        "tgn:1000001",
        "tgn:7012149",
        "tgn:2001291",
        "tgn:7007524",
        "tgn:7029392"
    ],
    "tgn:id":2350632,
    "tgn:name":"Glacier Lake",
    "tgn:placetype":[
        "aat:300006191"
    ]
},
  "bbox": [],
  "geometry": {"coordinates":[-113.9333,47.0333],"type":"Point"}
}