{
  "id": 2560666,
  "type": "Feature",
  "properties": {
    "tgn:hierarchy":[
        "tgn:2560666",
        "tgn:1000001",
        "tgn:7012149",
        "tgn:7007158",
        "tgn:2000246",
        "tgn:7029392"
    ],
    "tgn:id":2560666,
    "tgn:name":"Oregon Tunnel",
    "tgn:placetype":[
        "aat:300000390"
    ]
},
  "bbox": [],
  "geometry": {"coordinates":[-106.1167,38.2667],"type":"Point"}
}