{
  "id": 2744943,
  "type": "Feature",
  "properties": {
    "tgn:hierarchy":[
        "tgn:2744943",
        "tgn:1000001",
        "tgn:7012149",
        "tgn:2001712",
        "tgn:7007708",
        "tgn:7029392"
    ],
    "tgn:id":2744943,
    "tgn:name":"View Lake",
    "tgn:placetype":[
        "aat:300008680"
    ]
},
  "bbox": [],
  "geometry": {"coordinates":[-121.7833,44.7833],"type":"Point"}
}