{
  "id": 7436644,
  "type": "Feature",
  "properties": {
    "tgn:hierarchy":[
        "tgn:7436644",
        "tgn:7005587",
        "tgn:1000001",
        "tgn:7005560",
        "tgn:7029392"
    ],
    "tgn:id":7436644,
    "tgn:name":"Tepozoyuca",
    "tgn:placetype":[
        "aat:300008347"
    ]
},
  "bbox": [],
  "geometry": {"coordinates":[-98.733333,19.966667],"type":"Point"}
}