<<<<<<< HEAD
{
  "id": 2332590,
  "type": "Feature",
  "properties": {
    "tgn:hierarchy":[
        "tgn:2332590",
        "tgn:1000001",
        "tgn:7012149",
        "tgn:2000225",
        "tgn:7007158",
        "tgn:7029392"
    ],
    "tgn:id":2332590,
    "tgn:name":"Florida Mesa",
    "tgn:placetype":[
        "aat:300008798"
    ]
},
  "bbox": [],
  "geometry": {"coordinates":[-107.8,37.2667],"type":"Point"}
}
=======
{"geometry":{"type":"Point","coordinates":[-107.800000,37.266700]},"type":"Feature","properties":{"hierarchy":["tgn:2332590","tgn:1000001","tgn:7012149","tgn:2000225","tgn:7007158","tgn:7029392"],"placetype":["aat:300008798"],"id":2332590,"name:xx":"Florida Mesa"}}
>>>>>>> 03f74aca74312dbeaf24d7e61306dd6a786dc3d0
