{
  "id": 2672878,
  "type": "Feature",
  "properties": {
    "tgn:hierarchy":[
        "tgn:2672878",
        "tgn:1000001",
        "tgn:7016172",
        "tgn:2000110",
        "tgn:7012149",
        "tgn:7029392"
    ],
    "tgn:id":2672878,
    "tgn:name":"Snake Creek",
    "tgn:placetype":[
        "aat:300008706"
    ]
},
  "bbox": [],
  "geometry": {"coordinates":[-92.05,33.4833],"type":"Point"}
}