{
  "id": 2411105,
  "type": "Feature",
  "properties": {
    "tgn:hierarchy":[
        "tgn:2411105",
        "tgn:1000001",
        "tgn:7012149",
        "tgn:2000638",
        "tgn:7007253",
        "tgn:7029392"
    ],
    "tgn:id":2411105,
    "tgn:name":"Indian Creek Ditch",
    "tgn:placetype":[
        "aat:300006075"
    ]
},
  "bbox": [],
  "geometry": {"coordinates":[-95.8667,41.2167],"type":"Point"}
}