{
  "id": 2420462,
  "type": "Feature",
  "properties": {
    "tgn:hierarchy":[
        "tgn:2420462",
        "tgn:1000001",
        "tgn:7012149",
        "tgn:2001224",
        "tgn:7007523",
        "tgn:7029392"
    ],
    "tgn:id":2420462,
    "tgn:name":"Jenkins Creek",
    "tgn:placetype":[
        "aat:300008706"
    ]
},
  "bbox": [],
  "geometry": {"coordinates":[-94.9167,40.25],"type":"Point"}
}