{
  "id": 7393740,
  "type": "Feature",
  "properties": {
    "tgn:hierarchy":[
        "tgn:7393740",
        "tgn:1000001",
        "tgn:7005597",
        "tgn:7005560",
        "tgn:7029392"
    ],
    "tgn:id":7393740,
    "tgn:name":"San Jos\u00e9",
    "tgn:placetype":[
        "aat:300008347"
    ]
},
  "bbox": [],
  "geometry": {"coordinates":[-99.534444,24.238889],"type":"Point"}
}