{
  "id": 2778750,
  "type": "Feature",
  "properties": {
    "tgn:hierarchy":[
        "tgn:2778750",
        "tgn:1000001",
        "tgn:2001477",
        "tgn:7012149",
        "tgn:7007709",
        "tgn:7029392"
    ],
    "tgn:id":2778750,
    "tgn:name":"Wolf Branch",
    "tgn:placetype":[
        "aat:300008699"
    ]
},
  "bbox": [],
  "geometry": {"coordinates":[-76.9333,34.7333],"type":"Point"}
}