{
  "id": 2575433,
  "type": "Feature",
  "properties": {
    "tgn:hierarchy":[
        "tgn:2575433",
        "tgn:1000001",
        "tgn:7012149",
        "tgn:1002553",
        "tgn:7007920",
        "tgn:7029392"
    ],
    "tgn:id":2575433,
    "tgn:name":"Peoh Point",
    "tgn:placetype":[
        "aat:300008798"
    ]
},
  "bbox": [],
  "geometry": {"coordinates":[-120.9333,47.15],"type":"Point"}
}