{
  "id": 7034322,
  "type": "Feature",
  "properties": {
    "tgn:hierarchy":[
        "tgn:7034322",
        "tgn:7003138",
        "tgn:1000003",
        "tgn:7003080",
        "tgn:1000080",
        "tgn:7029392"
    ],
    "tgn:id":7034322,
    "tgn:name":"Banchina Compagnia Roma",
    "tgn:placetype":[
        "aat:300120782"
    ]
},
  "bbox": [],
  "geometry": {"coordinates":[11.783333,42.083333],"type":"Point"}
}