<<<<<<< HEAD
{
  "id": 7244660,
  "type": "Feature",
  "properties": {
    "tgn:hierarchy":[
        "tgn:7244660",
        "tgn:7003456",
        "tgn:1000003",
        "tgn:1000063",
        "tgn:7018236",
        "tgn:7029392"
    ],
    "tgn:id":7244660,
    "tgn:name":"Schans van Letterheide",
    "tgn:placetype":[
        "aat:300006909"
    ]
},
  "bbox": [],
  "geometry": {"coordinates":[4.316667,51.066667],"type":"Point"}
}
=======
{"geometry":{"type":"Point","coordinates":[4.316667,51.066667]},"type":"Feature","properties":{"hierarchy":["tgn:7244660","tgn:7003456","tgn:1000003","tgn:1000063","tgn:7018236","tgn:7029392"],"placetype":["aat:300006909"],"id":7244660,"name:xx":"Schans van Letterheide"}}
>>>>>>> 03f74aca74312dbeaf24d7e61306dd6a786dc3d0
