{
  "id": 7111888,
  "type": "Feature",
  "properties": {
    "tgn:hierarchy":[
        "tgn:7111888",
        "tgn:1000003",
        "tgn:7003678",
        "tgn:7000084",
        "tgn:7029392"
    ],
    "tgn:id":7111888,
    "tgn:name":"Richelsdorf",
    "tgn:placetype":[
        "aat:300008347"
    ]
},
  "bbox": [],
  "geometry": {"coordinates":[10.016667,50.983333],"type":"Point"}
}