{
  "id": 2035118,
  "type": "Feature",
  "properties": {
    "tgn:hierarchy":[
        "tgn:2035118",
        "tgn:1000001",
        "tgn:7012149",
        "tgn:2000653",
        "tgn:7007253",
        "tgn:7029392"
    ],
    "tgn:id":2035118,
    "tgn:name":"Lineville",
    "tgn:placetype":[
        "aat:300008347"
    ]
},
  "bbox": [],
  "geometry": {"coordinates":[-93.5167,40.5667],"type":"Point"}
}