{
  "id": 2439399,
  "type": "Feature",
  "properties": {
    "tgn:hierarchy":[
        "tgn:2439399",
        "tgn:1000001",
        "tgn:2000459",
        "tgn:7012149",
        "tgn:7007250",
        "tgn:7029392"
    ],
    "tgn:id":2439399,
    "tgn:name":"Kirkham Ridge",
    "tgn:placetype":[
        "aat:300266640"
    ]
},
  "bbox": [],
  "geometry": {"coordinates":[-115.5333,44.0833],"type":"Point"}
}