{
  "id": 7429055,
  "type": "Feature",
  "properties": {
    "tgn:hierarchy":[
        "tgn:7429055",
        "tgn:1001835",
        "tgn:1000001",
        "tgn:7005560",
        "tgn:7029392"
    ],
    "tgn:id":7429055,
    "tgn:name":"Francisco Villa",
    "tgn:placetype":[
        "aat:300008347"
    ]
},
  "bbox": [],
  "geometry": {"coordinates":[-115.866667,30.466667],"type":"Point"}
}