{
  "id": 2264173,
  "type": "Feature",
  "properties": {
    "tgn:hierarchy":[
        "tgn:2264173",
        "tgn:2000090",
        "tgn:1000001",
        "tgn:7006451",
        "tgn:7012149",
        "tgn:7029392"
    ],
    "tgn:id":2264173,
    "tgn:name":"Coyote Tank",
    "tgn:placetype":[
        "aat:300006191"
    ]
},
  "bbox": [],
  "geometry": {"coordinates":[-109.2333,33.8333],"type":"Point"}
}