{
  "id": 2347704,
  "type": "Feature",
  "properties": {
    "tgn:hierarchy":[
        "tgn:2347704",
        "tgn:2000090",
        "tgn:1000001",
        "tgn:7006451",
        "tgn:7012149",
        "tgn:7029392"
    ],
    "tgn:id":2347704,
    "tgn:name":"Georges Tank",
    "tgn:placetype":[
        "aat:300006191"
    ]
},
  "bbox": [],
  "geometry": {"coordinates":[-109.1333,33.85],"type":"Point"}
}