{
  "id": 2546701,
  "type": "Feature",
  "properties": {
    "tgn:hierarchy":[
        "tgn:2546701",
        "tgn:1000001",
        "tgn:7012149",
        "tgn:2001279",
        "tgn:7007524",
        "tgn:7029392"
    ],
    "tgn:id":2546701,
    "tgn:name":"North Fork Lower Willow Creek",
    "tgn:placetype":[
        "aat:300008706"
    ]
},
  "bbox": [],
  "geometry": {"coordinates":[-113.45,46.55],"type":"Point"}
}