{
  "id": 2147837,
  "type": "Feature",
  "properties": {
    "tgn:hierarchy":[
        "tgn:2147837",
        "tgn:1000001",
        "tgn:2000772",
        "tgn:7012149",
        "tgn:7007255",
        "tgn:7029392"
    ],
    "tgn:id":2147837,
    "tgn:name":"Barge Creek",
    "tgn:placetype":[
        "aat:300008706"
    ]
},
  "bbox": [],
  "geometry": {"coordinates":[-83.2667,37.4333],"type":"Point"}
}