{
  "id": 1106138,
  "type": "Feature",
  "properties": {
    "tgn:hierarchy":[
        "tgn:1106138",
        "tgn:7005735",
        "tgn:7005685",
        "tgn:1000001",
        "tgn:7029392"
    ],
    "tgn:id":1106138,
    "tgn:name":"Queen Bess, Mount",
    "tgn:placetype":[
        "aat:300008795"
    ]
},
  "bbox": [],
  "geometry": {"coordinates":[-124.5833,51.2167],"type":"Point"}
}