{
  "id": 7558750,
  "type": "Feature",
  "properties": {
    "tgn:hierarchy":[
        "tgn:7558750",
        "tgn:7016678",
        "tgn:7000204",
        "tgn:1000004",
        "tgn:1007275",
        "tgn:7000198",
        "tgn:7029392"
    ],
    "tgn:id":7558750,
    "tgn:name:en":"Indira Point",
    "tgn:placetype":[
        "aat:300386846"
    ]
},
  "bbox": [],
  "geometry": {"coordinates":[93.828611,6.755556],"type":"Point"}
}