{
  "id": 7505365,
  "type": "Feature",
  "properties": {
    "tgn:hierarchy":[
        "tgn:7505365",
        "tgn:1009227",
        "tgn:1000226",
        "tgn:7016729",
        "tgn:1000006",
        "tgn:7029392"
    ],
    "tgn:id":7505365,
    "tgn:name:en":"Willawa Point",
    "tgn:placetype":[
        "aat:300386846"
    ]
},
  "bbox": [],
  "geometry": {"coordinates":[174.05,-41.966667],"type":"Point"}
}