{
  "id": 2431157,
  "type": "Feature",
  "properties": {
    "tgn:hierarchy":[
        "tgn:2431157",
        "tgn:1000001",
        "tgn:7012149",
        "tgn:1002779",
        "tgn:7007710",
        "tgn:7029392"
    ],
    "tgn:id":2431157,
    "tgn:name":"Kansas Valley",
    "tgn:placetype":[
        "aat:300008761"
    ]
},
  "bbox": [],
  "geometry": {"coordinates":[-77.5333,40.3667],"type":"Point"}
}