{
  "id": 7590799,
  "type": "Feature",
  "properties": {
    "tgn:hierarchy":[
        "tgn:7590799",
        "tgn:1000004",
        "tgn:7000198",
        "tgn:7000799",
        "tgn:7029392"
    ],
    "tgn:id":7590799,
    "tgn:name:en":"Lehr",
    "tgn:placetype":[
        "aat:300008347"
    ]
},
  "bbox": [],
  "geometry": {"coordinates":[74.700271,32.912637],"type":"Point"}
}