{
  "id": 2486994,
  "type": "Feature",
  "properties": {
    "tgn:hierarchy":[
        "tgn:2486994",
        "tgn:1000001",
        "tgn:7006451",
        "tgn:7012149",
        "tgn:2000101",
        "tgn:7029392"
    ],
    "tgn:id":2486994,
    "tgn:name":"Lee Mountain",
    "tgn:placetype":[
        "aat:300008798"
    ]
},
  "bbox": [],
  "geometry": {"coordinates":[-110.6667,33.05],"type":"Point"}
}