{
  "id": 1028463,
  "type": "Feature",
  "properties": {
    "tgn:hierarchy":[
        "tgn:1028463",
        "tgn:7002445",
        "tgn:1000003",
        "tgn:7011961",
        "tgn:7008591",
        "tgn:7029392"
    ],
    "tgn:id":1028463,
    "tgn:name:en":"Bere Regis",
    "tgn:placetype":[
        "aat:300008347"
    ]
},
  "bbox": [],
  "geometry": {"coordinates":[-2.216667,50.75],"type":"Point"}
}