{
  "id": 7279244,
  "type": "Feature",
  "properties": {
    "tgn:hierarchy":[
        "tgn:7279244",
        "tgn:1001695",
        "tgn:1000049",
        "tgn:1000002",
        "tgn:7029392"
    ],
    "tgn:id":7279244,
    "tgn:name":"Roma Abajo",
    "tgn:placetype":[
        "aat:300008347"
    ]
},
  "bbox": [],
  "geometry": {"coordinates":[-70.916667,-34.583333],"type":"Point"}
}