{
  "id": 2639982,
  "type": "Feature",
  "properties": {
    "tgn:hierarchy":[
        "tgn:2639982",
        "tgn:1000001",
        "tgn:7012149",
        "tgn:1002440",
        "tgn:7007568",
        "tgn:7029392"
    ],
    "tgn:id":2639982,
    "tgn:name":"Sampson Lake",
    "tgn:placetype":[
        "aat:300008680"
    ]
},
  "bbox": [],
  "geometry": {"coordinates":[-74.5667,43.5667],"type":"Point"}
}