{
  "id": 2343160,
  "type": "Feature",
  "properties": {
    "tgn:hierarchy":[
        "tgn:2343160",
        "tgn:1000001",
        "tgn:7012149",
        "tgn:1002314",
        "tgn:7007240",
        "tgn:7029392"
    ],
    "tgn:id":2343160,
    "tgn:name":"Gables Estates",
    "tgn:placetype":[
        "aat:300008347"
    ]
},
  "bbox": [],
  "geometry": {"coordinates":[-80.25,25.6833],"type":"Point"}
}