{
  "id": 1136480,
  "type": "Feature",
  "properties": {
    "tgn:hierarchy":[
        "tgn:1136480",
        "tgn:7006477",
        "tgn:1001169",
        "tgn:1000002",
        "tgn:7029392"
    ],
    "tgn:id":1136480,
    "tgn:name":"Villa del Rosario",
    "tgn:placetype":[
        "aat:300008347"
    ]
},
  "bbox": [],
  "geometry": {"coordinates":[-63.5667,-31.6333],"type":"Point"}
}