{
  "id": 2115807,
  "type": "Feature",
  "properties": {
    "tgn:hierarchy":[
        "tgn:2115807",
        "tgn:1000001",
        "tgn:7012149",
        "tgn:1002594",
        "tgn:7007920",
        "tgn:7029392"
    ],
    "tgn:id":2115807,
    "tgn:name":"Forest",
    "tgn:placetype":[
        "aat:300008347",
        "aat:300387210"
    ]
},
  "bbox": [],
  "geometry": {"coordinates":[-122.85,46.5833],"type":"Point"}
}