{
  "id": 7014255,
  "type": "Feature",
  "properties": {
    "tgn:hierarchy":[
        "tgn:7014255",
        "tgn:1000001",
        "tgn:7012149",
        "tgn:1002607",
        "tgn:7007706",
        "tgn:7029392"
    ],
    "tgn:id":7014255,
    "tgn:name":"Oberlin",
    "tgn:placetype":[
        "aat:300008347"
    ]
},
  "bbox": [],
  "geometry": {"coordinates":[-82.2167,41.2833],"type":"Point"}
}