{
  "id": 2421997,
  "type": "Feature",
  "properties": {
    "tgn:hierarchy":[
        "tgn:2421997",
        "tgn:1000001",
        "tgn:7012149",
        "tgn:2001556",
        "tgn:7007709",
        "tgn:7029392"
    ],
    "tgn:id":2421997,
    "tgn:name":"Jim Creek",
    "tgn:placetype":[
        "aat:300008706"
    ]
},
  "bbox": [],
  "geometry": {"coordinates":[-82.4833,35.9833],"type":"Point"}
}