{
  "id": 2560378,
  "type": "Feature",
  "properties": {
    "tgn:hierarchy":[
        "tgn:2560378",
        "tgn:1000001",
        "tgn:7012149",
        "tgn:2001461",
        "tgn:7007568",
        "tgn:7029392"
    ],
    "tgn:id":2560378,
    "tgn:name":"Orchard Point",
    "tgn:placetype":[
        "aat:300008850"
    ]
},
  "bbox": [],
  "geometry": {"coordinates":[-73.4333,44.0167],"type":"Point"}
}