{
  "id": 7585012,
  "type": "Feature",
  "properties": {
    "tgn:hierarchy":[
        "tgn:7585012",
        "tgn:1000004",
        "tgn:7000198",
        "tgn:1001894",
        "tgn:7029392"
    ],
    "tgn:id":7585012,
    "tgn:name:en":"Bakwara",
    "tgn:placetype":[
        "aat:300008347"
    ]
},
  "bbox": [],
  "geometry": {"coordinates":[78.017822,24.018166],"type":"Point"}
}