{
  "id": 7517677,
  "type": "Feature",
  "properties": {
    "tgn:hierarchy":[
        "tgn:7517677",
        "tgn:1009227",
        "tgn:1000226",
        "tgn:7016822",
        "tgn:1000006",
        "tgn:7029392"
    ],
    "tgn:id":7517677,
    "tgn:name:en":"Knoll, The",
    "tgn:placetype":[
        "aat:300008798"
    ]
},
  "bbox": [],
  "geometry": {"coordinates":[168.183333,-44.35],"type":"Point"}
}