{
  "id": 2642989,
  "type": "Feature",
  "properties": {
    "tgn:hierarchy":[
        "tgn:2642989",
        "tgn:1000001",
        "tgn:7012149",
        "tgn:2002248",
        "tgn:7007920",
        "tgn:7029392"
    ],
    "tgn:id":2642989,
    "tgn:name":"Sandwich Creek",
    "tgn:placetype":[
        "aat:300008706"
    ]
},
  "bbox": [],
  "geometry": {"coordinates":[-117.1667,48.3333],"type":"Point"}
}