{
  "id": 7512826,
  "type": "Feature",
  "properties": {
    "tgn:hierarchy":[
        "tgn:7512826",
        "tgn:1008380",
        "tgn:7000507",
        "tgn:1000226",
        "tgn:1000006",
        "tgn:7029392"
    ],
    "tgn:id":7512826,
    "tgn:name:en":"Helena Bay",
    "tgn:placetype":[
        "aat:300132316"
    ]
},
  "bbox": [],
  "geometry": {"coordinates":[174.383333,-35.416667],"type":"Point"}
}