<<<<<<< HEAD
{
  "id": 2402952,
  "type": "Feature",
  "properties": {
    "tgn:hierarchy":[
        "tgn:2402952",
        "tgn:1000001",
        "tgn:2001938",
        "tgn:7012149",
        "tgn:7007826",
        "tgn:7029392"
    ],
    "tgn:id":2402952,
    "tgn:name":"Hough Creek",
    "tgn:placetype":[
        "aat:300008706"
    ]
},
  "bbox": [],
  "geometry": {"coordinates":[-99.3,29.8167],"type":"Point"}
}
=======
{"geometry":{"type":"Point","coordinates":[-99.300000,29.816700]},"type":"Feature","properties":{"hierarchy":["tgn:2402952","tgn:1000001","tgn:2001938","tgn:7012149","tgn:7007826","tgn:7029392"],"placetype":["aat:300008706"],"id":2402952,"name:xx":"Hough Creek"}}
>>>>>>> 03f74aca74312dbeaf24d7e61306dd6a786dc3d0
