{
  "id": 2459793,
  "type": "Feature",
  "properties": {
    "tgn:hierarchy":[
        "tgn:2459793",
        "tgn:1000001",
        "tgn:7012149",
        "tgn:7007157",
        "tgn:2000191",
        "tgn:7029392"
    ],
    "tgn:id":2459793,
    "tgn:name":"Little Ripstein Gulch",
    "tgn:placetype":[
        "aat:300008761"
    ]
},
  "bbox": [],
  "geometry": {"coordinates":[-123.05,40.8667],"type":"Point"}
}