{
  "id": 2208333,
  "type": "Feature",
  "properties": {
    "tgn:hierarchy":[
        "tgn:2208333",
        "tgn:7002659",
        "tgn:1000001",
        "tgn:7012149",
        "tgn:7029392"
    ],
    "tgn:id":2208333,
    "tgn:name":"Burnam Branch",
    "tgn:placetype":[
        "aat:300008699"
    ]
},
  "bbox": [],
  "geometry": {"coordinates":[-88.1333,32.3167],"type":"Point"}
}