{
  "id": 1035523,
  "type": "Feature",
  "properties": {
    "tgn:hierarchy":[
        "tgn:1035523",
        "tgn:1000003",
        "tgn:1000070",
        "tgn:7002897",
        "tgn:7029392"
    ],
    "tgn:id":1035523,
    "tgn:name":"Saint-Romans",
    "tgn:placetype":[
        "aat:300008347"
    ]
},
  "bbox": [],
  "geometry": {"coordinates":[5.3333,45.1167],"type":"Point"}
}