{
  "id": 7260825,
  "type": "Feature",
  "properties": {
    "tgn:hierarchy":[
        "tgn:7260825",
        "tgn:1000003",
        "tgn:7003622",
        "tgn:7016845",
        "tgn:7029392"
    ],
    "tgn:id":7260825,
    "tgn:name:nl":"De Molt",
    "tgn:placetype":[
        "aat:300008187"
    ]
},
  "bbox": [],
  "geometry": {"coordinates":[5.883333,50.783333],"type":"Point"}
}