{
  "id": 2190733,
  "type": "Feature",
  "properties": {
    "tgn:hierarchy":[
        "tgn:2190733",
        "tgn:1000001",
        "tgn:7012149",
        "tgn:2000847",
        "tgn:7007255",
        "tgn:7029392"
    ],
    "tgn:id":2190733,
    "tgn:name":"Boxville",
    "tgn:placetype":[
        "aat:300008347"
    ]
},
  "bbox": [],
  "geometry": {"coordinates":[-87.8167,37.6167],"type":"Point"}
}