{
  "id": 2312599,
  "type": "Feature",
  "properties": {
    "tgn:hierarchy":[
        "tgn:2312599",
        "tgn:1000001",
        "tgn:1003028",
        "tgn:7012149",
        "tgn:7007159",
        "tgn:7029392"
    ],
    "tgn:id":2312599,
    "tgn:name":"Ekonk Brook",
    "tgn:placetype":[
        "aat:300008699"
    ]
},
  "bbox": [],
  "geometry": {"coordinates":[-71.85,41.65],"type":"Point"}
}