{
  "id": 2366664,
  "type": "Feature",
  "properties": {
    "tgn:hierarchy":[
        "tgn:2366664",
        "tgn:1000001",
        "tgn:7012149",
        "tgn:1002382",
        "tgn:7007255",
        "tgn:7029392"
    ],
    "tgn:id":2366664,
    "tgn:name":"Grindstone Creek",
    "tgn:placetype":[
        "aat:300008706"
    ]
},
  "bbox": [],
  "geometry": {"coordinates":[-84.85,38.2333],"type":"Point"}
}