{
  "id": 7396675,
  "type": "Feature",
  "properties": {
    "tgn:hierarchy":[
        "tgn:7396675",
        "tgn:1001835",
        "tgn:1000001",
        "tgn:7005560",
        "tgn:7029392"
    ],
    "tgn:id":7396675,
    "tgn:name":"San Miguel",
    "tgn:placetype":[
        "aat:300008347"
    ]
},
  "bbox": [],
  "geometry": {"coordinates":[-113.783333,28.55],"type":"Point"}
}