{
  "id": 7377999,
  "type": "Feature",
  "properties": {
    "tgn:hierarchy":[
        "tgn:7377999",
        "tgn:7005583",
        "tgn:1000001",
        "tgn:7005560",
        "tgn:7029392"
    ],
    "tgn:id":7377999,
    "tgn:name":"La Portilla",
    "tgn:placetype":[
        "aat:300008347"
    ]
},
  "bbox": [],
  "geometry": {"coordinates":[-106.433333,25.066667],"type":"Point"}
}