<<<<<<< HEAD
{
  "id": 7377999,
  "type": "Feature",
  "properties": {
    "tgn:hierarchy":[
        "tgn:7377999",
        "tgn:7005583",
        "tgn:1000001",
        "tgn:7005560",
        "tgn:7029392"
    ],
    "tgn:id":7377999,
    "tgn:name":"La Portilla",
    "tgn:placetype":[
        "aat:300008347"
    ]
},
  "bbox": [],
  "geometry": {"coordinates":[-106.433333,25.066667],"type":"Point"}
}
=======
{"geometry":{"type":"Point","coordinates":[-106.433333,25.066667]},"type":"Feature","properties":{"hierarchy":["tgn:7377999","tgn:7005583","tgn:1000001","tgn:7005560","tgn:7029392"],"placetype":["aat:300008347"],"id":7377999,"name:xx":"La Portilla"}}
>>>>>>> 03f74aca74312dbeaf24d7e61306dd6a786dc3d0
