{
  "id": 1031280,
  "type": "Feature",
  "properties": {
    "tgn:hierarchy":[
        "tgn:1031280",
        "tgn:7024077",
        "tgn:1000003",
        "tgn:1000069",
        "tgn:7029392"
    ],
    "tgn:id":1031280,
    "tgn:name":"Friitala",
    "tgn:placetype":[
        "aat:300008347"
    ]
},
  "bbox": [],
  "geometry": {"coordinates":[21.8667,61.4333],"type":"Point"}
}