{
  "id": 7562340,
  "type": "Feature",
  "properties": {
    "tgn:hierarchy":[
        "tgn:7562340",
        "tgn:1000004",
        "tgn:7000198",
        "tgn:1001894",
        "tgn:7029392"
    ],
    "tgn:id":7562340,
    "tgn:name:en":"Dongarpura",
    "tgn:placetype":[
        "aat:300008347"
    ]
},
  "bbox": [],
  "geometry": {"coordinates":[79.056104,26.437452],"type":"Point"}
}