{
  "id": 7470507,
  "type": "Feature",
  "properties": {
    "tgn:hierarchy":[
        "tgn:7470507",
        "tgn:1000004",
        "tgn:7490934",
        "tgn:1000141",
        "tgn:7029392"
    ],
    "tgn:id":7470507,
    "tgn:name":"Touqianxi",
    "tgn:placetype":[
        "aat:300008347"
    ]
},
  "bbox": [],
  "geometry": {"coordinates":[120.474167,23.381667],"type":"Point"}
}