{
  "id": 7038026,
  "type": "Feature",
  "properties": {
    "tgn:hierarchy":[
        "tgn:7038026",
        "tgn:1001724",
        "tgn:1000003",
        "tgn:7003121",
        "tgn:1000080",
        "tgn:7029392"
    ],
    "tgn:id":7038026,
    "tgn:name":"Tanaunella",
    "tgn:placetype":[
        "aat:300008347"
    ]
},
  "bbox": [],
  "geometry": {"coordinates":[9.716667,40.683333],"type":"Point"}
}