{
  "id": 7082018,
  "type": "Feature",
  "properties": {
    "tgn:hierarchy":[
        "tgn:7082018",
        "tgn:7003692",
        "tgn:1000003",
        "tgn:7000084",
        "tgn:7029392"
    ],
    "tgn:id":7082018,
    "tgn:name":"Wieshof",
    "tgn:placetype":[
        "aat:300000206"
    ]
},
  "bbox": [],
  "geometry": {"coordinates":[8.916667,47.683333],"type":"Point"}
}