{
  "id": 7051928,
  "type": "Feature",
  "properties": {
    "tgn:hierarchy":[
        "tgn:7051928",
        "tgn:7003164",
        "tgn:1000003",
        "tgn:7009760",
        "tgn:1000080",
        "tgn:7029392"
    ],
    "tgn:id":7051928,
    "tgn:name":"Pero, Capo",
    "tgn:placetype":[
        "aat:300386846"
    ]
},
  "bbox": [],
  "geometry": {"coordinates":[10.433333,42.85],"type":"Point"}
}