<<<<<<< HEAD
{
  "id": 7051928,
  "type": "Feature",
  "properties": {
    "tgn:hierarchy":[
        "tgn:7051928",
        "tgn:7003164",
        "tgn:1000003",
        "tgn:7009760",
        "tgn:1000080",
        "tgn:7029392"
    ],
    "tgn:id":7051928,
    "tgn:name":"Pero, Capo",
    "tgn:placetype":[
        "aat:300386846"
    ]
},
  "bbox": [],
  "geometry": {"coordinates":[10.433333,42.85],"type":"Point"}
}
=======
{"geometry":{"type":"Point","coordinates":[10.433333,42.850000]},"type":"Feature","properties":{"hierarchy":["tgn:7051928","tgn:7003164","tgn:1000003","tgn:7009760","tgn:1000080","tgn:7029392"],"placetype":["aat:300386846"],"id":7051928,"name:xx":"Pero, Capo"}}
>>>>>>> 03f74aca74312dbeaf24d7e61306dd6a786dc3d0
