<<<<<<< HEAD
{
  "id": 7055964,
  "type": "Feature",
  "properties": {
    "tgn:hierarchy":[
        "tgn:7055964",
        "tgn:1003460",
        "tgn:1000003",
        "tgn:7009760",
        "tgn:1000080",
        "tgn:7029392"
    ],
    "tgn:id":7055964,
    "tgn:name":"Ombrone, Bocca d'",
    "tgn:placetype":[
        "aat:300387057"
    ]
},
  "bbox": [],
  "geometry": {"coordinates":[11.0,42.65],"type":"Point"}
}
=======
{"geometry":{"type":"Point","coordinates":[11.000000,42.650000]},"type":"Feature","properties":{"hierarchy":["tgn:7055964","tgn:1003460","tgn:1000003","tgn:7009760","tgn:1000080","tgn:7029392"],"placetype":["aat:300387057"],"id":7055964,"name:xx":"Ombrone, Bocca d'"}}
>>>>>>> 03f74aca74312dbeaf24d7e61306dd6a786dc3d0
