<<<<<<< HEAD
{
  "id": 2403236,
  "type": "Feature",
  "properties": {
    "tgn:hierarchy":[
        "tgn:2403236",
        "tgn:1000001",
        "tgn:7012149",
        "tgn:2001541",
        "tgn:7007709",
        "tgn:7029392"
    ],
    "tgn:id":2403236,
    "tgn:name":"House Rock",
    "tgn:placetype":[
        "aat:300008798"
    ]
},
  "bbox": [],
  "geometry": {"coordinates":[-80.2667,36.3667],"type":"Point"}
}
=======
{"geometry":{"type":"Point","coordinates":[-80.266700,36.366700]},"type":"Feature","properties":{"hierarchy":["tgn:2403236","tgn:1000001","tgn:7012149","tgn:2001541","tgn:7007709","tgn:7029392"],"placetype":["aat:300008798"],"id":2403236,"name:xx":"House Rock"}}
>>>>>>> 03f74aca74312dbeaf24d7e61306dd6a786dc3d0
