<<<<<<< HEAD
{
  "id": 2256717,
  "type": "Feature",
  "properties": {
    "tgn:hierarchy":[
        "tgn:2256717",
        "tgn:1000001",
        "tgn:7012149",
        "tgn:2002265",
        "tgn:7013961",
        "tgn:7029392"
    ],
    "tgn:id":2256717,
    "tgn:name":"Corduroy Hollow",
    "tgn:placetype":[
        "aat:300008761"
    ]
},
  "bbox": [],
  "geometry": {"coordinates":[-78.6833,39.5],"type":"Point"}
}
=======
{"geometry":{"type":"Point","coordinates":[-78.683300,39.500000]},"type":"Feature","properties":{"hierarchy":["tgn:2256717","tgn:1000001","tgn:7012149","tgn:2002265","tgn:7013961","tgn:7029392"],"placetype":["aat:300008761"],"id":2256717,"name:xx":"Corduroy Hollow"}}
>>>>>>> 03f74aca74312dbeaf24d7e61306dd6a786dc3d0
