{
  "id": 7317736,
  "type": "Feature",
  "properties": {
    "tgn:hierarchy":[
        "tgn:7317736",
        "tgn:1001702",
        "tgn:1000049",
        "tgn:1000002",
        "tgn:7029392"
    ],
    "tgn:id":7317736,
    "tgn:name":"Clarke, Punta",
    "tgn:placetype":[
        "aat:300386846"
    ]
},
  "bbox": [],
  "geometry": {"coordinates":[-74.383333,-49.183333],"type":"Point"}
}