{
  "id": 2735979,
  "type": "Feature",
  "properties": {
    "tgn:hierarchy":[
        "tgn:2735979",
        "tgn:1000001",
        "tgn:7012149",
        "tgn:2001300",
        "tgn:7007524",
        "tgn:7029392"
    ],
    "tgn:id":2735979,
    "tgn:name":"Twin Lakes",
    "tgn:placetype":[
        "aat:300008680"
    ]
},
  "bbox": [],
  "geometry": {"coordinates":[-114.4833,46.15],"type":"Point"}
}