<<<<<<< HEAD
{
  "id": 2761462,
  "type": "Feature",
  "properties": {
    "tgn:hierarchy":[
        "tgn:2761462",
        "tgn:1000001",
        "tgn:7012149",
        "tgn:1002924",
        "tgn:7007568",
        "tgn:7029392"
    ],
    "tgn:id":2761462,
    "tgn:name":"West Neck",
    "tgn:placetype":[
        "aat:300008850"
    ]
},
  "bbox": [],
  "geometry": {"coordinates":[-73.45,40.9],"type":"Point"}
}
=======
{"geometry":{"type":"Point","coordinates":[-73.450000,40.900000]},"type":"Feature","properties":{"hierarchy":["tgn:2761462","tgn:1000001","tgn:7012149","tgn:1002924","tgn:7007568","tgn:7029392"],"placetype":["aat:300008850"],"id":2761462,"name:xx":"West Neck"}}
>>>>>>> 03f74aca74312dbeaf24d7e61306dd6a786dc3d0
