{
  "id": 2327163,
  "type": "Feature",
  "properties": {
    "tgn:hierarchy":[
        "tgn:2327163",
        "tgn:1000001",
        "tgn:2000459",
        "tgn:7012149",
        "tgn:7007250",
        "tgn:7029392"
    ],
    "tgn:id":2327163,
    "tgn:name":"First Creek",
    "tgn:placetype":[
        "aat:300008706"
    ]
},
  "bbox": [],
  "geometry": {"coordinates":[-115.5833,43.8167],"type":"Point"}
}