{
  "id": 2071295,
  "type": "Feature",
  "properties": {
    "tgn:hierarchy":[
        "tgn:2071295",
        "tgn:1000001",
        "tgn:7012149",
        "tgn:1002993",
        "tgn:7007568",
        "tgn:7029392"
    ],
    "tgn:id":2071295,
    "tgn:name":"North Granville",
    "tgn:placetype":[
        "aat:300008347"
    ]
},
  "bbox": [],
  "geometry": {"coordinates":[-73.3333,43.45],"type":"Point"}
}