{
  "id": 7511100,
  "type": "Feature",
  "properties": {
    "tgn:hierarchy":[
        "tgn:7511100",
        "tgn:1009227",
        "tgn:1000226",
        "tgn:7016822",
        "tgn:1000006",
        "tgn:7029392"
    ],
    "tgn:id":7511100,
    "tgn:name:en":"Taruwhenua",
    "tgn:placetype":[
        "aat:300386846"
    ]
},
  "bbox": [],
  "geometry": {"coordinates":[-176.266667,-44.233333],"type":"Point"}
}