{
  "id": 1140981,
  "type": "Feature",
  "properties": {
    "tgn:hierarchy":[
        "tgn:1140981",
        "tgn:7000490",
        "tgn:1000006",
        "tgn:7006238",
        "tgn:7029392"
    ],
    "tgn:id":1140981,
    "tgn:name":"Hopetoun",
    "tgn:placetype":[
        "aat:300008347"
    ]
},
  "bbox": [],
  "geometry": {"coordinates":[142.3333,-35.7167],"type":"Point"}
}