{
  "id": 1033801,
  "type": "Feature",
  "properties": {
    "tgn:hierarchy":[
        "tgn:1033801",
        "tgn:1000003",
        "tgn:7002885",
        "tgn:1000070",
        "tgn:7029392"
    ],
    "tgn:id":1033801,
    "tgn:name":"Lasalle",
    "tgn:placetype":[
        "aat:300008347"
    ]
},
  "bbox": [],
  "geometry": {"coordinates":[3.85,44.05],"type":"Point"}
}