<<<<<<< HEAD
{
  "id": 2339603,
  "type": "Feature",
  "properties": {
    "tgn:hierarchy":[
        "tgn:2339603",
        "tgn:1000001",
        "tgn:7012149",
        "tgn:1002913",
        "tgn:7007919",
        "tgn:7029392"
    ],
    "tgn:id":2339603,
    "tgn:name":"Fredericksburg Bar",
    "tgn:placetype":[
        "aat:300132348"
    ]
},
  "bbox": [],
  "geometry": {"coordinates":[-77.45,38.2833],"type":"Point"}
}
=======
{"geometry":{"type":"Point","coordinates":[-77.450000,38.283300]},"type":"Feature","properties":{"hierarchy":["tgn:2339603","tgn:1000001","tgn:7012149","tgn:1002913","tgn:7007919","tgn:7029392"],"placetype":["aat:300132348"],"id":2339603,"name:xx":"Fredericksburg Bar"}}
>>>>>>> 03f74aca74312dbeaf24d7e61306dd6a786dc3d0
