{
  "id": 2539415,
  "type": "Feature",
  "properties": {
    "tgn:hierarchy":[
        "tgn:2539415",
        "tgn:1000001",
        "tgn:7012149",
        "tgn:2002329",
        "tgn:7007922",
        "tgn:7029392"
    ],
    "tgn:id":2539415,
    "tgn:name":"New Lisbon Lake",
    "tgn:placetype":[
        "aat:300006191"
    ]
},
  "bbox": [],
  "geometry": {"coordinates":[-90.15,43.8833],"type":"Point"}
}