{
  "id": 1140717,
  "type": "Feature",
  "properties": {
    "tgn:hierarchy":[
        "tgn:1140717",
        "tgn:1000004",
        "tgn:1001540",
        "tgn:1000135",
        "tgn:7029392"
    ],
    "tgn:id":1140717,
    "tgn:name":"Bulan",
    "tgn:placetype":[
        "aat:300008347"
    ]
},
  "bbox": [],
  "geometry": {"coordinates":[123.8833,12.6667],"type":"Point"}
}