<<<<<<< HEAD
{
  "id": 2252570,
  "type": "Feature",
  "properties": {
    "tgn:hierarchy":[
        "tgn:2252570",
        "tgn:1000001",
        "tgn:2001704",
        "tgn:7012149",
        "tgn:7007708",
        "tgn:7029392"
    ],
    "tgn:id":2252570,
    "tgn:name":"Conn Creek",
    "tgn:placetype":[
        "aat:300008706"
    ]
},
  "bbox": [],
  "geometry": {"coordinates":[-124.3667,42.3833],"type":"Point"}
}
=======
{"geometry":{"type":"Point","coordinates":[-124.366700,42.383300]},"type":"Feature","properties":{"hierarchy":["tgn:2252570","tgn:1000001","tgn:2001704","tgn:7012149","tgn:7007708","tgn:7029392"],"placetype":["aat:300008706"],"id":2252570,"name:xx":"Conn Creek"}}
>>>>>>> 03f74aca74312dbeaf24d7e61306dd6a786dc3d0
