{
  "id": 2252570,
  "type": "Feature",
  "properties": {
    "tgn:hierarchy":[
        "tgn:2252570",
        "tgn:1000001",
        "tgn:2001704",
        "tgn:7012149",
        "tgn:7007708",
        "tgn:7029392"
    ],
    "tgn:id":2252570,
    "tgn:name":"Conn Creek",
    "tgn:placetype":[
        "aat:300008706"
    ]
},
  "bbox": [],
  "geometry": {"coordinates":[-124.3667,42.3833],"type":"Point"}
}