{
  "id": 2619848,
  "type": "Feature",
  "properties": {
    "tgn:hierarchy":[
        "tgn:2619848",
        "tgn:1000001",
        "tgn:7012149",
        "tgn:7007157",
        "tgn:1002608",
        "tgn:7029392"
    ],
    "tgn:id":2619848,
    "tgn:name":"Rio Hondo",
    "tgn:placetype":[
        "aat:300008699"
    ]
},
  "bbox": [],
  "geometry": {"coordinates":[-118.0167,34.0833],"type":"Point"}
}