{
  "id": 7527872,
  "type": "Feature",
  "properties": {
    "tgn:hierarchy":[
        "tgn:7527872",
        "tgn:7001242",
        "tgn:7016833",
        "tgn:7001336",
        "tgn:7029392"
    ],
    "tgn:id":7527872,
    "tgn:name:en":"Umm Barqah, Jabal",
    "tgn:placetype":[
        "aat:300008795"
    ]
},
  "bbox": [],
  "geometry": {"coordinates":[34.368189,28.137198],"type":"Point"}
}