{
  "id": 2211136,
  "type": "Feature",
  "properties": {
    "tgn:hierarchy":[
        "tgn:2211136",
        "tgn:1000001",
        "tgn:7012149",
        "tgn:1002986",
        "tgn:7007568",
        "tgn:7029392"
    ],
    "tgn:id":2211136,
    "tgn:name":"Butler Storage Reservoir",
    "tgn:placetype":[
        "aat:300006191"
    ]
},
  "bbox": [],
  "geometry": {"coordinates":[-73.7167,43.35],"type":"Point"}
}