{
  "id": 2397665,
  "type": "Feature",
  "properties": {
    "tgn:hierarchy":[
        "tgn:2397665",
        "tgn:1000001",
        "tgn:2001014",
        "tgn:7012149",
        "tgn:7007521",
        "tgn:7029392"
    ],
    "tgn:id":2397665,
    "tgn:name":"Honeymoon Mountain",
    "tgn:placetype":[
        "aat:300008798"
    ]
},
  "bbox": [],
  "geometry": {"coordinates":[-90.8167,47.7167],"type":"Point"}
}