{
  "id": 7234236,
  "type": "Feature",
  "properties": {
    "tgn:hierarchy":[
        "tgn:7234236",
        "tgn:7011161",
        "tgn:7002674",
        "tgn:1000003",
        "tgn:1000074",
        "tgn:7029392"
    ],
    "tgn:id":7234236,
    "tgn:name":"Avg\u00f3nyma",
    "tgn:placetype":[
        "aat:300008347"
    ]
},
  "bbox": [],
  "geometry": {"coordinates":[26.019444,38.376667],"type":"Point"}
}