{
  "id": 2609424,
  "type": "Feature",
  "properties": {
    "tgn:hierarchy":[
        "tgn:2609424",
        "tgn:1000001",
        "tgn:7012149",
        "tgn:2002067",
        "tgn:7007826",
        "tgn:7029392"
    ],
    "tgn:id":2609424,
    "tgn:name":"Rayburn Branch",
    "tgn:placetype":[
        "aat:300008699"
    ]
},
  "bbox": [],
  "geometry": {"coordinates":[-94.25,31.2333],"type":"Point"}
}