{
  "id": 2446503,
  "type": "Feature",
  "properties": {
    "tgn:hierarchy":[
        "tgn:2446503",
        "tgn:2002365",
        "tgn:1000001",
        "tgn:7012149",
        "tgn:7007923",
        "tgn:7029392"
    ],
    "tgn:id":2446503,
    "tgn:name":"Lewis Lake",
    "tgn:placetype":[
        "aat:300008680"
    ]
},
  "bbox": [],
  "geometry": {"coordinates":[-106.2833,41.35],"type":"Point"}
}