{
  "id": 2553859,
  "type": "Feature",
  "properties": {
    "tgn:hierarchy":[
        "tgn:2553859",
        "tgn:1000001",
        "tgn:7012149",
        "tgn:7007713",
        "tgn:7029392"
    ],
    "tgn:id":2553859,
    "tgn:name":"Oak Hollow",
    "tgn:placetype":[
        "aat:300008761"
    ]
},
  "bbox": [],
  "geometry": {"coordinates":[-98.0667,43.1667],"type":"Point"}
}