{
  "id": 7473450,
  "type": "Feature",
  "properties": {
    "tgn:hierarchy":[
        "tgn:7473450",
        "tgn:1000957",
        "tgn:1000004",
        "tgn:1000141",
        "tgn:7029392"
    ],
    "tgn:id":7473450,
    "tgn:name":"Tongpan Yu",
    "tgn:placetype":[
        "aat:300008791"
    ]
},
  "bbox": [],
  "geometry": {"coordinates":[121.758249,25.1597],"type":"Point"}
}