{
  "id": 1092421,
  "type": "Feature",
  "properties": {
    "tgn:hierarchy":[
        "tgn:1092421",
        "tgn:7001242",
        "tgn:1001423",
        "tgn:1000185",
        "tgn:7029392"
    ],
    "tgn:id":1092421,
    "tgn:name":"Mazunga",
    "tgn:placetype":[
        "aat:300008347"
    ]
},
  "bbox": [],
  "geometry": {"coordinates":[29.8667,-21.75],"type":"Point"}
}