<<<<<<< HEAD
{
  "id": 2252220,
  "type": "Feature",
  "properties": {
    "tgn:hierarchy":[
        "tgn:2252220",
        "tgn:1000001",
        "tgn:7012149",
        "tgn:7007710",
        "tgn:7029392"
    ],
    "tgn:id":2252220,
    "tgn:name":"Conemaugh Gorge",
    "tgn:placetype":[
        "aat:300008761"
    ]
},
  "bbox": [],
  "geometry": {"coordinates":[-78.95,40.35],"type":"Point"}
}
=======
{"geometry":{"type":"Point","coordinates":[-78.950000,40.350000]},"type":"Feature","properties":{"hierarchy":["tgn:2252220","tgn:1000001","tgn:7012149","tgn:7007710","tgn:7029392"],"placetype":["aat:300008761"],"id":2252220,"name:xx":"Conemaugh Gorge"}}
>>>>>>> 03f74aca74312dbeaf24d7e61306dd6a786dc3d0
