{
  "id": 7066283,
  "type": "Feature",
  "properties": {
    "tgn:hierarchy":[
        "tgn:7066283",
        "tgn:1000003",
        "tgn:7003688",
        "tgn:7000084",
        "tgn:7029392"
    ],
    "tgn:id":7066283,
    "tgn:name":"\u00dclvesb\u00fcllerkoog",
    "tgn:placetype":[
        "aat:300006163"
    ]
},
  "bbox": [],
  "geometry": {"coordinates":[8.916667,54.416667],"type":"Point"}
}