{
  "id": 7447191,
  "type": "Feature",
  "properties": {
    "tgn:hierarchy":[
        "tgn:7447191",
        "tgn:7002445",
        "tgn:1000003",
        "tgn:7008178",
        "tgn:7008591",
        "tgn:7029392"
    ],
    "tgn:id":7447191,
    "tgn:name:en":"Ratley",
    "tgn:placetype":[
        "aat:300008347"
    ]
},
  "bbox": [],
  "geometry": {"coordinates":[-1.433333,52.116667],"type":"Point"}
}