{
  "id": 2726630,
  "type": "Feature",
  "properties": {
    "tgn:hierarchy":[
        "tgn:2726630",
        "tgn:1000001",
        "tgn:1002209",
        "tgn:7012149",
        "tgn:7007252",
        "tgn:7029392"
    ],
    "tgn:id":2726630,
    "tgn:name":"Town Hill",
    "tgn:placetype":[
        "aat:300008347"
    ]
},
  "bbox": [],
  "geometry": {"coordinates":[-86.2333,39.1833],"type":"Point"}
}