{
  "id": 2269802,
  "type": "Feature",
  "properties": {
    "tgn:hierarchy":[
        "tgn:2269802",
        "tgn:1000001",
        "tgn:7012149",
        "tgn:7007524",
        "tgn:7029392"
    ],
    "tgn:id":2269802,
    "tgn:name":"Crows Nest Creek",
    "tgn:placetype":[
        "aat:300008706"
    ]
},
  "bbox": [],
  "geometry": {"coordinates":[-112.1333,44.85],"type":"Point"}
}