<<<<<<< HEAD
{
  "id": 2157639,
  "type": "Feature",
  "properties": {
    "tgn:hierarchy":[
        "tgn:2157639",
        "tgn:1000001",
        "tgn:7012149",
        "tgn:2001711",
        "tgn:7007708",
        "tgn:7029392"
    ],
    "tgn:id":2157639,
    "tgn:name":"Beaver Dam Creek",
    "tgn:placetype":[
        "aat:300008706"
    ]
},
  "bbox": [],
  "geometry": {"coordinates":[-122.45,42.6],"type":"Point"}
}
=======
{"geometry":{"type":"Point","coordinates":[-122.450000,42.600000]},"type":"Feature","properties":{"hierarchy":["tgn:2157639","tgn:1000001","tgn:7012149","tgn:2001711","tgn:7007708","tgn:7029392"],"placetype":["aat:300008706"],"id":2157639,"name:xx":"Beaver Dam Creek"}}
>>>>>>> 03f74aca74312dbeaf24d7e61306dd6a786dc3d0
