{
  "id": 2695546,
  "type": "Feature",
  "properties": {
    "tgn:hierarchy":[
        "tgn:2695546",
        "tgn:1000001",
        "tgn:7020680",
        "tgn:7012149",
        "tgn:7007256",
        "tgn:7029392"
    ],
    "tgn:id":2695546,
    "tgn:name":"Stinkfinger Creek",
    "tgn:placetype":[
        "aat:300008706"
    ]
},
  "bbox": [],
  "geometry": {"coordinates":[-93.5667,31.8667],"type":"Point"}
}