{
  "id": 2231669,
  "type": "Feature",
  "properties": {
    "tgn:hierarchy":[
        "tgn:2231669",
        "tgn:1002169",
        "tgn:1000001",
        "tgn:7012149",
        "tgn:7007255",
        "tgn:7029392"
    ],
    "tgn:id":2231669,
    "tgn:name":"Chalybeate Branch",
    "tgn:placetype":[
        "aat:300008699"
    ]
},
  "bbox": [],
  "geometry": {"coordinates":[-83.6667,38.0667],"type":"Point"}
}