{
  "id": 2312575,
  "type": "Feature",
  "properties": {
    "tgn:hierarchy":[
        "tgn:2312575",
        "tgn:7006450",
        "tgn:1000001",
        "tgn:7012149",
        "tgn:2000087",
        "tgn:7029392"
    ],
    "tgn:id":2312575,
    "tgn:name":"Ekashluak Creek",
    "tgn:placetype":[
        "aat:300008706"
    ]
},
  "bbox": [],
  "geometry": {"coordinates":[-165.9167,61.7667],"type":"Point"}
}