{
  "id": 2643356,
  "type": "Feature",
  "properties": {
    "tgn:hierarchy":[
        "tgn:2643356",
        "tgn:1000001",
        "tgn:7012149",
        "tgn:2000964",
        "tgn:7007520",
        "tgn:7029392"
    ],
    "tgn:id":2643356,
    "tgn:name":"Sandy Drain",
    "tgn:placetype":[
        "aat:300006075"
    ]
},
  "bbox": [],
  "geometry": {"coordinates":[-83.0667,43.7333],"type":"Point"}
}