{
  "id": 2082871,
  "type": "Feature",
  "properties": {
    "tgn:hierarchy":[
        "tgn:2082871",
        "tgn:1000001",
        "tgn:2001629",
        "tgn:7012149",
        "tgn:7007707",
        "tgn:7029392"
    ],
    "tgn:id":2082871,
    "tgn:name":"Blue",
    "tgn:placetype":[
        "aat:300008347"
    ]
},
  "bbox": [],
  "geometry": {"coordinates":[-96.2167,33.9833],"type":"Point"}
}