{
  "id": 7582277,
  "type": "Feature",
  "properties": {
    "tgn:hierarchy":[
        "tgn:7582277",
        "tgn:1000004",
        "tgn:7000198",
        "tgn:7016883",
        "tgn:7029392"
    ],
    "tgn:id":7582277,
    "tgn:name:en":"M\u012brpur",
    "tgn:placetype":[
        "aat:300008347"
    ]
},
  "bbox": [],
  "geometry": {"coordinates":[76.852105,30.611793],"type":"Point"}
}