{
  "id": 7562535,
  "type": "Feature",
  "properties": {
    "tgn:hierarchy":[
        "tgn:7562535",
        "tgn:1000004",
        "tgn:7000198",
        "tgn:1001894",
        "tgn:7029392"
    ],
    "tgn:id":7562535,
    "tgn:name:en":"Rajpura",
    "tgn:placetype":[
        "aat:300008347"
    ]
},
  "bbox": [],
  "geometry": {"coordinates":[79.040741,26.309392],"type":"Point"}
}