{
  "id": 7382498,
  "type": "Feature",
  "properties": {
    "tgn:hierarchy":[
        "tgn:7382498",
        "tgn:1000001",
        "tgn:1001960",
        "tgn:7005560",
        "tgn:7029392"
    ],
    "tgn:id":7382498,
    "tgn:name":"Noria de El\u00edas",
    "tgn:placetype":[
        "aat:300008347"
    ]
},
  "bbox": [],
  "geometry": {"coordinates":[-109.983333,28.733333],"type":"Point"}
}