{
  "id": 2183417,
  "type": "Feature",
  "properties": {
    "tgn:hierarchy":[
        "tgn:2183417",
        "tgn:1000001",
        "tgn:7012149",
        "tgn:7007568",
        "tgn:7029392"
    ],
    "tgn:id":2183417,
    "tgn:name":"Bluff Head",
    "tgn:placetype":[
        "aat:300008850"
    ]
},
  "bbox": [],
  "geometry": {"coordinates":[-73.4833,43.6667],"type":"Point"}
}