{
  "id": 2410240,
  "type": "Feature",
  "properties": {
    "tgn:hierarchy":[
        "tgn:2410240",
        "tgn:1000001",
        "tgn:7012149",
        "tgn:7007158",
        "tgn:2000247",
        "tgn:7029392"
    ],
    "tgn:id":2410240,
    "tgn:name":"Index, The",
    "tgn:placetype":[
        "aat:300008798"
    ]
},
  "bbox": [],
  "geometry": {"coordinates":[-107.6167,37.6333],"type":"Point"}
}