<<<<<<< HEAD
{
  "id": 7488093,
  "type": "Feature",
  "properties": {
    "tgn:hierarchy":[
        "tgn:7488093",
        "tgn:1000004",
        "tgn:7467799",
        "tgn:1000141",
        "tgn:7029392"
    ],
    "tgn:id":7488093,
    "tgn:name":"Guang'erxiang",
    "tgn:placetype":[
        "aat:300008347"
    ]
},
  "bbox": [],
  "geometry": {"coordinates":[120.544415,23.847325],"type":"Point"}
}
=======
{"geometry":{"type":"Point","coordinates":[120.544415,23.847325]},"type":"Feature","properties":{"hierarchy":["tgn:7488093","tgn:1000004","tgn:7467799","tgn:1000141","tgn:7029392"],"placetype":["aat:300008347"],"id":7488093,"name:xx":"Guang'erxiang"}}
>>>>>>> 03f74aca74312dbeaf24d7e61306dd6a786dc3d0
