{
  "id": 2740554,
  "type": "Feature",
  "properties": {
    "tgn:hierarchy":[
        "tgn:2740554",
        "tgn:1000001",
        "tgn:7012149",
        "tgn:7007157",
        "tgn:1002858",
        "tgn:7029392"
    ],
    "tgn:id":2740554,
    "tgn:name":"Upper Otay Lake",
    "tgn:placetype":[
        "aat:300006191"
    ]
},
  "bbox": [],
  "geometry": {"coordinates":[-116.9167,32.6333],"type":"Point"}
}