{
  "id": 7169571,
  "type": "Feature",
  "properties": {
    "tgn:hierarchy":[
        "tgn:7169571",
        "tgn:7003669",
        "tgn:1000003",
        "tgn:7000084",
        "tgn:7029392"
    ],
    "tgn:id":7169571,
    "tgn:name":"Heu Berg",
    "tgn:placetype":[
        "aat:300008795"
    ]
},
  "bbox": [],
  "geometry": {"coordinates":[11.616667,47.766667],"type":"Point"}
}