{
  "id": 7516470,
  "type": "Feature",
  "properties": {
    "tgn:hierarchy":[
        "tgn:7516470",
        "tgn:1009227",
        "tgn:1000226",
        "tgn:7016729",
        "tgn:1000006",
        "tgn:7029392"
    ],
    "tgn:id":7516470,
    "tgn:name:en":"Ohau Stream",
    "tgn:placetype":[
        "aat:300008699"
    ]
},
  "bbox": [],
  "geometry": {"coordinates":[173.833333,-42.25],"type":"Point"}
}