{
  "id": 7540711,
  "type": "Feature",
  "properties": {
    "tgn:hierarchy":[
        "tgn:7540711",
        "tgn:7001242",
        "tgn:7016833",
        "tgn:7001334",
        "tgn:7029392"
    ],
    "tgn:id":7540711,
    "tgn:name:en":"Shabb, Barq\u0101t ash",
    "tgn:placetype":[
        "aat:300008777"
    ]
},
  "bbox": [],
  "geometry": {"coordinates":[30.505201,22.298691],"type":"Point"}
}