{
  "id": 7304793,
  "type": "Feature",
  "properties": {
    "tgn:hierarchy":[
        "tgn:7304793",
        "tgn:1001439",
        "tgn:1000003",
        "tgn:7002797",
        "tgn:1000095",
        "tgn:7029392"
    ],
    "tgn:id":7304793,
    "tgn:name":"La Vereda",
    "tgn:placetype":[
        "aat:300008347"
    ]
},
  "bbox": [],
  "geometry": {"coordinates":[-0.966667,37.666667],"type":"Point"}
}