{
  "id": 1004967,
  "type": "Feature",
  "properties": {
    "tgn:hierarchy":[
        "tgn:1004967",
        "tgn:1001945",
        "tgn:1000047",
        "tgn:7002457",
        "tgn:1000002",
        "tgn:7017121",
        "tgn:7029392"
    ],
    "tgn:id":1004967,
    "tgn:name":"Liberdade",
    "tgn:placetype":[
        "aat:300000745"
    ]
},
  "bbox": [],
  "geometry": {"coordinates":[-46.6167,-23.5833],"type":"Point"}
}