<<<<<<< HEAD
{
  "id": 7356860,
  "type": "Feature",
  "properties": {
    "tgn:hierarchy":[
        "tgn:7356860",
        "tgn:1000001",
        "tgn:1001937",
        "tgn:7005560",
        "tgn:7029392"
    ],
    "tgn:id":7356860,
    "tgn:name":"Chacatal, Caleta",
    "tgn:placetype":[
        "aat:300132317"
    ]
},
  "bbox": [],
  "geometry": {"coordinates":[-87.216667,20.5],"type":"Point"}
}
=======
{"geometry":{"type":"Point","coordinates":[-87.216667,20.500000]},"type":"Feature","properties":{"hierarchy":["tgn:7356860","tgn:1000001","tgn:1001937","tgn:7005560","tgn:7029392"],"placetype":["aat:300132317"],"id":7356860,"name:xx":"Chacatal, Caleta"}}
>>>>>>> 03f74aca74312dbeaf24d7e61306dd6a786dc3d0
