{
  "id": 7280027,
  "type": "Feature",
  "properties": {
    "tgn:hierarchy":[
        "tgn:7280027",
        "tgn:1001699",
        "tgn:1000049",
        "tgn:1000002",
        "tgn:7029392"
    ],
    "tgn:id":7280027,
    "tgn:name":"Rahue, R\u00edo",
    "tgn:placetype":[
        "aat:300008699"
    ]
},
  "bbox": [],
  "geometry": {"coordinates":[-73.333333,-40.316667],"type":"Point"}
}