{
  "id": 7388655,
  "type": "Feature",
  "properties": {
    "tgn:hierarchy":[
        "tgn:7388655",
        "tgn:1000001",
        "tgn:7005593",
        "tgn:7005560",
        "tgn:7029392"
    ],
    "tgn:id":7388655,
    "tgn:name":"Punta del Sauz",
    "tgn:placetype":[
        "aat:300008347"
    ]
},
  "bbox": [],
  "geometry": {"coordinates":[-99.85,20.783333],"type":"Point"}
}