{
  "id": 1118561,
  "type": "Feature",
  "properties": {
    "tgn:hierarchy":[
        "tgn:1118561",
        "tgn:1000004",
        "tgn:7000198",
        "tgn:1001895",
        "tgn:1008931",
        "tgn:7029392"
    ],
    "tgn:id":1118561,
    "tgn:name:en":"Veh\u0101r Lake",
    "tgn:placetype":[
        "aat:300008680"
    ]
},
  "bbox": [],
  "geometry": {"coordinates":[72.916667,19.15],"type":"Point"}
}