<<<<<<< HEAD
{
  "id": 7377429,
  "type": "Feature",
  "properties": {
    "tgn:hierarchy":[
        "tgn:7377429",
        "tgn:1000001",
        "tgn:1001960",
        "tgn:7005560",
        "tgn:7029392"
    ],
    "tgn:id":7377429,
    "tgn:name":"Rancho Las Norias",
    "tgn:placetype":[
        "aat:300000241"
    ]
},
  "bbox": [],
  "geometry": {"coordinates":[-112.45,31.083333],"type":"Point"}
}
=======
{"geometry":{"type":"Point","coordinates":[-112.450000,31.083333]},"type":"Feature","properties":{"hierarchy":["tgn:7377429","tgn:1000001","tgn:1001960","tgn:7005560","tgn:7029392"],"placetype":["aat:300000241"],"id":7377429,"name:xx":"Rancho Las Norias"}}
>>>>>>> 03f74aca74312dbeaf24d7e61306dd6a786dc3d0
