<<<<<<< HEAD
{
  "id": 7176177,
  "type": "Feature",
  "properties": {
    "tgn:hierarchy":[
        "tgn:7176177",
        "tgn:1000003",
        "tgn:7003676",
        "tgn:7000084",
        "tgn:7029392"
    ],
    "tgn:id":7176177,
    "tgn:name":"Gro\u00dfe Krautliet",
    "tgn:placetype":[
        "aat:300008777"
    ]
},
  "bbox": [],
  "geometry": {"coordinates":[10.233333,51.916667],"type":"Point"}
}
=======
{"geometry":{"type":"Point","coordinates":[10.233333,51.916667]},"type":"Feature","properties":{"hierarchy":["tgn:7176177","tgn:1000003","tgn:7003676","tgn:7000084","tgn:7029392"],"placetype":["aat:300008777"],"id":7176177,"name:xx":"Gro\u00dfe Krautliet"}}
>>>>>>> 03f74aca74312dbeaf24d7e61306dd6a786dc3d0
