{
  "id": 2042890,
  "type": "Feature",
  "properties": {
    "tgn:hierarchy":[
        "tgn:2042890",
        "tgn:1000001",
        "tgn:7012149",
        "tgn:2000894",
        "tgn:7007256",
        "tgn:7029392"
    ],
    "tgn:id":2042890,
    "tgn:name":"Grand Bayou",
    "tgn:placetype":[
        "aat:300008347"
    ]
},
  "bbox": [],
  "geometry": {"coordinates":[-93.4667,32.0833],"type":"Point"}
}