{
  "id": 2552824,
  "type": "Feature",
  "properties": {
    "tgn:hierarchy":[
        "tgn:2552824",
        "tgn:1000001",
        "tgn:7012149",
        "tgn:2001717",
        "tgn:7007708",
        "tgn:7029392"
    ],
    "tgn:id":2552824,
    "tgn:name":"O A Lake",
    "tgn:placetype":[
        "aat:300008680"
    ]
},
  "bbox": [],
  "geometry": {"coordinates":[-121.9167,44.55],"type":"Point"}
}