<<<<<<< HEAD
{
  "id": 7356096,
  "type": "Feature",
  "properties": {
    "tgn:hierarchy":[
        "tgn:7356096",
        "tgn:1000001",
        "tgn:7005594",
        "tgn:7005560",
        "tgn:7029392"
    ],
    "tgn:id":7356096,
    "tgn:name":"Camarones",
    "tgn:placetype":[
        "aat:300008347"
    ]
},
  "bbox": [],
  "geometry": {"coordinates":[-99.2,21.9],"type":"Point"}
}
=======
{"geometry":{"type":"Point","coordinates":[-99.200000,21.900000]},"type":"Feature","properties":{"hierarchy":["tgn:7356096","tgn:1000001","tgn:7005594","tgn:7005560","tgn:7029392"],"placetype":["aat:300008347"],"id":7356096,"name:xx":"Camarones"}}
>>>>>>> 03f74aca74312dbeaf24d7e61306dd6a786dc3d0
