{
  "id": 2453126,
  "type": "Feature",
  "properties": {
    "tgn:hierarchy":[
        "tgn:2453126",
        "tgn:2000947",
        "tgn:1000001",
        "tgn:7012149",
        "tgn:7007520",
        "tgn:7029392"
    ],
    "tgn:id":2453126,
    "tgn:name":"Little Carp River",
    "tgn:placetype":[
        "aat:300008707"
    ]
},
  "bbox": [],
  "geometry": {"coordinates":[-88.5667,46.7667],"type":"Point"}
}