{
  "id": 7394198,
  "type": "Feature",
  "properties": {
    "tgn:hierarchy":[
        "tgn:7394198",
        "tgn:7005581",
        "tgn:1000001",
        "tgn:7005560",
        "tgn:7029392"
    ],
    "tgn:id":7394198,
    "tgn:name":"San Blas",
    "tgn:placetype":[
        "aat:300008347"
    ]
},
  "bbox": [],
  "geometry": {"coordinates":[-107.35,28.916667],"type":"Point"}
}