{
  "id": 1066508,
  "type": "Feature",
  "properties": {
    "tgn:hierarchy":[
        "tgn:1066508",
        "tgn:1000004",
        "tgn:7001838",
        "tgn:1000111",
        "tgn:7029392"
    ],
    "tgn:id":1066508,
    "tgn:name":"Alxa Zuoqi",
    "tgn:placetype":[
        "aat:300008347"
    ]
},
  "bbox": [],
  "geometry": {"coordinates":[105.5833,38.9667],"type":"Point"}
}