{
  "id": 2301473,
  "type": "Feature",
  "properties": {
    "tgn:hierarchy":[
        "tgn:2301473",
        "tgn:1000001",
        "tgn:7012149",
        "tgn:2000831",
        "tgn:7007255",
        "tgn:7029392"
    ],
    "tgn:id":2301473,
    "tgn:name":"Dunnie Branch",
    "tgn:placetype":[
        "aat:300008699"
    ]
},
  "bbox": [],
  "geometry": {"coordinates":[-83.1333,37.8833],"type":"Point"}
}