{
  "id": 7218198,
  "type": "Feature",
  "properties": {
    "tgn:hierarchy":[
        "tgn:7218198",
        "tgn:7011161",
        "tgn:7002674",
        "tgn:1000003",
        "tgn:1000074",
        "tgn:7029392"
    ],
    "tgn:id":7218198,
    "tgn:name":"Christ\u00f3s",
    "tgn:placetype":[
        "aat:300007466"
    ]
},
  "bbox": [],
  "geometry": {"coordinates":[25.914722,38.265278],"type":"Point"}
}