{
  "id": 7046933,
  "type": "Feature",
  "properties": {
    "tgn:hierarchy":[
        "tgn:7046933",
        "tgn:7003166",
        "tgn:1000003",
        "tgn:7009760",
        "tgn:1000080",
        "tgn:7029392"
    ],
    "tgn:id":7046933,
    "tgn:name":"Cascetto, Monte",
    "tgn:placetype":[
        "aat:300008795"
    ]
},
  "bbox": [],
  "geometry": {"coordinates":[10.533333,43.75],"type":"Point"}
}