{
  "id": 2595451,
  "type": "Feature",
  "properties": {
    "tgn:hierarchy":[
        "tgn:2595451",
        "tgn:1000001",
        "tgn:2001427",
        "tgn:7012149",
        "tgn:7007564",
        "tgn:7029392"
    ],
    "tgn:id":2595451,
    "tgn:name":"Potato Hill",
    "tgn:placetype":[
        "aat:300008798"
    ]
},
  "bbox": [],
  "geometry": {"coordinates":[-72.2333,43.2833],"type":"Point"}
}