{
  "id": 7352252,
  "type": "Feature",
  "properties": {
    "tgn:hierarchy":[
        "tgn:7352252",
        "tgn:1000001",
        "tgn:1001893",
        "tgn:7005560",
        "tgn:7029392"
    ],
    "tgn:id":7352252,
    "tgn:name":"Barreras, R\u00edo",
    "tgn:placetype":[
        "aat:300008699"
    ]
},
  "bbox": [],
  "geometry": {"coordinates":[-103.383333,18.95],"type":"Point"}
}