{
  "id": 2478283,
  "type": "Feature",
  "properties": {
    "tgn:hierarchy":[
        "tgn:2478283",
        "tgn:1000001",
        "tgn:7012149",
        "tgn:2002114",
        "tgn:7007827",
        "tgn:7029392"
    ],
    "tgn:id":2478283,
    "tgn:name":"Macks Ditch",
    "tgn:placetype":[
        "aat:300006075"
    ]
},
  "bbox": [],
  "geometry": {"coordinates":[-112.2833,39.5333],"type":"Point"}
}