{
  "id": 2543328,
  "type": "Feature",
  "properties": {
    "tgn:hierarchy":[
        "tgn:2543328",
        "tgn:1000001",
        "tgn:7012149",
        "tgn:7007523",
        "tgn:7029392"
    ],
    "tgn:id":2543328,
    "tgn:name":"Norman Creek",
    "tgn:placetype":[
        "aat:300008706"
    ]
},
  "bbox": [],
  "geometry": {"coordinates":[-91.5167,37.7667],"type":"Point"}
}