{
  "id": 7356603,
  "type": "Feature",
  "properties": {
    "tgn:hierarchy":[
        "tgn:7356603",
        "tgn:1000001",
        "tgn:7005601",
        "tgn:7005560",
        "tgn:7029392"
    ],
    "tgn:id":7356603,
    "tgn:name":"Carretones",
    "tgn:placetype":[
        "aat:300008347"
    ]
},
  "bbox": [],
  "geometry": {"coordinates":[-102.95,21.833333],"type":"Point"}
}