{
  "id": 2691323,
  "type": "Feature",
  "properties": {
    "tgn:hierarchy":[
        "tgn:2691323",
        "tgn:1000001",
        "tgn:2001419",
        "tgn:7012149",
        "tgn:7007526",
        "tgn:7029392"
    ],
    "tgn:id":2691323,
    "tgn:name":"Star Creek",
    "tgn:placetype":[
        "aat:300008706"
    ]
},
  "bbox": [],
  "geometry": {"coordinates":[-118.1667,40.55],"type":"Point"}
}