{
  "id": 2372342,
  "type": "Feature",
  "properties": {
    "tgn:hierarchy":[
        "tgn:2372342",
        "tgn:7006450",
        "tgn:1000001",
        "tgn:7019698",
        "tgn:7012149",
        "tgn:7029392"
    ],
    "tgn:id":2372342,
    "tgn:name":"Halfway Island",
    "tgn:placetype":[
        "aat:300008791"
    ]
},
  "bbox": [],
  "geometry": {"coordinates":[-149.6667,60.95],"type":"Point"}
}