{
  "id": 2743173,
  "type": "Feature",
  "properties": {
    "tgn:hierarchy":[
        "tgn:2743173",
        "tgn:1000001",
        "tgn:2001840",
        "tgn:7012149",
        "tgn:7007825",
        "tgn:7029392"
    ],
    "tgn:id":2743173,
    "tgn:name":"Vance Mountain",
    "tgn:placetype":[
        "aat:300008798"
    ]
},
  "bbox": [],
  "geometry": {"coordinates":[-85.3833,35.5333],"type":"Point"}
}