<<<<<<< HEAD
{
  "id": 7360758,
  "type": "Feature",
  "properties": {
    "tgn:hierarchy":[
        "tgn:7360758",
        "tgn:7005583",
        "tgn:1000001",
        "tgn:7005560",
        "tgn:7029392"
    ],
    "tgn:id":7360758,
    "tgn:name":"Cueva del Negro",
    "tgn:placetype":[
        "aat:300008347"
    ]
},
  "bbox": [],
  "geometry": {"coordinates":[-106.1,25.116667],"type":"Point"}
}
=======
{"geometry":{"type":"Point","coordinates":[-106.100000,25.116667]},"type":"Feature","properties":{"hierarchy":["tgn:7360758","tgn:7005583","tgn:1000001","tgn:7005560","tgn:7029392"],"placetype":["aat:300008347"],"id":7360758,"name:xx":"Cueva del Negro"}}
>>>>>>> 03f74aca74312dbeaf24d7e61306dd6a786dc3d0
