{
  "id": 7309793,
  "type": "Feature",
  "properties": {
    "tgn:hierarchy":[
        "tgn:7309793",
        "tgn:7016598",
        "tgn:1000049",
        "tgn:1000002",
        "tgn:7029392"
    ],
    "tgn:id":7309793,
    "tgn:name":"Naguay\u00e1n, Cerro",
    "tgn:placetype":[
        "aat:300008795"
    ]
},
  "bbox": [],
  "geometry": {"coordinates":[-70.216667,-23.216667],"type":"Point"}
}