{
  "id": 2511990,
  "type": "Feature",
  "properties": {
    "tgn:hierarchy":[
        "tgn:2511990",
        "tgn:1000001",
        "tgn:1002198",
        "tgn:7012149",
        "tgn:7007826",
        "tgn:7029392"
    ],
    "tgn:id":2511990,
    "tgn:name":"Mill Bayou",
    "tgn:placetype":[
        "aat:300008699"
    ]
},
  "bbox": [],
  "geometry": {"coordinates":[-95.5333,29.15],"type":"Point"}
}