{
  "id": 7399261,
  "type": "Feature",
  "properties": {
    "tgn:hierarchy":[
        "tgn:7399261",
        "tgn:1000001",
        "tgn:7005593",
        "tgn:7005560",
        "tgn:7029392"
    ],
    "tgn:id":7399261,
    "tgn:name":"La Loma",
    "tgn:placetype":[
        "aat:300008347"
    ]
},
  "bbox": [],
  "geometry": {"coordinates":[-100.083333,20.158333],"type":"Point"}
}