{
  "id": 2645052,
  "type": "Feature",
  "properties": {
    "tgn:hierarchy":[
        "tgn:2645052",
        "tgn:1000001",
        "tgn:7012149",
        "tgn:7007157",
        "tgn:2000189",
        "tgn:7029392"
    ],
    "tgn:id":2645052,
    "tgn:name":"Sauerkraut Peak",
    "tgn:placetype":[
        "aat:300008798"
    ]
},
  "bbox": [],
  "geometry": {"coordinates":[-123.3333,41.3167],"type":"Point"}
}