<<<<<<< HEAD
{
  "id": 2762498,
  "type": "Feature",
  "properties": {
    "tgn:hierarchy":[
        "tgn:2762498",
        "tgn:1000001",
        "tgn:7012149",
        "tgn:2001377",
        "tgn:7007525",
        "tgn:7029392"
    ],
    "tgn:id":2762498,
    "tgn:name":"West Water Creek",
    "tgn:placetype":[
        "aat:300008706"
    ]
},
  "bbox": [],
  "geometry": {"coordinates":[-103.25,41.9],"type":"Point"}
}
=======
{"geometry":{"type":"Point","coordinates":[-103.250000,41.900000]},"type":"Feature","properties":{"hierarchy":["tgn:2762498","tgn:1000001","tgn:7012149","tgn:2001377","tgn:7007525","tgn:7029392"],"placetype":["aat:300008706"],"id":2762498,"name:xx":"West Water Creek"}}
>>>>>>> 03f74aca74312dbeaf24d7e61306dd6a786dc3d0
