{
  "id": 7312104,
  "type": "Feature",
  "properties": {
    "tgn:hierarchy":[
        "tgn:7312104",
        "tgn:1001768",
        "tgn:1000049",
        "tgn:1000002",
        "tgn:7029392"
    ],
    "tgn:id":7312104,
    "tgn:name":"Las Chilcas, Lomas",
    "tgn:placetype":[
        "aat:300387002"
    ]
},
  "bbox": [],
  "geometry": {"coordinates":[-70.783333,-32.283333],"type":"Point"}
}