{
  "id": 7055940,
  "type": "Feature",
  "properties": {
    "tgn:hierarchy":[
        "tgn:7055940",
        "tgn:7003168",
        "tgn:1000003",
        "tgn:7009760",
        "tgn:1000080",
        "tgn:7029392"
    ],
    "tgn:id":7055940,
    "tgn:name":"Onzola, Torrente",
    "tgn:placetype":[
        "aat:300008699"
    ]
},
  "bbox": [],
  "geometry": {"coordinates":[11.633333,43.033333],"type":"Point"}
}