{
  "id": 2511748,
  "type": "Feature",
  "properties": {
    "tgn:hierarchy":[
        "tgn:2511748",
        "tgn:1000001",
        "tgn:7012149",
        "tgn:2000884",
        "tgn:7007256",
        "tgn:7029392"
    ],
    "tgn:id":2511748,
    "tgn:name":"Miliam Creek",
    "tgn:placetype":[
        "aat:300008706"
    ]
},
  "bbox": [],
  "geometry": {"coordinates":[-92.8167,32.6333],"type":"Point"}
}