{
  "id": 2611158,
  "type": "Feature",
  "properties": {
    "tgn:hierarchy":[
        "tgn:2611158",
        "tgn:1000001",
        "tgn:7012149",
        "tgn:2002114",
        "tgn:7007827",
        "tgn:7029392"
    ],
    "tgn:id":2611158,
    "tgn:name":"Red Hills",
    "tgn:placetype":[
        "aat:300008798"
    ]
},
  "bbox": [],
  "geometry": {"coordinates":[-113.05,38.75],"type":"Point"}
}