{
  "id": 2762018,
  "type": "Feature",
  "properties": {
    "tgn:hierarchy":[
        "tgn:2762018",
        "tgn:1000001",
        "tgn:2001262",
        "tgn:7012149",
        "tgn:7007524",
        "tgn:7029392"
    ],
    "tgn:id":2762018,
    "tgn:name":"West Savoy Creek",
    "tgn:placetype":[
        "aat:300008706"
    ]
},
  "bbox": [],
  "geometry": {"coordinates":[-108.65,48.6833],"type":"Point"}
}