<<<<<<< HEAD
{
  "id": 7056352,
  "type": "Feature",
  "properties": {
    "tgn:hierarchy":[
        "tgn:7056352",
        "tgn:7005869",
        "tgn:1000003",
        "tgn:7003237",
        "tgn:1000080",
        "tgn:7029392"
    ],
    "tgn:id":7056352,
    "tgn:name":"Ognissanti",
    "tgn:placetype":[
        "aat:300008347"
    ]
},
  "bbox": [],
  "geometry": {"coordinates":[10.216667,45.116667],"type":"Point"}
}
=======
{"geometry":{"type":"Point","coordinates":[10.216667,45.116667]},"type":"Feature","properties":{"hierarchy":["tgn:7056352","tgn:7005869","tgn:1000003","tgn:7003237","tgn:1000080","tgn:7029392"],"placetype":["aat:300008347"],"id":7056352,"name:xx":"Ognissanti"}}
>>>>>>> 03f74aca74312dbeaf24d7e61306dd6a786dc3d0
