{
  "id": 7587321,
  "type": "Feature",
  "properties": {
    "tgn:hierarchy":[
        "tgn:7587321",
        "tgn:1000004",
        "tgn:7000198",
        "tgn:1001905",
        "tgn:7029392"
    ],
    "tgn:id":7587321,
    "tgn:name:en":"Zhekiya",
    "tgn:placetype":[
        "aat:300008347"
    ]
},
  "bbox": [],
  "geometry": {"coordinates":[94.489877,25.929965],"type":"Point"}
}