{
  "id": 7416440,
  "type": "Feature",
  "properties": {
    "tgn:hierarchy":[
        "tgn:7416440",
        "tgn:1000001",
        "tgn:7005591",
        "tgn:7005560",
        "tgn:7029392"
    ],
    "tgn:id":7416440,
    "tgn:name:es":"Santa Elena",
    "tgn:placetype":[
        "aat:300008347"
    ]
},
  "bbox": [],
  "geometry": {"coordinates":[-96.880278,15.753056],"type":"Point"}
}