<<<<<<< HEAD
{
  "id": 2333751,
  "type": "Feature",
  "properties": {
    "tgn:hierarchy":[
        "tgn:2333751",
        "tgn:1000001",
        "tgn:2001484",
        "tgn:7012149",
        "tgn:7007709",
        "tgn:7029392"
    ],
    "tgn:id":2333751,
    "tgn:name":"Foote Mineral Reservoir",
    "tgn:placetype":[
        "aat:300006191"
    ]
},
  "bbox": [],
  "geometry": {"coordinates":[-81.35,35.2],"type":"Point"}
}
=======
{"geometry":{"type":"Point","coordinates":[-81.350000,35.200000]},"type":"Feature","properties":{"hierarchy":["tgn:2333751","tgn:1000001","tgn:2001484","tgn:7012149","tgn:7007709","tgn:7029392"],"placetype":["aat:300006191"],"id":2333751,"name:xx":"Foote Mineral Reservoir"}}
>>>>>>> 03f74aca74312dbeaf24d7e61306dd6a786dc3d0
