{
  "id": 2487759,
  "type": "Feature",
  "properties": {
    "tgn:hierarchy":[
        "tgn:2487759",
        "tgn:1000001",
        "tgn:7012149",
        "tgn:7007250",
        "tgn:7029392"
    ],
    "tgn:id":2487759,
    "tgn:name":"Left Fork Placer Creek",
    "tgn:placetype":[
        "aat:300008706"
    ]
},
  "bbox": [],
  "geometry": {"coordinates":[-114.65,43.6333],"type":"Point"}
}