{
  "id": 2136692,
  "type": "Feature",
  "properties": {
    "tgn:hierarchy":[
        "tgn:2136692",
        "tgn:1000001",
        "tgn:7012149",
        "tgn:2001917",
        "tgn:7007825",
        "tgn:7029392"
    ],
    "tgn:id":2136692,
    "tgn:name":"Ardee",
    "tgn:placetype":[
        "aat:300008347"
    ]
},
  "bbox": [],
  "geometry": {"coordinates":[-87.6167,36.5333],"type":"Point"}
}