{
  "id": 1109149,
  "type": "Feature",
  "properties": {
    "tgn:hierarchy":[
        "tgn:1109149",
        "tgn:1000001",
        "tgn:7012149",
        "tgn:7029392"
    ],
    "tgn:id":1109149,
    "tgn:name":"Iron Mountains",
    "tgn:placetype":[
        "aat:300008795"
    ]
},
  "bbox": [],
  "geometry": {"coordinates":[-81.6833,36.6667],"type":"Point"}
}