{
  "id": 2711018,
  "type": "Feature",
  "properties": {
    "tgn:hierarchy":[
        "tgn:2711018",
        "tgn:1000001",
        "tgn:7012149",
        "tgn:1002819",
        "tgn:7007523",
        "tgn:7029392"
    ],
    "tgn:id":2711018,
    "tgn:name":"Tank Pond",
    "tgn:placetype":[
        "aat:300008680"
    ]
},
  "bbox": [],
  "geometry": {"coordinates":[-92.5333,39.4167],"type":"Point"}
}