{
  "id": 2627219,
  "type": "Feature",
  "properties": {
    "tgn:hierarchy":[
        "tgn:2627219",
        "tgn:1000001",
        "tgn:7012149",
        "tgn:7007157",
        "tgn:7014005",
        "tgn:7029392"
    ],
    "tgn:id":2627219,
    "tgn:name":"Rodeo Lagoon",
    "tgn:placetype":[
        "aat:300008680"
    ]
},
  "bbox": [],
  "geometry": {"coordinates":[-122.5167,37.8167],"type":"Point"}
}