{
  "id": 2652798,
  "type": "Feature",
  "properties": {
    "tgn:hierarchy":[
        "tgn:2652798",
        "tgn:1000001",
        "tgn:7012149",
        "tgn:7007825",
        "tgn:7029392"
    ],
    "tgn:id":2652798,
    "tgn:name":"Service Branch",
    "tgn:placetype":[
        "aat:300008699"
    ]
},
  "bbox": [],
  "geometry": {"coordinates":[-85.35,35.1833],"type":"Point"}
}