{
  "id": 2629182,
  "type": "Feature",
  "properties": {
    "tgn:hierarchy":[
        "tgn:2629182",
        "tgn:1000001",
        "tgn:7016172",
        "tgn:2000115",
        "tgn:7012149",
        "tgn:7029392"
    ],
    "tgn:id":2629182,
    "tgn:name":"Rose Pond Lateral",
    "tgn:placetype":[
        "aat:300006075"
    ]
},
  "bbox": [],
  "geometry": {"coordinates":[-90.5667,36.4833],"type":"Point"}
}