{
  "id": 2117893,
  "type": "Feature",
  "properties": {
    "tgn:hierarchy":[
        "tgn:2117893",
        "tgn:1000001",
        "tgn:7012149",
        "tgn:2002284",
        "tgn:7013961",
        "tgn:7029392"
    ],
    "tgn:id":2117893,
    "tgn:name":"Cottle",
    "tgn:placetype":[
        "aat:300008347"
    ]
},
  "bbox": [],
  "geometry": {"coordinates":[-80.6167,38.3333],"type":"Point"}
}