{
  "id": 7047801,
  "type": "Feature",
  "properties": {
    "tgn:hierarchy":[
        "tgn:7047801",
        "tgn:7003007",
        "tgn:1000003",
        "tgn:7002997",
        "tgn:1000080",
        "tgn:7029392"
    ],
    "tgn:id":7047801,
    "tgn:name":"Grassanella",
    "tgn:placetype":[
        "aat:300008347"
    ]
},
  "bbox": [],
  "geometry": {"coordinates":[11.283333,45.383333],"type":"Point"}
}