{
  "id": 7496007,
  "type": "Feature",
  "properties": {
    "tgn:hierarchy":[
        "tgn:7496007",
        "tgn:1000004",
        "tgn:1000454",
        "tgn:1000141",
        "tgn:7029392"
    ],
    "tgn:id":7496007,
    "tgn:name":"Ruizi Xi",
    "tgn:placetype":[
        "aat:300008699"
    ]
},
  "bbox": [],
  "geometry": {"coordinates":[121.448761,24.844341],"type":"Point"}
}