{
  "id": 2530388,
  "type": "Feature",
  "properties": {
    "tgn:hierarchy":[
        "tgn:2530388",
        "tgn:1000001",
        "tgn:7012149",
        "tgn:2000281",
        "tgn:7007240",
        "tgn:7029392"
    ],
    "tgn:id":2530388,
    "tgn:name":"Muddy Branch",
    "tgn:placetype":[
        "aat:300008699"
    ]
},
  "bbox": [],
  "geometry": {"coordinates":[-86.7667,30.85],"type":"Point"}
}