<<<<<<< HEAD
{
  "id": 7025839,
  "type": "Feature",
  "properties": {
    "tgn:hierarchy":[
        "tgn:7025839",
        "tgn:7002445",
        "tgn:1000003",
        "tgn:7011961",
        "tgn:7008591",
        "tgn:7029392"
    ],
    "tgn:id":7025839,
    "tgn:name":"Higher Bockhampton",
    "tgn:placetype":[
        "aat:300008347"
    ]
},
  "bbox": [],
  "geometry": {"coordinates":[-2.3833,50.7167],"type":"Point"}
}
=======
{"geometry":{"type":"Point","coordinates":[-2.383300,50.716700]},"type":"Feature","properties":{"hierarchy":["tgn:7025839","tgn:7002445","tgn:1000003","tgn:7011961","tgn:7008591","tgn:7029392"],"placetype":["aat:300008347"],"id":7025839,"name:xx":"Higher Bockhampton"}}
>>>>>>> 03f74aca74312dbeaf24d7e61306dd6a786dc3d0
