{
  "id": 2719752,
  "type": "Feature",
  "properties": {
    "tgn:hierarchy":[
        "tgn:2719752",
        "tgn:1000001",
        "tgn:7012149",
        "tgn:1002426",
        "tgn:7007255",
        "tgn:7029392"
    ],
    "tgn:id":2719752,
    "tgn:name":"Three Prong Branch",
    "tgn:placetype":[
        "aat:300008699"
    ]
},
  "bbox": [],
  "geometry": {"coordinates":[-83.1333,38.5167],"type":"Point"}
}