{
  "id": 2573516,
  "type": "Feature",
  "properties": {
    "tgn:hierarchy":[
        "tgn:2573516",
        "tgn:1000001",
        "tgn:7012149",
        "tgn:2002047",
        "tgn:7007826",
        "tgn:7029392"
    ],
    "tgn:id":2573516,
    "tgn:name":"Pecan Lake",
    "tgn:placetype":[
        "aat:300008680"
    ]
},
  "bbox": [],
  "geometry": {"coordinates":[-93.7333,30.5333],"type":"Point"}
}