{
  "id": 7014454,
  "type": "Feature",
  "properties": {
    "tgn:hierarchy":[
        "tgn:7014454",
        "tgn:1000001",
        "tgn:7012149",
        "tgn:7007157",
        "tgn:1002857",
        "tgn:7029392"
    ],
    "tgn:id":7014454,
    "tgn:name":"San Bernardino",
    "tgn:placetype":[
        "aat:300387277",
        "aat:300008347",
        "aat:300008416",
        "aat:300008389",
        "aat:300387302"
    ]
},
  "bbox": [],
  "geometry": {"coordinates":[-117.2667,34.0833],"type":"Point"}
}