{
  "id": 7342539,
  "type": "Feature",
  "properties": {
    "tgn:hierarchy":[
        "tgn:7342539",
        "tgn:7002829",
        "tgn:1000003",
        "tgn:7002786",
        "tgn:1000095",
        "tgn:7029392"
    ],
    "tgn:id":7342539,
    "tgn:name":"Casta\u00f1oso",
    "tgn:placetype":[
        "aat:300008347"
    ]
},
  "bbox": [],
  "geometry": {"coordinates":[-7.133333,43.15],"type":"Point"}
}