{
  "id": 2749753,
  "type": "Feature",
  "properties": {
    "tgn:hierarchy":[
        "tgn:2749753",
        "tgn:1000001",
        "tgn:7012149",
        "tgn:2002303",
        "tgn:7013961",
        "tgn:7029392"
    ],
    "tgn:id":2749753,
    "tgn:name":"Walnut Hill",
    "tgn:placetype":[
        "aat:300008798"
    ]
},
  "bbox": [],
  "geometry": {"coordinates":[-81.6667,39.1833],"type":"Point"}
}