{
  "id": 1033792,
  "type": "Feature",
  "properties": {
    "tgn:hierarchy":[
        "tgn:1033792",
        "tgn:7002871",
        "tgn:1000003",
        "tgn:1000070",
        "tgn:7029392"
    ],
    "tgn:id":1033792,
    "tgn:name":"Lapalisse",
    "tgn:placetype":[
        "aat:300008347"
    ]
},
  "bbox": [],
  "geometry": {"coordinates":[3.7333,46.25],"type":"Point"}
}