{
  "id": 2679399,
  "type": "Feature",
  "properties": {
    "tgn:hierarchy":[
        "tgn:2679399",
        "tgn:1000001",
        "tgn:7012149",
        "tgn:2001119",
        "tgn:7007522",
        "tgn:7029392"
    ],
    "tgn:id":2679399,
    "tgn:name":"South Fork Mill Creek",
    "tgn:placetype":[
        "aat:300008706"
    ]
},
  "bbox": [],
  "geometry": {"coordinates":[-89.25,31.6833],"type":"Point"}
}