<<<<<<< HEAD
{
  "id": 7481461,
  "type": "Feature",
  "properties": {
    "tgn:hierarchy":[
        "tgn:7481461",
        "tgn:1000004",
        "tgn:7471332",
        "tgn:1000141",
        "tgn:7029392"
    ],
    "tgn:id":7481461,
    "tgn:name":"Shibitan Shan",
    "tgn:placetype":[
        "aat:300008798"
    ]
},
  "bbox": [],
  "geometry": {"coordinates":[121.11,24.756667],"type":"Point"}
}
=======
{"geometry":{"type":"Point","coordinates":[121.110000,24.756667]},"type":"Feature","properties":{"hierarchy":["tgn:7481461","tgn:1000004","tgn:7471332","tgn:1000141","tgn:7029392"],"placetype":["aat:300008798"],"id":7481461,"name:xx":"Shibitan Shan"}}
>>>>>>> 03f74aca74312dbeaf24d7e61306dd6a786dc3d0
