{
  "id": 7481461,
  "type": "Feature",
  "properties": {
    "tgn:hierarchy":[
        "tgn:7481461",
        "tgn:1000004",
        "tgn:7471332",
        "tgn:1000141",
        "tgn:7029392"
    ],
    "tgn:id":7481461,
    "tgn:name":"Shibitan Shan",
    "tgn:placetype":[
        "aat:300008798"
    ]
},
  "bbox": [],
  "geometry": {"coordinates":[121.11,24.756667],"type":"Point"}
}