{
  "id": 2421237,
  "type": "Feature",
  "properties": {
    "tgn:hierarchy":[
        "tgn:2421237",
        "tgn:1000001",
        "tgn:7012149",
        "tgn:2000230",
        "tgn:7007158",
        "tgn:7029392"
    ],
    "tgn:id":2421237,
    "tgn:name":"Jerry Gulch",
    "tgn:placetype":[
        "aat:300008761"
    ]
},
  "bbox": [],
  "geometry": {"coordinates":[-108.0833,39.2667],"type":"Point"}
}