{
  "id": 7523704,
  "type": "Feature",
  "properties": {
    "tgn:hierarchy":[
        "tgn:7523704",
        "tgn:7001242",
        "tgn:7001311",
        "tgn:7016833",
        "tgn:7029392"
    ],
    "tgn:id":7523704,
    "tgn:name:en":"El-Kab Aqab",
    "tgn:placetype":[
        "aat:300379998"
    ]
},
  "bbox": [],
  "geometry": {"coordinates":[33.966667,26.266667],"type":"Point"}
}