{
  "id": 7069781,
  "type": "Feature",
  "properties": {
    "tgn:hierarchy":[
        "tgn:7069781",
        "tgn:1000003",
        "tgn:7003687",
        "tgn:7000084",
        "tgn:7029392"
    ],
    "tgn:id":7069781,
    "tgn:name":"Todth\u00fcgel",
    "tgn:placetype":[
        "aat:300008777"
    ]
},
  "bbox": [],
  "geometry": {"coordinates":[11.55,51.666667],"type":"Point"}
}