{
  "id": 7515381,
  "type": "Feature",
  "properties": {
    "tgn:hierarchy":[
        "tgn:7515381",
        "tgn:1009227",
        "tgn:7001866",
        "tgn:1000226",
        "tgn:1000006",
        "tgn:7029392"
    ],
    "tgn:id":7515381,
    "tgn:name:en":"Catherine, Lake",
    "tgn:placetype":[
        "aat:300008680"
    ]
},
  "bbox": [],
  "geometry": {"coordinates":[171.566667,-43.233333],"type":"Point"}
}