<<<<<<< HEAD
{
  "id": 7480585,
  "type": "Feature",
  "properties": {
    "tgn:hierarchy":[
        "tgn:7480585",
        "tgn:1000004",
        "tgn:7001013",
        "tgn:1000141",
        "tgn:7029392"
    ],
    "tgn:id":7480585,
    "tgn:name":"Zhujiazhuang",
    "tgn:placetype":[
        "aat:300008347"
    ]
},
  "bbox": [],
  "geometry": {"coordinates":[121.233056,24.875278],"type":"Point"}
}
=======
{"geometry":{"type":"Point","coordinates":[121.233056,24.875278]},"type":"Feature","properties":{"hierarchy":["tgn:7480585","tgn:1000004","tgn:7001013","tgn:1000141","tgn:7029392"],"placetype":["aat:300008347"],"id":7480585,"name:xx":"Zhujiazhuang"}}
>>>>>>> 03f74aca74312dbeaf24d7e61306dd6a786dc3d0
