{
  "id": 2298998,
  "type": "Feature",
  "properties": {
    "tgn:hierarchy":[
        "tgn:2298998",
        "tgn:1000001",
        "tgn:7012149",
        "tgn:2002354",
        "tgn:7007922",
        "tgn:7029392"
    ],
    "tgn:id":2298998,
    "tgn:name":"Duchess Creek",
    "tgn:placetype":[
        "aat:300008706"
    ]
},
  "bbox": [],
  "geometry": {"coordinates":[-88.45,44.85],"type":"Point"}
}