{
  "id": 2557627,
  "type": "Feature",
  "properties": {
    "tgn:hierarchy":[
        "tgn:2557627",
        "tgn:1000001",
        "tgn:7012149",
        "tgn:2000933",
        "tgn:7007515",
        "tgn:7029392"
    ],
    "tgn:id":2557627,
    "tgn:name":"Old Prince",
    "tgn:placetype":[
        "aat:300132348"
    ]
},
  "bbox": [],
  "geometry": {"coordinates":[-70.4167,43.35],"type":"Point"}
}