{
  "id": 2373068,
  "type": "Feature",
  "properties": {
    "tgn:hierarchy":[
        "tgn:2373068",
        "tgn:1002143",
        "tgn:1000001",
        "tgn:7012149",
        "tgn:7007252",
        "tgn:7029392"
    ],
    "tgn:id":2373068,
    "tgn:name":"Halls Corners",
    "tgn:placetype":[
        "aat:300008347"
    ]
},
  "bbox": [],
  "geometry": {"coordinates":[-84.85,41.2333],"type":"Point"}
}