<<<<<<< HEAD
{
  "id": 7361488,
  "type": "Feature",
  "properties": {
    "tgn:hierarchy":[
        "tgn:7361488",
        "tgn:7005580",
        "tgn:1000001",
        "tgn:7005560",
        "tgn:7029392"
    ],
    "tgn:id":7361488,
    "tgn:name":"El Coyol",
    "tgn:placetype":[
        "aat:300008347"
    ]
},
  "bbox": [],
  "geometry": {"coordinates":[-93.783333,16.116667],"type":"Point"}
}
=======
{"geometry":{"type":"Point","coordinates":[-93.783333,16.116667]},"type":"Feature","properties":{"hierarchy":["tgn:7361488","tgn:7005580","tgn:1000001","tgn:7005560","tgn:7029392"],"placetype":["aat:300008347"],"id":7361488,"name:xx":"El Coyol"}}
>>>>>>> 03f74aca74312dbeaf24d7e61306dd6a786dc3d0
