{
  "id": 2438639,
  "type": "Feature",
  "properties": {
    "tgn:hierarchy":[
        "tgn:2438639",
        "tgn:1000001",
        "tgn:7016172",
        "tgn:2000116",
        "tgn:7012149",
        "tgn:7029392"
    ],
    "tgn:id":2438639,
    "tgn:name":"Kingston Branch",
    "tgn:placetype":[
        "aat:300008699"
    ]
},
  "bbox": [],
  "geometry": {"coordinates":[-91.8167,35.6333],"type":"Point"}
}