{
  "id": 2595770,
  "type": "Feature",
  "properties": {
    "tgn:hierarchy":[
        "tgn:2595770",
        "tgn:1000001",
        "tgn:7012149",
        "tgn:2001115",
        "tgn:7007522",
        "tgn:7029392"
    ],
    "tgn:id":2595770,
    "tgn:name":"Poticaw Bayou",
    "tgn:placetype":[
        "aat:300008699"
    ]
},
  "bbox": [],
  "geometry": {"coordinates":[-88.6167,30.5167],"type":"Point"}
}