<<<<<<< HEAD
{
  "id": 2764104,
  "type": "Feature",
  "properties": {
    "tgn:hierarchy":[
        "tgn:2764104",
        "tgn:1000001",
        "tgn:2001181",
        "tgn:7012149",
        "tgn:7007523",
        "tgn:7029392"
    ],
    "tgn:id":2764104,
    "tgn:name":"Wheeler Hollow",
    "tgn:placetype":[
        "aat:300008761"
    ]
},
  "bbox": [],
  "geometry": {"coordinates":[-90.9667,37.0667],"type":"Point"}
}
=======
{"geometry":{"type":"Point","coordinates":[-90.966700,37.066700]},"type":"Feature","properties":{"hierarchy":["tgn:2764104","tgn:1000001","tgn:2001181","tgn:7012149","tgn:7007523","tgn:7029392"],"placetype":["aat:300008761"],"id":2764104,"name:xx":"Wheeler Hollow"}}
>>>>>>> 03f74aca74312dbeaf24d7e61306dd6a786dc3d0
