{
  "id": 2329171,
  "type": "Feature",
  "properties": {
    "tgn:hierarchy":[
        "tgn:2329171",
        "tgn:1000001",
        "tgn:7012149",
        "tgn:7007157",
        "tgn:7014475",
        "tgn:7029392"
    ],
    "tgn:id":2329171,
    "tgn:name":"Fitzgerald Ridge",
    "tgn:placetype":[
        "aat:300266640"
    ]
},
  "bbox": [],
  "geometry": {"coordinates":[-121.5333,37.15],"type":"Point"}
}