{
  "id": 2103109,
  "type": "Feature",
  "properties": {
    "tgn:hierarchy":[
        "tgn:2103109",
        "tgn:1000001",
        "tgn:7012149",
        "tgn:1002401",
        "tgn:7007826",
        "tgn:7029392"
    ],
    "tgn:id":2103109,
    "tgn:name":"Caplen",
    "tgn:placetype":[
        "aat:300008347",
        "aat:300387210"
    ]
},
  "bbox": [],
  "geometry": {"coordinates":[-94.5167,29.4833],"type":"Point"}
}