{
  "id": 2144597,
  "type": "Feature",
  "properties": {
    "tgn:hierarchy":[
        "tgn:2144597",
        "tgn:1000001",
        "tgn:7012149",
        "tgn:2001543",
        "tgn:7007709",
        "tgn:7029392"
    ],
    "tgn:id":2144597,
    "tgn:name":"Bald Branch",
    "tgn:placetype":[
        "aat:300008699"
    ]
},
  "bbox": [],
  "geometry": {"coordinates":[-83.55,35.2833],"type":"Point"}
}