{
  "id": 2205823,
  "type": "Feature",
  "properties": {
    "tgn:hierarchy":[
        "tgn:2205823",
        "tgn:1000001",
        "tgn:7012149",
        "tgn:1002733",
        "tgn:7007919",
        "tgn:7029392"
    ],
    "tgn:id":2205823,
    "tgn:name":"Bull Neck",
    "tgn:placetype":[
        "aat:300008850"
    ]
},
  "bbox": [],
  "geometry": {"coordinates":[-76.2667,37.8167],"type":"Point"}
}