<<<<<<< HEAD
{
  "id": 7360437,
  "type": "Feature",
  "properties": {
    "tgn:hierarchy":[
        "tgn:7360437",
        "tgn:7005581",
        "tgn:1000001",
        "tgn:7005560",
        "tgn:7029392"
    ],
    "tgn:id":7360437,
    "tgn:name":"Cochinito",
    "tgn:placetype":[
        "aat:300008347"
    ]
},
  "bbox": [],
  "geometry": {"coordinates":[-107.783333,28.1],"type":"Point"}
}
=======
{"geometry":{"type":"Point","coordinates":[-107.783333,28.100000]},"type":"Feature","properties":{"hierarchy":["tgn:7360437","tgn:7005581","tgn:1000001","tgn:7005560","tgn:7029392"],"placetype":["aat:300008347"],"id":7360437,"name:xx":"Cochinito"}}
>>>>>>> 03f74aca74312dbeaf24d7e61306dd6a786dc3d0
