{
  "id": 1017929,
  "type": "Feature",
  "properties": {
    "tgn:hierarchy":[
        "tgn:1017929",
        "tgn:7005585",
        "tgn:1000001",
        "tgn:7005560",
        "tgn:7029392"
    ],
    "tgn:id":1017929,
    "tgn:name":"Nueva Cuadrilla",
    "tgn:placetype":[
        "aat:300008347"
    ]
},
  "bbox": [],
  "geometry": {"coordinates":[-101.55,18.0667],"type":"Point"}
}