{
  "id": 2053939,
  "type": "Feature",
  "properties": {
    "tgn:hierarchy":[
        "tgn:2053939",
        "tgn:1000001",
        "tgn:7012149",
        "tgn:7021314",
        "tgn:7007521",
        "tgn:7029392"
    ],
    "tgn:id":2053939,
    "tgn:name":"Bellingham",
    "tgn:placetype":[
        "aat:300008347"
    ]
},
  "bbox": [],
  "geometry": {"coordinates":[-96.2833,45.1333],"type":"Point"}
}