{
  "id": 2173320,
  "type": "Feature",
  "properties": {
    "tgn:hierarchy":[
        "tgn:2173320",
        "tgn:1000001",
        "tgn:7012149",
        "tgn:2000475",
        "tgn:7007250",
        "tgn:7029392"
    ],
    "tgn:id":2173320,
    "tgn:name":"Birch Creek",
    "tgn:placetype":[
        "aat:300008706"
    ]
},
  "bbox": [],
  "geometry": {"coordinates":[-114.8667,42.85],"type":"Point"}
}