<<<<<<< HEAD
{
  "id": 7359184,
  "type": "Feature",
  "properties": {
    "tgn:hierarchy":[
        "tgn:7359184",
        "tgn:1000001",
        "tgn:1001960",
        "tgn:7005560",
        "tgn:7029392"
    ],
    "tgn:id":7359184,
    "tgn:name":"Cruz, Puerto de la",
    "tgn:placetype":[
        "aat:300259572"
    ]
},
  "bbox": [],
  "geometry": {"coordinates":[-109.383333,28.133333],"type":"Point"}
}
=======
{"geometry":{"type":"Point","coordinates":[-109.383333,28.133333]},"type":"Feature","properties":{"hierarchy":["tgn:7359184","tgn:1000001","tgn:1001960","tgn:7005560","tgn:7029392"],"placetype":["aat:300259572"],"id":7359184,"name:xx":"Cruz, Puerto de la"}}
>>>>>>> 03f74aca74312dbeaf24d7e61306dd6a786dc3d0
