{
  "id": 2511428,
  "type": "Feature",
  "properties": {
    "tgn:hierarchy":[
        "tgn:2511428",
        "tgn:1000001",
        "tgn:7012149",
        "tgn:2001706",
        "tgn:7007708",
        "tgn:7029392"
    ],
    "tgn:id":2511428,
    "tgn:name":"Mildred Mine",
    "tgn:placetype":[
        "aat:300000390"
    ]
},
  "bbox": [],
  "geometry": {"coordinates":[-123.1667,42.7333],"type":"Point"}
}