{
  "id": 2435761,
  "type": "Feature",
  "properties": {
    "tgn:hierarchy":[
        "tgn:2435761",
        "tgn:1000001",
        "tgn:7012149",
        "tgn:7007157",
        "tgn:2000191",
        "tgn:7029392"
    ],
    "tgn:id":2435761,
    "tgn:name":"Kettenpom Valley",
    "tgn:placetype":[
        "aat:300008761"
    ]
},
  "bbox": [],
  "geometry": {"coordinates":[-123.4167,40.1167],"type":"Point"}
}