{
  "id": 1115075,
  "type": "Feature",
  "properties": {
    "tgn:hierarchy":[
        "tgn:1115075",
        "tgn:7005667",
        "tgn:1010126",
        "tgn:1000006",
        "tgn:7029392"
    ],
    "tgn:id":1115075,
    "tgn:name":"Asaga Strait",
    "tgn:placetype":[
        "aat:300266559"
    ]
},
  "bbox": [],
  "geometry": {"coordinates":[-169.6667,-14.1833],"type":"Point"}
}