{
  "id": 2533692,
  "type": "Feature",
  "properties": {
    "tgn:hierarchy":[
        "tgn:2533692",
        "tgn:1000001",
        "tgn:2000596",
        "tgn:7012149",
        "tgn:7007253",
        "tgn:7029392"
    ],
    "tgn:id":2533692,
    "tgn:name":"Mustard Lateral",
    "tgn:placetype":[
        "aat:300006075"
    ]
},
  "bbox": [],
  "geometry": {"coordinates":[-95.7833,40.7833],"type":"Point"}
}