{
  "id": 7551352,
  "type": "Feature",
  "properties": {
    "tgn:hierarchy":[
        "tgn:7551352",
        "tgn:1000004",
        "tgn:7000198",
        "tgn:1001894",
        "tgn:7029392"
    ],
    "tgn:id":7551352,
    "tgn:name:en":"D\u012bw\u0101nganj",
    "tgn:placetype":[
        "aat:300008347"
    ]
},
  "bbox": [],
  "geometry": {"coordinates":[77.569362,23.420212],"type":"Point"}
}