{
  "id": 1048553,
  "type": "Feature",
  "properties": {
    "tgn:hierarchy":[
        "tgn:1048553",
        "tgn:7003651",
        "tgn:1000003",
        "tgn:1000088",
        "tgn:7029392"
    ],
    "tgn:id":1048553,
    "tgn:name":"Gre\u00e5ker",
    "tgn:placetype":[
        "aat:300008347"
    ]
},
  "bbox": [],
  "geometry": {"coordinates":[11.0333,59.2667],"type":"Point"}
}