{
  "id": 1102047,
  "type": "Feature",
  "properties": {
    "tgn:hierarchy":[
        "tgn:1102047",
        "tgn:1000001",
        "tgn:7012149",
        "tgn:7013961",
        "tgn:7029392"
    ],
    "tgn:id":1102047,
    "tgn:name":"Spruce Knob-Seneca Rocks National Recreation Area",
    "tgn:placetype":[
        "aat:300000510"
    ]
},
  "bbox": [],
  "geometry": {"coordinates":[-79.2833,38.8667],"type":"Point"}
}