<<<<<<< HEAD
{
  "id": 2254599,
  "type": "Feature",
  "properties": {
    "tgn:hierarchy":[
        "tgn:2254599",
        "tgn:1000001",
        "tgn:7012149",
        "tgn:2001914",
        "tgn:7007825",
        "tgn:7029392"
    ],
    "tgn:id":2254599,
    "tgn:name":"Coon Hollow",
    "tgn:placetype":[
        "aat:300008761"
    ]
},
  "bbox": [],
  "geometry": {"coordinates":[-83.55,35.6167],"type":"Point"}
}
=======
{"geometry":{"type":"Point","coordinates":[-83.550000,35.616700]},"type":"Feature","properties":{"hierarchy":["tgn:2254599","tgn:1000001","tgn:7012149","tgn:2001914","tgn:7007825","tgn:7029392"],"placetype":["aat:300008761"],"id":2254599,"name:xx":"Coon Hollow"}}
>>>>>>> 03f74aca74312dbeaf24d7e61306dd6a786dc3d0
