{
  "id": 7274606,
  "type": "Feature",
  "properties": {
    "tgn:hierarchy":[
        "tgn:7274606",
        "tgn:1000003",
        "tgn:7006951",
        "tgn:7016845",
        "tgn:7029392"
    ],
    "tgn:id":7274606,
    "tgn:name:nl":"Noordwinning Veld",
    "tgn:placetype":[
        "aat:300000401"
    ]
},
  "bbox": [],
  "geometry": {"coordinates":[3.133333,53.25],"type":"Point"}
}