{
  "id": 2661725,
  "type": "Feature",
  "properties": {
    "tgn:hierarchy":[
        "tgn:2661725",
        "tgn:1000001",
        "tgn:2001476",
        "tgn:7012149",
        "tgn:7007709",
        "tgn:7029392"
    ],
    "tgn:id":2661725,
    "tgn:name":"Shuford Pond",
    "tgn:placetype":[
        "aat:300006191"
    ]
},
  "bbox": [],
  "geometry": {"coordinates":[-81.3333,35.8167],"type":"Point"}
}