{
  "id": 2684614,
  "type": "Feature",
  "properties": {
    "tgn:hierarchy":[
        "tgn:2684614",
        "tgn:1000001",
        "tgn:7012149",
        "tgn:1002862",
        "tgn:7007920",
        "tgn:7029392"
    ],
    "tgn:id":2684614,
    "tgn:name":"Spindle Rock",
    "tgn:placetype":[
        "aat:300132348"
    ]
},
  "bbox": [],
  "geometry": {"coordinates":[-122.7833,48.5833],"type":"Point"}
}