{
  "id": 2274473,
  "type": "Feature",
  "properties": {
    "tgn:hierarchy":[
        "tgn:2274473",
        "tgn:1000001",
        "tgn:7012149",
        "tgn:1002659",
        "tgn:7007710",
        "tgn:7029392"
    ],
    "tgn:id":2274473,
    "tgn:name":"Daley Run",
    "tgn:placetype":[
        "aat:300008699"
    ]
},
  "bbox": [],
  "geometry": {"coordinates":[-80.3333,41.2333],"type":"Point"}
}