{
  "id": 7285359,
  "type": "Feature",
  "properties": {
    "tgn:hierarchy":[
        "tgn:7285359",
        "tgn:1001702",
        "tgn:1000049",
        "tgn:1000002",
        "tgn:7029392"
    ],
    "tgn:id":7285359,
    "tgn:name":"Plumper, Bajo",
    "tgn:placetype":[
        "aat:300387036"
    ]
},
  "bbox": [],
  "geometry": {"coordinates":[-73.783333,-52.933333],"type":"Point"}
}