{
  "id": 2345429,
  "type": "Feature",
  "properties": {
    "tgn:hierarchy":[
        "tgn:2345429",
        "tgn:1000001",
        "tgn:7012149",
        "tgn:1003034",
        "tgn:7007826",
        "tgn:7029392"
    ],
    "tgn:id":2345429,
    "tgn:name":"Garner Lake",
    "tgn:placetype":[
        "aat:300006191"
    ]
},
  "bbox": [],
  "geometry": {"coordinates":[-95.4667,32.7167],"type":"Point"}
}