{
  "id": 7480621,
  "type": "Feature",
  "properties": {
    "tgn:hierarchy":[
        "tgn:7480621",
        "tgn:1000004",
        "tgn:7490934",
        "tgn:1000141",
        "tgn:7029392"
    ],
    "tgn:id":7480621,
    "tgn:name":"Longtian Qiao",
    "tgn:placetype":[
        "aat:300007836"
    ]
},
  "bbox": [],
  "geometry": {"coordinates":[120.31551,23.200711],"type":"Point"}
}