{
  "id": 2681824,
  "type": "Feature",
  "properties": {
    "tgn:hierarchy":[
        "tgn:2681824",
        "tgn:1000001",
        "tgn:7012149",
        "tgn:7007712",
        "tgn:7029392"
    ],
    "tgn:id":2681824,
    "tgn:name":"South Santee River",
    "tgn:placetype":[
        "aat:300008707"
    ]
},
  "bbox": [],
  "geometry": {"coordinates":[-79.45,33.2333],"type":"Point"}
}