{
  "id": 7539785,
  "type": "Feature",
  "properties": {
    "tgn:hierarchy":[
        "tgn:7539785",
        "tgn:7001242",
        "tgn:7016833",
        "tgn:7000123",
        "tgn:7029392"
    ],
    "tgn:id":7539785,
    "tgn:name:en":"Nag' el-Garfiya",
    "tgn:placetype":[
        "aat:300008347"
    ]
},
  "bbox": [],
  "geometry": {"coordinates":[32.65,26.183333],"type":"Point"}
}