{
  "id": 1134104,
  "type": "Feature",
  "properties": {
    "tgn:hierarchy":[
        "tgn:1134104",
        "tgn:1000001",
        "tgn:7012149",
        "tgn:7007157",
        "tgn:1002863",
        "tgn:7029392"
    ],
    "tgn:id":1134104,
    "tgn:name":"Paloma Creek",
    "tgn:placetype":[
        "aat:300008706"
    ]
},
  "bbox": [],
  "geometry": {"coordinates":[-120.65,35.4167],"type":"Point"}
}