{
  "id": 7033802,
  "type": "Feature",
  "properties": {
    "tgn:hierarchy":[
        "tgn:7033802",
        "tgn:1000003",
        "tgn:7003236",
        "tgn:1000080",
        "tgn:7029392"
    ],
    "tgn:id":7033802,
    "tgn:name":"Marinnaro, Scoglio",
    "tgn:placetype":[
        "aat:300011692"
    ]
},
  "bbox": [],
  "geometry": {"coordinates":[9.25,44.333333],"type":"Point"}
}