{
  "id": 2667411,
  "type": "Feature",
  "properties": {
    "tgn:hierarchy":[
        "tgn:2667411",
        "tgn:1000001",
        "tgn:7012149",
        "tgn:2001706",
        "tgn:7007708",
        "tgn:7029392"
    ],
    "tgn:id":2667411,
    "tgn:name":"Skip Creek",
    "tgn:placetype":[
        "aat:300008706"
    ]
},
  "bbox": [],
  "geometry": {"coordinates":[-123.7167,43.3333],"type":"Point"}
}