{
  "id": 7187098,
  "type": "Feature",
  "properties": {
    "tgn:hierarchy":[
        "tgn:7187098",
        "tgn:1000003",
        "tgn:7003678",
        "tgn:7000084",
        "tgn:7029392"
    ],
    "tgn:id":7187098,
    "tgn:name":"Haltepunkt Eifa",
    "tgn:placetype":[
        "aat:300007783"
    ]
},
  "bbox": [],
  "geometry": {"coordinates":[8.566667,50.983333],"type":"Point"}
}