{
  "id": 2732093,
  "type": "Feature",
  "properties": {
    "tgn:hierarchy":[
        "tgn:2732093",
        "tgn:1000001",
        "tgn:7012149",
        "tgn:2001457",
        "tgn:7007566",
        "tgn:7029392"
    ],
    "tgn:id":2732093,
    "tgn:name":"Tunnel Hill",
    "tgn:placetype":[
        "aat:300008798"
    ]
},
  "bbox": [],
  "geometry": {"coordinates":[-105.4167,36.6333],"type":"Point"}
}