{
  "id": 1026306,
  "type": "Feature",
  "properties": {
    "tgn:hierarchy":[
        "tgn:1026306",
        "tgn:7003456",
        "tgn:1000003",
        "tgn:1000063",
        "tgn:7018236",
        "tgn:7029392"
    ],
    "tgn:id":1026306,
    "tgn:name":"Baarle-Hertog",
    "tgn:placetype":[
        "aat:300008347"
    ]
},
  "bbox": [],
  "geometry": {"coordinates":[4.933333,51.45],"type":"Point"}
}