{
  "id": 2306509,
  "type": "Feature",
  "properties": {
    "tgn:hierarchy":[
        "tgn:2306509",
        "tgn:1000001",
        "tgn:7012149",
        "tgn:2002113",
        "tgn:7007827",
        "tgn:7029392"
    ],
    "tgn:id":2306509,
    "tgn:name":"East Fork Deep Creek",
    "tgn:placetype":[
        "aat:300008706"
    ]
},
  "bbox": [],
  "geometry": {"coordinates":[-112.8167,37.5333],"type":"Point"}
}