<<<<<<< HEAD
{
  "id": 7357943,
  "type": "Feature",
  "properties": {
    "tgn:hierarchy":[
        "tgn:7357943",
        "tgn:1001835",
        "tgn:1000001",
        "tgn:7005560",
        "tgn:7029392"
    ],
    "tgn:id":7357943,
    "tgn:name":"Colonia Herrera",
    "tgn:placetype":[
        "aat:300000745"
    ]
},
  "bbox": [],
  "geometry": {"coordinates":[-117.066667,32.516667],"type":"Point"}
}
=======
{"geometry":{"type":"Point","coordinates":[-117.066667,32.516667]},"type":"Feature","properties":{"hierarchy":["tgn:7357943","tgn:1001835","tgn:1000001","tgn:7005560","tgn:7029392"],"placetype":["aat:300000745"],"id":7357943,"name:xx":"Colonia Herrera"}}
>>>>>>> 03f74aca74312dbeaf24d7e61306dd6a786dc3d0
