{
  "id": 7052592,
  "type": "Feature",
  "properties": {
    "tgn:hierarchy":[
        "tgn:7052592",
        "tgn:1003506",
        "tgn:1000003",
        "tgn:7002993",
        "tgn:1000080",
        "tgn:7029392"
    ],
    "tgn:id":7052592,
    "tgn:name":"Ipplis",
    "tgn:placetype":[
        "aat:300008347"
    ]
},
  "bbox": [],
  "geometry": {"coordinates":[13.414167,46.045278],"type":"Point"}
}