{
  "id": 2225209,
  "type": "Feature",
  "properties": {
    "tgn:hierarchy":[
        "tgn:2225209",
        "tgn:1000001",
        "tgn:7012149",
        "tgn:1002567",
        "tgn:7007240",
        "tgn:7029392"
    ],
    "tgn:id":2225209,
    "tgn:name":"Castle Hill",
    "tgn:placetype":[
        "aat:300008347"
    ]
},
  "bbox": [],
  "geometry": {"coordinates":[-81.6833,28.5333],"type":"Point"}
}