{
  "id": 2383193,
  "type": "Feature",
  "properties": {
    "tgn:hierarchy":[
        "tgn:2383193",
        "tgn:1000001",
        "tgn:2000925",
        "tgn:7012149",
        "tgn:7007515",
        "tgn:7029392"
    ],
    "tgn:id":2383193,
    "tgn:name":"Heal Pond",
    "tgn:placetype":[
        "aat:300008680"
    ]
},
  "bbox": [],
  "geometry": {"coordinates":[-69.7167,43.8833],"type":"Point"}
}