{
  "id": 7496238,
  "type": "Feature",
  "properties": {
    "tgn:hierarchy":[
        "tgn:7496238",
        "tgn:1000004",
        "tgn:7001014",
        "tgn:1000141",
        "tgn:7029392"
    ],
    "tgn:id":7496238,
    "tgn:name":"Changnan",
    "tgn:placetype":[
        "aat:300387033"
    ]
},
  "bbox": [],
  "geometry": {"coordinates":[120.260651,23.697684],"type":"Point"}
}