{
  "id": 1099985,
  "type": "Feature",
  "properties": {
    "tgn:hierarchy":[
        "tgn:1099985",
        "tgn:7003024",
        "tgn:1000003",
        "tgn:1000062",
        "tgn:7029392"
    ],
    "tgn:id":1099985,
    "tgn:name":"Gurk",
    "tgn:placetype":[
        "aat:300007466"
    ]
},
  "bbox": [],
  "geometry": {"coordinates":[14.25,46.8667],"type":"Point"}
}