{
  "id": 2700290,
  "type": "Feature",
  "properties": {
    "tgn:hierarchy":[
        "tgn:2700290",
        "tgn:1000001",
        "tgn:1002260",
        "tgn:7012149",
        "tgn:7007920",
        "tgn:7029392"
    ],
    "tgn:id":2700290,
    "tgn:name":"Sturm Creek",
    "tgn:placetype":[
        "aat:300008706"
    ]
},
  "bbox": [],
  "geometry": {"coordinates":[-120.7833,48.4167],"type":"Point"}
}