{
  "id": 7279986,
  "type": "Feature",
  "properties": {
    "tgn:hierarchy":[
        "tgn:7279986",
        "tgn:1001702",
        "tgn:1000049",
        "tgn:1000002",
        "tgn:7029392"
    ],
    "tgn:id":7279986,
    "tgn:name":"Redwood, Isla",
    "tgn:placetype":[
        "aat:300008791"
    ]
},
  "bbox": [],
  "geometry": {"coordinates":[-73.716667,-53.333333],"type":"Point"}
}