{
  "id": 2101781,
  "type": "Feature",
  "properties": {
    "tgn:hierarchy":[
        "tgn:2101781",
        "tgn:1000001",
        "tgn:7012149",
        "tgn:2001898",
        "tgn:7007825",
        "tgn:7029392"
    ],
    "tgn:id":2101781,
    "tgn:name":"Tellico Plains",
    "tgn:placetype":[
        "aat:300008347"
    ]
},
  "bbox": [],
  "geometry": {"coordinates":[-84.2833,35.35],"type":"Point"}
}