{
  "id": 7295087,
  "type": "Feature",
  "properties": {
    "tgn:hierarchy":[
        "tgn:7295087",
        "tgn:7002834",
        "tgn:1000003",
        "tgn:7002786",
        "tgn:1000095",
        "tgn:7029392"
    ],
    "tgn:id":7295087,
    "tgn:name":"Crego, Punta do",
    "tgn:placetype":[
        "aat:300386846"
    ]
},
  "bbox": [],
  "geometry": {"coordinates":[-8.75,42.265278],"type":"Point"}
}