{
  "id": 7422341,
  "type": "Feature",
  "properties": {
    "tgn:hierarchy":[
        "tgn:7422341",
        "tgn:1000001",
        "tgn:7005601",
        "tgn:7005560",
        "tgn:7029392"
    ],
    "tgn:id":7422341,
    "tgn:name":"Mesa de Fr\u00eds",
    "tgn:placetype":[
        "aat:300008347"
    ]
},
  "bbox": [],
  "geometry": {"coordinates":[-102.958333,21.45],"type":"Point"}
}