{
  "id": 7288120,
  "type": "Feature",
  "properties": {
    "tgn:hierarchy":[
        "tgn:7288120",
        "tgn:1001630",
        "tgn:1000049",
        "tgn:1000002",
        "tgn:7029392"
    ],
    "tgn:id":7288120,
    "tgn:name":"Jorquera, R\u00edo",
    "tgn:placetype":[
        "aat:300008699"
    ]
},
  "bbox": [],
  "geometry": {"coordinates":[-69.966667,-28.05],"type":"Point"}
}