{
  "id": 2272421,
  "type": "Feature",
  "properties": {
    "tgn:hierarchy":[
        "tgn:2272421",
        "tgn:1000001",
        "tgn:7012149",
        "tgn:2001308",
        "tgn:7007524",
        "tgn:7029392"
    ],
    "tgn:id":2272421,
    "tgn:name":"Curtis Gulch",
    "tgn:placetype":[
        "aat:300008761"
    ]
},
  "bbox": [],
  "geometry": {"coordinates":[-109.6833,45.6667],"type":"Point"}
}