{
  "id": 7122065,
  "type": "Feature",
  "properties": {
    "tgn:hierarchy":[
        "tgn:7122065",
        "tgn:1000003",
        "tgn:7003676",
        "tgn:7000084",
        "tgn:7029392"
    ],
    "tgn:id":7122065,
    "tgn:name":"Neu Wulmstorf",
    "tgn:placetype":[
        "aat:300008347"
    ]
},
  "bbox": [],
  "geometry": {"coordinates":[9.083333,52.916667],"type":"Point"}
}