{
  "id": 7026599,
  "type": "Feature",
  "properties": {
    "tgn:hierarchy":[
        "tgn:7026599",
        "tgn:7002445",
        "tgn:1000003",
        "tgn:7008132",
        "tgn:7008591",
        "tgn:7029392"
    ],
    "tgn:id":7026599,
    "tgn:name:en":"Coln Rogers",
    "tgn:placetype":[
        "aat:300008347",
        "aat:300008372"
    ]
},
  "bbox": [],
  "geometry": {"coordinates":[-1.883333,51.766667],"type":"Point"}
}