{
  "id": 7458315,
  "type": "Feature",
  "properties": {
    "tgn:hierarchy":[
        "tgn:7458315",
        "tgn:7002445",
        "tgn:1000003",
        "tgn:7008166",
        "tgn:7008591",
        "tgn:7029392"
    ],
    "tgn:id":7458315,
    "tgn:name:en":"Newton upon Ouse",
    "tgn:placetype":[
        "aat:300008347"
    ]
},
  "bbox": [],
  "geometry": {"coordinates":[-1.216667,54.033333],"type":"Point"}
}