{
  "id": 2690628,
  "type": "Feature",
  "properties": {
    "tgn:hierarchy":[
        "tgn:2690628",
        "tgn:1000001",
        "tgn:2001411",
        "tgn:7012149",
        "tgn:7007526",
        "tgn:7029392"
    ],
    "tgn:id":2690628,
    "tgn:name":"Stampede",
    "tgn:placetype":[
        "aat:300055621"
    ]
},
  "bbox": [],
  "geometry": {"coordinates":[-116.1333,40.7167],"type":"Point"}
}