{
  "id": 2428562,
  "type": "Feature",
  "properties": {
    "tgn:hierarchy":[
        "tgn:2428562",
        "tgn:1000001",
        "tgn:7012149",
        "tgn:7007522",
        "tgn:7029392"
    ],
    "tgn:id":2428562,
    "tgn:name":"Jug Lake",
    "tgn:placetype":[
        "aat:300008680"
    ]
},
  "bbox": [],
  "geometry": {"coordinates":[-90.45,33.3833],"type":"Point"}
}