{
  "id": 2161716,
  "type": "Feature",
  "properties": {
    "tgn:hierarchy":[
        "tgn:2161716",
        "tgn:1000001",
        "tgn:7012149",
        "tgn:2000354",
        "tgn:7007248",
        "tgn:7029392"
    ],
    "tgn:id":2161716,
    "tgn:name":"Belle Vista",
    "tgn:placetype":[
        "aat:300008347"
    ]
},
  "bbox": [],
  "geometry": {"coordinates":[-81.7333,31.35],"type":"Point"}
}