{
  "id": 2325969,
  "type": "Feature",
  "properties": {
    "tgn:hierarchy":[
        "tgn:2325969",
        "tgn:1000001",
        "tgn:7012149",
        "tgn:2001763",
        "tgn:7007712",
        "tgn:7029392"
    ],
    "tgn:id":2325969,
    "tgn:name":"Fifteenmile Creek",
    "tgn:placetype":[
        "aat:300008706"
    ]
},
  "bbox": [],
  "geometry": {"coordinates":[-82.7167,34.7667],"type":"Point"}
}