{
  "id": 7300275,
  "type": "Feature",
  "properties": {
    "tgn:hierarchy":[
        "tgn:7300275",
        "tgn:7002826",
        "tgn:7001158",
        "tgn:1000003",
        "tgn:1000095",
        "tgn:7029392"
    ],
    "tgn:id":7300275,
    "tgn:name":"Templarios, R\u00edo de los",
    "tgn:placetype":[
        "aat:300008699"
    ]
},
  "bbox": [],
  "geometry": {"coordinates":[-4.95,42.266667],"type":"Point"}
}