{
  "id": 2536233,
  "type": "Feature",
  "properties": {
    "tgn:hierarchy":[
        "tgn:2536233",
        "tgn:1000001",
        "tgn:7006451",
        "tgn:2000092",
        "tgn:7012149",
        "tgn:7029392"
    ],
    "tgn:id":2536233,
    "tgn:name":"Navajo Mountain Mission",
    "tgn:placetype":[
        "aat:300008347"
    ]
},
  "bbox": [],
  "geometry": {"coordinates":[-110.7667,36.9333],"type":"Point"}
}