{
  "id": 7371051,
  "type": "Feature",
  "properties": {
    "tgn:hierarchy":[
        "tgn:7371051",
        "tgn:1000001",
        "tgn:7005595",
        "tgn:7005560",
        "tgn:7029392"
    ],
    "tgn:id":7371051,
    "tgn:name":"Guiribampo",
    "tgn:placetype":[
        "aat:300008347"
    ]
},
  "bbox": [],
  "geometry": {"coordinates":[-108.816667,25.816667],"type":"Point"}
}