{
  "id": 7565093,
  "type": "Feature",
  "properties": {
    "tgn:hierarchy":[
        "tgn:7565093",
        "tgn:1000004",
        "tgn:7000198",
        "tgn:1001894",
        "tgn:7029392"
    ],
    "tgn:id":7565093,
    "tgn:name:en":"Tar\u012bchha ka Pah\u0101r",
    "tgn:placetype":[
        "aat:300008777"
    ]
},
  "bbox": [],
  "geometry": {"coordinates":[79.203881,24.816584],"type":"Point"}
}