{
  "id": 7351067,
  "type": "Feature",
  "properties": {
    "tgn:hierarchy":[
        "tgn:7351067",
        "tgn:1000001",
        "tgn:7005601",
        "tgn:7005560",
        "tgn:7029392"
    ],
    "tgn:id":7351067,
    "tgn:name":"Arcia, Picacho de",
    "tgn:placetype":[
        "aat:300008795"
    ]
},
  "bbox": [],
  "geometry": {"coordinates":[-101.683333,24.383333],"type":"Point"}
}