<<<<<<< HEAD
{
  "id": 7351067,
  "type": "Feature",
  "properties": {
    "tgn:hierarchy":[
        "tgn:7351067",
        "tgn:1000001",
        "tgn:7005601",
        "tgn:7005560",
        "tgn:7029392"
    ],
    "tgn:id":7351067,
    "tgn:name":"Arcia, Picacho de",
    "tgn:placetype":[
        "aat:300008795"
    ]
},
  "bbox": [],
  "geometry": {"coordinates":[-101.683333,24.383333],"type":"Point"}
}
=======
{"geometry":{"type":"Point","coordinates":[-101.683333,24.383333]},"type":"Feature","properties":{"hierarchy":["tgn:7351067","tgn:1000001","tgn:7005601","tgn:7005560","tgn:7029392"],"placetype":["aat:300008795"],"id":7351067,"name:xx":"Arcia, Picacho de"}}
>>>>>>> 03f74aca74312dbeaf24d7e61306dd6a786dc3d0
