{
  "id": 2524125,
  "type": "Feature",
  "properties": {
    "tgn:hierarchy":[
        "tgn:2524125",
        "tgn:1000001",
        "tgn:7006451",
        "tgn:7012149",
        "tgn:7029392"
    ],
    "tgn:id":2524125,
    "tgn:name":"Morgan City Wash",
    "tgn:placetype":[
        "aat:300008699"
    ]
},
  "bbox": [],
  "geometry": {"coordinates":[-112.4333,33.9333],"type":"Point"}
}