{
  "id": 7392764,
  "type": "Feature",
  "properties": {
    "tgn:hierarchy":[
        "tgn:7392764",
        "tgn:1000001",
        "tgn:7005592",
        "tgn:7005560",
        "tgn:7029392"
    ],
    "tgn:id":7392764,
    "tgn:name":"San Jer\u00f3nimo Xayacatl\u00e1n",
    "tgn:placetype":[
        "aat:300008347"
    ]
},
  "bbox": [],
  "geometry": {"coordinates":[-97.966667,18.25],"type":"Point"}
}