{
  "id": 2765138,
  "type": "Feature",
  "properties": {
    "tgn:hierarchy":[
        "tgn:2765138",
        "tgn:1000001",
        "tgn:7016172",
        "tgn:7012149",
        "tgn:2000147",
        "tgn:7029392"
    ],
    "tgn:id":2765138,
    "tgn:name":"Whispering Pines Addition",
    "tgn:placetype":[
        "aat:300008347"
    ]
},
  "bbox": [],
  "geometry": {"coordinates":[-91.9333,34.95],"type":"Point"}
}