<<<<<<< HEAD
{
  "id": 2408119,
  "type": "Feature",
  "properties": {
    "tgn:hierarchy":[
        "tgn:2408119",
        "tgn:1000001",
        "tgn:7012149",
        "tgn:2001309",
        "tgn:7007524",
        "tgn:7029392"
    ],
    "tgn:id":2408119,
    "tgn:name":"Hurricane Mountain",
    "tgn:placetype":[
        "aat:300008798"
    ]
},
  "bbox": [],
  "geometry": {"coordinates":[-112.85,48.1],"type":"Point"}
}
=======
{"geometry":{"type":"Point","coordinates":[-112.850000,48.100000]},"type":"Feature","properties":{"hierarchy":["tgn:2408119","tgn:1000001","tgn:7012149","tgn:2001309","tgn:7007524","tgn:7029392"],"placetype":["aat:300008798"],"id":2408119,"name:xx":"Hurricane Mountain"}}
>>>>>>> 03f74aca74312dbeaf24d7e61306dd6a786dc3d0
