<<<<<<< HEAD
{
  "id": 7117373,
  "type": "Feature",
  "properties": {
    "tgn:hierarchy":[
        "tgn:7117373",
        "tgn:7003692",
        "tgn:1000003",
        "tgn:7000084",
        "tgn:7029392"
    ],
    "tgn:id":7117373,
    "tgn:name":"Oedenges\u00e4\u00df",
    "tgn:placetype":[
        "aat:300008347"
    ]
},
  "bbox": [],
  "geometry": {"coordinates":[9.466667,49.733333],"type":"Point"}
}
=======
{"geometry":{"type":"Point","coordinates":[9.466667,49.733333]},"type":"Feature","properties":{"hierarchy":["tgn:7117373","tgn:7003692","tgn:1000003","tgn:7000084","tgn:7029392"],"placetype":["aat:300008347"],"id":7117373,"name:xx":"Oedenges\u00e4\u00df"}}
>>>>>>> 03f74aca74312dbeaf24d7e61306dd6a786dc3d0
