{
  "id": 7554603,
  "type": "Feature",
  "properties": {
    "tgn:hierarchy":[
        "tgn:7554603",
        "tgn:7001819",
        "tgn:1000004",
        "tgn:7000198",
        "tgn:7029392"
    ],
    "tgn:id":7554603,
    "tgn:name:en":"Mepumna",
    "tgn:placetype":[
        "aat:300008347"
    ]
},
  "bbox": [],
  "geometry": {"coordinates":[96.604481,28.10839],"type":"Point"}
}