{
  "id": 2499968,
  "type": "Feature",
  "properties": {
    "tgn:hierarchy":[
        "tgn:2499968",
        "tgn:1000001",
        "tgn:7012149",
        "tgn:1002995",
        "tgn:7007710",
        "tgn:7029392"
    ],
    "tgn:id":2499968,
    "tgn:name":"McCracken",
    "tgn:placetype":[
        "aat:300008347"
    ]
},
  "bbox": [],
  "geometry": {"coordinates":[-80.2333,40.0667],"type":"Point"}
}