<<<<<<< HEAD
{
  "id": 7024067,
  "type": "Feature",
  "properties": {
    "tgn:hierarchy":[
        "tgn:7024067",
        "tgn:1000004",
        "tgn:7024036",
        "tgn:7006651",
        "tgn:7029392"
    ],
    "tgn:id":7024067,
    "tgn:name:en":"Gugark'",
    "tgn:placetype":[
        "aat:300008347",
        "aat:300387220",
        "aat:300008375"
    ]
},
  "bbox": [],
  "geometry": {"coordinates":[44.542,40.807],"type":"Point"}
}
=======
{"geometry":{"type":"Point","coordinates":[44.542000,40.807000]},"type":"Feature","properties":{"hierarchy":["tgn:7024067","tgn:1000004","tgn:7024036","tgn:7006651","tgn:7029392"],"placetype":["aat:300008347","aat:300387220","aat:300008375"],"name:en":"Gugark'","id":7024067}}
>>>>>>> 03f74aca74312dbeaf24d7e61306dd6a786dc3d0
