{
  "id": 7513699,
  "type": "Feature",
  "properties": {
    "tgn:hierarchy":[
        "tgn:7513699",
        "tgn:1009227",
        "tgn:1000226",
        "tgn:1000006",
        "tgn:7016850",
        "tgn:7029392"
    ],
    "tgn:id":7513699,
    "tgn:name:en":"Fox River",
    "tgn:placetype":[
        "aat:300008699"
    ]
},
  "bbox": [],
  "geometry": {"coordinates":[169.916667,-43.466667],"type":"Point"}
}