{
  "id": 7243194,
  "type": "Feature",
  "properties": {
    "tgn:hierarchy":[
        "tgn:7243194",
        "tgn:7018239",
        "tgn:1000003",
        "tgn:1000063",
        "tgn:7018236",
        "tgn:7029392"
    ],
    "tgn:id":7243194,
    "tgn:name":"Krekelberg",
    "tgn:placetype":[
        "aat:300008347"
    ]
},
  "bbox": [],
  "geometry": {"coordinates":[4.75,50.85],"type":"Point"}
}