{
  "id": 2158754,
  "type": "Feature",
  "properties": {
    "tgn:hierarchy":[
        "tgn:2158754",
        "tgn:2001625",
        "tgn:1000001",
        "tgn:7012149",
        "tgn:7007707",
        "tgn:7029392"
    ],
    "tgn:id":2158754,
    "tgn:name":"Beck Creek",
    "tgn:placetype":[
        "aat:300008706"
    ]
},
  "bbox": [],
  "geometry": {"coordinates":[-96.0333,34.5667],"type":"Point"}
}