<<<<<<< HEAD
{
  "id": 2158754,
  "type": "Feature",
  "properties": {
    "tgn:hierarchy":[
        "tgn:2158754",
        "tgn:2001625",
        "tgn:1000001",
        "tgn:7012149",
        "tgn:7007707",
        "tgn:7029392"
    ],
    "tgn:id":2158754,
    "tgn:name":"Beck Creek",
    "tgn:placetype":[
        "aat:300008706"
    ]
},
  "bbox": [],
  "geometry": {"coordinates":[-96.0333,34.5667],"type":"Point"}
}
=======
{"geometry":{"type":"Point","coordinates":[-96.033300,34.566700]},"type":"Feature","properties":{"hierarchy":["tgn:2158754","tgn:2001625","tgn:1000001","tgn:7012149","tgn:7007707","tgn:7029392"],"placetype":["aat:300008706"],"id":2158754,"name:xx":"Beck Creek"}}
>>>>>>> 03f74aca74312dbeaf24d7e61306dd6a786dc3d0
