{
  "id": 7475379,
  "type": "Feature",
  "properties": {
    "tgn:hierarchy":[
        "tgn:7475379",
        "tgn:7001004",
        "tgn:1000004",
        "tgn:1000141",
        "tgn:7029392"
    ],
    "tgn:id":7475379,
    "tgn:name":"Wennan Cun",
    "tgn:placetype":[
        "aat:300387173"
    ]
},
  "bbox": [],
  "geometry": {"coordinates":[120.254167,22.850278],"type":"Point"}
}