<<<<<<< HEAD
{
  "id": 7475379,
  "type": "Feature",
  "properties": {
    "tgn:hierarchy":[
        "tgn:7475379",
        "tgn:7001004",
        "tgn:1000004",
        "tgn:1000141",
        "tgn:7029392"
    ],
    "tgn:id":7475379,
    "tgn:name":"Wennan Cun",
    "tgn:placetype":[
        "aat:300387173"
    ]
},
  "bbox": [],
  "geometry": {"coordinates":[120.254167,22.850278],"type":"Point"}
}
=======
{"geometry":{"type":"Point","coordinates":[120.254167,22.850278]},"type":"Feature","properties":{"hierarchy":["tgn:7475379","tgn:7001004","tgn:1000004","tgn:1000141","tgn:7029392"],"placetype":["aat:300387173"],"id":7475379,"name:xx":"Wennan Cun"}}
>>>>>>> 03f74aca74312dbeaf24d7e61306dd6a786dc3d0
