{
  "id": 2292552,
  "type": "Feature",
  "properties": {
    "tgn:hierarchy":[
        "tgn:2292552",
        "tgn:1000001",
        "tgn:7012149",
        "tgn:2001297",
        "tgn:7007524",
        "tgn:7029392"
    ],
    "tgn:id":2292552,
    "tgn:name":"Doonan Gulch",
    "tgn:placetype":[
        "aat:300008761"
    ]
},
  "bbox": [],
  "geometry": {"coordinates":[-105.9167,45.4667],"type":"Point"}
}