{
  "id": 7351006,
  "type": "Feature",
  "properties": {
    "tgn:hierarchy":[
        "tgn:7351006",
        "tgn:1000001",
        "tgn:7005595",
        "tgn:7005560",
        "tgn:7029392"
    ],
    "tgn:id":7351006,
    "tgn:name":"Boca del Rio",
    "tgn:placetype":[
        "aat:300008347"
    ]
},
  "bbox": [],
  "geometry": {"coordinates":[-108.483333,25.283333],"type":"Point"}
}