{
  "id": 2169324,
  "type": "Feature",
  "properties": {
    "tgn:hierarchy":[
        "tgn:2169324",
        "tgn:1000001",
        "tgn:7012149",
        "tgn:1002990",
        "tgn:7007708",
        "tgn:7029392"
    ],
    "tgn:id":2169324,
    "tgn:name":"Big Lake",
    "tgn:placetype":[
        "aat:300008680"
    ]
},
  "bbox": [],
  "geometry": {"coordinates":[-120.4833,44.9667],"type":"Point"}
}