{
  "id": 2192849,
  "type": "Feature",
  "properties": {
    "tgn:hierarchy":[
        "tgn:2192849",
        "tgn:1000001",
        "tgn:7012149",
        "tgn:7007713",
        "tgn:7029392"
    ],
    "tgn:id":2192849,
    "tgn:name":"Brave Bull Creek",
    "tgn:placetype":[
        "aat:300008706"
    ]
},
  "bbox": [],
  "geometry": {"coordinates":[-101.25,43.8333],"type":"Point"}
}