{
  "id": 2373310,
  "type": "Feature",
  "properties": {
    "tgn:hierarchy":[
        "tgn:2373310",
        "tgn:1000001",
        "tgn:7012149",
        "tgn:2001303",
        "tgn:7007524",
        "tgn:7029392"
    ],
    "tgn:id":2373310,
    "tgn:name":"Halvorson Hot Spring",
    "tgn:placetype":[
        "aat:300008697"
    ]
},
  "bbox": [],
  "geometry": {"coordinates":[-106.9167,46.7667],"type":"Point"}
}