{
  "id": 7399087,
  "type": "Feature",
  "properties": {
    "tgn:hierarchy":[
        "tgn:7399087",
        "tgn:1000001",
        "tgn:1001893",
        "tgn:7005560",
        "tgn:7029392"
    ],
    "tgn:id":7399087,
    "tgn:name":"Ocoyotepec Centro",
    "tgn:placetype":[
        "aat:300008347"
    ]
},
  "bbox": [],
  "geometry": {"coordinates":[-99.844444,19.494722],"type":"Point"}
}