{
  "id": 1057749,
  "type": "Feature",
  "properties": {
    "tgn:hierarchy":[
        "tgn:1057749",
        "tgn:7011450",
        "tgn:1000004",
        "tgn:7014786",
        "tgn:7029392"
    ],
    "tgn:id":1057749,
    "tgn:name":"Novorossiyskiy",
    "tgn:placetype":[
        "aat:300008347"
    ]
},
  "bbox": [],
  "geometry": {"coordinates":[57.95,50.2333],"type":"Point"}
}