<<<<<<< HEAD
{
  "id": 2158118,
  "type": "Feature",
  "properties": {
    "tgn:hierarchy":[
        "tgn:2158118",
        "tgn:1000001",
        "tgn:7012149",
        "tgn:1002986",
        "tgn:7007568",
        "tgn:7029392"
    ],
    "tgn:id":2158118,
    "tgn:name":"Beaver Pond",
    "tgn:placetype":[
        "aat:300008680"
    ]
},
  "bbox": [],
  "geometry": {"coordinates":[-73.7167,43.4833],"type":"Point"}
}
=======
{"geometry":{"type":"Point","coordinates":[-73.716700,43.483300]},"type":"Feature","properties":{"hierarchy":["tgn:2158118","tgn:1000001","tgn:7012149","tgn:1002986","tgn:7007568","tgn:7029392"],"placetype":["aat:300008680"],"id":2158118,"name:xx":"Beaver Pond"}}
>>>>>>> 03f74aca74312dbeaf24d7e61306dd6a786dc3d0
