{
  "id": 2158118,
  "type": "Feature",
  "properties": {
    "tgn:hierarchy":[
        "tgn:2158118",
        "tgn:1000001",
        "tgn:7012149",
        "tgn:1002986",
        "tgn:7007568",
        "tgn:7029392"
    ],
    "tgn:id":2158118,
    "tgn:name":"Beaver Pond",
    "tgn:placetype":[
        "aat:300008680"
    ]
},
  "bbox": [],
  "geometry": {"coordinates":[-73.7167,43.4833],"type":"Point"}
}