{
  "id": 1132680,
  "type": "Feature",
  "properties": {
    "tgn:hierarchy":[
        "tgn:1132680",
        "tgn:1000001",
        "tgn:7005589",
        "tgn:7005560",
        "tgn:7029392"
    ],
    "tgn:id":1132680,
    "tgn:name":"Camar\u00f3n",
    "tgn:placetype":[
        "aat:300266554",
        "aat:300008706",
        "aat:300008699"
    ]
},
  "bbox": [],
  "geometry": {"coordinates":[-99.963,27.116],"type":"Point"}
}