{
  "id": 2214526,
  "type": "Feature",
  "properties": {
    "tgn:hierarchy":[
        "tgn:2214526",
        "tgn:1000001",
        "tgn:7012149",
        "tgn:2000792",
        "tgn:7007255",
        "tgn:7029392"
    ],
    "tgn:id":2214526,
    "tgn:name":"Caldwell Creek",
    "tgn:placetype":[
        "aat:300008706"
    ]
},
  "bbox": [],
  "geometry": {"coordinates":[-88.5833,36.5167],"type":"Point"}
}