{
  "id": 2509267,
  "type": "Feature",
  "properties": {
    "tgn:hierarchy":[
        "tgn:2509267",
        "tgn:1000001",
        "tgn:7012149",
        "tgn:2002115",
        "tgn:7007827",
        "tgn:7029392"
    ],
    "tgn:id":2509267,
    "tgn:name":"Middle Fork Peterson Creek",
    "tgn:placetype":[
        "aat:300008706"
    ]
},
  "bbox": [],
  "geometry": {"coordinates":[-111.8167,41.0833],"type":"Point"}
}