{
  "id": 7415380,
  "type": "Feature",
  "properties": {
    "tgn:hierarchy":[
        "tgn:7415380",
        "tgn:7005584",
        "tgn:1000001",
        "tgn:7005560",
        "tgn:7029392"
    ],
    "tgn:id":7415380,
    "tgn:name":"Presa El Carrizal",
    "tgn:placetype":[
        "aat:300006191"
    ]
},
  "bbox": [],
  "geometry": {"coordinates":[-100.5625,20.871667],"type":"Point"}
}