{
  "id": 2492361,
  "type": "Feature",
  "properties": {
    "tgn:hierarchy":[
        "tgn:2492361",
        "tgn:1002366",
        "tgn:1000001",
        "tgn:7012149",
        "tgn:7007159",
        "tgn:7029392"
    ],
    "tgn:id":2492361,
    "tgn:name":"Margerie Lake Reservoir",
    "tgn:placetype":[
        "aat:300006191"
    ]
},
  "bbox": [],
  "geometry": {"coordinates":[-73.4667,41.4333],"type":"Point"}
}