{
  "id": 2381052,
  "type": "Feature",
  "properties": {
    "tgn:hierarchy":[
        "tgn:2381052",
        "tgn:7006450",
        "tgn:1000001",
        "tgn:7012149",
        "tgn:2000086",
        "tgn:7029392"
    ],
    "tgn:id":2381052,
    "tgn:name":"Hawkins Glacier",
    "tgn:placetype":[
        "aat:300008835"
    ]
},
  "bbox": [],
  "geometry": {"coordinates":[-141.8833,61.2167],"type":"Point"}
}