{
  "id": 1010332,
  "type": "Feature",
  "properties": {
    "tgn:hierarchy":[
        "tgn:1010332",
        "tgn:1000004",
        "tgn:1001567",
        "tgn:1000135",
        "tgn:7029392"
    ],
    "tgn:id":1010332,
    "tgn:name":"Tawitawi Group",
    "tgn:placetype":[
        "aat:300386853"
    ]
},
  "bbox": [],
  "geometry": {"coordinates":[120.25,5.1667],"type":"Point"}
}