{
  "id": 2176213,
  "type": "Feature",
  "properties": {
    "tgn:hierarchy":[
        "tgn:2176213",
        "tgn:1000001",
        "tgn:7006451",
        "tgn:2000094",
        "tgn:7012149",
        "tgn:7029392"
    ],
    "tgn:id":2176213,
    "tgn:name":"Black Hills",
    "tgn:placetype":[
        "aat:300008798"
    ]
},
  "bbox": [],
  "geometry": {"coordinates":[-109.9333,33.0667],"type":"Point"}
}