{
  "id": 1037996,
  "type": "Feature",
  "properties": {
    "tgn:hierarchy":[
        "tgn:1037996",
        "tgn:1000003",
        "tgn:7003685",
        "tgn:7000084",
        "tgn:7029392"
    ],
    "tgn:id":1037996,
    "tgn:name":"Wilkau-Hasslau",
    "tgn:placetype":[
        "aat:300008347"
    ]
},
  "bbox": [],
  "geometry": {"coordinates":[12.5167,50.6667],"type":"Point"}
}