<<<<<<< HEAD
{
  "id": 7111673,
  "type": "Feature",
  "properties": {
    "tgn:hierarchy":[
        "tgn:7111673",
        "tgn:1000003",
        "tgn:7000094",
        "tgn:7000084",
        "tgn:7029392"
    ],
    "tgn:id":7111673,
    "tgn:name":"Richtgraben",
    "tgn:placetype":[
        "aat:300266560"
    ]
},
  "bbox": [],
  "geometry": {"coordinates":[13.8,53.85],"type":"Point"}
}
=======
{"geometry":{"type":"Point","coordinates":[13.800000,53.850000]},"type":"Feature","properties":{"hierarchy":["tgn:7111673","tgn:1000003","tgn:7000094","tgn:7000084","tgn:7029392"],"placetype":["aat:300266560"],"id":7111673,"name:xx":"Richtgraben"}}
>>>>>>> 03f74aca74312dbeaf24d7e61306dd6a786dc3d0
