{
  "id": 7184358,
  "type": "Feature",
  "properties": {
    "tgn:hierarchy":[
        "tgn:7184358",
        "tgn:1000003",
        "tgn:7003682",
        "tgn:7000084",
        "tgn:7029392"
    ],
    "tgn:id":7184358,
    "tgn:name":"Gierschnach",
    "tgn:placetype":[
        "aat:300008347"
    ]
},
  "bbox": [],
  "geometry": {"coordinates":[7.35,50.266667],"type":"Point"}
}