{
  "id": 7424093,
  "type": "Feature",
  "properties": {
    "tgn:hierarchy":[
        "tgn:7424093",
        "tgn:1000001",
        "tgn:7005597",
        "tgn:7005560",
        "tgn:7029392"
    ],
    "tgn:id":7424093,
    "tgn:name":"La Loca, Laguna",
    "tgn:placetype":[
        "aat:300008680"
    ]
},
  "bbox": [],
  "geometry": {"coordinates":[-99.333333,22.333333],"type":"Point"}
}