{
  "id": 2491986,
  "type": "Feature",
  "properties": {
    "tgn:hierarchy":[
        "tgn:2491986",
        "tgn:1000001",
        "tgn:7012149",
        "tgn:2002186",
        "tgn:7007919",
        "tgn:7029392"
    ],
    "tgn:id":2491986,
    "tgn:name":"Marble Spring",
    "tgn:placetype":[
        "aat:300008697"
    ]
},
  "bbox": [],
  "geometry": {"coordinates":[-79.4333,37.5667],"type":"Point"}
}