{
  "id": 7310376,
  "type": "Feature",
  "properties": {
    "tgn:hierarchy":[
        "tgn:7310376",
        "tgn:1001623",
        "tgn:1000049",
        "tgn:1000002",
        "tgn:7029392"
    ],
    "tgn:id":7310376,
    "tgn:name":"Nimrod, Puerto",
    "tgn:placetype":[
        "aat:300132317"
    ]
},
  "bbox": [],
  "geometry": {"coordinates":[-75.55,-48.366667],"type":"Point"}
}