{
  "id": 2527847,
  "type": "Feature",
  "properties": {
    "tgn:hierarchy":[
        "tgn:2527847",
        "tgn:1000001",
        "tgn:7012149",
        "tgn:1003044",
        "tgn:7007708",
        "tgn:7029392"
    ],
    "tgn:id":2527847,
    "tgn:name":"Mountain House",
    "tgn:placetype":[
        "aat:300008347"
    ]
},
  "bbox": [],
  "geometry": {"coordinates":[-123.3167,45.3167],"type":"Point"}
}