{
  "id": 7300842,
  "type": "Feature",
  "properties": {
    "tgn:hierarchy":[
        "tgn:7300842",
        "tgn:7002804",
        "tgn:1000003",
        "tgn:7002793",
        "tgn:1000095",
        "tgn:7029392"
    ],
    "tgn:id":7300842,
    "tgn:name":"Moralet",
    "tgn:placetype":[
        "aat:300008347"
    ]
},
  "bbox": [],
  "geometry": {"coordinates":[-0.566667,38.416667],"type":"Point"}
}