{
  "id": 7110688,
  "type": "Feature",
  "properties": {
    "tgn:hierarchy":[
        "tgn:7110688",
        "tgn:7003692",
        "tgn:1000003",
        "tgn:7000084",
        "tgn:7029392"
    ],
    "tgn:id":7110688,
    "tgn:name":"Reichertsberg",
    "tgn:placetype":[
        "aat:300008863"
    ]
},
  "bbox": [],
  "geometry": {"coordinates":[9.116667,49.316667],"type":"Point"}
}