<<<<<<< HEAD
{
  "id": 7110688,
  "type": "Feature",
  "properties": {
    "tgn:hierarchy":[
        "tgn:7110688",
        "tgn:7003692",
        "tgn:1000003",
        "tgn:7000084",
        "tgn:7029392"
    ],
    "tgn:id":7110688,
    "tgn:name":"Reichertsberg",
    "tgn:placetype":[
        "aat:300008863"
    ]
},
  "bbox": [],
  "geometry": {"coordinates":[9.116667,49.316667],"type":"Point"}
}
=======
{"geometry":{"type":"Point","coordinates":[9.116667,49.316667]},"type":"Feature","properties":{"hierarchy":["tgn:7110688","tgn:7003692","tgn:1000003","tgn:7000084","tgn:7029392"],"placetype":["aat:300008863"],"id":7110688,"name:xx":"Reichertsberg"}}
>>>>>>> 03f74aca74312dbeaf24d7e61306dd6a786dc3d0
