{
  "id": 2505192,
  "type": "Feature",
  "properties": {
    "tgn:hierarchy":[
        "tgn:2505192",
        "tgn:1000001",
        "tgn:7012149",
        "tgn:1002350",
        "tgn:7007157",
        "tgn:7029392"
    ],
    "tgn:id":2505192,
    "tgn:name":"Mehrten Creek",
    "tgn:placetype":[
        "aat:300008706"
    ]
},
  "bbox": [],
  "geometry": {"coordinates":[-120.2833,38.55],"type":"Point"}
}