{
  "id": 2258401,
  "type": "Feature",
  "properties": {
    "tgn:hierarchy":[
        "tgn:2258401",
        "tgn:1000001",
        "tgn:7012149",
        "tgn:1002920",
        "tgn:7007568",
        "tgn:7029392"
    ],
    "tgn:id":2258401,
    "tgn:name":"Cotton Creek",
    "tgn:placetype":[
        "aat:300008706"
    ]
},
  "bbox": [],
  "geometry": {"coordinates":[-77.4333,42.3833],"type":"Point"}
}