<<<<<<< HEAD
{
  "id": 2258401,
  "type": "Feature",
  "properties": {
    "tgn:hierarchy":[
        "tgn:2258401",
        "tgn:1000001",
        "tgn:7012149",
        "tgn:1002920",
        "tgn:7007568",
        "tgn:7029392"
    ],
    "tgn:id":2258401,
    "tgn:name":"Cotton Creek",
    "tgn:placetype":[
        "aat:300008706"
    ]
},
  "bbox": [],
  "geometry": {"coordinates":[-77.4333,42.3833],"type":"Point"}
}
=======
{"geometry":{"type":"Point","coordinates":[-77.433300,42.383300]},"type":"Feature","properties":{"hierarchy":["tgn:2258401","tgn:1000001","tgn:7012149","tgn:1002920","tgn:7007568","tgn:7029392"],"placetype":["aat:300008706"],"id":2258401,"name:xx":"Cotton Creek"}}
>>>>>>> 03f74aca74312dbeaf24d7e61306dd6a786dc3d0
