{
  "id": 7282421,
  "type": "Feature",
  "properties": {
    "tgn:hierarchy":[
        "tgn:7282421",
        "tgn:7002464",
        "tgn:1000049",
        "tgn:1000002",
        "tgn:7029392"
    ],
    "tgn:id":7282421,
    "tgn:name":"Pisagua, Bahia de",
    "tgn:placetype":[
        "aat:300132316"
    ]
},
  "bbox": [],
  "geometry": {"coordinates":[-70.216667,-19.583333],"type":"Point"}
}