<<<<<<< HEAD
{
  "id": 7350285,
  "type": "Feature",
  "properties": {
    "tgn:hierarchy":[
        "tgn:7350285",
        "tgn:7005586",
        "tgn:1000001",
        "tgn:7005560",
        "tgn:7029392"
    ],
    "tgn:id":7350285,
    "tgn:name":"Bioto",
    "tgn:placetype":[
        "aat:300008347"
    ]
},
  "bbox": [],
  "geometry": {"coordinates":[-105.433333,20.266667],"type":"Point"}
}
=======
{"geometry":{"type":"Point","coordinates":[-105.433333,20.266667]},"type":"Feature","properties":{"hierarchy":["tgn:7350285","tgn:7005586","tgn:1000001","tgn:7005560","tgn:7029392"],"placetype":["aat:300008347"],"id":7350285,"name:xx":"Bioto"}}
>>>>>>> 03f74aca74312dbeaf24d7e61306dd6a786dc3d0
