{
  "id": 2672173,
  "type": "Feature",
  "properties": {
    "tgn:hierarchy":[
        "tgn:2672173",
        "tgn:7002659",
        "tgn:1000001",
        "tgn:7012149",
        "tgn:2000040",
        "tgn:7029392"
    ],
    "tgn:id":2672173,
    "tgn:name":"Smiths Lake",
    "tgn:placetype":[
        "aat:300006191"
    ]
},
  "bbox": [],
  "geometry": {"coordinates":[-85.0667,32.55],"type":"Point"}
}