{
  "id": 2728381,
  "type": "Feature",
  "properties": {
    "tgn:hierarchy":[
        "tgn:2728381",
        "tgn:1000001",
        "tgn:7012149",
        "tgn:2002089",
        "tgn:7007826",
        "tgn:7029392"
    ],
    "tgn:id":2728381,
    "tgn:name":"Treasure Branch",
    "tgn:placetype":[
        "aat:300008699"
    ]
},
  "bbox": [],
  "geometry": {"coordinates":[-94.5833,30.7833],"type":"Point"}
}