{
  "id": 7548140,
  "type": "Feature",
  "properties": {
    "tgn:hierarchy":[
        "tgn:7548140",
        "tgn:1000004",
        "tgn:7000198",
        "tgn:1001895",
        "tgn:7029392"
    ],
    "tgn:id":7548140,
    "tgn:name:en":"\u0100lamgaon",
    "tgn:placetype":[
        "aat:300008347"
    ]
},
  "bbox": [],
  "geometry": {"coordinates":[75.766667,19.733333],"type":"Point"}
}