<<<<<<< HEAD
{
  "id": 7056510,
  "type": "Feature",
  "properties": {
    "tgn:hierarchy":[
        "tgn:7056510",
        "tgn:7009084",
        "tgn:7003001",
        "tgn:1000003",
        "tgn:1000080",
        "tgn:7029392"
    ],
    "tgn:id":7056510,
    "tgn:name":"Bilanciere, Monte",
    "tgn:placetype":[
        "aat:300008795"
    ]
},
  "bbox": [],
  "geometry": {"coordinates":[13.5,42.633333],"type":"Point"}
}
=======
{"geometry":{"type":"Point","coordinates":[13.500000,42.633333]},"type":"Feature","properties":{"hierarchy":["tgn:7056510","tgn:7009084","tgn:7003001","tgn:1000003","tgn:1000080","tgn:7029392"],"placetype":["aat:300008795"],"id":7056510,"name:xx":"Bilanciere, Monte"}}
>>>>>>> 03f74aca74312dbeaf24d7e61306dd6a786dc3d0
