{
  "id": 2613509,
  "type": "Feature",
  "properties": {
    "tgn:hierarchy":[
        "tgn:2613509",
        "tgn:1000001",
        "tgn:7012149",
        "tgn:2001709",
        "tgn:7007708",
        "tgn:7029392"
    ],
    "tgn:id":2613509,
    "tgn:name":"Reed Spring",
    "tgn:placetype":[
        "aat:300008697"
    ]
},
  "bbox": [],
  "geometry": {"coordinates":[-119.3333,42.2667],"type":"Point"}
}