{
  "id": 7507638,
  "type": "Feature",
  "properties": {
    "tgn:hierarchy":[
        "tgn:7507638",
        "tgn:1009227",
        "tgn:1000226",
        "tgn:7016822",
        "tgn:1000006",
        "tgn:7029392"
    ],
    "tgn:id":7507638,
    "tgn:name:en":"Poporangi",
    "tgn:placetype":[
        "aat:300008749"
    ]
},
  "bbox": [],
  "geometry": {"coordinates":[-176.483333,-43.916667],"type":"Point"}
}