{
  "id": 2637790,
  "type": "Feature",
  "properties": {
    "tgn:hierarchy":[
        "tgn:2637790",
        "tgn:1000001",
        "tgn:2001261",
        "tgn:7012149",
        "tgn:7007524",
        "tgn:7029392"
    ],
    "tgn:id":2637790,
    "tgn:name":"Saint Xavier Coulee",
    "tgn:placetype":[
        "aat:300008761"
    ]
},
  "bbox": [],
  "geometry": {"coordinates":[-107.65,45.4333],"type":"Point"}
}