{
  "id": 2234989,
  "type": "Feature",
  "properties": {
    "tgn:hierarchy":[
        "tgn:2234989",
        "tgn:1000001",
        "tgn:7012149",
        "tgn:2001315",
        "tgn:7007524",
        "tgn:7029392"
    ],
    "tgn:id":2234989,
    "tgn:name":"Cherry Island",
    "tgn:placetype":[
        "aat:300008791"
    ]
},
  "bbox": [],
  "geometry": {"coordinates":[-108.4333,45.8167],"type":"Point"}
}