{
  "id": 7585551,
  "type": "Feature",
  "properties": {
    "tgn:hierarchy":[
        "tgn:7585551",
        "tgn:1000004",
        "tgn:7000198",
        "tgn:7000799",
        "tgn:7029392"
    ],
    "tgn:id":7585551,
    "tgn:name:en":"dheri\u0101n",
    "tgn:placetype":[
        "aat:300008347"
    ]
},
  "bbox": [],
  "geometry": {"coordinates":[74.238646,33.296342],"type":"Point"}
}