{
  "id": 2089192,
  "type": "Feature",
  "properties": {
    "tgn:hierarchy":[
        "tgn:2089192",
        "tgn:1000001",
        "tgn:7012149",
        "tgn:1002520",
        "tgn:7007710",
        "tgn:7029392"
    ],
    "tgn:id":2089192,
    "tgn:name":"Heathville",
    "tgn:placetype":[
        "aat:300008347"
    ]
},
  "bbox": [],
  "geometry": {"coordinates":[-79.1667,41.0833],"type":"Point"}
}