<<<<<<< HEAD
{
  "id": 7470143,
  "type": "Feature",
  "properties": {
    "tgn:hierarchy":[
        "tgn:7470143",
        "tgn:1000004",
        "tgn:7001014",
        "tgn:1000141",
        "tgn:7029392"
    ],
    "tgn:id":7470143,
    "tgn:name":"Xijing",
    "tgn:placetype":[
        "aat:300008347"
    ]
},
  "bbox": [],
  "geometry": {"coordinates":[120.253611,23.601111],"type":"Point"}
}
=======
{"geometry":{"type":"Point","coordinates":[120.253611,23.601111]},"type":"Feature","properties":{"hierarchy":["tgn:7470143","tgn:1000004","tgn:7001014","tgn:1000141","tgn:7029392"],"placetype":["aat:300008347"],"id":7470143,"name:xx":"Xijing"}}
>>>>>>> 03f74aca74312dbeaf24d7e61306dd6a786dc3d0
