{
  "id": 2176534,
  "type": "Feature",
  "properties": {
    "tgn:hierarchy":[
        "tgn:2176534",
        "tgn:1000001",
        "tgn:7012149",
        "tgn:2000988",
        "tgn:7007520",
        "tgn:7029392"
    ],
    "tgn:id":2176534,
    "tgn:name":"Black Lake",
    "tgn:placetype":[
        "aat:300008680"
    ]
},
  "bbox": [],
  "geometry": {"coordinates":[-83.9833,44.7667],"type":"Point"}
}