{
  "id": 7101545,
  "type": "Feature",
  "properties": {
    "tgn:hierarchy":[
        "tgn:7101545",
        "tgn:1000003",
        "tgn:7003685",
        "tgn:7000084",
        "tgn:7029392"
    ],
    "tgn:id":7101545,
    "tgn:name":"Rothersdorf",
    "tgn:placetype":[
        "aat:300008347"
    ]
},
  "bbox": [],
  "geometry": {"coordinates":[12.75,51.316667],"type":"Point"}
}