{
  "id": 7149110,
  "type": "Feature",
  "properties": {
    "tgn:hierarchy":[
        "tgn:7149110",
        "tgn:7003669",
        "tgn:1000003",
        "tgn:7000084",
        "tgn:7029392"
    ],
    "tgn:id":7149110,
    "tgn:name":"Krug Holz",
    "tgn:placetype":[
        "aat:300008863"
    ]
},
  "bbox": [],
  "geometry": {"coordinates":[13.15,48.566667],"type":"Point"}
}