{
  "id": 2159476,
  "type": "Feature",
  "properties": {
    "tgn:hierarchy":[
        "tgn:2159476",
        "tgn:1000001",
        "tgn:7016172",
        "tgn:2000109",
        "tgn:7012149",
        "tgn:7029392"
    ],
    "tgn:id":2159476,
    "tgn:name":"Bee Hollow",
    "tgn:placetype":[
        "aat:300008761"
    ]
},
  "bbox": [],
  "geometry": {"coordinates":[-93.1333,36.3667],"type":"Point"}
}