{
  "id": 2429136,
  "type": "Feature",
  "properties": {
    "tgn:hierarchy":[
        "tgn:2429136",
        "tgn:1000001",
        "tgn:7012149",
        "tgn:7007157",
        "tgn:2000189",
        "tgn:7029392"
    ],
    "tgn:id":2429136,
    "tgn:name":"Junction Spring",
    "tgn:placetype":[
        "aat:300008697"
    ]
},
  "bbox": [],
  "geometry": {"coordinates":[-122.0333,41.3833],"type":"Point"}
}