{
  "id": 2130599,
  "type": "Feature",
  "properties": {
    "tgn:hierarchy":[
        "tgn:2130599",
        "tgn:1000001",
        "tgn:7012149",
        "tgn:7007256",
        "tgn:7029392"
    ],
    "tgn:id":2130599,
    "tgn:name":"Alligator Island",
    "tgn:placetype":[
        "aat:300008791"
    ]
},
  "bbox": [],
  "geometry": {"coordinates":[-90.6167,30.2167],"type":"Point"}
}