{
  "id": 7263961,
  "type": "Feature",
  "properties": {
    "tgn:hierarchy":[
        "tgn:7263961",
        "tgn:1000003",
        "tgn:7003635",
        "tgn:7016845",
        "tgn:7029392"
    ],
    "tgn:id":7263961,
    "tgn:name:nl":"Hortenisse",
    "tgn:placetype":[
        "aat:300387145"
    ]
},
  "bbox": [],
  "geometry": {"coordinates":[4.016667,51.383333],"type":"Point"}
}