{
  "id": 2579401,
  "type": "Feature",
  "properties": {
    "tgn:hierarchy":[
        "tgn:2579401",
        "tgn:1000001",
        "tgn:7012149",
        "tgn:2001027",
        "tgn:7007521",
        "tgn:7029392"
    ],
    "tgn:id":2579401,
    "tgn:name":"Pickerel Lake",
    "tgn:placetype":[
        "aat:300008680"
    ]
},
  "bbox": [],
  "geometry": {"coordinates":[-94.9833,47.0333],"type":"Point"}
}