{
  "id": 7504328,
  "type": "Feature",
  "properties": {
    "tgn:hierarchy":[
        "tgn:7504328",
        "tgn:1008380",
        "tgn:1000226",
        "tgn:7000512",
        "tgn:1000006",
        "tgn:7029392"
    ],
    "tgn:id":7504328,
    "tgn:name:en":"Waitetumu Stream",
    "tgn:placetype":[
        "aat:300008699"
    ]
},
  "bbox": [],
  "geometry": {"coordinates":[175.336389,-41.597778],"type":"Point"}
}