{
  "id": 7395076,
  "type": "Feature",
  "properties": {
    "tgn:hierarchy":[
        "tgn:7395076",
        "tgn:1000001",
        "tgn:7005600",
        "tgn:7005560",
        "tgn:7029392"
    ],
    "tgn:id":7395076,
    "tgn:name":"San Antonio",
    "tgn:placetype":[
        "aat:300008347"
    ]
},
  "bbox": [],
  "geometry": {"coordinates":[-89.166667,20.083333],"type":"Point"}
}