{
  "id": 2523322,
  "type": "Feature",
  "properties": {
    "tgn:hierarchy":[
        "tgn:2523322",
        "tgn:1000001",
        "tgn:7012149",
        "tgn:2000933",
        "tgn:7007515",
        "tgn:7029392"
    ],
    "tgn:id":2523322,
    "tgn:name":"Moors Brook",
    "tgn:placetype":[
        "aat:300008699"
    ]
},
  "bbox": [],
  "geometry": {"coordinates":[-70.4333,43.45],"type":"Point"}
}