<<<<<<< HEAD
{
  "id": 7350426,
  "type": "Feature",
  "properties": {
    "tgn:hierarchy":[
        "tgn:7350426",
        "tgn:1000001",
        "tgn:1001893",
        "tgn:7005560",
        "tgn:7029392"
    ],
    "tgn:id":7350426,
    "tgn:name":"Apaxco de Ocampo",
    "tgn:placetype":[
        "aat:300008347"
    ]
},
  "bbox": [],
  "geometry": {"coordinates":[-99.173889,19.973889],"type":"Point"}
}
=======
{"geometry":{"type":"Point","coordinates":[-99.173889,19.973889]},"type":"Feature","properties":{"hierarchy":["tgn:7350426","tgn:1000001","tgn:1001893","tgn:7005560","tgn:7029392"],"placetype":["aat:300008347"],"id":7350426,"name:xx":"Apaxco de Ocampo"}}
>>>>>>> 03f74aca74312dbeaf24d7e61306dd6a786dc3d0
