{
  "id": 2192531,
  "type": "Feature",
  "properties": {
    "tgn:hierarchy":[
        "tgn:2192531",
        "tgn:1000001",
        "tgn:7012149",
        "tgn:1002967",
        "tgn:7007520",
        "tgn:7029392"
    ],
    "tgn:id":2192531,
    "tgn:name":"Brandywine Lake",
    "tgn:placetype":[
        "aat:300008680"
    ]
},
  "bbox": [],
  "geometry": {"coordinates":[-85.85,42.3333],"type":"Point"}
}