<<<<<<< HEAD
{
  "id": 2763409,
  "type": "Feature",
  "properties": {
    "tgn:hierarchy":[
        "tgn:2763409",
        "tgn:1000001",
        "tgn:1003023",
        "tgn:7012149",
        "tgn:7007516",
        "tgn:7029392"
    ],
    "tgn:id":2763409,
    "tgn:name":"Wetipquin Creek",
    "tgn:placetype":[
        "aat:300008706"
    ]
},
  "bbox": [],
  "geometry": {"coordinates":[-75.8,38.3],"type":"Point"}
}
=======
{"geometry":{"type":"Point","coordinates":[-75.800000,38.300000]},"type":"Feature","properties":{"hierarchy":["tgn:2763409","tgn:1000001","tgn:1003023","tgn:7012149","tgn:7007516","tgn:7029392"],"placetype":["aat:300008706"],"id":2763409,"name:xx":"Wetipquin Creek"}}
>>>>>>> 03f74aca74312dbeaf24d7e61306dd6a786dc3d0
