{
  "id": 2331407,
  "type": "Feature",
  "properties": {
    "tgn:hierarchy":[
        "tgn:2331407",
        "tgn:1000001",
        "tgn:7012149",
        "tgn:2002014",
        "tgn:7007826",
        "tgn:7029392"
    ],
    "tgn:id":2331407,
    "tgn:name":"Flatrock Creek",
    "tgn:placetype":[
        "aat:300008706"
    ]
},
  "bbox": [],
  "geometry": {"coordinates":[-99.65,32.7167],"type":"Point"}
}