<<<<<<< HEAD
{
  "id": 2331407,
  "type": "Feature",
  "properties": {
    "tgn:hierarchy":[
        "tgn:2331407",
        "tgn:1000001",
        "tgn:7012149",
        "tgn:2002014",
        "tgn:7007826",
        "tgn:7029392"
    ],
    "tgn:id":2331407,
    "tgn:name":"Flatrock Creek",
    "tgn:placetype":[
        "aat:300008706"
    ]
},
  "bbox": [],
  "geometry": {"coordinates":[-99.65,32.7167],"type":"Point"}
}
=======
{"geometry":{"type":"Point","coordinates":[-99.650000,32.716700]},"type":"Feature","properties":{"hierarchy":["tgn:2331407","tgn:1000001","tgn:7012149","tgn:2002014","tgn:7007826","tgn:7029392"],"placetype":["aat:300008706"],"id":2331407,"name:xx":"Flatrock Creek"}}
>>>>>>> 03f74aca74312dbeaf24d7e61306dd6a786dc3d0
