<<<<<<< HEAD
{
  "id": 7051715,
  "type": "Feature",
  "properties": {
    "tgn:hierarchy":[
        "tgn:7051715",
        "tgn:7003164",
        "tgn:1000003",
        "tgn:7009760",
        "tgn:1000080",
        "tgn:7029392"
    ],
    "tgn:id":7051715,
    "tgn:name":"Podere del Marchese",
    "tgn:placetype":[
        "aat:300000206"
    ]
},
  "bbox": [],
  "geometry": {"coordinates":[10.083333,42.616667],"type":"Point"}
}
=======
{"geometry":{"type":"Point","coordinates":[10.083333,42.616667]},"type":"Feature","properties":{"hierarchy":["tgn:7051715","tgn:7003164","tgn:1000003","tgn:7009760","tgn:1000080","tgn:7029392"],"placetype":["aat:300000206"],"id":7051715,"name:xx":"Podere del Marchese"}}
>>>>>>> 03f74aca74312dbeaf24d7e61306dd6a786dc3d0
