{
  "id": 2356656,
  "type": "Feature",
  "properties": {
    "tgn:hierarchy":[
        "tgn:2356656",
        "tgn:1000001",
        "tgn:2000266",
        "tgn:7012149",
        "tgn:7007240",
        "tgn:7029392"
    ],
    "tgn:id":2356656,
    "tgn:name":"Gore Lake",
    "tgn:placetype":[
        "aat:300008680"
    ]
},
  "bbox": [],
  "geometry": {"coordinates":[-81.2167,29.45],"type":"Point"}
}