{
  "id": 7120732,
  "type": "Feature",
  "properties": {
    "tgn:hierarchy":[
        "tgn:7120732",
        "tgn:1000003",
        "tgn:7003682",
        "tgn:7000084",
        "tgn:7029392"
    ],
    "tgn:id":7120732,
    "tgn:name":"Pfalz",
    "tgn:placetype":[
        "aat:300006891"
    ]
},
  "bbox": [],
  "geometry": {"coordinates":[7.766667,50.083333],"type":"Point"}
}