{
  "id": 7412261,
  "type": "Feature",
  "properties": {
    "tgn:hierarchy":[
        "tgn:7412261",
        "tgn:7005587",
        "tgn:1000001",
        "tgn:7005560",
        "tgn:7029392"
    ],
    "tgn:id":7412261,
    "tgn:name:es":"Acoapa",
    "tgn:placetype":[
        "aat:300008347"
    ]
},
  "bbox": [],
  "geometry": {"coordinates":[-98.483333,21.119444],"type":"Point"}
}