{
  "id": 1042257,
  "type": "Feature",
  "properties": {
    "tgn:hierarchy":[
        "tgn:1042257",
        "tgn:7002681",
        "tgn:7001395",
        "tgn:1000003",
        "tgn:1000074",
        "tgn:7029392"
    ],
    "tgn:id":1042257,
    "tgn:name":"Zogr\u00e1fos",
    "tgn:placetype":[
        "aat:300008347",
        "aat:300008389"
    ]
},
  "bbox": [],
  "geometry": {"coordinates":[23.25,40.283333],"type":"Point"}
}