{
  "id": 7577738,
  "type": "Feature",
  "properties": {
    "tgn:hierarchy":[
        "tgn:7577738",
        "tgn:1000004",
        "tgn:1001869",
        "tgn:7000198",
        "tgn:7029392"
    ],
    "tgn:id":7577738,
    "tgn:name:en":"Khodu",
    "tgn:placetype":[
        "aat:300008347"
    ]
},
  "bbox": [],
  "geometry": {"coordinates":[71.483333,22.783333],"type":"Point"}
}