<<<<<<< HEAD
{
  "id": 7475181,
  "type": "Feature",
  "properties": {
    "tgn:hierarchy":[
        "tgn:7475181",
        "tgn:1000004",
        "tgn:1000454",
        "tgn:1000141",
        "tgn:7029392"
    ],
    "tgn:id":7475181,
    "tgn:name":"Qianhua Guoxiao",
    "tgn:placetype":[
        "aat:300006495"
    ]
},
  "bbox": [],
  "geometry": {"coordinates":[121.592258,25.267787],"type":"Point"}
}
=======
{"geometry":{"type":"Point","coordinates":[121.592258,25.267787]},"type":"Feature","properties":{"hierarchy":["tgn:7475181","tgn:1000004","tgn:1000454","tgn:1000141","tgn:7029392"],"placetype":["aat:300006495"],"id":7475181,"name:xx":"Qianhua Guoxiao"}}
>>>>>>> 03f74aca74312dbeaf24d7e61306dd6a786dc3d0
