{
  "id": 1067089,
  "type": "Feature",
  "properties": {
    "tgn:hierarchy":[
        "tgn:1067089",
        "tgn:1000004",
        "tgn:7002372",
        "tgn:1000111",
        "tgn:7029392"
    ],
    "tgn:id":1067089,
    "tgn:name":"Changling",
    "tgn:placetype":[
        "aat:300008347"
    ]
},
  "bbox": [],
  "geometry": {"coordinates":[123.9667,44.2667],"type":"Point"}
}