{
  "id": 7559731,
  "type": "Feature",
  "properties": {
    "tgn:hierarchy":[
        "tgn:7559731",
        "tgn:1000004",
        "tgn:7000198",
        "tgn:7016722",
        "tgn:7029392"
    ],
    "tgn:id":7559731,
    "tgn:name:en":"Gadari\u0101n Nagla",
    "tgn:placetype":[
        "aat:300008347"
    ]
},
  "bbox": [],
  "geometry": {"coordinates":[79.4493,27.773061],"type":"Point"}
}