{
  "id": 2379200,
  "type": "Feature",
  "properties": {
    "tgn:hierarchy":[
        "tgn:2379200",
        "tgn:1000001",
        "tgn:7012149",
        "tgn:2001903",
        "tgn:7007825",
        "tgn:7029392"
    ],
    "tgn:id":2379200,
    "tgn:name":"Hartsaw Cove",
    "tgn:placetype":[
        "aat:300008761"
    ]
},
  "bbox": [],
  "geometry": {"coordinates":[-85.2667,36.2667],"type":"Point"}
}