{
  "id": 7282639,
  "type": "Feature",
  "properties": {
    "tgn:hierarchy":[
        "tgn:7282639",
        "tgn:1001657",
        "tgn:1000049",
        "tgn:1000002",
        "tgn:7029392"
    ],
    "tgn:id":7282639,
    "tgn:name":"Peralillo",
    "tgn:placetype":[
        "aat:300008347"
    ]
},
  "bbox": [],
  "geometry": {"coordinates":[-70.683333,-30.033333],"type":"Point"}
}