{
  "id": 2168402,
  "type": "Feature",
  "properties": {
    "tgn:hierarchy":[
        "tgn:2168402",
        "tgn:1000001",
        "tgn:2000459",
        "tgn:7012149",
        "tgn:7007250",
        "tgn:7029392"
    ],
    "tgn:id":2168402,
    "tgn:name":"Big Gulch",
    "tgn:placetype":[
        "aat:300008761"
    ]
},
  "bbox": [],
  "geometry": {"coordinates":[-115.9167,43.7833],"type":"Point"}
}