{
  "id": 2275778,
  "type": "Feature",
  "properties": {
    "tgn:hierarchy":[
        "tgn:2275778",
        "tgn:1000001",
        "tgn:7012149",
        "tgn:7007157",
        "tgn:2000191",
        "tgn:7029392"
    ],
    "tgn:id":2275778,
    "tgn:name":"Dark Gulch",
    "tgn:placetype":[
        "aat:300008761"
    ]
},
  "bbox": [],
  "geometry": {"coordinates":[-122.8333,40.6833],"type":"Point"}
}