<<<<<<< HEAD
{
  "id": 2151504,
  "type": "Feature",
  "properties": {
    "tgn:hierarchy":[
        "tgn:2151504",
        "tgn:1002933",
        "tgn:1000001",
        "tgn:7012149",
        "tgn:7007239",
        "tgn:7029392"
    ],
    "tgn:id":2151504,
    "tgn:name":"Batson Branch",
    "tgn:placetype":[
        "aat:300008699"
    ]
},
  "bbox": [],
  "geometry": {"coordinates":[-75.15,38.5],"type":"Point"}
}
=======
{"geometry":{"type":"Point","coordinates":[-75.150000,38.500000]},"type":"Feature","properties":{"hierarchy":["tgn:2151504","tgn:1002933","tgn:1000001","tgn:7012149","tgn:7007239","tgn:7029392"],"placetype":["aat:300008699"],"id":2151504,"name:xx":"Batson Branch"}}
>>>>>>> 03f74aca74312dbeaf24d7e61306dd6a786dc3d0
