<<<<<<< HEAD
{
  "id": 2157494,
  "type": "Feature",
  "properties": {
    "tgn:hierarchy":[
        "tgn:2157494",
        "tgn:1000001",
        "tgn:7012149",
        "tgn:2002175",
        "tgn:7007919",
        "tgn:7029392"
    ],
    "tgn:id":2157494,
    "tgn:name":"Beaver Creek",
    "tgn:placetype":[
        "aat:300008706"
    ]
},
  "bbox": [],
  "geometry": {"coordinates":[-78.7667,37.75],"type":"Point"}
}
=======
{"geometry":{"type":"Point","coordinates":[-78.766700,37.750000]},"type":"Feature","properties":{"hierarchy":["tgn:2157494","tgn:1000001","tgn:7012149","tgn:2002175","tgn:7007919","tgn:7029392"],"placetype":["aat:300008706"],"id":2157494,"name:xx":"Beaver Creek"}}
>>>>>>> 03f74aca74312dbeaf24d7e61306dd6a786dc3d0
