{
  "id": 2737792,
  "type": "Feature",
  "properties": {
    "tgn:hierarchy":[
        "tgn:2737792",
        "tgn:1000001",
        "tgn:1002304",
        "tgn:7012149",
        "tgn:7007706",
        "tgn:7029392"
    ],
    "tgn:id":2737792,
    "tgn:name":"Tyrone",
    "tgn:placetype":[
        "aat:300008347"
    ]
},
  "bbox": [],
  "geometry": {"coordinates":[-81.9667,40.25],"type":"Point"}
}