{
  "id": 2145258,
  "type": "Feature",
  "properties": {
    "tgn:hierarchy":[
        "tgn:2145258",
        "tgn:1000001",
        "tgn:2001418",
        "tgn:7012149",
        "tgn:7007526",
        "tgn:7029392"
    ],
    "tgn:id":2145258,
    "tgn:name":"Bald Mountain Canyon",
    "tgn:placetype":[
        "aat:300008761"
    ]
},
  "bbox": [],
  "geometry": {"coordinates":[-117.0333,38.5667],"type":"Point"}
}