{
  "id": 7503961,
  "type": "Feature",
  "properties": {
    "tgn:hierarchy":[
        "tgn:7503961",
        "tgn:1009227",
        "tgn:1000226",
        "tgn:7016729",
        "tgn:1000006",
        "tgn:7029392"
    ],
    "tgn:id":7503961,
    "tgn:name:en":"Wether Hill",
    "tgn:placetype":[
        "aat:300008795"
    ]
},
  "bbox": [],
  "geometry": {"coordinates":[173.116667,-41.666667],"type":"Point"}
}