<<<<<<< HEAD
{
  "id": 7020886,
  "type": "Feature",
  "properties": {
    "tgn:hierarchy":[
        "tgn:7020886",
        "tgn:1000001",
        "tgn:7029392"
    ],
    "tgn:id":7020886,
    "tgn:name":"Huron, Lake",
    "tgn:placetype":[
        "aat:300008680"
    ]
},
  "bbox": [],
  "geometry": {"coordinates":[-82.0,44.0],"type":"Point"}
}
=======
{"geometry":{"type":"Point","coordinates":[-82.000000,44.000000]},"type":"Feature","properties":{"hierarchy":["tgn:7020886","tgn:1000001","tgn:7029392"],"placetype":["aat:300008680"],"id":7020886,"name:xx":"Huron, Lake"}}
>>>>>>> 03f74aca74312dbeaf24d7e61306dd6a786dc3d0
