{
  "id": 7549959,
  "type": "Feature",
  "properties": {
    "tgn:hierarchy":[
        "tgn:7549959",
        "tgn:1000004",
        "tgn:1001842",
        "tgn:7000198",
        "tgn:7029392"
    ],
    "tgn:id":7549959,
    "tgn:name:en":"Dharmaut\u012b Nad\u012b",
    "tgn:placetype":[
        "aat:300008699"
    ]
},
  "bbox": [],
  "geometry": {"coordinates":[83.782265,25.39714],"type":"Point"}
}