<<<<<<< HEAD
{
  "id": 2251414,
  "type": "Feature",
  "properties": {
    "tgn:hierarchy":[
        "tgn:2251414",
        "tgn:1000001",
        "tgn:7012149",
        "tgn:7007157",
        "tgn:1002915",
        "tgn:7029392"
    ],
    "tgn:id":2251414,
    "tgn:name":"Cometa Lateral",
    "tgn:placetype":[
        "aat:300006075"
    ]
},
  "bbox": [],
  "geometry": {"coordinates":[-120.8667,37.8333],"type":"Point"}
}
=======
{"geometry":{"type":"Point","coordinates":[-120.866700,37.833300]},"type":"Feature","properties":{"hierarchy":["tgn:2251414","tgn:1000001","tgn:7012149","tgn:7007157","tgn:1002915","tgn:7029392"],"placetype":["aat:300006075"],"id":2251414,"name:xx":"Cometa Lateral"}}
>>>>>>> 03f74aca74312dbeaf24d7e61306dd6a786dc3d0
