{
  "id": 1021907,
  "type": "Feature",
  "properties": {
    "tgn:hierarchy":[
        "tgn:1021907",
        "tgn:7006237",
        "tgn:1000047",
        "tgn:7002457",
        "tgn:1000002",
        "tgn:7029392"
    ],
    "tgn:id":1021907,
    "tgn:name":"Jur\u00e9ia",
    "tgn:placetype":[
        "aat:300008347"
    ]
},
  "bbox": [],
  "geometry": {"coordinates":[-46.3667,-21.2833],"type":"Point"}
}