{
  "id": 2436695,
  "type": "Feature",
  "properties": {
    "tgn:hierarchy":[
        "tgn:2436695",
        "tgn:1002648",
        "tgn:1000001",
        "tgn:1008191",
        "tgn:7012149",
        "tgn:7007249",
        "tgn:7029392"
    ],
    "tgn:id":2436695,
    "tgn:name":"Kihaloko Fishpond",
    "tgn:placetype":[
        "aat:300008680"
    ]
},
  "bbox": [],
  "geometry": {"coordinates":[-156.7833,21.0833],"type":"Point"}
}