{
  "id": 7117013,
  "type": "Feature",
  "properties": {
    "tgn:hierarchy":[
        "tgn:7117013",
        "tgn:7003669",
        "tgn:1000003",
        "tgn:7000084",
        "tgn:7029392"
    ],
    "tgn:id":7117013,
    "tgn:name":"Obertattenbach",
    "tgn:placetype":[
        "aat:300008347"
    ]
},
  "bbox": [],
  "geometry": {"coordinates":[13.066667,48.466667],"type":"Point"}
}