{
  "id": 2236164,
  "type": "Feature",
  "properties": {
    "tgn:hierarchy":[
        "tgn:2236164",
        "tgn:7006450",
        "tgn:1000001",
        "tgn:7030517",
        "tgn:7012149",
        "tgn:7029392"
    ],
    "tgn:id":2236164,
    "tgn:name":"Chichagof, Cape",
    "tgn:placetype":[
        "aat:300008850"
    ]
},
  "bbox": [],
  "geometry": {"coordinates":[-157.5333,58.3667],"type":"Point"}
}