<<<<<<< HEAD
{
  "id": 7119522,
  "type": "Feature",
  "properties": {
    "tgn:hierarchy":[
        "tgn:7119522",
        "tgn:1000003",
        "tgn:7003685",
        "tgn:7000084",
        "tgn:7029392"
    ],
    "tgn:id":7119522,
    "tgn:name":"Podelwitz",
    "tgn:placetype":[
        "aat:300008347"
    ]
},
  "bbox": [],
  "geometry": {"coordinates":[12.383333,51.433333],"type":"Point"}
}
=======
{"geometry":{"type":"Point","coordinates":[12.383333,51.433333]},"type":"Feature","properties":{"hierarchy":["tgn:7119522","tgn:1000003","tgn:7003685","tgn:7000084","tgn:7029392"],"placetype":["aat:300008347"],"id":7119522,"name:xx":"Podelwitz"}}
>>>>>>> 03f74aca74312dbeaf24d7e61306dd6a786dc3d0
