{
  "id": 2586865,
  "type": "Feature",
  "properties": {
    "tgn:hierarchy":[
        "tgn:2586865",
        "tgn:1008293",
        "tgn:1000001",
        "tgn:1002705",
        "tgn:7012149",
        "tgn:7007517",
        "tgn:7029392"
    ],
    "tgn:id":2586865,
    "tgn:name":"Plainfield",
    "tgn:placetype":[
        "aat:300008347"
    ]
},
  "bbox": [],
  "geometry": {"coordinates":[-69.9833,41.2667],"type":"Point"}
}