{
  "id": 7502473,
  "type": "Feature",
  "properties": {
    "tgn:hierarchy":[
        "tgn:7502473",
        "tgn:7001004",
        "tgn:1000004",
        "tgn:1000141",
        "tgn:7029392"
    ],
    "tgn:id":7502473,
    "tgn:name":"Bailing",
    "tgn:placetype":[
        "aat:300008347"
    ]
},
  "bbox": [],
  "geometry": {"coordinates":[120.379167,22.806944],"type":"Point"}
}