{
  "id": 7372754,
  "type": "Feature",
  "properties": {
    "tgn:hierarchy":[
        "tgn:7372754",
        "tgn:1000001",
        "tgn:7005599",
        "tgn:7005560",
        "tgn:7029392"
    ],
    "tgn:id":7372754,
    "tgn:name":"La Oaxaque\u00f1a",
    "tgn:placetype":[
        "aat:300008347"
    ]
},
  "bbox": [],
  "geometry": {"coordinates":[-94.883333,17.433333],"type":"Point"}
}