{
  "id": 1084044,
  "type": "Feature",
  "properties": {
    "tgn:hierarchy":[
        "tgn:1084044",
        "tgn:1000004",
        "tgn:1001185",
        "tgn:1000135",
        "tgn:7029392"
    ],
    "tgn:id":1084044,
    "tgn:name":"Bogo",
    "tgn:placetype":[
        "aat:300008347"
    ]
},
  "bbox": [],
  "geometry": {"coordinates":[124.0333,11.05],"type":"Point"}
}