{
  "id": 2259198,
  "type": "Feature",
  "properties": {
    "tgn:hierarchy":[
        "tgn:2259198",
        "tgn:1000001",
        "tgn:7012149",
        "tgn:7007157",
        "tgn:1002828",
        "tgn:7029392"
    ],
    "tgn:id":2259198,
    "tgn:name":"Cottonwood Lake",
    "tgn:placetype":[
        "aat:300006191"
    ]
},
  "bbox": [],
  "geometry": {"coordinates":[-117.0167,33.7833],"type":"Point"}
}