<<<<<<< HEAD
{
  "id": 2259198,
  "type": "Feature",
  "properties": {
    "tgn:hierarchy":[
        "tgn:2259198",
        "tgn:1000001",
        "tgn:7012149",
        "tgn:7007157",
        "tgn:1002828",
        "tgn:7029392"
    ],
    "tgn:id":2259198,
    "tgn:name":"Cottonwood Lake",
    "tgn:placetype":[
        "aat:300006191"
    ]
},
  "bbox": [],
  "geometry": {"coordinates":[-117.0167,33.7833],"type":"Point"}
}
=======
{"geometry":{"type":"Point","coordinates":[-117.016700,33.783300]},"type":"Feature","properties":{"hierarchy":["tgn:2259198","tgn:1000001","tgn:7012149","tgn:7007157","tgn:1002828","tgn:7029392"],"placetype":["aat:300006191"],"id":2259198,"name:xx":"Cottonwood Lake"}}
>>>>>>> 03f74aca74312dbeaf24d7e61306dd6a786dc3d0
