{
  "id": 2067942,
  "type": "Feature",
  "properties": {
    "tgn:hierarchy":[
        "tgn:2067942",
        "tgn:1000001",
        "tgn:7012149",
        "tgn:1002752",
        "tgn:7007568",
        "tgn:7029392"
    ],
    "tgn:id":2067942,
    "tgn:name":"Barre Center",
    "tgn:placetype":[
        "aat:300008347"
    ]
},
  "bbox": [],
  "geometry": {"coordinates":[-78.1833,43.1833],"type":"Point"}
}