{
  "id": 2420845,
  "type": "Feature",
  "properties": {
    "tgn:hierarchy":[
        "tgn:2420845",
        "tgn:1000001",
        "tgn:7012149",
        "tgn:7007158",
        "tgn:7029392"
    ],
    "tgn:id":2420845,
    "tgn:name":"Jenny Creek",
    "tgn:placetype":[
        "aat:300008706"
    ]
},
  "bbox": [],
  "geometry": {"coordinates":[-105.65,39.9333],"type":"Point"}
}