{
  "id": 7050463,
  "type": "Feature",
  "properties": {
    "tgn:hierarchy":[
        "tgn:7050463",
        "tgn:1000003",
        "tgn:1001651",
        "tgn:7003122",
        "tgn:1000080",
        "tgn:7029392"
    ],
    "tgn:id":7050463,
    "tgn:name":"Masseria Macchiafava",
    "tgn:placetype":[
        "aat:300008347"
    ]
},
  "bbox": [],
  "geometry": {"coordinates":[14.766667,37.783333],"type":"Point"}
}