{
  "id": 2305360,
  "type": "Feature",
  "properties": {
    "tgn:hierarchy":[
        "tgn:2305360",
        "tgn:1000001",
        "tgn:7012149",
        "tgn:1003038",
        "tgn:7007517",
        "tgn:7029392"
    ],
    "tgn:id":2305360,
    "tgn:name":"East Branch Ware River",
    "tgn:placetype":[
        "aat:300008707"
    ]
},
  "bbox": [],
  "geometry": {"coordinates":[-72.9333,42.5167],"type":"Point"}
}