{
  "id": 1125775,
  "type": "Feature",
  "properties": {
    "tgn:hierarchy":[
        "tgn:1125775",
        "tgn:1000004",
        "tgn:7029392"
    ],
    "tgn:id":1125775,
    "tgn:name":"Kugart",
    "tgn:placetype":[
        "aat:300008707"
    ]
},
  "bbox": [],
  "geometry": {"coordinates":[72.8833,40.8667],"type":"Point"}
}