{
  "id": 7417346,
  "type": "Feature",
  "properties": {
    "tgn:hierarchy":[
        "tgn:7417346",
        "tgn:1000001",
        "tgn:7005591",
        "tgn:7005560",
        "tgn:7029392"
    ],
    "tgn:id":7417346,
    "tgn:name:es":"Santiago Llano Grande",
    "tgn:placetype":[
        "aat:300008347"
    ]
},
  "bbox": [],
  "geometry": {"coordinates":[-98.281111,16.494444],"type":"Point"}
}