{
  "id": 2374300,
  "type": "Feature",
  "properties": {
    "tgn:hierarchy":[
        "tgn:2374300",
        "tgn:2000855",
        "tgn:1000001",
        "tgn:7012149",
        "tgn:7007256",
        "tgn:7029392"
    ],
    "tgn:id":2374300,
    "tgn:name":"Hampton",
    "tgn:placetype":[
        "aat:300008347"
    ]
},
  "bbox": [],
  "geometry": {"coordinates":[-92.6167,30.5833],"type":"Point"}
}