<<<<<<< HEAD
{
  "id": 2257471,
  "type": "Feature",
  "properties": {
    "tgn:hierarchy":[
        "tgn:2257471",
        "tgn:1000001",
        "tgn:7012149",
        "tgn:1002917",
        "tgn:7007706",
        "tgn:7029392"
    ],
    "tgn:id":2257471,
    "tgn:name":"Coronado Lake",
    "tgn:placetype":[
        "aat:300006191"
    ]
},
  "bbox": [],
  "geometry": {"coordinates":[-81.5333,40.8333],"type":"Point"}
}
=======
{"geometry":{"type":"Point","coordinates":[-81.533300,40.833300]},"type":"Feature","properties":{"hierarchy":["tgn:2257471","tgn:1000001","tgn:7012149","tgn:1002917","tgn:7007706","tgn:7029392"],"placetype":["aat:300006191"],"id":2257471,"name:xx":"Coronado Lake"}}
>>>>>>> 03f74aca74312dbeaf24d7e61306dd6a786dc3d0
