{
  "id": 2715986,
  "type": "Feature",
  "properties": {
    "tgn:hierarchy":[
        "tgn:2715986",
        "tgn:1000001",
        "tgn:2001099",
        "tgn:7012149",
        "tgn:7007522",
        "tgn:7029392"
    ],
    "tgn:id":2715986,
    "tgn:name":"Texas Island",
    "tgn:placetype":[
        "aat:300008791"
    ]
},
  "bbox": [],
  "geometry": {"coordinates":[-90.5167,34.4333],"type":"Point"}
}