{
  "id": 2148110,
  "type": "Feature",
  "properties": {
    "tgn:hierarchy":[
        "tgn:2148110",
        "tgn:1000001",
        "tgn:7012149",
        "tgn:2001494",
        "tgn:7007709",
        "tgn:7029392"
    ],
    "tgn:id":2148110,
    "tgn:name":"Barkers Creek",
    "tgn:placetype":[
        "aat:300008706"
    ]
},
  "bbox": [],
  "geometry": {"coordinates":[-80.35,36.25],"type":"Point"}
}