{
  "id": 2548243,
  "type": "Feature",
  "properties": {
    "tgn:hierarchy":[
        "tgn:2548243",
        "tgn:1000001",
        "tgn:7012149",
        "tgn:2001455",
        "tgn:7007566",
        "tgn:7029392"
    ],
    "tgn:id":2548243,
    "tgn:name":"North Kelly Canyon",
    "tgn:placetype":[
        "aat:300008761"
    ]
},
  "bbox": [],
  "geometry": {"coordinates":[-107.3667,33.0167],"type":"Point"}
}