{
  "id": 1007549,
  "type": "Feature",
  "properties": {
    "tgn:hierarchy":[
        "tgn:1007549",
        "tgn:1001942",
        "tgn:1000047",
        "tgn:7002457",
        "tgn:1000002",
        "tgn:7029392"
    ],
    "tgn:id":1007549,
    "tgn:name":"Jib\u00f3ia, Ilha da",
    "tgn:placetype":[
        "aat:300008791"
    ]
},
  "bbox": [],
  "geometry": {"coordinates":[-44.3667,-23.05],"type":"Point"}
}