{
  "id": 2008247,
  "type": "Feature",
  "properties": {
    "tgn:hierarchy":[
        "tgn:2008247",
        "tgn:1000001",
        "tgn:7016172",
        "tgn:7012149",
        "tgn:2000160",
        "tgn:7029392"
    ],
    "tgn:id":2008247,
    "tgn:name":"Fisher",
    "tgn:placetype":[
        "aat:300008347"
    ]
},
  "bbox": [],
  "geometry": {"coordinates":[-90.9667,35.4833],"type":"Point"}
}