{
  "id": 2479962,
  "type": "Feature",
  "properties": {
    "tgn:hierarchy":[
        "tgn:2479962",
        "tgn:1000001",
        "tgn:7012149",
        "tgn:2001457",
        "tgn:7007566",
        "tgn:7029392"
    ],
    "tgn:id":2479962,
    "tgn:name":"Lake Fork Peak",
    "tgn:placetype":[
        "aat:300008798"
    ]
},
  "bbox": [],
  "geometry": {"coordinates":[-105.4333,36.55],"type":"Point"}
}