{
  "id": 2478216,
  "type": "Feature",
  "properties": {
    "tgn:hierarchy":[
        "tgn:2478216",
        "tgn:1000001",
        "tgn:7012149",
        "tgn:1002742",
        "tgn:7007920",
        "tgn:7029392"
    ],
    "tgn:id":2478216,
    "tgn:name":"Mackey Ridge",
    "tgn:placetype":[
        "aat:300266640"
    ]
},
  "bbox": [],
  "geometry": {"coordinates":[-119.0667,48.4333],"type":"Point"}
}