<<<<<<< HEAD
{
  "id": 2155054,
  "type": "Feature",
  "properties": {
    "tgn:hierarchy":[
        "tgn:2155054",
        "tgn:1000001",
        "tgn:7012149",
        "tgn:1002978",
        "tgn:7007252",
        "tgn:7029392"
    ],
    "tgn:id":2155054,
    "tgn:name":"Bear Lake",
    "tgn:placetype":[
        "aat:300008680"
    ]
},
  "bbox": [],
  "geometry": {"coordinates":[-85.9,41.0],"type":"Point"}
}
=======
{"geometry":{"type":"Point","coordinates":[-85.900000,41.000000]},"type":"Feature","properties":{"hierarchy":["tgn:2155054","tgn:1000001","tgn:7012149","tgn:1002978","tgn:7007252","tgn:7029392"],"placetype":["aat:300008680"],"id":2155054,"name:xx":"Bear Lake"}}
>>>>>>> 03f74aca74312dbeaf24d7e61306dd6a786dc3d0
