<<<<<<< HEAD
{
  "id": 7020548,
  "type": "Feature",
  "properties": {
    "tgn:hierarchy":[
        "tgn:7020548",
        "tgn:1000001",
        "tgn:7012149",
        "tgn:2001284",
        "tgn:7007524",
        "tgn:7029392"
    ],
    "tgn:id":7020548,
    "tgn:name":"Meyer Hill",
    "tgn:placetype":[
        "aat:300008798"
    ]
},
  "bbox": [],
  "geometry": {"coordinates":[-112.3,47.5],"type":"Point"}
}
=======
{"geometry":{"type":"Point","coordinates":[-112.300000,47.500000]},"type":"Feature","properties":{"hierarchy":["tgn:7020548","tgn:1000001","tgn:7012149","tgn:2001284","tgn:7007524","tgn:7029392"],"placetype":["aat:300008798"],"id":7020548,"name:xx":"Meyer Hill"}}
>>>>>>> 03f74aca74312dbeaf24d7e61306dd6a786dc3d0
