{
  "id": 2426126,
  "type": "Feature",
  "properties": {
    "tgn:hierarchy":[
        "tgn:2426126",
        "tgn:1000001",
        "tgn:7012149",
        "tgn:1002440",
        "tgn:7007568",
        "tgn:7029392"
    ],
    "tgn:id":2426126,
    "tgn:name":"Jones Brook",
    "tgn:placetype":[
        "aat:300008699"
    ]
},
  "bbox": [],
  "geometry": {"coordinates":[-74.65,43.45],"type":"Point"}
}