{
  "id": 2521003,
  "type": "Feature",
  "properties": {
    "tgn:hierarchy":[
        "tgn:2521003",
        "tgn:1000001",
        "tgn:2000704",
        "tgn:7012149",
        "tgn:7007254",
        "tgn:7029392"
    ],
    "tgn:id":2521003,
    "tgn:name":"Montana Creek",
    "tgn:placetype":[
        "aat:300008706"
    ]
},
  "bbox": [],
  "geometry": {"coordinates":[-98.1167,39.95],"type":"Point"}
}