{
  "id": 2144534,
  "type": "Feature",
  "properties": {
    "tgn:hierarchy":[
        "tgn:2144534",
        "tgn:1000001",
        "tgn:7012149",
        "tgn:2002047",
        "tgn:7007826",
        "tgn:7029392"
    ],
    "tgn:id":2144534,
    "tgn:name":"Balance Branch",
    "tgn:placetype":[
        "aat:300008699"
    ]
},
  "bbox": [],
  "geometry": {"coordinates":[-93.6833,31.0167],"type":"Point"}
}