{
  "id": 7102923,
  "type": "Feature",
  "properties": {
    "tgn:hierarchy":[
        "tgn:7102923",
        "tgn:1000003",
        "tgn:7003678",
        "tgn:7000084",
        "tgn:7029392"
    ],
    "tgn:id":7102923,
    "tgn:name":"Rotes Wasser",
    "tgn:placetype":[
        "aat:300008699"
    ]
},
  "bbox": [],
  "geometry": {"coordinates":[8.816667,50.85],"type":"Point"}
}