{
  "id": 2514831,
  "type": "Feature",
  "properties": {
    "tgn:hierarchy":[
        "tgn:2514831",
        "tgn:1000001",
        "tgn:1002261",
        "tgn:7012149",
        "tgn:7007568",
        "tgn:7029392"
    ],
    "tgn:id":2514831,
    "tgn:name":"Miller Pond",
    "tgn:placetype":[
        "aat:300008680"
    ]
},
  "bbox": [],
  "geometry": {"coordinates":[-76.7833,42.0667],"type":"Point"}
}