<<<<<<< HEAD
{
  "id": 2155769,
  "type": "Feature",
  "properties": {
    "tgn:hierarchy":[
        "tgn:2155769",
        "tgn:1002541",
        "tgn:1000001",
        "tgn:7012149",
        "tgn:7007711",
        "tgn:7029392"
    ],
    "tgn:id":2155769,
    "tgn:name":"Bear Swamp",
    "tgn:placetype":[
        "aat:300008905"
    ]
},
  "bbox": [],
  "geometry": {"coordinates":[-71.5167,41.6],"type":"Point"}
}
=======
{"geometry":{"type":"Point","coordinates":[-71.516700,41.600000]},"type":"Feature","properties":{"hierarchy":["tgn:2155769","tgn:1002541","tgn:1000001","tgn:7012149","tgn:7007711","tgn:7029392"],"placetype":["aat:300008905"],"id":2155769,"name:xx":"Bear Swamp"}}
>>>>>>> 03f74aca74312dbeaf24d7e61306dd6a786dc3d0
