{
  "id": 2296865,
  "type": "Feature",
  "properties": {
    "tgn:hierarchy":[
        "tgn:2296865",
        "tgn:1000001",
        "tgn:7012149",
        "tgn:2001217",
        "tgn:7007523",
        "tgn:7029392"
    ],
    "tgn:id":2296865,
    "tgn:name":"Dry Creek",
    "tgn:placetype":[
        "aat:300008706"
    ]
},
  "bbox": [],
  "geometry": {"coordinates":[-90.35,37.45],"type":"Point"}
}