{
  "id": 7153900,
  "type": "Feature",
  "properties": {
    "tgn:hierarchy":[
        "tgn:7153900",
        "tgn:7003672",
        "tgn:1000003",
        "tgn:7000084",
        "tgn:7029392"
    ],
    "tgn:id":7153900,
    "tgn:name":"Kalihafen",
    "tgn:placetype":[
        "aat:300008678"
    ]
},
  "bbox": [],
  "geometry": {"coordinates":[8.716667,53.133333],"type":"Point"}
}