{
  "id": 7099253,
  "type": "Feature",
  "properties": {
    "tgn:hierarchy":[
        "tgn:7099253",
        "tgn:7003669",
        "tgn:1000003",
        "tgn:7000084",
        "tgn:7029392"
    ],
    "tgn:id":7099253,
    "tgn:name":"Spie\u00dfberg",
    "tgn:placetype":[
        "aat:300008777"
    ]
},
  "bbox": [],
  "geometry": {"coordinates":[11.75,49.333333],"type":"Point"}
}