{
  "id": 7016119,
  "type": "Feature",
  "properties": {
    "tgn:hierarchy":[
        "tgn:7016119",
        "tgn:2000856",
        "tgn:1000001",
        "tgn:7012149",
        "tgn:7007256",
        "tgn:7029392"
    ],
    "tgn:id":7016119,
    "tgn:name":"Burnside",
    "tgn:placetype":[
        "aat:300387016"
    ]
},
  "bbox": [],
  "geometry": {"coordinates":[-90.9167,30.1333],"type":"Point"}
}