{
  "id": 2260607,
  "type": "Feature",
  "properties": {
    "tgn:hierarchy":[
        "tgn:2260607",
        "tgn:1000001",
        "tgn:7012149",
        "tgn:2001052",
        "tgn:7007521",
        "tgn:7029392"
    ],
    "tgn:id":2260607,
    "tgn:name":"County Ditch Number Fortytwo",
    "tgn:placetype":[
        "aat:300006075"
    ]
},
  "bbox": [],
  "geometry": {"coordinates":[-96.2167,47.3833],"type":"Point"}
}