{
  "id": 2733876,
  "type": "Feature",
  "properties": {
    "tgn:hierarchy":[
        "tgn:2733876",
        "tgn:1000001",
        "tgn:7012149",
        "tgn:2000436",
        "tgn:7007248",
        "tgn:7029392"
    ],
    "tgn:id":2733876,
    "tgn:name":"Turner Lake",
    "tgn:placetype":[
        "aat:300008680"
    ]
},
  "bbox": [],
  "geometry": {"coordinates":[-84.4333,32.9833],"type":"Point"}
}