{
  "id": 2716777,
  "type": "Feature",
  "properties": {
    "tgn:hierarchy":[
        "tgn:2716777",
        "tgn:1000001",
        "tgn:7012149",
        "tgn:2001761",
        "tgn:7007712",
        "tgn:7029392"
    ],
    "tgn:id":2716777,
    "tgn:name":"The Woods",
    "tgn:placetype":[
        "aat:300008347"
    ]
},
  "bbox": [],
  "geometry": {"coordinates":[-82.9833,34.65],"type":"Point"}
}