<<<<<<< HEAD
{
  "id": 7114358,
  "type": "Feature",
  "properties": {
    "tgn:hierarchy":[
        "tgn:7114358",
        "tgn:1000003",
        "tgn:7003677",
        "tgn:7000084",
        "tgn:7029392"
    ],
    "tgn:id":7114358,
    "tgn:name":"Robersmann",
    "tgn:placetype":[
        "aat:300000206"
    ]
},
  "bbox": [],
  "geometry": {"coordinates":[7.416667,51.883333],"type":"Point"}
}
=======
{"geometry":{"type":"Point","coordinates":[7.416667,51.883333]},"type":"Feature","properties":{"hierarchy":["tgn:7114358","tgn:1000003","tgn:7003677","tgn:7000084","tgn:7029392"],"placetype":["aat:300000206"],"id":7114358,"name:xx":"Robersmann"}}
>>>>>>> 03f74aca74312dbeaf24d7e61306dd6a786dc3d0
