{
  "id": 7114358,
  "type": "Feature",
  "properties": {
    "tgn:hierarchy":[
        "tgn:7114358",
        "tgn:1000003",
        "tgn:7003677",
        "tgn:7000084",
        "tgn:7029392"
    ],
    "tgn:id":7114358,
    "tgn:name":"Robersmann",
    "tgn:placetype":[
        "aat:300000206"
    ]
},
  "bbox": [],
  "geometry": {"coordinates":[7.416667,51.883333],"type":"Point"}
}