{
  "id": 7429384,
  "type": "Feature",
  "properties": {
    "tgn:hierarchy":[
        "tgn:7429384",
        "tgn:1001853",
        "tgn:1000001",
        "tgn:7005560",
        "tgn:7029392"
    ],
    "tgn:id":7429384,
    "tgn:name":"El Aguaje",
    "tgn:placetype":[
        "aat:300008347"
    ]
},
  "bbox": [],
  "geometry": {"coordinates":[-102.933333,24.783333],"type":"Point"}
}