{
  "id": 2000537,
  "type": "Feature",
  "properties": {
    "tgn:hierarchy":[
        "tgn:2000537",
        "tgn:1000001",
        "tgn:7012149",
        "tgn:7007251",
        "tgn:7029392"
    ],
    "tgn:id":2000537,
    "tgn:name":"White",
    "tgn:placetype":[
        "aat:300387145",
        "aat:300000771"
    ]
},
  "bbox": [],
  "geometry": {"coordinates":[-88.1667,38.0833],"type":"Point"}
}