<<<<<<< HEAD
{
  "id": 2766728,
  "type": "Feature",
  "properties": {
    "tgn:hierarchy":[
        "tgn:2766728",
        "tgn:1000001",
        "tgn:2000774",
        "tgn:7012149",
        "tgn:7007255",
        "tgn:7029392"
    ],
    "tgn:id":2766728,
    "tgn:name":"White Oak Ridge",
    "tgn:placetype":[
        "aat:300266640"
    ]
},
  "bbox": [],
  "geometry": {"coordinates":[-85.7667,38.05],"type":"Point"}
}
=======
{"geometry":{"type":"Point","coordinates":[-85.766700,38.050000]},"type":"Feature","properties":{"hierarchy":["tgn:2766728","tgn:1000001","tgn:2000774","tgn:7012149","tgn:7007255","tgn:7029392"],"placetype":["aat:300266640"],"id":2766728,"name:xx":"White Oak Ridge"}}
>>>>>>> 03f74aca74312dbeaf24d7e61306dd6a786dc3d0
