{
  "id": 2468547,
  "type": "Feature",
  "properties": {
    "tgn:hierarchy":[
        "tgn:2468547",
        "tgn:1000001",
        "tgn:1002473",
        "tgn:7012149",
        "tgn:7007240",
        "tgn:7029392"
    ],
    "tgn:id":2468547,
    "tgn:name":"Long Pond",
    "tgn:placetype":[
        "aat:300008680"
    ]
},
  "bbox": [],
  "geometry": {"coordinates":[-82.2833,28.45],"type":"Point"}
}