{
  "id": 2374327,
  "type": "Feature",
  "properties": {
    "tgn:hierarchy":[
        "tgn:2374327",
        "tgn:1000001",
        "tgn:7012149",
        "tgn:7007157",
        "tgn:1002972",
        "tgn:7029392"
    ],
    "tgn:id":2374327,
    "tgn:name":"Hampton Canyon",
    "tgn:placetype":[
        "aat:300008761"
    ]
},
  "bbox": [],
  "geometry": {"coordinates":[-119.15,34.3667],"type":"Point"}
}