{
  "id": 2571348,
  "type": "Feature",
  "properties": {
    "tgn:hierarchy":[
        "tgn:2571348",
        "tgn:1000001",
        "tgn:1002665",
        "tgn:7012149",
        "tgn:7007517",
        "tgn:7029392"
    ],
    "tgn:id":2571348,
    "tgn:name":"Paul Hill",
    "tgn:placetype":[
        "aat:300008798"
    ]
},
  "bbox": [],
  "geometry": {"coordinates":[-71.3667,42.2333],"type":"Point"}
}