{
  "id": 7517410,
  "type": "Feature",
  "properties": {
    "tgn:hierarchy":[
        "tgn:7517410",
        "tgn:1009227",
        "tgn:1000226",
        "tgn:7016729",
        "tgn:1000006",
        "tgn:7029392"
    ],
    "tgn:id":7517410,
    "tgn:name:en":"Nikau Bay",
    "tgn:placetype":[
        "aat:300132316"
    ]
},
  "bbox": [],
  "geometry": {"coordinates":[173.883333,-41.166667],"type":"Point"}
}