{
  "id": 1056207,
  "type": "Feature",
  "properties": {
    "tgn:hierarchy":[
        "tgn:1056207",
        "tgn:1000004",
        "tgn:7011478",
        "tgn:7006655",
        "tgn:7029392"
    ],
    "tgn:id":1056207,
    "tgn:name":"Kyrkkazyk",
    "tgn:placetype":[
        "aat:300008347"
    ]
},
  "bbox": [],
  "geometry": {"coordinates":[72.6833,41.8333],"type":"Point"}
}