{
  "id": 1121815,
  "type": "Feature",
  "properties": {
    "tgn:hierarchy":[
        "tgn:1121815",
        "tgn:1000004",
        "tgn:1003405",
        "tgn:7018214",
        "tgn:7002435",
        "tgn:7029392"
    ],
    "tgn:id":1121815,
    "tgn:name":"Ber'ozovaja",
    "tgn:placetype":[
        "aat:300008707"
    ]
},
  "bbox": [],
  "geometry": {"coordinates":[41.05,48.5167],"type":"Point"}
}