{
  "id": 2481269,
  "type": "Feature",
  "properties": {
    "tgn:hierarchy":[
        "tgn:2481269",
        "tgn:1000001",
        "tgn:7012149",
        "tgn:1003038",
        "tgn:7007517",
        "tgn:7029392"
    ],
    "tgn:id":2481269,
    "tgn:name":"Lamberton Brook Reservoir",
    "tgn:placetype":[
        "aat:300006191"
    ]
},
  "bbox": [],
  "geometry": {"coordinates":[-72.1667,42.2333],"type":"Point"}
}