{
  "id": 2355654,
  "type": "Feature",
  "properties": {
    "tgn:hierarchy":[
        "tgn:2355654",
        "tgn:1000001",
        "tgn:7012149",
        "tgn:1002988",
        "tgn:7007710",
        "tgn:7029392"
    ],
    "tgn:id":2355654,
    "tgn:name":"Goose Heaven Hill",
    "tgn:placetype":[
        "aat:300008798"
    ]
},
  "bbox": [],
  "geometry": {"coordinates":[-79.0833,41.8833],"type":"Point"}
}