{
  "id": 2600438,
  "type": "Feature",
  "properties": {
    "tgn:hierarchy":[
        "tgn:2600438",
        "tgn:1000001",
        "tgn:7012149",
        "tgn:2002374",
        "tgn:7007923",
        "tgn:7029392"
    ],
    "tgn:id":2600438,
    "tgn:name":"Puff Reservoir",
    "tgn:placetype":[
        "aat:300006191"
    ]
},
  "bbox": [],
  "geometry": {"coordinates":[-106.0333,44.3833],"type":"Point"}
}