<<<<<<< HEAD
{
  "id": 2331246,
  "type": "Feature",
  "properties": {
    "tgn:hierarchy":[
        "tgn:2331246",
        "tgn:1000001",
        "tgn:7012149",
        "tgn:2000238",
        "tgn:7007158",
        "tgn:7029392"
    ],
    "tgn:id":2331246,
    "tgn:name":"Flat Top Ridge",
    "tgn:placetype":[
        "aat:300266640"
    ]
},
  "bbox": [],
  "geometry": {"coordinates":[-105.4,38.7167],"type":"Point"}
}
=======
{"geometry":{"type":"Point","coordinates":[-105.400000,38.716700]},"type":"Feature","properties":{"hierarchy":["tgn:2331246","tgn:1000001","tgn:7012149","tgn:2000238","tgn:7007158","tgn:7029392"],"placetype":["aat:300266640"],"id":2331246,"name:xx":"Flat Top Ridge"}}
>>>>>>> 03f74aca74312dbeaf24d7e61306dd6a786dc3d0
