{
  "id": 2090461,
  "type": "Feature",
  "properties": {
    "tgn:hierarchy":[
        "tgn:2090461",
        "tgn:1002153",
        "tgn:1000001",
        "tgn:7012149",
        "tgn:7007710",
        "tgn:7029392"
    ],
    "tgn:id":2090461,
    "tgn:name":"McGrann",
    "tgn:placetype":[
        "aat:300008347"
    ]
},
  "bbox": [],
  "geometry": {"coordinates":[-79.5167,40.7667],"type":"Point"}
}