{
  "id": 2083311,
  "type": "Feature",
  "properties": {
    "tgn:hierarchy":[
        "tgn:2083311",
        "tgn:1000001",
        "tgn:7012149",
        "tgn:2001687",
        "tgn:7007707",
        "tgn:7029392"
    ],
    "tgn:id":2083311,
    "tgn:name":"Grimes",
    "tgn:placetype":[
        "aat:300008347",
        "aat:300387210"
    ]
},
  "bbox": [],
  "geometry": {"coordinates":[-99.75,35.45],"type":"Point"}
}