{
  "id": 2311527,
  "type": "Feature",
  "properties": {
    "tgn:hierarchy":[
        "tgn:2311527",
        "tgn:1000001",
        "tgn:7012149",
        "tgn:2001504",
        "tgn:7007709",
        "tgn:7029392"
    ],
    "tgn:id":2311527,
    "tgn:name":"Edneyville",
    "tgn:placetype":[
        "aat:300008798"
    ]
},
  "bbox": [],
  "geometry": {"coordinates":[-82.3333,35.3833],"type":"Point"}
}