<<<<<<< HEAD
{
  "id": 2333351,
  "type": "Feature",
  "properties": {
    "tgn:hierarchy":[
        "tgn:2333351",
        "tgn:1000001",
        "tgn:2000924",
        "tgn:7012149",
        "tgn:7007515",
        "tgn:7029392"
    ],
    "tgn:id":2333351,
    "tgn:name":"Foggs Hill",
    "tgn:placetype":[
        "aat:300008798"
    ]
},
  "bbox": [],
  "geometry": {"coordinates":[-69.1333,44.0],"type":"Point"}
}
=======
{"geometry":{"type":"Point","coordinates":[-69.133300,44.000000]},"type":"Feature","properties":{"hierarchy":["tgn:2333351","tgn:1000001","tgn:2000924","tgn:7012149","tgn:7007515","tgn:7029392"],"placetype":["aat:300008798"],"id":2333351,"name:xx":"Foggs Hill"}}
>>>>>>> 03f74aca74312dbeaf24d7e61306dd6a786dc3d0
