{
  "id": 7590489,
  "type": "Feature",
  "properties": {
    "tgn:hierarchy":[
        "tgn:7590489",
        "tgn:1000004",
        "tgn:1001871",
        "tgn:7000198",
        "tgn:7029392"
    ],
    "tgn:id":7590489,
    "tgn:name:en":"T\u0101jpur Tih\u0101ra Khurd",
    "tgn:placetype":[
        "aat:300008347"
    ]
},
  "bbox": [],
  "geometry": {"coordinates":[76.932222,28.982778],"type":"Point"}
}