{
  "id": 7485179,
  "type": "Feature",
  "properties": {
    "tgn:hierarchy":[
        "tgn:7485179",
        "tgn:1000004",
        "tgn:7491221",
        "tgn:1000141",
        "tgn:7029392"
    ],
    "tgn:id":7485179,
    "tgn:name":"Baluo'anying",
    "tgn:placetype":[
        "aat:300008347"
    ]
},
  "bbox": [],
  "geometry": {"coordinates":[121.265556,22.997222],"type":"Point"}
}