<<<<<<< HEAD
{
  "id": 7175446,
  "type": "Feature",
  "properties": {
    "tgn:hierarchy":[
        "tgn:7175446",
        "tgn:1000003",
        "tgn:7000094",
        "tgn:7000084",
        "tgn:7029392"
    ],
    "tgn:id":7175446,
    "tgn:name":"Gro\u00dfe Strand Wiese",
    "tgn:placetype":[
        "aat:300386990"
    ]
},
  "bbox": [],
  "geometry": {"coordinates":[13.8,54.166667],"type":"Point"}
}
=======
{"geometry":{"type":"Point","coordinates":[13.800000,54.166667]},"type":"Feature","properties":{"hierarchy":["tgn:7175446","tgn:1000003","tgn:7000094","tgn:7000084","tgn:7029392"],"placetype":["aat:300386990"],"id":7175446,"name:xx":"Gro\u00dfe Strand Wiese"}}
>>>>>>> 03f74aca74312dbeaf24d7e61306dd6a786dc3d0
