{
  "id": 1078988,
  "type": "Feature",
  "properties": {
    "tgn:hierarchy":[
        "tgn:1078988",
        "tgn:1000004",
        "tgn:7016768",
        "tgn:7000231",
        "tgn:7029392"
    ],
    "tgn:id":1078988,
    "tgn:name":"B\u012bdokht",
    "tgn:placetype":[
        "aat:300008347"
    ]
},
  "bbox": [],
  "geometry": {"coordinates":[58.7667,34.35],"type":"Point"}
}