{
  "id": 2633958,
  "type": "Feature",
  "properties": {
    "tgn:hierarchy":[
        "tgn:2633958",
        "tgn:1000001",
        "tgn:7012149",
        "tgn:1002518",
        "tgn:7007568",
        "tgn:7029392"
    ],
    "tgn:id":2633958,
    "tgn:name":"Rusho Bay",
    "tgn:placetype":[
        "aat:300132316"
    ]
},
  "bbox": [],
  "geometry": {"coordinates":[-76.0833,44.2667],"type":"Point"}
}