<<<<<<< HEAD
{
  "id": 7360630,
  "type": "Feature",
  "properties": {
    "tgn:hierarchy":[
        "tgn:7360630",
        "tgn:7005583",
        "tgn:1000001",
        "tgn:7005560",
        "tgn:7029392"
    ],
    "tgn:id":7360630,
    "tgn:name":"Ejido Carolina",
    "tgn:placetype":[
        "aat:300008347"
    ]
},
  "bbox": [],
  "geometry": {"coordinates":[-103.45,26.183333],"type":"Point"}
}
=======
{"geometry":{"type":"Point","coordinates":[-103.450000,26.183333]},"type":"Feature","properties":{"hierarchy":["tgn:7360630","tgn:7005583","tgn:1000001","tgn:7005560","tgn:7029392"],"placetype":["aat:300008347"],"id":7360630,"name:xx":"Ejido Carolina"}}
>>>>>>> 03f74aca74312dbeaf24d7e61306dd6a786dc3d0
