<<<<<<< HEAD
{
  "id": 7376999,
  "type": "Feature",
  "properties": {
    "tgn:hierarchy":[
        "tgn:7376999",
        "tgn:7005580",
        "tgn:1000001",
        "tgn:7005560",
        "tgn:7029392"
    ],
    "tgn:id":7376999,
    "tgn:name":"Las Mar\u00edas",
    "tgn:placetype":[
        "aat:300008347"
    ]
},
  "bbox": [],
  "geometry": {"coordinates":[-93.95,16.2],"type":"Point"}
}
=======
{"geometry":{"type":"Point","coordinates":[-93.950000,16.200000]},"type":"Feature","properties":{"hierarchy":["tgn:7376999","tgn:7005580","tgn:1000001","tgn:7005560","tgn:7029392"],"placetype":["aat:300008347"],"id":7376999,"name:xx":"Las Mar\u00edas"}}
>>>>>>> 03f74aca74312dbeaf24d7e61306dd6a786dc3d0
