<<<<<<< HEAD
{
  "id": 7110495,
  "type": "Feature",
  "properties": {
    "tgn:hierarchy":[
        "tgn:7110495",
        "tgn:7003669",
        "tgn:1000003",
        "tgn:7000084",
        "tgn:7029392"
    ],
    "tgn:id":7110495,
    "tgn:name":"Reichertswies",
    "tgn:placetype":[
        "aat:300008347"
    ]
},
  "bbox": [],
  "geometry": {"coordinates":[10.9,48.816667],"type":"Point"}
}
=======
{"geometry":{"type":"Point","coordinates":[10.900000,48.816667]},"type":"Feature","properties":{"hierarchy":["tgn:7110495","tgn:7003669","tgn:1000003","tgn:7000084","tgn:7029392"],"placetype":["aat:300008347"],"id":7110495,"name:xx":"Reichertswies"}}
>>>>>>> 03f74aca74312dbeaf24d7e61306dd6a786dc3d0
