{
  "id": 2193799,
  "type": "Feature",
  "properties": {
    "tgn:hierarchy":[
        "tgn:2193799",
        "tgn:1002165",
        "tgn:1000001",
        "tgn:7012149",
        "tgn:7007517",
        "tgn:7029392"
    ],
    "tgn:id":2193799,
    "tgn:name":"Briants Neck",
    "tgn:placetype":[
        "aat:300008850"
    ]
},
  "bbox": [],
  "geometry": {"coordinates":[-70.45,41.65],"type":"Point"}
}