{
  "id": 7062067,
  "type": "Feature",
  "properties": {
    "tgn:hierarchy":[
        "tgn:7062067",
        "tgn:1000003",
        "tgn:7003685",
        "tgn:7000084",
        "tgn:7029392"
    ],
    "tgn:id":7062067,
    "tgn:name":"Arnsdorf",
    "tgn:placetype":[
        "aat:300008347"
    ]
},
  "bbox": [],
  "geometry": {"coordinates":[13.133333,51.016667],"type":"Point"}
}