{
  "id": 2054468,
  "type": "Feature",
  "properties": {
    "tgn:hierarchy":[
        "tgn:2054468",
        "tgn:1000001",
        "tgn:2001011",
        "tgn:7012149",
        "tgn:7007521",
        "tgn:7029392"
    ],
    "tgn:id":2054468,
    "tgn:name":"Franconia",
    "tgn:placetype":[
        "aat:300008347"
    ]
},
  "bbox": [],
  "geometry": {"coordinates":[-92.6833,45.3667],"type":"Point"}
}