{
  "id": 7319930,
  "type": "Feature",
  "properties": {
    "tgn:hierarchy":[
        "tgn:7319930",
        "tgn:1001692",
        "tgn:1000049",
        "tgn:1000002",
        "tgn:7029392"
    ],
    "tgn:id":7319930,
    "tgn:name":"\u00c1guila, Alto",
    "tgn:placetype":[
        "aat:300008795"
    ]
},
  "bbox": [],
  "geometry": {"coordinates":[-72.65,-38.15],"type":"Point"}
}