{
  "id": 7292045,
  "type": "Feature",
  "properties": {
    "tgn:hierarchy":[
        "tgn:7292045",
        "tgn:1001630",
        "tgn:1000049",
        "tgn:1000002",
        "tgn:7029392"
    ],
    "tgn:id":7292045,
    "tgn:name":"Flamenco, Punta",
    "tgn:placetype":[
        "aat:300386846"
    ]
},
  "bbox": [],
  "geometry": {"coordinates":[-70.716667,-26.533333],"type":"Point"}
}