{
  "id": 2250567,
  "type": "Feature",
  "properties": {
    "tgn:hierarchy":[
        "tgn:2250567",
        "tgn:1000001",
        "tgn:2000458",
        "tgn:7012149",
        "tgn:7007250",
        "tgn:7029392"
    ],
    "tgn:id":2250567,
    "tgn:name":"Colorade Gulch",
    "tgn:placetype":[
        "aat:300008761"
    ]
},
  "bbox": [],
  "geometry": {"coordinates":[-114.3167,43.4667],"type":"Point"}
}