<<<<<<< HEAD
{
  "id": 2250567,
  "type": "Feature",
  "properties": {
    "tgn:hierarchy":[
        "tgn:2250567",
        "tgn:1000001",
        "tgn:2000458",
        "tgn:7012149",
        "tgn:7007250",
        "tgn:7029392"
    ],
    "tgn:id":2250567,
    "tgn:name":"Colorade Gulch",
    "tgn:placetype":[
        "aat:300008761"
    ]
},
  "bbox": [],
  "geometry": {"coordinates":[-114.3167,43.4667],"type":"Point"}
}
=======
{"geometry":{"type":"Point","coordinates":[-114.316700,43.466700]},"type":"Feature","properties":{"hierarchy":["tgn:2250567","tgn:1000001","tgn:2000458","tgn:7012149","tgn:7007250","tgn:7029392"],"placetype":["aat:300008761"],"id":2250567,"name:xx":"Colorade Gulch"}}
>>>>>>> 03f74aca74312dbeaf24d7e61306dd6a786dc3d0
