{
  "id": 1026680,
  "type": "Feature",
  "properties": {
    "tgn:hierarchy":[
        "tgn:1026680",
        "tgn:7003458",
        "tgn:1000003",
        "tgn:1000063",
        "tgn:7018236",
        "tgn:7029392"
    ],
    "tgn:id":1026680,
    "tgn:name":"Poelkapelle",
    "tgn:placetype":[
        "aat:300008347"
    ]
},
  "bbox": [],
  "geometry": {"coordinates":[2.956766,50.917904],"type":"Point"}
}