{
  "id": 2606304,
  "type": "Feature",
  "properties": {
    "tgn:hierarchy":[
        "tgn:2606304",
        "tgn:1000001",
        "tgn:7012149",
        "tgn:7014185",
        "tgn:7007710",
        "tgn:7029392"
    ],
    "tgn:id":2606304,
    "tgn:name":"Ralph",
    "tgn:placetype":[
        "aat:300008347"
    ]
},
  "bbox": [],
  "geometry": {"coordinates":[-79.8833,39.9167],"type":"Point"}
}