{
  "id": 7419278,
  "type": "Feature",
  "properties": {
    "tgn:hierarchy":[
        "tgn:7419278",
        "tgn:1001835",
        "tgn:1000001",
        "tgn:7005560",
        "tgn:7029392"
    ],
    "tgn:id":7419278,
    "tgn:name":"La Misi\u00f3n, Boca",
    "tgn:placetype":[
        "aat:300387057"
    ]
},
  "bbox": [],
  "geometry": {"coordinates":[-116.884722,32.091389],"type":"Point"}
}