{
  "id": 7419906,
  "type": "Feature",
  "properties": {
    "tgn:hierarchy":[
        "tgn:7419906",
        "tgn:1001836",
        "tgn:1000001",
        "tgn:7005560",
        "tgn:7029392"
    ],
    "tgn:id":7419906,
    "tgn:name":"El Salado, R\u00edo",
    "tgn:placetype":[
        "aat:300008699"
    ]
},
  "bbox": [],
  "geometry": {"coordinates":[-110.241667,23.408889],"type":"Point"}
}