{
  "id": 2570721,
  "type": "Feature",
  "properties": {
    "tgn:hierarchy":[
        "tgn:2570721",
        "tgn:1000001",
        "tgn:7012149",
        "tgn:7007712",
        "tgn:7029392"
    ],
    "tgn:id":2570721,
    "tgn:name":"Patsy Island",
    "tgn:placetype":[
        "aat:300008791"
    ]
},
  "bbox": [],
  "geometry": {"coordinates":[-79.3167,33.95],"type":"Point"}
}