{
  "id": 2467524,
  "type": "Feature",
  "properties": {
    "tgn:hierarchy":[
        "tgn:2467524",
        "tgn:1000001",
        "tgn:7012149",
        "tgn:1002669",
        "tgn:7007710",
        "tgn:7029392"
    ],
    "tgn:id":2467524,
    "tgn:name":"Long Hollow",
    "tgn:placetype":[
        "aat:300008761"
    ]
},
  "bbox": [],
  "geometry": {"coordinates":[-77.8333,40.45],"type":"Point"}
}