{
  "id": 7002757,
  "type": "Feature",
  "properties": {
    "tgn:hierarchy":[
        "tgn:7002757",
        "tgn:1001240",
        "tgn:1000004",
        "tgn:7018455",
        "tgn:1000144",
        "tgn:7029392"
    ],
    "tgn:id":7002757,
    "tgn:name":"Tanyeri",
    "tgn:placetype":[
        "aat:300008347"
    ]
},
  "bbox": [],
  "geometry": {"coordinates":[39.8333,39.6167],"type":"Point"}
}