{
  "id": 2031225,
  "type": "Feature",
  "properties": {
    "tgn:hierarchy":[
        "tgn:2031225",
        "tgn:1000001",
        "tgn:7012149",
        "tgn:1002946",
        "tgn:7007252",
        "tgn:7029392"
    ],
    "tgn:id":2031225,
    "tgn:name":"Buck Creek",
    "tgn:placetype":[
        "aat:300008347"
    ]
},
  "bbox": [],
  "geometry": {"coordinates":[-86.75,40.4833],"type":"Point"}
}