{
  "id": 2427469,
  "type": "Feature",
  "properties": {
    "tgn:hierarchy":[
        "tgn:2427469",
        "tgn:1000001",
        "tgn:7012149",
        "tgn:2001856",
        "tgn:7007825",
        "tgn:7029392"
    ],
    "tgn:id":2427469,
    "tgn:name":"Jordan Spring Branch",
    "tgn:placetype":[
        "aat:300008699"
    ]
},
  "bbox": [],
  "geometry": {"coordinates":[-88.0667,35.7167],"type":"Point"}
}