{
  "id": 7396026,
  "type": "Feature",
  "properties": {
    "tgn:hierarchy":[
        "tgn:7396026",
        "tgn:7005583",
        "tgn:1000001",
        "tgn:7005560",
        "tgn:7029392"
    ],
    "tgn:id":7396026,
    "tgn:name":"San Felipe",
    "tgn:placetype":[
        "aat:300008347"
    ]
},
  "bbox": [],
  "geometry": {"coordinates":[-104.683333,24.416667],"type":"Point"}
}