{
  "id": 7528888,
  "type": "Feature",
  "properties": {
    "tgn:hierarchy":[
        "tgn:7528888",
        "tgn:7001242",
        "tgn:7001311",
        "tgn:7016833",
        "tgn:7029392"
    ],
    "tgn:id":7528888,
    "tgn:name:en":"S\u012bd\u012b al Ghar\u012bb",
    "tgn:placetype":[
        "aat:300005926"
    ]
},
  "bbox": [],
  "geometry": {"coordinates":[32.819677,26.095633],"type":"Point"}
}