{
  "id": 7383320,
  "type": "Feature",
  "properties": {
    "tgn:hierarchy":[
        "tgn:7383320",
        "tgn:1000001",
        "tgn:7005597",
        "tgn:7005560",
        "tgn:7029392"
    ],
    "tgn:id":7383320,
    "tgn:name":"Rancho Mulas",
    "tgn:placetype":[
        "aat:300000241"
    ]
},
  "bbox": [],
  "geometry": {"coordinates":[-99.615278,24.189722],"type":"Point"}
}