{
  "id": 7230281,
  "type": "Feature",
  "properties": {
    "tgn:hierarchy":[
        "tgn:7230281",
        "tgn:7002690",
        "tgn:7012056",
        "tgn:1000003",
        "tgn:1000074",
        "tgn:7029392"
    ],
    "tgn:id":7230281,
    "tgn:name":"Kambi\u00e1",
    "tgn:placetype":[
        "aat:300008347"
    ]
},
  "bbox": [],
  "geometry": {"coordinates":[24.216667,35.45],"type":"Point"}
}