<<<<<<< HEAD
{
  "id": 2250274,
  "type": "Feature",
  "properties": {
    "tgn:hierarchy":[
        "tgn:2250274",
        "tgn:2001172",
        "tgn:1000001",
        "tgn:7012149",
        "tgn:7007523",
        "tgn:7029392"
    ],
    "tgn:id":2250274,
    "tgn:name":"Collins Shoals",
    "tgn:placetype":[
        "aat:300132348"
    ]
},
  "bbox": [],
  "geometry": {"coordinates":[-94.2,38.0333],"type":"Point"}
}
=======
{"geometry":{"type":"Point","coordinates":[-94.200000,38.033300]},"type":"Feature","properties":{"hierarchy":["tgn:2250274","tgn:2001172","tgn:1000001","tgn:7012149","tgn:7007523","tgn:7029392"],"placetype":["aat:300132348"],"id":2250274,"name:xx":"Collins Shoals"}}
>>>>>>> 03f74aca74312dbeaf24d7e61306dd6a786dc3d0
