{
  "id": 7108697,
  "type": "Feature",
  "properties": {
    "tgn:hierarchy":[
        "tgn:7108697",
        "tgn:7003669",
        "tgn:1000003",
        "tgn:7000084",
        "tgn:7029392"
    ],
    "tgn:id":7108697,
    "tgn:name":"Regina-See",
    "tgn:placetype":[
        "aat:300008680"
    ]
},
  "bbox": [],
  "geometry": {"coordinates":[11.216667,50.283333],"type":"Point"}
}