<<<<<<< HEAD
{
  "id": 7478647,
  "type": "Feature",
  "properties": {
    "tgn:hierarchy":[
        "tgn:7478647",
        "tgn:1000004",
        "tgn:7489179",
        "tgn:1000141",
        "tgn:7029392"
    ],
    "tgn:id":7478647,
    "tgn:name":"Shimin Guoxiao",
    "tgn:placetype":[
        "aat:300006495"
    ]
},
  "bbox": [],
  "geometry": {"coordinates":[121.854353,24.5913],"type":"Point"}
}
=======
{"geometry":{"type":"Point","coordinates":[121.854353,24.591300]},"type":"Feature","properties":{"hierarchy":["tgn:7478647","tgn:1000004","tgn:7489179","tgn:1000141","tgn:7029392"],"placetype":["aat:300006495"],"id":7478647,"name:xx":"Shimin Guoxiao"}}
>>>>>>> 03f74aca74312dbeaf24d7e61306dd6a786dc3d0
