{
  "id": 7588598,
  "type": "Feature",
  "properties": {
    "tgn:hierarchy":[
        "tgn:7588598",
        "tgn:1000004",
        "tgn:7000198",
        "tgn:1001977",
        "tgn:7029392"
    ],
    "tgn:id":7588598,
    "tgn:name:en":"Sonakhal",
    "tgn:placetype":[
        "aat:300008347"
    ]
},
  "bbox": [],
  "geometry": {"coordinates":[88.711129,22.230744],"type":"Point"}
}