{
  "id": 7183072,
  "type": "Feature",
  "properties": {
    "tgn:hierarchy":[
        "tgn:7183072",
        "tgn:7003669",
        "tgn:1000003",
        "tgn:7000084",
        "tgn:7029392"
    ],
    "tgn:id":7183072,
    "tgn:name":"F\u00fcnfeichen",
    "tgn:placetype":[
        "aat:300000206"
    ]
},
  "bbox": [],
  "geometry": {"coordinates":[13.083333,48.35],"type":"Point"}
}