{
  "id": 2372608,
  "type": "Feature",
  "properties": {
    "tgn:hierarchy":[
        "tgn:2372608",
        "tgn:1000001",
        "tgn:2000462",
        "tgn:7012149",
        "tgn:7007250",
        "tgn:7029392"
    ],
    "tgn:id":2372608,
    "tgn:name":"Hall Creek",
    "tgn:placetype":[
        "aat:300008706"
    ]
},
  "bbox": [],
  "geometry": {"coordinates":[-116.3833,48.9667],"type":"Point"}
}