{
  "id": 2015671,
  "type": "Feature",
  "properties": {
    "tgn:hierarchy":[
        "tgn:2015671",
        "tgn:1000001",
        "tgn:7012149",
        "tgn:2000216",
        "tgn:7007158",
        "tgn:7029392"
    ],
    "tgn:id":2015671,
    "tgn:name":"Gore",
    "tgn:placetype":[
        "aat:300387016"
    ]
},
  "bbox": [],
  "geometry": {"coordinates":[-106.4167,40.0333],"type":"Point"}
}