{
  "id": 2785851,
  "type": "Feature",
  "properties": {
    "tgn:hierarchy":[
        "tgn:2785851",
        "tgn:7002659",
        "tgn:1000001",
        "tgn:7012149",
        "tgn:2000055",
        "tgn:7029392"
    ],
    "tgn:id":2785851,
    "tgn:name":"York Prospect",
    "tgn:placetype":[
        "aat:300000390"
    ]
},
  "bbox": [],
  "geometry": {"coordinates":[-85.5333,33.4833],"type":"Point"}
}