{
  "id": 1060023,
  "type": "Feature",
  "properties": {
    "tgn:hierarchy":[
        "tgn:1060023",
        "tgn:1000003",
        "tgn:7016798",
        "tgn:7006660",
        "tgn:7029392"
    ],
    "tgn:id":1060023,
    "tgn:name":"Tyachiv",
    "tgn:placetype":[
        "aat:300008347"
    ]
},
  "bbox": [],
  "geometry": {"coordinates":[23.5667,48.0333],"type":"Point"}
}