{
  "id": 7498582,
  "type": "Feature",
  "properties": {
    "tgn:hierarchy":[
        "tgn:7498582",
        "tgn:1000004",
        "tgn:7491221",
        "tgn:1000141",
        "tgn:7029392"
    ],
    "tgn:id":7498582,
    "tgn:name":"Nanping Qiao",
    "tgn:placetype":[
        "aat:300007836"
    ]
},
  "bbox": [],
  "geometry": {"coordinates":[121.1065,22.776],"type":"Point"}
}