{
  "id": 1058071,
  "type": "Feature",
  "properties": {
    "tgn:hierarchy":[
        "tgn:1058071",
        "tgn:1000003",
        "tgn:7011667",
        "tgn:7006660",
        "tgn:7029392"
    ],
    "tgn:id":1058071,
    "tgn:name":"Ostroh",
    "tgn:placetype":[
        "aat:300008347"
    ]
},
  "bbox": [],
  "geometry": {"coordinates":[26.4833,50.3333],"type":"Point"}
}