{
  "id": 7220029,
  "type": "Feature",
  "properties": {
    "tgn:hierarchy":[
        "tgn:7220029",
        "tgn:7002748",
        "tgn:7001399",
        "tgn:1000003",
        "tgn:1000074",
        "tgn:7029392"
    ],
    "tgn:id":7220029,
    "tgn:name":"Vero\u00fasia",
    "tgn:placetype":[
        "aat:300266640"
    ]
},
  "bbox": [],
  "geometry": {"coordinates":[21.459167,39.322222],"type":"Point"}
}