{
  "id": 7345862,
  "type": "Feature",
  "properties": {
    "tgn:hierarchy":[
        "tgn:7345862",
        "tgn:7002760",
        "tgn:1000003",
        "tgn:1000095",
        "tgn:7029392"
    ],
    "tgn:id":7345862,
    "tgn:name":"B\u00e1dames",
    "tgn:placetype":[
        "aat:300008347"
    ]
},
  "bbox": [],
  "geometry": {"coordinates":[-3.483333,43.35],"type":"Point"}
}