{
  "id": 2777191,
  "type": "Feature",
  "properties": {
    "tgn:hierarchy":[
        "tgn:2777191",
        "tgn:1000001",
        "tgn:7012149",
        "tgn:2002371",
        "tgn:7007923",
        "tgn:7029392"
    ],
    "tgn:id":2777191,
    "tgn:name":"Windy, Mount",
    "tgn:placetype":[
        "aat:300008798"
    ]
},
  "bbox": [],
  "geometry": {"coordinates":[-109.2667,43.0667],"type":"Point"}
}