<<<<<<< HEAD
{
  "id": 7026212,
  "type": "Feature",
  "properties": {
    "tgn:hierarchy":[
        "tgn:7026212",
        "tgn:7002445",
        "tgn:1000003",
        "tgn:7008131",
        "tgn:7008591",
        "tgn:7029392"
    ],
    "tgn:id":7026212,
    "tgn:name":"Great Henny",
    "tgn:placetype":[
        "aat:300008347",
        "aat:300008369"
    ]
},
  "bbox": [],
  "geometry": {"coordinates":[0.7167,52.0],"type":"Point"}
}
=======
{"geometry":{"type":"Point","coordinates":[0.716700,52.000000]},"type":"Feature","properties":{"hierarchy":["tgn:7026212","tgn:7002445","tgn:1000003","tgn:7008131","tgn:7008591","tgn:7029392"],"placetype":["aat:300008347","aat:300008369"],"id":7026212,"name:xx":"Great Henny"}}
>>>>>>> 03f74aca74312dbeaf24d7e61306dd6a786dc3d0
