<<<<<<< HEAD
{
  "id": 7370942,
  "type": "Feature",
  "properties": {
    "tgn:hierarchy":[
        "tgn:7370942",
        "tgn:1000001",
        "tgn:7005591",
        "tgn:7005560",
        "tgn:7029392"
    ],
    "tgn:id":7370942,
    "tgn:name":"Guigoxo",
    "tgn:placetype":[
        "aat:300008347"
    ]
},
  "bbox": [],
  "geometry": {"coordinates":[-94.933333,16.866667],"type":"Point"}
}
=======
{"geometry":{"type":"Point","coordinates":[-94.933333,16.866667]},"type":"Feature","properties":{"hierarchy":["tgn:7370942","tgn:1000001","tgn:7005591","tgn:7005560","tgn:7029392"],"placetype":["aat:300008347"],"id":7370942,"name:xx":"Guigoxo"}}
>>>>>>> 03f74aca74312dbeaf24d7e61306dd6a786dc3d0
