{
  "id": 7544638,
  "type": "Feature",
  "properties": {
    "tgn:hierarchy":[
        "tgn:7544638",
        "tgn:1001828",
        "tgn:1000004",
        "tgn:7000198",
        "tgn:7029392"
    ],
    "tgn:id":7544638,
    "tgn:name:en":"Kushmanchi",
    "tgn:placetype":[
        "aat:300008347"
    ]
},
  "bbox": [],
  "geometry": {"coordinates":[79.95,17.216667],"type":"Point"}
}