{
  "id": 2629248,
  "type": "Feature",
  "properties": {
    "tgn:hierarchy":[
        "tgn:2629248",
        "tgn:1000001",
        "tgn:7012149",
        "tgn:7007157",
        "tgn:1002972",
        "tgn:7029392"
    ],
    "tgn:id":2629248,
    "tgn:name":"Rose Valley Creek",
    "tgn:placetype":[
        "aat:300008706"
    ]
},
  "bbox": [],
  "geometry": {"coordinates":[-119.1667,34.5167],"type":"Point"}
}