{
  "id": 2042086,
  "type": "Feature",
  "properties": {
    "tgn:hierarchy":[
        "tgn:2042086",
        "tgn:1000001",
        "tgn:7012149",
        "tgn:2000831",
        "tgn:7007255",
        "tgn:7029392"
    ],
    "tgn:id":2042086,
    "tgn:name":"Zag",
    "tgn:placetype":[
        "aat:300008347",
        "aat:300387210"
    ]
},
  "bbox": [],
  "geometry": {"coordinates":[-83.35,37.9833],"type":"Point"}
}