{
  "id": 2233803,
  "type": "Feature",
  "properties": {
    "tgn:hierarchy":[
        "tgn:2233803",
        "tgn:7002659",
        "tgn:1000001",
        "tgn:7012149",
        "tgn:7029392"
    ],
    "tgn:id":2233803,
    "tgn:name":"Chatahospee Creek",
    "tgn:placetype":[
        "aat:300008706"
    ]
},
  "bbox": [],
  "geometry": {"coordinates":[-85.3833,32.9167],"type":"Point"}
}