{
  "id": 7589426,
  "type": "Feature",
  "properties": {
    "tgn:hierarchy":[
        "tgn:7589426",
        "tgn:1000004",
        "tgn:7000198",
        "tgn:7000799",
        "tgn:7029392"
    ],
    "tgn:id":7589426,
    "tgn:name:en":"Paliari",
    "tgn:placetype":[
        "aat:300008347"
    ]
},
  "bbox": [],
  "geometry": {"coordinates":[74.3786,33.210899],"type":"Point"}
}