{
  "id": 2069189,
  "type": "Feature",
  "properties": {
    "tgn:hierarchy":[
        "tgn:2069189",
        "tgn:1000001",
        "tgn:7012149",
        "tgn:1002751",
        "tgn:7007568",
        "tgn:7029392"
    ],
    "tgn:id":2069189,
    "tgn:name":"Firthcliffe Heights",
    "tgn:placetype":[
        "aat:300008347"
    ]
},
  "bbox": [],
  "geometry": {"coordinates":[-74.05,41.4333],"type":"Point"}
}