<<<<<<< HEAD
{
  "id": 7475622,
  "type": "Feature",
  "properties": {
    "tgn:hierarchy":[
        "tgn:7475622",
        "tgn:1000004",
        "tgn:7489179",
        "tgn:1000141",
        "tgn:7029392"
    ],
    "tgn:id":7475622,
    "tgn:name":"Neipi Yugang",
    "tgn:placetype":[
        "aat:300008678"
    ]
},
  "bbox": [],
  "geometry": {"coordinates":[121.870611,24.579171],"type":"Point"}
}
=======
{"geometry":{"type":"Point","coordinates":[121.870611,24.579171]},"type":"Feature","properties":{"hierarchy":["tgn:7475622","tgn:1000004","tgn:7489179","tgn:1000141","tgn:7029392"],"placetype":["aat:300008678"],"id":7475622,"name:xx":"Neipi Yugang"}}
>>>>>>> 03f74aca74312dbeaf24d7e61306dd6a786dc3d0
