{
  "id": 7137799,
  "type": "Feature",
  "properties": {
    "tgn:hierarchy":[
        "tgn:7137799",
        "tgn:1000003",
        "tgn:7003676",
        "tgn:7000084",
        "tgn:7029392"
    ],
    "tgn:id":7137799,
    "tgn:name":"Leh-Berg",
    "tgn:placetype":[
        "aat:300008777"
    ]
},
  "bbox": [],
  "geometry": {"coordinates":[10.05,52.816667],"type":"Point"}
}