{
  "id": 7225695,
  "type": "Feature",
  "properties": {
    "tgn:hierarchy":[
        "tgn:7225695",
        "tgn:4003773",
        "tgn:7001395",
        "tgn:1000003",
        "tgn:1000074",
        "tgn:7029392"
    ],
    "tgn:id":7225695,
    "tgn:name":"Navp\u00e1ktou, \u00d3rmos",
    "tgn:placetype":[
        "aat:300132316"
    ]
},
  "bbox": [],
  "geometry": {"coordinates":[21.833333,38.383333],"type":"Point"}
}