{
  "id": 2299809,
  "type": "Feature",
  "properties": {
    "tgn:hierarchy":[
        "tgn:2299809",
        "tgn:7002659",
        "tgn:1000001",
        "tgn:7012149",
        "tgn:2000029",
        "tgn:7029392"
    ],
    "tgn:id":2299809,
    "tgn:name":"Dudley Hollow",
    "tgn:placetype":[
        "aat:300008761"
    ]
},
  "bbox": [],
  "geometry": {"coordinates":[-87.9167,34.55],"type":"Point"}
}