{
  "id": 2778803,
  "type": "Feature",
  "properties": {
    "tgn:hierarchy":[
        "tgn:2778803",
        "tgn:1000001",
        "tgn:7012149",
        "tgn:7007157",
        "tgn:1002863",
        "tgn:7029392"
    ],
    "tgn:id":2778803,
    "tgn:name":"Wolf Canyon",
    "tgn:placetype":[
        "aat:300008761"
    ]
},
  "bbox": [],
  "geometry": {"coordinates":[-120.45,35.75],"type":"Point"}
}