{
  "id": 7376166,
  "type": "Feature",
  "properties": {
    "tgn:hierarchy":[
        "tgn:7376166",
        "tgn:7005580",
        "tgn:1000001",
        "tgn:7005560",
        "tgn:7029392"
    ],
    "tgn:id":7376166,
    "tgn:name":"Las Victorias",
    "tgn:placetype":[
        "aat:300008347"
    ]
},
  "bbox": [],
  "geometry": {"coordinates":[-93.383333,16.166667],"type":"Point"}
}