{
  "id": 2726641,
  "type": "Feature",
  "properties": {
    "tgn:hierarchy":[
        "tgn:2726641",
        "tgn:1000001",
        "tgn:7012149",
        "tgn:2000810",
        "tgn:7007255",
        "tgn:7029392"
    ],
    "tgn:id":2726641,
    "tgn:name":"Town Hollow",
    "tgn:placetype":[
        "aat:300008761"
    ]
},
  "bbox": [],
  "geometry": {"coordinates":[-83.75,37.6167],"type":"Point"}
}