{
  "id": 7011539,
  "type": "Feature",
  "properties": {
    "tgn:hierarchy":[
        "tgn:7011539",
        "tgn:1000004",
        "tgn:7018214",
        "tgn:7002435",
        "tgn:7029392"
    ],
    "tgn:id":7011539,
    "tgn:name":"Primor'ye",
    "tgn:placetype":[
        "aat:300008631",
        "aat:300387145",
        "aat:300135982"
    ]
},
  "bbox": [],
  "geometry": {"coordinates":[135.4167,45.4167],"type":"Point"}
}