{
  "id": 2565528,
  "type": "Feature",
  "properties": {
    "tgn:hierarchy":[
        "tgn:2565528",
        "tgn:1000001",
        "tgn:1002231",
        "tgn:7012149",
        "tgn:7007255",
        "tgn:7029392"
    ],
    "tgn:id":2565528,
    "tgn:name":"Painter Run",
    "tgn:placetype":[
        "aat:300008699"
    ]
},
  "bbox": [],
  "geometry": {"coordinates":[-84.2833,38.9167],"type":"Point"}
}