{
  "id": 2274328,
  "type": "Feature",
  "properties": {
    "tgn:hierarchy":[
        "tgn:2274328",
        "tgn:1000001",
        "tgn:7012149",
        "tgn:2001821",
        "tgn:7007713",
        "tgn:7029392"
    ],
    "tgn:id":2274328,
    "tgn:name":"Dakota Calmet Mine",
    "tgn:placetype":[
        "aat:300000390"
    ]
},
  "bbox": [],
  "geometry": {"coordinates":[-103.4333,43.95],"type":"Point"}
}