{
  "id": 7453290,
  "type": "Feature",
  "properties": {
    "tgn:hierarchy":[
        "tgn:7453290",
        "tgn:7002444",
        "tgn:1000003",
        "tgn:7008082",
        "tgn:7008591",
        "tgn:7029392"
    ],
    "tgn:id":7453290,
    "tgn:name:en":"Churchton Bay",
    "tgn:placetype":[
        "aat:300132316"
    ]
},
  "bbox": [],
  "geometry": {"coordinates":[-6.083333,57.35],"type":"Point"}
}