{
  "id": 7081549,
  "type": "Feature",
  "properties": {
    "tgn:hierarchy":[
        "tgn:7081549",
        "tgn:1000003",
        "tgn:7003676",
        "tgn:7000084",
        "tgn:7029392"
    ],
    "tgn:id":7081549,
    "tgn:name":"Windm\u00fchlen Berg",
    "tgn:placetype":[
        "aat:300008777"
    ]
},
  "bbox": [],
  "geometry": {"coordinates":[7.516667,52.516667],"type":"Point"}
}