{
  "id": 7446241,
  "type": "Feature",
  "properties": {
    "tgn:hierarchy":[
        "tgn:7446241",
        "tgn:7019094",
        "tgn:7002444",
        "tgn:1000003",
        "tgn:7008591",
        "tgn:7029392"
    ],
    "tgn:id":7446241,
    "tgn:name:en":"Rhunahaorine",
    "tgn:placetype":[
        "aat:300008347"
    ]
},
  "bbox": [],
  "geometry": {"coordinates":[-5.65,55.666667],"type":"Point"}
}