{
  "id": 2618720,
  "type": "Feature",
  "properties": {
    "tgn:hierarchy":[
        "tgn:2618720",
        "tgn:1000001",
        "tgn:7012149",
        "tgn:2002299",
        "tgn:7013961",
        "tgn:7029392"
    ],
    "tgn:id":2618720,
    "tgn:name":"Right Fork Rich Creek",
    "tgn:placetype":[
        "aat:300008706"
    ]
},
  "bbox": [],
  "geometry": {"coordinates":[-82.3667,38.0167],"type":"Point"}
}