{
  "id": 7428632,
  "type": "Feature",
  "properties": {
    "tgn:hierarchy":[
        "tgn:7428632",
        "tgn:7005581",
        "tgn:1000001",
        "tgn:7005560",
        "tgn:7029392"
    ],
    "tgn:id":7428632,
    "tgn:name":"Estaci\u00f3n Nopalera",
    "tgn:placetype":[
        "aat:300007783"
    ]
},
  "bbox": [],
  "geometry": {"coordinates":[-106.433333,28.416667],"type":"Point"}
}