{
  "id": 2451553,
  "type": "Feature",
  "properties": {
    "tgn:hierarchy":[
        "tgn:2451553",
        "tgn:1000001",
        "tgn:2001429",
        "tgn:7012149",
        "tgn:7007566",
        "tgn:7029392"
    ],
    "tgn:id":2451553,
    "tgn:name":"Little Bear Canyon",
    "tgn:placetype":[
        "aat:300008761"
    ]
},
  "bbox": [],
  "geometry": {"coordinates":[-108.2333,33.2667],"type":"Point"}
}