{
  "id": 7375845,
  "type": "Feature",
  "properties": {
    "tgn:hierarchy":[
        "tgn:7375845",
        "tgn:7005581",
        "tgn:1000001",
        "tgn:7005560",
        "tgn:7029392"
    ],
    "tgn:id":7375845,
    "tgn:name":"La Reforma",
    "tgn:placetype":[
        "aat:300008347"
    ]
},
  "bbox": [],
  "geometry": {"coordinates":[-105.566667,26.85],"type":"Point"}
}