<<<<<<< HEAD
{
  "id": 2766822,
  "type": "Feature",
  "properties": {
    "tgn:hierarchy":[
        "tgn:2766822",
        "tgn:1000001",
        "tgn:7012149",
        "tgn:2001275",
        "tgn:7007524",
        "tgn:7029392"
    ],
    "tgn:id":2766822,
    "tgn:name":"White Peak",
    "tgn:placetype":[
        "aat:300008798"
    ]
},
  "bbox": [],
  "geometry": {"coordinates":[-111.2,44.9],"type":"Point"}
}
=======
{"geometry":{"type":"Point","coordinates":[-111.200000,44.900000]},"type":"Feature","properties":{"hierarchy":["tgn:2766822","tgn:1000001","tgn:7012149","tgn:2001275","tgn:7007524","tgn:7029392"],"placetype":["aat:300008798"],"id":2766822,"name:xx":"White Peak"}}
>>>>>>> 03f74aca74312dbeaf24d7e61306dd6a786dc3d0
