<<<<<<< HEAD
{
  "id": 2763501,
  "type": "Feature",
  "properties": {
    "tgn:hierarchy":[
        "tgn:2763501",
        "tgn:1000001",
        "tgn:1002724",
        "tgn:7012149",
        "tgn:7007517",
        "tgn:7029392"
    ],
    "tgn:id":2763501,
    "tgn:name":"Weymouth Fore River Marshes",
    "tgn:placetype":[
        "aat:300008905"
    ]
},
  "bbox": [],
  "geometry": {"coordinates":[-70.95,42.2167],"type":"Point"}
}
=======
{"geometry":{"type":"Point","coordinates":[-70.950000,42.216700]},"type":"Feature","properties":{"hierarchy":["tgn:2763501","tgn:1000001","tgn:1002724","tgn:7012149","tgn:7007517","tgn:7029392"],"placetype":["aat:300008905"],"id":2763501,"name:xx":"Weymouth Fore River Marshes"}}
>>>>>>> 03f74aca74312dbeaf24d7e61306dd6a786dc3d0
