{
  "id": 2763501,
  "type": "Feature",
  "properties": {
    "tgn:hierarchy":[
        "tgn:2763501",
        "tgn:1000001",
        "tgn:1002724",
        "tgn:7012149",
        "tgn:7007517",
        "tgn:7029392"
    ],
    "tgn:id":2763501,
    "tgn:name":"Weymouth Fore River Marshes",
    "tgn:placetype":[
        "aat:300008905"
    ]
},
  "bbox": [],
  "geometry": {"coordinates":[-70.95,42.2167],"type":"Point"}
}