{
  "id": 2299423,
  "type": "Feature",
  "properties": {
    "tgn:hierarchy":[
        "tgn:2299423",
        "tgn:7006450",
        "tgn:1000001",
        "tgn:2124012",
        "tgn:7012149",
        "tgn:7029392"
    ],
    "tgn:id":2299423,
    "tgn:name":"Duck Mountain",
    "tgn:placetype":[
        "aat:300008798"
    ]
},
  "bbox": [],
  "geometry": {"coordinates":[-152.4833,58.1667],"type":"Point"}
}