{
  "id": 1137088,
  "type": "Feature",
  "properties": {
    "tgn:hierarchy":[
        "tgn:1137088",
        "tgn:1000004",
        "tgn:7011585",
        "tgn:7018214",
        "tgn:7002435",
        "tgn:7029392"
    ],
    "tgn:id":1137088,
    "tgn:name":"\u010cornoje",
    "tgn:placetype":[
        "aat:300008347"
    ]
},
  "bbox": [],
  "geometry": {"coordinates":[46.4167,57.5333],"type":"Point"}
}