<<<<<<< HEAD
{
  "id": 2159753,
  "type": "Feature",
  "properties": {
    "tgn:hierarchy":[
        "tgn:2159753",
        "tgn:1000001",
        "tgn:1002286",
        "tgn:7012149",
        "tgn:7007710",
        "tgn:7029392"
    ],
    "tgn:id":2159753,
    "tgn:name":"Beech Bottom Natural Area",
    "tgn:placetype":[
        "aat:300055621"
    ]
},
  "bbox": [],
  "geometry": {"coordinates":[-77.8833,41.4667],"type":"Point"}
}
=======
{"geometry":{"type":"Point","coordinates":[-77.883300,41.466700]},"type":"Feature","properties":{"hierarchy":["tgn:2159753","tgn:1000001","tgn:1002286","tgn:7012149","tgn:7007710","tgn:7029392"],"placetype":["aat:300055621"],"id":2159753,"name:xx":"Beech Bottom Natural Area"}}
>>>>>>> 03f74aca74312dbeaf24d7e61306dd6a786dc3d0
