{
  "id": 1073460,
  "type": "Feature",
  "properties": {
    "tgn:hierarchy":[
        "tgn:1073460",
        "tgn:1000004",
        "tgn:1001261",
        "tgn:1000111",
        "tgn:7029392"
    ],
    "tgn:id":1073460,
    "tgn:name":"Yaojie",
    "tgn:placetype":[
        "aat:300008347"
    ]
},
  "bbox": [],
  "geometry": {"coordinates":[102.8667,36.4167],"type":"Point"}
}