{
  "id": 7221857,
  "type": "Feature",
  "properties": {
    "tgn:hierarchy":[
        "tgn:7221857",
        "tgn:7002707",
        "tgn:7002705",
        "tgn:1000003",
        "tgn:1000074",
        "tgn:7029392"
    ],
    "tgn:id":7221857,
    "tgn:name":"Kont\u00f3s",
    "tgn:placetype":[
        "aat:300008347"
    ]
},
  "bbox": [],
  "geometry": {"coordinates":[20.9225,39.503611],"type":"Point"}
}