{
  "id": 2605580,
  "type": "Feature",
  "properties": {
    "tgn:hierarchy":[
        "tgn:2605580",
        "tgn:1000001",
        "tgn:7012149",
        "tgn:2000181",
        "tgn:7007157",
        "tgn:7029392"
    ],
    "tgn:id":2605580,
    "tgn:name":"Railroad Gulch",
    "tgn:placetype":[
        "aat:300008761"
    ]
},
  "bbox": [],
  "geometry": {"coordinates":[-124.1667,40.6667],"type":"Point"}
}