{
  "id": 7198335,
  "type": "Feature",
  "properties": {
    "tgn:hierarchy":[
        "tgn:7198335",
        "tgn:7003669",
        "tgn:1000003",
        "tgn:7000084",
        "tgn:7029392"
    ],
    "tgn:id":7198335,
    "tgn:name":"Eichleithen",
    "tgn:placetype":[
        "aat:300008347"
    ]
},
  "bbox": [],
  "geometry": {"coordinates":[11.716667,49.966667],"type":"Point"}
}