{
  "id": 7581144,
  "type": "Feature",
  "properties": {
    "tgn:hierarchy":[
        "tgn:7581144",
        "tgn:1001828",
        "tgn:1000004",
        "tgn:7000198",
        "tgn:7029392"
    ],
    "tgn:id":7581144,
    "tgn:name:en":"Sigadam",
    "tgn:placetype":[
        "aat:300008347"
    ]
},
  "bbox": [],
  "geometry": {"coordinates":[83.683333,18.383333],"type":"Point"}
}