{
  "id": 2225351,
  "type": "Feature",
  "properties": {
    "tgn:hierarchy":[
        "tgn:2225351",
        "tgn:1000001",
        "tgn:7012149",
        "tgn:7007157",
        "tgn:1002957",
        "tgn:7029392"
    ],
    "tgn:id":2225351,
    "tgn:name":"Castle Rock",
    "tgn:placetype":[
        "aat:300008798"
    ]
},
  "bbox": [],
  "geometry": {"coordinates":[-119.8333,38.2333],"type":"Point"}
}