<<<<<<< HEAD
{
  "id": 7022290,
  "type": "Feature",
  "properties": {
    "tgn:hierarchy":[
        "tgn:7022290",
        "tgn:1000001",
        "tgn:7012149",
        "tgn:7007248",
        "tgn:7029392"
    ],
    "tgn:id":7022290,
    "tgn:name":"Allison Ridge",
    "tgn:placetype":[
        "aat:300266640"
    ]
},
  "bbox": [],
  "geometry": {"coordinates":[-83.7833,34.6833],"type":"Point"}
}
=======
{"geometry":{"type":"Point","coordinates":[-83.783300,34.683300]},"type":"Feature","properties":{"hierarchy":["tgn:7022290","tgn:1000001","tgn:7012149","tgn:7007248","tgn:7029392"],"placetype":["aat:300266640"],"id":7022290,"name:xx":"Allison Ridge"}}
>>>>>>> 03f74aca74312dbeaf24d7e61306dd6a786dc3d0
