<<<<<<< HEAD
{
  "id": 2256607,
  "type": "Feature",
  "properties": {
    "tgn:hierarchy":[
        "tgn:2256607",
        "tgn:1000001",
        "tgn:7012149",
        "tgn:1002932",
        "tgn:7007710",
        "tgn:7029392"
    ],
    "tgn:id":2256607,
    "tgn:name":"Cord Pond",
    "tgn:placetype":[
        "aat:300008680"
    ]
},
  "bbox": [],
  "geometry": {"coordinates":[-75.8333,41.65],"type":"Point"}
}
=======
{"geometry":{"type":"Point","coordinates":[-75.833300,41.650000]},"type":"Feature","properties":{"hierarchy":["tgn:2256607","tgn:1000001","tgn:7012149","tgn:1002932","tgn:7007710","tgn:7029392"],"placetype":["aat:300008680"],"id":2256607,"name:xx":"Cord Pond"}}
>>>>>>> 03f74aca74312dbeaf24d7e61306dd6a786dc3d0
