{
  "id": 7282040,
  "type": "Feature",
  "properties": {
    "tgn:hierarchy":[
        "tgn:7282040",
        "tgn:7016598",
        "tgn:1000049",
        "tgn:1000002",
        "tgn:7029392"
    ],
    "tgn:id":7282040,
    "tgn:name":"San Agustin, Quebrada",
    "tgn:placetype":[
        "aat:300266554",
        "aat:300008699"
    ]
},
  "bbox": [],
  "geometry": {"coordinates":[-70.316667,-25.383333],"type":"Point"}
}