{
  "id": 2396708,
  "type": "Feature",
  "properties": {
    "tgn:hierarchy":[
        "tgn:2396708",
        "tgn:1000001",
        "tgn:7012149",
        "tgn:1002469",
        "tgn:7007255",
        "tgn:7029392"
    ],
    "tgn:id":2396708,
    "tgn:name":"Holy Water Branch",
    "tgn:placetype":[
        "aat:300008699"
    ]
},
  "bbox": [],
  "geometry": {"coordinates":[-85.0333,38.4333],"type":"Point"}
}