{
  "id": 7528231,
  "type": "Feature",
  "properties": {
    "tgn:hierarchy":[
        "tgn:7528231",
        "tgn:7001242",
        "tgn:7016833",
        "tgn:7029392"
    ],
    "tgn:id":7528231,
    "tgn:name":"Ab\u016b Qarn, W\u0101d\u012b",
    "tgn:placetype":[
        "aat:300379998"
    ]
},
  "bbox": [],
  "geometry": {"coordinates":[31.654865,29.225739],"type":"Point"}
}