{
  "id": 2411567,
  "type": "Feature",
  "properties": {
    "tgn:hierarchy":[
        "tgn:2411567",
        "tgn:1000001",
        "tgn:7012149",
        "tgn:1002979",
        "tgn:7007920",
        "tgn:7029392"
    ],
    "tgn:id":2411567,
    "tgn:name":"Indian Jack Slough",
    "tgn:placetype":[
        "aat:300008699"
    ]
},
  "bbox": [],
  "geometry": {"coordinates":[-123.3667,46.2333],"type":"Point"}
}