{
  "id": 2057900,
  "type": "Feature",
  "properties": {
    "tgn:hierarchy":[
        "tgn:2057900",
        "tgn:1000001",
        "tgn:7012149",
        "tgn:2001207",
        "tgn:7007523",
        "tgn:7029392"
    ],
    "tgn:id":2057900,
    "tgn:name":"Arcadia",
    "tgn:placetype":[
        "aat:300008347"
    ]
},
  "bbox": [],
  "geometry": {"coordinates":[-90.6167,37.5833],"type":"Point"}
}