{
  "id": 2554788,
  "type": "Feature",
  "properties": {
    "tgn:hierarchy":[
        "tgn:2554788",
        "tgn:1000001",
        "tgn:7012149",
        "tgn:7007157",
        "tgn:1002858",
        "tgn:7029392"
    ],
    "tgn:id":2554788,
    "tgn:name":"Oakzanita Peak",
    "tgn:placetype":[
        "aat:300008798"
    ]
},
  "bbox": [],
  "geometry": {"coordinates":[-116.55,32.8833],"type":"Point"}
}