{
  "id": 2235440,
  "type": "Feature",
  "properties": {
    "tgn:hierarchy":[
        "tgn:2235440",
        "tgn:1000001",
        "tgn:1002267",
        "tgn:7012149",
        "tgn:7007919",
        "tgn:7029392"
    ],
    "tgn:id":2235440,
    "tgn:name":"Chester Club Lake",
    "tgn:placetype":[
        "aat:300006191"
    ]
},
  "bbox": [],
  "geometry": {"coordinates":[-77.4667,37.35],"type":"Point"}
}