{
  "id": 7207092,
  "type": "Feature",
  "properties": {
    "tgn:hierarchy":[
        "tgn:7207092",
        "tgn:1000003",
        "tgn:7003676",
        "tgn:7000084",
        "tgn:7029392"
    ],
    "tgn:id":7207092,
    "tgn:name":"Burgelsdorf",
    "tgn:placetype":[
        "aat:300008347"
    ]
},
  "bbox": [],
  "geometry": {"coordinates":[9.333333,53.233333],"type":"Point"}
}