<<<<<<< HEAD
{
  "id": 7023159,
  "type": "Feature",
  "properties": {
    "tgn:hierarchy":[
        "tgn:7023159",
        "tgn:1000001",
        "tgn:7012149",
        "tgn:7007568",
        "tgn:7029392"
    ],
    "tgn:id":7023159,
    "tgn:name":"Jerseyfield Lake",
    "tgn:placetype":[
        "aat:300008680"
    ]
},
  "bbox": [],
  "geometry": {"coordinates":[-74.75,43.3],"type":"Point"}
}
=======
{"geometry":{"type":"Point","coordinates":[-74.750000,43.300000]},"type":"Feature","properties":{"hierarchy":["tgn:7023159","tgn:1000001","tgn:7012149","tgn:7007568","tgn:7029392"],"placetype":["aat:300008680"],"id":7023159,"name:xx":"Jerseyfield Lake"}}
>>>>>>> 03f74aca74312dbeaf24d7e61306dd6a786dc3d0
