{
  "id": 2661039,
  "type": "Feature",
  "properties": {
    "tgn:hierarchy":[
        "tgn:2661039",
        "tgn:1000001",
        "tgn:7012149",
        "tgn:2002017",
        "tgn:7007826",
        "tgn:7029392"
    ],
    "tgn:id":2661039,
    "tgn:name":"Short Croton Creek",
    "tgn:placetype":[
        "aat:300008706"
    ]
},
  "bbox": [],
  "geometry": {"coordinates":[-100.5833,33.3333],"type":"Point"}
}