{
  "id": 2573209,
  "type": "Feature",
  "properties": {
    "tgn:hierarchy":[
        "tgn:2573209",
        "tgn:1000001",
        "tgn:1002344",
        "tgn:7012149",
        "tgn:7007517",
        "tgn:7029392"
    ],
    "tgn:id":2573209,
    "tgn:name":"Pease Ledge",
    "tgn:placetype":[
        "aat:300132348"
    ]
},
  "bbox": [],
  "geometry": {"coordinates":[-70.9167,41.4167],"type":"Point"}
}