{
  "id": 7282528,
  "type": "Feature",
  "properties": {
    "tgn:hierarchy":[
        "tgn:7282528",
        "tgn:1001699",
        "tgn:1000049",
        "tgn:1000002",
        "tgn:7029392"
    ],
    "tgn:id":7282528,
    "tgn:name":"Pescadores, Bah\u00eda",
    "tgn:placetype":[
        "aat:300132316"
    ]
},
  "bbox": [],
  "geometry": {"coordinates":[-72.893056,-43.588889],"type":"Point"}
}