{
  "id": 1036177,
  "type": "Feature",
  "properties": {
    "tgn:hierarchy":[
        "tgn:1036177",
        "tgn:1000003",
        "tgn:7002890",
        "tgn:1000070",
        "tgn:7029392"
    ],
    "tgn:id":1036177,
    "tgn:name":"Villers-Carbonnel",
    "tgn:placetype":[
        "aat:300008347"
    ]
},
  "bbox": [],
  "geometry": {"coordinates":[2.9167,49.8833],"type":"Point"}
}