{
  "id": 1076313,
  "type": "Feature",
  "properties": {
    "tgn:hierarchy":[
        "tgn:1076313",
        "tgn:1000004",
        "tgn:7000198",
        "tgn:1001977",
        "tgn:7029392"
    ],
    "tgn:id":1076313,
    "tgn:name":"N\u0101likul",
    "tgn:placetype":[
        "aat:300008347"
    ]
},
  "bbox": [],
  "geometry": {"coordinates":[88.1833,22.8167],"type":"Point"}
}