{
  "id": 7525580,
  "type": "Feature",
  "properties": {
    "tgn:hierarchy":[
        "tgn:7525580",
        "tgn:7001242",
        "tgn:7016833",
        "tgn:1001335",
        "tgn:7029392"
    ],
    "tgn:id":7525580,
    "tgn:name:en":"Qaryat al Muthallath",
    "tgn:placetype":[
        "aat:300008347"
    ]
},
  "bbox": [],
  "geometry": {"coordinates":[30.944223,31.253066],"type":"Point"}
}