{
  "id": 2327544,
  "type": "Feature",
  "properties": {
    "tgn:hierarchy":[
        "tgn:2327544",
        "tgn:1000001",
        "tgn:2000921",
        "tgn:7012149",
        "tgn:7007515",
        "tgn:7029392"
    ],
    "tgn:id":2327544,
    "tgn:name":"Fish Brook",
    "tgn:placetype":[
        "aat:300008699"
    ]
},
  "bbox": [],
  "geometry": {"coordinates":[-70.0833,44.7667],"type":"Point"}
}