{
  "id": 7486250,
  "type": "Feature",
  "properties": {
    "tgn:hierarchy":[
        "tgn:7486250",
        "tgn:1000004",
        "tgn:7491221",
        "tgn:1000141",
        "tgn:7029392"
    ],
    "tgn:id":7486250,
    "tgn:name":"Wuxian",
    "tgn:placetype":[
        "aat:300008347"
    ]
},
  "bbox": [],
  "geometry": {"coordinates":[121.209006,22.875969],"type":"Point"}
}