{
  "id": 7496930,
  "type": "Feature",
  "properties": {
    "tgn:hierarchy":[
        "tgn:7496930",
        "tgn:1000004",
        "tgn:1000959",
        "tgn:1000141",
        "tgn:7029392"
    ],
    "tgn:id":7496930,
    "tgn:name":"Taibei Yi Xueyuan",
    "tgn:placetype":[
        "aat:300006610"
    ]
},
  "bbox": [],
  "geometry": {"coordinates":[121.561571,25.025197],"type":"Point"}
}