{
  "id": 7146249,
  "type": "Feature",
  "properties": {
    "tgn:hierarchy":[
        "tgn:7146249",
        "tgn:1000003",
        "tgn:7003677",
        "tgn:7000084",
        "tgn:7029392"
    ],
    "tgn:id":7146249,
    "tgn:name":"Kluse",
    "tgn:placetype":[
        "aat:300000206"
    ]
},
  "bbox": [],
  "geometry": {"coordinates":[7.266667,51.216667],"type":"Point"}
}