<<<<<<< HEAD
{
  "id": 7361394,
  "type": "Feature",
  "properties": {
    "tgn:hierarchy":[
        "tgn:7361394",
        "tgn:1000001",
        "tgn:1001960",
        "tgn:7005560",
        "tgn:7029392"
    ],
    "tgn:id":7361394,
    "tgn:name":"El Jabali",
    "tgn:placetype":[
        "aat:300008795"
    ]
},
  "bbox": [],
  "geometry": {"coordinates":[-109.316667,27.55],"type":"Point"}
}
=======
{"geometry":{"type":"Point","coordinates":[-109.316667,27.550000]},"type":"Feature","properties":{"hierarchy":["tgn:7361394","tgn:1000001","tgn:1001960","tgn:7005560","tgn:7029392"],"placetype":["aat:300008795"],"id":7361394,"name:xx":"El Jabali"}}
>>>>>>> 03f74aca74312dbeaf24d7e61306dd6a786dc3d0
