{
  "id": 7326531,
  "type": "Feature",
  "properties": {
    "tgn:hierarchy":[
        "tgn:7326531",
        "tgn:1001439",
        "tgn:1000003",
        "tgn:7002797",
        "tgn:1000095",
        "tgn:7029392"
    ],
    "tgn:id":7326531,
    "tgn:name":"Perca, Rambla",
    "tgn:placetype":[
        "aat:300008699"
    ]
},
  "bbox": [],
  "geometry": {"coordinates":[-1.416667,38.05],"type":"Point"}
}