<<<<<<< HEAD
{
  "id": 7361151,
  "type": "Feature",
  "properties": {
    "tgn:hierarchy":[
        "tgn:7361151",
        "tgn:1000001",
        "tgn:1001960",
        "tgn:7005560",
        "tgn:7029392"
    ],
    "tgn:id":7361151,
    "tgn:name":"El Busani",
    "tgn:placetype":[
        "aat:300008347"
    ]
},
  "bbox": [],
  "geometry": {"coordinates":[-111.366667,31.15],"type":"Point"}
}
=======
{"geometry":{"type":"Point","coordinates":[-111.366667,31.150000]},"type":"Feature","properties":{"hierarchy":["tgn:7361151","tgn:1000001","tgn:1001960","tgn:7005560","tgn:7029392"],"placetype":["aat:300008347"],"id":7361151,"name:xx":"El Busani"}}
>>>>>>> 03f74aca74312dbeaf24d7e61306dd6a786dc3d0
