{
  "id": 2216555,
  "type": "Feature",
  "properties": {
    "tgn:hierarchy":[
        "tgn:2216555",
        "tgn:1000001",
        "tgn:7012149",
        "tgn:2001514",
        "tgn:7007709",
        "tgn:7029392"
    ],
    "tgn:id":2216555,
    "tgn:name":"Camp Creek",
    "tgn:placetype":[
        "aat:300008706"
    ]
},
  "bbox": [],
  "geometry": {"coordinates":[-82.1333,35.55],"type":"Point"}
}