<<<<<<< HEAD
{
  "id": 2768901,
  "type": "Feature",
  "properties": {
    "tgn:hierarchy":[
        "tgn:2768901",
        "tgn:1000001",
        "tgn:7012149",
        "tgn:2000210",
        "tgn:7007158",
        "tgn:7029392"
    ],
    "tgn:id":2768901,
    "tgn:name":"Whitney Lake",
    "tgn:placetype":[
        "aat:300008680"
    ]
},
  "bbox": [],
  "geometry": {"coordinates":[-106.45,39.4167],"type":"Point"}
}
=======
{"geometry":{"type":"Point","coordinates":[-106.450000,39.416700]},"type":"Feature","properties":{"hierarchy":["tgn:2768901","tgn:1000001","tgn:7012149","tgn:2000210","tgn:7007158","tgn:7029392"],"placetype":["aat:300008680"],"id":2768901,"name:xx":"Whitney Lake"}}
>>>>>>> 03f74aca74312dbeaf24d7e61306dd6a786dc3d0
