{
  "id": 2465796,
  "type": "Feature",
  "properties": {
    "tgn:hierarchy":[
        "tgn:2465796",
        "tgn:1000001",
        "tgn:7012149",
        "tgn:2000203",
        "tgn:7007158",
        "tgn:7029392"
    ],
    "tgn:id":2465796,
    "tgn:name":"Lone Rock Hill",
    "tgn:placetype":[
        "aat:300008798"
    ]
},
  "bbox": [],
  "geometry": {"coordinates":[-105.3167,37.5833],"type":"Point"}
}