{
  "id": 7326598,
  "type": "Feature",
  "properties": {
    "tgn:hierarchy":[
        "tgn:7326598",
        "tgn:7002834",
        "tgn:1000003",
        "tgn:7002786",
        "tgn:1000095",
        "tgn:7029392"
    ],
    "tgn:id":7326598,
    "tgn:name":"Peque\u00f1o, R\u00edo",
    "tgn:placetype":[
        "aat:300008699"
    ]
},
  "bbox": [],
  "geometry": {"coordinates":[-8.333333,42.283333],"type":"Point"}
}