<<<<<<< HEAD
{
  "id": 7481713,
  "type": "Feature",
  "properties": {
    "tgn:hierarchy":[
        "tgn:7481713",
        "tgn:1000004",
        "tgn:7490934",
        "tgn:1000141",
        "tgn:7029392"
    ],
    "tgn:id":7481713,
    "tgn:name":"Sankuaicuo",
    "tgn:placetype":[
        "aat:300387033"
    ]
},
  "bbox": [],
  "geometry": {"coordinates":[120.238189,23.348028],"type":"Point"}
}
=======
{"geometry":{"type":"Point","coordinates":[120.238189,23.348028]},"type":"Feature","properties":{"hierarchy":["tgn:7481713","tgn:1000004","tgn:7490934","tgn:1000141","tgn:7029392"],"placetype":["aat:300387033"],"id":7481713,"name:xx":"Sankuaicuo"}}
>>>>>>> 03f74aca74312dbeaf24d7e61306dd6a786dc3d0
