{
  "id": 2496201,
  "type": "Feature",
  "properties": {
    "tgn:hierarchy":[
        "tgn:2496201",
        "tgn:1000001",
        "tgn:7012149",
        "tgn:7007157",
        "tgn:7014475",
        "tgn:7029392"
    ],
    "tgn:id":2496201,
    "tgn:name":"Masters Hill",
    "tgn:placetype":[
        "aat:300008798"
    ]
},
  "bbox": [],
  "geometry": {"coordinates":[-121.7333,37.3333],"type":"Point"}
}