{
  "id": 2204113,
  "type": "Feature",
  "properties": {
    "tgn:hierarchy":[
        "tgn:2204113",
        "tgn:1000001",
        "tgn:2001411",
        "tgn:7012149",
        "tgn:7007526",
        "tgn:7029392"
    ],
    "tgn:id":2204113,
    "tgn:name":"Buell",
    "tgn:placetype":[
        "aat:300008347"
    ]
},
  "bbox": [],
  "geometry": {"coordinates":[-114.0333,41.25],"type":"Point"}
}