{
  "id": 7225299,
  "type": "Feature",
  "properties": {
    "tgn:hierarchy":[
        "tgn:7225299",
        "tgn:7002681",
        "tgn:7001395",
        "tgn:1000003",
        "tgn:1000074",
        "tgn:7029392"
    ],
    "tgn:id":7225299,
    "tgn:name":"N\u00e9a Zoryi\u00e1ni",
    "tgn:placetype":[
        "aat:300008347"
    ]
},
  "bbox": [],
  "geometry": {"coordinates":[23.866667,38.15],"type":"Point"}
}