{
  "id": 7183185,
  "type": "Feature",
  "properties": {
    "tgn:hierarchy":[
        "tgn:7183185",
        "tgn:7003692",
        "tgn:1000003",
        "tgn:7000084",
        "tgn:7029392"
    ],
    "tgn:id":7183185,
    "tgn:name":"Geggenau",
    "tgn:placetype":[
        "aat:300008863"
    ]
},
  "bbox": [],
  "geometry": {"coordinates":[8.166667,48.833333],"type":"Point"}
}