{
  "id": 2094230,
  "type": "Feature",
  "properties": {
    "tgn:hierarchy":[
        "tgn:2094230",
        "tgn:1000001",
        "tgn:7012149",
        "tgn:1002387",
        "tgn:7007710",
        "tgn:7029392"
    ],
    "tgn:id":2094230,
    "tgn:name":"Waynecastle",
    "tgn:placetype":[
        "aat:300008347",
        "aat:300387210"
    ]
},
  "bbox": [],
  "geometry": {"coordinates":[-77.65,39.7667],"type":"Point"}
}