{
  "id": 7555585,
  "type": "Feature",
  "properties": {
    "tgn:hierarchy":[
        "tgn:7555585",
        "tgn:1000004",
        "tgn:1001842",
        "tgn:7000198",
        "tgn:7029392"
    ],
    "tgn:id":7555585,
    "tgn:name:en":"Mohanpur",
    "tgn:placetype":[
        "aat:300008347"
    ]
},
  "bbox": [],
  "geometry": {"coordinates":[86.598059,24.626881],"type":"Point"}
}