{
  "id": 2272367,
  "type": "Feature",
  "properties": {
    "tgn:hierarchy":[
        "tgn:2272367",
        "tgn:1000001",
        "tgn:1002480",
        "tgn:7012149",
        "tgn:7007564",
        "tgn:7029392"
    ],
    "tgn:id":2272367,
    "tgn:name":"Curtis Corner",
    "tgn:placetype":[
        "aat:300008347"
    ]
},
  "bbox": [],
  "geometry": {"coordinates":[-71.7333,42.8667],"type":"Point"}
}