{
  "id": 2255628,
  "type": "Feature",
  "properties": {
    "tgn:hierarchy":[
        "tgn:2255628",
        "tgn:2000455",
        "tgn:1000001",
        "tgn:7012149",
        "tgn:7007250",
        "tgn:7029392"
    ],
    "tgn:id":2255628,
    "tgn:name":"Copenhagen Canyon",
    "tgn:placetype":[
        "aat:300008761"
    ]
},
  "bbox": [],
  "geometry": {"coordinates":[-111.55,42.3333],"type":"Point"}
}