{
  "id": 7591494,
  "type": "Feature",
  "properties": {
    "tgn:hierarchy":[
        "tgn:7591494",
        "tgn:1000004",
        "tgn:7000198",
        "tgn:7000799",
        "tgn:7029392"
    ],
    "tgn:id":7591494,
    "tgn:name:en":"Ainb\u016bsh\u0101hi da Danna",
    "tgn:placetype":[
        "aat:300008347"
    ]
},
  "bbox": [],
  "geometry": {"coordinates":[74.5875,32.969444],"type":"Point"}
}