<<<<<<< HEAD
{
  "id": 2338587,
  "type": "Feature",
  "properties": {
    "tgn:hierarchy":[
        "tgn:2338587",
        "tgn:1000001",
        "tgn:7012149",
        "tgn:2000446",
        "tgn:7007248",
        "tgn:7029392"
    ],
    "tgn:id":2338587,
    "tgn:name":"Frances, Lake",
    "tgn:placetype":[
        "aat:300006191"
    ]
},
  "bbox": [],
  "geometry": {"coordinates":[-84.9,34.8833],"type":"Point"}
}
=======
{"geometry":{"type":"Point","coordinates":[-84.900000,34.883300]},"type":"Feature","properties":{"hierarchy":["tgn:2338587","tgn:1000001","tgn:7012149","tgn:2000446","tgn:7007248","tgn:7029392"],"placetype":["aat:300006191"],"id":2338587,"name:xx":"Frances, Lake"}}
>>>>>>> 03f74aca74312dbeaf24d7e61306dd6a786dc3d0
