{
  "id": 7585764,
  "type": "Feature",
  "properties": {
    "tgn:hierarchy":[
        "tgn:7585764",
        "tgn:1000004",
        "tgn:7000198",
        "tgn:7000799",
        "tgn:7029392"
    ],
    "tgn:id":7585764,
    "tgn:name:en":"P\u0101lapur",
    "tgn:placetype":[
        "aat:300008347"
    ]
},
  "bbox": [],
  "geometry": {"coordinates":[74.361111,34.338889],"type":"Point"}
}