{
  "id": 7401583,
  "type": "Feature",
  "properties": {
    "tgn:hierarchy":[
        "tgn:7401583",
        "tgn:1000001",
        "tgn:7005599",
        "tgn:7005560",
        "tgn:7029392"
    ],
    "tgn:id":7401583,
    "tgn:name":"Jos\u00e9 G. Guti\u00e9rrez",
    "tgn:placetype":[
        "aat:300008347"
    ]
},
  "bbox": [],
  "geometry": {"coordinates":[-94.616667,18.020833],"type":"Point"}
}