{
  "id": 7541603,
  "type": "Feature",
  "properties": {
    "tgn:hierarchy":[
        "tgn:7541603",
        "tgn:7001242",
        "tgn:7001311",
        "tgn:7016833",
        "tgn:7029392"
    ],
    "tgn:id":7541603,
    "tgn:name:en":"J\u016bsat Ab\u016b Khish\u012br",
    "tgn:placetype":[
        "aat:300008777"
    ]
},
  "bbox": [],
  "geometry": {"coordinates":[30.979507,28.469027],"type":"Point"}
}