{
  "id": 7581360,
  "type": "Feature",
  "properties": {
    "tgn:hierarchy":[
        "tgn:7581360",
        "tgn:1000004",
        "tgn:7000198",
        "tgn:1001895",
        "tgn:7029392"
    ],
    "tgn:id":7581360,
    "tgn:name:en":"Surv\u0101ni",
    "tgn:placetype":[
        "aat:300008347"
    ]
},
  "bbox": [],
  "geometry": {"coordinates":[74.159682,21.820921],"type":"Point"}
}