{
  "id": 7278150,
  "type": "Feature",
  "properties": {
    "tgn:hierarchy":[
        "tgn:7278150",
        "tgn:1001702",
        "tgn:1000049",
        "tgn:1000002",
        "tgn:7029392"
    ],
    "tgn:id":7278150,
    "tgn:name":"Nadelkissen, Monte",
    "tgn:placetype":[
        "aat:300008795"
    ]
},
  "bbox": [],
  "geometry": {"coordinates":[-75.416667,-49.25],"type":"Point"}
}