{
  "id": 7581863,
  "type": "Feature",
  "properties": {
    "tgn:hierarchy":[
        "tgn:7581863",
        "tgn:1000004",
        "tgn:7000198",
        "tgn:1001882",
        "tgn:7029392"
    ],
    "tgn:id":7581863,
    "tgn:name:en":"Topaldoddi",
    "tgn:placetype":[
        "aat:300008347"
    ]
},
  "bbox": [],
  "geometry": {"coordinates":[76.783333,16.183333],"type":"Point"}
}