{
  "id": 1108955,
  "type": "Feature",
  "properties": {
    "tgn:hierarchy":[
        "tgn:1108955",
        "tgn:7029392"
    ],
    "tgn:id":1108955,
    "tgn:name":"Dari\u00e9n, Serran\u00eda del",
    "tgn:placetype":[
        "aat:300386831"
    ]
},
  "bbox": [],
  "geometry": {"coordinates":[-77.3667,8.3333],"type":"Point"}
}