<<<<<<< HEAD
{
  "id": 7241260,
  "type": "Feature",
  "properties": {
    "tgn:hierarchy":[
        "tgn:7241260",
        "tgn:7003465",
        "tgn:1000003",
        "tgn:1000063",
        "tgn:4012014",
        "tgn:7029392"
    ],
    "tgn:id":7241260,
    "tgn:name":"Le Beau Ban",
    "tgn:placetype":[
        "aat:300008347"
    ]
},
  "bbox": [],
  "geometry": {"coordinates":[5.283333,49.683333],"type":"Point"}
}
=======
{"geometry":{"type":"Point","coordinates":[5.283333,49.683333]},"type":"Feature","properties":{"hierarchy":["tgn:7241260","tgn:7003465","tgn:1000003","tgn:1000063","tgn:4012014","tgn:7029392"],"placetype":["aat:300008347"],"id":7241260,"name:xx":"Le Beau Ban"}}
>>>>>>> 03f74aca74312dbeaf24d7e61306dd6a786dc3d0
