{
  "id": 7464625,
  "type": "Feature",
  "properties": {
    "tgn:hierarchy":[
        "tgn:7464625",
        "tgn:7002444",
        "tgn:1000003",
        "tgn:7019100",
        "tgn:7008591",
        "tgn:7029392"
    ],
    "tgn:id":7464625,
    "tgn:name:en":"Braehead",
    "tgn:placetype":[
        "aat:300005433"
    ]
},
  "bbox": [],
  "geometry": {"coordinates":[-4.083333,55.85],"type":"Point"}
}