{
  "id": 2720020,
  "type": "Feature",
  "properties": {
    "tgn:hierarchy":[
        "tgn:2720020",
        "tgn:7006450",
        "tgn:1000001",
        "tgn:7012149",
        "tgn:2000086",
        "tgn:7029392"
    ],
    "tgn:id":2720020,
    "tgn:name":"Threemile Canyon",
    "tgn:placetype":[
        "aat:300008761"
    ]
},
  "bbox": [],
  "geometry": {"coordinates":[-144.1167,60.9833],"type":"Point"}
}