<<<<<<< HEAD
{
  "id": 2153792,
  "type": "Feature",
  "properties": {
    "tgn:hierarchy":[
        "tgn:2153792",
        "tgn:1000001",
        "tgn:7006451",
        "tgn:7012149",
        "tgn:7029392"
    ],
    "tgn:id":2153792,
    "tgn:name":"Bear Canyon",
    "tgn:placetype":[
        "aat:300008761"
    ]
},
  "bbox": [],
  "geometry": {"coordinates":[-109.5,33.0333],"type":"Point"}
}
=======
{"geometry":{"type":"Point","coordinates":[-109.500000,33.033300]},"type":"Feature","properties":{"hierarchy":["tgn:2153792","tgn:1000001","tgn:7006451","tgn:7012149","tgn:7029392"],"placetype":["aat:300008761"],"id":2153792,"name:xx":"Bear Canyon"}}
>>>>>>> 03f74aca74312dbeaf24d7e61306dd6a786dc3d0
