{
  "id": 2217160,
  "type": "Feature",
  "properties": {
    "tgn:hierarchy":[
        "tgn:2217160",
        "tgn:1000001",
        "tgn:7012149",
        "tgn:7014398",
        "tgn:7013961",
        "tgn:7029392"
    ],
    "tgn:id":2217160,
    "tgn:name":"Camp Run",
    "tgn:placetype":[
        "aat:300008699"
    ]
},
  "bbox": [],
  "geometry": {"coordinates":[-79.0833,38.75],"type":"Point"}
}