{
  "id": 7301960,
  "type": "Feature",
  "properties": {
    "tgn:hierarchy":[
        "tgn:7301960",
        "tgn:7002803",
        "tgn:1001647",
        "tgn:1000003",
        "tgn:1000095",
        "tgn:7029392"
    ],
    "tgn:id":7301960,
    "tgn:name":"Mizquitillas",
    "tgn:placetype":[
        "aat:300008347"
    ]
},
  "bbox": [],
  "geometry": {"coordinates":[-1.65,38.75],"type":"Point"}
}