{
  "id": 2671993,
  "type": "Feature",
  "properties": {
    "tgn:hierarchy":[
        "tgn:2671993",
        "tgn:1000001",
        "tgn:7012149",
        "tgn:2001420",
        "tgn:7007526",
        "tgn:7029392"
    ],
    "tgn:id":2671993,
    "tgn:name":"Smith Spring",
    "tgn:placetype":[
        "aat:300008697"
    ]
},
  "bbox": [],
  "geometry": {"coordinates":[-114.9833,39.4667],"type":"Point"}
}