{
  "id": 2731007,
  "type": "Feature",
  "properties": {
    "tgn:hierarchy":[
        "tgn:2731007",
        "tgn:1000001",
        "tgn:2001430",
        "tgn:7012149",
        "tgn:7007566",
        "tgn:7029392"
    ],
    "tgn:id":2731007,
    "tgn:name":"Tuck Tank",
    "tgn:placetype":[
        "aat:300006191"
    ]
},
  "bbox": [],
  "geometry": {"coordinates":[-104.9333,32.5333],"type":"Point"}
}