{
  "id": 1099253,
  "type": "Feature",
  "properties": {
    "tgn:hierarchy":[
        "tgn:1099253",
        "tgn:1008380",
        "tgn:1000226",
        "tgn:7018426",
        "tgn:1000006",
        "tgn:7029392"
    ],
    "tgn:id":1099253,
    "tgn:name":"Te Aroha",
    "tgn:placetype":[
        "aat:300008347"
    ]
},
  "bbox": [],
  "geometry": {"coordinates":[175.7167,-37.5333],"type":"Point"}
}