{
  "id": 2106485,
  "type": "Feature",
  "properties": {
    "tgn:hierarchy":[
        "tgn:2106485",
        "tgn:1000001",
        "tgn:7012149",
        "tgn:2002078",
        "tgn:7007826",
        "tgn:7029392"
    ],
    "tgn:id":2106485,
    "tgn:name":"Old Glory",
    "tgn:placetype":[
        "aat:300008347"
    ]
},
  "bbox": [],
  "geometry": {"coordinates":[-100.05,33.1167],"type":"Point"}
}