{
  "id": 7035990,
  "type": "Feature",
  "properties": {
    "tgn:hierarchy":[
        "tgn:7035990",
        "tgn:7002991",
        "tgn:1000003",
        "tgn:7002997",
        "tgn:1000080",
        "tgn:7029392"
    ],
    "tgn:id":7035990,
    "tgn:name":"Averau",
    "tgn:placetype":[
        "aat:300008795"
    ]
},
  "bbox": [],
  "geometry": {"coordinates":[12.025278,46.506111],"type":"Point"}
}