{
  "id": 7078797,
  "type": "Feature",
  "properties": {
    "tgn:hierarchy":[
        "tgn:7078797",
        "tgn:7003692",
        "tgn:1000003",
        "tgn:7000084",
        "tgn:7029392"
    ],
    "tgn:id":7078797,
    "tgn:name":"Wisserhof",
    "tgn:placetype":[
        "aat:300000206"
    ]
},
  "bbox": [],
  "geometry": {"coordinates":[7.916667,48.05],"type":"Point"}
}