{
  "id": 2700275,
  "type": "Feature",
  "properties": {
    "tgn:hierarchy":[
        "tgn:2700275",
        "tgn:1000001",
        "tgn:2000951",
        "tgn:7012149",
        "tgn:7007520",
        "tgn:7029392"
    ],
    "tgn:id":2700275,
    "tgn:name":"Sturgis Creek",
    "tgn:placetype":[
        "aat:300008706"
    ]
},
  "bbox": [],
  "geometry": {"coordinates":[-84.2667,45.3167],"type":"Point"}
}