{
  "id": 7289317,
  "type": "Feature",
  "properties": {
    "tgn:hierarchy":[
        "tgn:7289317",
        "tgn:1001702",
        "tgn:1000049",
        "tgn:1000002",
        "tgn:7029392"
    ],
    "tgn:id":7289317,
    "tgn:name":"Ingl\u00e9s, Paso",
    "tgn:placetype":[
        "aat:300387026"
    ]
},
  "bbox": [],
  "geometry": {"coordinates":[-72.166667,-53.666667],"type":"Point"}
}