{
  "id": 2642942,
  "type": "Feature",
  "properties": {
    "tgn:hierarchy":[
        "tgn:2642942",
        "tgn:1000001",
        "tgn:7012149",
        "tgn:2002371",
        "tgn:7007923",
        "tgn:7029392"
    ],
    "tgn:id":2642942,
    "tgn:name":"Sandstone Reservoir",
    "tgn:placetype":[
        "aat:300006191"
    ]
},
  "bbox": [],
  "geometry": {"coordinates":[-108.45,42.6667],"type":"Point"}
}