{
  "id": 2305525,
  "type": "Feature",
  "properties": {
    "tgn:hierarchy":[
        "tgn:2305525",
        "tgn:1000001",
        "tgn:7012149",
        "tgn:1002485",
        "tgn:7007826",
        "tgn:7029392"
    ],
    "tgn:id":2305525,
    "tgn:name":"East Caney Creek",
    "tgn:placetype":[
        "aat:300008706"
    ]
},
  "bbox": [],
  "geometry": {"coordinates":[-95.4333,33.0333],"type":"Point"}
}