{
  "id": 2640529,
  "type": "Feature",
  "properties": {
    "tgn:hierarchy":[
        "tgn:2640529",
        "tgn:1000001",
        "tgn:7012149",
        "tgn:7007826",
        "tgn:7029392"
    ],
    "tgn:id":2640529,
    "tgn:name":"San Juan Draw",
    "tgn:placetype":[
        "aat:300008761"
    ]
},
  "bbox": [],
  "geometry": {"coordinates":[-100.9833,30.5167],"type":"Point"}
}