{
  "id": 1076738,
  "type": "Feature",
  "properties": {
    "tgn:hierarchy":[
        "tgn:1076738",
        "tgn:1000004",
        "tgn:7000198",
        "tgn:1001977",
        "tgn:7029392"
    ],
    "tgn:id":1076738,
    "tgn:name":"Raiganj",
    "tgn:placetype":[
        "aat:300008347"
    ]
},
  "bbox": [],
  "geometry": {"coordinates":[88.124486,25.612809],"type":"Point"}
}