{
  "id": 2360854,
  "type": "Feature",
  "properties": {
    "tgn:hierarchy":[
        "tgn:2360854",
        "tgn:1000001",
        "tgn:7012149",
        "tgn:1002837",
        "tgn:7007255",
        "tgn:7029392"
    ],
    "tgn:id":2360854,
    "tgn:name":"Grassy Lick Branch",
    "tgn:placetype":[
        "aat:300008699"
    ]
},
  "bbox": [],
  "geometry": {"coordinates":[-83.4667,38.2333],"type":"Point"}
}