{
  "id": 7529448,
  "type": "Feature",
  "properties": {
    "tgn:hierarchy":[
        "tgn:7529448",
        "tgn:7001242",
        "tgn:7016833",
        "tgn:1001092",
        "tgn:7029392"
    ],
    "tgn:id":7529448,
    "tgn:name":"S\u012bd\u012b an Najd\u012b",
    "tgn:placetype":[
        "aat:300005926"
    ]
},
  "bbox": [],
  "geometry": {"coordinates":[31.25,30.25],"type":"Point"}
}