{
  "id": 2634286,
  "type": "Feature",
  "properties": {
    "tgn:hierarchy":[
        "tgn:2634286",
        "tgn:7002659",
        "tgn:1000001",
        "tgn:7012149",
        "tgn:2000035",
        "tgn:7029392"
    ],
    "tgn:id":2634286,
    "tgn:name":"Russell Point",
    "tgn:placetype":[
        "aat:300008850"
    ]
},
  "bbox": [],
  "geometry": {"coordinates":[-85.8833,34.85],"type":"Point"}
}