{
  "id": 2682289,
  "type": "Feature",
  "properties": {
    "tgn:hierarchy":[
        "tgn:2682289",
        "tgn:1000001",
        "tgn:2001410",
        "tgn:7012149",
        "tgn:7007526",
        "tgn:7029392"
    ],
    "tgn:id":2682289,
    "tgn:name":"South Virgin Mountains",
    "tgn:placetype":[
        "aat:300386831"
    ]
},
  "bbox": [],
  "geometry": {"coordinates":[-114.1833,36.25],"type":"Point"}
}