{
  "id": 7534121,
  "type": "Feature",
  "properties": {
    "tgn:hierarchy":[
        "tgn:7534121",
        "tgn:7001242",
        "tgn:7016833",
        "tgn:7001335",
        "tgn:7029392"
    ],
    "tgn:id":7534121,
    "tgn:name:en":"\u1e28asanah, Jabal al",
    "tgn:placetype":[
        "aat:300008795"
    ]
},
  "bbox": [],
  "geometry": {"coordinates":[33.783984,30.429054],"type":"Point"}
}