<<<<<<< HEAD
{
  "id": 7179938,
  "type": "Feature",
  "properties": {
    "tgn:hierarchy":[
        "tgn:7179938",
        "tgn:1000003",
        "tgn:7003676",
        "tgn:7000084",
        "tgn:7029392"
    ],
    "tgn:id":7179938,
    "tgn:name":"Haakd\u00fcnen",
    "tgn:placetype":[
        "aat:300008750"
    ]
},
  "bbox": [],
  "geometry": {"coordinates":[6.883333,53.666667],"type":"Point"}
}
=======
{"geometry":{"type":"Point","coordinates":[6.883333,53.666667]},"type":"Feature","properties":{"hierarchy":["tgn:7179938","tgn:1000003","tgn:7003676","tgn:7000084","tgn:7029392"],"placetype":["aat:300008750"],"id":7179938,"name:xx":"Haakd\u00fcnen"}}
>>>>>>> 03f74aca74312dbeaf24d7e61306dd6a786dc3d0
