<<<<<<< HEAD
{
  "id": 2403903,
  "type": "Feature",
  "properties": {
    "tgn:hierarchy":[
        "tgn:2403903",
        "tgn:1000001",
        "tgn:7012149",
        "tgn:2000975",
        "tgn:7007520",
        "tgn:7029392"
    ],
    "tgn:id":2403903,
    "tgn:name":"Howe Lake",
    "tgn:placetype":[
        "aat:300008680"
    ]
},
  "bbox": [],
  "geometry": {"coordinates":[-87.9333,46.8833],"type":"Point"}
}
=======
{"geometry":{"type":"Point","coordinates":[-87.933300,46.883300]},"type":"Feature","properties":{"hierarchy":["tgn:2403903","tgn:1000001","tgn:7012149","tgn:2000975","tgn:7007520","tgn:7029392"],"placetype":["aat:300008680"],"id":2403903,"name:xx":"Howe Lake"}}
>>>>>>> 03f74aca74312dbeaf24d7e61306dd6a786dc3d0
