{
  "id": 2403903,
  "type": "Feature",
  "properties": {
    "tgn:hierarchy":[
        "tgn:2403903",
        "tgn:1000001",
        "tgn:7012149",
        "tgn:2000975",
        "tgn:7007520",
        "tgn:7029392"
    ],
    "tgn:id":2403903,
    "tgn:name":"Howe Lake",
    "tgn:placetype":[
        "aat:300008680"
    ]
},
  "bbox": [],
  "geometry": {"coordinates":[-87.9333,46.8833],"type":"Point"}
}