{
  "id": 7281994,
  "type": "Feature",
  "properties": {
    "tgn:hierarchy":[
        "tgn:7281994",
        "tgn:1001692",
        "tgn:1000049",
        "tgn:1000002",
        "tgn:7029392"
    ],
    "tgn:id":7281994,
    "tgn:name":"San Pedro, Laguna",
    "tgn:placetype":[
        "aat:300008680"
    ]
},
  "bbox": [],
  "geometry": {"coordinates":[-71.316667,-38.433333],"type":"Point"}
}