{
  "id": 7536581,
  "type": "Feature",
  "properties": {
    "tgn:hierarchy":[
        "tgn:7536581",
        "tgn:7001242",
        "tgn:7001311",
        "tgn:7016833",
        "tgn:7029392"
    ],
    "tgn:id":7536581,
    "tgn:name:en":"Gurdi el- Soghair, W\u00e2di",
    "tgn:placetype":[
        "aat:300379998"
    ]
},
  "bbox": [],
  "geometry": {"coordinates":[32.566667,26.783333],"type":"Point"}
}