{
  "id": 2538335,
  "type": "Feature",
  "properties": {
    "tgn:hierarchy":[
        "tgn:2538335",
        "tgn:7006450",
        "tgn:1000001",
        "tgn:7030547",
        "tgn:7012149",
        "tgn:7029392"
    ],
    "tgn:id":2538335,
    "tgn:name":"Nenana River Gorge",
    "tgn:placetype":[
        "aat:300008761"
    ]
},
  "bbox": [],
  "geometry": {"coordinates":[-148.8833,63.75],"type":"Point"}
}