{
  "id": 1107336,
  "type": "Feature",
  "properties": {
    "tgn:hierarchy":[
        "tgn:1107336",
        "tgn:1000001",
        "tgn:7012149",
        "tgn:7007157",
        "tgn:1002684",
        "tgn:7029392"
    ],
    "tgn:id":1107336,
    "tgn:name":"Junipero Serra Peak",
    "tgn:placetype":[
        "aat:300008798"
    ]
},
  "bbox": [],
  "geometry": {"coordinates":[-121.4167,36.1333],"type":"Point"}
}