<<<<<<< HEAD
{
  "id": 2761341,
  "type": "Feature",
  "properties": {
    "tgn:hierarchy":[
        "tgn:2761341",
        "tgn:1000001",
        "tgn:7012149",
        "tgn:7007158",
        "tgn:7029392"
    ],
    "tgn:id":2761341,
    "tgn:name":"West Miller Creek",
    "tgn:placetype":[
        "aat:300008706"
    ]
},
  "bbox": [],
  "geometry": {"coordinates":[-107.8167,39.7667],"type":"Point"}
}
=======
{"geometry":{"type":"Point","coordinates":[-107.816700,39.766700]},"type":"Feature","properties":{"hierarchy":["tgn:2761341","tgn:1000001","tgn:7012149","tgn:7007158","tgn:7029392"],"placetype":["aat:300008706"],"id":2761341,"name:xx":"West Miller Creek"}}
>>>>>>> 03f74aca74312dbeaf24d7e61306dd6a786dc3d0
