{
  "id": 2761341,
  "type": "Feature",
  "properties": {
    "tgn:hierarchy":[
        "tgn:2761341",
        "tgn:1000001",
        "tgn:7012149",
        "tgn:7007158",
        "tgn:7029392"
    ],
    "tgn:id":2761341,
    "tgn:name":"West Miller Creek",
    "tgn:placetype":[
        "aat:300008706"
    ]
},
  "bbox": [],
  "geometry": {"coordinates":[-107.8167,39.7667],"type":"Point"}
}