{
  "id": 7342286,
  "type": "Feature",
  "properties": {
    "tgn:hierarchy":[
        "tgn:7342286",
        "tgn:7002808",
        "tgn:7030216",
        "tgn:1000003",
        "tgn:1000095",
        "tgn:7029392"
    ],
    "tgn:id":7342286,
    "tgn:name":"Castellfullit del Boix",
    "tgn:placetype":[
        "aat:300008347"
    ]
},
  "bbox": [],
  "geometry": {"coordinates":[1.683796,41.665811],"type":"Point"}
}