{
  "id": 7545951,
  "type": "Feature",
  "properties": {
    "tgn:hierarchy":[
        "tgn:7545951",
        "tgn:1000004",
        "tgn:7000198",
        "tgn:7031783",
        "tgn:7029392"
    ],
    "tgn:id":7545951,
    "tgn:name:en":"Bhoya",
    "tgn:placetype":[
        "aat:300008347"
    ]
},
  "bbox": [],
  "geometry": {"coordinates":[85.811937,22.677777],"type":"Point"}
}