{
  "id": 2480742,
  "type": "Feature",
  "properties": {
    "tgn:hierarchy":[
        "tgn:2480742",
        "tgn:1002338",
        "tgn:1000001",
        "tgn:7012149",
        "tgn:7007516",
        "tgn:7029392"
    ],
    "tgn:id":2480742,
    "tgn:name":"Lakesville",
    "tgn:placetype":[
        "aat:300008347"
    ]
},
  "bbox": [],
  "geometry": {"coordinates":[-76.1333,38.3333],"type":"Point"}
}