{
  "id": 1128394,
  "type": "Feature",
  "properties": {
    "tgn:hierarchy":[
        "tgn:1128394",
        "tgn:7006260",
        "tgn:7002454",
        "tgn:1000047",
        "tgn:1000002",
        "tgn:7029392"
    ],
    "tgn:id":1128394,
    "tgn:name":"Parana\u00edta",
    "tgn:placetype":[
        "aat:300008707"
    ]
},
  "bbox": [],
  "geometry": {"coordinates":[-56.7167,-9.4667],"type":"Point"}
}