{
  "id": 2770081,
  "type": "Feature",
  "properties": {
    "tgn:hierarchy":[
        "tgn:2770081",
        "tgn:1000001",
        "tgn:2001264",
        "tgn:7012149",
        "tgn:7007524",
        "tgn:7029392"
    ],
    "tgn:id":2770081,
    "tgn:name":"Wild Bill Lake",
    "tgn:placetype":[
        "aat:300008680"
    ]
},
  "bbox": [],
  "geometry": {"coordinates":[-109.3667,45.15],"type":"Point"}
}