<<<<<<< HEAD
{
  "id": 7175649,
  "type": "Feature",
  "properties": {
    "tgn:hierarchy":[
        "tgn:7175649",
        "tgn:1000003",
        "tgn:7003676",
        "tgn:7000084",
        "tgn:7029392"
    ],
    "tgn:id":7175649,
    "tgn:name":"Gro\u00dfes Moor",
    "tgn:placetype":[
        "aat:300008903"
    ]
},
  "bbox": [],
  "geometry": {"coordinates":[10.6,53.05],"type":"Point"}
}
=======
{"geometry":{"type":"Point","coordinates":[10.600000,53.050000]},"type":"Feature","properties":{"hierarchy":["tgn:7175649","tgn:1000003","tgn:7003676","tgn:7000084","tgn:7029392"],"placetype":["aat:300008903"],"id":7175649,"name:xx":"Gro\u00dfes Moor"}}
>>>>>>> 03f74aca74312dbeaf24d7e61306dd6a786dc3d0
