<<<<<<< HEAD
{
  "id": 2767186,
  "type": "Feature",
  "properties": {
    "tgn:hierarchy":[
        "tgn:2767186",
        "tgn:1000001",
        "tgn:7012149",
        "tgn:7007157",
        "tgn:1002706",
        "tgn:7029392"
    ],
    "tgn:id":2767186,
    "tgn:name":"White Rock Mine",
    "tgn:placetype":[
        "aat:300000390"
    ]
},
  "bbox": [],
  "geometry": {"coordinates":[-122.3667,38.65],"type":"Point"}
}
=======
{"geometry":{"type":"Point","coordinates":[-122.366700,38.650000]},"type":"Feature","properties":{"hierarchy":["tgn:2767186","tgn:1000001","tgn:7012149","tgn:7007157","tgn:1002706","tgn:7029392"],"placetype":["aat:300000390"],"id":2767186,"name:xx":"White Rock Mine"}}
>>>>>>> 03f74aca74312dbeaf24d7e61306dd6a786dc3d0
