{
  "id": 2160629,
  "type": "Feature",
  "properties": {
    "tgn:hierarchy":[
        "tgn:2160629",
        "tgn:1000001",
        "tgn:2002103",
        "tgn:7012149",
        "tgn:7007827",
        "tgn:7029392"
    ],
    "tgn:id":2160629,
    "tgn:name":"Beirdneau Hollow",
    "tgn:placetype":[
        "aat:300008761"
    ]
},
  "bbox": [],
  "geometry": {"coordinates":[-111.6833,41.7833],"type":"Point"}
}