<<<<<<< HEAD
{
  "id": 2707171,
  "type": "Feature",
  "properties": {
    "tgn:hierarchy":[
        "tgn:2707171",
        "tgn:2000943",
        "tgn:1000001",
        "tgn:7012149",
        "tgn:7007520",
        "tgn:7029392"
    ],
    "tgn:id":2707171,
    "tgn:name":"Swede Lake",
    "tgn:placetype":[
        "aat:300008680"
    ]
},
  "bbox": [],
  "geometry": {"coordinates":[-86.6333,46.3667],"type":"Point"}
}
=======
{"geometry":{"type":"Point","coordinates":[-86.633300,46.366700]},"type":"Feature","properties":{"hierarchy":["tgn:2707171","tgn:2000943","tgn:1000001","tgn:7012149","tgn:7007520","tgn:7029392"],"placetype":["aat:300008680"],"id":2707171,"name:xx":"Swede Lake"}}
>>>>>>> 03f74aca74312dbeaf24d7e61306dd6a786dc3d0
