{
  "id": 2707171,
  "type": "Feature",
  "properties": {
    "tgn:hierarchy":[
        "tgn:2707171",
        "tgn:2000943",
        "tgn:1000001",
        "tgn:7012149",
        "tgn:7007520",
        "tgn:7029392"
    ],
    "tgn:id":2707171,
    "tgn:name":"Swede Lake",
    "tgn:placetype":[
        "aat:300008680"
    ]
},
  "bbox": [],
  "geometry": {"coordinates":[-86.6333,46.3667],"type":"Point"}
}