{
  "id": 2640502,
  "type": "Feature",
  "properties": {
    "tgn:hierarchy":[
        "tgn:2640502",
        "tgn:1000001",
        "tgn:7012149",
        "tgn:2002049",
        "tgn:7007826",
        "tgn:7029392"
    ],
    "tgn:id":2640502,
    "tgn:name":"San Juan",
    "tgn:placetype":[
        "aat:300008347"
    ]
},
  "bbox": [],
  "geometry": {"coordinates":[-97.5333,27.7667],"type":"Point"}
}