{
  "id": 7276831,
  "type": "Feature",
  "properties": {
    "tgn:hierarchy":[
        "tgn:7276831",
        "tgn:1001699",
        "tgn:1000049",
        "tgn:1000002",
        "tgn:7029392"
    ],
    "tgn:id":7276831,
    "tgn:name":"Yahuecha, Punta",
    "tgn:placetype":[
        "aat:300386846"
    ]
},
  "bbox": [],
  "geometry": {"coordinates":[-73.133333,-41.75],"type":"Point"}
}