<<<<<<< HEAD
{
  "id": 2257353,
  "type": "Feature",
  "properties": {
    "tgn:hierarchy":[
        "tgn:2257353",
        "tgn:1000001",
        "tgn:7012149",
        "tgn:1002424",
        "tgn:7007706",
        "tgn:7029392"
    ],
    "tgn:id":2257353,
    "tgn:name":"Cornstalk",
    "tgn:placetype":[
        "aat:300008347"
    ]
},
  "bbox": [],
  "geometry": {"coordinates":[-83.9833,39.5667],"type":"Point"}
}
=======
{"geometry":{"type":"Point","coordinates":[-83.983300,39.566700]},"type":"Feature","properties":{"hierarchy":["tgn:2257353","tgn:1000001","tgn:7012149","tgn:1002424","tgn:7007706","tgn:7029392"],"placetype":["aat:300008347"],"id":2257353,"name:xx":"Cornstalk"}}
>>>>>>> 03f74aca74312dbeaf24d7e61306dd6a786dc3d0
