{
  "id": 2257353,
  "type": "Feature",
  "properties": {
    "tgn:hierarchy":[
        "tgn:2257353",
        "tgn:1000001",
        "tgn:7012149",
        "tgn:1002424",
        "tgn:7007706",
        "tgn:7029392"
    ],
    "tgn:id":2257353,
    "tgn:name":"Cornstalk",
    "tgn:placetype":[
        "aat:300008347"
    ]
},
  "bbox": [],
  "geometry": {"coordinates":[-83.9833,39.5667],"type":"Point"}
}