{
  "id": 2621904,
  "type": "Feature",
  "properties": {
    "tgn:hierarchy":[
        "tgn:2621904",
        "tgn:1000001",
        "tgn:7012149",
        "tgn:2001440",
        "tgn:7007566",
        "tgn:7029392"
    ],
    "tgn:id":2621904,
    "tgn:name":"Robert E Lee Mine",
    "tgn:placetype":[
        "aat:300000390"
    ]
},
  "bbox": [],
  "geometry": {"coordinates":[-108.75,32.25],"type":"Point"}
}