{
  "id": 7287718,
  "type": "Feature",
  "properties": {
    "tgn:hierarchy":[
        "tgn:7287718",
        "tgn:1001699",
        "tgn:1000049",
        "tgn:1000002",
        "tgn:7029392"
    ],
    "tgn:id":7287718,
    "tgn:name":"Imaleb, Isla de",
    "tgn:placetype":[
        "aat:300008791"
    ]
},
  "bbox": [],
  "geometry": {"coordinates":[-73.409167,-42.605],"type":"Point"}
}