{
  "id": 2538697,
  "type": "Feature",
  "properties": {
    "tgn:hierarchy":[
        "tgn:2538697",
        "tgn:1000001",
        "tgn:7012149",
        "tgn:1002458",
        "tgn:7007255",
        "tgn:7029392"
    ],
    "tgn:id":2538697,
    "tgn:name":"Neurls Run",
    "tgn:placetype":[
        "aat:300008699"
    ]
},
  "bbox": [],
  "geometry": {"coordinates":[-84.2833,38.4667],"type":"Point"}
}