{
  "id": 2411819,
  "type": "Feature",
  "properties": {
    "tgn:hierarchy":[
        "tgn:2411819",
        "tgn:1000001",
        "tgn:7012149",
        "tgn:2002195",
        "tgn:7007919",
        "tgn:7029392"
    ],
    "tgn:id":2411819,
    "tgn:name":"Indian Mountain",
    "tgn:placetype":[
        "aat:300266640"
    ]
},
  "bbox": [],
  "geometry": {"coordinates":[-82.6167,37.05],"type":"Point"}
}