{
  "id": 7572404,
  "type": "Feature",
  "properties": {
    "tgn:hierarchy":[
        "tgn:7572404",
        "tgn:7001819",
        "tgn:1000004",
        "tgn:7000198",
        "tgn:7029392"
    ],
    "tgn:id":7572404,
    "tgn:name:en":"Hong",
    "tgn:placetype":[
        "aat:300008347"
    ]
},
  "bbox": [],
  "geometry": {"coordinates":[93.849496,27.559219],"type":"Point"}
}