{
  "id": 2410246,
  "type": "Feature",
  "properties": {
    "tgn:hierarchy":[
        "tgn:2410246",
        "tgn:1000001",
        "tgn:7012149",
        "tgn:1002355",
        "tgn:7007826",
        "tgn:7029392"
    ],
    "tgn:id":2410246,
    "tgn:name":"India Branch",
    "tgn:placetype":[
        "aat:300008699"
    ]
},
  "bbox": [],
  "geometry": {"coordinates":[-96.6167,32.5167],"type":"Point"}
}