<<<<<<< HEAD
{
  "id": 7174501,
  "type": "Feature",
  "properties": {
    "tgn:hierarchy":[
        "tgn:7174501",
        "tgn:7003669",
        "tgn:1000003",
        "tgn:7000084",
        "tgn:7029392"
    ],
    "tgn:id":7174501,
    "tgn:name":"Grubm\u00fchle",
    "tgn:placetype":[
        "aat:300000206"
    ]
},
  "bbox": [],
  "geometry": {"coordinates":[12.9,48.25],"type":"Point"}
}
=======
{"geometry":{"type":"Point","coordinates":[12.900000,48.250000]},"type":"Feature","properties":{"hierarchy":["tgn:7174501","tgn:7003669","tgn:1000003","tgn:7000084","tgn:7029392"],"placetype":["aat:300000206"],"id":7174501,"name:xx":"Grubm\u00fchle"}}
>>>>>>> 03f74aca74312dbeaf24d7e61306dd6a786dc3d0
