{
  "id": 2401910,
  "type": "Feature",
  "properties": {
    "tgn:hierarchy":[
        "tgn:2401910",
        "tgn:1000001",
        "tgn:7012149",
        "tgn:2002337",
        "tgn:7007922",
        "tgn:7029392"
    ],
    "tgn:id":2401910,
    "tgn:name":"Horseshoe Lake",
    "tgn:placetype":[
        "aat:300008680"
    ]
},
  "bbox": [],
  "geometry": {"coordinates":[-88.05,45.1167],"type":"Point"}
}