{
  "id": 1108659,
  "type": "Feature",
  "properties": {
    "tgn:hierarchy":[
        "tgn:1108659",
        "tgn:1000001",
        "tgn:7012149",
        "tgn:2002119",
        "tgn:7007827",
        "tgn:7029392"
    ],
    "tgn:id":1108659,
    "tgn:name":"Abajo Mountains",
    "tgn:placetype":[
        "aat:300008795"
    ]
},
  "bbox": [],
  "geometry": {"coordinates":[-109.5333,37.85],"type":"Point"}
}