{
  "id": 7497825,
  "type": "Feature",
  "properties": {
    "tgn:hierarchy":[
        "tgn:7497825",
        "tgn:1000004",
        "tgn:1000454",
        "tgn:1000141",
        "tgn:7029392"
    ],
    "tgn:id":7497825,
    "tgn:name":"Beiji Xincheng",
    "tgn:placetype":[
        "aat:300000498"
    ]
},
  "bbox": [],
  "geometry": {"coordinates":[121.682942,25.176353],"type":"Point"}
}