{
  "id": 2743914,
  "type": "Feature",
  "properties": {
    "tgn:hierarchy":[
        "tgn:2743914",
        "tgn:2002143",
        "tgn:1000001",
        "tgn:7012149",
        "tgn:7007919",
        "tgn:7029392"
    ],
    "tgn:id":2743914,
    "tgn:name":"Venable Hollow",
    "tgn:placetype":[
        "aat:300008761"
    ]
},
  "bbox": [],
  "geometry": {"coordinates":[-79.6333,38.0667],"type":"Point"}
}