{
  "id": 1058543,
  "type": "Feature",
  "properties": {
    "tgn:hierarchy":[
        "tgn:1058543",
        "tgn:1000004",
        "tgn:7011565",
        "tgn:7018214",
        "tgn:7002435",
        "tgn:7029392"
    ],
    "tgn:id":1058543,
    "tgn:name":"Polessk",
    "tgn:placetype":[
        "aat:300008347"
    ]
},
  "bbox": [],
  "geometry": {"coordinates":[21.15,54.85],"type":"Point"}
}