{
  "id": 7253831,
  "type": "Feature",
  "properties": {
    "tgn:hierarchy":[
        "tgn:7253831",
        "tgn:7003456",
        "tgn:1000003",
        "tgn:1000063",
        "tgn:7018236",
        "tgn:7029392"
    ],
    "tgn:id":7253831,
    "tgn:name":"Terheidehoek",
    "tgn:placetype":[
        "aat:300008347"
    ]
},
  "bbox": [],
  "geometry": {"coordinates":[4.839933,50.942472],"type":"Point"}
}