{
  "id": 7272450,
  "type": "Feature",
  "properties": {
    "tgn:hierarchy":[
        "tgn:7272450",
        "tgn:7003614",
        "tgn:1000003",
        "tgn:7016845",
        "tgn:7029392"
    ],
    "tgn:id":7272450,
    "tgn:name:nl":"Hoge Veenkanal",
    "tgn:placetype":[
        "aat:300006075"
    ]
},
  "bbox": [],
  "geometry": {"coordinates":[6.516667,52.733333],"type":"Point"}
}