{
  "id": 2350381,
  "type": "Feature",
  "properties": {
    "tgn:hierarchy":[
        "tgn:2350381",
        "tgn:1000001",
        "tgn:7012149",
        "tgn:2001896",
        "tgn:7007825",
        "tgn:7029392"
    ],
    "tgn:id":2350381,
    "tgn:name":"Gipson Hollow",
    "tgn:placetype":[
        "aat:300008761"
    ]
},
  "bbox": [],
  "geometry": {"coordinates":[-87.25,35.55],"type":"Point"}
}