{
  "id": 2550532,
  "type": "Feature",
  "properties": {
    "tgn:hierarchy":[
        "tgn:2550532",
        "tgn:1000001",
        "tgn:7012149",
        "tgn:1002386",
        "tgn:7007706",
        "tgn:7029392"
    ],
    "tgn:id":2550532,
    "tgn:name":"Northwoods",
    "tgn:placetype":[
        "aat:300008347"
    ]
},
  "bbox": [],
  "geometry": {"coordinates":[-83.0167,40.1167],"type":"Point"}
}