{
  "id": 7136045,
  "type": "Feature",
  "properties": {
    "tgn:hierarchy":[
        "tgn:7136045",
        "tgn:1000003",
        "tgn:7003682",
        "tgn:7000084",
        "tgn:7029392"
    ],
    "tgn:id":7136045,
    "tgn:name":"Mohrenm\u00fchle",
    "tgn:placetype":[
        "aat:300000206"
    ]
},
  "bbox": [],
  "geometry": {"coordinates":[7.416667,50.183333],"type":"Point"}
}