{
  "id": 7563848,
  "type": "Feature",
  "properties": {
    "tgn:hierarchy":[
        "tgn:7563848",
        "tgn:1000004",
        "tgn:7000198",
        "tgn:1001894",
        "tgn:7029392"
    ],
    "tgn:id":7563848,
    "tgn:name:en":"K\u012bratpura",
    "tgn:placetype":[
        "aat:300008347"
    ]
},
  "bbox": [],
  "geometry": {"coordinates":[79.395301,24.973523],"type":"Point"}
}