{
  "id": 1111679,
  "type": "Feature",
  "properties": {
    "tgn:hierarchy":[
        "tgn:1111679",
        "tgn:7003025",
        "tgn:1000003",
        "tgn:1000062",
        "tgn:7029392"
    ],
    "tgn:id":1111679,
    "tgn:name":"H\u00f6llental",
    "tgn:placetype":[
        "aat:300008761"
    ]
},
  "bbox": [],
  "geometry": {"coordinates":[15.7833,47.75],"type":"Point"}
}