{
  "id": 7497260,
  "type": "Feature",
  "properties": {
    "tgn:hierarchy":[
        "tgn:7497260",
        "tgn:1000004",
        "tgn:1000959",
        "tgn:1000141",
        "tgn:7029392"
    ],
    "tgn:id":7497260,
    "tgn:name":"Tupijiao",
    "tgn:placetype":[
        "aat:300008347"
    ]
},
  "bbox": [],
  "geometry": {"coordinates":[121.590354,25.100833],"type":"Point"}
}