{
  "id": 2190709,
  "type": "Feature",
  "properties": {
    "tgn:hierarchy":[
        "tgn:2190709",
        "tgn:1000001",
        "tgn:7012149",
        "tgn:2002372",
        "tgn:7007923",
        "tgn:7029392"
    ],
    "tgn:id":2190709,
    "tgn:name":"Boxelder Spring",
    "tgn:placetype":[
        "aat:300008697"
    ]
},
  "bbox": [],
  "geometry": {"coordinates":[-104.1167,41.6833],"type":"Point"}
}