{
  "id": 2752332,
  "type": "Feature",
  "properties": {
    "tgn:hierarchy":[
        "tgn:2752332",
        "tgn:7006450",
        "tgn:1000001",
        "tgn:2124089",
        "tgn:7012149",
        "tgn:7029392"
    ],
    "tgn:id":2752332,
    "tgn:name":"Washington Basin",
    "tgn:placetype":[
        "aat:300386845"
    ]
},
  "bbox": [],
  "geometry": {"coordinates":[-134.1333,58.6333],"type":"Point"}
}