{
  "id": 2716778,
  "type": "Feature",
  "properties": {
    "tgn:hierarchy":[
        "tgn:2716778",
        "tgn:1000001",
        "tgn:7012149",
        "tgn:2001525",
        "tgn:7007709",
        "tgn:7029392"
    ],
    "tgn:id":2716778,
    "tgn:name":"The Woods At Laurel Hill",
    "tgn:placetype":[
        "aat:300008347"
    ]
},
  "bbox": [],
  "geometry": {"coordinates":[-79.0333,35.8833],"type":"Point"}
}