{
  "id": 2330202,
  "type": "Feature",
  "properties": {
    "tgn:hierarchy":[
        "tgn:2330202",
        "tgn:1000001",
        "tgn:7012149",
        "tgn:2001690",
        "tgn:7007707",
        "tgn:7029392"
    ],
    "tgn:id":2330202,
    "tgn:name":"Flanagan Mountain",
    "tgn:placetype":[
        "aat:300008798"
    ]
},
  "bbox": [],
  "geometry": {"coordinates":[-94.55,35.6167],"type":"Point"}
}