<<<<<<< HEAD
{
  "id": 2330202,
  "type": "Feature",
  "properties": {
    "tgn:hierarchy":[
        "tgn:2330202",
        "tgn:1000001",
        "tgn:7012149",
        "tgn:2001690",
        "tgn:7007707",
        "tgn:7029392"
    ],
    "tgn:id":2330202,
    "tgn:name":"Flanagan Mountain",
    "tgn:placetype":[
        "aat:300008798"
    ]
},
  "bbox": [],
  "geometry": {"coordinates":[-94.55,35.6167],"type":"Point"}
}
=======
{"geometry":{"type":"Point","coordinates":[-94.550000,35.616700]},"type":"Feature","properties":{"hierarchy":["tgn:2330202","tgn:1000001","tgn:7012149","tgn:2001690","tgn:7007707","tgn:7029392"],"placetype":["aat:300008798"],"id":2330202,"name:xx":"Flanagan Mountain"}}
>>>>>>> 03f74aca74312dbeaf24d7e61306dd6a786dc3d0
