{
  "id": 2740375,
  "type": "Feature",
  "properties": {
    "tgn:hierarchy":[
        "tgn:2740375",
        "tgn:1000001",
        "tgn:2001260",
        "tgn:7012149",
        "tgn:7007524",
        "tgn:7029392"
    ],
    "tgn:id":2740375,
    "tgn:name":"Upper Magpie Spring",
    "tgn:placetype":[
        "aat:300008697"
    ]
},
  "bbox": [],
  "geometry": {"coordinates":[-112.85,45.1833],"type":"Point"}
}