{
  "id": 2201744,
  "type": "Feature",
  "properties": {
    "tgn:hierarchy":[
        "tgn:2201744",
        "tgn:1000001",
        "tgn:7012149",
        "tgn:1002897",
        "tgn:7007920",
        "tgn:7029392"
    ],
    "tgn:id":2201744,
    "tgn:name":"Buck Creek",
    "tgn:placetype":[
        "aat:300008706"
    ]
},
  "bbox": [],
  "geometry": {"coordinates":[-121.65,46.35],"type":"Point"}
}