{
  "id": 7366388,
  "type": "Feature",
  "properties": {
    "tgn:hierarchy":[
        "tgn:7366388",
        "tgn:7005581",
        "tgn:1000001",
        "tgn:7005560",
        "tgn:7029392"
    ],
    "tgn:id":7366388,
    "tgn:name":"El Terrero",
    "tgn:placetype":[
        "aat:300008347"
    ]
},
  "bbox": [],
  "geometry": {"coordinates":[-106.566667,28.283333],"type":"Point"}
}