<<<<<<< HEAD
{
  "id": 2333195,
  "type": "Feature",
  "properties": {
    "tgn:hierarchy":[
        "tgn:2333195",
        "tgn:1000001",
        "tgn:7012149",
        "tgn:1002800",
        "tgn:7007710",
        "tgn:7029392"
    ],
    "tgn:id":2333195,
    "tgn:name":"Flynn Hollow",
    "tgn:placetype":[
        "aat:300008761"
    ]
},
  "bbox": [],
  "geometry": {"coordinates":[-77.6833,41.8167],"type":"Point"}
}
=======
{"geometry":{"type":"Point","coordinates":[-77.683300,41.816700]},"type":"Feature","properties":{"hierarchy":["tgn:2333195","tgn:1000001","tgn:7012149","tgn:1002800","tgn:7007710","tgn:7029392"],"placetype":["aat:300008761"],"id":2333195,"name:xx":"Flynn Hollow"}}
>>>>>>> 03f74aca74312dbeaf24d7e61306dd6a786dc3d0
