{
  "id": 7478107,
  "type": "Feature",
  "properties": {
    "tgn:hierarchy":[
        "tgn:7478107",
        "tgn:1000004",
        "tgn:7492971",
        "tgn:1000141",
        "tgn:7029392"
    ],
    "tgn:id":7478107,
    "tgn:name":"Chuantou Qiao",
    "tgn:placetype":[
        "aat:300007836"
    ]
},
  "bbox": [],
  "geometry": {"coordinates":[120.472106,22.463649],"type":"Point"}
}