{
  "id": 2260763,
  "type": "Feature",
  "properties": {
    "tgn:hierarchy":[
        "tgn:2260763",
        "tgn:1000001",
        "tgn:7012149",
        "tgn:2001072",
        "tgn:7007521",
        "tgn:7029392"
    ],
    "tgn:id":2260763,
    "tgn:name":"County Ditch Number Seven",
    "tgn:placetype":[
        "aat:300006075"
    ]
},
  "bbox": [],
  "geometry": {"coordinates":[-93.2833,44.0667],"type":"Point"}
}