{
  "id": 1140634,
  "type": "Feature",
  "properties": {
    "tgn:hierarchy":[
        "tgn:1140634",
        "tgn:1000004",
        "tgn:1000962",
        "tgn:7000896",
        "tgn:1000120",
        "tgn:7029392"
    ],
    "tgn:id":1140634,
    "tgn:name":"Yamada",
    "tgn:placetype":[
        "aat:300008347"
    ]
},
  "bbox": [],
  "geometry": {"coordinates":[135.65,34.5167],"type":"Point"}
}