{
  "id": 7003593,
  "type": "Feature",
  "properties": {
    "tgn:hierarchy":[
        "tgn:7003593",
        "tgn:7594007",
        "tgn:1000003",
        "tgn:1000066",
        "tgn:7029392"
    ],
    "tgn:id":7003593,
    "tgn:name":"Skagen",
    "tgn:placetype":[
        "aat:300008347"
    ]
},
  "bbox": [],
  "geometry": {"coordinates":[10.6167,57.7333],"type":"Point"}
}