{
  "id": 7294367,
  "type": "Feature",
  "properties": {
    "tgn:hierarchy":[
        "tgn:7294367",
        "tgn:7002820",
        "tgn:7030216",
        "tgn:1000003",
        "tgn:1000095",
        "tgn:7029392"
    ],
    "tgn:id":7294367,
    "tgn:name":"Vehinat de Esclet",
    "tgn:placetype":[
        "aat:300008347"
    ]
},
  "bbox": [],
  "geometry": {"coordinates":[2.866667,41.85],"type":"Point"}
}