{
  "id": 7422021,
  "type": "Feature",
  "properties": {
    "tgn:hierarchy":[
        "tgn:7422021",
        "tgn:1000001",
        "tgn:1001960",
        "tgn:7005560",
        "tgn:7029392"
    ],
    "tgn:id":7422021,
    "tgn:name":"El Trigo, R\u00edo",
    "tgn:placetype":[
        "aat:300008699"
    ]
},
  "bbox": [],
  "geometry": {"coordinates":[-109.183333,27.416667],"type":"Point"}
}