<<<<<<< HEAD
{
  "id": 7179817,
  "type": "Feature",
  "properties": {
    "tgn:hierarchy":[
        "tgn:7179817",
        "tgn:1000003",
        "tgn:7003677",
        "tgn:7000084",
        "tgn:7029392"
    ],
    "tgn:id":7179817,
    "tgn:name":"Hambach",
    "tgn:placetype":[
        "aat:300008347"
    ]
},
  "bbox": [],
  "geometry": {"coordinates":[6.45,50.9],"type":"Point"}
}
=======
{"geometry":{"type":"Point","coordinates":[6.450000,50.900000]},"type":"Feature","properties":{"hierarchy":["tgn:7179817","tgn:1000003","tgn:7003677","tgn:7000084","tgn:7029392"],"placetype":["aat:300008347"],"id":7179817,"name:xx":"Hambach"}}
>>>>>>> 03f74aca74312dbeaf24d7e61306dd6a786dc3d0
