{
  "id": 2162581,
  "type": "Feature",
  "properties": {
    "tgn:hierarchy":[
        "tgn:2162581",
        "tgn:1000001",
        "tgn:7012149",
        "tgn:7007157",
        "tgn:1002621",
        "tgn:7029392"
    ],
    "tgn:id":2162581,
    "tgn:name":"Bench Canyon",
    "tgn:placetype":[
        "aat:300008761"
    ]
},
  "bbox": [],
  "geometry": {"coordinates":[-119.2667,37.6667],"type":"Point"}
}