{
  "id": 7007115,
  "type": "Feature",
  "properties": {
    "tgn:hierarchy":[
        "tgn:7007115",
        "tgn:1000001",
        "tgn:7005589",
        "tgn:7005560",
        "tgn:7029392"
    ],
    "tgn:id":7007115,
    "tgn:name":"Monterrey",
    "tgn:placetype":[
        "aat:300387277",
        "aat:300008347",
        "aat:300008389",
        "aat:300264742",
        "aat:300387221",
        "aat:300387302"
    ]
},
  "bbox": [],
  "geometry": {"coordinates":[-100.316667,25.666667],"type":"Point"}
}