{
  "id": 2452080,
  "type": "Feature",
  "properties": {
    "tgn:hierarchy":[
        "tgn:2452080",
        "tgn:1000001",
        "tgn:7012149",
        "tgn:1002416",
        "tgn:7007252",
        "tgn:7029392"
    ],
    "tgn:id":2452080,
    "tgn:name":"Little Black Creek",
    "tgn:placetype":[
        "aat:300008706"
    ]
},
  "bbox": [],
  "geometry": {"coordinates":[-85.55,40.6167],"type":"Point"}
}