{
  "id": 2335101,
  "type": "Feature",
  "properties": {
    "tgn:hierarchy":[
        "tgn:2335101",
        "tgn:1000001",
        "tgn:7012149",
        "tgn:7016056",
        "tgn:7007520",
        "tgn:7029392"
    ],
    "tgn:id":2335101,
    "tgn:name":"Forster",
    "tgn:placetype":[
        "aat:300008347"
    ]
},
  "bbox": [],
  "geometry": {"coordinates":[-82.6167,42.55],"type":"Point"}
}