<<<<<<< HEAD
{
  "id": 7363586,
  "type": "Feature",
  "properties": {
    "tgn:hierarchy":[
        "tgn:7363586",
        "tgn:1000001",
        "tgn:7005599",
        "tgn:7005560",
        "tgn:7029392"
    ],
    "tgn:id":7363586,
    "tgn:name":"El Arroyo",
    "tgn:placetype":[
        "aat:300008347"
    ]
},
  "bbox": [],
  "geometry": {"coordinates":[-97.75,21.133333],"type":"Point"}
}
=======
{"geometry":{"type":"Point","coordinates":[-97.750000,21.133333]},"type":"Feature","properties":{"hierarchy":["tgn:7363586","tgn:1000001","tgn:7005599","tgn:7005560","tgn:7029392"],"placetype":["aat:300008347"],"id":7363586,"name:xx":"El Arroyo"}}
>>>>>>> 03f74aca74312dbeaf24d7e61306dd6a786dc3d0
