{
  "id": 1128415,
  "type": "Feature",
  "properties": {
    "tgn:hierarchy":[
        "tgn:1128415",
        "tgn:7006246",
        "tgn:1000047",
        "tgn:7002455",
        "tgn:1000002",
        "tgn:7029392"
    ],
    "tgn:id":1128415,
    "tgn:name":"Parna\u00ecbinha",
    "tgn:placetype":[
        "aat:300008707"
    ]
},
  "bbox": [],
  "geometry": {"coordinates":[-45.9167,-9.2833],"type":"Point"}
}