{
  "id": 7308221,
  "type": "Feature",
  "properties": {
    "tgn:hierarchy":[
        "tgn:7308221",
        "tgn:1001702",
        "tgn:1000049",
        "tgn:1000002",
        "tgn:7029392"
    ],
    "tgn:id":7308221,
    "tgn:name":"May, Islotes",
    "tgn:placetype":[
        "aat:300008791"
    ]
},
  "bbox": [],
  "geometry": {"coordinates":[-75.233333,-49.866667],"type":"Point"}
}