{
  "id": 2486568,
  "type": "Feature",
  "properties": {
    "tgn:hierarchy":[
        "tgn:2486568",
        "tgn:1000001",
        "tgn:2001418",
        "tgn:7012149",
        "tgn:7007526",
        "tgn:7029392"
    ],
    "tgn:id":2486568,
    "tgn:name":"Ledbetter Canyon",
    "tgn:placetype":[
        "aat:300008761"
    ]
},
  "bbox": [],
  "geometry": {"coordinates":[-117.4167,38.7333],"type":"Point"}
}