{
  "id": 7564848,
  "type": "Feature",
  "properties": {
    "tgn:hierarchy":[
        "tgn:7564848",
        "tgn:1000004",
        "tgn:7000198",
        "tgn:7016722",
        "tgn:7029392"
    ],
    "tgn:id":7564848,
    "tgn:name:en":"Hara\u012bpur",
    "tgn:placetype":[
        "aat:300008347"
    ]
},
  "bbox": [],
  "geometry": {"coordinates":[79.696416,26.899768],"type":"Point"}
}