{
  "id": 7590809,
  "type": "Feature",
  "properties": {
    "tgn:hierarchy":[
        "tgn:7590809",
        "tgn:1000004",
        "tgn:7000198",
        "tgn:7000799",
        "tgn:7029392"
    ],
    "tgn:id":7590809,
    "tgn:name:en":"Khalka Bh\u0101rda",
    "tgn:placetype":[
        "aat:300008347"
    ]
},
  "bbox": [],
  "geometry": {"coordinates":[74.720702,32.917313],"type":"Point"}
}