{
  "id": 7397575,
  "type": "Feature",
  "properties": {
    "tgn:hierarchy":[
        "tgn:7397575",
        "tgn:1000001",
        "tgn:7005597",
        "tgn:7005560",
        "tgn:7029392"
    ],
    "tgn:id":7397575,
    "tgn:name":"Santa Gertrudis, Arroyo",
    "tgn:placetype":[
        "aat:300266554",
        "aat:300008699"
    ]
},
  "bbox": [],
  "geometry": {"coordinates":[-98.716667,26.166667],"type":"Point"}
}