{
  "id": 7562590,
  "type": "Feature",
  "properties": {
    "tgn:hierarchy":[
        "tgn:7562590",
        "tgn:1000004",
        "tgn:7000198",
        "tgn:7016722",
        "tgn:7029392"
    ],
    "tgn:id":7562590,
    "tgn:name:en":"Anandpur",
    "tgn:placetype":[
        "aat:300008347"
    ]
},
  "bbox": [],
  "geometry": {"coordinates":[79.396527,27.839623],"type":"Point"}
}