{
  "id": 7418580,
  "type": "Feature",
  "properties": {
    "tgn:hierarchy":[
        "tgn:7418580",
        "tgn:7005579",
        "tgn:1000001",
        "tgn:7005560",
        "tgn:7029392"
    ],
    "tgn:id":7418580,
    "tgn:name":"La Espantosa, Arroyo",
    "tgn:placetype":[
        "aat:300266554",
        "aat:300008699"
    ]
},
  "bbox": [],
  "geometry": {"coordinates":[-102.05,22.216667],"type":"Point"}
}