{
  "id": 1096119,
  "type": "Feature",
  "properties": {
    "tgn:hierarchy":[
        "tgn:1096119",
        "tgn:7000490",
        "tgn:1000006",
        "tgn:7001831",
        "tgn:7029392"
    ],
    "tgn:id":1096119,
    "tgn:name":"Arno Bay",
    "tgn:placetype":[
        "aat:300008347"
    ]
},
  "bbox": [],
  "geometry": {"coordinates":[136.5167,-33.8833],"type":"Point"}
}