{
  "id": 2050515,
  "type": "Feature",
  "properties": {
    "tgn:hierarchy":[
        "tgn:2050515",
        "tgn:1002165",
        "tgn:1000001",
        "tgn:2049495",
        "tgn:7012149",
        "tgn:7007517",
        "tgn:7029392"
    ],
    "tgn:id":2050515,
    "tgn:name":"Sagamore Beach",
    "tgn:placetype":[
        "aat:300000745"
    ]
},
  "bbox": [],
  "geometry": {"coordinates":[-70.5167,41.7833],"type":"Point"}
}