{
  "id": 7402439,
  "type": "Feature",
  "properties": {
    "tgn:hierarchy":[
        "tgn:7402439",
        "tgn:1000001",
        "tgn:1001937",
        "tgn:7005560",
        "tgn:7029392"
    ],
    "tgn:id":7402439,
    "tgn:name":"Pozo Pemex",
    "tgn:placetype":[
        "aat:300008347"
    ]
},
  "bbox": [],
  "geometry": {"coordinates":[-88.083333,19.183333],"type":"Point"}
}