<<<<<<< HEAD
{
  "id": 7359812,
  "type": "Feature",
  "properties": {
    "tgn:hierarchy":[
        "tgn:7359812",
        "tgn:1001853",
        "tgn:1000001",
        "tgn:7005560",
        "tgn:7029392"
    ],
    "tgn:id":7359812,
    "tgn:name":"Concepci\u00f3n del \u00c1lamo",
    "tgn:placetype":[
        "aat:300008347"
    ]
},
  "bbox": [],
  "geometry": {"coordinates":[-100.8,25.283333],"type":"Point"}
}
=======
{"geometry":{"type":"Point","coordinates":[-100.800000,25.283333]},"type":"Feature","properties":{"hierarchy":["tgn:7359812","tgn:1001853","tgn:1000001","tgn:7005560","tgn:7029392"],"placetype":["aat:300008347"],"id":7359812,"name:xx":"Concepci\u00f3n del \u00c1lamo"}}
>>>>>>> 03f74aca74312dbeaf24d7e61306dd6a786dc3d0
