{
  "id": 2654809,
  "type": "Feature",
  "properties": {
    "tgn:hierarchy":[
        "tgn:2654809",
        "tgn:2000090",
        "tgn:1000001",
        "tgn:7006451",
        "tgn:7012149",
        "tgn:7029392"
    ],
    "tgn:id":2654809,
    "tgn:name":"Shale Tank",
    "tgn:placetype":[
        "aat:300006191"
    ]
},
  "bbox": [],
  "geometry": {"coordinates":[-109.8167,33.5667],"type":"Point"}
}