{
  "id": 7575877,
  "type": "Feature",
  "properties": {
    "tgn:hierarchy":[
        "tgn:7575877",
        "tgn:1001828",
        "tgn:1000004",
        "tgn:7000198",
        "tgn:7029392"
    ],
    "tgn:id":7575877,
    "tgn:name:en":"Kondapur",
    "tgn:placetype":[
        "aat:300008347"
    ]
},
  "bbox": [],
  "geometry": {"coordinates":[79.683333,17.666667],"type":"Point"}
}