{
  "id": 2592815,
  "type": "Feature",
  "properties": {
    "tgn:hierarchy":[
        "tgn:2592815",
        "tgn:1000001",
        "tgn:7012149",
        "tgn:2001714",
        "tgn:7007708",
        "tgn:7029392"
    ],
    "tgn:id":2592815,
    "tgn:name":"Pope Reservoir",
    "tgn:placetype":[
        "aat:300006191"
    ]
},
  "bbox": [],
  "geometry": {"coordinates":[-121.3333,42.05],"type":"Point"}
}