{
  "id": 2460957,
  "type": "Feature",
  "properties": {
    "tgn:hierarchy":[
        "tgn:2460957",
        "tgn:1000001",
        "tgn:7014423",
        "tgn:7012149",
        "tgn:7007517",
        "tgn:7029392"
    ],
    "tgn:id":2460957,
    "tgn:name":"Little Smelt Pond",
    "tgn:placetype":[
        "aat:300008680"
    ]
},
  "bbox": [],
  "geometry": {"coordinates":[-70.7167,41.95],"type":"Point"}
}