<<<<<<< HEAD
{
  "id": 2152894,
  "type": "Feature",
  "properties": {
    "tgn:hierarchy":[
        "tgn:2152894",
        "tgn:1000001",
        "tgn:7016172",
        "tgn:7012149",
        "tgn:2000124",
        "tgn:7029392"
    ],
    "tgn:id":2152894,
    "tgn:name":"Beach Branch",
    "tgn:placetype":[
        "aat:300008699"
    ]
},
  "bbox": [],
  "geometry": {"coordinates":[-92.8333,34.05],"type":"Point"}
}
=======
{"geometry":{"type":"Point","coordinates":[-92.833300,34.050000]},"type":"Feature","properties":{"hierarchy":["tgn:2152894","tgn:1000001","tgn:7016172","tgn:7012149","tgn:2000124","tgn:7029392"],"placetype":["aat:300008699"],"id":2152894,"name:xx":"Beach Branch"}}
>>>>>>> 03f74aca74312dbeaf24d7e61306dd6a786dc3d0
