{
  "id": 1027642,
  "type": "Feature",
  "properties": {
    "tgn:hierarchy":[
        "tgn:1027642",
        "tgn:7593913",
        "tgn:1000003",
        "tgn:1001780",
        "tgn:7029392"
    ],
    "tgn:id":1027642,
    "tgn:name":"Vojtanov",
    "tgn:placetype":[
        "aat:300008347"
    ]
},
  "bbox": [],
  "geometry": {"coordinates":[12.3167,50.1667],"type":"Point"}
}