{
  "id": 7377855,
  "type": "Feature",
  "properties": {
    "tgn:hierarchy":[
        "tgn:7377855",
        "tgn:1001835",
        "tgn:1000001",
        "tgn:7005560",
        "tgn:7029392"
    ],
    "tgn:id":7377855,
    "tgn:name":"Las Palmas",
    "tgn:placetype":[
        "aat:300008347"
    ]
},
  "bbox": [],
  "geometry": {"coordinates":[-114.733333,29.65],"type":"Point"}
}