{
  "id": 7168173,
  "type": "Feature",
  "properties": {
    "tgn:hierarchy":[
        "tgn:7168173",
        "tgn:1000003",
        "tgn:7003685",
        "tgn:7000084",
        "tgn:7029392"
    ],
    "tgn:id":7168173,
    "tgn:name":"Heiliger Berg",
    "tgn:placetype":[
        "aat:300008777"
    ]
},
  "bbox": [],
  "geometry": {"coordinates":[14.083333,51.233333],"type":"Point"}
}