{
  "id": 1040201,
  "type": "Feature",
  "properties": {
    "tgn:hierarchy":[
        "tgn:1040201",
        "tgn:7003692",
        "tgn:1000003",
        "tgn:7000084",
        "tgn:7029392"
    ],
    "tgn:id":1040201,
    "tgn:name":"M\u00fchringen",
    "tgn:placetype":[
        "aat:300008347"
    ]
},
  "bbox": [],
  "geometry": {"coordinates":[8.766667,48.416667],"type":"Point"}
}