{
  "id": 2208089,
  "type": "Feature",
  "properties": {
    "tgn:hierarchy":[
        "tgn:2208089",
        "tgn:1000001",
        "tgn:7012149",
        "tgn:2000450",
        "tgn:7007248",
        "tgn:7029392"
    ],
    "tgn:id":2208089,
    "tgn:name":"Burkett Lake",
    "tgn:placetype":[
        "aat:300006191"
    ]
},
  "bbox": [],
  "geometry": {"coordinates":[-83.7667,31.5833],"type":"Point"}
}