<<<<<<< HEAD
{
  "id": 2762606,
  "type": "Feature",
  "properties": {
    "tgn:hierarchy":[
        "tgn:2762606",
        "tgn:1000001",
        "tgn:7012149",
        "tgn:2000349",
        "tgn:7007248",
        "tgn:7029392"
    ],
    "tgn:id":2762606,
    "tgn:name":"Westbrook Lake",
    "tgn:placetype":[
        "aat:300006191"
    ]
},
  "bbox": [],
  "geometry": {"coordinates":[-84.25,34.2333],"type":"Point"}
}
=======
{"geometry":{"type":"Point","coordinates":[-84.250000,34.233300]},"type":"Feature","properties":{"hierarchy":["tgn:2762606","tgn:1000001","tgn:7012149","tgn:2000349","tgn:7007248","tgn:7029392"],"placetype":["aat:300006191"],"id":2762606,"name:xx":"Westbrook Lake"}}
>>>>>>> 03f74aca74312dbeaf24d7e61306dd6a786dc3d0
