{
  "id": 2179672,
  "type": "Feature",
  "properties": {
    "tgn:hierarchy":[
        "tgn:2179672",
        "tgn:1000001",
        "tgn:7012149",
        "tgn:2002042",
        "tgn:7007826",
        "tgn:7029392"
    ],
    "tgn:id":2179672,
    "tgn:name":"Blanket Creek Watershed Reservoir Number Eighteen",
    "tgn:placetype":[
        "aat:300006191"
    ]
},
  "bbox": [],
  "geometry": {"coordinates":[-98.65,31.6333],"type":"Point"}
}