{
  "id": 2356206,
  "type": "Feature",
  "properties": {
    "tgn:hierarchy":[
        "tgn:2356206",
        "tgn:1000001",
        "tgn:7012149",
        "tgn:2000929",
        "tgn:7007515",
        "tgn:7029392"
    ],
    "tgn:id":2356206,
    "tgn:name":"Gooseberry Island",
    "tgn:placetype":[
        "aat:300008791"
    ]
},
  "bbox": [],
  "geometry": {"coordinates":[-69.85,43.7167],"type":"Point"}
}