{
  "id": 2046252,
  "type": "Feature",
  "properties": {
    "tgn:hierarchy":[
        "tgn:2046252",
        "tgn:1002338",
        "tgn:1000001",
        "tgn:7012149",
        "tgn:7007516",
        "tgn:7029392"
    ],
    "tgn:id":2046252,
    "tgn:name":"Beulah",
    "tgn:placetype":[
        "aat:300008347"
    ]
},
  "bbox": [],
  "geometry": {"coordinates":[-75.8833,38.6667],"type":"Point"}
}