{
  "id": 7530273,
  "type": "Feature",
  "properties": {
    "tgn:hierarchy":[
        "tgn:7530273",
        "tgn:7001242",
        "tgn:7016833",
        "tgn:1001335",
        "tgn:7029392"
    ],
    "tgn:id":7530273,
    "tgn:name:en":"Qaryat Raqm 59",
    "tgn:placetype":[
        "aat:300008347"
    ]
},
  "bbox": [],
  "geometry": {"coordinates":[30.972156,31.368662],"type":"Point"}
}