<<<<<<< HEAD
{
  "id": 2764001,
  "type": "Feature",
  "properties": {
    "tgn:hierarchy":[
        "tgn:2764001",
        "tgn:1000001",
        "tgn:7012149",
        "tgn:7007568",
        "tgn:7029392"
    ],
    "tgn:id":2764001,
    "tgn:name":"Wheeler Brook",
    "tgn:placetype":[
        "aat:300008699"
    ]
},
  "bbox": [],
  "geometry": {"coordinates":[-79.05,42.4667],"type":"Point"}
}
=======
{"geometry":{"type":"Point","coordinates":[-79.050000,42.466700]},"type":"Feature","properties":{"hierarchy":["tgn:2764001","tgn:1000001","tgn:7012149","tgn:7007568","tgn:7029392"],"placetype":["aat:300008699"],"id":2764001,"name:xx":"Wheeler Brook"}}
>>>>>>> 03f74aca74312dbeaf24d7e61306dd6a786dc3d0
