{
  "id": 2462243,
  "type": "Feature",
  "properties": {
    "tgn:hierarchy":[
        "tgn:2462243",
        "tgn:1000001",
        "tgn:1002329",
        "tgn:7012149",
        "tgn:7007706",
        "tgn:7029392"
    ],
    "tgn:id":2462243,
    "tgn:name":"Little Walnut Creek",
    "tgn:placetype":[
        "aat:300008706"
    ]
},
  "bbox": [],
  "geometry": {"coordinates":[-82.8167,40.3333],"type":"Point"}
}