{
  "id": 7121416,
  "type": "Feature",
  "properties": {
    "tgn:hierarchy":[
        "tgn:7121416",
        "tgn:7003669",
        "tgn:1000003",
        "tgn:7000084",
        "tgn:7029392"
    ],
    "tgn:id":7121416,
    "tgn:name":"Pfaffenbuch",
    "tgn:placetype":[
        "aat:300000206"
    ]
},
  "bbox": [],
  "geometry": {"coordinates":[12.65,48.283333],"type":"Point"}
}