{
  "id": 2786268,
  "type": "Feature",
  "properties": {
    "tgn:hierarchy":[
        "tgn:2786268",
        "tgn:1000001",
        "tgn:7012149",
        "tgn:1002626",
        "tgn:7007826",
        "tgn:7029392"
    ],
    "tgn:id":2786268,
    "tgn:name":"Youngs Creek",
    "tgn:placetype":[
        "aat:300008706"
    ]
},
  "bbox": [],
  "geometry": {"coordinates":[-95.75,31.0833],"type":"Point"}
}