{
  "id": 7589477,
  "type": "Feature",
  "properties": {
    "tgn:hierarchy":[
        "tgn:7589477",
        "tgn:1000004",
        "tgn:7000198",
        "tgn:7000799",
        "tgn:7029392"
    ],
    "tgn:id":7589477,
    "tgn:name:en":"Bhaira Laihr",
    "tgn:placetype":[
        "aat:300008347"
    ]
},
  "bbox": [],
  "geometry": {"coordinates":[74.9875,32.7625],"type":"Point"}
}