{
  "id": 7153759,
  "type": "Feature",
  "properties": {
    "tgn:hierarchy":[
        "tgn:7153759",
        "tgn:1000003",
        "tgn:7003688",
        "tgn:7000084",
        "tgn:7029392"
    ],
    "tgn:id":7153759,
    "tgn:name":"J\u00f6rsrade",
    "tgn:placetype":[
        "aat:300000206"
    ]
},
  "bbox": [],
  "geometry": {"coordinates":[10.166667,54.183333],"type":"Point"}
}