{
  "id": 7404748,
  "type": "Feature",
  "properties": {
    "tgn:hierarchy":[
        "tgn:7404748",
        "tgn:7016644",
        "tgn:1000001",
        "tgn:7005560",
        "tgn:7029392"
    ],
    "tgn:id":7404748,
    "tgn:name":"El Para\u00edso",
    "tgn:placetype":[
        "aat:300008347"
    ]
},
  "bbox": [],
  "geometry": {"coordinates":[-103.990278,18.875],"type":"Point"}
}