{
  "id": 7439752,
  "type": "Feature",
  "properties": {
    "tgn:hierarchy":[
        "tgn:7439752",
        "tgn:1000001",
        "tgn:7005591",
        "tgn:7005560",
        "tgn:7029392"
    ],
    "tgn:id":7439752,
    "tgn:name":"Santa Mar\u00eda Zacatepec",
    "tgn:placetype":[
        "aat:300008347"
    ]
},
  "bbox": [],
  "geometry": {"coordinates":[-97.983333,16.766667],"type":"Point"}
}