{
  "id": 2044766,
  "type": "Feature",
  "properties": {
    "tgn:hierarchy":[
        "tgn:2044766",
        "tgn:2000918",
        "tgn:1000001",
        "tgn:7012149",
        "tgn:7007515",
        "tgn:7029392"
    ],
    "tgn:id":2044766,
    "tgn:name":"East Poland",
    "tgn:placetype":[
        "aat:300008347"
    ]
},
  "bbox": [],
  "geometry": {"coordinates":[-70.3167,44.0667],"type":"Point"}
}