{
  "id": 7507717,
  "type": "Feature",
  "properties": {
    "tgn:hierarchy":[
        "tgn:7507717",
        "tgn:1008380",
        "tgn:1000226",
        "tgn:7016827",
        "tgn:1000006",
        "tgn:7029392"
    ],
    "tgn:id":7507717,
    "tgn:name:en":"Poarangi",
    "tgn:placetype":[
        "aat:300008699"
    ]
},
  "bbox": [],
  "geometry": {"coordinates":[174.75,-39.183333],"type":"Point"}
}