{
  "id": 1134779,
  "type": "Feature",
  "properties": {
    "tgn:hierarchy":[
        "tgn:1134779",
        "tgn:1001945",
        "tgn:1000047",
        "tgn:7002457",
        "tgn:1000002",
        "tgn:7029392"
    ],
    "tgn:id":1134779,
    "tgn:name":"Tanque Grande, Ribeir\u00e3o",
    "tgn:placetype":[
        "aat:300008706"
    ]
},
  "bbox": [],
  "geometry": {"coordinates":[-46.4667,-23.4167],"type":"Point"}
}