{
  "id": 7481414,
  "type": "Feature",
  "properties": {
    "tgn:hierarchy":[
        "tgn:7481414",
        "tgn:1000004",
        "tgn:7491221",
        "tgn:1000141",
        "tgn:7029392"
    ],
    "tgn:id":7481414,
    "tgn:name":"Xiangbi Yan",
    "tgn:placetype":[
        "aat:300011692"
    ]
},
  "bbox": [],
  "geometry": {"coordinates":[121.599444,22.016667],"type":"Point"}
}