<<<<<<< HEAD
{
  "id": 2333545,
  "type": "Feature",
  "properties": {
    "tgn:hierarchy":[
        "tgn:2333545",
        "tgn:1000001",
        "tgn:1002340",
        "tgn:7012149",
        "tgn:7007526",
        "tgn:7029392"
    ],
    "tgn:id":2333545,
    "tgn:name":"Folsom Peak",
    "tgn:placetype":[
        "aat:300008798"
    ]
},
  "bbox": [],
  "geometry": {"coordinates":[-119.9,38.9667],"type":"Point"}
}
=======
{"geometry":{"type":"Point","coordinates":[-119.900000,38.966700]},"type":"Feature","properties":{"hierarchy":["tgn:2333545","tgn:1000001","tgn:1002340","tgn:7012149","tgn:7007526","tgn:7029392"],"placetype":["aat:300008798"],"id":2333545,"name:xx":"Folsom Peak"}}
>>>>>>> 03f74aca74312dbeaf24d7e61306dd6a786dc3d0
