{
  "id": 2149656,
  "type": "Feature",
  "properties": {
    "tgn:hierarchy":[
        "tgn:2149656",
        "tgn:1000001",
        "tgn:7012149",
        "tgn:2001950",
        "tgn:7007826",
        "tgn:7029392"
    ],
    "tgn:id":2149656,
    "tgn:name":"Barroom Bay",
    "tgn:placetype":[
        "aat:300132316"
    ]
},
  "bbox": [],
  "geometry": {"coordinates":[-96.4167,28.4167],"type":"Point"}
}