{
  "id": 2071863,
  "type": "Feature",
  "properties": {
    "tgn:hierarchy":[
        "tgn:2071863",
        "tgn:1000001",
        "tgn:7012149",
        "tgn:1002758",
        "tgn:7007568",
        "tgn:7029392"
    ],
    "tgn:id":2071863,
    "tgn:name":"Redfield",
    "tgn:placetype":[
        "aat:300008347"
    ]
},
  "bbox": [],
  "geometry": {"coordinates":[-75.8167,43.5167],"type":"Point"}
}