{
  "id": 2629273,
  "type": "Feature",
  "properties": {
    "tgn:hierarchy":[
        "tgn:2629273",
        "tgn:7002659",
        "tgn:1000001",
        "tgn:7012149",
        "tgn:2000035",
        "tgn:7029392"
    ],
    "tgn:id":2629273,
    "tgn:name":"Roseberry",
    "tgn:placetype":[
        "aat:300008347"
    ]
},
  "bbox": [],
  "geometry": {"coordinates":[-86.0167,34.6333],"type":"Point"}
}