{
  "id": 2493135,
  "type": "Feature",
  "properties": {
    "tgn:hierarchy":[
        "tgn:2493135",
        "tgn:7002659",
        "tgn:1000001",
        "tgn:7012149",
        "tgn:2000022",
        "tgn:7029392"
    ],
    "tgn:id":2493135,
    "tgn:name":"Marley Millpond",
    "tgn:placetype":[
        "aat:300006191"
    ]
},
  "bbox": [],
  "geometry": {"coordinates":[-85.6833,31.4833],"type":"Point"}
}