{
  "id": 2329205,
  "type": "Feature",
  "properties": {
    "tgn:hierarchy":[
        "tgn:2329205",
        "tgn:1000001",
        "tgn:7012149",
        "tgn:2000217",
        "tgn:7007158",
        "tgn:7029392"
    ],
    "tgn:id":2329205,
    "tgn:name":"Fitzpatrick Reservoir",
    "tgn:placetype":[
        "aat:300006191"
    ]
},
  "bbox": [],
  "geometry": {"coordinates":[-107.45,38.35],"type":"Point"}
}