{
  "id": 2009919,
  "type": "Feature",
  "properties": {
    "tgn:hierarchy":[
        "tgn:2009919",
        "tgn:1002138",
        "tgn:1000001",
        "tgn:7012149",
        "tgn:7007157",
        "tgn:7029392"
    ],
    "tgn:id":2009919,
    "tgn:name":"Albany",
    "tgn:placetype":[
        "aat:300008347"
    ]
},
  "bbox": [],
  "geometry": {"coordinates":[-122.2833,37.8833],"type":"Point"}
}