{
  "id": 7509708,
  "type": "Feature",
  "properties": {
    "tgn:hierarchy":[
        "tgn:7509708",
        "tgn:1009227",
        "tgn:1000226",
        "tgn:7520095",
        "tgn:1000006",
        "tgn:7029392"
    ],
    "tgn:id":7509708,
    "tgn:name:en":"Sunday Creek",
    "tgn:placetype":[
        "aat:300008699"
    ]
},
  "bbox": [],
  "geometry": {"coordinates":[172.883333,-41.283333],"type":"Point"}
}