{
  "id": 2765863,
  "type": "Feature",
  "properties": {
    "tgn:hierarchy":[
        "tgn:2765863",
        "tgn:1000001",
        "tgn:2001435",
        "tgn:7012149",
        "tgn:7007566",
        "tgn:7029392"
    ],
    "tgn:id":2765863,
    "tgn:name":"White Gap Tank",
    "tgn:placetype":[
        "aat:300006191"
    ]
},
  "bbox": [],
  "geometry": {"coordinates":[-107.1667,32.5167],"type":"Point"}
}