{
  "id": 2601348,
  "type": "Feature",
  "properties": {
    "tgn:hierarchy":[
        "tgn:2601348",
        "tgn:1000001",
        "tgn:7012149",
        "tgn:2001503",
        "tgn:7007709",
        "tgn:7029392"
    ],
    "tgn:id":2601348,
    "tgn:name":"Purchase Knob",
    "tgn:placetype":[
        "aat:300008798"
    ]
},
  "bbox": [],
  "geometry": {"coordinates":[-83.05,35.5833],"type":"Point"}
}