{
  "id": 7379838,
  "type": "Feature",
  "properties": {
    "tgn:hierarchy":[
        "tgn:7379838",
        "tgn:1000001",
        "tgn:7005593",
        "tgn:7005560",
        "tgn:7029392"
    ],
    "tgn:id":7379838,
    "tgn:name":"Los Encinos Bernal",
    "tgn:placetype":[
        "aat:300008347"
    ]
},
  "bbox": [],
  "geometry": {"coordinates":[-99.883333,20.716667],"type":"Point"}
}