{
  "id": 2539894,
  "type": "Feature",
  "properties": {
    "tgn:hierarchy":[
        "tgn:2539894",
        "tgn:1000001",
        "tgn:7012149",
        "tgn:7007157",
        "tgn:2000189",
        "tgn:7029392"
    ],
    "tgn:id":2539894,
    "tgn:name":"New York Gulch",
    "tgn:placetype":[
        "aat:300008761"
    ]
},
  "bbox": [],
  "geometry": {"coordinates":[-122.8333,41.6833],"type":"Point"}
}