{
  "id": 2676204,
  "type": "Feature",
  "properties": {
    "tgn:hierarchy":[
        "tgn:2676204",
        "tgn:2000919",
        "tgn:1000001",
        "tgn:7012149",
        "tgn:7007515",
        "tgn:7029392"
    ],
    "tgn:id":2676204,
    "tgn:name":"Soule Brook",
    "tgn:placetype":[
        "aat:300008699"
    ]
},
  "bbox": [],
  "geometry": {"coordinates":[-68.1833,46.1667],"type":"Point"}
}