{
  "id": 2209861,
  "type": "Feature",
  "properties": {
    "tgn:hierarchy":[
        "tgn:2209861",
        "tgn:1000001",
        "tgn:7012149",
        "tgn:1002392",
        "tgn:7007157",
        "tgn:7029392"
    ],
    "tgn:id":2209861,
    "tgn:name":"Burrough Valley",
    "tgn:placetype":[
        "aat:300386845"
    ]
},
  "bbox": [],
  "geometry": {"coordinates":[-119.35,36.9667],"type":"Point"}
}