{
  "id": 7300423,
  "type": "Feature",
  "properties": {
    "tgn:hierarchy":[
        "tgn:7300423",
        "tgn:7002815",
        "tgn:1000003",
        "tgn:7002793",
        "tgn:1000095",
        "tgn:7029392"
    ],
    "tgn:id":7300423,
    "tgn:name":"Torrecilla, Barranco de la",
    "tgn:placetype":[
        "aat:300266554",
        "aat:300008699"
    ]
},
  "bbox": [],
  "geometry": {"coordinates":[-0.466667,39.85],"type":"Point"}
}