{
  "id": 7250427,
  "type": "Feature",
  "properties": {
    "tgn:hierarchy":[
        "tgn:7250427",
        "tgn:7003457",
        "tgn:1000003",
        "tgn:1000063",
        "tgn:7018236",
        "tgn:7029392"
    ],
    "tgn:id":7250427,
    "tgn:name":"Parkbosbeek",
    "tgn:placetype":[
        "aat:300008699"
    ]
},
  "bbox": [],
  "geometry": {"coordinates":[3.84106,50.796939],"type":"Point"}
}