{
  "id": 7098987,
  "type": "Feature",
  "properties": {
    "tgn:hierarchy":[
        "tgn:7098987",
        "tgn:1000003",
        "tgn:7003688",
        "tgn:7000084",
        "tgn:7029392"
    ],
    "tgn:id":7098987,
    "tgn:name":"Selkweg",
    "tgn:placetype":[
        "aat:300000206"
    ]
},
  "bbox": [],
  "geometry": {"coordinates":[9.516667,53.75],"type":"Point"}
}