{
  "id": 2448779,
  "type": "Feature",
  "properties": {
    "tgn:hierarchy":[
        "tgn:2448779",
        "tgn:1000001",
        "tgn:7012149",
        "tgn:2002344",
        "tgn:7007922",
        "tgn:7029392"
    ],
    "tgn:id":2448779,
    "tgn:name":"Lima",
    "tgn:placetype":[
        "aat:300008347"
    ]
},
  "bbox": [],
  "geometry": {"coordinates":[-91.8667,44.6333],"type":"Point"}
}