{
  "id": 2519416,
  "type": "Feature",
  "properties": {
    "tgn:hierarchy":[
        "tgn:2519416",
        "tgn:1000001",
        "tgn:7012149",
        "tgn:7007157",
        "tgn:2000188",
        "tgn:7029392"
    ],
    "tgn:id":2519416,
    "tgn:name":"Modesty Gulch",
    "tgn:placetype":[
        "aat:300008761"
    ]
},
  "bbox": [],
  "geometry": {"coordinates":[-122.5833,40.6667],"type":"Point"}
}