{
  "id": 2752565,
  "type": "Feature",
  "properties": {
    "tgn:hierarchy":[
        "tgn:2752565",
        "tgn:1000001",
        "tgn:2001734",
        "tgn:7012149",
        "tgn:7007712",
        "tgn:7029392"
    ],
    "tgn:id":2752565,
    "tgn:name":"Washo Reserve",
    "tgn:placetype":[
        "aat:300008905"
    ]
},
  "bbox": [],
  "geometry": {"coordinates":[-79.3667,33.1333],"type":"Point"}
}