{
  "id": 7442785,
  "type": "Feature",
  "properties": {
    "tgn:hierarchy":[
        "tgn:7442785",
        "tgn:7002445",
        "tgn:7019021",
        "tgn:1000003",
        "tgn:7008591",
        "tgn:7029392"
    ],
    "tgn:id":7442785,
    "tgn:name:en":"Timsbury",
    "tgn:placetype":[
        "aat:300008347"
    ]
},
  "bbox": [],
  "geometry": {"coordinates":[-2.479167,51.324444],"type":"Point"}
}