{
  "id": 2521829,
  "type": "Feature",
  "properties": {
    "tgn:hierarchy":[
        "tgn:2521829",
        "tgn:1000001",
        "tgn:7012149",
        "tgn:7029392"
    ],
    "tgn:id":2521829,
    "tgn:name":"Monument Peak",
    "tgn:placetype":[
        "aat:300008798"
    ]
},
  "bbox": [],
  "geometry": {"coordinates":[-113.6833,45.25],"type":"Point"}
}