{
  "id": 2251404,
  "type": "Feature",
  "properties": {
    "tgn:hierarchy":[
        "tgn:2251404",
        "tgn:1000001",
        "tgn:7006451",
        "tgn:2000091",
        "tgn:7012149",
        "tgn:7029392"
    ],
    "tgn:id":2251404,
    "tgn:name":"Comet Spring, The",
    "tgn:placetype":[
        "aat:300008697"
    ]
},
  "bbox": [],
  "geometry": {"coordinates":[-109.3667,32.0667],"type":"Point"}
}