<<<<<<< HEAD
{
  "id": 2251404,
  "type": "Feature",
  "properties": {
    "tgn:hierarchy":[
        "tgn:2251404",
        "tgn:1000001",
        "tgn:7006451",
        "tgn:2000091",
        "tgn:7012149",
        "tgn:7029392"
    ],
    "tgn:id":2251404,
    "tgn:name":"Comet Spring, The",
    "tgn:placetype":[
        "aat:300008697"
    ]
},
  "bbox": [],
  "geometry": {"coordinates":[-109.3667,32.0667],"type":"Point"}
}
=======
{"geometry":{"type":"Point","coordinates":[-109.366700,32.066700]},"type":"Feature","properties":{"hierarchy":["tgn:2251404","tgn:1000001","tgn:7006451","tgn:2000091","tgn:7012149","tgn:7029392"],"placetype":["aat:300008697"],"id":2251404,"name:xx":"Comet Spring, The"}}
>>>>>>> 03f74aca74312dbeaf24d7e61306dd6a786dc3d0
