{
  "id": 2522847,
  "type": "Feature",
  "properties": {
    "tgn:hierarchy":[
        "tgn:2522847",
        "tgn:1000001",
        "tgn:2002243",
        "tgn:7012149",
        "tgn:7007920",
        "tgn:7029392"
    ],
    "tgn:id":2522847,
    "tgn:name":"Moore Draw",
    "tgn:placetype":[
        "aat:300008761"
    ]
},
  "bbox": [],
  "geometry": {"coordinates":[-118.4167,47.85],"type":"Point"}
}