{
  "id": 2549264,
  "type": "Feature",
  "properties": {
    "tgn:hierarchy":[
        "tgn:2549264",
        "tgn:1000001",
        "tgn:7013686",
        "tgn:7012149",
        "tgn:7007517",
        "tgn:7029392"
    ],
    "tgn:id":2549264,
    "tgn:name":"North Rockhouse Mountain",
    "tgn:placetype":[
        "aat:300008798"
    ]
},
  "bbox": [],
  "geometry": {"coordinates":[-72.85,42.2333],"type":"Point"}
}