{
  "id": 7534254,
  "type": "Feature",
  "properties": {
    "tgn:hierarchy":[
        "tgn:7534254",
        "tgn:7001242",
        "tgn:7016833",
        "tgn:7001312",
        "tgn:7029392"
    ],
    "tgn:id":7534254,
    "tgn:name:en":"Kafr Shubr\u0101 al Yaman",
    "tgn:placetype":[
        "aat:300008347"
    ]
},
  "bbox": [],
  "geometry": {"coordinates":[31.212618,30.827877],"type":"Point"}
}