{
  "id": 2136253,
  "type": "Feature",
  "properties": {
    "tgn:hierarchy":[
        "tgn:2136253",
        "tgn:1000001",
        "tgn:7012149",
        "tgn:1002785",
        "tgn:7007920",
        "tgn:7029392"
    ],
    "tgn:id":2136253,
    "tgn:name":"Ararat, Mount",
    "tgn:placetype":[
        "aat:300008798"
    ]
},
  "bbox": [],
  "geometry": {"coordinates":[-121.85,46.7833],"type":"Point"}
}