<<<<<<< HEAD
{
  "id": 2334210,
  "type": "Feature",
  "properties": {
    "tgn:hierarchy":[
        "tgn:2334210",
        "tgn:1000001",
        "tgn:7012149",
        "tgn:2000964",
        "tgn:7007520",
        "tgn:7029392"
    ],
    "tgn:id":2334210,
    "tgn:name":"Forest Bay",
    "tgn:placetype":[
        "aat:300132316"
    ]
},
  "bbox": [],
  "geometry": {"coordinates":[-82.6833,43.9],"type":"Point"}
}
=======
{"geometry":{"type":"Point","coordinates":[-82.683300,43.900000]},"type":"Feature","properties":{"hierarchy":["tgn:2334210","tgn:1000001","tgn:7012149","tgn:2000964","tgn:7007520","tgn:7029392"],"placetype":["aat:300132316"],"id":2334210,"name:xx":"Forest Bay"}}
>>>>>>> 03f74aca74312dbeaf24d7e61306dd6a786dc3d0
