{
  "id": 7194071,
  "type": "Feature",
  "properties": {
    "tgn:hierarchy":[
        "tgn:7194071",
        "tgn:1000003",
        "tgn:7003677",
        "tgn:7000084",
        "tgn:7029392"
    ],
    "tgn:id":7194071,
    "tgn:name":"Feld-Berg",
    "tgn:placetype":[
        "aat:300008777"
    ]
},
  "bbox": [],
  "geometry": {"coordinates":[8.633333,51.416667],"type":"Point"}
}