<<<<<<< HEAD
{
  "id": 7111054,
  "type": "Feature",
  "properties": {
    "tgn:hierarchy":[
        "tgn:7111054",
        "tgn:7003669",
        "tgn:1000003",
        "tgn:7000084",
        "tgn:7029392"
    ],
    "tgn:id":7111054,
    "tgn:name":"Renfting",
    "tgn:placetype":[
        "aat:300008777"
    ]
},
  "bbox": [],
  "geometry": {"coordinates":[13.7,48.65],"type":"Point"}
}
=======
{"geometry":{"type":"Point","coordinates":[13.700000,48.650000]},"type":"Feature","properties":{"hierarchy":["tgn:7111054","tgn:7003669","tgn:1000003","tgn:7000084","tgn:7029392"],"placetype":["aat:300008777"],"id":7111054,"name:xx":"Renfting"}}
>>>>>>> 03f74aca74312dbeaf24d7e61306dd6a786dc3d0
