{
  "id": 7301191,
  "type": "Feature",
  "properties": {
    "tgn:hierarchy":[
        "tgn:7301191",
        "tgn:7002825",
        "tgn:7016622",
        "tgn:1000003",
        "tgn:1000095",
        "tgn:7029392"
    ],
    "tgn:id":7301191,
    "tgn:name":"Monta\u00f1a Alta",
    "tgn:placetype":[
        "aat:300008347"
    ]
},
  "bbox": [],
  "geometry": {"coordinates":[-15.616667,28.083333],"type":"Point"}
}