{
  "id": 2576520,
  "type": "Feature",
  "properties": {
    "tgn:hierarchy":[
        "tgn:2576520",
        "tgn:1000001",
        "tgn:7012149",
        "tgn:2002078",
        "tgn:7007826",
        "tgn:7029392"
    ],
    "tgn:id":2576520,
    "tgn:name":"Perry Tank",
    "tgn:placetype":[
        "aat:300006191"
    ]
},
  "bbox": [],
  "geometry": {"coordinates":[-100.45,33.2833],"type":"Point"}
}