{
  "id": 2584450,
  "type": "Feature",
  "properties": {
    "tgn:hierarchy":[
        "tgn:2584450",
        "tgn:1000001",
        "tgn:1002539",
        "tgn:7012149",
        "tgn:7007516",
        "tgn:7029392"
    ],
    "tgn:id":2584450,
    "tgn:name":"Piney Grove",
    "tgn:placetype":[
        "aat:300008347"
    ]
},
  "bbox": [],
  "geometry": {"coordinates":[-76.0667,39.1667],"type":"Point"}
}