{
  "id": 2627914,
  "type": "Feature",
  "properties": {
    "tgn:hierarchy":[
        "tgn:2627914",
        "tgn:1000001",
        "tgn:7012149",
        "tgn:2002361",
        "tgn:7007922",
        "tgn:7029392"
    ],
    "tgn:id":2627914,
    "tgn:name":"Roland Lake",
    "tgn:placetype":[
        "aat:300008680"
    ]
},
  "bbox": [],
  "geometry": {"coordinates":[-88.9833,44.5167],"type":"Point"}
}