{
  "id": 2232271,
  "type": "Feature",
  "properties": {
    "tgn:hierarchy":[
        "tgn:2232271",
        "tgn:1000001",
        "tgn:7006451",
        "tgn:7012149",
        "tgn:2000097",
        "tgn:7029392"
    ],
    "tgn:id":2232271,
    "tgn:name":"Chandler Meadows Mobile Home Park",
    "tgn:placetype":[
        "aat:300008347"
    ]
},
  "bbox": [],
  "geometry": {"coordinates":[-111.8333,33.3167],"type":"Point"}
}