{
  "id": 2147311,
  "type": "Feature",
  "properties": {
    "tgn:hierarchy":[
        "tgn:2147311",
        "tgn:7006450",
        "tgn:1000001",
        "tgn:7012149",
        "tgn:2124002",
        "tgn:7029392"
    ],
    "tgn:id":2147311,
    "tgn:name":"Baranof Lake",
    "tgn:placetype":[
        "aat:300008680"
    ]
},
  "bbox": [],
  "geometry": {"coordinates":[-134.85,57.0833],"type":"Point"}
}