{
  "id": 2463641,
  "type": "Feature",
  "properties": {
    "tgn:hierarchy":[
        "tgn:2463641",
        "tgn:1000001",
        "tgn:7012149",
        "tgn:2002371",
        "tgn:7007923",
        "tgn:7029392"
    ],
    "tgn:id":2463641,
    "tgn:name":"Loch Leven",
    "tgn:placetype":[
        "aat:300008680"
    ]
},
  "bbox": [],
  "geometry": {"coordinates":[-109.2167,42.8333],"type":"Point"}
}