{
  "id": 2036802,
  "type": "Feature",
  "properties": {
    "tgn:hierarchy":[
        "tgn:2036802",
        "tgn:1000001",
        "tgn:2000674",
        "tgn:7012149",
        "tgn:7007254",
        "tgn:7029392"
    ],
    "tgn:id":2036802,
    "tgn:name":"Miltonvale",
    "tgn:placetype":[
        "aat:300008347"
    ]
},
  "bbox": [],
  "geometry": {"coordinates":[-97.4333,39.3333],"type":"Point"}
}