<<<<<<< HEAD
{
  "id": 2331151,
  "type": "Feature",
  "properties": {
    "tgn:hierarchy":[
        "tgn:2331151",
        "tgn:1000001",
        "tgn:7012149",
        "tgn:2002113",
        "tgn:7007827",
        "tgn:7029392"
    ],
    "tgn:id":2331151,
    "tgn:name":"Flat Top",
    "tgn:placetype":[
        "aat:300008798"
    ]
},
  "bbox": [],
  "geometry": {"coordinates":[-111.7667,37.0167],"type":"Point"}
}
=======
{"geometry":{"type":"Point","coordinates":[-111.766700,37.016700]},"type":"Feature","properties":{"hierarchy":["tgn:2331151","tgn:1000001","tgn:7012149","tgn:2002113","tgn:7007827","tgn:7029392"],"placetype":["aat:300008798"],"id":2331151,"name:xx":"Flat Top"}}
>>>>>>> 03f74aca74312dbeaf24d7e61306dd6a786dc3d0
