{
  "id": 7536801,
  "type": "Feature",
  "properties": {
    "tgn:hierarchy":[
        "tgn:7536801",
        "tgn:7001242",
        "tgn:7016833",
        "tgn:7001312",
        "tgn:7029392"
    ],
    "tgn:id":7536801,
    "tgn:name:en":"Kunayyisat Damsh\u012bt",
    "tgn:placetype":[
        "aat:300008347"
    ]
},
  "bbox": [],
  "geometry": {"coordinates":[31.018978,30.889228],"type":"Point"}
}