{
  "id": 7496290,
  "type": "Feature",
  "properties": {
    "tgn:hierarchy":[
        "tgn:7496290",
        "tgn:1000004",
        "tgn:1000454",
        "tgn:1000141",
        "tgn:7029392"
    ],
    "tgn:id":7496290,
    "tgn:name":"Fushan Yihao Qiao",
    "tgn:placetype":[
        "aat:300007836"
    ]
},
  "bbox": [],
  "geometry": {"coordinates":[121.5034,24.780688],"type":"Point"}
}