{
  "id": 2740731,
  "type": "Feature",
  "properties": {
    "tgn:hierarchy":[
        "tgn:2740731",
        "tgn:7002659",
        "tgn:1000001",
        "tgn:7012149",
        "tgn:2000035",
        "tgn:7029392"
    ],
    "tgn:id":2740731,
    "tgn:name":"Upper Rainbow Cave",
    "tgn:placetype":[
        "aat:300008746"
    ]
},
  "bbox": [],
  "geometry": {"coordinates":[-85.9667,34.8333],"type":"Point"}
}