{
  "id": 2345633,
  "type": "Feature",
  "properties": {
    "tgn:hierarchy":[
        "tgn:2345633",
        "tgn:1000001",
        "tgn:7012149",
        "tgn:2002180",
        "tgn:7007919",
        "tgn:7029392"
    ],
    "tgn:id":2345633,
    "tgn:name":"Garrett Branch",
    "tgn:placetype":[
        "aat:300008699"
    ]
},
  "bbox": [],
  "geometry": {"coordinates":[-79.6333,36.7833],"type":"Point"}
}