{
  "id": 7566669,
  "type": "Feature",
  "properties": {
    "tgn:hierarchy":[
        "tgn:7566669",
        "tgn:1000004",
        "tgn:7000198",
        "tgn:7016722",
        "tgn:7029392"
    ],
    "tgn:id":7566669,
    "tgn:name:en":"Ghurraiya",
    "tgn:placetype":[
        "aat:300008347"
    ]
},
  "bbox": [],
  "geometry": {"coordinates":[79.056009,25.547191],"type":"Point"}
}