<<<<<<< HEAD
{
  "id": 7176536,
  "type": "Feature",
  "properties": {
    "tgn:hierarchy":[
        "tgn:7176536",
        "tgn:7003692",
        "tgn:1000003",
        "tgn:7000084",
        "tgn:7029392"
    ],
    "tgn:id":7176536,
    "tgn:name":"Haaberg",
    "tgn:placetype":[
        "aat:300008347"
    ]
},
  "bbox": [],
  "geometry": {"coordinates":[8.183333,48.683333],"type":"Point"}
}
=======
{"geometry":{"type":"Point","coordinates":[8.183333,48.683333]},"type":"Feature","properties":{"hierarchy":["tgn:7176536","tgn:7003692","tgn:1000003","tgn:7000084","tgn:7029392"],"placetype":["aat:300008347"],"id":7176536,"name:xx":"Haaberg"}}
>>>>>>> 03f74aca74312dbeaf24d7e61306dd6a786dc3d0
