{
  "id": 2442931,
  "type": "Feature",
  "properties": {
    "tgn:hierarchy":[
        "tgn:2442931",
        "tgn:1000001",
        "tgn:2000696",
        "tgn:7012149",
        "tgn:7007254",
        "tgn:7029392"
    ],
    "tgn:id":2442931,
    "tgn:name":"Kuntz Branch",
    "tgn:placetype":[
        "aat:300008699"
    ]
},
  "bbox": [],
  "geometry": {"coordinates":[-96.0667,37.75],"type":"Point"}
}