{
  "id": 7368089,
  "type": "Feature",
  "properties": {
    "tgn:hierarchy":[
        "tgn:7368089",
        "tgn:1000001",
        "tgn:1001937",
        "tgn:7005560",
        "tgn:7029392"
    ],
    "tgn:id":7368089,
    "tgn:name":"Iglesia, Boca",
    "tgn:placetype":[
        "aat:300185707"
    ]
},
  "bbox": [],
  "geometry": {"coordinates":[-86.966667,21.533333],"type":"Point"}
}