<<<<<<< HEAD
{
  "id": 7368089,
  "type": "Feature",
  "properties": {
    "tgn:hierarchy":[
        "tgn:7368089",
        "tgn:1000001",
        "tgn:1001937",
        "tgn:7005560",
        "tgn:7029392"
    ],
    "tgn:id":7368089,
    "tgn:name":"Iglesia, Boca",
    "tgn:placetype":[
        "aat:300185707"
    ]
},
  "bbox": [],
  "geometry": {"coordinates":[-86.966667,21.533333],"type":"Point"}
}
=======
{"geometry":{"type":"Point","coordinates":[-86.966667,21.533333]},"type":"Feature","properties":{"hierarchy":["tgn:7368089","tgn:1000001","tgn:1001937","tgn:7005560","tgn:7029392"],"placetype":["aat:300185707"],"id":7368089,"name:xx":"Iglesia, Boca"}}
>>>>>>> 03f74aca74312dbeaf24d7e61306dd6a786dc3d0
