{
  "id": 2331466,
  "type": "Feature",
  "properties": {
    "tgn:hierarchy":[
        "tgn:2331466",
        "tgn:2001468",
        "tgn:1000001",
        "tgn:7012149",
        "tgn:7007709",
        "tgn:7029392"
    ],
    "tgn:id":2331466,
    "tgn:name":"Flattop Creek",
    "tgn:placetype":[
        "aat:300008706"
    ]
},
  "bbox": [],
  "geometry": {"coordinates":[-81.85,36.1167],"type":"Point"}
}