{
  "id": 2192484,
  "type": "Feature",
  "properties": {
    "tgn:hierarchy":[
        "tgn:2192484",
        "tgn:1000001",
        "tgn:7012149",
        "tgn:2000354",
        "tgn:7007248",
        "tgn:7029392"
    ],
    "tgn:id":2192484,
    "tgn:name":"Brandy Point",
    "tgn:placetype":[
        "aat:300008850"
    ]
},
  "bbox": [],
  "geometry": {"coordinates":[-81.4833,31.1167],"type":"Point"}
}