{
  "id": 2573870,
  "type": "Feature",
  "properties": {
    "tgn:hierarchy":[
        "tgn:2573870",
        "tgn:7006450",
        "tgn:1000001",
        "tgn:2124012",
        "tgn:7012149",
        "tgn:7029392"
    ],
    "tgn:id":2573870,
    "tgn:name":"Pedmar, Mount",
    "tgn:placetype":[
        "aat:300008798"
    ]
},
  "bbox": [],
  "geometry": {"coordinates":[-154.8167,58.0333],"type":"Point"}
}