{
  "id": 1127389,
  "type": "Feature",
  "properties": {
    "tgn:hierarchy":[
        "tgn:1127389",
        "tgn:1000824",
        "tgn:7001242",
        "tgn:1000150",
        "tgn:7029392"
    ],
    "tgn:id":1127389,
    "tgn:name":"Motloutse",
    "tgn:placetype":[
        "aat:300008707"
    ]
},
  "bbox": [],
  "geometry": {"coordinates":[29.0167,-22.2333],"type":"Point"}
}