{
  "id": 2265247,
  "type": "Feature",
  "properties": {
    "tgn:hierarchy":[
        "tgn:2265247",
        "tgn:1000001",
        "tgn:7012149",
        "tgn:1002821",
        "tgn:7007568",
        "tgn:7029392"
    ],
    "tgn:id":2265247,
    "tgn:name":"Cranberry Vly Creek",
    "tgn:placetype":[
        "aat:300008706"
    ]
},
  "bbox": [],
  "geometry": {"coordinates":[-73.45,42.6667],"type":"Point"}
}