{
  "id": 2056300,
  "type": "Feature",
  "properties": {
    "tgn:hierarchy":[
        "tgn:2056300",
        "tgn:1000001",
        "tgn:7012149",
        "tgn:2001108",
        "tgn:7007522",
        "tgn:7029392"
    ],
    "tgn:id":2056300,
    "tgn:name":"Diamondhead",
    "tgn:placetype":[
        "aat:300008347"
    ]
},
  "bbox": [],
  "geometry": {"coordinates":[-89.35,30.3833],"type":"Point"}
}