{
  "id": 1026195,
  "type": "Feature",
  "properties": {
    "tgn:hierarchy":[
        "tgn:1026195",
        "tgn:7003025",
        "tgn:1000003",
        "tgn:1000062",
        "tgn:7029392"
    ],
    "tgn:id":1026195,
    "tgn:name":"W\u00f6rdern",
    "tgn:placetype":[
        "aat:300008347"
    ]
},
  "bbox": [],
  "geometry": {"coordinates":[16.2167,48.3333],"type":"Point"}
}