{
  "id": 7282331,
  "type": "Feature",
  "properties": {
    "tgn:hierarchy":[
        "tgn:7282331",
        "tgn:7016598",
        "tgn:1000049",
        "tgn:1000002",
        "tgn:7029392"
    ],
    "tgn:id":7282331,
    "tgn:name":"Profeta, Cerro del",
    "tgn:placetype":[
        "aat:300008795"
    ]
},
  "bbox": [],
  "geometry": {"coordinates":[-69.283333,-24.65],"type":"Point"}
}