{
  "id": 2320392,
  "type": "Feature",
  "properties": {
    "tgn:hierarchy":[
        "tgn:2320392",
        "tgn:7002659",
        "tgn:1000001",
        "tgn:7012149",
        "tgn:2000038",
        "tgn:7029392"
    ],
    "tgn:id":2320392,
    "tgn:name":"Evergreen Estates",
    "tgn:placetype":[
        "aat:300008347"
    ]
},
  "bbox": [],
  "geometry": {"coordinates":[-87.5833,34.8333],"type":"Point"}
}