{
  "id": 2777274,
  "type": "Feature",
  "properties": {
    "tgn:hierarchy":[
        "tgn:2777274",
        "tgn:1000001",
        "tgn:7012149",
        "tgn:2002155",
        "tgn:7007919",
        "tgn:7029392"
    ],
    "tgn:id":2777274,
    "tgn:name":"Winfrey",
    "tgn:placetype":[
        "aat:300008347"
    ]
},
  "bbox": [],
  "geometry": {"coordinates":[-77.9667,38.4333],"type":"Point"}
}