{
  "id": 2286766,
  "type": "Feature",
  "properties": {
    "tgn:hierarchy":[
        "tgn:2286766",
        "tgn:1000001",
        "tgn:7012149",
        "tgn:7007157",
        "tgn:2000187",
        "tgn:7029392"
    ],
    "tgn:id":2286766,
    "tgn:name":"Diamond Springs",
    "tgn:placetype":[
        "aat:300008697"
    ]
},
  "bbox": [],
  "geometry": {"coordinates":[-121.05,39.6167],"type":"Point"}
}