{
  "id": 1067176,
  "type": "Feature",
  "properties": {
    "tgn:hierarchy":[
        "tgn:1067176",
        "tgn:1000004",
        "tgn:7002079",
        "tgn:1000111",
        "tgn:7029392"
    ],
    "tgn:id":1067176,
    "tgn:name":"Chenglingji",
    "tgn:placetype":[
        "aat:300008347"
    ]
},
  "bbox": [],
  "geometry": {"coordinates":[113.15,29.4333],"type":"Point"}
}