{
  "id": 2267246,
  "type": "Feature",
  "properties": {
    "tgn:hierarchy":[
        "tgn:2267246",
        "tgn:1000001",
        "tgn:7012149",
        "tgn:2002190",
        "tgn:7007919",
        "tgn:7029392"
    ],
    "tgn:id":2267246,
    "tgn:name":"Crim Cave",
    "tgn:placetype":[
        "aat:300008746"
    ]
},
  "bbox": [],
  "geometry": {"coordinates":[-78.6833,38.6333],"type":"Point"}
}