{
  "id": 7074081,
  "type": "Feature",
  "properties": {
    "tgn:hierarchy":[
        "tgn:7074081",
        "tgn:1000003",
        "tgn:7003676",
        "tgn:7000084",
        "tgn:7029392"
    ],
    "tgn:id":7074081,
    "tgn:name":"S\u00fcd Edewecht",
    "tgn:placetype":[
        "aat:300008347"
    ]
},
  "bbox": [],
  "geometry": {"coordinates":[7.983333,53.116667],"type":"Point"}
}