{
  "id": 1011163,
  "type": "Feature",
  "properties": {
    "tgn:hierarchy":[
        "tgn:1011163",
        "tgn:7005416",
        "tgn:1000001",
        "tgn:7005388",
        "tgn:7029392"
    ],
    "tgn:id":1011163,
    "tgn:name":"Saman\u00e1, Cabo",
    "tgn:placetype":[
        "aat:300008850"
    ]
},
  "bbox": [],
  "geometry": {"coordinates":[-69.152,19.301],"type":"Point"}
}