{
  "id": 2387396,
  "type": "Feature",
  "properties": {
    "tgn:hierarchy":[
        "tgn:2387396",
        "tgn:1000001",
        "tgn:7012149",
        "tgn:1002818",
        "tgn:7007252",
        "tgn:7029392"
    ],
    "tgn:id":2387396,
    "tgn:name":"Heuss Ditch",
    "tgn:placetype":[
        "aat:300006075"
    ]
},
  "bbox": [],
  "geometry": {"coordinates":[-85.1167,40.2667],"type":"Point"}
}