{
  "id": 2644146,
  "type": "Feature",
  "properties": {
    "tgn:hierarchy":[
        "tgn:2644146",
        "tgn:1000001",
        "tgn:7012149",
        "tgn:7007157",
        "tgn:1002863",
        "tgn:7029392"
    ],
    "tgn:id":2644146,
    "tgn:name":"Santa Rosa Reef",
    "tgn:placetype":[
        "aat:300132348"
    ]
},
  "bbox": [],
  "geometry": {"coordinates":[-120.7833,35.15],"type":"Point"}
}