<<<<<<< HEAD
{
  "id": 7364571,
  "type": "Feature",
  "properties": {
    "tgn:hierarchy":[
        "tgn:7364571",
        "tgn:7005581",
        "tgn:1000001",
        "tgn:7005560",
        "tgn:7029392"
    ],
    "tgn:id":7364571,
    "tgn:name":"Fierro, Laguna",
    "tgn:placetype":[
        "aat:300008680"
    ]
},
  "bbox": [],
  "geometry": {"coordinates":[-107.85,30.4],"type":"Point"}
}
=======
{"geometry":{"type":"Point","coordinates":[-107.850000,30.400000]},"type":"Feature","properties":{"hierarchy":["tgn:7364571","tgn:7005581","tgn:1000001","tgn:7005560","tgn:7029392"],"placetype":["aat:300008680"],"id":7364571,"name:xx":"Fierro, Laguna"}}
>>>>>>> 03f74aca74312dbeaf24d7e61306dd6a786dc3d0
