{
  "id": 2446149,
  "type": "Feature",
  "properties": {
    "tgn:hierarchy":[
        "tgn:2446149",
        "tgn:1000001",
        "tgn:2002314",
        "tgn:7012149",
        "tgn:7007922",
        "tgn:7029392"
    ],
    "tgn:id":2446149,
    "tgn:name":"Levis Mound",
    "tgn:placetype":[
        "aat:300008798"
    ]
},
  "bbox": [],
  "geometry": {"coordinates":[-90.7167,44.4667],"type":"Point"}
}