{
  "id": 2321271,
  "type": "Feature",
  "properties": {
    "tgn:hierarchy":[
        "tgn:2321271",
        "tgn:1000001",
        "tgn:2000923",
        "tgn:7012149",
        "tgn:7007515",
        "tgn:7029392"
    ],
    "tgn:id":2321271,
    "tgn:name":"Fairbanks Pond",
    "tgn:placetype":[
        "aat:300008680"
    ]
},
  "bbox": [],
  "geometry": {"coordinates":[-69.8167,44.3833],"type":"Point"}
}