<<<<<<< HEAD
{
  "id": 7053039,
  "type": "Feature",
  "properties": {
    "tgn:hierarchy":[
        "tgn:7053039",
        "tgn:7003154",
        "tgn:1000003",
        "tgn:7003120",
        "tgn:1000080",
        "tgn:7029392"
    ],
    "tgn:id":7053039,
    "tgn:name":"Pattemouche",
    "tgn:placetype":[
        "aat:300008347"
    ]
},
  "bbox": [],
  "geometry": {"coordinates":[6.916667,44.983333],"type":"Point"}
}
=======
{"geometry":{"type":"Point","coordinates":[6.916667,44.983333]},"type":"Feature","properties":{"hierarchy":["tgn:7053039","tgn:7003154","tgn:1000003","tgn:7003120","tgn:1000080","tgn:7029392"],"placetype":["aat:300008347"],"id":7053039,"name:xx":"Pattemouche"}}
>>>>>>> 03f74aca74312dbeaf24d7e61306dd6a786dc3d0
