{
  "id": 1124701,
  "type": "Feature",
  "properties": {
    "tgn:hierarchy":[
        "tgn:1124701",
        "tgn:1000001",
        "tgn:2000863",
        "tgn:7012149",
        "tgn:7007256",
        "tgn:7029392"
    ],
    "tgn:id":1124701,
    "tgn:name":"Houston",
    "tgn:placetype":[
        "aat:300008707"
    ]
},
  "bbox": [],
  "geometry": {"coordinates":[-93.5833,30.35],"type":"Point"}
}