<<<<<<< HEAD
{
  "id": 7174708,
  "type": "Feature",
  "properties": {
    "tgn:hierarchy":[
        "tgn:7174708",
        "tgn:7000096",
        "tgn:1000003",
        "tgn:7000084",
        "tgn:7029392"
    ],
    "tgn:id":7174708,
    "tgn:name":"Grubenm\u00fchle",
    "tgn:placetype":[
        "aat:300008347"
    ]
},
  "bbox": [],
  "geometry": {"coordinates":[13.983333,52.15],"type":"Point"}
}
=======
{"geometry":{"type":"Point","coordinates":[13.983333,52.150000]},"type":"Feature","properties":{"hierarchy":["tgn:7174708","tgn:7000096","tgn:1000003","tgn:7000084","tgn:7029392"],"placetype":["aat:300008347"],"id":7174708,"name:xx":"Grubenm\u00fchle"}}
>>>>>>> 03f74aca74312dbeaf24d7e61306dd6a786dc3d0
