<<<<<<< HEAD
{
  "id": 2250708,
  "type": "Feature",
  "properties": {
    "tgn:hierarchy":[
        "tgn:2250708",
        "tgn:1000001",
        "tgn:2000326",
        "tgn:7012149",
        "tgn:7007248",
        "tgn:7029392"
    ],
    "tgn:id":2250708,
    "tgn:name":"Colquitt County Lake",
    "tgn:placetype":[
        "aat:300006191"
    ]
},
  "bbox": [],
  "geometry": {"coordinates":[-83.7333,31.1667],"type":"Point"}
}
=======
{"geometry":{"type":"Point","coordinates":[-83.733300,31.166700]},"type":"Feature","properties":{"hierarchy":["tgn:2250708","tgn:1000001","tgn:2000326","tgn:7012149","tgn:7007248","tgn:7029392"],"placetype":["aat:300006191"],"id":2250708,"name:xx":"Colquitt County Lake"}}
>>>>>>> 03f74aca74312dbeaf24d7e61306dd6a786dc3d0
