{
  "id": 7127500,
  "type": "Feature",
  "properties": {
    "tgn:hierarchy":[
        "tgn:7127500",
        "tgn:1000003",
        "tgn:7003685",
        "tgn:7000084",
        "tgn:7029392"
    ],
    "tgn:id":7127500,
    "tgn:name":"Obergruna",
    "tgn:placetype":[
        "aat:300008347"
    ]
},
  "bbox": [],
  "geometry": {"coordinates":[13.316667,51.016667],"type":"Point"}
}