{
  "id": 2666015,
  "type": "Feature",
  "properties": {
    "tgn:hierarchy":[
        "tgn:2666015",
        "tgn:1000001",
        "tgn:7012149",
        "tgn:2000494",
        "tgn:7007250",
        "tgn:7029392"
    ],
    "tgn:id":2666015,
    "tgn:name":"Sisters Lakes",
    "tgn:placetype":[
        "aat:300008680"
    ]
},
  "bbox": [],
  "geometry": {"coordinates":[-115.9833,45.0167],"type":"Point"}
}