{
  "id": 2417659,
  "type": "Feature",
  "properties": {
    "tgn:hierarchy":[
        "tgn:2417659",
        "tgn:1000001",
        "tgn:7012149",
        "tgn:7014128",
        "tgn:7007709",
        "tgn:7029392"
    ],
    "tgn:id":2417659,
    "tgn:name":"Jackson Creek",
    "tgn:placetype":[
        "aat:300008706"
    ]
},
  "bbox": [],
  "geometry": {"coordinates":[-78.7333,36.2333],"type":"Point"}
}