<<<<<<< HEAD
{
  "id": 7471683,
  "type": "Feature",
  "properties": {
    "tgn:hierarchy":[
        "tgn:7471683",
        "tgn:1000004",
        "tgn:7491221",
        "tgn:1000141",
        "tgn:7029392"
    ],
    "tgn:id":7471683,
    "tgn:name":"Xinxing",
    "tgn:placetype":[
        "aat:300008347"
    ]
},
  "bbox": [],
  "geometry": {"coordinates":[121.2075,23.106667],"type":"Point"}
}
=======
{"geometry":{"type":"Point","coordinates":[121.207500,23.106667]},"type":"Feature","properties":{"hierarchy":["tgn:7471683","tgn:1000004","tgn:7491221","tgn:1000141","tgn:7029392"],"placetype":["aat:300008347"],"id":7471683,"name:xx":"Xinxing"}}
>>>>>>> 03f74aca74312dbeaf24d7e61306dd6a786dc3d0
