{
  "id": 7156269,
  "type": "Feature",
  "properties": {
    "tgn:hierarchy":[
        "tgn:7156269",
        "tgn:1000003",
        "tgn:7003673",
        "tgn:7000084",
        "tgn:7029392"
    ],
    "tgn:id":7156269,
    "tgn:name":"Kleinflottbek",
    "tgn:placetype":[
        "aat:300008347"
    ]
},
  "bbox": [],
  "geometry": {"coordinates":[9.866667,53.55],"type":"Point"}
}