{
  "id": 2540856,
  "type": "Feature",
  "properties": {
    "tgn:hierarchy":[
        "tgn:2540856",
        "tgn:1000001",
        "tgn:7012149",
        "tgn:7007525",
        "tgn:7029392"
    ],
    "tgn:id":2540856,
    "tgn:name":"Nichol Lake",
    "tgn:placetype":[
        "aat:300008680"
    ]
},
  "bbox": [],
  "geometry": {"coordinates":[-99.2167,41.9833],"type":"Point"}
}