{
  "id": 2377578,
  "type": "Feature",
  "properties": {
    "tgn:hierarchy":[
        "tgn:2377578",
        "tgn:1000001",
        "tgn:7012149",
        "tgn:1002545",
        "tgn:7007157",
        "tgn:7029392"
    ],
    "tgn:id":2377578,
    "tgn:name":"Harper Peak",
    "tgn:placetype":[
        "aat:300008798"
    ]
},
  "bbox": [],
  "geometry": {"coordinates":[-118.4833,35.3667],"type":"Point"}
}