{
  "id": 2320508,
  "type": "Feature",
  "properties": {
    "tgn:hierarchy":[
        "tgn:2320508",
        "tgn:1000001",
        "tgn:7012149",
        "tgn:2001897",
        "tgn:7007825",
        "tgn:7029392"
    ],
    "tgn:id":2320508,
    "tgn:name":"Eves Cave",
    "tgn:placetype":[
        "aat:300008746"
    ]
},
  "bbox": [],
  "geometry": {"coordinates":[-84.7833,35.55],"type":"Point"}
}