{
  "id": 7516029,
  "type": "Feature",
  "properties": {
    "tgn:hierarchy":[
        "tgn:7516029",
        "tgn:1009227",
        "tgn:7001866",
        "tgn:1000226",
        "tgn:1000006",
        "tgn:7029392"
    ],
    "tgn:id":7516029,
    "tgn:name:en":"Motu-ariki",
    "tgn:placetype":[
        "aat:300008791"
    ]
},
  "bbox": [],
  "geometry": {"coordinates":[170.533333,-43.933333],"type":"Point"}
}