{
  "id": 2114339,
  "type": "Feature",
  "properties": {
    "tgn:hierarchy":[
        "tgn:2114339",
        "tgn:2002142",
        "tgn:1000001",
        "tgn:7012149",
        "tgn:7007919",
        "tgn:7029392"
    ],
    "tgn:id":2114339,
    "tgn:name":"Spring Hill",
    "tgn:placetype":[
        "aat:300008347"
    ]
},
  "bbox": [],
  "geometry": {"coordinates":[-79.05,38.25],"type":"Point"}
}