<<<<<<< HEAD
{
  "id": 7371254,
  "type": "Feature",
  "properties": {
    "tgn:hierarchy":[
        "tgn:7371254",
        "tgn:7005580",
        "tgn:1000001",
        "tgn:7005560",
        "tgn:7029392"
    ],
    "tgn:id":7371254,
    "tgn:name":"Idalia",
    "tgn:placetype":[
        "aat:300008347"
    ]
},
  "bbox": [],
  "geometry": {"coordinates":[-93.1,15.45],"type":"Point"}
}
=======
{"geometry":{"type":"Point","coordinates":[-93.100000,15.450000]},"type":"Feature","properties":{"hierarchy":["tgn:7371254","tgn:7005580","tgn:1000001","tgn:7005560","tgn:7029392"],"placetype":["aat:300008347"],"id":7371254,"name:xx":"Idalia"}}
>>>>>>> 03f74aca74312dbeaf24d7e61306dd6a786dc3d0
