{
  "id": 2582318,
  "type": "Feature",
  "properties": {
    "tgn:hierarchy":[
        "tgn:2582318",
        "tgn:1000001",
        "tgn:7012149",
        "tgn:2001066",
        "tgn:7007521",
        "tgn:7029392"
    ],
    "tgn:id":2582318,
    "tgn:name":"Pine Creek Ditch",
    "tgn:placetype":[
        "aat:300006075"
    ]
},
  "bbox": [],
  "geometry": {"coordinates":[-96.05,48.9833],"type":"Point"}
}