{
  "id": 1089434,
  "type": "Feature",
  "properties": {
    "tgn:hierarchy":[
        "tgn:1089434",
        "tgn:1001143",
        "tgn:7001242",
        "tgn:1000159",
        "tgn:7029392"
    ],
    "tgn:id":1089434,
    "tgn:name":"Nsontin",
    "tgn:placetype":[
        "aat:300008347"
    ]
},
  "bbox": [],
  "geometry": {"coordinates":[17.9333,-3.1167],"type":"Point"}
}