{
  "id": 2138112,
  "type": "Feature",
  "properties": {
    "tgn:hierarchy":[
        "tgn:2138112",
        "tgn:1000001",
        "tgn:7012149",
        "tgn:2001451",
        "tgn:7007566",
        "tgn:7029392"
    ],
    "tgn:id":2138112,
    "tgn:name":"Arroyo la Jara",
    "tgn:placetype":[
        "aat:300008699"
    ]
},
  "bbox": [],
  "geometry": {"coordinates":[-106.9833,35.45],"type":"Point"}
}