{
  "id": 7586024,
  "type": "Feature",
  "properties": {
    "tgn:hierarchy":[
        "tgn:7586024",
        "tgn:1000004",
        "tgn:7000198",
        "tgn:7000799",
        "tgn:7029392"
    ],
    "tgn:id":7586024,
    "tgn:name:en":"Gunipur",
    "tgn:placetype":[
        "aat:300008347"
    ]
},
  "bbox": [],
  "geometry": {"coordinates":[74.28051,34.415854],"type":"Point"}
}