{
  "id": 2515485,
  "type": "Feature",
  "properties": {
    "tgn:hierarchy":[
        "tgn:2515485",
        "tgn:1000001",
        "tgn:2001639",
        "tgn:7012149",
        "tgn:7007707",
        "tgn:7029392"
    ],
    "tgn:id":2515485,
    "tgn:name":"Mills Creek",
    "tgn:placetype":[
        "aat:300008706"
    ]
},
  "bbox": [],
  "geometry": {"coordinates":[-98.2167,34.3333],"type":"Point"}
}