{
  "id": 7567688,
  "type": "Feature",
  "properties": {
    "tgn:hierarchy":[
        "tgn:7567688",
        "tgn:1000004",
        "tgn:7000198",
        "tgn:7031786",
        "tgn:7029392"
    ],
    "tgn:id":7567688,
    "tgn:name:en":"Barsw\u0101r",
    "tgn:placetype":[
        "aat:300008347"
    ]
},
  "bbox": [],
  "geometry": {"coordinates":[78.691211,29.811026],"type":"Point"}
}