{
  "id": 7581974,
  "type": "Feature",
  "properties": {
    "tgn:hierarchy":[
        "tgn:7581974",
        "tgn:1000004",
        "tgn:7018318",
        "tgn:7000198",
        "tgn:7029392"
    ],
    "tgn:id":7581974,
    "tgn:name:en":"Torxem",
    "tgn:placetype":[
        "aat:300008347"
    ]
},
  "bbox": [],
  "geometry": {"coordinates":[73.85,15.783333],"type":"Point"}
}