{
  "id": 2683335,
  "type": "Feature",
  "properties": {
    "tgn:hierarchy":[
        "tgn:2683335",
        "tgn:1000001",
        "tgn:7012149",
        "tgn:2000892",
        "tgn:7007256",
        "tgn:7029392"
    ],
    "tgn:id":2683335,
    "tgn:name":"Sparks",
    "tgn:placetype":[
        "aat:300008347"
    ]
},
  "bbox": [],
  "geometry": {"coordinates":[-91.5167,30.4833],"type":"Point"}
}