{
  "id": 2034800,
  "type": "Feature",
  "properties": {
    "tgn:hierarchy":[
        "tgn:2034800",
        "tgn:1000001",
        "tgn:7012149",
        "tgn:2000611",
        "tgn:7007253",
        "tgn:7029392"
    ],
    "tgn:id":2034800,
    "tgn:name":"Four Corners",
    "tgn:placetype":[
        "aat:300008347",
        "aat:300387210"
    ]
},
  "bbox": [],
  "geometry": {"coordinates":[-91.75,41.0167],"type":"Point"}
}