{
  "id": 1042447,
  "type": "Feature",
  "properties": {
    "tgn:hierarchy":[
        "tgn:1042447",
        "tgn:1000003",
        "tgn:1000474",
        "tgn:7006278",
        "tgn:7029392"
    ],
    "tgn:id":1042447,
    "tgn:name":"S\u00e1rmell\u00e9k",
    "tgn:placetype":[
        "aat:300008347"
    ]
},
  "bbox": [],
  "geometry": {"coordinates":[17.1667,46.7167],"type":"Point"}
}