{
  "id": 2475649,
  "type": "Feature",
  "properties": {
    "tgn:hierarchy":[
        "tgn:2475649",
        "tgn:1000001",
        "tgn:2001417",
        "tgn:7012149",
        "tgn:7007526",
        "tgn:7029392"
    ],
    "tgn:id":2475649,
    "tgn:name":"Lucky Four Mine",
    "tgn:placetype":[
        "aat:300000390"
    ]
},
  "bbox": [],
  "geometry": {"coordinates":[-118.6167,38.7833],"type":"Point"}
}