{
  "id": 7230452,
  "type": "Feature",
  "properties": {
    "tgn:hierarchy":[
        "tgn:7230452",
        "tgn:4003773",
        "tgn:7001395",
        "tgn:1000003",
        "tgn:1000074",
        "tgn:7029392"
    ],
    "tgn:id":7230452,
    "tgn:name":"Kr\u00edon Ner\u00f3n",
    "tgn:placetype":[
        "aat:300008347"
    ]
},
  "bbox": [],
  "geometry": {"coordinates":[21.583333,38.633333],"type":"Point"}
}