{
  "id": 2676934,
  "type": "Feature",
  "properties": {
    "tgn:hierarchy":[
        "tgn:2676934",
        "tgn:1000001",
        "tgn:7012149",
        "tgn:1002679",
        "tgn:7007520",
        "tgn:7029392"
    ],
    "tgn:id":2676934,
    "tgn:name":"South Branch La Plaisance Creek",
    "tgn:placetype":[
        "aat:300008706"
    ]
},
  "bbox": [],
  "geometry": {"coordinates":[-83.4833,41.8833],"type":"Point"}
}