{
  "id": 2308557,
  "type": "Feature",
  "properties": {
    "tgn:hierarchy":[
        "tgn:2308557",
        "tgn:1000001",
        "tgn:7012149",
        "tgn:7029392"
    ],
    "tgn:id":2308557,
    "tgn:name":"East Mountain Canyon",
    "tgn:placetype":[
        "aat:300008761"
    ]
},
  "bbox": [],
  "geometry": {"coordinates":[-114.0333,37.9333],"type":"Point"}
}