{
  "id": 2312948,
  "type": "Feature",
  "properties": {
    "tgn:hierarchy":[
        "tgn:2312948",
        "tgn:7002659",
        "tgn:1000001",
        "tgn:7012149",
        "tgn:2000045",
        "tgn:7029392"
    ],
    "tgn:id":2312948,
    "tgn:name":"Elam Branch",
    "tgn:placetype":[
        "aat:300008699"
    ]
},
  "bbox": [],
  "geometry": {"coordinates":[-87.5333,32.2833],"type":"Point"}
}