<<<<<<< HEAD
{
  "id": 7476545,
  "type": "Feature",
  "properties": {
    "tgn:hierarchy":[
        "tgn:7476545",
        "tgn:1000004",
        "tgn:7004300",
        "tgn:1000141",
        "tgn:7029392"
    ],
    "tgn:id":7476545,
    "tgn:name":"Zhongwei Yugang",
    "tgn:placetype":[
        "aat:300008678"
    ]
},
  "bbox": [],
  "geometry": {"coordinates":[119.588585,23.574339],"type":"Point"}
}
=======
{"geometry":{"type":"Point","coordinates":[119.588585,23.574339]},"type":"Feature","properties":{"hierarchy":["tgn:7476545","tgn:1000004","tgn:7004300","tgn:1000141","tgn:7029392"],"placetype":["aat:300008678"],"id":7476545,"name:xx":"Zhongwei Yugang"}}
>>>>>>> 03f74aca74312dbeaf24d7e61306dd6a786dc3d0
