{
  "id": 2370257,
  "type": "Feature",
  "properties": {
    "tgn:hierarchy":[
        "tgn:2370257",
        "tgn:1000001",
        "tgn:2001410",
        "tgn:7012149",
        "tgn:7007526",
        "tgn:7029392"
    ],
    "tgn:id":2370257,
    "tgn:name":"Gypsum Cave",
    "tgn:placetype":[
        "aat:300000810",
        "aat:300048808",
        "aat:300008746"
    ]
},
  "bbox": [],
  "geometry": {"coordinates":[-114.8833,36.2167],"type":"Point"}
}