{
  "id": 1035310,
  "type": "Feature",
  "properties": {
    "tgn:hierarchy":[
        "tgn:1035310",
        "tgn:1000003",
        "tgn:7002877",
        "tgn:1000070",
        "tgn:7029392"
    ],
    "tgn:id":1035310,
    "tgn:name":"Saint-Dy\u00e9-sur-Loire",
    "tgn:placetype":[
        "aat:300008347"
    ]
},
  "bbox": [],
  "geometry": {"coordinates":[1.4833,47.65],"type":"Point"}
}