{
  "id": 2653056,
  "type": "Feature",
  "properties": {
    "tgn:hierarchy":[
        "tgn:2653056",
        "tgn:1000001",
        "tgn:7012149",
        "tgn:2000931",
        "tgn:7007515",
        "tgn:7029392"
    ],
    "tgn:id":2653056,
    "tgn:name":"Seven Hundred Acre Island",
    "tgn:placetype":[
        "aat:300008791"
    ]
},
  "bbox": [],
  "geometry": {"coordinates":[-68.95,44.25],"type":"Point"}
}