{
  "id": 7214447,
  "type": "Feature",
  "properties": {
    "tgn:hierarchy":[
        "tgn:7214447",
        "tgn:7003692",
        "tgn:1000003",
        "tgn:7000084",
        "tgn:7029392"
    ],
    "tgn:id":7214447,
    "tgn:name":"Haltepunkt Beutelsbach",
    "tgn:placetype":[
        "aat:300007783"
    ]
},
  "bbox": [],
  "geometry": {"coordinates":[9.383333,48.816667],"type":"Point"}
}