{
  "id": 7230120,
  "type": "Feature",
  "properties": {
    "tgn:hierarchy":[
        "tgn:7230120",
        "tgn:7002707",
        "tgn:7002705",
        "tgn:1000003",
        "tgn:1000074",
        "tgn:7029392"
    ],
    "tgn:id":7230120,
    "tgn:name":"Chrys\u00f3douli",
    "tgn:placetype":[
        "aat:300008347"
    ]
},
  "bbox": [],
  "geometry": {"coordinates":[20.368333,39.931389],"type":"Point"}
}