<<<<<<< HEAD
{
  "id": 7245630,
  "type": "Feature",
  "properties": {
    "tgn:hierarchy":[
        "tgn:7245630",
        "tgn:7007877",
        "tgn:1000003",
        "tgn:1000063",
        "tgn:4012014",
        "tgn:7029392"
    ],
    "tgn:id":7245630,
    "tgn:name":"Clo\u00eetre",
    "tgn:placetype":[
        "aat:300008347"
    ]
},
  "bbox": [],
  "geometry": {"coordinates":[3.8,50.75],"type":"Point"}
}
=======
{"geometry":{"type":"Point","coordinates":[3.800000,50.750000]},"type":"Feature","properties":{"hierarchy":["tgn:7245630","tgn:7007877","tgn:1000003","tgn:1000063","tgn:4012014","tgn:7029392"],"placetype":["aat:300008347"],"id":7245630,"name:xx":"Clo\u00eetre"}}
>>>>>>> 03f74aca74312dbeaf24d7e61306dd6a786dc3d0
