{
  "id": 2228201,
  "type": "Feature",
  "properties": {
    "tgn:hierarchy":[
        "tgn:2228201",
        "tgn:7002659",
        "tgn:1000001",
        "tgn:2000014",
        "tgn:7012149",
        "tgn:7029392"
    ],
    "tgn:id":2228201,
    "tgn:name":"Cedar Creek",
    "tgn:placetype":[
        "aat:300008706"
    ]
},
  "bbox": [],
  "geometry": {"coordinates":[-85.55,33.5833],"type":"Point"}
}