{
  "id": 7327050,
  "type": "Feature",
  "properties": {
    "tgn:hierarchy":[
        "tgn:7327050",
        "tgn:7001158",
        "tgn:7002850",
        "tgn:1000003",
        "tgn:1000095",
        "tgn:7029392"
    ],
    "tgn:id":7327050,
    "tgn:name":"Pasariegos",
    "tgn:placetype":[
        "aat:300008347"
    ]
},
  "bbox": [],
  "geometry": {"coordinates":[-6.15,41.35],"type":"Point"}
}