{
  "id": 2320268,
  "type": "Feature",
  "properties": {
    "tgn:hierarchy":[
        "tgn:2320268",
        "tgn:1000001",
        "tgn:7012149",
        "tgn:7007157",
        "tgn:1002857",
        "tgn:7029392"
    ],
    "tgn:id":2320268,
    "tgn:name":"Evening Star Mine",
    "tgn:placetype":[
        "aat:300000390"
    ]
},
  "bbox": [],
  "geometry": {"coordinates":[-115.5333,35.35],"type":"Point"}
}