{
  "id": 7544515,
  "type": "Feature",
  "properties": {
    "tgn:hierarchy":[
        "tgn:7544515",
        "tgn:1000003",
        "tgn:7002889",
        "tgn:1000070",
        "tgn:7029392"
    ],
    "tgn:id":7544515,
    "tgn:name":"Aspet",
    "tgn:placetype":[
        "aat:300008347"
    ]
},
  "bbox": [],
  "geometry": {"coordinates":[0.803,43.014],"type":"Point"}
}