{
  "id": 7066351,
  "type": "Feature",
  "properties": {
    "tgn:hierarchy":[
        "tgn:7066351",
        "tgn:1000003",
        "tgn:7003685",
        "tgn:7000084",
        "tgn:7029392"
    ],
    "tgn:id":7066351,
    "tgn:name":"Ullersdorf",
    "tgn:placetype":[
        "aat:300008347"
    ]
},
  "bbox": [],
  "geometry": {"coordinates":[14.833333,51.25],"type":"Point"}
}