{
  "id": 2249550,
  "type": "Feature",
  "properties": {
    "tgn:hierarchy":[
        "tgn:2249550",
        "tgn:1000001",
        "tgn:7012149",
        "tgn:2000421",
        "tgn:7007248",
        "tgn:7029392"
    ],
    "tgn:id":2249550,
    "tgn:name":"Coleoatchee Creek",
    "tgn:placetype":[
        "aat:300008706"
    ]
},
  "bbox": [],
  "geometry": {"coordinates":[-84.5833,32.8333],"type":"Point"}
}