{
  "id": 7012312,
  "type": "Feature",
  "properties": {
    "tgn:hierarchy":[
        "tgn:7012312",
        "tgn:7003533",
        "tgn:1000003",
        "tgn:7003514",
        "tgn:7029392"
    ],
    "tgn:id":7012312,
    "tgn:name":"Echternach",
    "tgn:placetype":[
        "aat:300387273",
        "aat:300008347",
        "aat:300008375"
    ]
},
  "bbox": [],
  "geometry": {"coordinates":[6.422222,49.805556],"type":"Point"}
}