{
  "id": 1070378,
  "type": "Feature",
  "properties": {
    "tgn:hierarchy":[
        "tgn:1070378",
        "tgn:1000004",
        "tgn:7002085",
        "tgn:1000111",
        "tgn:7029392"
    ],
    "tgn:id":1070378,
    "tgn:name":"Matouji",
    "tgn:placetype":[
        "aat:300008347"
    ]
},
  "bbox": [],
  "geometry": {"coordinates":[115.0667,35.0167],"type":"Point"}
}