{
  "id": 2452601,
  "type": "Feature",
  "properties": {
    "tgn:hierarchy":[
        "tgn:2452601",
        "tgn:1000001",
        "tgn:7012149",
        "tgn:2000911",
        "tgn:7007256",
        "tgn:7029392"
    ],
    "tgn:id":2452601,
    "tgn:name":"Little Brushy Creek",
    "tgn:placetype":[
        "aat:300008706"
    ]
},
  "bbox": [],
  "geometry": {"coordinates":[-92.95,31.05],"type":"Point"}
}