{
  "id": 2785679,
  "type": "Feature",
  "properties": {
    "tgn:hierarchy":[
        "tgn:2785679",
        "tgn:1000001",
        "tgn:7012149",
        "tgn:7007826",
        "tgn:7029392"
    ],
    "tgn:id":2785679,
    "tgn:name":"Yoledigo Creek",
    "tgn:placetype":[
        "aat:300008706"
    ]
},
  "bbox": [],
  "geometry": {"coordinates":[-99.45,28.9833],"type":"Point"}
}