{
  "id": 2416053,
  "type": "Feature",
  "properties": {
    "tgn:hierarchy":[
        "tgn:2416053",
        "tgn:7006450",
        "tgn:1000001",
        "tgn:7012149",
        "tgn:2124014",
        "tgn:7029392"
    ],
    "tgn:id":2416053,
    "tgn:name":"Iyikrok Mountain",
    "tgn:placetype":[
        "aat:300008798"
    ]
},
  "bbox": [],
  "geometry": {"coordinates":[-163.65,67.9333],"type":"Point"}
}