{
  "id": 2650018,
  "type": "Feature",
  "properties": {
    "tgn:hierarchy":[
        "tgn:2650018",
        "tgn:1000001",
        "tgn:2002321",
        "tgn:7012149",
        "tgn:7007922",
        "tgn:7029392"
    ],
    "tgn:id":2650018,
    "tgn:name":"Sea Lion Lake",
    "tgn:placetype":[
        "aat:300008680"
    ]
},
  "bbox": [],
  "geometry": {"coordinates":[-88.3167,45.8667],"type":"Point"}
}