{
  "id": 7583164,
  "type": "Feature",
  "properties": {
    "tgn:hierarchy":[
        "tgn:7583164",
        "tgn:1000004",
        "tgn:1001871",
        "tgn:7000198",
        "tgn:7029392"
    ],
    "tgn:id":7583164,
    "tgn:name:en":"Sar\u0101i Sukhi",
    "tgn:placetype":[
        "aat:300008347"
    ]
},
  "bbox": [],
  "geometry": {"coordinates":[76.838859,30.060495],"type":"Point"}
}