{
  "id": 1012043,
  "type": "Feature",
  "properties": {
    "tgn:hierarchy":[
        "tgn:1012043",
        "tgn:7001242",
        "tgn:7016833",
        "tgn:1001418",
        "tgn:7029392"
    ],
    "tgn:id":1012043,
    "tgn:name:en":"\u1e28ikmah, Ra's al",
    "tgn:placetype":[
        "aat:300008850",
        "aat:300386846"
    ]
},
  "bbox": [],
  "geometry": {"coordinates":[27.855071,31.246601],"type":"Point"}
}