{
  "id": 7486632,
  "type": "Feature",
  "properties": {
    "tgn:hierarchy":[
        "tgn:7486632",
        "tgn:1000004",
        "tgn:7490934",
        "tgn:1000141",
        "tgn:7029392"
    ],
    "tgn:id":7486632,
    "tgn:name":"Liaoqian",
    "tgn:placetype":[
        "aat:300008347"
    ]
},
  "bbox": [],
  "geometry": {"coordinates":[120.27011,23.234462],"type":"Point"}
}