{
  "id": 1020508,
  "type": "Feature",
  "properties": {
    "tgn:hierarchy":[
        "tgn:1020508",
        "tgn:1001826",
        "tgn:1000047",
        "tgn:7002456",
        "tgn:1000002",
        "tgn:7029392"
    ],
    "tgn:id":1020508,
    "tgn:name":"Abufari",
    "tgn:placetype":[
        "aat:300008347"
    ]
},
  "bbox": [],
  "geometry": {"coordinates":[-62.9833,-5.1667],"type":"Point"}
}