{
  "id": 7552153,
  "type": "Feature",
  "properties": {
    "tgn:hierarchy":[
        "tgn:7552153",
        "tgn:1000004",
        "tgn:1001842",
        "tgn:7000198",
        "tgn:7029392"
    ],
    "tgn:id":7552153,
    "tgn:name:en":"Narganjo",
    "tgn:placetype":[
        "aat:300008347"
    ]
},
  "bbox": [],
  "geometry": {"coordinates":[86.465666,24.741998],"type":"Point"}
}