{
  "id": 7320867,
  "type": "Feature",
  "properties": {
    "tgn:hierarchy":[
        "tgn:7320867",
        "tgn:7002464",
        "tgn:1000049",
        "tgn:1000002",
        "tgn:7029392"
    ],
    "tgn:id":7320867,
    "tgn:name":"Blanco, Cerro",
    "tgn:placetype":[
        "aat:300008777"
    ]
},
  "bbox": [],
  "geometry": {"coordinates":[-70.083333,-18.566667],"type":"Point"}
}