{
  "id": 7141130,
  "type": "Feature",
  "properties": {
    "tgn:hierarchy":[
        "tgn:7141130",
        "tgn:1000003",
        "tgn:7003688",
        "tgn:7000084",
        "tgn:7029392"
    ],
    "tgn:id":7141130,
    "tgn:name":"Lurop",
    "tgn:placetype":[
        "aat:300000206"
    ]
},
  "bbox": [],
  "geometry": {"coordinates":[10.25,53.666667],"type":"Point"}
}