{
  "id": 2496988,
  "type": "Feature",
  "properties": {
    "tgn:hierarchy":[
        "tgn:2496988",
        "tgn:1000001",
        "tgn:7012149",
        "tgn:2001763",
        "tgn:7007712",
        "tgn:7029392"
    ],
    "tgn:id":2496988,
    "tgn:name":"Mauldin Mountain",
    "tgn:placetype":[
        "aat:300008798"
    ]
},
  "bbox": [],
  "geometry": {"coordinates":[-82.6333,34.8167],"type":"Point"}
}