{
  "id": 1071119,
  "type": "Feature",
  "properties": {
    "tgn:hierarchy":[
        "tgn:1071119",
        "tgn:1000004",
        "tgn:7002086",
        "tgn:1000111",
        "tgn:7029392"
    ],
    "tgn:id":1071119,
    "tgn:name":"Qinshui",
    "tgn:placetype":[
        "aat:300008347"
    ]
},
  "bbox": [],
  "geometry": {"coordinates":[112.25,35.75],"type":"Point"}
}