{
  "id": 7175030,
  "type": "Feature",
  "properties": {
    "tgn:hierarchy":[
        "tgn:7175030",
        "tgn:1000003",
        "tgn:7003682",
        "tgn:7000084",
        "tgn:7029392"
    ],
    "tgn:id":7175030,
    "tgn:name":"Gro\u00dfer Fisch-Berg",
    "tgn:placetype":[
        "aat:300008777"
    ]
},
  "bbox": [],
  "geometry": {"coordinates":[7.916667,49.266667],"type":"Point"}
}