{
  "id": 7289190,
  "type": "Feature",
  "properties": {
    "tgn:hierarchy":[
        "tgn:7289190",
        "tgn:7016598",
        "tgn:1000049",
        "tgn:1000002",
        "tgn:7029392"
    ],
    "tgn:id":7289190,
    "tgn:name":"Lagartos, Banco",
    "tgn:placetype":[
        "aat:300008808"
    ]
},
  "bbox": [],
  "geometry": {"coordinates":[-70.616667,-23.35],"type":"Point"}
}