<<<<<<< HEAD
{
  "id": 7361120,
  "type": "Feature",
  "properties": {
    "tgn:hierarchy":[
        "tgn:7361120",
        "tgn:1000001",
        "tgn:7005597",
        "tgn:7005560",
        "tgn:7029392"
    ],
    "tgn:id":7361120,
    "tgn:name":"El Huisachal",
    "tgn:placetype":[
        "aat:300008347"
    ]
},
  "bbox": [],
  "geometry": {"coordinates":[-99.616667,27.166667],"type":"Point"}
}
=======
{"geometry":{"type":"Point","coordinates":[-99.616667,27.166667]},"type":"Feature","properties":{"hierarchy":["tgn:7361120","tgn:1000001","tgn:7005597","tgn:7005560","tgn:7029392"],"placetype":["aat:300008347"],"id":7361120,"name:xx":"El Huisachal"}}
>>>>>>> 03f74aca74312dbeaf24d7e61306dd6a786dc3d0
