{
  "id": 2075449,
  "type": "Feature",
  "properties": {
    "tgn:hierarchy":[
        "tgn:2075449",
        "tgn:1000001",
        "tgn:2001470",
        "tgn:7012149",
        "tgn:7007709",
        "tgn:7029392"
    ],
    "tgn:id":2075449,
    "tgn:name":"Lewiston Woodville",
    "tgn:placetype":[
        "aat:300008347"
    ]
},
  "bbox": [],
  "geometry": {"coordinates":[-77.1667,36.1167],"type":"Point"}
}