{
  "id": 2411670,
  "type": "Feature",
  "properties": {
    "tgn:hierarchy":[
        "tgn:2411670",
        "tgn:1000001",
        "tgn:7012149",
        "tgn:2001057",
        "tgn:7007521",
        "tgn:7029392"
    ],
    "tgn:id":2411670,
    "tgn:name":"Indian Lake",
    "tgn:placetype":[
        "aat:300008680"
    ]
},
  "bbox": [],
  "geometry": {"coordinates":[-96.3167,44.0167],"type":"Point"}
}