{
  "id": 1049407,
  "type": "Feature",
  "properties": {
    "tgn:hierarchy":[
        "tgn:1049407",
        "tgn:7024116",
        "tgn:1000003",
        "tgn:7006366",
        "tgn:7029392"
    ],
    "tgn:id":1049407,
    "tgn:name":"Radziej\u00f3w",
    "tgn:placetype":[
        "aat:300008347"
    ]
},
  "bbox": [],
  "geometry": {"coordinates":[18.5167,52.65],"type":"Point"}
}