{
  "id": 2159601,
  "type": "Feature",
  "properties": {
    "tgn:hierarchy":[
        "tgn:2159601",
        "tgn:1000001",
        "tgn:1002294",
        "tgn:7012149",
        "tgn:7007710",
        "tgn:7029392"
    ],
    "tgn:id":2159601,
    "tgn:name":"Bee Sellers Hollow",
    "tgn:placetype":[
        "aat:300008761"
    ]
},
  "bbox": [],
  "geometry": {"coordinates":[-76.3833,41.1333],"type":"Point"}
}