{
  "id": 2315942,
  "type": "Feature",
  "properties": {
    "tgn:hierarchy":[
        "tgn:2315942",
        "tgn:1000001",
        "tgn:7012149",
        "tgn:7007568",
        "tgn:7029392"
    ],
    "tgn:id":2315942,
    "tgn:name":"Elm Creek",
    "tgn:placetype":[
        "aat:300008706"
    ]
},
  "bbox": [],
  "geometry": {"coordinates":[-78.1833,42.5333],"type":"Point"}
}