<<<<<<< HEAD
{
  "id": 7351694,
  "type": "Feature",
  "properties": {
    "tgn:hierarchy":[
        "tgn:7351694",
        "tgn:1000001",
        "tgn:1001960",
        "tgn:7005560",
        "tgn:7029392"
    ],
    "tgn:id":7351694,
    "tgn:name":"Cajeme",
    "tgn:placetype":[
        "aat:300007783"
    ]
},
  "bbox": [],
  "geometry": {"coordinates":[-109.933333,27.483333],"type":"Point"}
}
=======
{"geometry":{"type":"Point","coordinates":[-109.933333,27.483333]},"type":"Feature","properties":{"hierarchy":["tgn:7351694","tgn:1000001","tgn:1001960","tgn:7005560","tgn:7029392"],"placetype":["aat:300007783"],"id":7351694,"name:xx":"Cajeme"}}
>>>>>>> 03f74aca74312dbeaf24d7e61306dd6a786dc3d0
