{
  "id": 2416199,
  "type": "Feature",
  "properties": {
    "tgn:hierarchy":[
        "tgn:2416199",
        "tgn:7002659",
        "tgn:1000001",
        "tgn:7012149",
        "tgn:2000036",
        "tgn:7029392"
    ],
    "tgn:id":2416199,
    "tgn:name":"J M Roberts Pond",
    "tgn:placetype":[
        "aat:300006191"
    ]
},
  "bbox": [],
  "geometry": {"coordinates":[-86.55,33.6667],"type":"Point"}
}