<<<<<<< HEAD
{
  "id": 2405055,
  "type": "Feature",
  "properties": {
    "tgn:hierarchy":[
        "tgn:2405055",
        "tgn:7006450",
        "tgn:1000001",
        "tgn:7012149",
        "tgn:2000086",
        "tgn:7029392"
    ],
    "tgn:id":2405055,
    "tgn:name":"Hudson Lake",
    "tgn:placetype":[
        "aat:300008680"
    ]
},
  "bbox": [],
  "geometry": {"coordinates":[-145.6667,61.9],"type":"Point"}
}
=======
{"geometry":{"type":"Point","coordinates":[-145.666700,61.900000]},"type":"Feature","properties":{"hierarchy":["tgn:2405055","tgn:7006450","tgn:1000001","tgn:7012149","tgn:2000086","tgn:7029392"],"placetype":["aat:300008680"],"id":2405055,"name:xx":"Hudson Lake"}}
>>>>>>> 03f74aca74312dbeaf24d7e61306dd6a786dc3d0
