{
  "id": 2601312,
  "type": "Feature",
  "properties": {
    "tgn:hierarchy":[
        "tgn:2601312",
        "tgn:1000001",
        "tgn:7012149",
        "tgn:2001448",
        "tgn:7007566",
        "tgn:7029392"
    ],
    "tgn:id":2601312,
    "tgn:name":"Purcell",
    "tgn:placetype":[
        "aat:300008798"
    ]
},
  "bbox": [],
  "geometry": {"coordinates":[-103.05,34.95],"type":"Point"}
}