<<<<<<< HEAD
{
  "id": 7351700,
  "type": "Feature",
  "properties": {
    "tgn:hierarchy":[
        "tgn:7351700",
        "tgn:1000001",
        "tgn:7005595",
        "tgn:7005560",
        "tgn:7029392"
    ],
    "tgn:id":7351700,
    "tgn:name":"Caitime",
    "tgn:placetype":[
        "aat:300008347"
    ]
},
  "bbox": [],
  "geometry": {"coordinates":[-107.95,25.316667],"type":"Point"}
}
=======
{"geometry":{"type":"Point","coordinates":[-107.950000,25.316667]},"type":"Feature","properties":{"hierarchy":["tgn:7351700","tgn:1000001","tgn:7005595","tgn:7005560","tgn:7029392"],"placetype":["aat:300008347"],"id":7351700,"name:xx":"Caitime"}}
>>>>>>> 03f74aca74312dbeaf24d7e61306dd6a786dc3d0
