{
  "id": 7351700,
  "type": "Feature",
  "properties": {
    "tgn:hierarchy":[
        "tgn:7351700",
        "tgn:1000001",
        "tgn:7005595",
        "tgn:7005560",
        "tgn:7029392"
    ],
    "tgn:id":7351700,
    "tgn:name":"Caitime",
    "tgn:placetype":[
        "aat:300008347"
    ]
},
  "bbox": [],
  "geometry": {"coordinates":[-107.95,25.316667],"type":"Point"}
}