<<<<<<< HEAD
{
  "id": 7482536,
  "type": "Feature",
  "properties": {
    "tgn:hierarchy":[
        "tgn:7482536",
        "tgn:1000004",
        "tgn:7490934",
        "tgn:1000141",
        "tgn:7029392"
    ],
    "tgn:id":7482536,
    "tgn:name":"Guoli Tainan Yishu Xueyuan",
    "tgn:placetype":[
        "aat:300006610"
    ]
},
  "bbox": [],
  "geometry": {"coordinates":[120.375348,23.185264],"type":"Point"}
}
=======
{"geometry":{"type":"Point","coordinates":[120.375348,23.185264]},"type":"Feature","properties":{"hierarchy":["tgn:7482536","tgn:1000004","tgn:7490934","tgn:1000141","tgn:7029392"],"placetype":["aat:300006610"],"id":7482536,"name:xx":"Guoli Tainan Yishu Xueyuan"}}
>>>>>>> 03f74aca74312dbeaf24d7e61306dd6a786dc3d0
