{
  "id": 7514481,
  "type": "Feature",
  "properties": {
    "tgn:hierarchy":[
        "tgn:7514481",
        "tgn:1009227",
        "tgn:1000226",
        "tgn:7018437",
        "tgn:1000006",
        "tgn:7029392"
    ],
    "tgn:id":7514481,
    "tgn:name:en":"Dispute, Mount",
    "tgn:placetype":[
        "aat:300008795"
    ]
},
  "bbox": [],
  "geometry": {"coordinates":[168.933333,-44.133333],"type":"Point"}
}