{
  "id": 7360891,
  "type": "Feature",
  "properties": {
    "tgn:hierarchy":[
        "tgn:7360891",
        "tgn:1000001",
        "tgn:7005589",
        "tgn:7005560",
        "tgn:7029392"
    ],
    "tgn:id":7360891,
    "tgn:name":"El Nogalito",
    "tgn:placetype":[
        "aat:300008347"
    ]
},
  "bbox": [],
  "geometry": {"coordinates":[-99.616667,26.15],"type":"Point"}
}