{
  "id": 2671303,
  "type": "Feature",
  "properties": {
    "tgn:hierarchy":[
        "tgn:2671303",
        "tgn:2002239",
        "tgn:1000001",
        "tgn:7012149",
        "tgn:7007920",
        "tgn:7029392"
    ],
    "tgn:id":2671303,
    "tgn:name":"Smith Gulch",
    "tgn:placetype":[
        "aat:300008761"
    ]
},
  "bbox": [],
  "geometry": {"coordinates":[-117.3167,46.1667],"type":"Point"}
}