{
  "id": 2078285,
  "type": "Feature",
  "properties": {
    "tgn:hierarchy":[
        "tgn:2078285",
        "tgn:1000001",
        "tgn:7012149",
        "tgn:1002784",
        "tgn:7007706",
        "tgn:7029392"
    ],
    "tgn:id":2078285,
    "tgn:name":"Atlanta",
    "tgn:placetype":[
        "aat:300008347"
    ]
},
  "bbox": [],
  "geometry": {"coordinates":[-83.1833,39.55],"type":"Point"}
}