<<<<<<< HEAD
{
  "id": 7372547,
  "type": "Feature",
  "properties": {
    "tgn:hierarchy":[
        "tgn:7372547",
        "tgn:1000001",
        "tgn:1001906",
        "tgn:7005560",
        "tgn:7029392"
    ],
    "tgn:id":7372547,
    "tgn:name":"La Cantera",
    "tgn:placetype":[
        "aat:300008347"
    ]
},
  "bbox": [],
  "geometry": {"coordinates":[-104.833333,21.5],"type":"Point"}
}
=======
{"geometry":{"type":"Point","coordinates":[-104.833333,21.500000]},"type":"Feature","properties":{"hierarchy":["tgn:7372547","tgn:1000001","tgn:1001906","tgn:7005560","tgn:7029392"],"placetype":["aat:300008347"],"id":7372547,"name:xx":"La Cantera"}}
>>>>>>> 03f74aca74312dbeaf24d7e61306dd6a786dc3d0
