{
  "id": 2047049,
  "type": "Feature",
  "properties": {
    "tgn:hierarchy":[
        "tgn:2047049",
        "tgn:1000001",
        "tgn:1002902",
        "tgn:7012149",
        "tgn:7007516",
        "tgn:7029392"
    ],
    "tgn:id":2047049,
    "tgn:name":"Fairmount",
    "tgn:placetype":[
        "aat:300008347"
    ]
},
  "bbox": [],
  "geometry": {"coordinates":[-75.8167,38.0833],"type":"Point"}
}