{
  "id": 7429548,
  "type": "Feature",
  "properties": {
    "tgn:hierarchy":[
        "tgn:7429548",
        "tgn:1000001",
        "tgn:7005595",
        "tgn:7005560",
        "tgn:7029392"
    ],
    "tgn:id":7429548,
    "tgn:name":"Iguana, Isla",
    "tgn:placetype":[
        "aat:300008791"
    ]
},
  "bbox": [],
  "geometry": {"coordinates":[-107.633333,24.45],"type":"Point"}
}