{
  "id": 7287592,
  "type": "Feature",
  "properties": {
    "tgn:hierarchy":[
        "tgn:7287592",
        "tgn:1001768",
        "tgn:1000049",
        "tgn:1000002",
        "tgn:7029392"
    ],
    "tgn:id":7287592,
    "tgn:name":"La Enjalmita, Cerro",
    "tgn:placetype":[
        "aat:300008798"
    ]
},
  "bbox": [],
  "geometry": {"coordinates":[-70.833333,-32.383333],"type":"Point"}
}