{
  "id": 7411089,
  "type": "Feature",
  "properties": {
    "tgn:hierarchy":[
        "tgn:7411089",
        "tgn:1000001",
        "tgn:7005598",
        "tgn:7005560",
        "tgn:7029392"
    ],
    "tgn:id":7411089,
    "tgn:name":"El Pilanc\u00f3n",
    "tgn:placetype":[
        "aat:300008347"
    ]
},
  "bbox": [],
  "geometry": {"coordinates":[-97.902778,19.505556],"type":"Point"}
}