{
  "id": 2648554,
  "type": "Feature",
  "properties": {
    "tgn:hierarchy":[
        "tgn:2648554",
        "tgn:1000001",
        "tgn:7012149",
        "tgn:1002681",
        "tgn:7007568",
        "tgn:7029392"
    ],
    "tgn:id":2648554,
    "tgn:name":"Science Hill",
    "tgn:placetype":[
        "aat:300008798"
    ]
},
  "bbox": [],
  "geometry": {"coordinates":[-77.9167,43.0333],"type":"Point"}
}