<<<<<<< HEAD
{
  "id": 2251663,
  "type": "Feature",
  "properties": {
    "tgn:hierarchy":[
        "tgn:2251663",
        "tgn:1000001",
        "tgn:7012149",
        "tgn:1002990",
        "tgn:7007708",
        "tgn:7029392"
    ],
    "tgn:id":2251663,
    "tgn:name":"Company Hollow",
    "tgn:placetype":[
        "aat:300008761"
    ]
},
  "bbox": [],
  "geometry": {"coordinates":[-121.0167,45.5667],"type":"Point"}
}
=======
{"geometry":{"type":"Point","coordinates":[-121.016700,45.566700]},"type":"Feature","properties":{"hierarchy":["tgn:2251663","tgn:1000001","tgn:7012149","tgn:1002990","tgn:7007708","tgn:7029392"],"placetype":["aat:300008761"],"id":2251663,"name:xx":"Company Hollow"}}
>>>>>>> 03f74aca74312dbeaf24d7e61306dd6a786dc3d0
