<<<<<<< HEAD
{
  "id": 7249866,
  "type": "Feature",
  "properties": {
    "tgn:hierarchy":[
        "tgn:7249866",
        "tgn:7003457",
        "tgn:1000003",
        "tgn:1000063",
        "tgn:7018236",
        "tgn:7029392"
    ],
    "tgn:id":7249866,
    "tgn:name":"Overmere",
    "tgn:placetype":[
        "aat:300008347"
    ]
},
  "bbox": [],
  "geometry": {"coordinates":[3.946596,51.046905],"type":"Point"}
}
=======
{"geometry":{"type":"Point","coordinates":[3.946596,51.046905]},"type":"Feature","properties":{"hierarchy":["tgn:7249866","tgn:7003457","tgn:1000003","tgn:1000063","tgn:7018236","tgn:7029392"],"placetype":["aat:300008347"],"id":7249866,"name:xx":"Overmere"}}
>>>>>>> 03f74aca74312dbeaf24d7e61306dd6a786dc3d0
