<<<<<<< HEAD
{
  "id": 2400037,
  "type": "Feature",
  "properties": {
    "tgn:hierarchy":[
        "tgn:2400037",
        "tgn:2000195",
        "tgn:1000001",
        "tgn:7012149",
        "tgn:7007158",
        "tgn:7029392"
    ],
    "tgn:id":2400037,
    "tgn:name":"Horse Creek",
    "tgn:placetype":[
        "aat:300008706"
    ]
},
  "bbox": [],
  "geometry": {"coordinates":[-107.2667,37.2833],"type":"Point"}
}
=======
{"geometry":{"type":"Point","coordinates":[-107.266700,37.283300]},"type":"Feature","properties":{"hierarchy":["tgn:2400037","tgn:2000195","tgn:1000001","tgn:7012149","tgn:7007158","tgn:7029392"],"placetype":["aat:300008706"],"id":2400037,"name:xx":"Horse Creek"}}
>>>>>>> 03f74aca74312dbeaf24d7e61306dd6a786dc3d0
