<<<<<<< HEAD
{
  "id": 7351218,
  "type": "Feature",
  "properties": {
    "tgn:hierarchy":[
        "tgn:7351218",
        "tgn:1000001",
        "tgn:1001906",
        "tgn:7005560",
        "tgn:7029392"
    ],
    "tgn:id":7351218,
    "tgn:name":"Balleto, Punta",
    "tgn:placetype":[
        "aat:300386846"
    ]
},
  "bbox": [],
  "geometry": {"coordinates":[-106.5,21.6],"type":"Point"}
}
=======
{"geometry":{"type":"Point","coordinates":[-106.500000,21.600000]},"type":"Feature","properties":{"hierarchy":["tgn:7351218","tgn:1000001","tgn:1001906","tgn:7005560","tgn:7029392"],"placetype":["aat:300386846"],"id":7351218,"name:xx":"Balleto, Punta"}}
>>>>>>> 03f74aca74312dbeaf24d7e61306dd6a786dc3d0
