<<<<<<< HEAD
{
  "id": 2402560,
  "type": "Feature",
  "properties": {
    "tgn:hierarchy":[
        "tgn:2402560",
        "tgn:1000001",
        "tgn:7006451",
        "tgn:2000092",
        "tgn:7012149",
        "tgn:7029392"
    ],
    "tgn:id":2402560,
    "tgn:name":"Hospital Ridge",
    "tgn:placetype":[
        "aat:300266640"
    ]
},
  "bbox": [],
  "geometry": {"coordinates":[-111.1167,34.4333],"type":"Point"}
}
=======
{"geometry":{"type":"Point","coordinates":[-111.116700,34.433300]},"type":"Feature","properties":{"hierarchy":["tgn:2402560","tgn:1000001","tgn:7006451","tgn:2000092","tgn:7012149","tgn:7029392"],"placetype":["aat:300266640"],"id":2402560,"name:xx":"Hospital Ridge"}}
>>>>>>> 03f74aca74312dbeaf24d7e61306dd6a786dc3d0
