{
  "id": 2560453,
  "type": "Feature",
  "properties": {
    "tgn:hierarchy":[
        "tgn:2560453",
        "tgn:1000001",
        "tgn:7006451",
        "tgn:2000093",
        "tgn:7012149",
        "tgn:7029392"
    ],
    "tgn:id":2560453,
    "tgn:name":"Ord Mine",
    "tgn:placetype":[
        "aat:300000390"
    ]
},
  "bbox": [],
  "geometry": {"coordinates":[-111.3833,33.95],"type":"Point"}
}