{
  "id": 7320912,
  "type": "Feature",
  "properties": {
    "tgn:hierarchy":[
        "tgn:7320912",
        "tgn:7016598",
        "tgn:1000049",
        "tgn:1000002",
        "tgn:7029392"
    ],
    "tgn:id":7320912,
    "tgn:name":"Baltinache, Llano de",
    "tgn:placetype":[
        "aat:300008805"
    ]
},
  "bbox": [],
  "geometry": {"coordinates":[-68.183333,-23.033333],"type":"Point"}
}