{
  "id": 2526091,
  "type": "Feature",
  "properties": {
    "tgn:hierarchy":[
        "tgn:2526091",
        "tgn:1000001",
        "tgn:7012149",
        "tgn:2002342",
        "tgn:7007922",
        "tgn:7029392"
    ],
    "tgn:id":2526091,
    "tgn:name":"Mosquito Creek",
    "tgn:placetype":[
        "aat:300008706"
    ]
},
  "bbox": [],
  "geometry": {"coordinates":[-89.0833,45.8167],"type":"Point"}
}