{
  "id": 7584239,
  "type": "Feature",
  "properties": {
    "tgn:hierarchy":[
        "tgn:7584239",
        "tgn:1000004",
        "tgn:7000198",
        "tgn:7016883",
        "tgn:7029392"
    ],
    "tgn:id":7584239,
    "tgn:name:en":"Kachhwi",
    "tgn:placetype":[
        "aat:300008347"
    ]
},
  "bbox": [],
  "geometry": {"coordinates":[76.580947,30.188741],"type":"Point"}
}