{
  "id": 7425034,
  "type": "Feature",
  "properties": {
    "tgn:hierarchy":[
        "tgn:7425034",
        "tgn:1000001",
        "tgn:7005601",
        "tgn:7005560",
        "tgn:7029392"
    ],
    "tgn:id":7425034,
    "tgn:name":"El Carcelero",
    "tgn:placetype":[
        "aat:300008347"
    ]
},
  "bbox": [],
  "geometry": {"coordinates":[-102.783333,22.566667],"type":"Point"}
}