{
  "id": 1065357,
  "type": "Feature",
  "properties": {
    "tgn:hierarchy":[
        "tgn:1065357",
        "tgn:1000003",
        "tgn:7015085",
        "tgn:7006670",
        "tgn:7029392"
    ],
    "tgn:id":1065357,
    "tgn:name":"Zgornje Ho\u010de",
    "tgn:placetype":[
        "aat:300008347"
    ]
},
  "bbox": [],
  "geometry": {"coordinates":[15.6333,46.4833],"type":"Point"}
}