{
  "id": 2699461,
  "type": "Feature",
  "properties": {
    "tgn:hierarchy":[
        "tgn:2699461",
        "tgn:1002165",
        "tgn:1000001",
        "tgn:7012149",
        "tgn:7007517",
        "tgn:7029392"
    ],
    "tgn:id":2699461,
    "tgn:name":"Strong Island",
    "tgn:placetype":[
        "aat:300008791"
    ]
},
  "bbox": [],
  "geometry": {"coordinates":[-69.95,41.7167],"type":"Point"}
}