{
  "id": 7587206,
  "type": "Feature",
  "properties": {
    "tgn:hierarchy":[
        "tgn:7587206",
        "tgn:1000004",
        "tgn:7000198",
        "tgn:7000799",
        "tgn:7029392"
    ],
    "tgn:id":7587206,
    "tgn:name:en":"Latiwaz",
    "tgn:placetype":[
        "aat:300008347"
    ]
},
  "bbox": [],
  "geometry": {"coordinates":[74.702778,34.2375],"type":"Point"}
}