{
  "id": 7535431,
  "type": "Feature",
  "properties": {
    "tgn:hierarchy":[
        "tgn:7535431",
        "tgn:7001242",
        "tgn:7016833",
        "tgn:1001418",
        "tgn:7029392"
    ],
    "tgn:id":7535431,
    "tgn:name:en":"Qabr el Garr\u00e2ri",
    "tgn:placetype":[
        "aat:300005926"
    ]
},
  "bbox": [],
  "geometry": {"coordinates":[26.537839,30.902251],"type":"Point"}
}