{
  "id": 2368320,
  "type": "Feature",
  "properties": {
    "tgn:hierarchy":[
        "tgn:2368320",
        "tgn:1000001",
        "tgn:7012149",
        "tgn:2000785",
        "tgn:7007255",
        "tgn:7029392"
    ],
    "tgn:id":2368320,
    "tgn:name":"Guffey Hollow",
    "tgn:placetype":[
        "aat:300008761"
    ]
},
  "bbox": [],
  "geometry": {"coordinates":[-85.4667,36.6667],"type":"Point"}
}