{
  "id": 7449612,
  "type": "Feature",
  "properties": {
    "tgn:hierarchy":[
        "tgn:7449612",
        "tgn:7002448",
        "tgn:7008699",
        "tgn:1000003",
        "tgn:7008591",
        "tgn:7029392"
    ],
    "tgn:id":7449612,
    "tgn:name:en":"Glenkeen House",
    "tgn:placetype":[
        "aat:300387502"
    ]
},
  "bbox": [],
  "geometry": {"coordinates":[-7.25,54.95],"type":"Point"}
}