<<<<<<< HEAD
{
  "id": 7470810,
  "type": "Feature",
  "properties": {
    "tgn:hierarchy":[
        "tgn:7470810",
        "tgn:1000004",
        "tgn:7489179",
        "tgn:1000141",
        "tgn:7029392"
    ],
    "tgn:id":7470810,
    "tgn:name":"Yicun",
    "tgn:placetype":[
        "aat:300008347"
    ]
},
  "bbox": [],
  "geometry": {"coordinates":[121.8362,24.6044],"type":"Point"}
}
=======
{"geometry":{"type":"Point","coordinates":[121.836200,24.604400]},"type":"Feature","properties":{"hierarchy":["tgn:7470810","tgn:1000004","tgn:7489179","tgn:1000141","tgn:7029392"],"placetype":["aat:300008347"],"id":7470810,"name:xx":"Yicun"}}
>>>>>>> 03f74aca74312dbeaf24d7e61306dd6a786dc3d0
