{
  "id": 7106408,
  "type": "Feature",
  "properties": {
    "tgn:hierarchy":[
        "tgn:7106408",
        "tgn:1000003",
        "tgn:7003688",
        "tgn:7000084",
        "tgn:7029392"
    ],
    "tgn:id":7106408,
    "tgn:name":"Schleibach",
    "tgn:placetype":[
        "aat:300008699"
    ]
},
  "bbox": [],
  "geometry": {"coordinates":[10.016667,54.65],"type":"Point"}
}