{
  "id": 7504607,
  "type": "Feature",
  "properties": {
    "tgn:hierarchy":[
        "tgn:7504607",
        "tgn:1008380",
        "tgn:7000507",
        "tgn:1000226",
        "tgn:1000006",
        "tgn:7029392"
    ],
    "tgn:id":7504607,
    "tgn:name:en":"Bream Islands",
    "tgn:placetype":[
        "aat:300008791"
    ]
},
  "bbox": [],
  "geometry": {"coordinates":[174.595,-35.839444],"type":"Point"}
}