{
  "id": 2680828,
  "type": "Feature",
  "properties": {
    "tgn:hierarchy":[
        "tgn:2680828",
        "tgn:1000001",
        "tgn:7012149",
        "tgn:2124023",
        "tgn:7007248",
        "tgn:7029392"
    ],
    "tgn:id":2680828,
    "tgn:name":"South Kirkwood",
    "tgn:placetype":[
        "aat:300008347"
    ]
},
  "bbox": [],
  "geometry": {"coordinates":[-84.3167,33.75],"type":"Point"}
}