{
  "id": 1113673,
  "type": "Feature",
  "properties": {
    "tgn:hierarchy":[
        "tgn:1113673",
        "tgn:1008380",
        "tgn:7000507",
        "tgn:1000226",
        "tgn:1000006",
        "tgn:7029392"
    ],
    "tgn:id":1113673,
    "tgn:name:en":"Rangaunu Bay",
    "tgn:placetype":[
        "aat:300132316"
    ]
},
  "bbox": [],
  "geometry": {"coordinates":[173.25,-34.833333],"type":"Point"}
}