{
  "id": 7310008,
  "type": "Feature",
  "properties": {
    "tgn:hierarchy":[
        "tgn:7310008",
        "tgn:1001702",
        "tgn:1000049",
        "tgn:1000002",
        "tgn:7029392"
    ],
    "tgn:id":7310008,
    "tgn:name":"Murray, Caleta",
    "tgn:placetype":[
        "aat:300132317"
    ]
},
  "bbox": [],
  "geometry": {"coordinates":[-71.666667,-53.95],"type":"Point"}
}