{
  "id": 2122415,
  "type": "Feature",
  "properties": {
    "tgn:hierarchy":[
        "tgn:2122415",
        "tgn:1000001",
        "tgn:7012149",
        "tgn:2002341",
        "tgn:7007922",
        "tgn:7029392"
    ],
    "tgn:id":2122415,
    "tgn:name":"South Chase",
    "tgn:placetype":[
        "aat:300008347",
        "aat:300387210"
    ]
},
  "bbox": [],
  "geometry": {"coordinates":[-88.15,44.6833],"type":"Point"}
}