{
  "id": 7404308,
  "type": "Feature",
  "properties": {
    "tgn:hierarchy":[
        "tgn:7404308",
        "tgn:7016644",
        "tgn:1000001",
        "tgn:7005560",
        "tgn:7029392"
    ],
    "tgn:id":7404308,
    "tgn:name":"Canal Amela",
    "tgn:placetype":[
        "aat:300006075"
    ]
},
  "bbox": [],
  "geometry": {"coordinates":[-103.783333,18.816667],"type":"Point"}
}