{
  "id": 7334881,
  "type": "Feature",
  "properties": {
    "tgn:hierarchy":[
        "tgn:7334881",
        "tgn:7002849",
        "tgn:1000003",
        "tgn:7009604",
        "tgn:1000095",
        "tgn:7029392"
    ],
    "tgn:id":7334881,
    "tgn:name":"Garacoy",
    "tgn:placetype":[
        "aat:300008347"
    ]
},
  "bbox": [],
  "geometry": {"coordinates":[-2.775231,43.175897],"type":"Point"}
}