{
  "id": 2554884,
  "type": "Feature",
  "properties": {
    "tgn:hierarchy":[
        "tgn:2554884",
        "tgn:2000002",
        "tgn:7002659",
        "tgn:1000001",
        "tgn:7012149",
        "tgn:7029392"
    ],
    "tgn:id":2554884,
    "tgn:name":"Oateston",
    "tgn:placetype":[
        "aat:300008347"
    ]
},
  "bbox": [],
  "geometry": {"coordinates":[-85.3667,31.75],"type":"Point"}
}