{
  "id": 2491544,
  "type": "Feature",
  "properties": {
    "tgn:hierarchy":[
        "tgn:2491544",
        "tgn:1000001",
        "tgn:7014423",
        "tgn:7012149",
        "tgn:7007517",
        "tgn:7029392"
    ],
    "tgn:id":2491544,
    "tgn:name":"Maple Park Bogs",
    "tgn:placetype":[
        "aat:300008905"
    ]
},
  "bbox": [],
  "geometry": {"coordinates":[-70.65,41.7667],"type":"Point"}
}