{
  "id": 7362779,
  "type": "Feature",
  "properties": {
    "tgn:hierarchy":[
        "tgn:7362779",
        "tgn:1000001",
        "tgn:7005597",
        "tgn:7005560",
        "tgn:7029392"
    ],
    "tgn:id":7362779,
    "tgn:name":"El \u00c1lamo",
    "tgn:placetype":[
        "aat:300008347"
    ]
},
  "bbox": [],
  "geometry": {"coordinates":[-99.533333,27.516667],"type":"Point"}
}