{
  "id": 7261484,
  "type": "Feature",
  "properties": {
    "tgn:hierarchy":[
        "tgn:7261484",
        "tgn:7003614",
        "tgn:1000003",
        "tgn:7016845",
        "tgn:7029392"
    ],
    "tgn:id":7261484,
    "tgn:name:nl":"Grote Diep",
    "tgn:placetype":[
        "aat:300006075"
    ]
},
  "bbox": [],
  "geometry": {"coordinates":[6.833333,52.983333],"type":"Point"}
}