{
  "id": 2694828,
  "type": "Feature",
  "properties": {
    "tgn:hierarchy":[
        "tgn:2694828",
        "tgn:1000001",
        "tgn:1003029",
        "tgn:7012149",
        "tgn:7007828",
        "tgn:7029392"
    ],
    "tgn:id":2694828,
    "tgn:name":"Stickney Brook",
    "tgn:placetype":[
        "aat:300008699"
    ]
},
  "bbox": [],
  "geometry": {"coordinates":[-72.6667,42.9167],"type":"Point"}
}