{
  "id": 7315763,
  "type": "Feature",
  "properties": {
    "tgn:hierarchy":[
        "tgn:7315763",
        "tgn:1001702",
        "tgn:1000049",
        "tgn:1000002",
        "tgn:7029392"
    ],
    "tgn:id":7315763,
    "tgn:name":"Cercha, Punta",
    "tgn:placetype":[
        "aat:300386846"
    ]
},
  "bbox": [],
  "geometry": {"coordinates":[-72.833333,-52.566667],"type":"Point"}
}