{
  "id": 2590244,
  "type": "Feature",
  "properties": {
    "tgn:hierarchy":[
        "tgn:2590244",
        "tgn:7006450",
        "tgn:1000001",
        "tgn:7012149",
        "tgn:2000079",
        "tgn:7029392"
    ],
    "tgn:id":2590244,
    "tgn:name":"Poker Creek",
    "tgn:placetype":[
        "aat:300008706"
    ]
},
  "bbox": [],
  "geometry": {"coordinates":[-160.8333,63.5333],"type":"Point"}
}