{
  "id": 7478562,
  "type": "Feature",
  "properties": {
    "tgn:hierarchy":[
        "tgn:7478562",
        "tgn:1000004",
        "tgn:7492971",
        "tgn:1000141",
        "tgn:7029392"
    ],
    "tgn:id":7478562,
    "tgn:name":"Xingtianzi",
    "tgn:placetype":[
        "aat:300008347"
    ]
},
  "bbox": [],
  "geometry": {"coordinates":[120.363439,22.340345],"type":"Point"}
}