{
  "id": 7500171,
  "type": "Feature",
  "properties": {
    "tgn:hierarchy":[
        "tgn:7500171",
        "tgn:1000004",
        "tgn:1000454",
        "tgn:1000141",
        "tgn:7029392"
    ],
    "tgn:id":7500171,
    "tgn:name":"Shanghuang Xi Qiao",
    "tgn:placetype":[
        "aat:300007836"
    ]
},
  "bbox": [],
  "geometry": {"coordinates":[121.582158,25.179493],"type":"Point"}
}