{
  "id": 2607742,
  "type": "Feature",
  "properties": {
    "tgn:hierarchy":[
        "tgn:2607742",
        "tgn:1000001",
        "tgn:7016172",
        "tgn:7012149",
        "tgn:2000162",
        "tgn:7029392"
    ],
    "tgn:id":2607742,
    "tgn:name":"Raspberry",
    "tgn:placetype":[
        "aat:300008347"
    ]
},
  "bbox": [],
  "geometry": {"coordinates":[-92.9333,35.6833],"type":"Point"}
}