{
  "id": 2179619,
  "type": "Feature",
  "properties": {
    "tgn:hierarchy":[
        "tgn:2179619",
        "tgn:7006450",
        "tgn:1000001",
        "tgn:2124076",
        "tgn:7012149",
        "tgn:7029392"
    ],
    "tgn:id":2179619,
    "tgn:name":"Blank Point",
    "tgn:placetype":[
        "aat:300008850"
    ]
},
  "bbox": [],
  "geometry": {"coordinates":[-131.6667,55.25],"type":"Point"}
}