{
  "id": 7359060,
  "type": "Feature",
  "properties": {
    "tgn:hierarchy":[
        "tgn:7359060",
        "tgn:1000001",
        "tgn:7005595",
        "tgn:7005560",
        "tgn:7029392"
    ],
    "tgn:id":7359060,
    "tgn:name":"El Aguajito",
    "tgn:placetype":[
        "aat:300008347"
    ]
},
  "bbox": [],
  "geometry": {"coordinates":[-109.316667,25.95],"type":"Point"}
}