{
  "id": 2351114,
  "type": "Feature",
  "properties": {
    "tgn:hierarchy":[
        "tgn:2351114",
        "tgn:7002659",
        "tgn:1000001",
        "tgn:2000007",
        "tgn:7012149",
        "tgn:7029392"
    ],
    "tgn:id":2351114,
    "tgn:name":"Glass Spring",
    "tgn:placetype":[
        "aat:300008697"
    ]
},
  "bbox": [],
  "geometry": {"coordinates":[-85.8167,33.7667],"type":"Point"}
}