{
  "id": 1072039,
  "type": "Feature",
  "properties": {
    "tgn:hierarchy":[
        "tgn:1072039",
        "tgn:7002075",
        "tgn:1000004",
        "tgn:1000111",
        "tgn:7029392"
    ],
    "tgn:id":1072039,
    "tgn:name":"Suxian",
    "tgn:placetype":[
        "aat:300008347"
    ]
},
  "bbox": [],
  "geometry": {"coordinates":[116.9667,33.6333],"type":"Point"}
}