{
  "id": 7497609,
  "type": "Feature",
  "properties": {
    "tgn:hierarchy":[
        "tgn:7497609",
        "tgn:1000004",
        "tgn:7001009",
        "tgn:1000141",
        "tgn:7029392"
    ],
    "tgn:id":7497609,
    "tgn:name":"Changfu Qiao",
    "tgn:placetype":[
        "aat:300007836"
    ]
},
  "bbox": [],
  "geometry": {"coordinates":[120.700155,24.144636],"type":"Point"}
}