<<<<<<< HEAD
{
  "id": 2400777,
  "type": "Feature",
  "properties": {
    "tgn:hierarchy":[
        "tgn:2400777",
        "tgn:1000001",
        "tgn:7012149",
        "tgn:7007157",
        "tgn:2000189",
        "tgn:7029392"
    ],
    "tgn:id":2400777,
    "tgn:name":"Horse Pocket",
    "tgn:placetype":[
        "aat:300386845"
    ]
},
  "bbox": [],
  "geometry": {"coordinates":[-123.35,41.5],"type":"Point"}
}
=======
{"geometry":{"type":"Point","coordinates":[-123.350000,41.500000]},"type":"Feature","properties":{"hierarchy":["tgn:2400777","tgn:1000001","tgn:7012149","tgn:7007157","tgn:2000189","tgn:7029392"],"placetype":["aat:300386845"],"id":2400777,"name:xx":"Horse Pocket"}}
>>>>>>> 03f74aca74312dbeaf24d7e61306dd6a786dc3d0
