{
  "id": 7381884,
  "type": "Feature",
  "properties": {
    "tgn:hierarchy":[
        "tgn:7381884",
        "tgn:7005581",
        "tgn:1000001",
        "tgn:7005560",
        "tgn:7029392"
    ],
    "tgn:id":7381884,
    "tgn:name":"Rancho Los Nogales",
    "tgn:placetype":[
        "aat:300000241"
    ]
},
  "bbox": [],
  "geometry": {"coordinates":[-106.366667,30.133333],"type":"Point"}
}