{
  "id": 1019126,
  "type": "Feature",
  "properties": {
    "tgn:hierarchy":[
        "tgn:1019126",
        "tgn:7006477",
        "tgn:1001376",
        "tgn:1000002",
        "tgn:7029392"
    ],
    "tgn:id":1019126,
    "tgn:name":"Aimogasta",
    "tgn:placetype":[
        "aat:300008347"
    ]
},
  "bbox": [],
  "geometry": {"coordinates":[-66.8333,-28.55],"type":"Point"}
}