{
  "id": 7009753,
  "type": "Feature",
  "properties": {
    "tgn:hierarchy":[
        "tgn:7009753",
        "tgn:7019140",
        "tgn:7002444",
        "tgn:1000003",
        "tgn:7008591",
        "tgn:7029392"
    ],
    "tgn:id":7009753,
    "tgn:name:en":"Brechin",
    "tgn:placetype":[
        "aat:300008347"
    ]
},
  "bbox": [],
  "geometry": {"coordinates":[-2.65,56.733333],"type":"Point"}
}