{
  "id": 7040690,
  "type": "Feature",
  "properties": {
    "tgn:hierarchy":[
        "tgn:7040690",
        "tgn:7007850",
        "tgn:1003491",
        "tgn:1000003",
        "tgn:1000080",
        "tgn:7029392"
    ],
    "tgn:id":7040690,
    "tgn:name":"San Procopio",
    "tgn:placetype":[
        "aat:300008347"
    ]
},
  "bbox": [],
  "geometry": {"coordinates":[15.883333,38.283333],"type":"Point"}
}