{
  "id": 7283593,
  "type": "Feature",
  "properties": {
    "tgn:hierarchy":[
        "tgn:7283593",
        "tgn:1001768",
        "tgn:1000049",
        "tgn:1000002",
        "tgn:7029392"
    ],
    "tgn:id":7283593,
    "tgn:name":"Papudo, Puerto",
    "tgn:placetype":[
        "aat:300132316"
    ]
},
  "bbox": [],
  "geometry": {"coordinates":[-71.4675,-32.488333],"type":"Point"}
}