<<<<<<< HEAD
{
  "id": 2336628,
  "type": "Feature",
  "properties": {
    "tgn:hierarchy":[
        "tgn:2336628",
        "tgn:1000001",
        "tgn:7012149",
        "tgn:2000387",
        "tgn:7007248",
        "tgn:7029392"
    ],
    "tgn:id":2336628,
    "tgn:name":"Four Points",
    "tgn:placetype":[
        "aat:300008347"
    ]
},
  "bbox": [],
  "geometry": {"coordinates":[-83.9833,32.3167],"type":"Point"}
}
=======
{"geometry":{"type":"Point","coordinates":[-83.983300,32.316700]},"type":"Feature","properties":{"hierarchy":["tgn:2336628","tgn:1000001","tgn:7012149","tgn:2000387","tgn:7007248","tgn:7029392"],"placetype":["aat:300008347"],"id":2336628,"name:xx":"Four Points"}}
>>>>>>> 03f74aca74312dbeaf24d7e61306dd6a786dc3d0
