{
  "id": 7277653,
  "type": "Feature",
  "properties": {
    "tgn:hierarchy":[
        "tgn:7277653",
        "tgn:1001657",
        "tgn:1000049",
        "tgn:1000002",
        "tgn:7029392"
    ],
    "tgn:id":7277653,
    "tgn:name":"Verde, Isla",
    "tgn:placetype":[
        "aat:300008791"
    ]
},
  "bbox": [],
  "geometry": {"coordinates":[-71.540278,-31.867778],"type":"Point"}
}