{
  "id": 7521300,
  "type": "Feature",
  "properties": {
    "tgn:hierarchy":[
        "tgn:7521300",
        "tgn:7001242",
        "tgn:7016833",
        "tgn:7029392"
    ],
    "tgn:id":7521300,
    "tgn:name:en":"Abu Fir', W\u00e2di",
    "tgn:placetype":[
        "aat:300379998"
    ]
},
  "bbox": [],
  "geometry": {"coordinates":[31.492895,29.569644],"type":"Point"}
}