{
  "id": 7477037,
  "type": "Feature",
  "properties": {
    "tgn:hierarchy":[
        "tgn:7477037",
        "tgn:1000004",
        "tgn:7001013",
        "tgn:1000141",
        "tgn:7029392"
    ],
    "tgn:id":7477037,
    "tgn:name":"Kantoucuo",
    "tgn:placetype":[
        "aat:300008347"
    ]
},
  "bbox": [],
  "geometry": {"coordinates":[121.2223,25.032322],"type":"Point"}
}