<<<<<<< HEAD
{
  "id": 7360135,
  "type": "Feature",
  "properties": {
    "tgn:hierarchy":[
        "tgn:7360135",
        "tgn:1000001",
        "tgn:7005597",
        "tgn:7005560",
        "tgn:7029392"
    ],
    "tgn:id":7360135,
    "tgn:name":"Cuchilla de San Pedro, Sierra la",
    "tgn:placetype":[
        "aat:300266640"
    ]
},
  "bbox": [],
  "geometry": {"coordinates":[-99.183333,23.333333],"type":"Point"}
}
=======
{"geometry":{"type":"Point","coordinates":[-99.183333,23.333333]},"type":"Feature","properties":{"hierarchy":["tgn:7360135","tgn:1000001","tgn:7005597","tgn:7005560","tgn:7029392"],"placetype":["aat:300266640"],"id":7360135,"name:xx":"Cuchilla de San Pedro, Sierra la"}}
>>>>>>> 03f74aca74312dbeaf24d7e61306dd6a786dc3d0
