{
  "id": 2372540,
  "type": "Feature",
  "properties": {
    "tgn:hierarchy":[
        "tgn:2372540",
        "tgn:1000001",
        "tgn:7012149",
        "tgn:2001894",
        "tgn:7007825",
        "tgn:7029392"
    ],
    "tgn:id":2372540,
    "tgn:name":"Hall Branch",
    "tgn:placetype":[
        "aat:300008699"
    ]
},
  "bbox": [],
  "geometry": {"coordinates":[-85.55,35.1333],"type":"Point"}
}