{
  "id": 2593462,
  "type": "Feature",
  "properties": {
    "tgn:hierarchy":[
        "tgn:2593462",
        "tgn:1000001",
        "tgn:2001583",
        "tgn:7012149",
        "tgn:7007705",
        "tgn:7029392"
    ],
    "tgn:id":2593462,
    "tgn:name":"Porcupine Coulee",
    "tgn:placetype":[
        "aat:300008699"
    ]
},
  "bbox": [],
  "geometry": {"coordinates":[-103.1333,47.9667],"type":"Point"}
}