{
  "id": 2001889,
  "type": "Feature",
  "properties": {
    "tgn:hierarchy":[
        "tgn:2001889",
        "tgn:1000001",
        "tgn:7012149",
        "tgn:7007825",
        "tgn:7029392"
    ],
    "tgn:id":2001889,
    "tgn:name":"Loudon",
    "tgn:placetype":[
        "aat:300387145",
        "aat:300000771"
    ]
},
  "bbox": [],
  "geometry": {"coordinates":[-84.3167,35.7333],"type":"Point"}
}