{
  "id": 2761155,
  "type": "Feature",
  "properties": {
    "tgn:hierarchy":[
        "tgn:2761155",
        "tgn:1000001",
        "tgn:7012149",
        "tgn:7013867",
        "tgn:7007710",
        "tgn:7029392"
    ],
    "tgn:id":2761155,
    "tgn:name":"West Lampeter",
    "tgn:placetype":[
        "aat:300008347"
    ]
},
  "bbox": [],
  "geometry": {"coordinates":[-76.2667,40.0167],"type":"Point"}
}