{
  "id": 2517049,
  "type": "Feature",
  "properties": {
    "tgn:hierarchy":[
        "tgn:2517049",
        "tgn:1000001",
        "tgn:7012149",
        "tgn:2000472",
        "tgn:7007250",
        "tgn:7029392"
    ],
    "tgn:id":2517049,
    "tgn:name":"Mink Creek Spring",
    "tgn:placetype":[
        "aat:300008697"
    ]
},
  "bbox": [],
  "geometry": {"coordinates":[-111.5833,42.2833],"type":"Point"}
}