{
  "id": 2031652,
  "type": "Feature",
  "properties": {
    "tgn:hierarchy":[
        "tgn:2031652",
        "tgn:1002177",
        "tgn:1000001",
        "tgn:7012149",
        "tgn:7007252",
        "tgn:7029392"
    ],
    "tgn:id":2031652,
    "tgn:name":"Dunn",
    "tgn:placetype":[
        "aat:300008347",
        "aat:300387210"
    ]
},
  "bbox": [],
  "geometry": {"coordinates":[-87.45,40.55],"type":"Point"}
}