{
  "id": 2660164,
  "type": "Feature",
  "properties": {
    "tgn:hierarchy":[
        "tgn:2660164",
        "tgn:1000001",
        "tgn:7012149",
        "tgn:7014021",
        "tgn:7007709",
        "tgn:7029392"
    ],
    "tgn:id":2660164,
    "tgn:name":"Shoaf Lake",
    "tgn:placetype":[
        "aat:300006191"
    ]
},
  "bbox": [],
  "geometry": {"coordinates":[-80.95,35.1667],"type":"Point"}
}