{
  "id": 1056984,
  "type": "Feature",
  "properties": {
    "tgn:hierarchy":[
        "tgn:1056984",
        "tgn:1003391",
        "tgn:1000003",
        "tgn:7006657",
        "tgn:7029392"
    ],
    "tgn:id":1056984,
    "tgn:name":"Michanovi\u010di",
    "tgn:placetype":[
        "aat:300008347"
    ]
},
  "bbox": [],
  "geometry": {"coordinates":[27.6667,53.75],"type":"Point"}
}