{
  "id": 7438524,
  "type": "Feature",
  "properties": {
    "tgn:hierarchy":[
        "tgn:7438524",
        "tgn:7005581",
        "tgn:1000001",
        "tgn:7005560",
        "tgn:7029392"
    ],
    "tgn:id":7438524,
    "tgn:name":"Saucillo",
    "tgn:placetype":[
        "aat:300008347"
    ]
},
  "bbox": [],
  "geometry": {"coordinates":[-105.65,28.05],"type":"Point"}
}