{
  "id": 7400776,
  "type": "Feature",
  "properties": {
    "tgn:hierarchy":[
        "tgn:7400776",
        "tgn:1000001",
        "tgn:7005599",
        "tgn:7005560",
        "tgn:7029392"
    ],
    "tgn:id":7400776,
    "tgn:name":"La Florida",
    "tgn:placetype":[
        "aat:300008347"
    ]
},
  "bbox": [],
  "geometry": {"coordinates":[-97.575,20.470833],"type":"Point"}
}