{
  "id": 7590454,
  "type": "Feature",
  "properties": {
    "tgn:hierarchy":[
        "tgn:7590454",
        "tgn:1000004",
        "tgn:7000198",
        "tgn:7000799",
        "tgn:7029392"
    ],
    "tgn:id":7590454,
    "tgn:name:en":"Don\u0101ri",
    "tgn:placetype":[
        "aat:300008347"
    ]
},
  "bbox": [],
  "geometry": {"coordinates":[73.947048,34.441839],"type":"Point"}
}