{
  "id": 2343152,
  "type": "Feature",
  "properties": {
    "tgn:hierarchy":[
        "tgn:2343152",
        "tgn:7006450",
        "tgn:1000001",
        "tgn:7012149",
        "tgn:7019760",
        "tgn:7029392"
    ],
    "tgn:id":2343152,
    "tgn:name":"Gable Mountain",
    "tgn:placetype":[
        "aat:300008798"
    ]
},
  "bbox": [],
  "geometry": {"coordinates":[-136.5333,59.0667],"type":"Point"}
}