{
  "id": 2076081,
  "type": "Feature",
  "properties": {
    "tgn:hierarchy":[
        "tgn:2076081",
        "tgn:1000001",
        "tgn:7012149",
        "tgn:2001524",
        "tgn:7007709",
        "tgn:7029392"
    ],
    "tgn:id":2076081,
    "tgn:name":"Petersburg",
    "tgn:placetype":[
        "aat:300008347",
        "aat:300387210"
    ]
},
  "bbox": [],
  "geometry": {"coordinates":[-77.5333,34.9167],"type":"Point"}
}