{
  "id": 2181792,
  "type": "Feature",
  "properties": {
    "tgn:hierarchy":[
        "tgn:2181792",
        "tgn:1000001",
        "tgn:7012149",
        "tgn:7007157",
        "tgn:7014516",
        "tgn:7029392"
    ],
    "tgn:id":2181792,
    "tgn:name":"Blue Jay Ridge",
    "tgn:placetype":[
        "aat:300266640"
    ]
},
  "bbox": [],
  "geometry": {"coordinates":[-123.1333,38.55],"type":"Point"}
}