<<<<<<< HEAD
{
  "id": 2333045,
  "type": "Feature",
  "properties": {
    "tgn:hierarchy":[
        "tgn:2333045",
        "tgn:1000001",
        "tgn:7012149",
        "tgn:2001712",
        "tgn:7007708",
        "tgn:7029392"
    ],
    "tgn:id":2333045,
    "tgn:name":"Fly Creek",
    "tgn:placetype":[
        "aat:300008706"
    ]
},
  "bbox": [],
  "geometry": {"coordinates":[-121.5833,44.4667],"type":"Point"}
}
=======
{"geometry":{"type":"Point","coordinates":[-121.583300,44.466700]},"type":"Feature","properties":{"hierarchy":["tgn:2333045","tgn:1000001","tgn:7012149","tgn:2001712","tgn:7007708","tgn:7029392"],"placetype":["aat:300008706"],"id":2333045,"name:xx":"Fly Creek"}}
>>>>>>> 03f74aca74312dbeaf24d7e61306dd6a786dc3d0
