{
  "id": 2333045,
  "type": "Feature",
  "properties": {
    "tgn:hierarchy":[
        "tgn:2333045",
        "tgn:1000001",
        "tgn:7012149",
        "tgn:2001712",
        "tgn:7007708",
        "tgn:7029392"
    ],
    "tgn:id":2333045,
    "tgn:name":"Fly Creek",
    "tgn:placetype":[
        "aat:300008706"
    ]
},
  "bbox": [],
  "geometry": {"coordinates":[-121.5833,44.4667],"type":"Point"}
}