{
  "id": 2207904,
  "type": "Feature",
  "properties": {
    "tgn:hierarchy":[
        "tgn:2207904",
        "tgn:1000001",
        "tgn:2001701",
        "tgn:7012149",
        "tgn:7007708",
        "tgn:7029392"
    ],
    "tgn:id":2207904,
    "tgn:name":"Burgett Creek",
    "tgn:placetype":[
        "aat:300008706"
    ]
},
  "bbox": [],
  "geometry": {"coordinates":[-123.4833,44.6667],"type":"Point"}
}