{
  "id": 7409830,
  "type": "Feature",
  "properties": {
    "tgn:hierarchy":[
        "tgn:7409830",
        "tgn:1000001",
        "tgn:7005592",
        "tgn:7005560",
        "tgn:7029392"
    ],
    "tgn:id":7409830,
    "tgn:name":"Estaci\u00f3n Varela",
    "tgn:placetype":[
        "aat:300007783"
    ]
},
  "bbox": [],
  "geometry": {"coordinates":[-97.583333,19.433333],"type":"Point"}
}