{
  "id": 7585503,
  "type": "Feature",
  "properties": {
    "tgn:hierarchy":[
        "tgn:7585503",
        "tgn:1000004",
        "tgn:7000198",
        "tgn:7000799",
        "tgn:7029392"
    ],
    "tgn:id":7585503,
    "tgn:name:en":"Gir\u0101n",
    "tgn:placetype":[
        "aat:300008347"
    ]
},
  "bbox": [],
  "geometry": {"coordinates":[74.142509,33.259924],"type":"Point"}
}