{
  "id": 2361513,
  "type": "Feature",
  "properties": {
    "tgn:hierarchy":[
        "tgn:2361513",
        "tgn:1000001",
        "tgn:7012149",
        "tgn:1002521",
        "tgn:7007920",
        "tgn:7029392"
    ],
    "tgn:id":2361513,
    "tgn:name":"Graves Creek",
    "tgn:placetype":[
        "aat:300008706"
    ]
},
  "bbox": [],
  "geometry": {"coordinates":[-123.5167,47.5333],"type":"Point"}
}