{
  "id": 7516966,
  "type": "Feature",
  "properties": {
    "tgn:hierarchy":[
        "tgn:7516966",
        "tgn:1009227",
        "tgn:1000226",
        "tgn:1000006",
        "tgn:7016850",
        "tgn:7029392"
    ],
    "tgn:id":7516966,
    "tgn:name:en":"Miserable Ridge",
    "tgn:placetype":[
        "aat:300266640"
    ]
},
  "bbox": [],
  "geometry": {"coordinates":[170.966667,-43.033333],"type":"Point"}
}