{
  "id": 1087938,
  "type": "Feature",
  "properties": {
    "tgn:hierarchy":[
        "tgn:1087938",
        "tgn:7001242",
        "tgn:1000149",
        "tgn:1000899",
        "tgn:7029392"
    ],
    "tgn:id":1087938,
    "tgn:name":"Namachire",
    "tgn:placetype":[
        "aat:300008347"
    ]
},
  "bbox": [],
  "geometry": {"coordinates":[22.85,-11.4833],"type":"Point"}
}