{
  "id": 7017303,
  "type": "Feature",
  "properties": {
    "tgn:hierarchy":[
        "tgn:7017303",
        "tgn:1000003",
        "tgn:7006663",
        "tgn:7029392"
    ],
    "tgn:id":7017303,
    "tgn:name":"Brodsko-Posavska \u017dupanija",
    "tgn:placetype":[
        "aat:300387064",
        "aat:300000771"
    ]
},
  "bbox": [],
  "geometry": {"coordinates":[17.762,45.166],"type":"Point"}
}