<<<<<<< HEAD
{
  "id": 7171054,
  "type": "Feature",
  "properties": {
    "tgn:hierarchy":[
        "tgn:7171054",
        "tgn:1000003",
        "tgn:7003685",
        "tgn:7000084",
        "tgn:7029392"
    ],
    "tgn:id":7171054,
    "tgn:name":"Hirschh\u00fcbel",
    "tgn:placetype":[
        "aat:300008777"
    ]
},
  "bbox": [],
  "geometry": {"coordinates":[13.616667,50.716667],"type":"Point"}
}
=======
{"geometry":{"type":"Point","coordinates":[13.616667,50.716667]},"type":"Feature","properties":{"hierarchy":["tgn:7171054","tgn:1000003","tgn:7003685","tgn:7000084","tgn:7029392"],"placetype":["aat:300008777"],"id":7171054,"name:xx":"Hirschh\u00fcbel"}}
>>>>>>> 03f74aca74312dbeaf24d7e61306dd6a786dc3d0
