{
  "id": 7318698,
  "type": "Feature",
  "properties": {
    "tgn:hierarchy":[
        "tgn:7318698",
        "tgn:1001702",
        "tgn:1000049",
        "tgn:1000002",
        "tgn:7029392"
    ],
    "tgn:id":7318698,
    "tgn:name":"C\u00e1diz, Punta",
    "tgn:placetype":[
        "aat:300386846"
    ]
},
  "bbox": [],
  "geometry": {"coordinates":[-71.616667,-54.683333],"type":"Point"}
}