{
  "id": 2777234,
  "type": "Feature",
  "properties": {
    "tgn:hierarchy":[
        "tgn:2777234",
        "tgn:1000001",
        "tgn:1002249",
        "tgn:7012149",
        "tgn:7007710",
        "tgn:7029392"
    ],
    "tgn:id":2777234,
    "tgn:name":"Winehead, The",
    "tgn:placetype":[
        "aat:300008798"
    ]
},
  "bbox": [],
  "geometry": {"coordinates":[-77.4667,40.95],"type":"Point"}
}