{
  "id": 7465886,
  "type": "Feature",
  "properties": {
    "tgn:hierarchy":[
        "tgn:7465886",
        "tgn:7002444",
        "tgn:1000003",
        "tgn:7009907",
        "tgn:7008591",
        "tgn:7029392"
    ],
    "tgn:id":7465886,
    "tgn:name:en":"Barr Rock",
    "tgn:placetype":[
        "aat:300011692"
    ]
},
  "bbox": [],
  "geometry": {"coordinates":[-3.283333,58.95],"type":"Point"}
}