{
  "id": 7434816,
  "type": "Feature",
  "properties": {
    "tgn:hierarchy":[
        "tgn:7434816",
        "tgn:7005581",
        "tgn:1000001",
        "tgn:7005560",
        "tgn:7029392"
    ],
    "tgn:id":7434816,
    "tgn:name":"Rancho Trancas",
    "tgn:placetype":[
        "aat:300000241"
    ]
},
  "bbox": [],
  "geometry": {"coordinates":[-105.65,28.883333],"type":"Point"}
}