{
  "id": 7567032,
  "type": "Feature",
  "properties": {
    "tgn:hierarchy":[
        "tgn:7567032",
        "tgn:1001828",
        "tgn:1000004",
        "tgn:7000198",
        "tgn:7029392"
    ],
    "tgn:id":7567032,
    "tgn:name:en":"K\u0101s\u0101ram",
    "tgn:placetype":[
        "aat:300008347"
    ]
},
  "bbox": [],
  "geometry": {"coordinates":[78.170556,17.505833],"type":"Point"}
}