{
  "id": 1011333,
  "type": "Feature",
  "properties": {
    "tgn:hierarchy":[
        "tgn:1011333",
        "tgn:7006477",
        "tgn:1001522",
        "tgn:1000002",
        "tgn:7029392"
    ],
    "tgn:id":1011333,
    "tgn:name":"Tres Puntas, Cabo",
    "tgn:placetype":[
        "aat:300008850"
    ]
},
  "bbox": [],
  "geometry": {"coordinates":[-65.9167,-47.0833],"type":"Point"}
}