{
  "id": 7237343,
  "type": "Feature",
  "properties": {
    "tgn:hierarchy":[
        "tgn:7237343",
        "tgn:7002735",
        "tgn:7017076",
        "tgn:1000003",
        "tgn:1000074",
        "tgn:7029392"
    ],
    "tgn:id":7237343,
    "tgn:name":"\u00c1yioi Taxi\u00e1rkhai",
    "tgn:placetype":[
        "aat:300008347"
    ]
},
  "bbox": [],
  "geometry": {"coordinates":[22.683333,36.833333],"type":"Point"}
}