{
  "id": 2589771,
  "type": "Feature",
  "properties": {
    "tgn:hierarchy":[
        "tgn:2589771",
        "tgn:7006450",
        "tgn:1000001",
        "tgn:7012149",
        "tgn:2000087",
        "tgn:7029392"
    ],
    "tgn:id":2589771,
    "tgn:name":"Point Smith",
    "tgn:placetype":[
        "aat:300008850"
    ]
},
  "bbox": [],
  "geometry": {"coordinates":[-165.9167,61.8167],"type":"Point"}
}