{
  "id": 7207315,
  "type": "Feature",
  "properties": {
    "tgn:hierarchy":[
        "tgn:7207315",
        "tgn:1000003",
        "tgn:7003685",
        "tgn:7000084",
        "tgn:7029392"
    ],
    "tgn:id":7207315,
    "tgn:name":"Burg-Berg",
    "tgn:placetype":[
        "aat:300008777"
    ]
},
  "bbox": [],
  "geometry": {"coordinates":[13.766667,50.933333],"type":"Point"}
}