{
  "id": 2774715,
  "type": "Feature",
  "properties": {
    "tgn:hierarchy":[
        "tgn:2774715",
        "tgn:1000001",
        "tgn:7012149",
        "tgn:2002127",
        "tgn:7007827",
        "tgn:7029392"
    ],
    "tgn:id":2774715,
    "tgn:name":"Willow Spring",
    "tgn:placetype":[
        "aat:300008697"
    ]
},
  "bbox": [],
  "geometry": {"coordinates":[-113.2333,37.1167],"type":"Point"}
}