<<<<<<< HEAD
{
  "id": 7026084,
  "type": "Feature",
  "properties": {
    "tgn:hierarchy":[
        "tgn:7026084",
        "tgn:1001828",
        "tgn:1000004",
        "tgn:7000198",
        "tgn:7029392"
    ],
    "tgn:id":7026084,
    "tgn:name:en":"Pushpagiri",
    "tgn:placetype":[
        "aat:300008347"
    ]
},
  "bbox": [],
  "geometry": {"coordinates":[79.166667,12.65],"type":"Point"}
}
=======
{"geometry":{"type":"Point","coordinates":[79.166667,12.650000]},"type":"Feature","properties":{"hierarchy":["tgn:7026084","tgn:1001828","tgn:1000004","tgn:7000198","tgn:7029392"],"placetype":["aat:300008347"],"name:en":"Pushpagiri","id":7026084}}
>>>>>>> 03f74aca74312dbeaf24d7e61306dd6a786dc3d0
