{
  "id": 7473500,
  "type": "Feature",
  "properties": {
    "tgn:hierarchy":[
        "tgn:7473500",
        "tgn:1000004",
        "tgn:7492971",
        "tgn:1000141",
        "tgn:7029392"
    ],
    "tgn:id":7473500,
    "tgn:name":"Yanbu",
    "tgn:placetype":[
        "aat:300008347"
    ]
},
  "bbox": [],
  "geometry": {"coordinates":[120.5785,22.7546],"type":"Point"}
}