{
  "id": 2429250,
  "type": "Feature",
  "properties": {
    "tgn:hierarchy":[
        "tgn:2429250",
        "tgn:7006450",
        "tgn:2000069",
        "tgn:1000001",
        "tgn:7012149",
        "tgn:7029392"
    ],
    "tgn:id":2429250,
    "tgn:name":"Jungjuk Creek",
    "tgn:placetype":[
        "aat:300008706"
    ]
},
  "bbox": [],
  "geometry": {"coordinates":[-158.4333,61.75],"type":"Point"}
}