{
  "id": 2218776,
  "type": "Feature",
  "properties": {
    "tgn:hierarchy":[
        "tgn:2218776",
        "tgn:1000001",
        "tgn:7012149",
        "tgn:2000786",
        "tgn:7007255",
        "tgn:7029392"
    ],
    "tgn:id":2218776,
    "tgn:name":"Cane Run",
    "tgn:placetype":[
        "aat:300008699"
    ]
},
  "bbox": [],
  "geometry": {"coordinates":[-86.9167,37.6667],"type":"Point"}
}