{
  "id": 2573037,
  "type": "Feature",
  "properties": {
    "tgn:hierarchy":[
        "tgn:2573037",
        "tgn:1000001",
        "tgn:7012149",
        "tgn:2001709",
        "tgn:7007708",
        "tgn:7029392"
    ],
    "tgn:id":2573037,
    "tgn:name":"Pearl Wise Canyon",
    "tgn:placetype":[
        "aat:300008761"
    ]
},
  "bbox": [],
  "geometry": {"coordinates":[-118.75,42.2833],"type":"Point"}
}