{
  "id": 7040970,
  "type": "Feature",
  "properties": {
    "tgn:hierarchy":[
        "tgn:7040970",
        "tgn:1001641",
        "tgn:1000003",
        "tgn:7003121",
        "tgn:1000080",
        "tgn:7029392"
    ],
    "tgn:id":7040970,
    "tgn:name":"Sant'Avendrace",
    "tgn:placetype":[
        "aat:300008347"
    ]
},
  "bbox": [],
  "geometry": {"coordinates":[9.096944,39.230556],"type":"Point"}
}