{
  "id": 2468916,
  "type": "Feature",
  "properties": {
    "tgn:hierarchy":[
        "tgn:2468916",
        "tgn:1000001",
        "tgn:7012149",
        "tgn:1002612",
        "tgn:7007710",
        "tgn:7029392"
    ],
    "tgn:id":2468916,
    "tgn:name":"Long Run",
    "tgn:placetype":[
        "aat:300008699"
    ]
},
  "bbox": [],
  "geometry": {"coordinates":[-75.9667,41.05],"type":"Point"}
}