{
  "id": 7560531,
  "type": "Feature",
  "properties": {
    "tgn:hierarchy":[
        "tgn:7560531",
        "tgn:1000004",
        "tgn:7000198",
        "tgn:7016722",
        "tgn:7029392"
    ],
    "tgn:id":7560531,
    "tgn:name:en":"Sulem\u0101npurpatti",
    "tgn:placetype":[
        "aat:300008347"
    ]
},
  "bbox": [],
  "geometry": {"coordinates":[79.565369,27.607194],"type":"Point"}
}