{
  "id": 7497487,
  "type": "Feature",
  "properties": {
    "tgn:hierarchy":[
        "tgn:7497487",
        "tgn:7001004",
        "tgn:1000004",
        "tgn:1000141",
        "tgn:7029392"
    ],
    "tgn:id":7497487,
    "tgn:name":"Yuemei",
    "tgn:placetype":[
        "aat:300008347"
    ]
},
  "bbox": [],
  "geometry": {"coordinates":[120.327697,22.710639],"type":"Point"}
}