{
  "id": 7258908,
  "type": "Feature",
  "properties": {
    "tgn:hierarchy":[
        "tgn:7258908",
        "tgn:7003465",
        "tgn:1000003",
        "tgn:1000063",
        "tgn:4012014",
        "tgn:7029392"
    ],
    "tgn:id":7258908,
    "tgn:name":"Vir\u00e9e aux Scies",
    "tgn:placetype":[
        "aat:300008863"
    ]
},
  "bbox": [],
  "geometry": {"coordinates":[5.033333,50.016667],"type":"Point"}
}