{
  "id": 2476111,
  "type": "Feature",
  "properties": {
    "tgn:hierarchy":[
        "tgn:2476111",
        "tgn:7006450",
        "tgn:1000001",
        "tgn:7012149",
        "tgn:2000079",
        "tgn:7029392"
    ],
    "tgn:id":2476111,
    "tgn:name":"Lulu Creek",
    "tgn:placetype":[
        "aat:300008706"
    ]
},
  "bbox": [],
  "geometry": {"coordinates":[-166.0167,65.3333],"type":"Point"}
}