{
  "id": 1093566,
  "type": "Feature",
  "properties": {
    "tgn:hierarchy":[
        "tgn:1093566",
        "tgn:7001242",
        "tgn:7017576",
        "tgn:1000193",
        "tgn:7029392"
    ],
    "tgn:id":1093566,
    "tgn:name":"Rivasdale",
    "tgn:placetype":[
        "aat:300008347"
    ]
},
  "bbox": [],
  "geometry": {"coordinates":[27.9333,-26.2833],"type":"Point"}
}