{
  "id": 2616699,
  "type": "Feature",
  "properties": {
    "tgn:hierarchy":[
        "tgn:2616699",
        "tgn:1000001",
        "tgn:7012149",
        "tgn:2001067",
        "tgn:7007521",
        "tgn:7029392"
    ],
    "tgn:id":2616699,
    "tgn:name":"Rices Point",
    "tgn:placetype":[
        "aat:300008850"
    ]
},
  "bbox": [],
  "geometry": {"coordinates":[-92.0833,46.75],"type":"Point"}
}