<<<<<<< HEAD
{
  "id": 7179482,
  "type": "Feature",
  "properties": {
    "tgn:hierarchy":[
        "tgn:7179482",
        "tgn:7003669",
        "tgn:1000003",
        "tgn:7000084",
        "tgn:7029392"
    ],
    "tgn:id":7179482,
    "tgn:name":"Haarweiher",
    "tgn:placetype":[
        "aat:300008680"
    ]
},
  "bbox": [],
  "geometry": {"coordinates":[10.933333,49.75],"type":"Point"}
}
=======
{"geometry":{"type":"Point","coordinates":[10.933333,49.750000]},"type":"Feature","properties":{"hierarchy":["tgn:7179482","tgn:7003669","tgn:1000003","tgn:7000084","tgn:7029392"],"placetype":["aat:300008680"],"id":7179482,"name:xx":"Haarweiher"}}
>>>>>>> 03f74aca74312dbeaf24d7e61306dd6a786dc3d0
