{
  "id": 7220592,
  "type": "Feature",
  "properties": {
    "tgn:hierarchy":[
        "tgn:7220592",
        "tgn:7002681",
        "tgn:7001395",
        "tgn:1000003",
        "tgn:1000074",
        "tgn:7029392"
    ],
    "tgn:id":7220592,
    "tgn:name":"Vasilik\u00eds, Vr\u00edsi",
    "tgn:placetype":[
        "aat:300008697"
    ]
},
  "bbox": [],
  "geometry": {"coordinates":[23.316667,38.166667],"type":"Point"}
}