{
  "id": 7232432,
  "type": "Feature",
  "properties": {
    "tgn:hierarchy":[
        "tgn:7232432",
        "tgn:7002711",
        "tgn:7001338",
        "tgn:1000003",
        "tgn:1000074",
        "tgn:7029392"
    ],
    "tgn:id":7232432,
    "tgn:name":"K\u00e1vos",
    "tgn:placetype":[
        "aat:300008347"
    ]
},
  "bbox": [],
  "geometry": {"coordinates":[20.113333,39.383889],"type":"Point"}
}