{
  "id": 7149078,
  "type": "Feature",
  "properties": {
    "tgn:hierarchy":[
        "tgn:7149078",
        "tgn:1000003",
        "tgn:7003688",
        "tgn:7000084",
        "tgn:7029392"
    ],
    "tgn:id":7149078,
    "tgn:name":"Kummerfeld",
    "tgn:placetype":[
        "aat:300008347"
    ]
},
  "bbox": [],
  "geometry": {"coordinates":[9.783333,53.683333],"type":"Point"}
}