{
  "id": 7305721,
  "type": "Feature",
  "properties": {
    "tgn:hierarchy":[
        "tgn:7305721",
        "tgn:1001439",
        "tgn:1000003",
        "tgn:7002797",
        "tgn:1000095",
        "tgn:7029392"
    ],
    "tgn:id":7305721,
    "tgn:name":"Mazarr\u00f3n, Puerto de",
    "tgn:placetype":[
        "aat:300008678"
    ]
},
  "bbox": [],
  "geometry": {"coordinates":[-1.25,37.566667],"type":"Point"}
}