{
  "id": 7419391,
  "type": "Feature",
  "properties": {
    "tgn:hierarchy":[
        "tgn:7419391",
        "tgn:1000001",
        "tgn:7005589",
        "tgn:7005560",
        "tgn:7029392"
    ],
    "tgn:id":7419391,
    "tgn:name:es":"Los Tomates",
    "tgn:placetype":[
        "aat:300008347"
    ]
},
  "bbox": [],
  "geometry": {"coordinates":[-100.139167,27.031944],"type":"Point"}
}