{
  "id": 2687933,
  "type": "Feature",
  "properties": {
    "tgn:hierarchy":[
        "tgn:2687933",
        "tgn:1000001",
        "tgn:7012149",
        "tgn:2000229",
        "tgn:7007158",
        "tgn:7029392"
    ],
    "tgn:id":2687933,
    "tgn:name":"Springdale Ditch",
    "tgn:placetype":[
        "aat:300006075"
    ]
},
  "bbox": [],
  "geometry": {"coordinates":[-103.2333,40.6167],"type":"Point"}
}