<<<<<<< HEAD
{
  "id": 7475307,
  "type": "Feature",
  "properties": {
    "tgn:hierarchy":[
        "tgn:7475307",
        "tgn:7001004",
        "tgn:1000004",
        "tgn:1000141",
        "tgn:7029392"
    ],
    "tgn:id":7475307,
    "tgn:name":"Erliao Xi",
    "tgn:placetype":[
        "aat:300008699"
    ]
},
  "bbox": [],
  "geometry": {"coordinates":[120.649444,23.246389],"type":"Point"}
}
=======
{"geometry":{"type":"Point","coordinates":[120.649444,23.246389]},"type":"Feature","properties":{"hierarchy":["tgn:7475307","tgn:7001004","tgn:1000004","tgn:1000141","tgn:7029392"],"placetype":["aat:300008699"],"id":7475307,"name:xx":"Erliao Xi"}}
>>>>>>> 03f74aca74312dbeaf24d7e61306dd6a786dc3d0
