{
  "id": 2431629,
  "type": "Feature",
  "properties": {
    "tgn:hierarchy":[
        "tgn:2431629",
        "tgn:1000001",
        "tgn:7012149",
        "tgn:2000875",
        "tgn:7007256",
        "tgn:7029392"
    ],
    "tgn:id":2431629,
    "tgn:name":"Kateland Pond",
    "tgn:placetype":[
        "aat:300008680"
    ]
},
  "bbox": [],
  "geometry": {"coordinates":[-92.6667,31.45],"type":"Point"}
}