{
  "id": 7251775,
  "type": "Feature",
  "properties": {
    "tgn:hierarchy":[
        "tgn:7251775",
        "tgn:7003456",
        "tgn:1000003",
        "tgn:1000063",
        "tgn:7018236",
        "tgn:7029392"
    ],
    "tgn:id":7251775,
    "tgn:name":"Mastboom",
    "tgn:placetype":[
        "aat:300000206"
    ]
},
  "bbox": [],
  "geometry": {"coordinates":[4.383333,51.133333],"type":"Point"}
}