{
  "id": 7180314,
  "type": "Feature",
  "properties": {
    "tgn:hierarchy":[
        "tgn:7180314",
        "tgn:7003692",
        "tgn:1000003",
        "tgn:7000084",
        "tgn:7029392"
    ],
    "tgn:id":7180314,
    "tgn:name":"Gausbach",
    "tgn:placetype":[
        "aat:300008347"
    ]
},
  "bbox": [],
  "geometry": {"coordinates":[8.366667,48.683333],"type":"Point"}
}