<<<<<<< HEAD
{
  "id": 7023514,
  "type": "Feature",
  "properties": {
    "tgn:hierarchy":[
        "tgn:7023514",
        "tgn:1000001",
        "tgn:7012149",
        "tgn:7007515",
        "tgn:7029392"
    ],
    "tgn:id":7023514,
    "tgn:name":"Mud Pond Brook",
    "tgn:placetype":[
        "aat:300008699"
    ]
},
  "bbox": [],
  "geometry": {"coordinates":[-69.7167,45.3333],"type":"Point"}
}
=======
{"geometry":{"type":"Point","coordinates":[-69.716700,45.333300]},"type":"Feature","properties":{"hierarchy":["tgn:7023514","tgn:1000001","tgn:7012149","tgn:7007515","tgn:7029392"],"placetype":["aat:300008699"],"id":7023514,"name:xx":"Mud Pond Brook"}}
>>>>>>> 03f74aca74312dbeaf24d7e61306dd6a786dc3d0
