{
  "id": 7348984,
  "type": "Feature",
  "properties": {
    "tgn:hierarchy":[
        "tgn:7348984",
        "tgn:1000001",
        "tgn:7005589",
        "tgn:7005560",
        "tgn:7029392"
    ],
    "tgn:id":7348984,
    "tgn:name":"Alazanas, Cerro las",
    "tgn:placetype":[
        "aat:300008795"
    ]
},
  "bbox": [],
  "geometry": {"coordinates":[-100.083333,24.566667],"type":"Point"}
}