{
  "id": 2555374,
  "type": "Feature",
  "properties": {
    "tgn:hierarchy":[
        "tgn:2555374",
        "tgn:1000001",
        "tgn:7012149",
        "tgn:2001846",
        "tgn:7007825",
        "tgn:7029392"
    ],
    "tgn:id":2555374,
    "tgn:name":"Odemville",
    "tgn:placetype":[
        "aat:300008347"
    ]
},
  "bbox": [],
  "geometry": {"coordinates":[-82.0333,36.2333],"type":"Point"}
}