<<<<<<< HEAD
{
  "id": 7379241,
  "type": "Feature",
  "properties": {
    "tgn:hierarchy":[
        "tgn:7379241",
        "tgn:1000001",
        "tgn:1001960",
        "tgn:7005560",
        "tgn:7029392"
    ],
    "tgn:id":7379241,
    "tgn:name":"Margen Derecha",
    "tgn:placetype":[
        "aat:300008699"
    ]
},
  "bbox": [],
  "geometry": {"coordinates":[-109.683333,26.8],"type":"Point"}
}
=======
{"geometry":{"type":"Point","coordinates":[-109.683333,26.800000]},"type":"Feature","properties":{"hierarchy":["tgn:7379241","tgn:1000001","tgn:1001960","tgn:7005560","tgn:7029392"],"placetype":["aat:300008699"],"id":7379241,"name:xx":"Margen Derecha"}}
>>>>>>> 03f74aca74312dbeaf24d7e61306dd6a786dc3d0
