{
  "id": 7375796,
  "type": "Feature",
  "properties": {
    "tgn:hierarchy":[
        "tgn:7375796",
        "tgn:1000001",
        "tgn:1001960",
        "tgn:7005560",
        "tgn:7029392"
    ],
    "tgn:id":7375796,
    "tgn:name":"Lista Blanca",
    "tgn:placetype":[
        "aat:300008347"
    ]
},
  "bbox": [],
  "geometry": {"coordinates":[-111.066667,29.25],"type":"Point"}
}