{
  "id": 1064481,
  "type": "Feature",
  "properties": {
    "tgn:hierarchy":[
        "tgn:1064481",
        "tgn:1000003",
        "tgn:7003763",
        "tgn:7011731",
        "tgn:7029392"
    ],
    "tgn:id":1064481,
    "tgn:name":"Vallorbe",
    "tgn:placetype":[
        "aat:300008347"
    ]
},
  "bbox": [],
  "geometry": {"coordinates":[6.3833,46.7167],"type":"Point"}
}