{
  "id": 2061701,
  "type": "Feature",
  "properties": {
    "tgn:hierarchy":[
        "tgn:2061701",
        "tgn:1000001",
        "tgn:7012149",
        "tgn:2001283",
        "tgn:7007524",
        "tgn:7029392"
    ],
    "tgn:id":2061701,
    "tgn:name":"Salmon Prairie",
    "tgn:placetype":[
        "aat:300008347",
        "aat:300387210"
    ]
},
  "bbox": [],
  "geometry": {"coordinates":[-113.7833,47.6167],"type":"Point"}
}