{
  "id": 7089647,
  "type": "Feature",
  "properties": {
    "tgn:hierarchy":[
        "tgn:7089647",
        "tgn:7003669",
        "tgn:1000003",
        "tgn:7000084",
        "tgn:7029392"
    ],
    "tgn:id":7089647,
    "tgn:name":"Unterwald",
    "tgn:placetype":[
        "aat:300008863"
    ]
},
  "bbox": [],
  "geometry": {"coordinates":[11.783333,49.75],"type":"Point"}
}