{
  "id": 7090539,
  "type": "Feature",
  "properties": {
    "tgn:hierarchy":[
        "tgn:7090539",
        "tgn:1000003",
        "tgn:7003677",
        "tgn:7000084",
        "tgn:7029392"
    ],
    "tgn:id":7090539,
    "tgn:name":"Unterselbach",
    "tgn:placetype":[
        "aat:300008347"
    ]
},
  "bbox": [],
  "geometry": {"coordinates":[7.266667,51.033333],"type":"Point"}
}