{
  "id": 7376512,
  "type": "Feature",
  "properties": {
    "tgn:hierarchy":[
        "tgn:7376512",
        "tgn:1001853",
        "tgn:1000001",
        "tgn:7005560",
        "tgn:7029392"
    ],
    "tgn:id":7376512,
    "tgn:name":"Las Lajitas",
    "tgn:placetype":[
        "aat:300008347"
    ]
},
  "bbox": [],
  "geometry": {"coordinates":[-100.416667,28.533333],"type":"Point"}
}