{
  "id": 2295450,
  "type": "Feature",
  "properties": {
    "tgn:hierarchy":[
        "tgn:2295450",
        "tgn:7002659",
        "tgn:1000001",
        "tgn:7012149",
        "tgn:2000036",
        "tgn:7029392"
    ],
    "tgn:id":2295450,
    "tgn:name":"Drip Spring Hollow",
    "tgn:placetype":[
        "aat:300008761"
    ]
},
  "bbox": [],
  "geometry": {"coordinates":[-87.15,33.5167],"type":"Point"}
}