{
  "id": 2021279,
  "type": "Feature",
  "properties": {
    "tgn:hierarchy":[
        "tgn:2021279",
        "tgn:1000001",
        "tgn:1009159",
        "tgn:7012149",
        "tgn:1002870",
        "tgn:7007240",
        "tgn:7029392"
    ],
    "tgn:id":2021279,
    "tgn:name":"Siesta Key",
    "tgn:placetype":[
        "aat:300008347"
    ]
},
  "bbox": [],
  "geometry": {"coordinates":[-82.5667,27.3167],"type":"Point"}
}