<<<<<<< HEAD
{
  "id": 7378755,
  "type": "Feature",
  "properties": {
    "tgn:hierarchy":[
        "tgn:7378755",
        "tgn:1000001",
        "tgn:1001960",
        "tgn:7005560",
        "tgn:7029392"
    ],
    "tgn:id":7378755,
    "tgn:name":"Rancho Los Pozos",
    "tgn:placetype":[
        "aat:300000241"
    ]
},
  "bbox": [],
  "geometry": {"coordinates":[-112.016667,31.5],"type":"Point"}
}
=======
{"geometry":{"type":"Point","coordinates":[-112.016667,31.500000]},"type":"Feature","properties":{"hierarchy":["tgn:7378755","tgn:1000001","tgn:1001960","tgn:7005560","tgn:7029392"],"placetype":["aat:300000241"],"id":7378755,"name:xx":"Rancho Los Pozos"}}
>>>>>>> 03f74aca74312dbeaf24d7e61306dd6a786dc3d0
