{
  "id": 7122078,
  "type": "Feature",
  "properties": {
    "tgn:hierarchy":[
        "tgn:7122078",
        "tgn:1000003",
        "tgn:7003676",
        "tgn:7000084",
        "tgn:7029392"
    ],
    "tgn:id":7122078,
    "tgn:name":"Neu Wittorf",
    "tgn:placetype":[
        "aat:300000206"
    ]
},
  "bbox": [],
  "geometry": {"coordinates":[10.35,53.333333],"type":"Point"}
}