{
  "id": 7136369,
  "type": "Feature",
  "properties": {
    "tgn:hierarchy":[
        "tgn:7136369",
        "tgn:1000003",
        "tgn:7003676",
        "tgn:7000084",
        "tgn:7029392"
    ],
    "tgn:id":7136369,
    "tgn:name":"M\u00fchlen-Berg",
    "tgn:placetype":[
        "aat:300008777"
    ]
},
  "bbox": [],
  "geometry": {"coordinates":[9.866667,51.866667],"type":"Point"}
}