{
  "id": 2056364,
  "type": "Feature",
  "properties": {
    "tgn:hierarchy":[
        "tgn:2056364",
        "tgn:1000001",
        "tgn:7012149",
        "tgn:2001158",
        "tgn:7007522",
        "tgn:7029392"
    ],
    "tgn:id":2056364,
    "tgn:name":"Ellistown",
    "tgn:placetype":[
        "aat:300008347"
    ]
},
  "bbox": [],
  "geometry": {"coordinates":[-88.8333,34.4333],"type":"Point"}
}