{
  "id": 2684114,
  "type": "Feature",
  "properties": {
    "tgn:hierarchy":[
        "tgn:2684114",
        "tgn:1000001",
        "tgn:1002260",
        "tgn:7012149",
        "tgn:7007920",
        "tgn:7029392"
    ],
    "tgn:id":2684114,
    "tgn:name":"Spencer Lake",
    "tgn:placetype":[
        "aat:300008680"
    ]
},
  "bbox": [],
  "geometry": {"coordinates":[-120.25,47.6167],"type":"Point"}
}