{
  "id": 2745683,
  "type": "Feature",
  "properties": {
    "tgn:hierarchy":[
        "tgn:2745683",
        "tgn:1002159",
        "tgn:1000001",
        "tgn:7012149",
        "tgn:7007706",
        "tgn:7029392"
    ],
    "tgn:id":2745683,
    "tgn:name":"Virginia Creek",
    "tgn:placetype":[
        "aat:300008706"
    ]
},
  "bbox": [],
  "geometry": {"coordinates":[-84.0167,40.5833],"type":"Point"}
}