{
  "id": 7089785,
  "type": "Feature",
  "properties": {
    "tgn:hierarchy":[
        "tgn:7089785",
        "tgn:7003669",
        "tgn:1000003",
        "tgn:7000084",
        "tgn:7029392"
    ],
    "tgn:id":7089785,
    "tgn:name":"V\u00f6lkersleier",
    "tgn:placetype":[
        "aat:300008347"
    ]
},
  "bbox": [],
  "geometry": {"coordinates":[9.783333,50.183333],"type":"Point"}
}