{
  "id": 2180565,
  "type": "Feature",
  "properties": {
    "tgn:hierarchy":[
        "tgn:2180565",
        "tgn:1000001",
        "tgn:7012149",
        "tgn:2001461",
        "tgn:7007568",
        "tgn:7029392"
    ],
    "tgn:id":2180565,
    "tgn:name":"Bloody Pond",
    "tgn:placetype":[
        "aat:300008680"
    ]
},
  "bbox": [],
  "geometry": {"coordinates":[-73.6167,43.9833],"type":"Point"}
}