<<<<<<< HEAD
{
  "id": 7357727,
  "type": "Feature",
  "properties": {
    "tgn:hierarchy":[
        "tgn:7357727",
        "tgn:1000001",
        "tgn:7005595",
        "tgn:7005560",
        "tgn:7029392"
    ],
    "tgn:id":7357727,
    "tgn:name":"Ejido Ingeniero Luis V\u00e9lez",
    "tgn:placetype":[
        "aat:300008347"
    ]
},
  "bbox": [],
  "geometry": {"coordinates":[-107.610278,24.665],"type":"Point"}
}
=======
{"geometry":{"type":"Point","coordinates":[-107.610278,24.665000]},"type":"Feature","properties":{"hierarchy":["tgn:7357727","tgn:1000001","tgn:7005595","tgn:7005560","tgn:7029392"],"placetype":["aat:300008347"],"id":7357727,"name:xx":"Ejido Ingeniero Luis V\u00e9lez"}}
>>>>>>> 03f74aca74312dbeaf24d7e61306dd6a786dc3d0
