{
  "id": 7502382,
  "type": "Feature",
  "properties": {
    "tgn:hierarchy":[
        "tgn:7502382",
        "tgn:7001004",
        "tgn:1000004",
        "tgn:1000141",
        "tgn:7029392"
    ],
    "tgn:id":7502382,
    "tgn:name":"Shangmaocao Shan",
    "tgn:placetype":[
        "aat:300008777"
    ]
},
  "bbox": [],
  "geometry": {"coordinates":[120.398333,22.911667],"type":"Point"}
}