<<<<<<< HEAD
{
  "id": 2331410,
  "type": "Feature",
  "properties": {
    "tgn:hierarchy":[
        "tgn:2331410",
        "tgn:1000001",
        "tgn:7012149",
        "tgn:7007826",
        "tgn:7029392"
    ],
    "tgn:id":2331410,
    "tgn:name":"Flatrock Creek",
    "tgn:placetype":[
        "aat:300008706"
    ]
},
  "bbox": [],
  "geometry": {"coordinates":[-98.3,30.4333],"type":"Point"}
}
=======
{"geometry":{"type":"Point","coordinates":[-98.300000,30.433300]},"type":"Feature","properties":{"hierarchy":["tgn:2331410","tgn:1000001","tgn:7012149","tgn:7007826","tgn:7029392"],"placetype":["aat:300008706"],"id":2331410,"name:xx":"Flatrock Creek"}}
>>>>>>> 03f74aca74312dbeaf24d7e61306dd6a786dc3d0
