{
  "id": 2342175,
  "type": "Feature",
  "properties": {
    "tgn:hierarchy":[
        "tgn:2342175",
        "tgn:1000001",
        "tgn:7006451",
        "tgn:2000092",
        "tgn:7012149",
        "tgn:7029392"
    ],
    "tgn:id":2342175,
    "tgn:name":"Fues Spring",
    "tgn:placetype":[
        "aat:300008697"
    ]
},
  "bbox": [],
  "geometry": {"coordinates":[-112.1333,35.2833],"type":"Point"}
}