{
  "id": 2073900,
  "type": "Feature",
  "properties": {
    "tgn:hierarchy":[
        "tgn:2073900",
        "tgn:1000001",
        "tgn:7012149",
        "tgn:2001530",
        "tgn:7007709",
        "tgn:7029392"
    ],
    "tgn:id":2073900,
    "tgn:name":"California",
    "tgn:placetype":[
        "aat:300008347",
        "aat:300387210"
    ]
},
  "bbox": [],
  "geometry": {"coordinates":[-77.55,35.6167],"type":"Point"}
}