{
  "id": 2495652,
  "type": "Feature",
  "properties": {
    "tgn:hierarchy":[
        "tgn:2495652",
        "tgn:1000001",
        "tgn:1002949",
        "tgn:7012149",
        "tgn:7007159",
        "tgn:7029392"
    ],
    "tgn:id":2495652,
    "tgn:name":"Mashapaug Pond",
    "tgn:placetype":[
        "aat:300008680"
    ]
},
  "bbox": [],
  "geometry": {"coordinates":[-72.1167,42.0167],"type":"Point"}
}