<<<<<<< HEAD
{
  "id": 2331350,
  "type": "Feature",
  "properties": {
    "tgn:hierarchy":[
        "tgn:2331350",
        "tgn:1000001",
        "tgn:2000921",
        "tgn:7012149",
        "tgn:7007515",
        "tgn:7029392"
    ],
    "tgn:id":2331350,
    "tgn:name":"Flatiron Pond",
    "tgn:placetype":[
        "aat:300008680"
    ]
},
  "bbox": [],
  "geometry": {"coordinates":[-70.6833,45.0667],"type":"Point"}
}
=======
{"geometry":{"type":"Point","coordinates":[-70.683300,45.066700]},"type":"Feature","properties":{"hierarchy":["tgn:2331350","tgn:1000001","tgn:2000921","tgn:7012149","tgn:7007515","tgn:7029392"],"placetype":["aat:300008680"],"id":2331350,"name:xx":"Flatiron Pond"}}
>>>>>>> 03f74aca74312dbeaf24d7e61306dd6a786dc3d0
