<<<<<<< HEAD
{
  "id": 2409115,
  "type": "Feature",
  "properties": {
    "tgn:hierarchy":[
        "tgn:2409115",
        "tgn:1000001",
        "tgn:7012149",
        "tgn:2001615",
        "tgn:7007706",
        "tgn:7029392"
    ],
    "tgn:id":2409115,
    "tgn:name":"Ice Creek",
    "tgn:placetype":[
        "aat:300008706"
    ]
},
  "bbox": [],
  "geometry": {"coordinates":[-82.5167,38.5667],"type":"Point"}
}
=======
{"geometry":{"type":"Point","coordinates":[-82.516700,38.566700]},"type":"Feature","properties":{"hierarchy":["tgn:2409115","tgn:1000001","tgn:7012149","tgn:2001615","tgn:7007706","tgn:7029392"],"placetype":["aat:300008706"],"id":2409115,"name:xx":"Ice Creek"}}
>>>>>>> 03f74aca74312dbeaf24d7e61306dd6a786dc3d0
