{
  "id": 2370200,
  "type": "Feature",
  "properties": {
    "tgn:hierarchy":[
        "tgn:2370200",
        "tgn:2001001",
        "tgn:1000001",
        "tgn:7012149",
        "tgn:7007521",
        "tgn:7029392"
    ],
    "tgn:id":2370200,
    "tgn:name":"Gyles Lake",
    "tgn:placetype":[
        "aat:300008680"
    ]
},
  "bbox": [],
  "geometry": {"coordinates":[-95.3167,46.9167],"type":"Point"}
}