{
  "id": 2456692,
  "type": "Feature",
  "properties": {
    "tgn:hierarchy":[
        "tgn:2456692",
        "tgn:1000001",
        "tgn:7012149",
        "tgn:2001918",
        "tgn:7007825",
        "tgn:7029392"
    ],
    "tgn:id":2456692,
    "tgn:name":"Little Jacob Creek",
    "tgn:placetype":[
        "aat:300008706"
    ]
},
  "bbox": [],
  "geometry": {"coordinates":[-81.9333,36.5333],"type":"Point"}
}