{
  "id": 7289696,
  "type": "Feature",
  "properties": {
    "tgn:hierarchy":[
        "tgn:7289696",
        "tgn:1001708",
        "tgn:1000049",
        "tgn:1000002",
        "tgn:7029392"
    ],
    "tgn:id":7289696,
    "tgn:name":"El Manzano, Estero",
    "tgn:placetype":[
        "aat:300008699"
    ]
},
  "bbox": [],
  "geometry": {"coordinates":[-71.433333,-34.15],"type":"Point"}
}