{
  "id": 2234167,
  "type": "Feature",
  "properties": {
    "tgn:hierarchy":[
        "tgn:2234167",
        "tgn:1000001",
        "tgn:7012149",
        "tgn:7019676",
        "tgn:7007566",
        "tgn:7029392"
    ],
    "tgn:id":2234167,
    "tgn:name":"Chees Hollow",
    "tgn:placetype":[
        "aat:300008761"
    ]
},
  "bbox": [],
  "geometry": {"coordinates":[-108.5167,35.15],"type":"Point"}
}