{
  "id": 2612222,
  "type": "Feature",
  "properties": {
    "tgn:hierarchy":[
        "tgn:2612222",
        "tgn:1000001",
        "tgn:7012149",
        "tgn:2001282",
        "tgn:7007524",
        "tgn:7029392"
    ],
    "tgn:id":2612222,
    "tgn:name":"Red Shed Lake",
    "tgn:placetype":[
        "aat:300008680"
    ]
},
  "bbox": [],
  "geometry": {"coordinates":[-110.0833,46.9833],"type":"Point"}
}