<<<<<<< HEAD
{
  "id": 2259999,
  "type": "Feature",
  "properties": {
    "tgn:hierarchy":[
        "tgn:2259999",
        "tgn:1000001",
        "tgn:7012149",
        "tgn:1002392",
        "tgn:7007157",
        "tgn:7029392"
    ],
    "tgn:id":2259999,
    "tgn:name":"Council Lake",
    "tgn:placetype":[
        "aat:300008680"
    ]
},
  "bbox": [],
  "geometry": {"coordinates":[-118.8,37.2833],"type":"Point"}
}
=======
{"geometry":{"type":"Point","coordinates":[-118.800000,37.283300]},"type":"Feature","properties":{"hierarchy":["tgn:2259999","tgn:1000001","tgn:7012149","tgn:1002392","tgn:7007157","tgn:7029392"],"placetype":["aat:300008680"],"id":2259999,"name:xx":"Council Lake"}}
>>>>>>> 03f74aca74312dbeaf24d7e61306dd6a786dc3d0
