{
  "id": 1110508,
  "type": "Feature",
  "properties": {
    "tgn:hierarchy":[
        "tgn:1110508",
        "tgn:7001242",
        "tgn:7029392"
    ],
    "tgn:id":1110508,
    "tgn:name":"Kuruman-Heuwels",
    "tgn:placetype":[
        "aat:300008777"
    ]
},
  "bbox": [],
  "geometry": {"coordinates":[23.4333,-27.5833],"type":"Point"}
}