{
  "id": 7334375,
  "type": "Feature",
  "properties": {
    "tgn:hierarchy":[
        "tgn:7334375",
        "tgn:1001439",
        "tgn:1000003",
        "tgn:7002797",
        "tgn:1000095",
        "tgn:7029392"
    ],
    "tgn:id":7334375,
    "tgn:name":"Hormig\u00f3n, Islote",
    "tgn:placetype":[
        "aat:300008791"
    ]
},
  "bbox": [],
  "geometry": {"coordinates":[-0.65,37.65],"type":"Point"}
}