{
  "id": 7383256,
  "type": "Feature",
  "properties": {
    "tgn:hierarchy":[
        "tgn:7383256",
        "tgn:1000001",
        "tgn:7005599",
        "tgn:7005560",
        "tgn:7029392"
    ],
    "tgn:id":7383256,
    "tgn:name":"Panga",
    "tgn:placetype":[
        "aat:300387007"
    ]
},
  "bbox": [],
  "geometry": {"coordinates":[-97.816667,22.183333],"type":"Point"}
}