{
  "id": 2045131,
  "type": "Feature",
  "properties": {
    "tgn:hierarchy":[
        "tgn:2045131",
        "tgn:1000001",
        "tgn:7012149",
        "tgn:7014589",
        "tgn:7007515",
        "tgn:7029392"
    ],
    "tgn:id":2045131,
    "tgn:name":"Marion",
    "tgn:placetype":[
        "aat:300008347",
        "aat:300387210"
    ]
},
  "bbox": [],
  "geometry": {"coordinates":[-67.3167,44.8667],"type":"Point"}
}