{
  "id": 2418283,
  "type": "Feature",
  "properties": {
    "tgn:hierarchy":[
        "tgn:2418283",
        "tgn:1000001",
        "tgn:7012149",
        "tgn:1002516",
        "tgn:7007255",
        "tgn:7029392"
    ],
    "tgn:id":2418283,
    "tgn:name":"Jacobs Addition",
    "tgn:placetype":[
        "aat:300008347"
    ]
},
  "bbox": [],
  "geometry": {"coordinates":[-85.7833,38.1833],"type":"Point"}
}