{
  "id": 7561987,
  "type": "Feature",
  "properties": {
    "tgn:hierarchy":[
        "tgn:7561987",
        "tgn:1000004",
        "tgn:7000198",
        "tgn:7016722",
        "tgn:7029392"
    ],
    "tgn:id":7561987,
    "tgn:name:en":"Nagaria Kh\u0101nu",
    "tgn:placetype":[
        "aat:300008347"
    ]
},
  "bbox": [],
  "geometry": {"coordinates":[79.452387,27.940797],"type":"Point"}
}