{
  "id": 7286529,
  "type": "Feature",
  "properties": {
    "tgn:hierarchy":[
        "tgn:7286529",
        "tgn:1001623",
        "tgn:1000049",
        "tgn:1000002",
        "tgn:7029392"
    ],
    "tgn:id":7286529,
    "tgn:name":"Harchy, Punta",
    "tgn:placetype":[
        "aat:300386846"
    ]
},
  "bbox": [],
  "geometry": {"coordinates":[-73.883333,-45.716667],"type":"Point"}
}