{
  "id": 7457882,
  "type": "Feature",
  "properties": {
    "tgn:hierarchy":[
        "tgn:7457882",
        "tgn:7002445",
        "tgn:1000003",
        "tgn:5000748",
        "tgn:7008591",
        "tgn:7029392"
    ],
    "tgn:id":7457882,
    "tgn:name:en":"Normanton Park",
    "tgn:placetype":[
        "aat:300387502"
    ]
},
  "bbox": [],
  "geometry": {"coordinates":[-0.616667,52.633333],"type":"Point"}
}