<<<<<<< HEAD
{
  "id": 7358622,
  "type": "Feature",
  "properties": {
    "tgn:hierarchy":[
        "tgn:7358622",
        "tgn:7005583",
        "tgn:1000001",
        "tgn:7005560",
        "tgn:7029392"
    ],
    "tgn:id":7358622,
    "tgn:name":"Ejido Vencedores",
    "tgn:placetype":[
        "aat:300008347"
    ]
},
  "bbox": [],
  "geometry": {"coordinates":[-105.7,24.416667],"type":"Point"}
}
=======
{"geometry":{"type":"Point","coordinates":[-105.700000,24.416667]},"type":"Feature","properties":{"hierarchy":["tgn:7358622","tgn:7005583","tgn:1000001","tgn:7005560","tgn:7029392"],"placetype":["aat:300008347"],"id":7358622,"name:xx":"Ejido Vencedores"}}
>>>>>>> 03f74aca74312dbeaf24d7e61306dd6a786dc3d0
