{
  "id": 7402138,
  "type": "Feature",
  "properties": {
    "tgn:hierarchy":[
        "tgn:7402138",
        "tgn:1000001",
        "tgn:7005600",
        "tgn:7005560",
        "tgn:7029392"
    ],
    "tgn:id":7402138,
    "tgn:name":"Kanakom",
    "tgn:placetype":[
        "aat:300008347"
    ]
},
  "bbox": [],
  "geometry": {"coordinates":[-88.7625,20.445833],"type":"Point"}
}