{
  "id": 7199891,
  "type": "Feature",
  "properties": {
    "tgn:hierarchy":[
        "tgn:7199891",
        "tgn:1000003",
        "tgn:7003687",
        "tgn:7000084",
        "tgn:7029392"
    ],
    "tgn:id":7199891,
    "tgn:name":"Bahnhof Drei Annen Hohne",
    "tgn:placetype":[
        "aat:300007783"
    ]
},
  "bbox": [],
  "geometry": {"coordinates":[10.727222,51.77],"type":"Point"}
}