<<<<<<< HEAD
{
  "id": 7477843,
  "type": "Feature",
  "properties": {
    "tgn:hierarchy":[
        "tgn:7477843",
        "tgn:1000004",
        "tgn:1000454",
        "tgn:1000141",
        "tgn:7029392"
    ],
    "tgn:id":7477843,
    "tgn:name":"Nanya Shan",
    "tgn:placetype":[
        "aat:300008798"
    ]
},
  "bbox": [],
  "geometry": {"coordinates":[121.899802,25.113822],"type":"Point"}
}
=======
{"geometry":{"type":"Point","coordinates":[121.899802,25.113822]},"type":"Feature","properties":{"hierarchy":["tgn:7477843","tgn:1000004","tgn:1000454","tgn:1000141","tgn:7029392"],"placetype":["aat:300008798"],"id":7477843,"name:xx":"Nanya Shan"}}
>>>>>>> 03f74aca74312dbeaf24d7e61306dd6a786dc3d0
