{
  "id": 7497899,
  "type": "Feature",
  "properties": {
    "tgn:hierarchy":[
        "tgn:7497899",
        "tgn:1000957",
        "tgn:1000004",
        "tgn:1000141",
        "tgn:7029392"
    ],
    "tgn:id":7497899,
    "tgn:name":"Changlan Qiao",
    "tgn:placetype":[
        "aat:300007836"
    ]
},
  "bbox": [],
  "geometry": {"coordinates":[121.688555,25.111224],"type":"Point"}
}