{
  "id": 7431925,
  "type": "Feature",
  "properties": {
    "tgn:hierarchy":[
        "tgn:7431925",
        "tgn:1000001",
        "tgn:7005595",
        "tgn:7005560",
        "tgn:7029392"
    ],
    "tgn:id":7431925,
    "tgn:name":"Tabl\u00f3n",
    "tgn:placetype":[
        "aat:300008347"
    ]
},
  "bbox": [],
  "geometry": {"coordinates":[-105.975,23.083333],"type":"Point"}
}