{
  "id": 7376340,
  "type": "Feature",
  "properties": {
    "tgn:hierarchy":[
        "tgn:7376340",
        "tgn:7005583",
        "tgn:1000001",
        "tgn:7005560",
        "tgn:7029392"
    ],
    "tgn:id":7376340,
    "tgn:name":"Rancho La Tajada",
    "tgn:placetype":[
        "aat:300000241"
    ]
},
  "bbox": [],
  "geometry": {"coordinates":[-104.616667,25.483333],"type":"Point"}
}