{
  "id": 7004125,
  "type": "Feature",
  "properties": {
    "tgn:hierarchy":[
        "tgn:7004125",
        "tgn:1000003",
        "tgn:7004126",
        "tgn:1000091",
        "tgn:7029392"
    ],
    "tgn:id":7004125,
    "tgn:name":"Deva",
    "tgn:placetype":[
        "aat:300008347",
        "aat:300008416",
        "aat:300008389",
        "aat:300387308"
    ]
},
  "bbox": [],
  "geometry": {"coordinates":[22.9167,45.8833],"type":"Point"}
}