{
  "id": 7390667,
  "type": "Feature",
  "properties": {
    "tgn:hierarchy":[
        "tgn:7390667",
        "tgn:1001853",
        "tgn:1000001",
        "tgn:7005560",
        "tgn:7029392"
    ],
    "tgn:id":7390667,
    "tgn:name":"Rancho San Isidro",
    "tgn:placetype":[
        "aat:300008347"
    ]
},
  "bbox": [],
  "geometry": {"coordinates":[-100.716667,25.283333],"type":"Point"}
}