{
  "id": 7494863,
  "type": "Feature",
  "properties": {
    "tgn:hierarchy":[
        "tgn:7494863",
        "tgn:7487020",
        "tgn:1000004",
        "tgn:1000141",
        "tgn:7029392"
    ],
    "tgn:id":7494863,
    "tgn:name":"Zhongxing Guoxiao",
    "tgn:placetype":[
        "aat:300006495"
    ]
},
  "bbox": [],
  "geometry": {"coordinates":[120.809595,24.497381],"type":"Point"}
}