{
  "id": 2009659,
  "type": "Feature",
  "properties": {
    "tgn:hierarchy":[
        "tgn:2009659",
        "tgn:1000001",
        "tgn:7016172",
        "tgn:7012149",
        "tgn:2000125",
        "tgn:7029392"
    ],
    "tgn:id":2009659,
    "tgn:name":"Trippe Junction",
    "tgn:placetype":[
        "aat:300387016"
    ]
},
  "bbox": [],
  "geometry": {"coordinates":[-91.3333,33.5833],"type":"Point"}
}