{
  "id": 7312035,
  "type": "Feature",
  "properties": {
    "tgn:hierarchy":[
        "tgn:7312035",
        "tgn:1001705",
        "tgn:1000049",
        "tgn:1000002",
        "tgn:7029392"
    ],
    "tgn:id":7312035,
    "tgn:name":"Las Damas",
    "tgn:placetype":[
        "aat:300000206"
    ]
},
  "bbox": [],
  "geometry": {"coordinates":[-71.416667,-35.266667],"type":"Point"}
}