{
  "id": 7070953,
  "type": "Feature",
  "properties": {
    "tgn:hierarchy":[
        "tgn:7070953",
        "tgn:7003669",
        "tgn:1000003",
        "tgn:7000084",
        "tgn:7029392"
    ],
    "tgn:id":7070953,
    "tgn:name":"Stumpf\u00f6d",
    "tgn:placetype":[
        "aat:300000206"
    ]
},
  "bbox": [],
  "geometry": {"coordinates":[12.083333,48.866667],"type":"Point"}
}