{
  "id": 7164293,
  "type": "Feature",
  "properties": {
    "tgn:hierarchy":[
        "tgn:7164293",
        "tgn:1000003",
        "tgn:7003682",
        "tgn:7000084",
        "tgn:7029392"
    ],
    "tgn:id":7164293,
    "tgn:name":"Hunnen-Berg",
    "tgn:placetype":[
        "aat:300008777"
    ]
},
  "bbox": [],
  "geometry": {"coordinates":[6.55,49.783333],"type":"Point"}
}