{
  "id": 7478882,
  "type": "Feature",
  "properties": {
    "tgn:hierarchy":[
        "tgn:7478882",
        "tgn:7487020",
        "tgn:1000004",
        "tgn:1000141",
        "tgn:7029392"
    ],
    "tgn:id":7478882,
    "tgn:name":"Yongshan Qiao",
    "tgn:placetype":[
        "aat:300007836"
    ]
},
  "bbox": [],
  "geometry": {"coordinates":[120.933774,24.558039],"type":"Point"}
}