<<<<<<< HEAD
{
  "id": 2252450,
  "type": "Feature",
  "properties": {
    "tgn:hierarchy":[
        "tgn:2252450",
        "tgn:1000001",
        "tgn:7012149",
        "tgn:2001449",
        "tgn:7007566",
        "tgn:7029392"
    ],
    "tgn:id":2252450,
    "tgn:name":"Conjilon Tank",
    "tgn:placetype":[
        "aat:300006191"
    ]
},
  "bbox": [],
  "geometry": {"coordinates":[-106.4,36.4833],"type":"Point"}
}
=======
{"geometry":{"type":"Point","coordinates":[-106.400000,36.483300]},"type":"Feature","properties":{"hierarchy":["tgn:2252450","tgn:1000001","tgn:7012149","tgn:2001449","tgn:7007566","tgn:7029392"],"placetype":["aat:300006191"],"id":2252450,"name:xx":"Conjilon Tank"}}
>>>>>>> 03f74aca74312dbeaf24d7e61306dd6a786dc3d0
