{
  "id": 7498783,
  "type": "Feature",
  "properties": {
    "tgn:hierarchy":[
        "tgn:7498783",
        "tgn:1000004",
        "tgn:7001009",
        "tgn:1000141",
        "tgn:7029392"
    ],
    "tgn:id":7498783,
    "tgn:name":"Fentou",
    "tgn:placetype":[
        "aat:300008347"
    ]
},
  "bbox": [],
  "geometry": {"coordinates":[120.544094,24.230206],"type":"Point"}
}