{
  "id": 7500892,
  "type": "Feature",
  "properties": {
    "tgn:hierarchy":[
        "tgn:7500892",
        "tgn:7001004",
        "tgn:1000004",
        "tgn:1000141",
        "tgn:7029392"
    ],
    "tgn:id":7500892,
    "tgn:name":"Xiabuwei",
    "tgn:placetype":[
        "aat:300008347"
    ]
},
  "bbox": [],
  "geometry": {"coordinates":[120.444167,22.908611],"type":"Point"}
}