{
  "id": 7121647,
  "type": "Feature",
  "properties": {
    "tgn:hierarchy":[
        "tgn:7121647",
        "tgn:1000003",
        "tgn:7003682",
        "tgn:7000084",
        "tgn:7029392"
    ],
    "tgn:id":7121647,
    "tgn:name":"Pfaffen-Bach",
    "tgn:placetype":[
        "aat:300008699"
    ]
},
  "bbox": [],
  "geometry": {"coordinates":[7.416667,50.616667],"type":"Point"}
}