{
  "id": 2704382,
  "type": "Feature",
  "properties": {
    "tgn:hierarchy":[
        "tgn:2704382",
        "tgn:1000001",
        "tgn:7012149",
        "tgn:2000231",
        "tgn:7007158",
        "tgn:7029392"
    ],
    "tgn:id":2704382,
    "tgn:name":"Sunnyside",
    "tgn:placetype":[
        "aat:300008347"
    ]
},
  "bbox": [],
  "geometry": {"coordinates":[-106.95,37.8333],"type":"Point"}
}