{
  "id": 2025278,
  "type": "Feature",
  "properties": {
    "tgn:hierarchy":[
        "tgn:2025278",
        "tgn:1002648",
        "tgn:1000001",
        "tgn:7019158",
        "tgn:7012149",
        "tgn:7007249",
        "tgn:7029392"
    ],
    "tgn:id":2025278,
    "tgn:name":"Waiehu",
    "tgn:placetype":[
        "aat:300008347"
    ]
},
  "bbox": [],
  "geometry": {"coordinates":[-156.5333,20.9167],"type":"Point"}
}