{
  "id": 2175319,
  "type": "Feature",
  "properties": {
    "tgn:hierarchy":[
        "tgn:2175319",
        "tgn:1000001",
        "tgn:2001412",
        "tgn:7012149",
        "tgn:7007526",
        "tgn:7029392"
    ],
    "tgn:id":2175319,
    "tgn:name":"Black Butte",
    "tgn:placetype":[
        "aat:300008798"
    ]
},
  "bbox": [],
  "geometry": {"coordinates":[-117.1667,37.75],"type":"Point"}
}