{
  "id": 7045126,
  "type": "Feature",
  "properties": {
    "tgn:hierarchy":[
        "tgn:7045126",
        "tgn:7003170",
        "tgn:1000003",
        "tgn:7003125",
        "tgn:1000080",
        "tgn:7029392"
    ],
    "tgn:id":7045126,
    "tgn:name":"Corno, Fiume",
    "tgn:placetype":[
        "aat:300008699"
    ]
},
  "bbox": [],
  "geometry": {"coordinates":[12.916667,42.816667],"type":"Point"}
}