{
  "id": 7577663,
  "type": "Feature",
  "properties": {
    "tgn:hierarchy":[
        "tgn:7577663",
        "tgn:1000004",
        "tgn:7000198",
        "tgn:7001797",
        "tgn:7029392"
    ],
    "tgn:id":7577663,
    "tgn:name:en":"Karungulam",
    "tgn:placetype":[
        "aat:300008347"
    ]
},
  "bbox": [],
  "geometry": {"coordinates":[77.583333,8.166667],"type":"Point"}
}