{
  "id": 7357256,
  "type": "Feature",
  "properties": {
    "tgn:hierarchy":[
        "tgn:7357256",
        "tgn:1000001",
        "tgn:7005595",
        "tgn:7005560",
        "tgn:7029392"
    ],
    "tgn:id":7357256,
    "tgn:name":"Campo San Francisco",
    "tgn:placetype":[
        "aat:300008347"
    ]
},
  "bbox": [],
  "geometry": {"coordinates":[-107.568889,24.660278],"type":"Point"}
}