{
  "id": 2489407,
  "type": "Feature",
  "properties": {
    "tgn:hierarchy":[
        "tgn:2489407",
        "tgn:1000001",
        "tgn:7012149",
        "tgn:7019676",
        "tgn:7007566",
        "tgn:7029392"
    ],
    "tgn:id":2489407,
    "tgn:name":"Malcom Tank",
    "tgn:placetype":[
        "aat:300006191"
    ]
},
  "bbox": [],
  "geometry": {"coordinates":[-108.55,35.35],"type":"Point"}
}