{
  "id": 2507335,
  "type": "Feature",
  "properties": {
    "tgn:hierarchy":[
        "tgn:2507335",
        "tgn:2000090",
        "tgn:1000001",
        "tgn:7006451",
        "tgn:7012149",
        "tgn:7029392"
    ],
    "tgn:id":2507335,
    "tgn:name":"Mexican Hay Lake",
    "tgn:placetype":[
        "aat:300006191"
    ]
},
  "bbox": [],
  "geometry": {"coordinates":[-109.35,34.0333],"type":"Point"}
}