{
  "id": 2348475,
  "type": "Feature",
  "properties": {
    "tgn:hierarchy":[
        "tgn:2348475",
        "tgn:2000001",
        "tgn:7002659",
        "tgn:1000001",
        "tgn:7012149",
        "tgn:7029392"
    ],
    "tgn:id":2348475,
    "tgn:name":"Gibbons Branch",
    "tgn:placetype":[
        "aat:300008699"
    ]
},
  "bbox": [],
  "geometry": {"coordinates":[-87.4667,30.5833],"type":"Point"}
}