{
  "id": 7345642,
  "type": "Feature",
  "properties": {
    "tgn:hierarchy":[
        "tgn:7345642",
        "tgn:7002806",
        "tgn:7001158",
        "tgn:1000003",
        "tgn:1000095",
        "tgn:7029392"
    ],
    "tgn:id":7345642,
    "tgn:name":"Aldeaseca",
    "tgn:placetype":[
        "aat:300008347"
    ]
},
  "bbox": [],
  "geometry": {"coordinates":[-4.816667,41.05],"type":"Point"}
}