{
  "id": 7291286,
  "type": "Feature",
  "properties": {
    "tgn:hierarchy":[
        "tgn:7291286",
        "tgn:1001768",
        "tgn:1000049",
        "tgn:1000002",
        "tgn:7029392"
    ],
    "tgn:id":7291286,
    "tgn:name":"El Maitencillo",
    "tgn:placetype":[
        "aat:300008798"
    ]
},
  "bbox": [],
  "geometry": {"coordinates":[-71.066667,-32.65],"type":"Point"}
}