<<<<<<< HEAD
{
  "id": 7488659,
  "type": "Feature",
  "properties": {
    "tgn:hierarchy":[
        "tgn:7488659",
        "tgn:7488858",
        "tgn:1000004",
        "tgn:1000141",
        "tgn:7029392"
    ],
    "tgn:id":7488659,
    "tgn:name":"Nanshizi",
    "tgn:placetype":[
        "aat:300008347"
    ]
},
  "bbox": [],
  "geometry": {"coordinates":[120.669115,23.989471],"type":"Point"}
}
=======
{"geometry":{"type":"Point","coordinates":[120.669115,23.989471]},"type":"Feature","properties":{"hierarchy":["tgn:7488659","tgn:7488858","tgn:1000004","tgn:1000141","tgn:7029392"],"placetype":["aat:300008347"],"id":7488659,"name:xx":"Nanshizi"}}
>>>>>>> 03f74aca74312dbeaf24d7e61306dd6a786dc3d0
