{
  "id": 7488659,
  "type": "Feature",
  "properties": {
    "tgn:hierarchy":[
        "tgn:7488659",
        "tgn:7488858",
        "tgn:1000004",
        "tgn:1000141",
        "tgn:7029392"
    ],
    "tgn:id":7488659,
    "tgn:name":"Nanshizi",
    "tgn:placetype":[
        "aat:300008347"
    ]
},
  "bbox": [],
  "geometry": {"coordinates":[120.669115,23.989471],"type":"Point"}
}