{
  "id": 2676672,
  "type": "Feature",
  "properties": {
    "tgn:hierarchy":[
        "tgn:2676672",
        "tgn:1000001",
        "tgn:7012149",
        "tgn:2001067",
        "tgn:7007521",
        "tgn:7029392"
    ],
    "tgn:id":2676672,
    "tgn:name":"South Bog Lake",
    "tgn:placetype":[
        "aat:300008680"
    ]
},
  "bbox": [],
  "geometry": {"coordinates":[-92.75,48.1333],"type":"Point"}
}