<<<<<<< HEAD
{
  "id": 2332585,
  "type": "Feature",
  "properties": {
    "tgn:hierarchy":[
        "tgn:2332585",
        "tgn:1000001",
        "tgn:7012149",
        "tgn:2001878",
        "tgn:7007825",
        "tgn:7029392"
    ],
    "tgn:id":2332585,
    "tgn:name":"Florida Hollow",
    "tgn:placetype":[
        "aat:300008761"
    ]
},
  "bbox": [],
  "geometry": {"coordinates":[-87.8667,36.2333],"type":"Point"}
}
=======
{"geometry":{"type":"Point","coordinates":[-87.866700,36.233300]},"type":"Feature","properties":{"hierarchy":["tgn:2332585","tgn:1000001","tgn:7012149","tgn:2001878","tgn:7007825","tgn:7029392"],"placetype":["aat:300008761"],"id":2332585,"name:xx":"Florida Hollow"}}
>>>>>>> 03f74aca74312dbeaf24d7e61306dd6a786dc3d0
