<<<<<<< HEAD
{
  "id": 2409520,
  "type": "Feature",
  "properties": {
    "tgn:hierarchy":[
        "tgn:2409520",
        "tgn:1000001",
        "tgn:7012149",
        "tgn:1002453",
        "tgn:7007706",
        "tgn:7029392"
    ],
    "tgn:id":2409520,
    "tgn:name":"Idlewild, Lake",
    "tgn:placetype":[
        "aat:300006191"
    ]
},
  "bbox": [],
  "geometry": {"coordinates":[-83.6167,40.6667],"type":"Point"}
}
=======
{"geometry":{"type":"Point","coordinates":[-83.616700,40.666700]},"type":"Feature","properties":{"hierarchy":["tgn:2409520","tgn:1000001","tgn:7012149","tgn:1002453","tgn:7007706","tgn:7029392"],"placetype":["aat:300006191"],"id":2409520,"name:xx":"Idlewild, Lake"}}
>>>>>>> 03f74aca74312dbeaf24d7e61306dd6a786dc3d0
