{
  "id": 1096939,
  "type": "Feature",
  "properties": {
    "tgn:hierarchy":[
        "tgn:1096939",
        "tgn:7000490",
        "tgn:1000006",
        "tgn:7001992",
        "tgn:7029392"
    ],
    "tgn:id":1096939,
    "tgn:name":"Geeveston",
    "tgn:placetype":[
        "aat:300008347"
    ]
},
  "bbox": [],
  "geometry": {"coordinates":[146.8833,-43.1833],"type":"Point"}
}