{
  "id": 7234081,
  "type": "Feature",
  "properties": {
    "tgn:hierarchy":[
        "tgn:7234081",
        "tgn:7002728",
        "tgn:7002715",
        "tgn:1000003",
        "tgn:1000074",
        "tgn:7029392"
    ],
    "tgn:id":7234081,
    "tgn:name":"Akhl\u00e1dha",
    "tgn:placetype":[
        "aat:300008347"
    ]
},
  "bbox": [],
  "geometry": {"coordinates":[21.616667,40.866667],"type":"Point"}
}