{
  "id": 7460892,
  "type": "Feature",
  "properties": {
    "tgn:hierarchy":[
        "tgn:7460892",
        "tgn:7002445",
        "tgn:7026500",
        "tgn:1000003",
        "tgn:7008591",
        "tgn:7029392"
    ],
    "tgn:id":7460892,
    "tgn:name:en":"Holdenhurst",
    "tgn:placetype":[
        "aat:300000745"
    ]
},
  "bbox": [],
  "geometry": {"coordinates":[-1.816667,50.75],"type":"Point"}
}