{
  "id": 2385702,
  "type": "Feature",
  "properties": {
    "tgn:hierarchy":[
        "tgn:2385702",
        "tgn:1000001",
        "tgn:7012149",
        "tgn:2001448",
        "tgn:7007566",
        "tgn:7029392"
    ],
    "tgn:id":2385702,
    "tgn:name":"Hendricks Place",
    "tgn:placetype":[
        "aat:300008347"
    ]
},
  "bbox": [],
  "geometry": {"coordinates":[-103.4833,35.3333],"type":"Point"}
}