{
  "id": 7244650,
  "type": "Feature",
  "properties": {
    "tgn:hierarchy":[
        "tgn:7244650",
        "tgn:7003461",
        "tgn:1000003",
        "tgn:1000063",
        "tgn:7018236",
        "tgn:7029392"
    ],
    "tgn:id":7244650,
    "tgn:name":"Leukeneinde",
    "tgn:placetype":[
        "aat:300008347"
    ]
},
  "bbox": [],
  "geometry": {"coordinates":[5.566667,51.166667],"type":"Point"}
}