{
  "id": 2691915,
  "type": "Feature",
  "properties": {
    "tgn:hierarchy":[
        "tgn:2691915",
        "tgn:1000001",
        "tgn:2002241",
        "tgn:7012149",
        "tgn:7007920",
        "tgn:7029392"
    ],
    "tgn:id":2691915,
    "tgn:name":"Starvout Ridge",
    "tgn:placetype":[
        "aat:300266640"
    ]
},
  "bbox": [],
  "geometry": {"coordinates":[-117.7833,46.3167],"type":"Point"}
}