{
  "id": 2439751,
  "type": "Feature",
  "properties": {
    "tgn:hierarchy":[
        "tgn:2439751",
        "tgn:7002659",
        "tgn:1000001",
        "tgn:7012149",
        "tgn:2000055",
        "tgn:7029392"
    ],
    "tgn:id":2439751,
    "tgn:name":"Kitchen Prospect",
    "tgn:placetype":[
        "aat:300000390"
    ]
},
  "bbox": [],
  "geometry": {"coordinates":[-85.5667,33.4167],"type":"Point"}
}