{
  "id": 7529052,
  "type": "Feature",
  "properties": {
    "tgn:hierarchy":[
        "tgn:7529052",
        "tgn:7001242",
        "tgn:7016833",
        "tgn:1001418",
        "tgn:7029392"
    ],
    "tgn:id":7529052,
    "tgn:name:en":"\u0162agh\u0101gh\u012bn al Fawq\u0101n\u012byah, 'Ayn",
    "tgn:placetype":[
        "aat:300008697"
    ]
},
  "bbox": [],
  "geometry": {"coordinates":[25.466667,29.233333],"type":"Point"}
}