{
  "id": 7337174,
  "type": "Feature",
  "properties": {
    "tgn:hierarchy":[
        "tgn:7337174",
        "tgn:1001439",
        "tgn:1000003",
        "tgn:7002797",
        "tgn:1000095",
        "tgn:7029392"
    ],
    "tgn:id":7337174,
    "tgn:name":"Cocedor, Punta del",
    "tgn:placetype":[
        "aat:300386846"
    ]
},
  "bbox": [],
  "geometry": {"coordinates":[-0.733333,37.75],"type":"Point"}
}