{
  "id": 2517826,
  "type": "Feature",
  "properties": {
    "tgn:hierarchy":[
        "tgn:2517826",
        "tgn:1000001",
        "tgn:7012149",
        "tgn:7018871",
        "tgn:7007920",
        "tgn:7029392"
    ],
    "tgn:id":2517826,
    "tgn:name":"Mirror Lake",
    "tgn:placetype":[
        "aat:300008680"
    ]
},
  "bbox": [],
  "geometry": {"coordinates":[-122.3333,47.3167],"type":"Point"}
}