{
  "id": 7307382,
  "type": "Feature",
  "properties": {
    "tgn:hierarchy":[
        "tgn:7307382",
        "tgn:7002807",
        "tgn:1000003",
        "tgn:7003837",
        "tgn:1000095",
        "tgn:7029392"
    ],
    "tgn:id":7307382,
    "tgn:name":"Madera, Valle de la",
    "tgn:placetype":[
        "aat:300008761"
    ]
},
  "bbox": [],
  "geometry": {"coordinates":[-5.083333,38.75],"type":"Point"}
}