{
  "id": 7593020,
  "type": "Feature",
  "properties": {
    "tgn:hierarchy":[
        "tgn:7593020",
        "tgn:1000004",
        "tgn:7000198",
        "tgn:7000799",
        "tgn:7029392"
    ],
    "tgn:id":7593020,
    "tgn:name:en":"Mangm\u016br",
    "tgn:placetype":[
        "aat:300008347"
    ]
},
  "bbox": [],
  "geometry": {"coordinates":[76.148611,34.561111],"type":"Point"}
}