{
  "id": 2282857,
  "type": "Feature",
  "properties": {
    "tgn:hierarchy":[
        "tgn:2282857",
        "tgn:1000001",
        "tgn:1002240",
        "tgn:7012149",
        "tgn:7007255",
        "tgn:7029392"
    ],
    "tgn:id":2282857,
    "tgn:name":"Deevert",
    "tgn:placetype":[
        "aat:300008347"
    ]
},
  "bbox": [],
  "geometry": {"coordinates":[-83.0333,38.3833],"type":"Point"}
}