{
  "id": 2185653,
  "type": "Feature",
  "properties": {
    "tgn:hierarchy":[
        "tgn:2185653",
        "tgn:1000001",
        "tgn:7012149",
        "tgn:2001880",
        "tgn:7007825",
        "tgn:7029392"
    ],
    "tgn:id":2185653,
    "tgn:name":"Boils, The",
    "tgn:placetype":[
        "aat:300008697"
    ]
},
  "bbox": [],
  "geometry": {"coordinates":[-85.55,36.35],"type":"Point"}
}