{
  "id": 2729412,
  "type": "Feature",
  "properties": {
    "tgn:hierarchy":[
        "tgn:2729412",
        "tgn:1000001",
        "tgn:7012149",
        "tgn:2001723",
        "tgn:7007708",
        "tgn:7029392"
    ],
    "tgn:id":2729412,
    "tgn:name":"Tripp Canyon",
    "tgn:placetype":[
        "aat:300008761"
    ]
},
  "bbox": [],
  "geometry": {"coordinates":[-120.0833,44.9667],"type":"Point"}
}