{
  "id": 2499292,
  "type": "Feature",
  "properties": {
    "tgn:hierarchy":[
        "tgn:2499292",
        "tgn:7006450",
        "tgn:1000001",
        "tgn:7012149",
        "tgn:2124002",
        "tgn:7029392"
    ],
    "tgn:id":2499292,
    "tgn:name":"McClellan Group",
    "tgn:placetype":[
        "aat:300055621"
    ]
},
  "bbox": [],
  "geometry": {"coordinates":[-135.3333,57.0167],"type":"Point"}
}