<<<<<<< HEAD
{
  "id": 2769685,
  "type": "Feature",
  "properties": {
    "tgn:hierarchy":[
        "tgn:2769685",
        "tgn:1000001",
        "tgn:2000920",
        "tgn:7012149",
        "tgn:7007515",
        "tgn:7029392"
    ],
    "tgn:id":2769685,
    "tgn:name":"Wiggins Brook",
    "tgn:placetype":[
        "aat:300008699"
    ]
},
  "bbox": [],
  "geometry": {"coordinates":[-70.2833,43.85],"type":"Point"}
}
=======
{"geometry":{"type":"Point","coordinates":[-70.283300,43.850000]},"type":"Feature","properties":{"hierarchy":["tgn:2769685","tgn:1000001","tgn:2000920","tgn:7012149","tgn:7007515","tgn:7029392"],"placetype":["aat:300008699"],"id":2769685,"name:xx":"Wiggins Brook"}}
>>>>>>> 03f74aca74312dbeaf24d7e61306dd6a786dc3d0
