{
  "id": 7137136,
  "type": "Feature",
  "properties": {
    "tgn:hierarchy":[
        "tgn:7137136",
        "tgn:1000003",
        "tgn:7003676",
        "tgn:7000084",
        "tgn:7029392"
    ],
    "tgn:id":7137136,
    "tgn:name":"Lehmh\u00f6rne",
    "tgn:placetype":[
        "aat:300000206"
    ]
},
  "bbox": [],
  "geometry": {"coordinates":[7.966667,53.383333],"type":"Point"}
}