{
  "id": 7432688,
  "type": "Feature",
  "properties": {
    "tgn:hierarchy":[
        "tgn:7432688",
        "tgn:7005587",
        "tgn:1000001",
        "tgn:7005560",
        "tgn:7029392"
    ],
    "tgn:id":7432688,
    "tgn:name":"Zacacuautla",
    "tgn:placetype":[
        "aat:300008347"
    ]
},
  "bbox": [],
  "geometry": {"coordinates":[-98.216667,20.216667],"type":"Point"}
}