{
  "id": 7587802,
  "type": "Feature",
  "properties": {
    "tgn:hierarchy":[
        "tgn:7587802",
        "tgn:1000004",
        "tgn:7000198",
        "tgn:7000799",
        "tgn:7029392"
    ],
    "tgn:id":7587802,
    "tgn:name:en":"Khor",
    "tgn:placetype":[
        "aat:300008347"
    ]
},
  "bbox": [],
  "geometry": {"coordinates":[74.574949,34.12858],"type":"Point"}
}