{
  "id": 2355307,
  "type": "Feature",
  "properties": {
    "tgn:hierarchy":[
        "tgn:2355307",
        "tgn:1000001",
        "tgn:7012149",
        "tgn:7014344",
        "tgn:7007919",
        "tgn:7029392"
    ],
    "tgn:id":2355307,
    "tgn:name":"Goodwins Cave",
    "tgn:placetype":[
        "aat:300008746"
    ]
},
  "bbox": [],
  "geometry": {"coordinates":[-80.1167,37.2167],"type":"Point"}
}