{
  "id": 2424688,
  "type": "Feature",
  "properties": {
    "tgn:hierarchy":[
        "tgn:2424688",
        "tgn:1000001",
        "tgn:7012149",
        "tgn:7014510",
        "tgn:7007920",
        "tgn:7029392"
    ],
    "tgn:id":2424688,
    "tgn:name":"Johnson Creek",
    "tgn:placetype":[
        "aat:300008706"
    ]
},
  "bbox": [],
  "geometry": {"coordinates":[-122.25,48.35],"type":"Point"}
}