{
  "id": 7535111,
  "type": "Feature",
  "properties": {
    "tgn:hierarchy":[
        "tgn:7535111",
        "tgn:7001242",
        "tgn:7016833",
        "tgn:1001087",
        "tgn:7029392"
    ],
    "tgn:id":7535111,
    "tgn:name":"Kawm 'Ayy\u0101d",
    "tgn:placetype":[
        "aat:300008347"
    ]
},
  "bbox": [],
  "geometry": {"coordinates":[31.002815,30.348988],"type":"Point"}
}