<<<<<<< HEAD
{
  "id": 7367524,
  "type": "Feature",
  "properties": {
    "tgn:hierarchy":[
        "tgn:7367524",
        "tgn:1001853",
        "tgn:1000001",
        "tgn:7005560",
        "tgn:7029392"
    ],
    "tgn:id":7367524,
    "tgn:name":"El Varej\u00f3n",
    "tgn:placetype":[
        "aat:300008347"
    ]
},
  "bbox": [],
  "geometry": {"coordinates":[-101.583333,28.416667],"type":"Point"}
}
=======
{"geometry":{"type":"Point","coordinates":[-101.583333,28.416667]},"type":"Feature","properties":{"hierarchy":["tgn:7367524","tgn:1001853","tgn:1000001","tgn:7005560","tgn:7029392"],"placetype":["aat:300008347"],"id":7367524,"name:xx":"El Varej\u00f3n"}}
>>>>>>> 03f74aca74312dbeaf24d7e61306dd6a786dc3d0
