{
  "id": 1099641,
  "type": "Feature",
  "properties": {
    "tgn:hierarchy":[
        "tgn:1099641",
        "tgn:7002068",
        "tgn:1001273",
        "tgn:1000233",
        "tgn:1000006",
        "tgn:7029392"
    ],
    "tgn:id":1099641,
    "tgn:name":"Tangarare",
    "tgn:placetype":[
        "aat:300008347"
    ]
},
  "bbox": [],
  "geometry": {"coordinates":[159.65,-9.5833],"type":"Point"}
}