{
  "id": 2674751,
  "type": "Feature",
  "properties": {
    "tgn:hierarchy":[
        "tgn:2674751",
        "tgn:1000001",
        "tgn:7012149",
        "tgn:1002929",
        "tgn:7007240",
        "tgn:7029392"
    ],
    "tgn:id":2674751,
    "tgn:name":"Soapstone Island",
    "tgn:placetype":[
        "aat:300008791"
    ]
},
  "bbox": [],
  "geometry": {"coordinates":[-82.1667,28.7167],"type":"Point"}
}