{
  "id": 2140378,
  "type": "Feature",
  "properties": {
    "tgn:hierarchy":[
        "tgn:2140378",
        "tgn:1000001",
        "tgn:1002410",
        "tgn:7012149",
        "tgn:7007565",
        "tgn:7029392"
    ],
    "tgn:id":2140378,
    "tgn:name":"Aunt Debs Ditch",
    "tgn:placetype":[
        "aat:300006075"
    ]
},
  "bbox": [],
  "geometry": {"coordinates":[-75.3167,39.8333],"type":"Point"}
}