{
  "id": 2760567,
  "type": "Feature",
  "properties": {
    "tgn:hierarchy":[
        "tgn:2760567",
        "tgn:1000001",
        "tgn:7012149",
        "tgn:1002418",
        "tgn:7007920",
        "tgn:7029392"
    ],
    "tgn:id":2760567,
    "tgn:name":"West Fork Vesta Creek",
    "tgn:placetype":[
        "aat:300008706"
    ]
},
  "bbox": [],
  "geometry": {"coordinates":[-123.5333,46.9333],"type":"Point"}
}