{
  "id": 2589851,
  "type": "Feature",
  "properties": {
    "tgn:hierarchy":[
        "tgn:2589851",
        "tgn:1000001",
        "tgn:7006451",
        "tgn:2000094",
        "tgn:7012149",
        "tgn:7029392"
    ],
    "tgn:id":2589851,
    "tgn:name":"Point of Pines Lake",
    "tgn:placetype":[
        "aat:300006191"
    ]
},
  "bbox": [],
  "geometry": {"coordinates":[-109.7833,33.3667],"type":"Point"}
}