{
  "id": 1137130,
  "type": "Feature",
  "properties": {
    "tgn:hierarchy":[
        "tgn:1137130",
        "tgn:1000004",
        "tgn:1003379",
        "tgn:7018214",
        "tgn:7002435",
        "tgn:7029392"
    ],
    "tgn:id":1137130,
    "tgn:name":"Afanas'yevo",
    "tgn:placetype":[
        "aat:300008347"
    ]
},
  "bbox": [],
  "geometry": {"coordinates":[42.4667,58.8667],"type":"Point"}
}