{
  "id": 1133041,
  "type": "Feature",
  "properties": {
    "tgn:hierarchy":[
        "tgn:1133041",
        "tgn:1000001",
        "tgn:7012149",
        "tgn:7007826",
        "tgn:7029392"
    ],
    "tgn:id":1133041,
    "tgn:name":"Denton Creek",
    "tgn:placetype":[
        "aat:300008706"
    ]
},
  "bbox": [],
  "geometry": {"coordinates":[-97.3833,29.3667],"type":"Point"}
}