{
  "id": 7164013,
  "type": "Feature",
  "properties": {
    "tgn:hierarchy":[
        "tgn:7164013",
        "tgn:1000003",
        "tgn:7003688",
        "tgn:7000084",
        "tgn:7029392"
    ],
    "tgn:id":7164013,
    "tgn:name":"Im Hauen",
    "tgn:placetype":[
        "aat:300008347"
    ]
},
  "bbox": [],
  "geometry": {"coordinates":[9.766667,53.683333],"type":"Point"}
}