{
  "id": 7123776,
  "type": "Feature",
  "properties": {
    "tgn:hierarchy":[
        "tgn:7123776",
        "tgn:7003692",
        "tgn:1000003",
        "tgn:7000084",
        "tgn:7029392"
    ],
    "tgn:id":7123776,
    "tgn:name":"Neudorf",
    "tgn:placetype":[
        "aat:300008347"
    ]
},
  "bbox": [],
  "geometry": {"coordinates":[9.666667,48.25],"type":"Point"}
}