{
  "id": 7157186,
  "type": "Feature",
  "properties": {
    "tgn:hierarchy":[
        "tgn:7157186",
        "tgn:7003669",
        "tgn:1000003",
        "tgn:7000084",
        "tgn:7029392"
    ],
    "tgn:id":7157186,
    "tgn:name":"Kleiner Rauhen-Kopf",
    "tgn:placetype":[
        "aat:300008798"
    ]
},
  "bbox": [],
  "geometry": {"coordinates":[12.983333,47.666667],"type":"Point"}
}