{
  "id": 2434032,
  "type": "Feature",
  "properties": {
    "tgn:hierarchy":[
        "tgn:2434032",
        "tgn:7006450",
        "tgn:1000001",
        "tgn:7012149",
        "tgn:2000082",
        "tgn:7029392"
    ],
    "tgn:id":2434032,
    "tgn:name":"Kelp Island",
    "tgn:placetype":[
        "aat:300008791"
    ]
},
  "bbox": [],
  "geometry": {"coordinates":[-131.2667,54.8667],"type":"Point"}
}