{
  "id": 2774385,
  "type": "Feature",
  "properties": {
    "tgn:hierarchy":[
        "tgn:2774385",
        "tgn:1000001",
        "tgn:7016172",
        "tgn:7012149",
        "tgn:2000158",
        "tgn:7029392"
    ],
    "tgn:id":2774385,
    "tgn:name":"Willow Lake",
    "tgn:placetype":[
        "aat:300008680"
    ]
},
  "bbox": [],
  "geometry": {"coordinates":[-91.05,34.15],"type":"Point"}
}