<<<<<<< HEAD
{
  "id": 7241643,
  "type": "Feature",
  "properties": {
    "tgn:hierarchy":[
        "tgn:7241643",
        "tgn:7007877",
        "tgn:1000003",
        "tgn:1000063",
        "tgn:4012014",
        "tgn:7029392"
    ],
    "tgn:id":7241643,
    "tgn:name":"La Cav\u00e9e",
    "tgn:placetype":[
        "aat:300008347"
    ]
},
  "bbox": [],
  "geometry": {"coordinates":[3.934152,50.680261],"type":"Point"}
}
=======
{"geometry":{"type":"Point","coordinates":[3.934152,50.680261]},"type":"Feature","properties":{"hierarchy":["tgn:7241643","tgn:7007877","tgn:1000003","tgn:1000063","tgn:4012014","tgn:7029392"],"placetype":["aat:300008347"],"id":7241643,"name:xx":"La Cav\u00e9e"}}
>>>>>>> 03f74aca74312dbeaf24d7e61306dd6a786dc3d0
