{
  "id": 7206252,
  "type": "Feature",
  "properties": {
    "tgn:hierarchy":[
        "tgn:7206252",
        "tgn:1000003",
        "tgn:7003677",
        "tgn:7000084",
        "tgn:7029392"
    ],
    "tgn:id":7206252,
    "tgn:name":"B\u00fcckling",
    "tgn:placetype":[
        "aat:300008777"
    ]
},
  "bbox": [],
  "geometry": {"coordinates":[8.633333,51.15],"type":"Point"}
}