{
  "id": 2368743,
  "type": "Feature",
  "properties": {
    "tgn:hierarchy":[
        "tgn:2368743",
        "tgn:2002306",
        "tgn:1000001",
        "tgn:7012149",
        "tgn:7007922",
        "tgn:7029392"
    ],
    "tgn:id":2368743,
    "tgn:name":"Gull Island Shoal",
    "tgn:placetype":[
        "aat:300132348"
    ]
},
  "bbox": [],
  "geometry": {"coordinates":[-90.3833,46.9333],"type":"Point"}
}