{
  "id": 2212384,
  "type": "Feature",
  "properties": {
    "tgn:hierarchy":[
        "tgn:2212384",
        "tgn:1000001",
        "tgn:2000922",
        "tgn:7012149",
        "tgn:7007515",
        "tgn:7029392"
    ],
    "tgn:id":2212384,
    "tgn:name":"Byard Point",
    "tgn:placetype":[
        "aat:300008850"
    ]
},
  "bbox": [],
  "geometry": {"coordinates":[-68.6833,44.2833],"type":"Point"}
}