{
  "id": 2273409,
  "type": "Feature",
  "properties": {
    "tgn:hierarchy":[
        "tgn:2273409",
        "tgn:1000001",
        "tgn:7012149",
        "tgn:7007523",
        "tgn:7029392"
    ],
    "tgn:id":2273409,
    "tgn:name":"Cypress Ditch",
    "tgn:placetype":[
        "aat:300006075"
    ]
},
  "bbox": [],
  "geometry": {"coordinates":[-90.6333,36.5167],"type":"Point"}
}