{
  "id": 7558362,
  "type": "Feature",
  "properties": {
    "tgn:hierarchy":[
        "tgn:7558362",
        "tgn:1000004",
        "tgn:1001869",
        "tgn:7000198",
        "tgn:7029392"
    ],
    "tgn:id":7558362,
    "tgn:name:en":"Sanosra",
    "tgn:placetype":[
        "aat:300007783"
    ]
},
  "bbox": [],
  "geometry": {"coordinates":[71.783333,21.75],"type":"Point"}
}