<<<<<<< HEAD
{
  "id": 7369063,
  "type": "Feature",
  "properties": {
    "tgn:hierarchy":[
        "tgn:7369063",
        "tgn:7005575",
        "tgn:1000001",
        "tgn:7005560",
        "tgn:7029392"
    ],
    "tgn:id":7369063,
    "tgn:name":"Ixtahuacan",
    "tgn:placetype":[
        "aat:300008347"
    ]
},
  "bbox": [],
  "geometry": {"coordinates":[-99.016667,19.35],"type":"Point"}
}
=======
{"geometry":{"type":"Point","coordinates":[-99.016667,19.350000]},"type":"Feature","properties":{"hierarchy":["tgn:7369063","tgn:7005575","tgn:1000001","tgn:7005560","tgn:7029392"],"placetype":["aat:300008347"],"id":7369063,"name:xx":"Ixtahuacan"}}
>>>>>>> 03f74aca74312dbeaf24d7e61306dd6a786dc3d0
