{
  "id": 2773158,
  "type": "Feature",
  "properties": {
    "tgn:hierarchy":[
        "tgn:2773158",
        "tgn:1000001",
        "tgn:7012149",
        "tgn:2000363",
        "tgn:7007248",
        "tgn:7029392"
    ],
    "tgn:id":2773158,
    "tgn:name":"Williams, Lake",
    "tgn:placetype":[
        "aat:300006191"
    ]
},
  "bbox": [],
  "geometry": {"coordinates":[-85.05,32.6833],"type":"Point"}
}