{
  "id": 2399353,
  "type": "Feature",
  "properties": {
    "tgn:hierarchy":[
        "tgn:2399353",
        "tgn:1000001",
        "tgn:7016172",
        "tgn:7012149",
        "tgn:2000163",
        "tgn:7029392"
    ],
    "tgn:id":2399353,
    "tgn:name":"Horn Lake",
    "tgn:placetype":[
        "aat:300008680"
    ]
},
  "bbox": [],
  "geometry": {"coordinates":[-91.4333,34.95],"type":"Point"}
}