{
  "id": 7079829,
  "type": "Feature",
  "properties": {
    "tgn:hierarchy":[
        "tgn:7079829",
        "tgn:1000003",
        "tgn:7003687",
        "tgn:7000084",
        "tgn:7029392"
    ],
    "tgn:id":7079829,
    "tgn:name":"Wulffensche Stiftungsforst",
    "tgn:placetype":[
        "aat:300008863"
    ]
},
  "bbox": [],
  "geometry": {"coordinates":[11.916667,52.216667],"type":"Point"}
}