{
  "id": 7069188,
  "type": "Feature",
  "properties": {
    "tgn:hierarchy":[
        "tgn:7069188",
        "tgn:7003692",
        "tgn:1000003",
        "tgn:7000084",
        "tgn:7029392"
    ],
    "tgn:id":7069188,
    "tgn:name":"Tierbach",
    "tgn:placetype":[
        "aat:300008699"
    ]
},
  "bbox": [],
  "geometry": {"coordinates":[9.883333,49.35],"type":"Point"}
}