{
  "id": 1100689,
  "type": "Feature",
  "properties": {
    "tgn:hierarchy":[
        "tgn:1100689",
        "tgn:7013445",
        "tgn:1000001",
        "tgn:1002923",
        "tgn:7012149",
        "tgn:7007517",
        "tgn:7029392"
    ],
    "tgn:id":1100689,
    "tgn:name":"Dorchester Heights National Historic Site",
    "tgn:placetype":[
        "aat:300000833"
    ]
},
  "bbox": [],
  "geometry": {"coordinates":[-71.0333,42.3167],"type":"Point"}
}