{
  "id": 2762911,
  "type": "Feature",
  "properties": {
    "tgn:hierarchy":[
        "tgn:2762911",
        "tgn:1000001",
        "tgn:7012149",
        "tgn:1002598",
        "tgn:7007523",
        "tgn:7029392"
    ],
    "tgn:id":2762911,
    "tgn:name":"Westhoff Lake",
    "tgn:placetype":[
        "aat:300006191"
    ]
},
  "bbox": [],
  "geometry": {"coordinates":[-90.7333,38.9667],"type":"Point"}
}