<<<<<<< HEAD
{
  "id": 2762911,
  "type": "Feature",
  "properties": {
    "tgn:hierarchy":[
        "tgn:2762911",
        "tgn:1000001",
        "tgn:7012149",
        "tgn:1002598",
        "tgn:7007523",
        "tgn:7029392"
    ],
    "tgn:id":2762911,
    "tgn:name":"Westhoff Lake",
    "tgn:placetype":[
        "aat:300006191"
    ]
},
  "bbox": [],
  "geometry": {"coordinates":[-90.7333,38.9667],"type":"Point"}
}
=======
{"geometry":{"type":"Point","coordinates":[-90.733300,38.966700]},"type":"Feature","properties":{"hierarchy":["tgn:2762911","tgn:1000001","tgn:7012149","tgn:1002598","tgn:7007523","tgn:7029392"],"placetype":["aat:300006191"],"id":2762911,"name:xx":"Westhoff Lake"}}
>>>>>>> 03f74aca74312dbeaf24d7e61306dd6a786dc3d0
