{
  "id": 7303429,
  "type": "Feature",
  "properties": {
    "tgn:hierarchy":[
        "tgn:7303429",
        "tgn:7002839",
        "tgn:7001158",
        "tgn:1000003",
        "tgn:1000095",
        "tgn:7029392"
    ],
    "tgn:id":7303429,
    "tgn:name":"Navares de las Cuevas",
    "tgn:placetype":[
        "aat:300008347"
    ]
},
  "bbox": [],
  "geometry": {"coordinates":[-3.75,41.416667],"type":"Point"}
}