{
  "id": 2024703,
  "type": "Feature",
  "properties": {
    "tgn:hierarchy":[
        "tgn:2024703",
        "tgn:1000001",
        "tgn:7012149",
        "tgn:2000432",
        "tgn:7007248",
        "tgn:7029392"
    ],
    "tgn:id":2024703,
    "tgn:name":"West Point",
    "tgn:placetype":[
        "aat:300008347"
    ]
},
  "bbox": [],
  "geometry": {"coordinates":[-85.1833,32.8667],"type":"Point"}
}