{
  "id": 2722102,
  "type": "Feature",
  "properties": {
    "tgn:hierarchy":[
        "tgn:2722102",
        "tgn:1000001",
        "tgn:7012149",
        "tgn:1002451",
        "tgn:7007919",
        "tgn:7029392"
    ],
    "tgn:id":2722102,
    "tgn:name":"Timberlake Pond Number One",
    "tgn:placetype":[
        "aat:300006191"
    ]
},
  "bbox": [],
  "geometry": {"coordinates":[-77.3333,37.7167],"type":"Point"}
}