{
  "id": 2529537,
  "type": "Feature",
  "properties": {
    "tgn:hierarchy":[
        "tgn:2529537",
        "tgn:1000001",
        "tgn:7012149",
        "tgn:2002011",
        "tgn:7007826",
        "tgn:7029392"
    ],
    "tgn:id":2529537,
    "tgn:name":"Mud Lake",
    "tgn:placetype":[
        "aat:300008680"
    ]
},
  "bbox": [],
  "geometry": {"coordinates":[-94.3333,29.5667],"type":"Point"}
}