{
  "id": 7549426,
  "type": "Feature",
  "properties": {
    "tgn:hierarchy":[
        "tgn:7549426",
        "tgn:1000004",
        "tgn:7000198",
        "tgn:1001996",
        "tgn:7029392"
    ],
    "tgn:id":7549426,
    "tgn:name:en":"Dhanechar",
    "tgn:placetype":[
        "aat:300008347"
    ]
},
  "bbox": [],
  "geometry": {"coordinates":[77.35423,30.949949],"type":"Point"}
}