{
  "id": 2215893,
  "type": "Feature",
  "properties": {
    "tgn:hierarchy":[
        "tgn:2215893",
        "tgn:1000001",
        "tgn:2001945",
        "tgn:7012149",
        "tgn:7007826",
        "tgn:7029392"
    ],
    "tgn:id":2215893,
    "tgn:name":"Camels Hump",
    "tgn:placetype":[
        "aat:300008798"
    ]
},
  "bbox": [],
  "geometry": {"coordinates":[-103.5167,29.5333],"type":"Point"}
}