{
  "id": 2468872,
  "type": "Feature",
  "properties": {
    "tgn:hierarchy":[
        "tgn:2468872",
        "tgn:1000001",
        "tgn:2001704",
        "tgn:7012149",
        "tgn:7007708",
        "tgn:7029392"
    ],
    "tgn:id":2468872,
    "tgn:name":"Long Rock",
    "tgn:placetype":[
        "aat:300008791"
    ]
},
  "bbox": [],
  "geometry": {"coordinates":[-124.25,42.0167],"type":"Point"}
}