{
  "id": 1019005,
  "type": "Feature",
  "properties": {
    "tgn:hierarchy":[
        "tgn:1019005",
        "tgn:7017442",
        "tgn:1000001",
        "tgn:7004643",
        "tgn:7029392"
    ],
    "tgn:id":1019005,
    "tgn:name":"Playa de Fajardo",
    "tgn:placetype":[
        "aat:300008347"
    ]
},
  "bbox": [],
  "geometry": {"coordinates":[-65.6333,18.3333],"type":"Point"}
}