{
  "id": 2034098,
  "type": "Feature",
  "properties": {
    "tgn:hierarchy":[
        "tgn:2034098",
        "tgn:1000001",
        "tgn:7012149",
        "tgn:1002487",
        "tgn:7007252",
        "tgn:7029392"
    ],
    "tgn:id":2034098,
    "tgn:name":"West Liberty",
    "tgn:placetype":[
        "aat:300008347",
        "aat:300387210"
    ]
},
  "bbox": [],
  "geometry": {"coordinates":[-85.8833,40.4167],"type":"Point"}
}