{
  "id": 7307889,
  "type": "Feature",
  "properties": {
    "tgn:hierarchy":[
        "tgn:7307889",
        "tgn:7002464",
        "tgn:1000049",
        "tgn:1000002",
        "tgn:7029392"
    ],
    "tgn:id":7307889,
    "tgn:name":"Negra, Punta",
    "tgn:placetype":[
        "aat:300386846"
    ]
},
  "bbox": [],
  "geometry": {"coordinates":[-70.183333,-20.133333],"type":"Point"}
}