{
  "id": 2676386,
  "type": "Feature",
  "properties": {
    "tgn:hierarchy":[
        "tgn:2676386",
        "tgn:1000001",
        "tgn:2001945",
        "tgn:7012149",
        "tgn:7007826",
        "tgn:7029392"
    ],
    "tgn:id":2676386,
    "tgn:name":"South Alamo Creek",
    "tgn:placetype":[
        "aat:300008706"
    ]
},
  "bbox": [],
  "geometry": {"coordinates":[-102.8667,30.0167],"type":"Point"}
}