{
  "id": 7045405,
  "type": "Feature",
  "properties": {
    "tgn:hierarchy":[
        "tgn:7045405",
        "tgn:1003428",
        "tgn:1000003",
        "tgn:7003120",
        "tgn:1000080",
        "tgn:7029392"
    ],
    "tgn:id":7045405,
    "tgn:name":"Fontanile",
    "tgn:placetype":[
        "aat:300008347"
    ]
},
  "bbox": [],
  "geometry": {"coordinates":[8.416667,44.75],"type":"Point"}
}