{
  "id": 7384481,
  "type": "Feature",
  "properties": {
    "tgn:hierarchy":[
        "tgn:7384481",
        "tgn:1000001",
        "tgn:1001893",
        "tgn:7005560",
        "tgn:7029392"
    ],
    "tgn:id":7384481,
    "tgn:name":"Nariz, Sierra de la",
    "tgn:placetype":[
        "aat:300008795"
    ]
},
  "bbox": [],
  "geometry": {"coordinates":[-112.616667,31.783333],"type":"Point"}
}