<<<<<<< HEAD
{
  "id": 2250719,
  "type": "Feature",
  "properties": {
    "tgn:hierarchy":[
        "tgn:2250719",
        "tgn:1000001",
        "tgn:7012149",
        "tgn:2000490",
        "tgn:7007250",
        "tgn:7029392"
    ],
    "tgn:id":2250719,
    "tgn:name":"Colson Canyon",
    "tgn:placetype":[
        "aat:300008761"
    ]
},
  "bbox": [],
  "geometry": {"coordinates":[-112.7667,42.3333],"type":"Point"}
}
=======
{"geometry":{"type":"Point","coordinates":[-112.766700,42.333300]},"type":"Feature","properties":{"hierarchy":["tgn:2250719","tgn:1000001","tgn:7012149","tgn:2000490","tgn:7007250","tgn:7029392"],"placetype":["aat:300008761"],"id":2250719,"name:xx":"Colson Canyon"}}
>>>>>>> 03f74aca74312dbeaf24d7e61306dd6a786dc3d0
