{
  "id": 2123071,
  "type": "Feature",
  "properties": {
    "tgn:hierarchy":[
        "tgn:2123071",
        "tgn:1000001",
        "tgn:7012149",
        "tgn:2002371",
        "tgn:7007923",
        "tgn:7029392"
    ],
    "tgn:id":2123071,
    "tgn:name":"Moneta",
    "tgn:placetype":[
        "aat:300008347",
        "aat:300387210"
    ]
},
  "bbox": [],
  "geometry": {"coordinates":[-107.7167,43.15],"type":"Point"}
}