{
  "id": 2009951,
  "type": "Feature",
  "properties": {
    "tgn:hierarchy":[
        "tgn:2009951",
        "tgn:1000001",
        "tgn:7012149",
        "tgn:7007157",
        "tgn:1002710",
        "tgn:7029392"
    ],
    "tgn:id":2009951,
    "tgn:name":"Alta Hill",
    "tgn:placetype":[
        "aat:300008347"
    ]
},
  "bbox": [],
  "geometry": {"coordinates":[-121.0667,39.2167],"type":"Point"}
}