{
  "id": 2162887,
  "type": "Feature",
  "properties": {
    "tgn:hierarchy":[
        "tgn:2162887",
        "tgn:1000001",
        "tgn:7012149",
        "tgn:7007157",
        "tgn:2000189",
        "tgn:7029392"
    ],
    "tgn:id":2162887,
    "tgn:name":"Benjamin Creek",
    "tgn:placetype":[
        "aat:300008706"
    ]
},
  "bbox": [],
  "geometry": {"coordinates":[-123.4167,41.75],"type":"Point"}
}