{
  "id": 7319780,
  "type": "Feature",
  "properties": {
    "tgn:hierarchy":[
        "tgn:7319780",
        "tgn:1001699",
        "tgn:1000049",
        "tgn:1000002",
        "tgn:7029392"
    ],
    "tgn:id":7319780,
    "tgn:name":"Ahinco",
    "tgn:placetype":[
        "aat:300008347"
    ]
},
  "bbox": [],
  "geometry": {"coordinates":[-73.516667,-41.783333],"type":"Point"}
}