<<<<<<< HEAD
{
  "id": 2150484,
  "type": "Feature",
  "properties": {
    "tgn:hierarchy":[
        "tgn:2150484",
        "tgn:1000001",
        "tgn:7012149",
        "tgn:2000820",
        "tgn:7007255",
        "tgn:7029392"
    ],
    "tgn:id":2150484,
    "tgn:name":"Basin Mountain",
    "tgn:placetype":[
        "aat:300008798"
    ]
},
  "bbox": [],
  "geometry": {"coordinates":[-84.2167,37.5667],"type":"Point"}
}
=======
{"geometry":{"type":"Point","coordinates":[-84.216700,37.566700]},"type":"Feature","properties":{"hierarchy":["tgn:2150484","tgn:1000001","tgn:7012149","tgn:2000820","tgn:7007255","tgn:7029392"],"placetype":["aat:300008798"],"id":2150484,"name:xx":"Basin Mountain"}}
>>>>>>> 03f74aca74312dbeaf24d7e61306dd6a786dc3d0
