{
  "id": 2150484,
  "type": "Feature",
  "properties": {
    "tgn:hierarchy":[
        "tgn:2150484",
        "tgn:1000001",
        "tgn:7012149",
        "tgn:2000820",
        "tgn:7007255",
        "tgn:7029392"
    ],
    "tgn:id":2150484,
    "tgn:name":"Basin Mountain",
    "tgn:placetype":[
        "aat:300008798"
    ]
},
  "bbox": [],
  "geometry": {"coordinates":[-84.2167,37.5667],"type":"Point"}
}