{
  "id": 2171687,
  "type": "Feature",
  "properties": {
    "tgn:hierarchy":[
        "tgn:2171687",
        "tgn:1000001",
        "tgn:7012149",
        "tgn:2001488",
        "tgn:7007709",
        "tgn:7029392"
    ],
    "tgn:id":2171687,
    "tgn:name":"Big Tim Island",
    "tgn:placetype":[
        "aat:300008791"
    ]
},
  "bbox": [],
  "geometry": {"coordinates":[-75.55,35.7833],"type":"Point"}
}