{
  "id": 1020073,
  "type": "Feature",
  "properties": {
    "tgn:hierarchy":[
        "tgn:1020073",
        "tgn:7006477",
        "tgn:1001526",
        "tgn:1000002",
        "tgn:7029392"
    ],
    "tgn:id":1020073,
    "tgn:name":"Suncho Corral",
    "tgn:placetype":[
        "aat:300008347"
    ]
},
  "bbox": [],
  "geometry": {"coordinates":[-63.45,-27.9167],"type":"Point"}
}