{
  "id": 1020238,
  "type": "Feature",
  "properties": {
    "tgn:hierarchy":[
        "tgn:1020238",
        "tgn:1000662",
        "tgn:1000046",
        "tgn:1000002",
        "tgn:7029392"
    ],
    "tgn:id":1020238,
    "tgn:name":"Achacachi",
    "tgn:placetype":[
        "aat:300008347"
    ]
},
  "bbox": [],
  "geometry": {"coordinates":[-68.7333,-16.0167],"type":"Point"}
}