{
  "id": 7195894,
  "type": "Feature",
  "properties": {
    "tgn:hierarchy":[
        "tgn:7195894",
        "tgn:7003669",
        "tgn:1000003",
        "tgn:7000084",
        "tgn:7029392"
    ],
    "tgn:id":7195894,
    "tgn:name":"Dickelschwaig",
    "tgn:placetype":[
        "aat:300000206"
    ]
},
  "bbox": [],
  "geometry": {"coordinates":[11.033333,47.566667],"type":"Point"}
}