{
  "id": 7509948,
  "type": "Feature",
  "properties": {
    "tgn:hierarchy":[
        "tgn:7509948",
        "tgn:1008380",
        "tgn:1000226",
        "tgn:7016827",
        "tgn:1000006",
        "tgn:7029392"
    ],
    "tgn:id":7509948,
    "tgn:name:en":"Te Popo Stream",
    "tgn:placetype":[
        "aat:300008699"
    ]
},
  "bbox": [],
  "geometry": {"coordinates":[174.266667,-39.283333],"type":"Point"}
}