{
  "id": 7106043,
  "type": "Feature",
  "properties": {
    "tgn:hierarchy":[
        "tgn:7106043",
        "tgn:7003692",
        "tgn:1000003",
        "tgn:7000084",
        "tgn:7029392"
    ],
    "tgn:id":7106043,
    "tgn:name":"Ruine Schalksburg",
    "tgn:placetype":[
        "aat:300008057"
    ]
},
  "bbox": [],
  "geometry": {"coordinates":[8.916667,48.233333],"type":"Point"}
}