{
  "id": 2632859,
  "type": "Feature",
  "properties": {
    "tgn:hierarchy":[
        "tgn:2632859",
        "tgn:1000001",
        "tgn:7012149",
        "tgn:1002977",
        "tgn:7007240",
        "tgn:7029392"
    ],
    "tgn:id":2632859,
    "tgn:name":"Ruby, Lake",
    "tgn:placetype":[
        "aat:300008680"
    ]
},
  "bbox": [],
  "geometry": {"coordinates":[-81.25,29.0333],"type":"Point"}
}