{
  "id": 1074060,
  "type": "Feature",
  "properties": {
    "tgn:hierarchy":[
        "tgn:1074060",
        "tgn:7002075",
        "tgn:1000004",
        "tgn:1000111",
        "tgn:7029392"
    ],
    "tgn:id":1074060,
    "tgn:name":"Zhongqiao",
    "tgn:placetype":[
        "aat:300008347"
    ]
},
  "bbox": [],
  "geometry": {"coordinates":[119.1833,31.1833],"type":"Point"}
}