{
  "id": 7456609,
  "type": "Feature",
  "properties": {
    "tgn:hierarchy":[
        "tgn:7456609",
        "tgn:7019094",
        "tgn:7002444",
        "tgn:1000003",
        "tgn:7008591",
        "tgn:7029392"
    ],
    "tgn:id":7456609,
    "tgn:name:en":"Polliwilline Bay",
    "tgn:placetype":[
        "aat:300132316"
    ]
},
  "bbox": [],
  "geometry": {"coordinates":[-5.55,55.316667],"type":"Point"}
}