{
  "id": 7300897,
  "type": "Feature",
  "properties": {
    "tgn:hierarchy":[
        "tgn:7300897",
        "tgn:7002803",
        "tgn:1001647",
        "tgn:1000003",
        "tgn:1000095",
        "tgn:7029392"
    ],
    "tgn:id":7300897,
    "tgn:name":"Mora de Santa Quiteria",
    "tgn:placetype":[
        "aat:300008347"
    ]
},
  "bbox": [],
  "geometry": {"coordinates":[-1.583333,38.566667],"type":"Point"}
}