{
  "id": 7564442,
  "type": "Feature",
  "properties": {
    "tgn:hierarchy":[
        "tgn:7564442",
        "tgn:1000004",
        "tgn:7000198",
        "tgn:1001894",
        "tgn:7029392"
    ],
    "tgn:id":7564442,
    "tgn:name:en":"Devri Reserved Forest",
    "tgn:placetype":[
        "aat:300008865"
    ]
},
  "bbox": [],
  "geometry": {"coordinates":[79.32327,24.756874],"type":"Point"}
}