{
  "id": 7204521,
  "type": "Feature",
  "properties": {
    "tgn:hierarchy":[
        "tgn:7204521",
        "tgn:7003669",
        "tgn:1000003",
        "tgn:7000084",
        "tgn:7029392"
    ],
    "tgn:id":7204521,
    "tgn:name":"Brandst\u00e4tt",
    "tgn:placetype":[
        "aat:300000206"
    ]
},
  "bbox": [],
  "geometry": {"coordinates":[12.633333,48.133333],"type":"Point"}
}