{
  "id": 2701247,
  "type": "Feature",
  "properties": {
    "tgn:hierarchy":[
        "tgn:2701247",
        "tgn:1000001",
        "tgn:7012149",
        "tgn:2002113",
        "tgn:7007827",
        "tgn:7029392"
    ],
    "tgn:id":2701247,
    "tgn:name":"Sugar Knoll",
    "tgn:placetype":[
        "aat:300008798"
    ]
},
  "bbox": [],
  "geometry": {"coordinates":[-112.6333,37.2333],"type":"Point"}
}