{
  "id": 2303788,
  "type": "Feature",
  "properties": {
    "tgn:hierarchy":[
        "tgn:2303788",
        "tgn:1000001",
        "tgn:2001432",
        "tgn:7012149",
        "tgn:7007566",
        "tgn:7029392"
    ],
    "tgn:id":2303788,
    "tgn:name":"Eagle Nest Reservoir",
    "tgn:placetype":[
        "aat:300006191"
    ]
},
  "bbox": [],
  "geometry": {"coordinates":[-105.2333,36.5333],"type":"Point"}
}