{
  "id": 2184599,
  "type": "Feature",
  "properties": {
    "tgn:hierarchy":[
        "tgn:2184599",
        "tgn:1000001",
        "tgn:2000861",
        "tgn:7012149",
        "tgn:7007256",
        "tgn:7029392"
    ],
    "tgn:id":2184599,
    "tgn:name":"Bodcau Park",
    "tgn:placetype":[
        "aat:300008347"
    ]
},
  "bbox": [],
  "geometry": {"coordinates":[-93.5833,32.5333],"type":"Point"}
}