<<<<<<< HEAD
{
  "id": 7053513,
  "type": "Feature",
  "properties": {
    "tgn:hierarchy":[
        "tgn:7053513",
        "tgn:7003150",
        "tgn:1000003",
        "tgn:7003237",
        "tgn:1000080",
        "tgn:7029392"
    ],
    "tgn:id":7053513,
    "tgn:name":"Pantigliate",
    "tgn:placetype":[
        "aat:300008347"
    ]
},
  "bbox": [],
  "geometry": {"coordinates":[9.35,45.433333],"type":"Point"}
}
=======
{"geometry":{"type":"Point","coordinates":[9.350000,45.433333]},"type":"Feature","properties":{"hierarchy":["tgn:7053513","tgn:7003150","tgn:1000003","tgn:7003237","tgn:1000080","tgn:7029392"],"placetype":["aat:300008347"],"id":7053513,"name:xx":"Pantigliate"}}
>>>>>>> 03f74aca74312dbeaf24d7e61306dd6a786dc3d0
