{
  "id": 7053513,
  "type": "Feature",
  "properties": {
    "tgn:hierarchy":[
        "tgn:7053513",
        "tgn:7003150",
        "tgn:1000003",
        "tgn:7003237",
        "tgn:1000080",
        "tgn:7029392"
    ],
    "tgn:id":7053513,
    "tgn:name":"Pantigliate",
    "tgn:placetype":[
        "aat:300008347"
    ]
},
  "bbox": [],
  "geometry": {"coordinates":[9.35,45.433333],"type":"Point"}
}