{
  "id": 7523140,
  "type": "Feature",
  "properties": {
    "tgn:hierarchy":[
        "tgn:7523140",
        "tgn:7001242",
        "tgn:1001059",
        "tgn:7016833",
        "tgn:7029392"
    ],
    "tgn:id":7523140,
    "tgn:name:en":"Ash Shu'ar\u0101'",
    "tgn:placetype":[
        "aat:300008347"
    ]
},
  "bbox": [],
  "geometry": {"coordinates":[31.7927,31.404337],"type":"Point"}
}