{
  "id": 2279526,
  "type": "Feature",
  "properties": {
    "tgn:hierarchy":[
        "tgn:2279526",
        "tgn:1000001",
        "tgn:2001260",
        "tgn:7012149",
        "tgn:7007524",
        "tgn:7029392"
    ],
    "tgn:id":2279526,
    "tgn:name":"Deadman Lake",
    "tgn:placetype":[
        "aat:300008680"
    ]
},
  "bbox": [],
  "geometry": {"coordinates":[-112.85,44.4333],"type":"Point"}
}