{
  "id": 1104524,
  "type": "Feature",
  "properties": {
    "tgn:hierarchy":[
        "tgn:1104524",
        "tgn:1000001",
        "tgn:7012149",
        "tgn:2000224",
        "tgn:7007158",
        "tgn:7029392"
    ],
    "tgn:id":1104524,
    "tgn:name":"Elbert, Mount",
    "tgn:placetype":[
        "aat:300008795"
    ]
},
  "bbox": [],
  "geometry": {"coordinates":[-106.4333,39.1167],"type":"Point"}
}