{
  "id": 7307496,
  "type": "Feature",
  "properties": {
    "tgn:hierarchy":[
        "tgn:7307496",
        "tgn:7001122",
        "tgn:1000003",
        "tgn:7002765",
        "tgn:1000095",
        "tgn:7029392"
    ],
    "tgn:id":7307496,
    "tgn:name":"Llibrell, Cabo",
    "tgn:placetype":[
        "aat:300008850"
    ]
},
  "bbox": [],
  "geometry": {"coordinates":[1.516667,38.933333],"type":"Point"}
}