{
  "id": 7440022,
  "type": "Feature",
  "properties": {
    "tgn:hierarchy":[
        "tgn:7440022",
        "tgn:7005581",
        "tgn:1000001",
        "tgn:7005560",
        "tgn:7029392"
    ],
    "tgn:id":7440022,
    "tgn:name":"Santa Mar\u00eda de Cuevas",
    "tgn:placetype":[
        "aat:300008347"
    ]
},
  "bbox": [],
  "geometry": {"coordinates":[-106.383333,27.916667],"type":"Point"}
}