{
  "id": 2318710,
  "type": "Feature",
  "properties": {
    "tgn:hierarchy":[
        "tgn:2318710",
        "tgn:7030516",
        "tgn:7006450",
        "tgn:1000001",
        "tgn:7012149",
        "tgn:7029392"
    ],
    "tgn:id":2318710,
    "tgn:name":"Erskine Point",
    "tgn:placetype":[
        "aat:300008850"
    ]
},
  "bbox": [],
  "geometry": {"coordinates":[-166.2667,53.9667],"type":"Point"}
}