{
  "id": 2262912,
  "type": "Feature",
  "properties": {
    "tgn:hierarchy":[
        "tgn:2262912",
        "tgn:1000001",
        "tgn:7012149",
        "tgn:2002382",
        "tgn:7007923",
        "tgn:7029392"
    ],
    "tgn:id":2262912,
    "tgn:name":"Cowdell Waste Water Ditch",
    "tgn:placetype":[
        "aat:300006075"
    ]
},
  "bbox": [],
  "geometry": {"coordinates":[-110.1333,44.35],"type":"Point"}
}