{
  "id": 2644516,
  "type": "Feature",
  "properties": {
    "tgn:hierarchy":[
        "tgn:2644516",
        "tgn:1000001",
        "tgn:7012149",
        "tgn:2000282",
        "tgn:7007240",
        "tgn:7029392"
    ],
    "tgn:id":2644516,
    "tgn:name":"Saratoga Lake",
    "tgn:placetype":[
        "aat:300008680"
    ]
},
  "bbox": [],
  "geometry": {"coordinates":[-81.65,29.5333],"type":"Point"}
}