{
  "id": 7019115,
  "type": "Feature",
  "properties": {
    "tgn:hierarchy":[
        "tgn:7019115",
        "tgn:7002444",
        "tgn:1000003",
        "tgn:7008591",
        "tgn:7029392"
    ],
    "tgn:id":7019115,
    "tgn:name:en":"East Lothian",
    "tgn:placetype":[
        "aat:300387064",
        "aat:300387145",
        "aat:300000771",
        "aat:300387071"
    ]
},
  "bbox": [],
  "geometry": {"coordinates":[-3.0833,55.9167],"type":"Point"}
}