{
  "id": 2350542,
  "type": "Feature",
  "properties": {
    "tgn:hierarchy":[
        "tgn:2350542",
        "tgn:1000001",
        "tgn:7012149",
        "tgn:1002691",
        "tgn:7007826",
        "tgn:7029392"
    ],
    "tgn:id":2350542,
    "tgn:name":"Givins Pond",
    "tgn:placetype":[
        "aat:300008905"
    ]
},
  "bbox": [],
  "geometry": {"coordinates":[-95.35,30.1833],"type":"Point"}
}