{
  "id": 7563626,
  "type": "Feature",
  "properties": {
    "tgn:hierarchy":[
        "tgn:7563626",
        "tgn:1000004",
        "tgn:7000198",
        "tgn:7016788",
        "tgn:7029392"
    ],
    "tgn:id":7563626,
    "tgn:name:en":"Karanpura",
    "tgn:placetype":[
        "aat:300008347"
    ]
},
  "bbox": [],
  "geometry": {"coordinates":[74.986017,28.618306],"type":"Point"}
}