{
  "id": 7571535,
  "type": "Feature",
  "properties": {
    "tgn:hierarchy":[
        "tgn:7571535",
        "tgn:1000004",
        "tgn:7000198",
        "tgn:7031783",
        "tgn:7029392"
    ],
    "tgn:id":7571535,
    "tgn:name:en":"Jarangdih",
    "tgn:placetype":[
        "aat:300007783"
    ]
},
  "bbox": [],
  "geometry": {"coordinates":[85.930673,23.770222],"type":"Point"}
}