{
  "id": 7062788,
  "type": "Feature",
  "properties": {
    "tgn:hierarchy":[
        "tgn:7062788",
        "tgn:1000003",
        "tgn:7003678",
        "tgn:7000084",
        "tgn:7029392"
    ],
    "tgn:id":7062788,
    "tgn:name":"Amelose",
    "tgn:placetype":[
        "aat:300008347"
    ]
},
  "bbox": [],
  "geometry": {"coordinates":[8.533333,50.833333],"type":"Point"}
}