{
  "id": 7408644,
  "type": "Feature",
  "properties": {
    "tgn:hierarchy":[
        "tgn:7408644",
        "tgn:1000001",
        "tgn:7005590",
        "tgn:7005560",
        "tgn:7029392"
    ],
    "tgn:id":7408644,
    "tgn:name":"Las Trojes",
    "tgn:placetype":[
        "aat:300008347"
    ]
},
  "bbox": [],
  "geometry": {"coordinates":[-101.566667,19.516667],"type":"Point"}
}