{
  "id": 2476865,
  "type": "Feature",
  "properties": {
    "tgn:hierarchy":[
        "tgn:2476865",
        "tgn:1000001",
        "tgn:7012149",
        "tgn:2001531",
        "tgn:7007709",
        "tgn:7029392"
    ],
    "tgn:id":2476865,
    "tgn:name":"Lyles Lake",
    "tgn:placetype":[
        "aat:300008680"
    ]
},
  "bbox": [],
  "geometry": {"coordinates":[-81.9667,35.2333],"type":"Point"}
}