{
  "id": 2671925,
  "type": "Feature",
  "properties": {
    "tgn:hierarchy":[
        "tgn:2671925",
        "tgn:1000001",
        "tgn:7012149",
        "tgn:7007825",
        "tgn:7029392"
    ],
    "tgn:id":2671925,
    "tgn:name":"Smith Ridge",
    "tgn:placetype":[
        "aat:300266640"
    ]
},
  "bbox": [],
  "geometry": {"coordinates":[-84.9833,35.0833],"type":"Point"}
}