{
  "id": 2123003,
  "type": "Feature",
  "properties": {
    "tgn:hierarchy":[
        "tgn:2123003",
        "tgn:2002365",
        "tgn:1000001",
        "tgn:7012149",
        "tgn:7007923",
        "tgn:7029392"
    ],
    "tgn:id":2123003,
    "tgn:name":"Keystone",
    "tgn:placetype":[
        "aat:300008347",
        "aat:300387247"
    ]
},
  "bbox": [],
  "geometry": {"coordinates":[-106.25,41.1667],"type":"Point"}
}