{
  "id": 7189692,
  "type": "Feature",
  "properties": {
    "tgn:hierarchy":[
        "tgn:7189692",
        "tgn:1000003",
        "tgn:7003682",
        "tgn:7000084",
        "tgn:7029392"
    ],
    "tgn:id":7189692,
    "tgn:name":"Elsaffthal",
    "tgn:placetype":[
        "aat:300387173"
    ]
},
  "bbox": [],
  "geometry": {"coordinates":[7.383333,50.616667],"type":"Point"}
}