{
  "id": 2220440,
  "type": "Feature",
  "properties": {
    "tgn:hierarchy":[
        "tgn:2220440",
        "tgn:1000001",
        "tgn:7012149",
        "tgn:2000933",
        "tgn:7007515",
        "tgn:7029392"
    ],
    "tgn:id":2220440,
    "tgn:name":"Cape Island",
    "tgn:placetype":[
        "aat:300008791"
    ]
},
  "bbox": [],
  "geometry": {"coordinates":[-70.4167,43.35],"type":"Point"}
}