<<<<<<< HEAD
{
  "id": 2339538,
  "type": "Feature",
  "properties": {
    "tgn:hierarchy":[
        "tgn:2339538",
        "tgn:1000001",
        "tgn:7012149",
        "tgn:7007524",
        "tgn:7029392"
    ],
    "tgn:id":2339538,
    "tgn:name":"Freda Creek",
    "tgn:placetype":[
        "aat:300008706"
    ]
},
  "bbox": [],
  "geometry": {"coordinates":[-106.1333,45.8167],"type":"Point"}
}
=======
{"geometry":{"type":"Point","coordinates":[-106.133300,45.816700]},"type":"Feature","properties":{"hierarchy":["tgn:2339538","tgn:1000001","tgn:7012149","tgn:7007524","tgn:7029392"],"placetype":["aat:300008706"],"id":2339538,"name:xx":"Freda Creek"}}
>>>>>>> 03f74aca74312dbeaf24d7e61306dd6a786dc3d0
