{
  "id": 2216283,
  "type": "Feature",
  "properties": {
    "tgn:hierarchy":[
        "tgn:2216283",
        "tgn:2002137",
        "tgn:1000001",
        "tgn:7012149",
        "tgn:7007919",
        "tgn:7029392"
    ],
    "tgn:id":2216283,
    "tgn:name":"Camp Branch",
    "tgn:placetype":[
        "aat:300008699"
    ]
},
  "bbox": [],
  "geometry": {"coordinates":[-78.3667,38.0167],"type":"Point"}
}