<<<<<<< HEAD
{
  "id": 7353376,
  "type": "Feature",
  "properties": {
    "tgn:hierarchy":[
        "tgn:7353376",
        "tgn:7005581",
        "tgn:1000001",
        "tgn:7005560",
        "tgn:7029392"
    ],
    "tgn:id":7353376,
    "tgn:name":"Bella Vista",
    "tgn:placetype":[
        "aat:300008347"
    ]
},
  "bbox": [],
  "geometry": {"coordinates":[-105.8,27.466667],"type":"Point"}
}
=======
{"geometry":{"type":"Point","coordinates":[-105.800000,27.466667]},"type":"Feature","properties":{"hierarchy":["tgn:7353376","tgn:7005581","tgn:1000001","tgn:7005560","tgn:7029392"],"placetype":["aat:300008347"],"id":7353376,"name:xx":"Bella Vista"}}
>>>>>>> 03f74aca74312dbeaf24d7e61306dd6a786dc3d0
