{
  "id": 7416203,
  "type": "Feature",
  "properties": {
    "tgn:hierarchy":[
        "tgn:7416203",
        "tgn:1000001",
        "tgn:7005591",
        "tgn:7005560",
        "tgn:7029392"
    ],
    "tgn:id":7416203,
    "tgn:name:es":"Huertas",
    "tgn:placetype":[
        "aat:300008347"
    ]
},
  "bbox": [],
  "geometry": {"coordinates":[-97.941667,16.938889],"type":"Point"}
}