{
  "id": 7408929,
  "type": "Feature",
  "properties": {
    "tgn:hierarchy":[
        "tgn:7408929",
        "tgn:7005580",
        "tgn:1000001",
        "tgn:7005560",
        "tgn:7029392"
    ],
    "tgn:id":7408929,
    "tgn:name":"Santo Domingo, Cerro",
    "tgn:placetype":[
        "aat:300008795"
    ]
},
  "bbox": [],
  "geometry": {"coordinates":[-91.890278,16.581944],"type":"Point"}
}