{
  "id": 7337725,
  "type": "Feature",
  "properties": {
    "tgn:hierarchy":[
        "tgn:7337725",
        "tgn:7002836",
        "tgn:7016622",
        "tgn:1000003",
        "tgn:1000095",
        "tgn:7029392"
    ],
    "tgn:id":7337725,
    "tgn:name":"Chafari, Boca de",
    "tgn:placetype":[
        "aat:300132317"
    ]
},
  "bbox": [],
  "geometry": {"coordinates":[-16.216667,28.55],"type":"Point"}
}