{
  "id": 7312633,
  "type": "Feature",
  "properties": {
    "tgn:hierarchy":[
        "tgn:7312633",
        "tgn:7016598",
        "tgn:1000049",
        "tgn:1000002",
        "tgn:7029392"
    ],
    "tgn:id":7312633,
    "tgn:name":"La Perd\u00edz, Quebrada",
    "tgn:placetype":[
        "aat:300266554",
        "aat:300008699"
    ]
},
  "bbox": [],
  "geometry": {"coordinates":[-68.166667,-21.733333],"type":"Point"}
}