{
  "id": 2351203,
  "type": "Feature",
  "properties": {
    "tgn:hierarchy":[
        "tgn:2351203",
        "tgn:7019618",
        "tgn:1000001",
        "tgn:7012149",
        "tgn:7007564",
        "tgn:7029392"
    ],
    "tgn:id":2351203,
    "tgn:name":"Gleason Brook",
    "tgn:placetype":[
        "aat:300008699"
    ]
},
  "bbox": [],
  "geometry": {"coordinates":[-72.1167,42.8667],"type":"Point"}
}