{
  "id": 7409098,
  "type": "Feature",
  "properties": {
    "tgn:hierarchy":[
        "tgn:7409098",
        "tgn:1000001",
        "tgn:7005590",
        "tgn:7005560",
        "tgn:7029392"
    ],
    "tgn:id":7409098,
    "tgn:name":"Puerto El Le\u00f3n",
    "tgn:placetype":[
        "aat:300008347"
    ]
},
  "bbox": [],
  "geometry": {"coordinates":[-100.840278,19.675],"type":"Point"}
}