{
  "id": 2558485,
  "type": "Feature",
  "properties": {
    "tgn:hierarchy":[
        "tgn:2558485",
        "tgn:1000001",
        "tgn:7012149",
        "tgn:2001274",
        "tgn:7007524",
        "tgn:7029392"
    ],
    "tgn:id":2558485,
    "tgn:name":"Olive Lake",
    "tgn:placetype":[
        "aat:300008680"
    ]
},
  "bbox": [],
  "geometry": {"coordinates":[-114.0667,48.15],"type":"Point"}
}