{
  "id": 7165654,
  "type": "Feature",
  "properties": {
    "tgn:hierarchy":[
        "tgn:7165654",
        "tgn:1000003",
        "tgn:7003677",
        "tgn:7000084",
        "tgn:7029392"
    ],
    "tgn:id":7165654,
    "tgn:name":"Hargard",
    "tgn:placetype":[
        "aat:300000206"
    ]
},
  "bbox": [],
  "geometry": {"coordinates":[6.25,50.55],"type":"Point"}
}