{
  "id": 2106792,
  "type": "Feature",
  "properties": {
    "tgn:hierarchy":[
        "tgn:2106792",
        "tgn:1000001",
        "tgn:7012149",
        "tgn:1002230",
        "tgn:7007826",
        "tgn:7029392"
    ],
    "tgn:id":2106792,
    "tgn:name":"Pittsburg",
    "tgn:placetype":[
        "aat:300008347"
    ]
},
  "bbox": [],
  "geometry": {"coordinates":[-94.95,32.9833],"type":"Point"}
}