{
  "id": 2110838,
  "type": "Feature",
  "properties": {
    "tgn:hierarchy":[
        "tgn:2110838",
        "tgn:1000001",
        "tgn:2002147",
        "tgn:7012149",
        "tgn:7007919",
        "tgn:7029392"
    ],
    "tgn:id":2110838,
    "tgn:name":"Brunswick",
    "tgn:placetype":[
        "aat:300008347",
        "aat:300387210"
    ]
},
  "bbox": [],
  "geometry": {"coordinates":[-77.8667,36.6333],"type":"Point"}
}