{
  "id": 2333477,
  "type": "Feature",
  "properties": {
    "tgn:hierarchy":[
        "tgn:2333477",
        "tgn:1000001",
        "tgn:7012149",
        "tgn:2001036",
        "tgn:7007521",
        "tgn:7029392"
    ],
    "tgn:id":2333477,
    "tgn:name":"Folly Creek",
    "tgn:placetype":[
        "aat:300008706"
    ]
},
  "bbox": [],
  "geometry": {"coordinates":[-91.1667,47.6667],"type":"Point"}
}