<<<<<<< HEAD
{
  "id": 7056579,
  "type": "Feature",
  "properties": {
    "tgn:hierarchy":[
        "tgn:7056579",
        "tgn:7003006",
        "tgn:1000003",
        "tgn:7002997",
        "tgn:1000080",
        "tgn:7029392"
    ],
    "tgn:id":7056579,
    "tgn:name":"Bevazzana",
    "tgn:placetype":[
        "aat:300008347"
    ]
},
  "bbox": [],
  "geometry": {"coordinates":[13.064167,45.673611],"type":"Point"}
}
=======
{"geometry":{"type":"Point","coordinates":[13.064167,45.673611]},"type":"Feature","properties":{"hierarchy":["tgn:7056579","tgn:7003006","tgn:1000003","tgn:7002997","tgn:1000080","tgn:7029392"],"placetype":["aat:300008347"],"id":7056579,"name:xx":"Bevazzana"}}
>>>>>>> 03f74aca74312dbeaf24d7e61306dd6a786dc3d0
