{
  "id": 2440327,
  "type": "Feature",
  "properties": {
    "tgn:hierarchy":[
        "tgn:2440327",
        "tgn:1000001",
        "tgn:2001410",
        "tgn:7012149",
        "tgn:7007526",
        "tgn:7029392"
    ],
    "tgn:id":2440327,
    "tgn:name":"Klondike Cove",
    "tgn:placetype":[
        "aat:300132316"
    ]
},
  "bbox": [],
  "geometry": {"coordinates":[-114.6667,35.5167],"type":"Point"}
}