{
  "id": 2288877,
  "type": "Feature",
  "properties": {
    "tgn:hierarchy":[
        "tgn:2288877",
        "tgn:1000001",
        "tgn:7012149",
        "tgn:2000659",
        "tgn:7007253",
        "tgn:7029392"
    ],
    "tgn:id":2288877,
    "tgn:name":"Ditch Number 7",
    "tgn:placetype":[
        "aat:300006075"
    ]
},
  "bbox": [],
  "geometry": {"coordinates":[-93.5333,42.6333],"type":"Point"}
}