{
  "id": 2105368,
  "type": "Feature",
  "properties": {
    "tgn:hierarchy":[
        "tgn:2105368",
        "tgn:1000001",
        "tgn:7012149",
        "tgn:1002578",
        "tgn:7007826",
        "tgn:7029392"
    ],
    "tgn:id":2105368,
    "tgn:name":"Kinkler",
    "tgn:placetype":[
        "aat:300008347",
        "aat:300387210"
    ]
},
  "bbox": [],
  "geometry": {"coordinates":[-96.8833,29.5333],"type":"Point"}
}