{
  "id": 7220921,
  "type": "Feature",
  "properties": {
    "tgn:hierarchy":[
        "tgn:7220921",
        "tgn:7002715",
        "tgn:7002731",
        "tgn:1000003",
        "tgn:1000074",
        "tgn:7029392"
    ],
    "tgn:id":7220921,
    "tgn:name":"Petrot\u00f3n",
    "tgn:placetype":[
        "aat:300008347"
    ]
},
  "bbox": [],
  "geometry": {"coordinates":[22.868611,40.814167],"type":"Point"}
}