{
  "id": 7586981,
  "type": "Feature",
  "properties": {
    "tgn:hierarchy":[
        "tgn:7586981",
        "tgn:1000004",
        "tgn:7000198",
        "tgn:7000799",
        "tgn:7029392"
    ],
    "tgn:id":7586981,
    "tgn:name:en":"Sinemosundo",
    "tgn:placetype":[
        "aat:300008699"
    ]
},
  "bbox": [],
  "geometry": {"coordinates":[77.448303,34.462986],"type":"Point"}
}