{
  "id": 7217342,
  "type": "Feature",
  "properties": {
    "tgn:hierarchy":[
        "tgn:7217342",
        "tgn:7011164",
        "tgn:7002674",
        "tgn:1000003",
        "tgn:1000074",
        "tgn:7029392"
    ],
    "tgn:id":7217342,
    "tgn:name":"Avl\u00e1kia",
    "tgn:placetype":[
        "aat:300008347"
    ]
},
  "bbox": [],
  "geometry": {"coordinates":[26.859167,37.7975],"type":"Point"}
}