<<<<<<< HEAD
{
  "id": 2152545,
  "type": "Feature",
  "properties": {
    "tgn:hierarchy":[
        "tgn:2152545",
        "tgn:1000001",
        "tgn:7012149",
        "tgn:2000368",
        "tgn:7007248",
        "tgn:7029392"
    ],
    "tgn:id":2152545,
    "tgn:name":"Bay, The",
    "tgn:placetype":[
        "aat:300008905"
    ]
},
  "bbox": [],
  "geometry": {"coordinates":[-83.4333,31.7],"type":"Point"}
}
=======
{"geometry":{"type":"Point","coordinates":[-83.433300,31.700000]},"type":"Feature","properties":{"hierarchy":["tgn:2152545","tgn:1000001","tgn:7012149","tgn:2000368","tgn:7007248","tgn:7029392"],"placetype":["aat:300008905"],"id":2152545,"name:xx":"Bay, The"}}
>>>>>>> 03f74aca74312dbeaf24d7e61306dd6a786dc3d0
