{
  "id": 7544811,
  "type": "Feature",
  "properties": {
    "tgn:hierarchy":[
        "tgn:7544811",
        "tgn:1000004",
        "tgn:7000198",
        "tgn:7016788",
        "tgn:7029392"
    ],
    "tgn:id":7544811,
    "tgn:name:en":"Bharna",
    "tgn:placetype":[
        "aat:300008347"
    ]
},
  "bbox": [],
  "geometry": {"coordinates":[75.65893,25.971329],"type":"Point"}
}