{
  "id": 1123142,
  "type": "Feature",
  "properties": {
    "tgn:hierarchy":[
        "tgn:1123142",
        "tgn:7006260",
        "tgn:7002454",
        "tgn:1000047",
        "tgn:1000002",
        "tgn:7029392"
    ],
    "tgn:id":1123142,
    "tgn:name":"Cristalino",
    "tgn:placetype":[
        "aat:300008707"
    ]
},
  "bbox": [],
  "geometry": {"coordinates":[-50.6667,-12.6333],"type":"Point"}
}