{
  "id": 2774873,
  "type": "Feature",
  "properties": {
    "tgn:hierarchy":[
        "tgn:2774873",
        "tgn:1000001",
        "tgn:7012149",
        "tgn:7007157",
        "tgn:7014516",
        "tgn:7029392"
    ],
    "tgn:id":2774873,
    "tgn:name":"Willow Springs Creek",
    "tgn:placetype":[
        "aat:300008706"
    ]
},
  "bbox": [],
  "geometry": {"coordinates":[-123.0667,38.6833],"type":"Point"}
}