{
  "id": 1017897,
  "type": "Feature",
  "properties": {
    "tgn:hierarchy":[
        "tgn:1017897",
        "tgn:1000001",
        "tgn:1001960",
        "tgn:7005560",
        "tgn:7029392"
    ],
    "tgn:id":1017897,
    "tgn:name":"N\u00e1cori Chico",
    "tgn:placetype":[
        "aat:300008347"
    ]
},
  "bbox": [],
  "geometry": {"coordinates":[-108.966667,29.683333],"type":"Point"}
}