{
  "id": 7246495,
  "type": "Feature",
  "properties": {
    "tgn:hierarchy":[
        "tgn:7246495",
        "tgn:7003465",
        "tgn:1000003",
        "tgn:1000063",
        "tgn:4012014",
        "tgn:7029392"
    ],
    "tgn:id":7246495,
    "tgn:name":"Burnaimont, Bois de",
    "tgn:placetype":[
        "aat:300008863"
    ]
},
  "bbox": [],
  "geometry": {"coordinates":[5.516667,49.816667],"type":"Point"}
}