{
  "id": 7371236,
  "type": "Feature",
  "properties": {
    "tgn:hierarchy":[
        "tgn:7371236",
        "tgn:1000001",
        "tgn:7005597",
        "tgn:7005560",
        "tgn:7029392"
    ],
    "tgn:id":7371236,
    "tgn:name":"Grande",
    "tgn:placetype":[
        "aat:300007783"
    ]
},
  "bbox": [],
  "geometry": {"coordinates":[-99.316667,24.433333],"type":"Point"}
}