{
  "id": 7316544,
  "type": "Feature",
  "properties": {
    "tgn:hierarchy":[
        "tgn:7316544",
        "tgn:1001630",
        "tgn:1000049",
        "tgn:1000002",
        "tgn:7029392"
    ],
    "tgn:id":7316544,
    "tgn:name":"Caser\u00f3n",
    "tgn:placetype":[
        "aat:300008347"
    ]
},
  "bbox": [],
  "geometry": {"coordinates":[-70.666667,-27.35],"type":"Point"}
}