{
  "id": 2431843,
  "type": "Feature",
  "properties": {
    "tgn:hierarchy":[
        "tgn:2431843",
        "tgn:1000001",
        "tgn:7012149",
        "tgn:1002535",
        "tgn:7007826",
        "tgn:7029392"
    ],
    "tgn:id":2431843,
    "tgn:name":"Kaufman Branch",
    "tgn:placetype":[
        "aat:300008699"
    ]
},
  "bbox": [],
  "geometry": {"coordinates":[-96.25,32.6167],"type":"Point"}
}