{
  "id": 2574669,
  "type": "Feature",
  "properties": {
    "tgn:hierarchy":[
        "tgn:2574669",
        "tgn:1000001",
        "tgn:7012149",
        "tgn:7007157",
        "tgn:1002858",
        "tgn:7029392"
    ],
    "tgn:id":2574669,
    "tgn:name":"Pena Spring",
    "tgn:placetype":[
        "aat:300008697"
    ]
},
  "bbox": [],
  "geometry": {"coordinates":[-116.45,33.2167],"type":"Point"}
}