{
  "id": 7591511,
  "type": "Feature",
  "properties": {
    "tgn:hierarchy":[
        "tgn:7591511",
        "tgn:1000004",
        "tgn:7000198",
        "tgn:7000799",
        "tgn:7029392"
    ],
    "tgn:id":7591511,
    "tgn:name:en":"Gopiw\u0101la",
    "tgn:placetype":[
        "aat:300387033"
    ]
},
  "bbox": [],
  "geometry": {"coordinates":[74.611111,32.920833],"type":"Point"}
}