{
  "id": 7560478,
  "type": "Feature",
  "properties": {
    "tgn:hierarchy":[
        "tgn:7560478",
        "tgn:1000004",
        "tgn:7000198",
        "tgn:7016722",
        "tgn:7029392"
    ],
    "tgn:id":7560478,
    "tgn:name:en":"Umarsenda",
    "tgn:placetype":[
        "aat:300008347"
    ]
},
  "bbox": [],
  "geometry": {"coordinates":[79.231864,26.802628],"type":"Point"}
}