{
  "id": 7341773,
  "type": "Feature",
  "properties": {
    "tgn:hierarchy":[
        "tgn:7341773",
        "tgn:7002836",
        "tgn:7016622",
        "tgn:1000003",
        "tgn:1000095",
        "tgn:7029392"
    ],
    "tgn:id":7341773,
    "tgn:name":"Bermejo, Lomo",
    "tgn:placetype":[
        "aat:300008777"
    ]
},
  "bbox": [],
  "geometry": {"coordinates":[-16.133333,28.533333],"type":"Point"}
}