{
  "id": 2612242,
  "type": "Feature",
  "properties": {
    "tgn:hierarchy":[
        "tgn:2612242",
        "tgn:7006450",
        "tgn:1000001",
        "tgn:7012149",
        "tgn:2000089",
        "tgn:7029392"
    ],
    "tgn:id":2612242,
    "tgn:name":"Red Slough",
    "tgn:placetype":[
        "aat:300008699"
    ]
},
  "bbox": [],
  "geometry": {"coordinates":[-153.25,63.3833],"type":"Point"}
}