{
  "id": 2577619,
  "type": "Feature",
  "properties": {
    "tgn:hierarchy":[
        "tgn:2577619",
        "tgn:2002308",
        "tgn:1000001",
        "tgn:7012149",
        "tgn:7007922",
        "tgn:7029392"
    ],
    "tgn:id":2577619,
    "tgn:name":"Peterson Lake",
    "tgn:placetype":[
        "aat:300008680"
    ]
},
  "bbox": [],
  "geometry": {"coordinates":[-91.3667,46.55],"type":"Point"}
}