{
  "id": 2708899,
  "type": "Feature",
  "properties": {
    "tgn:hierarchy":[
        "tgn:2708899",
        "tgn:1000001",
        "tgn:7012149",
        "tgn:2001275",
        "tgn:7007524",
        "tgn:7029392"
    ],
    "tgn:id":2708899,
    "tgn:name":"Sypes Creek",
    "tgn:placetype":[
        "aat:300008706"
    ]
},
  "bbox": [],
  "geometry": {"coordinates":[-110.9667,45.7333],"type":"Point"}
}