{
  "id": 1114323,
  "type": "Feature",
  "properties": {
    "tgn:hierarchy":[
        "tgn:1114323",
        "tgn:1000003",
        "tgn:7006660",
        "tgn:7029392"
    ],
    "tgn:id":1114323,
    "tgn:name":"Dneprovskiy Liman",
    "tgn:placetype":[
        "aat:300266571"
    ]
},
  "bbox": [],
  "geometry": {"coordinates":[31.9167,46.5833],"type":"Point"}
}