{
  "id": 7551237,
  "type": "Feature",
  "properties": {
    "tgn:hierarchy":[
        "tgn:7551237",
        "tgn:1000004",
        "tgn:7000198",
        "tgn:1001977",
        "tgn:7029392"
    ],
    "tgn:id":7551237,
    "tgn:name:en":"Ch\u0101walh\u0101ti",
    "tgn:placetype":[
        "aat:300008347"
    ]
},
  "bbox": [],
  "geometry": {"coordinates":[88.567689,26.484108],"type":"Point"}
}