{
  "id": 2658373,
  "type": "Feature",
  "properties": {
    "tgn:hierarchy":[
        "tgn:2658373",
        "tgn:1000001",
        "tgn:7012149",
        "tgn:2001921",
        "tgn:7007825",
        "tgn:7029392"
    ],
    "tgn:id":2658373,
    "tgn:name":"Shephard Hollow",
    "tgn:placetype":[
        "aat:300008761"
    ]
},
  "bbox": [],
  "geometry": {"coordinates":[-86.2167,36.4667],"type":"Point"}
}