{
  "id": 2323080,
  "type": "Feature",
  "properties": {
    "tgn:hierarchy":[
        "tgn:2323080",
        "tgn:1000001",
        "tgn:7012149",
        "tgn:2001715",
        "tgn:7007708",
        "tgn:7029392"
    ],
    "tgn:id":2323080,
    "tgn:name":"Farleighs Reservoir",
    "tgn:placetype":[
        "aat:300006191"
    ]
},
  "bbox": [],
  "geometry": {"coordinates":[-120.4333,42.15],"type":"Point"}
}