{
  "id": 2560829,
  "type": "Feature",
  "properties": {
    "tgn:hierarchy":[
        "tgn:2560829",
        "tgn:1000001",
        "tgn:7012149",
        "tgn:2000879",
        "tgn:7007256",
        "tgn:7029392"
    ],
    "tgn:id":2560829,
    "tgn:name":"Orlandos Mobile Home Park",
    "tgn:placetype":[
        "aat:300008347"
    ]
},
  "bbox": [],
  "geometry": {"coordinates":[-90.1833,29.9667],"type":"Point"}
}