<<<<<<< HEAD
{
  "id": 7351675,
  "type": "Feature",
  "properties": {
    "tgn:hierarchy":[
        "tgn:7351675",
        "tgn:7005583",
        "tgn:1000001",
        "tgn:7005560",
        "tgn:7029392"
    ],
    "tgn:id":7351675,
    "tgn:name":"Cajoncito",
    "tgn:placetype":[
        "aat:300008347"
    ]
},
  "bbox": [],
  "geometry": {"coordinates":[-106.8,25.2],"type":"Point"}
}
=======
{"geometry":{"type":"Point","coordinates":[-106.800000,25.200000]},"type":"Feature","properties":{"hierarchy":["tgn:7351675","tgn:7005583","tgn:1000001","tgn:7005560","tgn:7029392"],"placetype":["aat:300008347"],"id":7351675,"name:xx":"Cajoncito"}}
>>>>>>> 03f74aca74312dbeaf24d7e61306dd6a786dc3d0
