{
  "id": 7556361,
  "type": "Feature",
  "properties": {
    "tgn:hierarchy":[
        "tgn:7556361",
        "tgn:1000004",
        "tgn:7000198",
        "tgn:1001882",
        "tgn:7029392"
    ],
    "tgn:id":7556361,
    "tgn:name:en":"Satteg\u0101lam",
    "tgn:placetype":[
        "aat:300008347"
    ]
},
  "bbox": [],
  "geometry": {"coordinates":[77.166667,12.233333],"type":"Point"}
}