{
  "id": 2461752,
  "type": "Feature",
  "properties": {
    "tgn:hierarchy":[
        "tgn:2461752",
        "tgn:1000001",
        "tgn:7012149",
        "tgn:2000718",
        "tgn:7007254",
        "tgn:7029392"
    ],
    "tgn:id":2461752,
    "tgn:name":"Little Timber Creek",
    "tgn:placetype":[
        "aat:300008706"
    ]
},
  "bbox": [],
  "geometry": {"coordinates":[-96.35,39.8167],"type":"Point"}
}