<<<<<<< HEAD
{
  "id": 2331183,
  "type": "Feature",
  "properties": {
    "tgn:hierarchy":[
        "tgn:2331183",
        "tgn:1000001",
        "tgn:7012149",
        "tgn:7019676",
        "tgn:7007566",
        "tgn:7029392"
    ],
    "tgn:id":2331183,
    "tgn:name":"Flat Top Hill",
    "tgn:placetype":[
        "aat:300008798"
    ]
},
  "bbox": [],
  "geometry": {"coordinates":[-108.3,35.7333],"type":"Point"}
}
=======
{"geometry":{"type":"Point","coordinates":[-108.300000,35.733300]},"type":"Feature","properties":{"hierarchy":["tgn:2331183","tgn:1000001","tgn:7012149","tgn:7019676","tgn:7007566","tgn:7029392"],"placetype":["aat:300008798"],"id":2331183,"name:xx":"Flat Top Hill"}}
>>>>>>> 03f74aca74312dbeaf24d7e61306dd6a786dc3d0
