{
  "id": 2139210,
  "type": "Feature",
  "properties": {
    "tgn:hierarchy":[
        "tgn:2139210",
        "tgn:1000001",
        "tgn:7012149",
        "tgn:7007157",
        "tgn:2000184",
        "tgn:7029392"
    ],
    "tgn:id":2139210,
    "tgn:name":"Ashurst Lake",
    "tgn:placetype":[
        "aat:300008680"
    ]
},
  "bbox": [],
  "geometry": {"coordinates":[-120.95,40.7333],"type":"Point"}
}