{
  "id": 7217880,
  "type": "Feature",
  "properties": {
    "tgn:hierarchy":[
        "tgn:7217880",
        "tgn:7011161",
        "tgn:7002674",
        "tgn:1000003",
        "tgn:1000074",
        "tgn:7029392"
    ],
    "tgn:id":7217880,
    "tgn:name":"Sylim\u00e1 Vr\u00fdsi",
    "tgn:placetype":[
        "aat:300008697"
    ]
},
  "bbox": [],
  "geometry": {"coordinates":[25.972778,38.447222],"type":"Point"}
}