<<<<<<< HEAD
{
  "id": 7353629,
  "type": "Feature",
  "properties": {
    "tgn:hierarchy":[
        "tgn:7353629",
        "tgn:1000001",
        "tgn:7005593",
        "tgn:7005560",
        "tgn:7029392"
    ],
    "tgn:id":7353629,
    "tgn:name":"Bernal",
    "tgn:placetype":[
        "aat:300008347"
    ]
},
  "bbox": [],
  "geometry": {"coordinates":[-99.95,20.75],"type":"Point"}
}
=======
{"geometry":{"type":"Point","coordinates":[-99.950000,20.750000]},"type":"Feature","properties":{"hierarchy":["tgn:7353629","tgn:1000001","tgn:7005593","tgn:7005560","tgn:7029392"],"placetype":["aat:300008347"],"id":7353629,"name:xx":"Bernal"}}
>>>>>>> 03f74aca74312dbeaf24d7e61306dd6a786dc3d0
