{
  "id": 2185131,
  "type": "Feature",
  "properties": {
    "tgn:hierarchy":[
        "tgn:2185131",
        "tgn:1000001",
        "tgn:7012149",
        "tgn:1002464",
        "tgn:7007826",
        "tgn:7029392"
    ],
    "tgn:id":2185131,
    "tgn:name":"Boggy Branch",
    "tgn:placetype":[
        "aat:300008699"
    ]
},
  "bbox": [],
  "geometry": {"coordinates":[-95.65,32.1667],"type":"Point"}
}