{
  "id": 7589262,
  "type": "Feature",
  "properties": {
    "tgn:hierarchy":[
        "tgn:7589262",
        "tgn:1000004",
        "tgn:7000198",
        "tgn:7000799",
        "tgn:7029392"
    ],
    "tgn:id":7589262,
    "tgn:name:en":"Laisar",
    "tgn:placetype":[
        "aat:300008347"
    ]
},
  "bbox": [],
  "geometry": {"coordinates":[74.370817,34.298388],"type":"Point"}
}