{
  "id": 2052791,
  "type": "Feature",
  "properties": {
    "tgn:hierarchy":[
        "tgn:2052791",
        "tgn:1000001",
        "tgn:7012149",
        "tgn:1002760",
        "tgn:7007520",
        "tgn:7029392"
    ],
    "tgn:id":2052791,
    "tgn:name":"Noordeloos",
    "tgn:placetype":[
        "aat:300008347",
        "aat:300387210"
    ]
},
  "bbox": [],
  "geometry": {"coordinates":[-86.05,42.8333],"type":"Point"}
}