<<<<<<< HEAD
{
  "id": 7376876,
  "type": "Feature",
  "properties": {
    "tgn:hierarchy":[
        "tgn:7376876",
        "tgn:1000001",
        "tgn:7005601",
        "tgn:7005560",
        "tgn:7029392"
    ],
    "tgn:id":7376876,
    "tgn:name":"La Tortuga",
    "tgn:placetype":[
        "aat:300008347"
    ]
},
  "bbox": [],
  "geometry": {"coordinates":[-102.15,24.666667],"type":"Point"}
}
=======
{"geometry":{"type":"Point","coordinates":[-102.150000,24.666667]},"type":"Feature","properties":{"hierarchy":["tgn:7376876","tgn:1000001","tgn:7005601","tgn:7005560","tgn:7029392"],"placetype":["aat:300008347"],"id":7376876,"name:xx":"La Tortuga"}}
>>>>>>> 03f74aca74312dbeaf24d7e61306dd6a786dc3d0
