{
  "id": 2198171,
  "type": "Feature",
  "properties": {
    "tgn:hierarchy":[
        "tgn:2198171",
        "tgn:1000001",
        "tgn:7012149",
        "tgn:2001864",
        "tgn:7007825",
        "tgn:7029392"
    ],
    "tgn:id":2198171,
    "tgn:name":"Brownlow Creek",
    "tgn:placetype":[
        "aat:300008706"
    ]
},
  "bbox": [],
  "geometry": {"coordinates":[-87.1333,35.45],"type":"Point"}
}