<<<<<<< HEAD
{
  "id": 2259653,
  "type": "Feature",
  "properties": {
    "tgn:hierarchy":[
        "tgn:2259653",
        "tgn:1000001",
        "tgn:7012149",
        "tgn:7007157",
        "tgn:1002858",
        "tgn:7029392"
    ],
    "tgn:id":2259653,
    "tgn:name":"Cougar Canyon",
    "tgn:placetype":[
        "aat:300008761"
    ]
},
  "bbox": [],
  "geometry": {"coordinates":[-116.55,33.3167],"type":"Point"}
}
=======
{"geometry":{"type":"Point","coordinates":[-116.550000,33.316700]},"type":"Feature","properties":{"hierarchy":["tgn:2259653","tgn:1000001","tgn:7012149","tgn:7007157","tgn:1002858","tgn:7029392"],"placetype":["aat:300008761"],"id":2259653,"name:xx":"Cougar Canyon"}}
>>>>>>> 03f74aca74312dbeaf24d7e61306dd6a786dc3d0
