{
  "id": 7330532,
  "type": "Feature",
  "properties": {
    "tgn:hierarchy":[
        "tgn:7330532",
        "tgn:7002825",
        "tgn:7016622",
        "tgn:1000003",
        "tgn:1000095",
        "tgn:7029392"
    ],
    "tgn:id":7330532,
    "tgn:name":"Herrero, Paso del",
    "tgn:placetype":[
        "aat:300387026"
    ]
},
  "bbox": [],
  "geometry": {"coordinates":[-15.816667,28.016667],"type":"Point"}
}