{
  "id": 1086368,
  "type": "Feature",
  "properties": {
    "tgn:hierarchy":[
        "tgn:1086368",
        "tgn:1001451",
        "tgn:1000004",
        "tgn:7018453",
        "tgn:1000144",
        "tgn:7029392"
    ],
    "tgn:id":1086368,
    "tgn:name":"Hac\u0131bekta\u015f",
    "tgn:placetype":[
        "aat:300008347"
    ]
},
  "bbox": [],
  "geometry": {"coordinates":[34.5667,38.9333],"type":"Point"}
}