{
  "id": 1054206,
  "type": "Feature",
  "properties": {
    "tgn:hierarchy":[
        "tgn:1054206",
        "tgn:1000004",
        "tgn:1003407",
        "tgn:7018214",
        "tgn:7002435",
        "tgn:7029392"
    ],
    "tgn:id":1054206,
    "tgn:name":"Gubino",
    "tgn:placetype":[
        "aat:300008347"
    ]
},
  "bbox": [],
  "geometry": {"coordinates":[48.7333,53.3167],"type":"Point"}
}