{
  "id": 2274856,
  "type": "Feature",
  "properties": {
    "tgn:hierarchy":[
        "tgn:2274856",
        "tgn:1000001",
        "tgn:7012149",
        "tgn:2002372",
        "tgn:7007923",
        "tgn:7029392"
    ],
    "tgn:id":2274856,
    "tgn:name":"Damrow Reservoir",
    "tgn:placetype":[
        "aat:300006191"
    ]
},
  "bbox": [],
  "geometry": {"coordinates":[-104.5333,42.4167],"type":"Point"}
}