{
  "id": 7220087,
  "type": "Feature",
  "properties": {
    "tgn:hierarchy":[
        "tgn:7220087",
        "tgn:7002707",
        "tgn:7002705",
        "tgn:1000003",
        "tgn:1000074",
        "tgn:7029392"
    ],
    "tgn:id":7220087,
    "tgn:name":"Technit\u00ed L\u00edmni A\u00f3ou",
    "tgn:placetype":[
        "aat:300006191"
    ]
},
  "bbox": [],
  "geometry": {"coordinates":[21.097222,39.827778],"type":"Point"}
}