{
  "id": 2506080,
  "type": "Feature",
  "properties": {
    "tgn:hierarchy":[
        "tgn:2506080",
        "tgn:1000001",
        "tgn:2000470",
        "tgn:7012149",
        "tgn:7007250",
        "tgn:7029392"
    ],
    "tgn:id":2506080,
    "tgn:name":"Merino Creek",
    "tgn:placetype":[
        "aat:300008706"
    ]
},
  "bbox": [],
  "geometry": {"coordinates":[-114.8667,44.6167],"type":"Point"}
}