{
  "id": 2726151,
  "type": "Feature",
  "properties": {
    "tgn:hierarchy":[
        "tgn:2726151",
        "tgn:1000001",
        "tgn:7016172",
        "tgn:7012149",
        "tgn:2000155",
        "tgn:7029392"
    ],
    "tgn:id":2726151,
    "tgn:name":"Tow Point",
    "tgn:placetype":[
        "aat:300008850"
    ]
},
  "bbox": [],
  "geometry": {"coordinates":[-93.35,35.7333],"type":"Point"}
}