{
  "id": 2251430,
  "type": "Feature",
  "properties": {
    "tgn:hierarchy":[
        "tgn:2251430",
        "tgn:1000001",
        "tgn:7012149",
        "tgn:2001036",
        "tgn:7007521",
        "tgn:7029392"
    ],
    "tgn:id":2251430,
    "tgn:name":"Comfort Lake",
    "tgn:placetype":[
        "aat:300008680"
    ]
},
  "bbox": [],
  "geometry": {"coordinates":[-91.2333,47.75],"type":"Point"}
}