<<<<<<< HEAD
{
  "id": 7352088,
  "type": "Feature",
  "properties": {
    "tgn:hierarchy":[
        "tgn:7352088",
        "tgn:1000001",
        "tgn:1001960",
        "tgn:7005560",
        "tgn:7029392"
    ],
    "tgn:id":7352088,
    "tgn:name":"Rancho de las Barrancas",
    "tgn:placetype":[
        "aat:300000241"
    ]
},
  "bbox": [],
  "geometry": {"coordinates":[-109.816667,28.05],"type":"Point"}
}
=======
{"geometry":{"type":"Point","coordinates":[-109.816667,28.050000]},"type":"Feature","properties":{"hierarchy":["tgn:7352088","tgn:1000001","tgn:1001960","tgn:7005560","tgn:7029392"],"placetype":["aat:300000241"],"id":7352088,"name:xx":"Rancho de las Barrancas"}}
>>>>>>> 03f74aca74312dbeaf24d7e61306dd6a786dc3d0
