{
  "id": 2487955,
  "type": "Feature",
  "properties": {
    "tgn:hierarchy":[
        "tgn:2487955",
        "tgn:1000001",
        "tgn:7006451",
        "tgn:7012149",
        "tgn:2000097",
        "tgn:7029392"
    ],
    "tgn:id":2487955,
    "tgn:name":"Maggie May Spring",
    "tgn:placetype":[
        "aat:300008697"
    ]
},
  "bbox": [],
  "geometry": {"coordinates":[-111.8667,33.9833],"type":"Point"}
}