{
  "id": 2094810,
  "type": "Feature",
  "properties": {
    "tgn:hierarchy":[
        "tgn:2094810",
        "tgn:1000001",
        "tgn:7012149",
        "tgn:1002387",
        "tgn:7007710",
        "tgn:7029392"
    ],
    "tgn:id":2094810,
    "tgn:name":"Zullinger",
    "tgn:placetype":[
        "aat:300008347"
    ]
},
  "bbox": [],
  "geometry": {"coordinates":[-77.6167,39.7667],"type":"Point"}
}