{
  "id": 2634661,
  "type": "Feature",
  "properties": {
    "tgn:hierarchy":[
        "tgn:2634661",
        "tgn:1000001",
        "tgn:2124001",
        "tgn:7012149",
        "tgn:7007516",
        "tgn:7029392"
    ],
    "tgn:id":2634661,
    "tgn:name":"Ruth, Lake",
    "tgn:placetype":[
        "aat:300008680"
    ]
},
  "bbox": [],
  "geometry": {"coordinates":[-76.8833,38.6833],"type":"Point"}
}