<<<<<<< HEAD
{
  "id": 7055629,
  "type": "Feature",
  "properties": {
    "tgn:hierarchy":[
        "tgn:7055629",
        "tgn:7003127",
        "tgn:1000003",
        "tgn:7008516",
        "tgn:1000080",
        "tgn:7029392"
    ],
    "tgn:id":7055629,
    "tgn:name":"Miravalle",
    "tgn:placetype":[
        "aat:300008347"
    ]
},
  "bbox": [],
  "geometry": {"coordinates":[11.616667,44.583333],"type":"Point"}
}
=======
{"geometry":{"type":"Point","coordinates":[11.616667,44.583333]},"type":"Feature","properties":{"hierarchy":["tgn:7055629","tgn:7003127","tgn:1000003","tgn:7008516","tgn:1000080","tgn:7029392"],"placetype":["aat:300008347"],"id":7055629,"name:xx":"Miravalle"}}
>>>>>>> 03f74aca74312dbeaf24d7e61306dd6a786dc3d0
