{
  "id": 2548782,
  "type": "Feature",
  "properties": {
    "tgn:hierarchy":[
        "tgn:2548782",
        "tgn:1000001",
        "tgn:7012149",
        "tgn:1003031",
        "tgn:7007826",
        "tgn:7029392"
    ],
    "tgn:id":2548782,
    "tgn:name":"North Pecan Creek",
    "tgn:placetype":[
        "aat:300008706"
    ]
},
  "bbox": [],
  "geometry": {"coordinates":[-97.4167,33.3833],"type":"Point"}
}