{
  "id": 2386623,
  "type": "Feature",
  "properties": {
    "tgn:hierarchy":[
        "tgn:2386623",
        "tgn:1002933",
        "tgn:1000001",
        "tgn:7012149",
        "tgn:7007239",
        "tgn:7029392"
    ],
    "tgn:id":2386623,
    "tgn:name":"Heritage Village",
    "tgn:placetype":[
        "aat:300008347"
    ]
},
  "bbox": [],
  "geometry": {"coordinates":[-75.6167,38.65],"type":"Point"}
}