{
  "id": 7061756,
  "type": "Feature",
  "properties": {
    "tgn:hierarchy":[
        "tgn:7061756",
        "tgn:1000003",
        "tgn:7003677",
        "tgn:7000084",
        "tgn:7029392"
    ],
    "tgn:id":7061756,
    "tgn:name":"Auf dem Kartel",
    "tgn:placetype":[
        "aat:300008347"
    ]
},
  "bbox": [],
  "geometry": {"coordinates":[8.666667,52.15],"type":"Point"}
}