{
  "id": 2531907,
  "type": "Feature",
  "properties": {
    "tgn:hierarchy":[
        "tgn:2531907",
        "tgn:7002659",
        "tgn:1000001",
        "tgn:7012149",
        "tgn:2000029",
        "tgn:7029392"
    ],
    "tgn:id":2531907,
    "tgn:name":"Mullins Branch",
    "tgn:placetype":[
        "aat:300008699"
    ]
},
  "bbox": [],
  "geometry": {"coordinates":[-87.75,34.35],"type":"Point"}
}