<<<<<<< HEAD
{
  "id": 7028583,
  "type": "Feature",
  "properties": {
    "tgn:hierarchy":[
        "tgn:7028583",
        "tgn:7002445",
        "tgn:1000003",
        "tgn:7008160",
        "tgn:7008591",
        "tgn:7029392"
    ],
    "tgn:id":7028583,
    "tgn:name":"West Runton",
    "tgn:placetype":[
        "aat:300008347",
        "aat:300387314",
        "aat:300000547",
        "aat:300008372"
    ]
},
  "bbox": [],
  "geometry": {"coordinates":[1.25,52.933333],"type":"Point"}
}
=======
{"geometry":{"type":"Point","coordinates":[1.250000,52.933333]},"type":"Feature","properties":{"hierarchy":["tgn:7028583","tgn:7002445","tgn:1000003","tgn:7008160","tgn:7008591","tgn:7029392"],"placetype":["aat:300008347","aat:300387314","aat:300000547","aat:300008372"],"id":7028583,"name:xx":"West Runton"}}
>>>>>>> 03f74aca74312dbeaf24d7e61306dd6a786dc3d0
