<<<<<<< HEAD
{
  "id": 2157072,
  "type": "Feature",
  "properties": {
    "tgn:hierarchy":[
        "tgn:2157072",
        "tgn:1000001",
        "tgn:7012149",
        "tgn:2002278",
        "tgn:7013961",
        "tgn:7029392"
    ],
    "tgn:id":2157072,
    "tgn:name":"Beaver Branch",
    "tgn:placetype":[
        "aat:300008699"
    ]
},
  "bbox": [],
  "geometry": {"coordinates":[-81.05,37.3833],"type":"Point"}
}
=======
{"geometry":{"type":"Point","coordinates":[-81.050000,37.383300]},"type":"Feature","properties":{"hierarchy":["tgn:2157072","tgn:1000001","tgn:7012149","tgn:2002278","tgn:7013961","tgn:7029392"],"placetype":["aat:300008699"],"id":2157072,"name:xx":"Beaver Branch"}}
>>>>>>> 03f74aca74312dbeaf24d7e61306dd6a786dc3d0
