{
  "id": 2146857,
  "type": "Feature",
  "properties": {
    "tgn:hierarchy":[
        "tgn:2146857",
        "tgn:7002659",
        "tgn:1000001",
        "tgn:7012149",
        "tgn:2000031",
        "tgn:7029392"
    ],
    "tgn:id":2146857,
    "tgn:name":"Banks Lake",
    "tgn:placetype":[
        "aat:300006191"
    ]
},
  "bbox": [],
  "geometry": {"coordinates":[-87.9167,32.8333],"type":"Point"}
}