{
  "id": 1053090,
  "type": "Feature",
  "properties": {
    "tgn:hierarchy":[
        "tgn:1053090",
        "tgn:1000004",
        "tgn:7011573",
        "tgn:7018214",
        "tgn:7002435",
        "tgn:7029392"
    ],
    "tgn:id":1053090,
    "tgn:name":"Bronnitsy",
    "tgn:placetype":[
        "aat:300008347"
    ]
},
  "bbox": [],
  "geometry": {"coordinates":[38.2667,55.4167],"type":"Point"}
}