{
  "id": 2300589,
  "type": "Feature",
  "properties": {
    "tgn:hierarchy":[
        "tgn:2300589",
        "tgn:1000001",
        "tgn:7014352",
        "tgn:7012149",
        "tgn:7007564",
        "tgn:7029392"
    ],
    "tgn:id":2300589,
    "tgn:name":"Dumplingtown Hill",
    "tgn:placetype":[
        "aat:300008798"
    ]
},
  "bbox": [],
  "geometry": {"coordinates":[-71.2333,43.0333],"type":"Point"}
}