{
  "id": 7231977,
  "type": "Feature",
  "properties": {
    "tgn:hierarchy":[
        "tgn:7231977",
        "tgn:7002718",
        "tgn:7002715",
        "tgn:1000003",
        "tgn:1000074",
        "tgn:7029392"
    ],
    "tgn:id":7231977,
    "tgn:name":"Koulo\u00fara",
    "tgn:placetype":[
        "aat:300008347"
    ]
},
  "bbox": [],
  "geometry": {"coordinates":[22.318056,40.545278],"type":"Point"}
}