{
  "id": 7156128,
  "type": "Feature",
  "properties": {
    "tgn:hierarchy":[
        "tgn:7156128",
        "tgn:7003669",
        "tgn:1000003",
        "tgn:7000084",
        "tgn:7029392"
    ],
    "tgn:id":7156128,
    "tgn:name":"Kleinaitingen",
    "tgn:placetype":[
        "aat:300008347"
    ]
},
  "bbox": [],
  "geometry": {"coordinates":[10.833333,48.216667],"type":"Point"}
}