{
  "id": 2763901,
  "type": "Feature",
  "properties": {
    "tgn:hierarchy":[
        "tgn:2763901",
        "tgn:1000001",
        "tgn:2001596",
        "tgn:7012149",
        "tgn:7007705",
        "tgn:7029392"
    ],
    "tgn:id":2763901,
    "tgn:name":"Wheaton Lake",
    "tgn:placetype":[
        "aat:300008680"
    ]
},
  "bbox": [],
  "geometry": {"coordinates":[-99.7833,48.9167],"type":"Point"}
}