<<<<<<< HEAD
{
  "id": 2763901,
  "type": "Feature",
  "properties": {
    "tgn:hierarchy":[
        "tgn:2763901",
        "tgn:1000001",
        "tgn:2001596",
        "tgn:7012149",
        "tgn:7007705",
        "tgn:7029392"
    ],
    "tgn:id":2763901,
    "tgn:name":"Wheaton Lake",
    "tgn:placetype":[
        "aat:300008680"
    ]
},
  "bbox": [],
  "geometry": {"coordinates":[-99.7833,48.9167],"type":"Point"}
}
=======
{"geometry":{"type":"Point","coordinates":[-99.783300,48.916700]},"type":"Feature","properties":{"hierarchy":["tgn:2763901","tgn:1000001","tgn:2001596","tgn:7012149","tgn:7007705","tgn:7029392"],"placetype":["aat:300008680"],"id":2763901,"name:xx":"Wheaton Lake"}}
>>>>>>> 03f74aca74312dbeaf24d7e61306dd6a786dc3d0
