{
  "id": 2727854,
  "type": "Feature",
  "properties": {
    "tgn:hierarchy":[
        "tgn:2727854",
        "tgn:1000001",
        "tgn:2001418",
        "tgn:7012149",
        "tgn:7007526",
        "tgn:7029392"
    ],
    "tgn:id":2727854,
    "tgn:name":"Tramps Mine",
    "tgn:placetype":[
        "aat:300000390"
    ]
},
  "bbox": [],
  "geometry": {"coordinates":[-116.8333,36.8833],"type":"Point"}
}