{
  "id": 1070653,
  "type": "Feature",
  "properties": {
    "tgn:hierarchy":[
        "tgn:1070653",
        "tgn:1000004",
        "tgn:7002076",
        "tgn:1000111",
        "tgn:7029392"
    ],
    "tgn:id":1070653,
    "tgn:name":"Nantian",
    "tgn:placetype":[
        "aat:300008347"
    ]
},
  "bbox": [],
  "geometry": {"coordinates":[119.9667,27.9167],"type":"Point"}
}