{
  "id": 2412740,
  "type": "Feature",
  "properties": {
    "tgn:hierarchy":[
        "tgn:2412740",
        "tgn:1000001",
        "tgn:7012149",
        "tgn:1002633",
        "tgn:7007252",
        "tgn:7029392"
    ],
    "tgn:id":2412740,
    "tgn:name":"Ingallston",
    "tgn:placetype":[
        "aat:300008347"
    ]
},
  "bbox": [],
  "geometry": {"coordinates":[-86.0833,39.7167],"type":"Point"}
}