{
  "id": 7456239,
  "type": "Feature",
  "properties": {
    "tgn:hierarchy":[
        "tgn:7456239",
        "tgn:7002445",
        "tgn:1000003",
        "tgn:7008117",
        "tgn:7008591",
        "tgn:7029392"
    ],
    "tgn:id":7456239,
    "tgn:name:en":"Clifton",
    "tgn:placetype":[
        "aat:300008347"
    ]
},
  "bbox": [],
  "geometry": {"coordinates":[-2.716667,54.616667],"type":"Point"}
}