{
  "id": 2359227,
  "type": "Feature",
  "properties": {
    "tgn:hierarchy":[
        "tgn:2359227",
        "tgn:1000001",
        "tgn:7012149",
        "tgn:7007157",
        "tgn:1002621",
        "tgn:7029392"
    ],
    "tgn:id":2359227,
    "tgn:name":"Granite Stairway",
    "tgn:placetype":[
        "aat:300008798"
    ]
},
  "bbox": [],
  "geometry": {"coordinates":[-119.1167,37.5833],"type":"Point"}
}