{
  "id": 2578424,
  "type": "Feature",
  "properties": {
    "tgn:hierarchy":[
        "tgn:2578424",
        "tgn:1000001",
        "tgn:7012149",
        "tgn:2002379",
        "tgn:7007923",
        "tgn:7029392"
    ],
    "tgn:id":2578424,
    "tgn:name":"Phelps Enlargement Thomas Reservoir",
    "tgn:placetype":[
        "aat:300006191"
    ]
},
  "bbox": [],
  "geometry": {"coordinates":[-109.1833,44.2167],"type":"Point"}
}