<<<<<<< HEAD
{
  "id": 2760006,
  "type": "Feature",
  "properties": {
    "tgn:hierarchy":[
        "tgn:2760006",
        "tgn:7006450",
        "tgn:1000001",
        "tgn:7019698",
        "tgn:7012149",
        "tgn:7029392"
    ],
    "tgn:id":2760006,
    "tgn:name":"West Fork Moose River",
    "tgn:placetype":[
        "aat:300008707"
    ]
},
  "bbox": [],
  "geometry": {"coordinates":[-150.7,60.6167],"type":"Point"}
}
=======
{"geometry":{"type":"Point","coordinates":[-150.700000,60.616700]},"type":"Feature","properties":{"hierarchy":["tgn:2760006","tgn:7006450","tgn:1000001","tgn:7019698","tgn:7012149","tgn:7029392"],"placetype":["aat:300008707"],"id":2760006,"name:xx":"West Fork Moose River"}}
>>>>>>> 03f74aca74312dbeaf24d7e61306dd6a786dc3d0
