{
  "id": 2382989,
  "type": "Feature",
  "properties": {
    "tgn:hierarchy":[
        "tgn:2382989",
        "tgn:1000001",
        "tgn:7012149",
        "tgn:2000796",
        "tgn:7007255",
        "tgn:7029392"
    ],
    "tgn:id":2382989,
    "tgn:name":"Head Of Rough Spring",
    "tgn:placetype":[
        "aat:300008697"
    ]
},
  "bbox": [],
  "geometry": {"coordinates":[-86.0667,37.7167],"type":"Point"}
}