<<<<<<< HEAD
{
  "id": 7171947,
  "type": "Feature",
  "properties": {
    "tgn:hierarchy":[
        "tgn:7171947",
        "tgn:1000003",
        "tgn:7003676",
        "tgn:7000084",
        "tgn:7029392"
    ],
    "tgn:id":7171947,
    "tgn:name":"Helmstedt, Staatsforst",
    "tgn:placetype":[
        "aat:300008863"
    ]
},
  "bbox": [],
  "geometry": {"coordinates":[11.05,52.25],"type":"Point"}
}
=======
{"geometry":{"type":"Point","coordinates":[11.050000,52.250000]},"type":"Feature","properties":{"hierarchy":["tgn:7171947","tgn:1000003","tgn:7003676","tgn:7000084","tgn:7029392"],"placetype":["aat:300008863"],"id":7171947,"name:xx":"Helmstedt, Staatsforst"}}
>>>>>>> 03f74aca74312dbeaf24d7e61306dd6a786dc3d0
