{
  "id": 1066579,
  "type": "Feature",
  "properties": {
    "tgn:hierarchy":[
        "tgn:1066579",
        "tgn:1000004",
        "tgn:1000958",
        "tgn:1000111",
        "tgn:7029392"
    ],
    "tgn:id":1066579,
    "tgn:name":"Anzhuang",
    "tgn:placetype":[
        "aat:300008347"
    ]
},
  "bbox": [],
  "geometry": {"coordinates":[121.0167,31.0667],"type":"Point"}
}