{
  "id": 7224784,
  "type": "Feature",
  "properties": {
    "tgn:hierarchy":[
        "tgn:7224784",
        "tgn:4003773",
        "tgn:7001395",
        "tgn:1000003",
        "tgn:1000074",
        "tgn:7029392"
    ],
    "tgn:id":7224784,
    "tgn:name":"Rin\u00f3rrema",
    "tgn:placetype":[
        "aat:300008699"
    ]
},
  "bbox": [],
  "geometry": {"coordinates":[22.266667,38.716667],"type":"Point"}
}