{
  "id": 7440881,
  "type": "Feature",
  "properties": {
    "tgn:hierarchy":[
        "tgn:7440881",
        "tgn:7005580",
        "tgn:1000001",
        "tgn:7005560",
        "tgn:7029392"
    ],
    "tgn:id":7440881,
    "tgn:name":"Santa Margarita",
    "tgn:placetype":[
        "aat:300008347"
    ]
},
  "bbox": [],
  "geometry": {"coordinates":[-91.483333,17.383333],"type":"Point"}
}