{
  "id": 1118440,
  "type": "Feature",
  "properties": {
    "tgn:hierarchy":[
        "tgn:1118440",
        "tgn:7005694",
        "tgn:7005685",
        "tgn:1000001",
        "tgn:7029392"
    ],
    "tgn:id":1118440,
    "tgn:name":"Touchwood Lake",
    "tgn:placetype":[
        "aat:300008680"
    ]
},
  "bbox": [],
  "geometry": {"coordinates":[-111.3833,54.8333],"type":"Point"}
}