{
  "id": 7565195,
  "type": "Feature",
  "properties": {
    "tgn:hierarchy":[
        "tgn:7565195",
        "tgn:1000004",
        "tgn:7000198",
        "tgn:1001894",
        "tgn:7029392"
    ],
    "tgn:id":7565195,
    "tgn:name:en":"Badora",
    "tgn:placetype":[
        "aat:300008347"
    ]
},
  "bbox": [],
  "geometry": {"coordinates":[79.106997,24.809964],"type":"Point"}
}