{
  "id": 2676340,
  "type": "Feature",
  "properties": {
    "tgn:hierarchy":[
        "tgn:2676340",
        "tgn:1000001",
        "tgn:7012149",
        "tgn:7007157",
        "tgn:1002858",
        "tgn:7029392"
    ],
    "tgn:id":2676340,
    "tgn:name":"Sourdough Spring",
    "tgn:placetype":[
        "aat:300008697"
    ]
},
  "bbox": [],
  "geometry": {"coordinates":[-116.8167,33.35],"type":"Point"}
}