{
  "id": 2192793,
  "type": "Feature",
  "properties": {
    "tgn:hierarchy":[
        "tgn:2192793",
        "tgn:1000001",
        "tgn:7012149",
        "tgn:1003019",
        "tgn:7007826",
        "tgn:7029392"
    ],
    "tgn:id":2192793,
    "tgn:name":"Bratcher Slough",
    "tgn:placetype":[
        "aat:300008699"
    ]
},
  "bbox": [],
  "geometry": {"coordinates":[-96.0667,29.4667],"type":"Point"}
}