{
  "id": 1081253,
  "type": "Feature",
  "properties": {
    "tgn:hierarchy":[
        "tgn:1081253",
        "tgn:1000004",
        "tgn:7000896",
        "tgn:7000277",
        "tgn:1000120",
        "tgn:7029392"
    ],
    "tgn:id":1081253,
    "tgn:name":"Seta",
    "tgn:placetype":[
        "aat:300008347"
    ]
},
  "bbox": [],
  "geometry": {"coordinates":[135.9167,34.9667],"type":"Point"}
}