{
  "id": 1109872,
  "type": "Feature",
  "properties": {
    "tgn:hierarchy":[
        "tgn:1109872",
        "tgn:1000004",
        "tgn:7029392"
    ],
    "tgn:id":1109872,
    "tgn:name":"Babatag, Khrebet",
    "tgn:placetype":[
        "aat:300386831"
    ]
},
  "bbox": [],
  "geometry": {"coordinates":[68.25,38.3333],"type":"Point"}
}