{
  "id": 2248564,
  "type": "Feature",
  "properties": {
    "tgn:hierarchy":[
        "tgn:2248564",
        "tgn:1000001",
        "tgn:1002245",
        "tgn:7012149",
        "tgn:7007568",
        "tgn:7029392"
    ],
    "tgn:id":2248564,
    "tgn:name":"Cold Spring Cove",
    "tgn:placetype":[
        "aat:300132316"
    ]
},
  "bbox": [],
  "geometry": {"coordinates":[-78.8667,42.0833],"type":"Point"}
}