{
  "id": 7026216,
  "type": "Feature",
  "properties": {
    "tgn:hierarchy":[
        "tgn:7026216",
        "tgn:7002445",
        "tgn:1000003",
        "tgn:7008131",
        "tgn:7008591",
        "tgn:7029392"
    ],
    "tgn:id":7026216,
    "tgn:name:en":"East Horndon",
    "tgn:placetype":[
        "aat:300008347",
        "aat:300008369"
    ]
},
  "bbox": [],
  "geometry": {"coordinates":[0.35,51.566667],"type":"Point"}
}