{
  "id": 7368304,
  "type": "Feature",
  "properties": {
    "tgn:hierarchy":[
        "tgn:7368304",
        "tgn:1000001",
        "tgn:1001960",
        "tgn:7005560",
        "tgn:7029392"
    ],
    "tgn:id":7368304,
    "tgn:name":"Grupo N\u00famero Dos",
    "tgn:placetype":[
        "aat:300008347"
    ]
},
  "bbox": [],
  "geometry": {"coordinates":[-112.268611,30.5225],"type":"Point"}
}