{
  "id": 7277383,
  "type": "Feature",
  "properties": {
    "tgn:hierarchy":[
        "tgn:7277383",
        "tgn:1001705",
        "tgn:1000049",
        "tgn:1000002",
        "tgn:7029392"
    ],
    "tgn:id":7277383,
    "tgn:name":"Yaca Yaca, Cerro",
    "tgn:placetype":[
        "aat:300008777"
    ]
},
  "bbox": [],
  "geometry": {"coordinates":[-71.966667,-35.05],"type":"Point"}
}