<<<<<<< HEAD
{
  "id": 7477684,
  "type": "Feature",
  "properties": {
    "tgn:hierarchy":[
        "tgn:7477684",
        "tgn:1000004",
        "tgn:7004300",
        "tgn:1000141",
        "tgn:7029392"
    ],
    "tgn:id":7477684,
    "tgn:name":"Zhong Shan",
    "tgn:placetype":[
        "aat:300008777"
    ]
},
  "bbox": [],
  "geometry": {"coordinates":[119.556759,23.717209],"type":"Point"}
}
=======
{"geometry":{"type":"Point","coordinates":[119.556759,23.717209]},"type":"Feature","properties":{"hierarchy":["tgn:7477684","tgn:1000004","tgn:7004300","tgn:1000141","tgn:7029392"],"placetype":["aat:300008777"],"id":7477684,"name:xx":"Zhong Shan"}}
>>>>>>> 03f74aca74312dbeaf24d7e61306dd6a786dc3d0
