<<<<<<< HEAD
{
  "id": 7370440,
  "type": "Feature",
  "properties": {
    "tgn:hierarchy":[
        "tgn:7370440",
        "tgn:1001835",
        "tgn:1000001",
        "tgn:7005560",
        "tgn:7029392"
    ],
    "tgn:id":7370440,
    "tgn:name":"Rancho Garcia",
    "tgn:placetype":[
        "aat:300000241"
    ]
},
  "bbox": [],
  "geometry": {"coordinates":[-116.333333,32.366667],"type":"Point"}
}
=======
{"geometry":{"type":"Point","coordinates":[-116.333333,32.366667]},"type":"Feature","properties":{"hierarchy":["tgn:7370440","tgn:1001835","tgn:1000001","tgn:7005560","tgn:7029392"],"placetype":["aat:300000241"],"id":7370440,"name:xx":"Rancho Garcia"}}
>>>>>>> 03f74aca74312dbeaf24d7e61306dd6a786dc3d0
