{
  "id": 7161779,
  "type": "Feature",
  "properties": {
    "tgn:hierarchy":[
        "tgn:7161779",
        "tgn:1000003",
        "tgn:7003688",
        "tgn:7000084",
        "tgn:7029392"
    ],
    "tgn:id":7161779,
    "tgn:name":"Hochmoor",
    "tgn:placetype":[
        "aat:300386886"
    ]
},
  "bbox": [],
  "geometry": {"coordinates":[9.816667,54.05],"type":"Point"}
}