{
  "id": 1137990,
  "type": "Feature",
  "properties": {
    "tgn:hierarchy":[
        "tgn:1137990",
        "tgn:1000004",
        "tgn:7011573",
        "tgn:7018214",
        "tgn:7002435",
        "tgn:7029392"
    ],
    "tgn:id":1137990,
    "tgn:name":"Nikol'skoye",
    "tgn:placetype":[
        "aat:300008347"
    ]
},
  "bbox": [],
  "geometry": {"coordinates":[36.0667,55.25],"type":"Point"}
}