{
  "id": 2210718,
  "type": "Feature",
  "properties": {
    "tgn:hierarchy":[
        "tgn:2210718",
        "tgn:1000001",
        "tgn:7006451",
        "tgn:2000093",
        "tgn:7012149",
        "tgn:7029392"
    ],
    "tgn:id":2210718,
    "tgn:name":"Butcher Creek",
    "tgn:placetype":[
        "aat:300008706"
    ]
},
  "bbox": [],
  "geometry": {"coordinates":[-111.3167,34.2833],"type":"Point"}
}