{
  "id": 7349827,
  "type": "Feature",
  "properties": {
    "tgn:hierarchy":[
        "tgn:7349827",
        "tgn:7005585",
        "tgn:1000001",
        "tgn:7005560",
        "tgn:7029392"
    ],
    "tgn:id":7349827,
    "tgn:name":"Acatepec",
    "tgn:placetype":[
        "aat:300008347"
    ]
},
  "bbox": [],
  "geometry": {"coordinates":[-98.483333,16.75],"type":"Point"}
}