{
  "id": 7228739,
  "type": "Feature",
  "properties": {
    "tgn:hierarchy":[
        "tgn:7228739",
        "tgn:7002745",
        "tgn:7017076",
        "tgn:1000003",
        "tgn:1000074",
        "tgn:7029392"
    ],
    "tgn:id":7228739,
    "tgn:name":"Kas\u00e9lla, Nis\u00eds",
    "tgn:placetype":[
        "aat:300008791"
    ]
},
  "bbox": [],
  "geometry": {"coordinates":[22.933333,36.483333],"type":"Point"}
}