{
  "id": 2308627,
  "type": "Feature",
  "properties": {
    "tgn:hierarchy":[
        "tgn:2308627",
        "tgn:1000001",
        "tgn:7012149",
        "tgn:7007157",
        "tgn:1002857",
        "tgn:7029392"
    ],
    "tgn:id":2308627,
    "tgn:name":"East Ord Mountain",
    "tgn:placetype":[
        "aat:300008798"
    ]
},
  "bbox": [],
  "geometry": {"coordinates":[-116.7667,34.6333],"type":"Point"}
}