<<<<<<< HEAD
{
  "id": 7110021,
  "type": "Feature",
  "properties": {
    "tgn:hierarchy":[
        "tgn:7110021",
        "tgn:1000003",
        "tgn:7003689",
        "tgn:7000084",
        "tgn:7029392"
    ],
    "tgn:id":7110021,
    "tgn:name":"Reihers-Berge",
    "tgn:placetype":[
        "aat:300008777"
    ]
},
  "bbox": [],
  "geometry": {"coordinates":[10.35,50.966667],"type":"Point"}
}
=======
{"geometry":{"type":"Point","coordinates":[10.350000,50.966667]},"type":"Feature","properties":{"hierarchy":["tgn:7110021","tgn:1000003","tgn:7003689","tgn:7000084","tgn:7029392"],"placetype":["aat:300008777"],"id":7110021,"name:xx":"Reihers-Berge"}}
>>>>>>> 03f74aca74312dbeaf24d7e61306dd6a786dc3d0
