{
  "id": 2291872,
  "type": "Feature",
  "properties": {
    "tgn:hierarchy":[
        "tgn:2291872",
        "tgn:1000001",
        "tgn:7012149",
        "tgn:2002382",
        "tgn:7007923",
        "tgn:7029392"
    ],
    "tgn:id":2291872,
    "tgn:name":"Dome Peak",
    "tgn:placetype":[
        "aat:300008798"
    ]
},
  "bbox": [],
  "geometry": {"coordinates":[-109.85,43.15],"type":"Point"}
}