{
  "id": 7321553,
  "type": "Feature",
  "properties": {
    "tgn:hierarchy":[
        "tgn:7321553",
        "tgn:1001702",
        "tgn:1000049",
        "tgn:1000002",
        "tgn:7029392"
    ],
    "tgn:id":7321553,
    "tgn:name":"Beloe, Alturas",
    "tgn:placetype":[
        "aat:300008777"
    ]
},
  "bbox": [],
  "geometry": {"coordinates":[-73.766667,-52.916667],"type":"Point"}
}