{
  "id": 2709688,
  "type": "Feature",
  "properties": {
    "tgn:hierarchy":[
        "tgn:2709688",
        "tgn:1000001",
        "tgn:7012149",
        "tgn:2001420",
        "tgn:7007526",
        "tgn:7029392"
    ],
    "tgn:id":2709688,
    "tgn:name":"Taft Lake",
    "tgn:placetype":[
        "aat:300008680"
    ]
},
  "bbox": [],
  "geometry": {"coordinates":[-114.45,39.3333],"type":"Point"}
}