{
  "id": 7244912,
  "type": "Feature",
  "properties": {
    "tgn:hierarchy":[
        "tgn:7244912",
        "tgn:7003465",
        "tgn:1000003",
        "tgn:1000063",
        "tgn:4012014",
        "tgn:7029392"
    ],
    "tgn:id":7244912,
    "tgn:name":"Au Grand \u00c9tang",
    "tgn:placetype":[
        "aat:300008688"
    ]
},
  "bbox": [],
  "geometry": {"coordinates":[5.766667,50.05],"type":"Point"}
}