<<<<<<< HEAD
{
  "id": 7244912,
  "type": "Feature",
  "properties": {
    "tgn:hierarchy":[
        "tgn:7244912",
        "tgn:7003465",
        "tgn:1000003",
        "tgn:1000063",
        "tgn:4012014",
        "tgn:7029392"
    ],
    "tgn:id":7244912,
    "tgn:name":"Au Grand \u00c9tang",
    "tgn:placetype":[
        "aat:300008688"
    ]
},
  "bbox": [],
  "geometry": {"coordinates":[5.766667,50.05],"type":"Point"}
}
=======
{"geometry":{"type":"Point","coordinates":[5.766667,50.050000]},"type":"Feature","properties":{"hierarchy":["tgn:7244912","tgn:7003465","tgn:1000003","tgn:1000063","tgn:4012014","tgn:7029392"],"placetype":["aat:300008688"],"id":7244912,"name:xx":"Au Grand \u00c9tang"}}
>>>>>>> 03f74aca74312dbeaf24d7e61306dd6a786dc3d0
