{
  "id": 1025111,
  "type": "Feature",
  "properties": {
    "tgn:hierarchy":[
        "tgn:1025111",
        "tgn:1001843",
        "tgn:1000002",
        "tgn:1000059",
        "tgn:7029392"
    ],
    "tgn:id":1025111,
    "tgn:name":"El Manteco",
    "tgn:placetype":[
        "aat:300008347"
    ]
},
  "bbox": [],
  "geometry": {"coordinates":[-62.5333,7.35],"type":"Point"}
}