{
  "id": 1014035,
  "type": "Feature",
  "properties": {
    "tgn:hierarchy":[
        "tgn:1014035",
        "tgn:7005685",
        "tgn:1000001",
        "tgn:7005734",
        "tgn:7029392"
    ],
    "tgn:id":1014035,
    "tgn:name":"Waskada",
    "tgn:placetype":[
        "aat:300008347"
    ]
},
  "bbox": [],
  "geometry": {"coordinates":[-100.8167,49.0833],"type":"Point"}
}