{
  "id": 1017704,
  "type": "Feature",
  "properties": {
    "tgn:hierarchy":[
        "tgn:1017704",
        "tgn:1001853",
        "tgn:1000001",
        "tgn:7005560",
        "tgn:7029392"
    ],
    "tgn:id":1017704,
    "tgn:name":"La Leona",
    "tgn:placetype":[
        "aat:300008347"
    ]
},
  "bbox": [],
  "geometry": {"coordinates":[-101.083333,25.866667],"type":"Point"}
}