{
  "id": 2148942,
  "type": "Feature",
  "properties": {
    "tgn:hierarchy":[
        "tgn:2148942",
        "tgn:1000001",
        "tgn:7012149",
        "tgn:1002350",
        "tgn:7007157",
        "tgn:7029392"
    ],
    "tgn:id":2148942,
    "tgn:name":"Barney Ridge",
    "tgn:placetype":[
        "aat:300266640"
    ]
},
  "bbox": [],
  "geometry": {"coordinates":[-120.4833,38.5333],"type":"Point"}
}