<<<<<<< HEAD
{
  "id": 7487131,
  "type": "Feature",
  "properties": {
    "tgn:hierarchy":[
        "tgn:7487131",
        "tgn:1000004",
        "tgn:7490934",
        "tgn:1000141",
        "tgn:7029392"
    ],
    "tgn:id":7487131,
    "tgn:name":"Baishui Xi",
    "tgn:placetype":[
        "aat:300008699"
    ]
},
  "bbox": [],
  "geometry": {"coordinates":[120.472222,23.3575],"type":"Point"}
}
=======
{"geometry":{"type":"Point","coordinates":[120.472222,23.357500]},"type":"Feature","properties":{"hierarchy":["tgn:7487131","tgn:1000004","tgn:7490934","tgn:1000141","tgn:7029392"],"placetype":["aat:300008699"],"id":7487131,"name:xx":"Baishui Xi"}}
>>>>>>> 03f74aca74312dbeaf24d7e61306dd6a786dc3d0
