{
  "id": 7487131,
  "type": "Feature",
  "properties": {
    "tgn:hierarchy":[
        "tgn:7487131",
        "tgn:1000004",
        "tgn:7490934",
        "tgn:1000141",
        "tgn:7029392"
    ],
    "tgn:id":7487131,
    "tgn:name":"Baishui Xi",
    "tgn:placetype":[
        "aat:300008699"
    ]
},
  "bbox": [],
  "geometry": {"coordinates":[120.472222,23.3575],"type":"Point"}
}