{
  "id": 2229515,
  "type": "Feature",
  "properties": {
    "tgn:hierarchy":[
        "tgn:2229515",
        "tgn:1000001",
        "tgn:2000774",
        "tgn:7012149",
        "tgn:7007255",
        "tgn:7029392"
    ],
    "tgn:id":2229515,
    "tgn:name":"Cedar Point Branch",
    "tgn:placetype":[
        "aat:300008699"
    ]
},
  "bbox": [],
  "geometry": {"coordinates":[-85.8167,37.9667],"type":"Point"}
}