{
  "id": 7025266,
  "type": "Feature",
  "properties": {
    "tgn:hierarchy":[
        "tgn:7025266",
        "tgn:7002445",
        "tgn:1000003",
        "tgn:7008118",
        "tgn:7008591",
        "tgn:7029392"
    ],
    "tgn:id":7025266,
    "tgn:name":"Osleston",
    "tgn:placetype":[
        "aat:300008347"
    ]
},
  "bbox": [],
  "geometry": {"coordinates":[-1.6333,52.9167],"type":"Point"}
}