{
  "id": 2547921,
  "type": "Feature",
  "properties": {
    "tgn:hierarchy":[
        "tgn:2547921",
        "tgn:1000001",
        "tgn:7012149",
        "tgn:1003026",
        "tgn:7007826",
        "tgn:7029392"
    ],
    "tgn:id":2547921,
    "tgn:name":"North Georgetown",
    "tgn:placetype":[
        "aat:300008347"
    ]
},
  "bbox": [],
  "geometry": {"coordinates":[-97.6667,30.6333],"type":"Point"}
}