{
  "id": 2299939,
  "type": "Feature",
  "properties": {
    "tgn:hierarchy":[
        "tgn:2299939",
        "tgn:1000001",
        "tgn:7012149",
        "tgn:7029392"
    ],
    "tgn:id":2299939,
    "tgn:name":"Duffield Creek",
    "tgn:placetype":[
        "aat:300008706"
    ]
},
  "bbox": [],
  "geometry": {"coordinates":[-116.9833,46.9667],"type":"Point"}
}