<<<<<<< HEAD
{
  "id": 2405112,
  "type": "Feature",
  "properties": {
    "tgn:hierarchy":[
        "tgn:2405112",
        "tgn:1000001",
        "tgn:7012149",
        "tgn:1002862",
        "tgn:7007920",
        "tgn:7029392"
    ],
    "tgn:id":2405112,
    "tgn:name":"Hudson, Point",
    "tgn:placetype":[
        "aat:300008850"
    ]
},
  "bbox": [],
  "geometry": {"coordinates":[-122.9167,48.5833],"type":"Point"}
}
=======
{"geometry":{"type":"Point","coordinates":[-122.916700,48.583300]},"type":"Feature","properties":{"hierarchy":["tgn:2405112","tgn:1000001","tgn:7012149","tgn:1002862","tgn:7007920","tgn:7029392"],"placetype":["aat:300008850"],"id":2405112,"name:xx":"Hudson, Point"}}
>>>>>>> 03f74aca74312dbeaf24d7e61306dd6a786dc3d0
