{
  "id": 2142767,
  "type": "Feature",
  "properties": {
    "tgn:hierarchy":[
        "tgn:2142767",
        "tgn:1000001",
        "tgn:7012149",
        "tgn:1002350",
        "tgn:7007157",
        "tgn:7029392"
    ],
    "tgn:id":2142767,
    "tgn:name":"Badger Hill Mine",
    "tgn:placetype":[
        "aat:300000390"
    ]
},
  "bbox": [],
  "geometry": {"coordinates":[-120.6333,38.7667],"type":"Point"}
}