{
  "id": 7281355,
  "type": "Feature",
  "properties": {
    "tgn:hierarchy":[
        "tgn:7281355",
        "tgn:1001708",
        "tgn:1000049",
        "tgn:1000002",
        "tgn:7029392"
    ],
    "tgn:id":7281355,
    "tgn:name":"San Eugenio",
    "tgn:placetype":[
        "aat:300000206"
    ]
},
  "bbox": [],
  "geometry": {"coordinates":[-70.916667,-33.65],"type":"Point"}
}