{
  "id": 7073222,
  "type": "Feature",
  "properties": {
    "tgn:hierarchy":[
        "tgn:7073222",
        "tgn:1000003",
        "tgn:7000094",
        "tgn:7000084",
        "tgn:7029392"
    ],
    "tgn:id":7073222,
    "tgn:name":"Strellin",
    "tgn:placetype":[
        "aat:300008347"
    ]
},
  "bbox": [],
  "geometry": {"coordinates":[13.483333,53.983333],"type":"Point"}
}