{
  "id": 7418394,
  "type": "Feature",
  "properties": {
    "tgn:hierarchy":[
        "tgn:7418394",
        "tgn:1001835",
        "tgn:1000001",
        "tgn:7005560",
        "tgn:7029392"
    ],
    "tgn:id":7418394,
    "tgn:name":"Belen",
    "tgn:placetype":[
        "aat:300008347"
    ]
},
  "bbox": [],
  "geometry": {"coordinates":[-116.495556,32.184444],"type":"Point"}
}