{
  "id": 2110542,
  "type": "Feature",
  "properties": {
    "tgn:hierarchy":[
        "tgn:2110542",
        "tgn:1000001",
        "tgn:7012149",
        "tgn:2002157",
        "tgn:7007919",
        "tgn:7029392"
    ],
    "tgn:id":2110542,
    "tgn:name":"Bartlick",
    "tgn:placetype":[
        "aat:300008347",
        "aat:300387210"
    ]
},
  "bbox": [],
  "geometry": {"coordinates":[-82.3167,37.2333],"type":"Point"}
}