{
  "id": 7451296,
  "type": "Feature",
  "properties": {
    "tgn:hierarchy":[
        "tgn:7451296",
        "tgn:7002444",
        "tgn:1000003",
        "tgn:7008082",
        "tgn:7008591",
        "tgn:7029392"
    ],
    "tgn:id":7451296,
    "tgn:name:en":"Fairburn Tower",
    "tgn:placetype":[
        "aat:300008057"
    ]
},
  "bbox": [],
  "geometry": {"coordinates":[-4.55,57.533333],"type":"Point"}
}