{
  "id": 7352056,
  "type": "Feature",
  "properties": {
    "tgn:hierarchy":[
        "tgn:7352056",
        "tgn:1000001",
        "tgn:1001937",
        "tgn:7005560",
        "tgn:7029392"
    ],
    "tgn:id":7352056,
    "tgn:name":"Botes",
    "tgn:placetype":[
        "aat:300008347"
    ]
},
  "bbox": [],
  "geometry": {"coordinates":[-88.716667,18.116667],"type":"Point"}
}