<<<<<<< HEAD
{
  "id": 2335445,
  "type": "Feature",
  "properties": {
    "tgn:hierarchy":[
        "tgn:2335445",
        "tgn:1000001",
        "tgn:7012149",
        "tgn:2002014",
        "tgn:7007826",
        "tgn:7029392"
    ],
    "tgn:id":2335445,
    "tgn:name":"Fort Phantom Hill, Lake",
    "tgn:placetype":[
        "aat:300006191"
    ]
},
  "bbox": [],
  "geometry": {"coordinates":[-99.6667,32.6167],"type":"Point"}
}
=======
{"geometry":{"type":"Point","coordinates":[-99.666700,32.616700]},"type":"Feature","properties":{"hierarchy":["tgn:2335445","tgn:1000001","tgn:7012149","tgn:2002014","tgn:7007826","tgn:7029392"],"placetype":["aat:300006191"],"id":2335445,"name:xx":"Fort Phantom Hill, Lake"}}
>>>>>>> 03f74aca74312dbeaf24d7e61306dd6a786dc3d0
