{
  "id": 2246718,
  "type": "Feature",
  "properties": {
    "tgn:hierarchy":[
        "tgn:2246718",
        "tgn:1000001",
        "tgn:7012149",
        "tgn:1002931",
        "tgn:7007919",
        "tgn:7029392"
    ],
    "tgn:id":2246718,
    "tgn:name":"Cobham Bay",
    "tgn:placetype":[
        "aat:300132316"
    ]
},
  "bbox": [],
  "geometry": {"coordinates":[-76.7167,37.15],"type":"Point"}
}