{
  "id": 7373070,
  "type": "Feature",
  "properties": {
    "tgn:hierarchy":[
        "tgn:7373070",
        "tgn:1000001",
        "tgn:1001960",
        "tgn:7005560",
        "tgn:7029392"
    ],
    "tgn:id":7373070,
    "tgn:name":"Rancho La C\u00e9ri",
    "tgn:placetype":[
        "aat:300000241"
    ]
},
  "bbox": [],
  "geometry": {"coordinates":[-110.883333,28.316667],"type":"Point"}
}