{
  "id": 2170165,
  "type": "Feature",
  "properties": {
    "tgn:hierarchy":[
        "tgn:2170165",
        "tgn:1000001",
        "tgn:1002724",
        "tgn:7012149",
        "tgn:7007517",
        "tgn:7029392"
    ],
    "tgn:id":2170165,
    "tgn:name":"Big Quamino Rock",
    "tgn:placetype":[
        "aat:300011692"
    ]
},
  "bbox": [],
  "geometry": {"coordinates":[-70.7833,42.25],"type":"Point"}
}