{
  "id": 7366376,
  "type": "Feature",
  "properties": {
    "tgn:hierarchy":[
        "tgn:7366376",
        "tgn:1000001",
        "tgn:7005601",
        "tgn:7005560",
        "tgn:7029392"
    ],
    "tgn:id":7366376,
    "tgn:name":"El Tesorero",
    "tgn:placetype":[
        "aat:300008347"
    ]
},
  "bbox": [],
  "geometry": {"coordinates":[-102.983333,22.816667],"type":"Point"}
}