{
  "id": 7336094,
  "type": "Feature",
  "properties": {
    "tgn:hierarchy":[
        "tgn:7336094",
        "tgn:7008911",
        "tgn:1000003",
        "tgn:7002763",
        "tgn:1000095",
        "tgn:7029392"
    ],
    "tgn:id":7336094,
    "tgn:name":"Fozana",
    "tgn:placetype":[
        "aat:300008347"
    ]
},
  "bbox": [],
  "geometry": {"coordinates":[-5.733333,43.366667],"type":"Point"}
}