{
  "id": 2283496,
  "type": "Feature",
  "properties": {
    "tgn:hierarchy":[
        "tgn:2283496",
        "tgn:1002157",
        "tgn:1000001",
        "tgn:7012149",
        "tgn:7007565",
        "tgn:7029392"
    ],
    "tgn:id":2283496,
    "tgn:name":"Delta Basin",
    "tgn:placetype":[
        "aat:300008678"
    ]
},
  "bbox": [],
  "geometry": {"coordinates":[-74.4167,39.3667],"type":"Point"}
}