<<<<<<< HEAD
{
  "id": 7471237,
  "type": "Feature",
  "properties": {
    "tgn:hierarchy":[
        "tgn:7471237",
        "tgn:7468018",
        "tgn:1000004",
        "tgn:1000141",
        "tgn:7029392"
    ],
    "tgn:id":7471237,
    "tgn:name":"Xinzhuang",
    "tgn:placetype":[
        "aat:300008347"
    ]
},
  "bbox": [],
  "geometry": {"coordinates":[120.2444,23.3613],"type":"Point"}
}
=======
{"geometry":{"type":"Point","coordinates":[120.244400,23.361300]},"type":"Feature","properties":{"hierarchy":["tgn:7471237","tgn:7468018","tgn:1000004","tgn:1000141","tgn:7029392"],"placetype":["aat:300008347"],"id":7471237,"name:xx":"Xinzhuang"}}
>>>>>>> 03f74aca74312dbeaf24d7e61306dd6a786dc3d0
