<<<<<<< HEAD
{
  "id": 2252752,
  "type": "Feature",
  "properties": {
    "tgn:hierarchy":[
        "tgn:2252752",
        "tgn:1000001",
        "tgn:7012149",
        "tgn:1002793",
        "tgn:7007240",
        "tgn:7029392"
    ],
    "tgn:id":2252752,
    "tgn:name":"Connie, Lake",
    "tgn:placetype":[
        "aat:300008680"
    ]
},
  "bbox": [],
  "geometry": {"coordinates":[-81.7167,28.05],"type":"Point"}
}
=======
{"geometry":{"type":"Point","coordinates":[-81.716700,28.050000]},"type":"Feature","properties":{"hierarchy":["tgn:2252752","tgn:1000001","tgn:7012149","tgn:1002793","tgn:7007240","tgn:7029392"],"placetype":["aat:300008680"],"id":2252752,"name:xx":"Connie, Lake"}}
>>>>>>> 03f74aca74312dbeaf24d7e61306dd6a786dc3d0
