{
  "id": 2252752,
  "type": "Feature",
  "properties": {
    "tgn:hierarchy":[
        "tgn:2252752",
        "tgn:1000001",
        "tgn:7012149",
        "tgn:1002793",
        "tgn:7007240",
        "tgn:7029392"
    ],
    "tgn:id":2252752,
    "tgn:name":"Connie, Lake",
    "tgn:placetype":[
        "aat:300008680"
    ]
},
  "bbox": [],
  "geometry": {"coordinates":[-81.7167,28.05],"type":"Point"}
}