{
  "id": 7043865,
  "type": "Feature",
  "properties": {
    "tgn:hierarchy":[
        "tgn:7043865",
        "tgn:7007850",
        "tgn:1003491",
        "tgn:1000003",
        "tgn:1000080",
        "tgn:7029392"
    ],
    "tgn:id":7043865,
    "tgn:name":"Croce Valanidi",
    "tgn:placetype":[
        "aat:300008347"
    ]
},
  "bbox": [],
  "geometry": {"coordinates":[15.683333,38.066667],"type":"Point"}
}