{
  "id": 2338769,
  "type": "Feature",
  "properties": {
    "tgn:hierarchy":[
        "tgn:2338769",
        "tgn:1000001",
        "tgn:7012149",
        "tgn:1002943",
        "tgn:7007708",
        "tgn:7029392"
    ],
    "tgn:id":2338769,
    "tgn:name":"Frank Creek",
    "tgn:placetype":[
        "aat:300008706"
    ]
},
  "bbox": [],
  "geometry": {"coordinates":[-123.8167,45.25],"type":"Point"}
}