<<<<<<< HEAD
{
  "id": 2338769,
  "type": "Feature",
  "properties": {
    "tgn:hierarchy":[
        "tgn:2338769",
        "tgn:1000001",
        "tgn:7012149",
        "tgn:1002943",
        "tgn:7007708",
        "tgn:7029392"
    ],
    "tgn:id":2338769,
    "tgn:name":"Frank Creek",
    "tgn:placetype":[
        "aat:300008706"
    ]
},
  "bbox": [],
  "geometry": {"coordinates":[-123.8167,45.25],"type":"Point"}
}
=======
{"geometry":{"type":"Point","coordinates":[-123.816700,45.250000]},"type":"Feature","properties":{"hierarchy":["tgn:2338769","tgn:1000001","tgn:7012149","tgn:1002943","tgn:7007708","tgn:7029392"],"placetype":["aat:300008706"],"id":2338769,"name:xx":"Frank Creek"}}
>>>>>>> 03f74aca74312dbeaf24d7e61306dd6a786dc3d0
