{
  "id": 7111720,
  "type": "Feature",
  "properties": {
    "tgn:hierarchy":[
        "tgn:7111720",
        "tgn:7003669",
        "tgn:1000003",
        "tgn:7000084",
        "tgn:7029392"
    ],
    "tgn:id":7111720,
    "tgn:name":"Ro\u00dfkopf Forst",
    "tgn:placetype":[
        "aat:300008863"
    ]
},
  "bbox": [],
  "geometry": {"coordinates":[10.483333,47.983333],"type":"Point"}
}