<<<<<<< HEAD
{
  "id": 7111720,
  "type": "Feature",
  "properties": {
    "tgn:hierarchy":[
        "tgn:7111720",
        "tgn:7003669",
        "tgn:1000003",
        "tgn:7000084",
        "tgn:7029392"
    ],
    "tgn:id":7111720,
    "tgn:name":"Ro\u00dfkopf Forst",
    "tgn:placetype":[
        "aat:300008863"
    ]
},
  "bbox": [],
  "geometry": {"coordinates":[10.483333,47.983333],"type":"Point"}
}
=======
{"geometry":{"type":"Point","coordinates":[10.483333,47.983333]},"type":"Feature","properties":{"hierarchy":["tgn:7111720","tgn:7003669","tgn:1000003","tgn:7000084","tgn:7029392"],"placetype":["aat:300008863"],"id":7111720,"name:xx":"Ro\u00dfkopf Forst"}}
>>>>>>> 03f74aca74312dbeaf24d7e61306dd6a786dc3d0
