{
  "id": 7211721,
  "type": "Feature",
  "properties": {
    "tgn:hierarchy":[
        "tgn:7211721",
        "tgn:7003669",
        "tgn:1000003",
        "tgn:7000084",
        "tgn:7029392"
    ],
    "tgn:id":7211721,
    "tgn:name":"Bergen",
    "tgn:placetype":[
        "aat:300008347"
    ]
},
  "bbox": [],
  "geometry": {"coordinates":[11.15,48.783333],"type":"Point"}
}