{
  "id": 7537662,
  "type": "Feature",
  "properties": {
    "tgn:hierarchy":[
        "tgn:7537662",
        "tgn:7001242",
        "tgn:1001059",
        "tgn:7016833",
        "tgn:7029392"
    ],
    "tgn:id":7537662,
    "tgn:name":"M\u012bt al Faram\u0101w\u012b",
    "tgn:placetype":[
        "aat:300008347"
    ]
},
  "bbox": [],
  "geometry": {"coordinates":[31.330655,30.691736],"type":"Point"}
}