{
  "id": 7530480,
  "type": "Feature",
  "properties": {
    "tgn:hierarchy":[
        "tgn:7530480",
        "tgn:7001242",
        "tgn:7016833",
        "tgn:1001083",
        "tgn:7029392"
    ],
    "tgn:id":7530480,
    "tgn:name":"Taqs\u012bm 'Amr\u016b Bin al '\u0100\u015f",
    "tgn:placetype":[
        "aat:300000745"
    ]
},
  "bbox": [],
  "geometry": {"coordinates":[31.19613,30.017749],"type":"Point"}
}