{
  "id": 2463260,
  "type": "Feature",
  "properties": {
    "tgn:hierarchy":[
        "tgn:2463260",
        "tgn:1000001",
        "tgn:7012149",
        "tgn:2001717",
        "tgn:7007708",
        "tgn:7029392"
    ],
    "tgn:id":2463260,
    "tgn:name":"Lizard Ridge",
    "tgn:placetype":[
        "aat:300266640"
    ]
},
  "bbox": [],
  "geometry": {"coordinates":[-121.85,44.6167],"type":"Point"}
}