{
  "id": 7320425,
  "type": "Feature",
  "properties": {
    "tgn:hierarchy":[
        "tgn:7320425",
        "tgn:1001699",
        "tgn:1000049",
        "tgn:1000002",
        "tgn:7029392"
    ],
    "tgn:id":7320425,
    "tgn:name":"Blas, Bajo",
    "tgn:placetype":[
        "aat:300008808"
    ]
},
  "bbox": [],
  "geometry": {"coordinates":[-72.633333,-42.05],"type":"Point"}
}