{
  "id": 7205619,
  "type": "Feature",
  "properties": {
    "tgn:hierarchy":[
        "tgn:7205619",
        "tgn:7003692",
        "tgn:1000003",
        "tgn:7000084",
        "tgn:7029392"
    ],
    "tgn:id":7205619,
    "tgn:name":"Buhhof",
    "tgn:placetype":[
        "aat:300000206"
    ]
},
  "bbox": [],
  "geometry": {"coordinates":[9.383333,47.866667],"type":"Point"}
}