{
  "id": 7494093,
  "type": "Feature",
  "properties": {
    "tgn:hierarchy":[
        "tgn:7494093",
        "tgn:1000004",
        "tgn:7001014",
        "tgn:1000141",
        "tgn:7029392"
    ],
    "tgn:id":7494093,
    "tgn:name":"Huilaicuo Qiao",
    "tgn:placetype":[
        "aat:300007836"
    ]
},
  "bbox": [],
  "geometry": {"coordinates":[120.486182,23.74367],"type":"Point"}
}