{
  "id": 2455456,
  "type": "Feature",
  "properties": {
    "tgn:hierarchy":[
        "tgn:2455456",
        "tgn:1000001",
        "tgn:2000470",
        "tgn:7012149",
        "tgn:7007250",
        "tgn:7029392"
    ],
    "tgn:id":2455456,
    "tgn:name":"Little Frog Lake",
    "tgn:placetype":[
        "aat:300008680"
    ]
},
  "bbox": [],
  "geometry": {"coordinates":[-114.5333,44.0667],"type":"Point"}
}