{
  "id": 2207832,
  "type": "Feature",
  "properties": {
    "tgn:hierarchy":[
        "tgn:2207832",
        "tgn:1000001",
        "tgn:7012149",
        "tgn:7007250",
        "tgn:7029392"
    ],
    "tgn:id":2207832,
    "tgn:name":"Burgess Canal",
    "tgn:placetype":[
        "aat:300006075"
    ]
},
  "bbox": [],
  "geometry": {"coordinates":[-111.9167,43.65],"type":"Point"}
}