{
  "id": 7230075,
  "type": "Feature",
  "properties": {
    "tgn:hierarchy":[
        "tgn:7230075",
        "tgn:7002681",
        "tgn:7001395",
        "tgn:1000003",
        "tgn:1000074",
        "tgn:7029392"
    ],
    "tgn:id":7230075,
    "tgn:name":"Lagon\u00edsi",
    "tgn:placetype":[
        "aat:300008804"
    ]
},
  "bbox": [],
  "geometry": {"coordinates":[23.883333,37.783333],"type":"Point"}
}