{
  "id": 2570903,
  "type": "Feature",
  "properties": {
    "tgn:hierarchy":[
        "tgn:2570903",
        "tgn:1000001",
        "tgn:7012149",
        "tgn:7007709",
        "tgn:7029392"
    ],
    "tgn:id":2570903,
    "tgn:name":"Patterson Creek",
    "tgn:placetype":[
        "aat:300008706"
    ]
},
  "bbox": [],
  "geometry": {"coordinates":[-79.2167,35.45],"type":"Point"}
}