{
  "id": 7387472,
  "type": "Feature",
  "properties": {
    "tgn:hierarchy":[
        "tgn:7387472",
        "tgn:7005586",
        "tgn:1000001",
        "tgn:7005560",
        "tgn:7029392"
    ],
    "tgn:id":7387472,
    "tgn:name":"Tlachichilco",
    "tgn:placetype":[
        "aat:300008347"
    ]
},
  "bbox": [],
  "geometry": {"coordinates":[-104.133333,20.65],"type":"Point"}
}