{
  "id": 2131680,
  "type": "Feature",
  "properties": {
    "tgn:hierarchy":[
        "tgn:2131680",
        "tgn:1000001",
        "tgn:7012149",
        "tgn:2001709",
        "tgn:7007708",
        "tgn:7029392"
    ],
    "tgn:id":2131680,
    "tgn:name":"Alvord Hot Springs",
    "tgn:placetype":[
        "aat:300008697"
    ]
},
  "bbox": [],
  "geometry": {"coordinates":[-118.5167,42.5333],"type":"Point"}
}