{
  "id": 7243658,
  "type": "Feature",
  "properties": {
    "tgn:hierarchy":[
        "tgn:7243658",
        "tgn:7003456",
        "tgn:1000003",
        "tgn:1000063",
        "tgn:7018236",
        "tgn:7029392"
    ],
    "tgn:id":7243658,
    "tgn:name":"Hunsberg",
    "tgn:placetype":[
        "aat:300008347"
    ]
},
  "bbox": [],
  "geometry": {"coordinates":[4.267666,50.951229],"type":"Point"}
}