{
  "id": 2211125,
  "type": "Feature",
  "properties": {
    "tgn:hierarchy":[
        "tgn:2211125",
        "tgn:1000001",
        "tgn:7006451",
        "tgn:7012149",
        "tgn:2000103",
        "tgn:7029392"
    ],
    "tgn:id":2211125,
    "tgn:name":"Butler Spring",
    "tgn:placetype":[
        "aat:300008697"
    ]
},
  "bbox": [],
  "geometry": {"coordinates":[-112.4333,34.25],"type":"Point"}
}