{
  "id": 1030674,
  "type": "Feature",
  "properties": {
    "tgn:hierarchy":[
        "tgn:1030674",
        "tgn:7002445",
        "tgn:1000003",
        "tgn:7008139",
        "tgn:7011396",
        "tgn:7008591",
        "tgn:7029392"
    ],
    "tgn:id":1030674,
    "tgn:name:en":"South Hayling",
    "tgn:placetype":[
        "aat:300008347",
        "aat:300008372"
    ]
},
  "bbox": [],
  "geometry": {"coordinates":[-0.966667,50.783333],"type":"Point"}
}