{
  "id": 7048322,
  "type": "Feature",
  "properties": {
    "tgn:hierarchy":[
        "tgn:7048322",
        "tgn:7015163",
        "tgn:1000003",
        "tgn:7003121",
        "tgn:1000080",
        "tgn:7029392"
    ],
    "tgn:id":7048322,
    "tgn:name":"Enas, Riu de",
    "tgn:placetype":[
        "aat:300008699"
    ]
},
  "bbox": [],
  "geometry": {"coordinates":[8.85,40.966667],"type":"Point"}
}