{
  "id": 2739564,
  "type": "Feature",
  "properties": {
    "tgn:hierarchy":[
        "tgn:2739564",
        "tgn:1000001",
        "tgn:7012149",
        "tgn:1002742",
        "tgn:7007920",
        "tgn:7029392"
    ],
    "tgn:id":2739564,
    "tgn:name":"Upper Cathedral Lake",
    "tgn:placetype":[
        "aat:300008680"
    ]
},
  "bbox": [],
  "geometry": {"coordinates":[-120.1833,48.9667],"type":"Point"}
}