{
  "id": 7478284,
  "type": "Feature",
  "properties": {
    "tgn:hierarchy":[
        "tgn:7478284",
        "tgn:1000004",
        "tgn:7492971",
        "tgn:1000141",
        "tgn:7029392"
    ],
    "tgn:id":7478284,
    "tgn:name":"Jingzikou",
    "tgn:placetype":[
        "aat:300008347"
    ]
},
  "bbox": [],
  "geometry": {"coordinates":[120.360423,22.323215],"type":"Point"}
}