{
  "id": 1071552,
  "type": "Feature",
  "properties": {
    "tgn:hierarchy":[
        "tgn:1071552",
        "tgn:1000004",
        "tgn:7001796",
        "tgn:1000111",
        "tgn:7029392"
    ],
    "tgn:id":1071552,
    "tgn:name":"Shaowu",
    "tgn:placetype":[
        "aat:300008347"
    ]
},
  "bbox": [],
  "geometry": {"coordinates":[117.45,27.35],"type":"Point"}
}