{
  "id": 2040341,
  "type": "Feature",
  "properties": {
    "tgn:hierarchy":[
        "tgn:2040341",
        "tgn:2000767",
        "tgn:1000001",
        "tgn:7012149",
        "tgn:7007255",
        "tgn:7029392"
    ],
    "tgn:id":2040341,
    "tgn:name":"Monkeys Eyebrow",
    "tgn:placetype":[
        "aat:300008347",
        "aat:300387210"
    ]
},
  "bbox": [],
  "geometry": {"coordinates":[-88.9833,37.1833],"type":"Point"}
}