{
  "id": 2234400,
  "type": "Feature",
  "properties": {
    "tgn:hierarchy":[
        "tgn:2234400",
        "tgn:1000001",
        "tgn:7012149",
        "tgn:2000890",
        "tgn:7007256",
        "tgn:7029392"
    ],
    "tgn:id":2234400,
    "tgn:name":"Cheniere Creek",
    "tgn:placetype":[
        "aat:300008706"
    ]
},
  "bbox": [],
  "geometry": {"coordinates":[-92.1833,32.45],"type":"Point"}
}