{
  "id": 1072516,
  "type": "Feature",
  "properties": {
    "tgn:hierarchy":[
        "tgn:1072516",
        "tgn:1000004",
        "tgn:7002078",
        "tgn:1000111",
        "tgn:7029392"
    ],
    "tgn:id":1072516,
    "tgn:name":"Wantan",
    "tgn:placetype":[
        "aat:300008347"
    ]
},
  "bbox": [],
  "geometry": {"coordinates":[113.2667,30.05],"type":"Point"}
}