{
  "id": 7469214,
  "type": "Feature",
  "properties": {
    "tgn:hierarchy":[
        "tgn:7469214",
        "tgn:1000004",
        "tgn:7467799",
        "tgn:1000141",
        "tgn:7029392"
    ],
    "tgn:id":7469214,
    "tgn:name":"Fufeng Li",
    "tgn:placetype":[
        "aat:300387173"
    ]
},
  "bbox": [],
  "geometry": {"coordinates":[120.424214,23.88583],"type":"Point"}
}