<<<<<<< HEAD
{
  "id": 7245148,
  "type": "Feature",
  "properties": {
    "tgn:hierarchy":[
        "tgn:7245148",
        "tgn:7003465",
        "tgn:1000003",
        "tgn:1000063",
        "tgn:4012014",
        "tgn:7029392"
    ],
    "tgn:id":7245148,
    "tgn:name":"Banibois",
    "tgn:placetype":[
        "aat:300008863"
    ]
},
  "bbox": [],
  "geometry": {"coordinates":[5.45,49.9],"type":"Point"}
}
=======
{"geometry":{"type":"Point","coordinates":[5.450000,49.900000]},"type":"Feature","properties":{"hierarchy":["tgn:7245148","tgn:7003465","tgn:1000003","tgn:1000063","tgn:4012014","tgn:7029392"],"placetype":["aat:300008863"],"id":7245148,"name:xx":"Banibois"}}
>>>>>>> 03f74aca74312dbeaf24d7e61306dd6a786dc3d0
