{
  "id": 1034007,
  "type": "Feature",
  "properties": {
    "tgn:hierarchy":[
        "tgn:1034007",
        "tgn:1000003",
        "tgn:1000070",
        "tgn:7002897",
        "tgn:7029392"
    ],
    "tgn:id":1034007,
    "tgn:name":"Les Praz-de-Chamonix",
    "tgn:placetype":[
        "aat:300008347"
    ]
},
  "bbox": [],
  "geometry": {"coordinates":[6.8667,45.9333],"type":"Point"}
}