{
  "id": 7107382,
  "type": "Feature",
  "properties": {
    "tgn:hierarchy":[
        "tgn:7107382",
        "tgn:7003669",
        "tgn:1000003",
        "tgn:7000084",
        "tgn:7029392"
    ],
    "tgn:id":7107382,
    "tgn:name":"Scheikl",
    "tgn:placetype":[
        "aat:300000206"
    ]
},
  "bbox": [],
  "geometry": {"coordinates":[13.216667,48.333333],"type":"Point"}
}