{
  "id": 6002441,
  "type": "Feature",
  "properties": {
    "tgn:hierarchy":[
        "tgn:6002441",
        "tgn:1000004",
        "tgn:1000144",
        "tgn:7029392"
    ],
    "tgn:id":6002441,
    "tgn:name":"K\u0131z\u0131l\u0131rmak",
    "tgn:placetype":[
        "aat:300000835",
        "aat:300008707"
    ]
},
  "bbox": [],
  "geometry": {"coordinates":[35.983,41.75],"type":"Point"}
}