{
  "id": 2200715,
  "type": "Feature",
  "properties": {
    "tgn:hierarchy":[
        "tgn:2200715",
        "tgn:1000001",
        "tgn:7012149",
        "tgn:2001156",
        "tgn:7007522",
        "tgn:7029392"
    ],
    "tgn:id":2200715,
    "tgn:name":"Bruton Mound",
    "tgn:placetype":[
        "aat:300008798"
    ]
},
  "bbox": [],
  "geometry": {"coordinates":[-88.1167,34.6333],"type":"Point"}
}