{
  "id": 2646929,
  "type": "Feature",
  "properties": {
    "tgn:hierarchy":[
        "tgn:2646929",
        "tgn:1000001",
        "tgn:7012149",
        "tgn:2000206",
        "tgn:7007158",
        "tgn:7029392"
    ],
    "tgn:id":2646929,
    "tgn:name":"Scenic Mesa",
    "tgn:placetype":[
        "aat:300008798"
    ]
},
  "bbox": [],
  "geometry": {"coordinates":[-107.7833,38.75],"type":"Point"}
}