{
  "id": 2174530,
  "type": "Feature",
  "properties": {
    "tgn:hierarchy":[
        "tgn:2174530",
        "tgn:1000001",
        "tgn:7012149",
        "tgn:2002124",
        "tgn:7007827",
        "tgn:7029392"
    ],
    "tgn:id":2174530,
    "tgn:name":"Bishop Spring",
    "tgn:placetype":[
        "aat:300008697"
    ]
},
  "bbox": [],
  "geometry": {"coordinates":[-109.8833,39.5833],"type":"Point"}
}