{
  "id": 2737163,
  "type": "Feature",
  "properties": {
    "tgn:hierarchy":[
        "tgn:2737163",
        "tgn:1000001",
        "tgn:1002664",
        "tgn:7012149",
        "tgn:7007159",
        "tgn:7029392"
    ],
    "tgn:id":2737163,
    "tgn:name":"Two Stone Brook",
    "tgn:placetype":[
        "aat:300008699"
    ]
},
  "bbox": [],
  "geometry": {"coordinates":[-72.6833,41.6667],"type":"Point"}
}