<<<<<<< HEAD
{
  "id": 7354446,
  "type": "Feature",
  "properties": {
    "tgn:hierarchy":[
        "tgn:7354446",
        "tgn:1000001",
        "tgn:7005590",
        "tgn:7005560",
        "tgn:7029392"
    ],
    "tgn:id":7354446,
    "tgn:name":"Chapultepec",
    "tgn:placetype":[
        "aat:300007783"
    ]
},
  "bbox": [],
  "geometry": {"coordinates":[-101.483333,19.55],"type":"Point"}
}
=======
{"geometry":{"type":"Point","coordinates":[-101.483333,19.550000]},"type":"Feature","properties":{"hierarchy":["tgn:7354446","tgn:1000001","tgn:7005590","tgn:7005560","tgn:7029392"],"placetype":["aat:300007783"],"id":7354446,"name:xx":"Chapultepec"}}
>>>>>>> 03f74aca74312dbeaf24d7e61306dd6a786dc3d0
