<<<<<<< HEAD
{
  "id": 2331249,
  "type": "Feature",
  "properties": {
    "tgn:hierarchy":[
        "tgn:2331249",
        "tgn:1000001",
        "tgn:7012149",
        "tgn:2001452",
        "tgn:7007566",
        "tgn:7029392"
    ],
    "tgn:id":2331249,
    "tgn:name":"Flat Top Rock",
    "tgn:placetype":[
        "aat:300008798"
    ]
},
  "bbox": [],
  "geometry": {"coordinates":[-108.7167,36.9667],"type":"Point"}
}
=======
{"geometry":{"type":"Point","coordinates":[-108.716700,36.966700]},"type":"Feature","properties":{"hierarchy":["tgn:2331249","tgn:1000001","tgn:7012149","tgn:2001452","tgn:7007566","tgn:7029392"],"placetype":["aat:300008798"],"id":2331249,"name:xx":"Flat Top Rock"}}
>>>>>>> 03f74aca74312dbeaf24d7e61306dd6a786dc3d0
