<<<<<<< HEAD
{
  "id": 7379174,
  "type": "Feature",
  "properties": {
    "tgn:hierarchy":[
        "tgn:7379174",
        "tgn:1000001",
        "tgn:7005597",
        "tgn:7005560",
        "tgn:7029392"
    ],
    "tgn:id":7379174,
    "tgn:name":"Los Salda\u00f1as",
    "tgn:placetype":[
        "aat:300008347"
    ]
},
  "bbox": [],
  "geometry": {"coordinates":[-99.416667,23.416667],"type":"Point"}
}
=======
{"geometry":{"type":"Point","coordinates":[-99.416667,23.416667]},"type":"Feature","properties":{"hierarchy":["tgn:7379174","tgn:1000001","tgn:7005597","tgn:7005560","tgn:7029392"],"placetype":["aat:300008347"],"id":7379174,"name:xx":"Los Salda\u00f1as"}}
>>>>>>> 03f74aca74312dbeaf24d7e61306dd6a786dc3d0
