{
  "id": 2453554,
  "type": "Feature",
  "properties": {
    "tgn:hierarchy":[
        "tgn:2453554",
        "tgn:1000001",
        "tgn:2002147",
        "tgn:7012149",
        "tgn:7007919",
        "tgn:7029392"
    ],
    "tgn:id":2453554,
    "tgn:name":"Little Coldwater Creek",
    "tgn:placetype":[
        "aat:300008706"
    ]
},
  "bbox": [],
  "geometry": {"coordinates":[-77.7667,36.6667],"type":"Point"}
}