{
  "id": 2514302,
  "type": "Feature",
  "properties": {
    "tgn:hierarchy":[
        "tgn:2514302",
        "tgn:1000001",
        "tgn:7012149",
        "tgn:1002685",
        "tgn:7007251",
        "tgn:7029392"
    ],
    "tgn:id":2514302,
    "tgn:name":"Miller Creek",
    "tgn:placetype":[
        "aat:300008706"
    ]
},
  "bbox": [],
  "geometry": {"coordinates":[-89.45,39.1333],"type":"Point"}
}