<<<<<<< HEAD
{
  "id": 7480883,
  "type": "Feature",
  "properties": {
    "tgn:hierarchy":[
        "tgn:7480883",
        "tgn:1000004",
        "tgn:7490934",
        "tgn:1000141",
        "tgn:7029392"
    ],
    "tgn:id":7480883,
    "tgn:name":"Shanbao Shan",
    "tgn:placetype":[
        "aat:300008777"
    ]
},
  "bbox": [],
  "geometry": {"coordinates":[120.406417,23.017287],"type":"Point"}
}
=======
{"geometry":{"type":"Point","coordinates":[120.406417,23.017287]},"type":"Feature","properties":{"hierarchy":["tgn:7480883","tgn:1000004","tgn:7490934","tgn:1000141","tgn:7029392"],"placetype":["aat:300008777"],"id":7480883,"name:xx":"Shanbao Shan"}}
>>>>>>> 03f74aca74312dbeaf24d7e61306dd6a786dc3d0
