{
  "id": 2502564,
  "type": "Feature",
  "properties": {
    "tgn:hierarchy":[
        "tgn:2502564",
        "tgn:1000001",
        "tgn:7012149",
        "tgn:2001759",
        "tgn:7007712",
        "tgn:7029392"
    ],
    "tgn:id":2502564,
    "tgn:name":"McLaurins Millpond",
    "tgn:placetype":[
        "aat:300008680"
    ]
},
  "bbox": [],
  "geometry": {"coordinates":[-79.75,34.6667],"type":"Point"}
}