{
  "id": 2662208,
  "type": "Feature",
  "properties": {
    "tgn:hierarchy":[
        "tgn:2662208",
        "tgn:1000001",
        "tgn:7012149",
        "tgn:2002117",
        "tgn:7007827",
        "tgn:7029392"
    ],
    "tgn:id":2662208,
    "tgn:name":"Sidehill Ditch",
    "tgn:placetype":[
        "aat:300006075"
    ]
},
  "bbox": [],
  "geometry": {"coordinates":[-111.1167,41.55],"type":"Point"}
}