{
  "id": 7265392,
  "type": "Feature",
  "properties": {
    "tgn:hierarchy":[
        "tgn:7265392",
        "tgn:1000003",
        "tgn:7003624",
        "tgn:7016845",
        "tgn:7029392"
    ],
    "tgn:id":7265392,
    "tgn:name:nl":"Hultensche Leij",
    "tgn:placetype":[
        "aat:300008699"
    ]
},
  "bbox": [],
  "geometry": {"coordinates":[4.95,51.566667],"type":"Point"}
}