{
  "id": 7098202,
  "type": "Feature",
  "properties": {
    "tgn:hierarchy":[
        "tgn:7098202",
        "tgn:7003692",
        "tgn:1000003",
        "tgn:7000084",
        "tgn:7029392"
    ],
    "tgn:id":7098202,
    "tgn:name":"Sonnenstein",
    "tgn:placetype":[
        "aat:300011692"
    ]
},
  "bbox": [],
  "geometry": {"coordinates":[9.266667,48.416667],"type":"Point"}
}