{
  "id": 2595932,
  "type": "Feature",
  "properties": {
    "tgn:hierarchy":[
        "tgn:2595932",
        "tgn:1000001",
        "tgn:7012149",
        "tgn:2001712",
        "tgn:7007708",
        "tgn:7029392"
    ],
    "tgn:id":2595932,
    "tgn:name":"Potter Canyon",
    "tgn:placetype":[
        "aat:300008761"
    ]
},
  "bbox": [],
  "geometry": {"coordinates":[-121.35,44.4833],"type":"Point"}
}