{
  "id": 7292374,
  "type": "Feature",
  "properties": {
    "tgn:hierarchy":[
        "tgn:7292374",
        "tgn:1001708",
        "tgn:1000049",
        "tgn:1000002",
        "tgn:7029392"
    ],
    "tgn:id":7292374,
    "tgn:name":"El Parr\u00f3n, Cerro",
    "tgn:placetype":[
        "aat:300008795"
    ]
},
  "bbox": [],
  "geometry": {"coordinates":[-71.066667,-33.533333],"type":"Point"}
}