{
  "id": 7353591,
  "type": "Feature",
  "properties": {
    "tgn:hierarchy":[
        "tgn:7353591",
        "tgn:7005586",
        "tgn:1000001",
        "tgn:7005560",
        "tgn:7029392"
    ],
    "tgn:id":7353591,
    "tgn:name":"Ayutla",
    "tgn:placetype":[
        "aat:300008699"
    ]
},
  "bbox": [],
  "geometry": {"coordinates":[-104.25,19.816667],"type":"Point"}
}