{
  "id": 7031779,
  "type": "Feature",
  "properties": {
    "tgn:hierarchy":[
        "tgn:7031779",
        "tgn:7010608",
        "tgn:1000003",
        "tgn:1000090",
        "tgn:7029392"
    ],
    "tgn:id":7031779,
    "tgn:name":"Arouca",
    "tgn:placetype":[
        "aat:300008347",
        "aat:300387218"
    ]
},
  "bbox": [],
  "geometry": {"coordinates":[-8.244,40.93],"type":"Point"}
}