{
  "id": 1098620,
  "type": "Feature",
  "properties": {
    "tgn:hierarchy":[
        "tgn:1098620",
        "tgn:7000490",
        "tgn:1000006",
        "tgn:7001830",
        "tgn:7029392"
    ],
    "tgn:id":1098620,
    "tgn:name":"Yalleroi",
    "tgn:placetype":[
        "aat:300008347"
    ]
},
  "bbox": [],
  "geometry": {"coordinates":[145.7667,-24.0833],"type":"Point"}
}