{
  "id": 7303599,
  "type": "Feature",
  "properties": {
    "tgn:hierarchy":[
        "tgn:7303599",
        "tgn:7002805",
        "tgn:7002758",
        "tgn:1000003",
        "tgn:1000095",
        "tgn:7029392"
    ],
    "tgn:id":7303599,
    "tgn:name":"Ohanes",
    "tgn:placetype":[
        "aat:300008347"
    ]
},
  "bbox": [],
  "geometry": {"coordinates":[-2.733333,37.033333],"type":"Point"}
}