{
  "id": 2189700,
  "type": "Feature",
  "properties": {
    "tgn:hierarchy":[
        "tgn:2189700",
        "tgn:1000001",
        "tgn:7012149",
        "tgn:2000358",
        "tgn:7007248",
        "tgn:7029392"
    ],
    "tgn:id":2189700,
    "tgn:name":"Bowens Lake",
    "tgn:placetype":[
        "aat:300006191"
    ]
},
  "bbox": [],
  "geometry": {"coordinates":[-84.0667,33.9333],"type":"Point"}
}