{
  "id": 2218348,
  "type": "Feature",
  "properties": {
    "tgn:hierarchy":[
        "tgn:2218348",
        "tgn:1000001",
        "tgn:1002200",
        "tgn:7012149",
        "tgn:7007240",
        "tgn:7029392"
    ],
    "tgn:id":2218348,
    "tgn:name":"Canaveral",
    "tgn:placetype":[
        "aat:300008347"
    ]
},
  "bbox": [],
  "geometry": {"coordinates":[-80.5333,28.4667],"type":"Point"}
}