{
  "id": 7381844,
  "type": "Feature",
  "properties": {
    "tgn:hierarchy":[
        "tgn:7381844",
        "tgn:1000001",
        "tgn:7005597",
        "tgn:7005560",
        "tgn:7029392"
    ],
    "tgn:id":7381844,
    "tgn:name":"Los Olmos",
    "tgn:placetype":[
        "aat:300008347"
    ]
},
  "bbox": [],
  "geometry": {"coordinates":[-97.883333,25.983333],"type":"Point"}
}