{
  "id": 2420288,
  "type": "Feature",
  "properties": {
    "tgn:hierarchy":[
        "tgn:2420288",
        "tgn:1000001",
        "tgn:1002712",
        "tgn:7012149",
        "tgn:7007159",
        "tgn:7029392"
    ],
    "tgn:id":2420288,
    "tgn:name":"Jeffrey Point",
    "tgn:placetype":[
        "aat:300008850"
    ]
},
  "bbox": [],
  "geometry": {"coordinates":[-72.8167,41.2333],"type":"Point"}
}