{
  "id": 7472410,
  "type": "Feature",
  "properties": {
    "tgn:hierarchy":[
        "tgn:7472410",
        "tgn:7001010",
        "tgn:1000004",
        "tgn:1000141",
        "tgn:7029392"
    ],
    "tgn:id":7472410,
    "tgn:name":"Lintan Qiao",
    "tgn:placetype":[
        "aat:300007836"
    ]
},
  "bbox": [],
  "geometry": {"coordinates":[121.628583,24.027433],"type":"Point"}
}