{
  "id": 2496864,
  "type": "Feature",
  "properties": {
    "tgn:hierarchy":[
        "tgn:2496864",
        "tgn:1000001",
        "tgn:7012149",
        "tgn:2000385",
        "tgn:7007248",
        "tgn:7029392"
    ],
    "tgn:id":2496864,
    "tgn:name":"Mattox Creek",
    "tgn:placetype":[
        "aat:300008706"
    ]
},
  "bbox": [],
  "geometry": {"coordinates":[-82.5833,33.45],"type":"Point"}
}