{
  "id": 2471350,
  "type": "Feature",
  "properties": {
    "tgn:hierarchy":[
        "tgn:2471350",
        "tgn:1000001",
        "tgn:7012149",
        "tgn:7007158",
        "tgn:7029392"
    ],
    "tgn:id":2471350,
    "tgn:name":"Lost Lake",
    "tgn:placetype":[
        "aat:300008680"
    ]
},
  "bbox": [],
  "geometry": {"coordinates":[-105.15,37.15],"type":"Point"}
}