{
  "id": 2316439,
  "type": "Feature",
  "properties": {
    "tgn:hierarchy":[
        "tgn:2316439",
        "tgn:1000001",
        "tgn:2002369",
        "tgn:7012149",
        "tgn:7007923",
        "tgn:7029392"
    ],
    "tgn:id":2316439,
    "tgn:name":"Elsie Reservoir",
    "tgn:placetype":[
        "aat:300006191"
    ]
},
  "bbox": [],
  "geometry": {"coordinates":[-105.6167,42.65],"type":"Point"}
}