{
  "id": 2520403,
  "type": "Feature",
  "properties": {
    "tgn:hierarchy":[
        "tgn:2520403",
        "tgn:1000001",
        "tgn:7012149",
        "tgn:1002886",
        "tgn:7007252",
        "tgn:7029392"
    ],
    "tgn:id":2520403,
    "tgn:name":"Money Hill",
    "tgn:placetype":[
        "aat:300008798"
    ]
},
  "bbox": [],
  "geometry": {"coordinates":[-85.85,39.4333],"type":"Point"}
}