{
  "id": 2499906,
  "type": "Feature",
  "properties": {
    "tgn:hierarchy":[
        "tgn:2499906",
        "tgn:1000001",
        "tgn:1002221",
        "tgn:7012149",
        "tgn:7007251",
        "tgn:7029392"
    ],
    "tgn:id":2499906,
    "tgn:name":"McCoy Island",
    "tgn:placetype":[
        "aat:300008791"
    ]
},
  "bbox": [],
  "geometry": {"coordinates":[-90.7667,39.2833],"type":"Point"}
}