{
  "id": 2471500,
  "type": "Feature",
  "properties": {
    "tgn:hierarchy":[
        "tgn:2471500",
        "tgn:1000001",
        "tgn:7012149",
        "tgn:2002079",
        "tgn:7007826",
        "tgn:7029392"
    ],
    "tgn:id":2471500,
    "tgn:name":"Lost Lake",
    "tgn:placetype":[
        "aat:300008680"
    ]
},
  "bbox": [],
  "geometry": {"coordinates":[-100.4833,30.45],"type":"Point"}
}