{
  "id": 7577082,
  "type": "Feature",
  "properties": {
    "tgn:hierarchy":[
        "tgn:7577082",
        "tgn:1001828",
        "tgn:1000004",
        "tgn:7000198",
        "tgn:7029392"
    ],
    "tgn:id":7577082,
    "tgn:name:en":"Koyy\u016bru",
    "tgn:placetype":[
        "aat:300008347"
    ]
},
  "bbox": [],
  "geometry": {"coordinates":[82.233333,17.666667],"type":"Point"}
}