{
  "id": 2129671,
  "type": "Feature",
  "properties": {
    "tgn:hierarchy":[
        "tgn:2129671",
        "tgn:1000001",
        "tgn:7012149",
        "tgn:2001256",
        "tgn:7007523",
        "tgn:7029392"
    ],
    "tgn:id":2129671,
    "tgn:name":"All",
    "tgn:placetype":[
        "aat:300008347"
    ]
},
  "bbox": [],
  "geometry": {"coordinates":[-93.0333,37.1667],"type":"Point"}
}