{
  "id": 7538954,
  "type": "Feature",
  "properties": {
    "tgn:hierarchy":[
        "tgn:7538954",
        "tgn:7001242",
        "tgn:1001059",
        "tgn:7016833",
        "tgn:7029392"
    ],
    "tgn:id":7538954,
    "tgn:name:en":"Nuqay\u0163ah",
    "tgn:placetype":[
        "aat:300008347"
    ]
},
  "bbox": [],
  "geometry": {"coordinates":[31.360628,31.000293],"type":"Point"}
}