{
  "id": 2376205,
  "type": "Feature",
  "properties": {
    "tgn:hierarchy":[
        "tgn:2376205",
        "tgn:1000001",
        "tgn:7006451",
        "tgn:7012149",
        "tgn:2000099",
        "tgn:7029392"
    ],
    "tgn:id":2376205,
    "tgn:name":"Hard Rocks",
    "tgn:placetype":[
        "aat:300008347"
    ]
},
  "bbox": [],
  "geometry": {"coordinates":[-110.4333,36.0667],"type":"Point"}
}