{
  "id": 2197918,
  "type": "Feature",
  "properties": {
    "tgn:hierarchy":[
        "tgn:2197918",
        "tgn:1000001",
        "tgn:7012149",
        "tgn:2001713",
        "tgn:7007708",
        "tgn:7029392"
    ],
    "tgn:id":2197918,
    "tgn:name":"Brown Slough",
    "tgn:placetype":[
        "aat:300008699"
    ]
},
  "bbox": [],
  "geometry": {"coordinates":[-123.5667,42.15],"type":"Point"}
}