{
  "id": 2116251,
  "type": "Feature",
  "properties": {
    "tgn:hierarchy":[
        "tgn:2116251",
        "tgn:1000001",
        "tgn:7012149",
        "tgn:1002899",
        "tgn:7007920",
        "tgn:7029392"
    ],
    "tgn:id":2116251,
    "tgn:name":"Martha Lake",
    "tgn:placetype":[
        "aat:300008680"
    ]
},
  "bbox": [],
  "geometry": {"coordinates":[-122.2333,47.85],"type":"Point"}
}