{
  "id": 1113837,
  "type": "Feature",
  "properties": {
    "tgn:hierarchy":[
        "tgn:1113837",
        "tgn:1000001",
        "tgn:7012149",
        "tgn:1002924",
        "tgn:7007568",
        "tgn:7029392"
    ],
    "tgn:id":1113837,
    "tgn:name":"Smithtown Bay",
    "tgn:placetype":[
        "aat:300132316"
    ]
},
  "bbox": [],
  "geometry": {"coordinates":[-73.1833,40.9333],"type":"Point"}
}