{
  "id": 7447480,
  "type": "Feature",
  "properties": {
    "tgn:hierarchy":[
        "tgn:7447480",
        "tgn:7002445",
        "tgn:1000003",
        "tgn:7008153",
        "tgn:7008591",
        "tgn:7029392"
    ],
    "tgn:id":7447480,
    "tgn:name:en":"Stephenson Shoal",
    "tgn:placetype":[
        "aat:300387036"
    ]
},
  "bbox": [],
  "geometry": {"coordinates":[0.883333,50.883333],"type":"Point"}
}