{
  "id": 7450302,
  "type": "Feature",
  "properties": {
    "tgn:hierarchy":[
        "tgn:7450302",
        "tgn:7002443",
        "tgn:5000552",
        "tgn:1000003",
        "tgn:7008591",
        "tgn:7029392"
    ],
    "tgn:id":7450302,
    "tgn:name:en":"Ginst Point",
    "tgn:placetype":[
        "aat:300386846"
    ]
},
  "bbox": [],
  "geometry": {"coordinates":[-4.419722,51.745278],"type":"Point"}
}