{
  "id": 2697938,
  "type": "Feature",
  "properties": {
    "tgn:hierarchy":[
        "tgn:2697938",
        "tgn:1000001",
        "tgn:7012149",
        "tgn:2002301",
        "tgn:7013961",
        "tgn:7029392"
    ],
    "tgn:id":2697938,
    "tgn:name":"Stottlemire Run",
    "tgn:placetype":[
        "aat:300008699"
    ]
},
  "bbox": [],
  "geometry": {"coordinates":[-80.4667,39.6667],"type":"Point"}
}