<<<<<<< HEAD
{
  "id": 2337386,
  "type": "Feature",
  "properties": {
    "tgn:hierarchy":[
        "tgn:2337386",
        "tgn:1000001",
        "tgn:2000925",
        "tgn:7012149",
        "tgn:7007515",
        "tgn:7029392"
    ],
    "tgn:id":2337386,
    "tgn:name":"Fowle Cove",
    "tgn:placetype":[
        "aat:300132316"
    ]
},
  "bbox": [],
  "geometry": {"coordinates":[-69.6667,43.9167],"type":"Point"}
}
=======
{"geometry":{"type":"Point","coordinates":[-69.666700,43.916700]},"type":"Feature","properties":{"hierarchy":["tgn:2337386","tgn:1000001","tgn:2000925","tgn:7012149","tgn:7007515","tgn:7029392"],"placetype":["aat:300132316"],"id":2337386,"name:xx":"Fowle Cove"}}
>>>>>>> 03f74aca74312dbeaf24d7e61306dd6a786dc3d0
