{
  "id": 7426878,
  "type": "Feature",
  "properties": {
    "tgn:hierarchy":[
        "tgn:7426878",
        "tgn:7005581",
        "tgn:1000001",
        "tgn:7005560",
        "tgn:7029392"
    ],
    "tgn:id":7426878,
    "tgn:name":"Llano Grande",
    "tgn:placetype":[
        "aat:300008347"
    ]
},
  "bbox": [],
  "geometry": {"coordinates":[-107.75,28.066667],"type":"Point"}
}