{
  "id": 1091186,
  "type": "Feature",
  "properties": {
    "tgn:hierarchy":[
        "tgn:1091186",
        "tgn:7001242",
        "tgn:1001691",
        "tgn:1000175",
        "tgn:7029392"
    ],
    "tgn:id":1091186,
    "tgn:name":"Kolokani",
    "tgn:placetype":[
        "aat:300008347"
    ]
},
  "bbox": [],
  "geometry": {"coordinates":[-8.0167,13.5833],"type":"Point"}
}