{
  "id": 1073551,
  "type": "Feature",
  "properties": {
    "tgn:hierarchy":[
        "tgn:1073551",
        "tgn:1000004",
        "tgn:7001800",
        "tgn:1000111",
        "tgn:7029392"
    ],
    "tgn:id":1073551,
    "tgn:name":"Yinggehai",
    "tgn:placetype":[
        "aat:300008347"
    ]
},
  "bbox": [],
  "geometry": {"coordinates":[108.6667,18.5167],"type":"Point"}
}