{
  "id": 7122716,
  "type": "Feature",
  "properties": {
    "tgn:hierarchy":[
        "tgn:7122716",
        "tgn:1000003",
        "tgn:7003685",
        "tgn:7000084",
        "tgn:7029392"
    ],
    "tgn:id":7122716,
    "tgn:name":"Niederneudorf",
    "tgn:placetype":[
        "aat:300000206"
    ]
},
  "bbox": [],
  "geometry": {"coordinates":[14.583333,51.066667],"type":"Point"}
}