{
  "id": 7407338,
  "type": "Feature",
  "properties": {
    "tgn:hierarchy":[
        "tgn:7407338",
        "tgn:7005580",
        "tgn:1000001",
        "tgn:7005560",
        "tgn:7029392"
    ],
    "tgn:id":7407338,
    "tgn:name":"La Manza, Cerro",
    "tgn:placetype":[
        "aat:300008795"
    ]
},
  "bbox": [],
  "geometry": {"coordinates":[-93.35,16.391667],"type":"Point"}
}