{
  "id": 7389534,
  "type": "Feature",
  "properties": {
    "tgn:hierarchy":[
        "tgn:7389534",
        "tgn:7005583",
        "tgn:1000001",
        "tgn:7005560",
        "tgn:7029392"
    ],
    "tgn:id":7389534,
    "tgn:name":"Rancho El Setenta",
    "tgn:placetype":[
        "aat:300008347"
    ]
},
  "bbox": [],
  "geometry": {"coordinates":[-104.283333,25.85],"type":"Point"}
}