{
  "id": 2360733,
  "type": "Feature",
  "properties": {
    "tgn:hierarchy":[
        "tgn:2360733",
        "tgn:1000001",
        "tgn:7012149",
        "tgn:2001556",
        "tgn:7007709",
        "tgn:7029392"
    ],
    "tgn:id":2360733,
    "tgn:name":"Grassy Knob Branch",
    "tgn:placetype":[
        "aat:300008699"
    ]
},
  "bbox": [],
  "geometry": {"coordinates":[-82.25,35.7333],"type":"Point"}
}