<<<<<<< HEAD
{
  "id": 7375591,
  "type": "Feature",
  "properties": {
    "tgn:hierarchy":[
        "tgn:7375591",
        "tgn:1000001",
        "tgn:7005595",
        "tgn:7005560",
        "tgn:7029392"
    ],
    "tgn:id":7375591,
    "tgn:name":"La Quebrada",
    "tgn:placetype":[
        "aat:300008347"
    ]
},
  "bbox": [],
  "geometry": {"coordinates":[-107.366667,25.3],"type":"Point"}
}
=======
{"geometry":{"type":"Point","coordinates":[-107.366667,25.300000]},"type":"Feature","properties":{"hierarchy":["tgn:7375591","tgn:1000001","tgn:7005595","tgn:7005560","tgn:7029392"],"placetype":["aat:300008347"],"id":7375591,"name:xx":"La Quebrada"}}
>>>>>>> 03f74aca74312dbeaf24d7e61306dd6a786dc3d0
