<<<<<<< HEAD
{
  "id": 7244668,
  "type": "Feature",
  "properties": {
    "tgn:hierarchy":[
        "tgn:7244668",
        "tgn:7007877",
        "tgn:1000003",
        "tgn:1000063",
        "tgn:4012014",
        "tgn:7029392"
    ],
    "tgn:id":7244668,
    "tgn:name":"Le Trou",
    "tgn:placetype":[
        "aat:300008347"
    ]
},
  "bbox": [],
  "geometry": {"coordinates":[4.032514,50.643139],"type":"Point"}
}
=======
{"geometry":{"type":"Point","coordinates":[4.032514,50.643139]},"type":"Feature","properties":{"hierarchy":["tgn:7244668","tgn:7007877","tgn:1000003","tgn:1000063","tgn:4012014","tgn:7029392"],"placetype":["aat:300008347"],"id":7244668,"name:xx":"Le Trou"}}
>>>>>>> 03f74aca74312dbeaf24d7e61306dd6a786dc3d0
