{
  "id": 7244668,
  "type": "Feature",
  "properties": {
    "tgn:hierarchy":[
        "tgn:7244668",
        "tgn:7007877",
        "tgn:1000003",
        "tgn:1000063",
        "tgn:4012014",
        "tgn:7029392"
    ],
    "tgn:id":7244668,
    "tgn:name":"Le Trou",
    "tgn:placetype":[
        "aat:300008347"
    ]
},
  "bbox": [],
  "geometry": {"coordinates":[4.032514,50.643139],"type":"Point"}
}