{
  "id": 2220513,
  "type": "Feature",
  "properties": {
    "tgn:hierarchy":[
        "tgn:2220513",
        "tgn:7016099",
        "tgn:1000001",
        "tgn:7012149",
        "tgn:7007516",
        "tgn:7029392"
    ],
    "tgn:id":2220513,
    "tgn:name":"Cape May Landing",
    "tgn:placetype":[
        "aat:300008347"
    ]
},
  "bbox": [],
  "geometry": {"coordinates":[-76.4167,39.2833],"type":"Point"}
}