{
  "id": 2014233,
  "type": "Feature",
  "properties": {
    "tgn:hierarchy":[
        "tgn:2014233",
        "tgn:1000001",
        "tgn:7012149",
        "tgn:7007157",
        "tgn:1002841",
        "tgn:7029392"
    ],
    "tgn:id":2014233,
    "tgn:name":"Sheldon",
    "tgn:placetype":[
        "aat:300008347",
        "aat:300387210"
    ]
},
  "bbox": [],
  "geometry": {"coordinates":[-121.2833,38.4167],"type":"Point"}
}