{
  "id": 7490854,
  "type": "Feature",
  "properties": {
    "tgn:hierarchy":[
        "tgn:7490854",
        "tgn:1000004",
        "tgn:7467799",
        "tgn:1000141",
        "tgn:7029392"
    ],
    "tgn:id":7490854,
    "tgn:name":"Bapaojun",
    "tgn:placetype":[
        "aat:300008347"
    ]
},
  "bbox": [],
  "geometry": {"coordinates":[120.566667,23.983333],"type":"Point"}
}