{
  "id": 2295223,
  "type": "Feature",
  "properties": {
    "tgn:hierarchy":[
        "tgn:2295223",
        "tgn:1000001",
        "tgn:7014352",
        "tgn:7012149",
        "tgn:7007564",
        "tgn:7029392"
    ],
    "tgn:id":2295223,
    "tgn:name":"Drew Brook",
    "tgn:placetype":[
        "aat:300008699"
    ]
},
  "bbox": [],
  "geometry": {"coordinates":[-71.2167,42.8833],"type":"Point"}
}