{
  "id": 2491624,
  "type": "Feature",
  "properties": {
    "tgn:hierarchy":[
        "tgn:2491624",
        "tgn:1000001",
        "tgn:7012149",
        "tgn:7007157",
        "tgn:1002706",
        "tgn:7029392"
    ],
    "tgn:id":2491624,
    "tgn:name":"Maple Spring",
    "tgn:placetype":[
        "aat:300008697"
    ]
},
  "bbox": [],
  "geometry": {"coordinates":[-122.5333,38.6167],"type":"Point"}
}