{
  "id": 2185690,
  "type": "Feature",
  "properties": {
    "tgn:hierarchy":[
        "tgn:2185690",
        "tgn:7006450",
        "tgn:1000001",
        "tgn:7012149",
        "tgn:2000079",
        "tgn:7029392"
    ],
    "tgn:id":2185690,
    "tgn:name":"Boise Creek",
    "tgn:placetype":[
        "aat:300008706"
    ]
},
  "bbox": [],
  "geometry": {"coordinates":[-164.15,64.7667],"type":"Point"}
}