{
  "id": 2233975,
  "type": "Feature",
  "properties": {
    "tgn:hierarchy":[
        "tgn:2233975",
        "tgn:1000001",
        "tgn:7012149",
        "tgn:2000890",
        "tgn:7007256",
        "tgn:7029392"
    ],
    "tgn:id":2233975,
    "tgn:name":"Chauvin Swamp",
    "tgn:placetype":[
        "aat:300008905"
    ]
},
  "bbox": [],
  "geometry": {"coordinates":[-92.05,32.55],"type":"Point"}
}