{
  "id": 1118012,
  "type": "Feature",
  "properties": {
    "tgn:hierarchy":[
        "tgn:1118012",
        "tgn:1000001",
        "tgn:7012149",
        "tgn:2001450",
        "tgn:7007566",
        "tgn:7029392"
    ],
    "tgn:id":1118012,
    "tgn:name":"Salt Lake",
    "tgn:placetype":[
        "aat:300008680"
    ]
},
  "bbox": [],
  "geometry": {"coordinates":[-103.0667,34.0833],"type":"Point"}
}