{
  "id": 2149866,
  "type": "Feature",
  "properties": {
    "tgn:hierarchy":[
        "tgn:2149866",
        "tgn:1000001",
        "tgn:2001425",
        "tgn:7012149",
        "tgn:7007564",
        "tgn:7029392"
    ],
    "tgn:id":2149866,
    "tgn:name":"Bartlett Brook",
    "tgn:placetype":[
        "aat:300008699"
    ]
},
  "bbox": [],
  "geometry": {"coordinates":[-71.7833,43.25],"type":"Point"}
}