{
  "id": 2280891,
  "type": "Feature",
  "properties": {
    "tgn:hierarchy":[
        "tgn:2280891",
        "tgn:1000001",
        "tgn:7012149",
        "tgn:1002575",
        "tgn:7007919",
        "tgn:7029392"
    ],
    "tgn:id":2280891,
    "tgn:name":"Deep Creek",
    "tgn:placetype":[
        "aat:300008706"
    ]
},
  "bbox": [],
  "geometry": {"coordinates":[-76.55,37.7833],"type":"Point"}
}