{
  "id": 2007187,
  "type": "Feature",
  "properties": {
    "tgn:hierarchy":[
        "tgn:2007187",
        "tgn:1000001",
        "tgn:7006451",
        "tgn:2000093",
        "tgn:7012149",
        "tgn:7029392"
    ],
    "tgn:id":2007187,
    "tgn:name":"Pinal",
    "tgn:placetype":[
        "aat:300387016"
    ]
},
  "bbox": [],
  "geometry": {"coordinates":[-110.75,33.3667],"type":"Point"}
}