{
  "id": 7071964,
  "type": "Feature",
  "properties": {
    "tgn:hierarchy":[
        "tgn:7071964",
        "tgn:7003692",
        "tgn:1000003",
        "tgn:7000084",
        "tgn:7029392"
    ],
    "tgn:id":7071964,
    "tgn:name":"Tauchenweiler",
    "tgn:placetype":[
        "aat:300000206"
    ]
},
  "bbox": [],
  "geometry": {"coordinates":[10.033333,48.783333],"type":"Point"}
}