{
  "id": 7145815,
  "type": "Feature",
  "properties": {
    "tgn:hierarchy":[
        "tgn:7145815",
        "tgn:1000003",
        "tgn:7003689",
        "tgn:7000084",
        "tgn:7029392"
    ],
    "tgn:id":7145815,
    "tgn:name":"Kleinurleben",
    "tgn:placetype":[
        "aat:300008347"
    ]
},
  "bbox": [],
  "geometry": {"coordinates":[10.766667,51.166667],"type":"Point"}
}