{
  "id": 2170753,
  "type": "Feature",
  "properties": {
    "tgn:hierarchy":[
        "tgn:2170753",
        "tgn:1000001",
        "tgn:7012149",
        "tgn:1002392",
        "tgn:7007157",
        "tgn:7029392"
    ],
    "tgn:id":2170753,
    "tgn:name":"Big Sandy Valley",
    "tgn:placetype":[
        "aat:300008761"
    ]
},
  "bbox": [],
  "geometry": {"coordinates":[-119.4167,37.0167],"type":"Point"}
}