{
  "id": 7094688,
  "type": "Feature",
  "properties": {
    "tgn:hierarchy":[
        "tgn:7094688",
        "tgn:1000003",
        "tgn:7003687",
        "tgn:7000084",
        "tgn:7029392"
    ],
    "tgn:id":7094688,
    "tgn:name":"Sch\u00f6nfeld",
    "tgn:placetype":[
        "aat:300008347"
    ]
},
  "bbox": [],
  "geometry": {"coordinates":[11.733333,52.616667],"type":"Point"}
}