{
  "id": 7553210,
  "type": "Feature",
  "properties": {
    "tgn:hierarchy":[
        "tgn:7553210",
        "tgn:1000004",
        "tgn:7000198",
        "tgn:1001895",
        "tgn:7029392"
    ],
    "tgn:id":7553210,
    "tgn:name:en":"Mul\u0101wa",
    "tgn:placetype":[
        "aat:300008347"
    ]
},
  "bbox": [],
  "geometry": {"coordinates":[77.566667,19.683333],"type":"Point"}
}