{
  "id": 2744201,
  "type": "Feature",
  "properties": {
    "tgn:hierarchy":[
        "tgn:2744201",
        "tgn:1000001",
        "tgn:7012149",
        "tgn:1002496",
        "tgn:7007252",
        "tgn:7029392"
    ],
    "tgn:id":2744201,
    "tgn:name":"Verdrick Ditch",
    "tgn:placetype":[
        "aat:300006075"
    ]
},
  "bbox": [],
  "geometry": {"coordinates":[-85.5667,40.9667],"type":"Point"}
}