{
  "id": 1071604,
  "type": "Feature",
  "properties": {
    "tgn:hierarchy":[
        "tgn:1071604",
        "tgn:1000004",
        "tgn:7001796",
        "tgn:1000111",
        "tgn:7029392"
    ],
    "tgn:id":1071604,
    "tgn:name":"Shenhu",
    "tgn:placetype":[
        "aat:300008347"
    ]
},
  "bbox": [],
  "geometry": {"coordinates":[118.6667,24.6333],"type":"Point"}
}