{
  "id": 7095817,
  "type": "Feature",
  "properties": {
    "tgn:hierarchy":[
        "tgn:7095817",
        "tgn:7003669",
        "tgn:1000003",
        "tgn:7000084",
        "tgn:7029392"
    ],
    "tgn:id":7095817,
    "tgn:name":"Schr\u00f6tting",
    "tgn:placetype":[
        "aat:300008347"
    ]
},
  "bbox": [],
  "geometry": {"coordinates":[12.533333,49.133333],"type":"Point"}
}