{
  "id": 2183027,
  "type": "Feature",
  "properties": {
    "tgn:hierarchy":[
        "tgn:2183027",
        "tgn:1000001",
        "tgn:7012149",
        "tgn:7013941",
        "tgn:7007568",
        "tgn:7029392"
    ],
    "tgn:id":2183027,
    "tgn:name":"Blueberry Pond",
    "tgn:placetype":[
        "aat:300008680"
    ]
},
  "bbox": [],
  "geometry": {"coordinates":[-74.2167,44.1833],"type":"Point"}
}