{
  "id": 7338500,
  "type": "Feature",
  "properties": {
    "tgn:hierarchy":[
        "tgn:7338500",
        "tgn:7002849",
        "tgn:1000003",
        "tgn:7009604",
        "tgn:1000095",
        "tgn:7029392"
    ],
    "tgn:id":7338500,
    "tgn:name":"El Desierto",
    "tgn:placetype":[
        "aat:300008347"
    ]
},
  "bbox": [],
  "geometry": {"coordinates":[-2.974341,43.304496],"type":"Point"}
}