{
  "id": 2539591,
  "type": "Feature",
  "properties": {
    "tgn:hierarchy":[
        "tgn:2539591",
        "tgn:1000001",
        "tgn:7012149",
        "tgn:2000182",
        "tgn:7007157",
        "tgn:7029392"
    ],
    "tgn:id":2539591,
    "tgn:name":"New River",
    "tgn:placetype":[
        "aat:300008707"
    ]
},
  "bbox": [],
  "geometry": {"coordinates":[-115.6833,33.1333],"type":"Point"}
}