{
  "id": 2130300,
  "type": "Feature",
  "properties": {
    "tgn:hierarchy":[
        "tgn:2130300",
        "tgn:1000001",
        "tgn:1002200",
        "tgn:7012149",
        "tgn:7007240",
        "tgn:7029392"
    ],
    "tgn:id":2130300,
    "tgn:name":"Allenhurst",
    "tgn:placetype":[
        "aat:300008347"
    ]
},
  "bbox": [],
  "geometry": {"coordinates":[-80.75,28.7333],"type":"Point"}
}