{
  "id": 7569102,
  "type": "Feature",
  "properties": {
    "tgn:hierarchy":[
        "tgn:7569102",
        "tgn:1001828",
        "tgn:1000004",
        "tgn:7000198",
        "tgn:7029392"
    ],
    "tgn:id":7569102,
    "tgn:name:en":"Dosuw\u0101da",
    "tgn:placetype":[
        "aat:300008347"
    ]
},
  "bbox": [],
  "geometry": {"coordinates":[78.257778,17.266944],"type":"Point"}
}