<<<<<<< HEAD
{
  "id": 7174210,
  "type": "Feature",
  "properties": {
    "tgn:hierarchy":[
        "tgn:7174210",
        "tgn:7003692",
        "tgn:1000003",
        "tgn:7000084",
        "tgn:7029392"
    ],
    "tgn:id":7174210,
    "tgn:name":"Gr\u00f6ningen",
    "tgn:placetype":[
        "aat:300008347"
    ]
},
  "bbox": [],
  "geometry": {"coordinates":[10.066667,49.183333],"type":"Point"}
}
=======
{"geometry":{"type":"Point","coordinates":[10.066667,49.183333]},"type":"Feature","properties":{"hierarchy":["tgn:7174210","tgn:7003692","tgn:1000003","tgn:7000084","tgn:7029392"],"placetype":["aat:300008347"],"id":7174210,"name:xx":"Gr\u00f6ningen"}}
>>>>>>> 03f74aca74312dbeaf24d7e61306dd6a786dc3d0
