{
  "id": 7070481,
  "type": "Feature",
  "properties": {
    "tgn:hierarchy":[
        "tgn:7070481",
        "tgn:1000003",
        "tgn:7003676",
        "tgn:7000084",
        "tgn:7029392"
    ],
    "tgn:id":7070481,
    "tgn:name":"Steimkerbach",
    "tgn:placetype":[
        "aat:300008699"
    ]
},
  "bbox": [],
  "geometry": {"coordinates":[10.25,51.983333],"type":"Point"}
}