{
  "id": 7484246,
  "type": "Feature",
  "properties": {
    "tgn:hierarchy":[
        "tgn:7484246",
        "tgn:7001004",
        "tgn:1000004",
        "tgn:1000141",
        "tgn:7029392"
    ],
    "tgn:id":7484246,
    "tgn:name":"Goushikeng",
    "tgn:placetype":[
        "aat:300008347"
    ]
},
  "bbox": [],
  "geometry": {"coordinates":[120.521389,23.005278],"type":"Point"}
}