{
  "id": 2353637,
  "type": "Feature",
  "properties": {
    "tgn:hierarchy":[
        "tgn:2353637",
        "tgn:1000001",
        "tgn:1002219",
        "tgn:7012149",
        "tgn:7007157",
        "tgn:7029392"
    ],
    "tgn:id":2353637,
    "tgn:name":"Gold Knoll Mine",
    "tgn:placetype":[
        "aat:300000390"
    ]
},
  "bbox": [],
  "geometry": {"coordinates":[-120.6667,37.9833],"type":"Point"}
}