{
  "id": 2637155,
  "type": "Feature",
  "properties": {
    "tgn:hierarchy":[
        "tgn:2637155",
        "tgn:1000001",
        "tgn:2002316",
        "tgn:7012149",
        "tgn:7007922",
        "tgn:7029392"
    ],
    "tgn:id":2637155,
    "tgn:name":"Saint Feriole Island",
    "tgn:placetype":[
        "aat:300008791"
    ]
},
  "bbox": [],
  "geometry": {"coordinates":[-91.15,43.05],"type":"Point"}
}