{
  "id": 2533684,
  "type": "Feature",
  "properties": {
    "tgn:hierarchy":[
        "tgn:2533684",
        "tgn:1000001",
        "tgn:7012149",
        "tgn:7007157",
        "tgn:1002863",
        "tgn:7029392"
    ],
    "tgn:id":2533684,
    "tgn:name":"Mustard Creek",
    "tgn:placetype":[
        "aat:300008706"
    ]
},
  "bbox": [],
  "geometry": {"coordinates":[-120.75,35.65],"type":"Point"}
}