{
  "id": 2144941,
  "type": "Feature",
  "properties": {
    "tgn:hierarchy":[
        "tgn:2144941",
        "tgn:1000001",
        "tgn:7012149",
        "tgn:2001683",
        "tgn:7007707",
        "tgn:7029392"
    ],
    "tgn:id":2144941,
    "tgn:name":"Bald Knob",
    "tgn:placetype":[
        "aat:300008798"
    ]
},
  "bbox": [],
  "geometry": {"coordinates":[-95.6333,34.8667],"type":"Point"}
}