{
  "id": 2342214,
  "type": "Feature",
  "properties": {
    "tgn:hierarchy":[
        "tgn:2342214",
        "tgn:1000001",
        "tgn:7012149",
        "tgn:7007158",
        "tgn:7029392"
    ],
    "tgn:id":2342214,
    "tgn:name":"Fulcher Gulch",
    "tgn:placetype":[
        "aat:300008761"
    ]
},
  "bbox": [],
  "geometry": {"coordinates":[-106.25,37.4167],"type":"Point"}
}