{
  "id": 2192165,
  "type": "Feature",
  "properties": {
    "tgn:hierarchy":[
        "tgn:2192165",
        "tgn:1000001",
        "tgn:7012149",
        "tgn:7007157",
        "tgn:2000191",
        "tgn:7029392"
    ],
    "tgn:id":2192165,
    "tgn:name":"Bramlet Place",
    "tgn:placetype":[
        "aat:300008347"
    ]
},
  "bbox": [],
  "geometry": {"coordinates":[-123.15,40.25],"type":"Point"}
}