{
  "id": 7285226,
  "type": "Feature",
  "properties": {
    "tgn:hierarchy":[
        "tgn:7285226",
        "tgn:1001623",
        "tgn:1000049",
        "tgn:1000002",
        "tgn:7029392"
    ],
    "tgn:id":7285226,
    "tgn:name":"Quetros, Islotes",
    "tgn:placetype":[
        "aat:300008791"
    ]
},
  "bbox": [],
  "geometry": {"coordinates":[-73.783333,-45.466667],"type":"Point"}
}