{
  "id": 2298036,
  "type": "Feature",
  "properties": {
    "tgn:hierarchy":[
        "tgn:2298036",
        "tgn:1000001",
        "tgn:7012149",
        "tgn:7007522",
        "tgn:7029392"
    ],
    "tgn:id":2298036,
    "tgn:name":"Dry Lake",
    "tgn:placetype":[
        "aat:300008680"
    ]
},
  "bbox": [],
  "geometry": {"coordinates":[-90.4333,34.0667],"type":"Point"}
}