{
  "id": 2309493,
  "type": "Feature",
  "properties": {
    "tgn:hierarchy":[
        "tgn:2309493",
        "tgn:1000001",
        "tgn:7012149",
        "tgn:2001040",
        "tgn:7007521",
        "tgn:7029392"
    ],
    "tgn:id":2309493,
    "tgn:name":"East Twin Lake",
    "tgn:placetype":[
        "aat:300008680"
    ]
},
  "bbox": [],
  "geometry": {"coordinates":[-96.0333,44.2167],"type":"Point"}
}