<<<<<<< HEAD
{
  "id": 7023580,
  "type": "Feature",
  "properties": {
    "tgn:hierarchy":[
        "tgn:7023580",
        "tgn:1000001",
        "tgn:7012149",
        "tgn:7007157",
        "tgn:7029392"
    ],
    "tgn:id":7023580,
    "tgn:name":"North Chalone Peak",
    "tgn:placetype":[
        "aat:300008798"
    ]
},
  "bbox": [],
  "geometry": {"coordinates":[-121.1833,36.4333],"type":"Point"}
}
=======
{"geometry":{"type":"Point","coordinates":[-121.183300,36.433300]},"type":"Feature","properties":{"hierarchy":["tgn:7023580","tgn:1000001","tgn:7012149","tgn:7007157","tgn:7029392"],"placetype":["aat:300008798"],"id":7023580,"name:xx":"North Chalone Peak"}}
>>>>>>> 03f74aca74312dbeaf24d7e61306dd6a786dc3d0
