{
  "id": 7097045,
  "type": "Feature",
  "properties": {
    "tgn:hierarchy":[
        "tgn:7097045",
        "tgn:7003669",
        "tgn:1000003",
        "tgn:7000084",
        "tgn:7029392"
    ],
    "tgn:id":7097045,
    "tgn:name":"Spandlhof",
    "tgn:placetype":[
        "aat:300000206"
    ]
},
  "bbox": [],
  "geometry": {"coordinates":[12.233333,49.216667],"type":"Point"}
}