{
  "id": 7586241,
  "type": "Feature",
  "properties": {
    "tgn:hierarchy":[
        "tgn:7586241",
        "tgn:1000004",
        "tgn:7000198",
        "tgn:7000799",
        "tgn:7029392"
    ],
    "tgn:id":7586241,
    "tgn:name:en":"Ladu Lodur",
    "tgn:placetype":[
        "aat:300008347"
    ]
},
  "bbox": [],
  "geometry": {"coordinates":[74.238889,34.272222],"type":"Point"}
}