{
  "id": 2774748,
  "type": "Feature",
  "properties": {
    "tgn:hierarchy":[
        "tgn:2774748",
        "tgn:1000001",
        "tgn:7012149",
        "tgn:2002373",
        "tgn:7007923",
        "tgn:7029392"
    ],
    "tgn:id":2774748,
    "tgn:name":"Willow Spring",
    "tgn:placetype":[
        "aat:300008697"
    ]
},
  "bbox": [],
  "geometry": {"coordinates":[-107.7167,43.4667],"type":"Point"}
}