{
  "id": 7075636,
  "type": "Feature",
  "properties": {
    "tgn:hierarchy":[
        "tgn:7075636",
        "tgn:7003692",
        "tgn:1000003",
        "tgn:7000084",
        "tgn:7029392"
    ],
    "tgn:id":7075636,
    "tgn:name":"Pfinzgau",
    "tgn:placetype":[
        "aat:300055621"
    ]
},
  "bbox": [],
  "geometry": {"coordinates":[8.516667,48.966667],"type":"Point"}
}