{
  "id": 2721315,
  "type": "Feature",
  "properties": {
    "tgn:hierarchy":[
        "tgn:2721315",
        "tgn:1000001",
        "tgn:7012149",
        "tgn:7018871",
        "tgn:7007920",
        "tgn:7029392"
    ],
    "tgn:id":2721315,
    "tgn:name":"Tiger Mountain",
    "tgn:placetype":[
        "aat:300008798"
    ]
},
  "bbox": [],
  "geometry": {"coordinates":[-121.9333,47.4833],"type":"Point"}
}