{
  "id": 7280824,
  "type": "Feature",
  "properties": {
    "tgn:hierarchy":[
        "tgn:7280824",
        "tgn:7016598",
        "tgn:1000049",
        "tgn:1000002",
        "tgn:7029392"
    ],
    "tgn:id":7280824,
    "tgn:name":"Sierra Baya, Cerro",
    "tgn:placetype":[
        "aat:300008795"
    ]
},
  "bbox": [],
  "geometry": {"coordinates":[-69.933333,-25.583333],"type":"Point"}
}