{
  "id": 2587047,
  "type": "Feature",
  "properties": {
    "tgn:hierarchy":[
        "tgn:2587047",
        "tgn:1000001",
        "tgn:7016172",
        "tgn:7012149",
        "tgn:2000126",
        "tgn:7029392"
    ],
    "tgn:id":2587047,
    "tgn:name":"Plantersville",
    "tgn:placetype":[
        "aat:300008347"
    ]
},
  "bbox": [],
  "geometry": {"coordinates":[-91.8667,33.7667],"type":"Point"}
}