{
  "id": 7586164,
  "type": "Feature",
  "properties": {
    "tgn:hierarchy":[
        "tgn:7586164",
        "tgn:1000004",
        "tgn:7000198",
        "tgn:7000799",
        "tgn:7029392"
    ],
    "tgn:id":7586164,
    "tgn:name:en":"Doly\u0101ri",
    "tgn:placetype":[
        "aat:300387200"
    ]
},
  "bbox": [],
  "geometry": {"coordinates":[74.883333,34.333333],"type":"Point"}
}