{
  "id": 2026571,
  "type": "Feature",
  "properties": {
    "tgn:hierarchy":[
        "tgn:2026571",
        "tgn:1000001",
        "tgn:7012149",
        "tgn:2000527",
        "tgn:7007251",
        "tgn:7029392"
    ],
    "tgn:id":2026571,
    "tgn:name":"Berryville",
    "tgn:placetype":[
        "aat:300008347"
    ]
},
  "bbox": [],
  "geometry": {"coordinates":[-87.9167,38.5833],"type":"Point"}
}