{
  "id": 7160865,
  "type": "Feature",
  "properties": {
    "tgn:hierarchy":[
        "tgn:7160865",
        "tgn:7003669",
        "tgn:1000003",
        "tgn:7000084",
        "tgn:7029392"
    ],
    "tgn:id":7160865,
    "tgn:name":"Hochwurz",
    "tgn:placetype":[
        "aat:300008863"
    ]
},
  "bbox": [],
  "geometry": {"coordinates":[11.783333,48.75],"type":"Point"}
}