{
  "id": 2599268,
  "type": "Feature",
  "properties": {
    "tgn:hierarchy":[
        "tgn:2599268",
        "tgn:1000001",
        "tgn:2001425",
        "tgn:7012149",
        "tgn:7007564",
        "tgn:7029392"
    ],
    "tgn:id":2599268,
    "tgn:name":"Proctor Hill",
    "tgn:placetype":[
        "aat:300008798"
    ]
},
  "bbox": [],
  "geometry": {"coordinates":[-71.8167,43.1667],"type":"Point"}
}