{
  "id": 2468941,
  "type": "Feature",
  "properties": {
    "tgn:hierarchy":[
        "tgn:2468941",
        "tgn:1000001",
        "tgn:7012149",
        "tgn:2002296",
        "tgn:7013961",
        "tgn:7029392"
    ],
    "tgn:id":2468941,
    "tgn:name":"Long Run",
    "tgn:placetype":[
        "aat:300008699"
    ]
},
  "bbox": [],
  "geometry": {"coordinates":[-79.55,39.15],"type":"Point"}
}