{
  "id": 2317251,
  "type": "Feature",
  "properties": {
    "tgn:hierarchy":[
        "tgn:2317251",
        "tgn:1000001",
        "tgn:7012149",
        "tgn:1002939",
        "tgn:7007826",
        "tgn:7029392"
    ],
    "tgn:id":2317251,
    "tgn:name":"Emmett",
    "tgn:placetype":[
        "aat:300008347"
    ]
},
  "bbox": [],
  "geometry": {"coordinates":[-96.7833,31.9833],"type":"Point"}
}