{
  "id": 1015691,
  "type": "Feature",
  "properties": {
    "tgn:hierarchy":[
        "tgn:1015691",
        "tgn:7005685",
        "tgn:1000001",
        "tgn:7005804",
        "tgn:7029392"
    ],
    "tgn:id":1015691,
    "tgn:name":"Saint-Marc-des-Carri\u00e8res",
    "tgn:placetype":[
        "aat:300008347"
    ]
},
  "bbox": [],
  "geometry": {"coordinates":[-72.05,46.6667],"type":"Point"}
}