{
  "id": 2449542,
  "type": "Feature",
  "properties": {
    "tgn:hierarchy":[
        "tgn:2449542",
        "tgn:1000001",
        "tgn:2000306",
        "tgn:7012149",
        "tgn:7007248",
        "tgn:7029392"
    ],
    "tgn:id":2449542,
    "tgn:name":"Lincoln Creek",
    "tgn:placetype":[
        "aat:300008706"
    ]
},
  "bbox": [],
  "geometry": {"coordinates":[-81.2167,31.7667],"type":"Point"}
}