<<<<<<< HEAD
{
  "id": 7370614,
  "type": "Feature",
  "properties": {
    "tgn:hierarchy":[
        "tgn:7370614",
        "tgn:7005580",
        "tgn:1000001",
        "tgn:7005560",
        "tgn:7029392"
    ],
    "tgn:id":7370614,
    "tgn:name":"Guayaquil",
    "tgn:placetype":[
        "aat:300008347"
    ]
},
  "bbox": [],
  "geometry": {"coordinates":[-91.616667,16.783333],"type":"Point"}
}
=======
{"geometry":{"type":"Point","coordinates":[-91.616667,16.783333]},"type":"Feature","properties":{"hierarchy":["tgn:7370614","tgn:7005580","tgn:1000001","tgn:7005560","tgn:7029392"],"placetype":["aat:300008347"],"id":7370614,"name:xx":"Guayaquil"}}
>>>>>>> 03f74aca74312dbeaf24d7e61306dd6a786dc3d0
