{
  "id": 7415296,
  "type": "Feature",
  "properties": {
    "tgn:hierarchy":[
        "tgn:7415296",
        "tgn:1000001",
        "tgn:7005591",
        "tgn:7005560",
        "tgn:7029392"
    ],
    "tgn:id":7415296,
    "tgn:name:es":"Yosoyuxi",
    "tgn:placetype":[
        "aat:300008347"
    ]
},
  "bbox": [],
  "geometry": {"coordinates":[-97.940278,17.179167],"type":"Point"}
}