<<<<<<< HEAD
{
  "id": 2259253,
  "type": "Feature",
  "properties": {
    "tgn:hierarchy":[
        "tgn:2259253",
        "tgn:1000001",
        "tgn:7012149",
        "tgn:2001715",
        "tgn:7007708",
        "tgn:7029392"
    ],
    "tgn:id":2259253,
    "tgn:name":"Cottonwood Meadow Lake",
    "tgn:placetype":[
        "aat:300006191"
    ]
},
  "bbox": [],
  "geometry": {"coordinates":[-120.6333,42.2667],"type":"Point"}
}
=======
{"geometry":{"type":"Point","coordinates":[-120.633300,42.266700]},"type":"Feature","properties":{"hierarchy":["tgn:2259253","tgn:1000001","tgn:7012149","tgn:2001715","tgn:7007708","tgn:7029392"],"placetype":["aat:300006191"],"id":2259253,"name:xx":"Cottonwood Meadow Lake"}}
>>>>>>> 03f74aca74312dbeaf24d7e61306dd6a786dc3d0
