{
  "id": 2583483,
  "type": "Feature",
  "properties": {
    "tgn:hierarchy":[
        "tgn:2583483",
        "tgn:1000001",
        "tgn:7012149",
        "tgn:7029392"
    ],
    "tgn:id":2583483,
    "tgn:name":"Pine Ridge",
    "tgn:placetype":[
        "aat:300266640"
    ]
},
  "bbox": [],
  "geometry": {"coordinates":[-78.6833,39.7167],"type":"Point"}
}