{
  "id": 2477188,
  "type": "Feature",
  "properties": {
    "tgn:hierarchy":[
        "tgn:2477188",
        "tgn:1000001",
        "tgn:2002245",
        "tgn:7012149",
        "tgn:7007920",
        "tgn:7029392"
    ],
    "tgn:id":2477188,
    "tgn:name":"Lynn Gulch",
    "tgn:placetype":[
        "aat:300008761"
    ]
},
  "bbox": [],
  "geometry": {"coordinates":[-117.5333,46.6333],"type":"Point"}
}