{
  "id": 7150516,
  "type": "Feature",
  "properties": {
    "tgn:hierarchy":[
        "tgn:7150516",
        "tgn:1000003",
        "tgn:7003688",
        "tgn:7000084",
        "tgn:7029392"
    ],
    "tgn:id":7150516,
    "tgn:name":"Kr\u00f6nerkate",
    "tgn:placetype":[
        "aat:300000206"
    ]
},
  "bbox": [],
  "geometry": {"coordinates":[10.816667,54.25],"type":"Point"}
}