{
  "id": 1028854,
  "type": "Feature",
  "properties": {
    "tgn:hierarchy":[
        "tgn:1028854",
        "tgn:7002445",
        "tgn:1000003",
        "tgn:7008118",
        "tgn:7008591",
        "tgn:7029392"
    ],
    "tgn:id":1028854,
    "tgn:name:ang":"Ceolhal",
    "tgn:placetype":[
        "aat:300008347"
    ]
},
  "bbox": [],
  "geometry": {"coordinates":[-1.95,53.4167],"type":"Point"}
}