{
  "id": 2253487,
  "type": "Feature",
  "properties": {
    "tgn:hierarchy":[
        "tgn:2253487",
        "tgn:1000001",
        "tgn:7012149",
        "tgn:2001131",
        "tgn:7007522",
        "tgn:7029392"
    ],
    "tgn:id":2253487,
    "tgn:name":"Cook Creek",
    "tgn:placetype":[
        "aat:300008706"
    ]
},
  "bbox": [],
  "geometry": {"coordinates":[-89.65,31.2167],"type":"Point"}
}