{
  "id": 2401247,
  "type": "Feature",
  "properties": {
    "tgn:hierarchy":[
        "tgn:2401247",
        "tgn:1000001",
        "tgn:7012149",
        "tgn:2000436",
        "tgn:7007248",
        "tgn:7029392"
    ],
    "tgn:id":2401247,
    "tgn:name":"Horseley Branch",
    "tgn:placetype":[
        "aat:300008699"
    ]
},
  "bbox": [],
  "geometry": {"coordinates":[-84.1833,32.8333],"type":"Point"}
}