<<<<<<< HEAD
{
  "id": 2401247,
  "type": "Feature",
  "properties": {
    "tgn:hierarchy":[
        "tgn:2401247",
        "tgn:1000001",
        "tgn:7012149",
        "tgn:2000436",
        "tgn:7007248",
        "tgn:7029392"
    ],
    "tgn:id":2401247,
    "tgn:name":"Horseley Branch",
    "tgn:placetype":[
        "aat:300008699"
    ]
},
  "bbox": [],
  "geometry": {"coordinates":[-84.1833,32.8333],"type":"Point"}
}
=======
{"geometry":{"type":"Point","coordinates":[-84.183300,32.833300]},"type":"Feature","properties":{"hierarchy":["tgn:2401247","tgn:1000001","tgn:7012149","tgn:2000436","tgn:7007248","tgn:7029392"],"placetype":["aat:300008699"],"id":2401247,"name:xx":"Horseley Branch"}}
>>>>>>> 03f74aca74312dbeaf24d7e61306dd6a786dc3d0
