{
  "id": 2347583,
  "type": "Feature",
  "properties": {
    "tgn:hierarchy":[
        "tgn:2347583",
        "tgn:1000001",
        "tgn:2001638",
        "tgn:7012149",
        "tgn:7007707",
        "tgn:7029392"
    ],
    "tgn:id":2347583,
    "tgn:name":"George, Lake",
    "tgn:placetype":[
        "aat:300006191"
    ]
},
  "bbox": [],
  "geometry": {"coordinates":[-98.3333,34.6333],"type":"Point"}
}