{
  "id": 2130202,
  "type": "Feature",
  "properties": {
    "tgn:hierarchy":[
        "tgn:2130202",
        "tgn:1000001",
        "tgn:2124001",
        "tgn:7016105",
        "tgn:7012149",
        "tgn:7007516",
        "tgn:7029392"
    ],
    "tgn:id":2130202,
    "tgn:name":"Allen Pond",
    "tgn:placetype":[
        "aat:300006191"
    ]
},
  "bbox": [],
  "geometry": {"coordinates":[-76.7333,38.9333],"type":"Point"}
}