{
  "id": 2664143,
  "type": "Feature",
  "properties": {
    "tgn:hierarchy":[
        "tgn:2664143",
        "tgn:2002365",
        "tgn:1000001",
        "tgn:7012149",
        "tgn:7007923",
        "tgn:7029392"
    ],
    "tgn:id":2664143,
    "tgn:name":"Silver Run Lake",
    "tgn:placetype":[
        "aat:300008680"
    ]
},
  "bbox": [],
  "geometry": {"coordinates":[-106.2333,41.3167],"type":"Point"}
}