{
  "id": 2126993,
  "type": "Feature",
  "properties": {
    "tgn:hierarchy":[
        "tgn:2126993",
        "tgn:7006450",
        "tgn:1000001",
        "tgn:2000071",
        "tgn:7012149",
        "tgn:7029392"
    ],
    "tgn:id":2126993,
    "tgn:name":"Agulowak River",
    "tgn:placetype":[
        "aat:300008707"
    ]
},
  "bbox": [],
  "geometry": {"coordinates":[-158.8333,59.4167],"type":"Point"}
}