{
  "id": 7233283,
  "type": "Feature",
  "properties": {
    "tgn:hierarchy":[
        "tgn:7233283",
        "tgn:7002680",
        "tgn:7001395",
        "tgn:1000003",
        "tgn:1000074",
        "tgn:7029392"
    ],
    "tgn:id":7233283,
    "tgn:name":"\u00c1lsos",
    "tgn:placetype":[
        "aat:300008347"
    ]
},
  "bbox": [],
  "geometry": {"coordinates":[21.983333,38.25],"type":"Point"}
}