{
  "id": 2038446,
  "type": "Feature",
  "properties": {
    "tgn:hierarchy":[
        "tgn:2038446",
        "tgn:1000001",
        "tgn:7012149",
        "tgn:2000826",
        "tgn:7007255",
        "tgn:7029392"
    ],
    "tgn:id":2038446,
    "tgn:name":"Dan",
    "tgn:placetype":[
        "aat:300008347",
        "aat:300387210"
    ]
},
  "bbox": [],
  "geometry": {"coordinates":[-83.45,37.95],"type":"Point"}
}