{
  "id": 7411883,
  "type": "Feature",
  "properties": {
    "tgn:hierarchy":[
        "tgn:7411883",
        "tgn:1000001",
        "tgn:7005596",
        "tgn:7005560",
        "tgn:7029392"
    ],
    "tgn:id":7411883,
    "tgn:name:es":"Ignacio Guti\u00e9rrez Primera Secci\u00f3n",
    "tgn:placetype":[
        "aat:300008347"
    ]
},
  "bbox": [],
  "geometry": {"coordinates":[-93.825,17.958333],"type":"Point"}
}