{
  "id": 2236027,
  "type": "Feature",
  "properties": {
    "tgn:hierarchy":[
        "tgn:2236027",
        "tgn:2001628",
        "tgn:1000001",
        "tgn:7012149",
        "tgn:7007707",
        "tgn:7029392"
    ],
    "tgn:id":2236027,
    "tgn:name":"Cheyenne Butte",
    "tgn:placetype":[
        "aat:300008798"
    ]
},
  "bbox": [],
  "geometry": {"coordinates":[-98.2167,35.7667],"type":"Point"}
}