{
  "id": 7121381,
  "type": "Feature",
  "properties": {
    "tgn:hierarchy":[
        "tgn:7121381",
        "tgn:7003692",
        "tgn:1000003",
        "tgn:7000084",
        "tgn:7029392"
    ],
    "tgn:id":7121381,
    "tgn:name":"Pistre",
    "tgn:placetype":[
        "aat:300008347"
    ]
},
  "bbox": [],
  "geometry": {"coordinates":[9.316667,48.216667],"type":"Point"}
}