<<<<<<< HEAD
{
  "id": 2762209,
  "type": "Feature",
  "properties": {
    "tgn:hierarchy":[
        "tgn:2762209",
        "tgn:1000001",
        "tgn:2000468",
        "tgn:7012149",
        "tgn:7007250",
        "tgn:7029392"
    ],
    "tgn:id":2762209,
    "tgn:name":"West Steel Creek",
    "tgn:placetype":[
        "aat:300008706"
    ]
},
  "bbox": [],
  "geometry": {"coordinates":[-112.05,44.4333],"type":"Point"}
}
=======
{"geometry":{"type":"Point","coordinates":[-112.050000,44.433300]},"type":"Feature","properties":{"hierarchy":["tgn:2762209","tgn:1000001","tgn:2000468","tgn:7012149","tgn:7007250","tgn:7029392"],"placetype":["aat:300008706"],"id":2762209,"name:xx":"West Steel Creek"}}
>>>>>>> 03f74aca74312dbeaf24d7e61306dd6a786dc3d0
