{
  "id": 2234724,
  "type": "Feature",
  "properties": {
    "tgn:hierarchy":[
        "tgn:2234724",
        "tgn:1000001",
        "tgn:7012149",
        "tgn:7007158",
        "tgn:2000243",
        "tgn:7029392"
    ],
    "tgn:id":2234724,
    "tgn:name":"Cherry Creek",
    "tgn:placetype":[
        "aat:300008706"
    ]
},
  "bbox": [],
  "geometry": {"coordinates":[-107.6667,40.05],"type":"Point"}
}