{
  "id": 2408695,
  "type": "Feature",
  "properties": {
    "tgn:hierarchy":[
        "tgn:2408695",
        "tgn:1000001",
        "tgn:7012149",
        "tgn:7007523",
        "tgn:7029392"
    ],
    "tgn:id":2408695,
    "tgn:name":"Hyatts Creek",
    "tgn:placetype":[
        "aat:300008706"
    ]
},
  "bbox": [],
  "geometry": {"coordinates":[-90.75,37.4333],"type":"Point"}
}