{
  "id": 2472775,
  "type": "Feature",
  "properties": {
    "tgn:hierarchy":[
        "tgn:2472775",
        "tgn:1000001",
        "tgn:7012149",
        "tgn:7007157",
        "tgn:7014516",
        "tgn:7029392"
    ],
    "tgn:id":2472775,
    "tgn:name":"Lovers Gulch Creek",
    "tgn:placetype":[
        "aat:300008706"
    ]
},
  "bbox": [],
  "geometry": {"coordinates":[-122.8167,38.7333],"type":"Point"}
}