<<<<<<< HEAD
{
  "id": 7375922,
  "type": "Feature",
  "properties": {
    "tgn:hierarchy":[
        "tgn:7375922",
        "tgn:1000001",
        "tgn:7005599",
        "tgn:7005560",
        "tgn:7029392"
    ],
    "tgn:id":7375922,
    "tgn:name":"Las Higueras",
    "tgn:placetype":[
        "aat:300008347"
    ]
},
  "bbox": [],
  "geometry": {"coordinates":[-96.6,20.05],"type":"Point"}
}
=======
{"geometry":{"type":"Point","coordinates":[-96.600000,20.050000]},"type":"Feature","properties":{"hierarchy":["tgn:7375922","tgn:1000001","tgn:7005599","tgn:7005560","tgn:7029392"],"placetype":["aat:300008347"],"id":7375922,"name:xx":"Las Higueras"}}
>>>>>>> 03f74aca74312dbeaf24d7e61306dd6a786dc3d0
