<<<<<<< HEAD
{
  "id": 2333281,
  "type": "Feature",
  "properties": {
    "tgn:hierarchy":[
        "tgn:2333281",
        "tgn:2000919",
        "tgn:1000001",
        "tgn:7012149",
        "tgn:7007515",
        "tgn:7029392"
    ],
    "tgn:id":2333281,
    "tgn:name":"Fog Brook",
    "tgn:placetype":[
        "aat:300008699"
    ]
},
  "bbox": [],
  "geometry": {"coordinates":[-68.3333,45.6],"type":"Point"}
}
=======
{"geometry":{"type":"Point","coordinates":[-68.333300,45.600000]},"type":"Feature","properties":{"hierarchy":["tgn:2333281","tgn:2000919","tgn:1000001","tgn:7012149","tgn:7007515","tgn:7029392"],"placetype":["aat:300008699"],"id":2333281,"name:xx":"Fog Brook"}}
>>>>>>> 03f74aca74312dbeaf24d7e61306dd6a786dc3d0
