{
  "id": 2388405,
  "type": "Feature",
  "properties": {
    "tgn:hierarchy":[
        "tgn:2388405",
        "tgn:1000001",
        "tgn:1002233",
        "tgn:7012149",
        "tgn:7007710",
        "tgn:7029392"
    ],
    "tgn:id":2388405,
    "tgn:name":"Hickory Run Lake",
    "tgn:placetype":[
        "aat:300006191"
    ]
},
  "bbox": [],
  "geometry": {"coordinates":[-75.6833,41.0333],"type":"Point"}
}