{
  "id": 7316504,
  "type": "Feature",
  "properties": {
    "tgn:hierarchy":[
        "tgn:7316504",
        "tgn:1001630",
        "tgn:1000049",
        "tgn:1000002",
        "tgn:7029392"
    ],
    "tgn:id":7316504,
    "tgn:name":"Castillo",
    "tgn:placetype":[
        "aat:300008347"
    ]
},
  "bbox": [],
  "geometry": {"coordinates":[-69.45,-26.266667],"type":"Point"}
}