{
  "id": 7584760,
  "type": "Feature",
  "properties": {
    "tgn:hierarchy":[
        "tgn:7584760",
        "tgn:1000004",
        "tgn:7000198",
        "tgn:1001894",
        "tgn:7029392"
    ],
    "tgn:id":7584760,
    "tgn:name:en":"Dhurdhuru",
    "tgn:placetype":[
        "aat:300008347"
    ]
},
  "bbox": [],
  "geometry": {"coordinates":[78.218161,24.099319],"type":"Point"}
}