{
  "id": 2754411,
  "type": "Feature",
  "properties": {
    "tgn:hierarchy":[
        "tgn:2754411",
        "tgn:1000001",
        "tgn:2002316",
        "tgn:7012149",
        "tgn:7007922",
        "tgn:7029392"
    ],
    "tgn:id":2754411,
    "tgn:name":"Wauzeka Ridge",
    "tgn:placetype":[
        "aat:300266640"
    ]
},
  "bbox": [],
  "geometry": {"coordinates":[-90.9667,43.1167],"type":"Point"}
}