{
  "id": 2169931,
  "type": "Feature",
  "properties": {
    "tgn:hierarchy":[
        "tgn:2169931",
        "tgn:1000001",
        "tgn:7006451",
        "tgn:7012149",
        "tgn:2000103",
        "tgn:7029392"
    ],
    "tgn:id":2169931,
    "tgn:name":"Big Pemberton Tank",
    "tgn:placetype":[
        "aat:300006191"
    ]
},
  "bbox": [],
  "geometry": {"coordinates":[-112.9167,34.0167],"type":"Point"}
}