{
  "id": 2441884,
  "type": "Feature",
  "properties": {
    "tgn:hierarchy":[
        "tgn:2441884",
        "tgn:1000001",
        "tgn:7012149",
        "tgn:7007157",
        "tgn:1002566",
        "tgn:7029392"
    ],
    "tgn:id":2441884,
    "tgn:name":"Konocti, Mount",
    "tgn:placetype":[
        "aat:300008798"
    ]
},
  "bbox": [],
  "geometry": {"coordinates":[-122.75,38.9667],"type":"Point"}
}