<<<<<<< HEAD
{
  "id": 2408415,
  "type": "Feature",
  "properties": {
    "tgn:hierarchy":[
        "tgn:2408415",
        "tgn:1000001",
        "tgn:7012149",
        "tgn:7007157",
        "tgn:1002621",
        "tgn:7029392"
    ],
    "tgn:id":2408415,
    "tgn:name":"Hutchings Creek",
    "tgn:placetype":[
        "aat:300008706"
    ]
},
  "bbox": [],
  "geometry": {"coordinates":[-119.2833,37.7333],"type":"Point"}
}
=======
{"geometry":{"type":"Point","coordinates":[-119.283300,37.733300]},"type":"Feature","properties":{"hierarchy":["tgn:2408415","tgn:1000001","tgn:7012149","tgn:7007157","tgn:1002621","tgn:7029392"],"placetype":["aat:300008706"],"id":2408415,"name:xx":"Hutchings Creek"}}
>>>>>>> 03f74aca74312dbeaf24d7e61306dd6a786dc3d0
