{
  "id": 7332859,
  "type": "Feature",
  "properties": {
    "tgn:hierarchy":[
        "tgn:7332859",
        "tgn:7002836",
        "tgn:7016622",
        "tgn:1000003",
        "tgn:1000095",
        "tgn:7029392"
    ],
    "tgn:id":7332859,
    "tgn:name":"La Monta\u00f1a",
    "tgn:placetype":[
        "aat:300008347"
    ]
},
  "bbox": [],
  "geometry": {"coordinates":[-17.75,28.633333],"type":"Point"}
}