{
  "id": 7505771,
  "type": "Feature",
  "properties": {
    "tgn:hierarchy":[
        "tgn:7505771",
        "tgn:1009227",
        "tgn:1000226",
        "tgn:7520095",
        "tgn:1000006",
        "tgn:7029392"
    ],
    "tgn:id":7505771,
    "tgn:name:en":"Tonga Roadstead",
    "tgn:placetype":[
        "aat:300132316"
    ]
},
  "bbox": [],
  "geometry": {"coordinates":[173.05,-40.883333],"type":"Point"}
}