<<<<<<< HEAD
{
  "id": 7059191,
  "type": "Feature",
  "properties": {
    "tgn:hierarchy":[
        "tgn:7059191",
        "tgn:7001242",
        "tgn:1001086",
        "tgn:1000201",
        "tgn:7029392"
    ],
    "tgn:id":7059191,
    "tgn:name":"Esh Shihenab",
    "tgn:placetype":[
        "aat:300000810",
        "aat:300387006"
    ]
},
  "bbox": [],
  "geometry": {"coordinates":[32.542,16.063],"type":"Point"}
}
=======
{"geometry":{"type":"Point","coordinates":[32.542000,16.063000]},"type":"Feature","properties":{"hierarchy":["tgn:7059191","tgn:7001242","tgn:1001086","tgn:1000201","tgn:7029392"],"placetype":["aat:300000810","aat:300387006"],"id":7059191,"name:xx":"Esh Shihenab"}}
>>>>>>> 03f74aca74312dbeaf24d7e61306dd6a786dc3d0
