{
  "id": 2440520,
  "type": "Feature",
  "properties": {
    "tgn:hierarchy":[
        "tgn:2440520",
        "tgn:1000001",
        "tgn:7012149",
        "tgn:7007568",
        "tgn:7029392"
    ],
    "tgn:id":2440520,
    "tgn:name":"Knapp Hill",
    "tgn:placetype":[
        "aat:300008798"
    ]
},
  "bbox": [],
  "geometry": {"coordinates":[-77.3833,42.5667],"type":"Point"}
}