{
  "id": 2486457,
  "type": "Feature",
  "properties": {
    "tgn:hierarchy":[
        "tgn:2486457",
        "tgn:1000001",
        "tgn:7012149",
        "tgn:2000721",
        "tgn:7007254",
        "tgn:7029392"
    ],
    "tgn:id":2486457,
    "tgn:name":"Leban Creek",
    "tgn:placetype":[
        "aat:300008706"
    ]
},
  "bbox": [],
  "geometry": {"coordinates":[-98.2167,39.3667],"type":"Point"}
}