{
  "id": 2663033,
  "type": "Feature",
  "properties": {
    "tgn:hierarchy":[
        "tgn:2663033",
        "tgn:1000001",
        "tgn:7012149",
        "tgn:1002314",
        "tgn:7007240",
        "tgn:7029392"
    ],
    "tgn:id":2663033,
    "tgn:name":"Silver Blue Lake",
    "tgn:placetype":[
        "aat:300008680"
    ]
},
  "bbox": [],
  "geometry": {"coordinates":[-80.2167,25.8667],"type":"Point"}
}