{
  "id": 2348653,
  "type": "Feature",
  "properties": {
    "tgn:hierarchy":[
        "tgn:2348653",
        "tgn:1000001",
        "tgn:7016172",
        "tgn:7012149",
        "tgn:2000144",
        "tgn:7029392"
    ],
    "tgn:id":2348653,
    "tgn:name":"Gibson Brake",
    "tgn:placetype":[
        "aat:300008905"
    ]
},
  "bbox": [],
  "geometry": {"coordinates":[-91.7167,33.9333],"type":"Point"}
}