{
  "id": 7263451,
  "type": "Feature",
  "properties": {
    "tgn:hierarchy":[
        "tgn:7263451",
        "tgn:7003615",
        "tgn:1000003",
        "tgn:7016845",
        "tgn:7029392"
    ],
    "tgn:id":7263451,
    "tgn:name:nl":"Larsertocht",
    "tgn:placetype":[
        "aat:300006075"
    ]
},
  "bbox": [],
  "geometry": {"coordinates":[5.566667,52.45],"type":"Point"}
}