{
  "id": 2560688,
  "type": "Feature",
  "properties": {
    "tgn:hierarchy":[
        "tgn:2560688",
        "tgn:1000001",
        "tgn:2001016",
        "tgn:7012149",
        "tgn:7007521",
        "tgn:7029392"
    ],
    "tgn:id":2560688,
    "tgn:name":"Oreland Lake",
    "tgn:placetype":[
        "aat:300008680"
    ]
},
  "bbox": [],
  "geometry": {"coordinates":[-93.9167,46.4167],"type":"Point"}
}