{
  "id": 2037972,
  "type": "Feature",
  "properties": {
    "tgn:hierarchy":[
        "tgn:2037972",
        "tgn:1000001",
        "tgn:7012149",
        "tgn:1002516",
        "tgn:7007255",
        "tgn:7029392"
    ],
    "tgn:id":2037972,
    "tgn:name":"Buechel",
    "tgn:placetype":[
        "aat:300008347"
    ]
},
  "bbox": [],
  "geometry": {"coordinates":[-85.65,38.1833],"type":"Point"}
}