<<<<<<< HEAD
{
  "id": 7361850,
  "type": "Feature",
  "properties": {
    "tgn:hierarchy":[
        "tgn:7361850",
        "tgn:1000001",
        "tgn:7005591",
        "tgn:7005560",
        "tgn:7029392"
    ],
    "tgn:id":7361850,
    "tgn:name":"El Capul\u00edn",
    "tgn:placetype":[
        "aat:300008347"
    ]
},
  "bbox": [],
  "geometry": {"coordinates":[-98.316667,16.516667],"type":"Point"}
}
=======
{"geometry":{"type":"Point","coordinates":[-98.316667,16.516667]},"type":"Feature","properties":{"hierarchy":["tgn:7361850","tgn:1000001","tgn:7005591","tgn:7005560","tgn:7029392"],"placetype":["aat:300008347"],"id":7361850,"name:xx":"El Capul\u00edn"}}
>>>>>>> 03f74aca74312dbeaf24d7e61306dd6a786dc3d0
