{
  "id": 7504985,
  "type": "Feature",
  "properties": {
    "tgn:hierarchy":[
        "tgn:7504985",
        "tgn:1008380",
        "tgn:1000226",
        "tgn:7000512",
        "tgn:1000006",
        "tgn:7029392"
    ],
    "tgn:id":7504985,
    "tgn:name:en":"Kapakura",
    "tgn:placetype":[
        "aat:300008850"
    ]
},
  "bbox": [],
  "geometry": {"coordinates":[175.651944,-41.446389],"type":"Point"}
}