{
  "id": 2138575,
  "type": "Feature",
  "properties": {
    "tgn:hierarchy":[
        "tgn:2138575",
        "tgn:1000001",
        "tgn:2001349",
        "tgn:7012149",
        "tgn:7007525",
        "tgn:7029392"
    ],
    "tgn:id":2138575,
    "tgn:name":"Ash Creek",
    "tgn:placetype":[
        "aat:300008706"
    ]
},
  "bbox": [],
  "geometry": {"coordinates":[-96.8333,40.1333],"type":"Point"}
}