{
  "id": 7366707,
  "type": "Feature",
  "properties": {
    "tgn:hierarchy":[
        "tgn:7366707",
        "tgn:7005580",
        "tgn:1000001",
        "tgn:7005560",
        "tgn:7029392"
    ],
    "tgn:id":7366707,
    "tgn:name":"Esp\u00edritu Santo",
    "tgn:placetype":[
        "aat:300008347"
    ]
},
  "bbox": [],
  "geometry": {"coordinates":[-92.083333,15.866667],"type":"Point"}
}