<<<<<<< HEAD
{
  "id": 2256418,
  "type": "Feature",
  "properties": {
    "tgn:hierarchy":[
        "tgn:2256418",
        "tgn:7006450",
        "tgn:1000001",
        "tgn:7012149",
        "tgn:2000088",
        "tgn:7029392"
    ],
    "tgn:id":2256418,
    "tgn:name":"Cora Island",
    "tgn:placetype":[
        "aat:300008791"
    ]
},
  "bbox": [],
  "geometry": {"coordinates":[-134.1167,55.9],"type":"Point"}
}
=======
{"geometry":{"type":"Point","coordinates":[-134.116700,55.900000]},"type":"Feature","properties":{"hierarchy":["tgn:2256418","tgn:7006450","tgn:1000001","tgn:7012149","tgn:2000088","tgn:7029392"],"placetype":["aat:300008791"],"id":2256418,"name:xx":"Cora Island"}}
>>>>>>> 03f74aca74312dbeaf24d7e61306dd6a786dc3d0
