{
  "id": 7281473,
  "type": "Feature",
  "properties": {
    "tgn:hierarchy":[
        "tgn:7281473",
        "tgn:1001702",
        "tgn:1000049",
        "tgn:1000002",
        "tgn:7029392"
    ],
    "tgn:id":7281473,
    "tgn:name":"Segunda, Punta",
    "tgn:placetype":[
        "aat:300386846"
    ]
},
  "bbox": [],
  "geometry": {"coordinates":[-73.083333,-52.116667],"type":"Point"}
}