{
  "id": 2471644,
  "type": "Feature",
  "properties": {
    "tgn:hierarchy":[
        "tgn:2471644",
        "tgn:1000001",
        "tgn:7012149",
        "tgn:2001190",
        "tgn:7007523",
        "tgn:7029392"
    ],
    "tgn:id":2471644,
    "tgn:name":"Lost Mountain",
    "tgn:placetype":[
        "aat:300008798"
    ]
},
  "bbox": [],
  "geometry": {"coordinates":[-91.4333,37.8333],"type":"Point"}
}