{
  "id": 7346327,
  "type": "Feature",
  "properties": {
    "tgn:hierarchy":[
        "tgn:7346327",
        "tgn:7002808",
        "tgn:7030216",
        "tgn:1000003",
        "tgn:1000095",
        "tgn:7029392"
    ],
    "tgn:id":7346327,
    "tgn:name":"Ayguafreda",
    "tgn:placetype":[
        "aat:300008347"
    ]
},
  "bbox": [],
  "geometry": {"coordinates":[2.250857,41.767667],"type":"Point"}
}