{
  "id": 2631663,
  "type": "Feature",
  "properties": {
    "tgn:hierarchy":[
        "tgn:2631663",
        "tgn:1000001",
        "tgn:7012149",
        "tgn:2000494",
        "tgn:7007250",
        "tgn:7029392"
    ],
    "tgn:id":2631663,
    "tgn:name":"Round Valley Creek",
    "tgn:placetype":[
        "aat:300008706"
    ]
},
  "bbox": [],
  "geometry": {"coordinates":[-115.95,44.3333],"type":"Point"}
}