{
  "id": 7385961,
  "type": "Feature",
  "properties": {
    "tgn:hierarchy":[
        "tgn:7385961",
        "tgn:1000001",
        "tgn:1001960",
        "tgn:7005560",
        "tgn:7029392"
    ],
    "tgn:id":7385961,
    "tgn:name":"Quiriego",
    "tgn:placetype":[
        "aat:300008347"
    ]
},
  "bbox": [],
  "geometry": {"coordinates":[-109.266667,27.516667],"type":"Point"}
}