<<<<<<< HEAD
{
  "id": 7052697,
  "type": "Feature",
  "properties": {
    "tgn:hierarchy":[
        "tgn:7052697",
        "tgn:1003510",
        "tgn:1000003",
        "tgn:7003120",
        "tgn:1000080",
        "tgn:7029392"
    ],
    "tgn:id":7052697,
    "tgn:name":"Peccia",
    "tgn:placetype":[
        "aat:300008347"
    ]
},
  "bbox": [],
  "geometry": {"coordinates":[7.9,45.8],"type":"Point"}
}
=======
{"geometry":{"type":"Point","coordinates":[7.900000,45.800000]},"type":"Feature","properties":{"hierarchy":["tgn:7052697","tgn:1003510","tgn:1000003","tgn:7003120","tgn:1000080","tgn:7029392"],"placetype":["aat:300008347"],"id":7052697,"name:xx":"Peccia"}}
>>>>>>> 03f74aca74312dbeaf24d7e61306dd6a786dc3d0
