{
  "id": 7229866,
  "type": "Feature",
  "properties": {
    "tgn:hierarchy":[
        "tgn:7229866",
        "tgn:7011330",
        "tgn:7002674",
        "tgn:1000003",
        "tgn:1000074",
        "tgn:7029392"
    ],
    "tgn:id":7229866,
    "tgn:name":"Kap\u00edon",
    "tgn:placetype":[
        "aat:300008347"
    ]
},
  "bbox": [],
  "geometry": {"coordinates":[27.916667,36.266667],"type":"Point"}
}