{
  "id": 7343950,
  "type": "Feature",
  "properties": {
    "tgn:hierarchy":[
        "tgn:7343950",
        "tgn:7002836",
        "tgn:7016622",
        "tgn:1000003",
        "tgn:1000095",
        "tgn:7029392"
    ],
    "tgn:id":7343950,
    "tgn:name":"Casa Nueva",
    "tgn:placetype":[
        "aat:300008347"
    ]
},
  "bbox": [],
  "geometry": {"coordinates":[-17.933333,28.65],"type":"Point"}
}