{
  "id": 7135172,
  "type": "Feature",
  "properties": {
    "tgn:hierarchy":[
        "tgn:7135172",
        "tgn:1000003",
        "tgn:7000094",
        "tgn:7000084",
        "tgn:7029392"
    ],
    "tgn:id":7135172,
    "tgn:name":"Nardevitz",
    "tgn:placetype":[
        "aat:300008347"
    ]
},
  "bbox": [],
  "geometry": {"coordinates":[13.566667,54.583333],"type":"Point"}
}