{
  "id": 2746027,
  "type": "Feature",
  "properties": {
    "tgn:hierarchy":[
        "tgn:2746027",
        "tgn:7006450",
        "tgn:1000001",
        "tgn:7012149",
        "tgn:2000089",
        "tgn:7029392"
    ],
    "tgn:id":2746027,
    "tgn:name":"Volcano Creek",
    "tgn:placetype":[
        "aat:300008706"
    ]
},
  "bbox": [],
  "geometry": {"coordinates":[-145.4667,65.0667],"type":"Point"}
}