<<<<<<< HEAD
{
  "id": 2155006,
  "type": "Feature",
  "properties": {
    "tgn:hierarchy":[
        "tgn:2155006",
        "tgn:1000001",
        "tgn:7012149",
        "tgn:2002272",
        "tgn:7013961",
        "tgn:7029392"
    ],
    "tgn:id":2155006,
    "tgn:name":"Bear Knob",
    "tgn:placetype":[
        "aat:300008798"
    ]
},
  "bbox": [],
  "geometry": {"coordinates":[-82.2167,38.15],"type":"Point"}
}
=======
{"geometry":{"type":"Point","coordinates":[-82.216700,38.150000]},"type":"Feature","properties":{"hierarchy":["tgn:2155006","tgn:1000001","tgn:7012149","tgn:2002272","tgn:7013961","tgn:7029392"],"placetype":["aat:300008798"],"id":2155006,"name:xx":"Bear Knob"}}
>>>>>>> 03f74aca74312dbeaf24d7e61306dd6a786dc3d0
