{
  "id": 1133243,
  "type": "Feature",
  "properties": {
    "tgn:hierarchy":[
        "tgn:1133243",
        "tgn:1000001",
        "tgn:1002273",
        "tgn:7012149",
        "tgn:7007252",
        "tgn:7029392"
    ],
    "tgn:id":1133243,
    "tgn:name":"Fourteenmile Creek",
    "tgn:placetype":[
        "aat:300008706"
    ]
},
  "bbox": [],
  "geometry": {"coordinates":[-85.5667,38.5667],"type":"Point"}
}