{
  "id": 7020011,
  "type": "Feature",
  "properties": {
    "tgn:hierarchy":[
        "tgn:7020011",
        "tgn:1002165",
        "tgn:1000001",
        "tgn:7012149",
        "tgn:7007517",
        "tgn:7029392"
    ],
    "tgn:id":7020011,
    "tgn:name":"Cape Cod National Seashore",
    "tgn:placetype":[
        "aat:300072250"
    ]
},
  "bbox": [],
  "geometry": {"coordinates":[-69.9167,41.4167],"type":"Point"}
}