<<<<<<< HEAD
{
  "id": 7020011,
  "type": "Feature",
  "properties": {
    "tgn:hierarchy":[
        "tgn:7020011",
        "tgn:1002165",
        "tgn:1000001",
        "tgn:7012149",
        "tgn:7007517",
        "tgn:7029392"
    ],
    "tgn:id":7020011,
    "tgn:name":"Cape Cod National Seashore",
    "tgn:placetype":[
        "aat:300072250"
    ]
},
  "bbox": [],
  "geometry": {"coordinates":[-69.9167,41.4167],"type":"Point"}
}
=======
{"geometry":{"type":"Point","coordinates":[-69.916700,41.416700]},"type":"Feature","properties":{"hierarchy":["tgn:7020011","tgn:1002165","tgn:1000001","tgn:7012149","tgn:7007517","tgn:7029392"],"placetype":["aat:300072250"],"id":7020011,"name:xx":"Cape Cod National Seashore"}}
>>>>>>> 03f74aca74312dbeaf24d7e61306dd6a786dc3d0
