{
  "id": 1018775,
  "type": "Feature",
  "properties": {
    "tgn:hierarchy":[
        "tgn:1018775",
        "tgn:1000742",
        "tgn:1000001",
        "tgn:7005562",
        "tgn:7029392"
    ],
    "tgn:id":1018775,
    "tgn:name":"San Jorge",
    "tgn:placetype":[
        "aat:300008347"
    ]
},
  "bbox": [],
  "geometry": {"coordinates":[-85.8167,11.4667],"type":"Point"}
}