{
  "id": 2590290,
  "type": "Feature",
  "properties": {
    "tgn:hierarchy":[
        "tgn:2590290",
        "tgn:1000001",
        "tgn:7012149",
        "tgn:2000897",
        "tgn:7007256",
        "tgn:7029392"
    ],
    "tgn:id":2590290,
    "tgn:name":"Pokey Dutch",
    "tgn:placetype":[
        "aat:300132316"
    ]
},
  "bbox": [],
  "geometry": {"coordinates":[-89.4333,30.1333],"type":"Point"}
}