{
  "id": 7385373,
  "type": "Feature",
  "properties": {
    "tgn:hierarchy":[
        "tgn:7385373",
        "tgn:1001836",
        "tgn:1000001",
        "tgn:7005560",
        "tgn:7029392"
    ],
    "tgn:id":7385373,
    "tgn:name":"Monta\u00f1a, Punta",
    "tgn:placetype":[
        "aat:300386846"
    ]
},
  "bbox": [],
  "geometry": {"coordinates":[-109.833333,24.133333],"type":"Point"}
}