{
  "id": 7579042,
  "type": "Feature",
  "properties": {
    "tgn:hierarchy":[
        "tgn:7579042",
        "tgn:1000004",
        "tgn:7000198",
        "tgn:1001996",
        "tgn:7029392"
    ],
    "tgn:id":7579042,
    "tgn:name:en":"Wangtu",
    "tgn:placetype":[
        "aat:300008347"
    ]
},
  "bbox": [],
  "geometry": {"coordinates":[78.014082,31.546854],"type":"Point"}
}