{
  "id": 2348473,
  "type": "Feature",
  "properties": {
    "tgn:hierarchy":[
        "tgn:2348473",
        "tgn:2000000",
        "tgn:7002659",
        "tgn:1000001",
        "tgn:7012149",
        "tgn:7029392"
    ],
    "tgn:id":2348473,
    "tgn:name":"Gibbons",
    "tgn:placetype":[
        "aat:300008347"
    ]
},
  "bbox": [],
  "geometry": {"coordinates":[-86.5833,32.5333],"type":"Point"}
}