{
  "id": 2112057,
  "type": "Feature",
  "properties": {
    "tgn:hierarchy":[
        "tgn:2112057",
        "tgn:1000001",
        "tgn:7012149",
        "tgn:1002411",
        "tgn:7007919",
        "tgn:7029392"
    ],
    "tgn:id":2112057,
    "tgn:name":"Gum Fork",
    "tgn:placetype":[
        "aat:300008347",
        "aat:300387210"
    ]
},
  "bbox": [],
  "geometry": {"coordinates":[-76.5667,37.3667],"type":"Point"}
}