{
  "id": 2687087,
  "type": "Feature",
  "properties": {
    "tgn:hierarchy":[
        "tgn:2687087",
        "tgn:1000001",
        "tgn:7012149",
        "tgn:1002995",
        "tgn:7007710",
        "tgn:7029392"
    ],
    "tgn:id":2687087,
    "tgn:name":"Spring Hill",
    "tgn:placetype":[
        "aat:300008798"
    ]
},
  "bbox": [],
  "geometry": {"coordinates":[-80.0167,40.0333],"type":"Point"}
}