{
  "id": 2468219,
  "type": "Feature",
  "properties": {
    "tgn:hierarchy":[
        "tgn:2468219",
        "tgn:1000001",
        "tgn:7012149",
        "tgn:1002789",
        "tgn:7007710",
        "tgn:7029392"
    ],
    "tgn:id":2468219,
    "tgn:name":"Long Meadow Brook",
    "tgn:placetype":[
        "aat:300008699"
    ]
},
  "bbox": [],
  "geometry": {"coordinates":[-74.8833,41.2667],"type":"Point"}
}