{
  "id": 7351608,
  "type": "Feature",
  "properties": {
    "tgn:hierarchy":[
        "tgn:7351608",
        "tgn:7005581",
        "tgn:1000001",
        "tgn:7005560",
        "tgn:7029392"
    ],
    "tgn:id":7351608,
    "tgn:name":"Rancho de la Boquilla",
    "tgn:placetype":[
        "aat:300000241"
    ]
},
  "bbox": [],
  "geometry": {"coordinates":[-105.683333,29.133333],"type":"Point"}
}