<<<<<<< HEAD
{
  "id": 7351608,
  "type": "Feature",
  "properties": {
    "tgn:hierarchy":[
        "tgn:7351608",
        "tgn:7005581",
        "tgn:1000001",
        "tgn:7005560",
        "tgn:7029392"
    ],
    "tgn:id":7351608,
    "tgn:name":"Rancho de la Boquilla",
    "tgn:placetype":[
        "aat:300000241"
    ]
},
  "bbox": [],
  "geometry": {"coordinates":[-105.683333,29.133333],"type":"Point"}
}
=======
{"geometry":{"type":"Point","coordinates":[-105.683333,29.133333]},"type":"Feature","properties":{"hierarchy":["tgn:7351608","tgn:7005581","tgn:1000001","tgn:7005560","tgn:7029392"],"placetype":["aat:300000241"],"id":7351608,"name:xx":"Rancho de la Boquilla"}}
>>>>>>> 03f74aca74312dbeaf24d7e61306dd6a786dc3d0
