<<<<<<< HEAD
{
  "id": 7113082,
  "type": "Feature",
  "properties": {
    "tgn:hierarchy":[
        "tgn:7113082",
        "tgn:7003692",
        "tgn:1000003",
        "tgn:7000084",
        "tgn:7029392"
    ],
    "tgn:id":7113082,
    "tgn:name":"Reute",
    "tgn:placetype":[
        "aat:300008347"
    ]
},
  "bbox": [],
  "geometry": {"coordinates":[9.35,47.683333],"type":"Point"}
}
=======
{"geometry":{"type":"Point","coordinates":[9.350000,47.683333]},"type":"Feature","properties":{"hierarchy":["tgn:7113082","tgn:7003692","tgn:1000003","tgn:7000084","tgn:7029392"],"placetype":["aat:300008347"],"id":7113082,"name:xx":"Reute"}}
>>>>>>> 03f74aca74312dbeaf24d7e61306dd6a786dc3d0
