{
  "id": 7113082,
  "type": "Feature",
  "properties": {
    "tgn:hierarchy":[
        "tgn:7113082",
        "tgn:7003692",
        "tgn:1000003",
        "tgn:7000084",
        "tgn:7029392"
    ],
    "tgn:id":7113082,
    "tgn:name":"Reute",
    "tgn:placetype":[
        "aat:300008347"
    ]
},
  "bbox": [],
  "geometry": {"coordinates":[9.35,47.683333],"type":"Point"}
}