{
  "id": 2324189,
  "type": "Feature",
  "properties": {
    "tgn:hierarchy":[
        "tgn:2324189",
        "tgn:1000001",
        "tgn:7012149",
        "tgn:2001442",
        "tgn:7007566",
        "tgn:7029392"
    ],
    "tgn:id":2324189,
    "tgn:name":"Feather Cave",
    "tgn:placetype":[
        "aat:300008746"
    ]
},
  "bbox": [],
  "geometry": {"coordinates":[-105.3833,33.4833],"type":"Point"}
}