<<<<<<< HEAD
{
  "id": 2766091,
  "type": "Feature",
  "properties": {
    "tgn:hierarchy":[
        "tgn:2766091",
        "tgn:1000001",
        "tgn:7012149",
        "tgn:7007157",
        "tgn:1002828",
        "tgn:7029392"
    ],
    "tgn:id":2766091,
    "tgn:name":"White House Canyon",
    "tgn:placetype":[
        "aat:300008761"
    ]
},
  "bbox": [],
  "geometry": {"coordinates":[-116.5333,34.0],"type":"Point"}
}
=======
{"geometry":{"type":"Point","coordinates":[-116.533300,34.000000]},"type":"Feature","properties":{"hierarchy":["tgn:2766091","tgn:1000001","tgn:7012149","tgn:7007157","tgn:1002828","tgn:7029392"],"placetype":["aat:300008761"],"id":2766091,"name:xx":"White House Canyon"}}
>>>>>>> 03f74aca74312dbeaf24d7e61306dd6a786dc3d0
