{
  "id": 7537191,
  "type": "Feature",
  "properties": {
    "tgn:hierarchy":[
        "tgn:7537191",
        "tgn:7001242",
        "tgn:7016833",
        "tgn:7001336",
        "tgn:7029392"
    ],
    "tgn:id":7537191,
    "tgn:name:en":"Qurnah, W\u0101d\u012b",
    "tgn:placetype":[
        "aat:300379998"
    ]
},
  "bbox": [],
  "geometry": {"coordinates":[34.414491,28.612125],"type":"Point"}
}