<<<<<<< HEAD
{
  "id": 2259779,
  "type": "Feature",
  "properties": {
    "tgn:hierarchy":[
        "tgn:2259779",
        "tgn:1000001",
        "tgn:7012149",
        "tgn:1002594",
        "tgn:7007920",
        "tgn:7029392"
    ],
    "tgn:id":2259779,
    "tgn:name":"Cougar Mountain",
    "tgn:placetype":[
        "aat:300008798"
    ]
},
  "bbox": [],
  "geometry": {"coordinates":[-122.3333,46.7],"type":"Point"}
}
=======
{"geometry":{"type":"Point","coordinates":[-122.333300,46.700000]},"type":"Feature","properties":{"hierarchy":["tgn:2259779","tgn:1000001","tgn:7012149","tgn:1002594","tgn:7007920","tgn:7029392"],"placetype":["aat:300008798"],"id":2259779,"name:xx":"Cougar Mountain"}}
>>>>>>> 03f74aca74312dbeaf24d7e61306dd6a786dc3d0
