{
  "id": 7464613,
  "type": "Feature",
  "properties": {
    "tgn:hierarchy":[
        "tgn:7464613",
        "tgn:7002444",
        "tgn:1000003",
        "tgn:7029508",
        "tgn:7008591",
        "tgn:7029392"
    ],
    "tgn:id":7464613,
    "tgn:name:en":"Brae Wick",
    "tgn:placetype":[
        "aat:300132316"
    ]
},
  "bbox": [],
  "geometry": {"coordinates":[-1.55,60.483333],"type":"Point"}
}