{
  "id": 2213286,
  "type": "Feature",
  "properties": {
    "tgn:hierarchy":[
        "tgn:2213286",
        "tgn:1000001",
        "tgn:7012149",
        "tgn:2001717",
        "tgn:7007708",
        "tgn:7029392"
    ],
    "tgn:id":2213286,
    "tgn:name":"Cabin Creek",
    "tgn:placetype":[
        "aat:300008706"
    ]
},
  "bbox": [],
  "geometry": {"coordinates":[-122.4667,44.4167],"type":"Point"}
}