{
  "id": 2436474,
  "type": "Feature",
  "properties": {
    "tgn:hierarchy":[
        "tgn:2436474",
        "tgn:1000001",
        "tgn:1002200",
        "tgn:7012149",
        "tgn:7007240",
        "tgn:7029392"
    ],
    "tgn:id":2436474,
    "tgn:name":"Kid Creek",
    "tgn:placetype":[
        "aat:300008706"
    ]
},
  "bbox": [],
  "geometry": {"coordinates":[-80.5333,27.9333],"type":"Point"}
}