{
  "id": 2207754,
  "type": "Feature",
  "properties": {
    "tgn:hierarchy":[
        "tgn:2207754",
        "tgn:1000001",
        "tgn:2001266",
        "tgn:7012149",
        "tgn:7007524",
        "tgn:7029392"
    ],
    "tgn:id":2207754,
    "tgn:name":"Burg Creek",
    "tgn:placetype":[
        "aat:300008706"
    ]
},
  "bbox": [],
  "geometry": {"coordinates":[-110.6833,46.95],"type":"Point"}
}