{
  "id": 7323937,
  "type": "Feature",
  "properties": {
    "tgn:hierarchy":[
        "tgn:7323937",
        "tgn:7002824",
        "tgn:1000003",
        "tgn:7002786",
        "tgn:1000095",
        "tgn:7029392"
    ],
    "tgn:id":7323937,
    "tgn:name":"Ribadeume",
    "tgn:placetype":[
        "aat:300008347"
    ]
},
  "bbox": [],
  "geometry": {"coordinates":[-8.066667,43.45],"type":"Point"}
}