{
  "id": 7329488,
  "type": "Feature",
  "properties": {
    "tgn:hierarchy":[
        "tgn:7329488",
        "tgn:7002760",
        "tgn:1000003",
        "tgn:1000095",
        "tgn:7029392"
    ],
    "tgn:id":7329488,
    "tgn:name":"Posadillo",
    "tgn:placetype":[
        "aat:300008347"
    ]
},
  "bbox": [],
  "geometry": {"coordinates":[-4.016667,43.383333],"type":"Point"}
}