{
  "id": 2596249,
  "type": "Feature",
  "properties": {
    "tgn:hierarchy":[
        "tgn:2596249",
        "tgn:1000001",
        "tgn:7012149",
        "tgn:7007516",
        "tgn:7029392"
    ],
    "tgn:id":2596249,
    "tgn:name":"Pound Marsh",
    "tgn:placetype":[
        "aat:300008905"
    ]
},
  "bbox": [],
  "geometry": {"coordinates":[-75.8667,38.35],"type":"Point"}
}