{
  "id": 2542408,
  "type": "Feature",
  "properties": {
    "tgn:hierarchy":[
        "tgn:2542408",
        "tgn:1000001",
        "tgn:7012149",
        "tgn:1002418",
        "tgn:7007920",
        "tgn:7029392"
    ],
    "tgn:id":2542408,
    "tgn:name":"No Name Creek",
    "tgn:placetype":[
        "aat:300008706"
    ]
},
  "bbox": [],
  "geometry": {"coordinates":[-124.1667,47.3833],"type":"Point"}
}