{
  "id": 2534875,
  "type": "Feature",
  "properties": {
    "tgn:hierarchy":[
        "tgn:2534875",
        "tgn:1007657",
        "tgn:1002534",
        "tgn:1000001",
        "tgn:7012149",
        "tgn:7007249",
        "tgn:7029392"
    ],
    "tgn:id":2534875,
    "tgn:name":"Nailiakauea",
    "tgn:placetype":[
        "aat:300008798"
    ]
},
  "bbox": [],
  "geometry": {"coordinates":[-159.35,22.0333],"type":"Point"}
}