{
  "id": 2366600,
  "type": "Feature",
  "properties": {
    "tgn:hierarchy":[
        "tgn:2366600",
        "tgn:1000001",
        "tgn:2001024",
        "tgn:7012149",
        "tgn:7007521",
        "tgn:7029392"
    ],
    "tgn:id":2366600,
    "tgn:name":"Grinder Lake",
    "tgn:placetype":[
        "aat:300008680"
    ]
},
  "bbox": [],
  "geometry": {"coordinates":[-95.9333,46.0833],"type":"Point"}
}