{
  "id": 2506793,
  "type": "Feature",
  "properties": {
    "tgn:hierarchy":[
        "tgn:2506793",
        "tgn:1000001",
        "tgn:2001436",
        "tgn:7012149",
        "tgn:7007566",
        "tgn:7029392"
    ],
    "tgn:id":2506793,
    "tgn:name":"Mescalero Sands",
    "tgn:placetype":[
        "aat:300055621"
    ]
},
  "bbox": [],
  "geometry": {"coordinates":[-103.95,32.9333],"type":"Point"}
}