{
  "id": 7523034,
  "type": "Feature",
  "properties": {
    "tgn:hierarchy":[
        "tgn:7523034",
        "tgn:7001242",
        "tgn:7016833",
        "tgn:7001312",
        "tgn:7029392"
    ],
    "tgn:id":7523034,
    "tgn:name:en":"Dir\u00een",
    "tgn:placetype":[
        "aat:300008347"
    ]
},
  "bbox": [],
  "geometry": {"coordinates":[31.268646,31.097736],"type":"Point"}
}