{
  "id": 7094872,
  "type": "Feature",
  "properties": {
    "tgn:hierarchy":[
        "tgn:7094872",
        "tgn:1000003",
        "tgn:7003677",
        "tgn:7000084",
        "tgn:7029392"
    ],
    "tgn:id":7094872,
    "tgn:name":"Schulze Natorp",
    "tgn:placetype":[
        "aat:300000206"
    ]
},
  "bbox": [],
  "geometry": {"coordinates":[7.75,51.816667],"type":"Point"}
}