{
  "id": 2384089,
  "type": "Feature",
  "properties": {
    "tgn:hierarchy":[
        "tgn:2384089",
        "tgn:7006450",
        "tgn:1000001",
        "tgn:7012149",
        "tgn:7019760",
        "tgn:7029392"
    ],
    "tgn:id":2384089,
    "tgn:name":"Heidi Rock",
    "tgn:placetype":[
        "aat:300008791"
    ]
},
  "bbox": [],
  "geometry": {"coordinates":[-135.0167,57.8833],"type":"Point"}
}