{
  "id": 7377846,
  "type": "Feature",
  "properties": {
    "tgn:hierarchy":[
        "tgn:7377846",
        "tgn:1000001",
        "tgn:7005594",
        "tgn:7005560",
        "tgn:7029392"
    ],
    "tgn:id":7377846,
    "tgn:name":"La Pitahaya",
    "tgn:placetype":[
        "aat:300008347"
    ]
},
  "bbox": [],
  "geometry": {"coordinates":[-99.116667,22.016667],"type":"Point"}
}