<<<<<<< HEAD
{
  "id": 7029770,
  "type": "Feature",
  "properties": {
    "tgn:hierarchy":[
        "tgn:7029770",
        "tgn:1000003",
        "tgn:7002877",
        "tgn:1000070",
        "tgn:7029392"
    ],
    "tgn:id":7029770,
    "tgn:name":"Sainte-Solange",
    "tgn:placetype":[
        "aat:300008347",
        "aat:300007466"
    ]
},
  "bbox": [],
  "geometry": {"coordinates":[2.542,47.116],"type":"Point"}
}
=======
{"geometry":{"type":"Point","coordinates":[2.542000,47.116000]},"type":"Feature","properties":{"hierarchy":["tgn:7029770","tgn:1000003","tgn:7002877","tgn:1000070","tgn:7029392"],"placetype":["aat:300008347","aat:300007466"],"id":7029770,"name:xx":"Sainte-Solange"}}
>>>>>>> 03f74aca74312dbeaf24d7e61306dd6a786dc3d0
