{
  "id": 2550243,
  "type": "Feature",
  "properties": {
    "tgn:hierarchy":[
        "tgn:2550243",
        "tgn:1000001",
        "tgn:7012149",
        "tgn:2000890",
        "tgn:7007256",
        "tgn:7029392"
    ],
    "tgn:id":2550243,
    "tgn:name":"Northgate",
    "tgn:placetype":[
        "aat:300008347"
    ]
},
  "bbox": [],
  "geometry": {"coordinates":[-92.0667,32.5333],"type":"Point"}
}