<<<<<<< HEAD
{
  "id": 7110445,
  "type": "Feature",
  "properties": {
    "tgn:hierarchy":[
        "tgn:7110445",
        "tgn:1000003",
        "tgn:7003685",
        "tgn:7000084",
        "tgn:7029392"
    ],
    "tgn:id":7110445,
    "tgn:name":"Reick",
    "tgn:placetype":[
        "aat:300000745"
    ]
},
  "bbox": [],
  "geometry": {"coordinates":[13.8,51.016667],"type":"Point"}
}
=======
{"geometry":{"type":"Point","coordinates":[13.800000,51.016667]},"type":"Feature","properties":{"hierarchy":["tgn:7110445","tgn:1000003","tgn:7003685","tgn:7000084","tgn:7029392"],"placetype":["aat:300000745"],"id":7110445,"name:xx":"Reick"}}
>>>>>>> 03f74aca74312dbeaf24d7e61306dd6a786dc3d0
