{
  "id": 7035118,
  "type": "Feature",
  "properties": {
    "tgn:hierarchy":[
        "tgn:7035118",
        "tgn:1003506",
        "tgn:1000003",
        "tgn:7002993",
        "tgn:1000080",
        "tgn:7029392"
    ],
    "tgn:id":7035118,
    "tgn:name":"Tribil di Sopra",
    "tgn:placetype":[
        "aat:300008347"
    ]
},
  "bbox": [],
  "geometry": {"coordinates":[13.6225,46.141389],"type":"Point"}
}