{
  "id": 7418554,
  "type": "Feature",
  "properties": {
    "tgn:hierarchy":[
        "tgn:7418554",
        "tgn:7005579",
        "tgn:1000001",
        "tgn:7005560",
        "tgn:7029392"
    ],
    "tgn:id":7418554,
    "tgn:name":"La Cantera, Cerro",
    "tgn:placetype":[
        "aat:300008795"
    ]
},
  "bbox": [],
  "geometry": {"coordinates":[-102.75,22.041667],"type":"Point"}
}