{
  "id": 2635798,
  "type": "Feature",
  "properties": {
    "tgn:hierarchy":[
        "tgn:2635798",
        "tgn:1000001",
        "tgn:7012149",
        "tgn:2002371",
        "tgn:7007923",
        "tgn:7029392"
    ],
    "tgn:id":2635798,
    "tgn:name":"Sacagawea, Mount",
    "tgn:placetype":[
        "aat:300008798"
    ]
},
  "bbox": [],
  "geometry": {"coordinates":[-109.6167,43.1333],"type":"Point"}
}