{
  "id": 7537148,
  "type": "Feature",
  "properties": {
    "tgn:hierarchy":[
        "tgn:7537148",
        "tgn:7001242",
        "tgn:7016833",
        "tgn:1001225",
        "tgn:7029392"
    ],
    "tgn:id":7537148,
    "tgn:name:en":"Shalabi, \u1e0cahr",
    "tgn:placetype":[
        "aat:300008791"
    ]
},
  "bbox": [],
  "geometry": {"coordinates":[31.900667,31.424441],"type":"Point"}
}