{
  "id": 7494159,
  "type": "Feature",
  "properties": {
    "tgn:hierarchy":[
        "tgn:7494159",
        "tgn:7001004",
        "tgn:1000004",
        "tgn:1000141",
        "tgn:7029392"
    ],
    "tgn:id":7494159,
    "tgn:name":"Yixi Diaoqiao",
    "tgn:placetype":[
        "aat:300007836"
    ]
},
  "bbox": [],
  "geometry": {"coordinates":[120.723349,23.291442],"type":"Point"}
}