{
  "id": 7207446,
  "type": "Feature",
  "properties": {
    "tgn:hierarchy":[
        "tgn:7207446",
        "tgn:1000003",
        "tgn:7000094",
        "tgn:7000084",
        "tgn:7029392"
    ],
    "tgn:id":7207446,
    "tgn:name":"Cronskamp",
    "tgn:placetype":[
        "aat:300008347"
    ]
},
  "bbox": [],
  "geometry": {"coordinates":[10.883333,53.766667],"type":"Point"}
}