{
  "id": 7587966,
  "type": "Feature",
  "properties": {
    "tgn:hierarchy":[
        "tgn:7587966",
        "tgn:1000004",
        "tgn:7000198",
        "tgn:7000799",
        "tgn:7029392"
    ],
    "tgn:id":7587966,
    "tgn:name:en":"Kunzar",
    "tgn:placetype":[
        "aat:300008347"
    ]
},
  "bbox": [],
  "geometry": {"coordinates":[74.499946,34.095193],"type":"Point"}
}