{
  "id": 2469668,
  "type": "Feature",
  "properties": {
    "tgn:hierarchy":[
        "tgn:2469668",
        "tgn:1000001",
        "tgn:1002934",
        "tgn:7012149",
        "tgn:7007565",
        "tgn:7029392"
    ],
    "tgn:id":2469668,
    "tgn:name":"Lookout Mountain",
    "tgn:placetype":[
        "aat:300008798"
    ]
},
  "bbox": [],
  "geometry": {"coordinates":[-74.65,40.9333],"type":"Point"}
}