{
  "id": 7217320,
  "type": "Feature",
  "properties": {
    "tgn:hierarchy":[
        "tgn:7217320",
        "tgn:7011164",
        "tgn:7002674",
        "tgn:1000003",
        "tgn:1000074",
        "tgn:7029392"
    ],
    "tgn:id":7217320,
    "tgn:name":"Meson\u00edsi",
    "tgn:placetype":[
        "aat:300266640"
    ]
},
  "bbox": [],
  "geometry": {"coordinates":[26.612778,37.754167],"type":"Point"}
}