{
  "id": 2578124,
  "type": "Feature",
  "properties": {
    "tgn:hierarchy":[
        "tgn:2578124",
        "tgn:1000001",
        "tgn:7020676",
        "tgn:7012149",
        "tgn:7007256",
        "tgn:7029392"
    ],
    "tgn:id":2578124,
    "tgn:name":"Peveto Beach",
    "tgn:placetype":[
        "aat:300008347"
    ]
},
  "bbox": [],
  "geometry": {"coordinates":[-93.55,29.75],"type":"Point"}
}