{
  "id": 7068554,
  "type": "Feature",
  "properties": {
    "tgn:hierarchy":[
        "tgn:7068554",
        "tgn:1000003",
        "tgn:7003687",
        "tgn:7000084",
        "tgn:7029392"
    ],
    "tgn:id":7068554,
    "tgn:name":"Stammersh\u00f6he",
    "tgn:placetype":[
        "aat:300008777"
    ]
},
  "bbox": [],
  "geometry": {"coordinates":[10.683333,51.816667],"type":"Point"}
}