{
  "id": 2240592,
  "type": "Feature",
  "properties": {
    "tgn:hierarchy":[
        "tgn:2240592",
        "tgn:1000001",
        "tgn:1002270",
        "tgn:7012149",
        "tgn:7007708",
        "tgn:7029392"
    ],
    "tgn:id":2240592,
    "tgn:name":"Clackamette Lake",
    "tgn:placetype":[
        "aat:300008680"
    ]
},
  "bbox": [],
  "geometry": {"coordinates":[-122.5833,45.3667],"type":"Point"}
}