{
  "id": 7004814,
  "type": "Feature",
  "properties": {
    "tgn:hierarchy":[
        "tgn:7004814",
        "tgn:1000976",
        "tgn:1000004",
        "tgn:7000893",
        "tgn:1000120",
        "tgn:7029392"
    ],
    "tgn:id":7004814,
    "tgn:name":"Shirakawa",
    "tgn:placetype":[
        "aat:300008347"
    ]
},
  "bbox": [],
  "geometry": {"coordinates":[140.1833,37.1167],"type":"Point"}
}