<<<<<<< HEAD
{
  "id": 7111453,
  "type": "Feature",
  "properties": {
    "tgn:hierarchy":[
        "tgn:7111453",
        "tgn:1000003",
        "tgn:7003678",
        "tgn:7000084",
        "tgn:7029392"
    ],
    "tgn:id":7111453,
    "tgn:name":"Rickshell",
    "tgn:placetype":[
        "aat:300008777"
    ]
},
  "bbox": [],
  "geometry": {"coordinates":[8.75,50.85],"type":"Point"}
}
=======
{"geometry":{"type":"Point","coordinates":[8.750000,50.850000]},"type":"Feature","properties":{"hierarchy":["tgn:7111453","tgn:1000003","tgn:7003678","tgn:7000084","tgn:7029392"],"placetype":["aat:300008777"],"id":7111453,"name:xx":"Rickshell"}}
>>>>>>> 03f74aca74312dbeaf24d7e61306dd6a786dc3d0
