{
  "id": 2054676,
  "type": "Feature",
  "properties": {
    "tgn:hierarchy":[
        "tgn:2054676",
        "tgn:1000001",
        "tgn:2001024",
        "tgn:7012149",
        "tgn:7007521",
        "tgn:7029392"
    ],
    "tgn:id":2054676,
    "tgn:name":"Hoffman",
    "tgn:placetype":[
        "aat:300008347"
    ]
},
  "bbox": [],
  "geometry": {"coordinates":[-95.7833,45.8167],"type":"Point"}
}