{
  "id": 7517836,
  "type": "Feature",
  "properties": {
    "tgn:hierarchy":[
        "tgn:7517836",
        "tgn:7000509",
        "tgn:1008380",
        "tgn:1000226",
        "tgn:1000006",
        "tgn:7029392"
    ],
    "tgn:id":7517836,
    "tgn:name:en":"Ngatamawahine Stream",
    "tgn:placetype":[
        "aat:300008699"
    ]
},
  "bbox": [],
  "geometry": {"coordinates":[176.766667,-38.35],"type":"Point"}
}