{
  "id": 7089398,
  "type": "Feature",
  "properties": {
    "tgn:hierarchy":[
        "tgn:7089398",
        "tgn:7003669",
        "tgn:1000003",
        "tgn:7000084",
        "tgn:7029392"
    ],
    "tgn:id":7089398,
    "tgn:name":"Unterwesterbach",
    "tgn:placetype":[
        "aat:300008347"
    ]
},
  "bbox": [],
  "geometry": {"coordinates":[13.183333,48.35],"type":"Point"}
}