<<<<<<< HEAD
{
  "id": 2156351,
  "type": "Feature",
  "properties": {
    "tgn:hierarchy":[
        "tgn:2156351",
        "tgn:1000001",
        "tgn:7012149",
        "tgn:2001519",
        "tgn:7007709",
        "tgn:7029392"
    ],
    "tgn:id":2156351,
    "tgn:name":"Bearpen Ridge",
    "tgn:placetype":[
        "aat:300266640"
    ]
},
  "bbox": [],
  "geometry": {"coordinates":[-82.1167,36.0833],"type":"Point"}
}
=======
{"geometry":{"type":"Point","coordinates":[-82.116700,36.083300]},"type":"Feature","properties":{"hierarchy":["tgn:2156351","tgn:1000001","tgn:7012149","tgn:2001519","tgn:7007709","tgn:7029392"],"placetype":["aat:300266640"],"id":2156351,"name:xx":"Bearpen Ridge"}}
>>>>>>> 03f74aca74312dbeaf24d7e61306dd6a786dc3d0
