{
  "id": 2156351,
  "type": "Feature",
  "properties": {
    "tgn:hierarchy":[
        "tgn:2156351",
        "tgn:1000001",
        "tgn:7012149",
        "tgn:2001519",
        "tgn:7007709",
        "tgn:7029392"
    ],
    "tgn:id":2156351,
    "tgn:name":"Bearpen Ridge",
    "tgn:placetype":[
        "aat:300266640"
    ]
},
  "bbox": [],
  "geometry": {"coordinates":[-82.1167,36.0833],"type":"Point"}
}