<<<<<<< HEAD
{
  "id": 7352822,
  "type": "Feature",
  "properties": {
    "tgn:hierarchy":[
        "tgn:7352822",
        "tgn:7005586",
        "tgn:1000001",
        "tgn:7005560",
        "tgn:7029392"
    ],
    "tgn:id":7352822,
    "tgn:name":"Alto Las Yeguas, Cerro",
    "tgn:placetype":[
        "aat:300008795"
    ]
},
  "bbox": [],
  "geometry": {"coordinates":[-104.233333,19.6],"type":"Point"}
}
=======
{"geometry":{"type":"Point","coordinates":[-104.233333,19.600000]},"type":"Feature","properties":{"hierarchy":["tgn:7352822","tgn:7005586","tgn:1000001","tgn:7005560","tgn:7029392"],"placetype":["aat:300008795"],"id":7352822,"name:xx":"Alto Las Yeguas, Cerro"}}
>>>>>>> 03f74aca74312dbeaf24d7e61306dd6a786dc3d0
