{
  "id": 7387813,
  "type": "Feature",
  "properties": {
    "tgn:hierarchy":[
        "tgn:7387813",
        "tgn:7005578",
        "tgn:1000001",
        "tgn:7005560",
        "tgn:7029392"
    ],
    "tgn:id":7387813,
    "tgn:name":"Pich",
    "tgn:placetype":[
        "aat:300008347"
    ]
},
  "bbox": [],
  "geometry": {"coordinates":[-90.083333,19.516667],"type":"Point"}
}