{
  "id": 2258248,
  "type": "Feature",
  "properties": {
    "tgn:hierarchy":[
        "tgn:2258248",
        "tgn:1000001",
        "tgn:7012149",
        "tgn:2002339",
        "tgn:7007922",
        "tgn:7029392"
    ],
    "tgn:id":2258248,
    "tgn:name":"Cott Lake",
    "tgn:placetype":[
        "aat:300008680"
    ]
},
  "bbox": [],
  "geometry": {"coordinates":[-88.7667,45.0833],"type":"Point"}
}