{
  "id": 2643706,
  "type": "Feature",
  "properties": {
    "tgn:hierarchy":[
        "tgn:2643706",
        "tgn:1000001",
        "tgn:7012149",
        "tgn:2000495",
        "tgn:7007250",
        "tgn:7029392"
    ],
    "tgn:id":2643706,
    "tgn:name":"Sandy Spring",
    "tgn:placetype":[
        "aat:300008697"
    ]
},
  "bbox": [],
  "geometry": {"coordinates":[-116.7667,44.3167],"type":"Point"}
}