{
  "id": 2284669,
  "type": "Feature",
  "properties": {
    "tgn:hierarchy":[
        "tgn:2284669",
        "tgn:1000001",
        "tgn:7006451",
        "tgn:7012149",
        "tgn:2000097",
        "tgn:7029392"
    ],
    "tgn:id":2284669,
    "tgn:name":"Desert Valley Estates",
    "tgn:placetype":[
        "aat:300008347"
    ]
},
  "bbox": [],
  "geometry": {"coordinates":[-112.0833,33.65],"type":"Point"}
}