{
  "id": 7579385,
  "type": "Feature",
  "properties": {
    "tgn:hierarchy":[
        "tgn:7579385",
        "tgn:1000004",
        "tgn:7000198",
        "tgn:7001797",
        "tgn:7029392"
    ],
    "tgn:id":7579385,
    "tgn:name:en":"Wodapatti",
    "tgn:placetype":[
        "aat:300008347"
    ]
},
  "bbox": [],
  "geometry": {"coordinates":[77.783333,12.133333],"type":"Point"}
}