{
  "id": 2544974,
  "type": "Feature",
  "properties": {
    "tgn:hierarchy":[
        "tgn:2544974",
        "tgn:1000001",
        "tgn:7012149",
        "tgn:1002593",
        "tgn:7007568",
        "tgn:7029392"
    ],
    "tgn:id":2544974,
    "tgn:name":"North Croghan Crossing",
    "tgn:placetype":[
        "aat:300008347"
    ]
},
  "bbox": [],
  "geometry": {"coordinates":[-75.4833,44.0333],"type":"Point"}
}