{
  "id": 2558773,
  "type": "Feature",
  "properties": {
    "tgn:hierarchy":[
        "tgn:2558773",
        "tgn:1000001",
        "tgn:7012149",
        "tgn:2002120",
        "tgn:7007827",
        "tgn:7029392"
    ],
    "tgn:id":2558773,
    "tgn:name":"Olsen Canyon",
    "tgn:placetype":[
        "aat:300008761"
    ]
},
  "bbox": [],
  "geometry": {"coordinates":[-111.6333,39.0667],"type":"Point"}
}