{
  "id": 2445401,
  "type": "Feature",
  "properties": {
    "tgn:hierarchy":[
        "tgn:2445401",
        "tgn:1000001",
        "tgn:7012149",
        "tgn:7018871",
        "tgn:7007920",
        "tgn:7029392"
    ],
    "tgn:id":2445401,
    "tgn:name":"Lennox Mountain",
    "tgn:placetype":[
        "aat:300008798"
    ]
},
  "bbox": [],
  "geometry": {"coordinates":[-121.4667,47.6667],"type":"Point"}
}