{
  "id": 2166281,
  "type": "Feature",
  "properties": {
    "tgn:hierarchy":[
        "tgn:2166281",
        "tgn:1000001",
        "tgn:7012149",
        "tgn:1002350",
        "tgn:7007157",
        "tgn:7029392"
    ],
    "tgn:id":2166281,
    "tgn:name":"Big Bend",
    "tgn:placetype":[
        "aat:300008798"
    ]
},
  "bbox": [],
  "geometry": {"coordinates":[-120.5167,38.85],"type":"Point"}
}