{
  "id": 2112989,
  "type": "Feature",
  "properties": {
    "tgn:hierarchy":[
        "tgn:2112989",
        "tgn:1000001",
        "tgn:2002150",
        "tgn:7012149",
        "tgn:7007919",
        "tgn:7029392"
    ],
    "tgn:id":2112989,
    "tgn:name":"Melrose",
    "tgn:placetype":[
        "aat:300008347",
        "aat:300387210"
    ]
},
  "bbox": [],
  "geometry": {"coordinates":[-79.05,37.0333],"type":"Point"}
}