{
  "id": 7314278,
  "type": "Feature",
  "properties": {
    "tgn:hierarchy":[
        "tgn:7314278",
        "tgn:1001637",
        "tgn:1000049",
        "tgn:1000002",
        "tgn:7029392"
    ],
    "tgn:id":7314278,
    "tgn:name":"Lircay",
    "tgn:placetype":[
        "aat:300000206"
    ]
},
  "bbox": [],
  "geometry": {"coordinates":[-72.316667,-36.316667],"type":"Point"}
}