{
  "id": 7229780,
  "type": "Feature",
  "properties": {
    "tgn:hierarchy":[
        "tgn:7229780",
        "tgn:7002721",
        "tgn:7002715",
        "tgn:1000003",
        "tgn:1000074",
        "tgn:7029392"
    ],
    "tgn:id":7229780,
    "tgn:name":"Kidhon\u00edai",
    "tgn:placetype":[
        "aat:300008347"
    ]
},
  "bbox": [],
  "geometry": {"coordinates":[21.283333,40.166667],"type":"Point"}
}