{
  "id": 7013975,
  "type": "Feature",
  "properties": {
    "tgn:hierarchy":[
        "tgn:7013975",
        "tgn:1000001",
        "tgn:1002665",
        "tgn:7012149",
        "tgn:7007517",
        "tgn:7029392"
    ],
    "tgn:id":7013975,
    "tgn:name":"Lowell",
    "tgn:placetype":[
        "aat:300008347",
        "aat:300008416",
        "aat:300008389",
        "aat:300387308",
        "aat:300264742",
        "aat:300387270",
        "aat:300387302"
    ]
},
  "bbox": [],
  "geometry": {"coordinates":[-71.3167,42.6333],"type":"Point"}
}