{
  "id": 2446232,
  "type": "Feature",
  "properties": {
    "tgn:hierarchy":[
        "tgn:2446232",
        "tgn:1000001",
        "tgn:7012149",
        "tgn:2001527",
        "tgn:7007709",
        "tgn:7029392"
    ],
    "tgn:id":2446232,
    "tgn:name":"Lewis Branch",
    "tgn:placetype":[
        "aat:300008699"
    ]
},
  "bbox": [],
  "geometry": {"coordinates":[-78.0667,34.4667],"type":"Point"}
}