<<<<<<< HEAD
{
  "id": 7350965,
  "type": "Feature",
  "properties": {
    "tgn:hierarchy":[
        "tgn:7350965",
        "tgn:1001835",
        "tgn:1000001",
        "tgn:7005560",
        "tgn:7029392"
    ],
    "tgn:id":7350965,
    "tgn:name":"Baj\u00edo Largo",
    "tgn:placetype":[
        "aat:300008347"
    ]
},
  "bbox": [],
  "geometry": {"coordinates":[-115.950278,32.086389],"type":"Point"}
}
=======
{"geometry":{"type":"Point","coordinates":[-115.950278,32.086389]},"type":"Feature","properties":{"hierarchy":["tgn:7350965","tgn:1001835","tgn:1000001","tgn:7005560","tgn:7029392"],"placetype":["aat:300008347"],"id":7350965,"name:xx":"Baj\u00edo Largo"}}
>>>>>>> 03f74aca74312dbeaf24d7e61306dd6a786dc3d0
