{
  "id": 2176613,
  "type": "Feature",
  "properties": {
    "tgn:hierarchy":[
        "tgn:2176613",
        "tgn:1000001",
        "tgn:7012149",
        "tgn:7007256",
        "tgn:7029392"
    ],
    "tgn:id":2176613,
    "tgn:name":"Black Lake Creek",
    "tgn:placetype":[
        "aat:300008706"
    ]
},
  "bbox": [],
  "geometry": {"coordinates":[-92.9167,32.5833],"type":"Point"}
}