{
  "id": 7207495,
  "type": "Feature",
  "properties": {
    "tgn:hierarchy":[
        "tgn:7207495",
        "tgn:1000003",
        "tgn:7003677",
        "tgn:7000084",
        "tgn:7029392"
    ],
    "tgn:id":7207495,
    "tgn:name":"B\u00fcttendorf",
    "tgn:placetype":[
        "aat:300008347"
    ]
},
  "bbox": [],
  "geometry": {"coordinates":[8.65,52.266667],"type":"Point"}
}