{
  "id": 2710669,
  "type": "Feature",
  "properties": {
    "tgn:hierarchy":[
        "tgn:2710669",
        "tgn:1000001",
        "tgn:7012149",
        "tgn:7007522",
        "tgn:7029392"
    ],
    "tgn:id":2710669,
    "tgn:name":"Tan Branch",
    "tgn:placetype":[
        "aat:300008699"
    ]
},
  "bbox": [],
  "geometry": {"coordinates":[-89.2333,34.2833],"type":"Point"}
}