{
  "id": 2355864,
  "type": "Feature",
  "properties": {
    "tgn:hierarchy":[
        "tgn:2355864",
        "tgn:1000001",
        "tgn:2001591",
        "tgn:7012149",
        "tgn:7007705",
        "tgn:7029392"
    ],
    "tgn:id":2355864,
    "tgn:name":"Goose Lake",
    "tgn:placetype":[
        "aat:300008680"
    ]
},
  "bbox": [],
  "geometry": {"coordinates":[-99.9167,48.4167],"type":"Point"}
}