{
  "id": 1030342,
  "type": "Feature",
  "properties": {
    "tgn:hierarchy":[
        "tgn:1030342",
        "tgn:7002445",
        "tgn:7008116",
        "tgn:1000003",
        "tgn:7008591",
        "tgn:7029392"
    ],
    "tgn:id":1030342,
    "tgn:name:en":"Polruan",
    "tgn:placetype":[
        "aat:300008347"
    ]
},
  "bbox": [],
  "geometry": {"coordinates":[-4.616667,50.316667],"type":"Point"}
}