<<<<<<< HEAD
{
  "id": 7117504,
  "type": "Feature",
  "properties": {
    "tgn:hierarchy":[
        "tgn:7117504",
        "tgn:1000003",
        "tgn:7003677",
        "tgn:7000084",
        "tgn:7029392"
    ],
    "tgn:id":7117504,
    "tgn:name":"\u00d6stliche Heide",
    "tgn:placetype":[
        "aat:300000206"
    ]
},
  "bbox": [],
  "geometry": {"coordinates":[8.95,52.4],"type":"Point"}
}
=======
{"geometry":{"type":"Point","coordinates":[8.950000,52.400000]},"type":"Feature","properties":{"hierarchy":["tgn:7117504","tgn:1000003","tgn:7003677","tgn:7000084","tgn:7029392"],"placetype":["aat:300000206"],"id":7117504,"name:xx":"\u00d6stliche Heide"}}
>>>>>>> 03f74aca74312dbeaf24d7e61306dd6a786dc3d0
