{
  "id": 7320837,
  "type": "Feature",
  "properties": {
    "tgn:hierarchy":[
        "tgn:7320837",
        "tgn:1001702",
        "tgn:1000049",
        "tgn:1000002",
        "tgn:7029392"
    ],
    "tgn:id":7320837,
    "tgn:name":"Burnt, Islas",
    "tgn:placetype":[
        "aat:300008791"
    ]
},
  "bbox": [],
  "geometry": {"coordinates":[-69.833333,-55.283333],"type":"Point"}
}