{
  "id": 7586060,
  "type": "Feature",
  "properties": {
    "tgn:hierarchy":[
        "tgn:7586060",
        "tgn:1000004",
        "tgn:7000198",
        "tgn:7000799",
        "tgn:7029392"
    ],
    "tgn:id":7586060,
    "tgn:name:en":"Hunur",
    "tgn:placetype":[
        "aat:300008347"
    ]
},
  "bbox": [],
  "geometry": {"coordinates":[74.242865,34.300748],"type":"Point"}
}