{
  "id": 7239705,
  "type": "Feature",
  "properties": {
    "tgn:hierarchy":[
        "tgn:7239705",
        "tgn:7003460",
        "tgn:1000003",
        "tgn:1000063",
        "tgn:4012014",
        "tgn:7029392"
    ],
    "tgn:id":7239705,
    "tgn:name":"Gr\u00fcfflingen",
    "tgn:placetype":[
        "aat:300008347"
    ]
},
  "bbox": [],
  "geometry": {"coordinates":[6.088889,50.224444],"type":"Point"}
}