{
  "id": 2368491,
  "type": "Feature",
  "properties": {
    "tgn:hierarchy":[
        "tgn:2368491",
        "tgn:1000001",
        "tgn:7012149",
        "tgn:2000238",
        "tgn:7007158",
        "tgn:7029392"
    ],
    "tgn:id":2368491,
    "tgn:name":"Guiraud Ditch",
    "tgn:placetype":[
        "aat:300006075"
    ]
},
  "bbox": [],
  "geometry": {"coordinates":[-105.8833,39.1167],"type":"Point"}
}