{
  "id": 1113046,
  "type": "Feature",
  "properties": {
    "tgn:hierarchy":[
        "tgn:1113046",
        "tgn:7014983",
        "tgn:1000001",
        "tgn:7004641",
        "tgn:7029392"
    ],
    "tgn:id":1113046,
    "tgn:name":"Grand Bay",
    "tgn:placetype":[
        "aat:300132316"
    ]
},
  "bbox": [],
  "geometry": {"coordinates":[-61.3167,15.2333],"type":"Point"}
}