{
  "id": 2572648,
  "type": "Feature",
  "properties": {
    "tgn:hierarchy":[
        "tgn:2572648",
        "tgn:1000001",
        "tgn:7012149",
        "tgn:2001665",
        "tgn:7007707",
        "tgn:7029392"
    ],
    "tgn:id":2572648,
    "tgn:name":"Peak Hill",
    "tgn:placetype":[
        "aat:300008798"
    ]
},
  "bbox": [],
  "geometry": {"coordinates":[-97.0833,33.9167],"type":"Point"}
}