{
  "id": 2688891,
  "type": "Feature",
  "properties": {
    "tgn:hierarchy":[
        "tgn:2688891",
        "tgn:1000001",
        "tgn:7012149",
        "tgn:2001252",
        "tgn:7007523",
        "tgn:7029392"
    ],
    "tgn:id":2688891,
    "tgn:name":"Spurlock Hollow",
    "tgn:placetype":[
        "aat:300008761"
    ]
},
  "bbox": [],
  "geometry": {"coordinates":[-92.1333,37.3167],"type":"Point"}
}