{
  "id": 2619601,
  "type": "Feature",
  "properties": {
    "tgn:hierarchy":[
        "tgn:2619601",
        "tgn:1000001",
        "tgn:2000202",
        "tgn:7012149",
        "tgn:7007158",
        "tgn:7029392"
    ],
    "tgn:id":2619601,
    "tgn:name":"Rincon, Ca\u00f1on",
    "tgn:placetype":[
        "aat:300008761"
    ]
},
  "bbox": [],
  "geometry": {"coordinates":[-106.5667,37.2667],"type":"Point"}
}