{
  "id": 1053474,
  "type": "Feature",
  "properties": {
    "tgn:hierarchy":[
        "tgn:1053474",
        "tgn:1000004",
        "tgn:7014474",
        "tgn:7018214",
        "tgn:7002435",
        "tgn:7029392"
    ],
    "tgn:id":1053474,
    "tgn:name":"Dzhaur",
    "tgn:placetype":[
        "aat:300008347"
    ]
},
  "bbox": [],
  "geometry": {"coordinates":[138.4833,50.0333],"type":"Point"}
}