{
  "id": 7435901,
  "type": "Feature",
  "properties": {
    "tgn:hierarchy":[
        "tgn:7435901",
        "tgn:1000001",
        "tgn:1001906",
        "tgn:7005560",
        "tgn:7029392"
    ],
    "tgn:id":7435901,
    "tgn:name":"San Valent\u00edn",
    "tgn:placetype":[
        "aat:300008347"
    ]
},
  "bbox": [],
  "geometry": {"coordinates":[-104.55,20.916667],"type":"Point"}
}