{
  "id": 2358709,
  "type": "Feature",
  "properties": {
    "tgn:hierarchy":[
        "tgn:2358709",
        "tgn:1000001",
        "tgn:7006451",
        "tgn:7012149",
        "tgn:2000103",
        "tgn:7029392"
    ],
    "tgn:id":2358709,
    "tgn:name":"Grandview Tank",
    "tgn:placetype":[
        "aat:300006191"
    ]
},
  "bbox": [],
  "geometry": {"coordinates":[-112.4667,33.95],"type":"Point"}
}