<<<<<<< HEAD
{
  "id": 2256515,
  "type": "Feature",
  "properties": {
    "tgn:hierarchy":[
        "tgn:2256515",
        "tgn:1000001",
        "tgn:2000457",
        "tgn:7012149",
        "tgn:7007250",
        "tgn:7029392"
    ],
    "tgn:id":2256515,
    "tgn:name":"Corbett Slough Canal",
    "tgn:placetype":[
        "aat:300006075"
    ]
},
  "bbox": [],
  "geometry": {"coordinates":[-112.3,43.2],"type":"Point"}
}
=======
{"geometry":{"type":"Point","coordinates":[-112.300000,43.200000]},"type":"Feature","properties":{"hierarchy":["tgn:2256515","tgn:1000001","tgn:2000457","tgn:7012149","tgn:7007250","tgn:7029392"],"placetype":["aat:300006075"],"id":2256515,"name:xx":"Corbett Slough Canal"}}
>>>>>>> 03f74aca74312dbeaf24d7e61306dd6a786dc3d0
