{
  "id": 7414811,
  "type": "Feature",
  "properties": {
    "tgn:hierarchy":[
        "tgn:7414811",
        "tgn:1000001",
        "tgn:7005591",
        "tgn:7005560",
        "tgn:7029392"
    ],
    "tgn:id":7414811,
    "tgn:name:es":"El Indio Dormido, Cord\u00f3n",
    "tgn:placetype":[
        "aat:300266640"
    ]
},
  "bbox": [],
  "geometry": {"coordinates":[-95.3125,16.574167],"type":"Point"}
}