{
  "id": 2656298,
  "type": "Feature",
  "properties": {
    "tgn:hierarchy":[
        "tgn:2656298",
        "tgn:1000001",
        "tgn:2001592",
        "tgn:7012149",
        "tgn:7007705",
        "tgn:7029392"
    ],
    "tgn:id":2656298,
    "tgn:name":"Shea Slough",
    "tgn:placetype":[
        "aat:300008905"
    ]
},
  "bbox": [],
  "geometry": {"coordinates":[-98.85,48.3833],"type":"Point"}
}