{
  "id": 2758473,
  "type": "Feature",
  "properties": {
    "tgn:hierarchy":[
        "tgn:2758473",
        "tgn:1000001",
        "tgn:2000461",
        "tgn:7012149",
        "tgn:7007250",
        "tgn:7029392"
    ],
    "tgn:id":2758473,
    "tgn:name":"West Center Canal",
    "tgn:placetype":[
        "aat:300006075"
    ]
},
  "bbox": [],
  "geometry": {"coordinates":[-111.9167,43.5333],"type":"Point"}
}