{
  "id": 7522693,
  "type": "Feature",
  "properties": {
    "tgn:hierarchy":[
        "tgn:7522693",
        "tgn:7001242",
        "tgn:7001105",
        "tgn:7016833",
        "tgn:7029392"
    ],
    "tgn:id":7522693,
    "tgn:name:en":"Ban\u012b \u015e\u0101li\u1e29",
    "tgn:placetype":[
        "aat:300008347"
    ]
},
  "bbox": [],
  "geometry": {"coordinates":[30.808056,29.359363],"type":"Point"}
}