{
  "id": 2459551,
  "type": "Feature",
  "properties": {
    "tgn:hierarchy":[
        "tgn:2459551",
        "tgn:1000001",
        "tgn:7019560",
        "tgn:7012149",
        "tgn:7007566",
        "tgn:7029392"
    ],
    "tgn:id":2459551,
    "tgn:name":"Little Ragland Tank",
    "tgn:placetype":[
        "aat:300006191"
    ]
},
  "bbox": [],
  "geometry": {"coordinates":[-104.7167,34.2167],"type":"Point"}
}