{
  "id": 2145576,
  "type": "Feature",
  "properties": {
    "tgn:hierarchy":[
        "tgn:2145576",
        "tgn:1000001",
        "tgn:2001023",
        "tgn:7012149",
        "tgn:7007521",
        "tgn:7029392"
    ],
    "tgn:id":2145576,
    "tgn:name":"Baldwin Island",
    "tgn:placetype":[
        "aat:300008791"
    ]
},
  "bbox": [],
  "geometry": {"coordinates":[-92.4833,44.55],"type":"Point"}
}