{
  "id": 7145612,
  "type": "Feature",
  "properties": {
    "tgn:hierarchy":[
        "tgn:7145612",
        "tgn:1000003",
        "tgn:7003676",
        "tgn:7000084",
        "tgn:7029392"
    ],
    "tgn:id":7145612,
    "tgn:name":"Klein Vollb\u00fcttel",
    "tgn:placetype":[
        "aat:300008347"
    ]
},
  "bbox": [],
  "geometry": {"coordinates":[10.483333,52.416667],"type":"Point"}
}