{
  "id": 7451023,
  "type": "Feature",
  "properties": {
    "tgn:hierarchy":[
        "tgn:7451023",
        "tgn:7002444",
        "tgn:1000003",
        "tgn:7008082",
        "tgn:7008591",
        "tgn:7029392"
    ],
    "tgn:id":7451023,
    "tgn:name:en":"Garry Loch",
    "tgn:placetype":[
        "aat:300008680"
    ]
},
  "bbox": [],
  "geometry": {"coordinates":[-4.916667,57.083333],"type":"Point"}
}