<<<<<<< HEAD
{
  "id": 7358100,
  "type": "Feature",
  "properties": {
    "tgn:hierarchy":[
        "tgn:7358100",
        "tgn:7005587",
        "tgn:1000001",
        "tgn:7005560",
        "tgn:7029392"
    ],
    "tgn:id":7358100,
    "tgn:name":"Cuxhuac\u00e1n",
    "tgn:placetype":[
        "aat:300008347"
    ]
},
  "bbox": [],
  "geometry": {"coordinates":[-98.8,20.966667],"type":"Point"}
}
=======
{"geometry":{"type":"Point","coordinates":[-98.800000,20.966667]},"type":"Feature","properties":{"hierarchy":["tgn:7358100","tgn:7005587","tgn:1000001","tgn:7005560","tgn:7029392"],"placetype":["aat:300008347"],"id":7358100,"name:xx":"Cuxhuac\u00e1n"}}
>>>>>>> 03f74aca74312dbeaf24d7e61306dd6a786dc3d0
