{
  "id": 7594401,
  "type": "Feature",
  "properties": {
    "tgn:hierarchy":[
        "tgn:7594401",
        "tgn:7002445",
        "tgn:1000003",
        "tgn:7012077",
        "tgn:7008591",
        "tgn:7029392"
    ],
    "tgn:id":7594401,
    "tgn:name":"Clovelly Dykes",
    "tgn:placetype":[
        "aat:300008347",
        "aat:300000810",
        "aat:300167671",
        "aat:300006911",
        "aat:300008020",
        "aat:300019279"
    ]
},
  "bbox": [],
  "geometry": {"coordinates":[-4.4072,50.9855],"type":"Point"}
}