{
  "id": 2486049,
  "type": "Feature",
  "properties": {
    "tgn:hierarchy":[
        "tgn:2486049",
        "tgn:1000001",
        "tgn:7012149",
        "tgn:2002250",
        "tgn:7007920",
        "tgn:7029392"
    ],
    "tgn:id":2486049,
    "tgn:name":"Lead Pencil Spring",
    "tgn:placetype":[
        "aat:300008697"
    ]
},
  "bbox": [],
  "geometry": {"coordinates":[-117.9667,48.9667],"type":"Point"}
}