{
  "id": 2491485,
  "type": "Feature",
  "properties": {
    "tgn:hierarchy":[
        "tgn:2491485",
        "tgn:1000001",
        "tgn:7012149",
        "tgn:2000970",
        "tgn:7007520",
        "tgn:7029392"
    ],
    "tgn:id":2491485,
    "tgn:name":"Maple Lake",
    "tgn:placetype":[
        "aat:300008680"
    ]
},
  "bbox": [],
  "geometry": {"coordinates":[-85.9833,44.15],"type":"Point"}
}