<<<<<<< HEAD
{
  "id": 7175438,
  "type": "Feature",
  "properties": {
    "tgn:hierarchy":[
        "tgn:7175438",
        "tgn:1000003",
        "tgn:7003677",
        "tgn:7000084",
        "tgn:7029392"
    ],
    "tgn:id":7175438,
    "tgn:name":"Gro\u00dfes Venn",
    "tgn:placetype":[
        "aat:300055621"
    ]
},
  "bbox": [],
  "geometry": {"coordinates":[8.1,52.033333],"type":"Point"}
}
=======
{"geometry":{"type":"Point","coordinates":[8.100000,52.033333]},"type":"Feature","properties":{"hierarchy":["tgn:7175438","tgn:1000003","tgn:7003677","tgn:7000084","tgn:7029392"],"placetype":["aat:300055621"],"id":7175438,"name:xx":"Gro\u00dfes Venn"}}
>>>>>>> 03f74aca74312dbeaf24d7e61306dd6a786dc3d0
