<<<<<<< HEAD
{
  "id": 7352882,
  "type": "Feature",
  "properties": {
    "tgn:hierarchy":[
        "tgn:7352882",
        "tgn:7005586",
        "tgn:1000001",
        "tgn:7005560",
        "tgn:7029392"
    ],
    "tgn:id":7352882,
    "tgn:name":"Atotoac, R\u00edo",
    "tgn:placetype":[
        "aat:300008699"
    ]
},
  "bbox": [],
  "geometry": {"coordinates":[-103.65,22.55],"type":"Point"}
}
=======
{"geometry":{"type":"Point","coordinates":[-103.650000,22.550000]},"type":"Feature","properties":{"hierarchy":["tgn:7352882","tgn:7005586","tgn:1000001","tgn:7005560","tgn:7029392"],"placetype":["aat:300008699"],"id":7352882,"name:xx":"Atotoac, R\u00edo"}}
>>>>>>> 03f74aca74312dbeaf24d7e61306dd6a786dc3d0
