{
  "id": 7540463,
  "type": "Feature",
  "properties": {
    "tgn:hierarchy":[
        "tgn:7540463",
        "tgn:7001242",
        "tgn:7016833",
        "tgn:7000124",
        "tgn:7029392"
    ],
    "tgn:id":7540463,
    "tgn:name:en":"Naj' at Taw\u0101dir",
    "tgn:placetype":[
        "aat:300008347"
    ]
},
  "bbox": [],
  "geometry": {"coordinates":[31.916667,26.266667],"type":"Point"}
}