{
  "id": 7285739,
  "type": "Feature",
  "properties": {
    "tgn:hierarchy":[
        "tgn:7285739",
        "tgn:1001699",
        "tgn:1000049",
        "tgn:1000002",
        "tgn:7029392"
    ],
    "tgn:id":7285739,
    "tgn:name":"Pucatrihue, Punta",
    "tgn:placetype":[
        "aat:300386846"
    ]
},
  "bbox": [],
  "geometry": {"coordinates":[-73.783333,-40.433333],"type":"Point"}
}