{
  "id": 7010110,
  "type": "Feature",
  "properties": {
    "tgn:hierarchy":[
        "tgn:7010110",
        "tgn:1003505",
        "tgn:1000003",
        "tgn:7002993",
        "tgn:1000080",
        "tgn:7029392"
    ],
    "tgn:id":7010110,
    "tgn:name":"Castello di Miramare",
    "tgn:placetype":[
        "aat:300004792",
        "aat:300006891"
    ]
},
  "bbox": [],
  "geometry": {"coordinates":[13.712,45.703],"type":"Point"}
}