{
  "id": 1078320,
  "type": "Feature",
  "properties": {
    "tgn:hierarchy":[
        "tgn:1078320",
        "tgn:1001150",
        "tgn:1000004",
        "tgn:1000116",
        "tgn:7029392"
    ],
    "tgn:id":1078320,
    "tgn:name":"Pasarbantal",
    "tgn:placetype":[
        "aat:300008347"
    ]
},
  "bbox": [],
  "geometry": {"coordinates":[101.3333,-2.6833],"type":"Point"}
}