{
  "id": 1008316,
  "type": "Feature",
  "properties": {
    "tgn:hierarchy":[
        "tgn:1008316",
        "tgn:7006450",
        "tgn:2000069",
        "tgn:1000001",
        "tgn:7012149",
        "tgn:7029392"
    ],
    "tgn:id":1008316,
    "tgn:name":"Nelson Island",
    "tgn:placetype":[
        "aat:300008791"
    ]
},
  "bbox": [],
  "geometry": {"coordinates":[-164.75,60.6333],"type":"Point"}
}