<<<<<<< HEAD
{
  "id": 7023544,
  "type": "Feature",
  "properties": {
    "tgn:hierarchy":[
        "tgn:7023544",
        "tgn:1000001",
        "tgn:7016172",
        "tgn:7012149",
        "tgn:7029392"
    ],
    "tgn:id":7023544,
    "tgn:name":"Surrounded Hill",
    "tgn:placetype":[
        "aat:300008798"
    ]
},
  "bbox": [],
  "geometry": {"coordinates":[-91.35,35.6],"type":"Point"}
}
=======
{"geometry":{"type":"Point","coordinates":[-91.350000,35.600000]},"type":"Feature","properties":{"hierarchy":["tgn:7023544","tgn:1000001","tgn:7016172","tgn:7012149","tgn:7029392"],"placetype":["aat:300008798"],"id":7023544,"name:xx":"Surrounded Hill"}}
>>>>>>> 03f74aca74312dbeaf24d7e61306dd6a786dc3d0
