{
  "id": 7591784,
  "type": "Feature",
  "properties": {
    "tgn:hierarchy":[
        "tgn:7591784",
        "tgn:1000004",
        "tgn:7000198",
        "tgn:7000799",
        "tgn:7029392"
    ],
    "tgn:id":7591784,
    "tgn:name:en":"B\u0101ble\u0101na",
    "tgn:placetype":[
        "aat:300008347"
    ]
},
  "bbox": [],
  "geometry": {"coordinates":[74.856944,32.668056],"type":"Point"}
}