<<<<<<< HEAD
{
  "id": 7245091,
  "type": "Feature",
  "properties": {
    "tgn:hierarchy":[
        "tgn:7245091",
        "tgn:7003457",
        "tgn:1000003",
        "tgn:1000063",
        "tgn:7018236",
        "tgn:7029392"
    ],
    "tgn:id":7245091,
    "tgn:name":"Bambrugge",
    "tgn:placetype":[
        "aat:300008347"
    ]
},
  "bbox": [],
  "geometry": {"coordinates":[3.929929,50.921154],"type":"Point"}
}
=======
{"geometry":{"type":"Point","coordinates":[3.929929,50.921154]},"type":"Feature","properties":{"hierarchy":["tgn:7245091","tgn:7003457","tgn:1000003","tgn:1000063","tgn:7018236","tgn:7029392"],"placetype":["aat:300008347"],"id":7245091,"name:xx":"Bambrugge"}}
>>>>>>> 03f74aca74312dbeaf24d7e61306dd6a786dc3d0
