{
  "id": 2243241,
  "type": "Feature",
  "properties": {
    "tgn:hierarchy":[
        "tgn:2243241",
        "tgn:2001729",
        "tgn:1000001",
        "tgn:7012149",
        "tgn:7007712",
        "tgn:7029392"
    ],
    "tgn:id":2243241,
    "tgn:name":"Clear Pond",
    "tgn:placetype":[
        "aat:300008347"
    ]
},
  "bbox": [],
  "geometry": {"coordinates":[-81.0167,33.1833],"type":"Point"}
}