{
  "id": 1061257,
  "type": "Feature",
  "properties": {
    "tgn:hierarchy":[
        "tgn:1061257",
        "tgn:1000004",
        "tgn:7011589",
        "tgn:7018214",
        "tgn:7002435",
        "tgn:7029392"
    ],
    "tgn:id":1061257,
    "tgn:name":"Vyuny",
    "tgn:placetype":[
        "aat:300008347"
    ]
},
  "bbox": [],
  "geometry": {"coordinates":[82.9667,55.5167],"type":"Point"}
}