{
  "id": 2750217,
  "type": "Feature",
  "properties": {
    "tgn:hierarchy":[
        "tgn:2750217",
        "tgn:1000001",
        "tgn:1002328",
        "tgn:7012149",
        "tgn:7007568",
        "tgn:7029392"
    ],
    "tgn:id":2750217,
    "tgn:name":"Walton Mountain",
    "tgn:placetype":[
        "aat:300008798"
    ]
},
  "bbox": [],
  "geometry": {"coordinates":[-75.1833,42.15],"type":"Point"}
}