{
  "id": 2731667,
  "type": "Feature",
  "properties": {
    "tgn:hierarchy":[
        "tgn:2731667",
        "tgn:1000001",
        "tgn:7016172",
        "tgn:7012149",
        "tgn:7029392"
    ],
    "tgn:id":2731667,
    "tgn:name":"Tulip Creek",
    "tgn:placetype":[
        "aat:300008706"
    ]
},
  "bbox": [],
  "geometry": {"coordinates":[-92.7333,33.8833],"type":"Point"}
}