{
  "id": 2332579,
  "type": "Feature",
  "properties": {
    "tgn:hierarchy":[
        "tgn:2332579",
        "tgn:1000001",
        "tgn:7012149",
        "tgn:1002545",
        "tgn:7007157",
        "tgn:7029392"
    ],
    "tgn:id":2332579,
    "tgn:name":"Florida Drain",
    "tgn:placetype":[
        "aat:300006075"
    ]
},
  "bbox": [],
  "geometry": {"coordinates":[-119.45,35.35],"type":"Point"}
}