<<<<<<< HEAD
{
  "id": 2250213,
  "type": "Feature",
  "properties": {
    "tgn:hierarchy":[
        "tgn:2250213",
        "tgn:1000001",
        "tgn:7012149",
        "tgn:2001849",
        "tgn:7007825",
        "tgn:7029392"
    ],
    "tgn:id":2250213,
    "tgn:name":"Collins Mill",
    "tgn:placetype":[
        "aat:300008347"
    ]
},
  "bbox": [],
  "geometry": {"coordinates":[-83.75,36.4167],"type":"Point"}
}
=======
{"geometry":{"type":"Point","coordinates":[-83.750000,36.416700]},"type":"Feature","properties":{"hierarchy":["tgn:2250213","tgn:1000001","tgn:7012149","tgn:2001849","tgn:7007825","tgn:7029392"],"placetype":["aat:300008347"],"id":2250213,"name:xx":"Collins Mill"}}
>>>>>>> 03f74aca74312dbeaf24d7e61306dd6a786dc3d0
