{
  "id": 2010231,
  "type": "Feature",
  "properties": {
    "tgn:hierarchy":[
        "tgn:2010231",
        "tgn:1000001",
        "tgn:7012149",
        "tgn:2000182",
        "tgn:7007157",
        "tgn:7029392"
    ],
    "tgn:id":2010231,
    "tgn:name":"Bertram",
    "tgn:placetype":[
        "aat:300387016"
    ]
},
  "bbox": [],
  "geometry": {"coordinates":[-115.7667,33.3667],"type":"Point"}
}