<<<<<<< HEAD
{
  "id": 2330062,
  "type": "Feature",
  "properties": {
    "tgn:hierarchy":[
        "tgn:2330062",
        "tgn:1000001",
        "tgn:7012149",
        "tgn:2002275",
        "tgn:7013961",
        "tgn:7029392"
    ],
    "tgn:id":2330062,
    "tgn:name":"Flaggy Meadow Run",
    "tgn:placetype":[
        "aat:300008699"
    ]
},
  "bbox": [],
  "geometry": {"coordinates":[-80.35,39.4833],"type":"Point"}
}
=======
{"geometry":{"type":"Point","coordinates":[-80.350000,39.483300]},"type":"Feature","properties":{"hierarchy":["tgn:2330062","tgn:1000001","tgn:7012149","tgn:2002275","tgn:7013961","tgn:7029392"],"placetype":["aat:300008699"],"id":2330062,"name:xx":"Flaggy Meadow Run"}}
>>>>>>> 03f74aca74312dbeaf24d7e61306dd6a786dc3d0
