{
  "id": 2636472,
  "type": "Feature",
  "properties": {
    "tgn:hierarchy":[
        "tgn:2636472",
        "tgn:1000001",
        "tgn:7012149",
        "tgn:7007520",
        "tgn:7029392"
    ],
    "tgn:id":2636472,
    "tgn:name":"Saganing Creek",
    "tgn:placetype":[
        "aat:300008706"
    ]
},
  "bbox": [],
  "geometry": {"coordinates":[-84.1667,43.9167],"type":"Point"}
}