{
  "id": 1012980,
  "type": "Feature",
  "properties": {
    "tgn:hierarchy":[
        "tgn:1012980",
        "tgn:7002445",
        "tgn:1003666",
        "tgn:1000003",
        "tgn:7029504",
        "tgn:7008591",
        "tgn:7029392"
    ],
    "tgn:id":1012980,
    "tgn:name:en":"Wirral",
    "tgn:placetype":[
        "aat:300008804"
    ]
},
  "bbox": [],
  "geometry": {"coordinates":[-3.083333,53.333333],"type":"Point"}
}