{
  "id": 7258112,
  "type": "Feature",
  "properties": {
    "tgn:concordances":{
        "gn:id":"2760055"
    },
    "tgn:hierarchy":[
        "tgn:7258112",
        "tgn:1000003",
        "tgn:7003632",
        "tgn:7016845",
        "tgn:7029392"
    ],
    "tgn:id":7258112,
    "tgn:name:nl":"Abtswoude",
    "tgn:placetype":[
        "aat:300008347"
    ]
},
  "bbox": [],
  "geometry": {"coordinates":[4.35,51.983333],"type":"Point"}
}