{
  "id": 1068392,
  "type": "Feature",
  "properties": {
    "tgn:hierarchy":[
        "tgn:1068392",
        "tgn:1000004",
        "tgn:7002081",
        "tgn:1000111",
        "tgn:7029392"
    ],
    "tgn:id":1068392,
    "tgn:name":"Guanhu",
    "tgn:placetype":[
        "aat:300008347"
    ]
},
  "bbox": [],
  "geometry": {"coordinates":[117.9833,34.4167],"type":"Point"}
}