<<<<<<< HEAD
{
  "id": 2258767,
  "type": "Feature",
  "properties": {
    "tgn:hierarchy":[
        "tgn:2258767",
        "tgn:1000001",
        "tgn:7012149",
        "tgn:1002604",
        "tgn:7007568",
        "tgn:7029392"
    ],
    "tgn:id":2258767,
    "tgn:name":"Cottonwood Cove",
    "tgn:placetype":[
        "aat:300008347"
    ]
},
  "bbox": [],
  "geometry": {"coordinates":[-77.7167,42.75],"type":"Point"}
}
=======
{"geometry":{"type":"Point","coordinates":[-77.716700,42.750000]},"type":"Feature","properties":{"hierarchy":["tgn:2258767","tgn:1000001","tgn:7012149","tgn:1002604","tgn:7007568","tgn:7029392"],"placetype":["aat:300008347"],"id":2258767,"name:xx":"Cottonwood Cove"}}
>>>>>>> 03f74aca74312dbeaf24d7e61306dd6a786dc3d0
