{
  "id": 7184051,
  "type": "Feature",
  "properties": {
    "tgn:hierarchy":[
        "tgn:7184051",
        "tgn:1000003",
        "tgn:7003689",
        "tgn:7000084",
        "tgn:7029392"
    ],
    "tgn:id":7184051,
    "tgn:name":"G\u00f6ttengr\u00fcn",
    "tgn:placetype":[
        "aat:300008347"
    ]
},
  "bbox": [],
  "geometry": {"coordinates":[11.833333,50.45],"type":"Point"}
}