{
  "id": 7479138,
  "type": "Feature",
  "properties": {
    "tgn:hierarchy":[
        "tgn:7479138",
        "tgn:1000004",
        "tgn:7490934",
        "tgn:1000141",
        "tgn:7029392"
    ],
    "tgn:id":7479138,
    "tgn:name":"Wangliao",
    "tgn:placetype":[
        "aat:300008347"
    ]
},
  "bbox": [],
  "geometry": {"coordinates":[120.370462,23.163256],"type":"Point"}
}