{
  "id": 7069015,
  "type": "Feature",
  "properties": {
    "tgn:hierarchy":[
        "tgn:7069015",
        "tgn:1000003",
        "tgn:7003688",
        "tgn:7000084",
        "tgn:7029392"
    ],
    "tgn:id":7069015,
    "tgn:name":"Steenodde",
    "tgn:placetype":[
        "aat:300008347"
    ]
},
  "bbox": [],
  "geometry": {"coordinates":[8.366667,54.633333],"type":"Point"}
}