{
  "id": 7461664,
  "type": "Feature",
  "properties": {
    "tgn:hierarchy":[
        "tgn:7461664",
        "tgn:7002444",
        "tgn:1000003",
        "tgn:7008082",
        "tgn:7008591",
        "tgn:7029392"
    ],
    "tgn:id":7461664,
    "tgn:name:en":"Lagain, Loch an",
    "tgn:placetype":[
        "aat:300008680"
    ]
},
  "bbox": [],
  "geometry": {"coordinates":[-4.266667,57.933333],"type":"Point"}
}