{
  "id": 2167395,
  "type": "Feature",
  "properties": {
    "tgn:hierarchy":[
        "tgn:2167395",
        "tgn:1000001",
        "tgn:2000953",
        "tgn:7012149",
        "tgn:7007520",
        "tgn:7029392"
    ],
    "tgn:id":2167395,
    "tgn:name":"Big Cranberry Lake",
    "tgn:placetype":[
        "aat:300008680"
    ]
},
  "bbox": [],
  "geometry": {"coordinates":[-85.0333,43.8667],"type":"Point"}
}