{
  "id": 2399547,
  "type": "Feature",
  "properties": {
    "tgn:hierarchy":[
        "tgn:2399547",
        "tgn:1000001",
        "tgn:1003023",
        "tgn:7012149",
        "tgn:7007516",
        "tgn:7029392"
    ],
    "tgn:id":2399547,
    "tgn:name":"Horner Gut",
    "tgn:placetype":[
        "aat:300008699"
    ]
},
  "bbox": [],
  "geometry": {"coordinates":[-75.8333,38.3333],"type":"Point"}
}