{
  "id": 7305736,
  "type": "Feature",
  "properties": {
    "tgn:hierarchy":[
        "tgn:7305736",
        "tgn:7002829",
        "tgn:1000003",
        "tgn:7002786",
        "tgn:1000095",
        "tgn:7029392"
    ],
    "tgn:id":7305736,
    "tgn:name":"Mazaira",
    "tgn:placetype":[
        "aat:300008347"
    ]
},
  "bbox": [],
  "geometry": {"coordinates":[-7.066667,42.966667],"type":"Point"}
}