{
  "id": 1083353,
  "type": "Feature",
  "properties": {
    "tgn:hierarchy":[
        "tgn:1083353",
        "tgn:7002460",
        "tgn:1000004",
        "tgn:1000133",
        "tgn:7029392"
    ],
    "tgn:id":1083353,
    "tgn:name":"B\u0101l\u0101kot",
    "tgn:placetype":[
        "aat:300008347"
    ]
},
  "bbox": [],
  "geometry": {"coordinates":[73.35,34.55],"type":"Point"}
}