{
  "id": 2496435,
  "type": "Feature",
  "properties": {
    "tgn:hierarchy":[
        "tgn:2496435",
        "tgn:7002659",
        "tgn:1000001",
        "tgn:7012149",
        "tgn:2000050",
        "tgn:7029392"
    ],
    "tgn:id":2496435,
    "tgn:name":"Mathews Slough",
    "tgn:placetype":[
        "aat:300008699"
    ]
},
  "bbox": [],
  "geometry": {"coordinates":[-86.0667,32.2667],"type":"Point"}
}