{
  "id": 5001611,
  "type": "Feature",
  "properties": {
    "tgn:hierarchy":[
        "tgn:5001611",
        "tgn:1000003",
        "tgn:7002883",
        "tgn:1000070",
        "tgn:7029392"
    ],
    "tgn:id":5001611,
    "tgn:name":"Bransles",
    "tgn:placetype":[
        "aat:300008347"
    ]
},
  "bbox": [],
  "geometry": {"coordinates":[2.8333,48.15],"type":"Point"}
}