{
  "id": 2715168,
  "type": "Feature",
  "properties": {
    "tgn:hierarchy":[
        "tgn:2715168",
        "tgn:1000001",
        "tgn:2000463",
        "tgn:7012149",
        "tgn:7007250",
        "tgn:7029392"
    ],
    "tgn:id":2715168,
    "tgn:name":"Tepee Circles",
    "tgn:placetype":[
        "aat:300000390"
    ]
},
  "bbox": [],
  "geometry": {"coordinates":[-113.5167,43.4333],"type":"Point"}
}