{
  "id": 7414404,
  "type": "Feature",
  "properties": {
    "tgn:hierarchy":[
        "tgn:7414404",
        "tgn:7005580",
        "tgn:1000001",
        "tgn:7005560",
        "tgn:7029392"
    ],
    "tgn:id":7414404,
    "tgn:name":"Yomono",
    "tgn:placetype":[
        "aat:300008347"
    ]
},
  "bbox": [],
  "geometry": {"coordinates":[-93.438889,17.183333],"type":"Point"}
}