<<<<<<< HEAD
{
  "id": 7055606,
  "type": "Feature",
  "properties": {
    "tgn:hierarchy":[
        "tgn:7055606",
        "tgn:1003460",
        "tgn:1000003",
        "tgn:7009760",
        "tgn:1000080",
        "tgn:7029392"
    ],
    "tgn:id":7055606,
    "tgn:name":"Orientina, Fosso dell'",
    "tgn:placetype":[
        "aat:300008699"
    ]
},
  "bbox": [],
  "geometry": {"coordinates":[11.666667,42.633333],"type":"Point"}
}
=======
{"geometry":{"type":"Point","coordinates":[11.666667,42.633333]},"type":"Feature","properties":{"hierarchy":["tgn:7055606","tgn:1003460","tgn:1000003","tgn:7009760","tgn:1000080","tgn:7029392"],"placetype":["aat:300008699"],"id":7055606,"name:xx":"Orientina, Fosso dell'"}}
>>>>>>> 03f74aca74312dbeaf24d7e61306dd6a786dc3d0
