{
  "id": 7071936,
  "type": "Feature",
  "properties": {
    "tgn:hierarchy":[
        "tgn:7071936",
        "tgn:1000003",
        "tgn:7003676",
        "tgn:7000084",
        "tgn:7029392"
    ],
    "tgn:id":7071936,
    "tgn:name":"Thedafeld",
    "tgn:placetype":[
        "aat:300000206"
    ]
},
  "bbox": [],
  "geometry": {"coordinates":[7.933333,53.683333],"type":"Point"}
}