{
  "id": 2732020,
  "type": "Feature",
  "properties": {
    "tgn:hierarchy":[
        "tgn:2732020",
        "tgn:1000001",
        "tgn:7012149",
        "tgn:1002742",
        "tgn:7007920",
        "tgn:7029392"
    ],
    "tgn:id":2732020,
    "tgn:name":"Tunk Valley",
    "tgn:placetype":[
        "aat:300008761"
    ]
},
  "bbox": [],
  "geometry": {"coordinates":[-119.3167,48.5167],"type":"Point"}
}