{
  "id": 1046486,
  "type": "Feature",
  "properties": {
    "tgn:hierarchy":[
        "tgn:1046486",
        "tgn:7005126",
        "tgn:1000003",
        "tgn:7003120",
        "tgn:1000080",
        "tgn:7029392"
    ],
    "tgn:id":1046486,
    "tgn:name":"San Damiano Macra",
    "tgn:placetype":[
        "aat:300008347"
    ]
},
  "bbox": [],
  "geometry": {"coordinates":[7.266667,44.483333],"type":"Point"}
}