<<<<<<< HEAD
{
  "id": 7352180,
  "type": "Feature",
  "properties": {
    "tgn:hierarchy":[
        "tgn:7352180",
        "tgn:1001853",
        "tgn:1000001",
        "tgn:7005560",
        "tgn:7029392"
    ],
    "tgn:id":7352180,
    "tgn:name":"Astillero, Puerto del",
    "tgn:placetype":[
        "aat:300259572"
    ]
},
  "bbox": [],
  "geometry": {"coordinates":[-103.233333,26.816667],"type":"Point"}
}
=======
{"geometry":{"type":"Point","coordinates":[-103.233333,26.816667]},"type":"Feature","properties":{"hierarchy":["tgn:7352180","tgn:1001853","tgn:1000001","tgn:7005560","tgn:7029392"],"placetype":["aat:300259572"],"id":7352180,"name:xx":"Astillero, Puerto del"}}
>>>>>>> 03f74aca74312dbeaf24d7e61306dd6a786dc3d0
