{
  "id": 7524081,
  "type": "Feature",
  "properties": {
    "tgn:hierarchy":[
        "tgn:7524081",
        "tgn:7001242",
        "tgn:7016833",
        "tgn:7001336",
        "tgn:7029392"
    ],
    "tgn:id":7524081,
    "tgn:name:en":"B\u00eer, W\u00e2di el-",
    "tgn:placetype":[
        "aat:300379998"
    ]
},
  "bbox": [],
  "geometry": {"coordinates":[32.800982,29.754103],"type":"Point"}
}