<<<<<<< HEAD
{
  "id": 2403498,
  "type": "Feature",
  "properties": {
    "tgn:hierarchy":[
        "tgn:2403498",
        "tgn:1000001",
        "tgn:7016172",
        "tgn:7012149",
        "tgn:2000161",
        "tgn:7029392"
    ],
    "tgn:id":2403498,
    "tgn:name":"Howard",
    "tgn:placetype":[
        "aat:300008347"
    ]
},
  "bbox": [],
  "geometry": {"coordinates":[-94.4333,34.7],"type":"Point"}
}
=======
{"geometry":{"type":"Point","coordinates":[-94.433300,34.700000]},"type":"Feature","properties":{"hierarchy":["tgn:2403498","tgn:1000001","tgn:7016172","tgn:7012149","tgn:2000161","tgn:7029392"],"placetype":["aat:300008347"],"id":2403498,"name:xx":"Howard"}}
>>>>>>> 03f74aca74312dbeaf24d7e61306dd6a786dc3d0
