{
  "id": 1001027,
  "type": "Feature",
  "properties": {
    "tgn:hierarchy":[
        "tgn:1001027",
        "tgn:7001242",
        "tgn:1000155",
        "tgn:7029392"
    ],
    "tgn:id":1001027,
    "tgn:name":"Sangha-Mbaere",
    "tgn:placetype":[
        "aat:300387064",
        "aat:300235099"
    ]
},
  "bbox": [],
  "geometry": {"coordinates":[16.3333,3.9167],"type":"Point"}
}