{
  "id": 7231806,
  "type": "Feature",
  "properties": {
    "tgn:hierarchy":[
        "tgn:7231806",
        "tgn:7011270",
        "tgn:7002674",
        "tgn:1000003",
        "tgn:1000074",
        "tgn:7029392"
    ],
    "tgn:id":7231806,
    "tgn:name":"K\u00e1lamos, \u00c1kra",
    "tgn:placetype":[
        "aat:300008850"
    ]
},
  "bbox": [],
  "geometry": {"coordinates":[25.866667,36.366667],"type":"Point"}
}