<<<<<<< HEAD
{
  "id": 7172653,
  "type": "Feature",
  "properties": {
    "tgn:hierarchy":[
        "tgn:7172653",
        "tgn:7003669",
        "tgn:1000003",
        "tgn:7000084",
        "tgn:7029392"
    ],
    "tgn:id":7172653,
    "tgn:name":"Hinter Ro\u00dfboden",
    "tgn:placetype":[
        "aat:300000206"
    ]
},
  "bbox": [],
  "geometry": {"coordinates":[13.016667,47.683333],"type":"Point"}
}
=======
{"geometry":{"type":"Point","coordinates":[13.016667,47.683333]},"type":"Feature","properties":{"hierarchy":["tgn:7172653","tgn:7003669","tgn:1000003","tgn:7000084","tgn:7029392"],"placetype":["aat:300000206"],"id":7172653,"name:xx":"Hinter Ro\u00dfboden"}}
>>>>>>> 03f74aca74312dbeaf24d7e61306dd6a786dc3d0
