{
  "id": 2467775,
  "type": "Feature",
  "properties": {
    "tgn:hierarchy":[
        "tgn:2467775",
        "tgn:1000001",
        "tgn:7012149",
        "tgn:1002595",
        "tgn:7007826",
        "tgn:7029392"
    ],
    "tgn:id":2467775,
    "tgn:name":"Long John Creek",
    "tgn:placetype":[
        "aat:300008706"
    ]
},
  "bbox": [],
  "geometry": {"coordinates":[-94.9167,30.1333],"type":"Point"}
}