{
  "id": 7100421,
  "type": "Feature",
  "properties": {
    "tgn:hierarchy":[
        "tgn:7100421",
        "tgn:1000003",
        "tgn:7003677",
        "tgn:7000084",
        "tgn:7029392"
    ],
    "tgn:id":7100421,
    "tgn:name":"Rotbach",
    "tgn:placetype":[
        "aat:300008699"
    ]
},
  "bbox": [],
  "geometry": {"coordinates":[6.783333,50.816667],"type":"Point"}
}