{
  "id": 2306194,
  "type": "Feature",
  "properties": {
    "tgn:hierarchy":[
        "tgn:2306194",
        "tgn:1000001",
        "tgn:7012149",
        "tgn:7007524",
        "tgn:7029392"
    ],
    "tgn:id":2306194,
    "tgn:name":"East Fork Blacktail Deer Creek",
    "tgn:placetype":[
        "aat:300008706"
    ]
},
  "bbox": [],
  "geometry": {"coordinates":[-112.1167,44.85],"type":"Point"}
}