{
  "id": 7375066,
  "type": "Feature",
  "properties": {
    "tgn:hierarchy":[
        "tgn:7375066",
        "tgn:1000001",
        "tgn:7005595",
        "tgn:7005560",
        "tgn:7029392"
    ],
    "tgn:id":7375066,
    "tgn:name":"Lechuguilla, Isla de la",
    "tgn:placetype":[
        "aat:300008791"
    ]
},
  "bbox": [],
  "geometry": {"coordinates":[-109.383333,25.716667],"type":"Point"}
}