<<<<<<< HEAD
{
  "id": 7375066,
  "type": "Feature",
  "properties": {
    "tgn:hierarchy":[
        "tgn:7375066",
        "tgn:1000001",
        "tgn:7005595",
        "tgn:7005560",
        "tgn:7029392"
    ],
    "tgn:id":7375066,
    "tgn:name":"Lechuguilla, Isla de la",
    "tgn:placetype":[
        "aat:300008791"
    ]
},
  "bbox": [],
  "geometry": {"coordinates":[-109.383333,25.716667],"type":"Point"}
}
=======
{"geometry":{"type":"Point","coordinates":[-109.383333,25.716667]},"type":"Feature","properties":{"hierarchy":["tgn:7375066","tgn:1000001","tgn:7005595","tgn:7005560","tgn:7029392"],"placetype":["aat:300008791"],"id":7375066,"name:xx":"Lechuguilla, Isla de la"}}
>>>>>>> 03f74aca74312dbeaf24d7e61306dd6a786dc3d0
