<<<<<<< HEAD
{
  "id": 7488865,
  "type": "Feature",
  "properties": {
    "tgn:hierarchy":[
        "tgn:7488865",
        "tgn:7001004",
        "tgn:1000004",
        "tgn:1000141",
        "tgn:7029392"
    ],
    "tgn:id":7488865,
    "tgn:name":"Longshui Li",
    "tgn:placetype":[
        "aat:300387173"
    ]
},
  "bbox": [],
  "geometry": {"coordinates":[120.286341,22.65307],"type":"Point"}
}
=======
{"geometry":{"type":"Point","coordinates":[120.286341,22.653070]},"type":"Feature","properties":{"hierarchy":["tgn:7488865","tgn:7001004","tgn:1000004","tgn:1000141","tgn:7029392"],"placetype":["aat:300387173"],"id":7488865,"name:xx":"Longshui Li"}}
>>>>>>> 03f74aca74312dbeaf24d7e61306dd6a786dc3d0
