{
  "id": 2417030,
  "type": "Feature",
  "properties": {
    "tgn:hierarchy":[
        "tgn:2417030",
        "tgn:7002659",
        "tgn:1000001",
        "tgn:7012149",
        "tgn:7029392"
    ],
    "tgn:id":2417030,
    "tgn:name":"Jackie Branch",
    "tgn:placetype":[
        "aat:300008699"
    ]
},
  "bbox": [],
  "geometry": {"coordinates":[-85.9167,34.5333],"type":"Point"}
}