{
  "id": 7226024,
  "type": "Feature",
  "properties": {
    "tgn:hierarchy":[
        "tgn:7226024",
        "tgn:7011171",
        "tgn:7001395",
        "tgn:1000003",
        "tgn:1000074",
        "tgn:7029392"
    ],
    "tgn:id":7226024,
    "tgn:name":"Mourter\u00f3n",
    "tgn:placetype":[
        "aat:300008347"
    ]
},
  "bbox": [],
  "geometry": {"coordinates":[23.933333,39.216667],"type":"Point"}
}