{
  "id": 2060711,
  "type": "Feature",
  "properties": {
    "tgn:hierarchy":[
        "tgn:2060711",
        "tgn:1000001",
        "tgn:7012149",
        "tgn:2001223",
        "tgn:7007523",
        "tgn:7029392"
    ],
    "tgn:id":2060711,
    "tgn:name":"Tipton Ford",
    "tgn:placetype":[
        "aat:300008347",
        "aat:300387210"
    ]
},
  "bbox": [],
  "geometry": {"coordinates":[-94.4167,36.9667],"type":"Point"}
}