{
  "id": 2262853,
  "type": "Feature",
  "properties": {
    "tgn:hierarchy":[
        "tgn:2262853",
        "tgn:1000001",
        "tgn:2001267",
        "tgn:7012149",
        "tgn:7007524",
        "tgn:7029392"
    ],
    "tgn:id":2262853,
    "tgn:name":"Cowboy Creek",
    "tgn:placetype":[
        "aat:300008706"
    ]
},
  "bbox": [],
  "geometry": {"coordinates":[-110.35,47.4667],"type":"Point"}
}