{
  "id": 2689574,
  "type": "Feature",
  "properties": {
    "tgn:hierarchy":[
        "tgn:2689574",
        "tgn:1000001",
        "tgn:7012149",
        "tgn:7007158",
        "tgn:2000245",
        "tgn:7029392"
    ],
    "tgn:id":2689574,
    "tgn:name":"Squaw Mountain",
    "tgn:placetype":[
        "aat:300008798"
    ]
},
  "bbox": [],
  "geometry": {"coordinates":[-107.2167,40.9667],"type":"Point"}
}