{
  "id": 2037600,
  "type": "Feature",
  "properties": {
    "tgn:hierarchy":[
        "tgn:2037600",
        "tgn:1000001",
        "tgn:7012149",
        "tgn:2000797",
        "tgn:7007255",
        "tgn:7029392"
    ],
    "tgn:id":2037600,
    "tgn:name":"Bardo",
    "tgn:placetype":[
        "aat:300008347"
    ]
},
  "bbox": [],
  "geometry": {"coordinates":[-83.3333,36.75],"type":"Point"}
}