{
  "id": 2427697,
  "type": "Feature",
  "properties": {
    "tgn:hierarchy":[
        "tgn:2427697",
        "tgn:7006450",
        "tgn:1000001",
        "tgn:7012149",
        "tgn:2000082",
        "tgn:7029392"
    ],
    "tgn:id":2427697,
    "tgn:name":"Josephine, Lake",
    "tgn:placetype":[
        "aat:300008680"
    ]
},
  "bbox": [],
  "geometry": {"coordinates":[-132.5667,55.2333],"type":"Point"}
}