{
  "id": 7255383,
  "type": "Feature",
  "properties": {
    "tgn:hierarchy":[
        "tgn:7255383",
        "tgn:7003460",
        "tgn:1000003",
        "tgn:1000063",
        "tgn:4012014",
        "tgn:7029392"
    ],
    "tgn:id":7255383,
    "tgn:name":"Roerberg",
    "tgn:placetype":[
        "aat:300008347"
    ]
},
  "bbox": [],
  "geometry": {"coordinates":[5.966667,50.733333],"type":"Point"}
}