{
  "id": 7577280,
  "type": "Feature",
  "properties": {
    "tgn:hierarchy":[
        "tgn:7577280",
        "tgn:1000004",
        "tgn:7000198",
        "tgn:7016788",
        "tgn:7029392"
    ],
    "tgn:id":7577280,
    "tgn:name:en":"Khera",
    "tgn:placetype":[
        "aat:300008347"
    ]
},
  "bbox": [],
  "geometry": {"coordinates":[73.563251,28.477522],"type":"Point"}
}