{
  "id": 7489354,
  "type": "Feature",
  "properties": {
    "tgn:hierarchy":[
        "tgn:7489354",
        "tgn:7488858",
        "tgn:1000004",
        "tgn:1000141",
        "tgn:7029392"
    ],
    "tgn:id":7489354,
    "tgn:name":"Ren'ai Xiang",
    "tgn:placetype":[
        "aat:300387173"
    ]
},
  "bbox": [],
  "geometry": {"coordinates":[121.131111,24.025278],"type":"Point"}
}