<<<<<<< HEAD
{
  "id": 7489354,
  "type": "Feature",
  "properties": {
    "tgn:hierarchy":[
        "tgn:7489354",
        "tgn:7488858",
        "tgn:1000004",
        "tgn:1000141",
        "tgn:7029392"
    ],
    "tgn:id":7489354,
    "tgn:name":"Ren'ai Xiang",
    "tgn:placetype":[
        "aat:300387173"
    ]
},
  "bbox": [],
  "geometry": {"coordinates":[121.131111,24.025278],"type":"Point"}
}
=======
{"geometry":{"type":"Point","coordinates":[121.131111,24.025278]},"type":"Feature","properties":{"hierarchy":["tgn:7489354","tgn:7488858","tgn:1000004","tgn:1000141","tgn:7029392"],"placetype":["aat:300387173"],"id":7489354,"name:xx":"Ren'ai Xiang"}}
>>>>>>> 03f74aca74312dbeaf24d7e61306dd6a786dc3d0
