{
  "id": 7222206,
  "type": "Feature",
  "properties": {
    "tgn:hierarchy":[
        "tgn:7222206",
        "tgn:7002690",
        "tgn:7012056",
        "tgn:1000003",
        "tgn:1000074",
        "tgn:7029392"
    ],
    "tgn:id":7222206,
    "tgn:name":"Sirik\u00e1rion",
    "tgn:placetype":[
        "aat:300008347"
    ]
},
  "bbox": [],
  "geometry": {"coordinates":[23.633333,35.416667],"type":"Point"}
}