{
  "id": 2176521,
  "type": "Feature",
  "properties": {
    "tgn:hierarchy":[
        "tgn:2176521",
        "tgn:1000001",
        "tgn:7012149",
        "tgn:2000885",
        "tgn:7007256",
        "tgn:7029392"
    ],
    "tgn:id":2176521,
    "tgn:name":"Black Lake",
    "tgn:placetype":[
        "aat:300008680"
    ]
},
  "bbox": [],
  "geometry": {"coordinates":[-90.6333,30.25],"type":"Point"}
}