{
  "id": 2219542,
  "type": "Feature",
  "properties": {
    "tgn:hierarchy":[
        "tgn:2219542",
        "tgn:1000001",
        "tgn:2000772",
        "tgn:7012149",
        "tgn:7007255",
        "tgn:7029392"
    ],
    "tgn:id":2219542,
    "tgn:name":"Canoe Creek",
    "tgn:placetype":[
        "aat:300008706"
    ]
},
  "bbox": [],
  "geometry": {"coordinates":[-83.45,37.4333],"type":"Point"}
}