<<<<<<< HEAD
{
  "id": 2335768,
  "type": "Feature",
  "properties": {
    "tgn:hierarchy":[
        "tgn:2335768",
        "tgn:1000001",
        "tgn:7012149",
        "tgn:2001927",
        "tgn:7007825",
        "tgn:7029392"
    ],
    "tgn:id":2335768,
    "tgn:name":"Fortyeight Creek",
    "tgn:placetype":[
        "aat:300008706"
    ]
},
  "bbox": [],
  "geometry": {"coordinates":[-87.6,35.2833],"type":"Point"}
}
=======
{"geometry":{"type":"Point","coordinates":[-87.600000,35.283300]},"type":"Feature","properties":{"hierarchy":["tgn:2335768","tgn:1000001","tgn:7012149","tgn:2001927","tgn:7007825","tgn:7029392"],"placetype":["aat:300008706"],"id":2335768,"name:xx":"Fortyeight Creek"}}
>>>>>>> 03f74aca74312dbeaf24d7e61306dd6a786dc3d0
