{
  "id": 7276267,
  "type": "Feature",
  "properties": {
    "tgn:hierarchy":[
        "tgn:7276267",
        "tgn:1001705",
        "tgn:1000049",
        "tgn:1000002",
        "tgn:7029392"
    ],
    "tgn:id":7276267,
    "tgn:name":"Tejer\u00eda",
    "tgn:placetype":[
        "aat:300008347"
    ]
},
  "bbox": [],
  "geometry": {"coordinates":[-72.433333,-35.716667],"type":"Point"}
}