{
  "id": 2216260,
  "type": "Feature",
  "properties": {
    "tgn:hierarchy":[
        "tgn:2216260",
        "tgn:1000001",
        "tgn:7012149",
        "tgn:2001901",
        "tgn:7007825",
        "tgn:7029392"
    ],
    "tgn:id":2216260,
    "tgn:name":"Camp Branch",
    "tgn:placetype":[
        "aat:300008699"
    ]
},
  "bbox": [],
  "geometry": {"coordinates":[-84.6833,36.0667],"type":"Point"}
}