{
  "id": 7315272,
  "type": "Feature",
  "properties": {
    "tgn:hierarchy":[
        "tgn:7315272",
        "tgn:7016598",
        "tgn:1000049",
        "tgn:1000002",
        "tgn:7029392"
    ],
    "tgn:id":7315272,
    "tgn:name":"Chocal, Carcanal de",
    "tgn:placetype":[
        "aat:300387002"
    ]
},
  "bbox": [],
  "geometry": {"coordinates":[-68.833333,-21.25],"type":"Point"}
}