{
  "id": 2379729,
  "type": "Feature",
  "properties": {
    "tgn:hierarchy":[
        "tgn:2379729",
        "tgn:1000001",
        "tgn:7006451",
        "tgn:7012149",
        "tgn:2000097",
        "tgn:7029392"
    ],
    "tgn:id":2379729,
    "tgn:name":"Hassayampa Plain",
    "tgn:placetype":[
        "aat:300008805"
    ]
},
  "bbox": [],
  "geometry": {"coordinates":[-112.9167,33.7667],"type":"Point"}
}