<<<<<<< HEAD
{
  "id": 2766077,
  "type": "Feature",
  "properties": {
    "tgn:hierarchy":[
        "tgn:2766077",
        "tgn:1000001",
        "tgn:2001419",
        "tgn:7012149",
        "tgn:7007526",
        "tgn:7029392"
    ],
    "tgn:id":2766077,
    "tgn:name":"White Horse Spring",
    "tgn:placetype":[
        "aat:300008697"
    ]
},
  "bbox": [],
  "geometry": {"coordinates":[-118.8833,40.5],"type":"Point"}
}
=======
{"geometry":{"type":"Point","coordinates":[-118.883300,40.500000]},"type":"Feature","properties":{"hierarchy":["tgn:2766077","tgn:1000001","tgn:2001419","tgn:7012149","tgn:7007526","tgn:7029392"],"placetype":["aat:300008697"],"id":2766077,"name:xx":"White Horse Spring"}}
>>>>>>> 03f74aca74312dbeaf24d7e61306dd6a786dc3d0
