{
  "id": 7510547,
  "type": "Feature",
  "properties": {
    "tgn:hierarchy":[
        "tgn:7510547",
        "tgn:1008380",
        "tgn:7000507",
        "tgn:1000226",
        "tgn:1000006",
        "tgn:7029392"
    ],
    "tgn:id":7510547,
    "tgn:name:en":"Upokorau Stream",
    "tgn:placetype":[
        "aat:300008699"
    ]
},
  "bbox": [],
  "geometry": {"coordinates":[173.816667,-35.133333],"type":"Point"}
}