{
  "id": 2607661,
  "type": "Feature",
  "properties": {
    "tgn:hierarchy":[
        "tgn:2607661",
        "tgn:1000001",
        "tgn:7012149",
        "tgn:2000227",
        "tgn:7007158",
        "tgn:7029392"
    ],
    "tgn:id":2607661,
    "tgn:name":"Rapson Mine",
    "tgn:placetype":[
        "aat:300000390"
    ]
},
  "bbox": [],
  "geometry": {"coordinates":[-104.6667,37.45],"type":"Point"}
}