{
  "id": 2670806,
  "type": "Feature",
  "properties": {
    "tgn:hierarchy":[
        "tgn:2670806",
        "tgn:1000001",
        "tgn:7013942",
        "tgn:7012149",
        "tgn:7007517",
        "tgn:7029392"
    ],
    "tgn:id":2670806,
    "tgn:name":"Smith Brook",
    "tgn:placetype":[
        "aat:300008699"
    ]
},
  "bbox": [],
  "geometry": {"coordinates":[-72.8167,42.5333],"type":"Point"}
}