{
  "id": 7317319,
  "type": "Feature",
  "properties": {
    "tgn:hierarchy":[
        "tgn:7317319",
        "tgn:1001630",
        "tgn:1000049",
        "tgn:1000002",
        "tgn:7029392"
    ],
    "tgn:id":7317319,
    "tgn:name":"Chimenea, Cerro",
    "tgn:placetype":[
        "aat:300008795"
    ]
},
  "bbox": [],
  "geometry": {"coordinates":[-70.533333,-28.383333],"type":"Point"}
}