{
  "id": 7472111,
  "type": "Feature",
  "properties": {
    "tgn:hierarchy":[
        "tgn:7472111",
        "tgn:7001010",
        "tgn:1000004",
        "tgn:1000141",
        "tgn:7029392"
    ],
    "tgn:id":7472111,
    "tgn:name":"Shangkan",
    "tgn:placetype":[
        "aat:300008347"
    ]
},
  "bbox": [],
  "geometry": {"coordinates":[121.6589,24.1612],"type":"Point"}
}