{
  "id": 2745070,
  "type": "Feature",
  "properties": {
    "tgn:hierarchy":[
        "tgn:2745070",
        "tgn:1000001",
        "tgn:2001431",
        "tgn:7012149",
        "tgn:7007566",
        "tgn:7029392"
    ],
    "tgn:id":2745070,
    "tgn:name":"Villa de Cubero",
    "tgn:placetype":[
        "aat:300008347"
    ]
},
  "bbox": [],
  "geometry": {"coordinates":[-107.5333,35.0833],"type":"Point"}
}