{
  "id": 7584575,
  "type": "Feature",
  "properties": {
    "tgn:hierarchy":[
        "tgn:7584575",
        "tgn:1000004",
        "tgn:7000198",
        "tgn:1001894",
        "tgn:7029392"
    ],
    "tgn:id":7584575,
    "tgn:name:en":"Mewali",
    "tgn:placetype":[
        "aat:300008347"
    ]
},
  "bbox": [],
  "geometry": {"coordinates":[78.181447,24.12899],"type":"Point"}
}