<<<<<<< HEAD
{
  "id": 7370817,
  "type": "Feature",
  "properties": {
    "tgn:hierarchy":[
        "tgn:7370817",
        "tgn:1000001",
        "tgn:7005592",
        "tgn:7005560",
        "tgn:7029392"
    ],
    "tgn:id":7370817,
    "tgn:name":"Huitzilac",
    "tgn:placetype":[
        "aat:300008347"
    ]
},
  "bbox": [],
  "geometry": {"coordinates":[-97.75,20.6],"type":"Point"}
}
=======
{"geometry":{"type":"Point","coordinates":[-97.750000,20.600000]},"type":"Feature","properties":{"hierarchy":["tgn:7370817","tgn:1000001","tgn:7005592","tgn:7005560","tgn:7029392"],"placetype":["aat:300008347"],"id":7370817,"name:xx":"Huitzilac"}}
>>>>>>> 03f74aca74312dbeaf24d7e61306dd6a786dc3d0
