{
  "id": 2089096,
  "type": "Feature",
  "properties": {
    "tgn:hierarchy":[
        "tgn:2089096",
        "tgn:1000001",
        "tgn:1002266",
        "tgn:7012149",
        "tgn:7007710",
        "tgn:7029392"
    ],
    "tgn:id":2089096,
    "tgn:name":"Harmony Hill",
    "tgn:placetype":[
        "aat:300008347"
    ]
},
  "bbox": [],
  "geometry": {"coordinates":[-75.6667,39.9667],"type":"Point"}
}