{
  "id": 2055838,
  "type": "Feature",
  "properties": {
    "tgn:hierarchy":[
        "tgn:2055838",
        "tgn:1000001",
        "tgn:7012149",
        "tgn:2001143",
        "tgn:7007522",
        "tgn:7029392"
    ],
    "tgn:id":2055838,
    "tgn:name":"Algoma",
    "tgn:placetype":[
        "aat:300008347"
    ]
},
  "bbox": [],
  "geometry": {"coordinates":[-89.0167,34.1667],"type":"Point"}
}