<<<<<<< HEAD
{
  "id": 7027782,
  "type": "Feature",
  "properties": {
    "tgn:hierarchy":[
        "tgn:7027782",
        "tgn:7002445",
        "tgn:1000003",
        "tgn:7008157",
        "tgn:7008591",
        "tgn:7029392"
    ],
    "tgn:id":7027782,
    "tgn:name:en":"Branston",
    "tgn:placetype":[
        "aat:300008347",
        "aat:300008372"
    ]
},
  "bbox": [],
  "geometry": {"coordinates":[-0.466667,53.183333],"type":"Point"}
}
=======
{"geometry":{"type":"Point","coordinates":[-0.466667,53.183333]},"type":"Feature","properties":{"hierarchy":["tgn:7027782","tgn:7002445","tgn:1000003","tgn:7008157","tgn:7008591","tgn:7029392"],"placetype":["aat:300008347","aat:300008372"],"name:en":"Branston","id":7027782}}
>>>>>>> 03f74aca74312dbeaf24d7e61306dd6a786dc3d0
