{
  "id": 2077076,
  "type": "Feature",
  "properties": {
    "tgn:hierarchy":[
        "tgn:2077076",
        "tgn:1000001",
        "tgn:7012149",
        "tgn:2001541",
        "tgn:7007709",
        "tgn:7029392"
    ],
    "tgn:id":2077076,
    "tgn:name":"Walnut Cove",
    "tgn:placetype":[
        "aat:300008347"
    ]
},
  "bbox": [],
  "geometry": {"coordinates":[-80.1333,36.2833],"type":"Point"}
}