{
  "id": 2633489,
  "type": "Feature",
  "properties": {
    "tgn:hierarchy":[
        "tgn:2633489",
        "tgn:1000001",
        "tgn:7012149",
        "tgn:7007922",
        "tgn:7029392"
    ],
    "tgn:id":2633489,
    "tgn:name":"Running Valley Creek",
    "tgn:placetype":[
        "aat:300008706"
    ]
},
  "bbox": [],
  "geometry": {"coordinates":[-91.6167,45.05],"type":"Point"}
}