<<<<<<< HEAD
{
  "id": 2764470,
  "type": "Feature",
  "properties": {
    "tgn:hierarchy":[
        "tgn:2764470",
        "tgn:1000001",
        "tgn:1002245",
        "tgn:7012149",
        "tgn:7007568",
        "tgn:7029392"
    ],
    "tgn:id":2764470,
    "tgn:name":"Whig Street Creek",
    "tgn:placetype":[
        "aat:300008706"
    ]
},
  "bbox": [],
  "geometry": {"coordinates":[-78.7167,42.25],"type":"Point"}
}
=======
{"geometry":{"type":"Point","coordinates":[-78.716700,42.250000]},"type":"Feature","properties":{"hierarchy":["tgn:2764470","tgn:1000001","tgn:1002245","tgn:7012149","tgn:7007568","tgn:7029392"],"placetype":["aat:300008706"],"id":2764470,"name:xx":"Whig Street Creek"}}
>>>>>>> 03f74aca74312dbeaf24d7e61306dd6a786dc3d0
