{
  "id": 7509271,
  "type": "Feature",
  "properties": {
    "tgn:hierarchy":[
        "tgn:7509271",
        "tgn:1009227",
        "tgn:1000226",
        "tgn:7016822",
        "tgn:1000006",
        "tgn:7029392"
    ],
    "tgn:id":7509271,
    "tgn:name:en":"Thurso River",
    "tgn:placetype":[
        "aat:300008699"
    ]
},
  "bbox": [],
  "geometry": {"coordinates":[167.816667,-44.55],"type":"Point"}
}