{
  "id": 7495430,
  "type": "Feature",
  "properties": {
    "tgn:hierarchy":[
        "tgn:7495430",
        "tgn:7468018",
        "tgn:1000004",
        "tgn:1000141",
        "tgn:7029392"
    ],
    "tgn:id":7495430,
    "tgn:name":"Disishibahao Qiao",
    "tgn:placetype":[
        "aat:300007836"
    ]
},
  "bbox": [],
  "geometry": {"coordinates":[120.732889,23.489372],"type":"Point"}
}