{
  "id": 1137657,
  "type": "Feature",
  "properties": {
    "tgn:hierarchy":[
        "tgn:1137657",
        "tgn:7012076",
        "tgn:1000003",
        "tgn:7006660",
        "tgn:7029392"
    ],
    "tgn:id":1137657,
    "tgn:name":"Kirovs'k",
    "tgn:placetype":[
        "aat:300008347"
    ]
},
  "bbox": [],
  "geometry": {"coordinates":[37.9333,49.0167],"type":"Point"}
}