{
  "id": 2368083,
  "type": "Feature",
  "properties": {
    "tgn:hierarchy":[
        "tgn:2368083",
        "tgn:1000001",
        "tgn:7006451",
        "tgn:2000093",
        "tgn:7012149",
        "tgn:7029392"
    ],
    "tgn:id":2368083,
    "tgn:name":"Gruwell Spring",
    "tgn:placetype":[
        "aat:300008697"
    ]
},
  "bbox": [],
  "geometry": {"coordinates":[-110.8833,34.15],"type":"Point"}
}