{
  "id": 7517782,
  "type": "Feature",
  "properties": {
    "tgn:hierarchy":[
        "tgn:7517782",
        "tgn:1008380",
        "tgn:1000226",
        "tgn:7016827",
        "tgn:1000006",
        "tgn:7029392"
    ],
    "tgn:id":7517782,
    "tgn:name:en":"Ngutuwera",
    "tgn:placetype":[
        "aat:300008347"
    ]
},
  "bbox": [],
  "geometry": {"coordinates":[174.733333,-39.75],"type":"Point"}
}