{
  "id": 2363224,
  "type": "Feature",
  "properties": {
    "tgn:hierarchy":[
        "tgn:2363224",
        "tgn:1000001",
        "tgn:7012149",
        "tgn:2000438",
        "tgn:7007248",
        "tgn:7029392"
    ],
    "tgn:id":2363224,
    "tgn:name":"Green Branch",
    "tgn:placetype":[
        "aat:300008699"
    ]
},
  "bbox": [],
  "geometry": {"coordinates":[-83.5833,33.7667],"type":"Point"}
}