{
  "id": 1021993,
  "type": "Feature",
  "properties": {
    "tgn:hierarchy":[
        "tgn:1021993",
        "tgn:7016581",
        "tgn:1000047",
        "tgn:7002455",
        "tgn:1000002",
        "tgn:7029392"
    ],
    "tgn:id":1021993,
    "tgn:name":"Macei\u00f3",
    "tgn:placetype":[
        "aat:300008347",
        "aat:300008389",
        "aat:300387221",
        "aat:300387302"
    ]
},
  "bbox": [],
  "geometry": {"coordinates":[-35.7333,-9.6667],"type":"Point"}
}