<<<<<<< HEAD
{
  "id": 2400539,
  "type": "Feature",
  "properties": {
    "tgn:hierarchy":[
        "tgn:2400539",
        "tgn:1000001",
        "tgn:7012149",
        "tgn:2001036",
        "tgn:7007521",
        "tgn:7029392"
    ],
    "tgn:id":2400539,
    "tgn:name":"Horse Lake",
    "tgn:placetype":[
        "aat:300008680"
    ]
},
  "bbox": [],
  "geometry": {"coordinates":[-91.75,48.0667],"type":"Point"}
}
=======
{"geometry":{"type":"Point","coordinates":[-91.750000,48.066700]},"type":"Feature","properties":{"hierarchy":["tgn:2400539","tgn:1000001","tgn:7012149","tgn:2001036","tgn:7007521","tgn:7029392"],"placetype":["aat:300008680"],"id":2400539,"name:xx":"Horse Lake"}}
>>>>>>> 03f74aca74312dbeaf24d7e61306dd6a786dc3d0
