{
  "id": 7418965,
  "type": "Feature",
  "properties": {
    "tgn:hierarchy":[
        "tgn:7418965",
        "tgn:1000001",
        "tgn:7005589",
        "tgn:7005560",
        "tgn:7029392"
    ],
    "tgn:id":7418965,
    "tgn:name:es":"Puentes",
    "tgn:placetype":[
        "aat:300008347"
    ]
},
  "bbox": [],
  "geometry": {"coordinates":[-100.059722,24.141944],"type":"Point"}
}