{
  "id": 1033397,
  "type": "Feature",
  "properties": {
    "tgn:hierarchy":[
        "tgn:1033397",
        "tgn:1000003",
        "tgn:7002888",
        "tgn:1000070",
        "tgn:7029392"
    ],
    "tgn:id":1033397,
    "tgn:name":"Hagondange",
    "tgn:placetype":[
        "aat:300008347"
    ]
},
  "bbox": [],
  "geometry": {"coordinates":[6.1833,49.2667],"type":"Point"}
}