{
  "id": 7288233,
  "type": "Feature",
  "properties": {
    "tgn:hierarchy":[
        "tgn:7288233",
        "tgn:1001702",
        "tgn:1000049",
        "tgn:1000002",
        "tgn:7029392"
    ],
    "tgn:id":7288233,
    "tgn:name":"Laipe, Islas",
    "tgn:placetype":[
        "aat:300008791"
    ]
},
  "bbox": [],
  "geometry": {"coordinates":[-75.033333,-51.516667],"type":"Point"}
}