<<<<<<< HEAD
{
  "id": 7176057,
  "type": "Feature",
  "properties": {
    "tgn:hierarchy":[
        "tgn:7176057",
        "tgn:1000003",
        "tgn:7000094",
        "tgn:7000084",
        "tgn:7029392"
    ],
    "tgn:id":7176057,
    "tgn:name":"Gro\u00df Thurow",
    "tgn:placetype":[
        "aat:300008347"
    ]
},
  "bbox": [],
  "geometry": {"coordinates":[10.933333,53.7],"type":"Point"}
}
=======
{"geometry":{"type":"Point","coordinates":[10.933333,53.700000]},"type":"Feature","properties":{"hierarchy":["tgn:7176057","tgn:1000003","tgn:7000094","tgn:7000084","tgn:7029392"],"placetype":["aat:300008347"],"id":7176057,"name:xx":"Gro\u00df Thurow"}}
>>>>>>> 03f74aca74312dbeaf24d7e61306dd6a786dc3d0
