<<<<<<< HEAD
{
  "id": 2258752,
  "type": "Feature",
  "properties": {
    "tgn:hierarchy":[
        "tgn:2258752",
        "tgn:1000001",
        "tgn:7016172",
        "tgn:2000113",
        "tgn:7012149",
        "tgn:7029392"
    ],
    "tgn:id":2258752,
    "tgn:name":"Cottonwood Chute",
    "tgn:placetype":[
        "aat:300008680"
    ]
},
  "bbox": [],
  "geometry": {"coordinates":[-91.1333,33.2833],"type":"Point"}
}
=======
{"geometry":{"type":"Point","coordinates":[-91.133300,33.283300]},"type":"Feature","properties":{"hierarchy":["tgn:2258752","tgn:1000001","tgn:7016172","tgn:2000113","tgn:7012149","tgn:7029392"],"placetype":["aat:300008680"],"id":2258752,"name:xx":"Cottonwood Chute"}}
>>>>>>> 03f74aca74312dbeaf24d7e61306dd6a786dc3d0
