{
  "id": 2058122,
  "type": "Feature",
  "properties": {
    "tgn:hierarchy":[
        "tgn:2058122",
        "tgn:1000001",
        "tgn:7012149",
        "tgn:2001213",
        "tgn:7007523",
        "tgn:7029392"
    ],
    "tgn:id":2058122,
    "tgn:name":"Bowers Mill",
    "tgn:placetype":[
        "aat:300008347",
        "aat:300167671",
        "aat:300387210"
    ]
},
  "bbox": [],
  "geometry": {"coordinates":[-94.05,37.1333],"type":"Point"}
}