{
  "id": 2068594,
  "type": "Feature",
  "properties": {
    "tgn:hierarchy":[
        "tgn:2068594",
        "tgn:1000001",
        "tgn:1002347",
        "tgn:7012149",
        "tgn:7007568",
        "tgn:7029392"
    ],
    "tgn:id":2068594,
    "tgn:name":"College Park",
    "tgn:placetype":[
        "aat:300008347"
    ]
},
  "bbox": [],
  "geometry": {"coordinates":[-73.8667,42.0167],"type":"Point"}
}