{
  "id": 1054966,
  "type": "Feature",
  "properties": {
    "tgn:hierarchy":[
        "tgn:1054966",
        "tgn:1000004",
        "tgn:7011628",
        "tgn:7014835",
        "tgn:7029392"
    ],
    "tgn:id":1054966,
    "tgn:name":"Kamyshkurgon",
    "tgn:placetype":[
        "aat:300008347"
    ]
},
  "bbox": [],
  "geometry": {"coordinates":[70.4333,40.55],"type":"Point"}
}