<<<<<<< HEAD
{
  "id": 2334876,
  "type": "Feature",
  "properties": {
    "tgn:hierarchy":[
        "tgn:2334876",
        "tgn:1000001",
        "tgn:7012149",
        "tgn:2001896",
        "tgn:7007825",
        "tgn:7029392"
    ],
    "tgn:id":2334876,
    "tgn:name":"Forked Deer Hollow",
    "tgn:placetype":[
        "aat:300008761"
    ]
},
  "bbox": [],
  "geometry": {"coordinates":[-87.1,35.7667],"type":"Point"}
}
=======
{"geometry":{"type":"Point","coordinates":[-87.100000,35.766700]},"type":"Feature","properties":{"hierarchy":["tgn:2334876","tgn:1000001","tgn:7012149","tgn:2001896","tgn:7007825","tgn:7029392"],"placetype":["aat:300008761"],"id":2334876,"name:xx":"Forked Deer Hollow"}}
>>>>>>> 03f74aca74312dbeaf24d7e61306dd6a786dc3d0
