{
  "id": 2482385,
  "type": "Feature",
  "properties": {
    "tgn:hierarchy":[
        "tgn:2482385",
        "tgn:1000001",
        "tgn:7012149",
        "tgn:1002986",
        "tgn:7007568",
        "tgn:7029392"
    ],
    "tgn:id":2482385,
    "tgn:name":"Langworthy Creek",
    "tgn:placetype":[
        "aat:300008706"
    ]
},
  "bbox": [],
  "geometry": {"coordinates":[-74.0167,43.45],"type":"Point"}
}