<<<<<<< HEAD
{
  "id": 7240746,
  "type": "Feature",
  "properties": {
    "tgn:hierarchy":[
        "tgn:7240746",
        "tgn:7007877",
        "tgn:1000003",
        "tgn:1000063",
        "tgn:4012014",
        "tgn:7029392"
    ],
    "tgn:id":7240746,
    "tgn:name":"Ferri\u00e8res",
    "tgn:placetype":[
        "aat:300008347"
    ]
},
  "bbox": [],
  "geometry": {"coordinates":[4.35,50.083333],"type":"Point"}
}
=======
{"geometry":{"type":"Point","coordinates":[4.350000,50.083333]},"type":"Feature","properties":{"hierarchy":["tgn:7240746","tgn:7007877","tgn:1000003","tgn:1000063","tgn:4012014","tgn:7029392"],"placetype":["aat:300008347"],"id":7240746,"name:xx":"Ferri\u00e8res"}}
>>>>>>> 03f74aca74312dbeaf24d7e61306dd6a786dc3d0
