{
  "id": 2757203,
  "type": "Feature",
  "properties": {
    "tgn:hierarchy":[
        "tgn:2757203",
        "tgn:1000001",
        "tgn:7012149",
        "tgn:2000283",
        "tgn:7007240",
        "tgn:7029392"
    ],
    "tgn:id":2757203,
    "tgn:name":"Wesley Manor Retirement Village",
    "tgn:placetype":[
        "aat:300008347"
    ]
},
  "bbox": [],
  "geometry": {"coordinates":[-81.6167,30.1167],"type":"Point"}
}