{
  "id": 7148073,
  "type": "Feature",
  "properties": {
    "tgn:hierarchy":[
        "tgn:7148073",
        "tgn:1000003",
        "tgn:7003689",
        "tgn:7000084",
        "tgn:7029392"
    ],
    "tgn:id":7148073,
    "tgn:name":"Vorwerk Langegrund",
    "tgn:placetype":[
        "aat:300000206"
    ]
},
  "bbox": [],
  "geometry": {"coordinates":[10.383333,51.033333],"type":"Point"}
}