{
  "id": 2138077,
  "type": "Feature",
  "properties": {
    "tgn:hierarchy":[
        "tgn:2138077",
        "tgn:2000090",
        "tgn:1000001",
        "tgn:7006451",
        "tgn:7012149",
        "tgn:7029392"
    ],
    "tgn:id":2138077,
    "tgn:name":"Arroy Tank",
    "tgn:placetype":[
        "aat:300006191"
    ]
},
  "bbox": [],
  "geometry": {"coordinates":[-109.05,33.7667],"type":"Point"}
}