{
  "id": 2433875,
  "type": "Feature",
  "properties": {
    "tgn:hierarchy":[
        "tgn:2433875",
        "tgn:1000001",
        "tgn:7012149",
        "tgn:2000927",
        "tgn:7007515",
        "tgn:7029392"
    ],
    "tgn:id":2433875,
    "tgn:name":"Kelly Mountain",
    "tgn:placetype":[
        "aat:300008798"
    ]
},
  "bbox": [],
  "geometry": {"coordinates":[-68.9833,44.7333],"type":"Point"}
}