{
  "id": 7089644,
  "type": "Feature",
  "properties": {
    "tgn:hierarchy":[
        "tgn:7089644",
        "tgn:7003669",
        "tgn:1000003",
        "tgn:7000084",
        "tgn:7029392"
    ],
    "tgn:id":7089644,
    "tgn:name":"Unter Wald",
    "tgn:placetype":[
        "aat:300008863"
    ]
},
  "bbox": [],
  "geometry": {"coordinates":[9.033333,50.066667],"type":"Point"}
}