{
  "id": 7134444,
  "type": "Feature",
  "properties": {
    "tgn:hierarchy":[
        "tgn:7134444",
        "tgn:1000003",
        "tgn:7003687",
        "tgn:7000084",
        "tgn:7029392"
    ],
    "tgn:id":7134444,
    "tgn:name":"Naundorf",
    "tgn:placetype":[
        "aat:300008347"
    ]
},
  "bbox": [],
  "geometry": {"coordinates":[12.883333,51.933333],"type":"Point"}
}