{
  "id": 7125771,
  "type": "Feature",
  "properties": {
    "tgn:hierarchy":[
        "tgn:7125771",
        "tgn:1000003",
        "tgn:7003688",
        "tgn:7000084",
        "tgn:7029392"
    ],
    "tgn:id":7125771,
    "tgn:name":"Norderstrom",
    "tgn:placetype":[
        "aat:300008699"
    ]
},
  "bbox": [],
  "geometry": {"coordinates":[8.85,54.716667],"type":"Point"}
}