{
  "id": 2577940,
  "type": "Feature",
  "properties": {
    "tgn:hierarchy":[
        "tgn:2577940",
        "tgn:1000001",
        "tgn:7012149",
        "tgn:2000966",
        "tgn:7007520",
        "tgn:7029392"
    ],
    "tgn:id":2577940,
    "tgn:name":"Petrow Lake",
    "tgn:placetype":[
        "aat:300008680"
    ]
},
  "bbox": [],
  "geometry": {"coordinates":[-88.6833,46.3667],"type":"Point"}
}