{
  "id": 7267041,
  "type": "Feature",
  "properties": {
    "tgn:concordances":{
        "gn:id":"2751903"
    },
    "tgn:hierarchy":[
        "tgn:7267041",
        "tgn:1000003",
        "tgn:7003635",
        "tgn:7016845",
        "tgn:7029392"
    ],
    "tgn:id":7267041,
    "tgn:name:nl":"Langeweegje",
    "tgn:placetype":[
        "aat:300008347"
    ]
},
  "bbox": [],
  "geometry": {"coordinates":[3.883333,51.433333],"type":"Point"}
}