{
  "id": 7103660,
  "type": "Feature",
  "properties": {
    "tgn:hierarchy":[
        "tgn:7103660",
        "tgn:1000003",
        "tgn:7000094",
        "tgn:7000084",
        "tgn:7029392"
    ],
    "tgn:id":7103660,
    "tgn:name":"Sandkrug",
    "tgn:placetype":[
        "aat:300008347"
    ]
},
  "bbox": [],
  "geometry": {"coordinates":[13.916667,53.55],"type":"Point"}
}