{
  "id": 7201603,
  "type": "Feature",
  "properties": {
    "tgn:hierarchy":[
        "tgn:7201603",
        "tgn:7003692",
        "tgn:1000003",
        "tgn:7000084",
        "tgn:7029392"
    ],
    "tgn:id":7201603,
    "tgn:name":"Breitmatt",
    "tgn:placetype":[
        "aat:300000206"
    ]
},
  "bbox": [],
  "geometry": {"coordinates":[8.216667,48.466667],"type":"Point"}
}