<<<<<<< HEAD
{
  "id": 2252972,
  "type": "Feature",
  "properties": {
    "tgn:hierarchy":[
        "tgn:2252972",
        "tgn:7002659",
        "tgn:1000001",
        "tgn:2000006",
        "tgn:7012149",
        "tgn:7029392"
    ],
    "tgn:id":2252972,
    "tgn:name":"Conservation Lake",
    "tgn:placetype":[
        "aat:300006191"
    ]
},
  "bbox": [],
  "geometry": {"coordinates":[-86.6833,31.8333],"type":"Point"}
}
=======
{"geometry":{"type":"Point","coordinates":[-86.683300,31.833300]},"type":"Feature","properties":{"hierarchy":["tgn:2252972","tgn:7002659","tgn:1000001","tgn:2000006","tgn:7012149","tgn:7029392"],"placetype":["aat:300006191"],"id":2252972,"name:xx":"Conservation Lake"}}
>>>>>>> 03f74aca74312dbeaf24d7e61306dd6a786dc3d0
