{
  "id": 7014375,
  "type": "Feature",
  "properties": {
    "tgn:hierarchy":[
        "tgn:7014375",
        "tgn:1000001",
        "tgn:7012149",
        "tgn:2001275",
        "tgn:7007524",
        "tgn:7029392"
    ],
    "tgn:id":7014375,
    "tgn:name":"Three Forks",
    "tgn:placetype":[
        "aat:300008347",
        "aat:300008375",
        "aat:300387250"
    ]
},
  "bbox": [],
  "geometry": {"coordinates":[-111.55,45.8833],"type":"Point"}
}