{
  "id": 7330073,
  "type": "Feature",
  "properties": {
    "tgn:hierarchy":[
        "tgn:7330073",
        "tgn:7002818",
        "tgn:1001647",
        "tgn:1000003",
        "tgn:1000095",
        "tgn:7029392"
    ],
    "tgn:id":7330073,
    "tgn:name":"Hoz, Barranco de la",
    "tgn:placetype":[
        "aat:300266554",
        "aat:300008699"
    ]
},
  "bbox": [],
  "geometry": {"coordinates":[-1.666667,39.516667],"type":"Point"}
}