<<<<<<< HEAD
{
  "id": 7375806,
  "type": "Feature",
  "properties": {
    "tgn:hierarchy":[
        "tgn:7375806",
        "tgn:7005586",
        "tgn:1000001",
        "tgn:7005560",
        "tgn:7029392"
    ],
    "tgn:id":7375806,
    "tgn:name":"Lindero, Cerro el",
    "tgn:placetype":[
        "aat:300008795"
    ]
},
  "bbox": [],
  "geometry": {"coordinates":[-104.116667,19.7],"type":"Point"}
}
=======
{"geometry":{"type":"Point","coordinates":[-104.116667,19.700000]},"type":"Feature","properties":{"hierarchy":["tgn:7375806","tgn:7005586","tgn:1000001","tgn:7005560","tgn:7029392"],"placetype":["aat:300008795"],"id":7375806,"name:xx":"Lindero, Cerro el"}}
>>>>>>> 03f74aca74312dbeaf24d7e61306dd6a786dc3d0
