{
  "id": 1040125,
  "type": "Feature",
  "properties": {
    "tgn:hierarchy":[
        "tgn:1040125",
        "tgn:1000003",
        "tgn:7003682",
        "tgn:7000084",
        "tgn:7029392"
    ],
    "tgn:id":1040125,
    "tgn:name":"Limburgerhof",
    "tgn:placetype":[
        "aat:300008347"
    ]
},
  "bbox": [],
  "geometry": {"coordinates":[8.391944,49.424444],"type":"Point"}
}