<<<<<<< HEAD
{
  "id": 2336705,
  "type": "Feature",
  "properties": {
    "tgn:hierarchy":[
        "tgn:2336705",
        "tgn:1000001",
        "tgn:7006451",
        "tgn:2000092",
        "tgn:7012149",
        "tgn:7029392"
    ],
    "tgn:id":2336705,
    "tgn:name":"Four, Tank",
    "tgn:placetype":[
        "aat:300006191"
    ]
},
  "bbox": [],
  "geometry": {"coordinates":[-111.6,35.45],"type":"Point"}
}
=======
{"geometry":{"type":"Point","coordinates":[-111.600000,35.450000]},"type":"Feature","properties":{"hierarchy":["tgn:2336705","tgn:1000001","tgn:7006451","tgn:2000092","tgn:7012149","tgn:7029392"],"placetype":["aat:300006191"],"id":2336705,"name:xx":"Four, Tank"}}
>>>>>>> 03f74aca74312dbeaf24d7e61306dd6a786dc3d0
