{
  "id": 7561793,
  "type": "Feature",
  "properties": {
    "tgn:hierarchy":[
        "tgn:7561793",
        "tgn:1000004",
        "tgn:7000198",
        "tgn:7016722",
        "tgn:7029392"
    ],
    "tgn:id":7561793,
    "tgn:name:en":"Nagla Basant",
    "tgn:placetype":[
        "aat:300008347"
    ]
},
  "bbox": [],
  "geometry": {"coordinates":[79.29972,27.118883],"type":"Point"}
}