{
  "id": 7513418,
  "type": "Feature",
  "properties": {
    "tgn:hierarchy":[
        "tgn:7513418",
        "tgn:1009227",
        "tgn:1000226",
        "tgn:7520095",
        "tgn:1000006",
        "tgn:7029392"
    ],
    "tgn:id":7513418,
    "tgn:name:en":"Goat Creek",
    "tgn:placetype":[
        "aat:300008699"
    ]
},
  "bbox": [],
  "geometry": {"coordinates":[172.783333,-41.233333],"type":"Point"}
}