{
  "id": 2146982,
  "type": "Feature",
  "properties": {
    "tgn:hierarchy":[
        "tgn:2146982",
        "tgn:1000001",
        "tgn:1002714",
        "tgn:7012149",
        "tgn:7007159",
        "tgn:7029392"
    ],
    "tgn:id":2146982,
    "tgn:name":"Banning Cove",
    "tgn:placetype":[
        "aat:300132316"
    ]
},
  "bbox": [],
  "geometry": {"coordinates":[-72.1833,41.3667],"type":"Point"}
}