{
  "id": 7336055,
  "type": "Feature",
  "properties": {
    "tgn:hierarchy":[
        "tgn:7336055",
        "tgn:7002829",
        "tgn:1000003",
        "tgn:7002786",
        "tgn:1000095",
        "tgn:7029392"
    ],
    "tgn:id":7336055,
    "tgn:name":"Fumayor",
    "tgn:placetype":[
        "aat:300008347"
    ]
},
  "bbox": [],
  "geometry": {"coordinates":[-7.083333,43.083333],"type":"Point"}
}