{
  "id": 7523750,
  "type": "Feature",
  "properties": {
    "tgn:hierarchy":[
        "tgn:7523750",
        "tgn:7001242",
        "tgn:7016833",
        "tgn:1001079",
        "tgn:7029392"
    ],
    "tgn:id":7523750,
    "tgn:name:en":"Ad Dayr",
    "tgn:placetype":[
        "aat:300008347"
    ]
},
  "bbox": [],
  "geometry": {"coordinates":[29.723056,31.078889],"type":"Point"}
}