{
  "id": 7483498,
  "type": "Feature",
  "properties": {
    "tgn:hierarchy":[
        "tgn:7483498",
        "tgn:1000004",
        "tgn:7489179",
        "tgn:1000141",
        "tgn:7029392"
    ],
    "tgn:id":7483498,
    "tgn:name":"Zhuzihu",
    "tgn:placetype":[
        "aat:300008347"
    ]
},
  "bbox": [],
  "geometry": {"coordinates":[121.916944,24.986111],"type":"Point"}
}