{
  "id": 2073993,
  "type": "Feature",
  "properties": {
    "tgn:hierarchy":[
        "tgn:2073993",
        "tgn:1000001",
        "tgn:7012149",
        "tgn:2001532",
        "tgn:7007709",
        "tgn:7029392"
    ],
    "tgn:id":2073993,
    "tgn:name":"Cedar Falls",
    "tgn:placetype":[
        "aat:300008347"
    ]
},
  "bbox": [],
  "geometry": {"coordinates":[-79.7167,35.75],"type":"Point"}
}