{
  "id": 7467935,
  "type": "Feature",
  "properties": {
    "tgn:hierarchy":[
        "tgn:7467935",
        "tgn:1000004",
        "tgn:7004300",
        "tgn:1000141",
        "tgn:7029392"
    ],
    "tgn:id":7467935,
    "tgn:name":"Chapo Yu",
    "tgn:placetype":[
        "aat:300008791"
    ]
},
  "bbox": [],
  "geometry": {"coordinates":[119.724662,23.558158],"type":"Point"}
}