{
  "id": 2167281,
  "type": "Feature",
  "properties": {
    "tgn:hierarchy":[
        "tgn:2167281",
        "tgn:7002659",
        "tgn:1000001",
        "tgn:7012149",
        "tgn:2000035",
        "tgn:7029392"
    ],
    "tgn:id":2167281,
    "tgn:name":"Big Coon Valley",
    "tgn:placetype":[
        "aat:300008761"
    ]
},
  "bbox": [],
  "geometry": {"coordinates":[-86.0167,34.8833],"type":"Point"}
}