{
  "id": 2195249,
  "type": "Feature",
  "properties": {
    "tgn:hierarchy":[
        "tgn:2195249",
        "tgn:1000001",
        "tgn:7012149",
        "tgn:2002380",
        "tgn:7007923",
        "tgn:7029392"
    ],
    "tgn:id":2195249,
    "tgn:name":"Brinton",
    "tgn:placetype":[
        "aat:300008347"
    ]
},
  "bbox": [],
  "geometry": {"coordinates":[-104.8833,41.7167],"type":"Point"}
}