<<<<<<< HEAD
{
  "id": 2338262,
  "type": "Feature",
  "properties": {
    "tgn:hierarchy":[
        "tgn:2338262",
        "tgn:1000001",
        "tgn:7012149",
        "tgn:2001724",
        "tgn:7007710",
        "tgn:7029392"
    ],
    "tgn:id":2338262,
    "tgn:name":"Fox Run",
    "tgn:placetype":[
        "aat:300008699"
    ]
},
  "bbox": [],
  "geometry": {"coordinates":[-80.1167,39.7667],"type":"Point"}
}
=======
{"geometry":{"type":"Point","coordinates":[-80.116700,39.766700]},"type":"Feature","properties":{"hierarchy":["tgn:2338262","tgn:1000001","tgn:7012149","tgn:2001724","tgn:7007710","tgn:7029392"],"placetype":["aat:300008699"],"id":2338262,"name:xx":"Fox Run"}}
>>>>>>> 03f74aca74312dbeaf24d7e61306dd6a786dc3d0
