{
  "id": 7343951,
  "type": "Feature",
  "properties": {
    "tgn:hierarchy":[
        "tgn:7343951",
        "tgn:7002810",
        "tgn:7001158",
        "tgn:1000003",
        "tgn:1000095",
        "tgn:7029392"
    ],
    "tgn:id":7343951,
    "tgn:name":"Casanova",
    "tgn:placetype":[
        "aat:300008347"
    ]
},
  "bbox": [],
  "geometry": {"coordinates":[-3.45,41.683333],"type":"Point"}
}