{
  "id": 2597272,
  "type": "Feature",
  "properties": {
    "tgn:hierarchy":[
        "tgn:2597272",
        "tgn:1000001",
        "tgn:7016172",
        "tgn:7012149",
        "tgn:2000170",
        "tgn:7029392"
    ],
    "tgn:id":2597272,
    "tgn:name":"Prairie Creek",
    "tgn:placetype":[
        "aat:300008347"
    ]
},
  "bbox": [],
  "geometry": {"coordinates":[-94.35,35.05],"type":"Point"}
}