{
  "id": 1063010,
  "type": "Feature",
  "properties": {
    "tgn:hierarchy":[
        "tgn:1063010",
        "tgn:1000003",
        "tgn:1000405",
        "tgn:1000097",
        "tgn:7029392"
    ],
    "tgn:id":1063010,
    "tgn:name":"Gemla",
    "tgn:placetype":[
        "aat:300008347"
    ]
},
  "bbox": [],
  "geometry": {"coordinates":[14.6333,56.8667],"type":"Point"}
}