<<<<<<< HEAD
{
  "id": 7110381,
  "type": "Feature",
  "properties": {
    "tgn:hierarchy":[
        "tgn:7110381",
        "tgn:7003669",
        "tgn:1000003",
        "tgn:7000084",
        "tgn:7029392"
    ],
    "tgn:id":7110381,
    "tgn:name":"Raitersaich",
    "tgn:placetype":[
        "aat:300008347"
    ]
},
  "bbox": [],
  "geometry": {"coordinates":[10.85,49.383333],"type":"Point"}
}
=======
{"geometry":{"type":"Point","coordinates":[10.850000,49.383333]},"type":"Feature","properties":{"hierarchy":["tgn:7110381","tgn:7003669","tgn:1000003","tgn:7000084","tgn:7029392"],"placetype":["aat:300008347"],"id":7110381,"name:xx":"Raitersaich"}}
>>>>>>> 03f74aca74312dbeaf24d7e61306dd6a786dc3d0
