<<<<<<< HEAD
{
  "id": 2335268,
  "type": "Feature",
  "properties": {
    "tgn:hierarchy":[
        "tgn:2335268",
        "tgn:1000001",
        "tgn:7012149",
        "tgn:7007707",
        "tgn:7029392"
    ],
    "tgn:id":2335268,
    "tgn:name":"Fort Gibson Lake",
    "tgn:placetype":[
        "aat:300006191"
    ]
},
  "bbox": [],
  "geometry": {"coordinates":[-95.2167,35.8667],"type":"Point"}
}
=======
{"geometry":{"type":"Point","coordinates":[-95.216700,35.866700]},"type":"Feature","properties":{"hierarchy":["tgn:2335268","tgn:1000001","tgn:7012149","tgn:7007707","tgn:7029392"],"placetype":["aat:300006191"],"id":2335268,"name:xx":"Fort Gibson Lake"}}
>>>>>>> 03f74aca74312dbeaf24d7e61306dd6a786dc3d0
