<<<<<<< HEAD
{
  "id": 7115552,
  "type": "Feature",
  "properties": {
    "tgn:hierarchy":[
        "tgn:7115552",
        "tgn:7003669",
        "tgn:1000003",
        "tgn:7000084",
        "tgn:7029392"
    ],
    "tgn:id":7115552,
    "tgn:name":"Oitzet",
    "tgn:placetype":[
        "aat:300000206"
    ]
},
  "bbox": [],
  "geometry": {"coordinates":[13.15,48.683333],"type":"Point"}
}
=======
{"geometry":{"type":"Point","coordinates":[13.150000,48.683333]},"type":"Feature","properties":{"hierarchy":["tgn:7115552","tgn:7003669","tgn:1000003","tgn:7000084","tgn:7029392"],"placetype":["aat:300000206"],"id":7115552,"name:xx":"Oitzet"}}
>>>>>>> 03f74aca74312dbeaf24d7e61306dd6a786dc3d0
