{
  "id": 2547088,
  "type": "Feature",
  "properties": {
    "tgn:hierarchy":[
        "tgn:2547088",
        "tgn:1000001",
        "tgn:7012149",
        "tgn:7007705",
        "tgn:7029392"
    ],
    "tgn:id":2547088,
    "tgn:name":"North Fork Prairie Dog Creek",
    "tgn:placetype":[
        "aat:300008706"
    ]
},
  "bbox": [],
  "geometry": {"coordinates":[-103.8167,47.3667],"type":"Point"}
}