{
  "id": 7587709,
  "type": "Feature",
  "properties": {
    "tgn:hierarchy":[
        "tgn:7587709",
        "tgn:1000004",
        "tgn:7000198",
        "tgn:7000799",
        "tgn:7029392"
    ],
    "tgn:id":7587709,
    "tgn:name:en":"Arampur",
    "tgn:placetype":[
        "aat:300008347"
    ]
},
  "bbox": [],
  "geometry": {"coordinates":[74.62045,34.129362],"type":"Point"}
}