{
  "id": 2688731,
  "type": "Feature",
  "properties": {
    "tgn:hierarchy":[
        "tgn:2688731",
        "tgn:1000001",
        "tgn:2000470",
        "tgn:7012149",
        "tgn:7007250",
        "tgn:7029392"
    ],
    "tgn:id":2688731,
    "tgn:name":"Spud Basin",
    "tgn:placetype":[
        "aat:300386845"
    ]
},
  "bbox": [],
  "geometry": {"coordinates":[-114.0333,44.4833],"type":"Point"}
}