{
  "id": 7395874,
  "type": "Feature",
  "properties": {
    "tgn:hierarchy":[
        "tgn:7395874",
        "tgn:7005583",
        "tgn:1000001",
        "tgn:7005560",
        "tgn:7029392"
    ],
    "tgn:id":7395874,
    "tgn:name":"San Juan",
    "tgn:placetype":[
        "aat:300008347"
    ]
},
  "bbox": [],
  "geometry": {"coordinates":[-104.483333,23.466667],"type":"Point"}
}