{
  "id": 7575718,
  "type": "Feature",
  "properties": {
    "tgn:hierarchy":[
        "tgn:7575718",
        "tgn:1000004",
        "tgn:7000198",
        "tgn:1001894",
        "tgn:7029392"
    ],
    "tgn:id":7575718,
    "tgn:name:en":"Kanhw\u0101ra",
    "tgn:placetype":[
        "aat:300008347"
    ]
},
  "bbox": [],
  "geometry": {"coordinates":[80.445792,23.923556],"type":"Point"}
}