{
  "id": 7084437,
  "type": "Feature",
  "properties": {
    "tgn:hierarchy":[
        "tgn:7084437",
        "tgn:1000003",
        "tgn:7000094",
        "tgn:7000084",
        "tgn:7029392"
    ],
    "tgn:id":7084437,
    "tgn:name":"Weitenhagen",
    "tgn:placetype":[
        "aat:300008347"
    ]
},
  "bbox": [],
  "geometry": {"coordinates":[12.783333,54.233333],"type":"Point"}
}