{
  "id": 2033309,
  "type": "Feature",
  "properties": {
    "tgn:hierarchy":[
        "tgn:2033309",
        "tgn:1000001",
        "tgn:7012149",
        "tgn:1002750",
        "tgn:7007252",
        "tgn:7029392"
    ],
    "tgn:id":2033309,
    "tgn:name":"Pine Valley",
    "tgn:placetype":[
        "aat:300008347",
        "aat:300387210"
    ]
},
  "bbox": [],
  "geometry": {"coordinates":[-86.45,38.4667],"type":"Point"}
}