{
  "id": 7415699,
  "type": "Feature",
  "properties": {
    "tgn:hierarchy":[
        "tgn:7415699",
        "tgn:1000001",
        "tgn:7005591",
        "tgn:7005560",
        "tgn:7029392"
    ],
    "tgn:id":7415699,
    "tgn:name:es":"La Laguna",
    "tgn:placetype":[
        "aat:300008347"
    ]
},
  "bbox": [],
  "geometry": {"coordinates":[-96.132778,16.998333],"type":"Point"}
}