{
  "id": 2555021,
  "type": "Feature",
  "properties": {
    "tgn:hierarchy":[
        "tgn:2555021",
        "tgn:1000001",
        "tgn:1002408",
        "tgn:7012149",
        "tgn:7007240",
        "tgn:7029392"
    ],
    "tgn:id":2555021,
    "tgn:name":"Observation Island",
    "tgn:placetype":[
        "aat:300008791"
    ]
},
  "bbox": [],
  "geometry": {"coordinates":[-80.95,26.8333],"type":"Point"}
}