{
  "id": 7221117,
  "type": "Feature",
  "properties": {
    "tgn:hierarchy":[
        "tgn:7221117",
        "tgn:7002725",
        "tgn:7002715",
        "tgn:1000003",
        "tgn:1000074",
        "tgn:7029392"
    ],
    "tgn:id":7221117,
    "tgn:name":"Nerof\u00e1goma R\u00e9ma",
    "tgn:placetype":[
        "aat:300008699"
    ]
},
  "bbox": [],
  "geometry": {"coordinates":[22.431667,41.108611],"type":"Point"}
}