{
  "id": 7515533,
  "type": "Feature",
  "properties": {
    "tgn:hierarchy":[
        "tgn:7515533",
        "tgn:7000509",
        "tgn:1008380",
        "tgn:1000226",
        "tgn:1000006",
        "tgn:7029392"
    ],
    "tgn:id":7515533,
    "tgn:name:en":"Omirinoko Stream",
    "tgn:placetype":[
        "aat:300008699"
    ]
},
  "bbox": [],
  "geometry": {"coordinates":[176.166667,-38.366667],"type":"Point"}
}