{
  "id": 1099385,
  "type": "Feature",
  "properties": {
    "tgn:hierarchy":[
        "tgn:1099385",
        "tgn:1007161",
        "tgn:7018511",
        "tgn:1000220",
        "tgn:1009774",
        "tgn:1000006",
        "tgn:7029392"
    ],
    "tgn:id":1099385,
    "tgn:name":"Gachpar",
    "tgn:placetype":[
        "aat:300008347"
    ]
},
  "bbox": [],
  "geometry": {"coordinates":[138.1667,9.55],"type":"Point"}
}