{
  "id": 1054756,
  "type": "Feature",
  "properties": {
    "tgn:hierarchy":[
        "tgn:1054756",
        "tgn:1000004",
        "tgn:7011509",
        "tgn:7002435",
        "tgn:7029392"
    ],
    "tgn:id":1054756,
    "tgn:name":"Yushkozero",
    "tgn:placetype":[
        "aat:300008347"
    ]
},
  "bbox": [],
  "geometry": {"coordinates":[32.05,64.75],"type":"Point"}
}