{
  "id": 7343355,
  "type": "Feature",
  "properties": {
    "tgn:hierarchy":[
        "tgn:7343355",
        "tgn:7002820",
        "tgn:7030216",
        "tgn:1000003",
        "tgn:1000095",
        "tgn:7029392"
    ],
    "tgn:id":7343355,
    "tgn:name":"Camprod\u00f3n",
    "tgn:placetype":[
        "aat:300008347"
    ]
},
  "bbox": [],
  "geometry": {"coordinates":[2.36524,42.313455],"type":"Point"}
}