<<<<<<< HEAD
{
  "id": 7474543,
  "type": "Feature",
  "properties": {
    "tgn:hierarchy":[
        "tgn:7474543",
        "tgn:7487020",
        "tgn:1000004",
        "tgn:1000141",
        "tgn:7029392"
    ],
    "tgn:id":7474543,
    "tgn:name":"Yonghe",
    "tgn:placetype":[
        "aat:300008347"
    ]
},
  "bbox": [],
  "geometry": {"coordinates":[120.926686,24.640232],"type":"Point"}
}
=======
{"geometry":{"type":"Point","coordinates":[120.926686,24.640232]},"type":"Feature","properties":{"hierarchy":["tgn:7474543","tgn:7487020","tgn:1000004","tgn:1000141","tgn:7029392"],"placetype":["aat:300008347"],"id":7474543,"name:xx":"Yonghe"}}
>>>>>>> 03f74aca74312dbeaf24d7e61306dd6a786dc3d0
