{
  "id": 7189984,
  "type": "Feature",
  "properties": {
    "tgn:hierarchy":[
        "tgn:7189984",
        "tgn:1000003",
        "tgn:7003677",
        "tgn:7000084",
        "tgn:7029392"
    ],
    "tgn:id":7189984,
    "tgn:name":"F\u00f6rsterei Einhang",
    "tgn:placetype":[
        "aat:300004792"
    ]
},
  "bbox": [],
  "geometry": {"coordinates":[6.716667,50.916667],"type":"Point"}
}