{
  "id": 1014583,
  "type": "Feature",
  "properties": {
    "tgn:hierarchy":[
        "tgn:1014583",
        "tgn:7005685",
        "tgn:1000001",
        "tgn:7013154",
        "tgn:7029392"
    ],
    "tgn:id":1014583,
    "tgn:name":"Beaverton",
    "tgn:placetype":[
        "aat:300008347"
    ]
},
  "bbox": [],
  "geometry": {"coordinates":[-79.1667,44.4167],"type":"Point"}
}