{
  "id": 7390264,
  "type": "Feature",
  "properties": {
    "tgn:hierarchy":[
        "tgn:7390264",
        "tgn:1000001",
        "tgn:7005597",
        "tgn:7005560",
        "tgn:7029392"
    ],
    "tgn:id":7390264,
    "tgn:name":"Rancho Jalape\u00f1o",
    "tgn:placetype":[
        "aat:300008347"
    ]
},
  "bbox": [],
  "geometry": {"coordinates":[-98.233333,25.816667],"type":"Point"}
}