{
  "id": 2636634,
  "type": "Feature",
  "properties": {
    "tgn:hierarchy":[
        "tgn:2636634",
        "tgn:7006450",
        "tgn:1000001",
        "tgn:7019674",
        "tgn:7012149",
        "tgn:7029392"
    ],
    "tgn:id":2636634,
    "tgn:name":"Sage Hill",
    "tgn:placetype":[
        "aat:300008798"
    ]
},
  "bbox": [],
  "geometry": {"coordinates":[-147.5167,64.85],"type":"Point"}
}