{
  "id": 1082991,
  "type": "Feature",
  "properties": {
    "tgn:hierarchy":[
        "tgn:1082991",
        "tgn:7000317",
        "tgn:1000004",
        "tgn:7016759",
        "tgn:1000128",
        "tgn:7029392"
    ],
    "tgn:id":1082991,
    "tgn:name":"Temerloh",
    "tgn:placetype":[
        "aat:300008347"
    ]
},
  "bbox": [],
  "geometry": {"coordinates":[102.4167,3.4667],"type":"Point"}
}