{
  "id": 2561832,
  "type": "Feature",
  "properties": {
    "tgn:hierarchy":[
        "tgn:2561832",
        "tgn:1000001",
        "tgn:2001941",
        "tgn:7012149",
        "tgn:7007826",
        "tgn:7029392"
    ],
    "tgn:id":2561832,
    "tgn:name":"Otis Ridge",
    "tgn:placetype":[
        "aat:300266640"
    ]
},
  "bbox": [],
  "geometry": {"coordinates":[-98.55,29.6667],"type":"Point"}
}