{
  "id": 2770110,
  "type": "Feature",
  "properties": {
    "tgn:hierarchy":[
        "tgn:2770110",
        "tgn:7002659",
        "tgn:1000001",
        "tgn:7012149",
        "tgn:2000026",
        "tgn:7029392"
    ],
    "tgn:id":2770110,
    "tgn:name":"Wild Branch",
    "tgn:placetype":[
        "aat:300008699"
    ]
},
  "bbox": [],
  "geometry": {"coordinates":[-87.25,31.1167],"type":"Point"}
}