{
  "id": 2738726,
  "type": "Feature",
  "properties": {
    "tgn:hierarchy":[
        "tgn:2738726",
        "tgn:1000001",
        "tgn:7012149",
        "tgn:2001276",
        "tgn:7007524",
        "tgn:7029392"
    ],
    "tgn:id":2738726,
    "tgn:name":"Union Creek",
    "tgn:placetype":[
        "aat:300008706"
    ]
},
  "bbox": [],
  "geometry": {"coordinates":[-107.4833,47.2167],"type":"Point"}
}