{
  "id": 7390724,
  "type": "Feature",
  "properties": {
    "tgn:hierarchy":[
        "tgn:7390724",
        "tgn:7005586",
        "tgn:1000001",
        "tgn:7005560",
        "tgn:7029392"
    ],
    "tgn:id":7390724,
    "tgn:name":"R\u00edo Caliente",
    "tgn:placetype":[
        "aat:300000241"
    ]
},
  "bbox": [],
  "geometry": {"coordinates":[-103.566667,20.683333],"type":"Point"}
}