{
  "id": 2291436,
  "type": "Feature",
  "properties": {
    "tgn:hierarchy":[
        "tgn:2291436",
        "tgn:7002659",
        "tgn:1000001",
        "tgn:7012149",
        "tgn:2000035",
        "tgn:7029392"
    ],
    "tgn:id":2291436,
    "tgn:name":"Dolberry Hollow",
    "tgn:placetype":[
        "aat:300008761"
    ]
},
  "bbox": [],
  "geometry": {"coordinates":[-86.0333,34.8333],"type":"Point"}
}