{
  "id": 7416270,
  "type": "Feature",
  "properties": {
    "tgn:hierarchy":[
        "tgn:7416270",
        "tgn:7005584",
        "tgn:1000001",
        "tgn:7005560",
        "tgn:7029392"
    ],
    "tgn:id":7416270,
    "tgn:name":"Las Coloradas",
    "tgn:placetype":[
        "aat:300008347"
    ]
},
  "bbox": [],
  "geometry": {"coordinates":[-101.718611,20.773333],"type":"Point"}
}