{
  "id": 2171710,
  "type": "Feature",
  "properties": {
    "tgn:hierarchy":[
        "tgn:2171710",
        "tgn:1000001",
        "tgn:7012149",
        "tgn:2000476",
        "tgn:7007250",
        "tgn:7029392"
    ],
    "tgn:id":2171710,
    "tgn:name":"Big Tinker Creek",
    "tgn:placetype":[
        "aat:300008706"
    ]
},
  "bbox": [],
  "geometry": {"coordinates":[-115.7833,46.0833],"type":"Point"}
}