{
  "id": 2547746,
  "type": "Feature",
  "properties": {
    "tgn:hierarchy":[
        "tgn:2547746",
        "tgn:1000001",
        "tgn:7012149",
        "tgn:7007920",
        "tgn:7029392"
    ],
    "tgn:id":2547746,
    "tgn:name":"North Fork Wenas Creek",
    "tgn:placetype":[
        "aat:300008706"
    ]
},
  "bbox": [],
  "geometry": {"coordinates":[-120.95,46.9833],"type":"Point"}
}