{
  "id": 2680949,
  "type": "Feature",
  "properties": {
    "tgn:hierarchy":[
        "tgn:2680949",
        "tgn:1000001",
        "tgn:7012149",
        "tgn:2001962",
        "tgn:7007826",
        "tgn:7029392"
    ],
    "tgn:id":2680949,
    "tgn:name":"South Leon River",
    "tgn:placetype":[
        "aat:300008707"
    ]
},
  "bbox": [],
  "geometry": {"coordinates":[-98.6333,31.7333],"type":"Point"}
}