{
  "id": 2782366,
  "type": "Feature",
  "properties": {
    "tgn:hierarchy":[
        "tgn:2782366",
        "tgn:1000001",
        "tgn:7012149",
        "tgn:2002176",
        "tgn:7007919",
        "tgn:7029392"
    ],
    "tgn:id":2782366,
    "tgn:name":"Woody Creek",
    "tgn:placetype":[
        "aat:300008706"
    ]
},
  "bbox": [],
  "geometry": {"coordinates":[-78.0667,37.1333],"type":"Point"}
}