<<<<<<< HEAD
{
  "id": 7240349,
  "type": "Feature",
  "properties": {
    "tgn:hierarchy":[
        "tgn:7240349",
        "tgn:7007877",
        "tgn:1000003",
        "tgn:1000063",
        "tgn:4012014",
        "tgn:7029392"
    ],
    "tgn:id":7240349,
    "tgn:name":"Ch\u00e2teau d' En Haut",
    "tgn:placetype":[
        "aat:300005567"
    ]
},
  "bbox": [],
  "geometry": {"coordinates":[4.183333,50.566667],"type":"Point"}
}
=======
{"geometry":{"type":"Point","coordinates":[4.183333,50.566667]},"type":"Feature","properties":{"hierarchy":["tgn:7240349","tgn:7007877","tgn:1000003","tgn:1000063","tgn:4012014","tgn:7029392"],"placetype":["aat:300005567"],"id":7240349,"name:xx":"Ch\u00e2teau d' En Haut"}}
>>>>>>> 03f74aca74312dbeaf24d7e61306dd6a786dc3d0
