<<<<<<< HEAD
{
  "id": 7113601,
  "type": "Feature",
  "properties": {
    "tgn:hierarchy":[
        "tgn:7113601",
        "tgn:1000003",
        "tgn:7003689",
        "tgn:7000084",
        "tgn:7029392"
    ],
    "tgn:id":7113601,
    "tgn:name":"Rosa-Luxemburg Siedlung",
    "tgn:placetype":[
        "aat:300008347"
    ]
},
  "bbox": [],
  "geometry": {"coordinates":[11.333333,51.016667],"type":"Point"}
}
=======
{"geometry":{"type":"Point","coordinates":[11.333333,51.016667]},"type":"Feature","properties":{"hierarchy":["tgn:7113601","tgn:1000003","tgn:7003689","tgn:7000084","tgn:7029392"],"placetype":["aat:300008347"],"id":7113601,"name:xx":"Rosa-Luxemburg Siedlung"}}
>>>>>>> 03f74aca74312dbeaf24d7e61306dd6a786dc3d0
