{
  "id": 7341868,
  "type": "Feature",
  "properties": {
    "tgn:hierarchy":[
        "tgn:7341868",
        "tgn:7002760",
        "tgn:1000003",
        "tgn:1000095",
        "tgn:7029392"
    ],
    "tgn:id":7341868,
    "tgn:name":"Bodia",
    "tgn:placetype":[
        "aat:300008347"
    ]
},
  "bbox": [],
  "geometry": {"coordinates":[-4.666667,43.15],"type":"Point"}
}