{
  "id": 2695711,
  "type": "Feature",
  "properties": {
    "tgn:hierarchy":[
        "tgn:2695711",
        "tgn:2001464",
        "tgn:1000001",
        "tgn:7012149",
        "tgn:7007709",
        "tgn:7029392"
    ],
    "tgn:id":2695711,
    "tgn:name":"Stirewalt Creek",
    "tgn:placetype":[
        "aat:300008706"
    ]
},
  "bbox": [],
  "geometry": {"coordinates":[-81.1667,35.9167],"type":"Point"}
}