{
  "id": 7282832,
  "type": "Feature",
  "properties": {
    "tgn:hierarchy":[
        "tgn:7282832",
        "tgn:1001702",
        "tgn:1000049",
        "tgn:1000002",
        "tgn:7029392"
    ],
    "tgn:id":7282832,
    "tgn:name":"Peligrosa, Punta",
    "tgn:placetype":[
        "aat:300386846"
    ]
},
  "bbox": [],
  "geometry": {"coordinates":[-73.616667,-52.283333],"type":"Point"}
}