{
  "id": 2560004,
  "type": "Feature",
  "properties": {
    "tgn:hierarchy":[
        "tgn:2560004",
        "tgn:1000001",
        "tgn:1002210",
        "tgn:7012149",
        "tgn:7007706",
        "tgn:7029392"
    ],
    "tgn:id":2560004,
    "tgn:name":"Opossum Run",
    "tgn:placetype":[
        "aat:300008699"
    ]
},
  "bbox": [],
  "geometry": {"coordinates":[-83.8833,38.85],"type":"Point"}
}