{
  "id": 7321897,
  "type": "Feature",
  "properties": {
    "tgn:hierarchy":[
        "tgn:7321897",
        "tgn:7002464",
        "tgn:1000049",
        "tgn:1000002",
        "tgn:7029392"
    ],
    "tgn:id":7321897,
    "tgn:name":"Caleta Buena",
    "tgn:placetype":[
        "aat:300008057"
    ]
},
  "bbox": [],
  "geometry": {"coordinates":[-70.15,-19.883333],"type":"Point"}
}