{
  "id": 2329287,
  "type": "Feature",
  "properties": {
    "tgn:hierarchy":[
        "tgn:2329287",
        "tgn:2000919",
        "tgn:1000001",
        "tgn:7012149",
        "tgn:7007515",
        "tgn:7029392"
    ],
    "tgn:id":2329287,
    "tgn:name":"Five Finger Brook",
    "tgn:placetype":[
        "aat:300008699"
    ]
},
  "bbox": [],
  "geometry": {"coordinates":[-69.0667,46.7833],"type":"Point"}
}