{
  "id": 2388728,
  "type": "Feature",
  "properties": {
    "tgn:hierarchy":[
        "tgn:2388728",
        "tgn:1000001",
        "tgn:2001419",
        "tgn:7012149",
        "tgn:7007526",
        "tgn:7029392"
    ],
    "tgn:id":2388728,
    "tgn:name":"Hidden Canyon",
    "tgn:placetype":[
        "aat:300008761"
    ]
},
  "bbox": [],
  "geometry": {"coordinates":[-117.8667,40.7333],"type":"Point"}
}