{
  "id": 7255208,
  "type": "Feature",
  "properties": {
    "tgn:hierarchy":[
        "tgn:7255208",
        "tgn:7003456",
        "tgn:1000003",
        "tgn:1000063",
        "tgn:7018236",
        "tgn:7029392"
    ],
    "tgn:id":7255208,
    "tgn:name":"Rivierenhof",
    "tgn:placetype":[
        "aat:300008347"
    ]
},
  "bbox": [],
  "geometry": {"coordinates":[4.466667,51.216667],"type":"Point"}
}