{
  "id": 7330198,
  "type": "Feature",
  "properties": {
    "tgn:hierarchy":[
        "tgn:7330198",
        "tgn:7002813",
        "tgn:7002758",
        "tgn:1000003",
        "tgn:1000095",
        "tgn:7029392"
    ],
    "tgn:id":7330198,
    "tgn:name":"Hornillo, Arroyo del",
    "tgn:placetype":[
        "aat:300266554",
        "aat:300008699"
    ]
},
  "bbox": [],
  "geometry": {"coordinates":[-5.65,36.783333],"type":"Point"}
}