{
  "id": 2565655,
  "type": "Feature",
  "properties": {
    "tgn:hierarchy":[
        "tgn:2565655",
        "tgn:1000001",
        "tgn:7012149",
        "tgn:2001210",
        "tgn:7007523",
        "tgn:7029392"
    ],
    "tgn:id":2565655,
    "tgn:name":"Pajastka, Lake",
    "tgn:placetype":[
        "aat:300006191"
    ]
},
  "bbox": [],
  "geometry": {"coordinates":[-93.7167,38.8667],"type":"Point"}
}