{
  "id": 2407766,
  "type": "Feature",
  "properties": {
    "tgn:hierarchy":[
        "tgn:2407766",
        "tgn:7002659",
        "tgn:1000001",
        "tgn:7012149",
        "tgn:2000049",
        "tgn:7029392"
    ],
    "tgn:id":2407766,
    "tgn:name":"Hurricane Branch",
    "tgn:placetype":[
        "aat:300008699"
    ]
},
  "bbox": [],
  "geometry": {"coordinates":[-87.4667,31.3167],"type":"Point"}
}