{
  "id": 2031596,
  "type": "Feature",
  "properties": {
    "tgn:hierarchy":[
        "tgn:2031596",
        "tgn:1000001",
        "tgn:7012149",
        "tgn:2000548",
        "tgn:7007252",
        "tgn:7029392"
    ],
    "tgn:id":2031596,
    "tgn:name":"Denmark",
    "tgn:placetype":[
        "aat:300008347",
        "aat:300387210"
    ]
},
  "bbox": [],
  "geometry": {"coordinates":[-87.0167,39.2667],"type":"Point"}
}