{
  "id": 7007278,
  "type": "Feature",
  "properties": {
    "tgn:hierarchy":[
        "tgn:7007278",
        "tgn:7003745",
        "tgn:1000003",
        "tgn:7011731",
        "tgn:7029392"
    ],
    "tgn:id":7007278,
    "tgn:name":"Fribourg",
    "tgn:placetype":[
        "aat:300008347",
        "aat:300387220",
        "aat:300008375"
    ]
},
  "bbox": [],
  "geometry": {"coordinates":[7.1667,46.8333],"type":"Point"}
}