{
  "id": 1104738,
  "type": "Feature",
  "properties": {
    "tgn:hierarchy":[
        "tgn:1104738",
        "tgn:1000003",
        "tgn:1000077",
        "tgn:7029392"
    ],
    "tgn:id":1104738,
    "tgn:name":"Gr\u00edmsv\u00f6tn",
    "tgn:placetype":[
        "aat:300387060",
        "aat:300008795"
    ]
},
  "bbox": [],
  "geometry": {"coordinates":[-17.339928,64.413146],"type":"Point"}
}