{
  "id": 2575055,
  "type": "Feature",
  "properties": {
    "tgn:hierarchy":[
        "tgn:2575055",
        "tgn:1000001",
        "tgn:7012149",
        "tgn:1002789",
        "tgn:7007710",
        "tgn:7029392"
    ],
    "tgn:id":2575055,
    "tgn:name":"Pennel Run Natural Area",
    "tgn:placetype":[
        "aat:300055621"
    ]
},
  "bbox": [],
  "geometry": {"coordinates":[-75.1333,41.1667],"type":"Point"}
}