{
  "id": 7007592,
  "type": "Feature",
  "properties": {
    "tgn:hierarchy":[
        "tgn:7007592",
        "tgn:1000003",
        "tgn:7024121",
        "tgn:7006366",
        "tgn:7029392"
    ],
    "tgn:id":7007592,
    "tgn:name":"Zyrard\u00f3w",
    "tgn:placetype":[
        "aat:300008347"
    ]
},
  "bbox": [],
  "geometry": {"coordinates":[20.4667,52.0333],"type":"Point"}
}