{
  "id": 2550086,
  "type": "Feature",
  "properties": {
    "tgn:hierarchy":[
        "tgn:2550086",
        "tgn:1000001",
        "tgn:7012149",
        "tgn:2001867",
        "tgn:7007825",
        "tgn:7029392"
    ],
    "tgn:id":2550086,
    "tgn:name":"Northcutt Cave",
    "tgn:placetype":[
        "aat:300008746"
    ]
},
  "bbox": [],
  "geometry": {"coordinates":[-85.75,35.4833],"type":"Point"}
}