{
  "id": 2379690,
  "type": "Feature",
  "properties": {
    "tgn:hierarchy":[
        "tgn:2379690",
        "tgn:1000001",
        "tgn:7012149",
        "tgn:2000888",
        "tgn:7007256",
        "tgn:7029392"
    ],
    "tgn:id":2379690,
    "tgn:name":"Haskin Creek",
    "tgn:placetype":[
        "aat:300008706"
    ]
},
  "bbox": [],
  "geometry": {"coordinates":[-93.4333,31.75],"type":"Point"}
}