{
  "id": 2374635,
  "type": "Feature",
  "properties": {
    "tgn:hierarchy":[
        "tgn:2374635",
        "tgn:1000001",
        "tgn:7012149",
        "tgn:1002596",
        "tgn:7007706",
        "tgn:7029392"
    ],
    "tgn:id":2374635,
    "tgn:name":"Hancock Pond",
    "tgn:placetype":[
        "aat:300008680"
    ]
},
  "bbox": [],
  "geometry": {"coordinates":[-82.5667,39.9833],"type":"Point"}
}