{
  "id": 7097099,
  "type": "Feature",
  "properties": {
    "tgn:hierarchy":[
        "tgn:7097099",
        "tgn:7003669",
        "tgn:1000003",
        "tgn:7000084",
        "tgn:7029392"
    ],
    "tgn:id":7097099,
    "tgn:name":"Sixtnitgern",
    "tgn:placetype":[
        "aat:300008347"
    ]
},
  "bbox": [],
  "geometry": {"coordinates":[11.216667,48.333333],"type":"Point"}
}