{
  "id": 2146014,
  "type": "Feature",
  "properties": {
    "tgn:hierarchy":[
        "tgn:2146014",
        "tgn:1000001",
        "tgn:7012149",
        "tgn:2001131",
        "tgn:7007522",
        "tgn:7029392"
    ],
    "tgn:id":2146014,
    "tgn:name":"Ball Mill Creek",
    "tgn:placetype":[
        "aat:300008706"
    ]
},
  "bbox": [],
  "geometry": {"coordinates":[-89.85,31.1167],"type":"Point"}
}