{
  "id": 1134091,
  "type": "Feature",
  "properties": {
    "tgn:hierarchy":[
        "tgn:1134091",
        "tgn:1000003",
        "tgn:7003677",
        "tgn:7000084",
        "tgn:7029392"
    ],
    "tgn:id":1134091,
    "tgn:name":"Paasbach",
    "tgn:placetype":[
        "aat:300008706"
    ]
},
  "bbox": [],
  "geometry": {"coordinates":[7.1833,51.4167],"type":"Point"}
}