{
  "id": 2445558,
  "type": "Feature",
  "properties": {
    "tgn:hierarchy":[
        "tgn:2445558",
        "tgn:1000001",
        "tgn:7012149",
        "tgn:2002374",
        "tgn:7007923",
        "tgn:7029392"
    ],
    "tgn:id":2445558,
    "tgn:name":"Leon Draw",
    "tgn:placetype":[
        "aat:300008761"
    ]
},
  "bbox": [],
  "geometry": {"coordinates":[-106.7167,43.6667],"type":"Point"}
}