{
  "id": 1076623,
  "type": "Feature",
  "properties": {
    "tgn:hierarchy":[
        "tgn:1076623",
        "tgn:1001828",
        "tgn:1000004",
        "tgn:7000198",
        "tgn:7029392"
    ],
    "tgn:id":1076623,
    "tgn:name:en":"Ponn\u016bru",
    "tgn:placetype":[
        "aat:300008347"
    ]
},
  "bbox": [],
  "geometry": {"coordinates":[80.5667,16.0667],"type":"Point"}
}