{
  "id": 7529073,
  "type": "Feature",
  "properties": {
    "tgn:hierarchy":[
        "tgn:7529073",
        "tgn:7001242",
        "tgn:7016833",
        "tgn:1001113",
        "tgn:7029392"
    ],
    "tgn:id":7529073,
    "tgn:name":"Tur'at al Mash\u0101'lah",
    "tgn:placetype":[
        "aat:300006075"
    ]
},
  "bbox": [],
  "geometry": {"coordinates":[31.70658,30.75018],"type":"Point"}
}