{
  "id": 2245264,
  "type": "Feature",
  "properties": {
    "tgn:hierarchy":[
        "tgn:2245264",
        "tgn:1000001",
        "tgn:2001653",
        "tgn:7012149",
        "tgn:7007707",
        "tgn:7029392"
    ],
    "tgn:id":2245264,
    "tgn:name":"Club Lake",
    "tgn:placetype":[
        "aat:300008680"
    ]
},
  "bbox": [],
  "geometry": {"coordinates":[-95.0833,35.2833],"type":"Point"}
}