{
  "id": 1072490,
  "type": "Feature",
  "properties": {
    "tgn:hierarchy":[
        "tgn:1072490",
        "tgn:1000004",
        "tgn:7002081",
        "tgn:1000111",
        "tgn:7029392"
    ],
    "tgn:id":1072490,
    "tgn:name":"Wangxiangshang",
    "tgn:placetype":[
        "aat:300008347"
    ]
},
  "bbox": [],
  "geometry": {"coordinates":[120.25,31.4833],"type":"Point"}
}