{
  "id": 7190997,
  "type": "Feature",
  "properties": {
    "tgn:hierarchy":[
        "tgn:7190997",
        "tgn:7003669",
        "tgn:1000003",
        "tgn:7000084",
        "tgn:7029392"
    ],
    "tgn:id":7190997,
    "tgn:name":"Fechheimer Berg",
    "tgn:placetype":[
        "aat:300008777"
    ]
},
  "bbox": [],
  "geometry": {"coordinates":[11.116667,50.283333],"type":"Point"}
}