<<<<<<< HEAD
{
  "id": 2405313,
  "type": "Feature",
  "properties": {
    "tgn:hierarchy":[
        "tgn:2405313",
        "tgn:1000001",
        "tgn:7012149",
        "tgn:2000992",
        "tgn:7007520",
        "tgn:7029392"
    ],
    "tgn:id":2405313,
    "tgn:name":"Huffman Drain",
    "tgn:placetype":[
        "aat:300006075"
    ]
},
  "bbox": [],
  "geometry": {"coordinates":[-84.0833,43.4333],"type":"Point"}
}
=======
{"geometry":{"type":"Point","coordinates":[-84.083300,43.433300]},"type":"Feature","properties":{"hierarchy":["tgn:2405313","tgn:1000001","tgn:7012149","tgn:2000992","tgn:7007520","tgn:7029392"],"placetype":["aat:300006075"],"id":2405313,"name:xx":"Huffman Drain"}}
>>>>>>> 03f74aca74312dbeaf24d7e61306dd6a786dc3d0
