{
  "id": 7232026,
  "type": "Feature",
  "properties": {
    "tgn:hierarchy":[
        "tgn:7232026",
        "tgn:7011270",
        "tgn:7002674",
        "tgn:1000003",
        "tgn:1000074",
        "tgn:7029392"
    ],
    "tgn:id":7232026,
    "tgn:name":"K\u00e9ndarkhos",
    "tgn:placetype":[
        "aat:300008347"
    ]
},
  "bbox": [],
  "geometry": {"coordinates":[24.516667,37.183333],"type":"Point"}
}