{
  "id": 2237195,
  "type": "Feature",
  "properties": {
    "tgn:hierarchy":[
        "tgn:2237195",
        "tgn:1000001",
        "tgn:7012149",
        "tgn:1003042",
        "tgn:7007920",
        "tgn:7029392"
    ],
    "tgn:id":2237195,
    "tgn:name":"Chimney Peaks",
    "tgn:placetype":[
        "aat:300008798"
    ]
},
  "bbox": [],
  "geometry": {"coordinates":[-121.0667,46.6333],"type":"Point"}
}