{
  "id": 2004793,
  "type": "Feature",
  "properties": {
    "tgn:hierarchy":[
        "tgn:2004793",
        "tgn:2000001",
        "tgn:7002659",
        "tgn:1000001",
        "tgn:7012149",
        "tgn:7029392"
    ],
    "tgn:id":2004793,
    "tgn:name":"Orange Beach",
    "tgn:placetype":[
        "aat:300008347"
    ]
},
  "bbox": [],
  "geometry": {"coordinates":[-87.5667,30.2833],"type":"Point"}
}