{
  "id": 7348873,
  "type": "Feature",
  "properties": {
    "tgn:hierarchy":[
        "tgn:7348873",
        "tgn:7005581",
        "tgn:1000001",
        "tgn:7005560",
        "tgn:7029392"
    ],
    "tgn:id":7348873,
    "tgn:name":"Alamo, Arroyo del",
    "tgn:placetype":[
        "aat:300008699"
    ]
},
  "bbox": [],
  "geometry": {"coordinates":[-106.766667,27.95],"type":"Point"}
}