{
  "id": 2582140,
  "type": "Feature",
  "properties": {
    "tgn:hierarchy":[
        "tgn:2582140",
        "tgn:1000001",
        "tgn:7012149",
        "tgn:2000481",
        "tgn:7007250",
        "tgn:7029392"
    ],
    "tgn:id":2582140,
    "tgn:name":"Pine Creek",
    "tgn:placetype":[
        "aat:300008706"
    ]
},
  "bbox": [],
  "geometry": {"coordinates":[-114.1333,45.2833],"type":"Point"}
}