{
  "id": 7387913,
  "type": "Feature",
  "properties": {
    "tgn:hierarchy":[
        "tgn:7387913",
        "tgn:7016644",
        "tgn:1000001",
        "tgn:7005560",
        "tgn:7029392"
    ],
    "tgn:id":7387913,
    "tgn:name":"Picila",
    "tgn:placetype":[
        "aat:300008347"
    ]
},
  "bbox": [],
  "geometry": {"coordinates":[-103.683333,19.166667],"type":"Point"}
}