{
  "id": 7237756,
  "type": "Feature",
  "properties": {
    "tgn:hierarchy":[
        "tgn:7237756",
        "tgn:7003456",
        "tgn:1000003",
        "tgn:1000063",
        "tgn:7018236",
        "tgn:7029392"
    ],
    "tgn:id":7237756,
    "tgn:name":"Goorheide",
    "tgn:placetype":[
        "aat:300008347"
    ]
},
  "bbox": [],
  "geometry": {"coordinates":[4.840334,51.091101],"type":"Point"}
}