{
  "id": 2731598,
  "type": "Feature",
  "properties": {
    "tgn:hierarchy":[
        "tgn:2731598",
        "tgn:1000001",
        "tgn:7012149",
        "tgn:7007920",
        "tgn:7029392"
    ],
    "tgn:id":2731598,
    "tgn:name":"Tule Prong",
    "tgn:placetype":[
        "aat:300008761"
    ]
},
  "bbox": [],
  "geometry": {"coordinates":[-120.0667,46.05],"type":"Point"}
}