<<<<<<< HEAD
{
  "id": 2764319,
  "type": "Feature",
  "properties": {
    "tgn:hierarchy":[
        "tgn:2764319",
        "tgn:1000001",
        "tgn:7012149",
        "tgn:7007827",
        "tgn:7029392"
    ],
    "tgn:id":2764319,
    "tgn:name":"Whetrock Canyon",
    "tgn:placetype":[
        "aat:300008761"
    ]
},
  "bbox": [],
  "geometry": {"coordinates":[-109.35,39.4167],"type":"Point"}
}
=======
{"geometry":{"type":"Point","coordinates":[-109.350000,39.416700]},"type":"Feature","properties":{"hierarchy":["tgn:2764319","tgn:1000001","tgn:7012149","tgn:7007827","tgn:7029392"],"placetype":["aat:300008761"],"id":2764319,"name:xx":"Whetrock Canyon"}}
>>>>>>> 03f74aca74312dbeaf24d7e61306dd6a786dc3d0
