{
  "id": 7293831,
  "type": "Feature",
  "properties": {
    "tgn:hierarchy":[
        "tgn:7293831",
        "tgn:7008912",
        "tgn:7030216",
        "tgn:1000003",
        "tgn:1000095",
        "tgn:7029392"
    ],
    "tgn:id":7293831,
    "tgn:name":"Vilanoveta",
    "tgn:placetype":[
        "aat:300008347"
    ]
},
  "bbox": [],
  "geometry": {"coordinates":[0.64308,41.603988],"type":"Point"}
}