{
  "id": 7252104,
  "type": "Feature",
  "properties": {
    "tgn:hierarchy":[
        "tgn:7252104",
        "tgn:7003460",
        "tgn:1000003",
        "tgn:1000063",
        "tgn:4012014",
        "tgn:7029392"
    ],
    "tgn:id":7252104,
    "tgn:name":"Merols",
    "tgn:placetype":[
        "aat:300008347"
    ]
},
  "bbox": [],
  "geometry": {"coordinates":[6.066667,50.666667],"type":"Point"}
}