{
  "id": 2524244,
  "type": "Feature",
  "properties": {
    "tgn:hierarchy":[
        "tgn:2524244",
        "tgn:1000001",
        "tgn:1002242",
        "tgn:7012149",
        "tgn:7007252",
        "tgn:7029392"
    ],
    "tgn:id":2524244,
    "tgn:name":"Morgan Hill",
    "tgn:placetype":[
        "aat:300008798"
    ]
},
  "bbox": [],
  "geometry": {"coordinates":[-86.3333,40.7167],"type":"Point"}
}