{
  "id": 2392757,
  "type": "Feature",
  "properties": {
    "tgn:hierarchy":[
        "tgn:2392757",
        "tgn:1000001",
        "tgn:7012149",
        "tgn:2001538",
        "tgn:7007709",
        "tgn:7029392"
    ],
    "tgn:id":2392757,
    "tgn:name":"Hobbs Crossroads",
    "tgn:placetype":[
        "aat:300008347"
    ]
},
  "bbox": [],
  "geometry": {"coordinates":[-78.3167,35.1667],"type":"Point"}
}