{
  "id": 2673012,
  "type": "Feature",
  "properties": {
    "tgn:hierarchy":[
        "tgn:2673012",
        "tgn:1000001",
        "tgn:7012149",
        "tgn:2001437",
        "tgn:7007566",
        "tgn:7029392"
    ],
    "tgn:id":2673012,
    "tgn:name":"Snake Hill",
    "tgn:placetype":[
        "aat:300008798"
    ]
},
  "bbox": [],
  "geometry": {"coordinates":[-108.15,32.7833],"type":"Point"}
}