<<<<<<< HEAD
{
  "id": 7373891,
  "type": "Feature",
  "properties": {
    "tgn:hierarchy":[
        "tgn:7373891",
        "tgn:1000001",
        "tgn:7005595",
        "tgn:7005560",
        "tgn:7029392"
    ],
    "tgn:id":7373891,
    "tgn:name":"La Bandera, Puerto",
    "tgn:placetype":[
        "aat:300259572"
    ]
},
  "bbox": [],
  "geometry": {"coordinates":[-108.65,26.133333],"type":"Point"}
}
=======
{"geometry":{"type":"Point","coordinates":[-108.650000,26.133333]},"type":"Feature","properties":{"hierarchy":["tgn:7373891","tgn:1000001","tgn:7005595","tgn:7005560","tgn:7029392"],"placetype":["aat:300259572"],"id":7373891,"name:xx":"La Bandera, Puerto"}}
>>>>>>> 03f74aca74312dbeaf24d7e61306dd6a786dc3d0
