{
  "id": 2620663,
  "type": "Feature",
  "properties": {
    "tgn:hierarchy":[
        "tgn:2620663",
        "tgn:1000001",
        "tgn:7012149",
        "tgn:2001930",
        "tgn:7007825",
        "tgn:7029392"
    ],
    "tgn:id":2620663,
    "tgn:name":"Riverside Branch",
    "tgn:placetype":[
        "aat:300008699"
    ]
},
  "bbox": [],
  "geometry": {"coordinates":[-86.8167,35.9167],"type":"Point"}
}