{
  "id": 7342426,
  "type": "Feature",
  "properties": {
    "tgn:hierarchy":[
        "tgn:7342426",
        "tgn:7002824",
        "tgn:1000003",
        "tgn:7002786",
        "tgn:1000095",
        "tgn:7029392"
    ],
    "tgn:id":7342426,
    "tgn:name":"Canduas",
    "tgn:placetype":[
        "aat:300008347"
    ]
},
  "bbox": [],
  "geometry": {"coordinates":[-8.983333,43.216667],"type":"Point"}
}