{
  "id": 2771957,
  "type": "Feature",
  "properties": {
    "tgn:hierarchy":[
        "tgn:2771957",
        "tgn:1000001",
        "tgn:7006451",
        "tgn:2000092",
        "tgn:7012149",
        "tgn:7029392"
    ],
    "tgn:id":2771957,
    "tgn:name":"Wilkins Canyon",
    "tgn:placetype":[
        "aat:300008761"
    ]
},
  "bbox": [],
  "geometry": {"coordinates":[-111.05,34.4833],"type":"Point"}
}