{
  "id": 2690678,
  "type": "Feature",
  "properties": {
    "tgn:hierarchy":[
        "tgn:2690678",
        "tgn:1000001",
        "tgn:7012149",
        "tgn:2001714",
        "tgn:7007708",
        "tgn:7029392"
    ],
    "tgn:id":2690678,
    "tgn:name":"Stan H Spring",
    "tgn:placetype":[
        "aat:300008697"
    ]
},
  "bbox": [],
  "geometry": {"coordinates":[-121.1333,42.2167],"type":"Point"}
}