{
  "id": 2214732,
  "type": "Feature",
  "properties": {
    "tgn:hierarchy":[
        "tgn:2214732",
        "tgn:1000001",
        "tgn:7012149",
        "tgn:7007524",
        "tgn:7029392"
    ],
    "tgn:id":2214732,
    "tgn:name":"Calf Creek",
    "tgn:placetype":[
        "aat:300008706"
    ]
},
  "bbox": [],
  "geometry": {"coordinates":[-113.1167,47.3167],"type":"Point"}
}