{
  "id": 2515309,
  "type": "Feature",
  "properties": {
    "tgn:hierarchy":[
        "tgn:2515309",
        "tgn:1000001",
        "tgn:7012149",
        "tgn:2001750",
        "tgn:7007712",
        "tgn:7029392"
    ],
    "tgn:id":2515309,
    "tgn:name":"Milliken Cove",
    "tgn:placetype":[
        "aat:300132316"
    ]
},
  "bbox": [],
  "geometry": {"coordinates":[-78.5667,33.8833],"type":"Point"}
}