{
  "id": 1067062,
  "type": "Feature",
  "properties": {
    "tgn:hierarchy":[
        "tgn:1067062",
        "tgn:1000956",
        "tgn:1000004",
        "tgn:1000111",
        "tgn:7029392"
    ],
    "tgn:id":1067062,
    "tgn:name":"Changdian",
    "tgn:placetype":[
        "aat:300008347"
    ]
},
  "bbox": [],
  "geometry": {"coordinates":[116.5333,40.0167],"type":"Point"}
}