<<<<<<< HEAD
{
  "id": 7025109,
  "type": "Feature",
  "properties": {
    "tgn:hierarchy":[
        "tgn:7025109",
        "tgn:7002445",
        "tgn:7008104",
        "tgn:1000003",
        "tgn:7008591",
        "tgn:7029392"
    ],
    "tgn:id":7025109,
    "tgn:name:ang":"Tochingeuuiche",
    "tgn:placetype":[
        "aat:300008347"
    ]
},
  "bbox": [],
  "geometry": {"coordinates":[-1.0167,51.85],"type":"Point"}
}
=======
{"geometry":{"type":"Point","coordinates":[-1.016700,51.850000]},"type":"Feature","properties":{"hierarchy":["tgn:7025109","tgn:7002445","tgn:7008104","tgn:1000003","tgn:7008591","tgn:7029392"],"placetype":["aat:300008347"],"id":7025109,"name:ang":"Tochingeuuiche"}}
>>>>>>> 03f74aca74312dbeaf24d7e61306dd6a786dc3d0
