{
  "id": 7014538,
  "type": "Feature",
  "properties": {
    "tgn:hierarchy":[
        "tgn:7014538",
        "tgn:1000001",
        "tgn:7012149",
        "tgn:7022216",
        "tgn:7007919",
        "tgn:7029392"
    ],
    "tgn:id":7014538,
    "tgn:name":"Staunton",
    "tgn:placetype":[
        "aat:300008347"
    ]
},
  "bbox": [],
  "geometry": {"coordinates":[-79.0667,38.1333],"type":"Point"}
}