{
  "id": 2339523,
  "type": "Feature",
  "properties": {
    "tgn:hierarchy":[
        "tgn:2339523",
        "tgn:1000001",
        "tgn:7012149",
        "tgn:2000228",
        "tgn:7007158",
        "tgn:7029392"
    ],
    "tgn:id":2339523,
    "tgn:name":"Fred Pauls Detention Reservoir Number 1",
    "tgn:placetype":[
        "aat:300006191"
    ]
},
  "bbox": [],
  "geometry": {"coordinates":[-103.6833,38.9667],"type":"Point"}
}