<<<<<<< HEAD
{
  "id": 2339523,
  "type": "Feature",
  "properties": {
    "tgn:hierarchy":[
        "tgn:2339523",
        "tgn:1000001",
        "tgn:7012149",
        "tgn:2000228",
        "tgn:7007158",
        "tgn:7029392"
    ],
    "tgn:id":2339523,
    "tgn:name":"Fred Pauls Detention Reservoir Number 1",
    "tgn:placetype":[
        "aat:300006191"
    ]
},
  "bbox": [],
  "geometry": {"coordinates":[-103.6833,38.9667],"type":"Point"}
}
=======
{"geometry":{"type":"Point","coordinates":[-103.683300,38.966700]},"type":"Feature","properties":{"hierarchy":["tgn:2339523","tgn:1000001","tgn:7012149","tgn:2000228","tgn:7007158","tgn:7029392"],"placetype":["aat:300006191"],"id":2339523,"name:xx":"Fred Pauls Detention Reservoir Number 1"}}
>>>>>>> 03f74aca74312dbeaf24d7e61306dd6a786dc3d0
