{
  "id": 2283289,
  "type": "Feature",
  "properties": {
    "tgn:hierarchy":[
        "tgn:2283289",
        "tgn:1000001",
        "tgn:7012149",
        "tgn:1002588",
        "tgn:7007520",
        "tgn:7029392"
    ],
    "tgn:id":2283289,
    "tgn:name":"Deline Drain",
    "tgn:placetype":[
        "aat:300008699"
    ]
},
  "bbox": [],
  "geometry": {"coordinates":[-84.15,41.7667],"type":"Point"}
}