{
  "id": 2086406,
  "type": "Feature",
  "properties": {
    "tgn:hierarchy":[
        "tgn:2086406",
        "tgn:7013416",
        "tgn:1000001",
        "tgn:7012149",
        "tgn:1002729",
        "tgn:7007710",
        "tgn:7029392"
    ],
    "tgn:id":2086406,
    "tgn:name":"Lincoln Park",
    "tgn:placetype":[
        "aat:300387331"
    ]
},
  "bbox": [],
  "geometry": {"coordinates":[-75.35,40.6333],"type":"Point"}
}