{
  "id": 1113127,
  "type": "Feature",
  "properties": {
    "tgn:hierarchy":[
        "tgn:1113127",
        "tgn:7023902",
        "tgn:1000001",
        "tgn:7012149",
        "tgn:7007249",
        "tgn:7029392"
    ],
    "tgn:id":1113127,
    "tgn:name":"Hilo Bay",
    "tgn:placetype":[
        "aat:300132316"
    ]
},
  "bbox": [],
  "geometry": {"coordinates":[-155.0667,19.7333],"type":"Point"}
}