{
  "id": 2516362,
  "type": "Feature",
  "properties": {
    "tgn:hierarchy":[
        "tgn:2516362",
        "tgn:1000001",
        "tgn:7012149",
        "tgn:2001708",
        "tgn:7007708",
        "tgn:7029392"
    ],
    "tgn:id":2516362,
    "tgn:name":"Miner Creek",
    "tgn:placetype":[
        "aat:300008706"
    ]
},
  "bbox": [],
  "geometry": {"coordinates":[-119.25,44.3167],"type":"Point"}
}