{
  "id": 2609801,
  "type": "Feature",
  "properties": {
    "tgn:hierarchy":[
        "tgn:2609801",
        "tgn:1000001",
        "tgn:7012149",
        "tgn:7014287",
        "tgn:7007568",
        "tgn:7029392"
    ],
    "tgn:id":2609801,
    "tgn:name":"Reall Creek",
    "tgn:placetype":[
        "aat:300008706"
    ]
},
  "bbox": [],
  "geometry": {"coordinates":[-75.1333,43.15],"type":"Point"}
}