<<<<<<< HEAD
{
  "id": 7023621,
  "type": "Feature",
  "properties": {
    "tgn:hierarchy":[
        "tgn:7023621",
        "tgn:1000001",
        "tgn:7012149",
        "tgn:7029392"
    ],
    "tgn:id":7023621,
    "tgn:name":"Overfalls Shoal",
    "tgn:placetype":[
        "aat:300132348"
    ]
},
  "bbox": [],
  "geometry": {"coordinates":[-75.0,38.8333],"type":"Point"}
}
=======
{"geometry":{"type":"Point","coordinates":[-75.000000,38.833300]},"type":"Feature","properties":{"hierarchy":["tgn:7023621","tgn:1000001","tgn:7012149","tgn:7029392"],"placetype":["aat:300132348"],"id":7023621,"name:xx":"Overfalls Shoal"}}
>>>>>>> 03f74aca74312dbeaf24d7e61306dd6a786dc3d0
