{
  "id": 2301206,
  "type": "Feature",
  "properties": {
    "tgn:hierarchy":[
        "tgn:2301206",
        "tgn:1000001",
        "tgn:7012149",
        "tgn:7018871",
        "tgn:7007920",
        "tgn:7029392"
    ],
    "tgn:id":2301206,
    "tgn:name":"Dunlap",
    "tgn:placetype":[
        "aat:300008347"
    ]
},
  "bbox": [],
  "geometry": {"coordinates":[-122.2667,47.5167],"type":"Point"}
}