{
  "id": 7501409,
  "type": "Feature",
  "properties": {
    "tgn:hierarchy":[
        "tgn:7501409",
        "tgn:7488858",
        "tgn:1000004",
        "tgn:1000141",
        "tgn:7029392"
    ],
    "tgn:id":7501409,
    "tgn:name":"Zhimao Shan Nanfeng",
    "tgn:placetype":[
        "aat:300008798"
    ]
},
  "bbox": [],
  "geometry": {"coordinates":[120.973889,23.737222],"type":"Point"}
}