{
  "id": 2360890,
  "type": "Feature",
  "properties": {
    "tgn:hierarchy":[
        "tgn:2360890",
        "tgn:1000001",
        "tgn:7012149",
        "tgn:2001873",
        "tgn:7007825",
        "tgn:7029392"
    ],
    "tgn:id":2360890,
    "tgn:name":"Grassy Mountain",
    "tgn:placetype":[
        "aat:300266640"
    ]
},
  "bbox": [],
  "geometry": {"coordinates":[-82.75,36.4167],"type":"Point"}
}