{
  "id": 7460454,
  "type": "Feature",
  "properties": {
    "tgn:hierarchy":[
        "tgn:7460454",
        "tgn:7002444",
        "tgn:1000003",
        "tgn:5000460",
        "tgn:7008591",
        "tgn:7029392"
    ],
    "tgn:id":7460454,
    "tgn:name:en":"Loch Coulter Reservoir",
    "tgn:placetype":[
        "aat:300006191"
    ]
},
  "bbox": [],
  "geometry": {"coordinates":[-3.983333,56.033333],"type":"Point"}
}