{
  "id": 7566310,
  "type": "Feature",
  "properties": {
    "tgn:hierarchy":[
        "tgn:7566310",
        "tgn:1000004",
        "tgn:1001832",
        "tgn:7000198",
        "tgn:7029392"
    ],
    "tgn:id":7566310,
    "tgn:name:en":"Jongbandha",
    "tgn:placetype":[
        "aat:300008347"
    ]
},
  "bbox": [],
  "geometry": {"coordinates":[89.823812,26.366358],"type":"Point"}
}