{
  "id": 7468117,
  "type": "Feature",
  "properties": {
    "tgn:hierarchy":[
        "tgn:7468117",
        "tgn:7487020",
        "tgn:1000004",
        "tgn:1000141",
        "tgn:7029392"
    ],
    "tgn:id":7468117,
    "tgn:name":"Jiali Shan",
    "tgn:placetype":[
        "aat:300008798"
    ]
},
  "bbox": [],
  "geometry": {"coordinates":[121.216111,24.459444],"type":"Point"}
}