{
  "id": 7010558,
  "type": "Feature",
  "properties": {
    "tgn:hierarchy":[
        "tgn:7010558",
        "tgn:1000003",
        "tgn:7002890",
        "tgn:1000070",
        "tgn:7029392"
    ],
    "tgn:id":7010558,
    "tgn:name":"Neuilly-Saint Front",
    "tgn:placetype":[
        "aat:300008347"
    ]
},
  "bbox": [],
  "geometry": {"coordinates":[3.2667,49.1667],"type":"Point"}
}