{
  "id": 1056966,
  "type": "Feature",
  "properties": {
    "tgn:hierarchy":[
        "tgn:1056966",
        "tgn:1000004",
        "tgn:6003227",
        "tgn:7018214",
        "tgn:7002435",
        "tgn:7029392"
    ],
    "tgn:id":1056966,
    "tgn:name":"Mishkino",
    "tgn:placetype":[
        "aat:300008347"
    ]
},
  "bbox": [],
  "geometry": {"coordinates":[63.8333,55.3667],"type":"Point"}
}