{
  "id": 2692705,
  "type": "Feature",
  "properties": {
    "tgn:hierarchy":[
        "tgn:2692705",
        "tgn:1000001",
        "tgn:1002712",
        "tgn:7012149",
        "tgn:7007159",
        "tgn:7029392"
    ],
    "tgn:id":2692705,
    "tgn:name":"Steel Brook",
    "tgn:placetype":[
        "aat:300008699"
    ]
},
  "bbox": [],
  "geometry": {"coordinates":[-73.05,41.3833],"type":"Point"}
}