{
  "id": 7262140,
  "type": "Feature",
  "properties": {
    "tgn:concordances":{
        "gn:id":"2755592"
    },
    "tgn:hierarchy":[
        "tgn:7262140",
        "tgn:1000003",
        "tgn:7003624",
        "tgn:7016845",
        "tgn:7029392"
    ],
    "tgn:id":7262140,
    "tgn:name:nl":"Geneneind",
    "tgn:placetype":[
        "aat:300008347"
    ]
},
  "bbox": [],
  "geometry": {"coordinates":[5.733333,51.516667],"type":"Point"}
}