{
  "id": 7270947,
  "type": "Feature",
  "properties": {
    "tgn:concordances":{
        "gn:id":"2747054"
    },
    "tgn:hierarchy":[
        "tgn:7270947",
        "tgn:1000003",
        "tgn:7003627",
        "tgn:7016845",
        "tgn:7029392"
    ],
    "tgn:id":7270947,
    "tgn:name:nl":"Snelrewaard",
    "tgn:placetype":[
        "aat:300008347"
    ]
},
  "bbox": [],
  "geometry": {"coordinates":[4.916667,52.033333],"type":"Point"}
}