{
  "id": 2496206,
  "type": "Feature",
  "properties": {
    "tgn:hierarchy":[
        "tgn:2496206",
        "tgn:1000001",
        "tgn:7012149",
        "tgn:2001195",
        "tgn:7007523",
        "tgn:7029392"
    ],
    "tgn:id":2496206,
    "tgn:name":"Masters Lake",
    "tgn:placetype":[
        "aat:300006191"
    ]
},
  "bbox": [],
  "geometry": {"coordinates":[-91.4833,37.7333],"type":"Point"}
}