{
  "id": 2185961,
  "type": "Feature",
  "properties": {
    "tgn:hierarchy":[
        "tgn:2185961",
        "tgn:1000001",
        "tgn:7012149",
        "tgn:1002883",
        "tgn:7007706",
        "tgn:7029392"
    ],
    "tgn:id":2185961,
    "tgn:name":"Bollinger Ditch",
    "tgn:placetype":[
        "aat:300006075"
    ]
},
  "bbox": [],
  "geometry": {"coordinates":[-82.9333,41.0167],"type":"Point"}
}