{
  "id": 2364193,
  "type": "Feature",
  "properties": {
    "tgn:hierarchy":[
        "tgn:2364193",
        "tgn:1000001",
        "tgn:7012149",
        "tgn:2000996",
        "tgn:7007520",
        "tgn:7029392"
    ],
    "tgn:id":2364193,
    "tgn:name":"Green Pond",
    "tgn:placetype":[
        "aat:300008680"
    ]
},
  "bbox": [],
  "geometry": {"coordinates":[-85.8833,46.4833],"type":"Point"}
}