<<<<<<< HEAD
{
  "id": 2409818,
  "type": "Feature",
  "properties": {
    "tgn:hierarchy":[
        "tgn:2409818",
        "tgn:1000001",
        "tgn:2000702",
        "tgn:7012149",
        "tgn:7007254",
        "tgn:7029392"
    ],
    "tgn:id":2409818,
    "tgn:name":"Illinois Creek",
    "tgn:placetype":[
        "aat:300008706"
    ]
},
  "bbox": [],
  "geometry": {"coordinates":[-95.9667,39.3333],"type":"Point"}
}
=======
{"geometry":{"type":"Point","coordinates":[-95.966700,39.333300]},"type":"Feature","properties":{"hierarchy":["tgn:2409818","tgn:1000001","tgn:2000702","tgn:7012149","tgn:7007254","tgn:7029392"],"placetype":["aat:300008706"],"id":2409818,"name:xx":"Illinois Creek"}}
>>>>>>> 03f74aca74312dbeaf24d7e61306dd6a786dc3d0
