{
  "id": 1107821,
  "type": "Feature",
  "properties": {
    "tgn:hierarchy":[
        "tgn:1107821",
        "tgn:1000004",
        "tgn:7593756",
        "tgn:1000140",
        "tgn:7029392"
    ],
    "tgn:id":1107821,
    "tgn:name":"\u1e24ajar, Tall al-",
    "tgn:placetype":[
        "aat:300008777"
    ]
},
  "bbox": [],
  "geometry": {"coordinates":[37.05,33.35],"type":"Point"}
}