<<<<<<< HEAD
{
  "id": 2336022,
  "type": "Feature",
  "properties": {
    "tgn:hierarchy":[
        "tgn:2336022",
        "tgn:1000001",
        "tgn:7014352",
        "tgn:7012149",
        "tgn:7007564",
        "tgn:7029392"
    ],
    "tgn:id":2336022,
    "tgn:name":"Foster Corners",
    "tgn:placetype":[
        "aat:300008347"
    ]
},
  "bbox": [],
  "geometry": {"coordinates":[-71.2,42.7667],"type":"Point"}
}
=======
{"geometry":{"type":"Point","coordinates":[-71.200000,42.766700]},"type":"Feature","properties":{"hierarchy":["tgn:2336022","tgn:1000001","tgn:7014352","tgn:7012149","tgn:7007564","tgn:7029392"],"placetype":["aat:300008347"],"id":2336022,"name:xx":"Foster Corners"}}
>>>>>>> 03f74aca74312dbeaf24d7e61306dd6a786dc3d0
