{
  "id": 7554877,
  "type": "Feature",
  "properties": {
    "tgn:hierarchy":[
        "tgn:7554877",
        "tgn:7001819",
        "tgn:1000004",
        "tgn:7000198",
        "tgn:7029392"
    ],
    "tgn:id":7554877,
    "tgn:name:en":"Mi\u0101o Bum",
    "tgn:placetype":[
        "aat:300008777"
    ]
},
  "bbox": [],
  "geometry": {"coordinates":[96.258134,27.451097],"type":"Point"}
}