{
  "id": 7320779,
  "type": "Feature",
  "properties": {
    "tgn:hierarchy":[
        "tgn:7320779",
        "tgn:1001623",
        "tgn:1000049",
        "tgn:1000002",
        "tgn:7029392"
    ],
    "tgn:id":7320779,
    "tgn:name":"Canal, Piedra",
    "tgn:placetype":[
        "aat:300011692"
    ]
},
  "bbox": [],
  "geometry": {"coordinates":[-74.183333,-45.666667],"type":"Point"}
}