{
  "id": 2206157,
  "type": "Feature",
  "properties": {
    "tgn:hierarchy":[
        "tgn:2206157",
        "tgn:1000001",
        "tgn:7012149",
        "tgn:2001456",
        "tgn:7007566",
        "tgn:7029392"
    ],
    "tgn:id":2206157,
    "tgn:name":"Bull Tank",
    "tgn:placetype":[
        "aat:300006191"
    ]
},
  "bbox": [],
  "geometry": {"coordinates":[-107.35,34.3833],"type":"Point"}
}