{
  "id": 2481349,
  "type": "Feature",
  "properties": {
    "tgn:hierarchy":[
        "tgn:2481349",
        "tgn:1000001",
        "tgn:7012149",
        "tgn:2000927",
        "tgn:7007515",
        "tgn:7029392"
    ],
    "tgn:id":2481349,
    "tgn:name":"Lambs Hill",
    "tgn:placetype":[
        "aat:300008798"
    ]
},
  "bbox": [],
  "geometry": {"coordinates":[-68.4667,45.0333],"type":"Point"}
}