{
  "id": 2187711,
  "type": "Feature",
  "properties": {
    "tgn:hierarchy":[
        "tgn:2187711",
        "tgn:1000001",
        "tgn:7012149",
        "tgn:7007157",
        "tgn:7014004",
        "tgn:7029392"
    ],
    "tgn:id":2187711,
    "tgn:name":"Boothe Lake",
    "tgn:placetype":[
        "aat:300008680"
    ]
},
  "bbox": [],
  "geometry": {"coordinates":[-119.3333,37.7833],"type":"Point"}
}