{
  "id": 2625024,
  "type": "Feature",
  "properties": {
    "tgn:hierarchy":[
        "tgn:2625024",
        "tgn:1000001",
        "tgn:7012149",
        "tgn:2001968",
        "tgn:7007826",
        "tgn:7029392"
    ],
    "tgn:id":2625024,
    "tgn:name":"Rock Trail Tank",
    "tgn:placetype":[
        "aat:300006191"
    ]
},
  "bbox": [],
  "geometry": {"coordinates":[-101.1833,33.5667],"type":"Point"}
}