{
  "id": 2035161,
  "type": "Feature",
  "properties": {
    "tgn:hierarchy":[
        "tgn:2035161",
        "tgn:1000001",
        "tgn:7012149",
        "tgn:2000638",
        "tgn:7007253",
        "tgn:7029392"
    ],
    "tgn:id":2035161,
    "tgn:name":"McClelland",
    "tgn:placetype":[
        "aat:300008347"
    ]
},
  "bbox": [],
  "geometry": {"coordinates":[-95.6833,41.3167],"type":"Point"}
}