{
  "id": 7432962,
  "type": "Feature",
  "properties": {
    "tgn:hierarchy":[
        "tgn:7432962",
        "tgn:1001853",
        "tgn:1000001",
        "tgn:7005560",
        "tgn:7029392"
    ],
    "tgn:id":7432962,
    "tgn:name":"Rancho Viejo",
    "tgn:placetype":[
        "aat:300000241"
    ]
},
  "bbox": [],
  "geometry": {"coordinates":[-101.516667,25.266667],"type":"Point"}
}