{
  "id": 2266134,
  "type": "Feature",
  "properties": {
    "tgn:hierarchy":[
        "tgn:2266134",
        "tgn:1000001",
        "tgn:2000327",
        "tgn:7012149",
        "tgn:7007248",
        "tgn:7029392"
    ],
    "tgn:id":2266134,
    "tgn:name":"Crawford Lake",
    "tgn:placetype":[
        "aat:300006191"
    ]
},
  "bbox": [],
  "geometry": {"coordinates":[-82.2833,33.5167],"type":"Point"}
}