{
  "id": 1015340,
  "type": "Feature",
  "properties": {
    "tgn:hierarchy":[
        "tgn:1015340",
        "tgn:7005685",
        "tgn:1000001",
        "tgn:7005804",
        "tgn:7029392"
    ],
    "tgn:id":1015340,
    "tgn:name":"Ch\u00e9n\u00e9ville",
    "tgn:placetype":[
        "aat:300008347"
    ]
},
  "bbox": [],
  "geometry": {"coordinates":[-75.05,45.8833],"type":"Point"}
}