{
  "id": 7163301,
  "type": "Feature",
  "properties": {
    "tgn:hierarchy":[
        "tgn:7163301",
        "tgn:1000003",
        "tgn:7003677",
        "tgn:7000084",
        "tgn:7029392"
    ],
    "tgn:id":7163301,
    "tgn:name":"Im Stubbig",
    "tgn:placetype":[
        "aat:300055621"
    ]
},
  "bbox": [],
  "geometry": {"coordinates":[9.183333,51.55],"type":"Point"}
}