{
  "id": 2168152,
  "type": "Feature",
  "properties": {
    "tgn:hierarchy":[
        "tgn:2168152",
        "tgn:1000001",
        "tgn:7012149",
        "tgn:2001457",
        "tgn:7007566",
        "tgn:7029392"
    ],
    "tgn:id":2168152,
    "tgn:name":"Big Five Prospect",
    "tgn:placetype":[
        "aat:300000390"
    ]
},
  "bbox": [],
  "geometry": {"coordinates":[-105.3333,36.75],"type":"Point"}
}