{
  "id": 2698403,
  "type": "Feature",
  "properties": {
    "tgn:hierarchy":[
        "tgn:2698403",
        "tgn:1000001",
        "tgn:7012149",
        "tgn:2002300",
        "tgn:7013961",
        "tgn:7029392"
    ],
    "tgn:id":2698403,
    "tgn:name":"Straight Creek Mountain",
    "tgn:placetype":[
        "aat:300266640"
    ]
},
  "bbox": [],
  "geometry": {"coordinates":[-80.25,38.4167],"type":"Point"}
}