{
  "id": 1091513,
  "type": "Feature",
  "properties": {
    "tgn:hierarchy":[
        "tgn:1091513",
        "tgn:7001242",
        "tgn:1000869",
        "tgn:1000180",
        "tgn:7029392"
    ],
    "tgn:id":1091513,
    "tgn:name":"Covane",
    "tgn:placetype":[
        "aat:300008347"
    ]
},
  "bbox": [],
  "geometry": {"coordinates":[33.9667,-21.3333],"type":"Point"}
}