{
  "id": 7589684,
  "type": "Feature",
  "properties": {
    "tgn:hierarchy":[
        "tgn:7589684",
        "tgn:1000004",
        "tgn:7000198",
        "tgn:7000799",
        "tgn:7029392"
    ],
    "tgn:id":7589684,
    "tgn:name:en":"M\u0101law\u0101li Khad",
    "tgn:placetype":[
        "aat:300266554",
        "aat:300008699"
    ]
},
  "bbox": [],
  "geometry": {"coordinates":[74.973611,32.761111],"type":"Point"}
}