{
  "id": 2030483,
  "type": "Feature",
  "properties": {
    "tgn:hierarchy":[
        "tgn:2030483",
        "tgn:1000001",
        "tgn:7012149",
        "tgn:1002531",
        "tgn:7007251",
        "tgn:7029392"
    ],
    "tgn:id":2030483,
    "tgn:name":"Valley View",
    "tgn:placetype":[
        "aat:300008347"
    ]
},
  "bbox": [],
  "geometry": {"coordinates":[-88.2833,41.95],"type":"Point"}
}