{
  "id": 7287139,
  "type": "Feature",
  "properties": {
    "tgn:hierarchy":[
        "tgn:7287139",
        "tgn:1001630",
        "tgn:1000049",
        "tgn:1000002",
        "tgn:7029392"
    ],
    "tgn:id":7287139,
    "tgn:name":"Gaviotas, Islote de las",
    "tgn:placetype":[
        "aat:300008791"
    ]
},
  "bbox": [],
  "geometry": {"coordinates":[-71.116667,-27.85],"type":"Point"}
}