{
  "id": 2442293,
  "type": "Feature",
  "properties": {
    "tgn:hierarchy":[
        "tgn:2442293",
        "tgn:7006450",
        "tgn:1000001",
        "tgn:7012149",
        "tgn:2000088",
        "tgn:7029392"
    ],
    "tgn:id":2442293,
    "tgn:name":"Krauses Hole",
    "tgn:placetype":[
        "aat:300132316"
    ]
},
  "bbox": [],
  "geometry": {"coordinates":[-133.05,56.5333],"type":"Point"}
}