{
  "id": 2588378,
  "type": "Feature",
  "properties": {
    "tgn:hierarchy":[
        "tgn:2588378",
        "tgn:1000001",
        "tgn:7012149",
        "tgn:2001297",
        "tgn:7007524",
        "tgn:7029392"
    ],
    "tgn:id":2588378,
    "tgn:name":"Plum Creek Reservoir",
    "tgn:placetype":[
        "aat:300006191"
    ]
},
  "bbox": [],
  "geometry": {"coordinates":[-105.8667,45.1833],"type":"Point"}
}