{
  "id": 2500396,
  "type": "Feature",
  "properties": {
    "tgn:hierarchy":[
        "tgn:2500396",
        "tgn:1000001",
        "tgn:7012149",
        "tgn:7007157",
        "tgn:1002608",
        "tgn:7029392"
    ],
    "tgn:id":2500396,
    "tgn:name":"McDill, Mount",
    "tgn:placetype":[
        "aat:300008798"
    ]
},
  "bbox": [],
  "geometry": {"coordinates":[-118.2667,34.55],"type":"Point"}
}