{
  "id": 2582136,
  "type": "Feature",
  "properties": {
    "tgn:hierarchy":[
        "tgn:2582136",
        "tgn:1000001",
        "tgn:7012149",
        "tgn:2000495",
        "tgn:7007250",
        "tgn:7029392"
    ],
    "tgn:id":2582136,
    "tgn:name":"Pine Creek",
    "tgn:placetype":[
        "aat:300008706"
    ]
},
  "bbox": [],
  "geometry": {"coordinates":[-116.8333,44.7167],"type":"Point"}
}