{
  "id": 1029649,
  "type": "Feature",
  "properties": {
    "tgn:hierarchy":[
        "tgn:1029649",
        "tgn:7002445",
        "tgn:1000003",
        "tgn:7008166",
        "tgn:7008591",
        "tgn:7029392"
    ],
    "tgn:id":1029649,
    "tgn:name":"Hutton Rudby",
    "tgn:placetype":[
        "aat:300008347"
    ]
},
  "bbox": [],
  "geometry": {"coordinates":[-1.2833,54.45],"type":"Point"}
}