{
  "id": 2189829,
  "type": "Feature",
  "properties": {
    "tgn:hierarchy":[
        "tgn:2189829",
        "tgn:1000001",
        "tgn:7012149",
        "tgn:2002121",
        "tgn:7007827",
        "tgn:7029392"
    ],
    "tgn:id":2189829,
    "tgn:name":"Bowery Creek",
    "tgn:placetype":[
        "aat:300008706"
    ]
},
  "bbox": [],
  "geometry": {"coordinates":[-111.7167,38.5667],"type":"Point"}
}