{
  "id": 2305843,
  "type": "Feature",
  "properties": {
    "tgn:hierarchy":[
        "tgn:2305843",
        "tgn:1000001",
        "tgn:1002328",
        "tgn:7012149",
        "tgn:7007568",
        "tgn:7029392"
    ],
    "tgn:id":2305843,
    "tgn:name":"East Delhi",
    "tgn:placetype":[
        "aat:300008347"
    ]
},
  "bbox": [],
  "geometry": {"coordinates":[-74.8667,42.2833],"type":"Point"}
}