{
  "id": 7279785,
  "type": "Feature",
  "properties": {
    "tgn:hierarchy":[
        "tgn:7279785",
        "tgn:7016598",
        "tgn:1000049",
        "tgn:1000002",
        "tgn:7029392"
    ],
    "tgn:id":7279785,
    "tgn:name":"Rinc\u00f3n, Punta",
    "tgn:placetype":[
        "aat:300386846"
    ]
},
  "bbox": [],
  "geometry": {"coordinates":[-70.516667,-24.933333],"type":"Point"}
}