{
  "id": 2132706,
  "type": "Feature",
  "properties": {
    "tgn:hierarchy":[
        "tgn:2132706",
        "tgn:1000001",
        "tgn:2000201",
        "tgn:7012149",
        "tgn:7007158",
        "tgn:7029392"
    ],
    "tgn:id":2132706,
    "tgn:name":"Anchor Gulch",
    "tgn:placetype":[
        "aat:300008761"
    ]
},
  "bbox": [],
  "geometry": {"coordinates":[-105.65,39.8333],"type":"Point"}
}