{
  "id": 2519793,
  "type": "Feature",
  "properties": {
    "tgn:hierarchy":[
        "tgn:2519793",
        "tgn:1007657",
        "tgn:1002534",
        "tgn:1000001",
        "tgn:7012149",
        "tgn:7007249",
        "tgn:7029392"
    ],
    "tgn:id":2519793,
    "tgn:name":"Moikeha Canal",
    "tgn:placetype":[
        "aat:300006075"
    ]
},
  "bbox": [],
  "geometry": {"coordinates":[-159.3167,22.0833],"type":"Point"}
}