{
  "id": 2538929,
  "type": "Feature",
  "properties": {
    "tgn:hierarchy":[
        "tgn:2538929",
        "tgn:7006450",
        "tgn:1000001",
        "tgn:2124053",
        "tgn:7012149",
        "tgn:7029392"
    ],
    "tgn:id":2538929,
    "tgn:name":"New Black Diamond Mine",
    "tgn:placetype":[
        "aat:300000390"
    ]
},
  "bbox": [],
  "geometry": {"coordinates":[-149.0333,61.7167],"type":"Point"}
}