{
  "id": 2732047,
  "type": "Feature",
  "properties": {
    "tgn:hierarchy":[
        "tgn:2732047",
        "tgn:1000001",
        "tgn:2001428",
        "tgn:7012149",
        "tgn:7007566",
        "tgn:7029392"
    ],
    "tgn:id":2732047,
    "tgn:name":"Tunnel Canyon",
    "tgn:placetype":[
        "aat:300008761"
    ]
},
  "bbox": [],
  "geometry": {"coordinates":[-106.3833,35.0333],"type":"Point"}
}