{
  "id": 7581604,
  "type": "Feature",
  "properties": {
    "tgn:hierarchy":[
        "tgn:7581604",
        "tgn:1000004",
        "tgn:7000198",
        "tgn:1001578",
        "tgn:7029392"
    ],
    "tgn:id":7581604,
    "tgn:name:en":"Tit\u0101s River",
    "tgn:placetype":[
        "aat:300008699"
    ]
},
  "bbox": [],
  "geometry": {"coordinates":[90.957573,23.912596],"type":"Point"}
}