{
  "id": 7573819,
  "type": "Feature",
  "properties": {
    "tgn:hierarchy":[
        "tgn:7573819",
        "tgn:1000004",
        "tgn:7000198",
        "tgn:1001977",
        "tgn:7029392"
    ],
    "tgn:id":7573819,
    "tgn:name:en":"Itinda",
    "tgn:placetype":[
        "aat:300008347"
    ]
},
  "bbox": [],
  "geometry": {"coordinates":[88.91665,22.677302],"type":"Point"}
}