{
  "id": 2293314,
  "type": "Feature",
  "properties": {
    "tgn:hierarchy":[
        "tgn:2293314",
        "tgn:1000001",
        "tgn:7012149",
        "tgn:7007157",
        "tgn:1002957",
        "tgn:7029392"
    ],
    "tgn:id":2293314,
    "tgn:name":"Double Dome Rock",
    "tgn:placetype":[
        "aat:300008798"
    ]
},
  "bbox": [],
  "geometry": {"coordinates":[-119.8667,38.3333],"type":"Point"}
}