<<<<<<< HEAD
{
  "id": 7114510,
  "type": "Feature",
  "properties": {
    "tgn:hierarchy":[
        "tgn:7114510",
        "tgn:1000003",
        "tgn:7000094",
        "tgn:7000084",
        "tgn:7029392"
    ],
    "tgn:id":7114510,
    "tgn:name":"Roloffshagen",
    "tgn:placetype":[
        "aat:300008347"
    ]
},
  "bbox": [],
  "geometry": {"coordinates":[12.966667,54.15],"type":"Point"}
}
=======
{"geometry":{"type":"Point","coordinates":[12.966667,54.150000]},"type":"Feature","properties":{"hierarchy":["tgn:7114510","tgn:1000003","tgn:7000094","tgn:7000084","tgn:7029392"],"placetype":["aat:300008347"],"id":7114510,"name:xx":"Roloffshagen"}}
>>>>>>> 03f74aca74312dbeaf24d7e61306dd6a786dc3d0
