{
  "id": 2181809,
  "type": "Feature",
  "properties": {
    "tgn:hierarchy":[
        "tgn:2181809",
        "tgn:1000001",
        "tgn:7012149",
        "tgn:2000476",
        "tgn:7007250",
        "tgn:7029392"
    ],
    "tgn:id":2181809,
    "tgn:name":"Blue Joint",
    "tgn:placetype":[
        "aat:300008798"
    ]
},
  "bbox": [],
  "geometry": {"coordinates":[-114.5667,45.55],"type":"Point"}
}