{
  "id": 2462097,
  "type": "Feature",
  "properties": {
    "tgn:hierarchy":[
        "tgn:2462097",
        "tgn:1000001",
        "tgn:7012149",
        "tgn:1002999",
        "tgn:7007526",
        "tgn:7029392"
    ],
    "tgn:id":2462097,
    "tgn:name":"Little Valley",
    "tgn:placetype":[
        "aat:300008761"
    ]
},
  "bbox": [],
  "geometry": {"coordinates":[-119.7167,39.9833],"type":"Point"}
}