{
  "id": 2257669,
  "type": "Feature",
  "properties": {
    "tgn:hierarchy":[
        "tgn:2257669",
        "tgn:1000001",
        "tgn:7012149",
        "tgn:2002059",
        "tgn:7007826",
        "tgn:7029392"
    ],
    "tgn:id":2257669,
    "tgn:name":"Corral Creek",
    "tgn:placetype":[
        "aat:300008706"
    ]
},
  "bbox": [],
  "geometry": {"coordinates":[-101.3667,31.6333],"type":"Point"}
}