{
  "id": 1093421,
  "type": "Feature",
  "properties": {
    "tgn:hierarchy":[
        "tgn:1093421",
        "tgn:7001242",
        "tgn:7017584",
        "tgn:1000193",
        "tgn:7029392"
    ],
    "tgn:id":1093421,
    "tgn:name":"Nelspoort",
    "tgn:placetype":[
        "aat:300008347"
    ]
},
  "bbox": [],
  "geometry": {"coordinates":[23.0167,-32.1167],"type":"Point"}
}