{
  "id": 2341499,
  "type": "Feature",
  "properties": {
    "tgn:hierarchy":[
        "tgn:2341499",
        "tgn:1000001",
        "tgn:7012149",
        "tgn:2001722",
        "tgn:7007708",
        "tgn:7029392"
    ],
    "tgn:id":2341499,
    "tgn:name":"Frog Pond",
    "tgn:placetype":[
        "aat:300008680"
    ]
},
  "bbox": [],
  "geometry": {"coordinates":[-116.95,45.8833],"type":"Point"}
}