{
  "id": 2436884,
  "type": "Feature",
  "properties": {
    "tgn:hierarchy":[
        "tgn:2436884",
        "tgn:1000001",
        "tgn:7012149",
        "tgn:2000232",
        "tgn:7007158",
        "tgn:7029392"
    ],
    "tgn:id":2436884,
    "tgn:name":"Kilgore Gulch",
    "tgn:placetype":[
        "aat:300008761"
    ]
},
  "bbox": [],
  "geometry": {"coordinates":[-107.3333,40.9667],"type":"Point"}
}