{
  "id": 2369168,
  "type": "Feature",
  "properties": {
    "tgn:hierarchy":[
        "tgn:2369168",
        "tgn:1000001",
        "tgn:7016172",
        "tgn:7012149",
        "tgn:2000138",
        "tgn:7029392"
    ],
    "tgn:id":2369168,
    "tgn:name":"Gum Pond Ditch",
    "tgn:placetype":[
        "aat:300006075"
    ]
},
  "bbox": [],
  "geometry": {"coordinates":[-91.0667,35.7167],"type":"Point"}
}