{
  "id": 7560042,
  "type": "Feature",
  "properties": {
    "tgn:hierarchy":[
        "tgn:7560042",
        "tgn:1000004",
        "tgn:7000198",
        "tgn:7016722",
        "tgn:7029392"
    ],
    "tgn:id":7560042,
    "tgn:name:en":"Prithv\u012bpur",
    "tgn:placetype":[
        "aat:300008347"
    ]
},
  "bbox": [],
  "geometry": {"coordinates":[79.011975,26.957715],"type":"Point"}
}