{
  "id": 7295446,
  "type": "Feature",
  "properties": {
    "tgn:hierarchy":[
        "tgn:7295446",
        "tgn:7002832",
        "tgn:7001158",
        "tgn:1000003",
        "tgn:1000095",
        "tgn:7029392"
    ],
    "tgn:id":7295446,
    "tgn:name":"Villaverde de la Pe\u00f1a",
    "tgn:placetype":[
        "aat:300008347"
    ]
},
  "bbox": [],
  "geometry": {"coordinates":[-4.616667,42.833333],"type":"Point"}
}