{
  "id": 1043030,
  "type": "Feature",
  "properties": {
    "tgn:hierarchy":[
        "tgn:1043030",
        "tgn:7593748",
        "tgn:7001201",
        "tgn:1000003",
        "tgn:1000078",
        "tgn:7029392"
    ],
    "tgn:id":1043030,
    "tgn:name":"Thurles",
    "tgn:placetype":[
        "aat:300008347"
    ]
},
  "bbox": [],
  "geometry": {"coordinates":[-7.8167,52.6833],"type":"Point"}
}