{
  "id": 7170711,
  "type": "Feature",
  "properties": {
    "tgn:hierarchy":[
        "tgn:7170711",
        "tgn:1000003",
        "tgn:7003677",
        "tgn:7000084",
        "tgn:7029392"
    ],
    "tgn:id":7170711,
    "tgn:name":"He\u00df-Berg",
    "tgn:placetype":[
        "aat:300008777"
    ]
},
  "bbox": [],
  "geometry": {"coordinates":[7.85,51.15],"type":"Point"}
}