<<<<<<< HEAD
{
  "id": 7170711,
  "type": "Feature",
  "properties": {
    "tgn:hierarchy":[
        "tgn:7170711",
        "tgn:1000003",
        "tgn:7003677",
        "tgn:7000084",
        "tgn:7029392"
    ],
    "tgn:id":7170711,
    "tgn:name":"He\u00df-Berg",
    "tgn:placetype":[
        "aat:300008777"
    ]
},
  "bbox": [],
  "geometry": {"coordinates":[7.85,51.15],"type":"Point"}
}
=======
{"geometry":{"type":"Point","coordinates":[7.850000,51.150000]},"type":"Feature","properties":{"hierarchy":["tgn:7170711","tgn:1000003","tgn:7003677","tgn:7000084","tgn:7029392"],"placetype":["aat:300008777"],"id":7170711,"name:xx":"He\u00df-Berg"}}
>>>>>>> 03f74aca74312dbeaf24d7e61306dd6a786dc3d0
