{
  "id": 1011565,
  "type": "Feature",
  "properties": {
    "tgn:hierarchy":[
        "tgn:1011565",
        "tgn:7001152",
        "tgn:1000003",
        "tgn:1000095",
        "tgn:7029392"
    ],
    "tgn:id":1011565,
    "tgn:name":"Almina, Punta",
    "tgn:placetype":[
        "aat:300386846"
    ]
},
  "bbox": [],
  "geometry": {"coordinates":[-5.277222,35.900833],"type":"Point"}
}