{
  "id": 7130294,
  "type": "Feature",
  "properties": {
    "tgn:hierarchy":[
        "tgn:7130294",
        "tgn:1000003",
        "tgn:7003682",
        "tgn:7000084",
        "tgn:7029392"
    ],
    "tgn:id":7130294,
    "tgn:name":"Meinbach",
    "tgn:placetype":[
        "aat:300008699"
    ]
},
  "bbox": [],
  "geometry": {"coordinates":[6.35,50.183333],"type":"Point"}
}