{
  "id": 7105517,
  "type": "Feature",
  "properties": {
    "tgn:hierarchy":[
        "tgn:7105517",
        "tgn:1000003",
        "tgn:7003676",
        "tgn:7000084",
        "tgn:7029392"
    ],
    "tgn:id":7105517,
    "tgn:name":"Schier",
    "tgn:placetype":[
        "aat:300008863"
    ]
},
  "bbox": [],
  "geometry": {"coordinates":[9.316667,52.416667],"type":"Point"}
}