{
  "id": 2624614,
  "type": "Feature",
  "properties": {
    "tgn:hierarchy":[
        "tgn:2624614",
        "tgn:1000001",
        "tgn:7012149",
        "tgn:2000532",
        "tgn:7007251",
        "tgn:7029392"
    ],
    "tgn:id":2624614,
    "tgn:name":"Rock Run",
    "tgn:placetype":[
        "aat:300008699"
    ]
},
  "bbox": [],
  "geometry": {"coordinates":[-89.5167,42.4833],"type":"Point"}
}