{
  "id": 7567566,
  "type": "Feature",
  "properties": {
    "tgn:hierarchy":[
        "tgn:7567566",
        "tgn:1001828",
        "tgn:1000004",
        "tgn:7000198",
        "tgn:7029392"
    ],
    "tgn:id":7567566,
    "tgn:name:en":"P\u0101mkunta",
    "tgn:placetype":[
        "aat:300008347"
    ]
},
  "bbox": [],
  "geometry": {"coordinates":[78.909167,17.760278],"type":"Point"}
}