{
  "id": 2773057,
  "type": "Feature",
  "properties": {
    "tgn:hierarchy":[
        "tgn:2773057",
        "tgn:1000001",
        "tgn:7012149",
        "tgn:7007158",
        "tgn:2000248",
        "tgn:7029392"
    ],
    "tgn:id":2773057,
    "tgn:name":"Williams Reservoir",
    "tgn:placetype":[
        "aat:300006191"
    ]
},
  "bbox": [],
  "geometry": {"coordinates":[-108.3167,38.0667],"type":"Point"}
}