<<<<<<< HEAD
{
  "id": 7179764,
  "type": "Feature",
  "properties": {
    "tgn:hierarchy":[
        "tgn:7179764",
        "tgn:7003669",
        "tgn:1000003",
        "tgn:7000084",
        "tgn:7029392"
    ],
    "tgn:id":7179764,
    "tgn:name":"Gr\u00fcn-See",
    "tgn:placetype":[
        "aat:300008680"
    ]
},
  "bbox": [],
  "geometry": {"coordinates":[12.95,47.5],"type":"Point"}
}
=======
{"geometry":{"type":"Point","coordinates":[12.950000,47.500000]},"type":"Feature","properties":{"hierarchy":["tgn:7179764","tgn:7003669","tgn:1000003","tgn:7000084","tgn:7029392"],"placetype":["aat:300008680"],"id":7179764,"name:xx":"Gr\u00fcn-See"}}
>>>>>>> 03f74aca74312dbeaf24d7e61306dd6a786dc3d0
