<<<<<<< HEAD
{
  "id": 2253330,
  "type": "Feature",
  "properties": {
    "tgn:hierarchy":[
        "tgn:2253330",
        "tgn:1000001",
        "tgn:7012149",
        "tgn:2000232",
        "tgn:7007158",
        "tgn:7029392"
    ],
    "tgn:id":2253330,
    "tgn:name":"Conway Draw",
    "tgn:placetype":[
        "aat:300008761"
    ]
},
  "bbox": [],
  "geometry": {"coordinates":[-108.6833,40.6333],"type":"Point"}
}
=======
{"geometry":{"type":"Point","coordinates":[-108.683300,40.633300]},"type":"Feature","properties":{"hierarchy":["tgn:2253330","tgn:1000001","tgn:7012149","tgn:2000232","tgn:7007158","tgn:7029392"],"placetype":["aat:300008761"],"id":2253330,"name:xx":"Conway Draw"}}
>>>>>>> 03f74aca74312dbeaf24d7e61306dd6a786dc3d0
