{
  "id": 2292405,
  "type": "Feature",
  "properties": {
    "tgn:hierarchy":[
        "tgn:2292405",
        "tgn:1000001",
        "tgn:1002614",
        "tgn:7012149",
        "tgn:7007526",
        "tgn:7029392"
    ],
    "tgn:id":2292405,
    "tgn:name":"Donovan Property Mine",
    "tgn:placetype":[
        "aat:300000390"
    ]
},
  "bbox": [],
  "geometry": {"coordinates":[-119.6333,39.25],"type":"Point"}
}