{
  "id": 7323386,
  "type": "Feature",
  "properties": {
    "tgn:hierarchy":[
        "tgn:7323386",
        "tgn:7002826",
        "tgn:7001158",
        "tgn:1000003",
        "tgn:1000095",
        "tgn:7029392"
    ],
    "tgn:id":7323386,
    "tgn:name":"R\u00edocastrillo de Ord\u00e1s",
    "tgn:placetype":[
        "aat:300008347"
    ]
},
  "bbox": [],
  "geometry": {"coordinates":[-5.85,42.75],"type":"Point"}
}