{
  "id": 2335984,
  "type": "Feature",
  "properties": {
    "tgn:hierarchy":[
        "tgn:2335984",
        "tgn:1000001",
        "tgn:7012149",
        "tgn:2000346",
        "tgn:7007248",
        "tgn:7029392"
    ],
    "tgn:id":2335984,
    "tgn:name":"Foster Branch",
    "tgn:placetype":[
        "aat:300008699"
    ]
},
  "bbox": [],
  "geometry": {"coordinates":[-84.55,34.8667],"type":"Point"}
}