<<<<<<< HEAD
{
  "id": 2335984,
  "type": "Feature",
  "properties": {
    "tgn:hierarchy":[
        "tgn:2335984",
        "tgn:1000001",
        "tgn:7012149",
        "tgn:2000346",
        "tgn:7007248",
        "tgn:7029392"
    ],
    "tgn:id":2335984,
    "tgn:name":"Foster Branch",
    "tgn:placetype":[
        "aat:300008699"
    ]
},
  "bbox": [],
  "geometry": {"coordinates":[-84.55,34.8667],"type":"Point"}
}
=======
{"geometry":{"type":"Point","coordinates":[-84.550000,34.866700]},"type":"Feature","properties":{"hierarchy":["tgn:2335984","tgn:1000001","tgn:7012149","tgn:2000346","tgn:7007248","tgn:7029392"],"placetype":["aat:300008699"],"id":2335984,"name:xx":"Foster Branch"}}
>>>>>>> 03f74aca74312dbeaf24d7e61306dd6a786dc3d0
