{
  "id": 7425943,
  "type": "Feature",
  "properties": {
    "tgn:hierarchy":[
        "tgn:7425943",
        "tgn:7005581",
        "tgn:1000001",
        "tgn:7005560",
        "tgn:7029392"
    ],
    "tgn:id":7425943,
    "tgn:name":"Rahuibachi",
    "tgn:placetype":[
        "aat:300008347"
    ]
},
  "bbox": [],
  "geometry": {"coordinates":[-107.666667,27.816667],"type":"Point"}
}