{
  "id": 7438696,
  "type": "Feature",
  "properties": {
    "tgn:hierarchy":[
        "tgn:7438696",
        "tgn:1000001",
        "tgn:7005595",
        "tgn:7005560",
        "tgn:7029392"
    ],
    "tgn:id":7438696,
    "tgn:name":"Tachichilte, Isla de",
    "tgn:placetype":[
        "aat:300008791"
    ]
},
  "bbox": [],
  "geometry": {"coordinates":[-108.066667,24.983333],"type":"Point"}
}