{
  "id": 2025772,
  "type": "Feature",
  "properties": {
    "tgn:hierarchy":[
        "tgn:2025772",
        "tgn:1000001",
        "tgn:2000465",
        "tgn:7012149",
        "tgn:7007250",
        "tgn:7029392"
    ],
    "tgn:id":2025772,
    "tgn:name":"Josephson",
    "tgn:placetype":[
        "aat:300387016"
    ]
},
  "bbox": [],
  "geometry": {"coordinates":[-116.6333,43.7333],"type":"Point"}
}