<<<<<<< HEAD
{
  "id": 2709886,
  "type": "Feature",
  "properties": {
    "tgn:hierarchy":[
        "tgn:2709886",
        "tgn:2001626",
        "tgn:1000001",
        "tgn:7012149",
        "tgn:7007707",
        "tgn:7029392"
    ],
    "tgn:id":2709886,
    "tgn:name":"Taintor Creek",
    "tgn:placetype":[
        "aat:300008706"
    ]
},
  "bbox": [],
  "geometry": {"coordinates":[-100.2333,36.9],"type":"Point"}
}
=======
{"geometry":{"type":"Point","coordinates":[-100.233300,36.900000]},"type":"Feature","properties":{"hierarchy":["tgn:2709886","tgn:2001626","tgn:1000001","tgn:7012149","tgn:7007707","tgn:7029392"],"placetype":["aat:300008706"],"id":2709886,"name:xx":"Taintor Creek"}}
>>>>>>> 03f74aca74312dbeaf24d7e61306dd6a786dc3d0
