{
  "id": 1078512,
  "type": "Feature",
  "properties": {
    "tgn:hierarchy":[
        "tgn:1078512",
        "tgn:1000004",
        "tgn:1001322",
        "tgn:1000116",
        "tgn:7029392"
    ],
    "tgn:id":1078512,
    "tgn:name":"Secang",
    "tgn:placetype":[
        "aat:300008347"
    ]
},
  "bbox": [],
  "geometry": {"coordinates":[110.25,-7.3833],"type":"Point"}
}