<<<<<<< HEAD
{
  "id": 7482244,
  "type": "Feature",
  "properties": {
    "tgn:hierarchy":[
        "tgn:7482244",
        "tgn:1000004",
        "tgn:7490934",
        "tgn:1000141",
        "tgn:7029392"
    ],
    "tgn:id":7482244,
    "tgn:name":"Yangming Zhongxue",
    "tgn:placetype":[
        "aat:300006495"
    ]
},
  "bbox": [],
  "geometry": {"coordinates":[120.328028,23.191772],"type":"Point"}
}
=======
{"geometry":{"type":"Point","coordinates":[120.328028,23.191772]},"type":"Feature","properties":{"hierarchy":["tgn:7482244","tgn:1000004","tgn:7490934","tgn:1000141","tgn:7029392"],"placetype":["aat:300006495"],"id":7482244,"name:xx":"Yangming Zhongxue"}}
>>>>>>> 03f74aca74312dbeaf24d7e61306dd6a786dc3d0
