{
  "id": 7248285,
  "type": "Feature",
  "properties": {
    "tgn:hierarchy":[
        "tgn:7248285",
        "tgn:7018239",
        "tgn:1000003",
        "tgn:1000063",
        "tgn:7018236",
        "tgn:7029392"
    ],
    "tgn:id":7248285,
    "tgn:name":"Bergbroek",
    "tgn:placetype":[
        "aat:300008347"
    ]
},
  "bbox": [],
  "geometry": {"coordinates":[4.766667,50.933333],"type":"Point"}
}