{
  "id": 1075087,
  "type": "Feature",
  "properties": {
    "tgn:hierarchy":[
        "tgn:1075087",
        "tgn:1000004",
        "tgn:7000198",
        "tgn:1001977",
        "tgn:7029392"
    ],
    "tgn:id":1075087,
    "tgn:name":"Darodih",
    "tgn:placetype":[
        "aat:300008347"
    ]
},
  "bbox": [],
  "geometry": {"coordinates":[86.451249,23.224223],"type":"Point"}
}