{
  "id": 7591464,
  "type": "Feature",
  "properties": {
    "tgn:hierarchy":[
        "tgn:7591464",
        "tgn:1000004",
        "tgn:7000198",
        "tgn:7000799",
        "tgn:7029392"
    ],
    "tgn:id":7591464,
    "tgn:name:en":"R\u0101je Chak",
    "tgn:placetype":[
        "aat:300008347"
    ]
},
  "bbox": [],
  "geometry": {"coordinates":[74.678888,32.940303],"type":"Point"}
}