{
  "id": 1083326,
  "type": "Feature",
  "properties": {
    "tgn:hierarchy":[
        "tgn:1083326",
        "tgn:7001426",
        "tgn:7001417",
        "tgn:1000004",
        "tgn:1000132",
        "tgn:7029392"
    ],
    "tgn:id":1083326,
    "tgn:name":"Th\u0101nkot",
    "tgn:placetype":[
        "aat:300008347"
    ]
},
  "bbox": [],
  "geometry": {"coordinates":[85.1833,27.6833],"type":"Point"}
}