{
  "id": 2237347,
  "type": "Feature",
  "properties": {
    "tgn:hierarchy":[
        "tgn:2237347",
        "tgn:1000001",
        "tgn:7012149",
        "tgn:2000853",
        "tgn:7007255",
        "tgn:7029392"
    ],
    "tgn:id":2237347,
    "tgn:name":"Chimney Top Rock",
    "tgn:placetype":[
        "aat:300008798"
    ]
},
  "bbox": [],
  "geometry": {"coordinates":[-83.6167,37.8167],"type":"Point"}
}