<<<<<<< HEAD
{
  "id": 2400956,
  "type": "Feature",
  "properties": {
    "tgn:hierarchy":[
        "tgn:2400956",
        "tgn:1000001",
        "tgn:2001436",
        "tgn:7012149",
        "tgn:7007566",
        "tgn:7029392"
    ],
    "tgn:id":2400956,
    "tgn:name":"Horse Spring",
    "tgn:placetype":[
        "aat:300008697"
    ]
},
  "bbox": [],
  "geometry": {"coordinates":[-104.65,32.1333],"type":"Point"}
}
=======
{"geometry":{"type":"Point","coordinates":[-104.650000,32.133300]},"type":"Feature","properties":{"hierarchy":["tgn:2400956","tgn:1000001","tgn:2001436","tgn:7012149","tgn:7007566","tgn:7029392"],"placetype":["aat:300008697"],"id":2400956,"name:xx":"Horse Spring"}}
>>>>>>> 03f74aca74312dbeaf24d7e61306dd6a786dc3d0
