{
  "id": 7204722,
  "type": "Feature",
  "properties": {
    "tgn:hierarchy":[
        "tgn:7204722",
        "tgn:1000003",
        "tgn:7003677",
        "tgn:7000084",
        "tgn:7029392"
    ],
    "tgn:id":7204722,
    "tgn:name":"Bullerbach",
    "tgn:placetype":[
        "aat:300008699"
    ]
},
  "bbox": [],
  "geometry": {"coordinates":[7.866667,52.116667],"type":"Point"}
}