{
  "id": 2164495,
  "type": "Feature",
  "properties": {
    "tgn:hierarchy":[
        "tgn:2164495",
        "tgn:1000001",
        "tgn:7012149",
        "tgn:2002360",
        "tgn:7007922",
        "tgn:7029392"
    ],
    "tgn:id":2164495,
    "tgn:name":"Berry Lake",
    "tgn:placetype":[
        "aat:300008680"
    ]
},
  "bbox": [],
  "geometry": {"coordinates":[-91.6333,45.6833],"type":"Point"}
}