{
  "id": 2739044,
  "type": "Feature",
  "properties": {
    "tgn:hierarchy":[
        "tgn:2739044",
        "tgn:1000001",
        "tgn:7012149",
        "tgn:2002123",
        "tgn:7007827",
        "tgn:7029392"
    ],
    "tgn:id":2739044,
    "tgn:name":"United States Mine",
    "tgn:placetype":[
        "aat:300000390"
    ]
},
  "bbox": [],
  "geometry": {"coordinates":[-113.8167,40.15],"type":"Point"}
}