{
  "id": 7200263,
  "type": "Feature",
  "properties": {
    "tgn:hierarchy":[
        "tgn:7200263",
        "tgn:7003692",
        "tgn:1000003",
        "tgn:7000084",
        "tgn:7029392"
    ],
    "tgn:id":7200263,
    "tgn:name":"D\u00fcrrenb\u00fcchig",
    "tgn:placetype":[
        "aat:300008347"
    ]
},
  "bbox": [],
  "geometry": {"coordinates":[8.649722,49.022222],"type":"Point"}
}