{
  "id": 2178581,
  "type": "Feature",
  "properties": {
    "tgn:hierarchy":[
        "tgn:2178581",
        "tgn:1000001",
        "tgn:7012149",
        "tgn:2001248",
        "tgn:7007523",
        "tgn:7029392"
    ],
    "tgn:id":2178581,
    "tgn:name":"Blackshire Branch",
    "tgn:placetype":[
        "aat:300008699"
    ]
},
  "bbox": [],
  "geometry": {"coordinates":[-89.9333,36.85],"type":"Point"}
}