{
  "id": 7364527,
  "type": "Feature",
  "properties": {
    "tgn:hierarchy":[
        "tgn:7364527",
        "tgn:1000001",
        "tgn:1001960",
        "tgn:7005560",
        "tgn:7029392"
    ],
    "tgn:id":7364527,
    "tgn:name":"Rancho El Prieto",
    "tgn:placetype":[
        "aat:300000241"
    ]
},
  "bbox": [],
  "geometry": {"coordinates":[-111.633333,30.466667],"type":"Point"}
}