{
  "id": 2152204,
  "type": "Feature",
  "properties": {
    "tgn:hierarchy":[
        "tgn:2152204",
        "tgn:1000001",
        "tgn:7012149",
        "tgn:2000408",
        "tgn:7007248",
        "tgn:7029392"
    ],
    "tgn:id":2152204,
    "tgn:name":"Bay Branch",
    "tgn:placetype":[
        "aat:300008699"
    ]
},
  "bbox": [],
  "geometry": {"coordinates":[-83.2833,33.2833],"type":"Point"}
}