{
  "id": 7563294,
  "type": "Feature",
  "properties": {
    "tgn:hierarchy":[
        "tgn:7563294",
        "tgn:1000004",
        "tgn:7000198",
        "tgn:7016722",
        "tgn:7029392"
    ],
    "tgn:id":7563294,
    "tgn:name:en":"Purwa Ah\u012bran",
    "tgn:placetype":[
        "aat:300008347"
    ]
},
  "bbox": [],
  "geometry": {"coordinates":[79.791122,26.624591],"type":"Point"}
}