{
  "id": 1124239,
  "type": "Feature",
  "properties": {
    "tgn:hierarchy":[
        "tgn:1124239",
        "tgn:1000004",
        "tgn:7000198",
        "tgn:7029392"
    ],
    "tgn:id":1124239,
    "tgn:name":"Gomati",
    "tgn:placetype":[
        "aat:300008707"
    ]
},
  "bbox": [],
  "geometry": {"coordinates":[83.1667,25.5333],"type":"Point"}
}