{
  "id": 2015600,
  "type": "Feature",
  "properties": {
    "tgn:hierarchy":[
        "tgn:2015600",
        "tgn:1000001",
        "tgn:7012149",
        "tgn:2000229",
        "tgn:7007158",
        "tgn:7029392"
    ],
    "tgn:id":2015600,
    "tgn:name":"Ford",
    "tgn:placetype":[
        "aat:300387016"
    ]
},
  "bbox": [],
  "geometry": {"coordinates":[-103.1333,40.7167],"type":"Point"}
}