{
  "id": 2639663,
  "type": "Feature",
  "properties": {
    "tgn:hierarchy":[
        "tgn:2639663",
        "tgn:1000001",
        "tgn:7012149",
        "tgn:7007157",
        "tgn:1002566",
        "tgn:7029392"
    ],
    "tgn:id":2639663,
    "tgn:name":"Sam Alley Ridge",
    "tgn:placetype":[
        "aat:300266640"
    ]
},
  "bbox": [],
  "geometry": {"coordinates":[-122.8667,39.1833],"type":"Point"}
}