{
  "id": 2091335,
  "type": "Feature",
  "properties": {
    "tgn:hierarchy":[
        "tgn:2091335",
        "tgn:1000001",
        "tgn:7012149",
        "tgn:1002690",
        "tgn:7007710",
        "tgn:7029392"
    ],
    "tgn:id":2091335,
    "tgn:name":"Niantic",
    "tgn:placetype":[
        "aat:300008347"
    ]
},
  "bbox": [],
  "geometry": {"coordinates":[-75.5667,40.3667],"type":"Point"}
}