{
  "id": 1000569,
  "type": "Feature",
  "properties": {
    "tgn:hierarchy":[
        "tgn:1000569",
        "tgn:1000001",
        "tgn:7005554",
        "tgn:7029392"
    ],
    "tgn:id":1000569,
    "tgn:name":"Choluteca",
    "tgn:placetype":[
        "aat:300387064",
        "aat:300000772"
    ]
},
  "bbox": [],
  "geometry": {"coordinates":[-87.0833,13.3333],"type":"Point"}
}