<<<<<<< HEAD
{
  "id": 2338690,
  "type": "Feature",
  "properties": {
    "tgn:hierarchy":[
        "tgn:2338690",
        "tgn:1000001",
        "tgn:7012149",
        "tgn:1002749",
        "tgn:7007240",
        "tgn:7029392"
    ],
    "tgn:id":2338690,
    "tgn:name":"Francis, Lake",
    "tgn:placetype":[
        "aat:300008680"
    ]
},
  "bbox": [],
  "geometry": {"coordinates":[-81.35,28.6],"type":"Point"}
}
=======
{"geometry":{"type":"Point","coordinates":[-81.350000,28.600000]},"type":"Feature","properties":{"hierarchy":["tgn:2338690","tgn:1000001","tgn:7012149","tgn:1002749","tgn:7007240","tgn:7029392"],"placetype":["aat:300008680"],"id":2338690,"name:xx":"Francis, Lake"}}
>>>>>>> 03f74aca74312dbeaf24d7e61306dd6a786dc3d0
