{
  "id": 2507681,
  "type": "Feature",
  "properties": {
    "tgn:hierarchy":[
        "tgn:2507681",
        "tgn:1000001",
        "tgn:7012149",
        "tgn:1002797",
        "tgn:7007706",
        "tgn:7029392"
    ],
    "tgn:id":2507681,
    "tgn:name":"Michael J. Kirwan Reservoir",
    "tgn:placetype":[
        "aat:300006191"
    ]
},
  "bbox": [],
  "geometry": {"coordinates":[-81.0667,41.15],"type":"Point"}
}