{
  "id": 1115873,
  "type": "Feature",
  "properties": {
    "tgn:hierarchy":[
        "tgn:1115873",
        "tgn:7005685",
        "tgn:1000001",
        "tgn:7005734",
        "tgn:7029392"
    ],
    "tgn:id":1115873,
    "tgn:name":"Charron Lake",
    "tgn:placetype":[
        "aat:300008680"
    ]
},
  "bbox": [],
  "geometry": {"coordinates":[-95.25,52.7333],"type":"Point"}
}