{
  "id": 7085934,
  "type": "Feature",
  "properties": {
    "tgn:hierarchy":[
        "tgn:7085934",
        "tgn:7003692",
        "tgn:1000003",
        "tgn:7000084",
        "tgn:7029392"
    ],
    "tgn:id":7085934,
    "tgn:name":"Weidet",
    "tgn:placetype":[
        "aat:300000206"
    ]
},
  "bbox": [],
  "geometry": {"coordinates":[9.983333,47.95],"type":"Point"}
}