{
  "id": 2589682,
  "type": "Feature",
  "properties": {
    "tgn:hierarchy":[
        "tgn:2589682",
        "tgn:1000001",
        "tgn:7012149",
        "tgn:2000877",
        "tgn:7007256",
        "tgn:7029392"
    ],
    "tgn:id":2589682,
    "tgn:name":"Point Pleasant",
    "tgn:placetype":[
        "aat:300008850"
    ]
},
  "bbox": [],
  "geometry": {"coordinates":[-91.1333,30.25],"type":"Point"}
}