{
  "id": 7500283,
  "type": "Feature",
  "properties": {
    "tgn:hierarchy":[
        "tgn:7500283",
        "tgn:7001010",
        "tgn:1000004",
        "tgn:1000141",
        "tgn:7029392"
    ],
    "tgn:id":7500283,
    "tgn:name":"Bugan Shan",
    "tgn:placetype":[
        "aat:300008798"
    ]
},
  "bbox": [],
  "geometry": {"coordinates":[121.16,23.468056],"type":"Point"}
}