{
  "id": 2351257,
  "type": "Feature",
  "properties": {
    "tgn:hierarchy":[
        "tgn:2351257",
        "tgn:7014651",
        "tgn:1000001",
        "tgn:7012149",
        "tgn:7007516",
        "tgn:7029392"
    ],
    "tgn:id":2351257,
    "tgn:name":"Glebe Bay",
    "tgn:placetype":[
        "aat:300132316"
    ]
},
  "bbox": [],
  "geometry": {"coordinates":[-76.5333,38.9167],"type":"Point"}
}