<<<<<<< HEAD
{
  "id": 2766428,
  "type": "Feature",
  "properties": {
    "tgn:hierarchy":[
        "tgn:2766428",
        "tgn:1000001",
        "tgn:7012149",
        "tgn:2002332",
        "tgn:7007922",
        "tgn:7029392"
    ],
    "tgn:id":2766428,
    "tgn:name":"White Oak",
    "tgn:placetype":[
        "aat:300008347"
    ]
},
  "bbox": [],
  "geometry": {"coordinates":[-90.2667,42.5167],"type":"Point"}
}
=======
{"geometry":{"type":"Point","coordinates":[-90.266700,42.516700]},"type":"Feature","properties":{"hierarchy":["tgn:2766428","tgn:1000001","tgn:7012149","tgn:2002332","tgn:7007922","tgn:7029392"],"placetype":["aat:300008347"],"id":2766428,"name:xx":"White Oak"}}
>>>>>>> 03f74aca74312dbeaf24d7e61306dd6a786dc3d0
