{
  "id": 1128873,
  "type": "Feature",
  "properties": {
    "tgn:hierarchy":[
        "tgn:1128873",
        "tgn:1000001",
        "tgn:7005562",
        "tgn:7029392"
    ],
    "tgn:id":1128873,
    "tgn:name":"Punta Gorda, R\u00edo",
    "tgn:placetype":[
        "aat:300008707"
    ]
},
  "bbox": [],
  "geometry": {"coordinates":[-83.773,11.508],"type":"Point"}
}