{
  "id": 7241640,
  "type": "Feature",
  "properties": {
    "tgn:hierarchy":[
        "tgn:7241640",
        "tgn:7007877",
        "tgn:1000003",
        "tgn:1000063",
        "tgn:4012014",
        "tgn:7029392"
    ],
    "tgn:id":7241640,
    "tgn:name":"La Chape",
    "tgn:placetype":[
        "aat:300000206"
    ]
},
  "bbox": [],
  "geometry": {"coordinates":[4.233333,50.666667],"type":"Point"}
}