<<<<<<< HEAD
{
  "id": 7025723,
  "type": "Feature",
  "properties": {
    "tgn:hierarchy":[
        "tgn:7025723",
        "tgn:7002445",
        "tgn:1000003",
        "tgn:7012077",
        "tgn:7008591",
        "tgn:7029392"
    ],
    "tgn:id":7025723,
    "tgn:name:en":"Sidbury",
    "tgn:placetype":[
        "aat:300008347"
    ]
},
  "bbox": [],
  "geometry": {"coordinates":[-3.2,50.716667],"type":"Point"}
}
=======
{"geometry":{"type":"Point","coordinates":[-3.200000,50.716667]},"type":"Feature","properties":{"hierarchy":["tgn:7025723","tgn:7002445","tgn:1000003","tgn:7012077","tgn:7008591","tgn:7029392"],"placetype":["aat:300008347"],"name:en":"Sidbury","id":7025723}}
>>>>>>> 03f74aca74312dbeaf24d7e61306dd6a786dc3d0
