{
  "id": 2413312,
  "type": "Feature",
  "properties": {
    "tgn:hierarchy":[
        "tgn:2413312",
        "tgn:1000001",
        "tgn:7012149",
        "tgn:7007515",
        "tgn:7029392"
    ],
    "tgn:id":2413312,
    "tgn:name":"Intervale Brook",
    "tgn:placetype":[
        "aat:300008699"
    ]
},
  "bbox": [],
  "geometry": {"coordinates":[-68.4333,44.8333],"type":"Point"}
}