{
  "id": 7222683,
  "type": "Feature",
  "properties": {
    "tgn:hierarchy":[
        "tgn:7222683",
        "tgn:7002711",
        "tgn:7001338",
        "tgn:1000003",
        "tgn:1000074",
        "tgn:7029392"
    ],
    "tgn:id":7222683,
    "tgn:name":"Plyt\u00edri, \u00c1kra",
    "tgn:placetype":[
        "aat:300008850"
    ]
},
  "bbox": [],
  "geometry": {"coordinates":[19.834444,39.561667],"type":"Point"}
}