{
  "id": 2272170,
  "type": "Feature",
  "properties": {
    "tgn:hierarchy":[
        "tgn:2272170",
        "tgn:1000001",
        "tgn:7012149",
        "tgn:2002058",
        "tgn:7007826",
        "tgn:7029392"
    ],
    "tgn:id":2272170,
    "tgn:name":"Currie Lake",
    "tgn:placetype":[
        "aat:300006191"
    ]
},
  "bbox": [],
  "geometry": {"coordinates":[-101.75,35.0333],"type":"Point"}
}