{
  "id": 2529238,
  "type": "Feature",
  "properties": {
    "tgn:hierarchy":[
        "tgn:2529238",
        "tgn:1000001",
        "tgn:7012149",
        "tgn:1002676",
        "tgn:7007240",
        "tgn:7029392"
    ],
    "tgn:id":2529238,
    "tgn:name":"Mud Keys",
    "tgn:placetype":[
        "aat:300008791"
    ]
},
  "bbox": [],
  "geometry": {"coordinates":[-81.6833,24.6667],"type":"Point"}
}