{
  "id": 2526723,
  "type": "Feature",
  "properties": {
    "tgn:hierarchy":[
        "tgn:2526723",
        "tgn:1000001",
        "tgn:7012149",
        "tgn:2001524",
        "tgn:7007709",
        "tgn:7029392"
    ],
    "tgn:id":2526723,
    "tgn:name":"Mott Creek",
    "tgn:placetype":[
        "aat:300008706"
    ]
},
  "bbox": [],
  "geometry": {"coordinates":[-77.3167,34.7167],"type":"Point"}
}