{
  "id": 2216807,
  "type": "Feature",
  "properties": {
    "tgn:hierarchy":[
        "tgn:2216807",
        "tgn:1000001",
        "tgn:2001092",
        "tgn:7012149",
        "tgn:7007522",
        "tgn:7029392"
    ],
    "tgn:id":2216807,
    "tgn:name":"Camp Ground Branch",
    "tgn:placetype":[
        "aat:300008699"
    ]
},
  "bbox": [],
  "geometry": {"coordinates":[-89.2667,33.9833],"type":"Point"}
}