{
  "id": 7439373,
  "type": "Feature",
  "properties": {
    "tgn:hierarchy":[
        "tgn:7439373",
        "tgn:1000001",
        "tgn:7005595",
        "tgn:7005560",
        "tgn:7029392"
    ],
    "tgn:id":7439373,
    "tgn:name":"Soyatita",
    "tgn:placetype":[
        "aat:300008347"
    ]
},
  "bbox": [],
  "geometry": {"coordinates":[-107.366667,25.75],"type":"Point"}
}