{
  "id": 7301626,
  "type": "Feature",
  "properties": {
    "tgn:hierarchy":[
        "tgn:7301626",
        "tgn:7002758",
        "tgn:7002821",
        "tgn:1000003",
        "tgn:1000095",
        "tgn:7029392"
    ],
    "tgn:id":7301626,
    "tgn:name":"Molina, Arroyo de",
    "tgn:placetype":[
        "aat:300008699"
    ]
},
  "bbox": [],
  "geometry": {"coordinates":[-4.05,37.316667],"type":"Point"}
}