{
  "id": 7238940,
  "type": "Feature",
  "properties": {
    "tgn:hierarchy":[
        "tgn:7238940",
        "tgn:7003458",
        "tgn:1000003",
        "tgn:1000063",
        "tgn:7018236",
        "tgn:7029392"
    ],
    "tgn:id":7238940,
    "tgn:name":"Hoeke",
    "tgn:placetype":[
        "aat:300008347"
    ]
},
  "bbox": [],
  "geometry": {"coordinates":[3.334918,51.292049],"type":"Point"}
}