{
  "id": 2083109,
  "type": "Feature",
  "properties": {
    "tgn:hierarchy":[
        "tgn:2083109",
        "tgn:1000001",
        "tgn:7012149",
        "tgn:2001677",
        "tgn:7007707",
        "tgn:7029392"
    ],
    "tgn:id":2083109,
    "tgn:name":"Del City",
    "tgn:placetype":[
        "aat:300008347"
    ]
},
  "bbox": [],
  "geometry": {"coordinates":[-97.4333,35.4333],"type":"Point"}
}