{
  "id": 7580899,
  "type": "Feature",
  "properties": {
    "tgn:hierarchy":[
        "tgn:7580899",
        "tgn:1000004",
        "tgn:1001869",
        "tgn:7000198",
        "tgn:7029392"
    ],
    "tgn:id":7580899,
    "tgn:name:en":"Timana",
    "tgn:placetype":[
        "aat:300008347"
    ]
},
  "bbox": [],
  "geometry": {"coordinates":[71.983333,21.433333],"type":"Point"}
}