{
  "id": 7336564,
  "type": "Feature",
  "properties": {
    "tgn:hierarchy":[
        "tgn:7336564",
        "tgn:7001155",
        "tgn:1000003",
        "tgn:7002790",
        "tgn:1000095",
        "tgn:7029392"
    ],
    "tgn:id":7336564,
    "tgn:name":"Fontellas",
    "tgn:placetype":[
        "aat:300008347"
    ]
},
  "bbox": [],
  "geometry": {"coordinates":[-1.566667,42.016667],"type":"Point"}
}