{
  "id": 2457581,
  "type": "Feature",
  "properties": {
    "tgn:hierarchy":[
        "tgn:2457581",
        "tgn:1000001",
        "tgn:7012149",
        "tgn:2000487",
        "tgn:7007250",
        "tgn:7029392"
    ],
    "tgn:id":2457581,
    "tgn:name":"Little Malad River",
    "tgn:placetype":[
        "aat:300008707"
    ]
},
  "bbox": [],
  "geometry": {"coordinates":[-112.45,42.3667],"type":"Point"}
}