{
  "id": 2372356,
  "type": "Feature",
  "properties": {
    "tgn:hierarchy":[
        "tgn:2372356",
        "tgn:1000001",
        "tgn:7012149",
        "tgn:2000972",
        "tgn:7007520",
        "tgn:7029392"
    ],
    "tgn:id":2372356,
    "tgn:name":"Halfway Lake",
    "tgn:placetype":[
        "aat:300008680"
    ]
},
  "bbox": [],
  "geometry": {"coordinates":[-85.5833,46.4667],"type":"Point"}
}