{
  "id": 2388643,
  "type": "Feature",
  "properties": {
    "tgn:hierarchy":[
        "tgn:2388643",
        "tgn:1000001",
        "tgn:7012149",
        "tgn:1002352",
        "tgn:7007710",
        "tgn:7029392"
    ],
    "tgn:id":2388643,
    "tgn:name":"Hicks Run Camping Area",
    "tgn:placetype":[
        "aat:300055621"
    ]
},
  "bbox": [],
  "geometry": {"coordinates":[-78.2667,41.3667],"type":"Point"}
}