{
  "id": 2335759,
  "type": "Feature",
  "properties": {
    "tgn:hierarchy":[
        "tgn:2335759",
        "tgn:1000001",
        "tgn:7012149",
        "tgn:7007708",
        "tgn:7029392"
    ],
    "tgn:id":2335759,
    "tgn:name":"Forty-five Spring",
    "tgn:placetype":[
        "aat:300008697"
    ]
},
  "bbox": [],
  "geometry": {"coordinates":[-119.35,43.95],"type":"Point"}
}