<<<<<<< HEAD
{
  "id": 2335759,
  "type": "Feature",
  "properties": {
    "tgn:hierarchy":[
        "tgn:2335759",
        "tgn:1000001",
        "tgn:7012149",
        "tgn:7007708",
        "tgn:7029392"
    ],
    "tgn:id":2335759,
    "tgn:name":"Forty-five Spring",
    "tgn:placetype":[
        "aat:300008697"
    ]
},
  "bbox": [],
  "geometry": {"coordinates":[-119.35,43.95],"type":"Point"}
}
=======
{"geometry":{"type":"Point","coordinates":[-119.350000,43.950000]},"type":"Feature","properties":{"hierarchy":["tgn:2335759","tgn:1000001","tgn:7012149","tgn:7007708","tgn:7029392"],"placetype":["aat:300008697"],"id":2335759,"name:xx":"Forty-five Spring"}}
>>>>>>> 03f74aca74312dbeaf24d7e61306dd6a786dc3d0
