{
  "id": 7526466,
  "type": "Feature",
  "properties": {
    "tgn:hierarchy":[
        "tgn:7526466",
        "tgn:7001242",
        "tgn:7001105",
        "tgn:7016833",
        "tgn:7029392"
    ],
    "tgn:id":7526466,
    "tgn:name:en":"Tall\u0101t",
    "tgn:placetype":[
        "aat:300008347"
    ]
},
  "bbox": [],
  "geometry": {"coordinates":[30.754523,29.333141],"type":"Point"}
}