{
  "id": 7230180,
  "type": "Feature",
  "properties": {
    "tgn:hierarchy":[
        "tgn:7230180",
        "tgn:7002735",
        "tgn:7017076",
        "tgn:1000003",
        "tgn:1000074",
        "tgn:7029392"
    ],
    "tgn:id":7230180,
    "tgn:name":"Khor\u00e9mis",
    "tgn:placetype":[
        "aat:300008347"
    ]
},
  "bbox": [],
  "geometry": {"coordinates":[22.083333,37.383333],"type":"Point"}
}