{
  "id": 7037716,
  "type": "Feature",
  "properties": {
    "tgn:hierarchy":[
        "tgn:7037716",
        "tgn:7003162",
        "tgn:1000003",
        "tgn:7009760",
        "tgn:1000080",
        "tgn:7029392"
    ],
    "tgn:id":7037716,
    "tgn:name":"Vacchereccia, Borro",
    "tgn:placetype":[
        "aat:300008699"
    ]
},
  "bbox": [],
  "geometry": {"coordinates":[11.516667,43.583333],"type":"Point"}
}