{
  "id": 2423791,
  "type": "Feature",
  "properties": {
    "tgn:hierarchy":[
        "tgn:2423791",
        "tgn:1000001",
        "tgn:7012149",
        "tgn:2001084",
        "tgn:7007521",
        "tgn:7029392"
    ],
    "tgn:id":2423791,
    "tgn:name":"John, Lake",
    "tgn:placetype":[
        "aat:300008680"
    ]
},
  "bbox": [],
  "geometry": {"coordinates":[-94.15,45.25],"type":"Point"}
}