{
  "id": 2651066,
  "type": "Feature",
  "properties": {
    "tgn:hierarchy":[
        "tgn:2651066",
        "tgn:1000001",
        "tgn:2001009",
        "tgn:7012149",
        "tgn:7007521",
        "tgn:7029392"
    ],
    "tgn:id":2651066,
    "tgn:name":"Second Trestle Lake",
    "tgn:placetype":[
        "aat:300008680"
    ]
},
  "bbox": [],
  "geometry": {"coordinates":[-94.5833,46.85],"type":"Point"}
}