{
  "id": 7577508,
  "type": "Feature",
  "properties": {
    "tgn:hierarchy":[
        "tgn:7577508",
        "tgn:1000004",
        "tgn:1001832",
        "tgn:7000198",
        "tgn:7029392"
    ],
    "tgn:id":7577508,
    "tgn:name:en":"K\u016bkichara",
    "tgn:placetype":[
        "aat:300008347"
    ]
},
  "bbox": [],
  "geometry": {"coordinates":[92.563262,24.386531],"type":"Point"}
}