{
  "id": 1032114,
  "type": "Feature",
  "properties": {
    "tgn:hierarchy":[
        "tgn:1032114",
        "tgn:1000003",
        "tgn:7002880",
        "tgn:1000070",
        "tgn:7029392"
    ],
    "tgn:id":1032114,
    "tgn:name":"Bergnicourt",
    "tgn:placetype":[
        "aat:300008347"
    ]
},
  "bbox": [],
  "geometry": {"coordinates":[4.25,49.4167],"type":"Point"}
}