{
  "id": 7335725,
  "type": "Feature",
  "properties": {
    "tgn:hierarchy":[
        "tgn:7335725",
        "tgn:7002834",
        "tgn:1000003",
        "tgn:7002786",
        "tgn:1000095",
        "tgn:7029392"
    ],
    "tgn:id":7335725,
    "tgn:name":"Golada",
    "tgn:placetype":[
        "aat:300008347"
    ]
},
  "bbox": [],
  "geometry": {"coordinates":[-7.983333,42.766667],"type":"Point"}
}