{
  "id": 2550333,
  "type": "Feature",
  "properties": {
    "tgn:hierarchy":[
        "tgn:2550333",
        "tgn:2001728",
        "tgn:1000001",
        "tgn:7012149",
        "tgn:7007712",
        "tgn:7029392"
    ],
    "tgn:id":2550333,
    "tgn:name":"Northview",
    "tgn:placetype":[
        "aat:300008347"
    ]
},
  "bbox": [],
  "geometry": {"coordinates":[-82.6833,34.5333],"type":"Point"}
}