{
  "id": 2700554,
  "type": "Feature",
  "properties": {
    "tgn:hierarchy":[
        "tgn:2700554",
        "tgn:1000001",
        "tgn:7012149",
        "tgn:1002440",
        "tgn:7007568",
        "tgn:7029392"
    ],
    "tgn:id":2700554,
    "tgn:name":"Sucker Brook",
    "tgn:placetype":[
        "aat:300008699"
    ]
},
  "bbox": [],
  "geometry": {"coordinates":[-74.4333,43.65],"type":"Point"}
}