{
  "id": 2535650,
  "type": "Feature",
  "properties": {
    "tgn:hierarchy":[
        "tgn:2535650",
        "tgn:1002141",
        "tgn:1000001",
        "tgn:7012149",
        "tgn:7007568",
        "tgn:7029392"
    ],
    "tgn:id":2535650,
    "tgn:name":"Narvoo Hollow",
    "tgn:placetype":[
        "aat:300008761"
    ]
},
  "bbox": [],
  "geometry": {"coordinates":[-78.25,42.0333],"type":"Point"}
}