{
  "id": 7187589,
  "type": "Feature",
  "properties": {
    "tgn:hierarchy":[
        "tgn:7187589",
        "tgn:1000003",
        "tgn:7003676",
        "tgn:7000084",
        "tgn:7029392"
    ],
    "tgn:id":7187589,
    "tgn:name":"Etzenborn",
    "tgn:placetype":[
        "aat:300008347"
    ]
},
  "bbox": [],
  "geometry": {"coordinates":[10.15,51.466667],"type":"Point"}
}