{
  "id": 7110618,
  "type": "Feature",
  "properties": {
    "tgn:hierarchy":[
        "tgn:7110618",
        "tgn:1000003",
        "tgn:7003676",
        "tgn:7000084",
        "tgn:7029392"
    ],
    "tgn:id":7110618,
    "tgn:name":"Pumpe",
    "tgn:placetype":[
        "aat:300000206"
    ]
},
  "bbox": [],
  "geometry": {"coordinates":[8.316667,53.55],"type":"Point"}
}