{
  "id": 7175201,
  "type": "Feature",
  "properties": {
    "tgn:hierarchy":[
        "tgn:7175201",
        "tgn:7003669",
        "tgn:1000003",
        "tgn:7000084",
        "tgn:7029392"
    ],
    "tgn:id":7175201,
    "tgn:name":"Gro\u00dfgerstetten",
    "tgn:placetype":[
        "aat:300008347"
    ]
},
  "bbox": [],
  "geometry": {"coordinates":[12.95,47.883333],"type":"Point"}
}