{
  "id": 4008451,
  "type": "Feature",
  "properties": {
    "tgn:hierarchy":[
        "tgn:4008451",
        "tgn:7002445",
        "tgn:1000003",
        "tgn:7008167",
        "tgn:7008591",
        "tgn:7029392"
    ],
    "tgn:id":4008451,
    "tgn:name:en":"Papplewick",
    "tgn:placetype":[
        "aat:300008347",
        "aat:300008372"
    ]
},
  "bbox": [],
  "geometry": {"coordinates":[-1.183333,53.05],"type":"Point"}
}