<<<<<<< HEAD
{
  "id": 7489278,
  "type": "Feature",
  "properties": {
    "tgn:hierarchy":[
        "tgn:7489278",
        "tgn:1000004",
        "tgn:7492971",
        "tgn:1000141",
        "tgn:7029392"
    ],
    "tgn:id":7489278,
    "tgn:name":"Neibu",
    "tgn:placetype":[
        "aat:300008347"
    ]
},
  "bbox": [],
  "geometry": {"coordinates":[120.7425,22.079722],"type":"Point"}
}
=======
{"geometry":{"type":"Point","coordinates":[120.742500,22.079722]},"type":"Feature","properties":{"hierarchy":["tgn:7489278","tgn:1000004","tgn:7492971","tgn:1000141","tgn:7029392"],"placetype":["aat:300008347"],"id":7489278,"name:xx":"Neibu"}}
>>>>>>> 03f74aca74312dbeaf24d7e61306dd6a786dc3d0
