{
  "id": 7421556,
  "type": "Feature",
  "properties": {
    "tgn:hierarchy":[
        "tgn:7421556",
        "tgn:7005579",
        "tgn:1000001",
        "tgn:7005560",
        "tgn:7029392"
    ],
    "tgn:id":7421556,
    "tgn:name":"Jaltiche de Arriba",
    "tgn:placetype":[
        "aat:300008347"
    ]
},
  "bbox": [],
  "geometry": {"coordinates":[-102.779167,21.773611],"type":"Point"}
}