{
  "id": 2242135,
  "type": "Feature",
  "properties": {
    "tgn:hierarchy":[
        "tgn:2242135",
        "tgn:2001422",
        "tgn:1000001",
        "tgn:7012149",
        "tgn:7007564",
        "tgn:7029392"
    ],
    "tgn:id":2242135,
    "tgn:name":"Clay Point",
    "tgn:placetype":[
        "aat:300008850"
    ]
},
  "bbox": [],
  "geometry": {"coordinates":[-71.2167,43.5333],"type":"Point"}
}