{
  "id": 2279198,
  "type": "Feature",
  "properties": {
    "tgn:hierarchy":[
        "tgn:2279198",
        "tgn:1000001",
        "tgn:7012149",
        "tgn:2000495",
        "tgn:7007250",
        "tgn:7029392"
    ],
    "tgn:id":2279198,
    "tgn:name":"Deadhorse Gulch",
    "tgn:placetype":[
        "aat:300008761"
    ]
},
  "bbox": [],
  "geometry": {"coordinates":[-116.9833,44.5333],"type":"Point"}
}