<<<<<<< HEAD
{
  "id": 2156781,
  "type": "Feature",
  "properties": {
    "tgn:hierarchy":[
        "tgn:2156781",
        "tgn:1000001",
        "tgn:7012149",
        "tgn:2000523",
        "tgn:7007251",
        "tgn:7029392"
    ],
    "tgn:id":2156781,
    "tgn:name":"Beatty Branch",
    "tgn:placetype":[
        "aat:300008699"
    ]
},
  "bbox": [],
  "geometry": {"coordinates":[-88.5,37.45],"type":"Point"}
}
=======
{"geometry":{"type":"Point","coordinates":[-88.500000,37.450000]},"type":"Feature","properties":{"hierarchy":["tgn:2156781","tgn:1000001","tgn:7012149","tgn:2000523","tgn:7007251","tgn:7029392"],"placetype":["aat:300008699"],"id":2156781,"name:xx":"Beatty Branch"}}
>>>>>>> 03f74aca74312dbeaf24d7e61306dd6a786dc3d0
