{
  "id": 2311416,
  "type": "Feature",
  "properties": {
    "tgn:hierarchy":[
        "tgn:2311416",
        "tgn:1000001",
        "tgn:7012149",
        "tgn:7016021",
        "tgn:7007568",
        "tgn:7029392"
    ],
    "tgn:id":2311416,
    "tgn:name":"Edmond Brook",
    "tgn:placetype":[
        "aat:300008699"
    ]
},
  "bbox": [],
  "geometry": {"coordinates":[-75.1333,44.4333],"type":"Point"}
}