{
  "id": 7279819,
  "type": "Feature",
  "properties": {
    "tgn:hierarchy":[
        "tgn:7279819",
        "tgn:1001637",
        "tgn:1000049",
        "tgn:1000002",
        "tgn:7029392"
    ],
    "tgn:id":7279819,
    "tgn:name":"Relbunco",
    "tgn:placetype":[
        "aat:300000206"
    ]
},
  "bbox": [],
  "geometry": {"coordinates":[-71.816667,-36.683333],"type":"Point"}
}