<<<<<<< HEAD
{
  "id": 7477274,
  "type": "Feature",
  "properties": {
    "tgn:hierarchy":[
        "tgn:7477274",
        "tgn:1000004",
        "tgn:7004300",
        "tgn:1000141",
        "tgn:7029392"
    ],
    "tgn:id":7477274,
    "tgn:name":"Jian Shan",
    "tgn:placetype":[
        "aat:300387033"
    ]
},
  "bbox": [],
  "geometry": {"coordinates":[119.569784,23.664449],"type":"Point"}
}
=======
{"geometry":{"type":"Point","coordinates":[119.569784,23.664449]},"type":"Feature","properties":{"hierarchy":["tgn:7477274","tgn:1000004","tgn:7004300","tgn:1000141","tgn:7029392"],"placetype":["aat:300387033"],"id":7477274,"name:xx":"Jian Shan"}}
>>>>>>> 03f74aca74312dbeaf24d7e61306dd6a786dc3d0
