{
  "id": 7477274,
  "type": "Feature",
  "properties": {
    "tgn:hierarchy":[
        "tgn:7477274",
        "tgn:1000004",
        "tgn:7004300",
        "tgn:1000141",
        "tgn:7029392"
    ],
    "tgn:id":7477274,
    "tgn:name":"Jian Shan",
    "tgn:placetype":[
        "aat:300387033"
    ]
},
  "bbox": [],
  "geometry": {"coordinates":[119.569784,23.664449],"type":"Point"}
}