{
  "id": 2012724,
  "type": "Feature",
  "properties": {
    "tgn:hierarchy":[
        "tgn:2012724",
        "tgn:1000001",
        "tgn:7012149",
        "tgn:7007157",
        "tgn:7014516",
        "tgn:7029392"
    ],
    "tgn:id":2012724,
    "tgn:name":"Mirabel Park",
    "tgn:placetype":[
        "aat:300008347"
    ]
},
  "bbox": [],
  "geometry": {"coordinates":[-122.8833,38.4833],"type":"Point"}
}