{
  "id": 1085446,
  "type": "Feature",
  "properties": {
    "tgn:hierarchy":[
        "tgn:1085446",
        "tgn:1001365",
        "tgn:7005191",
        "tgn:1000004",
        "tgn:1000142",
        "tgn:7029392"
    ],
    "tgn:id":1085446,
    "tgn:name":"Ban Khok Bao Sao",
    "tgn:placetype":[
        "aat:300008347"
    ]
},
  "bbox": [],
  "geometry": {"coordinates":[100.65,13.8667],"type":"Point"}
}