{
  "id": 7310706,
  "type": "Feature",
  "properties": {
    "tgn:hierarchy":[
        "tgn:7310706",
        "tgn:7016598",
        "tgn:1000049",
        "tgn:1000002",
        "tgn:7029392"
    ],
    "tgn:id":7310706,
    "tgn:name":"Morrales",
    "tgn:placetype":[
        "aat:300008347"
    ]
},
  "bbox": [],
  "geometry": {"coordinates":[-70.366667,-24.933333],"type":"Point"}
}