{
  "id": 7440451,
  "type": "Feature",
  "properties": {
    "tgn:hierarchy":[
        "tgn:7440451",
        "tgn:1001853",
        "tgn:1000001",
        "tgn:7005560",
        "tgn:7029392"
    ],
    "tgn:id":7440451,
    "tgn:name":"Santa Mar\u00eda",
    "tgn:placetype":[
        "aat:300008347"
    ]
},
  "bbox": [],
  "geometry": {"coordinates":[-100.666667,28.15],"type":"Point"}
}