{
  "id": 2702068,
  "type": "Feature",
  "properties": {
    "tgn:hierarchy":[
        "tgn:2702068",
        "tgn:1000001",
        "tgn:7012149",
        "tgn:7007255",
        "tgn:7029392"
    ],
    "tgn:id":2702068,
    "tgn:name":"Sugartree Run",
    "tgn:placetype":[
        "aat:300008699"
    ]
},
  "bbox": [],
  "geometry": {"coordinates":[-85.7833,38.0667],"type":"Point"}
}