{
  "id": 1070205,
  "type": "Feature",
  "properties": {
    "tgn:hierarchy":[
        "tgn:1070205",
        "tgn:1000004",
        "tgn:7002087",
        "tgn:1000111",
        "tgn:7029392"
    ],
    "tgn:id":1070205,
    "tgn:name":"Luojiang",
    "tgn:placetype":[
        "aat:300008347"
    ]
},
  "bbox": [],
  "geometry": {"coordinates":[104.5167,31.3333],"type":"Point"}
}