{
  "id": 7536864,
  "type": "Feature",
  "properties": {
    "tgn:hierarchy":[
        "tgn:7536864",
        "tgn:7001242",
        "tgn:7001311",
        "tgn:7016833",
        "tgn:7029392"
    ],
    "tgn:id":7536864,
    "tgn:name:en":"\u1e28a\u1e11rab\u012byah, Jabal",
    "tgn:placetype":[
        "aat:300008795"
    ]
},
  "bbox": [],
  "geometry": {"coordinates":[33.301769,26.601789],"type":"Point"}
}