{
  "id": 2727823,
  "type": "Feature",
  "properties": {
    "tgn:hierarchy":[
        "tgn:2727823",
        "tgn:7002659",
        "tgn:1000001",
        "tgn:2000008",
        "tgn:7012149",
        "tgn:7029392"
    ],
    "tgn:id":2727823,
    "tgn:name":"Trammel Crossroads",
    "tgn:placetype":[
        "aat:300008347"
    ]
},
  "bbox": [],
  "geometry": {"coordinates":[-85.5333,32.9667],"type":"Point"}
}