{
  "id": 2361208,
  "type": "Feature",
  "properties": {
    "tgn:hierarchy":[
        "tgn:2361208",
        "tgn:1002177",
        "tgn:1000001",
        "tgn:7012149",
        "tgn:7007252",
        "tgn:7029392"
    ],
    "tgn:id":2361208,
    "tgn:name":"Gravel Hill",
    "tgn:placetype":[
        "aat:300008347"
    ]
},
  "bbox": [],
  "geometry": {"coordinates":[-87.3667,40.65],"type":"Point"}
}