{
  "id": 2769214,
  "type": "Feature",
  "properties": {
    "tgn:hierarchy":[
        "tgn:2769214",
        "tgn:1000001",
        "tgn:1002347",
        "tgn:7012149",
        "tgn:7007568",
        "tgn:7029392"
    ],
    "tgn:id":2769214,
    "tgn:name":"Whortlekill Creek",
    "tgn:placetype":[
        "aat:300008706"
    ]
},
  "bbox": [],
  "geometry": {"coordinates":[-73.7333,41.6167],"type":"Point"}
}