{
  "id": 7513600,
  "type": "Feature",
  "properties": {
    "tgn:hierarchy":[
        "tgn:7513600",
        "tgn:1009227",
        "tgn:1000226",
        "tgn:7016729",
        "tgn:1000006",
        "tgn:7029392"
    ],
    "tgn:id":7513600,
    "tgn:name:en":"Gannet Point",
    "tgn:placetype":[
        "aat:300386846"
    ]
},
  "bbox": [],
  "geometry": {"coordinates":[174.216667,-41.05],"type":"Point"}
}