{
  "id": 1081150,
  "type": "Feature",
  "properties": {
    "tgn:hierarchy":[
        "tgn:1081150",
        "tgn:1000004",
        "tgn:7000894",
        "tgn:7016797",
        "tgn:1000120",
        "tgn:7029392"
    ],
    "tgn:id":1081150,
    "tgn:name":"Ry\u014dke",
    "tgn:placetype":[
        "aat:300008347"
    ]
},
  "bbox": [],
  "geometry": {"coordinates":[139.55,35.9667],"type":"Point"}
}