{
  "id": 2659680,
  "type": "Feature",
  "properties": {
    "tgn:hierarchy":[
        "tgn:2659680",
        "tgn:1000001",
        "tgn:2001472",
        "tgn:7012149",
        "tgn:7007709",
        "tgn:7029392"
    ],
    "tgn:id":2659680,
    "tgn:name":"Shingletree Bay",
    "tgn:placetype":[
        "aat:300008905"
    ]
},
  "bbox": [],
  "geometry": {"coordinates":[-78.3833,34.0333],"type":"Point"}
}