{
  "id": 2581087,
  "type": "Feature",
  "properties": {
    "tgn:hierarchy":[
        "tgn:2581087",
        "tgn:1000001",
        "tgn:7012149",
        "tgn:1002594",
        "tgn:7007920",
        "tgn:7029392"
    ],
    "tgn:id":2581087,
    "tgn:name":"Pikes Hill",
    "tgn:placetype":[
        "aat:300008798"
    ]
},
  "bbox": [],
  "geometry": {"coordinates":[-122.8833,46.4667],"type":"Point"}
}