{
  "id": 2579339,
  "type": "Feature",
  "properties": {
    "tgn:hierarchy":[
        "tgn:2579339",
        "tgn:1000001",
        "tgn:7012149",
        "tgn:7021313",
        "tgn:7007521",
        "tgn:7029392"
    ],
    "tgn:id":2579339,
    "tgn:name":"Pickeral Creek",
    "tgn:placetype":[
        "aat:300008706"
    ]
},
  "bbox": [],
  "geometry": {"coordinates":[-94.95,49.2667],"type":"Point"}
}