{
  "id": 7197156,
  "type": "Feature",
  "properties": {
    "tgn:hierarchy":[
        "tgn:7197156",
        "tgn:7003692",
        "tgn:1000003",
        "tgn:7000084",
        "tgn:7029392"
    ],
    "tgn:id":7197156,
    "tgn:name":"Dietenburg",
    "tgn:placetype":[
        "aat:300008057"
    ]
},
  "bbox": [],
  "geometry": {"coordinates":[9.483333,48.166667],"type":"Point"}
}