{
  "id": 7444974,
  "type": "Feature",
  "properties": {
    "tgn:hierarchy":[
        "tgn:7444974",
        "tgn:7002443",
        "tgn:1000003",
        "tgn:7018993",
        "tgn:7008591",
        "tgn:7029392"
    ],
    "tgn:id":7444974,
    "tgn:name:en":"Waterston",
    "tgn:placetype":[
        "aat:300008347"
    ]
},
  "bbox": [],
  "geometry": {"coordinates":[-4.989722,51.711111],"type":"Point"}
}