{
  "id": 2191481,
  "type": "Feature",
  "properties": {
    "tgn:hierarchy":[
        "tgn:2191481",
        "tgn:1000001",
        "tgn:7012149",
        "tgn:2000549",
        "tgn:7007252",
        "tgn:7029392"
    ],
    "tgn:id":2191481,
    "tgn:name":"Bradfield Corner",
    "tgn:placetype":[
        "aat:300008347"
    ]
},
  "bbox": [],
  "geometry": {"coordinates":[-87.2833,39.7167],"type":"Point"}
}