{
  "id": 7116476,
  "type": "Feature",
  "properties": {
    "tgn:hierarchy":[
        "tgn:7116476",
        "tgn:1000003",
        "tgn:7003682",
        "tgn:7000084",
        "tgn:7029392"
    ],
    "tgn:id":7116476,
    "tgn:name":"Offstein",
    "tgn:placetype":[
        "aat:300008347"
    ]
},
  "bbox": [],
  "geometry": {"coordinates":[8.238056,49.606111],"type":"Point"}
}