<<<<<<< HEAD
{
  "id": 2158327,
  "type": "Feature",
  "properties": {
    "tgn:hierarchy":[
        "tgn:2158327",
        "tgn:1000001",
        "tgn:7012149",
        "tgn:2002128",
        "tgn:7007827",
        "tgn:7029392"
    ],
    "tgn:id":2158327,
    "tgn:name":"Beaver Wash",
    "tgn:placetype":[
        "aat:300008699"
    ]
},
  "bbox": [],
  "geometry": {"coordinates":[-110.5833,38.2333],"type":"Point"}
}
=======
{"geometry":{"type":"Point","coordinates":[-110.583300,38.233300]},"type":"Feature","properties":{"hierarchy":["tgn:2158327","tgn:1000001","tgn:7012149","tgn:2002128","tgn:7007827","tgn:7029392"],"placetype":["aat:300008699"],"id":2158327,"name:xx":"Beaver Wash"}}
>>>>>>> 03f74aca74312dbeaf24d7e61306dd6a786dc3d0
