{
  "id": 2466638,
  "type": "Feature",
  "properties": {
    "tgn:hierarchy":[
        "tgn:2466638",
        "tgn:1000001",
        "tgn:7012149",
        "tgn:7013940",
        "tgn:7007709",
        "tgn:7029392"
    ],
    "tgn:id":2466638,
    "tgn:name":"Long Branch",
    "tgn:placetype":[
        "aat:300008699"
    ]
},
  "bbox": [],
  "geometry": {"coordinates":[-78.1667,36.0667],"type":"Point"}
}