{
  "id": 2748790,
  "type": "Feature",
  "properties": {
    "tgn:hierarchy":[
        "tgn:2748790",
        "tgn:1002165",
        "tgn:1000001",
        "tgn:7012149",
        "tgn:7007517",
        "tgn:7029392"
    ],
    "tgn:id":2748790,
    "tgn:name":"Walkers Narrows",
    "tgn:placetype":[
        "aat:300008794"
    ]
},
  "bbox": [],
  "geometry": {"coordinates":[-70.1167,41.7167],"type":"Point"}
}