{
  "id": 1103069,
  "type": "Feature",
  "properties": {
    "tgn:hierarchy":[
        "tgn:1103069",
        "tgn:1000003",
        "tgn:7003677",
        "tgn:7000084",
        "tgn:7029392"
    ],
    "tgn:id":1103069,
    "tgn:name":"Schwalm-Nette, Naturpark",
    "tgn:placetype":[
        "aat:300008178",
        "aat:300008187"
    ]
},
  "bbox": [],
  "geometry": {"coordinates":[6.183333,51.25],"type":"Point"}
}