{
  "id": 2204771,
  "type": "Feature",
  "properties": {
    "tgn:hierarchy":[
        "tgn:2204771",
        "tgn:1000001",
        "tgn:7012149",
        "tgn:2002301",
        "tgn:7013961",
        "tgn:7029392"
    ],
    "tgn:id":2204771,
    "tgn:name":"Buffalo Run",
    "tgn:placetype":[
        "aat:300008699"
    ]
},
  "bbox": [],
  "geometry": {"coordinates":[-80.6167,39.45],"type":"Point"}
}