{
  "id": 7041550,
  "type": "Feature",
  "properties": {
    "tgn:hierarchy":[
        "tgn:7041550",
        "tgn:1003450",
        "tgn:7007850",
        "tgn:1000003",
        "tgn:1000080",
        "tgn:7029392"
    ],
    "tgn:id":7041550,
    "tgn:name":"San Lauro",
    "tgn:placetype":[
        "aat:300008347"
    ]
},
  "bbox": [],
  "geometry": {"coordinates":[16.066667,39.55],"type":"Point"}
}