{
  "id": 2538200,
  "type": "Feature",
  "properties": {
    "tgn:hierarchy":[
        "tgn:2538200",
        "tgn:1000001",
        "tgn:7012149",
        "tgn:2002250",
        "tgn:7007920",
        "tgn:7029392"
    ],
    "tgn:id":2538200,
    "tgn:name":"Nelson Peak",
    "tgn:placetype":[
        "aat:300008798"
    ]
},
  "bbox": [],
  "geometry": {"coordinates":[-117.5167,48.1833],"type":"Point"}
}