{
  "id": 2721876,
  "type": "Feature",
  "properties": {
    "tgn:hierarchy":[
        "tgn:2721876",
        "tgn:1000001",
        "tgn:2001640",
        "tgn:7012149",
        "tgn:7007707",
        "tgn:7029392"
    ],
    "tgn:id":2721876,
    "tgn:name":"Timber Hill",
    "tgn:placetype":[
        "aat:300008798"
    ]
},
  "bbox": [],
  "geometry": {"coordinates":[-95.1167,36.7833],"type":"Point"}
}