{
  "id": 7442831,
  "type": "Feature",
  "properties": {
    "tgn:hierarchy":[
        "tgn:7442831",
        "tgn:7002445",
        "tgn:1000003",
        "tgn:7012077",
        "tgn:7008591",
        "tgn:7029392"
    ],
    "tgn:id":7442831,
    "tgn:name:en":"Ballsaddle Rock",
    "tgn:placetype":[
        "aat:300008808"
    ]
},
  "bbox": [],
  "geometry": {"coordinates":[-3.683333,50.216667],"type":"Point"}
}