<<<<<<< HEAD
{
  "id": 2764990,
  "type": "Feature",
  "properties": {
    "tgn:hierarchy":[
        "tgn:2764990",
        "tgn:1000001",
        "tgn:2001100",
        "tgn:7012149",
        "tgn:7007522",
        "tgn:7029392"
    ],
    "tgn:id":2764990,
    "tgn:name":"Whisky Creek",
    "tgn:placetype":[
        "aat:300008706"
    ]
},
  "bbox": [],
  "geometry": {"coordinates":[-90.55,31.9],"type":"Point"}
}
=======
{"geometry":{"type":"Point","coordinates":[-90.550000,31.900000]},"type":"Feature","properties":{"hierarchy":["tgn:2764990","tgn:1000001","tgn:2001100","tgn:7012149","tgn:7007522","tgn:7029392"],"placetype":["aat:300008706"],"id":2764990,"name:xx":"Whisky Creek"}}
>>>>>>> 03f74aca74312dbeaf24d7e61306dd6a786dc3d0
