{
  "id": 2413806,
  "type": "Feature",
  "properties": {
    "tgn:hierarchy":[
        "tgn:2413806",
        "tgn:1000001",
        "tgn:1002278",
        "tgn:7012149",
        "tgn:7007710",
        "tgn:7029392"
    ],
    "tgn:id":2413806,
    "tgn:name":"Irish Run",
    "tgn:placetype":[
        "aat:300008699"
    ]
},
  "bbox": [],
  "geometry": {"coordinates":[-78.6833,40.9833],"type":"Point"}
}