{
  "id": 2202932,
  "type": "Feature",
  "properties": {
    "tgn:hierarchy":[
        "tgn:2202932",
        "tgn:1000001",
        "tgn:7012149",
        "tgn:7007825",
        "tgn:7029392"
    ],
    "tgn:id":2202932,
    "tgn:name":"Buckeye Hollow",
    "tgn:placetype":[
        "aat:300008761"
    ]
},
  "bbox": [],
  "geometry": {"coordinates":[-87.5167,36.2167],"type":"Point"}
}