{
  "id": 2373307,
  "type": "Feature",
  "properties": {
    "tgn:hierarchy":[
        "tgn:2373307",
        "tgn:1000001",
        "tgn:7012149",
        "tgn:2002326",
        "tgn:7007922",
        "tgn:7029392"
    ],
    "tgn:id":2373307,
    "tgn:name":"Halverson Lake",
    "tgn:placetype":[
        "aat:300006191"
    ]
},
  "bbox": [],
  "geometry": {"coordinates":[-90.0833,43.0333],"type":"Point"}
}