{
  "id": 2693821,
  "type": "Feature",
  "properties": {
    "tgn:hierarchy":[
        "tgn:2693821",
        "tgn:1000001",
        "tgn:7012149",
        "tgn:7007708",
        "tgn:7029392"
    ],
    "tgn:id":2693821,
    "tgn:name":"Sterling Gulch",
    "tgn:placetype":[
        "aat:300008761"
    ]
},
  "bbox": [],
  "geometry": {"coordinates":[-116.9667,45.7167],"type":"Point"}
}