<<<<<<< HEAD
{
  "id": 2150518,
  "type": "Feature",
  "properties": {
    "tgn:hierarchy":[
        "tgn:2150518",
        "tgn:1000001",
        "tgn:7012149",
        "tgn:2000206",
        "tgn:7007158",
        "tgn:7029392"
    ],
    "tgn:id":2150518,
    "tgn:name":"Basin Reservoir Number 2",
    "tgn:placetype":[
        "aat:300006191"
    ]
},
  "bbox": [],
  "geometry": {"coordinates":[-108.0333,39.0],"type":"Point"}
}
=======
{"geometry":{"type":"Point","coordinates":[-108.033300,39.000000]},"type":"Feature","properties":{"hierarchy":["tgn:2150518","tgn:1000001","tgn:7012149","tgn:2000206","tgn:7007158","tgn:7029392"],"placetype":["aat:300006191"],"id":2150518,"name:xx":"Basin Reservoir Number 2"}}
>>>>>>> 03f74aca74312dbeaf24d7e61306dd6a786dc3d0
