{
  "id": 7343599,
  "type": "Feature",
  "properties": {
    "tgn:hierarchy":[
        "tgn:7343599",
        "tgn:7002759",
        "tgn:7008909",
        "tgn:1000003",
        "tgn:1000095",
        "tgn:7029392"
    ],
    "tgn:id":7343599,
    "tgn:name":"Campodarbe",
    "tgn:placetype":[
        "aat:300008347"
    ]
},
  "bbox": [],
  "geometry": {"coordinates":[0.016089,42.422191],"type":"Point"}
}