{
  "id": 2757977,
  "type": "Feature",
  "properties": {
    "tgn:hierarchy":[
        "tgn:2757977",
        "tgn:1000001",
        "tgn:7012149",
        "tgn:2000986",
        "tgn:7007520",
        "tgn:7029392"
    ],
    "tgn:id":2757977,
    "tgn:name":"West Branch Ontonagon River",
    "tgn:placetype":[
        "aat:300008707"
    ]
},
  "bbox": [],
  "geometry": {"coordinates":[-89.5333,46.5833],"type":"Point"}
}