{
  "id": 2674643,
  "type": "Feature",
  "properties": {
    "tgn:hierarchy":[
        "tgn:2674643",
        "tgn:1000001",
        "tgn:7012149",
        "tgn:7007157",
        "tgn:1002957",
        "tgn:7029392"
    ],
    "tgn:id":2674643,
    "tgn:name":"Soap Creek",
    "tgn:placetype":[
        "aat:300008706"
    ]
},
  "bbox": [],
  "geometry": {"coordinates":[-120.1333,38.2167],"type":"Point"}
}