{
  "id": 2765349,
  "type": "Feature",
  "properties": {
    "tgn:hierarchy":[
        "tgn:2765349",
        "tgn:1000001",
        "tgn:7012149",
        "tgn:2001449",
        "tgn:7007566",
        "tgn:7029392"
    ],
    "tgn:id":2765349,
    "tgn:name":"White",
    "tgn:placetype":[
        "aat:300000390"
    ]
},
  "bbox": [],
  "geometry": {"coordinates":[-106.0333,36.5167],"type":"Point"}
}