{
  "id": 2681127,
  "type": "Feature",
  "properties": {
    "tgn:hierarchy":[
        "tgn:2681127",
        "tgn:1000001",
        "tgn:7012149",
        "tgn:7007157",
        "tgn:2000186",
        "tgn:7029392"
    ],
    "tgn:id":2681127,
    "tgn:name":"South Mountain",
    "tgn:placetype":[
        "aat:300008798"
    ]
},
  "bbox": [],
  "geometry": {"coordinates":[-120.6333,41.8333],"type":"Point"}
}