{
  "id": 7176398,
  "type": "Feature",
  "properties": {
    "tgn:hierarchy":[
        "tgn:7176398",
        "tgn:1000003",
        "tgn:7003688",
        "tgn:7000084",
        "tgn:7029392"
    ],
    "tgn:id":7176398,
    "tgn:name":"Gr\u00fcnh\u00f6rn",
    "tgn:placetype":[
        "aat:300008347"
    ]
},
  "bbox": [],
  "geometry": {"coordinates":[8.75,54.366667],"type":"Point"}
}