{
  "id": 2138229,
  "type": "Feature",
  "properties": {
    "tgn:hierarchy":[
        "tgn:2138229",
        "tgn:7006450",
        "tgn:1000001",
        "tgn:7012149",
        "tgn:2124002",
        "tgn:7029392"
    ],
    "tgn:id":2138229,
    "tgn:name":"Arthur Point",
    "tgn:placetype":[
        "aat:300008850"
    ]
},
  "bbox": [],
  "geometry": {"coordinates":[-135.5833,57.4333],"type":"Point"}
}