<<<<<<< HEAD
{
  "id": 2401081,
  "type": "Feature",
  "properties": {
    "tgn:hierarchy":[
        "tgn:2401081",
        "tgn:1000001",
        "tgn:7012149",
        "tgn:2002111",
        "tgn:7007827",
        "tgn:7029392"
    ],
    "tgn:id":2401081,
    "tgn:name":"Horse Valley",
    "tgn:placetype":[
        "aat:300386845"
    ]
},
  "bbox": [],
  "geometry": {"coordinates":[-113.0833,38.0833],"type":"Point"}
}
=======
{"geometry":{"type":"Point","coordinates":[-113.083300,38.083300]},"type":"Feature","properties":{"hierarchy":["tgn:2401081","tgn:1000001","tgn:7012149","tgn:2002111","tgn:7007827","tgn:7029392"],"placetype":["aat:300386845"],"id":2401081,"name:xx":"Horse Valley"}}
>>>>>>> 03f74aca74312dbeaf24d7e61306dd6a786dc3d0
