{
  "id": 1092616,
  "type": "Feature",
  "properties": {
    "tgn:hierarchy":[
        "tgn:1092616",
        "tgn:7001242",
        "tgn:1001747",
        "tgn:1000192",
        "tgn:7029392"
    ],
    "tgn:id":1092616,
    "tgn:name":"Baraawe",
    "tgn:placetype":[
        "aat:300008347"
    ]
},
  "bbox": [],
  "geometry": {"coordinates":[44.0333,1.0333],"type":"Point"}
}