{
  "id": 2735183,
  "type": "Feature",
  "properties": {
    "tgn:hierarchy":[
        "tgn:2735183",
        "tgn:7002659",
        "tgn:1000001",
        "tgn:7012149",
        "tgn:2000035",
        "tgn:7029392"
    ],
    "tgn:id":2735183,
    "tgn:name":"Twentythree Dollar Pit",
    "tgn:placetype":[
        "aat:300008746"
    ]
},
  "bbox": [],
  "geometry": {"coordinates":[-86.25,34.8833],"type":"Point"}
}