{
  "id": 2515753,
  "type": "Feature",
  "properties": {
    "tgn:hierarchy":[
        "tgn:2515753",
        "tgn:1000001",
        "tgn:2002324",
        "tgn:7012149",
        "tgn:7007922",
        "tgn:7029392"
    ],
    "tgn:id":2515753,
    "tgn:name":"Millville Creek",
    "tgn:placetype":[
        "aat:300008706"
    ]
},
  "bbox": [],
  "geometry": {"coordinates":[-90.85,42.9667],"type":"Point"}
}