{
  "id": 7091131,
  "type": "Feature",
  "properties": {
    "tgn:hierarchy":[
        "tgn:7091131",
        "tgn:7003692",
        "tgn:1000003",
        "tgn:7000084",
        "tgn:7029392"
    ],
    "tgn:id":7091131,
    "tgn:name":"Vogelplatz",
    "tgn:placetype":[
        "aat:300008347"
    ]
},
  "bbox": [],
  "geometry": {"coordinates":[9.65,47.916667],"type":"Point"}
}