<<<<<<< HEAD
{
  "id": 7476633,
  "type": "Feature",
  "properties": {
    "tgn:hierarchy":[
        "tgn:7476633",
        "tgn:1000004",
        "tgn:7004300",
        "tgn:1000141",
        "tgn:7029392"
    ],
    "tgn:id":7476633,
    "tgn:name":"Wanshan Ci",
    "tgn:placetype":[
        "aat:300007595"
    ]
},
  "bbox": [],
  "geometry": {"coordinates":[119.637296,23.556074],"type":"Point"}
}
=======
{"geometry":{"type":"Point","coordinates":[119.637296,23.556074]},"type":"Feature","properties":{"hierarchy":["tgn:7476633","tgn:1000004","tgn:7004300","tgn:1000141","tgn:7029392"],"placetype":["aat:300007595"],"id":7476633,"name:xx":"Wanshan Ci"}}
>>>>>>> 03f74aca74312dbeaf24d7e61306dd6a786dc3d0
