{
  "id": 7221274,
  "type": "Feature",
  "properties": {
    "tgn:hierarchy":[
        "tgn:7221274",
        "tgn:7002711",
        "tgn:7001338",
        "tgn:1000003",
        "tgn:1000074",
        "tgn:7029392"
    ],
    "tgn:id":7221274,
    "tgn:name":"Agn\u00ed, \u00c1kra",
    "tgn:placetype":[
        "aat:300266559"
    ]
},
  "bbox": [],
  "geometry": {"coordinates":[19.929722,39.735278],"type":"Point"}
}