{
  "id": 4011813,
  "type": "Feature",
  "properties": {
    "tgn:hierarchy":[
        "tgn:4011813",
        "tgn:1000003",
        "tgn:7003677",
        "tgn:7000084",
        "tgn:7029392"
    ],
    "tgn:id":4011813,
    "tgn:name":"Vilich",
    "tgn:placetype":[
        "aat:300008347"
    ]
},
  "bbox": [],
  "geometry": {"coordinates":[7.133333,50.75],"type":"Point"}
}