{
  "id": 1042012,
  "type": "Feature",
  "properties": {
    "tgn:hierarchy":[
        "tgn:1042012",
        "tgn:7011369",
        "tgn:7017076",
        "tgn:1000003",
        "tgn:1000074",
        "tgn:7029392"
    ],
    "tgn:id":1042012,
    "tgn:name":"Filiatr\u00e1",
    "tgn:placetype":[
        "aat:300008347"
    ]
},
  "bbox": [],
  "geometry": {"coordinates":[21.583333,37.15],"type":"Point"}
}