{
  "id": 2031423,
  "type": "Feature",
  "properties": {
    "tgn:hierarchy":[
        "tgn:2031423",
        "tgn:1000001",
        "tgn:1002282",
        "tgn:7012149",
        "tgn:7007252",
        "tgn:7029392"
    ],
    "tgn:id":2031423,
    "tgn:name":"Colfax",
    "tgn:placetype":[
        "aat:300008347"
    ]
},
  "bbox": [],
  "geometry": {"coordinates":[-86.6667,40.1833],"type":"Point"}
}