{
  "id": 7514233,
  "type": "Feature",
  "properties": {
    "tgn:hierarchy":[
        "tgn:7514233",
        "tgn:1009227",
        "tgn:1000226",
        "tgn:7016729",
        "tgn:1000006",
        "tgn:7029392"
    ],
    "tgn:id":7514233,
    "tgn:name:en":"East Head",
    "tgn:placetype":[
        "aat:300008850"
    ]
},
  "bbox": [],
  "geometry": {"coordinates":[174.316667,-41.216667],"type":"Point"}
}