{
  "id": 1010601,
  "type": "Feature",
  "properties": {
    "tgn:hierarchy":[
        "tgn:1010601",
        "tgn:7005735",
        "tgn:7005685",
        "tgn:1000001",
        "tgn:7013409",
        "tgn:7029392"
    ],
    "tgn:id":1010601,
    "tgn:name":"Cook, Cape",
    "tgn:placetype":[
        "aat:300008850"
    ]
},
  "bbox": [],
  "geometry": {"coordinates":[-127.9167,50.1333],"type":"Point"}
}