{
  "id": 7549941,
  "type": "Feature",
  "properties": {
    "tgn:hierarchy":[
        "tgn:7549941",
        "tgn:1000004",
        "tgn:1001871",
        "tgn:7000198",
        "tgn:7029392"
    ],
    "tgn:id":7549941,
    "tgn:name:en":"Dharson",
    "tgn:placetype":[
        "aat:300008347"
    ]
},
  "bbox": [],
  "geometry": {"coordinates":[76.083333,28.116667],"type":"Point"}
}