{
  "id": 2190319,
  "type": "Feature",
  "properties": {
    "tgn:hierarchy":[
        "tgn:2190319",
        "tgn:1000001",
        "tgn:2001261",
        "tgn:7012149",
        "tgn:7007524",
        "tgn:7029392"
    ],
    "tgn:id":2190319,
    "tgn:name":"Box Canyon",
    "tgn:placetype":[
        "aat:300008761"
    ]
},
  "bbox": [],
  "geometry": {"coordinates":[-107.9833,45.2667],"type":"Point"}
}