{
  "id": 7438489,
  "type": "Feature",
  "properties": {
    "tgn:hierarchy":[
        "tgn:7438489",
        "tgn:1000001",
        "tgn:7005595",
        "tgn:7005560",
        "tgn:7029392"
    ],
    "tgn:id":7438489,
    "tgn:name":"Tacuilole",
    "tgn:placetype":[
        "aat:300008347"
    ]
},
  "bbox": [],
  "geometry": {"coordinates":[-107.279444,24.851389],"type":"Point"}
}