{
  "id": 7324448,
  "type": "Feature",
  "properties": {
    "tgn:hierarchy":[
        "tgn:7324448",
        "tgn:7002842",
        "tgn:7001158",
        "tgn:1000003",
        "tgn:1000095",
        "tgn:7029392"
    ],
    "tgn:id":7324448,
    "tgn:name":"Sauquillo de Paredes",
    "tgn:placetype":[
        "aat:300008347"
    ]
},
  "bbox": [],
  "geometry": {"coordinates":[-2.966667,41.366667],"type":"Point"}
}