{
  "id": 2395317,
  "type": "Feature",
  "properties": {
    "tgn:hierarchy":[
        "tgn:2395317",
        "tgn:1000001",
        "tgn:7012149",
        "tgn:2001909",
        "tgn:7007825",
        "tgn:7029392"
    ],
    "tgn:id":2395317,
    "tgn:name":"Holiday Shores",
    "tgn:placetype":[
        "aat:300008347"
    ]
},
  "bbox": [],
  "geometry": {"coordinates":[-84.4667,35.8833],"type":"Point"}
}