{
  "id": 2495737,
  "type": "Feature",
  "properties": {
    "tgn:hierarchy":[
        "tgn:2495737",
        "tgn:1000001",
        "tgn:2001425",
        "tgn:7012149",
        "tgn:7007564",
        "tgn:7029392"
    ],
    "tgn:id":2495737,
    "tgn:name":"Mason Brook",
    "tgn:placetype":[
        "aat:300008699"
    ]
},
  "bbox": [],
  "geometry": {"coordinates":[-71.3667,43.2167],"type":"Point"}
}