{
  "id": 2093672,
  "type": "Feature",
  "properties": {
    "tgn:hierarchy":[
        "tgn:2093672",
        "tgn:1000001",
        "tgn:1002308",
        "tgn:7012149",
        "tgn:7007710",
        "tgn:7029392"
    ],
    "tgn:id":2093672,
    "tgn:name":"Teepleville",
    "tgn:placetype":[
        "aat:300008347",
        "aat:300387210"
    ]
},
  "bbox": [],
  "geometry": {"coordinates":[-79.9333,41.75],"type":"Point"}
}