{
  "id": 7306958,
  "type": "Feature",
  "properties": {
    "tgn:hierarchy":[
        "tgn:7306958",
        "tgn:7002832",
        "tgn:7001158",
        "tgn:1000003",
        "tgn:1000095",
        "tgn:7029392"
    ],
    "tgn:id":7306958,
    "tgn:name":"Magaz",
    "tgn:placetype":[
        "aat:300008347"
    ]
},
  "bbox": [],
  "geometry": {"coordinates":[-4.416667,41.983333],"type":"Point"}
}