{
  "id": 2141803,
  "type": "Feature",
  "properties": {
    "tgn:hierarchy":[
        "tgn:2141803",
        "tgn:1000001",
        "tgn:7006451",
        "tgn:7012149",
        "tgn:2000100",
        "tgn:7029392"
    ],
    "tgn:id":2141803,
    "tgn:name":"Baboquivari Wash",
    "tgn:placetype":[
        "aat:300008699"
    ]
},
  "bbox": [],
  "geometry": {"coordinates":[-111.5833,31.7667],"type":"Point"}
}