<<<<<<< HEAD
{
  "id": 2331089,
  "type": "Feature",
  "properties": {
    "tgn:hierarchy":[
        "tgn:2331089",
        "tgn:1000001",
        "tgn:7012149",
        "tgn:2001487",
        "tgn:7007709",
        "tgn:7029392"
    ],
    "tgn:id":2331089,
    "tgn:name":"Flat Swamp Ditch",
    "tgn:placetype":[
        "aat:300006075"
    ]
},
  "bbox": [],
  "geometry": {"coordinates":[-78.8,35.1167],"type":"Point"}
}
=======
{"geometry":{"type":"Point","coordinates":[-78.800000,35.116700]},"type":"Feature","properties":{"hierarchy":["tgn:2331089","tgn:1000001","tgn:7012149","tgn:2001487","tgn:7007709","tgn:7029392"],"placetype":["aat:300006075"],"id":2331089,"name:xx":"Flat Swamp Ditch"}}
>>>>>>> 03f74aca74312dbeaf24d7e61306dd6a786dc3d0
