{
  "id": 2068858,
  "type": "Feature",
  "properties": {
    "tgn:hierarchy":[
        "tgn:2068858",
        "tgn:1000001",
        "tgn:7012149",
        "tgn:1002882",
        "tgn:7007568",
        "tgn:7029392"
    ],
    "tgn:id":2068858,
    "tgn:name":"Dublin",
    "tgn:placetype":[
        "aat:300008347",
        "aat:300387210"
    ]
},
  "bbox": [],
  "geometry": {"coordinates":[-76.9167,42.9833],"type":"Point"}
}