{
  "id": 7126400,
  "type": "Feature",
  "properties": {
    "tgn:hierarchy":[
        "tgn:7126400",
        "tgn:1000003",
        "tgn:7003677",
        "tgn:7000084",
        "tgn:7029392"
    ],
    "tgn:id":7126400,
    "tgn:name":"Oberbreunfeld",
    "tgn:placetype":[
        "aat:300008347"
    ]
},
  "bbox": [],
  "geometry": {"coordinates":[7.55,50.916667],"type":"Point"}
}