<<<<<<< HEAD
{
  "id": 2768686,
  "type": "Feature",
  "properties": {
    "tgn:hierarchy":[
        "tgn:2768686",
        "tgn:7002659",
        "tgn:1000001",
        "tgn:7012149",
        "tgn:2000029",
        "tgn:7029392"
    ],
    "tgn:id":2768686,
    "tgn:name":"Whitlock Branch",
    "tgn:placetype":[
        "aat:300008699"
    ]
},
  "bbox": [],
  "geometry": {"coordinates":[-87.6167,34.5167],"type":"Point"}
}
=======
{"geometry":{"type":"Point","coordinates":[-87.616700,34.516700]},"type":"Feature","properties":{"hierarchy":["tgn:2768686","tgn:7002659","tgn:1000001","tgn:7012149","tgn:2000029","tgn:7029392"],"placetype":["aat:300008699"],"id":2768686,"name:xx":"Whitlock Branch"}}
>>>>>>> 03f74aca74312dbeaf24d7e61306dd6a786dc3d0
