{
  "id": 7383783,
  "type": "Feature",
  "properties": {
    "tgn:hierarchy":[
        "tgn:7383783",
        "tgn:7005581",
        "tgn:1000001",
        "tgn:7005560",
        "tgn:7029392"
    ],
    "tgn:id":7383783,
    "tgn:name":"Nabogame, Arroyo",
    "tgn:placetype":[
        "aat:300008699"
    ]
},
  "bbox": [],
  "geometry": {"coordinates":[-106.95,26.233333],"type":"Point"}
}