{
  "id": 2155416,
  "type": "Feature",
  "properties": {
    "tgn:hierarchy":[
        "tgn:2155416",
        "tgn:2000105",
        "tgn:1000001",
        "tgn:7016172",
        "tgn:7012149",
        "tgn:7029392"
    ],
    "tgn:id":2155416,
    "tgn:name":"Bear Pond",
    "tgn:placetype":[
        "aat:300008680"
    ]
},
  "bbox": [],
  "geometry": {"coordinates":[-91.15,33.9667],"type":"Point"}
}