{
  "id": 7469710,
  "type": "Feature",
  "properties": {
    "tgn:hierarchy":[
        "tgn:7469710",
        "tgn:1000004",
        "tgn:7492971",
        "tgn:1000141",
        "tgn:7029392"
    ],
    "tgn:id":7469710,
    "tgn:name":"Xiapou",
    "tgn:placetype":[
        "aat:300008347"
    ]
},
  "bbox": [],
  "geometry": {"coordinates":[120.479831,22.576213],"type":"Point"}
}