<<<<<<< HEAD
{
  "id": 7356124,
  "type": "Feature",
  "properties": {
    "tgn:hierarchy":[
        "tgn:7356124",
        "tgn:1000001",
        "tgn:1001906",
        "tgn:7005560",
        "tgn:7029392"
    ],
    "tgn:id":7356124,
    "tgn:name":"Camalota",
    "tgn:placetype":[
        "aat:300008347"
    ]
},
  "bbox": [],
  "geometry": {"coordinates":[-105.2,21.516667],"type":"Point"}
}
=======
{"geometry":{"type":"Point","coordinates":[-105.200000,21.516667]},"type":"Feature","properties":{"hierarchy":["tgn:7356124","tgn:1000001","tgn:1001906","tgn:7005560","tgn:7029392"],"placetype":["aat:300008347"],"id":7356124,"name:xx":"Camalota"}}
>>>>>>> 03f74aca74312dbeaf24d7e61306dd6a786dc3d0
