{
  "id": 2339507,
  "type": "Feature",
  "properties": {
    "tgn:hierarchy":[
        "tgn:2339507",
        "tgn:1000001",
        "tgn:7012149",
        "tgn:7007923",
        "tgn:7029392"
    ],
    "tgn:id":2339507,
    "tgn:name":"Fred Draw",
    "tgn:placetype":[
        "aat:300008761"
    ]
},
  "bbox": [],
  "geometry": {"coordinates":[-104.7667,43.45],"type":"Point"}
}