{
  "id": 2759663,
  "type": "Feature",
  "properties": {
    "tgn:hierarchy":[
        "tgn:2759663",
        "tgn:1000001",
        "tgn:7012149",
        "tgn:7007825",
        "tgn:7029392"
    ],
    "tgn:id":2759663,
    "tgn:name":"West Fork Gunstocker Creek",
    "tgn:placetype":[
        "aat:300008706"
    ]
},
  "bbox": [],
  "geometry": {"coordinates":[-84.9833,35.2833],"type":"Point"}
}