{
  "id": 2294999,
  "type": "Feature",
  "properties": {
    "tgn:hierarchy":[
        "tgn:2294999",
        "tgn:1000001",
        "tgn:7012149",
        "tgn:2001711",
        "tgn:7007708",
        "tgn:7029392"
    ],
    "tgn:id":2294999,
    "tgn:name":"Draper",
    "tgn:placetype":[
        "aat:300008347"
    ]
},
  "bbox": [],
  "geometry": {"coordinates":[-123.1167,42.35],"type":"Point"}
}