{
  "id": 2508762,
  "type": "Feature",
  "properties": {
    "tgn:hierarchy":[
        "tgn:2508762",
        "tgn:1000001",
        "tgn:2000459",
        "tgn:7012149",
        "tgn:7007250",
        "tgn:7029392"
    ],
    "tgn:id":2508762,
    "tgn:name":"Middle Fork Big Pine Creek",
    "tgn:placetype":[
        "aat:300008706"
    ]
},
  "bbox": [],
  "geometry": {"coordinates":[-115.7167,44.1667],"type":"Point"}
}