{
  "id": 7565923,
  "type": "Feature",
  "properties": {
    "tgn:hierarchy":[
        "tgn:7565923",
        "tgn:1000004",
        "tgn:7000198",
        "tgn:7016722",
        "tgn:7029392"
    ],
    "tgn:id":7565923,
    "tgn:name:en":"Bijw\u0101ha",
    "tgn:placetype":[
        "aat:300008347"
    ]
},
  "bbox": [],
  "geometry": {"coordinates":[79.449386,26.364251],"type":"Point"}
}