{
  "id": 2511850,
  "type": "Feature",
  "properties": {
    "tgn:hierarchy":[
        "tgn:2511850",
        "tgn:1000001",
        "tgn:7012149",
        "tgn:7019676",
        "tgn:7007566",
        "tgn:7029392"
    ],
    "tgn:id":2511850,
    "tgn:name":"Milk Lake",
    "tgn:placetype":[
        "aat:300008680"
    ]
},
  "bbox": [],
  "geometry": {"coordinates":[-108.2333,35.8833],"type":"Point"}
}