{
  "id": 7307777,
  "type": "Feature",
  "properties": {
    "tgn:hierarchy":[
        "tgn:7307777",
        "tgn:7002758",
        "tgn:7002821",
        "tgn:1000003",
        "tgn:1000095",
        "tgn:7029392"
    ],
    "tgn:id":7307777,
    "tgn:name":"Margen de Abajo",
    "tgn:placetype":[
        "aat:300008347"
    ]
},
  "bbox": [],
  "geometry": {"coordinates":[-2.566667,37.633333],"type":"Point"}
}