{
  "id": 7064804,
  "type": "Feature",
  "properties": {
    "tgn:hierarchy":[
        "tgn:7064804",
        "tgn:7003692",
        "tgn:1000003",
        "tgn:7000084",
        "tgn:7029392"
    ],
    "tgn:id":7064804,
    "tgn:name":"Unterfischach",
    "tgn:placetype":[
        "aat:300008347"
    ]
},
  "bbox": [],
  "geometry": {"coordinates":[9.874722,49.026111],"type":"Point"}
}