{
  "id": 2022547,
  "type": "Feature",
  "properties": {
    "tgn:hierarchy":[
        "tgn:2022547",
        "tgn:1000001",
        "tgn:7012149",
        "tgn:2000346",
        "tgn:7007248",
        "tgn:7029392"
    ],
    "tgn:id":2022547,
    "tgn:name":"Colwell",
    "tgn:placetype":[
        "aat:300008347",
        "aat:300387210"
    ]
},
  "bbox": [],
  "geometry": {"coordinates":[-84.4667,34.8833],"type":"Point"}
}