{
  "id": 7498388,
  "type": "Feature",
  "properties": {
    "tgn:hierarchy":[
        "tgn:7498388",
        "tgn:1000004",
        "tgn:7491221",
        "tgn:1000141",
        "tgn:7029392"
    ],
    "tgn:id":7498388,
    "tgn:name":"Mobaolai Shan",
    "tgn:placetype":[
        "aat:300008798"
    ]
},
  "bbox": [],
  "geometry": {"coordinates":[120.972405,23.281985],"type":"Point"}
}