{
  "id": 2245991,
  "type": "Feature",
  "properties": {
    "tgn:hierarchy":[
        "tgn:2245991",
        "tgn:1000001",
        "tgn:7012149",
        "tgn:2001216",
        "tgn:7007523",
        "tgn:7029392"
    ],
    "tgn:id":2245991,
    "tgn:name":"Coal Mine Hill",
    "tgn:placetype":[
        "aat:300008798"
    ]
},
  "bbox": [],
  "geometry": {"coordinates":[-94.2833,36.7333],"type":"Point"}
}