{
  "id": 2542152,
  "type": "Feature",
  "properties": {
    "tgn:hierarchy":[
        "tgn:2542152",
        "tgn:7006450",
        "tgn:1000001",
        "tgn:7012149",
        "tgn:2000087",
        "tgn:7029392"
    ],
    "tgn:id":2542152,
    "tgn:name":"Nitumat Creek",
    "tgn:placetype":[
        "aat:300008706"
    ]
},
  "bbox": [],
  "geometry": {"coordinates":[-165.95,61.7833],"type":"Point"}
}