<<<<<<< HEAD
{
  "id": 7051357,
  "type": "Feature",
  "properties": {
    "tgn:hierarchy":[
        "tgn:7051357",
        "tgn:1003478",
        "tgn:1000003",
        "tgn:7003120",
        "tgn:1000080",
        "tgn:7029392"
    ],
    "tgn:id":7051357,
    "tgn:name":"La Frua",
    "tgn:placetype":[
        "aat:300008347"
    ]
},
  "bbox": [],
  "geometry": {"coordinates":[8.4,46.4],"type":"Point"}
}
=======
{"geometry":{"type":"Point","coordinates":[8.400000,46.400000]},"type":"Feature","properties":{"hierarchy":["tgn:7051357","tgn:1003478","tgn:1000003","tgn:7003120","tgn:1000080","tgn:7029392"],"placetype":["aat:300008347"],"id":7051357,"name:xx":"La Frua"}}
>>>>>>> 03f74aca74312dbeaf24d7e61306dd6a786dc3d0
