{
  "id": 7001950,
  "type": "Feature",
  "properties": {
    "tgn:hierarchy":[
        "tgn:7001950",
        "tgn:7000490",
        "tgn:1000006",
        "tgn:7001834",
        "tgn:7029392"
    ],
    "tgn:id":7001950,
    "tgn:name":"Big Bell",
    "tgn:placetype":[
        "aat:300008347"
    ]
},
  "bbox": [],
  "geometry": {"coordinates":[117.5833,-27.3333],"type":"Point"}
}