<<<<<<< HEAD
{
  "id": 2151455,
  "type": "Feature",
  "properties": {
    "tgn:hierarchy":[
        "tgn:2151455",
        "tgn:1000001",
        "tgn:7012149",
        "tgn:2001437",
        "tgn:7007566",
        "tgn:7029392"
    ],
    "tgn:id":2151455,
    "tgn:name":"Bathtub Draw",
    "tgn:placetype":[
        "aat:300008761"
    ]
},
  "bbox": [],
  "geometry": {"coordinates":[-108.95,32.9833],"type":"Point"}
}
=======
{"geometry":{"type":"Point","coordinates":[-108.950000,32.983300]},"type":"Feature","properties":{"hierarchy":["tgn:2151455","tgn:1000001","tgn:7012149","tgn:2001437","tgn:7007566","tgn:7029392"],"placetype":["aat:300008761"],"id":2151455,"name:xx":"Bathtub Draw"}}
>>>>>>> 03f74aca74312dbeaf24d7e61306dd6a786dc3d0
