{
  "id": 7383321,
  "type": "Feature",
  "properties": {
    "tgn:hierarchy":[
        "tgn:7383321",
        "tgn:7005583",
        "tgn:1000001",
        "tgn:7005560",
        "tgn:7029392"
    ],
    "tgn:id":7383321,
    "tgn:name":"Mulas, Arroyo de las",
    "tgn:placetype":[
        "aat:300266554",
        "aat:300008699"
    ]
},
  "bbox": [],
  "geometry": {"coordinates":[-104.45,24.933333],"type":"Point"}
}