{
  "id": 2378315,
  "type": "Feature",
  "properties": {
    "tgn:hierarchy":[
        "tgn:2378315",
        "tgn:1000001",
        "tgn:7012149",
        "tgn:2002373",
        "tgn:7007923",
        "tgn:7029392"
    ],
    "tgn:id":2378315,
    "tgn:name":"Harris Spring",
    "tgn:placetype":[
        "aat:300008697"
    ]
},
  "bbox": [],
  "geometry": {"coordinates":[-108.3333,43.7667],"type":"Point"}
}