{
  "id": 2392815,
  "type": "Feature",
  "properties": {
    "tgn:hierarchy":[
        "tgn:2392815",
        "tgn:1000001",
        "tgn:1002235",
        "tgn:7012149",
        "tgn:7007919",
        "tgn:7029392"
    ],
    "tgn:id":2392815,
    "tgn:name":"Hobby Swamp",
    "tgn:placetype":[
        "aat:300008699"
    ]
},
  "bbox": [],
  "geometry": {"coordinates":[-77.4667,38.0167],"type":"Point"}
}