{
  "id": 2542253,
  "type": "Feature",
  "properties": {
    "tgn:hierarchy":[
        "tgn:2542253",
        "tgn:1002309",
        "tgn:1000001",
        "tgn:7012149",
        "tgn:7007565",
        "tgn:7029392"
    ],
    "tgn:id":2542253,
    "tgn:name":"Nixons Branch",
    "tgn:placetype":[
        "aat:300008699"
    ]
},
  "bbox": [],
  "geometry": {"coordinates":[-74.9167,39.3333],"type":"Point"}
}