{
  "id": 7406452,
  "type": "Feature",
  "properties": {
    "tgn:hierarchy":[
        "tgn:7406452",
        "tgn:7005578",
        "tgn:1000001",
        "tgn:7005560",
        "tgn:7029392"
    ],
    "tgn:id":7406452,
    "tgn:name":"El Treinta",
    "tgn:placetype":[
        "aat:300008347"
    ]
},
  "bbox": [],
  "geometry": {"coordinates":[-90.475,18.1125],"type":"Point"}
}