{
  "id": 7588568,
  "type": "Feature",
  "properties": {
    "tgn:hierarchy":[
        "tgn:7588568",
        "tgn:1000004",
        "tgn:7000198",
        "tgn:7000799",
        "tgn:7029392"
    ],
    "tgn:id":7588568,
    "tgn:name:en":"Budan",
    "tgn:placetype":[
        "aat:300008347"
    ]
},
  "bbox": [],
  "geometry": {"coordinates":[74.71848,34.042211],"type":"Point"}
}