{
  "id": 2140233,
  "type": "Feature",
  "properties": {
    "tgn:hierarchy":[
        "tgn:2140233",
        "tgn:1000001",
        "tgn:7012149",
        "tgn:2002124",
        "tgn:7007827",
        "tgn:7029392"
    ],
    "tgn:id":2140233,
    "tgn:name":"Augusi Canyon",
    "tgn:placetype":[
        "aat:300008761"
    ]
},
  "bbox": [],
  "geometry": {"coordinates":[-109.0833,39.65],"type":"Point"}
}