{
  "id": 2475509,
  "type": "Feature",
  "properties": {
    "tgn:hierarchy":[
        "tgn:2475509",
        "tgn:1000001",
        "tgn:7012149",
        "tgn:2001437",
        "tgn:7007566",
        "tgn:7029392"
    ],
    "tgn:id":2475509,
    "tgn:name":"Luck Manganese Mine",
    "tgn:placetype":[
        "aat:300000390"
    ]
},
  "bbox": [],
  "geometry": {"coordinates":[-108.2667,32.7667],"type":"Point"}
}