<<<<<<< HEAD
{
  "id": 2409401,
  "type": "Feature",
  "properties": {
    "tgn:hierarchy":[
        "tgn:2409401",
        "tgn:1000001",
        "tgn:7012149",
        "tgn:2000488",
        "tgn:7007250",
        "tgn:7029392"
    ],
    "tgn:id":2409401,
    "tgn:name":"Idaho Lake",
    "tgn:placetype":[
        "aat:300008680"
    ]
},
  "bbox": [],
  "geometry": {"coordinates":[-115.45,42.0],"type":"Point"}
}
=======
{"geometry":{"type":"Point","coordinates":[-115.450000,42.000000]},"type":"Feature","properties":{"hierarchy":["tgn:2409401","tgn:1000001","tgn:7012149","tgn:2000488","tgn:7007250","tgn:7029392"],"placetype":["aat:300008680"],"id":2409401,"name:xx":"Idaho Lake"}}
>>>>>>> 03f74aca74312dbeaf24d7e61306dd6a786dc3d0
