{
  "id": 2291598,
  "type": "Feature",
  "properties": {
    "tgn:hierarchy":[
        "tgn:2291598",
        "tgn:1000001",
        "tgn:7012149",
        "tgn:2002122",
        "tgn:7007827",
        "tgn:7029392"
    ],
    "tgn:id":2291598,
    "tgn:name":"Dollar Lake",
    "tgn:placetype":[
        "aat:300008680"
    ]
},
  "bbox": [],
  "geometry": {"coordinates":[-110.3667,40.8167],"type":"Point"}
}