{
  "id": 2677974,
  "type": "Feature",
  "properties": {
    "tgn:hierarchy":[
        "tgn:2677974",
        "tgn:1000001",
        "tgn:7012149",
        "tgn:7007920",
        "tgn:7029392"
    ],
    "tgn:id":2677974,
    "tgn:name":"South Fork Asotin Creek",
    "tgn:placetype":[
        "aat:300008706"
    ]
},
  "bbox": [],
  "geometry": {"coordinates":[-117.4167,46.1333],"type":"Point"}
}