{
  "id": 2641781,
  "type": "Feature",
  "properties": {
    "tgn:hierarchy":[
        "tgn:2641781",
        "tgn:1000001",
        "tgn:7012149",
        "tgn:2001987",
        "tgn:7007826",
        "tgn:7029392"
    ],
    "tgn:id":2641781,
    "tgn:name":"Sand Hollow",
    "tgn:placetype":[
        "aat:300008761"
    ]
},
  "bbox": [],
  "geometry": {"coordinates":[-99.0167,28.9167],"type":"Point"}
}