<<<<<<< HEAD
{
  "id": 2767676,
  "type": "Feature",
  "properties": {
    "tgn:hierarchy":[
        "tgn:2767676",
        "tgn:1000001",
        "tgn:7012149",
        "tgn:1002672",
        "tgn:7007922",
        "tgn:7029392"
    ],
    "tgn:id":2767676,
    "tgn:name":"Whitefish Bay",
    "tgn:placetype":[
        "aat:300132316"
    ]
},
  "bbox": [],
  "geometry": {"coordinates":[-87.8833,43.1167],"type":"Point"}
}
=======
{"geometry":{"type":"Point","coordinates":[-87.883300,43.116700]},"type":"Feature","properties":{"hierarchy":["tgn:2767676","tgn:1000001","tgn:7012149","tgn:1002672","tgn:7007922","tgn:7029392"],"placetype":["aat:300132316"],"id":2767676,"name:xx":"Whitefish Bay"}}
>>>>>>> 03f74aca74312dbeaf24d7e61306dd6a786dc3d0
