{
  "id": 7330308,
  "type": "Feature",
  "properties": {
    "tgn:hierarchy":[
        "tgn:7330308",
        "tgn:7002822",
        "tgn:1001647",
        "tgn:1000003",
        "tgn:1000095",
        "tgn:7029392"
    ],
    "tgn:id":7330308,
    "tgn:name":"Hondo, Arroyo",
    "tgn:placetype":[
        "aat:300008699"
    ]
},
  "bbox": [],
  "geometry": {"coordinates":[-3.35,40.966667],"type":"Point"}
}