{
  "id": 2390719,
  "type": "Feature",
  "properties": {
    "tgn:hierarchy":[
        "tgn:2390719",
        "tgn:1000001",
        "tgn:7012149",
        "tgn:2001864",
        "tgn:7007825",
        "tgn:7029392"
    ],
    "tgn:id":2390719,
    "tgn:name":"Hightower Hollow",
    "tgn:placetype":[
        "aat:300008761"
    ]
},
  "bbox": [],
  "geometry": {"coordinates":[-87.0333,35.0667],"type":"Point"}
}