{
  "id": 7105996,
  "type": "Feature",
  "properties": {
    "tgn:hierarchy":[
        "tgn:7105996",
        "tgn:7003692",
        "tgn:1000003",
        "tgn:7000084",
        "tgn:7029392"
    ],
    "tgn:id":7105996,
    "tgn:name":"Scheuerlen",
    "tgn:placetype":[
        "aat:300000206"
    ]
},
  "bbox": [],
  "geometry": {"coordinates":[9.716667,47.916667],"type":"Point"}
}