{
  "id": 7574763,
  "type": "Feature",
  "properties": {
    "tgn:hierarchy":[
        "tgn:7574763",
        "tgn:1001828",
        "tgn:1000004",
        "tgn:7000198",
        "tgn:7029392"
    ],
    "tgn:id":7574763,
    "tgn:name:en":"Maddimadugu",
    "tgn:placetype":[
        "aat:300008347"
    ]
},
  "bbox": [],
  "geometry": {"coordinates":[78.783333,14.333333],"type":"Point"}
}