{
  "id": 7441232,
  "type": "Feature",
  "properties": {
    "tgn:hierarchy":[
        "tgn:7441232",
        "tgn:7005586",
        "tgn:1000001",
        "tgn:7005560",
        "tgn:7029392"
    ],
    "tgn:id":7441232,
    "tgn:name":"San Pablo",
    "tgn:placetype":[
        "aat:300008347"
    ]
},
  "bbox": [],
  "geometry": {"coordinates":[-104.483333,20.45],"type":"Point"}
}