{
  "id": 7564847,
  "type": "Feature",
  "properties": {
    "tgn:hierarchy":[
        "tgn:7564847",
        "tgn:1000004",
        "tgn:7000198",
        "tgn:7016722",
        "tgn:7029392"
    ],
    "tgn:id":7564847,
    "tgn:name:en":"Ganeshpur",
    "tgn:placetype":[
        "aat:300008347"
    ]
},
  "bbox": [],
  "geometry": {"coordinates":[79.700313,26.897169],"type":"Point"}
}