{
  "id": 2229459,
  "type": "Feature",
  "properties": {
    "tgn:hierarchy":[
        "tgn:2229459",
        "tgn:1002247",
        "tgn:1000001",
        "tgn:7012149",
        "tgn:7007516",
        "tgn:7029392"
    ],
    "tgn:id":2229459,
    "tgn:name":"Cedar Point",
    "tgn:placetype":[
        "aat:300008850"
    ]
},
  "bbox": [],
  "geometry": {"coordinates":[-75.8333,39.5833],"type":"Point"}
}