{
  "id": 7069860,
  "type": "Feature",
  "properties": {
    "tgn:hierarchy":[
        "tgn:7069860",
        "tgn:1000003",
        "tgn:7003676",
        "tgn:7000084",
        "tgn:7029392"
    ],
    "tgn:id":7069860,
    "tgn:name":"Tj\u00fccher Wilde",
    "tgn:placetype":[
        "aat:300000206"
    ]
},
  "bbox": [],
  "geometry": {"coordinates":[7.316667,53.533333],"type":"Point"}
}