{
  "id": 2113494,
  "type": "Feature",
  "properties": {
    "tgn:hierarchy":[
        "tgn:2113494",
        "tgn:1000001",
        "tgn:7012149",
        "tgn:2002194",
        "tgn:7007919",
        "tgn:7029392"
    ],
    "tgn:id":2113494,
    "tgn:name":"Old Glade Spring",
    "tgn:placetype":[
        "aat:300008347",
        "aat:300387210"
    ]
},
  "bbox": [],
  "geometry": {"coordinates":[-81.7667,36.7667],"type":"Point"}
}