{
  "id": 2436940,
  "type": "Feature",
  "properties": {
    "tgn:hierarchy":[
        "tgn:2436940",
        "tgn:2001623",
        "tgn:1000001",
        "tgn:7012149",
        "tgn:7007707",
        "tgn:7029392"
    ],
    "tgn:id":2436940,
    "tgn:name":"Kill Hollow",
    "tgn:placetype":[
        "aat:300008761"
    ]
},
  "bbox": [],
  "geometry": {"coordinates":[-94.6833,36.0833],"type":"Point"}
}