{
  "id": 2086364,
  "type": "Feature",
  "properties": {
    "tgn:hierarchy":[
        "tgn:2086364",
        "tgn:1000001",
        "tgn:1002194",
        "tgn:7012149",
        "tgn:7007710",
        "tgn:7029392"
    ],
    "tgn:id":2086364,
    "tgn:name":"Berrytown",
    "tgn:placetype":[
        "aat:300008347",
        "aat:300387210"
    ]
},
  "bbox": [],
  "geometry": {"coordinates":[-76.7667,41.8833],"type":"Point"}
}