{
  "id": 2683096,
  "type": "Feature",
  "properties": {
    "tgn:hierarchy":[
        "tgn:2683096",
        "tgn:2001086",
        "tgn:1000001",
        "tgn:7012149",
        "tgn:7007522",
        "tgn:7029392"
    ],
    "tgn:id":2683096,
    "tgn:name":"Spanish Bayou",
    "tgn:placetype":[
        "aat:300008699"
    ]
},
  "bbox": [],
  "geometry": {"coordinates":[-91.3833,31.55],"type":"Point"}
}