{
  "id": 2323955,
  "type": "Feature",
  "properties": {
    "tgn:hierarchy":[
        "tgn:2323955",
        "tgn:1000001",
        "tgn:7012149",
        "tgn:2000213",
        "tgn:7007158",
        "tgn:7029392"
    ],
    "tgn:id":2323955,
    "tgn:name":"Fawn Hollow",
    "tgn:placetype":[
        "aat:300008761"
    ]
},
  "bbox": [],
  "geometry": {"coordinates":[-105.1833,38.3833],"type":"Point"}
}