{
  "id": 1074454,
  "type": "Feature",
  "properties": {
    "tgn:hierarchy":[
        "tgn:1074454",
        "tgn:1000004",
        "tgn:7000198",
        "tgn:1001882",
        "tgn:7029392"
    ],
    "tgn:id":1074454,
    "tgn:name:en":"Arsikere",
    "tgn:placetype":[
        "aat:300008347"
    ]
},
  "bbox": [],
  "geometry": {"coordinates":[76.256111,13.313889],"type":"Point"}
}