{
  "id": 7060789,
  "type": "Feature",
  "properties": {
    "tgn:hierarchy":[
        "tgn:7060789",
        "tgn:1000003",
        "tgn:7000094",
        "tgn:7000084",
        "tgn:7029392"
    ],
    "tgn:id":7060789,
    "tgn:name":"Alt Pansow",
    "tgn:placetype":[
        "aat:300008347"
    ]
},
  "bbox": [],
  "geometry": {"coordinates":[13.25,54.05],"type":"Point"}
}