{
  "id": 5001078,
  "type": "Feature",
  "properties": {
    "tgn:hierarchy":[
        "tgn:5001078",
        "tgn:1000003",
        "tgn:7002885",
        "tgn:1000070",
        "tgn:7029392"
    ],
    "tgn:id":5001078,
    "tgn:name":"Azille",
    "tgn:placetype":[
        "aat:300008347"
    ]
},
  "bbox": [],
  "geometry": {"coordinates":[2.6667,43.2833],"type":"Point"}
}