{
  "id": 2718459,
  "type": "Feature",
  "properties": {
    "tgn:hierarchy":[
        "tgn:2718459",
        "tgn:1000001",
        "tgn:7012149",
        "tgn:2001293",
        "tgn:7007524",
        "tgn:7029392"
    ],
    "tgn:id":2718459,
    "tgn:name":"Thompson Lake",
    "tgn:placetype":[
        "aat:300008680"
    ]
},
  "bbox": [],
  "geometry": {"coordinates":[-110.55,45.1667],"type":"Point"}
}