{
  "id": 7353474,
  "type": "Feature",
  "properties": {
    "tgn:hierarchy":[
        "tgn:7353474",
        "tgn:1000001",
        "tgn:7005589",
        "tgn:7005560",
        "tgn:7029392"
    ],
    "tgn:id":7353474,
    "tgn:name":"Rancho Benavides",
    "tgn:placetype":[
        "aat:300000241"
    ]
},
  "bbox": [],
  "geometry": {"coordinates":[-99.633333,26.066667],"type":"Point"}
}