{
  "id": 7317595,
  "type": "Feature",
  "properties": {
    "tgn:hierarchy":[
        "tgn:7317595",
        "tgn:1001699",
        "tgn:1000049",
        "tgn:1000002",
        "tgn:7029392"
    ],
    "tgn:id":7317595,
    "tgn:name":"Chidguapi, Canal",
    "tgn:placetype":[
        "aat:300387026"
    ]
},
  "bbox": [],
  "geometry": {"coordinates":[-73.090556,-41.824167],"type":"Point"}
}