{
  "id": 2175612,
  "type": "Feature",
  "properties": {
    "tgn:hierarchy":[
        "tgn:2175612",
        "tgn:1000001",
        "tgn:2001267",
        "tgn:7012149",
        "tgn:7007524",
        "tgn:7029392"
    ],
    "tgn:id":2175612,
    "tgn:name":"Black Coulee",
    "tgn:placetype":[
        "aat:300008761"
    ]
},
  "bbox": [],
  "geometry": {"coordinates":[-111.0167,47.75],"type":"Point"}
}