{
  "id": 7113523,
  "type": "Feature",
  "properties": {
    "tgn:hierarchy":[
        "tgn:7113523",
        "tgn:7003669",
        "tgn:1000003",
        "tgn:7000084",
        "tgn:7029392"
    ],
    "tgn:id":7113523,
    "tgn:name":"Reuchelheim",
    "tgn:placetype":[
        "aat:300008347"
    ]
},
  "bbox": [],
  "geometry": {"coordinates":[9.930833,49.970833],"type":"Point"}
}