{
  "id": 2455485,
  "type": "Feature",
  "properties": {
    "tgn:hierarchy":[
        "tgn:2455485",
        "tgn:1000001",
        "tgn:7012149",
        "tgn:1002929",
        "tgn:7007240",
        "tgn:7029392"
    ],
    "tgn:id":2455485,
    "tgn:name":"Little Gant Lake",
    "tgn:placetype":[
        "aat:300008680"
    ]
},
  "bbox": [],
  "geometry": {"coordinates":[-82.0667,28.5833],"type":"Point"}
}