{
  "id": 2492140,
  "type": "Feature",
  "properties": {
    "tgn:hierarchy":[
        "tgn:2492140",
        "tgn:1000001",
        "tgn:7012149",
        "tgn:2000794",
        "tgn:7007255",
        "tgn:7029392"
    ],
    "tgn:id":2492140,
    "tgn:name":"Marcum Island",
    "tgn:placetype":[
        "aat:300008791"
    ]
},
  "bbox": [],
  "geometry": {"coordinates":[-85.45,37.2667],"type":"Point"}
}