{
  "id": 7478538,
  "type": "Feature",
  "properties": {
    "tgn:hierarchy":[
        "tgn:7478538",
        "tgn:1000004",
        "tgn:7467799",
        "tgn:1000141",
        "tgn:7029392"
    ],
    "tgn:id":7478538,
    "tgn:name":"Luocuo Guoxiao",
    "tgn:placetype":[
        "aat:300006495"
    ]
},
  "bbox": [],
  "geometry": {"coordinates":[120.512951,23.942387],"type":"Point"}
}