{
  "id": 2545057,
  "type": "Feature",
  "properties": {
    "tgn:hierarchy":[
        "tgn:2545057",
        "tgn:1000001",
        "tgn:7012149",
        "tgn:2002114",
        "tgn:7007827",
        "tgn:7029392"
    ],
    "tgn:id":2545057,
    "tgn:name":"North Ditch",
    "tgn:placetype":[
        "aat:300006075"
    ]
},
  "bbox": [],
  "geometry": {"coordinates":[-112.6667,39.2667],"type":"Point"}
}