<<<<<<< HEAD
{
  "id": 7022537,
  "type": "Feature",
  "properties": {
    "tgn:hierarchy":[
        "tgn:7022537",
        "tgn:1000001",
        "tgn:7012149",
        "tgn:2000351",
        "tgn:7007248",
        "tgn:7029392"
    ],
    "tgn:id":7022537,
    "tgn:name":"City of East Point Reservoir",
    "tgn:placetype":[
        "aat:300006191"
    ]
},
  "bbox": [],
  "geometry": {"coordinates":[-84.5333,33.6833],"type":"Point"}
}
=======
{"geometry":{"type":"Point","coordinates":[-84.533300,33.683300]},"type":"Feature","properties":{"hierarchy":["tgn:7022537","tgn:1000001","tgn:7012149","tgn:2000351","tgn:7007248","tgn:7029392"],"placetype":["aat:300006191"],"id":7022537,"name:xx":"City of East Point Reservoir"}}
>>>>>>> 03f74aca74312dbeaf24d7e61306dd6a786dc3d0
