{
  "id": 7022537,
  "type": "Feature",
  "properties": {
    "tgn:hierarchy":[
        "tgn:7022537",
        "tgn:1000001",
        "tgn:7012149",
        "tgn:2000351",
        "tgn:7007248",
        "tgn:7029392"
    ],
    "tgn:id":7022537,
    "tgn:name":"City of East Point Reservoir",
    "tgn:placetype":[
        "aat:300006191"
    ]
},
  "bbox": [],
  "geometry": {"coordinates":[-84.5333,33.6833],"type":"Point"}
}