{
  "id": 7564610,
  "type": "Feature",
  "properties": {
    "tgn:hierarchy":[
        "tgn:7564610",
        "tgn:1000004",
        "tgn:7000198",
        "tgn:7016722",
        "tgn:7029392"
    ],
    "tgn:id":7564610,
    "tgn:name:en":"Kurauli",
    "tgn:placetype":[
        "aat:300008347"
    ]
},
  "bbox": [],
  "geometry": {"coordinates":[79.350838,26.364387],"type":"Point"}
}