{
  "id": 7506968,
  "type": "Feature",
  "properties": {
    "tgn:hierarchy":[
        "tgn:7506968",
        "tgn:1008380",
        "tgn:1000226",
        "tgn:7018426",
        "tgn:1000006",
        "tgn:7029392"
    ],
    "tgn:id":7506968,
    "tgn:name:en":"Rangi",
    "tgn:placetype":[
        "aat:300008777"
    ]
},
  "bbox": [],
  "geometry": {"coordinates":[174.933333,-38.55],"type":"Point"}
}