{
  "id": 2721475,
  "type": "Feature",
  "properties": {
    "tgn:hierarchy":[
        "tgn:2721475",
        "tgn:1000001",
        "tgn:7012149",
        "tgn:1002749",
        "tgn:7007240",
        "tgn:7029392"
    ],
    "tgn:id":2721475,
    "tgn:name":"Tilden, Lake",
    "tgn:placetype":[
        "aat:300008680"
    ]
},
  "bbox": [],
  "geometry": {"coordinates":[-81.5833,28.5167],"type":"Point"}
}