{
  "id": 7463701,
  "type": "Feature",
  "properties": {
    "tgn:hierarchy":[
        "tgn:7463701",
        "tgn:7002445",
        "tgn:1000003",
        "tgn:7012034",
        "tgn:7008591",
        "tgn:7029392"
    ],
    "tgn:id":7463701,
    "tgn:name:en":"Leighton",
    "tgn:placetype":[
        "aat:300008347"
    ]
},
  "bbox": [],
  "geometry": {"coordinates":[-2.583333,52.65],"type":"Point"}
}