{
  "id": 2781613,
  "type": "Feature",
  "properties": {
    "tgn:hierarchy":[
        "tgn:2781613",
        "tgn:1000001",
        "tgn:7012149",
        "tgn:2001899",
        "tgn:7007825",
        "tgn:7029392"
    ],
    "tgn:id":2781613,
    "tgn:name":"Woodridge Estates",
    "tgn:placetype":[
        "aat:300008347"
    ]
},
  "bbox": [],
  "geometry": {"coordinates":[-87.25,36.4833],"type":"Point"}
}