{
  "id": 2607863,
  "type": "Feature",
  "properties": {
    "tgn:hierarchy":[
        "tgn:2607863",
        "tgn:1000001",
        "tgn:2002369",
        "tgn:7012149",
        "tgn:7007923",
        "tgn:7029392"
    ],
    "tgn:id":2607863,
    "tgn:name":"Rat Creek",
    "tgn:placetype":[
        "aat:300008706"
    ]
},
  "bbox": [],
  "geometry": {"coordinates":[-105.05,43.2833],"type":"Point"}
}