{
  "id": 2050581,
  "type": "Feature",
  "properties": {
    "tgn:hierarchy":[
        "tgn:2050581",
        "tgn:1002201",
        "tgn:1000001",
        "tgn:7012149",
        "tgn:7007517",
        "tgn:7029392"
    ],
    "tgn:id":2050581,
    "tgn:name":"Shore Acres",
    "tgn:placetype":[
        "aat:300008347"
    ]
},
  "bbox": [],
  "geometry": {"coordinates":[-70.9333,41.55],"type":"Point"}
}