{
  "id": 2010663,
  "type": "Feature",
  "properties": {
    "tgn:hierarchy":[
        "tgn:2010663",
        "tgn:1000001",
        "tgn:7012149",
        "tgn:7007157",
        "tgn:1003050",
        "tgn:7029392"
    ],
    "tgn:id":2010663,
    "tgn:name":"Challenge",
    "tgn:placetype":[
        "aat:300008347"
    ]
},
  "bbox": [],
  "geometry": {"coordinates":[-121.2167,39.4833],"type":"Point"}
}