{
  "id": 2750520,
  "type": "Feature",
  "properties": {
    "tgn:hierarchy":[
        "tgn:2750520",
        "tgn:1000001",
        "tgn:7012149",
        "tgn:1002897",
        "tgn:7007920",
        "tgn:7029392"
    ],
    "tgn:id":2750520,
    "tgn:name":"Wapiki, Lake",
    "tgn:placetype":[
        "aat:300008680"
    ]
},
  "bbox": [],
  "geometry": {"coordinates":[-121.7333,46.0167],"type":"Point"}
}