{
  "id": 7011424,
  "type": "Feature",
  "properties": {
    "tgn:hierarchy":[
        "tgn:7011424",
        "tgn:7002445",
        "tgn:1000003",
        "tgn:7008134",
        "tgn:7008591",
        "tgn:7029392"
    ],
    "tgn:id":7011424,
    "tgn:name:en":"Horsham",
    "tgn:placetype":[
        "aat:300008347"
    ]
},
  "bbox": [],
  "geometry": {"coordinates":[-0.333333,51.05],"type":"Point"}
}