{
  "id": 2213809,
  "type": "Feature",
  "properties": {
    "tgn:hierarchy":[
        "tgn:2213809",
        "tgn:1000001",
        "tgn:2001418",
        "tgn:7012149",
        "tgn:7007526",
        "tgn:7029392"
    ],
    "tgn:id":2213809,
    "tgn:name":"Cactus Spring",
    "tgn:placetype":[
        "aat:300008697"
    ]
},
  "bbox": [],
  "geometry": {"coordinates":[-116.8167,37.7167],"type":"Point"}
}