{
  "id": 2141254,
  "type": "Feature",
  "properties": {
    "tgn:hierarchy":[
        "tgn:2141254",
        "tgn:1000001",
        "tgn:7012149",
        "tgn:1002503",
        "tgn:7007520",
        "tgn:7029392"
    ],
    "tgn:id":2141254,
    "tgn:name":"Ayers Branch",
    "tgn:placetype":[
        "aat:300008699"
    ]
},
  "bbox": [],
  "geometry": {"coordinates":[-84.9167,42.9333],"type":"Point"}
}