{
  "id": 2629735,
  "type": "Feature",
  "properties": {
    "tgn:hierarchy":[
        "tgn:2629735",
        "tgn:1000001",
        "tgn:7012149",
        "tgn:2001298",
        "tgn:7007524",
        "tgn:7029392"
    ],
    "tgn:id":2629735,
    "tgn:name":"Ross Creek",
    "tgn:placetype":[
        "aat:300008706"
    ]
},
  "bbox": [],
  "geometry": {"coordinates":[-113.3167,47.2333],"type":"Point"}
}