{
  "id": 2199955,
  "type": "Feature",
  "properties": {
    "tgn:hierarchy":[
        "tgn:2199955",
        "tgn:1000001",
        "tgn:7012149",
        "tgn:2001214",
        "tgn:7007523",
        "tgn:7029392"
    ],
    "tgn:id":2199955,
    "tgn:name":"Brushy Branch",
    "tgn:placetype":[
        "aat:300008699"
    ]
},
  "bbox": [],
  "geometry": {"coordinates":[-93.0667,39.9167],"type":"Point"}
}