{
  "id": 1122815,
  "type": "Feature",
  "properties": {
    "tgn:hierarchy":[
        "tgn:1122815",
        "tgn:1000001",
        "tgn:7005493",
        "tgn:7029392"
    ],
    "tgn:id":1122815,
    "tgn:name":"Chixoy, R\u00edo",
    "tgn:placetype":[
        "aat:300008707"
    ]
},
  "bbox": [],
  "geometry": {"coordinates":[-90.45,16.0667],"type":"Point"}
}