{
  "id": 1096698,
  "type": "Feature",
  "properties": {
    "tgn:hierarchy":[
        "tgn:1096698",
        "tgn:7000490",
        "tgn:1000006",
        "tgn:7001828",
        "tgn:7029392"
    ],
    "tgn:id":1096698,
    "tgn:name":"Curlewis",
    "tgn:placetype":[
        "aat:300008347"
    ]
},
  "bbox": [],
  "geometry": {"coordinates":[150.2667,-31.1333],"type":"Point"}
}