<<<<<<< HEAD
{
  "id": 7024676,
  "type": "Feature",
  "properties": {
    "tgn:hierarchy":[
        "tgn:7024676",
        "tgn:7003025",
        "tgn:1000003",
        "tgn:1000062",
        "tgn:7029392"
    ],
    "tgn:id":7024676,
    "tgn:name":"Ollern",
    "tgn:placetype":[
        "aat:300008347"
    ]
},
  "bbox": [],
  "geometry": {"coordinates":[16.0833,48.2667],"type":"Point"}
}
=======
{"geometry":{"type":"Point","coordinates":[16.083300,48.266700]},"type":"Feature","properties":{"hierarchy":["tgn:7024676","tgn:7003025","tgn:1000003","tgn:1000062","tgn:7029392"],"placetype":["aat:300008347"],"id":7024676,"name:xx":"Ollern"}}
>>>>>>> 03f74aca74312dbeaf24d7e61306dd6a786dc3d0
