{
  "id": 2759297,
  "type": "Feature",
  "properties": {
    "tgn:hierarchy":[
        "tgn:2759297",
        "tgn:7013349",
        "tgn:1000001",
        "tgn:7012149",
        "tgn:7007708",
        "tgn:7029392"
    ],
    "tgn:id":2759297,
    "tgn:name":"West Fork Clear Creek",
    "tgn:placetype":[
        "aat:300008706"
    ]
},
  "bbox": [],
  "geometry": {"coordinates":[-117.15,45.0667],"type":"Point"}
}