{
  "id": 7380590,
  "type": "Feature",
  "properties": {
    "tgn:hierarchy":[
        "tgn:7380590",
        "tgn:1000001",
        "tgn:7005590",
        "tgn:7005560",
        "tgn:7029392"
    ],
    "tgn:id":7380590,
    "tgn:name":"Magallanes",
    "tgn:placetype":[
        "aat:300008347"
    ]
},
  "bbox": [],
  "geometry": {"coordinates":[-102.466667,20.05],"type":"Point"}
}