{
  "id": 1106933,
  "type": "Feature",
  "properties": {
    "tgn:hierarchy":[
        "tgn:1106933",
        "tgn:1000007",
        "tgn:7029392"
    ],
    "tgn:id":1106933,
    "tgn:name":"Wade, Mount",
    "tgn:placetype":[
        "aat:300008795"
    ]
},
  "bbox": [],
  "geometry": {"coordinates":[-174.25,-84.85],"type":"Point"}
}