{
  "id": 1006970,
  "type": "Feature",
  "properties": {
    "tgn:hierarchy":[
        "tgn:1006970",
        "tgn:7030515",
        "tgn:7006450",
        "tgn:1000001",
        "tgn:7012149",
        "tgn:7029392"
    ],
    "tgn:id":1006970,
    "tgn:name":"Dolgoi Island",
    "tgn:placetype":[
        "aat:300008791"
    ]
},
  "bbox": [],
  "geometry": {"coordinates":[-161.7333,55.1167],"type":"Point"}
}