{
  "id": 7164536,
  "type": "Feature",
  "properties": {
    "tgn:hierarchy":[
        "tgn:7164536",
        "tgn:7003692",
        "tgn:1000003",
        "tgn:7000084",
        "tgn:7029392"
    ],
    "tgn:id":7164536,
    "tgn:name":"Hungerberg",
    "tgn:placetype":[
        "aat:300008777"
    ]
},
  "bbox": [],
  "geometry": {"coordinates":[9.266667,49.283333],"type":"Point"}
}