{
  "id": 7210106,
  "type": "Feature",
  "properties": {
    "tgn:hierarchy":[
        "tgn:7210106",
        "tgn:1000003",
        "tgn:7003682",
        "tgn:7000084",
        "tgn:7029392"
    ],
    "tgn:id":7210106,
    "tgn:name":"B\u00e4rbach",
    "tgn:placetype":[
        "aat:300000206"
    ]
},
  "bbox": [],
  "geometry": {"coordinates":[7.983333,50.316667],"type":"Point"}
}