{
  "id": 7556863,
  "type": "Feature",
  "properties": {
    "tgn:hierarchy":[
        "tgn:7556863",
        "tgn:1000004",
        "tgn:7000198",
        "tgn:1001894",
        "tgn:7029392"
    ],
    "tgn:id":7556863,
    "tgn:name:en":"Seogarh",
    "tgn:placetype":[
        "aat:300008347"
    ]
},
  "bbox": [],
  "geometry": {"coordinates":[74.856199,23.353404],"type":"Point"}
}