{
  "id": 2436122,
  "type": "Feature",
  "properties": {
    "tgn:hierarchy":[
        "tgn:2436122",
        "tgn:1000001",
        "tgn:2001425",
        "tgn:7012149",
        "tgn:7007564",
        "tgn:7029392"
    ],
    "tgn:id":2436122,
    "tgn:name":"Keyser Pond",
    "tgn:placetype":[
        "aat:300008680"
    ]
},
  "bbox": [],
  "geometry": {"coordinates":[-71.75,43.1667],"type":"Point"}
}