{
  "id": 2433253,
  "type": "Feature",
  "properties": {
    "tgn:hierarchy":[
        "tgn:2433253",
        "tgn:1000001",
        "tgn:7006451",
        "tgn:7012149",
        "tgn:2000098",
        "tgn:7029392"
    ],
    "tgn:id":2433253,
    "tgn:name":"Keller Pond",
    "tgn:placetype":[
        "aat:300006191"
    ]
},
  "bbox": [],
  "geometry": {"coordinates":[-113.35,36.5333],"type":"Point"}
}