{
  "id": 7301750,
  "type": "Feature",
  "properties": {
    "tgn:hierarchy":[
        "tgn:7301750",
        "tgn:7002834",
        "tgn:1000003",
        "tgn:7002786",
        "tgn:1000095",
        "tgn:7029392"
    ],
    "tgn:id":7301750,
    "tgn:name":"Melojo",
    "tgn:placetype":[
        "aat:300008347"
    ]
},
  "bbox": [],
  "geometry": {"coordinates":[-8.883333,42.483333],"type":"Point"}
}