{
  "id": 7419219,
  "type": "Feature",
  "properties": {
    "tgn:hierarchy":[
        "tgn:7419219",
        "tgn:1000001",
        "tgn:7005589",
        "tgn:7005560",
        "tgn:7029392"
    ],
    "tgn:id":7419219,
    "tgn:name:es":"Puerto Dolores",
    "tgn:placetype":[
        "aat:300008347"
    ]
},
  "bbox": [],
  "geometry": {"coordinates":[-100.458333,23.565833],"type":"Point"}
}