{
  "id": 2356534,
  "type": "Feature",
  "properties": {
    "tgn:hierarchy":[
        "tgn:2356534",
        "tgn:1000001",
        "tgn:1002775",
        "tgn:7012149",
        "tgn:7007565",
        "tgn:7029392"
    ],
    "tgn:id":2356534,
    "tgn:name":"Gordon Lakes",
    "tgn:placetype":[
        "aat:300006191"
    ]
},
  "bbox": [],
  "geometry": {"coordinates":[-74.35,41.05],"type":"Point"}
}