{
  "id": 7537936,
  "type": "Feature",
  "properties": {
    "tgn:hierarchy":[
        "tgn:7537936",
        "tgn:7001242",
        "tgn:7016833",
        "tgn:7001312",
        "tgn:7029392"
    ],
    "tgn:id":7537936,
    "tgn:name:en":"M\u012bt Shar\u012bf",
    "tgn:placetype":[
        "aat:300008347"
    ]
},
  "bbox": [],
  "geometry": {"coordinates":[30.851803,30.969428],"type":"Point"}
}