{
  "id": 7457804,
  "type": "Feature",
  "properties": {
    "tgn:hierarchy":[
        "tgn:7457804",
        "tgn:7002445",
        "tgn:7008116",
        "tgn:1000003",
        "tgn:7008591",
        "tgn:7029392"
    ],
    "tgn:id":7457804,
    "tgn:name:en":"Pendeen",
    "tgn:placetype":[
        "aat:300386846"
    ]
},
  "bbox": [],
  "geometry": {"coordinates":[-5.666667,50.166667],"type":"Point"}
}