{
  "id": 2407206,
  "type": "Feature",
  "properties": {
    "tgn:hierarchy":[
        "tgn:2407206",
        "tgn:7002659",
        "tgn:1000001",
        "tgn:7012149",
        "tgn:2000064",
        "tgn:7029392"
    ],
    "tgn:id":2407206,
    "tgn:name":"Hunters Slough",
    "tgn:placetype":[
        "aat:300008699"
    ]
},
  "bbox": [],
  "geometry": {"coordinates":[-87.9333,31.35],"type":"Point"}
}