<<<<<<< HEAD
{
  "id": 2407206,
  "type": "Feature",
  "properties": {
    "tgn:hierarchy":[
        "tgn:2407206",
        "tgn:7002659",
        "tgn:1000001",
        "tgn:7012149",
        "tgn:2000064",
        "tgn:7029392"
    ],
    "tgn:id":2407206,
    "tgn:name":"Hunters Slough",
    "tgn:placetype":[
        "aat:300008699"
    ]
},
  "bbox": [],
  "geometry": {"coordinates":[-87.9333,31.35],"type":"Point"}
}
=======
{"geometry":{"type":"Point","coordinates":[-87.933300,31.350000]},"type":"Feature","properties":{"hierarchy":["tgn:2407206","tgn:7002659","tgn:1000001","tgn:7012149","tgn:2000064","tgn:7029392"],"placetype":["aat:300008699"],"id":2407206,"name:xx":"Hunters Slough"}}
>>>>>>> 03f74aca74312dbeaf24d7e61306dd6a786dc3d0
