{
  "id": 7041230,
  "type": "Feature",
  "properties": {
    "tgn:hierarchy":[
        "tgn:7041230",
        "tgn:7003138",
        "tgn:1000003",
        "tgn:7003080",
        "tgn:1000080",
        "tgn:7029392"
    ],
    "tgn:id":7041230,
    "tgn:name":"San Paolo",
    "tgn:placetype":[
        "aat:300007466"
    ]
},
  "bbox": [],
  "geometry": {"coordinates":[12.466667,41.85],"type":"Point"}
}