{
  "id": 2551787,
  "type": "Feature",
  "properties": {
    "tgn:hierarchy":[
        "tgn:2551787",
        "tgn:1000001",
        "tgn:7016172",
        "tgn:7012149",
        "tgn:2000158",
        "tgn:7029392"
    ],
    "tgn:id":2551787,
    "tgn:name":"Number 64, Island",
    "tgn:placetype":[
        "aat:300008791"
    ]
},
  "bbox": [],
  "geometry": {"coordinates":[-90.8667,34.2333],"type":"Point"}
}