{
  "id": 2602098,
  "type": "Feature",
  "properties": {
    "tgn:hierarchy":[
        "tgn:2602098",
        "tgn:1002483",
        "tgn:7019080",
        "tgn:1000001",
        "tgn:7012149",
        "tgn:7007249",
        "tgn:7029392"
    ],
    "tgn:id":2602098,
    "tgn:name":"Puu Peahinala",
    "tgn:placetype":[
        "aat:300008798"
    ]
},
  "bbox": [],
  "geometry": {"coordinates":[-157.9833,21.55],"type":"Point"}
}