{
  "id": 7495951,
  "type": "Feature",
  "properties": {
    "tgn:hierarchy":[
        "tgn:7495951",
        "tgn:7487020",
        "tgn:1000004",
        "tgn:1000141",
        "tgn:7029392"
    ],
    "tgn:id":7495951,
    "tgn:name":"Tuniugou",
    "tgn:placetype":[
        "aat:300008347"
    ]
},
  "bbox": [],
  "geometry": {"coordinates":[120.751066,24.562221],"type":"Point"}
}