{
  "id": 2592404,
  "type": "Feature",
  "properties": {
    "tgn:hierarchy":[
        "tgn:2592404",
        "tgn:1000001",
        "tgn:7012149",
        "tgn:2000933",
        "tgn:7007515",
        "tgn:7029392"
    ],
    "tgn:id":2592404,
    "tgn:name":"Pool, The",
    "tgn:placetype":[
        "aat:300132316"
    ]
},
  "bbox": [],
  "geometry": {"coordinates":[-70.35,43.4333],"type":"Point"}
}