{
  "id": 2670775,
  "type": "Feature",
  "properties": {
    "tgn:hierarchy":[
        "tgn:2670775",
        "tgn:1000001",
        "tgn:7012149",
        "tgn:2001987",
        "tgn:7007826",
        "tgn:7029392"
    ],
    "tgn:id":2670775,
    "tgn:name":"Smith Branch",
    "tgn:placetype":[
        "aat:300008699"
    ]
},
  "bbox": [],
  "geometry": {"coordinates":[-98.85,29.0333],"type":"Point"}
}