{
  "id": 7552297,
  "type": "Feature",
  "properties": {
    "tgn:hierarchy":[
        "tgn:7552297",
        "tgn:1001828",
        "tgn:1000004",
        "tgn:7000198",
        "tgn:7029392"
    ],
    "tgn:id":7552297,
    "tgn:name:en":"N\u0101rsingi",
    "tgn:placetype":[
        "aat:300008347"
    ]
},
  "bbox": [],
  "geometry": {"coordinates":[78.433333,18.033333],"type":"Point"}
}