{
  "id": 2668861,
  "type": "Feature",
  "properties": {
    "tgn:hierarchy":[
        "tgn:2668861",
        "tgn:1000001",
        "tgn:7012149",
        "tgn:1002613",
        "tgn:7007710",
        "tgn:7029392"
    ],
    "tgn:id":2668861,
    "tgn:name":"Slaughter Hollow",
    "tgn:placetype":[
        "aat:300008761"
    ]
},
  "bbox": [],
  "geometry": {"coordinates":[-76.95,41.4667],"type":"Point"}
}