{
  "id": 2268872,
  "type": "Feature",
  "properties": {
    "tgn:hierarchy":[
        "tgn:2268872",
        "tgn:1000001",
        "tgn:2000925",
        "tgn:7012149",
        "tgn:7007515",
        "tgn:7029392"
    ],
    "tgn:id":2268872,
    "tgn:name":"Cross River",
    "tgn:placetype":[
        "aat:300008707"
    ]
},
  "bbox": [],
  "geometry": {"coordinates":[-69.6167,43.8833],"type":"Point"}
}