<<<<<<< HEAD
{
  "id": 2258529,
  "type": "Feature",
  "properties": {
    "tgn:hierarchy":[
        "tgn:2258529",
        "tgn:7002659",
        "tgn:1000001",
        "tgn:7012149",
        "tgn:2000025",
        "tgn:7029392"
    ],
    "tgn:id":2258529,
    "tgn:name":"Cottonford Creek",
    "tgn:placetype":[
        "aat:300008706"
    ]
},
  "bbox": [],
  "geometry": {"coordinates":[-86.3667,32.5167],"type":"Point"}
}
=======
{"geometry":{"type":"Point","coordinates":[-86.366700,32.516700]},"type":"Feature","properties":{"hierarchy":["tgn:2258529","tgn:7002659","tgn:1000001","tgn:7012149","tgn:2000025","tgn:7029392"],"placetype":["aat:300008706"],"id":2258529,"name:xx":"Cottonford Creek"}}
>>>>>>> 03f74aca74312dbeaf24d7e61306dd6a786dc3d0
