{
  "id": 2287548,
  "type": "Feature",
  "properties": {
    "tgn:hierarchy":[
        "tgn:2287548",
        "tgn:1000001",
        "tgn:7012149",
        "tgn:2000181",
        "tgn:7007157",
        "tgn:7029392"
    ],
    "tgn:id":2287548,
    "tgn:name":"Digger Creek",
    "tgn:placetype":[
        "aat:300008706"
    ]
},
  "bbox": [],
  "geometry": {"coordinates":[-123.8833,40.65],"type":"Point"}
}