{
  "id": 2170809,
  "type": "Feature",
  "properties": {
    "tgn:hierarchy":[
        "tgn:2170809",
        "tgn:1000001",
        "tgn:7012149",
        "tgn:2001461",
        "tgn:7007568",
        "tgn:7029392"
    ],
    "tgn:id":2170809,
    "tgn:name":"Big Sherman Pond",
    "tgn:placetype":[
        "aat:300008680"
    ]
},
  "bbox": [],
  "geometry": {"coordinates":[-73.9667,43.8167],"type":"Point"}
}