{
  "id": 2226219,
  "type": "Feature",
  "properties": {
    "tgn:hierarchy":[
        "tgn:2226219",
        "tgn:1000001",
        "tgn:1002284",
        "tgn:7012149",
        "tgn:7007568",
        "tgn:7029392"
    ],
    "tgn:id":2226219,
    "tgn:name":"Catfish Bay",
    "tgn:placetype":[
        "aat:300132316"
    ]
},
  "bbox": [],
  "geometry": {"coordinates":[-73.35,44.95],"type":"Point"}
}