{
  "id": 2519835,
  "type": "Feature",
  "properties": {
    "tgn:hierarchy":[
        "tgn:2519835",
        "tgn:1000001",
        "tgn:7012149",
        "tgn:7019014",
        "tgn:7007251",
        "tgn:7029392"
    ],
    "tgn:id":2519835,
    "tgn:name":"Mokeler Creek",
    "tgn:placetype":[
        "aat:300008706"
    ]
},
  "bbox": [],
  "geometry": {"coordinates":[-88.5667,42.45],"type":"Point"}
}