{
  "id": 7232525,
  "type": "Feature",
  "properties": {
    "tgn:hierarchy":[
        "tgn:7232525",
        "tgn:7011167",
        "tgn:7001338",
        "tgn:1000003",
        "tgn:1000074",
        "tgn:7029392"
    ],
    "tgn:id":7232525,
    "tgn:name":"Ith\u00e1kis, Sten\u00f3",
    "tgn:placetype":[
        "aat:300387026"
    ]
},
  "bbox": [],
  "geometry": {"coordinates":[20.65,38.366667],"type":"Point"}
}