{
  "id": 2130645,
  "type": "Feature",
  "properties": {
    "tgn:hierarchy":[
        "tgn:2130645",
        "tgn:1002148",
        "tgn:1000001",
        "tgn:7012149",
        "tgn:7007826",
        "tgn:7029392"
    ],
    "tgn:id":2130645,
    "tgn:name":"Alligator Lake",
    "tgn:placetype":[
        "aat:300008680"
    ]
},
  "bbox": [],
  "geometry": {"coordinates":[-95.45,31.9833],"type":"Point"}
}