{
  "id": 7262066,
  "type": "Feature",
  "properties": {
    "tgn:hierarchy":[
        "tgn:7262066",
        "tgn:1000003",
        "tgn:7003624",
        "tgn:7016845",
        "tgn:7029392"
    ],
    "tgn:id":7262066,
    "tgn:name:nl":"Eikenhorst",
    "tgn:placetype":[
        "aat:300387502"
    ]
},
  "bbox": [],
  "geometry": {"coordinates":[5.316667,51.616667],"type":"Point"}
}