{
  "id": 2474652,
  "type": "Feature",
  "properties": {
    "tgn:hierarchy":[
        "tgn:2474652",
        "tgn:1000001",
        "tgn:7012149",
        "tgn:2000214",
        "tgn:7007158",
        "tgn:7029392"
    ],
    "tgn:id":2474652,
    "tgn:name":"Lower Short Creek",
    "tgn:placetype":[
        "aat:300008706"
    ]
},
  "bbox": [],
  "geometry": {"coordinates":[-107.2333,39.75],"type":"Point"}
}