{
  "id": 1031596,
  "type": "Feature",
  "properties": {
    "tgn:hierarchy":[
        "tgn:1031596",
        "tgn:7594391",
        "tgn:1000003",
        "tgn:1000069",
        "tgn:7029392"
    ],
    "tgn:id":1031596,
    "tgn:name":"V\u00e4rtsil\u00e4",
    "tgn:placetype":[
        "aat:300008347",
        "aat:300008372",
        "aat:300387302"
    ]
},
  "bbox": [],
  "geometry": {"coordinates":[30.609613,62.202304],"type":"Point"}
}