<<<<<<< HEAD
{
  "id": 2761561,
  "type": "Feature",
  "properties": {
    "tgn:hierarchy":[
        "tgn:2761561",
        "tgn:1000001",
        "tgn:7006451",
        "tgn:7012149",
        "tgn:2000099",
        "tgn:7029392"
    ],
    "tgn:id":2761561,
    "tgn:name":"West Park Tank",
    "tgn:placetype":[
        "aat:300006191"
    ]
},
  "bbox": [],
  "geometry": {"coordinates":[-110.5333,34.3],"type":"Point"}
}
=======
{"geometry":{"type":"Point","coordinates":[-110.533300,34.300000]},"type":"Feature","properties":{"hierarchy":["tgn:2761561","tgn:1000001","tgn:7006451","tgn:7012149","tgn:2000099","tgn:7029392"],"placetype":["aat:300006191"],"id":2761561,"name:xx":"West Park Tank"}}
>>>>>>> 03f74aca74312dbeaf24d7e61306dd6a786dc3d0
