{
  "id": 7563407,
  "type": "Feature",
  "properties": {
    "tgn:hierarchy":[
        "tgn:7563407",
        "tgn:1000004",
        "tgn:7000198",
        "tgn:1001894",
        "tgn:7029392"
    ],
    "tgn:id":7563407,
    "tgn:name:en":"N\u0101dpaun",
    "tgn:placetype":[
        "aat:300008347"
    ]
},
  "bbox": [],
  "geometry": {"coordinates":[79.214837,24.141137],"type":"Point"}
}