{
  "id": 2765578,
  "type": "Feature",
  "properties": {
    "tgn:hierarchy":[
        "tgn:2765578",
        "tgn:1000001",
        "tgn:7012149",
        "tgn:1002950",
        "tgn:7007568",
        "tgn:7029392"
    ],
    "tgn:id":2765578,
    "tgn:name":"White Church",
    "tgn:placetype":[
        "aat:300008347"
    ]
},
  "bbox": [],
  "geometry": {"coordinates":[-76.3833,42.3333],"type":"Point"}
}