<<<<<<< HEAD
{
  "id": 2765578,
  "type": "Feature",
  "properties": {
    "tgn:hierarchy":[
        "tgn:2765578",
        "tgn:1000001",
        "tgn:7012149",
        "tgn:1002950",
        "tgn:7007568",
        "tgn:7029392"
    ],
    "tgn:id":2765578,
    "tgn:name":"White Church",
    "tgn:placetype":[
        "aat:300008347"
    ]
},
  "bbox": [],
  "geometry": {"coordinates":[-76.3833,42.3333],"type":"Point"}
}
=======
{"geometry":{"type":"Point","coordinates":[-76.383300,42.333300]},"type":"Feature","properties":{"hierarchy":["tgn:2765578","tgn:1000001","tgn:7012149","tgn:1002950","tgn:7007568","tgn:7029392"],"placetype":["aat:300008347"],"id":2765578,"name:xx":"White Church"}}
>>>>>>> 03f74aca74312dbeaf24d7e61306dd6a786dc3d0
