<<<<<<< HEAD
{
  "id": 2155492,
  "type": "Feature",
  "properties": {
    "tgn:hierarchy":[
        "tgn:2155492",
        "tgn:1000001",
        "tgn:7012149",
        "tgn:7014612",
        "tgn:7007568",
        "tgn:7029392"
    ],
    "tgn:id":2155492,
    "tgn:name":"Bear Ridge Lake",
    "tgn:placetype":[
        "aat:300008680"
    ]
},
  "bbox": [],
  "geometry": {"coordinates":[-73.7667,41.1333],"type":"Point"}
}
=======
{"geometry":{"type":"Point","coordinates":[-73.766700,41.133300]},"type":"Feature","properties":{"hierarchy":["tgn:2155492","tgn:1000001","tgn:7012149","tgn:7014612","tgn:7007568","tgn:7029392"],"placetype":["aat:300008680"],"id":2155492,"name:xx":"Bear Ridge Lake"}}
>>>>>>> 03f74aca74312dbeaf24d7e61306dd6a786dc3d0
