{
  "id": 2155492,
  "type": "Feature",
  "properties": {
    "tgn:hierarchy":[
        "tgn:2155492",
        "tgn:1000001",
        "tgn:7012149",
        "tgn:7014612",
        "tgn:7007568",
        "tgn:7029392"
    ],
    "tgn:id":2155492,
    "tgn:name":"Bear Ridge Lake",
    "tgn:placetype":[
        "aat:300008680"
    ]
},
  "bbox": [],
  "geometry": {"coordinates":[-73.7667,41.1333],"type":"Point"}
}