{
  "id": 2568107,
  "type": "Feature",
  "properties": {
    "tgn:hierarchy":[
        "tgn:2568107",
        "tgn:1000001",
        "tgn:7012149",
        "tgn:2001449",
        "tgn:7007566",
        "tgn:7029392"
    ],
    "tgn:id":2568107,
    "tgn:name":"Parda, Loma",
    "tgn:placetype":[
        "aat:300008798"
    ]
},
  "bbox": [],
  "geometry": {"coordinates":[-106.3333,36.0667],"type":"Point"}
}