{
  "id": 7329013,
  "type": "Feature",
  "properties": {
    "tgn:hierarchy":[
        "tgn:7329013",
        "tgn:7002836",
        "tgn:7016622",
        "tgn:1000003",
        "tgn:1000095",
        "tgn:7029392"
    ],
    "tgn:id":7329013,
    "tgn:name":"Punta del Cascajo, Barranco",
    "tgn:placetype":[
        "aat:300266554",
        "aat:300008699"
    ]
},
  "bbox": [],
  "geometry": {"coordinates":[-18.083333,27.683333],"type":"Point"}
}