{
  "id": 2181043,
  "type": "Feature",
  "properties": {
    "tgn:hierarchy":[
        "tgn:2181043",
        "tgn:1000001",
        "tgn:2001786",
        "tgn:7012149",
        "tgn:7007713",
        "tgn:7029392"
    ],
    "tgn:id":2181043,
    "tgn:name":"Blue Bell",
    "tgn:placetype":[
        "aat:300008347"
    ]
},
  "bbox": [],
  "geometry": {"coordinates":[-103.4667,43.7167],"type":"Point"}
}