<<<<<<< HEAD
{
  "id": 2409389,
  "type": "Feature",
  "properties": {
    "tgn:hierarchy":[
        "tgn:2409389",
        "tgn:1000001",
        "tgn:1002271",
        "tgn:7012149",
        "tgn:7007920",
        "tgn:7029392"
    ],
    "tgn:id":2409389,
    "tgn:name":"Idaho Creek",
    "tgn:placetype":[
        "aat:300008706"
    ]
},
  "bbox": [],
  "geometry": {"coordinates":[-123.5,47.9667],"type":"Point"}
}
=======
{"geometry":{"type":"Point","coordinates":[-123.500000,47.966700]},"type":"Feature","properties":{"hierarchy":["tgn:2409389","tgn:1000001","tgn:1002271","tgn:7012149","tgn:7007920","tgn:7029392"],"placetype":["aat:300008706"],"id":2409389,"name:xx":"Idaho Creek"}}
>>>>>>> 03f74aca74312dbeaf24d7e61306dd6a786dc3d0
