{
  "id": 2249659,
  "type": "Feature",
  "properties": {
    "tgn:hierarchy":[
        "tgn:2249659",
        "tgn:1000001",
        "tgn:7012149",
        "tgn:2000831",
        "tgn:7007255",
        "tgn:7029392"
    ],
    "tgn:id":2249659,
    "tgn:name":"Coley Branch",
    "tgn:placetype":[
        "aat:300008699"
    ]
},
  "bbox": [],
  "geometry": {"coordinates":[-83.3333,38.0333],"type":"Point"}
}