{
  "id": 7400223,
  "type": "Feature",
  "properties": {
    "tgn:hierarchy":[
        "tgn:7400223",
        "tgn:1000001",
        "tgn:7005599",
        "tgn:7005560",
        "tgn:7029392"
    ],
    "tgn:id":7400223,
    "tgn:name":"El Desenga\u00f1o",
    "tgn:placetype":[
        "aat:300008347"
    ]
},
  "bbox": [],
  "geometry": {"coordinates":[-93.965278,17.35],"type":"Point"}
}