<<<<<<< HEAD
{
  "id": 2333852,
  "type": "Feature",
  "properties": {
    "tgn:hierarchy":[
        "tgn:2333852",
        "tgn:1000001",
        "tgn:7012149",
        "tgn:7014185",
        "tgn:7007710",
        "tgn:7029392"
    ],
    "tgn:id":2333852,
    "tgn:name":"Forbes State Forest",
    "tgn:placetype":[
        "aat:300008863"
    ]
},
  "bbox": [],
  "geometry": {"coordinates":[-79.6667,39.8167],"type":"Point"}
}
=======
{"geometry":{"type":"Point","coordinates":[-79.666700,39.816700]},"type":"Feature","properties":{"hierarchy":["tgn:2333852","tgn:1000001","tgn:7012149","tgn:7014185","tgn:7007710","tgn:7029392"],"placetype":["aat:300008863"],"id":2333852,"name:xx":"Forbes State Forest"}}
>>>>>>> 03f74aca74312dbeaf24d7e61306dd6a786dc3d0
