{
  "id": 7579206,
  "type": "Feature",
  "properties": {
    "tgn:hierarchy":[
        "tgn:7579206",
        "tgn:1000004",
        "tgn:7000198",
        "tgn:7000799",
        "tgn:7029392"
    ],
    "tgn:id":7579206,
    "tgn:name:en":"Sog\u0101m",
    "tgn:placetype":[
        "aat:300008347"
    ]
},
  "bbox": [],
  "geometry": {"coordinates":[74.37771,34.497461],"type":"Point"}
}