<<<<<<< HEAD
{
  "id": 2406915,
  "type": "Feature",
  "properties": {
    "tgn:hierarchy":[
        "tgn:2406915",
        "tgn:1000001",
        "tgn:7012149",
        "tgn:2001225",
        "tgn:7007523",
        "tgn:7029392"
    ],
    "tgn:id":2406915,
    "tgn:name":"Hunter Crossing",
    "tgn:placetype":[
        "aat:300008347"
    ]
},
  "bbox": [],
  "geometry": {"coordinates":[-91.6667,36.6667],"type":"Point"}
}
=======
{"geometry":{"type":"Point","coordinates":[-91.666700,36.666700]},"type":"Feature","properties":{"hierarchy":["tgn:2406915","tgn:1000001","tgn:7012149","tgn:2001225","tgn:7007523","tgn:7029392"],"placetype":["aat:300008347"],"id":2406915,"name:xx":"Hunter Crossing"}}
>>>>>>> 03f74aca74312dbeaf24d7e61306dd6a786dc3d0
