{
  "id": 2406915,
  "type": "Feature",
  "properties": {
    "tgn:hierarchy":[
        "tgn:2406915",
        "tgn:1000001",
        "tgn:7012149",
        "tgn:2001225",
        "tgn:7007523",
        "tgn:7029392"
    ],
    "tgn:id":2406915,
    "tgn:name":"Hunter Crossing",
    "tgn:placetype":[
        "aat:300008347"
    ]
},
  "bbox": [],
  "geometry": {"coordinates":[-91.6667,36.6667],"type":"Point"}
}