{
  "id": 7515662,
  "type": "Feature",
  "properties": {
    "tgn:hierarchy":[
        "tgn:7515662",
        "tgn:1008380",
        "tgn:7000507",
        "tgn:1000226",
        "tgn:1000006",
        "tgn:7029392"
    ],
    "tgn:id":7515662,
    "tgn:name:en":"Motukahakaha Bay",
    "tgn:placetype":[
        "aat:300132316"
    ]
},
  "bbox": [],
  "geometry": {"coordinates":[173.65,-34.95],"type":"Point"}
}