{
  "id": 7512580,
  "type": "Feature",
  "properties": {
    "tgn:hierarchy":[
        "tgn:7512580",
        "tgn:1008380",
        "tgn:7000507",
        "tgn:1000226",
        "tgn:1000006",
        "tgn:7029392"
    ],
    "tgn:id":7512580,
    "tgn:name:en":"Home Point",
    "tgn:placetype":[
        "aat:300386846"
    ]
},
  "bbox": [],
  "geometry": {"coordinates":[174.383333,-35.316667],"type":"Point"}
}