{
  "id": 2638088,
  "type": "Feature",
  "properties": {
    "tgn:hierarchy":[
        "tgn:2638088",
        "tgn:1000001",
        "tgn:7012149",
        "tgn:1002740",
        "tgn:7007252",
        "tgn:7029392"
    ],
    "tgn:id":2638088,
    "tgn:name":"Salem Ridge",
    "tgn:placetype":[
        "aat:300266640"
    ]
},
  "bbox": [],
  "geometry": {"coordinates":[-84.9167,38.9833],"type":"Point"}
}