{
  "id": 7404224,
  "type": "Feature",
  "properties": {
    "tgn:hierarchy":[
        "tgn:7404224",
        "tgn:7005578",
        "tgn:1000001",
        "tgn:7005560",
        "tgn:7029392"
    ],
    "tgn:id":7404224,
    "tgn:name":"La Venenosa",
    "tgn:placetype":[
        "aat:300008347"
    ]
},
  "bbox": [],
  "geometry": {"coordinates":[-90.266667,18.791667],"type":"Point"}
}