<<<<<<< HEAD
{
  "id": 7364278,
  "type": "Feature",
  "properties": {
    "tgn:hierarchy":[
        "tgn:7364278",
        "tgn:7005580",
        "tgn:1000001",
        "tgn:7005560",
        "tgn:7029392"
    ],
    "tgn:id":7364278,
    "tgn:name":"El Boquer\u00f3n",
    "tgn:placetype":[
        "aat:300008347"
    ]
},
  "bbox": [],
  "geometry": {"coordinates":[-93.1,15.4],"type":"Point"}
}
=======
{"geometry":{"type":"Point","coordinates":[-93.100000,15.400000]},"type":"Feature","properties":{"hierarchy":["tgn:7364278","tgn:7005580","tgn:1000001","tgn:7005560","tgn:7029392"],"placetype":["aat:300008347"],"id":7364278,"name:xx":"El Boquer\u00f3n"}}
>>>>>>> 03f74aca74312dbeaf24d7e61306dd6a786dc3d0
