{
  "id": 1059216,
  "type": "Feature",
  "properties": {
    "tgn:hierarchy":[
        "tgn:1059216",
        "tgn:1000004",
        "tgn:1003384",
        "tgn:7014786",
        "tgn:7029392"
    ],
    "tgn:id":1059216,
    "tgn:name":"Sarybasat",
    "tgn:placetype":[
        "aat:300008347"
    ]
},
  "bbox": [],
  "geometry": {"coordinates":[60.4167,46.6167],"type":"Point"}
}