{
  "id": 2421904,
  "type": "Feature",
  "properties": {
    "tgn:hierarchy":[
        "tgn:2421904",
        "tgn:1000001",
        "tgn:7012149",
        "tgn:7007240",
        "tgn:7029392"
    ],
    "tgn:id":2421904,
    "tgn:name":"Jim Branch",
    "tgn:placetype":[
        "aat:300008699"
    ]
},
  "bbox": [],
  "geometry": {"coordinates":[-81.2833,28.35],"type":"Point"}
}