{
  "id": 7416097,
  "type": "Feature",
  "properties": {
    "tgn:hierarchy":[
        "tgn:7416097",
        "tgn:7005584",
        "tgn:1000001",
        "tgn:7005560",
        "tgn:7029392"
    ],
    "tgn:id":7416097,
    "tgn:name":"Las Anaranjadas, Mesa",
    "tgn:placetype":[
        "aat:300008811"
    ]
},
  "bbox": [],
  "geometry": {"coordinates":[-101.078056,21.714722],"type":"Point"}
}