{
  "id": 2390954,
  "type": "Feature",
  "properties": {
    "tgn:hierarchy":[
        "tgn:2390954",
        "tgn:1000001",
        "tgn:7012149",
        "tgn:7007158",
        "tgn:7029392"
    ],
    "tgn:id":2390954,
    "tgn:name":"Hiline Lateral",
    "tgn:placetype":[
        "aat:300006075"
    ]
},
  "bbox": [],
  "geometry": {"coordinates":[-105.9667,37.7167],"type":"Point"}
}