{
  "id": 7034897,
  "type": "Feature",
  "properties": {
    "tgn:hierarchy":[
        "tgn:7034897",
        "tgn:1003500",
        "tgn:1000003",
        "tgn:7010380",
        "tgn:1000080",
        "tgn:7029392"
    ],
    "tgn:id":7034897,
    "tgn:name":"Tarantola, Secca",
    "tgn:placetype":[
        "aat:300387036"
    ]
},
  "bbox": [],
  "geometry": {"coordinates":[17.230556,40.448611],"type":"Point"}
}