{
  "id": 2534589,
  "type": "Feature",
  "properties": {
    "tgn:hierarchy":[
        "tgn:2534589",
        "tgn:1000001",
        "tgn:7012149",
        "tgn:2001282",
        "tgn:7007524",
        "tgn:7029392"
    ],
    "tgn:id":2534589,
    "tgn:name":"NW SW Section 22 Mine",
    "tgn:placetype":[
        "aat:300000390"
    ]
},
  "bbox": [],
  "geometry": {"coordinates":[-110.5667,47.0333],"type":"Point"}
}