{
  "id": 1060616,
  "type": "Feature",
  "properties": {
    "tgn:hierarchy":[
        "tgn:1060616",
        "tgn:1000004",
        "tgn:7011573",
        "tgn:7018214",
        "tgn:7002435",
        "tgn:7029392"
    ],
    "tgn:id":1060616,
    "tgn:name":"Ugryumovo",
    "tgn:placetype":[
        "aat:300008347"
    ]
},
  "bbox": [],
  "geometry": {"coordinates":[37.65,55.15],"type":"Point"}
}