{
  "id": 7520660,
  "type": "Feature",
  "properties": {
    "tgn:hierarchy":[
        "tgn:7520660",
        "tgn:7001242",
        "tgn:7001311",
        "tgn:7016833",
        "tgn:7029392"
    ],
    "tgn:id":7520660,
    "tgn:name:en":"Abu 'Ab\u00eed, Gebel",
    "tgn:placetype":[
        "aat:300008795"
    ]
},
  "bbox": [],
  "geometry": {"coordinates":[33.45213,26.958008],"type":"Point"}
}