{
  "id": 7500150,
  "type": "Feature",
  "properties": {
    "tgn:hierarchy":[
        "tgn:7500150",
        "tgn:1000004",
        "tgn:1000959",
        "tgn:1000141",
        "tgn:7029392"
    ],
    "tgn:id":7500150,
    "tgn:name":"Jiannan Qiao",
    "tgn:placetype":[
        "aat:300007836"
    ]
},
  "bbox": [],
  "geometry": {"coordinates":[121.557744,25.10758],"type":"Point"}
}