{
  "id": 2095563,
  "type": "Feature",
  "properties": {
    "tgn:hierarchy":[
        "tgn:2095563",
        "tgn:1000001",
        "tgn:2001742",
        "tgn:7012149",
        "tgn:7007712",
        "tgn:7029392"
    ],
    "tgn:id":2095563,
    "tgn:name":"Clubhouse Crossroads",
    "tgn:placetype":[
        "aat:300008347",
        "aat:300387210"
    ]
},
  "bbox": [],
  "geometry": {"coordinates":[-80.3167,32.8833],"type":"Point"}
}