<<<<<<< HEAD
{
  "id": 7368293,
  "type": "Feature",
  "properties": {
    "tgn:hierarchy":[
        "tgn:7368293",
        "tgn:1000001",
        "tgn:7005596",
        "tgn:7005560",
        "tgn:7029392"
    ],
    "tgn:id":7368293,
    "tgn:name":"Hermenegildo Galeana",
    "tgn:placetype":[
        "aat:300387502"
    ]
},
  "bbox": [],
  "geometry": {"coordinates":[-91.416667,17.45],"type":"Point"}
}
=======
{"geometry":{"type":"Point","coordinates":[-91.416667,17.450000]},"type":"Feature","properties":{"hierarchy":["tgn:7368293","tgn:1000001","tgn:7005596","tgn:7005560","tgn:7029392"],"placetype":["aat:300387502"],"id":7368293,"name:xx":"Hermenegildo Galeana"}}
>>>>>>> 03f74aca74312dbeaf24d7e61306dd6a786dc3d0
