{
  "id": 7184728,
  "type": "Feature",
  "properties": {
    "tgn:hierarchy":[
        "tgn:7184728",
        "tgn:7000096",
        "tgn:1000003",
        "tgn:7000084",
        "tgn:7029392"
    ],
    "tgn:id":7184728,
    "tgn:name":"Gosda",
    "tgn:placetype":[
        "aat:300008347"
    ]
},
  "bbox": [],
  "geometry": {"coordinates":[13.95,51.683333],"type":"Point"}
}