{
  "id": 2200518,
  "type": "Feature",
  "properties": {
    "tgn:hierarchy":[
        "tgn:2200518",
        "tgn:1000001",
        "tgn:7012149",
        "tgn:2001851",
        "tgn:7007825",
        "tgn:7029392"
    ],
    "tgn:id":2200518,
    "tgn:name":"Brushy Mountain",
    "tgn:placetype":[
        "aat:300008798"
    ]
},
  "bbox": [],
  "geometry": {"coordinates":[-82.9333,35.85],"type":"Point"}
}