{
  "id": 2566719,
  "type": "Feature",
  "properties": {
    "tgn:hierarchy":[
        "tgn:2566719",
        "tgn:1000001",
        "tgn:7012149",
        "tgn:2124023",
        "tgn:7007248",
        "tgn:7029392"
    ],
    "tgn:id":2566719,
    "tgn:name":"Panola Shoals",
    "tgn:placetype":[
        "aat:300132348"
    ]
},
  "bbox": [],
  "geometry": {"coordinates":[-84.1833,33.65],"type":"Point"}
}