{
  "id": 7035308,
  "type": "Feature",
  "properties": {
    "tgn:hierarchy":[
        "tgn:7035308",
        "tgn:7002991",
        "tgn:1000003",
        "tgn:7002997",
        "tgn:1000080",
        "tgn:7029392"
    ],
    "tgn:id":7035308,
    "tgn:name":"Fortezza, Cima",
    "tgn:placetype":[
        "aat:300008795"
    ]
},
  "bbox": [],
  "geometry": {"coordinates":[12.383056,46.316389],"type":"Point"}
}