{
  "id": 2489073,
  "type": "Feature",
  "properties": {
    "tgn:hierarchy":[
        "tgn:2489073",
        "tgn:1000001",
        "tgn:7012149",
        "tgn:2002129",
        "tgn:7007827",
        "tgn:7029392"
    ],
    "tgn:id":2489073,
    "tgn:name":"Majestic Heights Ten",
    "tgn:placetype":[
        "aat:300008347"
    ]
},
  "bbox": [],
  "geometry": {"coordinates":[-111.9667,41.3333],"type":"Point"}
}