{
  "id": 7191446,
  "type": "Feature",
  "properties": {
    "tgn:hierarchy":[
        "tgn:7191446",
        "tgn:7003669",
        "tgn:1000003",
        "tgn:7000084",
        "tgn:7029392"
    ],
    "tgn:id":7191446,
    "tgn:name":"Faschaberg",
    "tgn:placetype":[
        "aat:300008777"
    ]
},
  "bbox": [],
  "geometry": {"coordinates":[12.616667,49.166667],"type":"Point"}
}