{
  "id": 2021925,
  "type": "Feature",
  "properties": {
    "tgn:hierarchy":[
        "tgn:2021925",
        "tgn:2000297",
        "tgn:1000001",
        "tgn:7012149",
        "tgn:7007248",
        "tgn:7029392"
    ],
    "tgn:id":2021925,
    "tgn:name":"Alto",
    "tgn:placetype":[
        "aat:300008347"
    ]
},
  "bbox": [],
  "geometry": {"coordinates":[-83.5667,34.4667],"type":"Point"}
}