{
  "id": 2236463,
  "type": "Feature",
  "properties": {
    "tgn:hierarchy":[
        "tgn:2236463",
        "tgn:1000001",
        "tgn:7012149",
        "tgn:2000232",
        "tgn:7007158",
        "tgn:7029392"
    ],
    "tgn:id":2236463,
    "tgn:name":"Chicken Spring",
    "tgn:placetype":[
        "aat:300008697"
    ]
},
  "bbox": [],
  "geometry": {"coordinates":[-108.7667,40.8667],"type":"Point"}
}