{
  "id": 2201062,
  "type": "Feature",
  "properties": {
    "tgn:hierarchy":[
        "tgn:2201062",
        "tgn:1000001",
        "tgn:1002328",
        "tgn:7012149",
        "tgn:7007568",
        "tgn:7029392"
    ],
    "tgn:id":2201062,
    "tgn:name":"Bryden Hill Brook",
    "tgn:placetype":[
        "aat:300008699"
    ]
},
  "bbox": [],
  "geometry": {"coordinates":[-74.9167,42.1333],"type":"Point"}
}