{
  "id": 2557625,
  "type": "Feature",
  "properties": {
    "tgn:hierarchy":[
        "tgn:2557625",
        "tgn:1000001",
        "tgn:7012149",
        "tgn:7016022",
        "tgn:7007251",
        "tgn:7029392"
    ],
    "tgn:id":2557625,
    "tgn:name":"Old Prairie duPont Creek",
    "tgn:placetype":[
        "aat:300008706"
    ]
},
  "bbox": [],
  "geometry": {"coordinates":[-90.15,38.5333],"type":"Point"}
}