{
  "id": 2465767,
  "type": "Feature",
  "properties": {
    "tgn:hierarchy":[
        "tgn:2465767",
        "tgn:7006450",
        "tgn:1000001",
        "tgn:7030517",
        "tgn:7012149",
        "tgn:7029392"
    ],
    "tgn:id":2465767,
    "tgn:name":"Lone Rock",
    "tgn:placetype":[
        "aat:300008791"
    ]
},
  "bbox": [],
  "geometry": {"coordinates":[-156.4667,57.05],"type":"Point"}
}