{
  "id": 2272000,
  "type": "Feature",
  "properties": {
    "tgn:hierarchy":[
        "tgn:2272000",
        "tgn:1000001",
        "tgn:7012149",
        "tgn:1002467",
        "tgn:7007919",
        "tgn:7029392"
    ],
    "tgn:id":2272000,
    "tgn:name":"Curles Neck",
    "tgn:placetype":[
        "aat:300008850"
    ]
},
  "bbox": [],
  "geometry": {"coordinates":[-77.2833,37.3667],"type":"Point"}
}