<<<<<<< HEAD
{
  "id": 7374262,
  "type": "Feature",
  "properties": {
    "tgn:hierarchy":[
        "tgn:7374262",
        "tgn:7005586",
        "tgn:1000001",
        "tgn:7005560",
        "tgn:7029392"
    ],
    "tgn:id":7374262,
    "tgn:name":"La Malograda, Cerro",
    "tgn:placetype":[
        "aat:300008795"
    ]
},
  "bbox": [],
  "geometry": {"coordinates":[-103.666667,19.616667],"type":"Point"}
}
=======
{"geometry":{"type":"Point","coordinates":[-103.666667,19.616667]},"type":"Feature","properties":{"hierarchy":["tgn:7374262","tgn:7005586","tgn:1000001","tgn:7005560","tgn:7029392"],"placetype":["aat:300008795"],"id":7374262,"name:xx":"La Malograda, Cerro"}}
>>>>>>> 03f74aca74312dbeaf24d7e61306dd6a786dc3d0
