{
  "id": 2472201,
  "type": "Feature",
  "properties": {
    "tgn:hierarchy":[
        "tgn:2472201",
        "tgn:1000001",
        "tgn:7012149",
        "tgn:2000905",
        "tgn:7007256",
        "tgn:7029392"
    ],
    "tgn:id":2472201,
    "tgn:name":"Louie Island",
    "tgn:placetype":[
        "aat:300008791"
    ]
},
  "bbox": [],
  "geometry": {"coordinates":[-89.8333,30.5167],"type":"Point"}
}