{
  "id": 7190898,
  "type": "Feature",
  "properties": {
    "tgn:hierarchy":[
        "tgn:7190898",
        "tgn:7003669",
        "tgn:1000003",
        "tgn:7000084",
        "tgn:7029392"
    ],
    "tgn:id":7190898,
    "tgn:name":"Forsthart",
    "tgn:placetype":[
        "aat:300387173"
    ]
},
  "bbox": [],
  "geometry": {"coordinates":[13.033333,48.633333],"type":"Point"}
}