{
  "id": 7086230,
  "type": "Feature",
  "properties": {
    "tgn:hierarchy":[
        "tgn:7086230",
        "tgn:1000003",
        "tgn:7003687",
        "tgn:7000084",
        "tgn:7029392"
    ],
    "tgn:id":7086230,
    "tgn:name":"Warz-Berg",
    "tgn:placetype":[
        "aat:300008777"
    ]
},
  "bbox": [],
  "geometry": {"coordinates":[10.983333,52.066667],"type":"Point"}
}