<<<<<<< HEAD
{
  "id": 7051676,
  "type": "Feature",
  "properties": {
    "tgn:hierarchy":[
        "tgn:7051676",
        "tgn:7003171",
        "tgn:1000003",
        "tgn:7003125",
        "tgn:1000080",
        "tgn:7029392"
    ],
    "tgn:id":7051676,
    "tgn:name":"Margarello, Monte",
    "tgn:placetype":[
        "aat:300008795"
    ]
},
  "bbox": [],
  "geometry": {"coordinates":[12.75,42.55],"type":"Point"}
}
=======
{"geometry":{"type":"Point","coordinates":[12.750000,42.550000]},"type":"Feature","properties":{"hierarchy":["tgn:7051676","tgn:7003171","tgn:1000003","tgn:7003125","tgn:1000080","tgn:7029392"],"placetype":["aat:300008795"],"id":7051676,"name:xx":"Margarello, Monte"}}
>>>>>>> 03f74aca74312dbeaf24d7e61306dd6a786dc3d0
