<<<<<<< HEAD
{
  "id": 2259441,
  "type": "Feature",
  "properties": {
    "tgn:hierarchy":[
        "tgn:2259441",
        "tgn:1000001",
        "tgn:7012149",
        "tgn:2002113",
        "tgn:7007827",
        "tgn:7029392"
    ],
    "tgn:id":2259441,
    "tgn:name":"Cottonwood Spring",
    "tgn:placetype":[
        "aat:300008697"
    ]
},
  "bbox": [],
  "geometry": {"coordinates":[-112.3,37.25],"type":"Point"}
}
=======
{"geometry":{"type":"Point","coordinates":[-112.300000,37.250000]},"type":"Feature","properties":{"hierarchy":["tgn:2259441","tgn:1000001","tgn:7012149","tgn:2002113","tgn:7007827","tgn:7029392"],"placetype":["aat:300008697"],"id":2259441,"name:xx":"Cottonwood Spring"}}
>>>>>>> 03f74aca74312dbeaf24d7e61306dd6a786dc3d0
