{
  "id": 7337160,
  "type": "Feature",
  "properties": {
    "tgn:hierarchy":[
        "tgn:7337160",
        "tgn:7002829",
        "tgn:1000003",
        "tgn:7002786",
        "tgn:1000095",
        "tgn:7029392"
    ],
    "tgn:id":7337160,
    "tgn:name":"Codesido",
    "tgn:placetype":[
        "aat:300008347"
    ]
},
  "bbox": [],
  "geometry": {"coordinates":[-7.75,43.283333],"type":"Point"}
}