{
  "id": 7211203,
  "type": "Feature",
  "properties": {
    "tgn:hierarchy":[
        "tgn:7211203",
        "tgn:1000003",
        "tgn:7003677",
        "tgn:7000084",
        "tgn:7029392"
    ],
    "tgn:id":7211203,
    "tgn:name":"Balenbach",
    "tgn:placetype":[
        "aat:300000206"
    ]
},
  "bbox": [],
  "geometry": {"coordinates":[7.383333,50.783333],"type":"Point"}
}