{
  "id": 2087890,
  "type": "Feature",
  "properties": {
    "tgn:hierarchy":[
        "tgn:2087890",
        "tgn:1000001",
        "tgn:1002286",
        "tgn:7012149",
        "tgn:7007710",
        "tgn:7029392"
    ],
    "tgn:id":2087890,
    "tgn:name":"Drury Run",
    "tgn:placetype":[
        "aat:300008347",
        "aat:300387210"
    ]
},
  "bbox": [],
  "geometry": {"coordinates":[-77.7667,41.3167],"type":"Point"}
}