{
  "id": 7411160,
  "type": "Feature",
  "properties": {
    "tgn:hierarchy":[
        "tgn:7411160",
        "tgn:7005587",
        "tgn:1000001",
        "tgn:7005560",
        "tgn:7029392"
    ],
    "tgn:id":7411160,
    "tgn:name:es":"Taxhay",
    "tgn:placetype":[
        "aat:300008347"
    ]
},
  "bbox": [],
  "geometry": {"coordinates":[-99.216667,20.758333],"type":"Point"}
}