{
  "id": 2125797,
  "type": "Feature",
  "properties": {
    "tgn:hierarchy":[
        "tgn:2125797",
        "tgn:1000001",
        "tgn:7012149",
        "tgn:2000992",
        "tgn:7007520",
        "tgn:7029392"
    ],
    "tgn:id":2125797,
    "tgn:name":"Adams Drain",
    "tgn:placetype":[
        "aat:300006075"
    ]
},
  "bbox": [],
  "geometry": {"coordinates":[-84.0667,43.1667],"type":"Point"}
}