{
  "id": 2329576,
  "type": "Feature",
  "properties": {
    "tgn:hierarchy":[
        "tgn:2329576",
        "tgn:1000001",
        "tgn:7012149",
        "tgn:2001115",
        "tgn:7007522",
        "tgn:7029392"
    ],
    "tgn:id":2329576,
    "tgn:name":"Fivemile Branch",
    "tgn:placetype":[
        "aat:300008699"
    ]
},
  "bbox": [],
  "geometry": {"coordinates":[-88.75,30.65],"type":"Point"}
}