{
  "id": 2131103,
  "type": "Feature",
  "properties": {
    "tgn:hierarchy":[
        "tgn:2131103",
        "tgn:1000001",
        "tgn:2001945",
        "tgn:7012149",
        "tgn:7007826",
        "tgn:7029392"
    ],
    "tgn:id":2131103,
    "tgn:name":"Alpine Creek",
    "tgn:placetype":[
        "aat:300008706"
    ]
},
  "bbox": [],
  "geometry": {"coordinates":[-103.7167,30.2667],"type":"Point"}
}