<<<<<<< HEAD
{
  "id": 7020461,
  "type": "Feature",
  "properties": {
    "tgn:hierarchy":[
        "tgn:7020461",
        "tgn:1000001",
        "tgn:7012149",
        "tgn:2001537",
        "tgn:7007709",
        "tgn:7029392"
    ],
    "tgn:id":7020461,
    "tgn:name":"Buck Hollow Branch",
    "tgn:placetype":[
        "aat:300008699"
    ]
},
  "bbox": [],
  "geometry": {"coordinates":[-81.7833,35.5],"type":"Point"}
}
=======
{"geometry":{"type":"Point","coordinates":[-81.783300,35.500000]},"type":"Feature","properties":{"hierarchy":["tgn:7020461","tgn:1000001","tgn:7012149","tgn:2001537","tgn:7007709","tgn:7029392"],"placetype":["aat:300008699"],"id":7020461,"name:xx":"Buck Hollow Branch"}}
>>>>>>> 03f74aca74312dbeaf24d7e61306dd6a786dc3d0
