{
  "id": 2291498,
  "type": "Feature",
  "properties": {
    "tgn:hierarchy":[
        "tgn:2291498",
        "tgn:1000001",
        "tgn:7012149",
        "tgn:7007157",
        "tgn:2000190",
        "tgn:7029392"
    ],
    "tgn:id":2291498,
    "tgn:name":"Doll Ridge",
    "tgn:placetype":[
        "aat:300266640"
    ]
},
  "bbox": [],
  "geometry": {"coordinates":[-122.9167,39.8833],"type":"Point"}
}