{
  "id": 7443572,
  "type": "Feature",
  "properties": {
    "tgn:hierarchy":[
        "tgn:7443572",
        "tgn:7002445",
        "tgn:1000003",
        "tgn:7008166",
        "tgn:7008591",
        "tgn:7029392"
    ],
    "tgn:id":7443572,
    "tgn:name:en":"Oliver's Mount",
    "tgn:placetype":[
        "aat:300008777"
    ]
},
  "bbox": [],
  "geometry": {"coordinates":[-0.405,54.261667],"type":"Point"}
}