{
  "id": 1101141,
  "type": "Feature",
  "properties": {
    "tgn:hierarchy":[
        "tgn:1101141",
        "tgn:1000003",
        "tgn:7003676",
        "tgn:7000084",
        "tgn:7029392"
    ],
    "tgn:id":1101141,
    "tgn:name":"Innerstetalsperre",
    "tgn:placetype":[
        "aat:300006084"
    ]
},
  "bbox": [],
  "geometry": {"coordinates":[10.2833,51.9167],"type":"Point"}
}