{
  "id": 7586179,
  "type": "Feature",
  "properties": {
    "tgn:hierarchy":[
        "tgn:7586179",
        "tgn:1000004",
        "tgn:7000198",
        "tgn:7000799",
        "tgn:7029392"
    ],
    "tgn:id":7586179,
    "tgn:name:en":"Bodpathar",
    "tgn:placetype":[
        "aat:300008347"
    ]
},
  "bbox": [],
  "geometry": {"coordinates":[74.976389,34.373611],"type":"Point"}
}