{
  "id": 1004770,
  "type": "Feature",
  "properties": {
    "tgn:hierarchy":[
        "tgn:1004770",
        "tgn:7003321",
        "tgn:7003030",
        "tgn:1000003",
        "tgn:1000062",
        "tgn:7029392"
    ],
    "tgn:id":1004770,
    "tgn:name":"Jedlesee",
    "tgn:placetype":[
        "aat:300000874"
    ]
},
  "bbox": [],
  "geometry": {"coordinates":[16.3833,48.2667],"type":"Point"}
}