{
  "id": 7531329,
  "type": "Feature",
  "properties": {
    "tgn:hierarchy":[
        "tgn:7531329",
        "tgn:7001242",
        "tgn:7016833",
        "tgn:7001312",
        "tgn:7029392"
    ],
    "tgn:id":7531329,
    "tgn:name:en":"Al Khal\u012bj al 'Abb\u0101s\u012b",
    "tgn:placetype":[
        "aat:300006075"
    ]
},
  "bbox": [],
  "geometry": {"coordinates":[30.813056,30.916667],"type":"Point"}
}