{
  "id": 2179038,
  "type": "Feature",
  "properties": {
    "tgn:hierarchy":[
        "tgn:2179038",
        "tgn:1000001",
        "tgn:2001841",
        "tgn:7012149",
        "tgn:7007825",
        "tgn:7029392"
    ],
    "tgn:id":2179038,
    "tgn:name":"Blair Branch",
    "tgn:placetype":[
        "aat:300008699"
    ]
},
  "bbox": [],
  "geometry": {"coordinates":[-83.8333,35.6667],"type":"Point"}
}