{
  "id": 2582048,
  "type": "Feature",
  "properties": {
    "tgn:hierarchy":[
        "tgn:2582048",
        "tgn:1000001",
        "tgn:2001425",
        "tgn:7012149",
        "tgn:7007564",
        "tgn:7029392"
    ],
    "tgn:id":2582048,
    "tgn:name":"Pine Cliff",
    "tgn:placetype":[
        "aat:300008347"
    ]
},
  "bbox": [],
  "geometry": {"coordinates":[-72.0333,43.3333],"type":"Point"}
}