{
  "id": 2353921,
  "type": "Feature",
  "properties": {
    "tgn:hierarchy":[
        "tgn:2353921",
        "tgn:1000001",
        "tgn:2001419",
        "tgn:7012149",
        "tgn:7007526",
        "tgn:7029392"
    ],
    "tgn:id":2353921,
    "tgn:name":"Goldbanks Quicksilver Mine",
    "tgn:placetype":[
        "aat:300000390"
    ]
},
  "bbox": [],
  "geometry": {"coordinates":[-117.6667,40.4667],"type":"Point"}
}