<<<<<<< HEAD
{
  "id": 7474271,
  "type": "Feature",
  "properties": {
    "tgn:hierarchy":[
        "tgn:7474271",
        "tgn:1000004",
        "tgn:1000454",
        "tgn:1000141",
        "tgn:7029392"
    ],
    "tgn:id":7474271,
    "tgn:name":"Dingbu",
    "tgn:placetype":[
        "aat:300008347"
    ]
},
  "bbox": [],
  "geometry": {"coordinates":[121.417154,24.961268],"type":"Point"}
}
=======
{"geometry":{"type":"Point","coordinates":[121.417154,24.961268]},"type":"Feature","properties":{"hierarchy":["tgn:7474271","tgn:1000004","tgn:1000454","tgn:1000141","tgn:7029392"],"placetype":["aat:300008347"],"id":7474271,"name:xx":"Dingbu"}}
>>>>>>> 03f74aca74312dbeaf24d7e61306dd6a786dc3d0
