{
  "id": 7063985,
  "type": "Feature",
  "properties": {
    "tgn:hierarchy":[
        "tgn:7063985",
        "tgn:7003669",
        "tgn:1000003",
        "tgn:7000084",
        "tgn:7029392"
    ],
    "tgn:id":7063985,
    "tgn:name":"Assenhausen",
    "tgn:placetype":[
        "aat:300008347"
    ]
},
  "bbox": [],
  "geometry": {"coordinates":[11.35,47.95],"type":"Point"}
}