{
  "id": 7242015,
  "type": "Feature",
  "properties": {
    "tgn:hierarchy":[
        "tgn:7242015",
        "tgn:7003457",
        "tgn:1000003",
        "tgn:1000063",
        "tgn:7018236",
        "tgn:7029392"
    ],
    "tgn:id":7242015,
    "tgn:name":"Klemhout",
    "tgn:placetype":[
        "aat:300008347"
    ]
},
  "bbox": [],
  "geometry": {"coordinates":[3.816667,50.833333],"type":"Point"}
}