{
  "id": 1051464,
  "type": "Feature",
  "properties": {
    "tgn:hierarchy":[
        "tgn:1051464",
        "tgn:1000004",
        "tgn:7011528",
        "tgn:7002435",
        "tgn:7029392"
    ],
    "tgn:id":1051464,
    "tgn:name":"Churapcha",
    "tgn:placetype":[
        "aat:300008347"
    ]
},
  "bbox": [],
  "geometry": {"coordinates":[132.3333,62.05],"type":"Point"}
}