{
  "id": 7426248,
  "type": "Feature",
  "properties": {
    "tgn:hierarchy":[
        "tgn:7426248",
        "tgn:7005581",
        "tgn:1000001",
        "tgn:7005560",
        "tgn:7029392"
    ],
    "tgn:id":7426248,
    "tgn:name":"El Anc\u00f3n",
    "tgn:placetype":[
        "aat:300008347"
    ]
},
  "bbox": [],
  "geometry": {"coordinates":[-107.016667,29.316667],"type":"Point"}
}