{
  "id": 7109426,
  "type": "Feature",
  "properties": {
    "tgn:hierarchy":[
        "tgn:7109426",
        "tgn:1000003",
        "tgn:7003689",
        "tgn:7000084",
        "tgn:7029392"
    ],
    "tgn:id":7109426,
    "tgn:name":"Rangen-Berg",
    "tgn:placetype":[
        "aat:300008777"
    ]
},
  "bbox": [],
  "geometry": {"coordinates":[10.516667,50.483333],"type":"Point"}
}