{
  "id": 2309205,
  "type": "Feature",
  "properties": {
    "tgn:hierarchy":[
        "tgn:2309205",
        "tgn:2002130",
        "tgn:1000001",
        "tgn:7012149",
        "tgn:7007828",
        "tgn:7029392"
    ],
    "tgn:id":2309205,
    "tgn:name":"East Slang Creek",
    "tgn:placetype":[
        "aat:300008706"
    ]
},
  "bbox": [],
  "geometry": {"coordinates":[-73.2167,44.2167],"type":"Point"}
}