{
  "id": 2112297,
  "type": "Feature",
  "properties": {
    "tgn:hierarchy":[
        "tgn:2112297",
        "tgn:1000001",
        "tgn:7012149",
        "tgn:2002191",
        "tgn:7007919",
        "tgn:7029392"
    ],
    "tgn:id":2112297,
    "tgn:name":"Holston Mill",
    "tgn:placetype":[
        "aat:300008347",
        "aat:300387210"
    ]
},
  "bbox": [],
  "geometry": {"coordinates":[-81.5833,36.7667],"type":"Point"}
}