{
  "id": 7293846,
  "type": "Feature",
  "properties": {
    "tgn:hierarchy":[
        "tgn:7293846",
        "tgn:7002834",
        "tgn:1000003",
        "tgn:7002786",
        "tgn:1000095",
        "tgn:7029392"
    ],
    "tgn:id":7293846,
    "tgn:name":"Vilanova",
    "tgn:placetype":[
        "aat:300008347"
    ]
},
  "bbox": [],
  "geometry": {"coordinates":[-8.35,42.733333],"type":"Point"}
}