{
  "id": 2501867,
  "type": "Feature",
  "properties": {
    "tgn:hierarchy":[
        "tgn:2501867",
        "tgn:1000001",
        "tgn:2001013",
        "tgn:7012149",
        "tgn:7007521",
        "tgn:7029392"
    ],
    "tgn:id":2501867,
    "tgn:name":"McKay Lake",
    "tgn:placetype":[
        "aat:300008680"
    ]
},
  "bbox": [],
  "geometry": {"coordinates":[-95.1833,47.15],"type":"Point"}
}