{
  "id": 7140958,
  "type": "Feature",
  "properties": {
    "tgn:hierarchy":[
        "tgn:7140958",
        "tgn:1000003",
        "tgn:7003682",
        "tgn:7000084",
        "tgn:7029392"
    ],
    "tgn:id":7140958,
    "tgn:name":"Lorelei",
    "tgn:placetype":[
        "aat:300011692"
    ]
},
  "bbox": [],
  "geometry": {"coordinates":[7.716667,50.133333],"type":"Point"}
}