{
  "id": 2545762,
  "type": "Feature",
  "properties": {
    "tgn:hierarchy":[
        "tgn:2545762",
        "tgn:1000001",
        "tgn:7012149",
        "tgn:2001710",
        "tgn:7007708",
        "tgn:7029392"
    ],
    "tgn:id":2545762,
    "tgn:name":"North Fork Cold Spring Creek",
    "tgn:placetype":[
        "aat:300008706"
    ]
},
  "bbox": [],
  "geometry": {"coordinates":[-121.6333,45.3667],"type":"Point"}
}