<<<<<<< HEAD
{
  "id": 2703836,
  "type": "Feature",
  "properties": {
    "tgn:hierarchy":[
        "tgn:2703836",
        "tgn:1000001",
        "tgn:7012149",
        "tgn:1002594",
        "tgn:7007920",
        "tgn:7029392"
    ],
    "tgn:id":2703836,
    "tgn:name":"Sunbeam Creek",
    "tgn:placetype":[
        "aat:300008706"
    ]
},
  "bbox": [],
  "geometry": {"coordinates":[-121.7,46.75],"type":"Point"}
}
=======
{"geometry":{"type":"Point","coordinates":[-121.700000,46.750000]},"type":"Feature","properties":{"hierarchy":["tgn:2703836","tgn:1000001","tgn:7012149","tgn:1002594","tgn:7007920","tgn:7029392"],"placetype":["aat:300008706"],"id":2703836,"name:xx":"Sunbeam Creek"}}
>>>>>>> 03f74aca74312dbeaf24d7e61306dd6a786dc3d0
