{
  "id": 2351395,
  "type": "Feature",
  "properties": {
    "tgn:hierarchy":[
        "tgn:2351395",
        "tgn:1000001",
        "tgn:7012149",
        "tgn:2001548",
        "tgn:7007709",
        "tgn:7029392"
    ],
    "tgn:id":2351395,
    "tgn:name":"Glen Eden",
    "tgn:placetype":[
        "aat:300008347"
    ]
},
  "bbox": [],
  "geometry": {"coordinates":[-78.6833,35.8167],"type":"Point"}
}