{
  "id": 2582884,
  "type": "Feature",
  "properties": {
    "tgn:hierarchy":[
        "tgn:2582884",
        "tgn:1000001",
        "tgn:7012149",
        "tgn:2002360",
        "tgn:7007922",
        "tgn:7029392"
    ],
    "tgn:id":2582884,
    "tgn:name":"Pine Island Lake",
    "tgn:placetype":[
        "aat:300008680"
    ]
},
  "bbox": [],
  "geometry": {"coordinates":[-91.5667,45.75],"type":"Point"}
}