{
  "id": 2000784,
  "type": "Feature",
  "properties": {
    "tgn:hierarchy":[
        "tgn:2000784",
        "tgn:1000001",
        "tgn:7012149",
        "tgn:7007255",
        "tgn:7029392"
    ],
    "tgn:id":2000784,
    "tgn:name":"Crittenden",
    "tgn:placetype":[
        "aat:300387145",
        "aat:300000771"
    ]
},
  "bbox": [],
  "geometry": {"coordinates":[-88.0833,37.3333],"type":"Point"}
}