{
  "id": 7581043,
  "type": "Feature",
  "properties": {
    "tgn:hierarchy":[
        "tgn:7581043",
        "tgn:1000004",
        "tgn:7000198",
        "tgn:1001882",
        "tgn:7029392"
    ],
    "tgn:id":7581043,
    "tgn:name:en":"Sidd\u0101pur",
    "tgn:placetype":[
        "aat:300008347"
    ]
},
  "bbox": [],
  "geometry": {"coordinates":[74.883333,14.333333],"type":"Point"}
}