{
  "id": 1116760,
  "type": "Feature",
  "properties": {
    "tgn:hierarchy":[
        "tgn:1116760",
        "tgn:1000003",
        "tgn:7000094",
        "tgn:7000084",
        "tgn:7029392"
    ],
    "tgn:id":1116760,
    "tgn:name":"K\u00f6lpin-see",
    "tgn:placetype":[
        "aat:300008680"
    ]
},
  "bbox": [],
  "geometry": {"coordinates":[14.033333,54.033333],"type":"Point"}
}