{
  "id": 2301626,
  "type": "Feature",
  "properties": {
    "tgn:hierarchy":[
        "tgn:2301626",
        "tgn:1000001",
        "tgn:7012149",
        "tgn:2002270",
        "tgn:7013961",
        "tgn:7029392"
    ],
    "tgn:id":2301626,
    "tgn:name":"Dupont Waste Lake",
    "tgn:placetype":[
        "aat:300006191"
    ]
},
  "bbox": [],
  "geometry": {"coordinates":[-81.5333,38.25],"type":"Point"}
}