{
  "id": 1010026,
  "type": "Feature",
  "properties": {
    "tgn:hierarchy":[
        "tgn:1010026",
        "tgn:1001623",
        "tgn:1000049",
        "tgn:1000002",
        "tgn:7029392"
    ],
    "tgn:id":1010026,
    "tgn:name":"Guaitecas, Archipi\u00e9lago de las",
    "tgn:placetype":[
        "aat:300386853"
    ]
},
  "bbox": [],
  "geometry": {"coordinates":[-73.8333,-43.95],"type":"Point"}
}