<<<<<<< HEAD
{
  "id": 2330805,
  "type": "Feature",
  "properties": {
    "tgn:hierarchy":[
        "tgn:2330805",
        "tgn:1000001",
        "tgn:7016172",
        "tgn:7012149",
        "tgn:2000167",
        "tgn:7029392"
    ],
    "tgn:id":2330805,
    "tgn:name":"Flat Mountain",
    "tgn:placetype":[
        "aat:300008798"
    ]
},
  "bbox": [],
  "geometry": {"coordinates":[-92.6833,34.8],"type":"Point"}
}
=======
{"geometry":{"type":"Point","coordinates":[-92.683300,34.800000]},"type":"Feature","properties":{"hierarchy":["tgn:2330805","tgn:1000001","tgn:7016172","tgn:7012149","tgn:2000167","tgn:7029392"],"placetype":["aat:300008798"],"id":2330805,"name:xx":"Flat Mountain"}}
>>>>>>> 03f74aca74312dbeaf24d7e61306dd6a786dc3d0
