{
  "id": 7470895,
  "type": "Feature",
  "properties": {
    "tgn:hierarchy":[
        "tgn:7470895",
        "tgn:7487020",
        "tgn:1000004",
        "tgn:1000141",
        "tgn:7029392"
    ],
    "tgn:id":7470895,
    "tgn:name":"Erliaokeng",
    "tgn:placetype":[
        "aat:300008347"
    ]
},
  "bbox": [],
  "geometry": {"coordinates":[120.931947,24.605394],"type":"Point"}
}