{
  "id": 7285537,
  "type": "Feature",
  "properties": {
    "tgn:hierarchy":[
        "tgn:7285537",
        "tgn:1001695",
        "tgn:1000049",
        "tgn:1000002",
        "tgn:7029392"
    ],
    "tgn:id":7285537,
    "tgn:name":"Pucudegua",
    "tgn:placetype":[
        "aat:300000206"
    ]
},
  "bbox": [],
  "geometry": {"coordinates":[-71.166667,-34.666667],"type":"Point"}
}