<<<<<<< HEAD
{
  "id": 7023118,
  "type": "Feature",
  "properties": {
    "tgn:hierarchy":[
        "tgn:7023118",
        "tgn:1000001",
        "tgn:7012149",
        "tgn:7029392"
    ],
    "tgn:id":7023118,
    "tgn:name":"Sedgwick Draw",
    "tgn:placetype":[
        "aat:300008761"
    ]
},
  "bbox": [],
  "geometry": {"coordinates":[-102.6667,41.0333],"type":"Point"}
}
=======
{"geometry":{"type":"Point","coordinates":[-102.666700,41.033300]},"type":"Feature","properties":{"hierarchy":["tgn:7023118","tgn:1000001","tgn:7012149","tgn:7029392"],"placetype":["aat:300008761"],"id":7023118,"name:xx":"Sedgwick Draw"}}
>>>>>>> 03f74aca74312dbeaf24d7e61306dd6a786dc3d0
