{
  "id": 7023118,
  "type": "Feature",
  "properties": {
    "tgn:hierarchy":[
        "tgn:7023118",
        "tgn:1000001",
        "tgn:7012149",
        "tgn:7029392"
    ],
    "tgn:id":7023118,
    "tgn:name":"Sedgwick Draw",
    "tgn:placetype":[
        "aat:300008761"
    ]
},
  "bbox": [],
  "geometry": {"coordinates":[-102.6667,41.0333],"type":"Point"}
}