<<<<<<< HEAD
{
  "id": 2253796,
  "type": "Feature",
  "properties": {
    "tgn:hierarchy":[
        "tgn:2253796",
        "tgn:1000001",
        "tgn:7012149",
        "tgn:7007526",
        "tgn:7029392"
    ],
    "tgn:id":2253796,
    "tgn:name":"Cooks Creek",
    "tgn:placetype":[
        "aat:300008706"
    ]
},
  "bbox": [],
  "geometry": {"coordinates":[-116.9167,40.2833],"type":"Point"}
}
=======
{"geometry":{"type":"Point","coordinates":[-116.916700,40.283300]},"type":"Feature","properties":{"hierarchy":["tgn:2253796","tgn:1000001","tgn:7012149","tgn:7007526","tgn:7029392"],"placetype":["aat:300008706"],"id":2253796,"name:xx":"Cooks Creek"}}
>>>>>>> 03f74aca74312dbeaf24d7e61306dd6a786dc3d0
