{
  "id": 7279333,
  "type": "Feature",
  "properties": {
    "tgn:hierarchy":[
        "tgn:7279333",
        "tgn:1001705",
        "tgn:1000049",
        "tgn:1000002",
        "tgn:7029392"
    ],
    "tgn:id":7279333,
    "tgn:name":"Robles, Loma de los",
    "tgn:placetype":[
        "aat:300008795"
    ]
},
  "bbox": [],
  "geometry": {"coordinates":[-70.75,-35.433333],"type":"Point"}
}