{
  "id": 7556573,
  "type": "Feature",
  "properties": {
    "tgn:hierarchy":[
        "tgn:7556573",
        "tgn:1000004",
        "tgn:7000198",
        "tgn:7016788",
        "tgn:7029392"
    ],
    "tgn:id":7556573,
    "tgn:name:en":"Pil\u0101ni",
    "tgn:placetype":[
        "aat:300008347"
    ]
},
  "bbox": [],
  "geometry": {"coordinates":[75.602958,28.365399],"type":"Point"}
}