{
  "id": 2139616,
  "type": "Feature",
  "properties": {
    "tgn:hierarchy":[
        "tgn:2139616",
        "tgn:1000001",
        "tgn:7012149",
        "tgn:7014021",
        "tgn:7007709",
        "tgn:7029392"
    ],
    "tgn:id":2139616,
    "tgn:name":"Atando Junction",
    "tgn:placetype":[
        "aat:300008347"
    ]
},
  "bbox": [],
  "geometry": {"coordinates":[-80.8167,35.25],"type":"Point"}
}