{
  "id": 2341381,
  "type": "Feature",
  "properties": {
    "tgn:hierarchy":[
        "tgn:2341381",
        "tgn:1000001",
        "tgn:7012149",
        "tgn:1002604",
        "tgn:7007568",
        "tgn:7029392"
    ],
    "tgn:id":2341381,
    "tgn:name":"Frog Hill",
    "tgn:placetype":[
        "aat:300008798"
    ]
},
  "bbox": [],
  "geometry": {"coordinates":[-77.8167,42.5333],"type":"Point"}
}