{
  "id": 7130556,
  "type": "Feature",
  "properties": {
    "tgn:hierarchy":[
        "tgn:7130556",
        "tgn:1000003",
        "tgn:7003678",
        "tgn:7000084",
        "tgn:7029392"
    ],
    "tgn:id":7130556,
    "tgn:name":"Meiches",
    "tgn:placetype":[
        "aat:300008347"
    ]
},
  "bbox": [],
  "geometry": {"coordinates":[9.25,50.616667],"type":"Point"}
}