<<<<<<< HEAD
{
  "id": 7020653,
  "type": "Feature",
  "properties": {
    "tgn:hierarchy":[
        "tgn:7020653",
        "tgn:1000001",
        "tgn:7012149",
        "tgn:7007157",
        "tgn:1002857",
        "tgn:7029392"
    ],
    "tgn:id":7020653,
    "tgn:name":"Deer Island",
    "tgn:placetype":[
        "aat:300008791"
    ]
},
  "bbox": [],
  "geometry": {"coordinates":[-114.3667,34.1167],"type":"Point"}
}
=======
{"geometry":{"type":"Point","coordinates":[-114.366700,34.116700]},"type":"Feature","properties":{"hierarchy":["tgn:7020653","tgn:1000001","tgn:7012149","tgn:7007157","tgn:1002857","tgn:7029392"],"placetype":["aat:300008791"],"id":7020653,"name:xx":"Deer Island"}}
>>>>>>> 03f74aca74312dbeaf24d7e61306dd6a786dc3d0
