{
  "id": 2547400,
  "type": "Feature",
  "properties": {
    "tgn:hierarchy":[
        "tgn:2547400",
        "tgn:1000001",
        "tgn:7012149",
        "tgn:7007250",
        "tgn:7029392"
    ],
    "tgn:id":2547400,
    "tgn:name":"North Fork Smith Creek",
    "tgn:placetype":[
        "aat:300008706"
    ]
},
  "bbox": [],
  "geometry": {"coordinates":[-115.3667,45.1833],"type":"Point"}
}