{
  "id": 7340226,
  "type": "Feature",
  "properties": {
    "tgn:hierarchy":[
        "tgn:7340226",
        "tgn:7002829",
        "tgn:1000003",
        "tgn:7002786",
        "tgn:1000095",
        "tgn:7029392"
    ],
    "tgn:id":7340226,
    "tgn:name":"Corvelle",
    "tgn:placetype":[
        "aat:300008347"
    ]
},
  "bbox": [],
  "geometry": {"coordinates":[-7.566667,43.35],"type":"Point"}
}