{
  "id": 2513480,
  "type": "Feature",
  "properties": {
    "tgn:hierarchy":[
        "tgn:2513480",
        "tgn:1000001",
        "tgn:2000261",
        "tgn:7012149",
        "tgn:7007240",
        "tgn:7029392"
    ],
    "tgn:id":2513480,
    "tgn:name":"Mill Log Creek",
    "tgn:placetype":[
        "aat:300008706"
    ]
},
  "bbox": [],
  "geometry": {"coordinates":[-81.7667,30.0333],"type":"Point"}
}