{
  "id": 2140060,
  "type": "Feature",
  "properties": {
    "tgn:hierarchy":[
        "tgn:2140060",
        "tgn:1000001",
        "tgn:7012149",
        "tgn:2000985",
        "tgn:7007520",
        "tgn:7029392"
    ],
    "tgn:id":2140060,
    "tgn:name":"Au Sable Lake",
    "tgn:placetype":[
        "aat:300008680"
    ]
},
  "bbox": [],
  "geometry": {"coordinates":[-83.9167,44.4167],"type":"Point"}
}