{
  "id": 7337463,
  "type": "Feature",
  "properties": {
    "tgn:hierarchy":[
        "tgn:7337463",
        "tgn:7002829",
        "tgn:1000003",
        "tgn:7002786",
        "tgn:1000095",
        "tgn:7029392"
    ],
    "tgn:id":7337463,
    "tgn:name":"Choza",
    "tgn:placetype":[
        "aat:300008347"
    ]
},
  "bbox": [],
  "geometry": {"coordinates":[-7.15,43.466667],"type":"Point"}
}