{
  "id": 2626580,
  "type": "Feature",
  "properties": {
    "tgn:hierarchy":[
        "tgn:2626580",
        "tgn:1000001",
        "tgn:7012149",
        "tgn:2001508",
        "tgn:7007709",
        "tgn:7029392"
    ],
    "tgn:id":2626580,
    "tgn:name":"Rocky Knob",
    "tgn:placetype":[
        "aat:300008798"
    ]
},
  "bbox": [],
  "geometry": {"coordinates":[-83.0333,35.1833],"type":"Point"}
}