{
  "id": 1022137,
  "type": "Feature",
  "properties": {
    "tgn:hierarchy":[
        "tgn:1022137",
        "tgn:7006237",
        "tgn:1000047",
        "tgn:7002457",
        "tgn:1000002",
        "tgn:7029392"
    ],
    "tgn:id":1022137,
    "tgn:name":"Monte Azul",
    "tgn:placetype":[
        "aat:300008347"
    ]
},
  "bbox": [],
  "geometry": {"coordinates":[-42.8833,-15.2167],"type":"Point"}
}