{
  "id": 2706020,
  "type": "Feature",
  "properties": {
    "tgn:hierarchy":[
        "tgn:2706020",
        "tgn:1000001",
        "tgn:2001840",
        "tgn:7012149",
        "tgn:7007825",
        "tgn:7029392"
    ],
    "tgn:id":2706020,
    "tgn:name":"Swafford Pond",
    "tgn:placetype":[
        "aat:300008680"
    ]
},
  "bbox": [],
  "geometry": {"coordinates":[-85.15,35.6167],"type":"Point"}
}