{
  "id": 7269290,
  "type": "Feature",
  "properties": {
    "tgn:hierarchy":[
        "tgn:7269290",
        "tgn:7003619",
        "tgn:1000003",
        "tgn:7016845",
        "tgn:7029392"
    ],
    "tgn:id":7269290,
    "tgn:name:nl":"Nuldernauw",
    "tgn:placetype":[
        "aat:300386965"
    ]
},
  "bbox": [],
  "geometry": {"coordinates":[5.55,52.283333],"type":"Point"}
}