{
  "id": 1034026,
  "type": "Feature",
  "properties": {
    "tgn:hierarchy":[
        "tgn:1034026",
        "tgn:1000003",
        "tgn:7002883",
        "tgn:1000070",
        "tgn:7029392"
    ],
    "tgn:id":1034026,
    "tgn:name":"Leuville-sur-Orge",
    "tgn:placetype":[
        "aat:300008347"
    ]
},
  "bbox": [],
  "geometry": {"coordinates":[2.25,48.6167],"type":"Point"}
}