{
  "id": 2638589,
  "type": "Feature",
  "properties": {
    "tgn:hierarchy":[
        "tgn:2638589",
        "tgn:1000001",
        "tgn:7012149",
        "tgn:2000476",
        "tgn:7007250",
        "tgn:7029392"
    ],
    "tgn:id":2638589,
    "tgn:name":"Salmon River Mountains",
    "tgn:placetype":[
        "aat:300386831"
    ]
},
  "bbox": [],
  "geometry": {"coordinates":[-114.9167,45.4167],"type":"Point"}
}