{
  "id": 2503906,
  "type": "Feature",
  "properties": {
    "tgn:hierarchy":[
        "tgn:2503906",
        "tgn:1000001",
        "tgn:7012149",
        "tgn:7007825",
        "tgn:7029392"
    ],
    "tgn:id":2503906,
    "tgn:name":"Meadow Creek",
    "tgn:placetype":[
        "aat:300008706"
    ]
},
  "bbox": [],
  "geometry": {"coordinates":[-82.9667,35.9667],"type":"Point"}
}