{
  "id": 7255097,
  "type": "Feature",
  "properties": {
    "tgn:hierarchy":[
        "tgn:7255097",
        "tgn:7003458",
        "tgn:1000003",
        "tgn:1000063",
        "tgn:7018236",
        "tgn:7029392"
    ],
    "tgn:id":7255097,
    "tgn:name":"Vierwege",
    "tgn:placetype":[
        "aat:300008347"
    ]
},
  "bbox": [],
  "geometry": {"coordinates":[3.164994,51.285588],"type":"Point"}
}