{
  "id": 2274587,
  "type": "Feature",
  "properties": {
    "tgn:hierarchy":[
        "tgn:2274587",
        "tgn:1000001",
        "tgn:7012149",
        "tgn:1003004",
        "tgn:7007252",
        "tgn:7029392"
    ],
    "tgn:id":2274587,
    "tgn:name":"Dalton Drain",
    "tgn:placetype":[
        "aat:300006075"
    ]
},
  "bbox": [],
  "geometry": {"coordinates":[-85.1667,39.9833],"type":"Point"}
}