{
  "id": 2741497,
  "type": "Feature",
  "properties": {
    "tgn:hierarchy":[
        "tgn:2741497",
        "tgn:1000001",
        "tgn:7012149",
        "tgn:2002124",
        "tgn:7007827",
        "tgn:7029392"
    ],
    "tgn:id":2741497,
    "tgn:name":"Uriah Heap Springs",
    "tgn:placetype":[
        "aat:300008697"
    ]
},
  "bbox": [],
  "geometry": {"coordinates":[-109.8833,40.4167],"type":"Point"}
}