{
  "id": 1127179,
  "type": "Feature",
  "properties": {
    "tgn:hierarchy":[
        "tgn:1127179",
        "tgn:1000971",
        "tgn:1000004",
        "tgn:7000894",
        "tgn:1000120",
        "tgn:7029392"
    ],
    "tgn:id":1127179,
    "tgn:name":"Minato-gawa",
    "tgn:placetype":[
        "aat:300008707"
    ]
},
  "bbox": [],
  "geometry": {"coordinates":[139.8667,35.2167],"type":"Point"}
}