{
  "id": 2282392,
  "type": "Feature",
  "properties": {
    "tgn:hierarchy":[
        "tgn:2282392",
        "tgn:1000001",
        "tgn:1002218",
        "tgn:7012149",
        "tgn:7007157",
        "tgn:7029392"
    ],
    "tgn:id":2282392,
    "tgn:name":"Deer Peak",
    "tgn:placetype":[
        "aat:300008798"
    ]
},
  "bbox": [],
  "geometry": {"coordinates":[-121.5167,39.6667],"type":"Point"}
}