{
  "id": 1125022,
  "type": "Feature",
  "properties": {
    "tgn:hierarchy":[
        "tgn:1125022",
        "tgn:1001945",
        "tgn:1000047",
        "tgn:7002457",
        "tgn:1000002",
        "tgn:7029392"
    ],
    "tgn:id":1125022,
    "tgn:name":"Itapanha\u00fa",
    "tgn:placetype":[
        "aat:300008707"
    ]
},
  "bbox": [],
  "geometry": {"coordinates":[-46.1667,-23.85],"type":"Point"}
}