{
  "id": 7401087,
  "type": "Feature",
  "properties": {
    "tgn:hierarchy":[
        "tgn:7401087",
        "tgn:1000001",
        "tgn:7005599",
        "tgn:7005560",
        "tgn:7029392"
    ],
    "tgn:id":7401087,
    "tgn:name":"Atahualtitla",
    "tgn:placetype":[
        "aat:300008347"
    ]
},
  "bbox": [],
  "geometry": {"coordinates":[-98.166667,20.933333],"type":"Point"}
}