{
  "id": 2097834,
  "type": "Feature",
  "properties": {
    "tgn:hierarchy":[
        "tgn:2097834",
        "tgn:1000001",
        "tgn:7012149",
        "tgn:2001861",
        "tgn:7007825",
        "tgn:7029392"
    ],
    "tgn:id":2097834,
    "tgn:name":"Banner Springs",
    "tgn:placetype":[
        "aat:300008347"
    ]
},
  "bbox": [],
  "geometry": {"coordinates":[-84.9167,36.2333],"type":"Point"}
}