{
  "id": 2217582,
  "type": "Feature",
  "properties": {
    "tgn:hierarchy":[
        "tgn:2217582",
        "tgn:1000001",
        "tgn:7012149",
        "tgn:2001196",
        "tgn:7007523",
        "tgn:7029392"
    ],
    "tgn:id":2217582,
    "tgn:name":"Campbell Hill",
    "tgn:placetype":[
        "aat:300008798"
    ]
},
  "bbox": [],
  "geometry": {"coordinates":[-92.25,36.8833],"type":"Point"}
}