{
  "id": 2121682,
  "type": "Feature",
  "properties": {
    "tgn:hierarchy":[
        "tgn:2121682",
        "tgn:1000001",
        "tgn:7012149",
        "tgn:2002337",
        "tgn:7007922",
        "tgn:7029392"
    ],
    "tgn:id":2121682,
    "tgn:name":"McAllister",
    "tgn:placetype":[
        "aat:300008347"
    ]
},
  "bbox": [],
  "geometry": {"coordinates":[-87.7167,45.3167],"type":"Point"}
}