{
  "id": 7558358,
  "type": "Feature",
  "properties": {
    "tgn:hierarchy":[
        "tgn:7558358",
        "tgn:1000004",
        "tgn:7000198",
        "tgn:7001797",
        "tgn:7029392"
    ],
    "tgn:id":7558358,
    "tgn:name:en":"Pulivalam",
    "tgn:placetype":[
        "aat:300008347"
    ]
},
  "bbox": [],
  "geometry": {"coordinates":[78.633333,11.016667],"type":"Point"}
}