{
  "id": 7197239,
  "type": "Feature",
  "properties": {
    "tgn:hierarchy":[
        "tgn:7197239",
        "tgn:1000003",
        "tgn:7003688",
        "tgn:7000084",
        "tgn:7029392"
    ],
    "tgn:id":7197239,
    "tgn:name":"Der Ort",
    "tgn:placetype":[
        "aat:300386846"
    ]
},
  "bbox": [],
  "geometry": {"coordinates":[9.866667,54.466667],"type":"Point"}
}