{
  "id": 7491031,
  "type": "Feature",
  "properties": {
    "tgn:hierarchy":[
        "tgn:7491031",
        "tgn:1000004",
        "tgn:7492971",
        "tgn:1000141",
        "tgn:7029392"
    ],
    "tgn:id":7491031,
    "tgn:name":"Jiupeng Shan",
    "tgn:placetype":[
        "aat:300008798"
    ]
},
  "bbox": [],
  "geometry": {"coordinates":[120.875556,22.098333],"type":"Point"}
}