{
  "id": 7158652,
  "type": "Feature",
  "properties": {
    "tgn:hierarchy":[
        "tgn:7158652",
        "tgn:1000003",
        "tgn:7003685",
        "tgn:7000084",
        "tgn:7029392"
    ],
    "tgn:id":7158652,
    "tgn:name":"H\u00f6llengrund",
    "tgn:placetype":[
        "aat:300008773"
    ]
},
  "bbox": [],
  "geometry": {"coordinates":[14.05,50.966667],"type":"Point"}
}