{
  "id": 2634678,
  "type": "Feature",
  "properties": {
    "tgn:hierarchy":[
        "tgn:2634678",
        "tgn:1000001",
        "tgn:7012149",
        "tgn:2001883",
        "tgn:7007825",
        "tgn:7029392"
    ],
    "tgn:id":2634678,
    "tgn:name":"Rutherford Branch",
    "tgn:placetype":[
        "aat:300008699"
    ]
},
  "bbox": [],
  "geometry": {"coordinates":[-83.75,36.0167],"type":"Point"}
}