{
  "id": 2051870,
  "type": "Feature",
  "properties": {
    "tgn:hierarchy":[
        "tgn:2051870",
        "tgn:1000001",
        "tgn:7012149",
        "tgn:2000997",
        "tgn:7007520",
        "tgn:7029392"
    ],
    "tgn:id":2051870,
    "tgn:name":"Fairgrove",
    "tgn:placetype":[
        "aat:300008347"
    ]
},
  "bbox": [],
  "geometry": {"coordinates":[-83.5333,43.5167],"type":"Point"}
}