{
  "id": 2264203,
  "type": "Feature",
  "properties": {
    "tgn:hierarchy":[
        "tgn:2264203",
        "tgn:1000001",
        "tgn:7012149",
        "tgn:7007157",
        "tgn:2000185",
        "tgn:7029392"
    ],
    "tgn:id":2264203,
    "tgn:name":"Coyote Valley Rancheria",
    "tgn:placetype":[
        "aat:300008347",
        "aat:300167671"
    ]
},
  "bbox": [],
  "geometry": {"coordinates":[-123.15,39.2167],"type":"Point"}
}