{
  "id": 1135323,
  "type": "Feature",
  "properties": {
    "tgn:hierarchy":[
        "tgn:1135323",
        "tgn:1000001",
        "tgn:7014090",
        "tgn:7012149",
        "tgn:7007565",
        "tgn:7029392"
    ],
    "tgn:id":1135323,
    "tgn:name":"Nut Swamp Brook",
    "tgn:placetype":[
        "aat:300008703"
    ]
},
  "bbox": [],
  "geometry": {"coordinates":[-74.1333,40.3667],"type":"Point"}
}