{
  "id": 2547694,
  "type": "Feature",
  "properties": {
    "tgn:hierarchy":[
        "tgn:2547694",
        "tgn:2000456",
        "tgn:1000001",
        "tgn:7012149",
        "tgn:7007250",
        "tgn:7029392"
    ],
    "tgn:id":2547694,
    "tgn:name":"North Fork Tyson Creek",
    "tgn:placetype":[
        "aat:300008706"
    ]
},
  "bbox": [],
  "geometry": {"coordinates":[-116.4833,47.0833],"type":"Point"}
}