<<<<<<< HEAD
{
  "id": 7026241,
  "type": "Feature",
  "properties": {
    "tgn:hierarchy":[
        "tgn:7026241",
        "tgn:7002445",
        "tgn:1000003",
        "tgn:7011901",
        "tgn:7008591",
        "tgn:7029392"
    ],
    "tgn:id":7026241,
    "tgn:name":"Woughton on the Green",
    "tgn:placetype":[
        "aat:300008347",
        "aat:300008372"
    ]
},
  "bbox": [],
  "geometry": {"coordinates":[-0.7167,52.0167],"type":"Point"}
}
=======
{"geometry":{"type":"Point","coordinates":[-0.716700,52.016700]},"type":"Feature","properties":{"hierarchy":["tgn:7026241","tgn:7002445","tgn:1000003","tgn:7011901","tgn:7008591","tgn:7029392"],"placetype":["aat:300008347","aat:300008372"],"id":7026241,"name:xx":"Woughton on the Green"}}
>>>>>>> 03f74aca74312dbeaf24d7e61306dd6a786dc3d0
