{
  "id": 7033633,
  "type": "Feature",
  "properties": {
    "tgn:hierarchy":[
        "tgn:7033633",
        "tgn:7024843",
        "tgn:1000003",
        "tgn:7008516",
        "tgn:1000080",
        "tgn:7029392"
    ],
    "tgn:id":7033633,
    "tgn:name":"Rivabella",
    "tgn:placetype":[
        "aat:300008347"
    ]
},
  "bbox": [],
  "geometry": {"coordinates":[12.543889,44.088056],"type":"Point"}
}