{
  "id": 7326348,
  "type": "Feature",
  "properties": {
    "tgn:hierarchy":[
        "tgn:7326348",
        "tgn:7008911",
        "tgn:1000003",
        "tgn:7002763",
        "tgn:1000095",
        "tgn:7029392"
    ],
    "tgn:id":7326348,
    "tgn:name":"Piantes",
    "tgn:placetype":[
        "aat:300008347"
    ]
},
  "bbox": [],
  "geometry": {"coordinates":[-6.833333,43.516667],"type":"Point"}
}