{
  "id": 7509108,
  "type": "Feature",
  "properties": {
    "tgn:hierarchy":[
        "tgn:7509108",
        "tgn:1008380",
        "tgn:7520093",
        "tgn:1000226",
        "tgn:1000006",
        "tgn:7029392"
    ],
    "tgn:id":7509108,
    "tgn:name:en":"Tahuokaretu Stream",
    "tgn:placetype":[
        "aat:300008699"
    ]
},
  "bbox": [],
  "geometry": {"coordinates":[176.333333,-40.416667],"type":"Point"}
}