{
  "id": 7299794,
  "type": "Feature",
  "properties": {
    "tgn:hierarchy":[
        "tgn:7299794",
        "tgn:1001439",
        "tgn:1000003",
        "tgn:7002797",
        "tgn:1000095",
        "tgn:7029392"
    ],
    "tgn:id":7299794,
    "tgn:name":"Tienda, Pico de",
    "tgn:placetype":[
        "aat:300008798"
    ]
},
  "bbox": [],
  "geometry": {"coordinates":[-1.483333,38.433333],"type":"Point"}
}