<<<<<<< HEAD
{
  "id": 2335035,
  "type": "Feature",
  "properties": {
    "tgn:hierarchy":[
        "tgn:2335035",
        "tgn:1002538",
        "tgn:1000001",
        "tgn:7012149",
        "tgn:7007239",
        "tgn:7029392"
    ],
    "tgn:id":2335035,
    "tgn:name":"Forrest Grove Village",
    "tgn:placetype":[
        "aat:300008347"
    ]
},
  "bbox": [],
  "geometry": {"coordinates":[-75.6667,39.1667],"type":"Point"}
}
=======
{"geometry":{"type":"Point","coordinates":[-75.666700,39.166700]},"type":"Feature","properties":{"hierarchy":["tgn:2335035","tgn:1002538","tgn:1000001","tgn:7012149","tgn:7007239","tgn:7029392"],"placetype":["aat:300008347"],"id":2335035,"name:xx":"Forrest Grove Village"}}
>>>>>>> 03f74aca74312dbeaf24d7e61306dd6a786dc3d0
