{
  "id": 2768113,
  "type": "Feature",
  "properties": {
    "tgn:hierarchy":[
        "tgn:2768113",
        "tgn:1000001",
        "tgn:7012149",
        "tgn:2001249",
        "tgn:7007523",
        "tgn:7029392"
    ],
    "tgn:id":2768113,
    "tgn:name":"Whites Branch",
    "tgn:placetype":[
        "aat:300008699"
    ]
},
  "bbox": [],
  "geometry": {"coordinates":[-93.3833,36.6333],"type":"Point"}
}