{
  "id": 7183568,
  "type": "Feature",
  "properties": {
    "tgn:hierarchy":[
        "tgn:7183568",
        "tgn:1000003",
        "tgn:7003678",
        "tgn:7000084",
        "tgn:7029392"
    ],
    "tgn:id":7183568,
    "tgn:name":"G\u00f6tzen",
    "tgn:placetype":[
        "aat:300008347"
    ]
},
  "bbox": [],
  "geometry": {"coordinates":[9.133333,50.516667],"type":"Point"}
}