{
  "id": 2706584,
  "type": "Feature",
  "properties": {
    "tgn:hierarchy":[
        "tgn:2706584",
        "tgn:1000001",
        "tgn:2001182",
        "tgn:7012149",
        "tgn:7007523",
        "tgn:7029392"
    ],
    "tgn:id":2706584,
    "tgn:name":"Swan Lake",
    "tgn:placetype":[
        "aat:300006191"
    ]
},
  "bbox": [],
  "geometry": {"coordinates":[-94.3167,38.8167],"type":"Point"}
}