<<<<<<< HEAD
{
  "id": 7374251,
  "type": "Feature",
  "properties": {
    "tgn:hierarchy":[
        "tgn:7374251",
        "tgn:7005581",
        "tgn:1000001",
        "tgn:7005560",
        "tgn:7029392"
    ],
    "tgn:id":7374251,
    "tgn:name":"La Manga",
    "tgn:placetype":[
        "aat:300008347"
    ]
},
  "bbox": [],
  "geometry": {"coordinates":[-105.15,27.483333],"type":"Point"}
}
=======
{"geometry":{"type":"Point","coordinates":[-105.150000,27.483333]},"type":"Feature","properties":{"hierarchy":["tgn:7374251","tgn:7005581","tgn:1000001","tgn:7005560","tgn:7029392"],"placetype":["aat:300008347"],"id":7374251,"name:xx":"La Manga"}}
>>>>>>> 03f74aca74312dbeaf24d7e61306dd6a786dc3d0
