{
  "id": 2295525,
  "type": "Feature",
  "properties": {
    "tgn:hierarchy":[
        "tgn:2295525",
        "tgn:7002659",
        "tgn:1000001",
        "tgn:7012149",
        "tgn:2000047",
        "tgn:7029392"
    ],
    "tgn:id":2295525,
    "tgn:name":"Dripping Spring Branch",
    "tgn:placetype":[
        "aat:300008699"
    ]
},
  "bbox": [],
  "geometry": {"coordinates":[-86.35,34.3833],"type":"Point"}
}