{
  "id": 2398964,
  "type": "Feature",
  "properties": {
    "tgn:hierarchy":[
        "tgn:2398964",
        "tgn:1002538",
        "tgn:1000001",
        "tgn:7012149",
        "tgn:7007239",
        "tgn:7029392"
    ],
    "tgn:id":2398964,
    "tgn:name":"Hopkins Corners",
    "tgn:placetype":[
        "aat:300008347"
    ]
},
  "bbox": [],
  "geometry": {"coordinates":[-75.6667,38.95],"type":"Point"}
}