{
  "id": 7034619,
  "type": "Feature",
  "properties": {
    "tgn:hierarchy":[
        "tgn:7034619",
        "tgn:1003500",
        "tgn:1000003",
        "tgn:7010380",
        "tgn:1000080",
        "tgn:7029392"
    ],
    "tgn:id":7034619,
    "tgn:name":"Casino Ungaro",
    "tgn:placetype":[
        "aat:300004792"
    ]
},
  "bbox": [],
  "geometry": {"coordinates":[17.235278,40.415278],"type":"Point"}
}