{
  "id": 2193085,
  "type": "Feature",
  "properties": {
    "tgn:hierarchy":[
        "tgn:2193085",
        "tgn:1000001",
        "tgn:7012149",
        "tgn:2000479",
        "tgn:7007250",
        "tgn:7029392"
    ],
    "tgn:id":2193085,
    "tgn:name":"Breakfast Creek",
    "tgn:placetype":[
        "aat:300008706"
    ]
},
  "bbox": [],
  "geometry": {"coordinates":[-116.95,47.95],"type":"Point"}
}