{
  "id": 2054270,
  "type": "Feature",
  "properties": {
    "tgn:hierarchy":[
        "tgn:2054270",
        "tgn:1000001",
        "tgn:7012149",
        "tgn:2001054",
        "tgn:7007521",
        "tgn:7029392"
    ],
    "tgn:id":2054270,
    "tgn:name":"Doran",
    "tgn:placetype":[
        "aat:300008347"
    ]
},
  "bbox": [],
  "geometry": {"coordinates":[-96.4667,46.1833],"type":"Point"}
}