{
  "id": 7513903,
  "type": "Feature",
  "properties": {
    "tgn:hierarchy":[
        "tgn:7513903",
        "tgn:1009227",
        "tgn:1000226",
        "tgn:1000006",
        "tgn:7016850",
        "tgn:7029392"
    ],
    "tgn:id":7513903,
    "tgn:name:en":"Fern Flat",
    "tgn:placetype":[
        "aat:300008347"
    ]
},
  "bbox": [],
  "geometry": {"coordinates":[172.25,-41.783333],"type":"Point"}
}