{
  "id": 2673157,
  "type": "Feature",
  "properties": {
    "tgn:hierarchy":[
        "tgn:2673157",
        "tgn:1000001",
        "tgn:7012149",
        "tgn:2001904",
        "tgn:7007825",
        "tgn:7029392"
    ],
    "tgn:id":2673157,
    "tgn:name":"Snake Ridge",
    "tgn:placetype":[
        "aat:300266640"
    ]
},
  "bbox": [],
  "geometry": {"coordinates":[-87.7833,35.7833],"type":"Point"}
}