{
  "id": 2775495,
  "type": "Feature",
  "properties": {
    "tgn:hierarchy":[
        "tgn:2775495",
        "tgn:1000001",
        "tgn:7012149",
        "tgn:7007250",
        "tgn:7029392"
    ],
    "tgn:id":2775495,
    "tgn:name":"Wilson Creek",
    "tgn:placetype":[
        "aat:300008706"
    ]
},
  "bbox": [],
  "geometry": {"coordinates":[-111.6833,43.0333],"type":"Point"}
}