{
  "id": 2269246,
  "type": "Feature",
  "properties": {
    "tgn:hierarchy":[
        "tgn:2269246",
        "tgn:1000001",
        "tgn:7012149",
        "tgn:2000642",
        "tgn:7007253",
        "tgn:7029392"
    ],
    "tgn:id":2269246,
    "tgn:name":"Crow Creek",
    "tgn:placetype":[
        "aat:300008706"
    ]
},
  "bbox": [],
  "geometry": {"coordinates":[-90.5333,41.65],"type":"Point"}
}