{
  "id": 2696909,
  "type": "Feature",
  "properties": {
    "tgn:hierarchy":[
        "tgn:2696909",
        "tgn:1000001",
        "tgn:7012149",
        "tgn:2000790",
        "tgn:7007255",
        "tgn:7029392"
    ],
    "tgn:id":2696909,
    "tgn:name":"Stonewall Lake",
    "tgn:placetype":[
        "aat:300008680"
    ]
},
  "bbox": [],
  "geometry": {"coordinates":[-89.4667,36.5333],"type":"Point"}
}