{
  "id": 7454358,
  "type": "Feature",
  "properties": {
    "tgn:hierarchy":[
        "tgn:7454358",
        "tgn:7002444",
        "tgn:1000003",
        "tgn:7008082",
        "tgn:7008591",
        "tgn:7029392"
    ],
    "tgn:id":7454358,
    "tgn:name:en":"Corran Point",
    "tgn:placetype":[
        "aat:300386846"
    ]
},
  "bbox": [],
  "geometry": {"coordinates":[-5.25,56.716667],"type":"Point"}
}