<<<<<<< HEAD
{
  "id": 7249041,
  "type": "Feature",
  "properties": {
    "tgn:hierarchy":[
        "tgn:7249041",
        "tgn:7003465",
        "tgn:1000003",
        "tgn:1000063",
        "tgn:4012014",
        "tgn:7029392"
    ],
    "tgn:id":7249041,
    "tgn:name":"Ferme de Planchipont",
    "tgn:placetype":[
        "aat:300000206"
    ]
},
  "bbox": [],
  "geometry": {"coordinates":[5.5,49.916667],"type":"Point"}
}
=======
{"geometry":{"type":"Point","coordinates":[5.500000,49.916667]},"type":"Feature","properties":{"hierarchy":["tgn:7249041","tgn:7003465","tgn:1000003","tgn:1000063","tgn:4012014","tgn:7029392"],"placetype":["aat:300000206"],"id":7249041,"name:xx":"Ferme de Planchipont"}}
>>>>>>> 03f74aca74312dbeaf24d7e61306dd6a786dc3d0
