{
  "id": 2749006,
  "type": "Feature",
  "properties": {
    "tgn:hierarchy":[
        "tgn:2749006",
        "tgn:1000001",
        "tgn:7012149",
        "tgn:2001930",
        "tgn:7007825",
        "tgn:7029392"
    ],
    "tgn:id":2749006,
    "tgn:name":"Wallace Branch",
    "tgn:placetype":[
        "aat:300008699"
    ]
},
  "bbox": [],
  "geometry": {"coordinates":[-86.7667,35.7333],"type":"Point"}
}