{
  "id": 7024513,
  "type": "Feature",
  "properties": {
    "tgn:hierarchy":[
        "tgn:7024513",
        "tgn:7593552",
        "tgn:1000001",
        "tgn:7024573",
        "tgn:7029392"
    ],
    "tgn:id":7024513,
    "tgn:name":"Qeqertaq",
    "tgn:placetype":[
        "aat:300008791"
    ]
},
  "bbox": [],
  "geometry": {"coordinates":[-55.3333,72.2667],"type":"Point"}
}