{
  "id": 2571372,
  "type": "Feature",
  "properties": {
    "tgn:hierarchy":[
        "tgn:2571372",
        "tgn:1000001",
        "tgn:2000461",
        "tgn:7012149",
        "tgn:7007250",
        "tgn:7029392"
    ],
    "tgn:id":2571372,
    "tgn:name":"Paul Peak",
    "tgn:placetype":[
        "aat:300008798"
    ]
},
  "bbox": [],
  "geometry": {"coordinates":[-111.0833,43.2833],"type":"Point"}
}