{
  "id": 2673461,
  "type": "Feature",
  "properties": {
    "tgn:hierarchy":[
        "tgn:2673461",
        "tgn:1000001",
        "tgn:7012149",
        "tgn:2001711",
        "tgn:7007708",
        "tgn:7029392"
    ],
    "tgn:id":2673461,
    "tgn:name":"Snider Creek",
    "tgn:placetype":[
        "aat:300008706"
    ]
},
  "bbox": [],
  "geometry": {"coordinates":[-122.9333,42.5667],"type":"Point"}
}