{
  "id": 2520579,
  "type": "Feature",
  "properties": {
    "tgn:hierarchy":[
        "tgn:2520579",
        "tgn:1000001",
        "tgn:7006451",
        "tgn:7012149",
        "tgn:2000098",
        "tgn:7029392"
    ],
    "tgn:id":2520579,
    "tgn:name":"Monkey Cove",
    "tgn:placetype":[
        "aat:300132316"
    ]
},
  "bbox": [],
  "geometry": {"coordinates":[-114.3167,36.0333],"type":"Point"}
}