{
  "id": 2470143,
  "type": "Feature",
  "properties": {
    "tgn:hierarchy":[
        "tgn:2470143",
        "tgn:1000001",
        "tgn:7012149",
        "tgn:1002999",
        "tgn:7007526",
        "tgn:7029392"
    ],
    "tgn:id":2470143,
    "tgn:name":"Lope Spring",
    "tgn:placetype":[
        "aat:300008697"
    ]
},
  "bbox": [],
  "geometry": {"coordinates":[-119.6333,41.3333],"type":"Point"}
}