{
  "id": 2615966,
  "type": "Feature",
  "properties": {
    "tgn:hierarchy":[
        "tgn:2615966",
        "tgn:1000001",
        "tgn:7012149",
        "tgn:2001846",
        "tgn:7007825",
        "tgn:7029392"
    ],
    "tgn:id":2615966,
    "tgn:name":"Reynolds Spring",
    "tgn:placetype":[
        "aat:300008697"
    ]
},
  "bbox": [],
  "geometry": {"coordinates":[-82.2333,36.3667],"type":"Point"}
}