{
  "id": 7528856,
  "type": "Feature",
  "properties": {
    "tgn:hierarchy":[
        "tgn:7528856",
        "tgn:7001242",
        "tgn:7016833",
        "tgn:7001335",
        "tgn:7029392"
    ],
    "tgn:id":7528856,
    "tgn:name:en":"Umm Margab, W\u00e2di",
    "tgn:placetype":[
        "aat:300379998"
    ]
},
  "bbox": [],
  "geometry": {"coordinates":[34.157778,30.646389],"type":"Point"}
}