{
  "id": 2324221,
  "type": "Feature",
  "properties": {
    "tgn:hierarchy":[
        "tgn:2324221",
        "tgn:1000001",
        "tgn:7012149",
        "tgn:1002554",
        "tgn:7007920",
        "tgn:7029392"
    ],
    "tgn:id":2324221,
    "tgn:name":"Featherbed Creek",
    "tgn:placetype":[
        "aat:300008706"
    ]
},
  "bbox": [],
  "geometry": {"coordinates":[-120.9667,46.0167],"type":"Point"}
}