{
  "id": 7480708,
  "type": "Feature",
  "properties": {
    "tgn:hierarchy":[
        "tgn:7480708",
        "tgn:1000004",
        "tgn:7490934",
        "tgn:1000141",
        "tgn:7029392"
    ],
    "tgn:id":7480708,
    "tgn:name":"Jianan Dazhen Shanhua Zhixian",
    "tgn:placetype":[
        "aat:300006075"
    ]
},
  "bbox": [],
  "geometry": {"coordinates":[120.149874,23.059072],"type":"Point"}
}