<<<<<<< HEAD
{
  "id": 7480708,
  "type": "Feature",
  "properties": {
    "tgn:hierarchy":[
        "tgn:7480708",
        "tgn:1000004",
        "tgn:7490934",
        "tgn:1000141",
        "tgn:7029392"
    ],
    "tgn:id":7480708,
    "tgn:name":"Jianan Dazhen Shanhua Zhixian",
    "tgn:placetype":[
        "aat:300006075"
    ]
},
  "bbox": [],
  "geometry": {"coordinates":[120.149874,23.059072],"type":"Point"}
}
=======
{"geometry":{"type":"Point","coordinates":[120.149874,23.059072]},"type":"Feature","properties":{"hierarchy":["tgn:7480708","tgn:1000004","tgn:7490934","tgn:1000141","tgn:7029392"],"placetype":["aat:300006075"],"id":7480708,"name:xx":"Jianan Dazhen Shanhua Zhixian"}}
>>>>>>> 03f74aca74312dbeaf24d7e61306dd6a786dc3d0
