{
  "id": 2372745,
  "type": "Feature",
  "properties": {
    "tgn:hierarchy":[
        "tgn:2372745",
        "tgn:1002166",
        "tgn:1000001",
        "tgn:7012149",
        "tgn:7007520",
        "tgn:7029392"
    ],
    "tgn:id":2372745,
    "tgn:name":"Hall Lake",
    "tgn:placetype":[
        "aat:300008680"
    ]
},
  "bbox": [],
  "geometry": {"coordinates":[-85.2167,42.5833],"type":"Point"}
}