{
  "id": 7008631,
  "type": "Feature",
  "properties": {
    "tgn:hierarchy":[
        "tgn:7008631",
        "tgn:7002443",
        "tgn:1000003",
        "tgn:7008050",
        "tgn:7008591",
        "tgn:7029392"
    ],
    "tgn:id":7008631,
    "tgn:name:en":"Ithon",
    "tgn:placetype":[
        "aat:300008707",
        "aat:300008699"
    ]
},
  "bbox": [],
  "geometry": {"coordinates":[-3.45,52.216667],"type":"Point"}
}