{
  "id": 1048362,
  "type": "Feature",
  "properties": {
    "tgn:hierarchy":[
        "tgn:1048362",
        "tgn:7002448",
        "tgn:7019159",
        "tgn:1000003",
        "tgn:7008591",
        "tgn:7029392"
    ],
    "tgn:id":1048362,
    "tgn:name:en":"Glenarm",
    "tgn:placetype":[
        "aat:300008347"
    ]
},
  "bbox": [],
  "geometry": {"coordinates":[-5.966667,54.966667],"type":"Point"}
}