{
  "id": 2708109,
  "type": "Feature",
  "properties": {
    "tgn:hierarchy":[
        "tgn:2708109",
        "tgn:1000001",
        "tgn:7012149",
        "tgn:2000997",
        "tgn:7007520",
        "tgn:7029392"
    ],
    "tgn:id":2708109,
    "tgn:name":"Swineson Drain",
    "tgn:placetype":[
        "aat:300006075"
    ]
},
  "bbox": [],
  "geometry": {"coordinates":[-83.1333,43.35],"type":"Point"}
}