{
  "id": 2382396,
  "type": "Feature",
  "properties": {
    "tgn:hierarchy":[
        "tgn:2382396",
        "tgn:1000001",
        "tgn:7012149",
        "tgn:2000229",
        "tgn:7007158",
        "tgn:7029392"
    ],
    "tgn:id":2382396,
    "tgn:name":"Haystack Butte",
    "tgn:placetype":[
        "aat:300008798"
    ]
},
  "bbox": [],
  "geometry": {"coordinates":[-102.8667,40.9333],"type":"Point"}
}