{
  "id": 2113871,
  "type": "Feature",
  "properties": {
    "tgn:hierarchy":[
        "tgn:2113871",
        "tgn:1000001",
        "tgn:7012149",
        "tgn:1002730",
        "tgn:7007919",
        "tgn:7029392"
    ],
    "tgn:id":2113871,
    "tgn:name":"Red Bank",
    "tgn:placetype":[
        "aat:300008347",
        "aat:300387210"
    ]
},
  "bbox": [],
  "geometry": {"coordinates":[-75.8333,37.4333],"type":"Point"}
}