<<<<<<< HEAD
{
  "id": 2252979,
  "type": "Feature",
  "properties": {
    "tgn:hierarchy":[
        "tgn:2252979",
        "tgn:1000001",
        "tgn:7012149",
        "tgn:2001604",
        "tgn:7007705",
        "tgn:7029392"
    ],
    "tgn:id":2252979,
    "tgn:name":"Considine",
    "tgn:placetype":[
        "aat:300008347"
    ]
},
  "bbox": [],
  "geometry": {"coordinates":[-99.2667,48.55],"type":"Point"}
}
=======
{"geometry":{"type":"Point","coordinates":[-99.266700,48.550000]},"type":"Feature","properties":{"hierarchy":["tgn:2252979","tgn:1000001","tgn:7012149","tgn:2001604","tgn:7007705","tgn:7029392"],"placetype":["aat:300008347"],"id":2252979,"name:xx":"Considine"}}
>>>>>>> 03f74aca74312dbeaf24d7e61306dd6a786dc3d0
