{
  "id": 2252979,
  "type": "Feature",
  "properties": {
    "tgn:hierarchy":[
        "tgn:2252979",
        "tgn:1000001",
        "tgn:7012149",
        "tgn:2001604",
        "tgn:7007705",
        "tgn:7029392"
    ],
    "tgn:id":2252979,
    "tgn:name":"Considine",
    "tgn:placetype":[
        "aat:300008347"
    ]
},
  "bbox": [],
  "geometry": {"coordinates":[-99.2667,48.55],"type":"Point"}
}