{
  "id": 2242299,
  "type": "Feature",
  "properties": {
    "tgn:hierarchy":[
        "tgn:2242299",
        "tgn:1000001",
        "tgn:7012149",
        "tgn:1002701",
        "tgn:7007706",
        "tgn:7029392"
    ],
    "tgn:id":2242299,
    "tgn:name":"Claypools",
    "tgn:placetype":[
        "aat:300008347"
    ]
},
  "bbox": [],
  "geometry": {"coordinates":[-82.1667,40.0333],"type":"Point"}
}