{
  "id": 2145913,
  "type": "Feature",
  "properties": {
    "tgn:hierarchy":[
        "tgn:2145913",
        "tgn:1000001",
        "tgn:7012149",
        "tgn:2002328",
        "tgn:7007922",
        "tgn:7029392"
    ],
    "tgn:id":2145913,
    "tgn:name":"Ball Bluff",
    "tgn:placetype":[
        "aat:300008798"
    ]
},
  "bbox": [],
  "geometry": {"coordinates":[-90.45,44.1833],"type":"Point"}
}