{
  "id": 2475721,
  "type": "Feature",
  "properties": {
    "tgn:hierarchy":[
        "tgn:2475721",
        "tgn:1000001",
        "tgn:7012149",
        "tgn:7007157",
        "tgn:1002858",
        "tgn:7029392"
    ],
    "tgn:id":2475721,
    "tgn:name":"Lucky Pardner Mine",
    "tgn:placetype":[
        "aat:300000390"
    ]
},
  "bbox": [],
  "geometry": {"coordinates":[-116.5667,33.0667],"type":"Point"}
}