<<<<<<< HEAD
{
  "id": 7023642,
  "type": "Feature",
  "properties": {
    "tgn:hierarchy":[
        "tgn:7023642",
        "tgn:1000001",
        "tgn:7006451",
        "tgn:7012149",
        "tgn:7029392"
    ],
    "tgn:id":7023642,
    "tgn:name":"Peach Spring",
    "tgn:placetype":[
        "aat:300008697"
    ]
},
  "bbox": [],
  "geometry": {"coordinates":[-110.3833,32.7167],"type":"Point"}
}
=======
{"geometry":{"type":"Point","coordinates":[-110.383300,32.716700]},"type":"Feature","properties":{"hierarchy":["tgn:7023642","tgn:1000001","tgn:7006451","tgn:7012149","tgn:7029392"],"placetype":["aat:300008697"],"id":7023642,"name:xx":"Peach Spring"}}
>>>>>>> 03f74aca74312dbeaf24d7e61306dd6a786dc3d0
