{
  "id": 2548248,
  "type": "Feature",
  "properties": {
    "tgn:hierarchy":[
        "tgn:2548248",
        "tgn:1000001",
        "tgn:2001410",
        "tgn:7012149",
        "tgn:7007526",
        "tgn:7029392"
    ],
    "tgn:id":2548248,
    "tgn:name":"North Key West Spring",
    "tgn:placetype":[
        "aat:300008697"
    ]
},
  "bbox": [],
  "geometry": {"coordinates":[-114.1667,36.6167],"type":"Point"}
}