{
  "id": 7423845,
  "type": "Feature",
  "properties": {
    "tgn:hierarchy":[
        "tgn:7423845",
        "tgn:1000001",
        "tgn:7005597",
        "tgn:7005560",
        "tgn:7029392"
    ],
    "tgn:id":7423845,
    "tgn:name":"El Triunfo",
    "tgn:placetype":[
        "aat:300008347"
    ]
},
  "bbox": [],
  "geometry": {"coordinates":[-98.816667,22.433333],"type":"Point"}
}