{
  "id": 7195015,
  "type": "Feature",
  "properties": {
    "tgn:hierarchy":[
        "tgn:7195015",
        "tgn:1000003",
        "tgn:7003682",
        "tgn:7000084",
        "tgn:7029392"
    ],
    "tgn:id":7195015,
    "tgn:name":"Bahnhof Dellfeld",
    "tgn:placetype":[
        "aat:300007783"
    ]
},
  "bbox": [],
  "geometry": {"coordinates":[7.466667,49.233333],"type":"Point"}
}