{
  "id": 2594096,
  "type": "Feature",
  "properties": {
    "tgn:hierarchy":[
        "tgn:2594096",
        "tgn:1000001",
        "tgn:1002225",
        "tgn:7012149",
        "tgn:7007710",
        "tgn:7029392"
    ],
    "tgn:id":2594096,
    "tgn:name":"Portal Number 15",
    "tgn:placetype":[
        "aat:300000390"
    ]
},
  "bbox": [],
  "geometry": {"coordinates":[-78.8167,40.5667],"type":"Point"}
}