{
  "id": 7403181,
  "type": "Feature",
  "properties": {
    "tgn:hierarchy":[
        "tgn:7403181",
        "tgn:1000001",
        "tgn:7005600",
        "tgn:7005560",
        "tgn:7029392"
    ],
    "tgn:id":7403181,
    "tgn:name":"Santa Domingo",
    "tgn:placetype":[
        "aat:300008347"
    ]
},
  "bbox": [],
  "geometry": {"coordinates":[-88.666667,21.141667],"type":"Point"}
}