{
  "id": 1044125,
  "type": "Feature",
  "properties": {
    "tgn:hierarchy":[
        "tgn:1044125",
        "tgn:7003135",
        "tgn:1000003",
        "tgn:7003080",
        "tgn:1000080",
        "tgn:7029392"
    ],
    "tgn:id":1044125,
    "tgn:name":"Ceccano",
    "tgn:placetype":[
        "aat:300008347"
    ]
},
  "bbox": [],
  "geometry": {"coordinates":[13.333333,41.566667],"type":"Point"}
}