{
  "id": 2242604,
  "type": "Feature",
  "properties": {
    "tgn:hierarchy":[
        "tgn:2242604",
        "tgn:1000001",
        "tgn:2000461",
        "tgn:7012149",
        "tgn:7007250",
        "tgn:7029392"
    ],
    "tgn:id":2242604,
    "tgn:name":"Clear Creek",
    "tgn:placetype":[
        "aat:300008706"
    ]
},
  "bbox": [],
  "geometry": {"coordinates":[-111.3833,43.1833],"type":"Point"}
}