{
  "id": 2096302,
  "type": "Feature",
  "properties": {
    "tgn:hierarchy":[
        "tgn:2096302",
        "tgn:1000001",
        "tgn:2001748",
        "tgn:7012149",
        "tgn:7007712",
        "tgn:7029392"
    ],
    "tgn:id":2096302,
    "tgn:name":"New Market",
    "tgn:placetype":[
        "aat:300387016"
    ]
},
  "bbox": [],
  "geometry": {"coordinates":[-82.1333,34.15],"type":"Point"}
}