{
  "id": 1014501,
  "type": "Feature",
  "properties": {
    "tgn:hierarchy":[
        "tgn:1014501",
        "tgn:7005685",
        "tgn:1000001",
        "tgn:7005802",
        "tgn:7029392"
    ],
    "tgn:id":1014501,
    "tgn:name":"Pugwash",
    "tgn:placetype":[
        "aat:300008347"
    ]
},
  "bbox": [],
  "geometry": {"coordinates":[-63.6667,45.8667],"type":"Point"}
}