<<<<<<< HEAD
{
  "id": 7363912,
  "type": "Feature",
  "properties": {
    "tgn:hierarchy":[
        "tgn:7363912",
        "tgn:7005586",
        "tgn:1000001",
        "tgn:7005560",
        "tgn:7029392"
    ],
    "tgn:id":7363912,
    "tgn:name":"El Chorrillo",
    "tgn:placetype":[
        "aat:300008699"
    ]
},
  "bbox": [],
  "geometry": {"coordinates":[-104.7,20.7],"type":"Point"}
}
=======
{"geometry":{"type":"Point","coordinates":[-104.700000,20.700000]},"type":"Feature","properties":{"hierarchy":["tgn:7363912","tgn:7005586","tgn:1000001","tgn:7005560","tgn:7029392"],"placetype":["aat:300008699"],"id":7363912,"name:xx":"El Chorrillo"}}
>>>>>>> 03f74aca74312dbeaf24d7e61306dd6a786dc3d0
