{
  "id": 2639262,
  "type": "Feature",
  "properties": {
    "tgn:hierarchy":[
        "tgn:2639262",
        "tgn:1000001",
        "tgn:7012149",
        "tgn:2001620",
        "tgn:7007706",
        "tgn:7029392"
    ],
    "tgn:id":2639262,
    "tgn:name":"Salt Run",
    "tgn:placetype":[
        "aat:300008699"
    ]
},
  "bbox": [],
  "geometry": {"coordinates":[-82.2667,39.6333],"type":"Point"}
}