{
  "id": 2603927,
  "type": "Feature",
  "properties": {
    "tgn:hierarchy":[
        "tgn:2603927",
        "tgn:1000001",
        "tgn:1002840",
        "tgn:7012149",
        "tgn:7007828",
        "tgn:7029392"
    ],
    "tgn:id":2603927,
    "tgn:name":"Quimby Mountain",
    "tgn:placetype":[
        "aat:300008798"
    ]
},
  "bbox": [],
  "geometry": {"coordinates":[-72.75,43.6833],"type":"Point"}
}