{
  "id": 2028810,
  "type": "Feature",
  "properties": {
    "tgn:hierarchy":[
        "tgn:2028810",
        "tgn:1000001",
        "tgn:7012149",
        "tgn:1002536",
        "tgn:7007251",
        "tgn:7029392"
    ],
    "tgn:id":2028810,
    "tgn:name":"Little Rock",
    "tgn:placetype":[
        "aat:300008347"
    ]
},
  "bbox": [],
  "geometry": {"coordinates":[-88.5667,41.7167],"type":"Point"}
}