{
  "id": 2643161,
  "type": "Feature",
  "properties": {
    "tgn:hierarchy":[
        "tgn:2643161",
        "tgn:1000001",
        "tgn:7012149",
        "tgn:1002742",
        "tgn:7007920",
        "tgn:7029392"
    ],
    "tgn:id":2643161,
    "tgn:name":"Sandy Butte",
    "tgn:placetype":[
        "aat:300008798"
    ]
},
  "bbox": [],
  "geometry": {"coordinates":[-120.4333,48.55],"type":"Point"}
}