{
  "id": 7246242,
  "type": "Feature",
  "properties": {
    "tgn:hierarchy":[
        "tgn:7246242",
        "tgn:7003465",
        "tgn:1000003",
        "tgn:1000063",
        "tgn:4012014",
        "tgn:7029392"
    ],
    "tgn:id":7246242,
    "tgn:name":"Borlon",
    "tgn:placetype":[
        "aat:300008347"
    ]
},
  "bbox": [],
  "geometry": {"coordinates":[5.406349,50.378395],"type":"Point"}
}