{
  "id": 2698065,
  "type": "Feature",
  "properties": {
    "tgn:hierarchy":[
        "tgn:2698065",
        "tgn:2002140",
        "tgn:1000001",
        "tgn:7012149",
        "tgn:7007919",
        "tgn:7029392"
    ],
    "tgn:id":2698065,
    "tgn:name":"Stovall Creek",
    "tgn:placetype":[
        "aat:300008706"
    ]
},
  "bbox": [],
  "geometry": {"coordinates":[-79.0667,37.4667],"type":"Point"}
}