<<<<<<< HEAD
{
  "id": 7356178,
  "type": "Feature",
  "properties": {
    "tgn:hierarchy":[
        "tgn:7356178",
        "tgn:7005583",
        "tgn:1000001",
        "tgn:7005560",
        "tgn:7029392"
    ],
    "tgn:id":7356178,
    "tgn:name":"Carlos Real",
    "tgn:placetype":[
        "aat:300008347"
    ]
},
  "bbox": [],
  "geometry": {"coordinates":[-104.45,24.283333],"type":"Point"}
}
=======
{"geometry":{"type":"Point","coordinates":[-104.450000,24.283333]},"type":"Feature","properties":{"hierarchy":["tgn:7356178","tgn:7005583","tgn:1000001","tgn:7005560","tgn:7029392"],"placetype":["aat:300008347"],"id":7356178,"name:xx":"Carlos Real"}}
>>>>>>> 03f74aca74312dbeaf24d7e61306dd6a786dc3d0
