{
  "id": 2131300,
  "type": "Feature",
  "properties": {
    "tgn:hierarchy":[
        "tgn:2131300",
        "tgn:1000001",
        "tgn:7012149",
        "tgn:2001453",
        "tgn:7007566",
        "tgn:7029392"
    ],
    "tgn:id":2131300,
    "tgn:name":"Alta Vista",
    "tgn:placetype":[
        "aat:300008347"
    ]
},
  "bbox": [],
  "geometry": {"coordinates":[-104.7333,35.5333],"type":"Point"}
}