{
  "id": 2724174,
  "type": "Feature",
  "properties": {
    "tgn:hierarchy":[
        "tgn:2724174",
        "tgn:1000001",
        "tgn:7012149",
        "tgn:2000219",
        "tgn:7007158",
        "tgn:7029392"
    ],
    "tgn:id":2724174,
    "tgn:name":"Tom Branch",
    "tgn:placetype":[
        "aat:300008699"
    ]
},
  "bbox": [],
  "geometry": {"coordinates":[-104.9833,37.8167],"type":"Point"}
}