<<<<<<< HEAD
{
  "id": 2406357,
  "type": "Feature",
  "properties": {
    "tgn:hierarchy":[
        "tgn:2406357",
        "tgn:1000001",
        "tgn:7012149",
        "tgn:2001901",
        "tgn:7007825",
        "tgn:7029392"
    ],
    "tgn:id":2406357,
    "tgn:name":"Hundred-acre Hollow",
    "tgn:placetype":[
        "aat:300008761"
    ]
},
  "bbox": [],
  "geometry": {"coordinates":[-84.3833,36.0667],"type":"Point"}
}
=======
{"geometry":{"type":"Point","coordinates":[-84.383300,36.066700]},"type":"Feature","properties":{"hierarchy":["tgn:2406357","tgn:1000001","tgn:7012149","tgn:2001901","tgn:7007825","tgn:7029392"],"placetype":["aat:300008761"],"id":2406357,"name:xx":"Hundred-acre Hollow"}}
>>>>>>> 03f74aca74312dbeaf24d7e61306dd6a786dc3d0
