{
  "id": 2265850,
  "type": "Feature",
  "properties": {
    "tgn:hierarchy":[
        "tgn:2265850",
        "tgn:1000001",
        "tgn:7012149",
        "tgn:1003020",
        "tgn:7007920",
        "tgn:7029392"
    ],
    "tgn:id":2265850,
    "tgn:name":"Crater Mountain",
    "tgn:placetype":[
        "aat:300008798"
    ]
},
  "bbox": [],
  "geometry": {"coordinates":[-120.9167,48.7333],"type":"Point"}
}