{
  "id": 7036109,
  "type": "Feature",
  "properties": {
    "tgn:hierarchy":[
        "tgn:7036109",
        "tgn:1003440",
        "tgn:1000003",
        "tgn:7003124",
        "tgn:1000080",
        "tgn:7029392"
    ],
    "tgn:id":7036109,
    "tgn:name":"Nessano",
    "tgn:placetype":[
        "aat:300008347"
    ]
},
  "bbox": [],
  "geometry": {"coordinates":[12.009722,46.795278],"type":"Point"}
}