{
  "id": 2783455,
  "type": "Feature",
  "properties": {
    "tgn:hierarchy":[
        "tgn:2783455",
        "tgn:1000001",
        "tgn:7012149",
        "tgn:7007157",
        "tgn:1002956",
        "tgn:7029392"
    ],
    "tgn:id":2783455,
    "tgn:name":"Wutchumna Ditch",
    "tgn:placetype":[
        "aat:300006075"
    ]
},
  "bbox": [],
  "geometry": {"coordinates":[-119.1667,36.3833],"type":"Point"}
}