<<<<<<< HEAD
{
  "id": 7112924,
  "type": "Feature",
  "properties": {
    "tgn:hierarchy":[
        "tgn:7112924",
        "tgn:1000003",
        "tgn:7003688",
        "tgn:7000084",
        "tgn:7029392"
    ],
    "tgn:id":7112924,
    "tgn:name":"Rosengartener Tannen",
    "tgn:placetype":[
        "aat:300008863"
    ]
},
  "bbox": [],
  "geometry": {"coordinates":[10.8,53.533333],"type":"Point"}
}
=======
{"geometry":{"type":"Point","coordinates":[10.800000,53.533333]},"type":"Feature","properties":{"hierarchy":["tgn:7112924","tgn:1000003","tgn:7003688","tgn:7000084","tgn:7029392"],"placetype":["aat:300008863"],"id":7112924,"name:xx":"Rosengartener Tannen"}}
>>>>>>> 03f74aca74312dbeaf24d7e61306dd6a786dc3d0
