{
  "id": 7505779,
  "type": "Feature",
  "properties": {
    "tgn:hierarchy":[
        "tgn:7505779",
        "tgn:1009227",
        "tgn:1000226",
        "tgn:7520095",
        "tgn:1000006",
        "tgn:7029392"
    ],
    "tgn:id":7505779,
    "tgn:name:en":"Tonga Island",
    "tgn:placetype":[
        "aat:300008791"
    ]
},
  "bbox": [],
  "geometry": {"coordinates":[173.066667,-40.883333],"type":"Point"}
}