<<<<<<< HEAD
{
  "id": 2254411,
  "type": "Feature",
  "properties": {
    "tgn:hierarchy":[
        "tgn:2254411",
        "tgn:1000001",
        "tgn:2001411",
        "tgn:7012149",
        "tgn:7007526",
        "tgn:7029392"
    ],
    "tgn:id":2254411,
    "tgn:name":"Coon Creek",
    "tgn:placetype":[
        "aat:300008706"
    ]
},
  "bbox": [],
  "geometry": {"coordinates":[-115.9833,41.1],"type":"Point"}
}
=======
{"geometry":{"type":"Point","coordinates":[-115.983300,41.100000]},"type":"Feature","properties":{"hierarchy":["tgn:2254411","tgn:1000001","tgn:2001411","tgn:7012149","tgn:7007526","tgn:7029392"],"placetype":["aat:300008706"],"id":2254411,"name:xx":"Coon Creek"}}
>>>>>>> 03f74aca74312dbeaf24d7e61306dd6a786dc3d0
