{
  "id": 2029953,
  "type": "Feature",
  "properties": {
    "tgn:hierarchy":[
        "tgn:2029953",
        "tgn:1000001",
        "tgn:1002268",
        "tgn:7012149",
        "tgn:7007251",
        "tgn:7029392"
    ],
    "tgn:id":2029953,
    "tgn:name":"Rosamond",
    "tgn:placetype":[
        "aat:300008347"
    ]
},
  "bbox": [],
  "geometry": {"coordinates":[-89.15,39.3667],"type":"Point"}
}