{
  "id": 7141598,
  "type": "Feature",
  "properties": {
    "tgn:hierarchy":[
        "tgn:7141598",
        "tgn:7003669",
        "tgn:1000003",
        "tgn:7000084",
        "tgn:7029392"
    ],
    "tgn:id":7141598,
    "tgn:name":"L\u00fclsfeld",
    "tgn:placetype":[
        "aat:300008347"
    ]
},
  "bbox": [],
  "geometry": {"coordinates":[10.333333,49.866667],"type":"Point"}
}