{
  "id": 7484029,
  "type": "Feature",
  "properties": {
    "tgn:hierarchy":[
        "tgn:7484029",
        "tgn:1000004",
        "tgn:7001009",
        "tgn:1000141",
        "tgn:7029392"
    ],
    "tgn:id":7484029,
    "tgn:name":"Qingshui Gongyuan",
    "tgn:placetype":[
        "aat:300008187"
    ]
},
  "bbox": [],
  "geometry": {"coordinates":[120.580833,24.268056],"type":"Point"}
}