<<<<<<< HEAD
{
  "id": 7484029,
  "type": "Feature",
  "properties": {
    "tgn:hierarchy":[
        "tgn:7484029",
        "tgn:1000004",
        "tgn:7001009",
        "tgn:1000141",
        "tgn:7029392"
    ],
    "tgn:id":7484029,
    "tgn:name":"Qingshui Gongyuan",
    "tgn:placetype":[
        "aat:300008187"
    ]
},
  "bbox": [],
  "geometry": {"coordinates":[120.580833,24.268056],"type":"Point"}
}
=======
{"geometry":{"type":"Point","coordinates":[120.580833,24.268056]},"type":"Feature","properties":{"hierarchy":["tgn:7484029","tgn:1000004","tgn:7001009","tgn:1000141","tgn:7029392"],"placetype":["aat:300008187"],"id":7484029,"name:xx":"Qingshui Gongyuan"}}
>>>>>>> 03f74aca74312dbeaf24d7e61306dd6a786dc3d0
