{
  "id": 1018147,
  "type": "Feature",
  "properties": {
    "tgn:hierarchy":[
        "tgn:1018147",
        "tgn:1001853",
        "tgn:1000001",
        "tgn:7005560",
        "tgn:7029392"
    ],
    "tgn:id":1018147,
    "tgn:name":"San Alberto",
    "tgn:placetype":[
        "aat:300008347"
    ]
},
  "bbox": [],
  "geometry": {"coordinates":[-101.283333,27.433333],"type":"Point"}
}