{
  "id": 2230206,
  "type": "Feature",
  "properties": {
    "tgn:hierarchy":[
        "tgn:2230206",
        "tgn:1000001",
        "tgn:7006451",
        "tgn:7012149",
        "tgn:2000103",
        "tgn:7029392"
    ],
    "tgn:id":2230206,
    "tgn:name":"Cements, The",
    "tgn:placetype":[
        "aat:300008798"
    ]
},
  "bbox": [],
  "geometry": {"coordinates":[-112.4333,34.1667],"type":"Point"}
}