{
  "id": 7081304,
  "type": "Feature",
  "properties": {
    "tgn:hierarchy":[
        "tgn:7081304",
        "tgn:1000003",
        "tgn:7003676",
        "tgn:7000084",
        "tgn:7029392"
    ],
    "tgn:id":7081304,
    "tgn:name":"Wingst, Forst",
    "tgn:placetype":[
        "aat:300008863"
    ]
},
  "bbox": [],
  "geometry": {"coordinates":[9.05,53.733333],"type":"Point"}
}