{
  "id": 2731283,
  "type": "Feature",
  "properties": {
    "tgn:hierarchy":[
        "tgn:2731283",
        "tgn:1002300",
        "tgn:1000001",
        "tgn:7012149",
        "tgn:7007564",
        "tgn:7029392"
    ],
    "tgn:id":2731283,
    "tgn:name":"Tucker, Mount",
    "tgn:placetype":[
        "aat:300008798"
    ]
},
  "bbox": [],
  "geometry": {"coordinates":[-71.1333,44.9333],"type":"Point"}
}