{
  "id": 2654947,
  "type": "Feature",
  "properties": {
    "tgn:hierarchy":[
        "tgn:2654947",
        "tgn:7006450",
        "tgn:1000001",
        "tgn:7012149",
        "tgn:2000089",
        "tgn:7029392"
    ],
    "tgn:id":2654947,
    "tgn:name":"Shamrock Creek",
    "tgn:placetype":[
        "aat:300008706"
    ]
},
  "bbox": [],
  "geometry": {"coordinates":[-149.3833,67.45],"type":"Point"}
}