{
  "id": 1030095,
  "type": "Feature",
  "properties": {
    "tgn:hierarchy":[
        "tgn:1030095",
        "tgn:7002445",
        "tgn:1000003",
        "tgn:7008154",
        "tgn:7008591",
        "tgn:7029392"
    ],
    "tgn:id":1030095,
    "tgn:name:en":"Moss Side",
    "tgn:placetype":[
        "aat:300008347"
    ]
},
  "bbox": [],
  "geometry": {"coordinates":[-2.95,53.75],"type":"Point"}
}