{
  "id": 2449885,
  "type": "Feature",
  "properties": {
    "tgn:hierarchy":[
        "tgn:2449885",
        "tgn:1000001",
        "tgn:7012149",
        "tgn:2001032",
        "tgn:7007521",
        "tgn:7029392"
    ],
    "tgn:id":2449885,
    "tgn:name":"Lindgren Lake",
    "tgn:placetype":[
        "aat:300008680"
    ]
},
  "bbox": [],
  "geometry": {"coordinates":[-95.15,45.1667],"type":"Point"}
}