{
  "id": 7093654,
  "type": "Feature",
  "properties": {
    "tgn:hierarchy":[
        "tgn:7093654",
        "tgn:7003669",
        "tgn:1000003",
        "tgn:7000084",
        "tgn:7029392"
    ],
    "tgn:id":7093654,
    "tgn:name":"Schweibach",
    "tgn:placetype":[
        "aat:300000206"
    ]
},
  "bbox": [],
  "geometry": {"coordinates":[11.583333,49.383333],"type":"Point"}
}