{
  "id": 7350419,
  "type": "Feature",
  "properties": {
    "tgn:hierarchy":[
        "tgn:7350419",
        "tgn:1000001",
        "tgn:7005595",
        "tgn:7005560",
        "tgn:7029392"
    ],
    "tgn:id":7350419,
    "tgn:name":"Bacayopa",
    "tgn:placetype":[
        "aat:300008347"
    ]
},
  "bbox": [],
  "geometry": {"coordinates":[-108.1075,26.468333],"type":"Point"}
}