{
  "id": 1027723,
  "type": "Feature",
  "properties": {
    "tgn:hierarchy":[
        "tgn:1027723",
        "tgn:7594006",
        "tgn:1000003",
        "tgn:1000066",
        "tgn:7029392"
    ],
    "tgn:id":1027723,
    "tgn:name":"Ballen",
    "tgn:placetype":[
        "aat:300008347"
    ]
},
  "bbox": [],
  "geometry": {"coordinates":[10.6333,55.8167],"type":"Point"}
}