{
  "id": 7469615,
  "type": "Feature",
  "properties": {
    "tgn:hierarchy":[
        "tgn:7469615",
        "tgn:1000004",
        "tgn:7001014",
        "tgn:1000141",
        "tgn:7029392"
    ],
    "tgn:id":7469615,
    "tgn:name":"Haifeng Dao",
    "tgn:placetype":[
        "aat:300008791"
    ]
},
  "bbox": [],
  "geometry": {"coordinates":[120.140833,23.688611],"type":"Point"}
}