{
  "id": 7172946,
  "type": "Feature",
  "properties": {
    "tgn:hierarchy":[
        "tgn:7172946",
        "tgn:7000096",
        "tgn:1000003",
        "tgn:7000084",
        "tgn:7029392"
    ],
    "tgn:id":7172946,
    "tgn:name":"F\u00f6rsterei Gro\u00dfsee",
    "tgn:placetype":[
        "aat:300004792"
    ]
},
  "bbox": [],
  "geometry": {"coordinates":[14.483333,51.933333],"type":"Point"}
}