<<<<<<< HEAD
{
  "id": 7172946,
  "type": "Feature",
  "properties": {
    "tgn:hierarchy":[
        "tgn:7172946",
        "tgn:7000096",
        "tgn:1000003",
        "tgn:7000084",
        "tgn:7029392"
    ],
    "tgn:id":7172946,
    "tgn:name":"F\u00f6rsterei Gro\u00dfsee",
    "tgn:placetype":[
        "aat:300004792"
    ]
},
  "bbox": [],
  "geometry": {"coordinates":[14.483333,51.933333],"type":"Point"}
}
=======
{"geometry":{"type":"Point","coordinates":[14.483333,51.933333]},"type":"Feature","properties":{"hierarchy":["tgn:7172946","tgn:7000096","tgn:1000003","tgn:7000084","tgn:7029392"],"placetype":["aat:300004792"],"id":7172946,"name:xx":"F\u00f6rsterei Gro\u00dfsee"}}
>>>>>>> 03f74aca74312dbeaf24d7e61306dd6a786dc3d0
