{
  "id": 2342834,
  "type": "Feature",
  "properties": {
    "tgn:hierarchy":[
        "tgn:2342834",
        "tgn:1000001",
        "tgn:7012149",
        "tgn:1002732",
        "tgn:7007710",
        "tgn:7029392"
    ],
    "tgn:id":2342834,
    "tgn:name":"Furnace Hollow",
    "tgn:placetype":[
        "aat:300008761"
    ]
},
  "bbox": [],
  "geometry": {"coordinates":[-76.65,40.95],"type":"Point"}
}