{
  "id": 7166166,
  "type": "Feature",
  "properties": {
    "tgn:hierarchy":[
        "tgn:7166166",
        "tgn:1000003",
        "tgn:7003678",
        "tgn:7000084",
        "tgn:7029392"
    ],
    "tgn:id":7166166,
    "tgn:name":"Heidel Berg",
    "tgn:placetype":[
        "aat:300008777"
    ]
},
  "bbox": [],
  "geometry": {"coordinates":[8.95,49.816667],"type":"Point"}
}