{
  "id": 2597966,
  "type": "Feature",
  "properties": {
    "tgn:hierarchy":[
        "tgn:2597966",
        "tgn:1000001",
        "tgn:2001091",
        "tgn:7012149",
        "tgn:7007522",
        "tgn:7029392"
    ],
    "tgn:id":2597966,
    "tgn:name":"Prentiss Bar",
    "tgn:placetype":[
        "aat:300132348"
    ]
},
  "bbox": [],
  "geometry": {"coordinates":[-91.0833,33.75],"type":"Point"}
}