{
  "id": 7283415,
  "type": "Feature",
  "properties": {
    "tgn:hierarchy":[
        "tgn:7283415",
        "tgn:1001630",
        "tgn:1000049",
        "tgn:1000002",
        "tgn:7029392"
    ],
    "tgn:id":7283415,
    "tgn:name":"Pajonales, Sierra",
    "tgn:placetype":[
        "aat:300008795"
    ]
},
  "bbox": [],
  "geometry": {"coordinates":[-70.433333,-27.783333],"type":"Point"}
}