<<<<<<< HEAD
{
  "id": 2331263,
  "type": "Feature",
  "properties": {
    "tgn:hierarchy":[
        "tgn:2331263",
        "tgn:1000001",
        "tgn:7012149",
        "tgn:2001879",
        "tgn:7007825",
        "tgn:7029392"
    ],
    "tgn:id":2331263,
    "tgn:name":"Flat Woods",
    "tgn:placetype":[
        "aat:300132451"
    ]
},
  "bbox": [],
  "geometry": {"coordinates":[-87.8333,35.95],"type":"Point"}
}
=======
{"geometry":{"type":"Point","coordinates":[-87.833300,35.950000]},"type":"Feature","properties":{"hierarchy":["tgn:2331263","tgn:1000001","tgn:7012149","tgn:2001879","tgn:7007825","tgn:7029392"],"placetype":["aat:300132451"],"id":2331263,"name:xx":"Flat Woods"}}
>>>>>>> 03f74aca74312dbeaf24d7e61306dd6a786dc3d0
