{
  "id": 2331263,
  "type": "Feature",
  "properties": {
    "tgn:hierarchy":[
        "tgn:2331263",
        "tgn:1000001",
        "tgn:7012149",
        "tgn:2001879",
        "tgn:7007825",
        "tgn:7029392"
    ],
    "tgn:id":2331263,
    "tgn:name":"Flat Woods",
    "tgn:placetype":[
        "aat:300132451"
    ]
},
  "bbox": [],
  "geometry": {"coordinates":[-87.8333,35.95],"type":"Point"}
}