{
  "id": 2230517,
  "type": "Feature",
  "properties": {
    "tgn:hierarchy":[
        "tgn:2230517",
        "tgn:1000001",
        "tgn:7012149",
        "tgn:2000996",
        "tgn:7007520",
        "tgn:7029392"
    ],
    "tgn:id":2230517,
    "tgn:name":"Center Lake",
    "tgn:placetype":[
        "aat:300008680"
    ]
},
  "bbox": [],
  "geometry": {"coordinates":[-86.5167,46.2167],"type":"Point"}
}