<<<<<<< HEAD
{
  "id": 2153489,
  "type": "Feature",
  "properties": {
    "tgn:hierarchy":[
        "tgn:2153489",
        "tgn:1000001",
        "tgn:7012149",
        "tgn:1002552",
        "tgn:7007920",
        "tgn:7029392"
    ],
    "tgn:id":2153489,
    "tgn:name":"Beans Point",
    "tgn:placetype":[
        "aat:300008850"
    ]
},
  "bbox": [],
  "geometry": {"coordinates":[-122.5167,47.5667],"type":"Point"}
}
=======
{"geometry":{"type":"Point","coordinates":[-122.516700,47.566700]},"type":"Feature","properties":{"hierarchy":["tgn:2153489","tgn:1000001","tgn:7012149","tgn:1002552","tgn:7007920","tgn:7029392"],"placetype":["aat:300008850"],"id":2153489,"name:xx":"Beans Point"}}
>>>>>>> 03f74aca74312dbeaf24d7e61306dd6a786dc3d0
