{
  "id": 2573649,
  "type": "Feature",
  "properties": {
    "tgn:hierarchy":[
        "tgn:2573649",
        "tgn:1000001",
        "tgn:7012149",
        "tgn:7029392"
    ],
    "tgn:id":2573649,
    "tgn:name":"Peck Pond",
    "tgn:placetype":[
        "aat:300006191"
    ]
},
  "bbox": [],
  "geometry": {"coordinates":[-71.7833,41.9333],"type":"Point"}
}