{
  "id": 2756651,
  "type": "Feature",
  "properties": {
    "tgn:hierarchy":[
        "tgn:2756651",
        "tgn:1000001",
        "tgn:7012149",
        "tgn:2002331",
        "tgn:7007922",
        "tgn:7029392"
    ],
    "tgn:id":2756651,
    "tgn:name":"Wells Coulee",
    "tgn:placetype":[
        "aat:300008761"
    ]
},
  "bbox": [],
  "geometry": {"coordinates":[-91.15,43.8167],"type":"Point"}
}