{
  "id": 1023458,
  "type": "Feature",
  "properties": {
    "tgn:hierarchy":[
        "tgn:1023458",
        "tgn:1001708",
        "tgn:1000049",
        "tgn:1000002",
        "tgn:7029392"
    ],
    "tgn:id":1023458,
    "tgn:name":"El Volc\u00e1n",
    "tgn:placetype":[
        "aat:300008347"
    ]
},
  "bbox": [],
  "geometry": {"coordinates":[-70.166667,-33.816667],"type":"Point"}
}