{
  "id": 7549445,
  "type": "Feature",
  "properties": {
    "tgn:hierarchy":[
        "tgn:7549445",
        "tgn:1000004",
        "tgn:7000198",
        "tgn:1001894",
        "tgn:7029392"
    ],
    "tgn:id":7549445,
    "tgn:name:en":"Dh\u0101nasutha",
    "tgn:placetype":[
        "aat:300008347"
    ]
},
  "bbox": [],
  "geometry": {"coordinates":[75.31409,23.279725],"type":"Point"}
}