{
  "id": 7017125,
  "type": "Feature",
  "properties": {
    "tgn:hierarchy":[
        "tgn:7017125",
        "tgn:7002690",
        "tgn:7012056",
        "tgn:1000003",
        "tgn:1000074",
        "tgn:7029392"
    ],
    "tgn:id":7017125,
    "tgn:name":"\u00c1no Vi\u00e1nnos",
    "tgn:placetype":[
        "aat:300008347",
        "aat:300008375"
    ]
},
  "bbox": [],
  "geometry": {"coordinates":[25.416667,35.05],"type":"Point"}
}