{
  "id": 7486868,
  "type": "Feature",
  "properties": {
    "tgn:hierarchy":[
        "tgn:7486868",
        "tgn:7001010",
        "tgn:1000004",
        "tgn:1000141",
        "tgn:7029392"
    ],
    "tgn:id":7486868,
    "tgn:name":"Meilun",
    "tgn:placetype":[
        "aat:300000745"
    ]
},
  "bbox": [],
  "geometry": {"coordinates":[121.628611,23.995],"type":"Point"}
}