{
  "id": 2370211,
  "type": "Feature",
  "properties": {
    "tgn:hierarchy":[
        "tgn:2370211",
        "tgn:1000001",
        "tgn:7012149",
        "tgn:2001669",
        "tgn:7007707",
        "tgn:7029392"
    ],
    "tgn:id":2370211,
    "tgn:name":"Gyp Creek",
    "tgn:placetype":[
        "aat:300008706"
    ]
},
  "bbox": [],
  "geometry": {"coordinates":[-98.9333,36.3167],"type":"Point"}
}