<<<<<<< HEAD
{
  "id": 2765365,
  "type": "Feature",
  "properties": {
    "tgn:hierarchy":[
        "tgn:2765365",
        "tgn:1000001",
        "tgn:7012149",
        "tgn:2001454",
        "tgn:7007566",
        "tgn:7029392"
    ],
    "tgn:id":2765365,
    "tgn:name":"White Ash",
    "tgn:placetype":[
        "aat:300000390"
    ]
},
  "bbox": [],
  "geometry": {"coordinates":[-106.15,35.4],"type":"Point"}
}
=======
{"geometry":{"type":"Point","coordinates":[-106.150000,35.400000]},"type":"Feature","properties":{"hierarchy":["tgn:2765365","tgn:1000001","tgn:7012149","tgn:2001454","tgn:7007566","tgn:7029392"],"placetype":["aat:300000390"],"id":2765365,"name:xx":"White Ash"}}
>>>>>>> 03f74aca74312dbeaf24d7e61306dd6a786dc3d0
