{
  "id": 7590603,
  "type": "Feature",
  "properties": {
    "tgn:hierarchy":[
        "tgn:7590603",
        "tgn:1000004",
        "tgn:7000198",
        "tgn:7000799",
        "tgn:7029392"
    ],
    "tgn:id":7590603,
    "tgn:name:en":"T\u016bngaw\u0101li",
    "tgn:placetype":[
        "aat:300008347"
    ]
},
  "bbox": [],
  "geometry": {"coordinates":[74.336672,33.786265],"type":"Point"}
}