{
  "id": 2384109,
  "type": "Feature",
  "properties": {
    "tgn:hierarchy":[
        "tgn:2384109",
        "tgn:1000001",
        "tgn:7012149",
        "tgn:7007826",
        "tgn:7029392"
    ],
    "tgn:id":2384109,
    "tgn:name":"Heifer Creek",
    "tgn:placetype":[
        "aat:300008706"
    ]
},
  "bbox": [],
  "geometry": {"coordinates":[-100.8667,32.0667],"type":"Point"}
}