{
  "id": 2432113,
  "type": "Feature",
  "properties": {
    "tgn:hierarchy":[
        "tgn:2432113",
        "tgn:1007657",
        "tgn:1002534",
        "tgn:1000001",
        "tgn:7012149",
        "tgn:7007249",
        "tgn:7029392"
    ],
    "tgn:id":2432113,
    "tgn:name":"Kaweonui Point",
    "tgn:placetype":[
        "aat:300008850"
    ]
},
  "bbox": [],
  "geometry": {"coordinates":[-159.4667,22.2167],"type":"Point"}
}