{
  "id": 7399303,
  "type": "Feature",
  "properties": {
    "tgn:hierarchy":[
        "tgn:7399303",
        "tgn:1000001",
        "tgn:7005593",
        "tgn:7005560",
        "tgn:7029392"
    ],
    "tgn:id":7399303,
    "tgn:name":"Seco, Arroyo",
    "tgn:placetype":[
        "aat:300008699"
    ]
},
  "bbox": [],
  "geometry": {"coordinates":[-100.358333,20.325],"type":"Point"}
}