{
  "id": 1028257,
  "type": "Feature",
  "properties": {
    "tgn:hierarchy":[
        "tgn:1028257",
        "tgn:7002445",
        "tgn:1000003",
        "tgn:7008131",
        "tgn:7008591",
        "tgn:7029392"
    ],
    "tgn:id":1028257,
    "tgn:name":"Abridge",
    "tgn:placetype":[
        "aat:300008347"
    ]
},
  "bbox": [],
  "geometry": {"coordinates":[0.1333,51.6667],"type":"Point"}
}