{
  "id": 2309855,
  "type": "Feature",
  "properties": {
    "tgn:hierarchy":[
        "tgn:2309855",
        "tgn:1000001",
        "tgn:7012149",
        "tgn:2001146",
        "tgn:7007522",
        "tgn:7029392"
    ],
    "tgn:id":2309855,
    "tgn:name":"Easthaven",
    "tgn:placetype":[
        "aat:300008347"
    ]
},
  "bbox": [],
  "geometry": {"coordinates":[-89.9667,32.2833],"type":"Point"}
}