<<<<<<< HEAD
{
  "id": 7358169,
  "type": "Feature",
  "properties": {
    "tgn:hierarchy":[
        "tgn:7358169",
        "tgn:7005581",
        "tgn:1000001",
        "tgn:7005560",
        "tgn:7029392"
    ],
    "tgn:id":7358169,
    "tgn:name":"Ejido Nuevo Tampico",
    "tgn:placetype":[
        "aat:300008347"
    ]
},
  "bbox": [],
  "geometry": {"coordinates":[-104.866667,27.3],"type":"Point"}
}
=======
{"geometry":{"type":"Point","coordinates":[-104.866667,27.300000]},"type":"Feature","properties":{"hierarchy":["tgn:7358169","tgn:7005581","tgn:1000001","tgn:7005560","tgn:7029392"],"placetype":["aat:300008347"],"id":7358169,"name:xx":"Ejido Nuevo Tampico"}}
>>>>>>> 03f74aca74312dbeaf24d7e61306dd6a786dc3d0
