{
  "id": 2296075,
  "type": "Feature",
  "properties": {
    "tgn:hierarchy":[
        "tgn:2296075",
        "tgn:1000001",
        "tgn:7016172",
        "tgn:7012149",
        "tgn:2000167",
        "tgn:7029392"
    ],
    "tgn:id":2296075,
    "tgn:name":"Dry Branch",
    "tgn:placetype":[
        "aat:300008699"
    ]
},
  "bbox": [],
  "geometry": {"coordinates":[-92.6667,34.7333],"type":"Point"}
}