{
  "id": 2528073,
  "type": "Feature",
  "properties": {
    "tgn:hierarchy":[
        "tgn:2528073",
        "tgn:1000001",
        "tgn:7012149",
        "tgn:2001709",
        "tgn:7007708",
        "tgn:7029392"
    ],
    "tgn:id":2528073,
    "tgn:name":"Mountain Spring",
    "tgn:placetype":[
        "aat:300008697"
    ]
},
  "bbox": [],
  "geometry": {"coordinates":[-118.85,43.95],"type":"Point"}
}