{
  "id": 2666327,
  "type": "Feature",
  "properties": {
    "tgn:hierarchy":[
        "tgn:2666327",
        "tgn:1000001",
        "tgn:7012149",
        "tgn:1002768",
        "tgn:7007240",
        "tgn:7029392"
    ],
    "tgn:id":2666327,
    "tgn:name":"Sixmile Bend",
    "tgn:placetype":[
        "aat:300008347"
    ]
},
  "bbox": [],
  "geometry": {"coordinates":[-80.5667,26.6333],"type":"Point"}
}