{
  "id": 7313350,
  "type": "Feature",
  "properties": {
    "tgn:hierarchy":[
        "tgn:7313350",
        "tgn:1001692",
        "tgn:1000049",
        "tgn:1000002",
        "tgn:7029392"
    ],
    "tgn:id":7313350,
    "tgn:name":"Llollehue, Cerro",
    "tgn:placetype":[
        "aat:300008777"
    ]
},
  "bbox": [],
  "geometry": {"coordinates":[-73.216667,-39.016667],"type":"Point"}
}