{
  "id": 7494593,
  "type": "Feature",
  "properties": {
    "tgn:hierarchy":[
        "tgn:7494593",
        "tgn:1000004",
        "tgn:7467799",
        "tgn:1000141",
        "tgn:7029392"
    ],
    "tgn:id":7494593,
    "tgn:name":"Bizitou Tifang",
    "tgn:placetype":[
        "aat:300006156"
    ]
},
  "bbox": [],
  "geometry": {"coordinates":[120.650874,23.795488],"type":"Point"}
}