{
  "id": 7299101,
  "type": "Feature",
  "properties": {
    "tgn:hierarchy":[
        "tgn:7299101",
        "tgn:7008912",
        "tgn:7030216",
        "tgn:1000003",
        "tgn:1000095",
        "tgn:7029392"
    ],
    "tgn:id":7299101,
    "tgn:name":"Tolor\u00edu",
    "tgn:placetype":[
        "aat:300008347"
    ]
},
  "bbox": [],
  "geometry": {"coordinates":[1.628265,42.362598],"type":"Point"}
}