<<<<<<< HEAD
{
  "id": 7020907,
  "type": "Feature",
  "properties": {
    "tgn:hierarchy":[
        "tgn:7020907",
        "tgn:1000001",
        "tgn:2000468",
        "tgn:7012149",
        "tgn:7007250",
        "tgn:7029392"
    ],
    "tgn:id":7020907,
    "tgn:name":"Blue Creek",
    "tgn:placetype":[
        "aat:300008706"
    ]
},
  "bbox": [],
  "geometry": {"coordinates":[-112.5833,44.2167],"type":"Point"}
}
=======
{"geometry":{"type":"Point","coordinates":[-112.583300,44.216700]},"type":"Feature","properties":{"hierarchy":["tgn:7020907","tgn:1000001","tgn:2000468","tgn:7012149","tgn:7007250","tgn:7029392"],"placetype":["aat:300008706"],"id":7020907,"name:xx":"Blue Creek"}}
>>>>>>> 03f74aca74312dbeaf24d7e61306dd6a786dc3d0
