{
  "id": 7020907,
  "type": "Feature",
  "properties": {
    "tgn:hierarchy":[
        "tgn:7020907",
        "tgn:1000001",
        "tgn:2000468",
        "tgn:7012149",
        "tgn:7007250",
        "tgn:7029392"
    ],
    "tgn:id":7020907,
    "tgn:name":"Blue Creek",
    "tgn:placetype":[
        "aat:300008706"
    ]
},
  "bbox": [],
  "geometry": {"coordinates":[-112.5833,44.2167],"type":"Point"}
}