{
  "id": 1135765,
  "type": "Feature",
  "properties": {
    "tgn:hierarchy":[
        "tgn:1135765",
        "tgn:7001242",
        "tgn:7015044",
        "tgn:1000182",
        "tgn:7029392"
    ],
    "tgn:id":1135765,
    "tgn:name":"Escravos",
    "tgn:placetype":[
        "aat:300387055"
    ]
},
  "bbox": [],
  "geometry": {"coordinates":[5.1667,5.5833],"type":"Point"}
}