{
  "id": 7274562,
  "type": "Feature",
  "properties": {
    "tgn:hierarchy":[
        "tgn:7274562",
        "tgn:1000003",
        "tgn:7003626",
        "tgn:7016845",
        "tgn:7029392"
    ],
    "tgn:id":7274562,
    "tgn:name:nl":"Zwolsche Diep",
    "tgn:placetype":[
        "aat:300386965"
    ]
},
  "bbox": [],
  "geometry": {"coordinates":[6.016667,52.633333],"type":"Point"}
}