{
  "id": 2700758,
  "type": "Feature",
  "properties": {
    "tgn:hierarchy":[
        "tgn:2700758",
        "tgn:1000001",
        "tgn:1002923",
        "tgn:7012149",
        "tgn:7007517",
        "tgn:7029392"
    ],
    "tgn:id":2700758,
    "tgn:name":"Suffolk Downs Station",
    "tgn:placetype":[
        "aat:300008347"
    ]
},
  "bbox": [],
  "geometry": {"coordinates":[-70.9833,42.3833],"type":"Point"}
}