{
  "id": 7411782,
  "type": "Feature",
  "properties": {
    "tgn:hierarchy":[
        "tgn:7411782",
        "tgn:7005587",
        "tgn:1000001",
        "tgn:7005560",
        "tgn:7029392"
    ],
    "tgn:id":7411782,
    "tgn:name:es":"El Capul\u00edn",
    "tgn:placetype":[
        "aat:300008347"
    ]
},
  "bbox": [],
  "geometry": {"coordinates":[-98.275,19.783333],"type":"Point"}
}