{
  "id": 2425823,
  "type": "Feature",
  "properties": {
    "tgn:hierarchy":[
        "tgn:2425823",
        "tgn:1002132",
        "tgn:1000001",
        "tgn:7012149",
        "tgn:7007919",
        "tgn:7029392"
    ],
    "tgn:id":2425823,
    "tgn:name":"Jolleys Neck",
    "tgn:placetype":[
        "aat:300008850"
    ]
},
  "bbox": [],
  "geometry": {"coordinates":[-75.6167,37.95],"type":"Point"}
}