{
  "id": 7200026,
  "type": "Feature",
  "properties": {
    "tgn:hierarchy":[
        "tgn:7200026",
        "tgn:7003669",
        "tgn:1000003",
        "tgn:7000084",
        "tgn:7029392"
    ],
    "tgn:id":7200026,
    "tgn:name":"D\u00fcrrnbuch",
    "tgn:placetype":[
        "aat:300008347"
    ]
},
  "bbox": [],
  "geometry": {"coordinates":[10.45,49.75],"type":"Point"}
}