{
  "id": 1123954,
  "type": "Feature",
  "properties": {
    "tgn:hierarchy":[
        "tgn:1123954",
        "tgn:1000003",
        "tgn:7003677",
        "tgn:7000084",
        "tgn:7029392"
    ],
    "tgn:id":1123954,
    "tgn:name":"Fleuth",
    "tgn:placetype":[
        "aat:300008707",
        "aat:300008699"
    ]
},
  "bbox": [],
  "geometry": {"coordinates":[6.283333,51.583333],"type":"Point"}
}