{
  "id": 7370294,
  "type": "Feature",
  "properties": {
    "tgn:hierarchy":[
        "tgn:7370294",
        "tgn:1000001",
        "tgn:1001960",
        "tgn:7005560",
        "tgn:7029392"
    ],
    "tgn:id":7370294,
    "tgn:name":"Rancho Jaquiv\u00e9rachi",
    "tgn:placetype":[
        "aat:300000241"
    ]
},
  "bbox": [],
  "geometry": {"coordinates":[-108.783333,30.25],"type":"Point"}
}