<<<<<<< HEAD
{
  "id": 2152617,
  "type": "Feature",
  "properties": {
    "tgn:hierarchy":[
        "tgn:2152617",
        "tgn:1000001",
        "tgn:2002136",
        "tgn:7012149",
        "tgn:7007828",
        "tgn:7029392"
    ],
    "tgn:id":2152617,
    "tgn:name":"Baylies Hill",
    "tgn:placetype":[
        "aat:300008798"
    ]
},
  "bbox": [],
  "geometry": {"coordinates":[-72.5,43.6],"type":"Point"}
}
=======
{"geometry":{"type":"Point","coordinates":[-72.500000,43.600000]},"type":"Feature","properties":{"hierarchy":["tgn:2152617","tgn:1000001","tgn:2002136","tgn:7012149","tgn:7007828","tgn:7029392"],"placetype":["aat:300008798"],"id":2152617,"name:xx":"Baylies Hill"}}
>>>>>>> 03f74aca74312dbeaf24d7e61306dd6a786dc3d0
