{
  "id": 7343435,
  "type": "Feature",
  "properties": {
    "tgn:hierarchy":[
        "tgn:7343435",
        "tgn:7008911",
        "tgn:1000003",
        "tgn:7002763",
        "tgn:1000095",
        "tgn:7029392"
    ],
    "tgn:id":7343435,
    "tgn:name":"Cadanes",
    "tgn:placetype":[
        "aat:300008347"
    ]
},
  "bbox": [],
  "geometry": {"coordinates":[-5.333333,43.383333],"type":"Point"}
}