{
  "id": 1128987,
  "type": "Feature",
  "properties": {
    "tgn:hierarchy":[
        "tgn:1128987",
        "tgn:1009227",
        "tgn:1000226",
        "tgn:1000006",
        "tgn:7029392"
    ],
    "tgn:id":1128987,
    "tgn:name":"Rakaia",
    "tgn:placetype":[
        "aat:300008707",
        "aat:300008699"
    ]
},
  "bbox": [],
  "geometry": {"coordinates":[172.216667,-43.933333],"type":"Point"}
}