{
  "id": 2148902,
  "type": "Feature",
  "properties": {
    "tgn:hierarchy":[
        "tgn:2148902",
        "tgn:1000001",
        "tgn:7012149",
        "tgn:2000837",
        "tgn:7007255",
        "tgn:7029392"
    ],
    "tgn:id":2148902,
    "tgn:name":"Barney Hollow",
    "tgn:placetype":[
        "aat:300008761"
    ]
},
  "bbox": [],
  "geometry": {"coordinates":[-82.25,37.5667],"type":"Point"}
}