{
  "id": 7320634,
  "type": "Feature",
  "properties": {
    "tgn:hierarchy":[
        "tgn:7320634",
        "tgn:7002464",
        "tgn:1000049",
        "tgn:1000002",
        "tgn:7029392"
    ],
    "tgn:id":7320634,
    "tgn:name":"Blanco, R\u00edo",
    "tgn:placetype":[
        "aat:300008699"
    ]
},
  "bbox": [],
  "geometry": {"coordinates":[-68.666667,-19.85],"type":"Point"}
}