{
  "id": 2286284,
  "type": "Feature",
  "properties": {
    "tgn:hierarchy":[
        "tgn:2286284",
        "tgn:1000001",
        "tgn:7012149",
        "tgn:2001293",
        "tgn:7007524",
        "tgn:7029392"
    ],
    "tgn:id":2286284,
    "tgn:name":"Dexter Point",
    "tgn:placetype":[
        "aat:300008798"
    ]
},
  "bbox": [],
  "geometry": {"coordinates":[-110.5333,45.3833],"type":"Point"}
}