{
  "id": 2639340,
  "type": "Feature",
  "properties": {
    "tgn:hierarchy":[
        "tgn:2639340",
        "tgn:1000001",
        "tgn:7006451",
        "tgn:7012149",
        "tgn:2000099",
        "tgn:7029392"
    ],
    "tgn:id":2639340,
    "tgn:name":"Salt Tank",
    "tgn:placetype":[
        "aat:300006191"
    ]
},
  "bbox": [],
  "geometry": {"coordinates":[-110.05,34.0167],"type":"Point"}
}