{
  "id": 2169765,
  "type": "Feature",
  "properties": {
    "tgn:hierarchy":[
        "tgn:2169765",
        "tgn:1000001",
        "tgn:7012149",
        "tgn:1002999",
        "tgn:7007526",
        "tgn:7029392"
    ],
    "tgn:id":2169765,
    "tgn:name":"Big Mouth Mine",
    "tgn:placetype":[
        "aat:300000390"
    ]
},
  "bbox": [],
  "geometry": {"coordinates":[-119.4167,39.7667],"type":"Point"}
}