{
  "id": 7134857,
  "type": "Feature",
  "properties": {
    "tgn:hierarchy":[
        "tgn:7134857",
        "tgn:7003669",
        "tgn:1000003",
        "tgn:7000084",
        "tgn:7029392"
    ],
    "tgn:id":7134857,
    "tgn:name":"M\u00f6nchs Wald",
    "tgn:placetype":[
        "aat:300008863"
    ]
},
  "bbox": [],
  "geometry": {"coordinates":[10.85,50.216667],"type":"Point"}
}