{
  "id": 2241510,
  "type": "Feature",
  "properties": {
    "tgn:hierarchy":[
        "tgn:2241510",
        "tgn:1000001",
        "tgn:7012149",
        "tgn:1002521",
        "tgn:7007920",
        "tgn:7029392"
    ],
    "tgn:id":2241510,
    "tgn:name":"Clark, Mount",
    "tgn:placetype":[
        "aat:300008798"
    ]
},
  "bbox": [],
  "geometry": {"coordinates":[-123.2167,47.8333],"type":"Point"}
}