{
  "id": 7235972,
  "type": "Feature",
  "properties": {
    "tgn:hierarchy":[
        "tgn:7235972",
        "tgn:7002690",
        "tgn:7012056",
        "tgn:1000003",
        "tgn:1000074",
        "tgn:7029392"
    ],
    "tgn:id":7235972,
    "tgn:name":"Apo\u1e2fnion",
    "tgn:placetype":[
        "aat:300008347"
    ]
},
  "bbox": [],
  "geometry": {"coordinates":[25.116667,35.05],"type":"Point"}
}