{
  "id": 2772650,
  "type": "Feature",
  "properties": {
    "tgn:hierarchy":[
        "tgn:2772650",
        "tgn:1000001",
        "tgn:7012149",
        "tgn:7007524",
        "tgn:7029392"
    ],
    "tgn:id":2772650,
    "tgn:name":"Williams Creek",
    "tgn:placetype":[
        "aat:300008706"
    ]
},
  "bbox": [],
  "geometry": {"coordinates":[-110.6333,47.35],"type":"Point"}
}