{
  "id": 7501167,
  "type": "Feature",
  "properties": {
    "tgn:hierarchy":[
        "tgn:7501167",
        "tgn:1000004",
        "tgn:7467799",
        "tgn:1000141",
        "tgn:7029392"
    ],
    "tgn:id":7501167,
    "tgn:name":"Fubao Qiao",
    "tgn:placetype":[
        "aat:300007836"
    ]
},
  "bbox": [],
  "geometry": {"coordinates":[120.403333,24.0425],"type":"Point"}
}