{
  "id": 2133541,
  "type": "Feature",
  "properties": {
    "tgn:hierarchy":[
        "tgn:2133541",
        "tgn:7006450",
        "tgn:1000001",
        "tgn:7012149",
        "tgn:2000085",
        "tgn:7029392"
    ],
    "tgn:id":2133541,
    "tgn:name":"Andrew Lake",
    "tgn:placetype":[
        "aat:300008680"
    ]
},
  "bbox": [],
  "geometry": {"coordinates":[-141.9333,62.9333],"type":"Point"}
}