{
  "id": 7357962,
  "type": "Feature",
  "properties": {
    "tgn:hierarchy":[
        "tgn:7357962",
        "tgn:7005581",
        "tgn:1000001",
        "tgn:7005560",
        "tgn:7029392"
    ],
    "tgn:id":7357962,
    "tgn:name":"Colonia Enr\u00edquez",
    "tgn:placetype":[
        "aat:300008347"
    ]
},
  "bbox": [],
  "geometry": {"coordinates":[-107.95,30.483333],"type":"Point"}
}