{
  "id": 7173229,
  "type": "Feature",
  "properties": {
    "tgn:hierarchy":[
        "tgn:7173229",
        "tgn:1000003",
        "tgn:7003678",
        "tgn:7000084",
        "tgn:7029392"
    ],
    "tgn:id":7173229,
    "tgn:name":"Gro\u00dfer S\u00fcttels-Berg",
    "tgn:placetype":[
        "aat:300008777"
    ]
},
  "bbox": [],
  "geometry": {"coordinates":[9.633333,51.166667],"type":"Point"}
}