<<<<<<< HEAD
{
  "id": 7487726,
  "type": "Feature",
  "properties": {
    "tgn:hierarchy":[
        "tgn:7487726",
        "tgn:1000004",
        "tgn:7489179",
        "tgn:1000141",
        "tgn:7029392"
    ],
    "tgn:id":7487726,
    "tgn:name":"Hongchailin",
    "tgn:placetype":[
        "aat:300008347"
    ]
},
  "bbox": [],
  "geometry": {"coordinates":[121.677337,24.686553],"type":"Point"}
}
=======
{"geometry":{"type":"Point","coordinates":[121.677337,24.686553]},"type":"Feature","properties":{"hierarchy":["tgn:7487726","tgn:1000004","tgn:7489179","tgn:1000141","tgn:7029392"],"placetype":["aat:300008347"],"id":7487726,"name:xx":"Hongchailin"}}
>>>>>>> 03f74aca74312dbeaf24d7e61306dd6a786dc3d0
