{
  "id": 7491403,
  "type": "Feature",
  "properties": {
    "tgn:hierarchy":[
        "tgn:7491403",
        "tgn:7488858",
        "tgn:1000004",
        "tgn:1000141",
        "tgn:7029392"
    ],
    "tgn:id":7491403,
    "tgn:name":"Shuangliao",
    "tgn:placetype":[
        "aat:300008347"
    ]
},
  "bbox": [],
  "geometry": {"coordinates":[120.940841,23.980901],"type":"Point"}
}