{
  "id": 7405216,
  "type": "Feature",
  "properties": {
    "tgn:hierarchy":[
        "tgn:7405216",
        "tgn:7016644",
        "tgn:1000001",
        "tgn:7005560",
        "tgn:7029392"
    ],
    "tgn:id":7405216,
    "tgn:name":"La Tijera",
    "tgn:placetype":[
        "aat:300008347"
    ]
},
  "bbox": [],
  "geometry": {"coordinates":[-103.65,19.130556],"type":"Point"}
}