<<<<<<< HEAD
{
  "id": 2154868,
  "type": "Feature",
  "properties": {
    "tgn:hierarchy":[
        "tgn:2154868",
        "tgn:1000001",
        "tgn:7012149",
        "tgn:2001255",
        "tgn:7007523",
        "tgn:7029392"
    ],
    "tgn:id":2154868,
    "tgn:name":"Bear Hollow",
    "tgn:placetype":[
        "aat:300008761"
    ]
},
  "bbox": [],
  "geometry": {"coordinates":[-90.4667,36.95],"type":"Point"}
}
=======
{"geometry":{"type":"Point","coordinates":[-90.466700,36.950000]},"type":"Feature","properties":{"hierarchy":["tgn:2154868","tgn:1000001","tgn:7012149","tgn:2001255","tgn:7007523","tgn:7029392"],"placetype":["aat:300008761"],"id":2154868,"name:xx":"Bear Hollow"}}
>>>>>>> 03f74aca74312dbeaf24d7e61306dd6a786dc3d0
