{
  "id": 2580075,
  "type": "Feature",
  "properties": {
    "tgn:hierarchy":[
        "tgn:2580075",
        "tgn:1000001",
        "tgn:2000925",
        "tgn:7012149",
        "tgn:7007515",
        "tgn:7029392"
    ],
    "tgn:id":2580075,
    "tgn:name":"Pierce Cove",
    "tgn:placetype":[
        "aat:300132316"
    ]
},
  "bbox": [],
  "geometry": {"coordinates":[-69.6667,43.8333],"type":"Point"}
}