{
  "id": 7134205,
  "type": "Feature",
  "properties": {
    "tgn:hierarchy":[
        "tgn:7134205",
        "tgn:1000003",
        "tgn:7003677",
        "tgn:7000084",
        "tgn:7029392"
    ],
    "tgn:id":7134205,
    "tgn:name":"Nebelseifen",
    "tgn:placetype":[
        "aat:300000206"
    ]
},
  "bbox": [],
  "geometry": {"coordinates":[7.733333,50.966667],"type":"Point"}
}