{
  "id": 7336284,
  "type": "Feature",
  "properties": {
    "tgn:hierarchy":[
        "tgn:7336284",
        "tgn:7002807",
        "tgn:1000003",
        "tgn:7003837",
        "tgn:1000095",
        "tgn:7029392"
    ],
    "tgn:id":7336284,
    "tgn:name":"Fuentes de Le\u00f3n",
    "tgn:placetype":[
        "aat:300008347"
    ]
},
  "bbox": [],
  "geometry": {"coordinates":[-6.533333,38.066667],"type":"Point"}
}