{
  "id": 2471387,
  "type": "Feature",
  "properties": {
    "tgn:hierarchy":[
        "tgn:2471387",
        "tgn:1000001",
        "tgn:7019982",
        "tgn:7012149",
        "tgn:7007517",
        "tgn:7029392"
    ],
    "tgn:id":2471387,
    "tgn:name":"Lost Lake",
    "tgn:placetype":[
        "aat:300008680"
    ]
},
  "bbox": [],
  "geometry": {"coordinates":[-72.15,42.0833],"type":"Point"}
}