{
  "id": 7265708,
  "type": "Feature",
  "properties": {
    "tgn:hierarchy":[
        "tgn:7265708",
        "tgn:1000003",
        "tgn:7003635",
        "tgn:7016845",
        "tgn:7029392"
    ],
    "tgn:id":7265708,
    "tgn:name:nl":"Lage Springer",
    "tgn:placetype":[
        "aat:300132350"
    ]
},
  "bbox": [],
  "geometry": {"coordinates":[3.716667,51.383333],"type":"Point"}
}