{
  "id": 2565963,
  "type": "Feature",
  "properties": {
    "tgn:hierarchy":[
        "tgn:2565963",
        "tgn:1000001",
        "tgn:2002256",
        "tgn:7012149",
        "tgn:7013961",
        "tgn:7029392"
    ],
    "tgn:id":2565963,
    "tgn:name":"Palmer",
    "tgn:placetype":[
        "aat:300008347"
    ]
},
  "bbox": [],
  "geometry": {"coordinates":[-80.5833,38.65],"type":"Point"}
}