<<<<<<< HEAD
{
  "id": 2403796,
  "type": "Feature",
  "properties": {
    "tgn:hierarchy":[
        "tgn:2403796",
        "tgn:1000001",
        "tgn:7012149",
        "tgn:1002881",
        "tgn:7007240",
        "tgn:7029392"
    ],
    "tgn:id":2403796,
    "tgn:name":"Howard, Lake",
    "tgn:placetype":[
        "aat:300008680"
    ]
},
  "bbox": [],
  "geometry": {"coordinates":[-81.4,28.8],"type":"Point"}
}
=======
{"geometry":{"type":"Point","coordinates":[-81.400000,28.800000]},"type":"Feature","properties":{"hierarchy":["tgn:2403796","tgn:1000001","tgn:7012149","tgn:1002881","tgn:7007240","tgn:7029392"],"placetype":["aat:300008680"],"id":2403796,"name:xx":"Howard, Lake"}}
>>>>>>> 03f74aca74312dbeaf24d7e61306dd6a786dc3d0
