{
  "id": 2080363,
  "type": "Feature",
  "properties": {
    "tgn:hierarchy":[
        "tgn:2080363",
        "tgn:1000001",
        "tgn:7012149",
        "tgn:1002701",
        "tgn:7007706",
        "tgn:7029392"
    ],
    "tgn:id":2080363,
    "tgn:name":"Licking View",
    "tgn:placetype":[
        "aat:300008347"
    ]
},
  "bbox": [],
  "geometry": {"coordinates":[-82.0333,39.95],"type":"Point"}
}