{
  "id": 1014350,
  "type": "Feature",
  "properties": {
    "tgn:hierarchy":[
        "tgn:1014350",
        "tgn:7005685",
        "tgn:7005807",
        "tgn:1000001",
        "tgn:7005801",
        "tgn:7029392"
    ],
    "tgn:id":1014350,
    "tgn:name":"Winterton",
    "tgn:placetype":[
        "aat:300008347"
    ]
},
  "bbox": [],
  "geometry": {"coordinates":[-53.3333,47.9833],"type":"Point"}
}