{
  "id": 7480231,
  "type": "Feature",
  "properties": {
    "tgn:hierarchy":[
        "tgn:7480231",
        "tgn:1000004",
        "tgn:1000454",
        "tgn:1000141",
        "tgn:7029392"
    ],
    "tgn:id":7480231,
    "tgn:name":"Yushikeng",
    "tgn:placetype":[
        "aat:300008347"
    ]
},
  "bbox": [],
  "geometry": {"coordinates":[121.430861,25.101225],"type":"Point"}
}