{
  "id": 7023996,
  "type": "Feature",
  "properties": {
    "tgn:hierarchy":[
        "tgn:7023996",
        "tgn:7000606",
        "tgn:7001242",
        "tgn:1000172",
        "tgn:7029392"
    ],
    "tgn:id":7023996,
    "tgn:name":"Massah",
    "tgn:placetype":[
        "aat:300008347",
        "aat:300000810"
    ]
},
  "bbox": [],
  "geometry": {"coordinates":[21.6167,32.75],"type":"Point"}
}