{
  "id": 2648661,
  "type": "Feature",
  "properties": {
    "tgn:hierarchy":[
        "tgn:2648661",
        "tgn:1002201",
        "tgn:1000001",
        "tgn:7012149",
        "tgn:7007517",
        "tgn:7029392"
    ],
    "tgn:id":2648661,
    "tgn:name":"Sconticut Neck",
    "tgn:placetype":[
        "aat:300008850"
    ]
},
  "bbox": [],
  "geometry": {"coordinates":[-70.85,41.5833],"type":"Point"}
}