{
  "id": 2414318,
  "type": "Feature",
  "properties": {
    "tgn:hierarchy":[
        "tgn:2414318",
        "tgn:1000001",
        "tgn:7012149",
        "tgn:2000966",
        "tgn:7007520",
        "tgn:7029392"
    ],
    "tgn:id":2414318,
    "tgn:name":"Iron Range State Forest",
    "tgn:placetype":[
        "aat:300008863"
    ]
},
  "bbox": [],
  "geometry": {"coordinates":[-88.1833,46.0333],"type":"Point"}
}