{
  "id": 2623537,
  "type": "Feature",
  "properties": {
    "tgn:hierarchy":[
        "tgn:2623537",
        "tgn:2000456",
        "tgn:1000001",
        "tgn:7012149",
        "tgn:7007250",
        "tgn:7029392"
    ],
    "tgn:id":2623537,
    "tgn:name":"Rock Creek",
    "tgn:placetype":[
        "aat:300008706"
    ]
},
  "bbox": [],
  "geometry": {"coordinates":[-116.3667,47.1333],"type":"Point"}
}