{
  "id": 7283635,
  "type": "Feature",
  "properties": {
    "tgn:hierarchy":[
        "tgn:7283635",
        "tgn:1001692",
        "tgn:1000049",
        "tgn:1000002",
        "tgn:7029392"
    ],
    "tgn:id":7283635,
    "tgn:name":"Pantanos, Estero de los",
    "tgn:placetype":[
        "aat:300008699"
    ]
},
  "bbox": [],
  "geometry": {"coordinates":[-72.733333,-37.65],"type":"Point"}
}