{
  "id": 2662303,
  "type": "Feature",
  "properties": {
    "tgn:hierarchy":[
        "tgn:2662303",
        "tgn:1000001",
        "tgn:7012149",
        "tgn:2002111",
        "tgn:7007827",
        "tgn:7029392"
    ],
    "tgn:id":2662303,
    "tgn:name":"Sidney Valley",
    "tgn:placetype":[
        "aat:300386845"
    ]
},
  "bbox": [],
  "geometry": {"coordinates":[-112.7667,37.6833],"type":"Point"}
}