{
  "id": 2181236,
  "type": "Feature",
  "properties": {
    "tgn:hierarchy":[
        "tgn:2181236",
        "tgn:1000001",
        "tgn:7006451",
        "tgn:2000092",
        "tgn:7012149",
        "tgn:7029392"
    ],
    "tgn:id":2181236,
    "tgn:name":"Blue Cow Tank",
    "tgn:placetype":[
        "aat:300006191"
    ]
},
  "bbox": [],
  "geometry": {"coordinates":[-112.4833,35.3167],"type":"Point"}
}