{
  "id": 1082674,
  "type": "Feature",
  "properties": {
    "tgn:hierarchy":[
        "tgn:1082674",
        "tgn:7000317",
        "tgn:1000004",
        "tgn:1001907",
        "tgn:1000128",
        "tgn:7029392"
    ],
    "tgn:id":1082674,
    "tgn:name":"Bahau",
    "tgn:placetype":[
        "aat:300008347"
    ]
},
  "bbox": [],
  "geometry": {"coordinates":[102.4167,2.8167],"type":"Point"}
}