{
  "id": 2068192,
  "type": "Feature",
  "properties": {
    "tgn:hierarchy":[
        "tgn:2068192",
        "tgn:1000001",
        "tgn:7012149",
        "tgn:1002624",
        "tgn:7007568",
        "tgn:7029392"
    ],
    "tgn:id":2068192,
    "tgn:name":"Bridgeport",
    "tgn:placetype":[
        "aat:300008347"
    ]
},
  "bbox": [],
  "geometry": {"coordinates":[-75.9667,43.15],"type":"Point"}
}