{
  "id": 2605188,
  "type": "Feature",
  "properties": {
    "tgn:hierarchy":[
        "tgn:2605188",
        "tgn:1000001",
        "tgn:7012149",
        "tgn:1002418",
        "tgn:7007920",
        "tgn:7029392"
    ],
    "tgn:id":2605188,
    "tgn:name":"Raft River",
    "tgn:placetype":[
        "aat:300008707"
    ]
},
  "bbox": [],
  "geometry": {"coordinates":[-124.1833,47.4333],"type":"Point"}
}