{
  "id": 2315509,
  "type": "Feature",
  "properties": {
    "tgn:hierarchy":[
        "tgn:2315509",
        "tgn:1000001",
        "tgn:7012149",
        "tgn:2001289",
        "tgn:7007524",
        "tgn:7029392"
    ],
    "tgn:id":2315509,
    "tgn:name":"Ellis Canyon",
    "tgn:placetype":[
        "aat:300008761"
    ]
},
  "bbox": [],
  "geometry": {"coordinates":[-111.3333,46.7833],"type":"Point"}
}