{
  "id": 1093119,
  "type": "Feature",
  "properties": {
    "tgn:hierarchy":[
        "tgn:1093119",
        "tgn:7001242",
        "tgn:7016562",
        "tgn:1000193",
        "tgn:7029392"
    ],
    "tgn:id":1093119,
    "tgn:name":"Greenlands",
    "tgn:placetype":[
        "aat:300008347"
    ]
},
  "bbox": [],
  "geometry": {"coordinates":[27.6833,-27.1333],"type":"Point"}
}