{
  "id": 7365839,
  "type": "Feature",
  "properties": {
    "tgn:hierarchy":[
        "tgn:7365839",
        "tgn:7005578",
        "tgn:1000001",
        "tgn:7005560",
        "tgn:7029392"
    ],
    "tgn:id":7365839,
    "tgn:name":"Ensenada",
    "tgn:placetype":[
        "aat:300008347"
    ]
},
  "bbox": [],
  "geometry": {"coordinates":[-91.566667,18.733333],"type":"Point"}
}