{
  "id": 2136146,
  "type": "Feature",
  "properties": {
    "tgn:hierarchy":[
        "tgn:2136146",
        "tgn:1000001",
        "tgn:7012149",
        "tgn:2001255",
        "tgn:7007523",
        "tgn:7029392"
    ],
    "tgn:id":2136146,
    "tgn:name":"Arab",
    "tgn:placetype":[
        "aat:300008347"
    ]
},
  "bbox": [],
  "geometry": {"coordinates":[-90.1167,37.0667],"type":"Point"}
}