{
  "id": 2425779,
  "type": "Feature",
  "properties": {
    "tgn:hierarchy":[
        "tgn:2425779",
        "tgn:1000001",
        "tgn:7012149",
        "tgn:7007825",
        "tgn:7029392"
    ],
    "tgn:id":2425779,
    "tgn:name":"Joint Ridge",
    "tgn:placetype":[
        "aat:300266640"
    ]
},
  "bbox": [],
  "geometry": {"coordinates":[-83.65,35.6833],"type":"Point"}
}