{
  "id": 7552311,
  "type": "Feature",
  "properties": {
    "tgn:hierarchy":[
        "tgn:7552311",
        "tgn:1000004",
        "tgn:7000198",
        "tgn:7016883",
        "tgn:7029392"
    ],
    "tgn:id":7552311,
    "tgn:name:en":"Narot Mehra",
    "tgn:placetype":[
        "aat:300008347"
    ]
},
  "bbox": [],
  "geometry": {"coordinates":[75.56508,32.2673],"type":"Point"}
}