{
  "id": 2595844,
  "type": "Feature",
  "properties": {
    "tgn:hierarchy":[
        "tgn:2595844",
        "tgn:1000001",
        "tgn:7012149",
        "tgn:2002016",
        "tgn:7007826",
        "tgn:7029392"
    ],
    "tgn:id":2595844,
    "tgn:name":"Potrero Farias",
    "tgn:placetype":[
        "aat:300008798"
    ]
},
  "bbox": [],
  "geometry": {"coordinates":[-97.45,27.0167],"type":"Point"}
}