{
  "id": 1045468,
  "type": "Feature",
  "properties": {
    "tgn:hierarchy":[
        "tgn:1045468",
        "tgn:1000003",
        "tgn:7003141",
        "tgn:7003236",
        "tgn:1000080",
        "tgn:7029392"
    ],
    "tgn:id":1045468,
    "tgn:name":"Montalto Ligure",
    "tgn:placetype":[
        "aat:300008347"
    ]
},
  "bbox": [],
  "geometry": {"coordinates":[7.85,43.933333],"type":"Point"}
}