{
  "id": 7305145,
  "type": "Feature",
  "properties": {
    "tgn:hierarchy":[
        "tgn:7305145",
        "tgn:7008911",
        "tgn:1000003",
        "tgn:7002763",
        "tgn:1000095",
        "tgn:7029392"
    ],
    "tgn:id":7305145,
    "tgn:name":"Las Puentes",
    "tgn:placetype":[
        "aat:300008347"
    ]
},
  "bbox": [],
  "geometry": {"coordinates":[-5.766667,43.083333],"type":"Point"}
}