{
  "id": 2033969,
  "type": "Feature",
  "properties": {
    "tgn:hierarchy":[
        "tgn:2033969",
        "tgn:1000001",
        "tgn:7012149",
        "tgn:1002508",
        "tgn:7007252",
        "tgn:7029392"
    ],
    "tgn:id":2033969,
    "tgn:name":"Vallonia",
    "tgn:placetype":[
        "aat:300008347"
    ]
},
  "bbox": [],
  "geometry": {"coordinates":[-86.0833,38.8333],"type":"Point"}
}