{
  "id": 7150058,
  "type": "Feature",
  "properties": {
    "tgn:hierarchy":[
        "tgn:7150058",
        "tgn:7003669",
        "tgn:1000003",
        "tgn:7000084",
        "tgn:7029392"
    ],
    "tgn:id":7150058,
    "tgn:name":"Kr\u00f6nhof",
    "tgn:placetype":[
        "aat:300000206"
    ]
},
  "bbox": [],
  "geometry": {"coordinates":[11.383333,49.483333],"type":"Point"}
}