<<<<<<< HEAD
{
  "id": 2403783,
  "type": "Feature",
  "properties": {
    "tgn:hierarchy":[
        "tgn:2403783",
        "tgn:1000001",
        "tgn:7012149",
        "tgn:7007157",
        "tgn:1002566",
        "tgn:7029392"
    ],
    "tgn:id":2403783,
    "tgn:name":"Howard Springs",
    "tgn:placetype":[
        "aat:300008347"
    ]
},
  "bbox": [],
  "geometry": {"coordinates":[-122.6667,38.85],"type":"Point"}
}
=======
{"geometry":{"type":"Point","coordinates":[-122.666700,38.850000]},"type":"Feature","properties":{"hierarchy":["tgn:2403783","tgn:1000001","tgn:7012149","tgn:7007157","tgn:1002566","tgn:7029392"],"placetype":["aat:300008347"],"id":2403783,"name:xx":"Howard Springs"}}
>>>>>>> 03f74aca74312dbeaf24d7e61306dd6a786dc3d0
