{
  "id": 2517701,
  "type": "Feature",
  "properties": {
    "tgn:hierarchy":[
        "tgn:2517701",
        "tgn:1000001",
        "tgn:7012149",
        "tgn:2000906",
        "tgn:7007256",
        "tgn:7029392"
    ],
    "tgn:id":2517701,
    "tgn:name":"Mire Canal",
    "tgn:placetype":[
        "aat:300006075"
    ]
},
  "bbox": [],
  "geometry": {"coordinates":[-90.3333,30.3333],"type":"Point"}
}