{
  "id": 2250380,
  "type": "Feature",
  "properties": {
    "tgn:hierarchy":[
        "tgn:2250380",
        "tgn:1000001",
        "tgn:7012149",
        "tgn:2000878",
        "tgn:7007256",
        "tgn:7029392"
    ],
    "tgn:id":2250380,
    "tgn:name":"Colon Creek",
    "tgn:placetype":[
        "aat:300008706"
    ]
},
  "bbox": [],
  "geometry": {"coordinates":[-92.5667,32.4333],"type":"Point"}
}