{
  "id": 2109662,
  "type": "Feature",
  "properties": {
    "tgn:hierarchy":[
        "tgn:2109662",
        "tgn:1000001",
        "tgn:2002136",
        "tgn:7012149",
        "tgn:7007828",
        "tgn:7029392"
    ],
    "tgn:id":2109662,
    "tgn:name":"Goodrich Four Corners",
    "tgn:placetype":[
        "aat:300008347"
    ]
},
  "bbox": [],
  "geometry": {"coordinates":[-72.2667,43.75],"type":"Point"}
}