<<<<<<< HEAD
{
  "id": 2331022,
  "type": "Feature",
  "properties": {
    "tgn:hierarchy":[
        "tgn:2331022",
        "tgn:1000001",
        "tgn:7012149",
        "tgn:1002376",
        "tgn:7007252",
        "tgn:7029392"
    ],
    "tgn:id":2331022,
    "tgn:name":"Flat Run",
    "tgn:placetype":[
        "aat:300008699"
    ]
},
  "bbox": [],
  "geometry": {"coordinates":[-85.8333,38.3333],"type":"Point"}
}
=======
{"geometry":{"type":"Point","coordinates":[-85.833300,38.333300]},"type":"Feature","properties":{"hierarchy":["tgn:2331022","tgn:1000001","tgn:7012149","tgn:1002376","tgn:7007252","tgn:7029392"],"placetype":["aat:300008699"],"id":2331022,"name:xx":"Flat Run"}}
>>>>>>> 03f74aca74312dbeaf24d7e61306dd6a786dc3d0
