{
  "id": 2344843,
  "type": "Feature",
  "properties": {
    "tgn:hierarchy":[
        "tgn:2344843",
        "tgn:1000001",
        "tgn:7012149",
        "tgn:2000279",
        "tgn:7007240",
        "tgn:7029392"
    ],
    "tgn:id":2344843,
    "tgn:name":"Garden Pond",
    "tgn:placetype":[
        "aat:300008680"
    ]
},
  "bbox": [],
  "geometry": {"coordinates":[-83.4167,30.5667],"type":"Point"}
}