{
  "id": 2464495,
  "type": "Feature",
  "properties": {
    "tgn:hierarchy":[
        "tgn:2464495",
        "tgn:1000001",
        "tgn:7012149",
        "tgn:7007827",
        "tgn:7029392"
    ],
    "tgn:id":2464495,
    "tgn:name":"Log Cabin Ridge",
    "tgn:placetype":[
        "aat:300266640"
    ]
},
  "bbox": [],
  "geometry": {"coordinates":[-111.4667,41.8167],"type":"Point"}
}