{
  "id": 7107717,
  "type": "Feature",
  "properties": {
    "tgn:hierarchy":[
        "tgn:7107717",
        "tgn:1000003",
        "tgn:7000094",
        "tgn:7000084",
        "tgn:7029392"
    ],
    "tgn:id":7107717,
    "tgn:name":"Prohner Wiek",
    "tgn:placetype":[
        "aat:300132316"
    ]
},
  "bbox": [],
  "geometry": {"coordinates":[13.05,54.383333],"type":"Point"}
}