<<<<<<< HEAD
{
  "id": 2331325,
  "type": "Feature",
  "properties": {
    "tgn:hierarchy":[
        "tgn:2331325",
        "tgn:1000001",
        "tgn:7012149",
        "tgn:1002518",
        "tgn:7007568",
        "tgn:7029392"
    ],
    "tgn:id":2331325,
    "tgn:name":"Flatiron Island",
    "tgn:placetype":[
        "aat:300008791"
    ]
},
  "bbox": [],
  "geometry": {"coordinates":[-76.0333,44.3167],"type":"Point"}
}
=======
{"geometry":{"type":"Point","coordinates":[-76.033300,44.316700]},"type":"Feature","properties":{"hierarchy":["tgn:2331325","tgn:1000001","tgn:7012149","tgn:1002518","tgn:7007568","tgn:7029392"],"placetype":["aat:300008791"],"id":2331325,"name:xx":"Flatiron Island"}}
>>>>>>> 03f74aca74312dbeaf24d7e61306dd6a786dc3d0
