{
  "id": 2524759,
  "type": "Feature",
  "properties": {
    "tgn:hierarchy":[
        "tgn:2524759",
        "tgn:1000001",
        "tgn:7012149",
        "tgn:2002384",
        "tgn:7007923",
        "tgn:7029392"
    ],
    "tgn:id":2524759,
    "tgn:name":"Morning Glory Pool",
    "tgn:placetype":[
        "aat:300008680"
    ]
},
  "bbox": [],
  "geometry": {"coordinates":[-110.8333,44.4667],"type":"Point"}
}