<<<<<<< HEAD
{
  "id": 7022962,
  "type": "Feature",
  "properties": {
    "tgn:hierarchy":[
        "tgn:7022962",
        "tgn:1000001",
        "tgn:7012149",
        "tgn:7007159",
        "tgn:7029392"
    ],
    "tgn:id":7022962,
    "tgn:name":"Folly Brook",
    "tgn:placetype":[
        "aat:300008699"
    ]
},
  "bbox": [],
  "geometry": {"coordinates":[-72.5167,41.75],"type":"Point"}
}
=======
{"geometry":{"type":"Point","coordinates":[-72.516700,41.750000]},"type":"Feature","properties":{"hierarchy":["tgn:7022962","tgn:1000001","tgn:7012149","tgn:7007159","tgn:7029392"],"placetype":["aat:300008699"],"id":7022962,"name:xx":"Folly Brook"}}
>>>>>>> 03f74aca74312dbeaf24d7e61306dd6a786dc3d0
