{
  "id": 7225856,
  "type": "Feature",
  "properties": {
    "tgn:hierarchy":[
        "tgn:7225856",
        "tgn:7002681",
        "tgn:7001395",
        "tgn:1000003",
        "tgn:1000074",
        "tgn:7029392"
    ],
    "tgn:id":7225856,
    "tgn:name":"Ps\u00e1thas, \u00c1kra",
    "tgn:placetype":[
        "aat:300008850"
    ]
},
  "bbox": [],
  "geometry": {"coordinates":[23.166667,38.133333],"type":"Point"}
}