{
  "id": 1078006,
  "type": "Feature",
  "properties": {
    "tgn:hierarchy":[
        "tgn:1078006",
        "tgn:7016479",
        "tgn:1000004",
        "tgn:1000116",
        "tgn:7029392"
    ],
    "tgn:id":1078006,
    "tgn:name":"Lhokseumawe",
    "tgn:placetype":[
        "aat:300008347"
    ]
},
  "bbox": [],
  "geometry": {"coordinates":[97.15,5.15],"type":"Point"}
}