{
  "id": 2039407,
  "type": "Feature",
  "properties": {
    "tgn:hierarchy":[
        "tgn:2039407",
        "tgn:1000001",
        "tgn:7012149",
        "tgn:1002458",
        "tgn:7007255",
        "tgn:7029392"
    ],
    "tgn:id":2039407,
    "tgn:name":"Hinton",
    "tgn:placetype":[
        "aat:300008347"
    ]
},
  "bbox": [],
  "geometry": {"coordinates":[-84.5167,38.45],"type":"Point"}
}