<<<<<<< HEAD
{
  "id": 7176157,
  "type": "Feature",
  "properties": {
    "tgn:hierarchy":[
        "tgn:7176157",
        "tgn:1000003",
        "tgn:7003676",
        "tgn:7000084",
        "tgn:7029392"
    ],
    "tgn:id":7176157,
    "tgn:name":"Gro\u00df Ellershausen",
    "tgn:placetype":[
        "aat:300008347"
    ]
},
  "bbox": [],
  "geometry": {"coordinates":[9.866667,51.516667],"type":"Point"}
}
=======
{"geometry":{"type":"Point","coordinates":[9.866667,51.516667]},"type":"Feature","properties":{"hierarchy":["tgn:7176157","tgn:1000003","tgn:7003676","tgn:7000084","tgn:7029392"],"placetype":["aat:300008347"],"id":7176157,"name:xx":"Gro\u00df Ellershausen"}}
>>>>>>> 03f74aca74312dbeaf24d7e61306dd6a786dc3d0
