{
  "id": 2157309,
  "type": "Feature",
  "properties": {
    "tgn:hierarchy":[
        "tgn:2157309",
        "tgn:1000001",
        "tgn:7012149",
        "tgn:7007520",
        "tgn:7029392"
    ],
    "tgn:id":2157309,
    "tgn:name":"Beaver Creek",
    "tgn:placetype":[
        "aat:300008706"
    ]
},
  "bbox": [],
  "geometry": {"coordinates":[-86.1667,43.7167],"type":"Point"}
}