<<<<<<< HEAD
{
  "id": 2157309,
  "type": "Feature",
  "properties": {
    "tgn:hierarchy":[
        "tgn:2157309",
        "tgn:1000001",
        "tgn:7012149",
        "tgn:7007520",
        "tgn:7029392"
    ],
    "tgn:id":2157309,
    "tgn:name":"Beaver Creek",
    "tgn:placetype":[
        "aat:300008706"
    ]
},
  "bbox": [],
  "geometry": {"coordinates":[-86.1667,43.7167],"type":"Point"}
}
=======
{"geometry":{"type":"Point","coordinates":[-86.166700,43.716700]},"type":"Feature","properties":{"hierarchy":["tgn:2157309","tgn:1000001","tgn:7012149","tgn:7007520","tgn:7029392"],"placetype":["aat:300008706"],"id":2157309,"name:xx":"Beaver Creek"}}
>>>>>>> 03f74aca74312dbeaf24d7e61306dd6a786dc3d0
