{
  "id": 2786236,
  "type": "Feature",
  "properties": {
    "tgn:hierarchy":[
        "tgn:2786236",
        "tgn:1000001",
        "tgn:7006451",
        "tgn:2000092",
        "tgn:7012149",
        "tgn:7029392"
    ],
    "tgn:id":2786236,
    "tgn:name":"Youngs Canyon Tank",
    "tgn:placetype":[
        "aat:300006191"
    ]
},
  "bbox": [],
  "geometry": {"coordinates":[-111.3833,35.15],"type":"Point"}
}