{
  "id": 2174190,
  "type": "Feature",
  "properties": {
    "tgn:hierarchy":[
        "tgn:2174190",
        "tgn:1000001",
        "tgn:7012149",
        "tgn:2001753",
        "tgn:7007712",
        "tgn:7029392"
    ],
    "tgn:id":2174190,
    "tgn:name":"Birdtown",
    "tgn:placetype":[
        "aat:300008347"
    ]
},
  "bbox": [],
  "geometry": {"coordinates":[-80.4333,34.6167],"type":"Point"}
}