{
  "id": 2526357,
  "type": "Feature",
  "properties": {
    "tgn:hierarchy":[
        "tgn:2526357",
        "tgn:1000001",
        "tgn:7012149",
        "tgn:7007709",
        "tgn:7029392"
    ],
    "tgn:id":2526357,
    "tgn:name":"Moss Knob",
    "tgn:placetype":[
        "aat:300008798"
    ]
},
  "bbox": [],
  "geometry": {"coordinates":[-83.2167,35.2333],"type":"Point"}
}