<<<<<<< HEAD
{
  "id": 7481513,
  "type": "Feature",
  "properties": {
    "tgn:hierarchy":[
        "tgn:7481513",
        "tgn:1000004",
        "tgn:7001009",
        "tgn:1000141",
        "tgn:7029392"
    ],
    "tgn:id":7481513,
    "tgn:name":"Fuwan Shan Xifeng",
    "tgn:placetype":[
        "aat:300008798"
    ]
},
  "bbox": [],
  "geometry": {"coordinates":[121.145833,24.342222],"type":"Point"}
}
=======
{"geometry":{"type":"Point","coordinates":[121.145833,24.342222]},"type":"Feature","properties":{"hierarchy":["tgn:7481513","tgn:1000004","tgn:7001009","tgn:1000141","tgn:7029392"],"placetype":["aat:300008798"],"id":7481513,"name:xx":"Fuwan Shan Xifeng"}}
>>>>>>> 03f74aca74312dbeaf24d7e61306dd6a786dc3d0
