{
  "id": 7194253,
  "type": "Feature",
  "properties": {
    "tgn:hierarchy":[
        "tgn:7194253",
        "tgn:1000003",
        "tgn:7003676",
        "tgn:7000084",
        "tgn:7029392"
    ],
    "tgn:id":7194253,
    "tgn:name":"D\u00f6hrel",
    "tgn:placetype":[
        "aat:300008347"
    ]
},
  "bbox": [],
  "geometry": {"coordinates":[8.883333,52.683333],"type":"Point"}
}