{
  "id": 7081595,
  "type": "Feature",
  "properties": {
    "tgn:hierarchy":[
        "tgn:7081595",
        "tgn:1000003",
        "tgn:7003689",
        "tgn:7000084",
        "tgn:7029392"
    ],
    "tgn:id":7081595,
    "tgn:name":"W\u00fcstung Ottenhausen",
    "tgn:placetype":[
        "aat:300055621"
    ]
},
  "bbox": [],
  "geometry": {"coordinates":[10.266667,50.533333],"type":"Point"}
}