{
  "id": 2150593,
  "type": "Feature",
  "properties": {
    "tgn:hierarchy":[
        "tgn:2150593",
        "tgn:1000001",
        "tgn:1002480",
        "tgn:7012149",
        "tgn:7007564",
        "tgn:7029392"
    ],
    "tgn:id":2150593,
    "tgn:name":"Basin, The",
    "tgn:placetype":[
        "aat:300132316"
    ]
},
  "bbox": [],
  "geometry": {"coordinates":[-71.3833,42.95],"type":"Point"}
}