<<<<<<< HEAD
{
  "id": 2150364,
  "type": "Feature",
  "properties": {
    "tgn:hierarchy":[
        "tgn:2150364",
        "tgn:1000001",
        "tgn:7012149",
        "tgn:7007157",
        "tgn:1002957",
        "tgn:7029392"
    ],
    "tgn:id":2150364,
    "tgn:name":"Basin Creek",
    "tgn:placetype":[
        "aat:300008706"
    ]
},
  "bbox": [],
  "geometry": {"coordinates":[-120.0667,38.3167],"type":"Point"}
}
=======
{"geometry":{"type":"Point","coordinates":[-120.066700,38.316700]},"type":"Feature","properties":{"hierarchy":["tgn:2150364","tgn:1000001","tgn:7012149","tgn:7007157","tgn:1002957","tgn:7029392"],"placetype":["aat:300008706"],"id":2150364,"name:xx":"Basin Creek"}}
>>>>>>> 03f74aca74312dbeaf24d7e61306dd6a786dc3d0
