{
  "id": 7322925,
  "type": "Feature",
  "properties": {
    "tgn:hierarchy":[
        "tgn:7322925",
        "tgn:7008912",
        "tgn:7030216",
        "tgn:1000003",
        "tgn:1000095",
        "tgn:7029392"
    ],
    "tgn:id":7322925,
    "tgn:name":"Salada, Riera",
    "tgn:placetype":[
        "aat:300008699"
    ]
},
  "bbox": [],
  "geometry": {"coordinates":[1.282048,42.011587],"type":"Point"}
}