{
  "id": 7166172,
  "type": "Feature",
  "properties": {
    "tgn:hierarchy":[
        "tgn:7166172",
        "tgn:1000003",
        "tgn:7003676",
        "tgn:7000084",
        "tgn:7029392"
    ],
    "tgn:id":7166172,
    "tgn:name":"Heidelbeerk\u00f6pfe",
    "tgn:placetype":[
        "aat:300008795"
    ]
},
  "bbox": [],
  "geometry": {"coordinates":[10.333333,51.766667],"type":"Point"}
}