{
  "id": 1059339,
  "type": "Feature",
  "properties": {
    "tgn:hierarchy":[
        "tgn:1059339",
        "tgn:1000004",
        "tgn:1003399",
        "tgn:7018214",
        "tgn:7002435",
        "tgn:7029392"
    ],
    "tgn:id":1059339,
    "tgn:name":"Serdobsk",
    "tgn:placetype":[
        "aat:300008347"
    ]
},
  "bbox": [],
  "geometry": {"coordinates":[44.2167,52.4667],"type":"Point"}
}