{
  "id": 2241861,
  "type": "Feature",
  "properties": {
    "tgn:hierarchy":[
        "tgn:2241861",
        "tgn:1000001",
        "tgn:7012149",
        "tgn:7007522",
        "tgn:7029392"
    ],
    "tgn:id":2241861,
    "tgn:name":"Clausel Creek",
    "tgn:placetype":[
        "aat:300008706"
    ]
},
  "bbox": [],
  "geometry": {"coordinates":[-88.3833,34.7167],"type":"Point"}
}