{
  "id": 7128666,
  "type": "Feature",
  "properties": {
    "tgn:hierarchy":[
        "tgn:7128666",
        "tgn:7000096",
        "tgn:1000003",
        "tgn:7000084",
        "tgn:7029392"
    ],
    "tgn:id":7128666,
    "tgn:name":"Notte-Kanal",
    "tgn:placetype":[
        "aat:300006075"
    ]
},
  "bbox": [],
  "geometry": {"coordinates":[13.416667,52.183333],"type":"Point"}
}