{
  "id": 2510368,
  "type": "Feature",
  "properties": {
    "tgn:hierarchy":[
        "tgn:2510368",
        "tgn:1000001",
        "tgn:1002185",
        "tgn:7012149",
        "tgn:7007710",
        "tgn:7029392"
    ],
    "tgn:id":2510368,
    "tgn:name":"Middle Run",
    "tgn:placetype":[
        "aat:300008699"
    ]
},
  "bbox": [],
  "geometry": {"coordinates":[-78.3167,40.2667],"type":"Point"}
}