{
  "id": 2511479,
  "type": "Feature",
  "properties": {
    "tgn:hierarchy":[
        "tgn:2511479",
        "tgn:1000001",
        "tgn:2001744",
        "tgn:7012149",
        "tgn:7007712",
        "tgn:7029392"
    ],
    "tgn:id":2511479,
    "tgn:name":"Mile Branch",
    "tgn:placetype":[
        "aat:300008699"
    ]
},
  "bbox": [],
  "geometry": {"coordinates":[-81.2833,34.25],"type":"Point"}
}