{
  "id": 2410028,
  "type": "Feature",
  "properties": {
    "tgn:hierarchy":[
        "tgn:2410028",
        "tgn:1000001",
        "tgn:7012149",
        "tgn:1002518",
        "tgn:7007568",
        "tgn:7029392"
    ],
    "tgn:id":2410028,
    "tgn:name":"Ina Island",
    "tgn:placetype":[
        "aat:300008791"
    ]
},
  "bbox": [],
  "geometry": {"coordinates":[-75.8833,44.3667],"type":"Point"}
}