{
  "id": 2052616,
  "type": "Feature",
  "properties": {
    "tgn:hierarchy":[
        "tgn:2052616",
        "tgn:1000001",
        "tgn:2000955",
        "tgn:7012149",
        "tgn:7007520",
        "tgn:7029392"
    ],
    "tgn:id":2052616,
    "tgn:name":"Maywood",
    "tgn:placetype":[
        "aat:300008347"
    ]
},
  "bbox": [],
  "geometry": {"coordinates":[-86.9833,45.8333],"type":"Point"}
}