<<<<<<< HEAD
{
  "id": 7475212,
  "type": "Feature",
  "properties": {
    "tgn:hierarchy":[
        "tgn:7475212",
        "tgn:7001004",
        "tgn:1000004",
        "tgn:1000141",
        "tgn:7029392"
    ],
    "tgn:id":7475212,
    "tgn:name":"Weizhuangtou",
    "tgn:placetype":[
        "aat:300008347"
    ]
},
  "bbox": [],
  "geometry": {"coordinates":[120.5233,22.9745],"type":"Point"}
}
=======
{"geometry":{"type":"Point","coordinates":[120.523300,22.974500]},"type":"Feature","properties":{"hierarchy":["tgn:7475212","tgn:7001004","tgn:1000004","tgn:1000141","tgn:7029392"],"placetype":["aat:300008347"],"id":7475212,"name:xx":"Weizhuangtou"}}
>>>>>>> 03f74aca74312dbeaf24d7e61306dd6a786dc3d0
