{
  "id": 2225554,
  "type": "Feature",
  "properties": {
    "tgn:hierarchy":[
        "tgn:2225554",
        "tgn:1000001",
        "tgn:2001174",
        "tgn:7012149",
        "tgn:7007523",
        "tgn:7029392"
    ],
    "tgn:id":2225554,
    "tgn:name":"Castor",
    "tgn:placetype":[
        "aat:300008347"
    ]
},
  "bbox": [],
  "geometry": {"coordinates":[-89.9667,37.0667],"type":"Point"}
}