<<<<<<< HEAD
{
  "id": 7050442,
  "type": "Feature",
  "properties": {
    "tgn:hierarchy":[
        "tgn:7050442",
        "tgn:7003138",
        "tgn:1000003",
        "tgn:7003080",
        "tgn:1000080",
        "tgn:7029392"
    ],
    "tgn:id":7050442,
    "tgn:name":"Mastaccio, Monte",
    "tgn:placetype":[
        "aat:300008777"
    ]
},
  "bbox": [],
  "geometry": {"coordinates":[12.3,41.916667],"type":"Point"}
}
=======
{"geometry":{"type":"Point","coordinates":[12.300000,41.916667]},"type":"Feature","properties":{"hierarchy":["tgn:7050442","tgn:7003138","tgn:1000003","tgn:7003080","tgn:1000080","tgn:7029392"],"placetype":["aat:300008777"],"id":7050442,"name:xx":"Mastaccio, Monte"}}
>>>>>>> 03f74aca74312dbeaf24d7e61306dd6a786dc3d0
