{
  "id": 7443318,
  "type": "Feature",
  "properties": {
    "tgn:hierarchy":[
        "tgn:7443318",
        "tgn:7002445",
        "tgn:1000003",
        "tgn:7008153",
        "tgn:7008591",
        "tgn:7029392"
    ],
    "tgn:id":7443318,
    "tgn:name:en":"Dumpton Point",
    "tgn:placetype":[
        "aat:300386846"
    ]
},
  "bbox": [],
  "geometry": {"coordinates":[1.443333,51.35],"type":"Point"}
}