{
  "id": 7169032,
  "type": "Feature",
  "properties": {
    "tgn:hierarchy":[
        "tgn:7169032",
        "tgn:7003669",
        "tgn:1000003",
        "tgn:7000084",
        "tgn:7029392"
    ],
    "tgn:id":7169032,
    "tgn:name":"Harmating",
    "tgn:placetype":[
        "aat:300008347"
    ]
},
  "bbox": [],
  "geometry": {"coordinates":[11.55,47.883333],"type":"Point"}
}