{
  "id": 2145851,
  "type": "Feature",
  "properties": {
    "tgn:hierarchy":[
        "tgn:2145851",
        "tgn:1000001",
        "tgn:7012149",
        "tgn:7007157",
        "tgn:1002706",
        "tgn:7029392"
    ],
    "tgn:id":2145851,
    "tgn:name":"Bale Slough",
    "tgn:placetype":[
        "aat:300008699"
    ]
},
  "bbox": [],
  "geometry": {"coordinates":[-122.45,38.45],"type":"Point"}
}