{
  "id": 7334456,
  "type": "Feature",
  "properties": {
    "tgn:hierarchy":[
        "tgn:7334456",
        "tgn:7002758",
        "tgn:1001316",
        "tgn:1000003",
        "tgn:1000095",
        "tgn:7029392"
    ],
    "tgn:id":7334456,
    "tgn:name":"El Palomar",
    "tgn:placetype":[
        "aat:300008347"
    ]
},
  "bbox": [],
  "geometry": {"coordinates":[-2.966667,37.95],"type":"Point"}
}