{
  "id": 2226867,
  "type": "Feature",
  "properties": {
    "tgn:hierarchy":[
        "tgn:2226867",
        "tgn:1000001",
        "tgn:7012149",
        "tgn:2000214",
        "tgn:7007158",
        "tgn:7029392"
    ],
    "tgn:id":2226867,
    "tgn:name":"Caughman Ditch",
    "tgn:placetype":[
        "aat:300006075"
    ]
},
  "bbox": [],
  "geometry": {"coordinates":[-108.3833,39.4333],"type":"Point"}
}