{
  "id": 2417342,
  "type": "Feature",
  "properties": {
    "tgn:hierarchy":[
        "tgn:2417342",
        "tgn:2000766",
        "tgn:1000001",
        "tgn:7012149",
        "tgn:7007255",
        "tgn:7029392"
    ],
    "tgn:id":2417342,
    "tgn:name":"Jacks Hollowk Branch",
    "tgn:placetype":[
        "aat:300008699"
    ]
},
  "bbox": [],
  "geometry": {"coordinates":[-86.15,36.7167],"type":"Point"}
}