{
  "id": 7115081,
  "type": "Feature",
  "properties": {
    "tgn:hierarchy":[
        "tgn:7115081",
        "tgn:1000003",
        "tgn:7003688",
        "tgn:7000084",
        "tgn:7029392"
    ],
    "tgn:id":7115081,
    "tgn:name":"Oldersbek",
    "tgn:placetype":[
        "aat:300008347"
    ]
},
  "bbox": [],
  "geometry": {"coordinates":[9.166667,54.45],"type":"Point"}
}