<<<<<<< HEAD
{
  "id": 7115869,
  "type": "Feature",
  "properties": {
    "tgn:hierarchy":[
        "tgn:7115869",
        "tgn:1000003",
        "tgn:7003688",
        "tgn:7000084",
        "tgn:7029392"
    ],
    "tgn:id":7115869,
    "tgn:name":"Owschlag",
    "tgn:placetype":[
        "aat:300008347"
    ]
},
  "bbox": [],
  "geometry": {"coordinates":[9.6,54.383333],"type":"Point"}
}
=======
{"geometry":{"type":"Point","coordinates":[9.600000,54.383333]},"type":"Feature","properties":{"hierarchy":["tgn:7115869","tgn:1000003","tgn:7003688","tgn:7000084","tgn:7029392"],"placetype":["aat:300008347"],"id":7115869,"name:xx":"Owschlag"}}
>>>>>>> 03f74aca74312dbeaf24d7e61306dd6a786dc3d0
