{
  "id": 7281502,
  "type": "Feature",
  "properties": {
    "tgn:hierarchy":[
        "tgn:7281502",
        "tgn:1001702",
        "tgn:1000049",
        "tgn:1000002",
        "tgn:7029392"
    ],
    "tgn:id":7281502,
    "tgn:name":"Secci\u00f3n El Zurdo",
    "tgn:placetype":[
        "aat:300000241"
    ]
},
  "bbox": [],
  "geometry": {"coordinates":[-71.233333,-52.05],"type":"Point"}
}