{
  "id": 2390318,
  "type": "Feature",
  "properties": {
    "tgn:hierarchy":[
        "tgn:2390318",
        "tgn:1000001",
        "tgn:7012149",
        "tgn:7007157",
        "tgn:1003046",
        "tgn:7029392"
    ],
    "tgn:id":2390318,
    "tgn:name":"Highland Canal",
    "tgn:placetype":[
        "aat:300006075"
    ]
},
  "bbox": [],
  "geometry": {"coordinates":[-121.9833,38.5333],"type":"Point"}
}