{
  "id": 2060269,
  "type": "Feature",
  "properties": {
    "tgn:hierarchy":[
        "tgn:2060269",
        "tgn:1000001",
        "tgn:2001178",
        "tgn:7012149",
        "tgn:7007523",
        "tgn:7029392"
    ],
    "tgn:id":2060269,
    "tgn:name":"Roach",
    "tgn:placetype":[
        "aat:300008347"
    ]
},
  "bbox": [],
  "geometry": {"coordinates":[-92.8333,37.9833],"type":"Point"}
}