{
  "id": 2386959,
  "type": "Feature",
  "properties": {
    "tgn:hierarchy":[
        "tgn:2386959",
        "tgn:1000001",
        "tgn:1002328",
        "tgn:7012149",
        "tgn:7007568",
        "tgn:7029392"
    ],
    "tgn:id":2386959,
    "tgn:name":"Herrick Hollow",
    "tgn:placetype":[
        "aat:300008761"
    ]
},
  "bbox": [],
  "geometry": {"coordinates":[-75.2333,42.25],"type":"Point"}
}