<<<<<<< HEAD
{
  "id": 2253834,
  "type": "Feature",
  "properties": {
    "tgn:hierarchy":[
        "tgn:2253834",
        "tgn:1000001",
        "tgn:7012149",
        "tgn:2000347",
        "tgn:7007248",
        "tgn:7029392"
    ],
    "tgn:id":2253834,
    "tgn:name":"Cooks Lake",
    "tgn:placetype":[
        "aat:300006191"
    ]
},
  "bbox": [],
  "geometry": {"coordinates":[-84.5667,33.5],"type":"Point"}
}
=======
{"geometry":{"type":"Point","coordinates":[-84.566700,33.500000]},"type":"Feature","properties":{"hierarchy":["tgn:2253834","tgn:1000001","tgn:7012149","tgn:2000347","tgn:7007248","tgn:7029392"],"placetype":["aat:300006191"],"id":2253834,"name:xx":"Cooks Lake"}}
>>>>>>> 03f74aca74312dbeaf24d7e61306dd6a786dc3d0
