{
  "id": 2363982,
  "type": "Feature",
  "properties": {
    "tgn:hierarchy":[
        "tgn:2363982",
        "tgn:1000001",
        "tgn:2001181",
        "tgn:7012149",
        "tgn:7007523",
        "tgn:7029392"
    ],
    "tgn:id":2363982,
    "tgn:name":"Green Mountain",
    "tgn:placetype":[
        "aat:300008798"
    ]
},
  "bbox": [],
  "geometry": {"coordinates":[-91.1833,36.9167],"type":"Point"}
}