<<<<<<< HEAD
{
  "id": 7172219,
  "type": "Feature",
  "properties": {
    "tgn:hierarchy":[
        "tgn:7172219",
        "tgn:7003692",
        "tgn:1000003",
        "tgn:7000084",
        "tgn:7029392"
    ],
    "tgn:id":7172219,
    "tgn:name":"Hinteruhlberg",
    "tgn:placetype":[
        "aat:300008347"
    ]
},
  "bbox": [],
  "geometry": {"coordinates":[9.962222,49.055278],"type":"Point"}
}
=======
{"geometry":{"type":"Point","coordinates":[9.962222,49.055278]},"type":"Feature","properties":{"hierarchy":["tgn:7172219","tgn:7003692","tgn:1000003","tgn:7000084","tgn:7029392"],"placetype":["aat:300008347"],"id":7172219,"name:xx":"Hinteruhlberg"}}
>>>>>>> 03f74aca74312dbeaf24d7e61306dd6a786dc3d0
