{
  "id": 7094060,
  "type": "Feature",
  "properties": {
    "tgn:hierarchy":[
        "tgn:7094060",
        "tgn:7003692",
        "tgn:1000003",
        "tgn:7000084",
        "tgn:7029392"
    ],
    "tgn:id":7094060,
    "tgn:name":"Seeheimer-Berg",
    "tgn:placetype":[
        "aat:300008795"
    ]
},
  "bbox": [],
  "geometry": {"coordinates":[9.066667,48.333333],"type":"Point"}
}