{
  "id": 1139077,
  "type": "Feature",
  "properties": {
    "tgn:hierarchy":[
        "tgn:1139077",
        "tgn:1000004",
        "tgn:7002081",
        "tgn:1000111",
        "tgn:7029392"
    ],
    "tgn:id":1139077,
    "tgn:name":"Hengxi",
    "tgn:placetype":[
        "aat:300008347"
    ]
},
  "bbox": [],
  "geometry": {"coordinates":[118.7667,31.7167],"type":"Point"}
}