{
  "id": 7019428,
  "type": "Feature",
  "properties": {
    "tgn:hierarchy":[
        "tgn:7019428",
        "tgn:1000001",
        "tgn:2000924",
        "tgn:7012149",
        "tgn:7007515",
        "tgn:7029392"
    ],
    "tgn:id":7019428,
    "tgn:name":"Twobush Island",
    "tgn:placetype":[
        "aat:300008791"
    ]
},
  "bbox": [],
  "geometry": {"coordinates":[-69.3167,43.9167],"type":"Point"}
}