{
  "id": 2608176,
  "type": "Feature",
  "properties": {
    "tgn:hierarchy":[
        "tgn:2608176",
        "tgn:1000001",
        "tgn:7012149",
        "tgn:2001273",
        "tgn:7007524",
        "tgn:7029392"
    ],
    "tgn:id":2608176,
    "tgn:name":"Rattlesnake Butte",
    "tgn:placetype":[
        "aat:300008798"
    ]
},
  "bbox": [],
  "geometry": {"coordinates":[-108.9667,47.2667],"type":"Point"}
}