{
  "id": 2598813,
  "type": "Feature",
  "properties": {
    "tgn:hierarchy":[
        "tgn:2598813",
        "tgn:1000001",
        "tgn:7016172",
        "tgn:7012149",
        "tgn:2000167",
        "tgn:7029392"
    ],
    "tgn:id":2598813,
    "tgn:name":"Prillman Ridge",
    "tgn:placetype":[
        "aat:300266640"
    ]
},
  "bbox": [],
  "geometry": {"coordinates":[-92.7833,34.7333],"type":"Point"}
}