{
  "id": 7336709,
  "type": "Feature",
  "properties": {
    "tgn:hierarchy":[
        "tgn:7336709",
        "tgn:7002842",
        "tgn:7001158",
        "tgn:1000003",
        "tgn:1000095",
        "tgn:7029392"
    ],
    "tgn:id":7336709,
    "tgn:name":"Fuentelmonje",
    "tgn:placetype":[
        "aat:300008347"
    ]
},
  "bbox": [],
  "geometry": {"coordinates":[-2.183333,41.416667],"type":"Point"}
}