{
  "id": 2332702,
  "type": "Feature",
  "properties": {
    "tgn:hierarchy":[
        "tgn:2332702",
        "tgn:1000001",
        "tgn:7012149",
        "tgn:2000183",
        "tgn:7007157",
        "tgn:7029392"
    ],
    "tgn:id":2332702,
    "tgn:name":"Flower Lake",
    "tgn:placetype":[
        "aat:300008680"
    ]
},
  "bbox": [],
  "geometry": {"coordinates":[-118.35,36.7667],"type":"Point"}
}