{
  "id": 7455776,
  "type": "Feature",
  "properties": {
    "tgn:hierarchy":[
        "tgn:7455776",
        "tgn:7002443",
        "tgn:5000552",
        "tgn:1000003",
        "tgn:7008591",
        "tgn:7029392"
    ],
    "tgn:id":7455776,
    "tgn:name:en":"Clunderwen",
    "tgn:placetype":[
        "aat:300008347"
    ]
},
  "bbox": [],
  "geometry": {"coordinates":[-4.731667,51.840556],"type":"Point"}
}