{
  "id": 7489950,
  "type": "Feature",
  "properties": {
    "tgn:hierarchy":[
        "tgn:7489950",
        "tgn:1000004",
        "tgn:7492971",
        "tgn:1000141",
        "tgn:7029392"
    ],
    "tgn:id":7489950,
    "tgn:name":"Datan",
    "tgn:placetype":[
        "aat:300008347"
    ]
},
  "bbox": [],
  "geometry": {"coordinates":[120.493546,22.456044],"type":"Point"}
}