<<<<<<< HEAD
{
  "id": 7249678,
  "type": "Feature",
  "properties": {
    "tgn:hierarchy":[
        "tgn:7249678",
        "tgn:7003456",
        "tgn:1000003",
        "tgn:1000063",
        "tgn:7018236",
        "tgn:7029392"
    ],
    "tgn:id":7249678,
    "tgn:name":"Overbroek",
    "tgn:placetype":[
        "aat:300008347"
    ]
},
  "bbox": [],
  "geometry": {"coordinates":[4.606905,51.342519],"type":"Point"}
}
=======
{"geometry":{"type":"Point","coordinates":[4.606905,51.342519]},"type":"Feature","properties":{"hierarchy":["tgn:7249678","tgn:7003456","tgn:1000003","tgn:1000063","tgn:7018236","tgn:7029392"],"placetype":["aat:300008347"],"id":7249678,"name:xx":"Overbroek"}}
>>>>>>> 03f74aca74312dbeaf24d7e61306dd6a786dc3d0
