{
  "id": 1098718,
  "type": "Feature",
  "properties": {
    "tgn:hierarchy":[
        "tgn:1098718",
        "tgn:1007413",
        "tgn:7006215",
        "tgn:1000216",
        "tgn:1000006",
        "tgn:7029392"
    ],
    "tgn:id":1098718,
    "tgn:name":"Atuona",
    "tgn:placetype":[
        "aat:300008347"
    ]
},
  "bbox": [],
  "geometry": {"coordinates":[-139.05,-9.7833],"type":"Point"}
}