{
  "id": 2380375,
  "type": "Feature",
  "properties": {
    "tgn:hierarchy":[
        "tgn:2380375",
        "tgn:1000001",
        "tgn:7012149",
        "tgn:2001253",
        "tgn:7007523",
        "tgn:7029392"
    ],
    "tgn:id":2380375,
    "tgn:name":"Hattons Slough",
    "tgn:placetype":[
        "aat:300008699"
    ]
},
  "bbox": [],
  "geometry": {"coordinates":[-94.3833,37.8333],"type":"Point"}
}