{
  "id": 2690997,
  "type": "Feature",
  "properties": {
    "tgn:hierarchy":[
        "tgn:2690997",
        "tgn:1000001",
        "tgn:7012149",
        "tgn:2001255",
        "tgn:7007523",
        "tgn:7029392"
    ],
    "tgn:id":2690997,
    "tgn:name":"Stanley Creek",
    "tgn:placetype":[
        "aat:300008706"
    ]
},
  "bbox": [],
  "geometry": {"coordinates":[-90.2333,37.0167],"type":"Point"}
}