{
  "id": 7096018,
  "type": "Feature",
  "properties": {
    "tgn:hierarchy":[
        "tgn:7096018",
        "tgn:7000096",
        "tgn:1000003",
        "tgn:7000084",
        "tgn:7029392"
    ],
    "tgn:id":7096018,
    "tgn:name":"Schr\u00f6dershof",
    "tgn:placetype":[
        "aat:300000206"
    ]
},
  "bbox": [],
  "geometry": {"coordinates":[14.233333,52.233333],"type":"Point"}
}