{
  "id": 2606332,
  "type": "Feature",
  "properties": {
    "tgn:hierarchy":[
        "tgn:2606332",
        "tgn:1000001",
        "tgn:7012149",
        "tgn:7007157",
        "tgn:7014516",
        "tgn:7029392"
    ],
    "tgn:id":2606332,
    "tgn:name":"Ralphine, Lake",
    "tgn:placetype":[
        "aat:300006191"
    ]
},
  "bbox": [],
  "geometry": {"coordinates":[-122.6667,38.45],"type":"Point"}
}