{
  "id": 1135780,
  "type": "Feature",
  "properties": {
    "tgn:hierarchy":[
        "tgn:1135780",
        "tgn:1000004",
        "tgn:7000190",
        "tgn:1000105",
        "tgn:7029392"
    ],
    "tgn:id":1135780,
    "tgn:name":"Koyra",
    "tgn:placetype":[
        "aat:300387055"
    ]
},
  "bbox": [],
  "geometry": {"coordinates":[89.2667,22.45],"type":"Point"}
}