{
  "id": 2076550,
  "type": "Feature",
  "properties": {
    "tgn:hierarchy":[
        "tgn:2076550",
        "tgn:1000001",
        "tgn:7012149",
        "tgn:2001523",
        "tgn:7007709",
        "tgn:7029392"
    ],
    "tgn:id":2076550,
    "tgn:name":"Scotts Hill",
    "tgn:placetype":[
        "aat:300008347"
    ]
},
  "bbox": [],
  "geometry": {"coordinates":[-77.75,34.3167],"type":"Point"}
}