<<<<<<< HEAD
{
  "id": 2259984,
  "type": "Feature",
  "properties": {
    "tgn:hierarchy":[
        "tgn:2259984",
        "tgn:1000001",
        "tgn:7012149",
        "tgn:1002994",
        "tgn:7007708",
        "tgn:7029392"
    ],
    "tgn:id":2259984,
    "tgn:name":"Council Creek",
    "tgn:placetype":[
        "aat:300008706"
    ]
},
  "bbox": [],
  "geometry": {"coordinates":[-123.1,45.55],"type":"Point"}
}
=======
{"geometry":{"type":"Point","coordinates":[-123.100000,45.550000]},"type":"Feature","properties":{"hierarchy":["tgn:2259984","tgn:1000001","tgn:7012149","tgn:1002994","tgn:7007708","tgn:7029392"],"placetype":["aat:300008706"],"id":2259984,"name:xx":"Council Creek"}}
>>>>>>> 03f74aca74312dbeaf24d7e61306dd6a786dc3d0
