{
  "id": 1074941,
  "type": "Feature",
  "properties": {
    "tgn:hierarchy":[
        "tgn:1074941",
        "tgn:1000004",
        "tgn:7000198",
        "tgn:1001977",
        "tgn:7029392"
    ],
    "tgn:id":1074941,
    "tgn:name:en":"Champ\u0101d\u0101nga",
    "tgn:placetype":[
        "aat:300008347"
    ]
},
  "bbox": [],
  "geometry": {"coordinates":[87.975751,22.837713],"type":"Point"}
}