{
  "id": 2759285,
  "type": "Feature",
  "properties": {
    "tgn:hierarchy":[
        "tgn:2759285",
        "tgn:1000001",
        "tgn:7012149",
        "tgn:7007255",
        "tgn:7029392"
    ],
    "tgn:id":2759285,
    "tgn:name":"West Fork Clarks River",
    "tgn:placetype":[
        "aat:300008707"
    ]
},
  "bbox": [],
  "geometry": {"coordinates":[-88.3667,36.6167],"type":"Point"}
}