{
  "id": 2378620,
  "type": "Feature",
  "properties": {
    "tgn:hierarchy":[
        "tgn:2378620",
        "tgn:1000001",
        "tgn:7012149",
        "tgn:7007565",
        "tgn:7029392"
    ],
    "tgn:id":2378620,
    "tgn:name":"Harrisonville Lake",
    "tgn:placetype":[
        "aat:300006191"
    ]
},
  "bbox": [],
  "geometry": {"coordinates":[-75.2667,39.6667],"type":"Point"}
}