<<<<<<< HEAD
{
  "id": 2764474,
  "type": "Feature",
  "properties": {
    "tgn:hierarchy":[
        "tgn:2764474",
        "tgn:7006450",
        "tgn:1000001",
        "tgn:2124089",
        "tgn:7012149",
        "tgn:7029392"
    ],
    "tgn:id":2764474,
    "tgn:name":"Whigg Placer Mine",
    "tgn:placetype":[
        "aat:300000390"
    ]
},
  "bbox": [],
  "geometry": {"coordinates":[-133.8,58.0],"type":"Point"}
}
=======
{"geometry":{"type":"Point","coordinates":[-133.800000,58.000000]},"type":"Feature","properties":{"hierarchy":["tgn:2764474","tgn:7006450","tgn:1000001","tgn:2124089","tgn:7012149","tgn:7029392"],"placetype":["aat:300000390"],"id":2764474,"name:xx":"Whigg Placer Mine"}}
>>>>>>> 03f74aca74312dbeaf24d7e61306dd6a786dc3d0
