{
  "id": 2349506,
  "type": "Feature",
  "properties": {
    "tgn:hierarchy":[
        "tgn:2349506",
        "tgn:1000001",
        "tgn:7012149",
        "tgn:2002194",
        "tgn:7007919",
        "tgn:7029392"
    ],
    "tgn:id":2349506,
    "tgn:name":"Gill Hollow",
    "tgn:placetype":[
        "aat:300008761"
    ]
},
  "bbox": [],
  "geometry": {"coordinates":[-81.9833,36.6667],"type":"Point"}
}