{
  "id": 7545402,
  "type": "Feature",
  "properties": {
    "tgn:hierarchy":[
        "tgn:7545402",
        "tgn:1000004",
        "tgn:1001869",
        "tgn:7000198",
        "tgn:7029392"
    ],
    "tgn:id":7545402,
    "tgn:name:en":"Bagad River",
    "tgn:placetype":[
        "aat:300008699"
    ]
},
  "bbox": [],
  "geometry": {"coordinates":[71.983333,21.166667],"type":"Point"}
}