{
  "id": 1133579,
  "type": "Feature",
  "properties": {
    "tgn:hierarchy":[
        "tgn:1133579",
        "tgn:1001160",
        "tgn:7006477",
        "tgn:1000002",
        "tgn:7029392"
    ],
    "tgn:id":1133579,
    "tgn:name":"La Horqueta, Arroyo",
    "tgn:placetype":[
        "aat:300008706"
    ]
},
  "bbox": [],
  "geometry": {"coordinates":[-58.85,-34.6833],"type":"Point"}
}