{
  "id": 2574823,
  "type": "Feature",
  "properties": {
    "tgn:hierarchy":[
        "tgn:2574823",
        "tgn:1000001",
        "tgn:7012149",
        "tgn:2000931",
        "tgn:7007515",
        "tgn:7029392"
    ],
    "tgn:id":2574823,
    "tgn:name":"Pendleton Hill",
    "tgn:placetype":[
        "aat:300008798"
    ]
},
  "bbox": [],
  "geometry": {"coordinates":[-69.0167,44.2833],"type":"Point"}
}