{
  "id": 2696728,
  "type": "Feature",
  "properties": {
    "tgn:hierarchy":[
        "tgn:2696728",
        "tgn:1000001",
        "tgn:7012149",
        "tgn:2002379",
        "tgn:7007923",
        "tgn:7029392"
    ],
    "tgn:id":2696728,
    "tgn:name":"Stonecup Lake",
    "tgn:placetype":[
        "aat:300008680"
    ]
},
  "bbox": [],
  "geometry": {"coordinates":[-110.1333,44.5333],"type":"Point"}
}