<<<<<<< HEAD
{
  "id": 7022388,
  "type": "Feature",
  "properties": {
    "tgn:hierarchy":[
        "tgn:7022388",
        "tgn:1000001",
        "tgn:7012149",
        "tgn:7029392"
    ],
    "tgn:id":7022388,
    "tgn:name":"Billups Branch",
    "tgn:placetype":[
        "aat:300008699"
    ]
},
  "bbox": [],
  "geometry": {"coordinates":[-92.2,40.6333],"type":"Point"}
}
=======
{"geometry":{"type":"Point","coordinates":[-92.200000,40.633300]},"type":"Feature","properties":{"hierarchy":["tgn:7022388","tgn:1000001","tgn:7012149","tgn:7029392"],"placetype":["aat:300008699"],"id":7022388,"name:xx":"Billups Branch"}}
>>>>>>> 03f74aca74312dbeaf24d7e61306dd6a786dc3d0
