{
  "id": 1081612,
  "type": "Feature",
  "properties": {
    "tgn:hierarchy":[
        "tgn:1081612",
        "tgn:1000004",
        "tgn:1001012",
        "tgn:7000896",
        "tgn:1000120",
        "tgn:7029392"
    ],
    "tgn:id":1081612,
    "tgn:name":"Tsuge",
    "tgn:placetype":[
        "aat:300008347"
    ]
},
  "bbox": [],
  "geometry": {"coordinates":[135.95,34.6167],"type":"Point"}
}