{
  "id": 7418902,
  "type": "Feature",
  "properties": {
    "tgn:hierarchy":[
        "tgn:7418902",
        "tgn:7005584",
        "tgn:1000001",
        "tgn:7005560",
        "tgn:7029392"
    ],
    "tgn:id":7418902,
    "tgn:name":"El Carmen",
    "tgn:placetype":[
        "aat:300008347"
    ]
},
  "bbox": [],
  "geometry": {"coordinates":[-100.313333,21.241944],"type":"Point"}
}