{
  "id": 1027140,
  "type": "Feature",
  "properties": {
    "tgn:hierarchy":[
        "tgn:1027140",
        "tgn:7593919",
        "tgn:1000003",
        "tgn:1001780",
        "tgn:7029392"
    ],
    "tgn:id":1027140,
    "tgn:name":"D\u00fd\u0161ina",
    "tgn:placetype":[
        "aat:300008347"
    ]
},
  "bbox": [],
  "geometry": {"coordinates":[13.4833,49.7833],"type":"Point"}
}