{
  "id": 7419852,
  "type": "Feature",
  "properties": {
    "tgn:hierarchy":[
        "tgn:7419852",
        "tgn:1000001",
        "tgn:7005589",
        "tgn:7005560",
        "tgn:7029392"
    ],
    "tgn:id":7419852,
    "tgn:name:es":"El Puertecito",
    "tgn:placetype":[
        "aat:300008347"
    ]
},
  "bbox": [],
  "geometry": {"coordinates":[-100.444444,26.546667],"type":"Point"}
}