{
  "id": 2126970,
  "type": "Feature",
  "properties": {
    "tgn:hierarchy":[
        "tgn:2126970",
        "tgn:1000001",
        "tgn:7012149",
        "tgn:7019676",
        "tgn:7007566",
        "tgn:7029392"
    ],
    "tgn:id":2126970,
    "tgn:name":"Aguila, Cerro",
    "tgn:placetype":[
        "aat:300008798"
    ]
},
  "bbox": [],
  "geometry": {"coordinates":[-107.45,35.3167],"type":"Point"}
}