<<<<<<< HEAD
{
  "id": 2331512,
  "type": "Feature",
  "properties": {
    "tgn:hierarchy":[
        "tgn:2331512",
        "tgn:7002659",
        "tgn:1000001",
        "tgn:2000011",
        "tgn:7012149",
        "tgn:7029392"
    ],
    "tgn:id":2331512,
    "tgn:name":"Flatwood",
    "tgn:placetype":[
        "aat:300008347"
    ]
},
  "bbox": [],
  "geometry": {"coordinates":[-88.2333,31.7833],"type":"Point"}
}
=======
{"geometry":{"type":"Point","coordinates":[-88.233300,31.783300]},"type":"Feature","properties":{"hierarchy":["tgn:2331512","tgn:7002659","tgn:1000001","tgn:2000011","tgn:7012149","tgn:7029392"],"placetype":["aat:300008347"],"id":2331512,"name:xx":"Flatwood"}}
>>>>>>> 03f74aca74312dbeaf24d7e61306dd6a786dc3d0
