{
  "id": 2331512,
  "type": "Feature",
  "properties": {
    "tgn:hierarchy":[
        "tgn:2331512",
        "tgn:7002659",
        "tgn:1000001",
        "tgn:2000011",
        "tgn:7012149",
        "tgn:7029392"
    ],
    "tgn:id":2331512,
    "tgn:name":"Flatwood",
    "tgn:placetype":[
        "aat:300008347"
    ]
},
  "bbox": [],
  "geometry": {"coordinates":[-88.2333,31.7833],"type":"Point"}
}