{
  "id": 2141453,
  "type": "Feature",
  "properties": {
    "tgn:hierarchy":[
        "tgn:2141453",
        "tgn:1000001",
        "tgn:7012149",
        "tgn:2000471",
        "tgn:7007250",
        "tgn:7029392"
    ],
    "tgn:id":2141453,
    "tgn:name":"Azure Lake",
    "tgn:placetype":[
        "aat:300008680"
    ]
},
  "bbox": [],
  "geometry": {"coordinates":[-115.1167,43.95],"type":"Point"}
}