{
  "id": 7160029,
  "type": "Feature",
  "properties": {
    "tgn:hierarchy":[
        "tgn:7160029",
        "tgn:1000003",
        "tgn:7003688",
        "tgn:7000084",
        "tgn:7029392"
    ],
    "tgn:id":7160029,
    "tgn:name":"H\u00f6hndorf",
    "tgn:placetype":[
        "aat:300008347"
    ]
},
  "bbox": [],
  "geometry": {"coordinates":[10.366667,54.366667],"type":"Point"}
}