{
  "id": 7473243,
  "type": "Feature",
  "properties": {
    "tgn:hierarchy":[
        "tgn:7473243",
        "tgn:1000004",
        "tgn:7001014",
        "tgn:1000141",
        "tgn:7029392"
    ],
    "tgn:id":7473243,
    "tgn:name":"Yangchoucuo",
    "tgn:placetype":[
        "aat:300008347"
    ]
},
  "bbox": [],
  "geometry": {"coordinates":[120.198333,23.642778],"type":"Point"}
}