{
  "id": 2687284,
  "type": "Feature",
  "properties": {
    "tgn:hierarchy":[
        "tgn:2687284",
        "tgn:1000001",
        "tgn:2000498",
        "tgn:7012149",
        "tgn:7007251",
        "tgn:7029392"
    ],
    "tgn:id":2687284,
    "tgn:name":"Spring Lake",
    "tgn:placetype":[
        "aat:300008680"
    ]
},
  "bbox": [],
  "geometry": {"coordinates":[-90.1333,42.05],"type":"Point"}
}