{
  "id": 7592052,
  "type": "Feature",
  "properties": {
    "tgn:hierarchy":[
        "tgn:7592052",
        "tgn:1000004",
        "tgn:7000198",
        "tgn:7000799",
        "tgn:7029392"
    ],
    "tgn:id":7592052,
    "tgn:name:en":"Suli Dhakki",
    "tgn:placetype":[
        "aat:300008347"
    ]
},
  "bbox": [],
  "geometry": {"coordinates":[74.991667,32.690278],"type":"Point"}
}