{
  "id": 7427838,
  "type": "Feature",
  "properties": {
    "tgn:hierarchy":[
        "tgn:7427838",
        "tgn:1000001",
        "tgn:7005594",
        "tgn:7005560",
        "tgn:7029392"
    ],
    "tgn:id":7427838,
    "tgn:name":"San Jos\u00e9 del Lim\u00f3n",
    "tgn:placetype":[
        "aat:300008347"
    ]
},
  "bbox": [],
  "geometry": {"coordinates":[-98.633333,22.033333],"type":"Point"}
}