<<<<<<< HEAD
{
  "id": 2769176,
  "type": "Feature",
  "properties": {
    "tgn:hierarchy":[
        "tgn:2769176",
        "tgn:7006450",
        "tgn:1000001",
        "tgn:7012149",
        "tgn:2000089",
        "tgn:7029392"
    ],
    "tgn:id":2769176,
    "tgn:name":"Whontleya",
    "tgn:placetype":[
        "aat:300008791"
    ]
},
  "bbox": [],
  "geometry": {"coordinates":[-157.4667,64.8333],"type":"Point"}
}
=======
{"geometry":{"type":"Point","coordinates":[-157.466700,64.833300]},"type":"Feature","properties":{"hierarchy":["tgn:2769176","tgn:7006450","tgn:1000001","tgn:7012149","tgn:2000089","tgn:7029392"],"placetype":["aat:300008791"],"id":2769176,"name:xx":"Whontleya"}}
>>>>>>> 03f74aca74312dbeaf24d7e61306dd6a786dc3d0
