{
  "id": 2626695,
  "type": "Feature",
  "properties": {
    "tgn:hierarchy":[
        "tgn:2626695",
        "tgn:1000001",
        "tgn:7012149",
        "tgn:2002187",
        "tgn:7007919",
        "tgn:7029392"
    ],
    "tgn:id":2626695,
    "tgn:name":"Rocky Mountain Run",
    "tgn:placetype":[
        "aat:300008699"
    ]
},
  "bbox": [],
  "geometry": {"coordinates":[-78.65,38.2833],"type":"Point"}
}