{
  "id": 2410258,
  "type": "Feature",
  "properties": {
    "tgn:hierarchy":[
        "tgn:2410258",
        "tgn:1000001",
        "tgn:7012149",
        "tgn:2002192",
        "tgn:7007919",
        "tgn:7029392"
    ],
    "tgn:id":2410258,
    "tgn:name":"Indian",
    "tgn:placetype":[
        "aat:300008347"
    ]
},
  "bbox": [],
  "geometry": {"coordinates":[-81.75,37.0833],"type":"Point"}
}