{
  "id": 7310837,
  "type": "Feature",
  "properties": {
    "tgn:hierarchy":[
        "tgn:7310837",
        "tgn:7002464",
        "tgn:1000049",
        "tgn:1000002",
        "tgn:7029392"
    ],
    "tgn:id":7310837,
    "tgn:name":"Oficina San Patricio",
    "tgn:placetype":[
        "aat:300008057"
    ]
},
  "bbox": [],
  "geometry": {"coordinates":[-69.966667,-19.666667],"type":"Point"}
}