{
  "id": 7162211,
  "type": "Feature",
  "properties": {
    "tgn:hierarchy":[
        "tgn:7162211",
        "tgn:1000003",
        "tgn:7003676",
        "tgn:7000084",
        "tgn:7029392"
    ],
    "tgn:id":7162211,
    "tgn:name":"Iberg",
    "tgn:placetype":[
        "aat:300055621"
    ]
},
  "bbox": [],
  "geometry": {"coordinates":[9.266667,52.216667],"type":"Point"}
}