{
  "id": 2191456,
  "type": "Feature",
  "properties": {
    "tgn:hierarchy":[
        "tgn:2191456",
        "tgn:1000001",
        "tgn:2001733",
        "tgn:7012149",
        "tgn:7007712",
        "tgn:7029392"
    ],
    "tgn:id":2191456,
    "tgn:name":"Braddy Lake",
    "tgn:placetype":[
        "aat:300008680"
    ]
},
  "bbox": [],
  "geometry": {"coordinates":[-80.8167,33.7667],"type":"Point"}
}