{
  "id": 2279811,
  "type": "Feature",
  "properties": {
    "tgn:hierarchy":[
        "tgn:2279811",
        "tgn:1000001",
        "tgn:7012149",
        "tgn:2001293",
        "tgn:7007524",
        "tgn:7029392"
    ],
    "tgn:id":2279811,
    "tgn:name":"Deaf Jim Knob",
    "tgn:placetype":[
        "aat:300008798"
    ]
},
  "bbox": [],
  "geometry": {"coordinates":[-110.8333,45.05],"type":"Point"}
}