{
  "id": 7560149,
  "type": "Feature",
  "properties": {
    "tgn:hierarchy":[
        "tgn:7560149",
        "tgn:1000004",
        "tgn:7000198",
        "tgn:7016722",
        "tgn:7029392"
    ],
    "tgn:id":7560149,
    "tgn:name:en":"H\u012br\u0101pur",
    "tgn:placetype":[
        "aat:300008347"
    ]
},
  "bbox": [],
  "geometry": {"coordinates":[79.008878,26.88286],"type":"Point"}
}