{
  "id": 7230391,
  "type": "Feature",
  "properties": {
    "tgn:hierarchy":[
        "tgn:7230391",
        "tgn:7011330",
        "tgn:7002674",
        "tgn:1000003",
        "tgn:1000074",
        "tgn:7029392"
    ],
    "tgn:id":7230391,
    "tgn:name":"Kt\u00e9nia, Vr\u00e1choi",
    "tgn:placetype":[
        "aat:300011692"
    ]
},
  "bbox": [],
  "geometry": {"coordinates":[26.227222,36.528333],"type":"Point"}
}