{
  "id": 7569198,
  "type": "Feature",
  "properties": {
    "tgn:hierarchy":[
        "tgn:7569198",
        "tgn:1000004",
        "tgn:7000198",
        "tgn:7016788",
        "tgn:7029392"
    ],
    "tgn:id":7569198,
    "tgn:name:en":"Batw\u0101ri ki D\u016bngariy\u0101n",
    "tgn:placetype":[
        "aat:300008347"
    ]
},
  "bbox": [],
  "geometry": {"coordinates":[75.636983,25.64037],"type":"Point"}
}