{
  "id": 7225586,
  "type": "Feature",
  "properties": {
    "tgn:hierarchy":[
        "tgn:7225586",
        "tgn:7002681",
        "tgn:7001395",
        "tgn:1000003",
        "tgn:1000074",
        "tgn:7029392"
    ],
    "tgn:id":7225586,
    "tgn:name":"Perist\u00e9ria, Vrachonis\u00eddes",
    "tgn:placetype":[
        "aat:300008791"
    ]
},
  "bbox": [],
  "geometry": {"coordinates":[23.466667,37.883333],"type":"Point"}
}