{
  "id": 1017931,
  "type": "Feature",
  "properties": {
    "tgn:hierarchy":[
        "tgn:1017931",
        "tgn:1001853",
        "tgn:1000001",
        "tgn:7005560",
        "tgn:7029392"
    ],
    "tgn:id":1017931,
    "tgn:name":"Nueva Rosita",
    "tgn:placetype":[
        "aat:300008347"
    ]
},
  "bbox": [],
  "geometry": {"coordinates":[-101.216667,27.95],"type":"Point"}
}