{
  "id": 2777617,
  "type": "Feature",
  "properties": {
    "tgn:hierarchy":[
        "tgn:2777617",
        "tgn:1000001",
        "tgn:7012149",
        "tgn:7007708",
        "tgn:7029392"
    ],
    "tgn:id":2777617,
    "tgn:name":"Winom Creek",
    "tgn:placetype":[
        "aat:300008706"
    ]
},
  "bbox": [],
  "geometry": {"coordinates":[-118.6167,45.05],"type":"Point"}
}