{
  "id": 2161937,
  "type": "Feature",
  "properties": {
    "tgn:hierarchy":[
        "tgn:2161937",
        "tgn:1000001",
        "tgn:7012149",
        "tgn:2001755",
        "tgn:7007712",
        "tgn:7029392"
    ],
    "tgn:id":2161937,
    "tgn:name":"Bells Branch",
    "tgn:placetype":[
        "aat:300008699"
    ]
},
  "bbox": [],
  "geometry": {"coordinates":[-80.2833,34.25],"type":"Point"}
}