{
  "id": 1023071,
  "type": "Feature",
  "properties": {
    "tgn:hierarchy":[
        "tgn:1023071",
        "tgn:7012827",
        "tgn:7002454",
        "tgn:1000047",
        "tgn:1000002",
        "tgn:7029392"
    ],
    "tgn:id":1023071,
    "tgn:name":"Serran\u00f3polis",
    "tgn:placetype":[
        "aat:300008347"
    ]
},
  "bbox": [],
  "geometry": {"coordinates":[-51.9167,-18.25],"type":"Point"}
}