{
  "id": 7338391,
  "type": "Feature",
  "properties": {
    "tgn:hierarchy":[
        "tgn:7338391",
        "tgn:7002760",
        "tgn:1000003",
        "tgn:1000095",
        "tgn:7029392"
    ],
    "tgn:id":7338391,
    "tgn:name":"Caviedes",
    "tgn:placetype":[
        "aat:300008347"
    ]
},
  "bbox": [],
  "geometry": {"coordinates":[-4.316667,43.333333],"type":"Point"}
}