{
  "id": 7590472,
  "type": "Feature",
  "properties": {
    "tgn:hierarchy":[
        "tgn:7590472",
        "tgn:1000004",
        "tgn:7000198",
        "tgn:7000799",
        "tgn:7029392"
    ],
    "tgn:id":7590472,
    "tgn:name:en":"Rangpur Trewa",
    "tgn:placetype":[
        "aat:300008347"
    ]
},
  "bbox": [],
  "geometry": {"coordinates":[74.773611,32.501389],"type":"Point"}
}