{
  "id": 2687659,
  "type": "Feature",
  "properties": {
    "tgn:hierarchy":[
        "tgn:2687659",
        "tgn:1000001",
        "tgn:7012149",
        "tgn:2001706",
        "tgn:7007708",
        "tgn:7029392"
    ],
    "tgn:id":2687659,
    "tgn:name":"Spring River",
    "tgn:placetype":[
        "aat:300008707"
    ]
},
  "bbox": [],
  "geometry": {"coordinates":[-122.1333,43.2833],"type":"Point"}
}