{
  "id": 2777976,
  "type": "Feature",
  "properties": {
    "tgn:hierarchy":[
        "tgn:2777976",
        "tgn:1000001",
        "tgn:1002923",
        "tgn:7012149",
        "tgn:7007517",
        "tgn:7029392"
    ],
    "tgn:id":2777976,
    "tgn:name":"Winthrop Beach",
    "tgn:placetype":[
        "aat:300008347"
    ]
},
  "bbox": [],
  "geometry": {"coordinates":[-70.9667,42.3667],"type":"Point"}
}