{
  "id": 7107141,
  "type": "Feature",
  "properties": {
    "tgn:hierarchy":[
        "tgn:7107141",
        "tgn:7003669",
        "tgn:1000003",
        "tgn:7000084",
        "tgn:7029392"
    ],
    "tgn:id":7107141,
    "tgn:name":"Schellenberg",
    "tgn:placetype":[
        "aat:300008777"
    ]
},
  "bbox": [],
  "geometry": {"coordinates":[10.783333,48.716667],"type":"Point"}
}