{
  "id": 1089724,
  "type": "Feature",
  "properties": {
    "tgn:hierarchy":[
        "tgn:1089724",
        "tgn:7001242",
        "tgn:1001535",
        "tgn:7000489",
        "tgn:7029392"
    ],
    "tgn:id":1089724,
    "tgn:name":"\u0100wash",
    "tgn:placetype":[
        "aat:300008347"
    ]
},
  "bbox": [],
  "geometry": {"coordinates":[40.1667,9.0167],"type":"Point"}
}