{
  "id": 7286692,
  "type": "Feature",
  "properties": {
    "tgn:hierarchy":[
        "tgn:7286692",
        "tgn:7002464",
        "tgn:1000049",
        "tgn:1000002",
        "tgn:7029392"
    ],
    "tgn:id":7286692,
    "tgn:name":"Guasco Salinas",
    "tgn:placetype":[
        "aat:300008347"
    ]
},
  "bbox": [],
  "geometry": {"coordinates":[-68.883333,-20.266667],"type":"Point"}
}