<<<<<<< HEAD
{
  "id": 2409415,
  "type": "Feature",
  "properties": {
    "tgn:hierarchy":[
        "tgn:2409415",
        "tgn:7006450",
        "tgn:1000001",
        "tgn:2124053",
        "tgn:7012149",
        "tgn:7029392"
    ],
    "tgn:id":2409415,
    "tgn:name":"Idaho Peak",
    "tgn:placetype":[
        "aat:300008798"
    ]
},
  "bbox": [],
  "geometry": {"coordinates":[-149.1333,61.8],"type":"Point"}
}
=======
{"geometry":{"type":"Point","coordinates":[-149.133300,61.800000]},"type":"Feature","properties":{"hierarchy":["tgn:2409415","tgn:7006450","tgn:1000001","tgn:2124053","tgn:7012149","tgn:7029392"],"placetype":["aat:300008798"],"id":2409415,"name:xx":"Idaho Peak"}}
>>>>>>> 03f74aca74312dbeaf24d7e61306dd6a786dc3d0
