{
  "id": 2511803,
  "type": "Feature",
  "properties": {
    "tgn:hierarchy":[
        "tgn:2511803",
        "tgn:1000001",
        "tgn:7006451",
        "tgn:2000092",
        "tgn:7012149",
        "tgn:7029392"
    ],
    "tgn:id":2511803,
    "tgn:name":"Milk Creek",
    "tgn:placetype":[
        "aat:300008706"
    ]
},
  "bbox": [],
  "geometry": {"coordinates":[-112.1167,36.2833],"type":"Point"}
}