{
  "id": 1096390,
  "type": "Feature",
  "properties": {
    "tgn:hierarchy":[
        "tgn:1096390",
        "tgn:7000490",
        "tgn:1000006",
        "tgn:7001828",
        "tgn:7029392"
    ],
    "tgn:id":1096390,
    "tgn:name":"Brookvale",
    "tgn:placetype":[
        "aat:300008347"
    ]
},
  "bbox": [],
  "geometry": {"coordinates":[151.2833,-33.7667],"type":"Point"}
}