{
  "id": 2093462,
  "type": "Feature",
  "properties": {
    "tgn:hierarchy":[
        "tgn:2093462",
        "tgn:1000001",
        "tgn:1002266",
        "tgn:7012149",
        "tgn:7007710",
        "tgn:7029392"
    ],
    "tgn:id":2093462,
    "tgn:name":"Stottsville",
    "tgn:placetype":[
        "aat:300008347"
    ]
},
  "bbox": [],
  "geometry": {"coordinates":[-75.8833,39.95],"type":"Point"}
}