{
  "id": 7318935,
  "type": "Feature",
  "properties": {
    "tgn:hierarchy":[
        "tgn:7318935",
        "tgn:1001702",
        "tgn:1000049",
        "tgn:1000002",
        "tgn:7029392"
    ],
    "tgn:id":7318935,
    "tgn:name":"Ar\u00edstides, Isla",
    "tgn:placetype":[
        "aat:300008791"
    ]
},
  "bbox": [],
  "geometry": {"coordinates":[-74.983333,-50.966667],"type":"Point"}
}