{
  "id": 7490467,
  "type": "Feature",
  "properties": {
    "tgn:hierarchy":[
        "tgn:7490467",
        "tgn:1000004",
        "tgn:7001009",
        "tgn:1000141",
        "tgn:7029392"
    ],
    "tgn:id":7490467,
    "tgn:name":"Sancha",
    "tgn:placetype":[
        "aat:300008347"
    ]
},
  "bbox": [],
  "geometry": {"coordinates":[120.72478,24.139452],"type":"Point"}
}