{
  "id": 2786517,
  "type": "Feature",
  "properties": {
    "tgn:hierarchy":[
        "tgn:2786517",
        "tgn:1000001",
        "tgn:7012149",
        "tgn:7007923",
        "tgn:7029392"
    ],
    "tgn:id":2786517,
    "tgn:name":"Yukon Peak",
    "tgn:placetype":[
        "aat:300008798"
    ]
},
  "bbox": [],
  "geometry": {"coordinates":[-109.6833,43.25],"type":"Point"}
}