{
  "id": 2379426,
  "type": "Feature",
  "properties": {
    "tgn:hierarchy":[
        "tgn:2379426",
        "tgn:1000001",
        "tgn:7012149",
        "tgn:7007157",
        "tgn:2000186",
        "tgn:7029392"
    ],
    "tgn:id":2379426,
    "tgn:name":"Harvey Jones Butte",
    "tgn:placetype":[
        "aat:300008798"
    ]
},
  "bbox": [],
  "geometry": {"coordinates":[-121.25,41.75],"type":"Point"}
}