{
  "id": 2632280,
  "type": "Feature",
  "properties": {
    "tgn:hierarchy":[
        "tgn:2632280",
        "tgn:1000001",
        "tgn:2002325",
        "tgn:7012149",
        "tgn:7007922",
        "tgn:7029392"
    ],
    "tgn:id":2632280,
    "tgn:name":"Roy Creek",
    "tgn:placetype":[
        "aat:300008706"
    ]
},
  "bbox": [],
  "geometry": {"coordinates":[-88.9333,43.75],"type":"Point"}
}