{
  "id": 1112795,
  "type": "Feature",
  "properties": {
    "tgn:hierarchy":[
        "tgn:1112795",
        "tgn:7005685",
        "tgn:1000001",
        "tgn:7005802",
        "tgn:7029392"
    ],
    "tgn:id":1112795,
    "tgn:name":"Chedabucto Bay",
    "tgn:placetype":[
        "aat:300132316"
    ]
},
  "bbox": [],
  "geometry": {"coordinates":[-61.1667,45.3833],"type":"Point"}
}