{
  "id": 7275413,
  "type": "Feature",
  "properties": {
    "tgn:hierarchy":[
        "tgn:7275413",
        "tgn:1001702",
        "tgn:1000049",
        "tgn:1000002",
        "tgn:7029392"
    ],
    "tgn:id":7275413,
    "tgn:name":"Tucapel, Ensenada",
    "tgn:placetype":[
        "aat:300132316"
    ]
},
  "bbox": [],
  "geometry": {"coordinates":[-73.033333,-53.183333],"type":"Point"}
}