{
  "id": 2174988,
  "type": "Feature",
  "properties": {
    "tgn:hierarchy":[
        "tgn:2174988",
        "tgn:1000001",
        "tgn:2000861",
        "tgn:7012149",
        "tgn:7007256",
        "tgn:7029392"
    ],
    "tgn:id":2174988,
    "tgn:name":"Black Bayou",
    "tgn:placetype":[
        "aat:300008699"
    ]
},
  "bbox": [],
  "geometry": {"coordinates":[-93.7667,32.7333],"type":"Point"}
}