{
  "id": 2193475,
  "type": "Feature",
  "properties": {
    "tgn:hierarchy":[
        "tgn:2193475",
        "tgn:1000001",
        "tgn:7012149",
        "tgn:1002913",
        "tgn:7007919",
        "tgn:7029392"
    ],
    "tgn:id":2193475,
    "tgn:name":"Brent Marsh",
    "tgn:placetype":[
        "aat:300008905"
    ]
},
  "bbox": [],
  "geometry": {"coordinates":[-77.3167,38.4333],"type":"Point"}
}