{
  "id": 2554952,
  "type": "Feature",
  "properties": {
    "tgn:hierarchy":[
        "tgn:2554952",
        "tgn:1000001",
        "tgn:2001014",
        "tgn:7012149",
        "tgn:7007521",
        "tgn:7029392"
    ],
    "tgn:id":2554952,
    "tgn:name":"Oberg Mountain",
    "tgn:placetype":[
        "aat:300008798"
    ]
},
  "bbox": [],
  "geometry": {"coordinates":[-90.7667,47.6167],"type":"Point"}
}