<<<<<<< HEAD
{
  "id": 7243343,
  "type": "Feature",
  "properties": {
    "tgn:hierarchy":[
        "tgn:7243343",
        "tgn:7003457",
        "tgn:1000003",
        "tgn:1000063",
        "tgn:7018236",
        "tgn:7029392"
    ],
    "tgn:id":7243343,
    "tgn:name":"Kruisbeek",
    "tgn:placetype":[
        "aat:300008699"
    ]
},
  "bbox": [],
  "geometry": {"coordinates":[4.116667,50.883333],"type":"Point"}
}
=======
{"geometry":{"type":"Point","coordinates":[4.116667,50.883333]},"type":"Feature","properties":{"hierarchy":["tgn:7243343","tgn:7003457","tgn:1000003","tgn:1000063","tgn:7018236","tgn:7029392"],"placetype":["aat:300008699"],"id":7243343,"name:xx":"Kruisbeek"}}
>>>>>>> 03f74aca74312dbeaf24d7e61306dd6a786dc3d0
