{
  "id": 7580472,
  "type": "Feature",
  "properties": {
    "tgn:hierarchy":[
        "tgn:7580472",
        "tgn:1000004",
        "tgn:7000198",
        "tgn:7000799",
        "tgn:7029392"
    ],
    "tgn:id":7580472,
    "tgn:name:en":"Thratsang La",
    "tgn:placetype":[
        "aat:300259572"
    ]
},
  "bbox": [],
  "geometry": {"coordinates":[78.673692,34.026117],"type":"Point"}
}