{
  "id": 2552592,
  "type": "Feature",
  "properties": {
    "tgn:hierarchy":[
        "tgn:2552592",
        "tgn:1000001",
        "tgn:7012149",
        "tgn:7007157",
        "tgn:2000185",
        "tgn:7029392"
    ],
    "tgn:id":2552592,
    "tgn:name":"Nursey Gulch",
    "tgn:placetype":[
        "aat:300008761"
    ]
},
  "bbox": [],
  "geometry": {"coordinates":[-123.6167,39.2333],"type":"Point"}
}