<<<<<<< HEAD
{
  "id": 2760741,
  "type": "Feature",
  "properties": {
    "tgn:hierarchy":[
        "tgn:2760741",
        "tgn:1000001",
        "tgn:7012149",
        "tgn:7007158",
        "tgn:2000243",
        "tgn:7029392"
    ],
    "tgn:id":2760741,
    "tgn:name":"West Gordon Gulch",
    "tgn:placetype":[
        "aat:300008761"
    ]
},
  "bbox": [],
  "geometry": {"coordinates":[-108.05,39.75],"type":"Point"}
}
=======
{"geometry":{"type":"Point","coordinates":[-108.050000,39.750000]},"type":"Feature","properties":{"hierarchy":["tgn:2760741","tgn:1000001","tgn:7012149","tgn:7007158","tgn:2000243","tgn:7029392"],"placetype":["aat:300008761"],"id":2760741,"name:xx":"West Gordon Gulch"}}
>>>>>>> 03f74aca74312dbeaf24d7e61306dd6a786dc3d0
