{
  "id": 2091331,
  "type": "Feature",
  "properties": {
    "tgn:hierarchy":[
        "tgn:2091331",
        "tgn:1000001",
        "tgn:1002310",
        "tgn:7012149",
        "tgn:7007710",
        "tgn:7029392"
    ],
    "tgn:id":2091331,
    "tgn:name":"Newville",
    "tgn:placetype":[
        "aat:300008347"
    ]
},
  "bbox": [],
  "geometry": {"coordinates":[-77.3833,40.1667],"type":"Point"}
}