{
  "id": 7382163,
  "type": "Feature",
  "properties": {
    "tgn:hierarchy":[
        "tgn:7382163",
        "tgn:1000001",
        "tgn:1001960",
        "tgn:7005560",
        "tgn:7029392"
    ],
    "tgn:id":7382163,
    "tgn:name":"Monterrey, Sierra de",
    "tgn:placetype":[
        "aat:300008795"
    ]
},
  "bbox": [],
  "geometry": {"coordinates":[-110.75,29.05],"type":"Point"}
}