{
  "id": 2768293,
  "type": "Feature",
  "properties": {
    "tgn:hierarchy":[
        "tgn:2768293",
        "tgn:1000001",
        "tgn:7012149",
        "tgn:7007706",
        "tgn:7029392"
    ],
    "tgn:id":2768293,
    "tgn:name":"Whites Run",
    "tgn:placetype":[
        "aat:300008699"
    ]
},
  "bbox": [],
  "geometry": {"coordinates":[-81.7167,39.25],"type":"Point"}
}