<<<<<<< HEAD
{
  "id": 2768293,
  "type": "Feature",
  "properties": {
    "tgn:hierarchy":[
        "tgn:2768293",
        "tgn:1000001",
        "tgn:7012149",
        "tgn:7007706",
        "tgn:7029392"
    ],
    "tgn:id":2768293,
    "tgn:name":"Whites Run",
    "tgn:placetype":[
        "aat:300008699"
    ]
},
  "bbox": [],
  "geometry": {"coordinates":[-81.7167,39.25],"type":"Point"}
}
=======
{"geometry":{"type":"Point","coordinates":[-81.716700,39.250000]},"type":"Feature","properties":{"hierarchy":["tgn:2768293","tgn:1000001","tgn:7012149","tgn:7007706","tgn:7029392"],"placetype":["aat:300008699"],"id":2768293,"name:xx":"Whites Run"}}
>>>>>>> 03f74aca74312dbeaf24d7e61306dd6a786dc3d0
