{
  "id": 7444681,
  "type": "Feature",
  "properties": {
    "tgn:hierarchy":[
        "tgn:7444681",
        "tgn:7002443",
        "tgn:1000003",
        "tgn:7018993",
        "tgn:7008591",
        "tgn:7029392"
    ],
    "tgn:id":7444681,
    "tgn:name:en":"Turbot Bank",
    "tgn:placetype":[
        "aat:300386970"
    ]
},
  "bbox": [],
  "geometry": {"coordinates":[-5.133333,51.616667],"type":"Point"}
}