{
  "id": 7281726,
  "type": "Feature",
  "properties": {
    "tgn:hierarchy":[
        "tgn:7281726",
        "tgn:1001702",
        "tgn:1000049",
        "tgn:1000002",
        "tgn:7029392"
    ],
    "tgn:id":7281726,
    "tgn:name":"Seal, Rocas",
    "tgn:placetype":[
        "aat:300011692"
    ]
},
  "bbox": [],
  "geometry": {"coordinates":[-75.316667,-49.933333],"type":"Point"}
}