{
  "id": 7401244,
  "type": "Feature",
  "properties": {
    "tgn:hierarchy":[
        "tgn:7401244",
        "tgn:1000001",
        "tgn:7005599",
        "tgn:7005560",
        "tgn:7029392"
    ],
    "tgn:id":7401244,
    "tgn:name":"Coabosto",
    "tgn:placetype":[
        "aat:300008347"
    ]
},
  "bbox": [],
  "geometry": {"coordinates":[-96.975,19.315278],"type":"Point"}
}