{
  "id": 7517087,
  "type": "Feature",
  "properties": {
    "tgn:hierarchy":[
        "tgn:7517087",
        "tgn:7016670",
        "tgn:1008380",
        "tgn:1000226",
        "tgn:1000006",
        "tgn:7029392"
    ],
    "tgn:id":7517087,
    "tgn:name:en":"Mangamarahia",
    "tgn:placetype":[
        "aat:300008699"
    ]
},
  "bbox": [],
  "geometry": {"coordinates":[176.05,-39.466667],"type":"Point"}
}