{
  "id": 1113164,
  "type": "Feature",
  "properties": {
    "tgn:hierarchy":[
        "tgn:1113164",
        "tgn:1000004",
        "tgn:7016744",
        "tgn:1000135",
        "tgn:7029392"
    ],
    "tgn:id":1113164,
    "tgn:name":"Illana Bay",
    "tgn:placetype":[
        "aat:300132316"
    ]
},
  "bbox": [],
  "geometry": {"coordinates":[123.75,7.4167],"type":"Point"}
}