{
  "id": 7572449,
  "type": "Feature",
  "properties": {
    "tgn:hierarchy":[
        "tgn:7572449",
        "tgn:1000004",
        "tgn:7000198",
        "tgn:1001886",
        "tgn:7029392"
    ],
    "tgn:id":7572449,
    "tgn:name:en":"Ern\u0101kulam North",
    "tgn:placetype":[
        "aat:300007783"
    ]
},
  "bbox": [],
  "geometry": {"coordinates":[76.283333,9.966667],"type":"Point"}
}