{
  "id": 2427205,
  "type": "Feature",
  "properties": {
    "tgn:hierarchy":[
        "tgn:2427205",
        "tgn:1000001",
        "tgn:7012149",
        "tgn:7007515",
        "tgn:7029392"
    ],
    "tgn:id":2427205,
    "tgn:name":"Jordan Brook",
    "tgn:placetype":[
        "aat:300008699"
    ]
},
  "bbox": [],
  "geometry": {"coordinates":[-68.9167,45.5333],"type":"Point"}
}