{
  "id": 7004819,
  "type": "Feature",
  "properties": {
    "tgn:hierarchy":[
        "tgn:7004819",
        "tgn:1000992",
        "tgn:1000004",
        "tgn:7000903",
        "tgn:1000120",
        "tgn:7029392"
    ],
    "tgn:id":7004819,
    "tgn:name":"Takamatsu",
    "tgn:placetype":[
        "aat:300008347",
        "aat:300008389",
        "aat:300387220",
        "aat:300120599"
    ]
},
  "bbox": [],
  "geometry": {"coordinates":[134.0167,34.3333],"type":"Point"}
}