{
  "id": 2551328,
  "type": "Feature",
  "properties": {
    "tgn:hierarchy":[
        "tgn:2551328",
        "tgn:7006450",
        "tgn:1000001",
        "tgn:7012149",
        "tgn:2124005",
        "tgn:7029392"
    ],
    "tgn:id":2551328,
    "tgn:name":"Nuka River",
    "tgn:placetype":[
        "aat:300008707"
    ]
},
  "bbox": [],
  "geometry": {"coordinates":[-160.1333,68.5833],"type":"Point"}
}