{
  "id": 1017324,
  "type": "Feature",
  "properties": {
    "tgn:hierarchy":[
        "tgn:1017324",
        "tgn:1000001",
        "tgn:7005589",
        "tgn:7005560",
        "tgn:7029392"
    ],
    "tgn:id":1017324,
    "tgn:name":"Cucharas",
    "tgn:placetype":[
        "aat:300008347"
    ]
},
  "bbox": [],
  "geometry": {"coordinates":[-100.366667,25.816667],"type":"Point"}
}