<<<<<<< HEAD
{
  "id": 7241131,
  "type": "Feature",
  "properties": {
    "tgn:hierarchy":[
        "tgn:7241131",
        "tgn:7003456",
        "tgn:1000003",
        "tgn:1000063",
        "tgn:7018236",
        "tgn:7029392"
    ],
    "tgn:id":7241131,
    "tgn:name":"Hellicht",
    "tgn:placetype":[
        "aat:300008347"
    ]
},
  "bbox": [],
  "geometry": {"coordinates":[4.7,50.966667],"type":"Point"}
}
=======
{"geometry":{"type":"Point","coordinates":[4.700000,50.966667]},"type":"Feature","properties":{"hierarchy":["tgn:7241131","tgn:7003456","tgn:1000003","tgn:1000063","tgn:7018236","tgn:7029392"],"placetype":["aat:300008347"],"id":7241131,"name:xx":"Hellicht"}}
>>>>>>> 03f74aca74312dbeaf24d7e61306dd6a786dc3d0
