{
  "id": 1024154,
  "type": "Feature",
  "properties": {
    "tgn:hierarchy":[
        "tgn:1024154",
        "tgn:1001155",
        "tgn:7002561",
        "tgn:1000051",
        "tgn:1000002",
        "tgn:7029392"
    ],
    "tgn:id":1024154,
    "tgn:name":"San Jos\u00e9",
    "tgn:placetype":[
        "aat:300008347"
    ]
},
  "bbox": [],
  "geometry": {"coordinates":[-79.086,-1.998],"type":"Point"}
}