{
  "id": 7209686,
  "type": "Feature",
  "properties": {
    "tgn:hierarchy":[
        "tgn:7209686",
        "tgn:1000003",
        "tgn:7003685",
        "tgn:7000084",
        "tgn:7029392"
    ],
    "tgn:id":7209686,
    "tgn:name":"Bermsgr\u00fcn",
    "tgn:placetype":[
        "aat:300008347"
    ]
},
  "bbox": [],
  "geometry": {"coordinates":[12.783333,50.516667],"type":"Point"}
}