{
  "id": 2652317,
  "type": "Feature",
  "properties": {
    "tgn:hierarchy":[
        "tgn:2652317",
        "tgn:1000001",
        "tgn:7012149",
        "tgn:1002881",
        "tgn:7007240",
        "tgn:7029392"
    ],
    "tgn:id":2652317,
    "tgn:name":"Seminole, Lake",
    "tgn:placetype":[
        "aat:300008680"
    ]
},
  "bbox": [],
  "geometry": {"coordinates":[-81.35,28.6833],"type":"Point"}
}