{
  "id": 2657371,
  "type": "Feature",
  "properties": {
    "tgn:hierarchy":[
        "tgn:2657371",
        "tgn:1000001",
        "tgn:7012149",
        "tgn:2001718",
        "tgn:7007708",
        "tgn:7029392"
    ],
    "tgn:id":2657371,
    "tgn:name":"Sheephead Reservoir",
    "tgn:placetype":[
        "aat:300006191"
    ]
},
  "bbox": [],
  "geometry": {"coordinates":[-117.95,42.8667],"type":"Point"}
}