{
  "id": 7546074,
  "type": "Feature",
  "properties": {
    "tgn:hierarchy":[
        "tgn:7546074",
        "tgn:1000004",
        "tgn:7000198",
        "tgn:7016722",
        "tgn:7029392"
    ],
    "tgn:id":7546074,
    "tgn:name:en":"Bait\u0101lpur",
    "tgn:placetype":[
        "aat:300007783"
    ]
},
  "bbox": [],
  "geometry": {"coordinates":[83.737347,26.552607],"type":"Point"}
}