{
  "id": 2546502,
  "type": "Feature",
  "properties": {
    "tgn:hierarchy":[
        "tgn:2546502",
        "tgn:1000001",
        "tgn:7012149",
        "tgn:2001420",
        "tgn:7007526",
        "tgn:7029392"
    ],
    "tgn:id":2546502,
    "tgn:name":"North Fork Kalamazoo Creek",
    "tgn:placetype":[
        "aat:300008706"
    ]
},
  "bbox": [],
  "geometry": {"coordinates":[-114.65,39.5833],"type":"Point"}
}