{
  "id": 7140989,
  "type": "Feature",
  "properties": {
    "tgn:hierarchy":[
        "tgn:7140989",
        "tgn:1000003",
        "tgn:7003677",
        "tgn:7000084",
        "tgn:7029392"
    ],
    "tgn:id":7140989,
    "tgn:name":"Bahnhof Lippstadt-Nord",
    "tgn:placetype":[
        "aat:300007783"
    ]
},
  "bbox": [],
  "geometry": {"coordinates":[8.35,51.683333],"type":"Point"}
}