{
  "id": 7206988,
  "type": "Feature",
  "properties": {
    "tgn:hierarchy":[
        "tgn:7206988",
        "tgn:7003669",
        "tgn:1000003",
        "tgn:7000084",
        "tgn:7029392"
    ],
    "tgn:id":7206988,
    "tgn:name":"Dachsbau",
    "tgn:placetype":[
        "aat:300008863"
    ]
},
  "bbox": [],
  "geometry": {"coordinates":[11.95,49.816667],"type":"Point"}
}