{
  "id": 2145343,
  "type": "Feature",
  "properties": {
    "tgn:hierarchy":[
        "tgn:2145343",
        "tgn:1000001",
        "tgn:2000922",
        "tgn:7012149",
        "tgn:7007515",
        "tgn:7029392"
    ],
    "tgn:id":2145343,
    "tgn:name":"Bald Porcupine Island",
    "tgn:placetype":[
        "aat:300008791"
    ]
},
  "bbox": [],
  "geometry": {"coordinates":[-68.1667,44.3833],"type":"Point"}
}