{
  "id": 7316119,
  "type": "Feature",
  "properties": {
    "tgn:hierarchy":[
        "tgn:7316119",
        "tgn:1001702",
        "tgn:1000049",
        "tgn:1000002",
        "tgn:7029392"
    ],
    "tgn:id":7316119,
    "tgn:name":"Carlos, Caleta",
    "tgn:placetype":[
        "aat:300132317"
    ]
},
  "bbox": [],
  "geometry": {"coordinates":[-66.55,-55.166667],"type":"Point"}
}