{
  "id": 1127387,
  "type": "Feature",
  "properties": {
    "tgn:hierarchy":[
        "tgn:1127387",
        "tgn:1000001",
        "tgn:7029392"
    ],
    "tgn:id":1127387,
    "tgn:name":"Motagua, R\u00edo",
    "tgn:placetype":[
        "aat:300008707"
    ]
},
  "bbox": [],
  "geometry": {"coordinates":[-88.2333,15.7333],"type":"Point"}
}