{
  "id": 2454216,
  "type": "Feature",
  "properties": {
    "tgn:hierarchy":[
        "tgn:2454216",
        "tgn:1000001",
        "tgn:7012149",
        "tgn:2002111",
        "tgn:7007827",
        "tgn:7029392"
    ],
    "tgn:id":2454216,
    "tgn:name":"Little Creek",
    "tgn:placetype":[
        "aat:300008706"
    ]
},
  "bbox": [],
  "geometry": {"coordinates":[-112.6167,37.8333],"type":"Point"}
}