{
  "id": 7072620,
  "type": "Feature",
  "properties": {
    "tgn:hierarchy":[
        "tgn:7072620",
        "tgn:7003669",
        "tgn:1000003",
        "tgn:7000084",
        "tgn:7029392"
    ],
    "tgn:id":7072620,
    "tgn:name":"Thalhausen",
    "tgn:placetype":[
        "aat:300000206"
    ]
},
  "bbox": [],
  "geometry": {"coordinates":[12.75,47.85],"type":"Point"}
}