{
  "id": 2451516,
  "type": "Feature",
  "properties": {
    "tgn:hierarchy":[
        "tgn:2451516",
        "tgn:1000001",
        "tgn:7012149",
        "tgn:2000903",
        "tgn:7007256",
        "tgn:7029392"
    ],
    "tgn:id":2451516,
    "tgn:name":"Little Bayou Sorrel",
    "tgn:placetype":[
        "aat:300008699"
    ]
},
  "bbox": [],
  "geometry": {"coordinates":[-91.2833,29.7833],"type":"Point"}
}