{
  "id": 2419816,
  "type": "Feature",
  "properties": {
    "tgn:hierarchy":[
        "tgn:2419816",
        "tgn:7006450",
        "tgn:1000001",
        "tgn:7012149",
        "tgn:2124014",
        "tgn:7029392"
    ],
    "tgn:id":2419816,
    "tgn:name":"Jay Creek",
    "tgn:placetype":[
        "aat:300008706"
    ]
},
  "bbox": [],
  "geometry": {"coordinates":[-157.0167,67.0333],"type":"Point"}
}