{
  "id": 7119764,
  "type": "Feature",
  "properties": {
    "tgn:hierarchy":[
        "tgn:7119764",
        "tgn:7003712",
        "tgn:7003670",
        "tgn:1000003",
        "tgn:7000084",
        "tgn:7029392"
    ],
    "tgn:id":7119764,
    "tgn:name":"Pl\u00f6tzensee",
    "tgn:placetype":[
        "aat:300008680"
    ]
},
  "bbox": [],
  "geometry": {"coordinates":[13.333333,52.55],"type":"Point"}
}