{
  "id": 1132779,
  "type": "Feature",
  "properties": {
    "tgn:hierarchy":[
        "tgn:1132779",
        "tgn:1000001",
        "tgn:1002666",
        "tgn:7012149",
        "tgn:7007565",
        "tgn:7029392"
    ],
    "tgn:id":1132779,
    "tgn:name":"Cheesequake Creek",
    "tgn:placetype":[
        "aat:300008706"
    ]
},
  "bbox": [],
  "geometry": {"coordinates":[-74.2833,40.4333],"type":"Point"}
}