<<<<<<< HEAD
{
  "id": 2254615,
  "type": "Feature",
  "properties": {
    "tgn:hierarchy":[
        "tgn:2254615",
        "tgn:1000001",
        "tgn:2002255",
        "tgn:7012149",
        "tgn:7013961",
        "tgn:7029392"
    ],
    "tgn:id":2254615,
    "tgn:name":"Coon Hollow",
    "tgn:placetype":[
        "aat:300008761"
    ]
},
  "bbox": [],
  "geometry": {"coordinates":[-81.9333,38.1167],"type":"Point"}
}
=======
{"geometry":{"type":"Point","coordinates":[-81.933300,38.116700]},"type":"Feature","properties":{"hierarchy":["tgn:2254615","tgn:1000001","tgn:2002255","tgn:7012149","tgn:7013961","tgn:7029392"],"placetype":["aat:300008761"],"id":2254615,"name:xx":"Coon Hollow"}}
>>>>>>> 03f74aca74312dbeaf24d7e61306dd6a786dc3d0
