{
  "id": 7224689,
  "type": "Feature",
  "properties": {
    "tgn:hierarchy":[
        "tgn:7224689",
        "tgn:7011170",
        "tgn:7002715",
        "tgn:1000003",
        "tgn:1000074",
        "tgn:7029392"
    ],
    "tgn:id":7224689,
    "tgn:name":"Strofa\u00ed",
    "tgn:placetype":[
        "aat:300008057"
    ]
},
  "bbox": [],
  "geometry": {"coordinates":[24.383333,41.45],"type":"Point"}
}