<<<<<<< HEAD
{
  "id": 7178631,
  "type": "Feature",
  "properties": {
    "tgn:hierarchy":[
        "tgn:7178631",
        "tgn:1000003",
        "tgn:7003685",
        "tgn:7000084",
        "tgn:7029392"
    ],
    "tgn:id":7178631,
    "tgn:name":"G\u00fchren-Berg",
    "tgn:placetype":[
        "aat:300008777"
    ]
},
  "bbox": [],
  "geometry": {"coordinates":[13.616667,51.283333],"type":"Point"}
}
=======
{"geometry":{"type":"Point","coordinates":[13.616667,51.283333]},"type":"Feature","properties":{"hierarchy":["tgn:7178631","tgn:1000003","tgn:7003685","tgn:7000084","tgn:7029392"],"placetype":["aat:300008777"],"id":7178631,"name:xx":"G\u00fchren-Berg"}}
>>>>>>> 03f74aca74312dbeaf24d7e61306dd6a786dc3d0
