{
  "id": 2709134,
  "type": "Feature",
  "properties": {
    "tgn:hierarchy":[
        "tgn:2709134",
        "tgn:1000001",
        "tgn:7012149",
        "tgn:2002123",
        "tgn:7007827",
        "tgn:7029392"
    ],
    "tgn:id":2709134,
    "tgn:name":"Tabbys Peak",
    "tgn:placetype":[
        "aat:300008798"
    ]
},
  "bbox": [],
  "geometry": {"coordinates":[-112.9833,40.45],"type":"Point"}
}