{
  "id": 7370866,
  "type": "Feature",
  "properties": {
    "tgn:hierarchy":[
        "tgn:7370866",
        "tgn:1000001",
        "tgn:7005597",
        "tgn:7005560",
        "tgn:7029392"
    ],
    "tgn:id":7370866,
    "tgn:name":"G\u00f3mez Far\u00edas",
    "tgn:placetype":[
        "aat:300008347"
    ]
},
  "bbox": [],
  "geometry": {"coordinates":[-99.15,23.05],"type":"Point"}
}