{
  "id": 2208670,
  "type": "Feature",
  "properties": {
    "tgn:hierarchy":[
        "tgn:2208670",
        "tgn:1000001",
        "tgn:1002218",
        "tgn:7012149",
        "tgn:7007157",
        "tgn:7029392"
    ],
    "tgn:id":2208670,
    "tgn:name":"Burns Government Lateral",
    "tgn:placetype":[
        "aat:300006075"
    ]
},
  "bbox": [],
  "geometry": {"coordinates":[-121.7333,39.45],"type":"Point"}
}