<<<<<<< HEAD
{
  "id": 2253021,
  "type": "Feature",
  "properties": {
    "tgn:hierarchy":[
        "tgn:2253021",
        "tgn:1000001",
        "tgn:7012149",
        "tgn:1002459",
        "tgn:7007706",
        "tgn:7029392"
    ],
    "tgn:id":2253021,
    "tgn:name":"Consolidation Coal Company Pond",
    "tgn:placetype":[
        "aat:300006191"
    ]
},
  "bbox": [],
  "geometry": {"coordinates":[-80.9,40.2667],"type":"Point"}
}
=======
{"geometry":{"type":"Point","coordinates":[-80.900000,40.266700]},"type":"Feature","properties":{"hierarchy":["tgn:2253021","tgn:1000001","tgn:7012149","tgn:1002459","tgn:7007706","tgn:7029392"],"placetype":["aat:300006191"],"id":2253021,"name:xx":"Consolidation Coal Company Pond"}}
>>>>>>> 03f74aca74312dbeaf24d7e61306dd6a786dc3d0
