{
  "id": 3000560,
  "type": "Feature",
  "properties": {
    "tgn:hierarchy":[
        "tgn:3000560",
        "tgn:1003483",
        "tgn:1000003",
        "tgn:7003240",
        "tgn:1000080",
        "tgn:7029392"
    ],
    "tgn:id":3000560,
    "tgn:name":"Farneto",
    "tgn:placetype":[
        "aat:300008347"
    ]
},
  "bbox": [],
  "geometry": {"coordinates":[11.466667,44.35],"type":"Point"}
}