{
  "id": 1117440,
  "type": "Feature",
  "properties": {
    "tgn:hierarchy":[
        "tgn:1117440",
        "tgn:7005685",
        "tgn:1000001",
        "tgn:7013154",
        "tgn:7029392"
    ],
    "tgn:id":1117440,
    "tgn:name":"Nameigos Lake",
    "tgn:placetype":[
        "aat:300008680"
    ]
},
  "bbox": [],
  "geometry": {"coordinates":[-84.7167,48.7667],"type":"Point"}
}