{
  "id": 2567573,
  "type": "Feature",
  "properties": {
    "tgn:hierarchy":[
        "tgn:2567573",
        "tgn:1000001",
        "tgn:7013649",
        "tgn:7012149",
        "tgn:7007251",
        "tgn:7029392"
    ],
    "tgn:id":2567573,
    "tgn:name":"Papoose Lake",
    "tgn:placetype":[
        "aat:300008680"
    ]
},
  "bbox": [],
  "geometry": {"coordinates":[-87.85,41.65],"type":"Point"}
}