{
  "id": 7453756,
  "type": "Feature",
  "properties": {
    "tgn:hierarchy":[
        "tgn:7453756",
        "tgn:7002445",
        "tgn:1000003",
        "tgn:7012031",
        "tgn:7008591",
        "tgn:7029392"
    ],
    "tgn:id":7453756,
    "tgn:name:en":"Chipping Warden",
    "tgn:placetype":[
        "aat:300008347"
    ]
},
  "bbox": [],
  "geometry": {"coordinates":[-1.266667,52.116667],"type":"Point"}
}