{
  "id": 2597535,
  "type": "Feature",
  "properties": {
    "tgn:hierarchy":[
        "tgn:2597535",
        "tgn:1000001",
        "tgn:7006451",
        "tgn:7012149",
        "tgn:2000099",
        "tgn:7029392"
    ],
    "tgn:id":2597535,
    "tgn:name":"Prairie Pit Tank",
    "tgn:placetype":[
        "aat:300006191"
    ]
},
  "bbox": [],
  "geometry": {"coordinates":[-109.9167,33.6167],"type":"Point"}
}