{
  "id": 2615633,
  "type": "Feature",
  "properties": {
    "tgn:hierarchy":[
        "tgn:2615633",
        "tgn:1000001",
        "tgn:7012149",
        "tgn:7007524",
        "tgn:7029392"
    ],
    "tgn:id":2615633,
    "tgn:name":"Review Mountain",
    "tgn:placetype":[
        "aat:300266640"
    ]
},
  "bbox": [],
  "geometry": {"coordinates":[-114.6667,48.9167],"type":"Point"}
}