{
  "id": 2302366,
  "type": "Feature",
  "properties": {
    "tgn:hierarchy":[
        "tgn:2302366",
        "tgn:1000001",
        "tgn:7012149",
        "tgn:1002624",
        "tgn:7007568",
        "tgn:7029392"
    ],
    "tgn:id":2302366,
    "tgn:name":"Dutch Settlement Creek",
    "tgn:placetype":[
        "aat:300008706"
    ]
},
  "bbox": [],
  "geometry": {"coordinates":[-75.7167,43.05],"type":"Point"}
}