{
  "id": 2269572,
  "type": "Feature",
  "properties": {
    "tgn:hierarchy":[
        "tgn:2269572",
        "tgn:1000001",
        "tgn:2001418",
        "tgn:7012149",
        "tgn:7007526",
        "tgn:7029392"
    ],
    "tgn:id":2269572,
    "tgn:name":"Crowell Mine",
    "tgn:placetype":[
        "aat:300000390"
    ]
},
  "bbox": [],
  "geometry": {"coordinates":[-116.6833,36.8667],"type":"Point"}
}