{
  "id": 7495133,
  "type": "Feature",
  "properties": {
    "tgn:hierarchy":[
        "tgn:7495133",
        "tgn:7488858",
        "tgn:1000004",
        "tgn:1000141",
        "tgn:7029392"
    ],
    "tgn:id":7495133,
    "tgn:name":"Buzhongyang",
    "tgn:placetype":[
        "aat:300387033"
    ]
},
  "bbox": [],
  "geometry": {"coordinates":[120.650846,23.812484],"type":"Point"}
}