{
  "id": 2623745,
  "type": "Feature",
  "properties": {
    "tgn:hierarchy":[
        "tgn:2623745",
        "tgn:1000001",
        "tgn:7012149",
        "tgn:2001851",
        "tgn:7007825",
        "tgn:7029392"
    ],
    "tgn:id":2623745,
    "tgn:name":"Rock Creek",
    "tgn:placetype":[
        "aat:300008706"
    ]
},
  "bbox": [],
  "geometry": {"coordinates":[-82.9333,35.8833],"type":"Point"}
}