{
  "id": 2594037,
  "type": "Feature",
  "properties": {
    "tgn:hierarchy":[
        "tgn:2594037",
        "tgn:1000001",
        "tgn:1002271",
        "tgn:7012149",
        "tgn:7007920",
        "tgn:7029392"
    ],
    "tgn:id":2594037,
    "tgn:name":"Portage Head",
    "tgn:placetype":[
        "aat:300008850"
    ]
},
  "bbox": [],
  "geometry": {"coordinates":[-124.6833,48.2833],"type":"Point"}
}