{
  "id": 2744923,
  "type": "Feature",
  "properties": {
    "tgn:hierarchy":[
        "tgn:2744923",
        "tgn:1000001",
        "tgn:7012149",
        "tgn:2001036",
        "tgn:7007521",
        "tgn:7029392"
    ],
    "tgn:id":2744923,
    "tgn:name":"Vierge Lake",
    "tgn:placetype":[
        "aat:300008680"
    ]
},
  "bbox": [],
  "geometry": {"coordinates":[-91.0167,48.0333],"type":"Point"}
}