{
  "id": 7263655,
  "type": "Feature",
  "properties": {
    "tgn:hierarchy":[
        "tgn:7263655",
        "tgn:7003616",
        "tgn:1000003",
        "tgn:7016845",
        "tgn:7029392"
    ],
    "tgn:id":7263655,
    "tgn:name:nl":"Kofmansbult",
    "tgn:placetype":[
        "aat:300387036"
    ]
},
  "bbox": [],
  "geometry": {"coordinates":[5.516667,53.466667],"type":"Point"}
}