<<<<<<< HEAD
{
  "id": 2154197,
  "type": "Feature",
  "properties": {
    "tgn:hierarchy":[
        "tgn:2154197",
        "tgn:1000001",
        "tgn:7012149",
        "tgn:2001103",
        "tgn:7007522",
        "tgn:7029392"
    ],
    "tgn:id":2154197,
    "tgn:name":"Bear Creek",
    "tgn:placetype":[
        "aat:300008706"
    ]
},
  "bbox": [],
  "geometry": {"coordinates":[-89.2333,31.0167],"type":"Point"}
}
=======
{"geometry":{"type":"Point","coordinates":[-89.233300,31.016700]},"type":"Feature","properties":{"hierarchy":["tgn:2154197","tgn:1000001","tgn:7012149","tgn:2001103","tgn:7007522","tgn:7029392"],"placetype":["aat:300008706"],"id":2154197,"name:xx":"Bear Creek"}}
>>>>>>> 03f74aca74312dbeaf24d7e61306dd6a786dc3d0
