{
  "id": 7054770,
  "type": "Feature",
  "properties": {
    "tgn:hierarchy":[
        "tgn:7054770",
        "tgn:7015163",
        "tgn:1000003",
        "tgn:7003121",
        "tgn:1000080",
        "tgn:7029392"
    ],
    "tgn:id":7054770,
    "tgn:name":"Padda, Porto di la",
    "tgn:placetype":[
        "aat:300132316"
    ]
},
  "bbox": [],
  "geometry": {"coordinates":[9.15,41.183333],"type":"Point"}
}