{
  "id": 2235983,
  "type": "Feature",
  "properties": {
    "tgn:hierarchy":[
        "tgn:2235983",
        "tgn:1000001",
        "tgn:1002480",
        "tgn:7012149",
        "tgn:7007564",
        "tgn:7029392"
    ],
    "tgn:id":2235983,
    "tgn:name":"Chevy Hill",
    "tgn:placetype":[
        "aat:300008798"
    ]
},
  "bbox": [],
  "geometry": {"coordinates":[-71.7667,43.0833],"type":"Point"}
}