{
  "id": 7449639,
  "type": "Feature",
  "properties": {
    "tgn:hierarchy":[
        "tgn:7449639",
        "tgn:7002444",
        "tgn:1000003",
        "tgn:7009907",
        "tgn:7008591",
        "tgn:7029392"
    ],
    "tgn:id":7449639,
    "tgn:name:en":"Glendye Lodge",
    "tgn:placetype":[
        "aat:300004792"
    ]
},
  "bbox": [],
  "geometry": {"coordinates":[-2.583333,58.966667],"type":"Point"}
}