{
  "id": 1019723,
  "type": "Feature",
  "properties": {
    "tgn:hierarchy":[
        "tgn:1019723",
        "tgn:7006477",
        "tgn:1001375",
        "tgn:1000002",
        "tgn:7029392"
    ],
    "tgn:id":1019723,
    "tgn:name":"Macach\u00edn",
    "tgn:placetype":[
        "aat:300008347"
    ]
},
  "bbox": [],
  "geometry": {"coordinates":[-63.65,-37.15],"type":"Point"}
}