{
  "id": 1117798,
  "type": "Feature",
  "properties": {
    "tgn:hierarchy":[
        "tgn:1117798",
        "tgn:1000003",
        "tgn:7003155",
        "tgn:7003122",
        "tgn:1000080",
        "tgn:7029392"
    ],
    "tgn:id":1117798,
    "tgn:name":"Pozzillo, Lago di",
    "tgn:placetype":[
        "aat:300008680"
    ]
},
  "bbox": [],
  "geometry": {"coordinates":[14.5833,37.6667],"type":"Point"}
}