{
  "id": 2273183,
  "type": "Feature",
  "properties": {
    "tgn:hierarchy":[
        "tgn:2273183",
        "tgn:1000001",
        "tgn:2000306",
        "tgn:7012149",
        "tgn:7007248",
        "tgn:7029392"
    ],
    "tgn:id":2273183,
    "tgn:name":"Cypress Bay",
    "tgn:placetype":[
        "aat:300008905"
    ]
},
  "bbox": [],
  "geometry": {"coordinates":[-81.5333,32.0833],"type":"Point"}
}