<<<<<<< HEAD
{
  "id": 2409990,
  "type": "Feature",
  "properties": {
    "tgn:hierarchy":[
        "tgn:2409990",
        "tgn:1000001",
        "tgn:7012149",
        "tgn:7007826",
        "tgn:7029392"
    ],
    "tgn:id":2409990,
    "tgn:name":"Imperialist Creek",
    "tgn:placetype":[
        "aat:300008706"
    ]
},
  "bbox": [],
  "geometry": {"coordinates":[-100.3833,29.2833],"type":"Point"}
}
=======
{"geometry":{"type":"Point","coordinates":[-100.383300,29.283300]},"type":"Feature","properties":{"hierarchy":["tgn:2409990","tgn:1000001","tgn:7012149","tgn:7007826","tgn:7029392"],"placetype":["aat:300008706"],"id":2409990,"name:xx":"Imperialist Creek"}}
>>>>>>> 03f74aca74312dbeaf24d7e61306dd6a786dc3d0
