{
  "id": 7443975,
  "type": "Feature",
  "properties": {
    "tgn:hierarchy":[
        "tgn:7443975",
        "tgn:7019140",
        "tgn:7002444",
        "tgn:1000003",
        "tgn:7008591",
        "tgn:7029392"
    ],
    "tgn:id":7443975,
    "tgn:name:en":"Unich, Water of",
    "tgn:placetype":[
        "aat:300008699"
    ]
},
  "bbox": [],
  "geometry": {"coordinates":[-2.966667,56.883333],"type":"Point"}
}