{
  "id": 7139656,
  "type": "Feature",
  "properties": {
    "tgn:hierarchy":[
        "tgn:7139656",
        "tgn:7003669",
        "tgn:1000003",
        "tgn:7000084",
        "tgn:7029392"
    ],
    "tgn:id":7139656,
    "tgn:name":"Laufzorn",
    "tgn:placetype":[
        "aat:300008347"
    ]
},
  "bbox": [],
  "geometry": {"coordinates":[11.55,48.016667],"type":"Point"}
}