{
  "id": 2398725,
  "type": "Feature",
  "properties": {
    "tgn:hierarchy":[
        "tgn:2398725",
        "tgn:1000001",
        "tgn:7012149",
        "tgn:2002250",
        "tgn:7007920",
        "tgn:7029392"
    ],
    "tgn:id":2398725,
    "tgn:name":"Hope Creek",
    "tgn:placetype":[
        "aat:300008706"
    ]
},
  "bbox": [],
  "geometry": {"coordinates":[-118.0167,48.8667],"type":"Point"}
}