{
  "id": 2284638,
  "type": "Feature",
  "properties": {
    "tgn:hierarchy":[
        "tgn:2284638",
        "tgn:1000001",
        "tgn:7012149",
        "tgn:7007526",
        "tgn:7029392"
    ],
    "tgn:id":2284638,
    "tgn:name":"Desert Range",
    "tgn:placetype":[
        "aat:300386831"
    ]
},
  "bbox": [],
  "geometry": {"coordinates":[-115.3333,36.8333],"type":"Point"}
}