<<<<<<< HEAD
{
  "id": 2761395,
  "type": "Feature",
  "properties": {
    "tgn:hierarchy":[
        "tgn:2761395",
        "tgn:1000001",
        "tgn:7016172",
        "tgn:7012149",
        "tgn:2000176",
        "tgn:7029392"
    ],
    "tgn:id":2761395,
    "tgn:name":"West Mountain",
    "tgn:placetype":[
        "aat:300008798"
    ]
},
  "bbox": [],
  "geometry": {"coordinates":[-94.2,35.9],"type":"Point"}
}
=======
{"geometry":{"type":"Point","coordinates":[-94.200000,35.900000]},"type":"Feature","properties":{"hierarchy":["tgn:2761395","tgn:1000001","tgn:7016172","tgn:7012149","tgn:2000176","tgn:7029392"],"placetype":["aat:300008798"],"id":2761395,"name:xx":"West Mountain"}}
>>>>>>> 03f74aca74312dbeaf24d7e61306dd6a786dc3d0
