{
  "id": 7304407,
  "type": "Feature",
  "properties": {
    "tgn:hierarchy":[
        "tgn:7304407",
        "tgn:7002758",
        "tgn:7002823",
        "tgn:1000003",
        "tgn:1000095",
        "tgn:7029392"
    ],
    "tgn:id":7304407,
    "tgn:name":"Linares de la Sierra",
    "tgn:placetype":[
        "aat:300008347"
    ]
},
  "bbox": [],
  "geometry": {"coordinates":[-6.616667,37.883333],"type":"Point"}
}