{
  "id": 7389276,
  "type": "Feature",
  "properties": {
    "tgn:hierarchy":[
        "tgn:7389276",
        "tgn:1000001",
        "tgn:1001960",
        "tgn:7005560",
        "tgn:7029392"
    ],
    "tgn:id":7389276,
    "tgn:name":"Rancho El Pozo",
    "tgn:placetype":[
        "aat:300008347"
    ]
},
  "bbox": [],
  "geometry": {"coordinates":[-111.016667,27.966667],"type":"Point"}
}