{
  "id": 7563478,
  "type": "Feature",
  "properties": {
    "tgn:hierarchy":[
        "tgn:7563478",
        "tgn:1000004",
        "tgn:7000198",
        "tgn:7016788",
        "tgn:7029392"
    ],
    "tgn:id":7563478,
    "tgn:name:en":"Gul\u0101bgarh",
    "tgn:placetype":[
        "aat:300008347"
    ]
},
  "bbox": [],
  "geometry": {"coordinates":[74.21656,28.956589],"type":"Point"}
}