{
  "id": 2487270,
  "type": "Feature",
  "properties": {
    "tgn:hierarchy":[
        "tgn:2487270",
        "tgn:1000001",
        "tgn:7012149",
        "tgn:2000413",
        "tgn:7007248",
        "tgn:7029392"
    ],
    "tgn:id":2487270,
    "tgn:name":"Lees Lake",
    "tgn:placetype":[
        "aat:300006191"
    ]
},
  "bbox": [],
  "geometry": {"coordinates":[-84.0333,33.6833],"type":"Point"}
}