{
  "id": 1062599,
  "type": "Feature",
  "properties": {
    "tgn:hierarchy":[
        "tgn:1062599",
        "tgn:7001165",
        "tgn:1000003",
        "tgn:7002793",
        "tgn:1000095",
        "tgn:7029392"
    ],
    "tgn:id":1062599,
    "tgn:name":"Vall de Ux\u00f3",
    "tgn:placetype":[
        "aat:300008347"
    ]
},
  "bbox": [],
  "geometry": {"coordinates":[-0.233333,39.816667],"type":"Point"}
}