{
  "id": 7358184,
  "type": "Feature",
  "properties": {
    "tgn:hierarchy":[
        "tgn:7358184",
        "tgn:1000001",
        "tgn:1001893",
        "tgn:7005560",
        "tgn:7029392"
    ],
    "tgn:id":7358184,
    "tgn:name":"Coyamito",
    "tgn:placetype":[
        "aat:300387200"
    ]
},
  "bbox": [],
  "geometry": {"coordinates":[-105.066667,29.483333],"type":"Point"}
}