{
  "id": 2361527,
  "type": "Feature",
  "properties": {
    "tgn:hierarchy":[
        "tgn:2361527",
        "tgn:1000001",
        "tgn:7012149",
        "tgn:2001927",
        "tgn:7007825",
        "tgn:7029392"
    ],
    "tgn:id":2361527,
    "tgn:name":"Graves Hollow",
    "tgn:placetype":[
        "aat:300008761"
    ]
},
  "bbox": [],
  "geometry": {"coordinates":[-87.6667,35.45],"type":"Point"}
}