<<<<<<< HEAD
{
  "id": 2408525,
  "type": "Feature",
  "properties": {
    "tgn:hierarchy":[
        "tgn:2408525",
        "tgn:7006450",
        "tgn:1000001",
        "tgn:7012149",
        "tgn:2000089",
        "tgn:7029392"
    ],
    "tgn:id":2408525,
    "tgn:name":"Hutlinana Creek",
    "tgn:placetype":[
        "aat:300008706"
    ]
},
  "bbox": [],
  "geometry": {"coordinates":[-149.8333,65.3167],"type":"Point"}
}
=======
{"geometry":{"type":"Point","coordinates":[-149.833300,65.316700]},"type":"Feature","properties":{"hierarchy":["tgn:2408525","tgn:7006450","tgn:1000001","tgn:7012149","tgn:2000089","tgn:7029392"],"placetype":["aat:300008706"],"id":2408525,"name:xx":"Hutlinana Creek"}}
>>>>>>> 03f74aca74312dbeaf24d7e61306dd6a786dc3d0
