{
  "id": 2567968,
  "type": "Feature",
  "properties": {
    "tgn:hierarchy":[
        "tgn:2567968",
        "tgn:1000001",
        "tgn:7012149",
        "tgn:7007157",
        "tgn:2000185",
        "tgn:7029392"
    ],
    "tgn:id":2567968,
    "tgn:name":"Paradise Valley",
    "tgn:placetype":[
        "aat:300008761"
    ]
},
  "bbox": [],
  "geometry": {"coordinates":[-123.1833,39.6667],"type":"Point"}
}