{
  "id": 2355525,
  "type": "Feature",
  "properties": {
    "tgn:hierarchy":[
        "tgn:2355525",
        "tgn:1000001",
        "tgn:2001176",
        "tgn:7012149",
        "tgn:7007523",
        "tgn:7029392"
    ],
    "tgn:id":2355525,
    "tgn:name":"Goose Creek",
    "tgn:placetype":[
        "aat:300008706"
    ]
},
  "bbox": [],
  "geometry": {"coordinates":[-90.5167,36.8833],"type":"Point"}
}