{
  "id": 2225766,
  "type": "Feature",
  "properties": {
    "tgn:hierarchy":[
        "tgn:2225766",
        "tgn:7019618",
        "tgn:1000001",
        "tgn:7012149",
        "tgn:7007564",
        "tgn:7029392"
    ],
    "tgn:id":2225766,
    "tgn:name":"Cat Den Mountain",
    "tgn:placetype":[
        "aat:300008798"
    ]
},
  "bbox": [],
  "geometry": {"coordinates":[-72.45,42.7667],"type":"Point"}
}