{
  "id": 7472196,
  "type": "Feature",
  "properties": {
    "tgn:hierarchy":[
        "tgn:7472196",
        "tgn:1000004",
        "tgn:7467799",
        "tgn:1000141",
        "tgn:7029392"
    ],
    "tgn:id":7472196,
    "tgn:name":"Yuanjia Qiao",
    "tgn:placetype":[
        "aat:300007836"
    ]
},
  "bbox": [],
  "geometry": {"coordinates":[120.4335,23.8989],"type":"Point"}
}