<<<<<<< HEAD
{
  "id": 7472196,
  "type": "Feature",
  "properties": {
    "tgn:hierarchy":[
        "tgn:7472196",
        "tgn:1000004",
        "tgn:7467799",
        "tgn:1000141",
        "tgn:7029392"
    ],
    "tgn:id":7472196,
    "tgn:name":"Yuanjia Qiao",
    "tgn:placetype":[
        "aat:300007836"
    ]
},
  "bbox": [],
  "geometry": {"coordinates":[120.4335,23.8989],"type":"Point"}
}
=======
{"geometry":{"type":"Point","coordinates":[120.433500,23.898900]},"type":"Feature","properties":{"hierarchy":["tgn:7472196","tgn:1000004","tgn:7467799","tgn:1000141","tgn:7029392"],"placetype":["aat:300007836"],"id":7472196,"name:xx":"Yuanjia Qiao"}}
>>>>>>> 03f74aca74312dbeaf24d7e61306dd6a786dc3d0
