{
  "id": 1017770,
  "type": "Feature",
  "properties": {
    "tgn:hierarchy":[
        "tgn:1017770",
        "tgn:1000001",
        "tgn:7005589",
        "tgn:7005560",
        "tgn:7029392"
    ],
    "tgn:id":1017770,
    "tgn:name":"Linares",
    "tgn:placetype":[
        "aat:300008347"
    ]
},
  "bbox": [],
  "geometry": {"coordinates":[-99.567778,24.857778],"type":"Point"}
}