{
  "id": 2388318,
  "type": "Feature",
  "properties": {
    "tgn:hierarchy":[
        "tgn:2388318",
        "tgn:1000001",
        "tgn:7012149",
        "tgn:2002030",
        "tgn:7007826",
        "tgn:7029392"
    ],
    "tgn:id":2388318,
    "tgn:name":"Hickory Mountain Branch",
    "tgn:placetype":[
        "aat:300008699"
    ]
},
  "bbox": [],
  "geometry": {"coordinates":[-98.7167,30.6333],"type":"Point"}
}