{
  "id": 7019720,
  "type": "Feature",
  "properties": {
    "tgn:hierarchy":[
        "tgn:7019720",
        "tgn:2002365",
        "tgn:1000001",
        "tgn:7012149",
        "tgn:7007923",
        "tgn:7029392"
    ],
    "tgn:id":7019720,
    "tgn:name":"Lone Tree Reservoir Number 1",
    "tgn:placetype":[
        "aat:300006191"
    ]
},
  "bbox": [],
  "geometry": {"coordinates":[-105.75,41.0833],"type":"Point"}
}