<<<<<<< HEAD
{
  "id": 7474207,
  "type": "Feature",
  "properties": {
    "tgn:hierarchy":[
        "tgn:7474207",
        "tgn:1000004",
        "tgn:1000454",
        "tgn:1000141",
        "tgn:7029392"
    ],
    "tgn:id":7474207,
    "tgn:name":"Huoyan Shan",
    "tgn:placetype":[
        "aat:300008798"
    ]
},
  "bbox": [],
  "geometry": {"coordinates":[121.665922,24.917639],"type":"Point"}
}
=======
{"geometry":{"type":"Point","coordinates":[121.665922,24.917639]},"type":"Feature","properties":{"hierarchy":["tgn:7474207","tgn:1000004","tgn:1000454","tgn:1000141","tgn:7029392"],"placetype":["aat:300008798"],"id":7474207,"name:xx":"Huoyan Shan"}}
>>>>>>> 03f74aca74312dbeaf24d7e61306dd6a786dc3d0
