{
  "id": 2733940,
  "type": "Feature",
  "properties": {
    "tgn:hierarchy":[
        "tgn:2733940",
        "tgn:1002201",
        "tgn:1000001",
        "tgn:7012149",
        "tgn:7007517",
        "tgn:7029392"
    ],
    "tgn:id":2733940,
    "tgn:name":"Turner Pond",
    "tgn:placetype":[
        "aat:300006191"
    ]
},
  "bbox": [],
  "geometry": {"coordinates":[-70.9667,41.6667],"type":"Point"}
}