<<<<<<< HEAD
{
  "id": 2767377,
  "type": "Feature",
  "properties": {
    "tgn:hierarchy":[
        "tgn:2767377",
        "tgn:1000001",
        "tgn:7006451",
        "tgn:7012149",
        "tgn:2000103",
        "tgn:7029392"
    ],
    "tgn:id":2767377,
    "tgn:name":"White Spar Mine",
    "tgn:placetype":[
        "aat:300000390"
    ]
},
  "bbox": [],
  "geometry": {"coordinates":[-112.5333,34.4167],"type":"Point"}
}
=======
{"geometry":{"type":"Point","coordinates":[-112.533300,34.416700]},"type":"Feature","properties":{"hierarchy":["tgn:2767377","tgn:1000001","tgn:7006451","tgn:7012149","tgn:2000103","tgn:7029392"],"placetype":["aat:300000390"],"id":2767377,"name:xx":"White Spar Mine"}}
>>>>>>> 03f74aca74312dbeaf24d7e61306dd6a786dc3d0
