{
  "id": 2687890,
  "type": "Feature",
  "properties": {
    "tgn:hierarchy":[
        "tgn:2687890",
        "tgn:1000001",
        "tgn:7012149",
        "tgn:2001449",
        "tgn:7007566",
        "tgn:7029392"
    ],
    "tgn:id":2687890,
    "tgn:name":"Spring de la Jarita, Ca\u00f1ada",
    "tgn:placetype":[
        "aat:300008699"
    ]
},
  "bbox": [],
  "geometry": {"coordinates":[-106.0833,36.5667],"type":"Point"}
}