{
  "id": 2245182,
  "type": "Feature",
  "properties": {
    "tgn:hierarchy":[
        "tgn:2245182",
        "tgn:2001732",
        "tgn:1000001",
        "tgn:7012149",
        "tgn:7007712",
        "tgn:7029392"
    ],
    "tgn:id":2245182,
    "tgn:name":"Cloverleaf Mobile Home Park",
    "tgn:placetype":[
        "aat:300008347"
    ]
},
  "bbox": [],
  "geometry": {"coordinates":[-80.15,33.0333],"type":"Point"}
}