{
  "id": 7390999,
  "type": "Feature",
  "properties": {
    "tgn:hierarchy":[
        "tgn:7390999",
        "tgn:1000001",
        "tgn:7005601",
        "tgn:7005560",
        "tgn:7029392"
    ],
    "tgn:id":7390999,
    "tgn:name":"R\u00edo Toribio",
    "tgn:placetype":[
        "aat:300008347"
    ]
},
  "bbox": [],
  "geometry": {"coordinates":[-102.666667,23.783333],"type":"Point"}
}