{
  "id": 2348723,
  "type": "Feature",
  "properties": {
    "tgn:hierarchy":[
        "tgn:2348723",
        "tgn:1000001",
        "tgn:7012149",
        "tgn:7007158",
        "tgn:7029392"
    ],
    "tgn:id":2348723,
    "tgn:name":"Gibson Ditch",
    "tgn:placetype":[
        "aat:300006075"
    ]
},
  "bbox": [],
  "geometry": {"coordinates":[-105.8667,37.8167],"type":"Point"}
}