{
  "id": 7081219,
  "type": "Feature",
  "properties": {
    "tgn:hierarchy":[
        "tgn:7081219",
        "tgn:1000003",
        "tgn:7003676",
        "tgn:7000084",
        "tgn:7029392"
    ],
    "tgn:id":7081219,
    "tgn:name":"Woltershausen",
    "tgn:placetype":[
        "aat:300008347"
    ]
},
  "bbox": [],
  "geometry": {"coordinates":[9.95,51.983333],"type":"Point"}
}