{
  "id": 2656398,
  "type": "Feature",
  "properties": {
    "tgn:hierarchy":[
        "tgn:2656398",
        "tgn:1000001",
        "tgn:7012149",
        "tgn:1002516",
        "tgn:7007255",
        "tgn:7029392"
    ],
    "tgn:id":2656398,
    "tgn:name":"Sheckels Run",
    "tgn:placetype":[
        "aat:300008699"
    ]
},
  "bbox": [],
  "geometry": {"coordinates":[-85.4333,38.1167],"type":"Point"}
}