{
  "id": 2422829,
  "type": "Feature",
  "properties": {
    "tgn:hierarchy":[
        "tgn:2422829",
        "tgn:1000001",
        "tgn:2000108",
        "tgn:7016172",
        "tgn:7012149",
        "tgn:7029392"
    ],
    "tgn:id":2422829,
    "tgn:name":"Joe Creek",
    "tgn:placetype":[
        "aat:300008706"
    ]
},
  "bbox": [],
  "geometry": {"coordinates":[-93.9667,36.2667],"type":"Point"}
}