{
  "id": 2267088,
  "type": "Feature",
  "properties": {
    "tgn:hierarchy":[
        "tgn:2267088",
        "tgn:1000001",
        "tgn:7012149",
        "tgn:2001863",
        "tgn:7007825",
        "tgn:7029392"
    ],
    "tgn:id":2267088,
    "tgn:name":"Creswell Lake Number Twenty-nine",
    "tgn:placetype":[
        "aat:300006191"
    ]
},
  "bbox": [],
  "geometry": {"coordinates":[-88.7167,35.95],"type":"Point"}
}