{
  "id": 2718009,
  "type": "Feature",
  "properties": {
    "tgn:hierarchy":[
        "tgn:2718009",
        "tgn:7002659",
        "tgn:1000001",
        "tgn:7012149",
        "tgn:2000051",
        "tgn:7029392"
    ],
    "tgn:id":2718009,
    "tgn:name":"Thompson Branch",
    "tgn:placetype":[
        "aat:300008699"
    ]
},
  "bbox": [],
  "geometry": {"coordinates":[-86.8167,34.3833],"type":"Point"}
}