{
  "id": 7345712,
  "type": "Feature",
  "properties": {
    "tgn:hierarchy":[
        "tgn:7345712",
        "tgn:7002803",
        "tgn:1001647",
        "tgn:1000003",
        "tgn:1000095",
        "tgn:7029392"
    ],
    "tgn:id":7345712,
    "tgn:name":"Albojarico",
    "tgn:placetype":[
        "aat:300008347"
    ]
},
  "bbox": [],
  "geometry": {"coordinates":[-1.633333,38.583333],"type":"Point"}
}