{
  "id": 2559331,
  "type": "Feature",
  "properties": {
    "tgn:hierarchy":[
        "tgn:2559331",
        "tgn:1000001",
        "tgn:7012149",
        "tgn:1003026",
        "tgn:7007826",
        "tgn:7029392"
    ],
    "tgn:id":2559331,
    "tgn:name":"Onion Branch",
    "tgn:placetype":[
        "aat:300008699"
    ]
},
  "bbox": [],
  "geometry": {"coordinates":[-97.7167,30.55],"type":"Point"}
}