{
  "id": 7252084,
  "type": "Feature",
  "properties": {
    "tgn:hierarchy":[
        "tgn:7252084",
        "tgn:7003466",
        "tgn:1000003",
        "tgn:1000063",
        "tgn:4012014",
        "tgn:7029392"
    ],
    "tgn:id":7252084,
    "tgn:name":"Melin",
    "tgn:placetype":[
        "aat:300008347"
    ]
},
  "bbox": [],
  "geometry": {"coordinates":[4.8701,50.246812],"type":"Point"}
}