{
  "id": 2129286,
  "type": "Feature",
  "properties": {
    "tgn:hierarchy":[
        "tgn:2129286",
        "tgn:1000001",
        "tgn:2001005",
        "tgn:7012149",
        "tgn:7007521",
        "tgn:7029392"
    ],
    "tgn:id":2129286,
    "tgn:name":"Alice Lake",
    "tgn:placetype":[
        "aat:300008680"
    ]
},
  "bbox": [],
  "geometry": {"coordinates":[-93.7833,44.1167],"type":"Point"}
}