{
  "id": 2339812,
  "type": "Feature",
  "properties": {
    "tgn:hierarchy":[
        "tgn:2339812",
        "tgn:1000001",
        "tgn:7012149",
        "tgn:7007157",
        "tgn:1002608",
        "tgn:7029392"
    ],
    "tgn:id":2339812,
    "tgn:name":"Freeman Canyon",
    "tgn:placetype":[
        "aat:300008761"
    ]
},
  "bbox": [],
  "geometry": {"coordinates":[-118.85,34.7667],"type":"Point"}
}