{
  "id": 1002773,
  "type": "Feature",
  "properties": {
    "tgn:hierarchy":[
        "tgn:1002773",
        "tgn:1000001",
        "tgn:7012149",
        "tgn:7007240",
        "tgn:7029392"
    ],
    "tgn:id":1002773,
    "tgn:name":"Pasco",
    "tgn:placetype":[
        "aat:300387145",
        "aat:300000771"
    ]
},
  "bbox": [],
  "geometry": {"coordinates":[-82.4167,28.2833],"type":"Point"}
}