<<<<<<< HEAD
{
  "id": 2254097,
  "type": "Feature",
  "properties": {
    "tgn:hierarchy":[
        "tgn:2254097",
        "tgn:1000001",
        "tgn:7012149",
        "tgn:2002378",
        "tgn:7007923",
        "tgn:7029392"
    ],
    "tgn:id":2254097,
    "tgn:name":"Cooley Draw",
    "tgn:placetype":[
        "aat:300008761"
    ]
},
  "bbox": [],
  "geometry": {"coordinates":[-104.8333,42.8833],"type":"Point"}
}
=======
{"geometry":{"type":"Point","coordinates":[-104.833300,42.883300]},"type":"Feature","properties":{"hierarchy":["tgn:2254097","tgn:1000001","tgn:7012149","tgn:2002378","tgn:7007923","tgn:7029392"],"placetype":["aat:300008761"],"id":2254097,"name:xx":"Cooley Draw"}}
>>>>>>> 03f74aca74312dbeaf24d7e61306dd6a786dc3d0
