{
  "id": 2254097,
  "type": "Feature",
  "properties": {
    "tgn:hierarchy":[
        "tgn:2254097",
        "tgn:1000001",
        "tgn:7012149",
        "tgn:2002378",
        "tgn:7007923",
        "tgn:7029392"
    ],
    "tgn:id":2254097,
    "tgn:name":"Cooley Draw",
    "tgn:placetype":[
        "aat:300008761"
    ]
},
  "bbox": [],
  "geometry": {"coordinates":[-104.8333,42.8833],"type":"Point"}
}