{
  "id": 1133197,
  "type": "Feature",
  "properties": {
    "tgn:hierarchy":[
        "tgn:1133197",
        "tgn:1000001",
        "tgn:7012149",
        "tgn:7007568",
        "tgn:7029392"
    ],
    "tgn:id":1133197,
    "tgn:name":"Fish Creek",
    "tgn:placetype":[
        "aat:300008706"
    ]
},
  "bbox": [],
  "geometry": {"coordinates":[-76.2833,43.3667],"type":"Point"}
}