{
  "id": 2129914,
  "type": "Feature",
  "properties": {
    "tgn:hierarchy":[
        "tgn:2129914",
        "tgn:1000001",
        "tgn:7012149",
        "tgn:2001504",
        "tgn:7007709",
        "tgn:7029392"
    ],
    "tgn:id":2129914,
    "tgn:name":"Allen Cove",
    "tgn:placetype":[
        "aat:300008761"
    ]
},
  "bbox": [],
  "geometry": {"coordinates":[-82.6667,35.3833],"type":"Point"}
}