{
  "id": 7083862,
  "type": "Feature",
  "properties": {
    "tgn:hierarchy":[
        "tgn:7083862",
        "tgn:1000003",
        "tgn:7003676",
        "tgn:7000084",
        "tgn:7029392"
    ],
    "tgn:id":7083862,
    "tgn:name":"Wiedebrocksheide",
    "tgn:placetype":[
        "aat:300000206"
    ]
},
  "bbox": [],
  "geometry": {"coordinates":[8.283333,52.183333],"type":"Point"}
}