{
  "id": 2126782,
  "type": "Feature",
  "properties": {
    "tgn:hierarchy":[
        "tgn:2126782",
        "tgn:1000001",
        "tgn:7012149",
        "tgn:1002809",
        "tgn:7007252",
        "tgn:7029392"
    ],
    "tgn:id":2126782,
    "tgn:name":"Agnew Branch",
    "tgn:placetype":[
        "aat:300008699"
    ]
},
  "bbox": [],
  "geometry": {"coordinates":[-86.65,41.0833],"type":"Point"}
}