{
  "id": 2733219,
  "type": "Feature",
  "properties": {
    "tgn:hierarchy":[
        "tgn:2733219",
        "tgn:1000001",
        "tgn:2000308",
        "tgn:7012149",
        "tgn:7007248",
        "tgn:7029392"
    ],
    "tgn:id":2733219,
    "tgn:name":"Turkey Pond",
    "tgn:placetype":[
        "aat:300006191"
    ]
},
  "bbox": [],
  "geometry": {"coordinates":[-82.25,32.9333],"type":"Point"}
}