{
  "id": 7072404,
  "type": "Feature",
  "properties": {
    "tgn:hierarchy":[
        "tgn:7072404",
        "tgn:7003669",
        "tgn:1000003",
        "tgn:7000084",
        "tgn:7029392"
    ],
    "tgn:id":7072404,
    "tgn:name":"Tattenkofen",
    "tgn:placetype":[
        "aat:300008347"
    ]
},
  "bbox": [],
  "geometry": {"coordinates":[11.516667,47.866667],"type":"Point"}
}