{
  "id": 2128614,
  "type": "Feature",
  "properties": {
    "tgn:hierarchy":[
        "tgn:2128614",
        "tgn:7013349",
        "tgn:1000001",
        "tgn:7012149",
        "tgn:7007708",
        "tgn:7029392"
    ],
    "tgn:id":2128614,
    "tgn:name":"Alder Spring",
    "tgn:placetype":[
        "aat:300008697"
    ]
},
  "bbox": [],
  "geometry": {"coordinates":[-117.85,44.5833],"type":"Point"}
}