{
  "id": 7256451,
  "type": "Feature",
  "properties": {
    "tgn:concordances":{
        "gn:id":"2759004"
    },
    "tgn:hierarchy":[
        "tgn:7256451",
        "tgn:1000003",
        "tgn:7003622",
        "tgn:7016845",
        "tgn:7029392"
    ],
    "tgn:id":7256451,
    "tgn:name:nl":"Beutenaken",
    "tgn:placetype":[
        "aat:300008347"
    ]
},
  "bbox": [],
  "geometry": {"coordinates":[5.85,50.783333],"type":"Point"}
}