{
  "id": 1006688,
  "type": "Feature",
  "properties": {
    "tgn:hierarchy":[
        "tgn:1006688",
        "tgn:1000004",
        "tgn:1009904",
        "tgn:1001481",
        "tgn:1000135",
        "tgn:7029392"
    ],
    "tgn:id":1006688,
    "tgn:name":"Calusa Island",
    "tgn:placetype":[
        "aat:300008791"
    ]
},
  "bbox": [],
  "geometry": {"coordinates":[121.0333,9.5833],"type":"Point"}
}