{
  "id": 7589820,
  "type": "Feature",
  "properties": {
    "tgn:hierarchy":[
        "tgn:7589820",
        "tgn:1000004",
        "tgn:1001871",
        "tgn:7000198",
        "tgn:7029392"
    ],
    "tgn:id":7589820,
    "tgn:name:en":"Indargarh",
    "tgn:placetype":[
        "aat:300008347"
    ]
},
  "bbox": [],
  "geometry": {"coordinates":[77.062213,29.863585],"type":"Point"}
}