{
  "id": 7482507,
  "type": "Feature",
  "properties": {
    "tgn:hierarchy":[
        "tgn:7482507",
        "tgn:7469009",
        "tgn:1000004",
        "tgn:1000141",
        "tgn:7029392"
    ],
    "tgn:id":7482507,
    "tgn:name":"Yangshan Wan",
    "tgn:placetype":[
        "aat:300132316"
    ]
},
  "bbox": [],
  "geometry": {"coordinates":[118.392,24.492917],"type":"Point"}
}