<<<<<<< HEAD
{
  "id": 7482507,
  "type": "Feature",
  "properties": {
    "tgn:hierarchy":[
        "tgn:7482507",
        "tgn:7469009",
        "tgn:1000004",
        "tgn:1000141",
        "tgn:7029392"
    ],
    "tgn:id":7482507,
    "tgn:name":"Yangshan Wan",
    "tgn:placetype":[
        "aat:300132316"
    ]
},
  "bbox": [],
  "geometry": {"coordinates":[118.392,24.492917],"type":"Point"}
}
=======
{"geometry":{"type":"Point","coordinates":[118.392000,24.492917]},"type":"Feature","properties":{"hierarchy":["tgn:7482507","tgn:7469009","tgn:1000004","tgn:1000141","tgn:7029392"],"placetype":["aat:300132316"],"id":7482507,"name:xx":"Yangshan Wan"}}
>>>>>>> 03f74aca74312dbeaf24d7e61306dd6a786dc3d0
