<<<<<<< HEAD
{
  "id": 2155211,
  "type": "Feature",
  "properties": {
    "tgn:hierarchy":[
        "tgn:2155211",
        "tgn:1000001",
        "tgn:7006451",
        "tgn:2000093",
        "tgn:7012149",
        "tgn:7029392"
    ],
    "tgn:id":2155211,
    "tgn:name":"Bear Mountain",
    "tgn:placetype":[
        "aat:300008798"
    ]
},
  "bbox": [],
  "geometry": {"coordinates":[-110.5333,33.9333],"type":"Point"}
}
=======
{"geometry":{"type":"Point","coordinates":[-110.533300,33.933300]},"type":"Feature","properties":{"hierarchy":["tgn:2155211","tgn:1000001","tgn:7006451","tgn:2000093","tgn:7012149","tgn:7029392"],"placetype":["aat:300008798"],"id":2155211,"name:xx":"Bear Mountain"}}
>>>>>>> 03f74aca74312dbeaf24d7e61306dd6a786dc3d0
