{
  "id": 2631347,
  "type": "Feature",
  "properties": {
    "tgn:hierarchy":[
        "tgn:2631347",
        "tgn:1000001",
        "tgn:7012149",
        "tgn:7016021",
        "tgn:7007568",
        "tgn:7029392"
    ],
    "tgn:id":2631347,
    "tgn:name":"Round Pond",
    "tgn:placetype":[
        "aat:300008680"
    ]
},
  "bbox": [],
  "geometry": {"coordinates":[-75.0667,44.25],"type":"Point"}
}