{
  "id": 2678431,
  "type": "Feature",
  "properties": {
    "tgn:hierarchy":[
        "tgn:2678431",
        "tgn:1000001",
        "tgn:7012149",
        "tgn:7007524",
        "tgn:7029392"
    ],
    "tgn:id":2678431,
    "tgn:name":"South Fork Coal Bank Creek",
    "tgn:placetype":[
        "aat:300008706"
    ]
},
  "bbox": [],
  "geometry": {"coordinates":[-104.2167,45.9833],"type":"Point"}
}