<<<<<<< HEAD
{
  "id": 2337412,
  "type": "Feature",
  "properties": {
    "tgn:hierarchy":[
        "tgn:2337412",
        "tgn:1000001",
        "tgn:7012149",
        "tgn:2000928",
        "tgn:7007515",
        "tgn:7029392"
    ],
    "tgn:id":2337412,
    "tgn:name":"Fowler Brook",
    "tgn:placetype":[
        "aat:300008699"
    ]
},
  "bbox": [],
  "geometry": {"coordinates":[-68.85,46.1167],"type":"Point"}
}
=======
{"geometry":{"type":"Point","coordinates":[-68.850000,46.116700]},"type":"Feature","properties":{"hierarchy":["tgn:2337412","tgn:1000001","tgn:7012149","tgn:2000928","tgn:7007515","tgn:7029392"],"placetype":["aat:300008699"],"id":2337412,"name:xx":"Fowler Brook"}}
>>>>>>> 03f74aca74312dbeaf24d7e61306dd6a786dc3d0
