{
  "id": 2337412,
  "type": "Feature",
  "properties": {
    "tgn:hierarchy":[
        "tgn:2337412",
        "tgn:1000001",
        "tgn:7012149",
        "tgn:2000928",
        "tgn:7007515",
        "tgn:7029392"
    ],
    "tgn:id":2337412,
    "tgn:name":"Fowler Brook",
    "tgn:placetype":[
        "aat:300008699"
    ]
},
  "bbox": [],
  "geometry": {"coordinates":[-68.85,46.1167],"type":"Point"}
}