{
  "id": 7221166,
  "type": "Feature",
  "properties": {
    "tgn:hierarchy":[
        "tgn:7221166",
        "tgn:7002718",
        "tgn:7002715",
        "tgn:1000003",
        "tgn:1000074",
        "tgn:7029392"
    ],
    "tgn:id":7221166,
    "tgn:name":"Ergoch\u00f3rion",
    "tgn:placetype":[
        "aat:300008347"
    ]
},
  "bbox": [],
  "geometry": {"coordinates":[22.198611,40.543056],"type":"Point"}
}