{
  "id": 2201865,
  "type": "Feature",
  "properties": {
    "tgn:hierarchy":[
        "tgn:2201865",
        "tgn:1000001",
        "tgn:7012149",
        "tgn:2001750",
        "tgn:7007712",
        "tgn:7029392"
    ],
    "tgn:id":2201865,
    "tgn:name":"Buck Head Bay",
    "tgn:placetype":[
        "aat:300386845"
    ]
},
  "bbox": [],
  "geometry": {"coordinates":[-79.0667,34.2833],"type":"Point"}
}