{
  "id": 7436845,
  "type": "Feature",
  "properties": {
    "tgn:hierarchy":[
        "tgn:7436845",
        "tgn:7005586",
        "tgn:1000001",
        "tgn:7005560",
        "tgn:7029392"
    ],
    "tgn:id":7436845,
    "tgn:name":"Tepopol, Cerro el",
    "tgn:placetype":[
        "aat:300008795"
    ]
},
  "bbox": [],
  "geometry": {"coordinates":[-105.216667,19.866667],"type":"Point"}
}