<<<<<<< HEAD
{
  "id": 7371515,
  "type": "Feature",
  "properties": {
    "tgn:hierarchy":[
        "tgn:7371515",
        "tgn:1000001",
        "tgn:1001960",
        "tgn:7005560",
        "tgn:7029392"
    ],
    "tgn:id":7371515,
    "tgn:name":"Rancho La Higuera",
    "tgn:placetype":[
        "aat:300000241"
    ]
},
  "bbox": [],
  "geometry": {"coordinates":[-109.983333,30.716667],"type":"Point"}
}
=======
{"geometry":{"type":"Point","coordinates":[-109.983333,30.716667]},"type":"Feature","properties":{"hierarchy":["tgn:7371515","tgn:1000001","tgn:1001960","tgn:7005560","tgn:7029392"],"placetype":["aat:300000241"],"id":7371515,"name:xx":"Rancho La Higuera"}}
>>>>>>> 03f74aca74312dbeaf24d7e61306dd6a786dc3d0
