{
  "id": 7371515,
  "type": "Feature",
  "properties": {
    "tgn:hierarchy":[
        "tgn:7371515",
        "tgn:1000001",
        "tgn:1001960",
        "tgn:7005560",
        "tgn:7029392"
    ],
    "tgn:id":7371515,
    "tgn:name":"Rancho La Higuera",
    "tgn:placetype":[
        "aat:300000241"
    ]
},
  "bbox": [],
  "geometry": {"coordinates":[-109.983333,30.716667],"type":"Point"}
}