<<<<<<< HEAD
{
  "id": 7052468,
  "type": "Feature",
  "properties": {
    "tgn:hierarchy":[
        "tgn:7052468",
        "tgn:1003447",
        "tgn:7007850",
        "tgn:1000003",
        "tgn:1000080",
        "tgn:7029392"
    ],
    "tgn:id":7052468,
    "tgn:name":"Mandriagrande",
    "tgn:placetype":[
        "aat:300008347"
    ]
},
  "bbox": [],
  "geometry": {"coordinates":[16.516667,39.133333],"type":"Point"}
}
=======
{"geometry":{"type":"Point","coordinates":[16.516667,39.133333]},"type":"Feature","properties":{"hierarchy":["tgn:7052468","tgn:1003447","tgn:7007850","tgn:1000003","tgn:1000080","tgn:7029392"],"placetype":["aat:300008347"],"id":7052468,"name:xx":"Mandriagrande"}}
>>>>>>> 03f74aca74312dbeaf24d7e61306dd6a786dc3d0
