{
  "id": 7008285,
  "type": "Feature",
  "properties": {
    "tgn:hierarchy":[
        "tgn:7008285",
        "tgn:7003139",
        "tgn:1000003",
        "tgn:7003080",
        "tgn:1000080",
        "tgn:7029392"
    ],
    "tgn:id":7008285,
    "tgn:name":"Caprarola",
    "tgn:placetype":[
        "aat:300008347",
        "aat:300008375"
    ]
},
  "bbox": [],
  "geometry": {"coordinates":[12.233333,42.316667],"type":"Point"}
}