{
  "id": 2780674,
  "type": "Feature",
  "properties": {
    "tgn:hierarchy":[
        "tgn:2780674",
        "tgn:1000001",
        "tgn:2001567",
        "tgn:7012149",
        "tgn:7007705",
        "tgn:7029392"
    ],
    "tgn:id":2780674,
    "tgn:name":"Wood Lake",
    "tgn:placetype":[
        "aat:300008680"
    ]
},
  "bbox": [],
  "geometry": {"coordinates":[-98.9167,46.0667],"type":"Point"}
}