{
  "id": 2215008,
  "type": "Feature",
  "properties": {
    "tgn:hierarchy":[
        "tgn:2215008",
        "tgn:1000001",
        "tgn:2001091",
        "tgn:7012149",
        "tgn:7007522",
        "tgn:7029392"
    ],
    "tgn:id":2215008,
    "tgn:name":"California Brake",
    "tgn:placetype":[
        "aat:300387099",
        "aat:300008905"
    ]
},
  "bbox": [],
  "geometry": {"coordinates":[-90.75,33.8833],"type":"Point"}
}