{
  "id": 7545108,
  "type": "Feature",
  "properties": {
    "tgn:hierarchy":[
        "tgn:7545108",
        "tgn:1000004",
        "tgn:7000198",
        "tgn:7016694",
        "tgn:7029392"
    ],
    "tgn:id":7545108,
    "tgn:name:en":"B\u0101digarh",
    "tgn:placetype":[
        "aat:300008347"
    ]
},
  "bbox": [],
  "geometry": {"coordinates":[82.433333,18.55],"type":"Point"}
}