{
  "id": 7271288,
  "type": "Feature",
  "properties": {
    "tgn:concordances":{
        "gn:id":"2747606"
    },
    "tgn:hierarchy":[
        "tgn:7271288",
        "tgn:7003616",
        "tgn:1000003",
        "tgn:7016845",
        "tgn:7029392"
    ],
    "tgn:id":7271288,
    "tgn:name:nl":"Scherpenzeel",
    "tgn:placetype":[
        "aat:300008347"
    ]
},
  "bbox": [],
  "geometry": {"coordinates":[5.883333,52.833333],"type":"Point"}
}