{
  "id": 2215086,
  "type": "Feature",
  "properties": {
    "tgn:hierarchy":[
        "tgn:2215086",
        "tgn:1000001",
        "tgn:7012149",
        "tgn:2002039",
        "tgn:7007826",
        "tgn:7029392"
    ],
    "tgn:id":2215086,
    "tgn:name":"California Hill",
    "tgn:placetype":[
        "aat:300008798"
    ]
},
  "bbox": [],
  "geometry": {"coordinates":[-98.9167,29.25],"type":"Point"}
}