{
  "id": 2163933,
  "type": "Feature",
  "properties": {
    "tgn:hierarchy":[
        "tgn:2163933",
        "tgn:1000001",
        "tgn:7012149",
        "tgn:2000493",
        "tgn:7007250",
        "tgn:7029392"
    ],
    "tgn:id":2163933,
    "tgn:name":"Berger Butte",
    "tgn:placetype":[
        "aat:300008798"
    ]
},
  "bbox": [],
  "geometry": {"coordinates":[-114.6167,42.4167],"type":"Point"}
}