{
  "id": 1032676,
  "type": "Feature",
  "properties": {
    "tgn:hierarchy":[
        "tgn:1032676",
        "tgn:1000003",
        "tgn:1000070",
        "tgn:7002895",
        "tgn:7029392"
    ],
    "tgn:id":1032676,
    "tgn:name":"Chorges",
    "tgn:placetype":[
        "aat:300008347"
    ]
},
  "bbox": [],
  "geometry": {"coordinates":[6.2667,44.55],"type":"Point"}
}