{
  "id": 2611892,
  "type": "Feature",
  "properties": {
    "tgn:hierarchy":[
        "tgn:2611892",
        "tgn:1000001",
        "tgn:7012149",
        "tgn:2002377",
        "tgn:7007923",
        "tgn:7029392"
    ],
    "tgn:id":2611892,
    "tgn:name":"Red Ranch Reservoir",
    "tgn:placetype":[
        "aat:300006191"
    ]
},
  "bbox": [],
  "geometry": {"coordinates":[-107.3167,43.25],"type":"Point"}
}