{
  "id": 2675848,
  "type": "Feature",
  "properties": {
    "tgn:hierarchy":[
        "tgn:2675848",
        "tgn:1000001",
        "tgn:7012149",
        "tgn:2001283",
        "tgn:7007524",
        "tgn:7029392"
    ],
    "tgn:id":2675848,
    "tgn:name":"Sonielem Lake",
    "tgn:placetype":[
        "aat:300008680"
    ]
},
  "bbox": [],
  "geometry": {"coordinates":[-113.9167,47.3167],"type":"Point"}
}