{
  "id": 7586794,
  "type": "Feature",
  "properties": {
    "tgn:hierarchy":[
        "tgn:7586794",
        "tgn:1000004",
        "tgn:7000198",
        "tgn:1001977",
        "tgn:7029392"
    ],
    "tgn:id":7586794,
    "tgn:name:en":"G\u0101zipur",
    "tgn:placetype":[
        "aat:300008347"
    ]
},
  "bbox": [],
  "geometry": {"coordinates":[88.088219,22.389183],"type":"Point"}
}