{
  "id": 2695420,
  "type": "Feature",
  "properties": {
    "tgn:hierarchy":[
        "tgn:2695420",
        "tgn:1000001",
        "tgn:1002480",
        "tgn:7012149",
        "tgn:7007564",
        "tgn:7029392"
    ],
    "tgn:id":2695420,
    "tgn:name":"Stimson Hill",
    "tgn:placetype":[
        "aat:300008798"
    ]
},
  "bbox": [],
  "geometry": {"coordinates":[-71.7667,42.8833],"type":"Point"}
}