{
  "id": 7268691,
  "type": "Feature",
  "properties": {
    "tgn:hierarchy":[
        "tgn:7268691",
        "tgn:1000003",
        "tgn:7003624",
        "tgn:7016845",
        "tgn:7029392"
    ],
    "tgn:id":7268691,
    "tgn:name:nl":"Plantloon",
    "tgn:placetype":[
        "aat:300008178"
    ]
},
  "bbox": [],
  "geometry": {"coordinates":[5.083333,51.666667],"type":"Point"}
}