{
  "id": 4009476,
  "type": "Feature",
  "properties": {
    "tgn:hierarchy":[
        "tgn:4009476",
        "tgn:1000003",
        "tgn:7002885",
        "tgn:1000070",
        "tgn:7029392"
    ],
    "tgn:id":4009476,
    "tgn:name":"Roujan",
    "tgn:placetype":[
        "aat:300008347"
    ]
},
  "bbox": [],
  "geometry": {"coordinates":[3.3167,43.3167],"type":"Point"}
}