<<<<<<< HEAD
{
  "id": 2763990,
  "type": "Feature",
  "properties": {
    "tgn:hierarchy":[
        "tgn:2763990",
        "tgn:1000001",
        "tgn:7012149",
        "tgn:1002906",
        "tgn:7007826",
        "tgn:7029392"
    ],
    "tgn:id":2763990,
    "tgn:name":"Wheeler Branch",
    "tgn:placetype":[
        "aat:300008699"
    ]
},
  "bbox": [],
  "geometry": {"coordinates":[-97.7833,32.2667],"type":"Point"}
}
=======
{"geometry":{"type":"Point","coordinates":[-97.783300,32.266700]},"type":"Feature","properties":{"hierarchy":["tgn:2763990","tgn:1000001","tgn:7012149","tgn:1002906","tgn:7007826","tgn:7029392"],"placetype":["aat:300008699"],"id":2763990,"name:xx":"Wheeler Branch"}}
>>>>>>> 03f74aca74312dbeaf24d7e61306dd6a786dc3d0
