{
  "id": 2453597,
  "type": "Feature",
  "properties": {
    "tgn:hierarchy":[
        "tgn:2453597",
        "tgn:1000001",
        "tgn:7012149",
        "tgn:7013867",
        "tgn:7007710",
        "tgn:7029392"
    ],
    "tgn:id":2453597,
    "tgn:name":"Little Conestoga",
    "tgn:placetype":[
        "aat:300008699"
    ]
},
  "bbox": [],
  "geometry": {"coordinates":[-75.9167,40.15],"type":"Point"}
}