{
  "id": 2036769,
  "type": "Feature",
  "properties": {
    "tgn:hierarchy":[
        "tgn:2036769",
        "tgn:1000001",
        "tgn:2000668",
        "tgn:7012149",
        "tgn:7007254",
        "tgn:7029392"
    ],
    "tgn:id":2036769,
    "tgn:name":"Matfield Green",
    "tgn:placetype":[
        "aat:300008347"
    ]
},
  "bbox": [],
  "geometry": {"coordinates":[-96.55,38.15],"type":"Point"}
}