{
  "id": 1120425,
  "type": "Feature",
  "properties": {
    "tgn:hierarchy":[
        "tgn:1120425",
        "tgn:1000003",
        "tgn:1000095",
        "tgn:7029392"
    ],
    "tgn:id":1120425,
    "tgn:name":"San Juan, Embalse de",
    "tgn:placetype":[
        "aat:300006191"
    ]
},
  "bbox": [],
  "geometry": {"coordinates":[-4.4167,40.3833],"type":"Point"}
}