<<<<<<< HEAD
{
  "id": 2252848,
  "type": "Feature",
  "properties": {
    "tgn:hierarchy":[
        "tgn:2252848",
        "tgn:1000001",
        "tgn:7012149",
        "tgn:1002387",
        "tgn:7007710",
        "tgn:7029392"
    ],
    "tgn:id":2252848,
    "tgn:name":"Conococheague Island",
    "tgn:placetype":[
        "aat:300008791"
    ]
},
  "bbox": [],
  "geometry": {"coordinates":[-77.5667,39.9167],"type":"Point"}
}
=======
{"geometry":{"type":"Point","coordinates":[-77.566700,39.916700]},"type":"Feature","properties":{"hierarchy":["tgn:2252848","tgn:1000001","tgn:7012149","tgn:1002387","tgn:7007710","tgn:7029392"],"placetype":["aat:300008791"],"id":2252848,"name:xx":"Conococheague Island"}}
>>>>>>> 03f74aca74312dbeaf24d7e61306dd6a786dc3d0
