{
  "id": 2256564,
  "type": "Feature",
  "properties": {
    "tgn:hierarchy":[
        "tgn:2256564",
        "tgn:1000001",
        "tgn:7012149",
        "tgn:2001865",
        "tgn:7007825",
        "tgn:7029392"
    ],
    "tgn:id":2256564,
    "tgn:name":"Corbin Lake",
    "tgn:placetype":[
        "aat:300008680"
    ]
},
  "bbox": [],
  "geometry": {"coordinates":[-83.5833,36.25],"type":"Point"}
}