<<<<<<< HEAD
{
  "id": 7375084,
  "type": "Feature",
  "properties": {
    "tgn:hierarchy":[
        "tgn:7375084",
        "tgn:1001853",
        "tgn:1000001",
        "tgn:7005560",
        "tgn:7029392"
    ],
    "tgn:id":7375084,
    "tgn:name":"Leandro, Arroyo de",
    "tgn:placetype":[
        "aat:300008699"
    ]
},
  "bbox": [],
  "geometry": {"coordinates":[-100.983333,28.7],"type":"Point"}
}
=======
{"geometry":{"type":"Point","coordinates":[-100.983333,28.700000]},"type":"Feature","properties":{"hierarchy":["tgn:7375084","tgn:1001853","tgn:1000001","tgn:7005560","tgn:7029392"],"placetype":["aat:300008699"],"id":7375084,"name:xx":"Leandro, Arroyo de"}}
>>>>>>> 03f74aca74312dbeaf24d7e61306dd6a786dc3d0
