<<<<<<< HEAD
{
  "id": 7054123,
  "type": "Feature",
  "properties": {
    "tgn:hierarchy":[
        "tgn:7054123",
        "tgn:7003138",
        "tgn:1000003",
        "tgn:7003080",
        "tgn:1000080",
        "tgn:7029392"
    ],
    "tgn:id":7054123,
    "tgn:name":"Lunga, Valle",
    "tgn:placetype":[
        "aat:300008699"
    ]
},
  "bbox": [],
  "geometry": {"coordinates":[12.516667,42.016667],"type":"Point"}
}
=======
{"geometry":{"type":"Point","coordinates":[12.516667,42.016667]},"type":"Feature","properties":{"hierarchy":["tgn:7054123","tgn:7003138","tgn:1000003","tgn:7003080","tgn:1000080","tgn:7029392"],"placetype":["aat:300008699"],"id":7054123,"name:xx":"Lunga, Valle"}}
>>>>>>> 03f74aca74312dbeaf24d7e61306dd6a786dc3d0
