{
  "id": 2538917,
  "type": "Feature",
  "properties": {
    "tgn:hierarchy":[
        "tgn:2538917",
        "tgn:1000001",
        "tgn:7012149",
        "tgn:2001530",
        "tgn:7007709",
        "tgn:7029392"
    ],
    "tgn:id":2538917,
    "tgn:name":"New Belden",
    "tgn:placetype":[
        "aat:300008347"
    ]
},
  "bbox": [],
  "geometry": {"coordinates":[-77.2833,35.6167],"type":"Point"}
}