<<<<<<< HEAD
{
  "id": 7360666,
  "type": "Feature",
  "properties": {
    "tgn:hierarchy":[
        "tgn:7360666",
        "tgn:1000001",
        "tgn:1001937",
        "tgn:7005560",
        "tgn:7029392"
    ],
    "tgn:id":7360666,
    "tgn:name":"Coral, Cabeza de",
    "tgn:placetype":[
        "aat:300387036"
    ]
},
  "bbox": [],
  "geometry": {"coordinates":[-87.316667,18.783333],"type":"Point"}
}
=======
{"geometry":{"type":"Point","coordinates":[-87.316667,18.783333]},"type":"Feature","properties":{"hierarchy":["tgn:7360666","tgn:1000001","tgn:1001937","tgn:7005560","tgn:7029392"],"placetype":["aat:300387036"],"id":7360666,"name:xx":"Coral, Cabeza de"}}
>>>>>>> 03f74aca74312dbeaf24d7e61306dd6a786dc3d0
