{
  "id": 2610685,
  "type": "Feature",
  "properties": {
    "tgn:hierarchy":[
        "tgn:2610685",
        "tgn:1000001",
        "tgn:7012149",
        "tgn:2000213",
        "tgn:7007158",
        "tgn:7029392"
    ],
    "tgn:id":2610685,
    "tgn:name":"Red Creek Canyon",
    "tgn:placetype":[
        "aat:300008761"
    ]
},
  "bbox": [],
  "geometry": {"coordinates":[-104.9667,38.6333],"type":"Point"}
}