{
  "id": 7327077,
  "type": "Feature",
  "properties": {
    "tgn:hierarchy":[
        "tgn:7327077",
        "tgn:7008911",
        "tgn:1000003",
        "tgn:7002763",
        "tgn:1000095",
        "tgn:7029392"
    ],
    "tgn:id":7327077,
    "tgn:name":"Paradas",
    "tgn:placetype":[
        "aat:300008347"
    ]
},
  "bbox": [],
  "geometry": {"coordinates":[-6.816667,43.183333],"type":"Point"}
}