{
  "id": 7498830,
  "type": "Feature",
  "properties": {
    "tgn:hierarchy":[
        "tgn:7498830",
        "tgn:1000004",
        "tgn:7001009",
        "tgn:1000141",
        "tgn:7029392"
    ],
    "tgn:id":7498830,
    "tgn:name":"Fusheng Qiao",
    "tgn:placetype":[
        "aat:300007836"
    ]
},
  "bbox": [],
  "geometry": {"coordinates":[120.846682,24.243231],"type":"Point"}
}