{
  "id": 7161304,
  "type": "Feature",
  "properties": {
    "tgn:hierarchy":[
        "tgn:7161304",
        "tgn:1000003",
        "tgn:7003682",
        "tgn:7000084",
        "tgn:7029392"
    ],
    "tgn:id":7161304,
    "tgn:name":"F\u00f6rsterei Hochsteinchen",
    "tgn:placetype":[
        "aat:300004792"
    ]
},
  "bbox": [],
  "geometry": {"coordinates":[7.683333,49.983333],"type":"Point"}
}