{
  "id": 7255419,
  "type": "Feature",
  "properties": {
    "tgn:hierarchy":[
        "tgn:7255419",
        "tgn:7018237",
        "tgn:1000003",
        "tgn:1000063",
        "tgn:7029392"
    ],
    "tgn:id":7255419,
    "tgn:name":"Rodebeek",
    "tgn:placetype":[
        "aat:300008347"
    ]
},
  "bbox": [],
  "geometry": {"coordinates":[4.433333,50.85],"type":"Point"}
}