{
  "id": 7010695,
  "type": "Feature",
  "properties": {
    "tgn:hierarchy":[
        "tgn:7010695",
        "tgn:7019048",
        "tgn:7002445",
        "tgn:1000003",
        "tgn:7029505",
        "tgn:7008591",
        "tgn:7029392"
    ],
    "tgn:id":7010695,
    "tgn:name:en":"Barnsley",
    "tgn:placetype":[
        "aat:300008347",
        "aat:300008416",
        "aat:300008389",
        "aat:300387305",
        "aat:300387220",
        "aat:300387302"
    ]
},
  "bbox": [],
  "geometry": {"coordinates":[-1.483333,53.55],"type":"Point"}
}