{
  "id": 1011124,
  "type": "Feature",
  "properties": {
    "tgn:hierarchy":[
        "tgn:1011124",
        "tgn:1000811",
        "tgn:7001242",
        "tgn:1000149",
        "tgn:7029392"
    ],
    "tgn:id":1011124,
    "tgn:name":"S\u00e3o Braz, Cabo de",
    "tgn:placetype":[
        "aat:300008850"
    ]
},
  "bbox": [],
  "geometry": {"coordinates":[13.3667,-10.0333],"type":"Point"}
}