{
  "id": 2153168,
  "type": "Feature",
  "properties": {
    "tgn:hierarchy":[
        "tgn:2153168",
        "tgn:1000001",
        "tgn:7012149",
        "tgn:7007709",
        "tgn:7029392"
    ],
    "tgn:id":2153168,
    "tgn:name":"Beal Knob",
    "tgn:placetype":[
        "aat:300008798"
    ]
},
  "bbox": [],
  "geometry": {"coordinates":[-83.75,35.15],"type":"Point"}
}