{
  "id": 2672502,
  "type": "Feature",
  "properties": {
    "tgn:hierarchy":[
        "tgn:2672502",
        "tgn:1000001",
        "tgn:7012149",
        "tgn:7007705",
        "tgn:7029392"
    ],
    "tgn:id":2672502,
    "tgn:name":"Smoky Lake",
    "tgn:placetype":[
        "aat:300008680"
    ]
},
  "bbox": [],
  "geometry": {"coordinates":[-100.25,48.15],"type":"Point"}
}