<<<<<<< HEAD
{
  "id": 2400281,
  "type": "Feature",
  "properties": {
    "tgn:hierarchy":[
        "tgn:2400281",
        "tgn:1000001",
        "tgn:7012149",
        "tgn:2002378",
        "tgn:7007923",
        "tgn:7029392"
    ],
    "tgn:id":2400281,
    "tgn:name":"Horse Creek Springs",
    "tgn:placetype":[
        "aat:300008697"
    ]
},
  "bbox": [],
  "geometry": {"coordinates":[-107.1,42.7],"type":"Point"}
}
=======
{"geometry":{"type":"Point","coordinates":[-107.100000,42.700000]},"type":"Feature","properties":{"hierarchy":["tgn:2400281","tgn:1000001","tgn:7012149","tgn:2002378","tgn:7007923","tgn:7029392"],"placetype":["aat:300008697"],"id":2400281,"name:xx":"Horse Creek Springs"}}
>>>>>>> 03f74aca74312dbeaf24d7e61306dd6a786dc3d0
