{
  "id": 2700748,
  "type": "Feature",
  "properties": {
    "tgn:hierarchy":[
        "tgn:2700748",
        "tgn:1000001",
        "tgn:2001744",
        "tgn:7012149",
        "tgn:7007712",
        "tgn:7029392"
    ],
    "tgn:id":2700748,
    "tgn:name":"Sueville",
    "tgn:placetype":[
        "aat:300008347"
    ]
},
  "bbox": [],
  "geometry": {"coordinates":[-81.35,34.3167],"type":"Point"}
}