<<<<<<< HEAD
{
  "id": 7480741,
  "type": "Feature",
  "properties": {
    "tgn:hierarchy":[
        "tgn:7480741",
        "tgn:1000004",
        "tgn:7490934",
        "tgn:1000141",
        "tgn:7029392"
    ],
    "tgn:id":7480741,
    "tgn:name":"Kaijiangzi",
    "tgn:placetype":[
        "aat:300008791"
    ]
},
  "bbox": [],
  "geometry": {"coordinates":[120.375988,23.19882],"type":"Point"}
}
=======
{"geometry":{"type":"Point","coordinates":[120.375988,23.198820]},"type":"Feature","properties":{"hierarchy":["tgn:7480741","tgn:1000004","tgn:7490934","tgn:1000141","tgn:7029392"],"placetype":["aat:300008791"],"id":7480741,"name:xx":"Kaijiangzi"}}
>>>>>>> 03f74aca74312dbeaf24d7e61306dd6a786dc3d0
