{
  "id": 7480741,
  "type": "Feature",
  "properties": {
    "tgn:hierarchy":[
        "tgn:7480741",
        "tgn:1000004",
        "tgn:7490934",
        "tgn:1000141",
        "tgn:7029392"
    ],
    "tgn:id":7480741,
    "tgn:name":"Kaijiangzi",
    "tgn:placetype":[
        "aat:300008791"
    ]
},
  "bbox": [],
  "geometry": {"coordinates":[120.375988,23.19882],"type":"Point"}
}