{
  "id": 7239792,
  "type": "Feature",
  "properties": {
    "tgn:hierarchy":[
        "tgn:7239792",
        "tgn:7003460",
        "tgn:1000003",
        "tgn:1000063",
        "tgn:4012014",
        "tgn:7029392"
    ],
    "tgn:id":7239792,
    "tgn:name":"Gut Luft",
    "tgn:placetype":[
        "aat:300000206"
    ]
},
  "bbox": [],
  "geometry": {"coordinates":[6.066667,50.666667],"type":"Point"}
}