{
  "id": 7412894,
  "type": "Feature",
  "properties": {
    "tgn:hierarchy":[
        "tgn:7412894",
        "tgn:7005587",
        "tgn:1000001",
        "tgn:7005560",
        "tgn:7029392"
    ],
    "tgn:id":7412894,
    "tgn:name:es":"El Desierto",
    "tgn:placetype":[
        "aat:300008347"
    ]
},
  "bbox": [],
  "geometry": {"coordinates":[-99.766667,20.219444],"type":"Point"}
}