{
  "id": 7351082,
  "type": "Feature",
  "properties": {
    "tgn:hierarchy":[
        "tgn:7351082",
        "tgn:1000001",
        "tgn:1001893",
        "tgn:7005560",
        "tgn:7029392"
    ],
    "tgn:id":7351082,
    "tgn:name":"Cacahuac\u00e1n",
    "tgn:placetype":[
        "aat:300008347"
    ]
},
  "bbox": [],
  "geometry": {"coordinates":[-99.416667,19.633333],"type":"Point"}
}