{
  "id": 7261326,
  "type": "Feature",
  "properties": {
    "tgn:hierarchy":[
        "tgn:7261326",
        "tgn:7003616",
        "tgn:1000003",
        "tgn:7016845",
        "tgn:7029392"
    ],
    "tgn:id":7261326,
    "tgn:name:nl":"Echterveld",
    "tgn:placetype":[
        "aat:300006163"
    ]
},
  "bbox": [],
  "geometry": {"coordinates":[5.816667,52.833333],"type":"Point"}
}