{
  "id": 7095656,
  "type": "Feature",
  "properties": {
    "tgn:hierarchy":[
        "tgn:7095656",
        "tgn:1000003",
        "tgn:7003688",
        "tgn:7000084",
        "tgn:7029392"
    ],
    "tgn:id":7095656,
    "tgn:name":"Sch\u00f6nberger Au",
    "tgn:placetype":[
        "aat:300008699"
    ]
},
  "bbox": [],
  "geometry": {"coordinates":[10.383333,54.433333],"type":"Point"}
}