{
  "id": 2194376,
  "type": "Feature",
  "properties": {
    "tgn:hierarchy":[
        "tgn:2194376",
        "tgn:1000001",
        "tgn:2002243",
        "tgn:7012149",
        "tgn:7007920",
        "tgn:7029392"
    ],
    "tgn:id":2194376,
    "tgn:name":"Bridge Creek",
    "tgn:placetype":[
        "aat:300008706"
    ]
},
  "bbox": [],
  "geometry": {"coordinates":[-118.5333,48.3167],"type":"Point"}
}