{
  "id": 2356170,
  "type": "Feature",
  "properties": {
    "tgn:hierarchy":[
        "tgn:2356170",
        "tgn:1000001",
        "tgn:7012149",
        "tgn:7007157",
        "tgn:1002957",
        "tgn:7029392"
    ],
    "tgn:id":2356170,
    "tgn:name":"Gooseberry Creek",
    "tgn:placetype":[
        "aat:300008706"
    ]
},
  "bbox": [],
  "geometry": {"coordinates":[-119.95,38.1833],"type":"Point"}
}