{
  "id": 7531302,
  "type": "Feature",
  "properties": {
    "tgn:hierarchy":[
        "tgn:7531302",
        "tgn:7001242",
        "tgn:7016833",
        "tgn:1001091",
        "tgn:7029392"
    ],
    "tgn:id":7531302,
    "tgn:name":"\u1e28ad\u012bqat Alm\u0101z\u0327ah",
    "tgn:placetype":[
        "aat:300008187"
    ]
},
  "bbox": [],
  "geometry": {"coordinates":[31.381602,30.080092],"type":"Point"}
}