{
  "id": 7354507,
  "type": "Feature",
  "properties": {
    "tgn:hierarchy":[
        "tgn:7354507",
        "tgn:1000001",
        "tgn:7005600",
        "tgn:7005560",
        "tgn:7029392"
    ],
    "tgn:id":7354507,
    "tgn:name":"Chunyaxnic",
    "tgn:placetype":[
        "aat:300008347"
    ]
},
  "bbox": [],
  "geometry": {"coordinates":[-88.633333,21.416667],"type":"Point"}
}