{
  "id": 2758361,
  "type": "Feature",
  "properties": {
    "tgn:hierarchy":[
        "tgn:2758361",
        "tgn:1000001",
        "tgn:2001703",
        "tgn:7012149",
        "tgn:7007708",
        "tgn:7029392"
    ],
    "tgn:id":2758361,
    "tgn:name":"West Butte",
    "tgn:placetype":[
        "aat:300008798"
    ]
},
  "bbox": [],
  "geometry": {"coordinates":[-120.8333,43.95],"type":"Point"}
}