{
  "id": 7257051,
  "type": "Feature",
  "properties": {
    "tgn:hierarchy":[
        "tgn:7257051",
        "tgn:7016796",
        "tgn:7593115",
        "tgn:7593112",
        "tgn:1000001",
        "tgn:7029392"
    ],
    "tgn:id":7257051,
    "tgn:name:nl":"Lower Hell's Gate",
    "tgn:placetype":[
        "aat:300008347"
    ]
},
  "bbox": [],
  "geometry": {"coordinates":[-63.216667,17.633333],"type":"Point"}
}