{
  "id": 7336646,
  "type": "Feature",
  "properties": {
    "tgn:hierarchy":[
        "tgn:7336646",
        "tgn:7002836",
        "tgn:7016622",
        "tgn:1000003",
        "tgn:1000095",
        "tgn:7029392"
    ],
    "tgn:id":7336646,
    "tgn:name":"Gaviotas, Playa de las",
    "tgn:placetype":[
        "aat:300008816"
    ]
},
  "bbox": [],
  "geometry": {"coordinates":[-16.166667,28.516667],"type":"Point"}
}