{
  "id": 2488567,
  "type": "Feature",
  "properties": {
    "tgn:hierarchy":[
        "tgn:2488567",
        "tgn:1000001",
        "tgn:2002370",
        "tgn:7012149",
        "tgn:7007923",
        "tgn:7029392"
    ],
    "tgn:id":2488567,
    "tgn:name":"Mahoney Draw",
    "tgn:placetype":[
        "aat:300008761"
    ]
},
  "bbox": [],
  "geometry": {"coordinates":[-104.4833,44.6167],"type":"Point"}
}