{
  "id": 7307362,
  "type": "Feature",
  "properties": {
    "tgn:hierarchy":[
        "tgn:7307362",
        "tgn:7002824",
        "tgn:1000003",
        "tgn:7002786",
        "tgn:1000095",
        "tgn:7029392"
    ],
    "tgn:id":7307362,
    "tgn:name":"Maro\u00f1as",
    "tgn:placetype":[
        "aat:300008347"
    ]
},
  "bbox": [],
  "geometry": {"coordinates":[-8.916667,42.95],"type":"Point"}
}