{
  "id": 2577240,
  "type": "Feature",
  "properties": {
    "tgn:hierarchy":[
        "tgn:2577240",
        "tgn:1000001",
        "tgn:7012149",
        "tgn:7007712",
        "tgn:7029392"
    ],
    "tgn:id":2577240,
    "tgn:name":"Peters Creek",
    "tgn:placetype":[
        "aat:300008706"
    ]
},
  "bbox": [],
  "geometry": {"coordinates":[-81.5167,34.4667],"type":"Point"}
}