{
  "id": 1017311,
  "type": "Feature",
  "properties": {
    "tgn:hierarchy":[
        "tgn:1017311",
        "tgn:1000001",
        "tgn:7005597",
        "tgn:7005560",
        "tgn:7029392"
    ],
    "tgn:id":1017311,
    "tgn:name":"Cruillas",
    "tgn:placetype":[
        "aat:300008347"
    ]
},
  "bbox": [],
  "geometry": {"coordinates":[-98.516667,24.75],"type":"Point"}
}