{
  "id": 7523476,
  "type": "Feature",
  "properties": {
    "tgn:hierarchy":[
        "tgn:7523476",
        "tgn:7001242",
        "tgn:7016833",
        "tgn:1001335",
        "tgn:7029392"
    ],
    "tgn:id":7523476,
    "tgn:name:en":"Ba\u0163\u0163\u012bkh, Jaz\u012brat al",
    "tgn:placetype":[
        "aat:300008791"
    ]
},
  "bbox": [],
  "geometry": {"coordinates":[30.972222,31.363333],"type":"Point"}
}