<<<<<<< HEAD
{
  "id": 7175284,
  "type": "Feature",
  "properties": {
    "tgn:hierarchy":[
        "tgn:7175284",
        "tgn:1000003",
        "tgn:7003689",
        "tgn:7000084",
        "tgn:7029392"
    ],
    "tgn:id":7175284,
    "tgn:name":"Gro\u00dfer B\u00f6hler",
    "tgn:placetype":[
        "aat:300008777"
    ]
},
  "bbox": [],
  "geometry": {"coordinates":[10.7,50.75],"type":"Point"}
}
=======
{"geometry":{"type":"Point","coordinates":[10.700000,50.750000]},"type":"Feature","properties":{"hierarchy":["tgn:7175284","tgn:1000003","tgn:7003689","tgn:7000084","tgn:7029392"],"placetype":["aat:300008777"],"id":7175284,"name:xx":"Gro\u00dfer B\u00f6hler"}}
>>>>>>> 03f74aca74312dbeaf24d7e61306dd6a786dc3d0
