{
  "id": 2291166,
  "type": "Feature",
  "properties": {
    "tgn:hierarchy":[
        "tgn:2291166",
        "tgn:1000001",
        "tgn:7014090",
        "tgn:7012149",
        "tgn:7007565",
        "tgn:7029392"
    ],
    "tgn:id":2291166,
    "tgn:name":"Dogs Corners",
    "tgn:placetype":[
        "aat:300008347"
    ]
},
  "bbox": [],
  "geometry": {"coordinates":[-74.0333,40.25],"type":"Point"}
}