{
  "id": 2551797,
  "type": "Feature",
  "properties": {
    "tgn:hierarchy":[
        "tgn:2551797",
        "tgn:1000001",
        "tgn:7012149",
        "tgn:1002629",
        "tgn:7007523",
        "tgn:7029392"
    ],
    "tgn:id":2551797,
    "tgn:name":"Number 69 Lake",
    "tgn:placetype":[
        "aat:300006191"
    ]
},
  "bbox": [],
  "geometry": {"coordinates":[-91.6833,38.1333],"type":"Point"}
}