{
  "id": 2398918,
  "type": "Feature",
  "properties": {
    "tgn:hierarchy":[
        "tgn:2398918",
        "tgn:1000001",
        "tgn:7012149",
        "tgn:2001898",
        "tgn:7007825",
        "tgn:7029392"
    ],
    "tgn:id":2398918,
    "tgn:name":"Hopewell Mill",
    "tgn:placetype":[
        "aat:300008347"
    ]
},
  "bbox": [],
  "geometry": {"coordinates":[-84.25,35.5167],"type":"Point"}
}