{
  "id": 2104154,
  "type": "Feature",
  "properties": {
    "tgn:hierarchy":[
        "tgn:2104154",
        "tgn:1000001",
        "tgn:7012149",
        "tgn:1002533",
        "tgn:7007826",
        "tgn:7029392"
    ],
    "tgn:id":2104154,
    "tgn:name":"Falls City",
    "tgn:placetype":[
        "aat:300008347"
    ]
},
  "bbox": [],
  "geometry": {"coordinates":[-98.0167,28.9667],"type":"Point"}
}