{
  "id": 7047657,
  "type": "Feature",
  "properties": {
    "tgn:hierarchy":[
        "tgn:7047657",
        "tgn:7003128",
        "tgn:1000003",
        "tgn:7008516",
        "tgn:1000080",
        "tgn:7029392"
    ],
    "tgn:id":7047657,
    "tgn:name":"Cisi",
    "tgn:placetype":[
        "aat:300008347"
    ]
},
  "bbox": [],
  "geometry": {"coordinates":[11.966667,44.85],"type":"Point"}
}