{
  "id": 7096355,
  "type": "Feature",
  "properties": {
    "tgn:hierarchy":[
        "tgn:7096355",
        "tgn:1000003",
        "tgn:7003689",
        "tgn:7000084",
        "tgn:7029392"
    ],
    "tgn:id":7096355,
    "tgn:name":"Sch\u00f6mberg",
    "tgn:placetype":[
        "aat:300008347"
    ]
},
  "bbox": [],
  "geometry": {"coordinates":[12.016667,50.766667],"type":"Point"}
}