{
  "id": 2272479,
  "type": "Feature",
  "properties": {
    "tgn:hierarchy":[
        "tgn:2272479",
        "tgn:1000001",
        "tgn:1002724",
        "tgn:7012149",
        "tgn:7007517",
        "tgn:7029392"
    ],
    "tgn:id":2272479,
    "tgn:name":"Curtis Pond",
    "tgn:placetype":[
        "aat:300008680"
    ]
},
  "bbox": [],
  "geometry": {"coordinates":[-71.45,42.0667],"type":"Point"}
}