{
  "id": 2136454,
  "type": "Feature",
  "properties": {
    "tgn:hierarchy":[
        "tgn:2136454",
        "tgn:1000001",
        "tgn:7012149",
        "tgn:2001843",
        "tgn:7007825",
        "tgn:7029392"
    ],
    "tgn:id":2136454,
    "tgn:name":"Arch Hollow",
    "tgn:placetype":[
        "aat:300008761"
    ]
},
  "bbox": [],
  "geometry": {"coordinates":[-84.1167,36.4333],"type":"Point"}
}