{
  "id": 7438719,
  "type": "Feature",
  "properties": {
    "tgn:hierarchy":[
        "tgn:7438719",
        "tgn:7005586",
        "tgn:1000001",
        "tgn:7005560",
        "tgn:7029392"
    ],
    "tgn:id":7438719,
    "tgn:name":"Tabo",
    "tgn:placetype":[
        "aat:300008699"
    ]
},
  "bbox": [],
  "geometry": {"coordinates":[-105.652222,20.411667],"type":"Point"}
}