{
  "id": 2058687,
  "type": "Feature",
  "properties": {
    "tgn:hierarchy":[
        "tgn:2058687",
        "tgn:1000001",
        "tgn:7012149",
        "tgn:2001220",
        "tgn:7007523",
        "tgn:7029392"
    ],
    "tgn:id":2058687,
    "tgn:name":"Enon",
    "tgn:placetype":[
        "aat:300008347"
    ]
},
  "bbox": [],
  "geometry": {"coordinates":[-92.4833,38.45],"type":"Point"}
}