{
  "id": 7567091,
  "type": "Feature",
  "properties": {
    "tgn:hierarchy":[
        "tgn:7567091",
        "tgn:1000004",
        "tgn:7000198",
        "tgn:7001797",
        "tgn:7029392"
    ],
    "tgn:id":7567091,
    "tgn:name:en":"Trustpuram",
    "tgn:placetype":[
        "aat:300000745"
    ]
},
  "bbox": [],
  "geometry": {"coordinates":[80.225278,13.054444],"type":"Point"}
}