<<<<<<< HEAD
{
  "id": 2154785,
  "type": "Feature",
  "properties": {
    "tgn:hierarchy":[
        "tgn:2154785",
        "tgn:1000001",
        "tgn:2000859",
        "tgn:7012149",
        "tgn:7007256",
        "tgn:7029392"
    ],
    "tgn:id":2154785,
    "tgn:name":"Bear Head Marsh",
    "tgn:placetype":[
        "aat:300008699"
    ]
},
  "bbox": [],
  "geometry": {"coordinates":[-93.4167,30.7167],"type":"Point"}
}
=======
{"geometry":{"type":"Point","coordinates":[-93.416700,30.716700]},"type":"Feature","properties":{"hierarchy":["tgn:2154785","tgn:1000001","tgn:2000859","tgn:7012149","tgn:7007256","tgn:7029392"],"placetype":["aat:300008699"],"id":2154785,"name:xx":"Bear Head Marsh"}}
>>>>>>> 03f74aca74312dbeaf24d7e61306dd6a786dc3d0
