{
  "id": 2513083,
  "type": "Feature",
  "properties": {
    "tgn:hierarchy":[
        "tgn:2513083",
        "tgn:1000001",
        "tgn:7012149",
        "tgn:2002278",
        "tgn:7013961",
        "tgn:7029392"
    ],
    "tgn:id":2513083,
    "tgn:name":"Mill Creek",
    "tgn:placetype":[
        "aat:300008706"
    ]
},
  "bbox": [],
  "geometry": {"coordinates":[-81.3333,37.3333],"type":"Point"}
}