{
  "id": 7231699,
  "type": "Feature",
  "properties": {
    "tgn:hierarchy":[
        "tgn:7231699",
        "tgn:7011161",
        "tgn:7002674",
        "tgn:1000003",
        "tgn:1000074",
        "tgn:7029392"
    ],
    "tgn:id":7231699,
    "tgn:name":"K\u00e9ramos",
    "tgn:placetype":[
        "aat:300008347"
    ]
},
  "bbox": [],
  "geometry": {"coordinates":[25.935833,38.555556],"type":"Point"}
}