{
  "id": 2154621,
  "type": "Feature",
  "properties": {
    "tgn:hierarchy":[
        "tgn:2154621",
        "tgn:1000001",
        "tgn:7012149",
        "tgn:2002195",
        "tgn:7007919",
        "tgn:7029392"
    ],
    "tgn:id":2154621,
    "tgn:name":"Bear Fork",
    "tgn:placetype":[
        "aat:300008699"
    ]
},
  "bbox": [],
  "geometry": {"coordinates":[-82.7167,37.0833],"type":"Point"}
}