{
  "id": 2341359,
  "type": "Feature",
  "properties": {
    "tgn:hierarchy":[
        "tgn:2341359",
        "tgn:1000001",
        "tgn:7012149",
        "tgn:2001711",
        "tgn:7007708",
        "tgn:7029392"
    ],
    "tgn:id":2341359,
    "tgn:name":"Frog Creek",
    "tgn:placetype":[
        "aat:300008706"
    ]
},
  "bbox": [],
  "geometry": {"coordinates":[-122.5167,42.2333],"type":"Point"}
}