{
  "id": 2250691,
  "type": "Feature",
  "properties": {
    "tgn:hierarchy":[
        "tgn:2250691",
        "tgn:1000001",
        "tgn:7012149",
        "tgn:7007158",
        "tgn:2000243",
        "tgn:7029392"
    ],
    "tgn:id":2250691,
    "tgn:name":"Colorow Mountain",
    "tgn:placetype":[
        "aat:300008798"
    ]
},
  "bbox": [],
  "geometry": {"coordinates":[-108.1667,40.1667],"type":"Point"}
}