{
  "id": 2493680,
  "type": "Feature",
  "properties": {
    "tgn:hierarchy":[
        "tgn:2493680",
        "tgn:1000001",
        "tgn:7012149",
        "tgn:7022208",
        "tgn:7007919",
        "tgn:7029392"
    ],
    "tgn:id":2493680,
    "tgn:name":"Marsh Point",
    "tgn:placetype":[
        "aat:300008850"
    ]
},
  "bbox": [],
  "geometry": {"coordinates":[-76.3333,37.1667],"type":"Point"}
}