{
  "id": 2335977,
  "type": "Feature",
  "properties": {
    "tgn:hierarchy":[
        "tgn:2335977",
        "tgn:1000001",
        "tgn:2001261",
        "tgn:7012149",
        "tgn:7007524",
        "tgn:7029392"
    ],
    "tgn:id":2335977,
    "tgn:name":"Foster",
    "tgn:placetype":[
        "aat:300008347"
    ]
},
  "bbox": [],
  "geometry": {"coordinates":[-107.5833,45.9167],"type":"Point"}
}