{
  "id": 7140126,
  "type": "Feature",
  "properties": {
    "tgn:hierarchy":[
        "tgn:7140126",
        "tgn:7003669",
        "tgn:1000003",
        "tgn:7000084",
        "tgn:7029392"
    ],
    "tgn:id":7140126,
    "tgn:name":"Lindach Wald",
    "tgn:placetype":[
        "aat:300008863"
    ]
},
  "bbox": [],
  "geometry": {"coordinates":[10.666667,50.216667],"type":"Point"}
}