{
  "id": 7412006,
  "type": "Feature",
  "properties": {
    "tgn:hierarchy":[
        "tgn:7412006",
        "tgn:7005587",
        "tgn:1000001",
        "tgn:7005560",
        "tgn:7029392"
    ],
    "tgn:id":7412006,
    "tgn:name:es":"El Acocul",
    "tgn:placetype":[
        "aat:300008347"
    ]
},
  "bbox": [],
  "geometry": {"coordinates":[-98.388889,20.222222],"type":"Point"}
}