{
  "id": 7223869,
  "type": "Feature",
  "properties": {
    "tgn:hierarchy":[
        "tgn:7223869",
        "tgn:7002728",
        "tgn:7002715",
        "tgn:1000003",
        "tgn:1000074",
        "tgn:7029392"
    ],
    "tgn:id":7223869,
    "tgn:name":"Thiri\u00f3petra",
    "tgn:placetype":[
        "aat:300008347"
    ]
},
  "bbox": [],
  "geometry": {"coordinates":[22.156667,41.058889],"type":"Point"}
}