<<<<<<< HEAD
{
  "id": 7055138,
  "type": "Feature",
  "properties": {
    "tgn:hierarchy":[
        "tgn:7055138",
        "tgn:1003506",
        "tgn:1000003",
        "tgn:7002993",
        "tgn:1000080",
        "tgn:7029392"
    ],
    "tgn:id":7055138,
    "tgn:name":"Osternig",
    "tgn:placetype":[
        "aat:300008795"
    ]
},
  "bbox": [],
  "geometry": {"coordinates":[13.5,46.566667],"type":"Point"}
}
=======
{"geometry":{"type":"Point","coordinates":[13.500000,46.566667]},"type":"Feature","properties":{"hierarchy":["tgn:7055138","tgn:1003506","tgn:1000003","tgn:7002993","tgn:1000080","tgn:7029392"],"placetype":["aat:300008795"],"id":7055138,"name:xx":"Osternig"}}
>>>>>>> 03f74aca74312dbeaf24d7e61306dd6a786dc3d0
