{
  "id": 7126654,
  "type": "Feature",
  "properties": {
    "tgn:hierarchy":[
        "tgn:7126654",
        "tgn:1000003",
        "tgn:7003689",
        "tgn:7000084",
        "tgn:7029392"
    ],
    "tgn:id":7126654,
    "tgn:name":"Nonnenburg",
    "tgn:placetype":[
        "aat:300008777"
    ]
},
  "bbox": [],
  "geometry": {"coordinates":[10.65,51.366667],"type":"Point"}
}