<<<<<<< HEAD
{
  "id": 2406086,
  "type": "Feature",
  "properties": {
    "tgn:hierarchy":[
        "tgn:2406086",
        "tgn:1000001",
        "tgn:7012149",
        "tgn:1002392",
        "tgn:7007157",
        "tgn:7029392"
    ],
    "tgn:id":2406086,
    "tgn:name":"Hume Lake",
    "tgn:placetype":[
        "aat:300008680"
    ]
},
  "bbox": [],
  "geometry": {"coordinates":[-118.9,36.7833],"type":"Point"}
}
=======
{"geometry":{"type":"Point","coordinates":[-118.900000,36.783300]},"type":"Feature","properties":{"hierarchy":["tgn:2406086","tgn:1000001","tgn:7012149","tgn:1002392","tgn:7007157","tgn:7029392"],"placetype":["aat:300008680"],"id":2406086,"name:xx":"Hume Lake"}}
>>>>>>> 03f74aca74312dbeaf24d7e61306dd6a786dc3d0
