{
  "id": 7565583,
  "type": "Feature",
  "properties": {
    "tgn:hierarchy":[
        "tgn:7565583",
        "tgn:1000004",
        "tgn:7000198",
        "tgn:7016722",
        "tgn:7029392"
    ],
    "tgn:id":7565583,
    "tgn:name:en":"Purwa Gularia",
    "tgn:placetype":[
        "aat:300167671"
    ]
},
  "bbox": [],
  "geometry": {"coordinates":[79.537877,26.797354],"type":"Point"}
}