{
  "id": 7483581,
  "type": "Feature",
  "properties": {
    "tgn:hierarchy":[
        "tgn:7483581",
        "tgn:7487020",
        "tgn:1000004",
        "tgn:1000141",
        "tgn:7029392"
    ],
    "tgn:id":7483581,
    "tgn:name":"Luocuo",
    "tgn:placetype":[
        "aat:300008347"
    ]
},
  "bbox": [],
  "geometry": {"coordinates":[120.625278,24.421389],"type":"Point"}
}