{
  "id": 7504737,
  "type": "Feature",
  "properties": {
    "tgn:hierarchy":[
        "tgn:7504737",
        "tgn:7000508",
        "tgn:1008380",
        "tgn:1000226",
        "tgn:1000006",
        "tgn:7029392"
    ],
    "tgn:id":7504737,
    "tgn:name:en":"South Channel",
    "tgn:placetype":[
        "aat:300387026"
    ]
},
  "bbox": [],
  "geometry": {"coordinates":[174.815278,-36.462778],"type":"Point"}
}