{
  "id": 7536068,
  "type": "Feature",
  "properties": {
    "tgn:hierarchy":[
        "tgn:7536068",
        "tgn:7001242",
        "tgn:1001075",
        "tgn:7016833",
        "tgn:7029392"
    ],
    "tgn:id":7536068,
    "tgn:name:en":"Khubbayzah, B\u0101b al",
    "tgn:placetype":[
        "aat:300387026"
    ]
},
  "bbox": [],
  "geometry": {"coordinates":[30.333333,31.266667],"type":"Point"}
}