{
  "id": 2511749,
  "type": "Feature",
  "properties": {
    "tgn:hierarchy":[
        "tgn:2511749",
        "tgn:1000001",
        "tgn:7012149",
        "tgn:2002385",
        "tgn:7007923",
        "tgn:7029392"
    ],
    "tgn:id":2511749,
    "tgn:name":"Milich Ditch",
    "tgn:placetype":[
        "aat:300006075"
    ]
},
  "bbox": [],
  "geometry": {"coordinates":[-110.35,41.1833],"type":"Point"}
}