{
  "id": 7356811,
  "type": "Feature",
  "properties": {
    "tgn:hierarchy":[
        "tgn:7356811",
        "tgn:1000001",
        "tgn:7005595",
        "tgn:7005560",
        "tgn:7029392"
    ],
    "tgn:id":7356811,
    "tgn:name":"Campo Clouthier",
    "tgn:placetype":[
        "aat:300008347"
    ]
},
  "bbox": [],
  "geometry": {"coordinates":[-107.533333,24.587222],"type":"Point"}
}