{
  "id": 2776670,
  "type": "Feature",
  "properties": {
    "tgn:hierarchy":[
        "tgn:2776670",
        "tgn:1000001",
        "tgn:7012149",
        "tgn:2000401",
        "tgn:7007248",
        "tgn:7029392"
    ],
    "tgn:id":2776670,
    "tgn:name":"Windmill Creek",
    "tgn:placetype":[
        "aat:300008347"
    ]
},
  "bbox": [],
  "geometry": {"coordinates":[-84.8667,33.9833],"type":"Point"}
}