{
  "id": 7567952,
  "type": "Feature",
  "properties": {
    "tgn:hierarchy":[
        "tgn:7567952",
        "tgn:1000004",
        "tgn:7000198",
        "tgn:7031786",
        "tgn:7029392"
    ],
    "tgn:id":7567952,
    "tgn:name:en":"Kad\u016bri G\u0101d",
    "tgn:placetype":[
        "aat:300008699"
    ]
},
  "bbox": [],
  "geometry": {"coordinates":[78.704167,29.795],"type":"Point"}
}