{
  "id": 2611852,
  "type": "Feature",
  "properties": {
    "tgn:hierarchy":[
        "tgn:2611852",
        "tgn:1000001",
        "tgn:7012149",
        "tgn:2001207",
        "tgn:7007523",
        "tgn:7029392"
    ],
    "tgn:id":2611852,
    "tgn:name":"Red Point",
    "tgn:placetype":[
        "aat:300008347"
    ]
},
  "bbox": [],
  "geometry": {"coordinates":[-91.1333,37.6333],"type":"Point"}
}