<<<<<<< HEAD
{
  "id": 2152829,
  "type": "Feature",
  "properties": {
    "tgn:hierarchy":[
        "tgn:2152829",
        "tgn:2000001",
        "tgn:7002659",
        "tgn:1000001",
        "tgn:7012149",
        "tgn:7029392"
    ],
    "tgn:id":2152829,
    "tgn:name":"Bayside",
    "tgn:placetype":[
        "aat:300008347"
    ]
},
  "bbox": [],
  "geometry": {"coordinates":[-87.8167,30.4],"type":"Point"}
}
=======
{"geometry":{"type":"Point","coordinates":[-87.816700,30.400000]},"type":"Feature","properties":{"hierarchy":["tgn:2152829","tgn:2000001","tgn:7002659","tgn:1000001","tgn:7012149","tgn:7029392"],"placetype":["aat:300008347"],"id":2152829,"name:xx":"Bayside"}}
>>>>>>> 03f74aca74312dbeaf24d7e61306dd6a786dc3d0
