{
  "id": 2295157,
  "type": "Feature",
  "properties": {
    "tgn:hierarchy":[
        "tgn:2295157",
        "tgn:1000001",
        "tgn:7012149",
        "tgn:1002611",
        "tgn:7007706",
        "tgn:7029392"
    ],
    "tgn:id":2295157,
    "tgn:name":"Drennan Ditch",
    "tgn:placetype":[
        "aat:300006075"
    ]
},
  "bbox": [],
  "geometry": {"coordinates":[-83.75,41.6333],"type":"Point"}
}