{
  "id": 1032280,
  "type": "Feature",
  "properties": {
    "tgn:hierarchy":[
        "tgn:1032280",
        "tgn:1000003",
        "tgn:7002883",
        "tgn:1000070",
        "tgn:7029392"
    ],
    "tgn:id":1032280,
    "tgn:name":"Boussy-Saint-Antoine",
    "tgn:placetype":[
        "aat:300008347"
    ]
},
  "bbox": [],
  "geometry": {"coordinates":[2.5333,48.6833],"type":"Point"}
}