{
  "id": 1097540,
  "type": "Feature",
  "properties": {
    "tgn:hierarchy":[
        "tgn:1097540",
        "tgn:7000490",
        "tgn:1000006",
        "tgn:7001828",
        "tgn:7029392"
    ],
    "tgn:id":1097540,
    "tgn:name":"Merriwa",
    "tgn:placetype":[
        "aat:300008347"
    ]
},
  "bbox": [],
  "geometry": {"coordinates":[150.3333,-32.1333],"type":"Point"}
}