{
  "id": 7250425,
  "type": "Feature",
  "properties": {
    "tgn:hierarchy":[
        "tgn:7250425",
        "tgn:7003458",
        "tgn:1000003",
        "tgn:1000063",
        "tgn:7018236",
        "tgn:7029392"
    ],
    "tgn:id":7250425,
    "tgn:name":"Parochieveld",
    "tgn:placetype":[
        "aat:300008347"
    ]
},
  "bbox": [],
  "geometry": {"coordinates":[3.347551,51.080659],"type":"Point"}
}