{
  "id": 7287883,
  "type": "Feature",
  "properties": {
    "tgn:hierarchy":[
        "tgn:7287883",
        "tgn:1001702",
        "tgn:1000049",
        "tgn:1000002",
        "tgn:7029392"
    ],
    "tgn:id":7287883,
    "tgn:name":"Julia, Isla",
    "tgn:placetype":[
        "aat:300008791"
    ]
},
  "bbox": [],
  "geometry": {"coordinates":[-74.383333,-48.933333],"type":"Point"}
}