{
  "id": 7190863,
  "type": "Feature",
  "properties": {
    "tgn:hierarchy":[
        "tgn:7190863",
        "tgn:7003669",
        "tgn:1000003",
        "tgn:7000084",
        "tgn:7029392"
    ],
    "tgn:id":7190863,
    "tgn:name":"Forsting",
    "tgn:placetype":[
        "aat:300008347"
    ]
},
  "bbox": [],
  "geometry": {"coordinates":[12.333333,49.183333],"type":"Point"}
}