{
  "id": 2469082,
  "type": "Feature",
  "properties": {
    "tgn:hierarchy":[
        "tgn:2469082",
        "tgn:1000001",
        "tgn:7012149",
        "tgn:2000481",
        "tgn:7007250",
        "tgn:7029392"
    ],
    "tgn:id":2469082,
    "tgn:name":"Long Tom Mountain",
    "tgn:placetype":[
        "aat:300008798"
    ]
},
  "bbox": [],
  "geometry": {"coordinates":[-114.5667,45.3333],"type":"Point"}
}