<<<<<<< HEAD
{
  "id": 2252780,
  "type": "Feature",
  "properties": {
    "tgn:hierarchy":[
        "tgn:2252780",
        "tgn:1000001",
        "tgn:2000467",
        "tgn:7012149",
        "tgn:7007250",
        "tgn:7029392"
    ],
    "tgn:id":2252780,
    "tgn:name":"Connor Creek",
    "tgn:placetype":[
        "aat:300008706"
    ]
},
  "bbox": [],
  "geometry": {"coordinates":[-113.5833,42.3],"type":"Point"}
}
=======
{"geometry":{"type":"Point","coordinates":[-113.583300,42.300000]},"type":"Feature","properties":{"hierarchy":["tgn:2252780","tgn:1000001","tgn:2000467","tgn:7012149","tgn:7007250","tgn:7029392"],"placetype":["aat:300008706"],"id":2252780,"name:xx":"Connor Creek"}}
>>>>>>> 03f74aca74312dbeaf24d7e61306dd6a786dc3d0
