{
  "id": 2426128,
  "type": "Feature",
  "properties": {
    "tgn:hierarchy":[
        "tgn:2426128",
        "tgn:1000001",
        "tgn:7012149",
        "tgn:7007568",
        "tgn:7029392"
    ],
    "tgn:id":2426128,
    "tgn:name":"Jones Brook",
    "tgn:placetype":[
        "aat:300008699"
    ]
},
  "bbox": [],
  "geometry": {"coordinates":[-74.7667,43.55],"type":"Point"}
}