{
  "id": 7495626,
  "type": "Feature",
  "properties": {
    "tgn:hierarchy":[
        "tgn:7495626",
        "tgn:1000004",
        "tgn:7001014",
        "tgn:1000141",
        "tgn:7029392"
    ],
    "tgn:id":7495626,
    "tgn:name":"Maguang Guoxiao",
    "tgn:placetype":[
        "aat:300006495"
    ]
},
  "bbox": [],
  "geometry": {"coordinates":[120.351138,23.705431],"type":"Point"}
}