{
  "id": 2505244,
  "type": "Feature",
  "properties": {
    "tgn:hierarchy":[
        "tgn:2505244",
        "tgn:2000090",
        "tgn:1000001",
        "tgn:7006451",
        "tgn:7012149",
        "tgn:7029392"
    ],
    "tgn:id":2505244,
    "tgn:name":"Mel Tank",
    "tgn:placetype":[
        "aat:300006191"
    ]
},
  "bbox": [],
  "geometry": {"coordinates":[-109.3833,33.9667],"type":"Point"}
}