{
  "id": 2376820,
  "type": "Feature",
  "properties": {
    "tgn:hierarchy":[
        "tgn:2376820",
        "tgn:1000001",
        "tgn:7012149",
        "tgn:2002373",
        "tgn:7007923",
        "tgn:7029392"
    ],
    "tgn:id":2376820,
    "tgn:name":"Hardys Reservoir",
    "tgn:placetype":[
        "aat:300006191"
    ]
},
  "bbox": [],
  "geometry": {"coordinates":[-108.9667,43.75],"type":"Point"}
}