<<<<<<< HEAD
{
  "id": 7376445,
  "type": "Feature",
  "properties": {
    "tgn:hierarchy":[
        "tgn:7376445",
        "tgn:7005581",
        "tgn:1000001",
        "tgn:7005560",
        "tgn:7029392"
    ],
    "tgn:id":7376445,
    "tgn:name":"Rancho Las Adelas",
    "tgn:placetype":[
        "aat:300000241"
    ]
},
  "bbox": [],
  "geometry": {"coordinates":[-104.85,27.266667],"type":"Point"}
}
=======
{"geometry":{"type":"Point","coordinates":[-104.850000,27.266667]},"type":"Feature","properties":{"hierarchy":["tgn:7376445","tgn:7005581","tgn:1000001","tgn:7005560","tgn:7029392"],"placetype":["aat:300000241"],"id":7376445,"name:xx":"Rancho Las Adelas"}}
>>>>>>> 03f74aca74312dbeaf24d7e61306dd6a786dc3d0
