{
  "id": 2691933,
  "type": "Feature",
  "properties": {
    "tgn:hierarchy":[
        "tgn:2691933",
        "tgn:1000001",
        "tgn:7012149",
        "tgn:1002440",
        "tgn:7007568",
        "tgn:7029392"
    ],
    "tgn:id":2691933,
    "tgn:name":"State Brook Mountain",
    "tgn:placetype":[
        "aat:300008798"
    ]
},
  "bbox": [],
  "geometry": {"coordinates":[-74.5667,43.25],"type":"Point"}
}