{
  "id": 1079087,
  "type": "Feature",
  "properties": {
    "tgn:hierarchy":[
        "tgn:1079087",
        "tgn:1000004",
        "tgn:7016768",
        "tgn:7000231",
        "tgn:7029392"
    ],
    "tgn:id":1079087,
    "tgn:name":"Fedeshk",
    "tgn:placetype":[
        "aat:300008347"
    ]
},
  "bbox": [],
  "geometry": {"coordinates":[58.85,32.75],"type":"Point"}
}