{
  "id": 7456580,
  "type": "Feature",
  "properties": {
    "tgn:hierarchy":[
        "tgn:7456580",
        "tgn:7002444",
        "tgn:1000003",
        "tgn:7029508",
        "tgn:7008591",
        "tgn:7029392"
    ],
    "tgn:id":7456580,
    "tgn:name:en":"May Wick",
    "tgn:placetype":[
        "aat:300132316"
    ]
},
  "bbox": [],
  "geometry": {"coordinates":[-1.316667,60.016667],"type":"Point"}
}