{
  "id": 2345932,
  "type": "Feature",
  "properties": {
    "tgn:hierarchy":[
        "tgn:2345932",
        "tgn:1000001",
        "tgn:1002191",
        "tgn:7012149",
        "tgn:7007826",
        "tgn:7029392"
    ],
    "tgn:id":2345932,
    "tgn:name":"Gary Mountain",
    "tgn:placetype":[
        "aat:300008798"
    ]
},
  "bbox": [],
  "geometry": {"coordinates":[-97.7333,31.75],"type":"Point"}
}