{
  "id": 7389257,
  "type": "Feature",
  "properties": {
    "tgn:hierarchy":[
        "tgn:7389257",
        "tgn:1001835",
        "tgn:1000001",
        "tgn:7005560",
        "tgn:7029392"
    ],
    "tgn:id":7389257,
    "tgn:name":"Pil\u00f3n de Az\u00facar, Roca",
    "tgn:placetype":[
        "aat:300011692"
    ]
},
  "bbox": [],
  "geometry": {"coordinates":[-116.958056,32.221389],"type":"Point"}
}