{
  "id": 2137636,
  "type": "Feature",
  "properties": {
    "tgn:hierarchy":[
        "tgn:2137636",
        "tgn:1000001",
        "tgn:7012149",
        "tgn:2000351",
        "tgn:7007248",
        "tgn:7029392"
    ],
    "tgn:id":2137636,
    "tgn:name":"Arnold Mill",
    "tgn:placetype":[
        "aat:300008347"
    ]
},
  "bbox": [],
  "geometry": {"coordinates":[-84.3833,34.1167],"type":"Point"}
}