{
  "id": 7349306,
  "type": "Feature",
  "properties": {
    "tgn:hierarchy":[
        "tgn:7349306",
        "tgn:7005581",
        "tgn:1000001",
        "tgn:7005560",
        "tgn:7029392"
    ],
    "tgn:id":7349306,
    "tgn:name":"Allende",
    "tgn:placetype":[
        "aat:300008347"
    ]
},
  "bbox": [],
  "geometry": {"coordinates":[-105.75,31.15],"type":"Point"}
}