{
  "id": 2583532,
  "type": "Feature",
  "properties": {
    "tgn:hierarchy":[
        "tgn:2583532",
        "tgn:1000001",
        "tgn:7012149",
        "tgn:2001873",
        "tgn:7007825",
        "tgn:7029392"
    ],
    "tgn:id":2583532,
    "tgn:name":"Pine Ridge",
    "tgn:placetype":[
        "aat:300266640"
    ]
},
  "bbox": [],
  "geometry": {"coordinates":[-83.2333,36.3667],"type":"Point"}
}