{
  "id": 7404215,
  "type": "Feature",
  "properties": {
    "tgn:hierarchy":[
        "tgn:7404215",
        "tgn:7005585",
        "tgn:1000001",
        "tgn:7005560",
        "tgn:7029392"
    ],
    "tgn:id":7404215,
    "tgn:name":"San Pablo",
    "tgn:placetype":[
        "aat:300008347"
    ]
},
  "bbox": [],
  "geometry": {"coordinates":[-100.466667,18.033333],"type":"Point"}
}