<<<<<<< HEAD
{
  "id": 7247834,
  "type": "Feature",
  "properties": {
    "tgn:hierarchy":[
        "tgn:7247834",
        "tgn:7003465",
        "tgn:1000003",
        "tgn:1000063",
        "tgn:4012014",
        "tgn:7029392"
    ],
    "tgn:id":7247834,
    "tgn:name":"Ch\u00eane al Pierre",
    "tgn:placetype":[
        "aat:300008347"
    ]
},
  "bbox": [],
  "geometry": {"coordinates":[5.666667,50.333333],"type":"Point"}
}
=======
{"geometry":{"type":"Point","coordinates":[5.666667,50.333333]},"type":"Feature","properties":{"hierarchy":["tgn:7247834","tgn:7003465","tgn:1000003","tgn:1000063","tgn:4012014","tgn:7029392"],"placetype":["aat:300008347"],"id":7247834,"name:xx":"Ch\u00eane al Pierre"}}
>>>>>>> 03f74aca74312dbeaf24d7e61306dd6a786dc3d0
