{
  "id": 2095890,
  "type": "Feature",
  "properties": {
    "tgn:hierarchy":[
        "tgn:2095890",
        "tgn:2001731",
        "tgn:1000001",
        "tgn:7012149",
        "tgn:7007712",
        "tgn:7029392"
    ],
    "tgn:id":2095890,
    "tgn:name":"Grays Hill",
    "tgn:placetype":[
        "aat:300008347",
        "aat:300387210"
    ]
},
  "bbox": [],
  "geometry": {"coordinates":[-80.7333,32.4833],"type":"Point"}
}