{
  "id": 1073814,
  "type": "Feature",
  "properties": {
    "tgn:hierarchy":[
        "tgn:1073814",
        "tgn:1000004",
        "tgn:7002087",
        "tgn:1000111",
        "tgn:7029392"
    ],
    "tgn:id":1073814,
    "tgn:name":"Zh\u00eahor",
    "tgn:placetype":[
        "aat:300008347"
    ]
},
  "bbox": [],
  "geometry": {"coordinates":[100.2833,31.65],"type":"Point"}
}