{
  "id": 1068977,
  "type": "Feature",
  "properties": {
    "tgn:hierarchy":[
        "tgn:1068977",
        "tgn:1000004",
        "tgn:7002081",
        "tgn:1000111",
        "tgn:7029392"
    ],
    "tgn:id":1068977,
    "tgn:name":"Huashan",
    "tgn:placetype":[
        "aat:300008347"
    ]
},
  "bbox": [],
  "geometry": {"coordinates":[116.7333,34.6167],"type":"Point"}
}