{
  "id": 7283648,
  "type": "Feature",
  "properties": {
    "tgn:hierarchy":[
        "tgn:7283648",
        "tgn:1001637",
        "tgn:1000049",
        "tgn:1000002",
        "tgn:7029392"
    ],
    "tgn:id":7283648,
    "tgn:name":"Panquinagro, Cerro",
    "tgn:placetype":[
        "aat:300008795"
    ]
},
  "bbox": [],
  "geometry": {"coordinates":[-72.683333,-36.333333],"type":"Point"}
}