{
  "id": 7277878,
  "type": "Feature",
  "properties": {
    "tgn:hierarchy":[
        "tgn:7277878",
        "tgn:1001695",
        "tgn:1000049",
        "tgn:1000002",
        "tgn:7029392"
    ],
    "tgn:id":7277878,
    "tgn:name":"Venero",
    "tgn:placetype":[
        "aat:300008795"
    ]
},
  "bbox": [],
  "geometry": {"coordinates":[-71.15,-34.216667],"type":"Point"}
}