{
  "id": 7540595,
  "type": "Feature",
  "properties": {
    "tgn:hierarchy":[
        "tgn:7540595",
        "tgn:7001242",
        "tgn:7001311",
        "tgn:7016833",
        "tgn:7029392"
    ],
    "tgn:id":7540595,
    "tgn:name:en":"Serei, Wadi el",
    "tgn:placetype":[
        "aat:300379998"
    ]
},
  "bbox": [],
  "geometry": {"coordinates":[32.998015,26.107162],"type":"Point"}
}