{
  "id": 2135133,
  "type": "Feature",
  "properties": {
    "tgn:hierarchy":[
        "tgn:2135133",
        "tgn:1000001",
        "tgn:7012149",
        "tgn:2001983",
        "tgn:7007826",
        "tgn:7029392"
    ],
    "tgn:id":2135133,
    "tgn:name":"Anthony",
    "tgn:placetype":[
        "aat:300008347"
    ]
},
  "bbox": [],
  "geometry": {"coordinates":[-96.3667,33.6667],"type":"Point"}
}