{
  "id": 2760652,
  "type": "Feature",
  "properties": {
    "tgn:hierarchy":[
        "tgn:2760652",
        "tgn:1000001",
        "tgn:7012149",
        "tgn:7007254",
        "tgn:7029392"
    ],
    "tgn:id":2760652,
    "tgn:name":"West Fork Wolf Creek",
    "tgn:placetype":[
        "aat:300008706"
    ]
},
  "bbox": [],
  "geometry": {"coordinates":[-98.8333,39.1667],"type":"Point"}
}