{
  "id": 2077874,
  "type": "Feature",
  "properties": {
    "tgn:hierarchy":[
        "tgn:2077874",
        "tgn:1000001",
        "tgn:2001590",
        "tgn:7012149",
        "tgn:7007705",
        "tgn:7029392"
    ],
    "tgn:id":2077874,
    "tgn:name":"Neche",
    "tgn:placetype":[
        "aat:300008347"
    ]
},
  "bbox": [],
  "geometry": {"coordinates":[-97.55,48.9833],"type":"Point"}
}