{
  "id": 2710782,
  "type": "Feature",
  "properties": {
    "tgn:hierarchy":[
        "tgn:2710782",
        "tgn:1000001",
        "tgn:7012149",
        "tgn:2001924",
        "tgn:7007825",
        "tgn:7029392"
    ],
    "tgn:id":2710782,
    "tgn:name":"Tandy Knob",
    "tgn:placetype":[
        "aat:300008798"
    ]
},
  "bbox": [],
  "geometry": {"coordinates":[-85.5333,35.7667],"type":"Point"}
}