<<<<<<< HEAD
{
  "id": 2337514,
  "type": "Feature",
  "properties": {
    "tgn:hierarchy":[
        "tgn:2337514",
        "tgn:1000001",
        "tgn:7012149",
        "tgn:7022542",
        "tgn:7007825",
        "tgn:7029392"
    ],
    "tgn:id":2337514,
    "tgn:name":"Fowler Spring",
    "tgn:placetype":[
        "aat:300008697"
    ]
},
  "bbox": [],
  "geometry": {"coordinates":[-84.5167,35.3],"type":"Point"}
}
=======
{"geometry":{"type":"Point","coordinates":[-84.516700,35.300000]},"type":"Feature","properties":{"hierarchy":["tgn:2337514","tgn:1000001","tgn:7012149","tgn:7022542","tgn:7007825","tgn:7029392"],"placetype":["aat:300008697"],"id":2337514,"name:xx":"Fowler Spring"}}
>>>>>>> 03f74aca74312dbeaf24d7e61306dd6a786dc3d0
