{
  "id": 2592174,
  "type": "Feature",
  "properties": {
    "tgn:hierarchy":[
        "tgn:2592174",
        "tgn:1000001",
        "tgn:7012149",
        "tgn:1002793",
        "tgn:7007240",
        "tgn:7029392"
    ],
    "tgn:id":2592174,
    "tgn:name":"Pony Creek",
    "tgn:placetype":[
        "aat:300008706"
    ]
},
  "bbox": [],
  "geometry": {"coordinates":[-81.8667,28.2833],"type":"Point"}
}