{
  "id": 7403214,
  "type": "Feature",
  "properties": {
    "tgn:hierarchy":[
        "tgn:7403214",
        "tgn:1000001",
        "tgn:7005600",
        "tgn:7005560",
        "tgn:7029392"
    ],
    "tgn:id":7403214,
    "tgn:name":"Nohuay\u00fan",
    "tgn:placetype":[
        "aat:300008347"
    ]
},
  "bbox": [],
  "geometry": {"coordinates":[-89.966667,20.966667],"type":"Point"}
}