{
  "id": 2784529,
  "type": "Feature",
  "properties": {
    "tgn:hierarchy":[
        "tgn:2784529",
        "tgn:1000001",
        "tgn:7012149",
        "tgn:2001553",
        "tgn:7007709",
        "tgn:7029392"
    ],
    "tgn:id":2784529,
    "tgn:name":"Yates Creek",
    "tgn:placetype":[
        "aat:300008706"
    ]
},
  "bbox": [],
  "geometry": {"coordinates":[-81.3833,36.15],"type":"Point"}
}