{
  "id": 2321691,
  "type": "Feature",
  "properties": {
    "tgn:hierarchy":[
        "tgn:2321691",
        "tgn:1000001",
        "tgn:7012149",
        "tgn:2001716",
        "tgn:7007708",
        "tgn:7029392"
    ],
    "tgn:id":2321691,
    "tgn:name":"Fairview Mountain",
    "tgn:placetype":[
        "aat:300008798"
    ]
},
  "bbox": [],
  "geometry": {"coordinates":[-122.65,43.9167],"type":"Point"}
}