{
  "id": 7237893,
  "type": "Feature",
  "properties": {
    "tgn:hierarchy":[
        "tgn:7237893",
        "tgn:7003466",
        "tgn:1000003",
        "tgn:1000063",
        "tgn:4012014",
        "tgn:7029392"
    ],
    "tgn:id":7237893,
    "tgn:name":"Gramptinne",
    "tgn:placetype":[
        "aat:300008347"
    ]
},
  "bbox": [],
  "geometry": {"coordinates":[5.095323,50.382163],"type":"Point"}
}