{
  "id": 7335879,
  "type": "Feature",
  "properties": {
    "tgn:hierarchy":[
        "tgn:7335879",
        "tgn:7002807",
        "tgn:1000003",
        "tgn:7003837",
        "tgn:1000095",
        "tgn:7029392"
    ],
    "tgn:id":7335879,
    "tgn:name":"Fraile, Ribera del",
    "tgn:placetype":[
        "aat:300008699"
    ]
},
  "bbox": [],
  "geometry": {"coordinates":[-7.066667,39.233333],"type":"Point"}
}