{
  "id": 2361133,
  "type": "Feature",
  "properties": {
    "tgn:hierarchy":[
        "tgn:2361133",
        "tgn:7006450",
        "tgn:1000001",
        "tgn:7012149",
        "tgn:7019760",
        "tgn:7029392"
    ],
    "tgn:id":2361133,
    "tgn:name":"Grave Island",
    "tgn:placetype":[
        "aat:300008791"
    ]
},
  "bbox": [],
  "geometry": {"coordinates":[-134.0667,57.2667],"type":"Point"}
}