{
  "id": 2406689,
  "type": "Feature",
  "properties": {
    "tgn:hierarchy":[
        "tgn:2406689",
        "tgn:1000001",
        "tgn:2000920",
        "tgn:7012149",
        "tgn:7007515",
        "tgn:7029392"
    ],
    "tgn:id":2406689,
    "tgn:name":"Hunt Hill",
    "tgn:placetype":[
        "aat:300008798"
    ]
},
  "bbox": [],
  "geometry": {"coordinates":[-70.3167,43.85],"type":"Point"}
}