<<<<<<< HEAD
{
  "id": 2406689,
  "type": "Feature",
  "properties": {
    "tgn:hierarchy":[
        "tgn:2406689",
        "tgn:1000001",
        "tgn:2000920",
        "tgn:7012149",
        "tgn:7007515",
        "tgn:7029392"
    ],
    "tgn:id":2406689,
    "tgn:name":"Hunt Hill",
    "tgn:placetype":[
        "aat:300008798"
    ]
},
  "bbox": [],
  "geometry": {"coordinates":[-70.3167,43.85],"type":"Point"}
}
=======
{"geometry":{"type":"Point","coordinates":[-70.316700,43.850000]},"type":"Feature","properties":{"hierarchy":["tgn:2406689","tgn:1000001","tgn:2000920","tgn:7012149","tgn:7007515","tgn:7029392"],"placetype":["aat:300008798"],"id":2406689,"name:xx":"Hunt Hill"}}
>>>>>>> 03f74aca74312dbeaf24d7e61306dd6a786dc3d0
