{
  "id": 7536173,
  "type": "Feature",
  "properties": {
    "tgn:hierarchy":[
        "tgn:7536173",
        "tgn:7001242",
        "tgn:7016833",
        "tgn:7001334",
        "tgn:7029392"
    ],
    "tgn:id":7536173,
    "tgn:name:en":"B\u00eer Germashin 4",
    "tgn:placetype":[
        "aat:300006207"
    ]
},
  "bbox": [],
  "geometry": {"coordinates":[30.516667,25.066667],"type":"Point"}
}