{
  "id": 7348832,
  "type": "Feature",
  "properties": {
    "tgn:hierarchy":[
        "tgn:7348832",
        "tgn:7005583",
        "tgn:1000001",
        "tgn:7005560",
        "tgn:7029392"
    ],
    "tgn:id":7348832,
    "tgn:name":"Agua Caliente",
    "tgn:placetype":[
        "aat:300008347"
    ]
},
  "bbox": [],
  "geometry": {"coordinates":[-105.766667,25.433333],"type":"Point"}
}