{
  "id": 7198558,
  "type": "Feature",
  "properties": {
    "tgn:hierarchy":[
        "tgn:7198558",
        "tgn:1000003",
        "tgn:7003677",
        "tgn:7000084",
        "tgn:7029392"
    ],
    "tgn:id":7198558,
    "tgn:name":"Eichholz",
    "tgn:placetype":[
        "aat:300008347",
        "aat:300387200"
    ]
},
  "bbox": [],
  "geometry": {"coordinates":[7.716667,50.916667],"type":"Point"}
}