{
  "id": 7351569,
  "type": "Feature",
  "properties": {
    "tgn:hierarchy":[
        "tgn:7351569",
        "tgn:1000001",
        "tgn:1001960",
        "tgn:7005560",
        "tgn:7029392"
    ],
    "tgn:id":7351569,
    "tgn:name":"Bandera, Sierra de la",
    "tgn:placetype":[
        "aat:300008795"
    ]
},
  "bbox": [],
  "geometry": {"coordinates":[-109.883333,28.683333],"type":"Point"}
}