{
  "id": 7449644,
  "type": "Feature",
  "properties": {
    "tgn:hierarchy":[
        "tgn:7449644",
        "tgn:7002448",
        "tgn:7008699",
        "tgn:1000003",
        "tgn:7008591",
        "tgn:7029392"
    ],
    "tgn:id":7449644,
    "tgn:name:en":"Glendermot",
    "tgn:placetype":[
        "aat:300000773"
    ]
},
  "bbox": [],
  "geometry": {"coordinates":[-7.333333,54.95],"type":"Point"}
}