{
  "id": 7305315,
  "type": "Feature",
  "properties": {
    "tgn:hierarchy":[
        "tgn:7305315",
        "tgn:7002826",
        "tgn:7001158",
        "tgn:1000003",
        "tgn:1000095",
        "tgn:7029392"
    ],
    "tgn:id":7305315,
    "tgn:name":"Las Oma\u00f1as",
    "tgn:placetype":[
        "aat:300008347"
    ]
},
  "bbox": [],
  "geometry": {"coordinates":[-5.866667,42.683333],"type":"Point"}
}