{
  "id": 2411720,
  "type": "Feature",
  "properties": {
    "tgn:hierarchy":[
        "tgn:2411720",
        "tgn:1000001",
        "tgn:7012149",
        "tgn:2001931",
        "tgn:7007825",
        "tgn:7029392"
    ],
    "tgn:id":2411720,
    "tgn:name":"Indian Lake Farms",
    "tgn:placetype":[
        "aat:300008347"
    ]
},
  "bbox": [],
  "geometry": {"coordinates":[-86.55,36.2333],"type":"Point"}
}