{
  "id": 7560161,
  "type": "Feature",
  "properties": {
    "tgn:hierarchy":[
        "tgn:7560161",
        "tgn:1000004",
        "tgn:7000198",
        "tgn:7016722",
        "tgn:7029392"
    ],
    "tgn:id":7560161,
    "tgn:name:en":"Nagla Tabald\u0101r",
    "tgn:placetype":[
        "aat:300008347"
    ]
},
  "bbox": [],
  "geometry": {"coordinates":[79.376747,27.248366],"type":"Point"}
}