{
  "id": 7128351,
  "type": "Feature",
  "properties": {
    "tgn:hierarchy":[
        "tgn:7128351",
        "tgn:1000003",
        "tgn:7003677",
        "tgn:7000084",
        "tgn:7029392"
    ],
    "tgn:id":7128351,
    "tgn:name":"Oberl\u00fcckerath",
    "tgn:placetype":[
        "aat:300387200"
    ]
},
  "bbox": [],
  "geometry": {"coordinates":[7.433333,50.816667],"type":"Point"}
}