{
  "id": 2281172,
  "type": "Feature",
  "properties": {
    "tgn:hierarchy":[
        "tgn:2281172",
        "tgn:1000001",
        "tgn:2001432",
        "tgn:7012149",
        "tgn:7007566",
        "tgn:7029392"
    ],
    "tgn:id":2281172,
    "tgn:name":"Deep Lake",
    "tgn:placetype":[
        "aat:300008680"
    ]
},
  "bbox": [],
  "geometry": {"coordinates":[-105.1167,36.25],"type":"Point"}
}