{
  "id": 7317968,
  "type": "Feature",
  "properties": {
    "tgn:hierarchy":[
        "tgn:7317968",
        "tgn:7016598",
        "tgn:1000049",
        "tgn:1000002",
        "tgn:7029392"
    ],
    "tgn:id":7317968,
    "tgn:name":"Cifuncho, Caleta",
    "tgn:placetype":[
        "aat:300132317"
    ]
},
  "bbox": [],
  "geometry": {"coordinates":[-70.65,-25.633333],"type":"Point"}
}