{
  "id": 2561706,
  "type": "Feature",
  "properties": {
    "tgn:hierarchy":[
        "tgn:2561706",
        "tgn:1000001",
        "tgn:7012149",
        "tgn:2002125",
        "tgn:7007827",
        "tgn:7029392"
    ],
    "tgn:id":2561706,
    "tgn:name":"Ostler Spring",
    "tgn:placetype":[
        "aat:300008697"
    ]
},
  "bbox": [],
  "geometry": {"coordinates":[-110.9167,39.8833],"type":"Point"}
}