{
  "id": 2409114,
  "type": "Feature",
  "properties": {
    "tgn:hierarchy":[
        "tgn:2409114",
        "tgn:1000001",
        "tgn:7012149",
        "tgn:2001289",
        "tgn:7007524",
        "tgn:7029392"
    ],
    "tgn:id":2409114,
    "tgn:name":"Ice Creek",
    "tgn:placetype":[
        "aat:300008706"
    ]
},
  "bbox": [],
  "geometry": {"coordinates":[-110.7667,46.6667],"type":"Point"}
}