{
  "id": 7296378,
  "type": "Feature",
  "properties": {
    "tgn:hierarchy":[
        "tgn:7296378",
        "tgn:7002835",
        "tgn:7001158",
        "tgn:1000003",
        "tgn:1000095",
        "tgn:7029392"
    ],
    "tgn:id":7296378,
    "tgn:name":"Villarino, Rivera de",
    "tgn:placetype":[
        "aat:300266554",
        "aat:300008699"
    ]
},
  "bbox": [],
  "geometry": {"coordinates":[-6.416667,41.183333],"type":"Point"}
}