{
  "id": 2225287,
  "type": "Feature",
  "properties": {
    "tgn:hierarchy":[
        "tgn:2225287",
        "tgn:1000001",
        "tgn:7012149",
        "tgn:2002265",
        "tgn:7013961",
        "tgn:7029392"
    ],
    "tgn:id":2225287,
    "tgn:name":"Castle Mountain",
    "tgn:placetype":[
        "aat:300008798"
    ]
},
  "bbox": [],
  "geometry": {"coordinates":[-78.4167,39.3833],"type":"Point"}
}