{
  "id": 2164055,
  "type": "Feature",
  "properties": {
    "tgn:hierarchy":[
        "tgn:2164055",
        "tgn:1000001",
        "tgn:7012149",
        "tgn:2001281",
        "tgn:7007524",
        "tgn:7029392"
    ],
    "tgn:id":2164055,
    "tgn:name":"Berkin Gulch",
    "tgn:placetype":[
        "aat:300008761"
    ]
},
  "bbox": [],
  "geometry": {"coordinates":[-112.1833,46.1833],"type":"Point"}
}