{
  "id": 2440758,
  "type": "Feature",
  "properties": {
    "tgn:hierarchy":[
        "tgn:2440758",
        "tgn:1000001",
        "tgn:1002415",
        "tgn:7012149",
        "tgn:7007828",
        "tgn:7029392"
    ],
    "tgn:id":2440758,
    "tgn:name":"Knight Point",
    "tgn:placetype":[
        "aat:300008850"
    ]
},
  "bbox": [],
  "geometry": {"coordinates":[-73.2833,44.7667],"type":"Point"}
}