<<<<<<< HEAD
{
  "id": 2762643,
  "type": "Feature",
  "properties": {
    "tgn:hierarchy":[
        "tgn:2762643",
        "tgn:1000001",
        "tgn:7012149",
        "tgn:2001230",
        "tgn:7007523",
        "tgn:7029392"
    ],
    "tgn:id":2762643,
    "tgn:name":"Westcott",
    "tgn:placetype":[
        "aat:300008347"
    ]
},
  "bbox": [],
  "geometry": {"coordinates":[-91.8833,37.9667],"type":"Point"}
}
=======
{"geometry":{"type":"Point","coordinates":[-91.883300,37.966700]},"type":"Feature","properties":{"hierarchy":["tgn:2762643","tgn:1000001","tgn:7012149","tgn:2001230","tgn:7007523","tgn:7029392"],"placetype":["aat:300008347"],"id":2762643,"name:xx":"Westcott"}}
>>>>>>> 03f74aca74312dbeaf24d7e61306dd6a786dc3d0
