{
  "id": 2747083,
  "type": "Feature",
  "properties": {
    "tgn:hierarchy":[
        "tgn:2747083",
        "tgn:1000001",
        "tgn:2002109",
        "tgn:7012149",
        "tgn:7007827",
        "tgn:7029392"
    ],
    "tgn:id":2747083,
    "tgn:name":"Wagon Box Mesa",
    "tgn:placetype":[
        "aat:300008798"
    ]
},
  "bbox": [],
  "geometry": {"coordinates":[-111.0667,37.8167],"type":"Point"}
}