{
  "id": 2010439,
  "type": "Feature",
  "properties": {
    "tgn:hierarchy":[
        "tgn:2010439",
        "tgn:1000001",
        "tgn:7012149",
        "tgn:1002298",
        "tgn:7007157",
        "tgn:7029392"
    ],
    "tgn:id":2010439,
    "tgn:name":"Byron",
    "tgn:placetype":[
        "aat:300008347"
    ]
},
  "bbox": [],
  "geometry": {"coordinates":[-121.6333,37.8667],"type":"Point"}
}