{
  "id": 7183906,
  "type": "Feature",
  "properties": {
    "tgn:hierarchy":[
        "tgn:7183906",
        "tgn:1000003",
        "tgn:7003676",
        "tgn:7000084",
        "tgn:7029392"
    ],
    "tgn:id":7183906,
    "tgn:name":"Giffernkolk",
    "tgn:placetype":[
        "aat:300008905"
    ]
},
  "bbox": [],
  "geometry": {"coordinates":[7.133333,52.633333],"type":"Point"}
}