<<<<<<< HEAD
{
  "id": 2406715,
  "type": "Feature",
  "properties": {
    "tgn:hierarchy":[
        "tgn:2406715",
        "tgn:1000001",
        "tgn:7012149",
        "tgn:2000912",
        "tgn:7007256",
        "tgn:7029392"
    ],
    "tgn:id":2406715,
    "tgn:name":"Hunt Lake",
    "tgn:placetype":[
        "aat:300008680"
    ]
},
  "bbox": [],
  "geometry": {"coordinates":[-89.7333,30.9833],"type":"Point"}
}
=======
{"geometry":{"type":"Point","coordinates":[-89.733300,30.983300]},"type":"Feature","properties":{"hierarchy":["tgn:2406715","tgn:1000001","tgn:7012149","tgn:2000912","tgn:7007256","tgn:7029392"],"placetype":["aat:300008680"],"id":2406715,"name:xx":"Hunt Lake"}}
>>>>>>> 03f74aca74312dbeaf24d7e61306dd6a786dc3d0
