{
  "id": 2164914,
  "type": "Feature",
  "properties": {
    "tgn:hierarchy":[
        "tgn:2164914",
        "tgn:1000001",
        "tgn:1002903",
        "tgn:7012149",
        "tgn:7007565",
        "tgn:7029392"
    ],
    "tgn:id":2164914,
    "tgn:name":"Best Lake",
    "tgn:placetype":[
        "aat:300008680"
    ]
},
  "bbox": [],
  "geometry": {"coordinates":[-74.4333,40.6333],"type":"Point"}
}