{
  "id": 7288155,
  "type": "Feature",
  "properties": {
    "tgn:hierarchy":[
        "tgn:7288155",
        "tgn:1001692",
        "tgn:1000049",
        "tgn:1000002",
        "tgn:7029392"
    ],
    "tgn:id":7288155,
    "tgn:name":"Jord\u00e1n, Estero",
    "tgn:placetype":[
        "aat:300008699"
    ]
},
  "bbox": [],
  "geometry": {"coordinates":[-72.033333,-38.133333],"type":"Point"}
}