{
  "id": 2667532,
  "type": "Feature",
  "properties": {
    "tgn:hierarchy":[
        "tgn:2667532",
        "tgn:1000001",
        "tgn:7012149",
        "tgn:1002636",
        "tgn:7007708",
        "tgn:7029392"
    ],
    "tgn:id":2667532,
    "tgn:name":"Skookum Lakes",
    "tgn:placetype":[
        "aat:300008680"
    ]
},
  "bbox": [],
  "geometry": {"coordinates":[-122.95,45.25],"type":"Point"}
}