{
  "id": 7175035,
  "type": "Feature",
  "properties": {
    "tgn:hierarchy":[
        "tgn:7175035",
        "tgn:7003692",
        "tgn:1000003",
        "tgn:7000084",
        "tgn:7029392"
    ],
    "tgn:id":7175035,
    "tgn:name":"Gro\u00dfer Femelwald",
    "tgn:placetype":[
        "aat:300008863"
    ]
},
  "bbox": [],
  "geometry": {"coordinates":[9.516667,49.016667],"type":"Point"}
}