{
  "id": 7133300,
  "type": "Feature",
  "properties": {
    "tgn:hierarchy":[
        "tgn:7133300",
        "tgn:7003692",
        "tgn:1000003",
        "tgn:7000084",
        "tgn:7029392"
    ],
    "tgn:id":7133300,
    "tgn:name":"Neidling",
    "tgn:placetype":[
        "aat:300008863"
    ]
},
  "bbox": [],
  "geometry": {"coordinates":[9.25,47.95],"type":"Point"}
}