{
  "id": 7289389,
  "type": "Feature",
  "properties": {
    "tgn:hierarchy":[
        "tgn:7289389",
        "tgn:1001768",
        "tgn:1000049",
        "tgn:1000002",
        "tgn:7029392"
    ],
    "tgn:id":7289389,
    "tgn:name":"La Fragua, Loma",
    "tgn:placetype":[
        "aat:300387002"
    ]
},
  "bbox": [],
  "geometry": {"coordinates":[-70.866667,-32.283333],"type":"Point"}
}