{
  "id": 2499409,
  "type": "Feature",
  "properties": {
    "tgn:hierarchy":[
        "tgn:2499409",
        "tgn:1000001",
        "tgn:7012149",
        "tgn:2002301",
        "tgn:7013961",
        "tgn:7029392"
    ],
    "tgn:id":2499409,
    "tgn:name":"McCloud Run",
    "tgn:placetype":[
        "aat:300008699"
    ]
},
  "bbox": [],
  "geometry": {"coordinates":[-80.7833,39.65],"type":"Point"}
}