{
  "id": 7535631,
  "type": "Feature",
  "properties": {
    "tgn:hierarchy":[
        "tgn:7535631",
        "tgn:7001242",
        "tgn:1001075",
        "tgn:7016833",
        "tgn:7029392"
    ],
    "tgn:id":7535631,
    "tgn:name:en":"Ghaz\u0101l, Tall al",
    "tgn:placetype":[
        "aat:300008777"
    ]
},
  "bbox": [],
  "geometry": {"coordinates":[29.930278,31.06],"type":"Point"}
}