{
  "id": 2669298,
  "type": "Feature",
  "properties": {
    "tgn:hierarchy":[
        "tgn:2669298",
        "tgn:1000001",
        "tgn:7012149",
        "tgn:1002794",
        "tgn:7007708",
        "tgn:7029392"
    ],
    "tgn:id":2669298,
    "tgn:name":"Slick Creek",
    "tgn:placetype":[
        "aat:300008706"
    ]
},
  "bbox": [],
  "geometry": {"coordinates":[-123.5333,44.7833],"type":"Point"}
}