{
  "id": 7420859,
  "type": "Feature",
  "properties": {
    "tgn:hierarchy":[
        "tgn:7420859",
        "tgn:7005579",
        "tgn:1000001",
        "tgn:7005560",
        "tgn:7029392"
    ],
    "tgn:id":7420859,
    "tgn:name":"San Jos\u00e9 de Gracia",
    "tgn:placetype":[
        "aat:300008347"
    ]
},
  "bbox": [],
  "geometry": {"coordinates":[-102.416667,22.15],"type":"Point"}
}