{
  "id": 2212832,
  "type": "Feature",
  "properties": {
    "tgn:hierarchy":[
        "tgn:2212832",
        "tgn:1000001",
        "tgn:7012149",
        "tgn:1002406",
        "tgn:7007520",
        "tgn:7029392"
    ],
    "tgn:id":2212832,
    "tgn:name":"C S Mott Lake",
    "tgn:placetype":[
        "aat:300006191"
    ]
},
  "bbox": [],
  "geometry": {"coordinates":[-83.65,43.0667],"type":"Point"}
}