{
  "id": 7552326,
  "type": "Feature",
  "properties": {
    "tgn:hierarchy":[
        "tgn:7552326",
        "tgn:1000004",
        "tgn:7000198",
        "tgn:7000799",
        "tgn:7029392"
    ],
    "tgn:id":7552326,
    "tgn:name:en":"N\u0101r Kot",
    "tgn:placetype":[
        "aat:300008347"
    ]
},
  "bbox": [],
  "geometry": {"coordinates":[74.702924,33.261323],"type":"Point"}
}