{
  "id": 2011022,
  "type": "Feature",
  "properties": {
    "tgn:hierarchy":[
        "tgn:2011022",
        "tgn:1000001",
        "tgn:7012149",
        "tgn:7007157",
        "tgn:7014516",
        "tgn:7029392"
    ],
    "tgn:id":2011022,
    "tgn:name":"Del Rio Woods",
    "tgn:placetype":[
        "aat:300008347",
        "aat:300387210"
    ]
},
  "bbox": [],
  "geometry": {"coordinates":[-122.8333,38.6167],"type":"Point"}
}