{
  "id": 2355863,
  "type": "Feature",
  "properties": {
    "tgn:hierarchy":[
        "tgn:2355863",
        "tgn:1000001",
        "tgn:2001570",
        "tgn:7012149",
        "tgn:7007705",
        "tgn:7029392"
    ],
    "tgn:id":2355863,
    "tgn:name":"Goose Lake",
    "tgn:placetype":[
        "aat:300008680"
    ]
},
  "bbox": [],
  "geometry": {"coordinates":[-98.9667,47.8167],"type":"Point"}
}