{
  "id": 7497187,
  "type": "Feature",
  "properties": {
    "tgn:hierarchy":[
        "tgn:7497187",
        "tgn:1000004",
        "tgn:7001009",
        "tgn:1000141",
        "tgn:7029392"
    ],
    "tgn:id":7497187,
    "tgn:name":"Chongde Guozhong",
    "tgn:placetype":[
        "aat:300006495"
    ]
},
  "bbox": [],
  "geometry": {"coordinates":[120.684054,24.174967],"type":"Point"}
}