{
  "id": 7563771,
  "type": "Feature",
  "properties": {
    "tgn:hierarchy":[
        "tgn:7563771",
        "tgn:1000004",
        "tgn:7000198",
        "tgn:7016722",
        "tgn:7029392"
    ],
    "tgn:id":7563771,
    "tgn:name:en":"Beria",
    "tgn:placetype":[
        "aat:300008347"
    ]
},
  "bbox": [],
  "geometry": {"coordinates":[79.808229,26.594079],"type":"Point"}
}