{
  "id": 7269839,
  "type": "Feature",
  "properties": {
    "tgn:hierarchy":[
        "tgn:7269839",
        "tgn:1000003",
        "tgn:7006951",
        "tgn:7016845",
        "tgn:7029392"
    ],
    "tgn:id":7269839,
    "tgn:name:nl":"Mijzen, Polder",
    "tgn:placetype":[
        "aat:300006163"
    ]
},
  "bbox": [],
  "geometry": {"coordinates":[4.916667,52.616667],"type":"Point"}
}