{
  "id": 2781266,
  "type": "Feature",
  "properties": {
    "tgn:hierarchy":[
        "tgn:2781266",
        "tgn:1000001",
        "tgn:7012149",
        "tgn:2001146",
        "tgn:7007522",
        "tgn:7029392"
    ],
    "tgn:id":2781266,
    "tgn:name":"Woodlake",
    "tgn:placetype":[
        "aat:300008347"
    ]
},
  "bbox": [],
  "geometry": {"coordinates":[-90.0333,32.3833],"type":"Point"}
}