{
  "id": 2772762,
  "type": "Feature",
  "properties": {
    "tgn:hierarchy":[
        "tgn:2772762",
        "tgn:1000001",
        "tgn:7012149",
        "tgn:2000225",
        "tgn:7007158",
        "tgn:7029392"
    ],
    "tgn:id":2772762,
    "tgn:name":"Williams Gulch",
    "tgn:placetype":[
        "aat:300008761"
    ]
},
  "bbox": [],
  "geometry": {"coordinates":[-108.0333,37.4333],"type":"Point"}
}