{
  "id": 7042815,
  "type": "Feature",
  "properties": {
    "tgn:hierarchy":[
        "tgn:7042815",
        "tgn:1003440",
        "tgn:1000003",
        "tgn:7003124",
        "tgn:1000080",
        "tgn:7029392"
    ],
    "tgn:id":7042815,
    "tgn:name":"Rissa",
    "tgn:placetype":[
        "aat:300008347"
    ]
},
  "bbox": [],
  "geometry": {"coordinates":[11.233333,46.716667],"type":"Point"}
}