{
  "id": 7331648,
  "type": "Feature",
  "properties": {
    "tgn:hierarchy":[
        "tgn:7331648",
        "tgn:7002803",
        "tgn:1001647",
        "tgn:1000003",
        "tgn:1000095",
        "tgn:7029392"
    ],
    "tgn:id":7331648,
    "tgn:name":"Janoso, Cerro",
    "tgn:placetype":[
        "aat:300008777"
    ]
},
  "bbox": [],
  "geometry": {"coordinates":[-2.766667,38.55],"type":"Point"}
}