{
  "id": 7268672,
  "type": "Feature",
  "properties": {
    "tgn:hierarchy":[
        "tgn:7268672",
        "tgn:7003616",
        "tgn:1000003",
        "tgn:7016845",
        "tgn:7029392"
    ],
    "tgn:id":7268672,
    "tgn:name:nl":"Noorderleegpolder",
    "tgn:placetype":[
        "aat:300006163"
    ]
},
  "bbox": [],
  "geometry": {"coordinates":[5.733333,53.316667],"type":"Point"}
}