{
  "id": 2628643,
  "type": "Feature",
  "properties": {
    "tgn:hierarchy":[
        "tgn:2628643",
        "tgn:1000001",
        "tgn:7012149",
        "tgn:1002594",
        "tgn:7007920",
        "tgn:7029392"
    ],
    "tgn:id":2628643,
    "tgn:name":"Root House Creek",
    "tgn:placetype":[
        "aat:300008706"
    ]
},
  "bbox": [],
  "geometry": {"coordinates":[-123.1333,46.4667],"type":"Point"}
}