{
  "id": 7436545,
  "type": "Feature",
  "properties": {
    "tgn:hierarchy":[
        "tgn:7436545",
        "tgn:7005581",
        "tgn:1000001",
        "tgn:7005560",
        "tgn:7029392"
    ],
    "tgn:id":7436545,
    "tgn:name":"Santo Domingo",
    "tgn:placetype":[
        "aat:300008347"
    ]
},
  "bbox": [],
  "geometry": {"coordinates":[-106.816667,30.55],"type":"Point"}
}