{
  "id": 7462171,
  "type": "Feature",
  "properties": {
    "tgn:hierarchy":[
        "tgn:7462171",
        "tgn:7019140",
        "tgn:7002444",
        "tgn:1000003",
        "tgn:7008591",
        "tgn:7029392"
    ],
    "tgn:id":7462171,
    "tgn:name:en":"Kirkton of Menmuir",
    "tgn:placetype":[
        "aat:300008347"
    ]
},
  "bbox": [],
  "geometry": {"coordinates":[-2.75,56.766667],"type":"Point"}
}