{
  "id": 2450865,
  "type": "Feature",
  "properties": {
    "tgn:hierarchy":[
        "tgn:2450865",
        "tgn:1000001",
        "tgn:7012149",
        "tgn:2001297",
        "tgn:7007524",
        "tgn:7029392"
    ],
    "tgn:id":2450865,
    "tgn:name":"Liscom Butte",
    "tgn:placetype":[
        "aat:300008798"
    ]
},
  "bbox": [],
  "geometry": {"coordinates":[-105.9667,45.7333],"type":"Point"}
}