{
  "id": 2626128,
  "type": "Feature",
  "properties": {
    "tgn:hierarchy":[
        "tgn:2626128",
        "tgn:1000001",
        "tgn:7012149",
        "tgn:2000448",
        "tgn:7007248",
        "tgn:7029392"
    ],
    "tgn:id":2626128,
    "tgn:name":"Rocky Creek",
    "tgn:placetype":[
        "aat:300008706"
    ]
},
  "bbox": [],
  "geometry": {"coordinates":[-82.7333,33.7333],"type":"Point"}
}