<<<<<<< HEAD
{
  "id": 2156425,
  "type": "Feature",
  "properties": {
    "tgn:hierarchy":[
        "tgn:2156425",
        "tgn:1000001",
        "tgn:7012149",
        "tgn:1002540",
        "tgn:7007520",
        "tgn:7029392"
    ],
    "tgn:id":2156425,
    "tgn:name":"Bearslee Lake",
    "tgn:placetype":[
        "aat:300008680"
    ]
},
  "bbox": [],
  "geometry": {"coordinates":[-85.3,43.1333],"type":"Point"}
}
=======
{"geometry":{"type":"Point","coordinates":[-85.300000,43.133300]},"type":"Feature","properties":{"hierarchy":["tgn:2156425","tgn:1000001","tgn:7012149","tgn:1002540","tgn:7007520","tgn:7029392"],"placetype":["aat:300008680"],"id":2156425,"name:xx":"Bearslee Lake"}}
>>>>>>> 03f74aca74312dbeaf24d7e61306dd6a786dc3d0
