{
  "id": 2570409,
  "type": "Feature",
  "properties": {
    "tgn:hierarchy":[
        "tgn:2570409",
        "tgn:1000001",
        "tgn:7012149",
        "tgn:2001718",
        "tgn:7007708",
        "tgn:7029392"
    ],
    "tgn:id":2570409,
    "tgn:name":"Patch Island",
    "tgn:placetype":[
        "aat:300008791"
    ]
},
  "bbox": [],
  "geometry": {"coordinates":[-116.9667,44.2167],"type":"Point"}
}