{
  "id": 2685395,
  "type": "Feature",
  "properties": {
    "tgn:hierarchy":[
        "tgn:2685395",
        "tgn:1000001",
        "tgn:7016172",
        "tgn:2000116",
        "tgn:7012149",
        "tgn:7029392"
    ],
    "tgn:id":2685395,
    "tgn:name":"Spout Springs Hollow",
    "tgn:placetype":[
        "aat:300008761"
    ]
},
  "bbox": [],
  "geometry": {"coordinates":[-91.9333,35.35],"type":"Point"}
}