{
  "id": 7308820,
  "type": "Feature",
  "properties": {
    "tgn:hierarchy":[
        "tgn:7308820",
        "tgn:1001623",
        "tgn:1000049",
        "tgn:1000002",
        "tgn:7029392"
    ],
    "tgn:id":7308820,
    "tgn:name":"Los Yuyos, Grupo",
    "tgn:placetype":[
        "aat:300008791"
    ]
},
  "bbox": [],
  "geometry": {"coordinates":[-73.55,-44.983333],"type":"Point"}
}