{
  "id": 2446892,
  "type": "Feature",
  "properties": {
    "tgn:hierarchy":[
        "tgn:2446892",
        "tgn:1000001",
        "tgn:7012149",
        "tgn:2000845",
        "tgn:7007255",
        "tgn:7029392"
    ],
    "tgn:id":2446892,
    "tgn:name":"Liberty",
    "tgn:placetype":[
        "aat:300008347"
    ]
},
  "bbox": [],
  "geometry": {"coordinates":[-87.1833,36.8833],"type":"Point"}
}