{
  "id": 7287134,
  "type": "Feature",
  "properties": {
    "tgn:hierarchy":[
        "tgn:7287134",
        "tgn:1001702",
        "tgn:1000049",
        "tgn:1000002",
        "tgn:7029392"
    ],
    "tgn:id":7287134,
    "tgn:name":"Geikie, R\u00edo",
    "tgn:placetype":[
        "aat:300008699"
    ]
},
  "bbox": [],
  "geometry": {"coordinates":[-73.133333,-51.266667],"type":"Point"}
}