{
  "id": 2082379,
  "type": "Feature",
  "properties": {
    "tgn:hierarchy":[
        "tgn:2082379",
        "tgn:1000001",
        "tgn:1002317",
        "tgn:7012149",
        "tgn:7007706",
        "tgn:7029392"
    ],
    "tgn:id":2082379,
    "tgn:name":"Versailles",
    "tgn:placetype":[
        "aat:300008347"
    ]
},
  "bbox": [],
  "geometry": {"coordinates":[-84.4833,40.2167],"type":"Point"}
}