{
  "id": 7590317,
  "type": "Feature",
  "properties": {
    "tgn:hierarchy":[
        "tgn:7590317",
        "tgn:1000004",
        "tgn:7000198",
        "tgn:7000799",
        "tgn:7029392"
    ],
    "tgn:id":7590317,
    "tgn:name:en":"Kund\u0101n",
    "tgn:placetype":[
        "aat:300008347"
    ]
},
  "bbox": [],
  "geometry": {"coordinates":[74.258333,33.804167],"type":"Point"}
}