<<<<<<< HEAD
{
  "id": 7112901,
  "type": "Feature",
  "properties": {
    "tgn:hierarchy":[
        "tgn:7112901",
        "tgn:7003692",
        "tgn:1000003",
        "tgn:7000084",
        "tgn:7029392"
    ],
    "tgn:id":7112901,
    "tgn:name":"Rosenhof",
    "tgn:placetype":[
        "aat:300000206"
    ]
},
  "bbox": [],
  "geometry": {"coordinates":[8.633333,49.466667],"type":"Point"}
}
=======
{"geometry":{"type":"Point","coordinates":[8.633333,49.466667]},"type":"Feature","properties":{"hierarchy":["tgn:7112901","tgn:7003692","tgn:1000003","tgn:7000084","tgn:7029392"],"placetype":["aat:300000206"],"id":7112901,"name:xx":"Rosenhof"}}
>>>>>>> 03f74aca74312dbeaf24d7e61306dd6a786dc3d0
