{
  "id": 2593336,
  "type": "Feature",
  "properties": {
    "tgn:hierarchy":[
        "tgn:2593336",
        "tgn:1000001",
        "tgn:7012149",
        "tgn:1002994",
        "tgn:7007708",
        "tgn:7029392"
    ],
    "tgn:id":2593336,
    "tgn:name":"Popp Reservoir",
    "tgn:placetype":[
        "aat:300006191"
    ]
},
  "bbox": [],
  "geometry": {"coordinates":[-122.9833,45.4833],"type":"Point"}
}