{
  "id": 2272962,
  "type": "Feature",
  "properties": {
    "tgn:hierarchy":[
        "tgn:2272962",
        "tgn:1000001",
        "tgn:7012149",
        "tgn:2002298",
        "tgn:7013961",
        "tgn:7029392"
    ],
    "tgn:id":2272962,
    "tgn:name":"Cutright Run",
    "tgn:placetype":[
        "aat:300008699"
    ]
},
  "bbox": [],
  "geometry": {"coordinates":[-80.2833,38.9333],"type":"Point"}
}