{
  "id": 7562312,
  "type": "Feature",
  "properties": {
    "tgn:hierarchy":[
        "tgn:7562312",
        "tgn:1000004",
        "tgn:7000198",
        "tgn:7016722",
        "tgn:7029392"
    ],
    "tgn:id":7562312,
    "tgn:name:en":"Gauran Purwa",
    "tgn:placetype":[
        "aat:300008347"
    ]
},
  "bbox": [],
  "geometry": {"coordinates":[79.8503,27.142],"type":"Point"}
}