{
  "id": 2306321,
  "type": "Feature",
  "properties": {
    "tgn:hierarchy":[
        "tgn:2306321",
        "tgn:1000001",
        "tgn:2002105",
        "tgn:7012149",
        "tgn:7007827",
        "tgn:7029392"
    ],
    "tgn:id":2306321,
    "tgn:name":"East Fork Carter Creek",
    "tgn:placetype":[
        "aat:300008706"
    ]
},
  "bbox": [],
  "geometry": {"coordinates":[-109.8667,40.7667],"type":"Point"}
}