{
  "id": 2264166,
  "type": "Feature",
  "properties": {
    "tgn:hierarchy":[
        "tgn:2264166",
        "tgn:1000001",
        "tgn:7006451",
        "tgn:7012149",
        "tgn:2000101",
        "tgn:7029392"
    ],
    "tgn:id":2264166,
    "tgn:name":"Coyote Tank",
    "tgn:placetype":[
        "aat:300006191"
    ]
},
  "bbox": [],
  "geometry": {"coordinates":[-111.1167,32.8833],"type":"Point"}
}