{
  "id": 2480231,
  "type": "Feature",
  "properties": {
    "tgn:hierarchy":[
        "tgn:2480231",
        "tgn:1000001",
        "tgn:7012149",
        "tgn:1002773",
        "tgn:7007240",
        "tgn:7029392"
    ],
    "tgn:id":2480231,
    "tgn:name":"Lake Pasadena Heights",
    "tgn:placetype":[
        "aat:300008347"
    ]
},
  "bbox": [],
  "geometry": {"coordinates":[-82.2167,28.3167],"type":"Point"}
}