{
  "id": 2663232,
  "type": "Feature",
  "properties": {
    "tgn:hierarchy":[
        "tgn:2663232",
        "tgn:2000942",
        "tgn:1000001",
        "tgn:7012149",
        "tgn:7007520",
        "tgn:7029392"
    ],
    "tgn:id":2663232,
    "tgn:name":"Silver Creek",
    "tgn:placetype":[
        "aat:300008706"
    ]
},
  "bbox": [],
  "geometry": {"coordinates":[-83.3333,44.7833],"type":"Point"}
}