{
  "id": 2472319,
  "type": "Feature",
  "properties": {
    "tgn:hierarchy":[
        "tgn:2472319",
        "tgn:1000001",
        "tgn:7012149",
        "tgn:1002631",
        "tgn:7007240",
        "tgn:7029392"
    ],
    "tgn:id":2472319,
    "tgn:name":"Louise, Lake",
    "tgn:placetype":[
        "aat:300008680"
    ]
},
  "bbox": [],
  "geometry": {"coordinates":[-82.1333,29.15],"type":"Point"}
}