{
  "id": 7044938,
  "type": "Feature",
  "properties": {
    "tgn:hierarchy":[
        "tgn:7044938",
        "tgn:7003013",
        "tgn:7003005",
        "tgn:1000003",
        "tgn:1000080",
        "tgn:7029392"
    ],
    "tgn:id":7044938,
    "tgn:name":"Camposano",
    "tgn:placetype":[
        "aat:300008347"
    ]
},
  "bbox": [],
  "geometry": {"coordinates":[14.533333,40.95],"type":"Point"}
}