{
  "id": 7115572,
  "type": "Feature",
  "properties": {
    "tgn:hierarchy":[
        "tgn:7115572",
        "tgn:1000003",
        "tgn:7003676",
        "tgn:7000084",
        "tgn:7029392"
    ],
    "tgn:id":7115572,
    "tgn:name":"Ohrte",
    "tgn:placetype":[
        "aat:300008347"
    ]
},
  "bbox": [],
  "geometry": {"coordinates":[7.683333,52.583333],"type":"Point"}
}