{
  "id": 7573886,
  "type": "Feature",
  "properties": {
    "tgn:hierarchy":[
        "tgn:7573886",
        "tgn:1000004",
        "tgn:7000198",
        "tgn:1001882",
        "tgn:7029392"
    ],
    "tgn:id":7573886,
    "tgn:name:en":"Kaiga",
    "tgn:placetype":[
        "aat:300008347"
    ]
},
  "bbox": [],
  "geometry": {"coordinates":[74.433333,14.85],"type":"Point"}
}