{
  "id": 2073856,
  "type": "Feature",
  "properties": {
    "tgn:hierarchy":[
        "tgn:2073856",
        "tgn:1000001",
        "tgn:7013368",
        "tgn:7012149",
        "tgn:7007709",
        "tgn:7029392"
    ],
    "tgn:id":2073856,
    "tgn:name":"Bunyan",
    "tgn:placetype":[
        "aat:300008347",
        "aat:300387210"
    ]
},
  "bbox": [],
  "geometry": {"coordinates":[-76.9667,35.5333],"type":"Point"}
}