{
  "id": 7508708,
  "type": "Feature",
  "properties": {
    "tgn:hierarchy":[
        "tgn:7508708",
        "tgn:1009227",
        "tgn:1000226",
        "tgn:7016729",
        "tgn:1000006",
        "tgn:7029392"
    ],
    "tgn:id":7508708,
    "tgn:name:en":"Otu Bay",
    "tgn:placetype":[
        "aat:300132316"
    ]
},
  "bbox": [],
  "geometry": {"coordinates":[173.833333,-40.75],"type":"Point"}
}