{
  "id": 2492408,
  "type": "Feature",
  "properties": {
    "tgn:hierarchy":[
        "tgn:2492408",
        "tgn:1000001",
        "tgn:7012149",
        "tgn:2002247",
        "tgn:7007920",
        "tgn:7029392"
    ],
    "tgn:id":2492408,
    "tgn:name":"Marguette Spring",
    "tgn:placetype":[
        "aat:300008697"
    ]
},
  "bbox": [],
  "geometry": {"coordinates":[-118.5167,47.6833],"type":"Point"}
}