{
  "id": 2160332,
  "type": "Feature",
  "properties": {
    "tgn:hierarchy":[
        "tgn:2160332",
        "tgn:1000001",
        "tgn:1002260",
        "tgn:7012149",
        "tgn:7007920",
        "tgn:7029392"
    ],
    "tgn:id":2160332,
    "tgn:name":"Beehive Mountain",
    "tgn:placetype":[
        "aat:300008798"
    ]
},
  "bbox": [],
  "geometry": {"coordinates":[-120.3833,47.3167],"type":"Point"}
}