{
  "id": 2205526,
  "type": "Feature",
  "properties": {
    "tgn:hierarchy":[
        "tgn:2205526",
        "tgn:1000001",
        "tgn:7012149",
        "tgn:7007827",
        "tgn:7029392"
    ],
    "tgn:id":2205526,
    "tgn:name":"Bull Creek",
    "tgn:placetype":[
        "aat:300008706"
    ]
},
  "bbox": [],
  "geometry": {"coordinates":[-110.7833,38.0667],"type":"Point"}
}