{
  "id": 2610362,
  "type": "Feature",
  "properties": {
    "tgn:hierarchy":[
        "tgn:2610362",
        "tgn:1000001",
        "tgn:2001786",
        "tgn:7012149",
        "tgn:7007713",
        "tgn:7029392"
    ],
    "tgn:id":2610362,
    "tgn:name":"Red Butte",
    "tgn:placetype":[
        "aat:300008798"
    ]
},
  "bbox": [],
  "geometry": {"coordinates":[-103.95,43.7667],"type":"Point"}
}