{
  "id": 1076683,
  "type": "Feature",
  "properties": {
    "tgn:hierarchy":[
        "tgn:1076683",
        "tgn:1000004",
        "tgn:7000198",
        "tgn:1001977",
        "tgn:7029392"
    ],
    "tgn:id":1076683,
    "tgn:name:en":"R\u0101jnagar",
    "tgn:placetype":[
        "aat:300008347"
    ]
},
  "bbox": [],
  "geometry": {"coordinates":[87.315,23.945],"type":"Point"}
}