{
  "id": 7557880,
  "type": "Feature",
  "properties": {
    "tgn:hierarchy":[
        "tgn:7557880",
        "tgn:1000004",
        "tgn:7000198",
        "tgn:1001895",
        "tgn:7029392"
    ],
    "tgn:id":7557880,
    "tgn:name:en":"Ranjankhar",
    "tgn:placetype":[
        "aat:300008347"
    ]
},
  "bbox": [],
  "geometry": {"coordinates":[72.933611,18.807222],"type":"Point"}
}