{
  "id": 7373527,
  "type": "Feature",
  "properties": {
    "tgn:hierarchy":[
        "tgn:7373527",
        "tgn:1000001",
        "tgn:7005591",
        "tgn:7005560",
        "tgn:7029392"
    ],
    "tgn:id":7373527,
    "tgn:name":"La Llorona",
    "tgn:placetype":[
        "aat:300008347"
    ]
},
  "bbox": [],
  "geometry": {"coordinates":[-95.033333,16.816667],"type":"Point"}
}