{
  "id": 1054688,
  "type": "Feature",
  "properties": {
    "tgn:hierarchy":[
        "tgn:1054688",
        "tgn:1000004",
        "tgn:1003314",
        "tgn:7018214",
        "tgn:7002435",
        "tgn:7029392"
    ],
    "tgn:id":1054688,
    "tgn:name":"Yemelyanovo",
    "tgn:placetype":[
        "aat:300008347"
    ]
},
  "bbox": [],
  "geometry": {"coordinates":[92.6667,56.1833],"type":"Point"}
}