{
  "id": 1001000,
  "type": "Feature",
  "properties": {
    "tgn:hierarchy":[
        "tgn:1001000",
        "tgn:7001242",
        "tgn:1000156",
        "tgn:7029392"
    ],
    "tgn:id":1001000,
    "tgn:name":"Lac",
    "tgn:placetype":[
        "aat:300387064",
        "aat:300235099"
    ]
},
  "bbox": [],
  "geometry": {"coordinates":[19.75,10.5833],"type":"Point"}
}