{
  "id": 7248575,
  "type": "Feature",
  "properties": {
    "tgn:hierarchy":[
        "tgn:7248575",
        "tgn:7003458",
        "tgn:1000003",
        "tgn:1000063",
        "tgn:7018236",
        "tgn:7029392"
    ],
    "tgn:id":7248575,
    "tgn:name":"Blankaart",
    "tgn:placetype":[
        "aat:300008680"
    ]
},
  "bbox": [],
  "geometry": {"coordinates":[2.858707,50.984253],"type":"Point"}
}