{
  "id": 7560766,
  "type": "Feature",
  "properties": {
    "tgn:hierarchy":[
        "tgn:7560766",
        "tgn:1000004",
        "tgn:7000198",
        "tgn:7016722",
        "tgn:7029392"
    ],
    "tgn:id":7560766,
    "tgn:name:en":"Indhauwa",
    "tgn:placetype":[
        "aat:300008347"
    ]
},
  "bbox": [],
  "geometry": {"coordinates":[79.097581,26.757494],"type":"Point"}
}