<<<<<<< HEAD
{
  "id": 7479154,
  "type": "Feature",
  "properties": {
    "tgn:hierarchy":[
        "tgn:7479154",
        "tgn:1000004",
        "tgn:7490934",
        "tgn:1000141",
        "tgn:7029392"
    ],
    "tgn:id":7479154,
    "tgn:name":"Zhuangshi Zongci",
    "tgn:placetype":[
        "aat:300007595"
    ]
},
  "bbox": [],
  "geometry": {"coordinates":[120.177222,23.234722],"type":"Point"}
}
=======
{"geometry":{"type":"Point","coordinates":[120.177222,23.234722]},"type":"Feature","properties":{"hierarchy":["tgn:7479154","tgn:1000004","tgn:7490934","tgn:1000141","tgn:7029392"],"placetype":["aat:300007595"],"id":7479154,"name:xx":"Zhuangshi Zongci"}}
>>>>>>> 03f74aca74312dbeaf24d7e61306dd6a786dc3d0
