{
  "id": 2179499,
  "type": "Feature",
  "properties": {
    "tgn:hierarchy":[
        "tgn:2179499",
        "tgn:1000001",
        "tgn:2001415",
        "tgn:7012149",
        "tgn:7007526",
        "tgn:7029392"
    ],
    "tgn:id":2179499,
    "tgn:name":"Blanco",
    "tgn:placetype":[
        "aat:300008347",
        "aat:300167671"
    ]
},
  "bbox": [],
  "geometry": {"coordinates":[-117.1167,40.55],"type":"Point"}
}