{
  "id": 7214362,
  "type": "Feature",
  "properties": {
    "tgn:hierarchy":[
        "tgn:7214362",
        "tgn:1000003",
        "tgn:7003676",
        "tgn:7000084",
        "tgn:7029392"
    ],
    "tgn:id":7214362,
    "tgn:name":"Blocken-Berg",
    "tgn:placetype":[
        "aat:300008777"
    ]
},
  "bbox": [],
  "geometry": {"coordinates":[10.516667,52.033333],"type":"Point"}
}