{
  "id": 2163474,
  "type": "Feature",
  "properties": {
    "tgn:hierarchy":[
        "tgn:2163474",
        "tgn:7002659",
        "tgn:1000001",
        "tgn:2000010",
        "tgn:7012149",
        "tgn:7029392"
    ],
    "tgn:id":2163474,
    "tgn:name":"Benson Creek",
    "tgn:placetype":[
        "aat:300008706"
    ]
},
  "bbox": [],
  "geometry": {"coordinates":[-86.7333,32.85],"type":"Point"}
}