<<<<<<< HEAD
{
  "id": 7242476,
  "type": "Feature",
  "properties": {
    "tgn:hierarchy":[
        "tgn:7242476",
        "tgn:7007877",
        "tgn:1000003",
        "tgn:1000063",
        "tgn:4012014",
        "tgn:7029392"
    ],
    "tgn:id":7242476,
    "tgn:name":"Long Pourrat",
    "tgn:placetype":[
        "aat:300008347"
    ]
},
  "bbox": [],
  "geometry": {"coordinates":[4.016667,50.466667],"type":"Point"}
}
=======
{"geometry":{"type":"Point","coordinates":[4.016667,50.466667]},"type":"Feature","properties":{"hierarchy":["tgn:7242476","tgn:7007877","tgn:1000003","tgn:1000063","tgn:4012014","tgn:7029392"],"placetype":["aat:300008347"],"id":7242476,"name:xx":"Long Pourrat"}}
>>>>>>> 03f74aca74312dbeaf24d7e61306dd6a786dc3d0
