{
  "id": 2660849,
  "type": "Feature",
  "properties": {
    "tgn:hierarchy":[
        "tgn:2660849",
        "tgn:1000001",
        "tgn:7012149",
        "tgn:7015666",
        "tgn:7007825",
        "tgn:7029392"
    ],
    "tgn:id":2660849,
    "tgn:name":"Short Branch",
    "tgn:placetype":[
        "aat:300008699"
    ]
},
  "bbox": [],
  "geometry": {"coordinates":[-87.3667,35.65],"type":"Point"}
}