{
  "id": 1018997,
  "type": "Feature",
  "properties": {
    "tgn:hierarchy":[
        "tgn:1018997",
        "tgn:7017442",
        "tgn:1000001",
        "tgn:7004643",
        "tgn:7029392"
    ],
    "tgn:id":1018997,
    "tgn:name":"Palmer",
    "tgn:placetype":[
        "aat:300008347"
    ]
},
  "bbox": [],
  "geometry": {"coordinates":[-65.7667,18.3667],"type":"Point"}
}