{
  "id": 7129908,
  "type": "Feature",
  "properties": {
    "tgn:hierarchy":[
        "tgn:7129908",
        "tgn:7003669",
        "tgn:1000003",
        "tgn:7000084",
        "tgn:7029392"
    ],
    "tgn:id":7129908,
    "tgn:name":"Marwang",
    "tgn:placetype":[
        "aat:300008347"
    ]
},
  "bbox": [],
  "geometry": {"coordinates":[12.566667,47.85],"type":"Point"}
}