{
  "id": 2114181,
  "type": "Feature",
  "properties": {
    "tgn:hierarchy":[
        "tgn:2114181",
        "tgn:1000001",
        "tgn:7012149",
        "tgn:1002575",
        "tgn:7007919",
        "tgn:7029392"
    ],
    "tgn:id":2114181,
    "tgn:name":"Senora",
    "tgn:placetype":[
        "aat:300008347",
        "aat:300387210"
    ]
},
  "bbox": [],
  "geometry": {"coordinates":[-76.5167,37.6667],"type":"Point"}
}