{
  "id": 7318596,
  "type": "Feature",
  "properties": {
    "tgn:hierarchy":[
        "tgn:7318596",
        "tgn:1001623",
        "tgn:1000049",
        "tgn:1000002",
        "tgn:7029392"
    ],
    "tgn:id":7318596,
    "tgn:name":"Collaradas, Laguna",
    "tgn:placetype":[
        "aat:300008680"
    ]
},
  "bbox": [],
  "geometry": {"coordinates":[-72.166667,-47.233333],"type":"Point"}
}