{
  "id": 2041676,
  "type": "Feature",
  "properties": {
    "tgn:hierarchy":[
        "tgn:2041676",
        "tgn:1000001",
        "tgn:7012149",
        "tgn:2000835",
        "tgn:7007255",
        "tgn:7029392"
    ],
    "tgn:id":2041676,
    "tgn:name":"Travellers Rest",
    "tgn:placetype":[
        "aat:300008347",
        "aat:300387210"
    ]
},
  "bbox": [],
  "geometry": {"coordinates":[-83.7833,37.4333],"type":"Point"}
}