{
  "id": 2716685,
  "type": "Feature",
  "properties": {
    "tgn:hierarchy":[
        "tgn:2716685",
        "tgn:7006450",
        "tgn:1000001",
        "tgn:2124053",
        "tgn:7012149",
        "tgn:7029392"
    ],
    "tgn:id":2716685,
    "tgn:name":"The Rooster Comb",
    "tgn:placetype":[
        "aat:300008798"
    ]
},
  "bbox": [],
  "geometry": {"coordinates":[-150.8333,62.9667],"type":"Point"}
}