{
  "id": 7467550,
  "type": "Feature",
  "properties": {
    "tgn:hierarchy":[
        "tgn:7467550",
        "tgn:1000004",
        "tgn:7471332",
        "tgn:1000141",
        "tgn:7029392"
    ],
    "tgn:id":7467550,
    "tgn:name":"Chikeliao",
    "tgn:placetype":[
        "aat:300008347"
    ]
},
  "bbox": [],
  "geometry": {"coordinates":[121.118889,24.773333],"type":"Point"}
}