{
  "id": 7424179,
  "type": "Feature",
  "properties": {
    "tgn:hierarchy":[
        "tgn:7424179",
        "tgn:1000001",
        "tgn:7005601",
        "tgn:7005560",
        "tgn:7029392"
    ],
    "tgn:id":7424179,
    "tgn:name":"Tarasco",
    "tgn:placetype":[
        "aat:300008347"
    ]
},
  "bbox": [],
  "geometry": {"coordinates":[-103.05,22.333333],"type":"Point"}
}