{
  "id": 7308159,
  "type": "Feature",
  "properties": {
    "tgn:hierarchy":[
        "tgn:7308159",
        "tgn:1001702",
        "tgn:1000049",
        "tgn:1000002",
        "tgn:7029392"
    ],
    "tgn:id":7308159,
    "tgn:name":"Media Luna, Isla",
    "tgn:placetype":[
        "aat:300008791"
    ]
},
  "bbox": [],
  "geometry": {"coordinates":[-71.65,-51.633333],"type":"Point"}
}