{
  "id": 7261517,
  "type": "Feature",
  "properties": {
    "tgn:concordances":{
        "gn:id":"2756412"
    },
    "tgn:hierarchy":[
        "tgn:7261517",
        "tgn:7003619",
        "tgn:1000003",
        "tgn:7016845",
        "tgn:7029392"
    ],
    "tgn:id":7261517,
    "tgn:name:nl":"Eekt",
    "tgn:placetype":[
        "aat:300008347"
    ]
},
  "bbox": [],
  "geometry": {"coordinates":[5.883333,52.45],"type":"Point"}
}