{
  "id": 7330248,
  "type": "Feature",
  "properties": {
    "tgn:hierarchy":[
        "tgn:7330248",
        "tgn:7002811",
        "tgn:1000003",
        "tgn:7003837",
        "tgn:1000095",
        "tgn:7029392"
    ],
    "tgn:id":7330248,
    "tgn:name":"Horcajo, R\u00edo del",
    "tgn:placetype":[
        "aat:300008699"
    ]
},
  "bbox": [],
  "geometry": {"coordinates":[-5.866667,40.283333],"type":"Point"}
}