{
  "id": 7151501,
  "type": "Feature",
  "properties": {
    "tgn:hierarchy":[
        "tgn:7151501",
        "tgn:1000003",
        "tgn:7003673",
        "tgn:7000084",
        "tgn:7029392"
    ],
    "tgn:id":7151501,
    "tgn:name":"Jenfeld",
    "tgn:placetype":[
        "aat:300008347"
    ]
},
  "bbox": [],
  "geometry": {"coordinates":[10.133333,53.566667],"type":"Point"}
}