<<<<<<< HEAD
{
  "id": 7051258,
  "type": "Feature",
  "properties": {
    "tgn:hierarchy":[
        "tgn:7051258",
        "tgn:7003128",
        "tgn:1000003",
        "tgn:7008516",
        "tgn:1000080",
        "tgn:7029392"
    ],
    "tgn:id":7051258,
    "tgn:name":"Canale Marozzo",
    "tgn:placetype":[
        "aat:300006075"
    ]
},
  "bbox": [],
  "geometry": {"coordinates":[12.116667,44.783333],"type":"Point"}
}
=======
{"geometry":{"type":"Point","coordinates":[12.116667,44.783333]},"type":"Feature","properties":{"hierarchy":["tgn:7051258","tgn:7003128","tgn:1000003","tgn:7008516","tgn:1000080","tgn:7029392"],"placetype":["aat:300006075"],"id":7051258,"name:xx":"Canale Marozzo"}}
>>>>>>> 03f74aca74312dbeaf24d7e61306dd6a786dc3d0
