{
  "id": 7141868,
  "type": "Feature",
  "properties": {
    "tgn:hierarchy":[
        "tgn:7141868",
        "tgn:1000003",
        "tgn:7003682",
        "tgn:7000084",
        "tgn:7029392"
    ],
    "tgn:id":7141868,
    "tgn:name":"Lohrsdorf",
    "tgn:placetype":[
        "aat:300008347"
    ]
},
  "bbox": [],
  "geometry": {"coordinates":[7.183333,50.55],"type":"Point"}
}