<<<<<<< HEAD
{
  "id": 7352540,
  "type": "Feature",
  "properties": {
    "tgn:hierarchy":[
        "tgn:7352540",
        "tgn:7005584",
        "tgn:1000001",
        "tgn:7005560",
        "tgn:7029392"
    ],
    "tgn:id":7352540,
    "tgn:name":"Barr\u00f3n",
    "tgn:placetype":[
        "aat:300008347"
    ]
},
  "bbox": [],
  "geometry": {"coordinates":[-101.083333,20.683333],"type":"Point"}
}
=======
{"geometry":{"type":"Point","coordinates":[-101.083333,20.683333]},"type":"Feature","properties":{"hierarchy":["tgn:7352540","tgn:7005584","tgn:1000001","tgn:7005560","tgn:7029392"],"placetype":["aat:300008347"],"id":7352540,"name:xx":"Barr\u00f3n"}}
>>>>>>> 03f74aca74312dbeaf24d7e61306dd6a786dc3d0
