{
  "id": 1065690,
  "type": "Feature",
  "properties": {
    "tgn:hierarchy":[
        "tgn:1065690",
        "tgn:7000188",
        "tgn:1000004",
        "tgn:1000105",
        "tgn:7029392"
    ],
    "tgn:id":1065690,
    "tgn:name":"Elliotganj",
    "tgn:placetype":[
        "aat:300008347"
    ]
},
  "bbox": [],
  "geometry": {"coordinates":[90.8667,23.5167],"type":"Point"}
}