{
  "id": 1104641,
  "type": "Feature",
  "properties": {
    "tgn:hierarchy":[
        "tgn:1104641",
        "tgn:7016675",
        "tgn:1000004",
        "tgn:7000896",
        "tgn:1000120",
        "tgn:7029392"
    ],
    "tgn:id":1104641,
    "tgn:name":"Futatabi-yama",
    "tgn:placetype":[
        "aat:300008795"
    ]
},
  "bbox": [],
  "geometry": {"coordinates":[135.1833,34.7167],"type":"Point"}
}