{
  "id": 1105391,
  "type": "Feature",
  "properties": {
    "tgn:hierarchy":[
        "tgn:1105391",
        "tgn:1000003",
        "tgn:1000070",
        "tgn:7002895",
        "tgn:7029392"
    ],
    "tgn:id":1105391,
    "tgn:name":"Monges, les",
    "tgn:placetype":[
        "aat:300008795"
    ]
},
  "bbox": [],
  "geometry": {"coordinates":[6.1833,44.2833],"type":"Point"}
}