{
  "id": 2422050,
  "type": "Feature",
  "properties": {
    "tgn:hierarchy":[
        "tgn:2422050",
        "tgn:1000001",
        "tgn:7012149",
        "tgn:2001676",
        "tgn:7007707",
        "tgn:7029392"
    ],
    "tgn:id":2422050,
    "tgn:name":"Jim Day Lake",
    "tgn:placetype":[
        "aat:300008680"
    ]
},
  "bbox": [],
  "geometry": {"coordinates":[-96.25,35.6167],"type":"Point"}
}