{
  "id": 2148247,
  "type": "Feature",
  "properties": {
    "tgn:hierarchy":[
        "tgn:2148247",
        "tgn:1000001",
        "tgn:7012149",
        "tgn:1002862",
        "tgn:7007920",
        "tgn:7029392"
    ],
    "tgn:id":2148247,
    "tgn:name":"Barlow Bay",
    "tgn:placetype":[
        "aat:300132316"
    ]
},
  "bbox": [],
  "geometry": {"coordinates":[-122.8667,48.4333],"type":"Point"}
}