{
  "id": 2235097,
  "type": "Feature",
  "properties": {
    "tgn:hierarchy":[
        "tgn:2235097",
        "tgn:2000194",
        "tgn:1000001",
        "tgn:7012149",
        "tgn:7007158",
        "tgn:7029392"
    ],
    "tgn:id":2235097,
    "tgn:name":"Cherry Ridge",
    "tgn:placetype":[
        "aat:300008347"
    ]
},
  "bbox": [],
  "geometry": {"coordinates":[-104.9333,39.6167],"type":"Point"}
}