{
  "id": 2169810,
  "type": "Feature",
  "properties": {
    "tgn:hierarchy":[
        "tgn:2169810",
        "tgn:1000001",
        "tgn:7012149",
        "tgn:1002676",
        "tgn:7007240",
        "tgn:7029392"
    ],
    "tgn:id":2169810,
    "tgn:name":"Big Munson Island",
    "tgn:placetype":[
        "aat:300008791"
    ]
},
  "bbox": [],
  "geometry": {"coordinates":[-81.3833,24.6167],"type":"Point"}
}