{
  "id": 2297478,
  "type": "Feature",
  "properties": {
    "tgn:hierarchy":[
        "tgn:2297478",
        "tgn:1000001",
        "tgn:7012149",
        "tgn:2002121",
        "tgn:7007827",
        "tgn:7029392"
    ],
    "tgn:id":2297478,
    "tgn:name":"Dry Fork",
    "tgn:placetype":[
        "aat:300008699"
    ]
},
  "bbox": [],
  "geometry": {"coordinates":[-111.3333,38.95],"type":"Point"}
}