{
  "id": 7317170,
  "type": "Feature",
  "properties": {
    "tgn:hierarchy":[
        "tgn:7317170",
        "tgn:1001702",
        "tgn:1000049",
        "tgn:1000002",
        "tgn:7029392"
    ],
    "tgn:id":7317170,
    "tgn:name":"Crown, Punta",
    "tgn:placetype":[
        "aat:300386846"
    ]
},
  "bbox": [],
  "geometry": {"coordinates":[-71.233333,-54.016667],"type":"Point"}
}