{
  "id": 2541841,
  "type": "Feature",
  "properties": {
    "tgn:hierarchy":[
        "tgn:2541841",
        "tgn:1000001",
        "tgn:2001411",
        "tgn:7012149",
        "tgn:7007526",
        "tgn:7029392"
    ],
    "tgn:id":2541841,
    "tgn:name":"Ninemile Ridge",
    "tgn:placetype":[
        "aat:300266640"
    ]
},
  "bbox": [],
  "geometry": {"coordinates":[-114.4167,41.4833],"type":"Point"}
}