{
  "id": 7524107,
  "type": "Feature",
  "properties": {
    "tgn:hierarchy":[
        "tgn:7524107",
        "tgn:7001242",
        "tgn:1001059",
        "tgn:7016833",
        "tgn:7029392"
    ],
    "tgn:id":7524107,
    "tgn:name:en":"Rayy\u0101\u1e29 Bilq\u0101s",
    "tgn:placetype":[
        "aat:300006075"
    ]
},
  "bbox": [],
  "geometry": {"coordinates":[31.380939,31.134053],"type":"Point"}
}