<<<<<<< HEAD
{
  "id": 2155643,
  "type": "Feature",
  "properties": {
    "tgn:hierarchy":[
        "tgn:2155643",
        "tgn:1000001",
        "tgn:7012149",
        "tgn:2001449",
        "tgn:7007566",
        "tgn:7029392"
    ],
    "tgn:id":2155643,
    "tgn:name":"Bear Spring",
    "tgn:placetype":[
        "aat:300008697"
    ]
},
  "bbox": [],
  "geometry": {"coordinates":[-106.65,36.2333],"type":"Point"}
}
=======
{"geometry":{"type":"Point","coordinates":[-106.650000,36.233300]},"type":"Feature","properties":{"hierarchy":["tgn:2155643","tgn:1000001","tgn:7012149","tgn:2001449","tgn:7007566","tgn:7029392"],"placetype":["aat:300008697"],"id":2155643,"name:xx":"Bear Spring"}}
>>>>>>> 03f74aca74312dbeaf24d7e61306dd6a786dc3d0
