<<<<<<< HEAD
{
  "id": 7118477,
  "type": "Feature",
  "properties": {
    "tgn:hierarchy":[
        "tgn:7118477",
        "tgn:7000096",
        "tgn:1000003",
        "tgn:7000084",
        "tgn:7029392"
    ],
    "tgn:id":7118477,
    "tgn:name":"Petersdorfer See",
    "tgn:placetype":[
        "aat:300008680"
    ]
},
  "bbox": [],
  "geometry": {"coordinates":[14.066667,52.316667],"type":"Point"}
}
=======
{"geometry":{"type":"Point","coordinates":[14.066667,52.316667]},"type":"Feature","properties":{"hierarchy":["tgn:7118477","tgn:7000096","tgn:1000003","tgn:7000084","tgn:7029392"],"placetype":["aat:300008680"],"id":7118477,"name:xx":"Petersdorfer See"}}
>>>>>>> 03f74aca74312dbeaf24d7e61306dd6a786dc3d0
