{
  "id": 1016743,
  "type": "Feature",
  "properties": {
    "tgn:hierarchy":[
        "tgn:1016743",
        "tgn:7005519",
        "tgn:1000001",
        "tgn:7005502",
        "tgn:7029392"
    ],
    "tgn:id":1016743,
    "tgn:name":"Les Cayes",
    "tgn:placetype":[
        "aat:300008347",
        "aat:300387225",
        "aat:300008375"
    ]
},
  "bbox": [],
  "geometry": {"coordinates":[-73.746,18.193],"type":"Point"}
}