{
  "id": 7348091,
  "type": "Feature",
  "properties": {
    "tgn:hierarchy":[
        "tgn:7348091",
        "tgn:7002758",
        "tgn:7002823",
        "tgn:1000003",
        "tgn:1000095",
        "tgn:7029392"
    ],
    "tgn:id":7348091,
    "tgn:name":"Al\u00e1jar",
    "tgn:placetype":[
        "aat:300008347"
    ]
},
  "bbox": [],
  "geometry": {"coordinates":[-6.65,37.866667],"type":"Point"}
}