<<<<<<< HEAD
{
  "id": 7480905,
  "type": "Feature",
  "properties": {
    "tgn:hierarchy":[
        "tgn:7480905",
        "tgn:1000004",
        "tgn:7490934",
        "tgn:1000141",
        "tgn:7029392"
    ],
    "tgn:id":7480905,
    "tgn:name":"Kengnei Yihao Qiao",
    "tgn:placetype":[
        "aat:300007836"
    ]
},
  "bbox": [],
  "geometry": {"coordinates":[120.501219,23.109646],"type":"Point"}
}
=======
{"geometry":{"type":"Point","coordinates":[120.501219,23.109646]},"type":"Feature","properties":{"hierarchy":["tgn:7480905","tgn:1000004","tgn:7490934","tgn:1000141","tgn:7029392"],"placetype":["aat:300007836"],"id":7480905,"name:xx":"Kengnei Yihao Qiao"}}
>>>>>>> 03f74aca74312dbeaf24d7e61306dd6a786dc3d0
