<<<<<<< HEAD
{
  "id": 7356959,
  "type": "Feature",
  "properties": {
    "tgn:hierarchy":[
        "tgn:7356959",
        "tgn:1000001",
        "tgn:7005592",
        "tgn:7005560",
        "tgn:7029392"
    ],
    "tgn:id":7356959,
    "tgn:name":"Chagchaltzin",
    "tgn:placetype":[
        "aat:300008347"
    ]
},
  "bbox": [],
  "geometry": {"coordinates":[-97.483333,19.916667],"type":"Point"}
}
=======
{"geometry":{"type":"Point","coordinates":[-97.483333,19.916667]},"type":"Feature","properties":{"hierarchy":["tgn:7356959","tgn:1000001","tgn:7005592","tgn:7005560","tgn:7029392"],"placetype":["aat:300008347"],"id":7356959,"name:xx":"Chagchaltzin"}}
>>>>>>> 03f74aca74312dbeaf24d7e61306dd6a786dc3d0
