{
  "id": 2511318,
  "type": "Feature",
  "properties": {
    "tgn:hierarchy":[
        "tgn:2511318",
        "tgn:1000001",
        "tgn:7012149",
        "tgn:2000473",
        "tgn:7007250",
        "tgn:7029392"
    ],
    "tgn:id":2511318,
    "tgn:name":"Mikesell Reservoir Number 2",
    "tgn:placetype":[
        "aat:300006191"
    ]
},
  "bbox": [],
  "geometry": {"coordinates":[-111.5667,44.1167],"type":"Point"}
}