{
  "id": 7437986,
  "type": "Feature",
  "properties": {
    "tgn:hierarchy":[
        "tgn:7437986",
        "tgn:7005587",
        "tgn:1000001",
        "tgn:7005560",
        "tgn:7029392"
    ],
    "tgn:id":7437986,
    "tgn:name":"Tenango",
    "tgn:placetype":[
        "aat:300008347"
    ]
},
  "bbox": [],
  "geometry": {"coordinates":[-98.533333,20.85],"type":"Point"}
}