{
  "id": 2187036,
  "type": "Feature",
  "properties": {
    "tgn:hierarchy":[
        "tgn:2187036",
        "tgn:1000001",
        "tgn:7012149",
        "tgn:2001300",
        "tgn:7007524",
        "tgn:7029392"
    ],
    "tgn:id":2187036,
    "tgn:name":"Bonnie Blue Creek",
    "tgn:placetype":[
        "aat:300008706"
    ]
},
  "bbox": [],
  "geometry": {"coordinates":[-114.3167,45.75],"type":"Point"}
}