{
  "id": 2318223,
  "type": "Feature",
  "properties": {
    "tgn:hierarchy":[
        "tgn:2318223",
        "tgn:1000001",
        "tgn:7012149",
        "tgn:2002250",
        "tgn:7007920",
        "tgn:7029392"
    ],
    "tgn:id":2318223,
    "tgn:name":"Enterprise Valley",
    "tgn:placetype":[
        "aat:300008761"
    ]
},
  "bbox": [],
  "geometry": {"coordinates":[-118.2833,47.9833],"type":"Point"}
}