{
  "id": 7447892,
  "type": "Feature",
  "properties": {
    "tgn:hierarchy":[
        "tgn:7447892",
        "tgn:7002444",
        "tgn:1000003",
        "tgn:7009907",
        "tgn:7008591",
        "tgn:7029392"
    ],
    "tgn:id":7447892,
    "tgn:name:en":"Rami Geo",
    "tgn:placetype":[
        "aat:300132316"
    ]
},
  "bbox": [],
  "geometry": {"coordinates":[-2.916667,58.75],"type":"Point"}
}