{
  "id": 1068170,
  "type": "Feature",
  "properties": {
    "tgn:hierarchy":[
        "tgn:1068170",
        "tgn:1000004",
        "tgn:7002077",
        "tgn:1000111",
        "tgn:7029392"
    ],
    "tgn:id":1068170,
    "tgn:name":"Gangoumen",
    "tgn:placetype":[
        "aat:300008347"
    ]
},
  "bbox": [],
  "geometry": {"coordinates":[116.5833,41.6667],"type":"Point"}
}