{
  "id": 7065538,
  "type": "Feature",
  "properties": {
    "tgn:hierarchy":[
        "tgn:7065538",
        "tgn:7003669",
        "tgn:1000003",
        "tgn:7000084",
        "tgn:7029392"
    ],
    "tgn:id":7065538,
    "tgn:name":"Stepberg-Graben",
    "tgn:placetype":[
        "aat:300008699"
    ]
},
  "bbox": [],
  "geometry": {"coordinates":[11.05,47.516667],"type":"Point"}
}