{
  "id": 2381504,
  "type": "Feature",
  "properties": {
    "tgn:hierarchy":[
        "tgn:2381504",
        "tgn:1000001",
        "tgn:2001810",
        "tgn:7012149",
        "tgn:7007713",
        "tgn:7029392"
    ],
    "tgn:id":2381504,
    "tgn:name":"Hay Creek",
    "tgn:placetype":[
        "aat:300008706"
    ]
},
  "bbox": [],
  "geometry": {"coordinates":[-103.65,44.25],"type":"Point"}
}