{
  "id": 1064592,
  "type": "Feature",
  "properties": {
    "tgn:hierarchy":[
        "tgn:1064592",
        "tgn:7002443",
        "tgn:7018977",
        "tgn:1000003",
        "tgn:7008591",
        "tgn:7029392"
    ],
    "tgn:id":1064592,
    "tgn:name:en":"Bridgend",
    "tgn:placetype":[
        "aat:300008347",
        "aat:300387220"
    ]
},
  "bbox": [],
  "geometry": {"coordinates":[-3.577222,51.505833],"type":"Point"}
}