{
  "id": 2293167,
  "type": "Feature",
  "properties": {
    "tgn:hierarchy":[
        "tgn:2293167",
        "tgn:7002659",
        "tgn:1000001",
        "tgn:7012149",
        "tgn:2000054",
        "tgn:7029392"
    ],
    "tgn:id":2293167,
    "tgn:name":"Double Branch",
    "tgn:placetype":[
        "aat:300008699"
    ]
},
  "bbox": [],
  "geometry": {"coordinates":[-85.9833,31.7833],"type":"Point"}
}