{
  "id": 7161946,
  "type": "Feature",
  "properties": {
    "tgn:hierarchy":[
        "tgn:7161946",
        "tgn:1000003",
        "tgn:7003676",
        "tgn:7000084",
        "tgn:7029392"
    ],
    "tgn:id":7161946,
    "tgn:name":"Holzurburg",
    "tgn:placetype":[
        "aat:300008863"
    ]
},
  "bbox": [],
  "geometry": {"coordinates":[8.866667,53.65],"type":"Point"}
}