{
  "id": 2473701,
  "type": "Feature",
  "properties": {
    "tgn:hierarchy":[
        "tgn:2473701",
        "tgn:1000001",
        "tgn:7012149",
        "tgn:2001298",
        "tgn:7007524",
        "tgn:7029392"
    ],
    "tgn:id":2473701,
    "tgn:name":"Lower Elliot Lake",
    "tgn:placetype":[
        "aat:300008680"
    ]
},
  "bbox": [],
  "geometry": {"coordinates":[-112.9833,46.3333],"type":"Point"}
}