{
  "id": 2206003,
  "type": "Feature",
  "properties": {
    "tgn:hierarchy":[
        "tgn:2206003",
        "tgn:1000001",
        "tgn:2002109",
        "tgn:7012149",
        "tgn:7007827",
        "tgn:7029392"
    ],
    "tgn:id":2206003,
    "tgn:name":"Bull Run Canyon",
    "tgn:placetype":[
        "aat:300008761"
    ]
},
  "bbox": [],
  "geometry": {"coordinates":[-111.5667,37.6167],"type":"Point"}
}