{
  "id": 2550111,
  "type": "Feature",
  "properties": {
    "tgn:hierarchy":[
        "tgn:2550111",
        "tgn:1000001",
        "tgn:2000922",
        "tgn:7012149",
        "tgn:7007515",
        "tgn:7029392"
    ],
    "tgn:id":2550111,
    "tgn:name":"Northeast Cove",
    "tgn:placetype":[
        "aat:300132316"
    ]
},
  "bbox": [],
  "geometry": {"coordinates":[-68.45,44.6333],"type":"Point"}
}