{
  "id": 2594043,
  "type": "Feature",
  "properties": {
    "tgn:hierarchy":[
        "tgn:2594043",
        "tgn:7006450",
        "tgn:1000001",
        "tgn:2124012",
        "tgn:7012149",
        "tgn:7029392"
    ],
    "tgn:id":2594043,
    "tgn:name":"Portage Lake",
    "tgn:placetype":[
        "aat:300008680"
    ]
},
  "bbox": [],
  "geometry": {"coordinates":[-152.4167,58.2667],"type":"Point"}
}