{
  "id": 2513730,
  "type": "Feature",
  "properties": {
    "tgn:hierarchy":[
        "tgn:2513730",
        "tgn:2002138",
        "tgn:1000001",
        "tgn:7012149",
        "tgn:7007919",
        "tgn:7029392"
    ],
    "tgn:id":2513730,
    "tgn:name":"Mill Ridge",
    "tgn:placetype":[
        "aat:300266640"
    ]
},
  "bbox": [],
  "geometry": {"coordinates":[-80.15,37.6333],"type":"Point"}
}