<<<<<<< HEAD
{
  "id": 7118972,
  "type": "Feature",
  "properties": {
    "tgn:hierarchy":[
        "tgn:7118972",
        "tgn:7000096",
        "tgn:1000003",
        "tgn:7000084",
        "tgn:7029392"
    ],
    "tgn:id":7118972,
    "tgn:name":"Pernitz",
    "tgn:placetype":[
        "aat:300008347"
    ]
},
  "bbox": [],
  "geometry": {"coordinates":[12.6,52.283333],"type":"Point"}
}
=======
{"geometry":{"type":"Point","coordinates":[12.600000,52.283333]},"type":"Feature","properties":{"hierarchy":["tgn:7118972","tgn:7000096","tgn:1000003","tgn:7000084","tgn:7029392"],"placetype":["aat:300008347"],"id":7118972,"name:xx":"Pernitz"}}
>>>>>>> 03f74aca74312dbeaf24d7e61306dd6a786dc3d0
