{
  "id": 7590580,
  "type": "Feature",
  "properties": {
    "tgn:hierarchy":[
        "tgn:7590580",
        "tgn:1000004",
        "tgn:7000198",
        "tgn:7000799",
        "tgn:7029392"
    ],
    "tgn:id":7590580,
    "tgn:name:en":"Katha",
    "tgn:placetype":[
        "aat:300008347"
    ]
},
  "bbox": [],
  "geometry": {"coordinates":[74.36015,33.821955],"type":"Point"}
}