{
  "id": 7589250,
  "type": "Feature",
  "properties": {
    "tgn:hierarchy":[
        "tgn:7589250",
        "tgn:1000004",
        "tgn:7000198",
        "tgn:1001895",
        "tgn:7029392"
    ],
    "tgn:id":7589250,
    "tgn:name:en":"K\u0101nte Peak",
    "tgn:placetype":[
        "aat:300008777"
    ]
},
  "bbox": [],
  "geometry": {"coordinates":[73.0875,17.958889],"type":"Point"}
}