{
  "id": 7590274,
  "type": "Feature",
  "properties": {
    "tgn:hierarchy":[
        "tgn:7590274",
        "tgn:1000004",
        "tgn:7000198",
        "tgn:7000799",
        "tgn:7029392"
    ],
    "tgn:id":7590274,
    "tgn:name:en":"Bani",
    "tgn:placetype":[
        "aat:300008347"
    ]
},
  "bbox": [],
  "geometry": {"coordinates":[73.965213,34.316436],"type":"Point"}
}