{
  "id": 2168391,
  "type": "Feature",
  "properties": {
    "tgn:hierarchy":[
        "tgn:2168391",
        "tgn:7006450",
        "tgn:1000001",
        "tgn:7012149",
        "tgn:2000088",
        "tgn:7029392"
    ],
    "tgn:id":2168391,
    "tgn:name":"Big Gulch",
    "tgn:placetype":[
        "aat:300008761"
    ]
},
  "bbox": [],
  "geometry": {"coordinates":[-132.85,56.65],"type":"Point"}
}