{
  "id": 7517143,
  "type": "Feature",
  "properties": {
    "tgn:hierarchy":[
        "tgn:7517143",
        "tgn:1008380",
        "tgn:7520093",
        "tgn:1000226",
        "tgn:1000006",
        "tgn:7029392"
    ],
    "tgn:id":7517143,
    "tgn:name:en":"Mangahoeka",
    "tgn:placetype":[
        "aat:300008795"
    ]
},
  "bbox": [],
  "geometry": {"coordinates":[176.183333,-40.783333],"type":"Point"}
}