{
  "id": 2501787,
  "type": "Feature",
  "properties": {
    "tgn:hierarchy":[
        "tgn:2501787",
        "tgn:1000001",
        "tgn:7006451",
        "tgn:7012149",
        "tgn:2000103",
        "tgn:7029392"
    ],
    "tgn:id":2501787,
    "tgn:name":"McIntyre Tank",
    "tgn:placetype":[
        "aat:300006191"
    ]
},
  "bbox": [],
  "geometry": {"coordinates":[-112.7167,35.2333],"type":"Point"}
}