{
  "id": 2543891,
  "type": "Feature",
  "properties": {
    "tgn:hierarchy":[
        "tgn:2543891",
        "tgn:1000001",
        "tgn:7012149",
        "tgn:1002740",
        "tgn:7007252",
        "tgn:7029392"
    ],
    "tgn:id":2543891,
    "tgn:name":"North Branch Arnold Creek",
    "tgn:placetype":[
        "aat:300008706"
    ]
},
  "bbox": [],
  "geometry": {"coordinates":[-84.9167,38.9833],"type":"Point"}
}