{
  "id": 2226630,
  "type": "Feature",
  "properties": {
    "tgn:hierarchy":[
        "tgn:2226630",
        "tgn:1000001",
        "tgn:7012149",
        "tgn:2001854",
        "tgn:7007825",
        "tgn:7029392"
    ],
    "tgn:id":2226630,
    "tgn:name":"Catoosa Country",
    "tgn:placetype":[
        "aat:300008347"
    ]
},
  "bbox": [],
  "geometry": {"coordinates":[-84.9667,36.0667],"type":"Point"}
}