{
  "id": 2635479,
  "type": "Feature",
  "properties": {
    "tgn:hierarchy":[
        "tgn:2635479",
        "tgn:1000001",
        "tgn:7012149",
        "tgn:2002092",
        "tgn:7007826",
        "tgn:7029392"
    ],
    "tgn:id":2635479,
    "tgn:name":"SJ Lateral",
    "tgn:placetype":[
        "aat:300006075"
    ]
},
  "bbox": [],
  "geometry": {"coordinates":[-98.8167,33.85],"type":"Point"}
}