<<<<<<< HEAD
{
  "id": 2767408,
  "type": "Feature",
  "properties": {
    "tgn:hierarchy":[
        "tgn:2767408",
        "tgn:1000001",
        "tgn:2000273",
        "tgn:7012149",
        "tgn:7007240",
        "tgn:7029392"
    ],
    "tgn:id":2767408,
    "tgn:name":"White Springs",
    "tgn:placetype":[
        "aat:300008697"
    ]
},
  "bbox": [],
  "geometry": {"coordinates":[-84.9167,30.6167],"type":"Point"}
}
=======
{"geometry":{"type":"Point","coordinates":[-84.916700,30.616700]},"type":"Feature","properties":{"hierarchy":["tgn:2767408","tgn:1000001","tgn:2000273","tgn:7012149","tgn:7007240","tgn:7029392"],"placetype":["aat:300008697"],"id":2767408,"name:xx":"White Springs"}}
>>>>>>> 03f74aca74312dbeaf24d7e61306dd6a786dc3d0
