{
  "id": 7525060,
  "type": "Feature",
  "properties": {
    "tgn:hierarchy":[
        "tgn:7525060",
        "tgn:7001242",
        "tgn:7001311",
        "tgn:7016833",
        "tgn:7029392"
    ],
    "tgn:id":7525060,
    "tgn:name:en":"T\u00fbbya, Geziret",
    "tgn:placetype":[
        "aat:300008791"
    ]
},
  "bbox": [],
  "geometry": {"coordinates":[33.983333,26.833333],"type":"Point"}
}