{
  "id": 7232269,
  "type": "Feature",
  "properties": {
    "tgn:hierarchy":[
        "tgn:7232269",
        "tgn:7002748",
        "tgn:7001399",
        "tgn:1000003",
        "tgn:1000074",
        "tgn:7029392"
    ],
    "tgn:id":7232269,
    "tgn:name":"Makr\u00fdkampos",
    "tgn:placetype":[
        "aat:300008347"
    ]
},
  "bbox": [],
  "geometry": {"coordinates":[21.356944,39.208889],"type":"Point"}
}