{
  "id": 2323625,
  "type": "Feature",
  "properties": {
    "tgn:hierarchy":[
        "tgn:2323625",
        "tgn:1000001",
        "tgn:7012149",
        "tgn:1003038",
        "tgn:7007517",
        "tgn:7029392"
    ],
    "tgn:id":2323625,
    "tgn:name":"Farrow Hill",
    "tgn:placetype":[
        "aat:300008798"
    ]
},
  "bbox": [],
  "geometry": {"coordinates":[-72.1167,42.4167],"type":"Point"}
}