{
  "id": 7092995,
  "type": "Feature",
  "properties": {
    "tgn:hierarchy":[
        "tgn:7092995",
        "tgn:1000003",
        "tgn:7003678",
        "tgn:7000084",
        "tgn:7029392"
    ],
    "tgn:id":7092995,
    "tgn:name":"Schweinsberg",
    "tgn:placetype":[
        "aat:300008347"
    ]
},
  "bbox": [],
  "geometry": {"coordinates":[8.966667,50.766667],"type":"Point"}
}