<<<<<<< HEAD
{
  "id": 2152222,
  "type": "Feature",
  "properties": {
    "tgn:hierarchy":[
        "tgn:2152222",
        "tgn:1000001",
        "tgn:7012149",
        "tgn:7007712",
        "tgn:7029392"
    ],
    "tgn:id":2152222,
    "tgn:name":"Bay Branch",
    "tgn:placetype":[
        "aat:300008699"
    ]
},
  "bbox": [],
  "geometry": {"coordinates":[-80.75,33.55],"type":"Point"}
}
=======
{"geometry":{"type":"Point","coordinates":[-80.750000,33.550000]},"type":"Feature","properties":{"hierarchy":["tgn:2152222","tgn:1000001","tgn:7012149","tgn:7007712","tgn:7029392"],"placetype":["aat:300008699"],"id":2152222,"name:xx":"Bay Branch"}}
>>>>>>> 03f74aca74312dbeaf24d7e61306dd6a786dc3d0
