{
  "id": 7413571,
  "type": "Feature",
  "properties": {
    "tgn:hierarchy":[
        "tgn:7413571",
        "tgn:7005587",
        "tgn:1000001",
        "tgn:7005560",
        "tgn:7029392"
    ],
    "tgn:id":7413571,
    "tgn:name:es":"Potrero de los Reyes",
    "tgn:placetype":[
        "aat:300008347"
    ]
},
  "bbox": [],
  "geometry": {"coordinates":[-98.604167,20.316667],"type":"Point"}
}