{
  "id": 1098644,
  "type": "Feature",
  "properties": {
    "tgn:hierarchy":[
        "tgn:1098644",
        "tgn:7000490",
        "tgn:1000006",
        "tgn:7001828",
        "tgn:7029392"
    ],
    "tgn:id":1098644,
    "tgn:name":"Yarrangobilly",
    "tgn:placetype":[
        "aat:300008347"
    ]
},
  "bbox": [],
  "geometry": {"coordinates":[148.4833,-35.65],"type":"Point"}
}