<<<<<<< HEAD
{
  "id": 2764856,
  "type": "Feature",
  "properties": {
    "tgn:hierarchy":[
        "tgn:2764856",
        "tgn:1000001",
        "tgn:7012149",
        "tgn:2002121",
        "tgn:7007827",
        "tgn:7029392"
    ],
    "tgn:id":2764856,
    "tgn:name":"Whiskey Knoll",
    "tgn:placetype":[
        "aat:300008798"
    ]
},
  "bbox": [],
  "geometry": {"coordinates":[-111.7167,38.6167],"type":"Point"}
}
=======
{"geometry":{"type":"Point","coordinates":[-111.716700,38.616700]},"type":"Feature","properties":{"hierarchy":["tgn:2764856","tgn:1000001","tgn:7012149","tgn:2002121","tgn:7007827","tgn:7029392"],"placetype":["aat:300008798"],"id":2764856,"name:xx":"Whiskey Knoll"}}
>>>>>>> 03f74aca74312dbeaf24d7e61306dd6a786dc3d0
