{
  "id": 2716783,
  "type": "Feature",
  "properties": {
    "tgn:hierarchy":[
        "tgn:2716783",
        "tgn:1000001",
        "tgn:7012149",
        "tgn:7007157",
        "tgn:1002857",
        "tgn:7029392"
    ],
    "tgn:id":2716783,
    "tgn:name":"The Zanja",
    "tgn:placetype":[
        "aat:300008699"
    ]
},
  "bbox": [],
  "geometry": {"coordinates":[-117.0667,34.0667],"type":"Point"}
}