{
  "id": 2701027,
  "type": "Feature",
  "properties": {
    "tgn:hierarchy":[
        "tgn:2701027",
        "tgn:1000001",
        "tgn:7012149",
        "tgn:1002955",
        "tgn:7007706",
        "tgn:7029392"
    ],
    "tgn:id":2701027,
    "tgn:name":"Sugar Creek",
    "tgn:placetype":[
        "aat:300008706"
    ]
},
  "bbox": [],
  "geometry": {"coordinates":[-80.65,41.3167],"type":"Point"}
}