{
  "id": 7427868,
  "type": "Feature",
  "properties": {
    "tgn:hierarchy":[
        "tgn:7427868",
        "tgn:1000001",
        "tgn:7005594",
        "tgn:7005560",
        "tgn:7029392"
    ],
    "tgn:id":7427868,
    "tgn:name":"Pe\u00f1itas",
    "tgn:placetype":[
        "aat:300008347"
    ]
},
  "bbox": [],
  "geometry": {"coordinates":[-98.733333,22.266667],"type":"Point"}
}