{
  "id": 1084849,
  "type": "Feature",
  "properties": {
    "tgn:hierarchy":[
        "tgn:1084849",
        "tgn:7000676",
        "tgn:1000004",
        "tgn:7003879",
        "tgn:1000137",
        "tgn:7029392"
    ],
    "tgn:id":1084849,
    "tgn:name":"Ar-Raw\u1e0dah",
    "tgn:placetype":[
        "aat:300008347"
    ]
},
  "bbox": [],
  "geometry": {"coordinates":[40.6167,26.0833],"type":"Point"}
}