{
  "id": 2783695,
  "type": "Feature",
  "properties": {
    "tgn:hierarchy":[
        "tgn:2783695",
        "tgn:1000001",
        "tgn:1002724",
        "tgn:7012149",
        "tgn:7007517",
        "tgn:7029392"
    ],
    "tgn:id":2783695,
    "tgn:name":"Wyman Hill",
    "tgn:placetype":[
        "aat:300008798"
    ]
},
  "bbox": [],
  "geometry": {"coordinates":[-70.9667,42.2167],"type":"Point"}
}