{
  "id": 2677890,
  "type": "Feature",
  "properties": {
    "tgn:hierarchy":[
        "tgn:2677890",
        "tgn:1000001",
        "tgn:7012149",
        "tgn:2000213",
        "tgn:7007158",
        "tgn:7029392"
    ],
    "tgn:id":2677890,
    "tgn:name":"South Field Area",
    "tgn:placetype":[
        "aat:300000390"
    ]
},
  "bbox": [],
  "geometry": {"coordinates":[-105.15,38.2833],"type":"Point"}
}