<<<<<<< HEAD
{
  "id": 2251662,
  "type": "Feature",
  "properties": {
    "tgn:hierarchy":[
        "tgn:2251662",
        "tgn:1000001",
        "tgn:7012149",
        "tgn:2001249",
        "tgn:7007523",
        "tgn:7029392"
    ],
    "tgn:id":2251662,
    "tgn:name":"Company Hollow",
    "tgn:placetype":[
        "aat:300008761"
    ]
},
  "bbox": [],
  "geometry": {"coordinates":[-93.4333,36.55],"type":"Point"}
}
=======
{"geometry":{"type":"Point","coordinates":[-93.433300,36.550000]},"type":"Feature","properties":{"hierarchy":["tgn:2251662","tgn:1000001","tgn:7012149","tgn:2001249","tgn:7007523","tgn:7029392"],"placetype":["aat:300008761"],"id":2251662,"name:xx":"Company Hollow"}}
>>>>>>> 03f74aca74312dbeaf24d7e61306dd6a786dc3d0
