{
  "id": 2251662,
  "type": "Feature",
  "properties": {
    "tgn:hierarchy":[
        "tgn:2251662",
        "tgn:1000001",
        "tgn:7012149",
        "tgn:2001249",
        "tgn:7007523",
        "tgn:7029392"
    ],
    "tgn:id":2251662,
    "tgn:name":"Company Hollow",
    "tgn:placetype":[
        "aat:300008761"
    ]
},
  "bbox": [],
  "geometry": {"coordinates":[-93.4333,36.55],"type":"Point"}
}