{
  "id": 2575118,
  "type": "Feature",
  "properties": {
    "tgn:hierarchy":[
        "tgn:2575118",
        "tgn:1000001",
        "tgn:7012149",
        "tgn:7007255",
        "tgn:7029392"
    ],
    "tgn:id":2575118,
    "tgn:name":"Pennington Fork",
    "tgn:placetype":[
        "aat:300008699"
    ]
},
  "bbox": [],
  "geometry": {"coordinates":[-83.85,37.3167],"type":"Point"}
}