<<<<<<< HEAD
{
  "id": 7055427,
  "type": "Feature",
  "properties": {
    "tgn:hierarchy":[
        "tgn:7055427",
        "tgn:1003460",
        "tgn:1000003",
        "tgn:7009760",
        "tgn:1000080",
        "tgn:7029392"
    ],
    "tgn:id":7055427,
    "tgn:name":"Poggio Fuoco",
    "tgn:placetype":[
        "aat:300008347"
    ]
},
  "bbox": [],
  "geometry": {"coordinates":[11.483333,42.533333],"type":"Point"}
}
=======
{"geometry":{"type":"Point","coordinates":[11.483333,42.533333]},"type":"Feature","properties":{"hierarchy":["tgn:7055427","tgn:1003460","tgn:1000003","tgn:7009760","tgn:1000080","tgn:7029392"],"placetype":["aat:300008347"],"id":7055427,"name:xx":"Poggio Fuoco"}}
>>>>>>> 03f74aca74312dbeaf24d7e61306dd6a786dc3d0
