{
  "id": 7066570,
  "type": "Feature",
  "properties": {
    "tgn:hierarchy":[
        "tgn:7066570",
        "tgn:7003669",
        "tgn:1000003",
        "tgn:7000084",
        "tgn:7029392"
    ],
    "tgn:id":7066570,
    "tgn:name":"Stockholzschlag",
    "tgn:placetype":[
        "aat:300008863"
    ]
},
  "bbox": [],
  "geometry": {"coordinates":[10.483333,49.65],"type":"Point"}
}