{
  "id": 7320344,
  "type": "Feature",
  "properties": {
    "tgn:hierarchy":[
        "tgn:7320344",
        "tgn:1001657",
        "tgn:1000049",
        "tgn:1000002",
        "tgn:7029392"
    ],
    "tgn:id":7320344,
    "tgn:name":"Cabrito",
    "tgn:placetype":[
        "aat:300008347"
    ]
},
  "bbox": [],
  "geometry": {"coordinates":[-70.532778,-29.8975],"type":"Point"}
}