{
  "id": 2158211,
  "type": "Feature",
  "properties": {
    "tgn:hierarchy":[
        "tgn:2158211",
        "tgn:1000001",
        "tgn:7012149",
        "tgn:7007825",
        "tgn:7029392"
    ],
    "tgn:id":2158211,
    "tgn:name":"Beaver Ridge",
    "tgn:placetype":[
        "aat:300266640"
    ]
},
  "bbox": [],
  "geometry": {"coordinates":[-84.0833,35.9667],"type":"Point"}
}