{
  "id": 2238210,
  "type": "Feature",
  "properties": {
    "tgn:hierarchy":[
        "tgn:2238210",
        "tgn:1000001",
        "tgn:7012149",
        "tgn:1002717",
        "tgn:7007252",
        "tgn:7029392"
    ],
    "tgn:id":2238210,
    "tgn:name":"Chizum Ditch",
    "tgn:placetype":[
        "aat:300006075"
    ]
},
  "bbox": [],
  "geometry": {"coordinates":[-87.4167,40.8833],"type":"Point"}
}