{
  "id": 1071954,
  "type": "Feature",
  "properties": {
    "tgn:hierarchy":[
        "tgn:1071954",
        "tgn:1000004",
        "tgn:7002076",
        "tgn:1000111",
        "tgn:7029392"
    ],
    "tgn:id":1071954,
    "tgn:name":"Songcun",
    "tgn:placetype":[
        "aat:300008347"
    ]
},
  "bbox": [],
  "geometry": {"coordinates":[119.7167,30.4333],"type":"Point"}
}