{
  "id": 7411617,
  "type": "Feature",
  "properties": {
    "tgn:hierarchy":[
        "tgn:7411617",
        "tgn:7005587",
        "tgn:1000001",
        "tgn:7005560",
        "tgn:7029392"
    ],
    "tgn:id":7411617,
    "tgn:name:es":"Tecueyaca",
    "tgn:placetype":[
        "aat:300008347"
    ]
},
  "bbox": [],
  "geometry": {"coordinates":[-98.608333,20.933333],"type":"Point"}
}