{
  "id": 2217974,
  "type": "Feature",
  "properties": {
    "tgn:hierarchy":[
        "tgn:2217974",
        "tgn:1000001",
        "tgn:7012149",
        "tgn:7007157",
        "tgn:1002858",
        "tgn:7029392"
    ],
    "tgn:id":2217974,
    "tgn:name":"Camps Creek",
    "tgn:placetype":[
        "aat:300008706"
    ]
},
  "bbox": [],
  "geometry": {"coordinates":[-117.35,33.45],"type":"Point"}
}