{
  "id": 2682182,
  "type": "Feature",
  "properties": {
    "tgn:hierarchy":[
        "tgn:2682182",
        "tgn:1000001",
        "tgn:7012149",
        "tgn:7007826",
        "tgn:7029392"
    ],
    "tgn:id":2682182,
    "tgn:name":"South Tule Draw",
    "tgn:placetype":[
        "aat:300008761"
    ]
},
  "bbox": [],
  "geometry": {"coordinates":[-102.0167,34.4833],"type":"Point"}
}