{
  "id": 7580385,
  "type": "Feature",
  "properties": {
    "tgn:hierarchy":[
        "tgn:7580385",
        "tgn:1000004",
        "tgn:7000198",
        "tgn:1001998",
        "tgn:7029392"
    ],
    "tgn:id":7580385,
    "tgn:name:en":"Thenhlum",
    "tgn:placetype":[
        "aat:300008347"
    ]
},
  "bbox": [],
  "geometry": {"coordinates":[92.563344,23.223569],"type":"Point"}
}