<<<<<<< HEAD
{
  "id": 7028015,
  "type": "Feature",
  "properties": {
    "tgn:hierarchy":[
        "tgn:7028015",
        "tgn:7002445",
        "tgn:1000003",
        "tgn:7008157",
        "tgn:7008591",
        "tgn:7029392"
    ],
    "tgn:id":7028015,
    "tgn:name:en":"North Willingham",
    "tgn:placetype":[
        "aat:300008347",
        "aat:300008372"
    ]
},
  "bbox": [],
  "geometry": {"coordinates":[-0.25,53.383333],"type":"Point"}
}
=======
{"geometry":{"type":"Point","coordinates":[-0.250000,53.383333]},"type":"Feature","properties":{"hierarchy":["tgn:7028015","tgn:7002445","tgn:1000003","tgn:7008157","tgn:7008591","tgn:7029392"],"placetype":["aat:300008347","aat:300008372"],"name:en":"North Willingham","id":7028015}}
>>>>>>> 03f74aca74312dbeaf24d7e61306dd6a786dc3d0
