{
  "id": 2541836,
  "type": "Feature",
  "properties": {
    "tgn:hierarchy":[
        "tgn:2541836",
        "tgn:1000001",
        "tgn:7019982",
        "tgn:7012149",
        "tgn:7007517",
        "tgn:7029392"
    ],
    "tgn:id":2541836,
    "tgn:name":"Ninemile Pond",
    "tgn:placetype":[
        "aat:300008680"
    ]
},
  "bbox": [],
  "geometry": {"coordinates":[-72.4333,42.1333],"type":"Point"}
}