{
  "id": 7278694,
  "type": "Feature",
  "properties": {
    "tgn:hierarchy":[
        "tgn:7278694",
        "tgn:1001623",
        "tgn:1000049",
        "tgn:1000002",
        "tgn:7029392"
    ],
    "tgn:id":7278694,
    "tgn:name":"Sombrero, Cerro",
    "tgn:placetype":[
        "aat:300008795"
    ]
},
  "bbox": [],
  "geometry": {"coordinates":[-75.116667,-48.333333],"type":"Point"}
}