{
  "id": 2360288,
  "type": "Feature",
  "properties": {
    "tgn:hierarchy":[
        "tgn:2360288",
        "tgn:1000001",
        "tgn:7012149",
        "tgn:7007827",
        "tgn:7029392"
    ],
    "tgn:id":2360288,
    "tgn:name":"Grass Valley",
    "tgn:placetype":[
        "aat:300008761"
    ]
},
  "bbox": [],
  "geometry": {"coordinates":[-111.8333,38.55],"type":"Point"}
}