<<<<<<< HEAD
{
  "id": 7378535,
  "type": "Feature",
  "properties": {
    "tgn:hierarchy":[
        "tgn:7378535",
        "tgn:7005581",
        "tgn:1000001",
        "tgn:7005560",
        "tgn:7029392"
    ],
    "tgn:id":7378535,
    "tgn:name":"Rancho Las Cuatro Milpas",
    "tgn:placetype":[
        "aat:300000241"
    ]
},
  "bbox": [],
  "geometry": {"coordinates":[-104.483333,26.483333],"type":"Point"}
}
=======
{"geometry":{"type":"Point","coordinates":[-104.483333,26.483333]},"type":"Feature","properties":{"hierarchy":["tgn:7378535","tgn:7005581","tgn:1000001","tgn:7005560","tgn:7029392"],"placetype":["aat:300000241"],"id":7378535,"name:xx":"Rancho Las Cuatro Milpas"}}
>>>>>>> 03f74aca74312dbeaf24d7e61306dd6a786dc3d0
