{
  "id": 7378535,
  "type": "Feature",
  "properties": {
    "tgn:hierarchy":[
        "tgn:7378535",
        "tgn:7005581",
        "tgn:1000001",
        "tgn:7005560",
        "tgn:7029392"
    ],
    "tgn:id":7378535,
    "tgn:name":"Rancho Las Cuatro Milpas",
    "tgn:placetype":[
        "aat:300000241"
    ]
},
  "bbox": [],
  "geometry": {"coordinates":[-104.483333,26.483333],"type":"Point"}
}