{
  "id": 6001485,
  "type": "Feature",
  "properties": {
    "tgn:hierarchy":[
        "tgn:6001485",
        "tgn:7001242",
        "tgn:7016833",
        "tgn:7001336",
        "tgn:7029392"
    ],
    "tgn:id":6001485,
    "tgn:name":"Clysma",
    "tgn:placetype":[
        "aat:300008347",
        "aat:300167671",
        "aat:300120599"
    ]
},
  "bbox": [],
  "geometry": {"coordinates":[32.55,29.9667],"type":"Point"}
}