<<<<<<< HEAD
{
  "id": 2253568,
  "type": "Feature",
  "properties": {
    "tgn:hierarchy":[
        "tgn:2253568",
        "tgn:1000001",
        "tgn:7012149",
        "tgn:2001898",
        "tgn:7007825",
        "tgn:7029392"
    ],
    "tgn:id":2253568,
    "tgn:name":"Cook Hollow",
    "tgn:placetype":[
        "aat:300008761"
    ]
},
  "bbox": [],
  "geometry": {"coordinates":[-84.0167,35.5333],"type":"Point"}
}
=======
{"geometry":{"type":"Point","coordinates":[-84.016700,35.533300]},"type":"Feature","properties":{"hierarchy":["tgn:2253568","tgn:1000001","tgn:7012149","tgn:2001898","tgn:7007825","tgn:7029392"],"placetype":["aat:300008761"],"id":2253568,"name:xx":"Cook Hollow"}}
>>>>>>> 03f74aca74312dbeaf24d7e61306dd6a786dc3d0
