{
  "id": 7057947,
  "type": "Feature",
  "properties": {
    "tgn:hierarchy":[
        "tgn:7057947",
        "tgn:1003442",
        "tgn:1000003",
        "tgn:7010380",
        "tgn:1000080",
        "tgn:7029392"
    ],
    "tgn:id":7057947,
    "tgn:name":"Brindisi, Porto di",
    "tgn:placetype":[
        "aat:300132316"
    ]
},
  "bbox": [],
  "geometry": {"coordinates":[17.95,40.65],"type":"Point"}
}