{
  "id": 7589678,
  "type": "Feature",
  "properties": {
    "tgn:hierarchy":[
        "tgn:7589678",
        "tgn:1000004",
        "tgn:7000198",
        "tgn:7000799",
        "tgn:7029392"
    ],
    "tgn:id":7589678,
    "tgn:name:en":"Bal\u012bn N\u0101la",
    "tgn:placetype":[
        "aat:300008699"
    ]
},
  "bbox": [],
  "geometry": {"coordinates":[74.9125,32.8625],"type":"Point"}
}