{
  "id": 2206467,
  "type": "Feature",
  "properties": {
    "tgn:hierarchy":[
        "tgn:2206467",
        "tgn:1000001",
        "tgn:2001009",
        "tgn:7012149",
        "tgn:7007521",
        "tgn:7029392"
    ],
    "tgn:id":2206467,
    "tgn:name":"Bullhead Lake",
    "tgn:placetype":[
        "aat:300008680"
    ]
},
  "bbox": [],
  "geometry": {"coordinates":[-94.1833,46.9833],"type":"Point"}
}