{
  "id": 2130341,
  "type": "Feature",
  "properties": {
    "tgn:hierarchy":[
        "tgn:2130341",
        "tgn:1000001",
        "tgn:7012149",
        "tgn:2000365",
        "tgn:7007248",
        "tgn:7029392"
    ],
    "tgn:id":2130341,
    "tgn:name":"Allens Lake",
    "tgn:placetype":[
        "aat:300008680"
    ]
},
  "bbox": [],
  "geometry": {"coordinates":[-85.15,33.2667],"type":"Point"}
}