{
  "id": 7329011,
  "type": "Feature",
  "properties": {
    "tgn:hierarchy":[
        "tgn:7329011",
        "tgn:7002825",
        "tgn:7016622",
        "tgn:1000003",
        "tgn:1000095",
        "tgn:7029392"
    ],
    "tgn:id":7329011,
    "tgn:name":"Punta de Mujeres",
    "tgn:placetype":[
        "aat:300008347"
    ]
},
  "bbox": [],
  "geometry": {"coordinates":[-13.433333,29.133333],"type":"Point"}
}