{
  "id": 7290924,
  "type": "Feature",
  "properties": {
    "tgn:hierarchy":[
        "tgn:7290924",
        "tgn:1001637",
        "tgn:1000049",
        "tgn:1000002",
        "tgn:7029392"
    ],
    "tgn:id":7290924,
    "tgn:name":"Desag\u00fce, Estero",
    "tgn:placetype":[
        "aat:300008699"
    ]
},
  "bbox": [],
  "geometry": {"coordinates":[-72.566667,-37.383333],"type":"Point"}
}