{
  "id": 7033832,
  "type": "Feature",
  "properties": {
    "tgn:hierarchy":[
        "tgn:7033832",
        "tgn:1000003",
        "tgn:7003236",
        "tgn:1000080",
        "tgn:7029392"
    ],
    "tgn:id":7033832,
    "tgn:name":"Paraggi, Seno di",
    "tgn:placetype":[
        "aat:300132316"
    ]
},
  "bbox": [],
  "geometry": {"coordinates":[9.216667,44.316667],"type":"Point"}
}