{
  "id": 7457577,
  "type": "Feature",
  "properties": {
    "tgn:hierarchy":[
        "tgn:7457577",
        "tgn:7019094",
        "tgn:7002444",
        "tgn:1000003",
        "tgn:7008591",
        "tgn:7029392"
    ],
    "tgn:id":7457577,
    "tgn:name:en":"Pennyghael",
    "tgn:placetype":[
        "aat:300004792"
    ]
},
  "bbox": [],
  "geometry": {"coordinates":[-6.033333,56.366667],"type":"Point"}
}