{
  "id": 2472614,
  "type": "Feature",
  "properties": {
    "tgn:hierarchy":[
        "tgn:2472614",
        "tgn:1000001",
        "tgn:7012149",
        "tgn:7007157",
        "tgn:1002858",
        "tgn:7029392"
    ],
    "tgn:id":2472614,
    "tgn:name":"Love Valley",
    "tgn:placetype":[
        "aat:300386845"
    ]
},
  "bbox": [],
  "geometry": {"coordinates":[-116.7667,33.25],"type":"Point"}
}