{
  "id": 7483907,
  "type": "Feature",
  "properties": {
    "tgn:hierarchy":[
        "tgn:7483907",
        "tgn:1000004",
        "tgn:7001014",
        "tgn:1000141",
        "tgn:7029392"
    ],
    "tgn:id":7483907,
    "tgn:name":"Chaolong Gong",
    "tgn:placetype":[
        "aat:300007595"
    ]
},
  "bbox": [],
  "geometry": {"coordinates":[120.513889,23.681667],"type":"Point"}
}