{
  "id": 7480690,
  "type": "Feature",
  "properties": {
    "tgn:hierarchy":[
        "tgn:7480690",
        "tgn:7001010",
        "tgn:1000004",
        "tgn:1000141",
        "tgn:7029392"
    ],
    "tgn:id":7480690,
    "tgn:name":"Guangming Qiao",
    "tgn:placetype":[
        "aat:300007836"
    ]
},
  "bbox": [],
  "geometry": {"coordinates":[121.566667,23.781389],"type":"Point"}
}