{
  "id": 7440981,
  "type": "Feature",
  "properties": {
    "tgn:hierarchy":[
        "tgn:7440981",
        "tgn:1000001",
        "tgn:7005589",
        "tgn:7005560",
        "tgn:7029392"
    ],
    "tgn:id":7440981,
    "tgn:name":"Santa Ana de Abajo",
    "tgn:placetype":[
        "aat:300008347"
    ]
},
  "bbox": [],
  "geometry": {"coordinates":[-100.116667,25.566667],"type":"Point"}
}