{
  "id": 2155246,
  "type": "Feature",
  "properties": {
    "tgn:hierarchy":[
        "tgn:2155246",
        "tgn:1000001",
        "tgn:2000470",
        "tgn:7012149",
        "tgn:7007250",
        "tgn:7029392"
    ],
    "tgn:id":2155246,
    "tgn:name":"Bear Mountain",
    "tgn:placetype":[
        "aat:300008798"
    ]
},
  "bbox": [],
  "geometry": {"coordinates":[-113.45,44.35],"type":"Point"}
}