{
  "id": 2463007,
  "type": "Feature",
  "properties": {
    "tgn:hierarchy":[
        "tgn:2463007",
        "tgn:1000001",
        "tgn:1002258",
        "tgn:7012149",
        "tgn:7007240",
        "tgn:7029392"
    ],
    "tgn:id":2463007,
    "tgn:name":"Live Oak Point",
    "tgn:placetype":[
        "aat:300008850"
    ]
},
  "bbox": [],
  "geometry": {"coordinates":[-82.05,26.9333],"type":"Point"}
}