{
  "id": 2211207,
  "type": "Feature",
  "properties": {
    "tgn:hierarchy":[
        "tgn:2211207",
        "tgn:1000001",
        "tgn:7012149",
        "tgn:2002169",
        "tgn:7007919",
        "tgn:7029392"
    ],
    "tgn:id":2211207,
    "tgn:name":"Butt Of Powell Mountain",
    "tgn:placetype":[
        "aat:300008798"
    ]
},
  "bbox": [],
  "geometry": {"coordinates":[-82.8667,36.7333],"type":"Point"}
}