{
  "id": 7248914,
  "type": "Feature",
  "properties": {
    "tgn:hierarchy":[
        "tgn:7248914",
        "tgn:7003461",
        "tgn:1000003",
        "tgn:1000063",
        "tgn:7018236",
        "tgn:7029392"
    ],
    "tgn:id":7248914,
    "tgn:name":"Broekem",
    "tgn:placetype":[
        "aat:300008347"
    ]
},
  "bbox": [],
  "geometry": {"coordinates":[5.516667,50.883333],"type":"Point"}
}