{
  "id": 7095418,
  "type": "Feature",
  "properties": {
    "tgn:hierarchy":[
        "tgn:7095418",
        "tgn:1000003",
        "tgn:7003689",
        "tgn:7000084",
        "tgn:7029392"
    ],
    "tgn:id":7095418,
    "tgn:name":"Sch\u00f6nbrunn",
    "tgn:placetype":[
        "aat:300008347"
    ]
},
  "bbox": [],
  "geometry": {"coordinates":[12.05,50.583333],"type":"Point"}
}