{
  "id": 7521204,
  "type": "Feature",
  "properties": {
    "tgn:hierarchy":[
        "tgn:7521204",
        "tgn:7001242",
        "tgn:7016833",
        "tgn:7001336",
        "tgn:7029392"
    ],
    "tgn:id":7521204,
    "tgn:name":"Ab\u016b Durbah",
    "tgn:placetype":[
        "aat:300008347"
    ]
},
  "bbox": [],
  "geometry": {"coordinates":[33.328489,28.474424],"type":"Point"}
}