{
  "id": 7153844,
  "type": "Feature",
  "properties": {
    "tgn:hierarchy":[
        "tgn:7153844",
        "tgn:7003669",
        "tgn:1000003",
        "tgn:7000084",
        "tgn:7029392"
    ],
    "tgn:id":7153844,
    "tgn:name":"Karlinger",
    "tgn:placetype":[
        "aat:300000206"
    ]
},
  "bbox": [],
  "geometry": {"coordinates":[11.866667,47.816667],"type":"Point"}
}