{
  "id": 2276769,
  "type": "Feature",
  "properties": {
    "tgn:hierarchy":[
        "tgn:2276769",
        "tgn:1000001",
        "tgn:7012149",
        "tgn:1002553",
        "tgn:7007920",
        "tgn:7029392"
    ],
    "tgn:id":2276769,
    "tgn:name":"Davies Canyon",
    "tgn:placetype":[
        "aat:300008761"
    ]
},
  "bbox": [],
  "geometry": {"coordinates":[-120.1333,47.2333],"type":"Point"}
}