{
  "id": 1022923,
  "type": "Feature",
  "properties": {
    "tgn:hierarchy":[
        "tgn:1022923",
        "tgn:7005437",
        "tgn:1000047",
        "tgn:7002455",
        "tgn:1000002",
        "tgn:7029392"
    ],
    "tgn:id":1022923,
    "tgn:name":"Salgueiro",
    "tgn:placetype":[
        "aat:300008347"
    ]
},
  "bbox": [],
  "geometry": {"coordinates":[-39.0833,-8.0667],"type":"Point"}
}