<<<<<<< HEAD
{
  "id": 7173143,
  "type": "Feature",
  "properties": {
    "tgn:hierarchy":[
        "tgn:7173143",
        "tgn:1000003",
        "tgn:7003689",
        "tgn:7000084",
        "tgn:7029392"
    ],
    "tgn:id":7173143,
    "tgn:name":"Greiz, Forst",
    "tgn:placetype":[
        "aat:300008863"
    ]
},
  "bbox": [],
  "geometry": {"coordinates":[12.2,50.683333],"type":"Point"}
}
=======
{"geometry":{"type":"Point","coordinates":[12.200000,50.683333]},"type":"Feature","properties":{"hierarchy":["tgn:7173143","tgn:1000003","tgn:7003689","tgn:7000084","tgn:7029392"],"placetype":["aat:300008863"],"id":7173143,"name:xx":"Greiz, Forst"}}
>>>>>>> 03f74aca74312dbeaf24d7e61306dd6a786dc3d0
