{
  "id": 7498761,
  "type": "Feature",
  "properties": {
    "tgn:hierarchy":[
        "tgn:7498761",
        "tgn:1000004",
        "tgn:7491221",
        "tgn:1000141",
        "tgn:7029392"
    ],
    "tgn:id":7498761,
    "tgn:name":"Zhensha Qiao",
    "tgn:placetype":[
        "aat:300007836"
    ]
},
  "bbox": [],
  "geometry": {"coordinates":[121.186597,22.836906],"type":"Point"}
}