<<<<<<< HEAD
{
  "id": 2767449,
  "type": "Feature",
  "properties": {
    "tgn:hierarchy":[
        "tgn:2767449",
        "tgn:1000001",
        "tgn:2001178",
        "tgn:7012149",
        "tgn:7007523",
        "tgn:7029392"
    ],
    "tgn:id":2767449,
    "tgn:name":"White Sulphur Spring",
    "tgn:placetype":[
        "aat:300008697"
    ]
},
  "bbox": [],
  "geometry": {"coordinates":[-92.5667,38.05],"type":"Point"}
}
=======
{"geometry":{"type":"Point","coordinates":[-92.566700,38.050000]},"type":"Feature","properties":{"hierarchy":["tgn:2767449","tgn:1000001","tgn:2001178","tgn:7012149","tgn:7007523","tgn:7029392"],"placetype":["aat:300008697"],"id":2767449,"name:xx":"White Sulphur Spring"}}
>>>>>>> 03f74aca74312dbeaf24d7e61306dd6a786dc3d0
