{
  "id": 7455782,
  "type": "Feature",
  "properties": {
    "tgn:hierarchy":[
        "tgn:7455782",
        "tgn:7002444",
        "tgn:1000003",
        "tgn:7019091",
        "tgn:7008591",
        "tgn:7029392"
    ],
    "tgn:id":7455782,
    "tgn:name:en":"Clyde, River",
    "tgn:placetype":[
        "aat:300008699"
    ]
},
  "bbox": [],
  "geometry": {"coordinates":[-4.916667,55.733333],"type":"Point"}
}