{
  "id": 7194610,
  "type": "Feature",
  "properties": {
    "tgn:hierarchy":[
        "tgn:7194610",
        "tgn:1000003",
        "tgn:7000094",
        "tgn:7000084",
        "tgn:7029392"
    ],
    "tgn:id":7194610,
    "tgn:name":"Demminer Stadtforst",
    "tgn:placetype":[
        "aat:300008863"
    ]
},
  "bbox": [],
  "geometry": {"coordinates":[12.966667,53.933333],"type":"Point"}
}