{
  "id": 7413699,
  "type": "Feature",
  "properties": {
    "tgn:hierarchy":[
        "tgn:7413699",
        "tgn:7005580",
        "tgn:1000001",
        "tgn:7005560",
        "tgn:7029392"
    ],
    "tgn:id":7413699,
    "tgn:name":"Gracias a Dios",
    "tgn:placetype":[
        "aat:300008347"
    ]
},
  "bbox": [],
  "geometry": {"coordinates":[-93.241667,16.747222],"type":"Point"}
}