{
  "id": 2262689,
  "type": "Feature",
  "properties": {
    "tgn:hierarchy":[
        "tgn:2262689",
        "tgn:1000001",
        "tgn:7006451",
        "tgn:2000092",
        "tgn:7012149",
        "tgn:7029392"
    ],
    "tgn:id":2262689,
    "tgn:name":"Cow Trap Tank",
    "tgn:placetype":[
        "aat:300006191"
    ]
},
  "bbox": [],
  "geometry": {"coordinates":[-111.0833,34.7333],"type":"Point"}
}