<<<<<<< HEAD
{
  "id": 2252846,
  "type": "Feature",
  "properties": {
    "tgn:hierarchy":[
        "tgn:2252846",
        "tgn:1000001",
        "tgn:7016106",
        "tgn:7012149",
        "tgn:7007516",
        "tgn:7029392"
    ],
    "tgn:id":2252846,
    "tgn:name":"Conococheague",
    "tgn:placetype":[
        "aat:300008347"
    ]
},
  "bbox": [],
  "geometry": {"coordinates":[-77.8333,39.65],"type":"Point"}
}
=======
{"geometry":{"type":"Point","coordinates":[-77.833300,39.650000]},"type":"Feature","properties":{"hierarchy":["tgn:2252846","tgn:1000001","tgn:7016106","tgn:7012149","tgn:7007516","tgn:7029392"],"placetype":["aat:300008347"],"id":2252846,"name:xx":"Conococheague"}}
>>>>>>> 03f74aca74312dbeaf24d7e61306dd6a786dc3d0
