{
  "id": 2469698,
  "type": "Feature",
  "properties": {
    "tgn:hierarchy":[
        "tgn:2469698",
        "tgn:1000001",
        "tgn:7012149",
        "tgn:7014510",
        "tgn:7007920",
        "tgn:7029392"
    ],
    "tgn:id":2469698,
    "tgn:name":"Lookout Mountain",
    "tgn:placetype":[
        "aat:300008798"
    ]
},
  "bbox": [],
  "geometry": {"coordinates":[-121.3167,48.55],"type":"Point"}
}