<<<<<<< HEAD
{
  "id": 2156245,
  "type": "Feature",
  "properties": {
    "tgn:hierarchy":[
        "tgn:2156245",
        "tgn:1000001",
        "tgn:7012149",
        "tgn:7007157",
        "tgn:2000189",
        "tgn:7029392"
    ],
    "tgn:id":2156245,
    "tgn:name":"Bearground Gulch",
    "tgn:placetype":[
        "aat:300008761"
    ]
},
  "bbox": [],
  "geometry": {"coordinates":[-122.9333,41.95],"type":"Point"}
}
=======
{"geometry":{"type":"Point","coordinates":[-122.933300,41.950000]},"type":"Feature","properties":{"hierarchy":["tgn:2156245","tgn:1000001","tgn:7012149","tgn:7007157","tgn:2000189","tgn:7029392"],"placetype":["aat:300008761"],"id":2156245,"name:xx":"Bearground Gulch"}}
>>>>>>> 03f74aca74312dbeaf24d7e61306dd6a786dc3d0
