{
  "id": 7113889,
  "type": "Feature",
  "properties": {
    "tgn:hierarchy":[
        "tgn:7113889",
        "tgn:1000003",
        "tgn:7003689",
        "tgn:7000084",
        "tgn:7029392"
    ],
    "tgn:id":7113889,
    "tgn:name":"Rodameuschel",
    "tgn:placetype":[
        "aat:300008347"
    ]
},
  "bbox": [],
  "geometry": {"coordinates":[11.716667,51.033333],"type":"Point"}
}