{
  "id": 7140785,
  "type": "Feature",
  "properties": {
    "tgn:hierarchy":[
        "tgn:7140785",
        "tgn:1000003",
        "tgn:7003687",
        "tgn:7000084",
        "tgn:7029392"
    ],
    "tgn:id":7140785,
    "tgn:name":"Listerfehrda",
    "tgn:placetype":[
        "aat:300008347"
    ]
},
  "bbox": [],
  "geometry": {"coordinates":[12.85,51.816667],"type":"Point"}
}