{
  "id": 1108291,
  "type": "Feature",
  "properties": {
    "tgn:hierarchy":[
        "tgn:1108291",
        "tgn:1000001",
        "tgn:7012149",
        "tgn:2001667",
        "tgn:7007707",
        "tgn:7029392"
    ],
    "tgn:id":1108291,
    "tgn:name":"Williams Mountain",
    "tgn:placetype":[
        "aat:300008777"
    ]
},
  "bbox": [],
  "geometry": {"coordinates":[-94.55,34.2333],"type":"Point"}
}