{
  "id": 7107211,
  "type": "Feature",
  "properties": {
    "tgn:hierarchy":[
        "tgn:7107211",
        "tgn:7003669",
        "tgn:1000003",
        "tgn:7000084",
        "tgn:7029392"
    ],
    "tgn:id":7107211,
    "tgn:name":"Schadenreuth",
    "tgn:placetype":[
        "aat:300008347"
    ]
},
  "bbox": [],
  "geometry": {"coordinates":[12.016667,49.85],"type":"Point"}
}