<<<<<<< HEAD
{
  "id": 2768939,
  "type": "Feature",
  "properties": {
    "tgn:hierarchy":[
        "tgn:2768939",
        "tgn:1000001",
        "tgn:1002289",
        "tgn:7012149",
        "tgn:7007240",
        "tgn:7029392"
    ],
    "tgn:id":2768939,
    "tgn:name":"Whitney River",
    "tgn:placetype":[
        "aat:300008707"
    ]
},
  "bbox": [],
  "geometry": {"coordinates":[-81.5333,25.9667],"type":"Point"}
}
=======
{"geometry":{"type":"Point","coordinates":[-81.533300,25.966700]},"type":"Feature","properties":{"hierarchy":["tgn:2768939","tgn:1000001","tgn:1002289","tgn:7012149","tgn:7007240","tgn:7029392"],"placetype":["aat:300008707"],"id":2768939,"name:xx":"Whitney River"}}
>>>>>>> 03f74aca74312dbeaf24d7e61306dd6a786dc3d0
