{
  "id": 2768939,
  "type": "Feature",
  "properties": {
    "tgn:hierarchy":[
        "tgn:2768939",
        "tgn:1000001",
        "tgn:1002289",
        "tgn:7012149",
        "tgn:7007240",
        "tgn:7029392"
    ],
    "tgn:id":2768939,
    "tgn:name":"Whitney River",
    "tgn:placetype":[
        "aat:300008707"
    ]
},
  "bbox": [],
  "geometry": {"coordinates":[-81.5333,25.9667],"type":"Point"}
}