<<<<<<< HEAD
{
  "id": 7379179,
  "type": "Feature",
  "properties": {
    "tgn:hierarchy":[
        "tgn:7379179",
        "tgn:1000001",
        "tgn:7005597",
        "tgn:7005560",
        "tgn:7029392"
    ],
    "tgn:id":7379179,
    "tgn:name":"Rancho Los Sabinos",
    "tgn:placetype":[
        "aat:300000241"
    ]
},
  "bbox": [],
  "geometry": {"coordinates":[-99.083333,24.25],"type":"Point"}
}
=======
{"geometry":{"type":"Point","coordinates":[-99.083333,24.250000]},"type":"Feature","properties":{"hierarchy":["tgn:7379179","tgn:1000001","tgn:7005597","tgn:7005560","tgn:7029392"],"placetype":["aat:300000241"],"id":7379179,"name:xx":"Rancho Los Sabinos"}}
>>>>>>> 03f74aca74312dbeaf24d7e61306dd6a786dc3d0
