<<<<<<< HEAD
{
  "id": 2339509,
  "type": "Feature",
  "properties": {
    "tgn:hierarchy":[
        "tgn:2339509",
        "tgn:1000001",
        "tgn:7006451",
        "tgn:2000092",
        "tgn:7012149",
        "tgn:7029392"
    ],
    "tgn:id":2339509,
    "tgn:name":"Fred Haught Ridge",
    "tgn:placetype":[
        "aat:300266640"
    ]
},
  "bbox": [],
  "geometry": {"coordinates":[-111.2,34.4667],"type":"Point"}
}
=======
{"geometry":{"type":"Point","coordinates":[-111.200000,34.466700]},"type":"Feature","properties":{"hierarchy":["tgn:2339509","tgn:1000001","tgn:7006451","tgn:2000092","tgn:7012149","tgn:7029392"],"placetype":["aat:300266640"],"id":2339509,"name:xx":"Fred Haught Ridge"}}
>>>>>>> 03f74aca74312dbeaf24d7e61306dd6a786dc3d0
