{
  "id": 2355495,
  "type": "Feature",
  "properties": {
    "tgn:hierarchy":[
        "tgn:2355495",
        "tgn:1000001",
        "tgn:7012149",
        "tgn:1002644",
        "tgn:7007255",
        "tgn:7029392"
    ],
    "tgn:id":2355495,
    "tgn:name":"Goose Creek",
    "tgn:placetype":[
        "aat:300008706"
    ]
},
  "bbox": [],
  "geometry": {"coordinates":[-83.7333,38.6167],"type":"Point"}
}