{
  "id": 2433894,
  "type": "Feature",
  "properties": {
    "tgn:hierarchy":[
        "tgn:2433894",
        "tgn:1000001",
        "tgn:7012149",
        "tgn:1002440",
        "tgn:7007568",
        "tgn:7029392"
    ],
    "tgn:id":2433894,
    "tgn:name":"Kelly Point",
    "tgn:placetype":[
        "aat:300008850"
    ]
},
  "bbox": [],
  "geometry": {"coordinates":[-74.3667,44.0167],"type":"Point"}
}