<<<<<<< HEAD
{
  "id": 2255140,
  "type": "Feature",
  "properties": {
    "tgn:hierarchy":[
        "tgn:2255140",
        "tgn:1000001",
        "tgn:7012149",
        "tgn:7015666",
        "tgn:7007825",
        "tgn:7029392"
    ],
    "tgn:id":2255140,
    "tgn:name":"Cooper Hollow",
    "tgn:placetype":[
        "aat:300008761"
    ]
},
  "bbox": [],
  "geometry": {"coordinates":[-87.3167,35.85],"type":"Point"}
}
=======
{"geometry":{"type":"Point","coordinates":[-87.316700,35.850000]},"type":"Feature","properties":{"hierarchy":["tgn:2255140","tgn:1000001","tgn:7012149","tgn:7015666","tgn:7007825","tgn:7029392"],"placetype":["aat:300008761"],"id":2255140,"name:xx":"Cooper Hollow"}}
>>>>>>> 03f74aca74312dbeaf24d7e61306dd6a786dc3d0
