{
  "id": 7434366,
  "type": "Feature",
  "properties": {
    "tgn:hierarchy":[
        "tgn:7434366",
        "tgn:1001836",
        "tgn:1000001",
        "tgn:7005560",
        "tgn:7029392"
    ],
    "tgn:id":7434366,
    "tgn:name":"Tres Mar\u00edas",
    "tgn:placetype":[
        "aat:300008347"
    ]
},
  "bbox": [],
  "geometry": {"coordinates":[-112.079444,25.956389],"type":"Point"}
}