{
  "id": 7585746,
  "type": "Feature",
  "properties": {
    "tgn:hierarchy":[
        "tgn:7585746",
        "tgn:1000004",
        "tgn:7000198",
        "tgn:7000799",
        "tgn:7029392"
    ],
    "tgn:id":7585746,
    "tgn:name:en":"K\u0101jpathar",
    "tgn:placetype":[
        "aat:300008347"
    ]
},
  "bbox": [],
  "geometry": {"coordinates":[74.994544,34.256413],"type":"Point"}
}