{
  "id": 7495072,
  "type": "Feature",
  "properties": {
    "tgn:hierarchy":[
        "tgn:7495072",
        "tgn:7468018",
        "tgn:1000004",
        "tgn:1000141",
        "tgn:7029392"
    ],
    "tgn:id":7495072,
    "tgn:name":"Yayisana",
    "tgn:placetype":[
        "aat:300008347"
    ]
},
  "bbox": [],
  "geometry": {"coordinates":[120.695507,23.346491],"type":"Point"}
}