{
  "id": 2744523,
  "type": "Feature",
  "properties": {
    "tgn:hierarchy":[
        "tgn:2744523",
        "tgn:1000001",
        "tgn:7012149",
        "tgn:2000476",
        "tgn:7007250",
        "tgn:7029392"
    ],
    "tgn:id":2744523,
    "tgn:name":"Vetter Creek",
    "tgn:placetype":[
        "aat:300008706"
    ]
},
  "bbox": [],
  "geometry": {"coordinates":[-115.4833,45.65],"type":"Point"}
}