{
  "id": 7346476,
  "type": "Feature",
  "properties": {
    "tgn:hierarchy":[
        "tgn:7346476",
        "tgn:7002760",
        "tgn:1000003",
        "tgn:1000095",
        "tgn:7029392"
    ],
    "tgn:id":7346476,
    "tgn:name":"Belmonte",
    "tgn:placetype":[
        "aat:300008347"
    ]
},
  "bbox": [],
  "geometry": {"coordinates":[-4.45,43.116667],"type":"Point"}
}