{
  "id": 7563093,
  "type": "Feature",
  "properties": {
    "tgn:hierarchy":[
        "tgn:7563093",
        "tgn:1000004",
        "tgn:7000198",
        "tgn:7016722",
        "tgn:7029392"
    ],
    "tgn:id":7563093,
    "tgn:name:en":"K\u0101ndwa",
    "tgn:placetype":[
        "aat:300008347"
    ]
},
  "bbox": [],
  "geometry": {"coordinates":[79.212215,26.336753],"type":"Point"}
}