{
  "id": 7275426,
  "type": "Feature",
  "properties": {
    "tgn:hierarchy":[
        "tgn:7275426",
        "tgn:1001702",
        "tgn:1000049",
        "tgn:1000002",
        "tgn:7029392"
    ],
    "tgn:id":7275426,
    "tgn:name":"Tryon, Punta",
    "tgn:placetype":[
        "aat:300386846"
    ]
},
  "bbox": [],
  "geometry": {"coordinates":[-74.316667,-50.916667],"type":"Point"}
}