{
  "id": 2000622,
  "type": "Feature",
  "properties": {
    "tgn:hierarchy":[
        "tgn:2000622",
        "tgn:1000001",
        "tgn:7012149",
        "tgn:7007253",
        "tgn:7029392"
    ],
    "tgn:id":2000622,
    "tgn:name":"Mahaska",
    "tgn:placetype":[
        "aat:300387145",
        "aat:300000771"
    ]
},
  "bbox": [],
  "geometry": {"coordinates":[-92.65,41.3333],"type":"Point"}
}