<<<<<<< HEAD
{
  "id": 2409888,
  "type": "Feature",
  "properties": {
    "tgn:hierarchy":[
        "tgn:2409888",
        "tgn:7006450",
        "tgn:1000001",
        "tgn:7019698",
        "tgn:7012149",
        "tgn:7029392"
    ],
    "tgn:id":2409888,
    "tgn:name":"Imeri Lake",
    "tgn:placetype":[
        "aat:300008680"
    ]
},
  "bbox": [],
  "geometry": {"coordinates":[-150.4667,60.5333],"type":"Point"}
}
=======
{"geometry":{"type":"Point","coordinates":[-150.466700,60.533300]},"type":"Feature","properties":{"hierarchy":["tgn:2409888","tgn:7006450","tgn:1000001","tgn:7019698","tgn:7012149","tgn:7029392"],"placetype":["aat:300008680"],"id":2409888,"name:xx":"Imeri Lake"}}
>>>>>>> 03f74aca74312dbeaf24d7e61306dd6a786dc3d0
