{
  "id": 7057100,
  "type": "Feature",
  "properties": {
    "tgn:hierarchy":[
        "tgn:7057100",
        "tgn:1003460",
        "tgn:1000003",
        "tgn:7009760",
        "tgn:1000080",
        "tgn:7029392"
    ],
    "tgn:id":7057100,
    "tgn:name":"Barbanella",
    "tgn:placetype":[
        "aat:300008347"
    ]
},
  "bbox": [],
  "geometry": {"coordinates":[11.133333,42.783333],"type":"Point"}
}