{
  "id": 2694176,
  "type": "Feature",
  "properties": {
    "tgn:hierarchy":[
        "tgn:2694176",
        "tgn:1002145",
        "tgn:1000001",
        "tgn:7012149",
        "tgn:7007157",
        "tgn:7029392"
    ],
    "tgn:id":2694176,
    "tgn:name":"Stevens Lake",
    "tgn:placetype":[
        "aat:300006191"
    ]
},
  "bbox": [],
  "geometry": {"coordinates":[-119.7833,38.75],"type":"Point"}
}