{
  "id": 2566777,
  "type": "Feature",
  "properties": {
    "tgn:hierarchy":[
        "tgn:2566777",
        "tgn:1000001",
        "tgn:7012149",
        "tgn:2001925",
        "tgn:7007825",
        "tgn:7029392"
    ],
    "tgn:id":2566777,
    "tgn:name":"Panter Cave",
    "tgn:placetype":[
        "aat:300008746"
    ]
},
  "bbox": [],
  "geometry": {"coordinates":[-85.6333,35.5667],"type":"Point"}
}