{
  "id": 7576335,
  "type": "Feature",
  "properties": {
    "tgn:hierarchy":[
        "tgn:7576335",
        "tgn:1000004",
        "tgn:7000198",
        "tgn:7016788",
        "tgn:7029392"
    ],
    "tgn:id":7576335,
    "tgn:name:en":"Kh\u0101ndhar",
    "tgn:placetype":[
        "aat:300008347"
    ]
},
  "bbox": [],
  "geometry": {"coordinates":[76.604825,26.013486],"type":"Point"}
}