{
  "id": 7497383,
  "type": "Feature",
  "properties": {
    "tgn:hierarchy":[
        "tgn:7497383",
        "tgn:1000004",
        "tgn:1000959",
        "tgn:1000141",
        "tgn:7029392"
    ],
    "tgn:id":7497383,
    "tgn:name":"Sanhuijiao",
    "tgn:placetype":[
        "aat:300008347"
    ]
},
  "bbox": [],
  "geometry": {"coordinates":[121.5751,25.0171],"type":"Point"}
}