<<<<<<< HEAD
{
  "id": 2760540,
  "type": "Feature",
  "properties": {
    "tgn:hierarchy":[
        "tgn:2760540",
        "tgn:1000001",
        "tgn:7012149",
        "tgn:7007158",
        "tgn:7029392"
    ],
    "tgn:id":2760540,
    "tgn:name":"West Fork Turkey Creek",
    "tgn:placetype":[
        "aat:300008706"
    ]
},
  "bbox": [],
  "geometry": {"coordinates":[-104.9667,38.6667],"type":"Point"}
}
=======
{"geometry":{"type":"Point","coordinates":[-104.966700,38.666700]},"type":"Feature","properties":{"hierarchy":["tgn:2760540","tgn:1000001","tgn:7012149","tgn:7007158","tgn:7029392"],"placetype":["aat:300008706"],"id":2760540,"name:xx":"West Fork Turkey Creek"}}
>>>>>>> 03f74aca74312dbeaf24d7e61306dd6a786dc3d0
