{
  "id": 2760540,
  "type": "Feature",
  "properties": {
    "tgn:hierarchy":[
        "tgn:2760540",
        "tgn:1000001",
        "tgn:7012149",
        "tgn:7007158",
        "tgn:7029392"
    ],
    "tgn:id":2760540,
    "tgn:name":"West Fork Turkey Creek",
    "tgn:placetype":[
        "aat:300008706"
    ]
},
  "bbox": [],
  "geometry": {"coordinates":[-104.9667,38.6667],"type":"Point"}
}