{
  "id": 7293324,
  "type": "Feature",
  "properties": {
    "tgn:hierarchy":[
        "tgn:7293324",
        "tgn:7002806",
        "tgn:7001158",
        "tgn:1000003",
        "tgn:1000095",
        "tgn:7029392"
    ],
    "tgn:id":7293324,
    "tgn:name":"Vi\u00f1egra de Mora\u00f1a",
    "tgn:placetype":[
        "aat:300008347"
    ]
},
  "bbox": [],
  "geometry": {"coordinates":[-4.916667,40.85],"type":"Point"}
}