{
  "id": 2196779,
  "type": "Feature",
  "properties": {
    "tgn:hierarchy":[
        "tgn:2196779",
        "tgn:1000001",
        "tgn:7012149",
        "tgn:1002548",
        "tgn:7007919",
        "tgn:7029392"
    ],
    "tgn:id":2196779,
    "tgn:name":"Brooks Creek",
    "tgn:placetype":[
        "aat:300008706"
    ]
},
  "bbox": [],
  "geometry": {"coordinates":[-76.9333,37.6333],"type":"Point"}
}