<<<<<<< HEAD
{
  "id": 2159000,
  "type": "Feature",
  "properties": {
    "tgn:hierarchy":[
        "tgn:2159000",
        "tgn:7002659",
        "tgn:1000001",
        "tgn:7012149",
        "tgn:2000021",
        "tgn:7029392"
    ],
    "tgn:id":2159000,
    "tgn:name":"Beckworth Branch",
    "tgn:placetype":[
        "aat:300008699"
    ]
},
  "bbox": [],
  "geometry": {"coordinates":[-86.5833,34.2833],"type":"Point"}
}
=======
{"geometry":{"type":"Point","coordinates":[-86.583300,34.283300]},"type":"Feature","properties":{"hierarchy":["tgn:2159000","tgn:7002659","tgn:1000001","tgn:7012149","tgn:2000021","tgn:7029392"],"placetype":["aat:300008699"],"id":2159000,"name:xx":"Beckworth Branch"}}
>>>>>>> 03f74aca74312dbeaf24d7e61306dd6a786dc3d0
