{
  "id": 2754810,
  "type": "Feature",
  "properties": {
    "tgn:hierarchy":[
        "tgn:2754810",
        "tgn:7002659",
        "tgn:1000001",
        "tgn:7012149",
        "tgn:2000044",
        "tgn:7029392"
    ],
    "tgn:id":2754810,
    "tgn:name":"Weatherly Cove Branch",
    "tgn:placetype":[
        "aat:300008699"
    ]
},
  "bbox": [],
  "geometry": {"coordinates":[-86.5167,34.6333],"type":"Point"}
}