{
  "id": 2112754,
  "type": "Feature",
  "properties": {
    "tgn:hierarchy":[
        "tgn:2112754",
        "tgn:1000001",
        "tgn:7012149",
        "tgn:1002805",
        "tgn:7007919",
        "tgn:7029392"
    ],
    "tgn:id":2112754,
    "tgn:name":"Lower Brandon",
    "tgn:placetype":[
        "aat:300008347",
        "aat:300387210"
    ]
},
  "bbox": [],
  "geometry": {"coordinates":[-76.9667,37.25],"type":"Point"}
}