{
  "id": 7347617,
  "type": "Feature",
  "properties": {
    "tgn:hierarchy":[
        "tgn:7347617",
        "tgn:7002820",
        "tgn:7030216",
        "tgn:1000003",
        "tgn:1000095",
        "tgn:7029392"
    ],
    "tgn:id":7347617,
    "tgn:name":"Bas",
    "tgn:placetype":[
        "aat:300008347"
    ]
},
  "bbox": [],
  "geometry": {"coordinates":[2.45753,42.118452],"type":"Point"}
}