{
  "id": 2328313,
  "type": "Feature",
  "properties": {
    "tgn:hierarchy":[
        "tgn:2328313",
        "tgn:1000001",
        "tgn:2001267",
        "tgn:7012149",
        "tgn:7007524",
        "tgn:7029392"
    ],
    "tgn:id":2328313,
    "tgn:name":"Fisher Coulee",
    "tgn:placetype":[
        "aat:300008761"
    ]
},
  "bbox": [],
  "geometry": {"coordinates":[-110.5833,48.0833],"type":"Point"}
}