{
  "id": 7586969,
  "type": "Feature",
  "properties": {
    "tgn:hierarchy":[
        "tgn:7586969",
        "tgn:1000004",
        "tgn:7000198",
        "tgn:7000799",
        "tgn:7029392"
    ],
    "tgn:id":7586969,
    "tgn:name:en":"Shorbug",
    "tgn:placetype":[
        "aat:300008347"
    ]
},
  "bbox": [],
  "geometry": {"coordinates":[74.567487,34.224522],"type":"Point"}
}