{
  "id": 7006795,
  "type": "Feature",
  "properties": {
    "tgn:hierarchy":[
        "tgn:7006795",
        "tgn:7003139",
        "tgn:1000003",
        "tgn:7003080",
        "tgn:1000080",
        "tgn:7029392"
    ],
    "tgn:id":7006795,
    "tgn:name":"Oriolo Romano",
    "tgn:placetype":[
        "aat:300008347"
    ]
},
  "bbox": [],
  "geometry": {"coordinates":[12.133333,42.166667],"type":"Point"}
}