<<<<<<< HEAD
{
  "id": 7489241,
  "type": "Feature",
  "properties": {
    "tgn:hierarchy":[
        "tgn:7489241",
        "tgn:1000004",
        "tgn:7467799",
        "tgn:1000141",
        "tgn:7029392"
    ],
    "tgn:id":7489241,
    "tgn:name":"Kunlun Cun",
    "tgn:placetype":[
        "aat:300387173"
    ]
},
  "bbox": [],
  "geometry": {"coordinates":[120.4775,23.989167],"type":"Point"}
}
=======
{"geometry":{"type":"Point","coordinates":[120.477500,23.989167]},"type":"Feature","properties":{"hierarchy":["tgn:7489241","tgn:1000004","tgn:7467799","tgn:1000141","tgn:7029392"],"placetype":["aat:300387173"],"id":7489241,"name:xx":"Kunlun Cun"}}
>>>>>>> 03f74aca74312dbeaf24d7e61306dd6a786dc3d0
