{
  "id": 7132820,
  "type": "Feature",
  "properties": {
    "tgn:hierarchy":[
        "tgn:7132820",
        "tgn:7003669",
        "tgn:1000003",
        "tgn:7000084",
        "tgn:7029392"
    ],
    "tgn:id":7132820,
    "tgn:name":"Moggendorf",
    "tgn:placetype":[
        "aat:300008347"
    ]
},
  "bbox": [],
  "geometry": {"coordinates":[11.283333,49.916667],"type":"Point"}
}