{
  "id": 2646165,
  "type": "Feature",
  "properties": {
    "tgn:hierarchy":[
        "tgn:2646165",
        "tgn:1000001",
        "tgn:7012149",
        "tgn:7007157",
        "tgn:1002608",
        "tgn:7029392"
    ],
    "tgn:id":2646165,
    "tgn:name":"Sawpit Grounds",
    "tgn:placetype":[
        "aat:300055621"
    ]
},
  "bbox": [],
  "geometry": {"coordinates":[-117.9833,34.15],"type":"Point"}
}