{
  "id": 7039859,
  "type": "Feature",
  "properties": {
    "tgn:hierarchy":[
        "tgn:7039859",
        "tgn:7003129",
        "tgn:1000003",
        "tgn:7008516",
        "tgn:1000080",
        "tgn:7029392"
    ],
    "tgn:id":7039859,
    "tgn:name":"Selvapiana",
    "tgn:placetype":[
        "aat:300008347"
    ]
},
  "bbox": [],
  "geometry": {"coordinates":[12.033333,43.883333],"type":"Point"}
}