<<<<<<< HEAD
{
  "id": 2250668,
  "type": "Feature",
  "properties": {
    "tgn:hierarchy":[
        "tgn:2250668",
        "tgn:1000001",
        "tgn:7012149",
        "tgn:2001457",
        "tgn:7007566",
        "tgn:7029392"
    ],
    "tgn:id":2250668,
    "tgn:name":"Colorado, Cerrito",
    "tgn:placetype":[
        "aat:300008798"
    ]
},
  "bbox": [],
  "geometry": {"coordinates":[-105.4667,36.3333],"type":"Point"}
}
=======
{"geometry":{"type":"Point","coordinates":[-105.466700,36.333300]},"type":"Feature","properties":{"hierarchy":["tgn:2250668","tgn:1000001","tgn:7012149","tgn:2001457","tgn:7007566","tgn:7029392"],"placetype":["aat:300008798"],"id":2250668,"name:xx":"Colorado, Cerrito"}}
>>>>>>> 03f74aca74312dbeaf24d7e61306dd6a786dc3d0
