{
  "id": 1043622,
  "type": "Feature",
  "properties": {
    "tgn:hierarchy":[
        "tgn:1043622",
        "tgn:7003154",
        "tgn:1000003",
        "tgn:7003120",
        "tgn:1000080",
        "tgn:7029392"
    ],
    "tgn:id":1043622,
    "tgn:name":"Brandizzo",
    "tgn:placetype":[
        "aat:300008347"
    ]
},
  "bbox": [],
  "geometry": {"coordinates":[7.85,45.183333],"type":"Point"}
}