{
  "id": 2246235,
  "type": "Feature",
  "properties": {
    "tgn:hierarchy":[
        "tgn:2246235",
        "tgn:7002659",
        "tgn:1000001",
        "tgn:7012149",
        "tgn:2000058",
        "tgn:7029392"
    ],
    "tgn:id":2246235,
    "tgn:name":"Coalmont Mine",
    "tgn:placetype":[
        "aat:300000390"
    ]
},
  "bbox": [],
  "geometry": {"coordinates":[-86.8833,33.25],"type":"Point"}
}