{
  "id": 2775611,
  "type": "Feature",
  "properties": {
    "tgn:hierarchy":[
        "tgn:2775611",
        "tgn:1000001",
        "tgn:2001411",
        "tgn:7012149",
        "tgn:7007526",
        "tgn:7029392"
    ],
    "tgn:id":2775611,
    "tgn:name":"Wilson Creek Canyon",
    "tgn:placetype":[
        "aat:300008761"
    ]
},
  "bbox": [],
  "geometry": {"coordinates":[-116.2833,41.6833],"type":"Point"}
}