{
  "id": 7453634,
  "type": "Feature",
  "properties": {
    "tgn:hierarchy":[
        "tgn:7453634",
        "tgn:7019198",
        "tgn:7002448",
        "tgn:1000003",
        "tgn:7008591",
        "tgn:7029392"
    ],
    "tgn:id":7453634,
    "tgn:name:en":"The Diamond",
    "tgn:placetype":[
        "aat:300008347"
    ]
},
  "bbox": [],
  "geometry": {"coordinates":[-6.116667,54.383333],"type":"Point"}
}