{
  "id": 7085109,
  "type": "Feature",
  "properties": {
    "tgn:hierarchy":[
        "tgn:7085109",
        "tgn:1000003",
        "tgn:7003678",
        "tgn:7000084",
        "tgn:7029392"
    ],
    "tgn:id":7085109,
    "tgn:name":"Werker-Bach",
    "tgn:placetype":[
        "aat:300008699"
    ]
},
  "bbox": [],
  "geometry": {"coordinates":[7.866667,50.083333],"type":"Point"}
}