{
  "id": 7460834,
  "type": "Feature",
  "properties": {
    "tgn:hierarchy":[
        "tgn:7460834",
        "tgn:7002444",
        "tgn:1000003",
        "tgn:5000460",
        "tgn:7008591",
        "tgn:7029392"
    ],
    "tgn:id":7460834,
    "tgn:name:en":"Kepculloch",
    "tgn:placetype":[
        "aat:300008347"
    ]
},
  "bbox": [],
  "geometry": {"coordinates":[-4.35,56.083333],"type":"Point"}
}