{
  "id": 1007913,
  "type": "Feature",
  "properties": {
    "tgn:hierarchy":[
        "tgn:1007913",
        "tgn:7005685",
        "tgn:1000001",
        "tgn:1000296",
        "tgn:7029392"
    ],
    "tgn:id":1007913,
    "tgn:name":"Long Island",
    "tgn:placetype":[
        "aat:300008791"
    ]
},
  "bbox": [],
  "geometry": {"coordinates":[-79.3333,54.8333],"type":"Point"}
}