{
  "id": 2446618,
  "type": "Feature",
  "properties": {
    "tgn:hierarchy":[
        "tgn:2446618",
        "tgn:1000001",
        "tgn:2001410",
        "tgn:7012149",
        "tgn:7007526",
        "tgn:7029392"
    ],
    "tgn:id":2446618,
    "tgn:name":"Lewis Spring",
    "tgn:placetype":[
        "aat:300008697"
    ]
},
  "bbox": [],
  "geometry": {"coordinates":[-114.8833,35.2667],"type":"Point"}
}