{
  "id": 7505548,
  "type": "Feature",
  "properties": {
    "tgn:hierarchy":[
        "tgn:7505548",
        "tgn:1008380",
        "tgn:7000507",
        "tgn:1000226",
        "tgn:1000006",
        "tgn:7029392"
    ],
    "tgn:id":7505548,
    "tgn:name:en":"Wharehine",
    "tgn:placetype":[
        "aat:300008347"
    ]
},
  "bbox": [],
  "geometry": {"coordinates":[174.416667,-36.316667],"type":"Point"}
}