{
  "id": 7281285,
  "type": "Feature",
  "properties": {
    "tgn:hierarchy":[
        "tgn:7281285",
        "tgn:1001702",
        "tgn:1000049",
        "tgn:1000002",
        "tgn:7029392"
    ],
    "tgn:id":7281285,
    "tgn:name":"Se\u00f1alada, Punta",
    "tgn:placetype":[
        "aat:300386846"
    ]
},
  "bbox": [],
  "geometry": {"coordinates":[-68.366667,-54.916667],"type":"Point"}
}