{
  "id": 7146271,
  "type": "Feature",
  "properties": {
    "tgn:hierarchy":[
        "tgn:7146271",
        "tgn:1000003",
        "tgn:7000094",
        "tgn:7000084",
        "tgn:7029392"
    ],
    "tgn:id":7146271,
    "tgn:name":"Klein Siemz",
    "tgn:placetype":[
        "aat:300008347"
    ]
},
  "bbox": [],
  "geometry": {"coordinates":[10.916667,53.833333],"type":"Point"}
}