{
  "id": 7493714,
  "type": "Feature",
  "properties": {
    "tgn:hierarchy":[
        "tgn:7493714",
        "tgn:7468018",
        "tgn:1000004",
        "tgn:1000141",
        "tgn:7029392"
    ],
    "tgn:id":7493714,
    "tgn:name":"Toudong Shan",
    "tgn:placetype":[
        "aat:300008795"
    ]
},
  "bbox": [],
  "geometry": {"coordinates":[120.604934,23.395617],"type":"Point"}
}