{
  "id": 2073886,
  "type": "Feature",
  "properties": {
    "tgn:hierarchy":[
        "tgn:2073886",
        "tgn:1000001",
        "tgn:2001470",
        "tgn:7012149",
        "tgn:7007709",
        "tgn:7029392"
    ],
    "tgn:id":2073886,
    "tgn:name":"Buzzards Crossroads",
    "tgn:placetype":[
        "aat:300008347",
        "aat:300387210"
    ]
},
  "bbox": [],
  "geometry": {"coordinates":[-76.8833,36.15],"type":"Point"}
}