{
  "id": 2435337,
  "type": "Feature",
  "properties": {
    "tgn:hierarchy":[
        "tgn:2435337",
        "tgn:1000001",
        "tgn:7012149",
        "tgn:2002268",
        "tgn:7013961",
        "tgn:7029392"
    ],
    "tgn:id":2435337,
    "tgn:name":"Kera Lakes",
    "tgn:placetype":[
        "aat:300006191"
    ]
},
  "bbox": [],
  "geometry": {"coordinates":[-81.8167,38.9167],"type":"Point"}
}