<<<<<<< HEAD
{
  "id": 2767063,
  "type": "Feature",
  "properties": {
    "tgn:hierarchy":[
        "tgn:2767063",
        "tgn:1000001",
        "tgn:7012149",
        "tgn:7007157",
        "tgn:1002867",
        "tgn:7029392"
    ],
    "tgn:id":2767063,
    "tgn:name":"White Rock",
    "tgn:placetype":[
        "aat:300008791"
    ]
},
  "bbox": [],
  "geometry": {"coordinates":[-119.7167,33.95],"type":"Point"}
}
=======
{"geometry":{"type":"Point","coordinates":[-119.716700,33.950000]},"type":"Feature","properties":{"hierarchy":["tgn:2767063","tgn:1000001","tgn:7012149","tgn:7007157","tgn:1002867","tgn:7029392"],"placetype":["aat:300008791"],"id":2767063,"name:xx":"White Rock"}}
>>>>>>> 03f74aca74312dbeaf24d7e61306dd6a786dc3d0
