{
  "id": 2767063,
  "type": "Feature",
  "properties": {
    "tgn:hierarchy":[
        "tgn:2767063",
        "tgn:1000001",
        "tgn:7012149",
        "tgn:7007157",
        "tgn:1002867",
        "tgn:7029392"
    ],
    "tgn:id":2767063,
    "tgn:name":"White Rock",
    "tgn:placetype":[
        "aat:300008791"
    ]
},
  "bbox": [],
  "geometry": {"coordinates":[-119.7167,33.95],"type":"Point"}
}