{
  "id": 7503342,
  "type": "Feature",
  "properties": {
    "tgn:hierarchy":[
        "tgn:7503342",
        "tgn:1000004",
        "tgn:7471332",
        "tgn:1000141",
        "tgn:7029392"
    ],
    "tgn:id":7503342,
    "tgn:name":"Bunujiali Shan",
    "tgn:placetype":[
        "aat:300008798"
    ]
},
  "bbox": [],
  "geometry": {"coordinates":[121.243889,24.550833],"type":"Point"}
}