<<<<<<< HEAD
{
  "id": 7371574,
  "type": "Feature",
  "properties": {
    "tgn:hierarchy":[
        "tgn:7371574",
        "tgn:1000001",
        "tgn:7005597",
        "tgn:7005560",
        "tgn:7029392"
    ],
    "tgn:id":7371574,
    "tgn:name":"La Mora",
    "tgn:placetype":[
        "aat:300008347"
    ]
},
  "bbox": [],
  "geometry": {"coordinates":[-98.883333,22.783333],"type":"Point"}
}
=======
{"geometry":{"type":"Point","coordinates":[-98.883333,22.783333]},"type":"Feature","properties":{"hierarchy":["tgn:7371574","tgn:1000001","tgn:7005597","tgn:7005560","tgn:7029392"],"placetype":["aat:300008347"],"id":7371574,"name:xx":"La Mora"}}
>>>>>>> 03f74aca74312dbeaf24d7e61306dd6a786dc3d0
