<<<<<<< HEAD
{
  "id": 2763615,
  "type": "Feature",
  "properties": {
    "tgn:hierarchy":[
        "tgn:2763615",
        "tgn:1000001",
        "tgn:1002714",
        "tgn:7012149",
        "tgn:7007159",
        "tgn:7029392"
    ],
    "tgn:id":2763615,
    "tgn:name":"Whaleback Rock",
    "tgn:placetype":[
        "aat:300008791"
    ]
},
  "bbox": [],
  "geometry": {"coordinates":[-71.9833,41.3],"type":"Point"}
}
=======
{"geometry":{"type":"Point","coordinates":[-71.983300,41.300000]},"type":"Feature","properties":{"hierarchy":["tgn:2763615","tgn:1000001","tgn:1002714","tgn:7012149","tgn:7007159","tgn:7029392"],"placetype":["aat:300008791"],"id":2763615,"name:xx":"Whaleback Rock"}}
>>>>>>> 03f74aca74312dbeaf24d7e61306dd6a786dc3d0
