{
  "id": 2782077,
  "type": "Feature",
  "properties": {
    "tgn:hierarchy":[
        "tgn:2782077",
        "tgn:1000001",
        "tgn:7012149",
        "tgn:7021313",
        "tgn:7007521",
        "tgn:7029392"
    ],
    "tgn:id":2782077,
    "tgn:name":"Woods, Lake ff the",
    "tgn:placetype":[
        "aat:300008680"
    ]
},
  "bbox": [],
  "geometry": {"coordinates":[-94.75,49.25],"type":"Point"}
}