{
  "id": 7548371,
  "type": "Feature",
  "properties": {
    "tgn:hierarchy":[
        "tgn:7548371",
        "tgn:1000004",
        "tgn:7000198",
        "tgn:7016722",
        "tgn:7029392"
    ],
    "tgn:id":7548371,
    "tgn:name:en":"Brahm\u0101vart",
    "tgn:placetype":[
        "aat:300007783"
    ]
},
  "bbox": [],
  "geometry": {"coordinates":[80.27323,26.603644],"type":"Point"}
}