{
  "id": 1130015,
  "type": "Feature",
  "properties": {
    "tgn:hierarchy":[
        "tgn:1130015",
        "tgn:7005735",
        "tgn:7005685",
        "tgn:1000001",
        "tgn:7029392"
    ],
    "tgn:id":1130015,
    "tgn:name":"Sikanni Chief River",
    "tgn:placetype":[
        "aat:300008707"
    ]
},
  "bbox": [],
  "geometry": {"coordinates":[-121.8333,58.3333],"type":"Point"}
}