{
  "id": 7395697,
  "type": "Feature",
  "properties": {
    "tgn:hierarchy":[
        "tgn:7395697",
        "tgn:1000001",
        "tgn:7005600",
        "tgn:7005560",
        "tgn:7029392"
    ],
    "tgn:id":7395697,
    "tgn:name":"San Juan",
    "tgn:placetype":[
        "aat:300008347"
    ]
},
  "bbox": [],
  "geometry": {"coordinates":[-88.816667,20.216667],"type":"Point"}
}