{
  "id": 2323036,
  "type": "Feature",
  "properties": {
    "tgn:hierarchy":[
        "tgn:2323036",
        "tgn:1000001",
        "tgn:7016172",
        "tgn:2000112",
        "tgn:7012149",
        "tgn:7029392"
    ],
    "tgn:id":2323036,
    "tgn:name":"Farewell",
    "tgn:placetype":[
        "aat:300008347"
    ]
},
  "bbox": [],
  "geometry": {"coordinates":[-93.3667,36.3833],"type":"Point"}
}