{
  "id": 7346683,
  "type": "Feature",
  "properties": {
    "tgn:hierarchy":[
        "tgn:7346683",
        "tgn:7008912",
        "tgn:7030216",
        "tgn:1000003",
        "tgn:1000095",
        "tgn:7029392"
    ],
    "tgn:id":7346683,
    "tgn:name":"Belianes",
    "tgn:placetype":[
        "aat:300008347"
    ]
},
  "bbox": [],
  "geometry": {"coordinates":[1.016022,41.560246],"type":"Point"}
}