{
  "id": 7533757,
  "type": "Feature",
  "properties": {
    "tgn:hierarchy":[
        "tgn:7533757",
        "tgn:7001242",
        "tgn:7016833",
        "tgn:1001418",
        "tgn:7029392"
    ],
    "tgn:id":7533757,
    "tgn:name:en":"Madwar, Gebel el",
    "tgn:placetype":[
        "aat:300008777"
    ]
},
  "bbox": [],
  "geometry": {"coordinates":[27.142356,31.302645],"type":"Point"}
}