{
  "id": 2569666,
  "type": "Feature",
  "properties": {
    "tgn:hierarchy":[
        "tgn:2569666",
        "tgn:1000001",
        "tgn:7012149",
        "tgn:2002124",
        "tgn:7007827",
        "tgn:7029392"
    ],
    "tgn:id":2569666,
    "tgn:name":"Parson City Spring",
    "tgn:placetype":[
        "aat:300008697"
    ]
},
  "bbox": [],
  "geometry": {"coordinates":[-109.55,40.7167],"type":"Point"}
}