{
  "id": 2703601,
  "type": "Feature",
  "properties": {
    "tgn:hierarchy":[
        "tgn:2703601",
        "tgn:1000001",
        "tgn:7012149",
        "tgn:2001718",
        "tgn:7007708",
        "tgn:7029392"
    ],
    "tgn:id":2703601,
    "tgn:name":"Summit Spring",
    "tgn:placetype":[
        "aat:300008697"
    ]
},
  "bbox": [],
  "geometry": {"coordinates":[-117.8333,42.2833],"type":"Point"}
}