{
  "id": 7370075,
  "type": "Feature",
  "properties": {
    "tgn:hierarchy":[
        "tgn:7370075",
        "tgn:7005580",
        "tgn:1000001",
        "tgn:7005560",
        "tgn:7029392"
    ],
    "tgn:id":7370075,
    "tgn:name":"Guapinol",
    "tgn:placetype":[
        "aat:300008347"
    ]
},
  "bbox": [],
  "geometry": {"coordinates":[-92.583333,15.35],"type":"Point"}
}