{
  "id": 7340866,
  "type": "Feature",
  "properties": {
    "tgn:hierarchy":[
        "tgn:7340866",
        "tgn:7002760",
        "tgn:1000003",
        "tgn:1000095",
        "tgn:7029392"
    ],
    "tgn:id":7340866,
    "tgn:name":"Bustido\u00f1o",
    "tgn:placetype":[
        "aat:300008347"
    ]
},
  "bbox": [],
  "geometry": {"coordinates":[-3.983333,42.916667],"type":"Point"}
}