{
  "id": 7514400,
  "type": "Feature",
  "properties": {
    "tgn:hierarchy":[
        "tgn:7514400",
        "tgn:1009227",
        "tgn:1000226",
        "tgn:1000006",
        "tgn:7016850",
        "tgn:7029392"
    ],
    "tgn:id":7514400,
    "tgn:name:en":"Doughboy, The",
    "tgn:placetype":[
        "aat:300008795"
    ]
},
  "bbox": [],
  "geometry": {"coordinates":[171.066667,-42.916667],"type":"Point"}
}