{
  "id": 7086080,
  "type": "Feature",
  "properties": {
    "tgn:hierarchy":[
        "tgn:7086080",
        "tgn:7003692",
        "tgn:1000003",
        "tgn:7000084",
        "tgn:7029392"
    ],
    "tgn:id":7086080,
    "tgn:name":"Waldstetter Bach",
    "tgn:placetype":[
        "aat:300008699"
    ]
},
  "bbox": [],
  "geometry": {"coordinates":[9.816667,48.783333],"type":"Point"}
}