<<<<<<< HEAD
{
  "id": 2338095,
  "type": "Feature",
  "properties": {
    "tgn:hierarchy":[
        "tgn:2338095",
        "tgn:1000001",
        "tgn:7012149",
        "tgn:2002359",
        "tgn:7007922",
        "tgn:7029392"
    ],
    "tgn:id":2338095,
    "tgn:name":"Fox Lake",
    "tgn:placetype":[
        "aat:300008680"
    ]
},
  "bbox": [],
  "geometry": {"coordinates":[-89.9,46.2667],"type":"Point"}
}
=======
{"geometry":{"type":"Point","coordinates":[-89.900000,46.266700]},"type":"Feature","properties":{"hierarchy":["tgn:2338095","tgn:1000001","tgn:7012149","tgn:2002359","tgn:7007922","tgn:7029392"],"placetype":["aat:300008680"],"id":2338095,"name:xx":"Fox Lake"}}
>>>>>>> 03f74aca74312dbeaf24d7e61306dd6a786dc3d0
