{
  "id": 7243977,
  "type": "Feature",
  "properties": {
    "tgn:hierarchy":[
        "tgn:7243977",
        "tgn:7003460",
        "tgn:1000003",
        "tgn:1000063",
        "tgn:4012014",
        "tgn:7029392"
    ],
    "tgn:id":7243977,
    "tgn:name":"Jeneffe",
    "tgn:placetype":[
        "aat:300008347"
    ]
},
  "bbox": [],
  "geometry": {"coordinates":[5.357174,50.655036],"type":"Point"}
}