{
  "id": 2614001,
  "type": "Feature",
  "properties": {
    "tgn:hierarchy":[
        "tgn:2614001",
        "tgn:1000001",
        "tgn:7012149",
        "tgn:2000852",
        "tgn:7007255",
        "tgn:7029392"
    ],
    "tgn:id":2614001,
    "tgn:name":"Reese Creek",
    "tgn:placetype":[
        "aat:300008706"
    ]
},
  "bbox": [],
  "geometry": {"coordinates":[-84.0667,36.7667],"type":"Point"}
}