{
  "id": 2030279,
  "type": "Feature",
  "properties": {
    "tgn:hierarchy":[
        "tgn:2030279",
        "tgn:1000001",
        "tgn:7012149",
        "tgn:1002430",
        "tgn:7007251",
        "tgn:7029392"
    ],
    "tgn:id":2030279,
    "tgn:name":"Stockdale",
    "tgn:placetype":[
        "aat:300387016"
    ]
},
  "bbox": [],
  "geometry": {"coordinates":[-88.4833,41.35],"type":"Point"}
}