{
  "id": 2467905,
  "type": "Feature",
  "properties": {
    "tgn:hierarchy":[
        "tgn:2467905",
        "tgn:1000001",
        "tgn:2000866",
        "tgn:7012149",
        "tgn:7007256",
        "tgn:7029392"
    ],
    "tgn:id":2467905,
    "tgn:name":"Long Lake",
    "tgn:placetype":[
        "aat:300008680"
    ]
},
  "bbox": [],
  "geometry": {"coordinates":[-91.9333,31.6333],"type":"Point"}
}