{
  "id": 7510578,
  "type": "Feature",
  "properties": {
    "tgn:hierarchy":[
        "tgn:7510578",
        "tgn:1008380",
        "tgn:7000507",
        "tgn:1000226",
        "tgn:1000006",
        "tgn:7029392"
    ],
    "tgn:id":7510578,
    "tgn:name:en":"Umawera",
    "tgn:placetype":[
        "aat:300008347"
    ]
},
  "bbox": [],
  "geometry": {"coordinates":[173.583333,-35.283333],"type":"Point"}
}