{
  "id": 7468102,
  "type": "Feature",
  "properties": {
    "tgn:hierarchy":[
        "tgn:7468102",
        "tgn:7001010",
        "tgn:1000004",
        "tgn:1000141",
        "tgn:7029392"
    ],
    "tgn:id":7468102,
    "tgn:name":"Jialulan Shan",
    "tgn:placetype":[
        "aat:300008798"
    ]
},
  "bbox": [],
  "geometry": {"coordinates":[121.523611,23.68],"type":"Point"}
}