{
  "id": 2124697,
  "type": "Feature",
  "properties": {
    "tgn:hierarchy":[
        "tgn:2124697",
        "tgn:1000001",
        "tgn:7012149",
        "tgn:2001156",
        "tgn:7007522",
        "tgn:7029392"
    ],
    "tgn:id":2124697,
    "tgn:name":"Abe Branch",
    "tgn:placetype":[
        "aat:300008699"
    ]
},
  "bbox": [],
  "geometry": {"coordinates":[-88.15,34.7167],"type":"Point"}
}