<<<<<<< HEAD
{
  "id": 2400799,
  "type": "Feature",
  "properties": {
    "tgn:hierarchy":[
        "tgn:2400799",
        "tgn:1000001",
        "tgn:2000274",
        "tgn:7012149",
        "tgn:7007240",
        "tgn:7029392"
    ],
    "tgn:id":2400799,
    "tgn:name":"Horse Pond",
    "tgn:placetype":[
        "aat:300008680"
    ]
},
  "bbox": [],
  "geometry": {"coordinates":[-83.7333,30.6167],"type":"Point"}
}
=======
{"geometry":{"type":"Point","coordinates":[-83.733300,30.616700]},"type":"Feature","properties":{"hierarchy":["tgn:2400799","tgn:1000001","tgn:2000274","tgn:7012149","tgn:7007240","tgn:7029392"],"placetype":["aat:300008680"],"id":2400799,"name:xx":"Horse Pond"}}
>>>>>>> 03f74aca74312dbeaf24d7e61306dd6a786dc3d0
