{
  "id": 2400799,
  "type": "Feature",
  "properties": {
    "tgn:hierarchy":[
        "tgn:2400799",
        "tgn:1000001",
        "tgn:2000274",
        "tgn:7012149",
        "tgn:7007240",
        "tgn:7029392"
    ],
    "tgn:id":2400799,
    "tgn:name":"Horse Pond",
    "tgn:placetype":[
        "aat:300008680"
    ]
},
  "bbox": [],
  "geometry": {"coordinates":[-83.7333,30.6167],"type":"Point"}
}