{
  "id": 2533273,
  "type": "Feature",
  "properties": {
    "tgn:hierarchy":[
        "tgn:2533273",
        "tgn:1002309",
        "tgn:1000001",
        "tgn:7012149",
        "tgn:7007565",
        "tgn:7029392"
    ],
    "tgn:id":2533273,
    "tgn:name":"Muskee Creek",
    "tgn:placetype":[
        "aat:300008706"
    ]
},
  "bbox": [],
  "geometry": {"coordinates":[-74.9167,39.3167],"type":"Point"}
}