{
  "id": 1061467,
  "type": "Feature",
  "properties": {
    "tgn:hierarchy":[
        "tgn:1061467",
        "tgn:7012256",
        "tgn:1000004",
        "tgn:7006661",
        "tgn:7029392"
    ],
    "tgn:id":1061467,
    "tgn:name":"Zaamin",
    "tgn:placetype":[
        "aat:300008347"
    ]
},
  "bbox": [],
  "geometry": {"coordinates":[68.4167,39.9333],"type":"Point"}
}