{
  "id": 2695675,
  "type": "Feature",
  "properties": {
    "tgn:hierarchy":[
        "tgn:2695675",
        "tgn:1000001",
        "tgn:2000458",
        "tgn:7012149",
        "tgn:7007250",
        "tgn:7029392"
    ],
    "tgn:id":2695675,
    "tgn:name":"Stinson Canyon",
    "tgn:placetype":[
        "aat:300008761"
    ]
},
  "bbox": [],
  "geometry": {"coordinates":[-113.85,43.4333],"type":"Point"}
}