{
  "id": 1070234,
  "type": "Feature",
  "properties": {
    "tgn:hierarchy":[
        "tgn:1070234",
        "tgn:1000004",
        "tgn:7002076",
        "tgn:1000111",
        "tgn:7029392"
    ],
    "tgn:id":1070234,
    "tgn:name":"Luqiaozhen",
    "tgn:placetype":[
        "aat:300008347"
    ]
},
  "bbox": [],
  "geometry": {"coordinates":[121.3833,28.5833],"type":"Point"}
}