{
  "id": 2041360,
  "type": "Feature",
  "properties": {
    "tgn:hierarchy":[
        "tgn:2041360",
        "tgn:1000001",
        "tgn:7012149",
        "tgn:2000796",
        "tgn:7007255",
        "tgn:7029392"
    ],
    "tgn:id":2041360,
    "tgn:name":"Sonora",
    "tgn:placetype":[
        "aat:300008347"
    ]
},
  "bbox": [],
  "geometry": {"coordinates":[-85.8833,37.5167],"type":"Point"}
}