<<<<<<< HEAD
{
  "id": 7053501,
  "type": "Feature",
  "properties": {
    "tgn:hierarchy":[
        "tgn:7053501",
        "tgn:7015163",
        "tgn:1000003",
        "tgn:7003121",
        "tgn:1000080",
        "tgn:7029392"
    ],
    "tgn:id":7053501,
    "tgn:name":"Papa, Punta del",
    "tgn:placetype":[
        "aat:300386846"
    ]
},
  "bbox": [],
  "geometry": {"coordinates":[9.733333,40.916667],"type":"Point"}
}
=======
{"geometry":{"type":"Point","coordinates":[9.733333,40.916667]},"type":"Feature","properties":{"hierarchy":["tgn:7053501","tgn:7015163","tgn:1000003","tgn:7003121","tgn:1000080","tgn:7029392"],"placetype":["aat:300386846"],"id":7053501,"name:xx":"Papa, Punta del"}}
>>>>>>> 03f74aca74312dbeaf24d7e61306dd6a786dc3d0
