{
  "id": 7386246,
  "type": "Feature",
  "properties": {
    "tgn:hierarchy":[
        "tgn:7386246",
        "tgn:1000001",
        "tgn:7005590",
        "tgn:7005560",
        "tgn:7029392"
    ],
    "tgn:id":7386246,
    "tgn:name":"Estaci\u00f3n Raliz\u00e1val",
    "tgn:placetype":[
        "aat:300007783"
    ]
},
  "bbox": [],
  "geometry": {"coordinates":[-102.05,19.083333],"type":"Point"}
}