{
  "id": 2493429,
  "type": "Feature",
  "properties": {
    "tgn:hierarchy":[
        "tgn:2493429",
        "tgn:1000001",
        "tgn:7012149",
        "tgn:2002166",
        "tgn:7007919",
        "tgn:7029392"
    ],
    "tgn:id":2493429,
    "tgn:name":"Marsailles",
    "tgn:placetype":[
        "aat:300008347"
    ]
},
  "bbox": [],
  "geometry": {"coordinates":[-78.9833,36.6667],"type":"Point"}
}