{
  "id": 7267866,
  "type": "Feature",
  "properties": {
    "tgn:hierarchy":[
        "tgn:7267866",
        "tgn:7003616",
        "tgn:1000003",
        "tgn:7016845",
        "tgn:7029392"
    ],
    "tgn:id":7267866,
    "tgn:name:nl":"Rijpwegsend, Polder",
    "tgn:placetype":[
        "aat:300006163"
    ]
},
  "bbox": [],
  "geometry": {"coordinates":[5.933333,53.066667],"type":"Point"}
}