<<<<<<< HEAD
{
  "id": 7028214,
  "type": "Feature",
  "properties": {
    "tgn:hierarchy":[
        "tgn:7028214",
        "tgn:7002445",
        "tgn:1000003",
        "tgn:7019054",
        "tgn:7008591",
        "tgn:7029392"
    ],
    "tgn:id":7028214,
    "tgn:name:en":"Whitton",
    "tgn:placetype":[
        "aat:300008347",
        "aat:300008372"
    ]
},
  "bbox": [],
  "geometry": {"coordinates":[-0.633333,53.7],"type":"Point"}
}
=======
{"geometry":{"type":"Point","coordinates":[-0.633333,53.700000]},"type":"Feature","properties":{"hierarchy":["tgn:7028214","tgn:7002445","tgn:1000003","tgn:7019054","tgn:7008591","tgn:7029392"],"placetype":["aat:300008347","aat:300008372"],"name:en":"Whitton","id":7028214}}
>>>>>>> 03f74aca74312dbeaf24d7e61306dd6a786dc3d0
