{
  "id": 1114158,
  "type": "Feature",
  "properties": {
    "tgn:hierarchy":[
        "tgn:1114158",
        "tgn:7017308",
        "tgn:1000003",
        "tgn:7006663",
        "tgn:7029392"
    ],
    "tgn:id":1114158,
    "tgn:name":"Hvarski Kanal",
    "tgn:placetype":[
        "aat:300008713"
    ]
},
  "bbox": [],
  "geometry": {"coordinates":[16.6333,43.25],"type":"Point"}
}