{
  "id": 2510055,
  "type": "Feature",
  "properties": {
    "tgn:hierarchy":[
        "tgn:2510055",
        "tgn:1000001",
        "tgn:7012149",
        "tgn:7007923",
        "tgn:7029392"
    ],
    "tgn:id":2510055,
    "tgn:name":"Middle Piney Lake",
    "tgn:placetype":[
        "aat:300008680"
    ]
},
  "bbox": [],
  "geometry": {"coordinates":[-110.5667,42.5833],"type":"Point"}
}