{
  "id": 1013953,
  "type": "Feature",
  "properties": {
    "tgn:hierarchy":[
        "tgn:1013953",
        "tgn:7005685",
        "tgn:1000001",
        "tgn:7005734",
        "tgn:7029392"
    ],
    "tgn:id":1013953,
    "tgn:name":"Minitonas",
    "tgn:placetype":[
        "aat:300008347"
    ]
},
  "bbox": [],
  "geometry": {"coordinates":[-101.0333,52.0667],"type":"Point"}
}