{
  "id": 7005295,
  "type": "Feature",
  "properties": {
    "tgn:hierarchy":[
        "tgn:7005295",
        "tgn:1000003",
        "tgn:7003678",
        "tgn:7000084",
        "tgn:7029392"
    ],
    "tgn:id":7005295,
    "tgn:name":"Hanau",
    "tgn:placetype":[
        "aat:300008347",
        "aat:300000835",
        "aat:300008389",
        "aat:300387308",
        "aat:300005135",
        "aat:300120599"
    ]
},
  "bbox": [],
  "geometry": {"coordinates":[8.916667,50.133333],"type":"Point"}
}