<<<<<<< HEAD
{
  "id": 2767041,
  "type": "Feature",
  "properties": {
    "tgn:hierarchy":[
        "tgn:2767041",
        "tgn:1000001",
        "tgn:7012149",
        "tgn:7007158",
        "tgn:7029392"
    ],
    "tgn:id":2767041,
    "tgn:name":"White River National Forest",
    "tgn:placetype":[
        "aat:300008863"
    ]
},
  "bbox": [],
  "geometry": {"coordinates":[-106.8,39.4333],"type":"Point"}
}
=======
{"geometry":{"type":"Point","coordinates":[-106.800000,39.433300]},"type":"Feature","properties":{"hierarchy":["tgn:2767041","tgn:1000001","tgn:7012149","tgn:7007158","tgn:7029392"],"placetype":["aat:300008863"],"id":2767041,"name:xx":"White River National Forest"}}
>>>>>>> 03f74aca74312dbeaf24d7e61306dd6a786dc3d0
