{
  "id": 7418876,
  "type": "Feature",
  "properties": {
    "tgn:hierarchy":[
        "tgn:7418876",
        "tgn:7005584",
        "tgn:1000001",
        "tgn:7005560",
        "tgn:7029392"
    ],
    "tgn:id":7418876,
    "tgn:name":"La Merced",
    "tgn:placetype":[
        "aat:300008347"
    ]
},
  "bbox": [],
  "geometry": {"coordinates":[-100.4375,21.195833],"type":"Point"}
}