{
  "id": 7473677,
  "type": "Feature",
  "properties": {
    "tgn:hierarchy":[
        "tgn:7473677",
        "tgn:7001004",
        "tgn:1000004",
        "tgn:1000141",
        "tgn:7029392"
    ],
    "tgn:id":7473677,
    "tgn:name":"Yinghou",
    "tgn:placetype":[
        "aat:300008347"
    ]
},
  "bbox": [],
  "geometry": {"coordinates":[120.27,22.889167],"type":"Point"}
}