{
  "id": 7575840,
  "type": "Feature",
  "properties": {
    "tgn:hierarchy":[
        "tgn:7575840",
        "tgn:1000004",
        "tgn:7031781",
        "tgn:7000198",
        "tgn:7029392"
    ],
    "tgn:id":7575840,
    "tgn:name:en":"Konrra",
    "tgn:placetype":[
        "aat:300008347"
    ]
},
  "bbox": [],
  "geometry": {"coordinates":[84.341026,22.804627],"type":"Point"}
}