{
  "id": 7531247,
  "type": "Feature",
  "properties": {
    "tgn:hierarchy":[
        "tgn:7531247",
        "tgn:7001242",
        "tgn:7016833",
        "tgn:1001091",
        "tgn:7029392"
    ],
    "tgn:id":7531247,
    "tgn:name":"Markaz Amr\u0101\u1e11 a\u015f \u015eadr al Qalb",
    "tgn:placetype":[
        "aat:300006653"
    ]
},
  "bbox": [],
  "geometry": {"coordinates":[31.254247,30.077771],"type":"Point"}
}