{
  "id": 7452746,
  "type": "Feature",
  "properties": {
    "tgn:hierarchy":[
        "tgn:7452746",
        "tgn:7002445",
        "tgn:1000003",
        "tgn:7008157",
        "tgn:7008591",
        "tgn:7029392"
    ],
    "tgn:id":7452746,
    "tgn:name:en":"Harrington",
    "tgn:placetype":[
        "aat:300008347"
    ]
},
  "bbox": [],
  "geometry": {"coordinates":[0.05,53.216667],"type":"Point"}
}