{
  "id": 7390946,
  "type": "Feature",
  "properties": {
    "tgn:hierarchy":[
        "tgn:7390946",
        "tgn:1000001",
        "tgn:7005589",
        "tgn:7005560",
        "tgn:7029392"
    ],
    "tgn:id":7390946,
    "tgn:name":"Rancho San Luis",
    "tgn:placetype":[
        "aat:300008347"
    ]
},
  "bbox": [],
  "geometry": {"coordinates":[-99.783333,26.883333],"type":"Point"}
}