{
  "id": 7586355,
  "type": "Feature",
  "properties": {
    "tgn:hierarchy":[
        "tgn:7586355",
        "tgn:1000004",
        "tgn:7000198",
        "tgn:1001977",
        "tgn:7029392"
    ],
    "tgn:id":7586355,
    "tgn:name:en":"B\u0101nspul",
    "tgn:placetype":[
        "aat:300008347"
    ]
},
  "bbox": [],
  "geometry": {"coordinates":[88.488333,22.670833],"type":"Point"}
}