{
  "id": 2539885,
  "type": "Feature",
  "properties": {
    "tgn:hierarchy":[
        "tgn:2539885",
        "tgn:1000001",
        "tgn:7012149",
        "tgn:2000225",
        "tgn:7007158",
        "tgn:7029392"
    ],
    "tgn:id":2539885,
    "tgn:name":"New York Creek",
    "tgn:placetype":[
        "aat:300008706"
    ]
},
  "bbox": [],
  "geometry": {"coordinates":[-107.6333,37.6167],"type":"Point"}
}