{
  "id": 7346641,
  "type": "Feature",
  "properties": {
    "tgn:hierarchy":[
        "tgn:7346641",
        "tgn:7002759",
        "tgn:7002843",
        "tgn:1000003",
        "tgn:1000095",
        "tgn:7029392"
    ],
    "tgn:id":7346641,
    "tgn:name":"Argente",
    "tgn:placetype":[
        "aat:300008347"
    ]
},
  "bbox": [],
  "geometry": {"coordinates":[-1.166667,40.683333],"type":"Point"}
}