<<<<<<< HEAD
{
  "id": 7477151,
  "type": "Feature",
  "properties": {
    "tgn:hierarchy":[
        "tgn:7477151",
        "tgn:1000004",
        "tgn:7001013",
        "tgn:1000141",
        "tgn:7029392"
    ],
    "tgn:id":7477151,
    "tgn:name":"Shalun Guoxiao",
    "tgn:placetype":[
        "aat:300006495"
    ]
},
  "bbox": [],
  "geometry": {"coordinates":[121.222799,25.093025],"type":"Point"}
}
=======
{"geometry":{"type":"Point","coordinates":[121.222799,25.093025]},"type":"Feature","properties":{"hierarchy":["tgn:7477151","tgn:1000004","tgn:7001013","tgn:1000141","tgn:7029392"],"placetype":["aat:300006495"],"id":7477151,"name:xx":"Shalun Guoxiao"}}
>>>>>>> 03f74aca74312dbeaf24d7e61306dd6a786dc3d0
