{
  "id": 2202160,
  "type": "Feature",
  "properties": {
    "tgn:hierarchy":[
        "tgn:2202160",
        "tgn:1000001",
        "tgn:2001091",
        "tgn:7012149",
        "tgn:7007522",
        "tgn:7029392"
    ],
    "tgn:id":2202160,
    "tgn:name":"Buck Lake",
    "tgn:placetype":[
        "aat:300008680"
    ]
},
  "bbox": [],
  "geometry": {"coordinates":[-90.7833,34.0833],"type":"Point"}
}