<<<<<<< HEAD
{
  "id": 2151581,
  "type": "Feature",
  "properties": {
    "tgn:hierarchy":[
        "tgn:2151581",
        "tgn:1000001",
        "tgn:7012149",
        "tgn:2000180",
        "tgn:7007157",
        "tgn:7029392"
    ],
    "tgn:id":2151581,
    "tgn:name":"Battery Point",
    "tgn:placetype":[
        "aat:300008850"
    ]
},
  "bbox": [],
  "geometry": {"coordinates":[-124.2,41.7333],"type":"Point"}
}
=======
{"geometry":{"type":"Point","coordinates":[-124.200000,41.733300]},"type":"Feature","properties":{"hierarchy":["tgn:2151581","tgn:1000001","tgn:7012149","tgn:2000180","tgn:7007157","tgn:7029392"],"placetype":["aat:300008850"],"id":2151581,"name:xx":"Battery Point"}}
>>>>>>> 03f74aca74312dbeaf24d7e61306dd6a786dc3d0
