<<<<<<< HEAD
{
  "id": 7176904,
  "type": "Feature",
  "properties": {
    "tgn:hierarchy":[
        "tgn:7176904",
        "tgn:1000003",
        "tgn:7003676",
        "tgn:7000084",
        "tgn:7029392"
    ],
    "tgn:id":7176904,
    "tgn:name":"Halle",
    "tgn:placetype":[
        "aat:300000206"
    ]
},
  "bbox": [],
  "geometry": {"coordinates":[8.233333,52.233333],"type":"Point"}
}
=======
{"geometry":{"type":"Point","coordinates":[8.233333,52.233333]},"type":"Feature","properties":{"hierarchy":["tgn:7176904","tgn:1000003","tgn:7003676","tgn:7000084","tgn:7029392"],"placetype":["aat:300000206"],"id":7176904,"name:xx":"Halle"}}
>>>>>>> 03f74aca74312dbeaf24d7e61306dd6a786dc3d0
