{
  "id": 2295915,
  "type": "Feature",
  "properties": {
    "tgn:hierarchy":[
        "tgn:2295915",
        "tgn:1000001",
        "tgn:2001260",
        "tgn:7012149",
        "tgn:7007524",
        "tgn:7029392"
    ],
    "tgn:id":2295915,
    "tgn:name":"Drummy Ditch Number Two",
    "tgn:placetype":[
        "aat:300006075"
    ]
},
  "bbox": [],
  "geometry": {"coordinates":[-112.5667,45.3167],"type":"Point"}
}