{
  "id": 2202457,
  "type": "Feature",
  "properties": {
    "tgn:hierarchy":[
        "tgn:2202457",
        "tgn:1000001",
        "tgn:7012149",
        "tgn:2001506",
        "tgn:7007709",
        "tgn:7029392"
    ],
    "tgn:id":2202457,
    "tgn:name":"Buck Ridge",
    "tgn:placetype":[
        "aat:300266640"
    ]
},
  "bbox": [],
  "geometry": {"coordinates":[-76.2833,35.4333],"type":"Point"}
}