{
  "id": 7158123,
  "type": "Feature",
  "properties": {
    "tgn:hierarchy":[
        "tgn:7158123",
        "tgn:1000003",
        "tgn:7003685",
        "tgn:7000084",
        "tgn:7029392"
    ],
    "tgn:id":7158123,
    "tgn:name":"Kleiner Brand-Berg",
    "tgn:placetype":[
        "aat:300008777"
    ]
},
  "bbox": [],
  "geometry": {"coordinates":[12.666667,51.25],"type":"Point"}
}