{
  "id": 7563281,
  "type": "Feature",
  "properties": {
    "tgn:hierarchy":[
        "tgn:7563281",
        "tgn:1000004",
        "tgn:7000198",
        "tgn:7016722",
        "tgn:7029392"
    ],
    "tgn:id":7563281,
    "tgn:name:en":"Dary\u0101purpatti",
    "tgn:placetype":[
        "aat:300008347"
    ]
},
  "bbox": [],
  "geometry": {"coordinates":[79.9415,27.0588],"type":"Point"}
}