<<<<<<< HEAD
{
  "id": 2256371,
  "type": "Feature",
  "properties": {
    "tgn:hierarchy":[
        "tgn:2256371",
        "tgn:1002238",
        "tgn:1000001",
        "tgn:7012149",
        "tgn:7007516",
        "tgn:7029392"
    ],
    "tgn:id":2256371,
    "tgn:name":"Copps Branch",
    "tgn:placetype":[
        "aat:300008699"
    ]
},
  "bbox": [],
  "geometry": {"coordinates":[-77.0,39.5833],"type":"Point"}
}
=======
{"geometry":{"type":"Point","coordinates":[-77.000000,39.583300]},"type":"Feature","properties":{"hierarchy":["tgn:2256371","tgn:1002238","tgn:1000001","tgn:7012149","tgn:7007516","tgn:7029392"],"placetype":["aat:300008699"],"id":2256371,"name:xx":"Copps Branch"}}
>>>>>>> 03f74aca74312dbeaf24d7e61306dd6a786dc3d0
