{
  "id": 2766114,
  "type": "Feature",
  "properties": {
    "tgn:hierarchy":[
        "tgn:2766114",
        "tgn:1000001",
        "tgn:7006451",
        "tgn:7012149",
        "tgn:2000099",
        "tgn:7029392"
    ],
    "tgn:id":2766114,
    "tgn:name":"White House Valley",
    "tgn:placetype":[
        "aat:300008761"
    ]
},
  "bbox": [],
  "geometry": {"coordinates":[-110.2667,36.4333],"type":"Point"}
}