{
  "id": 2261252,
  "type": "Feature",
  "properties": {
    "tgn:hierarchy":[
        "tgn:2261252",
        "tgn:1000001",
        "tgn:7012149",
        "tgn:7007252",
        "tgn:7029392"
    ],
    "tgn:id":2261252,
    "tgn:name":"County Line Branch",
    "tgn:placetype":[
        "aat:300008699"
    ]
},
  "bbox": [],
  "geometry": {"coordinates":[-86.65,38.3833],"type":"Point"}
}