{
  "id": 7324393,
  "type": "Feature",
  "properties": {
    "tgn:hierarchy":[
        "tgn:7324393",
        "tgn:7002836",
        "tgn:7016622",
        "tgn:1000003",
        "tgn:1000095",
        "tgn:7029392"
    ],
    "tgn:id":7324393,
    "tgn:name":"Iglesia de San Francisco",
    "tgn:placetype":[
        "aat:300007466"
    ]
},
  "bbox": [],
  "geometry": {"coordinates":[-16.25,28.466667],"type":"Point"}
}