{
  "id": 7406418,
  "type": "Feature",
  "properties": {
    "tgn:hierarchy":[
        "tgn:7406418",
        "tgn:7005585",
        "tgn:1000001",
        "tgn:7005560",
        "tgn:7029392"
    ],
    "tgn:id":7406418,
    "tgn:name":"Casahualillo",
    "tgn:placetype":[
        "aat:300008347"
    ]
},
  "bbox": [],
  "geometry": {"coordinates":[-100.05,18.05],"type":"Point"}
}