{
  "id": 7520615,
  "type": "Feature",
  "properties": {
    "tgn:hierarchy":[
        "tgn:7520615",
        "tgn:7001242",
        "tgn:7016833",
        "tgn:1001080",
        "tgn:7029392"
    ],
    "tgn:id":7520615,
    "tgn:name:en":"Al Jaz\u012brah al Kha\u1e11r\u0101'",
    "tgn:placetype":[
        "aat:300008347"
    ]
},
  "bbox": [],
  "geometry": {"coordinates":[31.831282,30.533875],"type":"Point"}
}