{
  "id": 7152091,
  "type": "Feature",
  "properties": {
    "tgn:hierarchy":[
        "tgn:7152091",
        "tgn:1000003",
        "tgn:7003677",
        "tgn:7000084",
        "tgn:7029392"
    ],
    "tgn:id":7152091,
    "tgn:name":"Kamerun",
    "tgn:placetype":[
        "aat:300000206"
    ]
},
  "bbox": [],
  "geometry": {"coordinates":[8.783333,51.983333],"type":"Point"}
}