{
  "id": 2305929,
  "type": "Feature",
  "properties": {
    "tgn:hierarchy":[
        "tgn:2305929",
        "tgn:1000001",
        "tgn:7012149",
        "tgn:2002005",
        "tgn:7007826",
        "tgn:7029392"
    ],
    "tgn:id":2305929,
    "tgn:name":"East Elevenmile Tank",
    "tgn:placetype":[
        "aat:300006191"
    ]
},
  "bbox": [],
  "geometry": {"coordinates":[-105.85,31.9667],"type":"Point"}
}