<<<<<<< HEAD
{
  "id": 7354784,
  "type": "Feature",
  "properties": {
    "tgn:hierarchy":[
        "tgn:7354784",
        "tgn:7005580",
        "tgn:1000001",
        "tgn:7005560",
        "tgn:7029392"
    ],
    "tgn:id":7354784,
    "tgn:name":"Candelaria",
    "tgn:placetype":[
        "aat:300008347"
    ]
},
  "bbox": [],
  "geometry": {"coordinates":[-92.2,15.766667],"type":"Point"}
}
=======
{"geometry":{"type":"Point","coordinates":[-92.200000,15.766667]},"type":"Feature","properties":{"hierarchy":["tgn:7354784","tgn:7005580","tgn:1000001","tgn:7005560","tgn:7029392"],"placetype":["aat:300008347"],"id":7354784,"name:xx":"Candelaria"}}
>>>>>>> 03f74aca74312dbeaf24d7e61306dd6a786dc3d0
