{
  "id": 7061208,
  "type": "Feature",
  "properties": {
    "tgn:hierarchy":[
        "tgn:7061208",
        "tgn:7003669",
        "tgn:1000003",
        "tgn:7000084",
        "tgn:7029392"
    ],
    "tgn:id":7061208,
    "tgn:name":"Andorf",
    "tgn:placetype":[
        "aat:300000206"
    ]
},
  "bbox": [],
  "geometry": {"coordinates":[13.216667,48.383333],"type":"Point"}
}