<<<<<<< HEAD
{
  "id": 2251292,
  "type": "Feature",
  "properties": {
    "tgn:hierarchy":[
        "tgn:2251292",
        "tgn:1000001",
        "tgn:7012149",
        "tgn:2000838",
        "tgn:7007255",
        "tgn:7029392"
    ],
    "tgn:id":2251292,
    "tgn:name":"Combs Branch",
    "tgn:placetype":[
        "aat:300008699"
    ]
},
  "bbox": [],
  "geometry": {"coordinates":[-83.9,37.7667],"type":"Point"}
}
=======
{"geometry":{"type":"Point","coordinates":[-83.900000,37.766700]},"type":"Feature","properties":{"hierarchy":["tgn:2251292","tgn:1000001","tgn:7012149","tgn:2000838","tgn:7007255","tgn:7029392"],"placetype":["aat:300008699"],"id":2251292,"name:xx":"Combs Branch"}}
>>>>>>> 03f74aca74312dbeaf24d7e61306dd6a786dc3d0
