{
  "id": 7303905,
  "type": "Feature",
  "properties": {
    "tgn:hierarchy":[
        "tgn:7303905",
        "tgn:7002758",
        "tgn:7002830",
        "tgn:1000003",
        "tgn:1000095",
        "tgn:7029392"
    ],
    "tgn:id":7303905,
    "tgn:name":"Navachica",
    "tgn:placetype":[
        "aat:300008798"
    ]
},
  "bbox": [],
  "geometry": {"coordinates":[-3.816667,36.833333],"type":"Point"}
}