{
  "id": 1017580,
  "type": "Feature",
  "properties": {
    "tgn:hierarchy":[
        "tgn:1017580",
        "tgn:1001853",
        "tgn:1000001",
        "tgn:7005560",
        "tgn:7029392"
    ],
    "tgn:id":1017580,
    "tgn:name":"Huisachal",
    "tgn:placetype":[
        "aat:300008347"
    ]
},
  "bbox": [],
  "geometry": {"coordinates":[-101.116667,26.783333],"type":"Point"}
}