{
  "id": 7584716,
  "type": "Feature",
  "properties": {
    "tgn:hierarchy":[
        "tgn:7584716",
        "tgn:1000004",
        "tgn:7000198",
        "tgn:7000799",
        "tgn:7029392"
    ],
    "tgn:id":7584716,
    "tgn:name:en":"Zong",
    "tgn:placetype":[
        "aat:300008347"
    ]
},
  "bbox": [],
  "geometry": {"coordinates":[78.862625,32.685064],"type":"Point"}
}