{
  "id": 7155335,
  "type": "Feature",
  "properties": {
    "tgn:hierarchy":[
        "tgn:7155335",
        "tgn:1000003",
        "tgn:7003689",
        "tgn:7000084",
        "tgn:7029392"
    ],
    "tgn:id":7155335,
    "tgn:name":"Kleinkeula",
    "tgn:placetype":[
        "aat:300008347"
    ]
},
  "bbox": [],
  "geometry": {"coordinates":[10.483333,51.316667],"type":"Point"}
}