{
  "id": 2333209,
  "type": "Feature",
  "properties": {
    "tgn:hierarchy":[
        "tgn:2333209",
        "tgn:1000001",
        "tgn:7012149",
        "tgn:2001556",
        "tgn:7007709",
        "tgn:7029392"
    ],
    "tgn:id":2333209,
    "tgn:name":"Flynn Ridge",
    "tgn:placetype":[
        "aat:300266640"
    ]
},
  "bbox": [],
  "geometry": {"coordinates":[-82.2167,35.7333],"type":"Point"}
}