{
  "id": 7318201,
  "type": "Feature",
  "properties": {
    "tgn:hierarchy":[
        "tgn:7318201",
        "tgn:1001768",
        "tgn:1000049",
        "tgn:1000002",
        "tgn:7029392"
    ],
    "tgn:id":7318201,
    "tgn:name":"Chupalla",
    "tgn:placetype":[
        "aat:300008777"
    ]
},
  "bbox": [],
  "geometry": {"coordinates":[-71.233333,-32.333333],"type":"Point"}
}