{
  "id": 2393152,
  "type": "Feature",
  "properties": {
    "tgn:hierarchy":[
        "tgn:2393152",
        "tgn:7006450",
        "tgn:1000001",
        "tgn:7012149",
        "tgn:2000086",
        "tgn:7029392"
    ],
    "tgn:id":2393152,
    "tgn:name":"Hodgkins Point",
    "tgn:placetype":[
        "aat:300008850"
    ]
},
  "bbox": [],
  "geometry": {"coordinates":[-148.0167,60.7667],"type":"Point"}
}