{
  "id": 2468747,
  "type": "Feature",
  "properties": {
    "tgn:hierarchy":[
        "tgn:2468747",
        "tgn:1000001",
        "tgn:7016172",
        "tgn:7012149",
        "tgn:2000161",
        "tgn:7029392"
    ],
    "tgn:id":2468747,
    "tgn:name":"Long Ridge",
    "tgn:placetype":[
        "aat:300266640"
    ]
},
  "bbox": [],
  "geometry": {"coordinates":[-93.9167,34.6167],"type":"Point"}
}