{
  "id": 2395282,
  "type": "Feature",
  "properties": {
    "tgn:hierarchy":[
        "tgn:2395282",
        "tgn:1000001",
        "tgn:7012149",
        "tgn:2001212",
        "tgn:7007523",
        "tgn:7029392"
    ],
    "tgn:id":2395282,
    "tgn:name":"Holiday Lake",
    "tgn:placetype":[
        "aat:300006191"
    ]
},
  "bbox": [],
  "geometry": {"coordinates":[-94.0833,39.0333],"type":"Point"}
}