{
  "id": 2446034,
  "type": "Feature",
  "properties": {
    "tgn:hierarchy":[
        "tgn:2446034",
        "tgn:7002659",
        "tgn:1000001",
        "tgn:7012149",
        "tgn:2000063",
        "tgn:7029392"
    ],
    "tgn:id":2446034,
    "tgn:name":"Levan Number 2 Mine",
    "tgn:placetype":[
        "aat:300000390"
    ]
},
  "bbox": [],
  "geometry": {"coordinates":[-87.05,33.8333],"type":"Point"}
}