<<<<<<< HEAD
{
  "id": 2332363,
  "type": "Feature",
  "properties": {
    "tgn:hierarchy":[
        "tgn:2332363",
        "tgn:1000001",
        "tgn:2001704",
        "tgn:7012149",
        "tgn:7007708",
        "tgn:7029392"
    ],
    "tgn:id":2332363,
    "tgn:name":"Flora Dell Creek",
    "tgn:placetype":[
        "aat:300008706"
    ]
},
  "bbox": [],
  "geometry": {"coordinates":[-124.0,42.6667],"type":"Point"}
}
=======
{"geometry":{"type":"Point","coordinates":[-124.000000,42.666700]},"type":"Feature","properties":{"hierarchy":["tgn:2332363","tgn:1000001","tgn:2001704","tgn:7012149","tgn:7007708","tgn:7029392"],"placetype":["aat:300008706"],"id":2332363,"name:xx":"Flora Dell Creek"}}
>>>>>>> 03f74aca74312dbeaf24d7e61306dd6a786dc3d0
