{
  "id": 2619964,
  "type": "Feature",
  "properties": {
    "tgn:hierarchy":[
        "tgn:2619964",
        "tgn:1000001",
        "tgn:2001476",
        "tgn:7012149",
        "tgn:7007709",
        "tgn:7029392"
    ],
    "tgn:id":2619964,
    "tgn:name":"Rippetoe Mountain",
    "tgn:placetype":[
        "aat:300008798"
    ]
},
  "bbox": [],
  "geometry": {"coordinates":[-81.5333,35.85],"type":"Point"}
}