{
  "id": 1035052,
  "type": "Feature",
  "properties": {
    "tgn:hierarchy":[
        "tgn:1035052",
        "tgn:1000003",
        "tgn:7002881",
        "tgn:1000070",
        "tgn:7029392"
    ],
    "tgn:id":1035052,
    "tgn:name":"Recologne",
    "tgn:placetype":[
        "aat:300008347"
    ]
},
  "bbox": [],
  "geometry": {"coordinates":[5.8333,47.2667],"type":"Point"}
}