<<<<<<< HEAD
{
  "id": 7022087,
  "type": "Feature",
  "properties": {
    "tgn:hierarchy":[
        "tgn:7022087",
        "tgn:1000001",
        "tgn:7012149",
        "tgn:1002733",
        "tgn:7007919",
        "tgn:7029392"
    ],
    "tgn:id":7022087,
    "tgn:name":"Clark Millpond",
    "tgn:placetype":[
        "aat:300006191"
    ]
},
  "bbox": [],
  "geometry": {"coordinates":[-76.4667,37.9167],"type":"Point"}
}
=======
{"geometry":{"type":"Point","coordinates":[-76.466700,37.916700]},"type":"Feature","properties":{"hierarchy":["tgn:7022087","tgn:1000001","tgn:7012149","tgn:1002733","tgn:7007919","tgn:7029392"],"placetype":["aat:300006191"],"id":7022087,"name:xx":"Clark Millpond"}}
>>>>>>> 03f74aca74312dbeaf24d7e61306dd6a786dc3d0
