{
  "id": 7022087,
  "type": "Feature",
  "properties": {
    "tgn:hierarchy":[
        "tgn:7022087",
        "tgn:1000001",
        "tgn:7012149",
        "tgn:1002733",
        "tgn:7007919",
        "tgn:7029392"
    ],
    "tgn:id":7022087,
    "tgn:name":"Clark Millpond",
    "tgn:placetype":[
        "aat:300006191"
    ]
},
  "bbox": [],
  "geometry": {"coordinates":[-76.4667,37.9167],"type":"Point"}
}