{
  "id": 7502835,
  "type": "Feature",
  "properties": {
    "tgn:hierarchy":[
        "tgn:7502835",
        "tgn:7001010",
        "tgn:1000004",
        "tgn:1000141",
        "tgn:7029392"
    ],
    "tgn:id":7502835,
    "tgn:name":"Mingli Erhao Tifang",
    "tgn:placetype":[
        "aat:300006156"
    ]
},
  "bbox": [],
  "geometry": {"coordinates":[121.257222,23.194167],"type":"Point"}
}