{
  "id": 2311896,
  "type": "Feature",
  "properties": {
    "tgn:hierarchy":[
        "tgn:2311896",
        "tgn:1000001",
        "tgn:7012149",
        "tgn:1002871",
        "tgn:7007568",
        "tgn:7029392"
    ],
    "tgn:id":2311896,
    "tgn:name":"Efner Lake Brook",
    "tgn:placetype":[
        "aat:300008699"
    ]
},
  "bbox": [],
  "geometry": {"coordinates":[-73.9167,43.2667],"type":"Point"}
}