{
  "id": 2631088,
  "type": "Feature",
  "properties": {
    "tgn:hierarchy":[
        "tgn:2631088",
        "tgn:1000001",
        "tgn:2000462",
        "tgn:7012149",
        "tgn:7007250",
        "tgn:7029392"
    ],
    "tgn:id":2631088,
    "tgn:name":"Round Mountain",
    "tgn:placetype":[
        "aat:300008798"
    ]
},
  "bbox": [],
  "geometry": {"coordinates":[-116.4167,48.5833],"type":"Point"}
}