{
  "id": 7240478,
  "type": "Feature",
  "properties": {
    "tgn:hierarchy":[
        "tgn:7240478",
        "tgn:7007877",
        "tgn:1000003",
        "tgn:1000063",
        "tgn:4012014",
        "tgn:7029392"
    ],
    "tgn:id":7240478,
    "tgn:name":"Estafflers",
    "tgn:placetype":[
        "aat:300008347"
    ]
},
  "bbox": [],
  "geometry": {"coordinates":[3.257424,50.639615],"type":"Point"}
}