{
  "id": 2680667,
  "type": "Feature",
  "properties": {
    "tgn:hierarchy":[
        "tgn:2680667",
        "tgn:2000455",
        "tgn:1000001",
        "tgn:7012149",
        "tgn:7007250",
        "tgn:7029392"
    ],
    "tgn:id":2680667,
    "tgn:name":"South Hill",
    "tgn:placetype":[
        "aat:300008798"
    ]
},
  "bbox": [],
  "geometry": {"coordinates":[-111.3833,42.3833],"type":"Point"}
}