{
  "id": 2637107,
  "type": "Feature",
  "properties": {
    "tgn:hierarchy":[
        "tgn:2637107",
        "tgn:1002175",
        "tgn:1000001",
        "tgn:7012149",
        "tgn:7007706",
        "tgn:7029392"
    ],
    "tgn:id":2637107,
    "tgn:name":"Saint Clairsville Reservoir Number Two",
    "tgn:placetype":[
        "aat:300006191"
    ]
},
  "bbox": [],
  "geometry": {"coordinates":[-80.9167,40.0833],"type":"Point"}
}