{
  "id": 1053966,
  "type": "Feature",
  "properties": {
    "tgn:hierarchy":[
        "tgn:1053966",
        "tgn:1000004",
        "tgn:7012253",
        "tgn:7006661",
        "tgn:7029392"
    ],
    "tgn:id":1053966,
    "tgn:name":"Gazalkent",
    "tgn:placetype":[
        "aat:300008347"
    ]
},
  "bbox": [],
  "geometry": {"coordinates":[69.75,41.5167],"type":"Point"}
}