{
  "id": 2204387,
  "type": "Feature",
  "properties": {
    "tgn:hierarchy":[
        "tgn:2204387",
        "tgn:1000001",
        "tgn:2000595",
        "tgn:7012149",
        "tgn:7007253",
        "tgn:7029392"
    ],
    "tgn:id":2204387,
    "tgn:name":"Buffalo Creek",
    "tgn:placetype":[
        "aat:300008706"
    ]
},
  "bbox": [],
  "geometry": {"coordinates":[-93.4333,42.8333],"type":"Point"}
}