{
  "id": 7421358,
  "type": "Feature",
  "properties": {
    "tgn:hierarchy":[
        "tgn:7421358",
        "tgn:7005579",
        "tgn:1000001",
        "tgn:7005560",
        "tgn:7029392"
    ],
    "tgn:id":7421358,
    "tgn:name":"Triana",
    "tgn:placetype":[
        "aat:300008347"
    ]
},
  "bbox": [],
  "geometry": {"coordinates":[-102.729167,21.866667],"type":"Point"}
}