{
  "id": 7234774,
  "type": "Feature",
  "properties": {
    "tgn:hierarchy":[
        "tgn:7234774",
        "tgn:7002745",
        "tgn:7017076",
        "tgn:1000003",
        "tgn:1000074",
        "tgn:7029392"
    ],
    "tgn:id":7234774,
    "tgn:name":"Boutseli\u00e1nika",
    "tgn:placetype":[
        "aat:300008347"
    ]
},
  "bbox": [],
  "geometry": {"coordinates":[22.416667,36.733333],"type":"Point"}
}