<<<<<<< HEAD
{
  "id": 2768325,
  "type": "Feature",
  "properties": {
    "tgn:hierarchy":[
        "tgn:2768325",
        "tgn:1000001",
        "tgn:7012149",
        "tgn:2002155",
        "tgn:7007919",
        "tgn:7029392"
    ],
    "tgn:id":2768325,
    "tgn:name":"Whiteshop Estates",
    "tgn:placetype":[
        "aat:300008347"
    ]
},
  "bbox": [],
  "geometry": {"coordinates":[-78.05,38.45],"type":"Point"}
}
=======
{"geometry":{"type":"Point","coordinates":[-78.050000,38.450000]},"type":"Feature","properties":{"hierarchy":["tgn:2768325","tgn:1000001","tgn:7012149","tgn:2002155","tgn:7007919","tgn:7029392"],"placetype":["aat:300008347"],"id":2768325,"name:xx":"Whiteshop Estates"}}
>>>>>>> 03f74aca74312dbeaf24d7e61306dd6a786dc3d0
