{
  "id": 2274511,
  "type": "Feature",
  "properties": {
    "tgn:hierarchy":[
        "tgn:2274511",
        "tgn:7002659",
        "tgn:1000001",
        "tgn:7012149",
        "tgn:2000031",
        "tgn:7029392"
    ],
    "tgn:id":2274511,
    "tgn:name":"Dallas Branch",
    "tgn:placetype":[
        "aat:300008699"
    ]
},
  "bbox": [],
  "geometry": {"coordinates":[-88.0333,32.6333],"type":"Point"}
}