{
  "id": 7338879,
  "type": "Feature",
  "properties": {
    "tgn:hierarchy":[
        "tgn:7338879",
        "tgn:7002816",
        "tgn:1001647",
        "tgn:1000003",
        "tgn:1000095",
        "tgn:7029392"
    ],
    "tgn:id":7338879,
    "tgn:name":"Cuatro Cerros, Laguna de los",
    "tgn:placetype":[
        "aat:300008688"
    ]
},
  "bbox": [],
  "geometry": {"coordinates":[-4.466667,39.316667],"type":"Point"}
}