{
  "id": 2769757,
  "type": "Feature",
  "properties": {
    "tgn:hierarchy":[
        "tgn:2769757",
        "tgn:1000001",
        "tgn:2000922",
        "tgn:7012149",
        "tgn:7007515",
        "tgn:7029392"
    ],
    "tgn:id":2769757,
    "tgn:name":"Wight Pond",
    "tgn:placetype":[
        "aat:300008680"
    ]
},
  "bbox": [],
  "geometry": {"coordinates":[-68.6667,44.45],"type":"Point"}
}