{
  "id": 2295532,
  "type": "Feature",
  "properties": {
    "tgn:hierarchy":[
        "tgn:2295532",
        "tgn:1000001",
        "tgn:7012149",
        "tgn:2002039",
        "tgn:7007826",
        "tgn:7029392"
    ],
    "tgn:id":2295532,
    "tgn:name":"Dripping Spring Creek",
    "tgn:placetype":[
        "aat:300008706"
    ]
},
  "bbox": [],
  "geometry": {"coordinates":[-98.8667,29.5667],"type":"Point"}
}