{
  "id": 7095877,
  "type": "Feature",
  "properties": {
    "tgn:hierarchy":[
        "tgn:7095877",
        "tgn:1000003",
        "tgn:7003689",
        "tgn:7000084",
        "tgn:7029392"
    ],
    "tgn:id":7095877,
    "tgn:name":"Sch\u00f6n-Berg",
    "tgn:placetype":[
        "aat:300008777"
    ]
},
  "bbox": [],
  "geometry": {"coordinates":[10.516667,51.366667],"type":"Point"}
}