{
  "id": 2574705,
  "type": "Feature",
  "properties": {
    "tgn:hierarchy":[
        "tgn:2574705",
        "tgn:1000001",
        "tgn:7012149",
        "tgn:2001451",
        "tgn:7007566",
        "tgn:7029392"
    ],
    "tgn:id":2574705,
    "tgn:name":"Pe\u00f1asco Springs",
    "tgn:placetype":[
        "aat:300008697"
    ]
},
  "bbox": [],
  "geometry": {"coordinates":[-106.85,35.5833],"type":"Point"}
}