{
  "id": 2376222,
  "type": "Feature",
  "properties": {
    "tgn:hierarchy":[
        "tgn:2376222",
        "tgn:1000001",
        "tgn:7012149",
        "tgn:2000488",
        "tgn:7007250",
        "tgn:7029392"
    ],
    "tgn:id":2376222,
    "tgn:name":"Hard Up Gulch",
    "tgn:placetype":[
        "aat:300008761"
    ]
},
  "bbox": [],
  "geometry": {"coordinates":[-116.7667,42.95],"type":"Point"}
}