{
  "id": 2656086,
  "type": "Feature",
  "properties": {
    "tgn:hierarchy":[
        "tgn:2656086",
        "tgn:1000001",
        "tgn:7012149",
        "tgn:7007158",
        "tgn:2000246",
        "tgn:7029392"
    ],
    "tgn:id":2656086,
    "tgn:name":"Shaw Springs",
    "tgn:placetype":[
        "aat:300008697"
    ]
},
  "bbox": [],
  "geometry": {"coordinates":[-106.3167,37.75],"type":"Point"}
}