{
  "id": 7577076,
  "type": "Feature",
  "properties": {
    "tgn:hierarchy":[
        "tgn:7577076",
        "tgn:7001819",
        "tgn:1000004",
        "tgn:7000198",
        "tgn:7029392"
    ],
    "tgn:id":7577076,
    "tgn:name:en":"Krawnaon River",
    "tgn:placetype":[
        "aat:300387032"
    ]
},
  "bbox": [],
  "geometry": {"coordinates":[96.933333,27.883333],"type":"Point"}
}