{
  "id": 7149981,
  "type": "Feature",
  "properties": {
    "tgn:hierarchy":[
        "tgn:7149981",
        "tgn:7000096",
        "tgn:1000003",
        "tgn:7000084",
        "tgn:7029392"
    ],
    "tgn:id":7149981,
    "tgn:name":"Kuhlowitz",
    "tgn:placetype":[
        "aat:300008347"
    ]
},
  "bbox": [],
  "geometry": {"coordinates":[12.633333,52.133333],"type":"Point"}
}