{
  "id": 7512805,
  "type": "Feature",
  "properties": {
    "tgn:hierarchy":[
        "tgn:7512805",
        "tgn:1009227",
        "tgn:1000226",
        "tgn:7016822",
        "tgn:1000006",
        "tgn:7029392"
    ],
    "tgn:id":7512805,
    "tgn:name:en":"Hengaa",
    "tgn:placetype":[
        "aat:300008777"
    ]
},
  "bbox": [],
  "geometry": {"coordinates":[-176.566667,-43.833333],"type":"Point"}
}