{
  "id": 2301298,
  "type": "Feature",
  "properties": {
    "tgn:hierarchy":[
        "tgn:2301298",
        "tgn:1000001",
        "tgn:7012149",
        "tgn:2002057",
        "tgn:7007826",
        "tgn:7029392"
    ],
    "tgn:id":2301298,
    "tgn:name":"Dunman Creek",
    "tgn:placetype":[
        "aat:300008706"
    ]
},
  "bbox": [],
  "geometry": {"coordinates":[-104.1667,30.0167],"type":"Point"}
}