{
  "id": 7395606,
  "type": "Feature",
  "properties": {
    "tgn:hierarchy":[
        "tgn:7395606",
        "tgn:1000001",
        "tgn:7005594",
        "tgn:7005560",
        "tgn:7029392"
    ],
    "tgn:id":7395606,
    "tgn:name":"San Dieguito",
    "tgn:placetype":[
        "aat:300007783"
    ]
},
  "bbox": [],
  "geometry": {"coordinates":[-99.233333,22.033333],"type":"Point"}
}