{
  "id": 2489445,
  "type": "Feature",
  "properties": {
    "tgn:hierarchy":[
        "tgn:2489445",
        "tgn:1000001",
        "tgn:7012149",
        "tgn:2001718",
        "tgn:7007708",
        "tgn:7029392"
    ],
    "tgn:id":2489445,
    "tgn:name":"Malheur Junction",
    "tgn:placetype":[
        "aat:300008347"
    ]
},
  "bbox": [],
  "geometry": {"coordinates":[-116.9667,43.9833],"type":"Point"}
}