{
  "id": 2319843,
  "type": "Feature",
  "properties": {
    "tgn:hierarchy":[
        "tgn:2319843",
        "tgn:1000001",
        "tgn:7012149",
        "tgn:1002835",
        "tgn:7007706",
        "tgn:7029392"
    ],
    "tgn:id":2319843,
    "tgn:name":"Eustis",
    "tgn:placetype":[
        "aat:300008347"
    ]
},
  "bbox": [],
  "geometry": {"coordinates":[-82.9667,39.3667],"type":"Point"}
}