{
  "id": 7051995,
  "type": "Feature",
  "properties": {
    "tgn:hierarchy":[
        "tgn:7051995",
        "tgn:7003006",
        "tgn:1000003",
        "tgn:7002997",
        "tgn:1000080",
        "tgn:7029392"
    ],
    "tgn:id":7051995,
    "tgn:name":"Motta Amolara",
    "tgn:placetype":[
        "aat:300008347"
    ]
},
  "bbox": [],
  "geometry": {"coordinates":[12.15,45.166667],"type":"Point"}
}