<<<<<<< HEAD
{
  "id": 7051995,
  "type": "Feature",
  "properties": {
    "tgn:hierarchy":[
        "tgn:7051995",
        "tgn:7003006",
        "tgn:1000003",
        "tgn:7002997",
        "tgn:1000080",
        "tgn:7029392"
    ],
    "tgn:id":7051995,
    "tgn:name":"Motta Amolara",
    "tgn:placetype":[
        "aat:300008347"
    ]
},
  "bbox": [],
  "geometry": {"coordinates":[12.15,45.166667],"type":"Point"}
}
=======
{"geometry":{"type":"Point","coordinates":[12.150000,45.166667]},"type":"Feature","properties":{"hierarchy":["tgn:7051995","tgn:7003006","tgn:1000003","tgn:7002997","tgn:1000080","tgn:7029392"],"placetype":["aat:300008347"],"id":7051995,"name:xx":"Motta Amolara"}}
>>>>>>> 03f74aca74312dbeaf24d7e61306dd6a786dc3d0
