{
  "id": 2617623,
  "type": "Feature",
  "properties": {
    "tgn:hierarchy":[
        "tgn:2617623",
        "tgn:1000001",
        "tgn:7016172",
        "tgn:7012149",
        "tgn:2000147",
        "tgn:7029392"
    ],
    "tgn:id":2617623,
    "tgn:name":"Rickey Branch",
    "tgn:placetype":[
        "aat:300008699"
    ]
},
  "bbox": [],
  "geometry": {"coordinates":[-91.85,34.8167],"type":"Point"}
}