{
  "id": 7265226,
  "type": "Feature",
  "properties": {
    "tgn:concordances":{
        "gn:id":"2753478"
    },
    "tgn:hierarchy":[
        "tgn:7265226",
        "tgn:1000003",
        "tgn:7006951",
        "tgn:7016845",
        "tgn:7029392"
    ],
    "tgn:id":7265226,
    "tgn:name:nl":"Huiswaard",
    "tgn:placetype":[
        "aat:300008347"
    ]
},
  "bbox": [],
  "geometry": {"coordinates":[4.75,52.65],"type":"Point"}
}