{
  "id": 2230319,
  "type": "Feature",
  "properties": {
    "tgn:hierarchy":[
        "tgn:2230319",
        "tgn:7002659",
        "tgn:1000001",
        "tgn:2000020",
        "tgn:7012149",
        "tgn:7029392"
    ],
    "tgn:id":2230319,
    "tgn:name":"Centenary",
    "tgn:placetype":[
        "aat:300008347"
    ]
},
  "bbox": [],
  "geometry": {"coordinates":[-86.3667,31.7667],"type":"Point"}
}