{
  "id": 7298084,
  "type": "Feature",
  "properties": {
    "tgn:hierarchy":[
        "tgn:7298084",
        "tgn:7008911",
        "tgn:1000003",
        "tgn:7002763",
        "tgn:1000095",
        "tgn:7029392"
    ],
    "tgn:id":7298084,
    "tgn:name":"Sograndio de Arriba",
    "tgn:placetype":[
        "aat:300008347"
    ]
},
  "bbox": [],
  "geometry": {"coordinates":[-5.933333,43.35],"type":"Point"}
}