{
  "id": 7233001,
  "type": "Feature",
  "properties": {
    "tgn:hierarchy":[
        "tgn:7233001",
        "tgn:7011167",
        "tgn:7001338",
        "tgn:1000003",
        "tgn:1000074",
        "tgn:7029392"
    ],
    "tgn:id":7233001,
    "tgn:name":"Lo\u00fakha",
    "tgn:placetype":[
        "aat:300008347"
    ]
},
  "bbox": [],
  "geometry": {"coordinates":[20.716667,37.783333],"type":"Point"}
}