{
  "id": 7161230,
  "type": "Feature",
  "properties": {
    "tgn:hierarchy":[
        "tgn:7161230",
        "tgn:1000003",
        "tgn:7003677",
        "tgn:7000084",
        "tgn:7029392"
    ],
    "tgn:id":7161230,
    "tgn:name":"Hohe Liethe",
    "tgn:placetype":[
        "aat:300008777"
    ]
},
  "bbox": [],
  "geometry": {"coordinates":[8.066667,51.283333],"type":"Point"}
}