{
  "id": 7245336,
  "type": "Feature",
  "properties": {
    "tgn:hierarchy":[
        "tgn:7245336",
        "tgn:7003457",
        "tgn:1000003",
        "tgn:1000063",
        "tgn:7018236",
        "tgn:7029392"
    ],
    "tgn:id":7245336,
    "tgn:name":"Akselwal",
    "tgn:placetype":[
        "aat:300008347"
    ]
},
  "bbox": [],
  "geometry": {"coordinates":[3.636824,50.896583],"type":"Point"}
}