{
  "id": 2710595,
  "type": "Feature",
  "properties": {
    "tgn:hierarchy":[
        "tgn:2710595",
        "tgn:1000001",
        "tgn:7012149",
        "tgn:1002988",
        "tgn:7007710",
        "tgn:7029392"
    ],
    "tgn:id":2710595,
    "tgn:name":"Tamarack Swamp",
    "tgn:placetype":[
        "aat:300008905"
    ]
},
  "bbox": [],
  "geometry": {"coordinates":[-79.55,41.9833],"type":"Point"}
}