{
  "id": 7033324,
  "type": "Feature",
  "properties": {
    "tgn:hierarchy":[
        "tgn:7033324",
        "tgn:1003506",
        "tgn:1000003",
        "tgn:7002993",
        "tgn:1000080",
        "tgn:7029392"
    ],
    "tgn:id":7033324,
    "tgn:name":"Uccea",
    "tgn:placetype":[
        "aat:300008699"
    ]
},
  "bbox": [],
  "geometry": {"coordinates":[13.398056,46.306389],"type":"Point"}
}