{
  "id": 2720895,
  "type": "Feature",
  "properties": {
    "tgn:hierarchy":[
        "tgn:2720895",
        "tgn:7002659",
        "tgn:1000001",
        "tgn:7012149",
        "tgn:2000066",
        "tgn:7029392"
    ],
    "tgn:id":2720895,
    "tgn:name":"Ticky Branch",
    "tgn:placetype":[
        "aat:300008699"
    ]
},
  "bbox": [],
  "geometry": {"coordinates":[-87.35,34.05],"type":"Point"}
}