{
  "id": 7383204,
  "type": "Feature",
  "properties": {
    "tgn:hierarchy":[
        "tgn:7383204",
        "tgn:1000001",
        "tgn:7005599",
        "tgn:7005560",
        "tgn:7029392"
    ],
    "tgn:id":7383204,
    "tgn:name":"Orilla del Monte",
    "tgn:placetype":[
        "aat:300008347"
    ]
},
  "bbox": [],
  "geometry": {"coordinates":[-97.266667,19.666667],"type":"Point"}
}