{
  "id": 7531376,
  "type": "Feature",
  "properties": {
    "tgn:hierarchy":[
        "tgn:7531376",
        "tgn:7001242",
        "tgn:7016833",
        "tgn:1001091",
        "tgn:7029392"
    ],
    "tgn:id":7531376,
    "tgn:name":"Mas\u0101kin al Qubbah al Jad\u012bdah",
    "tgn:placetype":[
        "aat:300000745"
    ]
},
  "bbox": [],
  "geometry": {"coordinates":[31.287072,30.094247],"type":"Point"}
}