{
  "id": 2663174,
  "type": "Feature",
  "properties": {
    "tgn:hierarchy":[
        "tgn:2663174",
        "tgn:1000001",
        "tgn:7012149",
        "tgn:2000210",
        "tgn:7007158",
        "tgn:7029392"
    ],
    "tgn:id":2663174,
    "tgn:name":"Silver Creek",
    "tgn:placetype":[
        "aat:300008706"
    ]
},
  "bbox": [],
  "geometry": {"coordinates":[-106.6333,39.3667],"type":"Point"}
}