{
  "id": 2324330,
  "type": "Feature",
  "properties": {
    "tgn:hierarchy":[
        "tgn:2324330",
        "tgn:1000001",
        "tgn:7012149",
        "tgn:2001453",
        "tgn:7007566",
        "tgn:7029392"
    ],
    "tgn:id":2324330,
    "tgn:name":"Feed Pasture Tank",
    "tgn:placetype":[
        "aat:300006191"
    ]
},
  "bbox": [],
  "geometry": {"coordinates":[-104.0833,35.1667],"type":"Point"}
}