{
  "id": 2754252,
  "type": "Feature",
  "properties": {
    "tgn:hierarchy":[
        "tgn:2754252",
        "tgn:1000001",
        "tgn:7019560",
        "tgn:7012149",
        "tgn:7007566",
        "tgn:7029392"
    ],
    "tgn:id":2754252,
    "tgn:name":"Watts Hill",
    "tgn:placetype":[
        "aat:300008798"
    ]
},
  "bbox": [],
  "geometry": {"coordinates":[-104.0667,34.1833],"type":"Point"}
}