<<<<<<< HEAD
{
  "id": 2259700,
  "type": "Feature",
  "properties": {
    "tgn:hierarchy":[
        "tgn:2259700",
        "tgn:1000001",
        "tgn:7012149",
        "tgn:2001723",
        "tgn:7007708",
        "tgn:7029392"
    ],
    "tgn:id":2259700,
    "tgn:name":"Cougar Creek",
    "tgn:placetype":[
        "aat:300008706"
    ]
},
  "bbox": [],
  "geometry": {"coordinates":[-119.7,44.4],"type":"Point"}
}
=======
{"geometry":{"type":"Point","coordinates":[-119.700000,44.400000]},"type":"Feature","properties":{"hierarchy":["tgn:2259700","tgn:1000001","tgn:7012149","tgn:2001723","tgn:7007708","tgn:7029392"],"placetype":["aat:300008706"],"id":2259700,"name:xx":"Cougar Creek"}}
>>>>>>> 03f74aca74312dbeaf24d7e61306dd6a786dc3d0
