<<<<<<< HEAD
{
  "id": 7375852,
  "type": "Feature",
  "properties": {
    "tgn:hierarchy":[
        "tgn:7375852",
        "tgn:1000001",
        "tgn:7005589",
        "tgn:7005560",
        "tgn:7029392"
    ],
    "tgn:id":7375852,
    "tgn:name":"La Reforma",
    "tgn:placetype":[
        "aat:300008347"
    ]
},
  "bbox": [],
  "geometry": {"coordinates":[-100.0,25.25],"type":"Point"}
}
=======
{"geometry":{"type":"Point","coordinates":[-100.000000,25.250000]},"type":"Feature","properties":{"hierarchy":["tgn:7375852","tgn:1000001","tgn:7005589","tgn:7005560","tgn:7029392"],"placetype":["aat:300008347"],"id":7375852,"name:xx":"La Reforma"}}
>>>>>>> 03f74aca74312dbeaf24d7e61306dd6a786dc3d0
