{
  "id": 1005177,
  "type": "Feature",
  "properties": {
    "tgn:hierarchy":[
        "tgn:1005177",
        "tgn:1000003",
        "tgn:7003677",
        "tgn:7000084",
        "tgn:1040868",
        "tgn:7029392"
    ],
    "tgn:id":1005177,
    "tgn:name":"Neuenhof",
    "tgn:placetype":[
        "aat:300000745",
        "aat:300387332"
    ]
},
  "bbox": [],
  "geometry": {"coordinates":[7.2167,51.1667],"type":"Point"}
}