{
  "id": 5002670,
  "type": "Feature",
  "properties": {
    "tgn:hierarchy":[
        "tgn:5002670",
        "tgn:1003483",
        "tgn:1000003",
        "tgn:7003240",
        "tgn:1000080",
        "tgn:7029392"
    ],
    "tgn:id":5002670,
    "tgn:name":"Montefiorentino",
    "tgn:placetype":[
        "aat:300000635",
        "aat:300000641"
    ]
},
  "bbox": [],
  "geometry": {"coordinates":[12.35,43.75],"type":"Point"}
}