{
  "id": 2226541,
  "type": "Feature",
  "properties": {
    "tgn:hierarchy":[
        "tgn:2226541",
        "tgn:1000001",
        "tgn:7016172",
        "tgn:2000123",
        "tgn:7012149",
        "tgn:7029392"
    ],
    "tgn:id":2226541,
    "tgn:name":"Cathy Lake",
    "tgn:placetype":[
        "aat:300006191"
    ]
},
  "bbox": [],
  "geometry": {"coordinates":[-90.7667,35.1833],"type":"Point"}
}