{
  "id": 7513057,
  "type": "Feature",
  "properties": {
    "tgn:hierarchy":[
        "tgn:7513057",
        "tgn:1009227",
        "tgn:1000226",
        "tgn:7018437",
        "tgn:1000006",
        "tgn:7029392"
    ],
    "tgn:id":7513057,
    "tgn:name:en":"Hammond Hill",
    "tgn:placetype":[
        "aat:300008777"
    ]
},
  "bbox": [],
  "geometry": {"coordinates":[170.583333,-45.683333],"type":"Point"}
}