{
  "id": 2344663,
  "type": "Feature",
  "properties": {
    "tgn:hierarchy":[
        "tgn:2344663",
        "tgn:1000001",
        "tgn:7012149",
        "tgn:2001451",
        "tgn:7007566",
        "tgn:7029392"
    ],
    "tgn:id":2344663,
    "tgn:name":"Garcia, Mesa",
    "tgn:placetype":[
        "aat:300008798"
    ]
},
  "bbox": [],
  "geometry": {"coordinates":[-106.75,35.7167],"type":"Point"}
}