<<<<<<< HEAD
{
  "id": 2332634,
  "type": "Feature",
  "properties": {
    "tgn:hierarchy":[
        "tgn:2332634",
        "tgn:1000001",
        "tgn:7012149",
        "tgn:2001706",
        "tgn:7007708",
        "tgn:7029392"
    ],
    "tgn:id":2332634,
    "tgn:name":"Flory Spring",
    "tgn:placetype":[
        "aat:300008697"
    ]
},
  "bbox": [],
  "geometry": {"coordinates":[-123.4,42.75],"type":"Point"}
}
=======
{"geometry":{"type":"Point","coordinates":[-123.400000,42.750000]},"type":"Feature","properties":{"hierarchy":["tgn:2332634","tgn:1000001","tgn:7012149","tgn:2001706","tgn:7007708","tgn:7029392"],"placetype":["aat:300008697"],"id":2332634,"name:xx":"Flory Spring"}}
>>>>>>> 03f74aca74312dbeaf24d7e61306dd6a786dc3d0
