{
  "id": 1068462,
  "type": "Feature",
  "properties": {
    "tgn:hierarchy":[
        "tgn:1068462",
        "tgn:1000004",
        "tgn:7002082",
        "tgn:1000111",
        "tgn:7029392"
    ],
    "tgn:id":1068462,
    "tgn:name":"Gujiang",
    "tgn:placetype":[
        "aat:300008347"
    ]
},
  "bbox": [],
  "geometry": {"coordinates":[114.7833,27.1833],"type":"Point"}
}