{
  "id": 7500481,
  "type": "Feature",
  "properties": {
    "tgn:hierarchy":[
        "tgn:7500481",
        "tgn:7001010",
        "tgn:1000004",
        "tgn:1000141",
        "tgn:7029392"
    ],
    "tgn:id":7500481,
    "tgn:name":"Asanglaijia Shan",
    "tgn:placetype":[
        "aat:300387002"
    ]
},
  "bbox": [],
  "geometry": {"coordinates":[121.225556,23.370833],"type":"Point"}
}