{
  "id": 2394144,
  "type": "Feature",
  "properties": {
    "tgn:hierarchy":[
        "tgn:2394144",
        "tgn:1000001",
        "tgn:7012149",
        "tgn:2000434",
        "tgn:7007248",
        "tgn:7029392"
    ],
    "tgn:id":2394144,
    "tgn:name":"Hogan Lake",
    "tgn:placetype":[
        "aat:300006191"
    ]
},
  "bbox": [],
  "geometry": {"coordinates":[-83.3167,32.65],"type":"Point"}
}