{
  "id": 7574928,
  "type": "Feature",
  "properties": {
    "tgn:hierarchy":[
        "tgn:7574928",
        "tgn:1000004",
        "tgn:7000198",
        "tgn:7016788",
        "tgn:7029392"
    ],
    "tgn:id":7574928,
    "tgn:name:en":"Kaw\u0101s",
    "tgn:placetype":[
        "aat:300007783"
    ]
},
  "bbox": [],
  "geometry": {"coordinates":[71.547909,25.870778],"type":"Point"}
}