{
  "id": 2751151,
  "type": "Feature",
  "properties": {
    "tgn:hierarchy":[
        "tgn:2751151",
        "tgn:1000001",
        "tgn:1002902",
        "tgn:7012149",
        "tgn:7007516",
        "tgn:7029392"
    ],
    "tgn:id":2751151,
    "tgn:name":"Ware Point Marsh",
    "tgn:placetype":[
        "aat:300008905"
    ]
},
  "bbox": [],
  "geometry": {"coordinates":[-75.8333,37.9333],"type":"Point"}
}