{
  "id": 7459906,
  "type": "Feature",
  "properties": {
    "tgn:hierarchy":[
        "tgn:7459906",
        "tgn:7002444",
        "tgn:1000003",
        "tgn:7008072",
        "tgn:7008591",
        "tgn:7029392"
    ],
    "tgn:id":7459906,
    "tgn:name:en":"Oldhamstocks",
    "tgn:placetype":[
        "aat:300008347"
    ]
},
  "bbox": [],
  "geometry": {"coordinates":[-2.416667,55.916667],"type":"Point"}
}