{
  "id": 7587620,
  "type": "Feature",
  "properties": {
    "tgn:hierarchy":[
        "tgn:7587620",
        "tgn:1000004",
        "tgn:7000198",
        "tgn:7000799",
        "tgn:7029392"
    ],
    "tgn:id":7587620,
    "tgn:name:en":"Yekr\u0101jpur",
    "tgn:placetype":[
        "aat:300008347"
    ]
},
  "bbox": [],
  "geometry": {"coordinates":[74.820833,34.063889],"type":"Point"}
}