{
  "id": 7573903,
  "type": "Feature",
  "properties": {
    "tgn:hierarchy":[
        "tgn:7573903",
        "tgn:1000004",
        "tgn:7000198",
        "tgn:7016722",
        "tgn:7029392"
    ],
    "tgn:id":7573903,
    "tgn:name:en":"Jagamanpur",
    "tgn:placetype":[
        "aat:300008347"
    ]
},
  "bbox": [],
  "geometry": {"coordinates":[79.220685,26.406653],"type":"Point"}
}