{
  "id": 2414729,
  "type": "Feature",
  "properties": {
    "tgn:hierarchy":[
        "tgn:2414729",
        "tgn:1000001",
        "tgn:7012149",
        "tgn:2001486",
        "tgn:7007709",
        "tgn:7029392"
    ],
    "tgn:id":2414729,
    "tgn:name":"Isaac Creek",
    "tgn:placetype":[
        "aat:300008706"
    ]
},
  "bbox": [],
  "geometry": {"coordinates":[-76.65,34.8667],"type":"Point"}
}