{
  "id": 7079943,
  "type": "Feature",
  "properties": {
    "tgn:hierarchy":[
        "tgn:7079943",
        "tgn:7003692",
        "tgn:1000003",
        "tgn:7000084",
        "tgn:7029392"
    ],
    "tgn:id":7079943,
    "tgn:name":"Winterrain",
    "tgn:placetype":[
        "aat:300008347"
    ]
},
  "bbox": [],
  "geometry": {"coordinates":[9.65,49.15],"type":"Point"}
}