{
  "id": 2144863,
  "type": "Feature",
  "properties": {
    "tgn:hierarchy":[
        "tgn:2144863",
        "tgn:1000001",
        "tgn:2000922",
        "tgn:7012149",
        "tgn:7007515",
        "tgn:7029392"
    ],
    "tgn:id":2144863,
    "tgn:name":"Bald Island",
    "tgn:placetype":[
        "aat:300008791"
    ]
},
  "bbox": [],
  "geometry": {"coordinates":[-68.7833,44.1833],"type":"Point"}
}