{
  "id": 2609887,
  "type": "Feature",
  "properties": {
    "tgn:hierarchy":[
        "tgn:2609887",
        "tgn:1000001",
        "tgn:7012149",
        "tgn:2002164",
        "tgn:7007919",
        "tgn:7029392"
    ],
    "tgn:id":2609887,
    "tgn:name":"Reavistown",
    "tgn:placetype":[
        "aat:300008347"
    ]
},
  "bbox": [],
  "geometry": {"coordinates":[-80.9667,36.6333],"type":"Point"}
}