{
  "id": 2612862,
  "type": "Feature",
  "properties": {
    "tgn:hierarchy":[
        "tgn:2612862",
        "tgn:1000001",
        "tgn:7012149",
        "tgn:2002374",
        "tgn:7007923",
        "tgn:7029392"
    ],
    "tgn:id":2612862,
    "tgn:name":"Redman Ditch",
    "tgn:placetype":[
        "aat:300006075"
    ]
},
  "bbox": [],
  "geometry": {"coordinates":[-106.6167,44.3667],"type":"Point"}
}