{
  "id": 2432992,
  "type": "Feature",
  "properties": {
    "tgn:hierarchy":[
        "tgn:2432992",
        "tgn:1000001",
        "tgn:7012149",
        "tgn:2001501",
        "tgn:7007709",
        "tgn:7029392"
    ],
    "tgn:id":2432992,
    "tgn:name":"Kehukee Swamp",
    "tgn:placetype":[
        "aat:300008699"
    ]
},
  "bbox": [],
  "geometry": {"coordinates":[-77.45,36.1833],"type":"Point"}
}