<<<<<<< HEAD
{
  "id": 2705831,
  "type": "Feature",
  "properties": {
    "tgn:hierarchy":[
        "tgn:2705831",
        "tgn:1000001",
        "tgn:1002240",
        "tgn:7012149",
        "tgn:7007255",
        "tgn:7029392"
    ],
    "tgn:id":2705831,
    "tgn:name":"Sutton Branch",
    "tgn:placetype":[
        "aat:300008699"
    ]
},
  "bbox": [],
  "geometry": {"coordinates":[-83.1,38.4],"type":"Point"}
}
=======
{"geometry":{"type":"Point","coordinates":[-83.100000,38.400000]},"type":"Feature","properties":{"hierarchy":["tgn:2705831","tgn:1000001","tgn:1002240","tgn:7012149","tgn:7007255","tgn:7029392"],"placetype":["aat:300008699"],"id":2705831,"name:xx":"Sutton Branch"}}
>>>>>>> 03f74aca74312dbeaf24d7e61306dd6a786dc3d0
