{
  "id": 7583685,
  "type": "Feature",
  "properties": {
    "tgn:hierarchy":[
        "tgn:7583685",
        "tgn:1000004",
        "tgn:7000198",
        "tgn:7016722",
        "tgn:7029392"
    ],
    "tgn:id":7583685,
    "tgn:name:en":"Daroni",
    "tgn:placetype":[
        "aat:300008347"
    ]
},
  "bbox": [],
  "geometry": {"coordinates":[78.654232,24.659537],"type":"Point"}
}