{
  "id": 2591412,
  "type": "Feature",
  "properties": {
    "tgn:hierarchy":[
        "tgn:2591412",
        "tgn:1000001",
        "tgn:7006451",
        "tgn:2000092",
        "tgn:7012149",
        "tgn:7029392"
    ],
    "tgn:id":2591412,
    "tgn:name":"Polson Dam Draw",
    "tgn:placetype":[
        "aat:300008761"
    ]
},
  "bbox": [],
  "geometry": {"coordinates":[-112.35,35.3167],"type":"Point"}
}