{
  "id": 2640367,
  "type": "Feature",
  "properties": {
    "tgn:hierarchy":[
        "tgn:2640367",
        "tgn:1000001",
        "tgn:7012149",
        "tgn:2002088",
        "tgn:7007826",
        "tgn:7029392"
    ],
    "tgn:id":2640367,
    "tgn:name":"San Felipe Springs",
    "tgn:placetype":[
        "aat:300008697"
    ]
},
  "bbox": [],
  "geometry": {"coordinates":[-100.8667,29.3667],"type":"Point"}
}