{
  "id": 2283230,
  "type": "Feature",
  "properties": {
    "tgn:hierarchy":[
        "tgn:2283230",
        "tgn:1000001",
        "tgn:7012149",
        "tgn:7007826",
        "tgn:7029392"
    ],
    "tgn:id":2283230,
    "tgn:name":"Delba Creek",
    "tgn:placetype":[
        "aat:300008706"
    ]
},
  "bbox": [],
  "geometry": {"coordinates":[-96.3333,33.4167],"type":"Point"}
}