{
  "id": 2490231,
  "type": "Feature",
  "properties": {
    "tgn:hierarchy":[
        "tgn:2490231",
        "tgn:1000001",
        "tgn:7012149",
        "tgn:2002119",
        "tgn:7007827",
        "tgn:7029392"
    ],
    "tgn:id":2490231,
    "tgn:name":"Mancos Canyon",
    "tgn:placetype":[
        "aat:300008761"
    ]
},
  "bbox": [],
  "geometry": {"coordinates":[-110.3833,37.5833],"type":"Point"}
}