{
  "id": 7135353,
  "type": "Feature",
  "properties": {
    "tgn:hierarchy":[
        "tgn:7135353",
        "tgn:1000003",
        "tgn:7003682",
        "tgn:7000084",
        "tgn:7029392"
    ],
    "tgn:id":7135353,
    "tgn:name":"Molsberger Kopf",
    "tgn:placetype":[
        "aat:300008777"
    ]
},
  "bbox": [],
  "geometry": {"coordinates":[7.75,50.183333],"type":"Point"}
}