<<<<<<< HEAD
{
  "id": 7023266,
  "type": "Feature",
  "properties": {
    "tgn:hierarchy":[
        "tgn:7023266",
        "tgn:1000001",
        "tgn:7012149",
        "tgn:7007251",
        "tgn:7029392"
    ],
    "tgn:id":7023266,
    "tgn:name":"Little Piasa Creek",
    "tgn:placetype":[
        "aat:300008706"
    ]
},
  "bbox": [],
  "geometry": {"coordinates":[-90.1167,39.0667],"type":"Point"}
}
=======
{"geometry":{"type":"Point","coordinates":[-90.116700,39.066700]},"type":"Feature","properties":{"hierarchy":["tgn:7023266","tgn:1000001","tgn:7012149","tgn:7007251","tgn:7029392"],"placetype":["aat:300008706"],"id":7023266,"name:xx":"Little Piasa Creek"}}
>>>>>>> 03f74aca74312dbeaf24d7e61306dd6a786dc3d0
