{
  "id": 2227891,
  "type": "Feature",
  "properties": {
    "tgn:hierarchy":[
        "tgn:2227891",
        "tgn:1000001",
        "tgn:7012149",
        "tgn:2000975",
        "tgn:7007520",
        "tgn:7029392"
    ],
    "tgn:id":2227891,
    "tgn:name":"Cedar Bank",
    "tgn:placetype":[
        "aat:300008347"
    ]
},
  "bbox": [],
  "geometry": {"coordinates":[-87.2667,46.2833],"type":"Point"}
}