{
  "id": 7543415,
  "type": "Feature",
  "properties": {
    "tgn:hierarchy":[
        "tgn:7543415",
        "tgn:7001242",
        "tgn:7016833",
        "tgn:7001335",
        "tgn:7029392"
    ],
    "tgn:id":7543415,
    "tgn:name:en":"Yamit",
    "tgn:placetype":[
        "aat:300008057"
    ]
},
  "bbox": [],
  "geometry": {"coordinates":[34.167899,31.275438],"type":"Point"}
}