{
  "id": 1135384,
  "type": "Feature",
  "properties": {
    "tgn:hierarchy":[
        "tgn:1135384",
        "tgn:1000001",
        "tgn:7012149",
        "tgn:7014612",
        "tgn:7007568",
        "tgn:7029392"
    ],
    "tgn:id":1135384,
    "tgn:name":"Sheldon Brook",
    "tgn:placetype":[
        "aat:300008703"
    ]
},
  "bbox": [],
  "geometry": {"coordinates":[-73.8167,41.05],"type":"Point"}
}