{
  "id": 2201858,
  "type": "Feature",
  "properties": {
    "tgn:hierarchy":[
        "tgn:2201858",
        "tgn:1000001",
        "tgn:1002479",
        "tgn:7012149",
        "tgn:7007240",
        "tgn:7029392"
    ],
    "tgn:id":2201858,
    "tgn:name":"Buck Hammock",
    "tgn:placetype":[
        "aat:300008791"
    ]
},
  "bbox": [],
  "geometry": {"coordinates":[-82.3833,28.0667],"type":"Point"}
}