{
  "id": 2309331,
  "type": "Feature",
  "properties": {
    "tgn:hierarchy":[
        "tgn:2309331",
        "tgn:1000001",
        "tgn:7012149",
        "tgn:2002019",
        "tgn:7007826",
        "tgn:7029392"
    ],
    "tgn:id":2309331,
    "tgn:name":"East Sycamore Creek",
    "tgn:placetype":[
        "aat:300008706"
    ]
},
  "bbox": [],
  "geometry": {"coordinates":[-99.55,30.45],"type":"Point"}
}