{
  "id": 2551388,
  "type": "Feature",
  "properties": {
    "tgn:hierarchy":[
        "tgn:2551388",
        "tgn:1000001",
        "tgn:7016172",
        "tgn:7012149",
        "tgn:2000151",
        "tgn:7029392"
    ],
    "tgn:id":2551388,
    "tgn:name":"Number 1, Ditch",
    "tgn:placetype":[
        "aat:300006075"
    ]
},
  "bbox": [],
  "geometry": {"coordinates":[-90.0833,35.5167],"type":"Point"}
}