{
  "id": 2598083,
  "type": "Feature",
  "properties": {
    "tgn:hierarchy":[
        "tgn:2598083",
        "tgn:1000001",
        "tgn:7012149",
        "tgn:2000990",
        "tgn:7007520",
        "tgn:7029392"
    ],
    "tgn:id":2598083,
    "tgn:name":"Presque Isle",
    "tgn:placetype":[
        "aat:300008850"
    ]
},
  "bbox": [],
  "geometry": {"coordinates":[-83.4833,45.35],"type":"Point"}
}