{
  "id": 7392434,
  "type": "Feature",
  "properties": {
    "tgn:hierarchy":[
        "tgn:7392434",
        "tgn:1000001",
        "tgn:1001960",
        "tgn:7005560",
        "tgn:7029392"
    ],
    "tgn:id":7392434,
    "tgn:name":"El Jacalito",
    "tgn:placetype":[
        "aat:300008347"
    ]
},
  "bbox": [],
  "geometry": {"coordinates":[-110.630278,30.878611],"type":"Point"}
}