{
  "id": 7169310,
  "type": "Feature",
  "properties": {
    "tgn:hierarchy":[
        "tgn:7169310",
        "tgn:1000003",
        "tgn:7003682",
        "tgn:7000084",
        "tgn:7029392"
    ],
    "tgn:id":7169310,
    "tgn:name":"Heulingshof",
    "tgn:placetype":[
        "aat:300000206"
    ]
},
  "bbox": [],
  "geometry": {"coordinates":[7.133333,50.433333],"type":"Point"}
}