<<<<<<< HEAD
{
  "id": 2764420,
  "type": "Feature",
  "properties": {
    "tgn:hierarchy":[
        "tgn:2764420",
        "tgn:1000001",
        "tgn:7012149",
        "tgn:2002195",
        "tgn:7007919",
        "tgn:7029392"
    ],
    "tgn:id":2764420,
    "tgn:name":"Whetstone Ridge",
    "tgn:placetype":[
        "aat:300266640"
    ]
},
  "bbox": [],
  "geometry": {"coordinates":[-82.3167,36.9],"type":"Point"}
}
=======
{"geometry":{"type":"Point","coordinates":[-82.316700,36.900000]},"type":"Feature","properties":{"hierarchy":["tgn:2764420","tgn:1000001","tgn:7012149","tgn:2002195","tgn:7007919","tgn:7029392"],"placetype":["aat:300266640"],"id":2764420,"name:xx":"Whetstone Ridge"}}
>>>>>>> 03f74aca74312dbeaf24d7e61306dd6a786dc3d0
