<<<<<<< HEAD
{
  "id": 7361397,
  "type": "Feature",
  "properties": {
    "tgn:hierarchy":[
        "tgn:7361397",
        "tgn:7005586",
        "tgn:1000001",
        "tgn:7005560",
        "tgn:7029392"
    ],
    "tgn:id":7361397,
    "tgn:name":"El Izote",
    "tgn:placetype":[
        "aat:300008347"
    ]
},
  "bbox": [],
  "geometry": {"coordinates":[-104.366667,19.85],"type":"Point"}
}
=======
{"geometry":{"type":"Point","coordinates":[-104.366667,19.850000]},"type":"Feature","properties":{"hierarchy":["tgn:7361397","tgn:7005586","tgn:1000001","tgn:7005560","tgn:7029392"],"placetype":["aat:300008347"],"id":7361397,"name:xx":"El Izote"}}
>>>>>>> 03f74aca74312dbeaf24d7e61306dd6a786dc3d0
