{
  "id": 7277613,
  "type": "Feature",
  "properties": {
    "tgn:hierarchy":[
        "tgn:7277613",
        "tgn:1001702",
        "tgn:1000049",
        "tgn:1000002",
        "tgn:7029392"
    ],
    "tgn:id":7277613,
    "tgn:name":"William, Punta",
    "tgn:placetype":[
        "aat:300386846"
    ]
},
  "bbox": [],
  "geometry": {"coordinates":[-74.416667,-49.15],"type":"Point"}
}