{
  "id": 7356925,
  "type": "Feature",
  "properties": {
    "tgn:hierarchy":[
        "tgn:7356925",
        "tgn:1001853",
        "tgn:1000001",
        "tgn:7005560",
        "tgn:7029392"
    ],
    "tgn:id":7356925,
    "tgn:name":"Chiquero",
    "tgn:placetype":[
        "aat:300008347"
    ]
},
  "bbox": [],
  "geometry": {"coordinates":[-102.316667,26.816667],"type":"Point"}
}