{
  "id": 1062721,
  "type": "Feature",
  "properties": {
    "tgn:hierarchy":[
        "tgn:1062721",
        "tgn:1000003",
        "tgn:1000398",
        "tgn:1000097",
        "tgn:7029392"
    ],
    "tgn:id":1062721,
    "tgn:name":"\u00d6verum",
    "tgn:placetype":[
        "aat:300008347"
    ]
},
  "bbox": [],
  "geometry": {"coordinates":[16.3333,57.9667],"type":"Point"}
}