{
  "id": 7390447,
  "type": "Feature",
  "properties": {
    "tgn:hierarchy":[
        "tgn:7390447",
        "tgn:1000001",
        "tgn:7005589",
        "tgn:7005560",
        "tgn:7029392"
    ],
    "tgn:id":7390447,
    "tgn:name":"Rancho La Bandera",
    "tgn:placetype":[
        "aat:300008347"
    ]
},
  "bbox": [],
  "geometry": {"coordinates":[-100.066667,27.533333],"type":"Point"}
}