{
  "id": 1138340,
  "type": "Feature",
  "properties": {
    "tgn:hierarchy":[
        "tgn:1138340",
        "tgn:1000004",
        "tgn:7011523",
        "tgn:7002435",
        "tgn:7029392"
    ],
    "tgn:id":1138340,
    "tgn:name":"Ruzayevka",
    "tgn:placetype":[
        "aat:300008347"
    ]
},
  "bbox": [],
  "geometry": {"coordinates":[44.9167,54.0667],"type":"Point"}
}