<<<<<<< HEAD
{
  "id": 7373295,
  "type": "Feature",
  "properties": {
    "tgn:hierarchy":[
        "tgn:7373295",
        "tgn:7005586",
        "tgn:1000001",
        "tgn:7005560",
        "tgn:7029392"
    ],
    "tgn:id":7373295,
    "tgn:name":"La Garru\u00f1a",
    "tgn:placetype":[
        "aat:300000241"
    ]
},
  "bbox": [],
  "geometry": {"coordinates":[-103.133333,20.95],"type":"Point"}
}
=======
{"geometry":{"type":"Point","coordinates":[-103.133333,20.950000]},"type":"Feature","properties":{"hierarchy":["tgn:7373295","tgn:7005586","tgn:1000001","tgn:7005560","tgn:7029392"],"placetype":["aat:300000241"],"id":7373295,"name:xx":"La Garru\u00f1a"}}
>>>>>>> 03f74aca74312dbeaf24d7e61306dd6a786dc3d0
