{
  "id": 7419709,
  "type": "Feature",
  "properties": {
    "tgn:hierarchy":[
        "tgn:7419709",
        "tgn:7005579",
        "tgn:1000001",
        "tgn:7005560",
        "tgn:7029392"
    ],
    "tgn:id":7419709,
    "tgn:name":"Juan Grande",
    "tgn:placetype":[
        "aat:300008347"
    ]
},
  "bbox": [],
  "geometry": {"coordinates":[-101.925,21.961111],"type":"Point"}
}