{
  "id": 1112636,
  "type": "Feature",
  "properties": {
    "tgn:hierarchy":[
        "tgn:1112636",
        "tgn:7001199",
        "tgn:7003494",
        "tgn:1000003",
        "tgn:1000078",
        "tgn:7029392"
    ],
    "tgn:id":1112636,
    "tgn:name":"Ballyteige Bay",
    "tgn:placetype":[
        "aat:300132316"
    ]
},
  "bbox": [],
  "geometry": {"coordinates":[-6.65,52.1833],"type":"Point"}
}