{
  "id": 2416279,
  "type": "Feature",
  "properties": {
    "tgn:hierarchy":[
        "tgn:2416279",
        "tgn:1000001",
        "tgn:7012149",
        "tgn:2002009",
        "tgn:7007826",
        "tgn:7029392"
    ],
    "tgn:id":2416279,
    "tgn:name":"J and E Junction",
    "tgn:placetype":[
        "aat:300008347"
    ]
},
  "bbox": [],
  "geometry": {"coordinates":[-93.8833,30.6667],"type":"Point"}
}