{
  "id": 2737917,
  "type": "Feature",
  "properties": {
    "tgn:hierarchy":[
        "tgn:2737917",
        "tgn:1000001",
        "tgn:7012149",
        "tgn:7019676",
        "tgn:7007566",
        "tgn:7029392"
    ],
    "tgn:id":2737917,
    "tgn:name":"US Minning Section Six",
    "tgn:placetype":[
        "aat:300000390"
    ]
},
  "bbox": [],
  "geometry": {"coordinates":[-108.8833,35.55],"type":"Point"}
}