{
  "id": 2144333,
  "type": "Feature",
  "properties": {
    "tgn:hierarchy":[
        "tgn:2144333",
        "tgn:1000001",
        "tgn:7012149",
        "tgn:7007157",
        "tgn:1002956",
        "tgn:7029392"
    ],
    "tgn:id":2144333,
    "tgn:name":"Baker Ridge",
    "tgn:placetype":[
        "aat:300266640"
    ]
},
  "bbox": [],
  "geometry": {"coordinates":[-118.5167,35.8333],"type":"Point"}
}