{
  "id": 7430292,
  "type": "Feature",
  "properties": {
    "tgn:hierarchy":[
        "tgn:7430292",
        "tgn:1001853",
        "tgn:1000001",
        "tgn:7005560",
        "tgn:7029392"
    ],
    "tgn:id":7430292,
    "tgn:name":"Las Morenas",
    "tgn:placetype":[
        "aat:300008347"
    ]
},
  "bbox": [],
  "geometry": {"coordinates":[-103.383333,26.583333],"type":"Point"}
}