{
  "id": 1113167,
  "type": "Feature",
  "properties": {
    "tgn:hierarchy":[
        "tgn:1113167",
        "tgn:7002444",
        "tgn:1000003",
        "tgn:7008082",
        "tgn:7008591",
        "tgn:7029392"
    ],
    "tgn:id":1113167,
    "tgn:name:en":"Inchard, Loch",
    "tgn:placetype":[
        "aat:300132316"
    ]
},
  "bbox": [],
  "geometry": {"coordinates":[-5.066667,58.45],"type":"Point"}
}