{
  "id": 2704760,
  "type": "Feature",
  "properties": {
    "tgn:hierarchy":[
        "tgn:2704760",
        "tgn:1000001",
        "tgn:7012149",
        "tgn:7014287",
        "tgn:7007568",
        "tgn:7029392"
    ],
    "tgn:id":2704760,
    "tgn:name":"Sunset Hill",
    "tgn:placetype":[
        "aat:300008798"
    ]
},
  "bbox": [],
  "geometry": {"coordinates":[-75.3833,43.0333],"type":"Point"}
}