{
  "id": 2394517,
  "type": "Feature",
  "properties": {
    "tgn:hierarchy":[
        "tgn:2394517",
        "tgn:1000001",
        "tgn:2000264",
        "tgn:7012149",
        "tgn:7007240",
        "tgn:7029392"
    ],
    "tgn:id":2394517,
    "tgn:name":"Hogpen Creek",
    "tgn:placetype":[
        "aat:300008706"
    ]
},
  "bbox": [],
  "geometry": {"coordinates":[-81.45,30.2833],"type":"Point"}
}