{
  "id": 7281460,
  "type": "Feature",
  "properties": {
    "tgn:hierarchy":[
        "tgn:7281460",
        "tgn:1001702",
        "tgn:1000049",
        "tgn:1000002",
        "tgn:7029392"
    ],
    "tgn:id":7281460,
    "tgn:name":"Semillero, Grupo",
    "tgn:placetype":[
        "aat:300008791"
    ]
},
  "bbox": [],
  "geometry": {"coordinates":[-73.75,-52.833333],"type":"Point"}
}