{
  "id": 2262423,
  "type": "Feature",
  "properties": {
    "tgn:hierarchy":[
        "tgn:2262423",
        "tgn:1000001",
        "tgn:2000921",
        "tgn:7012149",
        "tgn:7007515",
        "tgn:7029392"
    ],
    "tgn:id":2262423,
    "tgn:name":"Cow Hill",
    "tgn:placetype":[
        "aat:300008798"
    ]
},
  "bbox": [],
  "geometry": {"coordinates":[-70.2333,44.4667],"type":"Point"}
}