{
  "id": 2319262,
  "type": "Feature",
  "properties": {
    "tgn:hierarchy":[
        "tgn:2319262",
        "tgn:1000001",
        "tgn:2001583",
        "tgn:7012149",
        "tgn:7007705",
        "tgn:7029392"
    ],
    "tgn:id":2319262,
    "tgn:name":"Estes Coulee",
    "tgn:placetype":[
        "aat:300008761"
    ]
},
  "bbox": [],
  "geometry": {"coordinates":[-103.9833,47.75],"type":"Point"}
}