{
  "id": 2318046,
  "type": "Feature",
  "properties": {
    "tgn:hierarchy":[
        "tgn:2318046",
        "tgn:1000001",
        "tgn:7012149",
        "tgn:2000836",
        "tgn:7007255",
        "tgn:7029392"
    ],
    "tgn:id":2318046,
    "tgn:name":"Enoch Fork",
    "tgn:placetype":[
        "aat:300008699"
    ]
},
  "bbox": [],
  "geometry": {"coordinates":[-83.55,37.3167],"type":"Point"}
}