{
  "id": 2731826,
  "type": "Feature",
  "properties": {
    "tgn:hierarchy":[
        "tgn:2731826",
        "tgn:1000001",
        "tgn:2000921",
        "tgn:7012149",
        "tgn:7007515",
        "tgn:7029392"
    ],
    "tgn:id":2731826,
    "tgn:name":"Tumbledown Brook",
    "tgn:placetype":[
        "aat:300008699"
    ]
},
  "bbox": [],
  "geometry": {"coordinates":[-70.5333,44.7333],"type":"Point"}
}