{
  "id": 7117861,
  "type": "Feature",
  "properties": {
    "tgn:hierarchy":[
        "tgn:7117861",
        "tgn:7003669",
        "tgn:1000003",
        "tgn:7000084",
        "tgn:7029392"
    ],
    "tgn:id":7117861,
    "tgn:name":"\u00d6denkatzbach",
    "tgn:placetype":[
        "aat:300000206"
    ]
},
  "bbox": [],
  "geometry": {"coordinates":[12.55,48.466667],"type":"Point"}
}