{
  "id": 7429078,
  "type": "Feature",
  "properties": {
    "tgn:hierarchy":[
        "tgn:7429078",
        "tgn:1000001",
        "tgn:7005595",
        "tgn:7005560",
        "tgn:7029392"
    ],
    "tgn:id":7429078,
    "tgn:name":"Guiltapa",
    "tgn:placetype":[
        "aat:300008347"
    ]
},
  "bbox": [],
  "geometry": {"coordinates":[-106.366667,24.15],"type":"Point"}
}