<<<<<<< HEAD
{
  "id": 7115617,
  "type": "Feature",
  "properties": {
    "tgn:hierarchy":[
        "tgn:7115617",
        "tgn:1000003",
        "tgn:7003685",
        "tgn:7000084",
        "tgn:7029392"
    ],
    "tgn:id":7115617,
    "tgn:name":"Oberw\u00fcrschnitz",
    "tgn:placetype":[
        "aat:300008347"
    ]
},
  "bbox": [],
  "geometry": {"coordinates":[12.233333,50.383333],"type":"Point"}
}
=======
{"geometry":{"type":"Point","coordinates":[12.233333,50.383333]},"type":"Feature","properties":{"hierarchy":["tgn:7115617","tgn:1000003","tgn:7003685","tgn:7000084","tgn:7029392"],"placetype":["aat:300008347"],"id":7115617,"name:xx":"Oberw\u00fcrschnitz"}}
>>>>>>> 03f74aca74312dbeaf24d7e61306dd6a786dc3d0
