{
  "id": 7408892,
  "type": "Feature",
  "properties": {
    "tgn:hierarchy":[
        "tgn:7408892",
        "tgn:1000001",
        "tgn:7005590",
        "tgn:7005560",
        "tgn:7029392"
    ],
    "tgn:id":7408892,
    "tgn:name":"Pino Real",
    "tgn:placetype":[
        "aat:300008347"
    ]
},
  "bbox": [],
  "geometry": {"coordinates":[-101.013889,19.641667],"type":"Point"}
}