{
  "id": 2190136,
  "type": "Feature",
  "properties": {
    "tgn:hierarchy":[
        "tgn:2190136",
        "tgn:1000001",
        "tgn:7012149",
        "tgn:2000970",
        "tgn:7007520",
        "tgn:7029392"
    ],
    "tgn:id":2190136,
    "tgn:name":"Bowman Lake",
    "tgn:placetype":[
        "aat:300008680"
    ]
},
  "bbox": [],
  "geometry": {"coordinates":[-85.9667,43.8833],"type":"Point"}
}