{
  "id": 2228517,
  "type": "Feature",
  "properties": {
    "tgn:hierarchy":[
        "tgn:2228517",
        "tgn:1000001",
        "tgn:7012149",
        "tgn:2001929",
        "tgn:7007825",
        "tgn:7029392"
    ],
    "tgn:id":2228517,
    "tgn:name":"Cedar Creek",
    "tgn:placetype":[
        "aat:300008706"
    ]
},
  "bbox": [],
  "geometry": {"coordinates":[-85.6167,35.9333],"type":"Point"}
}