{
  "id": 7346758,
  "type": "Feature",
  "properties": {
    "tgn:hierarchy":[
        "tgn:7346758",
        "tgn:7008912",
        "tgn:7030216",
        "tgn:1000003",
        "tgn:1000095",
        "tgn:7029392"
    ],
    "tgn:id":7346758,
    "tgn:name":"Barb\u00e9ns",
    "tgn:placetype":[
        "aat:300008347"
    ]
},
  "bbox": [],
  "geometry": {"coordinates":[1.016459,41.677615],"type":"Point"}
}