{
  "id": 2517584,
  "type": "Feature",
  "properties": {
    "tgn:hierarchy":[
        "tgn:2517584",
        "tgn:1000001",
        "tgn:7012149",
        "tgn:1002636",
        "tgn:7007708",
        "tgn:7029392"
    ],
    "tgn:id":2517584,
    "tgn:name":"Minto Creek",
    "tgn:placetype":[
        "aat:300008706"
    ]
},
  "bbox": [],
  "geometry": {"coordinates":[-122.3833,44.75],"type":"Point"}
}