{
  "id": 7282499,
  "type": "Feature",
  "properties": {
    "tgn:hierarchy":[
        "tgn:7282499",
        "tgn:1001692",
        "tgn:1000049",
        "tgn:1000002",
        "tgn:7029392"
    ],
    "tgn:id":7282499,
    "tgn:name":"Petrenco, Estero",
    "tgn:placetype":[
        "aat:300008699"
    ]
},
  "bbox": [],
  "geometry": {"coordinates":[-72.45,-39.133333],"type":"Point"}
}