{
  "id": 2358516,
  "type": "Feature",
  "properties": {
    "tgn:hierarchy":[
        "tgn:2358516",
        "tgn:1000001",
        "tgn:2000469",
        "tgn:7012149",
        "tgn:7007250",
        "tgn:7029392"
    ],
    "tgn:id":2358516,
    "tgn:name":"Grandad Creek",
    "tgn:placetype":[
        "aat:300008706"
    ]
},
  "bbox": [],
  "geometry": {"coordinates":[-115.8667,46.7833],"type":"Point"}
}