{
  "id": 2129478,
  "type": "Feature",
  "properties": {
    "tgn:hierarchy":[
        "tgn:2129478",
        "tgn:1000001",
        "tgn:2001265",
        "tgn:7012149",
        "tgn:7007524",
        "tgn:7029392"
    ],
    "tgn:id":2129478,
    "tgn:name":"Alkali Creek",
    "tgn:placetype":[
        "aat:300008706"
    ]
},
  "bbox": [],
  "geometry": {"coordinates":[-104.7333,46.0333],"type":"Point"}
}