{
  "id": 7575301,
  "type": "Feature",
  "properties": {
    "tgn:hierarchy":[
        "tgn:7575301",
        "tgn:1000004",
        "tgn:1001832",
        "tgn:7000198",
        "tgn:7029392"
    ],
    "tgn:id":7575301,
    "tgn:name:en":"Mah\u0101k\u0101l",
    "tgn:placetype":[
        "aat:300008347"
    ]
},
  "bbox": [],
  "geometry": {"coordinates":[92.492612,24.837347],"type":"Point"}
}