<<<<<<< HEAD
{
  "id": 7481065,
  "type": "Feature",
  "properties": {
    "tgn:hierarchy":[
        "tgn:7481065",
        "tgn:1000004",
        "tgn:7001014",
        "tgn:1000141",
        "tgn:7029392"
    ],
    "tgn:id":7481065,
    "tgn:name":"Mailiao Diwu Gongmu",
    "tgn:placetype":[
        "aat:300266755"
    ]
},
  "bbox": [],
  "geometry": {"coordinates":[120.232222,23.7875],"type":"Point"}
}
=======
{"geometry":{"type":"Point","coordinates":[120.232222,23.787500]},"type":"Feature","properties":{"hierarchy":["tgn:7481065","tgn:1000004","tgn:7001014","tgn:1000141","tgn:7029392"],"placetype":["aat:300266755"],"id":7481065,"name:xx":"Mailiao Diwu Gongmu"}}
>>>>>>> 03f74aca74312dbeaf24d7e61306dd6a786dc3d0
