{
  "id": 7275313,
  "type": "Feature",
  "properties": {
    "tgn:hierarchy":[
        "tgn:7275313",
        "tgn:1001695",
        "tgn:1000049",
        "tgn:1000002",
        "tgn:7029392"
    ],
    "tgn:id":7275313,
    "tgn:name":"Turca, Loma de la",
    "tgn:placetype":[
        "aat:300387002"
    ]
},
  "bbox": [],
  "geometry": {"coordinates":[-72.016667,-34.183333],"type":"Point"}
}