{
  "id": 2358348,
  "type": "Feature",
  "properties": {
    "tgn:hierarchy":[
        "tgn:2358348",
        "tgn:1000001",
        "tgn:7012149",
        "tgn:1002691",
        "tgn:7007826",
        "tgn:7029392"
    ],
    "tgn:id":2358348,
    "tgn:name":"Grand Lake",
    "tgn:placetype":[
        "aat:300008680"
    ]
},
  "bbox": [],
  "geometry": {"coordinates":[-95.4667,30.25],"type":"Point"}
}