{
  "id": 2415770,
  "type": "Feature",
  "properties": {
    "tgn:hierarchy":[
        "tgn:2415770",
        "tgn:1000001",
        "tgn:2001786",
        "tgn:7012149",
        "tgn:7007713",
        "tgn:7029392"
    ],
    "tgn:id":2415770,
    "tgn:name":"Ivanhoe",
    "tgn:placetype":[
        "aat:300008347"
    ]
},
  "bbox": [],
  "geometry": {"coordinates":[-103.6833,43.4667],"type":"Point"}
}