{
  "id": 2696181,
  "type": "Feature",
  "properties": {
    "tgn:hierarchy":[
        "tgn:2696181",
        "tgn:2000663",
        "tgn:1000001",
        "tgn:7012149",
        "tgn:7007254",
        "tgn:7029392"
    ],
    "tgn:id":2696181,
    "tgn:name":"Stolp Creek",
    "tgn:placetype":[
        "aat:300008706"
    ]
},
  "bbox": [],
  "geometry": {"coordinates":[-98.5167,37.3833],"type":"Point"}
}