{
  "id": 2783146,
  "type": "Feature",
  "properties": {
    "tgn:hierarchy":[
        "tgn:2783146",
        "tgn:1000001",
        "tgn:7019982",
        "tgn:7012149",
        "tgn:7007517",
        "tgn:7029392"
    ],
    "tgn:id":2783146,
    "tgn:name":"Wright Cutoff",
    "tgn:placetype":[
        "aat:300006191"
    ]
},
  "bbox": [],
  "geometry": {"coordinates":[-72.6333,42.1667],"type":"Point"}
}