{
  "id": 2484567,
  "type": "Feature",
  "properties": {
    "tgn:hierarchy":[
        "tgn:2484567",
        "tgn:7002659",
        "tgn:1000001",
        "tgn:7012149",
        "tgn:2000062",
        "tgn:7029392"
    ],
    "tgn:id":2484567,
    "tgn:name":"Laurel Hills",
    "tgn:placetype":[
        "aat:300008347"
    ]
},
  "bbox": [],
  "geometry": {"coordinates":[-87.4667,33.1833],"type":"Point"}
}