{
  "id": 7502775,
  "type": "Feature",
  "properties": {
    "tgn:hierarchy":[
        "tgn:7502775",
        "tgn:7487020",
        "tgn:1000004",
        "tgn:1000141",
        "tgn:7029392"
    ],
    "tgn:id":7502775,
    "tgn:name":"Guishan",
    "tgn:placetype":[
        "aat:300008347"
    ]
},
  "bbox": [],
  "geometry": {"coordinates":[120.8635,24.4177],"type":"Point"}
}