{
  "id": 7080316,
  "type": "Feature",
  "properties": {
    "tgn:hierarchy":[
        "tgn:7080316",
        "tgn:7003692",
        "tgn:1000003",
        "tgn:7000084",
        "tgn:7029392"
    ],
    "tgn:id":7080316,
    "tgn:name":"W\u00f6ssingen",
    "tgn:placetype":[
        "aat:300008347"
    ]
},
  "bbox": [],
  "geometry": {"coordinates":[8.601389,49.016111],"type":"Point"}
}