{
  "id": 2476299,
  "type": "Feature",
  "properties": {
    "tgn:hierarchy":[
        "tgn:2476299",
        "tgn:1000001",
        "tgn:7012149",
        "tgn:7007157",
        "tgn:1002894",
        "tgn:7029392"
    ],
    "tgn:id":2476299,
    "tgn:name":"Lunch Creek",
    "tgn:placetype":[
        "aat:300008706"
    ]
},
  "bbox": [],
  "geometry": {"coordinates":[-120.4833,39.6167],"type":"Point"}
}