{
  "id": 7023060,
  "type": "Feature",
  "properties": {
    "tgn:hierarchy":[
        "tgn:7023060",
        "tgn:1000001",
        "tgn:7012149",
        "tgn:7029392"
    ],
    "tgn:id":7023060,
    "tgn:name":"Sassafras Branch",
    "tgn:placetype":[
        "aat:300008699"
    ]
},
  "bbox": [],
  "geometry": {"coordinates":[-83.65,34.85],"type":"Point"}
}