<<<<<<< HEAD
{
  "id": 7023060,
  "type": "Feature",
  "properties": {
    "tgn:hierarchy":[
        "tgn:7023060",
        "tgn:1000001",
        "tgn:7012149",
        "tgn:7029392"
    ],
    "tgn:id":7023060,
    "tgn:name":"Sassafras Branch",
    "tgn:placetype":[
        "aat:300008699"
    ]
},
  "bbox": [],
  "geometry": {"coordinates":[-83.65,34.85],"type":"Point"}
}
=======
{"geometry":{"type":"Point","coordinates":[-83.650000,34.850000]},"type":"Feature","properties":{"hierarchy":["tgn:7023060","tgn:1000001","tgn:7012149","tgn:7029392"],"placetype":["aat:300008699"],"id":7023060,"name:xx":"Sassafras Branch"}}
>>>>>>> 03f74aca74312dbeaf24d7e61306dd6a786dc3d0
