{
  "id": 2101170,
  "type": "Feature",
  "properties": {
    "tgn:hierarchy":[
        "tgn:2101170",
        "tgn:1000001",
        "tgn:7012149",
        "tgn:2001886",
        "tgn:7007825",
        "tgn:7029392"
    ],
    "tgn:id":2101170,
    "tgn:name":"Ramah",
    "tgn:placetype":[
        "aat:300008347",
        "aat:300387210"
    ]
},
  "bbox": [],
  "geometry": {"coordinates":[-87.3167,35.0667],"type":"Point"}
}