<<<<<<< HEAD
{
  "id": 2405430,
  "type": "Feature",
  "properties": {
    "tgn:hierarchy":[
        "tgn:2405430",
        "tgn:1000001",
        "tgn:7012149",
        "tgn:2000809",
        "tgn:7007255",
        "tgn:7029392"
    ],
    "tgn:id":2405430,
    "tgn:name":"Hugh Sparks Hollow",
    "tgn:placetype":[
        "aat:300008761"
    ]
},
  "bbox": [],
  "geometry": {"coordinates":[-82.7333,38.1167],"type":"Point"}
}
=======
{"geometry":{"type":"Point","coordinates":[-82.733300,38.116700]},"type":"Feature","properties":{"hierarchy":["tgn:2405430","tgn:1000001","tgn:7012149","tgn:2000809","tgn:7007255","tgn:7029392"],"placetype":["aat:300008761"],"id":2405430,"name:xx":"Hugh Sparks Hollow"}}
>>>>>>> 03f74aca74312dbeaf24d7e61306dd6a786dc3d0
