{
  "id": 2265677,
  "type": "Feature",
  "properties": {
    "tgn:hierarchy":[
        "tgn:2265677",
        "tgn:1002808",
        "tgn:1000001",
        "tgn:7012149",
        "tgn:7007711",
        "tgn:7029392"
    ],
    "tgn:id":2265677,
    "tgn:name":"Cranston Print Works Pond",
    "tgn:placetype":[
        "aat:300006191"
    ]
},
  "bbox": [],
  "geometry": {"coordinates":[-71.45,41.7833],"type":"Point"}
}