<<<<<<< HEAD
{
  "id": 2256175,
  "type": "Feature",
  "properties": {
    "tgn:hierarchy":[
        "tgn:2256175",
        "tgn:1000001",
        "tgn:7012149",
        "tgn:2000351",
        "tgn:7007248",
        "tgn:7029392"
    ],
    "tgn:id":2256175,
    "tgn:name":"Copper Sandy Creek",
    "tgn:placetype":[
        "aat:300008706"
    ]
},
  "bbox": [],
  "geometry": {"coordinates":[-84.2667,34.1167],"type":"Point"}
}
=======
{"geometry":{"type":"Point","coordinates":[-84.266700,34.116700]},"type":"Feature","properties":{"hierarchy":["tgn:2256175","tgn:1000001","tgn:7012149","tgn:2000351","tgn:7007248","tgn:7029392"],"placetype":["aat:300008706"],"id":2256175,"name:xx":"Copper Sandy Creek"}}
>>>>>>> 03f74aca74312dbeaf24d7e61306dd6a786dc3d0
