{
  "id": 2532027,
  "type": "Feature",
  "properties": {
    "tgn:hierarchy":[
        "tgn:2532027",
        "tgn:7002659",
        "tgn:1000001",
        "tgn:7012149",
        "tgn:2000060",
        "tgn:7029392"
    ],
    "tgn:id":2532027,
    "tgn:name":"Mump Creek",
    "tgn:placetype":[
        "aat:300008706"
    ]
},
  "bbox": [],
  "geometry": {"coordinates":[-85.95,33.3833],"type":"Point"}
}