<<<<<<< HEAD
{
  "id": 2761664,
  "type": "Feature",
  "properties": {
    "tgn:hierarchy":[
        "tgn:2761664",
        "tgn:7030516",
        "tgn:7006450",
        "tgn:1000001",
        "tgn:7012149",
        "tgn:7029392"
    ],
    "tgn:id":2761664,
    "tgn:name":"West Point",
    "tgn:placetype":[
        "aat:300008850"
    ]
},
  "bbox": [],
  "geometry": {"coordinates":[-167.5667,53.4],"type":"Point"}
}
=======
{"geometry":{"type":"Point","coordinates":[-167.566700,53.400000]},"type":"Feature","properties":{"hierarchy":["tgn:2761664","tgn:7030516","tgn:7006450","tgn:1000001","tgn:7012149","tgn:7029392"],"placetype":["aat:300008850"],"id":2761664,"name:xx":"West Point"}}
>>>>>>> 03f74aca74312dbeaf24d7e61306dd6a786dc3d0
