{
  "id": 7563126,
  "type": "Feature",
  "properties": {
    "tgn:hierarchy":[
        "tgn:7563126",
        "tgn:1000004",
        "tgn:7000198",
        "tgn:7016722",
        "tgn:7029392"
    ],
    "tgn:id":7563126,
    "tgn:name:en":"Kil\u0101pur Kal\u0101n",
    "tgn:placetype":[
        "aat:300008347"
    ]
},
  "bbox": [],
  "geometry": {"coordinates":[79.551535,27.715609],"type":"Point"}
}