<<<<<<< HEAD
{
  "id": 7477687,
  "type": "Feature",
  "properties": {
    "tgn:hierarchy":[
        "tgn:7477687",
        "tgn:1000004",
        "tgn:7004300",
        "tgn:1000141",
        "tgn:7029392"
    ],
    "tgn:id":7477687,
    "tgn:name":"Heheng Guoxiao",
    "tgn:placetype":[
        "aat:300006495"
    ]
},
  "bbox": [],
  "geometry": {"coordinates":[119.531495,23.63841],"type":"Point"}
}
=======
{"geometry":{"type":"Point","coordinates":[119.531495,23.638410]},"type":"Feature","properties":{"hierarchy":["tgn:7477687","tgn:1000004","tgn:7004300","tgn:1000141","tgn:7029392"],"placetype":["aat:300006495"],"id":7477687,"name:xx":"Heheng Guoxiao"}}
>>>>>>> 03f74aca74312dbeaf24d7e61306dd6a786dc3d0
