{
  "id": 7477687,
  "type": "Feature",
  "properties": {
    "tgn:hierarchy":[
        "tgn:7477687",
        "tgn:1000004",
        "tgn:7004300",
        "tgn:1000141",
        "tgn:7029392"
    ],
    "tgn:id":7477687,
    "tgn:name":"Heheng Guoxiao",
    "tgn:placetype":[
        "aat:300006495"
    ]
},
  "bbox": [],
  "geometry": {"coordinates":[119.531495,23.63841],"type":"Point"}
}