<<<<<<< HEAD
{
  "id": 2336790,
  "type": "Feature",
  "properties": {
    "tgn:hierarchy":[
        "tgn:2336790",
        "tgn:1000001",
        "tgn:7012149",
        "tgn:2000930",
        "tgn:7007515",
        "tgn:7029392"
    ],
    "tgn:id":2336790,
    "tgn:name":"Fourmile Brook",
    "tgn:placetype":[
        "aat:300008699"
    ]
},
  "bbox": [],
  "geometry": {"coordinates":[-70.3167,45.85],"type":"Point"}
}
=======
{"geometry":{"type":"Point","coordinates":[-70.316700,45.850000]},"type":"Feature","properties":{"hierarchy":["tgn:2336790","tgn:1000001","tgn:7012149","tgn:2000930","tgn:7007515","tgn:7029392"],"placetype":["aat:300008699"],"id":2336790,"name:xx":"Fourmile Brook"}}
>>>>>>> 03f74aca74312dbeaf24d7e61306dd6a786dc3d0
