{
  "id": 2537534,
  "type": "Feature",
  "properties": {
    "tgn:hierarchy":[
        "tgn:2537534",
        "tgn:1000001",
        "tgn:7012149",
        "tgn:2001927",
        "tgn:7007825",
        "tgn:7029392"
    ],
    "tgn:id":2537534,
    "tgn:name":"Negro Ridge Mine",
    "tgn:placetype":[
        "aat:300000390"
    ]
},
  "bbox": [],
  "geometry": {"coordinates":[-87.6833,35.3167],"type":"Point"}
}