{
  "id": 7256529,
  "type": "Feature",
  "properties": {
    "tgn:concordances":{
        "gn:id":"2759700"
    },
    "tgn:hierarchy":[
        "tgn:7256529",
        "tgn:7003619",
        "tgn:1000003",
        "tgn:7016845",
        "tgn:7029392"
    ],
    "tgn:id":7256529,
    "tgn:name:nl":"Appel",
    "tgn:placetype":[
        "aat:300008347"
    ]
},
  "bbox": [],
  "geometry": {"coordinates":[5.55,52.183333],"type":"Point"}
}