{
  "id": 7215974,
  "type": "Feature",
  "properties": {
    "tgn:hierarchy":[
        "tgn:7215974",
        "tgn:7000096",
        "tgn:1000003",
        "tgn:7000084",
        "tgn:7029392"
    ],
    "tgn:id":7215974,
    "tgn:name":"Alt Kr\u00fcssow",
    "tgn:placetype":[
        "aat:300008347"
    ]
},
  "bbox": [],
  "geometry": {"coordinates":[12.266667,53.15],"type":"Point"}
}