<<<<<<< HEAD
{
  "id": 7024691,
  "type": "Feature",
  "properties": {
    "tgn:hierarchy":[
        "tgn:7024691",
        "tgn:7002804",
        "tgn:1000003",
        "tgn:7002793",
        "tgn:1000095",
        "tgn:7029392"
    ],
    "tgn:id":7024691,
    "tgn:name":"Guardamar del Segura",
    "tgn:placetype":[
        "aat:300008347"
    ]
},
  "bbox": [],
  "geometry": {"coordinates":[-0.65,38.1],"type":"Point"}
}
=======
{"geometry":{"type":"Point","coordinates":[-0.650000,38.100000]},"type":"Feature","properties":{"hierarchy":["tgn:7024691","tgn:7002804","tgn:1000003","tgn:7002793","tgn:1000095","tgn:7029392"],"placetype":["aat:300008347"],"id":7024691,"name:xx":"Guardamar del Segura"}}
>>>>>>> 03f74aca74312dbeaf24d7e61306dd6a786dc3d0
