{
  "id": 2546321,
  "type": "Feature",
  "properties": {
    "tgn:hierarchy":[
        "tgn:2546321",
        "tgn:1000001",
        "tgn:7012149",
        "tgn:2001716",
        "tgn:7007708",
        "tgn:7029392"
    ],
    "tgn:id":2546321,
    "tgn:name":"North Fork Groundhog Creek",
    "tgn:placetype":[
        "aat:300008706"
    ]
},
  "bbox": [],
  "geometry": {"coordinates":[-122.3167,43.5667],"type":"Point"}
}