{
  "id": 7261910,
  "type": "Feature",
  "properties": {
    "tgn:concordances":{
        "gn:id":"2754949"
    },
    "tgn:hierarchy":[
        "tgn:7261910",
        "tgn:1000003",
        "tgn:7003624",
        "tgn:7016845",
        "tgn:7029392"
    ],
    "tgn:id":7261910,
    "tgn:name:nl":"Hal",
    "tgn:placetype":[
        "aat:300008347"
    ]
},
  "bbox": [],
  "geometry": {"coordinates":[5.316667,51.633333],"type":"Point"}
}