{
  "id": 7331307,
  "type": "Feature",
  "properties": {
    "tgn:hierarchy":[
        "tgn:7331307",
        "tgn:7002758",
        "tgn:7002821",
        "tgn:1000003",
        "tgn:1000095",
        "tgn:7029392"
    ],
    "tgn:id":7331307,
    "tgn:name":"Lalor\u00edn, Arroyo",
    "tgn:placetype":[
        "aat:300008699"
    ]
},
  "bbox": [],
  "geometry": {"coordinates":[-3.166667,37.183333],"type":"Point"}
}