{
  "id": 2199347,
  "type": "Feature",
  "properties": {
    "tgn:hierarchy":[
        "tgn:2199347",
        "tgn:1000001",
        "tgn:1002218",
        "tgn:7012149",
        "tgn:7007157",
        "tgn:7029392"
    ],
    "tgn:id":2199347,
    "tgn:name":"Brush Creek",
    "tgn:placetype":[
        "aat:300008347"
    ]
},
  "bbox": [],
  "geometry": {"coordinates":[-121.3333,39.6833],"type":"Point"}
}