{
  "id": 2512465,
  "type": "Feature",
  "properties": {
    "tgn:hierarchy":[
        "tgn:2512465",
        "tgn:1000001",
        "tgn:7012149",
        "tgn:7007157",
        "tgn:7014516",
        "tgn:7029392"
    ],
    "tgn:id":2512465,
    "tgn:name":"Mill Creek",
    "tgn:placetype":[
        "aat:300008706"
    ]
},
  "bbox": [],
  "geometry": {"coordinates":[-122.55,38.3167],"type":"Point"}
}