{
  "id": 1014321,
  "type": "Feature",
  "properties": {
    "tgn:hierarchy":[
        "tgn:1014321",
        "tgn:7005685",
        "tgn:7005807",
        "tgn:1000001",
        "tgn:7005801",
        "tgn:7029392"
    ],
    "tgn:id":1014321,
    "tgn:name":"Seal Cove",
    "tgn:placetype":[
        "aat:300008347"
    ]
},
  "bbox": [],
  "geometry": {"coordinates":[-56.3667,49.95],"type":"Point"}
}