{
  "id": 2759237,
  "type": "Feature",
  "properties": {
    "tgn:hierarchy":[
        "tgn:2759237",
        "tgn:1000001",
        "tgn:7012149",
        "tgn:2001866",
        "tgn:7007825",
        "tgn:7029392"
    ],
    "tgn:id":2759237,
    "tgn:name":"West Fork Cassi Creek",
    "tgn:placetype":[
        "aat:300008706"
    ]
},
  "bbox": [],
  "geometry": {"coordinates":[-82.6167,36.0667],"type":"Point"}
}