{
  "id": 2320359,
  "type": "Feature",
  "properties": {
    "tgn:hierarchy":[
        "tgn:2320359",
        "tgn:1000001",
        "tgn:7012149",
        "tgn:7007240",
        "tgn:7029392"
    ],
    "tgn:id":2320359,
    "tgn:name":"Everglades, The",
    "tgn:placetype":[
        "aat:300008905"
    ]
},
  "bbox": [],
  "geometry": {"coordinates":[-80.7667,26.0833],"type":"Point"}
}