{
  "id": 2142983,
  "type": "Feature",
  "properties": {
    "tgn:hierarchy":[
        "tgn:2142983",
        "tgn:1000001",
        "tgn:7012149",
        "tgn:1002356",
        "tgn:7007568",
        "tgn:7029392"
    ],
    "tgn:id":2142983,
    "tgn:name":"Bagdad",
    "tgn:placetype":[
        "aat:300008347"
    ]
},
  "bbox": [],
  "geometry": {"coordinates":[-78.9167,42.4667],"type":"Point"}
}