{
  "id": 2143801,
  "type": "Feature",
  "properties": {
    "tgn:hierarchy":[
        "tgn:2143801",
        "tgn:1000001",
        "tgn:7016172",
        "tgn:7012149",
        "tgn:7029392"
    ],
    "tgn:id":2143801,
    "tgn:name":"Baker Branch",
    "tgn:placetype":[
        "aat:300008699"
    ]
},
  "bbox": [],
  "geometry": {"coordinates":[-91.7167,33.7667],"type":"Point"}
}