{
  "id": 2264449,
  "type": "Feature",
  "properties": {
    "tgn:hierarchy":[
        "tgn:2264449",
        "tgn:1000001",
        "tgn:7012149",
        "tgn:7007568",
        "tgn:7029392"
    ],
    "tgn:id":2264449,
    "tgn:name":"Crabb Kill",
    "tgn:placetype":[
        "aat:300008699"
    ]
},
  "bbox": [],
  "geometry": {"coordinates":[-74.0333,42.95],"type":"Point"}
}