{
  "id": 2733209,
  "type": "Feature",
  "properties": {
    "tgn:hierarchy":[
        "tgn:2733209",
        "tgn:1002309",
        "tgn:1000001",
        "tgn:7012149",
        "tgn:7007565",
        "tgn:7029392"
    ],
    "tgn:id":2733209,
    "tgn:name":"Turkey Point",
    "tgn:placetype":[
        "aat:300008850"
    ]
},
  "bbox": [],
  "geometry": {"coordinates":[-75.1167,39.25],"type":"Point"}
}