{
  "id": 2642444,
  "type": "Feature",
  "properties": {
    "tgn:hierarchy":[
        "tgn:2642444",
        "tgn:1000001",
        "tgn:7012149",
        "tgn:2000230",
        "tgn:7007158",
        "tgn:7029392"
    ],
    "tgn:id":2642444,
    "tgn:name":"Sand Wash",
    "tgn:placetype":[
        "aat:300008761"
    ]
},
  "bbox": [],
  "geometry": {"coordinates":[-108.1833,39.2167],"type":"Point"}
}