<<<<<<< HEAD
{
  "id": 7352821,
  "type": "Feature",
  "properties": {
    "tgn:hierarchy":[
        "tgn:7352821",
        "tgn:1000001",
        "tgn:7005597",
        "tgn:7005560",
        "tgn:7029392"
    ],
    "tgn:id":7352821,
    "tgn:name":"Alto Limpio",
    "tgn:placetype":[
        "aat:300008347"
    ]
},
  "bbox": [],
  "geometry": {"coordinates":[-99.116667,26.3],"type":"Point"}
}
=======
{"geometry":{"type":"Point","coordinates":[-99.116667,26.300000]},"type":"Feature","properties":{"hierarchy":["tgn:7352821","tgn:1000001","tgn:7005597","tgn:7005560","tgn:7029392"],"placetype":["aat:300008347"],"id":7352821,"name:xx":"Alto Limpio"}}
>>>>>>> 03f74aca74312dbeaf24d7e61306dd6a786dc3d0
