<<<<<<< HEAD
{
  "id": 7244480,
  "type": "Feature",
  "properties": {
    "tgn:hierarchy":[
        "tgn:7244480",
        "tgn:7018238",
        "tgn:1000003",
        "tgn:1000063",
        "tgn:4012014",
        "tgn:7029392"
    ],
    "tgn:id":7244480,
    "tgn:name":"Lauzelle, Bois de",
    "tgn:placetype":[
        "aat:300008863"
    ]
},
  "bbox": [],
  "geometry": {"coordinates":[4.6,50.683333],"type":"Point"}
}
=======
{"geometry":{"type":"Point","coordinates":[4.600000,50.683333]},"type":"Feature","properties":{"hierarchy":["tgn:7244480","tgn:7018238","tgn:1000003","tgn:1000063","tgn:4012014","tgn:7029392"],"placetype":["aat:300008863"],"id":7244480,"name:xx":"Lauzelle, Bois de"}}
>>>>>>> 03f74aca74312dbeaf24d7e61306dd6a786dc3d0
