{
  "id": 2466453,
  "type": "Feature",
  "properties": {
    "tgn:hierarchy":[
        "tgn:2466453",
        "tgn:1000001",
        "tgn:7012149",
        "tgn:2000410",
        "tgn:7007248",
        "tgn:7029392"
    ],
    "tgn:id":2466453,
    "tgn:name":"Long Branch",
    "tgn:placetype":[
        "aat:300008699"
    ]
},
  "bbox": [],
  "geometry": {"coordinates":[-83.5167,34.75],"type":"Point"}
}