{
  "id": 2239717,
  "type": "Feature",
  "properties": {
    "tgn:hierarchy":[
        "tgn:2239717",
        "tgn:1000001",
        "tgn:7006451",
        "tgn:7012149",
        "tgn:7029392"
    ],
    "tgn:id":2239717,
    "tgn:name":"Cibecue Canyon",
    "tgn:placetype":[
        "aat:300008761"
    ]
},
  "bbox": [],
  "geometry": {"coordinates":[-110.35,34.0167],"type":"Point"}
}