{
  "id": 7176347,
  "type": "Feature",
  "properties": {
    "tgn:hierarchy":[
        "tgn:7176347",
        "tgn:1000003",
        "tgn:7003677",
        "tgn:7000084",
        "tgn:7029392"
    ],
    "tgn:id":7176347,
    "tgn:name":"Haag",
    "tgn:placetype":[
        "aat:300000206"
    ]
},
  "bbox": [],
  "geometry": {"coordinates":[6.083333,51.083333],"type":"Point"}
}