{
  "id": 7093145,
  "type": "Feature",
  "properties": {
    "tgn:hierarchy":[
        "tgn:7093145",
        "tgn:1000003",
        "tgn:7003676",
        "tgn:7000084",
        "tgn:7029392"
    ],
    "tgn:id":7093145,
    "tgn:name":"Schoh\u00f6fen",
    "tgn:placetype":[
        "aat:300000206"
    ]
},
  "bbox": [],
  "geometry": {"coordinates":[9.183333,53.283333],"type":"Point"}
}