{
  "id": 7383592,
  "type": "Feature",
  "properties": {
    "tgn:hierarchy":[
        "tgn:7383592",
        "tgn:1000001",
        "tgn:1001960",
        "tgn:7005560",
        "tgn:7029392"
    ],
    "tgn:id":7383592,
    "tgn:name":"Rancho Muriotahueca",
    "tgn:placetype":[
        "aat:300000241"
    ]
},
  "bbox": [],
  "geometry": {"coordinates":[-109.716667,27.25],"type":"Point"}
}