{
  "id": 1101463,
  "type": "Feature",
  "properties": {
    "tgn:hierarchy":[
        "tgn:1101463",
        "tgn:7012076",
        "tgn:1000003",
        "tgn:7006660",
        "tgn:7029392"
    ],
    "tgn:id":1101463,
    "tgn:name":"Chomutovskaja Step', zapovednik",
    "tgn:placetype":[
        "aat:300008189"
    ]
},
  "bbox": [],
  "geometry": {"coordinates":[38.1833,47.2833],"type":"Point"}
}