{
  "id": 7281751,
  "type": "Feature",
  "properties": {
    "tgn:hierarchy":[
        "tgn:7281751",
        "tgn:1001768",
        "tgn:1000049",
        "tgn:1000002",
        "tgn:7029392"
    ],
    "tgn:id":7281751,
    "tgn:name":"San Regis, Estero",
    "tgn:placetype":[
        "aat:300008699"
    ]
},
  "bbox": [],
  "geometry": {"coordinates":[-70.733333,-32.716667],"type":"Point"}
}