{
  "id": 7298115,
  "type": "Feature",
  "properties": {
    "tgn:hierarchy":[
        "tgn:7298115",
        "tgn:7002839",
        "tgn:7001158",
        "tgn:1000003",
        "tgn:1000095",
        "tgn:7029392"
    ],
    "tgn:id":7298115,
    "tgn:name":"Siete Picos",
    "tgn:placetype":[
        "aat:300008798"
    ]
},
  "bbox": [],
  "geometry": {"coordinates":[-4.016667,40.783333],"type":"Point"}
}