{
  "id": 2722294,
  "type": "Feature",
  "properties": {
    "tgn:hierarchy":[
        "tgn:2722294",
        "tgn:1000001",
        "tgn:7012149",
        "tgn:1002593",
        "tgn:7007568",
        "tgn:7029392"
    ],
    "tgn:id":2722294,
    "tgn:name":"Tims Creek",
    "tgn:placetype":[
        "aat:300008706"
    ]
},
  "bbox": [],
  "geometry": {"coordinates":[-75.35,43.9833],"type":"Point"}
}