{
  "id": 7194144,
  "type": "Feature",
  "properties": {
    "tgn:hierarchy":[
        "tgn:7194144",
        "tgn:7000096",
        "tgn:1000003",
        "tgn:7000084",
        "tgn:7029392"
    ],
    "tgn:id":7194144,
    "tgn:name":"Der Brand",
    "tgn:placetype":[
        "aat:300055621"
    ]
},
  "bbox": [],
  "geometry": {"coordinates":[13.733333,52.033333],"type":"Point"}
}