<<<<<<< HEAD
{
  "id": 7470976,
  "type": "Feature",
  "properties": {
    "tgn:hierarchy":[
        "tgn:7470976",
        "tgn:1000004",
        "tgn:7001009",
        "tgn:1000141",
        "tgn:7029392"
    ],
    "tgn:id":7470976,
    "tgn:name":"Houli Chezhan",
    "tgn:placetype":[
        "aat:300007783"
    ]
},
  "bbox": [],
  "geometry": {"coordinates":[120.733056,24.309167],"type":"Point"}
}
=======
{"geometry":{"type":"Point","coordinates":[120.733056,24.309167]},"type":"Feature","properties":{"hierarchy":["tgn:7470976","tgn:1000004","tgn:7001009","tgn:1000141","tgn:7029392"],"placetype":["aat:300007783"],"id":7470976,"name:xx":"Houli Chezhan"}}
>>>>>>> 03f74aca74312dbeaf24d7e61306dd6a786dc3d0
