{
  "id": 2467980,
  "type": "Feature",
  "properties": {
    "tgn:hierarchy":[
        "tgn:2467980",
        "tgn:2001001",
        "tgn:1000001",
        "tgn:7012149",
        "tgn:7007521",
        "tgn:7029392"
    ],
    "tgn:id":2467980,
    "tgn:name":"Long Lake",
    "tgn:placetype":[
        "aat:300008680"
    ]
},
  "bbox": [],
  "geometry": {"coordinates":[-96.1667,46.7667],"type":"Point"}
}