{
  "id": 2388245,
  "type": "Feature",
  "properties": {
    "tgn:hierarchy":[
        "tgn:2388245",
        "tgn:1000001",
        "tgn:7016172",
        "tgn:7012149",
        "tgn:7029392"
    ],
    "tgn:id":2388245,
    "tgn:name":"Hickory Knob",
    "tgn:placetype":[
        "aat:300008798"
    ]
},
  "bbox": [],
  "geometry": {"coordinates":[-94.2333,34.95],"type":"Point"}
}