{
  "id": 7339593,
  "type": "Feature",
  "properties": {
    "tgn:hierarchy":[
        "tgn:7339593",
        "tgn:7002836",
        "tgn:7016622",
        "tgn:1000003",
        "tgn:1000095",
        "tgn:7029392"
    ],
    "tgn:id":7339593,
    "tgn:name":"Confital, Playa del",
    "tgn:placetype":[
        "aat:300008816"
    ]
},
  "bbox": [],
  "geometry": {"coordinates":[-16.55,28.016667],"type":"Point"}
}