{
  "id": 7556415,
  "type": "Feature",
  "properties": {
    "tgn:hierarchy":[
        "tgn:7556415",
        "tgn:1000004",
        "tgn:7000198",
        "tgn:7016788",
        "tgn:7029392"
    ],
    "tgn:id":7556415,
    "tgn:name:en":"Phulera",
    "tgn:placetype":[
        "aat:300008347"
    ]
},
  "bbox": [],
  "geometry": {"coordinates":[75.241709,26.87401],"type":"Point"}
}