<<<<<<< HEAD
{
  "id": 7029646,
  "type": "Feature",
  "properties": {
    "tgn:hierarchy":[
        "tgn:7029646",
        "tgn:7002826",
        "tgn:7001158",
        "tgn:1000003",
        "tgn:1000095",
        "tgn:7029392"
    ],
    "tgn:id":7029646,
    "tgn:name:es":"Villarente",
    "tgn:placetype":[
        "aat:300008347"
    ]
},
  "bbox": [],
  "geometry": {"coordinates":[-5.45,42.55],"type":"Point"}
}
=======
{"geometry":{"type":"Point","coordinates":[-5.450000,42.550000]},"type":"Feature","properties":{"hierarchy":["tgn:7029646","tgn:7002826","tgn:7001158","tgn:1000003","tgn:1000095","tgn:7029392"],"placetype":["aat:300008347"],"id":7029646,"name:es":"Villarente"}}
>>>>>>> 03f74aca74312dbeaf24d7e61306dd6a786dc3d0
