{
  "id": 7384019,
  "type": "Feature",
  "properties": {
    "tgn:hierarchy":[
        "tgn:7384019",
        "tgn:7005581",
        "tgn:1000001",
        "tgn:7005560",
        "tgn:7029392"
    ],
    "tgn:id":7384019,
    "tgn:name":"Naqu\u00e9achic",
    "tgn:placetype":[
        "aat:300008347"
    ]
},
  "bbox": [],
  "geometry": {"coordinates":[-107.466667,27.816667],"type":"Point"}
}