{
  "id": 2467793,
  "type": "Feature",
  "properties": {
    "tgn:hierarchy":[
        "tgn:2467793",
        "tgn:1000001",
        "tgn:7012149",
        "tgn:1002787",
        "tgn:7007523",
        "tgn:7029392"
    ],
    "tgn:id":2467793,
    "tgn:name":"Long Knob",
    "tgn:placetype":[
        "aat:300008798"
    ]
},
  "bbox": [],
  "geometry": {"coordinates":[-90.9833,39.35],"type":"Point"}
}