{
  "id": 7263979,
  "type": "Feature",
  "properties": {
    "tgn:hierarchy":[
        "tgn:7263979",
        "tgn:7003614",
        "tgn:1000003",
        "tgn:7016845",
        "tgn:7029392"
    ],
    "tgn:id":7263979,
    "tgn:name:nl":"Lentse Veen",
    "tgn:placetype":[
        "aat:300386887"
    ]
},
  "bbox": [],
  "geometry": {"coordinates":[6.566667,52.766667],"type":"Point"}
}