{
  "id": 2708244,
  "type": "Feature",
  "properties": {
    "tgn:hierarchy":[
        "tgn:2708244",
        "tgn:1000001",
        "tgn:7012149",
        "tgn:2001751",
        "tgn:7007712",
        "tgn:7029392"
    ],
    "tgn:id":2708244,
    "tgn:name":"Switzerland Canal",
    "tgn:placetype":[
        "aat:300006075"
    ]
},
  "bbox": [],
  "geometry": {"coordinates":[-81.0333,32.4333],"type":"Point"}
}