{
  "id": 2439293,
  "type": "Feature",
  "properties": {
    "tgn:hierarchy":[
        "tgn:2439293",
        "tgn:1000001",
        "tgn:2001182",
        "tgn:7012149",
        "tgn:7007523",
        "tgn:7029392"
    ],
    "tgn:id":2439293,
    "tgn:name":"Kirchers Upper Lake",
    "tgn:placetype":[
        "aat:300006191"
    ]
},
  "bbox": [],
  "geometry": {"coordinates":[-94.2333,38.65],"type":"Point"}
}