{
  "id": 7498882,
  "type": "Feature",
  "properties": {
    "tgn:hierarchy":[
        "tgn:7498882",
        "tgn:1000004",
        "tgn:1000959",
        "tgn:1000141",
        "tgn:7029392"
    ],
    "tgn:id":7498882,
    "tgn:name":"Xiaoguanyin Shan",
    "tgn:placetype":[
        "aat:300008798"
    ]
},
  "bbox": [],
  "geometry": {"coordinates":[121.542337,25.188827],"type":"Point"}
}