{
  "id": 2730590,
  "type": "Feature",
  "properties": {
    "tgn:hierarchy":[
        "tgn:2730590",
        "tgn:1000001",
        "tgn:2002323",
        "tgn:7012149",
        "tgn:7007922",
        "tgn:7029392"
    ],
    "tgn:id":2730590,
    "tgn:name":"Trump Lake",
    "tgn:placetype":[
        "aat:300008680"
    ]
},
  "bbox": [],
  "geometry": {"coordinates":[-88.65,45.4667],"type":"Point"}
}