<<<<<<< HEAD
{
  "id": 7361736,
  "type": "Feature",
  "properties": {
    "tgn:hierarchy":[
        "tgn:7361736",
        "tgn:7005581",
        "tgn:1000001",
        "tgn:7005560",
        "tgn:7029392"
    ],
    "tgn:id":7361736,
    "tgn:name":"Rancho El Jonuco",
    "tgn:placetype":[
        "aat:300000241"
    ]
},
  "bbox": [],
  "geometry": {"coordinates":[-106.666667,31.183333],"type":"Point"}
}
=======
{"geometry":{"type":"Point","coordinates":[-106.666667,31.183333]},"type":"Feature","properties":{"hierarchy":["tgn:7361736","tgn:7005581","tgn:1000001","tgn:7005560","tgn:7029392"],"placetype":["aat:300000241"],"id":7361736,"name:xx":"Rancho El Jonuco"}}
>>>>>>> 03f74aca74312dbeaf24d7e61306dd6a786dc3d0
