{
  "id": 7421104,
  "type": "Feature",
  "properties": {
    "tgn:hierarchy":[
        "tgn:7421104",
        "tgn:7005579",
        "tgn:1000001",
        "tgn:7005560",
        "tgn:7029392"
    ],
    "tgn:id":7421104,
    "tgn:name":"Milpillas de Arriba",
    "tgn:placetype":[
        "aat:300008347"
    ]
},
  "bbox": [],
  "geometry": {"coordinates":[-102.533333,21.933333],"type":"Point"}
}