{
  "id": 7285326,
  "type": "Feature",
  "properties": {
    "tgn:hierarchy":[
        "tgn:7285326",
        "tgn:7002464",
        "tgn:1000049",
        "tgn:1000002",
        "tgn:7029392"
    ],
    "tgn:id":7285326,
    "tgn:name":"Poconchile, Cerro",
    "tgn:placetype":[
        "aat:300008795"
    ]
},
  "bbox": [],
  "geometry": {"coordinates":[-70.116667,-18.45],"type":"Point"}
}