{
  "id": 7069475,
  "type": "Feature",
  "properties": {
    "tgn:hierarchy":[
        "tgn:7069475",
        "tgn:1000003",
        "tgn:7003676",
        "tgn:7000084",
        "tgn:7029392"
    ],
    "tgn:id":7069475,
    "tgn:name":"Thurauer Berg",
    "tgn:placetype":[
        "aat:300008777"
    ]
},
  "bbox": [],
  "geometry": {"coordinates":[11.25,52.95],"type":"Point"}
}