{
  "id": 7041076,
  "type": "Feature",
  "properties": {
    "tgn:hierarchy":[
        "tgn:7041076",
        "tgn:7003248",
        "tgn:1000003",
        "tgn:7010380",
        "tgn:1000080",
        "tgn:7029392"
    ],
    "tgn:id":7041076,
    "tgn:name":"San Cataldo, Punta",
    "tgn:placetype":[
        "aat:300386846"
    ]
},
  "bbox": [],
  "geometry": {"coordinates":[16.85,41.133333],"type":"Point"}
}