{
  "id": 7278639,
  "type": "Feature",
  "properties": {
    "tgn:hierarchy":[
        "tgn:7278639",
        "tgn:1001702",
        "tgn:1000049",
        "tgn:1000002",
        "tgn:7029392"
    ],
    "tgn:id":7278639,
    "tgn:name":"Davanzo, Caleta",
    "tgn:placetype":[
        "aat:300132317"
    ]
},
  "bbox": [],
  "geometry": {"coordinates":[-67.583333,-55.833333],"type":"Point"}
}