{
  "id": 7589346,
  "type": "Feature",
  "properties": {
    "tgn:hierarchy":[
        "tgn:7589346",
        "tgn:1000004",
        "tgn:7000198",
        "tgn:7000799",
        "tgn:7029392"
    ],
    "tgn:id":7589346,
    "tgn:name:en":"Pothi",
    "tgn:placetype":[
        "aat:300008347"
    ]
},
  "bbox": [],
  "geometry": {"coordinates":[74.194063,33.324874],"type":"Point"}
}