<<<<<<< HEAD
{
  "id": 7051814,
  "type": "Feature",
  "properties": {
    "tgn:hierarchy":[
        "tgn:7051814",
        "tgn:7003137",
        "tgn:1000003",
        "tgn:7003080",
        "tgn:1000080",
        "tgn:7029392"
    ],
    "tgn:id":7051814,
    "tgn:name":"Illica",
    "tgn:placetype":[
        "aat:300008347"
    ]
},
  "bbox": [],
  "geometry": {"coordinates":[13.25,42.7],"type":"Point"}
}
=======
{"geometry":{"type":"Point","coordinates":[13.250000,42.700000]},"type":"Feature","properties":{"hierarchy":["tgn:7051814","tgn:7003137","tgn:1000003","tgn:7003080","tgn:1000080","tgn:7029392"],"placetype":["aat:300008347"],"id":7051814,"name:xx":"Illica"}}
>>>>>>> 03f74aca74312dbeaf24d7e61306dd6a786dc3d0
