{
  "id": 7005534,
  "type": "Feature",
  "properties": {
    "tgn:hierarchy":[
        "tgn:7005534",
        "tgn:1003488",
        "tgn:1000003",
        "tgn:7002993",
        "tgn:1000080",
        "tgn:7029392"
    ],
    "tgn:id":7005534,
    "tgn:name":"Cordenons",
    "tgn:placetype":[
        "aat:300008347"
    ]
},
  "bbox": [],
  "geometry": {"coordinates":[12.701944,45.989722],"type":"Point"}
}