<<<<<<< HEAD
{
  "id": 2403862,
  "type": "Feature",
  "properties": {
    "tgn:hierarchy":[
        "tgn:2403862",
        "tgn:1000001",
        "tgn:7012149",
        "tgn:2002118",
        "tgn:7007827",
        "tgn:7029392"
    ],
    "tgn:id":2403862,
    "tgn:name":"Howe",
    "tgn:placetype":[
        "aat:300008347"
    ]
},
  "bbox": [],
  "geometry": {"coordinates":[-111.85,40.6333],"type":"Point"}
}
=======
{"geometry":{"type":"Point","coordinates":[-111.850000,40.633300]},"type":"Feature","properties":{"hierarchy":["tgn:2403862","tgn:1000001","tgn:7012149","tgn:2002118","tgn:7007827","tgn:7029392"],"placetype":["aat:300008347"],"id":2403862,"name:xx":"Howe"}}
>>>>>>> 03f74aca74312dbeaf24d7e61306dd6a786dc3d0
