{
  "id": 2386002,
  "type": "Feature",
  "properties": {
    "tgn:hierarchy":[
        "tgn:2386002",
        "tgn:1000001",
        "tgn:7012149",
        "tgn:2001526",
        "tgn:7007709",
        "tgn:7029392"
    ],
    "tgn:id":2386002,
    "tgn:name":"Henry Creek",
    "tgn:placetype":[
        "aat:300008706"
    ]
},
  "bbox": [],
  "geometry": {"coordinates":[-76.5833,35.2333],"type":"Point"}
}