{
  "id": 7146414,
  "type": "Feature",
  "properties": {
    "tgn:hierarchy":[
        "tgn:7146414",
        "tgn:1000003",
        "tgn:7003688",
        "tgn:7000084",
        "tgn:7029392"
    ],
    "tgn:id":7146414,
    "tgn:name":"K\u00f6hnholz",
    "tgn:placetype":[
        "aat:300008347"
    ]
},
  "bbox": [],
  "geometry": {"coordinates":[9.666667,54.666667],"type":"Point"}
}