{
  "id": 1121279,
  "type": "Feature",
  "properties": {
    "tgn:hierarchy":[
        "tgn:1121279",
        "tgn:7012827",
        "tgn:7002454",
        "tgn:1000047",
        "tgn:1000002",
        "tgn:7029392"
    ],
    "tgn:id":1121279,
    "tgn:name":"Apor\u00e9",
    "tgn:placetype":[
        "aat:300008707"
    ]
},
  "bbox": [],
  "geometry": {"coordinates":[-50.95,-19.45],"type":"Point"}
}