{
  "id": 7121215,
  "type": "Feature",
  "properties": {
    "tgn:hierarchy":[
        "tgn:7121215",
        "tgn:1000003",
        "tgn:7003678",
        "tgn:7000084",
        "tgn:7029392"
    ],
    "tgn:id":7121215,
    "tgn:name":"Pfaffenhausen",
    "tgn:placetype":[
        "aat:300008347"
    ]
},
  "bbox": [],
  "geometry": {"coordinates":[9.316667,51.016667],"type":"Point"}
}