{
  "id": 7516282,
  "type": "Feature",
  "properties": {
    "tgn:hierarchy":[
        "tgn:7516282",
        "tgn:1009227",
        "tgn:1000226",
        "tgn:7520095",
        "tgn:1000006",
        "tgn:7029392"
    ],
    "tgn:id":7516282,
    "tgn:name:en":"Left Hand Branch Tadmor River",
    "tgn:placetype":[
        "aat:300008699"
    ]
},
  "bbox": [],
  "geometry": {"coordinates":[172.683333,-41.566667],"type":"Point"}
}