{
  "id": 2679166,
  "type": "Feature",
  "properties": {
    "tgn:hierarchy":[
        "tgn:2679166",
        "tgn:1000001",
        "tgn:7012149",
        "tgn:2000481",
        "tgn:7007250",
        "tgn:7029392"
    ],
    "tgn:id":2679166,
    "tgn:name":"South Fork Lake",
    "tgn:placetype":[
        "aat:300008680"
    ]
},
  "bbox": [],
  "geometry": {"coordinates":[-114.6333,45.0667],"type":"Point"}
}