{
  "id": 7123186,
  "type": "Feature",
  "properties": {
    "tgn:hierarchy":[
        "tgn:7123186",
        "tgn:1000003",
        "tgn:7003676",
        "tgn:7000084",
        "tgn:7029392"
    ],
    "tgn:id":7123186,
    "tgn:name":"Niederlangen",
    "tgn:placetype":[
        "aat:300008347"
    ]
},
  "bbox": [],
  "geometry": {"coordinates":[7.283333,52.85],"type":"Point"}
}