{
  "id": 7063915,
  "type": "Feature",
  "properties": {
    "tgn:hierarchy":[
        "tgn:7063915",
        "tgn:1000003",
        "tgn:7003682",
        "tgn:7000084",
        "tgn:7029392"
    ],
    "tgn:id":7063915,
    "tgn:name":"Altschmiede",
    "tgn:placetype":[
        "aat:300000206"
    ]
},
  "bbox": [],
  "geometry": {"coordinates":[6.333333,49.85],"type":"Point"}
}