{
  "id": 7420041,
  "type": "Feature",
  "properties": {
    "tgn:hierarchy":[
        "tgn:7420041",
        "tgn:7005584",
        "tgn:1000001",
        "tgn:7005560",
        "tgn:7029392"
    ],
    "tgn:id":7420041,
    "tgn:name":"El Durasnillo",
    "tgn:placetype":[
        "aat:300008347"
    ]
},
  "bbox": [],
  "geometry": {"coordinates":[-100.120833,21.542222],"type":"Point"}
}