{
  "id": 2015440,
  "type": "Feature",
  "properties": {
    "tgn:hierarchy":[
        "tgn:2015440",
        "tgn:1000001",
        "tgn:7012149",
        "tgn:2000209",
        "tgn:7007158",
        "tgn:7029392"
    ],
    "tgn:id":2015440,
    "tgn:name":"Deckers",
    "tgn:placetype":[
        "aat:300008347"
    ]
},
  "bbox": [],
  "geometry": {"coordinates":[-105.2167,39.25],"type":"Point"}
}