{
  "id": 7497422,
  "type": "Feature",
  "properties": {
    "tgn:hierarchy":[
        "tgn:7497422",
        "tgn:1000004",
        "tgn:7001013",
        "tgn:1000141",
        "tgn:7029392"
    ],
    "tgn:id":7497422,
    "tgn:name":"Zhongbu Guoxiao",
    "tgn:placetype":[
        "aat:300006495"
    ]
},
  "bbox": [],
  "geometry": {"coordinates":[121.286959,25.009477],"type":"Point"}
}