{
  "id": 7187554,
  "type": "Feature",
  "properties": {
    "tgn:hierarchy":[
        "tgn:7187554",
        "tgn:7003669",
        "tgn:1000003",
        "tgn:7000084",
        "tgn:7029392"
    ],
    "tgn:id":7187554,
    "tgn:name":"Euben",
    "tgn:placetype":[
        "aat:300008347"
    ]
},
  "bbox": [],
  "geometry": {"coordinates":[11.583333,49.983333],"type":"Point"}
}