{
  "id": 2426608,
  "type": "Feature",
  "properties": {
    "tgn:hierarchy":[
        "tgn:2426608",
        "tgn:2001774",
        "tgn:1000001",
        "tgn:7012149",
        "tgn:7007713",
        "tgn:7029392"
    ],
    "tgn:id":2426608,
    "tgn:name":"Jones Island",
    "tgn:placetype":[
        "aat:300008791"
    ]
},
  "bbox": [],
  "geometry": {"coordinates":[-98.05,42.7667],"type":"Point"}
}