{
  "id": 2563086,
  "type": "Feature",
  "properties": {
    "tgn:hierarchy":[
        "tgn:2563086",
        "tgn:1000001",
        "tgn:2001268",
        "tgn:7012149",
        "tgn:7007524",
        "tgn:7029392"
    ],
    "tgn:id":2563086,
    "tgn:name":"Owens Coulee",
    "tgn:placetype":[
        "aat:300008761"
    ]
},
  "bbox": [],
  "geometry": {"coordinates":[-105.9833,46.6167],"type":"Point"}
}