{
  "id": 7132960,
  "type": "Feature",
  "properties": {
    "tgn:hierarchy":[
        "tgn:7132960",
        "tgn:1000003",
        "tgn:7003688",
        "tgn:7000084",
        "tgn:7029392"
    ],
    "tgn:id":7132960,
    "tgn:name":"M\u00fchlenbek",
    "tgn:placetype":[
        "aat:300000745"
    ]
},
  "bbox": [],
  "geometry": {"coordinates":[9.733333,53.95],"type":"Point"}
}