{
  "id": 2358800,
  "type": "Feature",
  "properties": {
    "tgn:hierarchy":[
        "tgn:2358800",
        "tgn:2001002",
        "tgn:1000001",
        "tgn:7012149",
        "tgn:7007521",
        "tgn:7029392"
    ],
    "tgn:id":2358800,
    "tgn:name":"Graning Lake",
    "tgn:placetype":[
        "aat:300008680"
    ]
},
  "bbox": [],
  "geometry": {"coordinates":[-95.1333,47.85],"type":"Point"}
}