{
  "id": 2200476,
  "type": "Feature",
  "properties": {
    "tgn:hierarchy":[
        "tgn:2200476",
        "tgn:1000001",
        "tgn:7006451",
        "tgn:7012149",
        "tgn:2000103",
        "tgn:7029392"
    ],
    "tgn:id":2200476,
    "tgn:name":"Brushy Mountain",
    "tgn:placetype":[
        "aat:300008798"
    ]
},
  "bbox": [],
  "geometry": {"coordinates":[-112.8333,34.8167],"type":"Point"}
}