{
  "id": 2685984,
  "type": "Feature",
  "properties": {
    "tgn:hierarchy":[
        "tgn:2685984",
        "tgn:1000001",
        "tgn:2000950",
        "tgn:7012149",
        "tgn:7007520",
        "tgn:7029392"
    ],
    "tgn:id":2685984,
    "tgn:name":"Spring Brook",
    "tgn:placetype":[
        "aat:300008699"
    ]
},
  "bbox": [],
  "geometry": {"coordinates":[-84.8667,45.2333],"type":"Point"}
}