{
  "id": 7198879,
  "type": "Feature",
  "properties": {
    "tgn:hierarchy":[
        "tgn:7198879",
        "tgn:1000003",
        "tgn:7003677",
        "tgn:7000084",
        "tgn:7029392"
    ],
    "tgn:id":7198879,
    "tgn:name":"Egge-Berg",
    "tgn:placetype":[
        "aat:300008777"
    ]
},
  "bbox": [],
  "geometry": {"coordinates":[8.833333,51.833333],"type":"Point"}
}