{
  "id": 2711952,
  "type": "Feature",
  "properties": {
    "tgn:hierarchy":[
        "tgn:2711952",
        "tgn:7002659",
        "tgn:1000001",
        "tgn:7012149",
        "tgn:2000036",
        "tgn:7029392"
    ],
    "tgn:id":2711952,
    "tgn:name":"Tarrant Spring Branch",
    "tgn:placetype":[
        "aat:300008699"
    ]
},
  "bbox": [],
  "geometry": {"coordinates":[-86.6833,33.6333],"type":"Point"}
}