{
  "id": 7241663,
  "type": "Feature",
  "properties": {
    "tgn:hierarchy":[
        "tgn:7241663",
        "tgn:7003457",
        "tgn:1000003",
        "tgn:1000063",
        "tgn:7018236",
        "tgn:7029392"
    ],
    "tgn:id":7241663,
    "tgn:name":"Ch\u00e2teau de Lilars",
    "tgn:placetype":[
        "aat:300005567"
    ]
},
  "bbox": [],
  "geometry": {"coordinates":[3.766667,50.816667],"type":"Point"}
}