{
  "id": 2738672,
  "type": "Feature",
  "properties": {
    "tgn:hierarchy":[
        "tgn:2738672",
        "tgn:1000001",
        "tgn:7006451",
        "tgn:2000094",
        "tgn:7012149",
        "tgn:7029392"
    ],
    "tgn:id":2738672,
    "tgn:name":"Union Canal",
    "tgn:placetype":[
        "aat:300006075"
    ]
},
  "bbox": [],
  "geometry": {"coordinates":[-109.6667,32.8167],"type":"Point"}
}