{
  "id": 2385305,
  "type": "Feature",
  "properties": {
    "tgn:hierarchy":[
        "tgn:2385305",
        "tgn:1000001",
        "tgn:7012149",
        "tgn:2002180",
        "tgn:7007919",
        "tgn:7029392"
    ],
    "tgn:id":2385305,
    "tgn:name":"Hemp Fork",
    "tgn:placetype":[
        "aat:300008699"
    ]
},
  "bbox": [],
  "geometry": {"coordinates":[-79.5167,36.8333],"type":"Point"}
}