{
  "id": 7466253,
  "type": "Feature",
  "properties": {
    "tgn:hierarchy":[
        "tgn:7466253",
        "tgn:7002444",
        "tgn:1000003",
        "tgn:7008082",
        "tgn:7008591",
        "tgn:7029392"
    ],
    "tgn:id":7466253,
    "tgn:name:en":"Brough Bay",
    "tgn:placetype":[
        "aat:300132316"
    ]
},
  "bbox": [],
  "geometry": {"coordinates":[-3.316667,58.65],"type":"Point"}
}