{
  "id": 2164158,
  "type": "Feature",
  "properties": {
    "tgn:hierarchy":[
        "tgn:2164158",
        "tgn:1000001",
        "tgn:7012149",
        "tgn:2001451",
        "tgn:7007566",
        "tgn:7029392"
    ],
    "tgn:id":2164158,
    "tgn:name":"Bernalillito, Arroyo",
    "tgn:placetype":[
        "aat:300008699"
    ]
},
  "bbox": [],
  "geometry": {"coordinates":[-107.05,35.5167],"type":"Point"}
}