{
  "id": 7586698,
  "type": "Feature",
  "properties": {
    "tgn:hierarchy":[
        "tgn:7586698",
        "tgn:1000004",
        "tgn:7000198",
        "tgn:7000799",
        "tgn:7029392"
    ],
    "tgn:id":7586698,
    "tgn:name:en":"Wopazwain",
    "tgn:placetype":[
        "aat:300008347"
    ]
},
  "bbox": [],
  "geometry": {"coordinates":[74.177587,34.452927],"type":"Point"}
}