{
  "id": 2001965,
  "type": "Feature",
  "properties": {
    "tgn:hierarchy":[
        "tgn:2001965",
        "tgn:1000001",
        "tgn:7012149",
        "tgn:7007826",
        "tgn:7029392"
    ],
    "tgn:id":2001965,
    "tgn:name":"Cottle",
    "tgn:placetype":[
        "aat:300387145",
        "aat:300000771"
    ]
},
  "bbox": [],
  "geometry": {"coordinates":[-100.2667,34.0833],"type":"Point"}
}