{
  "id": 7127954,
  "type": "Feature",
  "properties": {
    "tgn:hierarchy":[
        "tgn:7127954",
        "tgn:1000003",
        "tgn:7003688",
        "tgn:7000084",
        "tgn:7029392"
    ],
    "tgn:id":7127954,
    "tgn:name":"Oberg",
    "tgn:placetype":[
        "aat:300008777"
    ]
},
  "bbox": [],
  "geometry": {"coordinates":[10.083333,54.066667],"type":"Point"}
}