{
  "id": 7550018,
  "type": "Feature",
  "properties": {
    "tgn:hierarchy":[
        "tgn:7550018",
        "tgn:1000004",
        "tgn:7000198",
        "tgn:7016722",
        "tgn:7029392"
    ],
    "tgn:id":7550018,
    "tgn:name:en":"Binaur",
    "tgn:placetype":[
        "aat:300008347"
    ]
},
  "bbox": [],
  "geometry": {"coordinates":[80.154287,26.388094],"type":"Point"}
}