{
  "id": 2510653,
  "type": "Feature",
  "properties": {
    "tgn:hierarchy":[
        "tgn:2510653",
        "tgn:2002130",
        "tgn:1000001",
        "tgn:7012149",
        "tgn:7007828",
        "tgn:7029392"
    ],
    "tgn:id":2510653,
    "tgn:name":"Middlebury Swamp",
    "tgn:placetype":[
        "aat:300008905"
    ]
},
  "bbox": [],
  "geometry": {"coordinates":[-73.1667,43.9667],"type":"Point"}
}