<<<<<<< HEAD
{
  "id": 7374204,
  "type": "Feature",
  "properties": {
    "tgn:hierarchy":[
        "tgn:7374204",
        "tgn:1000001",
        "tgn:1001906",
        "tgn:7005560",
        "tgn:7029392"
    ],
    "tgn:id":7374204,
    "tgn:name":"Laguna, Cerro la",
    "tgn:placetype":[
        "aat:300008795"
    ]
},
  "bbox": [],
  "geometry": {"coordinates":[-104.666667,21.966667],"type":"Point"}
}
=======
{"geometry":{"type":"Point","coordinates":[-104.666667,21.966667]},"type":"Feature","properties":{"hierarchy":["tgn:7374204","tgn:1000001","tgn:1001906","tgn:7005560","tgn:7029392"],"placetype":["aat:300008795"],"id":7374204,"name:xx":"Laguna, Cerro la"}}
>>>>>>> 03f74aca74312dbeaf24d7e61306dd6a786dc3d0
