{
  "id": 2279593,
  "type": "Feature",
  "properties": {
    "tgn:hierarchy":[
        "tgn:2279593",
        "tgn:1000001",
        "tgn:7016172",
        "tgn:7012149",
        "tgn:2000138",
        "tgn:7029392"
    ],
    "tgn:id":2279593,
    "tgn:name":"Deadman Slough",
    "tgn:placetype":[
        "aat:300008699"
    ]
},
  "bbox": [],
  "geometry": {"coordinates":[-91.3167,35.45],"type":"Point"}
}