{
  "id": 1082924,
  "type": "Feature",
  "properties": {
    "tgn:hierarchy":[
        "tgn:1082924",
        "tgn:7000317",
        "tgn:1000004",
        "tgn:1001907",
        "tgn:1000128",
        "tgn:7029392"
    ],
    "tgn:id":1082924,
    "tgn:name":"Rantau",
    "tgn:placetype":[
        "aat:300008347"
    ]
},
  "bbox": [],
  "geometry": {"coordinates":[101.95,2.5833],"type":"Point"}
}