<<<<<<< HEAD
{
  "id": 2153166,
  "type": "Feature",
  "properties": {
    "tgn:hierarchy":[
        "tgn:2153166",
        "tgn:1000001",
        "tgn:7012149",
        "tgn:2000929",
        "tgn:7007515",
        "tgn:7029392"
    ],
    "tgn:id":2153166,
    "tgn:name":"Beal Island",
    "tgn:placetype":[
        "aat:300008791"
    ]
},
  "bbox": [],
  "geometry": {"coordinates":[-69.7333,43.8667],"type":"Point"}
}
=======
{"geometry":{"type":"Point","coordinates":[-69.733300,43.866700]},"type":"Feature","properties":{"hierarchy":["tgn:2153166","tgn:1000001","tgn:7012149","tgn:2000929","tgn:7007515","tgn:7029392"],"placetype":["aat:300008791"],"id":2153166,"name:xx":"Beal Island"}}
>>>>>>> 03f74aca74312dbeaf24d7e61306dd6a786dc3d0
