{
  "id": 2547332,
  "type": "Feature",
  "properties": {
    "tgn:hierarchy":[
        "tgn:2547332",
        "tgn:1000001",
        "tgn:2001260",
        "tgn:7012149",
        "tgn:7007524",
        "tgn:7029392"
    ],
    "tgn:id":2547332,
    "tgn:name":"North Fork Sheep Creek",
    "tgn:placetype":[
        "aat:300008706"
    ]
},
  "bbox": [],
  "geometry": {"coordinates":[-113.3333,45.5333],"type":"Point"}
}