{
  "id": 2416275,
  "type": "Feature",
  "properties": {
    "tgn:hierarchy":[
        "tgn:2416275",
        "tgn:1000001",
        "tgn:7012149",
        "tgn:2002387",
        "tgn:7007923",
        "tgn:7029392"
    ],
    "tgn:id":2416275,
    "tgn:name":"J W and M J Luman Reservoir",
    "tgn:placetype":[
        "aat:300006191"
    ]
},
  "bbox": [],
  "geometry": {"coordinates":[-104.7167,44.15],"type":"Point"}
}