{
  "id": 1054018,
  "type": "Feature",
  "properties": {
    "tgn:hierarchy":[
        "tgn:1054018",
        "tgn:1000004",
        "tgn:1003405",
        "tgn:7018214",
        "tgn:7002435",
        "tgn:7029392"
    ],
    "tgn:id":1054018,
    "tgn:name":"Glubokiy",
    "tgn:placetype":[
        "aat:300008347"
    ]
},
  "bbox": [],
  "geometry": {"coordinates":[42.7833,47.0167],"type":"Point"}
}