<<<<<<< HEAD
{
  "id": 2769283,
  "type": "Feature",
  "properties": {
    "tgn:hierarchy":[
        "tgn:2769283",
        "tgn:1000001",
        "tgn:7012149",
        "tgn:2001155",
        "tgn:7007522",
        "tgn:7029392"
    ],
    "tgn:id":2769283,
    "tgn:name":"Wicker Mountain",
    "tgn:placetype":[
        "aat:300008798"
    ]
},
  "bbox": [],
  "geometry": {"coordinates":[-88.9333,34.7833],"type":"Point"}
}
=======
{"geometry":{"type":"Point","coordinates":[-88.933300,34.783300]},"type":"Feature","properties":{"hierarchy":["tgn:2769283","tgn:1000001","tgn:7012149","tgn:2001155","tgn:7007522","tgn:7029392"],"placetype":["aat:300008798"],"id":2769283,"name:xx":"Wicker Mountain"}}
>>>>>>> 03f74aca74312dbeaf24d7e61306dd6a786dc3d0
