<<<<<<< HEAD
{
  "id": 7487769,
  "type": "Feature",
  "properties": {
    "tgn:hierarchy":[
        "tgn:7487769",
        "tgn:1000004",
        "tgn:7489179",
        "tgn:1000141",
        "tgn:7029392"
    ],
    "tgn:id":7487769,
    "tgn:name":"Nanqiao Li",
    "tgn:placetype":[
        "aat:300387173"
    ]
},
  "bbox": [],
  "geometry": {"coordinates":[121.74694,24.72896],"type":"Point"}
}
=======
{"geometry":{"type":"Point","coordinates":[121.746940,24.728960]},"type":"Feature","properties":{"hierarchy":["tgn:7487769","tgn:1000004","tgn:7489179","tgn:1000141","tgn:7029392"],"placetype":["aat:300387173"],"id":7487769,"name:xx":"Nanqiao Li"}}
>>>>>>> 03f74aca74312dbeaf24d7e61306dd6a786dc3d0
