{
  "id": 7189862,
  "type": "Feature",
  "properties": {
    "tgn:hierarchy":[
        "tgn:7189862",
        "tgn:7003692",
        "tgn:1000003",
        "tgn:7000084",
        "tgn:7029392"
    ],
    "tgn:id":7189862,
    "tgn:name":"Ensenberg",
    "tgn:placetype":[
        "aat:300008347"
    ]
},
  "bbox": [],
  "geometry": {"coordinates":[8.05,48.133333],"type":"Point"}
}