{
  "id": 7538079,
  "type": "Feature",
  "properties": {
    "tgn:hierarchy":[
        "tgn:7538079",
        "tgn:7001242",
        "tgn:7001311",
        "tgn:7016833",
        "tgn:7029392"
    ],
    "tgn:id":7538079,
    "tgn:name":"Gh\u0101rib",
    "tgn:placetype":[
        "aat:300000401"
    ]
},
  "bbox": [],
  "geometry": {"coordinates":[33.058056,28.384167],"type":"Point"}
}