{
  "id": 2209243,
  "type": "Feature",
  "properties": {
    "tgn:hierarchy":[
        "tgn:2209243",
        "tgn:1000001",
        "tgn:7012149",
        "tgn:1002506",
        "tgn:7007919",
        "tgn:7029392"
    ],
    "tgn:id":2209243,
    "tgn:name":"Burnt Mills Swamp",
    "tgn:placetype":[
        "aat:300008699"
    ]
},
  "bbox": [],
  "geometry": {"coordinates":[-76.7333,36.8333],"type":"Point"}
}