{
  "id": 7203830,
  "type": "Feature",
  "properties": {
    "tgn:hierarchy":[
        "tgn:7203830",
        "tgn:7000096",
        "tgn:1000003",
        "tgn:7000084",
        "tgn:7029392"
    ],
    "tgn:id":7203830,
    "tgn:name":"Breslack",
    "tgn:placetype":[
        "aat:300008347"
    ]
},
  "bbox": [],
  "geometry": {"coordinates":[14.733333,52.05],"type":"Point"}
}