{
  "id": 2475508,
  "type": "Feature",
  "properties": {
    "tgn:hierarchy":[
        "tgn:2475508",
        "tgn:2001002",
        "tgn:1000001",
        "tgn:7012149",
        "tgn:7007521",
        "tgn:7029392"
    ],
    "tgn:id":2475508,
    "tgn:name":"Luck Lake",
    "tgn:placetype":[
        "aat:300008680"
    ]
},
  "bbox": [],
  "geometry": {"coordinates":[-94.5667,47.45],"type":"Point"}
}