{
  "id": 7494156,
  "type": "Feature",
  "properties": {
    "tgn:hierarchy":[
        "tgn:7494156",
        "tgn:1000004",
        "tgn:7492971",
        "tgn:1000141",
        "tgn:7029392"
    ],
    "tgn:id":7494156,
    "tgn:name":"Gongguanyuan",
    "tgn:placetype":[
        "aat:300008347"
    ]
},
  "bbox": [],
  "geometry": {"coordinates":[120.5607,22.788818],"type":"Point"}
}