{
  "id": 2629432,
  "type": "Feature",
  "properties": {
    "tgn:hierarchy":[
        "tgn:2629432",
        "tgn:1000001",
        "tgn:7012149",
        "tgn:2000182",
        "tgn:7007157",
        "tgn:7029392"
    ],
    "tgn:id":2629432,
    "tgn:name":"Roselle Canal",
    "tgn:placetype":[
        "aat:300006075"
    ]
},
  "bbox": [],
  "geometry": {"coordinates":[-115.45,32.8167],"type":"Point"}
}