{
  "id": 2026649,
  "type": "Feature",
  "properties": {
    "tgn:hierarchy":[
        "tgn:2026649",
        "tgn:1000001",
        "tgn:7012149",
        "tgn:1002878",
        "tgn:7007251",
        "tgn:7029392"
    ],
    "tgn:id":2026649,
    "tgn:name":"Bluffs",
    "tgn:placetype":[
        "aat:300008347"
    ]
},
  "bbox": [],
  "geometry": {"coordinates":[-90.5333,39.75],"type":"Point"}
}