{
  "id": 7219256,
  "type": "Feature",
  "properties": {
    "tgn:hierarchy":[
        "tgn:7219256",
        "tgn:7002690",
        "tgn:7012056",
        "tgn:1000003",
        "tgn:1000074",
        "tgn:7029392"
    ],
    "tgn:id":7219256,
    "tgn:name":"Vorn\u00e1dhes",
    "tgn:placetype":[
        "aat:300008795"
    ]
},
  "bbox": [],
  "geometry": {"coordinates":[24.133333,35.333333],"type":"Point"}
}