{
  "id": 7271462,
  "type": "Feature",
  "properties": {
    "tgn:hierarchy":[
        "tgn:7271462",
        "tgn:1000003",
        "tgn:7003613",
        "tgn:7016845",
        "tgn:7029392"
    ],
    "tgn:id":7271462,
    "tgn:name:nl":"Swieringa's Polder",
    "tgn:placetype":[
        "aat:300006163"
    ]
},
  "bbox": [],
  "geometry": {"coordinates":[6.716667,53.283333],"type":"Point"}
}