{
  "id": 7536047,
  "type": "Feature",
  "properties": {
    "tgn:hierarchy":[
        "tgn:7536047",
        "tgn:7001242",
        "tgn:7016833",
        "tgn:7001336",
        "tgn:7029392"
    ],
    "tgn:id":7536047,
    "tgn:name:en":"Gereimli, Gebel",
    "tgn:placetype":[
        "aat:300008795"
    ]
},
  "bbox": [],
  "geometry": {"coordinates":[34.462571,28.526252],"type":"Point"}
}