{
  "id": 7233356,
  "type": "Feature",
  "properties": {
    "tgn:hierarchy":[
        "tgn:7233356",
        "tgn:4003773",
        "tgn:7001395",
        "tgn:1000003",
        "tgn:1000074",
        "tgn:7029392"
    ],
    "tgn:id":7233356,
    "tgn:name":"Dhok\u00edmia",
    "tgn:placetype":[
        "aat:300008347"
    ]
},
  "bbox": [],
  "geometry": {"coordinates":[21.683333,38.566667],"type":"Point"}
}