{
  "id": 7235555,
  "type": "Feature",
  "properties": {
    "tgn:hierarchy":[
        "tgn:7235555",
        "tgn:7002681",
        "tgn:7001395",
        "tgn:1000003",
        "tgn:1000074",
        "tgn:7029392"
    ],
    "tgn:id":7235555,
    "tgn:name":"Fil\u00e1gras, \u00d3rmos",
    "tgn:placetype":[
        "aat:300132316"
    ]
},
  "bbox": [],
  "geometry": {"coordinates":[24.35,38.166667],"type":"Point"}
}