{
  "id": 7440914,
  "type": "Feature",
  "properties": {
    "tgn:hierarchy":[
        "tgn:7440914",
        "tgn:7005581",
        "tgn:1000001",
        "tgn:7005560",
        "tgn:7029392"
    ],
    "tgn:id":7440914,
    "tgn:name":"Santa Luc\u00eda",
    "tgn:placetype":[
        "aat:300008347"
    ]
},
  "bbox": [],
  "geometry": {"coordinates":[-107.316667,29.083333],"type":"Point"}
}