{
  "id": 2304572,
  "type": "Feature",
  "properties": {
    "tgn:hierarchy":[
        "tgn:2304572",
        "tgn:1000001",
        "tgn:7012149",
        "tgn:2000277",
        "tgn:7007240",
        "tgn:7029392"
    ],
    "tgn:id":2304572,
    "tgn:name":"East Bank",
    "tgn:placetype":[
        "aat:300132348"
    ]
},
  "bbox": [],
  "geometry": {"coordinates":[-83.05,29.0667],"type":"Point"}
}