{
  "id": 2429029,
  "type": "Feature",
  "properties": {
    "tgn:hierarchy":[
        "tgn:2429029",
        "tgn:1000001",
        "tgn:7006451",
        "tgn:7012149",
        "tgn:2000099",
        "tgn:7029392"
    ],
    "tgn:id":2429029,
    "tgn:name":"Jumpoff Spring",
    "tgn:placetype":[
        "aat:300008697"
    ]
},
  "bbox": [],
  "geometry": {"coordinates":[-110.3833,34.1667],"type":"Point"}
}