{
  "id": 2775533,
  "type": "Feature",
  "properties": {
    "tgn:hierarchy":[
        "tgn:2775533",
        "tgn:1000001",
        "tgn:2001416",
        "tgn:7012149",
        "tgn:7007526",
        "tgn:7029392"
    ],
    "tgn:id":2775533,
    "tgn:name":"Wilson Creek",
    "tgn:placetype":[
        "aat:300008706"
    ]
},
  "bbox": [],
  "geometry": {"coordinates":[-114.3667,38.2333],"type":"Point"}
}