{
  "id": 2283291,
  "type": "Feature",
  "properties": {
    "tgn:hierarchy":[
        "tgn:2283291",
        "tgn:1000001",
        "tgn:7012149",
        "tgn:2001709",
        "tgn:7007708",
        "tgn:7029392"
    ],
    "tgn:id":2283291,
    "tgn:name":"Delintment Lake",
    "tgn:placetype":[
        "aat:300008680"
    ]
},
  "bbox": [],
  "geometry": {"coordinates":[-119.6167,43.8833],"type":"Point"}
}