{
  "id": 2420053,
  "type": "Feature",
  "properties": {
    "tgn:hierarchy":[
        "tgn:2420053",
        "tgn:1000001",
        "tgn:1002410",
        "tgn:7012149",
        "tgn:7007565",
        "tgn:7029392"
    ],
    "tgn:id":2420053,
    "tgn:name":"Jeesups Mill Lake",
    "tgn:placetype":[
        "aat:300008680"
    ]
},
  "bbox": [],
  "geometry": {"coordinates":[-75.1833,39.7667],"type":"Point"}
}