{
  "id": 7508687,
  "type": "Feature",
  "properties": {
    "tgn:hierarchy":[
        "tgn:7508687",
        "tgn:1008380",
        "tgn:7520093",
        "tgn:1000226",
        "tgn:1000006",
        "tgn:7029392"
    ],
    "tgn:id":7508687,
    "tgn:name:en":"Otunui Stream",
    "tgn:placetype":[
        "aat:300008699"
    ]
},
  "bbox": [],
  "geometry": {"coordinates":[175.15,-38.95],"type":"Point"}
}