{
  "id": 7549916,
  "type": "Feature",
  "properties": {
    "tgn:hierarchy":[
        "tgn:7549916",
        "tgn:1000004",
        "tgn:1001869",
        "tgn:7000198",
        "tgn:7029392"
    ],
    "tgn:id":7549916,
    "tgn:name:en":"Bilodra",
    "tgn:placetype":[
        "aat:300008347"
    ]
},
  "bbox": [],
  "geometry": {"coordinates":[72.65221,23.524715],"type":"Point"}
}