{
  "id": 2579432,
  "type": "Feature",
  "properties": {
    "tgn:hierarchy":[
        "tgn:2579432",
        "tgn:1002996",
        "tgn:1000001",
        "tgn:7012149",
        "tgn:7007711",
        "tgn:7029392"
    ],
    "tgn:id":2579432,
    "tgn:name":"Pickerel Point",
    "tgn:placetype":[
        "aat:300008850"
    ]
},
  "bbox": [],
  "geometry": {"coordinates":[-71.4833,41.45],"type":"Point"}
}