{
  "id": 1002729,
  "type": "Feature",
  "properties": {
    "tgn:hierarchy":[
        "tgn:1002729",
        "tgn:1000001",
        "tgn:7012149",
        "tgn:7007710",
        "tgn:7029392"
    ],
    "tgn:id":1002729,
    "tgn:name":"Northampton",
    "tgn:placetype":[
        "aat:300387145",
        "aat:300000771"
    ]
},
  "bbox": [],
  "geometry": {"coordinates":[-75.25,40.8667],"type":"Point"}
}