{
  "id": 2243881,
  "type": "Feature",
  "properties": {
    "tgn:hierarchy":[
        "tgn:2243881",
        "tgn:7013388",
        "tgn:1000001",
        "tgn:7012149",
        "tgn:7007517",
        "tgn:7029392"
    ],
    "tgn:id":2243881,
    "tgn:name":"Cleveland Mountain",
    "tgn:placetype":[
        "aat:300008798"
    ]
},
  "bbox": [],
  "geometry": {"coordinates":[-73.2333,42.0667],"type":"Point"}
}