{
  "id": 1088061,
  "type": "Feature",
  "properties": {
    "tgn:hierarchy":[
        "tgn:1088061",
        "tgn:7001242",
        "tgn:1000879",
        "tgn:1000150",
        "tgn:7029392"
    ],
    "tgn:id":1088061,
    "tgn:name":"Lephepe",
    "tgn:placetype":[
        "aat:300008347"
    ]
},
  "bbox": [],
  "geometry": {"coordinates":[25.8333,-23.3333],"type":"Point"}
}