{
  "id": 2629276,
  "type": "Feature",
  "properties": {
    "tgn:hierarchy":[
        "tgn:2629276",
        "tgn:1000001",
        "tgn:7012149",
        "tgn:2001883",
        "tgn:7007825",
        "tgn:7029392"
    ],
    "tgn:id":2629276,
    "tgn:name":"Roseberry Creek",
    "tgn:placetype":[
        "aat:300008706"
    ]
},
  "bbox": [],
  "geometry": {"coordinates":[-83.8333,36.1167],"type":"Point"}
}