<<<<<<< HEAD
{
  "id": 2157328,
  "type": "Feature",
  "properties": {
    "tgn:hierarchy":[
        "tgn:2157328",
        "tgn:1000001",
        "tgn:7012149",
        "tgn:2001162",
        "tgn:7007522",
        "tgn:7029392"
    ],
    "tgn:id":2157328,
    "tgn:name":"Beaver Creek",
    "tgn:placetype":[
        "aat:300008706"
    ]
},
  "bbox": [],
  "geometry": {"coordinates":[-88.6167,31.55],"type":"Point"}
}
=======
{"geometry":{"type":"Point","coordinates":[-88.616700,31.550000]},"type":"Feature","properties":{"hierarchy":["tgn:2157328","tgn:1000001","tgn:7012149","tgn:2001162","tgn:7007522","tgn:7029392"],"placetype":["aat:300008706"],"id":2157328,"name:xx":"Beaver Creek"}}
>>>>>>> 03f74aca74312dbeaf24d7e61306dd6a786dc3d0
