{
  "id": 7151642,
  "type": "Feature",
  "properties": {
    "tgn:hierarchy":[
        "tgn:7151642",
        "tgn:1000003",
        "tgn:7003677",
        "tgn:7000084",
        "tgn:7029392"
    ],
    "tgn:id":7151642,
    "tgn:name":"K\u00e4hling",
    "tgn:placetype":[
        "aat:300008777"
    ]
},
  "bbox": [],
  "geometry": {"coordinates":[8.216667,51.116667],"type":"Point"}
}