{
  "id": 1042211,
  "type": "Feature",
  "properties": {
    "tgn:hierarchy":[
        "tgn:1042211",
        "tgn:7002726",
        "tgn:7002715",
        "tgn:1000003",
        "tgn:1000074",
        "tgn:7029392"
    ],
    "tgn:id":1042211,
    "tgn:name":"Si\u00e1tista",
    "tgn:placetype":[
        "aat:300008347"
    ]
},
  "bbox": [],
  "geometry": {"coordinates":[21.544167,40.261944],"type":"Point"}
}