{
  "id": 2438429,
  "type": "Feature",
  "properties": {
    "tgn:hierarchy":[
        "tgn:2438429",
        "tgn:1000001",
        "tgn:7012149",
        "tgn:2001864",
        "tgn:7007825",
        "tgn:7029392"
    ],
    "tgn:id":2438429,
    "tgn:name":"Kings Mountain",
    "tgn:placetype":[
        "aat:300008798"
    ]
},
  "bbox": [],
  "geometry": {"coordinates":[-87.0333,35.2167],"type":"Point"}
}