{
  "id": 1083216,
  "type": "Feature",
  "properties": {
    "tgn:hierarchy":[
        "tgn:1083216",
        "tgn:1000004",
        "tgn:1001589",
        "tgn:7029379",
        "tgn:7029392"
    ],
    "tgn:id":1083216,
    "tgn:name":"Tes",
    "tgn:placetype":[
        "aat:300008347"
    ]
},
  "bbox": [],
  "geometry": {"coordinates":[93.5833,50.4667],"type":"Point"}
}