{
  "id": 2507202,
  "type": "Feature",
  "properties": {
    "tgn:hierarchy":[
        "tgn:2507202",
        "tgn:1000001",
        "tgn:7012149",
        "tgn:2000874",
        "tgn:7007256",
        "tgn:7029392"
    ],
    "tgn:id":2507202,
    "tgn:name":"Metropolis",
    "tgn:placetype":[
        "aat:300008347"
    ]
},
  "bbox": [],
  "geometry": {"coordinates":[-91.6833,31.95],"type":"Point"}
}