{
  "id": 7498525,
  "type": "Feature",
  "properties": {
    "tgn:hierarchy":[
        "tgn:7498525",
        "tgn:1000004",
        "tgn:7001009",
        "tgn:1000141",
        "tgn:7029392"
    ],
    "tgn:id":7498525,
    "tgn:name":"Xianshi Shifan Gongmu",
    "tgn:placetype":[
        "aat:300266755"
    ]
},
  "bbox": [],
  "geometry": {"coordinates":[120.606371,24.223074],"type":"Point"}
}