{
  "id": 7081872,
  "type": "Feature",
  "properties": {
    "tgn:hierarchy":[
        "tgn:7081872",
        "tgn:7003669",
        "tgn:1000003",
        "tgn:7000084",
        "tgn:7029392"
    ],
    "tgn:id":7081872,
    "tgn:name":"W\u00fcstenbruck",
    "tgn:placetype":[
        "aat:300008347"
    ]
},
  "bbox": [],
  "geometry": {"coordinates":[10.483333,49.283333],"type":"Point"}
}