{
  "id": 2368722,
  "type": "Feature",
  "properties": {
    "tgn:hierarchy":[
        "tgn:2368722",
        "tgn:2000948",
        "tgn:1000001",
        "tgn:7012149",
        "tgn:7007520",
        "tgn:7029392"
    ],
    "tgn:id":2368722,
    "tgn:name":"Gull Island",
    "tgn:placetype":[
        "aat:300008791"
    ]
},
  "bbox": [],
  "geometry": {"coordinates":[-83.85,43.65],"type":"Point"}
}