{
  "id": 7524772,
  "type": "Feature",
  "properties": {
    "tgn:hierarchy":[
        "tgn:7524772",
        "tgn:7001242",
        "tgn:7016833",
        "tgn:1001113",
        "tgn:7029392"
    ],
    "tgn:id":7524772,
    "tgn:name":"Al Maym\u016bnah",
    "tgn:placetype":[
        "aat:300008347"
    ]
},
  "bbox": [],
  "geometry": {"coordinates":[31.384946,30.603392],"type":"Point"}
}