{
  "id": 1095685,
  "type": "Feature",
  "properties": {
    "tgn:hierarchy":[
        "tgn:1095685",
        "tgn:7001242",
        "tgn:1001059",
        "tgn:7016833",
        "tgn:7029392"
    ],
    "tgn:id":1095685,
    "tgn:name:en":"Sanaf\u0101",
    "tgn:placetype":[
        "aat:300008347"
    ]
},
  "bbox": [],
  "geometry": {"coordinates":[31.35362,30.79074],"type":"Point"}
}