{
  "id": 2490259,
  "type": "Feature",
  "properties": {
    "tgn:hierarchy":[
        "tgn:2490259",
        "tgn:2002101",
        "tgn:1000001",
        "tgn:7012149",
        "tgn:7007827",
        "tgn:7029392"
    ],
    "tgn:id":2490259,
    "tgn:name":"Manderfield Reservoir",
    "tgn:placetype":[
        "aat:300006191"
    ]
},
  "bbox": [],
  "geometry": {"coordinates":[-112.4667,38.4167],"type":"Point"}
}