{
  "id": 7302540,
  "type": "Feature",
  "properties": {
    "tgn:hierarchy":[
        "tgn:7302540",
        "tgn:7001155",
        "tgn:1000003",
        "tgn:7002790",
        "tgn:1000095",
        "tgn:7029392"
    ],
    "tgn:id":7302540,
    "tgn:name":"Murillo de L\u00f3nguida",
    "tgn:placetype":[
        "aat:300008347"
    ]
},
  "bbox": [],
  "geometry": {"coordinates":[-1.35,42.75],"type":"Point"}
}