{
  "id": 7375004,
  "type": "Feature",
  "properties": {
    "tgn:hierarchy":[
        "tgn:7375004",
        "tgn:1000001",
        "tgn:1001960",
        "tgn:7005560",
        "tgn:7029392"
    ],
    "tgn:id":7375004,
    "tgn:name":"La Cuchilla",
    "tgn:placetype":[
        "aat:300008347"
    ]
},
  "bbox": [],
  "geometry": {"coordinates":[-111.416667,30.65],"type":"Point"}
}