{
  "id": 7304006,
  "type": "Feature",
  "properties": {
    "tgn:hierarchy":[
        "tgn:7304006",
        "tgn:7002807",
        "tgn:1000003",
        "tgn:7003837",
        "tgn:1000095",
        "tgn:7029392"
    ],
    "tgn:id":7304006,
    "tgn:name":"Ortiga, Sierra de la",
    "tgn:placetype":[
        "aat:300266640"
    ]
},
  "bbox": [],
  "geometry": {"coordinates":[-5.866667,38.866667],"type":"Point"}
}