{
  "id": 2192791,
  "type": "Feature",
  "properties": {
    "tgn:hierarchy":[
        "tgn:2192791",
        "tgn:1000001",
        "tgn:7012149",
        "tgn:2000337",
        "tgn:7007248",
        "tgn:7029392"
    ],
    "tgn:id":2192791,
    "tgn:name":"Bratcher Creek",
    "tgn:placetype":[
        "aat:300008706"
    ]
},
  "bbox": [],
  "geometry": {"coordinates":[-83.6667,32.1333],"type":"Point"}
}