{
  "id": 7320894,
  "type": "Feature",
  "properties": {
    "tgn:hierarchy":[
        "tgn:7320894",
        "tgn:1001623",
        "tgn:1000049",
        "tgn:1000002",
        "tgn:7029392"
    ],
    "tgn:id":7320894,
    "tgn:name":"Blanca, Roca",
    "tgn:placetype":[
        "aat:300011692"
    ]
},
  "bbox": [],
  "geometry": {"coordinates":[-73.342222,-44.469444],"type":"Point"}
}