{
  "id": 2384252,
  "type": "Feature",
  "properties": {
    "tgn:hierarchy":[
        "tgn:2384252",
        "tgn:1000001",
        "tgn:7012149",
        "tgn:2001883",
        "tgn:7007825",
        "tgn:7029392"
    ],
    "tgn:id":2384252,
    "tgn:name":"Heiskell Pit",
    "tgn:placetype":[
        "aat:300008746"
    ]
},
  "bbox": [],
  "geometry": {"coordinates":[-84.05,36.0833],"type":"Point"}
}