{
  "id": 7433141,
  "type": "Feature",
  "properties": {
    "tgn:hierarchy":[
        "tgn:7433141",
        "tgn:7005583",
        "tgn:1000001",
        "tgn:7005560",
        "tgn:7029392"
    ],
    "tgn:id":7433141,
    "tgn:name":"Yerban\u00eds",
    "tgn:placetype":[
        "aat:300008347"
    ]
},
  "bbox": [],
  "geometry": {"coordinates":[-103.843056,24.737778],"type":"Point"}
}