{
  "id": 2606266,
  "type": "Feature",
  "properties": {
    "tgn:hierarchy":[
        "tgn:2606266",
        "tgn:1000001",
        "tgn:7012149",
        "tgn:7007248",
        "tgn:7029392"
    ],
    "tgn:id":2606266,
    "tgn:name":"Rakestraw Creek",
    "tgn:placetype":[
        "aat:300008706"
    ]
},
  "bbox": [],
  "geometry": {"coordinates":[-84.7667,33.9167],"type":"Point"}
}