<<<<<<< HEAD
{
  "id": 2332693,
  "type": "Feature",
  "properties": {
    "tgn:hierarchy":[
        "tgn:2332693",
        "tgn:1000001",
        "tgn:7012149",
        "tgn:2002036",
        "tgn:7007826",
        "tgn:7029392"
    ],
    "tgn:id":2332693,
    "tgn:name":"Flower Grove",
    "tgn:placetype":[
        "aat:300008347"
    ]
},
  "bbox": [],
  "geometry": {"coordinates":[-101.8,32.4833],"type":"Point"}
}
=======
{"geometry":{"type":"Point","coordinates":[-101.800000,32.483300]},"type":"Feature","properties":{"hierarchy":["tgn:2332693","tgn:1000001","tgn:7012149","tgn:2002036","tgn:7007826","tgn:7029392"],"placetype":["aat:300008347"],"id":2332693,"name:xx":"Flower Grove"}}
>>>>>>> 03f74aca74312dbeaf24d7e61306dd6a786dc3d0
