{
  "id": 7453890,
  "type": "Feature",
  "properties": {
    "tgn:hierarchy":[
        "tgn:7453890",
        "tgn:7002445",
        "tgn:1000003",
        "tgn:7008185",
        "tgn:7008591",
        "tgn:7029392"
    ],
    "tgn:id":7453890,
    "tgn:name:en":"Covehithe",
    "tgn:placetype":[
        "aat:300008347"
    ]
},
  "bbox": [],
  "geometry": {"coordinates":[1.716667,52.366667],"type":"Point"}
}