{
  "id": 2322254,
  "type": "Feature",
  "properties": {
    "tgn:hierarchy":[
        "tgn:2322254",
        "tgn:1000001",
        "tgn:7012149",
        "tgn:7007522",
        "tgn:7029392"
    ],
    "tgn:id":2322254,
    "tgn:name":"Fallah, Bogue",
    "tgn:placetype":[
        "aat:300008699"
    ]
},
  "bbox": [],
  "geometry": {"coordinates":[-89.1333,33.3167],"type":"Point"}
}