{
  "id": 7459712,
  "type": "Feature",
  "properties": {
    "tgn:hierarchy":[
        "tgn:7459712",
        "tgn:7002443",
        "tgn:1000003",
        "tgn:7018956",
        "tgn:7008591",
        "tgn:7029392"
    ],
    "tgn:id":7459712,
    "tgn:name:en":"Nash",
    "tgn:placetype":[
        "aat:300008347"
    ]
},
  "bbox": [],
  "geometry": {"coordinates":[-2.946111,51.548889],"type":"Point"}
}