{
  "id": 7490802,
  "type": "Feature",
  "properties": {
    "tgn:hierarchy":[
        "tgn:7490802",
        "tgn:7001010",
        "tgn:1000004",
        "tgn:1000141",
        "tgn:7029392"
    ],
    "tgn:id":7490802,
    "tgn:name":"Sanfu Qiao",
    "tgn:placetype":[
        "aat:300007836"
    ]
},
  "bbox": [],
  "geometry": {"coordinates":[121.496241,23.44696],"type":"Point"}
}