{
  "id": 2128637,
  "type": "Feature",
  "properties": {
    "tgn:hierarchy":[
        "tgn:2128637",
        "tgn:1000001",
        "tgn:2002245",
        "tgn:7012149",
        "tgn:7007920",
        "tgn:7029392"
    ],
    "tgn:id":2128637,
    "tgn:name":"Alder Thicket Spring",
    "tgn:placetype":[
        "aat:300008697"
    ]
},
  "bbox": [],
  "geometry": {"coordinates":[-117.5667,46.25],"type":"Point"}
}