{
  "id": 2581014,
  "type": "Feature",
  "properties": {
    "tgn:hierarchy":[
        "tgn:2581014",
        "tgn:1000001",
        "tgn:2002313",
        "tgn:7012149",
        "tgn:7007922",
        "tgn:7029392"
    ],
    "tgn:id":2581014,
    "tgn:name":"Pike Lake",
    "tgn:placetype":[
        "aat:300008680"
    ]
},
  "bbox": [],
  "geometry": {"coordinates":[-91.0667,45.0667],"type":"Point"}
}