<<<<<<< HEAD
{
  "id": 2333315,
  "type": "Feature",
  "properties": {
    "tgn:hierarchy":[
        "tgn:2333315",
        "tgn:1000001",
        "tgn:7012149",
        "tgn:2001054",
        "tgn:7007521",
        "tgn:7029392"
    ],
    "tgn:id":2333315,
    "tgn:name":"Fogelberg Lake",
    "tgn:placetype":[
        "aat:300008680"
    ]
},
  "bbox": [],
  "geometry": {"coordinates":[-96.05,46.5167],"type":"Point"}
}
=======
{"geometry":{"type":"Point","coordinates":[-96.050000,46.516700]},"type":"Feature","properties":{"hierarchy":["tgn:2333315","tgn:1000001","tgn:7012149","tgn:2001054","tgn:7007521","tgn:7029392"],"placetype":["aat:300008680"],"id":2333315,"name:xx":"Fogelberg Lake"}}
>>>>>>> 03f74aca74312dbeaf24d7e61306dd6a786dc3d0
