{
  "id": 2275318,
  "type": "Feature",
  "properties": {
    "tgn:hierarchy":[
        "tgn:2275318",
        "tgn:7006450",
        "tgn:1000001",
        "tgn:7019698",
        "tgn:7012149",
        "tgn:7029392"
    ],
    "tgn:id":2275318,
    "tgn:name":"Daniels Lake",
    "tgn:placetype":[
        "aat:300008680"
    ]
},
  "bbox": [],
  "geometry": {"coordinates":[-151.1833,60.7333],"type":"Point"}
}