{
  "id": 2714402,
  "type": "Feature",
  "properties": {
    "tgn:hierarchy":[
        "tgn:2714402",
        "tgn:1000001",
        "tgn:7012149",
        "tgn:2002157",
        "tgn:7007919",
        "tgn:7029392"
    ],
    "tgn:id":2714402,
    "tgn:name":"Tempest Branch",
    "tgn:placetype":[
        "aat:300008699"
    ]
},
  "bbox": [],
  "geometry": {"coordinates":[-82.4667,37.05],"type":"Point"}
}