{
  "id": 2555188,
  "type": "Feature",
  "properties": {
    "tgn:hierarchy":[
        "tgn:2555188",
        "tgn:1000001",
        "tgn:2000273",
        "tgn:7012149",
        "tgn:7007240",
        "tgn:7029392"
    ],
    "tgn:id":2555188,
    "tgn:name":"Ocheesee Pond",
    "tgn:placetype":[
        "aat:300008905"
    ]
},
  "bbox": [],
  "geometry": {"coordinates":[-84.9667,30.6833],"type":"Point"}
}