{
  "id": 7047795,
  "type": "Feature",
  "properties": {
    "tgn:hierarchy":[
        "tgn:7047795",
        "tgn:1003460",
        "tgn:1000003",
        "tgn:7009760",
        "tgn:1000080",
        "tgn:7029392"
    ],
    "tgn:id":7047795,
    "tgn:name":"Graticcia",
    "tgn:placetype":[
        "aat:300008347"
    ]
},
  "bbox": [],
  "geometry": {"coordinates":[11.45,42.366667],"type":"Point"}
}