{
  "id": 7231452,
  "type": "Feature",
  "properties": {
    "tgn:hierarchy":[
        "tgn:7231452",
        "tgn:7002753",
        "tgn:7002756",
        "tgn:1000003",
        "tgn:1000074",
        "tgn:7029392"
    ],
    "tgn:id":7231452,
    "tgn:name":"Mar\u00e1sia",
    "tgn:placetype":[
        "aat:300008347"
    ]
},
  "bbox": [],
  "geometry": {"coordinates":[26.468056,41.665],"type":"Point"}
}