<<<<<<< HEAD
{
  "id": 7372961,
  "type": "Feature",
  "properties": {
    "tgn:hierarchy":[
        "tgn:7372961",
        "tgn:1000001",
        "tgn:7005589",
        "tgn:7005560",
        "tgn:7029392"
    ],
    "tgn:id":7372961,
    "tgn:name":"La Ceja",
    "tgn:placetype":[
        "aat:300008347"
    ]
},
  "bbox": [],
  "geometry": {"coordinates":[-99.05,26.0],"type":"Point"}
}
=======
{"geometry":{"type":"Point","coordinates":[-99.050000,26.000000]},"type":"Feature","properties":{"hierarchy":["tgn:7372961","tgn:1000001","tgn:7005589","tgn:7005560","tgn:7029392"],"placetype":["aat:300008347"],"id":7372961,"name:xx":"La Ceja"}}
>>>>>>> 03f74aca74312dbeaf24d7e61306dd6a786dc3d0
