{
  "id": 7415147,
  "type": "Feature",
  "properties": {
    "tgn:hierarchy":[
        "tgn:7415147",
        "tgn:7005584",
        "tgn:1000001",
        "tgn:7005560",
        "tgn:7029392"
    ],
    "tgn:id":7415147,
    "tgn:name":"Pantale\u00f3n",
    "tgn:placetype":[
        "aat:300008347"
    ]
},
  "bbox": [],
  "geometry": {"coordinates":[-100.793889,19.980278],"type":"Point"}
}