{
  "id": 2647601,
  "type": "Feature",
  "properties": {
    "tgn:hierarchy":[
        "tgn:2647601",
        "tgn:1000001",
        "tgn:7012149",
        "tgn:1002633",
        "tgn:7007252",
        "tgn:7029392"
    ],
    "tgn:id":2647601,
    "tgn:name":"School Creek",
    "tgn:placetype":[
        "aat:300008706"
    ]
},
  "bbox": [],
  "geometry": {"coordinates":[-86.2667,39.6833],"type":"Point"}
}