{
  "id": 7071133,
  "type": "Feature",
  "properties": {
    "tgn:hierarchy":[
        "tgn:7071133",
        "tgn:7003669",
        "tgn:1000003",
        "tgn:7000084",
        "tgn:7029392"
    ],
    "tgn:id":7071133,
    "tgn:name":"Stumpfer am Zaun",
    "tgn:placetype":[
        "aat:300000206"
    ]
},
  "bbox": [],
  "geometry": {"coordinates":[12.45,48.166667],"type":"Point"}
}