{
  "id": 2663962,
  "type": "Feature",
  "properties": {
    "tgn:hierarchy":[
        "tgn:2663962",
        "tgn:1000001",
        "tgn:7012149",
        "tgn:7007157",
        "tgn:1002957",
        "tgn:7029392"
    ],
    "tgn:id":2663962,
    "tgn:name":"Silver Mine Creek",
    "tgn:placetype":[
        "aat:300008706"
    ]
},
  "bbox": [],
  "geometry": {"coordinates":[-119.7667,38.2667],"type":"Point"}
}