{
  "id": 2157971,
  "type": "Feature",
  "properties": {
    "tgn:hierarchy":[
        "tgn:2157971",
        "tgn:2002130",
        "tgn:1000001",
        "tgn:7012149",
        "tgn:7007828",
        "tgn:7029392"
    ],
    "tgn:id":2157971,
    "tgn:name":"Beaver Meadow Brook",
    "tgn:placetype":[
        "aat:300008699"
    ]
},
  "bbox": [],
  "geometry": {"coordinates":[-72.9333,44.1167],"type":"Point"}
}