{
  "id": 2482224,
  "type": "Feature",
  "properties": {
    "tgn:hierarchy":[
        "tgn:2482224",
        "tgn:1000001",
        "tgn:1002293",
        "tgn:7012149",
        "tgn:7007708",
        "tgn:7029392"
    ],
    "tgn:id":2482224,
    "tgn:name":"Langfeld Creek",
    "tgn:placetype":[
        "aat:300008706"
    ]
},
  "bbox": [],
  "geometry": {"coordinates":[-123.1333,46.05],"type":"Point"}
}