{
  "id": 2215920,
  "type": "Feature",
  "properties": {
    "tgn:hierarchy":[
        "tgn:2215920",
        "tgn:1000001",
        "tgn:7012149",
        "tgn:1002545",
        "tgn:7007157",
        "tgn:7029392"
    ],
    "tgn:id":2215920,
    "tgn:name":"Cameron",
    "tgn:placetype":[
        "aat:300008347"
    ]
},
  "bbox": [],
  "geometry": {"coordinates":[-118.2833,35.0833],"type":"Point"}
}