{
  "id": 2499626,
  "type": "Feature",
  "properties": {
    "tgn:hierarchy":[
        "tgn:2499626",
        "tgn:1000001",
        "tgn:7012149",
        "tgn:7007526",
        "tgn:7029392"
    ],
    "tgn:id":2499626,
    "tgn:name":"McConnel Canyon",
    "tgn:placetype":[
        "aat:300008761"
    ]
},
  "bbox": [],
  "geometry": {"coordinates":[-119.35,41.1667],"type":"Point"}
}