{
  "id": 1035784,
  "type": "Feature",
  "properties": {
    "tgn:hierarchy":[
        "tgn:1035784",
        "tgn:7002870",
        "tgn:1000003",
        "tgn:1000070",
        "tgn:7029392"
    ],
    "tgn:id":1035784,
    "tgn:name":"Steinbourg",
    "tgn:placetype":[
        "aat:300008347"
    ]
},
  "bbox": [],
  "geometry": {"coordinates":[7.4167,48.7833],"type":"Point"}
}