<<<<<<< HEAD
{
  "id": 7051195,
  "type": "Feature",
  "properties": {
    "tgn:hierarchy":[
        "tgn:7051195",
        "tgn:1003500",
        "tgn:1000003",
        "tgn:7010380",
        "tgn:1000080",
        "tgn:7029392"
    ],
    "tgn:id":7051195,
    "tgn:name":"Stazione Nasisi",
    "tgn:placetype":[
        "aat:300007783"
    ]
},
  "bbox": [],
  "geometry": {"coordinates":[17.25,40.5],"type":"Point"}
}
=======
{"geometry":{"type":"Point","coordinates":[17.250000,40.500000]},"type":"Feature","properties":{"hierarchy":["tgn:7051195","tgn:1003500","tgn:1000003","tgn:7010380","tgn:1000080","tgn:7029392"],"placetype":["aat:300007783"],"id":7051195,"name:xx":"Stazione Nasisi"}}
>>>>>>> 03f74aca74312dbeaf24d7e61306dd6a786dc3d0
