{
  "id": 7494561,
  "type": "Feature",
  "properties": {
    "tgn:hierarchy":[
        "tgn:7494561",
        "tgn:1000004",
        "tgn:7001014",
        "tgn:1000141",
        "tgn:7029392"
    ],
    "tgn:id":7494561,
    "tgn:name":"Shanjin Qiao",
    "tgn:placetype":[
        "aat:300007836"
    ]
},
  "bbox": [],
  "geometry": {"coordinates":[120.46975,23.666632],"type":"Point"}
}