<<<<<<< HEAD
{
  "id": 7052659,
  "type": "Feature",
  "properties": {
    "tgn:hierarchy":[
        "tgn:7052659",
        "tgn:7015163",
        "tgn:1000003",
        "tgn:7003121",
        "tgn:1000080",
        "tgn:7029392"
    ],
    "tgn:id":7052659,
    "tgn:name":"Pedras Frittas, Punta",
    "tgn:placetype":[
        "aat:300008777"
    ]
},
  "bbox": [],
  "geometry": {"coordinates":[8.983333,40.6],"type":"Point"}
}
=======
{"geometry":{"type":"Point","coordinates":[8.983333,40.600000]},"type":"Feature","properties":{"hierarchy":["tgn:7052659","tgn:7015163","tgn:1000003","tgn:7003121","tgn:1000080","tgn:7029392"],"placetype":["aat:300008777"],"id":7052659,"name:xx":"Pedras Frittas, Punta"}}
>>>>>>> 03f74aca74312dbeaf24d7e61306dd6a786dc3d0
