<<<<<<< HEAD
{
  "id": 7471640,
  "type": "Feature",
  "properties": {
    "tgn:hierarchy":[
        "tgn:7471640",
        "tgn:7468018",
        "tgn:1000004",
        "tgn:1000141",
        "tgn:7029392"
    ],
    "tgn:id":7471640,
    "tgn:name":"Fanzigou",
    "tgn:placetype":[
        "aat:300008347"
    ]
},
  "bbox": [],
  "geometry": {"coordinates":[120.4325,23.474722],"type":"Point"}
}
=======
{"geometry":{"type":"Point","coordinates":[120.432500,23.474722]},"type":"Feature","properties":{"hierarchy":["tgn:7471640","tgn:7468018","tgn:1000004","tgn:1000141","tgn:7029392"],"placetype":["aat:300008347"],"id":7471640,"name:xx":"Fanzigou"}}
>>>>>>> 03f74aca74312dbeaf24d7e61306dd6a786dc3d0
