{
  "id": 1051691,
  "type": "Feature",
  "properties": {
    "tgn:hierarchy":[
        "tgn:1051691",
        "tgn:1003373",
        "tgn:1000004",
        "tgn:7018214",
        "tgn:7002435",
        "tgn:7029392"
    ],
    "tgn:id":1051691,
    "tgn:name":"Shitkino",
    "tgn:placetype":[
        "aat:300008347"
    ]
},
  "bbox": [],
  "geometry": {"coordinates":[98.35,56.4167],"type":"Point"}
}