{
  "id": 7284919,
  "type": "Feature",
  "properties": {
    "tgn:hierarchy":[
        "tgn:7284919",
        "tgn:1001708",
        "tgn:1000049",
        "tgn:1000002",
        "tgn:7029392"
    ],
    "tgn:id":7284919,
    "tgn:name":"Pollera, Cerro de la",
    "tgn:placetype":[
        "aat:300008795"
    ]
},
  "bbox": [],
  "geometry": {"coordinates":[-69.916667,-33.25],"type":"Point"}
}