{
  "id": 2317154,
  "type": "Feature",
  "properties": {
    "tgn:hierarchy":[
        "tgn:2317154",
        "tgn:7006450",
        "tgn:1000001",
        "tgn:7030547",
        "tgn:7012149",
        "tgn:7029392"
    ],
    "tgn:id":2317154,
    "tgn:name":"Emma Creek",
    "tgn:placetype":[
        "aat:300008706"
    ]
},
  "bbox": [],
  "geometry": {"coordinates":[-148.8167,63.9667],"type":"Point"}
}