{
  "id": 2495054,
  "type": "Feature",
  "properties": {
    "tgn:hierarchy":[
        "tgn:2495054",
        "tgn:1000001",
        "tgn:7012149",
        "tgn:2000977",
        "tgn:7007520",
        "tgn:7029392"
    ],
    "tgn:id":2495054,
    "tgn:name":"Martiny Lake",
    "tgn:placetype":[
        "aat:300006191"
    ]
},
  "bbox": [],
  "geometry": {"coordinates":[-85.1667,43.7167],"type":"Point"}
}