{
  "id": 2363526,
  "type": "Feature",
  "properties": {
    "tgn:hierarchy":[
        "tgn:2363526",
        "tgn:1000001",
        "tgn:7006451",
        "tgn:7012149",
        "tgn:2000103",
        "tgn:7029392"
    ],
    "tgn:id":2363526,
    "tgn:name":"Green Gulch",
    "tgn:placetype":[
        "aat:300008761"
    ]
},
  "bbox": [],
  "geometry": {"coordinates":[-112.3333,34.5167],"type":"Point"}
}