{
  "id": 7070776,
  "type": "Feature",
  "properties": {
    "tgn:hierarchy":[
        "tgn:7070776",
        "tgn:7003669",
        "tgn:1000003",
        "tgn:7000084",
        "tgn:7029392"
    ],
    "tgn:id":7070776,
    "tgn:name":"Steinbuckl",
    "tgn:placetype":[
        "aat:300000206"
    ]
},
  "bbox": [],
  "geometry": {"coordinates":[12.316667,49.05],"type":"Point"}
}