{
  "id": 7581940,
  "type": "Feature",
  "properties": {
    "tgn:hierarchy":[
        "tgn:7581940",
        "tgn:1000004",
        "tgn:1001871",
        "tgn:7000198",
        "tgn:7029392"
    ],
    "tgn:id":7581940,
    "tgn:name:en":"Chatar\u016bw\u0101la Johra",
    "tgn:placetype":[
        "aat:300008688"
    ]
},
  "bbox": [],
  "geometry": {"coordinates":[75.657497,28.778125],"type":"Point"}
}