{
  "id": 2379154,
  "type": "Feature",
  "properties": {
    "tgn:hierarchy":[
        "tgn:2379154",
        "tgn:1000001",
        "tgn:7012149",
        "tgn:7013961",
        "tgn:7029392"
    ],
    "tgn:id":2379154,
    "tgn:name":"Harts Branch",
    "tgn:placetype":[
        "aat:300008699"
    ]
},
  "bbox": [],
  "geometry": {"coordinates":[-81.25,38.45],"type":"Point"}
}