{
  "id": 7191440,
  "type": "Feature",
  "properties": {
    "tgn:hierarchy":[
        "tgn:7191440",
        "tgn:1000003",
        "tgn:7003676",
        "tgn:7000084",
        "tgn:7029392"
    ],
    "tgn:id":7191440,
    "tgn:name":"Fa\u00df-Berg",
    "tgn:placetype":[
        "aat:300008777"
    ]
},
  "bbox": [],
  "geometry": {"coordinates":[10.25,52.916667],"type":"Point"}
}