<<<<<<< HEAD
{
  "id": 7055112,
  "type": "Feature",
  "properties": {
    "tgn:hierarchy":[
        "tgn:7055112",
        "tgn:1003429",
        "tgn:1000003",
        "tgn:7003240",
        "tgn:1000080",
        "tgn:7029392"
    ],
    "tgn:id":7055112,
    "tgn:name":"Poggio San Vicino",
    "tgn:placetype":[
        "aat:300008347"
    ]
},
  "bbox": [],
  "geometry": {"coordinates":[13.066667,43.366667],"type":"Point"}
}
=======
{"geometry":{"type":"Point","coordinates":[13.066667,43.366667]},"type":"Feature","properties":{"hierarchy":["tgn:7055112","tgn:1003429","tgn:1000003","tgn:7003240","tgn:1000080","tgn:7029392"],"placetype":["aat:300008347"],"id":7055112,"name:xx":"Poggio San Vicino"}}
>>>>>>> 03f74aca74312dbeaf24d7e61306dd6a786dc3d0
