<<<<<<< HEAD
{
  "id": 7471490,
  "type": "Feature",
  "properties": {
    "tgn:hierarchy":[
        "tgn:7471490",
        "tgn:1000004",
        "tgn:7490934",
        "tgn:1000141",
        "tgn:7029392"
    ],
    "tgn:id":7471490,
    "tgn:name":"Xingbei",
    "tgn:placetype":[
        "aat:300008347"
    ]
},
  "bbox": [],
  "geometry": {"coordinates":[120.489832,23.204825],"type":"Point"}
}
=======
{"geometry":{"type":"Point","coordinates":[120.489832,23.204825]},"type":"Feature","properties":{"hierarchy":["tgn:7471490","tgn:1000004","tgn:7490934","tgn:1000141","tgn:7029392"],"placetype":["aat:300008347"],"id":7471490,"name:xx":"Xingbei"}}
>>>>>>> 03f74aca74312dbeaf24d7e61306dd6a786dc3d0
