{
  "id": 7394625,
  "type": "Feature",
  "properties": {
    "tgn:hierarchy":[
        "tgn:7394625",
        "tgn:7005581",
        "tgn:1000001",
        "tgn:7005560",
        "tgn:7029392"
    ],
    "tgn:id":7394625,
    "tgn:name":"San Carlos, Sierra de",
    "tgn:placetype":[
        "aat:300008795"
    ]
},
  "bbox": [],
  "geometry": {"coordinates":[-103.966667,28.883333],"type":"Point"}
}