{
  "id": 7294623,
  "type": "Feature",
  "properties": {
    "tgn:hierarchy":[
        "tgn:7294623",
        "tgn:7002832",
        "tgn:7001158",
        "tgn:1000003",
        "tgn:1000095",
        "tgn:7029392"
    ],
    "tgn:id":7294623,
    "tgn:name":"Valles de Cerrato",
    "tgn:placetype":[
        "aat:300387346"
    ]
},
  "bbox": [],
  "geometry": {"coordinates":[-4.333333,41.833333],"type":"Point"}
}