{
  "id": 7517478,
  "type": "Feature",
  "properties": {
    "tgn:hierarchy":[
        "tgn:7517478",
        "tgn:1009227",
        "tgn:7001866",
        "tgn:1000226",
        "tgn:1000006",
        "tgn:7029392"
    ],
    "tgn:id":7517478,
    "tgn:name:en":"McMillan, Mount",
    "tgn:placetype":[
        "aat:300008795"
    ]
},
  "bbox": [],
  "geometry": {"coordinates":[170.683333,-43.433333],"type":"Point"}
}