{
  "id": 7109994,
  "type": "Feature",
  "properties": {
    "tgn:hierarchy":[
        "tgn:7109994",
        "tgn:1000003",
        "tgn:7000094",
        "tgn:7000084",
        "tgn:7029392"
    ],
    "tgn:id":7109994,
    "tgn:name":"Reimershagen",
    "tgn:placetype":[
        "aat:300008347"
    ]
},
  "bbox": [],
  "geometry": {"coordinates":[12.183333,53.666667],"type":"Point"}
}