{
  "id": 7073657,
  "type": "Feature",
  "properties": {
    "tgn:hierarchy":[
        "tgn:7073657",
        "tgn:1000003",
        "tgn:7003688",
        "tgn:7000084",
        "tgn:7029392"
    ],
    "tgn:id":7073657,
    "tgn:name":"S\u00fcder Hesb\u00fcll",
    "tgn:placetype":[
        "aat:300008347"
    ]
},
  "bbox": [],
  "geometry": {"coordinates":[8.716667,54.85],"type":"Point"}
}