{
  "id": 7246279,
  "type": "Feature",
  "properties": {
    "tgn:hierarchy":[
        "tgn:7246279",
        "tgn:7007877",
        "tgn:1000003",
        "tgn:1000063",
        "tgn:4012014",
        "tgn:7029392"
    ],
    "tgn:id":7246279,
    "tgn:name":"Cornet",
    "tgn:placetype":[
        "aat:300008347"
    ]
},
  "bbox": [],
  "geometry": {"coordinates":[3.268923,50.626567],"type":"Point"}
}