{
  "id": 2601333,
  "type": "Feature",
  "properties": {
    "tgn:hierarchy":[
        "tgn:2601333",
        "tgn:1000001",
        "tgn:2000462",
        "tgn:7012149",
        "tgn:7007250",
        "tgn:7029392"
    ],
    "tgn:id":2601333,
    "tgn:name":"Purcell Mountains",
    "tgn:placetype":[
        "aat:300386831"
    ]
},
  "bbox": [],
  "geometry": {"coordinates":[-116.1833,48.8667],"type":"Point"}
}