{
  "id": 7356399,
  "type": "Feature",
  "properties": {
    "tgn:hierarchy":[
        "tgn:7356399",
        "tgn:7005581",
        "tgn:1000001",
        "tgn:7005560",
        "tgn:7029392"
    ],
    "tgn:id":7356399,
    "tgn:name":"Calera de los Ch\u00e1vez",
    "tgn:placetype":[
        "aat:300008347"
    ]
},
  "bbox": [],
  "geometry": {"coordinates":[-107.05,27.983333],"type":"Point"}
}