{
  "id": 7244001,
  "type": "Feature",
  "properties": {
    "tgn:hierarchy":[
        "tgn:7244001",
        "tgn:7003466",
        "tgn:1000003",
        "tgn:1000063",
        "tgn:4012014",
        "tgn:7029392"
    ],
    "tgn:id":7244001,
    "tgn:name":"Jean, Bois",
    "tgn:placetype":[
        "aat:300008863"
    ]
},
  "bbox": [],
  "geometry": {"coordinates":[4.866667,49.866667],"type":"Point"}
}