{
  "id": 7559996,
  "type": "Feature",
  "properties": {
    "tgn:hierarchy":[
        "tgn:7559996",
        "tgn:1000004",
        "tgn:7000198",
        "tgn:7016722",
        "tgn:7029392"
    ],
    "tgn:id":7559996,
    "tgn:name:en":"Nagla B\u0101t",
    "tgn:placetype":[
        "aat:300008347"
    ]
},
  "bbox": [],
  "geometry": {"coordinates":[79.248376,27.176773],"type":"Point"}
}