{
  "id": 2225887,
  "type": "Feature",
  "properties": {
    "tgn:hierarchy":[
        "tgn:2225887",
        "tgn:1000001",
        "tgn:7012149",
        "tgn:2000203",
        "tgn:7007158",
        "tgn:7029392"
    ],
    "tgn:id":2225887,
    "tgn:name":"Cat Mountain",
    "tgn:placetype":[
        "aat:300008798"
    ]
},
  "bbox": [],
  "geometry": {"coordinates":[-105.2833,37.3833],"type":"Point"}
}