{
  "id": 7546748,
  "type": "Feature",
  "properties": {
    "tgn:hierarchy":[
        "tgn:7546748",
        "tgn:1000004",
        "tgn:7000198",
        "tgn:7000799",
        "tgn:7029392"
    ],
    "tgn:id":7546748,
    "tgn:name:en":"Bein River",
    "tgn:placetype":[
        "aat:300008699"
    ]
},
  "bbox": [],
  "geometry": {"coordinates":[75.002693,32.067054],"type":"Point"}
}