<<<<<<< HEAD
{
  "id": 2404724,
  "type": "Feature",
  "properties": {
    "tgn:hierarchy":[
        "tgn:2404724",
        "tgn:1000001",
        "tgn:7012149",
        "tgn:2002067",
        "tgn:7007826",
        "tgn:7029392"
    ],
    "tgn:id":2404724,
    "tgn:name":"Huckleberry Creek",
    "tgn:placetype":[
        "aat:300008706"
    ]
},
  "bbox": [],
  "geometry": {"coordinates":[-94.0667,31.2667],"type":"Point"}
}
=======
{"geometry":{"type":"Point","coordinates":[-94.066700,31.266700]},"type":"Feature","properties":{"hierarchy":["tgn:2404724","tgn:1000001","tgn:7012149","tgn:2002067","tgn:7007826","tgn:7029392"],"placetype":["aat:300008706"],"id":2404724,"name:xx":"Huckleberry Creek"}}
>>>>>>> 03f74aca74312dbeaf24d7e61306dd6a786dc3d0
