{
  "id": 7110943,
  "type": "Feature",
  "properties": {
    "tgn:hierarchy":[
        "tgn:7110943",
        "tgn:7003692",
        "tgn:1000003",
        "tgn:7000084",
        "tgn:7029392"
    ],
    "tgn:id":7110943,
    "tgn:name":"Reichenbacher Hof",
    "tgn:placetype":[
        "aat:300000206"
    ]
},
  "bbox": [],
  "geometry": {"coordinates":[8.866667,48.283333],"type":"Point"}
}