{
  "id": 2586704,
  "type": "Feature",
  "properties": {
    "tgn:hierarchy":[
        "tgn:2586704",
        "tgn:2002238",
        "tgn:1000001",
        "tgn:7012149",
        "tgn:7007920",
        "tgn:7029392"
    ],
    "tgn:id":2586704,
    "tgn:name":"Pizarro",
    "tgn:placetype":[
        "aat:300008347"
    ]
},
  "bbox": [],
  "geometry": {"coordinates":[-118.4333,46.95],"type":"Point"}
}