<<<<<<< HEAD
{
  "id": 2408029,
  "type": "Feature",
  "properties": {
    "tgn:hierarchy":[
        "tgn:2408029",
        "tgn:1000001",
        "tgn:7012149",
        "tgn:2002127",
        "tgn:7007827",
        "tgn:7029392"
    ],
    "tgn:id":2408029,
    "tgn:name":"Hurricane Fields",
    "tgn:placetype":[
        "aat:300055621"
    ]
},
  "bbox": [],
  "geometry": {"coordinates":[-113.3,37.15],"type":"Point"}
}
=======
{"geometry":{"type":"Point","coordinates":[-113.300000,37.150000]},"type":"Feature","properties":{"hierarchy":["tgn:2408029","tgn:1000001","tgn:7012149","tgn:2002127","tgn:7007827","tgn:7029392"],"placetype":["aat:300055621"],"id":2408029,"name:xx":"Hurricane Fields"}}
>>>>>>> 03f74aca74312dbeaf24d7e61306dd6a786dc3d0
