{
  "id": 2765672,
  "type": "Feature",
  "properties": {
    "tgn:hierarchy":[
        "tgn:2765672",
        "tgn:1000001",
        "tgn:2000469",
        "tgn:7012149",
        "tgn:7007250",
        "tgn:7029392"
    ],
    "tgn:id":2765672,
    "tgn:name":"White Creek",
    "tgn:placetype":[
        "aat:300008706"
    ]
},
  "bbox": [],
  "geometry": {"coordinates":[-116.0167,46.5833],"type":"Point"}
}