{
  "id": 1018515,
  "type": "Feature",
  "properties": {
    "tgn:hierarchy":[
        "tgn:1018515",
        "tgn:1000001",
        "tgn:7005590",
        "tgn:7005560",
        "tgn:7029392"
    ],
    "tgn:id":1018515,
    "tgn:name":"Tlazazalca",
    "tgn:placetype":[
        "aat:300008347"
    ]
},
  "bbox": [],
  "geometry": {"coordinates":[-102.066667,19.966667],"type":"Point"}
}