{
  "id": 2292143,
  "type": "Feature",
  "properties": {
    "tgn:hierarchy":[
        "tgn:2292143",
        "tgn:1000001",
        "tgn:7012149",
        "tgn:2001899",
        "tgn:7007825",
        "tgn:7029392"
    ],
    "tgn:id":2292143,
    "tgn:name":"Donaldson Creek",
    "tgn:placetype":[
        "aat:300008706"
    ]
},
  "bbox": [],
  "geometry": {"coordinates":[-87.4167,36.5333],"type":"Point"}
}