{
  "id": 2031557,
  "type": "Feature",
  "properties": {
    "tgn:hierarchy":[
        "tgn:2031557",
        "tgn:1000001",
        "tgn:1002327",
        "tgn:7012149",
        "tgn:7007252",
        "tgn:7029392"
    ],
    "tgn:id":2031557,
    "tgn:name":"Daleville",
    "tgn:placetype":[
        "aat:300008347"
    ]
},
  "bbox": [],
  "geometry": {"coordinates":[-85.55,40.1167],"type":"Point"}
}