{
  "id": 7461271,
  "type": "Feature",
  "properties": {
    "tgn:hierarchy":[
        "tgn:7461271",
        "tgn:7002445",
        "tgn:1000003",
        "tgn:7008166",
        "tgn:7008591",
        "tgn:7029392"
    ],
    "tgn:id":7461271,
    "tgn:name:en":"Kelder Steel",
    "tgn:placetype":[
        "aat:300386918"
    ]
},
  "bbox": [],
  "geometry": {"coordinates":[-0.666667,54.516667],"type":"Point"}
}