{
  "id": 2684564,
  "type": "Feature",
  "properties": {
    "tgn:hierarchy":[
        "tgn:2684564",
        "tgn:1000001",
        "tgn:7012149",
        "tgn:2001516",
        "tgn:7007709",
        "tgn:7029392"
    ],
    "tgn:id":2684564,
    "tgn:name":"Spillcorn Creek",
    "tgn:placetype":[
        "aat:300008706"
    ]
},
  "bbox": [],
  "geometry": {"coordinates":[-82.6333,35.95],"type":"Point"}
}