{
  "id": 7034960,
  "type": "Feature",
  "properties": {
    "tgn:hierarchy":[
        "tgn:7034960",
        "tgn:7015163",
        "tgn:1000003",
        "tgn:7003121",
        "tgn:1000080",
        "tgn:7029392"
    ],
    "tgn:id":7034960,
    "tgn:name":"Torre de Bantine Sale",
    "tgn:placetype":[
        "aat:300004847"
    ]
},
  "bbox": [],
  "geometry": {"coordinates":[8.196944,40.678056],"type":"Point"}
}