<<<<<<< HEAD
{
  "id": 2400216,
  "type": "Feature",
  "properties": {
    "tgn:hierarchy":[
        "tgn:2400216",
        "tgn:1000001",
        "tgn:7012149",
        "tgn:2002274",
        "tgn:7013961",
        "tgn:7029392"
    ],
    "tgn:id":2400216,
    "tgn:name":"Horse Creek",
    "tgn:placetype":[
        "aat:300008706"
    ]
},
  "bbox": [],
  "geometry": {"coordinates":[-81.8,37.4],"type":"Point"}
}
=======
{"geometry":{"type":"Point","coordinates":[-81.800000,37.400000]},"type":"Feature","properties":{"hierarchy":["tgn:2400216","tgn:1000001","tgn:7012149","tgn:2002274","tgn:7013961","tgn:7029392"],"placetype":["aat:300008706"],"id":2400216,"name:xx":"Horse Creek"}}
>>>>>>> 03f74aca74312dbeaf24d7e61306dd6a786dc3d0
