{
  "id": 7230023,
  "type": "Feature",
  "properties": {
    "tgn:hierarchy":[
        "tgn:7230023",
        "tgn:7011170",
        "tgn:7002715",
        "tgn:1000003",
        "tgn:1000074",
        "tgn:7029392"
    ],
    "tgn:id":7230023,
    "tgn:name":"L\u00e1kkoma",
    "tgn:placetype":[
        "aat:300008347"
    ]
},
  "bbox": [],
  "geometry": {"coordinates":[25.533333,40.433333],"type":"Point"}
}