{
  "id": 7290184,
  "type": "Feature",
  "properties": {
    "tgn:hierarchy":[
        "tgn:7290184",
        "tgn:1001702",
        "tgn:1000049",
        "tgn:1000002",
        "tgn:7029392"
    ],
    "tgn:id":7290184,
    "tgn:name":"Duncan, Isla",
    "tgn:placetype":[
        "aat:300008791"
    ]
},
  "bbox": [],
  "geometry": {"coordinates":[-75.266667,-51.166667],"type":"Point"}
}