{
  "id": 1029085,
  "type": "Feature",
  "properties": {
    "tgn:hierarchy":[
        "tgn:1029085",
        "tgn:7002445",
        "tgn:1000003",
        "tgn:7008178",
        "tgn:7008591",
        "tgn:7029392"
    ],
    "tgn:id":1029085,
    "tgn:name:en":"Dunchurch",
    "tgn:placetype":[
        "aat:300008347"
    ]
},
  "bbox": [],
  "geometry": {"coordinates":[-1.283333,52.333333],"type":"Point"}
}