{
  "id": 1114722,
  "type": "Feature",
  "properties": {
    "tgn:hierarchy":[
        "tgn:1114722",
        "tgn:1000617",
        "tgn:1000001",
        "tgn:7005554",
        "tgn:7029392"
    ],
    "tgn:id":1114722,
    "tgn:name":"Caratasca, Laguna de",
    "tgn:placetype":[
        "aat:300008679"
    ]
},
  "bbox": [],
  "geometry": {"coordinates":[-83.9167,15.3833],"type":"Point"}
}