<<<<<<< HEAD
{
  "id": 7174423,
  "type": "Feature",
  "properties": {
    "tgn:hierarchy":[
        "tgn:7174423",
        "tgn:7003692",
        "tgn:1000003",
        "tgn:7000084",
        "tgn:7029392"
    ],
    "tgn:id":7174423,
    "tgn:name":"Grombach",
    "tgn:placetype":[
        "aat:300008347"
    ]
},
  "bbox": [],
  "geometry": {"coordinates":[8.994167,49.228333],"type":"Point"}
}
=======
{"geometry":{"type":"Point","coordinates":[8.994167,49.228333]},"type":"Feature","properties":{"hierarchy":["tgn:7174423","tgn:7003692","tgn:1000003","tgn:7000084","tgn:7029392"],"placetype":["aat:300008347"],"id":7174423,"name:xx":"Grombach"}}
>>>>>>> 03f74aca74312dbeaf24d7e61306dd6a786dc3d0
