{
  "id": 2201871,
  "type": "Feature",
  "properties": {
    "tgn:hierarchy":[
        "tgn:2201871",
        "tgn:1000001",
        "tgn:1002461",
        "tgn:7012149",
        "tgn:7007159",
        "tgn:7029392"
    ],
    "tgn:id":2201871,
    "tgn:name":"Buck Hill",
    "tgn:placetype":[
        "aat:300008798"
    ]
},
  "bbox": [],
  "geometry": {"coordinates":[-72.6333,42.0167],"type":"Point"}
}