{
  "id": 7023122,
  "type": "Feature",
  "properties": {
    "tgn:hierarchy":[
        "tgn:7023122",
        "tgn:1000001",
        "tgn:7012149",
        "tgn:7007827",
        "tgn:7029392"
    ],
    "tgn:id":7023122,
    "tgn:name":"Sevier Bridge Reservoir",
    "tgn:placetype":[
        "aat:300006191"
    ]
},
  "bbox": [],
  "geometry": {"coordinates":[-112.0167,39.3667],"type":"Point"}
}