{
  "id": 2558507,
  "type": "Feature",
  "properties": {
    "tgn:hierarchy":[
        "tgn:2558507",
        "tgn:1000001",
        "tgn:2001368",
        "tgn:7012149",
        "tgn:7007525",
        "tgn:7029392"
    ],
    "tgn:id":2558507,
    "tgn:name":"Oliver",
    "tgn:placetype":[
        "aat:300008347"
    ]
},
  "bbox": [],
  "geometry": {"coordinates":[-103.7833,41.2167],"type":"Point"}
}