{
  "id": 7050937,
  "type": "Feature",
  "properties": {
    "tgn:hierarchy":[
        "tgn:7050937",
        "tgn:7003163",
        "tgn:1000003",
        "tgn:7009760",
        "tgn:1000080",
        "tgn:7029392"
    ],
    "tgn:id":7050937,
    "tgn:name":"Lamole",
    "tgn:placetype":[
        "aat:300008347"
    ]
},
  "bbox": [],
  "geometry": {"coordinates":[11.35,43.55],"type":"Point"}
}