{
  "id": 2243809,
  "type": "Feature",
  "properties": {
    "tgn:hierarchy":[
        "tgn:2243809",
        "tgn:1000001",
        "tgn:2002133",
        "tgn:7012149",
        "tgn:7007828",
        "tgn:7029392"
    ],
    "tgn:id":2243809,
    "tgn:name":"Cleveland Corners",
    "tgn:placetype":[
        "aat:300008347"
    ]
},
  "bbox": [],
  "geometry": {"coordinates":[-72.55,44.5833],"type":"Point"}
}