{
  "id": 4000395,
  "type": "Feature",
  "properties": {
    "tgn:hierarchy":[
        "tgn:4000395",
        "tgn:7002758",
        "tgn:7002817",
        "tgn:1000003",
        "tgn:1000095",
        "tgn:7029392"
    ],
    "tgn:id":4000395,
    "tgn:name":"Adamuz",
    "tgn:placetype":[
        "aat:300008347"
    ]
},
  "bbox": [],
  "geometry": {"coordinates":[-4.516667,38.033333],"type":"Point"}
}