{
  "id": 2510515,
  "type": "Feature",
  "properties": {
    "tgn:hierarchy":[
        "tgn:2510515",
        "tgn:1000001",
        "tgn:2001431",
        "tgn:7012149",
        "tgn:7007566",
        "tgn:7029392"
    ],
    "tgn:id":2510515,
    "tgn:name":"Middle Tank",
    "tgn:placetype":[
        "aat:300006191"
    ]
},
  "bbox": [],
  "geometry": {"coordinates":[-107.4333,34.5833],"type":"Point"}
}