{
  "id": 2026129,
  "type": "Feature",
  "properties": {
    "tgn:hierarchy":[
        "tgn:2026129",
        "tgn:1000001",
        "tgn:7012149",
        "tgn:2000479",
        "tgn:7007250",
        "tgn:7029392"
    ],
    "tgn:id":2026129,
    "tgn:name":"Silver Sands Beach",
    "tgn:placetype":[
        "aat:300008347"
    ]
},
  "bbox": [],
  "geometry": {"coordinates":[-116.8833,47.8833],"type":"Point"}
}