{
  "id": 7322892,
  "type": "Feature",
  "properties": {
    "tgn:hierarchy":[
        "tgn:7322892",
        "tgn:7002813",
        "tgn:7002758",
        "tgn:1000003",
        "tgn:1000095",
        "tgn:7029392"
    ],
    "tgn:id":7322892,
    "tgn:name":"Salado, Arroyo del",
    "tgn:placetype":[
        "aat:300008699"
    ]
},
  "bbox": [],
  "geometry": {"coordinates":[-5.316667,36.966667],"type":"Point"}
}