{
  "id": 7477518,
  "type": "Feature",
  "properties": {
    "tgn:hierarchy":[
        "tgn:7477518",
        "tgn:7001010",
        "tgn:1000004",
        "tgn:1000141",
        "tgn:7029392"
    ],
    "tgn:id":7477518,
    "tgn:name":"Fengyi Shequ",
    "tgn:placetype":[
        "aat:300000498"
    ]
},
  "bbox": [],
  "geometry": {"coordinates":[121.446333,23.751197],"type":"Point"}
}