{
  "id": 7073922,
  "type": "Feature",
  "properties": {
    "tgn:hierarchy":[
        "tgn:7073922",
        "tgn:7003692",
        "tgn:1000003",
        "tgn:7000084",
        "tgn:7029392"
    ],
    "tgn:id":7073922,
    "tgn:name":"Ruine Straubenhart",
    "tgn:placetype":[
        "aat:300008057"
    ]
},
  "bbox": [],
  "geometry": {"coordinates":[8.566667,48.833333],"type":"Point"}
}