{
  "id": 2379874,
  "type": "Feature",
  "properties": {
    "tgn:hierarchy":[
        "tgn:2379874",
        "tgn:1000001",
        "tgn:7012149",
        "tgn:2000969",
        "tgn:7007520",
        "tgn:7029392"
    ],
    "tgn:id":2379874,
    "tgn:name":"Hat Island",
    "tgn:placetype":[
        "aat:300008791"
    ]
},
  "bbox": [],
  "geometry": {"coordinates":[-88.7667,47.9833],"type":"Point"}
}