{
  "id": 7098691,
  "type": "Feature",
  "properties": {
    "tgn:hierarchy":[
        "tgn:7098691",
        "tgn:7003692",
        "tgn:1000003",
        "tgn:7000084",
        "tgn:7029392"
    ],
    "tgn:id":7098691,
    "tgn:name":"Silberbrunnen",
    "tgn:placetype":[
        "aat:300000206"
    ]
},
  "bbox": [],
  "geometry": {"coordinates":[7.716667,48.116667],"type":"Point"}
}