{
  "id": 1039575,
  "type": "Feature",
  "properties": {
    "tgn:hierarchy":[
        "tgn:1039575",
        "tgn:1000003",
        "tgn:7003677",
        "tgn:7000084",
        "tgn:7029392"
    ],
    "tgn:id":1039575,
    "tgn:name":"Herscheid",
    "tgn:placetype":[
        "aat:300008347"
    ]
},
  "bbox": [],
  "geometry": {"coordinates":[7.75,51.183333],"type":"Point"}
}