{
  "id": 7592627,
  "type": "Feature",
  "properties": {
    "tgn:hierarchy":[
        "tgn:7592627",
        "tgn:1000004",
        "tgn:7000198",
        "tgn:7000799",
        "tgn:7029392"
    ],
    "tgn:id":7592627,
    "tgn:name:en":"S\u012bjangar",
    "tgn:placetype":[
        "aat:300008347"
    ]
},
  "bbox": [],
  "geometry": {"coordinates":[74.307809,33.246723],"type":"Point"}
}