<<<<<<< HEAD
{
  "id": 7055966,
  "type": "Feature",
  "properties": {
    "tgn:hierarchy":[
        "tgn:7055966",
        "tgn:1003506",
        "tgn:1000003",
        "tgn:7002993",
        "tgn:1000080",
        "tgn:7029392"
    ],
    "tgn:id":7055966,
    "tgn:name":"Ombladet, Cima",
    "tgn:placetype":[
        "aat:300008795"
    ]
},
  "bbox": [],
  "geometry": {"coordinates":[12.816667,46.6],"type":"Point"}
}
=======
{"geometry":{"type":"Point","coordinates":[12.816667,46.600000]},"type":"Feature","properties":{"hierarchy":["tgn:7055966","tgn:1003506","tgn:1000003","tgn:7002993","tgn:1000080","tgn:7029392"],"placetype":["aat:300008795"],"id":7055966,"name:xx":"Ombladet, Cima"}}
>>>>>>> 03f74aca74312dbeaf24d7e61306dd6a786dc3d0
