{
  "id": 7305627,
  "type": "Feature",
  "properties": {
    "tgn:hierarchy":[
        "tgn:7305627",
        "tgn:7002836",
        "tgn:7016622",
        "tgn:1000003",
        "tgn:1000095",
        "tgn:7029392"
    ],
    "tgn:id":7305627,
    "tgn:name":"Larga, Punta",
    "tgn:placetype":[
        "aat:300386846"
    ]
},
  "bbox": [],
  "geometry": {"coordinates":[-16.35,28.35],"type":"Point"}
}