{
  "id": 2680005,
  "type": "Feature",
  "properties": {
    "tgn:hierarchy":[
        "tgn:2680005",
        "tgn:1000001",
        "tgn:7012149",
        "tgn:7007157",
        "tgn:2000188",
        "tgn:7029392"
    ],
    "tgn:id":2680005,
    "tgn:name":"South Fork Slate Creek",
    "tgn:placetype":[
        "aat:300008706"
    ]
},
  "bbox": [],
  "geometry": {"coordinates":[-122.5333,40.9667],"type":"Point"}
}