{
  "id": 2018890,
  "type": "Feature",
  "properties": {
    "tgn:hierarchy":[
        "tgn:2018890",
        "tgn:1000001",
        "tgn:7012149",
        "tgn:1002749",
        "tgn:7007240",
        "tgn:7029392"
    ],
    "tgn:id":2018890,
    "tgn:name":"Christmas",
    "tgn:placetype":[
        "aat:300008347"
    ]
},
  "bbox": [],
  "geometry": {"coordinates":[-81.0167,28.5333],"type":"Point"}
}