{
  "id": 7234579,
  "type": "Feature",
  "properties": {
    "tgn:hierarchy":[
        "tgn:7234579",
        "tgn:7002715",
        "tgn:7002731",
        "tgn:1000003",
        "tgn:1000074",
        "tgn:7029392"
    ],
    "tgn:id":7234579,
    "tgn:name":"Aspr\u00f3lakkos",
    "tgn:placetype":[
        "aat:300008699"
    ]
},
  "bbox": [],
  "geometry": {"coordinates":[23.833333,40.466667],"type":"Point"}
}