{
  "id": 2309230,
  "type": "Feature",
  "properties": {
    "tgn:hierarchy":[
        "tgn:2309230",
        "tgn:1000001",
        "tgn:2001633",
        "tgn:7012149",
        "tgn:7007707",
        "tgn:7029392"
    ],
    "tgn:id":2309230,
    "tgn:name":"East Spaniard Creek",
    "tgn:placetype":[
        "aat:300008706"
    ]
},
  "bbox": [],
  "geometry": {"coordinates":[-95.05,35.7833],"type":"Point"}
}