{
  "id": 7235685,
  "type": "Feature",
  "properties": {
    "tgn:hierarchy":[
        "tgn:7235685",
        "tgn:7002724",
        "tgn:7002715",
        "tgn:1000003",
        "tgn:1000074",
        "tgn:7029392"
    ],
    "tgn:id":7235685,
    "tgn:name":"\u00c1yios Yerman\u00f3s",
    "tgn:placetype":[
        "aat:300008347"
    ]
},
  "bbox": [],
  "geometry": {"coordinates":[21.166667,40.833333],"type":"Point"}
}