{
  "id": 2567151,
  "type": "Feature",
  "properties": {
    "tgn:hierarchy":[
        "tgn:2567151",
        "tgn:1000001",
        "tgn:7012149",
        "tgn:1002669",
        "tgn:7007710",
        "tgn:7029392"
    ],
    "tgn:id":2567151,
    "tgn:name":"Panther Hollow",
    "tgn:placetype":[
        "aat:300008761"
    ]
},
  "bbox": [],
  "geometry": {"coordinates":[-77.4833,40.7833],"type":"Point"}
}