{
  "id": 2269625,
  "type": "Feature",
  "properties": {
    "tgn:hierarchy":[
        "tgn:2269625",
        "tgn:1000001",
        "tgn:7012149",
        "tgn:2000204",
        "tgn:7007158",
        "tgn:7029392"
    ],
    "tgn:id":2269625,
    "tgn:name":"Crowley Drain Canal",
    "tgn:placetype":[
        "aat:300006075"
    ]
},
  "bbox": [],
  "geometry": {"coordinates":[-103.8167,38.1667],"type":"Point"}
}