{
  "id": 2709266,
  "type": "Feature",
  "properties": {
    "tgn:hierarchy":[
        "tgn:2709266",
        "tgn:1000001",
        "tgn:7012149",
        "tgn:2001279",
        "tgn:7007524",
        "tgn:7029392"
    ],
    "tgn:id":2709266,
    "tgn:name":"Table Mountain",
    "tgn:placetype":[
        "aat:300008798"
    ]
},
  "bbox": [],
  "geometry": {"coordinates":[-113.7167,46.0667],"type":"Point"}
}