{
  "id": 2753777,
  "type": "Feature",
  "properties": {
    "tgn:hierarchy":[
        "tgn:2753777",
        "tgn:1000001",
        "tgn:2002368",
        "tgn:7012149",
        "tgn:7007923",
        "tgn:7029392"
    ],
    "tgn:id":2753777,
    "tgn:name":"Watkins Draw",
    "tgn:placetype":[
        "aat:300008761"
    ]
},
  "bbox": [],
  "geometry": {"coordinates":[-106.4333,42.0667],"type":"Point"}
}