{
  "id": 1055967,
  "type": "Feature",
  "properties": {
    "tgn:hierarchy":[
        "tgn:1055967",
        "tgn:1000004",
        "tgn:1003405",
        "tgn:7018214",
        "tgn:7002435",
        "tgn:7029392"
    ],
    "tgn:id":1055967,
    "tgn:name":"Krymskiy",
    "tgn:placetype":[
        "aat:300008347"
    ]
},
  "bbox": [],
  "geometry": {"coordinates":[40.7667,47.6667],"type":"Point"}
}