{
  "id": 2355251,
  "type": "Feature",
  "properties": {
    "tgn:hierarchy":[
        "tgn:2355251",
        "tgn:7013349",
        "tgn:1000001",
        "tgn:7012149",
        "tgn:7007708",
        "tgn:7029392"
    ],
    "tgn:id":2355251,
    "tgn:name":"Goodwin Gulch",
    "tgn:placetype":[
        "aat:300008761"
    ]
},
  "bbox": [],
  "geometry": {"coordinates":[-117.2333,44.7833],"type":"Point"}
}