{
  "id": 7336835,
  "type": "Feature",
  "properties": {
    "tgn:hierarchy":[
        "tgn:7336835",
        "tgn:7001122",
        "tgn:1000003",
        "tgn:7002765",
        "tgn:1000095",
        "tgn:7029392"
    ],
    "tgn:id":7336835,
    "tgn:name":"Estells de Fuera",
    "tgn:placetype":[
        "aat:300008791"
    ]
},
  "bbox": [],
  "geometry": {"coordinates":[2.933333,39.116667],"type":"Point"}
}