{
  "id": 2099327,
  "type": "Feature",
  "properties": {
    "tgn:hierarchy":[
        "tgn:2099327",
        "tgn:1000001",
        "tgn:7012149",
        "tgn:7015666",
        "tgn:7007825",
        "tgn:7029392"
    ],
    "tgn:id":2099327,
    "tgn:name":"Graham",
    "tgn:placetype":[
        "aat:300008347",
        "aat:300387210"
    ]
},
  "bbox": [],
  "geometry": {"coordinates":[-87.45,35.8667],"type":"Point"}
}