{
  "id": 2588509,
  "type": "Feature",
  "properties": {
    "tgn:hierarchy":[
        "tgn:2588509",
        "tgn:1000001",
        "tgn:7012149",
        "tgn:7007157",
        "tgn:2000188",
        "tgn:7029392"
    ],
    "tgn:id":2588509,
    "tgn:name":"Plum Valley",
    "tgn:placetype":[
        "aat:300008761"
    ]
},
  "bbox": [],
  "geometry": {"coordinates":[-121.3667,40.6833],"type":"Point"}
}