{
  "id": 7486247,
  "type": "Feature",
  "properties": {
    "tgn:hierarchy":[
        "tgn:7486247",
        "tgn:1000004",
        "tgn:7491221",
        "tgn:1000141",
        "tgn:7029392"
    ],
    "tgn:id":7486247,
    "tgn:name":"Nishui Xi",
    "tgn:placetype":[
        "aat:300008699"
    ]
},
  "bbox": [],
  "geometry": {"coordinates":[121.199444,23.055556],"type":"Point"}
}