<<<<<<< HEAD
{
  "id": 7486247,
  "type": "Feature",
  "properties": {
    "tgn:hierarchy":[
        "tgn:7486247",
        "tgn:1000004",
        "tgn:7491221",
        "tgn:1000141",
        "tgn:7029392"
    ],
    "tgn:id":7486247,
    "tgn:name":"Nishui Xi",
    "tgn:placetype":[
        "aat:300008699"
    ]
},
  "bbox": [],
  "geometry": {"coordinates":[121.199444,23.055556],"type":"Point"}
}
=======
{"geometry":{"type":"Point","coordinates":[121.199444,23.055556]},"type":"Feature","properties":{"hierarchy":["tgn:7486247","tgn:1000004","tgn:7491221","tgn:1000141","tgn:7029392"],"placetype":["aat:300008699"],"id":7486247,"name:xx":"Nishui Xi"}}
>>>>>>> 03f74aca74312dbeaf24d7e61306dd6a786dc3d0
