<<<<<<< HEAD
{
  "id": 2337262,
  "type": "Feature",
  "properties": {
    "tgn:hierarchy":[
        "tgn:2337262",
        "tgn:1000001",
        "tgn:1002260",
        "tgn:7012149",
        "tgn:7007920",
        "tgn:7029392"
    ],
    "tgn:id":2337262,
    "tgn:name":"Fourth Of July Mountain",
    "tgn:placetype":[
        "aat:300008798"
    ]
},
  "bbox": [],
  "geometry": {"coordinates":[-120.15,47.95],"type":"Point"}
}
=======
{"geometry":{"type":"Point","coordinates":[-120.150000,47.950000]},"type":"Feature","properties":{"hierarchy":["tgn:2337262","tgn:1000001","tgn:1002260","tgn:7012149","tgn:7007920","tgn:7029392"],"placetype":["aat:300008798"],"id":2337262,"name:xx":"Fourth Of July Mountain"}}
>>>>>>> 03f74aca74312dbeaf24d7e61306dd6a786dc3d0
