{
  "id": 7496400,
  "type": "Feature",
  "properties": {
    "tgn:hierarchy":[
        "tgn:7496400",
        "tgn:7001004",
        "tgn:1000004",
        "tgn:1000141",
        "tgn:7029392"
    ],
    "tgn:id":7496400,
    "tgn:name":"Jili Qiao",
    "tgn:placetype":[
        "aat:300007836"
    ]
},
  "bbox": [],
  "geometry": {"coordinates":[120.519524,22.855473],"type":"Point"}
}