{
  "id": 7577146,
  "type": "Feature",
  "properties": {
    "tgn:hierarchy":[
        "tgn:7577146",
        "tgn:1000004",
        "tgn:7000198",
        "tgn:1001882",
        "tgn:7029392"
    ],
    "tgn:id":7577146,
    "tgn:name:en":"Linganamakki",
    "tgn:placetype":[
        "aat:300008347"
    ]
},
  "bbox": [],
  "geometry": {"coordinates":[74.85,14.166667],"type":"Point"}
}