{
  "id": 7284266,
  "type": "Feature",
  "properties": {
    "tgn:hierarchy":[
        "tgn:7284266",
        "tgn:1001630",
        "tgn:1000049",
        "tgn:1000002",
        "tgn:7029392"
    ],
    "tgn:id":7284266,
    "tgn:name":"Pinguito",
    "tgn:placetype":[
        "aat:300008795"
    ]
},
  "bbox": [],
  "geometry": {"coordinates":[-69.616667,-26.716667],"type":"Point"}
}