<<<<<<< HEAD
{
  "id": 7170903,
  "type": "Feature",
  "properties": {
    "tgn:hierarchy":[
        "tgn:7170903",
        "tgn:1000003",
        "tgn:7003687",
        "tgn:7000084",
        "tgn:7029392"
    ],
    "tgn:id":7170903,
    "tgn:name":"Himmelreich",
    "tgn:placetype":[
        "aat:300008347"
    ]
},
  "bbox": [],
  "geometry": {"coordinates":[11.166667,52.483333],"type":"Point"}
}
=======
{"geometry":{"type":"Point","coordinates":[11.166667,52.483333]},"type":"Feature","properties":{"hierarchy":["tgn:7170903","tgn:1000003","tgn:7003687","tgn:7000084","tgn:7029392"],"placetype":["aat:300008347"],"id":7170903,"name:xx":"Himmelreich"}}
>>>>>>> 03f74aca74312dbeaf24d7e61306dd6a786dc3d0
