{
  "id": 7370672,
  "type": "Feature",
  "properties": {
    "tgn:hierarchy":[
        "tgn:7370672",
        "tgn:1000001",
        "tgn:7005599",
        "tgn:7005560",
        "tgn:7029392"
    ],
    "tgn:id":7370672,
    "tgn:name":"Huilozintla",
    "tgn:placetype":[
        "aat:300008347"
    ]
},
  "bbox": [],
  "geometry": {"coordinates":[-97.583333,20.883333],"type":"Point"}
}