{
  "id": 7035396,
  "type": "Feature",
  "properties": {
    "tgn:hierarchy":[
        "tgn:7035396",
        "tgn:1003459",
        "tgn:1000003",
        "tgn:7002993",
        "tgn:1000080",
        "tgn:7029392"
    ],
    "tgn:id":7035396,
    "tgn:name":"Doberd\u00f2, Lago di",
    "tgn:placetype":[
        "aat:300008680"
    ]
},
  "bbox": [],
  "geometry": {"coordinates":[13.561389,45.830278],"type":"Point"}
}