<<<<<<< HEAD
{
  "id": 2155440,
  "type": "Feature",
  "properties": {
    "tgn:hierarchy":[
        "tgn:2155440",
        "tgn:1000001",
        "tgn:1002216",
        "tgn:7012149",
        "tgn:7007706",
        "tgn:7029392"
    ],
    "tgn:id":2155440,
    "tgn:name":"Bear Pond",
    "tgn:placetype":[
        "aat:300006191"
    ]
},
  "bbox": [],
  "geometry": {"coordinates":[-84.5,39.5167],"type":"Point"}
}
=======
{"geometry":{"type":"Point","coordinates":[-84.500000,39.516700]},"type":"Feature","properties":{"hierarchy":["tgn:2155440","tgn:1000001","tgn:1002216","tgn:7012149","tgn:7007706","tgn:7029392"],"placetype":["aat:300006191"],"id":2155440,"name:xx":"Bear Pond"}}
>>>>>>> 03f74aca74312dbeaf24d7e61306dd6a786dc3d0
