{
  "id": 2246976,
  "type": "Feature",
  "properties": {
    "tgn:hierarchy":[
        "tgn:2246976",
        "tgn:1000001",
        "tgn:7012149",
        "tgn:2001280",
        "tgn:7007524",
        "tgn:7029392"
    ],
    "tgn:id":2246976,
    "tgn:name":"Cockerel Spring",
    "tgn:placetype":[
        "aat:300008697"
    ]
},
  "bbox": [],
  "geometry": {"coordinates":[-110.7167,48.4333],"type":"Point"}
}