{
  "id": 7112968,
  "type": "Feature",
  "properties": {
    "tgn:hierarchy":[
        "tgn:7112968",
        "tgn:1000003",
        "tgn:7003685",
        "tgn:7000084",
        "tgn:7029392"
    ],
    "tgn:id":7112968,
    "tgn:name":"R\u00f6dingen",
    "tgn:placetype":[
        "aat:300008347"
    ]
},
  "bbox": [],
  "geometry": {"coordinates":[13.116667,51.55],"type":"Point"}
}