{
  "id": 2321990,
  "type": "Feature",
  "properties": {
    "tgn:hierarchy":[
        "tgn:2321990",
        "tgn:1000001",
        "tgn:1002840",
        "tgn:7012149",
        "tgn:7007828",
        "tgn:7029392"
    ],
    "tgn:id":2321990,
    "tgn:name":"Fall Brook",
    "tgn:placetype":[
        "aat:300008699"
    ]
},
  "bbox": [],
  "geometry": {"coordinates":[-73.0833,43.35],"type":"Point"}
}