{
  "id": 7416000,
  "type": "Feature",
  "properties": {
    "tgn:hierarchy":[
        "tgn:7416000",
        "tgn:1000001",
        "tgn:7005591",
        "tgn:7005560",
        "tgn:7029392"
    ],
    "tgn:id":7416000,
    "tgn:name:es":"San Antonio Huitepec",
    "tgn:placetype":[
        "aat:300008347"
    ]
},
  "bbox": [],
  "geometry": {"coordinates":[-97.153056,16.941389],"type":"Point"}
}