<<<<<<< HEAD
{
  "id": 2402652,
  "type": "Feature",
  "properties": {
    "tgn:hierarchy":[
        "tgn:2402652",
        "tgn:1000001",
        "tgn:7012149",
        "tgn:1002439",
        "tgn:7007252",
        "tgn:7029392"
    ],
    "tgn:id":2402652,
    "tgn:name":"Hot Lick Creek",
    "tgn:placetype":[
        "aat:300008706"
    ]
},
  "bbox": [],
  "geometry": {"coordinates":[-86.1,39.9667],"type":"Point"}
}
=======
{"geometry":{"type":"Point","coordinates":[-86.100000,39.966700]},"type":"Feature","properties":{"hierarchy":["tgn:2402652","tgn:1000001","tgn:7012149","tgn:1002439","tgn:7007252","tgn:7029392"],"placetype":["aat:300008706"],"id":2402652,"name:xx":"Hot Lick Creek"}}
>>>>>>> 03f74aca74312dbeaf24d7e61306dd6a786dc3d0
