{
  "id": 2741338,
  "type": "Feature",
  "properties": {
    "tgn:hierarchy":[
        "tgn:2741338",
        "tgn:1000001",
        "tgn:2001415",
        "tgn:7012149",
        "tgn:7007526",
        "tgn:7029392"
    ],
    "tgn:id":2741338,
    "tgn:name":"Upper Wood Spring",
    "tgn:placetype":[
        "aat:300008697"
    ]
},
  "bbox": [],
  "geometry": {"coordinates":[-116.7667,40.0333],"type":"Point"}
}