{
  "id": 7382180,
  "type": "Feature",
  "properties": {
    "tgn:hierarchy":[
        "tgn:7382180",
        "tgn:1000001",
        "tgn:7005597",
        "tgn:7005560",
        "tgn:7029392"
    ],
    "tgn:id":7382180,
    "tgn:name":"Monterito",
    "tgn:placetype":[
        "aat:300008347"
    ]
},
  "bbox": [],
  "geometry": {"coordinates":[-99.466667,26.783333],"type":"Point"}
}