<<<<<<< HEAD
{
  "id": 2409242,
  "type": "Feature",
  "properties": {
    "tgn:hierarchy":[
        "tgn:2409242",
        "tgn:1000001",
        "tgn:7006451",
        "tgn:2000093",
        "tgn:7012149",
        "tgn:7029392"
    ],
    "tgn:id":2409242,
    "tgn:name":"Icehouse Canyon",
    "tgn:placetype":[
        "aat:300008761"
    ]
},
  "bbox": [],
  "geometry": {"coordinates":[-110.8333,33.2833],"type":"Point"}
}
=======
{"geometry":{"type":"Point","coordinates":[-110.833300,33.283300]},"type":"Feature","properties":{"hierarchy":["tgn:2409242","tgn:1000001","tgn:7006451","tgn:2000093","tgn:7012149","tgn:7029392"],"placetype":["aat:300008761"],"id":2409242,"name:xx":"Icehouse Canyon"}}
>>>>>>> 03f74aca74312dbeaf24d7e61306dd6a786dc3d0
