{
  "id": 7468043,
  "type": "Feature",
  "properties": {
    "tgn:hierarchy":[
        "tgn:7468043",
        "tgn:1000004",
        "tgn:7001013",
        "tgn:1000141",
        "tgn:7029392"
    ],
    "tgn:id":7468043,
    "tgn:name":"Bianzhou Li",
    "tgn:placetype":[
        "aat:300387173"
    ]
},
  "bbox": [],
  "geometry": {"coordinates":[121.311925,25.024152],"type":"Point"}
}