{
  "id": 2303249,
  "type": "Feature",
  "properties": {
    "tgn:hierarchy":[
        "tgn:2303249",
        "tgn:1000001",
        "tgn:7012149",
        "tgn:1002990",
        "tgn:7007708",
        "tgn:7029392"
    ],
    "tgn:id":2303249,
    "tgn:name":"Eagle Butte",
    "tgn:placetype":[
        "aat:300008798"
    ]
},
  "bbox": [],
  "geometry": {"coordinates":[-121.2333,44.8333],"type":"Point"}
}