{
  "id": 2509444,
  "type": "Feature",
  "properties": {
    "tgn:hierarchy":[
        "tgn:2509444",
        "tgn:1000001",
        "tgn:7012149",
        "tgn:2000806",
        "tgn:7007255",
        "tgn:7029392"
    ],
    "tgn:id":2509444,
    "tgn:name":"Middle Fork Stinking Creek",
    "tgn:placetype":[
        "aat:300008706"
    ]
},
  "bbox": [],
  "geometry": {"coordinates":[-83.6833,36.9333],"type":"Point"}
}