{
  "id": 2644138,
  "type": "Feature",
  "properties": {
    "tgn:hierarchy":[
        "tgn:2644138",
        "tgn:1000001",
        "tgn:7012149",
        "tgn:7007157",
        "tgn:1002828",
        "tgn:7029392"
    ],
    "tgn:id":2644138,
    "tgn:name":"Santa Rosa Mine",
    "tgn:placetype":[
        "aat:300000390"
    ]
},
  "bbox": [],
  "geometry": {"coordinates":[-117.3333,33.7833],"type":"Point"}
}