{
  "id": 1057715,
  "type": "Feature",
  "properties": {
    "tgn:hierarchy":[
        "tgn:1057715",
        "tgn:1000004",
        "tgn:7018212",
        "tgn:7002435",
        "tgn:7029392"
    ],
    "tgn:id":1057715,
    "tgn:name":"Novomelnikoye",
    "tgn:placetype":[
        "aat:300008347"
    ]
},
  "bbox": [],
  "geometry": {"coordinates":[45.15,43.9333],"type":"Point"}
}