{
  "id": 7455480,
  "type": "Feature",
  "properties": {
    "tgn:hierarchy":[
        "tgn:7455480",
        "tgn:7002448",
        "tgn:7008699",
        "tgn:1000003",
        "tgn:7008591",
        "tgn:7029392"
    ],
    "tgn:id":7455480,
    "tgn:name:en":"Culmore",
    "tgn:placetype":[
        "aat:300008347"
    ]
},
  "bbox": [],
  "geometry": {"coordinates":[-7.266667,55.05],"type":"Point"}
}