{
  "id": 7439423,
  "type": "Feature",
  "properties": {
    "tgn:hierarchy":[
        "tgn:7439423",
        "tgn:7005578",
        "tgn:1000001",
        "tgn:7005560",
        "tgn:7029392"
    ],
    "tgn:id":7439423,
    "tgn:name":"San Rafael",
    "tgn:placetype":[
        "aat:300008347"
    ]
},
  "bbox": [],
  "geometry": {"coordinates":[-90.75,18.266667],"type":"Point"}
}