<<<<<<< HEAD
{
  "id": 7489706,
  "type": "Feature",
  "properties": {
    "tgn:hierarchy":[
        "tgn:7489706",
        "tgn:1000004",
        "tgn:7467799",
        "tgn:1000141",
        "tgn:7029392"
    ],
    "tgn:id":7489706,
    "tgn:name":"Guoyewei",
    "tgn:placetype":[
        "aat:300008347"
    ]
},
  "bbox": [],
  "geometry": {"coordinates":[120.45,24.083333],"type":"Point"}
}
=======
{"geometry":{"type":"Point","coordinates":[120.450000,24.083333]},"type":"Feature","properties":{"hierarchy":["tgn:7489706","tgn:1000004","tgn:7467799","tgn:1000141","tgn:7029392"],"placetype":["aat:300008347"],"id":7489706,"name:xx":"Guoyewei"}}
>>>>>>> 03f74aca74312dbeaf24d7e61306dd6a786dc3d0
