{
  "id": 7248554,
  "type": "Feature",
  "properties": {
    "tgn:hierarchy":[
        "tgn:7248554",
        "tgn:7007877",
        "tgn:1000003",
        "tgn:1000063",
        "tgn:4012014",
        "tgn:7029392"
    ],
    "tgn:id":7248554,
    "tgn:name":"Biesme l'Eau, Ruisseau",
    "tgn:placetype":[
        "aat:300008699"
    ]
},
  "bbox": [],
  "geometry": {"coordinates":[4.266667,50.333333],"type":"Point"}
}