{
  "id": 7578113,
  "type": "Feature",
  "properties": {
    "tgn:hierarchy":[
        "tgn:7578113",
        "tgn:7001819",
        "tgn:1000004",
        "tgn:7000198",
        "tgn:7029392"
    ],
    "tgn:id":7578113,
    "tgn:name:en":"Tse La",
    "tgn:placetype":[
        "aat:300259572"
    ]
},
  "bbox": [],
  "geometry": {"coordinates":[92.366667,27.633333],"type":"Point"}
}