{
  "id": 2550435,
  "type": "Feature",
  "properties": {
    "tgn:hierarchy":[
        "tgn:2550435",
        "tgn:1000001",
        "tgn:1002738",
        "tgn:7012149",
        "tgn:7007565",
        "tgn:7029392"
    ],
    "tgn:id":2550435,
    "tgn:name":"Northwest Point Island",
    "tgn:placetype":[
        "aat:300008791"
    ]
},
  "bbox": [],
  "geometry": {"coordinates":[-74.0667,39.9833],"type":"Point"}
}