{
  "id": 1014653,
  "type": "Feature",
  "properties": {
    "tgn:hierarchy":[
        "tgn:1014653",
        "tgn:7005685",
        "tgn:1000001",
        "tgn:7013154",
        "tgn:7029392"
    ],
    "tgn:id":1014653,
    "tgn:name":"Cataraqui",
    "tgn:placetype":[
        "aat:300008347"
    ]
},
  "bbox": [],
  "geometry": {"coordinates":[-76.5333,44.2667],"type":"Point"}
}