{
  "id": 2666090,
  "type": "Feature",
  "properties": {
    "tgn:hierarchy":[
        "tgn:2666090",
        "tgn:7006450",
        "tgn:1000001",
        "tgn:2124012",
        "tgn:7012149",
        "tgn:7029392"
    ],
    "tgn:id":2666090,
    "tgn:name":"Sitkinak Lagoon",
    "tgn:placetype":[
        "aat:300132316"
    ]
},
  "bbox": [],
  "geometry": {"coordinates":[-154.05,56.55],"type":"Point"}
}