{
  "id": 1014009,
  "type": "Feature",
  "properties": {
    "tgn:hierarchy":[
        "tgn:1014009",
        "tgn:7005685",
        "tgn:1000001",
        "tgn:7005734",
        "tgn:7029392"
    ],
    "tgn:id":1014009,
    "tgn:name":"Shoal Lake",
    "tgn:placetype":[
        "aat:300008347"
    ]
},
  "bbox": [],
  "geometry": {"coordinates":[-100.5833,50.4667],"type":"Point"}
}