{
  "id": 7273855,
  "type": "Feature",
  "properties": {
    "tgn:hierarchy":[
        "tgn:7273855",
        "tgn:7003614",
        "tgn:1000003",
        "tgn:7016845",
        "tgn:7029392"
    ],
    "tgn:id":7273855,
    "tgn:name:nl":"Wapsernoordenveld",
    "tgn:placetype":[
        "aat:300386887"
    ]
},
  "bbox": [],
  "geometry": {"coordinates":[6.266667,52.866667],"type":"Point"}
}