{
  "id": 2223696,
  "type": "Feature",
  "properties": {
    "tgn:hierarchy":[
        "tgn:2223696",
        "tgn:1000001",
        "tgn:7012149",
        "tgn:2001878",
        "tgn:7007825",
        "tgn:7029392"
    ],
    "tgn:id":2223696,
    "tgn:name":"Carter Hollow",
    "tgn:placetype":[
        "aat:300008761"
    ]
},
  "bbox": [],
  "geometry": {"coordinates":[-87.6667,36.35],"type":"Point"}
}