{
  "id": 7526253,
  "type": "Feature",
  "properties": {
    "tgn:hierarchy":[
        "tgn:7526253",
        "tgn:7001242",
        "tgn:7016833",
        "tgn:1001079",
        "tgn:7029392"
    ],
    "tgn:id":7526253,
    "tgn:name:en":"S\u012bd\u012b J\u0101bir",
    "tgn:placetype":[
        "aat:300000745"
    ]
},
  "bbox": [],
  "geometry": {"coordinates":[29.934167,31.221944],"type":"Point"}
}