{
  "id": 7562616,
  "type": "Feature",
  "properties": {
    "tgn:hierarchy":[
        "tgn:7562616",
        "tgn:1000004",
        "tgn:7000198",
        "tgn:7016722",
        "tgn:7029392"
    ],
    "tgn:id":7562616,
    "tgn:name:en":"Bamanpura",
    "tgn:placetype":[
        "aat:300008347"
    ]
},
  "bbox": [],
  "geometry": {"coordinates":[79.321294,27.850338],"type":"Point"}
}