{
  "id": 1124539,
  "type": "Feature",
  "properties": {
    "tgn:hierarchy":[
        "tgn:1124539",
        "tgn:7001242",
        "tgn:7030585",
        "tgn:1000198",
        "tgn:7029392"
    ],
    "tgn:id":1124539,
    "tgn:name":"Hamrivier",
    "tgn:placetype":[
        "aat:300008707"
    ]
},
  "bbox": [],
  "geometry": {"coordinates":[19.5667,-28.1833],"type":"Point"}
}