{
  "id": 2396879,
  "type": "Feature",
  "properties": {
    "tgn:hierarchy":[
        "tgn:2396879",
        "tgn:1000001",
        "tgn:7012149",
        "tgn:1002550",
        "tgn:7007157",
        "tgn:7029392"
    ],
    "tgn:id":2396879,
    "tgn:name":"Homeland Canal",
    "tgn:placetype":[
        "aat:300006075"
    ]
},
  "bbox": [],
  "geometry": {"coordinates":[-119.6333,35.8833],"type":"Point"}
}