{
  "id": 2609956,
  "type": "Feature",
  "properties": {
    "tgn:hierarchy":[
        "tgn:2609956",
        "tgn:1000001",
        "tgn:7012149",
        "tgn:2001710",
        "tgn:7007708",
        "tgn:7029392"
    ],
    "tgn:id":2609956,
    "tgn:name":"Recession Lakes",
    "tgn:placetype":[
        "aat:300008680"
    ]
},
  "bbox": [],
  "geometry": {"coordinates":[-121.6833,45.3833],"type":"Point"}
}