<<<<<<< HEAD
{
  "id": 7176789,
  "type": "Feature",
  "properties": {
    "tgn:hierarchy":[
        "tgn:7176789",
        "tgn:7003669",
        "tgn:1000003",
        "tgn:7000084",
        "tgn:7029392"
    ],
    "tgn:id":7176789,
    "tgn:name":"Guthof",
    "tgn:placetype":[
        "aat:300000206"
    ]
},
  "bbox": [],
  "geometry": {"coordinates":[12.516667,49.133333],"type":"Point"}
}
=======
{"geometry":{"type":"Point","coordinates":[12.516667,49.133333]},"type":"Feature","properties":{"hierarchy":["tgn:7176789","tgn:7003669","tgn:1000003","tgn:7000084","tgn:7029392"],"placetype":["aat:300000206"],"id":7176789,"name:xx":"Guthof"}}
>>>>>>> 03f74aca74312dbeaf24d7e61306dd6a786dc3d0
