{
  "id": 7284038,
  "type": "Feature",
  "properties": {
    "tgn:hierarchy":[
        "tgn:7284038",
        "tgn:7002464",
        "tgn:1000049",
        "tgn:1000002",
        "tgn:7029392"
    ],
    "tgn:id":7284038,
    "tgn:name":"Piojo, Punta",
    "tgn:placetype":[
        "aat:300386846"
    ]
},
  "bbox": [],
  "geometry": {"coordinates":[-70.183333,-19.683333],"type":"Point"}
}