{
  "id": 2347029,
  "type": "Feature",
  "properties": {
    "tgn:hierarchy":[
        "tgn:2347029",
        "tgn:1000001",
        "tgn:7012149",
        "tgn:2001492",
        "tgn:7007709",
        "tgn:7029392"
    ],
    "tgn:id":2347029,
    "tgn:name":"General Electric Lake Number Two",
    "tgn:placetype":[
        "aat:300006191"
    ]
},
  "bbox": [],
  "geometry": {"coordinates":[-78.8333,35.9167],"type":"Point"}
}