{
  "id": 2052765,
  "type": "Feature",
  "properties": {
    "tgn:hierarchy":[
        "tgn:2052765",
        "tgn:1000001",
        "tgn:7012149",
        "tgn:1002737",
        "tgn:7007520",
        "tgn:7029392"
    ],
    "tgn:id":2052765,
    "tgn:name":"Newark",
    "tgn:placetype":[
        "aat:300008347",
        "aat:300387210"
    ]
},
  "bbox": [],
  "geometry": {"coordinates":[-83.6167,42.85],"type":"Point"}
}