{
  "id": 1129683,
  "type": "Feature",
  "properties": {
    "tgn:hierarchy":[
        "tgn:1129683",
        "tgn:1000002",
        "tgn:7015386",
        "tgn:7029392"
    ],
    "tgn:id":1129683,
    "tgn:name":"Saramacca Rivier",
    "tgn:placetype":[
        "aat:300008707"
    ]
},
  "bbox": [],
  "geometry": {"coordinates":[-55.883,5.85],"type":"Point"}
}