<<<<<<< HEAD
{
  "id": 7372648,
  "type": "Feature",
  "properties": {
    "tgn:hierarchy":[
        "tgn:7372648",
        "tgn:1000001",
        "tgn:7005594",
        "tgn:7005560",
        "tgn:7029392"
    ],
    "tgn:id":7372648,
    "tgn:name":"La Ladrillera",
    "tgn:placetype":[
        "aat:300008347"
    ]
},
  "bbox": [],
  "geometry": {"coordinates":[-100.983333,22.133333],"type":"Point"}
}
=======
{"geometry":{"type":"Point","coordinates":[-100.983333,22.133333]},"type":"Feature","properties":{"hierarchy":["tgn:7372648","tgn:1000001","tgn:7005594","tgn:7005560","tgn:7029392"],"placetype":["aat:300008347"],"id":7372648,"name:xx":"La Ladrillera"}}
>>>>>>> 03f74aca74312dbeaf24d7e61306dd6a786dc3d0
