{
  "id": 7148179,
  "type": "Feature",
  "properties": {
    "tgn:hierarchy":[
        "tgn:7148179",
        "tgn:1000003",
        "tgn:7000094",
        "tgn:7000084",
        "tgn:7029392"
    ],
    "tgn:id":7148179,
    "tgn:name":"Krusenhagen",
    "tgn:placetype":[
        "aat:300008347"
    ]
},
  "bbox": [],
  "geometry": {"coordinates":[11.533333,53.95],"type":"Point"}
}