{
  "id": 7350457,
  "type": "Feature",
  "properties": {
    "tgn:hierarchy":[
        "tgn:7350457",
        "tgn:1001853",
        "tgn:1000001",
        "tgn:7005560",
        "tgn:7029392"
    ],
    "tgn:id":7350457,
    "tgn:name":"Apache, Puerto del",
    "tgn:placetype":[
        "aat:300259572"
    ]
},
  "bbox": [],
  "geometry": {"coordinates":[-101.766667,27.066667],"type":"Point"}
}