{
  "id": 1137306,
  "type": "Feature",
  "properties": {
    "tgn:hierarchy":[
        "tgn:1137306",
        "tgn:1000004",
        "tgn:1003379",
        "tgn:7018214",
        "tgn:7002435",
        "tgn:7029392"
    ],
    "tgn:id":1137306,
    "tgn:name":"Bogorodskoye",
    "tgn:placetype":[
        "aat:300008347"
    ]
},
  "bbox": [],
  "geometry": {"coordinates":[50.8333,57.8333],"type":"Point"}
}