{
  "id": 1015550,
  "type": "Feature",
  "properties": {
    "tgn:hierarchy":[
        "tgn:1015550",
        "tgn:7005685",
        "tgn:1000001",
        "tgn:7005804",
        "tgn:7029392"
    ],
    "tgn:id":1015550,
    "tgn:name":"Plessisville",
    "tgn:placetype":[
        "aat:300008347"
    ]
},
  "bbox": [],
  "geometry": {"coordinates":[-71.7667,46.2333],"type":"Point"}
}