{
  "id": 2045901,
  "type": "Feature",
  "properties": {
    "tgn:hierarchy":[
        "tgn:2045901",
        "tgn:1000001",
        "tgn:2000920",
        "tgn:7012149",
        "tgn:7007515",
        "tgn:7029392"
    ],
    "tgn:id":2045901,
    "tgn:name":"Windham Hill",
    "tgn:placetype":[
        "aat:300008347"
    ]
},
  "bbox": [],
  "geometry": {"coordinates":[-70.4167,43.7833],"type":"Point"}
}