{
  "id": 2145251,
  "type": "Feature",
  "properties": {
    "tgn:hierarchy":[
        "tgn:2145251",
        "tgn:2000919",
        "tgn:1000001",
        "tgn:7012149",
        "tgn:7007515",
        "tgn:7029392"
    ],
    "tgn:id":2145251,
    "tgn:name":"Bald Mountain Brook",
    "tgn:placetype":[
        "aat:300008699"
    ]
},
  "bbox": [],
  "geometry": {"coordinates":[-68.7167,46.7167],"type":"Point"}
}