{
  "id": 1011537,
  "type": "Feature",
  "properties": {
    "tgn:hierarchy":[
        "tgn:1011537",
        "tgn:7002443",
        "tgn:1000003",
        "tgn:7018973",
        "tgn:7008591",
        "tgn:7029392"
    ],
    "tgn:id":1011537,
    "tgn:name:en":"Worms Head",
    "tgn:placetype":[
        "aat:300008791",
        "aat:300387499"
    ]
},
  "bbox": [],
  "geometry": {"coordinates":[-4.325278,51.565],"type":"Point"}
}