{
  "id": 7428328,
  "type": "Feature",
  "properties": {
    "tgn:hierarchy":[
        "tgn:7428328",
        "tgn:1000001",
        "tgn:7005594",
        "tgn:7005560",
        "tgn:7029392"
    ],
    "tgn:id":7428328,
    "tgn:name":"Las Tablas",
    "tgn:placetype":[
        "aat:300008347"
    ]
},
  "bbox": [],
  "geometry": {"coordinates":[-99.866667,22.25],"type":"Point"}
}