{
  "id": 7230382,
  "type": "Feature",
  "properties": {
    "tgn:hierarchy":[
        "tgn:7230382",
        "tgn:7002725",
        "tgn:7002715",
        "tgn:1000003",
        "tgn:1000074",
        "tgn:7029392"
    ],
    "tgn:id":7230382,
    "tgn:name":"Kuch\u00fak Al\u00ed R\u00e9ma",
    "tgn:placetype":[
        "aat:300008699"
    ]
},
  "bbox": [],
  "geometry": {"coordinates":[23.516667,41.133333],"type":"Point"}
}