{
  "id": 7419226,
  "type": "Feature",
  "properties": {
    "tgn:hierarchy":[
        "tgn:7419226",
        "tgn:7005579",
        "tgn:1000001",
        "tgn:7005560",
        "tgn:7029392"
    ],
    "tgn:id":7419226,
    "tgn:name":"Los Pirules, Arroyo",
    "tgn:placetype":[
        "aat:300266554",
        "aat:300008699"
    ]
},
  "bbox": [],
  "geometry": {"coordinates":[-102.575,21.766667],"type":"Point"}
}