{
  "id": 2449807,
  "type": "Feature",
  "properties": {
    "tgn:hierarchy":[
        "tgn:2449807",
        "tgn:1000001",
        "tgn:7012149",
        "tgn:2000397",
        "tgn:7007248",
        "tgn:7029392"
    ],
    "tgn:id":2449807,
    "tgn:name":"Linden",
    "tgn:placetype":[
        "aat:300008347"
    ]
},
  "bbox": [],
  "geometry": {"coordinates":[-84.9167,32.45],"type":"Point"}
}