{
  "id": 1139021,
  "type": "Feature",
  "properties": {
    "tgn:hierarchy":[
        "tgn:1139021",
        "tgn:1000004",
        "tgn:7002085",
        "tgn:1000111",
        "tgn:7029392"
    ],
    "tgn:id":1139021,
    "tgn:name":"Guan Xian",
    "tgn:placetype":[
        "aat:300008347"
    ]
},
  "bbox": [],
  "geometry": {"coordinates":[115.35,36.4833],"type":"Point"}
}