{
  "id": 2001602,
  "type": "Feature",
  "properties": {
    "tgn:hierarchy":[
        "tgn:2001602",
        "tgn:1000001",
        "tgn:7012149",
        "tgn:7007705",
        "tgn:7029392"
    ],
    "tgn:id":2001602,
    "tgn:name":"Steele",
    "tgn:placetype":[
        "aat:300387145",
        "aat:300000771"
    ]
},
  "bbox": [],
  "geometry": {"coordinates":[-97.7167,47.4333],"type":"Point"}
}