{
  "id": 7491348,
  "type": "Feature",
  "properties": {
    "tgn:hierarchy":[
        "tgn:7491348",
        "tgn:1000004",
        "tgn:7489179",
        "tgn:1000141",
        "tgn:7029392"
    ],
    "tgn:id":7491348,
    "tgn:name":"Sanbaozhu",
    "tgn:placetype":[
        "aat:300008347"
    ]
},
  "bbox": [],
  "geometry": {"coordinates":[121.823333,24.833333],"type":"Point"}
}