{
  "id": 1096727,
  "type": "Feature",
  "properties": {
    "tgn:hierarchy":[
        "tgn:1096727",
        "tgn:7000490",
        "tgn:1000006",
        "tgn:7006238",
        "tgn:7029392"
    ],
    "tgn:id":1096727,
    "tgn:name":"Dartmoor",
    "tgn:placetype":[
        "aat:300008347"
    ]
},
  "bbox": [],
  "geometry": {"coordinates":[141.2833,-37.9333],"type":"Point"}
}