{
  "id": 2332956,
  "type": "Feature",
  "properties": {
    "tgn:hierarchy":[
        "tgn:2332956",
        "tgn:1000001",
        "tgn:7012149",
        "tgn:2000476",
        "tgn:7007250",
        "tgn:7029392"
    ],
    "tgn:id":2332956,
    "tgn:name":"Flume Gulch",
    "tgn:placetype":[
        "aat:300008761"
    ]
},
  "bbox": [],
  "geometry": {"coordinates":[-116.3333,45.4167],"type":"Point"}
}