<<<<<<< HEAD
{
  "id": 2332956,
  "type": "Feature",
  "properties": {
    "tgn:hierarchy":[
        "tgn:2332956",
        "tgn:1000001",
        "tgn:7012149",
        "tgn:2000476",
        "tgn:7007250",
        "tgn:7029392"
    ],
    "tgn:id":2332956,
    "tgn:name":"Flume Gulch",
    "tgn:placetype":[
        "aat:300008761"
    ]
},
  "bbox": [],
  "geometry": {"coordinates":[-116.3333,45.4167],"type":"Point"}
}
=======
{"geometry":{"type":"Point","coordinates":[-116.333300,45.416700]},"type":"Feature","properties":{"hierarchy":["tgn:2332956","tgn:1000001","tgn:7012149","tgn:2000476","tgn:7007250","tgn:7029392"],"placetype":["aat:300008761"],"id":2332956,"name:xx":"Flume Gulch"}}
>>>>>>> 03f74aca74312dbeaf24d7e61306dd6a786dc3d0
