{
  "id": 2307561,
  "type": "Feature",
  "properties": {
    "tgn:hierarchy":[
        "tgn:2307561",
        "tgn:1000001",
        "tgn:7012149",
        "tgn:7007158",
        "tgn:2000243",
        "tgn:7029392"
    ],
    "tgn:id":2307561,
    "tgn:name":"East Fork Spring",
    "tgn:placetype":[
        "aat:300008699"
    ]
},
  "bbox": [],
  "geometry": {"coordinates":[-108.5333,40.0333],"type":"Point"}
}