{
  "id": 2770756,
  "type": "Feature",
  "properties": {
    "tgn:hierarchy":[
        "tgn:2770756",
        "tgn:2000090",
        "tgn:1000001",
        "tgn:7006451",
        "tgn:7012149",
        "tgn:7029392"
    ],
    "tgn:id":2770756,
    "tgn:name":"Wildcat Creek",
    "tgn:placetype":[
        "aat:300008706"
    ]
},
  "bbox": [],
  "geometry": {"coordinates":[-109.4833,33.7833],"type":"Point"}
}