{
  "id": 2440668,
  "type": "Feature",
  "properties": {
    "tgn:hierarchy":[
        "tgn:2440668",
        "tgn:1000001",
        "tgn:7012149",
        "tgn:2002112",
        "tgn:7007827",
        "tgn:7029392"
    ],
    "tgn:id":2440668,
    "tgn:name":"Knight",
    "tgn:placetype":[
        "aat:300008347"
    ]
},
  "bbox": [],
  "geometry": {"coordinates":[-112.1833,39.9333],"type":"Point"}
}