{
  "id": 7152887,
  "type": "Feature",
  "properties": {
    "tgn:hierarchy":[
        "tgn:7152887",
        "tgn:1000003",
        "tgn:7594165",
        "tgn:7000084",
        "tgn:7029392"
    ],
    "tgn:id":7152887,
    "tgn:name":"NAME NOT KNOWN",
    "tgn:placetype":[
        "aat:300008795"
    ]
},
  "bbox": [],
  "geometry": {"coordinates":[13.116667,49.216667],"type":"Point"}
}