{
  "id": 7311500,
  "type": "Feature",
  "properties": {
    "tgn:hierarchy":[
        "tgn:7311500",
        "tgn:1001708",
        "tgn:1000049",
        "tgn:1000002",
        "tgn:7029392"
    ],
    "tgn:id":7311500,
    "tgn:name":"Lo Castillo",
    "tgn:placetype":[
        "aat:300000206"
    ]
},
  "bbox": [],
  "geometry": {"coordinates":[-70.683333,-33.25],"type":"Point"}
}