{
  "id": 2091149,
  "type": "Feature",
  "properties": {
    "tgn:hierarchy":[
        "tgn:2091149",
        "tgn:1000001",
        "tgn:7012149",
        "tgn:1003047",
        "tgn:7007710",
        "tgn:7029392"
    ],
    "tgn:id":2091149,
    "tgn:name":"Neiman",
    "tgn:placetype":[
        "aat:300008347"
    ]
},
  "bbox": [],
  "geometry": {"coordinates":[-76.7833,39.8167],"type":"Point"}
}