<<<<<<< HEAD
{
  "id": 7489872,
  "type": "Feature",
  "properties": {
    "tgn:hierarchy":[
        "tgn:7489872",
        "tgn:7488858",
        "tgn:1000004",
        "tgn:1000141",
        "tgn:7029392"
    ],
    "tgn:id":7489872,
    "tgn:name":"Dachelu",
    "tgn:placetype":[
        "aat:300008347"
    ]
},
  "bbox": [],
  "geometry": {"coordinates":[120.648,23.829795],"type":"Point"}
}
=======
{"geometry":{"type":"Point","coordinates":[120.648000,23.829795]},"type":"Feature","properties":{"hierarchy":["tgn:7489872","tgn:7488858","tgn:1000004","tgn:1000141","tgn:7029392"],"placetype":["aat:300008347"],"id":7489872,"name:xx":"Dachelu"}}
>>>>>>> 03f74aca74312dbeaf24d7e61306dd6a786dc3d0
