{
  "id": 7308858,
  "type": "Feature",
  "properties": {
    "tgn:hierarchy":[
        "tgn:7308858",
        "tgn:1001630",
        "tgn:1000049",
        "tgn:1000002",
        "tgn:7029392"
    ],
    "tgn:id":7308858,
    "tgn:name":"Los Toros, Caleta",
    "tgn:placetype":[
        "aat:300132317"
    ]
},
  "bbox": [],
  "geometry": {"coordinates":[-71.05,-27.733333],"type":"Point"}
}