{
  "id": 7482632,
  "type": "Feature",
  "properties": {
    "tgn:hierarchy":[
        "tgn:7482632",
        "tgn:7468018",
        "tgn:1000004",
        "tgn:1000141",
        "tgn:7029392"
    ],
    "tgn:id":7482632,
    "tgn:name":"Xindi Qiao",
    "tgn:placetype":[
        "aat:300007836"
    ]
},
  "bbox": [],
  "geometry": {"coordinates":[120.564722,23.5875],"type":"Point"}
}