<<<<<<< HEAD
{
  "id": 7482632,
  "type": "Feature",
  "properties": {
    "tgn:hierarchy":[
        "tgn:7482632",
        "tgn:7468018",
        "tgn:1000004",
        "tgn:1000141",
        "tgn:7029392"
    ],
    "tgn:id":7482632,
    "tgn:name":"Xindi Qiao",
    "tgn:placetype":[
        "aat:300007836"
    ]
},
  "bbox": [],
  "geometry": {"coordinates":[120.564722,23.5875],"type":"Point"}
}
=======
{"geometry":{"type":"Point","coordinates":[120.564722,23.587500]},"type":"Feature","properties":{"hierarchy":["tgn:7482632","tgn:7468018","tgn:1000004","tgn:1000141","tgn:7029392"],"placetype":["aat:300007836"],"id":7482632,"name:xx":"Xindi Qiao"}}
>>>>>>> 03f74aca74312dbeaf24d7e61306dd6a786dc3d0
