{
  "id": 2324473,
  "type": "Feature",
  "properties": {
    "tgn:hierarchy":[
        "tgn:2324473",
        "tgn:1000001",
        "tgn:2000776",
        "tgn:7012149",
        "tgn:7007255",
        "tgn:7029392"
    ],
    "tgn:id":2324473,
    "tgn:name":"Felker Hill",
    "tgn:placetype":[
        "aat:300008798"
    ]
},
  "bbox": [],
  "geometry": {"coordinates":[-87.9667,37.25],"type":"Point"}
}