{
  "id": 7499225,
  "type": "Feature",
  "properties": {
    "tgn:hierarchy":[
        "tgn:7499225",
        "tgn:1000004",
        "tgn:7491221",
        "tgn:1000141",
        "tgn:7029392"
    ],
    "tgn:id":7499225,
    "tgn:name":"Mukeng Xi",
    "tgn:placetype":[
        "aat:300008699"
    ]
},
  "bbox": [],
  "geometry": {"coordinates":[121.174795,22.96333],"type":"Point"}
}