{
  "id": 7469178,
  "type": "Feature",
  "properties": {
    "tgn:hierarchy":[
        "tgn:7469178",
        "tgn:1000004",
        "tgn:7491221",
        "tgn:1000141",
        "tgn:7029392"
    ],
    "tgn:id":7469178,
    "tgn:name":"Fuxing Shan",
    "tgn:placetype":[
        "aat:300008795"
    ]
},
  "bbox": [],
  "geometry": {"coordinates":[121.247778,23.071111],"type":"Point"}
}