{
  "id": 7565684,
  "type": "Feature",
  "properties": {
    "tgn:hierarchy":[
        "tgn:7565684",
        "tgn:1000004",
        "tgn:7000198",
        "tgn:7016722",
        "tgn:7029392"
    ],
    "tgn:id":7565684,
    "tgn:name:en":"Sikri R\u0101ja",
    "tgn:placetype":[
        "aat:300008347"
    ]
},
  "bbox": [],
  "geometry": {"coordinates":[79.25789,26.11315],"type":"Point"}
}