{
  "id": 2768109,
  "type": "Feature",
  "properties": {
    "tgn:hierarchy":[
        "tgn:2768109",
        "tgn:1000001",
        "tgn:2000782",
        "tgn:7012149",
        "tgn:7007255",
        "tgn:7029392"
    ],
    "tgn:id":2768109,
    "tgn:name":"Whites Branch",
    "tgn:placetype":[
        "aat:300008699"
    ]
},
  "bbox": [],
  "geometry": {"coordinates":[-83.85,37.05],"type":"Point"}
}