<<<<<<< HEAD
{
  "id": 2768109,
  "type": "Feature",
  "properties": {
    "tgn:hierarchy":[
        "tgn:2768109",
        "tgn:1000001",
        "tgn:2000782",
        "tgn:7012149",
        "tgn:7007255",
        "tgn:7029392"
    ],
    "tgn:id":2768109,
    "tgn:name":"Whites Branch",
    "tgn:placetype":[
        "aat:300008699"
    ]
},
  "bbox": [],
  "geometry": {"coordinates":[-83.85,37.05],"type":"Point"}
}
=======
{"geometry":{"type":"Point","coordinates":[-83.850000,37.050000]},"type":"Feature","properties":{"hierarchy":["tgn:2768109","tgn:1000001","tgn:2000782","tgn:7012149","tgn:7007255","tgn:7029392"],"placetype":["aat:300008699"],"id":2768109,"name:xx":"Whites Branch"}}
>>>>>>> 03f74aca74312dbeaf24d7e61306dd6a786dc3d0
