<<<<<<< HEAD
{
  "id": 7020965,
  "type": "Feature",
  "properties": {
    "tgn:hierarchy":[
        "tgn:7020965",
        "tgn:1000001",
        "tgn:7012149",
        "tgn:2000488",
        "tgn:7007250",
        "tgn:7029392"
    ],
    "tgn:id":7020965,
    "tgn:name":"Deep Creek",
    "tgn:placetype":[
        "aat:300008706"
    ]
},
  "bbox": [],
  "geometry": {"coordinates":[-116.6667,42.55],"type":"Point"}
}
=======
{"geometry":{"type":"Point","coordinates":[-116.666700,42.550000]},"type":"Feature","properties":{"hierarchy":["tgn:7020965","tgn:1000001","tgn:7012149","tgn:2000488","tgn:7007250","tgn:7029392"],"placetype":["aat:300008706"],"id":7020965,"name:xx":"Deep Creek"}}
>>>>>>> 03f74aca74312dbeaf24d7e61306dd6a786dc3d0
