{
  "id": 2703794,
  "type": "Feature",
  "properties": {
    "tgn:hierarchy":[
        "tgn:2703794",
        "tgn:1000001",
        "tgn:1002934",
        "tgn:7012149",
        "tgn:7007565",
        "tgn:7029392"
    ],
    "tgn:id":2703794,
    "tgn:name":"Sun Rise Point",
    "tgn:placetype":[
        "aat:300008850"
    ]
},
  "bbox": [],
  "geometry": {"coordinates":[-74.65,40.95],"type":"Point"}
}