{
  "id": 7102652,
  "type": "Feature",
  "properties": {
    "tgn:hierarchy":[
        "tgn:7102652",
        "tgn:1000003",
        "tgn:7003676",
        "tgn:7000084",
        "tgn:7029392"
    ],
    "tgn:id":7102652,
    "tgn:name":"Rothehof",
    "tgn:placetype":[
        "aat:300000206"
    ]
},
  "bbox": [],
  "geometry": {"coordinates":[9.033333,52.35],"type":"Point"}
}