{
  "id": 2205279,
  "type": "Feature",
  "properties": {
    "tgn:hierarchy":[
        "tgn:2205279",
        "tgn:1000001",
        "tgn:7012149",
        "tgn:7014589",
        "tgn:7007515",
        "tgn:7029392"
    ],
    "tgn:id":2205279,
    "tgn:name":"Bull Brook",
    "tgn:placetype":[
        "aat:300008699"
    ]
},
  "bbox": [],
  "geometry": {"coordinates":[-67.5667,45.4667],"type":"Point"}
}