{
  "id": 1045952,
  "type": "Feature",
  "properties": {
    "tgn:hierarchy":[
        "tgn:1045952",
        "tgn:1000003",
        "tgn:7003122",
        "tgn:7003157",
        "tgn:1000080",
        "tgn:7029392"
    ],
    "tgn:id":1045952,
    "tgn:name":"Pettineo",
    "tgn:placetype":[
        "aat:300008347"
    ]
},
  "bbox": [],
  "geometry": {"coordinates":[14.283333,37.966667],"type":"Point"}
}