{
  "id": 2324378,
  "type": "Feature",
  "properties": {
    "tgn:hierarchy":[
        "tgn:2324378",
        "tgn:1000001",
        "tgn:2000507",
        "tgn:7012149",
        "tgn:7007251",
        "tgn:7029392"
    ],
    "tgn:id":2324378,
    "tgn:name":"Fehrer Lake",
    "tgn:placetype":[
        "aat:300008680"
    ]
},
  "bbox": [],
  "geometry": {"coordinates":[-88.0667,37.75],"type":"Point"}
}