{
  "id": 7406072,
  "type": "Feature",
  "properties": {
    "tgn:hierarchy":[
        "tgn:7406072",
        "tgn:1000001",
        "tgn:1001906",
        "tgn:7005560",
        "tgn:7029392"
    ],
    "tgn:id":7406072,
    "tgn:name":"La Silare\u00f1a",
    "tgn:placetype":[
        "aat:300008347"
    ]
},
  "bbox": [],
  "geometry": {"coordinates":[-105.108333,22.029167],"type":"Point"}
}