{
  "id": 2774633,
  "type": "Feature",
  "properties": {
    "tgn:hierarchy":[
        "tgn:2774633",
        "tgn:1000001",
        "tgn:7006451",
        "tgn:2000095",
        "tgn:7012149",
        "tgn:7029392"
    ],
    "tgn:id":2774633,
    "tgn:name":"Willow Spring",
    "tgn:placetype":[
        "aat:300008697"
    ]
},
  "bbox": [],
  "geometry": {"coordinates":[-109.3167,33.6167],"type":"Point"}
}