{
  "id": 7052290,
  "type": "Feature",
  "properties": {
    "tgn:hierarchy":[
        "tgn:7052290",
        "tgn:7003164",
        "tgn:1000003",
        "tgn:7009760",
        "tgn:1000080",
        "tgn:7029392"
    ],
    "tgn:id":7052290,
    "tgn:name":"Penisola, Punta",
    "tgn:placetype":[
        "aat:300386846"
    ]
},
  "bbox": [],
  "geometry": {"coordinates":[10.25,42.816667],"type":"Point"}
}