{
  "id": 2098537,
  "type": "Feature",
  "properties": {
    "tgn:hierarchy":[
        "tgn:2098537",
        "tgn:1000001",
        "tgn:7012149",
        "tgn:2001930",
        "tgn:7007825",
        "tgn:7029392"
    ],
    "tgn:id":2098537,
    "tgn:name":"Clovercroft",
    "tgn:placetype":[
        "aat:300008347"
    ]
},
  "bbox": [],
  "geometry": {"coordinates":[-86.7667,35.9167],"type":"Point"}
}