{
  "id": 1046755,
  "type": "Feature",
  "properties": {
    "tgn:hierarchy":[
        "tgn:1046755",
        "tgn:7002991",
        "tgn:1000003",
        "tgn:7002997",
        "tgn:1000080",
        "tgn:7029392"
    ],
    "tgn:id":1046755,
    "tgn:name":"Sappada",
    "tgn:placetype":[
        "aat:300008347"
    ]
},
  "bbox": [],
  "geometry": {"coordinates":[12.725,46.571944],"type":"Point"}
}