{
  "id": 7503132,
  "type": "Feature",
  "properties": {
    "tgn:hierarchy":[
        "tgn:7503132",
        "tgn:1000004",
        "tgn:7004300",
        "tgn:1000141",
        "tgn:7029392"
    ],
    "tgn:id":7503132,
    "tgn:name":"Biqi Gang",
    "tgn:placetype":[
        "aat:300008678"
    ]
},
  "bbox": [],
  "geometry": {"coordinates":[119.509722,23.376944],"type":"Point"}
}