{
  "id": 2118756,
  "type": "Feature",
  "properties": {
    "tgn:hierarchy":[
        "tgn:2118756",
        "tgn:1000001",
        "tgn:2002254",
        "tgn:7012149",
        "tgn:7013961",
        "tgn:7029392"
    ],
    "tgn:id":2118756,
    "tgn:name":"Johnsontown",
    "tgn:placetype":[
        "aat:300008347",
        "aat:300387210"
    ]
},
  "bbox": [],
  "geometry": {"coordinates":[-78.0333,39.5667],"type":"Point"}
}