{
  "id": 7224514,
  "type": "Feature",
  "properties": {
    "tgn:hierarchy":[
        "tgn:7224514",
        "tgn:7002709",
        "tgn:7002705",
        "tgn:1000003",
        "tgn:1000074",
        "tgn:7029392"
    ],
    "tgn:id":7224514,
    "tgn:name":"Nikol\u00edtsion",
    "tgn:placetype":[
        "aat:300008347"
    ]
},
  "bbox": [],
  "geometry": {"coordinates":[20.410556,39.456389],"type":"Point"}
}