{
  "id": 7378011,
  "type": "Feature",
  "properties": {
    "tgn:hierarchy":[
        "tgn:7378011",
        "tgn:1000001",
        "tgn:7005594",
        "tgn:7005560",
        "tgn:7029392"
    ],
    "tgn:id":7378011,
    "tgn:name":"La P\u00f3lvora",
    "tgn:placetype":[
        "aat:300008347"
    ]
},
  "bbox": [],
  "geometry": {"coordinates":[-100.35,22.933333],"type":"Point"}
}