{
  "id": 7033638,
  "type": "Feature",
  "properties": {
    "tgn:hierarchy":[
        "tgn:7033638",
        "tgn:7003129",
        "tgn:1000003",
        "tgn:7008516",
        "tgn:1000080",
        "tgn:7029392"
    ],
    "tgn:id":7033638,
    "tgn:name":"Valle",
    "tgn:placetype":[
        "aat:300008699"
    ]
},
  "bbox": [],
  "geometry": {"coordinates":[12.266389,44.265556],"type":"Point"}
}