{
  "id": 7283396,
  "type": "Feature",
  "properties": {
    "tgn:hierarchy":[
        "tgn:7283396",
        "tgn:1001623",
        "tgn:1000049",
        "tgn:1000002",
        "tgn:7029392"
    ],
    "tgn:id":7283396,
    "tgn:name":"Punta Palena",
    "tgn:placetype":[
        "aat:300386846"
    ]
},
  "bbox": [],
  "geometry": {"coordinates":[-72.978889,-43.761111],"type":"Point"}
}