{
  "id": 2251123,
  "type": "Feature",
  "properties": {
    "tgn:hierarchy":[
        "tgn:2251123",
        "tgn:1002541",
        "tgn:1000001",
        "tgn:7012149",
        "tgn:7007711",
        "tgn:7029392"
    ],
    "tgn:id":2251123,
    "tgn:name":"Colvintown",
    "tgn:placetype":[
        "aat:300008347"
    ]
},
  "bbox": [],
  "geometry": {"coordinates":[-71.5667,41.7167],"type":"Point"}
}