{
  "id": 2681501,
  "type": "Feature",
  "properties": {
    "tgn:hierarchy":[
        "tgn:2681501",
        "tgn:1000001",
        "tgn:7012149",
        "tgn:2001502",
        "tgn:7007709",
        "tgn:7029392"
    ],
    "tgn:id":2681501,
    "tgn:name":"South Prong Anderson Creek",
    "tgn:placetype":[
        "aat:300008706"
    ]
},
  "bbox": [],
  "geometry": {"coordinates":[-78.9667,35.2833],"type":"Point"}
}