{
  "id": 7381123,
  "type": "Feature",
  "properties": {
    "tgn:hierarchy":[
        "tgn:7381123",
        "tgn:1001853",
        "tgn:1000001",
        "tgn:7005560",
        "tgn:7029392"
    ],
    "tgn:id":7381123,
    "tgn:name":"Medio, Cerro del",
    "tgn:placetype":[
        "aat:300008795"
    ]
},
  "bbox": [],
  "geometry": {"coordinates":[-100.75,25.283333],"type":"Point"}
}