{
  "id": 2785285,
  "type": "Feature",
  "properties": {
    "tgn:hierarchy":[
        "tgn:2785285",
        "tgn:1000001",
        "tgn:1002193",
        "tgn:7012149",
        "tgn:7007255",
        "tgn:7029392"
    ],
    "tgn:id":2785285,
    "tgn:name":"Yellow Willow Creek",
    "tgn:placetype":[
        "aat:300008706"
    ]
},
  "bbox": [],
  "geometry": {"coordinates":[-84.1833,38.6167],"type":"Point"}
}