{
  "id": 2686739,
  "type": "Feature",
  "properties": {
    "tgn:hierarchy":[
        "tgn:2686739",
        "tgn:1000001",
        "tgn:7012149",
        "tgn:2002328",
        "tgn:7007922",
        "tgn:7029392"
    ],
    "tgn:id":2686739,
    "tgn:name":"Spring Creek",
    "tgn:placetype":[
        "aat:300008706"
    ]
},
  "bbox": [],
  "geometry": {"coordinates":[-90.9167,44.25],"type":"Point"}
}