{
  "id": 7291747,
  "type": "Feature",
  "properties": {
    "tgn:hierarchy":[
        "tgn:7291747",
        "tgn:1001768",
        "tgn:1000049",
        "tgn:1000002",
        "tgn:7029392"
    ],
    "tgn:id":7291747,
    "tgn:name":"El Infiernillo",
    "tgn:placetype":[
        "aat:300387200"
    ]
},
  "bbox": [],
  "geometry": {"coordinates":[-71.283333,-32.616667],"type":"Point"}
}