<<<<<<< HEAD
{
  "id": 7053906,
  "type": "Feature",
  "properties": {
    "tgn:hierarchy":[
        "tgn:7053906",
        "tgn:1000003",
        "tgn:7003236",
        "tgn:7003144",
        "tgn:1000080",
        "tgn:7029392"
    ],
    "tgn:id":7053906,
    "tgn:name":"Palo",
    "tgn:placetype":[
        "aat:300008347"
    ]
},
  "bbox": [],
  "geometry": {"coordinates":[8.533333,44.483333],"type":"Point"}
}
=======
{"geometry":{"type":"Point","coordinates":[8.533333,44.483333]},"type":"Feature","properties":{"hierarchy":["tgn:7053906","tgn:1000003","tgn:7003236","tgn:7003144","tgn:1000080","tgn:7029392"],"placetype":["aat:300008347"],"id":7053906,"name:xx":"Palo"}}
>>>>>>> 03f74aca74312dbeaf24d7e61306dd6a786dc3d0
