{
  "id": 2777293,
  "type": "Feature",
  "properties": {
    "tgn:hierarchy":[
        "tgn:2777293",
        "tgn:1000001",
        "tgn:7013686",
        "tgn:7012149",
        "tgn:7007517",
        "tgn:7029392"
    ],
    "tgn:id":2777293,
    "tgn:name":"Wing Hill",
    "tgn:placetype":[
        "aat:300008798"
    ]
},
  "bbox": [],
  "geometry": {"coordinates":[-72.7667,42.45],"type":"Point"}
}