{
  "id": 2593427,
  "type": "Feature",
  "properties": {
    "tgn:hierarchy":[
        "tgn:2593427",
        "tgn:1000001",
        "tgn:7012149",
        "tgn:1003017",
        "tgn:7007710",
        "tgn:7029392"
    ],
    "tgn:id":2593427,
    "tgn:name":"Porch Mine",
    "tgn:placetype":[
        "aat:300000390"
    ]
},
  "bbox": [],
  "geometry": {"coordinates":[-79.4167,40.1833],"type":"Point"}
}