<<<<<<< HEAD
{
  "id": 2156627,
  "type": "Feature",
  "properties": {
    "tgn:hierarchy":[
        "tgn:2156627",
        "tgn:1000001",
        "tgn:7012149",
        "tgn:2001556",
        "tgn:7007709",
        "tgn:7029392"
    ],
    "tgn:id":2156627,
    "tgn:name":"Bearwallow Stand Ridge",
    "tgn:placetype":[
        "aat:300266640"
    ]
},
  "bbox": [],
  "geometry": {"coordinates":[-82.3167,35.75],"type":"Point"}
}
=======
{"geometry":{"type":"Point","coordinates":[-82.316700,35.750000]},"type":"Feature","properties":{"hierarchy":["tgn:2156627","tgn:1000001","tgn:7012149","tgn:2001556","tgn:7007709","tgn:7029392"],"placetype":["aat:300266640"],"id":2156627,"name:xx":"Bearwallow Stand Ridge"}}
>>>>>>> 03f74aca74312dbeaf24d7e61306dd6a786dc3d0
