<<<<<<< HEAD
{
  "id": 7366204,
  "type": "Feature",
  "properties": {
    "tgn:hierarchy":[
        "tgn:7366204",
        "tgn:7005581",
        "tgn:1000001",
        "tgn:7005560",
        "tgn:7029392"
    ],
    "tgn:id":7366204,
    "tgn:name":"El Terreno",
    "tgn:placetype":[
        "aat:300008347"
    ]
},
  "bbox": [],
  "geometry": {"coordinates":[-107.383333,29.166667],"type":"Point"}
}
=======
{"geometry":{"type":"Point","coordinates":[-107.383333,29.166667]},"type":"Feature","properties":{"hierarchy":["tgn:7366204","tgn:7005581","tgn:1000001","tgn:7005560","tgn:7029392"],"placetype":["aat:300008347"],"id":7366204,"name:xx":"El Terreno"}}
>>>>>>> 03f74aca74312dbeaf24d7e61306dd6a786dc3d0
