{
  "id": 2685886,
  "type": "Feature",
  "properties": {
    "tgn:hierarchy":[
        "tgn:2685886",
        "tgn:1000001",
        "tgn:7012149",
        "tgn:2001959",
        "tgn:7007826",
        "tgn:7029392"
    ],
    "tgn:id":2685886,
    "tgn:name":"Spring Branch",
    "tgn:placetype":[
        "aat:300008699"
    ]
},
  "bbox": [],
  "geometry": {"coordinates":[-99.3333,31.9833],"type":"Point"}
}