{
  "id": 2034946,
  "type": "Feature",
  "properties": {
    "tgn:hierarchy":[
        "tgn:2034946",
        "tgn:1000001",
        "tgn:7012149",
        "tgn:2000628",
        "tgn:7007253",
        "tgn:7029392"
    ],
    "tgn:id":2034946,
    "tgn:name":"Hiteman",
    "tgn:placetype":[
        "aat:300008347"
    ]
},
  "bbox": [],
  "geometry": {"coordinates":[-92.8833,41.05],"type":"Point"}
}