{
  "id": 7591587,
  "type": "Feature",
  "properties": {
    "tgn:hierarchy":[
        "tgn:7591587",
        "tgn:1000004",
        "tgn:7000198",
        "tgn:7031786",
        "tgn:7029392"
    ],
    "tgn:id":7591587,
    "tgn:name:en":"\u0100mw\u0101la Tarla",
    "tgn:placetype":[
        "aat:300008347"
    ]
},
  "bbox": [],
  "geometry": {"coordinates":[77.996824,30.373829],"type":"Point"}
}