{
  "id": 2281320,
  "type": "Feature",
  "properties": {
    "tgn:hierarchy":[
        "tgn:2281320",
        "tgn:1000001",
        "tgn:7012149",
        "tgn:1002742",
        "tgn:7007920",
        "tgn:7029392"
    ],
    "tgn:id":2281320,
    "tgn:name":"Deep Spring",
    "tgn:placetype":[
        "aat:300008697"
    ]
},
  "bbox": [],
  "geometry": {"coordinates":[-119.3333,48.3167],"type":"Point"}
}