{
  "id": 2494819,
  "type": "Feature",
  "properties": {
    "tgn:hierarchy":[
        "tgn:2494819",
        "tgn:7006450",
        "tgn:1000001",
        "tgn:2124012",
        "tgn:7012149",
        "tgn:7029392"
    ],
    "tgn:id":2494819,
    "tgn:name":"Martin, Mount",
    "tgn:placetype":[
        "aat:300008798"
    ]
},
  "bbox": [],
  "geometry": {"coordinates":[-155.35,58.1667],"type":"Point"}
}