{
  "id": 2522498,
  "type": "Feature",
  "properties": {
    "tgn:hierarchy":[
        "tgn:2522498",
        "tgn:1000001",
        "tgn:7012149",
        "tgn:7007526",
        "tgn:7029392"
    ],
    "tgn:id":2522498,
    "tgn:name":"Moonshine Canyon",
    "tgn:placetype":[
        "aat:300008761"
    ]
},
  "bbox": [],
  "geometry": {"coordinates":[-115.8667,37.95],"type":"Point"}
}