{
  "id": 2340048,
  "type": "Feature",
  "properties": {
    "tgn:hierarchy":[
        "tgn:2340048",
        "tgn:1000001",
        "tgn:7012149",
        "tgn:2000491",
        "tgn:7007250",
        "tgn:7029392"
    ],
    "tgn:id":2340048,
    "tgn:name":"Freezeout Creek",
    "tgn:placetype":[
        "aat:300008706"
    ]
},
  "bbox": [],
  "geometry": {"coordinates":[-116.0333,47.0167],"type":"Point"}
}