{
  "id": 7410168,
  "type": "Feature",
  "properties": {
    "tgn:hierarchy":[
        "tgn:7410168",
        "tgn:1000001",
        "tgn:7005590",
        "tgn:7005560",
        "tgn:7029392"
    ],
    "tgn:id":7410168,
    "tgn:name":"El Ma\u00edz de Pl\u00e1tano",
    "tgn:placetype":[
        "aat:300008347"
    ]
},
  "bbox": [],
  "geometry": {"coordinates":[-102.323611,18.575],"type":"Point"}
}