{
  "id": 7279502,
  "type": "Feature",
  "properties": {
    "tgn:hierarchy":[
        "tgn:7279502",
        "tgn:1001623",
        "tgn:1000049",
        "tgn:1000002",
        "tgn:7029392"
    ],
    "tgn:id":7279502,
    "tgn:name":"Ratones, Grupo",
    "tgn:placetype":[
        "aat:300008791"
    ]
},
  "bbox": [],
  "geometry": {"coordinates":[-75.066667,-47.65],"type":"Point"}
}