{
  "id": 2574686,
  "type": "Feature",
  "properties": {
    "tgn:hierarchy":[
        "tgn:2574686",
        "tgn:1000001",
        "tgn:7012149",
        "tgn:2002016",
        "tgn:7007826",
        "tgn:7029392"
    ],
    "tgn:id":2574686,
    "tgn:name":"Penascal, Point",
    "tgn:placetype":[
        "aat:300008850"
    ]
},
  "bbox": [],
  "geometry": {"coordinates":[-97.4167,27.25],"type":"Point"}
}