{
  "id": 2607669,
  "type": "Feature",
  "properties": {
    "tgn:hierarchy":[
        "tgn:2607669",
        "tgn:1000001",
        "tgn:7012149",
        "tgn:7013941",
        "tgn:7007568",
        "tgn:7029392"
    ],
    "tgn:id":2607669,
    "tgn:name":"Raquette Pond",
    "tgn:placetype":[
        "aat:300006191"
    ]
},
  "bbox": [],
  "geometry": {"coordinates":[-74.5167,44.2333],"type":"Point"}
}