{
  "id": 7407575,
  "type": "Feature",
  "properties": {
    "tgn:hierarchy":[
        "tgn:7407575",
        "tgn:7005580",
        "tgn:1000001",
        "tgn:7005560",
        "tgn:7029392"
    ],
    "tgn:id":7407575,
    "tgn:name":"Sierra Alta, Cerro",
    "tgn:placetype":[
        "aat:300008795"
    ]
},
  "bbox": [],
  "geometry": {"coordinates":[-93.05,16.475],"type":"Point"}
}