{
  "id": 7289767,
  "type": "Feature",
  "properties": {
    "tgn:hierarchy":[
        "tgn:7289767",
        "tgn:1001695",
        "tgn:1000049",
        "tgn:1000002",
        "tgn:7029392"
    ],
    "tgn:id":7289767,
    "tgn:name":"El Carmen del Abra",
    "tgn:placetype":[
        "aat:300000206"
    ]
},
  "bbox": [],
  "geometry": {"coordinates":[-70.883333,-34.283333],"type":"Point"}
}