{
  "id": 2340543,
  "type": "Feature",
  "properties": {
    "tgn:hierarchy":[
        "tgn:2340543",
        "tgn:1000001",
        "tgn:2001413",
        "tgn:7012149",
        "tgn:7007526",
        "tgn:7029392"
    ],
    "tgn:id":2340543,
    "tgn:name":"Frenchie Creek",
    "tgn:placetype":[
        "aat:300008706"
    ]
},
  "bbox": [],
  "geometry": {"coordinates":[-116.2833,40.3333],"type":"Point"}
}