{
  "id": 7253132,
  "type": "Feature",
  "properties": {
    "tgn:hierarchy":[
        "tgn:7253132",
        "tgn:7003466",
        "tgn:1000003",
        "tgn:1000063",
        "tgn:4012014",
        "tgn:7029392"
    ],
    "tgn:id":7253132,
    "tgn:name":"Surice, Bois de",
    "tgn:placetype":[
        "aat:300008863"
    ]
},
  "bbox": [],
  "geometry": {"coordinates":[4.683333,50.15],"type":"Point"}
}