{
  "id": 7320418,
  "type": "Feature",
  "properties": {
    "tgn:hierarchy":[
        "tgn:7320418",
        "tgn:1001623",
        "tgn:1000049",
        "tgn:1000002",
        "tgn:7029392"
    ],
    "tgn:id":7320418,
    "tgn:name":"Bluff, Caleta",
    "tgn:placetype":[
        "aat:300132317"
    ]
},
  "bbox": [],
  "geometry": {"coordinates":[-72.883333,-45.466667],"type":"Point"}
}