{
  "id": 2177448,
  "type": "Feature",
  "properties": {
    "tgn:hierarchy":[
        "tgn:2177448",
        "tgn:1000001",
        "tgn:7006451",
        "tgn:7012149",
        "tgn:2000098",
        "tgn:7029392"
    ],
    "tgn:id":2177448,
    "tgn:name":"Black Rock Gulch",
    "tgn:placetype":[
        "aat:300008761"
    ]
},
  "bbox": [],
  "geometry": {"coordinates":[-113.65,36.8167],"type":"Point"}
}