<<<<<<< HEAD
{
  "id": 2155262,
  "type": "Feature",
  "properties": {
    "tgn:hierarchy":[
        "tgn:2155262",
        "tgn:1000001",
        "tgn:7012149",
        "tgn:2001295",
        "tgn:7007524",
        "tgn:7029392"
    ],
    "tgn:id":2155262,
    "tgn:name":"Bear Mountain",
    "tgn:placetype":[
        "aat:300008798"
    ]
},
  "bbox": [],
  "geometry": {"coordinates":[-108.4667,47.9333],"type":"Point"}
}
=======
{"geometry":{"type":"Point","coordinates":[-108.466700,47.933300]},"type":"Feature","properties":{"hierarchy":["tgn:2155262","tgn:1000001","tgn:7012149","tgn:2001295","tgn:7007524","tgn:7029392"],"placetype":["aat:300008798"],"id":2155262,"name:xx":"Bear Mountain"}}
>>>>>>> 03f74aca74312dbeaf24d7e61306dd6a786dc3d0
