<<<<<<< HEAD
{
  "id": 2336799,
  "type": "Feature",
  "properties": {
    "tgn:hierarchy":[
        "tgn:2336799",
        "tgn:1000001",
        "tgn:2001705",
        "tgn:7012149",
        "tgn:7007708",
        "tgn:7029392"
    ],
    "tgn:id":2336799,
    "tgn:name":"Fourmile Butte",
    "tgn:placetype":[
        "aat:300008798"
    ]
},
  "bbox": [],
  "geometry": {"coordinates":[-121.6667,44.3],"type":"Point"}
}
=======
{"geometry":{"type":"Point","coordinates":[-121.666700,44.300000]},"type":"Feature","properties":{"hierarchy":["tgn:2336799","tgn:1000001","tgn:2001705","tgn:7012149","tgn:7007708","tgn:7029392"],"placetype":["aat:300008798"],"id":2336799,"name:xx":"Fourmile Butte"}}
>>>>>>> 03f74aca74312dbeaf24d7e61306dd6a786dc3d0
