{
  "id": 7038789,
  "type": "Feature",
  "properties": {
    "tgn:hierarchy":[
        "tgn:7038789",
        "tgn:7003163",
        "tgn:1000003",
        "tgn:7009760",
        "tgn:1000080",
        "tgn:7029392"
    ],
    "tgn:id":7038789,
    "tgn:name":"Stefanieri, Poggio",
    "tgn:placetype":[
        "aat:300008795"
    ]
},
  "bbox": [],
  "geometry": {"coordinates":[11.566667,43.75],"type":"Point"}
}