{
  "id": 7357756,
  "type": "Feature",
  "properties": {
    "tgn:hierarchy":[
        "tgn:7357756",
        "tgn:1000001",
        "tgn:7005599",
        "tgn:7005560",
        "tgn:7029392"
    ],
    "tgn:id":7357756,
    "tgn:name":"Corral Nuevo",
    "tgn:placetype":[
        "aat:300008347"
    ]
},
  "bbox": [],
  "geometry": {"coordinates":[-95.15,18.133333],"type":"Point"}
}