{
  "id": 2455395,
  "type": "Feature",
  "properties": {
    "tgn:hierarchy":[
        "tgn:2455395",
        "tgn:1000001",
        "tgn:7012149",
        "tgn:7029392"
    ],
    "tgn:id":2455395,
    "tgn:name":"Little Four Mile Creek",
    "tgn:placetype":[
        "aat:300008706"
    ]
},
  "bbox": [],
  "geometry": {"coordinates":[-84.8167,39.75],"type":"Point"}
}