{
  "id": 7395791,
  "type": "Feature",
  "properties": {
    "tgn:hierarchy":[
        "tgn:7395791",
        "tgn:1000001",
        "tgn:7005597",
        "tgn:7005560",
        "tgn:7029392"
    ],
    "tgn:id":7395791,
    "tgn:name":"San Antonio",
    "tgn:placetype":[
        "aat:300008347"
    ]
},
  "bbox": [],
  "geometry": {"coordinates":[-98.866667,24.666667],"type":"Point"}
}