{
  "id": 1038099,
  "type": "Feature",
  "properties": {
    "tgn:hierarchy":[
        "tgn:1038099",
        "tgn:7003669",
        "tgn:1000003",
        "tgn:7000084",
        "tgn:7029392"
    ],
    "tgn:id":1038099,
    "tgn:name":"Aach im Allg\u00e4u",
    "tgn:placetype":[
        "aat:300008347"
    ]
},
  "bbox": [],
  "geometry": {"coordinates":[9.9667,47.5167],"type":"Point"}
}