<<<<<<< HEAD
{
  "id": 2761818,
  "type": "Feature",
  "properties": {
    "tgn:hierarchy":[
        "tgn:2761818",
        "tgn:1000001",
        "tgn:7012149",
        "tgn:2001486",
        "tgn:7007709",
        "tgn:7029392"
    ],
    "tgn:id":2761818,
    "tgn:name":"West Prong Mortons Mill Pond",
    "tgn:placetype":[
        "aat:300008699"
    ]
},
  "bbox": [],
  "geometry": {"coordinates":[-76.8,34.85],"type":"Point"}
}
=======
{"geometry":{"type":"Point","coordinates":[-76.800000,34.850000]},"type":"Feature","properties":{"hierarchy":["tgn:2761818","tgn:1000001","tgn:7012149","tgn:2001486","tgn:7007709","tgn:7029392"],"placetype":["aat:300008699"],"id":2761818,"name:xx":"West Prong Mortons Mill Pond"}}
>>>>>>> 03f74aca74312dbeaf24d7e61306dd6a786dc3d0
