{
  "id": 7294447,
  "type": "Feature",
  "properties": {
    "tgn:hierarchy":[
        "tgn:7294447",
        "tgn:7002826",
        "tgn:7001158",
        "tgn:1000003",
        "tgn:1000095",
        "tgn:7029392"
    ],
    "tgn:id":7294447,
    "tgn:name":"Valmadrigal, Arroyo de",
    "tgn:placetype":[
        "aat:300266554",
        "aat:300008699"
    ]
},
  "bbox": [],
  "geometry": {"coordinates":[-5.283333,42.333333],"type":"Point"}
}