{
  "id": 7579947,
  "type": "Feature",
  "properties": {
    "tgn:hierarchy":[
        "tgn:7579947",
        "tgn:1001828",
        "tgn:1000004",
        "tgn:7000198",
        "tgn:7029392"
    ],
    "tgn:id":7579947,
    "tgn:name:en":"Thadkalp\u016bdi",
    "tgn:placetype":[
        "aat:300007783"
    ]
},
  "bbox": [],
  "geometry": {"coordinates":[80.466667,17.533333],"type":"Point"}
}