{
  "id": 7284857,
  "type": "Feature",
  "properties": {
    "tgn:hierarchy":[
        "tgn:7284857",
        "tgn:1001623",
        "tgn:1000049",
        "tgn:1000002",
        "tgn:7029392"
    ],
    "tgn:id":7284857,
    "tgn:name":"Puesto Viejo",
    "tgn:placetype":[
        "aat:300008347"
    ]
},
  "bbox": [],
  "geometry": {"coordinates":[-71.35,-45.266667],"type":"Point"}
}