{
  "id": 2772670,
  "type": "Feature",
  "properties": {
    "tgn:hierarchy":[
        "tgn:2772670",
        "tgn:1000001",
        "tgn:1002194",
        "tgn:7012149",
        "tgn:7007710",
        "tgn:7029392"
    ],
    "tgn:id":2772670,
    "tgn:name":"Williams Creek",
    "tgn:placetype":[
        "aat:300008706"
    ]
},
  "bbox": [],
  "geometry": {"coordinates":[-76.1833,41.8667],"type":"Point"}
}