<<<<<<< HEAD
{
  "id": 7051043,
  "type": "Feature",
  "properties": {
    "tgn:hierarchy":[
        "tgn:7051043",
        "tgn:7005611",
        "tgn:1000003",
        "tgn:7003120",
        "tgn:1000080",
        "tgn:7029392"
    ],
    "tgn:id":7051043,
    "tgn:name":"Piano",
    "tgn:placetype":[
        "aat:300008347"
    ]
},
  "bbox": [],
  "geometry": {"coordinates":[8.166667,44.833333],"type":"Point"}
}
=======
{"geometry":{"type":"Point","coordinates":[8.166667,44.833333]},"type":"Feature","properties":{"hierarchy":["tgn:7051043","tgn:7005611","tgn:1000003","tgn:7003120","tgn:1000080","tgn:7029392"],"placetype":["aat:300008347"],"id":7051043,"name:xx":"Piano"}}
>>>>>>> 03f74aca74312dbeaf24d7e61306dd6a786dc3d0
