<<<<<<< HEAD
{
  "id": 2766942,
  "type": "Feature",
  "properties": {
    "tgn:hierarchy":[
        "tgn:2766942",
        "tgn:1000001",
        "tgn:7016098",
        "tgn:7012149",
        "tgn:7007516",
        "tgn:7029392"
    ],
    "tgn:id":2766942,
    "tgn:name":"White Point Bar",
    "tgn:placetype":[
        "aat:300132348"
    ]
},
  "bbox": [],
  "geometry": {"coordinates":[-76.8167,38.2833],"type":"Point"}
}
=======
{"geometry":{"type":"Point","coordinates":[-76.816700,38.283300]},"type":"Feature","properties":{"hierarchy":["tgn:2766942","tgn:1000001","tgn:7016098","tgn:7012149","tgn:7007516","tgn:7029392"],"placetype":["aat:300132348"],"id":2766942,"name:xx":"White Point Bar"}}
>>>>>>> 03f74aca74312dbeaf24d7e61306dd6a786dc3d0
