{
  "id": 7223235,
  "type": "Feature",
  "properties": {
    "tgn:hierarchy":[
        "tgn:7223235",
        "tgn:7002750",
        "tgn:7001399",
        "tgn:1000003",
        "tgn:1000074",
        "tgn:7029392"
    ],
    "tgn:id":7223235,
    "tgn:name":"Melo\u00fana",
    "tgn:placetype":[
        "aat:300008795"
    ]
},
  "bbox": [],
  "geometry": {"coordinates":[22.216667,39.833333],"type":"Point"}
}