{
  "id": 2330530,
  "type": "Feature",
  "properties": {
    "tgn:hierarchy":[
        "tgn:2330530",
        "tgn:1000001",
        "tgn:7012149",
        "tgn:1002382",
        "tgn:7007255",
        "tgn:7029392"
    ],
    "tgn:id":2330530,
    "tgn:name":"Flat Creek",
    "tgn:placetype":[
        "aat:300008706"
    ]
},
  "bbox": [],
  "geometry": {"coordinates":[-84.9167,38.2667],"type":"Point"}
}