<<<<<<< HEAD
{
  "id": 2330530,
  "type": "Feature",
  "properties": {
    "tgn:hierarchy":[
        "tgn:2330530",
        "tgn:1000001",
        "tgn:7012149",
        "tgn:1002382",
        "tgn:7007255",
        "tgn:7029392"
    ],
    "tgn:id":2330530,
    "tgn:name":"Flat Creek",
    "tgn:placetype":[
        "aat:300008706"
    ]
},
  "bbox": [],
  "geometry": {"coordinates":[-84.9167,38.2667],"type":"Point"}
}
=======
{"geometry":{"type":"Point","coordinates":[-84.916700,38.266700]},"type":"Feature","properties":{"hierarchy":["tgn:2330530","tgn:1000001","tgn:7012149","tgn:1002382","tgn:7007255","tgn:7029392"],"placetype":["aat:300008706"],"id":2330530,"name:xx":"Flat Creek"}}
>>>>>>> 03f74aca74312dbeaf24d7e61306dd6a786dc3d0
