{
  "id": 2781502,
  "type": "Feature",
  "properties": {
    "tgn:hierarchy":[
        "tgn:2781502",
        "tgn:1000001",
        "tgn:2001426",
        "tgn:7012149",
        "tgn:7007564",
        "tgn:7029392"
    ],
    "tgn:id":2781502,
    "tgn:name":"Woodman Brook",
    "tgn:placetype":[
        "aat:300008699"
    ]
},
  "bbox": [],
  "geometry": {"coordinates":[-70.95,43.1167],"type":"Point"}
}