{
  "id": 7027098,
  "type": "Feature",
  "properties": {
    "tgn:hierarchy":[
        "tgn:7027098",
        "tgn:7002445",
        "tgn:1000003",
        "tgn:7008143",
        "tgn:7008591",
        "tgn:7029392"
    ],
    "tgn:id":7027098,
    "tgn:name":"Monnington on Wye",
    "tgn:placetype":[
        "aat:300008347",
        "aat:300008372"
    ]
},
  "bbox": [],
  "geometry": {"coordinates":[-2.9167,52.0833],"type":"Point"}
}