{
  "id": 7217914,
  "type": "Feature",
  "properties": {
    "tgn:hierarchy":[
        "tgn:7217914",
        "tgn:7011164",
        "tgn:7002674",
        "tgn:1000003",
        "tgn:1000074",
        "tgn:7029392"
    ],
    "tgn:id":7217914,
    "tgn:name":"Mon\u00ed Zood\u00f3chou Pig\u00eds",
    "tgn:placetype":[
        "aat:300000641"
    ]
},
  "bbox": [],
  "geometry": {"coordinates":[27.03,37.769444],"type":"Point"}
}