{
  "id": 7291789,
  "type": "Feature",
  "properties": {
    "tgn:hierarchy":[
        "tgn:7291789",
        "tgn:1001695",
        "tgn:1000049",
        "tgn:1000002",
        "tgn:7029392"
    ],
    "tgn:id":7291789,
    "tgn:name":"El Guindo",
    "tgn:placetype":[
        "aat:300008347"
    ]
},
  "bbox": [],
  "geometry": {"coordinates":[-71.266667,-34.633333],"type":"Point"}
}