{
  "id": 2626493,
  "type": "Feature",
  "properties": {
    "tgn:hierarchy":[
        "tgn:2626493",
        "tgn:1000001",
        "tgn:7016172",
        "tgn:7012149",
        "tgn:2000155",
        "tgn:7029392"
    ],
    "tgn:id":2626493,
    "tgn:name":"Rocky Hollow",
    "tgn:placetype":[
        "aat:300008761"
    ]
},
  "bbox": [],
  "geometry": {"coordinates":[-93.3167,36.0167],"type":"Point"}
}