{
  "id": 1063856,
  "type": "Feature",
  "properties": {
    "tgn:hierarchy":[
        "tgn:1063856",
        "tgn:1000003",
        "tgn:7003774",
        "tgn:1000097",
        "tgn:7029392"
    ],
    "tgn:id":1063856,
    "tgn:name":"Vittangi",
    "tgn:placetype":[
        "aat:300008347"
    ]
},
  "bbox": [],
  "geometry": {"coordinates":[21.6667,67.6833],"type":"Point"}
}