{
  "id": 1122658,
  "type": "Feature",
  "properties": {
    "tgn:hierarchy":[
        "tgn:1122658",
        "tgn:1001985",
        "tgn:1000002",
        "tgn:1000059",
        "tgn:7029392"
    ],
    "tgn:id":1122658,
    "tgn:name":"Chama, R\u00edo",
    "tgn:placetype":[
        "aat:300008707"
    ]
},
  "bbox": [],
  "geometry": {"coordinates":[-71.616,9.066],"type":"Point"}
}