{
  "id": 7575391,
  "type": "Feature",
  "properties": {
    "tgn:hierarchy":[
        "tgn:7575391",
        "tgn:1000004",
        "tgn:7000198",
        "tgn:7031783",
        "tgn:7029392"
    ],
    "tgn:id":7575391,
    "tgn:name:en":"Lachmipur",
    "tgn:placetype":[
        "aat:300008347"
    ]
},
  "bbox": [],
  "geometry": {"coordinates":[87.133526,24.504103],"type":"Point"}
}