<<<<<<< HEAD
{
  "id": 2406604,
  "type": "Feature",
  "properties": {
    "tgn:hierarchy":[
        "tgn:2406604",
        "tgn:1000001",
        "tgn:2000860",
        "tgn:7012149",
        "tgn:7007256",
        "tgn:7029392"
    ],
    "tgn:id":2406604,
    "tgn:name":"Hunt",
    "tgn:placetype":[
        "aat:300008347"
    ]
},
  "bbox": [],
  "geometry": {"coordinates":[-92.8667,32.2833],"type":"Point"}
}
=======
{"geometry":{"type":"Point","coordinates":[-92.866700,32.283300]},"type":"Feature","properties":{"hierarchy":["tgn:2406604","tgn:1000001","tgn:2000860","tgn:7012149","tgn:7007256","tgn:7029392"],"placetype":["aat:300008347"],"id":2406604,"name:xx":"Hunt"}}
>>>>>>> 03f74aca74312dbeaf24d7e61306dd6a786dc3d0
