{
  "id": 7523709,
  "type": "Feature",
  "properties": {
    "tgn:hierarchy":[
        "tgn:7523709",
        "tgn:7001242",
        "tgn:7016833",
        "tgn:7001334",
        "tgn:7029392"
    ],
    "tgn:id":7523709,
    "tgn:name:en":"Al \u1e28umrah ash Sh\u0101mikhah",
    "tgn:placetype":[
        "aat:300008795"
    ]
},
  "bbox": [],
  "geometry": {"coordinates":[32.396551,25.303386],"type":"Point"}
}