{
  "id": 2532162,
  "type": "Feature",
  "properties": {
    "tgn:hierarchy":[
        "tgn:2532162",
        "tgn:1000001",
        "tgn:7012149",
        "tgn:7007254",
        "tgn:7029392"
    ],
    "tgn:id":2532162,
    "tgn:name":"Munkers Creek",
    "tgn:placetype":[
        "aat:300008706"
    ]
},
  "bbox": [],
  "geometry": {"coordinates":[-96.5167,38.85],"type":"Point"}
}