{
  "id": 2204412,
  "type": "Feature",
  "properties": {
    "tgn:hierarchy":[
        "tgn:2204412",
        "tgn:1000001",
        "tgn:7012149",
        "tgn:1002787",
        "tgn:7007523",
        "tgn:7029392"
    ],
    "tgn:id":2204412,
    "tgn:name":"Buffalo Creek",
    "tgn:placetype":[
        "aat:300008706"
    ]
},
  "bbox": [],
  "geometry": {"coordinates":[-91.0667,39.2667],"type":"Point"}
}