{
  "id": 2443164,
  "type": "Feature",
  "properties": {
    "tgn:hierarchy":[
        "tgn:2443164",
        "tgn:1000001",
        "tgn:7012149",
        "tgn:7007706",
        "tgn:7029392"
    ],
    "tgn:id":2443164,
    "tgn:name":"Kyger Run",
    "tgn:placetype":[
        "aat:300008699"
    ]
},
  "bbox": [],
  "geometry": {"coordinates":[-82.4667,38.9667],"type":"Point"}
}