{
  "id": 7556619,
  "type": "Feature",
  "properties": {
    "tgn:hierarchy":[
        "tgn:7556619",
        "tgn:1000004",
        "tgn:7000198",
        "tgn:1001977",
        "tgn:7029392"
    ],
    "tgn:id":7556619,
    "tgn:name:en":"Sebu La",
    "tgn:placetype":[
        "aat:300259572"
    ]
},
  "bbox": [],
  "geometry": {"coordinates":[88.666667,27.95],"type":"Point"}
}