{
  "id": 2501149,
  "type": "Feature",
  "properties": {
    "tgn:hierarchy":[
        "tgn:2501149",
        "tgn:1000001",
        "tgn:7012149",
        "tgn:2002186",
        "tgn:7007919",
        "tgn:7029392"
    ],
    "tgn:id":2501149,
    "tgn:name":"McGee Run",
    "tgn:placetype":[
        "aat:300008699"
    ]
},
  "bbox": [],
  "geometry": {"coordinates":[-79.6167,37.7333],"type":"Point"}
}