{
  "id": 1033675,
  "type": "Feature",
  "properties": {
    "tgn:hierarchy":[
        "tgn:1033675",
        "tgn:1000003",
        "tgn:7002877",
        "tgn:1000070",
        "tgn:7029392"
    ],
    "tgn:id":1033675,
    "tgn:name":"Marolle-en-Sologne, la",
    "tgn:placetype":[
        "aat:300008347"
    ]
},
  "bbox": [],
  "geometry": {"coordinates":[1.7833,47.5833],"type":"Point"}
}