{
  "id": 2081437,
  "type": "Feature",
  "properties": {
    "tgn:hierarchy":[
        "tgn:2081437",
        "tgn:1000001",
        "tgn:7012149",
        "tgn:1002917",
        "tgn:7007706",
        "tgn:7029392"
    ],
    "tgn:id":2081437,
    "tgn:name":"Pleasant View",
    "tgn:placetype":[
        "aat:300008347",
        "aat:300387210"
    ]
},
  "bbox": [],
  "geometry": {"coordinates":[-81.3333,40.8167],"type":"Point"}
}