{
  "id": 7555159,
  "type": "Feature",
  "properties": {
    "tgn:hierarchy":[
        "tgn:7555159",
        "tgn:1000004",
        "tgn:7000198",
        "tgn:7000799",
        "tgn:7029392"
    ],
    "tgn:id":7555159,
    "tgn:name:en":"Mir\u0101n S\u0101hib",
    "tgn:placetype":[
        "aat:300007783"
    ]
},
  "bbox": [],
  "geometry": {"coordinates":[74.833333,32.616667],"type":"Point"}
}