{
  "id": 2520699,
  "type": "Feature",
  "properties": {
    "tgn:hierarchy":[
        "tgn:2520699",
        "tgn:1000001",
        "tgn:2000952",
        "tgn:7012149",
        "tgn:7007520",
        "tgn:7029392"
    ],
    "tgn:id":2520699,
    "tgn:name":"Monocle Lake",
    "tgn:placetype":[
        "aat:300008680"
    ]
},
  "bbox": [],
  "geometry": {"coordinates":[-84.6333,46.4667],"type":"Point"}
}