{
  "id": 7033634,
  "type": "Feature",
  "properties": {
    "tgn:hierarchy":[
        "tgn:7033634",
        "tgn:7003129",
        "tgn:1000003",
        "tgn:7008516",
        "tgn:1000080",
        "tgn:7029392"
    ],
    "tgn:id":7033634,
    "tgn:name":"Orsoleto",
    "tgn:placetype":[
        "aat:300008347"
    ]
},
  "bbox": [],
  "geometry": {"coordinates":[12.525833,44.084722],"type":"Point"}
}