{
  "id": 1018853,
  "type": "Feature",
  "properties": {
    "tgn:hierarchy":[
        "tgn:1018853",
        "tgn:1001593",
        "tgn:1000001",
        "tgn:7005565",
        "tgn:7029392"
    ],
    "tgn:id":1018853,
    "tgn:name":"Las Palmas",
    "tgn:placetype":[
        "aat:300008347"
    ]
},
  "bbox": [],
  "geometry": {"coordinates":[-81.4667,8.15],"type":"Point"}
}