{
  "id": 2562746,
  "type": "Feature",
  "properties": {
    "tgn:hierarchy":[
        "tgn:2562746",
        "tgn:1000001",
        "tgn:7012149",
        "tgn:2002191",
        "tgn:7007919",
        "tgn:7029392"
    ],
    "tgn:id":2562746,
    "tgn:name":"Overbay Hollow",
    "tgn:placetype":[
        "aat:300008761"
    ]
},
  "bbox": [],
  "geometry": {"coordinates":[-81.3667,36.8333],"type":"Point"}
}