{
  "id": 1136313,
  "type": "Feature",
  "properties": {
    "tgn:hierarchy":[
        "tgn:1136313",
        "tgn:7005581",
        "tgn:1000001",
        "tgn:7005560",
        "tgn:7029392"
    ],
    "tgn:id":1136313,
    "tgn:name":"Ignacio Zaragoza",
    "tgn:placetype":[
        "aat:300008347"
    ]
},
  "bbox": [],
  "geometry": {"coordinates":[-107.75,29.65],"type":"Point"}
}