{
  "id": 2349275,
  "type": "Feature",
  "properties": {
    "tgn:hierarchy":[
        "tgn:2349275",
        "tgn:7019618",
        "tgn:1000001",
        "tgn:7012149",
        "tgn:7007564",
        "tgn:7029392"
    ],
    "tgn:id":2349275,
    "tgn:name":"Gilboa",
    "tgn:placetype":[
        "aat:300008347"
    ]
},
  "bbox": [],
  "geometry": {"coordinates":[-72.3833,42.9833],"type":"Point"}
}