{
  "id": 2682024,
  "type": "Feature",
  "properties": {
    "tgn:hierarchy":[
        "tgn:2682024",
        "tgn:1000001",
        "tgn:7012149",
        "tgn:2001496",
        "tgn:7007709",
        "tgn:7029392"
    ],
    "tgn:id":2682024,
    "tgn:name":"South Stanley Creek",
    "tgn:placetype":[
        "aat:300008706"
    ]
},
  "bbox": [],
  "geometry": {"coordinates":[-81.0833,35.35],"type":"Point"}
}