{
  "id": 7222987,
  "type": "Feature",
  "properties": {
    "tgn:hierarchy":[
        "tgn:7222987",
        "tgn:4003773",
        "tgn:7001395",
        "tgn:1000003",
        "tgn:1000074",
        "tgn:7029392"
    ],
    "tgn:id":7222987,
    "tgn:name":"Plat\u00edstomon",
    "tgn:placetype":[
        "aat:300008347"
    ]
},
  "bbox": [],
  "geometry": {"coordinates":[22.116667,38.966667],"type":"Point"}
}