{
  "id": 7314291,
  "type": "Feature",
  "properties": {
    "tgn:hierarchy":[
        "tgn:7314291",
        "tgn:1001705",
        "tgn:1000049",
        "tgn:1000002",
        "tgn:7029392"
    ],
    "tgn:id":7314291,
    "tgn:name":"Lipim\u00e1vida",
    "tgn:placetype":[
        "aat:300008347"
    ]
},
  "bbox": [],
  "geometry": {"coordinates":[-72.15,-34.85],"type":"Point"}
}