{
  "id": 2330357,
  "type": "Feature",
  "properties": {
    "tgn:hierarchy":[
        "tgn:2330357",
        "tgn:1000001",
        "tgn:7012149",
        "tgn:2000797",
        "tgn:7007255",
        "tgn:7029392"
    ],
    "tgn:id":2330357,
    "tgn:name":"Flat Branch",
    "tgn:placetype":[
        "aat:300008699"
    ]
},
  "bbox": [],
  "geometry": {"coordinates":[-83.45,36.7667],"type":"Point"}
}