{
  "id": 1073083,
  "type": "Feature",
  "properties": {
    "tgn:hierarchy":[
        "tgn:1073083",
        "tgn:1000004",
        "tgn:7002079",
        "tgn:1000111",
        "tgn:7029392"
    ],
    "tgn:id":1073083,
    "tgn:name":"Xinhua",
    "tgn:placetype":[
        "aat:300008347"
    ]
},
  "bbox": [],
  "geometry": {"coordinates":[111.0333,27.6167],"type":"Point"}
}