{
  "id": 1043776,
  "type": "Feature",
  "properties": {
    "tgn:hierarchy":[
        "tgn:1043776",
        "tgn:7003168",
        "tgn:1000003",
        "tgn:7009760",
        "tgn:1000080",
        "tgn:7029392"
    ],
    "tgn:id":1043776,
    "tgn:name":"Campiglia dei Fosci",
    "tgn:placetype":[
        "aat:300008347",
        "aat:300008375"
    ]
},
  "bbox": [],
  "geometry": {"coordinates":[11.05,43.45],"type":"Point"}
}