{
  "id": 2438618,
  "type": "Feature",
  "properties": {
    "tgn:hierarchy":[
        "tgn:2438618",
        "tgn:1000001",
        "tgn:7012149",
        "tgn:7015770",
        "tgn:7007919",
        "tgn:7029392"
    ],
    "tgn:id":2438618,
    "tgn:name":"Kingsley Lake",
    "tgn:placetype":[
        "aat:300006191"
    ]
},
  "bbox": [],
  "geometry": {"coordinates":[-77.6667,39.0667],"type":"Point"}
}