{
  "id": 1004787,
  "type": "Feature",
  "properties": {
    "tgn:hierarchy":[
        "tgn:1004787",
        "tgn:1000003",
        "tgn:7003677",
        "tgn:7000084",
        "tgn:7004943",
        "tgn:7029392"
    ],
    "tgn:id":1004787,
    "tgn:name":"K\u00fcllenhahn",
    "tgn:placetype":[
        "aat:300000745",
        "aat:300387332"
    ]
},
  "bbox": [],
  "geometry": {"coordinates":[7.116667,51.216667],"type":"Point"}
}