{
  "id": 2434124,
  "type": "Feature",
  "properties": {
    "tgn:hierarchy":[
        "tgn:2434124",
        "tgn:1000001",
        "tgn:2001471",
        "tgn:7012149",
        "tgn:7007709",
        "tgn:7029392"
    ],
    "tgn:id":2434124,
    "tgn:name":"Kelso Bay",
    "tgn:placetype":[
        "aat:300008905"
    ]
},
  "bbox": [],
  "geometry": {"coordinates":[-78.3667,34.6667],"type":"Point"}
}