{
  "id": 7397740,
  "type": "Feature",
  "properties": {
    "tgn:hierarchy":[
        "tgn:7397740",
        "tgn:1000001",
        "tgn:1001893",
        "tgn:7005560",
        "tgn:7029392"
    ],
    "tgn:id":7397740,
    "tgn:name":"Huizachal",
    "tgn:placetype":[
        "aat:300008347"
    ]
},
  "bbox": [],
  "geometry": {"coordinates":[-99.208333,19.45],"type":"Point"}
}