{
  "id": 7418495,
  "type": "Feature",
  "properties": {
    "tgn:hierarchy":[
        "tgn:7418495",
        "tgn:1000001",
        "tgn:7005589",
        "tgn:7005560",
        "tgn:7029392"
    ],
    "tgn:id":7418495,
    "tgn:name:es":"Potrero Prieto de Arriba",
    "tgn:placetype":[
        "aat:300008347"
    ]
},
  "bbox": [],
  "geometry": {"coordinates":[-99.9925,24.849167],"type":"Point"}
}