{
  "id": 7230828,
  "type": "Feature",
  "properties": {
    "tgn:hierarchy":[
        "tgn:7230828",
        "tgn:7011170",
        "tgn:7002715",
        "tgn:1000003",
        "tgn:1000074",
        "tgn:7029392"
    ],
    "tgn:id":7230828,
    "tgn:name":"Kremast\u00ed",
    "tgn:placetype":[
        "aat:300008347"
    ]
},
  "bbox": [],
  "geometry": {"coordinates":[24.766667,41.016667],"type":"Point"}
}