{
  "id": 2321777,
  "type": "Feature",
  "properties": {
    "tgn:hierarchy":[
        "tgn:2321777",
        "tgn:7006450",
        "tgn:1000001",
        "tgn:7012149",
        "tgn:7019760",
        "tgn:7029392"
    ],
    "tgn:id":2321777,
    "tgn:name":"Fairweather Ground",
    "tgn:placetype":[
        "aat:300132348"
    ]
},
  "bbox": [],
  "geometry": {"coordinates":[-138.4667,58.2667],"type":"Point"}
}