{
  "id": 7291409,
  "type": "Feature",
  "properties": {
    "tgn:hierarchy":[
        "tgn:7291409",
        "tgn:1001699",
        "tgn:1000049",
        "tgn:1000002",
        "tgn:7029392"
    ],
    "tgn:id":7291409,
    "tgn:name":"Escal\u00f3n, Cerro",
    "tgn:placetype":[
        "aat:300008795"
    ]
},
  "bbox": [],
  "geometry": {"coordinates":[-71.983333,-41.266667],"type":"Point"}
}