{
  "id": 2042004,
  "type": "Feature",
  "properties": {
    "tgn:hierarchy":[
        "tgn:2042004",
        "tgn:1000001",
        "tgn:7012149",
        "tgn:2000804",
        "tgn:7007255",
        "tgn:7029392"
    ],
    "tgn:id":2042004,
    "tgn:name":"Winifred",
    "tgn:placetype":[
        "aat:300008347",
        "aat:300387210"
    ]
},
  "bbox": [],
  "geometry": {"coordinates":[-82.85,37.9333],"type":"Point"}
}