{
  "id": 2132692,
  "type": "Feature",
  "properties": {
    "tgn:hierarchy":[
        "tgn:2132692",
        "tgn:1000001",
        "tgn:7012149",
        "tgn:2001706",
        "tgn:7007708",
        "tgn:7029392"
    ],
    "tgn:id":2132692,
    "tgn:name":"Anchor",
    "tgn:placetype":[
        "aat:300008347"
    ]
},
  "bbox": [],
  "geometry": {"coordinates":[-123.15,42.8333],"type":"Point"}
}