{
  "id": 7278030,
  "type": "Feature",
  "properties": {
    "tgn:hierarchy":[
        "tgn:7278030",
        "tgn:1001657",
        "tgn:1000049",
        "tgn:1000002",
        "tgn:7029392"
    ],
    "tgn:id":7278030,
    "tgn:name":"Los \u00d1onques, Punta",
    "tgn:placetype":[
        "aat:300386846"
    ]
},
  "bbox": [],
  "geometry": {"coordinates":[-71.666667,-30.308333],"type":"Point"}
}