{
  "id": 7008588,
  "type": "Feature",
  "properties": {
    "tgn:hierarchy":[
        "tgn:7008588",
        "tgn:1000003",
        "tgn:7002892",
        "tgn:1000070",
        "tgn:7029392"
    ],
    "tgn:id":7008588,
    "tgn:name":"Saujon",
    "tgn:placetype":[
        "aat:300008347"
    ]
},
  "bbox": [],
  "geometry": {"coordinates":[-0.9167,45.6667],"type":"Point"}
}