{
  "id": 2305860,
  "type": "Feature",
  "properties": {
    "tgn:hierarchy":[
        "tgn:2305860",
        "tgn:1000001",
        "tgn:2001261",
        "tgn:7012149",
        "tgn:7007524",
        "tgn:7029392"
    ],
    "tgn:id":2305860,
    "tgn:name":"East Dipping Vat Coulee",
    "tgn:placetype":[
        "aat:300008761"
    ]
},
  "bbox": [],
  "geometry": {"coordinates":[-107.5667,45.3833],"type":"Point"}
}