{
  "id": 7310729,
  "type": "Feature",
  "properties": {
    "tgn:hierarchy":[
        "tgn:7310729",
        "tgn:1001692",
        "tgn:1000049",
        "tgn:1000002",
        "tgn:7029392"
    ],
    "tgn:id":7310729,
    "tgn:name":"Milladomuche, Quebrada",
    "tgn:placetype":[
        "aat:300008699"
    ]
},
  "bbox": [],
  "geometry": {"coordinates":[-72.75,-38.083333],"type":"Point"}
}