{
  "id": 2146143,
  "type": "Feature",
  "properties": {
    "tgn:hierarchy":[
        "tgn:2146143",
        "tgn:1000001",
        "tgn:7012149",
        "tgn:2001190",
        "tgn:7007523",
        "tgn:7029392"
    ],
    "tgn:id":2146143,
    "tgn:name":"Ballard Lake Section 14",
    "tgn:placetype":[
        "aat:300006191"
    ]
},
  "bbox": [],
  "geometry": {"coordinates":[-91.3167,37.8167],"type":"Point"}
}