{
  "id": 2618058,
  "type": "Feature",
  "properties": {
    "tgn:hierarchy":[
        "tgn:2618058",
        "tgn:1000001",
        "tgn:7012149",
        "tgn:2001440",
        "tgn:7007566",
        "tgn:7029392"
    ],
    "tgn:id":2618058,
    "tgn:name":"Ridgewood",
    "tgn:placetype":[
        "aat:300000390"
    ]
},
  "bbox": [],
  "geometry": {"coordinates":[-108.45,31.8167],"type":"Point"}
}