<<<<<<< HEAD
{
  "id": 2250071,
  "type": "Feature",
  "properties": {
    "tgn:hierarchy":[
        "tgn:2250071",
        "tgn:1002157",
        "tgn:1000001",
        "tgn:7012149",
        "tgn:7007565",
        "tgn:7029392"
    ],
    "tgn:id":2250071,
    "tgn:name":"Collins Cove",
    "tgn:placetype":[
        "aat:300132316"
    ]
},
  "bbox": [],
  "geometry": {"coordinates":[-74.4667,39.5333],"type":"Point"}
}
=======
{"geometry":{"type":"Point","coordinates":[-74.466700,39.533300]},"type":"Feature","properties":{"hierarchy":["tgn:2250071","tgn:1002157","tgn:1000001","tgn:7012149","tgn:7007565","tgn:7029392"],"placetype":["aat:300132316"],"id":2250071,"name:xx":"Collins Cove"}}
>>>>>>> 03f74aca74312dbeaf24d7e61306dd6a786dc3d0
