{
  "id": 2116329,
  "type": "Feature",
  "properties": {
    "tgn:hierarchy":[
        "tgn:2116329",
        "tgn:1000001",
        "tgn:7012149",
        "tgn:1002505",
        "tgn:7007920",
        "tgn:7029392"
    ],
    "tgn:id":2116329,
    "tgn:name":"Mountain View Beach",
    "tgn:placetype":[
        "aat:300008347"
    ]
},
  "bbox": [],
  "geometry": {"coordinates":[-122.4333,48.1333],"type":"Point"}
}