{
  "id": 7286235,
  "type": "Feature",
  "properties": {
    "tgn:hierarchy":[
        "tgn:7286235",
        "tgn:1001768",
        "tgn:1000049",
        "tgn:1000002",
        "tgn:7029392"
    ],
    "tgn:id":7286235,
    "tgn:name":"Hornillas, Cerro",
    "tgn:placetype":[
        "aat:300008777"
    ]
},
  "bbox": [],
  "geometry": {"coordinates":[-71.35,-32.316667],"type":"Point"}
}