{
  "id": 2363941,
  "type": "Feature",
  "properties": {
    "tgn:hierarchy":[
        "tgn:2363941",
        "tgn:1000001",
        "tgn:7012149",
        "tgn:7007157",
        "tgn:1002675",
        "tgn:7029392"
    ],
    "tgn:id":2363941,
    "tgn:name":"Green Monster Mine",
    "tgn:placetype":[
        "aat:300000390"
    ]
},
  "bbox": [],
  "geometry": {"coordinates":[-118.2167,37.7333],"type":"Point"}
}