{
  "id": 1034996,
  "type": "Feature",
  "properties": {
    "tgn:hierarchy":[
        "tgn:1034996",
        "tgn:1000003",
        "tgn:1000070",
        "tgn:7002895",
        "tgn:7029392"
    ],
    "tgn:id":1034996,
    "tgn:name":"Puget-Ville",
    "tgn:placetype":[
        "aat:300008347"
    ]
},
  "bbox": [],
  "geometry": {"coordinates":[6.1333,43.2833],"type":"Point"}
}