{
  "id": 2133462,
  "type": "Feature",
  "properties": {
    "tgn:hierarchy":[
        "tgn:2133462",
        "tgn:1000001",
        "tgn:7012149",
        "tgn:7007157",
        "tgn:1002710",
        "tgn:7029392"
    ],
    "tgn:id":2133462,
    "tgn:name":"Andesite Peak",
    "tgn:placetype":[
        "aat:300008798"
    ]
},
  "bbox": [],
  "geometry": {"coordinates":[-120.35,39.35],"type":"Point"}
}