{
  "id": 1038148,
  "type": "Feature",
  "properties": {
    "tgn:hierarchy":[
        "tgn:1038148",
        "tgn:1000003",
        "tgn:7003677",
        "tgn:7000084",
        "tgn:7029392"
    ],
    "tgn:id":1038148,
    "tgn:name":"Allagen",
    "tgn:placetype":[
        "aat:300008347"
    ]
},
  "bbox": [],
  "geometry": {"coordinates":[8.233333,51.483333],"type":"Point"}
}