{
  "id": 7061528,
  "type": "Feature",
  "properties": {
    "tgn:hierarchy":[
        "tgn:7061528",
        "tgn:1000003",
        "tgn:7003676",
        "tgn:7000084",
        "tgn:7029392"
    ],
    "tgn:id":7061528,
    "tgn:name":"Auf den Vieren",
    "tgn:placetype":[
        "aat:300000206"
    ]
},
  "bbox": [],
  "geometry": {"coordinates":[8.366667,52.216667],"type":"Point"}
}