{
  "id": 7491010,
  "type": "Feature",
  "properties": {
    "tgn:hierarchy":[
        "tgn:7491010",
        "tgn:1000004",
        "tgn:7001009",
        "tgn:1000141",
        "tgn:7029392"
    ],
    "tgn:id":7491010,
    "tgn:name":"Beikengzi",
    "tgn:placetype":[
        "aat:300008347"
    ]
},
  "bbox": [],
  "geometry": {"coordinates":[120.771944,24.038889],"type":"Point"}
}