{
  "id": 7176168,
  "type": "Feature",
  "properties": {
    "tgn:hierarchy":[
        "tgn:7176168",
        "tgn:7003692",
        "tgn:1000003",
        "tgn:7000084",
        "tgn:7029392"
    ],
    "tgn:id":7176168,
    "tgn:name":"Gr\u00f6sselbach",
    "tgn:placetype":[
        "aat:300008699"
    ]
},
  "bbox": [],
  "geometry": {"coordinates":[8.616667,48.85],"type":"Point"}
}