{
  "id": 2223765,
  "type": "Feature",
  "properties": {
    "tgn:hierarchy":[
        "tgn:2223765",
        "tgn:1000001",
        "tgn:7012149",
        "tgn:2000355",
        "tgn:7007248",
        "tgn:7029392"
    ],
    "tgn:id":2223765,
    "tgn:name":"Carter Mountain",
    "tgn:placetype":[
        "aat:300008798"
    ]
},
  "bbox": [],
  "geometry": {"coordinates":[-84.6833,34.4333],"type":"Point"}
}