{
  "id": 7201287,
  "type": "Feature",
  "properties": {
    "tgn:hierarchy":[
        "tgn:7201287",
        "tgn:1000003",
        "tgn:7003676",
        "tgn:7000084",
        "tgn:7029392"
    ],
    "tgn:id":7201287,
    "tgn:name":"Born",
    "tgn:placetype":[
        "aat:300000745"
    ]
},
  "bbox": [],
  "geometry": {"coordinates":[8.633333,53.316667],"type":"Point"}
}