{
  "id": 2250999,
  "type": "Feature",
  "properties": {
    "tgn:hierarchy":[
        "tgn:2250999",
        "tgn:1000001",
        "tgn:7012149",
        "tgn:2002127",
        "tgn:7007827",
        "tgn:7029392"
    ],
    "tgn:id":2250999,
    "tgn:name":"Columbine Spring",
    "tgn:placetype":[
        "aat:300008697"
    ]
},
  "bbox": [],
  "geometry": {"coordinates":[-113.4333,37.3167],"type":"Point"}
}