<<<<<<< HEAD
{
  "id": 2250999,
  "type": "Feature",
  "properties": {
    "tgn:hierarchy":[
        "tgn:2250999",
        "tgn:1000001",
        "tgn:7012149",
        "tgn:2002127",
        "tgn:7007827",
        "tgn:7029392"
    ],
    "tgn:id":2250999,
    "tgn:name":"Columbine Spring",
    "tgn:placetype":[
        "aat:300008697"
    ]
},
  "bbox": [],
  "geometry": {"coordinates":[-113.4333,37.3167],"type":"Point"}
}
=======
{"geometry":{"type":"Point","coordinates":[-113.433300,37.316700]},"type":"Feature","properties":{"hierarchy":["tgn:2250999","tgn:1000001","tgn:7012149","tgn:2002127","tgn:7007827","tgn:7029392"],"placetype":["aat:300008697"],"id":2250999,"name:xx":"Columbine Spring"}}
>>>>>>> 03f74aca74312dbeaf24d7e61306dd6a786dc3d0
