{
  "id": 2244430,
  "type": "Feature",
  "properties": {
    "tgn:hierarchy":[
        "tgn:2244430",
        "tgn:1000001",
        "tgn:7012149",
        "tgn:2001494",
        "tgn:7007709",
        "tgn:7029392"
    ],
    "tgn:id":2244430,
    "tgn:name":"Clinard Lake",
    "tgn:placetype":[
        "aat:300006191"
    ]
},
  "bbox": [],
  "geometry": {"coordinates":[-80.3167,36.1333],"type":"Point"}
}