{
  "id": 7564800,
  "type": "Feature",
  "properties": {
    "tgn:hierarchy":[
        "tgn:7564800",
        "tgn:1000004",
        "tgn:7000198",
        "tgn:7016722",
        "tgn:7029392"
    ],
    "tgn:id":7564800,
    "tgn:name:en":"Rah\u0101oli",
    "tgn:placetype":[
        "aat:300008347"
    ]
},
  "bbox": [],
  "geometry": {"coordinates":[79.261084,26.310563],"type":"Point"}
}