{
  "id": 2621410,
  "type": "Feature",
  "properties": {
    "tgn:hierarchy":[
        "tgn:2621410",
        "tgn:2000292",
        "tgn:1000001",
        "tgn:7012149",
        "tgn:7007248",
        "tgn:7029392"
    ],
    "tgn:id":2621410,
    "tgn:name":"Roaring Creek",
    "tgn:placetype":[
        "aat:300008706"
    ]
},
  "bbox": [],
  "geometry": {"coordinates":[-82.25,31.8833],"type":"Point"}
}