{
  "id": 2203999,
  "type": "Feature",
  "properties": {
    "tgn:hierarchy":[
        "tgn:2203999",
        "tgn:7006450",
        "tgn:1000001",
        "tgn:7012149",
        "tgn:2000087",
        "tgn:7029392"
    ],
    "tgn:id":2203999,
    "tgn:name":"Bud Creek",
    "tgn:placetype":[
        "aat:300008706"
    ]
},
  "bbox": [],
  "geometry": {"coordinates":[-161.9667,61.8333],"type":"Point"}
}