{
  "id": 2367827,
  "type": "Feature",
  "properties": {
    "tgn:hierarchy":[
        "tgn:2367827",
        "tgn:1000001",
        "tgn:7012149",
        "tgn:2001718",
        "tgn:7007708",
        "tgn:7029392"
    ],
    "tgn:id":2367827,
    "tgn:name":"Grove Spring",
    "tgn:placetype":[
        "aat:300008347"
    ]
},
  "bbox": [],
  "geometry": {"coordinates":[-117.4167,44.1833],"type":"Point"}
}