{
  "id": 2125760,
  "type": "Feature",
  "properties": {
    "tgn:hierarchy":[
        "tgn:2125760",
        "tgn:1000001",
        "tgn:7012149",
        "tgn:7007709",
        "tgn:7029392"
    ],
    "tgn:id":2125760,
    "tgn:name":"Adams Creek",
    "tgn:placetype":[
        "aat:300008706"
    ]
},
  "bbox": [],
  "geometry": {"coordinates":[-76.6833,34.8833],"type":"Point"}
}