{
  "id": 2526845,
  "type": "Feature",
  "properties": {
    "tgn:hierarchy":[
        "tgn:2526845",
        "tgn:1000001",
        "tgn:7014423",
        "tgn:7012149",
        "tgn:7007517",
        "tgn:7029392"
    ],
    "tgn:id":2526845,
    "tgn:name":"Mounce Pond",
    "tgn:placetype":[
        "aat:300008680"
    ]
},
  "bbox": [],
  "geometry": {"coordinates":[-70.7667,42.1167],"type":"Point"}
}