{
  "id": 2770121,
  "type": "Feature",
  "properties": {
    "tgn:hierarchy":[
        "tgn:2770121",
        "tgn:1000001",
        "tgn:7012149",
        "tgn:2001456",
        "tgn:7007566",
        "tgn:7029392"
    ],
    "tgn:id":2770121,
    "tgn:name":"Wild Bull Canyon",
    "tgn:placetype":[
        "aat:300008761"
    ]
},
  "bbox": [],
  "geometry": {"coordinates":[-107.5167,33.6167],"type":"Point"}
}