{
  "id": 7191770,
  "type": "Feature",
  "properties": {
    "tgn:hierarchy":[
        "tgn:7191770",
        "tgn:7003669",
        "tgn:1000003",
        "tgn:7000084",
        "tgn:7029392"
    ],
    "tgn:id":7191770,
    "tgn:name":"F\u00f6hrenreuth",
    "tgn:placetype":[
        "aat:300008347"
    ]
},
  "bbox": [],
  "geometry": {"coordinates":[11.816667,50.283333],"type":"Point"}
}