{
  "id": 7301668,
  "type": "Feature",
  "properties": {
    "tgn:hierarchy":[
        "tgn:7301668",
        "tgn:7002758",
        "tgn:7002817",
        "tgn:1000003",
        "tgn:1000095",
        "tgn:7029392"
    ],
    "tgn:id":7301668,
    "tgn:name":"Mojapi\u00e9s, Arroyo",
    "tgn:placetype":[
        "aat:300008699"
    ]
},
  "bbox": [],
  "geometry": {"coordinates":[-4.333333,38.066667],"type":"Point"}
}