<<<<<<< HEAD
{
  "id": 2259056,
  "type": "Feature",
  "properties": {
    "tgn:hierarchy":[
        "tgn:2259056",
        "tgn:1000001",
        "tgn:7012149",
        "tgn:2002371",
        "tgn:7007923",
        "tgn:7029392"
    ],
    "tgn:id":2259056,
    "tgn:name":"Cottonwood Creek",
    "tgn:placetype":[
        "aat:300008706"
    ]
},
  "bbox": [],
  "geometry": {"coordinates":[-107.9667,42.3833],"type":"Point"}
}
=======
{"geometry":{"type":"Point","coordinates":[-107.966700,42.383300]},"type":"Feature","properties":{"hierarchy":["tgn:2259056","tgn:1000001","tgn:7012149","tgn:2002371","tgn:7007923","tgn:7029392"],"placetype":["aat:300008706"],"id":2259056,"name:xx":"Cottonwood Creek"}}
>>>>>>> 03f74aca74312dbeaf24d7e61306dd6a786dc3d0
