{
  "id": 2259056,
  "type": "Feature",
  "properties": {
    "tgn:hierarchy":[
        "tgn:2259056",
        "tgn:1000001",
        "tgn:7012149",
        "tgn:2002371",
        "tgn:7007923",
        "tgn:7029392"
    ],
    "tgn:id":2259056,
    "tgn:name":"Cottonwood Creek",
    "tgn:placetype":[
        "aat:300008706"
    ]
},
  "bbox": [],
  "geometry": {"coordinates":[-107.9667,42.3833],"type":"Point"}
}