{
  "id": 7376978,
  "type": "Feature",
  "properties": {
    "tgn:hierarchy":[
        "tgn:7376978",
        "tgn:7005583",
        "tgn:1000001",
        "tgn:7005560",
        "tgn:7029392"
    ],
    "tgn:id":7376978,
    "tgn:name":"Las Mercedes, Arroyo",
    "tgn:placetype":[
        "aat:300266554",
        "aat:300008699"
    ]
},
  "bbox": [],
  "geometry": {"coordinates":[-103.783333,25.116667],"type":"Point"}
}