{
  "id": 7340001,
  "type": "Feature",
  "properties": {
    "tgn:hierarchy":[
        "tgn:7340001",
        "tgn:7002829",
        "tgn:1000003",
        "tgn:7002786",
        "tgn:1000095",
        "tgn:7029392"
    ],
    "tgn:id":7340001,
    "tgn:name":"Cot\u00e1",
    "tgn:placetype":[
        "aat:300008347"
    ]
},
  "bbox": [],
  "geometry": {"coordinates":[-7.716667,43.05],"type":"Point"}
}