{
  "id": 7243325,
  "type": "Feature",
  "properties": {
    "tgn:hierarchy":[
        "tgn:7243325",
        "tgn:7018238",
        "tgn:1000003",
        "tgn:1000063",
        "tgn:4012014",
        "tgn:7029392"
    ],
    "tgn:id":7243325,
    "tgn:name":"Les Monts",
    "tgn:placetype":[
        "aat:300008347"
    ]
},
  "bbox": [],
  "geometry": {"coordinates":[4.666667,50.75],"type":"Point"}
}