{
  "id": 2030508,
  "type": "Feature",
  "properties": {
    "tgn:hierarchy":[
        "tgn:2030508",
        "tgn:1000001",
        "tgn:1002395",
        "tgn:7012149",
        "tgn:7007251",
        "tgn:7029392"
    ],
    "tgn:id":2030508,
    "tgn:name":"Vermont",
    "tgn:placetype":[
        "aat:300008347"
    ]
},
  "bbox": [],
  "geometry": {"coordinates":[-90.4167,40.2833],"type":"Point"}
}