{
  "id": 7033437,
  "type": "Feature",
  "properties": {
    "tgn:hierarchy":[
        "tgn:7033437",
        "tgn:1003488",
        "tgn:1000003",
        "tgn:7002993",
        "tgn:1000080",
        "tgn:7029392"
    ],
    "tgn:id":7033437,
    "tgn:name":"Gleris",
    "tgn:placetype":[
        "aat:300008347"
    ]
},
  "bbox": [],
  "geometry": {"coordinates":[12.872778,45.8975],"type":"Point"}
}