{
  "id": 2631955,
  "type": "Feature",
  "properties": {
    "tgn:hierarchy":[
        "tgn:2631955",
        "tgn:7002659",
        "tgn:1000001",
        "tgn:7012149",
        "tgn:2000035",
        "tgn:7029392"
    ],
    "tgn:id":2631955,
    "tgn:name":"Rover Cave",
    "tgn:placetype":[
        "aat:300008746"
    ]
},
  "bbox": [],
  "geometry": {"coordinates":[-86.2667,34.75],"type":"Point"}
}