{
  "id": 7589073,
  "type": "Feature",
  "properties": {
    "tgn:hierarchy":[
        "tgn:7589073",
        "tgn:1000004",
        "tgn:1001869",
        "tgn:7000198",
        "tgn:7029392"
    ],
    "tgn:id":7589073,
    "tgn:name:en":"Bhojr\u0101j",
    "tgn:placetype":[
        "aat:300008347"
    ]
},
  "bbox": [],
  "geometry": {"coordinates":[69.258561,23.160831],"type":"Point"}
}