{
  "id": 7144425,
  "type": "Feature",
  "properties": {
    "tgn:hierarchy":[
        "tgn:7144425",
        "tgn:1000003",
        "tgn:7000094",
        "tgn:7000084",
        "tgn:7029392"
    ],
    "tgn:id":7144425,
    "tgn:name":"Klingen-Berg",
    "tgn:placetype":[
        "aat:300008777"
    ]
},
  "bbox": [],
  "geometry": {"coordinates":[12.466667,53.733333],"type":"Point"}
}