<<<<<<< HEAD
{
  "id": 2763352,
  "type": "Feature",
  "properties": {
    "tgn:hierarchy":[
        "tgn:2763352",
        "tgn:1000001",
        "tgn:7012149",
        "tgn:2002127",
        "tgn:7007827",
        "tgn:7029392"
    ],
    "tgn:id":2763352,
    "tgn:name":"Wet Sandy",
    "tgn:placetype":[
        "aat:300008699"
    ]
},
  "bbox": [],
  "geometry": {"coordinates":[-113.4,37.3333],"type":"Point"}
}
=======
{"geometry":{"type":"Point","coordinates":[-113.400000,37.333300]},"type":"Feature","properties":{"hierarchy":["tgn:2763352","tgn:1000001","tgn:7012149","tgn:2002127","tgn:7007827","tgn:7029392"],"placetype":["aat:300008699"],"id":2763352,"name:xx":"Wet Sandy"}}
>>>>>>> 03f74aca74312dbeaf24d7e61306dd6a786dc3d0
