{
  "id": 2693347,
  "type": "Feature",
  "properties": {
    "tgn:hierarchy":[
        "tgn:2693347",
        "tgn:1000001",
        "tgn:7012149",
        "tgn:7007157",
        "tgn:2000188",
        "tgn:7029392"
    ],
    "tgn:id":2693347,
    "tgn:name":"Stein Creek",
    "tgn:placetype":[
        "aat:300008706"
    ]
},
  "bbox": [],
  "geometry": {"coordinates":[-122.05,40.7667],"type":"Point"}
}