{
  "id": 2250951,
  "type": "Feature",
  "properties": {
    "tgn:hierarchy":[
        "tgn:2250951",
        "tgn:1000001",
        "tgn:7012149",
        "tgn:2001131",
        "tgn:7007522",
        "tgn:7029392"
    ],
    "tgn:id":2250951,
    "tgn:name":"Columbia, Lake",
    "tgn:placetype":[
        "aat:300006191"
    ]
},
  "bbox": [],
  "geometry": {"coordinates":[-89.7333,31.1833],"type":"Point"}
}