{
  "id": 1026146,
  "type": "Feature",
  "properties": {
    "tgn:hierarchy":[
        "tgn:1026146",
        "tgn:7003027",
        "tgn:1000003",
        "tgn:1000062",
        "tgn:7029392"
    ],
    "tgn:id":1026146,
    "tgn:name":"Thalgau",
    "tgn:placetype":[
        "aat:300008347"
    ]
},
  "bbox": [],
  "geometry": {"coordinates":[13.25,47.8667],"type":"Point"}
}