{
  "id": 2561623,
  "type": "Feature",
  "properties": {
    "tgn:hierarchy":[
        "tgn:2561623",
        "tgn:1000001",
        "tgn:7012149",
        "tgn:2002057",
        "tgn:7007826",
        "tgn:7029392"
    ],
    "tgn:id":2561623,
    "tgn:name":"Oso Spring",
    "tgn:placetype":[
        "aat:300008697"
    ]
},
  "bbox": [],
  "geometry": {"coordinates":[-104.0333,29.4167],"type":"Point"}
}