{
  "id": 7220521,
  "type": "Feature",
  "properties": {
    "tgn:hierarchy":[
        "tgn:7220521",
        "tgn:7002715",
        "tgn:7002731",
        "tgn:1000003",
        "tgn:1000074",
        "tgn:7029392"
    ],
    "tgn:id":7220521,
    "tgn:name":"Vath\u00fdlakkos",
    "tgn:placetype":[
        "aat:300008347"
    ]
},
  "bbox": [],
  "geometry": {"coordinates":[22.701667,40.769444],"type":"Point"}
}