{
  "id": 2441292,
  "type": "Feature",
  "properties": {
    "tgn:hierarchy":[
        "tgn:2441292",
        "tgn:1000001",
        "tgn:7012149",
        "tgn:7007157",
        "tgn:2000189",
        "tgn:7029392"
    ],
    "tgn:id":2441292,
    "tgn:name":"Knownothing Lake",
    "tgn:placetype":[
        "aat:300008680"
    ]
},
  "bbox": [],
  "geometry": {"coordinates":[-123.3667,41.15],"type":"Point"}
}