{
  "id": 2137486,
  "type": "Feature",
  "properties": {
    "tgn:hierarchy":[
        "tgn:2137486",
        "tgn:1000001",
        "tgn:7012149",
        "tgn:1003042",
        "tgn:7007920",
        "tgn:7029392"
    ],
    "tgn:id":2137486,
    "tgn:name":"Arnesons Peak",
    "tgn:placetype":[
        "aat:300008798"
    ]
},
  "bbox": [],
  "geometry": {"coordinates":[-121.2833,46.7167],"type":"Point"}
}