{
  "id": 7217600,
  "type": "Feature",
  "properties": {
    "tgn:hierarchy":[
        "tgn:7217600",
        "tgn:7011161",
        "tgn:7002674",
        "tgn:1000003",
        "tgn:1000074",
        "tgn:7029392"
    ],
    "tgn:id":7217600,
    "tgn:name":"Tso\u00fampos",
    "tgn:placetype":[
        "aat:300008798"
    ]
},
  "bbox": [],
  "geometry": {"coordinates":[26.071389,38.438056],"type":"Point"}
}