{
  "id": 2243098,
  "type": "Feature",
  "properties": {
    "tgn:hierarchy":[
        "tgn:2243098",
        "tgn:1000001",
        "tgn:7012149",
        "tgn:1002598",
        "tgn:7007523",
        "tgn:7029392"
    ],
    "tgn:id":2243098,
    "tgn:name":"Clear Lake",
    "tgn:placetype":[
        "aat:300008680"
    ]
},
  "bbox": [],
  "geometry": {"coordinates":[-90.6833,38.9833],"type":"Point"}
}