{
  "id": 7296958,
  "type": "Feature",
  "properties": {
    "tgn:hierarchy":[
        "tgn:7296958",
        "tgn:7002849",
        "tgn:1000003",
        "tgn:7009604",
        "tgn:1000095",
        "tgn:7029392"
    ],
    "tgn:id":7296958,
    "tgn:name":"Triano",
    "tgn:placetype":[
        "aat:300008347"
    ]
},
  "bbox": [],
  "geometry": {"coordinates":[-3.067619,43.292959],"type":"Point"}
}