{
  "id": 7551414,
  "type": "Feature",
  "properties": {
    "tgn:hierarchy":[
        "tgn:7551414",
        "tgn:1000004",
        "tgn:7000198",
        "tgn:7016694",
        "tgn:7029392"
    ],
    "tgn:id":7551414,
    "tgn:name:en":"Bola",
    "tgn:placetype":[
        "aat:300008795"
    ]
},
  "bbox": [],
  "geometry": {"coordinates":[86.2625,21.263333],"type":"Point"}
}