{
  "id": 2756886,
  "type": "Feature",
  "properties": {
    "tgn:hierarchy":[
        "tgn:2756886",
        "tgn:1000001",
        "tgn:7012149",
        "tgn:2002340",
        "tgn:7007922",
        "tgn:7029392"
    ],
    "tgn:id":2756886,
    "tgn:name":"Welsh Valley",
    "tgn:placetype":[
        "aat:300008761"
    ]
},
  "bbox": [],
  "geometry": {"coordinates":[-90.7833,44.0167],"type":"Point"}
}