{
  "id": 7250134,
  "type": "Feature",
  "properties": {
    "tgn:hierarchy":[
        "tgn:7250134",
        "tgn:7003461",
        "tgn:1000003",
        "tgn:1000063",
        "tgn:7018236",
        "tgn:7029392"
    ],
    "tgn:id":7250134,
    "tgn:name":"Pannenwinning",
    "tgn:placetype":[
        "aat:300000206"
    ]
},
  "bbox": [],
  "geometry": {"coordinates":[5.266667,50.966667],"type":"Point"}
}