{
  "id": 1137387,
  "type": "Feature",
  "properties": {
    "tgn:hierarchy":[
        "tgn:1137387",
        "tgn:1000004",
        "tgn:1003424",
        "tgn:7018214",
        "tgn:7002435",
        "tgn:7029392"
    ],
    "tgn:id":1137387,
    "tgn:name":"Dubovka",
    "tgn:placetype":[
        "aat:300008347"
    ]
},
  "bbox": [],
  "geometry": {"coordinates":[41.4333,51.45],"type":"Point"}
}