{
  "id": 2442909,
  "type": "Feature",
  "properties": {
    "tgn:hierarchy":[
        "tgn:2442909",
        "tgn:1000001",
        "tgn:7012149",
        "tgn:1002440",
        "tgn:7007568",
        "tgn:7029392"
    ],
    "tgn:id":2442909,
    "tgn:name":"Kunjamuk Cave",
    "tgn:placetype":[
        "aat:300008746"
    ]
},
  "bbox": [],
  "geometry": {"coordinates":[-74.3167,43.5167],"type":"Point"}
}