<<<<<<< HEAD
{
  "id": 2409810,
  "type": "Feature",
  "properties": {
    "tgn:hierarchy":[
        "tgn:2409810",
        "tgn:1000001",
        "tgn:7012149",
        "tgn:1002514",
        "tgn:7007251",
        "tgn:7029392"
    ],
    "tgn:id":2409810,
    "tgn:name":"Illinois Central Reservoir",
    "tgn:placetype":[
        "aat:300006191"
    ]
},
  "bbox": [],
  "geometry": {"coordinates":[-88.7167,38.3],"type":"Point"}
}
=======
{"geometry":{"type":"Point","coordinates":[-88.716700,38.300000]},"type":"Feature","properties":{"hierarchy":["tgn:2409810","tgn:1000001","tgn:7012149","tgn:1002514","tgn:7007251","tgn:7029392"],"placetype":["aat:300006191"],"id":2409810,"name:xx":"Illinois Central Reservoir"}}
>>>>>>> 03f74aca74312dbeaf24d7e61306dd6a786dc3d0
