{
  "id": 2315816,
  "type": "Feature",
  "properties": {
    "tgn:hierarchy":[
        "tgn:2315816",
        "tgn:1000001",
        "tgn:7012149",
        "tgn:2001277",
        "tgn:7007524",
        "tgn:7029392"
    ],
    "tgn:id":2315816,
    "tgn:name":"Ellsworth, Mount",
    "tgn:placetype":[
        "aat:300008798"
    ]
},
  "bbox": [],
  "geometry": {"coordinates":[-113.3667,48.4333],"type":"Point"}
}