{
  "id": 7590898,
  "type": "Feature",
  "properties": {
    "tgn:hierarchy":[
        "tgn:7590898",
        "tgn:1000004",
        "tgn:7000198",
        "tgn:7000799",
        "tgn:7029392"
    ],
    "tgn:id":7590898,
    "tgn:name:en":"Kirp\u0101lpur",
    "tgn:placetype":[
        "aat:300008347"
    ]
},
  "bbox": [],
  "geometry": {"coordinates":[74.997741,32.555365],"type":"Point"}
}