{
  "id": 2659235,
  "type": "Feature",
  "properties": {
    "tgn:hierarchy":[
        "tgn:2659235",
        "tgn:1000001",
        "tgn:7012149",
        "tgn:2001665",
        "tgn:7007707",
        "tgn:7029392"
    ],
    "tgn:id":2659235,
    "tgn:name":"Shiggin Creek",
    "tgn:placetype":[
        "aat:300008706"
    ]
},
  "bbox": [],
  "geometry": {"coordinates":[-97.15,33.9667],"type":"Point"}
}