{
  "id": 2597992,
  "type": "Feature",
  "properties": {
    "tgn:hierarchy":[
        "tgn:2597992",
        "tgn:1000001",
        "tgn:7012149",
        "tgn:2001449",
        "tgn:7007566",
        "tgn:7029392"
    ],
    "tgn:id":2597992,
    "tgn:name":"Presa, Arroyo de la",
    "tgn:placetype":[
        "aat:300008699"
    ]
},
  "bbox": [],
  "geometry": {"coordinates":[-106.0833,36.1167],"type":"Point"}
}