{
  "id": 1062468,
  "type": "Feature",
  "properties": {
    "tgn:hierarchy":[
        "tgn:1062468",
        "tgn:7002807",
        "tgn:1000003",
        "tgn:7003837",
        "tgn:1000095",
        "tgn:7029392"
    ],
    "tgn:id":1062468,
    "tgn:name":"San Vicente de Alc\u00e1ntara",
    "tgn:placetype":[
        "aat:300008347"
    ]
},
  "bbox": [],
  "geometry": {"coordinates":[-7.133333,39.35],"type":"Point"}
}