{
  "id": 1015048,
  "type": "Feature",
  "properties": {
    "tgn:hierarchy":[
        "tgn:1015048",
        "tgn:7005685",
        "tgn:1000001",
        "tgn:7013154",
        "tgn:7029392"
    ],
    "tgn:id":1015048,
    "tgn:name":"Prince Albert",
    "tgn:placetype":[
        "aat:300008347"
    ]
},
  "bbox": [],
  "geometry": {"coordinates":[-78.9667,44.0833],"type":"Point"}
}