{
  "id": 7579618,
  "type": "Feature",
  "properties": {
    "tgn:hierarchy":[
        "tgn:7579618",
        "tgn:1000004",
        "tgn:7000198",
        "tgn:1001895",
        "tgn:7029392"
    ],
    "tgn:id":7579618,
    "tgn:name:en":"Sondo",
    "tgn:placetype":[
        "aat:300008347"
    ]
},
  "bbox": [],
  "geometry": {"coordinates":[79.333333,19.666667],"type":"Point"}
}