{
  "id": 2003364,
  "type": "Feature",
  "properties": {
    "tgn:hierarchy":[
        "tgn:2003364",
        "tgn:7002659",
        "tgn:1000001",
        "tgn:7012149",
        "tgn:2000021",
        "tgn:7029392"
    ],
    "tgn:id":2003364,
    "tgn:name":"Dyers Crossroads",
    "tgn:placetype":[
        "aat:300008347",
        "aat:300387210"
    ]
},
  "bbox": [],
  "geometry": {"coordinates":[-86.8167,34.2333],"type":"Point"}
}