{
  "id": 7485264,
  "type": "Feature",
  "properties": {
    "tgn:hierarchy":[
        "tgn:7485264",
        "tgn:1000004",
        "tgn:7492971",
        "tgn:1000141",
        "tgn:7029392"
    ],
    "tgn:id":7485264,
    "tgn:name":"Disanbasihao Qiao",
    "tgn:placetype":[
        "aat:300007836"
    ]
},
  "bbox": [],
  "geometry": {"coordinates":[120.697778,22.1625],"type":"Point"}
}