{
  "id": 2436638,
  "type": "Feature",
  "properties": {
    "tgn:hierarchy":[
        "tgn:2436638",
        "tgn:1000001",
        "tgn:7006451",
        "tgn:2000094",
        "tgn:7012149",
        "tgn:7029392"
    ],
    "tgn:id":2436638,
    "tgn:name":"Kielberg Tank",
    "tgn:placetype":[
        "aat:300006191"
    ]
},
  "bbox": [],
  "geometry": {"coordinates":[-110.3333,32.5667],"type":"Point"}
}