<<<<<<< HEAD
{
  "id": 2252843,
  "type": "Feature",
  "properties": {
    "tgn:hierarchy":[
        "tgn:2252843",
        "tgn:1000001",
        "tgn:2000202",
        "tgn:7012149",
        "tgn:7007158",
        "tgn:7029392"
    ],
    "tgn:id":2252843,
    "tgn:name":"Conoboy Canyon",
    "tgn:placetype":[
        "aat:300008761"
    ]
},
  "bbox": [],
  "geometry": {"coordinates":[-106.2167,37.05],"type":"Point"}
}
=======
{"geometry":{"type":"Point","coordinates":[-106.216700,37.050000]},"type":"Feature","properties":{"hierarchy":["tgn:2252843","tgn:1000001","tgn:2000202","tgn:7012149","tgn:7007158","tgn:7029392"],"placetype":["aat:300008761"],"id":2252843,"name:xx":"Conoboy Canyon"}}
>>>>>>> 03f74aca74312dbeaf24d7e61306dd6a786dc3d0
