{
  "id": 1008397,
  "type": "Feature",
  "properties": {
    "tgn:hierarchy":[
        "tgn:1008397",
        "tgn:7006247",
        "tgn:1000047",
        "tgn:7002456",
        "tgn:1000002",
        "tgn:7029392"
    ],
    "tgn:id":1008397,
    "tgn:name":"Nova, Ilha",
    "tgn:placetype":[
        "aat:300008791"
    ]
},
  "bbox": [],
  "geometry": {"coordinates":[-49.6667,0.3333],"type":"Point"}
}