{
  "id": 7280099,
  "type": "Feature",
  "properties": {
    "tgn:hierarchy":[
        "tgn:7280099",
        "tgn:1001705",
        "tgn:1000049",
        "tgn:1000002",
        "tgn:7029392"
    ],
    "tgn:id":7280099,
    "tgn:name":"Retiro",
    "tgn:placetype":[
        "aat:300008347"
    ]
},
  "bbox": [],
  "geometry": {"coordinates":[-71.766667,-36.05],"type":"Point"}
}