{
  "id": 2702050,
  "type": "Feature",
  "properties": {
    "tgn:hierarchy":[
        "tgn:2702050",
        "tgn:1000001",
        "tgn:7012149",
        "tgn:2002272",
        "tgn:7013961",
        "tgn:7029392"
    ],
    "tgn:id":2702050,
    "tgn:name":"Sugartree Fork",
    "tgn:placetype":[
        "aat:300008699"
    ]
},
  "bbox": [],
  "geometry": {"coordinates":[-81.9333,38.1833],"type":"Point"}
}