{
  "id": 7094927,
  "type": "Feature",
  "properties": {
    "tgn:hierarchy":[
        "tgn:7094927",
        "tgn:7003692",
        "tgn:1000003",
        "tgn:7000084",
        "tgn:7029392"
    ],
    "tgn:id":7094927,
    "tgn:name":"Sch\u00f6nenberg",
    "tgn:placetype":[
        "aat:300008347"
    ]
},
  "bbox": [],
  "geometry": {"coordinates":[9.758889,49.168889],"type":"Point"}
}