<<<<<<< HEAD
{
  "id": 2157097,
  "type": "Feature",
  "properties": {
    "tgn:hierarchy":[
        "tgn:2157097",
        "tgn:1000001",
        "tgn:2001424",
        "tgn:7012149",
        "tgn:7007564",
        "tgn:7029392"
    ],
    "tgn:id":2157097,
    "tgn:name":"Beaver Brook",
    "tgn:placetype":[
        "aat:300008699"
    ]
},
  "bbox": [],
  "geometry": {"coordinates":[-71.7,43.9833],"type":"Point"}
}
=======
{"geometry":{"type":"Point","coordinates":[-71.700000,43.983300]},"type":"Feature","properties":{"hierarchy":["tgn:2157097","tgn:1000001","tgn:2001424","tgn:7012149","tgn:7007564","tgn:7029392"],"placetype":["aat:300008699"],"id":2157097,"name:xx":"Beaver Brook"}}
>>>>>>> 03f74aca74312dbeaf24d7e61306dd6a786dc3d0
