{
  "id": 7280061,
  "type": "Feature",
  "properties": {
    "tgn:hierarchy":[
        "tgn:7280061",
        "tgn:7002464",
        "tgn:1000049",
        "tgn:1000002",
        "tgn:7029392"
    ],
    "tgn:id":7280061,
    "tgn:name":"Rabo de Ballena, Punta",
    "tgn:placetype":[
        "aat:300386846"
    ]
},
  "bbox": [],
  "geometry": {"coordinates":[-70.15,-19.866667],"type":"Point"}
}