{
  "id": 7136718,
  "type": "Feature",
  "properties": {
    "tgn:hierarchy":[
        "tgn:7136718",
        "tgn:1000003",
        "tgn:7003689",
        "tgn:7000084",
        "tgn:7029392"
    ],
    "tgn:id":7136718,
    "tgn:name":"Laub-Berg",
    "tgn:placetype":[
        "aat:300008777"
    ]
},
  "bbox": [],
  "geometry": {"coordinates":[10.683333,50.45],"type":"Point"}
}