{
  "id": 7320973,
  "type": "Feature",
  "properties": {
    "tgn:hierarchy":[
        "tgn:7320973",
        "tgn:1001768",
        "tgn:1000049",
        "tgn:1000002",
        "tgn:7029392"
    ],
    "tgn:id":7320973,
    "tgn:name":"Campiche Bajo",
    "tgn:placetype":[
        "aat:300387200"
    ]
},
  "bbox": [],
  "geometry": {"coordinates":[-71.466667,-32.716667],"type":"Point"}
}