{
  "id": 7544143,
  "type": "Feature",
  "properties": {
    "tgn:hierarchy":[
        "tgn:7544143",
        "tgn:7001242",
        "tgn:1001075",
        "tgn:7016833",
        "tgn:7029392"
    ],
    "tgn:id":7544143,
    "tgn:name:en":"Mad\u012bnat W\u0101d\u012b an Na\u0163r\u016bn",
    "tgn:placetype":[
        "aat:300008347"
    ]
},
  "bbox": [],
  "geometry": {"coordinates":[30.348785,30.386422],"type":"Point"}
}