{
  "id": 7206794,
  "type": "Feature",
  "properties": {
    "tgn:hierarchy":[
        "tgn:7206794",
        "tgn:7003669",
        "tgn:1000003",
        "tgn:7000084",
        "tgn:7029392"
    ],
    "tgn:id":7206794,
    "tgn:name":"Dachsberg",
    "tgn:placetype":[
        "aat:300008777"
    ]
},
  "bbox": [],
  "geometry": {"coordinates":[10.85,50.166667],"type":"Point"}
}