{
  "id": 2204445,
  "type": "Feature",
  "properties": {
    "tgn:hierarchy":[
        "tgn:2204445",
        "tgn:1000001",
        "tgn:7012149",
        "tgn:7007705",
        "tgn:7029392"
    ],
    "tgn:id":2204445,
    "tgn:name":"Buffalo Creek",
    "tgn:placetype":[
        "aat:300008706"
    ]
},
  "bbox": [],
  "geometry": {"coordinates":[-102.1833,46.55],"type":"Point"}
}