{
  "id": 2337183,
  "type": "Feature",
  "properties": {
    "tgn:hierarchy":[
        "tgn:2337183",
        "tgn:7002659",
        "tgn:1000001",
        "tgn:7012149",
        "tgn:2000059",
        "tgn:7029392"
    ],
    "tgn:id":2337183,
    "tgn:name":"Fourth Creek",
    "tgn:placetype":[
        "aat:300008706"
    ]
},
  "bbox": [],
  "geometry": {"coordinates":[-88.25,32.4167],"type":"Point"}
}