{
  "id": 7217597,
  "type": "Feature",
  "properties": {
    "tgn:hierarchy":[
        "tgn:7217597",
        "tgn:7011161",
        "tgn:7002674",
        "tgn:1000003",
        "tgn:1000074",
        "tgn:7029392"
    ],
    "tgn:id":7217597,
    "tgn:name":"Meligk\u00e1s",
    "tgn:placetype":[
        "aat:300008777"
    ]
},
  "bbox": [],
  "geometry": {"coordinates":[26.148056,38.453056],"type":"Point"}
}