{
  "id": 2341419,
  "type": "Feature",
  "properties": {
    "tgn:hierarchy":[
        "tgn:2341419",
        "tgn:1000001",
        "tgn:7012149",
        "tgn:1002392",
        "tgn:7007157",
        "tgn:7029392"
    ],
    "tgn:id":2341419,
    "tgn:name":"Frog Lake",
    "tgn:placetype":[
        "aat:300008680"
    ]
},
  "bbox": [],
  "geometry": {"coordinates":[-118.8167,37.4167],"type":"Point"}
}