{
  "id": 2653103,
  "type": "Feature",
  "properties": {
    "tgn:hierarchy":[
        "tgn:2653103",
        "tgn:1000001",
        "tgn:7012149",
        "tgn:7029392"
    ],
    "tgn:id":2653103,
    "tgn:name":"Seven Lakes Mountain",
    "tgn:placetype":[
        "aat:300008798"
    ]
},
  "bbox": [],
  "geometry": {"coordinates":[-119.95,39.9167],"type":"Point"}
}