{
  "id": 7469461,
  "type": "Feature",
  "properties": {
    "tgn:hierarchy":[
        "tgn:7469461",
        "tgn:7468018",
        "tgn:1000004",
        "tgn:1000141",
        "tgn:7029392"
    ],
    "tgn:id":7469461,
    "tgn:name":"Fushou Cun",
    "tgn:placetype":[
        "aat:300387173"
    ]
},
  "bbox": [],
  "geometry": {"coordinates":[120.483889,23.443889],"type":"Point"}
}