<<<<<<< HEAD
{
  "id": 7248877,
  "type": "Feature",
  "properties": {
    "tgn:hierarchy":[
        "tgn:7248877",
        "tgn:7007877",
        "tgn:1000003",
        "tgn:1000063",
        "tgn:4012014",
        "tgn:7029392"
    ],
    "tgn:id":7248877,
    "tgn:name":"Bois des Ma\u00eetres",
    "tgn:placetype":[
        "aat:300008347"
    ]
},
  "bbox": [],
  "geometry": {"coordinates":[4.266667,50.466667],"type":"Point"}
}
=======
{"geometry":{"type":"Point","coordinates":[4.266667,50.466667]},"type":"Feature","properties":{"hierarchy":["tgn:7248877","tgn:7007877","tgn:1000003","tgn:1000063","tgn:4012014","tgn:7029392"],"placetype":["aat:300008347"],"id":7248877,"name:xx":"Bois des Ma\u00eetres"}}
>>>>>>> 03f74aca74312dbeaf24d7e61306dd6a786dc3d0
