{
  "id": 2148345,
  "type": "Feature",
  "properties": {
    "tgn:hierarchy":[
        "tgn:2148345",
        "tgn:1000001",
        "tgn:7012149",
        "tgn:2001861",
        "tgn:7007825",
        "tgn:7029392"
    ],
    "tgn:id":2148345,
    "tgn:name":"Barn Creek",
    "tgn:placetype":[
        "aat:300008706"
    ]
},
  "bbox": [],
  "geometry": {"coordinates":[-84.85,36.35],"type":"Point"}
}