{
  "id": 2578008,
  "type": "Feature",
  "properties": {
    "tgn:hierarchy":[
        "tgn:2578008",
        "tgn:2001171",
        "tgn:1000001",
        "tgn:7012149",
        "tgn:7007523",
        "tgn:7029392"
    ],
    "tgn:id":2578008,
    "tgn:name":"Pettis Creek",
    "tgn:placetype":[
        "aat:300008706"
    ]
},
  "bbox": [],
  "geometry": {"coordinates":[-94.1167,37.3833],"type":"Point"}
}