{
  "id": 1057769,
  "type": "Feature",
  "properties": {
    "tgn:hierarchy":[
        "tgn:1057769",
        "tgn:1000004",
        "tgn:1003421",
        "tgn:7018214",
        "tgn:7002435",
        "tgn:7029392"
    ],
    "tgn:id":1057769,
    "tgn:name":"Novoselovo",
    "tgn:placetype":[
        "aat:300008347"
    ]
},
  "bbox": [],
  "geometry": {"coordinates":[39.0667,56.0667],"type":"Point"}
}