{
  "id": 2671463,
  "type": "Feature",
  "properties": {
    "tgn:hierarchy":[
        "tgn:2671463",
        "tgn:1000001",
        "tgn:7012149",
        "tgn:1002782",
        "tgn:7007710",
        "tgn:7029392"
    ],
    "tgn:id":2671463,
    "tgn:name":"Smith Island",
    "tgn:placetype":[
        "aat:300386851",
        "aat:300008791"
    ]
},
  "bbox": [],
  "geometry": {"coordinates":[-75.1333,39.9333],"type":"Point"}
}