{
  "id": 2462452,
  "type": "Feature",
  "properties": {
    "tgn:hierarchy":[
        "tgn:2462452",
        "tgn:1000001",
        "tgn:7012149",
        "tgn:7007248",
        "tgn:7029392"
    ],
    "tgn:id":2462452,
    "tgn:name":"Little White Oak Creek",
    "tgn:placetype":[
        "aat:300008706"
    ]
},
  "bbox": [],
  "geometry": {"coordinates":[-84.6333,33.2667],"type":"Point"}
}