{
  "id": 7004880,
  "type": "Feature",
  "properties": {
    "tgn:hierarchy":[
        "tgn:7004880",
        "tgn:7000895",
        "tgn:1000004",
        "tgn:1001010",
        "tgn:1000120",
        "tgn:7029392"
    ],
    "tgn:id":7004880,
    "tgn:name":"Nagano",
    "tgn:placetype":[
        "aat:300008347",
        "aat:300008389",
        "aat:300387512",
        "aat:300387220"
    ]
},
  "bbox": [],
  "geometry": {"coordinates":[138.1667,36.65],"type":"Point"}
}