{
  "id": 1078032,
  "type": "Feature",
  "properties": {
    "tgn:hierarchy":[
        "tgn:1078032",
        "tgn:1009368",
        "tgn:1000004",
        "tgn:1009876",
        "tgn:1001555",
        "tgn:1000116",
        "tgn:7029392"
    ],
    "tgn:id":1078032,
    "tgn:name":"Luaha-sibuha",
    "tgn:placetype":[
        "aat:300008347"
    ]
},
  "bbox": [],
  "geometry": {"coordinates":[98.4667,-0.5167],"type":"Point"}
}