<<<<<<< HEAD
{
  "id": 7473266,
  "type": "Feature",
  "properties": {
    "tgn:hierarchy":[
        "tgn:7473266",
        "tgn:7488858",
        "tgn:1000004",
        "tgn:1000141",
        "tgn:7029392"
    ],
    "tgn:id":7473266,
    "tgn:name":"Dianziqian",
    "tgn:placetype":[
        "aat:300008347"
    ]
},
  "bbox": [],
  "geometry": {"coordinates":[120.717193,23.807113],"type":"Point"}
}
=======
{"geometry":{"type":"Point","coordinates":[120.717193,23.807113]},"type":"Feature","properties":{"hierarchy":["tgn:7473266","tgn:7488858","tgn:1000004","tgn:1000141","tgn:7029392"],"placetype":["aat:300008347"],"id":7473266,"name:xx":"Dianziqian"}}
>>>>>>> 03f74aca74312dbeaf24d7e61306dd6a786dc3d0
