{
  "id": 7515871,
  "type": "Feature",
  "properties": {
    "tgn:hierarchy":[
        "tgn:7515871",
        "tgn:1009227",
        "tgn:1000226",
        "tgn:7016822",
        "tgn:1000006",
        "tgn:7029392"
    ],
    "tgn:id":7515871,
    "tgn:name:en":"Lincoln Hill",
    "tgn:placetype":[
        "aat:300008795"
    ]
},
  "bbox": [],
  "geometry": {"coordinates":[168.166667,-45.416667],"type":"Point"}
}