{
  "id": 2523854,
  "type": "Feature",
  "properties": {
    "tgn:hierarchy":[
        "tgn:2523854",
        "tgn:1000001",
        "tgn:1002278",
        "tgn:7012149",
        "tgn:7007710",
        "tgn:7029392"
    ],
    "tgn:id":2523854,
    "tgn:name":"Moravian Run",
    "tgn:placetype":[
        "aat:300008699"
    ]
},
  "bbox": [],
  "geometry": {"coordinates":[-78.2667,40.9667],"type":"Point"}
}