{
  "id": 2646669,
  "type": "Feature",
  "properties": {
    "tgn:hierarchy":[
        "tgn:2646669",
        "tgn:1000001",
        "tgn:7012149",
        "tgn:2001911",
        "tgn:7007825",
        "tgn:7029392"
    ],
    "tgn:id":2646669,
    "tgn:name":"Scales Mountain",
    "tgn:placetype":[
        "aat:300008798"
    ]
},
  "bbox": [],
  "geometry": {"coordinates":[-86.5667,35.8333],"type":"Point"}
}