{
  "id": 7534008,
  "type": "Feature",
  "properties": {
    "tgn:hierarchy":[
        "tgn:7534008",
        "tgn:7001242",
        "tgn:7016833",
        "tgn:1001418",
        "tgn:7029392"
    ],
    "tgn:id":7534008,
    "tgn:name:en":"\u1e28arrah, Dayr al",
    "tgn:placetype":[
        "aat:300386860"
    ]
},
  "bbox": [],
  "geometry": {"coordinates":[28.589757,30.700166],"type":"Point"}
}