{
  "id": 2077844,
  "type": "Feature",
  "properties": {
    "tgn:hierarchy":[
        "tgn:2077844",
        "tgn:1000001",
        "tgn:2001588",
        "tgn:7012149",
        "tgn:7007705",
        "tgn:7029392"
    ],
    "tgn:id":2077844,
    "tgn:name":"Michigan",
    "tgn:placetype":[
        "aat:300008347"
    ]
},
  "bbox": [],
  "geometry": {"coordinates":[-98.1167,48.0167],"type":"Point"}
}