{
  "id": 7234152,
  "type": "Feature",
  "properties": {
    "tgn:hierarchy":[
        "tgn:7234152",
        "tgn:7002739",
        "tgn:7017076",
        "tgn:1000003",
        "tgn:1000074",
        "tgn:7029392"
    ],
    "tgn:id":7234152,
    "tgn:name":"Dh\u00e9ndra",
    "tgn:placetype":[
        "aat:300008347"
    ]
},
  "bbox": [],
  "geometry": {"coordinates":[22.833333,37.65],"type":"Point"}
}