{
  "id": 1093202,
  "type": "Feature",
  "properties": {
    "tgn:hierarchy":[
        "tgn:1093202",
        "tgn:7001242",
        "tgn:7017584",
        "tgn:1000193",
        "tgn:7029392"
    ],
    "tgn:id":1093202,
    "tgn:name":"Jonkersberg",
    "tgn:placetype":[
        "aat:300008347"
    ]
},
  "bbox": [],
  "geometry": {"coordinates":[22.2167,-33.9167],"type":"Point"}
}