{
  "id": 7267932,
  "type": "Feature",
  "properties": {
    "tgn:hierarchy":[
        "tgn:7267932",
        "tgn:7003616",
        "tgn:1000003",
        "tgn:7016845",
        "tgn:7029392"
    ],
    "tgn:id":7267932,
    "tgn:name:nl":"Nijemirdumerheide",
    "tgn:placetype":[
        "aat:300008187"
    ]
},
  "bbox": [],
  "geometry": {"coordinates":[5.55,52.866667],"type":"Point"}
}