{
  "id": 1068308,
  "type": "Feature",
  "properties": {
    "tgn:hierarchy":[
        "tgn:1068308",
        "tgn:1000004",
        "tgn:7002078",
        "tgn:1000111",
        "tgn:7029392"
    ],
    "tgn:id":1068308,
    "tgn:name":"Gong'an",
    "tgn:placetype":[
        "aat:300008347"
    ]
},
  "bbox": [],
  "geometry": {"coordinates":[112.1667,30.0333],"type":"Point"}
}