{
  "id": 2273411,
  "type": "Feature",
  "properties": {
    "tgn:hierarchy":[
        "tgn:2273411",
        "tgn:1000001",
        "tgn:7012149",
        "tgn:2000290",
        "tgn:7007240",
        "tgn:7029392"
    ],
    "tgn:id":2273411,
    "tgn:name":"Cypress Drains",
    "tgn:placetype":[
        "aat:300008905"
    ]
},
  "bbox": [],
  "geometry": {"coordinates":[-86.1833,30.8667],"type":"Point"}
}