{
  "id": 7564215,
  "type": "Feature",
  "properties": {
    "tgn:hierarchy":[
        "tgn:7564215",
        "tgn:1000004",
        "tgn:7000198",
        "tgn:7016722",
        "tgn:7029392"
    ],
    "tgn:id":7564215,
    "tgn:name:en":"Purwa Kurin",
    "tgn:placetype":[
        "aat:300008347"
    ]
},
  "bbox": [],
  "geometry": {"coordinates":[79.913799,26.520082],"type":"Point"}
}