{
  "id": 7046869,
  "type": "Feature",
  "properties": {
    "tgn:hierarchy":[
        "tgn:7046869",
        "tgn:7003127",
        "tgn:1000003",
        "tgn:7008516",
        "tgn:1000080",
        "tgn:7029392"
    ],
    "tgn:id":7046869,
    "tgn:name":"Case di Ribano",
    "tgn:placetype":[
        "aat:300008347"
    ]
},
  "bbox": [],
  "geometry": {"coordinates":[11.483333,44.383333],"type":"Point"}
}