{
  "id": 7395301,
  "type": "Feature",
  "properties": {
    "tgn:hierarchy":[
        "tgn:7395301",
        "tgn:1000001",
        "tgn:7005595",
        "tgn:7005560",
        "tgn:7029392"
    ],
    "tgn:id":7395301,
    "tgn:name":"Rancho San Jos\u00e9 de los Pericos",
    "tgn:placetype":[
        "aat:300000241"
    ]
},
  "bbox": [],
  "geometry": {"coordinates":[-108.278611,26.3875],"type":"Point"}
}