{
  "id": 2465171,
  "type": "Feature",
  "properties": {
    "tgn:hierarchy":[
        "tgn:2465171",
        "tgn:1000001",
        "tgn:7012149",
        "tgn:2000227",
        "tgn:7007158",
        "tgn:7029392"
    ],
    "tgn:id":2465171,
    "tgn:name":"Loma de los Conejos",
    "tgn:placetype":[
        "aat:300266640"
    ]
},
  "bbox": [],
  "geometry": {"coordinates":[-104.35,37.0833],"type":"Point"}
}