{
  "id": 2044853,
  "type": "Feature",
  "properties": {
    "tgn:hierarchy":[
        "tgn:2044853",
        "tgn:1000001",
        "tgn:7012149",
        "tgn:7014589",
        "tgn:7007515",
        "tgn:7029392"
    ],
    "tgn:id":2044853,
    "tgn:name":"Forest City",
    "tgn:placetype":[
        "aat:300008347"
    ]
},
  "bbox": [],
  "geometry": {"coordinates":[-67.7167,45.65],"type":"Point"}
}