{
  "id": 7220986,
  "type": "Feature",
  "properties": {
    "tgn:hierarchy":[
        "tgn:7220986",
        "tgn:7011164",
        "tgn:7002674",
        "tgn:1000003",
        "tgn:1000074",
        "tgn:7029392"
    ],
    "tgn:id":7220986,
    "tgn:name":"Bourni\u00e1s",
    "tgn:placetype":[
        "aat:300008798"
    ]
},
  "bbox": [],
  "geometry": {"coordinates":[26.808889,37.66],"type":"Point"}
}