{
  "id": 2684632,
  "type": "Feature",
  "properties": {
    "tgn:hierarchy":[
        "tgn:2684632",
        "tgn:1000001",
        "tgn:7012149",
        "tgn:7007157",
        "tgn:1002621",
        "tgn:7029392"
    ],
    "tgn:id":2684632,
    "tgn:name":"Spinecup Ridge",
    "tgn:placetype":[
        "aat:300266640"
    ]
},
  "bbox": [],
  "geometry": {"coordinates":[-119.8667,37.2167],"type":"Point"}
}