<<<<<<< HEAD
{
  "id": 2254627,
  "type": "Feature",
  "properties": {
    "tgn:hierarchy":[
        "tgn:2254627",
        "tgn:7006450",
        "tgn:1000001",
        "tgn:2124076",
        "tgn:7012149",
        "tgn:7029392"
    ],
    "tgn:id":2254627,
    "tgn:name":"Coon Island",
    "tgn:placetype":[
        "aat:300008791"
    ]
},
  "bbox": [],
  "geometry": {"coordinates":[-131.5,55.45],"type":"Point"}
}
=======
{"geometry":{"type":"Point","coordinates":[-131.500000,55.450000]},"type":"Feature","properties":{"hierarchy":["tgn:2254627","tgn:7006450","tgn:1000001","tgn:2124076","tgn:7012149","tgn:7029392"],"placetype":["aat:300008791"],"id":2254627,"name:xx":"Coon Island"}}
>>>>>>> 03f74aca74312dbeaf24d7e61306dd6a786dc3d0
