{
  "id": 2411072,
  "type": "Feature",
  "properties": {
    "tgn:hierarchy":[
        "tgn:2411072",
        "tgn:1000001",
        "tgn:7012149",
        "tgn:2002340",
        "tgn:7007922",
        "tgn:7029392"
    ],
    "tgn:id":2411072,
    "tgn:name":"Indian Creek",
    "tgn:placetype":[
        "aat:300008706"
    ]
},
  "bbox": [],
  "geometry": {"coordinates":[-90.4167,43.9167],"type":"Point"}
}