{
  "id": 2134635,
  "type": "Feature",
  "properties": {
    "tgn:hierarchy":[
        "tgn:2134635",
        "tgn:1000001",
        "tgn:2001786",
        "tgn:7012149",
        "tgn:7007713",
        "tgn:7029392"
    ],
    "tgn:id":2134635,
    "tgn:name":"Antelope Canyon",
    "tgn:placetype":[
        "aat:300008761"
    ]
},
  "bbox": [],
  "geometry": {"coordinates":[-103.5333,43.5667],"type":"Point"}
}