{
  "id": 1076855,
  "type": "Feature",
  "properties": {
    "tgn:hierarchy":[
        "tgn:1076855",
        "tgn:1000004",
        "tgn:7000198",
        "tgn:1001977",
        "tgn:7029392"
    ],
    "tgn:id":1076855,
    "tgn:name":"Sam\u016bdragarh",
    "tgn:placetype":[
        "aat:300008347"
    ]
},
  "bbox": [],
  "geometry": {"coordinates":[88.3333,23.35],"type":"Point"}
}