{
  "id": 7487193,
  "type": "Feature",
  "properties": {
    "tgn:hierarchy":[
        "tgn:7487193",
        "tgn:7001004",
        "tgn:1000004",
        "tgn:1000141",
        "tgn:7029392"
    ],
    "tgn:id":7487193,
    "tgn:name":"Gaoxiong Chezhan",
    "tgn:placetype":[
        "aat:300007783"
    ]
},
  "bbox": [],
  "geometry": {"coordinates":[120.303664,22.639811],"type":"Point"}
}