{
  "id": 7440188,
  "type": "Feature",
  "properties": {
    "tgn:hierarchy":[
        "tgn:7440188",
        "tgn:1000001",
        "tgn:1001893",
        "tgn:7005560",
        "tgn:7029392"
    ],
    "tgn:id":7440188,
    "tgn:name":"San Marcos",
    "tgn:placetype":[
        "aat:300008347"
    ]
},
  "bbox": [],
  "geometry": {"coordinates":[-100.266667,18.716667],"type":"Point"}
}