{
  "id": 7564917,
  "type": "Feature",
  "properties": {
    "tgn:hierarchy":[
        "tgn:7564917",
        "tgn:1000004",
        "tgn:7000198",
        "tgn:1001894",
        "tgn:7029392"
    ],
    "tgn:id":7564917,
    "tgn:name:en":"Lahar Khurd Protected Forest",
    "tgn:placetype":[
        "aat:300008865"
    ]
},
  "bbox": [],
  "geometry": {"coordinates":[79.010613,24.891582],"type":"Point"}
}