{
  "id": 7546200,
  "type": "Feature",
  "properties": {
    "tgn:hierarchy":[
        "tgn:7546200",
        "tgn:1000004",
        "tgn:7000198",
        "tgn:1001996",
        "tgn:7029392"
    ],
    "tgn:id":7546200,
    "tgn:name:en":"Bajaura",
    "tgn:placetype":[
        "aat:300008347"
    ]
},
  "bbox": [],
  "geometry": {"coordinates":[77.145761,31.849919],"type":"Point"}
}