{
  "id": 2429482,
  "type": "Feature",
  "properties": {
    "tgn:hierarchy":[
        "tgn:2429482",
        "tgn:1000001",
        "tgn:7012149",
        "tgn:2000290",
        "tgn:7007240",
        "tgn:7029392"
    ],
    "tgn:id":2429482,
    "tgn:name":"Juniper Lake",
    "tgn:placetype":[
        "aat:300006191"
    ]
},
  "bbox": [],
  "geometry": {"coordinates":[-86.1167,30.75],"type":"Point"}
}