{
  "id": 7329430,
  "type": "Feature",
  "properties": {
    "tgn:hierarchy":[
        "tgn:7329430",
        "tgn:7002813",
        "tgn:7002758",
        "tgn:1000003",
        "tgn:1000095",
        "tgn:7029392"
    ],
    "tgn:id":7329430,
    "tgn:name":"Puerto Serrano",
    "tgn:placetype":[
        "aat:300008347"
    ]
},
  "bbox": [],
  "geometry": {"coordinates":[-5.55,36.933333],"type":"Point"}
}