{
  "id": 2181775,
  "type": "Feature",
  "properties": {
    "tgn:hierarchy":[
        "tgn:2181775",
        "tgn:2000453",
        "tgn:1000001",
        "tgn:7012149",
        "tgn:7007250",
        "tgn:7029392"
    ],
    "tgn:id":2181775,
    "tgn:name":"Blue Jay Gulch",
    "tgn:placetype":[
        "aat:300008761"
    ]
},
  "bbox": [],
  "geometry": {"coordinates":[-116.7333,44.8667],"type":"Point"}
}