{
  "id": 2687796,
  "type": "Feature",
  "properties": {
    "tgn:hierarchy":[
        "tgn:2687796",
        "tgn:1000001",
        "tgn:7012149",
        "tgn:7021516",
        "tgn:7007706",
        "tgn:7029392"
    ],
    "tgn:id":2687796,
    "tgn:name":"Spring Valley",
    "tgn:placetype":[
        "aat:300008347"
    ]
},
  "bbox": [],
  "geometry": {"coordinates":[-81.3333,41.35],"type":"Point"}
}