{
  "id": 2642965,
  "type": "Feature",
  "properties": {
    "tgn:hierarchy":[
        "tgn:2642965",
        "tgn:1000001",
        "tgn:7012149",
        "tgn:7007706",
        "tgn:7029392"
    ],
    "tgn:id":2642965,
    "tgn:name":"Sandsuck Hollow",
    "tgn:placetype":[
        "aat:300008761"
    ]
},
  "bbox": [],
  "geometry": {"coordinates":[-82.7167,39.1833],"type":"Point"}
}