{
  "id": 7503796,
  "type": "Feature",
  "properties": {
    "tgn:hierarchy":[
        "tgn:7503796",
        "tgn:1000004",
        "tgn:7491221",
        "tgn:1000141",
        "tgn:7029392"
    ],
    "tgn:id":7503796,
    "tgn:name":"Jian Shan",
    "tgn:placetype":[
        "aat:300008798"
    ]
},
  "bbox": [],
  "geometry": {"coordinates":[120.861389,22.634722],"type":"Point"}
}