{
  "id": 2569130,
  "type": "Feature",
  "properties": {
    "tgn:hierarchy":[
        "tgn:2569130",
        "tgn:1000001",
        "tgn:1002712",
        "tgn:7012149",
        "tgn:7007159",
        "tgn:7029392"
    ],
    "tgn:id":2569130,
    "tgn:name":"Parkers Pond",
    "tgn:placetype":[
        "aat:300008680"
    ]
},
  "bbox": [],
  "geometry": {"coordinates":[-73.05,41.3333],"type":"Point"}
}