{
  "id": 7234595,
  "type": "Feature",
  "properties": {
    "tgn:hierarchy":[
        "tgn:7234595",
        "tgn:7002743",
        "tgn:7017076",
        "tgn:1000003",
        "tgn:1000074",
        "tgn:7029392"
    ],
    "tgn:id":7234595,
    "tgn:name":"Agr\u00eddhion",
    "tgn:placetype":[
        "aat:300008347"
    ]
},
  "bbox": [],
  "geometry": {"coordinates":[21.516667,37.616667],"type":"Point"}
}