{
  "id": 7505999,
  "type": "Feature",
  "properties": {
    "tgn:hierarchy":[
        "tgn:7505999",
        "tgn:1009227",
        "tgn:1000226",
        "tgn:7016822",
        "tgn:1000006",
        "tgn:7029392"
    ],
    "tgn:id":7505999,
    "tgn:name:en":"Sharp Head",
    "tgn:placetype":[
        "aat:300008850"
    ]
},
  "bbox": [],
  "geometry": {"coordinates":[167.116667,-45.283333],"type":"Point"}
}