{
  "id": 7040600,
  "type": "Feature",
  "properties": {
    "tgn:hierarchy":[
        "tgn:7040600",
        "tgn:1003483",
        "tgn:1000003",
        "tgn:7003240",
        "tgn:1000080",
        "tgn:7029392"
    ],
    "tgn:id":7040600,
    "tgn:name":"San Sisto",
    "tgn:placetype":[
        "aat:300008347"
    ]
},
  "bbox": [],
  "geometry": {"coordinates":[12.35,43.75],"type":"Point"}
}