{
  "id": 2559773,
  "type": "Feature",
  "properties": {
    "tgn:hierarchy":[
        "tgn:2559773",
        "tgn:2000258",
        "tgn:1000001",
        "tgn:7012149",
        "tgn:7007240",
        "tgn:7029392"
    ],
    "tgn:id":2559773,
    "tgn:name":"Open Pond",
    "tgn:placetype":[
        "aat:300008680"
    ]
},
  "bbox": [],
  "geometry": {"coordinates":[-85.4667,30.3833],"type":"Point"}
}