{
  "id": 1107272,
  "type": "Feature",
  "properties": {
    "tgn:hierarchy":[
        "tgn:1107272",
        "tgn:1000001",
        "tgn:7012149",
        "tgn:1003042",
        "tgn:7007920",
        "tgn:7029392"
    ],
    "tgn:id":1107272,
    "tgn:name":"Goat Peak",
    "tgn:placetype":[
        "aat:300008798"
    ]
},
  "bbox": [],
  "geometry": {"coordinates":[-121.25,46.9333],"type":"Point"}
}