{
  "id": 1124419,
  "type": "Feature",
  "properties": {
    "tgn:hierarchy":[
        "tgn:1124419",
        "tgn:1001835",
        "tgn:1000001",
        "tgn:7005560",
        "tgn:7029392"
    ],
    "tgn:id":1124419,
    "tgn:name":"Guadalupe",
    "tgn:placetype":[
        "aat:300008707",
        "aat:300008699"
    ]
},
  "bbox": [],
  "geometry": {"coordinates":[-116.884167,32.088611],"type":"Point"}
}