{
  "id": 7463168,
  "type": "Feature",
  "properties": {
    "tgn:hierarchy":[
        "tgn:7463168",
        "tgn:7002444",
        "tgn:1000003",
        "tgn:7029508",
        "tgn:7008591",
        "tgn:7029392"
    ],
    "tgn:id":7463168,
    "tgn:name:en":"Loose Head",
    "tgn:placetype":[
        "aat:300386846"
    ]
},
  "bbox": [],
  "geometry": {"coordinates":[-1.35,59.983333],"type":"Point"}
}