<<<<<<< HEAD
{
  "id": 7353975,
  "type": "Feature",
  "properties": {
    "tgn:hierarchy":[
        "tgn:7353975",
        "tgn:7005586",
        "tgn:1000001",
        "tgn:7005560",
        "tgn:7029392"
    ],
    "tgn:id":7353975,
    "tgn:name":"Casablanca",
    "tgn:placetype":[
        "aat:300008347"
    ]
},
  "bbox": [],
  "geometry": {"coordinates":[-103.033333,20.4],"type":"Point"}
}
=======
{"geometry":{"type":"Point","coordinates":[-103.033333,20.400000]},"type":"Feature","properties":{"hierarchy":["tgn:7353975","tgn:7005586","tgn:1000001","tgn:7005560","tgn:7029392"],"placetype":["aat:300008347"],"id":7353975,"name:xx":"Casablanca"}}
>>>>>>> 03f74aca74312dbeaf24d7e61306dd6a786dc3d0
