{
  "id": 7540984,
  "type": "Feature",
  "properties": {
    "tgn:hierarchy":[
        "tgn:7540984",
        "tgn:7001242",
        "tgn:1001075",
        "tgn:7016833",
        "tgn:7029392"
    ],
    "tgn:id":7540984,
    "tgn:name:en":"Qaryat \u1e28ir\u0101'",
    "tgn:placetype":[
        "aat:300008347"
    ]
},
  "bbox": [],
  "geometry": {"coordinates":[30.680556,30.676111],"type":"Point"}
}