{
  "id": 7027866,
  "type": "Feature",
  "properties": {
    "tgn:hierarchy":[
        "tgn:7027866",
        "tgn:7002445",
        "tgn:1000003",
        "tgn:7019054",
        "tgn:7008591",
        "tgn:7029392"
    ],
    "tgn:id":7027866,
    "tgn:name:en":"Flixborough",
    "tgn:placetype":[
        "aat:300008347",
        "aat:300008372"
    ]
},
  "bbox": [],
  "geometry": {"coordinates":[-0.683333,53.616667],"type":"Point"}
}