{
  "id": 2603392,
  "type": "Feature",
  "properties": {
    "tgn:hierarchy":[
        "tgn:2603392",
        "tgn:1000001",
        "tgn:2002368",
        "tgn:7012149",
        "tgn:7007923",
        "tgn:7029392"
    ],
    "tgn:id":2603392,
    "tgn:name":"Quealy Lake",
    "tgn:placetype":[
        "aat:300008680"
    ]
},
  "bbox": [],
  "geometry": {"coordinates":[-106.3333,41.3833],"type":"Point"}
}