{
  "id": 1103847,
  "type": "Feature",
  "properties": {
    "tgn:hierarchy":[
        "tgn:1103847",
        "tgn:2002143",
        "tgn:1000001",
        "tgn:7012149",
        "tgn:7007919",
        "tgn:7029392"
    ],
    "tgn:id":1103847,
    "tgn:name":"Bald Knob",
    "tgn:placetype":[
        "aat:300008795"
    ]
},
  "bbox": [],
  "geometry": {"coordinates":[-79.85,37.9167],"type":"Point"}
}