{
  "id": 2107303,
  "type": "Feature",
  "properties": {
    "tgn:hierarchy":[
        "tgn:2107303",
        "tgn:1000001",
        "tgn:7012149",
        "tgn:1002709",
        "tgn:7007826",
        "tgn:7029392"
    ],
    "tgn:id":2107303,
    "tgn:name":"Rural Shade",
    "tgn:placetype":[
        "aat:300008347"
    ]
},
  "bbox": [],
  "geometry": {"coordinates":[-96.1333,32.05],"type":"Point"}
}