<<<<<<< HEAD
{
  "id": 2332400,
  "type": "Feature",
  "properties": {
    "tgn:hierarchy":[
        "tgn:2332400",
        "tgn:1000001",
        "tgn:7012149",
        "tgn:2001711",
        "tgn:7007708",
        "tgn:7029392"
    ],
    "tgn:id":2332400,
    "tgn:name":"Floras Creek",
    "tgn:placetype":[
        "aat:300008706"
    ]
},
  "bbox": [],
  "geometry": {"coordinates":[-122.5333,42.65],"type":"Point"}
}
=======
{"geometry":{"type":"Point","coordinates":[-122.533300,42.650000]},"type":"Feature","properties":{"hierarchy":["tgn:2332400","tgn:1000001","tgn:7012149","tgn:2001711","tgn:7007708","tgn:7029392"],"placetype":["aat:300008706"],"id":2332400,"name:xx":"Floras Creek"}}
>>>>>>> 03f74aca74312dbeaf24d7e61306dd6a786dc3d0
