{
  "id": 2330796,
  "type": "Feature",
  "properties": {
    "tgn:hierarchy":[
        "tgn:2330796",
        "tgn:1000001",
        "tgn:7006451",
        "tgn:2000092",
        "tgn:7012149",
        "tgn:7029392"
    ],
    "tgn:id":2330796,
    "tgn:name":"Flat Mesa",
    "tgn:placetype":[
        "aat:300008798"
    ]
},
  "bbox": [],
  "geometry": {"coordinates":[-112.35,35.1833],"type":"Point"}
}