{
  "id": 2718834,
  "type": "Feature",
  "properties": {
    "tgn:hierarchy":[
        "tgn:2718834",
        "tgn:1000001",
        "tgn:7012149",
        "tgn:1002544",
        "tgn:7007255",
        "tgn:7029392"
    ],
    "tgn:id":2718834,
    "tgn:name":"Thorn Hill Lake",
    "tgn:placetype":[
        "aat:300006191"
    ]
},
  "bbox": [],
  "geometry": {"coordinates":[-84.45,38.85],"type":"Point"}
}