{
  "id": 2536506,
  "type": "Feature",
  "properties": {
    "tgn:hierarchy":[
        "tgn:2536506",
        "tgn:1000001",
        "tgn:1002210",
        "tgn:7012149",
        "tgn:7007706",
        "tgn:7029392"
    ],
    "tgn:id":2536506,
    "tgn:name":"Neals Corner",
    "tgn:placetype":[
        "aat:300008347"
    ]
},
  "bbox": [],
  "geometry": {"coordinates":[-83.9667,38.95],"type":"Point"}
}