{
  "id": 2507068,
  "type": "Feature",
  "properties": {
    "tgn:hierarchy":[
        "tgn:2507068",
        "tgn:1000001",
        "tgn:7012149",
        "tgn:7007157",
        "tgn:1002858",
        "tgn:7029392"
    ],
    "tgn:id":2507068,
    "tgn:name":"Metate Hill",
    "tgn:placetype":[
        "aat:300008798"
    ]
},
  "bbox": [],
  "geometry": {"coordinates":[-116.2833,33.2167],"type":"Point"}
}