{
  "id": 2590340,
  "type": "Feature",
  "properties": {
    "tgn:hierarchy":[
        "tgn:2590340",
        "tgn:7006450",
        "tgn:2000069",
        "tgn:1000001",
        "tgn:7012149",
        "tgn:7029392"
    ],
    "tgn:id":2590340,
    "tgn:name":"Polar Bear Creek",
    "tgn:placetype":[
        "aat:300008706"
    ]
},
  "bbox": [],
  "geometry": {"coordinates":[-159.95,60.1833],"type":"Point"}
}