{
  "id": 2133855,
  "type": "Feature",
  "properties": {
    "tgn:hierarchy":[
        "tgn:2133855",
        "tgn:1000001",
        "tgn:7006451",
        "tgn:7012149",
        "tgn:2000096",
        "tgn:7029392"
    ],
    "tgn:id":2133855,
    "tgn:name":"Angel Point",
    "tgn:placetype":[
        "aat:300008798"
    ]
},
  "bbox": [],
  "geometry": {"coordinates":[-114.3333,33.7667],"type":"Point"}
}