{
  "id": 7432421,
  "type": "Feature",
  "properties": {
    "tgn:hierarchy":[
        "tgn:7432421",
        "tgn:7005585",
        "tgn:1000001",
        "tgn:7005560",
        "tgn:7029392"
    ],
    "tgn:id":7432421,
    "tgn:name":"Tonalapa del R\u00edo",
    "tgn:placetype":[
        "aat:300008347"
    ]
},
  "bbox": [],
  "geometry": {"coordinates":[-99.683333,18.333333],"type":"Point"}
}