{
  "id": 7578469,
  "type": "Feature",
  "properties": {
    "tgn:hierarchy":[
        "tgn:7578469",
        "tgn:1000004",
        "tgn:7000198",
        "tgn:7016883",
        "tgn:7029392"
    ],
    "tgn:id":7578469,
    "tgn:name:en":"Talwan",
    "tgn:placetype":[
        "aat:300008347"
    ]
},
  "bbox": [],
  "geometry": {"coordinates":[75.609617,31.011157],"type":"Point"}
}