<<<<<<< HEAD
{
  "id": 2150402,
  "type": "Feature",
  "properties": {
    "tgn:hierarchy":[
        "tgn:2150402",
        "tgn:1000001",
        "tgn:2001704",
        "tgn:7012149",
        "tgn:7007708",
        "tgn:7029392"
    ],
    "tgn:id":2150402,
    "tgn:name":"Basin Creek",
    "tgn:placetype":[
        "aat:300008706"
    ]
},
  "bbox": [],
  "geometry": {"coordinates":[-124.1,42.15],"type":"Point"}
}
=======
{"geometry":{"type":"Point","coordinates":[-124.100000,42.150000]},"type":"Feature","properties":{"hierarchy":["tgn:2150402","tgn:1000001","tgn:2001704","tgn:7012149","tgn:7007708","tgn:7029392"],"placetype":["aat:300008706"],"id":2150402,"name:xx":"Basin Creek"}}
>>>>>>> 03f74aca74312dbeaf24d7e61306dd6a786dc3d0
