{
  "id": 7108531,
  "type": "Feature",
  "properties": {
    "tgn:hierarchy":[
        "tgn:7108531",
        "tgn:1000003",
        "tgn:7003678",
        "tgn:7000084",
        "tgn:7029392"
    ],
    "tgn:id":7108531,
    "tgn:name":"Rasen-Berg",
    "tgn:placetype":[
        "aat:300008777"
    ]
},
  "bbox": [],
  "geometry": {"coordinates":[8.233333,50.583333],"type":"Point"}
}