{
  "id": 2525375,
  "type": "Feature",
  "properties": {
    "tgn:hierarchy":[
        "tgn:2525375",
        "tgn:1000001",
        "tgn:7012149",
        "tgn:7007157",
        "tgn:2000189",
        "tgn:7029392"
    ],
    "tgn:id":2525375,
    "tgn:name":"Morrison-Carlock Mine",
    "tgn:placetype":[
        "aat:300000390"
    ]
},
  "bbox": [],
  "geometry": {"coordinates":[-122.95,41.5667],"type":"Point"}
}