{
  "id": 1051571,
  "type": "Feature",
  "properties": {
    "tgn:hierarchy":[
        "tgn:1051571",
        "tgn:1000004",
        "tgn:1003405",
        "tgn:7018214",
        "tgn:7002435",
        "tgn:7029392"
    ],
    "tgn:id":1051571,
    "tgn:name":"\u0160arpajevka",
    "tgn:placetype":[
        "aat:300008347"
    ]
},
  "bbox": [],
  "geometry": {"coordinates":[40.9833,48.5667],"type":"Point"}
}