{
  "id": 7400225,
  "type": "Feature",
  "properties": {
    "tgn:hierarchy":[
        "tgn:7400225",
        "tgn:1000001",
        "tgn:7005599",
        "tgn:7005560",
        "tgn:7029392"
    ],
    "tgn:id":7400225,
    "tgn:name":"Desenga\u00f1o Nanchital, R\u00edo",
    "tgn:placetype":[
        "aat:300008699"
    ]
},
  "bbox": [],
  "geometry": {"coordinates":[-93.783333,17.233333],"type":"Point"}
}