<<<<<<< HEAD
{
  "id": 2335764,
  "type": "Feature",
  "properties": {
    "tgn:hierarchy":[
        "tgn:2335764",
        "tgn:1000001",
        "tgn:7012149",
        "tgn:2000234",
        "tgn:7007158",
        "tgn:7029392"
    ],
    "tgn:id":2335764,
    "tgn:name":"Forty-seven Creek",
    "tgn:placetype":[
        "aat:300008706"
    ]
},
  "bbox": [],
  "geometry": {"coordinates":[-108.5,38.4167],"type":"Point"}
}
=======
{"geometry":{"type":"Point","coordinates":[-108.500000,38.416700]},"type":"Feature","properties":{"hierarchy":["tgn:2335764","tgn:1000001","tgn:7012149","tgn:2000234","tgn:7007158","tgn:7029392"],"placetype":["aat:300008706"],"id":2335764,"name:xx":"Forty-seven Creek"}}
>>>>>>> 03f74aca74312dbeaf24d7e61306dd6a786dc3d0
