{
  "id": 2058262,
  "type": "Feature",
  "properties": {
    "tgn:hierarchy":[
        "tgn:2058262",
        "tgn:1000001",
        "tgn:7012149",
        "tgn:2001197",
        "tgn:7007523",
        "tgn:7029392"
    ],
    "tgn:id":2058262,
    "tgn:name":"Cardwell",
    "tgn:placetype":[
        "aat:300008347"
    ]
},
  "bbox": [],
  "geometry": {"coordinates":[-90.2833,36.0333],"type":"Point"}
}