<<<<<<< HEAD
{
  "id": 7245227,
  "type": "Feature",
  "properties": {
    "tgn:hierarchy":[
        "tgn:7245227",
        "tgn:7018238",
        "tgn:1000003",
        "tgn:1000063",
        "tgn:4012014",
        "tgn:7029392"
    ],
    "tgn:id":7245227,
    "tgn:name":"Abeiche",
    "tgn:placetype":[
        "aat:300008347"
    ]
},
  "bbox": [],
  "geometry": {"coordinates":[4.366667,50.7],"type":"Point"}
}
=======
{"geometry":{"type":"Point","coordinates":[4.366667,50.700000]},"type":"Feature","properties":{"hierarchy":["tgn:7245227","tgn:7018238","tgn:1000003","tgn:1000063","tgn:4012014","tgn:7029392"],"placetype":["aat:300008347"],"id":7245227,"name:xx":"Abeiche"}}
>>>>>>> 03f74aca74312dbeaf24d7e61306dd6a786dc3d0
