{
  "id": 2344272,
  "type": "Feature",
  "properties": {
    "tgn:hierarchy":[
        "tgn:2344272",
        "tgn:7002659",
        "tgn:1000001",
        "tgn:2000010",
        "tgn:7012149",
        "tgn:7029392"
    ],
    "tgn:id":2344272,
    "tgn:name":"Gandy Creek",
    "tgn:placetype":[
        "aat:300008706"
    ]
},
  "bbox": [],
  "geometry": {"coordinates":[-86.8333,32.6833],"type":"Point"}
}