{
  "id": 7345297,
  "type": "Feature",
  "properties": {
    "tgn:hierarchy":[
        "tgn:7345297",
        "tgn:7001122",
        "tgn:1000003",
        "tgn:7002765",
        "tgn:1000095",
        "tgn:7029392"
    ],
    "tgn:id":7345297,
    "tgn:name":"Alg\u00e1, Cala",
    "tgn:placetype":[
        "aat:300132317"
    ]
},
  "bbox": [],
  "geometry": {"coordinates":[3.283333,39.416667],"type":"Point"}
}