<<<<<<< HEAD
{
  "id": 2151229,
  "type": "Feature",
  "properties": {
    "tgn:hierarchy":[
        "tgn:2151229",
        "tgn:1000001",
        "tgn:7012149",
        "tgn:7022544",
        "tgn:7007825",
        "tgn:7029392"
    ],
    "tgn:id":2151229,
    "tgn:name":"Bateman Hollow",
    "tgn:placetype":[
        "aat:300008761"
    ]
},
  "bbox": [],
  "geometry": {"coordinates":[-88.5,35.15],"type":"Point"}
}
=======
{"geometry":{"type":"Point","coordinates":[-88.500000,35.150000]},"type":"Feature","properties":{"hierarchy":["tgn:2151229","tgn:1000001","tgn:7012149","tgn:7022544","tgn:7007825","tgn:7029392"],"placetype":["aat:300008761"],"id":2151229,"name:xx":"Bateman Hollow"}}
>>>>>>> 03f74aca74312dbeaf24d7e61306dd6a786dc3d0
