{
  "id": 7469528,
  "type": "Feature",
  "properties": {
    "tgn:hierarchy":[
        "tgn:7469528",
        "tgn:1000004",
        "tgn:7489179",
        "tgn:1000141",
        "tgn:7029392"
    ],
    "tgn:id":7469528,
    "tgn:name":"Xiaowei",
    "tgn:placetype":[
        "aat:300008347"
    ]
},
  "bbox": [],
  "geometry": {"coordinates":[121.810679,24.697354],"type":"Point"}
}