{
  "id": 2685321,
  "type": "Feature",
  "properties": {
    "tgn:hierarchy":[
        "tgn:2685321",
        "tgn:1000001",
        "tgn:7012149",
        "tgn:2002088",
        "tgn:7007826",
        "tgn:7029392"
    ],
    "tgn:id":2685321,
    "tgn:name":"Spotted Oak Spring",
    "tgn:placetype":[
        "aat:300008697"
    ]
},
  "bbox": [],
  "geometry": {"coordinates":[-100.8667,29.8667],"type":"Point"}
}