{
  "id": 7323083,
  "type": "Feature",
  "properties": {
    "tgn:hierarchy":[
        "tgn:7323083",
        "tgn:7001158",
        "tgn:7002848",
        "tgn:1000003",
        "tgn:1000095",
        "tgn:7029392"
    ],
    "tgn:id":7323083,
    "tgn:name":"Rumbos, Arroyo",
    "tgn:placetype":[
        "aat:300266554",
        "aat:300008699"
    ]
},
  "bbox": [],
  "geometry": {"coordinates":[-4.716667,41.383333],"type":"Point"}
}