{
  "id": 1096382,
  "type": "Feature",
  "properties": {
    "tgn:hierarchy":[
        "tgn:1096382",
        "tgn:7000490",
        "tgn:1000006",
        "tgn:7001834",
        "tgn:7029392"
    ],
    "tgn:id":1096382,
    "tgn:name":"Broad Arrow",
    "tgn:placetype":[
        "aat:300008347"
    ]
},
  "bbox": [],
  "geometry": {"coordinates":[121.3333,-30.5333],"type":"Point"}
}