{
  "id": 2295238,
  "type": "Feature",
  "properties": {
    "tgn:hierarchy":[
        "tgn:2295238",
        "tgn:1000001",
        "tgn:7012149",
        "tgn:2001706",
        "tgn:7007708",
        "tgn:7029392"
    ],
    "tgn:id":2295238,
    "tgn:name":"Drew Lake",
    "tgn:placetype":[
        "aat:300008680"
    ]
},
  "bbox": [],
  "geometry": {"coordinates":[-122.9333,42.7833],"type":"Point"}
}