{
  "id": 7308148,
  "type": "Feature",
  "properties": {
    "tgn:hierarchy":[
        "tgn:7308148",
        "tgn:1001630",
        "tgn:1000049",
        "tgn:1000002",
        "tgn:7029392"
    ],
    "tgn:id":7308148,
    "tgn:name":"Del Medio, Caleta",
    "tgn:placetype":[
        "aat:300132317"
    ]
},
  "bbox": [],
  "geometry": {"coordinates":[-70.95,-27.65],"type":"Point"}
}