{
  "id": 7476071,
  "type": "Feature",
  "properties": {
    "tgn:hierarchy":[
        "tgn:7476071",
        "tgn:1000004",
        "tgn:7489179",
        "tgn:1000141",
        "tgn:7029392"
    ],
    "tgn:id":7476071,
    "tgn:name":"Huayu Guoxiao",
    "tgn:placetype":[
        "aat:300006495"
    ]
},
  "bbox": [],
  "geometry": {"coordinates":[121.652028,24.711502],"type":"Point"}
}