{
  "id": 2565881,
  "type": "Feature",
  "properties": {
    "tgn:hierarchy":[
        "tgn:2565881",
        "tgn:1000001",
        "tgn:7012149",
        "tgn:7007157",
        "tgn:1002858",
        "tgn:7029392"
    ],
    "tgn:id":2565881,
    "tgn:name":"Palm Bowl Grove",
    "tgn:placetype":[
        "aat:300132451"
    ]
},
  "bbox": [],
  "geometry": {"coordinates":[-116.2167,32.85],"type":"Point"}
}