{
  "id": 2619146,
  "type": "Feature",
  "properties": {
    "tgn:hierarchy":[
        "tgn:2619146",
        "tgn:1000001",
        "tgn:7012149",
        "tgn:7007710",
        "tgn:7029392"
    ],
    "tgn:id":2619146,
    "tgn:name":"Riley Creek",
    "tgn:placetype":[
        "aat:300008706"
    ]
},
  "bbox": [],
  "geometry": {"coordinates":[-75.9833,41.7333],"type":"Point"}
}