{
  "id": 2103469,
  "type": "Feature",
  "properties": {
    "tgn:hierarchy":[
        "tgn:2103469",
        "tgn:1000001",
        "tgn:7012149",
        "tgn:1002709",
        "tgn:7007826",
        "tgn:7029392"
    ],
    "tgn:id":2103469,
    "tgn:name":"Corsicana",
    "tgn:placetype":[
        "aat:300008347"
    ]
},
  "bbox": [],
  "geometry": {"coordinates":[-96.4667,32.0833],"type":"Point"}
}