{
  "id": 1048297,
  "type": "Feature",
  "properties": {
    "tgn:hierarchy":[
        "tgn:1048297",
        "tgn:7002448",
        "tgn:7019157",
        "tgn:1000003",
        "tgn:7008591",
        "tgn:7029392"
    ],
    "tgn:id":1048297,
    "tgn:name:en":"Ballintoy",
    "tgn:placetype":[
        "aat:300008347"
    ]
},
  "bbox": [],
  "geometry": {"coordinates":[-6.35,55.233333],"type":"Point"}
}