{
  "id": 2034427,
  "type": "Feature",
  "properties": {
    "tgn:hierarchy":[
        "tgn:2034427",
        "tgn:1000001",
        "tgn:7012149",
        "tgn:2000615",
        "tgn:7007253",
        "tgn:7029392"
    ],
    "tgn:id":2034427,
    "tgn:name":"Burt",
    "tgn:placetype":[
        "aat:300008347"
    ]
},
  "bbox": [],
  "geometry": {"coordinates":[-94.2167,43.1833],"type":"Point"}
}