{
  "id": 2095813,
  "type": "Feature",
  "properties": {
    "tgn:hierarchy":[
        "tgn:2095813",
        "tgn:1000001",
        "tgn:7012149",
        "tgn:2001770",
        "tgn:7007712",
        "tgn:7029392"
    ],
    "tgn:id":2095813,
    "tgn:name":"Forest Lake",
    "tgn:placetype":[
        "aat:300008347",
        "aat:300387210"
    ]
},
  "bbox": [],
  "geometry": {"coordinates":[-80.9333,35.0667],"type":"Point"}
}