{
  "id": 7237687,
  "type": "Feature",
  "properties": {
    "tgn:hierarchy":[
        "tgn:7237687",
        "tgn:7007877",
        "tgn:1000003",
        "tgn:1000063",
        "tgn:4012014",
        "tgn:7029392"
    ],
    "tgn:id":7237687,
    "tgn:name":"Fostr\u00e9e",
    "tgn:placetype":[
        "aat:300008347"
    ]
},
  "bbox": [],
  "geometry": {"coordinates":[4.030952,50.612827],"type":"Point"}
}