{
  "id": 7262117,
  "type": "Feature",
  "properties": {
    "tgn:concordances":{
        "gn:id":"2754942"
    },
    "tgn:hierarchy":[
        "tgn:7262117",
        "tgn:1000003",
        "tgn:7006951",
        "tgn:7016845",
        "tgn:7029392"
    ],
    "tgn:id":7262117,
    "tgn:name:nl":"Halfweg",
    "tgn:placetype":[
        "aat:300008347"
    ]
},
  "bbox": [],
  "geometry": {"coordinates":[4.933333,52.533333],"type":"Point"}
}