{
  "id": 7094956,
  "type": "Feature",
  "properties": {
    "tgn:hierarchy":[
        "tgn:7094956",
        "tgn:1000003",
        "tgn:7003689",
        "tgn:7000084",
        "tgn:7029392"
    ],
    "tgn:id":7094956,
    "tgn:name":"Sch\u00f6ne H\u00f6he",
    "tgn:placetype":[
        "aat:300008777"
    ]
},
  "bbox": [],
  "geometry": {"coordinates":[11.966667,50.633333],"type":"Point"}
}