{
  "id": 7110435,
  "type": "Feature",
  "properties": {
    "tgn:hierarchy":[
        "tgn:7110435",
        "tgn:1000003",
        "tgn:7003677",
        "tgn:7000084",
        "tgn:7029392"
    ],
    "tgn:id":7110435,
    "tgn:name":"Pungshaus",
    "tgn:placetype":[
        "aat:300008347"
    ]
},
  "bbox": [],
  "geometry": {"coordinates":[6.95,51.166667],"type":"Point"}
}