{
  "id": 2721106,
  "type": "Feature",
  "properties": {
    "tgn:hierarchy":[
        "tgn:2721106",
        "tgn:1000001",
        "tgn:7012149",
        "tgn:1003042",
        "tgn:7007920",
        "tgn:7029392"
    ],
    "tgn:id":2721106,
    "tgn:name":"Tieton Basin",
    "tgn:placetype":[
        "aat:300386845"
    ]
},
  "bbox": [],
  "geometry": {"coordinates":[-121.0667,46.65],"type":"Point"}
}