{
  "id": 2514701,
  "type": "Feature",
  "properties": {
    "tgn:hierarchy":[
        "tgn:2514701",
        "tgn:1000001",
        "tgn:7012149",
        "tgn:2001886",
        "tgn:7007825",
        "tgn:7029392"
    ],
    "tgn:id":2514701,
    "tgn:name":"Miller Lake",
    "tgn:placetype":[
        "aat:300006191"
    ]
},
  "bbox": [],
  "geometry": {"coordinates":[-87.3667,35.45],"type":"Point"}
}