{
  "id": 2035761,
  "type": "Feature",
  "properties": {
    "tgn:hierarchy":[
        "tgn:2035761",
        "tgn:1000001",
        "tgn:7012149",
        "tgn:2000606",
        "tgn:7007253",
        "tgn:7029392"
    ],
    "tgn:id":2035761,
    "tgn:name":"Thor",
    "tgn:placetype":[
        "aat:300008347"
    ]
},
  "bbox": [],
  "geometry": {"coordinates":[-94.0333,42.6833],"type":"Point"}
}