<<<<<<< HEAD
{
  "id": 7051204,
  "type": "Feature",
  "properties": {
    "tgn:hierarchy":[
        "tgn:7051204",
        "tgn:7007850",
        "tgn:1003491",
        "tgn:1000003",
        "tgn:1000080",
        "tgn:7029392"
    ],
    "tgn:id":7051204,
    "tgn:name":"Nardo",
    "tgn:placetype":[
        "aat:300008347"
    ]
},
  "bbox": [],
  "geometry": {"coordinates":[16.35,38.433333],"type":"Point"}
}
=======
{"geometry":{"type":"Point","coordinates":[16.350000,38.433333]},"type":"Feature","properties":{"hierarchy":["tgn:7051204","tgn:7007850","tgn:1003491","tgn:1000003","tgn:1000080","tgn:7029392"],"placetype":["aat:300008347"],"id":7051204,"name:xx":"Nardo"}}
>>>>>>> 03f74aca74312dbeaf24d7e61306dd6a786dc3d0
