{
  "id": 2211020,
  "type": "Feature",
  "properties": {
    "tgn:hierarchy":[
        "tgn:2211020",
        "tgn:1000001",
        "tgn:7016172",
        "tgn:2000116",
        "tgn:7012149",
        "tgn:7029392"
    ],
    "tgn:id":2211020,
    "tgn:name":"Butler Hollow",
    "tgn:placetype":[
        "aat:300008761"
    ]
},
  "bbox": [],
  "geometry": {"coordinates":[-92.0833,35.6667],"type":"Point"}
}