{
  "id": 7033237,
  "type": "Feature",
  "properties": {
    "tgn:hierarchy":[
        "tgn:7033237",
        "tgn:7002991",
        "tgn:1000003",
        "tgn:7002997",
        "tgn:1000080",
        "tgn:7029392"
    ],
    "tgn:id":7033237,
    "tgn:name":"Puner",
    "tgn:placetype":[
        "aat:300008699"
    ]
},
  "bbox": [],
  "geometry": {"coordinates":[12.070833,46.059167],"type":"Point"}
}