{
  "id": 7050129,
  "type": "Feature",
  "properties": {
    "tgn:hierarchy":[
        "tgn:7050129",
        "tgn:7003154",
        "tgn:1000003",
        "tgn:7003120",
        "tgn:1000080",
        "tgn:7029392"
    ],
    "tgn:id":7050129,
    "tgn:name":"Laval",
    "tgn:placetype":[
        "aat:300008347"
    ]
},
  "bbox": [],
  "geometry": {"coordinates":[6.916667,44.966667],"type":"Point"}
}