{
  "id": 2527195,
  "type": "Feature",
  "properties": {
    "tgn:hierarchy":[
        "tgn:2527195",
        "tgn:1000001",
        "tgn:7012149",
        "tgn:7013867",
        "tgn:7007710",
        "tgn:7029392"
    ],
    "tgn:id":2527195,
    "tgn:name":"Mount Joy Cave Number Five",
    "tgn:placetype":[
        "aat:300008746"
    ]
},
  "bbox": [],
  "geometry": {"coordinates":[-76.4833,40.1167],"type":"Point"}
}