{
  "id": 7571054,
  "type": "Feature",
  "properties": {
    "tgn:hierarchy":[
        "tgn:7571054",
        "tgn:1000004",
        "tgn:7000198",
        "tgn:7001797",
        "tgn:7029392"
    ],
    "tgn:id":7571054,
    "tgn:name:en":"Kallaru Reef",
    "tgn:placetype":[
        "aat:300008808"
    ]
},
  "bbox": [],
  "geometry": {"coordinates":[79.233333,9.25],"type":"Point"}
}