{
  "id": 2574492,
  "type": "Feature",
  "properties": {
    "tgn:hierarchy":[
        "tgn:2574492",
        "tgn:1000001",
        "tgn:7012149",
        "tgn:7007157",
        "tgn:2000190",
        "tgn:7029392"
    ],
    "tgn:id":2574492,
    "tgn:name":"Pellow Place",
    "tgn:placetype":[
        "aat:300008347"
    ]
},
  "bbox": [],
  "geometry": {"coordinates":[-122.6167,39.9667],"type":"Point"}
}