{
  "id": 7017716,
  "type": "Feature",
  "properties": {
    "tgn:hierarchy":[
        "tgn:7017716",
        "tgn:1000001",
        "tgn:7012149",
        "tgn:2001115",
        "tgn:7007522",
        "tgn:7029392"
    ],
    "tgn:id":7017716,
    "tgn:name":"Petit Bois Island",
    "tgn:placetype":[
        "aat:300008791"
    ]
},
  "bbox": [],
  "geometry": {"coordinates":[-88.45,30.1833],"type":"Point"}
}