{
  "id": 2522658,
  "type": "Feature",
  "properties": {
    "tgn:hierarchy":[
        "tgn:2522658",
        "tgn:1000001",
        "tgn:7012149",
        "tgn:2000278",
        "tgn:7007240",
        "tgn:7029392"
    ],
    "tgn:id":2522658,
    "tgn:name":"Moore Branch",
    "tgn:placetype":[
        "aat:300008699"
    ]
},
  "bbox": [],
  "geometry": {"coordinates":[-84.85,30.4667],"type":"Point"}
}