{
  "id": 7581303,
  "type": "Feature",
  "properties": {
    "tgn:hierarchy":[
        "tgn:7581303",
        "tgn:7001819",
        "tgn:1000004",
        "tgn:7000198",
        "tgn:7029392"
    ],
    "tgn:id":7581303,
    "tgn:name:en":"Sike River",
    "tgn:placetype":[
        "aat:300008699"
    ]
},
  "bbox": [],
  "geometry": {"coordinates":[94.64265,28.546241],"type":"Point"}
}