{
  "id": 7180742,
  "type": "Feature",
  "properties": {
    "tgn:hierarchy":[
        "tgn:7180742",
        "tgn:1000003",
        "tgn:7003685",
        "tgn:7000084",
        "tgn:7029392"
    ],
    "tgn:id":7180742,
    "tgn:name":"Gatschel-Berg",
    "tgn:placetype":[
        "aat:300008777"
    ]
},
  "bbox": [],
  "geometry": {"coordinates":[13.35,51.116667],"type":"Point"}
}