{
  "id": 7152382,
  "type": "Feature",
  "properties": {
    "tgn:hierarchy":[
        "tgn:7152382",
        "tgn:1000003",
        "tgn:7003676",
        "tgn:7000084",
        "tgn:7029392"
    ],
    "tgn:id":7152382,
    "tgn:name":"Kachelotplate",
    "tgn:placetype":[
        "aat:300386885"
    ]
},
  "bbox": [],
  "geometry": {"coordinates":[6.816667,53.633333],"type":"Point"}
}