{
  "id": 7252909,
  "type": "Feature",
  "properties": {
    "tgn:hierarchy":[
        "tgn:7252909",
        "tgn:7003458",
        "tgn:1000003",
        "tgn:1000063",
        "tgn:7018236",
        "tgn:7029392"
    ],
    "tgn:id":7252909,
    "tgn:name":"Sint-Juliaan",
    "tgn:placetype":[
        "aat:300008347"
    ]
},
  "bbox": [],
  "geometry": {"coordinates":[2.937116,50.890257],"type":"Point"}
}