{
  "id": 2235156,
  "type": "Feature",
  "properties": {
    "tgn:hierarchy":[
        "tgn:2235156",
        "tgn:1000001",
        "tgn:7012149",
        "tgn:1002839",
        "tgn:7007826",
        "tgn:7029392"
    ],
    "tgn:id":2235156,
    "tgn:name":"Cherry Slough",
    "tgn:placetype":[
        "aat:300008699"
    ]
},
  "bbox": [],
  "geometry": {"coordinates":[-94.5667,32.2333],"type":"Point"}
}