{
  "id": 1053712,
  "type": "Feature",
  "properties": {
    "tgn:hierarchy":[
        "tgn:1053712",
        "tgn:7012187",
        "tgn:1000003",
        "tgn:7006657",
        "tgn:7029392"
    ],
    "tgn:id":1053712,
    "tgn:name":"Dovsk",
    "tgn:placetype":[
        "aat:300008347"
    ]
},
  "bbox": [],
  "geometry": {"coordinates":[30.4833,53.1167],"type":"Point"}
}