{
  "id": 2437703,
  "type": "Feature",
  "properties": {
    "tgn:hierarchy":[
        "tgn:2437703",
        "tgn:1000001",
        "tgn:7012149",
        "tgn:2000216",
        "tgn:7007158",
        "tgn:7029392"
    ],
    "tgn:id":2437703,
    "tgn:name":"King Creek",
    "tgn:placetype":[
        "aat:300008706"
    ]
},
  "bbox": [],
  "geometry": {"coordinates":[-106.2833,39.9333],"type":"Point"}
}