{
  "id": 2621074,
  "type": "Feature",
  "properties": {
    "tgn:hierarchy":[
        "tgn:2621074",
        "tgn:1000001",
        "tgn:7012149",
        "tgn:1002376",
        "tgn:7007252",
        "tgn:7029392"
    ],
    "tgn:id":2621074,
    "tgn:name":"Road Hollow",
    "tgn:placetype":[
        "aat:300008761"
    ]
},
  "bbox": [],
  "geometry": {"coordinates":[-85.8667,38.2667],"type":"Point"}
}