{
  "id": 2147262,
  "type": "Feature",
  "properties": {
    "tgn:hierarchy":[
        "tgn:2147262",
        "tgn:1000001",
        "tgn:7012149",
        "tgn:2000609",
        "tgn:7007253",
        "tgn:7029392"
    ],
    "tgn:id":2147262,
    "tgn:name":"Bar Slough",
    "tgn:placetype":[
        "aat:300008699"
    ]
},
  "bbox": [],
  "geometry": {"coordinates":[-90.3333,42.1833],"type":"Point"}
}