{
  "id": 2136013,
  "type": "Feature",
  "properties": {
    "tgn:hierarchy":[
        "tgn:2136013",
        "tgn:1000001",
        "tgn:7012149",
        "tgn:2000812",
        "tgn:7007255",
        "tgn:7029392"
    ],
    "tgn:id":2136013,
    "tgn:name":"Appletree Branch",
    "tgn:placetype":[
        "aat:300008699"
    ]
},
  "bbox": [],
  "geometry": {"coordinates":[-82.75,37.25],"type":"Point"}
}