{
  "id": 2660088,
  "type": "Feature",
  "properties": {
    "tgn:hierarchy":[
        "tgn:2660088",
        "tgn:1000001",
        "tgn:7012149",
        "tgn:7007157",
        "tgn:2000189",
        "tgn:7029392"
    ],
    "tgn:id":2660088,
    "tgn:name":"Shirttail Canyon",
    "tgn:placetype":[
        "aat:300008761"
    ]
},
  "bbox": [],
  "geometry": {"coordinates":[-121.8333,41.3333],"type":"Point"}
}