<<<<<<< HEAD
{
  "id": 2251355,
  "type": "Feature",
  "properties": {
    "tgn:hierarchy":[
        "tgn:2251355",
        "tgn:1000001",
        "tgn:2001336",
        "tgn:7012149",
        "tgn:7007525",
        "tgn:7029392"
    ],
    "tgn:id":2251355,
    "tgn:name":"Comer Canyon",
    "tgn:placetype":[
        "aat:300008761"
    ]
},
  "bbox": [],
  "geometry": {"coordinates":[-99.4,41.35],"type":"Point"}
}
=======
{"geometry":{"type":"Point","coordinates":[-99.400000,41.350000]},"type":"Feature","properties":{"hierarchy":["tgn:2251355","tgn:1000001","tgn:2001336","tgn:7012149","tgn:7007525","tgn:7029392"],"placetype":["aat:300008761"],"id":2251355,"name:xx":"Comer Canyon"}}
>>>>>>> 03f74aca74312dbeaf24d7e61306dd6a786dc3d0
