{
  "id": 2265487,
  "type": "Feature",
  "properties": {
    "tgn:hierarchy":[
        "tgn:2265487",
        "tgn:1000001",
        "tgn:1002665",
        "tgn:7012149",
        "tgn:7007517",
        "tgn:7029392"
    ],
    "tgn:id":2265487,
    "tgn:name":"Crane Meadow",
    "tgn:placetype":[
        "aat:300008905"
    ]
},
  "bbox": [],
  "geometry": {"coordinates":[-71.5667,42.3167],"type":"Point"}
}