{
  "id": 1122005,
  "type": "Feature",
  "properties": {
    "tgn:hierarchy":[
        "tgn:1122005",
        "tgn:1000051",
        "tgn:1000002",
        "tgn:7029392"
    ],
    "tgn:id":1122005,
    "tgn:name":"Blanco, R\u00edo",
    "tgn:placetype":[
        "aat:300008707"
    ]
},
  "bbox": [],
  "geometry": {"coordinates":[-79.381,0.478],"type":"Point"}
}