{
  "id": 7151674,
  "type": "Feature",
  "properties": {
    "tgn:hierarchy":[
        "tgn:7151674",
        "tgn:7000096",
        "tgn:1000003",
        "tgn:7000084",
        "tgn:7029392"
    ],
    "tgn:id":7151674,
    "tgn:name":"Kahler Berg",
    "tgn:placetype":[
        "aat:300008777"
    ]
},
  "bbox": [],
  "geometry": {"coordinates":[13.433333,51.916667],"type":"Point"}
}