{
  "id": 2714572,
  "type": "Feature",
  "properties": {
    "tgn:hierarchy":[
        "tgn:2714572",
        "tgn:1000001",
        "tgn:7006451",
        "tgn:7012149",
        "tgn:2000104",
        "tgn:7029392"
    ],
    "tgn:id":2714572,
    "tgn:name":"Ten Ewe Canyon",
    "tgn:placetype":[
        "aat:300008761"
    ]
},
  "bbox": [],
  "geometry": {"coordinates":[-114.0667,33.35],"type":"Point"}
}