{
  "id": 2145615,
  "type": "Feature",
  "properties": {
    "tgn:hierarchy":[
        "tgn:2145615",
        "tgn:1000001",
        "tgn:7012149",
        "tgn:7007158",
        "tgn:2000242",
        "tgn:7029392"
    ],
    "tgn:id":2145615,
    "tgn:name":"Baldwin Reservoir",
    "tgn:placetype":[
        "aat:300006191"
    ]
},
  "bbox": [],
  "geometry": {"coordinates":[-104.2167,37.9333],"type":"Point"}
}