{
  "id": 2725795,
  "type": "Feature",
  "properties": {
    "tgn:hierarchy":[
        "tgn:2725795",
        "tgn:1000001",
        "tgn:2002243",
        "tgn:7012149",
        "tgn:7007920",
        "tgn:7029392"
    ],
    "tgn:id":2725795,
    "tgn:name":"Toroda",
    "tgn:placetype":[
        "aat:300008347"
    ]
},
  "bbox": [],
  "geometry": {"coordinates":[-118.75,48.9333],"type":"Point"}
}