{
  "id": 7196040,
  "type": "Feature",
  "properties": {
    "tgn:hierarchy":[
        "tgn:7196040",
        "tgn:1000003",
        "tgn:7003688",
        "tgn:7000084",
        "tgn:7029392"
    ],
    "tgn:id":7196040,
    "tgn:name":"Dingwatt",
    "tgn:placetype":[
        "aat:300000206"
    ]
},
  "bbox": [],
  "geometry": {"coordinates":[9.65,54.633333],"type":"Point"}
}