{
  "id": 2170186,
  "type": "Feature",
  "properties": {
    "tgn:hierarchy":[
        "tgn:2170186",
        "tgn:1000001",
        "tgn:2001703",
        "tgn:7012149",
        "tgn:7007708",
        "tgn:7029392"
    ],
    "tgn:id":2170186,
    "tgn:name":"Big Rattlesnake Butte",
    "tgn:placetype":[
        "aat:300008798"
    ]
},
  "bbox": [],
  "geometry": {"coordinates":[-119.9333,44.2333],"type":"Point"}
}