{
  "id": 2296014,
  "type": "Feature",
  "properties": {
    "tgn:hierarchy":[
        "tgn:2296014",
        "tgn:1000001",
        "tgn:7012149",
        "tgn:2001157",
        "tgn:7007522",
        "tgn:7029392"
    ],
    "tgn:id":2296014,
    "tgn:name":"Dry Bayou",
    "tgn:placetype":[
        "aat:300008699"
    ]
},
  "bbox": [],
  "geometry": {"coordinates":[-90.3333,34.4667],"type":"Point"}
}