{
  "id": 2191149,
  "type": "Feature",
  "properties": {
    "tgn:hierarchy":[
        "tgn:2191149",
        "tgn:1000001",
        "tgn:1002182",
        "tgn:7012149",
        "tgn:7007520",
        "tgn:7029392"
    ],
    "tgn:id":2191149,
    "tgn:name":"Boyle Lake",
    "tgn:placetype":[
        "aat:300008680"
    ]
},
  "bbox": [],
  "geometry": {"coordinates":[-86.45,41.8667],"type":"Point"}
}