<<<<<<< HEAD
{
  "id": 2258549,
  "type": "Feature",
  "properties": {
    "tgn:hierarchy":[
        "tgn:2258549",
        "tgn:1000001",
        "tgn:7012149",
        "tgn:2000784",
        "tgn:7007255",
        "tgn:7029392"
    ],
    "tgn:id":2258549,
    "tgn:name":"Cottonpatch Ridge",
    "tgn:placetype":[
        "aat:300266640"
    ]
},
  "bbox": [],
  "geometry": {"coordinates":[-88.0667,37.45],"type":"Point"}
}
=======
{"geometry":{"type":"Point","coordinates":[-88.066700,37.450000]},"type":"Feature","properties":{"hierarchy":["tgn:2258549","tgn:1000001","tgn:7012149","tgn:2000784","tgn:7007255","tgn:7029392"],"placetype":["aat:300266640"],"id":2258549,"name:xx":"Cottonpatch Ridge"}}
>>>>>>> 03f74aca74312dbeaf24d7e61306dd6a786dc3d0
