<<<<<<< HEAD
{
  "id": 7172840,
  "type": "Feature",
  "properties": {
    "tgn:hierarchy":[
        "tgn:7172840",
        "tgn:1000003",
        "tgn:7003677",
        "tgn:7000084",
        "tgn:7029392"
    ],
    "tgn:id":7172840,
    "tgn:name":"Gro\u00dfeheide",
    "tgn:placetype":[
        "aat:300008347"
    ]
},
  "bbox": [],
  "geometry": {"coordinates":[7.2,51.05],"type":"Point"}
}
=======
{"geometry":{"type":"Point","coordinates":[7.200000,51.050000]},"type":"Feature","properties":{"hierarchy":["tgn:7172840","tgn:1000003","tgn:7003677","tgn:7000084","tgn:7029392"],"placetype":["aat:300008347"],"id":7172840,"name:xx":"Gro\u00dfeheide"}}
>>>>>>> 03f74aca74312dbeaf24d7e61306dd6a786dc3d0
