{
  "id": 2751628,
  "type": "Feature",
  "properties": {
    "tgn:hierarchy":[
        "tgn:2751628",
        "tgn:1000001",
        "tgn:2001425",
        "tgn:7012149",
        "tgn:7007564",
        "tgn:7029392"
    ],
    "tgn:id":2751628,
    "tgn:name":"Warner River",
    "tgn:placetype":[
        "aat:300008707"
    ]
},
  "bbox": [],
  "geometry": {"coordinates":[-71.95,43.25],"type":"Point"}
}