{
  "id": 2333025,
  "type": "Feature",
  "properties": {
    "tgn:hierarchy":[
        "tgn:2333025",
        "tgn:1000001",
        "tgn:7012149",
        "tgn:2000481",
        "tgn:7007250",
        "tgn:7029392"
    ],
    "tgn:id":2333025,
    "tgn:name":"Fly Creek",
    "tgn:placetype":[
        "aat:300008706"
    ]
},
  "bbox": [],
  "geometry": {"coordinates":[-114.5333,44.65],"type":"Point"}
}