<<<<<<< HEAD
{
  "id": 2333025,
  "type": "Feature",
  "properties": {
    "tgn:hierarchy":[
        "tgn:2333025",
        "tgn:1000001",
        "tgn:7012149",
        "tgn:2000481",
        "tgn:7007250",
        "tgn:7029392"
    ],
    "tgn:id":2333025,
    "tgn:name":"Fly Creek",
    "tgn:placetype":[
        "aat:300008706"
    ]
},
  "bbox": [],
  "geometry": {"coordinates":[-114.5333,44.65],"type":"Point"}
}
=======
{"geometry":{"type":"Point","coordinates":[-114.533300,44.650000]},"type":"Feature","properties":{"hierarchy":["tgn:2333025","tgn:1000001","tgn:7012149","tgn:2000481","tgn:7007250","tgn:7029392"],"placetype":["aat:300008706"],"id":2333025,"name:xx":"Fly Creek"}}
>>>>>>> 03f74aca74312dbeaf24d7e61306dd6a786dc3d0
