{
  "id": 7171117,
  "type": "Feature",
  "properties": {
    "tgn:hierarchy":[
        "tgn:7171117",
        "tgn:7003669",
        "tgn:1000003",
        "tgn:7000084",
        "tgn:7029392"
    ],
    "tgn:id":7171117,
    "tgn:name":"Himmelberg",
    "tgn:placetype":[
        "aat:300000206"
    ]
},
  "bbox": [],
  "geometry": {"coordinates":[12.65,49.283333],"type":"Point"}
}