{
  "id": 7568783,
  "type": "Feature",
  "properties": {
    "tgn:hierarchy":[
        "tgn:7568783",
        "tgn:1000004",
        "tgn:7000198",
        "tgn:7016722",
        "tgn:7029392"
    ],
    "tgn:id":7568783,
    "tgn:name:en":"Rash\u012bdgarh",
    "tgn:placetype":[
        "aat:300008347"
    ]
},
  "bbox": [],
  "geometry": {"coordinates":[77.391166,29.576064],"type":"Point"}
}