{
  "id": 2230714,
  "type": "Feature",
  "properties": {
    "tgn:hierarchy":[
        "tgn:2230714",
        "tgn:1002138",
        "tgn:1000001",
        "tgn:7012149",
        "tgn:7007157",
        "tgn:7029392"
    ],
    "tgn:id":2230714,
    "tgn:name":"Centerville District",
    "tgn:placetype":[
        "aat:300008347"
    ]
},
  "bbox": [],
  "geometry": {"coordinates":[-121.9833,37.55],"type":"Point"}
}