{
  "id": 2143082,
  "type": "Feature",
  "properties": {
    "tgn:hierarchy":[
        "tgn:2143082",
        "tgn:1000001",
        "tgn:7012149",
        "tgn:2001751",
        "tgn:7007712",
        "tgn:7029392"
    ],
    "tgn:id":2143082,
    "tgn:name":"Bagshaw Swamp",
    "tgn:placetype":[
        "aat:300008905"
    ]
},
  "bbox": [],
  "geometry": {"coordinates":[-81.0333,32.3667],"type":"Point"}
}