{
  "id": 7188002,
  "type": "Feature",
  "properties": {
    "tgn:hierarchy":[
        "tgn:7188002",
        "tgn:7003669",
        "tgn:1000003",
        "tgn:7000084",
        "tgn:7029392"
    ],
    "tgn:id":7188002,
    "tgn:name":"Ettensberg",
    "tgn:placetype":[
        "aat:300008347"
    ]
},
  "bbox": [],
  "geometry": {"coordinates":[10.233333,47.75],"type":"Point"}
}