{
  "id": 2735891,
  "type": "Feature",
  "properties": {
    "tgn:hierarchy":[
        "tgn:2735891",
        "tgn:1000001",
        "tgn:7012149",
        "tgn:2000479",
        "tgn:7007250",
        "tgn:7029392"
    ],
    "tgn:id":2735891,
    "tgn:name":"Twin Lakes",
    "tgn:placetype":[
        "aat:300006191"
    ]
},
  "bbox": [],
  "geometry": {"coordinates":[-116.85,47.85],"type":"Point"}
}