{
  "id": 2730102,
  "type": "Feature",
  "properties": {
    "tgn:hierarchy":[
        "tgn:2730102",
        "tgn:1000001",
        "tgn:7012149",
        "tgn:2000972",
        "tgn:7007520",
        "tgn:7029392"
    ],
    "tgn:id":2730102,
    "tgn:name":"Trout Lake",
    "tgn:placetype":[
        "aat:300008680"
    ]
},
  "bbox": [],
  "geometry": {"coordinates":[-85.6667,46.65],"type":"Point"}
}