{
  "id": 7349612,
  "type": "Feature",
  "properties": {
    "tgn:hierarchy":[
        "tgn:7349612",
        "tgn:1000001",
        "tgn:7005601",
        "tgn:7005560",
        "tgn:7029392"
    ],
    "tgn:id":7349612,
    "tgn:name":"Agua Nueva",
    "tgn:placetype":[
        "aat:300008347"
    ]
},
  "bbox": [],
  "geometry": {"coordinates":[-102.15,23.783333],"type":"Point"}
}