<<<<<<< HEAD
{
  "id": 7371131,
  "type": "Feature",
  "properties": {
    "tgn:hierarchy":[
        "tgn:7371131",
        "tgn:7005581",
        "tgn:1000001",
        "tgn:7005560",
        "tgn:7029392"
    ],
    "tgn:id":7371131,
    "tgn:name":"Rancho de Grac\u00eda",
    "tgn:placetype":[
        "aat:300000241"
    ]
},
  "bbox": [],
  "geometry": {"coordinates":[-107.4,29.316667],"type":"Point"}
}
=======
{"geometry":{"type":"Point","coordinates":[-107.400000,29.316667]},"type":"Feature","properties":{"hierarchy":["tgn:7371131","tgn:7005581","tgn:1000001","tgn:7005560","tgn:7029392"],"placetype":["aat:300000241"],"id":7371131,"name:xx":"Rancho de Grac\u00eda"}}
>>>>>>> 03f74aca74312dbeaf24d7e61306dd6a786dc3d0
