{
  "id": 2243591,
  "type": "Feature",
  "properties": {
    "tgn:hierarchy":[
        "tgn:2243591",
        "tgn:1000001",
        "tgn:7012149",
        "tgn:1002520",
        "tgn:7007710",
        "tgn:7029392"
    ],
    "tgn:id":2243591,
    "tgn:name":"Clemans Run",
    "tgn:placetype":[
        "aat:300008699"
    ]
},
  "bbox": [],
  "geometry": {"coordinates":[-79.05,41.2833],"type":"Point"}
}