{
  "id": 2589282,
  "type": "Feature",
  "properties": {
    "tgn:hierarchy":[
        "tgn:2589282",
        "tgn:1000001",
        "tgn:2001747",
        "tgn:7012149",
        "tgn:7007712",
        "tgn:7029392"
    ],
    "tgn:id":2589282,
    "tgn:name":"Poinsetta",
    "tgn:placetype":[
        "aat:300008347"
    ]
},
  "bbox": [],
  "geometry": {"coordinates":[-82.2333,34.7167],"type":"Point"}
}