{
  "id": 7559271,
  "type": "Feature",
  "properties": {
    "tgn:hierarchy":[
        "tgn:7559271",
        "tgn:1000004",
        "tgn:7000198",
        "tgn:1001895",
        "tgn:7029392"
    ],
    "tgn:id":7559271,
    "tgn:name:en":"Rohini",
    "tgn:placetype":[
        "aat:300007783"
    ]
},
  "bbox": [],
  "geometry": {"coordinates":[74.883333,20.383333],"type":"Point"}
}