{
  "id": 7500425,
  "type": "Feature",
  "properties": {
    "tgn:hierarchy":[
        "tgn:7500425",
        "tgn:7001004",
        "tgn:1000004",
        "tgn:1000141",
        "tgn:7029392"
    ],
    "tgn:id":7500425,
    "tgn:name":"Wulu Xi",
    "tgn:placetype":[
        "aat:300008699"
    ]
},
  "bbox": [],
  "geometry": {"coordinates":[120.473611,22.863056],"type":"Point"}
}