{
  "id": 2084418,
  "type": "Feature",
  "properties": {
    "tgn:hierarchy":[
        "tgn:2084418",
        "tgn:1000001",
        "tgn:7012149",
        "tgn:1002994",
        "tgn:7007708",
        "tgn:7029392"
    ],
    "tgn:id":2084418,
    "tgn:name":"Bethany",
    "tgn:placetype":[
        "aat:300008347",
        "aat:300387210"
    ]
},
  "bbox": [],
  "geometry": {"coordinates":[-122.85,45.55],"type":"Point"}
}