{
  "id": 2486502,
  "type": "Feature",
  "properties": {
    "tgn:hierarchy":[
        "tgn:2486502",
        "tgn:7013388",
        "tgn:1000001",
        "tgn:7012149",
        "tgn:7007517",
        "tgn:7029392"
    ],
    "tgn:id":2486502,
    "tgn:name":"Lebanon, Mount",
    "tgn:placetype":[
        "aat:300008798"
    ]
},
  "bbox": [],
  "geometry": {"coordinates":[-73.3667,42.45],"type":"Point"}
}