{
  "id": 4002549,
  "type": "Feature",
  "properties": {
    "tgn:hierarchy":[
        "tgn:4002549",
        "tgn:7002445",
        "tgn:1000003",
        "tgn:7008175",
        "tgn:7008591",
        "tgn:7029392"
    ],
    "tgn:id":4002549,
    "tgn:name:en":"Charlwood",
    "tgn:placetype":[
        "aat:300008347"
    ]
},
  "bbox": [],
  "geometry": {"coordinates":[-0.216667,51.15],"type":"Point"}
}