{
  "id": 2574555,
  "type": "Feature",
  "properties": {
    "tgn:hierarchy":[
        "tgn:2574555",
        "tgn:1000001",
        "tgn:7012149",
        "tgn:1002810",
        "tgn:7007568",
        "tgn:7029392"
    ],
    "tgn:id":2574555,
    "tgn:name":"Pelton Pond",
    "tgn:placetype":[
        "aat:300008680"
    ]
},
  "bbox": [],
  "geometry": {"coordinates":[-73.8167,41.45],"type":"Point"}
}