{
  "id": 2515670,
  "type": "Feature",
  "properties": {
    "tgn:hierarchy":[
        "tgn:2515670",
        "tgn:1000001",
        "tgn:7012149",
        "tgn:2002291",
        "tgn:7013961",
        "tgn:7029392"
    ],
    "tgn:id":2515670,
    "tgn:name":"Millstone Gap Ridge",
    "tgn:placetype":[
        "aat:300266640"
    ]
},
  "bbox": [],
  "geometry": {"coordinates":[-79.8333,38.7667],"type":"Point"}
}