{
  "id": 2163464,
  "type": "Feature",
  "properties": {
    "tgn:hierarchy":[
        "tgn:2163464",
        "tgn:1000001",
        "tgn:2000922",
        "tgn:7012149",
        "tgn:7007515",
        "tgn:7029392"
    ],
    "tgn:id":2163464,
    "tgn:name":"Benson Brook",
    "tgn:placetype":[
        "aat:300008699"
    ]
},
  "bbox": [],
  "geometry": {"coordinates":[-68.7833,44.35],"type":"Point"}
}