{
  "id": 7288955,
  "type": "Feature",
  "properties": {
    "tgn:hierarchy":[
        "tgn:7288955",
        "tgn:1001768",
        "tgn:1000049",
        "tgn:1000002",
        "tgn:7029392"
    ],
    "tgn:id":7288955,
    "tgn:name":"La Greda, Morro",
    "tgn:placetype":[
        "aat:300008798"
    ]
},
  "bbox": [],
  "geometry": {"coordinates":[-70.666667,-32.416667],"type":"Point"}
}