{
  "id": 7545766,
  "type": "Feature",
  "properties": {
    "tgn:hierarchy":[
        "tgn:7545766",
        "tgn:1000004",
        "tgn:1001842",
        "tgn:7000198",
        "tgn:7029392"
    ],
    "tgn:id":7545766,
    "tgn:name:en":"Amh\u0101ra",
    "tgn:placetype":[
        "aat:300008347"
    ]
},
  "bbox": [],
  "geometry": {"coordinates":[87.326607,26.284587],"type":"Point"}
}