{
  "id": 2571573,
  "type": "Feature",
  "properties": {
    "tgn:hierarchy":[
        "tgn:2571573",
        "tgn:1000001",
        "tgn:7012149",
        "tgn:7007524",
        "tgn:7029392"
    ],
    "tgn:id":2571573,
    "tgn:name":"Paupers Dream Mine",
    "tgn:placetype":[
        "aat:300000390"
    ]
},
  "bbox": [],
  "geometry": {"coordinates":[-112.2833,46.4167],"type":"Point"}
}