{
  "id": 2356772,
  "type": "Feature",
  "properties": {
    "tgn:hierarchy":[
        "tgn:2356772",
        "tgn:1000001",
        "tgn:7012149",
        "tgn:1002501",
        "tgn:7007710",
        "tgn:7029392"
    ],
    "tgn:id":2356772,
    "tgn:name":"Gorman Summit",
    "tgn:placetype":[
        "aat:300008347"
    ]
},
  "bbox": [],
  "geometry": {"coordinates":[-78.8833,40.7833],"type":"Point"}
}