{
  "id": 7332541,
  "type": "Feature",
  "properties": {
    "tgn:hierarchy":[
        "tgn:7332541",
        "tgn:7002760",
        "tgn:1000003",
        "tgn:1000095",
        "tgn:7029392"
    ],
    "tgn:id":7332541,
    "tgn:name":"La Altura",
    "tgn:placetype":[
        "aat:300008347"
    ]
},
  "bbox": [],
  "geometry": {"coordinates":[-3.266667,43.233333],"type":"Point"}
}