{
  "id": 7487100,
  "type": "Feature",
  "properties": {
    "tgn:hierarchy":[
        "tgn:7487100",
        "tgn:1000004",
        "tgn:7491221",
        "tgn:1000141",
        "tgn:7029392"
    ],
    "tgn:id":7487100,
    "tgn:name":"Balangwei Shan",
    "tgn:placetype":[
        "aat:300008798"
    ]
},
  "bbox": [],
  "geometry": {"coordinates":[120.878889,22.3225],"type":"Point"}
}