<<<<<<< HEAD
{
  "id": 7487100,
  "type": "Feature",
  "properties": {
    "tgn:hierarchy":[
        "tgn:7487100",
        "tgn:1000004",
        "tgn:7491221",
        "tgn:1000141",
        "tgn:7029392"
    ],
    "tgn:id":7487100,
    "tgn:name":"Balangwei Shan",
    "tgn:placetype":[
        "aat:300008798"
    ]
},
  "bbox": [],
  "geometry": {"coordinates":[120.878889,22.3225],"type":"Point"}
}
=======
{"geometry":{"type":"Point","coordinates":[120.878889,22.322500]},"type":"Feature","properties":{"hierarchy":["tgn:7487100","tgn:1000004","tgn:7491221","tgn:1000141","tgn:7029392"],"placetype":["aat:300008798"],"id":7487100,"name:xx":"Balangwei Shan"}}
>>>>>>> 03f74aca74312dbeaf24d7e61306dd6a786dc3d0
