<<<<<<< HEAD
{
  "id": 2252213,
  "type": "Feature",
  "properties": {
    "tgn:hierarchy":[
        "tgn:2252213",
        "tgn:1000001",
        "tgn:7012149",
        "tgn:1003047",
        "tgn:7007710",
        "tgn:7029392"
    ],
    "tgn:id":2252213,
    "tgn:name":"Conejohela Valley",
    "tgn:placetype":[
        "aat:300008761"
    ]
},
  "bbox": [],
  "geometry": {"coordinates":[-76.55,39.9667],"type":"Point"}
}
=======
{"geometry":{"type":"Point","coordinates":[-76.550000,39.966700]},"type":"Feature","properties":{"hierarchy":["tgn:2252213","tgn:1000001","tgn:7012149","tgn:1003047","tgn:7007710","tgn:7029392"],"placetype":["aat:300008761"],"id":2252213,"name:xx":"Conejohela Valley"}}
>>>>>>> 03f74aca74312dbeaf24d7e61306dd6a786dc3d0
