{
  "id": 1130818,
  "type": "Feature",
  "properties": {
    "tgn:hierarchy":[
        "tgn:1130818",
        "tgn:7005685",
        "tgn:1000001",
        "tgn:7013154",
        "tgn:7029392"
    ],
    "tgn:id":1130818,
    "tgn:name":"Thorne",
    "tgn:placetype":[
        "aat:300008707"
    ]
},
  "bbox": [],
  "geometry": {"coordinates":[-90.5833,54.9333],"type":"Point"}
}