{
  "id": 7105498,
  "type": "Feature",
  "properties": {
    "tgn:hierarchy":[
        "tgn:7105498",
        "tgn:1000003",
        "tgn:7003688",
        "tgn:7000084",
        "tgn:7029392"
    ],
    "tgn:id":7105498,
    "tgn:name":"Schierenh\u00f6he",
    "tgn:placetype":[
        "aat:300008347"
    ]
},
  "bbox": [],
  "geometry": {"coordinates":[9.733333,53.833333],"type":"Point"}
}