{
  "id": 1006176,
  "type": "Feature",
  "properties": {
    "tgn:hierarchy":[
        "tgn:1006176",
        "tgn:7006641",
        "tgn:1000003",
        "tgn:7006540",
        "tgn:7029392"
    ],
    "tgn:id":1006176,
    "tgn:name:en":"Abruka",
    "tgn:placetype":[
        "aat:300008791"
    ]
},
  "bbox": [],
  "geometry": {"coordinates":[22.508,58.148],"type":"Point"}
}