{
  "id": 2607157,
  "type": "Feature",
  "properties": {
    "tgn:hierarchy":[
        "tgn:2607157",
        "tgn:1000001",
        "tgn:7012149",
        "tgn:7016021",
        "tgn:7007568",
        "tgn:7029392"
    ],
    "tgn:id":2607157,
    "tgn:name":"Randall Hill",
    "tgn:placetype":[
        "aat:300008798"
    ]
},
  "bbox": [],
  "geometry": {"coordinates":[-75.0167,44.35],"type":"Point"}
}