{
  "id": 1005395,
  "type": "Feature",
  "properties": {
    "tgn:hierarchy":[
        "tgn:1005395",
        "tgn:7006280",
        "tgn:7010546",
        "tgn:7017994",
        "tgn:1000003",
        "tgn:7006278",
        "tgn:7029392"
    ],
    "tgn:id":1005395,
    "tgn:name":"R\u00e1kospalota",
    "tgn:placetype":[
        "aat:300000745"
    ]
},
  "bbox": [],
  "geometry": {"coordinates":[19.1333,47.5667],"type":"Point"}
}