<<<<<<< HEAD
{
  "id": 2334962,
  "type": "Feature",
  "properties": {
    "tgn:hierarchy":[
        "tgn:2334962",
        "tgn:1000001",
        "tgn:7012149",
        "tgn:1002569",
        "tgn:7007252",
        "tgn:7029392"
    ],
    "tgn:id":2334962,
    "tgn:name":"Forks, The",
    "tgn:placetype":[
        "aat:300008678"
    ]
},
  "bbox": [],
  "geometry": {"coordinates":[-87.4667,41.6333],"type":"Point"}
}
=======
{"geometry":{"type":"Point","coordinates":[-87.466700,41.633300]},"type":"Feature","properties":{"hierarchy":["tgn:2334962","tgn:1000001","tgn:7012149","tgn:1002569","tgn:7007252","tgn:7029392"],"placetype":["aat:300008678"],"id":2334962,"name:xx":"Forks, The"}}
>>>>>>> 03f74aca74312dbeaf24d7e61306dd6a786dc3d0
