{
  "id": 7143057,
  "type": "Feature",
  "properties": {
    "tgn:hierarchy":[
        "tgn:7143057",
        "tgn:1000003",
        "tgn:7003678",
        "tgn:7000084",
        "tgn:7029392"
    ],
    "tgn:id":7143057,
    "tgn:name":"Linden-Berg",
    "tgn:placetype":[
        "aat:300008777"
    ]
},
  "bbox": [],
  "geometry": {"coordinates":[9.633333,51.616667],"type":"Point"}
}