<<<<<<< HEAD
{
  "id": 7483517,
  "type": "Feature",
  "properties": {
    "tgn:hierarchy":[
        "tgn:7483517",
        "tgn:7468018",
        "tgn:1000004",
        "tgn:1000141",
        "tgn:7029392"
    ],
    "tgn:id":7483517,
    "tgn:name":"Siwei Qiao",
    "tgn:placetype":[
        "aat:300007836"
    ]
},
  "bbox": [],
  "geometry": {"coordinates":[120.554722,23.225833],"type":"Point"}
}
=======
{"geometry":{"type":"Point","coordinates":[120.554722,23.225833]},"type":"Feature","properties":{"hierarchy":["tgn:7483517","tgn:7468018","tgn:1000004","tgn:1000141","tgn:7029392"],"placetype":["aat:300007836"],"id":7483517,"name:xx":"Siwei Qiao"}}
>>>>>>> 03f74aca74312dbeaf24d7e61306dd6a786dc3d0
