{
  "id": 2084638,
  "type": "Feature",
  "properties": {
    "tgn:hierarchy":[
        "tgn:2084638",
        "tgn:1000001",
        "tgn:2001705",
        "tgn:7012149",
        "tgn:7007708",
        "tgn:7029392"
    ],
    "tgn:id":2084638,
    "tgn:name":"Deschutes",
    "tgn:placetype":[
        "aat:300387016"
    ]
},
  "bbox": [],
  "geometry": {"coordinates":[-121.25,44.15],"type":"Point"}
}