{
  "id": 2406246,
  "type": "Feature",
  "properties": {
    "tgn:hierarchy":[
        "tgn:2406246",
        "tgn:1000001",
        "tgn:2001745",
        "tgn:7012149",
        "tgn:7007712",
        "tgn:7029392"
    ],
    "tgn:id":2406246,
    "tgn:name":"Humphrey Lake",
    "tgn:placetype":[
        "aat:300008680"
    ]
},
  "bbox": [],
  "geometry": {"coordinates":[-79.9833,34.0333],"type":"Point"}
}