<<<<<<< HEAD
{
  "id": 7023380,
  "type": "Feature",
  "properties": {
    "tgn:hierarchy":[
        "tgn:7023380",
        "tgn:1000001",
        "tgn:7012149",
        "tgn:7007919",
        "tgn:7029392"
    ],
    "tgn:id":7023380,
    "tgn:name":"Matoaka Lake",
    "tgn:placetype":[
        "aat:300006191"
    ]
},
  "bbox": [],
  "geometry": {"coordinates":[-76.7167,37.25],"type":"Point"}
}
=======
{"geometry":{"type":"Point","coordinates":[-76.716700,37.250000]},"type":"Feature","properties":{"hierarchy":["tgn:7023380","tgn:1000001","tgn:7012149","tgn:7007919","tgn:7029392"],"placetype":["aat:300006191"],"id":7023380,"name:xx":"Matoaka Lake"}}
>>>>>>> 03f74aca74312dbeaf24d7e61306dd6a786dc3d0
