{
  "id": 7415496,
  "type": "Feature",
  "properties": {
    "tgn:hierarchy":[
        "tgn:7415496",
        "tgn:1000001",
        "tgn:7005591",
        "tgn:7005560",
        "tgn:7029392"
    ],
    "tgn:id":7415496,
    "tgn:name:es":"Uni\u00f3n Ju\u00e1rez",
    "tgn:placetype":[
        "aat:300008347"
    ]
},
  "bbox": [],
  "geometry": {"coordinates":[-96.000278,16.745278],"type":"Point"}
}