{
  "id": 2749977,
  "type": "Feature",
  "properties": {
    "tgn:hierarchy":[
        "tgn:2749977",
        "tgn:1000001",
        "tgn:7012149",
        "tgn:7018871",
        "tgn:7007920",
        "tgn:7029392"
    ],
    "tgn:id":2749977,
    "tgn:name":"Walsh Lake Diversion Ditch",
    "tgn:placetype":[
        "aat:300006075"
    ]
},
  "bbox": [],
  "geometry": {"coordinates":[-121.95,47.3833],"type":"Point"}
}