{
  "id": 7428245,
  "type": "Feature",
  "properties": {
    "tgn:hierarchy":[
        "tgn:7428245",
        "tgn:1000001",
        "tgn:7005601",
        "tgn:7005560",
        "tgn:7029392"
    ],
    "tgn:id":7428245,
    "tgn:name":"El Epazote",
    "tgn:placetype":[
        "aat:300008347"
    ]
},
  "bbox": [],
  "geometry": {"coordinates":[-101.283333,23.966667],"type":"Point"}
}