{
  "id": 7543792,
  "type": "Feature",
  "properties": {
    "tgn:hierarchy":[
        "tgn:7543792",
        "tgn:7001242",
        "tgn:1001059",
        "tgn:7016833",
        "tgn:7029392"
    ],
    "tgn:id":7543792,
    "tgn:name":"Tur'at al M\u0101li\u1e29ah",
    "tgn:placetype":[
        "aat:300006075"
    ]
},
  "bbox": [],
  "geometry": {"coordinates":[31.51439,31.291936],"type":"Point"}
}