{
  "id": 2470905,
  "type": "Feature",
  "properties": {
    "tgn:hierarchy":[
        "tgn:2470905",
        "tgn:1000001",
        "tgn:7012149",
        "tgn:7007248",
        "tgn:7029392"
    ],
    "tgn:id":2470905,
    "tgn:name":"Lost Creek",
    "tgn:placetype":[
        "aat:300008706"
    ]
},
  "bbox": [],
  "geometry": {"coordinates":[-84.05,31.25],"type":"Point"}
}