{
  "id": 7256558,
  "type": "Feature",
  "properties": {
    "tgn:hierarchy":[
        "tgn:7256558",
        "tgn:7004783",
        "tgn:7593114",
        "tgn:7593112",
        "tgn:1000001",
        "tgn:7029392"
    ],
    "tgn:id":7256558,
    "tgn:name:nl":"Bellevue",
    "tgn:placetype":[
        "aat:300387200"
    ]
},
  "bbox": [],
  "geometry": {"coordinates":[-62.966667,17.466667],"type":"Point"}
}