{
  "id": 7592554,
  "type": "Feature",
  "properties": {
    "tgn:hierarchy":[
        "tgn:7592554",
        "tgn:1000004",
        "tgn:7000198",
        "tgn:7016722",
        "tgn:7029392"
    ],
    "tgn:id":7592554,
    "tgn:name:en":"Mohan Reserved Forest",
    "tgn:placetype":[
        "aat:300008863"
    ]
},
  "bbox": [],
  "geometry": {"coordinates":[77.922508,30.151593],"type":"Point"}
}