{
  "id": 7529295,
  "type": "Feature",
  "properties": {
    "tgn:hierarchy":[
        "tgn:7529295",
        "tgn:7001242",
        "tgn:7016833",
        "tgn:7001336",
        "tgn:7029392"
    ],
    "tgn:id":7529295,
    "tgn:name:en":"Umm Sh\u016bmar, Jabal",
    "tgn:placetype":[
        "aat:300008795"
    ]
},
  "bbox": [],
  "geometry": {"coordinates":[33.915379,28.362569],"type":"Point"}
}