{
  "id": 2217075,
  "type": "Feature",
  "properties": {
    "tgn:hierarchy":[
        "tgn:2217075",
        "tgn:1000001",
        "tgn:7012149",
        "tgn:1002356",
        "tgn:7007568",
        "tgn:7029392"
    ],
    "tgn:id":2217075,
    "tgn:name":"Camp Pioneer",
    "tgn:placetype":[
        "aat:300008347"
    ]
},
  "bbox": [],
  "geometry": {"coordinates":[-79.0667,42.6167],"type":"Point"}
}