{
  "id": 2230219,
  "type": "Feature",
  "properties": {
    "tgn:hierarchy":[
        "tgn:2230219",
        "tgn:1000001",
        "tgn:2001425",
        "tgn:7012149",
        "tgn:7007564",
        "tgn:7029392"
    ],
    "tgn:id":2230219,
    "tgn:name":"Cemetery Brook",
    "tgn:placetype":[
        "aat:300008699"
    ]
},
  "bbox": [],
  "geometry": {"coordinates":[-71.4667,43.25],"type":"Point"}
}