{
  "id": 2305423,
  "type": "Feature",
  "properties": {
    "tgn:hierarchy":[
        "tgn:2305423",
        "tgn:1000001",
        "tgn:7012149",
        "tgn:7007828",
        "tgn:7029392"
    ],
    "tgn:id":2305423,
    "tgn:name":"East Brook",
    "tgn:placetype":[
        "aat:300008699"
    ]
},
  "bbox": [],
  "geometry": {"coordinates":[-72.2167,44.1667],"type":"Point"}
}