{
  "id": 2656364,
  "type": "Feature",
  "properties": {
    "tgn:hierarchy":[
        "tgn:2656364",
        "tgn:1002538",
        "tgn:1000001",
        "tgn:7012149",
        "tgn:7007239",
        "tgn:7029392"
    ],
    "tgn:id":2656364,
    "tgn:name":"Shearness Pool",
    "tgn:placetype":[
        "aat:300006191"
    ]
},
  "bbox": [],
  "geometry": {"coordinates":[-75.4667,39.2667],"type":"Point"}
}