{
  "id": 7157438,
  "type": "Feature",
  "properties": {
    "tgn:hierarchy":[
        "tgn:7157438",
        "tgn:7003669",
        "tgn:1000003",
        "tgn:7000084",
        "tgn:7029392"
    ],
    "tgn:id":7157438,
    "tgn:name":"Kleiner Leimig",
    "tgn:placetype":[
        "aat:300008777"
    ]
},
  "bbox": [],
  "geometry": {"coordinates":[9.933333,49.866667],"type":"Point"}
}