{
  "id": 2476728,
  "type": "Feature",
  "properties": {
    "tgn:hierarchy":[
        "tgn:2476728",
        "tgn:1000001",
        "tgn:7012149",
        "tgn:7007157",
        "tgn:1002858",
        "tgn:7029392"
    ],
    "tgn:id":2476728,
    "tgn:name":"Lycium Wash",
    "tgn:placetype":[
        "aat:300008699"
    ]
},
  "bbox": [],
  "geometry": {"coordinates":[-116.1333,33.0167],"type":"Point"}
}