{
  "id": 2008023,
  "type": "Feature",
  "properties": {
    "tgn:hierarchy":[
        "tgn:2008023",
        "tgn:2000107",
        "tgn:1000001",
        "tgn:7016172",
        "tgn:7012149",
        "tgn:7029392"
    ],
    "tgn:id":2008023,
    "tgn:name":"Cotter",
    "tgn:placetype":[
        "aat:300008347"
    ]
},
  "bbox": [],
  "geometry": {"coordinates":[-92.5333,36.2667],"type":"Point"}
}