{
  "id": 2517404,
  "type": "Feature",
  "properties": {
    "tgn:hierarchy":[
        "tgn:2517404",
        "tgn:1000001",
        "tgn:7012149",
        "tgn:1002865",
        "tgn:7007706",
        "tgn:7029392"
    ],
    "tgn:id":2517404,
    "tgn:name":"Minnow Creek",
    "tgn:placetype":[
        "aat:300008706"
    ]
},
  "bbox": [],
  "geometry": {"coordinates":[-83.15,41.3333],"type":"Point"}
}