{
  "id": 2296548,
  "type": "Feature",
  "properties": {
    "tgn:hierarchy":[
        "tgn:2296548",
        "tgn:1000001",
        "tgn:7012149",
        "tgn:2001867",
        "tgn:7007825",
        "tgn:7029392"
    ],
    "tgn:id":2296548,
    "tgn:name":"Dry Cave",
    "tgn:placetype":[
        "aat:300008746"
    ]
},
  "bbox": [],
  "geometry": {"coordinates":[-85.7333,35.5167],"type":"Point"}
}