{
  "id": 2261982,
  "type": "Feature",
  "properties": {
    "tgn:hierarchy":[
        "tgn:2261982",
        "tgn:1000001",
        "tgn:7012149",
        "tgn:7007256",
        "tgn:7029392"
    ],
    "tgn:id":2261982,
    "tgn:name":"Cow Bayou",
    "tgn:placetype":[
        "aat:300008699"
    ]
},
  "bbox": [],
  "geometry": {"coordinates":[-93.7167,31.9667],"type":"Point"}
}