{
  "id": 2170608,
  "type": "Feature",
  "properties": {
    "tgn:hierarchy":[
        "tgn:2170608",
        "tgn:1000001",
        "tgn:7016172",
        "tgn:7012149",
        "tgn:7029392"
    ],
    "tgn:id":2170608,
    "tgn:name":"Big Running Water Creek",
    "tgn:placetype":[
        "aat:300008706"
    ]
},
  "bbox": [],
  "geometry": {"coordinates":[-90.85,36.2167],"type":"Point"}
}