{
  "id": 2450312,
  "type": "Feature",
  "properties": {
    "tgn:hierarchy":[
        "tgn:2450312",
        "tgn:7002659",
        "tgn:1000001",
        "tgn:7012149",
        "tgn:2000033",
        "tgn:7029392"
    ],
    "tgn:id":2450312,
    "tgn:name":"Lingo Pond",
    "tgn:placetype":[
        "aat:300006191"
    ]
},
  "bbox": [],
  "geometry": {"coordinates":[-85.3667,31.65],"type":"Point"}
}