{
  "id": 7414934,
  "type": "Feature",
  "properties": {
    "tgn:hierarchy":[
        "tgn:7414934",
        "tgn:7005584",
        "tgn:1000001",
        "tgn:7005560",
        "tgn:7029392"
    ],
    "tgn:id":7414934,
    "tgn:name":"La Huerta, Arroyo",
    "tgn:placetype":[
        "aat:300266554",
        "aat:300008699"
    ]
},
  "bbox": [],
  "geometry": {"coordinates":[-100.913889,20.131944],"type":"Point"}
}