{
  "id": 2543789,
  "type": "Feature",
  "properties": {
    "tgn:hierarchy":[
        "tgn:2543789",
        "tgn:1000001",
        "tgn:7012149",
        "tgn:1002465",
        "tgn:7007252",
        "tgn:7029392"
    ],
    "tgn:id":2543789,
    "tgn:name":"North Belleville",
    "tgn:placetype":[
        "aat:300008347"
    ]
},
  "bbox": [],
  "geometry": {"coordinates":[-86.4833,39.6833],"type":"Point"}
}