{
  "id": 2143057,
  "type": "Feature",
  "properties": {
    "tgn:hierarchy":[
        "tgn:2143057",
        "tgn:1000001",
        "tgn:7012149",
        "tgn:1003020",
        "tgn:7007920",
        "tgn:7029392"
    ],
    "tgn:id":2143057,
    "tgn:name":"Bagley Lakes",
    "tgn:placetype":[
        "aat:300008680"
    ]
},
  "bbox": [],
  "geometry": {"coordinates":[-121.6833,48.85],"type":"Point"}
}