{
  "id": 2055277,
  "type": "Feature",
  "properties": {
    "tgn:hierarchy":[
        "tgn:2055277",
        "tgn:1000001",
        "tgn:7012149",
        "tgn:2001032",
        "tgn:7007521",
        "tgn:7029392"
    ],
    "tgn:id":2055277,
    "tgn:name":"Priam",
    "tgn:placetype":[
        "aat:300008347"
    ]
},
  "bbox": [],
  "geometry": {"coordinates":[-95.1333,45.0667],"type":"Point"}
}