{
  "id": 7131542,
  "type": "Feature",
  "properties": {
    "tgn:hierarchy":[
        "tgn:7131542",
        "tgn:1000003",
        "tgn:7003688",
        "tgn:7000084",
        "tgn:7029392"
    ],
    "tgn:id":7131542,
    "tgn:name":"Marienh\u00f6lzung",
    "tgn:placetype":[
        "aat:300008863"
    ]
},
  "bbox": [],
  "geometry": {"coordinates":[9.383333,54.783333],"type":"Point"}
}