<<<<<<< HEAD
{
  "id": 2157142,
  "type": "Feature",
  "properties": {
    "tgn:hierarchy":[
        "tgn:2157142",
        "tgn:1000001",
        "tgn:7006451",
        "tgn:2000092",
        "tgn:7012149",
        "tgn:7029392"
    ],
    "tgn:id":2157142,
    "tgn:name":"Beaver Canyon",
    "tgn:placetype":[
        "aat:300008761"
    ]
},
  "bbox": [],
  "geometry": {"coordinates":[-111.0333,34.3667],"type":"Point"}
}
=======
{"geometry":{"type":"Point","coordinates":[-111.033300,34.366700]},"type":"Feature","properties":{"hierarchy":["tgn:2157142","tgn:1000001","tgn:7006451","tgn:2000092","tgn:7012149","tgn:7029392"],"placetype":["aat:300008761"],"id":2157142,"name:xx":"Beaver Canyon"}}
>>>>>>> 03f74aca74312dbeaf24d7e61306dd6a786dc3d0
