<<<<<<< HEAD
{
  "id": 7471392,
  "type": "Feature",
  "properties": {
    "tgn:hierarchy":[
        "tgn:7471392",
        "tgn:7488858",
        "tgn:1000004",
        "tgn:1000141",
        "tgn:7029392"
    ],
    "tgn:id":7471392,
    "tgn:name":"Zhuoshui Shan",
    "tgn:placetype":[
        "aat:300008798"
    ]
},
  "bbox": [],
  "geometry": {"coordinates":[121.066667,24.134167],"type":"Point"}
}
=======
{"geometry":{"type":"Point","coordinates":[121.066667,24.134167]},"type":"Feature","properties":{"hierarchy":["tgn:7471392","tgn:7488858","tgn:1000004","tgn:1000141","tgn:7029392"],"placetype":["aat:300008798"],"id":7471392,"name:xx":"Zhuoshui Shan"}}
>>>>>>> 03f74aca74312dbeaf24d7e61306dd6a786dc3d0
