{
  "id": 7471392,
  "type": "Feature",
  "properties": {
    "tgn:hierarchy":[
        "tgn:7471392",
        "tgn:7488858",
        "tgn:1000004",
        "tgn:1000141",
        "tgn:7029392"
    ],
    "tgn:id":7471392,
    "tgn:name":"Zhuoshui Shan",
    "tgn:placetype":[
        "aat:300008798"
    ]
},
  "bbox": [],
  "geometry": {"coordinates":[121.066667,24.134167],"type":"Point"}
}