{
  "id": 2689314,
  "type": "Feature",
  "properties": {
    "tgn:hierarchy":[
        "tgn:2689314",
        "tgn:1000001",
        "tgn:7012149",
        "tgn:2001381",
        "tgn:7007525",
        "tgn:7029392"
    ],
    "tgn:id":2689314,
    "tgn:name":"Squaw Creek",
    "tgn:placetype":[
        "aat:300008706"
    ]
},
  "bbox": [],
  "geometry": {"coordinates":[-95.9167,40.7333],"type":"Point"}
}