{
  "id": 2560104,
  "type": "Feature",
  "properties": {
    "tgn:hierarchy":[
        "tgn:2560104",
        "tgn:1000001",
        "tgn:7012149",
        "tgn:2002377",
        "tgn:7007923",
        "tgn:7029392"
    ],
    "tgn:id":2560104,
    "tgn:name":"Oral Reservoir",
    "tgn:placetype":[
        "aat:300006191"
    ]
},
  "bbox": [],
  "geometry": {"coordinates":[-106.6333,42.8333],"type":"Point"}
}