{
  "id": 7307579,
  "type": "Feature",
  "properties": {
    "tgn:hierarchy":[
        "tgn:7307579",
        "tgn:7002807",
        "tgn:1000003",
        "tgn:7003837",
        "tgn:1000095",
        "tgn:7029392"
    ],
    "tgn:id":7307579,
    "tgn:name":"Marigarc\u00eda, Arroyo de",
    "tgn:placetype":[
        "aat:300266554",
        "aat:300008699"
    ]
},
  "bbox": [],
  "geometry": {"coordinates":[-6.05,38.883333],"type":"Point"}
}