{
  "id": 2196410,
  "type": "Feature",
  "properties": {
    "tgn:hierarchy":[
        "tgn:2196410",
        "tgn:1000001",
        "tgn:7012149",
        "tgn:1002423",
        "tgn:7007568",
        "tgn:7029392"
    ],
    "tgn:id":2196410,
    "tgn:name":"Broncks Lake",
    "tgn:placetype":[
        "aat:300006191"
    ]
},
  "bbox": [],
  "geometry": {"coordinates":[-73.8667,42.3333],"type":"Point"}
}