{
  "id": 7563081,
  "type": "Feature",
  "properties": {
    "tgn:hierarchy":[
        "tgn:7563081",
        "tgn:1000004",
        "tgn:7000198",
        "tgn:7016722",
        "tgn:7029392"
    ],
    "tgn:id":7563081,
    "tgn:name:en":"Khorh",
    "tgn:placetype":[
        "aat:300008347"
    ]
},
  "bbox": [],
  "geometry": {"coordinates":[79.128348,26.342752],"type":"Point"}
}