{
  "id": 7393878,
  "type": "Feature",
  "properties": {
    "tgn:hierarchy":[
        "tgn:7393878",
        "tgn:1000001",
        "tgn:1001960",
        "tgn:7005560",
        "tgn:7029392"
    ],
    "tgn:id":7393878,
    "tgn:name":"San Jos\u00e9",
    "tgn:placetype":[
        "aat:300008347"
    ]
},
  "bbox": [],
  "geometry": {"coordinates":[-109.266667,27.033333],"type":"Point"}
}