{
  "id": 7228234,
  "type": "Feature",
  "properties": {
    "tgn:hierarchy":[
        "tgn:7228234",
        "tgn:1042193",
        "tgn:7002705",
        "tgn:1000003",
        "tgn:1000074",
        "tgn:7029392"
    ],
    "tgn:id":7228234,
    "tgn:name":"L\u00edmi, \u00c1kra",
    "tgn:placetype":[
        "aat:300008850"
    ]
},
  "bbox": [],
  "geometry": {"coordinates":[20.716667,38.783333],"type":"Point"}
}