{
  "id": 2098745,
  "type": "Feature",
  "properties": {
    "tgn:hierarchy":[
        "tgn:2098745",
        "tgn:1000001",
        "tgn:7012149",
        "tgn:2001844",
        "tgn:7007825",
        "tgn:7029392"
    ],
    "tgn:id":2098745,
    "tgn:name":"Curlee",
    "tgn:placetype":[
        "aat:300008347",
        "aat:300387210"
    ]
},
  "bbox": [],
  "geometry": {"coordinates":[-86.15,35.7667],"type":"Point"}
}