{
  "id": 2026650,
  "type": "Feature",
  "properties": {
    "tgn:hierarchy":[
        "tgn:2026650",
        "tgn:1000001",
        "tgn:7012149",
        "tgn:7016022",
        "tgn:7007251",
        "tgn:7029392"
    ],
    "tgn:id":2026650,
    "tgn:name":"Bluffside",
    "tgn:placetype":[
        "aat:300008347",
        "aat:300387210"
    ]
},
  "bbox": [],
  "geometry": {"coordinates":[-90.15,38.4833],"type":"Point"}
}