{
  "id": 2743613,
  "type": "Feature",
  "properties": {
    "tgn:hierarchy":[
        "tgn:2743613",
        "tgn:1000001",
        "tgn:2000769",
        "tgn:7012149",
        "tgn:7007255",
        "tgn:7029392"
    ],
    "tgn:id":2743613,
    "tgn:name":"Vaughn Branch",
    "tgn:placetype":[
        "aat:300008699"
    ]
},
  "bbox": [],
  "geometry": {"coordinates":[-83.65,36.85],"type":"Point"}
}