{
  "id": 7428468,
  "type": "Feature",
  "properties": {
    "tgn:hierarchy":[
        "tgn:7428468",
        "tgn:1000001",
        "tgn:7005601",
        "tgn:7005560",
        "tgn:7029392"
    ],
    "tgn:id":7428468,
    "tgn:name":"Noria de Providencia",
    "tgn:placetype":[
        "aat:300008347"
    ]
},
  "bbox": [],
  "geometry": {"coordinates":[-102.533333,24.15],"type":"Point"}
}