{
  "id": 2504918,
  "type": "Feature",
  "properties": {
    "tgn:hierarchy":[
        "tgn:2504918",
        "tgn:1000001",
        "tgn:7012149",
        "tgn:7007158",
        "tgn:2000253",
        "tgn:7029392"
    ],
    "tgn:id":2504918,
    "tgn:name":"Medow Island Ditch Number 1",
    "tgn:placetype":[
        "aat:300006075"
    ]
},
  "bbox": [],
  "geometry": {"coordinates":[-104.85,40.1667],"type":"Point"}
}