{
  "id": 2163157,
  "type": "Feature",
  "properties": {
    "tgn:hierarchy":[
        "tgn:2163157",
        "tgn:7002659",
        "tgn:1000001",
        "tgn:2000004",
        "tgn:7012149",
        "tgn:7029392"
    ],
    "tgn:id":2163157,
    "tgn:name":"Bennett Mine",
    "tgn:placetype":[
        "aat:300000390"
    ]
},
  "bbox": [],
  "geometry": {"coordinates":[-86.4667,33.8833],"type":"Point"}
}