{
  "id": 7259680,
  "type": "Feature",
  "properties": {
    "tgn:hierarchy":[
        "tgn:7259680",
        "tgn:7003460",
        "tgn:1000003",
        "tgn:1000063",
        "tgn:4012014",
        "tgn:7029392"
    ],
    "tgn:id":7259680,
    "tgn:name":"Wedden",
    "tgn:placetype":[
        "aat:300008347"
    ]
},
  "bbox": [],
  "geometry": {"coordinates":[6.166667,50.433333],"type":"Point"}
}