<<<<<<< HEAD
{
  "id": 2768151,
  "type": "Feature",
  "properties": {
    "tgn:hierarchy":[
        "tgn:2768151",
        "tgn:1000001",
        "tgn:7012149",
        "tgn:2000372",
        "tgn:7007248",
        "tgn:7029392"
    ],
    "tgn:id":2768151,
    "tgn:name":"Whites Creek",
    "tgn:placetype":[
        "aat:300008706"
    ]
},
  "bbox": [],
  "geometry": {"coordinates":[-82.4667,32.9167],"type":"Point"}
}
=======
{"geometry":{"type":"Point","coordinates":[-82.466700,32.916700]},"type":"Feature","properties":{"hierarchy":["tgn:2768151","tgn:1000001","tgn:7012149","tgn:2000372","tgn:7007248","tgn:7029392"],"placetype":["aat:300008706"],"id":2768151,"name:xx":"Whites Creek"}}
>>>>>>> 03f74aca74312dbeaf24d7e61306dd6a786dc3d0
