<<<<<<< HEAD
{
  "id": 7114755,
  "type": "Feature",
  "properties": {
    "tgn:hierarchy":[
        "tgn:7114755",
        "tgn:7003669",
        "tgn:1000003",
        "tgn:7000084",
        "tgn:7029392"
    ],
    "tgn:id":7114755,
    "tgn:name":"Oberschellnberg",
    "tgn:placetype":[
        "aat:300000206"
    ]
},
  "bbox": [],
  "geometry": {"coordinates":[12.8,48.95],"type":"Point"}
}
=======
{"geometry":{"type":"Point","coordinates":[12.800000,48.950000]},"type":"Feature","properties":{"hierarchy":["tgn:7114755","tgn:7003669","tgn:1000003","tgn:7000084","tgn:7029392"],"placetype":["aat:300000206"],"id":7114755,"name:xx":"Oberschellnberg"}}
>>>>>>> 03f74aca74312dbeaf24d7e61306dd6a786dc3d0
