{
  "id": 2043011,
  "type": "Feature",
  "properties": {
    "tgn:hierarchy":[
        "tgn:2043011",
        "tgn:1000001",
        "tgn:7012149",
        "tgn:2000878",
        "tgn:7007256",
        "tgn:7029392"
    ],
    "tgn:id":2043011,
    "tgn:name":"Hodge",
    "tgn:placetype":[
        "aat:300008347"
    ]
},
  "bbox": [],
  "geometry": {"coordinates":[-92.7167,32.2667],"type":"Point"}
}