{
  "id": 2199468,
  "type": "Feature",
  "properties": {
    "tgn:hierarchy":[
        "tgn:2199468",
        "tgn:1000001",
        "tgn:7012149",
        "tgn:2001212",
        "tgn:7007523",
        "tgn:7029392"
    ],
    "tgn:id":2199468,
    "tgn:name":"Brush Creek",
    "tgn:placetype":[
        "aat:300008706"
    ]
},
  "bbox": [],
  "geometry": {"coordinates":[-93.8667,39.0333],"type":"Point"}
}