{
  "id": 2381974,
  "type": "Feature",
  "properties": {
    "tgn:hierarchy":[
        "tgn:2381974",
        "tgn:1000001",
        "tgn:7012149",
        "tgn:7014398",
        "tgn:7013961",
        "tgn:7029392"
    ],
    "tgn:id":2381974,
    "tgn:name":"Hayes Gap Run",
    "tgn:placetype":[
        "aat:300008699"
    ]
},
  "bbox": [],
  "geometry": {"coordinates":[-79.25,38.7167],"type":"Point"}
}