{
  "id": 1039790,
  "type": "Feature",
  "properties": {
    "tgn:hierarchy":[
        "tgn:1039790",
        "tgn:7003669",
        "tgn:1000003",
        "tgn:7000084",
        "tgn:7029392"
    ],
    "tgn:id":1039790,
    "tgn:name":"K\u00fchbach",
    "tgn:placetype":[
        "aat:300008347"
    ]
},
  "bbox": [],
  "geometry": {"coordinates":[11.183333,48.483333],"type":"Point"}
}