{
  "id": 2327592,
  "type": "Feature",
  "properties": {
    "tgn:hierarchy":[
        "tgn:2327592",
        "tgn:1000001",
        "tgn:7012149",
        "tgn:7007157",
        "tgn:1002710",
        "tgn:7029392"
    ],
    "tgn:id":2327592,
    "tgn:name":"Fish Creek",
    "tgn:placetype":[
        "aat:300008706"
    ]
},
  "bbox": [],
  "geometry": {"coordinates":[-120.8333,39.3167],"type":"Point"}
}