{
  "id": 2491772,
  "type": "Feature",
  "properties": {
    "tgn:hierarchy":[
        "tgn:2491772",
        "tgn:1000001",
        "tgn:7006451",
        "tgn:2000095",
        "tgn:7012149",
        "tgn:7029392"
    ],
    "tgn:id":2491772,
    "tgn:name":"Maques Place",
    "tgn:placetype":[
        "aat:300008347"
    ]
},
  "bbox": [],
  "geometry": {"coordinates":[-109.35,32.9667],"type":"Point"}
}