{
  "id": 2231349,
  "type": "Feature",
  "properties": {
    "tgn:hierarchy":[
        "tgn:2231349",
        "tgn:1000001",
        "tgn:7006451",
        "tgn:2000092",
        "tgn:7012149",
        "tgn:7029392"
    ],
    "tgn:id":2231349,
    "tgn:name":"Chair Crossing",
    "tgn:placetype":[
        "aat:300008347"
    ]
},
  "bbox": [],
  "geometry": {"coordinates":[-111.5833,36.8667],"type":"Point"}
}