{
  "id": 7500747,
  "type": "Feature",
  "properties": {
    "tgn:hierarchy":[
        "tgn:7500747",
        "tgn:7487020",
        "tgn:1000004",
        "tgn:1000141",
        "tgn:7029392"
    ],
    "tgn:id":7500747,
    "tgn:name":"Tudigongbu",
    "tgn:placetype":[
        "aat:300008347"
    ]
},
  "bbox": [],
  "geometry": {"coordinates":[120.715,24.469444],"type":"Point"}
}