<<<<<<< HEAD
{
  "id": 2406214,
  "type": "Feature",
  "properties": {
    "tgn:hierarchy":[
        "tgn:2406214",
        "tgn:7006450",
        "tgn:1000001",
        "tgn:7012149",
        "tgn:2124005",
        "tgn:7029392"
    ],
    "tgn:id":2406214,
    "tgn:name":"Humphery Point",
    "tgn:placetype":[
        "aat:300008850"
    ]
},
  "bbox": [],
  "geometry": {"coordinates":[-142.5167,69.9667],"type":"Point"}
}
=======
{"geometry":{"type":"Point","coordinates":[-142.516700,69.966700]},"type":"Feature","properties":{"hierarchy":["tgn:2406214","tgn:7006450","tgn:1000001","tgn:7012149","tgn:2124005","tgn:7029392"],"placetype":["aat:300008850"],"id":2406214,"name:xx":"Humphery Point"}}
>>>>>>> 03f74aca74312dbeaf24d7e61306dd6a786dc3d0
