{
  "id": 1081507,
  "type": "Feature",
  "properties": {
    "tgn:hierarchy":[
        "tgn:1081507",
        "tgn:7016687",
        "tgn:1000004",
        "tgn:7000893",
        "tgn:1000120",
        "tgn:7029392"
    ],
    "tgn:id":1081507,
    "tgn:name":"Taneichi",
    "tgn:placetype":[
        "aat:300008347"
    ]
},
  "bbox": [],
  "geometry": {"coordinates":[141.7333,40.3833],"type":"Point"}
}