{
  "id": 1076037,
  "type": "Feature",
  "properties": {
    "tgn:hierarchy":[
        "tgn:1076037",
        "tgn:1000004",
        "tgn:7000198",
        "tgn:1001977",
        "tgn:7029392"
    ],
    "tgn:id":1076037,
    "tgn:name:en":"Low\u0101da",
    "tgn:placetype":[
        "aat:300008347"
    ]
},
  "bbox": [],
  "geometry": {"coordinates":[87.615884,22.448744],"type":"Point"}
}