{
  "id": 7392623,
  "type": "Feature",
  "properties": {
    "tgn:hierarchy":[
        "tgn:7392623",
        "tgn:1000001",
        "tgn:7005600",
        "tgn:7005560",
        "tgn:7029392"
    ],
    "tgn:id":7392623,
    "tgn:name":"Sacchich",
    "tgn:placetype":[
        "aat:300008347"
    ]
},
  "bbox": [],
  "geometry": {"coordinates":[-89.45,20.816667],"type":"Point"}
}