{
  "id": 2733633,
  "type": "Feature",
  "properties": {
    "tgn:hierarchy":[
        "tgn:2733633",
        "tgn:1000001",
        "tgn:7012149",
        "tgn:2001887",
        "tgn:7007825",
        "tgn:7029392"
    ],
    "tgn:id":2733633,
    "tgn:name":"Turnbow Hollow",
    "tgn:placetype":[
        "aat:300008761"
    ]
},
  "bbox": [],
  "geometry": {"coordinates":[-87.6833,35.55],"type":"Point"}
}