{
  "id": 2451813,
  "type": "Feature",
  "properties": {
    "tgn:hierarchy":[
        "tgn:2451813",
        "tgn:1000001",
        "tgn:2000458",
        "tgn:7012149",
        "tgn:7007250",
        "tgn:7029392"
    ],
    "tgn:id":2451813,
    "tgn:name":"Little Beaver Creek",
    "tgn:placetype":[
        "aat:300008706"
    ]
},
  "bbox": [],
  "geometry": {"coordinates":[-114.8333,43.85],"type":"Point"}
}