{
  "id": 2115021,
  "type": "Feature",
  "properties": {
    "tgn:hierarchy":[
        "tgn:2115021",
        "tgn:1000001",
        "tgn:7012149",
        "tgn:2002190",
        "tgn:7007919",
        "tgn:7029392"
    ],
    "tgn:id":2115021,
    "tgn:name":"Wheatfield",
    "tgn:placetype":[
        "aat:300008347"
    ]
},
  "bbox": [],
  "geometry": {"coordinates":[-78.3667,39.0667],"type":"Point"}
}