{
  "id": 2257856,
  "type": "Feature",
  "properties": {
    "tgn:hierarchy":[
        "tgn:2257856",
        "tgn:1000001",
        "tgn:7012149",
        "tgn:7007157",
        "tgn:1002869",
        "tgn:7029392"
    ],
    "tgn:id":2257856,
    "tgn:name":"Corralitos Creek",
    "tgn:placetype":[
        "aat:300008706"
    ]
},
  "bbox": [],
  "geometry": {"coordinates":[-121.8333,37.0667],"type":"Point"}
}