{
  "id": 7471786,
  "type": "Feature",
  "properties": {
    "tgn:hierarchy":[
        "tgn:7471786",
        "tgn:1000004",
        "tgn:7491221",
        "tgn:1000141",
        "tgn:7029392"
    ],
    "tgn:id":7471786,
    "tgn:name":"Xinxitou",
    "tgn:placetype":[
        "aat:300008773"
    ]
},
  "bbox": [],
  "geometry": {"coordinates":[121.039444,23.130833],"type":"Point"}
}