{
  "id": 7536969,
  "type": "Feature",
  "properties": {
    "tgn:hierarchy":[
        "tgn:7536969",
        "tgn:7001242",
        "tgn:1001059",
        "tgn:7016833",
        "tgn:7029392"
    ],
    "tgn:id":7536969,
    "tgn:name:en":"Kut\u0101mah ash Sharq\u012byah",
    "tgn:placetype":[
        "aat:300008347"
    ]
},
  "bbox": [],
  "geometry": {"coordinates":[31.422936,31.140496],"type":"Point"}
}