{
  "id": 2387544,
  "type": "Feature",
  "properties": {
    "tgn:hierarchy":[
        "tgn:2387544",
        "tgn:1000001",
        "tgn:2000469",
        "tgn:7012149",
        "tgn:7007250",
        "tgn:7029392"
    ],
    "tgn:id":2387544,
    "tgn:name":"Heywood Creek",
    "tgn:placetype":[
        "aat:300008706"
    ]
},
  "bbox": [],
  "geometry": {"coordinates":[-115.8333,46.4167],"type":"Point"}
}