{
  "id": 2210114,
  "type": "Feature",
  "properties": {
    "tgn:hierarchy":[
        "tgn:2210114",
        "tgn:1000001",
        "tgn:7012149",
        "tgn:1003044",
        "tgn:7007708",
        "tgn:7029392"
    ],
    "tgn:id":2210114,
    "tgn:name":"Burton Ridge",
    "tgn:placetype":[
        "aat:300266640"
    ]
},
  "bbox": [],
  "geometry": {"coordinates":[-123.5667,45.15],"type":"Point"}
}