{
  "id": 7292485,
  "type": "Feature",
  "properties": {
    "tgn:hierarchy":[
        "tgn:7292485",
        "tgn:1001630",
        "tgn:1000049",
        "tgn:1000002",
        "tgn:7029392"
    ],
    "tgn:id":7292485,
    "tgn:name":"Faro",
    "tgn:placetype":[
        "aat:300004792"
    ]
},
  "bbox": [],
  "geometry": {"coordinates":[-71.25,-28.45],"type":"Point"}
}