{
  "id": 1104170,
  "type": "Feature",
  "properties": {
    "tgn:hierarchy":[
        "tgn:1104170",
        "tgn:1000001",
        "tgn:7012149",
        "tgn:1002440",
        "tgn:7007568",
        "tgn:7029392"
    ],
    "tgn:id":1104170,
    "tgn:name":"Cathead Mountain",
    "tgn:placetype":[
        "aat:300008795"
    ]
},
  "bbox": [],
  "geometry": {"coordinates":[-74.2833,43.2833],"type":"Point"}
}