{
  "id": 2128733,
  "type": "Feature",
  "properties": {
    "tgn:hierarchy":[
        "tgn:2128733",
        "tgn:1000001",
        "tgn:2001263",
        "tgn:7012149",
        "tgn:7007524",
        "tgn:7029392"
    ],
    "tgn:id":2128733,
    "tgn:name":"Aldrich Spring",
    "tgn:placetype":[
        "aat:300008697"
    ]
},
  "bbox": [],
  "geometry": {"coordinates":[-111.7333,46.2667],"type":"Point"}
}