{
  "id": 2417826,
  "type": "Feature",
  "properties": {
    "tgn:hierarchy":[
        "tgn:2417826",
        "tgn:1000001",
        "tgn:7012149",
        "tgn:2001254",
        "tgn:7007523",
        "tgn:7029392"
    ],
    "tgn:id":2417826,
    "tgn:name":"Jackson Hollow",
    "tgn:placetype":[
        "aat:300008761"
    ]
},
  "bbox": [],
  "geometry": {"coordinates":[-90.9167,38.1167],"type":"Point"}
}