{
  "id": 2295104,
  "type": "Feature",
  "properties": {
    "tgn:hierarchy":[
        "tgn:2295104",
        "tgn:1000001",
        "tgn:7012149",
        "tgn:7014612",
        "tgn:7007568",
        "tgn:7029392"
    ],
    "tgn:id":2295104,
    "tgn:name":"Dream Lake",
    "tgn:placetype":[
        "aat:300008680"
    ]
},
  "bbox": [],
  "geometry": {"coordinates":[-73.8167,41.2167],"type":"Point"}
}