{
  "id": 5001961,
  "type": "Feature",
  "properties": {
    "tgn:hierarchy":[
        "tgn:5001961",
        "tgn:7002690",
        "tgn:7012056",
        "tgn:1000003",
        "tgn:1000074",
        "tgn:7029392"
    ],
    "tgn:id":5001961,
    "tgn:name":"Prini\u00e1s",
    "tgn:placetype":[
        "aat:300008347",
        "aat:300000810",
        "aat:300016967",
        "aat:300019275",
        "aat:300020101",
        "aat:300008372"
    ]
},
  "bbox": [],
  "geometry": {"coordinates":[22.716667,39.65],"type":"Point"}
}