{
  "id": 7314742,
  "type": "Feature",
  "properties": {
    "tgn:hierarchy":[
        "tgn:7314742",
        "tgn:1001699",
        "tgn:1000049",
        "tgn:1000002",
        "tgn:7029392"
    ],
    "tgn:id":7314742,
    "tgn:name":"Lili, Punta",
    "tgn:placetype":[
        "aat:300386846"
    ]
},
  "bbox": [],
  "geometry": {"coordinates":[-73.65,-43.183333],"type":"Point"}
}