{
  "id": 1014305,
  "type": "Feature",
  "properties": {
    "tgn:hierarchy":[
        "tgn:1014305",
        "tgn:7005685",
        "tgn:7005807",
        "tgn:1000001",
        "tgn:7005801",
        "tgn:7029392"
    ],
    "tgn:id":1014305,
    "tgn:name":"Roddickton",
    "tgn:placetype":[
        "aat:300008347"
    ]
},
  "bbox": [],
  "geometry": {"coordinates":[-56.1333,50.85],"type":"Point"}
}