{
  "id": 7411836,
  "type": "Feature",
  "properties": {
    "tgn:hierarchy":[
        "tgn:7411836",
        "tgn:7005587",
        "tgn:1000001",
        "tgn:7005560",
        "tgn:7029392"
    ],
    "tgn:id":7411836,
    "tgn:name:es":"Atlapexco, R\u00edo",
    "tgn:placetype":[
        "aat:300008699"
    ]
},
  "bbox": [],
  "geometry": {"coordinates":[-98.368056,20.897222],"type":"Point"}
}