{
  "id": 7560648,
  "type": "Feature",
  "properties": {
    "tgn:hierarchy":[
        "tgn:7560648",
        "tgn:1000004",
        "tgn:7000198",
        "tgn:7016722",
        "tgn:7029392"
    ],
    "tgn:id":7560648,
    "tgn:name:en":"Bandha ka Purwa",
    "tgn:placetype":[
        "aat:300008347"
    ]
},
  "bbox": [],
  "geometry": {"coordinates":[79.330803,26.490906],"type":"Point"}
}