<<<<<<< HEAD
{
  "id": 7366827,
  "type": "Feature",
  "properties": {
    "tgn:hierarchy":[
        "tgn:7366827",
        "tgn:1000001",
        "tgn:7005589",
        "tgn:7005560",
        "tgn:7029392"
    ],
    "tgn:id":7366827,
    "tgn:name":"El Toro",
    "tgn:placetype":[
        "aat:300008347"
    ]
},
  "bbox": [],
  "geometry": {"coordinates":[-98.75,25.283333],"type":"Point"}
}
=======
{"geometry":{"type":"Point","coordinates":[-98.750000,25.283333]},"type":"Feature","properties":{"hierarchy":["tgn:7366827","tgn:1000001","tgn:7005589","tgn:7005560","tgn:7029392"],"placetype":["aat:300008347"],"id":7366827,"name:xx":"El Toro"}}
>>>>>>> 03f74aca74312dbeaf24d7e61306dd6a786dc3d0
