{
  "id": 2155305,
  "type": "Feature",
  "properties": {
    "tgn:hierarchy":[
        "tgn:2155305",
        "tgn:1000001",
        "tgn:1002260",
        "tgn:7012149",
        "tgn:7007920",
        "tgn:7029392"
    ],
    "tgn:id":2155305,
    "tgn:name":"Bear Mountain",
    "tgn:placetype":[
        "aat:300008798"
    ]
},
  "bbox": [],
  "geometry": {"coordinates":[-120.15,47.8167],"type":"Point"}
}