{
  "id": 2750423,
  "type": "Feature",
  "properties": {
    "tgn:hierarchy":[
        "tgn:2750423",
        "tgn:1000001",
        "tgn:1002601",
        "tgn:7012149",
        "tgn:7007159",
        "tgn:7029392"
    ],
    "tgn:id":2750423,
    "tgn:name":"Wangum Lake Brook",
    "tgn:placetype":[
        "aat:300008699"
    ]
},
  "bbox": [],
  "geometry": {"coordinates":[-73.2667,41.9667],"type":"Point"}
}