{
  "id": 7279115,
  "type": "Feature",
  "properties": {
    "tgn:hierarchy":[
        "tgn:7279115",
        "tgn:1001702",
        "tgn:1000049",
        "tgn:1000002",
        "tgn:7029392"
    ],
    "tgn:id":7279115,
    "tgn:name":"Rowe, Punta",
    "tgn:placetype":[
        "aat:300386846"
    ]
},
  "bbox": [],
  "geometry": {"coordinates":[-72.383333,-53.566667],"type":"Point"}
}