{
  "id": 1132666,
  "type": "Feature",
  "properties": {
    "tgn:hierarchy":[
        "tgn:1132666",
        "tgn:1000001",
        "tgn:7012149",
        "tgn:7007706",
        "tgn:7029392"
    ],
    "tgn:id":1132666,
    "tgn:name":"Caesar Creek",
    "tgn:placetype":[
        "aat:300008706"
    ]
},
  "bbox": [],
  "geometry": {"coordinates":[-83.6667,39.6833],"type":"Point"}
}