<<<<<<< HEAD
{
  "id": 7020296,
  "type": "Feature",
  "properties": {
    "tgn:hierarchy":[
        "tgn:7020296",
        "tgn:1000001",
        "tgn:7012149",
        "tgn:2001508",
        "tgn:7007709",
        "tgn:7029392"
    ],
    "tgn:id":7020296,
    "tgn:name":"Wolf Creek Reservoir",
    "tgn:placetype":[
        "aat:300006191"
    ]
},
  "bbox": [],
  "geometry": {"coordinates":[-83.0,35.2167],"type":"Point"}
}
=======
{"geometry":{"type":"Point","coordinates":[-83.000000,35.216700]},"type":"Feature","properties":{"hierarchy":["tgn:7020296","tgn:1000001","tgn:7012149","tgn:2001508","tgn:7007709","tgn:7029392"],"placetype":["aat:300006191"],"id":7020296,"name:xx":"Wolf Creek Reservoir"}}
>>>>>>> 03f74aca74312dbeaf24d7e61306dd6a786dc3d0
