{
  "id": 2012167,
  "type": "Feature",
  "properties": {
    "tgn:hierarchy":[
        "tgn:2012167",
        "tgn:1000001",
        "tgn:7012149",
        "tgn:7007157",
        "tgn:1002684",
        "tgn:7029392"
    ],
    "tgn:id":2012167,
    "tgn:name":"Las Lomas",
    "tgn:placetype":[
        "aat:300008347"
    ]
},
  "bbox": [],
  "geometry": {"coordinates":[-121.7333,36.85],"type":"Point"}
}