{
  "id": 2719674,
  "type": "Feature",
  "properties": {
    "tgn:hierarchy":[
        "tgn:2719674",
        "tgn:7002659",
        "tgn:1000001",
        "tgn:2000009",
        "tgn:7012149",
        "tgn:7029392"
    ],
    "tgn:id":2719674,
    "tgn:name":"Three Mile Creek",
    "tgn:placetype":[
        "aat:300008706"
    ]
},
  "bbox": [],
  "geometry": {"coordinates":[-85.5333,34.1333],"type":"Point"}
}