<<<<<<< HEAD
{
  "id": 2408446,
  "type": "Feature",
  "properties": {
    "tgn:hierarchy":[
        "tgn:2408446",
        "tgn:1002300",
        "tgn:1000001",
        "tgn:7012149",
        "tgn:7007564",
        "tgn:7029392"
    ],
    "tgn:id":2408446,
    "tgn:name":"Hutchins Mountain",
    "tgn:placetype":[
        "aat:300008798"
    ]
},
  "bbox": [],
  "geometry": {"coordinates":[-71.45,44.5333],"type":"Point"}
}
=======
{"geometry":{"type":"Point","coordinates":[-71.450000,44.533300]},"type":"Feature","properties":{"hierarchy":["tgn:2408446","tgn:1002300","tgn:1000001","tgn:7012149","tgn:7007564","tgn:7029392"],"placetype":["aat:300008798"],"id":2408446,"name:xx":"Hutchins Mountain"}}
>>>>>>> 03f74aca74312dbeaf24d7e61306dd6a786dc3d0
