{
  "id": 7140899,
  "type": "Feature",
  "properties": {
    "tgn:hierarchy":[
        "tgn:7140899",
        "tgn:1000003",
        "tgn:7003678",
        "tgn:7000084",
        "tgn:7029392"
    ],
    "tgn:id":7140899,
    "tgn:name":"L\u00fcstefeld",
    "tgn:placetype":[
        "aat:300000206"
    ]
},
  "bbox": [],
  "geometry": {"coordinates":[10.116667,51.066667],"type":"Point"}
}