{
  "id": 7347252,
  "type": "Feature",
  "properties": {
    "tgn:hierarchy":[
        "tgn:7347252",
        "tgn:7002810",
        "tgn:7001158",
        "tgn:1000003",
        "tgn:1000095",
        "tgn:7029392"
    ],
    "tgn:id":7347252,
    "tgn:name":"Ascarza",
    "tgn:placetype":[
        "aat:300008347"
    ]
},
  "bbox": [],
  "geometry": {"coordinates":[-2.706642,42.76162],"type":"Point"}
}