{
  "id": 7232924,
  "type": "Feature",
  "properties": {
    "tgn:hierarchy":[
        "tgn:7232924",
        "tgn:7002681",
        "tgn:7001395",
        "tgn:1000003",
        "tgn:1000074",
        "tgn:7029392"
    ],
    "tgn:id":7232924,
    "tgn:name":"Ili\u00f3kastron",
    "tgn:placetype":[
        "aat:300008347"
    ]
},
  "bbox": [],
  "geometry": {"coordinates":[23.266515,37.44689],"type":"Point"}
}