{
  "id": 2405803,
  "type": "Feature",
  "properties": {
    "tgn:hierarchy":[
        "tgn:2405803",
        "tgn:1000001",
        "tgn:7012149",
        "tgn:2000216",
        "tgn:7007158",
        "tgn:7029392"
    ],
    "tgn:id":2405803,
    "tgn:name":"Hull Creek",
    "tgn:placetype":[
        "aat:300008706"
    ]
},
  "bbox": [],
  "geometry": {"coordinates":[-105.9667,39.9333],"type":"Point"}
}