{
  "id": 2418993,
  "type": "Feature",
  "properties": {
    "tgn:hierarchy":[
        "tgn:2418993",
        "tgn:1000001",
        "tgn:7012149",
        "tgn:2000412",
        "tgn:7007248",
        "tgn:7029392"
    ],
    "tgn:id":2418993,
    "tgn:name":"James Pond",
    "tgn:placetype":[
        "aat:300006191"
    ]
},
  "bbox": [],
  "geometry": {"coordinates":[-82.15,33.3333],"type":"Point"}
}