{
  "id": 7434380,
  "type": "Feature",
  "properties": {
    "tgn:hierarchy":[
        "tgn:7434380",
        "tgn:7005581",
        "tgn:1000001",
        "tgn:7005560",
        "tgn:7029392"
    ],
    "tgn:id":7434380,
    "tgn:name":"Rancho Tres Hermanos",
    "tgn:placetype":[
        "aat:300000241"
    ]
},
  "bbox": [],
  "geometry": {"coordinates":[-105.65,26.816667],"type":"Point"}
}