{
  "id": 2648767,
  "type": "Feature",
  "properties": {
    "tgn:hierarchy":[
        "tgn:2648767",
        "tgn:1000001",
        "tgn:2002134",
        "tgn:7012149",
        "tgn:7007828",
        "tgn:7029392"
    ],
    "tgn:id":2648767,
    "tgn:name":"Scotch Hollow",
    "tgn:placetype":[
        "aat:300008761"
    ]
},
  "bbox": [],
  "geometry": {"coordinates":[-72.1333,44.15],"type":"Point"}
}