{
  "id": 7266060,
  "type": "Feature",
  "properties": {
    "tgn:concordances":{
        "gn:id":"2754780"
    },
    "tgn:hierarchy":[
        "tgn:7266060",
        "tgn:1000003",
        "tgn:7003622",
        "tgn:7016845",
        "tgn:7029392"
    ],
    "tgn:id":7266060,
    "tgn:name:nl":"Hasselt",
    "tgn:placetype":[
        "aat:300008347"
    ]
},
  "bbox": [],
  "geometry": {"coordinates":[6.166667,51.433333],"type":"Point"}
}