{
  "id": 2477275,
  "type": "Feature",
  "properties": {
    "tgn:hierarchy":[
        "tgn:2477275",
        "tgn:1000001",
        "tgn:7012149",
        "tgn:2000521",
        "tgn:7007251",
        "tgn:7029392"
    ],
    "tgn:id":2477275,
    "tgn:name":"Lynnhurst, Lake",
    "tgn:placetype":[
        "aat:300006191"
    ]
},
  "bbox": [],
  "geometry": {"coordinates":[-89.6667,40.7667],"type":"Point"}
}