{
  "id": 2473291,
  "type": "Feature",
  "properties": {
    "tgn:hierarchy":[
        "tgn:2473291",
        "tgn:1000001",
        "tgn:7012149",
        "tgn:2002118",
        "tgn:7007827",
        "tgn:7029392"
    ],
    "tgn:id":2473291,
    "tgn:name":"Lower Bells Canyon Reservoir",
    "tgn:placetype":[
        "aat:300006191"
    ]
},
  "bbox": [],
  "geometry": {"coordinates":[-111.7833,40.55],"type":"Point"}
}