{
  "id": 7566946,
  "type": "Feature",
  "properties": {
    "tgn:hierarchy":[
        "tgn:7566946",
        "tgn:1000004",
        "tgn:7000198",
        "tgn:7031786",
        "tgn:7029392"
    ],
    "tgn:id":7566946,
    "tgn:name:en":"P\u0101li Malli",
    "tgn:placetype":[
        "aat:300008347"
    ]
},
  "bbox": [],
  "geometry": {"coordinates":[78.658504,29.865654],"type":"Point"}
}