{
  "id": 7468722,
  "type": "Feature",
  "properties": {
    "tgn:hierarchy":[
        "tgn:7468722",
        "tgn:7487020",
        "tgn:1000004",
        "tgn:1000141",
        "tgn:7029392"
    ],
    "tgn:id":7468722,
    "tgn:name":"Fengzikeng",
    "tgn:placetype":[
        "aat:300008347"
    ]
},
  "bbox": [],
  "geometry": {"coordinates":[120.838493,24.479047],"type":"Point"}
}