{
  "id": 1120470,
  "type": "Feature",
  "properties": {
    "tgn:hierarchy":[
        "tgn:1120470",
        "tgn:7000490",
        "tgn:1000006",
        "tgn:7006238",
        "tgn:7029392"
    ],
    "tgn:id":1120470,
    "tgn:name":"Silvan Reservoir",
    "tgn:placetype":[
        "aat:300006191"
    ]
},
  "bbox": [],
  "geometry": {"coordinates":[145.4167,-37.8333],"type":"Point"}
}