{
  "id": 7295301,
  "type": "Feature",
  "properties": {
    "tgn:hierarchy":[
        "tgn:7295301",
        "tgn:7002813",
        "tgn:7002758",
        "tgn:1000003",
        "tgn:1000095",
        "tgn:7029392"
    ],
    "tgn:id":7295301,
    "tgn:name":"Sables, Roca de los",
    "tgn:placetype":[
        "aat:300011692"
    ]
},
  "bbox": [],
  "geometry": {"coordinates":[-5.433333,36.093056],"type":"Point"}
}