{
  "id": 2490767,
  "type": "Feature",
  "properties": {
    "tgn:hierarchy":[
        "tgn:2490767",
        "tgn:2000257",
        "tgn:1000001",
        "tgn:7012149",
        "tgn:7007240",
        "tgn:7029392"
    ],
    "tgn:id":2490767,
    "tgn:name":"Manns Spur",
    "tgn:placetype":[
        "aat:300008347"
    ]
},
  "bbox": [],
  "geometry": {"coordinates":[-82.3167,30.2333],"type":"Point"}
}