{
  "id": 1131489,
  "type": "Feature",
  "properties": {
    "tgn:hierarchy":[
        "tgn:1131489",
        "tgn:7002872",
        "tgn:1000003",
        "tgn:1000070",
        "tgn:7029392"
    ],
    "tgn:id":1131489,
    "tgn:name":"Vire",
    "tgn:placetype":[
        "aat:300008707"
    ]
},
  "bbox": [],
  "geometry": {"coordinates":[-1.0833,49.3333],"type":"Point"}
}