{
  "id": 7110155,
  "type": "Feature",
  "properties": {
    "tgn:hierarchy":[
        "tgn:7110155",
        "tgn:1000003",
        "tgn:7000094",
        "tgn:7000084",
        "tgn:7029392"
    ],
    "tgn:id":7110155,
    "tgn:name":"Ramelow",
    "tgn:placetype":[
        "aat:300008347"
    ]
},
  "bbox": [],
  "geometry": {"coordinates":[13.483333,53.733333],"type":"Point"}
}