{
  "id": 2014962,
  "type": "Feature",
  "properties": {
    "tgn:hierarchy":[
        "tgn:2014962",
        "tgn:1000001",
        "tgn:7012149",
        "tgn:7007157",
        "tgn:1002828",
        "tgn:7029392"
    ],
    "tgn:id":2014962,
    "tgn:name":"White Water",
    "tgn:placetype":[
        "aat:300008347"
    ]
},
  "bbox": [],
  "geometry": {"coordinates":[-116.6333,33.9167],"type":"Point"}
}