{
  "id": 2621996,
  "type": "Feature",
  "properties": {
    "tgn:hierarchy":[
        "tgn:2621996",
        "tgn:1000001",
        "tgn:7012149",
        "tgn:2001898",
        "tgn:7007825",
        "tgn:7029392"
    ],
    "tgn:id":2621996,
    "tgn:name":"Roberts Branch",
    "tgn:placetype":[
        "aat:300008699"
    ]
},
  "bbox": [],
  "geometry": {"coordinates":[-84.2167,35.35],"type":"Point"}
}