{
  "id": 7154338,
  "type": "Feature",
  "properties": {
    "tgn:hierarchy":[
        "tgn:7154338",
        "tgn:1000003",
        "tgn:7003677",
        "tgn:7000084",
        "tgn:7029392"
    ],
    "tgn:id":7154338,
    "tgn:name":"Kaplans Kuhlen",
    "tgn:placetype":[
        "aat:300008680"
    ]
},
  "bbox": [],
  "geometry": {"coordinates":[6.483333,51.466667],"type":"Point"}
}