{
  "id": 7529181,
  "type": "Feature",
  "properties": {
    "tgn:hierarchy":[
        "tgn:7529181",
        "tgn:7001242",
        "tgn:1001059",
        "tgn:7016833",
        "tgn:7029392"
    ],
    "tgn:id":7529181,
    "tgn:name":"Tur'at Ma\u1e29b\u016bbah",
    "tgn:placetype":[
        "aat:300006075"
    ]
},
  "bbox": [],
  "geometry": {"coordinates":[31.567761,30.857518],"type":"Point"}
}