{
  "id": 2476998,
  "type": "Feature",
  "properties": {
    "tgn:hierarchy":[
        "tgn:2476998",
        "tgn:1000001",
        "tgn:7012149",
        "tgn:2002061",
        "tgn:7007826",
        "tgn:7029392"
    ],
    "tgn:id":2476998,
    "tgn:name":"Lynch Creek",
    "tgn:placetype":[
        "aat:300008706"
    ]
},
  "bbox": [],
  "geometry": {"coordinates":[-95.05,33.5833],"type":"Point"}
}