{
  "id": 2330892,
  "type": "Feature",
  "properties": {
    "tgn:hierarchy":[
        "tgn:2330892",
        "tgn:7002659",
        "tgn:1000001",
        "tgn:7012149",
        "tgn:2000039",
        "tgn:7029392"
    ],
    "tgn:id":2330892,
    "tgn:name":"Flat Rock",
    "tgn:placetype":[
        "aat:300008798"
    ]
},
  "bbox": [],
  "geometry": {"coordinates":[-87.2167,34.5833],"type":"Point"}
}