<<<<<<< HEAD
{
  "id": 2330892,
  "type": "Feature",
  "properties": {
    "tgn:hierarchy":[
        "tgn:2330892",
        "tgn:7002659",
        "tgn:1000001",
        "tgn:7012149",
        "tgn:2000039",
        "tgn:7029392"
    ],
    "tgn:id":2330892,
    "tgn:name":"Flat Rock",
    "tgn:placetype":[
        "aat:300008798"
    ]
},
  "bbox": [],
  "geometry": {"coordinates":[-87.2167,34.5833],"type":"Point"}
}
=======
{"geometry":{"type":"Point","coordinates":[-87.216700,34.583300]},"type":"Feature","properties":{"hierarchy":["tgn:2330892","tgn:7002659","tgn:1000001","tgn:7012149","tgn:2000039","tgn:7029392"],"placetype":["aat:300008798"],"id":2330892,"name:xx":"Flat Rock"}}
>>>>>>> 03f74aca74312dbeaf24d7e61306dd6a786dc3d0
