{
  "id": 2529027,
  "type": "Feature",
  "properties": {
    "tgn:hierarchy":[
        "tgn:2529027",
        "tgn:1000001",
        "tgn:7012149",
        "tgn:1002771",
        "tgn:7007826",
        "tgn:7029392"
    ],
    "tgn:id":2529027,
    "tgn:name":"Mud Creek",
    "tgn:placetype":[
        "aat:300008706"
    ]
},
  "bbox": [],
  "geometry": {"coordinates":[-97.75,32.5667],"type":"Point"}
}