{
  "id": 2302342,
  "type": "Feature",
  "properties": {
    "tgn:hierarchy":[
        "tgn:2302342",
        "tgn:1000001",
        "tgn:7012149",
        "tgn:2000512",
        "tgn:7007251",
        "tgn:7029392"
    ],
    "tgn:id":2302342,
    "tgn:name":"Dutch Ridge",
    "tgn:placetype":[
        "aat:300266640"
    ]
},
  "bbox": [],
  "geometry": {"coordinates":[-89.2833,37.6333],"type":"Point"}
}