{
  "id": 2580213,
  "type": "Feature",
  "properties": {
    "tgn:hierarchy":[
        "tgn:2580213",
        "tgn:2001089",
        "tgn:1000001",
        "tgn:7012149",
        "tgn:7007522",
        "tgn:7029392"
    ],
    "tgn:id":2580213,
    "tgn:name":"Pierces Chapel",
    "tgn:placetype":[
        "aat:300008347"
    ]
},
  "bbox": [],
  "geometry": {"coordinates":[-89.55,33.15],"type":"Point"}
}