{
  "id": 2729770,
  "type": "Feature",
  "properties": {
    "tgn:hierarchy":[
        "tgn:2729770",
        "tgn:1000001",
        "tgn:7012149",
        "tgn:2001720",
        "tgn:7007708",
        "tgn:7029392"
    ],
    "tgn:id":2729770,
    "tgn:name":"Trough Spring",
    "tgn:placetype":[
        "aat:300008697"
    ]
},
  "bbox": [],
  "geometry": {"coordinates":[-118.7333,45.15],"type":"Point"}
}