{
  "id": 7252996,
  "type": "Feature",
  "properties": {
    "tgn:hierarchy":[
        "tgn:7252996",
        "tgn:7003460",
        "tgn:1000003",
        "tgn:1000063",
        "tgn:4012014",
        "tgn:7029392"
    ],
    "tgn:id":7252996,
    "tgn:name":"Saint-Vith, Bois de",
    "tgn:placetype":[
        "aat:300008863"
    ]
},
  "bbox": [],
  "geometry": {"coordinates":[6.185278,50.28],"type":"Point"}
}