{
  "id": 7228818,
  "type": "Feature",
  "properties": {
    "tgn:hierarchy":[
        "tgn:7228818",
        "tgn:7011270",
        "tgn:7002674",
        "tgn:1000003",
        "tgn:1000074",
        "tgn:7029392"
    ],
    "tgn:id":7228818,
    "tgn:name":"Kark\u00e1dhos",
    "tgn:placetype":[
        "aat:300008347"
    ]
},
  "bbox": [],
  "geometry": {"coordinates":[25.116667,37.616667],"type":"Point"}
}