{
  "id": 7035504,
  "type": "Feature",
  "properties": {
    "tgn:hierarchy":[
        "tgn:7035504",
        "tgn:1003506",
        "tgn:1000003",
        "tgn:7002993",
        "tgn:1000080",
        "tgn:7029392"
    ],
    "tgn:id":7035504,
    "tgn:name":"Modeon del Buinz",
    "tgn:placetype":[
        "aat:300008795"
    ]
},
  "bbox": [],
  "geometry": {"coordinates":[13.474444,46.421667],"type":"Point"}
}