<<<<<<< HEAD
{
  "id": 7470912,
  "type": "Feature",
  "properties": {
    "tgn:hierarchy":[
        "tgn:7470912",
        "tgn:7498210",
        "tgn:1000004",
        "tgn:1000141",
        "tgn:7029392"
    ],
    "tgn:id":7470912,
    "tgn:name":"Erchong Shan",
    "tgn:placetype":[
        "aat:300008777"
    ]
},
  "bbox": [],
  "geometry": {"coordinates":[120.499872,26.369842],"type":"Point"}
}
=======
{"geometry":{"type":"Point","coordinates":[120.499872,26.369842]},"type":"Feature","properties":{"hierarchy":["tgn:7470912","tgn:7498210","tgn:1000004","tgn:1000141","tgn:7029392"],"placetype":["aat:300008777"],"id":7470912,"name:xx":"Erchong Shan"}}
>>>>>>> 03f74aca74312dbeaf24d7e61306dd6a786dc3d0
