<<<<<<< HEAD
{
  "id": 7170409,
  "type": "Feature",
  "properties": {
    "tgn:hierarchy":[
        "tgn:7170409",
        "tgn:7003692",
        "tgn:1000003",
        "tgn:7000084",
        "tgn:7029392"
    ],
    "tgn:id":7170409,
    "tgn:name":"Hinterbach",
    "tgn:placetype":[
        "aat:300387200"
    ]
},
  "bbox": [],
  "geometry": {"coordinates":[8.316667,48.233333],"type":"Point"}
}
=======
{"geometry":{"type":"Point","coordinates":[8.316667,48.233333]},"type":"Feature","properties":{"hierarchy":["tgn:7170409","tgn:7003692","tgn:1000003","tgn:7000084","tgn:7029392"],"placetype":["aat:300387200"],"id":7170409,"name:xx":"Hinterbach"}}
>>>>>>> 03f74aca74312dbeaf24d7e61306dd6a786dc3d0
