{
  "id": 7387607,
  "type": "Feature",
  "properties": {
    "tgn:hierarchy":[
        "tgn:7387607",
        "tgn:1000001",
        "tgn:7005591",
        "tgn:7005560",
        "tgn:7029392"
    ],
    "tgn:id":7387607,
    "tgn:name":"Portillo de las Cruces",
    "tgn:placetype":[
        "aat:300008347"
    ]
},
  "bbox": [],
  "geometry": {"coordinates":[-95.916667,16.116667],"type":"Point"}
}