{
  "id": 7522120,
  "type": "Feature",
  "properties": {
    "tgn:hierarchy":[
        "tgn:7522120",
        "tgn:7001242",
        "tgn:7016833",
        "tgn:7001312",
        "tgn:7029392"
    ],
    "tgn:id":7522120,
    "tgn:name:en":"Al \u1e28add\u0101d",
    "tgn:placetype":[
        "aat:300008347"
    ]
},
  "bbox": [],
  "geometry": {"coordinates":[30.863985,30.886455],"type":"Point"}
}