{
  "id": 2109844,
  "type": "Feature",
  "properties": {
    "tgn:hierarchy":[
        "tgn:2109844",
        "tgn:2002130",
        "tgn:1000001",
        "tgn:7012149",
        "tgn:7007828",
        "tgn:7029392"
    ],
    "tgn:id":2109844,
    "tgn:name":"New Haven",
    "tgn:placetype":[
        "aat:300008347"
    ]
},
  "bbox": [],
  "geometry": {"coordinates":[-73.15,44.1167],"type":"Point"}
}