{
  "id": 2709730,
  "type": "Feature",
  "properties": {
    "tgn:hierarchy":[
        "tgn:2709730",
        "tgn:1000001",
        "tgn:7012149",
        "tgn:1002678",
        "tgn:7007252",
        "tgn:7029392"
    ],
    "tgn:id":2709730,
    "tgn:name":"Taggart",
    "tgn:placetype":[
        "aat:300008347"
    ]
},
  "bbox": [],
  "geometry": {"coordinates":[-86.1333,39.25],"type":"Point"}
}