{
  "id": 7586882,
  "type": "Feature",
  "properties": {
    "tgn:hierarchy":[
        "tgn:7586882",
        "tgn:1000004",
        "tgn:7000198",
        "tgn:7000799",
        "tgn:7029392"
    ],
    "tgn:id":7586882,
    "tgn:name:en":"L\u0101l Mandi",
    "tgn:placetype":[
        "aat:300387200"
    ]
},
  "bbox": [],
  "geometry": {"coordinates":[74.809722,34.063889],"type":"Point"}
}