{
  "id": 2781055,
  "type": "Feature",
  "properties": {
    "tgn:hierarchy":[
        "tgn:2781055",
        "tgn:1000001",
        "tgn:7012149",
        "tgn:1002352",
        "tgn:7007710",
        "tgn:7029392"
    ],
    "tgn:id":2781055,
    "tgn:name":"Woodchuck Run",
    "tgn:placetype":[
        "aat:300008699"
    ]
},
  "bbox": [],
  "geometry": {"coordinates":[-78.9167,41.45],"type":"Point"}
}