{
  "id": 2603817,
  "type": "Feature",
  "properties": {
    "tgn:hierarchy":[
        "tgn:2603817",
        "tgn:1000001",
        "tgn:7012149",
        "tgn:2000413",
        "tgn:7007248",
        "tgn:7029392"
    ],
    "tgn:id":2603817,
    "tgn:name":"Quigg Branch",
    "tgn:placetype":[
        "aat:300008699"
    ]
},
  "bbox": [],
  "geometry": {"coordinates":[-83.9833,33.65],"type":"Point"}
}