<<<<<<< HEAD
{
  "id": 7473198,
  "type": "Feature",
  "properties": {
    "tgn:hierarchy":[
        "tgn:7473198",
        "tgn:1000004",
        "tgn:1000454",
        "tgn:1000141",
        "tgn:7029392"
    ],
    "tgn:id":7473198,
    "tgn:name":"Yeliu Wan",
    "tgn:placetype":[
        "aat:300266557"
    ]
},
  "bbox": [],
  "geometry": {"coordinates":[121.683333,25.216667],"type":"Point"}
}
=======
{"geometry":{"type":"Point","coordinates":[121.683333,25.216667]},"type":"Feature","properties":{"hierarchy":["tgn:7473198","tgn:1000004","tgn:1000454","tgn:1000141","tgn:7029392"],"placetype":["aat:300266557"],"id":7473198,"name:xx":"Yeliu Wan"}}
>>>>>>> 03f74aca74312dbeaf24d7e61306dd6a786dc3d0
