{
  "id": 7515396,
  "type": "Feature",
  "properties": {
    "tgn:hierarchy":[
        "tgn:7515396",
        "tgn:1008380",
        "tgn:1000226",
        "tgn:7018426",
        "tgn:1000006",
        "tgn:7029392"
    ],
    "tgn:id":7515396,
    "tgn:name:en":"Castle Rock",
    "tgn:placetype":[
        "aat:300011692"
    ]
},
  "bbox": [],
  "geometry": {"coordinates":[175.883333,-36.866667],"type":"Point"}
}