{
  "id": 2138032,
  "type": "Feature",
  "properties": {
    "tgn:hierarchy":[
        "tgn:2138032",
        "tgn:1000001",
        "tgn:2000458",
        "tgn:7012149",
        "tgn:7007250",
        "tgn:7029392"
    ],
    "tgn:id":2138032,
    "tgn:name":"Arrowhead Spring Number Two",
    "tgn:placetype":[
        "aat:300008697"
    ]
},
  "bbox": [],
  "geometry": {"coordinates":[-114.15,43.25],"type":"Point"}
}