{
  "id": 7340003,
  "type": "Feature",
  "properties": {
    "tgn:hierarchy":[
        "tgn:7340003",
        "tgn:7002815",
        "tgn:1000003",
        "tgn:7002793",
        "tgn:1000095",
        "tgn:7029392"
    ],
    "tgn:id":7340003,
    "tgn:name":"Costur",
    "tgn:placetype":[
        "aat:300008347"
    ]
},
  "bbox": [],
  "geometry": {"coordinates":[-0.166667,40.116667],"type":"Point"}
}