{
  "id": 2305544,
  "type": "Feature",
  "properties": {
    "tgn:hierarchy":[
        "tgn:2305544",
        "tgn:1000001",
        "tgn:7012149",
        "tgn:2001459",
        "tgn:7007566",
        "tgn:7029392"
    ],
    "tgn:id":2305544,
    "tgn:name":"East Canyon",
    "tgn:placetype":[
        "aat:300008761"
    ]
},
  "bbox": [],
  "geometry": {"coordinates":[-103.05,36.8333],"type":"Point"}
}