{
  "id": 7594221,
  "type": "Feature",
  "properties": {
    "tgn:hierarchy":[
        "tgn:7594221",
        "tgn:1000003",
        "tgn:7005729",
        "tgn:7029392"
    ],
    "tgn:id":7594221,
    "tgn:name":"Piet\u00e0",
    "tgn:placetype":[
        "aat:300387064",
        "aat:300387205"
    ]
},
  "bbox": [],
  "geometry": {"coordinates":[14.493889,35.8925],"type":"Point"}
}