<<<<<<< HEAD
{
  "id": 2256413,
  "type": "Feature",
  "properties": {
    "tgn:hierarchy":[
        "tgn:2256413",
        "tgn:1000001",
        "tgn:7012149",
        "tgn:7007157",
        "tgn:1002621",
        "tgn:7029392"
    ],
    "tgn:id":2256413,
    "tgn:name":"Cora Creek",
    "tgn:placetype":[
        "aat:300008706"
    ]
},
  "bbox": [],
  "geometry": {"coordinates":[-119.2667,37.5833],"type":"Point"}
}
=======
{"geometry":{"type":"Point","coordinates":[-119.266700,37.583300]},"type":"Feature","properties":{"hierarchy":["tgn:2256413","tgn:1000001","tgn:7012149","tgn:7007157","tgn:1002621","tgn:7029392"],"placetype":["aat:300008706"],"id":2256413,"name:xx":"Cora Creek"}}
>>>>>>> 03f74aca74312dbeaf24d7e61306dd6a786dc3d0
