{
  "id": 7016567,
  "type": "Feature",
  "properties": {
    "tgn:hierarchy":[
        "tgn:7016567",
        "tgn:7001242",
        "tgn:1000179",
        "tgn:7593684",
        "tgn:7029392"
    ],
    "tgn:id":7016567,
    "tgn:name":"Sal\u00e9",
    "tgn:placetype":[
        "aat:300008347",
        "aat:300008389",
        "aat:300179493",
        "aat:300120599"
    ]
},
  "bbox": [],
  "geometry": {"coordinates":[-6.8333,34.0667],"type":"Point"}
}