<<<<<<< HEAD
{
  "id": 2157703,
  "type": "Feature",
  "properties": {
    "tgn:hierarchy":[
        "tgn:2157703",
        "tgn:2000090",
        "tgn:1000001",
        "tgn:7006451",
        "tgn:7012149",
        "tgn:7029392"
    ],
    "tgn:id":2157703,
    "tgn:name":"Beaver Dam Wash",
    "tgn:placetype":[
        "aat:300008699"
    ]
},
  "bbox": [],
  "geometry": {"coordinates":[-109.5167,34.8],"type":"Point"}
}
=======
{"geometry":{"type":"Point","coordinates":[-109.516700,34.800000]},"type":"Feature","properties":{"hierarchy":["tgn:2157703","tgn:2000090","tgn:1000001","tgn:7006451","tgn:7012149","tgn:7029392"],"placetype":["aat:300008699"],"id":2157703,"name:xx":"Beaver Dam Wash"}}
>>>>>>> 03f74aca74312dbeaf24d7e61306dd6a786dc3d0
