{
  "id": 7258946,
  "type": "Feature",
  "properties": {
    "tgn:hierarchy":[
        "tgn:7258946",
        "tgn:7003619",
        "tgn:1000003",
        "tgn:7016845",
        "tgn:7029392"
    ],
    "tgn:id":7258946,
    "tgn:name:nl":"Brakkenstein",
    "tgn:placetype":[
        "aat:300000745"
    ]
},
  "bbox": [],
  "geometry": {"coordinates":[5.866667,51.816667],"type":"Point"}
}