{
  "id": 2491617,
  "type": "Feature",
  "properties": {
    "tgn:hierarchy":[
        "tgn:2491617",
        "tgn:1000001",
        "tgn:7006451",
        "tgn:2000094",
        "tgn:7012149",
        "tgn:7029392"
    ],
    "tgn:id":2491617,
    "tgn:name":"Maple Spring",
    "tgn:placetype":[
        "aat:300008697"
    ]
},
  "bbox": [],
  "geometry": {"coordinates":[-110.2833,32.5167],"type":"Point"}
}