{
  "id": 7369764,
  "type": "Feature",
  "properties": {
    "tgn:hierarchy":[
        "tgn:7369764",
        "tgn:1000001",
        "tgn:1001960",
        "tgn:7005560",
        "tgn:7029392"
    ],
    "tgn:id":7369764,
    "tgn:name":"Jag\u00fcey",
    "tgn:placetype":[
        "aat:300008347"
    ]
},
  "bbox": [],
  "geometry": {"coordinates":[-110.633333,28.75],"type":"Point"}
}