{
  "id": 1015549,
  "type": "Feature",
  "properties": {
    "tgn:hierarchy":[
        "tgn:1015549",
        "tgn:7005685",
        "tgn:1000001",
        "tgn:7005804",
        "tgn:7029392"
    ],
    "tgn:id":1015549,
    "tgn:name":"Pine Beach",
    "tgn:placetype":[
        "aat:300008347"
    ]
},
  "bbox": [],
  "geometry": {"coordinates":[-73.95,45.5333],"type":"Point"}
}