{
  "id": 7089264,
  "type": "Feature",
  "properties": {
    "tgn:hierarchy":[
        "tgn:7089264",
        "tgn:7003692",
        "tgn:1000003",
        "tgn:7000084",
        "tgn:7029392"
    ],
    "tgn:id":7089264,
    "tgn:name":"Unterhorgen",
    "tgn:placetype":[
        "aat:300008347"
    ]
},
  "bbox": [],
  "geometry": {"coordinates":[9.883333,47.766667],"type":"Point"}
}