{
  "id": 7008758,
  "type": "Feature",
  "properties": {
    "tgn:hierarchy":[
        "tgn:7008758",
        "tgn:1000003",
        "tgn:1000070",
        "tgn:7002897",
        "tgn:7029392"
    ],
    "tgn:id":7008758,
    "tgn:name":"Charlieu",
    "tgn:placetype":[
        "aat:300008347"
    ]
},
  "bbox": [],
  "geometry": {"coordinates":[4.1667,46.1667],"type":"Point"}
}