{
  "id": 1130520,
  "type": "Feature",
  "properties": {
    "tgn:hierarchy":[
        "tgn:1130520",
        "tgn:1001826",
        "tgn:1000047",
        "tgn:7002456",
        "tgn:1000002",
        "tgn:7029392"
    ],
    "tgn:id":1130520,
    "tgn:name":"Taciu\u00e3, Lago",
    "tgn:placetype":[
        "aat:300008707"
    ]
},
  "bbox": [],
  "geometry": {"coordinates":[-60.5833,-4.4833],"type":"Point"}
}