{
  "id": 2043871,
  "type": "Feature",
  "properties": {
    "tgn:hierarchy":[
        "tgn:2043871",
        "tgn:1000001",
        "tgn:2000864",
        "tgn:7012149",
        "tgn:7007256",
        "tgn:7029392"
    ],
    "tgn:id":2043871,
    "tgn:name":"Riverton",
    "tgn:placetype":[
        "aat:300008347"
    ]
},
  "bbox": [],
  "geometry": {"coordinates":[-92.0833,32.15],"type":"Point"}
}