{
  "id": 7577717,
  "type": "Feature",
  "properties": {
    "tgn:hierarchy":[
        "tgn:7577717",
        "tgn:1000004",
        "tgn:1001869",
        "tgn:7000198",
        "tgn:7029392"
    ],
    "tgn:id":7577717,
    "tgn:name:en":"Khombhadi Nana",
    "tgn:placetype":[
        "aat:300008347"
    ]
},
  "bbox": [],
  "geometry": {"coordinates":[69.126043,23.420329],"type":"Point"}
}