{
  "id": 7566876,
  "type": "Feature",
  "properties": {
    "tgn:hierarchy":[
        "tgn:7566876",
        "tgn:1000004",
        "tgn:1001871",
        "tgn:7000198",
        "tgn:7029392"
    ],
    "tgn:id":7566876,
    "tgn:name:en":"Mahr\u0101na",
    "tgn:placetype":[
        "aat:300008347"
    ]
},
  "bbox": [],
  "geometry": {"coordinates":[76.952318,29.341846],"type":"Point"}
}