{
  "id": 2780331,
  "type": "Feature",
  "properties": {
    "tgn:hierarchy":[
        "tgn:2780331",
        "tgn:1000001",
        "tgn:2001014",
        "tgn:7012149",
        "tgn:7007521",
        "tgn:7029392"
    ],
    "tgn:id":2780331,
    "tgn:name":"Wonder Lake",
    "tgn:placetype":[
        "aat:300008680"
    ]
},
  "bbox": [],
  "geometry": {"coordinates":[-90.9167,47.8333],"type":"Point"}
}