{
  "id": 2772260,
  "type": "Feature",
  "properties": {
    "tgn:hierarchy":[
        "tgn:2772260",
        "tgn:1000001",
        "tgn:7012149",
        "tgn:2001909",
        "tgn:7007825",
        "tgn:7029392"
    ],
    "tgn:id":2772260,
    "tgn:name":"Willet Mountain",
    "tgn:placetype":[
        "aat:300008798"
    ]
},
  "bbox": [],
  "geometry": {"coordinates":[-84.7333,35.8333],"type":"Point"}
}