{
  "id": 7309082,
  "type": "Feature",
  "properties": {
    "tgn:hierarchy":[
        "tgn:7309082",
        "tgn:7002464",
        "tgn:1000049",
        "tgn:1000002",
        "tgn:7029392"
    ],
    "tgn:id":7309082,
    "tgn:name":"Majala, Quebrada de",
    "tgn:placetype":[
        "aat:300266554",
        "aat:300008699"
    ]
},
  "bbox": [],
  "geometry": {"coordinates":[-69.083333,-20.933333],"type":"Point"}
}