{
  "id": 7586022,
  "type": "Feature",
  "properties": {
    "tgn:hierarchy":[
        "tgn:7586022",
        "tgn:1000004",
        "tgn:7000198",
        "tgn:7000799",
        "tgn:7029392"
    ],
    "tgn:id":7586022,
    "tgn:name:en":"Khirman-i-Hunud",
    "tgn:placetype":[
        "aat:300008347"
    ]
},
  "bbox": [],
  "geometry": {"coordinates":[74.284722,34.409722],"type":"Point"}
}