{
  "id": 7504782,
  "type": "Feature",
  "properties": {
    "tgn:hierarchy":[
        "tgn:7504782",
        "tgn:7000508",
        "tgn:1008380",
        "tgn:1000226",
        "tgn:1000006",
        "tgn:7029392"
    ],
    "tgn:id":7504782,
    "tgn:name:en":"Hakaimango Point",
    "tgn:placetype":[
        "aat:300386846"
    ]
},
  "bbox": [],
  "geometry": {"coordinates":[175.014722,-36.770556],"type":"Point"}
}