{
  "id": 2750400,
  "type": "Feature",
  "properties": {
    "tgn:hierarchy":[
        "tgn:2750400",
        "tgn:1000001",
        "tgn:7012149",
        "tgn:1002501",
        "tgn:7007710",
        "tgn:7029392"
    ],
    "tgn:id":2750400,
    "tgn:name":"Wandin Junction",
    "tgn:placetype":[
        "aat:300008347"
    ]
},
  "bbox": [],
  "geometry": {"coordinates":[-78.95,40.6667],"type":"Point"}
}