{
  "id": 7031923,
  "type": "Feature",
  "properties": {
    "tgn:hierarchy":[
        "tgn:7031923",
        "tgn:7001242",
        "tgn:7017583",
        "tgn:1000193",
        "tgn:7029392"
    ],
    "tgn:id":7031923,
    "tgn:name":"Kamdebooberge",
    "tgn:placetype":[
        "aat:300008795"
    ]
},
  "bbox": [],
  "geometry": {"coordinates":[23.881,-32.333],"type":"Point"}
}