{
  "id": 1048413,
  "type": "Feature",
  "properties": {
    "tgn:hierarchy":[
        "tgn:1048413",
        "tgn:7002448",
        "tgn:7019216",
        "tgn:1000003",
        "tgn:7008591",
        "tgn:7029392"
    ],
    "tgn:id":1048413,
    "tgn:name:en":"Portrush",
    "tgn:placetype":[
        "aat:300008347"
    ]
},
  "bbox": [],
  "geometry": {"coordinates":[-6.65,55.216667],"type":"Point"}
}