{
  "id": 2424172,
  "type": "Feature",
  "properties": {
    "tgn:hierarchy":[
        "tgn:2424172",
        "tgn:1000001",
        "tgn:7012149",
        "tgn:2001761",
        "tgn:7007712",
        "tgn:7029392"
    ],
    "tgn:id":2424172,
    "tgn:name":"Johns Pond",
    "tgn:placetype":[
        "aat:300006191"
    ]
},
  "bbox": [],
  "geometry": {"coordinates":[-83.1333,34.6167],"type":"Point"}
}