{
  "id": 2510399,
  "type": "Feature",
  "properties": {
    "tgn:hierarchy":[
        "tgn:2510399",
        "tgn:1000001",
        "tgn:7012149",
        "tgn:7007923",
        "tgn:7029392"
    ],
    "tgn:id":2510399,
    "tgn:name":"Middle Sawtooth Mountain",
    "tgn:placetype":[
        "aat:300008798"
    ]
},
  "bbox": [],
  "geometry": {"coordinates":[-105.5667,42.3833],"type":"Point"}
}