{
  "id": 2439998,
  "type": "Feature",
  "properties": {
    "tgn:hierarchy":[
        "tgn:2439998",
        "tgn:7006450",
        "tgn:1000001",
        "tgn:7012149",
        "tgn:2124005",
        "tgn:7029392"
    ],
    "tgn:id":2439998,
    "tgn:name":"Kivliktort Mountain",
    "tgn:placetype":[
        "aat:300008798"
    ]
},
  "bbox": [],
  "geometry": {"coordinates":[-156.5167,68.2667],"type":"Point"}
}