{
  "id": 7324986,
  "type": "Feature",
  "properties": {
    "tgn:hierarchy":[
        "tgn:7324986",
        "tgn:7008911",
        "tgn:1000003",
        "tgn:7002763",
        "tgn:1000095",
        "tgn:7029392"
    ],
    "tgn:id":7324986,
    "tgn:name":"Santa Eulalia de Cueras",
    "tgn:placetype":[
        "aat:300008347"
    ]
},
  "bbox": [],
  "geometry": {"coordinates":[-6.55,43.166667],"type":"Point"}
}