{
  "id": 2246008,
  "type": "Feature",
  "properties": {
    "tgn:hierarchy":[
        "tgn:2246008",
        "tgn:1000001",
        "tgn:7012149",
        "tgn:2001308",
        "tgn:7007524",
        "tgn:7029392"
    ],
    "tgn:id":2246008,
    "tgn:name":"Coal Mine Rim",
    "tgn:placetype":[
        "aat:300266640"
    ]
},
  "bbox": [],
  "geometry": {"coordinates":[-110.1667,45.6167],"type":"Point"}
}