{
  "id": 2440074,
  "type": "Feature",
  "properties": {
    "tgn:hierarchy":[
        "tgn:2440074",
        "tgn:1000001",
        "tgn:7012149",
        "tgn:2001714",
        "tgn:7007708",
        "tgn:7029392"
    ],
    "tgn:id":2440074,
    "tgn:name":"Klamath Strait",
    "tgn:placetype":[
        "aat:300006075"
    ]
},
  "bbox": [],
  "geometry": {"coordinates":[-121.8167,42.0667],"type":"Point"}
}