{
  "id": 7576008,
  "type": "Feature",
  "properties": {
    "tgn:hierarchy":[
        "tgn:7576008",
        "tgn:1000004",
        "tgn:7000198",
        "tgn:1001882",
        "tgn:7029392"
    ],
    "tgn:id":7576008,
    "tgn:name:en":"Kanva Hole",
    "tgn:placetype":[
        "aat:300008699"
    ]
},
  "bbox": [],
  "geometry": {"coordinates":[77.15,12.483333],"type":"Point"}
}