<<<<<<< HEAD
{
  "id": 7487480,
  "type": "Feature",
  "properties": {
    "tgn:hierarchy":[
        "tgn:7487480",
        "tgn:7488858",
        "tgn:1000004",
        "tgn:1000141",
        "tgn:7029392"
    ],
    "tgn:id":7487480,
    "tgn:name":"Beishankeng",
    "tgn:placetype":[
        "aat:300008699"
    ]
},
  "bbox": [],
  "geometry": {"coordinates":[120.871224,23.982],"type":"Point"}
}
=======
{"geometry":{"type":"Point","coordinates":[120.871224,23.982000]},"type":"Feature","properties":{"hierarchy":["tgn:7487480","tgn:7488858","tgn:1000004","tgn:1000141","tgn:7029392"],"placetype":["aat:300008699"],"id":7487480,"name:xx":"Beishankeng"}}
>>>>>>> 03f74aca74312dbeaf24d7e61306dd6a786dc3d0
