{
  "id": 2277881,
  "type": "Feature",
  "properties": {
    "tgn:hierarchy":[
        "tgn:2277881",
        "tgn:1000001",
        "tgn:7012149",
        "tgn:1003044",
        "tgn:7007708",
        "tgn:7029392"
    ],
    "tgn:id":2277881,
    "tgn:name":"Dawson Spring",
    "tgn:placetype":[
        "aat:300008697"
    ]
},
  "bbox": [],
  "geometry": {"coordinates":[-123.2833,45.35],"type":"Point"}
}