{
  "id": 2261410,
  "type": "Feature",
  "properties": {
    "tgn:hierarchy":[
        "tgn:2261410",
        "tgn:1000001",
        "tgn:7012149",
        "tgn:7007919",
        "tgn:7029392"
    ],
    "tgn:id":2261410,
    "tgn:name":"Courthouse Creek",
    "tgn:placetype":[
        "aat:300008706"
    ]
},
  "bbox": [],
  "geometry": {"coordinates":[-77.8833,37.75],"type":"Point"}
}