{
  "id": 7034086,
  "type": "Feature",
  "properties": {
    "tgn:hierarchy":[
        "tgn:7034086",
        "tgn:1003468",
        "tgn:1000003",
        "tgn:7010380",
        "tgn:1000080",
        "tgn:7029392"
    ],
    "tgn:id":7034086,
    "tgn:name":"Masseria Terenzano",
    "tgn:placetype":[
        "aat:300000206"
    ]
},
  "bbox": [],
  "geometry": {"coordinates":[18.028333,40.425556],"type":"Point"}
}