{
  "id": 7291671,
  "type": "Feature",
  "properties": {
    "tgn:hierarchy":[
        "tgn:7291671",
        "tgn:1001630",
        "tgn:1000049",
        "tgn:1000002",
        "tgn:7029392"
    ],
    "tgn:id":7291671,
    "tgn:name":"Enriqueta",
    "tgn:placetype":[
        "aat:300008697"
    ]
},
  "bbox": [],
  "geometry": {"coordinates":[-69.666667,-26.616667],"type":"Point"}
}