<<<<<<< HEAD
{
  "id": 2769051,
  "type": "Feature",
  "properties": {
    "tgn:hierarchy":[
        "tgn:2769051",
        "tgn:1000001",
        "tgn:7012149",
        "tgn:7007251",
        "tgn:7029392"
    ],
    "tgn:id":2769051,
    "tgn:name":"Whitten Branch",
    "tgn:placetype":[
        "aat:300008699"
    ]
},
  "bbox": [],
  "geometry": {"coordinates":[-89.2167,40.5333],"type":"Point"}
}
=======
{"geometry":{"type":"Point","coordinates":[-89.216700,40.533300]},"type":"Feature","properties":{"hierarchy":["tgn:2769051","tgn:1000001","tgn:7012149","tgn:7007251","tgn:7029392"],"placetype":["aat:300008699"],"id":2769051,"name:xx":"Whitten Branch"}}
>>>>>>> 03f74aca74312dbeaf24d7e61306dd6a786dc3d0
