{
  "id": 2296288,
  "type": "Feature",
  "properties": {
    "tgn:hierarchy":[
        "tgn:2296288",
        "tgn:1000001",
        "tgn:7012149",
        "tgn:2002060",
        "tgn:7007826",
        "tgn:7029392"
    ],
    "tgn:id":2296288,
    "tgn:name":"Dry Branch",
    "tgn:placetype":[
        "aat:300008699"
    ]
},
  "bbox": [],
  "geometry": {"coordinates":[-99.6833,29.6833],"type":"Point"}
}