{
  "id": 7555513,
  "type": "Feature",
  "properties": {
    "tgn:hierarchy":[
        "tgn:7555513",
        "tgn:1000004",
        "tgn:7000198",
        "tgn:7016788",
        "tgn:7029392"
    ],
    "tgn:id":7555513,
    "tgn:name:en":"Mandela",
    "tgn:placetype":[
        "aat:300008347"
    ]
},
  "bbox": [],
  "geometry": {"coordinates":[75.433212,28.31291],"type":"Point"}
}