{
  "id": 2268999,
  "type": "Feature",
  "properties": {
    "tgn:hierarchy":[
        "tgn:2268999",
        "tgn:1000001",
        "tgn:1002666",
        "tgn:7012149",
        "tgn:7007565",
        "tgn:7029392"
    ],
    "tgn:id":2268999,
    "tgn:name":"Crossmans",
    "tgn:placetype":[
        "aat:300008347"
    ]
},
  "bbox": [],
  "geometry": {"coordinates":[-74.3167,40.4833],"type":"Point"}
}