{
  "id": 7301922,
  "type": "Feature",
  "properties": {
    "tgn:hierarchy":[
        "tgn:7301922",
        "tgn:7002834",
        "tgn:1000003",
        "tgn:7002786",
        "tgn:1000095",
        "tgn:7029392"
    ],
    "tgn:id":7301922,
    "tgn:name":"Meijome",
    "tgn:placetype":[
        "aat:300008347"
    ]
},
  "bbox": [],
  "geometry": {"coordinates":[-8.166667,42.716667],"type":"Point"}
}