{
  "id": 2775792,
  "type": "Feature",
  "properties": {
    "tgn:hierarchy":[
        "tgn:2775792",
        "tgn:1000001",
        "tgn:7016172",
        "tgn:7012149",
        "tgn:2000164",
        "tgn:7029392"
    ],
    "tgn:id":2775792,
    "tgn:name":"Wilson Knob",
    "tgn:placetype":[
        "aat:300008798"
    ]
},
  "bbox": [],
  "geometry": {"coordinates":[-92.15,34.95],"type":"Point"}
}