{
  "id": 2710545,
  "type": "Feature",
  "properties": {
    "tgn:hierarchy":[
        "tgn:2710545",
        "tgn:1000001",
        "tgn:7012149",
        "tgn:7013941",
        "tgn:7007568",
        "tgn:7029392"
    ],
    "tgn:id":2710545,
    "tgn:name":"Tamarack Pond",
    "tgn:placetype":[
        "aat:300008680"
    ]
},
  "bbox": [],
  "geometry": {"coordinates":[-74.2833,44.2667],"type":"Point"}
}