{
  "id": 2275413,
  "type": "Feature",
  "properties": {
    "tgn:hierarchy":[
        "tgn:2275413",
        "tgn:1000001",
        "tgn:7012149",
        "tgn:1002426",
        "tgn:7007255",
        "tgn:7029392"
    ],
    "tgn:id":2275413,
    "tgn:name":"Danleyton",
    "tgn:placetype":[
        "aat:300008347"
    ]
},
  "bbox": [],
  "geometry": {"coordinates":[-82.7667,38.4833],"type":"Point"}
}