{
  "id": 2435789,
  "type": "Feature",
  "properties": {
    "tgn:hierarchy":[
        "tgn:2435789",
        "tgn:1000001",
        "tgn:2000920",
        "tgn:7012149",
        "tgn:7007515",
        "tgn:7029392"
    ],
    "tgn:id":2435789,
    "tgn:name":"Kettle Cove",
    "tgn:placetype":[
        "aat:300132316"
    ]
},
  "bbox": [],
  "geometry": {"coordinates":[-70.5333,43.9167],"type":"Point"}
}