{
  "id": 2010661,
  "type": "Feature",
  "properties": {
    "tgn:hierarchy":[
        "tgn:2010661",
        "tgn:1000001",
        "tgn:7012149",
        "tgn:1002545",
        "tgn:7007157",
        "tgn:7029392"
    ],
    "tgn:id":2010661,
    "tgn:name":"Chaffee",
    "tgn:placetype":[
        "aat:300387016"
    ]
},
  "bbox": [],
  "geometry": {"coordinates":[-118.1667,35.0667],"type":"Point"}
}