{
  "id": 7221740,
  "type": "Feature",
  "properties": {
    "tgn:hierarchy":[
        "tgn:7221740",
        "tgn:7011369",
        "tgn:7017076",
        "tgn:1000003",
        "tgn:1000074",
        "tgn:7029392"
    ],
    "tgn:id":7221740,
    "tgn:name":"Mili\u00f3tion",
    "tgn:placetype":[
        "aat:300008347"
    ]
},
  "bbox": [],
  "geometry": {"coordinates":[21.816667,37.066667],"type":"Point"}
}