{
  "id": 7336787,
  "type": "Feature",
  "properties": {
    "tgn:hierarchy":[
        "tgn:7336787",
        "tgn:7008911",
        "tgn:1000003",
        "tgn:7002763",
        "tgn:1000095",
        "tgn:7029392"
    ],
    "tgn:id":7336787,
    "tgn:name":"Fontalba",
    "tgn:placetype":[
        "aat:300008347"
    ]
},
  "bbox": [],
  "geometry": {"coordinates":[-6.55,43.283333],"type":"Point"}
}