{
  "id": 2570558,
  "type": "Feature",
  "properties": {
    "tgn:hierarchy":[
        "tgn:2570558",
        "tgn:1000001",
        "tgn:2002367",
        "tgn:7012149",
        "tgn:7007923",
        "tgn:7029392"
    ],
    "tgn:id":2570558,
    "tgn:name":"Patra Number 3 Reservoir",
    "tgn:placetype":[
        "aat:300006191"
    ]
},
  "bbox": [],
  "geometry": {"coordinates":[-105.6333,44.0833],"type":"Point"}
}