{
  "id": 2392992,
  "type": "Feature",
  "properties": {
    "tgn:hierarchy":[
        "tgn:2392992",
        "tgn:1000001",
        "tgn:7012149",
        "tgn:2002300",
        "tgn:7013961",
        "tgn:7029392"
    ],
    "tgn:id":2392992,
    "tgn:name":"Hodam Creek",
    "tgn:placetype":[
        "aat:300008706"
    ]
},
  "bbox": [],
  "geometry": {"coordinates":[-80.3667,38.5833],"type":"Point"}
}