{
  "id": 2545010,
  "type": "Feature",
  "properties": {
    "tgn:hierarchy":[
        "tgn:2545010",
        "tgn:1000001",
        "tgn:7012149",
        "tgn:2000227",
        "tgn:7007158",
        "tgn:7029392"
    ],
    "tgn:id":2545010,
    "tgn:name":"North Deadman Canyon",
    "tgn:placetype":[
        "aat:300008761"
    ]
},
  "bbox": [],
  "geometry": {"coordinates":[-103.3167,37.5333],"type":"Point"}
}