{
  "id": 7459309,
  "type": "Feature",
  "properties": {
    "tgn:hierarchy":[
        "tgn:7459309",
        "tgn:7002445",
        "tgn:1000003",
        "tgn:7008165",
        "tgn:7008591",
        "tgn:7029392"
    ],
    "tgn:id":7459309,
    "tgn:name:en":"Mickley",
    "tgn:placetype":[
        "aat:300008347"
    ]
},
  "bbox": [],
  "geometry": {"coordinates":[-1.866667,54.95],"type":"Point"}
}