{
  "id": 7015847,
  "type": "Feature",
  "properties": {
    "tgn:hierarchy":[
        "tgn:7015847",
        "tgn:7022658",
        "tgn:1000001",
        "tgn:7012149",
        "tgn:7007567",
        "tgn:7007568",
        "tgn:7029392"
    ],
    "tgn:id":7015847,
    "tgn:name":"City Island",
    "tgn:placetype":[
        "aat:300000745",
        "aat:300008791"
    ]
},
  "bbox": [],
  "geometry": {"coordinates":[-73.7833,40.8333],"type":"Point"}
}