{
  "id": 7010975,
  "type": "Feature",
  "properties": {
    "tgn:hierarchy":[
        "tgn:7010975",
        "tgn:1000882",
        "tgn:1000003",
        "tgn:1000090",
        "tgn:7029392"
    ],
    "tgn:id":7010975,
    "tgn:name":"Odrinhas",
    "tgn:placetype":[
        "aat:300008347"
    ]
},
  "bbox": [],
  "geometry": {"coordinates":[-9.371,38.882],"type":"Point"}
}