{
  "id": 2092208,
  "type": "Feature",
  "properties": {
    "tgn:hierarchy":[
        "tgn:2092208",
        "tgn:1000001",
        "tgn:7012149",
        "tgn:1002586",
        "tgn:7007710",
        "tgn:7029392"
    ],
    "tgn:id":2092208,
    "tgn:name":"Powder Valley",
    "tgn:placetype":[
        "aat:300008347",
        "aat:300387210"
    ]
},
  "bbox": [],
  "geometry": {"coordinates":[-75.5167,40.45],"type":"Point"}
}