{
  "id": 1032096,
  "type": "Feature",
  "properties": {
    "tgn:hierarchy":[
        "tgn:1032096",
        "tgn:1000003",
        "tgn:7002875",
        "tgn:1000070",
        "tgn:7029392"
    ],
    "tgn:id":1032096,
    "tgn:name":"Bellevesvre",
    "tgn:placetype":[
        "aat:300008347"
    ]
},
  "bbox": [],
  "geometry": {"coordinates":[5.3833,46.8333],"type":"Point"}
}