<<<<<<< HEAD
{
  "id": 7246987,
  "type": "Feature",
  "properties": {
    "tgn:hierarchy":[
        "tgn:7246987",
        "tgn:7018237",
        "tgn:1000003",
        "tgn:1000063",
        "tgn:7029392"
    ],
    "tgn:id":7246987,
    "tgn:name":"Cureghem",
    "tgn:placetype":[
        "aat:300008347"
    ]
},
  "bbox": [],
  "geometry": {"coordinates":[4.333333,50.833333],"type":"Point"}
}
=======
{"geometry":{"type":"Point","coordinates":[4.333333,50.833333]},"type":"Feature","properties":{"hierarchy":["tgn:7246987","tgn:7018237","tgn:1000003","tgn:1000063","tgn:7029392"],"placetype":["aat:300008347"],"id":7246987,"name:xx":"Cureghem"}}
>>>>>>> 03f74aca74312dbeaf24d7e61306dd6a786dc3d0
