{
  "id": 7382620,
  "type": "Feature",
  "properties": {
    "tgn:hierarchy":[
        "tgn:7382620",
        "tgn:1000001",
        "tgn:1001960",
        "tgn:7005560",
        "tgn:7029392"
    ],
    "tgn:id":7382620,
    "tgn:name":"Moreno",
    "tgn:placetype":[
        "aat:300008347"
    ]
},
  "bbox": [],
  "geometry": {"coordinates":[-111.233333,30.533333],"type":"Point"}
}