{
  "id": 7471727,
  "type": "Feature",
  "properties": {
    "tgn:hierarchy":[
        "tgn:7471727",
        "tgn:7468018",
        "tgn:1000004",
        "tgn:1000141",
        "tgn:7029392"
    ],
    "tgn:id":7471727,
    "tgn:name":"Juechiling",
    "tgn:placetype":[
        "aat:300008347"
    ]
},
  "bbox": [],
  "geometry": {"coordinates":[120.626389,23.561389],"type":"Point"}
}