{
  "id": 7403414,
  "type": "Feature",
  "properties": {
    "tgn:hierarchy":[
        "tgn:7403414",
        "tgn:1000001",
        "tgn:1001906",
        "tgn:7005560",
        "tgn:7029392"
    ],
    "tgn:id":7403414,
    "tgn:name":"Las Mesas",
    "tgn:placetype":[
        "aat:300008347"
    ]
},
  "bbox": [],
  "geometry": {"coordinates":[-104.1375,21.220833],"type":"Point"}
}