{
  "id": 7063704,
  "type": "Feature",
  "properties": {
    "tgn:hierarchy":[
        "tgn:7063704",
        "tgn:7003669",
        "tgn:1000003",
        "tgn:7000084",
        "tgn:7029392"
    ],
    "tgn:id":7063704,
    "tgn:name":"Auling",
    "tgn:placetype":[
        "aat:300000206"
    ]
},
  "bbox": [],
  "geometry": {"coordinates":[13.416667,48.616667],"type":"Point"}
}