{
  "id": 7286871,
  "type": "Feature",
  "properties": {
    "tgn:hierarchy":[
        "tgn:7286871",
        "tgn:1001702",
        "tgn:1000049",
        "tgn:1000002",
        "tgn:7029392"
    ],
    "tgn:id":7286871,
    "tgn:name":"Guanacos, Estero",
    "tgn:placetype":[
        "aat:300008699"
    ]
},
  "bbox": [],
  "geometry": {"coordinates":[-69.733333,-53.033333],"type":"Point"}
}