{
  "id": 2350773,
  "type": "Feature",
  "properties": {
    "tgn:hierarchy":[
        "tgn:2350773",
        "tgn:1000001",
        "tgn:7012149",
        "tgn:2002284",
        "tgn:7013961",
        "tgn:7029392"
    ],
    "tgn:id":2350773,
    "tgn:name":"Glade Creek",
    "tgn:placetype":[
        "aat:300008706"
    ]
},
  "bbox": [],
  "geometry": {"coordinates":[-80.75,38.3167],"type":"Point"}
}