{
  "id": 7232044,
  "type": "Feature",
  "properties": {
    "tgn:hierarchy":[
        "tgn:7232044",
        "tgn:1042193",
        "tgn:7002705",
        "tgn:1000003",
        "tgn:1000074",
        "tgn:7029392"
    ],
    "tgn:id":7232044,
    "tgn:name":"Keladi\u00f3, \u00c1kra",
    "tgn:placetype":[
        "aat:300008850"
    ]
},
  "bbox": [],
  "geometry": {"coordinates":[20.385556,39.279167],"type":"Point"}
}