{
  "id": 7204178,
  "type": "Feature",
  "properties": {
    "tgn:hierarchy":[
        "tgn:7204178",
        "tgn:7003692",
        "tgn:1000003",
        "tgn:7000084",
        "tgn:7029392"
    ],
    "tgn:id":7204178,
    "tgn:name":"Bruderhof",
    "tgn:placetype":[
        "aat:300000206"
    ]
},
  "bbox": [],
  "geometry": {"coordinates":[8.916667,47.666667],"type":"Point"}
}