<<<<<<< HEAD
{
  "id": 7486078,
  "type": "Feature",
  "properties": {
    "tgn:hierarchy":[
        "tgn:7486078",
        "tgn:1000004",
        "tgn:7004300",
        "tgn:1000141",
        "tgn:7029392"
    ],
    "tgn:id":7486078,
    "tgn:name":"Laizi",
    "tgn:placetype":[
        "aat:300386846"
    ]
},
  "bbox": [],
  "geometry": {"coordinates":[119.6,23.666667],"type":"Point"}
}
=======
{"geometry":{"type":"Point","coordinates":[119.600000,23.666667]},"type":"Feature","properties":{"hierarchy":["tgn:7486078","tgn:1000004","tgn:7004300","tgn:1000141","tgn:7029392"],"placetype":["aat:300386846"],"id":7486078,"name:xx":"Laizi"}}
>>>>>>> 03f74aca74312dbeaf24d7e61306dd6a786dc3d0
