{
  "id": 2341622,
  "type": "Feature",
  "properties": {
    "tgn:hierarchy":[
        "tgn:2341622",
        "tgn:7006450",
        "tgn:1000001",
        "tgn:7019698",
        "tgn:7012149",
        "tgn:7029392"
    ],
    "tgn:id":2341622,
    "tgn:name":"Front Point",
    "tgn:placetype":[
        "aat:300008850"
    ]
},
  "bbox": [],
  "geometry": {"coordinates":[-150.8833,59.2667],"type":"Point"}
}