<<<<<<< HEAD
{
  "id": 7369949,
  "type": "Feature",
  "properties": {
    "tgn:hierarchy":[
        "tgn:7369949",
        "tgn:7016644",
        "tgn:1000001",
        "tgn:7005560",
        "tgn:7029392"
    ],
    "tgn:id":7369949,
    "tgn:name":"Jala",
    "tgn:placetype":[
        "aat:300007783"
    ]
},
  "bbox": [],
  "geometry": {"coordinates":[-103.85,19.133333],"type":"Point"}
}
=======
{"geometry":{"type":"Point","coordinates":[-103.850000,19.133333]},"type":"Feature","properties":{"hierarchy":["tgn:7369949","tgn:7016644","tgn:1000001","tgn:7005560","tgn:7029392"],"placetype":["aat:300007783"],"id":7369949,"name:xx":"Jala"}}
>>>>>>> 03f74aca74312dbeaf24d7e61306dd6a786dc3d0
