{
  "id": 2661309,
  "type": "Feature",
  "properties": {
    "tgn:hierarchy":[
        "tgn:2661309",
        "tgn:1000001",
        "tgn:2000462",
        "tgn:7012149",
        "tgn:7007250",
        "tgn:7029392"
    ],
    "tgn:id":2661309,
    "tgn:name":"Shorty Creek",
    "tgn:placetype":[
        "aat:300008706"
    ]
},
  "bbox": [],
  "geometry": {"coordinates":[-116.6833,48.9333],"type":"Point"}
}