{
  "id": 7499147,
  "type": "Feature",
  "properties": {
    "tgn:hierarchy":[
        "tgn:7499147",
        "tgn:1000004",
        "tgn:7001009",
        "tgn:1000141",
        "tgn:7029392"
    ],
    "tgn:id":7499147,
    "tgn:name":"Zhugaokeng",
    "tgn:placetype":[
        "aat:300387032"
    ]
},
  "bbox": [],
  "geometry": {"coordinates":[120.746948,24.015593],"type":"Point"}
}