{
  "id": 2266924,
  "type": "Feature",
  "properties": {
    "tgn:hierarchy":[
        "tgn:2266924",
        "tgn:1000001",
        "tgn:2002368",
        "tgn:7012149",
        "tgn:7007923",
        "tgn:7029392"
    ],
    "tgn:id":2266924,
    "tgn:name":"Cress Creek",
    "tgn:placetype":[
        "aat:300008706"
    ]
},
  "bbox": [],
  "geometry": {"coordinates":[-107.2833,42.2333],"type":"Point"}
}