{
  "id": 1060322,
  "type": "Feature",
  "properties": {
    "tgn:hierarchy":[
        "tgn:1060322",
        "tgn:1000004",
        "tgn:1003405",
        "tgn:7018214",
        "tgn:7002435",
        "tgn:7029392"
    ],
    "tgn:id":1060322,
    "tgn:name":"Titovka",
    "tgn:placetype":[
        "aat:300008347"
    ]
},
  "bbox": [],
  "geometry": {"coordinates":[39.7333,48.9833],"type":"Point"}
}