{
  "id": 2504928,
  "type": "Feature",
  "properties": {
    "tgn:hierarchy":[
        "tgn:2504928",
        "tgn:2000919",
        "tgn:1000001",
        "tgn:7012149",
        "tgn:7007515",
        "tgn:7029392"
    ],
    "tgn:id":2504928,
    "tgn:name":"Meduxnekeag Lake",
    "tgn:placetype":[
        "aat:300008680"
    ]
},
  "bbox": [],
  "geometry": {"coordinates":[-68.0167,46.0833],"type":"Point"}
}