{
  "id": 2349486,
  "type": "Feature",
  "properties": {
    "tgn:hierarchy":[
        "tgn:2349486",
        "tgn:1000001",
        "tgn:2001007",
        "tgn:7012149",
        "tgn:7007521",
        "tgn:7029392"
    ],
    "tgn:id":2349486,
    "tgn:name":"Gill Creek",
    "tgn:placetype":[
        "aat:300008706"
    ]
},
  "bbox": [],
  "geometry": {"coordinates":[-92.3333,46.6667],"type":"Point"}
}