{
  "id": 7544819,
  "type": "Feature",
  "properties": {
    "tgn:hierarchy":[
        "tgn:7544819",
        "tgn:1000004",
        "tgn:7000198",
        "tgn:7000799",
        "tgn:7029392"
    ],
    "tgn:id":7544819,
    "tgn:name:en":"Bhargi",
    "tgn:placetype":[
        "aat:300008347"
    ]
},
  "bbox": [],
  "geometry": {"coordinates":[75.903306,33.03631],"type":"Point"}
}