<<<<<<< HEAD
{
  "id": 7115857,
  "type": "Feature",
  "properties": {
    "tgn:hierarchy":[
        "tgn:7115857",
        "tgn:7003669",
        "tgn:1000003",
        "tgn:7000084",
        "tgn:7029392"
    ],
    "tgn:id":7115857,
    "tgn:name":"Oberwiesenbach",
    "tgn:placetype":[
        "aat:300008347"
    ]
},
  "bbox": [],
  "geometry": {"coordinates":[10.3,48.283333],"type":"Point"}
}
=======
{"geometry":{"type":"Point","coordinates":[10.300000,48.283333]},"type":"Feature","properties":{"hierarchy":["tgn:7115857","tgn:7003669","tgn:1000003","tgn:7000084","tgn:7029392"],"placetype":["aat:300008347"],"id":7115857,"name:xx":"Oberwiesenbach"}}
>>>>>>> 03f74aca74312dbeaf24d7e61306dd6a786dc3d0
