{
  "id": 2427860,
  "type": "Feature",
  "properties": {
    "tgn:hierarchy":[
        "tgn:2427860",
        "tgn:1000001",
        "tgn:7012149",
        "tgn:2000888",
        "tgn:7007256",
        "tgn:7029392"
    ],
    "tgn:id":2427860,
    "tgn:name":"Jowers Creek",
    "tgn:placetype":[
        "aat:300008706"
    ]
},
  "bbox": [],
  "geometry": {"coordinates":[-92.8833,31.4333],"type":"Point"}
}