{
  "id": 2118303,
  "type": "Feature",
  "properties": {
    "tgn:hierarchy":[
        "tgn:2118303",
        "tgn:1000001",
        "tgn:7012149",
        "tgn:2002273",
        "tgn:7013961",
        "tgn:7029392"
    ],
    "tgn:id":2118303,
    "tgn:name":"Frogtown",
    "tgn:placetype":[
        "aat:300008347"
    ]
},
  "bbox": [],
  "geometry": {"coordinates":[-82.0667,37.8167],"type":"Point"}
}