{
  "id": 2754238,
  "type": "Feature",
  "properties": {
    "tgn:hierarchy":[
        "tgn:2754238",
        "tgn:1000001",
        "tgn:2001097",
        "tgn:7012149",
        "tgn:7007522",
        "tgn:7029392"
    ],
    "tgn:id":2754238,
    "tgn:name":"Watts Creek",
    "tgn:placetype":[
        "aat:300008706"
    ]
},
  "bbox": [],
  "geometry": {"coordinates":[-88.7667,31.95],"type":"Point"}
}