{
  "id": 7464144,
  "type": "Feature",
  "properties": {
    "tgn:hierarchy":[
        "tgn:7464144",
        "tgn:7002443",
        "tgn:1000003",
        "tgn:7018966",
        "tgn:7008591",
        "tgn:7029392"
    ],
    "tgn:id":7464144,
    "tgn:name:en":"Breaksea Point",
    "tgn:placetype":[
        "aat:300386846"
    ]
},
  "bbox": [],
  "geometry": {"coordinates":[-3.403333,51.383889],"type":"Point"}
}