{
  "id": 2400580,
  "type": "Feature",
  "properties": {
    "tgn:hierarchy":[
        "tgn:2400580",
        "tgn:1000001",
        "tgn:7012149",
        "tgn:2000181",
        "tgn:7007157",
        "tgn:7029392"
    ],
    "tgn:id":2400580,
    "tgn:name":"Horse Linto Creek",
    "tgn:placetype":[
        "aat:300008706"
    ]
},
  "bbox": [],
  "geometry": {"coordinates":[-123.45,41.05],"type":"Point"}
}