{
  "id": 2474104,
  "type": "Feature",
  "properties": {
    "tgn:hierarchy":[
        "tgn:2474104",
        "tgn:1000001",
        "tgn:7012149",
        "tgn:7007158",
        "tgn:2000253",
        "tgn:7029392"
    ],
    "tgn:id":2474104,
    "tgn:name":"Lower Latham Outlet",
    "tgn:placetype":[
        "aat:300006075"
    ]
},
  "bbox": [],
  "geometry": {"coordinates":[-104.6333,40.3667],"type":"Point"}
}