<<<<<<< HEAD
{
  "id": 2400438,
  "type": "Feature",
  "properties": {
    "tgn:hierarchy":[
        "tgn:2400438",
        "tgn:1000001",
        "tgn:7012149",
        "tgn:2000805",
        "tgn:7007255",
        "tgn:7029392"
    ],
    "tgn:id":2400438,
    "tgn:name":"Horse Hollow",
    "tgn:placetype":[
        "aat:300008761"
    ]
},
  "bbox": [],
  "geometry": {"coordinates":[-83.1,37.45],"type":"Point"}
}
=======
{"geometry":{"type":"Point","coordinates":[-83.100000,37.450000]},"type":"Feature","properties":{"hierarchy":["tgn:2400438","tgn:1000001","tgn:7012149","tgn:2000805","tgn:7007255","tgn:7029392"],"placetype":["aat:300008761"],"id":2400438,"name:xx":"Horse Hollow"}}
>>>>>>> 03f74aca74312dbeaf24d7e61306dd6a786dc3d0
