{
  "id": 1019695,
  "type": "Feature",
  "properties": {
    "tgn:hierarchy":[
        "tgn:1019695",
        "tgn:1001160",
        "tgn:7006477",
        "tgn:1000002",
        "tgn:7029392"
    ],
    "tgn:id":1019695,
    "tgn:name":"Lobos",
    "tgn:placetype":[
        "aat:300008347"
    ]
},
  "bbox": [],
  "geometry": {"coordinates":[-59.1333,-35.1833],"type":"Point"}
}