{
  "id": 2460432,
  "type": "Feature",
  "properties": {
    "tgn:hierarchy":[
        "tgn:2460432",
        "tgn:1000001",
        "tgn:7012149",
        "tgn:2002371",
        "tgn:7007923",
        "tgn:7029392"
    ],
    "tgn:id":2460432,
    "tgn:name":"Little Sand Draw",
    "tgn:placetype":[
        "aat:300008761"
    ]
},
  "bbox": [],
  "geometry": {"coordinates":[-108.1333,42.7167],"type":"Point"}
}