{
  "id": 2194210,
  "type": "Feature",
  "properties": {
    "tgn:hierarchy":[
        "tgn:2194210",
        "tgn:7002659",
        "tgn:1000001",
        "tgn:7012149",
        "tgn:2000039",
        "tgn:7029392"
    ],
    "tgn:id":2194210,
    "tgn:name":"Brides Hill",
    "tgn:placetype":[
        "aat:300008347"
    ]
},
  "bbox": [],
  "geometry": {"coordinates":[-87.2333,34.6667],"type":"Point"}
}