{
  "id": 7229924,
  "type": "Feature",
  "properties": {
    "tgn:hierarchy":[
        "tgn:7229924",
        "tgn:7002681",
        "tgn:7001395",
        "tgn:1000003",
        "tgn:1000074",
        "tgn:7029392"
    ],
    "tgn:id":7229924,
    "tgn:name":"Meg\u00e1lo, Nis\u00eds",
    "tgn:placetype":[
        "aat:300008791"
    ]
},
  "bbox": [],
  "geometry": {"coordinates":[24.75,37.833333],"type":"Point"}
}