{
  "id": 1124000,
  "type": "Feature",
  "properties": {
    "tgn:hierarchy":[
        "tgn:1124000",
        "tgn:1000003",
        "tgn:7002877",
        "tgn:1000070",
        "tgn:7029392"
    ],
    "tgn:id":1124000,
    "tgn:name":"Fouzon",
    "tgn:placetype":[
        "aat:300008707"
    ]
},
  "bbox": [],
  "geometry": {"coordinates":[1.45,47.2667],"type":"Point"}
}