{
  "id": 2564967,
  "type": "Feature",
  "properties": {
    "tgn:hierarchy":[
        "tgn:2564967",
        "tgn:1000001",
        "tgn:7012149",
        "tgn:1002440",
        "tgn:7007568",
        "tgn:7029392"
    ],
    "tgn:id":2564967,
    "tgn:name":"Page Brook",
    "tgn:placetype":[
        "aat:300008699"
    ]
},
  "bbox": [],
  "geometry": {"coordinates":[-74.4667,43.5833],"type":"Point"}
}