{
  "id": 1123466,
  "type": "Feature",
  "properties": {
    "tgn:hierarchy":[
        "tgn:1123466",
        "tgn:1000004",
        "tgn:7002435",
        "tgn:7029392"
    ],
    "tgn:id":1123466,
    "tgn:name":"Don",
    "tgn:placetype":[
        "aat:300008707"
    ]
},
  "bbox": [],
  "geometry": {"coordinates":[39.2833,47.05],"type":"Point"}
}