{
  "id": 2615227,
  "type": "Feature",
  "properties": {
    "tgn:hierarchy":[
        "tgn:2615227",
        "tgn:1000001",
        "tgn:7012149",
        "tgn:2001297",
        "tgn:7007524",
        "tgn:7029392"
    ],
    "tgn:id":2615227,
    "tgn:name":"Reservoir Creek",
    "tgn:placetype":[
        "aat:300008706"
    ]
},
  "bbox": [],
  "geometry": {"coordinates":[-105.75,45.3833],"type":"Point"}
}