{
  "id": 2637925,
  "type": "Feature",
  "properties": {
    "tgn:hierarchy":[
        "tgn:2637925",
        "tgn:1000001",
        "tgn:7012149",
        "tgn:1002943",
        "tgn:7007708",
        "tgn:7029392"
    ],
    "tgn:id":2637925,
    "tgn:name":"Salal Point",
    "tgn:placetype":[
        "aat:300008798"
    ]
},
  "bbox": [],
  "geometry": {"coordinates":[-123.8833,45.15],"type":"Point"}
}