{
  "id": 1129896,
  "type": "Feature",
  "properties": {
    "tgn:hierarchy":[
        "tgn:1129896",
        "tgn:7002445",
        "tgn:1000003",
        "tgn:7008166",
        "tgn:7008591",
        "tgn:7029392"
    ],
    "tgn:id":1129896,
    "tgn:name:en":"Seven",
    "tgn:placetype":[
        "aat:300008707",
        "aat:300008699"
    ]
},
  "bbox": [],
  "geometry": {"coordinates":[-0.85,54.183333],"type":"Point"}
}