<<<<<<< HEAD
{
  "id": 7377622,
  "type": "Feature",
  "properties": {
    "tgn:hierarchy":[
        "tgn:7377622",
        "tgn:1001835",
        "tgn:1000001",
        "tgn:7005560",
        "tgn:7029392"
    ],
    "tgn:id":7377622,
    "tgn:name":"Las Calabazas, Cerro de",
    "tgn:placetype":[
        "aat:300008795"
    ]
},
  "bbox": [],
  "geometry": {"coordinates":[-115.9,31.433333],"type":"Point"}
}
=======
{"geometry":{"type":"Point","coordinates":[-115.900000,31.433333]},"type":"Feature","properties":{"hierarchy":["tgn:7377622","tgn:1001835","tgn:1000001","tgn:7005560","tgn:7029392"],"placetype":["aat:300008795"],"id":7377622,"name:xx":"Las Calabazas, Cerro de"}}
>>>>>>> 03f74aca74312dbeaf24d7e61306dd6a786dc3d0
