{
  "id": 2745981,
  "type": "Feature",
  "properties": {
    "tgn:hierarchy":[
        "tgn:2745981",
        "tgn:1000001",
        "tgn:7012149",
        "tgn:7014510",
        "tgn:7007920",
        "tgn:7029392"
    ],
    "tgn:id":2745981,
    "tgn:name":"Vogler Lake",
    "tgn:placetype":[
        "aat:300008680"
    ]
},
  "bbox": [],
  "geometry": {"coordinates":[-121.7667,48.5667],"type":"Point"}
}