<<<<<<< HEAD
{
  "id": 2407393,
  "type": "Feature",
  "properties": {
    "tgn:hierarchy":[
        "tgn:2407393",
        "tgn:7006450",
        "tgn:1000001",
        "tgn:2124053",
        "tgn:7012149",
        "tgn:7029392"
    ],
    "tgn:id":2407393,
    "tgn:name":"Huntington, Mount",
    "tgn:placetype":[
        "aat:300008798"
    ]
},
  "bbox": [],
  "geometry": {"coordinates":[-150.8833,62.9667],"type":"Point"}
}
=======
{"geometry":{"type":"Point","coordinates":[-150.883300,62.966700]},"type":"Feature","properties":{"hierarchy":["tgn:2407393","tgn:7006450","tgn:1000001","tgn:2124053","tgn:7012149","tgn:7029392"],"placetype":["aat:300008798"],"id":2407393,"name:xx":"Huntington, Mount"}}
>>>>>>> 03f74aca74312dbeaf24d7e61306dd6a786dc3d0
