{
  "id": 2407393,
  "type": "Feature",
  "properties": {
    "tgn:hierarchy":[
        "tgn:2407393",
        "tgn:7006450",
        "tgn:1000001",
        "tgn:2124053",
        "tgn:7012149",
        "tgn:7029392"
    ],
    "tgn:id":2407393,
    "tgn:name":"Huntington, Mount",
    "tgn:placetype":[
        "aat:300008798"
    ]
},
  "bbox": [],
  "geometry": {"coordinates":[-150.8833,62.9667],"type":"Point"}
}