{
  "id": 2741588,
  "type": "Feature",
  "properties": {
    "tgn:hierarchy":[
        "tgn:2741588",
        "tgn:1000001",
        "tgn:7012149",
        "tgn:2001879",
        "tgn:7007825",
        "tgn:7029392"
    ],
    "tgn:id":2741588,
    "tgn:name":"Ussery Hollow",
    "tgn:placetype":[
        "aat:300008761"
    ]
},
  "bbox": [],
  "geometry": {"coordinates":[-87.7667,36.1167],"type":"Point"}
}