{
  "id": 2426416,
  "type": "Feature",
  "properties": {
    "tgn:hierarchy":[
        "tgn:2426416",
        "tgn:1000001",
        "tgn:7012149",
        "tgn:2002385",
        "tgn:7007923",
        "tgn:7029392"
    ],
    "tgn:id":2426416,
    "tgn:name":"Jones Creek",
    "tgn:placetype":[
        "aat:300008706"
    ]
},
  "bbox": [],
  "geometry": {"coordinates":[-110.5333,41.1333],"type":"Point"}
}