{
  "id": 7164977,
  "type": "Feature",
  "properties": {
    "tgn:hierarchy":[
        "tgn:7164977",
        "tgn:1000003",
        "tgn:7003678",
        "tgn:7000084",
        "tgn:7029392"
    ],
    "tgn:id":7164977,
    "tgn:name":"Hundsloh",
    "tgn:placetype":[
        "aat:300008777"
    ]
},
  "bbox": [],
  "geometry": {"coordinates":[9.35,50.45],"type":"Point"}
}