{
  "id": 7533179,
  "type": "Feature",
  "properties": {
    "tgn:hierarchy":[
        "tgn:7533179",
        "tgn:7001242",
        "tgn:7016833",
        "tgn:1001335",
        "tgn:7029392"
    ],
    "tgn:id":7533179,
    "tgn:name:en":"Tur'at Ab\u016b Rayyah",
    "tgn:placetype":[
        "aat:300006075"
    ]
},
  "bbox": [],
  "geometry": {"coordinates":[30.956194,31.192763],"type":"Point"}
}