{
  "id": 2593530,
  "type": "Feature",
  "properties": {
    "tgn:hierarchy":[
        "tgn:2593530",
        "tgn:1000001",
        "tgn:1002260",
        "tgn:7012149",
        "tgn:7007920",
        "tgn:7029392"
    ],
    "tgn:id":2593530,
    "tgn:name":"Porcupine Creek",
    "tgn:placetype":[
        "aat:300008706"
    ]
},
  "bbox": [],
  "geometry": {"coordinates":[-120.8333,47.4667],"type":"Point"}
}