{
  "id": 7521775,
  "type": "Feature",
  "properties": {
    "tgn:hierarchy":[
        "tgn:7521775",
        "tgn:7001242",
        "tgn:7016833",
        "tgn:7001335",
        "tgn:7029392"
    ],
    "tgn:id":7521775,
    "tgn:name:en":"Ab\u016b Kan\u0101d\u016b, Jabal",
    "tgn:placetype":[
        "aat:300008777"
    ]
},
  "bbox": [],
  "geometry": {"coordinates":[33.557171,30.086659],"type":"Point"}
}