{
  "id": 2543358,
  "type": "Feature",
  "properties": {
    "tgn:hierarchy":[
        "tgn:2543358",
        "tgn:1000001",
        "tgn:7012149",
        "tgn:1002798",
        "tgn:7007252",
        "tgn:7029392"
    ],
    "tgn:id":2543358,
    "tgn:name":"Norman Olson Lake",
    "tgn:placetype":[
        "aat:300006191"
    ]
},
  "bbox": [],
  "geometry": {"coordinates":[-87.1667,41.45],"type":"Point"}
}