<<<<<<< HEAD
{
  "id": 2335938,
  "type": "Feature",
  "properties": {
    "tgn:hierarchy":[
        "tgn:2335938",
        "tgn:1000001",
        "tgn:7012149",
        "tgn:2001715",
        "tgn:7007708",
        "tgn:7029392"
    ],
    "tgn:id":2335938,
    "tgn:name":"Fossil Lake",
    "tgn:placetype":[
        "aat:300008680"
    ]
},
  "bbox": [],
  "geometry": {"coordinates":[-120.4833,43.3167],"type":"Point"}
}
=======
{"geometry":{"type":"Point","coordinates":[-120.483300,43.316700]},"type":"Feature","properties":{"hierarchy":["tgn:2335938","tgn:1000001","tgn:7012149","tgn:2001715","tgn:7007708","tgn:7029392"],"placetype":["aat:300008680"],"id":2335938,"name:xx":"Fossil Lake"}}
>>>>>>> 03f74aca74312dbeaf24d7e61306dd6a786dc3d0
