{
  "id": 2172670,
  "type": "Feature",
  "properties": {
    "tgn:hierarchy":[
        "tgn:2172670",
        "tgn:1000001",
        "tgn:7012149",
        "tgn:7007252",
        "tgn:7029392"
    ],
    "tgn:id":2172670,
    "tgn:name":"Billman Ditch",
    "tgn:placetype":[
        "aat:300006075"
    ]
},
  "bbox": [],
  "geometry": {"coordinates":[-86.05,41.5333],"type":"Point"}
}