{
  "id": 2423893,
  "type": "Feature",
  "properties": {
    "tgn:hierarchy":[
        "tgn:2423893",
        "tgn:1000001",
        "tgn:7012149",
        "tgn:1002742",
        "tgn:7007920",
        "tgn:7029392"
    ],
    "tgn:id":2423893,
    "tgn:name":"Johnny Lakes",
    "tgn:placetype":[
        "aat:300008680"
    ]
},
  "bbox": [],
  "geometry": {"coordinates":[-120.45,48.8167],"type":"Point"}
}