{
  "id": 2363379,
  "type": "Feature",
  "properties": {
    "tgn:hierarchy":[
        "tgn:2363379",
        "tgn:1000001",
        "tgn:7016172",
        "tgn:2000119",
        "tgn:7012149",
        "tgn:7029392"
    ],
    "tgn:id":2363379,
    "tgn:name":"Green Creek",
    "tgn:placetype":[
        "aat:300008706"
    ]
},
  "bbox": [],
  "geometry": {"coordinates":[-92.6167,35.35],"type":"Point"}
}