{
  "id": 2219035,
  "type": "Feature",
  "properties": {
    "tgn:hierarchy":[
        "tgn:2219035",
        "tgn:1000001",
        "tgn:2000769",
        "tgn:7012149",
        "tgn:7007255",
        "tgn:7029392"
    ],
    "tgn:id":2219035,
    "tgn:name":"Caney Creek",
    "tgn:placetype":[
        "aat:300008706"
    ]
},
  "bbox": [],
  "geometry": {"coordinates":[-83.8167,36.65],"type":"Point"}
}