{
  "id": 2269628,
  "type": "Feature",
  "properties": {
    "tgn:hierarchy":[
        "tgn:2269628",
        "tgn:1000001",
        "tgn:1002286",
        "tgn:7012149",
        "tgn:7007710",
        "tgn:7029392"
    ],
    "tgn:id":2269628,
    "tgn:name":"Crowley Hollow",
    "tgn:placetype":[
        "aat:300008761"
    ]
},
  "bbox": [],
  "geometry": {"coordinates":[-77.9167,41.3167],"type":"Point"}
}