{
  "id": 2174527,
  "type": "Feature",
  "properties": {
    "tgn:hierarchy":[
        "tgn:2174527",
        "tgn:1000001",
        "tgn:2001416",
        "tgn:7012149",
        "tgn:7007526",
        "tgn:7029392"
    ],
    "tgn:id":2174527,
    "tgn:name":"Bishop Spring",
    "tgn:placetype":[
        "aat:300008697"
    ]
},
  "bbox": [],
  "geometry": {"coordinates":[-114.6333,37.4167],"type":"Point"}
}