{
  "id": 2564042,
  "type": "Feature",
  "properties": {
    "tgn:hierarchy":[
        "tgn:2564042",
        "tgn:1002338",
        "tgn:1000001",
        "tgn:7012149",
        "tgn:7007516",
        "tgn:7029392"
    ],
    "tgn:id":2564042,
    "tgn:name":"Oystershell Point",
    "tgn:placetype":[
        "aat:300008850"
    ]
},
  "bbox": [],
  "geometry": {"coordinates":[-75.9833,38.5833],"type":"Point"}
}