<<<<<<< HEAD
{
  "id": 2402588,
  "type": "Feature",
  "properties": {
    "tgn:hierarchy":[
        "tgn:2402588",
        "tgn:1000001",
        "tgn:7012149",
        "tgn:2000278",
        "tgn:7007240",
        "tgn:7029392"
    ],
    "tgn:id":2402588,
    "tgn:name":"Hostage Branch",
    "tgn:placetype":[
        "aat:300008699"
    ]
},
  "bbox": [],
  "geometry": {"coordinates":[-84.9,30.2333],"type":"Point"}
}
=======
{"geometry":{"type":"Point","coordinates":[-84.900000,30.233300]},"type":"Feature","properties":{"hierarchy":["tgn:2402588","tgn:1000001","tgn:7012149","tgn:2000278","tgn:7007240","tgn:7029392"],"placetype":["aat:300008699"],"id":2402588,"name:xx":"Hostage Branch"}}
>>>>>>> 03f74aca74312dbeaf24d7e61306dd6a786dc3d0
