{
  "id": 2495653,
  "type": "Feature",
  "properties": {
    "tgn:hierarchy":[
        "tgn:2495653",
        "tgn:1002808",
        "tgn:1000001",
        "tgn:7012149",
        "tgn:7007711",
        "tgn:7029392"
    ],
    "tgn:id":2495653,
    "tgn:name":"Mashapaug Pond",
    "tgn:placetype":[
        "aat:300008680"
    ]
},
  "bbox": [],
  "geometry": {"coordinates":[-71.4333,41.7833],"type":"Point"}
}