{
  "id": 7161205,
  "type": "Feature",
  "properties": {
    "tgn:hierarchy":[
        "tgn:7161205",
        "tgn:1000003",
        "tgn:7003678",
        "tgn:7000084",
        "tgn:7029392"
    ],
    "tgn:id":7161205,
    "tgn:name":"Hoheroth",
    "tgn:placetype":[
        "aat:300008777"
    ]
},
  "bbox": [],
  "geometry": {"coordinates":[9.366667,50.383333],"type":"Point"}
}