{
  "id": 7398062,
  "type": "Feature",
  "properties": {
    "tgn:hierarchy":[
        "tgn:7398062",
        "tgn:1000001",
        "tgn:1001960",
        "tgn:7005560",
        "tgn:7029392"
    ],
    "tgn:id":7398062,
    "tgn:name":"Pueblo Viejo",
    "tgn:placetype":[
        "aat:300266554",
        "aat:300008699"
    ]
},
  "bbox": [],
  "geometry": {"coordinates":[-110.618056,30.898889],"type":"Point"}
}