{
  "id": 2543772,
  "type": "Feature",
  "properties": {
    "tgn:hierarchy":[
        "tgn:2543772",
        "tgn:1000001",
        "tgn:2002367",
        "tgn:7012149",
        "tgn:7007923",
        "tgn:7029392"
    ],
    "tgn:id":2543772,
    "tgn:name":"North Beaver Creek",
    "tgn:placetype":[
        "aat:300008706"
    ]
},
  "bbox": [],
  "geometry": {"coordinates":[-105.7333,43.9833],"type":"Point"}
}