{
  "id": 1120817,
  "type": "Feature",
  "properties": {
    "tgn:hierarchy":[
        "tgn:1120817",
        "tgn:1000003",
        "tgn:7006660",
        "tgn:7029392"
    ],
    "tgn:id":1120817,
    "tgn:name":"\u010ceremo\u0161",
    "tgn:placetype":[
        "aat:300008707"
    ]
},
  "bbox": [],
  "geometry": {"coordinates":[25.6167,48.3833],"type":"Point"}
}