{
  "id": 1103837,
  "type": "Feature",
  "properties": {
    "tgn:hierarchy":[
        "tgn:1103837",
        "tgn:1000004",
        "tgn:7000198",
        "tgn:1001996",
        "tgn:7029392"
    ],
    "tgn:id":1103837,
    "tgn:name":"Baih\u0101li Jot",
    "tgn:placetype":[
        "aat:300008795"
    ]
},
  "bbox": [],
  "geometry": {"coordinates":[76.5333,32.85],"type":"Point"}
}