{
  "id": 2575816,
  "type": "Feature",
  "properties": {
    "tgn:hierarchy":[
        "tgn:2575816",
        "tgn:1000001",
        "tgn:7012149",
        "tgn:2001556",
        "tgn:7007709",
        "tgn:7029392"
    ],
    "tgn:id":2575816,
    "tgn:name":"Percys Peak",
    "tgn:placetype":[
        "aat:300008798"
    ]
},
  "bbox": [],
  "geometry": {"coordinates":[-82.2333,35.8333],"type":"Point"}
}