{
  "id": 7342370,
  "type": "Feature",
  "properties": {
    "tgn:hierarchy":[
        "tgn:7342370",
        "tgn:7002760",
        "tgn:1000003",
        "tgn:1000095",
        "tgn:7029392"
    ],
    "tgn:id":7342370,
    "tgn:name":"Carrascal de Cocej\u00f3n",
    "tgn:placetype":[
        "aat:300008347"
    ]
},
  "bbox": [],
  "geometry": {"coordinates":[-3.866667,43.083333],"type":"Point"}
}