{
  "id": 2364246,
  "type": "Feature",
  "properties": {
    "tgn:hierarchy":[
        "tgn:2364246",
        "tgn:1000001",
        "tgn:7012149",
        "tgn:2001516",
        "tgn:7007709",
        "tgn:7029392"
    ],
    "tgn:id":2364246,
    "tgn:name":"Green Ridge",
    "tgn:placetype":[
        "aat:300266640"
    ]
},
  "bbox": [],
  "geometry": {"coordinates":[-82.6333,36.0333],"type":"Point"}
}