<<<<<<< HEAD
{
  "id": 2156527,
  "type": "Feature",
  "properties": {
    "tgn:hierarchy":[
        "tgn:2156527",
        "tgn:1000001",
        "tgn:7012149",
        "tgn:2000481",
        "tgn:7007250",
        "tgn:7029392"
    ],
    "tgn:id":2156527,
    "tgn:name":"Beartrap Ridge",
    "tgn:placetype":[
        "aat:300266640"
    ]
},
  "bbox": [],
  "geometry": {"coordinates":[-114.3833,45.4167],"type":"Point"}
}
=======
{"geometry":{"type":"Point","coordinates":[-114.383300,45.416700]},"type":"Feature","properties":{"hierarchy":["tgn:2156527","tgn:1000001","tgn:7012149","tgn:2000481","tgn:7007250","tgn:7029392"],"placetype":["aat:300266640"],"id":2156527,"name:xx":"Beartrap Ridge"}}
>>>>>>> 03f74aca74312dbeaf24d7e61306dd6a786dc3d0
