{
  "id": 7065974,
  "type": "Feature",
  "properties": {
    "tgn:hierarchy":[
        "tgn:7065974",
        "tgn:7003669",
        "tgn:1000003",
        "tgn:7000084",
        "tgn:7029392"
    ],
    "tgn:id":7065974,
    "tgn:name":"T\u00fcrken",
    "tgn:placetype":[
        "aat:300000206"
    ]
},
  "bbox": [],
  "geometry": {"coordinates":[10.233333,47.666667],"type":"Point"}
}