{
  "id": 7281207,
  "type": "Feature",
  "properties": {
    "tgn:hierarchy":[
        "tgn:7281207",
        "tgn:1001702",
        "tgn:1000049",
        "tgn:1000002",
        "tgn:7029392"
    ],
    "tgn:id":7281207,
    "tgn:name":"Swett, Isla",
    "tgn:placetype":[
        "aat:300008791"
    ]
},
  "bbox": [],
  "geometry": {"coordinates":[-73.683333,-52.666667],"type":"Point"}
}