{
  "id": 2461942,
  "type": "Feature",
  "properties": {
    "tgn:hierarchy":[
        "tgn:2461942",
        "tgn:1000001",
        "tgn:7012149",
        "tgn:7007158",
        "tgn:7029392"
    ],
    "tgn:id":2461942,
    "tgn:name":"Little Turkey Creek",
    "tgn:placetype":[
        "aat:300008706"
    ]
},
  "bbox": [],
  "geometry": {"coordinates":[-105.25,39.0667],"type":"Point"}
}