<<<<<<< HEAD
{
  "id": 2153428,
  "type": "Feature",
  "properties": {
    "tgn:hierarchy":[
        "tgn:2153428",
        "tgn:2001423",
        "tgn:1000001",
        "tgn:7012149",
        "tgn:7007564",
        "tgn:7029392"
    ],
    "tgn:id":2153428,
    "tgn:name":"Bean Pond",
    "tgn:placetype":[
        "aat:300008680"
    ]
},
  "bbox": [],
  "geometry": {"coordinates":[-71.2167,43.75],"type":"Point"}
}
=======
{"geometry":{"type":"Point","coordinates":[-71.216700,43.750000]},"type":"Feature","properties":{"hierarchy":["tgn:2153428","tgn:2001423","tgn:1000001","tgn:7012149","tgn:7007564","tgn:7029392"],"placetype":["aat:300008680"],"id":2153428,"name:xx":"Bean Pond"}}
>>>>>>> 03f74aca74312dbeaf24d7e61306dd6a786dc3d0
