{
  "id": 7283349,
  "type": "Feature",
  "properties": {
    "tgn:hierarchy":[
        "tgn:7283349",
        "tgn:1001702",
        "tgn:1000049",
        "tgn:1000002",
        "tgn:7029392"
    ],
    "tgn:id":7283349,
    "tgn:name":"Pan de Az\u00facar, Isla",
    "tgn:placetype":[
        "aat:300008791"
    ]
},
  "bbox": [],
  "geometry": {"coordinates":[-72.366667,-53.266667],"type":"Point"}
}