<<<<<<< HEAD
{
  "id": 2763562,
  "type": "Feature",
  "properties": {
    "tgn:hierarchy":[
        "tgn:2763562",
        "tgn:1000001",
        "tgn:7012149",
        "tgn:2001274",
        "tgn:7007524",
        "tgn:7029392"
    ],
    "tgn:id":2763562,
    "tgn:name":"Whale Lake",
    "tgn:placetype":[
        "aat:300008680"
    ]
},
  "bbox": [],
  "geometry": {"coordinates":[-114.7,48.8],"type":"Point"}
}
=======
{"geometry":{"type":"Point","coordinates":[-114.700000,48.800000]},"type":"Feature","properties":{"hierarchy":["tgn:2763562","tgn:1000001","tgn:7012149","tgn:2001274","tgn:7007524","tgn:7029392"],"placetype":["aat:300008680"],"id":2763562,"name:xx":"Whale Lake"}}
>>>>>>> 03f74aca74312dbeaf24d7e61306dd6a786dc3d0
