<<<<<<< HEAD
{
  "id": 2257616,
  "type": "Feature",
  "properties": {
    "tgn:hierarchy":[
        "tgn:2257616",
        "tgn:1000001",
        "tgn:7012149",
        "tgn:2000476",
        "tgn:7007250",
        "tgn:7029392"
    ],
    "tgn:id":2257616,
    "tgn:name":"Corral Creek",
    "tgn:placetype":[
        "aat:300008706"
    ]
},
  "bbox": [],
  "geometry": {"coordinates":[-116.3833,45.5667],"type":"Point"}
}
=======
{"geometry":{"type":"Point","coordinates":[-116.383300,45.566700]},"type":"Feature","properties":{"hierarchy":["tgn:2257616","tgn:1000001","tgn:7012149","tgn:2000476","tgn:7007250","tgn:7029392"],"placetype":["aat:300008706"],"id":2257616,"name:xx":"Corral Creek"}}
>>>>>>> 03f74aca74312dbeaf24d7e61306dd6a786dc3d0
