<<<<<<< HEAD
{
  "id": 2762037,
  "type": "Feature",
  "properties": {
    "tgn:hierarchy":[
        "tgn:2762037",
        "tgn:1000001",
        "tgn:7012149",
        "tgn:2000232",
        "tgn:7007158",
        "tgn:7029392"
    ],
    "tgn:id":2762037,
    "tgn:name":"West Serviceberry Draw",
    "tgn:placetype":[
        "aat:300008761"
    ]
},
  "bbox": [],
  "geometry": {"coordinates":[-108.8333,40.4333],"type":"Point"}
}
=======
{"geometry":{"type":"Point","coordinates":[-108.833300,40.433300]},"type":"Feature","properties":{"hierarchy":["tgn:2762037","tgn:1000001","tgn:7012149","tgn:2000232","tgn:7007158","tgn:7029392"],"placetype":["aat:300008761"],"id":2762037,"name:xx":"West Serviceberry Draw"}}
>>>>>>> 03f74aca74312dbeaf24d7e61306dd6a786dc3d0
