{
  "id": 7197390,
  "type": "Feature",
  "properties": {
    "tgn:hierarchy":[
        "tgn:7197390",
        "tgn:7000096",
        "tgn:1000003",
        "tgn:7000084",
        "tgn:7029392"
    ],
    "tgn:id":7197390,
    "tgn:name":"Die Schwarzenberge",
    "tgn:placetype":[
        "aat:300008777"
    ]
},
  "bbox": [],
  "geometry": {"coordinates":[12.25,53.116667],"type":"Point"}
}