{
  "id": 1126657,
  "type": "Feature",
  "properties": {
    "tgn:hierarchy":[
        "tgn:1126657",
        "tgn:1000004",
        "tgn:7016720",
        "tgn:1000135",
        "tgn:7029392"
    ],
    "tgn:id":1126657,
    "tgn:name":"Magat",
    "tgn:placetype":[
        "aat:300008707"
    ]
},
  "bbox": [],
  "geometry": {"coordinates":[121.8167,17.0333],"type":"Point"}
}