{
  "id": 2700091,
  "type": "Feature",
  "properties": {
    "tgn:hierarchy":[
        "tgn:2700091",
        "tgn:1000001",
        "tgn:7012149",
        "tgn:1002742",
        "tgn:7007920",
        "tgn:7029392"
    ],
    "tgn:id":2700091,
    "tgn:name":"Stump Springs",
    "tgn:placetype":[
        "aat:300008697"
    ]
},
  "bbox": [],
  "geometry": {"coordinates":[-119.8167,48.7833],"type":"Point"}
}