{
  "id": 7546144,
  "type": "Feature",
  "properties": {
    "tgn:hierarchy":[
        "tgn:7546144",
        "tgn:1000004",
        "tgn:7000198",
        "tgn:1001977",
        "tgn:7029392"
    ],
    "tgn:id":7546144,
    "tgn:name:en":"B\u0101tang La",
    "tgn:placetype":[
        "aat:300259572"
    ]
},
  "bbox": [],
  "geometry": {"coordinates":[88.916667,27.330556],"type":"Point"}
}