{
  "id": 2560676,
  "type": "Feature",
  "properties": {
    "tgn:hierarchy":[
        "tgn:2560676",
        "tgn:1000001",
        "tgn:7012149",
        "tgn:2001709",
        "tgn:7007708",
        "tgn:7029392"
    ],
    "tgn:id":2560676,
    "tgn:name":"Orejana Waterhole",
    "tgn:placetype":[
        "aat:300006191"
    ]
},
  "bbox": [],
  "geometry": {"coordinates":[-119.4667,42.9333],"type":"Point"}
}