{
  "id": 1124367,
  "type": "Feature",
  "properties": {
    "tgn:hierarchy":[
        "tgn:1124367",
        "tgn:1001826",
        "tgn:1000047",
        "tgn:7002456",
        "tgn:1000002",
        "tgn:7029392"
    ],
    "tgn:id":1124367,
    "tgn:name":"Greg\u00f3rio",
    "tgn:placetype":[
        "aat:300008707"
    ]
},
  "bbox": [],
  "geometry": {"coordinates":[-70.7667,-6.8333],"type":"Point"}
}