{
  "id": 1081147,
  "type": "Feature",
  "properties": {
    "tgn:hierarchy":[
        "tgn:1081147",
        "tgn:1000985",
        "tgn:7016529",
        "tgn:7016531",
        "tgn:1000004",
        "tgn:1000120",
        "tgn:7029392"
    ],
    "tgn:id":1081147,
    "tgn:name":"Rumoi",
    "tgn:placetype":[
        "aat:300008347"
    ]
},
  "bbox": [],
  "geometry": {"coordinates":[141.6667,43.95],"type":"Point"}
}