{
  "id": 2669840,
  "type": "Feature",
  "properties": {
    "tgn:hierarchy":[
        "tgn:2669840",
        "tgn:1000001",
        "tgn:7012149",
        "tgn:2001887",
        "tgn:7007825",
        "tgn:7029392"
    ],
    "tgn:id":2669840,
    "tgn:name":"Slippery Branch",
    "tgn:placetype":[
        "aat:300008699"
    ]
},
  "bbox": [],
  "geometry": {"coordinates":[-87.5667,35.6333],"type":"Point"}
}