{
  "id": 7227788,
  "type": "Feature",
  "properties": {
    "tgn:hierarchy":[
        "tgn:7227788",
        "tgn:7002711",
        "tgn:7001338",
        "tgn:1000003",
        "tgn:1000074",
        "tgn:7029392"
    ],
    "tgn:id":7227788,
    "tgn:name":"Grammatika\u00edika",
    "tgn:placetype":[
        "aat:300008347"
    ]
},
  "bbox": [],
  "geometry": {"coordinates":[20.141111,39.214722],"type":"Point"}
}