<<<<<<< HEAD
{
  "id": 7051404,
  "type": "Feature",
  "properties": {
    "tgn:hierarchy":[
        "tgn:7051404",
        "tgn:1000003",
        "tgn:7003120",
        "tgn:1000080",
        "tgn:7029392"
    ],
    "tgn:id":7051404,
    "tgn:name":"La Colletta",
    "tgn:placetype":[
        "aat:300259572"
    ]
},
  "bbox": [],
  "geometry": {"coordinates":[7.3,44.7],"type":"Point"}
}
=======
{"geometry":{"type":"Point","coordinates":[7.300000,44.700000]},"type":"Feature","properties":{"hierarchy":["tgn:7051404","tgn:1000003","tgn:7003120","tgn:1000080","tgn:7029392"],"placetype":["aat:300259572"],"id":7051404,"name:xx":"La Colletta"}}
>>>>>>> 03f74aca74312dbeaf24d7e61306dd6a786dc3d0
