{
  "id": 2329819,
  "type": "Feature",
  "properties": {
    "tgn:hierarchy":[
        "tgn:2329819",
        "tgn:7013349",
        "tgn:1000001",
        "tgn:7012149",
        "tgn:7007708",
        "tgn:7029392"
    ],
    "tgn:id":2329819,
    "tgn:name":"Fizz Spring",
    "tgn:placetype":[
        "aat:300008697"
    ]
},
  "bbox": [],
  "geometry": {"coordinates":[-117.25,44.9167],"type":"Point"}
}