<<<<<<< HEAD
{
  "id": 2336118,
  "type": "Feature",
  "properties": {
    "tgn:hierarchy":[
        "tgn:2336118",
        "tgn:1000001",
        "tgn:7012149",
        "tgn:2000346",
        "tgn:7007248",
        "tgn:7029392"
    ],
    "tgn:id":2336118,
    "tgn:name":"Foster Hollow",
    "tgn:placetype":[
        "aat:300008761"
    ]
},
  "bbox": [],
  "geometry": {"coordinates":[-84.4833,34.9],"type":"Point"}
}
=======
{"geometry":{"type":"Point","coordinates":[-84.483300,34.900000]},"type":"Feature","properties":{"hierarchy":["tgn:2336118","tgn:1000001","tgn:7012149","tgn:2000346","tgn:7007248","tgn:7029392"],"placetype":["aat:300008761"],"id":2336118,"name:xx":"Foster Hollow"}}
>>>>>>> 03f74aca74312dbeaf24d7e61306dd6a786dc3d0
