{
  "id": 7591787,
  "type": "Feature",
  "properties": {
    "tgn:hierarchy":[
        "tgn:7591787",
        "tgn:1000004",
        "tgn:7000198",
        "tgn:7000799",
        "tgn:7029392"
    ],
    "tgn:id":7591787,
    "tgn:name:en":"Karan B\u0101gh",
    "tgn:placetype":[
        "aat:300008347"
    ]
},
  "bbox": [],
  "geometry": {"coordinates":[74.8375,32.669444],"type":"Point"}
}