<<<<<<< HEAD
{
  "id": 2258005,
  "type": "Feature",
  "properties": {
    "tgn:hierarchy":[
        "tgn:2258005",
        "tgn:1000001",
        "tgn:2000925",
        "tgn:7012149",
        "tgn:7007515",
        "tgn:7029392"
    ],
    "tgn:id":2258005,
    "tgn:name":"Corvette Ledge",
    "tgn:placetype":[
        "aat:300132348"
    ]
},
  "bbox": [],
  "geometry": {"coordinates":[-69.5333,43.8667],"type":"Point"}
}
=======
{"geometry":{"type":"Point","coordinates":[-69.533300,43.866700]},"type":"Feature","properties":{"hierarchy":["tgn:2258005","tgn:1000001","tgn:2000925","tgn:7012149","tgn:7007515","tgn:7029392"],"placetype":["aat:300132348"],"id":2258005,"name:xx":"Corvette Ledge"}}
>>>>>>> 03f74aca74312dbeaf24d7e61306dd6a786dc3d0
