{
  "id": 7377653,
  "type": "Feature",
  "properties": {
    "tgn:hierarchy":[
        "tgn:7377653",
        "tgn:1000001",
        "tgn:7005589",
        "tgn:7005560",
        "tgn:7029392"
    ],
    "tgn:id":7377653,
    "tgn:name":"Las Bolas, Arroyo",
    "tgn:placetype":[
        "aat:300266554",
        "aat:300008699"
    ]
},
  "bbox": [],
  "geometry": {"coordinates":[-100.216667,27.05],"type":"Point"}
}