{
  "id": 7588491,
  "type": "Feature",
  "properties": {
    "tgn:hierarchy":[
        "tgn:7588491",
        "tgn:1000004",
        "tgn:7000198",
        "tgn:7000799",
        "tgn:7029392"
    ],
    "tgn:id":7588491,
    "tgn:name:en":"Gheta",
    "tgn:placetype":[
        "aat:300008347"
    ]
},
  "bbox": [],
  "geometry": {"coordinates":[74.241667,33.822222],"type":"Point"}
}