{
  "id": 7083130,
  "type": "Feature",
  "properties": {
    "tgn:hierarchy":[
        "tgn:7083130",
        "tgn:7003669",
        "tgn:1000003",
        "tgn:7000084",
        "tgn:7029392"
    ],
    "tgn:id":7083130,
    "tgn:name":"Willing",
    "tgn:placetype":[
        "aat:300008347"
    ]
},
  "bbox": [],
  "geometry": {"coordinates":[12.966667,48.633333],"type":"Point"}
}