<<<<<<< HEAD
{
  "id": 7025924,
  "type": "Feature",
  "properties": {
    "tgn:hierarchy":[
        "tgn:7025924",
        "tgn:7002445",
        "tgn:1000003",
        "tgn:7011961",
        "tgn:7008591",
        "tgn:7029392"
    ],
    "tgn:id":7025924,
    "tgn:name:ang":"Mapledre",
    "tgn:placetype":[
        "aat:300008347",
        "aat:300008372"
    ]
},
  "bbox": [],
  "geometry": {"coordinates":[-2.4,50.85],"type":"Point"}
}
=======
{"geometry":{"type":"Point","coordinates":[-2.400000,50.850000]},"type":"Feature","properties":{"hierarchy":["tgn:7025924","tgn:7002445","tgn:1000003","tgn:7011961","tgn:7008591","tgn:7029392"],"placetype":["aat:300008347","aat:300008372"],"id":7025924,"name:ang":"Mapledre"}}
>>>>>>> 03f74aca74312dbeaf24d7e61306dd6a786dc3d0
