{
  "id": 1051834,
  "type": "Feature",
  "properties": {
    "tgn:hierarchy":[
        "tgn:1051834",
        "tgn:7012908",
        "tgn:1000004",
        "tgn:7014786",
        "tgn:7029392"
    ],
    "tgn:id":1051834,
    "tgn:name":"Zhilaya Kosa",
    "tgn:placetype":[
        "aat:300008347"
    ]
},
  "bbox": [],
  "geometry": {"coordinates":[53.1667,46.8167],"type":"Point"}
}