{
  "id": 2157654,
  "type": "Feature",
  "properties": {
    "tgn:hierarchy":[
        "tgn:2157654",
        "tgn:1002140",
        "tgn:1000001",
        "tgn:7012149",
        "tgn:7007520",
        "tgn:7029392"
    ],
    "tgn:id":2157654,
    "tgn:name":"Beaver Dam Drain",
    "tgn:placetype":[
        "aat:300006075"
    ]
},
  "bbox": [],
  "geometry": {"coordinates":[-86.15,42.55],"type":"Point"}
}