{
  "id": 2428051,
  "type": "Feature",
  "properties": {
    "tgn:hierarchy":[
        "tgn:2428051",
        "tgn:1000001",
        "tgn:7012149",
        "tgn:2001456",
        "tgn:7007566",
        "tgn:7029392"
    ],
    "tgn:id":2428051,
    "tgn:name":"Juanita Tunnel",
    "tgn:placetype":[
        "aat:300000390"
    ]
},
  "bbox": [],
  "geometry": {"coordinates":[-107.1833,34.0833],"type":"Point"}
}