{
  "id": 7535703,
  "type": "Feature",
  "properties": {
    "tgn:hierarchy":[
        "tgn:7535703",
        "tgn:7001242",
        "tgn:7016833",
        "tgn:1001088",
        "tgn:7029392"
    ],
    "tgn:id":7535703,
    "tgn:name:en":"Ibsh\u0101d\u0101t",
    "tgn:placetype":[
        "aat:300008347"
    ]
},
  "bbox": [],
  "geometry": {"coordinates":[30.742474,27.84143],"type":"Point"}
}