{
  "id": 7233259,
  "type": "Feature",
  "properties": {
    "tgn:hierarchy":[
        "tgn:7233259",
        "tgn:7002750",
        "tgn:7001399",
        "tgn:1000003",
        "tgn:1000074",
        "tgn:7029392"
    ],
    "tgn:id":7233259,
    "tgn:name":"Ampel\u00e1kia",
    "tgn:placetype":[
        "aat:300008347"
    ]
},
  "bbox": [],
  "geometry": {"coordinates":[22.556111,39.853889],"type":"Point"}
}