{
  "id": 2009995,
  "type": "Feature",
  "properties": {
    "tgn:hierarchy":[
        "tgn:2009995",
        "tgn:1000001",
        "tgn:7012149",
        "tgn:7007157",
        "tgn:1002857",
        "tgn:7029392"
    ],
    "tgn:id":2009995,
    "tgn:name":"Angelus Oaks",
    "tgn:placetype":[
        "aat:300008347"
    ]
},
  "bbox": [],
  "geometry": {"coordinates":[-116.9667,34.1333],"type":"Point"}
}