{
  "id": 2776323,
  "type": "Feature",
  "properties": {
    "tgn:hierarchy":[
        "tgn:2776323",
        "tgn:1000001",
        "tgn:1002601",
        "tgn:7012149",
        "tgn:7007159",
        "tgn:7029392"
    ],
    "tgn:id":2776323,
    "tgn:name":"Winchester Club Pond",
    "tgn:placetype":[
        "aat:300006191"
    ]
},
  "bbox": [],
  "geometry": {"coordinates":[-73.1167,41.9167],"type":"Point"}
}