{
  "id": 2705899,
  "type": "Feature",
  "properties": {
    "tgn:hierarchy":[
        "tgn:2705899",
        "tgn:1000001",
        "tgn:7012149",
        "tgn:1002971",
        "tgn:7007710",
        "tgn:7029392"
    ],
    "tgn:id":2705899,
    "tgn:name":"Sutton Mill",
    "tgn:placetype":[
        "aat:300008347"
    ]
},
  "bbox": [],
  "geometry": {"coordinates":[-79.7667,41.1833],"type":"Point"}
}