{
  "id": 2737162,
  "type": "Feature",
  "properties": {
    "tgn:hierarchy":[
        "tgn:2737162",
        "tgn:1000001",
        "tgn:7006451",
        "tgn:2000092",
        "tgn:7012149",
        "tgn:7029392"
    ],
    "tgn:id":2737162,
    "tgn:name":"Two Springs Ridge",
    "tgn:placetype":[
        "aat:300266640"
    ]
},
  "bbox": [],
  "geometry": {"coordinates":[-112.2833,36.35],"type":"Point"}
}