{
  "id": 2668558,
  "type": "Feature",
  "properties": {
    "tgn:hierarchy":[
        "tgn:2668558",
        "tgn:1000001",
        "tgn:7012149",
        "tgn:7007157",
        "tgn:1002957",
        "tgn:7029392"
    ],
    "tgn:id":2668558,
    "tgn:name":"Slate Gulch",
    "tgn:placetype":[
        "aat:300008761"
    ]
},
  "bbox": [],
  "geometry": {"coordinates":[-120.3667,37.8833],"type":"Point"}
}