{
  "id": 2364161,
  "type": "Feature",
  "properties": {
    "tgn:hierarchy":[
        "tgn:2364161",
        "tgn:1000001",
        "tgn:1002293",
        "tgn:7012149",
        "tgn:7007708",
        "tgn:7029392"
    ],
    "tgn:id":2364161,
    "tgn:name":"Green Point",
    "tgn:placetype":[
        "aat:300008850"
    ]
},
  "bbox": [],
  "geometry": {"coordinates":[-123.0833,46.1667],"type":"Point"}
}