<<<<<<< HEAD
{
  "id": 2333871,
  "type": "Feature",
  "properties": {
    "tgn:hierarchy":[
        "tgn:2333871",
        "tgn:1000001",
        "tgn:2000954",
        "tgn:7012149",
        "tgn:7007520",
        "tgn:7029392"
    ],
    "tgn:id":2333871,
    "tgn:name":"Forbush Corner",
    "tgn:placetype":[
        "aat:300008347"
    ]
},
  "bbox": [],
  "geometry": {"coordinates":[-84.7,44.7833],"type":"Point"}
}
=======
{"geometry":{"type":"Point","coordinates":[-84.700000,44.783300]},"type":"Feature","properties":{"hierarchy":["tgn:2333871","tgn:1000001","tgn:2000954","tgn:7012149","tgn:7007520","tgn:7029392"],"placetype":["aat:300008347"],"id":2333871,"name:xx":"Forbush Corner"}}
>>>>>>> 03f74aca74312dbeaf24d7e61306dd6a786dc3d0
