<<<<<<< HEAD
{
  "id": 7117508,
  "type": "Feature",
  "properties": {
    "tgn:hierarchy":[
        "tgn:7117508",
        "tgn:1000003",
        "tgn:7003676",
        "tgn:7000084",
        "tgn:7029392"
    ],
    "tgn:id":7117508,
    "tgn:name":"Ostland",
    "tgn:placetype":[
        "aat:300008347"
    ]
},
  "bbox": [],
  "geometry": {"coordinates":[6.733333,53.6],"type":"Point"}
}
=======
{"geometry":{"type":"Point","coordinates":[6.733333,53.600000]},"type":"Feature","properties":{"hierarchy":["tgn:7117508","tgn:1000003","tgn:7003676","tgn:7000084","tgn:7029392"],"placetype":["aat:300008347"],"id":7117508,"name:xx":"Ostland"}}
>>>>>>> 03f74aca74312dbeaf24d7e61306dd6a786dc3d0
