{
  "id": 2711671,
  "type": "Feature",
  "properties": {
    "tgn:hierarchy":[
        "tgn:2711671",
        "tgn:1000001",
        "tgn:7012149",
        "tgn:2001542",
        "tgn:7007709",
        "tgn:7029392"
    ],
    "tgn:id":2711671,
    "tgn:name":"Tar Ridge",
    "tgn:placetype":[
        "aat:300266640"
    ]
},
  "bbox": [],
  "geometry": {"coordinates":[-80.95,36.45],"type":"Point"}
}