{
  "id": 2240143,
  "type": "Feature",
  "properties": {
    "tgn:hierarchy":[
        "tgn:2240143",
        "tgn:1000001",
        "tgn:2001575",
        "tgn:7012149",
        "tgn:7007705",
        "tgn:7029392"
    ],
    "tgn:id":2240143,
    "tgn:name":"Circle Buttes",
    "tgn:placetype":[
        "aat:300386831"
    ]
},
  "bbox": [],
  "geometry": {"coordinates":[-101.55,46.3833],"type":"Point"}
}