{
  "id": 7203152,
  "type": "Feature",
  "properties": {
    "tgn:hierarchy":[
        "tgn:7203152",
        "tgn:1000003",
        "tgn:7003676",
        "tgn:7000084",
        "tgn:7029392"
    ],
    "tgn:id":7203152,
    "tgn:name":"Brinkmoor",
    "tgn:placetype":[
        "aat:300008903"
    ]
},
  "bbox": [],
  "geometry": {"coordinates":[8.933333,52.516667],"type":"Point"}
}