{
  "id": 7466062,
  "type": "Feature",
  "properties": {
    "tgn:hierarchy":[
        "tgn:7466062",
        "tgn:7002445",
        "tgn:1000003",
        "tgn:7008185",
        "tgn:7008591",
        "tgn:7029392"
    ],
    "tgn:id":7466062,
    "tgn:name:en":"Blaxhall",
    "tgn:placetype":[
        "aat:300008347"
    ]
},
  "bbox": [],
  "geometry": {"coordinates":[1.45,52.15],"type":"Point"}
}