<<<<<<< HEAD
{
  "id": 7483583,
  "type": "Feature",
  "properties": {
    "tgn:hierarchy":[
        "tgn:7483583",
        "tgn:7487020",
        "tgn:1000004",
        "tgn:1000141",
        "tgn:7029392"
    ],
    "tgn:id":7483583,
    "tgn:name":"Xinghua Gongshang",
    "tgn:placetype":[
        "aat:300006495"
    ]
},
  "bbox": [],
  "geometry": {"coordinates":[120.642778,24.429167],"type":"Point"}
}
=======
{"geometry":{"type":"Point","coordinates":[120.642778,24.429167]},"type":"Feature","properties":{"hierarchy":["tgn:7483583","tgn:7487020","tgn:1000004","tgn:1000141","tgn:7029392"],"placetype":["aat:300006495"],"id":7483583,"name:xx":"Xinghua Gongshang"}}
>>>>>>> 03f74aca74312dbeaf24d7e61306dd6a786dc3d0
