{
  "id": 2011296,
  "type": "Feature",
  "properties": {
    "tgn:hierarchy":[
        "tgn:2011296",
        "tgn:1000001",
        "tgn:7012149",
        "tgn:7007157",
        "tgn:1002956",
        "tgn:7029392"
    ],
    "tgn:id":2011296,
    "tgn:name":"Fairview",
    "tgn:placetype":[
        "aat:300008347"
    ]
},
  "bbox": [],
  "geometry": {"coordinates":[-118.4833,35.9167],"type":"Point"}
}