{
  "id": 7544418,
  "type": "Feature",
  "properties": {
    "tgn:hierarchy":[
        "tgn:7544418",
        "tgn:7001242",
        "tgn:7016833",
        "tgn:7001335",
        "tgn:7029392"
    ],
    "tgn:id":7544418,
    "tgn:name:en":"Khubay\u0163 al Kab\u012br, W\u0101d\u012b",
    "tgn:placetype":[
        "aat:300379998"
    ]
},
  "bbox": [],
  "geometry": {"coordinates":[33.874812,30.24254],"type":"Point"}
}