{
  "id": 7157661,
  "type": "Feature",
  "properties": {
    "tgn:hierarchy":[
        "tgn:7157661",
        "tgn:7003669",
        "tgn:1000003",
        "tgn:7000084",
        "tgn:7029392"
    ],
    "tgn:id":7157661,
    "tgn:name":"Kleiner Kalter",
    "tgn:placetype":[
        "aat:300008798"
    ]
},
  "bbox": [],
  "geometry": {"coordinates":[12.866667,47.583333],"type":"Point"}
}