{
  "id": 2502697,
  "type": "Feature",
  "properties": {
    "tgn:hierarchy":[
        "tgn:2502697",
        "tgn:1000001",
        "tgn:7012149",
        "tgn:1002793",
        "tgn:7007240",
        "tgn:7029392"
    ],
    "tgn:id":2502697,
    "tgn:name":"McLeod, Lake",
    "tgn:placetype":[
        "aat:300008680"
    ]
},
  "bbox": [],
  "geometry": {"coordinates":[-81.75,27.9667],"type":"Point"}
}