{
  "id": 7076512,
  "type": "Feature",
  "properties": {
    "tgn:hierarchy":[
        "tgn:7076512",
        "tgn:1000003",
        "tgn:7003682",
        "tgn:7000084",
        "tgn:7029392"
    ],
    "tgn:id":7076512,
    "tgn:name":"Herzfeld",
    "tgn:placetype":[
        "aat:300008347"
    ]
},
  "bbox": [],
  "geometry": {"coordinates":[6.216667,50.133333],"type":"Point"}
}