{
  "id": 2494472,
  "type": "Feature",
  "properties": {
    "tgn:hierarchy":[
        "tgn:2494472",
        "tgn:1000001",
        "tgn:1002188",
        "tgn:7012149",
        "tgn:7007252",
        "tgn:7029392"
    ],
    "tgn:id":2494472,
    "tgn:name":"Martin Ditch",
    "tgn:placetype":[
        "aat:300006075"
    ]
},
  "bbox": [],
  "geometry": {"coordinates":[-86.2667,40.1167],"type":"Point"}
}