{
  "id": 2400526,
  "type": "Feature",
  "properties": {
    "tgn:hierarchy":[
        "tgn:2400526",
        "tgn:1000001",
        "tgn:7012149",
        "tgn:7007157",
        "tgn:2000184",
        "tgn:7029392"
    ],
    "tgn:id":2400526,
    "tgn:name":"Horse Lake",
    "tgn:placetype":[
        "aat:300008680"
    ]
},
  "bbox": [],
  "geometry": {"coordinates":[-120.4833,40.65],"type":"Point"}
}