{
  "id": 2270177,
  "type": "Feature",
  "properties": {
    "tgn:hierarchy":[
        "tgn:2270177",
        "tgn:1000001",
        "tgn:7006451",
        "tgn:2000095",
        "tgn:7012149",
        "tgn:7029392"
    ],
    "tgn:id":2270177,
    "tgn:name":"Crystal Cave",
    "tgn:placetype":[
        "aat:300008746"
    ]
},
  "bbox": [],
  "geometry": {"coordinates":[-109.3667,33.1667],"type":"Point"}
}