{
  "id": 2634079,
  "type": "Feature",
  "properties": {
    "tgn:hierarchy":[
        "tgn:2634079",
        "tgn:1000001",
        "tgn:2000782",
        "tgn:7012149",
        "tgn:7007255",
        "tgn:7029392"
    ],
    "tgn:id":2634079,
    "tgn:name":"Russell Branch",
    "tgn:placetype":[
        "aat:300008699"
    ]
},
  "bbox": [],
  "geometry": {"coordinates":[-83.7333,37.0167],"type":"Point"}
}