<<<<<<< HEAD
{
  "id": 7474125,
  "type": "Feature",
  "properties": {
    "tgn:hierarchy":[
        "tgn:7474125",
        "tgn:7001004",
        "tgn:1000004",
        "tgn:1000141",
        "tgn:7029392"
    ],
    "tgn:id":7474125,
    "tgn:name":"Zhougongcuo",
    "tgn:placetype":[
        "aat:300008347"
    ]
},
  "bbox": [],
  "geometry": {"coordinates":[120.391711,22.647304],"type":"Point"}
}
=======
{"geometry":{"type":"Point","coordinates":[120.391711,22.647304]},"type":"Feature","properties":{"hierarchy":["tgn:7474125","tgn:7001004","tgn:1000004","tgn:1000141","tgn:7029392"],"placetype":["aat:300008347"],"id":7474125,"name:xx":"Zhougongcuo"}}
>>>>>>> 03f74aca74312dbeaf24d7e61306dd6a786dc3d0
