{
  "id": 2474931,
  "type": "Feature",
  "properties": {
    "tgn:hierarchy":[
        "tgn:2474931",
        "tgn:1000001",
        "tgn:7012149",
        "tgn:2001451",
        "tgn:7007566",
        "tgn:7029392"
    ],
    "tgn:id":2474931,
    "tgn:name":"Lower Vallecito Reservoir",
    "tgn:placetype":[
        "aat:300006191"
    ]
},
  "bbox": [],
  "geometry": {"coordinates":[-106.65,35.7667],"type":"Point"}
}