<<<<<<< HEAD
{
  "id": 2257475,
  "type": "Feature",
  "properties": {
    "tgn:hierarchy":[
        "tgn:2257475",
        "tgn:1000001",
        "tgn:7006451",
        "tgn:7012149",
        "tgn:2000097",
        "tgn:7029392"
    ],
    "tgn:id":2257475,
    "tgn:name":"Coronado Mobile Home Park",
    "tgn:placetype":[
        "aat:300008347"
    ]
},
  "bbox": [],
  "geometry": {"coordinates":[-111.7667,33.4],"type":"Point"}
}
=======
{"geometry":{"type":"Point","coordinates":[-111.766700,33.400000]},"type":"Feature","properties":{"hierarchy":["tgn:2257475","tgn:1000001","tgn:7006451","tgn:7012149","tgn:2000097","tgn:7029392"],"placetype":["aat:300008347"],"id":2257475,"name:xx":"Coronado Mobile Home Park"}}
>>>>>>> 03f74aca74312dbeaf24d7e61306dd6a786dc3d0
