<<<<<<< HEAD
{
  "id": 7371869,
  "type": "Feature",
  "properties": {
    "tgn:hierarchy":[
        "tgn:7371869",
        "tgn:7005586",
        "tgn:1000001",
        "tgn:7005560",
        "tgn:7029392"
    ],
    "tgn:id":7371869,
    "tgn:name":"La Mota\u00f1a",
    "tgn:placetype":[
        "aat:300008347"
    ]
},
  "bbox": [],
  "geometry": {"coordinates":[-104.133333,21.083333],"type":"Point"}
}
=======
{"geometry":{"type":"Point","coordinates":[-104.133333,21.083333]},"type":"Feature","properties":{"hierarchy":["tgn:7371869","tgn:7005586","tgn:1000001","tgn:7005560","tgn:7029392"],"placetype":["aat:300008347"],"id":7371869,"name:xx":"La Mota\u00f1a"}}
>>>>>>> 03f74aca74312dbeaf24d7e61306dd6a786dc3d0
