{
  "id": 1040691,
  "type": "Feature",
  "properties": {
    "tgn:hierarchy":[
        "tgn:1040691",
        "tgn:1000003",
        "tgn:7003682",
        "tgn:7000084",
        "tgn:7029392"
    ],
    "tgn:id":1040691,
    "tgn:name":"P\u00fcnderich",
    "tgn:placetype":[
        "aat:300008347"
    ]
},
  "bbox": [],
  "geometry": {"coordinates":[7.116667,50.033333],"type":"Point"}
}