{
  "id": 2439538,
  "type": "Feature",
  "properties": {
    "tgn:hierarchy":[
        "tgn:2439538",
        "tgn:1000001",
        "tgn:7012149",
        "tgn:2000216",
        "tgn:7007158",
        "tgn:7029392"
    ],
    "tgn:id":2439538,
    "tgn:name":"Kirtz Ditch",
    "tgn:placetype":[
        "aat:300006075"
    ]
},
  "bbox": [],
  "geometry": {"coordinates":[-106.3333,40.1333],"type":"Point"}
}