{
  "id": 7319060,
  "type": "Feature",
  "properties": {
    "tgn:hierarchy":[
        "tgn:7319060",
        "tgn:7002464",
        "tgn:1000049",
        "tgn:1000002",
        "tgn:7029392"
    ],
    "tgn:id":7319060,
    "tgn:name":"Aquilaxo, Quebrada",
    "tgn:placetype":[
        "aat:300266554",
        "aat:300008699"
    ]
},
  "bbox": [],
  "geometry": {"coordinates":[-68.633333,-19.466667],"type":"Point"}
}