{
  "id": 2386887,
  "type": "Feature",
  "properties": {
    "tgn:hierarchy":[
        "tgn:2386887",
        "tgn:1002538",
        "tgn:1000001",
        "tgn:7012149",
        "tgn:7007239",
        "tgn:7029392"
    ],
    "tgn:id":2386887,
    "tgn:name":"Heron Drain",
    "tgn:placetype":[
        "aat:300008699"
    ]
},
  "bbox": [],
  "geometry": {"coordinates":[-75.5833,39.05],"type":"Point"}
}