<<<<<<< HEAD
{
  "id": 7174566,
  "type": "Feature",
  "properties": {
    "tgn:hierarchy":[
        "tgn:7174566",
        "tgn:1000003",
        "tgn:7003676",
        "tgn:7000084",
        "tgn:7029392"
    ],
    "tgn:id":7174566,
    "tgn:name":"Gro\u00dfer Kellerhals Teich",
    "tgn:placetype":[
        "aat:300008688"
    ]
},
  "bbox": [],
  "geometry": {"coordinates":[10.366667,51.85],"type":"Point"}
}
=======
{"geometry":{"type":"Point","coordinates":[10.366667,51.850000]},"type":"Feature","properties":{"hierarchy":["tgn:7174566","tgn:1000003","tgn:7003676","tgn:7000084","tgn:7029392"],"placetype":["aat:300008688"],"id":7174566,"name:xx":"Gro\u00dfer Kellerhals Teich"}}
>>>>>>> 03f74aca74312dbeaf24d7e61306dd6a786dc3d0
