{
  "id": 7174566,
  "type": "Feature",
  "properties": {
    "tgn:hierarchy":[
        "tgn:7174566",
        "tgn:1000003",
        "tgn:7003676",
        "tgn:7000084",
        "tgn:7029392"
    ],
    "tgn:id":7174566,
    "tgn:name":"Gro\u00dfer Kellerhals Teich",
    "tgn:placetype":[
        "aat:300008688"
    ]
},
  "bbox": [],
  "geometry": {"coordinates":[10.366667,51.85],"type":"Point"}
}