{
  "id": 7067480,
  "type": "Feature",
  "properties": {
    "tgn:hierarchy":[
        "tgn:7067480",
        "tgn:7000096",
        "tgn:1000003",
        "tgn:7000084",
        "tgn:7029392"
    ],
    "tgn:id":7067480,
    "tgn:name":"Trechwitz",
    "tgn:placetype":[
        "aat:300008347"
    ]
},
  "bbox": [],
  "geometry": {"coordinates":[12.716667,52.366667],"type":"Point"}
}