{
  "id": 7074364,
  "type": "Feature",
  "properties": {
    "tgn:hierarchy":[
        "tgn:7074364",
        "tgn:7003669",
        "tgn:1000003",
        "tgn:7000084",
        "tgn:7029392"
    ],
    "tgn:id":7074364,
    "tgn:name":"Stra\u00dfbach",
    "tgn:placetype":[
        "aat:300008347"
    ]
},
  "bbox": [],
  "geometry": {"coordinates":[11.416667,48.35],"type":"Point"}
}