{
  "id": 2439599,
  "type": "Feature",
  "properties": {
    "tgn:hierarchy":[
        "tgn:2439599",
        "tgn:1000001",
        "tgn:7012149",
        "tgn:1003030",
        "tgn:7007251",
        "tgn:7029392"
    ],
    "tgn:id":2439599,
    "tgn:name":"Kishwaukee",
    "tgn:placetype":[
        "aat:300008347"
    ]
},
  "bbox": [],
  "geometry": {"coordinates":[-89.15,42.15],"type":"Point"}
}