{
  "id": 7098006,
  "type": "Feature",
  "properties": {
    "tgn:hierarchy":[
        "tgn:7098006",
        "tgn:7003692",
        "tgn:1000003",
        "tgn:7000084",
        "tgn:7029392"
    ],
    "tgn:id":7098006,
    "tgn:name":"Simonsberg",
    "tgn:placetype":[
        "aat:300008347"
    ]
},
  "bbox": [],
  "geometry": {"coordinates":[10.133333,49.183333],"type":"Point"}
}