{
  "id": 2398215,
  "type": "Feature",
  "properties": {
    "tgn:hierarchy":[
        "tgn:2398215",
        "tgn:1000001",
        "tgn:2000463",
        "tgn:7012149",
        "tgn:7007250",
        "tgn:7029392"
    ],
    "tgn:id":2398215,
    "tgn:name":"Hooley Creek",
    "tgn:placetype":[
        "aat:300008706"
    ]
},
  "bbox": [],
  "geometry": {"coordinates":[-113.6333,43.6333],"type":"Point"}
}