{
  "id": 2028185,
  "type": "Feature",
  "properties": {
    "tgn:hierarchy":[
        "tgn:2028185",
        "tgn:1000001",
        "tgn:7013649",
        "tgn:7012149",
        "tgn:7007251",
        "tgn:7029392"
    ],
    "tgn:id":2028185,
    "tgn:name":"Hanover Park",
    "tgn:placetype":[
        "aat:300008347"
    ]
},
  "bbox": [],
  "geometry": {"coordinates":[-88.1333,41.9833],"type":"Point"}
}