{
  "id": 7443582,
  "type": "Feature",
  "properties": {
    "tgn:hierarchy":[
        "tgn:7443582",
        "tgn:7002445",
        "tgn:1000003",
        "tgn:7019065",
        "tgn:7008591",
        "tgn:7029392"
    ],
    "tgn:id":7443582,
    "tgn:name:en":"Hunt Cliff",
    "tgn:placetype":[
        "aat:300008749"
    ]
},
  "bbox": [],
  "geometry": {"coordinates":[-0.935556,54.588333],"type":"Point"}
}