{
  "id": 2639208,
  "type": "Feature",
  "properties": {
    "tgn:hierarchy":[
        "tgn:2639208",
        "tgn:1000001",
        "tgn:2000924",
        "tgn:7012149",
        "tgn:7007515",
        "tgn:7029392"
    ],
    "tgn:id":2639208,
    "tgn:name":"Salt Pond",
    "tgn:placetype":[
        "aat:300008680"
    ]
},
  "bbox": [],
  "geometry": {"coordinates":[-68.85,44.15],"type":"Point"}
}