{
  "id": 2260639,
  "type": "Feature",
  "properties": {
    "tgn:hierarchy":[
        "tgn:2260639",
        "tgn:1000001",
        "tgn:7012149",
        "tgn:2000962",
        "tgn:7007520",
        "tgn:7029392"
    ],
    "tgn:id":2260639,
    "tgn:name":"County Ditch Number Fourty-nine",
    "tgn:placetype":[
        "aat:300006075"
    ]
},
  "bbox": [],
  "geometry": {"coordinates":[-84.75,43.15],"type":"Point"}
}