{
  "id": 1128929,
  "type": "Feature",
  "properties": {
    "tgn:hierarchy":[
        "tgn:1128929",
        "tgn:1001945",
        "tgn:1000047",
        "tgn:7002457",
        "tgn:1000002",
        "tgn:7029392"
    ],
    "tgn:id":1128929,
    "tgn:name":"Quilombo",
    "tgn:placetype":[
        "aat:300008707"
    ]
},
  "bbox": [],
  "geometry": {"coordinates":[-46.35,-23.8667],"type":"Point"}
}