{
  "id": 1104999,
  "type": "Feature",
  "properties": {
    "tgn:hierarchy":[
        "tgn:1104999",
        "tgn:7003025",
        "tgn:1000003",
        "tgn:1000062",
        "tgn:7029392"
    ],
    "tgn:id":1104999,
    "tgn:name":"Hutwisch",
    "tgn:placetype":[
        "aat:300008795"
    ]
},
  "bbox": [],
  "geometry": {"coordinates":[16.2167,47.4667],"type":"Point"}
}