{
  "id": 7155136,
  "type": "Feature",
  "properties": {
    "tgn:hierarchy":[
        "tgn:7155136",
        "tgn:7000096",
        "tgn:1000003",
        "tgn:7000084",
        "tgn:7029392"
    ],
    "tgn:id":7155136,
    "tgn:name":"Klein K\u00f6lzig",
    "tgn:placetype":[
        "aat:300008347"
    ]
},
  "bbox": [],
  "geometry": {"coordinates":[14.583333,51.65],"type":"Point"}
}