{
  "id": 2474827,
  "type": "Feature",
  "properties": {
    "tgn:hierarchy":[
        "tgn:2474827",
        "tgn:1000001",
        "tgn:7006451",
        "tgn:2000092",
        "tgn:7012149",
        "tgn:7029392"
    ],
    "tgn:id":2474827,
    "tgn:name":"Lower Tillman Tank",
    "tgn:placetype":[
        "aat:300006191"
    ]
},
  "bbox": [],
  "geometry": {"coordinates":[-110.7833,34.6167],"type":"Point"}
}