{
  "id": 7568491,
  "type": "Feature",
  "properties": {
    "tgn:hierarchy":[
        "tgn:7568491",
        "tgn:1000004",
        "tgn:7000198",
        "tgn:7016788",
        "tgn:7029392"
    ],
    "tgn:id":7568491,
    "tgn:name:en":"Dhan\u0101tri",
    "tgn:placetype":[
        "aat:300008347"
    ]
},
  "bbox": [],
  "geometry": {"coordinates":[75.649348,25.311712],"type":"Point"}
}