{
  "id": 7426624,
  "type": "Feature",
  "properties": {
    "tgn:hierarchy":[
        "tgn:7426624",
        "tgn:7005581",
        "tgn:1000001",
        "tgn:7005560",
        "tgn:7029392"
    ],
    "tgn:id":7426624,
    "tgn:name":"Los Sauces",
    "tgn:placetype":[
        "aat:300008347"
    ]
},
  "bbox": [],
  "geometry": {"coordinates":[-105.683333,26.733333],"type":"Point"}
}