{
  "id": 7496578,
  "type": "Feature",
  "properties": {
    "tgn:hierarchy":[
        "tgn:7496578",
        "tgn:7001004",
        "tgn:1000004",
        "tgn:1000141",
        "tgn:7029392"
    ],
    "tgn:id":7496578,
    "tgn:name":"Neiliao Qiao",
    "tgn:placetype":[
        "aat:300007836"
    ]
},
  "bbox": [],
  "geometry": {"coordinates":[120.553517,22.962574],"type":"Point"}
}