{
  "id": 2756159,
  "type": "Feature",
  "properties": {
    "tgn:hierarchy":[
        "tgn:2756159",
        "tgn:1000001",
        "tgn:7012149",
        "tgn:1002749",
        "tgn:7007240",
        "tgn:7029392"
    ],
    "tgn:id":2756159,
    "tgn:name":"Wekiva, Lake",
    "tgn:placetype":[
        "aat:300008680"
    ]
},
  "bbox": [],
  "geometry": {"coordinates":[-81.4167,28.5833],"type":"Point"}
}