{
  "id": 2286163,
  "type": "Feature",
  "properties": {
    "tgn:hierarchy":[
        "tgn:2286163",
        "tgn:1000001",
        "tgn:7012149",
        "tgn:2000789",
        "tgn:7007255",
        "tgn:7029392"
    ],
    "tgn:id":2286163,
    "tgn:name":"Dewey Lake",
    "tgn:placetype":[
        "aat:300006191"
    ]
},
  "bbox": [],
  "geometry": {"coordinates":[-82.7167,37.7333],"type":"Point"}
}