<<<<<<< HEAD
{
  "id": 2767750,
  "type": "Feature",
  "properties": {
    "tgn:hierarchy":[
        "tgn:2767750",
        "tgn:1000001",
        "tgn:2001093",
        "tgn:7012149",
        "tgn:7007522",
        "tgn:7029392"
    ],
    "tgn:id":2767750,
    "tgn:name":"Whitehead Creek",
    "tgn:placetype":[
        "aat:300008706"
    ]
},
  "bbox": [],
  "geometry": {"coordinates":[-89.8,33.45],"type":"Point"}
}
=======
{"geometry":{"type":"Point","coordinates":[-89.800000,33.450000]},"type":"Feature","properties":{"hierarchy":["tgn:2767750","tgn:1000001","tgn:2001093","tgn:7012149","tgn:7007522","tgn:7029392"],"placetype":["aat:300008706"],"id":2767750,"name:xx":"Whitehead Creek"}}
>>>>>>> 03f74aca74312dbeaf24d7e61306dd6a786dc3d0
