<<<<<<< HEAD
{
  "id": 2764874,
  "type": "Feature",
  "properties": {
    "tgn:hierarchy":[
        "tgn:2764874",
        "tgn:1000001",
        "tgn:7006451",
        "tgn:2000094",
        "tgn:7012149",
        "tgn:7029392"
    ],
    "tgn:id":2764874,
    "tgn:name":"Whiskey Ridge",
    "tgn:placetype":[
        "aat:300266640"
    ]
},
  "bbox": [],
  "geometry": {"coordinates":[-109.7,33.2],"type":"Point"}
}
=======
{"geometry":{"type":"Point","coordinates":[-109.700000,33.200000]},"type":"Feature","properties":{"hierarchy":["tgn:2764874","tgn:1000001","tgn:7006451","tgn:2000094","tgn:7012149","tgn:7029392"],"placetype":["aat:300266640"],"id":2764874,"name:xx":"Whiskey Ridge"}}
>>>>>>> 03f74aca74312dbeaf24d7e61306dd6a786dc3d0
