{
  "id": 2755150,
  "type": "Feature",
  "properties": {
    "tgn:hierarchy":[
        "tgn:2755150",
        "tgn:7013349",
        "tgn:1000001",
        "tgn:7012149",
        "tgn:7007708",
        "tgn:7029392"
    ],
    "tgn:id":2755150,
    "tgn:name":"Webb Gulch",
    "tgn:placetype":[
        "aat:300008761"
    ]
},
  "bbox": [],
  "geometry": {"coordinates":[-118.3167,44.4833],"type":"Point"}
}