{
  "id": 2430901,
  "type": "Feature",
  "properties": {
    "tgn:hierarchy":[
        "tgn:2430901",
        "tgn:1000001",
        "tgn:7012149",
        "tgn:7007157",
        "tgn:7029392"
    ],
    "tgn:id":2430901,
    "tgn:name":"Kanaka Cutoff",
    "tgn:placetype":[
        "aat:300006075"
    ]
},
  "bbox": [],
  "geometry": {"coordinates":[-121.6333,38.7667],"type":"Point"}
}