<<<<<<< HEAD
{
  "id": 7350550,
  "type": "Feature",
  "properties": {
    "tgn:hierarchy":[
        "tgn:7350550",
        "tgn:1000001",
        "tgn:7005589",
        "tgn:7005560",
        "tgn:7029392"
    ],
    "tgn:id":7350550,
    "tgn:name":"Bustamante, Sierra de",
    "tgn:placetype":[
        "aat:300008795"
    ]
},
  "bbox": [],
  "geometry": {"coordinates":[-100.583333,26.583333],"type":"Point"}
}
=======
{"geometry":{"type":"Point","coordinates":[-100.583333,26.583333]},"type":"Feature","properties":{"hierarchy":["tgn:7350550","tgn:1000001","tgn:7005589","tgn:7005560","tgn:7029392"],"placetype":["aat:300008795"],"id":7350550,"name:xx":"Bustamante, Sierra de"}}
>>>>>>> 03f74aca74312dbeaf24d7e61306dd6a786dc3d0
