{
  "id": 7359408,
  "type": "Feature",
  "properties": {
    "tgn:hierarchy":[
        "tgn:7359408",
        "tgn:1000001",
        "tgn:1001906",
        "tgn:7005560",
        "tgn:7029392"
    ],
    "tgn:id":7359408,
    "tgn:name":"Dolores",
    "tgn:placetype":[
        "aat:300008347"
    ]
},
  "bbox": [],
  "geometry": {"coordinates":[-104.383333,20.983333],"type":"Point"}
}