{
  "id": 1126665,
  "type": "Feature",
  "properties": {
    "tgn:hierarchy":[
        "tgn:1126665",
        "tgn:7005685",
        "tgn:1000001",
        "tgn:7013154",
        "tgn:7029392"
    ],
    "tgn:id":1126665,
    "tgn:name":"Magpie",
    "tgn:placetype":[
        "aat:300008707"
    ]
},
  "bbox": [],
  "geometry": {"coordinates":[-84.8333,47.9333],"type":"Point"}
}