{
  "id": 7281792,
  "type": "Feature",
  "properties": {
    "tgn:hierarchy":[
        "tgn:7281792",
        "tgn:1001702",
        "tgn:1000049",
        "tgn:1000002",
        "tgn:7029392"
    ],
    "tgn:id":7281792,
    "tgn:name":"San Pedro y San Pablo, Rocas",
    "tgn:placetype":[
        "aat:300011692"
    ]
},
  "bbox": [],
  "geometry": {"coordinates":[-70.716667,-53.716667],"type":"Point"}
}