<<<<<<< HEAD
{
  "id": 2157315,
  "type": "Feature",
  "properties": {
    "tgn:hierarchy":[
        "tgn:2157315",
        "tgn:1000001",
        "tgn:7012149",
        "tgn:2000996",
        "tgn:7007520",
        "tgn:7029392"
    ],
    "tgn:id":2157315,
    "tgn:name":"Beaver Creek",
    "tgn:placetype":[
        "aat:300008706"
    ]
},
  "bbox": [],
  "geometry": {"coordinates":[-86.55,46.3167],"type":"Point"}
}
=======
{"geometry":{"type":"Point","coordinates":[-86.550000,46.316700]},"type":"Feature","properties":{"hierarchy":["tgn:2157315","tgn:1000001","tgn:7012149","tgn:2000996","tgn:7007520","tgn:7029392"],"placetype":["aat:300008706"],"id":2157315,"name:xx":"Beaver Creek"}}
>>>>>>> 03f74aca74312dbeaf24d7e61306dd6a786dc3d0
