{
  "id": 7592444,
  "type": "Feature",
  "properties": {
    "tgn:hierarchy":[
        "tgn:7592444",
        "tgn:1000004",
        "tgn:7000198",
        "tgn:7000799",
        "tgn:7029392"
    ],
    "tgn:id":7592444,
    "tgn:name:en":"Tunra da Kalia",
    "tgn:placetype":[
        "aat:300008347"
    ]
},
  "bbox": [],
  "geometry": {"coordinates":[74.197847,33.094993],"type":"Point"}
}