{
  "id": 2563496,
  "type": "Feature",
  "properties": {
    "tgn:hierarchy":[
        "tgn:2563496",
        "tgn:1000001",
        "tgn:7012149",
        "tgn:1002833",
        "tgn:7007568",
        "tgn:7029392"
    ],
    "tgn:id":2563496,
    "tgn:name":"Owl Lake",
    "tgn:placetype":[
        "aat:300008680"
    ]
},
  "bbox": [],
  "geometry": {"coordinates":[-74.0333,41.2667],"type":"Point"}
}