{
  "id": 2406754,
  "type": "Feature",
  "properties": {
    "tgn:hierarchy":[
        "tgn:2406754",
        "tgn:1000001",
        "tgn:7012149",
        "tgn:7014589",
        "tgn:7007515",
        "tgn:7029392"
    ],
    "tgn:id":2406754,
    "tgn:name":"Hunt Ridge",
    "tgn:placetype":[
        "aat:300266640"
    ]
},
  "bbox": [],
  "geometry": {"coordinates":[-67.7167,45.4333],"type":"Point"}
}