<<<<<<< HEAD
{
  "id": 2765376,
  "type": "Feature",
  "properties": {
    "tgn:hierarchy":[
        "tgn:2765376",
        "tgn:1000001",
        "tgn:7006451",
        "tgn:2000095",
        "tgn:7012149",
        "tgn:7029392"
    ],
    "tgn:id":2765376,
    "tgn:name":"White Basin Tank",
    "tgn:placetype":[
        "aat:300006191"
    ]
},
  "bbox": [],
  "geometry": {"coordinates":[-109.1667,33.25],"type":"Point"}
}
=======
{"geometry":{"type":"Point","coordinates":[-109.166700,33.250000]},"type":"Feature","properties":{"hierarchy":["tgn:2765376","tgn:1000001","tgn:7006451","tgn:2000095","tgn:7012149","tgn:7029392"],"placetype":["aat:300006191"],"id":2765376,"name:xx":"White Basin Tank"}}
>>>>>>> 03f74aca74312dbeaf24d7e61306dd6a786dc3d0
