<<<<<<< HEAD
{
  "id": 7178768,
  "type": "Feature",
  "properties": {
    "tgn:hierarchy":[
        "tgn:7178768",
        "tgn:1000003",
        "tgn:7003677",
        "tgn:7000084",
        "tgn:7029392"
    ],
    "tgn:id":7178768,
    "tgn:name":"Hackel-Berg",
    "tgn:placetype":[
        "aat:300008795"
    ]
},
  "bbox": [],
  "geometry": {"coordinates":[8.55,51.133333],"type":"Point"}
}
=======
{"geometry":{"type":"Point","coordinates":[8.550000,51.133333]},"type":"Feature","properties":{"hierarchy":["tgn:7178768","tgn:1000003","tgn:7003677","tgn:7000084","tgn:7029392"],"placetype":["aat:300008795"],"id":7178768,"name:xx":"Hackel-Berg"}}
>>>>>>> 03f74aca74312dbeaf24d7e61306dd6a786dc3d0
