{
  "id": 1076476,
  "type": "Feature",
  "properties": {
    "tgn:hierarchy":[
        "tgn:1076476",
        "tgn:1000004",
        "tgn:7000198",
        "tgn:1001977",
        "tgn:7029392"
    ],
    "tgn:id":1076476,
    "tgn:name":"P\u0101nchur",
    "tgn:placetype":[
        "aat:300008347"
    ]
},
  "bbox": [],
  "geometry": {"coordinates":[88.2667,22.5333],"type":"Point"}
}