{
  "id": 1020132,
  "type": "Feature",
  "properties": {
    "tgn:hierarchy":[
        "tgn:1020132",
        "tgn:7006477",
        "tgn:1001237",
        "tgn:1000002",
        "tgn:7029392"
    ],
    "tgn:id":1020132,
    "tgn:name":"Urdinarrain",
    "tgn:placetype":[
        "aat:300008347"
    ]
},
  "bbox": [],
  "geometry": {"coordinates":[-58.8833,-32.6833],"type":"Point"}
}