<<<<<<< HEAD
{
  "id": 7022136,
  "type": "Feature",
  "properties": {
    "tgn:hierarchy":[
        "tgn:7022136",
        "tgn:1002538",
        "tgn:1000001",
        "tgn:7012149",
        "tgn:7007239",
        "tgn:7029392"
    ],
    "tgn:id":7022136,
    "tgn:name":"Delaware Correctional Center",
    "tgn:placetype":[
        "aat:300006448"
    ]
},
  "bbox": [],
  "geometry": {"coordinates":[-75.6,39.3333],"type":"Point"}
}
=======
{"geometry":{"type":"Point","coordinates":[-75.600000,39.333300]},"type":"Feature","properties":{"hierarchy":["tgn:7022136","tgn:1002538","tgn:1000001","tgn:7012149","tgn:7007239","tgn:7029392"],"placetype":["aat:300006448"],"id":7022136,"name:xx":"Delaware Correctional Center"}}
>>>>>>> 03f74aca74312dbeaf24d7e61306dd6a786dc3d0
