{
  "id": 2444214,
  "type": "Feature",
  "properties": {
    "tgn:hierarchy":[
        "tgn:2444214",
        "tgn:1000001",
        "tgn:1002260",
        "tgn:7012149",
        "tgn:7007920",
        "tgn:7029392"
    ],
    "tgn:id":2444214,
    "tgn:name":"Labyrinth Mountain",
    "tgn:placetype":[
        "aat:300008798"
    ]
},
  "bbox": [],
  "geometry": {"coordinates":[-121.0333,47.85],"type":"Point"}
}