{
  "id": 7583382,
  "type": "Feature",
  "properties": {
    "tgn:hierarchy":[
        "tgn:7583382",
        "tgn:1000004",
        "tgn:7000198",
        "tgn:7016788",
        "tgn:7029392"
    ],
    "tgn:id":7583382,
    "tgn:name:en":"Kh\u0101ra Loh\u0101n",
    "tgn:placetype":[
        "aat:300008347"
    ]
},
  "bbox": [],
  "geometry": {"coordinates":[72.998335,27.581997],"type":"Point"}
}