{
  "id": 7349332,
  "type": "Feature",
  "properties": {
    "tgn:hierarchy":[
        "tgn:7349332",
        "tgn:1001836",
        "tgn:1000001",
        "tgn:7005560",
        "tgn:7029392"
    ],
    "tgn:id":7349332,
    "tgn:name":"Alijos, Escollos",
    "tgn:placetype":[
        "aat:300011692"
    ]
},
  "bbox": [],
  "geometry": {"coordinates":[-115.733333,24.95],"type":"Point"}
}