{
  "id": 2328433,
  "type": "Feature",
  "properties": {
    "tgn:hierarchy":[
        "tgn:2328433",
        "tgn:1000001",
        "tgn:7012149",
        "tgn:2001453",
        "tgn:7007566",
        "tgn:7029392"
    ],
    "tgn:id":2328433,
    "tgn:name":"Fisher Hill",
    "tgn:placetype":[
        "aat:300008798"
    ]
},
  "bbox": [],
  "geometry": {"coordinates":[-105.4333,35.5667],"type":"Point"}
}