{
  "id": 1072852,
  "type": "Feature",
  "properties": {
    "tgn:hierarchy":[
        "tgn:1072852",
        "tgn:1000004",
        "tgn:7002077",
        "tgn:1000111",
        "tgn:7029392"
    ],
    "tgn:id":1072852,
    "tgn:name":"Xiaojingfang",
    "tgn:placetype":[
        "aat:300008347"
    ]
},
  "bbox": [],
  "geometry": {"coordinates":[116.5667,39.3667],"type":"Point"}
}