{
  "id": 2519820,
  "type": "Feature",
  "properties": {
    "tgn:hierarchy":[
        "tgn:2519820",
        "tgn:1000001",
        "tgn:7006451",
        "tgn:7012149",
        "tgn:2000098",
        "tgn:7029392"
    ],
    "tgn:id":2519820,
    "tgn:name":"Mokaac Spring",
    "tgn:placetype":[
        "aat:300008697"
    ]
},
  "bbox": [],
  "geometry": {"coordinates":[-113.5667,36.8833],"type":"Point"}
}