{
  "id": 2090601,
  "type": "Feature",
  "properties": {
    "tgn:hierarchy":[
        "tgn:2090601",
        "tgn:1000001",
        "tgn:7012149",
        "tgn:7013867",
        "tgn:7007710",
        "tgn:7029392"
    ],
    "tgn:id":2090601,
    "tgn:name":"Martindale",
    "tgn:placetype":[
        "aat:300008347"
    ]
},
  "bbox": [],
  "geometry": {"coordinates":[-76.0833,40.15],"type":"Point"}
}