{
  "id": 7183213,
  "type": "Feature",
  "properties": {
    "tgn:hierarchy":[
        "tgn:7183213",
        "tgn:1000003",
        "tgn:7000094",
        "tgn:7000084",
        "tgn:7029392"
    ],
    "tgn:id":7183213,
    "tgn:name":"Galgen-Berg",
    "tgn:placetype":[
        "aat:300008777"
    ]
},
  "bbox": [],
  "geometry": {"coordinates":[13.966667,53.416667],"type":"Point"}
}