{
  "id": 2787138,
  "type": "Feature",
  "properties": {
    "tgn:hierarchy":[
        "tgn:2787138",
        "tgn:1000001",
        "tgn:7012149",
        "tgn:2001909",
        "tgn:7007825",
        "tgn:7029392"
    ],
    "tgn:id":2787138,
    "tgn:name":"Zion Spring Branch",
    "tgn:placetype":[
        "aat:300008699"
    ]
},
  "bbox": [],
  "geometry": {"coordinates":[-84.4833,35.7167],"type":"Point"}
}