{
  "id": 2493731,
  "type": "Feature",
  "properties": {
    "tgn:hierarchy":[
        "tgn:2493731",
        "tgn:1000001",
        "tgn:2000935",
        "tgn:7012149",
        "tgn:7007516",
        "tgn:7029392"
    ],
    "tgn:id":2493731,
    "tgn:name":"Marsh Run Cove",
    "tgn:placetype":[
        "aat:300132316"
    ]
},
  "bbox": [],
  "geometry": {"coordinates":[-79.35,39.5333],"type":"Point"}
}