{
  "id": 1075024,
  "type": "Feature",
  "properties": {
    "tgn:hierarchy":[
        "tgn:1075024",
        "tgn:1000004",
        "tgn:7000198",
        "tgn:7016722",
        "tgn:7029392"
    ],
    "tgn:id":1075024,
    "tgn:name:en":"Chopan",
    "tgn:placetype":[
        "aat:300008347"
    ]
},
  "bbox": [],
  "geometry": {"coordinates":[83.02337,24.517056],"type":"Point"}
}