{
  "id": 7484074,
  "type": "Feature",
  "properties": {
    "tgn:hierarchy":[
        "tgn:7484074",
        "tgn:1000004",
        "tgn:7490934",
        "tgn:1000141",
        "tgn:7029392"
    ],
    "tgn:id":7484074,
    "tgn:name":"Dingkan",
    "tgn:placetype":[
        "aat:300008347"
    ]
},
  "bbox": [],
  "geometry": {"coordinates":[120.526389,23.084444],"type":"Point"}
}