{
  "id": 7368472,
  "type": "Feature",
  "properties": {
    "tgn:hierarchy":[
        "tgn:7368472",
        "tgn:1000001",
        "tgn:7005591",
        "tgn:7005560",
        "tgn:7029392"
    ],
    "tgn:id":7368472,
    "tgn:name":"Guadalupe",
    "tgn:placetype":[
        "aat:300008347"
    ]
},
  "bbox": [],
  "geometry": {"coordinates":[-94.166667,16.333333],"type":"Point"}
}