{
  "id": 2240884,
  "type": "Feature",
  "properties": {
    "tgn:hierarchy":[
        "tgn:2240884",
        "tgn:1000001",
        "tgn:2001175",
        "tgn:7012149",
        "tgn:7007523",
        "tgn:7029392"
    ],
    "tgn:id":2240884,
    "tgn:name":"Clarence Jones East Lake",
    "tgn:placetype":[
        "aat:300006191"
    ]
},
  "bbox": [],
  "geometry": {"coordinates":[-94.75,39.6167],"type":"Point"}
}