{
  "id": 2732732,
  "type": "Feature",
  "properties": {
    "tgn:hierarchy":[
        "tgn:2732732",
        "tgn:1000001",
        "tgn:2001641",
        "tgn:7012149",
        "tgn:7007707",
        "tgn:7029392"
    ],
    "tgn:id":2732732,
    "tgn:name":"Turkey Creek",
    "tgn:placetype":[
        "aat:300008706"
    ]
},
  "bbox": [],
  "geometry": {"coordinates":[-96.2833,36.0333],"type":"Point"}
}