{
  "id": 7334286,
  "type": "Feature",
  "properties": {
    "tgn:hierarchy":[
        "tgn:7334286",
        "tgn:7002805",
        "tgn:7002758",
        "tgn:1000003",
        "tgn:1000095",
        "tgn:7029392"
    ],
    "tgn:id":7334286,
    "tgn:name":"El Pillico",
    "tgn:placetype":[
        "aat:300008347"
    ]
},
  "bbox": [],
  "geometry": {"coordinates":[-2.566667,36.816667],"type":"Point"}
}