{
  "id": 2353915,
  "type": "Feature",
  "properties": {
    "tgn:hierarchy":[
        "tgn:2353915",
        "tgn:1000001",
        "tgn:2001415",
        "tgn:7012149",
        "tgn:7007526",
        "tgn:7029392"
    ],
    "tgn:id":2353915,
    "tgn:name":"Gold and Silver Circle Mine",
    "tgn:placetype":[
        "aat:300000390"
    ]
},
  "bbox": [],
  "geometry": {"coordinates":[-116.8833,40.4167],"type":"Point"}
}