{
  "id": 2503868,
  "type": "Feature",
  "properties": {
    "tgn:hierarchy":[
        "tgn:2503868",
        "tgn:1000001",
        "tgn:7012149",
        "tgn:2001300",
        "tgn:7007524",
        "tgn:7029392"
    ],
    "tgn:id":2503868,
    "tgn:name":"Meadow Creek",
    "tgn:placetype":[
        "aat:300008706"
    ]
},
  "bbox": [],
  "geometry": {"coordinates":[-113.7667,45.7833],"type":"Point"}
}