{
  "id": 2590837,
  "type": "Feature",
  "properties": {
    "tgn:hierarchy":[
        "tgn:2590837",
        "tgn:1000001",
        "tgn:7012149",
        "tgn:1002866",
        "tgn:7007251",
        "tgn:7029392"
    ],
    "tgn:id":2590837,
    "tgn:name":"Polecat Creek",
    "tgn:placetype":[
        "aat:300008706"
    ]
},
  "bbox": [],
  "geometry": {"coordinates":[-89.75,39.6333],"type":"Point"}
}