{
  "id": 2634104,
  "type": "Feature",
  "properties": {
    "tgn:hierarchy":[
        "tgn:2634104",
        "tgn:1000001",
        "tgn:1002840",
        "tgn:7012149",
        "tgn:7007828",
        "tgn:7029392"
    ],
    "tgn:id":2634104,
    "tgn:name":"Russell Brook",
    "tgn:placetype":[
        "aat:300008699"
    ]
},
  "bbox": [],
  "geometry": {"coordinates":[-72.7833,43.4833],"type":"Point"}
}