<<<<<<< HEAD
{
  "id": 2409637,
  "type": "Feature",
  "properties": {
    "tgn:hierarchy":[
        "tgn:2409637",
        "tgn:7006450",
        "tgn:2000069",
        "tgn:1000001",
        "tgn:7012149",
        "tgn:7029392"
    ],
    "tgn:id":2409637,
    "tgn:name":"Ikathleewimjingia Point",
    "tgn:placetype":[
        "aat:300008850"
    ]
},
  "bbox": [],
  "geometry": {"coordinates":[-165.7167,60.3],"type":"Point"}
}
=======
{"geometry":{"type":"Point","coordinates":[-165.716700,60.300000]},"type":"Feature","properties":{"hierarchy":["tgn:2409637","tgn:7006450","tgn:2000069","tgn:1000001","tgn:7012149","tgn:7029392"],"placetype":["aat:300008850"],"id":2409637,"name:xx":"Ikathleewimjingia Point"}}
>>>>>>> 03f74aca74312dbeaf24d7e61306dd6a786dc3d0
