{
  "id": 2057415,
  "type": "Feature",
  "properties": {
    "tgn:hierarchy":[
        "tgn:2057415",
        "tgn:2001089",
        "tgn:1000001",
        "tgn:7012149",
        "tgn:7007522",
        "tgn:7029392"
    ],
    "tgn:id":2057415,
    "tgn:name":"Sallis",
    "tgn:placetype":[
        "aat:300008347"
    ]
},
  "bbox": [],
  "geometry": {"coordinates":[-89.75,33.0167],"type":"Point"}
}