{
  "id": 2244294,
  "type": "Feature",
  "properties": {
    "tgn:hierarchy":[
        "tgn:2244294",
        "tgn:1000001",
        "tgn:1002274",
        "tgn:7012149",
        "tgn:7007706",
        "tgn:7029392"
    ],
    "tgn:id":2244294,
    "tgn:name":"Clifton Gorge",
    "tgn:placetype":[
        "aat:300008761"
    ]
},
  "bbox": [],
  "geometry": {"coordinates":[-83.8167,39.7833],"type":"Point"}
}