{
  "id": 7046221,
  "type": "Feature",
  "properties": {
    "tgn:hierarchy":[
        "tgn:7046221",
        "tgn:7003163",
        "tgn:1000003",
        "tgn:7009760",
        "tgn:1000080",
        "tgn:7029392"
    ],
    "tgn:id":7046221,
    "tgn:name":"Stazione Firenze Campo di Marte",
    "tgn:placetype":[
        "aat:300007783"
    ]
},
  "bbox": [],
  "geometry": {"coordinates":[11.266667,43.783333],"type":"Point"}
}