{
  "id": 7438228,
  "type": "Feature",
  "properties": {
    "tgn:hierarchy":[
        "tgn:7438228",
        "tgn:1000001",
        "tgn:7005594",
        "tgn:7005560",
        "tgn:7029392"
    ],
    "tgn:id":7438228,
    "tgn:name":"Tam\u00e1n",
    "tgn:placetype":[
        "aat:300008347"
    ]
},
  "bbox": [],
  "geometry": {"coordinates":[-98.883333,21.216667],"type":"Point"}
}