{
  "id": 1021084,
  "type": "Feature",
  "properties": {
    "tgn:hierarchy":[
        "tgn:1021084",
        "tgn:1001826",
        "tgn:1000047",
        "tgn:7002456",
        "tgn:1000002",
        "tgn:7029392"
    ],
    "tgn:id":1021084,
    "tgn:name":"Carauari",
    "tgn:placetype":[
        "aat:300008347"
    ]
},
  "bbox": [],
  "geometry": {"coordinates":[-66.95,-4.9167],"type":"Point"}
}