{
  "id": 1023945,
  "type": "Feature",
  "properties": {
    "tgn:hierarchy":[
        "tgn:1023945",
        "tgn:1000554",
        "tgn:1000050",
        "tgn:1000002",
        "tgn:7029392"
    ],
    "tgn:id":1023945,
    "tgn:name":"Puerto Tejada",
    "tgn:placetype":[
        "aat:300008347"
    ]
},
  "bbox": [],
  "geometry": {"coordinates":[-76.3667,3.2667],"type":"Point"}
}