{
  "id": 2573813,
  "type": "Feature",
  "properties": {
    "tgn:hierarchy":[
        "tgn:2573813",
        "tgn:1000001",
        "tgn:2000201",
        "tgn:7012149",
        "tgn:7007158",
        "tgn:7029392"
    ],
    "tgn:id":2573813,
    "tgn:name":"Pedee Creek",
    "tgn:placetype":[
        "aat:300008706"
    ]
},
  "bbox": [],
  "geometry": {"coordinates":[-105.5333,39.6167],"type":"Point"}
}