{
  "id": 2160467,
  "type": "Feature",
  "properties": {
    "tgn:hierarchy":[
        "tgn:2160467",
        "tgn:1000001",
        "tgn:7012149",
        "tgn:7007253",
        "tgn:7029392"
    ],
    "tgn:id":2160467,
    "tgn:name":"Beers Creek",
    "tgn:placetype":[
        "aat:300008706"
    ]
},
  "bbox": [],
  "geometry": {"coordinates":[-91.1167,42.0833],"type":"Point"}
}