<<<<<<< HEAD
{
  "id": 7244237,
  "type": "Feature",
  "properties": {
    "tgn:hierarchy":[
        "tgn:7244237",
        "tgn:7003457",
        "tgn:1000003",
        "tgn:1000063",
        "tgn:7018236",
        "tgn:7029392"
    ],
    "tgn:id":7244237,
    "tgn:name":"Kaster",
    "tgn:placetype":[
        "aat:300008347"
    ]
},
  "bbox": [],
  "geometry": {"coordinates":[3.65,50.85],"type":"Point"}
}
=======
{"geometry":{"type":"Point","coordinates":[3.650000,50.850000]},"type":"Feature","properties":{"hierarchy":["tgn:7244237","tgn:7003457","tgn:1000003","tgn:1000063","tgn:7018236","tgn:7029392"],"placetype":["aat:300008347"],"id":7244237,"name:xx":"Kaster"}}
>>>>>>> 03f74aca74312dbeaf24d7e61306dd6a786dc3d0
