{
  "id": 2624084,
  "type": "Feature",
  "properties": {
    "tgn:hierarchy":[
        "tgn:2624084",
        "tgn:1000001",
        "tgn:7012149",
        "tgn:1002988",
        "tgn:7007710",
        "tgn:7029392"
    ],
    "tgn:id":2624084,
    "tgn:name":"Rock Hollow",
    "tgn:placetype":[
        "aat:300008761"
    ]
},
  "bbox": [],
  "geometry": {"coordinates":[-79.45,41.75],"type":"Point"}
}