{
  "id": 2622953,
  "type": "Feature",
  "properties": {
    "tgn:hierarchy":[
        "tgn:2622953",
        "tgn:7002659",
        "tgn:1000001",
        "tgn:7012149",
        "tgn:2000041",
        "tgn:7029392"
    ],
    "tgn:id":2622953,
    "tgn:name":"Robinson Sink Cave",
    "tgn:placetype":[
        "aat:300008746"
    ]
},
  "bbox": [],
  "geometry": {"coordinates":[-87.1333,34.9333],"type":"Point"}
}