{
  "id": 7589032,
  "type": "Feature",
  "properties": {
    "tgn:hierarchy":[
        "tgn:7589032",
        "tgn:1000004",
        "tgn:7000198",
        "tgn:7000799",
        "tgn:7029392"
    ],
    "tgn:id":7589032,
    "tgn:name:en":"Bh\u0101la Khatar",
    "tgn:placetype":[
        "aat:300008347"
    ]
},
  "bbox": [],
  "geometry": {"coordinates":[74.164137,33.119854],"type":"Point"}
}