{
  "id": 2286577,
  "type": "Feature",
  "properties": {
    "tgn:hierarchy":[
        "tgn:2286577",
        "tgn:1000001",
        "tgn:2001411",
        "tgn:7012149",
        "tgn:7007526",
        "tgn:7029392"
    ],
    "tgn:id":2286577,
    "tgn:name":"Diamond Jim Mine",
    "tgn:placetype":[
        "aat:300000390"
    ]
},
  "bbox": [],
  "geometry": {"coordinates":[-115.65,41.75],"type":"Point"}
}