{
  "id": 2625130,
  "type": "Feature",
  "properties": {
    "tgn:hierarchy":[
        "tgn:2625130",
        "tgn:1000001",
        "tgn:7012149",
        "tgn:2000839",
        "tgn:7007255",
        "tgn:7029392"
    ],
    "tgn:id":2625130,
    "tgn:name":"Rockcastle Springs Ridge",
    "tgn:placetype":[
        "aat:300266640"
    ]
},
  "bbox": [],
  "geometry": {"coordinates":[-84.3333,37.0167],"type":"Point"}
}