{
  "id": 2487788,
  "type": "Feature",
  "properties": {
    "tgn:hierarchy":[
        "tgn:2487788",
        "tgn:1000001",
        "tgn:7012149",
        "tgn:7022542",
        "tgn:7007825",
        "tgn:7029392"
    ],
    "tgn:id":2487788,
    "tgn:name":"Left Fork Rock Creek",
    "tgn:placetype":[
        "aat:300008706"
    ]
},
  "bbox": [],
  "geometry": {"coordinates":[-84.75,35.4667],"type":"Point"}
}