{
  "id": 7357850,
  "type": "Feature",
  "properties": {
    "tgn:hierarchy":[
        "tgn:7357850",
        "tgn:1000001",
        "tgn:7005597",
        "tgn:7005560",
        "tgn:7029392"
    ],
    "tgn:id":7357850,
    "tgn:name":"Cortadura, Canal la",
    "tgn:placetype":[
        "aat:300008713"
    ]
},
  "bbox": [],
  "geometry": {"coordinates":[-97.833333,22.216667],"type":"Point"}
}