{
  "id": 2544133,
  "type": "Feature",
  "properties": {
    "tgn:hierarchy":[
        "tgn:2544133",
        "tgn:1000001",
        "tgn:7012149",
        "tgn:2002375",
        "tgn:7007923",
        "tgn:7029392"
    ],
    "tgn:id":2544133,
    "tgn:name":"North Branch Little Bear Creek",
    "tgn:placetype":[
        "aat:300008706"
    ]
},
  "bbox": [],
  "geometry": {"coordinates":[-105.1667,41.4667],"type":"Point"}
}