{
  "id": 2244828,
  "type": "Feature",
  "properties": {
    "tgn:hierarchy":[
        "tgn:2244828",
        "tgn:1000001",
        "tgn:7012149",
        "tgn:2001288",
        "tgn:7007524",
        "tgn:7029392"
    ],
    "tgn:id":2244828,
    "tgn:name":"Cloudrest Peak",
    "tgn:placetype":[
        "aat:300008798"
    ]
},
  "bbox": [],
  "geometry": {"coordinates":[-112.0667,45.5333],"type":"Point"}
}