{
  "id": 7413295,
  "type": "Feature",
  "properties": {
    "tgn:hierarchy":[
        "tgn:7413295",
        "tgn:1000001",
        "tgn:7005598",
        "tgn:7005560",
        "tgn:7029392"
    ],
    "tgn:id":7413295,
    "tgn:name":"Texmala",
    "tgn:placetype":[
        "aat:300008347"
    ]
},
  "bbox": [],
  "geometry": {"coordinates":[-98.041667,19.425],"type":"Point"}
}