{
  "id": 7206562,
  "type": "Feature",
  "properties": {
    "tgn:hierarchy":[
        "tgn:7206562",
        "tgn:7003692",
        "tgn:1000003",
        "tgn:7000084",
        "tgn:7029392"
    ],
    "tgn:id":7206562,
    "tgn:name":"Dachswald",
    "tgn:placetype":[
        "aat:300008347"
    ]
},
  "bbox": [],
  "geometry": {"coordinates":[9.116667,48.75],"type":"Point"}
}