{
  "id": 2498392,
  "type": "Feature",
  "properties": {
    "tgn:hierarchy":[
        "tgn:2498392",
        "tgn:1000001",
        "tgn:7012149",
        "tgn:2000231",
        "tgn:7007158",
        "tgn:7029392"
    ],
    "tgn:id":2498392,
    "tgn:name":"Mc Kenzie Mountain",
    "tgn:placetype":[
        "aat:300008798"
    ]
},
  "bbox": [],
  "geometry": {"coordinates":[-106.9833,37.8833],"type":"Point"}
}