{
  "id": 1136206,
  "type": "Feature",
  "properties": {
    "tgn:hierarchy":[
        "tgn:1136206",
        "tgn:1001160",
        "tgn:7006477",
        "tgn:1000002",
        "tgn:7029392"
    ],
    "tgn:id":1136206,
    "tgn:name":"Costanero, Canal",
    "tgn:placetype":[
        "aat:300386965"
    ]
},
  "bbox": [],
  "geometry": {"coordinates":[-58.4667,-34.4667],"type":"Point"}
}