{
  "id": 7344217,
  "type": "Feature",
  "properties": {
    "tgn:hierarchy":[
        "tgn:7344217",
        "tgn:1001439",
        "tgn:1000003",
        "tgn:7002797",
        "tgn:1000095",
        "tgn:7029392"
    ],
    "tgn:id":7344217,
    "tgn:name":"Barrio de Peral",
    "tgn:placetype":[
        "aat:300008347"
    ]
},
  "bbox": [],
  "geometry": {"coordinates":[-0.983333,37.616667],"type":"Point"}
}