{
  "id": 2151326,
  "type": "Feature",
  "properties": {
    "tgn:hierarchy":[
        "tgn:2151326",
        "tgn:1000001",
        "tgn:1002753",
        "tgn:7012149",
        "tgn:7007828",
        "tgn:7029392"
    ],
    "tgn:id":2151326,
    "tgn:name":"Bates Hill",
    "tgn:placetype":[
        "aat:300008798"
    ]
},
  "bbox": [],
  "geometry": {"coordinates":[-72.0833,44.9333],"type":"Point"}
}