<<<<<<< HEAD
{
  "id": 2403960,
  "type": "Feature",
  "properties": {
    "tgn:hierarchy":[
        "tgn:2403960",
        "tgn:1000001",
        "tgn:7012149",
        "tgn:1002990",
        "tgn:7007708",
        "tgn:7029392"
    ],
    "tgn:id":2403960,
    "tgn:name":"Howell Canyon",
    "tgn:placetype":[
        "aat:300008761"
    ]
},
  "bbox": [],
  "geometry": {"coordinates":[-120.7333,45.1],"type":"Point"}
}
=======
{"geometry":{"type":"Point","coordinates":[-120.733300,45.100000]},"type":"Feature","properties":{"hierarchy":["tgn:2403960","tgn:1000001","tgn:7012149","tgn:1002990","tgn:7007708","tgn:7029392"],"placetype":["aat:300008761"],"id":2403960,"name:xx":"Howell Canyon"}}
>>>>>>> 03f74aca74312dbeaf24d7e61306dd6a786dc3d0
