{
  "id": 2349345,
  "type": "Feature",
  "properties": {
    "tgn:hierarchy":[
        "tgn:2349345",
        "tgn:7002659",
        "tgn:1000001",
        "tgn:7012149",
        "tgn:7029392"
    ],
    "tgn:id":2349345,
    "tgn:name":"Gile Creek",
    "tgn:placetype":[
        "aat:300008706"
    ]
},
  "bbox": [],
  "geometry": {"coordinates":[-87.5833,32.8833],"type":"Point"}
}