{
  "id": 2135584,
  "type": "Feature",
  "properties": {
    "tgn:hierarchy":[
        "tgn:2135584",
        "tgn:1000001",
        "tgn:7012149",
        "tgn:7007825",
        "tgn:7029392"
    ],
    "tgn:id":2135584,
    "tgn:name":"Apache Creek",
    "tgn:placetype":[
        "aat:300008706"
    ]
},
  "bbox": [],
  "geometry": {"coordinates":[-82.2167,36.3833],"type":"Point"}
}