{
  "id": 2709067,
  "type": "Feature",
  "properties": {
    "tgn:hierarchy":[
        "tgn:2709067",
        "tgn:1000001",
        "tgn:7006451",
        "tgn:2000092",
        "tgn:7012149",
        "tgn:7029392"
    ],
    "tgn:id":2709067,
    "tgn:name":"T-bar Tank Number Two",
    "tgn:placetype":[
        "aat:300006191"
    ]
},
  "bbox": [],
  "geometry": {"coordinates":[-111.5167,34.7167],"type":"Point"}
}