{
  "id": 2494685,
  "type": "Feature",
  "properties": {
    "tgn:hierarchy":[
        "tgn:2494685",
        "tgn:1000001",
        "tgn:7012149",
        "tgn:2001291",
        "tgn:7007524",
        "tgn:7029392"
    ],
    "tgn:id":2494685,
    "tgn:name":"Martin Point",
    "tgn:placetype":[
        "aat:300008798"
    ]
},
  "bbox": [],
  "geometry": {"coordinates":[-114.4833,46.95],"type":"Point"}
}