{
  "id": 7273270,
  "type": "Feature",
  "properties": {
    "tgn:hierarchy":[
        "tgn:7273270",
        "tgn:1000003",
        "tgn:7003613",
        "tgn:7016845",
        "tgn:7029392"
    ],
    "tgn:id":7273270,
    "tgn:name:nl":"Westeremdervoorwerk",
    "tgn:placetype":[
        "aat:300387200"
    ]
},
  "bbox": [],
  "geometry": {"coordinates":[6.716667,53.35],"type":"Point"}
}