{
  "id": 2766348,
  "type": "Feature",
  "properties": {
    "tgn:hierarchy":[
        "tgn:2766348",
        "tgn:1000001",
        "tgn:7012149",
        "tgn:7007157",
        "tgn:1002857",
        "tgn:7029392"
    ],
    "tgn:id":2766348,
    "tgn:name":"White Mountain",
    "tgn:placetype":[
        "aat:300008798"
    ]
},
  "bbox": [],
  "geometry": {"coordinates":[-119.0167,34.35],"type":"Point"}
}