{
  "id": 7009159,
  "type": "Feature",
  "properties": {
    "tgn:hierarchy":[
        "tgn:7009159",
        "tgn:7002870",
        "tgn:1000003",
        "tgn:1000070",
        "tgn:7029392"
    ],
    "tgn:id":7009159,
    "tgn:name":"Ensisheim",
    "tgn:placetype":[
        "aat:300008347"
    ]
},
  "bbox": [],
  "geometry": {"coordinates":[7.3333,47.85],"type":"Point"}
}