{
  "id": 2227955,
  "type": "Feature",
  "properties": {
    "tgn:hierarchy":[
        "tgn:2227955",
        "tgn:1000001",
        "tgn:7012149",
        "tgn:2002093",
        "tgn:7007826",
        "tgn:7029392"
    ],
    "tgn:id":2227955,
    "tgn:name":"Cedar Bluff Tank",
    "tgn:placetype":[
        "aat:300006191"
    ]
},
  "bbox": [],
  "geometry": {"coordinates":[-99.3667,33.95],"type":"Point"}
}