{
  "id": 2139265,
  "type": "Feature",
  "properties": {
    "tgn:hierarchy":[
        "tgn:2139265",
        "tgn:1000001",
        "tgn:7012149",
        "tgn:2000366",
        "tgn:7007248",
        "tgn:7029392"
    ],
    "tgn:id":2139265,
    "tgn:name":"Askew Lakes-North Lake",
    "tgn:placetype":[
        "aat:300006191"
    ]
},
  "bbox": [],
  "geometry": {"coordinates":[-84.25,33.55],"type":"Point"}
}