{
  "id": 2593090,
  "type": "Feature",
  "properties": {
    "tgn:hierarchy":[
        "tgn:2593090",
        "tgn:1000001",
        "tgn:7012149",
        "tgn:2000831",
        "tgn:7007255",
        "tgn:7029392"
    ],
    "tgn:id":2593090,
    "tgn:name":"Poplar Hollow",
    "tgn:placetype":[
        "aat:300008761"
    ]
},
  "bbox": [],
  "geometry": {"coordinates":[-83.2333,38.0333],"type":"Point"}
}