<<<<<<< HEAD
{
  "id": 7240739,
  "type": "Feature",
  "properties": {
    "tgn:hierarchy":[
        "tgn:7240739",
        "tgn:7003466",
        "tgn:1000003",
        "tgn:1000063",
        "tgn:4012014",
        "tgn:7029392"
    ],
    "tgn:id":7240739,
    "tgn:name":"Fevie",
    "tgn:placetype":[
        "aat:300008347"
    ]
},
  "bbox": [],
  "geometry": {"coordinates":[5.182262,50.301577],"type":"Point"}
}
=======
{"geometry":{"type":"Point","coordinates":[5.182262,50.301577]},"type":"Feature","properties":{"hierarchy":["tgn:7240739","tgn:7003466","tgn:1000003","tgn:1000063","tgn:4012014","tgn:7029392"],"placetype":["aat:300008347"],"id":7240739,"name:xx":"Fevie"}}
>>>>>>> 03f74aca74312dbeaf24d7e61306dd6a786dc3d0
