{
  "id": 2707734,
  "type": "Feature",
  "properties": {
    "tgn:hierarchy":[
        "tgn:2707734",
        "tgn:1000001",
        "tgn:7012149",
        "tgn:1002517",
        "tgn:7007523",
        "tgn:7029392"
    ],
    "tgn:id":2707734,
    "tgn:name":"Sweetwater Lake",
    "tgn:placetype":[
        "aat:300006191"
    ]
},
  "bbox": [],
  "geometry": {"coordinates":[-90.5833,38.35],"type":"Point"}
}