{
  "id": 2398281,
  "type": "Feature",
  "properties": {
    "tgn:hierarchy":[
        "tgn:2398281",
        "tgn:1000001",
        "tgn:7012149",
        "tgn:2001497",
        "tgn:7007709",
        "tgn:7029392"
    ],
    "tgn:id":2398281,
    "tgn:name":"Hooper Branch",
    "tgn:placetype":[
        "aat:300008699"
    ]
},
  "bbox": [],
  "geometry": {"coordinates":[-83.85,35.2833],"type":"Point"}
}