<<<<<<< HEAD
{
  "id": 7172402,
  "type": "Feature",
  "properties": {
    "tgn:hierarchy":[
        "tgn:7172402",
        "tgn:1000003",
        "tgn:7003677",
        "tgn:7000084",
        "tgn:7029392"
    ],
    "tgn:id":7172402,
    "tgn:name":"Hellinghausen",
    "tgn:placetype":[
        "aat:300000206"
    ]
},
  "bbox": [],
  "geometry": {"coordinates":[8.95,52.166667],"type":"Point"}
}
=======
{"geometry":{"type":"Point","coordinates":[8.950000,52.166667]},"type":"Feature","properties":{"hierarchy":["tgn:7172402","tgn:1000003","tgn:7003677","tgn:7000084","tgn:7029392"],"placetype":["aat:300000206"],"id":7172402,"name:xx":"Hellinghausen"}}
>>>>>>> 03f74aca74312dbeaf24d7e61306dd6a786dc3d0
