{
  "id": 2166531,
  "type": "Feature",
  "properties": {
    "tgn:hierarchy":[
        "tgn:2166531",
        "tgn:2000294",
        "tgn:1000001",
        "tgn:7012149",
        "tgn:7007248",
        "tgn:7029392"
    ],
    "tgn:id":2166531,
    "tgn:name":"Big Branch",
    "tgn:placetype":[
        "aat:300008699"
    ]
},
  "bbox": [],
  "geometry": {"coordinates":[-82.4667,31.4833],"type":"Point"}
}