{
  "id": 7540786,
  "type": "Feature",
  "properties": {
    "tgn:hierarchy":[
        "tgn:7540786",
        "tgn:7001242",
        "tgn:1001075",
        "tgn:7016833",
        "tgn:7029392"
    ],
    "tgn:id":7540786,
    "tgn:name:en":"Tir'at an Naj\u0101\u1e29",
    "tgn:placetype":[
        "aat:300006075"
    ]
},
  "bbox": [],
  "geometry": {"coordinates":[30.597261,30.596066],"type":"Point"}
}