{
  "id": 7140176,
  "type": "Feature",
  "properties": {
    "tgn:hierarchy":[
        "tgn:7140176",
        "tgn:1000003",
        "tgn:7003678",
        "tgn:7000084",
        "tgn:7029392"
    ],
    "tgn:id":7140176,
    "tgn:name":"L\u00fctzelbach",
    "tgn:placetype":[
        "aat:300008347"
    ]
},
  "bbox": [],
  "geometry": {"coordinates":[8.7675,49.7425],"type":"Point"}
}