{
  "id": 2480465,
  "type": "Feature",
  "properties": {
    "tgn:hierarchy":[
        "tgn:2480465",
        "tgn:2001463",
        "tgn:1000001",
        "tgn:7012149",
        "tgn:7007709",
        "tgn:7029392"
    ],
    "tgn:id":2480465,
    "tgn:name":"Lake View Estates Pond",
    "tgn:placetype":[
        "aat:300006191"
    ]
},
  "bbox": [],
  "geometry": {"coordinates":[-79.3833,36.1167],"type":"Point"}
}