{
  "id": 2660243,
  "type": "Feature",
  "properties": {
    "tgn:hierarchy":[
        "tgn:2660243",
        "tgn:7002659",
        "tgn:1000001",
        "tgn:7012149",
        "tgn:2000057",
        "tgn:7029392"
    ],
    "tgn:id":2660243,
    "tgn:name":"Shoal Creek Mountain",
    "tgn:placetype":[
        "aat:300008798"
    ]
},
  "bbox": [],
  "geometry": {"coordinates":[-86.4667,33.5167],"type":"Point"}
}