{
  "id": 7473455,
  "type": "Feature",
  "properties": {
    "tgn:hierarchy":[
        "tgn:7473455",
        "tgn:1000004",
        "tgn:1000454",
        "tgn:1000141",
        "tgn:7029392"
    ],
    "tgn:id":7473455,
    "tgn:name":"Xinxian Yanti",
    "tgn:placetype":[
        "aat:300170882"
    ]
},
  "bbox": [],
  "geometry": {"coordinates":[121.526575,24.831772],"type":"Point"}
}