{
  "id": 2347246,
  "type": "Feature",
  "properties": {
    "tgn:hierarchy":[
        "tgn:2347246",
        "tgn:1000001",
        "tgn:7006451",
        "tgn:7012149",
        "tgn:2000099",
        "tgn:7029392"
    ],
    "tgn:id":2347246,
    "tgn:name":"Gentry Trail Tank",
    "tgn:placetype":[
        "aat:300006191"
    ]
},
  "bbox": [],
  "geometry": {"coordinates":[-110.7167,34.05],"type":"Point"}
}