{
  "id": 7138751,
  "type": "Feature",
  "properties": {
    "tgn:hierarchy":[
        "tgn:7138751",
        "tgn:7003669",
        "tgn:1000003",
        "tgn:7000084",
        "tgn:7029392"
    ],
    "tgn:id":7138751,
    "tgn:name":"Lauterhof",
    "tgn:placetype":[
        "aat:300000206"
    ]
},
  "bbox": [],
  "geometry": {"coordinates":[9.116667,49.85],"type":"Point"}
}