{
  "id": 7331346,
  "type": "Feature",
  "properties": {
    "tgn:hierarchy":[
        "tgn:7331346",
        "tgn:7002836",
        "tgn:7016622",
        "tgn:1000003",
        "tgn:1000095",
        "tgn:7029392"
    ],
    "tgn:id":7331346,
    "tgn:name":"La Costa",
    "tgn:placetype":[
        "aat:300008347"
    ]
},
  "bbox": [],
  "geometry": {"coordinates":[-16.383333,28.316667],"type":"Point"}
}