{
  "id": 7535443,
  "type": "Feature",
  "properties": {
    "tgn:hierarchy":[
        "tgn:7535443",
        "tgn:7001242",
        "tgn:7016833",
        "tgn:1001110",
        "tgn:7029392"
    ],
    "tgn:id":7535443,
    "tgn:name:en":"Jal\u0101lah, Khashm al",
    "tgn:placetype":[
        "aat:300387002"
    ]
},
  "bbox": [],
  "geometry": {"coordinates":[32.336389,29.569444],"type":"Point"}
}