{
  "id": 7402251,
  "type": "Feature",
  "properties": {
    "tgn:hierarchy":[
        "tgn:7402251",
        "tgn:1000001",
        "tgn:7005599",
        "tgn:7005560",
        "tgn:7029392"
    ],
    "tgn:id":7402251,
    "tgn:name":"San Jos\u00e9 de Pastor\u00edas",
    "tgn:placetype":[
        "aat:300008347"
    ]
},
  "bbox": [],
  "geometry": {"coordinates":[-96.570833,19.558333],"type":"Point"}
}