{
  "id": 7513988,
  "type": "Feature",
  "properties": {
    "tgn:hierarchy":[
        "tgn:7513988",
        "tgn:1009227",
        "tgn:7001866",
        "tgn:1000226",
        "tgn:1000006",
        "tgn:7029392"
    ],
    "tgn:id":7513988,
    "tgn:name:en":"Eyrewell",
    "tgn:placetype":[
        "aat:300000206"
    ]
},
  "bbox": [],
  "geometry": {"coordinates":[172.383333,-43.383333],"type":"Point"}
}