{
  "id": 2747513,
  "type": "Feature",
  "properties": {
    "tgn:hierarchy":[
        "tgn:2747513",
        "tgn:1007657",
        "tgn:1002534",
        "tgn:1000001",
        "tgn:7012149",
        "tgn:7007249",
        "tgn:7029392"
    ],
    "tgn:id":2747513,
    "tgn:name":"Waieli Draw",
    "tgn:placetype":[
        "aat:300008699"
    ]
},
  "bbox": [],
  "geometry": {"coordinates":[-159.7833,22.0167],"type":"Point"}
}