{
  "id": 2151656,
  "type": "Feature",
  "properties": {
    "tgn:hierarchy":[
        "tgn:2151656",
        "tgn:1000001",
        "tgn:7012149",
        "tgn:7007523",
        "tgn:7029392"
    ],
    "tgn:id":2151656,
    "tgn:name":"Battle Creek",
    "tgn:placetype":[
        "aat:300008706"
    ]
},
  "bbox": [],
  "geometry": {"coordinates":[-91.2333,39.5833],"type":"Point"}
}