<<<<<<< HEAD
{
  "id": 2151656,
  "type": "Feature",
  "properties": {
    "tgn:hierarchy":[
        "tgn:2151656",
        "tgn:1000001",
        "tgn:7012149",
        "tgn:7007523",
        "tgn:7029392"
    ],
    "tgn:id":2151656,
    "tgn:name":"Battle Creek",
    "tgn:placetype":[
        "aat:300008706"
    ]
},
  "bbox": [],
  "geometry": {"coordinates":[-91.2333,39.5833],"type":"Point"}
}
=======
{"geometry":{"type":"Point","coordinates":[-91.233300,39.583300]},"type":"Feature","properties":{"hierarchy":["tgn:2151656","tgn:1000001","tgn:7012149","tgn:7007523","tgn:7029392"],"placetype":["aat:300008706"],"id":2151656,"name:xx":"Battle Creek"}}
>>>>>>> 03f74aca74312dbeaf24d7e61306dd6a786dc3d0
