{
  "id": 2428369,
  "type": "Feature",
  "properties": {
    "tgn:hierarchy":[
        "tgn:2428369",
        "tgn:1000001",
        "tgn:7012149",
        "tgn:2001062",
        "tgn:7007521",
        "tgn:7029392"
    ],
    "tgn:id":2428369,
    "tgn:name":"Judicial Ditch Number Twelve",
    "tgn:placetype":[
        "aat:300006075"
    ]
},
  "bbox": [],
  "geometry": {"coordinates":[-95.5167,44.3333],"type":"Point"}
}