{
  "id": 7544842,
  "type": "Feature",
  "properties": {
    "tgn:hierarchy":[
        "tgn:7544842",
        "tgn:1000004",
        "tgn:7000198",
        "tgn:7016788",
        "tgn:7029392"
    ],
    "tgn:id":7544842,
    "tgn:name:en":"Bh\u0101vla",
    "tgn:placetype":[
        "aat:300008347"
    ]
},
  "bbox": [],
  "geometry": {"coordinates":[74.095673,26.980954],"type":"Point"}
}