{
  "id": 2667785,
  "type": "Feature",
  "properties": {
    "tgn:hierarchy":[
        "tgn:2667785",
        "tgn:1000001",
        "tgn:7012149",
        "tgn:7007157",
        "tgn:1002957",
        "tgn:7029392"
    ],
    "tgn:id":2667785,
    "tgn:name":"Skunk Creek",
    "tgn:placetype":[
        "aat:300008706"
    ]
},
  "bbox": [],
  "geometry": {"coordinates":[-119.9833,37.9833],"type":"Point"}
}