{
  "id": 1138393,
  "type": "Feature",
  "properties": {
    "tgn:hierarchy":[
        "tgn:1138393",
        "tgn:7011700",
        "tgn:1000003",
        "tgn:7006657",
        "tgn:7029392"
    ],
    "tgn:id":1138393,
    "tgn:name":"Slawharad",
    "tgn:placetype":[
        "aat:300008347"
    ]
},
  "bbox": [],
  "geometry": {"coordinates":[30.9833,53.4333],"type":"Point"}
}