{
  "id": 2692808,
  "type": "Feature",
  "properties": {
    "tgn:hierarchy":[
        "tgn:2692808",
        "tgn:7002659",
        "tgn:1000001",
        "tgn:7012149",
        "tgn:2000029",
        "tgn:7029392"
    ],
    "tgn:id":2692808,
    "tgn:name":"Steele Branch",
    "tgn:placetype":[
        "aat:300008699"
    ]
},
  "bbox": [],
  "geometry": {"coordinates":[-87.8167,34.4167],"type":"Point"}
}