{
  "id": 2397476,
  "type": "Feature",
  "properties": {
    "tgn:hierarchy":[
        "tgn:2397476",
        "tgn:1000001",
        "tgn:1002213",
        "tgn:7012149",
        "tgn:7007710",
        "tgn:7029392"
    ],
    "tgn:id":2397476,
    "tgn:name":"Honey Hollow Pond",
    "tgn:placetype":[
        "aat:300006191"
    ]
},
  "bbox": [],
  "geometry": {"coordinates":[-74.9833,40.3667],"type":"Point"}
}