{
  "id": 2237407,
  "type": "Feature",
  "properties": {
    "tgn:hierarchy":[
        "tgn:2237407",
        "tgn:1000001",
        "tgn:7012149",
        "tgn:2001709",
        "tgn:7007708",
        "tgn:7029392"
    ],
    "tgn:id":2237407,
    "tgn:name":"China Cap Mine",
    "tgn:placetype":[
        "aat:300000390"
    ]
},
  "bbox": [],
  "geometry": {"coordinates":[-119.7333,43.1833],"type":"Point"}
}