<<<<<<< HEAD
{
  "id": 2159220,
  "type": "Feature",
  "properties": {
    "tgn:hierarchy":[
        "tgn:2159220",
        "tgn:1000001",
        "tgn:7012149",
        "tgn:7007522",
        "tgn:7029392"
    ],
    "tgn:id":2159220,
    "tgn:name":"Bee Bayou",
    "tgn:placetype":[
        "aat:300008699"
    ]
},
  "bbox": [],
  "geometry": {"coordinates":[-90.9667,33.5833],"type":"Point"}
}
=======
{"geometry":{"type":"Point","coordinates":[-90.966700,33.583300]},"type":"Feature","properties":{"hierarchy":["tgn:2159220","tgn:1000001","tgn:7012149","tgn:7007522","tgn:7029392"],"placetype":["aat:300008699"],"id":2159220,"name:xx":"Bee Bayou"}}
>>>>>>> 03f74aca74312dbeaf24d7e61306dd6a786dc3d0
