{
  "id": 2159220,
  "type": "Feature",
  "properties": {
    "tgn:hierarchy":[
        "tgn:2159220",
        "tgn:1000001",
        "tgn:7012149",
        "tgn:7007522",
        "tgn:7029392"
    ],
    "tgn:id":2159220,
    "tgn:name":"Bee Bayou",
    "tgn:placetype":[
        "aat:300008699"
    ]
},
  "bbox": [],
  "geometry": {"coordinates":[-90.9667,33.5833],"type":"Point"}
}