{
  "id": 2623892,
  "type": "Feature",
  "properties": {
    "tgn:hierarchy":[
        "tgn:2623892",
        "tgn:1000001",
        "tgn:7012149",
        "tgn:2002376",
        "tgn:7007923",
        "tgn:7029392"
    ],
    "tgn:id":2623892,
    "tgn:name":"Rock Creek Ridge",
    "tgn:placetype":[
        "aat:300266640"
    ]
},
  "bbox": [],
  "geometry": {"coordinates":[-110.8333,41.9333],"type":"Point"}
}