{
  "id": 7030448,
  "type": "Feature",
  "properties": {
    "tgn:hierarchy":[
        "tgn:7030448",
        "tgn:1000004",
        "tgn:1001606",
        "tgn:7018453",
        "tgn:1000144",
        "tgn:7029392"
    ],
    "tgn:id":7030448,
    "tgn:name":"B\u00fcy\u00fcknefes",
    "tgn:placetype":[
        "aat:300008347",
        "aat:300020669",
        "aat:300008542",
        "aat:300008372",
        "aat:300387286"
    ]
},
  "bbox": [],
  "geometry": {"coordinates":[34.525,39.858],"type":"Point"}
}