{
  "id": 7394056,
  "type": "Feature",
  "properties": {
    "tgn:hierarchy":[
        "tgn:7394056",
        "tgn:1001836",
        "tgn:1000001",
        "tgn:7005560",
        "tgn:7029392"
    ],
    "tgn:id":7394056,
    "tgn:name":"San Benito, Arroyo",
    "tgn:placetype":[
        "aat:300008699"
    ]
},
  "bbox": [],
  "geometry": {"coordinates":[-112.966667,26.566667],"type":"Point"}
}