{
  "id": 2377840,
  "type": "Feature",
  "properties": {
    "tgn:hierarchy":[
        "tgn:2377840",
        "tgn:1000001",
        "tgn:7012149",
        "tgn:2001996",
        "tgn:7007826",
        "tgn:7029392"
    ],
    "tgn:id":2377840,
    "tgn:name":"Harrington Cove",
    "tgn:placetype":[
        "aat:300386845"
    ]
},
  "bbox": [],
  "geometry": {"coordinates":[-98.25,31.5167],"type":"Point"}
}