{
  "id": 2282391,
  "type": "Feature",
  "properties": {
    "tgn:hierarchy":[
        "tgn:2282391",
        "tgn:1000001",
        "tgn:1002219",
        "tgn:7012149",
        "tgn:7007157",
        "tgn:7029392"
    ],
    "tgn:id":2282391,
    "tgn:name":"Deer Peak",
    "tgn:placetype":[
        "aat:300008798"
    ]
},
  "bbox": [],
  "geometry": {"coordinates":[-120.7167,38.1667],"type":"Point"}
}