{
  "id": 2086114,
  "type": "Feature",
  "properties": {
    "tgn:hierarchy":[
        "tgn:2086114",
        "tgn:1002153",
        "tgn:1000001",
        "tgn:7012149",
        "tgn:7007710",
        "tgn:7029392"
    ],
    "tgn:id":2086114,
    "tgn:name":"Atwood",
    "tgn:placetype":[
        "aat:300008347"
    ]
},
  "bbox": [],
  "geometry": {"coordinates":[-79.2667,40.75],"type":"Point"}
}