{
  "id": 7275597,
  "type": "Feature",
  "properties": {
    "tgn:hierarchy":[
        "tgn:7275597",
        "tgn:1001637",
        "tgn:1000049",
        "tgn:1000002",
        "tgn:7029392"
    ],
    "tgn:id":7275597,
    "tgn:name":"Tres Morros, Cerro",
    "tgn:placetype":[
        "aat:300008795"
    ]
},
  "bbox": [],
  "geometry": {"coordinates":[-71.466667,-36.65],"type":"Point"}
}