{
  "id": 7394386,
  "type": "Feature",
  "properties": {
    "tgn:hierarchy":[
        "tgn:7394386",
        "tgn:1000001",
        "tgn:7005597",
        "tgn:7005560",
        "tgn:7029392"
    ],
    "tgn:id":7394386,
    "tgn:name":"San Lorenzo",
    "tgn:placetype":[
        "aat:300008347"
    ]
},
  "bbox": [],
  "geometry": {"coordinates":[-99.624444,24.597778],"type":"Point"}
}