{
  "id": 7275934,
  "type": "Feature",
  "properties": {
    "tgn:hierarchy":[
        "tgn:7275934",
        "tgn:1001657",
        "tgn:1000049",
        "tgn:1000002",
        "tgn:7029392"
    ],
    "tgn:id":7275934,
    "tgn:name":"Ternero, R\u00edo",
    "tgn:placetype":[
        "aat:300008699"
    ]
},
  "bbox": [],
  "geometry": {"coordinates":[-70.316667,-30.566667],"type":"Point"}
}