{
  "id": 1103942,
  "type": "Feature",
  "properties": {
    "tgn:hierarchy":[
        "tgn:1103942",
        "tgn:1000001",
        "tgn:7012149",
        "tgn:2000352",
        "tgn:7007248",
        "tgn:7029392"
    ],
    "tgn:id":1103942,
    "tgn:name":"Big Bald Mountain",
    "tgn:placetype":[
        "aat:300008795"
    ]
},
  "bbox": [],
  "geometry": {"coordinates":[-84.3167,34.75],"type":"Point"}
}