{
  "id": 1001640,
  "type": "Feature",
  "properties": {
    "tgn:hierarchy":[
        "tgn:1001640",
        "tgn:7001242",
        "tgn:1000166",
        "tgn:7029392"
    ],
    "tgn:id":1001640,
    "tgn:name":"Brong-Ahafo",
    "tgn:placetype":[
        "aat:300387064",
        "aat:300236112"
    ]
},
  "bbox": [],
  "geometry": {"coordinates":[-0.2167,7.7667],"type":"Point"}
}