{
  "id": 7569226,
  "type": "Feature",
  "properties": {
    "tgn:hierarchy":[
        "tgn:7569226",
        "tgn:1000004",
        "tgn:7000198",
        "tgn:7016788",
        "tgn:7029392"
    ],
    "tgn:id":7569226,
    "tgn:name:en":"Bhairopura",
    "tgn:placetype":[
        "aat:300008347"
    ]
},
  "bbox": [],
  "geometry": {"coordinates":[75.69553,25.688838],"type":"Point"}
}