{
  "id": 7455148,
  "type": "Feature",
  "properties": {
    "tgn:hierarchy":[
        "tgn:7455148",
        "tgn:7002445",
        "tgn:1000003",
        "tgn:7008167",
        "tgn:7008591",
        "tgn:7029392"
    ],
    "tgn:id":7455148,
    "tgn:name:en":"Caunton",
    "tgn:placetype":[
        "aat:300008347"
    ]
},
  "bbox": [],
  "geometry": {"coordinates":[-0.883333,53.133333],"type":"Point"}
}