{
  "id": 7200184,
  "type": "Feature",
  "properties": {
    "tgn:hierarchy":[
        "tgn:7200184",
        "tgn:7003669",
        "tgn:1000003",
        "tgn:7000084",
        "tgn:7029392"
    ],
    "tgn:id":7200184,
    "tgn:name":"Eden",
    "tgn:placetype":[
        "aat:300008347"
    ]
},
  "bbox": [],
  "geometry": {"coordinates":[13.25,48.433333],"type":"Point"}
}