{
  "id": 2318010,
  "type": "Feature",
  "properties": {
    "tgn:hierarchy":[
        "tgn:2318010",
        "tgn:1000001",
        "tgn:7016172",
        "tgn:7012149",
        "tgn:2000173",
        "tgn:7029392"
    ],
    "tgn:id":2318010,
    "tgn:name":"Ennis Cave",
    "tgn:placetype":[
        "aat:300008746"
    ]
},
  "bbox": [],
  "geometry": {"coordinates":[-91.8667,35.85],"type":"Point"}
}