{
  "id": 2478916,
  "type": "Feature",
  "properties": {
    "tgn:hierarchy":[
        "tgn:2478916",
        "tgn:1000001",
        "tgn:7012149",
        "tgn:2002374",
        "tgn:7007923",
        "tgn:7029392"
    ],
    "tgn:id":2478916,
    "tgn:name":"Magdalene Lake",
    "tgn:placetype":[
        "aat:300008680"
    ]
},
  "bbox": [],
  "geometry": {"coordinates":[-107.0167,44.2333],"type":"Point"}
}