<<<<<<< HEAD
{
  "id": 2330377,
  "type": "Feature",
  "properties": {
    "tgn:hierarchy":[
        "tgn:2330377",
        "tgn:1000001",
        "tgn:7012149",
        "tgn:2001551",
        "tgn:7007709",
        "tgn:7029392"
    ],
    "tgn:id":2330377,
    "tgn:name":"Flat Branch",
    "tgn:placetype":[
        "aat:300008699"
    ]
},
  "bbox": [],
  "geometry": {"coordinates":[-81.5167,36.15],"type":"Point"}
}
=======
{"geometry":{"type":"Point","coordinates":[-81.516700,36.150000]},"type":"Feature","properties":{"hierarchy":["tgn:2330377","tgn:1000001","tgn:7012149","tgn:2001551","tgn:7007709","tgn:7029392"],"placetype":["aat:300008699"],"id":2330377,"name:xx":"Flat Branch"}}
>>>>>>> 03f74aca74312dbeaf24d7e61306dd6a786dc3d0
