{
  "id": 2122205,
  "type": "Feature",
  "properties": {
    "tgn:hierarchy":[
        "tgn:2122205",
        "tgn:1000001",
        "tgn:7012149",
        "tgn:2002353",
        "tgn:7007922",
        "tgn:7029392"
    ],
    "tgn:id":2122205,
    "tgn:name":"Radisson",
    "tgn:placetype":[
        "aat:300008347"
    ]
},
  "bbox": [],
  "geometry": {"coordinates":[-91.2167,45.7667],"type":"Point"}
}