{
  "id": 1130612,
  "type": "Feature",
  "properties": {
    "tgn:hierarchy":[
        "tgn:1130612",
        "tgn:1000050",
        "tgn:1000704",
        "tgn:1000002",
        "tgn:7029392"
    ],
    "tgn:id":1130612,
    "tgn:name":"Tapaje",
    "tgn:placetype":[
        "aat:300008707"
    ]
},
  "bbox": [],
  "geometry": {"coordinates":[-78.1167,2.7333],"type":"Point"}
}