{
  "id": 2409523,
  "type": "Feature",
  "properties": {
    "tgn:hierarchy":[
        "tgn:2409523",
        "tgn:1002300",
        "tgn:1000001",
        "tgn:7012149",
        "tgn:7007564",
        "tgn:7029392"
    ],
    "tgn:id":2409523,
    "tgn:name":"Idlewilde",
    "tgn:placetype":[
        "aat:300008347"
    ]
},
  "bbox": [],
  "geometry": {"coordinates":[-71.1667,45.15],"type":"Point"}
}