<<<<<<< HEAD
{
  "id": 2409523,
  "type": "Feature",
  "properties": {
    "tgn:hierarchy":[
        "tgn:2409523",
        "tgn:1002300",
        "tgn:1000001",
        "tgn:7012149",
        "tgn:7007564",
        "tgn:7029392"
    ],
    "tgn:id":2409523,
    "tgn:name":"Idlewilde",
    "tgn:placetype":[
        "aat:300008347"
    ]
},
  "bbox": [],
  "geometry": {"coordinates":[-71.1667,45.15],"type":"Point"}
}
=======
{"geometry":{"type":"Point","coordinates":[-71.166700,45.150000]},"type":"Feature","properties":{"hierarchy":["tgn:2409523","tgn:1002300","tgn:1000001","tgn:7012149","tgn:7007564","tgn:7029392"],"placetype":["aat:300008347"],"id":2409523,"name:xx":"Idlewilde"}}
>>>>>>> 03f74aca74312dbeaf24d7e61306dd6a786dc3d0
