{
  "id": 2463569,
  "type": "Feature",
  "properties": {
    "tgn:hierarchy":[
        "tgn:2463569",
        "tgn:1000001",
        "tgn:7012149",
        "tgn:2001721",
        "tgn:7007708",
        "tgn:7029392"
    ],
    "tgn:id":2463569,
    "tgn:name":"Lobo Creek",
    "tgn:placetype":[
        "aat:300008706"
    ]
},
  "bbox": [],
  "geometry": {"coordinates":[-117.6833,45.4167],"type":"Point"}
}