{
  "id": 7505971,
  "type": "Feature",
  "properties": {
    "tgn:hierarchy":[
        "tgn:7505971",
        "tgn:1009227",
        "tgn:1000226",
        "tgn:7018437",
        "tgn:1000006",
        "tgn:7029392"
    ],
    "tgn:id":7505971,
    "tgn:name:en":"Shepherds Creek",
    "tgn:placetype":[
        "aat:300008699"
    ]
},
  "bbox": [],
  "geometry": {"coordinates":[169.166667,-45.083333],"type":"Point"}
}