{
  "id": 7344484,
  "type": "Feature",
  "properties": {
    "tgn:hierarchy":[
        "tgn:7344484",
        "tgn:7002759",
        "tgn:7008909",
        "tgn:1000003",
        "tgn:1000095",
        "tgn:7029392"
    ],
    "tgn:id":7344484,
    "tgn:name":"Ara, R\u00edo",
    "tgn:placetype":[
        "aat:300008699"
    ]
},
  "bbox": [],
  "geometry": {"coordinates":[0.141265,42.413648],"type":"Point"}
}