{
  "id": 1109471,
  "type": "Feature",
  "properties": {
    "tgn:hierarchy":[
        "tgn:1109471",
        "tgn:1000001",
        "tgn:2001411",
        "tgn:7012149",
        "tgn:7007526",
        "tgn:7029392"
    ],
    "tgn:id":1109471,
    "tgn:name":"Pequop Mountains",
    "tgn:placetype":[
        "aat:300008795"
    ]
},
  "bbox": [],
  "geometry": {"coordinates":[-114.5833,40.85],"type":"Point"}
}