{
  "id": 2568188,
  "type": "Feature",
  "properties": {
    "tgn:hierarchy":[
        "tgn:2568188",
        "tgn:1000001",
        "tgn:7012149",
        "tgn:2001456",
        "tgn:7007566",
        "tgn:7029392"
    ],
    "tgn:id":2568188,
    "tgn:name":"Parida, Ojo de la",
    "tgn:placetype":[
        "aat:300008697"
    ]
},
  "bbox": [],
  "geometry": {"coordinates":[-106.7833,34.1333],"type":"Point"}
}