{
  "id": 7123424,
  "type": "Feature",
  "properties": {
    "tgn:hierarchy":[
        "tgn:7123424",
        "tgn:1000003",
        "tgn:7003685",
        "tgn:7000084",
        "tgn:7029392"
    ],
    "tgn:id":7123424,
    "tgn:name":"Neuspremberg",
    "tgn:placetype":[
        "aat:300008347"
    ]
},
  "bbox": [],
  "geometry": {"coordinates":[14.533333,51.033333],"type":"Point"}
}