{
  "id": 1089820,
  "type": "Feature",
  "properties": {
    "tgn:hierarchy":[
        "tgn:1089820",
        "tgn:7001242",
        "tgn:1001260",
        "tgn:7000489",
        "tgn:7029392"
    ],
    "tgn:id":1089820,
    "tgn:name":"G\u012bdol\u0113",
    "tgn:placetype":[
        "aat:300008347"
    ]
},
  "bbox": [],
  "geometry": {"coordinates":[37.4667,5.6333],"type":"Point"}
}