{
  "id": 2163557,
  "type": "Feature",
  "properties": {
    "tgn:hierarchy":[
        "tgn:2163557",
        "tgn:7013349",
        "tgn:1000001",
        "tgn:7012149",
        "tgn:7007708",
        "tgn:7029392"
    ],
    "tgn:id":2163557,
    "tgn:name":"Benson Spring",
    "tgn:placetype":[
        "aat:300008697"
    ]
},
  "bbox": [],
  "geometry": {"coordinates":[-117.2667,44.45],"type":"Point"}
}