{
  "id": 2184728,
  "type": "Feature",
  "properties": {
    "tgn:hierarchy":[
        "tgn:2184728",
        "tgn:1000001",
        "tgn:7012149",
        "tgn:2002347",
        "tgn:7007922",
        "tgn:7029392"
    ],
    "tgn:id":2184728,
    "tgn:name":"Boelter Lake",
    "tgn:placetype":[
        "aat:300008680"
    ]
},
  "bbox": [],
  "geometry": {"coordinates":[-89.3333,44.3333],"type":"Point"}
}