{
  "id": 7293323,
  "type": "Feature",
  "properties": {
    "tgn:hierarchy":[
        "tgn:7293323",
        "tgn:7002827",
        "tgn:1000003",
        "tgn:7002789",
        "tgn:1000095",
        "tgn:7029392"
    ],
    "tgn:id":7293323,
    "tgn:name":"Viniegra de Abajo",
    "tgn:placetype":[
        "aat:300008347"
    ]
},
  "bbox": [],
  "geometry": {"coordinates":[-2.883333,42.15],"type":"Point"}
}