{
  "id": 2039207,
  "type": "Feature",
  "properties": {
    "tgn:hierarchy":[
        "tgn:2039207",
        "tgn:1000001",
        "tgn:7012149",
        "tgn:2000786",
        "tgn:7007255",
        "tgn:7029392"
    ],
    "tgn:id":2039207,
    "tgn:name":"Habit",
    "tgn:placetype":[
        "aat:300008347"
    ]
},
  "bbox": [],
  "geometry": {"coordinates":[-86.9833,37.6833],"type":"Point"}
}