{
  "id": 2551228,
  "type": "Feature",
  "properties": {
    "tgn:hierarchy":[
        "tgn:2551228",
        "tgn:1000001",
        "tgn:7012149",
        "tgn:2001451",
        "tgn:7007566",
        "tgn:7029392"
    ],
    "tgn:id":2551228,
    "tgn:name":"Nuestra Se\u00f1ora, Cerro de",
    "tgn:placetype":[
        "aat:300008798"
    ]
},
  "bbox": [],
  "geometry": {"coordinates":[-107.1667,35.3833],"type":"Point"}
}