<<<<<<< HEAD
{
  "id": 2159168,
  "type": "Feature",
  "properties": {
    "tgn:hierarchy":[
        "tgn:2159168",
        "tgn:1000001",
        "tgn:7012149",
        "tgn:2001273",
        "tgn:7007524",
        "tgn:7029392"
    ],
    "tgn:id":2159168,
    "tgn:name":"Bedrock Canyon",
    "tgn:placetype":[
        "aat:300008761"
    ]
},
  "bbox": [],
  "geometry": {"coordinates":[-109.4833,47.3],"type":"Point"}
}
=======
{"geometry":{"type":"Point","coordinates":[-109.483300,47.300000]},"type":"Feature","properties":{"hierarchy":["tgn:2159168","tgn:1000001","tgn:7012149","tgn:2001273","tgn:7007524","tgn:7029392"],"placetype":["aat:300008761"],"id":2159168,"name:xx":"Bedrock Canyon"}}
>>>>>>> 03f74aca74312dbeaf24d7e61306dd6a786dc3d0
