{
  "id": 7150214,
  "type": "Feature",
  "properties": {
    "tgn:hierarchy":[
        "tgn:7150214",
        "tgn:1000003",
        "tgn:7003676",
        "tgn:7000084",
        "tgn:7029392"
    ],
    "tgn:id":7150214,
    "tgn:name":"K\u00fchle",
    "tgn:placetype":[
        "aat:300008777"
    ]
},
  "bbox": [],
  "geometry": {"coordinates":[10.383333,51.616667],"type":"Point"}
}