{
  "id": 2472014,
  "type": "Feature",
  "properties": {
    "tgn:hierarchy":[
        "tgn:2472014",
        "tgn:7002659",
        "tgn:1000001",
        "tgn:7012149",
        "tgn:2000038",
        "tgn:7029392"
    ],
    "tgn:id":2472014,
    "tgn:name":"Lot Hollow",
    "tgn:placetype":[
        "aat:300008761"
    ]
},
  "bbox": [],
  "geometry": {"coordinates":[-87.9833,34.95],"type":"Point"}
}