<<<<<<< HEAD
{
  "id": 7374886,
  "type": "Feature",
  "properties": {
    "tgn:hierarchy":[
        "tgn:7374886",
        "tgn:1001853",
        "tgn:1000001",
        "tgn:7005560",
        "tgn:7029392"
    ],
    "tgn:id":7374886,
    "tgn:name":"Rancho La Herradura",
    "tgn:placetype":[
        "aat:300000241"
    ]
},
  "bbox": [],
  "geometry": {"coordinates":[-101.6,25.0],"type":"Point"}
}
=======
{"geometry":{"type":"Point","coordinates":[-101.600000,25.000000]},"type":"Feature","properties":{"hierarchy":["tgn:7374886","tgn:1001853","tgn:1000001","tgn:7005560","tgn:7029392"],"placetype":["aat:300000241"],"id":7374886,"name:xx":"Rancho La Herradura"}}
>>>>>>> 03f74aca74312dbeaf24d7e61306dd6a786dc3d0
