{
  "id": 2451439,
  "type": "Feature",
  "properties": {
    "tgn:hierarchy":[
        "tgn:2451439",
        "tgn:1000001",
        "tgn:7012149",
        "tgn:2000206",
        "tgn:7007158",
        "tgn:7029392"
    ],
    "tgn:id":2451439,
    "tgn:name":"Little Battlement Reservoir",
    "tgn:placetype":[
        "aat:300006191"
    ]
},
  "bbox": [],
  "geometry": {"coordinates":[-108.05,38.9833],"type":"Point"}
}