<<<<<<< HEAD
{
  "id": 7020309,
  "type": "Feature",
  "properties": {
    "tgn:hierarchy":[
        "tgn:7020309",
        "tgn:1000001",
        "tgn:7012149",
        "tgn:2000827",
        "tgn:7007255",
        "tgn:7029392"
    ],
    "tgn:id":7020309,
    "tgn:name":"Shawnee Springs",
    "tgn:placetype":[
        "aat:300008697"
    ]
},
  "bbox": [],
  "geometry": {"coordinates":[-84.8,37.8],"type":"Point"}
}
=======
{"geometry":{"type":"Point","coordinates":[-84.800000,37.800000]},"type":"Feature","properties":{"hierarchy":["tgn:7020309","tgn:1000001","tgn:7012149","tgn:2000827","tgn:7007255","tgn:7029392"],"placetype":["aat:300008697"],"id":7020309,"name:xx":"Shawnee Springs"}}
>>>>>>> 03f74aca74312dbeaf24d7e61306dd6a786dc3d0
