{
  "id": 7146217,
  "type": "Feature",
  "properties": {
    "tgn:hierarchy":[
        "tgn:7146217",
        "tgn:1000003",
        "tgn:7003688",
        "tgn:7000084",
        "tgn:7029392"
    ],
    "tgn:id":7146217,
    "tgn:name":"Kluvensieker Holz",
    "tgn:placetype":[
        "aat:300008863"
    ]
},
  "bbox": [],
  "geometry": {"coordinates":[9.85,54.366667],"type":"Point"}
}