<<<<<<< HEAD
{
  "id": 2255122,
  "type": "Feature",
  "properties": {
    "tgn:hierarchy":[
        "tgn:2255122",
        "tgn:1000001",
        "tgn:7012149",
        "tgn:2000436",
        "tgn:7007248",
        "tgn:7029392"
    ],
    "tgn:id":2255122,
    "tgn:name":"Cooper Hill East Lake",
    "tgn:placetype":[
        "aat:300006191"
    ]
},
  "bbox": [],
  "geometry": {"coordinates":[-84.3167,32.85],"type":"Point"}
}
=======
{"geometry":{"type":"Point","coordinates":[-84.316700,32.850000]},"type":"Feature","properties":{"hierarchy":["tgn:2255122","tgn:1000001","tgn:7012149","tgn:2000436","tgn:7007248","tgn:7029392"],"placetype":["aat:300006191"],"id":2255122,"name:xx":"Cooper Hill East Lake"}}
>>>>>>> 03f74aca74312dbeaf24d7e61306dd6a786dc3d0
