<<<<<<< HEAD
{
  "id": 7352772,
  "type": "Feature",
  "properties": {
    "tgn:hierarchy":[
        "tgn:7352772",
        "tgn:1000001",
        "tgn:7005596",
        "tgn:7005560",
        "tgn:7029392"
    ],
    "tgn:id":7352772,
    "tgn:name":"Buenavista",
    "tgn:placetype":[
        "aat:300008347"
    ]
},
  "bbox": [],
  "geometry": {"coordinates":[-91.45,18.0],"type":"Point"}
}
=======
{"geometry":{"type":"Point","coordinates":[-91.450000,18.000000]},"type":"Feature","properties":{"hierarchy":["tgn:7352772","tgn:1000001","tgn:7005596","tgn:7005560","tgn:7029392"],"placetype":["aat:300008347"],"id":7352772,"name:xx":"Buenavista"}}
>>>>>>> 03f74aca74312dbeaf24d7e61306dd6a786dc3d0
