{
  "id": 7286195,
  "type": "Feature",
  "properties": {
    "tgn:hierarchy":[
        "tgn:7286195",
        "tgn:1001768",
        "tgn:1000049",
        "tgn:1000002",
        "tgn:7029392"
    ],
    "tgn:id":7286195,
    "tgn:name":"Horqueta, Cerro",
    "tgn:placetype":[
        "aat:300008795"
    ]
},
  "bbox": [],
  "geometry": {"coordinates":[-71.166667,-32.583333],"type":"Point"}
}