{
  "id": 1031343,
  "type": "Feature",
  "properties": {
    "tgn:hierarchy":[
        "tgn:1031343",
        "tgn:7024077",
        "tgn:1000003",
        "tgn:1000069",
        "tgn:7029392"
    ],
    "tgn:id":1031343,
    "tgn:name":"Kankaanp\u00e4\u00e4",
    "tgn:placetype":[
        "aat:300008347"
    ]
},
  "bbox": [],
  "geometry": {"coordinates":[22.4167,61.7833],"type":"Point"}
}