{
  "id": 7160185,
  "type": "Feature",
  "properties": {
    "tgn:hierarchy":[
        "tgn:7160185",
        "tgn:1000003",
        "tgn:7003682",
        "tgn:7000084",
        "tgn:7029392"
    ],
    "tgn:id":7160185,
    "tgn:name":"H\u00f6lz-Berg",
    "tgn:placetype":[
        "aat:300008777"
    ]
},
  "bbox": [],
  "geometry": {"coordinates":[7.733333,50.466667],"type":"Point"}
}