{
  "id": 2718256,
  "type": "Feature",
  "properties": {
    "tgn:hierarchy":[
        "tgn:2718256",
        "tgn:1000001",
        "tgn:7012149",
        "tgn:2001928",
        "tgn:7007825",
        "tgn:7029392"
    ],
    "tgn:id":2718256,
    "tgn:name":"Thompson Creek Branch",
    "tgn:placetype":[
        "aat:300008706"
    ]
},
  "bbox": [],
  "geometry": {"coordinates":[-88.5667,36.3333],"type":"Point"}
}