{
  "id": 2699418,
  "type": "Feature",
  "properties": {
    "tgn:hierarchy":[
        "tgn:2699418",
        "tgn:7006450",
        "tgn:1000001",
        "tgn:2124089",
        "tgn:7012149",
        "tgn:7029392"
    ],
    "tgn:id":2699418,
    "tgn:name":"Stroller White Mountain",
    "tgn:placetype":[
        "aat:300008798"
    ]
},
  "bbox": [],
  "geometry": {"coordinates":[-134.5667,58.4667],"type":"Point"}
}