{
  "id": 7312878,
  "type": "Feature",
  "properties": {
    "tgn:hierarchy":[
        "tgn:7312878",
        "tgn:1001699",
        "tgn:1000049",
        "tgn:1000002",
        "tgn:7029392"
    ],
    "tgn:id":7312878,
    "tgn:name":"Lamedi, Estero",
    "tgn:placetype":[
        "aat:300008699"
    ]
},
  "bbox": [],
  "geometry": {"coordinates":[-73.366667,-41.366667],"type":"Point"}
}