{
  "id": 7593384,
  "type": "Feature",
  "properties": {
    "tgn:hierarchy":[
        "tgn:7593384",
        "tgn:7005393",
        "tgn:1000001",
        "tgn:7005388",
        "tgn:7029392"
    ],
    "tgn:id":7593384,
    "tgn:name":"Partido",
    "tgn:placetype":[
        "aat:300008347"
    ]
},
  "bbox": [],
  "geometry": {"coordinates":[-70.391,19.384],"type":"Point"}
}