<<<<<<< HEAD
{
  "id": 2769017,
  "type": "Feature",
  "properties": {
    "tgn:hierarchy":[
        "tgn:2769017",
        "tgn:1000001",
        "tgn:7012149",
        "tgn:2001526",
        "tgn:7007709",
        "tgn:7029392"
    ],
    "tgn:id":2769017,
    "tgn:name":"Whittaker Point",
    "tgn:placetype":[
        "aat:300008850"
    ]
},
  "bbox": [],
  "geometry": {"coordinates":[-76.6667,35.0167],"type":"Point"}
}
=======
{"geometry":{"type":"Point","coordinates":[-76.666700,35.016700]},"type":"Feature","properties":{"hierarchy":["tgn:2769017","tgn:1000001","tgn:7012149","tgn:2001526","tgn:7007709","tgn:7029392"],"placetype":["aat:300008850"],"id":2769017,"name:xx":"Whittaker Point"}}
>>>>>>> 03f74aca74312dbeaf24d7e61306dd6a786dc3d0
