{
  "id": 2769017,
  "type": "Feature",
  "properties": {
    "tgn:hierarchy":[
        "tgn:2769017",
        "tgn:1000001",
        "tgn:7012149",
        "tgn:2001526",
        "tgn:7007709",
        "tgn:7029392"
    ],
    "tgn:id":2769017,
    "tgn:name":"Whittaker Point",
    "tgn:placetype":[
        "aat:300008850"
    ]
},
  "bbox": [],
  "geometry": {"coordinates":[-76.6667,35.0167],"type":"Point"}
}