{
  "id": 1065585,
  "type": "Feature",
  "properties": {
    "tgn:hierarchy":[
        "tgn:1065585",
        "tgn:7000188",
        "tgn:1000004",
        "tgn:1000105",
        "tgn:7029392"
    ],
    "tgn:id":1065585,
    "tgn:name":"B\u0101khr\u0101b\u0101d",
    "tgn:placetype":[
        "aat:300008347"
    ]
},
  "bbox": [],
  "geometry": {"coordinates":[90.8833,23.7167],"type":"Point"}
}