{
  "id": 1072652,
  "type": "Feature",
  "properties": {
    "tgn:hierarchy":[
        "tgn:1072652",
        "tgn:1000004",
        "tgn:7002087",
        "tgn:1000111",
        "tgn:7029392"
    ],
    "tgn:id":1072652,
    "tgn:name":"Wulaxi",
    "tgn:placetype":[
        "aat:300008347"
    ]
},
  "bbox": [],
  "geometry": {"coordinates":[101.6667,28.6333],"type":"Point"}
}