{
  "id": 2063206,
  "type": "Feature",
  "properties": {
    "tgn:hierarchy":[
        "tgn:2063206",
        "tgn:1000001",
        "tgn:1002614",
        "tgn:7012149",
        "tgn:7007526",
        "tgn:7029392"
    ],
    "tgn:id":2063206,
    "tgn:name":"Yerington",
    "tgn:placetype":[
        "aat:300008347"
    ]
},
  "bbox": [],
  "geometry": {"coordinates":[-119.15,38.9833],"type":"Point"}
}