{
  "id": 7373525,
  "type": "Feature",
  "properties": {
    "tgn:hierarchy":[
        "tgn:7373525",
        "tgn:7005586",
        "tgn:1000001",
        "tgn:7005560",
        "tgn:7029392"
    ],
    "tgn:id":7373525,
    "tgn:name":"Lalo, Sierra",
    "tgn:placetype":[
        "aat:300008795"
    ]
},
  "bbox": [],
  "geometry": {"coordinates":[-103.183333,19.25],"type":"Point"}
}