{
  "id": 2556734,
  "type": "Feature",
  "properties": {
    "tgn:hierarchy":[
        "tgn:2556734",
        "tgn:1000001",
        "tgn:7012149",
        "tgn:2001200",
        "tgn:7007523",
        "tgn:7029392"
    ],
    "tgn:id":2556734,
    "tgn:name":"Old Channel Thompson River",
    "tgn:placetype":[
        "aat:300008707"
    ]
},
  "bbox": [],
  "geometry": {"coordinates":[-93.7167,40.1833],"type":"Point"}
}