{
  "id": 2490507,
  "type": "Feature",
  "properties": {
    "tgn:hierarchy":[
        "tgn:2490507",
        "tgn:1000001",
        "tgn:7012149",
        "tgn:7014097",
        "tgn:7007158",
        "tgn:7029392"
    ],
    "tgn:id":2490507,
    "tgn:name":"Manitou, Mount",
    "tgn:placetype":[
        "aat:300008798"
    ]
},
  "bbox": [],
  "geometry": {"coordinates":[-104.95,38.85],"type":"Point"}
}