{
  "id": 2775648,
  "type": "Feature",
  "properties": {
    "tgn:hierarchy":[
        "tgn:2775648",
        "tgn:1000001",
        "tgn:7012149",
        "tgn:1002617",
        "tgn:7007520",
        "tgn:7029392"
    ],
    "tgn:id":2775648,
    "tgn:name":"Wilson Drain",
    "tgn:placetype":[
        "aat:300008699"
    ]
},
  "bbox": [],
  "geometry": {"coordinates":[-83.0167,42.8333],"type":"Point"}
}