{
  "id": 1011945,
  "type": "Feature",
  "properties": {
    "tgn:hierarchy":[
        "tgn:1011945",
        "tgn:7002444",
        "tgn:1000003",
        "tgn:7008082",
        "tgn:7008591",
        "tgn:7029392"
    ],
    "tgn:id":1011945,
    "tgn:name:en":"Greenstone Point",
    "tgn:placetype":[
        "aat:300386846"
    ]
},
  "bbox": [],
  "geometry": {"coordinates":[-5.633333,57.916667],"type":"Point"}
}