{
  "id": 7426669,
  "type": "Feature",
  "properties": {
    "tgn:hierarchy":[
        "tgn:7426669",
        "tgn:7005581",
        "tgn:1000001",
        "tgn:7005560",
        "tgn:7029392"
    ],
    "tgn:id":7426669,
    "tgn:name":"El Cuatro",
    "tgn:placetype":[
        "aat:300008347"
    ]
},
  "bbox": [],
  "geometry": {"coordinates":[-105.033333,28.65],"type":"Point"}
}