{
  "id": 2539302,
  "type": "Feature",
  "properties": {
    "tgn:hierarchy":[
        "tgn:2539302",
        "tgn:7002659",
        "tgn:1000001",
        "tgn:7012149",
        "tgn:2000055",
        "tgn:7029392"
    ],
    "tgn:id":2539302,
    "tgn:name":"New Hope Lake",
    "tgn:placetype":[
        "aat:300006191"
    ]
},
  "bbox": [],
  "geometry": {"coordinates":[-85.4167,33.3167],"type":"Point"}
}