{
  "id": 7557462,
  "type": "Feature",
  "properties": {
    "tgn:hierarchy":[
        "tgn:7557462",
        "tgn:7001819",
        "tgn:1000004",
        "tgn:7000198",
        "tgn:7029392"
    ],
    "tgn:id":7557462,
    "tgn:name:en":"Ramsing",
    "tgn:placetype":[
        "aat:300008347"
    ]
},
  "bbox": [],
  "geometry": {"coordinates":[94.980951,28.653863],"type":"Point"}
}