{
  "id": 7180085,
  "type": "Feature",
  "properties": {
    "tgn:hierarchy":[
        "tgn:7180085",
        "tgn:7003669",
        "tgn:1000003",
        "tgn:7000084",
        "tgn:7029392"
    ],
    "tgn:id":7180085,
    "tgn:name":"Geberskirchen",
    "tgn:placetype":[
        "aat:300008347"
    ]
},
  "bbox": [],
  "geometry": {"coordinates":[11.966667,48.583333],"type":"Point"}
}