{
  "id": 7293738,
  "type": "Feature",
  "properties": {
    "tgn:hierarchy":[
        "tgn:7293738",
        "tgn:7002831",
        "tgn:1000003",
        "tgn:7002786",
        "tgn:1000095",
        "tgn:7029392"
    ],
    "tgn:id":7293738,
    "tgn:name":"Vilela",
    "tgn:placetype":[
        "aat:300008347"
    ]
},
  "bbox": [],
  "geometry": {"coordinates":[-7.616667,41.966667],"type":"Point"}
}