{
  "id": 2073539,
  "type": "Feature",
  "properties": {
    "tgn:hierarchy":[
        "tgn:2073539",
        "tgn:1000001",
        "tgn:7012149",
        "tgn:2001486",
        "tgn:7007709",
        "tgn:7029392"
    ],
    "tgn:id":2073539,
    "tgn:name":"Askin",
    "tgn:placetype":[
        "aat:300008347"
    ]
},
  "bbox": [],
  "geometry": {"coordinates":[-77.0667,35.2167],"type":"Point"}
}