{
  "id": 1125028,
  "type": "Feature",
  "properties": {
    "tgn:hierarchy":[
        "tgn:1125028",
        "tgn:7006247",
        "tgn:1000047",
        "tgn:7002456",
        "tgn:1000002",
        "tgn:7029392"
    ],
    "tgn:id":1125028,
    "tgn:name":"Itat\u00e1",
    "tgn:placetype":[
        "aat:300008707"
    ]
},
  "bbox": [],
  "geometry": {"coordinates":[-51.95,-3.4667],"type":"Point"}
}