{
  "id": 7235294,
  "type": "Feature",
  "properties": {
    "tgn:hierarchy":[
        "tgn:7235294",
        "tgn:7002715",
        "tgn:7002729",
        "tgn:1000003",
        "tgn:1000074",
        "tgn:7029392"
    ],
    "tgn:id":7235294,
    "tgn:name":"Fl\u00e1mbouron",
    "tgn:placetype":[
        "aat:300008347"
    ]
},
  "bbox": [],
  "geometry": {"coordinates":[22.25,39.966667],"type":"Point"}
}