{
  "id": 7218963,
  "type": "Feature",
  "properties": {
    "tgn:hierarchy":[
        "tgn:7218963",
        "tgn:1042193",
        "tgn:7002705",
        "tgn:1000003",
        "tgn:1000074",
        "tgn:7029392"
    ],
    "tgn:id":7218963,
    "tgn:name":"Vouvop\u00f3tamos",
    "tgn:placetype":[
        "aat:300008699"
    ]
},
  "bbox": [],
  "geometry": {"coordinates":[20.535556,39.231944],"type":"Point"}
}