{
  "id": 2081597,
  "type": "Feature",
  "properties": {
    "tgn:hierarchy":[
        "tgn:2081597",
        "tgn:1002156",
        "tgn:1000001",
        "tgn:7012149",
        "tgn:7007706",
        "tgn:7029392"
    ],
    "tgn:id":2081597,
    "tgn:name":"Richmond Center",
    "tgn:placetype":[
        "aat:300008347"
    ]
},
  "bbox": [],
  "geometry": {"coordinates":[-80.5667,41.6667],"type":"Point"}
}