{
  "id": 2204331,
  "type": "Feature",
  "properties": {
    "tgn:hierarchy":[
        "tgn:2204331",
        "tgn:1000001",
        "tgn:7012149",
        "tgn:1002999",
        "tgn:7007526",
        "tgn:7029392"
    ],
    "tgn:id":2204331,
    "tgn:name":"Buffalo Canyon",
    "tgn:placetype":[
        "aat:300008761"
    ]
},
  "bbox": [],
  "geometry": {"coordinates":[-119.8167,40.8333],"type":"Point"}
}