<<<<<<< HEAD
{
  "id": 2402708,
  "type": "Feature",
  "properties": {
    "tgn:hierarchy":[
        "tgn:2402708",
        "tgn:1000001",
        "tgn:2001411",
        "tgn:7012149",
        "tgn:7007526",
        "tgn:7029392"
    ],
    "tgn:id":2402708,
    "tgn:name":"Hot Spring Creek",
    "tgn:placetype":[
        "aat:300008706"
    ]
},
  "bbox": [],
  "geometry": {"coordinates":[-115.95,41.1333],"type":"Point"}
}
=======
{"geometry":{"type":"Point","coordinates":[-115.950000,41.133300]},"type":"Feature","properties":{"hierarchy":["tgn:2402708","tgn:1000001","tgn:2001411","tgn:7012149","tgn:7007526","tgn:7029392"],"placetype":["aat:300008706"],"id":2402708,"name:xx":"Hot Spring Creek"}}
>>>>>>> 03f74aca74312dbeaf24d7e61306dd6a786dc3d0
