{
  "id": 1134225,
  "type": "Feature",
  "properties": {
    "tgn:hierarchy":[
        "tgn:1134225",
        "tgn:7006237",
        "tgn:1000047",
        "tgn:7002457",
        "tgn:1000002",
        "tgn:7029392"
    ],
    "tgn:id":1134225,
    "tgn:name":"Pitangueiras, Ribeir\u00e3o das",
    "tgn:placetype":[
        "aat:300008706"
    ]
},
  "bbox": [],
  "geometry": {"coordinates":[-44.45,-21.45],"type":"Point"}
}