{
  "id": 7257486,
  "type": "Feature",
  "properties": {
    "tgn:hierarchy":[
        "tgn:7257486",
        "tgn:7003458",
        "tgn:1000003",
        "tgn:1000063",
        "tgn:7018236",
        "tgn:7029392"
    ],
    "tgn:id":7257486,
    "tgn:name":"Wittepoort",
    "tgn:placetype":[
        "aat:300000206"
    ]
},
  "bbox": [],
  "geometry": {"coordinates":[2.933333,50.85],"type":"Point"}
}