<<<<<<< HEAD
{
  "id": 2765844,
  "type": "Feature",
  "properties": {
    "tgn:hierarchy":[
        "tgn:2765844",
        "tgn:7006450",
        "tgn:1000001",
        "tgn:7012149",
        "tgn:2000089",
        "tgn:7029392"
    ],
    "tgn:id":2765844,
    "tgn:name":"White Fish Lake",
    "tgn:placetype":[
        "aat:300008680"
    ]
},
  "bbox": [],
  "geometry": {"coordinates":[-158.0333,64.4667],"type":"Point"}
}
=======
{"geometry":{"type":"Point","coordinates":[-158.033300,64.466700]},"type":"Feature","properties":{"hierarchy":["tgn:2765844","tgn:7006450","tgn:1000001","tgn:7012149","tgn:2000089","tgn:7029392"],"placetype":["aat:300008680"],"id":2765844,"name:xx":"White Fish Lake"}}
>>>>>>> 03f74aca74312dbeaf24d7e61306dd6a786dc3d0
