{
  "id": 2191208,
  "type": "Feature",
  "properties": {
    "tgn:hierarchy":[
        "tgn:2191208",
        "tgn:1000001",
        "tgn:2002136",
        "tgn:7012149",
        "tgn:7007828",
        "tgn:7029392"
    ],
    "tgn:id":2191208,
    "tgn:name":"Boynton Hollow",
    "tgn:placetype":[
        "aat:300008761"
    ]
},
  "bbox": [],
  "geometry": {"coordinates":[-72.75,43.3167],"type":"Point"}
}