<<<<<<< HEAD
{
  "id": 7487605,
  "type": "Feature",
  "properties": {
    "tgn:hierarchy":[
        "tgn:7487605",
        "tgn:1000004",
        "tgn:7490934",
        "tgn:1000141",
        "tgn:7029392"
    ],
    "tgn:id":7487605,
    "tgn:name":"Liujia Xiang",
    "tgn:placetype":[
        "aat:300387173"
    ]
},
  "bbox": [],
  "geometry": {"coordinates":[120.366667,23.216667],"type":"Point"}
}
=======
{"geometry":{"type":"Point","coordinates":[120.366667,23.216667]},"type":"Feature","properties":{"hierarchy":["tgn:7487605","tgn:1000004","tgn:7490934","tgn:1000141","tgn:7029392"],"placetype":["aat:300387173"],"id":7487605,"name:xx":"Liujia Xiang"}}
>>>>>>> 03f74aca74312dbeaf24d7e61306dd6a786dc3d0
