{
  "id": 7095761,
  "type": "Feature",
  "properties": {
    "tgn:hierarchy":[
        "tgn:7095761",
        "tgn:7003669",
        "tgn:1000003",
        "tgn:7000084",
        "tgn:7029392"
    ],
    "tgn:id":7095761,
    "tgn:name":"Spiegelau mit Schwarzach",
    "tgn:placetype":[
        "aat:300008347"
    ]
},
  "bbox": [],
  "geometry": {"coordinates":[13.366667,48.916667],"type":"Point"}
}