{
  "id": 1099587,
  "type": "Feature",
  "properties": {
    "tgn:hierarchy":[
        "tgn:1099587",
        "tgn:1000826",
        "tgn:7006160",
        "tgn:1000006",
        "tgn:7029392"
    ],
    "tgn:id":1099587,
    "tgn:name":"Tapini",
    "tgn:placetype":[
        "aat:300008347"
    ]
},
  "bbox": [],
  "geometry": {"coordinates":[146.9167,-8.2667],"type":"Point"}
}