{
  "id": 2781565,
  "type": "Feature",
  "properties": {
    "tgn:hierarchy":[
        "tgn:2781565",
        "tgn:1000001",
        "tgn:2000201",
        "tgn:7012149",
        "tgn:7007158",
        "tgn:7029392"
    ],
    "tgn:id":2781565,
    "tgn:name":"Woodpecker Gulch",
    "tgn:placetype":[
        "aat:300008761"
    ]
},
  "bbox": [],
  "geometry": {"coordinates":[-105.5667,39.7833],"type":"Point"}
}