{
  "id": 7313773,
  "type": "Feature",
  "properties": {
    "tgn:hierarchy":[
        "tgn:7313773",
        "tgn:1001705",
        "tgn:1000049",
        "tgn:1000002",
        "tgn:7029392"
    ],
    "tgn:id":7313773,
    "tgn:name":"Los Arrayanes, Cerro",
    "tgn:placetype":[
        "aat:300008777"
    ]
},
  "bbox": [],
  "geometry": {"coordinates":[-71.533333,-35.233333],"type":"Point"}
}