{
  "id": 2274611,
  "type": "Feature",
  "properties": {
    "tgn:hierarchy":[
        "tgn:2274611",
        "tgn:1002300",
        "tgn:1000001",
        "tgn:7012149",
        "tgn:7007564",
        "tgn:7029392"
    ],
    "tgn:id":2274611,
    "tgn:name":"Dalton Mountain",
    "tgn:placetype":[
        "aat:300008798"
    ]
},
  "bbox": [],
  "geometry": {"coordinates":[-71.6667,44.3667],"type":"Point"}
}