<<<<<<< HEAD
{
  "id": 7020803,
  "type": "Feature",
  "properties": {
    "tgn:hierarchy":[
        "tgn:7020803",
        "tgn:1000001",
        "tgn:7012149",
        "tgn:7029392"
    ],
    "tgn:id":7020803,
    "tgn:name":"Goodman Swamp",
    "tgn:placetype":[
        "aat:300008905",
        "aat:300008699"
    ]
},
  "bbox": [],
  "geometry": {"coordinates":[-76.65,36.55],"type":"Point"}
}
=======
{"geometry":{"type":"Point","coordinates":[-76.650000,36.550000]},"type":"Feature","properties":{"hierarchy":["tgn:7020803","tgn:1000001","tgn:7012149","tgn:7029392"],"placetype":["aat:300008905","aat:300008699"],"id":7020803,"name:xx":"Goodman Swamp"}}
>>>>>>> 03f74aca74312dbeaf24d7e61306dd6a786dc3d0
