{
  "id": 7044952,
  "type": "Feature",
  "properties": {
    "tgn:hierarchy":[
        "tgn:7044952",
        "tgn:7003168",
        "tgn:1000003",
        "tgn:7009760",
        "tgn:1000080",
        "tgn:7029392"
    ],
    "tgn:id":7044952,
    "tgn:name":"Fosini",
    "tgn:placetype":[
        "aat:300008347"
    ]
},
  "bbox": [],
  "geometry": {"coordinates":[10.933333,43.166667],"type":"Point"}
}