{
  "id": 2681467,
  "type": "Feature",
  "properties": {
    "tgn:hierarchy":[
        "tgn:2681467",
        "tgn:1000001",
        "tgn:2002134",
        "tgn:7012149",
        "tgn:7007828",
        "tgn:7029392"
    ],
    "tgn:id":2681467,
    "tgn:name":"South Pond",
    "tgn:placetype":[
        "aat:300008680"
    ]
},
  "bbox": [],
  "geometry": {"coordinates":[-72.6167,44.0333],"type":"Point"}
}