{
  "id": 7125489,
  "type": "Feature",
  "properties": {
    "tgn:hierarchy":[
        "tgn:7125489",
        "tgn:1000003",
        "tgn:7000094",
        "tgn:7000084",
        "tgn:7029392"
    ],
    "tgn:id":7125489,
    "tgn:name":"Nevern",
    "tgn:placetype":[
        "aat:300008347"
    ]
},
  "bbox": [],
  "geometry": {"coordinates":[11.666667,53.883333],"type":"Point"}
}