{
  "id": 1082347,
  "type": "Feature",
  "properties": {
    "tgn:hierarchy":[
        "tgn:1082347",
        "tgn:1000004",
        "tgn:1001372",
        "tgn:7000299",
        "tgn:7029392"
    ],
    "tgn:id":1082347,
    "tgn:name":"S\u014fnsan",
    "tgn:placetype":[
        "aat:300008347"
    ]
},
  "bbox": [],
  "geometry": {"coordinates":[128.2833,36.2333],"type":"Point"}
}