{
  "id": 2115647,
  "type": "Feature",
  "properties": {
    "tgn:hierarchy":[
        "tgn:2115647",
        "tgn:1000001",
        "tgn:7012149",
        "tgn:1002505",
        "tgn:7007920",
        "tgn:7029392"
    ],
    "tgn:id":2115647,
    "tgn:name":"Driftwood Shores",
    "tgn:placetype":[
        "aat:300008347"
    ]
},
  "bbox": [],
  "geometry": {"coordinates":[-122.4667,48.1833],"type":"Point"}
}