<<<<<<< HEAD
{
  "id": 7055200,
  "type": "Feature",
  "properties": {
    "tgn:hierarchy":[
        "tgn:7055200",
        "tgn:1003506",
        "tgn:1000003",
        "tgn:7002993",
        "tgn:1000080",
        "tgn:7029392"
    ],
    "tgn:id":7055200,
    "tgn:name":"Oseacco",
    "tgn:placetype":[
        "aat:300008347"
    ]
},
  "bbox": [],
  "geometry": {"coordinates":[13.315,46.363611],"type":"Point"}
}
=======
{"geometry":{"type":"Point","coordinates":[13.315000,46.363611]},"type":"Feature","properties":{"hierarchy":["tgn:7055200","tgn:1003506","tgn:1000003","tgn:7002993","tgn:1000080","tgn:7029392"],"placetype":["aat:300008347"],"id":7055200,"name:xx":"Oseacco"}}
>>>>>>> 03f74aca74312dbeaf24d7e61306dd6a786dc3d0
