{
  "id": 7496403,
  "type": "Feature",
  "properties": {
    "tgn:hierarchy":[
        "tgn:7496403",
        "tgn:7001004",
        "tgn:1000004",
        "tgn:1000141",
        "tgn:7029392"
    ],
    "tgn:id":7496403,
    "tgn:name":"Nanlong Guozhong",
    "tgn:placetype":[
        "aat:300006495"
    ]
},
  "bbox": [],
  "geometry": {"coordinates":[120.535526,22.865648],"type":"Point"}
}