{
  "id": 7496263,
  "type": "Feature",
  "properties": {
    "tgn:hierarchy":[
        "tgn:7496263",
        "tgn:1000004",
        "tgn:7001013",
        "tgn:1000141",
        "tgn:7029392"
    ],
    "tgn:id":7496263,
    "tgn:name":"Shijia",
    "tgn:placetype":[
        "aat:300008347"
    ]
},
  "bbox": [],
  "geometry": {"coordinates":[121.29763,24.911883],"type":"Point"}
}