{
  "id": 2122712,
  "type": "Feature",
  "properties": {
    "tgn:hierarchy":[
        "tgn:2122712",
        "tgn:1000001",
        "tgn:7012149",
        "tgn:2002351",
        "tgn:7007922",
        "tgn:7029392"
    ],
    "tgn:id":2122712,
    "tgn:name":"Wilson",
    "tgn:placetype":[
        "aat:300008347"
    ]
},
  "bbox": [],
  "geometry": {"coordinates":[-92.1667,44.95],"type":"Point"}
}