{
  "id": 7232975,
  "type": "Feature",
  "properties": {
    "tgn:hierarchy":[
        "tgn:7232975",
        "tgn:1042193",
        "tgn:7002705",
        "tgn:1000003",
        "tgn:1000074",
        "tgn:7029392"
    ],
    "tgn:id":7232975,
    "tgn:name":"Lo\u00faros Potam\u00f3s",
    "tgn:placetype":[
        "aat:300008699"
    ]
},
  "bbox": [],
  "geometry": {"coordinates":[20.778611,39.046111],"type":"Point"}
}