{
  "id": 7502366,
  "type": "Feature",
  "properties": {
    "tgn:hierarchy":[
        "tgn:7502366",
        "tgn:1000004",
        "tgn:7001009",
        "tgn:1000141",
        "tgn:7029392"
    ],
    "tgn:id":7502366,
    "tgn:name":"Kaideng Suidao",
    "tgn:placetype":[
        "aat:300007899"
    ]
},
  "bbox": [],
  "geometry": {"coordinates":[120.961944,24.171111],"type":"Point"}
}