{
  "id": 2425857,
  "type": "Feature",
  "properties": {
    "tgn:hierarchy":[
        "tgn:2425857",
        "tgn:1000001",
        "tgn:7012149",
        "tgn:7007564",
        "tgn:7029392"
    ],
    "tgn:id":2425857,
    "tgn:name":"Jolly Island",
    "tgn:placetype":[
        "aat:300008791"
    ]
},
  "bbox": [],
  "geometry": {"coordinates":[-71.3667,43.6167],"type":"Point"}
}