{
  "id": 2532798,
  "type": "Feature",
  "properties": {
    "tgn:hierarchy":[
        "tgn:2532798",
        "tgn:1000001",
        "tgn:7012149",
        "tgn:1002506",
        "tgn:7007919",
        "tgn:7029392"
    ],
    "tgn:id":2532798,
    "tgn:name":"Murphys Millpond",
    "tgn:placetype":[
        "aat:300006191"
    ]
},
  "bbox": [],
  "geometry": {"coordinates":[-76.65,36.85],"type":"Point"}
}