{
  "id": 2015640,
  "type": "Feature",
  "properties": {
    "tgn:hierarchy":[
        "tgn:2015640",
        "tgn:1000001",
        "tgn:2000199",
        "tgn:7012149",
        "tgn:7007158",
        "tgn:7029392"
    ],
    "tgn:id":2015640,
    "tgn:name":"Garfield",
    "tgn:placetype":[
        "aat:300008347"
    ]
},
  "bbox": [],
  "geometry": {"coordinates":[-106.2833,38.55],"type":"Point"}
}