{
  "id": 7364538,
  "type": "Feature",
  "properties": {
    "tgn:hierarchy":[
        "tgn:7364538",
        "tgn:7005583",
        "tgn:1000001",
        "tgn:7005560",
        "tgn:7029392"
    ],
    "tgn:id":7364538,
    "tgn:name":"El Presidio",
    "tgn:placetype":[
        "aat:300008347"
    ]
},
  "bbox": [],
  "geometry": {"coordinates":[-106.143611,24.654722],"type":"Point"}
}