<<<<<<< HEAD
{
  "id": 7364538,
  "type": "Feature",
  "properties": {
    "tgn:hierarchy":[
        "tgn:7364538",
        "tgn:7005583",
        "tgn:1000001",
        "tgn:7005560",
        "tgn:7029392"
    ],
    "tgn:id":7364538,
    "tgn:name":"El Presidio",
    "tgn:placetype":[
        "aat:300008347"
    ]
},
  "bbox": [],
  "geometry": {"coordinates":[-106.143611,24.654722],"type":"Point"}
}
=======
{"geometry":{"type":"Point","coordinates":[-106.143611,24.654722]},"type":"Feature","properties":{"hierarchy":["tgn:7364538","tgn:7005583","tgn:1000001","tgn:7005560","tgn:7029392"],"placetype":["aat:300008347"],"id":7364538,"name:xx":"El Presidio"}}
>>>>>>> 03f74aca74312dbeaf24d7e61306dd6a786dc3d0
