<<<<<<< HEAD
{
  "id": 7479799,
  "type": "Feature",
  "properties": {
    "tgn:hierarchy":[
        "tgn:7479799",
        "tgn:1000004",
        "tgn:7490934",
        "tgn:1000141",
        "tgn:7029392"
    ],
    "tgn:id":7479799,
    "tgn:name":"Guangfu Guoxiao",
    "tgn:placetype":[
        "aat:300006495"
    ]
},
  "bbox": [],
  "geometry": {"coordinates":[120.106667,23.148611],"type":"Point"}
}
=======
{"geometry":{"type":"Point","coordinates":[120.106667,23.148611]},"type":"Feature","properties":{"hierarchy":["tgn:7479799","tgn:1000004","tgn:7490934","tgn:1000141","tgn:7029392"],"placetype":["aat:300006495"],"id":7479799,"name:xx":"Guangfu Guoxiao"}}
>>>>>>> 03f74aca74312dbeaf24d7e61306dd6a786dc3d0
