{
  "id": 7040440,
  "type": "Feature",
  "properties": {
    "tgn:hierarchy":[
        "tgn:7040440",
        "tgn:7002994",
        "tgn:1000003",
        "tgn:7002997",
        "tgn:1000080",
        "tgn:7029392"
    ],
    "tgn:id":7040440,
    "tgn:name":"Santa Margherita d'Adige",
    "tgn:placetype":[
        "aat:300008347"
    ]
},
  "bbox": [],
  "geometry": {"coordinates":[11.55,45.216667],"type":"Point"}
}