{
  "id": 2417305,
  "type": "Feature",
  "properties": {
    "tgn:hierarchy":[
        "tgn:2417305",
        "tgn:1000001",
        "tgn:1002235",
        "tgn:7012149",
        "tgn:7007919",
        "tgn:7029392"
    ],
    "tgn:id":2417305,
    "tgn:name":"Jacks Creek",
    "tgn:placetype":[
        "aat:300008706"
    ]
},
  "bbox": [],
  "geometry": {"coordinates":[-77.1833,37.9833],"type":"Point"}
}