{
  "id": 7411562,
  "type": "Feature",
  "properties": {
    "tgn:hierarchy":[
        "tgn:7411562",
        "tgn:7005587",
        "tgn:1000001",
        "tgn:7005560",
        "tgn:7029392"
    ],
    "tgn:id":7411562,
    "tgn:name:es":"Llanos de Apan, Laguna",
    "tgn:placetype":[
        "aat:300008680"
    ]
},
  "bbox": [],
  "geometry": {"coordinates":[-98.483333,19.730556],"type":"Point"}
}