{
  "id": 2387612,
  "type": "Feature",
  "properties": {
    "tgn:hierarchy":[
        "tgn:2387612",
        "tgn:1000001",
        "tgn:7012149",
        "tgn:2000996",
        "tgn:7007520",
        "tgn:7029392"
    ],
    "tgn:id":2387612,
    "tgn:name":"Hiawatha",
    "tgn:placetype":[
        "aat:300008347"
    ]
},
  "bbox": [],
  "geometry": {"coordinates":[-86.25,46.1167],"type":"Point"}
}