{
  "id": 7489778,
  "type": "Feature",
  "properties": {
    "tgn:hierarchy":[
        "tgn:7489778",
        "tgn:7001004",
        "tgn:1000004",
        "tgn:1000141",
        "tgn:7029392"
    ],
    "tgn:id":7489778,
    "tgn:name":"Shige",
    "tgn:placetype":[
        "aat:300008347"
    ]
},
  "bbox": [],
  "geometry": {"coordinates":[120.405833,22.773611],"type":"Point"}
}