{
  "id": 7588494,
  "type": "Feature",
  "properties": {
    "tgn:hierarchy":[
        "tgn:7588494",
        "tgn:1000004",
        "tgn:7000198",
        "tgn:7000799",
        "tgn:7029392"
    ],
    "tgn:id":7588494,
    "tgn:name:en":"Fak\u012br Dorax",
    "tgn:placetype":[
        "aat:300008347"
    ]
},
  "bbox": [],
  "geometry": {"coordinates":[74.021998,33.759082],"type":"Point"}
}