{
  "id": 2589858,
  "type": "Feature",
  "properties": {
    "tgn:hierarchy":[
        "tgn:2589858",
        "tgn:1000001",
        "tgn:2001418",
        "tgn:7012149",
        "tgn:7007526",
        "tgn:7029392"
    ],
    "tgn:id":2589858,
    "tgn:name":"Point of Rock Spring",
    "tgn:placetype":[
        "aat:300008697"
    ]
},
  "bbox": [],
  "geometry": {"coordinates":[-116.6667,38.2833],"type":"Point"}
}