{
  "id": 7276162,
  "type": "Feature",
  "properties": {
    "tgn:hierarchy":[
        "tgn:7276162",
        "tgn:1001702",
        "tgn:1000049",
        "tgn:1000002",
        "tgn:7029392"
    ],
    "tgn:id":7276162,
    "tgn:name":"Toro, Cerro",
    "tgn:placetype":[
        "aat:300008795"
    ]
},
  "bbox": [],
  "geometry": {"coordinates":[-74.683333,-52.266667],"type":"Point"}
}