{
  "id": 2119381,
  "type": "Feature",
  "properties": {
    "tgn:hierarchy":[
        "tgn:2119381",
        "tgn:1000001",
        "tgn:7012149",
        "tgn:2002277",
        "tgn:7013961",
        "tgn:7029392"
    ],
    "tgn:id":2119381,
    "tgn:name":"New Haven",
    "tgn:placetype":[
        "aat:300008347"
    ]
},
  "bbox": [],
  "geometry": {"coordinates":[-81.9667,38.9833],"type":"Point"}
}