{
  "id": 7276658,
  "type": "Feature",
  "properties": {
    "tgn:hierarchy":[
        "tgn:7276658",
        "tgn:7016598",
        "tgn:1000049",
        "tgn:1000002",
        "tgn:7029392"
    ],
    "tgn:id":7276658,
    "tgn:name":"Zanelli, Cerro",
    "tgn:placetype":[
        "aat:300008795"
    ]
},
  "bbox": [],
  "geometry": {"coordinates":[-69.55,-23.55],"type":"Point"}
}