{
  "id": 2491802,
  "type": "Feature",
  "properties": {
    "tgn:hierarchy":[
        "tgn:2491802",
        "tgn:1000001",
        "tgn:2002316",
        "tgn:7012149",
        "tgn:7007922",
        "tgn:7029392"
    ],
    "tgn:id":2491802,
    "tgn:name":"Marais Lake",
    "tgn:placetype":[
        "aat:300008680"
    ]
},
  "bbox": [],
  "geometry": {"coordinates":[-91.15,43.0667],"type":"Point"}
}