<<<<<<< HEAD
{
  "id": 2765572,
  "type": "Feature",
  "properties": {
    "tgn:hierarchy":[
        "tgn:2765572",
        "tgn:1000001",
        "tgn:7012149",
        "tgn:7007157",
        "tgn:1002956",
        "tgn:7029392"
    ],
    "tgn:id":2765572,
    "tgn:name":"White Chief Peak",
    "tgn:placetype":[
        "aat:300008798"
    ]
},
  "bbox": [],
  "geometry": {"coordinates":[-118.5833,36.4],"type":"Point"}
}
=======
{"geometry":{"type":"Point","coordinates":[-118.583300,36.400000]},"type":"Feature","properties":{"hierarchy":["tgn:2765572","tgn:1000001","tgn:7012149","tgn:7007157","tgn:1002956","tgn:7029392"],"placetype":["aat:300008798"],"id":2765572,"name:xx":"White Chief Peak"}}
>>>>>>> 03f74aca74312dbeaf24d7e61306dd6a786dc3d0
