<<<<<<< HEAD
{
  "id": 2400333,
  "type": "Feature",
  "properties": {
    "tgn:hierarchy":[
        "tgn:2400333",
        "tgn:1000001",
        "tgn:2001263",
        "tgn:7012149",
        "tgn:7007524",
        "tgn:7029392"
    ],
    "tgn:id":2400333,
    "tgn:name":"Horse Gulch",
    "tgn:placetype":[
        "aat:300008761"
    ]
},
  "bbox": [],
  "geometry": {"coordinates":[-111.45,46.6333],"type":"Point"}
}
=======
{"geometry":{"type":"Point","coordinates":[-111.450000,46.633300]},"type":"Feature","properties":{"hierarchy":["tgn:2400333","tgn:1000001","tgn:2001263","tgn:7012149","tgn:7007524","tgn:7029392"],"placetype":["aat:300008761"],"id":2400333,"name:xx":"Horse Gulch"}}
>>>>>>> 03f74aca74312dbeaf24d7e61306dd6a786dc3d0
