{
  "id": 2400333,
  "type": "Feature",
  "properties": {
    "tgn:hierarchy":[
        "tgn:2400333",
        "tgn:1000001",
        "tgn:2001263",
        "tgn:7012149",
        "tgn:7007524",
        "tgn:7029392"
    ],
    "tgn:id":2400333,
    "tgn:name":"Horse Gulch",
    "tgn:placetype":[
        "aat:300008761"
    ]
},
  "bbox": [],
  "geometry": {"coordinates":[-111.45,46.6333],"type":"Point"}
}