<<<<<<< HEAD
{
  "id": 2407643,
  "type": "Feature",
  "properties": {
    "tgn:hierarchy":[
        "tgn:2407643",
        "tgn:1002300",
        "tgn:1000001",
        "tgn:7012149",
        "tgn:7007564",
        "tgn:7029392"
    ],
    "tgn:id":2407643,
    "tgn:name":"Hurlbert Swamp",
    "tgn:placetype":[
        "aat:300008905"
    ]
},
  "bbox": [],
  "geometry": {"coordinates":[-71.4333,44.9833],"type":"Point"}
}
=======
{"geometry":{"type":"Point","coordinates":[-71.433300,44.983300]},"type":"Feature","properties":{"hierarchy":["tgn:2407643","tgn:1002300","tgn:1000001","tgn:7012149","tgn:7007564","tgn:7029392"],"placetype":["aat:300008905"],"id":2407643,"name:xx":"Hurlbert Swamp"}}
>>>>>>> 03f74aca74312dbeaf24d7e61306dd6a786dc3d0
