{
  "id": 2582321,
  "type": "Feature",
  "properties": {
    "tgn:hierarchy":[
        "tgn:2582321",
        "tgn:1000001",
        "tgn:7012149",
        "tgn:7007710",
        "tgn:7029392"
    ],
    "tgn:id":2582321,
    "tgn:name":"Pine Creek Gorge",
    "tgn:placetype":[
        "aat:300008761"
    ]
},
  "bbox": [],
  "geometry": {"coordinates":[-77.4167,41.7333],"type":"Point"}
}