{
  "id": 7556599,
  "type": "Feature",
  "properties": {
    "tgn:hierarchy":[
        "tgn:7556599",
        "tgn:1000004",
        "tgn:7000198",
        "tgn:7001797",
        "tgn:7029392"
    ],
    "tgn:id":7556599,
    "tgn:name:en":"Sekkadi",
    "tgn:placetype":[
        "aat:300008347"
    ]
},
  "bbox": [],
  "geometry": {"coordinates":[78.366667,11.433333],"type":"Point"}
}