{
  "id": 2693618,
  "type": "Feature",
  "properties": {
    "tgn:hierarchy":[
        "tgn:2693618",
        "tgn:1000001",
        "tgn:7012149",
        "tgn:1002678",
        "tgn:7007252",
        "tgn:7029392"
    ],
    "tgn:id":2693618,
    "tgn:name":"Stephens Creek",
    "tgn:placetype":[
        "aat:300008706"
    ]
},
  "bbox": [],
  "geometry": {"coordinates":[-86.4333,39.2167],"type":"Point"}
}