{
  "id": 2671142,
  "type": "Feature",
  "properties": {
    "tgn:hierarchy":[
        "tgn:2671142",
        "tgn:1000001",
        "tgn:7012149",
        "tgn:2002174",
        "tgn:7007919",
        "tgn:7029392"
    ],
    "tgn:id":2671142,
    "tgn:name":"Smith Creek",
    "tgn:placetype":[
        "aat:300008706"
    ]
},
  "bbox": [],
  "geometry": {"coordinates":[-80.4333,37.0833],"type":"Point"}
}