{
  "id": 2113424,
  "type": "Feature",
  "properties": {
    "tgn:hierarchy":[
        "tgn:2113424",
        "tgn:1000001",
        "tgn:7012149",
        "tgn:2002166",
        "tgn:7007919",
        "tgn:7029392"
    ],
    "tgn:id":2113424,
    "tgn:name":"North Stanton",
    "tgn:placetype":[
        "aat:300008347"
    ]
},
  "bbox": [],
  "geometry": {"coordinates":[-79.0667,36.95],"type":"Point"}
}