{
  "id": 7149703,
  "type": "Feature",
  "properties": {
    "tgn:hierarchy":[
        "tgn:7149703",
        "tgn:1000003",
        "tgn:7003682",
        "tgn:7000084",
        "tgn:7029392"
    ],
    "tgn:id":7149703,
    "tgn:name":"Lambsheim",
    "tgn:placetype":[
        "aat:300008347"
    ]
},
  "bbox": [],
  "geometry": {"coordinates":[8.287778,49.513611],"type":"Point"}
}