{
  "id": 1117483,
  "type": "Feature",
  "properties": {
    "tgn:hierarchy":[
        "tgn:1117483",
        "tgn:2000256",
        "tgn:1000001",
        "tgn:7012149",
        "tgn:7007240",
        "tgn:7029392"
    ],
    "tgn:id":1117483,
    "tgn:name":"Newnans Lake",
    "tgn:placetype":[
        "aat:300008680"
    ]
},
  "bbox": [],
  "geometry": {"coordinates":[-82.2167,29.6333],"type":"Point"}
}