{
  "id": 2392745,
  "type": "Feature",
  "properties": {
    "tgn:hierarchy":[
        "tgn:2392745",
        "tgn:1000001",
        "tgn:7012149",
        "tgn:2001925",
        "tgn:7007825",
        "tgn:7029392"
    ],
    "tgn:id":2392745,
    "tgn:name":"Hobbs Cave",
    "tgn:placetype":[
        "aat:300008746"
    ]
},
  "bbox": [],
  "geometry": {"coordinates":[-85.75,35.5833],"type":"Point"}
}