{
  "id": 2416153,
  "type": "Feature",
  "properties": {
    "tgn:hierarchy":[
        "tgn:2416153",
        "tgn:1000001",
        "tgn:7012149",
        "tgn:2002375",
        "tgn:7007923",
        "tgn:7029392"
    ],
    "tgn:id":2416153,
    "tgn:name":"J H D Reservoir Number 1",
    "tgn:placetype":[
        "aat:300006191"
    ]
},
  "bbox": [],
  "geometry": {"coordinates":[-104.6167,41.45],"type":"Point"}
}