{
  "id": 1062555,
  "type": "Feature",
  "properties": {
    "tgn:hierarchy":[
        "tgn:1062555",
        "tgn:7002832",
        "tgn:7001158",
        "tgn:1000003",
        "tgn:1000095",
        "tgn:7029392"
    ],
    "tgn:id":1062555,
    "tgn:name":"Torquemada",
    "tgn:placetype":[
        "aat:300008347"
    ]
},
  "bbox": [],
  "geometry": {"coordinates":[-4.316667,42.033333],"type":"Point"}
}