<<<<<<< HEAD
{
  "id": 2257566,
  "type": "Feature",
  "properties": {
    "tgn:hierarchy":[
        "tgn:2257566",
        "tgn:1000001",
        "tgn:7012149",
        "tgn:2002115",
        "tgn:7007827",
        "tgn:7029392"
    ],
    "tgn:id":2257566,
    "tgn:name":"Corral Canyon",
    "tgn:placetype":[
        "aat:300008761"
    ]
},
  "bbox": [],
  "geometry": {"coordinates":[-111.4833,41.1833],"type":"Point"}
}
=======
{"geometry":{"type":"Point","coordinates":[-111.483300,41.183300]},"type":"Feature","properties":{"hierarchy":["tgn:2257566","tgn:1000001","tgn:7012149","tgn:2002115","tgn:7007827","tgn:7029392"],"placetype":["aat:300008761"],"id":2257566,"name:xx":"Corral Canyon"}}
>>>>>>> 03f74aca74312dbeaf24d7e61306dd6a786dc3d0
