{
  "id": 2402242,
  "type": "Feature",
  "properties": {
    "tgn:hierarchy":[
        "tgn:2402242",
        "tgn:1000001",
        "tgn:2001265",
        "tgn:7012149",
        "tgn:7007524",
        "tgn:7029392"
    ],
    "tgn:id":2402242,
    "tgn:name":"Horsetrack Draw",
    "tgn:placetype":[
        "aat:300008761"
    ]
},
  "bbox": [],
  "geometry": {"coordinates":[-104.4333,45.6167],"type":"Point"}
}