{
  "id": 1057469,
  "type": "Feature",
  "properties": {
    "tgn:hierarchy":[
        "tgn:1057469",
        "tgn:1000004",
        "tgn:1003413",
        "tgn:7018214",
        "tgn:7002435",
        "tgn:7029392"
    ],
    "tgn:id":1057469,
    "tgn:name":"Nizhneye Romanovo",
    "tgn:placetype":[
        "aat:300008347"
    ]
},
  "bbox": [],
  "geometry": {"coordinates":[69.5833,59.7833],"type":"Point"}
}