{
  "id": 2681051,
  "type": "Feature",
  "properties": {
    "tgn:hierarchy":[
        "tgn:2681051",
        "tgn:1000001",
        "tgn:7012149",
        "tgn:2001288",
        "tgn:7007524",
        "tgn:7029392"
    ],
    "tgn:id":2681051,
    "tgn:name":"South Meadow Creek Lake",
    "tgn:placetype":[
        "aat:300008680"
    ]
},
  "bbox": [],
  "geometry": {"coordinates":[-111.9167,45.45],"type":"Point"}
}