{
  "id": 7224417,
  "type": "Feature",
  "properties": {
    "tgn:hierarchy":[
        "tgn:7224417",
        "tgn:7002718",
        "tgn:7002715",
        "tgn:1000003",
        "tgn:1000074",
        "tgn:7029392"
    ],
    "tgn:id":7224417,
    "tgn:name":"Rodh\u00f3n",
    "tgn:placetype":[
        "aat:300008347"
    ]
},
  "bbox": [],
  "geometry": {"coordinates":[21.633333,40.666667],"type":"Point"}
}