{
  "id": 7294827,
  "type": "Feature",
  "properties": {
    "tgn:hierarchy":[
        "tgn:7294827",
        "tgn:1001702",
        "tgn:1000049",
        "tgn:1000002",
        "tgn:7029392"
    ],
    "tgn:id":7294827,
    "tgn:name":"Abarca, Isla",
    "tgn:placetype":[
        "aat:300008791"
    ]
},
  "bbox": [],
  "geometry": {"coordinates":[-68.266667,-54.916667],"type":"Point"}
}