{
  "id": 7415812,
  "type": "Feature",
  "properties": {
    "tgn:hierarchy":[
        "tgn:7415812",
        "tgn:7005584",
        "tgn:1000001",
        "tgn:7005560",
        "tgn:7029392"
    ],
    "tgn:id":7415812,
    "tgn:name":"La Mina, Cerro",
    "tgn:placetype":[
        "aat:300008795"
    ]
},
  "bbox": [],
  "geometry": {"coordinates":[-101.091667,20.871111],"type":"Point"}
}