{
  "id": 7552791,
  "type": "Feature",
  "properties": {
    "tgn:hierarchy":[
        "tgn:7552791",
        "tgn:1000004",
        "tgn:7000198",
        "tgn:7016722",
        "tgn:7029392"
    ],
    "tgn:id":7552791,
    "tgn:name:en":"Mu\u0101zzampur N\u0101r\u0101yan",
    "tgn:placetype":[
        "aat:300008347"
    ]
},
  "bbox": [],
  "geometry": {"coordinates":[78.213136,29.586428],"type":"Point"}
}