{
  "id": 7239583,
  "type": "Feature",
  "properties": {
    "tgn:hierarchy":[
        "tgn:7239583",
        "tgn:7003461",
        "tgn:1000003",
        "tgn:1000063",
        "tgn:7018236",
        "tgn:7029392"
    ],
    "tgn:id":7239583,
    "tgn:name":"Heiderheide",
    "tgn:placetype":[
        "aat:300008863"
    ]
},
  "bbox": [],
  "geometry": {"coordinates":[5.316667,51.266667],"type":"Point"}
}