{
  "id": 2437177,
  "type": "Feature",
  "properties": {
    "tgn:hierarchy":[
        "tgn:2437177",
        "tgn:1000001",
        "tgn:7012149",
        "tgn:2000930",
        "tgn:7007515",
        "tgn:7029392"
    ],
    "tgn:id":2437177,
    "tgn:name":"Kimball Brook",
    "tgn:placetype":[
        "aat:300008699"
    ]
},
  "bbox": [],
  "geometry": {"coordinates":[-69.55,44.9833],"type":"Point"}
}