{
  "id": 7366977,
  "type": "Feature",
  "properties": {
    "tgn:hierarchy":[
        "tgn:7366977",
        "tgn:1000001",
        "tgn:7005601",
        "tgn:7005560",
        "tgn:7029392"
    ],
    "tgn:id":7366977,
    "tgn:name":"Estaci\u00f3n Margarita",
    "tgn:placetype":[
        "aat:300008347"
    ]
},
  "bbox": [],
  "geometry": {"coordinates":[-101.366667,24.633333],"type":"Point"}
}