<<<<<<< HEAD
{
  "id": 7366977,
  "type": "Feature",
  "properties": {
    "tgn:hierarchy":[
        "tgn:7366977",
        "tgn:1000001",
        "tgn:7005601",
        "tgn:7005560",
        "tgn:7029392"
    ],
    "tgn:id":7366977,
    "tgn:name":"Estaci\u00f3n Margarita",
    "tgn:placetype":[
        "aat:300008347"
    ]
},
  "bbox": [],
  "geometry": {"coordinates":[-101.366667,24.633333],"type":"Point"}
}
=======
{"geometry":{"type":"Point","coordinates":[-101.366667,24.633333]},"type":"Feature","properties":{"hierarchy":["tgn:7366977","tgn:1000001","tgn:7005601","tgn:7005560","tgn:7029392"],"placetype":["aat:300008347"],"id":7366977,"name:xx":"Estaci\u00f3n Margarita"}}
>>>>>>> 03f74aca74312dbeaf24d7e61306dd6a786dc3d0
