{
  "id": 2754879,
  "type": "Feature",
  "properties": {
    "tgn:hierarchy":[
        "tgn:2754879",
        "tgn:1000001",
        "tgn:7012149",
        "tgn:1002624",
        "tgn:7007568",
        "tgn:7029392"
    ],
    "tgn:id":2754879,
    "tgn:name":"Weaver Corner",
    "tgn:placetype":[
        "aat:300008347"
    ]
},
  "bbox": [],
  "geometry": {"coordinates":[-75.9167,43.1167],"type":"Point"}
}