{
  "id": 1120791,
  "type": "Feature",
  "properties": {
    "tgn:hierarchy":[
        "tgn:1120791",
        "tgn:1000004",
        "tgn:1001192",
        "tgn:7029379",
        "tgn:7029392"
    ],
    "tgn:id":1120791,
    "tgn:name":"\u00dc\u00fcr Gol",
    "tgn:placetype":[
        "aat:300008707"
    ]
},
  "bbox": [],
  "geometry": {"coordinates":[101.516,50.766],"type":"Point"}
}