{
  "id": 2464060,
  "type": "Feature",
  "properties": {
    "tgn:hierarchy":[
        "tgn:2464060",
        "tgn:1000001",
        "tgn:7016172",
        "tgn:7012149",
        "tgn:2000132",
        "tgn:7029392"
    ],
    "tgn:id":2464060,
    "tgn:name":"Locust Creek",
    "tgn:placetype":[
        "aat:300008706"
    ]
},
  "bbox": [],
  "geometry": {"coordinates":[-90.5667,36.15],"type":"Point"}
}