{
  "id": 7464423,
  "type": "Feature",
  "properties": {
    "tgn:hierarchy":[
        "tgn:7464423",
        "tgn:7002445",
        "tgn:1000003",
        "tgn:7008117",
        "tgn:7008591",
        "tgn:7029392"
    ],
    "tgn:id":7464423,
    "tgn:name:en":"Braithwaite",
    "tgn:placetype":[
        "aat:300008347"
    ]
},
  "bbox": [],
  "geometry": {"coordinates":[-3.183333,54.583333],"type":"Point"}
}