{
  "id": 2525847,
  "type": "Feature",
  "properties": {
    "tgn:hierarchy":[
        "tgn:2525847",
        "tgn:1000001",
        "tgn:7012149",
        "tgn:2001280",
        "tgn:7007524",
        "tgn:7029392"
    ],
    "tgn:id":2525847,
    "tgn:name":"Moses Mountain",
    "tgn:placetype":[
        "aat:300008798"
    ]
},
  "bbox": [],
  "geometry": {"coordinates":[-109.6167,48.1833],"type":"Point"}
}