{
  "id": 7503623,
  "type": "Feature",
  "properties": {
    "tgn:hierarchy":[
        "tgn:7503623",
        "tgn:7487020",
        "tgn:1000004",
        "tgn:1000141",
        "tgn:7029392"
    ],
    "tgn:id":7503623,
    "tgn:name":"Jialawan",
    "tgn:placetype":[
        "aat:300008347"
    ]
},
  "bbox": [],
  "geometry": {"coordinates":[121.033889,24.598611],"type":"Point"}
}