{
  "id": 2700404,
  "type": "Feature",
  "properties": {
    "tgn:hierarchy":[
        "tgn:2700404",
        "tgn:1000001",
        "tgn:1002276",
        "tgn:7012149",
        "tgn:7007708",
        "tgn:7029392"
    ],
    "tgn:id":2700404,
    "tgn:name":"Submarine Rock",
    "tgn:placetype":[
        "aat:300008791"
    ]
},
  "bbox": [],
  "geometry": {"coordinates":[-123.9667,45.9167],"type":"Point"}
}