{
  "id": 7155266,
  "type": "Feature",
  "properties": {
    "tgn:hierarchy":[
        "tgn:7155266",
        "tgn:1000003",
        "tgn:7003689",
        "tgn:7000084",
        "tgn:7029392"
    ],
    "tgn:id":7155266,
    "tgn:name":"Kirchgandern",
    "tgn:placetype":[
        "aat:300008347"
    ]
},
  "bbox": [],
  "geometry": {"coordinates":[9.95,51.366667],"type":"Point"}
}