{
  "id": 2048789,
  "type": "Feature",
  "properties": {
    "tgn:hierarchy":[
        "tgn:2048789",
        "tgn:7014651",
        "tgn:1000001",
        "tgn:7012149",
        "tgn:7007516",
        "tgn:7029392"
    ],
    "tgn:id":2048789,
    "tgn:name":"South Haven",
    "tgn:placetype":[
        "aat:300008347"
    ]
},
  "bbox": [],
  "geometry": {"coordinates":[-76.5667,38.95],"type":"Point"}
}