{
  "id": 2083973,
  "type": "Feature",
  "properties": {
    "tgn:hierarchy":[
        "tgn:2083973",
        "tgn:1000001",
        "tgn:7012149",
        "tgn:2001683",
        "tgn:7007707",
        "tgn:7029392"
    ],
    "tgn:id":2083973,
    "tgn:name":"Scipio",
    "tgn:placetype":[
        "aat:300008347"
    ]
},
  "bbox": [],
  "geometry": {"coordinates":[-95.95,35.05],"type":"Point"}
}