{
  "id": 7133513,
  "type": "Feature",
  "properties": {
    "tgn:hierarchy":[
        "tgn:7133513",
        "tgn:1000003",
        "tgn:7003688",
        "tgn:7000084",
        "tgn:7029392"
    ],
    "tgn:id":7133513,
    "tgn:name":"Nehmser See",
    "tgn:placetype":[
        "aat:300008680"
    ]
},
  "bbox": [],
  "geometry": {"coordinates":[10.366667,54.016667],"type":"Point"}
}