{
  "id": 7497672,
  "type": "Feature",
  "properties": {
    "tgn:hierarchy":[
        "tgn:7497672",
        "tgn:1000004",
        "tgn:1000454",
        "tgn:1000141",
        "tgn:7029392"
    ],
    "tgn:id":7497672,
    "tgn:name":"Shibafen",
    "tgn:placetype":[
        "aat:300008347"
    ]
},
  "bbox": [],
  "geometry": {"coordinates":[121.39224,25.046637],"type":"Point"}
}