{
  "id": 7207566,
  "type": "Feature",
  "properties": {
    "tgn:hierarchy":[
        "tgn:7207566",
        "tgn:1000003",
        "tgn:7003677",
        "tgn:7000084",
        "tgn:7029392"
    ],
    "tgn:id":7207566,
    "tgn:name":"Burg",
    "tgn:placetype":[
        "aat:300008777"
    ]
},
  "bbox": [],
  "geometry": {"coordinates":[8.616667,51.483333],"type":"Point"}
}