{
  "id": 2536781,
  "type": "Feature",
  "properties": {
    "tgn:hierarchy":[
        "tgn:2536781",
        "tgn:1000001",
        "tgn:7012149",
        "tgn:1002591",
        "tgn:7007255",
        "tgn:7029392"
    ],
    "tgn:id":2536781,
    "tgn:name":"Neds Branch",
    "tgn:placetype":[
        "aat:300008699"
    ]
},
  "bbox": [],
  "geometry": {"coordinates":[-83.3167,38.55],"type":"Point"}
}