{
  "id": 7540075,
  "type": "Feature",
  "properties": {
    "tgn:hierarchy":[
        "tgn:7540075",
        "tgn:7001242",
        "tgn:7001311",
        "tgn:7016833",
        "tgn:7029392"
    ],
    "tgn:id":7540075,
    "tgn:name:en":"Migwal Ligaia",
    "tgn:placetype":[
        "aat:300006207"
    ]
},
  "bbox": [],
  "geometry": {"coordinates":[35.216667,24.083333],"type":"Point"}
}