<<<<<<< HEAD
{
  "id": 2767411,
  "type": "Feature",
  "properties": {
    "tgn:hierarchy":[
        "tgn:2767411",
        "tgn:1000001",
        "tgn:7012149",
        "tgn:2000794",
        "tgn:7007255",
        "tgn:7029392"
    ],
    "tgn:id":2767411,
    "tgn:name":"White Springs Hole",
    "tgn:placetype":[
        "aat:300008680"
    ]
},
  "bbox": [],
  "geometry": {"coordinates":[-85.4333,37.2667],"type":"Point"}
}
=======
{"geometry":{"type":"Point","coordinates":[-85.433300,37.266700]},"type":"Feature","properties":{"hierarchy":["tgn:2767411","tgn:1000001","tgn:7012149","tgn:2000794","tgn:7007255","tgn:7029392"],"placetype":["aat:300008680"],"id":2767411,"name:xx":"White Springs Hole"}}
>>>>>>> 03f74aca74312dbeaf24d7e61306dd6a786dc3d0
