<<<<<<< HEAD
{
  "id": 7023727,
  "type": "Feature",
  "properties": {
    "tgn:hierarchy":[
        "tgn:7023727",
        "tgn:1000001",
        "tgn:7012149",
        "tgn:7007522",
        "tgn:7029392"
    ],
    "tgn:id":7023727,
    "tgn:name":"Tallabogue",
    "tgn:placetype":[
        "aat:300008699"
    ]
},
  "bbox": [],
  "geometry": {"coordinates":[-89.4833,32.35],"type":"Point"}
}
=======
{"geometry":{"type":"Point","coordinates":[-89.483300,32.350000]},"type":"Feature","properties":{"hierarchy":["tgn:7023727","tgn:1000001","tgn:7012149","tgn:7007522","tgn:7029392"],"placetype":["aat:300008699"],"id":7023727,"name:xx":"Tallabogue"}}
>>>>>>> 03f74aca74312dbeaf24d7e61306dd6a786dc3d0
