{
  "id": 2698064,
  "type": "Feature",
  "properties": {
    "tgn:hierarchy":[
        "tgn:2698064",
        "tgn:1002149",
        "tgn:1000001",
        "tgn:7012149",
        "tgn:7007826",
        "tgn:7029392"
    ],
    "tgn:id":2698064,
    "tgn:name":"Stovall Creek",
    "tgn:placetype":[
        "aat:300008706"
    ]
},
  "bbox": [],
  "geometry": {"coordinates":[-94.7333,31.2333],"type":"Point"}
}