{
  "id": 2427513,
  "type": "Feature",
  "properties": {
    "tgn:hierarchy":[
        "tgn:2427513",
        "tgn:1000001",
        "tgn:7012149",
        "tgn:2000414",
        "tgn:7007248",
        "tgn:7029392"
    ],
    "tgn:id":2427513,
    "tgn:name":"Jorden Lake",
    "tgn:placetype":[
        "aat:300006191"
    ]
},
  "bbox": [],
  "geometry": {"coordinates":[-84.3167,32.2167],"type":"Point"}
}