{
  "id": 2765184,
  "type": "Feature",
  "properties": {
    "tgn:hierarchy":[
        "tgn:2765184",
        "tgn:1000001",
        "tgn:7006451",
        "tgn:7012149",
        "tgn:2000103",
        "tgn:7029392"
    ],
    "tgn:id":2765184,
    "tgn:name":"Whistle Tank",
    "tgn:placetype":[
        "aat:300006191"
    ]
},
  "bbox": [],
  "geometry": {"coordinates":[-113.0667,34.85],"type":"Point"}
}