{
  "id": 7562333,
  "type": "Feature",
  "properties": {
    "tgn:hierarchy":[
        "tgn:7562333",
        "tgn:1000004",
        "tgn:7000198",
        "tgn:7016722",
        "tgn:7029392"
    ],
    "tgn:id":7562333,
    "tgn:name:en":"Majhara Kh\u0101s",
    "tgn:placetype":[
        "aat:300008347"
    ]
},
  "bbox": [],
  "geometry": {"coordinates":[79.488209,27.94271],"type":"Point"}
}