{
  "id": 2729352,
  "type": "Feature",
  "properties": {
    "tgn:hierarchy":[
        "tgn:2729352",
        "tgn:7006450",
        "tgn:1000001",
        "tgn:7012149",
        "tgn:2124002",
        "tgn:7029392"
    ],
    "tgn:id":2729352,
    "tgn:name":"Triplet Islands",
    "tgn:placetype":[
        "aat:300386853"
    ]
},
  "bbox": [],
  "geometry": {"coordinates":[-136.2167,57.7167],"type":"Point"}
}