{
  "id": 7434900,
  "type": "Feature",
  "properties": {
    "tgn:hierarchy":[
        "tgn:7434900",
        "tgn:7005585",
        "tgn:1000001",
        "tgn:7005560",
        "tgn:7029392"
    ],
    "tgn:id":7434900,
    "tgn:name":"Zihuatanejo, Bah\u00eda de",
    "tgn:placetype":[
        "aat:300132316"
    ]
},
  "bbox": [],
  "geometry": {"coordinates":[-101.566667,17.616667],"type":"Point"}
}