{
  "id": 7302083,
  "type": "Feature",
  "properties": {
    "tgn:hierarchy":[
        "tgn:7302083",
        "tgn:7002805",
        "tgn:7002758",
        "tgn:1000003",
        "tgn:1000095",
        "tgn:7029392"
    ],
    "tgn:id":7302083,
    "tgn:name":"Media Naranja, Punta de la",
    "tgn:placetype":[
        "aat:300386846"
    ]
},
  "bbox": [],
  "geometry": {"coordinates":[-1.916667,36.933333],"type":"Point"}
}