{
  "id": 7496111,
  "type": "Feature",
  "properties": {
    "tgn:hierarchy":[
        "tgn:7496111",
        "tgn:7487020",
        "tgn:1000004",
        "tgn:1000141",
        "tgn:7029392"
    ],
    "tgn:id":7496111,
    "tgn:name":"Longgang Yugang",
    "tgn:placetype":[
        "aat:300008678"
    ]
},
  "bbox": [],
  "geometry": {"coordinates":[120.757328,24.613524],"type":"Point"}
}