{
  "id": 2400548,
  "type": "Feature",
  "properties": {
    "tgn:hierarchy":[
        "tgn:2400548",
        "tgn:1000001",
        "tgn:7012149",
        "tgn:2001437",
        "tgn:7007566",
        "tgn:7029392"
    ],
    "tgn:id":2400548,
    "tgn:name":"Horse Lake",
    "tgn:placetype":[
        "aat:300008680"
    ]
},
  "bbox": [],
  "geometry": {"coordinates":[-108.7333,33.0167],"type":"Point"}
}