{
  "id": 2557427,
  "type": "Feature",
  "properties": {
    "tgn:hierarchy":[
        "tgn:2557427",
        "tgn:1000001",
        "tgn:1002724",
        "tgn:7012149",
        "tgn:7007517",
        "tgn:7029392"
    ],
    "tgn:id":2557427,
    "tgn:name":"Old Mill Brook",
    "tgn:placetype":[
        "aat:300008699"
    ]
},
  "bbox": [],
  "geometry": {"coordinates":[-71.3167,42.0167],"type":"Point"}
}