{
  "id": 2723861,
  "type": "Feature",
  "properties": {
    "tgn:hierarchy":[
        "tgn:2723861",
        "tgn:1000001",
        "tgn:7012149",
        "tgn:2002016",
        "tgn:7007826",
        "tgn:7029392"
    ],
    "tgn:id":2723861,
    "tgn:name":"Tokyo Hill",
    "tgn:placetype":[
        "aat:300008798"
    ]
},
  "bbox": [],
  "geometry": {"coordinates":[-97.85,26.9167],"type":"Point"}
}