{
  "id": 7314068,
  "type": "Feature",
  "properties": {
    "tgn:hierarchy":[
        "tgn:7314068",
        "tgn:1001623",
        "tgn:1000049",
        "tgn:1000002",
        "tgn:7029392"
    ],
    "tgn:id":7314068,
    "tgn:name":"Liucura, Canal",
    "tgn:placetype":[
        "aat:300387026"
    ]
},
  "bbox": [],
  "geometry": {"coordinates":[-73.783333,-46.016667],"type":"Point"}
}