{
  "id": 2742298,
  "type": "Feature",
  "properties": {
    "tgn:hierarchy":[
        "tgn:2742298",
        "tgn:1000001",
        "tgn:7012149",
        "tgn:7007157",
        "tgn:1002901",
        "tgn:7029392"
    ],
    "tgn:id":2742298,
    "tgn:name":"Vallejo Heights",
    "tgn:placetype":[
        "aat:300008798"
    ]
},
  "bbox": [],
  "geometry": {"coordinates":[-122.25,38.1167],"type":"Point"}
}