{
  "id": 2746099,
  "type": "Feature",
  "properties": {
    "tgn:hierarchy":[
        "tgn:2746099",
        "tgn:1000001",
        "tgn:7006451",
        "tgn:2000092",
        "tgn:7012149",
        "tgn:7029392"
    ],
    "tgn:id":2746099,
    "tgn:name":"Volunteer Tank",
    "tgn:placetype":[
        "aat:300006191"
    ]
},
  "bbox": [],
  "geometry": {"coordinates":[-111.9167,35.2333],"type":"Point"}
}