{
  "id": 7470277,
  "type": "Feature",
  "properties": {
    "tgn:hierarchy":[
        "tgn:7470277",
        "tgn:1000004",
        "tgn:1000454",
        "tgn:1000141",
        "tgn:7029392"
    ],
    "tgn:id":7470277,
    "tgn:name":"Zhutai Yu",
    "tgn:placetype":[
        "aat:300008791"
    ]
},
  "bbox": [],
  "geometry": {"coordinates":[121.654707,25.232934],"type":"Point"}
}