{
  "id": 2369832,
  "type": "Feature",
  "properties": {
    "tgn:hierarchy":[
        "tgn:2369832",
        "tgn:1000001",
        "tgn:2001786",
        "tgn:7012149",
        "tgn:7007713",
        "tgn:7029392"
    ],
    "tgn:id":2369832,
    "tgn:name":"Gurney Spring",
    "tgn:placetype":[
        "aat:300008697"
    ]
},
  "bbox": [],
  "geometry": {"coordinates":[-104.0333,43.7167],"type":"Point"}
}