{
  "id": 7089519,
  "type": "Feature",
  "properties": {
    "tgn:hierarchy":[
        "tgn:7089519",
        "tgn:7000096",
        "tgn:1000003",
        "tgn:7000084",
        "tgn:7029392"
    ],
    "tgn:id":7089519,
    "tgn:name":"Vollmersdorf",
    "tgn:placetype":[
        "aat:300008347"
    ]
},
  "bbox": [],
  "geometry": {"coordinates":[12.333333,52.916667],"type":"Point"}
}