{
  "id": 2367866,
  "type": "Feature",
  "properties": {
    "tgn:hierarchy":[
        "tgn:2367866",
        "tgn:1000001",
        "tgn:2000470",
        "tgn:7012149",
        "tgn:7007250",
        "tgn:7029392"
    ],
    "tgn:id":2367866,
    "tgn:name":"Grover Gulch",
    "tgn:placetype":[
        "aat:300008761"
    ]
},
  "bbox": [],
  "geometry": {"coordinates":[-114.8333,44.1333],"type":"Point"}
}