{
  "id": 1110684,
  "type": "Feature",
  "properties": {
    "tgn:hierarchy":[
        "tgn:1110684",
        "tgn:1000001",
        "tgn:7012149",
        "tgn:7007157",
        "tgn:1002748",
        "tgn:7029392"
    ],
    "tgn:id":1110684,
    "tgn:name":"Loma Ridge",
    "tgn:placetype":[
        "aat:300266640"
    ]
},
  "bbox": [],
  "geometry": {"coordinates":[-117.7167,33.75],"type":"Point"}
}