{
  "id": 7324860,
  "type": "Feature",
  "properties": {
    "tgn:hierarchy":[
        "tgn:7324860",
        "tgn:7002839",
        "tgn:7001158",
        "tgn:1000003",
        "tgn:1000095",
        "tgn:7029392"
    ],
    "tgn:id":7324860,
    "tgn:name":"San Crist\u00f3bal de Segovia",
    "tgn:placetype":[
        "aat:300008347"
    ]
},
  "bbox": [],
  "geometry": {"coordinates":[-4.066667,40.95],"type":"Point"}
}