{
  "id": 7419463,
  "type": "Feature",
  "properties": {
    "tgn:hierarchy":[
        "tgn:7419463",
        "tgn:7005579",
        "tgn:1000001",
        "tgn:7005560",
        "tgn:7029392"
    ],
    "tgn:id":7419463,
    "tgn:name":"La Ci\u00e9nega, Arroyo",
    "tgn:placetype":[
        "aat:300266554",
        "aat:300008699"
    ]
},
  "bbox": [],
  "geometry": {"coordinates":[-102.833333,21.916667],"type":"Point"}
}