{
  "id": 7487562,
  "type": "Feature",
  "properties": {
    "tgn:hierarchy":[
        "tgn:7487562",
        "tgn:1000004",
        "tgn:7467799",
        "tgn:1000141",
        "tgn:7029392"
    ],
    "tgn:id":7487562,
    "tgn:name":"Wazi",
    "tgn:placetype":[
        "aat:300008347"
    ]
},
  "bbox": [],
  "geometry": {"coordinates":[120.441751,23.953106],"type":"Point"}
}