<<<<<<< HEAD
{
  "id": 7487562,
  "type": "Feature",
  "properties": {
    "tgn:hierarchy":[
        "tgn:7487562",
        "tgn:1000004",
        "tgn:7467799",
        "tgn:1000141",
        "tgn:7029392"
    ],
    "tgn:id":7487562,
    "tgn:name":"Wazi",
    "tgn:placetype":[
        "aat:300008347"
    ]
},
  "bbox": [],
  "geometry": {"coordinates":[120.441751,23.953106],"type":"Point"}
}
=======
{"geometry":{"type":"Point","coordinates":[120.441751,23.953106]},"type":"Feature","properties":{"hierarchy":["tgn:7487562","tgn:1000004","tgn:7467799","tgn:1000141","tgn:7029392"],"placetype":["aat:300008347"],"id":7487562,"name:xx":"Wazi"}}
>>>>>>> 03f74aca74312dbeaf24d7e61306dd6a786dc3d0
