{
  "id": 2751729,
  "type": "Feature",
  "properties": {
    "tgn:hierarchy":[
        "tgn:2751729",
        "tgn:1000001",
        "tgn:7012149",
        "tgn:7029392"
    ],
    "tgn:id":2751729,
    "tgn:name":"Warren Creek",
    "tgn:placetype":[
        "aat:300008706"
    ]
},
  "bbox": [],
  "geometry": {"coordinates":[-85.6333,34.95],"type":"Point"}
}