{
  "id": 2757724,
  "type": "Feature",
  "properties": {
    "tgn:hierarchy":[
        "tgn:2757724",
        "tgn:1000001",
        "tgn:1002963",
        "tgn:7012149",
        "tgn:7007565",
        "tgn:7029392"
    ],
    "tgn:id":2757724,
    "tgn:name":"West Branch Elizabeth River",
    "tgn:placetype":[
        "aat:300008707"
    ]
},
  "bbox": [],
  "geometry": {"coordinates":[-74.2833,40.6833],"type":"Point"}
}