{
  "id": 2569485,
  "type": "Feature",
  "properties": {
    "tgn:hierarchy":[
        "tgn:2569485",
        "tgn:1000001",
        "tgn:7012149",
        "tgn:2002371",
        "tgn:7007923",
        "tgn:7029392"
    ],
    "tgn:id":2569485,
    "tgn:name":"Parque Creek",
    "tgn:placetype":[
        "aat:300008706"
    ]
},
  "bbox": [],
  "geometry": {"coordinates":[-109.7167,43.7667],"type":"Point"}
}