{
  "id": 7498912,
  "type": "Feature",
  "properties": {
    "tgn:hierarchy":[
        "tgn:7498912",
        "tgn:1000004",
        "tgn:1000454",
        "tgn:1000141",
        "tgn:7029392"
    ],
    "tgn:id":7498912,
    "tgn:name":"Tianxiu Gong",
    "tgn:placetype":[
        "aat:300007595"
    ]
},
  "bbox": [],
  "geometry": {"coordinates":[121.662884,25.053941],"type":"Point"}
}