{
  "id": 2024848,
  "type": "Feature",
  "properties": {
    "tgn:hierarchy":[
        "tgn:2024848",
        "tgn:7023902",
        "tgn:1000001",
        "tgn:7012149",
        "tgn:7007249",
        "tgn:7029392"
    ],
    "tgn:id":2024848,
    "tgn:name":"Haina",
    "tgn:placetype":[
        "aat:300008347",
        "aat:300387210"
    ]
},
  "bbox": [],
  "geometry": {"coordinates":[-155.4667,20.0667],"type":"Point"}
}