{
  "id": 2669163,
  "type": "Feature",
  "properties": {
    "tgn:hierarchy":[
        "tgn:2669163",
        "tgn:1000001",
        "tgn:2002254",
        "tgn:7012149",
        "tgn:7013961",
        "tgn:7029392"
    ],
    "tgn:id":2669163,
    "tgn:name":"Sleepy Creek Lake",
    "tgn:placetype":[
        "aat:300006191"
    ]
},
  "bbox": [],
  "geometry": {"coordinates":[-78.15,39.4833],"type":"Point"}
}