{
  "id": 1068296,
  "type": "Feature",
  "properties": {
    "tgn:hierarchy":[
        "tgn:1068296",
        "tgn:1000004",
        "tgn:1001390",
        "tgn:1000111",
        "tgn:7029392"
    ],
    "tgn:id":1068296,
    "tgn:name":"Gejiatun",
    "tgn:placetype":[
        "aat:300008347"
    ]
},
  "bbox": [],
  "geometry": {"coordinates":[119.9167,40.45],"type":"Point"}
}