{
  "id": 7587907,
  "type": "Feature",
  "properties": {
    "tgn:hierarchy":[
        "tgn:7587907",
        "tgn:1000004",
        "tgn:7000198",
        "tgn:1001977",
        "tgn:7029392"
    ],
    "tgn:id":7587907,
    "tgn:name:en":"Gokulpur",
    "tgn:placetype":[
        "aat:300008347"
    ]
},
  "bbox": [],
  "geometry": {"coordinates":[88.8491,22.778166],"type":"Point"}
}