{
  "id": 1049716,
  "type": "Feature",
  "properties": {
    "tgn:hierarchy":[
        "tgn:1049716",
        "tgn:1000882",
        "tgn:1000003",
        "tgn:1000090",
        "tgn:7029392"
    ],
    "tgn:id":1049716,
    "tgn:name":"Belas",
    "tgn:placetype":[
        "aat:300008347"
    ]
},
  "bbox": [],
  "geometry": {"coordinates":[-9.26,38.777],"type":"Point"}
}