{
  "id": 7394106,
  "type": "Feature",
  "properties": {
    "tgn:hierarchy":[
        "tgn:7394106",
        "tgn:1001835",
        "tgn:1000001",
        "tgn:7005560",
        "tgn:7029392"
    ],
    "tgn:id":7394106,
    "tgn:name":"San Francisquito, Punta",
    "tgn:placetype":[
        "aat:300386846"
    ]
},
  "bbox": [],
  "geometry": {"coordinates":[-112.916667,28.466667],"type":"Point"}
}