<<<<<<< HEAD
{
  "id": 7484329,
  "type": "Feature",
  "properties": {
    "tgn:hierarchy":[
        "tgn:7484329",
        "tgn:7487020",
        "tgn:1000004",
        "tgn:1000141",
        "tgn:7029392"
    ],
    "tgn:id":7484329,
    "tgn:name":"Qingren Qiao",
    "tgn:placetype":[
        "aat:300007836"
    ]
},
  "bbox": [],
  "geometry": {"coordinates":[120.656667,24.445],"type":"Point"}
}
=======
{"geometry":{"type":"Point","coordinates":[120.656667,24.445000]},"type":"Feature","properties":{"hierarchy":["tgn:7484329","tgn:7487020","tgn:1000004","tgn:1000141","tgn:7029392"],"placetype":["aat:300007836"],"id":7484329,"name:xx":"Qingren Qiao"}}
>>>>>>> 03f74aca74312dbeaf24d7e61306dd6a786dc3d0
