{
  "id": 2139549,
  "type": "Feature",
  "properties": {
    "tgn:hierarchy":[
        "tgn:2139549",
        "tgn:1000001",
        "tgn:7012149",
        "tgn:7007158",
        "tgn:2000246",
        "tgn:7029392"
    ],
    "tgn:id":2139549,
    "tgn:name":"Asterhouse Spring",
    "tgn:placetype":[
        "aat:300008697"
    ]
},
  "bbox": [],
  "geometry": {"coordinates":[-106.05,38.1667],"type":"Point"}
}