{
  "id": 7480687,
  "type": "Feature",
  "properties": {
    "tgn:hierarchy":[
        "tgn:7480687",
        "tgn:7001010",
        "tgn:1000004",
        "tgn:1000141",
        "tgn:7029392"
    ],
    "tgn:id":7480687,
    "tgn:name":"Nankeng",
    "tgn:placetype":[
        "aat:300008347"
    ]
},
  "bbox": [],
  "geometry": {"coordinates":[121.546667,23.771111],"type":"Point"}
}