{
  "id": 1068252,
  "type": "Feature",
  "properties": {
    "tgn:hierarchy":[
        "tgn:1068252",
        "tgn:1000004",
        "tgn:7001796",
        "tgn:1000111",
        "tgn:7029392"
    ],
    "tgn:id":1068252,
    "tgn:name":"Gaosha",
    "tgn:placetype":[
        "aat:300008347"
    ]
},
  "bbox": [],
  "geometry": {"coordinates":[119.55,26.4333],"type":"Point"}
}