{
  "id": 1023824,
  "type": "Feature",
  "properties": {
    "tgn:hierarchy":[
        "tgn:1023824",
        "tgn:1000640",
        "tgn:1000050",
        "tgn:1000002",
        "tgn:7029392"
    ],
    "tgn:id":1023824,
    "tgn:name":"Garz\u00f3n",
    "tgn:placetype":[
        "aat:300008347"
    ]
},
  "bbox": [],
  "geometry": {"coordinates":[-75.6167,2.2333],"type":"Point"}
}