{
  "id": 2741492,
  "type": "Feature",
  "properties": {
    "tgn:hierarchy":[
        "tgn:2741492",
        "tgn:1000001",
        "tgn:7012149",
        "tgn:7013867",
        "tgn:7007710",
        "tgn:7029392"
    ],
    "tgn:id":2741492,
    "tgn:name":"Urey Islands",
    "tgn:placetype":[
        "aat:300386853"
    ]
},
  "bbox": [],
  "geometry": {"coordinates":[-76.3667,39.8667],"type":"Point"}
}