{
  "id": 2019164,
  "type": "Feature",
  "properties": {
    "tgn:hierarchy":[
        "tgn:2019164",
        "tgn:1000001",
        "tgn:7012149",
        "tgn:2000283",
        "tgn:7007240",
        "tgn:7029392"
    ],
    "tgn:id":2019164,
    "tgn:name":"Durbin",
    "tgn:placetype":[
        "aat:300387016"
    ]
},
  "bbox": [],
  "geometry": {"coordinates":[-81.45,30.0833],"type":"Point"}
}