<<<<<<< HEAD
{
  "id": 2402804,
  "type": "Feature",
  "properties": {
    "tgn:hierarchy":[
        "tgn:2402804",
        "tgn:1000001",
        "tgn:2001413",
        "tgn:7012149",
        "tgn:7007526",
        "tgn:7029392"
    ],
    "tgn:id":2402804,
    "tgn:name":"Hot Springs Point",
    "tgn:placetype":[
        "aat:300008798"
    ]
},
  "bbox": [],
  "geometry": {"coordinates":[-116.5,40.4],"type":"Point"}
}
=======
{"geometry":{"type":"Point","coordinates":[-116.500000,40.400000]},"type":"Feature","properties":{"hierarchy":["tgn:2402804","tgn:1000001","tgn:2001413","tgn:7012149","tgn:7007526","tgn:7029392"],"placetype":["aat:300008798"],"id":2402804,"name:xx":"Hot Springs Point"}}
>>>>>>> 03f74aca74312dbeaf24d7e61306dd6a786dc3d0
