{
  "id": 7198397,
  "type": "Feature",
  "properties": {
    "tgn:hierarchy":[
        "tgn:7198397",
        "tgn:7003669",
        "tgn:1000003",
        "tgn:7000084",
        "tgn:7029392"
    ],
    "tgn:id":7198397,
    "tgn:name":"Eglham",
    "tgn:placetype":[
        "aat:300008347"
    ]
},
  "bbox": [],
  "geometry": {"coordinates":[12.166667,47.95],"type":"Point"}
}