{
  "id": 2471228,
  "type": "Feature",
  "properties": {
    "tgn:hierarchy":[
        "tgn:2471228",
        "tgn:1000001",
        "tgn:7012149",
        "tgn:2001233",
        "tgn:7007523",
        "tgn:7029392"
    ],
    "tgn:id":2471228,
    "tgn:name":"Lost Hill",
    "tgn:placetype":[
        "aat:300008798"
    ]
},
  "bbox": [],
  "geometry": {"coordinates":[-92.0833,37.8167],"type":"Point"}
}