{
  "id": 7224610,
  "type": "Feature",
  "properties": {
    "tgn:hierarchy":[
        "tgn:7224610",
        "tgn:7002690",
        "tgn:7012056",
        "tgn:1000003",
        "tgn:1000074",
        "tgn:7029392"
    ],
    "tgn:id":7224610,
    "tgn:name":"Tambarian\u00e1",
    "tgn:placetype":[
        "aat:300008347"
    ]
},
  "bbox": [],
  "geometry": {"coordinates":[23.616667,35.466667],"type":"Point"}
}