{
  "id": 2529863,
  "type": "Feature",
  "properties": {
    "tgn:hierarchy":[
        "tgn:2529863",
        "tgn:1000001",
        "tgn:7012149",
        "tgn:7007251",
        "tgn:7029392"
    ],
    "tgn:id":2529863,
    "tgn:name":"Mud Run",
    "tgn:placetype":[
        "aat:300008699"
    ]
},
  "bbox": [],
  "geometry": {"coordinates":[-90.0167,41.1333],"type":"Point"}
}