{
  "id": 7237749,
  "type": "Feature",
  "properties": {
    "tgn:hierarchy":[
        "tgn:7237749",
        "tgn:7003456",
        "tgn:1000003",
        "tgn:1000063",
        "tgn:7018236",
        "tgn:7029392"
    ],
    "tgn:id":7237749,
    "tgn:name":"Goorloop",
    "tgn:placetype":[
        "aat:300008699"
    ]
},
  "bbox": [],
  "geometry": {"coordinates":[4.733333,51.116667],"type":"Point"}
}