{
  "id": 7191008,
  "type": "Feature",
  "properties": {
    "tgn:hierarchy":[
        "tgn:7191008",
        "tgn:7003692",
        "tgn:1000003",
        "tgn:7000084",
        "tgn:7029392"
    ],
    "tgn:id":7191008,
    "tgn:name":"Faustenhof",
    "tgn:placetype":[
        "aat:300000206"
    ]
},
  "bbox": [],
  "geometry": {"coordinates":[9.316667,49.45],"type":"Point"}
}