{
  "id": 2543653,
  "type": "Feature",
  "properties": {
    "tgn:hierarchy":[
        "tgn:2543653",
        "tgn:1000001",
        "tgn:7012149",
        "tgn:2001296",
        "tgn:7007524",
        "tgn:7029392"
    ],
    "tgn:id":2543653,
    "tgn:name":"North Badger Creek",
    "tgn:placetype":[
        "aat:300008706"
    ]
},
  "bbox": [],
  "geometry": {"coordinates":[-113.2167,48.1667],"type":"Point"}
}