{
  "id": 7583215,
  "type": "Feature",
  "properties": {
    "tgn:hierarchy":[
        "tgn:7583215",
        "tgn:1000004",
        "tgn:7000198",
        "tgn:1001894",
        "tgn:7029392"
    ],
    "tgn:id":7583215,
    "tgn:name:en":"Ronda",
    "tgn:placetype":[
        "aat:300008347"
    ]
},
  "bbox": [],
  "geometry": {"coordinates":[78.502528,24.17799],"type":"Point"}
}