<<<<<<< HEAD
{
  "id": 7360897,
  "type": "Feature",
  "properties": {
    "tgn:hierarchy":[
        "tgn:7360897",
        "tgn:7005581",
        "tgn:1000001",
        "tgn:7005560",
        "tgn:7029392"
    ],
    "tgn:id":7360897,
    "tgn:name":"Rancho El Nogal",
    "tgn:placetype":[
        "aat:300000241"
    ]
},
  "bbox": [],
  "geometry": {"coordinates":[-107.016667,29.083333],"type":"Point"}
}
=======
{"geometry":{"type":"Point","coordinates":[-107.016667,29.083333]},"type":"Feature","properties":{"hierarchy":["tgn:7360897","tgn:7005581","tgn:1000001","tgn:7005560","tgn:7029392"],"placetype":["aat:300000241"],"id":7360897,"name:xx":"Rancho El Nogal"}}
>>>>>>> 03f74aca74312dbeaf24d7e61306dd6a786dc3d0
