{
  "id": 7014397,
  "type": "Feature",
  "properties": {
    "tgn:hierarchy":[
        "tgn:7014397",
        "tgn:1000001",
        "tgn:7012149",
        "tgn:2001763",
        "tgn:7007712",
        "tgn:7029392"
    ],
    "tgn:id":7014397,
    "tgn:name":"Pendleton",
    "tgn:placetype":[
        "aat:300008347"
    ]
},
  "bbox": [],
  "geometry": {"coordinates":[-82.7833,34.65],"type":"Point"}
}