{
  "id": 2432692,
  "type": "Feature",
  "properties": {
    "tgn:hierarchy":[
        "tgn:2432692",
        "tgn:7006450",
        "tgn:1000001",
        "tgn:7012149",
        "tgn:2000085",
        "tgn:7029392"
    ],
    "tgn:id":2432692,
    "tgn:name":"Keenan Creek",
    "tgn:placetype":[
        "aat:300008706"
    ]
},
  "bbox": [],
  "geometry": {"coordinates":[-142.1333,65.2167],"type":"Point"}
}