<<<<<<< HEAD
{
  "id": 2402685,
  "type": "Feature",
  "properties": {
    "tgn:hierarchy":[
        "tgn:2402685",
        "tgn:1000001",
        "tgn:2001414",
        "tgn:7012149",
        "tgn:7007526",
        "tgn:7029392"
    ],
    "tgn:id":2402685,
    "tgn:name":"Hot Spring",
    "tgn:placetype":[
        "aat:300008697"
    ]
},
  "bbox": [],
  "geometry": {"coordinates":[-118.7167,41.05],"type":"Point"}
}
=======
{"geometry":{"type":"Point","coordinates":[-118.716700,41.050000]},"type":"Feature","properties":{"hierarchy":["tgn:2402685","tgn:1000001","tgn:2001414","tgn:7012149","tgn:7007526","tgn:7029392"],"placetype":["aat:300008697"],"id":2402685,"name:xx":"Hot Spring"}}
>>>>>>> 03f74aca74312dbeaf24d7e61306dd6a786dc3d0
