{
  "id": 1123562,
  "type": "Feature",
  "properties": {
    "tgn:hierarchy":[
        "tgn:1123562",
        "tgn:1000001",
        "tgn:7012149",
        "tgn:2000917",
        "tgn:7007256",
        "tgn:7029392"
    ],
    "tgn:id":1123562,
    "tgn:name":"Dugdemona",
    "tgn:placetype":[
        "aat:300008707"
    ]
},
  "bbox": [],
  "geometry": {"coordinates":[-92.35,31.7833],"type":"Point"}
}