{
  "id": 7300649,
  "type": "Feature",
  "properties": {
    "tgn:hierarchy":[
        "tgn:7300649",
        "tgn:7002820",
        "tgn:7030216",
        "tgn:1000003",
        "tgn:1000095",
        "tgn:7029392"
    ],
    "tgn:id":7300649,
    "tgn:name":"Norfeo, Cabo",
    "tgn:placetype":[
        "aat:300008850"
    ]
},
  "bbox": [],
  "geometry": {"coordinates":[3.265311,42.239078],"type":"Point"}
}