{
  "id": 2695059,
  "type": "Feature",
  "properties": {
    "tgn:hierarchy":[
        "tgn:2695059",
        "tgn:1000001",
        "tgn:7012149",
        "tgn:2001247",
        "tgn:7007523",
        "tgn:7029392"
    ],
    "tgn:id":2695059,
    "tgn:name":"Still Spring Hollow",
    "tgn:placetype":[
        "aat:300008761"
    ]
},
  "bbox": [],
  "geometry": {"coordinates":[-91.4333,37.3833],"type":"Point"}
}