{
  "id": 2510475,
  "type": "Feature",
  "properties": {
    "tgn:hierarchy":[
        "tgn:2510475",
        "tgn:1000001",
        "tgn:2001009",
        "tgn:7012149",
        "tgn:7007521",
        "tgn:7029392"
    ],
    "tgn:id":2510475,
    "tgn:name":"Middle Sucker Wildlife Impoundment",
    "tgn:placetype":[
        "aat:300006191"
    ]
},
  "bbox": [],
  "geometry": {"coordinates":[-94.4333,47.3333],"type":"Point"}
}