{
  "id": 2155529,
  "type": "Feature",
  "properties": {
    "tgn:hierarchy":[
        "tgn:2155529",
        "tgn:1000001",
        "tgn:7012149",
        "tgn:1002830",
        "tgn:7007826",
        "tgn:7029392"
    ],
    "tgn:id":2155529,
    "tgn:name":"Bear Rough Lake",
    "tgn:placetype":[
        "aat:300008680"
    ]
},
  "bbox": [],
  "geometry": {"coordinates":[-96.3167,31.2167],"type":"Point"}
}