<<<<<<< HEAD
{
  "id": 2155529,
  "type": "Feature",
  "properties": {
    "tgn:hierarchy":[
        "tgn:2155529",
        "tgn:1000001",
        "tgn:7012149",
        "tgn:1002830",
        "tgn:7007826",
        "tgn:7029392"
    ],
    "tgn:id":2155529,
    "tgn:name":"Bear Rough Lake",
    "tgn:placetype":[
        "aat:300008680"
    ]
},
  "bbox": [],
  "geometry": {"coordinates":[-96.3167,31.2167],"type":"Point"}
}
=======
{"geometry":{"type":"Point","coordinates":[-96.316700,31.216700]},"type":"Feature","properties":{"hierarchy":["tgn:2155529","tgn:1000001","tgn:7012149","tgn:1002830","tgn:7007826","tgn:7029392"],"placetype":["aat:300008680"],"id":2155529,"name:xx":"Bear Rough Lake"}}
>>>>>>> 03f74aca74312dbeaf24d7e61306dd6a786dc3d0
