{
  "id": 7220041,
  "type": "Feature",
  "properties": {
    "tgn:hierarchy":[
        "tgn:7220041",
        "tgn:7002743",
        "tgn:7017076",
        "tgn:1000003",
        "tgn:1000074",
        "tgn:7029392"
    ],
    "tgn:id":7220041,
    "tgn:name":"V\u00e9rgas R\u00e9ma",
    "tgn:placetype":[
        "aat:300008699"
    ]
},
  "bbox": [],
  "geometry": {"coordinates":[21.316667,38.016667],"type":"Point"}
}