{
  "id": 2238219,
  "type": "Feature",
  "properties": {
    "tgn:hierarchy":[
        "tgn:2238219",
        "tgn:1000001",
        "tgn:7012149",
        "tgn:2002111",
        "tgn:7007827",
        "tgn:7029392"
    ],
    "tgn:id":2238219,
    "tgn:name":"Chloride Canyon",
    "tgn:placetype":[
        "aat:300008761"
    ]
},
  "bbox": [],
  "geometry": {"coordinates":[-113.45,37.7333],"type":"Point"}
}