{
  "id": 7044841,
  "type": "Feature",
  "properties": {
    "tgn:hierarchy":[
        "tgn:7044841",
        "tgn:1003428",
        "tgn:1000003",
        "tgn:7003120",
        "tgn:1000080",
        "tgn:7029392"
    ],
    "tgn:id":7044841,
    "tgn:name":"Castelnuovo Bormida",
    "tgn:placetype":[
        "aat:300008347"
    ]
},
  "bbox": [],
  "geometry": {"coordinates":[8.55,44.75],"type":"Point"}
}