<<<<<<< HEAD
{
  "id": 2332364,
  "type": "Feature",
  "properties": {
    "tgn:hierarchy":[
        "tgn:2332364",
        "tgn:1000001",
        "tgn:7012149",
        "tgn:2002340",
        "tgn:7007922",
        "tgn:7029392"
    ],
    "tgn:id":2332364,
    "tgn:name":"Flora Dell Lake",
    "tgn:placetype":[
        "aat:300006191"
    ]
},
  "bbox": [],
  "geometry": {"coordinates":[-90.6,44.0],"type":"Point"}
}
=======
{"geometry":{"type":"Point","coordinates":[-90.600000,44.000000]},"type":"Feature","properties":{"hierarchy":["tgn:2332364","tgn:1000001","tgn:7012149","tgn:2002340","tgn:7007922","tgn:7029392"],"placetype":["aat:300006191"],"id":2332364,"name:xx":"Flora Dell Lake"}}
>>>>>>> 03f74aca74312dbeaf24d7e61306dd6a786dc3d0
