{
  "id": 7531523,
  "type": "Feature",
  "properties": {
    "tgn:hierarchy":[
        "tgn:7531523",
        "tgn:7001242",
        "tgn:7016833",
        "tgn:7001335",
        "tgn:7029392"
    ],
    "tgn:id":7531523,
    "tgn:name":"Mu\u1e25aysin, Juzur",
    "tgn:placetype":[
        "aat:300008791"
    ]
},
  "bbox": [],
  "geometry": {"coordinates":[33.316944,31.191667],"type":"Point"}
}