{
  "id": 7017952,
  "type": "Feature",
  "properties": {
    "tgn:hierarchy":[
        "tgn:7017952",
        "tgn:7001242",
        "tgn:7029392"
    ],
    "tgn:id":7017952,
    "tgn:name":"Akobo",
    "tgn:placetype":[
        "aat:300008707"
    ]
},
  "bbox": [],
  "geometry": {"coordinates":[33.05,7.7833],"type":"Point"}
}