{
  "id": 7426999,
  "type": "Feature",
  "properties": {
    "tgn:hierarchy":[
        "tgn:7426999",
        "tgn:1000001",
        "tgn:7005594",
        "tgn:7005560",
        "tgn:7029392"
    ],
    "tgn:id":7426999,
    "tgn:name":"La Mesita, Laguna",
    "tgn:placetype":[
        "aat:300008680"
    ]
},
  "bbox": [],
  "geometry": {"coordinates":[-101.65,22.866667],"type":"Point"}
}