{
  "id": 7470203,
  "type": "Feature",
  "properties": {
    "tgn:hierarchy":[
        "tgn:7470203",
        "tgn:7488858",
        "tgn:1000004",
        "tgn:1000141",
        "tgn:7029392"
    ],
    "tgn:id":7470203,
    "tgn:name":"Luanda Xi",
    "tgn:placetype":[
        "aat:300008699"
    ]
},
  "bbox": [],
  "geometry": {"coordinates":[121.018006,23.705423],"type":"Point"}
}