<<<<<<< HEAD
{
  "id": 7470203,
  "type": "Feature",
  "properties": {
    "tgn:hierarchy":[
        "tgn:7470203",
        "tgn:7488858",
        "tgn:1000004",
        "tgn:1000141",
        "tgn:7029392"
    ],
    "tgn:id":7470203,
    "tgn:name":"Luanda Xi",
    "tgn:placetype":[
        "aat:300008699"
    ]
},
  "bbox": [],
  "geometry": {"coordinates":[121.018006,23.705423],"type":"Point"}
}
=======
{"geometry":{"type":"Point","coordinates":[121.018006,23.705423]},"type":"Feature","properties":{"hierarchy":["tgn:7470203","tgn:7488858","tgn:1000004","tgn:1000141","tgn:7029392"],"placetype":["aat:300008699"],"id":7470203,"name:xx":"Luanda Xi"}}
>>>>>>> 03f74aca74312dbeaf24d7e61306dd6a786dc3d0
