{
  "id": 2591772,
  "type": "Feature",
  "properties": {
    "tgn:hierarchy":[
        "tgn:2591772",
        "tgn:1002300",
        "tgn:1000001",
        "tgn:7012149",
        "tgn:7007564",
        "tgn:7029392"
    ],
    "tgn:id":2591772,
    "tgn:name":"Pond Hill",
    "tgn:placetype":[
        "aat:300008798"
    ]
},
  "bbox": [],
  "geometry": {"coordinates":[-71.35,44.4167],"type":"Point"}
}