{
  "id": 2466785,
  "type": "Feature",
  "properties": {
    "tgn:hierarchy":[
        "tgn:2466785",
        "tgn:1000001",
        "tgn:7012149",
        "tgn:7007919",
        "tgn:7029392"
    ],
    "tgn:id":2466785,
    "tgn:name":"Long Branch",
    "tgn:placetype":[
        "aat:300008699"
    ]
},
  "bbox": [],
  "geometry": {"coordinates":[-77.8167,37.1833],"type":"Point"}
}