<<<<<<< HEAD
{
  "id": 2404487,
  "type": "Feature",
  "properties": {
    "tgn:hierarchy":[
        "tgn:2404487",
        "tgn:1000001",
        "tgn:2001412",
        "tgn:7012149",
        "tgn:7007526",
        "tgn:7029392"
    ],
    "tgn:id":2404487,
    "tgn:name":"Hubbard Mine",
    "tgn:placetype":[
        "aat:300000390"
    ]
},
  "bbox": [],
  "geometry": {"coordinates":[-117.35,37.7167],"type":"Point"}
}
=======
{"geometry":{"type":"Point","coordinates":[-117.350000,37.716700]},"type":"Feature","properties":{"hierarchy":["tgn:2404487","tgn:1000001","tgn:2001412","tgn:7012149","tgn:7007526","tgn:7029392"],"placetype":["aat:300000390"],"id":2404487,"name:xx":"Hubbard Mine"}}
>>>>>>> 03f74aca74312dbeaf24d7e61306dd6a786dc3d0
