{
  "id": 7159748,
  "type": "Feature",
  "properties": {
    "tgn:hierarchy":[
        "tgn:7159748",
        "tgn:1000003",
        "tgn:7000094",
        "tgn:7000084",
        "tgn:7029392"
    ],
    "tgn:id":7159748,
    "tgn:name":"Holzendorfer See",
    "tgn:placetype":[
        "aat:300008680"
    ]
},
  "bbox": [],
  "geometry": {"coordinates":[11.633333,53.683333],"type":"Point"}
}