{
  "id": 7208449,
  "type": "Feature",
  "properties": {
    "tgn:hierarchy":[
        "tgn:7208449",
        "tgn:7000096",
        "tgn:1000003",
        "tgn:7000084",
        "tgn:7029392"
    ],
    "tgn:id":7208449,
    "tgn:name":"Beetzer See",
    "tgn:placetype":[
        "aat:300008680"
    ]
},
  "bbox": [],
  "geometry": {"coordinates":[13.033333,52.816667],"type":"Point"}
}