{
  "id": 2244431,
  "type": "Feature",
  "properties": {
    "tgn:hierarchy":[
        "tgn:2244431",
        "tgn:2000256",
        "tgn:1000001",
        "tgn:7012149",
        "tgn:7007240",
        "tgn:7029392"
    ],
    "tgn:id":2244431,
    "tgn:name":"Clinch",
    "tgn:placetype":[
        "aat:300008347"
    ]
},
  "bbox": [],
  "geometry": {"coordinates":[-82.3833,29.5667],"type":"Point"}
}