{
  "id": 2143556,
  "type": "Feature",
  "properties": {
    "tgn:hierarchy":[
        "tgn:2143556",
        "tgn:1000001",
        "tgn:7012149",
        "tgn:2002169",
        "tgn:7007919",
        "tgn:7029392"
    ],
    "tgn:id":2143556,
    "tgn:name":"Baileys Cave",
    "tgn:placetype":[
        "aat:300008746"
    ]
},
  "bbox": [],
  "geometry": {"coordinates":[-82.8833,36.7667],"type":"Point"}
}