{
  "id": 2223775,
  "type": "Feature",
  "properties": {
    "tgn:hierarchy":[
        "tgn:2223775",
        "tgn:1000001",
        "tgn:7012149",
        "tgn:1002440",
        "tgn:7007568",
        "tgn:7029392"
    ],
    "tgn:id":2223775,
    "tgn:name":"Carter Mudhole",
    "tgn:placetype":[
        "aat:300008905"
    ]
},
  "bbox": [],
  "geometry": {"coordinates":[-74.7333,43.5833],"type":"Point"}
}