{
  "id": 2678892,
  "type": "Feature",
  "properties": {
    "tgn:hierarchy":[
        "tgn:2678892",
        "tgn:1000001",
        "tgn:2001414",
        "tgn:7012149",
        "tgn:7007526",
        "tgn:7029392"
    ],
    "tgn:id":2678892,
    "tgn:name":"South Fork Granite Creek",
    "tgn:placetype":[
        "aat:300008706"
    ]
},
  "bbox": [],
  "geometry": {"coordinates":[-118.65,41.75],"type":"Point"}
}