<<<<<<< HEAD
{
  "id": 7366784,
  "type": "Feature",
  "properties": {
    "tgn:hierarchy":[
        "tgn:7366784",
        "tgn:1000001",
        "tgn:7005597",
        "tgn:7005560",
        "tgn:7029392"
    ],
    "tgn:id":7366784,
    "tgn:name":"El Plan, Laguna",
    "tgn:placetype":[
        "aat:300387086"
    ]
},
  "bbox": [],
  "geometry": {"coordinates":[-97.8,24.133333],"type":"Point"}
}
=======
{"geometry":{"type":"Point","coordinates":[-97.800000,24.133333]},"type":"Feature","properties":{"hierarchy":["tgn:7366784","tgn:1000001","tgn:7005597","tgn:7005560","tgn:7029392"],"placetype":["aat:300387086"],"id":7366784,"name:xx":"El Plan, Laguna"}}
>>>>>>> 03f74aca74312dbeaf24d7e61306dd6a786dc3d0
