{
  "id": 1074960,
  "type": "Feature",
  "properties": {
    "tgn:hierarchy":[
        "tgn:1074960",
        "tgn:1000004",
        "tgn:7000198",
        "tgn:1001977",
        "tgn:7029392"
    ],
    "tgn:id":1074960,
    "tgn:name:en":"Charanpur",
    "tgn:placetype":[
        "aat:300008347"
    ]
},
  "bbox": [],
  "geometry": {"coordinates":[87.045853,23.742984],"type":"Point"}
}