{
  "id": 7329436,
  "type": "Feature",
  "properties": {
    "tgn:hierarchy":[
        "tgn:7329436",
        "tgn:7002811",
        "tgn:1000003",
        "tgn:7003837",
        "tgn:1000095",
        "tgn:7029392"
    ],
    "tgn:id":7329436,
    "tgn:name":"Puerto Rey",
    "tgn:placetype":[
        "aat:300008347"
    ]
},
  "bbox": [],
  "geometry": {"coordinates":[-5.016667,39.45],"type":"Point"}
}