<<<<<<< HEAD
{
  "id": 7027063,
  "type": "Feature",
  "properties": {
    "tgn:hierarchy":[
        "tgn:7027063",
        "tgn:7002445",
        "tgn:1000003",
        "tgn:7008143",
        "tgn:7008591",
        "tgn:7029392"
    ],
    "tgn:id":7027063,
    "tgn:name":"King's Pyon",
    "tgn:placetype":[
        "aat:300008347",
        "aat:300008372"
    ]
},
  "bbox": [],
  "geometry": {"coordinates":[-2.816667,52.15],"type":"Point"}
}
=======
{"geometry":{"type":"Point","coordinates":[-2.816667,52.150000]},"type":"Feature","properties":{"hierarchy":["tgn:7027063","tgn:7002445","tgn:1000003","tgn:7008143","tgn:7008591","tgn:7029392"],"placetype":["aat:300008347","aat:300008372"],"id":7027063,"name:xx":"King's Pyon"}}
>>>>>>> 03f74aca74312dbeaf24d7e61306dd6a786dc3d0
