{
  "id": 7401016,
  "type": "Feature",
  "properties": {
    "tgn:hierarchy":[
        "tgn:7401016",
        "tgn:1000001",
        "tgn:7005599",
        "tgn:7005560",
        "tgn:7029392"
    ],
    "tgn:id":7401016,
    "tgn:name":"Chiconcoa",
    "tgn:placetype":[
        "aat:300008347"
    ]
},
  "bbox": [],
  "geometry": {"coordinates":[-97.433333,20.766667],"type":"Point"}
}