{
  "id": 2777455,
  "type": "Feature",
  "properties": {
    "tgn:hierarchy":[
        "tgn:2777455",
        "tgn:1000001",
        "tgn:7012149",
        "tgn:2001286",
        "tgn:7007524",
        "tgn:7029392"
    ],
    "tgn:id":2777455,
    "tgn:name":"Winkum Creek",
    "tgn:placetype":[
        "aat:300008706"
    ]
},
  "bbox": [],
  "geometry": {"coordinates":[-115.9333,48.95],"type":"Point"}
}