{
  "id": 2709406,
  "type": "Feature",
  "properties": {
    "tgn:hierarchy":[
        "tgn:2709406",
        "tgn:1000001",
        "tgn:7006451",
        "tgn:2000092",
        "tgn:7012149",
        "tgn:7029392"
    ],
    "tgn:id":2709406,
    "tgn:name":"Table Rock Tank",
    "tgn:placetype":[
        "aat:300006191"
    ]
},
  "bbox": [],
  "geometry": {"coordinates":[-112.4167,36.6833],"type":"Point"}
}