{
  "id": 7152594,
  "type": "Feature",
  "properties": {
    "tgn:hierarchy":[
        "tgn:7152594",
        "tgn:1000003",
        "tgn:7003678",
        "tgn:7000084",
        "tgn:7029392"
    ],
    "tgn:id":7152594,
    "tgn:name":"Justush\u00fctte",
    "tgn:placetype":[
        "aat:300000206"
    ]
},
  "bbox": [],
  "geometry": {"coordinates":[8.55,50.783333],"type":"Point"}
}