{
  "id": 7454172,
  "type": "Feature",
  "properties": {
    "tgn:hierarchy":[
        "tgn:7454172",
        "tgn:7002445",
        "tgn:1000003",
        "tgn:7026533",
        "tgn:7008591",
        "tgn:7029392"
    ],
    "tgn:id":7454172,
    "tgn:name:en":"Chetwynd Aston",
    "tgn:placetype":[
        "aat:300008347"
    ]
},
  "bbox": [],
  "geometry": {"coordinates":[-2.366667,52.75],"type":"Point"}
}