{
  "id": 2036269,
  "type": "Feature",
  "properties": {
    "tgn:hierarchy":[
        "tgn:2036269",
        "tgn:1000001",
        "tgn:2000680",
        "tgn:7012149",
        "tgn:7007254",
        "tgn:7029392"
    ],
    "tgn:id":2036269,
    "tgn:name":"Detroit",
    "tgn:placetype":[
        "aat:300008347"
    ]
},
  "bbox": [],
  "geometry": {"coordinates":[-97.1167,38.9333],"type":"Point"}
}