{
  "id": 2735352,
  "type": "Feature",
  "properties": {
    "tgn:hierarchy":[
        "tgn:2735352",
        "tgn:2000090",
        "tgn:1000001",
        "tgn:7006451",
        "tgn:7012149",
        "tgn:7029392"
    ],
    "tgn:id":2735352,
    "tgn:name":"Twin Buttes",
    "tgn:placetype":[
        "aat:300008798"
    ]
},
  "bbox": [],
  "geometry": {"coordinates":[-109.45,34.6167],"type":"Point"}
}