{
  "id": 2402998,
  "type": "Feature",
  "properties": {
    "tgn:hierarchy":[
        "tgn:2402998",
        "tgn:1000001",
        "tgn:7012149",
        "tgn:7007920",
        "tgn:7029392"
    ],
    "tgn:id":2402998,
    "tgn:name":"Houghton Creek",
    "tgn:placetype":[
        "aat:300008706"
    ]
},
  "bbox": [],
  "geometry": {"coordinates":[-122.6333,45.9667],"type":"Point"}
}