<<<<<<< HEAD
{
  "id": 2402998,
  "type": "Feature",
  "properties": {
    "tgn:hierarchy":[
        "tgn:2402998",
        "tgn:1000001",
        "tgn:7012149",
        "tgn:7007920",
        "tgn:7029392"
    ],
    "tgn:id":2402998,
    "tgn:name":"Houghton Creek",
    "tgn:placetype":[
        "aat:300008706"
    ]
},
  "bbox": [],
  "geometry": {"coordinates":[-122.6333,45.9667],"type":"Point"}
}
=======
{"geometry":{"type":"Point","coordinates":[-122.633300,45.966700]},"type":"Feature","properties":{"hierarchy":["tgn:2402998","tgn:1000001","tgn:7012149","tgn:7007920","tgn:7029392"],"placetype":["aat:300008706"],"id":2402998,"name:xx":"Houghton Creek"}}
>>>>>>> 03f74aca74312dbeaf24d7e61306dd6a786dc3d0
