{
  "id": 2029898,
  "type": "Feature",
  "properties": {
    "tgn:hierarchy":[
        "tgn:2029898",
        "tgn:1000001",
        "tgn:7012149",
        "tgn:1002866",
        "tgn:7007251",
        "tgn:7029392"
    ],
    "tgn:id":2029898,
    "tgn:name":"Rochester",
    "tgn:placetype":[
        "aat:300008347"
    ]
},
  "bbox": [],
  "geometry": {"coordinates":[-89.5167,39.7333],"type":"Point"}
}