{
  "id": 2744026,
  "type": "Feature",
  "properties": {
    "tgn:hierarchy":[
        "tgn:2744026",
        "tgn:1000001",
        "tgn:7006451",
        "tgn:7012149",
        "tgn:2000100",
        "tgn:7029392"
    ],
    "tgn:id":2744026,
    "tgn:name":"Ventana Canyon",
    "tgn:placetype":[
        "aat:300008761"
    ]
},
  "bbox": [],
  "geometry": {"coordinates":[-110.8667,32.3667],"type":"Point"}
}