{
  "id": 2663238,
  "type": "Feature",
  "properties": {
    "tgn:hierarchy":[
        "tgn:2663238",
        "tgn:1000001",
        "tgn:1002243",
        "tgn:7012149",
        "tgn:7007520",
        "tgn:7029392"
    ],
    "tgn:id":2663238,
    "tgn:name":"Silver Creek",
    "tgn:placetype":[
        "aat:300008706"
    ]
},
  "bbox": [],
  "geometry": {"coordinates":[-86.15,42.0667],"type":"Point"}
}