{
  "id": 7254950,
  "type": "Feature",
  "properties": {
    "tgn:hierarchy":[
        "tgn:7254950",
        "tgn:7003460",
        "tgn:1000003",
        "tgn:1000063",
        "tgn:4012014",
        "tgn:7029392"
    ],
    "tgn:id":7254950,
    "tgn:name":"Steffeshausen",
    "tgn:placetype":[
        "aat:300008347"
    ]
},
  "bbox": [],
  "geometry": {"coordinates":[6.158333,50.198611],"type":"Point"}
}