{
  "id": 2663715,
  "type": "Feature",
  "properties": {
    "tgn:hierarchy":[
        "tgn:2663715",
        "tgn:7013388",
        "tgn:1000001",
        "tgn:7012149",
        "tgn:7007517",
        "tgn:7029392"
    ],
    "tgn:id":2663715,
    "tgn:name":"Silver Lake",
    "tgn:placetype":[
        "aat:300008680"
    ]
},
  "bbox": [],
  "geometry": {"coordinates":[-73.2333,42.45],"type":"Point"}
}