{
  "id": 7345282,
  "type": "Feature",
  "properties": {
    "tgn:hierarchy":[
        "tgn:7345282",
        "tgn:7002847",
        "tgn:1001647",
        "tgn:1000003",
        "tgn:1000095",
        "tgn:7029392"
    ],
    "tgn:id":7345282,
    "tgn:name":"Algarbe, Arroyo del",
    "tgn:placetype":[
        "aat:300266554",
        "aat:300008699"
    ]
},
  "bbox": [],
  "geometry": {"coordinates":[-4.25,39.783333],"type":"Point"}
}