{
  "id": 1016808,
  "type": "Feature",
  "properties": {
    "tgn:hierarchy":[
        "tgn:1016808",
        "tgn:1000512",
        "tgn:1000001",
        "tgn:7005554",
        "tgn:7029392"
    ],
    "tgn:id":1016808,
    "tgn:name":"Mezapa",
    "tgn:placetype":[
        "aat:300008347"
    ]
},
  "bbox": [],
  "geometry": {"coordinates":[-87.3833,15.55],"type":"Point"}
}