{
  "id": 2038072,
  "type": "Feature",
  "properties": {
    "tgn:hierarchy":[
        "tgn:2038072",
        "tgn:1000001",
        "tgn:7012149",
        "tgn:2000846",
        "tgn:7007255",
        "tgn:7029392"
    ],
    "tgn:id":2038072,
    "tgn:name":"Canton",
    "tgn:placetype":[
        "aat:300008347"
    ]
},
  "bbox": [],
  "geometry": {"coordinates":[-87.95,36.7833],"type":"Point"}
}