{
  "id": 7449981,
  "type": "Feature",
  "properties": {
    "tgn:hierarchy":[
        "tgn:7449981",
        "tgn:7002445",
        "tgn:1000003",
        "tgn:7026382",
        "tgn:7008591",
        "tgn:7029392"
    ],
    "tgn:id":7449981,
    "tgn:name:en":"East Shefford",
    "tgn:placetype":[
        "aat:300008347"
    ]
},
  "bbox": [],
  "geometry": {"coordinates":[-1.433333,51.45],"type":"Point"}
}