<<<<<<< HEAD
{
  "id": 7476169,
  "type": "Feature",
  "properties": {
    "tgn:hierarchy":[
        "tgn:7476169",
        "tgn:7487020",
        "tgn:1000004",
        "tgn:1000141",
        "tgn:7029392"
    ],
    "tgn:id":7476169,
    "tgn:name":"Xiaodong He",
    "tgn:placetype":[
        "aat:300008699"
    ]
},
  "bbox": [],
  "geometry": {"coordinates":[120.991833,24.580809],"type":"Point"}
}
=======
{"geometry":{"type":"Point","coordinates":[120.991833,24.580809]},"type":"Feature","properties":{"hierarchy":["tgn:7476169","tgn:7487020","tgn:1000004","tgn:1000141","tgn:7029392"],"placetype":["aat:300008699"],"id":7476169,"name:xx":"Xiaodong He"}}
>>>>>>> 03f74aca74312dbeaf24d7e61306dd6a786dc3d0
