<<<<<<< HEAD
{
  "id": 2766703,
  "type": "Feature",
  "properties": {
    "tgn:hierarchy":[
        "tgn:2766703",
        "tgn:1000001",
        "tgn:7012149",
        "tgn:2001503",
        "tgn:7007709",
        "tgn:7029392"
    ],
    "tgn:id":2766703,
    "tgn:name":"White Oak Mountain",
    "tgn:placetype":[
        "aat:300008798"
    ]
},
  "bbox": [],
  "geometry": {"coordinates":[-83.05,35.6667],"type":"Point"}
}
=======
{"geometry":{"type":"Point","coordinates":[-83.050000,35.666700]},"type":"Feature","properties":{"hierarchy":["tgn:2766703","tgn:1000001","tgn:7012149","tgn:2001503","tgn:7007709","tgn:7029392"],"placetype":["aat:300008798"],"id":2766703,"name:xx":"White Oak Mountain"}}
>>>>>>> 03f74aca74312dbeaf24d7e61306dd6a786dc3d0
