{
  "id": 2751030,
  "type": "Feature",
  "properties": {
    "tgn:hierarchy":[
        "tgn:2751030",
        "tgn:7014651",
        "tgn:1000001",
        "tgn:7012149",
        "tgn:7007516",
        "tgn:7029392"
    ],
    "tgn:id":2751030,
    "tgn:name":"Wardour Bluffs",
    "tgn:placetype":[
        "aat:300008347"
    ]
},
  "bbox": [],
  "geometry": {"coordinates":[-76.4833,38.9833],"type":"Point"}
}