{
  "id": 7002494,
  "type": "Feature",
  "properties": {
    "tgn:hierarchy":[
        "tgn:7002494",
        "tgn:1001117",
        "tgn:1000004",
        "tgn:7018451",
        "tgn:1000144",
        "tgn:7029392"
    ],
    "tgn:id":7002494,
    "tgn:name":"Didyma",
    "tgn:placetype":[
        "aat:300000810",
        "aat:300387272",
        "aat:300000833"
    ]
},
  "bbox": [],
  "geometry": {"coordinates":[27.2333,37.35],"type":"Point"}
}