{
  "id": 7227223,
  "type": "Feature",
  "properties": {
    "tgn:hierarchy":[
        "tgn:7227223",
        "tgn:7002739",
        "tgn:7017076",
        "tgn:1000003",
        "tgn:1000074",
        "tgn:7029392"
    ],
    "tgn:id":7227223,
    "tgn:name":"Skyl\u00f3magkas, \u00c1kra",
    "tgn:placetype":[
        "aat:300008850"
    ]
},
  "bbox": [],
  "geometry": {"coordinates":[23.341603,37.674225],"type":"Point"}
}