{
  "id": 2604126,
  "type": "Feature",
  "properties": {
    "tgn:hierarchy":[
        "tgn:2604126",
        "tgn:1000001",
        "tgn:7012149",
        "tgn:2000833",
        "tgn:7007255",
        "tgn:7029392"
    ],
    "tgn:id":2604126,
    "tgn:name":"Quirks Branch",
    "tgn:placetype":[
        "aat:300008699"
    ]
},
  "bbox": [],
  "geometry": {"coordinates":[-85.45,37.7167],"type":"Point"}
}