{
  "id": 7153047,
  "type": "Feature",
  "properties": {
    "tgn:hierarchy":[
        "tgn:7153047",
        "tgn:1000003",
        "tgn:7003678",
        "tgn:7000084",
        "tgn:7029392"
    ],
    "tgn:id":7153047,
    "tgn:name":"Jungfern-Kopf",
    "tgn:placetype":[
        "aat:300008777"
    ]
},
  "bbox": [],
  "geometry": {"coordinates":[9.233333,51.083333],"type":"Point"}
}