{
  "id": 1012553,
  "type": "Feature",
  "properties": {
    "tgn:hierarchy":[
        "tgn:1012553",
        "tgn:7006218",
        "tgn:7006211",
        "tgn:1000216",
        "tgn:1000006",
        "tgn:7029392"
    ],
    "tgn:id":1012553,
    "tgn:name":"Tataa, Pointe",
    "tgn:placetype":[
        "aat:300386846"
    ]
},
  "bbox": [],
  "geometry": {"coordinates":[-149.6167,-17.5667],"type":"Point"}
}