{
  "id": 2786295,
  "type": "Feature",
  "properties": {
    "tgn:hierarchy":[
        "tgn:2786295",
        "tgn:1000001",
        "tgn:7006451",
        "tgn:2000092",
        "tgn:7012149",
        "tgn:7029392"
    ],
    "tgn:id":2786295,
    "tgn:name":"Youngs Lake",
    "tgn:placetype":[
        "aat:300008680"
    ]
},
  "bbox": [],
  "geometry": {"coordinates":[-111.4667,35.0833],"type":"Point"}
}