{
  "id": 7184940,
  "type": "Feature",
  "properties": {
    "tgn:hierarchy":[
        "tgn:7184940",
        "tgn:1000003",
        "tgn:7003677",
        "tgn:7000084",
        "tgn:7029392"
    ],
    "tgn:id":7184940,
    "tgn:name":"Gorspen",
    "tgn:placetype":[
        "aat:300008347"
    ]
},
  "bbox": [],
  "geometry": {"coordinates":[9.033333,52.383333],"type":"Point"}
}