{
  "id": 2332887,
  "type": "Feature",
  "properties": {
    "tgn:hierarchy":[
        "tgn:2332887",
        "tgn:1000001",
        "tgn:2001419",
        "tgn:7012149",
        "tgn:7007526",
        "tgn:7029392"
    ],
    "tgn:id":2332887,
    "tgn:name":"Floyds Shaft",
    "tgn:placetype":[
        "aat:300000390"
    ]
},
  "bbox": [],
  "geometry": {"coordinates":[-117.8167,40.65],"type":"Point"}
}