<<<<<<< HEAD
{
  "id": 2332887,
  "type": "Feature",
  "properties": {
    "tgn:hierarchy":[
        "tgn:2332887",
        "tgn:1000001",
        "tgn:2001419",
        "tgn:7012149",
        "tgn:7007526",
        "tgn:7029392"
    ],
    "tgn:id":2332887,
    "tgn:name":"Floyds Shaft",
    "tgn:placetype":[
        "aat:300000390"
    ]
},
  "bbox": [],
  "geometry": {"coordinates":[-117.8167,40.65],"type":"Point"}
}
=======
{"geometry":{"type":"Point","coordinates":[-117.816700,40.650000]},"type":"Feature","properties":{"hierarchy":["tgn:2332887","tgn:1000001","tgn:2001419","tgn:7012149","tgn:7007526","tgn:7029392"],"placetype":["aat:300000390"],"id":2332887,"name:xx":"Floyds Shaft"}}
>>>>>>> 03f74aca74312dbeaf24d7e61306dd6a786dc3d0
