<<<<<<< HEAD
{
  "id": 2252184,
  "type": "Feature",
  "properties": {
    "tgn:hierarchy":[
        "tgn:2252184",
        "tgn:1002165",
        "tgn:1000001",
        "tgn:7012149",
        "tgn:7007517",
        "tgn:7029392"
    ],
    "tgn:id":2252184,
    "tgn:name":"Cone Rock",
    "tgn:placetype":[
        "aat:300011692"
    ]
},
  "bbox": [],
  "geometry": {"coordinates":[-70.3167,41.7],"type":"Point"}
}
=======
{"geometry":{"type":"Point","coordinates":[-70.316700,41.700000]},"type":"Feature","properties":{"hierarchy":["tgn:2252184","tgn:1002165","tgn:1000001","tgn:7012149","tgn:7007517","tgn:7029392"],"placetype":["aat:300011692"],"id":2252184,"name:xx":"Cone Rock"}}
>>>>>>> 03f74aca74312dbeaf24d7e61306dd6a786dc3d0
