{
  "id": 2621228,
  "type": "Feature",
  "properties": {
    "tgn:hierarchy":[
        "tgn:2621228",
        "tgn:1000001",
        "tgn:2001417",
        "tgn:7012149",
        "tgn:7007526",
        "tgn:7029392"
    ],
    "tgn:id":2621228,
    "tgn:name":"Roadside Spring",
    "tgn:placetype":[
        "aat:300008697"
    ]
},
  "bbox": [],
  "geometry": {"coordinates":[-117.9667,38.3833],"type":"Point"}
}