<<<<<<< HEAD
{
  "id": 2259087,
  "type": "Feature",
  "properties": {
    "tgn:hierarchy":[
        "tgn:2259087",
        "tgn:1000001",
        "tgn:7012149",
        "tgn:2000210",
        "tgn:7007158",
        "tgn:7029392"
    ],
    "tgn:id":2259087,
    "tgn:name":"Cottonwood Divide",
    "tgn:placetype":[
        "aat:300266640"
    ]
},
  "bbox": [],
  "geometry": {"coordinates":[-107.0667,39.5333],"type":"Point"}
}
=======
{"geometry":{"type":"Point","coordinates":[-107.066700,39.533300]},"type":"Feature","properties":{"hierarchy":["tgn:2259087","tgn:1000001","tgn:7012149","tgn:2000210","tgn:7007158","tgn:7029392"],"placetype":["aat:300266640"],"id":2259087,"name:xx":"Cottonwood Divide"}}
>>>>>>> 03f74aca74312dbeaf24d7e61306dd6a786dc3d0
