{
  "id": 2162162,
  "type": "Feature",
  "properties": {
    "tgn:hierarchy":[
        "tgn:2162162",
        "tgn:1000001",
        "tgn:7006451",
        "tgn:7012149",
        "tgn:2000102",
        "tgn:7029392"
    ],
    "tgn:id":2162162,
    "tgn:name":"Belmont Mine",
    "tgn:placetype":[
        "aat:300000390"
    ]
},
  "bbox": [],
  "geometry": {"coordinates":[-110.6833,31.3667],"type":"Point"}
}