{
  "id": 2575469,
  "type": "Feature",
  "properties": {
    "tgn:hierarchy":[
        "tgn:2575469",
        "tgn:1000001",
        "tgn:2000261",
        "tgn:7012149",
        "tgn:7007240",
        "tgn:7029392"
    ],
    "tgn:id":2575469,
    "tgn:name":"Peoria Point",
    "tgn:placetype":[
        "aat:300008850"
    ]
},
  "bbox": [],
  "geometry": {"coordinates":[-81.75,30.1167],"type":"Point"}
}