{
  "id": 1056876,
  "type": "Feature",
  "properties": {
    "tgn:hierarchy":[
        "tgn:1056876",
        "tgn:7011476",
        "tgn:1000004",
        "tgn:7006655",
        "tgn:7029392"
    ],
    "tgn:id":1056876,
    "tgn:name":"Mazarsu",
    "tgn:placetype":[
        "aat:300008347"
    ]
},
  "bbox": [],
  "geometry": {"coordinates":[72.5667,41.9167],"type":"Point"}
}