{
  "id": 2540171,
  "type": "Feature",
  "properties": {
    "tgn:hierarchy":[
        "tgn:2540171",
        "tgn:1000001",
        "tgn:7012149",
        "tgn:7007827",
        "tgn:7029392"
    ],
    "tgn:id":2540171,
    "tgn:name":"Newfoundland Mountains",
    "tgn:placetype":[
        "aat:300386831"
    ]
},
  "bbox": [],
  "geometry": {"coordinates":[-113.3667,41.1333],"type":"Point"}
}