{
  "id": 2470189,
  "type": "Feature",
  "properties": {
    "tgn:hierarchy":[
        "tgn:2470189",
        "tgn:1000001",
        "tgn:7012149",
        "tgn:7007157",
        "tgn:1002684",
        "tgn:7029392"
    ],
    "tgn:id":2470189,
    "tgn:name":"Lopez Rock",
    "tgn:placetype":[
        "aat:300008791"
    ]
},
  "bbox": [],
  "geometry": {"coordinates":[-121.5667,36.0167],"type":"Point"}
}