{
  "id": 7355734,
  "type": "Feature",
  "properties": {
    "tgn:hierarchy":[
        "tgn:7355734",
        "tgn:1000001",
        "tgn:7005594",
        "tgn:7005560",
        "tgn:7029392"
    ],
    "tgn:id":7355734,
    "tgn:name":"Car\u00e1cuero",
    "tgn:placetype":[
        "aat:300008347"
    ]
},
  "bbox": [],
  "geometry": {"coordinates":[-100.583333,23.833333],"type":"Point"}
}