{
  "id": 7563359,
  "type": "Feature",
  "properties": {
    "tgn:hierarchy":[
        "tgn:7563359",
        "tgn:1000004",
        "tgn:7000198",
        "tgn:1001894",
        "tgn:7029392"
    ],
    "tgn:id":7563359,
    "tgn:name:en":"\u0100m\u0101koi Reserved Forest",
    "tgn:placetype":[
        "aat:300008865"
    ]
},
  "bbox": [],
  "geometry": {"coordinates":[79.142667,24.080139],"type":"Point"}
}