{
  "id": 2062385,
  "type": "Feature",
  "properties": {
    "tgn:hierarchy":[
        "tgn:2062385",
        "tgn:1000001",
        "tgn:2001341",
        "tgn:7012149",
        "tgn:7007525",
        "tgn:7029392"
    ],
    "tgn:id":2062385,
    "tgn:name":"Maskell",
    "tgn:placetype":[
        "aat:300008347"
    ]
},
  "bbox": [],
  "geometry": {"coordinates":[-96.9667,42.6833],"type":"Point"}
}