<<<<<<< HEAD
{
  "id": 2409097,
  "type": "Feature",
  "properties": {
    "tgn:hierarchy":[
        "tgn:2409097",
        "tgn:1000001",
        "tgn:1002260",
        "tgn:7012149",
        "tgn:7007920",
        "tgn:7029392"
    ],
    "tgn:id":2409097,
    "tgn:name":"Ice Cliff Glacier",
    "tgn:placetype":[
        "aat:300008835"
    ]
},
  "bbox": [],
  "geometry": {"coordinates":[-120.8833,47.4667],"type":"Point"}
}
=======
{"geometry":{"type":"Point","coordinates":[-120.883300,47.466700]},"type":"Feature","properties":{"hierarchy":["tgn:2409097","tgn:1000001","tgn:1002260","tgn:7012149","tgn:7007920","tgn:7029392"],"placetype":["aat:300008835"],"id":2409097,"name:xx":"Ice Cliff Glacier"}}
>>>>>>> 03f74aca74312dbeaf24d7e61306dd6a786dc3d0
