{
  "id": 7464465,
  "type": "Feature",
  "properties": {
    "tgn:hierarchy":[
        "tgn:7464465",
        "tgn:7002444",
        "tgn:1000003",
        "tgn:7008094",
        "tgn:7008591",
        "tgn:7029392"
    ],
    "tgn:id":7464465,
    "tgn:name:en":"Berneray, Sound of",
    "tgn:placetype":[
        "aat:300266558"
    ]
},
  "bbox": [],
  "geometry": {"coordinates":[-7.216667,57.716667],"type":"Point"}
}