{
  "id": 1127156,
  "type": "Feature",
  "properties": {
    "tgn:hierarchy":[
        "tgn:1127156",
        "tgn:1000001",
        "tgn:1002359",
        "tgn:7012149",
        "tgn:7007517",
        "tgn:7029392"
    ],
    "tgn:id":1127156,
    "tgn:name":"Miles",
    "tgn:placetype":[
        "aat:300008707"
    ]
},
  "bbox": [],
  "geometry": {"coordinates":[-70.8667,42.5833],"type":"Point"}
}