<<<<<<< HEAD
{
  "id": 2251285,
  "type": "Feature",
  "properties": {
    "tgn:hierarchy":[
        "tgn:2251285",
        "tgn:1000001",
        "tgn:2001416",
        "tgn:7012149",
        "tgn:7007526",
        "tgn:7029392"
    ],
    "tgn:id":2251285,
    "tgn:name":"Combined Metals Mine",
    "tgn:placetype":[
        "aat:300000390"
    ]
},
  "bbox": [],
  "geometry": {"coordinates":[-114.7,38.0833],"type":"Point"}
}
=======
{"geometry":{"type":"Point","coordinates":[-114.700000,38.083300]},"type":"Feature","properties":{"hierarchy":["tgn:2251285","tgn:1000001","tgn:2001416","tgn:7012149","tgn:7007526","tgn:7029392"],"placetype":["aat:300000390"],"id":2251285,"name:xx":"Combined Metals Mine"}}
>>>>>>> 03f74aca74312dbeaf24d7e61306dd6a786dc3d0
