<<<<<<< HEAD
{
  "id": 7172147,
  "type": "Feature",
  "properties": {
    "tgn:hierarchy":[
        "tgn:7172147",
        "tgn:1000003",
        "tgn:7003688",
        "tgn:7000084",
        "tgn:7029392"
    ],
    "tgn:id":7172147,
    "tgn:name":"Helmsand",
    "tgn:placetype":[
        "aat:300008791"
    ]
},
  "bbox": [],
  "geometry": {"coordinates":[8.966667,54.066667],"type":"Point"}
}
=======
{"geometry":{"type":"Point","coordinates":[8.966667,54.066667]},"type":"Feature","properties":{"hierarchy":["tgn:7172147","tgn:1000003","tgn:7003688","tgn:7000084","tgn:7029392"],"placetype":["aat:300008791"],"id":7172147,"name:xx":"Helmsand"}}
>>>>>>> 03f74aca74312dbeaf24d7e61306dd6a786dc3d0
