{
  "id": 2229534,
  "type": "Feature",
  "properties": {
    "tgn:hierarchy":[
        "tgn:2229534",
        "tgn:1000001",
        "tgn:7012149",
        "tgn:2000930",
        "tgn:7007515",
        "tgn:7029392"
    ],
    "tgn:id":2229534,
    "tgn:name":"Cedar Pond",
    "tgn:placetype":[
        "aat:300008680"
    ]
},
  "bbox": [],
  "geometry": {"coordinates":[-70.3333,45.3667],"type":"Point"}
}