{
  "id": 7058143,
  "type": "Feature",
  "properties": {
    "tgn:hierarchy":[
        "tgn:7058143",
        "tgn:7003170",
        "tgn:1000003",
        "tgn:7003125",
        "tgn:1000080",
        "tgn:7029392"
    ],
    "tgn:id":7058143,
    "tgn:name":"Branca",
    "tgn:placetype":[
        "aat:300008347"
    ]
},
  "bbox": [],
  "geometry": {"coordinates":[12.683333,43.266667],"type":"Point"}
}