{
  "id": 7503146,
  "type": "Feature",
  "properties": {
    "tgn:hierarchy":[
        "tgn:7503146",
        "tgn:1000004",
        "tgn:7004300",
        "tgn:1000141",
        "tgn:7029392"
    ],
    "tgn:id":7503146,
    "tgn:name":"Zaolong",
    "tgn:placetype":[
        "aat:300008749"
    ]
},
  "bbox": [],
  "geometry": {"coordinates":[119.6125,23.252222],"type":"Point"}
}