{
  "id": 7134581,
  "type": "Feature",
  "properties": {
    "tgn:hierarchy":[
        "tgn:7134581",
        "tgn:7003669",
        "tgn:1000003",
        "tgn:7000084",
        "tgn:7029392"
    ],
    "tgn:id":7134581,
    "tgn:name":"M\u00fchlbach",
    "tgn:placetype":[
        "aat:300008347"
    ]
},
  "bbox": [],
  "geometry": {"coordinates":[11.616667,49.016667],"type":"Point"}
}