<<<<<<< HEAD
{
  "id": 7020082,
  "type": "Feature",
  "properties": {
    "tgn:hierarchy":[
        "tgn:7020082",
        "tgn:1000001",
        "tgn:7012149",
        "tgn:1002554",
        "tgn:7007920",
        "tgn:7029392"
    ],
    "tgn:id":7020082,
    "tgn:name":"McIlroy Canyon",
    "tgn:placetype":[
        "aat:300008761"
    ]
},
  "bbox": [],
  "geometry": {"coordinates":[-121.5333,45.85],"type":"Point"}
}
=======
{"geometry":{"type":"Point","coordinates":[-121.533300,45.850000]},"type":"Feature","properties":{"hierarchy":["tgn:7020082","tgn:1000001","tgn:7012149","tgn:1002554","tgn:7007920","tgn:7029392"],"placetype":["aat:300008761"],"id":7020082,"name:xx":"McIlroy Canyon"}}
>>>>>>> 03f74aca74312dbeaf24d7e61306dd6a786dc3d0
