{
  "id": 7020082,
  "type": "Feature",
  "properties": {
    "tgn:hierarchy":[
        "tgn:7020082",
        "tgn:1000001",
        "tgn:7012149",
        "tgn:1002554",
        "tgn:7007920",
        "tgn:7029392"
    ],
    "tgn:id":7020082,
    "tgn:name":"McIlroy Canyon",
    "tgn:placetype":[
        "aat:300008761"
    ]
},
  "bbox": [],
  "geometry": {"coordinates":[-121.5333,45.85],"type":"Point"}
}