{
  "id": 2545639,
  "type": "Feature",
  "properties": {
    "tgn:hierarchy":[
        "tgn:2545639",
        "tgn:1000001",
        "tgn:7012149",
        "tgn:7019676",
        "tgn:7007566",
        "tgn:7029392"
    ],
    "tgn:id":2545639,
    "tgn:name":"North Fork Catron Wash",
    "tgn:placetype":[
        "aat:300008699"
    ]
},
  "bbox": [],
  "geometry": {"coordinates":[-108.95,35.7833],"type":"Point"}
}