{
  "id": 7556286,
  "type": "Feature",
  "properties": {
    "tgn:hierarchy":[
        "tgn:7556286",
        "tgn:1000004",
        "tgn:7000198",
        "tgn:7016722",
        "tgn:7029392"
    ],
    "tgn:id":7556286,
    "tgn:name:en":"Sachendi",
    "tgn:placetype":[
        "aat:300008347"
    ]
},
  "bbox": [],
  "geometry": {"coordinates":[80.169131,26.425379],"type":"Point"}
}