{
  "id": 7332568,
  "type": "Feature",
  "properties": {
    "tgn:hierarchy":[
        "tgn:7332568",
        "tgn:7002822",
        "tgn:1001647",
        "tgn:1000003",
        "tgn:1000095",
        "tgn:7029392"
    ],
    "tgn:id":7332568,
    "tgn:name":"Iri\u00e9pal",
    "tgn:placetype":[
        "aat:300008347"
    ]
},
  "bbox": [],
  "geometry": {"coordinates":[-3.116667,40.633333],"type":"Point"}
}