{
  "id": 7456090,
  "type": "Feature",
  "properties": {
    "tgn:hierarchy":[
        "tgn:7456090",
        "tgn:7002448",
        "tgn:1000003",
        "tgn:7019199",
        "tgn:7008591",
        "tgn:7029392"
    ],
    "tgn:id":7456090,
    "tgn:name:en":"Drumbanagher House",
    "tgn:placetype":[
        "aat:300387502"
    ]
},
  "bbox": [],
  "geometry": {"coordinates":[-6.383333,54.266667],"type":"Point"}
}