{
  "id": 7462059,
  "type": "Feature",
  "properties": {
    "tgn:hierarchy":[
        "tgn:7462059",
        "tgn:7002444",
        "tgn:1000003",
        "tgn:7008094",
        "tgn:7008591",
        "tgn:7029392"
    ],
    "tgn:id":7462059,
    "tgn:name:en":"Hermetray Group",
    "tgn:placetype":[
        "aat:300008791"
    ]
},
  "bbox": [],
  "geometry": {"coordinates":[-7.033333,57.666667],"type":"Point"}
}