{
  "id": 2441241,
  "type": "Feature",
  "properties": {
    "tgn:hierarchy":[
        "tgn:2441241",
        "tgn:1000001",
        "tgn:7012149",
        "tgn:1002785",
        "tgn:7007920",
        "tgn:7029392"
    ],
    "tgn:id":2441241,
    "tgn:name":"Knowles Hill",
    "tgn:placetype":[
        "aat:300008798"
    ]
},
  "bbox": [],
  "geometry": {"coordinates":[-122.5667,47.05],"type":"Point"}
}