{
  "id": 2667720,
  "type": "Feature",
  "properties": {
    "tgn:hierarchy":[
        "tgn:2667720",
        "tgn:1000001",
        "tgn:7006451",
        "tgn:7012149",
        "tgn:2000103",
        "tgn:7029392"
    ],
    "tgn:id":2667720,
    "tgn:name":"Skull Valley Wash",
    "tgn:placetype":[
        "aat:300008699"
    ]
},
  "bbox": [],
  "geometry": {"coordinates":[-112.6833,34.4833],"type":"Point"}
}