<<<<<<< HEAD
{
  "id": 2761692,
  "type": "Feature",
  "properties": {
    "tgn:hierarchy":[
        "tgn:2761692",
        "tgn:1000001",
        "tgn:1002276",
        "tgn:7012149",
        "tgn:7007708",
        "tgn:7029392"
    ],
    "tgn:id":2761692,
    "tgn:name":"West Point",
    "tgn:placetype":[
        "aat:300008850"
    ]
},
  "bbox": [],
  "geometry": {"coordinates":[-123.9667,45.9667],"type":"Point"}
}
=======
{"geometry":{"type":"Point","coordinates":[-123.966700,45.966700]},"type":"Feature","properties":{"hierarchy":["tgn:2761692","tgn:1000001","tgn:1002276","tgn:7012149","tgn:7007708","tgn:7029392"],"placetype":["aat:300008850"],"id":2761692,"name:xx":"West Point"}}
>>>>>>> 03f74aca74312dbeaf24d7e61306dd6a786dc3d0
