{
  "id": 1115448,
  "type": "Feature",
  "properties": {
    "tgn:hierarchy":[
        "tgn:1115448",
        "tgn:7002444",
        "tgn:1000003",
        "tgn:7008082",
        "tgn:7008591",
        "tgn:7029392"
    ],
    "tgn:id":1115448,
    "tgn:name:en":"Arkaig, Loch",
    "tgn:placetype":[
        "aat:300008680"
    ]
},
  "bbox": [],
  "geometry": {"coordinates":[-5.133333,56.966667],"type":"Point"}
}