{
  "id": 7218057,
  "type": "Feature",
  "properties": {
    "tgn:hierarchy":[
        "tgn:7218057",
        "tgn:7002690",
        "tgn:7012056",
        "tgn:1000003",
        "tgn:1000074",
        "tgn:7029392"
    ],
    "tgn:id":7218057,
    "tgn:name":"Xir\u00f3n Khor\u00edon",
    "tgn:placetype":[
        "aat:300008347"
    ]
},
  "bbox": [],
  "geometry": {"coordinates":[24.516667,35.35],"type":"Point"}
}