{
  "id": 7115989,
  "type": "Feature",
  "properties": {
    "tgn:hierarchy":[
        "tgn:7115989",
        "tgn:7003669",
        "tgn:1000003",
        "tgn:7000084",
        "tgn:7029392"
    ],
    "tgn:id":7115989,
    "tgn:name":"Ohnatsberg",
    "tgn:placetype":[
        "aat:300000206"
    ]
},
  "bbox": [],
  "geometry": {"coordinates":[12.683333,48.35],"type":"Point"}
}