<<<<<<< HEAD
{
  "id": 7115989,
  "type": "Feature",
  "properties": {
    "tgn:hierarchy":[
        "tgn:7115989",
        "tgn:7003669",
        "tgn:1000003",
        "tgn:7000084",
        "tgn:7029392"
    ],
    "tgn:id":7115989,
    "tgn:name":"Ohnatsberg",
    "tgn:placetype":[
        "aat:300000206"
    ]
},
  "bbox": [],
  "geometry": {"coordinates":[12.683333,48.35],"type":"Point"}
}
=======
{"geometry":{"type":"Point","coordinates":[12.683333,48.350000]},"type":"Feature","properties":{"hierarchy":["tgn:7115989","tgn:7003669","tgn:1000003","tgn:7000084","tgn:7029392"],"placetype":["aat:300000206"],"id":7115989,"name:xx":"Ohnatsberg"}}
>>>>>>> 03f74aca74312dbeaf24d7e61306dd6a786dc3d0
