{
  "id": 2346367,
  "type": "Feature",
  "properties": {
    "tgn:hierarchy":[
        "tgn:2346367",
        "tgn:2001731",
        "tgn:1000001",
        "tgn:7012149",
        "tgn:7007712",
        "tgn:7029392"
    ],
    "tgn:id":2346367,
    "tgn:name":"Gator Field",
    "tgn:placetype":[
        "aat:300008347"
    ]
},
  "bbox": [],
  "geometry": {"coordinates":[-80.6833,32.2333],"type":"Point"}
}