{
  "id": 2249490,
  "type": "Feature",
  "properties": {
    "tgn:hierarchy":[
        "tgn:2249490",
        "tgn:1000001",
        "tgn:7012149",
        "tgn:7007157",
        "tgn:1002684",
        "tgn:7029392"
    ],
    "tgn:id":2249490,
    "tgn:name":"Coleman Reservoir",
    "tgn:placetype":[
        "aat:300006191"
    ]
},
  "bbox": [],
  "geometry": {"coordinates":[-121.2667,36.0833],"type":"Point"}
}