{
  "id": 2435075,
  "type": "Feature",
  "properties": {
    "tgn:hierarchy":[
        "tgn:2435075",
        "tgn:1000001",
        "tgn:7012149",
        "tgn:7007157",
        "tgn:2000189",
        "tgn:7029392"
    ],
    "tgn:id":2435075,
    "tgn:name":"Kentuck Gulch",
    "tgn:placetype":[
        "aat:300008761"
    ]
},
  "bbox": [],
  "geometry": {"coordinates":[-122.8667,41.7167],"type":"Point"}
}