{
  "id": 7300294,
  "type": "Feature",
  "properties": {
    "tgn:hierarchy":[
        "tgn:7300294",
        "tgn:7002758",
        "tgn:7002823",
        "tgn:1000003",
        "tgn:1000095",
        "tgn:7029392"
    ],
    "tgn:id":7300294,
    "tgn:name":"Valdejud\u00edos, Arroyo de",
    "tgn:placetype":[
        "aat:300008699"
    ]
},
  "bbox": [],
  "geometry": {"coordinates":[-7.333333,37.266667],"type":"Point"}
}