{
  "id": 7354403,
  "type": "Feature",
  "properties": {
    "tgn:hierarchy":[
        "tgn:7354403",
        "tgn:7005586",
        "tgn:1000001",
        "tgn:7005560",
        "tgn:7029392"
    ],
    "tgn:id":7354403,
    "tgn:name":"Casas Viejas",
    "tgn:placetype":[
        "aat:300008347"
    ]
},
  "bbox": [],
  "geometry": {"coordinates":[-102.216667,21.333333],"type":"Point"}
}