<<<<<<< HEAD
{
  "id": 2334326,
  "type": "Feature",
  "properties": {
    "tgn:hierarchy":[
        "tgn:2334326",
        "tgn:1000001",
        "tgn:7016172",
        "tgn:7012149",
        "tgn:2000133",
        "tgn:7029392"
    ],
    "tgn:id":2334326,
    "tgn:name":"Forest Hills",
    "tgn:placetype":[
        "aat:300008347"
    ]
},
  "bbox": [],
  "geometry": {"coordinates":[-93.6,33.65],"type":"Point"}
}
=======
{"geometry":{"type":"Point","coordinates":[-93.600000,33.650000]},"type":"Feature","properties":{"hierarchy":["tgn:2334326","tgn:1000001","tgn:7016172","tgn:7012149","tgn:2000133","tgn:7029392"],"placetype":["aat:300008347"],"id":2334326,"name:xx":"Forest Hills"}}
>>>>>>> 03f74aca74312dbeaf24d7e61306dd6a786dc3d0
