{
  "id": 7191689,
  "type": "Feature",
  "properties": {
    "tgn:hierarchy":[
        "tgn:7191689",
        "tgn:7003669",
        "tgn:1000003",
        "tgn:7000084",
        "tgn:7029392"
    ],
    "tgn:id":7191689,
    "tgn:name":"Schloss Fantasie",
    "tgn:placetype":[
        "aat:300006891"
    ]
},
  "bbox": [],
  "geometry": {"coordinates":[11.516667,49.933333],"type":"Point"}
}