{
  "id": 7165432,
  "type": "Feature",
  "properties": {
    "tgn:hierarchy":[
        "tgn:7165432",
        "tgn:1000003",
        "tgn:7003676",
        "tgn:7000084",
        "tgn:7029392"
    ],
    "tgn:id":7165432,
    "tgn:name":"Idt-Berg",
    "tgn:placetype":[
        "aat:300008777"
    ]
},
  "bbox": [],
  "geometry": {"coordinates":[9.75,51.933333],"type":"Point"}
}