{
  "id": 7577720,
  "type": "Feature",
  "properties": {
    "tgn:hierarchy":[
        "tgn:7577720",
        "tgn:1000004",
        "tgn:7000198",
        "tgn:1001895",
        "tgn:7029392"
    ],
    "tgn:id":7577720,
    "tgn:name:en":"Khol\u0101pur",
    "tgn:placetype":[
        "aat:300008347"
    ]
},
  "bbox": [],
  "geometry": {"coordinates":[77.514493,20.948953],"type":"Point"}
}