{
  "id": 7002302,
  "type": "Feature",
  "properties": {
    "tgn:hierarchy":[
        "tgn:7002302",
        "tgn:1002066",
        "tgn:1000004",
        "tgn:1000140",
        "tgn:7029392"
    ],
    "tgn:id":7002302,
    "tgn:name":"Qanawat",
    "tgn:placetype":[
        "aat:300008347",
        "aat:300000810",
        "aat:300008375"
    ]
},
  "bbox": [],
  "geometry": {"coordinates":[36.6167,32.75],"type":"Point"}
}