{
  "id": 2654989,
  "type": "Feature",
  "properties": {
    "tgn:hierarchy":[
        "tgn:2654989",
        "tgn:1000001",
        "tgn:7012149",
        "tgn:2001454",
        "tgn:7007566",
        "tgn:7029392"
    ],
    "tgn:id":2654989,
    "tgn:name":"Shamrock Mine",
    "tgn:placetype":[
        "aat:300000390"
    ]
},
  "bbox": [],
  "geometry": {"coordinates":[-106.1833,35.25],"type":"Point"}
}