{
  "id": 2558036,
  "type": "Feature",
  "properties": {
    "tgn:hierarchy":[
        "tgn:2558036",
        "tgn:1000001",
        "tgn:2000772",
        "tgn:7012149",
        "tgn:7007255",
        "tgn:7029392"
    ],
    "tgn:id":2558036,
    "tgn:name":"Old Trace Branch",
    "tgn:placetype":[
        "aat:300008699"
    ]
},
  "bbox": [],
  "geometry": {"coordinates":[-83.15,37.5333],"type":"Point"}
}