{
  "id": 2498808,
  "type": "Feature",
  "properties": {
    "tgn:hierarchy":[
        "tgn:2498808",
        "tgn:1000001",
        "tgn:7012149",
        "tgn:2000182",
        "tgn:7007157",
        "tgn:7029392"
    ],
    "tgn:id":2498808,
    "tgn:name":"McCall Drain Five",
    "tgn:placetype":[
        "aat:300006075"
    ]
},
  "bbox": [],
  "geometry": {"coordinates":[-115.5167,32.8333],"type":"Point"}
}