<<<<<<< HEAD
{
  "id": 7369462,
  "type": "Feature",
  "properties": {
    "tgn:hierarchy":[
        "tgn:7369462",
        "tgn:7005580",
        "tgn:1000001",
        "tgn:7005560",
        "tgn:7029392"
    ],
    "tgn:id":7369462,
    "tgn:name":"Gu\u00e1dalupe Victoria",
    "tgn:placetype":[
        "aat:300008347"
    ]
},
  "bbox": [],
  "geometry": {"coordinates":[-92.25,14.8],"type":"Point"}
}
=======
{"geometry":{"type":"Point","coordinates":[-92.250000,14.800000]},"type":"Feature","properties":{"hierarchy":["tgn:7369462","tgn:7005580","tgn:1000001","tgn:7005560","tgn:7029392"],"placetype":["aat:300008347"],"id":7369462,"name:xx":"Gu\u00e1dalupe Victoria"}}
>>>>>>> 03f74aca74312dbeaf24d7e61306dd6a786dc3d0
