{
  "id": 2641401,
  "type": "Feature",
  "properties": {
    "tgn:hierarchy":[
        "tgn:2641401",
        "tgn:1000001",
        "tgn:7012149",
        "tgn:2001697",
        "tgn:7007707",
        "tgn:7029392"
    ],
    "tgn:id":2641401,
    "tgn:name":"Sand Creek",
    "tgn:placetype":[
        "aat:300008706"
    ]
},
  "bbox": [],
  "geometry": {"coordinates":[-99.1667,35.3667],"type":"Point"}
}