{
  "id": 7358059,
  "type": "Feature",
  "properties": {
    "tgn:hierarchy":[
        "tgn:7358059",
        "tgn:1000001",
        "tgn:1001960",
        "tgn:7005560",
        "tgn:7029392"
    ],
    "tgn:id":7358059,
    "tgn:name":"Ejido Morelos",
    "tgn:placetype":[
        "aat:300008347"
    ]
},
  "bbox": [],
  "geometry": {"coordinates":[-109.983333,27.266667],"type":"Point"}
}